package com.mobile.ui.paymenthub.activity;

import android.content.Context;
import android.content.Intent;
import android.os.Bundle;
import android.support.v4.app.Fragment;
import android.support.v4.app.FragmentManager;
import android.support.v4.app.FragmentTransaction;
import com.mobile.ui.R.id;
import com.mobile.ui.R.layout;
import com.mobile.ui.common.activity.AppTimeoutActivity;
import com.mobile.ui.common.activity.BaseActivity.rrrggg;
import com.mobile.ui.paymenthub.fragment.PaymentHubReactivateIsaDeclarationFragment;
import com.mobile.ui.paymenthub.fragment.PaymentHubReactivateIsaDeclarationFragment.yhyyhh;
import com.mobile.ui.reactivateisa.fragment.ReactivateIsaFragment.isiisi;
import java.util.Map;
import kkkkkk.ccrrcc;
import kkkkkk.gguuuu;
import kkkkkk.ssisii;

public class PaymentHubReactivateIsaActivity
  extends AppTimeoutActivity
  implements ReactivateIsaFragment.isiisi, PaymentHubReactivateIsaDeclarationFragment.yhyyhh
{
  private static final String EXTRA_ARRANGEMENT_ID = "u\n\007\006u\025w\n\013z\t\003\002\013\004\016\025!\f\b";
  public static int b042704270427Ч0427Ч04270427 = 94;
  public static int b0427ЧЧ04270427Ч04270427 = 2;
  public static int bЧ0427ЧЧЧ042704270427 = 0;
  public static int bЧЧЧ04270427Ч04270427 = 1;
  
  static
  {
    String str = EXTRA_ARRANGEMENT_ID;
    if ((b042704270427Ч0427Ч04270427 + bЧЧЧ04270427Ч04270427) * b042704270427Ч0427Ч04270427 % b0427ЧЧ04270427Ч04270427 != bЧ0427ЧЧЧ042704270427)
    {
      b042704270427Ч0427Ч04270427 = bЧ0427Ч04270427Ч04270427();
      bЧ0427ЧЧЧ042704270427 = 88;
    }
    switch (1)
    {
    case 0: 
    default: 
      for (;;)
      {
        switch (0)
        {
        }
      }
    }
    EXTRA_ARRANGEMENT_ID = gguuuu.bк043Aккк043Aкк043A043A(str, 'î', '¾', '\001');
  }
  
  public PaymentHubReactivateIsaActivity() {}
  
  public static int b04270427Ч04270427Ч04270427()
  {
    return 1;
  }
  
  public static int b04270427ЧЧЧ042704270427()
  {
    return 2;
  }
  
  public static int bЧ04270427ЧЧ042704270427()
  {
    return 0;
  }
  
  public static int bЧ0427Ч04270427Ч04270427()
  {
    return 81;
  }
  
  public static Intent getIntent(Context paramContext, String paramString)
  {
    paramContext = new Intent(paramContext, PaymentHubReactivateIsaActivity.class);
    switch (0)
    {
    case 1: 
    default: 
      for (;;)
      {
        switch (0)
        {
        }
      }
    }
    int i = b042704270427Ч0427Ч04270427;
    switch (i * (bЧЧЧ04270427Ч04270427 + i) % b0427ЧЧ04270427Ч04270427)
    {
    default: 
      b042704270427Ч0427Ч04270427 = 92;
      bЧЧЧ04270427Ч04270427 = bЧ0427Ч04270427Ч04270427();
    }
    String str = gguuuu.bк043Aккк043Aкк043A043A("&:76&E(:;+932;4>EQ<8", '^', '', '\003');
    i = bЧ0427Ч04270427Ч04270427();
    switch (i * (bЧЧЧ04270427Ч04270427 + i) % b0427ЧЧ04270427Ч04270427)
    {
    default: 
      b042704270427Ч0427Ч04270427 = bЧ0427Ч04270427Ч04270427();
      bЧЧЧ04270427Ч04270427 = 32;
    }
    paramContext.putExtra(str, paramString);
    return paramContext;
  }
  
  public Map<String, Bundle> getDeepLinkMap(Context paramContext)
  {
    paramContext = NOT_LINKABLE_MAP;
    int i = b042704270427Ч0427Ч04270427;
    switch (i * (b04270427Ч04270427Ч04270427() + i) % b0427ЧЧ04270427Ч04270427)
    {
    default: 
      switch (1)
      {
      case 0: 
      default: 
        for (;;)
        {
          switch (1)
          {
          }
        }
      }
      b042704270427Ч0427Ч04270427 = 54;
      i = bЧ0427Ч04270427Ч04270427();
      int j = b042704270427Ч0427Ч04270427;
      switch (j * (b04270427Ч04270427Ч04270427() + j) % b0427ЧЧ04270427Ч04270427)
      {
      default: 
        b042704270427Ч0427Ч04270427 = bЧ0427Ч04270427Ч04270427();
        bЧЧЧ04270427Ч04270427 = bЧ0427Ч04270427Ч04270427();
      }
      bЧЧЧ04270427Ч04270427 = i;
    }
    switch (1)
    {
    case 0: 
    default: 
      for (;;)
      {
        switch (0)
        {
        }
      }
    }
    return paramContext;
  }
  
  protected int getLayoutId()
  {
    int i = b042704270427Ч0427Ч04270427;
    switch (i * (bЧЧЧ04270427Ч04270427 + i) % b0427ЧЧ04270427Ч04270427)
    {
    default: 
      b042704270427Ч0427Ч04270427 = bЧ0427Ч04270427Ч04270427();
      bЧЧЧ04270427Ч04270427 = 76;
    }
    return R.layout.activity_reactivate_isa;
  }
  
  protected BaseActivity.rrrggg getMenuType()
  {
    throw new Runtime("d2j fail translate: java.lang.IndexOutOfBoundsException: fromIndex < 0: -1\n\tat java.util.BitSet.nextSetBit(BitSet.java:712)\n\tat com.googlecode.dex2jar.ir.ts.array.FillArrayTransformer.makeSureAllElementAreAssigned(FillArrayTransformer.java:505)\n\tat com.googlecode.dex2jar.ir.ts.array.FillArrayTransformer.transformReportChanged(FillArrayTransformer.java:123)\n\tat com.googlecode.dex2jar.ir.ts.StatedTransformer.transform(StatedTransformer.java:10)\n\tat com.googlecode.d2j.dex.Dex2jar$2.optimize(Dex2jar.java:149)\n\tat com.googlecode.d2j.dex.Dex2Asm.convertCode(Dex2Asm.java:414)\n\tat com.googlecode.d2j.dex.ExDex2Asm.convertCode(ExDex2Asm.java:42)\n\tat com.googlecode.d2j.dex.Dex2jar$2.convertCode(Dex2jar.java:128)\n\tat com.googlecode.d2j.dex.Dex2Asm.convertMethod(Dex2Asm.java:509)\n\tat com.googlecode.d2j.dex.Dex2Asm.convertClass(Dex2Asm.java:406)\n\tat com.googlecode.d2j.dex.Dex2Asm.convertDex(Dex2Asm.java:422)\n\tat com.googlecode.d2j.dex.Dex2jar.doTranslate(Dex2jar.java:172)\n\tat com.googlecode.d2j.dex.Dex2jar.to(Dex2jar.java:272)\n\tat com.googlecode.dex2jar.tools.Dex2jarCmd.doCommandLine(Dex2jarCmd.java:108)\n\tat com.googlecode.dex2jar.tools.BaseCmd.doMain(BaseCmd.java:288)\n\tat com.googlecode.dex2jar.tools.Dex2jarCmd.main(Dex2jarCmd.java:32)\n");
  }
  
  public void onBackPressed()
  {
    int i = b042704270427Ч0427Ч04270427;
    switch (i * (bЧЧЧ04270427Ч04270427 + i) % b0427ЧЧ04270427Ч04270427)
    {
    default: 
      b042704270427Ч0427Ч04270427 = bЧ0427Ч04270427Ч04270427();
      bЧ0427ЧЧЧ042704270427 = bЧ0427Ч04270427Ч04270427();
      if ((b042704270427Ч0427Ч04270427 + bЧЧЧ04270427Ч04270427) * b042704270427Ч0427Ч04270427 % b04270427ЧЧЧ042704270427() != bЧ0427ЧЧЧ042704270427)
      {
        b042704270427Ч0427Ч04270427 = bЧ0427Ч04270427Ч04270427();
        bЧ0427ЧЧЧ042704270427 = bЧ0427Ч04270427Ч04270427();
      }
      break;
    }
    Fragment localFragment = getSupportFragmentManager().findFragmentById(R.id.reactivateIsaContainer);
    if ((localFragment instanceof ssisii)) {}
    for (boolean bool = ((ssisii)localFragment).onBackPressed();; bool = false)
    {
      switch (1)
      {
      case 0: 
      default: 
        for (;;)
        {
          switch (0)
          {
          }
        }
      }
      if (!bool) {
        super.onBackPressed();
      }
      return;
    }
  }
  
  /* Error */
  protected void onCreate(@android.support.annotation.Nullable Bundle paramBundle)
  {
    // Byte code:
    //   0: aload_0
    //   1: invokevirtual 124	com/mobile/ui/paymenthub/activity/PaymentHubReactivateIsaActivity:getApplicationContext	()Landroid/content/Context;
    //   4: invokestatic 130	kkkkkk/nkkkkk:bЗЗ0417З0417З0417041704170417	(Landroid/content/Context;)V
    //   7: getstatic 27	com/mobile/ui/paymenthub/activity/PaymentHubReactivateIsaActivity:b042704270427Ч0427Ч04270427	I
    //   10: istore_2
    //   11: iload_2
    //   12: getstatic 29	com/mobile/ui/paymenthub/activity/PaymentHubReactivateIsaActivity:bЧЧЧ04270427Ч04270427	I
    //   15: iload_2
    //   16: iadd
    //   17: imul
    //   18: getstatic 31	com/mobile/ui/paymenthub/activity/PaymentHubReactivateIsaActivity:b0427ЧЧ04270427Ч04270427	I
    //   21: irem
    //   22: tableswitch	default:+18->40, 0:+29->51
    //   40: bipush 73
    //   42: putstatic 27	com/mobile/ui/paymenthub/activity/PaymentHubReactivateIsaActivity:b042704270427Ч0427Ч04270427	I
    //   45: invokestatic 37	com/mobile/ui/paymenthub/activity/PaymentHubReactivateIsaActivity:bЧ0427Ч04270427Ч04270427	()I
    //   48: putstatic 33	com/mobile/ui/paymenthub/activity/PaymentHubReactivateIsaActivity:bЧ0427ЧЧЧ042704270427	I
    //   51: aload_0
    //   52: invokevirtual 124	com/mobile/ui/paymenthub/activity/PaymentHubReactivateIsaActivity:getApplicationContext	()Landroid/content/Context;
    //   55: invokestatic 135	kkkkkk/nnnkkk:bхх0445ххххххх	(Landroid/content/Context;)V
    //   58: getstatic 27	com/mobile/ui/paymenthub/activity/PaymentHubReactivateIsaActivity:b042704270427Ч0427Ч04270427	I
    //   61: getstatic 29	com/mobile/ui/paymenthub/activity/PaymentHubReactivateIsaActivity:bЧЧЧ04270427Ч04270427	I
    //   64: iadd
    //   65: getstatic 27	com/mobile/ui/paymenthub/activity/PaymentHubReactivateIsaActivity:b042704270427Ч0427Ч04270427	I
    //   68: imul
    //   69: getstatic 31	com/mobile/ui/paymenthub/activity/PaymentHubReactivateIsaActivity:b0427ЧЧ04270427Ч04270427	I
    //   72: irem
    //   73: getstatic 33	com/mobile/ui/paymenthub/activity/PaymentHubReactivateIsaActivity:bЧ0427ЧЧЧ042704270427	I
    //   76: if_icmpeq +15 -> 91
    //   79: invokestatic 37	com/mobile/ui/paymenthub/activity/PaymentHubReactivateIsaActivity:bЧ0427Ч04270427Ч04270427	()I
    //   82: putstatic 27	com/mobile/ui/paymenthub/activity/PaymentHubReactivateIsaActivity:b042704270427Ч0427Ч04270427	I
    //   85: invokestatic 37	com/mobile/ui/paymenthub/activity/PaymentHubReactivateIsaActivity:bЧ0427Ч04270427Ч04270427	()I
    //   88: putstatic 33	com/mobile/ui/paymenthub/activity/PaymentHubReactivateIsaActivity:bЧ0427ЧЧЧ042704270427	I
    //   91: aload_0
    //   92: invokevirtual 124	com/mobile/ui/paymenthub/activity/PaymentHubReactivateIsaActivity:getApplicationContext	()Landroid/content/Context;
    //   95: invokestatic 140	kkkkkk/nknnkk:bх0445ххх04450445ххх	(Landroid/content/Context;)V
    //   98: aload_0
    //   99: aload_1
    //   100: invokespecial 142	com/mobile/ui/common/activity/AppTimeoutActivity:onCreate	(Landroid/os/Bundle;)V
    //   103: ldc -112
    //   105: sipush 197
    //   108: iconst_0
    //   109: invokestatic 148	kkkkkk/gguuuu:bккккк043Aкк043A043A	(Ljava/lang/String;CC)Ljava/lang/String;
    //   112: iconst_1
    //   113: invokestatic 154	com/appdynamics/eumagent/runtime/Instrumentation:leaveBreadcrumb	(Ljava/lang/String;I)V
    //   116: aload_1
    //   117: ifnonnull +7 -> 124
    //   120: aload_0
    //   121: invokevirtual 157	com/mobile/ui/paymenthub/activity/PaymentHubReactivateIsaActivity:showReactivateIsaDeclarationFragment	()V
    //   124: return
    //   125: astore_1
    //   126: aload_1
    //   127: athrow
    //   128: astore_1
    //   129: aload_1
    //   130: athrow
    // Local variable table:
    //   start	length	slot	name	signature
    //   0	131	0	this	PaymentHubReactivateIsaActivity
    //   0	131	1	paramBundle	Bundle
    //   10	8	2	i	int
    // Exception table:
    //   from	to	target	type
    //   51	58	125	java/lang/Exception
    //   120	124	125	java/lang/Exception
    //   0	7	128	java/lang/Exception
    //   91	116	128	java/lang/Exception
  }
  
  public void onReactivateButtonClicked()
  {
    int i = bЧ0427Ч04270427Ч04270427();
    switch (1)
    {
    case 0: 
    default: 
      for (;;)
      {
        switch (0)
        {
        }
      }
    }
    switch (i * (bЧЧЧ04270427Ч04270427 + i) % b0427ЧЧ04270427Ч04270427)
    {
    default: 
      b042704270427Ч0427Ч04270427 = 8;
      bЧ0427ЧЧЧ042704270427 = 55;
      i = b042704270427Ч0427Ч04270427;
      switch (i * (bЧЧЧ04270427Ч04270427 + i) % b0427ЧЧ04270427Ч04270427)
      {
      default: 
        b042704270427Ч0427Ч04270427 = bЧ0427Ч04270427Ч04270427();
        bЧ0427ЧЧЧ042704270427 = 28;
      }
      break;
    }
    try
    {
      showReactivateIsaFragment();
      return;
    }
    catch (Exception localException)
    {
      throw localException;
    }
  }
  
  public void onReactivateIsaSuccess(String paramString1, String paramString2, String paramString3, String paramString4, String paramString5, ccrrcc paramCcrrcc)
  {
    if ((bЧ0427Ч04270427Ч04270427() + bЧЧЧ04270427Ч04270427) * bЧ0427Ч04270427Ч04270427() % b04270427ЧЧЧ042704270427() != bЧ0427ЧЧЧ042704270427)
    {
      if ((b042704270427Ч0427Ч04270427 + bЧЧЧ04270427Ч04270427) * b042704270427Ч0427Ч04270427 % b0427ЧЧ04270427Ч04270427 != bЧ0427ЧЧЧ042704270427)
      {
        b042704270427Ч0427Ч04270427 = bЧ0427Ч04270427Ч04270427();
        bЧ0427ЧЧЧ042704270427 = bЧ0427Ч04270427Ч04270427();
      }
      b042704270427Ч0427Ч04270427 = bЧ0427Ч04270427Ч04270427();
      bЧ0427ЧЧЧ042704270427 = 15;
    }
    setResult(-1);
    switch (0)
    {
    case 1: 
    default: 
      for (;;)
      {
        switch (1)
        {
        }
      }
    }
    finish();
  }
  
  protected boolean shouldRestartAppIfSecureCoreNotInitialized()
  {
    if ((b042704270427Ч0427Ч04270427 + bЧЧЧ04270427Ч04270427) * b042704270427Ч0427Ч04270427 % b0427ЧЧ04270427Ч04270427 != bЧ0427ЧЧЧ042704270427)
    {
      b042704270427Ч0427Ч04270427 = bЧ0427Ч04270427Ч04270427();
      bЧ0427ЧЧЧ042704270427 = bЧ0427Ч04270427Ч04270427();
    }
    if ((b042704270427Ч0427Ч04270427 + bЧЧЧ04270427Ч04270427) * b042704270427Ч0427Ч04270427 % b0427ЧЧ04270427Ч04270427 != bЧ0427ЧЧЧ042704270427)
    {
      b042704270427Ч0427Ч04270427 = 92;
      bЧ0427ЧЧЧ042704270427 = 75;
    }
    return false;
  }
  
  protected void showReactivateIsaDeclarationFragment()
  {
    String str = getIntent().getStringExtra(gguuuu.bккккк043Aкк043A043A("\013\037\034\033\013*\r\037 \020\036\030\027 \031#*6!\035", '\027', '\001'));
    try
    {
      throw new NullPointerException();
    }
    catch (Exception localException)
    {
      b042704270427Ч0427Ч04270427 = bЧ0427Ч04270427Ч04270427();
      getSupportFragmentManager().beginTransaction().replace(R.id.reactivateIsaContainer, PaymentHubReactivateIsaDeclarationFragment.newInstance(str)).commit();
      switch (0)
      {
      case 1: 
      default: 
        for (;;)
        {
          switch (1)
          {
          }
        }
      }
    }
  }
  
  /* Error */
  protected void showReactivateIsaFragment()
  {
    // Byte code:
    //   0: aload_0
    //   1: invokevirtual 175	com/mobile/ui/paymenthub/activity/PaymentHubReactivateIsaActivity:getIntent	()Landroid/content/Intent;
    //   4: ldc -51
    //   6: bipush 127
    //   8: bipush 59
    //   10: iconst_0
    //   11: invokestatic 43	kkkkkk/gguuuu:bк043Aккк043Aкк043A043A	(Ljava/lang/String;CCC)Ljava/lang/String;
    //   14: invokevirtual 181	android/content/Intent:getStringExtra	(Ljava/lang/String;)Ljava/lang/String;
    //   17: astore 4
    //   19: aload_0
    //   20: invokevirtual 97	com/mobile/ui/paymenthub/activity/PaymentHubReactivateIsaActivity:getSupportFragmentManager	()Landroid/support/v4/app/FragmentManager;
    //   23: invokevirtual 188	android/support/v4/app/FragmentManager:beginTransaction	()Landroid/support/v4/app/FragmentTransaction;
    //   26: astore_3
    //   27: getstatic 102	com/mobile/ui/R$id:reactivateIsaContainer	I
    //   30: istore_1
    //   31: aload 4
    //   33: invokestatic 210	com/mobile/ui/reactivateisa/fragment/ReactivateIsaFragment:newInstance	(Ljava/lang/String;)Lcom/mobile/ui/reactivateisa/fragment/ReactivateIsaFragment;
    //   36: astore 4
    //   38: getstatic 27	com/mobile/ui/paymenthub/activity/PaymentHubReactivateIsaActivity:b042704270427Ч0427Ч04270427	I
    //   41: getstatic 29	com/mobile/ui/paymenthub/activity/PaymentHubReactivateIsaActivity:bЧЧЧ04270427Ч04270427	I
    //   44: iadd
    //   45: getstatic 27	com/mobile/ui/paymenthub/activity/PaymentHubReactivateIsaActivity:b042704270427Ч0427Ч04270427	I
    //   48: imul
    //   49: getstatic 31	com/mobile/ui/paymenthub/activity/PaymentHubReactivateIsaActivity:b0427ЧЧ04270427Ч04270427	I
    //   52: irem
    //   53: invokestatic 212	com/mobile/ui/paymenthub/activity/PaymentHubReactivateIsaActivity:bЧ04270427ЧЧ042704270427	()I
    //   56: if_icmpeq +58 -> 114
    //   59: getstatic 27	com/mobile/ui/paymenthub/activity/PaymentHubReactivateIsaActivity:b042704270427Ч0427Ч04270427	I
    //   62: istore_2
    //   63: iload_2
    //   64: getstatic 29	com/mobile/ui/paymenthub/activity/PaymentHubReactivateIsaActivity:bЧЧЧ04270427Ч04270427	I
    //   67: iload_2
    //   68: iadd
    //   69: imul
    //   70: getstatic 31	com/mobile/ui/paymenthub/activity/PaymentHubReactivateIsaActivity:b0427ЧЧ04270427Ч04270427	I
    //   73: irem
    //   74: tableswitch	default:+18->92, 0:+29->103
    //   92: invokestatic 37	com/mobile/ui/paymenthub/activity/PaymentHubReactivateIsaActivity:bЧ0427Ч04270427Ч04270427	()I
    //   95: putstatic 27	com/mobile/ui/paymenthub/activity/PaymentHubReactivateIsaActivity:b042704270427Ч0427Ч04270427	I
    //   98: bipush 40
    //   100: putstatic 33	com/mobile/ui/paymenthub/activity/PaymentHubReactivateIsaActivity:bЧ0427ЧЧЧ042704270427	I
    //   103: invokestatic 37	com/mobile/ui/paymenthub/activity/PaymentHubReactivateIsaActivity:bЧ0427Ч04270427Ч04270427	()I
    //   106: putstatic 27	com/mobile/ui/paymenthub/activity/PaymentHubReactivateIsaActivity:b042704270427Ч0427Ч04270427	I
    //   109: bipush 65
    //   111: putstatic 33	com/mobile/ui/paymenthub/activity/PaymentHubReactivateIsaActivity:bЧ0427ЧЧЧ042704270427	I
    //   114: aload_3
    //   115: iload_1
    //   116: aload 4
    //   118: invokevirtual 200	android/support/v4/app/FragmentTransaction:replace	(ILandroid/support/v4/app/Fragment;)Landroid/support/v4/app/FragmentTransaction;
    //   121: invokevirtual 203	android/support/v4/app/FragmentTransaction:commit	()I
    //   124: pop
    //   125: iconst_1
    //   126: tableswitch	default:+22->148, 0:+-1->125, 1:+49->175
    //   148: iconst_0
    //   149: tableswitch	default:+23->172, 0:+26->175, 1:+-24->125
    //   172: goto -24 -> 148
    //   175: return
    //   176: astore_3
    //   177: aload_3
    //   178: athrow
    //   179: astore_3
    //   180: aload_3
    //   181: athrow
    // Local variable table:
    //   start	length	slot	name	signature
    //   0	182	0	this	PaymentHubReactivateIsaActivity
    //   30	86	1	i	int
    //   62	8	2	j	int
    //   26	89	3	localFragmentTransaction	FragmentTransaction
    //   176	2	3	localException1	Exception
    //   179	2	3	localException2	Exception
    //   17	100	4	localObject	Object
    // Exception table:
    //   from	to	target	type
    //   0	19	176	java/lang/Exception
    //   114	125	176	java/lang/Exception
    //   19	38	179	java/lang/Exception
  }
}
