package com.google.android.gms.internal;

import android.os.Binder;
import android.os.IBinder;
import android.os.IInterface;
import android.os.Parcel;
import android.os.Parcelable.Creator;
import android.os.RemoteException;
import com.google.android.gms.common.data.d;
import com.google.android.gms.common.data.e;
import com.google.android.gms.games.multiplayer.realtime.RealTimeMessage;

public abstract interface ay
  extends IInterface
{
  public abstract void B(int paramInt)
    throws RemoteException;
  
  public abstract void C(int paramInt)
    throws RemoteException;
  
  public abstract void D(int paramInt)
    throws RemoteException;
  
  public abstract void E(int paramInt)
    throws RemoteException;
  
  public abstract void a(int paramInt1, int paramInt2, String paramString)
    throws RemoteException;
  
  public abstract void a(int paramInt, String paramString)
    throws RemoteException;
  
  public abstract void a(int paramInt, String paramString, boolean paramBoolean)
    throws RemoteException;
  
  public abstract void a(d paramD1, d paramD2)
    throws RemoteException;
  
  public abstract void a(d paramD, String[] paramArrayOfString)
    throws RemoteException;
  
  public abstract void b(d paramD)
    throws RemoteException;
  
  public abstract void b(d paramD, String[] paramArrayOfString)
    throws RemoteException;
  
  public abstract void c(d paramD)
    throws RemoteException;
  
  public abstract void c(d paramD, String[] paramArrayOfString)
    throws RemoteException;
  
  public abstract void d(d paramD)
    throws RemoteException;
  
  public abstract void d(d paramD, String[] paramArrayOfString)
    throws RemoteException;
  
  public abstract void e(d paramD)
    throws RemoteException;
  
  public abstract void e(d paramD, String[] paramArrayOfString)
    throws RemoteException;
  
  public abstract void f(d paramD)
    throws RemoteException;
  
  public abstract void f(d paramD, String[] paramArrayOfString)
    throws RemoteException;
  
  public abstract void g(d paramD)
    throws RemoteException;
  
  public abstract void h(d paramD)
    throws RemoteException;
  
  public abstract void i(d paramD)
    throws RemoteException;
  
  public abstract void j(d paramD)
    throws RemoteException;
  
  public abstract void k(d paramD)
    throws RemoteException;
  
  public abstract void l(d paramD)
    throws RemoteException;
  
  public abstract void m(d paramD)
    throws RemoteException;
  
  public abstract void n(d paramD)
    throws RemoteException;
  
  public abstract void o(d paramD)
    throws RemoteException;
  
  public abstract void onAchievementUpdated(int paramInt, String paramString)
    throws RemoteException;
  
  public abstract void onLeftRoom(int paramInt, String paramString)
    throws RemoteException;
  
  public abstract void onP2PConnected(String paramString)
    throws RemoteException;
  
  public abstract void onP2PDisconnected(String paramString)
    throws RemoteException;
  
  public abstract void onRealTimeMessageReceived(RealTimeMessage paramRealTimeMessage)
    throws RemoteException;
  
  public abstract void onSignOutComplete()
    throws RemoteException;
  
  public abstract void p(d paramD)
    throws RemoteException;
  
  public abstract void q(d paramD)
    throws RemoteException;
  
  public abstract void r(d paramD)
    throws RemoteException;
  
  public abstract void s(d paramD)
    throws RemoteException;
  
  public abstract void t(d paramD)
    throws RemoteException;
  
  public abstract void u(d paramD)
    throws RemoteException;
  
  public abstract void v(d paramD)
    throws RemoteException;
  
  public abstract void w(d paramD)
    throws RemoteException;
  
  public static abstract class a
    extends Binder
    implements ay
  {
    public a()
    {
      attachInterface(this, "com.google.android.gms.games.internal.IGamesCallbacks");
    }
    
    public static ay n(IBinder paramIBinder)
    {
      if (paramIBinder == null) {
        return null;
      }
      IInterface localIInterface = paramIBinder.queryLocalInterface("com.google.android.gms.games.internal.IGamesCallbacks");
      if ((localIInterface != null) && ((localIInterface instanceof ay))) {
        return (ay)localIInterface;
      }
      return new a(paramIBinder);
    }
    
    public IBinder asBinder()
    {
      return this;
    }
    
    public boolean onTransact(int paramInt1, Parcel paramParcel1, Parcel paramParcel2, int paramInt2)
      throws RemoteException
    {
      Object localObject2 = null;
      d localD = null;
      Object localObject3 = null;
      Object localObject4 = null;
      Object localObject5 = null;
      Object localObject6 = null;
      Object localObject7 = null;
      Object localObject8 = null;
      Object localObject9 = null;
      Object localObject10 = null;
      Object localObject11 = null;
      Object localObject12 = null;
      Object localObject13 = null;
      Object localObject14 = null;
      Object localObject15 = null;
      Object localObject16 = null;
      Object localObject17 = null;
      Object localObject18 = null;
      Object localObject19 = null;
      Object localObject20 = null;
      Object localObject21 = null;
      Object localObject22 = null;
      Object localObject23 = null;
      Object localObject24 = null;
      Object localObject25 = null;
      Object localObject26 = null;
      Object localObject27 = null;
      Object localObject28 = null;
      Object localObject29 = null;
      Object localObject1 = null;
      switch (paramInt1)
      {
      default: 
        return super.onTransact(paramInt1, paramParcel1, paramParcel2, paramInt2);
      case 1598968902: 
        paramParcel2.writeString("com.google.android.gms.games.internal.IGamesCallbacks");
        return true;
      case 5001: 
        paramParcel1.enforceInterface("com.google.android.gms.games.internal.IGamesCallbacks");
        a(paramParcel1.readInt(), paramParcel1.readString());
        paramParcel2.writeNoException();
        return true;
      case 5002: 
        paramParcel1.enforceInterface("com.google.android.gms.games.internal.IGamesCallbacks");
        if (paramParcel1.readInt() != 0) {
          localObject1 = d.CREATOR.a(paramParcel1);
        }
        b((d)localObject1);
        paramParcel2.writeNoException();
        return true;
      case 5003: 
        paramParcel1.enforceInterface("com.google.android.gms.games.internal.IGamesCallbacks");
        onAchievementUpdated(paramParcel1.readInt(), paramParcel1.readString());
        paramParcel2.writeNoException();
        return true;
      case 5004: 
        paramParcel1.enforceInterface("com.google.android.gms.games.internal.IGamesCallbacks");
        localObject1 = localObject2;
        if (paramParcel1.readInt() != 0) {
          localObject1 = d.CREATOR.a(paramParcel1);
        }
        c((d)localObject1);
        paramParcel2.writeNoException();
        return true;
      case 5005: 
        paramParcel1.enforceInterface("com.google.android.gms.games.internal.IGamesCallbacks");
        if (paramParcel1.readInt() != 0) {}
        for (localObject1 = d.CREATOR.a(paramParcel1);; localObject1 = null)
        {
          if (paramParcel1.readInt() != 0) {
            localD = d.CREATOR.a(paramParcel1);
          }
          a((d)localObject1, localD);
          paramParcel2.writeNoException();
          return true;
        }
      case 5006: 
        paramParcel1.enforceInterface("com.google.android.gms.games.internal.IGamesCallbacks");
        localObject1 = localObject3;
        if (paramParcel1.readInt() != 0) {
          localObject1 = d.CREATOR.a(paramParcel1);
        }
        d((d)localObject1);
        paramParcel2.writeNoException();
        return true;
      case 5007: 
        paramParcel1.enforceInterface("com.google.android.gms.games.internal.IGamesCallbacks");
        localObject1 = localObject4;
        if (paramParcel1.readInt() != 0) {
          localObject1 = d.CREATOR.a(paramParcel1);
        }
        e((d)localObject1);
        paramParcel2.writeNoException();
        return true;
      case 5008: 
        paramParcel1.enforceInterface("com.google.android.gms.games.internal.IGamesCallbacks");
        localObject1 = localObject5;
        if (paramParcel1.readInt() != 0) {
          localObject1 = d.CREATOR.a(paramParcel1);
        }
        f((d)localObject1);
        paramParcel2.writeNoException();
        return true;
      case 5009: 
        paramParcel1.enforceInterface("com.google.android.gms.games.internal.IGamesCallbacks");
        localObject1 = localObject6;
        if (paramParcel1.readInt() != 0) {
          localObject1 = d.CREATOR.a(paramParcel1);
        }
        g((d)localObject1);
        paramParcel2.writeNoException();
        return true;
      case 5010: 
        paramParcel1.enforceInterface("com.google.android.gms.games.internal.IGamesCallbacks");
        localObject1 = localObject7;
        if (paramParcel1.readInt() != 0) {
          localObject1 = d.CREATOR.a(paramParcel1);
        }
        h((d)localObject1);
        paramParcel2.writeNoException();
        return true;
      case 5011: 
        paramParcel1.enforceInterface("com.google.android.gms.games.internal.IGamesCallbacks");
        localObject1 = localObject8;
        if (paramParcel1.readInt() != 0) {
          localObject1 = d.CREATOR.a(paramParcel1);
        }
        i((d)localObject1);
        paramParcel2.writeNoException();
        return true;
      case 5012: 
        paramParcel1.enforceInterface("com.google.android.gms.games.internal.IGamesCallbacks");
        localObject1 = localObject9;
        if (paramParcel1.readInt() != 0) {
          localObject1 = d.CREATOR.a(paramParcel1);
        }
        l((d)localObject1);
        paramParcel2.writeNoException();
        return true;
      case 5013: 
        paramParcel1.enforceInterface("com.google.android.gms.games.internal.IGamesCallbacks");
        B(paramParcel1.readInt());
        paramParcel2.writeNoException();
        return true;
      case 5014: 
        paramParcel1.enforceInterface("com.google.android.gms.games.internal.IGamesCallbacks");
        localObject1 = localObject10;
        if (paramParcel1.readInt() != 0) {
          localObject1 = d.CREATOR.a(paramParcel1);
        }
        m((d)localObject1);
        paramParcel2.writeNoException();
        return true;
      case 5015: 
        paramParcel1.enforceInterface("com.google.android.gms.games.internal.IGamesCallbacks");
        C(paramParcel1.readInt());
        paramParcel2.writeNoException();
        return true;
      case 5016: 
        paramParcel1.enforceInterface("com.google.android.gms.games.internal.IGamesCallbacks");
        onSignOutComplete();
        paramParcel2.writeNoException();
        return true;
      case 5017: 
        paramParcel1.enforceInterface("com.google.android.gms.games.internal.IGamesCallbacks");
        localObject1 = localObject11;
        if (paramParcel1.readInt() != 0) {
          localObject1 = d.CREATOR.a(paramParcel1);
        }
        j((d)localObject1);
        paramParcel2.writeNoException();
        return true;
      case 5037: 
        paramParcel1.enforceInterface("com.google.android.gms.games.internal.IGamesCallbacks");
        localObject1 = localObject12;
        if (paramParcel1.readInt() != 0) {
          localObject1 = d.CREATOR.a(paramParcel1);
        }
        k((d)localObject1);
        paramParcel2.writeNoException();
        return true;
      case 5018: 
        paramParcel1.enforceInterface("com.google.android.gms.games.internal.IGamesCallbacks");
        localObject1 = localObject13;
        if (paramParcel1.readInt() != 0) {
          localObject1 = d.CREATOR.a(paramParcel1);
        }
        n((d)localObject1);
        paramParcel2.writeNoException();
        return true;
      case 5019: 
        paramParcel1.enforceInterface("com.google.android.gms.games.internal.IGamesCallbacks");
        localObject1 = localObject14;
        if (paramParcel1.readInt() != 0) {
          localObject1 = d.CREATOR.a(paramParcel1);
        }
        o((d)localObject1);
        paramParcel2.writeNoException();
        return true;
      case 5020: 
        paramParcel1.enforceInterface("com.google.android.gms.games.internal.IGamesCallbacks");
        onLeftRoom(paramParcel1.readInt(), paramParcel1.readString());
        paramParcel2.writeNoException();
        return true;
      case 5021: 
        paramParcel1.enforceInterface("com.google.android.gms.games.internal.IGamesCallbacks");
        localObject1 = localObject15;
        if (paramParcel1.readInt() != 0) {
          localObject1 = d.CREATOR.a(paramParcel1);
        }
        p((d)localObject1);
        paramParcel2.writeNoException();
        return true;
      case 5022: 
        paramParcel1.enforceInterface("com.google.android.gms.games.internal.IGamesCallbacks");
        localObject1 = localObject16;
        if (paramParcel1.readInt() != 0) {
          localObject1 = d.CREATOR.a(paramParcel1);
        }
        q((d)localObject1);
        paramParcel2.writeNoException();
        return true;
      case 5023: 
        paramParcel1.enforceInterface("com.google.android.gms.games.internal.IGamesCallbacks");
        localObject1 = localObject17;
        if (paramParcel1.readInt() != 0) {
          localObject1 = d.CREATOR.a(paramParcel1);
        }
        r((d)localObject1);
        paramParcel2.writeNoException();
        return true;
      case 5024: 
        paramParcel1.enforceInterface("com.google.android.gms.games.internal.IGamesCallbacks");
        localObject1 = localObject18;
        if (paramParcel1.readInt() != 0) {
          localObject1 = d.CREATOR.a(paramParcel1);
        }
        s((d)localObject1);
        paramParcel2.writeNoException();
        return true;
      case 5025: 
        paramParcel1.enforceInterface("com.google.android.gms.games.internal.IGamesCallbacks");
        localObject1 = localObject19;
        if (paramParcel1.readInt() != 0) {
          localObject1 = d.CREATOR.a(paramParcel1);
        }
        t((d)localObject1);
        paramParcel2.writeNoException();
        return true;
      case 5026: 
        paramParcel1.enforceInterface("com.google.android.gms.games.internal.IGamesCallbacks");
        localObject1 = localObject20;
        if (paramParcel1.readInt() != 0) {
          localObject1 = d.CREATOR.a(paramParcel1);
        }
        a((d)localObject1, paramParcel1.createStringArray());
        paramParcel2.writeNoException();
        return true;
      case 5027: 
        paramParcel1.enforceInterface("com.google.android.gms.games.internal.IGamesCallbacks");
        localObject1 = localObject21;
        if (paramParcel1.readInt() != 0) {
          localObject1 = d.CREATOR.a(paramParcel1);
        }
        b((d)localObject1, paramParcel1.createStringArray());
        paramParcel2.writeNoException();
        return true;
      case 5028: 
        paramParcel1.enforceInterface("com.google.android.gms.games.internal.IGamesCallbacks");
        localObject1 = localObject22;
        if (paramParcel1.readInt() != 0) {
          localObject1 = d.CREATOR.a(paramParcel1);
        }
        c((d)localObject1, paramParcel1.createStringArray());
        paramParcel2.writeNoException();
        return true;
      case 5029: 
        paramParcel1.enforceInterface("com.google.android.gms.games.internal.IGamesCallbacks");
        localObject1 = localObject23;
        if (paramParcel1.readInt() != 0) {
          localObject1 = d.CREATOR.a(paramParcel1);
        }
        d((d)localObject1, paramParcel1.createStringArray());
        paramParcel2.writeNoException();
        return true;
      case 5030: 
        paramParcel1.enforceInterface("com.google.android.gms.games.internal.IGamesCallbacks");
        localObject1 = localObject24;
        if (paramParcel1.readInt() != 0) {
          localObject1 = d.CREATOR.a(paramParcel1);
        }
        e((d)localObject1, paramParcel1.createStringArray());
        paramParcel2.writeNoException();
        return true;
      case 5031: 
        paramParcel1.enforceInterface("com.google.android.gms.games.internal.IGamesCallbacks");
        localObject1 = localObject25;
        if (paramParcel1.readInt() != 0) {
          localObject1 = d.CREATOR.a(paramParcel1);
        }
        f((d)localObject1, paramParcel1.createStringArray());
        paramParcel2.writeNoException();
        return true;
      case 5032: 
        paramParcel1.enforceInterface("com.google.android.gms.games.internal.IGamesCallbacks");
        localObject1 = localObject26;
        if (paramParcel1.readInt() != 0) {
          localObject1 = (RealTimeMessage)RealTimeMessage.CREATOR.createFromParcel(paramParcel1);
        }
        onRealTimeMessageReceived((RealTimeMessage)localObject1);
        paramParcel2.writeNoException();
        return true;
      case 5033: 
        paramParcel1.enforceInterface("com.google.android.gms.games.internal.IGamesCallbacks");
        a(paramParcel1.readInt(), paramParcel1.readInt(), paramParcel1.readString());
        paramParcel2.writeNoException();
        return true;
      case 5034: 
        paramParcel1.enforceInterface("com.google.android.gms.games.internal.IGamesCallbacks");
        paramInt1 = paramParcel1.readInt();
        localObject1 = paramParcel1.readString();
        if (paramParcel1.readInt() != 0) {}
        for (boolean bool = true;; bool = false)
        {
          a(paramInt1, (String)localObject1, bool);
          paramParcel2.writeNoException();
          return true;
        }
      case 5038: 
        paramParcel1.enforceInterface("com.google.android.gms.games.internal.IGamesCallbacks");
        localObject1 = localObject27;
        if (paramParcel1.readInt() != 0) {
          localObject1 = d.CREATOR.a(paramParcel1);
        }
        u((d)localObject1);
        paramParcel2.writeNoException();
        return true;
      case 5035: 
        paramParcel1.enforceInterface("com.google.android.gms.games.internal.IGamesCallbacks");
        localObject1 = localObject28;
        if (paramParcel1.readInt() != 0) {
          localObject1 = d.CREATOR.a(paramParcel1);
        }
        v((d)localObject1);
        paramParcel2.writeNoException();
        return true;
      case 5036: 
        paramParcel1.enforceInterface("com.google.android.gms.games.internal.IGamesCallbacks");
        D(paramParcel1.readInt());
        paramParcel2.writeNoException();
        return true;
      case 5039: 
        paramParcel1.enforceInterface("com.google.android.gms.games.internal.IGamesCallbacks");
        localObject1 = localObject29;
        if (paramParcel1.readInt() != 0) {
          localObject1 = d.CREATOR.a(paramParcel1);
        }
        w((d)localObject1);
        paramParcel2.writeNoException();
        return true;
      case 5040: 
        paramParcel1.enforceInterface("com.google.android.gms.games.internal.IGamesCallbacks");
        E(paramParcel1.readInt());
        paramParcel2.writeNoException();
        return true;
      case 6001: 
        paramParcel1.enforceInterface("com.google.android.gms.games.internal.IGamesCallbacks");
        onP2PConnected(paramParcel1.readString());
        paramParcel2.writeNoException();
        return true;
      }
      paramParcel1.enforceInterface("com.google.android.gms.games.internal.IGamesCallbacks");
      onP2PDisconnected(paramParcel1.readString());
      paramParcel2.writeNoException();
      return true;
    }
    
    private static class a
      implements ay
    {
      private IBinder a;
      
      a(IBinder paramIBinder)
      {
        this.a = paramIBinder;
      }
      
      public void B(int paramInt)
        throws RemoteException
      {
        Parcel localParcel1 = Parcel.obtain();
        Parcel localParcel2 = Parcel.obtain();
        try
        {
          localParcel1.writeInterfaceToken("com.google.android.gms.games.internal.IGamesCallbacks");
          localParcel1.writeInt(paramInt);
          this.a.transact(5013, localParcel1, localParcel2, 0);
          localParcel2.readException();
          return;
        }
        finally
        {
          localParcel2.recycle();
          localParcel1.recycle();
        }
      }
      
      public void C(int paramInt)
        throws RemoteException
      {
        Parcel localParcel1 = Parcel.obtain();
        Parcel localParcel2 = Parcel.obtain();
        try
        {
          localParcel1.writeInterfaceToken("com.google.android.gms.games.internal.IGamesCallbacks");
          localParcel1.writeInt(paramInt);
          this.a.transact(5015, localParcel1, localParcel2, 0);
          localParcel2.readException();
          return;
        }
        finally
        {
          localParcel2.recycle();
          localParcel1.recycle();
        }
      }
      
      public void D(int paramInt)
        throws RemoteException
      {
        Parcel localParcel1 = Parcel.obtain();
        Parcel localParcel2 = Parcel.obtain();
        try
        {
          localParcel1.writeInterfaceToken("com.google.android.gms.games.internal.IGamesCallbacks");
          localParcel1.writeInt(paramInt);
          this.a.transact(5036, localParcel1, localParcel2, 0);
          localParcel2.readException();
          return;
        }
        finally
        {
          localParcel2.recycle();
          localParcel1.recycle();
        }
      }
      
      public void E(int paramInt)
        throws RemoteException
      {
        Parcel localParcel1 = Parcel.obtain();
        Parcel localParcel2 = Parcel.obtain();
        try
        {
          localParcel1.writeInterfaceToken("com.google.android.gms.games.internal.IGamesCallbacks");
          localParcel1.writeInt(paramInt);
          this.a.transact(5040, localParcel1, localParcel2, 0);
          localParcel2.readException();
          return;
        }
        finally
        {
          localParcel2.recycle();
          localParcel1.recycle();
        }
      }
      
      public void a(int paramInt1, int paramInt2, String paramString)
        throws RemoteException
      {
        Parcel localParcel1 = Parcel.obtain();
        Parcel localParcel2 = Parcel.obtain();
        try
        {
          localParcel1.writeInterfaceToken("com.google.android.gms.games.internal.IGamesCallbacks");
          localParcel1.writeInt(paramInt1);
          localParcel1.writeInt(paramInt2);
          localParcel1.writeString(paramString);
          this.a.transact(5033, localParcel1, localParcel2, 0);
          localParcel2.readException();
          return;
        }
        finally
        {
          localParcel2.recycle();
          localParcel1.recycle();
        }
      }
      
      public void a(int paramInt, String paramString)
        throws RemoteException
      {
        Parcel localParcel1 = Parcel.obtain();
        Parcel localParcel2 = Parcel.obtain();
        try
        {
          localParcel1.writeInterfaceToken("com.google.android.gms.games.internal.IGamesCallbacks");
          localParcel1.writeInt(paramInt);
          localParcel1.writeString(paramString);
          this.a.transact(5001, localParcel1, localParcel2, 0);
          localParcel2.readException();
          return;
        }
        finally
        {
          localParcel2.recycle();
          localParcel1.recycle();
        }
      }
      
      public void a(int paramInt, String paramString, boolean paramBoolean)
        throws RemoteException
      {
        int i = 0;
        Parcel localParcel1 = Parcel.obtain();
        Parcel localParcel2 = Parcel.obtain();
        try
        {
          localParcel1.writeInterfaceToken("com.google.android.gms.games.internal.IGamesCallbacks");
          localParcel1.writeInt(paramInt);
          localParcel1.writeString(paramString);
          paramInt = i;
          if (paramBoolean) {
            paramInt = 1;
          }
          localParcel1.writeInt(paramInt);
          this.a.transact(5034, localParcel1, localParcel2, 0);
          localParcel2.readException();
          return;
        }
        finally
        {
          localParcel2.recycle();
          localParcel1.recycle();
        }
      }
      
      public void a(d paramD1, d paramD2)
        throws RemoteException
      {
        Parcel localParcel1 = Parcel.obtain();
        Parcel localParcel2 = Parcel.obtain();
        for (;;)
        {
          try
          {
            localParcel1.writeInterfaceToken("com.google.android.gms.games.internal.IGamesCallbacks");
            if (paramD1 != null)
            {
              localParcel1.writeInt(1);
              paramD1.writeToParcel(localParcel1, 0);
              if (paramD2 != null)
              {
                localParcel1.writeInt(1);
                paramD2.writeToParcel(localParcel1, 0);
                this.a.transact(5005, localParcel1, localParcel2, 0);
                localParcel2.readException();
              }
            }
            else
            {
              localParcel1.writeInt(0);
              continue;
            }
            localParcel1.writeInt(0);
          }
          finally
          {
            localParcel2.recycle();
            localParcel1.recycle();
          }
        }
      }
      
      /* Error */
      public void a(d paramD, String[] paramArrayOfString)
        throws RemoteException
      {
        // Byte code:
        //   0: invokestatic 28	android/os/Parcel:obtain	()Landroid/os/Parcel;
        //   3: astore_3
        //   4: invokestatic 28	android/os/Parcel:obtain	()Landroid/os/Parcel;
        //   7: astore 4
        //   9: aload_3
        //   10: ldc 30
        //   12: invokevirtual 34	android/os/Parcel:writeInterfaceToken	(Ljava/lang/String;)V
        //   15: aload_1
        //   16: ifnull +51 -> 67
        //   19: aload_3
        //   20: iconst_1
        //   21: invokevirtual 37	android/os/Parcel:writeInt	(I)V
        //   24: aload_1
        //   25: aload_3
        //   26: iconst_0
        //   27: invokevirtual 66	com/google/android/gms/common/data/d:writeToParcel	(Landroid/os/Parcel;I)V
        //   30: aload_3
        //   31: aload_2
        //   32: invokevirtual 71	android/os/Parcel:writeStringArray	([Ljava/lang/String;)V
        //   35: aload_0
        //   36: getfield 17	com/google/android/gms/internal/ay$a$a:a	Landroid/os/IBinder;
        //   39: sipush 5026
        //   42: aload_3
        //   43: aload 4
        //   45: iconst_0
        //   46: invokeinterface 43 5 0
        //   51: pop
        //   52: aload 4
        //   54: invokevirtual 46	android/os/Parcel:readException	()V
        //   57: aload 4
        //   59: invokevirtual 49	android/os/Parcel:recycle	()V
        //   62: aload_3
        //   63: invokevirtual 49	android/os/Parcel:recycle	()V
        //   66: return
        //   67: aload_3
        //   68: iconst_0
        //   69: invokevirtual 37	android/os/Parcel:writeInt	(I)V
        //   72: goto -42 -> 30
        //   75: astore_1
        //   76: aload 4
        //   78: invokevirtual 49	android/os/Parcel:recycle	()V
        //   81: aload_3
        //   82: invokevirtual 49	android/os/Parcel:recycle	()V
        //   85: aload_1
        //   86: athrow
        // Local variable table:
        //   start	length	slot	name	signature
        //   0	87	0	this	a
        //   0	87	1	paramD	d
        //   0	87	2	paramArrayOfString	String[]
        //   3	79	3	localParcel1	Parcel
        //   7	70	4	localParcel2	Parcel
        // Exception table:
        //   from	to	target	type
        //   9	15	75	finally
        //   19	30	75	finally
        //   30	57	75	finally
        //   67	72	75	finally
      }
      
      public IBinder asBinder()
      {
        return this.a;
      }
      
      /* Error */
      public void b(d paramD)
        throws RemoteException
      {
        // Byte code:
        //   0: invokestatic 28	android/os/Parcel:obtain	()Landroid/os/Parcel;
        //   3: astore_2
        //   4: invokestatic 28	android/os/Parcel:obtain	()Landroid/os/Parcel;
        //   7: astore_3
        //   8: aload_2
        //   9: ldc 30
        //   11: invokevirtual 34	android/os/Parcel:writeInterfaceToken	(Ljava/lang/String;)V
        //   14: aload_1
        //   15: ifnull +43 -> 58
        //   18: aload_2
        //   19: iconst_1
        //   20: invokevirtual 37	android/os/Parcel:writeInt	(I)V
        //   23: aload_1
        //   24: aload_2
        //   25: iconst_0
        //   26: invokevirtual 66	com/google/android/gms/common/data/d:writeToParcel	(Landroid/os/Parcel;I)V
        //   29: aload_0
        //   30: getfield 17	com/google/android/gms/internal/ay$a$a:a	Landroid/os/IBinder;
        //   33: sipush 5002
        //   36: aload_2
        //   37: aload_3
        //   38: iconst_0
        //   39: invokeinterface 43 5 0
        //   44: pop
        //   45: aload_3
        //   46: invokevirtual 46	android/os/Parcel:readException	()V
        //   49: aload_3
        //   50: invokevirtual 49	android/os/Parcel:recycle	()V
        //   53: aload_2
        //   54: invokevirtual 49	android/os/Parcel:recycle	()V
        //   57: return
        //   58: aload_2
        //   59: iconst_0
        //   60: invokevirtual 37	android/os/Parcel:writeInt	(I)V
        //   63: goto -34 -> 29
        //   66: astore_1
        //   67: aload_3
        //   68: invokevirtual 49	android/os/Parcel:recycle	()V
        //   71: aload_2
        //   72: invokevirtual 49	android/os/Parcel:recycle	()V
        //   75: aload_1
        //   76: athrow
        // Local variable table:
        //   start	length	slot	name	signature
        //   0	77	0	this	a
        //   0	77	1	paramD	d
        //   3	69	2	localParcel1	Parcel
        //   7	61	3	localParcel2	Parcel
        // Exception table:
        //   from	to	target	type
        //   8	14	66	finally
        //   18	29	66	finally
        //   29	49	66	finally
        //   58	63	66	finally
      }
      
      /* Error */
      public void b(d paramD, String[] paramArrayOfString)
        throws RemoteException
      {
        // Byte code:
        //   0: invokestatic 28	android/os/Parcel:obtain	()Landroid/os/Parcel;
        //   3: astore_3
        //   4: invokestatic 28	android/os/Parcel:obtain	()Landroid/os/Parcel;
        //   7: astore 4
        //   9: aload_3
        //   10: ldc 30
        //   12: invokevirtual 34	android/os/Parcel:writeInterfaceToken	(Ljava/lang/String;)V
        //   15: aload_1
        //   16: ifnull +51 -> 67
        //   19: aload_3
        //   20: iconst_1
        //   21: invokevirtual 37	android/os/Parcel:writeInt	(I)V
        //   24: aload_1
        //   25: aload_3
        //   26: iconst_0
        //   27: invokevirtual 66	com/google/android/gms/common/data/d:writeToParcel	(Landroid/os/Parcel;I)V
        //   30: aload_3
        //   31: aload_2
        //   32: invokevirtual 71	android/os/Parcel:writeStringArray	([Ljava/lang/String;)V
        //   35: aload_0
        //   36: getfield 17	com/google/android/gms/internal/ay$a$a:a	Landroid/os/IBinder;
        //   39: sipush 5027
        //   42: aload_3
        //   43: aload 4
        //   45: iconst_0
        //   46: invokeinterface 43 5 0
        //   51: pop
        //   52: aload 4
        //   54: invokevirtual 46	android/os/Parcel:readException	()V
        //   57: aload 4
        //   59: invokevirtual 49	android/os/Parcel:recycle	()V
        //   62: aload_3
        //   63: invokevirtual 49	android/os/Parcel:recycle	()V
        //   66: return
        //   67: aload_3
        //   68: iconst_0
        //   69: invokevirtual 37	android/os/Parcel:writeInt	(I)V
        //   72: goto -42 -> 30
        //   75: astore_1
        //   76: aload 4
        //   78: invokevirtual 49	android/os/Parcel:recycle	()V
        //   81: aload_3
        //   82: invokevirtual 49	android/os/Parcel:recycle	()V
        //   85: aload_1
        //   86: athrow
        // Local variable table:
        //   start	length	slot	name	signature
        //   0	87	0	this	a
        //   0	87	1	paramD	d
        //   0	87	2	paramArrayOfString	String[]
        //   3	79	3	localParcel1	Parcel
        //   7	70	4	localParcel2	Parcel
        // Exception table:
        //   from	to	target	type
        //   9	15	75	finally
        //   19	30	75	finally
        //   30	57	75	finally
        //   67	72	75	finally
      }
      
      /* Error */
      public void c(d paramD)
        throws RemoteException
      {
        // Byte code:
        //   0: invokestatic 28	android/os/Parcel:obtain	()Landroid/os/Parcel;
        //   3: astore_2
        //   4: invokestatic 28	android/os/Parcel:obtain	()Landroid/os/Parcel;
        //   7: astore_3
        //   8: aload_2
        //   9: ldc 30
        //   11: invokevirtual 34	android/os/Parcel:writeInterfaceToken	(Ljava/lang/String;)V
        //   14: aload_1
        //   15: ifnull +43 -> 58
        //   18: aload_2
        //   19: iconst_1
        //   20: invokevirtual 37	android/os/Parcel:writeInt	(I)V
        //   23: aload_1
        //   24: aload_2
        //   25: iconst_0
        //   26: invokevirtual 66	com/google/android/gms/common/data/d:writeToParcel	(Landroid/os/Parcel;I)V
        //   29: aload_0
        //   30: getfield 17	com/google/android/gms/internal/ay$a$a:a	Landroid/os/IBinder;
        //   33: sipush 5004
        //   36: aload_2
        //   37: aload_3
        //   38: iconst_0
        //   39: invokeinterface 43 5 0
        //   44: pop
        //   45: aload_3
        //   46: invokevirtual 46	android/os/Parcel:readException	()V
        //   49: aload_3
        //   50: invokevirtual 49	android/os/Parcel:recycle	()V
        //   53: aload_2
        //   54: invokevirtual 49	android/os/Parcel:recycle	()V
        //   57: return
        //   58: aload_2
        //   59: iconst_0
        //   60: invokevirtual 37	android/os/Parcel:writeInt	(I)V
        //   63: goto -34 -> 29
        //   66: astore_1
        //   67: aload_3
        //   68: invokevirtual 49	android/os/Parcel:recycle	()V
        //   71: aload_2
        //   72: invokevirtual 49	android/os/Parcel:recycle	()V
        //   75: aload_1
        //   76: athrow
        // Local variable table:
        //   start	length	slot	name	signature
        //   0	77	0	this	a
        //   0	77	1	paramD	d
        //   3	69	2	localParcel1	Parcel
        //   7	61	3	localParcel2	Parcel
        // Exception table:
        //   from	to	target	type
        //   8	14	66	finally
        //   18	29	66	finally
        //   29	49	66	finally
        //   58	63	66	finally
      }
      
      /* Error */
      public void c(d paramD, String[] paramArrayOfString)
        throws RemoteException
      {
        // Byte code:
        //   0: invokestatic 28	android/os/Parcel:obtain	()Landroid/os/Parcel;
        //   3: astore_3
        //   4: invokestatic 28	android/os/Parcel:obtain	()Landroid/os/Parcel;
        //   7: astore 4
        //   9: aload_3
        //   10: ldc 30
        //   12: invokevirtual 34	android/os/Parcel:writeInterfaceToken	(Ljava/lang/String;)V
        //   15: aload_1
        //   16: ifnull +51 -> 67
        //   19: aload_3
        //   20: iconst_1
        //   21: invokevirtual 37	android/os/Parcel:writeInt	(I)V
        //   24: aload_1
        //   25: aload_3
        //   26: iconst_0
        //   27: invokevirtual 66	com/google/android/gms/common/data/d:writeToParcel	(Landroid/os/Parcel;I)V
        //   30: aload_3
        //   31: aload_2
        //   32: invokevirtual 71	android/os/Parcel:writeStringArray	([Ljava/lang/String;)V
        //   35: aload_0
        //   36: getfield 17	com/google/android/gms/internal/ay$a$a:a	Landroid/os/IBinder;
        //   39: sipush 5028
        //   42: aload_3
        //   43: aload 4
        //   45: iconst_0
        //   46: invokeinterface 43 5 0
        //   51: pop
        //   52: aload 4
        //   54: invokevirtual 46	android/os/Parcel:readException	()V
        //   57: aload 4
        //   59: invokevirtual 49	android/os/Parcel:recycle	()V
        //   62: aload_3
        //   63: invokevirtual 49	android/os/Parcel:recycle	()V
        //   66: return
        //   67: aload_3
        //   68: iconst_0
        //   69: invokevirtual 37	android/os/Parcel:writeInt	(I)V
        //   72: goto -42 -> 30
        //   75: astore_1
        //   76: aload 4
        //   78: invokevirtual 49	android/os/Parcel:recycle	()V
        //   81: aload_3
        //   82: invokevirtual 49	android/os/Parcel:recycle	()V
        //   85: aload_1
        //   86: athrow
        // Local variable table:
        //   start	length	slot	name	signature
        //   0	87	0	this	a
        //   0	87	1	paramD	d
        //   0	87	2	paramArrayOfString	String[]
        //   3	79	3	localParcel1	Parcel
        //   7	70	4	localParcel2	Parcel
        // Exception table:
        //   from	to	target	type
        //   9	15	75	finally
        //   19	30	75	finally
        //   30	57	75	finally
        //   67	72	75	finally
      }
      
      /* Error */
      public void d(d paramD)
        throws RemoteException
      {
        // Byte code:
        //   0: invokestatic 28	android/os/Parcel:obtain	()Landroid/os/Parcel;
        //   3: astore_2
        //   4: invokestatic 28	android/os/Parcel:obtain	()Landroid/os/Parcel;
        //   7: astore_3
        //   8: aload_2
        //   9: ldc 30
        //   11: invokevirtual 34	android/os/Parcel:writeInterfaceToken	(Ljava/lang/String;)V
        //   14: aload_1
        //   15: ifnull +43 -> 58
        //   18: aload_2
        //   19: iconst_1
        //   20: invokevirtual 37	android/os/Parcel:writeInt	(I)V
        //   23: aload_1
        //   24: aload_2
        //   25: iconst_0
        //   26: invokevirtual 66	com/google/android/gms/common/data/d:writeToParcel	(Landroid/os/Parcel;I)V
        //   29: aload_0
        //   30: getfield 17	com/google/android/gms/internal/ay$a$a:a	Landroid/os/IBinder;
        //   33: sipush 5006
        //   36: aload_2
        //   37: aload_3
        //   38: iconst_0
        //   39: invokeinterface 43 5 0
        //   44: pop
        //   45: aload_3
        //   46: invokevirtual 46	android/os/Parcel:readException	()V
        //   49: aload_3
        //   50: invokevirtual 49	android/os/Parcel:recycle	()V
        //   53: aload_2
        //   54: invokevirtual 49	android/os/Parcel:recycle	()V
        //   57: return
        //   58: aload_2
        //   59: iconst_0
        //   60: invokevirtual 37	android/os/Parcel:writeInt	(I)V
        //   63: goto -34 -> 29
        //   66: astore_1
        //   67: aload_3
        //   68: invokevirtual 49	android/os/Parcel:recycle	()V
        //   71: aload_2
        //   72: invokevirtual 49	android/os/Parcel:recycle	()V
        //   75: aload_1
        //   76: athrow
        // Local variable table:
        //   start	length	slot	name	signature
        //   0	77	0	this	a
        //   0	77	1	paramD	d
        //   3	69	2	localParcel1	Parcel
        //   7	61	3	localParcel2	Parcel
        // Exception table:
        //   from	to	target	type
        //   8	14	66	finally
        //   18	29	66	finally
        //   29	49	66	finally
        //   58	63	66	finally
      }
      
      /* Error */
      public void d(d paramD, String[] paramArrayOfString)
        throws RemoteException
      {
        // Byte code:
        //   0: invokestatic 28	android/os/Parcel:obtain	()Landroid/os/Parcel;
        //   3: astore_3
        //   4: invokestatic 28	android/os/Parcel:obtain	()Landroid/os/Parcel;
        //   7: astore 4
        //   9: aload_3
        //   10: ldc 30
        //   12: invokevirtual 34	android/os/Parcel:writeInterfaceToken	(Ljava/lang/String;)V
        //   15: aload_1
        //   16: ifnull +51 -> 67
        //   19: aload_3
        //   20: iconst_1
        //   21: invokevirtual 37	android/os/Parcel:writeInt	(I)V
        //   24: aload_1
        //   25: aload_3
        //   26: iconst_0
        //   27: invokevirtual 66	com/google/android/gms/common/data/d:writeToParcel	(Landroid/os/Parcel;I)V
        //   30: aload_3
        //   31: aload_2
        //   32: invokevirtual 71	android/os/Parcel:writeStringArray	([Ljava/lang/String;)V
        //   35: aload_0
        //   36: getfield 17	com/google/android/gms/internal/ay$a$a:a	Landroid/os/IBinder;
        //   39: sipush 5029
        //   42: aload_3
        //   43: aload 4
        //   45: iconst_0
        //   46: invokeinterface 43 5 0
        //   51: pop
        //   52: aload 4
        //   54: invokevirtual 46	android/os/Parcel:readException	()V
        //   57: aload 4
        //   59: invokevirtual 49	android/os/Parcel:recycle	()V
        //   62: aload_3
        //   63: invokevirtual 49	android/os/Parcel:recycle	()V
        //   66: return
        //   67: aload_3
        //   68: iconst_0
        //   69: invokevirtual 37	android/os/Parcel:writeInt	(I)V
        //   72: goto -42 -> 30
        //   75: astore_1
        //   76: aload 4
        //   78: invokevirtual 49	android/os/Parcel:recycle	()V
        //   81: aload_3
        //   82: invokevirtual 49	android/os/Parcel:recycle	()V
        //   85: aload_1
        //   86: athrow
        // Local variable table:
        //   start	length	slot	name	signature
        //   0	87	0	this	a
        //   0	87	1	paramD	d
        //   0	87	2	paramArrayOfString	String[]
        //   3	79	3	localParcel1	Parcel
        //   7	70	4	localParcel2	Parcel
        // Exception table:
        //   from	to	target	type
        //   9	15	75	finally
        //   19	30	75	finally
        //   30	57	75	finally
        //   67	72	75	finally
      }
      
      /* Error */
      public void e(d paramD)
        throws RemoteException
      {
        // Byte code:
        //   0: invokestatic 28	android/os/Parcel:obtain	()Landroid/os/Parcel;
        //   3: astore_2
        //   4: invokestatic 28	android/os/Parcel:obtain	()Landroid/os/Parcel;
        //   7: astore_3
        //   8: aload_2
        //   9: ldc 30
        //   11: invokevirtual 34	android/os/Parcel:writeInterfaceToken	(Ljava/lang/String;)V
        //   14: aload_1
        //   15: ifnull +43 -> 58
        //   18: aload_2
        //   19: iconst_1
        //   20: invokevirtual 37	android/os/Parcel:writeInt	(I)V
        //   23: aload_1
        //   24: aload_2
        //   25: iconst_0
        //   26: invokevirtual 66	com/google/android/gms/common/data/d:writeToParcel	(Landroid/os/Parcel;I)V
        //   29: aload_0
        //   30: getfield 17	com/google/android/gms/internal/ay$a$a:a	Landroid/os/IBinder;
        //   33: sipush 5007
        //   36: aload_2
        //   37: aload_3
        //   38: iconst_0
        //   39: invokeinterface 43 5 0
        //   44: pop
        //   45: aload_3
        //   46: invokevirtual 46	android/os/Parcel:readException	()V
        //   49: aload_3
        //   50: invokevirtual 49	android/os/Parcel:recycle	()V
        //   53: aload_2
        //   54: invokevirtual 49	android/os/Parcel:recycle	()V
        //   57: return
        //   58: aload_2
        //   59: iconst_0
        //   60: invokevirtual 37	android/os/Parcel:writeInt	(I)V
        //   63: goto -34 -> 29
        //   66: astore_1
        //   67: aload_3
        //   68: invokevirtual 49	android/os/Parcel:recycle	()V
        //   71: aload_2
        //   72: invokevirtual 49	android/os/Parcel:recycle	()V
        //   75: aload_1
        //   76: athrow
        // Local variable table:
        //   start	length	slot	name	signature
        //   0	77	0	this	a
        //   0	77	1	paramD	d
        //   3	69	2	localParcel1	Parcel
        //   7	61	3	localParcel2	Parcel
        // Exception table:
        //   from	to	target	type
        //   8	14	66	finally
        //   18	29	66	finally
        //   29	49	66	finally
        //   58	63	66	finally
      }
      
      /* Error */
      public void e(d paramD, String[] paramArrayOfString)
        throws RemoteException
      {
        // Byte code:
        //   0: invokestatic 28	android/os/Parcel:obtain	()Landroid/os/Parcel;
        //   3: astore_3
        //   4: invokestatic 28	android/os/Parcel:obtain	()Landroid/os/Parcel;
        //   7: astore 4
        //   9: aload_3
        //   10: ldc 30
        //   12: invokevirtual 34	android/os/Parcel:writeInterfaceToken	(Ljava/lang/String;)V
        //   15: aload_1
        //   16: ifnull +51 -> 67
        //   19: aload_3
        //   20: iconst_1
        //   21: invokevirtual 37	android/os/Parcel:writeInt	(I)V
        //   24: aload_1
        //   25: aload_3
        //   26: iconst_0
        //   27: invokevirtual 66	com/google/android/gms/common/data/d:writeToParcel	(Landroid/os/Parcel;I)V
        //   30: aload_3
        //   31: aload_2
        //   32: invokevirtual 71	android/os/Parcel:writeStringArray	([Ljava/lang/String;)V
        //   35: aload_0
        //   36: getfield 17	com/google/android/gms/internal/ay$a$a:a	Landroid/os/IBinder;
        //   39: sipush 5030
        //   42: aload_3
        //   43: aload 4
        //   45: iconst_0
        //   46: invokeinterface 43 5 0
        //   51: pop
        //   52: aload 4
        //   54: invokevirtual 46	android/os/Parcel:readException	()V
        //   57: aload 4
        //   59: invokevirtual 49	android/os/Parcel:recycle	()V
        //   62: aload_3
        //   63: invokevirtual 49	android/os/Parcel:recycle	()V
        //   66: return
        //   67: aload_3
        //   68: iconst_0
        //   69: invokevirtual 37	android/os/Parcel:writeInt	(I)V
        //   72: goto -42 -> 30
        //   75: astore_1
        //   76: aload 4
        //   78: invokevirtual 49	android/os/Parcel:recycle	()V
        //   81: aload_3
        //   82: invokevirtual 49	android/os/Parcel:recycle	()V
        //   85: aload_1
        //   86: athrow
        // Local variable table:
        //   start	length	slot	name	signature
        //   0	87	0	this	a
        //   0	87	1	paramD	d
        //   0	87	2	paramArrayOfString	String[]
        //   3	79	3	localParcel1	Parcel
        //   7	70	4	localParcel2	Parcel
        // Exception table:
        //   from	to	target	type
        //   9	15	75	finally
        //   19	30	75	finally
        //   30	57	75	finally
        //   67	72	75	finally
      }
      
      /* Error */
      public void f(d paramD)
        throws RemoteException
      {
        // Byte code:
        //   0: invokestatic 28	android/os/Parcel:obtain	()Landroid/os/Parcel;
        //   3: astore_2
        //   4: invokestatic 28	android/os/Parcel:obtain	()Landroid/os/Parcel;
        //   7: astore_3
        //   8: aload_2
        //   9: ldc 30
        //   11: invokevirtual 34	android/os/Parcel:writeInterfaceToken	(Ljava/lang/String;)V
        //   14: aload_1
        //   15: ifnull +43 -> 58
        //   18: aload_2
        //   19: iconst_1
        //   20: invokevirtual 37	android/os/Parcel:writeInt	(I)V
        //   23: aload_1
        //   24: aload_2
        //   25: iconst_0
        //   26: invokevirtual 66	com/google/android/gms/common/data/d:writeToParcel	(Landroid/os/Parcel;I)V
        //   29: aload_0
        //   30: getfield 17	com/google/android/gms/internal/ay$a$a:a	Landroid/os/IBinder;
        //   33: sipush 5008
        //   36: aload_2
        //   37: aload_3
        //   38: iconst_0
        //   39: invokeinterface 43 5 0
        //   44: pop
        //   45: aload_3
        //   46: invokevirtual 46	android/os/Parcel:readException	()V
        //   49: aload_3
        //   50: invokevirtual 49	android/os/Parcel:recycle	()V
        //   53: aload_2
        //   54: invokevirtual 49	android/os/Parcel:recycle	()V
        //   57: return
        //   58: aload_2
        //   59: iconst_0
        //   60: invokevirtual 37	android/os/Parcel:writeInt	(I)V
        //   63: goto -34 -> 29
        //   66: astore_1
        //   67: aload_3
        //   68: invokevirtual 49	android/os/Parcel:recycle	()V
        //   71: aload_2
        //   72: invokevirtual 49	android/os/Parcel:recycle	()V
        //   75: aload_1
        //   76: athrow
        // Local variable table:
        //   start	length	slot	name	signature
        //   0	77	0	this	a
        //   0	77	1	paramD	d
        //   3	69	2	localParcel1	Parcel
        //   7	61	3	localParcel2	Parcel
        // Exception table:
        //   from	to	target	type
        //   8	14	66	finally
        //   18	29	66	finally
        //   29	49	66	finally
        //   58	63	66	finally
      }
      
      /* Error */
      public void f(d paramD, String[] paramArrayOfString)
        throws RemoteException
      {
        // Byte code:
        //   0: invokestatic 28	android/os/Parcel:obtain	()Landroid/os/Parcel;
        //   3: astore_3
        //   4: invokestatic 28	android/os/Parcel:obtain	()Landroid/os/Parcel;
        //   7: astore 4
        //   9: aload_3
        //   10: ldc 30
        //   12: invokevirtual 34	android/os/Parcel:writeInterfaceToken	(Ljava/lang/String;)V
        //   15: aload_1
        //   16: ifnull +51 -> 67
        //   19: aload_3
        //   20: iconst_1
        //   21: invokevirtual 37	android/os/Parcel:writeInt	(I)V
        //   24: aload_1
        //   25: aload_3
        //   26: iconst_0
        //   27: invokevirtual 66	com/google/android/gms/common/data/d:writeToParcel	(Landroid/os/Parcel;I)V
        //   30: aload_3
        //   31: aload_2
        //   32: invokevirtual 71	android/os/Parcel:writeStringArray	([Ljava/lang/String;)V
        //   35: aload_0
        //   36: getfield 17	com/google/android/gms/internal/ay$a$a:a	Landroid/os/IBinder;
        //   39: sipush 5031
        //   42: aload_3
        //   43: aload 4
        //   45: iconst_0
        //   46: invokeinterface 43 5 0
        //   51: pop
        //   52: aload 4
        //   54: invokevirtual 46	android/os/Parcel:readException	()V
        //   57: aload 4
        //   59: invokevirtual 49	android/os/Parcel:recycle	()V
        //   62: aload_3
        //   63: invokevirtual 49	android/os/Parcel:recycle	()V
        //   66: return
        //   67: aload_3
        //   68: iconst_0
        //   69: invokevirtual 37	android/os/Parcel:writeInt	(I)V
        //   72: goto -42 -> 30
        //   75: astore_1
        //   76: aload 4
        //   78: invokevirtual 49	android/os/Parcel:recycle	()V
        //   81: aload_3
        //   82: invokevirtual 49	android/os/Parcel:recycle	()V
        //   85: aload_1
        //   86: athrow
        // Local variable table:
        //   start	length	slot	name	signature
        //   0	87	0	this	a
        //   0	87	1	paramD	d
        //   0	87	2	paramArrayOfString	String[]
        //   3	79	3	localParcel1	Parcel
        //   7	70	4	localParcel2	Parcel
        // Exception table:
        //   from	to	target	type
        //   9	15	75	finally
        //   19	30	75	finally
        //   30	57	75	finally
        //   67	72	75	finally
      }
      
      /* Error */
      public void g(d paramD)
        throws RemoteException
      {
        // Byte code:
        //   0: invokestatic 28	android/os/Parcel:obtain	()Landroid/os/Parcel;
        //   3: astore_2
        //   4: invokestatic 28	android/os/Parcel:obtain	()Landroid/os/Parcel;
        //   7: astore_3
        //   8: aload_2
        //   9: ldc 30
        //   11: invokevirtual 34	android/os/Parcel:writeInterfaceToken	(Ljava/lang/String;)V
        //   14: aload_1
        //   15: ifnull +43 -> 58
        //   18: aload_2
        //   19: iconst_1
        //   20: invokevirtual 37	android/os/Parcel:writeInt	(I)V
        //   23: aload_1
        //   24: aload_2
        //   25: iconst_0
        //   26: invokevirtual 66	com/google/android/gms/common/data/d:writeToParcel	(Landroid/os/Parcel;I)V
        //   29: aload_0
        //   30: getfield 17	com/google/android/gms/internal/ay$a$a:a	Landroid/os/IBinder;
        //   33: sipush 5009
        //   36: aload_2
        //   37: aload_3
        //   38: iconst_0
        //   39: invokeinterface 43 5 0
        //   44: pop
        //   45: aload_3
        //   46: invokevirtual 46	android/os/Parcel:readException	()V
        //   49: aload_3
        //   50: invokevirtual 49	android/os/Parcel:recycle	()V
        //   53: aload_2
        //   54: invokevirtual 49	android/os/Parcel:recycle	()V
        //   57: return
        //   58: aload_2
        //   59: iconst_0
        //   60: invokevirtual 37	android/os/Parcel:writeInt	(I)V
        //   63: goto -34 -> 29
        //   66: astore_1
        //   67: aload_3
        //   68: invokevirtual 49	android/os/Parcel:recycle	()V
        //   71: aload_2
        //   72: invokevirtual 49	android/os/Parcel:recycle	()V
        //   75: aload_1
        //   76: athrow
        // Local variable table:
        //   start	length	slot	name	signature
        //   0	77	0	this	a
        //   0	77	1	paramD	d
        //   3	69	2	localParcel1	Parcel
        //   7	61	3	localParcel2	Parcel
        // Exception table:
        //   from	to	target	type
        //   8	14	66	finally
        //   18	29	66	finally
        //   29	49	66	finally
        //   58	63	66	finally
      }
      
      /* Error */
      public void h(d paramD)
        throws RemoteException
      {
        // Byte code:
        //   0: invokestatic 28	android/os/Parcel:obtain	()Landroid/os/Parcel;
        //   3: astore_2
        //   4: invokestatic 28	android/os/Parcel:obtain	()Landroid/os/Parcel;
        //   7: astore_3
        //   8: aload_2
        //   9: ldc 30
        //   11: invokevirtual 34	android/os/Parcel:writeInterfaceToken	(Ljava/lang/String;)V
        //   14: aload_1
        //   15: ifnull +43 -> 58
        //   18: aload_2
        //   19: iconst_1
        //   20: invokevirtual 37	android/os/Parcel:writeInt	(I)V
        //   23: aload_1
        //   24: aload_2
        //   25: iconst_0
        //   26: invokevirtual 66	com/google/android/gms/common/data/d:writeToParcel	(Landroid/os/Parcel;I)V
        //   29: aload_0
        //   30: getfield 17	com/google/android/gms/internal/ay$a$a:a	Landroid/os/IBinder;
        //   33: sipush 5010
        //   36: aload_2
        //   37: aload_3
        //   38: iconst_0
        //   39: invokeinterface 43 5 0
        //   44: pop
        //   45: aload_3
        //   46: invokevirtual 46	android/os/Parcel:readException	()V
        //   49: aload_3
        //   50: invokevirtual 49	android/os/Parcel:recycle	()V
        //   53: aload_2
        //   54: invokevirtual 49	android/os/Parcel:recycle	()V
        //   57: return
        //   58: aload_2
        //   59: iconst_0
        //   60: invokevirtual 37	android/os/Parcel:writeInt	(I)V
        //   63: goto -34 -> 29
        //   66: astore_1
        //   67: aload_3
        //   68: invokevirtual 49	android/os/Parcel:recycle	()V
        //   71: aload_2
        //   72: invokevirtual 49	android/os/Parcel:recycle	()V
        //   75: aload_1
        //   76: athrow
        // Local variable table:
        //   start	length	slot	name	signature
        //   0	77	0	this	a
        //   0	77	1	paramD	d
        //   3	69	2	localParcel1	Parcel
        //   7	61	3	localParcel2	Parcel
        // Exception table:
        //   from	to	target	type
        //   8	14	66	finally
        //   18	29	66	finally
        //   29	49	66	finally
        //   58	63	66	finally
      }
      
      /* Error */
      public void i(d paramD)
        throws RemoteException
      {
        // Byte code:
        //   0: invokestatic 28	android/os/Parcel:obtain	()Landroid/os/Parcel;
        //   3: astore_2
        //   4: invokestatic 28	android/os/Parcel:obtain	()Landroid/os/Parcel;
        //   7: astore_3
        //   8: aload_2
        //   9: ldc 30
        //   11: invokevirtual 34	android/os/Parcel:writeInterfaceToken	(Ljava/lang/String;)V
        //   14: aload_1
        //   15: ifnull +43 -> 58
        //   18: aload_2
        //   19: iconst_1
        //   20: invokevirtual 37	android/os/Parcel:writeInt	(I)V
        //   23: aload_1
        //   24: aload_2
        //   25: iconst_0
        //   26: invokevirtual 66	com/google/android/gms/common/data/d:writeToParcel	(Landroid/os/Parcel;I)V
        //   29: aload_0
        //   30: getfield 17	com/google/android/gms/internal/ay$a$a:a	Landroid/os/IBinder;
        //   33: sipush 5011
        //   36: aload_2
        //   37: aload_3
        //   38: iconst_0
        //   39: invokeinterface 43 5 0
        //   44: pop
        //   45: aload_3
        //   46: invokevirtual 46	android/os/Parcel:readException	()V
        //   49: aload_3
        //   50: invokevirtual 49	android/os/Parcel:recycle	()V
        //   53: aload_2
        //   54: invokevirtual 49	android/os/Parcel:recycle	()V
        //   57: return
        //   58: aload_2
        //   59: iconst_0
        //   60: invokevirtual 37	android/os/Parcel:writeInt	(I)V
        //   63: goto -34 -> 29
        //   66: astore_1
        //   67: aload_3
        //   68: invokevirtual 49	android/os/Parcel:recycle	()V
        //   71: aload_2
        //   72: invokevirtual 49	android/os/Parcel:recycle	()V
        //   75: aload_1
        //   76: athrow
        // Local variable table:
        //   start	length	slot	name	signature
        //   0	77	0	this	a
        //   0	77	1	paramD	d
        //   3	69	2	localParcel1	Parcel
        //   7	61	3	localParcel2	Parcel
        // Exception table:
        //   from	to	target	type
        //   8	14	66	finally
        //   18	29	66	finally
        //   29	49	66	finally
        //   58	63	66	finally
      }
      
      /* Error */
      public void j(d paramD)
        throws RemoteException
      {
        // Byte code:
        //   0: invokestatic 28	android/os/Parcel:obtain	()Landroid/os/Parcel;
        //   3: astore_2
        //   4: invokestatic 28	android/os/Parcel:obtain	()Landroid/os/Parcel;
        //   7: astore_3
        //   8: aload_2
        //   9: ldc 30
        //   11: invokevirtual 34	android/os/Parcel:writeInterfaceToken	(Ljava/lang/String;)V
        //   14: aload_1
        //   15: ifnull +43 -> 58
        //   18: aload_2
        //   19: iconst_1
        //   20: invokevirtual 37	android/os/Parcel:writeInt	(I)V
        //   23: aload_1
        //   24: aload_2
        //   25: iconst_0
        //   26: invokevirtual 66	com/google/android/gms/common/data/d:writeToParcel	(Landroid/os/Parcel;I)V
        //   29: aload_0
        //   30: getfield 17	com/google/android/gms/internal/ay$a$a:a	Landroid/os/IBinder;
        //   33: sipush 5017
        //   36: aload_2
        //   37: aload_3
        //   38: iconst_0
        //   39: invokeinterface 43 5 0
        //   44: pop
        //   45: aload_3
        //   46: invokevirtual 46	android/os/Parcel:readException	()V
        //   49: aload_3
        //   50: invokevirtual 49	android/os/Parcel:recycle	()V
        //   53: aload_2
        //   54: invokevirtual 49	android/os/Parcel:recycle	()V
        //   57: return
        //   58: aload_2
        //   59: iconst_0
        //   60: invokevirtual 37	android/os/Parcel:writeInt	(I)V
        //   63: goto -34 -> 29
        //   66: astore_1
        //   67: aload_3
        //   68: invokevirtual 49	android/os/Parcel:recycle	()V
        //   71: aload_2
        //   72: invokevirtual 49	android/os/Parcel:recycle	()V
        //   75: aload_1
        //   76: athrow
        // Local variable table:
        //   start	length	slot	name	signature
        //   0	77	0	this	a
        //   0	77	1	paramD	d
        //   3	69	2	localParcel1	Parcel
        //   7	61	3	localParcel2	Parcel
        // Exception table:
        //   from	to	target	type
        //   8	14	66	finally
        //   18	29	66	finally
        //   29	49	66	finally
        //   58	63	66	finally
      }
      
      /* Error */
      public void k(d paramD)
        throws RemoteException
      {
        // Byte code:
        //   0: invokestatic 28	android/os/Parcel:obtain	()Landroid/os/Parcel;
        //   3: astore_2
        //   4: invokestatic 28	android/os/Parcel:obtain	()Landroid/os/Parcel;
        //   7: astore_3
        //   8: aload_2
        //   9: ldc 30
        //   11: invokevirtual 34	android/os/Parcel:writeInterfaceToken	(Ljava/lang/String;)V
        //   14: aload_1
        //   15: ifnull +43 -> 58
        //   18: aload_2
        //   19: iconst_1
        //   20: invokevirtual 37	android/os/Parcel:writeInt	(I)V
        //   23: aload_1
        //   24: aload_2
        //   25: iconst_0
        //   26: invokevirtual 66	com/google/android/gms/common/data/d:writeToParcel	(Landroid/os/Parcel;I)V
        //   29: aload_0
        //   30: getfield 17	com/google/android/gms/internal/ay$a$a:a	Landroid/os/IBinder;
        //   33: sipush 5037
        //   36: aload_2
        //   37: aload_3
        //   38: iconst_0
        //   39: invokeinterface 43 5 0
        //   44: pop
        //   45: aload_3
        //   46: invokevirtual 46	android/os/Parcel:readException	()V
        //   49: aload_3
        //   50: invokevirtual 49	android/os/Parcel:recycle	()V
        //   53: aload_2
        //   54: invokevirtual 49	android/os/Parcel:recycle	()V
        //   57: return
        //   58: aload_2
        //   59: iconst_0
        //   60: invokevirtual 37	android/os/Parcel:writeInt	(I)V
        //   63: goto -34 -> 29
        //   66: astore_1
        //   67: aload_3
        //   68: invokevirtual 49	android/os/Parcel:recycle	()V
        //   71: aload_2
        //   72: invokevirtual 49	android/os/Parcel:recycle	()V
        //   75: aload_1
        //   76: athrow
        // Local variable table:
        //   start	length	slot	name	signature
        //   0	77	0	this	a
        //   0	77	1	paramD	d
        //   3	69	2	localParcel1	Parcel
        //   7	61	3	localParcel2	Parcel
        // Exception table:
        //   from	to	target	type
        //   8	14	66	finally
        //   18	29	66	finally
        //   29	49	66	finally
        //   58	63	66	finally
      }
      
      /* Error */
      public void l(d paramD)
        throws RemoteException
      {
        // Byte code:
        //   0: invokestatic 28	android/os/Parcel:obtain	()Landroid/os/Parcel;
        //   3: astore_2
        //   4: invokestatic 28	android/os/Parcel:obtain	()Landroid/os/Parcel;
        //   7: astore_3
        //   8: aload_2
        //   9: ldc 30
        //   11: invokevirtual 34	android/os/Parcel:writeInterfaceToken	(Ljava/lang/String;)V
        //   14: aload_1
        //   15: ifnull +43 -> 58
        //   18: aload_2
        //   19: iconst_1
        //   20: invokevirtual 37	android/os/Parcel:writeInt	(I)V
        //   23: aload_1
        //   24: aload_2
        //   25: iconst_0
        //   26: invokevirtual 66	com/google/android/gms/common/data/d:writeToParcel	(Landroid/os/Parcel;I)V
        //   29: aload_0
        //   30: getfield 17	com/google/android/gms/internal/ay$a$a:a	Landroid/os/IBinder;
        //   33: sipush 5012
        //   36: aload_2
        //   37: aload_3
        //   38: iconst_0
        //   39: invokeinterface 43 5 0
        //   44: pop
        //   45: aload_3
        //   46: invokevirtual 46	android/os/Parcel:readException	()V
        //   49: aload_3
        //   50: invokevirtual 49	android/os/Parcel:recycle	()V
        //   53: aload_2
        //   54: invokevirtual 49	android/os/Parcel:recycle	()V
        //   57: return
        //   58: aload_2
        //   59: iconst_0
        //   60: invokevirtual 37	android/os/Parcel:writeInt	(I)V
        //   63: goto -34 -> 29
        //   66: astore_1
        //   67: aload_3
        //   68: invokevirtual 49	android/os/Parcel:recycle	()V
        //   71: aload_2
        //   72: invokevirtual 49	android/os/Parcel:recycle	()V
        //   75: aload_1
        //   76: athrow
        // Local variable table:
        //   start	length	slot	name	signature
        //   0	77	0	this	a
        //   0	77	1	paramD	d
        //   3	69	2	localParcel1	Parcel
        //   7	61	3	localParcel2	Parcel
        // Exception table:
        //   from	to	target	type
        //   8	14	66	finally
        //   18	29	66	finally
        //   29	49	66	finally
        //   58	63	66	finally
      }
      
      /* Error */
      public void m(d paramD)
        throws RemoteException
      {
        // Byte code:
        //   0: invokestatic 28	android/os/Parcel:obtain	()Landroid/os/Parcel;
        //   3: astore_2
        //   4: invokestatic 28	android/os/Parcel:obtain	()Landroid/os/Parcel;
        //   7: astore_3
        //   8: aload_2
        //   9: ldc 30
        //   11: invokevirtual 34	android/os/Parcel:writeInterfaceToken	(Ljava/lang/String;)V
        //   14: aload_1
        //   15: ifnull +43 -> 58
        //   18: aload_2
        //   19: iconst_1
        //   20: invokevirtual 37	android/os/Parcel:writeInt	(I)V
        //   23: aload_1
        //   24: aload_2
        //   25: iconst_0
        //   26: invokevirtual 66	com/google/android/gms/common/data/d:writeToParcel	(Landroid/os/Parcel;I)V
        //   29: aload_0
        //   30: getfield 17	com/google/android/gms/internal/ay$a$a:a	Landroid/os/IBinder;
        //   33: sipush 5014
        //   36: aload_2
        //   37: aload_3
        //   38: iconst_0
        //   39: invokeinterface 43 5 0
        //   44: pop
        //   45: aload_3
        //   46: invokevirtual 46	android/os/Parcel:readException	()V
        //   49: aload_3
        //   50: invokevirtual 49	android/os/Parcel:recycle	()V
        //   53: aload_2
        //   54: invokevirtual 49	android/os/Parcel:recycle	()V
        //   57: return
        //   58: aload_2
        //   59: iconst_0
        //   60: invokevirtual 37	android/os/Parcel:writeInt	(I)V
        //   63: goto -34 -> 29
        //   66: astore_1
        //   67: aload_3
        //   68: invokevirtual 49	android/os/Parcel:recycle	()V
        //   71: aload_2
        //   72: invokevirtual 49	android/os/Parcel:recycle	()V
        //   75: aload_1
        //   76: athrow
        // Local variable table:
        //   start	length	slot	name	signature
        //   0	77	0	this	a
        //   0	77	1	paramD	d
        //   3	69	2	localParcel1	Parcel
        //   7	61	3	localParcel2	Parcel
        // Exception table:
        //   from	to	target	type
        //   8	14	66	finally
        //   18	29	66	finally
        //   29	49	66	finally
        //   58	63	66	finally
      }
      
      /* Error */
      public void n(d paramD)
        throws RemoteException
      {
        // Byte code:
        //   0: invokestatic 28	android/os/Parcel:obtain	()Landroid/os/Parcel;
        //   3: astore_2
        //   4: invokestatic 28	android/os/Parcel:obtain	()Landroid/os/Parcel;
        //   7: astore_3
        //   8: aload_2
        //   9: ldc 30
        //   11: invokevirtual 34	android/os/Parcel:writeInterfaceToken	(Ljava/lang/String;)V
        //   14: aload_1
        //   15: ifnull +43 -> 58
        //   18: aload_2
        //   19: iconst_1
        //   20: invokevirtual 37	android/os/Parcel:writeInt	(I)V
        //   23: aload_1
        //   24: aload_2
        //   25: iconst_0
        //   26: invokevirtual 66	com/google/android/gms/common/data/d:writeToParcel	(Landroid/os/Parcel;I)V
        //   29: aload_0
        //   30: getfield 17	com/google/android/gms/internal/ay$a$a:a	Landroid/os/IBinder;
        //   33: sipush 5018
        //   36: aload_2
        //   37: aload_3
        //   38: iconst_0
        //   39: invokeinterface 43 5 0
        //   44: pop
        //   45: aload_3
        //   46: invokevirtual 46	android/os/Parcel:readException	()V
        //   49: aload_3
        //   50: invokevirtual 49	android/os/Parcel:recycle	()V
        //   53: aload_2
        //   54: invokevirtual 49	android/os/Parcel:recycle	()V
        //   57: return
        //   58: aload_2
        //   59: iconst_0
        //   60: invokevirtual 37	android/os/Parcel:writeInt	(I)V
        //   63: goto -34 -> 29
        //   66: astore_1
        //   67: aload_3
        //   68: invokevirtual 49	android/os/Parcel:recycle	()V
        //   71: aload_2
        //   72: invokevirtual 49	android/os/Parcel:recycle	()V
        //   75: aload_1
        //   76: athrow
        // Local variable table:
        //   start	length	slot	name	signature
        //   0	77	0	this	a
        //   0	77	1	paramD	d
        //   3	69	2	localParcel1	Parcel
        //   7	61	3	localParcel2	Parcel
        // Exception table:
        //   from	to	target	type
        //   8	14	66	finally
        //   18	29	66	finally
        //   29	49	66	finally
        //   58	63	66	finally
      }
      
      /* Error */
      public void o(d paramD)
        throws RemoteException
      {
        // Byte code:
        //   0: invokestatic 28	android/os/Parcel:obtain	()Landroid/os/Parcel;
        //   3: astore_2
        //   4: invokestatic 28	android/os/Parcel:obtain	()Landroid/os/Parcel;
        //   7: astore_3
        //   8: aload_2
        //   9: ldc 30
        //   11: invokevirtual 34	android/os/Parcel:writeInterfaceToken	(Ljava/lang/String;)V
        //   14: aload_1
        //   15: ifnull +43 -> 58
        //   18: aload_2
        //   19: iconst_1
        //   20: invokevirtual 37	android/os/Parcel:writeInt	(I)V
        //   23: aload_1
        //   24: aload_2
        //   25: iconst_0
        //   26: invokevirtual 66	com/google/android/gms/common/data/d:writeToParcel	(Landroid/os/Parcel;I)V
        //   29: aload_0
        //   30: getfield 17	com/google/android/gms/internal/ay$a$a:a	Landroid/os/IBinder;
        //   33: sipush 5019
        //   36: aload_2
        //   37: aload_3
        //   38: iconst_0
        //   39: invokeinterface 43 5 0
        //   44: pop
        //   45: aload_3
        //   46: invokevirtual 46	android/os/Parcel:readException	()V
        //   49: aload_3
        //   50: invokevirtual 49	android/os/Parcel:recycle	()V
        //   53: aload_2
        //   54: invokevirtual 49	android/os/Parcel:recycle	()V
        //   57: return
        //   58: aload_2
        //   59: iconst_0
        //   60: invokevirtual 37	android/os/Parcel:writeInt	(I)V
        //   63: goto -34 -> 29
        //   66: astore_1
        //   67: aload_3
        //   68: invokevirtual 49	android/os/Parcel:recycle	()V
        //   71: aload_2
        //   72: invokevirtual 49	android/os/Parcel:recycle	()V
        //   75: aload_1
        //   76: athrow
        // Local variable table:
        //   start	length	slot	name	signature
        //   0	77	0	this	a
        //   0	77	1	paramD	d
        //   3	69	2	localParcel1	Parcel
        //   7	61	3	localParcel2	Parcel
        // Exception table:
        //   from	to	target	type
        //   8	14	66	finally
        //   18	29	66	finally
        //   29	49	66	finally
        //   58	63	66	finally
      }
      
      public void onAchievementUpdated(int paramInt, String paramString)
        throws RemoteException
      {
        Parcel localParcel1 = Parcel.obtain();
        Parcel localParcel2 = Parcel.obtain();
        try
        {
          localParcel1.writeInterfaceToken("com.google.android.gms.games.internal.IGamesCallbacks");
          localParcel1.writeInt(paramInt);
          localParcel1.writeString(paramString);
          this.a.transact(5003, localParcel1, localParcel2, 0);
          localParcel2.readException();
          return;
        }
        finally
        {
          localParcel2.recycle();
          localParcel1.recycle();
        }
      }
      
      public void onLeftRoom(int paramInt, String paramString)
        throws RemoteException
      {
        Parcel localParcel1 = Parcel.obtain();
        Parcel localParcel2 = Parcel.obtain();
        try
        {
          localParcel1.writeInterfaceToken("com.google.android.gms.games.internal.IGamesCallbacks");
          localParcel1.writeInt(paramInt);
          localParcel1.writeString(paramString);
          this.a.transact(5020, localParcel1, localParcel2, 0);
          localParcel2.readException();
          return;
        }
        finally
        {
          localParcel2.recycle();
          localParcel1.recycle();
        }
      }
      
      public void onP2PConnected(String paramString)
        throws RemoteException
      {
        Parcel localParcel1 = Parcel.obtain();
        Parcel localParcel2 = Parcel.obtain();
        try
        {
          localParcel1.writeInterfaceToken("com.google.android.gms.games.internal.IGamesCallbacks");
          localParcel1.writeString(paramString);
          this.a.transact(6001, localParcel1, localParcel2, 0);
          localParcel2.readException();
          return;
        }
        finally
        {
          localParcel2.recycle();
          localParcel1.recycle();
        }
      }
      
      public void onP2PDisconnected(String paramString)
        throws RemoteException
      {
        Parcel localParcel1 = Parcel.obtain();
        Parcel localParcel2 = Parcel.obtain();
        try
        {
          localParcel1.writeInterfaceToken("com.google.android.gms.games.internal.IGamesCallbacks");
          localParcel1.writeString(paramString);
          this.a.transact(6002, localParcel1, localParcel2, 0);
          localParcel2.readException();
          return;
        }
        finally
        {
          localParcel2.recycle();
          localParcel1.recycle();
        }
      }
      
      /* Error */
      public void onRealTimeMessageReceived(RealTimeMessage paramRealTimeMessage)
        throws RemoteException
      {
        // Byte code:
        //   0: invokestatic 28	android/os/Parcel:obtain	()Landroid/os/Parcel;
        //   3: astore_2
        //   4: invokestatic 28	android/os/Parcel:obtain	()Landroid/os/Parcel;
        //   7: astore_3
        //   8: aload_2
        //   9: ldc 30
        //   11: invokevirtual 34	android/os/Parcel:writeInterfaceToken	(Ljava/lang/String;)V
        //   14: aload_1
        //   15: ifnull +43 -> 58
        //   18: aload_2
        //   19: iconst_1
        //   20: invokevirtual 37	android/os/Parcel:writeInt	(I)V
        //   23: aload_1
        //   24: aload_2
        //   25: iconst_0
        //   26: invokevirtual 97	com/google/android/gms/games/multiplayer/realtime/RealTimeMessage:writeToParcel	(Landroid/os/Parcel;I)V
        //   29: aload_0
        //   30: getfield 17	com/google/android/gms/internal/ay$a$a:a	Landroid/os/IBinder;
        //   33: sipush 5032
        //   36: aload_2
        //   37: aload_3
        //   38: iconst_0
        //   39: invokeinterface 43 5 0
        //   44: pop
        //   45: aload_3
        //   46: invokevirtual 46	android/os/Parcel:readException	()V
        //   49: aload_3
        //   50: invokevirtual 49	android/os/Parcel:recycle	()V
        //   53: aload_2
        //   54: invokevirtual 49	android/os/Parcel:recycle	()V
        //   57: return
        //   58: aload_2
        //   59: iconst_0
        //   60: invokevirtual 37	android/os/Parcel:writeInt	(I)V
        //   63: goto -34 -> 29
        //   66: astore_1
        //   67: aload_3
        //   68: invokevirtual 49	android/os/Parcel:recycle	()V
        //   71: aload_2
        //   72: invokevirtual 49	android/os/Parcel:recycle	()V
        //   75: aload_1
        //   76: athrow
        // Local variable table:
        //   start	length	slot	name	signature
        //   0	77	0	this	a
        //   0	77	1	paramRealTimeMessage	RealTimeMessage
        //   3	69	2	localParcel1	Parcel
        //   7	61	3	localParcel2	Parcel
        // Exception table:
        //   from	to	target	type
        //   8	14	66	finally
        //   18	29	66	finally
        //   29	49	66	finally
        //   58	63	66	finally
      }
      
      public void onSignOutComplete()
        throws RemoteException
      {
        Parcel localParcel1 = Parcel.obtain();
        Parcel localParcel2 = Parcel.obtain();
        try
        {
          localParcel1.writeInterfaceToken("com.google.android.gms.games.internal.IGamesCallbacks");
          this.a.transact(5016, localParcel1, localParcel2, 0);
          localParcel2.readException();
          return;
        }
        finally
        {
          localParcel2.recycle();
          localParcel1.recycle();
        }
      }
      
      /* Error */
      public void p(d paramD)
        throws RemoteException
      {
        // Byte code:
        //   0: invokestatic 28	android/os/Parcel:obtain	()Landroid/os/Parcel;
        //   3: astore_2
        //   4: invokestatic 28	android/os/Parcel:obtain	()Landroid/os/Parcel;
        //   7: astore_3
        //   8: aload_2
        //   9: ldc 30
        //   11: invokevirtual 34	android/os/Parcel:writeInterfaceToken	(Ljava/lang/String;)V
        //   14: aload_1
        //   15: ifnull +43 -> 58
        //   18: aload_2
        //   19: iconst_1
        //   20: invokevirtual 37	android/os/Parcel:writeInt	(I)V
        //   23: aload_1
        //   24: aload_2
        //   25: iconst_0
        //   26: invokevirtual 66	com/google/android/gms/common/data/d:writeToParcel	(Landroid/os/Parcel;I)V
        //   29: aload_0
        //   30: getfield 17	com/google/android/gms/internal/ay$a$a:a	Landroid/os/IBinder;
        //   33: sipush 5021
        //   36: aload_2
        //   37: aload_3
        //   38: iconst_0
        //   39: invokeinterface 43 5 0
        //   44: pop
        //   45: aload_3
        //   46: invokevirtual 46	android/os/Parcel:readException	()V
        //   49: aload_3
        //   50: invokevirtual 49	android/os/Parcel:recycle	()V
        //   53: aload_2
        //   54: invokevirtual 49	android/os/Parcel:recycle	()V
        //   57: return
        //   58: aload_2
        //   59: iconst_0
        //   60: invokevirtual 37	android/os/Parcel:writeInt	(I)V
        //   63: goto -34 -> 29
        //   66: astore_1
        //   67: aload_3
        //   68: invokevirtual 49	android/os/Parcel:recycle	()V
        //   71: aload_2
        //   72: invokevirtual 49	android/os/Parcel:recycle	()V
        //   75: aload_1
        //   76: athrow
        // Local variable table:
        //   start	length	slot	name	signature
        //   0	77	0	this	a
        //   0	77	1	paramD	d
        //   3	69	2	localParcel1	Parcel
        //   7	61	3	localParcel2	Parcel
        // Exception table:
        //   from	to	target	type
        //   8	14	66	finally
        //   18	29	66	finally
        //   29	49	66	finally
        //   58	63	66	finally
      }
      
      /* Error */
      public void q(d paramD)
        throws RemoteException
      {
        // Byte code:
        //   0: invokestatic 28	android/os/Parcel:obtain	()Landroid/os/Parcel;
        //   3: astore_2
        //   4: invokestatic 28	android/os/Parcel:obtain	()Landroid/os/Parcel;
        //   7: astore_3
        //   8: aload_2
        //   9: ldc 30
        //   11: invokevirtual 34	android/os/Parcel:writeInterfaceToken	(Ljava/lang/String;)V
        //   14: aload_1
        //   15: ifnull +43 -> 58
        //   18: aload_2
        //   19: iconst_1
        //   20: invokevirtual 37	android/os/Parcel:writeInt	(I)V
        //   23: aload_1
        //   24: aload_2
        //   25: iconst_0
        //   26: invokevirtual 66	com/google/android/gms/common/data/d:writeToParcel	(Landroid/os/Parcel;I)V
        //   29: aload_0
        //   30: getfield 17	com/google/android/gms/internal/ay$a$a:a	Landroid/os/IBinder;
        //   33: sipush 5022
        //   36: aload_2
        //   37: aload_3
        //   38: iconst_0
        //   39: invokeinterface 43 5 0
        //   44: pop
        //   45: aload_3
        //   46: invokevirtual 46	android/os/Parcel:readException	()V
        //   49: aload_3
        //   50: invokevirtual 49	android/os/Parcel:recycle	()V
        //   53: aload_2
        //   54: invokevirtual 49	android/os/Parcel:recycle	()V
        //   57: return
        //   58: aload_2
        //   59: iconst_0
        //   60: invokevirtual 37	android/os/Parcel:writeInt	(I)V
        //   63: goto -34 -> 29
        //   66: astore_1
        //   67: aload_3
        //   68: invokevirtual 49	android/os/Parcel:recycle	()V
        //   71: aload_2
        //   72: invokevirtual 49	android/os/Parcel:recycle	()V
        //   75: aload_1
        //   76: athrow
        // Local variable table:
        //   start	length	slot	name	signature
        //   0	77	0	this	a
        //   0	77	1	paramD	d
        //   3	69	2	localParcel1	Parcel
        //   7	61	3	localParcel2	Parcel
        // Exception table:
        //   from	to	target	type
        //   8	14	66	finally
        //   18	29	66	finally
        //   29	49	66	finally
        //   58	63	66	finally
      }
      
      /* Error */
      public void r(d paramD)
        throws RemoteException
      {
        // Byte code:
        //   0: invokestatic 28	android/os/Parcel:obtain	()Landroid/os/Parcel;
        //   3: astore_2
        //   4: invokestatic 28	android/os/Parcel:obtain	()Landroid/os/Parcel;
        //   7: astore_3
        //   8: aload_2
        //   9: ldc 30
        //   11: invokevirtual 34	android/os/Parcel:writeInterfaceToken	(Ljava/lang/String;)V
        //   14: aload_1
        //   15: ifnull +43 -> 58
        //   18: aload_2
        //   19: iconst_1
        //   20: invokevirtual 37	android/os/Parcel:writeInt	(I)V
        //   23: aload_1
        //   24: aload_2
        //   25: iconst_0
        //   26: invokevirtual 66	com/google/android/gms/common/data/d:writeToParcel	(Landroid/os/Parcel;I)V
        //   29: aload_0
        //   30: getfield 17	com/google/android/gms/internal/ay$a$a:a	Landroid/os/IBinder;
        //   33: sipush 5023
        //   36: aload_2
        //   37: aload_3
        //   38: iconst_0
        //   39: invokeinterface 43 5 0
        //   44: pop
        //   45: aload_3
        //   46: invokevirtual 46	android/os/Parcel:readException	()V
        //   49: aload_3
        //   50: invokevirtual 49	android/os/Parcel:recycle	()V
        //   53: aload_2
        //   54: invokevirtual 49	android/os/Parcel:recycle	()V
        //   57: return
        //   58: aload_2
        //   59: iconst_0
        //   60: invokevirtual 37	android/os/Parcel:writeInt	(I)V
        //   63: goto -34 -> 29
        //   66: astore_1
        //   67: aload_3
        //   68: invokevirtual 49	android/os/Parcel:recycle	()V
        //   71: aload_2
        //   72: invokevirtual 49	android/os/Parcel:recycle	()V
        //   75: aload_1
        //   76: athrow
        // Local variable table:
        //   start	length	slot	name	signature
        //   0	77	0	this	a
        //   0	77	1	paramD	d
        //   3	69	2	localParcel1	Parcel
        //   7	61	3	localParcel2	Parcel
        // Exception table:
        //   from	to	target	type
        //   8	14	66	finally
        //   18	29	66	finally
        //   29	49	66	finally
        //   58	63	66	finally
      }
      
      /* Error */
      public void s(d paramD)
        throws RemoteException
      {
        // Byte code:
        //   0: invokestatic 28	android/os/Parcel:obtain	()Landroid/os/Parcel;
        //   3: astore_2
        //   4: invokestatic 28	android/os/Parcel:obtain	()Landroid/os/Parcel;
        //   7: astore_3
        //   8: aload_2
        //   9: ldc 30
        //   11: invokevirtual 34	android/os/Parcel:writeInterfaceToken	(Ljava/lang/String;)V
        //   14: aload_1
        //   15: ifnull +43 -> 58
        //   18: aload_2
        //   19: iconst_1
        //   20: invokevirtual 37	android/os/Parcel:writeInt	(I)V
        //   23: aload_1
        //   24: aload_2
        //   25: iconst_0
        //   26: invokevirtual 66	com/google/android/gms/common/data/d:writeToParcel	(Landroid/os/Parcel;I)V
        //   29: aload_0
        //   30: getfield 17	com/google/android/gms/internal/ay$a$a:a	Landroid/os/IBinder;
        //   33: sipush 5024
        //   36: aload_2
        //   37: aload_3
        //   38: iconst_0
        //   39: invokeinterface 43 5 0
        //   44: pop
        //   45: aload_3
        //   46: invokevirtual 46	android/os/Parcel:readException	()V
        //   49: aload_3
        //   50: invokevirtual 49	android/os/Parcel:recycle	()V
        //   53: aload_2
        //   54: invokevirtual 49	android/os/Parcel:recycle	()V
        //   57: return
        //   58: aload_2
        //   59: iconst_0
        //   60: invokevirtual 37	android/os/Parcel:writeInt	(I)V
        //   63: goto -34 -> 29
        //   66: astore_1
        //   67: aload_3
        //   68: invokevirtual 49	android/os/Parcel:recycle	()V
        //   71: aload_2
        //   72: invokevirtual 49	android/os/Parcel:recycle	()V
        //   75: aload_1
        //   76: athrow
        // Local variable table:
        //   start	length	slot	name	signature
        //   0	77	0	this	a
        //   0	77	1	paramD	d
        //   3	69	2	localParcel1	Parcel
        //   7	61	3	localParcel2	Parcel
        // Exception table:
        //   from	to	target	type
        //   8	14	66	finally
        //   18	29	66	finally
        //   29	49	66	finally
        //   58	63	66	finally
      }
      
      /* Error */
      public void t(d paramD)
        throws RemoteException
      {
        // Byte code:
        //   0: invokestatic 28	android/os/Parcel:obtain	()Landroid/os/Parcel;
        //   3: astore_2
        //   4: invokestatic 28	android/os/Parcel:obtain	()Landroid/os/Parcel;
        //   7: astore_3
        //   8: aload_2
        //   9: ldc 30
        //   11: invokevirtual 34	android/os/Parcel:writeInterfaceToken	(Ljava/lang/String;)V
        //   14: aload_1
        //   15: ifnull +43 -> 58
        //   18: aload_2
        //   19: iconst_1
        //   20: invokevirtual 37	android/os/Parcel:writeInt	(I)V
        //   23: aload_1
        //   24: aload_2
        //   25: iconst_0
        //   26: invokevirtual 66	com/google/android/gms/common/data/d:writeToParcel	(Landroid/os/Parcel;I)V
        //   29: aload_0
        //   30: getfield 17	com/google/android/gms/internal/ay$a$a:a	Landroid/os/IBinder;
        //   33: sipush 5025
        //   36: aload_2
        //   37: aload_3
        //   38: iconst_0
        //   39: invokeinterface 43 5 0
        //   44: pop
        //   45: aload_3
        //   46: invokevirtual 46	android/os/Parcel:readException	()V
        //   49: aload_3
        //   50: invokevirtual 49	android/os/Parcel:recycle	()V
        //   53: aload_2
        //   54: invokevirtual 49	android/os/Parcel:recycle	()V
        //   57: return
        //   58: aload_2
        //   59: iconst_0
        //   60: invokevirtual 37	android/os/Parcel:writeInt	(I)V
        //   63: goto -34 -> 29
        //   66: astore_1
        //   67: aload_3
        //   68: invokevirtual 49	android/os/Parcel:recycle	()V
        //   71: aload_2
        //   72: invokevirtual 49	android/os/Parcel:recycle	()V
        //   75: aload_1
        //   76: athrow
        // Local variable table:
        //   start	length	slot	name	signature
        //   0	77	0	this	a
        //   0	77	1	paramD	d
        //   3	69	2	localParcel1	Parcel
        //   7	61	3	localParcel2	Parcel
        // Exception table:
        //   from	to	target	type
        //   8	14	66	finally
        //   18	29	66	finally
        //   29	49	66	finally
        //   58	63	66	finally
      }
      
      /* Error */
      public void u(d paramD)
        throws RemoteException
      {
        // Byte code:
        //   0: invokestatic 28	android/os/Parcel:obtain	()Landroid/os/Parcel;
        //   3: astore_2
        //   4: invokestatic 28	android/os/Parcel:obtain	()Landroid/os/Parcel;
        //   7: astore_3
        //   8: aload_2
        //   9: ldc 30
        //   11: invokevirtual 34	android/os/Parcel:writeInterfaceToken	(Ljava/lang/String;)V
        //   14: aload_1
        //   15: ifnull +43 -> 58
        //   18: aload_2
        //   19: iconst_1
        //   20: invokevirtual 37	android/os/Parcel:writeInt	(I)V
        //   23: aload_1
        //   24: aload_2
        //   25: iconst_0
        //   26: invokevirtual 66	com/google/android/gms/common/data/d:writeToParcel	(Landroid/os/Parcel;I)V
        //   29: aload_0
        //   30: getfield 17	com/google/android/gms/internal/ay$a$a:a	Landroid/os/IBinder;
        //   33: sipush 5038
        //   36: aload_2
        //   37: aload_3
        //   38: iconst_0
        //   39: invokeinterface 43 5 0
        //   44: pop
        //   45: aload_3
        //   46: invokevirtual 46	android/os/Parcel:readException	()V
        //   49: aload_3
        //   50: invokevirtual 49	android/os/Parcel:recycle	()V
        //   53: aload_2
        //   54: invokevirtual 49	android/os/Parcel:recycle	()V
        //   57: return
        //   58: aload_2
        //   59: iconst_0
        //   60: invokevirtual 37	android/os/Parcel:writeInt	(I)V
        //   63: goto -34 -> 29
        //   66: astore_1
        //   67: aload_3
        //   68: invokevirtual 49	android/os/Parcel:recycle	()V
        //   71: aload_2
        //   72: invokevirtual 49	android/os/Parcel:recycle	()V
        //   75: aload_1
        //   76: athrow
        // Local variable table:
        //   start	length	slot	name	signature
        //   0	77	0	this	a
        //   0	77	1	paramD	d
        //   3	69	2	localParcel1	Parcel
        //   7	61	3	localParcel2	Parcel
        // Exception table:
        //   from	to	target	type
        //   8	14	66	finally
        //   18	29	66	finally
        //   29	49	66	finally
        //   58	63	66	finally
      }
      
      /* Error */
      public void v(d paramD)
        throws RemoteException
      {
        // Byte code:
        //   0: invokestatic 28	android/os/Parcel:obtain	()Landroid/os/Parcel;
        //   3: astore_2
        //   4: invokestatic 28	android/os/Parcel:obtain	()Landroid/os/Parcel;
        //   7: astore_3
        //   8: aload_2
        //   9: ldc 30
        //   11: invokevirtual 34	android/os/Parcel:writeInterfaceToken	(Ljava/lang/String;)V
        //   14: aload_1
        //   15: ifnull +43 -> 58
        //   18: aload_2
        //   19: iconst_1
        //   20: invokevirtual 37	android/os/Parcel:writeInt	(I)V
        //   23: aload_1
        //   24: aload_2
        //   25: iconst_0
        //   26: invokevirtual 66	com/google/android/gms/common/data/d:writeToParcel	(Landroid/os/Parcel;I)V
        //   29: aload_0
        //   30: getfield 17	com/google/android/gms/internal/ay$a$a:a	Landroid/os/IBinder;
        //   33: sipush 5035
        //   36: aload_2
        //   37: aload_3
        //   38: iconst_0
        //   39: invokeinterface 43 5 0
        //   44: pop
        //   45: aload_3
        //   46: invokevirtual 46	android/os/Parcel:readException	()V
        //   49: aload_3
        //   50: invokevirtual 49	android/os/Parcel:recycle	()V
        //   53: aload_2
        //   54: invokevirtual 49	android/os/Parcel:recycle	()V
        //   57: return
        //   58: aload_2
        //   59: iconst_0
        //   60: invokevirtual 37	android/os/Parcel:writeInt	(I)V
        //   63: goto -34 -> 29
        //   66: astore_1
        //   67: aload_3
        //   68: invokevirtual 49	android/os/Parcel:recycle	()V
        //   71: aload_2
        //   72: invokevirtual 49	android/os/Parcel:recycle	()V
        //   75: aload_1
        //   76: athrow
        // Local variable table:
        //   start	length	slot	name	signature
        //   0	77	0	this	a
        //   0	77	1	paramD	d
        //   3	69	2	localParcel1	Parcel
        //   7	61	3	localParcel2	Parcel
        // Exception table:
        //   from	to	target	type
        //   8	14	66	finally
        //   18	29	66	finally
        //   29	49	66	finally
        //   58	63	66	finally
      }
      
      /* Error */
      public void w(d paramD)
        throws RemoteException
      {
        // Byte code:
        //   0: invokestatic 28	android/os/Parcel:obtain	()Landroid/os/Parcel;
        //   3: astore_2
        //   4: invokestatic 28	android/os/Parcel:obtain	()Landroid/os/Parcel;
        //   7: astore_3
        //   8: aload_2
        //   9: ldc 30
        //   11: invokevirtual 34	android/os/Parcel:writeInterfaceToken	(Ljava/lang/String;)V
        //   14: aload_1
        //   15: ifnull +43 -> 58
        //   18: aload_2
        //   19: iconst_1
        //   20: invokevirtual 37	android/os/Parcel:writeInt	(I)V
        //   23: aload_1
        //   24: aload_2
        //   25: iconst_0
        //   26: invokevirtual 66	com/google/android/gms/common/data/d:writeToParcel	(Landroid/os/Parcel;I)V
        //   29: aload_0
        //   30: getfield 17	com/google/android/gms/internal/ay$a$a:a	Landroid/os/IBinder;
        //   33: sipush 5039
        //   36: aload_2
        //   37: aload_3
        //   38: iconst_0
        //   39: invokeinterface 43 5 0
        //   44: pop
        //   45: aload_3
        //   46: invokevirtual 46	android/os/Parcel:readException	()V
        //   49: aload_3
        //   50: invokevirtual 49	android/os/Parcel:recycle	()V
        //   53: aload_2
        //   54: invokevirtual 49	android/os/Parcel:recycle	()V
        //   57: return
        //   58: aload_2
        //   59: iconst_0
        //   60: invokevirtual 37	android/os/Parcel:writeInt	(I)V
        //   63: goto -34 -> 29
        //   66: astore_1
        //   67: aload_3
        //   68: invokevirtual 49	android/os/Parcel:recycle	()V
        //   71: aload_2
        //   72: invokevirtual 49	android/os/Parcel:recycle	()V
        //   75: aload_1
        //   76: athrow
        // Local variable table:
        //   start	length	slot	name	signature
        //   0	77	0	this	a
        //   0	77	1	paramD	d
        //   3	69	2	localParcel1	Parcel
        //   7	61	3	localParcel2	Parcel
        // Exception table:
        //   from	to	target	type
        //   8	14	66	finally
        //   18	29	66	finally
        //   29	49	66	finally
        //   58	63	66	finally
      }
    }
  }
}
