import io.fabric.sdk.android.services.network.HttpMethod;

final class ayj
  extends xur
{
  public ayj(xuj paramXuj, String paramString1, String paramString2, xxa paramXxa)
  {
    super(paramXuj, paramString1, paramString2, paramXxa, HttpMethod.a);
  }
  
  /* Error */
  public final ayk a(String paramString1, String paramString2, ayi paramAyi)
  {
    // Byte code:
    //   0: new 21	java/util/HashMap
    //   3: dup
    //   4: invokespecial 24	java/util/HashMap:<init>	()V
    //   7: astore 5
    //   9: aload 5
    //   11: ldc 26
    //   13: aload_3
    //   14: getfield 31	ayi:a	Ljava/lang/String;
    //   17: invokeinterface 37 3 0
    //   22: pop
    //   23: aload 5
    //   25: ldc 39
    //   27: aload_3
    //   28: getfield 42	ayi:b	Ljava/lang/String;
    //   31: invokeinterface 37 3 0
    //   36: pop
    //   37: aload 5
    //   39: ldc 44
    //   41: aload_3
    //   42: getfield 47	ayi:c	Ljava/lang/String;
    //   45: invokeinterface 37 3 0
    //   50: pop
    //   51: aload 5
    //   53: ldc 49
    //   55: ldc 51
    //   57: invokeinterface 37 3 0
    //   62: pop
    //   63: aload_0
    //   64: aload 5
    //   66: invokevirtual 54	ayj:a	(Ljava/util/Map;)Lio/fabric/sdk/android/services/network/HttpRequest;
    //   69: astore_3
    //   70: aload_3
    //   71: ldc 56
    //   73: ldc 58
    //   75: invokevirtual 63	io/fabric/sdk/android/services/network/HttpRequest:a	(Ljava/lang/String;Ljava/lang/String;)Lio/fabric/sdk/android/services/network/HttpRequest;
    //   78: astore 6
    //   80: new 65	java/lang/StringBuilder
    //   83: dup
    //   84: ldc 67
    //   86: invokespecial 70	java/lang/StringBuilder:<init>	(Ljava/lang/String;)V
    //   89: astore 7
    //   91: aload 7
    //   93: aload_0
    //   94: getfield 73	ayj:b	Lxuj;
    //   97: invokevirtual 78	xuj:a	()Ljava/lang/String;
    //   100: invokevirtual 82	java/lang/StringBuilder:append	(Ljava/lang/String;)Ljava/lang/StringBuilder;
    //   103: pop
    //   104: aload 6
    //   106: ldc 84
    //   108: aload 7
    //   110: invokevirtual 87	java/lang/StringBuilder:toString	()Ljava/lang/String;
    //   113: invokevirtual 63	io/fabric/sdk/android/services/network/HttpRequest:a	(Ljava/lang/String;Ljava/lang/String;)Lio/fabric/sdk/android/services/network/HttpRequest;
    //   116: ldc 89
    //   118: ldc 91
    //   120: invokevirtual 63	io/fabric/sdk/android/services/network/HttpRequest:a	(Ljava/lang/String;Ljava/lang/String;)Lio/fabric/sdk/android/services/network/HttpRequest;
    //   123: ldc 93
    //   125: ldc 95
    //   127: invokevirtual 63	io/fabric/sdk/android/services/network/HttpRequest:a	(Ljava/lang/String;Ljava/lang/String;)Lio/fabric/sdk/android/services/network/HttpRequest;
    //   130: ldc 97
    //   132: aload_0
    //   133: getfield 73	ayj:b	Lxuj;
    //   136: invokevirtual 78	xuj:a	()Ljava/lang/String;
    //   139: invokevirtual 63	io/fabric/sdk/android/services/network/HttpRequest:a	(Ljava/lang/String;Ljava/lang/String;)Lio/fabric/sdk/android/services/network/HttpRequest;
    //   142: ldc 99
    //   144: aload_1
    //   145: invokevirtual 63	io/fabric/sdk/android/services/network/HttpRequest:a	(Ljava/lang/String;Ljava/lang/String;)Lio/fabric/sdk/android/services/network/HttpRequest;
    //   148: astore_1
    //   149: new 65	java/lang/StringBuilder
    //   152: dup
    //   153: ldc 101
    //   155: invokespecial 70	java/lang/StringBuilder:<init>	(Ljava/lang/String;)V
    //   158: astore 6
    //   160: aload 6
    //   162: aload_2
    //   163: invokevirtual 82	java/lang/StringBuilder:append	(Ljava/lang/String;)Ljava/lang/StringBuilder;
    //   166: pop
    //   167: aload_1
    //   168: ldc 103
    //   170: aload 6
    //   172: invokevirtual 87	java/lang/StringBuilder:toString	()Ljava/lang/String;
    //   175: invokevirtual 63	io/fabric/sdk/android/services/network/HttpRequest:a	(Ljava/lang/String;Ljava/lang/String;)Lio/fabric/sdk/android/services/network/HttpRequest;
    //   178: astore_1
    //   179: aload_1
    //   180: astore_2
    //   181: invokestatic 108	xuc:a	()Lxum;
    //   184: pop
    //   185: aload_1
    //   186: astore_2
    //   187: new 65	java/lang/StringBuilder
    //   190: dup
    //   191: ldc 110
    //   193: invokespecial 70	java/lang/StringBuilder:<init>	(Ljava/lang/String;)V
    //   196: aload_0
    //   197: getfield 111	xur:a	Ljava/lang/String;
    //   200: invokevirtual 82	java/lang/StringBuilder:append	(Ljava/lang/String;)Ljava/lang/StringBuilder;
    //   203: pop
    //   204: aload_1
    //   205: astore_2
    //   206: invokestatic 108	xuc:a	()Lxum;
    //   209: pop
    //   210: aload_1
    //   211: astore_2
    //   212: new 65	java/lang/StringBuilder
    //   215: dup
    //   216: ldc 113
    //   218: invokespecial 70	java/lang/StringBuilder:<init>	(Ljava/lang/String;)V
    //   221: aload 5
    //   223: invokevirtual 116	java/lang/StringBuilder:append	(Ljava/lang/Object;)Ljava/lang/StringBuilder;
    //   226: pop
    //   227: aload_1
    //   228: astore_2
    //   229: sipush 200
    //   232: aload_1
    //   233: invokevirtual 119	io/fabric/sdk/android/services/network/HttpRequest:b	()I
    //   236: if_icmpne +285 -> 521
    //   239: iconst_1
    //   240: istore 4
    //   242: goto +3 -> 245
    //   245: iload 4
    //   247: ifeq +110 -> 357
    //   250: aload_1
    //   251: astore_2
    //   252: invokestatic 108	xuc:a	()Lxum;
    //   255: pop
    //   256: aload_1
    //   257: astore_2
    //   258: new 121	org/json/JSONObject
    //   261: dup
    //   262: aload_1
    //   263: invokevirtual 123	io/fabric/sdk/android/services/network/HttpRequest:c	()Ljava/lang/String;
    //   266: invokespecial 124	org/json/JSONObject:<init>	(Ljava/lang/String;)V
    //   269: astore_3
    //   270: aload_1
    //   271: astore_2
    //   272: aload_3
    //   273: ldc 126
    //   275: aconst_null
    //   276: invokevirtual 130	org/json/JSONObject:optString	(Ljava/lang/String;Ljava/lang/String;)Ljava/lang/String;
    //   279: pop
    //   280: aload_1
    //   281: astore_2
    //   282: aload_3
    //   283: ldc -124
    //   285: aconst_null
    //   286: invokevirtual 130	org/json/JSONObject:optString	(Ljava/lang/String;Ljava/lang/String;)Ljava/lang/String;
    //   289: pop
    //   290: aload_1
    //   291: astore_2
    //   292: aload_3
    //   293: ldc 26
    //   295: aconst_null
    //   296: invokevirtual 130	org/json/JSONObject:optString	(Ljava/lang/String;Ljava/lang/String;)Ljava/lang/String;
    //   299: pop
    //   300: aload_1
    //   301: astore_2
    //   302: aload_3
    //   303: ldc 39
    //   305: aconst_null
    //   306: invokevirtual 130	org/json/JSONObject:optString	(Ljava/lang/String;Ljava/lang/String;)Ljava/lang/String;
    //   309: pop
    //   310: aload_1
    //   311: astore_2
    //   312: aload_3
    //   313: ldc -122
    //   315: aconst_null
    //   316: invokevirtual 130	org/json/JSONObject:optString	(Ljava/lang/String;Ljava/lang/String;)Ljava/lang/String;
    //   319: pop
    //   320: aload_1
    //   321: astore_2
    //   322: aload_3
    //   323: ldc -120
    //   325: aconst_null
    //   326: invokevirtual 130	org/json/JSONObject:optString	(Ljava/lang/String;Ljava/lang/String;)Ljava/lang/String;
    //   329: pop
    //   330: aload_1
    //   331: astore_2
    //   332: new 138	ayk
    //   335: dup
    //   336: invokespecial 139	ayk:<init>	()V
    //   339: astore_3
    //   340: aload_1
    //   341: ifnull +14 -> 355
    //   344: aload_1
    //   345: ldc -115
    //   347: invokevirtual 144	io/fabric/sdk/android/services/network/HttpRequest:a	(Ljava/lang/String;)Ljava/lang/String;
    //   350: pop
    //   351: invokestatic 108	xuc:a	()Lxum;
    //   354: pop
    //   355: aload_3
    //   356: areturn
    //   357: aload_1
    //   358: astore_2
    //   359: invokestatic 108	xuc:a	()Lxum;
    //   362: astore_3
    //   363: aload_1
    //   364: astore_2
    //   365: new 65	java/lang/StringBuilder
    //   368: dup
    //   369: ldc -110
    //   371: invokespecial 70	java/lang/StringBuilder:<init>	(Ljava/lang/String;)V
    //   374: astore 5
    //   376: aload_1
    //   377: astore_2
    //   378: aload 5
    //   380: aload_1
    //   381: invokevirtual 119	io/fabric/sdk/android/services/network/HttpRequest:b	()I
    //   384: invokevirtual 149	java/lang/StringBuilder:append	(I)Ljava/lang/StringBuilder;
    //   387: pop
    //   388: aload_1
    //   389: astore_2
    //   390: aload_3
    //   391: ldc -105
    //   393: aload 5
    //   395: invokevirtual 87	java/lang/StringBuilder:toString	()Ljava/lang/String;
    //   398: invokeinterface 156 3 0
    //   403: aload_1
    //   404: ifnull +97 -> 501
    //   407: goto +83 -> 490
    //   410: astore_3
    //   411: goto +26 -> 437
    //   414: astore_1
    //   415: aload_3
    //   416: astore_2
    //   417: goto +87 -> 504
    //   420: astore_2
    //   421: aload_3
    //   422: astore_1
    //   423: aload_2
    //   424: astore_3
    //   425: goto +12 -> 437
    //   428: astore_1
    //   429: aconst_null
    //   430: astore_2
    //   431: goto +73 -> 504
    //   434: astore_3
    //   435: aconst_null
    //   436: astore_1
    //   437: aload_1
    //   438: astore_2
    //   439: invokestatic 108	xuc:a	()Lxum;
    //   442: astore 5
    //   444: aload_1
    //   445: astore_2
    //   446: new 65	java/lang/StringBuilder
    //   449: dup
    //   450: ldc -98
    //   452: invokespecial 70	java/lang/StringBuilder:<init>	(Ljava/lang/String;)V
    //   455: astore 6
    //   457: aload_1
    //   458: astore_2
    //   459: aload 6
    //   461: aload_0
    //   462: getfield 111	xur:a	Ljava/lang/String;
    //   465: invokevirtual 82	java/lang/StringBuilder:append	(Ljava/lang/String;)Ljava/lang/StringBuilder;
    //   468: pop
    //   469: aload_1
    //   470: astore_2
    //   471: aload 5
    //   473: ldc -105
    //   475: aload 6
    //   477: invokevirtual 87	java/lang/StringBuilder:toString	()Ljava/lang/String;
    //   480: aload_3
    //   481: invokeinterface 161 4 0
    //   486: aload_1
    //   487: ifnull +14 -> 501
    //   490: aload_1
    //   491: ldc -115
    //   493: invokevirtual 144	io/fabric/sdk/android/services/network/HttpRequest:a	(Ljava/lang/String;)Ljava/lang/String;
    //   496: pop
    //   497: invokestatic 108	xuc:a	()Lxum;
    //   500: pop
    //   501: aconst_null
    //   502: areturn
    //   503: astore_1
    //   504: aload_2
    //   505: ifnull +14 -> 519
    //   508: aload_2
    //   509: ldc -115
    //   511: invokevirtual 144	io/fabric/sdk/android/services/network/HttpRequest:a	(Ljava/lang/String;)Ljava/lang/String;
    //   514: pop
    //   515: invokestatic 108	xuc:a	()Lxum;
    //   518: pop
    //   519: aload_1
    //   520: athrow
    //   521: iconst_0
    //   522: istore 4
    //   524: goto -279 -> 245
    // Local variable table:
    //   start	length	slot	name	signature
    //   0	527	0	this	ayj
    //   0	527	1	paramString1	String
    //   0	527	2	paramString2	String
    //   0	527	3	paramAyi	ayi
    //   240	283	4	i	int
    //   7	465	5	localObject1	Object
    //   78	398	6	localObject2	Object
    //   89	20	7	localStringBuilder	StringBuilder
    // Exception table:
    //   from	to	target	type
    //   181	185	410	java/lang/Exception
    //   187	204	410	java/lang/Exception
    //   206	210	410	java/lang/Exception
    //   212	227	410	java/lang/Exception
    //   229	239	410	java/lang/Exception
    //   252	256	410	java/lang/Exception
    //   258	270	410	java/lang/Exception
    //   272	280	410	java/lang/Exception
    //   282	290	410	java/lang/Exception
    //   292	300	410	java/lang/Exception
    //   302	310	410	java/lang/Exception
    //   312	320	410	java/lang/Exception
    //   322	330	410	java/lang/Exception
    //   332	340	410	java/lang/Exception
    //   359	363	410	java/lang/Exception
    //   365	376	410	java/lang/Exception
    //   378	388	410	java/lang/Exception
    //   390	403	410	java/lang/Exception
    //   70	179	414	finally
    //   70	179	420	java/lang/Exception
    //   0	70	428	finally
    //   0	70	434	java/lang/Exception
    //   181	185	503	finally
    //   187	204	503	finally
    //   206	210	503	finally
    //   212	227	503	finally
    //   229	239	503	finally
    //   252	256	503	finally
    //   258	270	503	finally
    //   272	280	503	finally
    //   282	290	503	finally
    //   292	300	503	finally
    //   302	310	503	finally
    //   312	320	503	finally
    //   322	330	503	finally
    //   332	340	503	finally
    //   359	363	503	finally
    //   365	376	503	finally
    //   378	388	503	finally
    //   390	403	503	finally
    //   439	444	503	finally
    //   446	457	503	finally
    //   459	469	503	finally
    //   471	486	503	finally
  }
}
