import java.net.Socket;

final class bhs
  implements Runnable
{
  private final Socket a;
  
  public bhs(bho paramBho, Socket paramSocket)
  {
    this.a = paramSocket;
  }
  
  /* Error */
  public final void run()
  {
    // Byte code:
    //   0: aload_0
    //   1: getfield 14	bhs:b	Lbho;
    //   4: astore 9
    //   6: aload_0
    //   7: getfield 19	bhs:a	Ljava/net/Socket;
    //   10: astore 14
    //   12: aload 9
    //   14: astore 10
    //   16: aload 9
    //   18: astore 11
    //   20: aload 9
    //   22: astore 12
    //   24: aload 14
    //   26: invokevirtual 33	java/net/Socket:getInputStream	()Ljava/io/InputStream;
    //   29: invokestatic 38	bhm:a	(Ljava/io/InputStream;)Lbhm;
    //   32: astore 13
    //   34: aload 9
    //   36: astore 10
    //   38: aload 9
    //   40: astore 11
    //   42: aload 9
    //   44: astore 12
    //   46: new 40	java/lang/StringBuilder
    //   49: dup
    //   50: ldc 42
    //   52: invokespecial 45	java/lang/StringBuilder:<init>	(Ljava/lang/String;)V
    //   55: aload 13
    //   57: invokevirtual 49	java/lang/StringBuilder:append	(Ljava/lang/Object;)Ljava/lang/StringBuilder;
    //   60: pop
    //   61: aload 9
    //   63: astore 10
    //   65: aload 9
    //   67: astore 11
    //   69: aload 9
    //   71: astore 12
    //   73: aload 13
    //   75: getfield 52	bhm:a	Ljava/lang/String;
    //   78: invokestatic 57	bia:b	(Ljava/lang/String;)Ljava/lang/String;
    //   81: astore 15
    //   83: aload 9
    //   85: astore 10
    //   87: aload 9
    //   89: astore 11
    //   91: aload 9
    //   93: astore 12
    //   95: ldc 59
    //   97: aload 15
    //   99: invokevirtual 65	java/lang/String:equals	(Ljava/lang/Object;)Z
    //   102: ifeq +69 -> 171
    //   105: aload 9
    //   107: astore 10
    //   109: aload 9
    //   111: astore 11
    //   113: aload 9
    //   115: astore 12
    //   117: aload 14
    //   119: invokevirtual 69	java/net/Socket:getOutputStream	()Ljava/io/OutputStream;
    //   122: astore 13
    //   124: aload 9
    //   126: astore 10
    //   128: aload 9
    //   130: astore 11
    //   132: aload 9
    //   134: astore 12
    //   136: aload 13
    //   138: ldc 71
    //   140: invokevirtual 75	java/lang/String:getBytes	()[B
    //   143: invokevirtual 81	java/io/OutputStream:write	([B)V
    //   146: aload 9
    //   148: astore 10
    //   150: aload 9
    //   152: astore 11
    //   154: aload 9
    //   156: astore 12
    //   158: aload 13
    //   160: ldc 83
    //   162: invokevirtual 75	java/lang/String:getBytes	()[B
    //   165: invokevirtual 81	java/io/OutputStream:write	([B)V
    //   168: goto +478 -> 646
    //   171: aload 9
    //   173: astore 10
    //   175: aload 9
    //   177: astore 11
    //   179: aload 9
    //   181: astore 12
    //   183: aload 9
    //   185: aload 15
    //   187: invokevirtual 89	bho:c	(Ljava/lang/String;)Lbhu;
    //   190: astore 15
    //   192: aload 9
    //   194: astore 10
    //   196: aload 9
    //   198: astore 11
    //   200: aload 9
    //   202: astore 12
    //   204: aload 15
    //   206: invokevirtual 93	bhu:a	()V
    //   209: aload 15
    //   211: getfield 96	bhu:a	Ljava/util/concurrent/atomic/AtomicInteger;
    //   214: invokevirtual 102	java/util/concurrent/atomic/AtomicInteger:incrementAndGet	()I
    //   217: pop
    //   218: aload 15
    //   220: getfield 105	bhu:b	Lbhn;
    //   223: astore 12
    //   225: new 107	java/io/BufferedOutputStream
    //   228: dup
    //   229: aload 14
    //   231: invokevirtual 69	java/net/Socket:getOutputStream	()Ljava/io/OutputStream;
    //   234: invokespecial 110	java/io/BufferedOutputStream:<init>	(Ljava/io/OutputStream;)V
    //   237: astore 16
    //   239: aload 12
    //   241: getfield 115	bhn:a	Lbhw;
    //   244: invokevirtual 120	bhw:c	()Ljava/lang/String;
    //   247: astore 18
    //   249: aload 18
    //   251: invokestatic 126	android/text/TextUtils:isEmpty	(Ljava/lang/CharSequence;)Z
    //   254: istore 6
    //   256: aload 12
    //   258: getfield 129	bhn:b	Lbhc;
    //   261: invokevirtual 135	bhc:d	()Z
    //   264: ifeq +15 -> 279
    //   267: aload 12
    //   269: getfield 129	bhn:b	Lbhc;
    //   272: invokevirtual 137	bhc:a	()I
    //   275: istore_2
    //   276: goto +581 -> 857
    //   279: aload 12
    //   281: getfield 115	bhn:a	Lbhw;
    //   284: invokevirtual 138	bhw:a	()I
    //   287: istore_2
    //   288: goto +569 -> 857
    //   291: aload 13
    //   293: getfield 141	bhm:c	Z
    //   296: ifeq +575 -> 871
    //   299: iload_2
    //   300: i2l
    //   301: aload 13
    //   303: getfield 144	bhm:b	J
    //   306: lsub
    //   307: lstore 7
    //   309: goto +3 -> 312
    //   312: iload_1
    //   313: istore_3
    //   314: iload_3
    //   315: ifeq +563 -> 878
    //   318: aload 13
    //   320: getfield 141	bhm:c	Z
    //   323: ifeq +555 -> 878
    //   326: iconst_1
    //   327: istore_1
    //   328: goto +3 -> 331
    //   331: new 40	java/lang/StringBuilder
    //   334: dup
    //   335: invokespecial 145	java/lang/StringBuilder:<init>	()V
    //   338: astore 17
    //   340: aload 13
    //   342: getfield 141	bhm:c	Z
    //   345: ifeq +538 -> 883
    //   348: ldc -109
    //   350: astore 10
    //   352: goto +3 -> 355
    //   355: aload 17
    //   357: aload 10
    //   359: invokevirtual 150	java/lang/StringBuilder:append	(Ljava/lang/String;)Ljava/lang/StringBuilder;
    //   362: pop
    //   363: aload 17
    //   365: ldc -104
    //   367: invokevirtual 150	java/lang/StringBuilder:append	(Ljava/lang/String;)Ljava/lang/StringBuilder;
    //   370: pop
    //   371: iload_3
    //   372: ifeq +30 -> 402
    //   375: ldc -102
    //   377: iconst_1
    //   378: anewarray 4	java/lang/Object
    //   381: dup
    //   382: iconst_0
    //   383: lload 7
    //   385: invokestatic 160	java/lang/Long:valueOf	(J)Ljava/lang/Long;
    //   388: aastore
    //   389: invokestatic 164	java/lang/String:format	(Ljava/lang/String;[Ljava/lang/Object;)Ljava/lang/String;
    //   392: astore 11
    //   394: goto +12 -> 406
    //   397: astore 13
    //   399: goto +315 -> 714
    //   402: ldc -90
    //   404: astore 11
    //   406: aload 9
    //   408: astore 10
    //   410: aload 17
    //   412: aload 11
    //   414: invokevirtual 150	java/lang/StringBuilder:append	(Ljava/lang/String;)Ljava/lang/StringBuilder;
    //   417: pop
    //   418: iload_1
    //   419: ifeq +44 -> 463
    //   422: ldc -88
    //   424: iconst_3
    //   425: anewarray 4	java/lang/Object
    //   428: dup
    //   429: iconst_0
    //   430: aload 13
    //   432: getfield 144	bhm:b	J
    //   435: invokestatic 160	java/lang/Long:valueOf	(J)Ljava/lang/Long;
    //   438: aastore
    //   439: dup
    //   440: iconst_1
    //   441: iload_2
    //   442: iconst_1
    //   443: isub
    //   444: invokestatic 173	java/lang/Integer:valueOf	(I)Ljava/lang/Integer;
    //   447: aastore
    //   448: dup
    //   449: iconst_2
    //   450: iload_2
    //   451: invokestatic 173	java/lang/Integer:valueOf	(I)Ljava/lang/Integer;
    //   454: aastore
    //   455: invokestatic 164	java/lang/String:format	(Ljava/lang/String;[Ljava/lang/Object;)Ljava/lang/String;
    //   458: astore 11
    //   460: goto +7 -> 467
    //   463: ldc -90
    //   465: astore 11
    //   467: aload 17
    //   469: aload 11
    //   471: invokevirtual 150	java/lang/StringBuilder:append	(Ljava/lang/String;)Ljava/lang/StringBuilder;
    //   474: pop
    //   475: iload 6
    //   477: iconst_1
    //   478: ixor
    //   479: ifeq +22 -> 501
    //   482: ldc -81
    //   484: iconst_1
    //   485: anewarray 4	java/lang/Object
    //   488: dup
    //   489: iconst_0
    //   490: aload 18
    //   492: aastore
    //   493: invokestatic 164	java/lang/String:format	(Ljava/lang/String;[Ljava/lang/Object;)Ljava/lang/String;
    //   496: astore 11
    //   498: goto +7 -> 505
    //   501: ldc -90
    //   503: astore 11
    //   505: iconst_1
    //   506: istore_3
    //   507: aload 17
    //   509: aload 11
    //   511: invokevirtual 150	java/lang/StringBuilder:append	(Ljava/lang/String;)Ljava/lang/StringBuilder;
    //   514: pop
    //   515: aload 17
    //   517: ldc -79
    //   519: invokevirtual 150	java/lang/StringBuilder:append	(Ljava/lang/String;)Ljava/lang/StringBuilder;
    //   522: pop
    //   523: aload 16
    //   525: aload 17
    //   527: invokevirtual 180	java/lang/StringBuilder:toString	()Ljava/lang/String;
    //   530: ldc -74
    //   532: invokevirtual 185	java/lang/String:getBytes	(Ljava/lang/String;)[B
    //   535: invokevirtual 81	java/io/OutputStream:write	([B)V
    //   538: aload 13
    //   540: getfield 144	bhm:b	J
    //   543: lstore 7
    //   545: aload 12
    //   547: getfield 115	bhn:a	Lbhw;
    //   550: invokevirtual 138	bhw:a	()I
    //   553: istore 4
    //   555: iload 4
    //   557: ifle +333 -> 890
    //   560: iconst_1
    //   561: istore_1
    //   562: goto +3 -> 565
    //   565: aload 12
    //   567: getfield 129	bhn:b	Lbhc;
    //   570: invokevirtual 137	bhc:a	()I
    //   573: istore 5
    //   575: iload_3
    //   576: istore_2
    //   577: iload_1
    //   578: ifeq +38 -> 616
    //   581: iload_3
    //   582: istore_2
    //   583: aload 13
    //   585: getfield 141	bhm:c	Z
    //   588: ifeq +28 -> 616
    //   591: aload 13
    //   593: getfield 144	bhm:b	J
    //   596: l2f
    //   597: iload 5
    //   599: i2f
    //   600: iload 4
    //   602: i2f
    //   603: ldc -70
    //   605: fmul
    //   606: fadd
    //   607: fcmpg
    //   608: ifgt +287 -> 895
    //   611: iload_3
    //   612: istore_2
    //   613: goto +3 -> 616
    //   616: iload_2
    //   617: ifeq +15 -> 632
    //   620: aload 12
    //   622: aload 16
    //   624: lload 7
    //   626: invokevirtual 189	bhn:a	(Ljava/io/OutputStream;J)V
    //   629: goto +12 -> 641
    //   632: aload 12
    //   634: aload 16
    //   636: lload 7
    //   638: invokevirtual 191	bhn:b	(Ljava/io/OutputStream;J)V
    //   641: aload 15
    //   643: invokevirtual 193	bhu:b	()V
    //   646: aload 14
    //   648: invokestatic 196	bho:a	(Ljava/net/Socket;)V
    //   651: new 40	java/lang/StringBuilder
    //   654: dup
    //   655: ldc -58
    //   657: invokespecial 45	java/lang/StringBuilder:<init>	(Ljava/lang/String;)V
    //   660: astore 10
    //   662: aload 10
    //   664: aload 9
    //   666: invokevirtual 200	bho:c	()I
    //   669: invokevirtual 203	java/lang/StringBuilder:append	(I)Ljava/lang/StringBuilder;
    //   672: pop
    //   673: return
    //   674: astore 9
    //   676: goto +72 -> 748
    //   679: astore 11
    //   681: aload 10
    //   683: astore 9
    //   685: goto +76 -> 761
    //   688: aload 10
    //   690: astore 12
    //   692: goto +132 -> 824
    //   695: astore 11
    //   697: aload 10
    //   699: astore 9
    //   701: aload 11
    //   703: astore 10
    //   705: goto +5 -> 710
    //   708: astore 10
    //   710: aload 10
    //   712: astore 13
    //   714: aload 9
    //   716: astore 10
    //   718: aload 9
    //   720: astore 11
    //   722: aload 9
    //   724: astore 12
    //   726: aload 15
    //   728: invokevirtual 193	bhu:b	()V
    //   731: aload 9
    //   733: astore 10
    //   735: aload 9
    //   737: astore 11
    //   739: aload 9
    //   741: astore 12
    //   743: aload 13
    //   745: athrow
    //   746: astore 9
    //   748: goto +50 -> 798
    //   751: astore 10
    //   753: aload 11
    //   755: astore 9
    //   757: aload 10
    //   759: astore 11
    //   761: aload 9
    //   763: astore 10
    //   765: new 25	com/facebook/ads/internal/i/b/l
    //   768: dup
    //   769: ldc -51
    //   771: aload 11
    //   773: invokespecial 208	com/facebook/ads/internal/i/b/l:<init>	(Ljava/lang/String;Ljava/lang/Throwable;)V
    //   776: invokestatic 211	bho:a	(Ljava/lang/Throwable;)V
    //   779: aload 14
    //   781: invokestatic 196	bho:a	(Ljava/net/Socket;)V
    //   784: new 40	java/lang/StringBuilder
    //   787: dup
    //   788: ldc -58
    //   790: invokespecial 45	java/lang/StringBuilder:<init>	(Ljava/lang/String;)V
    //   793: astore 10
    //   795: goto -133 -> 662
    //   798: aload 14
    //   800: invokestatic 196	bho:a	(Ljava/net/Socket;)V
    //   803: new 40	java/lang/StringBuilder
    //   806: dup
    //   807: ldc -58
    //   809: invokespecial 45	java/lang/StringBuilder:<init>	(Ljava/lang/String;)V
    //   812: aload 10
    //   814: invokevirtual 200	bho:c	()I
    //   817: invokevirtual 203	java/lang/StringBuilder:append	(I)Ljava/lang/StringBuilder;
    //   820: pop
    //   821: aload 9
    //   823: athrow
    //   824: aload 14
    //   826: invokestatic 196	bho:a	(Ljava/net/Socket;)V
    //   829: new 40	java/lang/StringBuilder
    //   832: dup
    //   833: ldc -58
    //   835: invokespecial 45	java/lang/StringBuilder:<init>	(Ljava/lang/String;)V
    //   838: astore 10
    //   840: aload 12
    //   842: astore 9
    //   844: goto -182 -> 662
    //   847: astore 9
    //   849: goto -25 -> 824
    //   852: astore 9
    //   854: goto -166 -> 688
    //   857: iload_2
    //   858: iflt +8 -> 866
    //   861: iconst_1
    //   862: istore_1
    //   863: goto -572 -> 291
    //   866: iconst_0
    //   867: istore_1
    //   868: goto -577 -> 291
    //   871: iload_2
    //   872: i2l
    //   873: lstore 7
    //   875: goto -563 -> 312
    //   878: iconst_0
    //   879: istore_1
    //   880: goto -549 -> 331
    //   883: ldc -43
    //   885: astore 10
    //   887: goto -532 -> 355
    //   890: iconst_0
    //   891: istore_1
    //   892: goto -327 -> 565
    //   895: iconst_0
    //   896: istore_2
    //   897: goto -281 -> 616
    // Local variable table:
    //   start	length	slot	name	signature
    //   0	900	0	this	bhs
    //   312	580	1	i	int
    //   275	622	2	j	int
    //   313	299	3	k	int
    //   553	48	4	m	int
    //   573	25	5	n	int
    //   254	225	6	bool	boolean
    //   307	567	7	l	long
    //   4	661	9	localBho	bho
    //   674	1	9	localObject1	Object
    //   683	57	9	localObject2	Object
    //   746	1	9	localObject3	Object
    //   755	88	9	localObject4	Object
    //   847	1	9	localSocketException1	java.net.SocketException
    //   852	1	9	localSocketException2	java.net.SocketException
    //   14	690	10	localObject5	Object
    //   708	3	10	localObject6	Object
    //   716	18	10	localObject7	Object
    //   751	7	10	localL1	com.facebook.ads.internal.i.b.l
    //   763	123	10	localObject8	Object
    //   18	492	11	localObject9	Object
    //   679	1	11	localL2	com.facebook.ads.internal.i.b.l
    //   695	7	11	localObject10	Object
    //   720	52	11	localObject11	Object
    //   22	819	12	localObject12	Object
    //   32	309	13	localObject13	Object
    //   397	195	13	localObject14	Object
    //   712	32	13	localObject15	Object
    //   10	815	14	localSocket	Socket
    //   81	646	15	localObject16	Object
    //   237	398	16	localBufferedOutputStream	java.io.BufferedOutputStream
    //   338	188	17	localStringBuilder	StringBuilder
    //   247	244	18	str	String
    // Exception table:
    //   from	to	target	type
    //   375	394	397	finally
    //   422	460	397	finally
    //   482	498	397	finally
    //   583	611	397	finally
    //   620	629	397	finally
    //   641	646	674	finally
    //   641	646	679	com/facebook/ads/internal/i/b/l
    //   641	646	679	java/io/IOException
    //   410	418	695	finally
    //   467	475	695	finally
    //   507	555	695	finally
    //   565	575	695	finally
    //   632	641	695	finally
    //   209	276	708	finally
    //   279	288	708	finally
    //   291	309	708	finally
    //   318	326	708	finally
    //   331	348	708	finally
    //   355	371	708	finally
    //   24	34	746	finally
    //   46	61	746	finally
    //   73	83	746	finally
    //   95	105	746	finally
    //   117	124	746	finally
    //   136	146	746	finally
    //   158	168	746	finally
    //   183	192	746	finally
    //   204	209	746	finally
    //   726	731	746	finally
    //   743	746	746	finally
    //   765	779	746	finally
    //   24	34	751	com/facebook/ads/internal/i/b/l
    //   24	34	751	java/io/IOException
    //   46	61	751	com/facebook/ads/internal/i/b/l
    //   46	61	751	java/io/IOException
    //   73	83	751	com/facebook/ads/internal/i/b/l
    //   73	83	751	java/io/IOException
    //   95	105	751	com/facebook/ads/internal/i/b/l
    //   95	105	751	java/io/IOException
    //   117	124	751	com/facebook/ads/internal/i/b/l
    //   117	124	751	java/io/IOException
    //   136	146	751	com/facebook/ads/internal/i/b/l
    //   136	146	751	java/io/IOException
    //   158	168	751	com/facebook/ads/internal/i/b/l
    //   158	168	751	java/io/IOException
    //   183	192	751	com/facebook/ads/internal/i/b/l
    //   183	192	751	java/io/IOException
    //   204	209	751	com/facebook/ads/internal/i/b/l
    //   204	209	751	java/io/IOException
    //   726	731	751	com/facebook/ads/internal/i/b/l
    //   726	731	751	java/io/IOException
    //   743	746	751	com/facebook/ads/internal/i/b/l
    //   743	746	751	java/io/IOException
    //   24	34	847	java/net/SocketException
    //   46	61	847	java/net/SocketException
    //   73	83	847	java/net/SocketException
    //   95	105	847	java/net/SocketException
    //   117	124	847	java/net/SocketException
    //   136	146	847	java/net/SocketException
    //   158	168	847	java/net/SocketException
    //   183	192	847	java/net/SocketException
    //   204	209	847	java/net/SocketException
    //   726	731	847	java/net/SocketException
    //   743	746	847	java/net/SocketException
    //   641	646	852	java/net/SocketException
  }
}
