import android.os.Handler;
import android.os.Handler.Callback;
import android.os.HandlerThread;
import android.os.Message;
import android.os.SystemClock;
import android.util.Log;
import android.util.Pair;
import com.google.android.exoplayer2.ExoPlaybackException;
import com.google.android.exoplayer2.IllegalSeekPositionException;

final class bqo
  implements Handler.Callback, bzr, bzt, cdm
{
  private long A;
  private int B;
  private bqr C;
  private long D;
  private bqp E;
  private bqp F;
  private bqp G;
  private brj H;
  final Handler a;
  boolean b;
  int c;
  private final brc[] d;
  private final brd[] e;
  private final cdl f;
  private final bqw g;
  private final cff h;
  private final HandlerThread i;
  private final Handler j;
  private final bqi k;
  private final brl l;
  private final brk m;
  private final bqx n;
  private bqq o;
  private bqz p;
  private brc q;
  private cev r;
  private bzs s;
  private brc[] t;
  private boolean u;
  private boolean v;
  private boolean w;
  private int x;
  private int y;
  private int z;
  
  public bqo(brc[] paramArrayOfBrc, cdl paramCdl, bqw paramBqw, boolean paramBoolean, int paramInt, Handler paramHandler, bqq paramBqq, bqi paramBqi)
  {
    this.d = paramArrayOfBrc;
    this.f = paramCdl;
    this.g = paramBqw;
    this.u = paramBoolean;
    this.y = paramInt;
    this.j = paramHandler;
    this.x = 1;
    this.o = paramBqq;
    this.k = paramBqi;
    this.e = new brd[paramArrayOfBrc.length];
    paramInt = 0;
    while (paramInt < paramArrayOfBrc.length)
    {
      paramArrayOfBrc[paramInt].a(paramInt);
      this.e[paramInt] = paramArrayOfBrc[paramInt].b();
      paramInt += 1;
    }
    this.h = new cff();
    this.t = new brc[0];
    this.l = new brl();
    this.m = new brk();
    this.n = new bqx();
    paramCdl.b = this;
    this.p = bqz.a;
    this.i = new HandlerThread("ExoPlayerImplInternal:Handler", -16);
    this.i.start();
    this.a = new Handler(this.i.getLooper(), this);
  }
  
  private int a(int paramInt, brj paramBrj1, brj paramBrj2)
  {
    int i3 = paramBrj1.c();
    int i1 = 0;
    int i2 = paramInt;
    paramInt = -1;
    while ((i1 < i3) && (paramInt == -1))
    {
      i2 = paramBrj1.a(i2, this.m, this.l, this.y);
      if (i2 == -1) {
        break;
      }
      paramInt = paramBrj2.a(paramBrj1.a(i2, this.m, true).a);
      i1 += 1;
    }
    return paramInt;
  }
  
  private long a(bzu paramBzu, long paramLong)
  {
    d();
    this.v = false;
    a(2);
    Object localObject;
    int i1;
    if (this.G == null)
    {
      if (this.E != null) {
        this.E.d();
      }
      localObject = null;
    }
    else
    {
      bqp localBqp1 = this.G;
      bqp localBqp2 = null;
      for (;;)
      {
        localObject = localBqp2;
        if (localBqp1 == null) {
          break;
        }
        if ((paramBzu.equals(localBqp1.f.a)) && (localBqp1.g))
        {
          this.H.a(localBqp1.f.a.a, this.m, false);
          i1 = 1;
        }
        else
        {
          i1 = 0;
        }
        if (i1 != 0) {
          localBqp2 = localBqp1;
        } else {
          localBqp1.d();
        }
        localBqp1 = localBqp1.i;
      }
    }
    if ((this.G != localObject) || (this.G != this.F))
    {
      paramBzu = this.t;
      int i2 = paramBzu.length;
      i1 = 0;
      while (i1 < i2)
      {
        paramBzu[i1].l();
        i1 += 1;
      }
      this.t = new brc[0];
      this.r = null;
      this.q = null;
      this.G = null;
    }
    if (localObject != null)
    {
      localObject.i = null;
      this.E = localObject;
      this.F = localObject;
      b(localObject);
      long l1 = paramLong;
      if (this.G.h) {
        l1 = this.G.a.b(paramLong);
      }
      a(l1);
      i();
      paramLong = l1;
    }
    else
    {
      this.E = null;
      this.F = null;
      this.G = null;
      a(paramLong);
    }
    this.a.sendEmptyMessage(2);
    return paramLong;
  }
  
  private Pair<Integer, Long> a(bqr paramBqr)
  {
    Object localObject2 = paramBqr.a;
    Object localObject1 = localObject2;
    if (((brj)localObject2).a()) {
      localObject1 = this.H;
    }
    try
    {
      localObject2 = ((brj)localObject1).a(this.l, this.m, paramBqr.b, paramBqr.c);
      if (this.H == localObject1) {
        return localObject2;
      }
      int i1 = this.H.a(((brj)localObject1).a(((Integer)((Pair)localObject2).first).intValue(), this.m, true).a);
      if (i1 != -1) {
        return Pair.create(Integer.valueOf(i1), ((Pair)localObject2).second);
      }
      i1 = a(((Integer)((Pair)localObject2).first).intValue(), (brj)localObject1, this.H);
      if (i1 != -1)
      {
        this.H.a(i1, this.m, false);
        return h();
      }
      return null;
    }
    catch (IndexOutOfBoundsException localIndexOutOfBoundsException)
    {
      for (;;) {}
    }
    throw new IllegalSeekPositionException(this.H, paramBqr.b, paramBqr.c);
  }
  
  private bqp a(bqp paramBqp, int paramInt)
  {
    for (;;)
    {
      paramBqp.f = this.n.a(paramBqp.f, paramInt);
      if (paramBqp.f.f) {
        break;
      }
      if (paramBqp.i == null) {
        return paramBqp;
      }
      paramBqp = paramBqp.i;
    }
    return paramBqp;
  }
  
  private void a(int paramInt)
  {
    if (this.x != paramInt)
    {
      this.x = paramInt;
      this.j.obtainMessage(1, paramInt, 0).sendToTarget();
    }
  }
  
  private void a(long paramLong)
  {
    if (this.G == null) {
      paramLong += 60000000L;
    } else {
      paramLong += this.G.a();
    }
    this.D = paramLong;
    this.h.a(this.D);
    brc[] arrayOfBrc = this.t;
    int i2 = arrayOfBrc.length;
    int i1 = 0;
    while (i1 < i2)
    {
      arrayOfBrc[i1].a(this.D);
      i1 += 1;
    }
  }
  
  private void a(long paramLong1, long paramLong2)
  {
    this.a.removeMessages(2);
    paramLong1 = paramLong1 + paramLong2 - SystemClock.elapsedRealtime();
    if (paramLong1 <= 0L)
    {
      this.a.sendEmptyMessage(2);
      return;
    }
    this.a.sendEmptyMessageDelayed(2, paramLong1);
  }
  
  private static void a(bqp paramBqp)
  {
    while (paramBqp != null)
    {
      paramBqp.d();
      paramBqp = paramBqp.i;
    }
  }
  
  private static void a(brc paramBrc)
  {
    if (paramBrc.d() == 2) {
      paramBrc.k();
    }
  }
  
  private void a(Object paramObject, int paramInt)
  {
    this.o = new bqq(0L);
    b(paramObject, paramInt);
    this.o = new bqq(-9223372036854775807L);
    a(4);
    b(false);
  }
  
  private void a(boolean paramBoolean)
  {
    throw new Runtime("d2j fail translate: java.lang.RuntimeException: can not merge I and Z\n\tat com.googlecode.dex2jar.ir.TypeClass.merge(TypeClass.java:100)\n\tat com.googlecode.dex2jar.ir.ts.TypeTransformer$TypeRef.updateTypeClass(TypeTransformer.java:174)\n\tat com.googlecode.dex2jar.ir.ts.TypeTransformer$TypeAnalyze.copyTypes(TypeTransformer.java:311)\n\tat com.googlecode.dex2jar.ir.ts.TypeTransformer$TypeAnalyze.fixTypes(TypeTransformer.java:226)\n\tat com.googlecode.dex2jar.ir.ts.TypeTransformer$TypeAnalyze.analyze(TypeTransformer.java:207)\n\tat com.googlecode.dex2jar.ir.ts.TypeTransformer.transform(TypeTransformer.java:44)\n\tat com.googlecode.d2j.dex.Dex2jar$2.optimize(Dex2jar.java:162)\n\tat com.googlecode.d2j.dex.Dex2Asm.convertCode(Dex2Asm.java:414)\n\tat com.googlecode.d2j.dex.ExDex2Asm.convertCode(ExDex2Asm.java:42)\n\tat com.googlecode.d2j.dex.Dex2jar$2.convertCode(Dex2jar.java:128)\n\tat com.googlecode.d2j.dex.Dex2Asm.convertMethod(Dex2Asm.java:509)\n\tat com.googlecode.d2j.dex.Dex2Asm.convertClass(Dex2Asm.java:406)\n\tat com.googlecode.d2j.dex.Dex2Asm.convertDex(Dex2Asm.java:422)\n\tat com.googlecode.d2j.dex.Dex2jar.doTranslate(Dex2jar.java:172)\n\tat com.googlecode.d2j.dex.Dex2jar.to(Dex2jar.java:272)\n\tat com.googlecode.dex2jar.tools.Dex2jarCmd.doCommandLine(Dex2jarCmd.java:108)\n\tat com.googlecode.dex2jar.tools.BaseCmd.doMain(BaseCmd.java:288)\n\tat com.googlecode.dex2jar.tools.Dex2jarCmd.main(Dex2jarCmd.java:32)\n");
  }
  
  private void a(boolean[] paramArrayOfBoolean, int paramInt)
  {
    this.t = new brc[paramInt];
    paramInt = 0;
    int i2;
    for (int i1 = paramInt; paramInt < this.d.length; i1 = i2)
    {
      brc localBrc = this.d[paramInt];
      Object localObject = this.G.j.a.b[paramInt];
      i2 = i1;
      if (localObject != null)
      {
        this.t[i1] = localBrc;
        if (localBrc.d() == 0)
        {
          bre localBre = this.G.j.b[paramInt];
          if ((this.u) && (this.x == 3)) {
            i2 = 1;
          } else {
            i2 = 0;
          }
          boolean bool;
          if ((paramArrayOfBoolean[paramInt] == 0) && (i2 != 0)) {
            bool = true;
          } else {
            bool = false;
          }
          bqu[] arrayOfBqu = new bqu[((cdi)localObject).d()];
          int i3 = 0;
          while (i3 < arrayOfBqu.length)
          {
            arrayOfBqu[i3] = ((cdi)localObject).a(i3);
            i3 += 1;
          }
          localBrc.a(localBre, arrayOfBqu, this.G.d[paramInt], this.D, bool, this.G.a());
          localObject = localBrc.c();
          if (localObject != null)
          {
            if (this.r != null) {
              throw ExoPlaybackException.a(new IllegalStateException("Multiple renderer media clocks enabled."));
            }
            this.r = ((cev)localObject);
            this.q = localBrc;
            this.r.a(this.p);
          }
          if (i2 != 0) {
            localBrc.e();
          }
        }
        i2 = i1 + 1;
      }
      paramInt += 1;
    }
  }
  
  private void b(bqp paramBqp)
  {
    if (this.G == paramBqp) {
      return;
    }
    boolean[] arrayOfBoolean = new boolean[this.d.length];
    int i1 = 0;
    int i3;
    for (int i2 = i1; i1 < this.d.length; i2 = i3)
    {
      brc localBrc = this.d[i1];
      int i4;
      if (localBrc.d() != 0) {
        i4 = 1;
      } else {
        i4 = 0;
      }
      arrayOfBoolean[i1] = i4;
      cdi localCdi = paramBqp.j.a.b[i1];
      i3 = i2;
      if (localCdi != null) {
        i3 = i2 + 1;
      }
      if ((arrayOfBoolean[i1] != 0) && ((localCdi == null) || ((localBrc.i()) && (localBrc.f() == this.G.d[i1]))))
      {
        if (localBrc == this.q)
        {
          this.h.a(this.r);
          this.r = null;
          this.q = null;
        }
        a(localBrc);
        localBrc.l();
      }
      i1 += 1;
    }
    this.G = paramBqp;
    this.j.obtainMessage(3, paramBqp.j).sendToTarget();
    a(arrayOfBoolean, i2);
  }
  
  private void b(Object paramObject, int paramInt)
  {
    this.j.obtainMessage(6, new bqs(this.H, paramObject, this.o, paramInt)).sendToTarget();
  }
  
  private void b(boolean paramBoolean)
  {
    this.a.removeMessages(2);
    this.v = false;
    this.h.a();
    this.r = null;
    this.q = null;
    this.D = 60000000L;
    Object localObject = this.t;
    int i2 = localObject.length;
    int i1 = 0;
    while (i1 < i2)
    {
      brc localBrc = localObject[i1];
      try
      {
        a(localBrc);
        localBrc.l();
      }
      catch (ExoPlaybackException|RuntimeException localExoPlaybackException)
      {
        Log.e("ExoPlayerImplInternal", "Stop failed.", localExoPlaybackException);
      }
      i1 += 1;
    }
    this.t = new brc[0];
    if (this.G != null) {
      localObject = this.G;
    } else {
      localObject = this.E;
    }
    a((bqp)localObject);
    this.E = null;
    this.F = null;
    this.G = null;
    a(false);
    if (paramBoolean)
    {
      if (this.s != null)
      {
        this.s.a();
        this.s = null;
      }
      this.n.c = null;
      this.H = null;
    }
  }
  
  private boolean b(long paramLong)
  {
    return (paramLong == -9223372036854775807L) || (this.o.d < paramLong) || ((this.G.i != null) && ((this.G.i.g) || (this.G.i.f.a.a())));
  }
  
  private void c()
  {
    int i1 = 0;
    this.v = false;
    Object localObject = this.h;
    if (!((cff)localObject).a)
    {
      ((cff)localObject).b = SystemClock.elapsedRealtime();
      ((cff)localObject).a = true;
    }
    localObject = this.t;
    int i2 = localObject.length;
    while (i1 < i2)
    {
      localObject[i1].e();
      i1 += 1;
    }
  }
  
  private void d()
  {
    this.h.a();
    brc[] arrayOfBrc = this.t;
    int i1 = 0;
    int i2 = arrayOfBrc.length;
    while (i1 < i2)
    {
      a(arrayOfBrc[i1]);
      i1 += 1;
    }
  }
  
  private void e()
  {
    if (this.G == null) {
      return;
    }
    long l1 = this.G.a.c();
    if (l1 != -9223372036854775807L)
    {
      a(l1);
    }
    else
    {
      if ((this.q != null) && (!this.q.r()))
      {
        this.D = this.r.v();
        this.h.a(this.D);
      }
      else
      {
        this.D = this.h.v();
      }
      localObject = this.G;
      l1 = this.D - ((bqp)localObject).a();
    }
    this.o.d = l1;
    this.A = (SystemClock.elapsedRealtime() * 1000L);
    if (this.t.length == 0) {
      l1 = Long.MIN_VALUE;
    } else {
      l1 = this.G.a.d();
    }
    Object localObject = this.o;
    long l2 = l1;
    if (l1 == Long.MIN_VALUE) {
      l2 = this.G.f.e;
    }
    ((bqq)localObject).e = l2;
  }
  
  private void f()
  {
    b(true);
    this.g.b();
    a(1);
  }
  
  private void g()
  {
    if ((this.E != null) && (!this.E.g) && ((this.F == null) || (this.F.i == this.E)))
    {
      brc[] arrayOfBrc = this.t;
      int i2 = arrayOfBrc.length;
      int i1 = 0;
      while (i1 < i2)
      {
        if (!arrayOfBrc[i1].g()) {
          return;
        }
        i1 += 1;
      }
      this.E.a.f_();
    }
  }
  
  private Pair<Integer, Long> h()
  {
    return this.H.a(this.l, this.m, 0, -9223372036854775807L);
  }
  
  private void i()
  {
    bqp localBqp = this.E;
    long l2 = this.D;
    long l1;
    if (!localBqp.g) {
      l1 = 0L;
    } else {
      l1 = localBqp.a.e();
    }
    boolean bool;
    if (l1 == Long.MIN_VALUE)
    {
      bool = false;
    }
    else
    {
      long l3 = localBqp.a();
      bool = localBqp.k.a(l1 - (l2 - l3));
    }
    a(bool);
    if (bool)
    {
      localBqp = this.E;
      l1 = this.D;
      l2 = localBqp.a();
      localBqp.a.c(l1 - l2);
    }
  }
  
  public final void a()
  {
    int i1;
    for (;;)
    {
      try
      {
        boolean bool = this.b;
        if (bool) {
          return;
        }
        this.a.sendEmptyMessage(6);
        i1 = 0;
        bool = this.b;
        if (bool) {
          break;
        }
      }
      finally {}
      try
      {
        wait();
      }
      catch (InterruptedException localInterruptedException)
      {
        continue;
      }
      i1 = 1;
    }
    if (i1 != 0) {
      Thread.currentThread().interrupt();
    }
    this.i.quit();
  }
  
  public final void a(brj paramBrj, int paramInt, long paramLong)
  {
    this.a.obtainMessage(3, new bqr(paramBrj, paramInt, paramLong)).sendToTarget();
  }
  
  public final void a(brj paramBrj, Object paramObject)
  {
    this.a.obtainMessage(7, Pair.create(paramBrj, paramObject)).sendToTarget();
  }
  
  public final void a(bzq paramBzq)
  {
    this.a.obtainMessage(8, paramBzq).sendToTarget();
  }
  
  public final void a(bql... paramVarArgs)
  {
    int i1;
    for (;;)
    {
      try
      {
        boolean bool = this.b;
        if (bool) {
          return;
        }
        int i2 = this.c;
        this.c = (i2 + 1);
        this.a.obtainMessage(11, paramVarArgs).sendToTarget();
        i1 = 0;
        int i3 = this.z;
        if (i3 > i2) {
          break;
        }
      }
      finally {}
      try
      {
        wait();
      }
      catch (InterruptedException paramVarArgs)
      {
        continue;
      }
      i1 = 1;
    }
    if (i1 != 0) {
      Thread.currentThread().interrupt();
    }
  }
  
  public final void b()
  {
    this.a.sendEmptyMessage(10);
  }
  
  /* Error */
  public final boolean handleMessage(Message paramMessage)
  {
    // Byte code:
    //   0: aload_1
    //   1: getfield 528	android/os/Message:what	I
    //   4: istore_3
    //   5: lconst_0
    //   6: lstore 7
    //   8: iconst_0
    //   9: istore_2
    //   10: iconst_0
    //   11: istore 4
    //   13: iload_3
    //   14: tableswitch	default:+66->80, 0:+4411->4425, 1:+4327->4341, 2:+2570->2584, 3:+2171->2185, 4:+2113->2127, 5:+2107->2121, 6:+2068->2082, 7:+1143->1157, 8:+995->1009, 9:+961->975, 10:+492->506, 11:+369->383, 12:+68->82
    //   80: iconst_0
    //   81: ireturn
    //   82: aload_1
    //   83: getfield 531	android/os/Message:arg1	I
    //   86: istore_2
    //   87: aload_0
    //   88: iload_2
    //   89: putfield 83	bqo:y	I
    //   92: aload_0
    //   93: getfield 125	bqo:n	Lbqx;
    //   96: iload_2
    //   97: putfield 533	bqx:d	I
    //   100: aload_0
    //   101: getfield 186	bqo:G	Lbqp;
    //   104: ifnull +11 -> 115
    //   107: aload_0
    //   108: getfield 186	bqo:G	Lbqp;
    //   111: astore_1
    //   112: goto +4519 -> 4631
    //   115: aload_0
    //   116: getfield 188	bqo:E	Lbqp;
    //   119: astore_1
    //   120: goto +4511 -> 4631
    //   123: aload_0
    //   124: getfield 209	bqo:H	Lbrj;
    //   127: aload_1
    //   128: getfield 194	bqp:f	Lbqy;
    //   131: getfield 199	bqy:a	Lbzu;
    //   134: getfield 211	bzu:a	I
    //   137: aload_0
    //   138: getfield 120	bqo:m	Lbrk;
    //   141: aload_0
    //   142: getfield 115	bqo:l	Lbrl;
    //   145: iload_2
    //   146: invokevirtual 169	brj:a	(ILbrk;Lbrl;I)I
    //   149: istore_3
    //   150: aload_1
    //   151: getfield 213	bqp:i	Lbqp;
    //   154: ifnull +21 -> 175
    //   157: aload_1
    //   158: getfield 194	bqp:f	Lbqy;
    //   161: getfield 299	bqy:f	Z
    //   164: ifne +11 -> 175
    //   167: aload_1
    //   168: getfield 213	bqp:i	Lbqp;
    //   171: astore_1
    //   172: goto -22 -> 150
    //   175: iload_3
    //   176: iconst_m1
    //   177: if_icmpeq +35 -> 212
    //   180: aload_1
    //   181: getfield 213	bqp:i	Lbqp;
    //   184: ifnull +28 -> 212
    //   187: aload_1
    //   188: getfield 213	bqp:i	Lbqp;
    //   191: getfield 194	bqp:f	Lbqy;
    //   194: getfield 199	bqy:a	Lbzu;
    //   197: getfield 211	bzu:a	I
    //   200: iload_3
    //   201: if_icmpne +11 -> 212
    //   204: aload_1
    //   205: getfield 213	bqp:i	Lbqp;
    //   208: astore_1
    //   209: goto -86 -> 123
    //   212: aload_0
    //   213: getfield 188	bqo:E	Lbqp;
    //   216: getfield 534	bqp:c	I
    //   219: istore_3
    //   220: aload_0
    //   221: getfield 215	bqo:F	Lbqp;
    //   224: ifnull +4414 -> 4638
    //   227: aload_0
    //   228: getfield 215	bqo:F	Lbqp;
    //   231: getfield 534	bqp:c	I
    //   234: istore_2
    //   235: goto +3 -> 238
    //   238: aload_1
    //   239: getfield 213	bqp:i	Lbqp;
    //   242: ifnull +15 -> 257
    //   245: aload_1
    //   246: getfield 213	bqp:i	Lbqp;
    //   249: invokestatic 440	bqo:a	(Lbqp;)V
    //   252: aload_1
    //   253: aconst_null
    //   254: putfield 213	bqp:i	Lbqp;
    //   257: aload_0
    //   258: getfield 125	bqo:n	Lbqx;
    //   261: astore 16
    //   263: aload_1
    //   264: getfield 194	bqp:f	Lbqy;
    //   267: astore 15
    //   269: aload_1
    //   270: aload 16
    //   272: aload 15
    //   274: aload 15
    //   276: getfield 199	bqy:a	Lbzu;
    //   279: invokevirtual 537	bqx:a	(Lbqy;Lbzu;)Lbqy;
    //   282: putfield 194	bqp:f	Lbqy;
    //   285: iload_3
    //   286: aload_1
    //   287: getfield 534	bqp:c	I
    //   290: if_icmpgt +4353 -> 4643
    //   293: iconst_1
    //   294: istore_3
    //   295: goto +3 -> 298
    //   298: iload_3
    //   299: ifne +8 -> 307
    //   302: aload_0
    //   303: aload_1
    //   304: putfield 188	bqo:E	Lbqp;
    //   307: iload 4
    //   309: istore_3
    //   310: iload_2
    //   311: iconst_m1
    //   312: if_icmpeq +16 -> 328
    //   315: iload 4
    //   317: istore_3
    //   318: iload_2
    //   319: aload_1
    //   320: getfield 534	bqp:c	I
    //   323: if_icmpgt +5 -> 328
    //   326: iconst_1
    //   327: istore_3
    //   328: iload_3
    //   329: ifne +4319 -> 4648
    //   332: aload_0
    //   333: getfield 186	bqo:G	Lbqp;
    //   336: ifnull +4312 -> 4648
    //   339: aload_0
    //   340: getfield 186	bqo:G	Lbqp;
    //   343: getfield 194	bqp:f	Lbqy;
    //   346: getfield 199	bqy:a	Lbzu;
    //   349: astore_1
    //   350: aload_0
    //   351: new 338	bqq
    //   354: dup
    //   355: aload_1
    //   356: aload_0
    //   357: aload_1
    //   358: aload_0
    //   359: getfield 89	bqo:o	Lbqq;
    //   362: getfield 452	bqq:d	J
    //   365: invokespecial 539	bqo:a	(Lbzu;J)J
    //   368: aload_0
    //   369: getfield 89	bqo:o	Lbqq;
    //   372: getfield 540	bqq:c	J
    //   375: invokespecial 543	bqq:<init>	(Lbzu;JJ)V
    //   378: putfield 89	bqo:o	Lbqq;
    //   381: iconst_1
    //   382: ireturn
    //   383: aload_1
    //   384: getfield 546	android/os/Message:obj	Ljava/lang/Object;
    //   387: checkcast 548	[Lbql;
    //   390: astore 15
    //   392: aload 15
    //   394: arraylength
    //   395: istore_3
    //   396: iload_2
    //   397: iload_3
    //   398: if_icmpge +32 -> 430
    //   401: aload 15
    //   403: iload_2
    //   404: aaload
    //   405: astore_1
    //   406: aload_1
    //   407: getfield 553	bql:a	Lbqk;
    //   410: aload_1
    //   411: getfield 554	bql:b	I
    //   414: aload_1
    //   415: getfield 556	bql:c	Ljava/lang/Object;
    //   418: invokeinterface 561 3 0
    //   423: iload_2
    //   424: iconst_1
    //   425: iadd
    //   426: istore_2
    //   427: goto -31 -> 396
    //   430: aload_0
    //   431: getfield 87	bqo:x	I
    //   434: iconst_3
    //   435: if_icmpeq +11 -> 446
    //   438: aload_0
    //   439: getfield 87	bqo:x	I
    //   442: iconst_2
    //   443: if_icmpne +12 -> 455
    //   446: aload_0
    //   447: getfield 159	bqo:a	Landroid/os/Handler;
    //   450: iconst_2
    //   451: invokevirtual 243	android/os/Handler:sendEmptyMessage	(I)Z
    //   454: pop
    //   455: aload_0
    //   456: monitorenter
    //   457: aload_0
    //   458: aload_0
    //   459: getfield 521	bqo:z	I
    //   462: iconst_1
    //   463: iadd
    //   464: putfield 521	bqo:z	I
    //   467: aload_0
    //   468: invokevirtual 564	java/lang/Object:notifyAll	()V
    //   471: aload_0
    //   472: monitorexit
    //   473: iconst_1
    //   474: ireturn
    //   475: astore_1
    //   476: aload_0
    //   477: monitorexit
    //   478: aload_1
    //   479: athrow
    //   480: astore_1
    //   481: aload_0
    //   482: monitorenter
    //   483: aload_0
    //   484: aload_0
    //   485: getfield 521	bqo:z	I
    //   488: iconst_1
    //   489: iadd
    //   490: putfield 521	bqo:z	I
    //   493: aload_0
    //   494: invokevirtual 564	java/lang/Object:notifyAll	()V
    //   497: aload_0
    //   498: monitorexit
    //   499: aload_1
    //   500: athrow
    //   501: astore_1
    //   502: aload_0
    //   503: monitorexit
    //   504: aload_1
    //   505: athrow
    //   506: aload_0
    //   507: getfield 186	bqo:G	Lbqp;
    //   510: ifnull +4163 -> 4673
    //   513: aload_0
    //   514: getfield 186	bqo:G	Lbqp;
    //   517: astore_1
    //   518: iconst_1
    //   519: istore_2
    //   520: aload_1
    //   521: ifnull +4152 -> 4673
    //   524: aload_1
    //   525: getfield 207	bqp:g	Z
    //   528: ifne +5 -> 533
    //   531: iconst_1
    //   532: ireturn
    //   533: aload_1
    //   534: invokevirtual 566	bqp:c	()Z
    //   537: ifne +21 -> 558
    //   540: aload_1
    //   541: aload_0
    //   542: getfield 215	bqo:F	Lbqp;
    //   545: if_acmpne +5 -> 550
    //   548: iconst_0
    //   549: istore_2
    //   550: aload_1
    //   551: getfield 213	bqp:i	Lbqp;
    //   554: astore_1
    //   555: goto -35 -> 520
    //   558: iload_2
    //   559: ifeq +307 -> 866
    //   562: aload_0
    //   563: getfield 215	bqo:F	Lbqp;
    //   566: aload_0
    //   567: getfield 186	bqo:G	Lbqp;
    //   570: if_acmpeq +4080 -> 4650
    //   573: iconst_1
    //   574: istore 6
    //   576: goto +3 -> 579
    //   579: aload_0
    //   580: getfield 186	bqo:G	Lbqp;
    //   583: getfield 213	bqp:i	Lbqp;
    //   586: invokestatic 440	bqo:a	(Lbqp;)V
    //   589: aload_0
    //   590: getfield 186	bqo:G	Lbqp;
    //   593: aconst_null
    //   594: putfield 213	bqp:i	Lbqp;
    //   597: aload_0
    //   598: aload_0
    //   599: getfield 186	bqo:G	Lbqp;
    //   602: putfield 188	bqo:E	Lbqp;
    //   605: aload_0
    //   606: aload_0
    //   607: getfield 186	bqo:G	Lbqp;
    //   610: putfield 215	bqo:F	Lbqp;
    //   613: aload_0
    //   614: getfield 75	bqo:d	[Lbrc;
    //   617: arraylength
    //   618: newarray boolean
    //   620: astore 15
    //   622: aload_0
    //   623: getfield 186	bqo:G	Lbqp;
    //   626: aload_0
    //   627: getfield 89	bqo:o	Lbqq;
    //   630: getfield 452	bqq:d	J
    //   633: iload 6
    //   635: aload 15
    //   637: invokevirtual 569	bqp:a	(JZ[Z)J
    //   640: lstore 7
    //   642: lload 7
    //   644: aload_0
    //   645: getfield 89	bqo:o	Lbqq;
    //   648: getfield 452	bqq:d	J
    //   651: lcmp
    //   652: ifeq +18 -> 670
    //   655: aload_0
    //   656: getfield 89	bqo:o	Lbqq;
    //   659: lload 7
    //   661: putfield 452	bqq:d	J
    //   664: aload_0
    //   665: lload 7
    //   667: invokespecial 237	bqo:a	(J)V
    //   670: aload_0
    //   671: getfield 75	bqo:d	[Lbrc;
    //   674: arraylength
    //   675: newarray boolean
    //   677: astore 16
    //   679: iconst_0
    //   680: istore 4
    //   682: iconst_0
    //   683: istore_2
    //   684: iload 4
    //   686: aload_0
    //   687: getfield 75	bqo:d	[Lbrc;
    //   690: arraylength
    //   691: if_icmpge +150 -> 841
    //   694: aload_0
    //   695: getfield 75	bqo:d	[Lbrc;
    //   698: iload 4
    //   700: aaload
    //   701: astore 18
    //   703: aload 18
    //   705: invokeinterface 333 1 0
    //   710: ifeq +3946 -> 4656
    //   713: iconst_1
    //   714: istore 6
    //   716: goto +3 -> 719
    //   719: aload 16
    //   721: iload 4
    //   723: iload 6
    //   725: bastore
    //   726: aload_0
    //   727: getfield 186	bqo:G	Lbqp;
    //   730: getfield 384	bqp:d	[Lcaa;
    //   733: iload 4
    //   735: aaload
    //   736: astore 17
    //   738: iload_2
    //   739: istore_3
    //   740: aload 17
    //   742: ifnull +7 -> 749
    //   745: iload_2
    //   746: iconst_1
    //   747: iadd
    //   748: istore_3
    //   749: aload 16
    //   751: iload 4
    //   753: baload
    //   754: ifeq +3908 -> 4662
    //   757: aload 17
    //   759: aload 18
    //   761: invokeinterface 412 1 0
    //   766: if_acmpeq +53 -> 819
    //   769: aload 18
    //   771: aload_0
    //   772: getfield 221	bqo:q	Lbrc;
    //   775: if_acmpne +29 -> 804
    //   778: aload 17
    //   780: ifnonnull +14 -> 794
    //   783: aload_0
    //   784: getfield 108	bqo:h	Lcff;
    //   787: aload_0
    //   788: getfield 219	bqo:r	Lcev;
    //   791: invokevirtual 415	cff:a	(Lcev;)V
    //   794: aload_0
    //   795: aconst_null
    //   796: putfield 219	bqo:r	Lcev;
    //   799: aload_0
    //   800: aconst_null
    //   801: putfield 221	bqo:q	Lbrc;
    //   804: aload 18
    //   806: invokestatic 417	bqo:a	(Lbrc;)V
    //   809: aload 18
    //   811: invokeinterface 217 1 0
    //   816: goto +3846 -> 4662
    //   819: aload 15
    //   821: iload 4
    //   823: baload
    //   824: ifeq +3838 -> 4662
    //   827: aload 18
    //   829: aload_0
    //   830: getfield 315	bqo:D	J
    //   833: invokeinterface 317 3 0
    //   838: goto +3824 -> 4662
    //   841: aload_0
    //   842: getfield 85	bqo:j	Landroid/os/Handler;
    //   845: iconst_3
    //   846: aload_1
    //   847: getfield 360	bqp:j	Lcdn;
    //   850: invokevirtual 420	android/os/Handler:obtainMessage	(ILjava/lang/Object;)Landroid/os/Message;
    //   853: invokevirtual 308	android/os/Message:sendToTarget	()V
    //   856: aload_0
    //   857: aload 16
    //   859: iload_2
    //   860: invokespecial 422	bqo:a	([ZI)V
    //   863: goto +93 -> 956
    //   866: aload_0
    //   867: aload_1
    //   868: putfield 188	bqo:E	Lbqp;
    //   871: aload_0
    //   872: getfield 188	bqo:E	Lbqp;
    //   875: getfield 213	bqp:i	Lbqp;
    //   878: astore_1
    //   879: aload_1
    //   880: ifnull +15 -> 895
    //   883: aload_1
    //   884: invokevirtual 191	bqp:d	()V
    //   887: aload_1
    //   888: getfield 213	bqp:i	Lbqp;
    //   891: astore_1
    //   892: goto -13 -> 879
    //   895: aload_0
    //   896: getfield 188	bqo:E	Lbqp;
    //   899: aconst_null
    //   900: putfield 213	bqp:i	Lbqp;
    //   903: aload_0
    //   904: getfield 188	bqo:E	Lbqp;
    //   907: getfield 207	bqp:g	Z
    //   910: ifeq +46 -> 956
    //   913: aload_0
    //   914: getfield 188	bqo:E	Lbqp;
    //   917: getfield 194	bqp:f	Lbqy;
    //   920: getfield 570	bqy:b	J
    //   923: lstore 7
    //   925: aload_0
    //   926: getfield 188	bqo:E	Lbqp;
    //   929: astore_1
    //   930: lload 7
    //   932: aload_0
    //   933: getfield 315	bqo:D	J
    //   936: aload_1
    //   937: invokevirtual 313	bqp:a	()J
    //   940: lsub
    //   941: invokestatic 576	java/lang/Math:max	(JJ)J
    //   944: lstore 7
    //   946: aload_0
    //   947: getfield 188	bqo:E	Lbqp;
    //   950: lload 7
    //   952: invokevirtual 578	bqp:a	(J)J
    //   955: pop2
    //   956: aload_0
    //   957: invokespecial 239	bqo:i	()V
    //   960: aload_0
    //   961: invokespecial 579	bqo:e	()V
    //   964: aload_0
    //   965: getfield 159	bqo:a	Landroid/os/Handler;
    //   968: iconst_2
    //   969: invokevirtual 243	android/os/Handler:sendEmptyMessage	(I)Z
    //   972: pop
    //   973: iconst_1
    //   974: ireturn
    //   975: aload_1
    //   976: getfield 546	android/os/Message:obj	Ljava/lang/Object;
    //   979: checkcast 231	bzq
    //   982: astore_1
    //   983: aload_0
    //   984: getfield 188	bqo:E	Lbqp;
    //   987: ifnull +3688 -> 4675
    //   990: aload_0
    //   991: getfield 188	bqo:E	Lbqp;
    //   994: getfield 229	bqp:a	Lbzq;
    //   997: aload_1
    //   998: if_acmpeq +5 -> 1003
    //   1001: iconst_1
    //   1002: ireturn
    //   1003: aload_0
    //   1004: invokespecial 239	bqo:i	()V
    //   1007: iconst_1
    //   1008: ireturn
    //   1009: aload_1
    //   1010: getfield 546	android/os/Message:obj	Ljava/lang/Object;
    //   1013: checkcast 231	bzq
    //   1016: astore_1
    //   1017: aload_0
    //   1018: getfield 188	bqo:E	Lbqp;
    //   1021: ifnull +3656 -> 4677
    //   1024: aload_0
    //   1025: getfield 188	bqo:E	Lbqp;
    //   1028: getfield 229	bqp:a	Lbzq;
    //   1031: aload_1
    //   1032: if_acmpeq +5 -> 1037
    //   1035: iconst_1
    //   1036: ireturn
    //   1037: aload_0
    //   1038: getfield 188	bqo:E	Lbqp;
    //   1041: astore_1
    //   1042: aload_1
    //   1043: iconst_1
    //   1044: putfield 207	bqp:g	Z
    //   1047: aload_1
    //   1048: invokevirtual 566	bqp:c	()Z
    //   1051: pop
    //   1052: aload_1
    //   1053: aload_1
    //   1054: getfield 194	bqp:f	Lbqy;
    //   1057: getfield 570	bqy:b	J
    //   1060: invokevirtual 578	bqp:a	(J)J
    //   1063: lstore 7
    //   1065: aload_1
    //   1066: getfield 194	bqp:f	Lbqy;
    //   1069: astore 15
    //   1071: aload_1
    //   1072: new 196	bqy
    //   1075: dup
    //   1076: aload 15
    //   1078: getfield 199	bqy:a	Lbzu;
    //   1081: lload 7
    //   1083: aload 15
    //   1085: getfield 580	bqy:c	J
    //   1088: aload 15
    //   1090: getfield 581	bqy:d	J
    //   1093: aload 15
    //   1095: getfield 474	bqy:e	J
    //   1098: aload 15
    //   1100: getfield 299	bqy:f	Z
    //   1103: aload 15
    //   1105: getfield 582	bqy:g	Z
    //   1108: invokespecial 585	bqy:<init>	(Lbzu;JJJJZZ)V
    //   1111: putfield 194	bqp:f	Lbqy;
    //   1114: aload_0
    //   1115: getfield 186	bqo:G	Lbqp;
    //   1118: ifnonnull +33 -> 1151
    //   1121: aload_0
    //   1122: aload_0
    //   1123: getfield 188	bqo:E	Lbqp;
    //   1126: putfield 215	bqo:F	Lbqp;
    //   1129: aload_0
    //   1130: aload_0
    //   1131: getfield 215	bqo:F	Lbqp;
    //   1134: getfield 194	bqp:f	Lbqy;
    //   1137: getfield 570	bqy:b	J
    //   1140: invokespecial 237	bqo:a	(J)V
    //   1143: aload_0
    //   1144: aload_0
    //   1145: getfield 215	bqo:F	Lbqp;
    //   1148: invokespecial 224	bqo:b	(Lbqp;)V
    //   1151: aload_0
    //   1152: invokespecial 239	bqo:i	()V
    //   1155: iconst_1
    //   1156: ireturn
    //   1157: aload_1
    //   1158: getfield 546	android/os/Message:obj	Ljava/lang/Object;
    //   1161: checkcast 262	android/util/Pair
    //   1164: astore_1
    //   1165: aload_0
    //   1166: getfield 209	bqo:H	Lbrj;
    //   1169: astore 17
    //   1171: aload_0
    //   1172: aload_1
    //   1173: getfield 265	android/util/Pair:first	Ljava/lang/Object;
    //   1176: checkcast 163	brj
    //   1179: putfield 209	bqo:H	Lbrj;
    //   1182: aload_0
    //   1183: getfield 125	bqo:n	Lbqx;
    //   1186: aload_0
    //   1187: getfield 209	bqo:H	Lbrj;
    //   1190: putfield 449	bqx:c	Lbrj;
    //   1193: aload_1
    //   1194: getfield 277	android/util/Pair:second	Ljava/lang/Object;
    //   1197: astore 16
    //   1199: aload 17
    //   1201: ifnonnull +225 -> 1426
    //   1204: aload_0
    //   1205: getfield 587	bqo:B	I
    //   1208: ifle +110 -> 1318
    //   1211: aload_0
    //   1212: aload_0
    //   1213: getfield 589	bqo:C	Lbqr;
    //   1216: invokespecial 591	bqo:a	(Lbqr;)Landroid/util/Pair;
    //   1219: astore_1
    //   1220: aload_0
    //   1221: getfield 587	bqo:B	I
    //   1224: istore_2
    //   1225: aload_0
    //   1226: iconst_0
    //   1227: putfield 587	bqo:B	I
    //   1230: aload_0
    //   1231: aconst_null
    //   1232: putfield 589	bqo:C	Lbqr;
    //   1235: aload_1
    //   1236: ifnonnull +12 -> 1248
    //   1239: aload_0
    //   1240: aload 16
    //   1242: iload_2
    //   1243: invokespecial 593	bqo:a	(Ljava/lang/Object;I)V
    //   1246: iconst_1
    //   1247: ireturn
    //   1248: aload_1
    //   1249: getfield 265	android/util/Pair:first	Ljava/lang/Object;
    //   1252: checkcast 267	java/lang/Integer
    //   1255: invokevirtual 270	java/lang/Integer:intValue	()I
    //   1258: istore_3
    //   1259: aload_1
    //   1260: getfield 277	android/util/Pair:second	Ljava/lang/Object;
    //   1263: checkcast 595	java/lang/Long
    //   1266: invokevirtual 598	java/lang/Long:longValue	()J
    //   1269: lstore 9
    //   1271: aload_0
    //   1272: getfield 125	bqo:n	Lbqx;
    //   1275: iload_3
    //   1276: invokevirtual 601	bqx:a	(I)Lbzu;
    //   1279: astore_1
    //   1280: aload_1
    //   1281: invokevirtual 453	bzu:a	()Z
    //   1284: ifeq +3395 -> 4679
    //   1287: lconst_0
    //   1288: lstore 7
    //   1290: goto +3 -> 1293
    //   1293: aload_0
    //   1294: new 338	bqq
    //   1297: dup
    //   1298: aload_1
    //   1299: lload 7
    //   1301: lload 9
    //   1303: invokespecial 543	bqq:<init>	(Lbzu;JJ)V
    //   1306: putfield 89	bqo:o	Lbqq;
    //   1309: aload_0
    //   1310: aload 16
    //   1312: iload_2
    //   1313: invokespecial 342	bqo:b	(Ljava/lang/Object;I)V
    //   1316: iconst_1
    //   1317: ireturn
    //   1318: aload_0
    //   1319: getfield 89	bqo:o	Lbqq;
    //   1322: getfield 602	bqq:b	J
    //   1325: ldc2_w 343
    //   1328: lcmp
    //   1329: ifne +88 -> 1417
    //   1332: aload_0
    //   1333: getfield 209	bqo:H	Lbrj;
    //   1336: invokevirtual 253	brj:a	()Z
    //   1339: ifeq +12 -> 1351
    //   1342: aload_0
    //   1343: aload 16
    //   1345: iconst_0
    //   1346: invokespecial 593	bqo:a	(Ljava/lang/Object;I)V
    //   1349: iconst_1
    //   1350: ireturn
    //   1351: aload_0
    //   1352: invokespecial 286	bqo:h	()Landroid/util/Pair;
    //   1355: astore_1
    //   1356: aload_1
    //   1357: getfield 265	android/util/Pair:first	Ljava/lang/Object;
    //   1360: checkcast 267	java/lang/Integer
    //   1363: invokevirtual 270	java/lang/Integer:intValue	()I
    //   1366: istore_2
    //   1367: aload_1
    //   1368: getfield 277	android/util/Pair:second	Ljava/lang/Object;
    //   1371: checkcast 595	java/lang/Long
    //   1374: invokevirtual 598	java/lang/Long:longValue	()J
    //   1377: lstore 9
    //   1379: aload_0
    //   1380: getfield 125	bqo:n	Lbqx;
    //   1383: iload_2
    //   1384: invokevirtual 601	bqx:a	(I)Lbzu;
    //   1387: astore_1
    //   1388: aload_1
    //   1389: invokevirtual 453	bzu:a	()Z
    //   1392: ifeq +3294 -> 4686
    //   1395: lconst_0
    //   1396: lstore 7
    //   1398: goto +3 -> 1401
    //   1401: aload_0
    //   1402: new 338	bqq
    //   1405: dup
    //   1406: aload_1
    //   1407: lload 7
    //   1409: lload 9
    //   1411: invokespecial 543	bqq:<init>	(Lbzu;JJ)V
    //   1414: putfield 89	bqo:o	Lbqq;
    //   1417: aload_0
    //   1418: aload 16
    //   1420: iconst_0
    //   1421: invokespecial 342	bqo:b	(Ljava/lang/Object;I)V
    //   1424: iconst_1
    //   1425: ireturn
    //   1426: aload_0
    //   1427: getfield 89	bqo:o	Lbqq;
    //   1430: getfield 603	bqq:a	Lbzu;
    //   1433: getfield 211	bzu:a	I
    //   1436: istore_3
    //   1437: aload_0
    //   1438: getfield 186	bqo:G	Lbqp;
    //   1441: ifnull +11 -> 1452
    //   1444: aload_0
    //   1445: getfield 186	bqo:G	Lbqp;
    //   1448: astore_1
    //   1449: goto +8 -> 1457
    //   1452: aload_0
    //   1453: getfield 188	bqo:E	Lbqp;
    //   1456: astore_1
    //   1457: aload_1
    //   1458: ifnonnull +12 -> 1470
    //   1461: iload_3
    //   1462: aload 17
    //   1464: invokevirtual 166	brj:c	()I
    //   1467: if_icmpge +606 -> 2073
    //   1470: aload_1
    //   1471: ifnonnull +22 -> 1493
    //   1474: aload 17
    //   1476: iload_3
    //   1477: aload_0
    //   1478: getfield 120	bqo:m	Lbrk;
    //   1481: iconst_1
    //   1482: invokevirtual 172	brj:a	(ILbrk;Z)Lbrk;
    //   1485: getfield 175	brk:a	Ljava/lang/Object;
    //   1488: astore 15
    //   1490: goto +9 -> 1499
    //   1493: aload_1
    //   1494: getfield 605	bqp:b	Ljava/lang/Object;
    //   1497: astore 15
    //   1499: aload_0
    //   1500: getfield 209	bqo:H	Lbrj;
    //   1503: aload 15
    //   1505: invokevirtual 178	brj:a	(Ljava/lang/Object;)I
    //   1508: istore_2
    //   1509: iload_2
    //   1510: iconst_m1
    //   1511: if_icmpne +200 -> 1711
    //   1514: aload_0
    //   1515: iload_3
    //   1516: aload 17
    //   1518: aload_0
    //   1519: getfield 209	bqo:H	Lbrj;
    //   1522: invokespecial 283	bqo:a	(ILbrj;Lbrj;)I
    //   1525: istore_2
    //   1526: iload_2
    //   1527: iconst_m1
    //   1528: if_icmpne +12 -> 1540
    //   1531: aload_0
    //   1532: aload 16
    //   1534: iconst_0
    //   1535: invokespecial 593	bqo:a	(Ljava/lang/Object;I)V
    //   1538: iconst_1
    //   1539: ireturn
    //   1540: aload_0
    //   1541: getfield 209	bqo:H	Lbrj;
    //   1544: iload_2
    //   1545: aload_0
    //   1546: getfield 120	bqo:m	Lbrk;
    //   1549: iconst_0
    //   1550: invokevirtual 172	brj:a	(ILbrk;Z)Lbrk;
    //   1553: pop
    //   1554: aload_0
    //   1555: invokespecial 286	bqo:h	()Landroid/util/Pair;
    //   1558: astore 15
    //   1560: aload 15
    //   1562: getfield 265	android/util/Pair:first	Ljava/lang/Object;
    //   1565: checkcast 267	java/lang/Integer
    //   1568: invokevirtual 270	java/lang/Integer:intValue	()I
    //   1571: istore_2
    //   1572: aload 15
    //   1574: getfield 277	android/util/Pair:second	Ljava/lang/Object;
    //   1577: checkcast 595	java/lang/Long
    //   1580: invokevirtual 598	java/lang/Long:longValue	()J
    //   1583: lstore 7
    //   1585: aload_0
    //   1586: getfield 209	bqo:H	Lbrj;
    //   1589: iload_2
    //   1590: aload_0
    //   1591: getfield 120	bqo:m	Lbrk;
    //   1594: iconst_1
    //   1595: invokevirtual 172	brj:a	(ILbrk;Z)Lbrk;
    //   1598: pop
    //   1599: aload_1
    //   1600: ifnull +80 -> 1680
    //   1603: aload_0
    //   1604: getfield 120	bqo:m	Lbrk;
    //   1607: getfield 175	brk:a	Ljava/lang/Object;
    //   1610: astore 15
    //   1612: aload_1
    //   1613: aload_1
    //   1614: getfield 194	bqp:f	Lbqy;
    //   1617: invokevirtual 608	bqy:a	()Lbqy;
    //   1620: putfield 194	bqp:f	Lbqy;
    //   1623: aload_1
    //   1624: getfield 213	bqp:i	Lbqp;
    //   1627: ifnull +53 -> 1680
    //   1630: aload_1
    //   1631: getfield 213	bqp:i	Lbqp;
    //   1634: astore_1
    //   1635: aload_1
    //   1636: getfield 605	bqp:b	Ljava/lang/Object;
    //   1639: aload 15
    //   1641: invokevirtual 609	java/lang/Object:equals	(Ljava/lang/Object;)Z
    //   1644: ifeq +22 -> 1666
    //   1647: aload_1
    //   1648: aload_0
    //   1649: getfield 125	bqo:n	Lbqx;
    //   1652: aload_1
    //   1653: getfield 194	bqp:f	Lbqy;
    //   1656: iload_2
    //   1657: invokevirtual 297	bqx:a	(Lbqy;I)Lbqy;
    //   1660: putfield 194	bqp:f	Lbqy;
    //   1663: goto -40 -> 1623
    //   1666: aload_1
    //   1667: aload_1
    //   1668: getfield 194	bqp:f	Lbqy;
    //   1671: invokevirtual 608	bqy:a	()Lbqy;
    //   1674: putfield 194	bqp:f	Lbqy;
    //   1677: goto -54 -> 1623
    //   1680: new 201	bzu
    //   1683: dup
    //   1684: iload_2
    //   1685: invokespecial 611	bzu:<init>	(I)V
    //   1688: astore_1
    //   1689: aload_0
    //   1690: new 338	bqq
    //   1693: dup
    //   1694: aload_1
    //   1695: aload_0
    //   1696: aload_1
    //   1697: lload 7
    //   1699: invokespecial 539	bqo:a	(Lbzu;J)J
    //   1702: invokespecial 614	bqq:<init>	(Lbzu;J)V
    //   1705: putfield 89	bqo:o	Lbqq;
    //   1708: goto +365 -> 2073
    //   1711: iload_2
    //   1712: iload_3
    //   1713: if_icmpeq +63 -> 1776
    //   1716: aload_0
    //   1717: getfield 89	bqo:o	Lbqq;
    //   1720: astore 15
    //   1722: new 338	bqq
    //   1725: dup
    //   1726: aload 15
    //   1728: getfield 603	bqq:a	Lbzu;
    //   1731: iload_2
    //   1732: invokevirtual 615	bzu:a	(I)Lbzu;
    //   1735: aload 15
    //   1737: getfield 602	bqq:b	J
    //   1740: aload 15
    //   1742: getfield 540	bqq:c	J
    //   1745: invokespecial 543	bqq:<init>	(Lbzu;JJ)V
    //   1748: astore 17
    //   1750: aload 17
    //   1752: aload 15
    //   1754: getfield 452	bqq:d	J
    //   1757: putfield 452	bqq:d	J
    //   1760: aload 17
    //   1762: aload 15
    //   1764: getfield 475	bqq:e	J
    //   1767: putfield 475	bqq:e	J
    //   1770: aload_0
    //   1771: aload 17
    //   1773: putfield 89	bqo:o	Lbqq;
    //   1776: aload_0
    //   1777: getfield 89	bqo:o	Lbqq;
    //   1780: getfield 603	bqq:a	Lbzu;
    //   1783: invokevirtual 453	bzu:a	()Z
    //   1786: ifeq +94 -> 1880
    //   1789: aload_0
    //   1790: getfield 125	bqo:n	Lbqx;
    //   1793: iload_2
    //   1794: invokevirtual 601	bqx:a	(I)Lbzu;
    //   1797: astore 15
    //   1799: aload 15
    //   1801: invokevirtual 453	bzu:a	()Z
    //   1804: ifeq +21 -> 1825
    //   1807: aload 15
    //   1809: getfield 616	bzu:c	I
    //   1812: aload_0
    //   1813: getfield 89	bqo:o	Lbqq;
    //   1816: getfield 603	bqq:a	Lbzu;
    //   1819: getfield 616	bzu:c	I
    //   1822: if_icmpeq +58 -> 1880
    //   1825: aload_0
    //   1826: aload 15
    //   1828: aload_0
    //   1829: getfield 89	bqo:o	Lbqq;
    //   1832: getfield 540	bqq:c	J
    //   1835: invokespecial 539	bqo:a	(Lbzu;J)J
    //   1838: lstore 9
    //   1840: aload 15
    //   1842: invokevirtual 453	bzu:a	()Z
    //   1845: ifeq +2848 -> 4693
    //   1848: aload_0
    //   1849: getfield 89	bqo:o	Lbqq;
    //   1852: getfield 540	bqq:c	J
    //   1855: lstore 7
    //   1857: goto +3 -> 1860
    //   1860: aload_0
    //   1861: new 338	bqq
    //   1864: dup
    //   1865: aload 15
    //   1867: lload 9
    //   1869: lload 7
    //   1871: invokespecial 543	bqq:<init>	(Lbzu;JJ)V
    //   1874: putfield 89	bqo:o	Lbqq;
    //   1877: goto +196 -> 2073
    //   1880: aload_1
    //   1881: ifnull +192 -> 2073
    //   1884: aload_0
    //   1885: aload_1
    //   1886: iload_2
    //   1887: invokespecial 618	bqo:a	(Lbqp;I)Lbqp;
    //   1890: astore_1
    //   1891: aload_1
    //   1892: getfield 213	bqp:i	Lbqp;
    //   1895: ifnull +178 -> 2073
    //   1898: aload_1
    //   1899: getfield 213	bqp:i	Lbqp;
    //   1902: astore 15
    //   1904: aload_0
    //   1905: getfield 209	bqo:H	Lbrj;
    //   1908: iload_2
    //   1909: aload_0
    //   1910: getfield 120	bqo:m	Lbrk;
    //   1913: aload_0
    //   1914: getfield 115	bqo:l	Lbrl;
    //   1917: aload_0
    //   1918: getfield 83	bqo:y	I
    //   1921: invokevirtual 169	brj:a	(ILbrk;Lbrl;I)I
    //   1924: istore_2
    //   1925: iload_2
    //   1926: iconst_m1
    //   1927: if_icmpeq +41 -> 1968
    //   1930: aload 15
    //   1932: getfield 605	bqp:b	Ljava/lang/Object;
    //   1935: aload_0
    //   1936: getfield 209	bqo:H	Lbrj;
    //   1939: iload_2
    //   1940: aload_0
    //   1941: getfield 120	bqo:m	Lbrk;
    //   1944: iconst_1
    //   1945: invokevirtual 172	brj:a	(ILbrk;Z)Lbrk;
    //   1948: getfield 175	brk:a	Ljava/lang/Object;
    //   1951: invokevirtual 609	java/lang/Object:equals	(Ljava/lang/Object;)Z
    //   1954: ifeq +14 -> 1968
    //   1957: aload_0
    //   1958: aload 15
    //   1960: iload_2
    //   1961: invokespecial 618	bqo:a	(Lbqp;I)Lbqp;
    //   1964: astore_1
    //   1965: goto -74 -> 1891
    //   1968: aload_0
    //   1969: getfield 215	bqo:F	Lbqp;
    //   1972: ifnull +2729 -> 4701
    //   1975: aload_0
    //   1976: getfield 215	bqo:F	Lbqp;
    //   1979: getfield 534	bqp:c	I
    //   1982: aload 15
    //   1984: getfield 534	bqp:c	I
    //   1987: if_icmpge +2714 -> 4701
    //   1990: iconst_1
    //   1991: istore_2
    //   1992: goto +3 -> 1995
    //   1995: iload_2
    //   1996: ifne +59 -> 2055
    //   1999: aload_0
    //   2000: aload_0
    //   2001: getfield 186	bqo:G	Lbqp;
    //   2004: getfield 194	bqp:f	Lbqy;
    //   2007: getfield 199	bqy:a	Lbzu;
    //   2010: aload_0
    //   2011: getfield 89	bqo:o	Lbqq;
    //   2014: getfield 452	bqq:d	J
    //   2017: invokespecial 539	bqo:a	(Lbzu;J)J
    //   2020: lstore 7
    //   2022: aload_0
    //   2023: new 338	bqq
    //   2026: dup
    //   2027: aload_0
    //   2028: getfield 186	bqo:G	Lbqp;
    //   2031: getfield 194	bqp:f	Lbqy;
    //   2034: getfield 199	bqy:a	Lbzu;
    //   2037: lload 7
    //   2039: aload_0
    //   2040: getfield 89	bqo:o	Lbqq;
    //   2043: getfield 540	bqq:c	J
    //   2046: invokespecial 543	bqq:<init>	(Lbzu;JJ)V
    //   2049: putfield 89	bqo:o	Lbqq;
    //   2052: goto +21 -> 2073
    //   2055: aload_0
    //   2056: aload_1
    //   2057: putfield 188	bqo:E	Lbqp;
    //   2060: aload_0
    //   2061: getfield 188	bqo:E	Lbqp;
    //   2064: aconst_null
    //   2065: putfield 213	bqp:i	Lbqp;
    //   2068: aload 15
    //   2070: invokestatic 440	bqo:a	(Lbqp;)V
    //   2073: aload_0
    //   2074: aload 16
    //   2076: iconst_0
    //   2077: invokespecial 342	bqo:b	(Ljava/lang/Object;I)V
    //   2080: iconst_1
    //   2081: ireturn
    //   2082: aload_0
    //   2083: iconst_1
    //   2084: invokespecial 347	bqo:b	(Z)V
    //   2087: aload_0
    //   2088: getfield 79	bqo:g	Lbqw;
    //   2091: invokeinterface 620 1 0
    //   2096: aload_0
    //   2097: iconst_1
    //   2098: invokespecial 184	bqo:a	(I)V
    //   2101: aload_0
    //   2102: monitorenter
    //   2103: aload_0
    //   2104: iconst_1
    //   2105: putfield 497	bqo:b	Z
    //   2108: aload_0
    //   2109: invokevirtual 564	java/lang/Object:notifyAll	()V
    //   2112: aload_0
    //   2113: monitorexit
    //   2114: iconst_1
    //   2115: ireturn
    //   2116: astore_1
    //   2117: aload_0
    //   2118: monitorexit
    //   2119: aload_1
    //   2120: athrow
    //   2121: aload_0
    //   2122: invokespecial 622	bqo:f	()V
    //   2125: iconst_1
    //   2126: ireturn
    //   2127: aload_1
    //   2128: getfield 546	android/os/Message:obj	Ljava/lang/Object;
    //   2131: checkcast 132	bqz
    //   2134: astore_1
    //   2135: aload_0
    //   2136: getfield 219	bqo:r	Lcev;
    //   2139: ifnull +17 -> 2156
    //   2142: aload_0
    //   2143: getfield 219	bqo:r	Lcev;
    //   2146: aload_1
    //   2147: invokeinterface 405 2 0
    //   2152: astore_1
    //   2153: goto +12 -> 2165
    //   2156: aload_0
    //   2157: getfield 108	bqo:h	Lcff;
    //   2160: aload_1
    //   2161: invokevirtual 623	cff:a	(Lbqz;)Lbqz;
    //   2164: astore_1
    //   2165: aload_0
    //   2166: aload_1
    //   2167: putfield 136	bqo:p	Lbqz;
    //   2170: aload_0
    //   2171: getfield 85	bqo:j	Landroid/os/Handler;
    //   2174: bipush 7
    //   2176: aload_1
    //   2177: invokevirtual 420	android/os/Handler:obtainMessage	(ILjava/lang/Object;)Landroid/os/Message;
    //   2180: invokevirtual 308	android/os/Message:sendToTarget	()V
    //   2183: iconst_1
    //   2184: ireturn
    //   2185: aload_1
    //   2186: getfield 546	android/os/Message:obj	Ljava/lang/Object;
    //   2189: checkcast 248	bqr
    //   2192: astore 15
    //   2194: aload_0
    //   2195: getfield 209	bqo:H	Lbrj;
    //   2198: ifnonnull +21 -> 2219
    //   2201: aload_0
    //   2202: aload_0
    //   2203: getfield 587	bqo:B	I
    //   2206: iconst_1
    //   2207: iadd
    //   2208: putfield 587	bqo:B	I
    //   2211: aload_0
    //   2212: aload 15
    //   2214: putfield 589	bqo:C	Lbqr;
    //   2217: iconst_1
    //   2218: ireturn
    //   2219: aload_0
    //   2220: aload 15
    //   2222: invokespecial 591	bqo:a	(Lbqr;)Landroid/util/Pair;
    //   2225: astore_1
    //   2226: aload_1
    //   2227: ifnonnull +58 -> 2285
    //   2230: aload_0
    //   2231: new 338	bqq
    //   2234: dup
    //   2235: lconst_0
    //   2236: invokespecial 340	bqq:<init>	(J)V
    //   2239: putfield 89	bqo:o	Lbqq;
    //   2242: aload_0
    //   2243: getfield 85	bqo:j	Landroid/os/Handler;
    //   2246: iconst_4
    //   2247: iconst_1
    //   2248: iconst_0
    //   2249: aload_0
    //   2250: getfield 89	bqo:o	Lbqq;
    //   2253: invokevirtual 626	android/os/Handler:obtainMessage	(IIILjava/lang/Object;)Landroid/os/Message;
    //   2256: invokevirtual 308	android/os/Message:sendToTarget	()V
    //   2259: aload_0
    //   2260: new 338	bqq
    //   2263: dup
    //   2264: ldc2_w 343
    //   2267: invokespecial 340	bqq:<init>	(J)V
    //   2270: putfield 89	bqo:o	Lbqq;
    //   2273: aload_0
    //   2274: iconst_4
    //   2275: invokespecial 184	bqo:a	(I)V
    //   2278: aload_0
    //   2279: iconst_0
    //   2280: invokespecial 347	bqo:b	(Z)V
    //   2283: iconst_1
    //   2284: ireturn
    //   2285: aload 15
    //   2287: getfield 257	bqr:c	J
    //   2290: ldc2_w 343
    //   2293: lcmp
    //   2294: ifne +2412 -> 4706
    //   2297: iconst_1
    //   2298: istore_2
    //   2299: goto +3 -> 2302
    //   2302: aload_1
    //   2303: getfield 265	android/util/Pair:first	Ljava/lang/Object;
    //   2306: checkcast 267	java/lang/Integer
    //   2309: invokevirtual 270	java/lang/Integer:intValue	()I
    //   2312: istore_3
    //   2313: aload_1
    //   2314: getfield 277	android/util/Pair:second	Ljava/lang/Object;
    //   2317: checkcast 595	java/lang/Long
    //   2320: invokevirtual 598	java/lang/Long:longValue	()J
    //   2323: lstore 13
    //   2325: aload_0
    //   2326: getfield 125	bqo:n	Lbqx;
    //   2329: iload_3
    //   2330: invokevirtual 601	bqx:a	(I)Lbzu;
    //   2333: astore 15
    //   2335: aload 15
    //   2337: invokevirtual 453	bzu:a	()Z
    //   2340: istore 6
    //   2342: iload 6
    //   2344: ifeq +8 -> 2352
    //   2347: iconst_1
    //   2348: istore_2
    //   2349: goto +7 -> 2356
    //   2352: lload 13
    //   2354: lstore 7
    //   2356: lload 7
    //   2358: lstore 11
    //   2360: lload 7
    //   2362: lstore 9
    //   2364: aload 15
    //   2366: aload_0
    //   2367: getfield 89	bqo:o	Lbqq;
    //   2370: getfield 603	bqq:a	Lbzu;
    //   2373: invokevirtual 205	bzu:equals	(Ljava/lang/Object;)Z
    //   2376: ifeq +95 -> 2471
    //   2379: lload 7
    //   2381: lstore 9
    //   2383: lload 7
    //   2385: ldc2_w 465
    //   2388: ldiv
    //   2389: lstore 11
    //   2391: lload 7
    //   2393: lstore 9
    //   2395: aload_0
    //   2396: getfield 89	bqo:o	Lbqq;
    //   2399: astore_1
    //   2400: aload_1
    //   2401: getfield 452	bqq:d	J
    //   2404: ldc2_w 465
    //   2407: ldiv
    //   2408: lstore 9
    //   2410: lload 11
    //   2412: lload 9
    //   2414: lcmp
    //   2415: ifne +41 -> 2456
    //   2418: aload_0
    //   2419: new 338	bqq
    //   2422: dup
    //   2423: aload 15
    //   2425: lload 7
    //   2427: lload 13
    //   2429: invokespecial 543	bqq:<init>	(Lbzu;JJ)V
    //   2432: putfield 89	bqo:o	Lbqq;
    //   2435: aload_0
    //   2436: getfield 85	bqo:j	Landroid/os/Handler;
    //   2439: iconst_4
    //   2440: iload_2
    //   2441: iconst_0
    //   2442: aload_0
    //   2443: getfield 89	bqo:o	Lbqq;
    //   2446: invokevirtual 626	android/os/Handler:obtainMessage	(IIILjava/lang/Object;)Landroid/os/Message;
    //   2449: astore_1
    //   2450: aload_1
    //   2451: invokevirtual 308	android/os/Message:sendToTarget	()V
    //   2454: iconst_1
    //   2455: ireturn
    //   2456: lload 7
    //   2458: lstore 11
    //   2460: goto +11 -> 2471
    //   2463: astore_1
    //   2464: lload 7
    //   2466: lstore 9
    //   2468: goto +80 -> 2548
    //   2471: lload 11
    //   2473: lstore 9
    //   2475: aload_0
    //   2476: aload 15
    //   2478: lload 11
    //   2480: invokespecial 539	bqo:a	(Lbzu;J)J
    //   2483: lstore 7
    //   2485: lload 11
    //   2487: lload 7
    //   2489: lcmp
    //   2490: ifeq +8 -> 2498
    //   2493: iconst_1
    //   2494: istore_3
    //   2495: goto +5 -> 2500
    //   2498: iconst_0
    //   2499: istore_3
    //   2500: aload_0
    //   2501: new 338	bqq
    //   2504: dup
    //   2505: aload 15
    //   2507: lload 7
    //   2509: lload 13
    //   2511: invokespecial 543	bqq:<init>	(Lbzu;JJ)V
    //   2514: putfield 89	bqo:o	Lbqq;
    //   2517: aload_0
    //   2518: getfield 85	bqo:j	Landroid/os/Handler;
    //   2521: astore_1
    //   2522: iload_2
    //   2523: iload_3
    //   2524: ior
    //   2525: ifeq +2186 -> 4711
    //   2528: iconst_1
    //   2529: istore_2
    //   2530: goto +3 -> 2533
    //   2533: aload_1
    //   2534: iconst_4
    //   2535: iload_2
    //   2536: iconst_0
    //   2537: aload_0
    //   2538: getfield 89	bqo:o	Lbqq;
    //   2541: invokevirtual 626	android/os/Handler:obtainMessage	(IIILjava/lang/Object;)Landroid/os/Message;
    //   2544: astore_1
    //   2545: goto -95 -> 2450
    //   2548: aload_0
    //   2549: new 338	bqq
    //   2552: dup
    //   2553: aload 15
    //   2555: lload 9
    //   2557: lload 13
    //   2559: invokespecial 543	bqq:<init>	(Lbzu;JJ)V
    //   2562: putfield 89	bqo:o	Lbqq;
    //   2565: aload_0
    //   2566: getfield 85	bqo:j	Landroid/os/Handler;
    //   2569: iconst_4
    //   2570: iload_2
    //   2571: iconst_0
    //   2572: aload_0
    //   2573: getfield 89	bqo:o	Lbqq;
    //   2576: invokevirtual 626	android/os/Handler:obtainMessage	(IIILjava/lang/Object;)Landroid/os/Message;
    //   2579: invokevirtual 308	android/os/Message:sendToTarget	()V
    //   2582: aload_1
    //   2583: athrow
    //   2584: invokestatic 326	android/os/SystemClock:elapsedRealtime	()J
    //   2587: lstore 11
    //   2589: aload_0
    //   2590: getfield 209	bqo:H	Lbrj;
    //   2593: ifnull +2171 -> 4764
    //   2596: aload_0
    //   2597: getfield 188	bqo:E	Lbqp;
    //   2600: ifnonnull +37 -> 2637
    //   2603: aload_0
    //   2604: getfield 125	bqo:n	Lbqx;
    //   2607: astore_1
    //   2608: aload_0
    //   2609: getfield 89	bqo:o	Lbqq;
    //   2612: astore 15
    //   2614: aload_1
    //   2615: aload 15
    //   2617: getfield 603	bqq:a	Lbzu;
    //   2620: aload 15
    //   2622: getfield 540	bqq:c	J
    //   2625: aload 15
    //   2627: getfield 602	bqq:b	J
    //   2630: invokevirtual 629	bqx:a	(Lbzu;JJ)Lbqy;
    //   2633: astore_1
    //   2634: goto +374 -> 3008
    //   2637: aload_0
    //   2638: getfield 188	bqo:E	Lbqp;
    //   2641: getfield 194	bqp:f	Lbqy;
    //   2644: getfield 582	bqy:g	Z
    //   2647: ifne +550 -> 3197
    //   2650: aload_0
    //   2651: getfield 188	bqo:E	Lbqp;
    //   2654: invokevirtual 631	bqp:b	()Z
    //   2657: ifeq +540 -> 3197
    //   2660: aload_0
    //   2661: getfield 188	bqo:E	Lbqp;
    //   2664: getfield 194	bqp:f	Lbqy;
    //   2667: getfield 474	bqy:e	J
    //   2670: ldc2_w 343
    //   2673: lcmp
    //   2674: ifne +6 -> 2680
    //   2677: goto +520 -> 3197
    //   2680: aload_0
    //   2681: getfield 186	bqo:G	Lbqp;
    //   2684: ifnull +23 -> 2707
    //   2687: aload_0
    //   2688: getfield 188	bqo:E	Lbqp;
    //   2691: getfield 534	bqp:c	I
    //   2694: aload_0
    //   2695: getfield 186	bqo:G	Lbqp;
    //   2698: getfield 534	bqp:c	I
    //   2701: isub
    //   2702: bipush 100
    //   2704: if_icmpeq +493 -> 3197
    //   2707: aload_0
    //   2708: getfield 125	bqo:n	Lbqx;
    //   2711: astore 16
    //   2713: aload_0
    //   2714: getfield 188	bqo:E	Lbqp;
    //   2717: getfield 194	bqp:f	Lbqy;
    //   2720: astore 17
    //   2722: aload_0
    //   2723: getfield 188	bqo:E	Lbqp;
    //   2726: invokevirtual 313	bqp:a	()J
    //   2729: lstore 9
    //   2731: aload_0
    //   2732: getfield 315	bqo:D	J
    //   2735: lstore 7
    //   2737: aload 17
    //   2739: getfield 299	bqy:f	Z
    //   2742: ifeq +168 -> 2910
    //   2745: aload 16
    //   2747: getfield 449	bqx:c	Lbrj;
    //   2750: astore_1
    //   2751: aload_1
    //   2752: aload 17
    //   2754: getfield 199	bqy:a	Lbzu;
    //   2757: getfield 211	bzu:a	I
    //   2760: aload 16
    //   2762: getfield 633	bqx:a	Lbrk;
    //   2765: aload 16
    //   2767: getfield 635	bqx:b	Lbrl;
    //   2770: aload 16
    //   2772: getfield 533	bqx:d	I
    //   2775: invokevirtual 169	brj:a	(ILbrk;Lbrl;I)I
    //   2778: istore_2
    //   2779: iload_2
    //   2780: iconst_m1
    //   2781: if_icmpeq +1945 -> 4726
    //   2784: aload 16
    //   2786: getfield 449	bqx:c	Lbrj;
    //   2789: iload_2
    //   2790: aload 16
    //   2792: getfield 633	bqx:a	Lbrk;
    //   2795: iconst_0
    //   2796: invokevirtual 172	brj:a	(ILbrk;Z)Lbrk;
    //   2799: pop
    //   2800: aload 16
    //   2802: getfield 449	bqx:c	Lbrj;
    //   2805: iconst_0
    //   2806: aload 16
    //   2808: getfield 635	bqx:b	Lbrl;
    //   2811: invokevirtual 638	brj:a	(ILbrl;)Lbrl;
    //   2814: pop
    //   2815: iload_2
    //   2816: ifne +1904 -> 4720
    //   2819: aload 17
    //   2821: getfield 474	bqy:e	J
    //   2824: lstore 13
    //   2826: aload 16
    //   2828: getfield 449	bqx:c	Lbrj;
    //   2831: aload 16
    //   2833: getfield 635	bqx:b	Lbrl;
    //   2836: aload 16
    //   2838: getfield 633	bqx:a	Lbrk;
    //   2841: iconst_0
    //   2842: ldc2_w 343
    //   2845: lconst_0
    //   2846: lload 9
    //   2848: lload 13
    //   2850: ladd
    //   2851: lload 7
    //   2853: lsub
    //   2854: invokestatic 576	java/lang/Math:max	(JJ)J
    //   2857: invokevirtual 641	brj:a	(Lbrl;Lbrk;IJJ)Landroid/util/Pair;
    //   2860: astore_1
    //   2861: aload_1
    //   2862: ifnull +1864 -> 4726
    //   2865: aload_1
    //   2866: getfield 265	android/util/Pair:first	Ljava/lang/Object;
    //   2869: checkcast 267	java/lang/Integer
    //   2872: invokevirtual 270	java/lang/Integer:intValue	()I
    //   2875: istore_2
    //   2876: aload_1
    //   2877: getfield 277	android/util/Pair:second	Ljava/lang/Object;
    //   2880: checkcast 595	java/lang/Long
    //   2883: invokevirtual 598	java/lang/Long:longValue	()J
    //   2886: lstore 7
    //   2888: goto +3 -> 2891
    //   2891: aload 16
    //   2893: aload 16
    //   2895: iload_2
    //   2896: invokevirtual 601	bqx:a	(I)Lbzu;
    //   2899: lload 7
    //   2901: lload 7
    //   2903: invokevirtual 629	bqx:a	(Lbzu;JJ)Lbqy;
    //   2906: astore_1
    //   2907: goto +101 -> 3008
    //   2910: aload 17
    //   2912: getfield 199	bqy:a	Lbzu;
    //   2915: astore 18
    //   2917: aload 18
    //   2919: invokevirtual 453	bzu:a	()Z
    //   2922: ifeq +39 -> 2961
    //   2925: aload 18
    //   2927: getfield 642	bzu:b	I
    //   2930: istore_2
    //   2931: aload 16
    //   2933: getfield 449	bqx:c	Lbrj;
    //   2936: aload 18
    //   2938: getfield 211	bzu:a	I
    //   2941: aload 16
    //   2943: getfield 633	bqx:a	Lbrk;
    //   2946: iconst_0
    //   2947: invokevirtual 172	brj:a	(ILbrk;Z)Lbrk;
    //   2950: pop
    //   2951: aconst_null
    //   2952: astore_1
    //   2953: new 644	java/lang/NullPointerException
    //   2956: dup
    //   2957: invokespecial 645	java/lang/NullPointerException:<init>	()V
    //   2960: athrow
    //   2961: aconst_null
    //   2962: astore 15
    //   2964: aload 15
    //   2966: astore_1
    //   2967: aload 17
    //   2969: getfield 580	bqy:c	J
    //   2972: ldc2_w 469
    //   2975: lcmp
    //   2976: ifeq +32 -> 3008
    //   2979: aload 15
    //   2981: astore_1
    //   2982: iconst_m1
    //   2983: iconst_0
    //   2984: invokestatic 648	brk:a	(II)Z
    //   2987: ifeq +21 -> 3008
    //   2990: aload 16
    //   2992: aload 18
    //   2994: getfield 211	bzu:a	I
    //   2997: iconst_m1
    //   2998: iconst_0
    //   2999: aload 17
    //   3001: getfield 580	bqy:c	J
    //   3004: invokevirtual 651	bqx:a	(IIIJ)Lbqy;
    //   3007: astore_1
    //   3008: aload_1
    //   3009: ifnull +188 -> 3197
    //   3012: aload_0
    //   3013: getfield 188	bqo:E	Lbqp;
    //   3016: ifnonnull +11 -> 3027
    //   3019: ldc2_w 309
    //   3022: lstore 7
    //   3024: goto +23 -> 3047
    //   3027: aload_0
    //   3028: getfield 188	bqo:E	Lbqp;
    //   3031: invokevirtual 313	bqp:a	()J
    //   3034: aload_0
    //   3035: getfield 188	bqo:E	Lbqp;
    //   3038: getfield 194	bqp:f	Lbqy;
    //   3041: getfield 474	bqy:e	J
    //   3044: ladd
    //   3045: lstore 7
    //   3047: aload_0
    //   3048: getfield 188	bqo:E	Lbqp;
    //   3051: ifnonnull +8 -> 3059
    //   3054: iconst_0
    //   3055: istore_2
    //   3056: goto +15 -> 3071
    //   3059: aload_0
    //   3060: getfield 188	bqo:E	Lbqp;
    //   3063: getfield 534	bqp:c	I
    //   3066: istore_2
    //   3067: iload_2
    //   3068: iconst_1
    //   3069: iadd
    //   3070: istore_2
    //   3071: aload_0
    //   3072: getfield 209	bqo:H	Lbrj;
    //   3075: aload_1
    //   3076: getfield 199	bqy:a	Lbzu;
    //   3079: getfield 211	bzu:a	I
    //   3082: aload_0
    //   3083: getfield 120	bqo:m	Lbrk;
    //   3086: iconst_1
    //   3087: invokevirtual 172	brj:a	(ILbrk;Z)Lbrk;
    //   3090: astore 15
    //   3092: aload 15
    //   3094: getfield 175	brk:a	Ljava/lang/Object;
    //   3097: astore 15
    //   3099: new 190	bqp
    //   3102: dup
    //   3103: aload_0
    //   3104: getfield 75	bqo:d	[Lbrc;
    //   3107: aload_0
    //   3108: getfield 95	bqo:e	[Lbrd;
    //   3111: lload 7
    //   3113: aload_0
    //   3114: getfield 77	bqo:f	Lcdl;
    //   3117: aload_0
    //   3118: getfield 79	bqo:g	Lbqw;
    //   3121: aload_0
    //   3122: getfield 444	bqo:s	Lbzs;
    //   3125: aload 15
    //   3127: iload_2
    //   3128: aload_1
    //   3129: invokespecial 654	bqp:<init>	([Lbrc;[Lbrd;JLcdl;Lbqw;Lbzs;Ljava/lang/Object;ILbqy;)V
    //   3132: astore 15
    //   3134: aload_0
    //   3135: getfield 188	bqo:E	Lbqp;
    //   3138: ifnull +12 -> 3150
    //   3141: aload_0
    //   3142: getfield 188	bqo:E	Lbqp;
    //   3145: aload 15
    //   3147: putfield 213	bqp:i	Lbqp;
    //   3150: aload_0
    //   3151: aload 15
    //   3153: putfield 188	bqo:E	Lbqp;
    //   3156: aload_0
    //   3157: getfield 188	bqo:E	Lbqp;
    //   3160: getfield 229	bqp:a	Lbzq;
    //   3163: aload_0
    //   3164: aload_1
    //   3165: getfield 570	bqy:b	J
    //   3168: invokeinterface 657 4 0
    //   3173: aload_0
    //   3174: iconst_1
    //   3175: invokespecial 442	bqo:a	(Z)V
    //   3178: goto +19 -> 3197
    //   3181: astore_1
    //   3182: goto +1343 -> 4525
    //   3185: astore_1
    //   3186: goto +1343 -> 4529
    //   3189: astore_1
    //   3190: goto +1377 -> 4567
    //   3193: astore_1
    //   3194: goto +1407 -> 4601
    //   3197: aload_0
    //   3198: getfield 188	bqo:E	Lbqp;
    //   3201: ifnull +37 -> 3238
    //   3204: aload_0
    //   3205: getfield 188	bqo:E	Lbqp;
    //   3208: invokevirtual 631	bqp:b	()Z
    //   3211: ifeq +6 -> 3217
    //   3214: goto +24 -> 3238
    //   3217: aload_0
    //   3218: getfield 188	bqo:E	Lbqp;
    //   3221: ifnull +22 -> 3243
    //   3224: aload_0
    //   3225: getfield 659	bqo:w	Z
    //   3228: ifne +15 -> 3243
    //   3231: aload_0
    //   3232: invokespecial 239	bqo:i	()V
    //   3235: goto +8 -> 3243
    //   3238: aload_0
    //   3239: iconst_0
    //   3240: invokespecial 442	bqo:a	(Z)V
    //   3243: aload_0
    //   3244: getfield 186	bqo:G	Lbqp;
    //   3247: ifnull +489 -> 3736
    //   3250: aload_0
    //   3251: getfield 186	bqo:G	Lbqp;
    //   3254: aload_0
    //   3255: getfield 215	bqo:F	Lbqp;
    //   3258: if_acmpeq +102 -> 3360
    //   3261: aload_0
    //   3262: getfield 315	bqo:D	J
    //   3265: aload_0
    //   3266: getfield 186	bqo:G	Lbqp;
    //   3269: getfield 213	bqp:i	Lbqp;
    //   3272: getfield 660	bqp:e	J
    //   3275: lcmp
    //   3276: iflt +84 -> 3360
    //   3279: aload_0
    //   3280: getfield 186	bqo:G	Lbqp;
    //   3283: invokevirtual 191	bqp:d	()V
    //   3286: aload_0
    //   3287: aload_0
    //   3288: getfield 186	bqo:G	Lbqp;
    //   3291: getfield 213	bqp:i	Lbqp;
    //   3294: invokespecial 224	bqo:b	(Lbqp;)V
    //   3297: aload_0
    //   3298: new 338	bqq
    //   3301: dup
    //   3302: aload_0
    //   3303: getfield 186	bqo:G	Lbqp;
    //   3306: getfield 194	bqp:f	Lbqy;
    //   3309: getfield 199	bqy:a	Lbzu;
    //   3312: aload_0
    //   3313: getfield 186	bqo:G	Lbqp;
    //   3316: getfield 194	bqp:f	Lbqy;
    //   3319: getfield 570	bqy:b	J
    //   3322: aload_0
    //   3323: getfield 186	bqo:G	Lbqp;
    //   3326: getfield 194	bqp:f	Lbqy;
    //   3329: getfield 581	bqy:d	J
    //   3332: invokespecial 543	bqq:<init>	(Lbzu;JJ)V
    //   3335: putfield 89	bqo:o	Lbqq;
    //   3338: aload_0
    //   3339: invokespecial 579	bqo:e	()V
    //   3342: aload_0
    //   3343: getfield 85	bqo:j	Landroid/os/Handler;
    //   3346: iconst_5
    //   3347: aload_0
    //   3348: getfield 89	bqo:o	Lbqq;
    //   3351: invokevirtual 420	android/os/Handler:obtainMessage	(ILjava/lang/Object;)Landroid/os/Message;
    //   3354: invokevirtual 308	android/os/Message:sendToTarget	()V
    //   3357: goto -107 -> 3250
    //   3360: aload_0
    //   3361: getfield 215	bqo:F	Lbqp;
    //   3364: getfield 194	bqp:f	Lbqy;
    //   3367: getfield 582	bqy:g	Z
    //   3370: ifeq +1368 -> 4738
    //   3373: iconst_0
    //   3374: istore_2
    //   3375: iload_2
    //   3376: aload_0
    //   3377: getfield 75	bqo:d	[Lbrc;
    //   3380: arraylength
    //   3381: if_icmpge +355 -> 3736
    //   3384: aload_0
    //   3385: getfield 75	bqo:d	[Lbrc;
    //   3388: iload_2
    //   3389: aaload
    //   3390: astore_1
    //   3391: aload_0
    //   3392: getfield 215	bqo:F	Lbqp;
    //   3395: getfield 384	bqp:d	[Lcaa;
    //   3398: iload_2
    //   3399: aaload
    //   3400: astore 15
    //   3402: aload 15
    //   3404: ifnull +1327 -> 4731
    //   3407: aload_1
    //   3408: invokeinterface 412 1 0
    //   3413: aload 15
    //   3415: if_acmpne +1316 -> 4731
    //   3418: aload_1
    //   3419: invokeinterface 481 1 0
    //   3424: ifeq +1307 -> 4731
    //   3427: aload_1
    //   3428: invokeinterface 662 1 0
    //   3433: goto +1298 -> 4731
    //   3436: iload_2
    //   3437: aload_0
    //   3438: getfield 75	bqo:d	[Lbrc;
    //   3441: arraylength
    //   3442: if_icmpge +49 -> 3491
    //   3445: aload_0
    //   3446: getfield 75	bqo:d	[Lbrc;
    //   3449: iload_2
    //   3450: aaload
    //   3451: astore_1
    //   3452: aload_0
    //   3453: getfield 215	bqo:F	Lbqp;
    //   3456: getfield 384	bqp:d	[Lcaa;
    //   3459: iload_2
    //   3460: aaload
    //   3461: astore 15
    //   3463: aload_1
    //   3464: invokeinterface 412 1 0
    //   3469: aload 15
    //   3471: if_acmpne +265 -> 3736
    //   3474: aload 15
    //   3476: ifnull +1267 -> 4743
    //   3479: aload_1
    //   3480: invokeinterface 481 1 0
    //   3485: ifne +1258 -> 4743
    //   3488: goto +248 -> 3736
    //   3491: aload_0
    //   3492: getfield 215	bqo:F	Lbqp;
    //   3495: getfield 213	bqp:i	Lbqp;
    //   3498: ifnull +238 -> 3736
    //   3501: aload_0
    //   3502: getfield 215	bqo:F	Lbqp;
    //   3505: getfield 213	bqp:i	Lbqp;
    //   3508: getfield 207	bqp:g	Z
    //   3511: ifeq +225 -> 3736
    //   3514: aload_0
    //   3515: getfield 215	bqo:F	Lbqp;
    //   3518: getfield 360	bqp:j	Lcdn;
    //   3521: astore 15
    //   3523: aload_0
    //   3524: aload_0
    //   3525: getfield 215	bqo:F	Lbqp;
    //   3528: getfield 213	bqp:i	Lbqp;
    //   3531: putfield 215	bqo:F	Lbqp;
    //   3534: aload_0
    //   3535: getfield 215	bqo:F	Lbqp;
    //   3538: getfield 360	bqp:j	Lcdn;
    //   3541: astore 16
    //   3543: aload_0
    //   3544: getfield 215	bqo:F	Lbqp;
    //   3547: getfield 229	bqp:a	Lbzq;
    //   3550: invokeinterface 459 1 0
    //   3555: ldc2_w 343
    //   3558: lcmp
    //   3559: ifeq +1191 -> 4750
    //   3562: iconst_1
    //   3563: istore_2
    //   3564: goto +1188 -> 4752
    //   3567: iload_3
    //   3568: aload_0
    //   3569: getfield 75	bqo:d	[Lbrc;
    //   3572: arraylength
    //   3573: if_icmpge +163 -> 3736
    //   3576: aload_0
    //   3577: getfield 75	bqo:d	[Lbrc;
    //   3580: iload_3
    //   3581: aaload
    //   3582: astore 17
    //   3584: aload 15
    //   3586: getfield 365	cdn:a	Lcdk;
    //   3589: getfield 370	cdk:b	[Lcdi;
    //   3592: iload_3
    //   3593: aaload
    //   3594: ifnull +1163 -> 4757
    //   3597: iload_2
    //   3598: ifne +128 -> 3726
    //   3601: aload 17
    //   3603: invokeinterface 409 1 0
    //   3608: ifne +1149 -> 4757
    //   3611: aload 16
    //   3613: getfield 365	cdn:a	Lcdk;
    //   3616: getfield 370	cdk:b	[Lcdi;
    //   3619: iload_3
    //   3620: aaload
    //   3621: astore_1
    //   3622: aload 15
    //   3624: getfield 373	cdn:b	[Lbre;
    //   3627: iload_3
    //   3628: aaload
    //   3629: astore 19
    //   3631: aload 16
    //   3633: getfield 373	cdn:b	[Lbre;
    //   3636: iload_3
    //   3637: aaload
    //   3638: astore 18
    //   3640: aload_1
    //   3641: ifnull +85 -> 3726
    //   3644: aload 18
    //   3646: aload 19
    //   3648: invokevirtual 665	bre:equals	(Ljava/lang/Object;)Z
    //   3651: ifeq +75 -> 3726
    //   3654: aload_1
    //   3655: invokeinterface 376 1 0
    //   3660: anewarray 378	bqu
    //   3663: astore 18
    //   3665: iconst_0
    //   3666: istore 4
    //   3668: iload 4
    //   3670: aload 18
    //   3672: arraylength
    //   3673: if_icmpge +25 -> 3698
    //   3676: aload 18
    //   3678: iload 4
    //   3680: aload_1
    //   3681: iload 4
    //   3683: invokeinterface 381 2 0
    //   3688: aastore
    //   3689: iload 4
    //   3691: iconst_1
    //   3692: iadd
    //   3693: istore 4
    //   3695: goto -27 -> 3668
    //   3698: aload 17
    //   3700: aload 18
    //   3702: aload_0
    //   3703: getfield 215	bqo:F	Lbqp;
    //   3706: getfield 384	bqp:d	[Lcaa;
    //   3709: iload_3
    //   3710: aaload
    //   3711: aload_0
    //   3712: getfield 215	bqo:F	Lbqp;
    //   3715: invokevirtual 313	bqp:a	()J
    //   3718: invokeinterface 668 5 0
    //   3723: goto +1034 -> 4757
    //   3726: aload 17
    //   3728: invokeinterface 662 1 0
    //   3733: goto +1024 -> 4757
    //   3736: aload_0
    //   3737: getfield 186	bqo:G	Lbqp;
    //   3740: ifnonnull +19 -> 3759
    //   3743: aload_0
    //   3744: invokespecial 670	bqo:g	()V
    //   3747: aload_0
    //   3748: lload 11
    //   3750: ldc2_w 671
    //   3753: invokespecial 674	bqo:a	(JJ)V
    //   3756: goto +1011 -> 4767
    //   3759: ldc_w 676
    //   3762: invokestatic 680	cfi:a	(Ljava/lang/String;)V
    //   3765: aload_0
    //   3766: invokespecial 579	bqo:e	()V
    //   3769: aload_0
    //   3770: getfield 186	bqo:G	Lbqp;
    //   3773: getfield 229	bqp:a	Lbzq;
    //   3776: aload_0
    //   3777: getfield 89	bqo:o	Lbqq;
    //   3780: getfield 452	bqq:d	J
    //   3783: invokeinterface 681 3 0
    //   3788: aload_0
    //   3789: getfield 110	bqo:t	[Lbrc;
    //   3792: astore 15
    //   3794: aload 15
    //   3796: arraylength
    //   3797: istore 5
    //   3799: iconst_0
    //   3800: istore_3
    //   3801: iconst_1
    //   3802: istore 6
    //   3804: iconst_1
    //   3805: istore_2
    //   3806: iload_3
    //   3807: iload 5
    //   3809: if_icmpge +75 -> 3884
    //   3812: aload 15
    //   3814: iload_3
    //   3815: aaload
    //   3816: astore_1
    //   3817: aload_1
    //   3818: aload_0
    //   3819: getfield 315	bqo:D	J
    //   3822: aload_0
    //   3823: getfield 468	bqo:A	J
    //   3826: invokeinterface 682 5 0
    //   3831: iload_2
    //   3832: ifeq +937 -> 4769
    //   3835: aload_1
    //   3836: invokeinterface 461 1 0
    //   3841: ifeq +928 -> 4769
    //   3844: iconst_1
    //   3845: istore_2
    //   3846: goto +3 -> 3849
    //   3849: aload_1
    //   3850: invokeinterface 684 1 0
    //   3855: ifne +925 -> 4780
    //   3858: aload_1
    //   3859: invokeinterface 461 1 0
    //   3864: ifeq +910 -> 4774
    //   3867: goto +913 -> 4780
    //   3870: iload 4
    //   3872: ifne +914 -> 4786
    //   3875: aload_1
    //   3876: invokeinterface 686 1 0
    //   3881: goto +905 -> 4786
    //   3884: iload 6
    //   3886: ifne +7 -> 3893
    //   3889: aload_0
    //   3890: invokespecial 670	bqo:g	()V
    //   3893: aload_0
    //   3894: getfield 219	bqo:r	Lcev;
    //   3897: ifnull +53 -> 3950
    //   3900: aload_0
    //   3901: getfield 219	bqo:r	Lcev;
    //   3904: invokeinterface 689 1 0
    //   3909: astore_1
    //   3910: aload_1
    //   3911: aload_0
    //   3912: getfield 136	bqo:p	Lbqz;
    //   3915: invokevirtual 690	bqz:equals	(Ljava/lang/Object;)Z
    //   3918: ifne +32 -> 3950
    //   3921: aload_0
    //   3922: aload_1
    //   3923: putfield 136	bqo:p	Lbqz;
    //   3926: aload_0
    //   3927: getfield 108	bqo:h	Lcff;
    //   3930: aload_0
    //   3931: getfield 219	bqo:r	Lcev;
    //   3934: invokevirtual 415	cff:a	(Lcev;)V
    //   3937: aload_0
    //   3938: getfield 85	bqo:j	Landroid/os/Handler;
    //   3941: bipush 7
    //   3943: aload_1
    //   3944: invokevirtual 420	android/os/Handler:obtainMessage	(ILjava/lang/Object;)Landroid/os/Message;
    //   3947: invokevirtual 308	android/os/Message:sendToTarget	()V
    //   3950: aload_0
    //   3951: getfield 186	bqo:G	Lbqp;
    //   3954: getfield 194	bqp:f	Lbqy;
    //   3957: getfield 474	bqy:e	J
    //   3960: lstore 7
    //   3962: iload_2
    //   3963: ifeq +50 -> 4013
    //   3966: lload 7
    //   3968: ldc2_w 343
    //   3971: lcmp
    //   3972: ifeq +16 -> 3988
    //   3975: lload 7
    //   3977: aload_0
    //   3978: getfield 89	bqo:o	Lbqq;
    //   3981: getfield 452	bqq:d	J
    //   3984: lcmp
    //   3985: ifgt +28 -> 4013
    //   3988: aload_0
    //   3989: getfield 186	bqo:G	Lbqp;
    //   3992: getfield 194	bqp:f	Lbqy;
    //   3995: getfield 582	bqy:g	Z
    //   3998: ifeq +15 -> 4013
    //   4001: aload_0
    //   4002: iconst_4
    //   4003: invokespecial 184	bqo:a	(I)V
    //   4006: aload_0
    //   4007: invokespecial 181	bqo:d	()V
    //   4010: goto +216 -> 4226
    //   4013: aload_0
    //   4014: getfield 87	bqo:x	I
    //   4017: iconst_2
    //   4018: if_icmpne +159 -> 4177
    //   4021: aload_0
    //   4022: getfield 110	bqo:t	[Lbrc;
    //   4025: arraylength
    //   4026: ifle +119 -> 4145
    //   4029: iload 6
    //   4031: ifeq +792 -> 4823
    //   4034: aload_0
    //   4035: getfield 188	bqo:E	Lbqp;
    //   4038: astore_1
    //   4039: aload_0
    //   4040: getfield 183	bqo:v	Z
    //   4043: istore 6
    //   4045: aload_0
    //   4046: getfield 315	bqo:D	J
    //   4049: lstore 13
    //   4051: aload_1
    //   4052: getfield 207	bqp:g	Z
    //   4055: ifne +15 -> 4070
    //   4058: aload_1
    //   4059: getfield 194	bqp:f	Lbqy;
    //   4062: getfield 570	bqy:b	J
    //   4065: lstore 7
    //   4067: goto +14 -> 4081
    //   4070: aload_1
    //   4071: getfield 229	bqp:a	Lbzq;
    //   4074: invokeinterface 472 1 0
    //   4079: lstore 7
    //   4081: lload 7
    //   4083: lstore 9
    //   4085: lload 7
    //   4087: ldc2_w 469
    //   4090: lcmp
    //   4091: ifne +28 -> 4119
    //   4094: aload_1
    //   4095: getfield 194	bqp:f	Lbqy;
    //   4098: getfield 582	bqy:g	Z
    //   4101: ifeq +9 -> 4110
    //   4104: iconst_1
    //   4105: istore 6
    //   4107: goto +705 -> 4812
    //   4110: aload_1
    //   4111: getfield 194	bqp:f	Lbqy;
    //   4114: getfield 474	bqy:e	J
    //   4117: lstore 9
    //   4119: aload_1
    //   4120: getfield 489	bqp:k	Lbqw;
    //   4123: lload 9
    //   4125: lload 13
    //   4127: aload_1
    //   4128: invokevirtual 313	bqp:a	()J
    //   4131: lsub
    //   4132: lsub
    //   4133: iload 6
    //   4135: invokeinterface 693 4 0
    //   4140: istore 6
    //   4142: goto +670 -> 4812
    //   4145: aload_0
    //   4146: lload 7
    //   4148: invokespecial 695	bqo:b	(J)Z
    //   4151: istore 6
    //   4153: iload 6
    //   4155: ifeq +71 -> 4226
    //   4158: aload_0
    //   4159: iconst_3
    //   4160: invokespecial 184	bqo:a	(I)V
    //   4163: aload_0
    //   4164: getfield 81	bqo:u	Z
    //   4167: ifeq +59 -> 4226
    //   4170: aload_0
    //   4171: invokespecial 696	bqo:c	()V
    //   4174: goto +52 -> 4226
    //   4177: aload_0
    //   4178: getfield 87	bqo:x	I
    //   4181: iconst_3
    //   4182: if_icmpne +44 -> 4226
    //   4185: aload_0
    //   4186: getfield 110	bqo:t	[Lbrc;
    //   4189: arraylength
    //   4190: ifle +6 -> 4196
    //   4193: goto +11 -> 4204
    //   4196: aload_0
    //   4197: lload 7
    //   4199: invokespecial 695	bqo:b	(J)Z
    //   4202: istore 6
    //   4204: iload 6
    //   4206: ifne +20 -> 4226
    //   4209: aload_0
    //   4210: aload_0
    //   4211: getfield 81	bqo:u	Z
    //   4214: putfield 183	bqo:v	Z
    //   4217: aload_0
    //   4218: iconst_2
    //   4219: invokespecial 184	bqo:a	(I)V
    //   4222: aload_0
    //   4223: invokespecial 181	bqo:d	()V
    //   4226: aload_0
    //   4227: getfield 87	bqo:x	I
    //   4230: iconst_2
    //   4231: if_icmpne +33 -> 4264
    //   4234: aload_0
    //   4235: getfield 110	bqo:t	[Lbrc;
    //   4238: astore_1
    //   4239: aload_1
    //   4240: arraylength
    //   4241: istore_3
    //   4242: iconst_0
    //   4243: istore_2
    //   4244: iload_2
    //   4245: iload_3
    //   4246: if_icmpge +18 -> 4264
    //   4249: aload_1
    //   4250: iload_2
    //   4251: aaload
    //   4252: invokeinterface 686 1 0
    //   4257: iload_2
    //   4258: iconst_1
    //   4259: iadd
    //   4260: istore_2
    //   4261: goto -17 -> 4244
    //   4264: aload_0
    //   4265: getfield 81	bqo:u	Z
    //   4268: ifeq +11 -> 4279
    //   4271: aload_0
    //   4272: getfield 87	bqo:x	I
    //   4275: iconst_3
    //   4276: if_icmpeq +11 -> 4287
    //   4279: aload_0
    //   4280: getfield 87	bqo:x	I
    //   4283: iconst_2
    //   4284: if_icmpne +15 -> 4299
    //   4287: aload_0
    //   4288: lload 11
    //   4290: ldc2_w 671
    //   4293: invokespecial 674	bqo:a	(JJ)V
    //   4296: goto +39 -> 4335
    //   4299: aload_0
    //   4300: getfield 110	bqo:t	[Lbrc;
    //   4303: arraylength
    //   4304: ifeq +23 -> 4327
    //   4307: aload_0
    //   4308: getfield 87	bqo:x	I
    //   4311: iconst_4
    //   4312: if_icmpeq +15 -> 4327
    //   4315: aload_0
    //   4316: lload 11
    //   4318: ldc2_w 465
    //   4321: invokespecial 674	bqo:a	(JJ)V
    //   4324: goto +11 -> 4335
    //   4327: aload_0
    //   4328: getfield 159	bqo:a	Landroid/os/Handler;
    //   4331: iconst_2
    //   4332: invokevirtual 321	android/os/Handler:removeMessages	(I)V
    //   4335: invokestatic 697	cfi:a	()V
    //   4338: goto +429 -> 4767
    //   4341: aload_1
    //   4342: getfield 531	android/os/Message:arg1	I
    //   4345: ifeq +495 -> 4840
    //   4348: iconst_1
    //   4349: istore 6
    //   4351: goto +486 -> 4837
    //   4354: aload_0
    //   4355: iconst_0
    //   4356: putfield 183	bqo:v	Z
    //   4359: aload_0
    //   4360: iload 6
    //   4362: putfield 81	bqo:u	Z
    //   4365: iload 6
    //   4367: ifne +14 -> 4381
    //   4370: aload_0
    //   4371: invokespecial 181	bqo:d	()V
    //   4374: aload_0
    //   4375: invokespecial 579	bqo:e	()V
    //   4378: goto +468 -> 4846
    //   4381: aload_0
    //   4382: getfield 87	bqo:x	I
    //   4385: iconst_3
    //   4386: if_icmpne +19 -> 4405
    //   4389: aload_0
    //   4390: invokespecial 696	bqo:c	()V
    //   4393: aload_0
    //   4394: getfield 159	bqo:a	Landroid/os/Handler;
    //   4397: iconst_2
    //   4398: invokevirtual 243	android/os/Handler:sendEmptyMessage	(I)Z
    //   4401: pop
    //   4402: goto +444 -> 4846
    //   4405: aload_0
    //   4406: getfield 87	bqo:x	I
    //   4409: iconst_2
    //   4410: if_icmpne +436 -> 4846
    //   4413: aload_0
    //   4414: getfield 159	bqo:a	Landroid/os/Handler;
    //   4417: iconst_2
    //   4418: invokevirtual 243	android/os/Handler:sendEmptyMessage	(I)Z
    //   4421: pop
    //   4422: goto +424 -> 4846
    //   4425: aload_1
    //   4426: getfield 546	android/os/Message:obj	Ljava/lang/Object;
    //   4429: checkcast 446	bzs
    //   4432: astore 15
    //   4434: aload_1
    //   4435: getfield 531	android/os/Message:arg1	I
    //   4438: ifeq +410 -> 4848
    //   4441: iconst_1
    //   4442: istore_2
    //   4443: goto +3 -> 4446
    //   4446: aload_0
    //   4447: getfield 85	bqo:j	Landroid/os/Handler;
    //   4450: iconst_0
    //   4451: invokevirtual 243	android/os/Handler:sendEmptyMessage	(I)Z
    //   4454: pop
    //   4455: aload_0
    //   4456: iconst_1
    //   4457: invokespecial 347	bqo:b	(Z)V
    //   4460: aload_0
    //   4461: getfield 79	bqo:g	Lbqw;
    //   4464: invokeinterface 698 1 0
    //   4469: iload_2
    //   4470: ifeq +17 -> 4487
    //   4473: aload_0
    //   4474: new 338	bqq
    //   4477: dup
    //   4478: ldc2_w 343
    //   4481: invokespecial 340	bqq:<init>	(J)V
    //   4484: putfield 89	bqo:o	Lbqq;
    //   4487: aload_0
    //   4488: aload 15
    //   4490: putfield 444	bqo:s	Lbzs;
    //   4493: aload_0
    //   4494: getfield 91	bqo:k	Lbqi;
    //   4497: astore_1
    //   4498: aload 15
    //   4500: aload_1
    //   4501: iconst_1
    //   4502: aload_0
    //   4503: invokeinterface 701 4 0
    //   4508: aload_0
    //   4509: iconst_2
    //   4510: invokespecial 184	bqo:a	(I)V
    //   4513: aload_0
    //   4514: getfield 159	bqo:a	Landroid/os/Handler;
    //   4517: iconst_2
    //   4518: invokevirtual 243	android/os/Handler:sendEmptyMessage	(I)Z
    //   4521: pop
    //   4522: iconst_1
    //   4523: ireturn
    //   4524: astore_1
    //   4525: goto +42 -> 4567
    //   4528: astore_1
    //   4529: goto +72 -> 4601
    //   4532: astore_1
    //   4533: ldc_w 431
    //   4536: ldc_w 703
    //   4539: aload_1
    //   4540: invokestatic 438	android/util/Log:e	(Ljava/lang/String;Ljava/lang/String;Ljava/lang/Throwable;)I
    //   4543: pop
    //   4544: aload_0
    //   4545: getfield 85	bqo:j	Landroid/os/Handler;
    //   4548: bipush 8
    //   4550: aload_1
    //   4551: invokestatic 400	com/google/android/exoplayer2/ExoPlaybackException:a	(Ljava/lang/RuntimeException;)Lcom/google/android/exoplayer2/ExoPlaybackException;
    //   4554: invokevirtual 420	android/os/Handler:obtainMessage	(ILjava/lang/Object;)Landroid/os/Message;
    //   4557: invokevirtual 308	android/os/Message:sendToTarget	()V
    //   4560: aload_0
    //   4561: invokespecial 622	bqo:f	()V
    //   4564: iconst_1
    //   4565: ireturn
    //   4566: astore_1
    //   4567: ldc_w 431
    //   4570: ldc_w 705
    //   4573: aload_1
    //   4574: invokestatic 438	android/util/Log:e	(Ljava/lang/String;Ljava/lang/String;Ljava/lang/Throwable;)I
    //   4577: pop
    //   4578: aload_0
    //   4579: getfield 85	bqo:j	Landroid/os/Handler;
    //   4582: bipush 8
    //   4584: aload_1
    //   4585: invokestatic 708	com/google/android/exoplayer2/ExoPlaybackException:a	(Ljava/io/IOException;)Lcom/google/android/exoplayer2/ExoPlaybackException;
    //   4588: invokevirtual 420	android/os/Handler:obtainMessage	(ILjava/lang/Object;)Landroid/os/Message;
    //   4591: invokevirtual 308	android/os/Message:sendToTarget	()V
    //   4594: aload_0
    //   4595: invokespecial 622	bqo:f	()V
    //   4598: iconst_1
    //   4599: ireturn
    //   4600: astore_1
    //   4601: ldc_w 431
    //   4604: ldc_w 710
    //   4607: aload_1
    //   4608: invokestatic 438	android/util/Log:e	(Ljava/lang/String;Ljava/lang/String;Ljava/lang/Throwable;)I
    //   4611: pop
    //   4612: aload_0
    //   4613: getfield 85	bqo:j	Landroid/os/Handler;
    //   4616: bipush 8
    //   4618: aload_1
    //   4619: invokevirtual 420	android/os/Handler:obtainMessage	(ILjava/lang/Object;)Landroid/os/Message;
    //   4622: invokevirtual 308	android/os/Message:sendToTarget	()V
    //   4625: aload_0
    //   4626: invokespecial 622	bqo:f	()V
    //   4629: iconst_1
    //   4630: ireturn
    //   4631: aload_1
    //   4632: ifnull +16 -> 4648
    //   4635: goto -4512 -> 123
    //   4638: iconst_m1
    //   4639: istore_2
    //   4640: goto -4402 -> 238
    //   4643: iconst_0
    //   4644: istore_3
    //   4645: goto -4347 -> 298
    //   4648: iconst_1
    //   4649: ireturn
    //   4650: iconst_0
    //   4651: istore 6
    //   4653: goto -4074 -> 579
    //   4656: iconst_0
    //   4657: istore 6
    //   4659: goto -3940 -> 719
    //   4662: iload 4
    //   4664: iconst_1
    //   4665: iadd
    //   4666: istore 4
    //   4668: iload_3
    //   4669: istore_2
    //   4670: goto -3986 -> 684
    //   4673: iconst_1
    //   4674: ireturn
    //   4675: iconst_1
    //   4676: ireturn
    //   4677: iconst_1
    //   4678: ireturn
    //   4679: lload 9
    //   4681: lstore 7
    //   4683: goto -3390 -> 1293
    //   4686: lload 9
    //   4688: lstore 7
    //   4690: goto -3289 -> 1401
    //   4693: ldc2_w 343
    //   4696: lstore 7
    //   4698: goto -2838 -> 1860
    //   4701: iconst_0
    //   4702: istore_2
    //   4703: goto -2708 -> 1995
    //   4706: iconst_0
    //   4707: istore_2
    //   4708: goto -2406 -> 2302
    //   4711: iconst_0
    //   4712: istore_2
    //   4713: goto -2180 -> 2533
    //   4716: astore_1
    //   4717: goto -2169 -> 2548
    //   4720: lconst_0
    //   4721: lstore 7
    //   4723: goto -1832 -> 2891
    //   4726: aconst_null
    //   4727: astore_1
    //   4728: goto -1720 -> 3008
    //   4731: iload_2
    //   4732: iconst_1
    //   4733: iadd
    //   4734: istore_2
    //   4735: goto -1360 -> 3375
    //   4738: iconst_0
    //   4739: istore_2
    //   4740: goto -1304 -> 3436
    //   4743: iload_2
    //   4744: iconst_1
    //   4745: iadd
    //   4746: istore_2
    //   4747: goto -1311 -> 3436
    //   4750: iconst_0
    //   4751: istore_2
    //   4752: iconst_0
    //   4753: istore_3
    //   4754: goto -1187 -> 3567
    //   4757: iload_3
    //   4758: iconst_1
    //   4759: iadd
    //   4760: istore_3
    //   4761: goto -1194 -> 3567
    //   4764: goto -1028 -> 3736
    //   4767: iconst_1
    //   4768: ireturn
    //   4769: iconst_0
    //   4770: istore_2
    //   4771: goto -922 -> 3849
    //   4774: iconst_0
    //   4775: istore 4
    //   4777: goto -907 -> 3870
    //   4780: iconst_1
    //   4781: istore 4
    //   4783: goto -913 -> 3870
    //   4786: iload 6
    //   4788: ifeq +14 -> 4802
    //   4791: iload 4
    //   4793: ifeq +9 -> 4802
    //   4796: iconst_1
    //   4797: istore 6
    //   4799: goto +6 -> 4805
    //   4802: iconst_0
    //   4803: istore 6
    //   4805: iload_3
    //   4806: iconst_1
    //   4807: iadd
    //   4808: istore_3
    //   4809: goto -1003 -> 3806
    //   4812: iload 6
    //   4814: ifeq +9 -> 4823
    //   4817: iconst_1
    //   4818: istore 6
    //   4820: goto -667 -> 4153
    //   4823: iconst_0
    //   4824: istore 6
    //   4826: goto -673 -> 4153
    //   4829: astore_1
    //   4830: goto -305 -> 4525
    //   4833: astore_1
    //   4834: goto -305 -> 4529
    //   4837: goto -483 -> 4354
    //   4840: iconst_0
    //   4841: istore 6
    //   4843: goto -6 -> 4837
    //   4846: iconst_1
    //   4847: ireturn
    //   4848: iconst_0
    //   4849: istore_2
    //   4850: goto -404 -> 4446
    // Local variable table:
    //   start	length	slot	name	signature
    //   0	4853	0	this	bqo
    //   0	4853	1	paramMessage	Message
    //   9	4841	2	i1	int
    //   4	4805	3	i2	int
    //   11	4781	4	i3	int
    //   3797	13	5	i4	int
    //   574	4268	6	bool	boolean
    //   6	4716	7	l1	long
    //   1269	3418	9	l2	long
    //   2358	1959	11	l3	long
    //   2323	1803	13	l4	long
    //   267	4232	15	localObject1	Object
    //   261	3371	16	localObject2	Object
    //   736	2991	17	localObject3	Object
    //   701	3000	18	localObject4	Object
    //   3629	18	19	localBre	bre
    // Exception table:
    //   from	to	target	type
    //   457	473	475	finally
    //   476	478	475	finally
    //   392	396	480	finally
    //   406	423	480	finally
    //   430	446	480	finally
    //   446	455	480	finally
    //   483	499	501	finally
    //   502	504	501	finally
    //   2103	2114	2116	finally
    //   2117	2119	2116	finally
    //   2400	2410	2463	finally
    //   3173	3178	3181	java/io/IOException
    //   3173	3178	3185	com/google/android/exoplayer2/ExoPlaybackException
    //   3071	3092	3189	java/io/IOException
    //   3071	3092	3193	com/google/android/exoplayer2/ExoPlaybackException
    //   2751	2779	4524	java/io/IOException
    //   2784	2815	4524	java/io/IOException
    //   2819	2861	4524	java/io/IOException
    //   2865	2888	4524	java/io/IOException
    //   2891	2907	4524	java/io/IOException
    //   2910	2951	4524	java/io/IOException
    //   2953	2961	4524	java/io/IOException
    //   2967	2979	4524	java/io/IOException
    //   2982	3008	4524	java/io/IOException
    //   3012	3019	4524	java/io/IOException
    //   3027	3047	4524	java/io/IOException
    //   3047	3054	4524	java/io/IOException
    //   3059	3067	4524	java/io/IOException
    //   3092	3150	4524	java/io/IOException
    //   3150	3173	4524	java/io/IOException
    //   3197	3214	4524	java/io/IOException
    //   3217	3235	4524	java/io/IOException
    //   3238	3243	4524	java/io/IOException
    //   3243	3250	4524	java/io/IOException
    //   3250	3357	4524	java/io/IOException
    //   3360	3373	4524	java/io/IOException
    //   3375	3402	4524	java/io/IOException
    //   3407	3433	4524	java/io/IOException
    //   3436	3474	4524	java/io/IOException
    //   3479	3488	4524	java/io/IOException
    //   3491	3562	4524	java/io/IOException
    //   3567	3597	4524	java/io/IOException
    //   3601	3640	4524	java/io/IOException
    //   3644	3665	4524	java/io/IOException
    //   3668	3689	4524	java/io/IOException
    //   3698	3723	4524	java/io/IOException
    //   3726	3733	4524	java/io/IOException
    //   3736	3756	4524	java/io/IOException
    //   3759	3799	4524	java/io/IOException
    //   3817	3831	4524	java/io/IOException
    //   3835	3844	4524	java/io/IOException
    //   3849	3867	4524	java/io/IOException
    //   3875	3881	4524	java/io/IOException
    //   3889	3893	4524	java/io/IOException
    //   3893	3950	4524	java/io/IOException
    //   3950	3962	4524	java/io/IOException
    //   3975	3988	4524	java/io/IOException
    //   3988	4010	4524	java/io/IOException
    //   4013	4029	4524	java/io/IOException
    //   4034	4067	4524	java/io/IOException
    //   4070	4081	4524	java/io/IOException
    //   4094	4104	4524	java/io/IOException
    //   4110	4119	4524	java/io/IOException
    //   4119	4142	4524	java/io/IOException
    //   4145	4153	4524	java/io/IOException
    //   4158	4174	4524	java/io/IOException
    //   4177	4193	4524	java/io/IOException
    //   4196	4204	4524	java/io/IOException
    //   4209	4226	4524	java/io/IOException
    //   4226	4242	4524	java/io/IOException
    //   4249	4257	4524	java/io/IOException
    //   4264	4279	4524	java/io/IOException
    //   4279	4287	4524	java/io/IOException
    //   4287	4296	4524	java/io/IOException
    //   4299	4324	4524	java/io/IOException
    //   4327	4335	4524	java/io/IOException
    //   4335	4338	4524	java/io/IOException
    //   4341	4348	4524	java/io/IOException
    //   4354	4365	4524	java/io/IOException
    //   4370	4378	4524	java/io/IOException
    //   4381	4402	4524	java/io/IOException
    //   4405	4422	4524	java/io/IOException
    //   4425	4441	4524	java/io/IOException
    //   4446	4455	4524	java/io/IOException
    //   4460	4469	4524	java/io/IOException
    //   4473	4487	4524	java/io/IOException
    //   4487	4498	4524	java/io/IOException
    //   2751	2779	4528	com/google/android/exoplayer2/ExoPlaybackException
    //   2784	2815	4528	com/google/android/exoplayer2/ExoPlaybackException
    //   2819	2861	4528	com/google/android/exoplayer2/ExoPlaybackException
    //   2865	2888	4528	com/google/android/exoplayer2/ExoPlaybackException
    //   2891	2907	4528	com/google/android/exoplayer2/ExoPlaybackException
    //   2910	2951	4528	com/google/android/exoplayer2/ExoPlaybackException
    //   2953	2961	4528	com/google/android/exoplayer2/ExoPlaybackException
    //   2967	2979	4528	com/google/android/exoplayer2/ExoPlaybackException
    //   2982	3008	4528	com/google/android/exoplayer2/ExoPlaybackException
    //   3012	3019	4528	com/google/android/exoplayer2/ExoPlaybackException
    //   3027	3047	4528	com/google/android/exoplayer2/ExoPlaybackException
    //   3047	3054	4528	com/google/android/exoplayer2/ExoPlaybackException
    //   3059	3067	4528	com/google/android/exoplayer2/ExoPlaybackException
    //   3092	3150	4528	com/google/android/exoplayer2/ExoPlaybackException
    //   3150	3173	4528	com/google/android/exoplayer2/ExoPlaybackException
    //   3197	3214	4528	com/google/android/exoplayer2/ExoPlaybackException
    //   3217	3235	4528	com/google/android/exoplayer2/ExoPlaybackException
    //   3238	3243	4528	com/google/android/exoplayer2/ExoPlaybackException
    //   3243	3250	4528	com/google/android/exoplayer2/ExoPlaybackException
    //   3250	3357	4528	com/google/android/exoplayer2/ExoPlaybackException
    //   3360	3373	4528	com/google/android/exoplayer2/ExoPlaybackException
    //   3375	3402	4528	com/google/android/exoplayer2/ExoPlaybackException
    //   3407	3433	4528	com/google/android/exoplayer2/ExoPlaybackException
    //   3436	3474	4528	com/google/android/exoplayer2/ExoPlaybackException
    //   3479	3488	4528	com/google/android/exoplayer2/ExoPlaybackException
    //   3491	3562	4528	com/google/android/exoplayer2/ExoPlaybackException
    //   3567	3597	4528	com/google/android/exoplayer2/ExoPlaybackException
    //   3601	3640	4528	com/google/android/exoplayer2/ExoPlaybackException
    //   3644	3665	4528	com/google/android/exoplayer2/ExoPlaybackException
    //   3668	3689	4528	com/google/android/exoplayer2/ExoPlaybackException
    //   3698	3723	4528	com/google/android/exoplayer2/ExoPlaybackException
    //   3726	3733	4528	com/google/android/exoplayer2/ExoPlaybackException
    //   3736	3756	4528	com/google/android/exoplayer2/ExoPlaybackException
    //   3759	3799	4528	com/google/android/exoplayer2/ExoPlaybackException
    //   3817	3831	4528	com/google/android/exoplayer2/ExoPlaybackException
    //   3835	3844	4528	com/google/android/exoplayer2/ExoPlaybackException
    //   3849	3867	4528	com/google/android/exoplayer2/ExoPlaybackException
    //   3875	3881	4528	com/google/android/exoplayer2/ExoPlaybackException
    //   3889	3893	4528	com/google/android/exoplayer2/ExoPlaybackException
    //   3893	3950	4528	com/google/android/exoplayer2/ExoPlaybackException
    //   3950	3962	4528	com/google/android/exoplayer2/ExoPlaybackException
    //   3975	3988	4528	com/google/android/exoplayer2/ExoPlaybackException
    //   3988	4010	4528	com/google/android/exoplayer2/ExoPlaybackException
    //   4013	4029	4528	com/google/android/exoplayer2/ExoPlaybackException
    //   4034	4067	4528	com/google/android/exoplayer2/ExoPlaybackException
    //   4070	4081	4528	com/google/android/exoplayer2/ExoPlaybackException
    //   4094	4104	4528	com/google/android/exoplayer2/ExoPlaybackException
    //   4110	4119	4528	com/google/android/exoplayer2/ExoPlaybackException
    //   4119	4142	4528	com/google/android/exoplayer2/ExoPlaybackException
    //   4145	4153	4528	com/google/android/exoplayer2/ExoPlaybackException
    //   4158	4174	4528	com/google/android/exoplayer2/ExoPlaybackException
    //   4177	4193	4528	com/google/android/exoplayer2/ExoPlaybackException
    //   4196	4204	4528	com/google/android/exoplayer2/ExoPlaybackException
    //   4209	4226	4528	com/google/android/exoplayer2/ExoPlaybackException
    //   4226	4242	4528	com/google/android/exoplayer2/ExoPlaybackException
    //   4249	4257	4528	com/google/android/exoplayer2/ExoPlaybackException
    //   4264	4279	4528	com/google/android/exoplayer2/ExoPlaybackException
    //   4279	4287	4528	com/google/android/exoplayer2/ExoPlaybackException
    //   4287	4296	4528	com/google/android/exoplayer2/ExoPlaybackException
    //   4299	4324	4528	com/google/android/exoplayer2/ExoPlaybackException
    //   4327	4335	4528	com/google/android/exoplayer2/ExoPlaybackException
    //   4335	4338	4528	com/google/android/exoplayer2/ExoPlaybackException
    //   4341	4348	4528	com/google/android/exoplayer2/ExoPlaybackException
    //   4354	4365	4528	com/google/android/exoplayer2/ExoPlaybackException
    //   4370	4378	4528	com/google/android/exoplayer2/ExoPlaybackException
    //   4381	4402	4528	com/google/android/exoplayer2/ExoPlaybackException
    //   4405	4422	4528	com/google/android/exoplayer2/ExoPlaybackException
    //   4425	4441	4528	com/google/android/exoplayer2/ExoPlaybackException
    //   4446	4455	4528	com/google/android/exoplayer2/ExoPlaybackException
    //   4460	4469	4528	com/google/android/exoplayer2/ExoPlaybackException
    //   4473	4487	4528	com/google/android/exoplayer2/ExoPlaybackException
    //   4487	4498	4528	com/google/android/exoplayer2/ExoPlaybackException
    //   0	5	4532	java/lang/RuntimeException
    //   82	112	4532	java/lang/RuntimeException
    //   115	120	4532	java/lang/RuntimeException
    //   123	150	4532	java/lang/RuntimeException
    //   150	172	4532	java/lang/RuntimeException
    //   180	209	4532	java/lang/RuntimeException
    //   212	235	4532	java/lang/RuntimeException
    //   238	257	4532	java/lang/RuntimeException
    //   257	293	4532	java/lang/RuntimeException
    //   302	307	4532	java/lang/RuntimeException
    //   318	326	4532	java/lang/RuntimeException
    //   332	381	4532	java/lang/RuntimeException
    //   383	392	4532	java/lang/RuntimeException
    //   455	457	4532	java/lang/RuntimeException
    //   478	480	4532	java/lang/RuntimeException
    //   481	483	4532	java/lang/RuntimeException
    //   499	501	4532	java/lang/RuntimeException
    //   504	506	4532	java/lang/RuntimeException
    //   506	518	4532	java/lang/RuntimeException
    //   524	531	4532	java/lang/RuntimeException
    //   533	540	4532	java/lang/RuntimeException
    //   540	548	4532	java/lang/RuntimeException
    //   550	555	4532	java/lang/RuntimeException
    //   562	573	4532	java/lang/RuntimeException
    //   579	670	4532	java/lang/RuntimeException
    //   670	679	4532	java/lang/RuntimeException
    //   684	713	4532	java/lang/RuntimeException
    //   726	738	4532	java/lang/RuntimeException
    //   757	778	4532	java/lang/RuntimeException
    //   783	794	4532	java/lang/RuntimeException
    //   794	804	4532	java/lang/RuntimeException
    //   804	816	4532	java/lang/RuntimeException
    //   827	838	4532	java/lang/RuntimeException
    //   841	863	4532	java/lang/RuntimeException
    //   866	879	4532	java/lang/RuntimeException
    //   883	892	4532	java/lang/RuntimeException
    //   895	956	4532	java/lang/RuntimeException
    //   956	973	4532	java/lang/RuntimeException
    //   975	1001	4532	java/lang/RuntimeException
    //   1003	1007	4532	java/lang/RuntimeException
    //   1009	1035	4532	java/lang/RuntimeException
    //   1037	1151	4532	java/lang/RuntimeException
    //   1151	1155	4532	java/lang/RuntimeException
    //   1157	1199	4532	java/lang/RuntimeException
    //   1204	1235	4532	java/lang/RuntimeException
    //   1239	1246	4532	java/lang/RuntimeException
    //   1248	1287	4532	java/lang/RuntimeException
    //   1293	1316	4532	java/lang/RuntimeException
    //   1318	1349	4532	java/lang/RuntimeException
    //   1351	1395	4532	java/lang/RuntimeException
    //   1401	1417	4532	java/lang/RuntimeException
    //   1417	1424	4532	java/lang/RuntimeException
    //   1426	1449	4532	java/lang/RuntimeException
    //   1452	1457	4532	java/lang/RuntimeException
    //   1461	1470	4532	java/lang/RuntimeException
    //   1474	1490	4532	java/lang/RuntimeException
    //   1493	1499	4532	java/lang/RuntimeException
    //   1499	1509	4532	java/lang/RuntimeException
    //   1514	1526	4532	java/lang/RuntimeException
    //   1531	1538	4532	java/lang/RuntimeException
    //   1540	1599	4532	java/lang/RuntimeException
    //   1603	1623	4532	java/lang/RuntimeException
    //   1623	1663	4532	java/lang/RuntimeException
    //   1666	1677	4532	java/lang/RuntimeException
    //   1680	1708	4532	java/lang/RuntimeException
    //   1716	1776	4532	java/lang/RuntimeException
    //   1776	1825	4532	java/lang/RuntimeException
    //   1825	1857	4532	java/lang/RuntimeException
    //   1860	1877	4532	java/lang/RuntimeException
    //   1884	1891	4532	java/lang/RuntimeException
    //   1891	1925	4532	java/lang/RuntimeException
    //   1930	1965	4532	java/lang/RuntimeException
    //   1968	1990	4532	java/lang/RuntimeException
    //   1999	2052	4532	java/lang/RuntimeException
    //   2055	2073	4532	java/lang/RuntimeException
    //   2073	2080	4532	java/lang/RuntimeException
    //   2082	2103	4532	java/lang/RuntimeException
    //   2119	2121	4532	java/lang/RuntimeException
    //   2121	2125	4532	java/lang/RuntimeException
    //   2127	2153	4532	java/lang/RuntimeException
    //   2156	2165	4532	java/lang/RuntimeException
    //   2165	2183	4532	java/lang/RuntimeException
    //   2185	2217	4532	java/lang/RuntimeException
    //   2219	2226	4532	java/lang/RuntimeException
    //   2230	2283	4532	java/lang/RuntimeException
    //   2285	2297	4532	java/lang/RuntimeException
    //   2302	2342	4532	java/lang/RuntimeException
    //   2418	2450	4532	java/lang/RuntimeException
    //   2450	2454	4532	java/lang/RuntimeException
    //   2500	2522	4532	java/lang/RuntimeException
    //   2533	2545	4532	java/lang/RuntimeException
    //   2548	2584	4532	java/lang/RuntimeException
    //   2584	2634	4532	java/lang/RuntimeException
    //   2637	2677	4532	java/lang/RuntimeException
    //   2680	2707	4532	java/lang/RuntimeException
    //   2707	2751	4532	java/lang/RuntimeException
    //   2751	2779	4532	java/lang/RuntimeException
    //   2784	2815	4532	java/lang/RuntimeException
    //   2819	2861	4532	java/lang/RuntimeException
    //   2865	2888	4532	java/lang/RuntimeException
    //   2891	2907	4532	java/lang/RuntimeException
    //   2910	2951	4532	java/lang/RuntimeException
    //   2953	2961	4532	java/lang/RuntimeException
    //   2967	2979	4532	java/lang/RuntimeException
    //   2982	3008	4532	java/lang/RuntimeException
    //   3012	3019	4532	java/lang/RuntimeException
    //   3027	3047	4532	java/lang/RuntimeException
    //   3047	3054	4532	java/lang/RuntimeException
    //   3059	3067	4532	java/lang/RuntimeException
    //   3071	3092	4532	java/lang/RuntimeException
    //   3092	3150	4532	java/lang/RuntimeException
    //   3150	3173	4532	java/lang/RuntimeException
    //   3173	3178	4532	java/lang/RuntimeException
    //   3197	3214	4532	java/lang/RuntimeException
    //   3217	3235	4532	java/lang/RuntimeException
    //   3238	3243	4532	java/lang/RuntimeException
    //   3243	3250	4532	java/lang/RuntimeException
    //   3250	3357	4532	java/lang/RuntimeException
    //   3360	3373	4532	java/lang/RuntimeException
    //   3375	3402	4532	java/lang/RuntimeException
    //   3407	3433	4532	java/lang/RuntimeException
    //   3436	3474	4532	java/lang/RuntimeException
    //   3479	3488	4532	java/lang/RuntimeException
    //   3491	3562	4532	java/lang/RuntimeException
    //   3567	3597	4532	java/lang/RuntimeException
    //   3601	3640	4532	java/lang/RuntimeException
    //   3644	3665	4532	java/lang/RuntimeException
    //   3668	3689	4532	java/lang/RuntimeException
    //   3698	3723	4532	java/lang/RuntimeException
    //   3726	3733	4532	java/lang/RuntimeException
    //   3736	3756	4532	java/lang/RuntimeException
    //   3759	3799	4532	java/lang/RuntimeException
    //   3817	3831	4532	java/lang/RuntimeException
    //   3835	3844	4532	java/lang/RuntimeException
    //   3849	3867	4532	java/lang/RuntimeException
    //   3875	3881	4532	java/lang/RuntimeException
    //   3889	3893	4532	java/lang/RuntimeException
    //   3893	3950	4532	java/lang/RuntimeException
    //   3950	3962	4532	java/lang/RuntimeException
    //   3975	3988	4532	java/lang/RuntimeException
    //   3988	4010	4532	java/lang/RuntimeException
    //   4013	4029	4532	java/lang/RuntimeException
    //   4034	4067	4532	java/lang/RuntimeException
    //   4070	4081	4532	java/lang/RuntimeException
    //   4094	4104	4532	java/lang/RuntimeException
    //   4110	4119	4532	java/lang/RuntimeException
    //   4119	4142	4532	java/lang/RuntimeException
    //   4145	4153	4532	java/lang/RuntimeException
    //   4158	4174	4532	java/lang/RuntimeException
    //   4177	4193	4532	java/lang/RuntimeException
    //   4196	4204	4532	java/lang/RuntimeException
    //   4209	4226	4532	java/lang/RuntimeException
    //   4226	4242	4532	java/lang/RuntimeException
    //   4249	4257	4532	java/lang/RuntimeException
    //   4264	4279	4532	java/lang/RuntimeException
    //   4279	4287	4532	java/lang/RuntimeException
    //   4287	4296	4532	java/lang/RuntimeException
    //   4299	4324	4532	java/lang/RuntimeException
    //   4327	4335	4532	java/lang/RuntimeException
    //   4335	4338	4532	java/lang/RuntimeException
    //   4341	4348	4532	java/lang/RuntimeException
    //   4354	4365	4532	java/lang/RuntimeException
    //   4370	4378	4532	java/lang/RuntimeException
    //   4381	4402	4532	java/lang/RuntimeException
    //   4405	4422	4532	java/lang/RuntimeException
    //   4425	4441	4532	java/lang/RuntimeException
    //   4446	4455	4532	java/lang/RuntimeException
    //   4455	4460	4532	java/lang/RuntimeException
    //   4460	4469	4532	java/lang/RuntimeException
    //   4473	4487	4532	java/lang/RuntimeException
    //   4487	4498	4532	java/lang/RuntimeException
    //   4498	4522	4532	java/lang/RuntimeException
    //   0	5	4566	java/io/IOException
    //   0	5	4600	com/google/android/exoplayer2/ExoPlaybackException
    //   2364	2379	4716	finally
    //   2383	2391	4716	finally
    //   2395	2400	4716	finally
    //   2475	2485	4716	finally
    //   82	112	4829	java/io/IOException
    //   115	120	4829	java/io/IOException
    //   123	150	4829	java/io/IOException
    //   150	172	4829	java/io/IOException
    //   180	209	4829	java/io/IOException
    //   212	235	4829	java/io/IOException
    //   238	257	4829	java/io/IOException
    //   257	293	4829	java/io/IOException
    //   302	307	4829	java/io/IOException
    //   318	326	4829	java/io/IOException
    //   332	381	4829	java/io/IOException
    //   383	392	4829	java/io/IOException
    //   455	457	4829	java/io/IOException
    //   478	480	4829	java/io/IOException
    //   481	483	4829	java/io/IOException
    //   499	501	4829	java/io/IOException
    //   504	506	4829	java/io/IOException
    //   506	518	4829	java/io/IOException
    //   524	531	4829	java/io/IOException
    //   533	540	4829	java/io/IOException
    //   540	548	4829	java/io/IOException
    //   550	555	4829	java/io/IOException
    //   562	573	4829	java/io/IOException
    //   579	670	4829	java/io/IOException
    //   670	679	4829	java/io/IOException
    //   684	713	4829	java/io/IOException
    //   726	738	4829	java/io/IOException
    //   757	778	4829	java/io/IOException
    //   783	794	4829	java/io/IOException
    //   794	804	4829	java/io/IOException
    //   804	816	4829	java/io/IOException
    //   827	838	4829	java/io/IOException
    //   841	863	4829	java/io/IOException
    //   866	879	4829	java/io/IOException
    //   883	892	4829	java/io/IOException
    //   895	956	4829	java/io/IOException
    //   956	973	4829	java/io/IOException
    //   975	1001	4829	java/io/IOException
    //   1003	1007	4829	java/io/IOException
    //   1009	1035	4829	java/io/IOException
    //   1037	1151	4829	java/io/IOException
    //   1151	1155	4829	java/io/IOException
    //   1157	1199	4829	java/io/IOException
    //   1204	1235	4829	java/io/IOException
    //   1239	1246	4829	java/io/IOException
    //   1248	1287	4829	java/io/IOException
    //   1293	1316	4829	java/io/IOException
    //   1318	1349	4829	java/io/IOException
    //   1351	1395	4829	java/io/IOException
    //   1401	1417	4829	java/io/IOException
    //   1417	1424	4829	java/io/IOException
    //   1426	1449	4829	java/io/IOException
    //   1452	1457	4829	java/io/IOException
    //   1461	1470	4829	java/io/IOException
    //   1474	1490	4829	java/io/IOException
    //   1493	1499	4829	java/io/IOException
    //   1499	1509	4829	java/io/IOException
    //   1514	1526	4829	java/io/IOException
    //   1531	1538	4829	java/io/IOException
    //   1540	1599	4829	java/io/IOException
    //   1603	1623	4829	java/io/IOException
    //   1623	1663	4829	java/io/IOException
    //   1666	1677	4829	java/io/IOException
    //   1680	1708	4829	java/io/IOException
    //   1716	1776	4829	java/io/IOException
    //   1776	1825	4829	java/io/IOException
    //   1825	1857	4829	java/io/IOException
    //   1860	1877	4829	java/io/IOException
    //   1884	1891	4829	java/io/IOException
    //   1891	1925	4829	java/io/IOException
    //   1930	1965	4829	java/io/IOException
    //   1968	1990	4829	java/io/IOException
    //   1999	2052	4829	java/io/IOException
    //   2055	2073	4829	java/io/IOException
    //   2073	2080	4829	java/io/IOException
    //   2082	2103	4829	java/io/IOException
    //   2119	2121	4829	java/io/IOException
    //   2121	2125	4829	java/io/IOException
    //   2127	2153	4829	java/io/IOException
    //   2156	2165	4829	java/io/IOException
    //   2165	2183	4829	java/io/IOException
    //   2185	2217	4829	java/io/IOException
    //   2219	2226	4829	java/io/IOException
    //   2230	2283	4829	java/io/IOException
    //   2285	2297	4829	java/io/IOException
    //   2302	2342	4829	java/io/IOException
    //   2418	2450	4829	java/io/IOException
    //   2450	2454	4829	java/io/IOException
    //   2500	2522	4829	java/io/IOException
    //   2533	2545	4829	java/io/IOException
    //   2548	2584	4829	java/io/IOException
    //   2584	2634	4829	java/io/IOException
    //   2637	2677	4829	java/io/IOException
    //   2680	2707	4829	java/io/IOException
    //   2707	2751	4829	java/io/IOException
    //   4455	4460	4829	java/io/IOException
    //   4498	4522	4829	java/io/IOException
    //   82	112	4833	com/google/android/exoplayer2/ExoPlaybackException
    //   115	120	4833	com/google/android/exoplayer2/ExoPlaybackException
    //   123	150	4833	com/google/android/exoplayer2/ExoPlaybackException
    //   150	172	4833	com/google/android/exoplayer2/ExoPlaybackException
    //   180	209	4833	com/google/android/exoplayer2/ExoPlaybackException
    //   212	235	4833	com/google/android/exoplayer2/ExoPlaybackException
    //   238	257	4833	com/google/android/exoplayer2/ExoPlaybackException
    //   257	293	4833	com/google/android/exoplayer2/ExoPlaybackException
    //   302	307	4833	com/google/android/exoplayer2/ExoPlaybackException
    //   318	326	4833	com/google/android/exoplayer2/ExoPlaybackException
    //   332	381	4833	com/google/android/exoplayer2/ExoPlaybackException
    //   383	392	4833	com/google/android/exoplayer2/ExoPlaybackException
    //   455	457	4833	com/google/android/exoplayer2/ExoPlaybackException
    //   478	480	4833	com/google/android/exoplayer2/ExoPlaybackException
    //   481	483	4833	com/google/android/exoplayer2/ExoPlaybackException
    //   499	501	4833	com/google/android/exoplayer2/ExoPlaybackException
    //   504	506	4833	com/google/android/exoplayer2/ExoPlaybackException
    //   506	518	4833	com/google/android/exoplayer2/ExoPlaybackException
    //   524	531	4833	com/google/android/exoplayer2/ExoPlaybackException
    //   533	540	4833	com/google/android/exoplayer2/ExoPlaybackException
    //   540	548	4833	com/google/android/exoplayer2/ExoPlaybackException
    //   550	555	4833	com/google/android/exoplayer2/ExoPlaybackException
    //   562	573	4833	com/google/android/exoplayer2/ExoPlaybackException
    //   579	670	4833	com/google/android/exoplayer2/ExoPlaybackException
    //   670	679	4833	com/google/android/exoplayer2/ExoPlaybackException
    //   684	713	4833	com/google/android/exoplayer2/ExoPlaybackException
    //   726	738	4833	com/google/android/exoplayer2/ExoPlaybackException
    //   757	778	4833	com/google/android/exoplayer2/ExoPlaybackException
    //   783	794	4833	com/google/android/exoplayer2/ExoPlaybackException
    //   794	804	4833	com/google/android/exoplayer2/ExoPlaybackException
    //   804	816	4833	com/google/android/exoplayer2/ExoPlaybackException
    //   827	838	4833	com/google/android/exoplayer2/ExoPlaybackException
    //   841	863	4833	com/google/android/exoplayer2/ExoPlaybackException
    //   866	879	4833	com/google/android/exoplayer2/ExoPlaybackException
    //   883	892	4833	com/google/android/exoplayer2/ExoPlaybackException
    //   895	956	4833	com/google/android/exoplayer2/ExoPlaybackException
    //   956	973	4833	com/google/android/exoplayer2/ExoPlaybackException
    //   975	1001	4833	com/google/android/exoplayer2/ExoPlaybackException
    //   1003	1007	4833	com/google/android/exoplayer2/ExoPlaybackException
    //   1009	1035	4833	com/google/android/exoplayer2/ExoPlaybackException
    //   1037	1151	4833	com/google/android/exoplayer2/ExoPlaybackException
    //   1151	1155	4833	com/google/android/exoplayer2/ExoPlaybackException
    //   1157	1199	4833	com/google/android/exoplayer2/ExoPlaybackException
    //   1204	1235	4833	com/google/android/exoplayer2/ExoPlaybackException
    //   1239	1246	4833	com/google/android/exoplayer2/ExoPlaybackException
    //   1248	1287	4833	com/google/android/exoplayer2/ExoPlaybackException
    //   1293	1316	4833	com/google/android/exoplayer2/ExoPlaybackException
    //   1318	1349	4833	com/google/android/exoplayer2/ExoPlaybackException
    //   1351	1395	4833	com/google/android/exoplayer2/ExoPlaybackException
    //   1401	1417	4833	com/google/android/exoplayer2/ExoPlaybackException
    //   1417	1424	4833	com/google/android/exoplayer2/ExoPlaybackException
    //   1426	1449	4833	com/google/android/exoplayer2/ExoPlaybackException
    //   1452	1457	4833	com/google/android/exoplayer2/ExoPlaybackException
    //   1461	1470	4833	com/google/android/exoplayer2/ExoPlaybackException
    //   1474	1490	4833	com/google/android/exoplayer2/ExoPlaybackException
    //   1493	1499	4833	com/google/android/exoplayer2/ExoPlaybackException
    //   1499	1509	4833	com/google/android/exoplayer2/ExoPlaybackException
    //   1514	1526	4833	com/google/android/exoplayer2/ExoPlaybackException
    //   1531	1538	4833	com/google/android/exoplayer2/ExoPlaybackException
    //   1540	1599	4833	com/google/android/exoplayer2/ExoPlaybackException
    //   1603	1623	4833	com/google/android/exoplayer2/ExoPlaybackException
    //   1623	1663	4833	com/google/android/exoplayer2/ExoPlaybackException
    //   1666	1677	4833	com/google/android/exoplayer2/ExoPlaybackException
    //   1680	1708	4833	com/google/android/exoplayer2/ExoPlaybackException
    //   1716	1776	4833	com/google/android/exoplayer2/ExoPlaybackException
    //   1776	1825	4833	com/google/android/exoplayer2/ExoPlaybackException
    //   1825	1857	4833	com/google/android/exoplayer2/ExoPlaybackException
    //   1860	1877	4833	com/google/android/exoplayer2/ExoPlaybackException
    //   1884	1891	4833	com/google/android/exoplayer2/ExoPlaybackException
    //   1891	1925	4833	com/google/android/exoplayer2/ExoPlaybackException
    //   1930	1965	4833	com/google/android/exoplayer2/ExoPlaybackException
    //   1968	1990	4833	com/google/android/exoplayer2/ExoPlaybackException
    //   1999	2052	4833	com/google/android/exoplayer2/ExoPlaybackException
    //   2055	2073	4833	com/google/android/exoplayer2/ExoPlaybackException
    //   2073	2080	4833	com/google/android/exoplayer2/ExoPlaybackException
    //   2082	2103	4833	com/google/android/exoplayer2/ExoPlaybackException
    //   2119	2121	4833	com/google/android/exoplayer2/ExoPlaybackException
    //   2121	2125	4833	com/google/android/exoplayer2/ExoPlaybackException
    //   2127	2153	4833	com/google/android/exoplayer2/ExoPlaybackException
    //   2156	2165	4833	com/google/android/exoplayer2/ExoPlaybackException
    //   2165	2183	4833	com/google/android/exoplayer2/ExoPlaybackException
    //   2185	2217	4833	com/google/android/exoplayer2/ExoPlaybackException
    //   2219	2226	4833	com/google/android/exoplayer2/ExoPlaybackException
    //   2230	2283	4833	com/google/android/exoplayer2/ExoPlaybackException
    //   2285	2297	4833	com/google/android/exoplayer2/ExoPlaybackException
    //   2302	2342	4833	com/google/android/exoplayer2/ExoPlaybackException
    //   2418	2450	4833	com/google/android/exoplayer2/ExoPlaybackException
    //   2450	2454	4833	com/google/android/exoplayer2/ExoPlaybackException
    //   2500	2522	4833	com/google/android/exoplayer2/ExoPlaybackException
    //   2533	2545	4833	com/google/android/exoplayer2/ExoPlaybackException
    //   2548	2584	4833	com/google/android/exoplayer2/ExoPlaybackException
    //   2584	2634	4833	com/google/android/exoplayer2/ExoPlaybackException
    //   2637	2677	4833	com/google/android/exoplayer2/ExoPlaybackException
    //   2680	2707	4833	com/google/android/exoplayer2/ExoPlaybackException
    //   2707	2751	4833	com/google/android/exoplayer2/ExoPlaybackException
    //   4455	4460	4833	com/google/android/exoplayer2/ExoPlaybackException
    //   4498	4522	4833	com/google/android/exoplayer2/ExoPlaybackException
  }
}
