package com.db.pwcc.dbmobile.foundation.data.manager.broadcasting;

import android.content.BroadcastReceiver;
import android.content.IntentFilter;
import android.os.Bundle;
import com.db.pwcc.dbmobile.model.error.DbError;
import java.lang.reflect.InvocationTargetException;
import java.lang.reflect.Method;
import uuuuuu.ppphhp;
import xxxxxx.uxxxxx;

public abstract class ModelUpdatedBroadcastReceiver
  extends BroadcastReceiver
{
  private static final String BR_ACTION_MODEL_UPDATED = "\006\004\030\006%\024\t\027\013\022\021\037-\021\"0\023\026(\036%%7&)\037!)=40%#7))";
  private static final String BR_EXTRA_BUNDLE = "^ZlXubUaSXUamO^jOa\\YGdFXPELD";
  private static final String BR_EXTRA_ERROR = "CAUCbQFTHON\\jN_mThedTsZhigk";
  private static final String BR_EXTRA_MODEL_TAG = "kgye\003obn`ebnz\\kw\\nifTq^_SSYk_KP";
  public static int b006C006C006C006C006C006Cl = 1;
  public static int b006Cl006C006C006C006Cl = 8;
  public static int bl006Cllll006C = 0;
  public static int bllllll006C = 2;
  
  public ModelUpdatedBroadcastReceiver() {}
  
  public static int b006C006Cllll006C()
  {
    return 1;
  }
  
  public static int b006Clllll006C()
  {
    return 42;
  }
  
  public static int bl006C006C006C006C006Cl()
  {
    return 0;
  }
  
  public static int bll006Clll006C()
  {
    return 2;
  }
  
  /* Error */
  public static android.content.Intent makeModelUpdatedIntent(String paramString, Bundle paramBundle, DbError paramDbError)
  {
    // Byte code:
    //   0: new 42	android/content/Intent
    //   3: dup
    //   4: invokespecial 43	android/content/Intent:<init>	()V
    //   7: astore_3
    //   8: ldc 45
    //   10: ldc 47
    //   12: sipush 220
    //   15: iconst_1
    //   16: invokestatic 53	xxxxxx/uxxxxx:bb00620062bb0062b0062b0062	(Ljava/lang/String;CC)Ljava/lang/String;
    //   19: iconst_3
    //   20: anewarray 55	java/lang/Class
    //   23: dup
    //   24: iconst_0
    //   25: ldc 57
    //   27: aastore
    //   28: dup
    //   29: iconst_1
    //   30: getstatic 63	java/lang/Character:TYPE	Ljava/lang/Class;
    //   33: aastore
    //   34: dup
    //   35: iconst_2
    //   36: getstatic 63	java/lang/Character:TYPE	Ljava/lang/Class;
    //   39: aastore
    //   40: invokevirtual 67	java/lang/Class:getMethod	(Ljava/lang/String;[Ljava/lang/Class;)Ljava/lang/reflect/Method;
    //   43: astore 4
    //   45: aload 4
    //   47: aconst_null
    //   48: iconst_3
    //   49: anewarray 69	java/lang/Object
    //   52: dup
    //   53: iconst_0
    //   54: ldc 71
    //   56: aastore
    //   57: dup
    //   58: iconst_1
    //   59: sipush 164
    //   62: invokestatic 75	java/lang/Character:valueOf	(C)Ljava/lang/Character;
    //   65: aastore
    //   66: dup
    //   67: iconst_2
    //   68: iconst_1
    //   69: invokestatic 75	java/lang/Character:valueOf	(C)Ljava/lang/Character;
    //   72: aastore
    //   73: invokevirtual 81	java/lang/reflect/Method:invoke	(Ljava/lang/Object;[Ljava/lang/Object;)Ljava/lang/Object;
    //   76: astore 4
    //   78: aload_3
    //   79: aload 4
    //   81: checkcast 57	java/lang/String
    //   84: invokevirtual 85	android/content/Intent:setAction	(Ljava/lang/String;)Landroid/content/Intent;
    //   87: pop
    //   88: getstatic 87	com/db/pwcc/dbmobile/foundation/data/manager/broadcasting/ModelUpdatedBroadcastReceiver:b006Cl006C006C006C006Cl	I
    //   91: getstatic 89	com/db/pwcc/dbmobile/foundation/data/manager/broadcasting/ModelUpdatedBroadcastReceiver:b006C006C006C006C006C006Cl	I
    //   94: iadd
    //   95: getstatic 87	com/db/pwcc/dbmobile/foundation/data/manager/broadcasting/ModelUpdatedBroadcastReceiver:b006Cl006C006C006C006Cl	I
    //   98: imul
    //   99: getstatic 91	com/db/pwcc/dbmobile/foundation/data/manager/broadcasting/ModelUpdatedBroadcastReceiver:bllllll006C	I
    //   102: irem
    //   103: getstatic 93	com/db/pwcc/dbmobile/foundation/data/manager/broadcasting/ModelUpdatedBroadcastReceiver:bl006Cllll006C	I
    //   106: if_icmpeq +14 -> 120
    //   109: invokestatic 95	com/db/pwcc/dbmobile/foundation/data/manager/broadcasting/ModelUpdatedBroadcastReceiver:b006Clllll006C	()I
    //   112: putstatic 87	com/db/pwcc/dbmobile/foundation/data/manager/broadcasting/ModelUpdatedBroadcastReceiver:b006Cl006C006C006C006Cl	I
    //   115: bipush 38
    //   117: putstatic 93	com/db/pwcc/dbmobile/foundation/data/manager/broadcasting/ModelUpdatedBroadcastReceiver:bl006Cllll006C	I
    //   120: ldc 45
    //   122: ldc 97
    //   124: sipush 196
    //   127: iconst_5
    //   128: invokestatic 53	xxxxxx/uxxxxx:bb00620062bb0062b0062b0062	(Ljava/lang/String;CC)Ljava/lang/String;
    //   131: iconst_4
    //   132: anewarray 55	java/lang/Class
    //   135: dup
    //   136: iconst_0
    //   137: ldc 57
    //   139: aastore
    //   140: dup
    //   141: iconst_1
    //   142: getstatic 63	java/lang/Character:TYPE	Ljava/lang/Class;
    //   145: aastore
    //   146: dup
    //   147: iconst_2
    //   148: getstatic 63	java/lang/Character:TYPE	Ljava/lang/Class;
    //   151: aastore
    //   152: dup
    //   153: iconst_3
    //   154: getstatic 63	java/lang/Character:TYPE	Ljava/lang/Class;
    //   157: aastore
    //   158: invokevirtual 67	java/lang/Class:getMethod	(Ljava/lang/String;[Ljava/lang/Class;)Ljava/lang/reflect/Method;
    //   161: astore 4
    //   163: aload 4
    //   165: aconst_null
    //   166: iconst_4
    //   167: anewarray 69	java/lang/Object
    //   170: dup
    //   171: iconst_0
    //   172: ldc 99
    //   174: aastore
    //   175: dup
    //   176: iconst_1
    //   177: sipush 227
    //   180: invokestatic 75	java/lang/Character:valueOf	(C)Ljava/lang/Character;
    //   183: aastore
    //   184: dup
    //   185: iconst_2
    //   186: sipush 195
    //   189: invokestatic 75	java/lang/Character:valueOf	(C)Ljava/lang/Character;
    //   192: aastore
    //   193: dup
    //   194: iconst_3
    //   195: iconst_0
    //   196: invokestatic 75	java/lang/Character:valueOf	(C)Ljava/lang/Character;
    //   199: aastore
    //   200: invokevirtual 81	java/lang/reflect/Method:invoke	(Ljava/lang/Object;[Ljava/lang/Object;)Ljava/lang/Object;
    //   203: astore 4
    //   205: aload_3
    //   206: aload 4
    //   208: checkcast 57	java/lang/String
    //   211: aload_0
    //   212: invokevirtual 103	android/content/Intent:putExtra	(Ljava/lang/String;Ljava/lang/String;)Landroid/content/Intent;
    //   215: pop
    //   216: aload_1
    //   217: ifnull +94 -> 311
    //   220: ldc 45
    //   222: ldc 105
    //   224: sipush 241
    //   227: iconst_1
    //   228: invokestatic 53	xxxxxx/uxxxxx:bb00620062bb0062b0062b0062	(Ljava/lang/String;CC)Ljava/lang/String;
    //   231: iconst_4
    //   232: anewarray 55	java/lang/Class
    //   235: dup
    //   236: iconst_0
    //   237: ldc 57
    //   239: aastore
    //   240: dup
    //   241: iconst_1
    //   242: getstatic 63	java/lang/Character:TYPE	Ljava/lang/Class;
    //   245: aastore
    //   246: dup
    //   247: iconst_2
    //   248: getstatic 63	java/lang/Character:TYPE	Ljava/lang/Class;
    //   251: aastore
    //   252: dup
    //   253: iconst_3
    //   254: getstatic 63	java/lang/Character:TYPE	Ljava/lang/Class;
    //   257: aastore
    //   258: invokevirtual 67	java/lang/Class:getMethod	(Ljava/lang/String;[Ljava/lang/Class;)Ljava/lang/reflect/Method;
    //   261: astore_0
    //   262: aload_0
    //   263: aconst_null
    //   264: iconst_4
    //   265: anewarray 69	java/lang/Object
    //   268: dup
    //   269: iconst_0
    //   270: ldc 107
    //   272: aastore
    //   273: dup
    //   274: iconst_1
    //   275: bipush 66
    //   277: invokestatic 75	java/lang/Character:valueOf	(C)Ljava/lang/Character;
    //   280: aastore
    //   281: dup
    //   282: iconst_2
    //   283: sipush 173
    //   286: invokestatic 75	java/lang/Character:valueOf	(C)Ljava/lang/Character;
    //   289: aastore
    //   290: dup
    //   291: iconst_3
    //   292: iconst_0
    //   293: invokestatic 75	java/lang/Character:valueOf	(C)Ljava/lang/Character;
    //   296: aastore
    //   297: invokevirtual 81	java/lang/reflect/Method:invoke	(Ljava/lang/Object;[Ljava/lang/Object;)Ljava/lang/Object;
    //   300: astore_0
    //   301: aload_3
    //   302: aload_0
    //   303: checkcast 57	java/lang/String
    //   306: aload_1
    //   307: invokevirtual 110	android/content/Intent:putExtra	(Ljava/lang/String;Landroid/os/Bundle;)Landroid/content/Intent;
    //   310: pop
    //   311: aload_2
    //   312: ifnull +114 -> 426
    //   315: ldc 45
    //   317: ldc 112
    //   319: bipush 47
    //   321: iconst_0
    //   322: invokestatic 53	xxxxxx/uxxxxx:bb00620062bb0062b0062b0062	(Ljava/lang/String;CC)Ljava/lang/String;
    //   325: iconst_3
    //   326: anewarray 55	java/lang/Class
    //   329: dup
    //   330: iconst_0
    //   331: ldc 57
    //   333: aastore
    //   334: dup
    //   335: iconst_1
    //   336: getstatic 63	java/lang/Character:TYPE	Ljava/lang/Class;
    //   339: aastore
    //   340: dup
    //   341: iconst_2
    //   342: getstatic 63	java/lang/Character:TYPE	Ljava/lang/Class;
    //   345: aastore
    //   346: invokevirtual 67	java/lang/Class:getMethod	(Ljava/lang/String;[Ljava/lang/Class;)Ljava/lang/reflect/Method;
    //   349: astore_0
    //   350: aload_0
    //   351: aconst_null
    //   352: iconst_3
    //   353: anewarray 69	java/lang/Object
    //   356: dup
    //   357: iconst_0
    //   358: ldc 114
    //   360: aastore
    //   361: dup
    //   362: iconst_1
    //   363: sipush 137
    //   366: invokestatic 75	java/lang/Character:valueOf	(C)Ljava/lang/Character;
    //   369: aastore
    //   370: dup
    //   371: iconst_2
    //   372: iconst_3
    //   373: invokestatic 75	java/lang/Character:valueOf	(C)Ljava/lang/Character;
    //   376: aastore
    //   377: invokevirtual 81	java/lang/reflect/Method:invoke	(Ljava/lang/Object;[Ljava/lang/Object;)Ljava/lang/Object;
    //   380: astore_0
    //   381: aload_0
    //   382: checkcast 57	java/lang/String
    //   385: astore_0
    //   386: getstatic 87	com/db/pwcc/dbmobile/foundation/data/manager/broadcasting/ModelUpdatedBroadcastReceiver:b006Cl006C006C006C006Cl	I
    //   389: getstatic 89	com/db/pwcc/dbmobile/foundation/data/manager/broadcasting/ModelUpdatedBroadcastReceiver:b006C006C006C006C006C006Cl	I
    //   392: iadd
    //   393: getstatic 87	com/db/pwcc/dbmobile/foundation/data/manager/broadcasting/ModelUpdatedBroadcastReceiver:b006Cl006C006C006C006Cl	I
    //   396: imul
    //   397: getstatic 91	com/db/pwcc/dbmobile/foundation/data/manager/broadcasting/ModelUpdatedBroadcastReceiver:bllllll006C	I
    //   400: irem
    //   401: invokestatic 116	com/db/pwcc/dbmobile/foundation/data/manager/broadcasting/ModelUpdatedBroadcastReceiver:bl006C006C006C006C006Cl	()I
    //   404: if_icmpeq +15 -> 419
    //   407: invokestatic 95	com/db/pwcc/dbmobile/foundation/data/manager/broadcasting/ModelUpdatedBroadcastReceiver:b006Clllll006C	()I
    //   410: putstatic 87	com/db/pwcc/dbmobile/foundation/data/manager/broadcasting/ModelUpdatedBroadcastReceiver:b006Cl006C006C006C006Cl	I
    //   413: invokestatic 95	com/db/pwcc/dbmobile/foundation/data/manager/broadcasting/ModelUpdatedBroadcastReceiver:b006Clllll006C	()I
    //   416: putstatic 89	com/db/pwcc/dbmobile/foundation/data/manager/broadcasting/ModelUpdatedBroadcastReceiver:b006C006C006C006C006C006Cl	I
    //   419: aload_3
    //   420: aload_0
    //   421: aload_2
    //   422: invokevirtual 119	android/content/Intent:putExtra	(Ljava/lang/String;Landroid/os/Parcelable;)Landroid/content/Intent;
    //   425: pop
    //   426: aload_3
    //   427: areturn
    //   428: astore_0
    //   429: aload_0
    //   430: invokevirtual 123	java/lang/reflect/InvocationTargetException:getCause	()Ljava/lang/Throwable;
    //   433: athrow
    //   434: astore_0
    //   435: aload_0
    //   436: invokevirtual 123	java/lang/reflect/InvocationTargetException:getCause	()Ljava/lang/Throwable;
    //   439: athrow
    //   440: astore_0
    //   441: aload_0
    //   442: invokevirtual 123	java/lang/reflect/InvocationTargetException:getCause	()Ljava/lang/Throwable;
    //   445: athrow
    //   446: astore_0
    //   447: aload_0
    //   448: invokevirtual 123	java/lang/reflect/InvocationTargetException:getCause	()Ljava/lang/Throwable;
    //   451: athrow
    // Local variable table:
    //   start	length	slot	name	signature
    //   0	452	0	paramString	String
    //   0	452	1	paramBundle	Bundle
    //   0	452	2	paramDbError	DbError
    //   7	420	3	localIntent	android.content.Intent
    //   43	164	4	localObject	Object
    // Exception table:
    //   from	to	target	type
    //   350	381	428	java/lang/reflect/InvocationTargetException
    //   45	78	434	java/lang/reflect/InvocationTargetException
    //   262	301	440	java/lang/reflect/InvocationTargetException
    //   163	205	446	java/lang/reflect/InvocationTargetException
  }
  
  public static IntentFilter makeModelUpdatedIntentFilter()
  {
    if ((b006Clllll006C() + b006C006C006C006C006C006Cl) * b006Clllll006C() % bllllll006C != bl006Cllll006C)
    {
      b006Cl006C006C006C006Cl = 32;
      bl006Cllll006C = 49;
    }
    IntentFilter localIntentFilter = new IntentFilter();
    Object localObject = ppphhp.class.getMethod(uxxxxx.bbbb0062b0062b0062b0062("\022(abjk-.ghpqkltu7pqyztu}~@", 'M', 'a', '\003'), new Class[] { String.class, Character.TYPE, Character.TYPE, Character.TYPE });
    try
    {
      localObject = ((Method)localObject).invoke(null, new Object[] { "\\XjVs`S_QVS_kM\\hIJZNSQaNOCCI[PJ=9K;9", Character.valueOf('º'), Character.valueOf('«'), Character.valueOf('\000') });
      localIntentFilter.addAction((String)localObject);
      if ((b006Cl006C006C006C006Cl + b006C006C006C006C006C006Cl) * b006Cl006C006C006C006Cl % bllllll006C != bl006Cllll006C)
      {
        b006Cl006C006C006C006Cl = 92;
        bl006Cllll006C = b006Clllll006C();
      }
      return localIntentFilter;
    }
    catch (InvocationTargetException localInvocationTargetException)
    {
      throw localInvocationTargetException.getCause();
    }
  }
  
  public abstract void onDataModelUpdateFailed(String paramString, DbError paramDbError, Bundle paramBundle);
  
  public abstract void onDataModelUpdated(String paramString, Bundle paramBundle);
  
  /* Error */
  public void onReceive(android.content.Context paramContext, android.content.Intent paramIntent)
  {
    // Byte code:
    //   0: aload_2
    //   1: invokevirtual 150	android/content/Intent:getAction	()Ljava/lang/String;
    //   4: astore_1
    //   5: aload_1
    //   6: ifnonnull +4 -> 10
    //   9: return
    //   10: ldc 45
    //   12: ldc -104
    //   14: bipush 41
    //   16: bipush 84
    //   18: iconst_2
    //   19: invokestatic 134	xxxxxx/uxxxxx:bbbb0062b0062b0062b0062	(Ljava/lang/String;CCC)Ljava/lang/String;
    //   22: iconst_3
    //   23: anewarray 55	java/lang/Class
    //   26: dup
    //   27: iconst_0
    //   28: ldc 57
    //   30: aastore
    //   31: dup
    //   32: iconst_1
    //   33: getstatic 63	java/lang/Character:TYPE	Ljava/lang/Class;
    //   36: aastore
    //   37: dup
    //   38: iconst_2
    //   39: getstatic 63	java/lang/Character:TYPE	Ljava/lang/Class;
    //   42: aastore
    //   43: invokevirtual 67	java/lang/Class:getMethod	(Ljava/lang/String;[Ljava/lang/Class;)Ljava/lang/reflect/Method;
    //   46: astore 4
    //   48: aload 4
    //   50: aconst_null
    //   51: iconst_3
    //   52: anewarray 69	java/lang/Object
    //   55: dup
    //   56: iconst_0
    //   57: ldc -102
    //   59: aastore
    //   60: dup
    //   61: iconst_1
    //   62: sipush 244
    //   65: invokestatic 75	java/lang/Character:valueOf	(C)Ljava/lang/Character;
    //   68: aastore
    //   69: dup
    //   70: iconst_2
    //   71: iconst_0
    //   72: invokestatic 75	java/lang/Character:valueOf	(C)Ljava/lang/Character;
    //   75: aastore
    //   76: invokevirtual 81	java/lang/reflect/Method:invoke	(Ljava/lang/Object;[Ljava/lang/Object;)Ljava/lang/Object;
    //   79: astore 4
    //   81: aload_1
    //   82: aload 4
    //   84: checkcast 57	java/lang/String
    //   87: invokevirtual 158	java/lang/String:equals	(Ljava/lang/Object;)Z
    //   90: istore_3
    //   91: getstatic 87	com/db/pwcc/dbmobile/foundation/data/manager/broadcasting/ModelUpdatedBroadcastReceiver:b006Cl006C006C006C006Cl	I
    //   94: getstatic 89	com/db/pwcc/dbmobile/foundation/data/manager/broadcasting/ModelUpdatedBroadcastReceiver:b006C006C006C006C006C006Cl	I
    //   97: iadd
    //   98: getstatic 87	com/db/pwcc/dbmobile/foundation/data/manager/broadcasting/ModelUpdatedBroadcastReceiver:b006Cl006C006C006C006Cl	I
    //   101: imul
    //   102: invokestatic 160	com/db/pwcc/dbmobile/foundation/data/manager/broadcasting/ModelUpdatedBroadcastReceiver:bll006Clll006C	()I
    //   105: irem
    //   106: invokestatic 116	com/db/pwcc/dbmobile/foundation/data/manager/broadcasting/ModelUpdatedBroadcastReceiver:bl006C006C006C006C006Cl	()I
    //   109: if_icmpeq +14 -> 123
    //   112: bipush 99
    //   114: putstatic 87	com/db/pwcc/dbmobile/foundation/data/manager/broadcasting/ModelUpdatedBroadcastReceiver:b006Cl006C006C006C006Cl	I
    //   117: invokestatic 95	com/db/pwcc/dbmobile/foundation/data/manager/broadcasting/ModelUpdatedBroadcastReceiver:b006Clllll006C	()I
    //   120: putstatic 93	com/db/pwcc/dbmobile/foundation/data/manager/broadcasting/ModelUpdatedBroadcastReceiver:bl006Cllll006C	I
    //   123: iload_3
    //   124: ifeq -115 -> 9
    //   127: ldc 45
    //   129: ldc -94
    //   131: sipush 172
    //   134: bipush 95
    //   136: iconst_2
    //   137: invokestatic 134	xxxxxx/uxxxxx:bbbb0062b0062b0062b0062	(Ljava/lang/String;CCC)Ljava/lang/String;
    //   140: iconst_3
    //   141: anewarray 55	java/lang/Class
    //   144: dup
    //   145: iconst_0
    //   146: ldc 57
    //   148: aastore
    //   149: dup
    //   150: iconst_1
    //   151: getstatic 63	java/lang/Character:TYPE	Ljava/lang/Class;
    //   154: aastore
    //   155: dup
    //   156: iconst_2
    //   157: getstatic 63	java/lang/Character:TYPE	Ljava/lang/Class;
    //   160: aastore
    //   161: invokevirtual 67	java/lang/Class:getMethod	(Ljava/lang/String;[Ljava/lang/Class;)Ljava/lang/reflect/Method;
    //   164: astore_1
    //   165: aload_1
    //   166: aconst_null
    //   167: iconst_3
    //   168: anewarray 69	java/lang/Object
    //   171: dup
    //   172: iconst_0
    //   173: ldc -92
    //   175: aastore
    //   176: dup
    //   177: iconst_1
    //   178: sipush 186
    //   181: invokestatic 75	java/lang/Character:valueOf	(C)Ljava/lang/Character;
    //   184: aastore
    //   185: dup
    //   186: iconst_2
    //   187: iconst_0
    //   188: invokestatic 75	java/lang/Character:valueOf	(C)Ljava/lang/Character;
    //   191: aastore
    //   192: invokevirtual 81	java/lang/reflect/Method:invoke	(Ljava/lang/Object;[Ljava/lang/Object;)Ljava/lang/Object;
    //   195: astore_1
    //   196: aload_2
    //   197: aload_1
    //   198: checkcast 57	java/lang/String
    //   201: invokevirtual 168	android/content/Intent:getStringExtra	(Ljava/lang/String;)Ljava/lang/String;
    //   204: astore_1
    //   205: ldc 45
    //   207: ldc -86
    //   209: bipush 88
    //   211: iconst_4
    //   212: invokestatic 53	xxxxxx/uxxxxx:bb00620062bb0062b0062b0062	(Ljava/lang/String;CC)Ljava/lang/String;
    //   215: iconst_4
    //   216: anewarray 55	java/lang/Class
    //   219: dup
    //   220: iconst_0
    //   221: ldc 57
    //   223: aastore
    //   224: dup
    //   225: iconst_1
    //   226: getstatic 63	java/lang/Character:TYPE	Ljava/lang/Class;
    //   229: aastore
    //   230: dup
    //   231: iconst_2
    //   232: getstatic 63	java/lang/Character:TYPE	Ljava/lang/Class;
    //   235: aastore
    //   236: dup
    //   237: iconst_3
    //   238: getstatic 63	java/lang/Character:TYPE	Ljava/lang/Class;
    //   241: aastore
    //   242: invokevirtual 67	java/lang/Class:getMethod	(Ljava/lang/String;[Ljava/lang/Class;)Ljava/lang/reflect/Method;
    //   245: astore 4
    //   247: aload 4
    //   249: aconst_null
    //   250: iconst_4
    //   251: anewarray 69	java/lang/Object
    //   254: dup
    //   255: iconst_0
    //   256: ldc -84
    //   258: aastore
    //   259: dup
    //   260: iconst_1
    //   261: iconst_5
    //   262: invokestatic 75	java/lang/Character:valueOf	(C)Ljava/lang/Character;
    //   265: aastore
    //   266: dup
    //   267: iconst_2
    //   268: bipush 13
    //   270: invokestatic 75	java/lang/Character:valueOf	(C)Ljava/lang/Character;
    //   273: aastore
    //   274: dup
    //   275: iconst_3
    //   276: iconst_1
    //   277: invokestatic 75	java/lang/Character:valueOf	(C)Ljava/lang/Character;
    //   280: aastore
    //   281: invokevirtual 81	java/lang/reflect/Method:invoke	(Ljava/lang/Object;[Ljava/lang/Object;)Ljava/lang/Object;
    //   284: astore 4
    //   286: aload_2
    //   287: aload 4
    //   289: checkcast 57	java/lang/String
    //   292: invokevirtual 176	android/content/Intent:getBundleExtra	(Ljava/lang/String;)Landroid/os/Bundle;
    //   295: astore 4
    //   297: ldc 45
    //   299: ldc -78
    //   301: bipush 66
    //   303: iconst_2
    //   304: invokestatic 53	xxxxxx/uxxxxx:bb00620062bb0062b0062b0062	(Ljava/lang/String;CC)Ljava/lang/String;
    //   307: iconst_3
    //   308: anewarray 55	java/lang/Class
    //   311: dup
    //   312: iconst_0
    //   313: ldc 57
    //   315: aastore
    //   316: dup
    //   317: iconst_1
    //   318: getstatic 63	java/lang/Character:TYPE	Ljava/lang/Class;
    //   321: aastore
    //   322: dup
    //   323: iconst_2
    //   324: getstatic 63	java/lang/Character:TYPE	Ljava/lang/Class;
    //   327: aastore
    //   328: invokevirtual 67	java/lang/Class:getMethod	(Ljava/lang/String;[Ljava/lang/Class;)Ljava/lang/reflect/Method;
    //   331: astore 5
    //   333: aload 5
    //   335: aconst_null
    //   336: iconst_3
    //   337: anewarray 69	java/lang/Object
    //   340: dup
    //   341: iconst_0
    //   342: ldc -76
    //   344: aastore
    //   345: dup
    //   346: iconst_1
    //   347: sipush 232
    //   350: invokestatic 75	java/lang/Character:valueOf	(C)Ljava/lang/Character;
    //   353: aastore
    //   354: dup
    //   355: iconst_2
    //   356: iconst_1
    //   357: invokestatic 75	java/lang/Character:valueOf	(C)Ljava/lang/Character;
    //   360: aastore
    //   361: invokevirtual 81	java/lang/reflect/Method:invoke	(Ljava/lang/Object;[Ljava/lang/Object;)Ljava/lang/Object;
    //   364: astore 5
    //   366: aload_2
    //   367: aload 5
    //   369: checkcast 57	java/lang/String
    //   372: invokevirtual 184	android/content/Intent:getParcelableExtra	(Ljava/lang/String;)Landroid/os/Parcelable;
    //   375: astore_2
    //   376: getstatic 87	com/db/pwcc/dbmobile/foundation/data/manager/broadcasting/ModelUpdatedBroadcastReceiver:b006Cl006C006C006C006Cl	I
    //   379: invokestatic 186	com/db/pwcc/dbmobile/foundation/data/manager/broadcasting/ModelUpdatedBroadcastReceiver:b006C006Cllll006C	()I
    //   382: iadd
    //   383: getstatic 87	com/db/pwcc/dbmobile/foundation/data/manager/broadcasting/ModelUpdatedBroadcastReceiver:b006Cl006C006C006C006Cl	I
    //   386: imul
    //   387: getstatic 91	com/db/pwcc/dbmobile/foundation/data/manager/broadcasting/ModelUpdatedBroadcastReceiver:bllllll006C	I
    //   390: irem
    //   391: getstatic 93	com/db/pwcc/dbmobile/foundation/data/manager/broadcasting/ModelUpdatedBroadcastReceiver:bl006Cllll006C	I
    //   394: if_icmpeq +14 -> 408
    //   397: invokestatic 95	com/db/pwcc/dbmobile/foundation/data/manager/broadcasting/ModelUpdatedBroadcastReceiver:b006Clllll006C	()I
    //   400: putstatic 87	com/db/pwcc/dbmobile/foundation/data/manager/broadcasting/ModelUpdatedBroadcastReceiver:b006Cl006C006C006C006Cl	I
    //   403: bipush 53
    //   405: putstatic 93	com/db/pwcc/dbmobile/foundation/data/manager/broadcasting/ModelUpdatedBroadcastReceiver:bl006Cllll006C	I
    //   408: aload_2
    //   409: checkcast 188	com/db/pwcc/dbmobile/model/error/DbError
    //   412: astore_2
    //   413: aload_1
    //   414: ifnull -405 -> 9
    //   417: aload_2
    //   418: ifnonnull +35 -> 453
    //   421: aload_0
    //   422: aload_1
    //   423: aload 4
    //   425: invokevirtual 190	com/db/pwcc/dbmobile/foundation/data/manager/broadcasting/ModelUpdatedBroadcastReceiver:onDataModelUpdated	(Ljava/lang/String;Landroid/os/Bundle;)V
    //   428: return
    //   429: astore_1
    //   430: aload_1
    //   431: invokevirtual 123	java/lang/reflect/InvocationTargetException:getCause	()Ljava/lang/Throwable;
    //   434: athrow
    //   435: astore_1
    //   436: aload_1
    //   437: invokevirtual 123	java/lang/reflect/InvocationTargetException:getCause	()Ljava/lang/Throwable;
    //   440: athrow
    //   441: astore_1
    //   442: aload_1
    //   443: invokevirtual 123	java/lang/reflect/InvocationTargetException:getCause	()Ljava/lang/Throwable;
    //   446: athrow
    //   447: astore_1
    //   448: aload_1
    //   449: invokevirtual 123	java/lang/reflect/InvocationTargetException:getCause	()Ljava/lang/Throwable;
    //   452: athrow
    //   453: aload_0
    //   454: aload_1
    //   455: aload_2
    //   456: aload 4
    //   458: invokevirtual 192	com/db/pwcc/dbmobile/foundation/data/manager/broadcasting/ModelUpdatedBroadcastReceiver:onDataModelUpdateFailed	(Ljava/lang/String;Lcom/db/pwcc/dbmobile/model/error/DbError;Landroid/os/Bundle;)V
    //   461: return
    // Local variable table:
    //   start	length	slot	name	signature
    //   0	462	0	this	ModelUpdatedBroadcastReceiver
    //   0	462	1	paramContext	android.content.Context
    //   0	462	2	paramIntent	android.content.Intent
    //   90	34	3	bool	boolean
    //   46	411	4	localObject1	Object
    //   331	37	5	localObject2	Object
    // Exception table:
    //   from	to	target	type
    //   48	81	429	java/lang/reflect/InvocationTargetException
    //   165	196	435	java/lang/reflect/InvocationTargetException
    //   333	366	441	java/lang/reflect/InvocationTargetException
    //   247	286	447	java/lang/reflect/InvocationTargetException
  }
}
