package com.liveperson.infra.ui.view.adapter.viewholder;

import android.view.View;
import android.widget.TextView;
import com.liveperson.infra.ui.R.id;

public class HeaderViewHolder
  extends BaseViewHolder
{
  private static final String TAG;
  public static int b04130413ГГГГГ = 0;
  public static int b041AК041A041A041A041A041A = 2;
  public static int bК041A041A041A041A041A041A = 94;
  public static int bКК041A041A041A041A041A = 1;
  private TextView mHeaderTextView;
  
  /* Error */
  static
  {
    // Byte code:
    //   0: ldc 2
    //   2: invokevirtual 27	java/lang/Class:getSimpleName	()Ljava/lang/String;
    //   5: astore_1
    //   6: aload_1
    //   7: putstatic 29	com/liveperson/infra/ui/view/adapter/viewholder/HeaderViewHolder:TAG	Ljava/lang/String;
    //   10: invokestatic 33	com/liveperson/infra/ui/view/adapter/viewholder/HeaderViewHolder:b041A041AК041A041A041A041A	()I
    //   13: istore_0
    //   14: iload_0
    //   15: getstatic 35	com/liveperson/infra/ui/view/adapter/viewholder/HeaderViewHolder:bКК041A041A041A041A041A	I
    //   18: iload_0
    //   19: iadd
    //   20: imul
    //   21: getstatic 37	com/liveperson/infra/ui/view/adapter/viewholder/HeaderViewHolder:b041AК041A041A041A041A041A	I
    //   24: irem
    //   25: tableswitch	default:+19->44, 0:+70->95
    //   44: bipush 91
    //   46: putstatic 35	com/liveperson/infra/ui/view/adapter/viewholder/HeaderViewHolder:bКК041A041A041A041A041A	I
    //   49: getstatic 39	com/liveperson/infra/ui/view/adapter/viewholder/HeaderViewHolder:bК041A041A041A041A041A041A	I
    //   52: istore_0
    //   53: iload_0
    //   54: getstatic 35	com/liveperson/infra/ui/view/adapter/viewholder/HeaderViewHolder:bКК041A041A041A041A041A	I
    //   57: iload_0
    //   58: iadd
    //   59: imul
    //   60: getstatic 37	com/liveperson/infra/ui/view/adapter/viewholder/HeaderViewHolder:b041AК041A041A041A041A041A	I
    //   63: irem
    //   64: tableswitch	default:+20->84, 0:+31->95
    //   84: invokestatic 33	com/liveperson/infra/ui/view/adapter/viewholder/HeaderViewHolder:b041A041AК041A041A041A041A	()I
    //   87: putstatic 39	com/liveperson/infra/ui/view/adapter/viewholder/HeaderViewHolder:bК041A041A041A041A041A041A	I
    //   90: bipush 64
    //   92: putstatic 35	com/liveperson/infra/ui/view/adapter/viewholder/HeaderViewHolder:bКК041A041A041A041A041A	I
    //   95: return
    //   96: astore_1
    //   97: aload_1
    //   98: athrow
    //   99: astore_1
    //   100: aload_1
    //   101: athrow
    // Local variable table:
    //   start	length	slot	name	signature
    //   13	47	0	i	int
    //   5	2	1	str	String
    //   96	2	1	localException1	Exception
    //   99	2	1	localException2	Exception
    // Exception table:
    //   from	to	target	type
    //   0	6	96	java/lang/Exception
    //   6	10	99	java/lang/Exception
  }
  
  public HeaderViewHolder(View paramView)
  {
    super(paramView);
    this.mHeaderTextView = ((TextView)paramView.findViewById(R.id.lpui_message_text));
  }
  
  public static int b041A041AК041A041A041A041A()
  {
    return 53;
  }
  
  public static int bГГ0413ГГГГ()
  {
    return 1;
  }
  
  public String getTextToCopy()
  {
    switch (1)
    {
    case 0: 
    default: 
      for (;;)
      {
        switch (1)
        {
        case 0: 
        default: 
          for (;;)
          {
            switch (1)
            {
            }
          }
        }
        if ((bК041A041A041A041A041A041A + bГГ0413ГГГГ()) * bК041A041A041A041A041A041A % b041AК041A041A041A041A041A != b04130413ГГГГГ)
        {
          bК041A041A041A041A041A041A = 5;
          b04130413ГГГГГ = 35;
        }
        switch (1)
        {
        }
      }
    }
    try
    {
      throw new NullPointerException();
    }
    catch (Exception localException)
    {
      bК041A041A041A041A041A041A = 55;
    }
    return null;
  }
  
  public void setHeaderText(String paramString)
  {
    this.mHeaderTextView.setText(paramString);
    switch (1)
    {
    case 0: 
    default: 
      for (;;)
      {
        switch (1)
        {
        }
      }
    }
    if ((bК041A041A041A041A041A041A + bГГ0413ГГГГ()) * bК041A041A041A041A041A041A % b041AК041A041A041A041A041A != b04130413ГГГГГ)
    {
      bК041A041A041A041A041A041A = b041A041AК041A041A041A041A();
      b04130413ГГГГГ = b041A041AК041A041A041A041A();
    }
  }
  
  public void updateContentDescription()
  {
    if ((bК041A041A041A041A041A041A + bКК041A041A041A041A041A) * bК041A041A041A041A041A041A % b041AК041A041A041A041A041A != b04130413ГГГГГ)
    {
      bК041A041A041A041A041A041A = 5;
      b04130413ГГГГГ = b041A041AК041A041A041A041A();
    }
    switch (0)
    {
    case 1: 
    default: 
      for (;;)
      {
        switch (0)
        {
        }
      }
    }
  }
}
