package uuuuuu;

import com.db.pwcc.dbmobile.model.error.DbError;
import com.db.pwcc.dbmobile.multi_bank_aggregator.model.Bank;
import com.db.pwcc.dbmobile.multi_bank_aggregator.model.CreateMbaSynchronizationResponse;
import java.util.List;
import java.util.Set;
import javax.inject.Inject;

public class mmmqqm
  extends ssssst<qqmqqm.qmmqqm>
  implements qqmqqm.mqmqqm, alllal.lallal
{
  public static int b00760076vvv0076v0076v = 1;
  public static int b0076vvvv0076v0076v = 65;
  public static int bv0076vvv0076v0076v = 0;
  public static int bvv0076vv0076v0076v = 2;
  public CreateMbaSynchronizationResponse b00760076007600760076vv0076v;
  public DbError b00760076v00760076vv0076v;
  private ossooo b0076v007600760076vv0076v;
  public Bank b0076vv00760076vv0076v;
  public boolean bv0076007600760076vv0076v;
  public String bv0076v00760076vv0076v;
  @Inject
  public qqpqqq bvv007600760076vv0076v;
  public Set<String> bvvv00760076vv0076v;
  public List<String> bvvvvv0076v0076v;
  
  public mmmqqm()
  {
    xvvvxx.b0075uu00750075007500750075u0075().bp0070p00700070ppppp(this);
  }
  
  public static int b0075007500750075uu0075uu0075()
  {
    return 0;
  }
  
  public static int b0075u00750075uu0075uu0075()
  {
    return 10;
  }
  
  /* Error */
  private void b0075u0075u0075u0075uu0075()
  {
    // Byte code:
    //   0: aload_0
    //   1: getfield 63	uuuuuu/mmmqqm:bvvvvv0076v0076v	Ljava/util/List;
    //   4: ifnull +424 -> 428
    //   7: aload_0
    //   8: getfield 65	uuuuuu/mmmqqm:bvvv00760076vv0076v	Ljava/util/Set;
    //   11: ifnull +417 -> 428
    //   14: aload_0
    //   15: getfield 65	uuuuuu/mmmqqm:bvvv00760076vv0076v	Ljava/util/Set;
    //   18: aload_0
    //   19: getfield 63	uuuuuu/mmmqqm:bvvvvv0076v0076v	Ljava/util/List;
    //   22: invokeinterface 71 2 0
    //   27: pop
    //   28: aload_0
    //   29: getfield 65	uuuuuu/mmmqqm:bvvv00760076vv0076v	Ljava/util/Set;
    //   32: astore_2
    //   33: getstatic 73	uuuuuu/mmmqqm:b0076vvvv0076v0076v	I
    //   36: istore_3
    //   37: iload_3
    //   38: iload_3
    //   39: getstatic 75	uuuuuu/mmmqqm:b00760076vvv0076v0076v	I
    //   42: iadd
    //   43: imul
    //   44: getstatic 77	uuuuuu/mmmqqm:bvv0076vv0076v0076v	I
    //   47: irem
    //   48: tableswitch	default:+20->68, 0:+30->78
    //   68: bipush 31
    //   70: putstatic 73	uuuuuu/mmmqqm:b0076vvvv0076v0076v	I
    //   73: bipush 96
    //   75: putstatic 79	uuuuuu/mmmqqm:bv0076vvv0076v0076v	I
    //   78: aload_2
    //   79: invokeinterface 83 1 0
    //   84: astore 4
    //   86: getstatic 73	uuuuuu/mmmqqm:b0076vvvv0076v0076v	I
    //   89: istore 5
    //   91: iload 5
    //   93: iload 5
    //   95: getstatic 75	uuuuuu/mmmqqm:b00760076vvv0076v0076v	I
    //   98: iadd
    //   99: imul
    //   100: getstatic 77	uuuuuu/mmmqqm:bvv0076vv0076v0076v	I
    //   103: irem
    //   104: tableswitch	default:+20->124, 0:+72->176
    //   124: bipush 99
    //   126: putstatic 73	uuuuuu/mmmqqm:b0076vvvv0076v0076v	I
    //   129: ldc 2
    //   131: ldc 85
    //   133: sipush 142
    //   136: iconst_2
    //   137: invokestatic 91	xxxxxx/uxxxxx:bb00620062bb0062b0062b0062	(Ljava/lang/String;CC)Ljava/lang/String;
    //   140: iconst_0
    //   141: anewarray 93	java/lang/Class
    //   144: invokevirtual 97	java/lang/Class:getMethod	(Ljava/lang/String;[Ljava/lang/Class;)Ljava/lang/reflect/Method;
    //   147: astore 19
    //   149: iconst_0
    //   150: anewarray 99	java/lang/Object
    //   153: astore 20
    //   155: aload 19
    //   157: aconst_null
    //   158: aload 20
    //   160: invokevirtual 105	java/lang/reflect/Method:invoke	(Ljava/lang/Object;[Ljava/lang/Object;)Ljava/lang/Object;
    //   163: astore 22
    //   165: aload 22
    //   167: checkcast 107	java/lang/Integer
    //   170: invokevirtual 110	java/lang/Integer:intValue	()I
    //   173: putstatic 79	uuuuuu/mmmqqm:bv0076vvv0076v0076v	I
    //   176: getstatic 73	uuuuuu/mmmqqm:b0076vvvv0076v0076v	I
    //   179: getstatic 75	uuuuuu/mmmqqm:b00760076vvv0076v0076v	I
    //   182: iadd
    //   183: getstatic 73	uuuuuu/mmmqqm:b0076vvvv0076v0076v	I
    //   186: imul
    //   187: getstatic 77	uuuuuu/mmmqqm:bvv0076vv0076v0076v	I
    //   190: irem
    //   191: getstatic 79	uuuuuu/mmmqqm:bv0076vvv0076v0076v	I
    //   194: if_icmpeq +172 -> 366
    //   197: getstatic 73	uuuuuu/mmmqqm:b0076vvvv0076v0076v	I
    //   200: getstatic 75	uuuuuu/mmmqqm:b00760076vvv0076v0076v	I
    //   203: iadd
    //   204: getstatic 73	uuuuuu/mmmqqm:b0076vvvv0076v0076v	I
    //   207: imul
    //   208: getstatic 77	uuuuuu/mmmqqm:bvv0076vv0076v0076v	I
    //   211: irem
    //   212: getstatic 79	uuuuuu/mmmqqm:bv0076vvv0076v0076v	I
    //   215: if_icmpeq +99 -> 314
    //   218: ldc 2
    //   220: ldc 112
    //   222: sipush 184
    //   225: iconst_1
    //   226: invokestatic 91	xxxxxx/uxxxxx:bb00620062bb0062b0062b0062	(Ljava/lang/String;CC)Ljava/lang/String;
    //   229: iconst_0
    //   230: anewarray 93	java/lang/Class
    //   233: invokevirtual 97	java/lang/Class:getMethod	(Ljava/lang/String;[Ljava/lang/Class;)Ljava/lang/reflect/Method;
    //   236: astore 11
    //   238: iconst_0
    //   239: anewarray 99	java/lang/Object
    //   242: astore 12
    //   244: aload 11
    //   246: aconst_null
    //   247: aload 12
    //   249: invokevirtual 105	java/lang/reflect/Method:invoke	(Ljava/lang/Object;[Ljava/lang/Object;)Ljava/lang/Object;
    //   252: astore 14
    //   254: aload 14
    //   256: checkcast 107	java/lang/Integer
    //   259: invokevirtual 110	java/lang/Integer:intValue	()I
    //   262: putstatic 73	uuuuuu/mmmqqm:b0076vvvv0076v0076v	I
    //   265: ldc 2
    //   267: ldc 114
    //   269: bipush 126
    //   271: sipush 212
    //   274: iconst_3
    //   275: invokestatic 118	xxxxxx/uxxxxx:bbbb0062b0062b0062b0062	(Ljava/lang/String;CCC)Ljava/lang/String;
    //   278: iconst_0
    //   279: anewarray 93	java/lang/Class
    //   282: invokevirtual 97	java/lang/Class:getMethod	(Ljava/lang/String;[Ljava/lang/Class;)Ljava/lang/reflect/Method;
    //   285: astore 15
    //   287: iconst_0
    //   288: anewarray 99	java/lang/Object
    //   291: astore 16
    //   293: aload 15
    //   295: aconst_null
    //   296: aload 16
    //   298: invokevirtual 105	java/lang/reflect/Method:invoke	(Ljava/lang/Object;[Ljava/lang/Object;)Ljava/lang/Object;
    //   301: astore 18
    //   303: aload 18
    //   305: checkcast 107	java/lang/Integer
    //   308: invokevirtual 110	java/lang/Integer:intValue	()I
    //   311: putstatic 79	uuuuuu/mmmqqm:bv0076vvv0076v0076v	I
    //   314: bipush 16
    //   316: putstatic 73	uuuuuu/mmmqqm:b0076vvvv0076v0076v	I
    //   319: ldc 2
    //   321: ldc 120
    //   323: sipush 194
    //   326: iconst_5
    //   327: invokestatic 91	xxxxxx/uxxxxx:bb00620062bb0062b0062b0062	(Ljava/lang/String;CC)Ljava/lang/String;
    //   330: iconst_0
    //   331: anewarray 93	java/lang/Class
    //   334: invokevirtual 97	java/lang/Class:getMethod	(Ljava/lang/String;[Ljava/lang/Class;)Ljava/lang/reflect/Method;
    //   337: astore 7
    //   339: iconst_0
    //   340: anewarray 99	java/lang/Object
    //   343: astore 8
    //   345: aload 7
    //   347: aconst_null
    //   348: aload 8
    //   350: invokevirtual 105	java/lang/reflect/Method:invoke	(Ljava/lang/Object;[Ljava/lang/Object;)Ljava/lang/Object;
    //   353: astore 10
    //   355: aload 10
    //   357: checkcast 107	java/lang/Integer
    //   360: invokevirtual 110	java/lang/Integer:intValue	()I
    //   363: putstatic 79	uuuuuu/mmmqqm:bv0076vvv0076v0076v	I
    //   366: aload 4
    //   368: invokeinterface 126 1 0
    //   373: ifeq +55 -> 428
    //   376: aload 4
    //   378: invokeinterface 130 1 0
    //   383: checkcast 132	java/lang/String
    //   386: pop
    //   387: getstatic 138	uuuuuu/vvrvrv:bh00680068h0068hh00680068	Luuuuuu/vvrvrv;
    //   390: invokestatic 144	uuuuuu/rrvvrv:b0071q0071qq0071q0071q0071	(Luuuuuu/vvrvrv;)V
    //   393: goto -217 -> 176
    //   396: astore 9
    //   398: aload 9
    //   400: invokevirtual 148	java/lang/reflect/InvocationTargetException:getCause	()Ljava/lang/Throwable;
    //   403: athrow
    //   404: astore 13
    //   406: aload 13
    //   408: invokevirtual 148	java/lang/reflect/InvocationTargetException:getCause	()Ljava/lang/Throwable;
    //   411: athrow
    //   412: astore 17
    //   414: aload 17
    //   416: invokevirtual 148	java/lang/reflect/InvocationTargetException:getCause	()Ljava/lang/Throwable;
    //   419: athrow
    //   420: astore 21
    //   422: aload 21
    //   424: invokevirtual 148	java/lang/reflect/InvocationTargetException:getCause	()Ljava/lang/Throwable;
    //   427: athrow
    //   428: return
    // Local variable table:
    //   start	length	slot	name	signature
    //   0	429	0	this	mmmqqm
    //   32	47	2	localSet	Set
    //   36	8	3	i	int
    //   84	293	4	localIterator	java.util.Iterator
    //   89	11	5	j	int
    //   337	9	7	localMethod1	java.lang.reflect.Method
    //   343	6	8	arrayOfObject1	Object[]
    //   396	3	9	localInvocationTargetException1	java.lang.reflect.InvocationTargetException
    //   353	3	10	localObject1	Object
    //   236	9	11	localMethod2	java.lang.reflect.Method
    //   242	6	12	arrayOfObject2	Object[]
    //   404	3	13	localInvocationTargetException2	java.lang.reflect.InvocationTargetException
    //   252	3	14	localObject2	Object
    //   285	9	15	localMethod3	java.lang.reflect.Method
    //   291	6	16	arrayOfObject3	Object[]
    //   412	3	17	localInvocationTargetException3	java.lang.reflect.InvocationTargetException
    //   301	3	18	localObject3	Object
    //   147	9	19	localMethod4	java.lang.reflect.Method
    //   153	6	20	arrayOfObject4	Object[]
    //   420	3	21	localInvocationTargetException4	java.lang.reflect.InvocationTargetException
    //   163	3	22	localObject4	Object
    // Exception table:
    //   from	to	target	type
    //   345	355	396	java/lang/reflect/InvocationTargetException
    //   244	254	404	java/lang/reflect/InvocationTargetException
    //   293	303	412	java/lang/reflect/InvocationTargetException
    //   155	165	420	java/lang/reflect/InvocationTargetException
  }
  
  public static int buu00750075uu0075uu0075()
  {
    return 1;
  }
  
  /* Error */
  private void buu0075u0075u0075uu0075()
  {
    // Byte code:
    //   0: aload_0
    //   1: getfield 63	uuuuuu/mmmqqm:bvvvvv0076v0076v	Ljava/util/List;
    //   4: ifnull +333 -> 337
    //   7: aload_0
    //   8: getfield 63	uuuuuu/mmmqqm:bvvvvv0076v0076v	Ljava/util/List;
    //   11: invokeinterface 153 1 0
    //   16: astore_1
    //   17: getstatic 73	uuuuuu/mmmqqm:b0076vvvv0076v0076v	I
    //   20: getstatic 75	uuuuuu/mmmqqm:b00760076vvv0076v0076v	I
    //   23: iadd
    //   24: getstatic 73	uuuuuu/mmmqqm:b0076vvvv0076v0076v	I
    //   27: imul
    //   28: getstatic 77	uuuuuu/mmmqqm:bvv0076vv0076v0076v	I
    //   31: irem
    //   32: istore_2
    //   33: getstatic 73	uuuuuu/mmmqqm:b0076vvvv0076v0076v	I
    //   36: getstatic 75	uuuuuu/mmmqqm:b00760076vvv0076v0076v	I
    //   39: iadd
    //   40: getstatic 73	uuuuuu/mmmqqm:b0076vvvv0076v0076v	I
    //   43: imul
    //   44: getstatic 77	uuuuuu/mmmqqm:bvv0076vv0076v0076v	I
    //   47: irem
    //   48: istore_3
    //   49: ldc 2
    //   51: ldc -101
    //   53: bipush 37
    //   55: iconst_5
    //   56: invokestatic 91	xxxxxx/uxxxxx:bb00620062bb0062b0062b0062	(Ljava/lang/String;CC)Ljava/lang/String;
    //   59: iconst_0
    //   60: anewarray 93	java/lang/Class
    //   63: invokevirtual 97	java/lang/Class:getMethod	(Ljava/lang/String;[Ljava/lang/Class;)Ljava/lang/reflect/Method;
    //   66: astore 4
    //   68: iconst_0
    //   69: anewarray 99	java/lang/Object
    //   72: astore 5
    //   74: aload 4
    //   76: aconst_null
    //   77: aload 5
    //   79: invokevirtual 105	java/lang/reflect/Method:invoke	(Ljava/lang/Object;[Ljava/lang/Object;)Ljava/lang/Object;
    //   82: astore 7
    //   84: iload_3
    //   85: aload 7
    //   87: checkcast 107	java/lang/Integer
    //   90: invokevirtual 110	java/lang/Integer:intValue	()I
    //   93: if_icmpeq +13 -> 106
    //   96: bipush 98
    //   98: putstatic 73	uuuuuu/mmmqqm:b0076vvvv0076v0076v	I
    //   101: bipush 13
    //   103: putstatic 79	uuuuuu/mmmqqm:bv0076vvv0076v0076v	I
    //   106: getstatic 73	uuuuuu/mmmqqm:b0076vvvv0076v0076v	I
    //   109: getstatic 75	uuuuuu/mmmqqm:b00760076vvv0076v0076v	I
    //   112: iadd
    //   113: getstatic 73	uuuuuu/mmmqqm:b0076vvvv0076v0076v	I
    //   116: imul
    //   117: istore 8
    //   119: ldc 2
    //   121: ldc -99
    //   123: bipush 45
    //   125: iconst_4
    //   126: invokestatic 91	xxxxxx/uxxxxx:bb00620062bb0062b0062b0062	(Ljava/lang/String;CC)Ljava/lang/String;
    //   129: iconst_0
    //   130: anewarray 93	java/lang/Class
    //   133: invokevirtual 97	java/lang/Class:getMethod	(Ljava/lang/String;[Ljava/lang/Class;)Ljava/lang/reflect/Method;
    //   136: astore 9
    //   138: iconst_0
    //   139: anewarray 99	java/lang/Object
    //   142: astore 10
    //   144: aload 9
    //   146: aconst_null
    //   147: aload 10
    //   149: invokevirtual 105	java/lang/reflect/Method:invoke	(Ljava/lang/Object;[Ljava/lang/Object;)Ljava/lang/Object;
    //   152: astore 12
    //   154: iload 8
    //   156: aload 12
    //   158: checkcast 107	java/lang/Integer
    //   161: invokevirtual 110	java/lang/Integer:intValue	()I
    //   164: irem
    //   165: getstatic 79	uuuuuu/mmmqqm:bv0076vvv0076v0076v	I
    //   168: if_icmpeq +55 -> 223
    //   171: ldc 2
    //   173: ldc -97
    //   175: sipush 197
    //   178: iconst_3
    //   179: invokestatic 91	xxxxxx/uxxxxx:bb00620062bb0062b0062b0062	(Ljava/lang/String;CC)Ljava/lang/String;
    //   182: iconst_0
    //   183: anewarray 93	java/lang/Class
    //   186: invokevirtual 97	java/lang/Class:getMethod	(Ljava/lang/String;[Ljava/lang/Class;)Ljava/lang/reflect/Method;
    //   189: astore 15
    //   191: iconst_0
    //   192: anewarray 99	java/lang/Object
    //   195: astore 16
    //   197: aload 15
    //   199: aconst_null
    //   200: aload 16
    //   202: invokevirtual 105	java/lang/reflect/Method:invoke	(Ljava/lang/Object;[Ljava/lang/Object;)Ljava/lang/Object;
    //   205: astore 18
    //   207: aload 18
    //   209: checkcast 107	java/lang/Integer
    //   212: invokevirtual 110	java/lang/Integer:intValue	()I
    //   215: putstatic 73	uuuuuu/mmmqqm:b0076vvvv0076v0076v	I
    //   218: bipush 27
    //   220: putstatic 79	uuuuuu/mmmqqm:bv0076vvv0076v0076v	I
    //   223: iload_2
    //   224: getstatic 79	uuuuuu/mmmqqm:bv0076vvv0076v0076v	I
    //   227: if_icmpeq +13 -> 240
    //   230: bipush 43
    //   232: putstatic 73	uuuuuu/mmmqqm:b0076vvvv0076v0076v	I
    //   235: bipush 12
    //   237: putstatic 79	uuuuuu/mmmqqm:bv0076vvv0076v0076v	I
    //   240: aload_1
    //   241: invokeinterface 126 1 0
    //   246: ifeq +91 -> 337
    //   249: aload_1
    //   250: invokeinterface 130 1 0
    //   255: checkcast 132	java/lang/String
    //   258: pop
    //   259: getstatic 162	uuuuuu/vvrvrv:b0068h0068h0068hh00680068	Luuuuuu/vvrvrv;
    //   262: invokestatic 144	uuuuuu/rrvvrv:b0071q0071qq0071q0071q0071	(Luuuuuu/vvrvrv;)V
    //   265: getstatic 73	uuuuuu/mmmqqm:b0076vvvv0076v0076v	I
    //   268: istore 14
    //   270: iload 14
    //   272: iload 14
    //   274: getstatic 75	uuuuuu/mmmqqm:b00760076vvv0076v0076v	I
    //   277: iadd
    //   278: imul
    //   279: getstatic 77	uuuuuu/mmmqqm:bvv0076vv0076v0076v	I
    //   282: irem
    //   283: tableswitch	default:+17->300, 0:+-266->17
    //   300: bipush 62
    //   302: putstatic 73	uuuuuu/mmmqqm:b0076vvvv0076v0076v	I
    //   305: bipush 87
    //   307: putstatic 79	uuuuuu/mmmqqm:bv0076vvv0076v0076v	I
    //   310: goto -293 -> 17
    //   313: astore 6
    //   315: aload 6
    //   317: invokevirtual 148	java/lang/reflect/InvocationTargetException:getCause	()Ljava/lang/Throwable;
    //   320: athrow
    //   321: astore 11
    //   323: aload 11
    //   325: invokevirtual 148	java/lang/reflect/InvocationTargetException:getCause	()Ljava/lang/Throwable;
    //   328: athrow
    //   329: astore 17
    //   331: aload 17
    //   333: invokevirtual 148	java/lang/reflect/InvocationTargetException:getCause	()Ljava/lang/Throwable;
    //   336: athrow
    //   337: return
    // Local variable table:
    //   start	length	slot	name	signature
    //   0	338	0	this	mmmqqm
    //   16	234	1	localIterator	java.util.Iterator
    //   32	196	2	i	int
    //   48	46	3	j	int
    //   66	9	4	localMethod1	java.lang.reflect.Method
    //   72	6	5	arrayOfObject1	Object[]
    //   313	3	6	localInvocationTargetException1	java.lang.reflect.InvocationTargetException
    //   82	4	7	localObject1	Object
    //   117	48	8	k	int
    //   136	9	9	localMethod2	java.lang.reflect.Method
    //   142	6	10	arrayOfObject2	Object[]
    //   321	3	11	localInvocationTargetException2	java.lang.reflect.InvocationTargetException
    //   152	5	12	localObject2	Object
    //   268	11	14	m	int
    //   189	9	15	localMethod3	java.lang.reflect.Method
    //   195	6	16	arrayOfObject3	Object[]
    //   329	3	17	localInvocationTargetException3	java.lang.reflect.InvocationTargetException
    //   205	3	18	localObject3	Object
    // Exception table:
    //   from	to	target	type
    //   74	84	313	java/lang/reflect/InvocationTargetException
    //   144	154	321	java/lang/reflect/InvocationTargetException
    //   197	207	329	java/lang/reflect/InvocationTargetException
  }
  
  public static int buuuu0075u0075uu0075()
  {
    return 2;
  }
  
  /* Error */
  public void b00750075u0075uu0075uu0075(String paramString, boolean paramBoolean)
  {
    // Byte code:
    //   0: iload_2
    //   1: ifeq +582 -> 583
    //   4: aload_0
    //   5: getfield 63	uuuuuu/mmmqqm:bvvvvv0076v0076v	Ljava/util/List;
    //   8: aload_1
    //   9: invokeinterface 171 2 0
    //   14: pop
    //   15: getstatic 73	uuuuuu/mmmqqm:b0076vvvv0076v0076v	I
    //   18: getstatic 75	uuuuuu/mmmqqm:b00760076vvv0076v0076v	I
    //   21: iadd
    //   22: getstatic 73	uuuuuu/mmmqqm:b0076vvvv0076v0076v	I
    //   25: imul
    //   26: getstatic 77	uuuuuu/mmmqqm:bvv0076vv0076v0076v	I
    //   29: irem
    //   30: getstatic 79	uuuuuu/mmmqqm:bv0076vvv0076v0076v	I
    //   33: if_icmpeq +299 -> 332
    //   36: ldc 2
    //   38: ldc -83
    //   40: sipush 139
    //   43: iconst_1
    //   44: invokestatic 91	xxxxxx/uxxxxx:bb00620062bb0062b0062b0062	(Ljava/lang/String;CC)Ljava/lang/String;
    //   47: iconst_0
    //   48: anewarray 93	java/lang/Class
    //   51: invokevirtual 97	java/lang/Class:getMethod	(Ljava/lang/String;[Ljava/lang/Class;)Ljava/lang/reflect/Method;
    //   54: astore 19
    //   56: iconst_0
    //   57: anewarray 99	java/lang/Object
    //   60: astore 20
    //   62: aload 19
    //   64: aconst_null
    //   65: aload 20
    //   67: invokevirtual 105	java/lang/reflect/Method:invoke	(Ljava/lang/Object;[Ljava/lang/Object;)Ljava/lang/Object;
    //   70: astore 22
    //   72: aload 22
    //   74: checkcast 107	java/lang/Integer
    //   77: invokevirtual 110	java/lang/Integer:intValue	()I
    //   80: getstatic 75	uuuuuu/mmmqqm:b00760076vvv0076v0076v	I
    //   83: iadd
    //   84: istore 23
    //   86: ldc 2
    //   88: ldc -81
    //   90: sipush 205
    //   93: iconst_0
    //   94: invokestatic 91	xxxxxx/uxxxxx:bb00620062bb0062b0062b0062	(Ljava/lang/String;CC)Ljava/lang/String;
    //   97: iconst_0
    //   98: anewarray 93	java/lang/Class
    //   101: invokevirtual 97	java/lang/Class:getMethod	(Ljava/lang/String;[Ljava/lang/Class;)Ljava/lang/reflect/Method;
    //   104: astore 24
    //   106: iconst_0
    //   107: anewarray 99	java/lang/Object
    //   110: astore 25
    //   112: aload 24
    //   114: aconst_null
    //   115: aload 25
    //   117: invokevirtual 105	java/lang/reflect/Method:invoke	(Ljava/lang/Object;[Ljava/lang/Object;)Ljava/lang/Object;
    //   120: astore 27
    //   122: iload 23
    //   124: aload 27
    //   126: checkcast 107	java/lang/Integer
    //   129: invokevirtual 110	java/lang/Integer:intValue	()I
    //   132: imul
    //   133: getstatic 77	uuuuuu/mmmqqm:bvv0076vv0076v0076v	I
    //   136: irem
    //   137: getstatic 79	uuuuuu/mmmqqm:bv0076vvv0076v0076v	I
    //   140: if_icmpeq +100 -> 240
    //   143: ldc 2
    //   145: ldc -79
    //   147: bipush 86
    //   149: bipush 43
    //   151: iconst_3
    //   152: invokestatic 118	xxxxxx/uxxxxx:bbbb0062b0062b0062b0062	(Ljava/lang/String;CCC)Ljava/lang/String;
    //   155: iconst_0
    //   156: anewarray 93	java/lang/Class
    //   159: invokevirtual 97	java/lang/Class:getMethod	(Ljava/lang/String;[Ljava/lang/Class;)Ljava/lang/reflect/Method;
    //   162: astore 36
    //   164: iconst_0
    //   165: anewarray 99	java/lang/Object
    //   168: astore 37
    //   170: aload 36
    //   172: aconst_null
    //   173: aload 37
    //   175: invokevirtual 105	java/lang/reflect/Method:invoke	(Ljava/lang/Object;[Ljava/lang/Object;)Ljava/lang/Object;
    //   178: astore 39
    //   180: aload 39
    //   182: checkcast 107	java/lang/Integer
    //   185: invokevirtual 110	java/lang/Integer:intValue	()I
    //   188: putstatic 73	uuuuuu/mmmqqm:b0076vvvv0076v0076v	I
    //   191: ldc 2
    //   193: ldc -77
    //   195: bipush 65
    //   197: sipush 139
    //   200: iconst_3
    //   201: invokestatic 118	xxxxxx/uxxxxx:bbbb0062b0062b0062b0062	(Ljava/lang/String;CCC)Ljava/lang/String;
    //   204: iconst_0
    //   205: anewarray 93	java/lang/Class
    //   208: invokevirtual 97	java/lang/Class:getMethod	(Ljava/lang/String;[Ljava/lang/Class;)Ljava/lang/reflect/Method;
    //   211: astore 40
    //   213: iconst_0
    //   214: anewarray 99	java/lang/Object
    //   217: astore 41
    //   219: aload 40
    //   221: aconst_null
    //   222: aload 41
    //   224: invokevirtual 105	java/lang/reflect/Method:invoke	(Ljava/lang/Object;[Ljava/lang/Object;)Ljava/lang/Object;
    //   227: astore 43
    //   229: aload 43
    //   231: checkcast 107	java/lang/Integer
    //   234: invokevirtual 110	java/lang/Integer:intValue	()I
    //   237: putstatic 79	uuuuuu/mmmqqm:bv0076vvv0076v0076v	I
    //   240: ldc 2
    //   242: ldc -75
    //   244: bipush 40
    //   246: iconst_5
    //   247: invokestatic 91	xxxxxx/uxxxxx:bb00620062bb0062b0062b0062	(Ljava/lang/String;CC)Ljava/lang/String;
    //   250: iconst_0
    //   251: anewarray 93	java/lang/Class
    //   254: invokevirtual 97	java/lang/Class:getMethod	(Ljava/lang/String;[Ljava/lang/Class;)Ljava/lang/reflect/Method;
    //   257: astore 28
    //   259: iconst_0
    //   260: anewarray 99	java/lang/Object
    //   263: astore 29
    //   265: aload 28
    //   267: aconst_null
    //   268: aload 29
    //   270: invokevirtual 105	java/lang/reflect/Method:invoke	(Ljava/lang/Object;[Ljava/lang/Object;)Ljava/lang/Object;
    //   273: astore 31
    //   275: aload 31
    //   277: checkcast 107	java/lang/Integer
    //   280: invokevirtual 110	java/lang/Integer:intValue	()I
    //   283: putstatic 73	uuuuuu/mmmqqm:b0076vvvv0076v0076v	I
    //   286: ldc 2
    //   288: ldc -73
    //   290: bipush 117
    //   292: iconst_2
    //   293: invokestatic 91	xxxxxx/uxxxxx:bb00620062bb0062b0062b0062	(Ljava/lang/String;CC)Ljava/lang/String;
    //   296: iconst_0
    //   297: anewarray 93	java/lang/Class
    //   300: invokevirtual 97	java/lang/Class:getMethod	(Ljava/lang/String;[Ljava/lang/Class;)Ljava/lang/reflect/Method;
    //   303: astore 32
    //   305: iconst_0
    //   306: anewarray 99	java/lang/Object
    //   309: astore 33
    //   311: aload 32
    //   313: aconst_null
    //   314: aload 33
    //   316: invokevirtual 105	java/lang/reflect/Method:invoke	(Ljava/lang/Object;[Ljava/lang/Object;)Ljava/lang/Object;
    //   319: astore 35
    //   321: aload 35
    //   323: checkcast 107	java/lang/Integer
    //   326: invokevirtual 110	java/lang/Integer:intValue	()I
    //   329: putstatic 79	uuuuuu/mmmqqm:bv0076vvv0076v0076v	I
    //   332: ldc 2
    //   334: ldc -71
    //   336: sipush 187
    //   339: iconst_4
    //   340: invokestatic 91	xxxxxx/uxxxxx:bb00620062bb0062b0062b0062	(Ljava/lang/String;CC)Ljava/lang/String;
    //   343: iconst_0
    //   344: anewarray 93	java/lang/Class
    //   347: invokevirtual 97	java/lang/Class:getMethod	(Ljava/lang/String;[Ljava/lang/Class;)Ljava/lang/reflect/Method;
    //   350: astore 4
    //   352: iconst_0
    //   353: anewarray 99	java/lang/Object
    //   356: astore 5
    //   358: aload 4
    //   360: aload_0
    //   361: aload 5
    //   363: invokevirtual 105	java/lang/reflect/Method:invoke	(Ljava/lang/Object;[Ljava/lang/Object;)Ljava/lang/Object;
    //   366: astore 7
    //   368: aload 7
    //   370: checkcast 187	java/lang/Boolean
    //   373: invokevirtual 190	java/lang/Boolean:booleanValue	()Z
    //   376: ifeq +43 -> 419
    //   379: aload_0
    //   380: getfield 194	uuuuuu/mmmqqm:bnnnnn006E006E006En	Luuuuuu/ttssst$tsssst;
    //   383: checkcast 196	uuuuuu/qqmqqm$qmmqqm
    //   386: getstatic 202	uuuuuu/kvkvvv:bf00660066f0066f006600660066	Luuuuuu/kvkvvv;
    //   389: invokeinterface 206 2 0
    //   394: return
    //   395: astore 30
    //   397: aload 30
    //   399: invokevirtual 148	java/lang/reflect/InvocationTargetException:getCause	()Ljava/lang/Throwable;
    //   402: athrow
    //   403: astore 34
    //   405: aload 34
    //   407: invokevirtual 148	java/lang/reflect/InvocationTargetException:getCause	()Ljava/lang/Throwable;
    //   410: athrow
    //   411: astore 6
    //   413: aload 6
    //   415: invokevirtual 148	java/lang/reflect/InvocationTargetException:getCause	()Ljava/lang/Throwable;
    //   418: athrow
    //   419: aload_0
    //   420: getfield 194	uuuuuu/mmmqqm:bnnnnn006E006E006En	Luuuuuu/ttssst$tsssst;
    //   423: checkcast 196	uuuuuu/qqmqqm$qmmqqm
    //   426: getstatic 209	uuuuuu/kvkvvv:bff0066f0066f006600660066	Luuuuuu/kvkvvv;
    //   429: invokeinterface 206 2 0
    //   434: getstatic 73	uuuuuu/mmmqqm:b0076vvvv0076v0076v	I
    //   437: istore 8
    //   439: ldc 2
    //   441: ldc -45
    //   443: sipush 148
    //   446: sipush 253
    //   449: iconst_1
    //   450: invokestatic 118	xxxxxx/uxxxxx:bbbb0062b0062b0062b0062	(Ljava/lang/String;CCC)Ljava/lang/String;
    //   453: iconst_0
    //   454: anewarray 93	java/lang/Class
    //   457: invokevirtual 97	java/lang/Class:getMethod	(Ljava/lang/String;[Ljava/lang/Class;)Ljava/lang/reflect/Method;
    //   460: astore 9
    //   462: iconst_0
    //   463: anewarray 99	java/lang/Object
    //   466: astore 10
    //   468: aload 9
    //   470: aconst_null
    //   471: aload 10
    //   473: invokevirtual 105	java/lang/reflect/Method:invoke	(Ljava/lang/Object;[Ljava/lang/Object;)Ljava/lang/Object;
    //   476: astore 12
    //   478: iload 8
    //   480: iload 8
    //   482: aload 12
    //   484: checkcast 107	java/lang/Integer
    //   487: invokevirtual 110	java/lang/Integer:intValue	()I
    //   490: iadd
    //   491: imul
    //   492: getstatic 77	uuuuuu/mmmqqm:bvv0076vv0076v0076v	I
    //   495: irem
    //   496: tableswitch	default:+20->516, 0:+73->569
    //   516: ldc 2
    //   518: ldc -43
    //   520: bipush 18
    //   522: bipush 9
    //   524: iconst_3
    //   525: invokestatic 118	xxxxxx/uxxxxx:bbbb0062b0062b0062b0062	(Ljava/lang/String;CCC)Ljava/lang/String;
    //   528: iconst_0
    //   529: anewarray 93	java/lang/Class
    //   532: invokevirtual 97	java/lang/Class:getMethod	(Ljava/lang/String;[Ljava/lang/Class;)Ljava/lang/reflect/Method;
    //   535: astore 15
    //   537: iconst_0
    //   538: anewarray 99	java/lang/Object
    //   541: astore 16
    //   543: aload 15
    //   545: aconst_null
    //   546: aload 16
    //   548: invokevirtual 105	java/lang/reflect/Method:invoke	(Ljava/lang/Object;[Ljava/lang/Object;)Ljava/lang/Object;
    //   551: astore 18
    //   553: aload 18
    //   555: checkcast 107	java/lang/Integer
    //   558: invokevirtual 110	java/lang/Integer:intValue	()I
    //   561: putstatic 73	uuuuuu/mmmqqm:b0076vvvv0076v0076v	I
    //   564: bipush 77
    //   566: putstatic 79	uuuuuu/mmmqqm:bv0076vvv0076v0076v	I
    //   569: iconst_m1
    //   570: newarray int
    //   572: pop
    //   573: goto -4 -> 569
    //   576: astore 13
    //   578: iconst_1
    //   579: putstatic 73	uuuuuu/mmmqqm:b0076vvvv0076v0076v	I
    //   582: return
    //   583: aload_0
    //   584: getfield 63	uuuuuu/mmmqqm:bvvvvv0076v0076v	Ljava/util/List;
    //   587: aload_1
    //   588: invokeinterface 216 2 0
    //   593: pop
    //   594: goto -579 -> 15
    //   597: astore 11
    //   599: aload 11
    //   601: invokevirtual 148	java/lang/reflect/InvocationTargetException:getCause	()Ljava/lang/Throwable;
    //   604: athrow
    //   605: astore 17
    //   607: aload 17
    //   609: invokevirtual 148	java/lang/reflect/InvocationTargetException:getCause	()Ljava/lang/Throwable;
    //   612: athrow
    //   613: astore 21
    //   615: aload 21
    //   617: invokevirtual 148	java/lang/reflect/InvocationTargetException:getCause	()Ljava/lang/Throwable;
    //   620: athrow
    //   621: astore 26
    //   623: aload 26
    //   625: invokevirtual 148	java/lang/reflect/InvocationTargetException:getCause	()Ljava/lang/Throwable;
    //   628: athrow
    //   629: astore 38
    //   631: aload 38
    //   633: invokevirtual 148	java/lang/reflect/InvocationTargetException:getCause	()Ljava/lang/Throwable;
    //   636: athrow
    //   637: astore 42
    //   639: aload 42
    //   641: invokevirtual 148	java/lang/reflect/InvocationTargetException:getCause	()Ljava/lang/Throwable;
    //   644: athrow
    // Local variable table:
    //   start	length	slot	name	signature
    //   0	645	0	this	mmmqqm
    //   0	645	1	paramString	String
    //   0	645	2	paramBoolean	boolean
    //   350	9	4	localMethod1	java.lang.reflect.Method
    //   356	6	5	arrayOfObject1	Object[]
    //   411	3	6	localInvocationTargetException1	java.lang.reflect.InvocationTargetException
    //   366	3	7	localObject1	Object
    //   437	55	8	i	int
    //   460	9	9	localMethod2	java.lang.reflect.Method
    //   466	6	10	arrayOfObject2	Object[]
    //   597	3	11	localInvocationTargetException2	java.lang.reflect.InvocationTargetException
    //   476	7	12	localObject2	Object
    //   576	1	13	localException	Exception
    //   535	9	15	localMethod3	java.lang.reflect.Method
    //   541	6	16	arrayOfObject3	Object[]
    //   605	3	17	localInvocationTargetException3	java.lang.reflect.InvocationTargetException
    //   551	3	18	localObject3	Object
    //   54	9	19	localMethod4	java.lang.reflect.Method
    //   60	6	20	arrayOfObject4	Object[]
    //   613	3	21	localInvocationTargetException4	java.lang.reflect.InvocationTargetException
    //   70	3	22	localObject4	Object
    //   84	49	23	j	int
    //   104	9	24	localMethod5	java.lang.reflect.Method
    //   110	6	25	arrayOfObject5	Object[]
    //   621	3	26	localInvocationTargetException5	java.lang.reflect.InvocationTargetException
    //   120	5	27	localObject5	Object
    //   257	9	28	localMethod6	java.lang.reflect.Method
    //   263	6	29	arrayOfObject6	Object[]
    //   395	3	30	localInvocationTargetException6	java.lang.reflect.InvocationTargetException
    //   273	3	31	localObject6	Object
    //   303	9	32	localMethod7	java.lang.reflect.Method
    //   309	6	33	arrayOfObject7	Object[]
    //   403	3	34	localInvocationTargetException7	java.lang.reflect.InvocationTargetException
    //   319	3	35	localObject7	Object
    //   162	9	36	localMethod8	java.lang.reflect.Method
    //   168	6	37	arrayOfObject8	Object[]
    //   629	3	38	localInvocationTargetException8	java.lang.reflect.InvocationTargetException
    //   178	3	39	localObject8	Object
    //   211	9	40	localMethod9	java.lang.reflect.Method
    //   217	6	41	arrayOfObject9	Object[]
    //   637	3	42	localInvocationTargetException9	java.lang.reflect.InvocationTargetException
    //   227	3	43	localObject9	Object
    // Exception table:
    //   from	to	target	type
    //   265	275	395	java/lang/reflect/InvocationTargetException
    //   311	321	403	java/lang/reflect/InvocationTargetException
    //   358	368	411	java/lang/reflect/InvocationTargetException
    //   569	573	576	java/lang/Exception
    //   468	478	597	java/lang/reflect/InvocationTargetException
    //   543	553	605	java/lang/reflect/InvocationTargetException
    //   62	72	613	java/lang/reflect/InvocationTargetException
    //   112	122	621	java/lang/reflect/InvocationTargetException
    //   170	180	629	java/lang/reflect/InvocationTargetException
    //   219	229	637	java/lang/reflect/InvocationTargetException
  }
  
  /* Error */
  public void b00750075uu0075u0075uu0075(CreateMbaSynchronizationResponse paramCreateMbaSynchronizationResponse)
  {
    // Byte code:
    //   0: aload_0
    //   1: invokevirtual 221	uuuuuu/mmmqqm:bkk006Bk006Bk006Bk006Bk	()Z
    //   4: ifne +56 -> 60
    //   7: getstatic 73	uuuuuu/mmmqqm:b0076vvvv0076v0076v	I
    //   10: istore 39
    //   12: iload 39
    //   14: iload 39
    //   16: getstatic 75	uuuuuu/mmmqqm:b00760076vvv0076v0076v	I
    //   19: iadd
    //   20: imul
    //   21: getstatic 77	uuuuuu/mmmqqm:bvv0076vv0076v0076v	I
    //   24: irem
    //   25: tableswitch	default:+19->44, 0:+29->54
    //   44: bipush 83
    //   46: putstatic 73	uuuuuu/mmmqqm:b0076vvvv0076v0076v	I
    //   49: bipush 72
    //   51: putstatic 79	uuuuuu/mmmqqm:bv0076vvv0076v0076v	I
    //   54: aload_0
    //   55: aload_1
    //   56: putfield 223	uuuuuu/mmmqqm:b00760076007600760076vv0076v	Lcom/db/pwcc/dbmobile/multi_bank_aggregator/model/CreateMbaSynchronizationResponse;
    //   59: return
    //   60: aload_0
    //   61: getfield 225	uuuuuu/mmmqqm:b0076vv00760076vv0076v	Lcom/db/pwcc/dbmobile/multi_bank_aggregator/model/Bank;
    //   64: ifnull +566 -> 630
    //   67: new 227	com/db/pwcc/dbmobile/multi_bank_aggregator/model/MbaSynchronization
    //   70: dup
    //   71: invokespecial 228	com/db/pwcc/dbmobile/multi_bank_aggregator/model/MbaSynchronization:<init>	()V
    //   74: astore_2
    //   75: getstatic 73	uuuuuu/mmmqqm:b0076vvvv0076v0076v	I
    //   78: getstatic 75	uuuuuu/mmmqqm:b00760076vvv0076v0076v	I
    //   81: iadd
    //   82: getstatic 73	uuuuuu/mmmqqm:b0076vvvv0076v0076v	I
    //   85: imul
    //   86: getstatic 77	uuuuuu/mmmqqm:bvv0076vv0076v0076v	I
    //   89: irem
    //   90: getstatic 79	uuuuuu/mmmqqm:bv0076vvv0076v0076v	I
    //   93: if_icmpeq +57 -> 150
    //   96: bipush 36
    //   98: putstatic 73	uuuuuu/mmmqqm:b0076vvvv0076v0076v	I
    //   101: ldc 2
    //   103: ldc -26
    //   105: sipush 246
    //   108: bipush 34
    //   110: iconst_2
    //   111: invokestatic 118	xxxxxx/uxxxxx:bbbb0062b0062b0062b0062	(Ljava/lang/String;CCC)Ljava/lang/String;
    //   114: iconst_0
    //   115: anewarray 93	java/lang/Class
    //   118: invokevirtual 97	java/lang/Class:getMethod	(Ljava/lang/String;[Ljava/lang/Class;)Ljava/lang/reflect/Method;
    //   121: astore 35
    //   123: iconst_0
    //   124: anewarray 99	java/lang/Object
    //   127: astore 36
    //   129: aload 35
    //   131: aconst_null
    //   132: aload 36
    //   134: invokevirtual 105	java/lang/reflect/Method:invoke	(Ljava/lang/Object;[Ljava/lang/Object;)Ljava/lang/Object;
    //   137: astore 38
    //   139: aload 38
    //   141: checkcast 107	java/lang/Integer
    //   144: invokevirtual 110	java/lang/Integer:intValue	()I
    //   147: putstatic 79	uuuuuu/mmmqqm:bv0076vvv0076v0076v	I
    //   150: aload_2
    //   151: aload_1
    //   152: invokevirtual 236	com/db/pwcc/dbmobile/multi_bank_aggregator/model/CreateMbaSynchronizationResponse:getBankLogin	()Lcom/db/pwcc/dbmobile/multi_bank_aggregator/model/BankLogin;
    //   155: invokevirtual 240	com/db/pwcc/dbmobile/multi_bank_aggregator/model/MbaSynchronization:setBankLogin	(Lcom/db/pwcc/dbmobile/multi_bank_aggregator/model/BankLogin;)V
    //   158: aload_2
    //   159: aload_1
    //   160: invokevirtual 244	com/db/pwcc/dbmobile/multi_bank_aggregator/model/CreateMbaSynchronizationResponse:getHref	()Ljava/lang/String;
    //   163: invokevirtual 248	com/db/pwcc/dbmobile/multi_bank_aggregator/model/MbaSynchronization:setHref	(Ljava/lang/String;)V
    //   166: aload_2
    //   167: aload_0
    //   168: getfield 250	uuuuuu/mmmqqm:bv0076v00760076vv0076v	Ljava/lang/String;
    //   171: invokevirtual 253	com/db/pwcc/dbmobile/multi_bank_aggregator/model/MbaSynchronization:setPin	(Ljava/lang/String;)V
    //   174: aload_2
    //   175: aload_0
    //   176: getfield 255	uuuuuu/mmmqqm:bv0076007600760076vv0076v	Z
    //   179: invokevirtual 259	com/db/pwcc/dbmobile/multi_bank_aggregator/model/MbaSynchronization:setPinSaved	(Z)V
    //   182: aload_0
    //   183: getfield 225	uuuuuu/mmmqqm:b0076vv00760076vv0076v	Lcom/db/pwcc/dbmobile/multi_bank_aggregator/model/Bank;
    //   186: invokevirtual 264	com/db/pwcc/dbmobile/multi_bank_aggregator/model/Bank:getName	()Ljava/lang/String;
    //   189: astore_3
    //   190: aload_0
    //   191: getfield 225	uuuuuu/mmmqqm:b0076vv00760076vv0076v	Lcom/db/pwcc/dbmobile/multi_bank_aggregator/model/Bank;
    //   194: invokevirtual 267	com/db/pwcc/dbmobile/multi_bank_aggregator/model/Bank:getCode	()Ljava/lang/String;
    //   197: astore 4
    //   199: aload_0
    //   200: getfield 225	uuuuuu/mmmqqm:b0076vv00760076vv0076v	Lcom/db/pwcc/dbmobile/multi_bank_aggregator/model/Bank;
    //   203: invokevirtual 271	com/db/pwcc/dbmobile/multi_bank_aggregator/model/Bank:getId	()Ljava/lang/Integer;
    //   206: invokevirtual 110	java/lang/Integer:intValue	()I
    //   209: istore 5
    //   211: aload_1
    //   212: invokevirtual 236	com/db/pwcc/dbmobile/multi_bank_aggregator/model/CreateMbaSynchronizationResponse:getBankLogin	()Lcom/db/pwcc/dbmobile/multi_bank_aggregator/model/BankLogin;
    //   215: invokevirtual 275	com/db/pwcc/dbmobile/multi_bank_aggregator/model/BankLogin:getId	()Ljava/lang/String;
    //   218: astore 6
    //   220: aload_0
    //   221: getfield 277	uuuuuu/mmmqqm:bvv007600760076vv0076v	Luuuuuu/qqpqqq;
    //   224: ldc_w 279
    //   227: invokevirtual 285	uuuuuu/qqpqqq:b006Bk006Bk006B006Bk006Bkk	(Ljava/lang/Class;)Luuuuuu/ppqpqq;
    //   230: checkcast 279	uuuuuu/vxvvvx
    //   233: astore 7
    //   235: aload 7
    //   237: aload 6
    //   239: invokevirtual 289	uuuuuu/vxvvvx:b0075u00750075u00750075u00750075	(Ljava/lang/String;)Lcom/db/pwcc/dbmobile/multi_bank_aggregator/data/MbaFinancialOverviewData;
    //   242: astore 8
    //   244: aload 8
    //   246: ifnull +271 -> 517
    //   249: getstatic 73	uuuuuu/mmmqqm:b0076vvvv0076v0076v	I
    //   252: istore 17
    //   254: iload 17
    //   256: iload 17
    //   258: getstatic 75	uuuuuu/mmmqqm:b00760076vvv0076v0076v	I
    //   261: iadd
    //   262: imul
    //   263: istore 18
    //   265: ldc 2
    //   267: ldc_w 291
    //   270: bipush 22
    //   272: iconst_4
    //   273: invokestatic 91	xxxxxx/uxxxxx:bb00620062bb0062b0062b0062	(Ljava/lang/String;CC)Ljava/lang/String;
    //   276: iconst_0
    //   277: anewarray 93	java/lang/Class
    //   280: invokevirtual 97	java/lang/Class:getMethod	(Ljava/lang/String;[Ljava/lang/Class;)Ljava/lang/reflect/Method;
    //   283: astore 19
    //   285: iconst_0
    //   286: anewarray 99	java/lang/Object
    //   289: astore 20
    //   291: aload 19
    //   293: aconst_null
    //   294: aload 20
    //   296: invokevirtual 105	java/lang/reflect/Method:invoke	(Ljava/lang/Object;[Ljava/lang/Object;)Ljava/lang/Object;
    //   299: astore 22
    //   301: iload 18
    //   303: aload 22
    //   305: checkcast 107	java/lang/Integer
    //   308: invokevirtual 110	java/lang/Integer:intValue	()I
    //   311: irem
    //   312: tableswitch	default:+20->332, 0:+114->426
    //   332: ldc 2
    //   334: ldc -43
    //   336: sipush 159
    //   339: iconst_5
    //   340: iconst_2
    //   341: invokestatic 118	xxxxxx/uxxxxx:bbbb0062b0062b0062b0062	(Ljava/lang/String;CCC)Ljava/lang/String;
    //   344: iconst_0
    //   345: anewarray 93	java/lang/Class
    //   348: invokevirtual 97	java/lang/Class:getMethod	(Ljava/lang/String;[Ljava/lang/Class;)Ljava/lang/reflect/Method;
    //   351: astore 27
    //   353: iconst_0
    //   354: anewarray 99	java/lang/Object
    //   357: astore 28
    //   359: aload 27
    //   361: aconst_null
    //   362: aload 28
    //   364: invokevirtual 105	java/lang/reflect/Method:invoke	(Ljava/lang/Object;[Ljava/lang/Object;)Ljava/lang/Object;
    //   367: astore 30
    //   369: aload 30
    //   371: checkcast 107	java/lang/Integer
    //   374: invokevirtual 110	java/lang/Integer:intValue	()I
    //   377: putstatic 73	uuuuuu/mmmqqm:b0076vvvv0076v0076v	I
    //   380: ldc 2
    //   382: ldc 85
    //   384: bipush 15
    //   386: iconst_2
    //   387: invokestatic 91	xxxxxx/uxxxxx:bb00620062bb0062b0062b0062	(Ljava/lang/String;CC)Ljava/lang/String;
    //   390: iconst_0
    //   391: anewarray 93	java/lang/Class
    //   394: invokevirtual 97	java/lang/Class:getMethod	(Ljava/lang/String;[Ljava/lang/Class;)Ljava/lang/reflect/Method;
    //   397: astore 31
    //   399: iconst_0
    //   400: anewarray 99	java/lang/Object
    //   403: astore 32
    //   405: aload 31
    //   407: aconst_null
    //   408: aload 32
    //   410: invokevirtual 105	java/lang/reflect/Method:invoke	(Ljava/lang/Object;[Ljava/lang/Object;)Ljava/lang/Object;
    //   413: astore 34
    //   415: aload 34
    //   417: checkcast 107	java/lang/Integer
    //   420: invokevirtual 110	java/lang/Integer:intValue	()I
    //   423: putstatic 79	uuuuuu/mmmqqm:bv0076vvv0076v0076v	I
    //   426: getstatic 73	uuuuuu/mmmqqm:b0076vvvv0076v0076v	I
    //   429: getstatic 75	uuuuuu/mmmqqm:b00760076vvv0076v0076v	I
    //   432: iadd
    //   433: getstatic 73	uuuuuu/mmmqqm:b0076vvvv0076v0076v	I
    //   436: imul
    //   437: getstatic 77	uuuuuu/mmmqqm:bvv0076vv0076v0076v	I
    //   440: irem
    //   441: getstatic 79	uuuuuu/mmmqqm:bv0076vvv0076v0076v	I
    //   444: if_icmpeq +58 -> 502
    //   447: ldc 2
    //   449: ldc -77
    //   451: sipush 139
    //   454: sipush 192
    //   457: iconst_3
    //   458: invokestatic 118	xxxxxx/uxxxxx:bbbb0062b0062b0062b0062	(Ljava/lang/String;CCC)Ljava/lang/String;
    //   461: iconst_0
    //   462: anewarray 93	java/lang/Class
    //   465: invokevirtual 97	java/lang/Class:getMethod	(Ljava/lang/String;[Ljava/lang/Class;)Ljava/lang/reflect/Method;
    //   468: astore 23
    //   470: iconst_0
    //   471: anewarray 99	java/lang/Object
    //   474: astore 24
    //   476: aload 23
    //   478: aconst_null
    //   479: aload 24
    //   481: invokevirtual 105	java/lang/reflect/Method:invoke	(Ljava/lang/Object;[Ljava/lang/Object;)Ljava/lang/Object;
    //   484: astore 26
    //   486: aload 26
    //   488: checkcast 107	java/lang/Integer
    //   491: invokevirtual 110	java/lang/Integer:intValue	()I
    //   494: putstatic 73	uuuuuu/mmmqqm:b0076vvvv0076v0076v	I
    //   497: bipush 20
    //   499: putstatic 79	uuuuuu/mmmqqm:bv0076vvv0076v0076v	I
    //   502: aload 8
    //   504: invokevirtual 297	com/db/pwcc/dbmobile/multi_bank_aggregator/data/MbaFinancialOverviewData:getSynchronization	()Lcom/db/pwcc/dbmobile/multi_bank_aggregator/model/MbaSynchronization;
    //   507: ifnull +10 -> 517
    //   510: aload 7
    //   512: aload 6
    //   514: invokevirtual 300	uuuuuu/vxvvvx:b006Bk006B006B006B006Bk006Bkk	(Ljava/lang/String;)V
    //   517: aload 7
    //   519: aload_2
    //   520: iload 5
    //   522: aload_3
    //   523: aload 4
    //   525: invokevirtual 304	uuuuuu/vxvvvx:bu0075uuu00750075u00750075	(Lcom/db/pwcc/dbmobile/multi_bank_aggregator/model/MbaSynchronization;ILjava/lang/String;Ljava/lang/String;)V
    //   528: ldc 2
    //   530: ldc_w 306
    //   533: bipush 33
    //   535: iconst_0
    //   536: invokestatic 91	xxxxxx/uxxxxx:bb00620062bb0062b0062b0062	(Ljava/lang/String;CC)Ljava/lang/String;
    //   539: iconst_0
    //   540: anewarray 93	java/lang/Class
    //   543: invokevirtual 309	java/lang/Class:getDeclaredMethod	(Ljava/lang/String;[Ljava/lang/Class;)Ljava/lang/reflect/Method;
    //   546: astore 9
    //   548: iconst_0
    //   549: anewarray 99	java/lang/Object
    //   552: astore 10
    //   554: aload 9
    //   556: aload_0
    //   557: aload 10
    //   559: invokevirtual 105	java/lang/reflect/Method:invoke	(Ljava/lang/Object;[Ljava/lang/Object;)Ljava/lang/Object;
    //   562: pop
    //   563: ldc 2
    //   565: ldc_w 311
    //   568: sipush 246
    //   571: bipush 84
    //   573: iconst_2
    //   574: invokestatic 118	xxxxxx/uxxxxx:bbbb0062b0062b0062b0062	(Ljava/lang/String;CCC)Ljava/lang/String;
    //   577: iconst_0
    //   578: anewarray 93	java/lang/Class
    //   581: invokevirtual 309	java/lang/Class:getDeclaredMethod	(Ljava/lang/String;[Ljava/lang/Class;)Ljava/lang/reflect/Method;
    //   584: astore 13
    //   586: iconst_0
    //   587: anewarray 99	java/lang/Object
    //   590: astore 14
    //   592: aload 13
    //   594: aload_0
    //   595: aload 14
    //   597: invokevirtual 105	java/lang/reflect/Method:invoke	(Ljava/lang/Object;[Ljava/lang/Object;)Ljava/lang/Object;
    //   600: pop
    //   601: aload 7
    //   603: aload 6
    //   605: invokevirtual 314	uuuuuu/vxvvvx:b0075uuuu00750075u00750075	(Ljava/lang/String;)V
    //   608: aload_0
    //   609: getfield 194	uuuuuu/mmmqqm:bnnnnn006E006E006En	Luuuuuu/ttssst$tsssst;
    //   612: checkcast 196	uuuuuu/qqmqqm$qmmqqm
    //   615: aload_1
    //   616: invokeinterface 317 2 0
    //   621: return
    //   622: astore 11
    //   624: aload 11
    //   626: invokevirtual 148	java/lang/reflect/InvocationTargetException:getCause	()Ljava/lang/Throwable;
    //   629: athrow
    //   630: aload_0
    //   631: getfield 194	uuuuuu/mmmqqm:bnnnnn006E006E006En	Luuuuuu/ttssst$tsssst;
    //   634: checkcast 196	uuuuuu/qqmqqm$qmmqqm
    //   637: getstatic 322	com/db/pwcc/dbmobile/multi_bank_aggregator/R$string:technical_error_retry	I
    //   640: invokeinterface 326 2 0
    //   645: aload_0
    //   646: getfield 194	uuuuuu/mmmqqm:bnnnnn006E006E006En	Luuuuuu/ttssst$tsssst;
    //   649: checkcast 196	uuuuuu/qqmqqm$qmmqqm
    //   652: getstatic 202	uuuuuu/kvkvvv:bf00660066f0066f006600660066	Luuuuuu/kvkvvv;
    //   655: invokeinterface 206 2 0
    //   660: return
    //   661: astore 21
    //   663: aload 21
    //   665: invokevirtual 148	java/lang/reflect/InvocationTargetException:getCause	()Ljava/lang/Throwable;
    //   668: athrow
    //   669: astore 15
    //   671: aload 15
    //   673: invokevirtual 148	java/lang/reflect/InvocationTargetException:getCause	()Ljava/lang/Throwable;
    //   676: athrow
    //   677: astore 29
    //   679: aload 29
    //   681: invokevirtual 148	java/lang/reflect/InvocationTargetException:getCause	()Ljava/lang/Throwable;
    //   684: athrow
    //   685: astore 33
    //   687: aload 33
    //   689: invokevirtual 148	java/lang/reflect/InvocationTargetException:getCause	()Ljava/lang/Throwable;
    //   692: athrow
    //   693: astore 37
    //   695: aload 37
    //   697: invokevirtual 148	java/lang/reflect/InvocationTargetException:getCause	()Ljava/lang/Throwable;
    //   700: athrow
    //   701: astore 25
    //   703: aload 25
    //   705: invokevirtual 148	java/lang/reflect/InvocationTargetException:getCause	()Ljava/lang/Throwable;
    //   708: athrow
    // Local variable table:
    //   start	length	slot	name	signature
    //   0	709	0	this	mmmqqm
    //   0	709	1	paramCreateMbaSynchronizationResponse	CreateMbaSynchronizationResponse
    //   74	446	2	localMbaSynchronization	com.db.pwcc.dbmobile.multi_bank_aggregator.model.MbaSynchronization
    //   189	334	3	str1	String
    //   197	327	4	str2	String
    //   209	312	5	i	int
    //   218	386	6	str3	String
    //   233	369	7	localVxvvvx	vxvvvx
    //   242	261	8	localMbaFinancialOverviewData	com.db.pwcc.dbmobile.multi_bank_aggregator.data.MbaFinancialOverviewData
    //   546	9	9	localMethod1	java.lang.reflect.Method
    //   552	6	10	arrayOfObject1	Object[]
    //   622	3	11	localInvocationTargetException1	java.lang.reflect.InvocationTargetException
    //   584	9	13	localMethod2	java.lang.reflect.Method
    //   590	6	14	arrayOfObject2	Object[]
    //   669	3	15	localInvocationTargetException2	java.lang.reflect.InvocationTargetException
    //   252	11	17	j	int
    //   263	49	18	k	int
    //   283	9	19	localMethod3	java.lang.reflect.Method
    //   289	6	20	arrayOfObject3	Object[]
    //   661	3	21	localInvocationTargetException3	java.lang.reflect.InvocationTargetException
    //   299	5	22	localObject1	Object
    //   468	9	23	localMethod4	java.lang.reflect.Method
    //   474	6	24	arrayOfObject4	Object[]
    //   701	3	25	localInvocationTargetException4	java.lang.reflect.InvocationTargetException
    //   484	3	26	localObject2	Object
    //   351	9	27	localMethod5	java.lang.reflect.Method
    //   357	6	28	arrayOfObject5	Object[]
    //   677	3	29	localInvocationTargetException5	java.lang.reflect.InvocationTargetException
    //   367	3	30	localObject3	Object
    //   397	9	31	localMethod6	java.lang.reflect.Method
    //   403	6	32	arrayOfObject6	Object[]
    //   685	3	33	localInvocationTargetException6	java.lang.reflect.InvocationTargetException
    //   413	3	34	localObject4	Object
    //   121	9	35	localMethod7	java.lang.reflect.Method
    //   127	6	36	arrayOfObject7	Object[]
    //   693	3	37	localInvocationTargetException7	java.lang.reflect.InvocationTargetException
    //   137	3	38	localObject5	Object
    //   10	11	39	m	int
    // Exception table:
    //   from	to	target	type
    //   554	563	622	java/lang/reflect/InvocationTargetException
    //   291	301	661	java/lang/reflect/InvocationTargetException
    //   592	601	669	java/lang/reflect/InvocationTargetException
    //   359	369	677	java/lang/reflect/InvocationTargetException
    //   405	415	685	java/lang/reflect/InvocationTargetException
    //   129	139	693	java/lang/reflect/InvocationTargetException
    //   476	486	701	java/lang/reflect/InvocationTargetException
  }
  
  /* Error */
  public void b0075uu0075uu0075uu0075(Bank paramBank, com.db.pwcc.dbmobile.multi_bank_aggregator.model.ProductInfoArray paramProductInfoArray, String paramString, boolean paramBoolean)
  {
    // Byte code:
    //   0: new 330	uuuuuu/ossooo
    //   3: dup
    //   4: invokespecial 331	uuuuuu/ossooo:<init>	()V
    //   7: astore 5
    //   9: getstatic 73	uuuuuu/mmmqqm:b0076vvvv0076v0076v	I
    //   12: getstatic 75	uuuuuu/mmmqqm:b00760076vvv0076v0076v	I
    //   15: iadd
    //   16: getstatic 73	uuuuuu/mmmqqm:b0076vvvv0076v0076v	I
    //   19: imul
    //   20: getstatic 77	uuuuuu/mmmqqm:bvv0076vv0076v0076v	I
    //   23: irem
    //   24: istore 6
    //   26: getstatic 79	uuuuuu/mmmqqm:bv0076vvv0076v0076v	I
    //   29: istore 7
    //   31: getstatic 73	uuuuuu/mmmqqm:b0076vvvv0076v0076v	I
    //   34: istore 8
    //   36: iload 8
    //   38: iload 8
    //   40: getstatic 75	uuuuuu/mmmqqm:b00760076vvv0076v0076v	I
    //   43: iadd
    //   44: imul
    //   45: getstatic 77	uuuuuu/mmmqqm:bvv0076vv0076v0076v	I
    //   48: irem
    //   49: tableswitch	default:+19->68, 0:+72->121
    //   68: ldc 2
    //   70: ldc_w 333
    //   73: sipush 234
    //   76: iconst_5
    //   77: invokestatic 91	xxxxxx/uxxxxx:bb00620062bb0062b0062b0062	(Ljava/lang/String;CC)Ljava/lang/String;
    //   80: iconst_0
    //   81: anewarray 93	java/lang/Class
    //   84: invokevirtual 97	java/lang/Class:getMethod	(Ljava/lang/String;[Ljava/lang/Class;)Ljava/lang/reflect/Method;
    //   87: astore 35
    //   89: iconst_0
    //   90: anewarray 99	java/lang/Object
    //   93: astore 36
    //   95: aload 35
    //   97: aconst_null
    //   98: aload 36
    //   100: invokevirtual 105	java/lang/reflect/Method:invoke	(Ljava/lang/Object;[Ljava/lang/Object;)Ljava/lang/Object;
    //   103: astore 38
    //   105: aload 38
    //   107: checkcast 107	java/lang/Integer
    //   110: invokevirtual 110	java/lang/Integer:intValue	()I
    //   113: putstatic 73	uuuuuu/mmmqqm:b0076vvvv0076v0076v	I
    //   116: bipush 81
    //   118: putstatic 79	uuuuuu/mmmqqm:bv0076vvv0076v0076v	I
    //   121: iload 6
    //   123: iload 7
    //   125: if_icmpeq +97 -> 222
    //   128: ldc 2
    //   130: ldc_w 335
    //   133: bipush 122
    //   135: iconst_0
    //   136: invokestatic 91	xxxxxx/uxxxxx:bb00620062bb0062b0062b0062	(Ljava/lang/String;CC)Ljava/lang/String;
    //   139: iconst_0
    //   140: anewarray 93	java/lang/Class
    //   143: invokevirtual 97	java/lang/Class:getMethod	(Ljava/lang/String;[Ljava/lang/Class;)Ljava/lang/reflect/Method;
    //   146: astore 27
    //   148: iconst_0
    //   149: anewarray 99	java/lang/Object
    //   152: astore 28
    //   154: aload 27
    //   156: aconst_null
    //   157: aload 28
    //   159: invokevirtual 105	java/lang/reflect/Method:invoke	(Ljava/lang/Object;[Ljava/lang/Object;)Ljava/lang/Object;
    //   162: astore 30
    //   164: aload 30
    //   166: checkcast 107	java/lang/Integer
    //   169: invokevirtual 110	java/lang/Integer:intValue	()I
    //   172: putstatic 73	uuuuuu/mmmqqm:b0076vvvv0076v0076v	I
    //   175: ldc 2
    //   177: ldc_w 337
    //   180: bipush 99
    //   182: iconst_1
    //   183: invokestatic 91	xxxxxx/uxxxxx:bb00620062bb0062b0062b0062	(Ljava/lang/String;CC)Ljava/lang/String;
    //   186: iconst_0
    //   187: anewarray 93	java/lang/Class
    //   190: invokevirtual 97	java/lang/Class:getMethod	(Ljava/lang/String;[Ljava/lang/Class;)Ljava/lang/reflect/Method;
    //   193: astore 31
    //   195: iconst_0
    //   196: anewarray 99	java/lang/Object
    //   199: astore 32
    //   201: aload 31
    //   203: aconst_null
    //   204: aload 32
    //   206: invokevirtual 105	java/lang/reflect/Method:invoke	(Ljava/lang/Object;[Ljava/lang/Object;)Ljava/lang/Object;
    //   209: astore 34
    //   211: aload 34
    //   213: checkcast 107	java/lang/Integer
    //   216: invokevirtual 110	java/lang/Integer:intValue	()I
    //   219: putstatic 79	uuuuuu/mmmqqm:bv0076vvv0076v0076v	I
    //   222: aload_0
    //   223: aload 5
    //   225: putfield 339	uuuuuu/mmmqqm:b0076v007600760076vv0076v	Luuuuuu/ossooo;
    //   228: new 341	java/util/ArrayList
    //   231: dup
    //   232: invokespecial 342	java/util/ArrayList:<init>	()V
    //   235: astore 9
    //   237: aload_2
    //   238: invokevirtual 348	com/db/pwcc/dbmobile/multi_bank_aggregator/model/ProductInfoArray:getProductInfoArray	()Ljava/util/ArrayList;
    //   241: invokevirtual 349	java/util/ArrayList:iterator	()Ljava/util/Iterator;
    //   244: astore 10
    //   246: aload 10
    //   248: invokeinterface 126 1 0
    //   253: ifeq +41 -> 294
    //   256: aload 9
    //   258: aload 10
    //   260: invokeinterface 130 1 0
    //   265: checkcast 351	com/db/pwcc/dbmobile/multi_bank_aggregator/model/ProductInfo
    //   268: invokevirtual 352	com/db/pwcc/dbmobile/multi_bank_aggregator/model/ProductInfo:getId	()Ljava/lang/String;
    //   271: invokevirtual 353	java/util/ArrayList:add	(Ljava/lang/Object;)Z
    //   274: pop
    //   275: goto -29 -> 246
    //   278: astore 29
    //   280: aload 29
    //   282: invokevirtual 148	java/lang/reflect/InvocationTargetException:getCause	()Ljava/lang/Throwable;
    //   285: athrow
    //   286: astore 33
    //   288: aload 33
    //   290: invokevirtual 148	java/lang/reflect/InvocationTargetException:getCause	()Ljava/lang/Throwable;
    //   293: athrow
    //   294: aload_0
    //   295: aload 9
    //   297: putfield 63	uuuuuu/mmmqqm:bvvvvv0076v0076v	Ljava/util/List;
    //   300: aload_0
    //   301: new 355	java/util/HashSet
    //   304: dup
    //   305: aload 9
    //   307: invokespecial 358	java/util/HashSet:<init>	(Ljava/util/Collection;)V
    //   310: putfield 65	uuuuuu/mmmqqm:bvvv00760076vv0076v	Ljava/util/Set;
    //   313: aload_0
    //   314: aload_1
    //   315: putfield 225	uuuuuu/mmmqqm:b0076vv00760076vv0076v	Lcom/db/pwcc/dbmobile/multi_bank_aggregator/model/Bank;
    //   318: getstatic 73	uuuuuu/mmmqqm:b0076vvvv0076v0076v	I
    //   321: istore 11
    //   323: ldc 2
    //   325: ldc_w 360
    //   328: bipush 126
    //   330: sipush 186
    //   333: iconst_1
    //   334: invokestatic 118	xxxxxx/uxxxxx:bbbb0062b0062b0062b0062	(Ljava/lang/String;CCC)Ljava/lang/String;
    //   337: iconst_0
    //   338: anewarray 93	java/lang/Class
    //   341: invokevirtual 97	java/lang/Class:getMethod	(Ljava/lang/String;[Ljava/lang/Class;)Ljava/lang/reflect/Method;
    //   344: astore 12
    //   346: iconst_0
    //   347: anewarray 99	java/lang/Object
    //   350: astore 13
    //   352: aload 12
    //   354: aconst_null
    //   355: aload 13
    //   357: invokevirtual 105	java/lang/reflect/Method:invoke	(Ljava/lang/Object;[Ljava/lang/Object;)Ljava/lang/Object;
    //   360: astore 15
    //   362: iload 11
    //   364: aload 15
    //   366: checkcast 107	java/lang/Integer
    //   369: invokevirtual 110	java/lang/Integer:intValue	()I
    //   372: iadd
    //   373: getstatic 73	uuuuuu/mmmqqm:b0076vvvv0076v0076v	I
    //   376: imul
    //   377: istore 16
    //   379: getstatic 73	uuuuuu/mmmqqm:b0076vvvv0076v0076v	I
    //   382: istore 17
    //   384: iload 17
    //   386: iload 17
    //   388: getstatic 75	uuuuuu/mmmqqm:b00760076vvv0076v0076v	I
    //   391: iadd
    //   392: imul
    //   393: getstatic 77	uuuuuu/mmmqqm:bvv0076vv0076v0076v	I
    //   396: irem
    //   397: tableswitch	default:+19->416, 0:+71->468
    //   416: ldc 2
    //   418: ldc_w 362
    //   421: bipush 120
    //   423: iconst_1
    //   424: invokestatic 91	xxxxxx/uxxxxx:bb00620062bb0062b0062b0062	(Ljava/lang/String;CC)Ljava/lang/String;
    //   427: iconst_0
    //   428: anewarray 93	java/lang/Class
    //   431: invokevirtual 97	java/lang/Class:getMethod	(Ljava/lang/String;[Ljava/lang/Class;)Ljava/lang/reflect/Method;
    //   434: astore 22
    //   436: iconst_0
    //   437: anewarray 99	java/lang/Object
    //   440: astore 23
    //   442: aload 22
    //   444: aconst_null
    //   445: aload 23
    //   447: invokevirtual 105	java/lang/reflect/Method:invoke	(Ljava/lang/Object;[Ljava/lang/Object;)Ljava/lang/Object;
    //   450: astore 25
    //   452: aload 25
    //   454: checkcast 107	java/lang/Integer
    //   457: invokevirtual 110	java/lang/Integer:intValue	()I
    //   460: putstatic 73	uuuuuu/mmmqqm:b0076vvvv0076v0076v	I
    //   463: bipush 31
    //   465: putstatic 79	uuuuuu/mmmqqm:bv0076vvv0076v0076v	I
    //   468: iload 16
    //   470: getstatic 77	uuuuuu/mmmqqm:bvv0076vv0076v0076v	I
    //   473: irem
    //   474: getstatic 79	uuuuuu/mmmqqm:bv0076vvv0076v0076v	I
    //   477: if_icmpeq +55 -> 532
    //   480: ldc 2
    //   482: ldc_w 364
    //   485: bipush 121
    //   487: iconst_1
    //   488: invokestatic 91	xxxxxx/uxxxxx:bb00620062bb0062b0062b0062	(Ljava/lang/String;CC)Ljava/lang/String;
    //   491: iconst_0
    //   492: anewarray 93	java/lang/Class
    //   495: invokevirtual 97	java/lang/Class:getMethod	(Ljava/lang/String;[Ljava/lang/Class;)Ljava/lang/reflect/Method;
    //   498: astore 18
    //   500: iconst_0
    //   501: anewarray 99	java/lang/Object
    //   504: astore 19
    //   506: aload 18
    //   508: aconst_null
    //   509: aload 19
    //   511: invokevirtual 105	java/lang/reflect/Method:invoke	(Ljava/lang/Object;[Ljava/lang/Object;)Ljava/lang/Object;
    //   514: astore 21
    //   516: aload 21
    //   518: checkcast 107	java/lang/Integer
    //   521: invokevirtual 110	java/lang/Integer:intValue	()I
    //   524: putstatic 73	uuuuuu/mmmqqm:b0076vvvv0076v0076v	I
    //   527: bipush 82
    //   529: putstatic 79	uuuuuu/mmmqqm:bv0076vvv0076v0076v	I
    //   532: aload_0
    //   533: aload_3
    //   534: putfield 250	uuuuuu/mmmqqm:bv0076v00760076vv0076v	Ljava/lang/String;
    //   537: aload_0
    //   538: iload 4
    //   540: putfield 255	uuuuuu/mmmqqm:bv0076007600760076vv0076v	Z
    //   543: return
    //   544: astore 14
    //   546: aload 14
    //   548: invokevirtual 148	java/lang/reflect/InvocationTargetException:getCause	()Ljava/lang/Throwable;
    //   551: athrow
    //   552: astore 37
    //   554: aload 37
    //   556: invokevirtual 148	java/lang/reflect/InvocationTargetException:getCause	()Ljava/lang/Throwable;
    //   559: athrow
    //   560: astore 20
    //   562: aload 20
    //   564: invokevirtual 148	java/lang/reflect/InvocationTargetException:getCause	()Ljava/lang/Throwable;
    //   567: athrow
    //   568: astore 24
    //   570: aload 24
    //   572: invokevirtual 148	java/lang/reflect/InvocationTargetException:getCause	()Ljava/lang/Throwable;
    //   575: athrow
    // Local variable table:
    //   start	length	slot	name	signature
    //   0	576	0	this	mmmqqm
    //   0	576	1	paramBank	Bank
    //   0	576	2	paramProductInfoArray	com.db.pwcc.dbmobile.multi_bank_aggregator.model.ProductInfoArray
    //   0	576	3	paramString	String
    //   0	576	4	paramBoolean	boolean
    //   7	217	5	localOssooo	ossooo
    //   24	102	6	i	int
    //   29	97	7	j	int
    //   34	11	8	k	int
    //   235	71	9	localArrayList	java.util.ArrayList
    //   244	15	10	localIterator	java.util.Iterator
    //   321	52	11	m	int
    //   344	9	12	localMethod1	java.lang.reflect.Method
    //   350	6	13	arrayOfObject1	Object[]
    //   544	3	14	localInvocationTargetException1	java.lang.reflect.InvocationTargetException
    //   360	5	15	localObject1	Object
    //   377	97	16	n	int
    //   382	11	17	i1	int
    //   498	9	18	localMethod2	java.lang.reflect.Method
    //   504	6	19	arrayOfObject2	Object[]
    //   560	3	20	localInvocationTargetException2	java.lang.reflect.InvocationTargetException
    //   514	3	21	localObject2	Object
    //   434	9	22	localMethod3	java.lang.reflect.Method
    //   440	6	23	arrayOfObject3	Object[]
    //   568	3	24	localInvocationTargetException3	java.lang.reflect.InvocationTargetException
    //   450	3	25	localObject3	Object
    //   146	9	27	localMethod4	java.lang.reflect.Method
    //   152	6	28	arrayOfObject4	Object[]
    //   278	3	29	localInvocationTargetException4	java.lang.reflect.InvocationTargetException
    //   162	3	30	localObject4	Object
    //   193	9	31	localMethod5	java.lang.reflect.Method
    //   199	6	32	arrayOfObject5	Object[]
    //   286	3	33	localInvocationTargetException5	java.lang.reflect.InvocationTargetException
    //   209	3	34	localObject5	Object
    //   87	9	35	localMethod6	java.lang.reflect.Method
    //   93	6	36	arrayOfObject6	Object[]
    //   552	3	37	localInvocationTargetException6	java.lang.reflect.InvocationTargetException
    //   103	3	38	localObject6	Object
    // Exception table:
    //   from	to	target	type
    //   154	164	278	java/lang/reflect/InvocationTargetException
    //   201	211	286	java/lang/reflect/InvocationTargetException
    //   352	362	544	java/lang/reflect/InvocationTargetException
    //   95	105	552	java/lang/reflect/InvocationTargetException
    //   506	516	560	java/lang/reflect/InvocationTargetException
    //   442	452	568	java/lang/reflect/InvocationTargetException
  }
  
  /* Error */
  public boolean b0075uuu0075u0075uu0075()
  {
    // Byte code:
    //   0: aload_0
    //   1: getfield 63	uuuuuu/mmmqqm:bvvvvv0076v0076v	Ljava/util/List;
    //   4: invokeinterface 368 1 0
    //   9: ifne +197 -> 206
    //   12: getstatic 73	uuuuuu/mmmqqm:b0076vvvv0076v0076v	I
    //   15: istore 25
    //   17: ldc 2
    //   19: ldc_w 370
    //   22: bipush 23
    //   24: iconst_0
    //   25: invokestatic 91	xxxxxx/uxxxxx:bb00620062bb0062b0062b0062	(Ljava/lang/String;CC)Ljava/lang/String;
    //   28: iconst_0
    //   29: anewarray 93	java/lang/Class
    //   32: invokevirtual 97	java/lang/Class:getMethod	(Ljava/lang/String;[Ljava/lang/Class;)Ljava/lang/reflect/Method;
    //   35: astore 26
    //   37: iconst_0
    //   38: anewarray 99	java/lang/Object
    //   41: astore 27
    //   43: aload 26
    //   45: aconst_null
    //   46: aload 27
    //   48: invokevirtual 105	java/lang/reflect/Method:invoke	(Ljava/lang/Object;[Ljava/lang/Object;)Ljava/lang/Object;
    //   51: astore 29
    //   53: iload 25
    //   55: iload 25
    //   57: aload 29
    //   59: checkcast 107	java/lang/Integer
    //   62: invokevirtual 110	java/lang/Integer:intValue	()I
    //   65: iadd
    //   66: imul
    //   67: getstatic 77	uuuuuu/mmmqqm:bvv0076vv0076v0076v	I
    //   70: irem
    //   71: tableswitch	default:+17->88, 0:+70->141
    //   88: ldc 2
    //   90: ldc_w 372
    //   93: sipush 248
    //   96: iconst_0
    //   97: invokestatic 91	xxxxxx/uxxxxx:bb00620062bb0062b0062b0062	(Ljava/lang/String;CC)Ljava/lang/String;
    //   100: iconst_0
    //   101: anewarray 93	java/lang/Class
    //   104: invokevirtual 97	java/lang/Class:getMethod	(Ljava/lang/String;[Ljava/lang/Class;)Ljava/lang/reflect/Method;
    //   107: astore 30
    //   109: iconst_0
    //   110: anewarray 99	java/lang/Object
    //   113: astore 31
    //   115: aload 30
    //   117: aconst_null
    //   118: aload 31
    //   120: invokevirtual 105	java/lang/reflect/Method:invoke	(Ljava/lang/Object;[Ljava/lang/Object;)Ljava/lang/Object;
    //   123: astore 33
    //   125: aload 33
    //   127: checkcast 107	java/lang/Integer
    //   130: invokevirtual 110	java/lang/Integer:intValue	()I
    //   133: putstatic 73	uuuuuu/mmmqqm:b0076vvvv0076v0076v	I
    //   136: bipush 14
    //   138: putstatic 79	uuuuuu/mmmqqm:bv0076vvv0076v0076v	I
    //   141: iconst_1
    //   142: ireturn
    //   143: astore 20
    //   145: ldc 2
    //   147: ldc_w 374
    //   150: sipush 196
    //   153: sipush 220
    //   156: iconst_2
    //   157: invokestatic 118	xxxxxx/uxxxxx:bbbb0062b0062b0062b0062	(Ljava/lang/String;CCC)Ljava/lang/String;
    //   160: iconst_0
    //   161: anewarray 93	java/lang/Class
    //   164: invokevirtual 97	java/lang/Class:getMethod	(Ljava/lang/String;[Ljava/lang/Class;)Ljava/lang/reflect/Method;
    //   167: astore 21
    //   169: iconst_0
    //   170: anewarray 99	java/lang/Object
    //   173: astore 22
    //   175: aload 21
    //   177: aconst_null
    //   178: aload 22
    //   180: invokevirtual 105	java/lang/reflect/Method:invoke	(Ljava/lang/Object;[Ljava/lang/Object;)Ljava/lang/Object;
    //   183: astore 24
    //   185: aload 24
    //   187: checkcast 107	java/lang/Integer
    //   190: invokevirtual 110	java/lang/Integer:intValue	()I
    //   193: putstatic 73	uuuuuu/mmmqqm:b0076vvvv0076v0076v	I
    //   196: iconst_0
    //   197: ireturn
    //   198: astore 23
    //   200: aload 23
    //   202: invokevirtual 148	java/lang/reflect/InvocationTargetException:getCause	()Ljava/lang/Throwable;
    //   205: athrow
    //   206: iconst_m1
    //   207: newarray int
    //   209: pop
    //   210: ldc 2
    //   212: ldc_w 376
    //   215: sipush 250
    //   218: iconst_4
    //   219: invokestatic 91	xxxxxx/uxxxxx:bb00620062bb0062b0062b0062	(Ljava/lang/String;CC)Ljava/lang/String;
    //   222: iconst_0
    //   223: anewarray 93	java/lang/Class
    //   226: invokevirtual 97	java/lang/Class:getMethod	(Ljava/lang/String;[Ljava/lang/Class;)Ljava/lang/reflect/Method;
    //   229: astore_2
    //   230: iconst_0
    //   231: anewarray 99	java/lang/Object
    //   234: astore_3
    //   235: aload_2
    //   236: aconst_null
    //   237: aload_3
    //   238: invokevirtual 105	java/lang/reflect/Method:invoke	(Ljava/lang/Object;[Ljava/lang/Object;)Ljava/lang/Object;
    //   241: astore 5
    //   243: aload 5
    //   245: checkcast 107	java/lang/Integer
    //   248: invokevirtual 110	java/lang/Integer:intValue	()I
    //   251: getstatic 75	uuuuuu/mmmqqm:b00760076vvv0076v0076v	I
    //   254: iadd
    //   255: istore 6
    //   257: ldc 2
    //   259: ldc_w 378
    //   262: sipush 153
    //   265: iconst_0
    //   266: invokestatic 91	xxxxxx/uxxxxx:bb00620062bb0062b0062b0062	(Ljava/lang/String;CC)Ljava/lang/String;
    //   269: iconst_0
    //   270: anewarray 93	java/lang/Class
    //   273: invokevirtual 97	java/lang/Class:getMethod	(Ljava/lang/String;[Ljava/lang/Class;)Ljava/lang/reflect/Method;
    //   276: astore 7
    //   278: iconst_0
    //   279: anewarray 99	java/lang/Object
    //   282: astore 8
    //   284: aload 7
    //   286: aconst_null
    //   287: aload 8
    //   289: invokevirtual 105	java/lang/reflect/Method:invoke	(Ljava/lang/Object;[Ljava/lang/Object;)Ljava/lang/Object;
    //   292: astore 10
    //   294: iload 6
    //   296: aload 10
    //   298: checkcast 107	java/lang/Integer
    //   301: invokevirtual 110	java/lang/Integer:intValue	()I
    //   304: imul
    //   305: getstatic 77	uuuuuu/mmmqqm:bvv0076vv0076v0076v	I
    //   308: irem
    //   309: getstatic 79	uuuuuu/mmmqqm:bv0076vvv0076v0076v	I
    //   312: if_icmpeq +98 -> 410
    //   315: ldc 2
    //   317: ldc_w 380
    //   320: sipush 140
    //   323: iconst_3
    //   324: invokestatic 91	xxxxxx/uxxxxx:bb00620062bb0062b0062b0062	(Ljava/lang/String;CC)Ljava/lang/String;
    //   327: iconst_0
    //   328: anewarray 93	java/lang/Class
    //   331: invokevirtual 97	java/lang/Class:getMethod	(Ljava/lang/String;[Ljava/lang/Class;)Ljava/lang/reflect/Method;
    //   334: astore 12
    //   336: iconst_0
    //   337: anewarray 99	java/lang/Object
    //   340: astore 13
    //   342: aload 12
    //   344: aconst_null
    //   345: aload 13
    //   347: invokevirtual 105	java/lang/reflect/Method:invoke	(Ljava/lang/Object;[Ljava/lang/Object;)Ljava/lang/Object;
    //   350: astore 15
    //   352: aload 15
    //   354: checkcast 107	java/lang/Integer
    //   357: invokevirtual 110	java/lang/Integer:intValue	()I
    //   360: putstatic 73	uuuuuu/mmmqqm:b0076vvvv0076v0076v	I
    //   363: ldc 2
    //   365: ldc_w 382
    //   368: bipush 13
    //   370: iconst_0
    //   371: invokestatic 91	xxxxxx/uxxxxx:bb00620062bb0062b0062b0062	(Ljava/lang/String;CC)Ljava/lang/String;
    //   374: iconst_0
    //   375: anewarray 93	java/lang/Class
    //   378: invokevirtual 97	java/lang/Class:getMethod	(Ljava/lang/String;[Ljava/lang/Class;)Ljava/lang/reflect/Method;
    //   381: astore 16
    //   383: iconst_0
    //   384: anewarray 99	java/lang/Object
    //   387: astore 17
    //   389: aload 16
    //   391: aconst_null
    //   392: aload 17
    //   394: invokevirtual 105	java/lang/reflect/Method:invoke	(Ljava/lang/Object;[Ljava/lang/Object;)Ljava/lang/Object;
    //   397: astore 19
    //   399: aload 19
    //   401: checkcast 107	java/lang/Integer
    //   404: invokevirtual 110	java/lang/Integer:intValue	()I
    //   407: putstatic 79	uuuuuu/mmmqqm:bv0076vvv0076v0076v	I
    //   410: getstatic 73	uuuuuu/mmmqqm:b0076vvvv0076v0076v	I
    //   413: istore 11
    //   415: iload 11
    //   417: iload 11
    //   419: getstatic 75	uuuuuu/mmmqqm:b00760076vvv0076v0076v	I
    //   422: iadd
    //   423: imul
    //   424: getstatic 77	uuuuuu/mmmqqm:bvv0076vv0076v0076v	I
    //   427: irem
    //   428: tableswitch	default:+20->448, 0:+-222->206
    //   448: bipush 96
    //   450: putstatic 73	uuuuuu/mmmqqm:b0076vvvv0076v0076v	I
    //   453: bipush 80
    //   455: putstatic 79	uuuuuu/mmmqqm:bv0076vvv0076v0076v	I
    //   458: goto -252 -> 206
    //   461: astore 4
    //   463: aload 4
    //   465: invokevirtual 148	java/lang/reflect/InvocationTargetException:getCause	()Ljava/lang/Throwable;
    //   468: athrow
    //   469: astore 9
    //   471: aload 9
    //   473: invokevirtual 148	java/lang/reflect/InvocationTargetException:getCause	()Ljava/lang/Throwable;
    //   476: athrow
    //   477: astore 28
    //   479: aload 28
    //   481: invokevirtual 148	java/lang/reflect/InvocationTargetException:getCause	()Ljava/lang/Throwable;
    //   484: athrow
    //   485: astore 32
    //   487: aload 32
    //   489: invokevirtual 148	java/lang/reflect/InvocationTargetException:getCause	()Ljava/lang/Throwable;
    //   492: athrow
    //   493: astore 14
    //   495: aload 14
    //   497: invokevirtual 148	java/lang/reflect/InvocationTargetException:getCause	()Ljava/lang/Throwable;
    //   500: athrow
    //   501: astore 18
    //   503: aload 18
    //   505: invokevirtual 148	java/lang/reflect/InvocationTargetException:getCause	()Ljava/lang/Throwable;
    //   508: athrow
    // Local variable table:
    //   start	length	slot	name	signature
    //   0	509	0	this	mmmqqm
    //   229	7	2	localMethod1	java.lang.reflect.Method
    //   234	4	3	arrayOfObject1	Object[]
    //   461	3	4	localInvocationTargetException1	java.lang.reflect.InvocationTargetException
    //   241	3	5	localObject1	Object
    //   255	50	6	i	int
    //   276	9	7	localMethod2	java.lang.reflect.Method
    //   282	6	8	arrayOfObject2	Object[]
    //   469	3	9	localInvocationTargetException2	java.lang.reflect.InvocationTargetException
    //   292	5	10	localObject2	Object
    //   413	11	11	j	int
    //   334	9	12	localMethod3	java.lang.reflect.Method
    //   340	6	13	arrayOfObject3	Object[]
    //   493	3	14	localInvocationTargetException3	java.lang.reflect.InvocationTargetException
    //   350	3	15	localObject3	Object
    //   381	9	16	localMethod4	java.lang.reflect.Method
    //   387	6	17	arrayOfObject4	Object[]
    //   501	3	18	localInvocationTargetException4	java.lang.reflect.InvocationTargetException
    //   397	3	19	localObject4	Object
    //   143	1	20	localException	Exception
    //   167	9	21	localMethod5	java.lang.reflect.Method
    //   173	6	22	arrayOfObject5	Object[]
    //   198	3	23	localInvocationTargetException5	java.lang.reflect.InvocationTargetException
    //   183	3	24	localObject5	Object
    //   15	52	25	k	int
    //   35	9	26	localMethod6	java.lang.reflect.Method
    //   41	6	27	arrayOfObject6	Object[]
    //   477	3	28	localInvocationTargetException6	java.lang.reflect.InvocationTargetException
    //   51	7	29	localObject6	Object
    //   107	9	30	localMethod7	java.lang.reflect.Method
    //   113	6	31	arrayOfObject7	Object[]
    //   485	3	32	localInvocationTargetException7	java.lang.reflect.InvocationTargetException
    //   123	3	33	localObject7	Object
    // Exception table:
    //   from	to	target	type
    //   206	210	143	java/lang/Exception
    //   175	185	198	java/lang/reflect/InvocationTargetException
    //   235	243	461	java/lang/reflect/InvocationTargetException
    //   284	294	469	java/lang/reflect/InvocationTargetException
    //   43	53	477	java/lang/reflect/InvocationTargetException
    //   115	125	485	java/lang/reflect/InvocationTargetException
    //   342	352	493	java/lang/reflect/InvocationTargetException
    //   389	399	501	java/lang/reflect/InvocationTargetException
  }
  
  /* Error */
  public void bu007500750075uu0075uu0075(qqmqqm.qmmqqm paramQmmqqm)
  {
    // Byte code:
    //   0: getstatic 73	uuuuuu/mmmqqm:b0076vvvv0076v0076v	I
    //   3: getstatic 75	uuuuuu/mmmqqm:b00760076vvv0076v0076v	I
    //   6: iadd
    //   7: getstatic 73	uuuuuu/mmmqqm:b0076vvvv0076v0076v	I
    //   10: imul
    //   11: getstatic 77	uuuuuu/mmmqqm:bvv0076vv0076v0076v	I
    //   14: irem
    //   15: getstatic 79	uuuuuu/mmmqqm:bv0076vvv0076v0076v	I
    //   18: if_icmpeq +55 -> 73
    //   21: ldc 2
    //   23: ldc_w 404
    //   26: bipush 109
    //   28: iconst_4
    //   29: invokestatic 91	xxxxxx/uxxxxx:bb00620062bb0062b0062b0062	(Ljava/lang/String;CC)Ljava/lang/String;
    //   32: iconst_0
    //   33: anewarray 93	java/lang/Class
    //   36: invokevirtual 97	java/lang/Class:getMethod	(Ljava/lang/String;[Ljava/lang/Class;)Ljava/lang/reflect/Method;
    //   39: astore 35
    //   41: iconst_0
    //   42: anewarray 99	java/lang/Object
    //   45: astore 36
    //   47: aload 35
    //   49: aconst_null
    //   50: aload 36
    //   52: invokevirtual 105	java/lang/reflect/Method:invoke	(Ljava/lang/Object;[Ljava/lang/Object;)Ljava/lang/Object;
    //   55: astore 38
    //   57: aload 38
    //   59: checkcast 107	java/lang/Integer
    //   62: invokevirtual 110	java/lang/Integer:intValue	()I
    //   65: putstatic 73	uuuuuu/mmmqqm:b0076vvvv0076v0076v	I
    //   68: bipush 47
    //   70: putstatic 79	uuuuuu/mmmqqm:bv0076vvv0076v0076v	I
    //   73: aload_0
    //   74: aload_1
    //   75: invokespecial 406	uuuuuu/ssssst:ba0061a0061a0061a0061aa	(Luuuuuu/ttssst$tsssst;)V
    //   78: aload_0
    //   79: getfield 223	uuuuuu/mmmqqm:b00760076007600760076vv0076v	Lcom/db/pwcc/dbmobile/multi_bank_aggregator/model/CreateMbaSynchronizationResponse;
    //   82: ifnull +352 -> 434
    //   85: aload_0
    //   86: getfield 223	uuuuuu/mmmqqm:b00760076007600760076vv0076v	Lcom/db/pwcc/dbmobile/multi_bank_aggregator/model/CreateMbaSynchronizationResponse;
    //   89: astore 8
    //   91: ldc 2
    //   93: ldc_w 408
    //   96: sipush 152
    //   99: iconst_4
    //   100: invokestatic 91	xxxxxx/uxxxxx:bb00620062bb0062b0062b0062	(Ljava/lang/String;CC)Ljava/lang/String;
    //   103: iconst_1
    //   104: anewarray 93	java/lang/Class
    //   107: dup
    //   108: iconst_0
    //   109: ldc -24
    //   111: aastore
    //   112: invokevirtual 97	java/lang/Class:getMethod	(Ljava/lang/String;[Ljava/lang/Class;)Ljava/lang/reflect/Method;
    //   115: astore 9
    //   117: iconst_1
    //   118: anewarray 99	java/lang/Object
    //   121: dup
    //   122: iconst_0
    //   123: aload 8
    //   125: aastore
    //   126: astore 10
    //   128: aload 9
    //   130: aload_0
    //   131: aload 10
    //   133: invokevirtual 105	java/lang/reflect/Method:invoke	(Ljava/lang/Object;[Ljava/lang/Object;)Ljava/lang/Object;
    //   136: pop
    //   137: ldc 2
    //   139: ldc_w 410
    //   142: bipush 104
    //   144: iconst_3
    //   145: invokestatic 91	xxxxxx/uxxxxx:bb00620062bb0062b0062b0062	(Ljava/lang/String;CC)Ljava/lang/String;
    //   148: iconst_0
    //   149: anewarray 93	java/lang/Class
    //   152: invokevirtual 97	java/lang/Class:getMethod	(Ljava/lang/String;[Ljava/lang/Class;)Ljava/lang/reflect/Method;
    //   155: astore 13
    //   157: iconst_0
    //   158: anewarray 99	java/lang/Object
    //   161: astore 14
    //   163: aload 13
    //   165: aconst_null
    //   166: aload 14
    //   168: invokevirtual 105	java/lang/reflect/Method:invoke	(Ljava/lang/Object;[Ljava/lang/Object;)Ljava/lang/Object;
    //   171: astore 16
    //   173: aload 16
    //   175: checkcast 107	java/lang/Integer
    //   178: invokevirtual 110	java/lang/Integer:intValue	()I
    //   181: getstatic 75	uuuuuu/mmmqqm:b00760076vvv0076v0076v	I
    //   184: iadd
    //   185: istore 17
    //   187: ldc 2
    //   189: ldc_w 412
    //   192: bipush 33
    //   194: iconst_0
    //   195: invokestatic 91	xxxxxx/uxxxxx:bb00620062bb0062b0062b0062	(Ljava/lang/String;CC)Ljava/lang/String;
    //   198: iconst_0
    //   199: anewarray 93	java/lang/Class
    //   202: invokevirtual 97	java/lang/Class:getMethod	(Ljava/lang/String;[Ljava/lang/Class;)Ljava/lang/reflect/Method;
    //   205: astore 18
    //   207: iconst_0
    //   208: anewarray 99	java/lang/Object
    //   211: astore 19
    //   213: aload 18
    //   215: aconst_null
    //   216: aload 19
    //   218: invokevirtual 105	java/lang/reflect/Method:invoke	(Ljava/lang/Object;[Ljava/lang/Object;)Ljava/lang/Object;
    //   221: astore 21
    //   223: iload 17
    //   225: aload 21
    //   227: checkcast 107	java/lang/Integer
    //   230: invokevirtual 110	java/lang/Integer:intValue	()I
    //   233: imul
    //   234: getstatic 77	uuuuuu/mmmqqm:bvv0076vv0076v0076v	I
    //   237: irem
    //   238: getstatic 79	uuuuuu/mmmqqm:bv0076vvv0076v0076v	I
    //   241: if_icmpeq +55 -> 296
    //   244: bipush 11
    //   246: putstatic 73	uuuuuu/mmmqqm:b0076vvvv0076v0076v	I
    //   249: ldc 2
    //   251: ldc_w 362
    //   254: bipush 113
    //   256: iconst_2
    //   257: invokestatic 91	xxxxxx/uxxxxx:bb00620062bb0062b0062b0062	(Ljava/lang/String;CC)Ljava/lang/String;
    //   260: iconst_0
    //   261: anewarray 93	java/lang/Class
    //   264: invokevirtual 97	java/lang/Class:getMethod	(Ljava/lang/String;[Ljava/lang/Class;)Ljava/lang/reflect/Method;
    //   267: astore 31
    //   269: iconst_0
    //   270: anewarray 99	java/lang/Object
    //   273: astore 32
    //   275: aload 31
    //   277: aconst_null
    //   278: aload 32
    //   280: invokevirtual 105	java/lang/reflect/Method:invoke	(Ljava/lang/Object;[Ljava/lang/Object;)Ljava/lang/Object;
    //   283: astore 34
    //   285: aload 34
    //   287: checkcast 107	java/lang/Integer
    //   290: invokevirtual 110	java/lang/Integer:intValue	()I
    //   293: putstatic 79	uuuuuu/mmmqqm:bv0076vvv0076v0076v	I
    //   296: getstatic 73	uuuuuu/mmmqqm:b0076vvvv0076v0076v	I
    //   299: istore 22
    //   301: iload 22
    //   303: iload 22
    //   305: getstatic 75	uuuuuu/mmmqqm:b00760076vvv0076v0076v	I
    //   308: iadd
    //   309: imul
    //   310: getstatic 77	uuuuuu/mmmqqm:bvv0076vv0076v0076v	I
    //   313: irem
    //   314: tableswitch	default:+18->332, 0:+114->428
    //   332: ldc 2
    //   334: ldc_w 414
    //   337: bipush 115
    //   339: sipush 165
    //   342: iconst_0
    //   343: invokestatic 118	xxxxxx/uxxxxx:bbbb0062b0062b0062b0062	(Ljava/lang/String;CCC)Ljava/lang/String;
    //   346: iconst_0
    //   347: anewarray 93	java/lang/Class
    //   350: invokevirtual 97	java/lang/Class:getMethod	(Ljava/lang/String;[Ljava/lang/Class;)Ljava/lang/reflect/Method;
    //   353: astore 23
    //   355: iconst_0
    //   356: anewarray 99	java/lang/Object
    //   359: astore 24
    //   361: aload 23
    //   363: aconst_null
    //   364: aload 24
    //   366: invokevirtual 105	java/lang/reflect/Method:invoke	(Ljava/lang/Object;[Ljava/lang/Object;)Ljava/lang/Object;
    //   369: astore 26
    //   371: aload 26
    //   373: checkcast 107	java/lang/Integer
    //   376: invokevirtual 110	java/lang/Integer:intValue	()I
    //   379: putstatic 73	uuuuuu/mmmqqm:b0076vvvv0076v0076v	I
    //   382: ldc 2
    //   384: ldc_w 416
    //   387: iconst_3
    //   388: iconst_4
    //   389: invokestatic 91	xxxxxx/uxxxxx:bb00620062bb0062b0062b0062	(Ljava/lang/String;CC)Ljava/lang/String;
    //   392: iconst_0
    //   393: anewarray 93	java/lang/Class
    //   396: invokevirtual 97	java/lang/Class:getMethod	(Ljava/lang/String;[Ljava/lang/Class;)Ljava/lang/reflect/Method;
    //   399: astore 27
    //   401: iconst_0
    //   402: anewarray 99	java/lang/Object
    //   405: astore 28
    //   407: aload 27
    //   409: aconst_null
    //   410: aload 28
    //   412: invokevirtual 105	java/lang/reflect/Method:invoke	(Ljava/lang/Object;[Ljava/lang/Object;)Ljava/lang/Object;
    //   415: astore 30
    //   417: aload 30
    //   419: checkcast 107	java/lang/Integer
    //   422: invokevirtual 110	java/lang/Integer:intValue	()I
    //   425: putstatic 79	uuuuuu/mmmqqm:bv0076vvv0076v0076v	I
    //   428: aload_0
    //   429: aconst_null
    //   430: putfield 223	uuuuuu/mmmqqm:b00760076007600760076vv0076v	Lcom/db/pwcc/dbmobile/multi_bank_aggregator/model/CreateMbaSynchronizationResponse;
    //   433: return
    //   434: aload_0
    //   435: getfield 418	uuuuuu/mmmqqm:b00760076v00760076vv0076v	Lcom/db/pwcc/dbmobile/model/error/DbError;
    //   438: ifnull -5 -> 433
    //   441: aload_0
    //   442: getfield 418	uuuuuu/mmmqqm:b00760076v00760076vv0076v	Lcom/db/pwcc/dbmobile/model/error/DbError;
    //   445: astore_2
    //   446: ldc 2
    //   448: ldc_w 420
    //   451: bipush 122
    //   453: bipush 43
    //   455: iconst_0
    //   456: invokestatic 118	xxxxxx/uxxxxx:bbbb0062b0062b0062b0062	(Ljava/lang/String;CCC)Ljava/lang/String;
    //   459: iconst_1
    //   460: anewarray 93	java/lang/Class
    //   463: dup
    //   464: iconst_0
    //   465: ldc_w 422
    //   468: aastore
    //   469: invokevirtual 97	java/lang/Class:getMethod	(Ljava/lang/String;[Ljava/lang/Class;)Ljava/lang/reflect/Method;
    //   472: astore_3
    //   473: iconst_1
    //   474: anewarray 99	java/lang/Object
    //   477: dup
    //   478: iconst_0
    //   479: aload_2
    //   480: aastore
    //   481: astore 4
    //   483: aload_3
    //   484: aload_0
    //   485: aload 4
    //   487: invokevirtual 105	java/lang/reflect/Method:invoke	(Ljava/lang/Object;[Ljava/lang/Object;)Ljava/lang/Object;
    //   490: pop
    //   491: getstatic 73	uuuuuu/mmmqqm:b0076vvvv0076v0076v	I
    //   494: istore 7
    //   496: iload 7
    //   498: iload 7
    //   500: getstatic 75	uuuuuu/mmmqqm:b00760076vvv0076v0076v	I
    //   503: iadd
    //   504: imul
    //   505: getstatic 77	uuuuuu/mmmqqm:bvv0076vv0076v0076v	I
    //   508: irem
    //   509: tableswitch	default:+19->528, 0:+29->538
    //   528: bipush 74
    //   530: putstatic 73	uuuuuu/mmmqqm:b0076vvvv0076v0076v	I
    //   533: bipush 71
    //   535: putstatic 79	uuuuuu/mmmqqm:bv0076vvv0076v0076v	I
    //   538: aload_0
    //   539: aconst_null
    //   540: putfield 418	uuuuuu/mmmqqm:b00760076v00760076vv0076v	Lcom/db/pwcc/dbmobile/model/error/DbError;
    //   543: return
    //   544: astore 11
    //   546: aload 11
    //   548: invokevirtual 148	java/lang/reflect/InvocationTargetException:getCause	()Ljava/lang/Throwable;
    //   551: athrow
    //   552: astore 5
    //   554: aload 5
    //   556: invokevirtual 148	java/lang/reflect/InvocationTargetException:getCause	()Ljava/lang/Throwable;
    //   559: athrow
    //   560: astore 25
    //   562: aload 25
    //   564: invokevirtual 148	java/lang/reflect/InvocationTargetException:getCause	()Ljava/lang/Throwable;
    //   567: athrow
    //   568: astore 29
    //   570: aload 29
    //   572: invokevirtual 148	java/lang/reflect/InvocationTargetException:getCause	()Ljava/lang/Throwable;
    //   575: athrow
    //   576: astore 15
    //   578: aload 15
    //   580: invokevirtual 148	java/lang/reflect/InvocationTargetException:getCause	()Ljava/lang/Throwable;
    //   583: athrow
    //   584: astore 20
    //   586: aload 20
    //   588: invokevirtual 148	java/lang/reflect/InvocationTargetException:getCause	()Ljava/lang/Throwable;
    //   591: athrow
    //   592: astore 37
    //   594: aload 37
    //   596: invokevirtual 148	java/lang/reflect/InvocationTargetException:getCause	()Ljava/lang/Throwable;
    //   599: athrow
    //   600: astore 33
    //   602: aload 33
    //   604: invokevirtual 148	java/lang/reflect/InvocationTargetException:getCause	()Ljava/lang/Throwable;
    //   607: athrow
    // Local variable table:
    //   start	length	slot	name	signature
    //   0	608	0	this	mmmqqm
    //   0	608	1	paramQmmqqm	qqmqqm.qmmqqm
    //   445	35	2	localDbError	DbError
    //   472	12	3	localMethod1	java.lang.reflect.Method
    //   481	5	4	arrayOfObject1	Object[]
    //   552	3	5	localInvocationTargetException1	java.lang.reflect.InvocationTargetException
    //   494	11	7	i	int
    //   89	35	8	localCreateMbaSynchronizationResponse	CreateMbaSynchronizationResponse
    //   115	14	9	localMethod2	java.lang.reflect.Method
    //   126	6	10	arrayOfObject2	Object[]
    //   544	3	11	localInvocationTargetException2	java.lang.reflect.InvocationTargetException
    //   155	9	13	localMethod3	java.lang.reflect.Method
    //   161	6	14	arrayOfObject3	Object[]
    //   576	3	15	localInvocationTargetException3	java.lang.reflect.InvocationTargetException
    //   171	3	16	localObject1	Object
    //   185	49	17	j	int
    //   205	9	18	localMethod4	java.lang.reflect.Method
    //   211	6	19	arrayOfObject4	Object[]
    //   584	3	20	localInvocationTargetException4	java.lang.reflect.InvocationTargetException
    //   221	5	21	localObject2	Object
    //   299	11	22	k	int
    //   353	9	23	localMethod5	java.lang.reflect.Method
    //   359	6	24	arrayOfObject5	Object[]
    //   560	3	25	localInvocationTargetException5	java.lang.reflect.InvocationTargetException
    //   369	3	26	localObject3	Object
    //   399	9	27	localMethod6	java.lang.reflect.Method
    //   405	6	28	arrayOfObject6	Object[]
    //   568	3	29	localInvocationTargetException6	java.lang.reflect.InvocationTargetException
    //   415	3	30	localObject4	Object
    //   267	9	31	localMethod7	java.lang.reflect.Method
    //   273	6	32	arrayOfObject7	Object[]
    //   600	3	33	localInvocationTargetException7	java.lang.reflect.InvocationTargetException
    //   283	3	34	localObject5	Object
    //   39	9	35	localMethod8	java.lang.reflect.Method
    //   45	6	36	arrayOfObject8	Object[]
    //   592	3	37	localInvocationTargetException8	java.lang.reflect.InvocationTargetException
    //   55	3	38	localObject6	Object
    // Exception table:
    //   from	to	target	type
    //   128	137	544	java/lang/reflect/InvocationTargetException
    //   483	491	552	java/lang/reflect/InvocationTargetException
    //   361	371	560	java/lang/reflect/InvocationTargetException
    //   407	417	568	java/lang/reflect/InvocationTargetException
    //   163	173	576	java/lang/reflect/InvocationTargetException
    //   213	223	584	java/lang/reflect/InvocationTargetException
    //   47	57	592	java/lang/reflect/InvocationTargetException
    //   275	285	600	java/lang/reflect/InvocationTargetException
  }
  
  /* Error */
  public void bu0075u0075uu0075uu0075()
  {
    // Byte code:
    //   0: new 425	com/db/pwcc/dbmobile/multi_bank_aggregator/model/MbaInstituteLoginRequest
    //   3: dup
    //   4: invokespecial 426	com/db/pwcc/dbmobile/multi_bank_aggregator/model/MbaInstituteLoginRequest:<init>	()V
    //   7: astore_1
    //   8: aload_0
    //   9: getfield 63	uuuuuu/mmmqqm:bvvvvv0076v0076v	Ljava/util/List;
    //   12: astore_2
    //   13: getstatic 73	uuuuuu/mmmqqm:b0076vvvv0076v0076v	I
    //   16: getstatic 75	uuuuuu/mmmqqm:b00760076vvv0076v0076v	I
    //   19: iadd
    //   20: getstatic 73	uuuuuu/mmmqqm:b0076vvvv0076v0076v	I
    //   23: imul
    //   24: getstatic 77	uuuuuu/mmmqqm:bvv0076vv0076v0076v	I
    //   27: irem
    //   28: getstatic 79	uuuuuu/mmmqqm:bv0076vvv0076v0076v	I
    //   31: if_icmpeq +13 -> 44
    //   34: bipush 94
    //   36: putstatic 73	uuuuuu/mmmqqm:b0076vvvv0076v0076v	I
    //   39: bipush 80
    //   41: putstatic 79	uuuuuu/mmmqqm:bv0076vvv0076v0076v	I
    //   44: aload_0
    //   45: getfield 63	uuuuuu/mmmqqm:bvvvvv0076v0076v	Ljava/util/List;
    //   48: invokeinterface 429 1 0
    //   53: istore_3
    //   54: getstatic 73	uuuuuu/mmmqqm:b0076vvvv0076v0076v	I
    //   57: getstatic 75	uuuuuu/mmmqqm:b00760076vvv0076v0076v	I
    //   60: iadd
    //   61: getstatic 73	uuuuuu/mmmqqm:b0076vvvv0076v0076v	I
    //   64: imul
    //   65: istore 4
    //   67: ldc 2
    //   69: ldc_w 431
    //   72: bipush 127
    //   74: iconst_0
    //   75: invokestatic 91	xxxxxx/uxxxxx:bb00620062bb0062b0062b0062	(Ljava/lang/String;CC)Ljava/lang/String;
    //   78: iconst_0
    //   79: anewarray 93	java/lang/Class
    //   82: invokevirtual 97	java/lang/Class:getMethod	(Ljava/lang/String;[Ljava/lang/Class;)Ljava/lang/reflect/Method;
    //   85: astore 5
    //   87: iconst_0
    //   88: anewarray 99	java/lang/Object
    //   91: astore 6
    //   93: aload 5
    //   95: aconst_null
    //   96: aload 6
    //   98: invokevirtual 105	java/lang/reflect/Method:invoke	(Ljava/lang/Object;[Ljava/lang/Object;)Ljava/lang/Object;
    //   101: astore 8
    //   103: iload 4
    //   105: aload 8
    //   107: checkcast 107	java/lang/Integer
    //   110: invokevirtual 110	java/lang/Integer:intValue	()I
    //   113: irem
    //   114: getstatic 79	uuuuuu/mmmqqm:bv0076vvv0076v0076v	I
    //   117: if_icmpeq +130 -> 247
    //   120: getstatic 73	uuuuuu/mmmqqm:b0076vvvv0076v0076v	I
    //   123: getstatic 75	uuuuuu/mmmqqm:b00760076vvv0076v0076v	I
    //   126: iadd
    //   127: getstatic 73	uuuuuu/mmmqqm:b0076vvvv0076v0076v	I
    //   130: imul
    //   131: getstatic 77	uuuuuu/mmmqqm:bvv0076vv0076v0076v	I
    //   134: irem
    //   135: getstatic 79	uuuuuu/mmmqqm:bv0076vvv0076v0076v	I
    //   138: if_icmpeq +99 -> 237
    //   141: ldc 2
    //   143: ldc_w 433
    //   146: sipush 145
    //   149: iconst_5
    //   150: invokestatic 91	xxxxxx/uxxxxx:bb00620062bb0062b0062b0062	(Ljava/lang/String;CC)Ljava/lang/String;
    //   153: iconst_0
    //   154: anewarray 93	java/lang/Class
    //   157: invokevirtual 97	java/lang/Class:getMethod	(Ljava/lang/String;[Ljava/lang/Class;)Ljava/lang/reflect/Method;
    //   160: astore 10
    //   162: iconst_0
    //   163: anewarray 99	java/lang/Object
    //   166: astore 11
    //   168: aload 10
    //   170: aconst_null
    //   171: aload 11
    //   173: invokevirtual 105	java/lang/reflect/Method:invoke	(Ljava/lang/Object;[Ljava/lang/Object;)Ljava/lang/Object;
    //   176: astore 13
    //   178: aload 13
    //   180: checkcast 107	java/lang/Integer
    //   183: invokevirtual 110	java/lang/Integer:intValue	()I
    //   186: putstatic 73	uuuuuu/mmmqqm:b0076vvvv0076v0076v	I
    //   189: ldc 2
    //   191: ldc_w 435
    //   194: sipush 227
    //   197: iconst_3
    //   198: invokestatic 91	xxxxxx/uxxxxx:bb00620062bb0062b0062b0062	(Ljava/lang/String;CC)Ljava/lang/String;
    //   201: iconst_0
    //   202: anewarray 93	java/lang/Class
    //   205: invokevirtual 97	java/lang/Class:getMethod	(Ljava/lang/String;[Ljava/lang/Class;)Ljava/lang/reflect/Method;
    //   208: astore 14
    //   210: iconst_0
    //   211: anewarray 99	java/lang/Object
    //   214: astore 15
    //   216: aload 14
    //   218: aconst_null
    //   219: aload 15
    //   221: invokevirtual 105	java/lang/reflect/Method:invoke	(Ljava/lang/Object;[Ljava/lang/Object;)Ljava/lang/Object;
    //   224: astore 17
    //   226: aload 17
    //   228: checkcast 107	java/lang/Integer
    //   231: invokevirtual 110	java/lang/Integer:intValue	()I
    //   234: putstatic 79	uuuuuu/mmmqqm:bv0076vvv0076v0076v	I
    //   237: bipush 44
    //   239: putstatic 73	uuuuuu/mmmqqm:b0076vvvv0076v0076v	I
    //   242: bipush 31
    //   244: putstatic 79	uuuuuu/mmmqqm:bv0076vvv0076v0076v	I
    //   247: aload_2
    //   248: iload_3
    //   249: anewarray 132	java/lang/String
    //   252: invokeinterface 439 2 0
    //   257: checkcast 441	[Ljava/lang/String;
    //   260: astore 9
    //   262: getstatic 73	uuuuuu/mmmqqm:b0076vvvv0076v0076v	I
    //   265: getstatic 75	uuuuuu/mmmqqm:b00760076vvv0076v0076v	I
    //   268: iadd
    //   269: getstatic 73	uuuuuu/mmmqqm:b0076vvvv0076v0076v	I
    //   272: imul
    //   273: getstatic 77	uuuuuu/mmmqqm:bvv0076vv0076v0076v	I
    //   276: irem
    //   277: getstatic 79	uuuuuu/mmmqqm:bv0076vvv0076v0076v	I
    //   280: if_icmpeq +13 -> 293
    //   283: bipush 48
    //   285: putstatic 73	uuuuuu/mmmqqm:b0076vvvv0076v0076v	I
    //   288: bipush 27
    //   290: putstatic 79	uuuuuu/mmmqqm:bv0076vvv0076v0076v	I
    //   293: aload_1
    //   294: aload 9
    //   296: invokevirtual 445	com/db/pwcc/dbmobile/multi_bank_aggregator/model/MbaInstituteLoginRequest:setAccountIds	([Ljava/lang/String;)V
    //   299: aload_0
    //   300: getfield 194	uuuuuu/mmmqqm:bnnnnn006E006E006En	Luuuuuu/ttssst$tsssst;
    //   303: checkcast 196	uuuuuu/qqmqqm$qmmqqm
    //   306: getstatic 448	uuuuuu/kvkvvv:b0066f0066f0066f006600660066	Luuuuuu/kvkvvv;
    //   309: invokeinterface 206 2 0
    //   314: aload_0
    //   315: getfield 194	uuuuuu/mmmqqm:bnnnnn006E006E006En	Luuuuuu/ttssst$tsssst;
    //   318: checkcast 196	uuuuuu/qqmqqm$qmmqqm
    //   321: iconst_0
    //   322: invokeinterface 451 2 0
    //   327: aload_0
    //   328: getfield 339	uuuuuu/mmmqqm:b0076v007600760076vv0076v	Luuuuuu/ossooo;
    //   331: aload_0
    //   332: aload_0
    //   333: getfield 455	uuuuuu/mmmqqm:b006E006E006E006E006En006E006En	Luuuuuu/hyhyhh;
    //   336: invokevirtual 460	uuuuuu/hyhyhh:b0070pp007000700070p007000700070	()Ljava/lang/String;
    //   339: aload_1
    //   340: invokevirtual 464	uuuuuu/ossooo:buu00750075u00750075007500750075	(Luuuuuu/alllal$lallal;Ljava/lang/String;Lcom/db/pwcc/dbmobile/multi_bank_aggregator/model/MbaInstituteLoginRequest;)V
    //   343: getstatic 467	uuuuuu/vvrvrv:b0068hhh0068hh00680068	Luuuuuu/vvrvrv;
    //   346: invokestatic 144	uuuuuu/rrvvrv:b0071q0071qq0071q0071q0071	(Luuuuuu/vvrvrv;)V
    //   349: return
    //   350: astore 7
    //   352: aload 7
    //   354: invokevirtual 148	java/lang/reflect/InvocationTargetException:getCause	()Ljava/lang/Throwable;
    //   357: athrow
    //   358: astore 12
    //   360: aload 12
    //   362: invokevirtual 148	java/lang/reflect/InvocationTargetException:getCause	()Ljava/lang/Throwable;
    //   365: athrow
    //   366: astore 16
    //   368: aload 16
    //   370: invokevirtual 148	java/lang/reflect/InvocationTargetException:getCause	()Ljava/lang/Throwable;
    //   373: athrow
    // Local variable table:
    //   start	length	slot	name	signature
    //   0	374	0	this	mmmqqm
    //   7	333	1	localMbaInstituteLoginRequest	com.db.pwcc.dbmobile.multi_bank_aggregator.model.MbaInstituteLoginRequest
    //   12	236	2	localList	List
    //   53	196	3	i	int
    //   65	49	4	j	int
    //   85	9	5	localMethod1	java.lang.reflect.Method
    //   91	6	6	arrayOfObject1	Object[]
    //   350	3	7	localInvocationTargetException1	java.lang.reflect.InvocationTargetException
    //   101	5	8	localObject1	Object
    //   260	35	9	arrayOfString	String[]
    //   160	9	10	localMethod2	java.lang.reflect.Method
    //   166	6	11	arrayOfObject2	Object[]
    //   358	3	12	localInvocationTargetException2	java.lang.reflect.InvocationTargetException
    //   176	3	13	localObject2	Object
    //   208	9	14	localMethod3	java.lang.reflect.Method
    //   214	6	15	arrayOfObject3	Object[]
    //   366	3	16	localInvocationTargetException3	java.lang.reflect.InvocationTargetException
    //   224	3	17	localObject3	Object
    // Exception table:
    //   from	to	target	type
    //   93	103	350	java/lang/reflect/InvocationTargetException
    //   168	178	358	java/lang/reflect/InvocationTargetException
    //   216	226	366	java/lang/reflect/InvocationTargetException
  }
  
  /* Error */
  public void bu0075uu0075u0075uu0075(DbError paramDbError)
  {
    // Byte code:
    //   0: getstatic 73	uuuuuu/mmmqqm:b0076vvvv0076v0076v	I
    //   3: istore_2
    //   4: ldc 2
    //   6: ldc_w 471
    //   9: sipush 221
    //   12: sipush 255
    //   15: iconst_0
    //   16: invokestatic 118	xxxxxx/uxxxxx:bbbb0062b0062b0062b0062	(Ljava/lang/String;CCC)Ljava/lang/String;
    //   19: iconst_0
    //   20: anewarray 93	java/lang/Class
    //   23: invokevirtual 97	java/lang/Class:getMethod	(Ljava/lang/String;[Ljava/lang/Class;)Ljava/lang/reflect/Method;
    //   26: astore_3
    //   27: iconst_0
    //   28: anewarray 99	java/lang/Object
    //   31: astore 4
    //   33: aload_3
    //   34: aconst_null
    //   35: aload 4
    //   37: invokevirtual 105	java/lang/reflect/Method:invoke	(Ljava/lang/Object;[Ljava/lang/Object;)Ljava/lang/Object;
    //   40: astore 6
    //   42: iload_2
    //   43: iload_2
    //   44: aload 6
    //   46: checkcast 107	java/lang/Integer
    //   49: invokevirtual 110	java/lang/Integer:intValue	()I
    //   52: iadd
    //   53: imul
    //   54: istore 7
    //   56: ldc 2
    //   58: ldc_w 473
    //   61: sipush 202
    //   64: iconst_1
    //   65: invokestatic 91	xxxxxx/uxxxxx:bb00620062bb0062b0062b0062	(Ljava/lang/String;CC)Ljava/lang/String;
    //   68: iconst_0
    //   69: anewarray 93	java/lang/Class
    //   72: invokevirtual 97	java/lang/Class:getMethod	(Ljava/lang/String;[Ljava/lang/Class;)Ljava/lang/reflect/Method;
    //   75: astore 8
    //   77: iconst_0
    //   78: anewarray 99	java/lang/Object
    //   81: astore 9
    //   83: aload 8
    //   85: aconst_null
    //   86: aload 9
    //   88: invokevirtual 105	java/lang/reflect/Method:invoke	(Ljava/lang/Object;[Ljava/lang/Object;)Ljava/lang/Object;
    //   91: astore 11
    //   93: iload 7
    //   95: aload 11
    //   97: checkcast 107	java/lang/Integer
    //   100: invokevirtual 110	java/lang/Integer:intValue	()I
    //   103: irem
    //   104: tableswitch	default:+20->124, 0:+293->397
    //   124: ldc 2
    //   126: ldc_w 475
    //   129: bipush 118
    //   131: sipush 142
    //   134: iconst_1
    //   135: invokestatic 118	xxxxxx/uxxxxx:bbbb0062b0062b0062b0062	(Ljava/lang/String;CCC)Ljava/lang/String;
    //   138: iconst_0
    //   139: anewarray 93	java/lang/Class
    //   142: invokevirtual 97	java/lang/Class:getMethod	(Ljava/lang/String;[Ljava/lang/Class;)Ljava/lang/reflect/Method;
    //   145: astore 12
    //   147: iconst_0
    //   148: anewarray 99	java/lang/Object
    //   151: astore 13
    //   153: aload 12
    //   155: aconst_null
    //   156: aload 13
    //   158: invokevirtual 105	java/lang/reflect/Method:invoke	(Ljava/lang/Object;[Ljava/lang/Object;)Ljava/lang/Object;
    //   161: astore 15
    //   163: aload 15
    //   165: checkcast 107	java/lang/Integer
    //   168: invokevirtual 110	java/lang/Integer:intValue	()I
    //   171: putstatic 73	uuuuuu/mmmqqm:b0076vvvv0076v0076v	I
    //   174: ldc 2
    //   176: ldc_w 477
    //   179: bipush 38
    //   181: sipush 241
    //   184: iconst_1
    //   185: invokestatic 118	xxxxxx/uxxxxx:bbbb0062b0062b0062b0062	(Ljava/lang/String;CCC)Ljava/lang/String;
    //   188: iconst_0
    //   189: anewarray 93	java/lang/Class
    //   192: invokevirtual 97	java/lang/Class:getMethod	(Ljava/lang/String;[Ljava/lang/Class;)Ljava/lang/reflect/Method;
    //   195: astore 16
    //   197: iconst_0
    //   198: anewarray 99	java/lang/Object
    //   201: astore 17
    //   203: aload 16
    //   205: aconst_null
    //   206: aload 17
    //   208: invokevirtual 105	java/lang/reflect/Method:invoke	(Ljava/lang/Object;[Ljava/lang/Object;)Ljava/lang/Object;
    //   211: astore 19
    //   213: aload 19
    //   215: checkcast 107	java/lang/Integer
    //   218: invokevirtual 110	java/lang/Integer:intValue	()I
    //   221: putstatic 79	uuuuuu/mmmqqm:bv0076vvv0076v0076v	I
    //   224: getstatic 73	uuuuuu/mmmqqm:b0076vvvv0076v0076v	I
    //   227: istore 20
    //   229: iload 20
    //   231: iload 20
    //   233: getstatic 75	uuuuuu/mmmqqm:b00760076vvv0076v0076v	I
    //   236: iadd
    //   237: imul
    //   238: getstatic 77	uuuuuu/mmmqqm:bvv0076vv0076v0076v	I
    //   241: irem
    //   242: tableswitch	default:+18->260, 0:+155->397
    //   260: bipush 50
    //   262: putstatic 73	uuuuuu/mmmqqm:b0076vvvv0076v0076v	I
    //   265: bipush 24
    //   267: putstatic 79	uuuuuu/mmmqqm:bv0076vvv0076v0076v	I
    //   270: getstatic 73	uuuuuu/mmmqqm:b0076vvvv0076v0076v	I
    //   273: getstatic 75	uuuuuu/mmmqqm:b00760076vvv0076v0076v	I
    //   276: iadd
    //   277: istore 21
    //   279: getstatic 73	uuuuuu/mmmqqm:b0076vvvv0076v0076v	I
    //   282: istore 22
    //   284: iload 22
    //   286: iload 22
    //   288: getstatic 75	uuuuuu/mmmqqm:b00760076vvv0076v0076v	I
    //   291: iadd
    //   292: imul
    //   293: getstatic 77	uuuuuu/mmmqqm:bvv0076vv0076v0076v	I
    //   296: irem
    //   297: tableswitch	default:+19->316, 0:+74->371
    //   316: ldc 2
    //   318: ldc_w 479
    //   321: sipush 191
    //   324: bipush 32
    //   326: iconst_3
    //   327: invokestatic 118	xxxxxx/uxxxxx:bbbb0062b0062b0062b0062	(Ljava/lang/String;CCC)Ljava/lang/String;
    //   330: iconst_0
    //   331: anewarray 93	java/lang/Class
    //   334: invokevirtual 97	java/lang/Class:getMethod	(Ljava/lang/String;[Ljava/lang/Class;)Ljava/lang/reflect/Method;
    //   337: astore 23
    //   339: iconst_0
    //   340: anewarray 99	java/lang/Object
    //   343: astore 24
    //   345: aload 23
    //   347: aconst_null
    //   348: aload 24
    //   350: invokevirtual 105	java/lang/reflect/Method:invoke	(Ljava/lang/Object;[Ljava/lang/Object;)Ljava/lang/Object;
    //   353: astore 26
    //   355: aload 26
    //   357: checkcast 107	java/lang/Integer
    //   360: invokevirtual 110	java/lang/Integer:intValue	()I
    //   363: putstatic 73	uuuuuu/mmmqqm:b0076vvvv0076v0076v	I
    //   366: bipush 82
    //   368: putstatic 79	uuuuuu/mmmqqm:bv0076vvv0076v0076v	I
    //   371: iload 21
    //   373: getstatic 73	uuuuuu/mmmqqm:b0076vvvv0076v0076v	I
    //   376: imul
    //   377: getstatic 77	uuuuuu/mmmqqm:bvv0076vv0076v0076v	I
    //   380: irem
    //   381: getstatic 79	uuuuuu/mmmqqm:bv0076vvv0076v0076v	I
    //   384: if_icmpeq +13 -> 397
    //   387: bipush 73
    //   389: putstatic 73	uuuuuu/mmmqqm:b0076vvvv0076v0076v	I
    //   392: bipush 49
    //   394: putstatic 79	uuuuuu/mmmqqm:bv0076vvv0076v0076v	I
    //   397: aload_0
    //   398: invokevirtual 221	uuuuuu/mmmqqm:bkk006Bk006Bk006Bk006Bk	()Z
    //   401: ifne +9 -> 410
    //   404: aload_0
    //   405: aload_1
    //   406: putfield 418	uuuuuu/mmmqqm:b00760076v00760076vv0076v	Lcom/db/pwcc/dbmobile/model/error/DbError;
    //   409: return
    //   410: aload_1
    //   411: invokevirtual 483	com/db/pwcc/dbmobile/model/error/DbError:getDbCode	()Lcom/db/pwcc/dbmobile/model/error/DbErrorCode;
    //   414: getstatic 489	com/db/pwcc/dbmobile/model/error/DbErrorCode:NO_INTERNET_ERROR	Lcom/db/pwcc/dbmobile/model/error/DbErrorCode;
    //   417: if_acmpne +50 -> 467
    //   420: aload_0
    //   421: getfield 194	uuuuuu/mmmqqm:bnnnnn006E006E006En	Luuuuuu/ttssst$tsssst;
    //   424: checkcast 196	uuuuuu/qqmqqm$qmmqqm
    //   427: getstatic 492	com/db/pwcc/dbmobile/multi_bank_aggregator/R$string:no_internet	I
    //   430: getstatic 495	com/db/pwcc/dbmobile/multi_bank_aggregator/R$string:check_internet_connection	I
    //   433: invokeinterface 498 3 0
    //   438: aload_0
    //   439: getfield 194	uuuuuu/mmmqqm:bnnnnn006E006E006En	Luuuuuu/ttssst$tsssst;
    //   442: checkcast 196	uuuuuu/qqmqqm$qmmqqm
    //   445: getstatic 202	uuuuuu/kvkvvv:bf00660066f0066f006600660066	Luuuuuu/kvkvvv;
    //   448: invokeinterface 206 2 0
    //   453: aload_0
    //   454: getfield 194	uuuuuu/mmmqqm:bnnnnn006E006E006En	Luuuuuu/ttssst$tsssst;
    //   457: checkcast 196	uuuuuu/qqmqqm$qmmqqm
    //   460: iconst_1
    //   461: invokeinterface 451 2 0
    //   466: return
    //   467: aload_0
    //   468: getfield 194	uuuuuu/mmmqqm:bnnnnn006E006E006En	Luuuuuu/ttssst$tsssst;
    //   471: checkcast 196	uuuuuu/qqmqqm$qmmqqm
    //   474: getstatic 322	com/db/pwcc/dbmobile/multi_bank_aggregator/R$string:technical_error_retry	I
    //   477: invokeinterface 326 2 0
    //   482: goto -44 -> 438
    //   485: astore 5
    //   487: aload 5
    //   489: invokevirtual 148	java/lang/reflect/InvocationTargetException:getCause	()Ljava/lang/Throwable;
    //   492: athrow
    //   493: astore 10
    //   495: aload 10
    //   497: invokevirtual 148	java/lang/reflect/InvocationTargetException:getCause	()Ljava/lang/Throwable;
    //   500: athrow
    //   501: astore 14
    //   503: aload 14
    //   505: invokevirtual 148	java/lang/reflect/InvocationTargetException:getCause	()Ljava/lang/Throwable;
    //   508: athrow
    //   509: astore 18
    //   511: aload 18
    //   513: invokevirtual 148	java/lang/reflect/InvocationTargetException:getCause	()Ljava/lang/Throwable;
    //   516: athrow
    //   517: astore 25
    //   519: aload 25
    //   521: invokevirtual 148	java/lang/reflect/InvocationTargetException:getCause	()Ljava/lang/Throwable;
    //   524: athrow
    // Local variable table:
    //   start	length	slot	name	signature
    //   0	525	0	this	mmmqqm
    //   0	525	1	paramDbError	DbError
    //   3	51	2	i	int
    //   26	8	3	localMethod1	java.lang.reflect.Method
    //   31	5	4	arrayOfObject1	Object[]
    //   485	3	5	localInvocationTargetException1	java.lang.reflect.InvocationTargetException
    //   40	5	6	localObject1	Object
    //   54	50	7	j	int
    //   75	9	8	localMethod2	java.lang.reflect.Method
    //   81	6	9	arrayOfObject2	Object[]
    //   493	3	10	localInvocationTargetException2	java.lang.reflect.InvocationTargetException
    //   91	5	11	localObject2	Object
    //   145	9	12	localMethod3	java.lang.reflect.Method
    //   151	6	13	arrayOfObject3	Object[]
    //   501	3	14	localInvocationTargetException3	java.lang.reflect.InvocationTargetException
    //   161	3	15	localObject3	Object
    //   195	9	16	localMethod4	java.lang.reflect.Method
    //   201	6	17	arrayOfObject4	Object[]
    //   509	3	18	localInvocationTargetException4	java.lang.reflect.InvocationTargetException
    //   211	3	19	localObject4	Object
    //   227	11	20	k	int
    //   277	100	21	m	int
    //   282	11	22	n	int
    //   337	9	23	localMethod5	java.lang.reflect.Method
    //   343	6	24	arrayOfObject5	Object[]
    //   517	3	25	localInvocationTargetException5	java.lang.reflect.InvocationTargetException
    //   353	3	26	localObject5	Object
    // Exception table:
    //   from	to	target	type
    //   33	42	485	java/lang/reflect/InvocationTargetException
    //   83	93	493	java/lang/reflect/InvocationTargetException
    //   153	163	501	java/lang/reflect/InvocationTargetException
    //   203	213	509	java/lang/reflect/InvocationTargetException
    //   345	355	517	java/lang/reflect/InvocationTargetException
  }
}
