package uuuuuu;

import android.content.Context;
import com.appdynamics.eumagent.runtime.Instrumentation;
import java.lang.reflect.InvocationTargetException;
import java.lang.reflect.Method;
import xxxxxx.uxxxxx;

public class rrvvrv
{
  public static int b00780078xxx0078xxx = 0;
  public static int b0078x0078xx0078xxx = 2;
  private static final String b0078xxxx0078xxx = rrvvrv.class.getSimpleName();
  public static int bx0078xxx0078xxx = 71;
  public static int bxx0078xx0078xxx = 1;
  private static final int bxxxxx0078xxx = 1;
  
  static
  {
    int i = bx0078xxx0078xxx;
    switch (i * (i + bxx0078xx0078xxx) % b0078x0078xx0078xxx)
    {
    default: 
      bx0078xxx0078xxx = b00710071007100710071qq0071q0071();
      b00780078xxx0078xxx = 48;
    }
    if ((bx0078xxx0078xxx + bxx0078xx0078xxx) * bx0078xxx0078xxx % b0071qqqq0071q0071q0071() != b00780078xxx0078xxx)
    {
      bx0078xxx0078xxx = 69;
      b00780078xxx0078xxx = 40;
    }
  }
  
  public rrvvrv() {}
  
  public static int b00710071007100710071qq0071q0071()
  {
    return 16;
  }
  
  public static void b007100710071qq0071q0071q0071(String paramString)
  {
    bqqq0071q0071q0071q0071(paramString, 1);
    int i = (bx0078xxx0078xxx + bxx0078xx0078xxx) * bx0078xxx0078xxx;
    if ((bx0078xxx0078xxx + bxx0078xx0078xxx) * bx0078xxx0078xxx % b0078x0078xx0078xxx != b00780078xxx0078xxx)
    {
      bx0078xxx0078xxx = b00710071007100710071qq0071q0071();
      b00780078xxx0078xxx = 34;
    }
    if (i % b0078x0078xx0078xxx != bqqqqq0071q0071q0071())
    {
      bx0078xxx0078xxx = 80;
      b00780078xxx0078xxx = b00710071007100710071qq0071q0071();
    }
  }
  
  public static void b00710071qqq0071q0071q0071(vvrvrv paramVvrvrv)
  {
    int i = (bx0078xxx0078xxx + bq0071qqq0071q0071q0071()) * bx0078xxx0078xxx % b0078x0078xx0078xxx;
    int j = bx0078xxx0078xxx;
    switch (j * (j + bq0071qqq0071q0071q0071()) % b0078x0078xx0078xxx)
    {
    default: 
      bx0078xxx0078xxx = 74;
      b00780078xxx0078xxx = b00710071007100710071qq0071q0071();
    }
    if (i != b00780078xxx0078xxx)
    {
      bx0078xxx0078xxx = 76;
      b00780078xxx0078xxx = 58;
    }
    bqq0071qq0071q0071q0071(paramVvrvrv.toString());
  }
  
  public static void b0071q0071qq0071q0071q0071(vvrvrv paramVvrvrv)
  {
    int i = b00710071007100710071qq0071q0071();
    switch (i * (i + bxx0078xx0078xxx) % b0078x0078xx0078xxx)
    {
    default: 
      bx0078xxx0078xxx = b00710071007100710071qq0071q0071();
      b00780078xxx0078xxx = 22;
    }
    if ((bx0078xxx0078xxx + bxx0078xx0078xxx) * bx0078xxx0078xxx % b0078x0078xx0078xxx != b00780078xxx0078xxx)
    {
      bx0078xxx0078xxx = b00710071007100710071qq0071q0071();
      b00780078xxx0078xxx = b00710071007100710071qq0071q0071();
    }
    bq00710071qq0071q0071q0071(paramVvrvrv, 1);
  }
  
  /* Error */
  public static void b0071qq0071q0071q0071q0071(String paramString1, String paramString2)
  {
    // Byte code:
    //   0: getstatic 26	uuuuuu/rrvvrv:b0078xxxx0078xxx	Ljava/lang/String;
    //   3: astore 10
    //   5: getstatic 28	uuuuuu/rrvvrv:bx0078xxx0078xxx	I
    //   8: getstatic 30	uuuuuu/rrvvrv:bxx0078xx0078xxx	I
    //   11: iadd
    //   12: getstatic 28	uuuuuu/rrvvrv:bx0078xxx0078xxx	I
    //   15: imul
    //   16: getstatic 32	uuuuuu/rrvvrv:b0078x0078xx0078xxx	I
    //   19: irem
    //   20: invokestatic 53	uuuuuu/rrvvrv:bqqqqq0071q0071q0071	()I
    //   23: if_icmpeq +45 -> 68
    //   26: invokestatic 36	uuuuuu/rrvvrv:b00710071007100710071qq0071q0071	()I
    //   29: putstatic 28	uuuuuu/rrvvrv:bx0078xxx0078xxx	I
    //   32: bipush 48
    //   34: putstatic 38	uuuuuu/rrvvrv:b00780078xxx0078xxx	I
    //   37: getstatic 28	uuuuuu/rrvvrv:bx0078xxx0078xxx	I
    //   40: getstatic 30	uuuuuu/rrvvrv:bxx0078xx0078xxx	I
    //   43: iadd
    //   44: getstatic 28	uuuuuu/rrvvrv:bx0078xxx0078xxx	I
    //   47: imul
    //   48: getstatic 32	uuuuuu/rrvvrv:b0078x0078xx0078xxx	I
    //   51: irem
    //   52: getstatic 38	uuuuuu/rrvvrv:b00780078xxx0078xxx	I
    //   55: if_icmpeq +13 -> 68
    //   58: iconst_1
    //   59: putstatic 28	uuuuuu/rrvvrv:bx0078xxx0078xxx	I
    //   62: invokestatic 36	uuuuuu/rrvvrv:b00710071007100710071qq0071q0071	()I
    //   65: putstatic 38	uuuuuu/rrvvrv:b00780078xxx0078xxx	I
    //   68: new 79	java/lang/StringBuilder
    //   71: dup
    //   72: invokespecial 80	java/lang/StringBuilder:<init>	()V
    //   75: astore 11
    //   77: ldc 82
    //   79: bipush 97
    //   81: iconst_3
    //   82: invokestatic 88	xxxxxx/uxxxxx:bb00620062bb0062b0062b0062	(Ljava/lang/String;CC)Ljava/lang/String;
    //   85: astore 12
    //   87: iconst_4
    //   88: anewarray 20	java/lang/Class
    //   91: astore 13
    //   93: aload 13
    //   95: iconst_0
    //   96: ldc 90
    //   98: aastore
    //   99: aload 13
    //   101: iconst_1
    //   102: getstatic 96	java/lang/Character:TYPE	Ljava/lang/Class;
    //   105: aastore
    //   106: aload 13
    //   108: iconst_2
    //   109: getstatic 96	java/lang/Character:TYPE	Ljava/lang/Class;
    //   112: aastore
    //   113: aload 13
    //   115: iconst_3
    //   116: getstatic 96	java/lang/Character:TYPE	Ljava/lang/Class;
    //   119: aastore
    //   120: ldc 98
    //   122: aload 12
    //   124: aload 13
    //   126: invokevirtual 102	java/lang/Class:getMethod	(Ljava/lang/String;[Ljava/lang/Class;)Ljava/lang/reflect/Method;
    //   129: astore 14
    //   131: iconst_4
    //   132: anewarray 4	java/lang/Object
    //   135: astore 15
    //   137: aload 15
    //   139: iconst_0
    //   140: ldc 104
    //   142: aastore
    //   143: aload 15
    //   145: iconst_1
    //   146: sipush 213
    //   149: invokestatic 108	java/lang/Character:valueOf	(C)Ljava/lang/Character;
    //   152: aastore
    //   153: aload 15
    //   155: iconst_2
    //   156: sipush 135
    //   159: invokestatic 108	java/lang/Character:valueOf	(C)Ljava/lang/Character;
    //   162: aastore
    //   163: aload 15
    //   165: iconst_3
    //   166: iconst_2
    //   167: invokestatic 108	java/lang/Character:valueOf	(C)Ljava/lang/Character;
    //   170: aastore
    //   171: aload 14
    //   173: aconst_null
    //   174: aload 15
    //   176: invokevirtual 114	java/lang/reflect/Method:invoke	(Ljava/lang/Object;[Ljava/lang/Object;)Ljava/lang/Object;
    //   179: astore 17
    //   181: aload 17
    //   183: checkcast 90	java/lang/String
    //   186: astore 18
    //   188: aload 11
    //   190: aload 18
    //   192: invokevirtual 118	java/lang/StringBuilder:append	(Ljava/lang/String;)Ljava/lang/StringBuilder;
    //   195: aload_0
    //   196: invokevirtual 118	java/lang/StringBuilder:append	(Ljava/lang/String;)Ljava/lang/StringBuilder;
    //   199: astore 19
    //   201: ldc 120
    //   203: sipush 247
    //   206: iconst_3
    //   207: invokestatic 88	xxxxxx/uxxxxx:bb00620062bb0062b0062b0062	(Ljava/lang/String;CC)Ljava/lang/String;
    //   210: astore 20
    //   212: iconst_4
    //   213: anewarray 20	java/lang/Class
    //   216: astore 21
    //   218: aload 21
    //   220: iconst_0
    //   221: ldc 90
    //   223: aastore
    //   224: aload 21
    //   226: iconst_1
    //   227: getstatic 96	java/lang/Character:TYPE	Ljava/lang/Class;
    //   230: aastore
    //   231: aload 21
    //   233: iconst_2
    //   234: getstatic 96	java/lang/Character:TYPE	Ljava/lang/Class;
    //   237: aastore
    //   238: aload 21
    //   240: iconst_3
    //   241: getstatic 96	java/lang/Character:TYPE	Ljava/lang/Class;
    //   244: aastore
    //   245: ldc 98
    //   247: aload 20
    //   249: aload 21
    //   251: invokevirtual 102	java/lang/Class:getMethod	(Ljava/lang/String;[Ljava/lang/Class;)Ljava/lang/reflect/Method;
    //   254: astore 22
    //   256: iconst_4
    //   257: anewarray 4	java/lang/Object
    //   260: astore 23
    //   262: aload 23
    //   264: iconst_0
    //   265: ldc 122
    //   267: aastore
    //   268: aload 23
    //   270: iconst_1
    //   271: bipush 51
    //   273: invokestatic 108	java/lang/Character:valueOf	(C)Ljava/lang/Character;
    //   276: aastore
    //   277: aload 23
    //   279: iconst_2
    //   280: bipush 98
    //   282: invokestatic 108	java/lang/Character:valueOf	(C)Ljava/lang/Character;
    //   285: aastore
    //   286: aload 23
    //   288: iconst_3
    //   289: iconst_3
    //   290: invokestatic 108	java/lang/Character:valueOf	(C)Ljava/lang/Character;
    //   293: aastore
    //   294: aload 22
    //   296: aconst_null
    //   297: aload 23
    //   299: invokevirtual 114	java/lang/reflect/Method:invoke	(Ljava/lang/Object;[Ljava/lang/Object;)Ljava/lang/Object;
    //   302: astore 25
    //   304: aload 25
    //   306: checkcast 90	java/lang/String
    //   309: astore 26
    //   311: aload 10
    //   313: aload 19
    //   315: aload 26
    //   317: invokevirtual 118	java/lang/StringBuilder:append	(Ljava/lang/String;)Ljava/lang/StringBuilder;
    //   320: aload_1
    //   321: invokevirtual 118	java/lang/StringBuilder:append	(Ljava/lang/String;)Ljava/lang/StringBuilder;
    //   324: invokevirtual 123	java/lang/StringBuilder:toString	()Ljava/lang/String;
    //   327: invokestatic 128	uuuuuu/rvvvrv:b007100710071q00710071q0071q0071	(Ljava/lang/String;Ljava/lang/String;)V
    //   330: aload_0
    //   331: aload_1
    //   332: iconst_0
    //   333: invokestatic 134	com/appdynamics/eumagent/runtime/Instrumentation:setUserData	(Ljava/lang/String;Ljava/lang/String;Z)V
    //   336: return
    //   337: astore 16
    //   339: aload 16
    //   341: invokevirtual 138	java/lang/reflect/InvocationTargetException:getCause	()Ljava/lang/Throwable;
    //   344: athrow
    //   345: astore_2
    //   346: getstatic 26	uuuuuu/rrvvrv:b0078xxxx0078xxx	Ljava/lang/String;
    //   349: astore_3
    //   350: ldc -116
    //   352: sipush 158
    //   355: iconst_0
    //   356: invokestatic 88	xxxxxx/uxxxxx:bb00620062bb0062b0062b0062	(Ljava/lang/String;CC)Ljava/lang/String;
    //   359: astore 4
    //   361: iconst_3
    //   362: anewarray 20	java/lang/Class
    //   365: astore 5
    //   367: aload 5
    //   369: iconst_0
    //   370: ldc 90
    //   372: aastore
    //   373: aload 5
    //   375: iconst_1
    //   376: getstatic 96	java/lang/Character:TYPE	Ljava/lang/Class;
    //   379: aastore
    //   380: aload 5
    //   382: iconst_2
    //   383: getstatic 96	java/lang/Character:TYPE	Ljava/lang/Class;
    //   386: aastore
    //   387: ldc 98
    //   389: aload 4
    //   391: aload 5
    //   393: invokevirtual 102	java/lang/Class:getMethod	(Ljava/lang/String;[Ljava/lang/Class;)Ljava/lang/reflect/Method;
    //   396: astore 6
    //   398: iconst_3
    //   399: anewarray 4	java/lang/Object
    //   402: astore 7
    //   404: aload 7
    //   406: iconst_0
    //   407: ldc -114
    //   409: aastore
    //   410: aload 7
    //   412: iconst_1
    //   413: sipush 250
    //   416: invokestatic 108	java/lang/Character:valueOf	(C)Ljava/lang/Character;
    //   419: aastore
    //   420: aload 7
    //   422: iconst_2
    //   423: iconst_4
    //   424: invokestatic 108	java/lang/Character:valueOf	(C)Ljava/lang/Character;
    //   427: aastore
    //   428: aload 6
    //   430: aconst_null
    //   431: aload 7
    //   433: invokevirtual 114	java/lang/reflect/Method:invoke	(Ljava/lang/Object;[Ljava/lang/Object;)Ljava/lang/Object;
    //   436: astore 9
    //   438: aload_3
    //   439: aload 9
    //   441: checkcast 90	java/lang/String
    //   444: aload_2
    //   445: invokestatic 146	uuuuuu/rvvvrv:b00710071qq00710071q0071q0071	(Ljava/lang/String;Ljava/lang/String;Ljava/lang/Throwable;)V
    //   448: return
    //   449: astore 8
    //   451: aload 8
    //   453: invokevirtual 138	java/lang/reflect/InvocationTargetException:getCause	()Ljava/lang/Throwable;
    //   456: athrow
    //   457: astore 24
    //   459: aload 24
    //   461: invokevirtual 138	java/lang/reflect/InvocationTargetException:getCause	()Ljava/lang/Throwable;
    //   464: athrow
    // Local variable table:
    //   start	length	slot	name	signature
    //   0	465	0	paramString1	String
    //   0	465	1	paramString2	String
    //   345	100	2	localRuntimeException	RuntimeException
    //   349	90	3	str1	String
    //   359	31	4	str2	String
    //   365	27	5	arrayOfClass1	Class[]
    //   396	33	6	localMethod1	Method
    //   402	30	7	arrayOfObject1	Object[]
    //   449	3	8	localInvocationTargetException1	InvocationTargetException
    //   436	4	9	localObject1	Object
    //   3	309	10	str3	String
    //   75	114	11	localStringBuilder1	StringBuilder
    //   85	38	12	str4	String
    //   91	34	13	arrayOfClass2	Class[]
    //   129	43	14	localMethod2	Method
    //   135	40	15	arrayOfObject2	Object[]
    //   337	3	16	localInvocationTargetException2	InvocationTargetException
    //   179	3	17	localObject2	Object
    //   186	5	18	str5	String
    //   199	115	19	localStringBuilder2	StringBuilder
    //   210	38	20	str6	String
    //   216	34	21	arrayOfClass3	Class[]
    //   254	41	22	localMethod3	Method
    //   260	38	23	arrayOfObject3	Object[]
    //   457	3	24	localInvocationTargetException3	InvocationTargetException
    //   302	3	25	localObject3	Object
    //   309	7	26	str7	String
    // Exception table:
    //   from	to	target	type
    //   171	181	337	java/lang/reflect/InvocationTargetException
    //   0	5	345	java/lang/RuntimeException
    //   68	77	345	java/lang/RuntimeException
    //   171	181	345	java/lang/RuntimeException
    //   188	201	345	java/lang/RuntimeException
    //   294	304	345	java/lang/RuntimeException
    //   311	336	345	java/lang/RuntimeException
    //   339	345	345	java/lang/RuntimeException
    //   459	465	345	java/lang/RuntimeException
    //   428	438	449	java/lang/reflect/InvocationTargetException
    //   294	304	457	java/lang/reflect/InvocationTargetException
  }
  
  public static int b0071qqqq0071q0071q0071()
  {
    return 2;
  }
  
  public static void bq00710071qq0071q0071q0071(vvrvrv paramVvrvrv, int paramInt)
  {
    if ((b00710071007100710071qq0071q0071() + bxx0078xx0078xxx) * b00710071007100710071qq0071q0071() % b0078x0078xx0078xxx != b00780078xxx0078xxx)
    {
      if ((bx0078xxx0078xxx + bxx0078xx0078xxx) * bx0078xxx0078xxx % b0078x0078xx0078xxx != bqqqqq0071q0071q0071())
      {
        bx0078xxx0078xxx = 66;
        b00780078xxx0078xxx = 5;
      }
      bx0078xxx0078xxx = 59;
      b00780078xxx0078xxx = b00710071007100710071qq0071q0071();
    }
    bqqq0071q0071q0071q0071(paramVvrvrv.toString(), paramInt);
  }
  
  public static void bq0071q0071q0071q0071q0071(String paramString, Context paramContext)
  {
    try
    {
      Instrumentation.start(paramString, paramContext);
      return;
    }
    catch (RuntimeException localRuntimeException)
    {
      for (;;)
      {
        String str1 = b0078xxxx0078xxx;
        String str2 = uxxxxx.bb00620062bb0062b0062b0062("H^_`a\033\034$%\037 ()j$%-.()12s", 'L', '\000');
        Class[] arrayOfClass = new Class[3];
        arrayOfClass[0] = String.class;
        arrayOfClass[1] = Character.TYPE;
        arrayOfClass[2] = Character.TYPE;
        Method localMethod = ppphhp.class.getMethod(str2, arrayOfClass);
        Object[] arrayOfObject = new Object[3];
        arrayOfObject[0] = "\023\027\021\033\017\006\020\f\034\002\024\b\r\013;\001z\002\004{y";
        arrayOfObject[1] = Character.valueOf('G');
        arrayOfObject[2] = Character.valueOf('\005');
        try
        {
          Object localObject = localMethod.invoke(null, arrayOfObject);
          rvvvrv.b00710071qq00710071q0071q0071(str1, (String)localObject, localRuntimeException);
          if ((b00710071007100710071qq0071q0071() + bxx0078xx0078xxx) * b00710071007100710071qq0071q0071() % b0078x0078xx0078xxx == b00780078xxx0078xxx) {
            continue;
          }
          bx0078xxx0078xxx = b00710071007100710071qq0071q0071();
          b00780078xxx0078xxx = 54;
          if ((bx0078xxx0078xxx + bq0071qqq0071q0071q0071()) * bx0078xxx0078xxx % b0078x0078xx0078xxx == b00780078xxx0078xxx) {
            continue;
          }
          bx0078xxx0078xxx = 54;
          b00780078xxx0078xxx = 60;
          return;
        }
        catch (InvocationTargetException localInvocationTargetException)
        {
          throw localInvocationTargetException.getCause();
        }
      }
    }
  }
  
  public static int bq0071qqq0071q0071q0071()
  {
    return 1;
  }
  
  /* Error */
  public static void bqq0071qq0071q0071q0071(String paramString)
  {
    // Byte code:
    //   0: getstatic 26	uuuuuu/rrvvrv:b0078xxxx0078xxx	Ljava/lang/String;
    //   3: astore 9
    //   5: new 79	java/lang/StringBuilder
    //   8: dup
    //   9: invokespecial 80	java/lang/StringBuilder:<init>	()V
    //   12: astore 10
    //   14: ldc -99
    //   16: sipush 156
    //   19: iconst_5
    //   20: invokestatic 88	xxxxxx/uxxxxx:bb00620062bb0062b0062b0062	(Ljava/lang/String;CC)Ljava/lang/String;
    //   23: astore 11
    //   25: iconst_3
    //   26: anewarray 20	java/lang/Class
    //   29: astore 12
    //   31: aload 12
    //   33: iconst_0
    //   34: ldc 90
    //   36: aastore
    //   37: aload 12
    //   39: iconst_1
    //   40: getstatic 96	java/lang/Character:TYPE	Ljava/lang/Class;
    //   43: aastore
    //   44: aload 12
    //   46: iconst_2
    //   47: getstatic 96	java/lang/Character:TYPE	Ljava/lang/Class;
    //   50: aastore
    //   51: ldc 98
    //   53: aload 11
    //   55: aload 12
    //   57: invokevirtual 102	java/lang/Class:getMethod	(Ljava/lang/String;[Ljava/lang/Class;)Ljava/lang/reflect/Method;
    //   60: astore 13
    //   62: iconst_3
    //   63: anewarray 4	java/lang/Object
    //   66: astore 14
    //   68: aload 14
    //   70: iconst_0
    //   71: ldc -97
    //   73: aastore
    //   74: aload 14
    //   76: iconst_1
    //   77: sipush 169
    //   80: invokestatic 108	java/lang/Character:valueOf	(C)Ljava/lang/Character;
    //   83: aastore
    //   84: aload 14
    //   86: iconst_2
    //   87: iconst_1
    //   88: invokestatic 108	java/lang/Character:valueOf	(C)Ljava/lang/Character;
    //   91: aastore
    //   92: aload 13
    //   94: aconst_null
    //   95: aload 14
    //   97: invokevirtual 114	java/lang/reflect/Method:invoke	(Ljava/lang/Object;[Ljava/lang/Object;)Ljava/lang/Object;
    //   100: astore 16
    //   102: aload 16
    //   104: checkcast 90	java/lang/String
    //   107: astore 17
    //   109: aload 10
    //   111: aload 17
    //   113: invokevirtual 118	java/lang/StringBuilder:append	(Ljava/lang/String;)Ljava/lang/StringBuilder;
    //   116: astore 18
    //   118: getstatic 28	uuuuuu/rrvvrv:bx0078xxx0078xxx	I
    //   121: istore 19
    //   123: iload 19
    //   125: iload 19
    //   127: getstatic 30	uuuuuu/rrvvrv:bxx0078xx0078xxx	I
    //   130: iadd
    //   131: imul
    //   132: getstatic 32	uuuuuu/rrvvrv:b0078x0078xx0078xxx	I
    //   135: irem
    //   136: tableswitch	default:+20->156, 0:+32->168
    //   156: invokestatic 36	uuuuuu/rrvvrv:b00710071007100710071qq0071q0071	()I
    //   159: putstatic 28	uuuuuu/rrvvrv:bx0078xxx0078xxx	I
    //   162: invokestatic 36	uuuuuu/rrvvrv:b00710071007100710071qq0071q0071	()I
    //   165: putstatic 38	uuuuuu/rrvvrv:b00780078xxx0078xxx	I
    //   168: invokestatic 36	uuuuuu/rrvvrv:b00710071007100710071qq0071q0071	()I
    //   171: invokestatic 58	uuuuuu/rrvvrv:bq0071qqq0071q0071q0071	()I
    //   174: iadd
    //   175: invokestatic 36	uuuuuu/rrvvrv:b00710071007100710071qq0071q0071	()I
    //   178: imul
    //   179: getstatic 32	uuuuuu/rrvvrv:b0078x0078xx0078xxx	I
    //   182: irem
    //   183: getstatic 38	uuuuuu/rrvvrv:b00780078xxx0078xxx	I
    //   186: if_icmpeq +14 -> 200
    //   189: invokestatic 36	uuuuuu/rrvvrv:b00710071007100710071qq0071q0071	()I
    //   192: putstatic 28	uuuuuu/rrvvrv:bx0078xxx0078xxx	I
    //   195: bipush 66
    //   197: putstatic 38	uuuuuu/rrvvrv:b00780078xxx0078xxx	I
    //   200: aload 9
    //   202: aload 18
    //   204: aload_0
    //   205: invokevirtual 118	java/lang/StringBuilder:append	(Ljava/lang/String;)Ljava/lang/StringBuilder;
    //   208: invokevirtual 123	java/lang/StringBuilder:toString	()Ljava/lang/String;
    //   211: invokestatic 128	uuuuuu/rvvvrv:b007100710071q00710071q0071q0071	(Ljava/lang/String;Ljava/lang/String;)V
    //   214: aload_0
    //   215: iconst_1
    //   216: invokestatic 162	com/appdynamics/eumagent/runtime/Instrumentation:leaveBreadcrumb	(Ljava/lang/String;I)V
    //   219: return
    //   220: astore_1
    //   221: getstatic 26	uuuuuu/rrvvrv:b0078xxxx0078xxx	Ljava/lang/String;
    //   224: astore_2
    //   225: ldc -92
    //   227: sipush 158
    //   230: iconst_3
    //   231: invokestatic 88	xxxxxx/uxxxxx:bb00620062bb0062b0062b0062	(Ljava/lang/String;CC)Ljava/lang/String;
    //   234: astore_3
    //   235: iconst_3
    //   236: anewarray 20	java/lang/Class
    //   239: astore 4
    //   241: aload 4
    //   243: iconst_0
    //   244: ldc 90
    //   246: aastore
    //   247: aload 4
    //   249: iconst_1
    //   250: getstatic 96	java/lang/Character:TYPE	Ljava/lang/Class;
    //   253: aastore
    //   254: aload 4
    //   256: iconst_2
    //   257: getstatic 96	java/lang/Character:TYPE	Ljava/lang/Class;
    //   260: aastore
    //   261: ldc 98
    //   263: aload_3
    //   264: aload 4
    //   266: invokevirtual 102	java/lang/Class:getMethod	(Ljava/lang/String;[Ljava/lang/Class;)Ljava/lang/reflect/Method;
    //   269: astore 5
    //   271: iconst_3
    //   272: anewarray 4	java/lang/Object
    //   275: astore 6
    //   277: aload 6
    //   279: iconst_0
    //   280: ldc -90
    //   282: aastore
    //   283: aload 6
    //   285: iconst_1
    //   286: bipush 63
    //   288: invokestatic 108	java/lang/Character:valueOf	(C)Ljava/lang/Character;
    //   291: aastore
    //   292: aload 6
    //   294: iconst_2
    //   295: iconst_3
    //   296: invokestatic 108	java/lang/Character:valueOf	(C)Ljava/lang/Character;
    //   299: aastore
    //   300: aload 5
    //   302: aconst_null
    //   303: aload 6
    //   305: invokevirtual 114	java/lang/reflect/Method:invoke	(Ljava/lang/Object;[Ljava/lang/Object;)Ljava/lang/Object;
    //   308: astore 8
    //   310: aload_2
    //   311: aload 8
    //   313: checkcast 90	java/lang/String
    //   316: aload_1
    //   317: invokestatic 146	uuuuuu/rvvvrv:b00710071qq00710071q0071q0071	(Ljava/lang/String;Ljava/lang/String;Ljava/lang/Throwable;)V
    //   320: return
    //   321: astore 15
    //   323: aload 15
    //   325: invokevirtual 138	java/lang/reflect/InvocationTargetException:getCause	()Ljava/lang/Throwable;
    //   328: athrow
    //   329: astore 7
    //   331: aload 7
    //   333: invokevirtual 138	java/lang/reflect/InvocationTargetException:getCause	()Ljava/lang/Throwable;
    //   336: athrow
    // Local variable table:
    //   start	length	slot	name	signature
    //   0	337	0	paramString	String
    //   220	97	1	localRuntimeException	RuntimeException
    //   224	87	2	str1	String
    //   234	30	3	str2	String
    //   239	26	4	arrayOfClass1	Class[]
    //   269	32	5	localMethod1	Method
    //   275	29	6	arrayOfObject1	Object[]
    //   329	3	7	localInvocationTargetException1	InvocationTargetException
    //   308	4	8	localObject1	Object
    //   3	198	9	str3	String
    //   12	98	10	localStringBuilder1	StringBuilder
    //   23	31	11	str4	String
    //   29	27	12	arrayOfClass2	Class[]
    //   60	33	13	localMethod2	Method
    //   66	30	14	arrayOfObject2	Object[]
    //   321	3	15	localInvocationTargetException2	InvocationTargetException
    //   100	3	16	localObject2	Object
    //   107	5	17	str5	String
    //   116	87	18	localStringBuilder2	StringBuilder
    //   121	11	19	i	int
    // Exception table:
    //   from	to	target	type
    //   0	14	220	java/lang/RuntimeException
    //   92	102	220	java/lang/RuntimeException
    //   109	118	220	java/lang/RuntimeException
    //   200	219	220	java/lang/RuntimeException
    //   323	329	220	java/lang/RuntimeException
    //   92	102	321	java/lang/reflect/InvocationTargetException
    //   300	310	329	java/lang/reflect/InvocationTargetException
  }
  
  /* Error */
  public static void bqqq0071q0071q0071q0071(String paramString, int paramInt)
  {
    // Byte code:
    //   0: getstatic 26	uuuuuu/rrvvrv:b0078xxxx0078xxx	Ljava/lang/String;
    //   3: astore 10
    //   5: new 79	java/lang/StringBuilder
    //   8: dup
    //   9: invokespecial 80	java/lang/StringBuilder:<init>	()V
    //   12: astore 11
    //   14: ldc -88
    //   16: sipush 245
    //   19: iconst_0
    //   20: invokestatic 88	xxxxxx/uxxxxx:bb00620062bb0062b0062b0062	(Ljava/lang/String;CC)Ljava/lang/String;
    //   23: astore 12
    //   25: iconst_4
    //   26: anewarray 20	java/lang/Class
    //   29: astore 13
    //   31: aload 13
    //   33: iconst_0
    //   34: ldc 90
    //   36: aastore
    //   37: aload 13
    //   39: iconst_1
    //   40: getstatic 96	java/lang/Character:TYPE	Ljava/lang/Class;
    //   43: aastore
    //   44: aload 13
    //   46: iconst_2
    //   47: getstatic 96	java/lang/Character:TYPE	Ljava/lang/Class;
    //   50: aastore
    //   51: aload 13
    //   53: iconst_3
    //   54: getstatic 96	java/lang/Character:TYPE	Ljava/lang/Class;
    //   57: aastore
    //   58: ldc 98
    //   60: aload 12
    //   62: aload 13
    //   64: invokevirtual 102	java/lang/Class:getMethod	(Ljava/lang/String;[Ljava/lang/Class;)Ljava/lang/reflect/Method;
    //   67: astore 14
    //   69: iconst_4
    //   70: anewarray 4	java/lang/Object
    //   73: astore 15
    //   75: aload 15
    //   77: iconst_0
    //   78: ldc -86
    //   80: aastore
    //   81: aload 15
    //   83: iconst_1
    //   84: bipush 87
    //   86: invokestatic 108	java/lang/Character:valueOf	(C)Ljava/lang/Character;
    //   89: aastore
    //   90: aload 15
    //   92: iconst_2
    //   93: sipush 215
    //   96: invokestatic 108	java/lang/Character:valueOf	(C)Ljava/lang/Character;
    //   99: aastore
    //   100: aload 15
    //   102: iconst_3
    //   103: iconst_0
    //   104: invokestatic 108	java/lang/Character:valueOf	(C)Ljava/lang/Character;
    //   107: aastore
    //   108: aload 14
    //   110: aconst_null
    //   111: aload 15
    //   113: invokevirtual 114	java/lang/reflect/Method:invoke	(Ljava/lang/Object;[Ljava/lang/Object;)Ljava/lang/Object;
    //   116: astore 17
    //   118: aload 17
    //   120: checkcast 90	java/lang/String
    //   123: astore 18
    //   125: aload 11
    //   127: aload 18
    //   129: invokevirtual 118	java/lang/StringBuilder:append	(Ljava/lang/String;)Ljava/lang/StringBuilder;
    //   132: aload_0
    //   133: invokevirtual 118	java/lang/StringBuilder:append	(Ljava/lang/String;)Ljava/lang/StringBuilder;
    //   136: astore 19
    //   138: ldc -84
    //   140: sipush 215
    //   143: iconst_4
    //   144: invokestatic 88	xxxxxx/uxxxxx:bb00620062bb0062b0062b0062	(Ljava/lang/String;CC)Ljava/lang/String;
    //   147: astore 20
    //   149: iconst_3
    //   150: anewarray 20	java/lang/Class
    //   153: astore 21
    //   155: aload 21
    //   157: iconst_0
    //   158: ldc 90
    //   160: aastore
    //   161: aload 21
    //   163: iconst_1
    //   164: getstatic 96	java/lang/Character:TYPE	Ljava/lang/Class;
    //   167: aastore
    //   168: aload 21
    //   170: iconst_2
    //   171: getstatic 96	java/lang/Character:TYPE	Ljava/lang/Class;
    //   174: aastore
    //   175: ldc 98
    //   177: aload 20
    //   179: aload 21
    //   181: invokevirtual 102	java/lang/Class:getMethod	(Ljava/lang/String;[Ljava/lang/Class;)Ljava/lang/reflect/Method;
    //   184: astore 22
    //   186: iconst_3
    //   187: anewarray 4	java/lang/Object
    //   190: astore 23
    //   192: aload 23
    //   194: iconst_0
    //   195: ldc -82
    //   197: aastore
    //   198: aload 23
    //   200: iconst_1
    //   201: bipush 15
    //   203: invokestatic 108	java/lang/Character:valueOf	(C)Ljava/lang/Character;
    //   206: aastore
    //   207: aload 23
    //   209: iconst_2
    //   210: iconst_0
    //   211: invokestatic 108	java/lang/Character:valueOf	(C)Ljava/lang/Character;
    //   214: aastore
    //   215: aload 22
    //   217: aconst_null
    //   218: aload 23
    //   220: invokevirtual 114	java/lang/reflect/Method:invoke	(Ljava/lang/Object;[Ljava/lang/Object;)Ljava/lang/Object;
    //   223: astore 25
    //   225: aload 25
    //   227: checkcast 90	java/lang/String
    //   230: astore 26
    //   232: aload 19
    //   234: aload 26
    //   236: invokevirtual 118	java/lang/StringBuilder:append	(Ljava/lang/String;)Ljava/lang/StringBuilder;
    //   239: iload_1
    //   240: invokevirtual 177	java/lang/StringBuilder:append	(I)Ljava/lang/StringBuilder;
    //   243: astore 27
    //   245: getstatic 28	uuuuuu/rrvvrv:bx0078xxx0078xxx	I
    //   248: getstatic 30	uuuuuu/rrvvrv:bxx0078xx0078xxx	I
    //   251: iadd
    //   252: getstatic 28	uuuuuu/rrvvrv:bx0078xxx0078xxx	I
    //   255: imul
    //   256: getstatic 32	uuuuuu/rrvvrv:b0078x0078xx0078xxx	I
    //   259: irem
    //   260: getstatic 38	uuuuuu/rrvvrv:b00780078xxx0078xxx	I
    //   263: if_icmpeq +15 -> 278
    //   266: invokestatic 36	uuuuuu/rrvvrv:b00710071007100710071qq0071q0071	()I
    //   269: putstatic 28	uuuuuu/rrvvrv:bx0078xxx0078xxx	I
    //   272: invokestatic 36	uuuuuu/rrvvrv:b00710071007100710071qq0071q0071	()I
    //   275: putstatic 38	uuuuuu/rrvvrv:b00780078xxx0078xxx	I
    //   278: ldc -77
    //   280: sipush 177
    //   283: iconst_1
    //   284: invokestatic 88	xxxxxx/uxxxxx:bb00620062bb0062b0062b0062	(Ljava/lang/String;CC)Ljava/lang/String;
    //   287: astore 28
    //   289: iconst_3
    //   290: anewarray 20	java/lang/Class
    //   293: astore 29
    //   295: aload 29
    //   297: iconst_0
    //   298: ldc 90
    //   300: aastore
    //   301: aload 29
    //   303: iconst_1
    //   304: getstatic 96	java/lang/Character:TYPE	Ljava/lang/Class;
    //   307: aastore
    //   308: aload 29
    //   310: iconst_2
    //   311: getstatic 96	java/lang/Character:TYPE	Ljava/lang/Class;
    //   314: aastore
    //   315: ldc 98
    //   317: aload 28
    //   319: aload 29
    //   321: invokevirtual 102	java/lang/Class:getMethod	(Ljava/lang/String;[Ljava/lang/Class;)Ljava/lang/reflect/Method;
    //   324: astore 30
    //   326: iconst_3
    //   327: anewarray 4	java/lang/Object
    //   330: astore 31
    //   332: aload 31
    //   334: iconst_0
    //   335: ldc -75
    //   337: aastore
    //   338: aload 31
    //   340: iconst_1
    //   341: sipush 224
    //   344: invokestatic 108	java/lang/Character:valueOf	(C)Ljava/lang/Character;
    //   347: aastore
    //   348: aload 31
    //   350: iconst_2
    //   351: iconst_1
    //   352: invokestatic 108	java/lang/Character:valueOf	(C)Ljava/lang/Character;
    //   355: aastore
    //   356: aload 30
    //   358: aconst_null
    //   359: aload 31
    //   361: invokevirtual 114	java/lang/reflect/Method:invoke	(Ljava/lang/Object;[Ljava/lang/Object;)Ljava/lang/Object;
    //   364: astore 33
    //   366: aload 33
    //   368: checkcast 90	java/lang/String
    //   371: astore 34
    //   373: aload 10
    //   375: aload 27
    //   377: aload 34
    //   379: invokevirtual 118	java/lang/StringBuilder:append	(Ljava/lang/String;)Ljava/lang/StringBuilder;
    //   382: invokevirtual 123	java/lang/StringBuilder:toString	()Ljava/lang/String;
    //   385: invokestatic 128	uuuuuu/rvvvrv:b007100710071q00710071q0071q0071	(Ljava/lang/String;Ljava/lang/String;)V
    //   388: aload_0
    //   389: iload_1
    //   390: i2l
    //   391: invokestatic 185	com/appdynamics/eumagent/runtime/Instrumentation:reportMetric	(Ljava/lang/String;J)V
    //   394: return
    //   395: astore_2
    //   396: getstatic 26	uuuuuu/rrvvrv:b0078xxxx0078xxx	Ljava/lang/String;
    //   399: astore_3
    //   400: ldc -69
    //   402: bipush 119
    //   404: bipush 74
    //   406: iconst_1
    //   407: invokestatic 191	xxxxxx/uxxxxx:bbbb0062b0062b0062b0062	(Ljava/lang/String;CCC)Ljava/lang/String;
    //   410: astore 4
    //   412: iconst_4
    //   413: anewarray 20	java/lang/Class
    //   416: astore 5
    //   418: aload 5
    //   420: iconst_0
    //   421: ldc 90
    //   423: aastore
    //   424: aload 5
    //   426: iconst_1
    //   427: getstatic 96	java/lang/Character:TYPE	Ljava/lang/Class;
    //   430: aastore
    //   431: aload 5
    //   433: iconst_2
    //   434: getstatic 96	java/lang/Character:TYPE	Ljava/lang/Class;
    //   437: aastore
    //   438: aload 5
    //   440: iconst_3
    //   441: getstatic 96	java/lang/Character:TYPE	Ljava/lang/Class;
    //   444: aastore
    //   445: ldc 98
    //   447: aload 4
    //   449: aload 5
    //   451: invokevirtual 102	java/lang/Class:getMethod	(Ljava/lang/String;[Ljava/lang/Class;)Ljava/lang/reflect/Method;
    //   454: astore 6
    //   456: iconst_4
    //   457: anewarray 4	java/lang/Object
    //   460: astore 7
    //   462: aload 7
    //   464: iconst_0
    //   465: ldc -63
    //   467: aastore
    //   468: aload 7
    //   470: iconst_1
    //   471: bipush 100
    //   473: invokestatic 108	java/lang/Character:valueOf	(C)Ljava/lang/Character;
    //   476: aastore
    //   477: aload 7
    //   479: iconst_2
    //   480: sipush 153
    //   483: invokestatic 108	java/lang/Character:valueOf	(C)Ljava/lang/Character;
    //   486: aastore
    //   487: aload 7
    //   489: iconst_3
    //   490: iconst_2
    //   491: invokestatic 108	java/lang/Character:valueOf	(C)Ljava/lang/Character;
    //   494: aastore
    //   495: aload 6
    //   497: aconst_null
    //   498: aload 7
    //   500: invokevirtual 114	java/lang/reflect/Method:invoke	(Ljava/lang/Object;[Ljava/lang/Object;)Ljava/lang/Object;
    //   503: astore 9
    //   505: aload_3
    //   506: aload 9
    //   508: checkcast 90	java/lang/String
    //   511: aload_2
    //   512: invokestatic 146	uuuuuu/rvvvrv:b00710071qq00710071q0071q0071	(Ljava/lang/String;Ljava/lang/String;Ljava/lang/Throwable;)V
    //   515: getstatic 28	uuuuuu/rrvvrv:bx0078xxx0078xxx	I
    //   518: getstatic 30	uuuuuu/rrvvrv:bxx0078xx0078xxx	I
    //   521: iadd
    //   522: getstatic 28	uuuuuu/rrvvrv:bx0078xxx0078xxx	I
    //   525: imul
    //   526: getstatic 32	uuuuuu/rrvvrv:b0078x0078xx0078xxx	I
    //   529: irem
    //   530: getstatic 38	uuuuuu/rrvvrv:b00780078xxx0078xxx	I
    //   533: if_icmpeq -139 -> 394
    //   536: invokestatic 36	uuuuuu/rrvvrv:b00710071007100710071qq0071q0071	()I
    //   539: putstatic 28	uuuuuu/rrvvrv:bx0078xxx0078xxx	I
    //   542: invokestatic 36	uuuuuu/rrvvrv:b00710071007100710071qq0071q0071	()I
    //   545: putstatic 38	uuuuuu/rrvvrv:b00780078xxx0078xxx	I
    //   548: return
    //   549: astore 32
    //   551: aload 32
    //   553: invokevirtual 138	java/lang/reflect/InvocationTargetException:getCause	()Ljava/lang/Throwable;
    //   556: athrow
    //   557: astore 16
    //   559: aload 16
    //   561: invokevirtual 138	java/lang/reflect/InvocationTargetException:getCause	()Ljava/lang/Throwable;
    //   564: athrow
    //   565: astore 8
    //   567: aload 8
    //   569: invokevirtual 138	java/lang/reflect/InvocationTargetException:getCause	()Ljava/lang/Throwable;
    //   572: athrow
    //   573: astore 24
    //   575: aload 24
    //   577: invokevirtual 138	java/lang/reflect/InvocationTargetException:getCause	()Ljava/lang/Throwable;
    //   580: athrow
    // Local variable table:
    //   start	length	slot	name	signature
    //   0	581	0	paramString	String
    //   0	581	1	paramInt	int
    //   395	117	2	localRuntimeException	RuntimeException
    //   399	107	3	str1	String
    //   410	38	4	str2	String
    //   416	34	5	arrayOfClass1	Class[]
    //   454	42	6	localMethod1	Method
    //   460	39	7	arrayOfObject1	Object[]
    //   565	3	8	localInvocationTargetException1	InvocationTargetException
    //   503	4	9	localObject1	Object
    //   3	371	10	str3	String
    //   12	114	11	localStringBuilder1	StringBuilder
    //   23	38	12	str4	String
    //   29	34	13	arrayOfClass2	Class[]
    //   67	42	14	localMethod2	Method
    //   73	39	15	arrayOfObject2	Object[]
    //   557	3	16	localInvocationTargetException2	InvocationTargetException
    //   116	3	17	localObject2	Object
    //   123	5	18	str5	String
    //   136	97	19	localStringBuilder2	StringBuilder
    //   147	31	20	str6	String
    //   153	27	21	arrayOfClass3	Class[]
    //   184	32	22	localMethod3	Method
    //   190	29	23	arrayOfObject3	Object[]
    //   573	3	24	localInvocationTargetException3	InvocationTargetException
    //   223	3	25	localObject3	Object
    //   230	5	26	str7	String
    //   243	133	27	localStringBuilder3	StringBuilder
    //   287	31	28	str8	String
    //   293	27	29	arrayOfClass4	Class[]
    //   324	33	30	localMethod4	Method
    //   330	30	31	arrayOfObject4	Object[]
    //   549	3	32	localInvocationTargetException4	InvocationTargetException
    //   364	3	33	localObject4	Object
    //   371	7	34	str9	String
    // Exception table:
    //   from	to	target	type
    //   0	14	395	java/lang/RuntimeException
    //   108	118	395	java/lang/RuntimeException
    //   125	138	395	java/lang/RuntimeException
    //   215	225	395	java/lang/RuntimeException
    //   232	245	395	java/lang/RuntimeException
    //   356	366	395	java/lang/RuntimeException
    //   373	394	395	java/lang/RuntimeException
    //   551	557	395	java/lang/RuntimeException
    //   559	565	395	java/lang/RuntimeException
    //   575	581	395	java/lang/RuntimeException
    //   356	366	549	java/lang/reflect/InvocationTargetException
    //   108	118	557	java/lang/reflect/InvocationTargetException
    //   495	505	565	java/lang/reflect/InvocationTargetException
    //   215	225	573	java/lang/reflect/InvocationTargetException
  }
  
  public static int bqqqqq0071q0071q0071()
  {
    return 0;
  }
}
