package uuuuuu;

public final class rvrvrv
{
  public static int b00680068h006800680068hh0068 = 2;
  public static int b0068hh006800680068hh0068 = 5;
  public static int bh0068h006800680068hh0068 = 1;
  public static int bhh0068006800680068hh0068 = 0;
  public static final String bhhh006800680068hh0068 = "BBB<OEL";
  
  private rvrvrv() {}
  
  public static int b007100710071q0071qq0071q0071()
  {
    return 83;
  }
  
  /* Error */
  public static String b0071qq00710071qq0071q0071(String arg0)
  {
    // Byte code:
    //   0: aload_0
    //   1: invokevirtual 32	java/lang/String:hashCode	()I
    //   4: lookupswitch	default:+260->264, 49:+5422->5426, 50:+5762->5766, 51:+5878->5882, 52:+2149->2153, 53:+2287->2291, 54:+6600->6604, 55:+6715->6719, 56:+3000->3004, 65:+1511->1515, 66:+1661->1665, 67:+6222->6226, 68:+6109->6113, 69:+656->660, 71:+1362->1366, 72:+795->799, 74:+7455->7459, 75:+2859->2863, 76:+3354->3358, 77:+3505->3509, 78:+3677->3681, 79:+4976->4980, 80:+5147->5151, 82:+4597->4601, 84:+5297->5301, 85:+5992->5996, 86:+1188->1192, 87:+4447->4451, 88:+3861->3865, 89:+4285->4289, 90:+5648->5652, 1544803905:+998->1002
    //   264: iconst_m1
    //   265: istore 7
    //   267: iload 7
    //   269: tableswitch	default:+139->408, 0:+1657->1926, 1:+2882->3151, 2:+3870->4139, 3:+7314->7583, 4:+6117->6386, 5:+1554->1823, 6:+6738->7007, 7:+4483->4752, 8:+5272->5541, 9:+6957->7226, 10:+7075->7344, 11:+3768->4037, 12:+1766->2035, 13:+1766->2035, 14:+1766->2035, 15:+2484->2753, 16:+8002->8271, 17:+8124->8393, 18:+6588->6857, 19:+2161->2430, 20:+4603->4872, 21:+7428->7697, 22:+7547->7816, 23:+7651->7920, 24:+2271->2540, 25:+2388->2657, 26:+6848->7117, 27:+7795->8064, 28:+7897->8166, 29:+6232->6501, 30:+2994->3263
    //   408: new 34	java/lang/StringBuilder
    //   411: dup
    //   412: invokespecial 35	java/lang/StringBuilder:<init>	()V
    //   415: astore -72
    //   417: ldc 37
    //   419: sipush 221
    //   422: bipush 52
    //   424: iconst_1
    //   425: invokestatic 43	xxxxxx/uxxxxx:bbbb0062b0062b0062b0062	(Ljava/lang/String;CCC)Ljava/lang/String;
    //   428: astore -71
    //   430: iconst_4
    //   431: anewarray 45	java/lang/Class
    //   434: astore -70
    //   436: aload -70
    //   438: iconst_0
    //   439: ldc 29
    //   441: aastore
    //   442: aload -70
    //   444: iconst_1
    //   445: getstatic 51	java/lang/Character:TYPE	Ljava/lang/Class;
    //   448: aastore
    //   449: aload -70
    //   451: iconst_2
    //   452: getstatic 51	java/lang/Character:TYPE	Ljava/lang/Class;
    //   455: aastore
    //   456: aload -70
    //   458: iconst_3
    //   459: getstatic 51	java/lang/Character:TYPE	Ljava/lang/Class;
    //   462: aastore
    //   463: ldc 53
    //   465: aload -71
    //   467: aload -70
    //   469: invokevirtual 57	java/lang/Class:getMethod	(Ljava/lang/String;[Ljava/lang/Class;)Ljava/lang/reflect/Method;
    //   472: astore -69
    //   474: iconst_4
    //   475: anewarray 4	java/lang/Object
    //   478: astore -68
    //   480: aload -68
    //   482: iconst_0
    //   483: ldc 59
    //   485: aastore
    //   486: aload -68
    //   488: iconst_1
    //   489: bipush 14
    //   491: invokestatic 63	java/lang/Character:valueOf	(C)Ljava/lang/Character;
    //   494: aastore
    //   495: aload -68
    //   497: iconst_2
    //   498: sipush 189
    //   501: invokestatic 63	java/lang/Character:valueOf	(C)Ljava/lang/Character;
    //   504: aastore
    //   505: aload -68
    //   507: iconst_3
    //   508: iconst_1
    //   509: invokestatic 63	java/lang/Character:valueOf	(C)Ljava/lang/Character;
    //   512: aastore
    //   513: aload -69
    //   515: aconst_null
    //   516: aload -68
    //   518: invokevirtual 69	java/lang/reflect/Method:invoke	(Ljava/lang/Object;[Ljava/lang/Object;)Ljava/lang/Object;
    //   521: astore -66
    //   523: aload -72
    //   525: aload -66
    //   527: checkcast 29	java/lang/String
    //   530: invokevirtual 73	java/lang/StringBuilder:append	(Ljava/lang/String;)Ljava/lang/StringBuilder;
    //   533: aload_0
    //   534: invokevirtual 73	java/lang/StringBuilder:append	(Ljava/lang/String;)Ljava/lang/StringBuilder;
    //   537: astore -65
    //   539: ldc 75
    //   541: bipush 52
    //   543: iconst_4
    //   544: invokestatic 79	xxxxxx/uxxxxx:bb00620062bb0062b0062b0062	(Ljava/lang/String;CC)Ljava/lang/String;
    //   547: astore -64
    //   549: iconst_4
    //   550: anewarray 45	java/lang/Class
    //   553: astore -63
    //   555: aload -63
    //   557: iconst_0
    //   558: ldc 29
    //   560: aastore
    //   561: aload -63
    //   563: iconst_1
    //   564: getstatic 51	java/lang/Character:TYPE	Ljava/lang/Class;
    //   567: aastore
    //   568: aload -63
    //   570: iconst_2
    //   571: getstatic 51	java/lang/Character:TYPE	Ljava/lang/Class;
    //   574: aastore
    //   575: aload -63
    //   577: iconst_3
    //   578: getstatic 51	java/lang/Character:TYPE	Ljava/lang/Class;
    //   581: aastore
    //   582: ldc 53
    //   584: aload -64
    //   586: aload -63
    //   588: invokevirtual 57	java/lang/Class:getMethod	(Ljava/lang/String;[Ljava/lang/Class;)Ljava/lang/reflect/Method;
    //   591: astore -62
    //   593: iconst_4
    //   594: anewarray 4	java/lang/Object
    //   597: astore -61
    //   599: aload -61
    //   601: iconst_0
    //   602: ldc 81
    //   604: aastore
    //   605: aload -61
    //   607: iconst_1
    //   608: sipush 222
    //   611: invokestatic 63	java/lang/Character:valueOf	(C)Ljava/lang/Character;
    //   614: aastore
    //   615: aload -61
    //   617: iconst_2
    //   618: bipush 7
    //   620: invokestatic 63	java/lang/Character:valueOf	(C)Ljava/lang/Character;
    //   623: aastore
    //   624: aload -61
    //   626: iconst_3
    //   627: iconst_2
    //   628: invokestatic 63	java/lang/Character:valueOf	(C)Ljava/lang/Character;
    //   631: aastore
    //   632: aload -62
    //   634: aconst_null
    //   635: aload -61
    //   637: invokevirtual 69	java/lang/reflect/Method:invoke	(Ljava/lang/Object;[Ljava/lang/Object;)Ljava/lang/Object;
    //   640: astore -59
    //   642: aload -65
    //   644: aload -59
    //   646: checkcast 29	java/lang/String
    //   649: invokevirtual 73	java/lang/StringBuilder:append	(Ljava/lang/String;)Ljava/lang/StringBuilder;
    //   652: invokevirtual 85	java/lang/StringBuilder:toString	()Ljava/lang/String;
    //   655: astore 122
    //   657: aload 122
    //   659: areturn
    //   660: ldc 87
    //   662: bipush 48
    //   664: bipush 68
    //   666: iconst_2
    //   667: invokestatic 43	xxxxxx/uxxxxx:bbbb0062b0062b0062b0062	(Ljava/lang/String;CCC)Ljava/lang/String;
    //   670: wide
    //   674: iconst_3
    //   675: anewarray 45	java/lang/Class
    //   678: wide
    //   682: wide
    //   686: iconst_0
    //   687: ldc 29
    //   689: aastore
    //   690: wide
    //   694: iconst_1
    //   695: getstatic 51	java/lang/Character:TYPE	Ljava/lang/Class;
    //   698: aastore
    //   699: wide
    //   703: iconst_2
    //   704: getstatic 51	java/lang/Character:TYPE	Ljava/lang/Class;
    //   707: aastore
    //   708: ldc 53
    //   710: wide
    //   714: wide
    //   718: invokevirtual 57	java/lang/Class:getMethod	(Ljava/lang/String;[Ljava/lang/Class;)Ljava/lang/reflect/Method;
    //   721: wide
    //   725: iconst_3
    //   726: anewarray 4	java/lang/Object
    //   729: wide
    //   733: wide
    //   737: iconst_0
    //   738: ldc 89
    //   740: aastore
    //   741: wide
    //   745: iconst_1
    //   746: sipush 207
    //   749: invokestatic 63	java/lang/Character:valueOf	(C)Ljava/lang/Character;
    //   752: aastore
    //   753: wide
    //   757: iconst_2
    //   758: iconst_2
    //   759: invokestatic 63	java/lang/Character:valueOf	(C)Ljava/lang/Character;
    //   762: aastore
    //   763: wide
    //   767: aconst_null
    //   768: wide
    //   772: invokevirtual 69	java/lang/reflect/Method:invoke	(Ljava/lang/Object;[Ljava/lang/Object;)Ljava/lang/Object;
    //   775: wide
    //   779: aload_0
    //   780: wide
    //   784: checkcast 29	java/lang/String
    //   787: invokevirtual 93	java/lang/String:equals	(Ljava/lang/Object;)Z
    //   790: ifeq -526 -> 264
    //   793: iconst_5
    //   794: istore 7
    //   796: goto -529 -> 267
    //   799: ldc 95
    //   801: sipush 219
    //   804: iconst_3
    //   805: invokestatic 79	xxxxxx/uxxxxx:bb00620062bb0062b0062b0062	(Ljava/lang/String;CC)Ljava/lang/String;
    //   808: wide
    //   812: iconst_3
    //   813: anewarray 45	java/lang/Class
    //   816: wide
    //   820: wide
    //   824: iconst_0
    //   825: ldc 29
    //   827: aastore
    //   828: wide
    //   832: iconst_1
    //   833: getstatic 51	java/lang/Character:TYPE	Ljava/lang/Class;
    //   836: aastore
    //   837: wide
    //   841: iconst_2
    //   842: getstatic 51	java/lang/Character:TYPE	Ljava/lang/Class;
    //   845: aastore
    //   846: ldc 53
    //   848: wide
    //   852: wide
    //   856: invokevirtual 57	java/lang/Class:getMethod	(Ljava/lang/String;[Ljava/lang/Class;)Ljava/lang/reflect/Method;
    //   859: wide
    //   863: iconst_3
    //   864: anewarray 4	java/lang/Object
    //   867: wide
    //   871: wide
    //   875: iconst_0
    //   876: ldc 97
    //   878: aastore
    //   879: wide
    //   883: iconst_1
    //   884: bipush 60
    //   886: invokestatic 63	java/lang/Character:valueOf	(C)Ljava/lang/Character;
    //   889: aastore
    //   890: wide
    //   894: iconst_2
    //   895: iconst_1
    //   896: invokestatic 63	java/lang/Character:valueOf	(C)Ljava/lang/Character;
    //   899: aastore
    //   900: wide
    //   904: aconst_null
    //   905: wide
    //   909: invokevirtual 69	java/lang/reflect/Method:invoke	(Ljava/lang/Object;[Ljava/lang/Object;)Ljava/lang/Object;
    //   912: wide
    //   916: aload_0
    //   917: wide
    //   921: checkcast 29	java/lang/String
    //   924: invokevirtual 93	java/lang/String:equals	(Ljava/lang/Object;)Z
    //   927: ifeq -663 -> 264
    //   930: bipush 7
    //   932: istore 7
    //   934: getstatic 99	uuuuuu/rvrvrv:b0068hh006800680068hh0068	I
    //   937: wide
    //   941: wide
    //   945: wide
    //   949: getstatic 101	uuuuuu/rvrvrv:bh0068h006800680068hh0068	I
    //   952: iadd
    //   953: imul
    //   954: getstatic 103	uuuuuu/rvrvrv:b00680068h006800680068hh0068	I
    //   957: irem
    //   958: tableswitch	default:+18->976, 0:+-691->267
    //   976: invokestatic 105	uuuuuu/rvrvrv:b007100710071q0071qq0071q0071	()I
    //   979: putstatic 99	uuuuuu/rvrvrv:b0068hh006800680068hh0068	I
    //   982: bipush 67
    //   984: putstatic 101	uuuuuu/rvrvrv:bh0068h006800680068hh0068	I
    //   987: goto -720 -> 267
    //   990: wide
    //   994: wide
    //   998: invokevirtual 109	java/lang/reflect/InvocationTargetException:getCause	()Ljava/lang/Throwable;
    //   1001: athrow
    //   1002: ldc 111
    //   1004: bipush 97
    //   1006: iconst_4
    //   1007: invokestatic 79	xxxxxx/uxxxxx:bb00620062bb0062b0062b0062	(Ljava/lang/String;CC)Ljava/lang/String;
    //   1010: wide
    //   1014: iconst_3
    //   1015: anewarray 45	java/lang/Class
    //   1018: wide
    //   1022: wide
    //   1026: iconst_0
    //   1027: ldc 29
    //   1029: aastore
    //   1030: wide
    //   1034: iconst_1
    //   1035: getstatic 51	java/lang/Character:TYPE	Ljava/lang/Class;
    //   1038: aastore
    //   1039: wide
    //   1043: iconst_2
    //   1044: getstatic 51	java/lang/Character:TYPE	Ljava/lang/Class;
    //   1047: aastore
    //   1048: ldc 53
    //   1050: wide
    //   1054: wide
    //   1058: invokevirtual 57	java/lang/Class:getMethod	(Ljava/lang/String;[Ljava/lang/Class;)Ljava/lang/reflect/Method;
    //   1061: wide
    //   1065: iconst_3
    //   1066: anewarray 4	java/lang/Object
    //   1069: wide
    //   1073: wide
    //   1077: iconst_0
    //   1078: ldc 113
    //   1080: aastore
    //   1081: wide
    //   1085: iconst_1
    //   1086: sipush 131
    //   1089: invokestatic 63	java/lang/Character:valueOf	(C)Ljava/lang/Character;
    //   1092: aastore
    //   1093: wide
    //   1097: iconst_2
    //   1098: iconst_5
    //   1099: invokestatic 63	java/lang/Character:valueOf	(C)Ljava/lang/Character;
    //   1102: aastore
    //   1103: wide
    //   1107: aconst_null
    //   1108: wide
    //   1112: invokevirtual 69	java/lang/reflect/Method:invoke	(Ljava/lang/Object;[Ljava/lang/Object;)Ljava/lang/Object;
    //   1115: wide
    //   1119: aload_0
    //   1120: wide
    //   1124: checkcast 29	java/lang/String
    //   1127: invokevirtual 93	java/lang/String:equals	(Ljava/lang/Object;)Z
    //   1130: ifeq -866 -> 264
    //   1133: getstatic 99	uuuuuu/rvrvrv:b0068hh006800680068hh0068	I
    //   1136: wide
    //   1140: wide
    //   1144: wide
    //   1148: invokestatic 116	uuuuuu/rvrvrv:bqqq00710071qq0071q0071	()I
    //   1151: iadd
    //   1152: imul
    //   1153: getstatic 103	uuuuuu/rvrvrv:b00680068h006800680068hh0068	I
    //   1156: irem
    //   1157: tableswitch	default:+19->1176, 0:+7367->8524
    //   1176: iconst_3
    //   1177: putstatic 99	uuuuuu/rvrvrv:b0068hh006800680068hh0068	I
    //   1180: invokestatic 105	uuuuuu/rvrvrv:b007100710071q0071qq0071q0071	()I
    //   1183: putstatic 101	uuuuuu/rvrvrv:bh0068h006800680068hh0068	I
    //   1186: iconst_0
    //   1187: istore 7
    //   1189: goto -922 -> 267
    //   1192: ldc 118
    //   1194: sipush 145
    //   1197: sipush 173
    //   1200: iconst_0
    //   1201: invokestatic 43	xxxxxx/uxxxxx:bbbb0062b0062b0062b0062	(Ljava/lang/String;CCC)Ljava/lang/String;
    //   1204: wide
    //   1208: iconst_4
    //   1209: anewarray 45	java/lang/Class
    //   1212: wide
    //   1216: wide
    //   1220: iconst_0
    //   1221: ldc 29
    //   1223: aastore
    //   1224: wide
    //   1228: iconst_1
    //   1229: getstatic 51	java/lang/Character:TYPE	Ljava/lang/Class;
    //   1232: aastore
    //   1233: wide
    //   1237: iconst_2
    //   1238: getstatic 51	java/lang/Character:TYPE	Ljava/lang/Class;
    //   1241: aastore
    //   1242: wide
    //   1246: iconst_3
    //   1247: getstatic 51	java/lang/Character:TYPE	Ljava/lang/Class;
    //   1250: aastore
    //   1251: ldc 53
    //   1253: wide
    //   1257: wide
    //   1261: invokevirtual 57	java/lang/Class:getMethod	(Ljava/lang/String;[Ljava/lang/Class;)Ljava/lang/reflect/Method;
    //   1264: wide
    //   1268: iconst_4
    //   1269: anewarray 4	java/lang/Object
    //   1272: wide
    //   1276: wide
    //   1280: iconst_0
    //   1281: ldc 120
    //   1283: aastore
    //   1284: wide
    //   1288: iconst_1
    //   1289: bipush 48
    //   1291: invokestatic 63	java/lang/Character:valueOf	(C)Ljava/lang/Character;
    //   1294: aastore
    //   1295: wide
    //   1299: iconst_2
    //   1300: sipush 223
    //   1303: invokestatic 63	java/lang/Character:valueOf	(C)Ljava/lang/Character;
    //   1306: aastore
    //   1307: wide
    //   1311: iconst_3
    //   1312: iconst_0
    //   1313: invokestatic 63	java/lang/Character:valueOf	(C)Ljava/lang/Character;
    //   1316: aastore
    //   1317: wide
    //   1321: aconst_null
    //   1322: wide
    //   1326: invokevirtual 69	java/lang/reflect/Method:invoke	(Ljava/lang/Object;[Ljava/lang/Object;)Ljava/lang/Object;
    //   1329: wide
    //   1333: aload_0
    //   1334: wide
    //   1338: checkcast 29	java/lang/String
    //   1341: invokevirtual 93	java/lang/String:equals	(Ljava/lang/Object;)Z
    //   1344: ifeq -1080 -> 264
    //   1347: bipush 19
    //   1349: istore 7
    //   1351: goto -1084 -> 267
    //   1354: wide
    //   1358: wide
    //   1362: invokevirtual 109	java/lang/reflect/InvocationTargetException:getCause	()Ljava/lang/Throwable;
    //   1365: athrow
    //   1366: ldc 122
    //   1368: bipush 48
    //   1370: iconst_0
    //   1371: invokestatic 79	xxxxxx/uxxxxx:bb00620062bb0062b0062b0062	(Ljava/lang/String;CC)Ljava/lang/String;
    //   1374: wide
    //   1378: iconst_3
    //   1379: anewarray 45	java/lang/Class
    //   1382: wide
    //   1386: wide
    //   1390: iconst_0
    //   1391: ldc 29
    //   1393: aastore
    //   1394: wide
    //   1398: iconst_1
    //   1399: getstatic 51	java/lang/Character:TYPE	Ljava/lang/Class;
    //   1402: aastore
    //   1403: wide
    //   1407: iconst_2
    //   1408: getstatic 51	java/lang/Character:TYPE	Ljava/lang/Class;
    //   1411: aastore
    //   1412: ldc 53
    //   1414: wide
    //   1418: wide
    //   1422: invokevirtual 57	java/lang/Class:getMethod	(Ljava/lang/String;[Ljava/lang/Class;)Ljava/lang/reflect/Method;
    //   1425: wide
    //   1429: iconst_3
    //   1430: anewarray 4	java/lang/Object
    //   1433: wide
    //   1437: wide
    //   1441: iconst_0
    //   1442: ldc 81
    //   1444: aastore
    //   1445: wide
    //   1449: iconst_1
    //   1450: bipush 104
    //   1452: invokestatic 63	java/lang/Character:valueOf	(C)Ljava/lang/Character;
    //   1455: aastore
    //   1456: wide
    //   1460: iconst_2
    //   1461: iconst_0
    //   1462: invokestatic 63	java/lang/Character:valueOf	(C)Ljava/lang/Character;
    //   1465: aastore
    //   1466: wide
    //   1470: aconst_null
    //   1471: wide
    //   1475: invokevirtual 69	java/lang/reflect/Method:invoke	(Ljava/lang/Object;[Ljava/lang/Object;)Ljava/lang/Object;
    //   1478: wide
    //   1482: aload_0
    //   1483: wide
    //   1487: checkcast 29	java/lang/String
    //   1490: invokevirtual 93	java/lang/String:equals	(Ljava/lang/Object;)Z
    //   1493: ifeq -1229 -> 264
    //   1496: bipush 6
    //   1498: istore 7
    //   1500: goto -1233 -> 267
    //   1503: wide
    //   1507: wide
    //   1511: invokevirtual 109	java/lang/reflect/InvocationTargetException:getCause	()Ljava/lang/Throwable;
    //   1514: athrow
    //   1515: ldc 124
    //   1517: sipush 128
    //   1520: iconst_2
    //   1521: invokestatic 79	xxxxxx/uxxxxx:bb00620062bb0062b0062b0062	(Ljava/lang/String;CC)Ljava/lang/String;
    //   1524: wide
    //   1528: iconst_3
    //   1529: anewarray 45	java/lang/Class
    //   1532: wide
    //   1536: wide
    //   1540: iconst_0
    //   1541: ldc 29
    //   1543: aastore
    //   1544: wide
    //   1548: iconst_1
    //   1549: getstatic 51	java/lang/Character:TYPE	Ljava/lang/Class;
    //   1552: aastore
    //   1553: wide
    //   1557: iconst_2
    //   1558: getstatic 51	java/lang/Character:TYPE	Ljava/lang/Class;
    //   1561: aastore
    //   1562: ldc 53
    //   1564: wide
    //   1568: wide
    //   1572: invokevirtual 57	java/lang/Class:getMethod	(Ljava/lang/String;[Ljava/lang/Class;)Ljava/lang/reflect/Method;
    //   1575: wide
    //   1579: iconst_3
    //   1580: anewarray 4	java/lang/Object
    //   1583: wide
    //   1587: wide
    //   1591: iconst_0
    //   1592: ldc 126
    //   1594: aastore
    //   1595: wide
    //   1599: iconst_1
    //   1600: sipush 182
    //   1603: invokestatic 63	java/lang/Character:valueOf	(C)Ljava/lang/Character;
    //   1606: aastore
    //   1607: wide
    //   1611: iconst_2
    //   1612: iconst_4
    //   1613: invokestatic 63	java/lang/Character:valueOf	(C)Ljava/lang/Character;
    //   1616: aastore
    //   1617: wide
    //   1621: aconst_null
    //   1622: wide
    //   1626: invokevirtual 69	java/lang/reflect/Method:invoke	(Ljava/lang/Object;[Ljava/lang/Object;)Ljava/lang/Object;
    //   1629: wide
    //   1633: aload_0
    //   1634: wide
    //   1638: checkcast 29	java/lang/String
    //   1641: invokevirtual 93	java/lang/String:equals	(Ljava/lang/Object;)Z
    //   1644: ifeq -1380 -> 264
    //   1647: iconst_1
    //   1648: istore 7
    //   1650: goto -1383 -> 267
    //   1653: wide
    //   1657: wide
    //   1661: invokevirtual 109	java/lang/reflect/InvocationTargetException:getCause	()Ljava/lang/Throwable;
    //   1664: athrow
    //   1665: ldc -128
    //   1667: sipush 152
    //   1670: iconst_5
    //   1671: invokestatic 79	xxxxxx/uxxxxx:bb00620062bb0062b0062b0062	(Ljava/lang/String;CC)Ljava/lang/String;
    //   1674: wide
    //   1678: iconst_4
    //   1679: anewarray 45	java/lang/Class
    //   1682: wide
    //   1686: wide
    //   1690: iconst_0
    //   1691: ldc 29
    //   1693: aastore
    //   1694: wide
    //   1698: iconst_1
    //   1699: getstatic 51	java/lang/Character:TYPE	Ljava/lang/Class;
    //   1702: aastore
    //   1703: wide
    //   1707: iconst_2
    //   1708: getstatic 51	java/lang/Character:TYPE	Ljava/lang/Class;
    //   1711: aastore
    //   1712: wide
    //   1716: iconst_3
    //   1717: getstatic 51	java/lang/Character:TYPE	Ljava/lang/Class;
    //   1720: aastore
    //   1721: ldc 53
    //   1723: wide
    //   1727: wide
    //   1731: invokevirtual 57	java/lang/Class:getMethod	(Ljava/lang/String;[Ljava/lang/Class;)Ljava/lang/reflect/Method;
    //   1734: wide
    //   1738: iconst_4
    //   1739: anewarray 4	java/lang/Object
    //   1742: wide
    //   1746: wide
    //   1750: iconst_0
    //   1751: ldc -126
    //   1753: aastore
    //   1754: wide
    //   1758: iconst_1
    //   1759: sipush 229
    //   1762: invokestatic 63	java/lang/Character:valueOf	(C)Ljava/lang/Character;
    //   1765: aastore
    //   1766: wide
    //   1770: iconst_2
    //   1771: bipush 30
    //   1773: invokestatic 63	java/lang/Character:valueOf	(C)Ljava/lang/Character;
    //   1776: aastore
    //   1777: wide
    //   1781: iconst_3
    //   1782: iconst_2
    //   1783: invokestatic 63	java/lang/Character:valueOf	(C)Ljava/lang/Character;
    //   1786: aastore
    //   1787: wide
    //   1791: aconst_null
    //   1792: wide
    //   1796: invokevirtual 69	java/lang/reflect/Method:invoke	(Ljava/lang/Object;[Ljava/lang/Object;)Ljava/lang/Object;
    //   1799: wide
    //   1803: aload_0
    //   1804: wide
    //   1808: checkcast 29	java/lang/String
    //   1811: invokevirtual 93	java/lang/String:equals	(Ljava/lang/Object;)Z
    //   1814: ifeq -1550 -> 264
    //   1817: iconst_2
    //   1818: istore 7
    //   1820: goto -1553 -> 267
    //   1823: ldc -124
    //   1825: sipush 136
    //   1828: bipush 79
    //   1830: iconst_1
    //   1831: invokestatic 43	xxxxxx/uxxxxx:bbbb0062b0062b0062b0062	(Ljava/lang/String;CCC)Ljava/lang/String;
    //   1834: astore -78
    //   1836: iconst_3
    //   1837: anewarray 45	java/lang/Class
    //   1840: astore -77
    //   1842: aload -77
    //   1844: iconst_0
    //   1845: ldc 29
    //   1847: aastore
    //   1848: aload -77
    //   1850: iconst_1
    //   1851: getstatic 51	java/lang/Character:TYPE	Ljava/lang/Class;
    //   1854: aastore
    //   1855: aload -77
    //   1857: iconst_2
    //   1858: getstatic 51	java/lang/Character:TYPE	Ljava/lang/Class;
    //   1861: aastore
    //   1862: ldc 53
    //   1864: aload -78
    //   1866: aload -77
    //   1868: invokevirtual 57	java/lang/Class:getMethod	(Ljava/lang/String;[Ljava/lang/Class;)Ljava/lang/reflect/Method;
    //   1871: astore -76
    //   1873: iconst_3
    //   1874: anewarray 4	java/lang/Object
    //   1877: astore -75
    //   1879: aload -75
    //   1881: iconst_0
    //   1882: ldc -122
    //   1884: aastore
    //   1885: aload -75
    //   1887: iconst_1
    //   1888: bipush 83
    //   1890: invokestatic 63	java/lang/Character:valueOf	(C)Ljava/lang/Character;
    //   1893: aastore
    //   1894: aload -75
    //   1896: iconst_2
    //   1897: iconst_0
    //   1898: invokestatic 63	java/lang/Character:valueOf	(C)Ljava/lang/Character;
    //   1901: aastore
    //   1902: aload -76
    //   1904: aconst_null
    //   1905: aload -75
    //   1907: invokevirtual 69	java/lang/reflect/Method:invoke	(Ljava/lang/Object;[Ljava/lang/Object;)Ljava/lang/Object;
    //   1910: astore -73
    //   1912: aload -73
    //   1914: checkcast 29	java/lang/String
    //   1917: areturn
    //   1918: astore -74
    //   1920: aload -74
    //   1922: invokevirtual 109	java/lang/reflect/InvocationTargetException:getCause	()Ljava/lang/Throwable;
    //   1925: athrow
    //   1926: ldc -120
    //   1928: bipush 13
    //   1930: iconst_0
    //   1931: invokestatic 79	xxxxxx/uxxxxx:bb00620062bb0062b0062b0062	(Ljava/lang/String;CC)Ljava/lang/String;
    //   1934: astore -84
    //   1936: iconst_4
    //   1937: anewarray 45	java/lang/Class
    //   1940: astore -83
    //   1942: aload -83
    //   1944: iconst_0
    //   1945: ldc 29
    //   1947: aastore
    //   1948: aload -83
    //   1950: iconst_1
    //   1951: getstatic 51	java/lang/Character:TYPE	Ljava/lang/Class;
    //   1954: aastore
    //   1955: aload -83
    //   1957: iconst_2
    //   1958: getstatic 51	java/lang/Character:TYPE	Ljava/lang/Class;
    //   1961: aastore
    //   1962: aload -83
    //   1964: iconst_3
    //   1965: getstatic 51	java/lang/Character:TYPE	Ljava/lang/Class;
    //   1968: aastore
    //   1969: ldc 53
    //   1971: aload -84
    //   1973: aload -83
    //   1975: invokevirtual 57	java/lang/Class:getMethod	(Ljava/lang/String;[Ljava/lang/Class;)Ljava/lang/reflect/Method;
    //   1978: astore -82
    //   1980: iconst_4
    //   1981: anewarray 4	java/lang/Object
    //   1984: astore -81
    //   1986: aload -81
    //   1988: iconst_0
    //   1989: ldc -118
    //   1991: aastore
    //   1992: aload -81
    //   1994: iconst_1
    //   1995: sipush 203
    //   1998: invokestatic 63	java/lang/Character:valueOf	(C)Ljava/lang/Character;
    //   2001: aastore
    //   2002: aload -81
    //   2004: iconst_2
    //   2005: bipush 67
    //   2007: invokestatic 63	java/lang/Character:valueOf	(C)Ljava/lang/Character;
    //   2010: aastore
    //   2011: aload -81
    //   2013: iconst_3
    //   2014: iconst_2
    //   2015: invokestatic 63	java/lang/Character:valueOf	(C)Ljava/lang/Character;
    //   2018: aastore
    //   2019: aload -82
    //   2021: aconst_null
    //   2022: aload -81
    //   2024: invokevirtual 69	java/lang/reflect/Method:invoke	(Ljava/lang/Object;[Ljava/lang/Object;)Ljava/lang/Object;
    //   2027: astore -79
    //   2029: aload -79
    //   2031: checkcast 29	java/lang/String
    //   2034: areturn
    //   2035: ldc -116
    //   2037: sipush 144
    //   2040: iconst_4
    //   2041: invokestatic 79	xxxxxx/uxxxxx:bb00620062bb0062b0062b0062	(Ljava/lang/String;CC)Ljava/lang/String;
    //   2044: astore -90
    //   2046: iconst_4
    //   2047: anewarray 45	java/lang/Class
    //   2050: astore -89
    //   2052: aload -89
    //   2054: iconst_0
    //   2055: ldc 29
    //   2057: aastore
    //   2058: aload -89
    //   2060: iconst_1
    //   2061: getstatic 51	java/lang/Character:TYPE	Ljava/lang/Class;
    //   2064: aastore
    //   2065: aload -89
    //   2067: iconst_2
    //   2068: getstatic 51	java/lang/Character:TYPE	Ljava/lang/Class;
    //   2071: aastore
    //   2072: aload -89
    //   2074: iconst_3
    //   2075: getstatic 51	java/lang/Character:TYPE	Ljava/lang/Class;
    //   2078: aastore
    //   2079: ldc 53
    //   2081: aload -90
    //   2083: aload -89
    //   2085: invokevirtual 57	java/lang/Class:getMethod	(Ljava/lang/String;[Ljava/lang/Class;)Ljava/lang/reflect/Method;
    //   2088: astore -88
    //   2090: iconst_4
    //   2091: anewarray 4	java/lang/Object
    //   2094: astore -87
    //   2096: aload -87
    //   2098: iconst_0
    //   2099: ldc -114
    //   2101: aastore
    //   2102: aload -87
    //   2104: iconst_1
    //   2105: sipush 236
    //   2108: invokestatic 63	java/lang/Character:valueOf	(C)Ljava/lang/Character;
    //   2111: aastore
    //   2112: aload -87
    //   2114: iconst_2
    //   2115: bipush 59
    //   2117: invokestatic 63	java/lang/Character:valueOf	(C)Ljava/lang/Character;
    //   2120: aastore
    //   2121: aload -87
    //   2123: iconst_3
    //   2124: iconst_1
    //   2125: invokestatic 63	java/lang/Character:valueOf	(C)Ljava/lang/Character;
    //   2128: aastore
    //   2129: aload -88
    //   2131: aconst_null
    //   2132: aload -87
    //   2134: invokevirtual 69	java/lang/reflect/Method:invoke	(Ljava/lang/Object;[Ljava/lang/Object;)Ljava/lang/Object;
    //   2137: astore -85
    //   2139: aload -85
    //   2141: checkcast 29	java/lang/String
    //   2144: areturn
    //   2145: astore -86
    //   2147: aload -86
    //   2149: invokevirtual 109	java/lang/reflect/InvocationTargetException:getCause	()Ljava/lang/Throwable;
    //   2152: athrow
    //   2153: ldc -112
    //   2155: sipush 186
    //   2158: iconst_4
    //   2159: invokestatic 79	xxxxxx/uxxxxx:bb00620062bb0062b0062b0062	(Ljava/lang/String;CC)Ljava/lang/String;
    //   2162: wide
    //   2166: iconst_3
    //   2167: anewarray 45	java/lang/Class
    //   2170: wide
    //   2174: wide
    //   2178: iconst_0
    //   2179: ldc 29
    //   2181: aastore
    //   2182: wide
    //   2186: iconst_1
    //   2187: getstatic 51	java/lang/Character:TYPE	Ljava/lang/Class;
    //   2190: aastore
    //   2191: wide
    //   2195: iconst_2
    //   2196: getstatic 51	java/lang/Character:TYPE	Ljava/lang/Class;
    //   2199: aastore
    //   2200: ldc 53
    //   2202: wide
    //   2206: wide
    //   2210: invokevirtual 57	java/lang/Class:getMethod	(Ljava/lang/String;[Ljava/lang/Class;)Ljava/lang/reflect/Method;
    //   2213: wide
    //   2217: iconst_3
    //   2218: anewarray 4	java/lang/Object
    //   2221: wide
    //   2225: wide
    //   2229: iconst_0
    //   2230: ldc 120
    //   2232: aastore
    //   2233: wide
    //   2237: iconst_1
    //   2238: bipush 79
    //   2240: invokestatic 63	java/lang/Character:valueOf	(C)Ljava/lang/Character;
    //   2243: aastore
    //   2244: wide
    //   2248: iconst_2
    //   2249: iconst_5
    //   2250: invokestatic 63	java/lang/Character:valueOf	(C)Ljava/lang/Character;
    //   2253: aastore
    //   2254: wide
    //   2258: aconst_null
    //   2259: wide
    //   2263: invokevirtual 69	java/lang/reflect/Method:invoke	(Ljava/lang/Object;[Ljava/lang/Object;)Ljava/lang/Object;
    //   2266: wide
    //   2270: aload_0
    //   2271: wide
    //   2275: checkcast 29	java/lang/String
    //   2278: invokevirtual 93	java/lang/String:equals	(Ljava/lang/Object;)Z
    //   2281: ifeq -2017 -> 264
    //   2284: bipush 26
    //   2286: istore 7
    //   2288: goto -2021 -> 267
    //   2291: ldc -110
    //   2293: sipush 142
    //   2296: iconst_4
    //   2297: invokestatic 79	xxxxxx/uxxxxx:bb00620062bb0062b0062b0062	(Ljava/lang/String;CC)Ljava/lang/String;
    //   2300: wide
    //   2304: iconst_3
    //   2305: anewarray 45	java/lang/Class
    //   2308: wide
    //   2312: wide
    //   2316: iconst_0
    //   2317: ldc 29
    //   2319: aastore
    //   2320: wide
    //   2324: iconst_1
    //   2325: getstatic 51	java/lang/Character:TYPE	Ljava/lang/Class;
    //   2328: aastore
    //   2329: wide
    //   2333: iconst_2
    //   2334: getstatic 51	java/lang/Character:TYPE	Ljava/lang/Class;
    //   2337: aastore
    //   2338: ldc 53
    //   2340: wide
    //   2344: wide
    //   2348: invokevirtual 57	java/lang/Class:getMethod	(Ljava/lang/String;[Ljava/lang/Class;)Ljava/lang/reflect/Method;
    //   2351: wide
    //   2355: iconst_3
    //   2356: anewarray 4	java/lang/Object
    //   2359: wide
    //   2363: wide
    //   2367: iconst_0
    //   2368: ldc -108
    //   2370: aastore
    //   2371: wide
    //   2375: iconst_1
    //   2376: sipush 150
    //   2379: invokestatic 63	java/lang/Character:valueOf	(C)Ljava/lang/Character;
    //   2382: aastore
    //   2383: wide
    //   2387: iconst_2
    //   2388: iconst_4
    //   2389: invokestatic 63	java/lang/Character:valueOf	(C)Ljava/lang/Character;
    //   2392: aastore
    //   2393: wide
    //   2397: aconst_null
    //   2398: wide
    //   2402: invokevirtual 69	java/lang/reflect/Method:invoke	(Ljava/lang/Object;[Ljava/lang/Object;)Ljava/lang/Object;
    //   2405: wide
    //   2409: aload_0
    //   2410: wide
    //   2414: checkcast 29	java/lang/String
    //   2417: invokevirtual 93	java/lang/String:equals	(Ljava/lang/Object;)Z
    //   2420: ifeq -2156 -> 264
    //   2423: bipush 27
    //   2425: istore 7
    //   2427: goto -2160 -> 267
    //   2430: ldc -106
    //   2432: sipush 190
    //   2435: iconst_4
    //   2436: invokestatic 79	xxxxxx/uxxxxx:bb00620062bb0062b0062b0062	(Ljava/lang/String;CC)Ljava/lang/String;
    //   2439: astore -96
    //   2441: iconst_4
    //   2442: anewarray 45	java/lang/Class
    //   2445: astore -95
    //   2447: aload -95
    //   2449: iconst_0
    //   2450: ldc 29
    //   2452: aastore
    //   2453: aload -95
    //   2455: iconst_1
    //   2456: getstatic 51	java/lang/Character:TYPE	Ljava/lang/Class;
    //   2459: aastore
    //   2460: aload -95
    //   2462: iconst_2
    //   2463: getstatic 51	java/lang/Character:TYPE	Ljava/lang/Class;
    //   2466: aastore
    //   2467: aload -95
    //   2469: iconst_3
    //   2470: getstatic 51	java/lang/Character:TYPE	Ljava/lang/Class;
    //   2473: aastore
    //   2474: ldc 53
    //   2476: aload -96
    //   2478: aload -95
    //   2480: invokevirtual 57	java/lang/Class:getMethod	(Ljava/lang/String;[Ljava/lang/Class;)Ljava/lang/reflect/Method;
    //   2483: astore -94
    //   2485: iconst_4
    //   2486: anewarray 4	java/lang/Object
    //   2489: astore -93
    //   2491: aload -93
    //   2493: iconst_0
    //   2494: ldc -104
    //   2496: aastore
    //   2497: aload -93
    //   2499: iconst_1
    //   2500: bipush 65
    //   2502: invokestatic 63	java/lang/Character:valueOf	(C)Ljava/lang/Character;
    //   2505: aastore
    //   2506: aload -93
    //   2508: iconst_2
    //   2509: sipush 255
    //   2512: invokestatic 63	java/lang/Character:valueOf	(C)Ljava/lang/Character;
    //   2515: aastore
    //   2516: aload -93
    //   2518: iconst_3
    //   2519: iconst_3
    //   2520: invokestatic 63	java/lang/Character:valueOf	(C)Ljava/lang/Character;
    //   2523: aastore
    //   2524: aload -94
    //   2526: aconst_null
    //   2527: aload -93
    //   2529: invokevirtual 69	java/lang/reflect/Method:invoke	(Ljava/lang/Object;[Ljava/lang/Object;)Ljava/lang/Object;
    //   2532: astore -91
    //   2534: aload -91
    //   2536: checkcast 29	java/lang/String
    //   2539: areturn
    //   2540: ldc -102
    //   2542: bipush 121
    //   2544: iconst_0
    //   2545: invokestatic 79	xxxxxx/uxxxxx:bb00620062bb0062b0062b0062	(Ljava/lang/String;CC)Ljava/lang/String;
    //   2548: astore -102
    //   2550: iconst_4
    //   2551: anewarray 45	java/lang/Class
    //   2554: astore -101
    //   2556: aload -101
    //   2558: iconst_0
    //   2559: ldc 29
    //   2561: aastore
    //   2562: aload -101
    //   2564: iconst_1
    //   2565: getstatic 51	java/lang/Character:TYPE	Ljava/lang/Class;
    //   2568: aastore
    //   2569: aload -101
    //   2571: iconst_2
    //   2572: getstatic 51	java/lang/Character:TYPE	Ljava/lang/Class;
    //   2575: aastore
    //   2576: aload -101
    //   2578: iconst_3
    //   2579: getstatic 51	java/lang/Character:TYPE	Ljava/lang/Class;
    //   2582: aastore
    //   2583: ldc 53
    //   2585: aload -102
    //   2587: aload -101
    //   2589: invokevirtual 57	java/lang/Class:getMethod	(Ljava/lang/String;[Ljava/lang/Class;)Ljava/lang/reflect/Method;
    //   2592: astore -100
    //   2594: iconst_4
    //   2595: anewarray 4	java/lang/Object
    //   2598: astore -99
    //   2600: aload -99
    //   2602: iconst_0
    //   2603: ldc -100
    //   2605: aastore
    //   2606: aload -99
    //   2608: iconst_1
    //   2609: bipush 24
    //   2611: invokestatic 63	java/lang/Character:valueOf	(C)Ljava/lang/Character;
    //   2614: aastore
    //   2615: aload -99
    //   2617: iconst_2
    //   2618: sipush 129
    //   2621: invokestatic 63	java/lang/Character:valueOf	(C)Ljava/lang/Character;
    //   2624: aastore
    //   2625: aload -99
    //   2627: iconst_3
    //   2628: iconst_3
    //   2629: invokestatic 63	java/lang/Character:valueOf	(C)Ljava/lang/Character;
    //   2632: aastore
    //   2633: aload -100
    //   2635: aconst_null
    //   2636: aload -99
    //   2638: invokevirtual 69	java/lang/reflect/Method:invoke	(Ljava/lang/Object;[Ljava/lang/Object;)Ljava/lang/Object;
    //   2641: astore -97
    //   2643: aload -97
    //   2645: checkcast 29	java/lang/String
    //   2648: areturn
    //   2649: astore -98
    //   2651: aload -98
    //   2653: invokevirtual 109	java/lang/reflect/InvocationTargetException:getCause	()Ljava/lang/Throwable;
    //   2656: athrow
    //   2657: ldc -98
    //   2659: bipush 42
    //   2661: sipush 225
    //   2664: iconst_0
    //   2665: invokestatic 43	xxxxxx/uxxxxx:bbbb0062b0062b0062b0062	(Ljava/lang/String;CCC)Ljava/lang/String;
    //   2668: astore -108
    //   2670: iconst_3
    //   2671: anewarray 45	java/lang/Class
    //   2674: astore -107
    //   2676: aload -107
    //   2678: iconst_0
    //   2679: ldc 29
    //   2681: aastore
    //   2682: aload -107
    //   2684: iconst_1
    //   2685: getstatic 51	java/lang/Character:TYPE	Ljava/lang/Class;
    //   2688: aastore
    //   2689: aload -107
    //   2691: iconst_2
    //   2692: getstatic 51	java/lang/Character:TYPE	Ljava/lang/Class;
    //   2695: aastore
    //   2696: ldc 53
    //   2698: aload -108
    //   2700: aload -107
    //   2702: invokevirtual 57	java/lang/Class:getMethod	(Ljava/lang/String;[Ljava/lang/Class;)Ljava/lang/reflect/Method;
    //   2705: astore -106
    //   2707: iconst_3
    //   2708: anewarray 4	java/lang/Object
    //   2711: astore -105
    //   2713: aload -105
    //   2715: iconst_0
    //   2716: ldc -96
    //   2718: aastore
    //   2719: aload -105
    //   2721: iconst_1
    //   2722: sipush 221
    //   2725: invokestatic 63	java/lang/Character:valueOf	(C)Ljava/lang/Character;
    //   2728: aastore
    //   2729: aload -105
    //   2731: iconst_2
    //   2732: iconst_4
    //   2733: invokestatic 63	java/lang/Character:valueOf	(C)Ljava/lang/Character;
    //   2736: aastore
    //   2737: aload -106
    //   2739: aconst_null
    //   2740: aload -105
    //   2742: invokevirtual 69	java/lang/reflect/Method:invoke	(Ljava/lang/Object;[Ljava/lang/Object;)Ljava/lang/Object;
    //   2745: astore -103
    //   2747: aload -103
    //   2749: checkcast 29	java/lang/String
    //   2752: areturn
    //   2753: ldc -94
    //   2755: bipush 70
    //   2757: bipush 26
    //   2759: iconst_0
    //   2760: invokestatic 43	xxxxxx/uxxxxx:bbbb0062b0062b0062b0062	(Ljava/lang/String;CCC)Ljava/lang/String;
    //   2763: astore -114
    //   2765: iconst_4
    //   2766: anewarray 45	java/lang/Class
    //   2769: astore -113
    //   2771: aload -113
    //   2773: iconst_0
    //   2774: ldc 29
    //   2776: aastore
    //   2777: aload -113
    //   2779: iconst_1
    //   2780: getstatic 51	java/lang/Character:TYPE	Ljava/lang/Class;
    //   2783: aastore
    //   2784: aload -113
    //   2786: iconst_2
    //   2787: getstatic 51	java/lang/Character:TYPE	Ljava/lang/Class;
    //   2790: aastore
    //   2791: aload -113
    //   2793: iconst_3
    //   2794: getstatic 51	java/lang/Character:TYPE	Ljava/lang/Class;
    //   2797: aastore
    //   2798: ldc 53
    //   2800: aload -114
    //   2802: aload -113
    //   2804: invokevirtual 57	java/lang/Class:getMethod	(Ljava/lang/String;[Ljava/lang/Class;)Ljava/lang/reflect/Method;
    //   2807: astore -112
    //   2809: iconst_4
    //   2810: anewarray 4	java/lang/Object
    //   2813: astore -111
    //   2815: aload -111
    //   2817: iconst_0
    //   2818: ldc -92
    //   2820: aastore
    //   2821: aload -111
    //   2823: iconst_1
    //   2824: bipush 65
    //   2826: invokestatic 63	java/lang/Character:valueOf	(C)Ljava/lang/Character;
    //   2829: aastore
    //   2830: aload -111
    //   2832: iconst_2
    //   2833: bipush 121
    //   2835: invokestatic 63	java/lang/Character:valueOf	(C)Ljava/lang/Character;
    //   2838: aastore
    //   2839: aload -111
    //   2841: iconst_3
    //   2842: iconst_1
    //   2843: invokestatic 63	java/lang/Character:valueOf	(C)Ljava/lang/Character;
    //   2846: aastore
    //   2847: aload -112
    //   2849: aconst_null
    //   2850: aload -111
    //   2852: invokevirtual 69	java/lang/reflect/Method:invoke	(Ljava/lang/Object;[Ljava/lang/Object;)Ljava/lang/Object;
    //   2855: astore -109
    //   2857: aload -109
    //   2859: checkcast 29	java/lang/String
    //   2862: areturn
    //   2863: ldc -124
    //   2865: sipush 144
    //   2868: sipush 167
    //   2871: iconst_0
    //   2872: invokestatic 43	xxxxxx/uxxxxx:bbbb0062b0062b0062b0062	(Ljava/lang/String;CCC)Ljava/lang/String;
    //   2875: wide
    //   2879: iconst_3
    //   2880: anewarray 45	java/lang/Class
    //   2883: wide
    //   2887: wide
    //   2891: iconst_0
    //   2892: ldc 29
    //   2894: aastore
    //   2895: wide
    //   2899: iconst_1
    //   2900: getstatic 51	java/lang/Character:TYPE	Ljava/lang/Class;
    //   2903: aastore
    //   2904: wide
    //   2908: iconst_2
    //   2909: getstatic 51	java/lang/Character:TYPE	Ljava/lang/Class;
    //   2912: aastore
    //   2913: ldc 53
    //   2915: wide
    //   2919: wide
    //   2923: invokevirtual 57	java/lang/Class:getMethod	(Ljava/lang/String;[Ljava/lang/Class;)Ljava/lang/reflect/Method;
    //   2926: wide
    //   2930: iconst_3
    //   2931: anewarray 4	java/lang/Object
    //   2934: wide
    //   2938: wide
    //   2942: iconst_0
    //   2943: ldc -90
    //   2945: aastore
    //   2946: wide
    //   2950: iconst_1
    //   2951: bipush 11
    //   2953: invokestatic 63	java/lang/Character:valueOf	(C)Ljava/lang/Character;
    //   2956: aastore
    //   2957: wide
    //   2961: iconst_2
    //   2962: iconst_0
    //   2963: invokestatic 63	java/lang/Character:valueOf	(C)Ljava/lang/Character;
    //   2966: aastore
    //   2967: wide
    //   2971: aconst_null
    //   2972: wide
    //   2976: invokevirtual 69	java/lang/reflect/Method:invoke	(Ljava/lang/Object;[Ljava/lang/Object;)Ljava/lang/Object;
    //   2979: wide
    //   2983: aload_0
    //   2984: wide
    //   2988: checkcast 29	java/lang/String
    //   2991: invokevirtual 93	java/lang/String:equals	(Ljava/lang/Object;)Z
    //   2994: ifeq -2730 -> 264
    //   2997: bipush 9
    //   2999: istore 7
    //   3001: goto -2734 -> 267
    //   3004: ldc -88
    //   3006: sipush 138
    //   3009: iconst_1
    //   3010: invokestatic 79	xxxxxx/uxxxxx:bb00620062bb0062b0062b0062	(Ljava/lang/String;CC)Ljava/lang/String;
    //   3013: wide
    //   3017: iconst_3
    //   3018: anewarray 45	java/lang/Class
    //   3021: wide
    //   3025: wide
    //   3029: iconst_0
    //   3030: ldc 29
    //   3032: aastore
    //   3033: wide
    //   3037: iconst_1
    //   3038: getstatic 51	java/lang/Character:TYPE	Ljava/lang/Class;
    //   3041: aastore
    //   3042: wide
    //   3046: iconst_2
    //   3047: getstatic 51	java/lang/Character:TYPE	Ljava/lang/Class;
    //   3050: aastore
    //   3051: ldc 53
    //   3053: wide
    //   3057: wide
    //   3061: invokevirtual 57	java/lang/Class:getMethod	(Ljava/lang/String;[Ljava/lang/Class;)Ljava/lang/reflect/Method;
    //   3064: wide
    //   3068: iconst_3
    //   3069: anewarray 4	java/lang/Object
    //   3072: wide
    //   3076: wide
    //   3080: iconst_0
    //   3081: ldc -86
    //   3083: aastore
    //   3084: wide
    //   3088: iconst_1
    //   3089: sipush 211
    //   3092: invokestatic 63	java/lang/Character:valueOf	(C)Ljava/lang/Character;
    //   3095: aastore
    //   3096: wide
    //   3100: iconst_2
    //   3101: iconst_5
    //   3102: invokestatic 63	java/lang/Character:valueOf	(C)Ljava/lang/Character;
    //   3105: aastore
    //   3106: wide
    //   3110: aconst_null
    //   3111: wide
    //   3115: invokevirtual 69	java/lang/reflect/Method:invoke	(Ljava/lang/Object;[Ljava/lang/Object;)Ljava/lang/Object;
    //   3118: wide
    //   3122: aload_0
    //   3123: wide
    //   3127: checkcast 29	java/lang/String
    //   3130: invokevirtual 93	java/lang/String:equals	(Ljava/lang/Object;)Z
    //   3133: ifeq -2869 -> 264
    //   3136: bipush 30
    //   3138: istore 7
    //   3140: goto -2873 -> 267
    //   3143: astore -80
    //   3145: aload -80
    //   3147: invokevirtual 109	java/lang/reflect/InvocationTargetException:getCause	()Ljava/lang/Throwable;
    //   3150: athrow
    //   3151: ldc -84
    //   3153: bipush 81
    //   3155: bipush 73
    //   3157: iconst_0
    //   3158: invokestatic 43	xxxxxx/uxxxxx:bbbb0062b0062b0062b0062	(Ljava/lang/String;CCC)Ljava/lang/String;
    //   3161: astore -120
    //   3163: iconst_4
    //   3164: anewarray 45	java/lang/Class
    //   3167: astore -119
    //   3169: aload -119
    //   3171: iconst_0
    //   3172: ldc 29
    //   3174: aastore
    //   3175: aload -119
    //   3177: iconst_1
    //   3178: getstatic 51	java/lang/Character:TYPE	Ljava/lang/Class;
    //   3181: aastore
    //   3182: aload -119
    //   3184: iconst_2
    //   3185: getstatic 51	java/lang/Character:TYPE	Ljava/lang/Class;
    //   3188: aastore
    //   3189: aload -119
    //   3191: iconst_3
    //   3192: getstatic 51	java/lang/Character:TYPE	Ljava/lang/Class;
    //   3195: aastore
    //   3196: ldc 53
    //   3198: aload -120
    //   3200: aload -119
    //   3202: invokevirtual 57	java/lang/Class:getMethod	(Ljava/lang/String;[Ljava/lang/Class;)Ljava/lang/reflect/Method;
    //   3205: astore -118
    //   3207: iconst_4
    //   3208: anewarray 4	java/lang/Object
    //   3211: astore -117
    //   3213: aload -117
    //   3215: iconst_0
    //   3216: ldc -82
    //   3218: aastore
    //   3219: aload -117
    //   3221: iconst_1
    //   3222: sipush 193
    //   3225: invokestatic 63	java/lang/Character:valueOf	(C)Ljava/lang/Character;
    //   3228: aastore
    //   3229: aload -117
    //   3231: iconst_2
    //   3232: sipush 220
    //   3235: invokestatic 63	java/lang/Character:valueOf	(C)Ljava/lang/Character;
    //   3238: aastore
    //   3239: aload -117
    //   3241: iconst_3
    //   3242: iconst_1
    //   3243: invokestatic 63	java/lang/Character:valueOf	(C)Ljava/lang/Character;
    //   3246: aastore
    //   3247: aload -118
    //   3249: aconst_null
    //   3250: aload -117
    //   3252: invokevirtual 69	java/lang/reflect/Method:invoke	(Ljava/lang/Object;[Ljava/lang/Object;)Ljava/lang/Object;
    //   3255: astore -115
    //   3257: aload -115
    //   3259: checkcast 29	java/lang/String
    //   3262: areturn
    //   3263: ldc -80
    //   3265: sipush 178
    //   3268: bipush 89
    //   3270: iconst_2
    //   3271: invokestatic 43	xxxxxx/uxxxxx:bbbb0062b0062b0062b0062	(Ljava/lang/String;CCC)Ljava/lang/String;
    //   3274: astore -126
    //   3276: iconst_3
    //   3277: anewarray 45	java/lang/Class
    //   3280: astore -125
    //   3282: aload -125
    //   3284: iconst_0
    //   3285: ldc 29
    //   3287: aastore
    //   3288: aload -125
    //   3290: iconst_1
    //   3291: getstatic 51	java/lang/Character:TYPE	Ljava/lang/Class;
    //   3294: aastore
    //   3295: aload -125
    //   3297: iconst_2
    //   3298: getstatic 51	java/lang/Character:TYPE	Ljava/lang/Class;
    //   3301: aastore
    //   3302: ldc 53
    //   3304: aload -126
    //   3306: aload -125
    //   3308: invokevirtual 57	java/lang/Class:getMethod	(Ljava/lang/String;[Ljava/lang/Class;)Ljava/lang/reflect/Method;
    //   3311: astore -124
    //   3313: iconst_3
    //   3314: anewarray 4	java/lang/Object
    //   3317: astore -123
    //   3319: aload -123
    //   3321: iconst_0
    //   3322: ldc -78
    //   3324: aastore
    //   3325: aload -123
    //   3327: iconst_1
    //   3328: bipush 76
    //   3330: invokestatic 63	java/lang/Character:valueOf	(C)Ljava/lang/Character;
    //   3333: aastore
    //   3334: aload -123
    //   3336: iconst_2
    //   3337: iconst_0
    //   3338: invokestatic 63	java/lang/Character:valueOf	(C)Ljava/lang/Character;
    //   3341: aastore
    //   3342: aload -124
    //   3344: aconst_null
    //   3345: aload -123
    //   3347: invokevirtual 69	java/lang/reflect/Method:invoke	(Ljava/lang/Object;[Ljava/lang/Object;)Ljava/lang/Object;
    //   3350: astore -121
    //   3352: aload -121
    //   3354: checkcast 29	java/lang/String
    //   3357: areturn
    //   3358: ldc -76
    //   3360: sipush 237
    //   3363: iconst_4
    //   3364: invokestatic 79	xxxxxx/uxxxxx:bb00620062bb0062b0062b0062	(Ljava/lang/String;CC)Ljava/lang/String;
    //   3367: wide
    //   3371: iconst_3
    //   3372: anewarray 45	java/lang/Class
    //   3375: wide
    //   3379: wide
    //   3383: iconst_0
    //   3384: ldc 29
    //   3386: aastore
    //   3387: wide
    //   3391: iconst_1
    //   3392: getstatic 51	java/lang/Character:TYPE	Ljava/lang/Class;
    //   3395: aastore
    //   3396: wide
    //   3400: iconst_2
    //   3401: getstatic 51	java/lang/Character:TYPE	Ljava/lang/Class;
    //   3404: aastore
    //   3405: ldc 53
    //   3407: wide
    //   3411: wide
    //   3415: invokevirtual 57	java/lang/Class:getMethod	(Ljava/lang/String;[Ljava/lang/Class;)Ljava/lang/reflect/Method;
    //   3418: wide
    //   3422: iconst_3
    //   3423: anewarray 4	java/lang/Object
    //   3426: wide
    //   3430: wide
    //   3434: iconst_0
    //   3435: ldc -74
    //   3437: aastore
    //   3438: wide
    //   3442: iconst_1
    //   3443: sipush 199
    //   3446: invokestatic 63	java/lang/Character:valueOf	(C)Ljava/lang/Character;
    //   3449: aastore
    //   3450: wide
    //   3454: iconst_2
    //   3455: iconst_4
    //   3456: invokestatic 63	java/lang/Character:valueOf	(C)Ljava/lang/Character;
    //   3459: aastore
    //   3460: wide
    //   3464: aconst_null
    //   3465: wide
    //   3469: invokevirtual 69	java/lang/reflect/Method:invoke	(Ljava/lang/Object;[Ljava/lang/Object;)Ljava/lang/Object;
    //   3472: wide
    //   3476: aload_0
    //   3477: wide
    //   3481: checkcast 29	java/lang/String
    //   3484: invokevirtual 93	java/lang/String:equals	(Ljava/lang/Object;)Z
    //   3487: ifeq -3223 -> 264
    //   3490: bipush 10
    //   3492: istore 7
    //   3494: goto -3227 -> 267
    //   3497: wide
    //   3501: wide
    //   3505: invokevirtual 109	java/lang/reflect/InvocationTargetException:getCause	()Ljava/lang/Throwable;
    //   3508: athrow
    //   3509: ldc -72
    //   3511: bipush 10
    //   3513: bipush 125
    //   3515: iconst_1
    //   3516: invokestatic 43	xxxxxx/uxxxxx:bbbb0062b0062b0062b0062	(Ljava/lang/String;CCC)Ljava/lang/String;
    //   3519: wide
    //   3523: iconst_4
    //   3524: anewarray 45	java/lang/Class
    //   3527: wide
    //   3531: wide
    //   3535: iconst_0
    //   3536: ldc 29
    //   3538: aastore
    //   3539: wide
    //   3543: iconst_1
    //   3544: getstatic 51	java/lang/Character:TYPE	Ljava/lang/Class;
    //   3547: aastore
    //   3548: wide
    //   3552: iconst_2
    //   3553: getstatic 51	java/lang/Character:TYPE	Ljava/lang/Class;
    //   3556: aastore
    //   3557: wide
    //   3561: iconst_3
    //   3562: getstatic 51	java/lang/Character:TYPE	Ljava/lang/Class;
    //   3565: aastore
    //   3566: ldc 53
    //   3568: wide
    //   3572: wide
    //   3576: invokevirtual 57	java/lang/Class:getMethod	(Ljava/lang/String;[Ljava/lang/Class;)Ljava/lang/reflect/Method;
    //   3579: wide
    //   3583: iconst_4
    //   3584: anewarray 4	java/lang/Object
    //   3587: wide
    //   3591: wide
    //   3595: iconst_0
    //   3596: ldc -70
    //   3598: aastore
    //   3599: wide
    //   3603: iconst_1
    //   3604: sipush 180
    //   3607: invokestatic 63	java/lang/Character:valueOf	(C)Ljava/lang/Character;
    //   3610: aastore
    //   3611: wide
    //   3615: iconst_2
    //   3616: bipush 33
    //   3618: invokestatic 63	java/lang/Character:valueOf	(C)Ljava/lang/Character;
    //   3621: aastore
    //   3622: wide
    //   3626: iconst_3
    //   3627: iconst_0
    //   3628: invokestatic 63	java/lang/Character:valueOf	(C)Ljava/lang/Character;
    //   3631: aastore
    //   3632: wide
    //   3636: aconst_null
    //   3637: wide
    //   3641: invokevirtual 69	java/lang/reflect/Method:invoke	(Ljava/lang/Object;[Ljava/lang/Object;)Ljava/lang/Object;
    //   3644: wide
    //   3648: aload_0
    //   3649: wide
    //   3653: checkcast 29	java/lang/String
    //   3656: invokevirtual 93	java/lang/String:equals	(Ljava/lang/Object;)Z
    //   3659: ifeq -3395 -> 264
    //   3662: bipush 11
    //   3664: istore 7
    //   3666: goto -3399 -> 267
    //   3669: wide
    //   3673: wide
    //   3677: invokevirtual 109	java/lang/reflect/InvocationTargetException:getCause	()Ljava/lang/Throwable;
    //   3680: athrow
    //   3681: ldc -68
    //   3683: bipush 57
    //   3685: sipush 215
    //   3688: iconst_0
    //   3689: invokestatic 43	xxxxxx/uxxxxx:bbbb0062b0062b0062b0062	(Ljava/lang/String;CCC)Ljava/lang/String;
    //   3692: wide
    //   3696: iconst_4
    //   3697: anewarray 45	java/lang/Class
    //   3700: wide
    //   3704: wide
    //   3708: iconst_0
    //   3709: ldc 29
    //   3711: aastore
    //   3712: wide
    //   3716: iconst_1
    //   3717: getstatic 51	java/lang/Character:TYPE	Ljava/lang/Class;
    //   3720: aastore
    //   3721: wide
    //   3725: iconst_2
    //   3726: getstatic 51	java/lang/Character:TYPE	Ljava/lang/Class;
    //   3729: aastore
    //   3730: wide
    //   3734: iconst_3
    //   3735: getstatic 51	java/lang/Character:TYPE	Ljava/lang/Class;
    //   3738: aastore
    //   3739: ldc 53
    //   3741: wide
    //   3745: wide
    //   3749: invokevirtual 57	java/lang/Class:getMethod	(Ljava/lang/String;[Ljava/lang/Class;)Ljava/lang/reflect/Method;
    //   3752: wide
    //   3756: iconst_4
    //   3757: anewarray 4	java/lang/Object
    //   3760: wide
    //   3764: wide
    //   3768: iconst_0
    //   3769: ldc -66
    //   3771: aastore
    //   3772: wide
    //   3776: iconst_1
    //   3777: bipush 49
    //   3779: invokestatic 63	java/lang/Character:valueOf	(C)Ljava/lang/Character;
    //   3782: aastore
    //   3783: wide
    //   3787: iconst_2
    //   3788: bipush 121
    //   3790: invokestatic 63	java/lang/Character:valueOf	(C)Ljava/lang/Character;
    //   3793: aastore
    //   3794: wide
    //   3798: iconst_3
    //   3799: iconst_1
    //   3800: invokestatic 63	java/lang/Character:valueOf	(C)Ljava/lang/Character;
    //   3803: aastore
    //   3804: wide
    //   3808: aconst_null
    //   3809: wide
    //   3813: invokevirtual 69	java/lang/reflect/Method:invoke	(Ljava/lang/Object;[Ljava/lang/Object;)Ljava/lang/Object;
    //   3816: wide
    //   3820: aload_0
    //   3821: wide
    //   3825: checkcast 29	java/lang/String
    //   3828: invokevirtual 93	java/lang/String:equals	(Ljava/lang/Object;)Z
    //   3831: ifeq -3567 -> 264
    //   3834: bipush 12
    //   3836: istore 7
    //   3838: goto -3571 -> 267
    //   3841: wide
    //   3845: wide
    //   3849: invokevirtual 109	java/lang/reflect/InvocationTargetException:getCause	()Ljava/lang/Throwable;
    //   3852: athrow
    //   3853: wide
    //   3857: wide
    //   3861: invokevirtual 109	java/lang/reflect/InvocationTargetException:getCause	()Ljava/lang/Throwable;
    //   3864: athrow
    //   3865: ldc -64
    //   3867: bipush 10
    //   3869: bipush 116
    //   3871: iconst_1
    //   3872: invokestatic 43	xxxxxx/uxxxxx:bbbb0062b0062b0062b0062	(Ljava/lang/String;CCC)Ljava/lang/String;
    //   3875: wide
    //   3879: iconst_4
    //   3880: anewarray 45	java/lang/Class
    //   3883: wide
    //   3887: wide
    //   3891: iconst_0
    //   3892: ldc 29
    //   3894: aastore
    //   3895: wide
    //   3899: iconst_1
    //   3900: getstatic 51	java/lang/Character:TYPE	Ljava/lang/Class;
    //   3903: aastore
    //   3904: wide
    //   3908: iconst_2
    //   3909: getstatic 51	java/lang/Character:TYPE	Ljava/lang/Class;
    //   3912: aastore
    //   3913: wide
    //   3917: iconst_3
    //   3918: getstatic 51	java/lang/Character:TYPE	Ljava/lang/Class;
    //   3921: aastore
    //   3922: ldc 53
    //   3924: wide
    //   3928: wide
    //   3932: invokevirtual 57	java/lang/Class:getMethod	(Ljava/lang/String;[Ljava/lang/Class;)Ljava/lang/reflect/Method;
    //   3935: wide
    //   3939: iconst_4
    //   3940: anewarray 4	java/lang/Object
    //   3943: wide
    //   3947: wide
    //   3951: iconst_0
    //   3952: ldc -62
    //   3954: aastore
    //   3955: wide
    //   3959: iconst_1
    //   3960: bipush 41
    //   3962: invokestatic 63	java/lang/Character:valueOf	(C)Ljava/lang/Character;
    //   3965: aastore
    //   3966: wide
    //   3970: iconst_2
    //   3971: sipush 219
    //   3974: invokestatic 63	java/lang/Character:valueOf	(C)Ljava/lang/Character;
    //   3977: aastore
    //   3978: wide
    //   3982: iconst_3
    //   3983: iconst_2
    //   3984: invokestatic 63	java/lang/Character:valueOf	(C)Ljava/lang/Character;
    //   3987: aastore
    //   3988: wide
    //   3992: aconst_null
    //   3993: wide
    //   3997: invokevirtual 69	java/lang/reflect/Method:invoke	(Ljava/lang/Object;[Ljava/lang/Object;)Ljava/lang/Object;
    //   4000: wide
    //   4004: aload_0
    //   4005: wide
    //   4009: checkcast 29	java/lang/String
    //   4012: invokevirtual 93	java/lang/String:equals	(Ljava/lang/Object;)Z
    //   4015: ifeq -3751 -> 264
    //   4018: bipush 14
    //   4020: istore 7
    //   4022: goto -3755 -> 267
    //   4025: wide
    //   4029: wide
    //   4033: invokevirtual 109	java/lang/reflect/InvocationTargetException:getCause	()Ljava/lang/Throwable;
    //   4036: athrow
    //   4037: ldc -60
    //   4039: sipush 194
    //   4042: iconst_1
    //   4043: invokestatic 79	xxxxxx/uxxxxx:bb00620062bb0062b0062b0062	(Ljava/lang/String;CC)Ljava/lang/String;
    //   4046: astore 124
    //   4048: iconst_3
    //   4049: anewarray 45	java/lang/Class
    //   4052: astore 125
    //   4054: aload 125
    //   4056: iconst_0
    //   4057: ldc 29
    //   4059: aastore
    //   4060: aload 125
    //   4062: iconst_1
    //   4063: getstatic 51	java/lang/Character:TYPE	Ljava/lang/Class;
    //   4066: aastore
    //   4067: aload 125
    //   4069: iconst_2
    //   4070: getstatic 51	java/lang/Character:TYPE	Ljava/lang/Class;
    //   4073: aastore
    //   4074: ldc 53
    //   4076: aload 124
    //   4078: aload 125
    //   4080: invokevirtual 57	java/lang/Class:getMethod	(Ljava/lang/String;[Ljava/lang/Class;)Ljava/lang/reflect/Method;
    //   4083: astore 126
    //   4085: iconst_3
    //   4086: anewarray 4	java/lang/Object
    //   4089: astore 127
    //   4091: aload 127
    //   4093: iconst_0
    //   4094: ldc -58
    //   4096: aastore
    //   4097: aload 127
    //   4099: iconst_1
    //   4100: sipush 249
    //   4103: invokestatic 63	java/lang/Character:valueOf	(C)Ljava/lang/Character;
    //   4106: aastore
    //   4107: aload 127
    //   4109: iconst_2
    //   4110: iconst_4
    //   4111: invokestatic 63	java/lang/Character:valueOf	(C)Ljava/lang/Character;
    //   4114: aastore
    //   4115: aload 126
    //   4117: aconst_null
    //   4118: aload 127
    //   4120: invokevirtual 69	java/lang/reflect/Method:invoke	(Ljava/lang/Object;[Ljava/lang/Object;)Ljava/lang/Object;
    //   4123: astore -127
    //   4125: aload -127
    //   4127: checkcast 29	java/lang/String
    //   4130: areturn
    //   4131: astore -128
    //   4133: aload -128
    //   4135: invokevirtual 109	java/lang/reflect/InvocationTargetException:getCause	()Ljava/lang/Throwable;
    //   4138: athrow
    //   4139: ldc -56
    //   4141: sipush 223
    //   4144: iconst_4
    //   4145: invokestatic 79	xxxxxx/uxxxxx:bb00620062bb0062b0062b0062	(Ljava/lang/String;CC)Ljava/lang/String;
    //   4148: astore 116
    //   4150: iconst_3
    //   4151: anewarray 45	java/lang/Class
    //   4154: astore 117
    //   4156: aload 117
    //   4158: iconst_0
    //   4159: ldc 29
    //   4161: aastore
    //   4162: aload 117
    //   4164: iconst_1
    //   4165: getstatic 51	java/lang/Character:TYPE	Ljava/lang/Class;
    //   4168: aastore
    //   4169: aload 117
    //   4171: iconst_2
    //   4172: getstatic 51	java/lang/Character:TYPE	Ljava/lang/Class;
    //   4175: aastore
    //   4176: ldc 53
    //   4178: aload 116
    //   4180: aload 117
    //   4182: invokevirtual 57	java/lang/Class:getMethod	(Ljava/lang/String;[Ljava/lang/Class;)Ljava/lang/reflect/Method;
    //   4185: astore 118
    //   4187: iconst_3
    //   4188: anewarray 4	java/lang/Object
    //   4191: astore 119
    //   4193: aload 119
    //   4195: iconst_0
    //   4196: ldc -54
    //   4198: aastore
    //   4199: aload 119
    //   4201: iconst_1
    //   4202: bipush 106
    //   4204: invokestatic 63	java/lang/Character:valueOf	(C)Ljava/lang/Character;
    //   4207: aastore
    //   4208: aload 119
    //   4210: iconst_2
    //   4211: iconst_4
    //   4212: invokestatic 63	java/lang/Character:valueOf	(C)Ljava/lang/Character;
    //   4215: aastore
    //   4216: aload 118
    //   4218: aconst_null
    //   4219: aload 119
    //   4221: invokevirtual 69	java/lang/reflect/Method:invoke	(Ljava/lang/Object;[Ljava/lang/Object;)Ljava/lang/Object;
    //   4224: astore 121
    //   4226: aload 121
    //   4228: checkcast 29	java/lang/String
    //   4231: astore 122
    //   4233: getstatic 99	uuuuuu/rvrvrv:b0068hh006800680068hh0068	I
    //   4236: istore 123
    //   4238: iload 123
    //   4240: iload 123
    //   4242: getstatic 101	uuuuuu/rvrvrv:bh0068h006800680068hh0068	I
    //   4245: iadd
    //   4246: imul
    //   4247: getstatic 103	uuuuuu/rvrvrv:b00680068h006800680068hh0068	I
    //   4250: irem
    //   4251: tableswitch	default:+17->4268, 0:+-3594->657
    //   4268: bipush 27
    //   4270: putstatic 99	uuuuuu/rvrvrv:b0068hh006800680068hh0068	I
    //   4273: bipush 11
    //   4275: putstatic 101	uuuuuu/rvrvrv:bh0068h006800680068hh0068	I
    //   4278: aload 122
    //   4280: areturn
    //   4281: astore -60
    //   4283: aload -60
    //   4285: invokevirtual 109	java/lang/reflect/InvocationTargetException:getCause	()Ljava/lang/Throwable;
    //   4288: athrow
    //   4289: ldc -52
    //   4291: sipush 216
    //   4294: sipush 221
    //   4297: iconst_0
    //   4298: invokestatic 43	xxxxxx/uxxxxx:bbbb0062b0062b0062b0062	(Ljava/lang/String;CCC)Ljava/lang/String;
    //   4301: wide
    //   4305: iconst_4
    //   4306: anewarray 45	java/lang/Class
    //   4309: wide
    //   4313: wide
    //   4317: iconst_0
    //   4318: ldc 29
    //   4320: aastore
    //   4321: wide
    //   4325: iconst_1
    //   4326: getstatic 51	java/lang/Character:TYPE	Ljava/lang/Class;
    //   4329: aastore
    //   4330: wide
    //   4334: iconst_2
    //   4335: getstatic 51	java/lang/Character:TYPE	Ljava/lang/Class;
    //   4338: aastore
    //   4339: wide
    //   4343: iconst_3
    //   4344: getstatic 51	java/lang/Character:TYPE	Ljava/lang/Class;
    //   4347: aastore
    //   4348: ldc 53
    //   4350: wide
    //   4354: wide
    //   4358: invokevirtual 57	java/lang/Class:getMethod	(Ljava/lang/String;[Ljava/lang/Class;)Ljava/lang/reflect/Method;
    //   4361: wide
    //   4365: iconst_4
    //   4366: anewarray 4	java/lang/Object
    //   4369: wide
    //   4373: wide
    //   4377: iconst_0
    //   4378: ldc -50
    //   4380: aastore
    //   4381: wide
    //   4385: iconst_1
    //   4386: sipush 132
    //   4389: invokestatic 63	java/lang/Character:valueOf	(C)Ljava/lang/Character;
    //   4392: aastore
    //   4393: wide
    //   4397: iconst_2
    //   4398: bipush 117
    //   4400: invokestatic 63	java/lang/Character:valueOf	(C)Ljava/lang/Character;
    //   4403: aastore
    //   4404: wide
    //   4408: iconst_3
    //   4409: iconst_1
    //   4410: invokestatic 63	java/lang/Character:valueOf	(C)Ljava/lang/Character;
    //   4413: aastore
    //   4414: wide
    //   4418: aconst_null
    //   4419: wide
    //   4423: invokevirtual 69	java/lang/reflect/Method:invoke	(Ljava/lang/Object;[Ljava/lang/Object;)Ljava/lang/Object;
    //   4426: wide
    //   4430: aload_0
    //   4431: wide
    //   4435: checkcast 29	java/lang/String
    //   4438: invokevirtual 93	java/lang/String:equals	(Ljava/lang/Object;)Z
    //   4441: ifeq -4177 -> 264
    //   4444: bipush 21
    //   4446: istore 7
    //   4448: goto -4181 -> 267
    //   4451: ldc -48
    //   4453: sipush 175
    //   4456: iconst_3
    //   4457: invokestatic 79	xxxxxx/uxxxxx:bb00620062bb0062b0062b0062	(Ljava/lang/String;CC)Ljava/lang/String;
    //   4460: wide
    //   4464: iconst_3
    //   4465: anewarray 45	java/lang/Class
    //   4468: wide
    //   4472: wide
    //   4476: iconst_0
    //   4477: ldc 29
    //   4479: aastore
    //   4480: wide
    //   4484: iconst_1
    //   4485: getstatic 51	java/lang/Character:TYPE	Ljava/lang/Class;
    //   4488: aastore
    //   4489: wide
    //   4493: iconst_2
    //   4494: getstatic 51	java/lang/Character:TYPE	Ljava/lang/Class;
    //   4497: aastore
    //   4498: ldc 53
    //   4500: wide
    //   4504: wide
    //   4508: invokevirtual 57	java/lang/Class:getMethod	(Ljava/lang/String;[Ljava/lang/Class;)Ljava/lang/reflect/Method;
    //   4511: wide
    //   4515: iconst_3
    //   4516: anewarray 4	java/lang/Object
    //   4519: wide
    //   4523: wide
    //   4527: iconst_0
    //   4528: ldc -46
    //   4530: aastore
    //   4531: wide
    //   4535: iconst_1
    //   4536: bipush 104
    //   4538: invokestatic 63	java/lang/Character:valueOf	(C)Ljava/lang/Character;
    //   4541: aastore
    //   4542: wide
    //   4546: iconst_2
    //   4547: iconst_5
    //   4548: invokestatic 63	java/lang/Character:valueOf	(C)Ljava/lang/Character;
    //   4551: aastore
    //   4552: wide
    //   4556: aconst_null
    //   4557: wide
    //   4561: invokevirtual 69	java/lang/reflect/Method:invoke	(Ljava/lang/Object;[Ljava/lang/Object;)Ljava/lang/Object;
    //   4564: wide
    //   4568: aload_0
    //   4569: wide
    //   4573: checkcast 29	java/lang/String
    //   4576: invokevirtual 93	java/lang/String:equals	(Ljava/lang/Object;)Z
    //   4579: ifeq -4315 -> 264
    //   4582: bipush 20
    //   4584: istore 7
    //   4586: goto -4319 -> 267
    //   4589: wide
    //   4593: wide
    //   4597: invokevirtual 109	java/lang/reflect/InvocationTargetException:getCause	()Ljava/lang/Throwable;
    //   4600: athrow
    //   4601: ldc -44
    //   4603: bipush 121
    //   4605: bipush 49
    //   4607: iconst_2
    //   4608: invokestatic 43	xxxxxx/uxxxxx:bbbb0062b0062b0062b0062	(Ljava/lang/String;CCC)Ljava/lang/String;
    //   4611: wide
    //   4615: iconst_3
    //   4616: anewarray 45	java/lang/Class
    //   4619: wide
    //   4623: wide
    //   4627: iconst_0
    //   4628: ldc 29
    //   4630: aastore
    //   4631: wide
    //   4635: iconst_1
    //   4636: getstatic 51	java/lang/Character:TYPE	Ljava/lang/Class;
    //   4639: aastore
    //   4640: wide
    //   4644: iconst_2
    //   4645: getstatic 51	java/lang/Character:TYPE	Ljava/lang/Class;
    //   4648: aastore
    //   4649: ldc 53
    //   4651: wide
    //   4655: wide
    //   4659: invokevirtual 57	java/lang/Class:getMethod	(Ljava/lang/String;[Ljava/lang/Class;)Ljava/lang/reflect/Method;
    //   4662: wide
    //   4666: iconst_3
    //   4667: anewarray 4	java/lang/Object
    //   4670: wide
    //   4674: wide
    //   4678: iconst_0
    //   4679: ldc -42
    //   4681: aastore
    //   4682: wide
    //   4686: iconst_1
    //   4687: bipush 73
    //   4689: invokestatic 63	java/lang/Character:valueOf	(C)Ljava/lang/Character;
    //   4692: aastore
    //   4693: wide
    //   4697: iconst_2
    //   4698: iconst_1
    //   4699: invokestatic 63	java/lang/Character:valueOf	(C)Ljava/lang/Character;
    //   4702: aastore
    //   4703: wide
    //   4707: aconst_null
    //   4708: wide
    //   4712: invokevirtual 69	java/lang/reflect/Method:invoke	(Ljava/lang/Object;[Ljava/lang/Object;)Ljava/lang/Object;
    //   4715: wide
    //   4719: aload_0
    //   4720: wide
    //   4724: checkcast 29	java/lang/String
    //   4727: invokevirtual 93	java/lang/String:equals	(Ljava/lang/Object;)Z
    //   4730: ifeq -4466 -> 264
    //   4733: bipush 13
    //   4735: istore 7
    //   4737: goto -4470 -> 267
    //   4740: wide
    //   4744: wide
    //   4748: invokevirtual 109	java/lang/reflect/InvocationTargetException:getCause	()Ljava/lang/Throwable;
    //   4751: athrow
    //   4752: ldc -40
    //   4754: sipush 218
    //   4757: bipush 23
    //   4759: iconst_0
    //   4760: invokestatic 43	xxxxxx/uxxxxx:bbbb0062b0062b0062b0062	(Ljava/lang/String;CCC)Ljava/lang/String;
    //   4763: astore 110
    //   4765: iconst_4
    //   4766: anewarray 45	java/lang/Class
    //   4769: astore 111
    //   4771: aload 111
    //   4773: iconst_0
    //   4774: ldc 29
    //   4776: aastore
    //   4777: aload 111
    //   4779: iconst_1
    //   4780: getstatic 51	java/lang/Character:TYPE	Ljava/lang/Class;
    //   4783: aastore
    //   4784: aload 111
    //   4786: iconst_2
    //   4787: getstatic 51	java/lang/Character:TYPE	Ljava/lang/Class;
    //   4790: aastore
    //   4791: aload 111
    //   4793: iconst_3
    //   4794: getstatic 51	java/lang/Character:TYPE	Ljava/lang/Class;
    //   4797: aastore
    //   4798: ldc 53
    //   4800: aload 110
    //   4802: aload 111
    //   4804: invokevirtual 57	java/lang/Class:getMethod	(Ljava/lang/String;[Ljava/lang/Class;)Ljava/lang/reflect/Method;
    //   4807: astore 112
    //   4809: iconst_4
    //   4810: anewarray 4	java/lang/Object
    //   4813: astore 113
    //   4815: aload 113
    //   4817: iconst_0
    //   4818: ldc -38
    //   4820: aastore
    //   4821: aload 113
    //   4823: iconst_1
    //   4824: sipush 158
    //   4827: invokestatic 63	java/lang/Character:valueOf	(C)Ljava/lang/Character;
    //   4830: aastore
    //   4831: aload 113
    //   4833: iconst_2
    //   4834: bipush 58
    //   4836: invokestatic 63	java/lang/Character:valueOf	(C)Ljava/lang/Character;
    //   4839: aastore
    //   4840: aload 113
    //   4842: iconst_3
    //   4843: iconst_2
    //   4844: invokestatic 63	java/lang/Character:valueOf	(C)Ljava/lang/Character;
    //   4847: aastore
    //   4848: aload 112
    //   4850: aconst_null
    //   4851: aload 113
    //   4853: invokevirtual 69	java/lang/reflect/Method:invoke	(Ljava/lang/Object;[Ljava/lang/Object;)Ljava/lang/Object;
    //   4856: astore 115
    //   4858: aload 115
    //   4860: checkcast 29	java/lang/String
    //   4863: areturn
    //   4864: astore 114
    //   4866: aload 114
    //   4868: invokevirtual 109	java/lang/reflect/InvocationTargetException:getCause	()Ljava/lang/Throwable;
    //   4871: athrow
    //   4872: ldc -36
    //   4874: bipush 25
    //   4876: iconst_1
    //   4877: invokestatic 79	xxxxxx/uxxxxx:bb00620062bb0062b0062b0062	(Ljava/lang/String;CC)Ljava/lang/String;
    //   4880: astore 104
    //   4882: iconst_4
    //   4883: anewarray 45	java/lang/Class
    //   4886: astore 105
    //   4888: aload 105
    //   4890: iconst_0
    //   4891: ldc 29
    //   4893: aastore
    //   4894: aload 105
    //   4896: iconst_1
    //   4897: getstatic 51	java/lang/Character:TYPE	Ljava/lang/Class;
    //   4900: aastore
    //   4901: aload 105
    //   4903: iconst_2
    //   4904: getstatic 51	java/lang/Character:TYPE	Ljava/lang/Class;
    //   4907: aastore
    //   4908: aload 105
    //   4910: iconst_3
    //   4911: getstatic 51	java/lang/Character:TYPE	Ljava/lang/Class;
    //   4914: aastore
    //   4915: ldc 53
    //   4917: aload 104
    //   4919: aload 105
    //   4921: invokevirtual 57	java/lang/Class:getMethod	(Ljava/lang/String;[Ljava/lang/Class;)Ljava/lang/reflect/Method;
    //   4924: astore 106
    //   4926: iconst_4
    //   4927: anewarray 4	java/lang/Object
    //   4930: astore 107
    //   4932: aload 107
    //   4934: iconst_0
    //   4935: ldc -34
    //   4937: aastore
    //   4938: aload 107
    //   4940: iconst_1
    //   4941: bipush 61
    //   4943: invokestatic 63	java/lang/Character:valueOf	(C)Ljava/lang/Character;
    //   4946: aastore
    //   4947: aload 107
    //   4949: iconst_2
    //   4950: bipush 45
    //   4952: invokestatic 63	java/lang/Character:valueOf	(C)Ljava/lang/Character;
    //   4955: aastore
    //   4956: aload 107
    //   4958: iconst_3
    //   4959: iconst_3
    //   4960: invokestatic 63	java/lang/Character:valueOf	(C)Ljava/lang/Character;
    //   4963: aastore
    //   4964: aload 106
    //   4966: aconst_null
    //   4967: aload 107
    //   4969: invokevirtual 69	java/lang/reflect/Method:invoke	(Ljava/lang/Object;[Ljava/lang/Object;)Ljava/lang/Object;
    //   4972: astore 109
    //   4974: aload 109
    //   4976: checkcast 29	java/lang/String
    //   4979: areturn
    //   4980: ldc -32
    //   4982: sipush 217
    //   4985: iconst_4
    //   4986: invokestatic 79	xxxxxx/uxxxxx:bb00620062bb0062b0062b0062	(Ljava/lang/String;CC)Ljava/lang/String;
    //   4989: wide
    //   4993: iconst_4
    //   4994: anewarray 45	java/lang/Class
    //   4997: wide
    //   5001: wide
    //   5005: iconst_0
    //   5006: ldc 29
    //   5008: aastore
    //   5009: wide
    //   5013: iconst_1
    //   5014: getstatic 51	java/lang/Character:TYPE	Ljava/lang/Class;
    //   5017: aastore
    //   5018: wide
    //   5022: iconst_2
    //   5023: getstatic 51	java/lang/Character:TYPE	Ljava/lang/Class;
    //   5026: aastore
    //   5027: wide
    //   5031: iconst_3
    //   5032: getstatic 51	java/lang/Character:TYPE	Ljava/lang/Class;
    //   5035: aastore
    //   5036: ldc 53
    //   5038: wide
    //   5042: wide
    //   5046: invokevirtual 57	java/lang/Class:getMethod	(Ljava/lang/String;[Ljava/lang/Class;)Ljava/lang/reflect/Method;
    //   5049: wide
    //   5053: iconst_4
    //   5054: anewarray 4	java/lang/Object
    //   5057: wide
    //   5061: wide
    //   5065: iconst_0
    //   5066: ldc -30
    //   5068: aastore
    //   5069: wide
    //   5073: iconst_1
    //   5074: bipush 64
    //   5076: invokestatic 63	java/lang/Character:valueOf	(C)Ljava/lang/Character;
    //   5079: aastore
    //   5080: wide
    //   5084: iconst_2
    //   5085: sipush 234
    //   5088: invokestatic 63	java/lang/Character:valueOf	(C)Ljava/lang/Character;
    //   5091: aastore
    //   5092: wide
    //   5096: iconst_3
    //   5097: iconst_2
    //   5098: invokestatic 63	java/lang/Character:valueOf	(C)Ljava/lang/Character;
    //   5101: aastore
    //   5102: wide
    //   5106: aconst_null
    //   5107: wide
    //   5111: invokevirtual 69	java/lang/reflect/Method:invoke	(Ljava/lang/Object;[Ljava/lang/Object;)Ljava/lang/Object;
    //   5114: wide
    //   5118: aload_0
    //   5119: wide
    //   5123: checkcast 29	java/lang/String
    //   5126: invokevirtual 93	java/lang/String:equals	(Ljava/lang/Object;)Z
    //   5129: ifeq -4865 -> 264
    //   5132: bipush 15
    //   5134: istore 7
    //   5136: goto -4869 -> 267
    //   5139: wide
    //   5143: wide
    //   5147: invokevirtual 109	java/lang/reflect/InvocationTargetException:getCause	()Ljava/lang/Throwable;
    //   5150: athrow
    //   5151: ldc -28
    //   5153: bipush 108
    //   5155: iconst_4
    //   5156: invokestatic 79	xxxxxx/uxxxxx:bb00620062bb0062b0062b0062	(Ljava/lang/String;CC)Ljava/lang/String;
    //   5159: wide
    //   5163: iconst_3
    //   5164: anewarray 45	java/lang/Class
    //   5167: wide
    //   5171: wide
    //   5175: iconst_0
    //   5176: ldc 29
    //   5178: aastore
    //   5179: wide
    //   5183: iconst_1
    //   5184: getstatic 51	java/lang/Character:TYPE	Ljava/lang/Class;
    //   5187: aastore
    //   5188: wide
    //   5192: iconst_2
    //   5193: getstatic 51	java/lang/Character:TYPE	Ljava/lang/Class;
    //   5196: aastore
    //   5197: ldc 53
    //   5199: wide
    //   5203: wide
    //   5207: invokevirtual 57	java/lang/Class:getMethod	(Ljava/lang/String;[Ljava/lang/Class;)Ljava/lang/reflect/Method;
    //   5210: wide
    //   5214: iconst_3
    //   5215: anewarray 4	java/lang/Object
    //   5218: wide
    //   5222: wide
    //   5226: iconst_0
    //   5227: ldc -26
    //   5229: aastore
    //   5230: wide
    //   5234: iconst_1
    //   5235: sipush 169
    //   5238: invokestatic 63	java/lang/Character:valueOf	(C)Ljava/lang/Character;
    //   5241: aastore
    //   5242: wide
    //   5246: iconst_2
    //   5247: iconst_5
    //   5248: invokestatic 63	java/lang/Character:valueOf	(C)Ljava/lang/Character;
    //   5251: aastore
    //   5252: wide
    //   5256: aconst_null
    //   5257: wide
    //   5261: invokevirtual 69	java/lang/reflect/Method:invoke	(Ljava/lang/Object;[Ljava/lang/Object;)Ljava/lang/Object;
    //   5264: wide
    //   5268: aload_0
    //   5269: wide
    //   5273: checkcast 29	java/lang/String
    //   5276: invokevirtual 93	java/lang/String:equals	(Ljava/lang/Object;)Z
    //   5279: ifeq -5015 -> 264
    //   5282: bipush 16
    //   5284: istore 7
    //   5286: goto -5019 -> 267
    //   5289: wide
    //   5293: wide
    //   5297: invokevirtual 109	java/lang/reflect/InvocationTargetException:getCause	()Ljava/lang/Throwable;
    //   5300: athrow
    //   5301: ldc -24
    //   5303: sipush 254
    //   5306: sipush 158
    //   5309: iconst_1
    //   5310: invokestatic 43	xxxxxx/uxxxxx:bbbb0062b0062b0062b0062	(Ljava/lang/String;CCC)Ljava/lang/String;
    //   5313: astore -4
    //   5315: iconst_3
    //   5316: anewarray 45	java/lang/Class
    //   5319: astore -3
    //   5321: aload -3
    //   5323: iconst_0
    //   5324: ldc 29
    //   5326: aastore
    //   5327: aload -3
    //   5329: iconst_1
    //   5330: getstatic 51	java/lang/Character:TYPE	Ljava/lang/Class;
    //   5333: aastore
    //   5334: aload -3
    //   5336: iconst_2
    //   5337: getstatic 51	java/lang/Character:TYPE	Ljava/lang/Class;
    //   5340: aastore
    //   5341: ldc 53
    //   5343: aload -4
    //   5345: aload -3
    //   5347: invokevirtual 57	java/lang/Class:getMethod	(Ljava/lang/String;[Ljava/lang/Class;)Ljava/lang/reflect/Method;
    //   5350: astore -2
    //   5352: iconst_3
    //   5353: anewarray 4	java/lang/Object
    //   5356: astore -1
    //   5358: aload -1
    //   5360: iconst_0
    //   5361: ldc -22
    //   5363: aastore
    //   5364: aload -1
    //   5366: iconst_1
    //   5367: bipush 66
    //   5369: invokestatic 63	java/lang/Character:valueOf	(C)Ljava/lang/Character;
    //   5372: aastore
    //   5373: aload -1
    //   5375: iconst_2
    //   5376: iconst_3
    //   5377: invokestatic 63	java/lang/Character:valueOf	(C)Ljava/lang/Character;
    //   5380: aastore
    //   5381: aload -2
    //   5383: aconst_null
    //   5384: aload -1
    //   5386: invokevirtual 69	java/lang/reflect/Method:invoke	(Ljava/lang/Object;[Ljava/lang/Object;)Ljava/lang/Object;
    //   5389: wide
    //   5393: aload_0
    //   5394: wide
    //   5398: checkcast 29	java/lang/String
    //   5401: invokevirtual 93	java/lang/String:equals	(Ljava/lang/Object;)Z
    //   5404: ifeq -5140 -> 264
    //   5407: bipush 17
    //   5409: istore 7
    //   5411: goto -5144 -> 267
    //   5414: wide
    //   5418: wide
    //   5422: invokevirtual 109	java/lang/reflect/InvocationTargetException:getCause	()Ljava/lang/Throwable;
    //   5425: athrow
    //   5426: ldc -20
    //   5428: sipush 246
    //   5431: iconst_0
    //   5432: invokestatic 79	xxxxxx/uxxxxx:bb00620062bb0062b0062b0062	(Ljava/lang/String;CC)Ljava/lang/String;
    //   5435: astore -10
    //   5437: iconst_3
    //   5438: anewarray 45	java/lang/Class
    //   5441: astore -9
    //   5443: aload -9
    //   5445: iconst_0
    //   5446: ldc 29
    //   5448: aastore
    //   5449: aload -9
    //   5451: iconst_1
    //   5452: getstatic 51	java/lang/Character:TYPE	Ljava/lang/Class;
    //   5455: aastore
    //   5456: aload -9
    //   5458: iconst_2
    //   5459: getstatic 51	java/lang/Character:TYPE	Ljava/lang/Class;
    //   5462: aastore
    //   5463: ldc 53
    //   5465: aload -10
    //   5467: aload -9
    //   5469: invokevirtual 57	java/lang/Class:getMethod	(Ljava/lang/String;[Ljava/lang/Class;)Ljava/lang/reflect/Method;
    //   5472: astore -8
    //   5474: iconst_3
    //   5475: anewarray 4	java/lang/Object
    //   5478: astore -7
    //   5480: aload -7
    //   5482: iconst_0
    //   5483: ldc -18
    //   5485: aastore
    //   5486: aload -7
    //   5488: iconst_1
    //   5489: sipush 135
    //   5492: invokestatic 63	java/lang/Character:valueOf	(C)Ljava/lang/Character;
    //   5495: aastore
    //   5496: aload -7
    //   5498: iconst_2
    //   5499: iconst_2
    //   5500: invokestatic 63	java/lang/Character:valueOf	(C)Ljava/lang/Character;
    //   5503: aastore
    //   5504: aload -8
    //   5506: aconst_null
    //   5507: aload -7
    //   5509: invokevirtual 69	java/lang/reflect/Method:invoke	(Ljava/lang/Object;[Ljava/lang/Object;)Ljava/lang/Object;
    //   5512: astore -5
    //   5514: aload_0
    //   5515: aload -5
    //   5517: checkcast 29	java/lang/String
    //   5520: invokevirtual 93	java/lang/String:equals	(Ljava/lang/Object;)Z
    //   5523: ifeq -5259 -> 264
    //   5526: bipush 23
    //   5528: istore 7
    //   5530: goto -5263 -> 267
    //   5533: astore -6
    //   5535: aload -6
    //   5537: invokevirtual 109	java/lang/reflect/InvocationTargetException:getCause	()Ljava/lang/Throwable;
    //   5540: athrow
    //   5541: ldc -16
    //   5543: bipush 31
    //   5545: bipush 46
    //   5547: iconst_1
    //   5548: invokestatic 43	xxxxxx/uxxxxx:bbbb0062b0062b0062b0062	(Ljava/lang/String;CCC)Ljava/lang/String;
    //   5551: astore 98
    //   5553: iconst_4
    //   5554: anewarray 45	java/lang/Class
    //   5557: astore 99
    //   5559: aload 99
    //   5561: iconst_0
    //   5562: ldc 29
    //   5564: aastore
    //   5565: aload 99
    //   5567: iconst_1
    //   5568: getstatic 51	java/lang/Character:TYPE	Ljava/lang/Class;
    //   5571: aastore
    //   5572: aload 99
    //   5574: iconst_2
    //   5575: getstatic 51	java/lang/Character:TYPE	Ljava/lang/Class;
    //   5578: aastore
    //   5579: aload 99
    //   5581: iconst_3
    //   5582: getstatic 51	java/lang/Character:TYPE	Ljava/lang/Class;
    //   5585: aastore
    //   5586: ldc 53
    //   5588: aload 98
    //   5590: aload 99
    //   5592: invokevirtual 57	java/lang/Class:getMethod	(Ljava/lang/String;[Ljava/lang/Class;)Ljava/lang/reflect/Method;
    //   5595: astore 100
    //   5597: iconst_4
    //   5598: anewarray 4	java/lang/Object
    //   5601: astore 101
    //   5603: aload 101
    //   5605: iconst_0
    //   5606: ldc -14
    //   5608: aastore
    //   5609: aload 101
    //   5611: iconst_1
    //   5612: sipush 207
    //   5615: invokestatic 63	java/lang/Character:valueOf	(C)Ljava/lang/Character;
    //   5618: aastore
    //   5619: aload 101
    //   5621: iconst_2
    //   5622: bipush 46
    //   5624: invokestatic 63	java/lang/Character:valueOf	(C)Ljava/lang/Character;
    //   5627: aastore
    //   5628: aload 101
    //   5630: iconst_3
    //   5631: iconst_2
    //   5632: invokestatic 63	java/lang/Character:valueOf	(C)Ljava/lang/Character;
    //   5635: aastore
    //   5636: aload 100
    //   5638: aconst_null
    //   5639: aload 101
    //   5641: invokevirtual 69	java/lang/reflect/Method:invoke	(Ljava/lang/Object;[Ljava/lang/Object;)Ljava/lang/Object;
    //   5644: astore 103
    //   5646: aload 103
    //   5648: checkcast 29	java/lang/String
    //   5651: areturn
    //   5652: ldc -12
    //   5654: bipush 41
    //   5656: iconst_5
    //   5657: invokestatic 79	xxxxxx/uxxxxx:bb00620062bb0062b0062b0062	(Ljava/lang/String;CC)Ljava/lang/String;
    //   5660: astore -16
    //   5662: iconst_3
    //   5663: anewarray 45	java/lang/Class
    //   5666: astore -15
    //   5668: aload -15
    //   5670: iconst_0
    //   5671: ldc 29
    //   5673: aastore
    //   5674: aload -15
    //   5676: iconst_1
    //   5677: getstatic 51	java/lang/Character:TYPE	Ljava/lang/Class;
    //   5680: aastore
    //   5681: aload -15
    //   5683: iconst_2
    //   5684: getstatic 51	java/lang/Character:TYPE	Ljava/lang/Class;
    //   5687: aastore
    //   5688: ldc 53
    //   5690: aload -16
    //   5692: aload -15
    //   5694: invokevirtual 57	java/lang/Class:getMethod	(Ljava/lang/String;[Ljava/lang/Class;)Ljava/lang/reflect/Method;
    //   5697: astore -14
    //   5699: iconst_3
    //   5700: anewarray 4	java/lang/Object
    //   5703: astore -13
    //   5705: aload -13
    //   5707: iconst_0
    //   5708: ldc -10
    //   5710: aastore
    //   5711: aload -13
    //   5713: iconst_1
    //   5714: sipush 233
    //   5717: invokestatic 63	java/lang/Character:valueOf	(C)Ljava/lang/Character;
    //   5720: aastore
    //   5721: aload -13
    //   5723: iconst_2
    //   5724: iconst_0
    //   5725: invokestatic 63	java/lang/Character:valueOf	(C)Ljava/lang/Character;
    //   5728: aastore
    //   5729: aload -14
    //   5731: aconst_null
    //   5732: aload -13
    //   5734: invokevirtual 69	java/lang/reflect/Method:invoke	(Ljava/lang/Object;[Ljava/lang/Object;)Ljava/lang/Object;
    //   5737: astore -11
    //   5739: aload_0
    //   5740: aload -11
    //   5742: checkcast 29	java/lang/String
    //   5745: invokevirtual 93	java/lang/String:equals	(Ljava/lang/Object;)Z
    //   5748: ifeq -5484 -> 264
    //   5751: bipush 22
    //   5753: istore 7
    //   5755: goto -5488 -> 267
    //   5758: astore -12
    //   5760: aload -12
    //   5762: invokevirtual 109	java/lang/reflect/InvocationTargetException:getCause	()Ljava/lang/Throwable;
    //   5765: athrow
    //   5766: ldc -8
    //   5768: bipush 68
    //   5770: sipush 202
    //   5773: iconst_1
    //   5774: invokestatic 43	xxxxxx/uxxxxx:bbbb0062b0062b0062b0062	(Ljava/lang/String;CCC)Ljava/lang/String;
    //   5777: astore -22
    //   5779: iconst_3
    //   5780: anewarray 45	java/lang/Class
    //   5783: astore -21
    //   5785: aload -21
    //   5787: iconst_0
    //   5788: ldc 29
    //   5790: aastore
    //   5791: aload -21
    //   5793: iconst_1
    //   5794: getstatic 51	java/lang/Character:TYPE	Ljava/lang/Class;
    //   5797: aastore
    //   5798: aload -21
    //   5800: iconst_2
    //   5801: getstatic 51	java/lang/Character:TYPE	Ljava/lang/Class;
    //   5804: aastore
    //   5805: ldc 53
    //   5807: aload -22
    //   5809: aload -21
    //   5811: invokevirtual 57	java/lang/Class:getMethod	(Ljava/lang/String;[Ljava/lang/Class;)Ljava/lang/reflect/Method;
    //   5814: astore -20
    //   5816: iconst_3
    //   5817: anewarray 4	java/lang/Object
    //   5820: astore -19
    //   5822: aload -19
    //   5824: iconst_0
    //   5825: ldc -6
    //   5827: aastore
    //   5828: aload -19
    //   5830: iconst_1
    //   5831: bipush 20
    //   5833: invokestatic 63	java/lang/Character:valueOf	(C)Ljava/lang/Character;
    //   5836: aastore
    //   5837: aload -19
    //   5839: iconst_2
    //   5840: iconst_2
    //   5841: invokestatic 63	java/lang/Character:valueOf	(C)Ljava/lang/Character;
    //   5844: aastore
    //   5845: aload -20
    //   5847: aconst_null
    //   5848: aload -19
    //   5850: invokevirtual 69	java/lang/reflect/Method:invoke	(Ljava/lang/Object;[Ljava/lang/Object;)Ljava/lang/Object;
    //   5853: astore -17
    //   5855: aload_0
    //   5856: aload -17
    //   5858: checkcast 29	java/lang/String
    //   5861: invokevirtual 93	java/lang/String:equals	(Ljava/lang/Object;)Z
    //   5864: ifeq -5600 -> 264
    //   5867: bipush 24
    //   5869: istore 7
    //   5871: goto -5604 -> 267
    //   5874: astore 108
    //   5876: aload 108
    //   5878: invokevirtual 109	java/lang/reflect/InvocationTargetException:getCause	()Ljava/lang/Throwable;
    //   5881: athrow
    //   5882: ldc -4
    //   5884: sipush 151
    //   5887: iconst_2
    //   5888: invokestatic 79	xxxxxx/uxxxxx:bb00620062bb0062b0062b0062	(Ljava/lang/String;CC)Ljava/lang/String;
    //   5891: astore -28
    //   5893: iconst_3
    //   5894: anewarray 45	java/lang/Class
    //   5897: astore -27
    //   5899: aload -27
    //   5901: iconst_0
    //   5902: ldc 29
    //   5904: aastore
    //   5905: aload -27
    //   5907: iconst_1
    //   5908: getstatic 51	java/lang/Character:TYPE	Ljava/lang/Class;
    //   5911: aastore
    //   5912: aload -27
    //   5914: iconst_2
    //   5915: getstatic 51	java/lang/Character:TYPE	Ljava/lang/Class;
    //   5918: aastore
    //   5919: ldc 53
    //   5921: aload -28
    //   5923: aload -27
    //   5925: invokevirtual 57	java/lang/Class:getMethod	(Ljava/lang/String;[Ljava/lang/Class;)Ljava/lang/reflect/Method;
    //   5928: astore -26
    //   5930: iconst_3
    //   5931: anewarray 4	java/lang/Object
    //   5934: astore -25
    //   5936: aload -25
    //   5938: iconst_0
    //   5939: ldc -2
    //   5941: aastore
    //   5942: aload -25
    //   5944: iconst_1
    //   5945: bipush 111
    //   5947: invokestatic 63	java/lang/Character:valueOf	(C)Ljava/lang/Character;
    //   5950: aastore
    //   5951: aload -25
    //   5953: iconst_2
    //   5954: iconst_5
    //   5955: invokestatic 63	java/lang/Character:valueOf	(C)Ljava/lang/Character;
    //   5958: aastore
    //   5959: aload -26
    //   5961: aconst_null
    //   5962: aload -25
    //   5964: invokevirtual 69	java/lang/reflect/Method:invoke	(Ljava/lang/Object;[Ljava/lang/Object;)Ljava/lang/Object;
    //   5967: astore -23
    //   5969: aload_0
    //   5970: aload -23
    //   5972: checkcast 29	java/lang/String
    //   5975: invokevirtual 93	java/lang/String:equals	(Ljava/lang/Object;)Z
    //   5978: ifeq -5714 -> 264
    //   5981: bipush 25
    //   5983: istore 7
    //   5985: goto -5718 -> 267
    //   5988: astore -24
    //   5990: aload -24
    //   5992: invokevirtual 109	java/lang/reflect/InvocationTargetException:getCause	()Ljava/lang/Throwable;
    //   5995: athrow
    //   5996: ldc_w 256
    //   5999: sipush 198
    //   6002: iconst_3
    //   6003: invokestatic 79	xxxxxx/uxxxxx:bb00620062bb0062b0062b0062	(Ljava/lang/String;CC)Ljava/lang/String;
    //   6006: astore -34
    //   6008: iconst_3
    //   6009: anewarray 45	java/lang/Class
    //   6012: astore -33
    //   6014: aload -33
    //   6016: iconst_0
    //   6017: ldc 29
    //   6019: aastore
    //   6020: aload -33
    //   6022: iconst_1
    //   6023: getstatic 51	java/lang/Character:TYPE	Ljava/lang/Class;
    //   6026: aastore
    //   6027: aload -33
    //   6029: iconst_2
    //   6030: getstatic 51	java/lang/Character:TYPE	Ljava/lang/Class;
    //   6033: aastore
    //   6034: ldc 53
    //   6036: aload -34
    //   6038: aload -33
    //   6040: invokevirtual 57	java/lang/Class:getMethod	(Ljava/lang/String;[Ljava/lang/Class;)Ljava/lang/reflect/Method;
    //   6043: astore -32
    //   6045: iconst_3
    //   6046: anewarray 4	java/lang/Object
    //   6049: astore -31
    //   6051: aload -31
    //   6053: iconst_0
    //   6054: ldc_w 258
    //   6057: aastore
    //   6058: aload -31
    //   6060: iconst_1
    //   6061: sipush 159
    //   6064: invokestatic 63	java/lang/Character:valueOf	(C)Ljava/lang/Character;
    //   6067: aastore
    //   6068: aload -31
    //   6070: iconst_2
    //   6071: iconst_3
    //   6072: invokestatic 63	java/lang/Character:valueOf	(C)Ljava/lang/Character;
    //   6075: aastore
    //   6076: aload -32
    //   6078: aconst_null
    //   6079: aload -31
    //   6081: invokevirtual 69	java/lang/reflect/Method:invoke	(Ljava/lang/Object;[Ljava/lang/Object;)Ljava/lang/Object;
    //   6084: astore -29
    //   6086: aload_0
    //   6087: aload -29
    //   6089: checkcast 29	java/lang/String
    //   6092: invokevirtual 93	java/lang/String:equals	(Ljava/lang/Object;)Z
    //   6095: ifeq -5831 -> 264
    //   6098: bipush 18
    //   6100: istore 7
    //   6102: goto -5835 -> 267
    //   6105: astore -30
    //   6107: aload -30
    //   6109: invokevirtual 109	java/lang/reflect/InvocationTargetException:getCause	()Ljava/lang/Throwable;
    //   6112: athrow
    //   6113: ldc_w 260
    //   6116: bipush 20
    //   6118: iconst_2
    //   6119: invokestatic 79	xxxxxx/uxxxxx:bb00620062bb0062b0062b0062	(Ljava/lang/String;CC)Ljava/lang/String;
    //   6122: astore -40
    //   6124: iconst_3
    //   6125: anewarray 45	java/lang/Class
    //   6128: astore -39
    //   6130: aload -39
    //   6132: iconst_0
    //   6133: ldc 29
    //   6135: aastore
    //   6136: aload -39
    //   6138: iconst_1
    //   6139: getstatic 51	java/lang/Character:TYPE	Ljava/lang/Class;
    //   6142: aastore
    //   6143: aload -39
    //   6145: iconst_2
    //   6146: getstatic 51	java/lang/Character:TYPE	Ljava/lang/Class;
    //   6149: aastore
    //   6150: ldc 53
    //   6152: aload -40
    //   6154: aload -39
    //   6156: invokevirtual 57	java/lang/Class:getMethod	(Ljava/lang/String;[Ljava/lang/Class;)Ljava/lang/reflect/Method;
    //   6159: astore -38
    //   6161: iconst_3
    //   6162: anewarray 4	java/lang/Object
    //   6165: astore -37
    //   6167: aload -37
    //   6169: iconst_0
    //   6170: ldc 126
    //   6172: aastore
    //   6173: aload -37
    //   6175: iconst_1
    //   6176: bipush 47
    //   6178: invokestatic 63	java/lang/Character:valueOf	(C)Ljava/lang/Character;
    //   6181: aastore
    //   6182: aload -37
    //   6184: iconst_2
    //   6185: iconst_0
    //   6186: invokestatic 63	java/lang/Character:valueOf	(C)Ljava/lang/Character;
    //   6189: aastore
    //   6190: aload -38
    //   6192: aconst_null
    //   6193: aload -37
    //   6195: invokevirtual 69	java/lang/reflect/Method:invoke	(Ljava/lang/Object;[Ljava/lang/Object;)Ljava/lang/Object;
    //   6198: astore -35
    //   6200: aload_0
    //   6201: aload -35
    //   6203: checkcast 29	java/lang/String
    //   6206: invokevirtual 93	java/lang/String:equals	(Ljava/lang/Object;)Z
    //   6209: ifeq -5945 -> 264
    //   6212: iconst_4
    //   6213: istore 7
    //   6215: goto -5948 -> 267
    //   6218: astore -36
    //   6220: aload -36
    //   6222: invokevirtual 109	java/lang/reflect/InvocationTargetException:getCause	()Ljava/lang/Throwable;
    //   6225: athrow
    //   6226: ldc_w 262
    //   6229: bipush 69
    //   6231: iconst_1
    //   6232: invokestatic 79	xxxxxx/uxxxxx:bb00620062bb0062b0062b0062	(Ljava/lang/String;CC)Ljava/lang/String;
    //   6235: astore -46
    //   6237: iconst_3
    //   6238: anewarray 45	java/lang/Class
    //   6241: astore -45
    //   6243: aload -45
    //   6245: iconst_0
    //   6246: ldc 29
    //   6248: aastore
    //   6249: aload -45
    //   6251: iconst_1
    //   6252: getstatic 51	java/lang/Character:TYPE	Ljava/lang/Class;
    //   6255: aastore
    //   6256: aload -45
    //   6258: iconst_2
    //   6259: getstatic 51	java/lang/Character:TYPE	Ljava/lang/Class;
    //   6262: aastore
    //   6263: ldc 53
    //   6265: aload -46
    //   6267: aload -45
    //   6269: invokevirtual 57	java/lang/Class:getMethod	(Ljava/lang/String;[Ljava/lang/Class;)Ljava/lang/reflect/Method;
    //   6272: astore -44
    //   6274: iconst_3
    //   6275: anewarray 4	java/lang/Object
    //   6278: astore -43
    //   6280: aload -43
    //   6282: iconst_0
    //   6283: ldc_w 264
    //   6286: aastore
    //   6287: aload -43
    //   6289: iconst_1
    //   6290: sipush 230
    //   6293: invokestatic 63	java/lang/Character:valueOf	(C)Ljava/lang/Character;
    //   6296: aastore
    //   6297: aload -43
    //   6299: iconst_2
    //   6300: iconst_0
    //   6301: invokestatic 63	java/lang/Character:valueOf	(C)Ljava/lang/Character;
    //   6304: aastore
    //   6305: aload -44
    //   6307: aconst_null
    //   6308: aload -43
    //   6310: invokevirtual 69	java/lang/reflect/Method:invoke	(Ljava/lang/Object;[Ljava/lang/Object;)Ljava/lang/Object;
    //   6313: astore -41
    //   6315: aload_0
    //   6316: aload -41
    //   6318: checkcast 29	java/lang/String
    //   6321: invokevirtual 93	java/lang/String:equals	(Ljava/lang/Object;)Z
    //   6324: ifeq -6060 -> 264
    //   6327: getstatic 99	uuuuuu/rvrvrv:b0068hh006800680068hh0068	I
    //   6330: invokestatic 116	uuuuuu/rvrvrv:bqqq00710071qq0071q0071	()I
    //   6333: iadd
    //   6334: getstatic 99	uuuuuu/rvrvrv:b0068hh006800680068hh0068	I
    //   6337: imul
    //   6338: getstatic 103	uuuuuu/rvrvrv:b00680068h006800680068hh0068	I
    //   6341: irem
    //   6342: getstatic 266	uuuuuu/rvrvrv:bhh0068006800680068hh0068	I
    //   6345: if_icmpeq +2185 -> 8530
    //   6348: invokestatic 105	uuuuuu/rvrvrv:b007100710071q0071qq0071q0071	()I
    //   6351: putstatic 99	uuuuuu/rvrvrv:b0068hh006800680068hh0068	I
    //   6354: invokestatic 105	uuuuuu/rvrvrv:b007100710071q0071qq0071q0071	()I
    //   6357: putstatic 266	uuuuuu/rvrvrv:bhh0068006800680068hh0068	I
    //   6360: iconst_3
    //   6361: istore 7
    //   6363: goto -6096 -> 267
    //   6366: astore -42
    //   6368: aload -42
    //   6370: invokevirtual 109	java/lang/reflect/InvocationTargetException:getCause	()Ljava/lang/Throwable;
    //   6373: athrow
    //   6374: wide
    //   6378: wide
    //   6382: invokevirtual 109	java/lang/reflect/InvocationTargetException:getCause	()Ljava/lang/Throwable;
    //   6385: athrow
    //   6386: ldc_w 268
    //   6389: bipush 122
    //   6391: iconst_0
    //   6392: invokestatic 79	xxxxxx/uxxxxx:bb00620062bb0062b0062b0062	(Ljava/lang/String;CC)Ljava/lang/String;
    //   6395: astore 92
    //   6397: iconst_3
    //   6398: anewarray 45	java/lang/Class
    //   6401: astore 93
    //   6403: aload 93
    //   6405: iconst_0
    //   6406: ldc 29
    //   6408: aastore
    //   6409: aload 93
    //   6411: iconst_1
    //   6412: getstatic 51	java/lang/Character:TYPE	Ljava/lang/Class;
    //   6415: aastore
    //   6416: aload 93
    //   6418: iconst_2
    //   6419: getstatic 51	java/lang/Character:TYPE	Ljava/lang/Class;
    //   6422: aastore
    //   6423: ldc 53
    //   6425: aload 92
    //   6427: aload 93
    //   6429: invokevirtual 57	java/lang/Class:getMethod	(Ljava/lang/String;[Ljava/lang/Class;)Ljava/lang/reflect/Method;
    //   6432: astore 94
    //   6434: iconst_3
    //   6435: anewarray 4	java/lang/Object
    //   6438: astore 95
    //   6440: aload 95
    //   6442: iconst_0
    //   6443: ldc_w 270
    //   6446: aastore
    //   6447: aload 95
    //   6449: iconst_1
    //   6450: sipush 187
    //   6453: invokestatic 63	java/lang/Character:valueOf	(C)Ljava/lang/Character;
    //   6456: aastore
    //   6457: aload 95
    //   6459: iconst_2
    //   6460: iconst_4
    //   6461: invokestatic 63	java/lang/Character:valueOf	(C)Ljava/lang/Character;
    //   6464: aastore
    //   6465: aload 94
    //   6467: aconst_null
    //   6468: aload 95
    //   6470: invokevirtual 69	java/lang/reflect/Method:invoke	(Ljava/lang/Object;[Ljava/lang/Object;)Ljava/lang/Object;
    //   6473: astore 97
    //   6475: aload 97
    //   6477: checkcast 29	java/lang/String
    //   6480: areturn
    //   6481: astore 96
    //   6483: aload 96
    //   6485: invokevirtual 109	java/lang/reflect/InvocationTargetException:getCause	()Ljava/lang/Throwable;
    //   6488: athrow
    //   6489: wide
    //   6493: wide
    //   6497: invokevirtual 109	java/lang/reflect/InvocationTargetException:getCause	()Ljava/lang/Throwable;
    //   6500: athrow
    //   6501: ldc_w 256
    //   6504: bipush 71
    //   6506: iconst_3
    //   6507: invokestatic 79	xxxxxx/uxxxxx:bb00620062bb0062b0062b0062	(Ljava/lang/String;CC)Ljava/lang/String;
    //   6510: astore 86
    //   6512: iconst_3
    //   6513: anewarray 45	java/lang/Class
    //   6516: astore 87
    //   6518: aload 87
    //   6520: iconst_0
    //   6521: ldc 29
    //   6523: aastore
    //   6524: aload 87
    //   6526: iconst_1
    //   6527: getstatic 51	java/lang/Character:TYPE	Ljava/lang/Class;
    //   6530: aastore
    //   6531: aload 87
    //   6533: iconst_2
    //   6534: getstatic 51	java/lang/Character:TYPE	Ljava/lang/Class;
    //   6537: aastore
    //   6538: ldc 53
    //   6540: aload 86
    //   6542: aload 87
    //   6544: invokevirtual 57	java/lang/Class:getMethod	(Ljava/lang/String;[Ljava/lang/Class;)Ljava/lang/reflect/Method;
    //   6547: astore 88
    //   6549: iconst_3
    //   6550: anewarray 4	java/lang/Object
    //   6553: astore 89
    //   6555: aload 89
    //   6557: iconst_0
    //   6558: ldc_w 272
    //   6561: aastore
    //   6562: aload 89
    //   6564: iconst_1
    //   6565: sipush 217
    //   6568: invokestatic 63	java/lang/Character:valueOf	(C)Ljava/lang/Character;
    //   6571: aastore
    //   6572: aload 89
    //   6574: iconst_2
    //   6575: iconst_2
    //   6576: invokestatic 63	java/lang/Character:valueOf	(C)Ljava/lang/Character;
    //   6579: aastore
    //   6580: aload 88
    //   6582: aconst_null
    //   6583: aload 89
    //   6585: invokevirtual 69	java/lang/reflect/Method:invoke	(Ljava/lang/Object;[Ljava/lang/Object;)Ljava/lang/Object;
    //   6588: astore 91
    //   6590: aload 91
    //   6592: checkcast 29	java/lang/String
    //   6595: areturn
    //   6596: astore 90
    //   6598: aload 90
    //   6600: invokevirtual 109	java/lang/reflect/InvocationTargetException:getCause	()Ljava/lang/Throwable;
    //   6603: athrow
    //   6604: ldc_w 274
    //   6607: bipush 126
    //   6609: iconst_5
    //   6610: invokestatic 79	xxxxxx/uxxxxx:bb00620062bb0062b0062b0062	(Ljava/lang/String;CC)Ljava/lang/String;
    //   6613: astore -52
    //   6615: iconst_3
    //   6616: anewarray 45	java/lang/Class
    //   6619: astore -51
    //   6621: aload -51
    //   6623: iconst_0
    //   6624: ldc 29
    //   6626: aastore
    //   6627: aload -51
    //   6629: iconst_1
    //   6630: getstatic 51	java/lang/Character:TYPE	Ljava/lang/Class;
    //   6633: aastore
    //   6634: aload -51
    //   6636: iconst_2
    //   6637: getstatic 51	java/lang/Character:TYPE	Ljava/lang/Class;
    //   6640: aastore
    //   6641: ldc 53
    //   6643: aload -52
    //   6645: aload -51
    //   6647: invokevirtual 57	java/lang/Class:getMethod	(Ljava/lang/String;[Ljava/lang/Class;)Ljava/lang/reflect/Method;
    //   6650: astore -50
    //   6652: iconst_3
    //   6653: anewarray 4	java/lang/Object
    //   6656: astore -49
    //   6658: aload -49
    //   6660: iconst_0
    //   6661: ldc_w 276
    //   6664: aastore
    //   6665: aload -49
    //   6667: iconst_1
    //   6668: bipush 37
    //   6670: invokestatic 63	java/lang/Character:valueOf	(C)Ljava/lang/Character;
    //   6673: aastore
    //   6674: aload -49
    //   6676: iconst_2
    //   6677: iconst_2
    //   6678: invokestatic 63	java/lang/Character:valueOf	(C)Ljava/lang/Character;
    //   6681: aastore
    //   6682: aload -50
    //   6684: aconst_null
    //   6685: aload -49
    //   6687: invokevirtual 69	java/lang/reflect/Method:invoke	(Ljava/lang/Object;[Ljava/lang/Object;)Ljava/lang/Object;
    //   6690: astore -47
    //   6692: aload_0
    //   6693: aload -47
    //   6695: checkcast 29	java/lang/String
    //   6698: invokevirtual 93	java/lang/String:equals	(Ljava/lang/Object;)Z
    //   6701: ifeq -6437 -> 264
    //   6704: bipush 28
    //   6706: istore 7
    //   6708: goto -6441 -> 267
    //   6711: astore -48
    //   6713: aload -48
    //   6715: invokevirtual 109	java/lang/reflect/InvocationTargetException:getCause	()Ljava/lang/Throwable;
    //   6718: athrow
    //   6719: ldc_w 278
    //   6722: bipush 28
    //   6724: sipush 223
    //   6727: iconst_1
    //   6728: invokestatic 43	xxxxxx/uxxxxx:bbbb0062b0062b0062b0062	(Ljava/lang/String;CCC)Ljava/lang/String;
    //   6731: astore -58
    //   6733: iconst_3
    //   6734: anewarray 45	java/lang/Class
    //   6737: astore -57
    //   6739: aload -57
    //   6741: iconst_0
    //   6742: ldc 29
    //   6744: aastore
    //   6745: aload -57
    //   6747: iconst_1
    //   6748: getstatic 51	java/lang/Character:TYPE	Ljava/lang/Class;
    //   6751: aastore
    //   6752: aload -57
    //   6754: iconst_2
    //   6755: getstatic 51	java/lang/Character:TYPE	Ljava/lang/Class;
    //   6758: aastore
    //   6759: ldc 53
    //   6761: aload -58
    //   6763: aload -57
    //   6765: invokevirtual 57	java/lang/Class:getMethod	(Ljava/lang/String;[Ljava/lang/Class;)Ljava/lang/reflect/Method;
    //   6768: astore -56
    //   6770: iconst_3
    //   6771: anewarray 4	java/lang/Object
    //   6774: astore -55
    //   6776: aload -55
    //   6778: iconst_0
    //   6779: ldc_w 280
    //   6782: aastore
    //   6783: aload -55
    //   6785: iconst_1
    //   6786: bipush 86
    //   6788: invokestatic 63	java/lang/Character:valueOf	(C)Ljava/lang/Character;
    //   6791: aastore
    //   6792: aload -55
    //   6794: iconst_2
    //   6795: iconst_4
    //   6796: invokestatic 63	java/lang/Character:valueOf	(C)Ljava/lang/Character;
    //   6799: aastore
    //   6800: aload -56
    //   6802: aconst_null
    //   6803: aload -55
    //   6805: invokevirtual 69	java/lang/reflect/Method:invoke	(Ljava/lang/Object;[Ljava/lang/Object;)Ljava/lang/Object;
    //   6808: astore -53
    //   6810: aload_0
    //   6811: aload -53
    //   6813: checkcast 29	java/lang/String
    //   6816: invokevirtual 93	java/lang/String:equals	(Ljava/lang/Object;)Z
    //   6819: ifeq -6555 -> 264
    //   6822: bipush 29
    //   6824: istore 7
    //   6826: goto -6559 -> 267
    //   6829: astore -54
    //   6831: aload -54
    //   6833: invokevirtual 109	java/lang/reflect/InvocationTargetException:getCause	()Ljava/lang/Throwable;
    //   6836: athrow
    //   6837: astore -67
    //   6839: aload -67
    //   6841: invokevirtual 109	java/lang/reflect/InvocationTargetException:getCause	()Ljava/lang/Throwable;
    //   6844: athrow
    //   6845: wide
    //   6849: wide
    //   6853: invokevirtual 109	java/lang/reflect/InvocationTargetException:getCause	()Ljava/lang/Throwable;
    //   6856: athrow
    //   6857: ldc_w 282
    //   6860: bipush 97
    //   6862: iconst_2
    //   6863: invokestatic 79	xxxxxx/uxxxxx:bb00620062bb0062b0062b0062	(Ljava/lang/String;CC)Ljava/lang/String;
    //   6866: astore 80
    //   6868: iconst_4
    //   6869: anewarray 45	java/lang/Class
    //   6872: astore 81
    //   6874: aload 81
    //   6876: iconst_0
    //   6877: ldc 29
    //   6879: aastore
    //   6880: aload 81
    //   6882: iconst_1
    //   6883: getstatic 51	java/lang/Character:TYPE	Ljava/lang/Class;
    //   6886: aastore
    //   6887: aload 81
    //   6889: iconst_2
    //   6890: getstatic 51	java/lang/Character:TYPE	Ljava/lang/Class;
    //   6893: aastore
    //   6894: aload 81
    //   6896: iconst_3
    //   6897: getstatic 51	java/lang/Character:TYPE	Ljava/lang/Class;
    //   6900: aastore
    //   6901: ldc 53
    //   6903: aload 80
    //   6905: aload 81
    //   6907: invokevirtual 57	java/lang/Class:getMethod	(Ljava/lang/String;[Ljava/lang/Class;)Ljava/lang/reflect/Method;
    //   6910: astore 82
    //   6912: iconst_4
    //   6913: anewarray 4	java/lang/Object
    //   6916: astore 83
    //   6918: aload 83
    //   6920: iconst_0
    //   6921: ldc_w 284
    //   6924: aastore
    //   6925: aload 83
    //   6927: iconst_1
    //   6928: bipush 37
    //   6930: invokestatic 63	java/lang/Character:valueOf	(C)Ljava/lang/Character;
    //   6933: aastore
    //   6934: aload 83
    //   6936: iconst_2
    //   6937: bipush 68
    //   6939: invokestatic 63	java/lang/Character:valueOf	(C)Ljava/lang/Character;
    //   6942: aastore
    //   6943: aload 83
    //   6945: iconst_3
    //   6946: iconst_1
    //   6947: invokestatic 63	java/lang/Character:valueOf	(C)Ljava/lang/Character;
    //   6950: aastore
    //   6951: aload 82
    //   6953: aconst_null
    //   6954: aload 83
    //   6956: invokevirtual 69	java/lang/reflect/Method:invoke	(Ljava/lang/Object;[Ljava/lang/Object;)Ljava/lang/Object;
    //   6959: astore 85
    //   6961: aload 85
    //   6963: checkcast 29	java/lang/String
    //   6966: areturn
    //   6967: wide
    //   6971: wide
    //   6975: invokevirtual 109	java/lang/reflect/InvocationTargetException:getCause	()Ljava/lang/Throwable;
    //   6978: athrow
    //   6979: astore 84
    //   6981: aload 84
    //   6983: invokevirtual 109	java/lang/reflect/InvocationTargetException:getCause	()Ljava/lang/Throwable;
    //   6986: athrow
    //   6987: astore -116
    //   6989: aload -116
    //   6991: invokevirtual 109	java/lang/reflect/InvocationTargetException:getCause	()Ljava/lang/Throwable;
    //   6994: athrow
    //   6995: wide
    //   6999: wide
    //   7003: invokevirtual 109	java/lang/reflect/InvocationTargetException:getCause	()Ljava/lang/Throwable;
    //   7006: athrow
    //   7007: ldc_w 286
    //   7010: bipush 73
    //   7012: iconst_1
    //   7013: invokestatic 79	xxxxxx/uxxxxx:bb00620062bb0062b0062b0062	(Ljava/lang/String;CC)Ljava/lang/String;
    //   7016: astore 74
    //   7018: iconst_3
    //   7019: anewarray 45	java/lang/Class
    //   7022: astore 75
    //   7024: aload 75
    //   7026: iconst_0
    //   7027: ldc 29
    //   7029: aastore
    //   7030: aload 75
    //   7032: iconst_1
    //   7033: getstatic 51	java/lang/Character:TYPE	Ljava/lang/Class;
    //   7036: aastore
    //   7037: aload 75
    //   7039: iconst_2
    //   7040: getstatic 51	java/lang/Character:TYPE	Ljava/lang/Class;
    //   7043: aastore
    //   7044: ldc 53
    //   7046: aload 74
    //   7048: aload 75
    //   7050: invokevirtual 57	java/lang/Class:getMethod	(Ljava/lang/String;[Ljava/lang/Class;)Ljava/lang/reflect/Method;
    //   7053: astore 76
    //   7055: iconst_3
    //   7056: anewarray 4	java/lang/Object
    //   7059: astore 77
    //   7061: aload 77
    //   7063: iconst_0
    //   7064: ldc_w 288
    //   7067: aastore
    //   7068: aload 77
    //   7070: iconst_1
    //   7071: bipush 7
    //   7073: invokestatic 63	java/lang/Character:valueOf	(C)Ljava/lang/Character;
    //   7076: aastore
    //   7077: aload 77
    //   7079: iconst_2
    //   7080: iconst_3
    //   7081: invokestatic 63	java/lang/Character:valueOf	(C)Ljava/lang/Character;
    //   7084: aastore
    //   7085: aload 76
    //   7087: aconst_null
    //   7088: aload 77
    //   7090: invokevirtual 69	java/lang/reflect/Method:invoke	(Ljava/lang/Object;[Ljava/lang/Object;)Ljava/lang/Object;
    //   7093: astore 79
    //   7095: aload 79
    //   7097: checkcast 29	java/lang/String
    //   7100: areturn
    //   7101: astore 78
    //   7103: aload 78
    //   7105: invokevirtual 109	java/lang/reflect/InvocationTargetException:getCause	()Ljava/lang/Throwable;
    //   7108: athrow
    //   7109: astore -104
    //   7111: aload -104
    //   7113: invokevirtual 109	java/lang/reflect/InvocationTargetException:getCause	()Ljava/lang/Throwable;
    //   7116: athrow
    //   7117: ldc -48
    //   7119: bipush 48
    //   7121: iconst_3
    //   7122: invokestatic 79	xxxxxx/uxxxxx:bb00620062bb0062b0062b0062	(Ljava/lang/String;CC)Ljava/lang/String;
    //   7125: astore 68
    //   7127: iconst_3
    //   7128: anewarray 45	java/lang/Class
    //   7131: astore 69
    //   7133: aload 69
    //   7135: iconst_0
    //   7136: ldc 29
    //   7138: aastore
    //   7139: aload 69
    //   7141: iconst_1
    //   7142: getstatic 51	java/lang/Character:TYPE	Ljava/lang/Class;
    //   7145: aastore
    //   7146: aload 69
    //   7148: iconst_2
    //   7149: getstatic 51	java/lang/Character:TYPE	Ljava/lang/Class;
    //   7152: aastore
    //   7153: ldc 53
    //   7155: aload 68
    //   7157: aload 69
    //   7159: invokevirtual 57	java/lang/Class:getMethod	(Ljava/lang/String;[Ljava/lang/Class;)Ljava/lang/reflect/Method;
    //   7162: astore 70
    //   7164: iconst_3
    //   7165: anewarray 4	java/lang/Object
    //   7168: astore 71
    //   7170: aload 71
    //   7172: iconst_0
    //   7173: ldc_w 290
    //   7176: aastore
    //   7177: aload 71
    //   7179: iconst_1
    //   7180: bipush 113
    //   7182: invokestatic 63	java/lang/Character:valueOf	(C)Ljava/lang/Character;
    //   7185: aastore
    //   7186: aload 71
    //   7188: iconst_2
    //   7189: iconst_5
    //   7190: invokestatic 63	java/lang/Character:valueOf	(C)Ljava/lang/Character;
    //   7193: aastore
    //   7194: aload 70
    //   7196: aconst_null
    //   7197: aload 71
    //   7199: invokevirtual 69	java/lang/reflect/Method:invoke	(Ljava/lang/Object;[Ljava/lang/Object;)Ljava/lang/Object;
    //   7202: astore 73
    //   7204: aload 73
    //   7206: checkcast 29	java/lang/String
    //   7209: areturn
    //   7210: astore -18
    //   7212: aload -18
    //   7214: invokevirtual 109	java/lang/reflect/InvocationTargetException:getCause	()Ljava/lang/Throwable;
    //   7217: athrow
    //   7218: astore 102
    //   7220: aload 102
    //   7222: invokevirtual 109	java/lang/reflect/InvocationTargetException:getCause	()Ljava/lang/Throwable;
    //   7225: athrow
    //   7226: ldc -116
    //   7228: bipush 17
    //   7230: iconst_4
    //   7231: invokestatic 79	xxxxxx/uxxxxx:bb00620062bb0062b0062b0062	(Ljava/lang/String;CC)Ljava/lang/String;
    //   7234: astore 62
    //   7236: iconst_4
    //   7237: anewarray 45	java/lang/Class
    //   7240: astore 63
    //   7242: aload 63
    //   7244: iconst_0
    //   7245: ldc 29
    //   7247: aastore
    //   7248: aload 63
    //   7250: iconst_1
    //   7251: getstatic 51	java/lang/Character:TYPE	Ljava/lang/Class;
    //   7254: aastore
    //   7255: aload 63
    //   7257: iconst_2
    //   7258: getstatic 51	java/lang/Character:TYPE	Ljava/lang/Class;
    //   7261: aastore
    //   7262: aload 63
    //   7264: iconst_3
    //   7265: getstatic 51	java/lang/Character:TYPE	Ljava/lang/Class;
    //   7268: aastore
    //   7269: ldc 53
    //   7271: aload 62
    //   7273: aload 63
    //   7275: invokevirtual 57	java/lang/Class:getMethod	(Ljava/lang/String;[Ljava/lang/Class;)Ljava/lang/reflect/Method;
    //   7278: astore 64
    //   7280: iconst_4
    //   7281: anewarray 4	java/lang/Object
    //   7284: astore 65
    //   7286: aload 65
    //   7288: iconst_0
    //   7289: ldc_w 292
    //   7292: aastore
    //   7293: aload 65
    //   7295: iconst_1
    //   7296: bipush 121
    //   7298: invokestatic 63	java/lang/Character:valueOf	(C)Ljava/lang/Character;
    //   7301: aastore
    //   7302: aload 65
    //   7304: iconst_2
    //   7305: sipush 193
    //   7308: invokestatic 63	java/lang/Character:valueOf	(C)Ljava/lang/Character;
    //   7311: aastore
    //   7312: aload 65
    //   7314: iconst_3
    //   7315: iconst_3
    //   7316: invokestatic 63	java/lang/Character:valueOf	(C)Ljava/lang/Character;
    //   7319: aastore
    //   7320: aload 64
    //   7322: aconst_null
    //   7323: aload 65
    //   7325: invokevirtual 69	java/lang/reflect/Method:invoke	(Ljava/lang/Object;[Ljava/lang/Object;)Ljava/lang/Object;
    //   7328: astore 67
    //   7330: aload 67
    //   7332: checkcast 29	java/lang/String
    //   7335: areturn
    //   7336: astore 66
    //   7338: aload 66
    //   7340: invokevirtual 109	java/lang/reflect/InvocationTargetException:getCause	()Ljava/lang/Throwable;
    //   7343: athrow
    //   7344: ldc_w 294
    //   7347: sipush 209
    //   7350: sipush 245
    //   7353: iconst_2
    //   7354: invokestatic 43	xxxxxx/uxxxxx:bbbb0062b0062b0062b0062	(Ljava/lang/String;CCC)Ljava/lang/String;
    //   7357: astore 56
    //   7359: iconst_3
    //   7360: anewarray 45	java/lang/Class
    //   7363: astore 57
    //   7365: aload 57
    //   7367: iconst_0
    //   7368: ldc 29
    //   7370: aastore
    //   7371: aload 57
    //   7373: iconst_1
    //   7374: getstatic 51	java/lang/Character:TYPE	Ljava/lang/Class;
    //   7377: aastore
    //   7378: aload 57
    //   7380: iconst_2
    //   7381: getstatic 51	java/lang/Character:TYPE	Ljava/lang/Class;
    //   7384: aastore
    //   7385: ldc 53
    //   7387: aload 56
    //   7389: aload 57
    //   7391: invokevirtual 57	java/lang/Class:getMethod	(Ljava/lang/String;[Ljava/lang/Class;)Ljava/lang/reflect/Method;
    //   7394: astore 58
    //   7396: iconst_3
    //   7397: anewarray 4	java/lang/Object
    //   7400: astore 59
    //   7402: aload 59
    //   7404: iconst_0
    //   7405: ldc_w 296
    //   7408: aastore
    //   7409: aload 59
    //   7411: iconst_1
    //   7412: sipush 254
    //   7415: invokestatic 63	java/lang/Character:valueOf	(C)Ljava/lang/Character;
    //   7418: aastore
    //   7419: aload 59
    //   7421: iconst_2
    //   7422: iconst_2
    //   7423: invokestatic 63	java/lang/Character:valueOf	(C)Ljava/lang/Character;
    //   7426: aastore
    //   7427: aload 58
    //   7429: aconst_null
    //   7430: aload 59
    //   7432: invokevirtual 69	java/lang/reflect/Method:invoke	(Ljava/lang/Object;[Ljava/lang/Object;)Ljava/lang/Object;
    //   7435: astore 61
    //   7437: aload 61
    //   7439: checkcast 29	java/lang/String
    //   7442: areturn
    //   7443: astore 60
    //   7445: aload 60
    //   7447: invokevirtual 109	java/lang/reflect/InvocationTargetException:getCause	()Ljava/lang/Throwable;
    //   7450: athrow
    //   7451: astore 120
    //   7453: aload 120
    //   7455: invokevirtual 109	java/lang/reflect/InvocationTargetException:getCause	()Ljava/lang/Throwable;
    //   7458: athrow
    //   7459: ldc_w 298
    //   7462: sipush 233
    //   7465: bipush 27
    //   7467: iconst_0
    //   7468: invokestatic 43	xxxxxx/uxxxxx:bbbb0062b0062b0062b0062	(Ljava/lang/String;CCC)Ljava/lang/String;
    //   7471: astore_1
    //   7472: iconst_4
    //   7473: anewarray 45	java/lang/Class
    //   7476: astore_2
    //   7477: aload_2
    //   7478: iconst_0
    //   7479: ldc 29
    //   7481: aastore
    //   7482: aload_2
    //   7483: iconst_1
    //   7484: getstatic 51	java/lang/Character:TYPE	Ljava/lang/Class;
    //   7487: aastore
    //   7488: aload_2
    //   7489: iconst_2
    //   7490: getstatic 51	java/lang/Character:TYPE	Ljava/lang/Class;
    //   7493: aastore
    //   7494: aload_2
    //   7495: iconst_3
    //   7496: getstatic 51	java/lang/Character:TYPE	Ljava/lang/Class;
    //   7499: aastore
    //   7500: ldc 53
    //   7502: aload_1
    //   7503: aload_2
    //   7504: invokevirtual 57	java/lang/Class:getMethod	(Ljava/lang/String;[Ljava/lang/Class;)Ljava/lang/reflect/Method;
    //   7507: astore_3
    //   7508: iconst_4
    //   7509: anewarray 4	java/lang/Object
    //   7512: astore 4
    //   7514: aload 4
    //   7516: iconst_0
    //   7517: ldc -46
    //   7519: aastore
    //   7520: aload 4
    //   7522: iconst_1
    //   7523: sipush 247
    //   7526: invokestatic 63	java/lang/Character:valueOf	(C)Ljava/lang/Character;
    //   7529: aastore
    //   7530: aload 4
    //   7532: iconst_2
    //   7533: bipush 38
    //   7535: invokestatic 63	java/lang/Character:valueOf	(C)Ljava/lang/Character;
    //   7538: aastore
    //   7539: aload 4
    //   7541: iconst_3
    //   7542: iconst_2
    //   7543: invokestatic 63	java/lang/Character:valueOf	(C)Ljava/lang/Character;
    //   7546: aastore
    //   7547: aload_3
    //   7548: aconst_null
    //   7549: aload 4
    //   7551: invokevirtual 69	java/lang/reflect/Method:invoke	(Ljava/lang/Object;[Ljava/lang/Object;)Ljava/lang/Object;
    //   7554: astore 6
    //   7556: aload_0
    //   7557: aload 6
    //   7559: checkcast 29	java/lang/String
    //   7562: invokevirtual 93	java/lang/String:equals	(Ljava/lang/Object;)Z
    //   7565: ifeq -7301 -> 264
    //   7568: bipush 8
    //   7570: istore 7
    //   7572: goto -7305 -> 267
    //   7575: astore 5
    //   7577: aload 5
    //   7579: invokevirtual 109	java/lang/reflect/InvocationTargetException:getCause	()Ljava/lang/Throwable;
    //   7582: athrow
    //   7583: ldc_w 300
    //   7586: sipush 179
    //   7589: bipush 40
    //   7591: iconst_3
    //   7592: invokestatic 43	xxxxxx/uxxxxx:bbbb0062b0062b0062b0062	(Ljava/lang/String;CCC)Ljava/lang/String;
    //   7595: astore 50
    //   7597: iconst_3
    //   7598: anewarray 45	java/lang/Class
    //   7601: astore 51
    //   7603: aload 51
    //   7605: iconst_0
    //   7606: ldc 29
    //   7608: aastore
    //   7609: aload 51
    //   7611: iconst_1
    //   7612: getstatic 51	java/lang/Character:TYPE	Ljava/lang/Class;
    //   7615: aastore
    //   7616: aload 51
    //   7618: iconst_2
    //   7619: getstatic 51	java/lang/Character:TYPE	Ljava/lang/Class;
    //   7622: aastore
    //   7623: ldc 53
    //   7625: aload 50
    //   7627: aload 51
    //   7629: invokevirtual 57	java/lang/Class:getMethod	(Ljava/lang/String;[Ljava/lang/Class;)Ljava/lang/reflect/Method;
    //   7632: astore 52
    //   7634: iconst_3
    //   7635: anewarray 4	java/lang/Object
    //   7638: astore 53
    //   7640: aload 53
    //   7642: iconst_0
    //   7643: ldc_w 302
    //   7646: aastore
    //   7647: aload 53
    //   7649: iconst_1
    //   7650: sipush 231
    //   7653: invokestatic 63	java/lang/Character:valueOf	(C)Ljava/lang/Character;
    //   7656: aastore
    //   7657: aload 53
    //   7659: iconst_2
    //   7660: iconst_3
    //   7661: invokestatic 63	java/lang/Character:valueOf	(C)Ljava/lang/Character;
    //   7664: aastore
    //   7665: aload 52
    //   7667: aconst_null
    //   7668: aload 53
    //   7670: invokevirtual 69	java/lang/reflect/Method:invoke	(Ljava/lang/Object;[Ljava/lang/Object;)Ljava/lang/Object;
    //   7673: astore 55
    //   7675: aload 55
    //   7677: checkcast 29	java/lang/String
    //   7680: areturn
    //   7681: astore 54
    //   7683: aload 54
    //   7685: invokevirtual 109	java/lang/reflect/InvocationTargetException:getCause	()Ljava/lang/Throwable;
    //   7688: athrow
    //   7689: astore -92
    //   7691: aload -92
    //   7693: invokevirtual 109	java/lang/reflect/InvocationTargetException:getCause	()Ljava/lang/Throwable;
    //   7696: athrow
    //   7697: ldc_w 304
    //   7700: sipush 134
    //   7703: iconst_2
    //   7704: invokestatic 79	xxxxxx/uxxxxx:bb00620062bb0062b0062b0062	(Ljava/lang/String;CC)Ljava/lang/String;
    //   7707: astore 44
    //   7709: iconst_4
    //   7710: anewarray 45	java/lang/Class
    //   7713: astore 45
    //   7715: aload 45
    //   7717: iconst_0
    //   7718: ldc 29
    //   7720: aastore
    //   7721: aload 45
    //   7723: iconst_1
    //   7724: getstatic 51	java/lang/Character:TYPE	Ljava/lang/Class;
    //   7727: aastore
    //   7728: aload 45
    //   7730: iconst_2
    //   7731: getstatic 51	java/lang/Character:TYPE	Ljava/lang/Class;
    //   7734: aastore
    //   7735: aload 45
    //   7737: iconst_3
    //   7738: getstatic 51	java/lang/Character:TYPE	Ljava/lang/Class;
    //   7741: aastore
    //   7742: ldc 53
    //   7744: aload 44
    //   7746: aload 45
    //   7748: invokevirtual 57	java/lang/Class:getMethod	(Ljava/lang/String;[Ljava/lang/Class;)Ljava/lang/reflect/Method;
    //   7751: astore 46
    //   7753: iconst_4
    //   7754: anewarray 4	java/lang/Object
    //   7757: astore 47
    //   7759: aload 47
    //   7761: iconst_0
    //   7762: ldc_w 306
    //   7765: aastore
    //   7766: aload 47
    //   7768: iconst_1
    //   7769: bipush 70
    //   7771: invokestatic 63	java/lang/Character:valueOf	(C)Ljava/lang/Character;
    //   7774: aastore
    //   7775: aload 47
    //   7777: iconst_2
    //   7778: bipush 68
    //   7780: invokestatic 63	java/lang/Character:valueOf	(C)Ljava/lang/Character;
    //   7783: aastore
    //   7784: aload 47
    //   7786: iconst_3
    //   7787: iconst_2
    //   7788: invokestatic 63	java/lang/Character:valueOf	(C)Ljava/lang/Character;
    //   7791: aastore
    //   7792: aload 46
    //   7794: aconst_null
    //   7795: aload 47
    //   7797: invokevirtual 69	java/lang/reflect/Method:invoke	(Ljava/lang/Object;[Ljava/lang/Object;)Ljava/lang/Object;
    //   7800: astore 49
    //   7802: aload 49
    //   7804: checkcast 29	java/lang/String
    //   7807: areturn
    //   7808: astore 48
    //   7810: aload 48
    //   7812: invokevirtual 109	java/lang/reflect/InvocationTargetException:getCause	()Ljava/lang/Throwable;
    //   7815: athrow
    //   7816: ldc_w 308
    //   7819: bipush 17
    //   7821: bipush 78
    //   7823: iconst_1
    //   7824: invokestatic 43	xxxxxx/uxxxxx:bbbb0062b0062b0062b0062	(Ljava/lang/String;CCC)Ljava/lang/String;
    //   7827: astore 38
    //   7829: iconst_3
    //   7830: anewarray 45	java/lang/Class
    //   7833: astore 39
    //   7835: aload 39
    //   7837: iconst_0
    //   7838: ldc 29
    //   7840: aastore
    //   7841: aload 39
    //   7843: iconst_1
    //   7844: getstatic 51	java/lang/Character:TYPE	Ljava/lang/Class;
    //   7847: aastore
    //   7848: aload 39
    //   7850: iconst_2
    //   7851: getstatic 51	java/lang/Character:TYPE	Ljava/lang/Class;
    //   7854: aastore
    //   7855: ldc 53
    //   7857: aload 38
    //   7859: aload 39
    //   7861: invokevirtual 57	java/lang/Class:getMethod	(Ljava/lang/String;[Ljava/lang/Class;)Ljava/lang/reflect/Method;
    //   7864: astore 40
    //   7866: iconst_3
    //   7867: anewarray 4	java/lang/Object
    //   7870: astore 41
    //   7872: aload 41
    //   7874: iconst_0
    //   7875: ldc_w 310
    //   7878: aastore
    //   7879: aload 41
    //   7881: iconst_1
    //   7882: bipush 88
    //   7884: invokestatic 63	java/lang/Character:valueOf	(C)Ljava/lang/Character;
    //   7887: aastore
    //   7888: aload 41
    //   7890: iconst_2
    //   7891: iconst_4
    //   7892: invokestatic 63	java/lang/Character:valueOf	(C)Ljava/lang/Character;
    //   7895: aastore
    //   7896: aload 40
    //   7898: aconst_null
    //   7899: aload 41
    //   7901: invokevirtual 69	java/lang/reflect/Method:invoke	(Ljava/lang/Object;[Ljava/lang/Object;)Ljava/lang/Object;
    //   7904: astore 43
    //   7906: aload 43
    //   7908: checkcast 29	java/lang/String
    //   7911: areturn
    //   7912: astore 42
    //   7914: aload 42
    //   7916: invokevirtual 109	java/lang/reflect/InvocationTargetException:getCause	()Ljava/lang/Throwable;
    //   7919: athrow
    //   7920: ldc_w 312
    //   7923: sipush 197
    //   7926: iconst_5
    //   7927: invokestatic 79	xxxxxx/uxxxxx:bb00620062bb0062b0062b0062	(Ljava/lang/String;CC)Ljava/lang/String;
    //   7930: astore 32
    //   7932: iconst_3
    //   7933: anewarray 45	java/lang/Class
    //   7936: astore 33
    //   7938: aload 33
    //   7940: iconst_0
    //   7941: ldc 29
    //   7943: aastore
    //   7944: aload 33
    //   7946: iconst_1
    //   7947: getstatic 51	java/lang/Character:TYPE	Ljava/lang/Class;
    //   7950: aastore
    //   7951: aload 33
    //   7953: iconst_2
    //   7954: getstatic 51	java/lang/Character:TYPE	Ljava/lang/Class;
    //   7957: aastore
    //   7958: ldc 53
    //   7960: aload 32
    //   7962: aload 33
    //   7964: invokevirtual 57	java/lang/Class:getMethod	(Ljava/lang/String;[Ljava/lang/Class;)Ljava/lang/reflect/Method;
    //   7967: astore 34
    //   7969: iconst_3
    //   7970: anewarray 4	java/lang/Object
    //   7973: astore 35
    //   7975: aload 35
    //   7977: iconst_0
    //   7978: ldc_w 314
    //   7981: aastore
    //   7982: aload 35
    //   7984: iconst_1
    //   7985: sipush 192
    //   7988: invokestatic 63	java/lang/Character:valueOf	(C)Ljava/lang/Character;
    //   7991: aastore
    //   7992: aload 35
    //   7994: iconst_2
    //   7995: iconst_4
    //   7996: invokestatic 63	java/lang/Character:valueOf	(C)Ljava/lang/Character;
    //   7999: aastore
    //   8000: aload 34
    //   8002: aconst_null
    //   8003: aload 35
    //   8005: invokevirtual 69	java/lang/reflect/Method:invoke	(Ljava/lang/Object;[Ljava/lang/Object;)Ljava/lang/Object;
    //   8008: astore 37
    //   8010: aload 37
    //   8012: checkcast 29	java/lang/String
    //   8015: areturn
    //   8016: astore 36
    //   8018: aload 36
    //   8020: invokevirtual 109	java/lang/reflect/InvocationTargetException:getCause	()Ljava/lang/Throwable;
    //   8023: athrow
    //   8024: wide
    //   8028: wide
    //   8032: invokevirtual 109	java/lang/reflect/InvocationTargetException:getCause	()Ljava/lang/Throwable;
    //   8035: athrow
    //   8036: astore -110
    //   8038: aload -110
    //   8040: invokevirtual 109	java/lang/reflect/InvocationTargetException:getCause	()Ljava/lang/Throwable;
    //   8043: athrow
    //   8044: wide
    //   8048: wide
    //   8052: invokevirtual 109	java/lang/reflect/InvocationTargetException:getCause	()Ljava/lang/Throwable;
    //   8055: athrow
    //   8056: astore 72
    //   8058: aload 72
    //   8060: invokevirtual 109	java/lang/reflect/InvocationTargetException:getCause	()Ljava/lang/Throwable;
    //   8063: athrow
    //   8064: ldc_w 316
    //   8067: iconst_3
    //   8068: iconst_1
    //   8069: invokestatic 79	xxxxxx/uxxxxx:bb00620062bb0062b0062b0062	(Ljava/lang/String;CC)Ljava/lang/String;
    //   8072: astore 26
    //   8074: iconst_3
    //   8075: anewarray 45	java/lang/Class
    //   8078: astore 27
    //   8080: aload 27
    //   8082: iconst_0
    //   8083: ldc 29
    //   8085: aastore
    //   8086: aload 27
    //   8088: iconst_1
    //   8089: getstatic 51	java/lang/Character:TYPE	Ljava/lang/Class;
    //   8092: aastore
    //   8093: aload 27
    //   8095: iconst_2
    //   8096: getstatic 51	java/lang/Character:TYPE	Ljava/lang/Class;
    //   8099: aastore
    //   8100: ldc 53
    //   8102: aload 26
    //   8104: aload 27
    //   8106: invokevirtual 57	java/lang/Class:getMethod	(Ljava/lang/String;[Ljava/lang/Class;)Ljava/lang/reflect/Method;
    //   8109: astore 28
    //   8111: iconst_3
    //   8112: anewarray 4	java/lang/Object
    //   8115: astore 29
    //   8117: aload 29
    //   8119: iconst_0
    //   8120: ldc_w 318
    //   8123: aastore
    //   8124: aload 29
    //   8126: iconst_1
    //   8127: sipush 178
    //   8130: invokestatic 63	java/lang/Character:valueOf	(C)Ljava/lang/Character;
    //   8133: aastore
    //   8134: aload 29
    //   8136: iconst_2
    //   8137: iconst_5
    //   8138: invokestatic 63	java/lang/Character:valueOf	(C)Ljava/lang/Character;
    //   8141: aastore
    //   8142: aload 28
    //   8144: aconst_null
    //   8145: aload 29
    //   8147: invokevirtual 69	java/lang/reflect/Method:invoke	(Ljava/lang/Object;[Ljava/lang/Object;)Ljava/lang/Object;
    //   8150: astore 31
    //   8152: aload 31
    //   8154: checkcast 29	java/lang/String
    //   8157: areturn
    //   8158: astore 30
    //   8160: aload 30
    //   8162: invokevirtual 109	java/lang/reflect/InvocationTargetException:getCause	()Ljava/lang/Throwable;
    //   8165: athrow
    //   8166: ldc_w 320
    //   8169: bipush 31
    //   8171: sipush 143
    //   8174: iconst_0
    //   8175: invokestatic 43	xxxxxx/uxxxxx:bbbb0062b0062b0062b0062	(Ljava/lang/String;CCC)Ljava/lang/String;
    //   8178: astore 20
    //   8180: iconst_3
    //   8181: anewarray 45	java/lang/Class
    //   8184: astore 21
    //   8186: aload 21
    //   8188: iconst_0
    //   8189: ldc 29
    //   8191: aastore
    //   8192: aload 21
    //   8194: iconst_1
    //   8195: getstatic 51	java/lang/Character:TYPE	Ljava/lang/Class;
    //   8198: aastore
    //   8199: aload 21
    //   8201: iconst_2
    //   8202: getstatic 51	java/lang/Character:TYPE	Ljava/lang/Class;
    //   8205: aastore
    //   8206: ldc 53
    //   8208: aload 20
    //   8210: aload 21
    //   8212: invokevirtual 57	java/lang/Class:getMethod	(Ljava/lang/String;[Ljava/lang/Class;)Ljava/lang/reflect/Method;
    //   8215: astore 22
    //   8217: iconst_3
    //   8218: anewarray 4	java/lang/Object
    //   8221: astore 23
    //   8223: aload 23
    //   8225: iconst_0
    //   8226: ldc_w 322
    //   8229: aastore
    //   8230: aload 23
    //   8232: iconst_1
    //   8233: bipush 127
    //   8235: invokestatic 63	java/lang/Character:valueOf	(C)Ljava/lang/Character;
    //   8238: aastore
    //   8239: aload 23
    //   8241: iconst_2
    //   8242: iconst_3
    //   8243: invokestatic 63	java/lang/Character:valueOf	(C)Ljava/lang/Character;
    //   8246: aastore
    //   8247: aload 22
    //   8249: aconst_null
    //   8250: aload 23
    //   8252: invokevirtual 69	java/lang/reflect/Method:invoke	(Ljava/lang/Object;[Ljava/lang/Object;)Ljava/lang/Object;
    //   8255: astore 25
    //   8257: aload 25
    //   8259: checkcast 29	java/lang/String
    //   8262: areturn
    //   8263: astore 24
    //   8265: aload 24
    //   8267: invokevirtual 109	java/lang/reflect/InvocationTargetException:getCause	()Ljava/lang/Throwable;
    //   8270: athrow
    //   8271: ldc_w 324
    //   8274: bipush 50
    //   8276: bipush 118
    //   8278: iconst_1
    //   8279: invokestatic 43	xxxxxx/uxxxxx:bbbb0062b0062b0062b0062	(Ljava/lang/String;CCC)Ljava/lang/String;
    //   8282: astore 14
    //   8284: iconst_4
    //   8285: anewarray 45	java/lang/Class
    //   8288: astore 15
    //   8290: aload 15
    //   8292: iconst_0
    //   8293: ldc 29
    //   8295: aastore
    //   8296: aload 15
    //   8298: iconst_1
    //   8299: getstatic 51	java/lang/Character:TYPE	Ljava/lang/Class;
    //   8302: aastore
    //   8303: aload 15
    //   8305: iconst_2
    //   8306: getstatic 51	java/lang/Character:TYPE	Ljava/lang/Class;
    //   8309: aastore
    //   8310: aload 15
    //   8312: iconst_3
    //   8313: getstatic 51	java/lang/Character:TYPE	Ljava/lang/Class;
    //   8316: aastore
    //   8317: ldc 53
    //   8319: aload 14
    //   8321: aload 15
    //   8323: invokevirtual 57	java/lang/Class:getMethod	(Ljava/lang/String;[Ljava/lang/Class;)Ljava/lang/reflect/Method;
    //   8326: astore 16
    //   8328: iconst_4
    //   8329: anewarray 4	java/lang/Object
    //   8332: astore 17
    //   8334: aload 17
    //   8336: iconst_0
    //   8337: ldc_w 326
    //   8340: aastore
    //   8341: aload 17
    //   8343: iconst_1
    //   8344: sipush 155
    //   8347: invokestatic 63	java/lang/Character:valueOf	(C)Ljava/lang/Character;
    //   8350: aastore
    //   8351: aload 17
    //   8353: iconst_2
    //   8354: sipush 205
    //   8357: invokestatic 63	java/lang/Character:valueOf	(C)Ljava/lang/Character;
    //   8360: aastore
    //   8361: aload 17
    //   8363: iconst_3
    //   8364: iconst_1
    //   8365: invokestatic 63	java/lang/Character:valueOf	(C)Ljava/lang/Character;
    //   8368: aastore
    //   8369: aload 16
    //   8371: aconst_null
    //   8372: aload 17
    //   8374: invokevirtual 69	java/lang/reflect/Method:invoke	(Ljava/lang/Object;[Ljava/lang/Object;)Ljava/lang/Object;
    //   8377: astore 19
    //   8379: aload 19
    //   8381: checkcast 29	java/lang/String
    //   8384: areturn
    //   8385: astore 18
    //   8387: aload 18
    //   8389: invokevirtual 109	java/lang/reflect/InvocationTargetException:getCause	()Ljava/lang/Throwable;
    //   8392: athrow
    //   8393: ldc_w 328
    //   8396: bipush 97
    //   8398: sipush 238
    //   8401: iconst_2
    //   8402: invokestatic 43	xxxxxx/uxxxxx:bbbb0062b0062b0062b0062	(Ljava/lang/String;CCC)Ljava/lang/String;
    //   8405: astore 8
    //   8407: iconst_4
    //   8408: anewarray 45	java/lang/Class
    //   8411: astore 9
    //   8413: aload 9
    //   8415: iconst_0
    //   8416: ldc 29
    //   8418: aastore
    //   8419: aload 9
    //   8421: iconst_1
    //   8422: getstatic 51	java/lang/Character:TYPE	Ljava/lang/Class;
    //   8425: aastore
    //   8426: aload 9
    //   8428: iconst_2
    //   8429: getstatic 51	java/lang/Character:TYPE	Ljava/lang/Class;
    //   8432: aastore
    //   8433: aload 9
    //   8435: iconst_3
    //   8436: getstatic 51	java/lang/Character:TYPE	Ljava/lang/Class;
    //   8439: aastore
    //   8440: ldc 53
    //   8442: aload 8
    //   8444: aload 9
    //   8446: invokevirtual 57	java/lang/Class:getMethod	(Ljava/lang/String;[Ljava/lang/Class;)Ljava/lang/reflect/Method;
    //   8449: astore 10
    //   8451: iconst_4
    //   8452: anewarray 4	java/lang/Object
    //   8455: astore 11
    //   8457: aload 11
    //   8459: iconst_0
    //   8460: ldc_w 330
    //   8463: aastore
    //   8464: aload 11
    //   8466: iconst_1
    //   8467: sipush 128
    //   8470: invokestatic 63	java/lang/Character:valueOf	(C)Ljava/lang/Character;
    //   8473: aastore
    //   8474: aload 11
    //   8476: iconst_2
    //   8477: sipush 218
    //   8480: invokestatic 63	java/lang/Character:valueOf	(C)Ljava/lang/Character;
    //   8483: aastore
    //   8484: aload 11
    //   8486: iconst_3
    //   8487: iconst_0
    //   8488: invokestatic 63	java/lang/Character:valueOf	(C)Ljava/lang/Character;
    //   8491: aastore
    //   8492: aload 10
    //   8494: aconst_null
    //   8495: aload 11
    //   8497: invokevirtual 69	java/lang/reflect/Method:invoke	(Ljava/lang/Object;[Ljava/lang/Object;)Ljava/lang/Object;
    //   8500: astore 13
    //   8502: aload 13
    //   8504: checkcast 29	java/lang/String
    //   8507: areturn
    //   8508: astore 12
    //   8510: aload 12
    //   8512: invokevirtual 109	java/lang/reflect/InvocationTargetException:getCause	()Ljava/lang/Throwable;
    //   8515: athrow
    //   8516: astore -122
    //   8518: aload -122
    //   8520: invokevirtual 109	java/lang/reflect/InvocationTargetException:getCause	()Ljava/lang/Throwable;
    //   8523: athrow
    //   8524: iconst_0
    //   8525: istore 7
    //   8527: goto -8260 -> 267
    //   8530: iconst_3
    //   8531: istore 7
    //   8533: goto -8266 -> 267
    // Exception table:
    //   from	to	target	type
    //   900	916	990	java/lang/reflect/InvocationTargetException
    //   1317	1333	1354	java/lang/reflect/InvocationTargetException
    //   1466	1482	1503	java/lang/reflect/InvocationTargetException
    //   1617	1633	1653	java/lang/reflect/InvocationTargetException
    //   1902	1912	1918	java/lang/reflect/InvocationTargetException
    //   2129	2139	2145	java/lang/reflect/InvocationTargetException
    //   2633	2643	2649	java/lang/reflect/InvocationTargetException
    //   2019	2029	3143	java/lang/reflect/InvocationTargetException
    //   3460	3476	3497	java/lang/reflect/InvocationTargetException
    //   3632	3648	3669	java/lang/reflect/InvocationTargetException
    //   3804	3820	3841	java/lang/reflect/InvocationTargetException
    //   1787	1803	3853	java/lang/reflect/InvocationTargetException
    //   3988	4004	4025	java/lang/reflect/InvocationTargetException
    //   4115	4125	4131	java/lang/reflect/InvocationTargetException
    //   632	642	4281	java/lang/reflect/InvocationTargetException
    //   4552	4568	4589	java/lang/reflect/InvocationTargetException
    //   4703	4719	4740	java/lang/reflect/InvocationTargetException
    //   4848	4858	4864	java/lang/reflect/InvocationTargetException
    //   5102	5118	5139	java/lang/reflect/InvocationTargetException
    //   5252	5268	5289	java/lang/reflect/InvocationTargetException
    //   5381	5393	5414	java/lang/reflect/InvocationTargetException
    //   5504	5514	5533	java/lang/reflect/InvocationTargetException
    //   5729	5739	5758	java/lang/reflect/InvocationTargetException
    //   4964	4974	5874	java/lang/reflect/InvocationTargetException
    //   5959	5969	5988	java/lang/reflect/InvocationTargetException
    //   6076	6086	6105	java/lang/reflect/InvocationTargetException
    //   6190	6200	6218	java/lang/reflect/InvocationTargetException
    //   6305	6315	6366	java/lang/reflect/InvocationTargetException
    //   2967	2983	6374	java/lang/reflect/InvocationTargetException
    //   6465	6475	6481	java/lang/reflect/InvocationTargetException
    //   2393	2409	6489	java/lang/reflect/InvocationTargetException
    //   6580	6590	6596	java/lang/reflect/InvocationTargetException
    //   6682	6692	6711	java/lang/reflect/InvocationTargetException
    //   6800	6810	6829	java/lang/reflect/InvocationTargetException
    //   513	523	6837	java/lang/reflect/InvocationTargetException
    //   3106	3122	6845	java/lang/reflect/InvocationTargetException
    //   763	779	6967	java/lang/reflect/InvocationTargetException
    //   6951	6961	6979	java/lang/reflect/InvocationTargetException
    //   3247	3257	6987	java/lang/reflect/InvocationTargetException
    //   4414	4430	6995	java/lang/reflect/InvocationTargetException
    //   7085	7095	7101	java/lang/reflect/InvocationTargetException
    //   2737	2747	7109	java/lang/reflect/InvocationTargetException
    //   5845	5855	7210	java/lang/reflect/InvocationTargetException
    //   5636	5646	7218	java/lang/reflect/InvocationTargetException
    //   7320	7330	7336	java/lang/reflect/InvocationTargetException
    //   7427	7437	7443	java/lang/reflect/InvocationTargetException
    //   4216	4226	7451	java/lang/reflect/InvocationTargetException
    //   7547	7556	7575	java/lang/reflect/InvocationTargetException
    //   7665	7675	7681	java/lang/reflect/InvocationTargetException
    //   2524	2534	7689	java/lang/reflect/InvocationTargetException
    //   7792	7802	7808	java/lang/reflect/InvocationTargetException
    //   7896	7906	7912	java/lang/reflect/InvocationTargetException
    //   8000	8010	8016	java/lang/reflect/InvocationTargetException
    //   1103	1119	8024	java/lang/reflect/InvocationTargetException
    //   2847	2857	8036	java/lang/reflect/InvocationTargetException
    //   2254	2270	8044	java/lang/reflect/InvocationTargetException
    //   7194	7204	8056	java/lang/reflect/InvocationTargetException
    //   8142	8152	8158	java/lang/reflect/InvocationTargetException
    //   8247	8257	8263	java/lang/reflect/InvocationTargetException
    //   8369	8379	8385	java/lang/reflect/InvocationTargetException
    //   8492	8502	8508	java/lang/reflect/InvocationTargetException
    //   3342	3352	8516	java/lang/reflect/InvocationTargetException
  }
  
  public static int bqqq00710071qq0071q0071()
  {
    return 1;
  }
}
