package uuuuuu;

import android.content.SharedPreferences.OnSharedPreferenceChangeListener;
import com.db.pwcc.dbmobile.secure.SecurityUtils;
import com.db.pwcc.dbmobile.secure.preferences.SharedPreferencesHelper;
import javax.inject.Inject;

public class sttsst<V extends tsstst.tttsst>
  extends ssssst<V>
  implements tsstst.ssstst<V>
{
  public static int b006E006E006E006Enn006E006En = 82;
  public static int b006En006E006Enn006E006En = 1;
  public static int bn006E006E006Enn006E006En = 2;
  public static final int bnnn006Enn006E006En = 999;
  public static int bnnnn006En006E006En;
  @Inject
  public SharedPreferencesHelper b006E006En006Enn006E006En;
  public boolean b006Enn006Enn006E006En = false;
  @Inject
  public SecurityUtils bn006En006Enn006E006En;
  public SharedPreferences.OnSharedPreferenceChangeListener bnn006E006Enn006E006En = new sttsst.1(this);
  
  public sttsst() {}
  
  public static int b006B006B006B006B006B006Bkk006Bk()
  {
    return 85;
  }
  
  public static int b006Bk006B006B006B006Bkk006Bk()
  {
    return 2;
  }
  
  public static int bk006B006B006B006B006Bkk006Bk()
  {
    return 1;
  }
  
  /* Error */
  private void bkk006Bkkk006Bk006Bk()
  {
    // Byte code:
    //   0: iconst_1
    //   1: istore_1
    //   2: ldc 2
    //   4: ldc 105
    //   6: bipush 67
    //   8: iconst_3
    //   9: invokestatic 91	xxxxxx/uxxxxx:bb00620062bb0062b0062b0062	(Ljava/lang/String;CC)Ljava/lang/String;
    //   12: iconst_0
    //   13: anewarray 56	java/lang/Class
    //   16: invokevirtual 60	java/lang/Class:getMethod	(Ljava/lang/String;[Ljava/lang/Class;)Ljava/lang/reflect/Method;
    //   19: astore_2
    //   20: iconst_0
    //   21: anewarray 62	java/lang/Object
    //   24: astore_3
    //   25: aload_2
    //   26: aload_0
    //   27: aload_3
    //   28: invokevirtual 68	java/lang/reflect/Method:invoke	(Ljava/lang/Object;[Ljava/lang/Object;)Ljava/lang/Object;
    //   31: astore 5
    //   33: aload 5
    //   35: checkcast 70	java/lang/Integer
    //   38: invokevirtual 73	java/lang/Integer:intValue	()I
    //   41: istore 6
    //   43: getstatic 77	uuuuuu/sttsst:b006E006E006E006Enn006E006En	I
    //   46: istore 7
    //   48: ldc 2
    //   50: ldc 107
    //   52: sipush 148
    //   55: iconst_0
    //   56: invokestatic 91	xxxxxx/uxxxxx:bb00620062bb0062b0062b0062	(Ljava/lang/String;CC)Ljava/lang/String;
    //   59: iconst_0
    //   60: anewarray 56	java/lang/Class
    //   63: invokevirtual 60	java/lang/Class:getMethod	(Ljava/lang/String;[Ljava/lang/Class;)Ljava/lang/reflect/Method;
    //   66: astore 8
    //   68: iconst_0
    //   69: anewarray 62	java/lang/Object
    //   72: astore 9
    //   74: aload 8
    //   76: aconst_null
    //   77: aload 9
    //   79: invokevirtual 68	java/lang/reflect/Method:invoke	(Ljava/lang/Object;[Ljava/lang/Object;)Ljava/lang/Object;
    //   82: astore 11
    //   84: iload 7
    //   86: aload 11
    //   88: checkcast 70	java/lang/Integer
    //   91: invokevirtual 73	java/lang/Integer:intValue	()I
    //   94: iadd
    //   95: getstatic 77	uuuuuu/sttsst:b006E006E006E006Enn006E006En	I
    //   98: imul
    //   99: getstatic 83	uuuuuu/sttsst:bn006E006E006Enn006E006En	I
    //   102: irem
    //   103: istore 12
    //   105: ldc 2
    //   107: ldc 109
    //   109: sipush 198
    //   112: iconst_2
    //   113: invokestatic 91	xxxxxx/uxxxxx:bb00620062bb0062b0062b0062	(Ljava/lang/String;CC)Ljava/lang/String;
    //   116: iconst_0
    //   117: anewarray 56	java/lang/Class
    //   120: invokevirtual 60	java/lang/Class:getMethod	(Ljava/lang/String;[Ljava/lang/Class;)Ljava/lang/reflect/Method;
    //   123: astore 13
    //   125: iconst_0
    //   126: anewarray 62	java/lang/Object
    //   129: astore 14
    //   131: aload 13
    //   133: aconst_null
    //   134: aload 14
    //   136: invokevirtual 68	java/lang/reflect/Method:invoke	(Ljava/lang/Object;[Ljava/lang/Object;)Ljava/lang/Object;
    //   139: astore 16
    //   141: iload 12
    //   143: aload 16
    //   145: checkcast 70	java/lang/Integer
    //   148: invokevirtual 73	java/lang/Integer:intValue	()I
    //   151: if_icmpeq +13 -> 164
    //   154: bipush 71
    //   156: putstatic 77	uuuuuu/sttsst:b006E006E006E006Enn006E006En	I
    //   159: bipush 14
    //   161: putstatic 81	uuuuuu/sttsst:bnnnn006En006E006En	I
    //   164: ldc 2
    //   166: ldc 111
    //   168: sipush 138
    //   171: bipush 81
    //   173: iconst_0
    //   174: invokestatic 54	xxxxxx/uxxxxx:bbbb0062b0062b0062b0062	(Ljava/lang/String;CCC)Ljava/lang/String;
    //   177: iconst_0
    //   178: anewarray 56	java/lang/Class
    //   181: invokevirtual 60	java/lang/Class:getMethod	(Ljava/lang/String;[Ljava/lang/Class;)Ljava/lang/reflect/Method;
    //   184: astore 17
    //   186: iconst_0
    //   187: anewarray 62	java/lang/Object
    //   190: astore 18
    //   192: aload 17
    //   194: aload_0
    //   195: aload 18
    //   197: invokevirtual 68	java/lang/reflect/Method:invoke	(Ljava/lang/Object;[Ljava/lang/Object;)Ljava/lang/Object;
    //   200: astore 20
    //   202: aload 20
    //   204: checkcast 113	java/lang/Boolean
    //   207: invokevirtual 117	java/lang/Boolean:booleanValue	()Z
    //   210: ifne +10 -> 220
    //   213: aload_0
    //   214: invokevirtual 120	uuuuuu/sttsst:b006Bk006B006Bkk006Bk006Bk	()Z
    //   217: ifeq +387 -> 604
    //   220: iload 6
    //   222: ifle +382 -> 604
    //   225: iload_1
    //   226: istore 27
    //   228: ldc 2
    //   230: ldc 122
    //   232: sipush 150
    //   235: iconst_5
    //   236: invokestatic 91	xxxxxx/uxxxxx:bb00620062bb0062b0062b0062	(Ljava/lang/String;CC)Ljava/lang/String;
    //   239: iconst_0
    //   240: anewarray 56	java/lang/Class
    //   243: invokevirtual 60	java/lang/Class:getMethod	(Ljava/lang/String;[Ljava/lang/Class;)Ljava/lang/reflect/Method;
    //   246: astore 28
    //   248: iconst_0
    //   249: anewarray 62	java/lang/Object
    //   252: astore 29
    //   254: aload 28
    //   256: aload_0
    //   257: aload 29
    //   259: invokevirtual 68	java/lang/reflect/Method:invoke	(Ljava/lang/Object;[Ljava/lang/Object;)Ljava/lang/Object;
    //   262: astore 31
    //   264: aload 31
    //   266: checkcast 113	java/lang/Boolean
    //   269: invokevirtual 117	java/lang/Boolean:booleanValue	()Z
    //   272: ifne +434 -> 706
    //   275: ldc 2
    //   277: ldc 124
    //   279: sipush 217
    //   282: sipush 214
    //   285: iconst_0
    //   286: invokestatic 54	xxxxxx/uxxxxx:bbbb0062b0062b0062b0062	(Ljava/lang/String;CCC)Ljava/lang/String;
    //   289: iconst_0
    //   290: anewarray 56	java/lang/Class
    //   293: invokevirtual 60	java/lang/Class:getMethod	(Ljava/lang/String;[Ljava/lang/Class;)Ljava/lang/reflect/Method;
    //   296: astore 48
    //   298: iconst_0
    //   299: anewarray 62	java/lang/Object
    //   302: astore 49
    //   304: aload 48
    //   306: aload_0
    //   307: aload 49
    //   309: invokevirtual 68	java/lang/reflect/Method:invoke	(Ljava/lang/Object;[Ljava/lang/Object;)Ljava/lang/Object;
    //   312: astore 51
    //   314: aload 51
    //   316: checkcast 113	java/lang/Boolean
    //   319: invokevirtual 117	java/lang/Boolean:booleanValue	()Z
    //   322: ifne +384 -> 706
    //   325: iload_1
    //   326: istore 33
    //   328: ldc 2
    //   330: ldc 126
    //   332: sipush 232
    //   335: iconst_4
    //   336: invokestatic 91	xxxxxx/uxxxxx:bb00620062bb0062b0062b0062	(Ljava/lang/String;CC)Ljava/lang/String;
    //   339: iconst_0
    //   340: anewarray 56	java/lang/Class
    //   343: invokevirtual 60	java/lang/Class:getMethod	(Ljava/lang/String;[Ljava/lang/Class;)Ljava/lang/reflect/Method;
    //   346: astore 34
    //   348: iconst_0
    //   349: anewarray 62	java/lang/Object
    //   352: astore 35
    //   354: aload 34
    //   356: aload_0
    //   357: aload 35
    //   359: invokevirtual 68	java/lang/reflect/Method:invoke	(Ljava/lang/Object;[Ljava/lang/Object;)Ljava/lang/Object;
    //   362: astore 37
    //   364: aload 37
    //   366: checkcast 113	java/lang/Boolean
    //   369: invokevirtual 117	java/lang/Boolean:booleanValue	()Z
    //   372: ifne +192 -> 564
    //   375: aload_0
    //   376: getfield 130	uuuuuu/sttsst:bnnnnn006E006E006En	Luuuuuu/ttssst$tsssst;
    //   379: checkcast 132	uuuuuu/tsstst$tttsst
    //   382: iconst_0
    //   383: aconst_null
    //   384: invokeinterface 136 3 0
    //   389: return
    //   390: iload 33
    //   392: ifeq +343 -> 735
    //   395: aload_0
    //   396: getfield 130	uuuuuu/sttsst:bnnnnn006E006E006En	Luuuuuu/ttssst$tsssst;
    //   399: checkcast 132	uuuuuu/tsstst$tttsst
    //   402: iload_1
    //   403: aconst_null
    //   404: invokeinterface 136 3 0
    //   409: return
    //   410: aload_0
    //   411: getfield 130	uuuuuu/sttsst:bnnnnn006E006E006En	Luuuuuu/ttssst$tsssst;
    //   414: checkcast 132	uuuuuu/tsstst$tttsst
    //   417: astore 38
    //   419: new 138	java/lang/StringBuilder
    //   422: dup
    //   423: invokespecial 139	java/lang/StringBuilder:<init>	()V
    //   426: sipush 999
    //   429: invokestatic 145	java/lang/String:valueOf	(I)Ljava/lang/String;
    //   432: invokevirtual 149	java/lang/StringBuilder:append	(Ljava/lang/String;)Ljava/lang/StringBuilder;
    //   435: astore 39
    //   437: ldc -105
    //   439: sipush 138
    //   442: sipush 186
    //   445: iconst_0
    //   446: invokestatic 54	xxxxxx/uxxxxx:bbbb0062b0062b0062b0062	(Ljava/lang/String;CCC)Ljava/lang/String;
    //   449: astore 40
    //   451: iconst_4
    //   452: anewarray 56	java/lang/Class
    //   455: astore 41
    //   457: aload 41
    //   459: iconst_0
    //   460: ldc -115
    //   462: aastore
    //   463: aload 41
    //   465: iload_1
    //   466: getstatic 157	java/lang/Character:TYPE	Ljava/lang/Class;
    //   469: aastore
    //   470: aload 41
    //   472: iconst_2
    //   473: getstatic 157	java/lang/Character:TYPE	Ljava/lang/Class;
    //   476: aastore
    //   477: aload 41
    //   479: iconst_3
    //   480: getstatic 157	java/lang/Character:TYPE	Ljava/lang/Class;
    //   483: aastore
    //   484: ldc -97
    //   486: aload 40
    //   488: aload 41
    //   490: invokevirtual 60	java/lang/Class:getMethod	(Ljava/lang/String;[Ljava/lang/Class;)Ljava/lang/reflect/Method;
    //   493: astore 42
    //   495: iconst_4
    //   496: anewarray 62	java/lang/Object
    //   499: astore 43
    //   501: aload 43
    //   503: iconst_0
    //   504: ldc -95
    //   506: aastore
    //   507: aload 43
    //   509: iload_1
    //   510: iconst_2
    //   511: invokestatic 164	java/lang/Character:valueOf	(C)Ljava/lang/Character;
    //   514: aastore
    //   515: aload 43
    //   517: iconst_2
    //   518: bipush 59
    //   520: invokestatic 164	java/lang/Character:valueOf	(C)Ljava/lang/Character;
    //   523: aastore
    //   524: aload 43
    //   526: iconst_3
    //   527: iconst_0
    //   528: invokestatic 164	java/lang/Character:valueOf	(C)Ljava/lang/Character;
    //   531: aastore
    //   532: aload 42
    //   534: aconst_null
    //   535: aload 43
    //   537: invokevirtual 68	java/lang/reflect/Method:invoke	(Ljava/lang/Object;[Ljava/lang/Object;)Ljava/lang/Object;
    //   540: astore 45
    //   542: aload 38
    //   544: iload_1
    //   545: aload 39
    //   547: aload 45
    //   549: checkcast 141	java/lang/String
    //   552: invokevirtual 149	java/lang/StringBuilder:append	(Ljava/lang/String;)Ljava/lang/StringBuilder;
    //   555: invokevirtual 168	java/lang/StringBuilder:toString	()Ljava/lang/String;
    //   558: invokeinterface 136 3 0
    //   563: return
    //   564: iload 27
    //   566: ifeq -176 -> 390
    //   569: iload 6
    //   571: sipush 999
    //   574: if_icmpgt -164 -> 410
    //   577: aload_0
    //   578: getfield 130	uuuuuu/sttsst:bnnnnn006E006E006En	Luuuuuu/ttssst$tsssst;
    //   581: checkcast 132	uuuuuu/tsstst$tttsst
    //   584: iload_1
    //   585: iload 6
    //   587: invokestatic 145	java/lang/String:valueOf	(I)Ljava/lang/String;
    //   590: invokeinterface 136 3 0
    //   595: return
    //   596: astore 44
    //   598: aload 44
    //   600: invokevirtual 100	java/lang/reflect/InvocationTargetException:getCause	()Ljava/lang/Throwable;
    //   603: athrow
    //   604: iconst_4
    //   605: istore 21
    //   607: iload 21
    //   609: iconst_0
    //   610: idiv
    //   611: istore 21
    //   613: goto -6 -> 607
    //   616: astore 4
    //   618: aload 4
    //   620: invokevirtual 100	java/lang/reflect/InvocationTargetException:getCause	()Ljava/lang/Throwable;
    //   623: athrow
    //   624: astore 10
    //   626: aload 10
    //   628: invokevirtual 100	java/lang/reflect/InvocationTargetException:getCause	()Ljava/lang/Throwable;
    //   631: athrow
    //   632: astore 15
    //   634: aload 15
    //   636: invokevirtual 100	java/lang/reflect/InvocationTargetException:getCause	()Ljava/lang/Throwable;
    //   639: athrow
    //   640: astore 22
    //   642: ldc 2
    //   644: ldc -86
    //   646: bipush 112
    //   648: sipush 218
    //   651: iload_1
    //   652: i2c
    //   653: invokestatic 54	xxxxxx/uxxxxx:bbbb0062b0062b0062b0062	(Ljava/lang/String;CCC)Ljava/lang/String;
    //   656: iconst_0
    //   657: anewarray 56	java/lang/Class
    //   660: invokevirtual 60	java/lang/Class:getMethod	(Ljava/lang/String;[Ljava/lang/Class;)Ljava/lang/reflect/Method;
    //   663: astore 23
    //   665: iconst_0
    //   666: anewarray 62	java/lang/Object
    //   669: astore 24
    //   671: aload 23
    //   673: aconst_null
    //   674: aload 24
    //   676: invokevirtual 68	java/lang/reflect/Method:invoke	(Ljava/lang/Object;[Ljava/lang/Object;)Ljava/lang/Object;
    //   679: astore 26
    //   681: aload 26
    //   683: checkcast 70	java/lang/Integer
    //   686: invokevirtual 73	java/lang/Integer:intValue	()I
    //   689: putstatic 77	uuuuuu/sttsst:b006E006E006E006Enn006E006En	I
    //   692: iconst_0
    //   693: istore 27
    //   695: goto -467 -> 228
    //   698: astore 50
    //   700: aload 50
    //   702: invokevirtual 100	java/lang/reflect/InvocationTargetException:getCause	()Ljava/lang/Throwable;
    //   705: athrow
    //   706: aconst_null
    //   707: invokevirtual 173	java/lang/String:length	()I
    //   710: pop
    //   711: goto -5 -> 706
    //   714: astore 32
    //   716: bipush 53
    //   718: putstatic 77	uuuuuu/sttsst:b006E006E006E006Enn006E006En	I
    //   721: iconst_0
    //   722: istore 33
    //   724: goto -396 -> 328
    //   727: astore 30
    //   729: aload 30
    //   731: invokevirtual 100	java/lang/reflect/InvocationTargetException:getCause	()Ljava/lang/Throwable;
    //   734: athrow
    //   735: aload_0
    //   736: getfield 130	uuuuuu/sttsst:bnnnnn006E006E006En	Luuuuuu/ttssst$tsssst;
    //   739: checkcast 132	uuuuuu/tsstst$tttsst
    //   742: iconst_0
    //   743: aconst_null
    //   744: invokeinterface 136 3 0
    //   749: iload_1
    //   750: iconst_0
    //   751: idiv
    //   752: istore_1
    //   753: goto -4 -> 749
    //   756: astore 46
    //   758: bipush 48
    //   760: putstatic 77	uuuuuu/sttsst:b006E006E006E006Enn006E006En	I
    //   763: return
    //   764: astore 25
    //   766: aload 25
    //   768: invokevirtual 100	java/lang/reflect/InvocationTargetException:getCause	()Ljava/lang/Throwable;
    //   771: athrow
    //   772: astore 36
    //   774: aload 36
    //   776: invokevirtual 100	java/lang/reflect/InvocationTargetException:getCause	()Ljava/lang/Throwable;
    //   779: athrow
    //   780: astore 19
    //   782: aload 19
    //   784: invokevirtual 100	java/lang/reflect/InvocationTargetException:getCause	()Ljava/lang/Throwable;
    //   787: athrow
    // Local variable table:
    //   start	length	slot	name	signature
    //   0	788	0	this	sttsst
    //   1	751	1	bool1	boolean
    //   752	1	1	i	int
    //   19	7	2	localMethod1	java.lang.reflect.Method
    //   24	4	3	arrayOfObject1	Object[]
    //   616	3	4	localInvocationTargetException1	java.lang.reflect.InvocationTargetException
    //   31	3	5	localObject1	Object
    //   41	545	6	j	int
    //   46	49	7	k	int
    //   66	9	8	localMethod2	java.lang.reflect.Method
    //   72	6	9	arrayOfObject2	Object[]
    //   624	3	10	localInvocationTargetException2	java.lang.reflect.InvocationTargetException
    //   82	5	11	localObject2	Object
    //   103	49	12	m	int
    //   123	9	13	localMethod3	java.lang.reflect.Method
    //   129	6	14	arrayOfObject3	Object[]
    //   632	3	15	localInvocationTargetException3	java.lang.reflect.InvocationTargetException
    //   139	5	16	localObject3	Object
    //   184	9	17	localMethod4	java.lang.reflect.Method
    //   190	6	18	arrayOfObject4	Object[]
    //   780	3	19	localInvocationTargetException4	java.lang.reflect.InvocationTargetException
    //   200	3	20	localObject4	Object
    //   605	7	21	n	int
    //   640	1	22	localException1	Exception
    //   663	9	23	localMethod5	java.lang.reflect.Method
    //   669	6	24	arrayOfObject5	Object[]
    //   764	3	25	localInvocationTargetException5	java.lang.reflect.InvocationTargetException
    //   679	3	26	localObject5	Object
    //   226	468	27	bool2	boolean
    //   246	9	28	localMethod6	java.lang.reflect.Method
    //   252	6	29	arrayOfObject6	Object[]
    //   727	3	30	localInvocationTargetException6	java.lang.reflect.InvocationTargetException
    //   262	3	31	localObject6	Object
    //   714	1	32	localException2	Exception
    //   326	397	33	bool3	boolean
    //   346	9	34	localMethod7	java.lang.reflect.Method
    //   352	6	35	arrayOfObject7	Object[]
    //   772	3	36	localInvocationTargetException7	java.lang.reflect.InvocationTargetException
    //   362	3	37	localObject7	Object
    //   417	126	38	localTttsst	tsstst.tttsst
    //   435	111	39	localStringBuilder	StringBuilder
    //   449	38	40	str	String
    //   455	34	41	arrayOfClass	Class[]
    //   493	40	42	localMethod8	java.lang.reflect.Method
    //   499	37	43	arrayOfObject8	Object[]
    //   596	3	44	localInvocationTargetException8	java.lang.reflect.InvocationTargetException
    //   540	8	45	localObject8	Object
    //   756	1	46	localException3	Exception
    //   296	9	48	localMethod9	java.lang.reflect.Method
    //   302	6	49	arrayOfObject9	Object[]
    //   698	3	50	localInvocationTargetException9	java.lang.reflect.InvocationTargetException
    //   312	3	51	localObject9	Object
    // Exception table:
    //   from	to	target	type
    //   532	542	596	java/lang/reflect/InvocationTargetException
    //   25	33	616	java/lang/reflect/InvocationTargetException
    //   74	84	624	java/lang/reflect/InvocationTargetException
    //   131	141	632	java/lang/reflect/InvocationTargetException
    //   607	613	640	java/lang/Exception
    //   304	314	698	java/lang/reflect/InvocationTargetException
    //   706	711	714	java/lang/Exception
    //   254	264	727	java/lang/reflect/InvocationTargetException
    //   749	753	756	java/lang/Exception
    //   671	681	764	java/lang/reflect/InvocationTargetException
    //   354	364	772	java/lang/reflect/InvocationTargetException
    //   192	202	780	java/lang/reflect/InvocationTargetException
  }
  
  public static int bkkkkkk006Bk006Bk()
  {
    return 0;
  }
  
  /* Error */
  public boolean b006B006Bkkkk006Bk006Bk()
  {
    // Byte code:
    //   0: getstatic 77	uuuuuu/sttsst:b006E006E006E006Enn006E006En	I
    //   3: istore_1
    //   4: getstatic 77	uuuuuu/sttsst:b006E006E006E006Enn006E006En	I
    //   7: getstatic 75	uuuuuu/sttsst:b006En006E006Enn006E006En	I
    //   10: iadd
    //   11: getstatic 77	uuuuuu/sttsst:b006E006E006E006Enn006E006En	I
    //   14: imul
    //   15: istore_2
    //   16: ldc 2
    //   18: ldc -79
    //   20: sipush 185
    //   23: iconst_1
    //   24: invokestatic 91	xxxxxx/uxxxxx:bb00620062bb0062b0062b0062	(Ljava/lang/String;CC)Ljava/lang/String;
    //   27: iconst_0
    //   28: anewarray 56	java/lang/Class
    //   31: invokevirtual 60	java/lang/Class:getMethod	(Ljava/lang/String;[Ljava/lang/Class;)Ljava/lang/reflect/Method;
    //   34: astore_3
    //   35: iconst_0
    //   36: anewarray 62	java/lang/Object
    //   39: astore 4
    //   41: aload_3
    //   42: aconst_null
    //   43: aload 4
    //   45: invokevirtual 68	java/lang/reflect/Method:invoke	(Ljava/lang/Object;[Ljava/lang/Object;)Ljava/lang/Object;
    //   48: astore 6
    //   50: iload_2
    //   51: aload 6
    //   53: checkcast 70	java/lang/Integer
    //   56: invokevirtual 73	java/lang/Integer:intValue	()I
    //   59: irem
    //   60: getstatic 81	uuuuuu/sttsst:bnnnn006En006E006En	I
    //   63: if_icmpeq +96 -> 159
    //   66: ldc 2
    //   68: ldc -77
    //   70: sipush 173
    //   73: iconst_2
    //   74: invokestatic 91	xxxxxx/uxxxxx:bb00620062bb0062b0062b0062	(Ljava/lang/String;CC)Ljava/lang/String;
    //   77: iconst_0
    //   78: anewarray 56	java/lang/Class
    //   81: invokevirtual 60	java/lang/Class:getMethod	(Ljava/lang/String;[Ljava/lang/Class;)Ljava/lang/reflect/Method;
    //   84: astore 45
    //   86: iconst_0
    //   87: anewarray 62	java/lang/Object
    //   90: astore 46
    //   92: aload 45
    //   94: aconst_null
    //   95: aload 46
    //   97: invokevirtual 68	java/lang/reflect/Method:invoke	(Ljava/lang/Object;[Ljava/lang/Object;)Ljava/lang/Object;
    //   100: astore 48
    //   102: aload 48
    //   104: checkcast 70	java/lang/Integer
    //   107: invokevirtual 73	java/lang/Integer:intValue	()I
    //   110: putstatic 77	uuuuuu/sttsst:b006E006E006E006Enn006E006En	I
    //   113: ldc 2
    //   115: ldc -75
    //   117: bipush 23
    //   119: iconst_3
    //   120: invokestatic 91	xxxxxx/uxxxxx:bb00620062bb0062b0062b0062	(Ljava/lang/String;CC)Ljava/lang/String;
    //   123: iconst_0
    //   124: anewarray 56	java/lang/Class
    //   127: invokevirtual 60	java/lang/Class:getMethod	(Ljava/lang/String;[Ljava/lang/Class;)Ljava/lang/reflect/Method;
    //   130: astore 49
    //   132: iconst_0
    //   133: anewarray 62	java/lang/Object
    //   136: astore 50
    //   138: aload 49
    //   140: aconst_null
    //   141: aload 50
    //   143: invokevirtual 68	java/lang/reflect/Method:invoke	(Ljava/lang/Object;[Ljava/lang/Object;)Ljava/lang/Object;
    //   146: astore 52
    //   148: aload 52
    //   150: checkcast 70	java/lang/Integer
    //   153: invokevirtual 73	java/lang/Integer:intValue	()I
    //   156: putstatic 81	uuuuuu/sttsst:bnnnn006En006E006En	I
    //   159: iload_1
    //   160: iload_1
    //   161: getstatic 75	uuuuuu/sttsst:b006En006E006Enn006E006En	I
    //   164: iadd
    //   165: imul
    //   166: istore 7
    //   168: ldc 2
    //   170: ldc -73
    //   172: bipush 46
    //   174: sipush 170
    //   177: iconst_3
    //   178: invokestatic 54	xxxxxx/uxxxxx:bbbb0062b0062b0062b0062	(Ljava/lang/String;CCC)Ljava/lang/String;
    //   181: iconst_0
    //   182: anewarray 56	java/lang/Class
    //   185: invokevirtual 60	java/lang/Class:getMethod	(Ljava/lang/String;[Ljava/lang/Class;)Ljava/lang/reflect/Method;
    //   188: astore 8
    //   190: iconst_0
    //   191: anewarray 62	java/lang/Object
    //   194: astore 9
    //   196: aload 8
    //   198: aconst_null
    //   199: aload 9
    //   201: invokevirtual 68	java/lang/reflect/Method:invoke	(Ljava/lang/Object;[Ljava/lang/Object;)Ljava/lang/Object;
    //   204: astore 11
    //   206: iload 7
    //   208: aload 11
    //   210: checkcast 70	java/lang/Integer
    //   213: invokevirtual 73	java/lang/Integer:intValue	()I
    //   216: irem
    //   217: tableswitch	default:+19->236, 0:+161->378
    //   236: bipush 96
    //   238: putstatic 77	uuuuuu/sttsst:b006E006E006E006Enn006E006En	I
    //   241: ldc 2
    //   243: ldc -71
    //   245: bipush 29
    //   247: iconst_2
    //   248: invokestatic 91	xxxxxx/uxxxxx:bb00620062bb0062b0062b0062	(Ljava/lang/String;CC)Ljava/lang/String;
    //   251: iconst_0
    //   252: anewarray 56	java/lang/Class
    //   255: invokevirtual 60	java/lang/Class:getMethod	(Ljava/lang/String;[Ljava/lang/Class;)Ljava/lang/reflect/Method;
    //   258: astore 36
    //   260: iconst_0
    //   261: anewarray 62	java/lang/Object
    //   264: astore 37
    //   266: aload 36
    //   268: aconst_null
    //   269: aload 37
    //   271: invokevirtual 68	java/lang/reflect/Method:invoke	(Ljava/lang/Object;[Ljava/lang/Object;)Ljava/lang/Object;
    //   274: astore 39
    //   276: aload 39
    //   278: checkcast 70	java/lang/Integer
    //   281: invokevirtual 73	java/lang/Integer:intValue	()I
    //   284: putstatic 81	uuuuuu/sttsst:bnnnn006En006E006En	I
    //   287: getstatic 77	uuuuuu/sttsst:b006E006E006E006Enn006E006En	I
    //   290: istore 40
    //   292: iload 40
    //   294: iload 40
    //   296: getstatic 75	uuuuuu/sttsst:b006En006E006Enn006E006En	I
    //   299: iadd
    //   300: imul
    //   301: getstatic 83	uuuuuu/sttsst:bn006E006E006Enn006E006En	I
    //   304: irem
    //   305: tableswitch	default:+19->324, 0:+73->378
    //   324: ldc 2
    //   326: ldc -69
    //   328: sipush 226
    //   331: bipush 20
    //   333: iconst_2
    //   334: invokestatic 54	xxxxxx/uxxxxx:bbbb0062b0062b0062b0062	(Ljava/lang/String;CCC)Ljava/lang/String;
    //   337: iconst_0
    //   338: anewarray 56	java/lang/Class
    //   341: invokevirtual 60	java/lang/Class:getMethod	(Ljava/lang/String;[Ljava/lang/Class;)Ljava/lang/reflect/Method;
    //   344: astore 41
    //   346: iconst_0
    //   347: anewarray 62	java/lang/Object
    //   350: astore 42
    //   352: aload 41
    //   354: aconst_null
    //   355: aload 42
    //   357: invokevirtual 68	java/lang/reflect/Method:invoke	(Ljava/lang/Object;[Ljava/lang/Object;)Ljava/lang/Object;
    //   360: astore 44
    //   362: aload 44
    //   364: checkcast 70	java/lang/Integer
    //   367: invokevirtual 73	java/lang/Integer:intValue	()I
    //   370: putstatic 77	uuuuuu/sttsst:b006E006E006E006Enn006E006En	I
    //   373: bipush 73
    //   375: putstatic 81	uuuuuu/sttsst:bnnnn006En006E006En	I
    //   378: ldc -67
    //   380: sipush 140
    //   383: iconst_5
    //   384: invokestatic 91	xxxxxx/uxxxxx:bb00620062bb0062b0062b0062	(Ljava/lang/String;CC)Ljava/lang/String;
    //   387: astore 12
    //   389: iconst_3
    //   390: anewarray 56	java/lang/Class
    //   393: astore 13
    //   395: aload 13
    //   397: iconst_0
    //   398: ldc -115
    //   400: aastore
    //   401: aload 13
    //   403: iconst_1
    //   404: getstatic 157	java/lang/Character:TYPE	Ljava/lang/Class;
    //   407: aastore
    //   408: aload 13
    //   410: iconst_2
    //   411: getstatic 157	java/lang/Character:TYPE	Ljava/lang/Class;
    //   414: aastore
    //   415: ldc -97
    //   417: aload 12
    //   419: aload 13
    //   421: invokevirtual 60	java/lang/Class:getMethod	(Ljava/lang/String;[Ljava/lang/Class;)Ljava/lang/reflect/Method;
    //   424: astore 14
    //   426: iconst_3
    //   427: anewarray 62	java/lang/Object
    //   430: astore 15
    //   432: aload 15
    //   434: iconst_0
    //   435: ldc -65
    //   437: aastore
    //   438: aload 15
    //   440: iconst_1
    //   441: sipush 181
    //   444: invokestatic 164	java/lang/Character:valueOf	(C)Ljava/lang/Character;
    //   447: aastore
    //   448: aload 15
    //   450: iconst_2
    //   451: iconst_5
    //   452: invokestatic 164	java/lang/Character:valueOf	(C)Ljava/lang/Character;
    //   455: aastore
    //   456: aload 14
    //   458: aconst_null
    //   459: aload 15
    //   461: invokevirtual 68	java/lang/reflect/Method:invoke	(Ljava/lang/Object;[Ljava/lang/Object;)Ljava/lang/Object;
    //   464: astore 17
    //   466: aload 17
    //   468: checkcast 141	java/lang/String
    //   471: astore 18
    //   473: aload_0
    //   474: getfield 193	uuuuuu/sttsst:b006E006En006Enn006E006En	Lcom/db/pwcc/dbmobile/secure/preferences/SharedPreferencesHelper;
    //   477: astore 19
    //   479: ldc -61
    //   481: sipush 226
    //   484: iconst_4
    //   485: invokestatic 91	xxxxxx/uxxxxx:bb00620062bb0062b0062b0062	(Ljava/lang/String;CC)Ljava/lang/String;
    //   488: astore 20
    //   490: iconst_3
    //   491: anewarray 56	java/lang/Class
    //   494: astore 21
    //   496: aload 21
    //   498: iconst_0
    //   499: ldc -115
    //   501: aastore
    //   502: aload 21
    //   504: iconst_1
    //   505: getstatic 157	java/lang/Character:TYPE	Ljava/lang/Class;
    //   508: aastore
    //   509: aload 21
    //   511: iconst_2
    //   512: getstatic 157	java/lang/Character:TYPE	Ljava/lang/Class;
    //   515: aastore
    //   516: ldc -97
    //   518: aload 20
    //   520: aload 21
    //   522: invokevirtual 60	java/lang/Class:getMethod	(Ljava/lang/String;[Ljava/lang/Class;)Ljava/lang/reflect/Method;
    //   525: astore 22
    //   527: iconst_3
    //   528: anewarray 62	java/lang/Object
    //   531: astore 23
    //   533: aload 23
    //   535: iconst_0
    //   536: ldc -59
    //   538: aastore
    //   539: aload 23
    //   541: iconst_1
    //   542: sipush 175
    //   545: invokestatic 164	java/lang/Character:valueOf	(C)Ljava/lang/Character;
    //   548: aastore
    //   549: aload 23
    //   551: iconst_2
    //   552: iconst_3
    //   553: invokestatic 164	java/lang/Character:valueOf	(C)Ljava/lang/Character;
    //   556: aastore
    //   557: aload 22
    //   559: aconst_null
    //   560: aload 23
    //   562: invokevirtual 68	java/lang/reflect/Method:invoke	(Ljava/lang/Object;[Ljava/lang/Object;)Ljava/lang/Object;
    //   565: astore 25
    //   567: aload 25
    //   569: checkcast 141	java/lang/String
    //   572: astore 26
    //   574: ldc 2
    //   576: ldc -57
    //   578: bipush 86
    //   580: iconst_2
    //   581: invokestatic 91	xxxxxx/uxxxxx:bb00620062bb0062b0062b0062	(Ljava/lang/String;CC)Ljava/lang/String;
    //   584: iconst_0
    //   585: anewarray 56	java/lang/Class
    //   588: invokevirtual 60	java/lang/Class:getMethod	(Ljava/lang/String;[Ljava/lang/Class;)Ljava/lang/reflect/Method;
    //   591: astore 27
    //   593: iconst_0
    //   594: anewarray 62	java/lang/Object
    //   597: astore 28
    //   599: aload 27
    //   601: aconst_null
    //   602: aload 28
    //   604: invokevirtual 68	java/lang/reflect/Method:invoke	(Ljava/lang/Object;[Ljava/lang/Object;)Ljava/lang/Object;
    //   607: astore 30
    //   609: aload 30
    //   611: checkcast 70	java/lang/Integer
    //   614: invokevirtual 73	java/lang/Integer:intValue	()I
    //   617: istore 31
    //   619: iload 31
    //   621: iload 31
    //   623: getstatic 75	uuuuuu/sttsst:b006En006E006Enn006E006En	I
    //   626: iadd
    //   627: imul
    //   628: getstatic 83	uuuuuu/sttsst:bn006E006E006Enn006E006En	I
    //   631: irem
    //   632: tableswitch	default:+20->652, 0:+30->662
    //   652: bipush 74
    //   654: putstatic 77	uuuuuu/sttsst:b006E006E006E006Enn006E006En	I
    //   657: bipush 99
    //   659: putstatic 81	uuuuuu/sttsst:bnnnn006En006E006En	I
    //   662: ldc -55
    //   664: ldc -53
    //   666: bipush 56
    //   668: bipush 73
    //   670: iconst_3
    //   671: invokestatic 54	xxxxxx/uxxxxx:bbbb0062b0062b0062b0062	(Ljava/lang/String;CCC)Ljava/lang/String;
    //   674: iconst_1
    //   675: anewarray 56	java/lang/Class
    //   678: dup
    //   679: iconst_0
    //   680: ldc -115
    //   682: aastore
    //   683: invokevirtual 60	java/lang/Class:getMethod	(Ljava/lang/String;[Ljava/lang/Class;)Ljava/lang/reflect/Method;
    //   686: astore 32
    //   688: iconst_1
    //   689: anewarray 62	java/lang/Object
    //   692: dup
    //   693: iconst_0
    //   694: aload 26
    //   696: aastore
    //   697: astore 33
    //   699: aload 32
    //   701: aload 19
    //   703: aload 33
    //   705: invokevirtual 68	java/lang/reflect/Method:invoke	(Ljava/lang/Object;[Ljava/lang/Object;)Ljava/lang/Object;
    //   708: astore 35
    //   710: aload 18
    //   712: aload 35
    //   714: checkcast 141	java/lang/String
    //   717: invokevirtual 207	java/lang/String:equals	(Ljava/lang/Object;)Z
    //   720: ireturn
    //   721: astore 43
    //   723: aload 43
    //   725: invokevirtual 100	java/lang/reflect/InvocationTargetException:getCause	()Ljava/lang/Throwable;
    //   728: athrow
    //   729: astore 10
    //   731: aload 10
    //   733: invokevirtual 100	java/lang/reflect/InvocationTargetException:getCause	()Ljava/lang/Throwable;
    //   736: athrow
    //   737: astore 5
    //   739: aload 5
    //   741: invokevirtual 100	java/lang/reflect/InvocationTargetException:getCause	()Ljava/lang/Throwable;
    //   744: athrow
    //   745: astore 34
    //   747: aload 34
    //   749: invokevirtual 100	java/lang/reflect/InvocationTargetException:getCause	()Ljava/lang/Throwable;
    //   752: athrow
    //   753: astore 16
    //   755: aload 16
    //   757: invokevirtual 100	java/lang/reflect/InvocationTargetException:getCause	()Ljava/lang/Throwable;
    //   760: athrow
    //   761: astore 38
    //   763: aload 38
    //   765: invokevirtual 100	java/lang/reflect/InvocationTargetException:getCause	()Ljava/lang/Throwable;
    //   768: athrow
    //   769: astore 24
    //   771: aload 24
    //   773: invokevirtual 100	java/lang/reflect/InvocationTargetException:getCause	()Ljava/lang/Throwable;
    //   776: athrow
    //   777: astore 29
    //   779: aload 29
    //   781: invokevirtual 100	java/lang/reflect/InvocationTargetException:getCause	()Ljava/lang/Throwable;
    //   784: athrow
    //   785: astore 47
    //   787: aload 47
    //   789: invokevirtual 100	java/lang/reflect/InvocationTargetException:getCause	()Ljava/lang/Throwable;
    //   792: athrow
    //   793: astore 51
    //   795: aload 51
    //   797: invokevirtual 100	java/lang/reflect/InvocationTargetException:getCause	()Ljava/lang/Throwable;
    //   800: athrow
    // Local variable table:
    //   start	length	slot	name	signature
    //   0	801	0	this	sttsst
    //   3	163	1	i	int
    //   15	45	2	j	int
    //   34	8	3	localMethod1	java.lang.reflect.Method
    //   39	5	4	arrayOfObject1	Object[]
    //   737	3	5	localInvocationTargetException1	java.lang.reflect.InvocationTargetException
    //   48	4	6	localObject1	Object
    //   166	51	7	k	int
    //   188	9	8	localMethod2	java.lang.reflect.Method
    //   194	6	9	arrayOfObject2	Object[]
    //   729	3	10	localInvocationTargetException2	java.lang.reflect.InvocationTargetException
    //   204	5	11	localObject2	Object
    //   387	31	12	str1	String
    //   393	27	13	arrayOfClass1	Class[]
    //   424	33	14	localMethod3	java.lang.reflect.Method
    //   430	30	15	arrayOfObject3	Object[]
    //   753	3	16	localInvocationTargetException3	java.lang.reflect.InvocationTargetException
    //   464	3	17	localObject3	Object
    //   471	240	18	str2	String
    //   477	225	19	localSharedPreferencesHelper	SharedPreferencesHelper
    //   488	31	20	str3	String
    //   494	27	21	arrayOfClass2	Class[]
    //   525	33	22	localMethod4	java.lang.reflect.Method
    //   531	30	23	arrayOfObject4	Object[]
    //   769	3	24	localInvocationTargetException4	java.lang.reflect.InvocationTargetException
    //   565	3	25	localObject4	Object
    //   572	123	26	str4	String
    //   591	9	27	localMethod5	java.lang.reflect.Method
    //   597	6	28	arrayOfObject5	Object[]
    //   777	3	29	localInvocationTargetException5	java.lang.reflect.InvocationTargetException
    //   607	3	30	localObject5	Object
    //   617	11	31	m	int
    //   686	14	32	localMethod6	java.lang.reflect.Method
    //   697	7	33	arrayOfObject6	Object[]
    //   745	3	34	localInvocationTargetException6	java.lang.reflect.InvocationTargetException
    //   708	5	35	localObject6	Object
    //   258	9	36	localMethod7	java.lang.reflect.Method
    //   264	6	37	arrayOfObject7	Object[]
    //   761	3	38	localInvocationTargetException7	java.lang.reflect.InvocationTargetException
    //   274	3	39	localObject7	Object
    //   290	11	40	n	int
    //   344	9	41	localMethod8	java.lang.reflect.Method
    //   350	6	42	arrayOfObject8	Object[]
    //   721	3	43	localInvocationTargetException8	java.lang.reflect.InvocationTargetException
    //   360	3	44	localObject8	Object
    //   84	9	45	localMethod9	java.lang.reflect.Method
    //   90	6	46	arrayOfObject9	Object[]
    //   785	3	47	localInvocationTargetException9	java.lang.reflect.InvocationTargetException
    //   100	3	48	localObject9	Object
    //   130	9	49	localMethod10	java.lang.reflect.Method
    //   136	6	50	arrayOfObject10	Object[]
    //   793	3	51	localInvocationTargetException10	java.lang.reflect.InvocationTargetException
    //   146	3	52	localObject10	Object
    // Exception table:
    //   from	to	target	type
    //   352	362	721	java/lang/reflect/InvocationTargetException
    //   196	206	729	java/lang/reflect/InvocationTargetException
    //   41	50	737	java/lang/reflect/InvocationTargetException
    //   699	710	745	java/lang/reflect/InvocationTargetException
    //   456	466	753	java/lang/reflect/InvocationTargetException
    //   266	276	761	java/lang/reflect/InvocationTargetException
    //   557	567	769	java/lang/reflect/InvocationTargetException
    //   599	609	777	java/lang/reflect/InvocationTargetException
    //   92	102	785	java/lang/reflect/InvocationTargetException
    //   138	148	793	java/lang/reflect/InvocationTargetException
  }
  
  /* Error */
  public void b006Bkk006B006B006Bkk006Bk(boolean paramBoolean)
  {
    // Byte code:
    //   0: getstatic 77	uuuuuu/sttsst:b006E006E006E006Enn006E006En	I
    //   3: istore_2
    //   4: ldc 2
    //   6: ldc -45
    //   8: bipush 80
    //   10: bipush 94
    //   12: iconst_3
    //   13: invokestatic 54	xxxxxx/uxxxxx:bbbb0062b0062b0062b0062	(Ljava/lang/String;CCC)Ljava/lang/String;
    //   16: iconst_0
    //   17: anewarray 56	java/lang/Class
    //   20: invokevirtual 60	java/lang/Class:getMethod	(Ljava/lang/String;[Ljava/lang/Class;)Ljava/lang/reflect/Method;
    //   23: astore_3
    //   24: iconst_0
    //   25: anewarray 62	java/lang/Object
    //   28: astore 4
    //   30: aload_3
    //   31: aconst_null
    //   32: aload 4
    //   34: invokevirtual 68	java/lang/reflect/Method:invoke	(Ljava/lang/Object;[Ljava/lang/Object;)Ljava/lang/Object;
    //   37: astore 6
    //   39: iload_2
    //   40: iload_2
    //   41: aload 6
    //   43: checkcast 70	java/lang/Integer
    //   46: invokevirtual 73	java/lang/Integer:intValue	()I
    //   49: iadd
    //   50: imul
    //   51: getstatic 83	uuuuuu/sttsst:bn006E006E006Enn006E006En	I
    //   54: irem
    //   55: tableswitch	default:+17->72, 0:+69->124
    //   72: ldc 2
    //   74: ldc -43
    //   76: sipush 194
    //   79: iconst_2
    //   80: invokestatic 91	xxxxxx/uxxxxx:bb00620062bb0062b0062b0062	(Ljava/lang/String;CC)Ljava/lang/String;
    //   83: iconst_0
    //   84: anewarray 56	java/lang/Class
    //   87: invokevirtual 60	java/lang/Class:getMethod	(Ljava/lang/String;[Ljava/lang/Class;)Ljava/lang/reflect/Method;
    //   90: astore 22
    //   92: iconst_0
    //   93: anewarray 62	java/lang/Object
    //   96: astore 23
    //   98: aload 22
    //   100: aconst_null
    //   101: aload 23
    //   103: invokevirtual 68	java/lang/reflect/Method:invoke	(Ljava/lang/Object;[Ljava/lang/Object;)Ljava/lang/Object;
    //   106: astore 25
    //   108: aload 25
    //   110: checkcast 70	java/lang/Integer
    //   113: invokevirtual 73	java/lang/Integer:intValue	()I
    //   116: putstatic 77	uuuuuu/sttsst:b006E006E006E006Enn006E006En	I
    //   119: bipush 93
    //   121: putstatic 81	uuuuuu/sttsst:bnnnn006En006E006En	I
    //   124: aload_0
    //   125: iload_1
    //   126: putfield 32	uuuuuu/sttsst:b006Enn006Enn006E006En	Z
    //   129: iconst_m1
    //   130: newarray int
    //   132: pop
    //   133: goto -4 -> 129
    //   136: astore 7
    //   138: getstatic 77	uuuuuu/sttsst:b006E006E006E006Enn006E006En	I
    //   141: getstatic 75	uuuuuu/sttsst:b006En006E006Enn006E006En	I
    //   144: iadd
    //   145: getstatic 77	uuuuuu/sttsst:b006E006E006E006Enn006E006En	I
    //   148: imul
    //   149: getstatic 83	uuuuuu/sttsst:bn006E006E006Enn006E006En	I
    //   152: irem
    //   153: getstatic 81	uuuuuu/sttsst:bnnnn006En006E006En	I
    //   156: if_icmpeq +173 -> 329
    //   159: getstatic 77	uuuuuu/sttsst:b006E006E006E006Enn006E006En	I
    //   162: getstatic 75	uuuuuu/sttsst:b006En006E006Enn006E006En	I
    //   165: iadd
    //   166: getstatic 77	uuuuuu/sttsst:b006E006E006E006Enn006E006En	I
    //   169: imul
    //   170: istore 8
    //   172: ldc 2
    //   174: ldc -41
    //   176: sipush 233
    //   179: iconst_5
    //   180: invokestatic 91	xxxxxx/uxxxxx:bb00620062bb0062b0062b0062	(Ljava/lang/String;CC)Ljava/lang/String;
    //   183: iconst_0
    //   184: anewarray 56	java/lang/Class
    //   187: invokevirtual 60	java/lang/Class:getMethod	(Ljava/lang/String;[Ljava/lang/Class;)Ljava/lang/reflect/Method;
    //   190: astore 9
    //   192: iconst_0
    //   193: anewarray 62	java/lang/Object
    //   196: astore 10
    //   198: aload 9
    //   200: aconst_null
    //   201: aload 10
    //   203: invokevirtual 68	java/lang/reflect/Method:invoke	(Ljava/lang/Object;[Ljava/lang/Object;)Ljava/lang/Object;
    //   206: astore 12
    //   208: iload 8
    //   210: aload 12
    //   212: checkcast 70	java/lang/Integer
    //   215: invokevirtual 73	java/lang/Integer:intValue	()I
    //   218: irem
    //   219: getstatic 81	uuuuuu/sttsst:bnnnn006En006E006En	I
    //   222: if_icmpeq +13 -> 235
    //   225: bipush 56
    //   227: putstatic 77	uuuuuu/sttsst:b006E006E006E006Enn006E006En	I
    //   230: bipush 84
    //   232: putstatic 81	uuuuuu/sttsst:bnnnn006En006E006En	I
    //   235: ldc 2
    //   237: ldc -39
    //   239: bipush 23
    //   241: bipush 88
    //   243: iconst_0
    //   244: invokestatic 54	xxxxxx/uxxxxx:bbbb0062b0062b0062b0062	(Ljava/lang/String;CCC)Ljava/lang/String;
    //   247: iconst_0
    //   248: anewarray 56	java/lang/Class
    //   251: invokevirtual 60	java/lang/Class:getMethod	(Ljava/lang/String;[Ljava/lang/Class;)Ljava/lang/reflect/Method;
    //   254: astore 13
    //   256: iconst_0
    //   257: anewarray 62	java/lang/Object
    //   260: astore 14
    //   262: aload 13
    //   264: aconst_null
    //   265: aload 14
    //   267: invokevirtual 68	java/lang/reflect/Method:invoke	(Ljava/lang/Object;[Ljava/lang/Object;)Ljava/lang/Object;
    //   270: astore 16
    //   272: aload 16
    //   274: checkcast 70	java/lang/Integer
    //   277: invokevirtual 73	java/lang/Integer:intValue	()I
    //   280: putstatic 77	uuuuuu/sttsst:b006E006E006E006Enn006E006En	I
    //   283: ldc 2
    //   285: ldc -37
    //   287: bipush 85
    //   289: iconst_1
    //   290: invokestatic 91	xxxxxx/uxxxxx:bb00620062bb0062b0062b0062	(Ljava/lang/String;CC)Ljava/lang/String;
    //   293: iconst_0
    //   294: anewarray 56	java/lang/Class
    //   297: invokevirtual 60	java/lang/Class:getMethod	(Ljava/lang/String;[Ljava/lang/Class;)Ljava/lang/reflect/Method;
    //   300: astore 17
    //   302: iconst_0
    //   303: anewarray 62	java/lang/Object
    //   306: astore 18
    //   308: aload 17
    //   310: aconst_null
    //   311: aload 18
    //   313: invokevirtual 68	java/lang/reflect/Method:invoke	(Ljava/lang/Object;[Ljava/lang/Object;)Ljava/lang/Object;
    //   316: astore 20
    //   318: aload 20
    //   320: checkcast 70	java/lang/Integer
    //   323: invokevirtual 73	java/lang/Integer:intValue	()I
    //   326: putstatic 81	uuuuuu/sttsst:bnnnn006En006E006En	I
    //   329: bipush 84
    //   331: putstatic 77	uuuuuu/sttsst:b006E006E006E006Enn006E006En	I
    //   334: return
    //   335: astore 15
    //   337: aload 15
    //   339: invokevirtual 100	java/lang/reflect/InvocationTargetException:getCause	()Ljava/lang/Throwable;
    //   342: athrow
    //   343: astore 19
    //   345: aload 19
    //   347: invokevirtual 100	java/lang/reflect/InvocationTargetException:getCause	()Ljava/lang/Throwable;
    //   350: athrow
    //   351: astore 24
    //   353: aload 24
    //   355: invokevirtual 100	java/lang/reflect/InvocationTargetException:getCause	()Ljava/lang/Throwable;
    //   358: athrow
    //   359: astore 11
    //   361: aload 11
    //   363: invokevirtual 100	java/lang/reflect/InvocationTargetException:getCause	()Ljava/lang/Throwable;
    //   366: athrow
    //   367: astore 5
    //   369: aload 5
    //   371: invokevirtual 100	java/lang/reflect/InvocationTargetException:getCause	()Ljava/lang/Throwable;
    //   374: athrow
    // Local variable table:
    //   start	length	slot	name	signature
    //   0	375	0	this	sttsst
    //   0	375	1	paramBoolean	boolean
    //   3	48	2	i	int
    //   23	8	3	localMethod1	java.lang.reflect.Method
    //   28	5	4	arrayOfObject1	Object[]
    //   367	3	5	localInvocationTargetException1	java.lang.reflect.InvocationTargetException
    //   37	5	6	localObject1	Object
    //   136	1	7	localException	Exception
    //   170	49	8	j	int
    //   190	9	9	localMethod2	java.lang.reflect.Method
    //   196	6	10	arrayOfObject2	Object[]
    //   359	3	11	localInvocationTargetException2	java.lang.reflect.InvocationTargetException
    //   206	5	12	localObject2	Object
    //   254	9	13	localMethod3	java.lang.reflect.Method
    //   260	6	14	arrayOfObject3	Object[]
    //   335	3	15	localInvocationTargetException3	java.lang.reflect.InvocationTargetException
    //   270	3	16	localObject3	Object
    //   300	9	17	localMethod4	java.lang.reflect.Method
    //   306	6	18	arrayOfObject4	Object[]
    //   343	3	19	localInvocationTargetException4	java.lang.reflect.InvocationTargetException
    //   316	3	20	localObject4	Object
    //   90	9	22	localMethod5	java.lang.reflect.Method
    //   96	6	23	arrayOfObject5	Object[]
    //   351	3	24	localInvocationTargetException5	java.lang.reflect.InvocationTargetException
    //   106	3	25	localObject5	Object
    // Exception table:
    //   from	to	target	type
    //   129	133	136	java/lang/Exception
    //   262	272	335	java/lang/reflect/InvocationTargetException
    //   308	318	343	java/lang/reflect/InvocationTargetException
    //   98	108	351	java/lang/reflect/InvocationTargetException
    //   198	208	359	java/lang/reflect/InvocationTargetException
    //   30	39	367	java/lang/reflect/InvocationTargetException
  }
  
  /* Error */
  @android.support.annotation.CallSuper
  public void b006Bkk006Bkkkk006Bk(V paramV)
  {
    // Byte code:
    //   0: getstatic 77	uuuuuu/sttsst:b006E006E006E006Enn006E006En	I
    //   3: istore_2
    //   4: iload_2
    //   5: iload_2
    //   6: getstatic 75	uuuuuu/sttsst:b006En006E006Enn006E006En	I
    //   9: iadd
    //   10: imul
    //   11: istore_3
    //   12: ldc 2
    //   14: ldc -32
    //   16: bipush 78
    //   18: iconst_4
    //   19: invokestatic 91	xxxxxx/uxxxxx:bb00620062bb0062b0062b0062	(Ljava/lang/String;CC)Ljava/lang/String;
    //   22: iconst_0
    //   23: anewarray 56	java/lang/Class
    //   26: invokevirtual 60	java/lang/Class:getMethod	(Ljava/lang/String;[Ljava/lang/Class;)Ljava/lang/reflect/Method;
    //   29: astore 4
    //   31: iconst_0
    //   32: anewarray 62	java/lang/Object
    //   35: astore 5
    //   37: aload 4
    //   39: aconst_null
    //   40: aload 5
    //   42: invokevirtual 68	java/lang/reflect/Method:invoke	(Ljava/lang/Object;[Ljava/lang/Object;)Ljava/lang/Object;
    //   45: astore 7
    //   47: iload_3
    //   48: aload 7
    //   50: checkcast 70	java/lang/Integer
    //   53: invokevirtual 73	java/lang/Integer:intValue	()I
    //   56: irem
    //   57: tableswitch	default:+19->76, 0:+193->250
    //   76: ldc 2
    //   78: ldc -75
    //   80: sipush 139
    //   83: sipush 138
    //   86: iconst_0
    //   87: invokestatic 54	xxxxxx/uxxxxx:bbbb0062b0062b0062b0062	(Ljava/lang/String;CCC)Ljava/lang/String;
    //   90: iconst_0
    //   91: anewarray 56	java/lang/Class
    //   94: invokevirtual 60	java/lang/Class:getMethod	(Ljava/lang/String;[Ljava/lang/Class;)Ljava/lang/reflect/Method;
    //   97: astore 31
    //   99: iconst_0
    //   100: anewarray 62	java/lang/Object
    //   103: astore 32
    //   105: aload 31
    //   107: aconst_null
    //   108: aload 32
    //   110: invokevirtual 68	java/lang/reflect/Method:invoke	(Ljava/lang/Object;[Ljava/lang/Object;)Ljava/lang/Object;
    //   113: astore 34
    //   115: aload 34
    //   117: checkcast 70	java/lang/Integer
    //   120: invokevirtual 73	java/lang/Integer:intValue	()I
    //   123: putstatic 77	uuuuuu/sttsst:b006E006E006E006Enn006E006En	I
    //   126: ldc 2
    //   128: ldc -30
    //   130: sipush 193
    //   133: sipush 133
    //   136: iconst_3
    //   137: invokestatic 54	xxxxxx/uxxxxx:bbbb0062b0062b0062b0062	(Ljava/lang/String;CCC)Ljava/lang/String;
    //   140: iconst_0
    //   141: anewarray 56	java/lang/Class
    //   144: invokevirtual 60	java/lang/Class:getMethod	(Ljava/lang/String;[Ljava/lang/Class;)Ljava/lang/reflect/Method;
    //   147: astore 35
    //   149: iconst_0
    //   150: anewarray 62	java/lang/Object
    //   153: astore 36
    //   155: aload 35
    //   157: aconst_null
    //   158: aload 36
    //   160: invokevirtual 68	java/lang/reflect/Method:invoke	(Ljava/lang/Object;[Ljava/lang/Object;)Ljava/lang/Object;
    //   163: astore 38
    //   165: aload 38
    //   167: checkcast 70	java/lang/Integer
    //   170: invokevirtual 73	java/lang/Integer:intValue	()I
    //   173: putstatic 81	uuuuuu/sttsst:bnnnn006En006E006En	I
    //   176: getstatic 77	uuuuuu/sttsst:b006E006E006E006Enn006E006En	I
    //   179: getstatic 75	uuuuuu/sttsst:b006En006E006Enn006E006En	I
    //   182: iadd
    //   183: getstatic 77	uuuuuu/sttsst:b006E006E006E006Enn006E006En	I
    //   186: imul
    //   187: getstatic 83	uuuuuu/sttsst:bn006E006E006Enn006E006En	I
    //   190: irem
    //   191: getstatic 81	uuuuuu/sttsst:bnnnn006En006E006En	I
    //   194: if_icmpeq +56 -> 250
    //   197: bipush 37
    //   199: putstatic 77	uuuuuu/sttsst:b006E006E006E006Enn006E006En	I
    //   202: ldc 2
    //   204: ldc -75
    //   206: bipush 114
    //   208: bipush 91
    //   210: iconst_1
    //   211: invokestatic 54	xxxxxx/uxxxxx:bbbb0062b0062b0062b0062	(Ljava/lang/String;CCC)Ljava/lang/String;
    //   214: iconst_0
    //   215: anewarray 56	java/lang/Class
    //   218: invokevirtual 60	java/lang/Class:getMethod	(Ljava/lang/String;[Ljava/lang/Class;)Ljava/lang/reflect/Method;
    //   221: astore 39
    //   223: iconst_0
    //   224: anewarray 62	java/lang/Object
    //   227: astore 40
    //   229: aload 39
    //   231: aconst_null
    //   232: aload 40
    //   234: invokevirtual 68	java/lang/reflect/Method:invoke	(Ljava/lang/Object;[Ljava/lang/Object;)Ljava/lang/Object;
    //   237: astore 42
    //   239: aload 42
    //   241: checkcast 70	java/lang/Integer
    //   244: invokevirtual 73	java/lang/Integer:intValue	()I
    //   247: putstatic 81	uuuuuu/sttsst:bnnnn006En006E006En	I
    //   250: aload_0
    //   251: aload_1
    //   252: invokespecial 230	uuuuuu/ssssst:ba0061a0061a0061a0061aa	(Luuuuuu/ttssst$tsssst;)V
    //   255: invokestatic 236	uuuuuu/pqqppq:b006B006B006Bkkk006Bkkk	()Luuuuuu/pppqpq;
    //   258: aload_0
    //   259: invokeinterface 241 2 0
    //   264: getstatic 77	uuuuuu/sttsst:b006E006E006E006Enn006E006En	I
    //   267: getstatic 75	uuuuuu/sttsst:b006En006E006Enn006E006En	I
    //   270: iadd
    //   271: getstatic 77	uuuuuu/sttsst:b006E006E006E006Enn006E006En	I
    //   274: imul
    //   275: getstatic 83	uuuuuu/sttsst:bn006E006E006Enn006E006En	I
    //   278: irem
    //   279: getstatic 81	uuuuuu/sttsst:bnnnn006En006E006En	I
    //   282: if_icmpeq +187 -> 469
    //   285: ldc 2
    //   287: ldc -13
    //   289: bipush 30
    //   291: bipush 123
    //   293: iconst_1
    //   294: invokestatic 54	xxxxxx/uxxxxx:bbbb0062b0062b0062b0062	(Ljava/lang/String;CCC)Ljava/lang/String;
    //   297: iconst_0
    //   298: anewarray 56	java/lang/Class
    //   301: invokevirtual 60	java/lang/Class:getMethod	(Ljava/lang/String;[Ljava/lang/Class;)Ljava/lang/reflect/Method;
    //   304: astore 18
    //   306: iconst_0
    //   307: anewarray 62	java/lang/Object
    //   310: astore 19
    //   312: aload 18
    //   314: aconst_null
    //   315: aload 19
    //   317: invokevirtual 68	java/lang/reflect/Method:invoke	(Ljava/lang/Object;[Ljava/lang/Object;)Ljava/lang/Object;
    //   320: astore 21
    //   322: aload 21
    //   324: checkcast 70	java/lang/Integer
    //   327: invokevirtual 73	java/lang/Integer:intValue	()I
    //   330: putstatic 77	uuuuuu/sttsst:b006E006E006E006Enn006E006En	I
    //   333: getstatic 77	uuuuuu/sttsst:b006E006E006E006Enn006E006En	I
    //   336: istore 22
    //   338: iload 22
    //   340: iload 22
    //   342: getstatic 75	uuuuuu/sttsst:b006En006E006Enn006E006En	I
    //   345: iadd
    //   346: imul
    //   347: getstatic 83	uuuuuu/sttsst:bn006E006E006Enn006E006En	I
    //   350: irem
    //   351: tableswitch	default:+17->368, 0:+71->422
    //   368: bipush 25
    //   370: putstatic 77	uuuuuu/sttsst:b006E006E006E006Enn006E006En	I
    //   373: ldc 2
    //   375: ldc -11
    //   377: sipush 154
    //   380: bipush 115
    //   382: iconst_3
    //   383: invokestatic 54	xxxxxx/uxxxxx:bbbb0062b0062b0062b0062	(Ljava/lang/String;CCC)Ljava/lang/String;
    //   386: iconst_0
    //   387: anewarray 56	java/lang/Class
    //   390: invokevirtual 60	java/lang/Class:getMethod	(Ljava/lang/String;[Ljava/lang/Class;)Ljava/lang/reflect/Method;
    //   393: astore 27
    //   395: iconst_0
    //   396: anewarray 62	java/lang/Object
    //   399: astore 28
    //   401: aload 27
    //   403: aconst_null
    //   404: aload 28
    //   406: invokevirtual 68	java/lang/reflect/Method:invoke	(Ljava/lang/Object;[Ljava/lang/Object;)Ljava/lang/Object;
    //   409: astore 30
    //   411: aload 30
    //   413: checkcast 70	java/lang/Integer
    //   416: invokevirtual 73	java/lang/Integer:intValue	()I
    //   419: putstatic 81	uuuuuu/sttsst:bnnnn006En006E006En	I
    //   422: ldc 2
    //   424: ldc -9
    //   426: sipush 158
    //   429: iconst_3
    //   430: invokestatic 91	xxxxxx/uxxxxx:bb00620062bb0062b0062b0062	(Ljava/lang/String;CC)Ljava/lang/String;
    //   433: iconst_0
    //   434: anewarray 56	java/lang/Class
    //   437: invokevirtual 60	java/lang/Class:getMethod	(Ljava/lang/String;[Ljava/lang/Class;)Ljava/lang/reflect/Method;
    //   440: astore 23
    //   442: iconst_0
    //   443: anewarray 62	java/lang/Object
    //   446: astore 24
    //   448: aload 23
    //   450: aconst_null
    //   451: aload 24
    //   453: invokevirtual 68	java/lang/reflect/Method:invoke	(Ljava/lang/Object;[Ljava/lang/Object;)Ljava/lang/Object;
    //   456: astore 26
    //   458: aload 26
    //   460: checkcast 70	java/lang/Integer
    //   463: invokevirtual 73	java/lang/Integer:intValue	()I
    //   466: putstatic 81	uuuuuu/sttsst:bnnnn006En006E006En	I
    //   469: aload_0
    //   470: getfield 193	uuuuuu/sttsst:b006E006En006Enn006E006En	Lcom/db/pwcc/dbmobile/secure/preferences/SharedPreferencesHelper;
    //   473: astore 8
    //   475: aload_0
    //   476: getfield 39	uuuuuu/sttsst:bnn006E006Enn006E006En	Landroid/content/SharedPreferences$OnSharedPreferenceChangeListener;
    //   479: astore 9
    //   481: ldc -55
    //   483: ldc -7
    //   485: bipush 94
    //   487: sipush 201
    //   490: iconst_1
    //   491: invokestatic 54	xxxxxx/uxxxxx:bbbb0062b0062b0062b0062	(Ljava/lang/String;CCC)Ljava/lang/String;
    //   494: iconst_1
    //   495: anewarray 56	java/lang/Class
    //   498: dup
    //   499: iconst_0
    //   500: ldc -5
    //   502: aastore
    //   503: invokevirtual 60	java/lang/Class:getMethod	(Ljava/lang/String;[Ljava/lang/Class;)Ljava/lang/reflect/Method;
    //   506: astore 10
    //   508: iconst_1
    //   509: anewarray 62	java/lang/Object
    //   512: dup
    //   513: iconst_0
    //   514: aload 9
    //   516: aastore
    //   517: astore 11
    //   519: aload 10
    //   521: aload 8
    //   523: aload 11
    //   525: invokevirtual 68	java/lang/reflect/Method:invoke	(Ljava/lang/Object;[Ljava/lang/Object;)Ljava/lang/Object;
    //   528: pop
    //   529: ldc 2
    //   531: ldc -3
    //   533: sipush 222
    //   536: iconst_2
    //   537: invokestatic 91	xxxxxx/uxxxxx:bb00620062bb0062b0062b0062	(Ljava/lang/String;CC)Ljava/lang/String;
    //   540: iconst_0
    //   541: anewarray 56	java/lang/Class
    //   544: invokevirtual 96	java/lang/Class:getDeclaredMethod	(Ljava/lang/String;[Ljava/lang/Class;)Ljava/lang/reflect/Method;
    //   547: astore 14
    //   549: iconst_0
    //   550: anewarray 62	java/lang/Object
    //   553: astore 15
    //   555: aload 14
    //   557: aload_0
    //   558: aload 15
    //   560: invokevirtual 68	java/lang/reflect/Method:invoke	(Ljava/lang/Object;[Ljava/lang/Object;)Ljava/lang/Object;
    //   563: pop
    //   564: return
    //   565: astore 33
    //   567: aload 33
    //   569: invokevirtual 100	java/lang/reflect/InvocationTargetException:getCause	()Ljava/lang/Throwable;
    //   572: athrow
    //   573: astore 37
    //   575: aload 37
    //   577: invokevirtual 100	java/lang/reflect/InvocationTargetException:getCause	()Ljava/lang/Throwable;
    //   580: athrow
    //   581: astore 29
    //   583: aload 29
    //   585: invokevirtual 100	java/lang/reflect/InvocationTargetException:getCause	()Ljava/lang/Throwable;
    //   588: athrow
    //   589: astore 6
    //   591: aload 6
    //   593: invokevirtual 100	java/lang/reflect/InvocationTargetException:getCause	()Ljava/lang/Throwable;
    //   596: athrow
    //   597: astore 25
    //   599: aload 25
    //   601: invokevirtual 100	java/lang/reflect/InvocationTargetException:getCause	()Ljava/lang/Throwable;
    //   604: athrow
    //   605: astore 12
    //   607: aload 12
    //   609: invokevirtual 100	java/lang/reflect/InvocationTargetException:getCause	()Ljava/lang/Throwable;
    //   612: athrow
    //   613: astore 16
    //   615: aload 16
    //   617: invokevirtual 100	java/lang/reflect/InvocationTargetException:getCause	()Ljava/lang/Throwable;
    //   620: athrow
    //   621: astore 20
    //   623: aload 20
    //   625: invokevirtual 100	java/lang/reflect/InvocationTargetException:getCause	()Ljava/lang/Throwable;
    //   628: athrow
    //   629: astore 41
    //   631: aload 41
    //   633: invokevirtual 100	java/lang/reflect/InvocationTargetException:getCause	()Ljava/lang/Throwable;
    //   636: athrow
    // Local variable table:
    //   start	length	slot	name	signature
    //   0	637	0	this	sttsst
    //   0	637	1	paramV	V
    //   3	8	2	i	int
    //   11	46	3	j	int
    //   29	9	4	localMethod1	java.lang.reflect.Method
    //   35	6	5	arrayOfObject1	Object[]
    //   589	3	6	localInvocationTargetException1	java.lang.reflect.InvocationTargetException
    //   45	4	7	localObject1	Object
    //   473	49	8	localSharedPreferencesHelper	SharedPreferencesHelper
    //   479	36	9	localOnSharedPreferenceChangeListener	SharedPreferences.OnSharedPreferenceChangeListener
    //   506	14	10	localMethod2	java.lang.reflect.Method
    //   517	7	11	arrayOfObject2	Object[]
    //   605	3	12	localInvocationTargetException2	java.lang.reflect.InvocationTargetException
    //   547	9	14	localMethod3	java.lang.reflect.Method
    //   553	6	15	arrayOfObject3	Object[]
    //   613	3	16	localInvocationTargetException3	java.lang.reflect.InvocationTargetException
    //   304	9	18	localMethod4	java.lang.reflect.Method
    //   310	6	19	arrayOfObject4	Object[]
    //   621	3	20	localInvocationTargetException4	java.lang.reflect.InvocationTargetException
    //   320	3	21	localObject2	Object
    //   336	11	22	k	int
    //   440	9	23	localMethod5	java.lang.reflect.Method
    //   446	6	24	arrayOfObject5	Object[]
    //   597	3	25	localInvocationTargetException5	java.lang.reflect.InvocationTargetException
    //   456	3	26	localObject3	Object
    //   393	9	27	localMethod6	java.lang.reflect.Method
    //   399	6	28	arrayOfObject6	Object[]
    //   581	3	29	localInvocationTargetException6	java.lang.reflect.InvocationTargetException
    //   409	3	30	localObject4	Object
    //   97	9	31	localMethod7	java.lang.reflect.Method
    //   103	6	32	arrayOfObject7	Object[]
    //   565	3	33	localInvocationTargetException7	java.lang.reflect.InvocationTargetException
    //   113	3	34	localObject5	Object
    //   147	9	35	localMethod8	java.lang.reflect.Method
    //   153	6	36	arrayOfObject8	Object[]
    //   573	3	37	localInvocationTargetException8	java.lang.reflect.InvocationTargetException
    //   163	3	38	localObject6	Object
    //   221	9	39	localMethod9	java.lang.reflect.Method
    //   227	6	40	arrayOfObject9	Object[]
    //   629	3	41	localInvocationTargetException9	java.lang.reflect.InvocationTargetException
    //   237	3	42	localObject7	Object
    // Exception table:
    //   from	to	target	type
    //   105	115	565	java/lang/reflect/InvocationTargetException
    //   155	165	573	java/lang/reflect/InvocationTargetException
    //   401	411	581	java/lang/reflect/InvocationTargetException
    //   37	47	589	java/lang/reflect/InvocationTargetException
    //   448	458	597	java/lang/reflect/InvocationTargetException
    //   519	529	605	java/lang/reflect/InvocationTargetException
    //   555	564	613	java/lang/reflect/InvocationTargetException
    //   312	322	621	java/lang/reflect/InvocationTargetException
    //   229	239	629	java/lang/reflect/InvocationTargetException
  }
  
  /* Error */
  public int b006Bkkkkk006Bk006Bk()
  {
    // Byte code:
    //   0: aload_0
    //   1: getfield 193	uuuuuu/sttsst:b006E006En006Enn006E006En	Lcom/db/pwcc/dbmobile/secure/preferences/SharedPreferencesHelper;
    //   4: astore_1
    //   5: getstatic 77	uuuuuu/sttsst:b006E006E006E006Enn006E006En	I
    //   8: istore_2
    //   9: ldc 2
    //   11: ldc_w 256
    //   14: sipush 211
    //   17: iconst_2
    //   18: invokestatic 91	xxxxxx/uxxxxx:bb00620062bb0062b0062b0062	(Ljava/lang/String;CC)Ljava/lang/String;
    //   21: iconst_0
    //   22: anewarray 56	java/lang/Class
    //   25: invokevirtual 60	java/lang/Class:getMethod	(Ljava/lang/String;[Ljava/lang/Class;)Ljava/lang/reflect/Method;
    //   28: astore_3
    //   29: iconst_0
    //   30: anewarray 62	java/lang/Object
    //   33: astore 4
    //   35: aload_3
    //   36: aconst_null
    //   37: aload 4
    //   39: invokevirtual 68	java/lang/reflect/Method:invoke	(Ljava/lang/Object;[Ljava/lang/Object;)Ljava/lang/Object;
    //   42: astore 6
    //   44: iload_2
    //   45: iload_2
    //   46: aload 6
    //   48: checkcast 70	java/lang/Integer
    //   51: invokevirtual 73	java/lang/Integer:intValue	()I
    //   54: iadd
    //   55: imul
    //   56: istore 7
    //   58: ldc 2
    //   60: ldc_w 258
    //   63: bipush 34
    //   65: sipush 156
    //   68: iconst_3
    //   69: invokestatic 54	xxxxxx/uxxxxx:bbbb0062b0062b0062b0062	(Ljava/lang/String;CCC)Ljava/lang/String;
    //   72: iconst_0
    //   73: anewarray 56	java/lang/Class
    //   76: invokevirtual 60	java/lang/Class:getMethod	(Ljava/lang/String;[Ljava/lang/Class;)Ljava/lang/reflect/Method;
    //   79: astore 8
    //   81: iconst_0
    //   82: anewarray 62	java/lang/Object
    //   85: astore 9
    //   87: aload 8
    //   89: aconst_null
    //   90: aload 9
    //   92: invokevirtual 68	java/lang/reflect/Method:invoke	(Ljava/lang/Object;[Ljava/lang/Object;)Ljava/lang/Object;
    //   95: astore 11
    //   97: aload 11
    //   99: checkcast 70	java/lang/Integer
    //   102: invokevirtual 73	java/lang/Integer:intValue	()I
    //   105: istore 12
    //   107: iload 12
    //   109: iload 12
    //   111: getstatic 75	uuuuuu/sttsst:b006En006E006Enn006E006En	I
    //   114: iadd
    //   115: imul
    //   116: istore 13
    //   118: ldc 2
    //   120: ldc_w 260
    //   123: sipush 142
    //   126: iconst_3
    //   127: invokestatic 91	xxxxxx/uxxxxx:bb00620062bb0062b0062b0062	(Ljava/lang/String;CC)Ljava/lang/String;
    //   130: iconst_0
    //   131: anewarray 56	java/lang/Class
    //   134: invokevirtual 60	java/lang/Class:getMethod	(Ljava/lang/String;[Ljava/lang/Class;)Ljava/lang/reflect/Method;
    //   137: astore 14
    //   139: iconst_0
    //   140: anewarray 62	java/lang/Object
    //   143: astore 15
    //   145: aload 14
    //   147: aconst_null
    //   148: aload 15
    //   150: invokevirtual 68	java/lang/reflect/Method:invoke	(Ljava/lang/Object;[Ljava/lang/Object;)Ljava/lang/Object;
    //   153: astore 17
    //   155: iload 13
    //   157: aload 17
    //   159: checkcast 70	java/lang/Integer
    //   162: invokevirtual 73	java/lang/Integer:intValue	()I
    //   165: irem
    //   166: tableswitch	default:+18->184, 0:+71->237
    //   184: ldc 2
    //   186: ldc_w 262
    //   189: sipush 230
    //   192: iconst_2
    //   193: invokestatic 91	xxxxxx/uxxxxx:bb00620062bb0062b0062b0062	(Ljava/lang/String;CC)Ljava/lang/String;
    //   196: iconst_0
    //   197: anewarray 56	java/lang/Class
    //   200: invokevirtual 60	java/lang/Class:getMethod	(Ljava/lang/String;[Ljava/lang/Class;)Ljava/lang/reflect/Method;
    //   203: astore 27
    //   205: iconst_0
    //   206: anewarray 62	java/lang/Object
    //   209: astore 28
    //   211: aload 27
    //   213: aconst_null
    //   214: aload 28
    //   216: invokevirtual 68	java/lang/reflect/Method:invoke	(Ljava/lang/Object;[Ljava/lang/Object;)Ljava/lang/Object;
    //   219: astore 30
    //   221: aload 30
    //   223: checkcast 70	java/lang/Integer
    //   226: invokevirtual 73	java/lang/Integer:intValue	()I
    //   229: putstatic 77	uuuuuu/sttsst:b006E006E006E006Enn006E006En	I
    //   232: bipush 41
    //   234: putstatic 81	uuuuuu/sttsst:bnnnn006En006E006En	I
    //   237: iload 7
    //   239: getstatic 83	uuuuuu/sttsst:bn006E006E006Enn006E006En	I
    //   242: irem
    //   243: tableswitch	default:+17->260, 0:+56->299
    //   260: getstatic 77	uuuuuu/sttsst:b006E006E006E006Enn006E006En	I
    //   263: getstatic 75	uuuuuu/sttsst:b006En006E006Enn006E006En	I
    //   266: iadd
    //   267: getstatic 77	uuuuuu/sttsst:b006E006E006E006Enn006E006En	I
    //   270: imul
    //   271: getstatic 83	uuuuuu/sttsst:bn006E006E006Enn006E006En	I
    //   274: irem
    //   275: getstatic 81	uuuuuu/sttsst:bnnnn006En006E006En	I
    //   278: if_icmpeq +12 -> 290
    //   281: iconst_5
    //   282: putstatic 77	uuuuuu/sttsst:b006E006E006E006Enn006E006En	I
    //   285: bipush 32
    //   287: putstatic 81	uuuuuu/sttsst:bnnnn006En006E006En	I
    //   290: bipush 44
    //   292: putstatic 77	uuuuuu/sttsst:b006E006E006E006Enn006E006En	I
    //   295: iconst_0
    //   296: putstatic 81	uuuuuu/sttsst:bnnnn006En006E006En	I
    //   299: ldc -55
    //   301: ldc_w 264
    //   304: sipush 246
    //   307: bipush 85
    //   309: iconst_2
    //   310: invokestatic 54	xxxxxx/uxxxxx:bbbb0062b0062b0062b0062	(Ljava/lang/String;CCC)Ljava/lang/String;
    //   313: iconst_0
    //   314: anewarray 56	java/lang/Class
    //   317: invokevirtual 60	java/lang/Class:getMethod	(Ljava/lang/String;[Ljava/lang/Class;)Ljava/lang/reflect/Method;
    //   320: astore 18
    //   322: iconst_0
    //   323: anewarray 62	java/lang/Object
    //   326: astore 19
    //   328: aload 18
    //   330: aload_1
    //   331: aload 19
    //   333: invokevirtual 68	java/lang/reflect/Method:invoke	(Ljava/lang/Object;[Ljava/lang/Object;)Ljava/lang/Object;
    //   336: astore 21
    //   338: aload 21
    //   340: checkcast 70	java/lang/Integer
    //   343: invokevirtual 73	java/lang/Integer:intValue	()I
    //   346: istore 22
    //   348: getstatic 77	uuuuuu/sttsst:b006E006E006E006Enn006E006En	I
    //   351: getstatic 75	uuuuuu/sttsst:b006En006E006Enn006E006En	I
    //   354: iadd
    //   355: getstatic 77	uuuuuu/sttsst:b006E006E006E006Enn006E006En	I
    //   358: imul
    //   359: getstatic 83	uuuuuu/sttsst:bn006E006E006Enn006E006En	I
    //   362: irem
    //   363: getstatic 81	uuuuuu/sttsst:bnnnn006En006E006En	I
    //   366: if_icmpeq +54 -> 420
    //   369: ldc 2
    //   371: ldc_w 266
    //   374: iconst_5
    //   375: iconst_1
    //   376: invokestatic 91	xxxxxx/uxxxxx:bb00620062bb0062b0062b0062	(Ljava/lang/String;CC)Ljava/lang/String;
    //   379: iconst_0
    //   380: anewarray 56	java/lang/Class
    //   383: invokevirtual 60	java/lang/Class:getMethod	(Ljava/lang/String;[Ljava/lang/Class;)Ljava/lang/reflect/Method;
    //   386: astore 23
    //   388: iconst_0
    //   389: anewarray 62	java/lang/Object
    //   392: astore 24
    //   394: aload 23
    //   396: aconst_null
    //   397: aload 24
    //   399: invokevirtual 68	java/lang/reflect/Method:invoke	(Ljava/lang/Object;[Ljava/lang/Object;)Ljava/lang/Object;
    //   402: astore 26
    //   404: aload 26
    //   406: checkcast 70	java/lang/Integer
    //   409: invokevirtual 73	java/lang/Integer:intValue	()I
    //   412: putstatic 77	uuuuuu/sttsst:b006E006E006E006Enn006E006En	I
    //   415: bipush 59
    //   417: putstatic 81	uuuuuu/sttsst:bnnnn006En006E006En	I
    //   420: iload 22
    //   422: ireturn
    //   423: astore 29
    //   425: aload 29
    //   427: invokevirtual 100	java/lang/reflect/InvocationTargetException:getCause	()Ljava/lang/Throwable;
    //   430: athrow
    //   431: astore 10
    //   433: aload 10
    //   435: invokevirtual 100	java/lang/reflect/InvocationTargetException:getCause	()Ljava/lang/Throwable;
    //   438: athrow
    //   439: astore 5
    //   441: aload 5
    //   443: invokevirtual 100	java/lang/reflect/InvocationTargetException:getCause	()Ljava/lang/Throwable;
    //   446: athrow
    //   447: astore 20
    //   449: aload 20
    //   451: invokevirtual 100	java/lang/reflect/InvocationTargetException:getCause	()Ljava/lang/Throwable;
    //   454: athrow
    //   455: astore 16
    //   457: aload 16
    //   459: invokevirtual 100	java/lang/reflect/InvocationTargetException:getCause	()Ljava/lang/Throwable;
    //   462: athrow
    //   463: astore 25
    //   465: aload 25
    //   467: invokevirtual 100	java/lang/reflect/InvocationTargetException:getCause	()Ljava/lang/Throwable;
    //   470: athrow
    // Local variable table:
    //   start	length	slot	name	signature
    //   0	471	0	this	sttsst
    //   4	327	1	localSharedPreferencesHelper	SharedPreferencesHelper
    //   8	48	2	i	int
    //   28	8	3	localMethod1	java.lang.reflect.Method
    //   33	5	4	arrayOfObject1	Object[]
    //   439	3	5	localInvocationTargetException1	java.lang.reflect.InvocationTargetException
    //   42	5	6	localObject1	Object
    //   56	187	7	j	int
    //   79	9	8	localMethod2	java.lang.reflect.Method
    //   85	6	9	arrayOfObject2	Object[]
    //   431	3	10	localInvocationTargetException2	java.lang.reflect.InvocationTargetException
    //   95	3	11	localObject2	Object
    //   105	11	12	k	int
    //   116	50	13	m	int
    //   137	9	14	localMethod3	java.lang.reflect.Method
    //   143	6	15	arrayOfObject3	Object[]
    //   455	3	16	localInvocationTargetException3	java.lang.reflect.InvocationTargetException
    //   153	5	17	localObject3	Object
    //   320	9	18	localMethod4	java.lang.reflect.Method
    //   326	6	19	arrayOfObject4	Object[]
    //   447	3	20	localInvocationTargetException4	java.lang.reflect.InvocationTargetException
    //   336	3	21	localObject4	Object
    //   346	75	22	n	int
    //   386	9	23	localMethod5	java.lang.reflect.Method
    //   392	6	24	arrayOfObject5	Object[]
    //   463	3	25	localInvocationTargetException5	java.lang.reflect.InvocationTargetException
    //   402	3	26	localObject5	Object
    //   203	9	27	localMethod6	java.lang.reflect.Method
    //   209	6	28	arrayOfObject6	Object[]
    //   423	3	29	localInvocationTargetException6	java.lang.reflect.InvocationTargetException
    //   219	3	30	localObject6	Object
    // Exception table:
    //   from	to	target	type
    //   211	221	423	java/lang/reflect/InvocationTargetException
    //   87	97	431	java/lang/reflect/InvocationTargetException
    //   35	44	439	java/lang/reflect/InvocationTargetException
    //   328	338	447	java/lang/reflect/InvocationTargetException
    //   145	155	455	java/lang/reflect/InvocationTargetException
    //   394	404	463	java/lang/reflect/InvocationTargetException
  }
  
  /* Error */
  public void ba006100610061a0061aa0061a()
  {
    // Byte code:
    //   0: getstatic 77	uuuuuu/sttsst:b006E006E006E006Enn006E006En	I
    //   3: istore_1
    //   4: iload_1
    //   5: iload_1
    //   6: getstatic 75	uuuuuu/sttsst:b006En006E006Enn006E006En	I
    //   9: iadd
    //   10: imul
    //   11: getstatic 83	uuuuuu/sttsst:bn006E006E006Enn006E006En	I
    //   14: irem
    //   15: tableswitch	default:+17->32, 0:+27->42
    //   32: bipush 6
    //   34: putstatic 77	uuuuuu/sttsst:b006E006E006E006Enn006E006En	I
    //   37: bipush 63
    //   39: putstatic 81	uuuuuu/sttsst:bnnnn006En006E006En	I
    //   42: aload_0
    //   43: getfield 193	uuuuuu/sttsst:b006E006En006Enn006E006En	Lcom/db/pwcc/dbmobile/secure/preferences/SharedPreferencesHelper;
    //   46: astore_2
    //   47: aload_0
    //   48: getfield 39	uuuuuu/sttsst:bnn006E006Enn006E006En	Landroid/content/SharedPreferences$OnSharedPreferenceChangeListener;
    //   51: astore_3
    //   52: ldc -55
    //   54: ldc_w 269
    //   57: sipush 156
    //   60: iconst_5
    //   61: invokestatic 91	xxxxxx/uxxxxx:bb00620062bb0062b0062b0062	(Ljava/lang/String;CC)Ljava/lang/String;
    //   64: iconst_1
    //   65: anewarray 56	java/lang/Class
    //   68: dup
    //   69: iconst_0
    //   70: ldc -5
    //   72: aastore
    //   73: invokevirtual 60	java/lang/Class:getMethod	(Ljava/lang/String;[Ljava/lang/Class;)Ljava/lang/reflect/Method;
    //   76: astore 4
    //   78: iconst_1
    //   79: anewarray 62	java/lang/Object
    //   82: dup
    //   83: iconst_0
    //   84: aload_3
    //   85: aastore
    //   86: astore 5
    //   88: aload 4
    //   90: aload_2
    //   91: aload 5
    //   93: invokevirtual 68	java/lang/reflect/Method:invoke	(Ljava/lang/Object;[Ljava/lang/Object;)Ljava/lang/Object;
    //   96: pop
    //   97: getstatic 77	uuuuuu/sttsst:b006E006E006E006Enn006E006En	I
    //   100: getstatic 75	uuuuuu/sttsst:b006En006E006Enn006E006En	I
    //   103: iadd
    //   104: getstatic 77	uuuuuu/sttsst:b006E006E006E006Enn006E006En	I
    //   107: imul
    //   108: getstatic 83	uuuuuu/sttsst:bn006E006E006Enn006E006En	I
    //   111: irem
    //   112: istore 8
    //   114: ldc 2
    //   116: ldc_w 271
    //   119: bipush 29
    //   121: bipush 11
    //   123: iconst_3
    //   124: invokestatic 54	xxxxxx/uxxxxx:bbbb0062b0062b0062b0062	(Ljava/lang/String;CCC)Ljava/lang/String;
    //   127: iconst_0
    //   128: anewarray 56	java/lang/Class
    //   131: invokevirtual 60	java/lang/Class:getMethod	(Ljava/lang/String;[Ljava/lang/Class;)Ljava/lang/reflect/Method;
    //   134: astore 9
    //   136: iconst_0
    //   137: anewarray 62	java/lang/Object
    //   140: astore 10
    //   142: aload 9
    //   144: aconst_null
    //   145: aload 10
    //   147: invokevirtual 68	java/lang/reflect/Method:invoke	(Ljava/lang/Object;[Ljava/lang/Object;)Ljava/lang/Object;
    //   150: astore 12
    //   152: iload 8
    //   154: aload 12
    //   156: checkcast 70	java/lang/Integer
    //   159: invokevirtual 73	java/lang/Integer:intValue	()I
    //   162: if_icmpeq +174 -> 336
    //   165: bipush 16
    //   167: putstatic 77	uuuuuu/sttsst:b006E006E006E006Enn006E006En	I
    //   170: ldc 2
    //   172: ldc 85
    //   174: bipush 65
    //   176: iconst_2
    //   177: invokestatic 91	xxxxxx/uxxxxx:bb00620062bb0062b0062b0062	(Ljava/lang/String;CC)Ljava/lang/String;
    //   180: iconst_0
    //   181: anewarray 56	java/lang/Class
    //   184: invokevirtual 60	java/lang/Class:getMethod	(Ljava/lang/String;[Ljava/lang/Class;)Ljava/lang/reflect/Method;
    //   187: astore 22
    //   189: iconst_0
    //   190: anewarray 62	java/lang/Object
    //   193: astore 23
    //   195: aload 22
    //   197: aconst_null
    //   198: aload 23
    //   200: invokevirtual 68	java/lang/reflect/Method:invoke	(Ljava/lang/Object;[Ljava/lang/Object;)Ljava/lang/Object;
    //   203: astore 25
    //   205: aload 25
    //   207: checkcast 70	java/lang/Integer
    //   210: invokevirtual 73	java/lang/Integer:intValue	()I
    //   213: putstatic 81	uuuuuu/sttsst:bnnnn006En006E006En	I
    //   216: getstatic 77	uuuuuu/sttsst:b006E006E006E006Enn006E006En	I
    //   219: getstatic 75	uuuuuu/sttsst:b006En006E006Enn006E006En	I
    //   222: iadd
    //   223: getstatic 77	uuuuuu/sttsst:b006E006E006E006Enn006E006En	I
    //   226: imul
    //   227: getstatic 83	uuuuuu/sttsst:bn006E006E006Enn006E006En	I
    //   230: irem
    //   231: getstatic 81	uuuuuu/sttsst:bnnnn006En006E006En	I
    //   234: if_icmpeq +102 -> 336
    //   237: ldc 2
    //   239: ldc_w 273
    //   242: sipush 146
    //   245: iconst_4
    //   246: invokestatic 91	xxxxxx/uxxxxx:bb00620062bb0062b0062b0062	(Ljava/lang/String;CC)Ljava/lang/String;
    //   249: iconst_0
    //   250: anewarray 56	java/lang/Class
    //   253: invokevirtual 60	java/lang/Class:getMethod	(Ljava/lang/String;[Ljava/lang/Class;)Ljava/lang/reflect/Method;
    //   256: astore 26
    //   258: iconst_0
    //   259: anewarray 62	java/lang/Object
    //   262: astore 27
    //   264: aload 26
    //   266: aconst_null
    //   267: aload 27
    //   269: invokevirtual 68	java/lang/reflect/Method:invoke	(Ljava/lang/Object;[Ljava/lang/Object;)Ljava/lang/Object;
    //   272: astore 29
    //   274: aload 29
    //   276: checkcast 70	java/lang/Integer
    //   279: invokevirtual 73	java/lang/Integer:intValue	()I
    //   282: putstatic 77	uuuuuu/sttsst:b006E006E006E006Enn006E006En	I
    //   285: ldc 2
    //   287: ldc_w 275
    //   290: sipush 134
    //   293: sipush 143
    //   296: iconst_2
    //   297: invokestatic 54	xxxxxx/uxxxxx:bbbb0062b0062b0062b0062	(Ljava/lang/String;CCC)Ljava/lang/String;
    //   300: iconst_0
    //   301: anewarray 56	java/lang/Class
    //   304: invokevirtual 60	java/lang/Class:getMethod	(Ljava/lang/String;[Ljava/lang/Class;)Ljava/lang/reflect/Method;
    //   307: astore 30
    //   309: iconst_0
    //   310: anewarray 62	java/lang/Object
    //   313: astore 31
    //   315: aload 30
    //   317: aconst_null
    //   318: aload 31
    //   320: invokevirtual 68	java/lang/reflect/Method:invoke	(Ljava/lang/Object;[Ljava/lang/Object;)Ljava/lang/Object;
    //   323: astore 33
    //   325: aload 33
    //   327: checkcast 70	java/lang/Integer
    //   330: invokevirtual 73	java/lang/Integer:intValue	()I
    //   333: putstatic 81	uuuuuu/sttsst:bnnnn006En006E006En	I
    //   336: aload_0
    //   337: invokespecial 277	uuuuuu/ssssst:ba006100610061a0061aa0061a	()V
    //   340: getstatic 77	uuuuuu/sttsst:b006E006E006E006Enn006E006En	I
    //   343: istore 13
    //   345: iload 13
    //   347: iload 13
    //   349: getstatic 75	uuuuuu/sttsst:b006En006E006Enn006E006En	I
    //   352: iadd
    //   353: imul
    //   354: getstatic 83	uuuuuu/sttsst:bn006E006E006Enn006E006En	I
    //   357: irem
    //   358: tableswitch	default:+18->376, 0:+114->472
    //   376: ldc 2
    //   378: ldc_w 279
    //   381: sipush 189
    //   384: iconst_0
    //   385: invokestatic 91	xxxxxx/uxxxxx:bb00620062bb0062b0062b0062	(Ljava/lang/String;CC)Ljava/lang/String;
    //   388: iconst_0
    //   389: anewarray 56	java/lang/Class
    //   392: invokevirtual 60	java/lang/Class:getMethod	(Ljava/lang/String;[Ljava/lang/Class;)Ljava/lang/reflect/Method;
    //   395: astore 14
    //   397: iconst_0
    //   398: anewarray 62	java/lang/Object
    //   401: astore 15
    //   403: aload 14
    //   405: aconst_null
    //   406: aload 15
    //   408: invokevirtual 68	java/lang/reflect/Method:invoke	(Ljava/lang/Object;[Ljava/lang/Object;)Ljava/lang/Object;
    //   411: astore 17
    //   413: aload 17
    //   415: checkcast 70	java/lang/Integer
    //   418: invokevirtual 73	java/lang/Integer:intValue	()I
    //   421: putstatic 77	uuuuuu/sttsst:b006E006E006E006Enn006E006En	I
    //   424: ldc 2
    //   426: ldc_w 281
    //   429: sipush 152
    //   432: iconst_2
    //   433: invokestatic 91	xxxxxx/uxxxxx:bb00620062bb0062b0062b0062	(Ljava/lang/String;CC)Ljava/lang/String;
    //   436: iconst_0
    //   437: anewarray 56	java/lang/Class
    //   440: invokevirtual 60	java/lang/Class:getMethod	(Ljava/lang/String;[Ljava/lang/Class;)Ljava/lang/reflect/Method;
    //   443: astore 18
    //   445: iconst_0
    //   446: anewarray 62	java/lang/Object
    //   449: astore 19
    //   451: aload 18
    //   453: aconst_null
    //   454: aload 19
    //   456: invokevirtual 68	java/lang/reflect/Method:invoke	(Ljava/lang/Object;[Ljava/lang/Object;)Ljava/lang/Object;
    //   459: astore 21
    //   461: aload 21
    //   463: checkcast 70	java/lang/Integer
    //   466: invokevirtual 73	java/lang/Integer:intValue	()I
    //   469: putstatic 81	uuuuuu/sttsst:bnnnn006En006E006En	I
    //   472: return
    //   473: astore 11
    //   475: aload 11
    //   477: invokevirtual 100	java/lang/reflect/InvocationTargetException:getCause	()Ljava/lang/Throwable;
    //   480: athrow
    //   481: astore 6
    //   483: aload 6
    //   485: invokevirtual 100	java/lang/reflect/InvocationTargetException:getCause	()Ljava/lang/Throwable;
    //   488: athrow
    //   489: astore 24
    //   491: aload 24
    //   493: invokevirtual 100	java/lang/reflect/InvocationTargetException:getCause	()Ljava/lang/Throwable;
    //   496: athrow
    //   497: astore 16
    //   499: aload 16
    //   501: invokevirtual 100	java/lang/reflect/InvocationTargetException:getCause	()Ljava/lang/Throwable;
    //   504: athrow
    //   505: astore 20
    //   507: aload 20
    //   509: invokevirtual 100	java/lang/reflect/InvocationTargetException:getCause	()Ljava/lang/Throwable;
    //   512: athrow
    //   513: astore 28
    //   515: aload 28
    //   517: invokevirtual 100	java/lang/reflect/InvocationTargetException:getCause	()Ljava/lang/Throwable;
    //   520: athrow
    //   521: astore 32
    //   523: aload 32
    //   525: invokevirtual 100	java/lang/reflect/InvocationTargetException:getCause	()Ljava/lang/Throwable;
    //   528: athrow
    // Local variable table:
    //   start	length	slot	name	signature
    //   0	529	0	this	sttsst
    //   3	8	1	i	int
    //   46	45	2	localSharedPreferencesHelper	SharedPreferencesHelper
    //   51	34	3	localOnSharedPreferenceChangeListener	SharedPreferences.OnSharedPreferenceChangeListener
    //   76	13	4	localMethod1	java.lang.reflect.Method
    //   86	6	5	arrayOfObject1	Object[]
    //   481	3	6	localInvocationTargetException1	java.lang.reflect.InvocationTargetException
    //   112	51	8	j	int
    //   134	9	9	localMethod2	java.lang.reflect.Method
    //   140	6	10	arrayOfObject2	Object[]
    //   473	3	11	localInvocationTargetException2	java.lang.reflect.InvocationTargetException
    //   150	5	12	localObject1	Object
    //   343	11	13	k	int
    //   395	9	14	localMethod3	java.lang.reflect.Method
    //   401	6	15	arrayOfObject3	Object[]
    //   497	3	16	localInvocationTargetException3	java.lang.reflect.InvocationTargetException
    //   411	3	17	localObject2	Object
    //   443	9	18	localMethod4	java.lang.reflect.Method
    //   449	6	19	arrayOfObject4	Object[]
    //   505	3	20	localInvocationTargetException4	java.lang.reflect.InvocationTargetException
    //   459	3	21	localObject3	Object
    //   187	9	22	localMethod5	java.lang.reflect.Method
    //   193	6	23	arrayOfObject5	Object[]
    //   489	3	24	localInvocationTargetException5	java.lang.reflect.InvocationTargetException
    //   203	3	25	localObject4	Object
    //   256	9	26	localMethod6	java.lang.reflect.Method
    //   262	6	27	arrayOfObject6	Object[]
    //   513	3	28	localInvocationTargetException6	java.lang.reflect.InvocationTargetException
    //   272	3	29	localObject5	Object
    //   307	9	30	localMethod7	java.lang.reflect.Method
    //   313	6	31	arrayOfObject7	Object[]
    //   521	3	32	localInvocationTargetException7	java.lang.reflect.InvocationTargetException
    //   323	3	33	localObject6	Object
    // Exception table:
    //   from	to	target	type
    //   142	152	473	java/lang/reflect/InvocationTargetException
    //   88	97	481	java/lang/reflect/InvocationTargetException
    //   195	205	489	java/lang/reflect/InvocationTargetException
    //   403	413	497	java/lang/reflect/InvocationTargetException
    //   451	461	505	java/lang/reflect/InvocationTargetException
    //   264	274	513	java/lang/reflect/InvocationTargetException
    //   315	325	521	java/lang/reflect/InvocationTargetException
  }
  
  /* Error */
  public boolean bk006Bk006B006B006Bkk006Bk()
  {
    // Byte code:
    //   0: getstatic 77	uuuuuu/sttsst:b006E006E006E006Enn006E006En	I
    //   3: getstatic 75	uuuuuu/sttsst:b006En006E006Enn006E006En	I
    //   6: iadd
    //   7: getstatic 77	uuuuuu/sttsst:b006E006E006E006Enn006E006En	I
    //   10: imul
    //   11: getstatic 83	uuuuuu/sttsst:bn006E006E006Enn006E006En	I
    //   14: irem
    //   15: getstatic 81	uuuuuu/sttsst:bnnnn006En006E006En	I
    //   18: if_icmpeq +97 -> 115
    //   21: ldc 2
    //   23: ldc_w 302
    //   26: bipush 84
    //   28: iconst_4
    //   29: invokestatic 91	xxxxxx/uxxxxx:bb00620062bb0062b0062b0062	(Ljava/lang/String;CC)Ljava/lang/String;
    //   32: iconst_0
    //   33: anewarray 56	java/lang/Class
    //   36: invokevirtual 60	java/lang/Class:getMethod	(Ljava/lang/String;[Ljava/lang/Class;)Ljava/lang/reflect/Method;
    //   39: astore 28
    //   41: iconst_0
    //   42: anewarray 62	java/lang/Object
    //   45: astore 29
    //   47: aload 28
    //   49: aconst_null
    //   50: aload 29
    //   52: invokevirtual 68	java/lang/reflect/Method:invoke	(Ljava/lang/Object;[Ljava/lang/Object;)Ljava/lang/Object;
    //   55: astore 31
    //   57: aload 31
    //   59: checkcast 70	java/lang/Integer
    //   62: invokevirtual 73	java/lang/Integer:intValue	()I
    //   65: putstatic 77	uuuuuu/sttsst:b006E006E006E006Enn006E006En	I
    //   68: ldc 2
    //   70: ldc -77
    //   72: sipush 150
    //   75: iconst_1
    //   76: invokestatic 91	xxxxxx/uxxxxx:bb00620062bb0062b0062b0062	(Ljava/lang/String;CC)Ljava/lang/String;
    //   79: iconst_0
    //   80: anewarray 56	java/lang/Class
    //   83: invokevirtual 60	java/lang/Class:getMethod	(Ljava/lang/String;[Ljava/lang/Class;)Ljava/lang/reflect/Method;
    //   86: astore 32
    //   88: iconst_0
    //   89: anewarray 62	java/lang/Object
    //   92: astore 33
    //   94: aload 32
    //   96: aconst_null
    //   97: aload 33
    //   99: invokevirtual 68	java/lang/reflect/Method:invoke	(Ljava/lang/Object;[Ljava/lang/Object;)Ljava/lang/Object;
    //   102: astore 35
    //   104: aload 35
    //   106: checkcast 70	java/lang/Integer
    //   109: invokevirtual 73	java/lang/Integer:intValue	()I
    //   112: putstatic 81	uuuuuu/sttsst:bnnnn006En006E006En	I
    //   115: aload_0
    //   116: getfield 32	uuuuuu/sttsst:b006Enn006Enn006E006En	Z
    //   119: istore_1
    //   120: getstatic 77	uuuuuu/sttsst:b006E006E006E006Enn006E006En	I
    //   123: istore_2
    //   124: ldc 2
    //   126: ldc_w 304
    //   129: bipush 118
    //   131: sipush 210
    //   134: iconst_1
    //   135: invokestatic 54	xxxxxx/uxxxxx:bbbb0062b0062b0062b0062	(Ljava/lang/String;CCC)Ljava/lang/String;
    //   138: iconst_0
    //   139: anewarray 56	java/lang/Class
    //   142: invokevirtual 60	java/lang/Class:getMethod	(Ljava/lang/String;[Ljava/lang/Class;)Ljava/lang/reflect/Method;
    //   145: astore_3
    //   146: iconst_0
    //   147: anewarray 62	java/lang/Object
    //   150: astore 4
    //   152: aload_3
    //   153: aconst_null
    //   154: aload 4
    //   156: invokevirtual 68	java/lang/reflect/Method:invoke	(Ljava/lang/Object;[Ljava/lang/Object;)Ljava/lang/Object;
    //   159: astore 6
    //   161: aload 6
    //   163: checkcast 70	java/lang/Integer
    //   166: invokevirtual 73	java/lang/Integer:intValue	()I
    //   169: istore 7
    //   171: getstatic 77	uuuuuu/sttsst:b006E006E006E006Enn006E006En	I
    //   174: istore 8
    //   176: getstatic 75	uuuuuu/sttsst:b006En006E006Enn006E006En	I
    //   179: istore 9
    //   181: getstatic 77	uuuuuu/sttsst:b006E006E006E006Enn006E006En	I
    //   184: istore 10
    //   186: iload 10
    //   188: iload 10
    //   190: getstatic 75	uuuuuu/sttsst:b006En006E006Enn006E006En	I
    //   193: iadd
    //   194: imul
    //   195: istore 11
    //   197: ldc 2
    //   199: ldc_w 306
    //   202: bipush 84
    //   204: bipush 39
    //   206: iconst_2
    //   207: invokestatic 54	xxxxxx/uxxxxx:bbbb0062b0062b0062b0062	(Ljava/lang/String;CCC)Ljava/lang/String;
    //   210: iconst_0
    //   211: anewarray 56	java/lang/Class
    //   214: invokevirtual 60	java/lang/Class:getMethod	(Ljava/lang/String;[Ljava/lang/Class;)Ljava/lang/reflect/Method;
    //   217: astore 12
    //   219: iconst_0
    //   220: anewarray 62	java/lang/Object
    //   223: astore 13
    //   225: aload 12
    //   227: aconst_null
    //   228: aload 13
    //   230: invokevirtual 68	java/lang/reflect/Method:invoke	(Ljava/lang/Object;[Ljava/lang/Object;)Ljava/lang/Object;
    //   233: astore 15
    //   235: iload 11
    //   237: aload 15
    //   239: checkcast 70	java/lang/Integer
    //   242: invokevirtual 73	java/lang/Integer:intValue	()I
    //   245: irem
    //   246: tableswitch	default:+18->264, 0:+70->316
    //   264: ldc 2
    //   266: ldc_w 308
    //   269: bipush 53
    //   271: iconst_3
    //   272: invokestatic 91	xxxxxx/uxxxxx:bb00620062bb0062b0062b0062	(Ljava/lang/String;CC)Ljava/lang/String;
    //   275: iconst_0
    //   276: anewarray 56	java/lang/Class
    //   279: invokevirtual 60	java/lang/Class:getMethod	(Ljava/lang/String;[Ljava/lang/Class;)Ljava/lang/reflect/Method;
    //   282: astore 24
    //   284: iconst_0
    //   285: anewarray 62	java/lang/Object
    //   288: astore 25
    //   290: aload 24
    //   292: aconst_null
    //   293: aload 25
    //   295: invokevirtual 68	java/lang/reflect/Method:invoke	(Ljava/lang/Object;[Ljava/lang/Object;)Ljava/lang/Object;
    //   298: astore 27
    //   300: aload 27
    //   302: checkcast 70	java/lang/Integer
    //   305: invokevirtual 73	java/lang/Integer:intValue	()I
    //   308: putstatic 77	uuuuuu/sttsst:b006E006E006E006Enn006E006En	I
    //   311: bipush 26
    //   313: putstatic 81	uuuuuu/sttsst:bnnnn006En006E006En	I
    //   316: iload 8
    //   318: iload 8
    //   320: iload 9
    //   322: iadd
    //   323: imul
    //   324: getstatic 83	uuuuuu/sttsst:bn006E006E006Enn006E006En	I
    //   327: irem
    //   328: tableswitch	default:+20->348, 0:+75->403
    //   348: bipush 65
    //   350: putstatic 77	uuuuuu/sttsst:b006E006E006E006Enn006E006En	I
    //   353: ldc 2
    //   355: ldc_w 310
    //   358: bipush 76
    //   360: sipush 244
    //   363: iconst_1
    //   364: invokestatic 54	xxxxxx/uxxxxx:bbbb0062b0062b0062b0062	(Ljava/lang/String;CCC)Ljava/lang/String;
    //   367: iconst_0
    //   368: anewarray 56	java/lang/Class
    //   371: invokevirtual 60	java/lang/Class:getMethod	(Ljava/lang/String;[Ljava/lang/Class;)Ljava/lang/reflect/Method;
    //   374: astore 20
    //   376: iconst_0
    //   377: anewarray 62	java/lang/Object
    //   380: astore 21
    //   382: aload 20
    //   384: aconst_null
    //   385: aload 21
    //   387: invokevirtual 68	java/lang/reflect/Method:invoke	(Ljava/lang/Object;[Ljava/lang/Object;)Ljava/lang/Object;
    //   390: astore 23
    //   392: aload 23
    //   394: checkcast 70	java/lang/Integer
    //   397: invokevirtual 73	java/lang/Integer:intValue	()I
    //   400: putstatic 81	uuuuuu/sttsst:bnnnn006En006E006En	I
    //   403: iload_2
    //   404: iload 7
    //   406: iadd
    //   407: getstatic 77	uuuuuu/sttsst:b006E006E006E006Enn006E006En	I
    //   410: imul
    //   411: getstatic 83	uuuuuu/sttsst:bn006E006E006Enn006E006En	I
    //   414: irem
    //   415: getstatic 81	uuuuuu/sttsst:bnnnn006En006E006En	I
    //   418: if_icmpeq +56 -> 474
    //   421: bipush 6
    //   423: putstatic 77	uuuuuu/sttsst:b006E006E006E006Enn006E006En	I
    //   426: ldc 2
    //   428: ldc_w 285
    //   431: sipush 185
    //   434: iconst_3
    //   435: invokestatic 91	xxxxxx/uxxxxx:bb00620062bb0062b0062b0062	(Ljava/lang/String;CC)Ljava/lang/String;
    //   438: iconst_0
    //   439: anewarray 56	java/lang/Class
    //   442: invokevirtual 60	java/lang/Class:getMethod	(Ljava/lang/String;[Ljava/lang/Class;)Ljava/lang/reflect/Method;
    //   445: astore 16
    //   447: iconst_0
    //   448: anewarray 62	java/lang/Object
    //   451: astore 17
    //   453: aload 16
    //   455: aconst_null
    //   456: aload 17
    //   458: invokevirtual 68	java/lang/reflect/Method:invoke	(Ljava/lang/Object;[Ljava/lang/Object;)Ljava/lang/Object;
    //   461: astore 19
    //   463: aload 19
    //   465: checkcast 70	java/lang/Integer
    //   468: invokevirtual 73	java/lang/Integer:intValue	()I
    //   471: putstatic 81	uuuuuu/sttsst:bnnnn006En006E006En	I
    //   474: iload_1
    //   475: ireturn
    //   476: astore 18
    //   478: aload 18
    //   480: invokevirtual 100	java/lang/reflect/InvocationTargetException:getCause	()Ljava/lang/Throwable;
    //   483: athrow
    //   484: astore 30
    //   486: aload 30
    //   488: invokevirtual 100	java/lang/reflect/InvocationTargetException:getCause	()Ljava/lang/Throwable;
    //   491: athrow
    //   492: astore 34
    //   494: aload 34
    //   496: invokevirtual 100	java/lang/reflect/InvocationTargetException:getCause	()Ljava/lang/Throwable;
    //   499: athrow
    //   500: astore 5
    //   502: aload 5
    //   504: invokevirtual 100	java/lang/reflect/InvocationTargetException:getCause	()Ljava/lang/Throwable;
    //   507: athrow
    //   508: astore 14
    //   510: aload 14
    //   512: invokevirtual 100	java/lang/reflect/InvocationTargetException:getCause	()Ljava/lang/Throwable;
    //   515: athrow
    //   516: astore 22
    //   518: aload 22
    //   520: invokevirtual 100	java/lang/reflect/InvocationTargetException:getCause	()Ljava/lang/Throwable;
    //   523: athrow
    //   524: astore 26
    //   526: aload 26
    //   528: invokevirtual 100	java/lang/reflect/InvocationTargetException:getCause	()Ljava/lang/Throwable;
    //   531: athrow
    // Local variable table:
    //   start	length	slot	name	signature
    //   0	532	0	this	sttsst
    //   119	356	1	bool	boolean
    //   123	284	2	i	int
    //   145	8	3	localMethod1	java.lang.reflect.Method
    //   150	5	4	arrayOfObject1	Object[]
    //   500	3	5	localInvocationTargetException1	java.lang.reflect.InvocationTargetException
    //   159	3	6	localObject1	Object
    //   169	238	7	j	int
    //   174	150	8	k	int
    //   179	144	9	m	int
    //   184	11	10	n	int
    //   195	51	11	i1	int
    //   217	9	12	localMethod2	java.lang.reflect.Method
    //   223	6	13	arrayOfObject2	Object[]
    //   508	3	14	localInvocationTargetException2	java.lang.reflect.InvocationTargetException
    //   233	5	15	localObject2	Object
    //   445	9	16	localMethod3	java.lang.reflect.Method
    //   451	6	17	arrayOfObject3	Object[]
    //   476	3	18	localInvocationTargetException3	java.lang.reflect.InvocationTargetException
    //   461	3	19	localObject3	Object
    //   374	9	20	localMethod4	java.lang.reflect.Method
    //   380	6	21	arrayOfObject4	Object[]
    //   516	3	22	localInvocationTargetException4	java.lang.reflect.InvocationTargetException
    //   390	3	23	localObject4	Object
    //   282	9	24	localMethod5	java.lang.reflect.Method
    //   288	6	25	arrayOfObject5	Object[]
    //   524	3	26	localInvocationTargetException5	java.lang.reflect.InvocationTargetException
    //   298	3	27	localObject5	Object
    //   39	9	28	localMethod6	java.lang.reflect.Method
    //   45	6	29	arrayOfObject6	Object[]
    //   484	3	30	localInvocationTargetException6	java.lang.reflect.InvocationTargetException
    //   55	3	31	localObject6	Object
    //   86	9	32	localMethod7	java.lang.reflect.Method
    //   92	6	33	arrayOfObject7	Object[]
    //   492	3	34	localInvocationTargetException7	java.lang.reflect.InvocationTargetException
    //   102	3	35	localObject7	Object
    // Exception table:
    //   from	to	target	type
    //   453	463	476	java/lang/reflect/InvocationTargetException
    //   47	57	484	java/lang/reflect/InvocationTargetException
    //   94	104	492	java/lang/reflect/InvocationTargetException
    //   152	161	500	java/lang/reflect/InvocationTargetException
    //   225	235	508	java/lang/reflect/InvocationTargetException
    //   382	392	516	java/lang/reflect/InvocationTargetException
    //   290	300	524	java/lang/reflect/InvocationTargetException
  }
  
  /* Error */
  public boolean bk006Bkkkk006Bk006Bk()
  {
    // Byte code:
    //   0: aload_0
    //   1: getfield 315	uuuuuu/sttsst:b006E006E006E006E006En006E006En	Luuuuuu/hyhyhh;
    //   4: invokevirtual 320	uuuuuu/hyhyhh:b0070pp007000700070p007000700070	()Ljava/lang/String;
    //   7: astore_1
    //   8: aload_1
    //   9: ifnull +293 -> 302
    //   12: aload_0
    //   13: getfield 322	uuuuuu/sttsst:bn006En006Enn006E006En	Lcom/db/pwcc/dbmobile/secure/SecurityUtils;
    //   16: astore 19
    //   18: ldc_w 324
    //   21: ldc_w 326
    //   24: bipush 37
    //   26: iconst_5
    //   27: invokestatic 91	xxxxxx/uxxxxx:bb00620062bb0062b0062b0062	(Ljava/lang/String;CC)Ljava/lang/String;
    //   30: iconst_1
    //   31: anewarray 56	java/lang/Class
    //   34: dup
    //   35: iconst_0
    //   36: ldc -115
    //   38: aastore
    //   39: invokevirtual 60	java/lang/Class:getMethod	(Ljava/lang/String;[Ljava/lang/Class;)Ljava/lang/reflect/Method;
    //   42: astore 20
    //   44: iconst_1
    //   45: anewarray 62	java/lang/Object
    //   48: dup
    //   49: iconst_0
    //   50: aload_1
    //   51: aastore
    //   52: astore 21
    //   54: aload 20
    //   56: aload 19
    //   58: aload 21
    //   60: invokevirtual 68	java/lang/reflect/Method:invoke	(Ljava/lang/Object;[Ljava/lang/Object;)Ljava/lang/Object;
    //   63: astore 23
    //   65: aload 23
    //   67: checkcast 113	java/lang/Boolean
    //   70: invokevirtual 117	java/lang/Boolean:booleanValue	()Z
    //   73: ifeq +229 -> 302
    //   76: getstatic 77	uuuuuu/sttsst:b006E006E006E006Enn006E006En	I
    //   79: istore 24
    //   81: ldc 2
    //   83: ldc_w 328
    //   86: bipush 70
    //   88: bipush 89
    //   90: iconst_2
    //   91: invokestatic 54	xxxxxx/uxxxxx:bbbb0062b0062b0062b0062	(Ljava/lang/String;CCC)Ljava/lang/String;
    //   94: iconst_0
    //   95: anewarray 56	java/lang/Class
    //   98: invokevirtual 60	java/lang/Class:getMethod	(Ljava/lang/String;[Ljava/lang/Class;)Ljava/lang/reflect/Method;
    //   101: astore 25
    //   103: iconst_0
    //   104: anewarray 62	java/lang/Object
    //   107: astore 26
    //   109: aload 25
    //   111: aconst_null
    //   112: aload 26
    //   114: invokevirtual 68	java/lang/reflect/Method:invoke	(Ljava/lang/Object;[Ljava/lang/Object;)Ljava/lang/Object;
    //   117: astore 28
    //   119: iload 24
    //   121: aload 28
    //   123: checkcast 70	java/lang/Integer
    //   126: invokevirtual 73	java/lang/Integer:intValue	()I
    //   129: iadd
    //   130: getstatic 77	uuuuuu/sttsst:b006E006E006E006Enn006E006En	I
    //   133: imul
    //   134: istore 29
    //   136: ldc 2
    //   138: ldc_w 330
    //   141: sipush 226
    //   144: bipush 65
    //   146: iconst_3
    //   147: invokestatic 54	xxxxxx/uxxxxx:bbbb0062b0062b0062b0062	(Ljava/lang/String;CCC)Ljava/lang/String;
    //   150: iconst_0
    //   151: anewarray 56	java/lang/Class
    //   154: invokevirtual 60	java/lang/Class:getMethod	(Ljava/lang/String;[Ljava/lang/Class;)Ljava/lang/reflect/Method;
    //   157: astore 30
    //   159: iconst_0
    //   160: anewarray 62	java/lang/Object
    //   163: astore 31
    //   165: aload 30
    //   167: aconst_null
    //   168: aload 31
    //   170: invokevirtual 68	java/lang/reflect/Method:invoke	(Ljava/lang/Object;[Ljava/lang/Object;)Ljava/lang/Object;
    //   173: astore 33
    //   175: iload 29
    //   177: aload 33
    //   179: checkcast 70	java/lang/Integer
    //   182: invokevirtual 73	java/lang/Integer:intValue	()I
    //   185: irem
    //   186: getstatic 81	uuuuuu/sttsst:bnnnn006En006E006En	I
    //   189: if_icmpeq +414 -> 603
    //   192: ldc 2
    //   194: ldc_w 332
    //   197: bipush 35
    //   199: bipush 72
    //   201: iconst_1
    //   202: invokestatic 54	xxxxxx/uxxxxx:bbbb0062b0062b0062b0062	(Ljava/lang/String;CCC)Ljava/lang/String;
    //   205: iconst_0
    //   206: anewarray 56	java/lang/Class
    //   209: invokevirtual 60	java/lang/Class:getMethod	(Ljava/lang/String;[Ljava/lang/Class;)Ljava/lang/reflect/Method;
    //   212: astore 34
    //   214: iconst_0
    //   215: anewarray 62	java/lang/Object
    //   218: astore 35
    //   220: aload 34
    //   222: aconst_null
    //   223: aload 35
    //   225: invokevirtual 68	java/lang/reflect/Method:invoke	(Ljava/lang/Object;[Ljava/lang/Object;)Ljava/lang/Object;
    //   228: astore 37
    //   230: aload 37
    //   232: checkcast 70	java/lang/Integer
    //   235: invokevirtual 73	java/lang/Integer:intValue	()I
    //   238: putstatic 77	uuuuuu/sttsst:b006E006E006E006Enn006E006En	I
    //   241: ldc 2
    //   243: ldc_w 334
    //   246: sipush 231
    //   249: sipush 254
    //   252: iconst_3
    //   253: invokestatic 54	xxxxxx/uxxxxx:bbbb0062b0062b0062b0062	(Ljava/lang/String;CCC)Ljava/lang/String;
    //   256: iconst_0
    //   257: anewarray 56	java/lang/Class
    //   260: invokevirtual 60	java/lang/Class:getMethod	(Ljava/lang/String;[Ljava/lang/Class;)Ljava/lang/reflect/Method;
    //   263: astore 38
    //   265: iconst_0
    //   266: anewarray 62	java/lang/Object
    //   269: astore 39
    //   271: aload 38
    //   273: aconst_null
    //   274: aload 39
    //   276: invokevirtual 68	java/lang/reflect/Method:invoke	(Ljava/lang/Object;[Ljava/lang/Object;)Ljava/lang/Object;
    //   279: astore 41
    //   281: aload 41
    //   283: checkcast 70	java/lang/Integer
    //   286: invokevirtual 73	java/lang/Integer:intValue	()I
    //   289: putstatic 81	uuuuuu/sttsst:bnnnn006En006E006En	I
    //   292: iconst_1
    //   293: ireturn
    //   294: astore 22
    //   296: aload 22
    //   298: invokevirtual 100	java/lang/reflect/InvocationTargetException:getCause	()Ljava/lang/Throwable;
    //   301: athrow
    //   302: iconst_5
    //   303: istore_2
    //   304: iload_2
    //   305: iconst_0
    //   306: idiv
    //   307: istore 13
    //   309: getstatic 77	uuuuuu/sttsst:b006E006E006E006Enn006E006En	I
    //   312: istore 14
    //   314: iload 14
    //   316: iload 14
    //   318: getstatic 75	uuuuuu/sttsst:b006En006E006Enn006E006En	I
    //   321: iadd
    //   322: imul
    //   323: getstatic 83	uuuuuu/sttsst:bn006E006E006Enn006E006En	I
    //   326: irem
    //   327: tableswitch	default:+17->344, 0:+278->605
    //   344: bipush 7
    //   346: putstatic 77	uuuuuu/sttsst:b006E006E006E006Enn006E006En	I
    //   349: ldc 2
    //   351: ldc_w 336
    //   354: bipush 94
    //   356: sipush 171
    //   359: iconst_1
    //   360: invokestatic 54	xxxxxx/uxxxxx:bbbb0062b0062b0062b0062	(Ljava/lang/String;CCC)Ljava/lang/String;
    //   363: iconst_0
    //   364: anewarray 56	java/lang/Class
    //   367: invokevirtual 60	java/lang/Class:getMethod	(Ljava/lang/String;[Ljava/lang/Class;)Ljava/lang/reflect/Method;
    //   370: astore 15
    //   372: iconst_0
    //   373: anewarray 62	java/lang/Object
    //   376: astore 16
    //   378: aload 15
    //   380: aconst_null
    //   381: aload 16
    //   383: invokevirtual 68	java/lang/reflect/Method:invoke	(Ljava/lang/Object;[Ljava/lang/Object;)Ljava/lang/Object;
    //   386: astore 18
    //   388: aload 18
    //   390: checkcast 70	java/lang/Integer
    //   393: invokevirtual 73	java/lang/Integer:intValue	()I
    //   396: putstatic 81	uuuuuu/sttsst:bnnnn006En006E006En	I
    //   399: iload 13
    //   401: istore_2
    //   402: goto -98 -> 304
    //   405: astore_3
    //   406: getstatic 77	uuuuuu/sttsst:b006E006E006E006Enn006E006En	I
    //   409: istore 4
    //   411: iload 4
    //   413: iload 4
    //   415: getstatic 75	uuuuuu/sttsst:b006En006E006Enn006E006En	I
    //   418: iadd
    //   419: imul
    //   420: getstatic 83	uuuuuu/sttsst:bn006E006E006Enn006E006En	I
    //   423: irem
    //   424: tableswitch	default:+20->444, 0:+116->540
    //   444: ldc 2
    //   446: ldc_w 338
    //   449: sipush 175
    //   452: iconst_0
    //   453: invokestatic 91	xxxxxx/uxxxxx:bb00620062bb0062b0062b0062	(Ljava/lang/String;CC)Ljava/lang/String;
    //   456: iconst_0
    //   457: anewarray 56	java/lang/Class
    //   460: invokevirtual 60	java/lang/Class:getMethod	(Ljava/lang/String;[Ljava/lang/Class;)Ljava/lang/reflect/Method;
    //   463: astore 5
    //   465: iconst_0
    //   466: anewarray 62	java/lang/Object
    //   469: astore 6
    //   471: aload 5
    //   473: aconst_null
    //   474: aload 6
    //   476: invokevirtual 68	java/lang/reflect/Method:invoke	(Ljava/lang/Object;[Ljava/lang/Object;)Ljava/lang/Object;
    //   479: astore 8
    //   481: aload 8
    //   483: checkcast 70	java/lang/Integer
    //   486: invokevirtual 73	java/lang/Integer:intValue	()I
    //   489: putstatic 77	uuuuuu/sttsst:b006E006E006E006Enn006E006En	I
    //   492: ldc 2
    //   494: ldc_w 340
    //   497: sipush 222
    //   500: iconst_4
    //   501: invokestatic 91	xxxxxx/uxxxxx:bb00620062bb0062b0062b0062	(Ljava/lang/String;CC)Ljava/lang/String;
    //   504: iconst_0
    //   505: anewarray 56	java/lang/Class
    //   508: invokevirtual 60	java/lang/Class:getMethod	(Ljava/lang/String;[Ljava/lang/Class;)Ljava/lang/reflect/Method;
    //   511: astore 9
    //   513: iconst_0
    //   514: anewarray 62	java/lang/Object
    //   517: astore 10
    //   519: aload 9
    //   521: aconst_null
    //   522: aload 10
    //   524: invokevirtual 68	java/lang/reflect/Method:invoke	(Ljava/lang/Object;[Ljava/lang/Object;)Ljava/lang/Object;
    //   527: astore 12
    //   529: aload 12
    //   531: checkcast 70	java/lang/Integer
    //   534: invokevirtual 73	java/lang/Integer:intValue	()I
    //   537: putstatic 81	uuuuuu/sttsst:bnnnn006En006E006En	I
    //   540: bipush 13
    //   542: putstatic 77	uuuuuu/sttsst:b006E006E006E006Enn006E006En	I
    //   545: iconst_0
    //   546: ireturn
    //   547: astore 7
    //   549: aload 7
    //   551: invokevirtual 100	java/lang/reflect/InvocationTargetException:getCause	()Ljava/lang/Throwable;
    //   554: athrow
    //   555: astore 11
    //   557: aload 11
    //   559: invokevirtual 100	java/lang/reflect/InvocationTargetException:getCause	()Ljava/lang/Throwable;
    //   562: athrow
    //   563: astore 36
    //   565: aload 36
    //   567: invokevirtual 100	java/lang/reflect/InvocationTargetException:getCause	()Ljava/lang/Throwable;
    //   570: athrow
    //   571: astore 27
    //   573: aload 27
    //   575: invokevirtual 100	java/lang/reflect/InvocationTargetException:getCause	()Ljava/lang/Throwable;
    //   578: athrow
    //   579: astore 32
    //   581: aload 32
    //   583: invokevirtual 100	java/lang/reflect/InvocationTargetException:getCause	()Ljava/lang/Throwable;
    //   586: athrow
    //   587: astore 40
    //   589: aload 40
    //   591: invokevirtual 100	java/lang/reflect/InvocationTargetException:getCause	()Ljava/lang/Throwable;
    //   594: athrow
    //   595: astore 17
    //   597: aload 17
    //   599: invokevirtual 100	java/lang/reflect/InvocationTargetException:getCause	()Ljava/lang/Throwable;
    //   602: athrow
    //   603: iconst_1
    //   604: ireturn
    //   605: iload 13
    //   607: istore_2
    //   608: goto -304 -> 304
    // Local variable table:
    //   start	length	slot	name	signature
    //   0	611	0	this	sttsst
    //   7	44	1	str	String
    //   303	305	2	i	int
    //   405	1	3	localException	Exception
    //   409	11	4	j	int
    //   463	9	5	localMethod1	java.lang.reflect.Method
    //   469	6	6	arrayOfObject1	Object[]
    //   547	3	7	localInvocationTargetException1	java.lang.reflect.InvocationTargetException
    //   479	3	8	localObject1	Object
    //   511	9	9	localMethod2	java.lang.reflect.Method
    //   517	6	10	arrayOfObject2	Object[]
    //   555	3	11	localInvocationTargetException2	java.lang.reflect.InvocationTargetException
    //   527	3	12	localObject2	Object
    //   307	299	13	k	int
    //   312	11	14	m	int
    //   370	9	15	localMethod3	java.lang.reflect.Method
    //   376	6	16	arrayOfObject3	Object[]
    //   595	3	17	localInvocationTargetException3	java.lang.reflect.InvocationTargetException
    //   386	3	18	localObject3	Object
    //   16	41	19	localSecurityUtils	SecurityUtils
    //   42	13	20	localMethod4	java.lang.reflect.Method
    //   52	7	21	arrayOfObject4	Object[]
    //   294	3	22	localInvocationTargetException4	java.lang.reflect.InvocationTargetException
    //   63	3	23	localObject4	Object
    //   79	51	24	n	int
    //   101	9	25	localMethod5	java.lang.reflect.Method
    //   107	6	26	arrayOfObject5	Object[]
    //   571	3	27	localInvocationTargetException5	java.lang.reflect.InvocationTargetException
    //   117	5	28	localObject5	Object
    //   134	52	29	i1	int
    //   157	9	30	localMethod6	java.lang.reflect.Method
    //   163	6	31	arrayOfObject6	Object[]
    //   579	3	32	localInvocationTargetException6	java.lang.reflect.InvocationTargetException
    //   173	5	33	localObject6	Object
    //   212	9	34	localMethod7	java.lang.reflect.Method
    //   218	6	35	arrayOfObject7	Object[]
    //   563	3	36	localInvocationTargetException7	java.lang.reflect.InvocationTargetException
    //   228	3	37	localObject7	Object
    //   263	9	38	localMethod8	java.lang.reflect.Method
    //   269	6	39	arrayOfObject8	Object[]
    //   587	3	40	localInvocationTargetException8	java.lang.reflect.InvocationTargetException
    //   279	3	41	localObject8	Object
    // Exception table:
    //   from	to	target	type
    //   54	65	294	java/lang/reflect/InvocationTargetException
    //   304	309	405	java/lang/Exception
    //   471	481	547	java/lang/reflect/InvocationTargetException
    //   519	529	555	java/lang/reflect/InvocationTargetException
    //   220	230	563	java/lang/reflect/InvocationTargetException
    //   109	119	571	java/lang/reflect/InvocationTargetException
    //   165	175	579	java/lang/reflect/InvocationTargetException
    //   271	281	587	java/lang/reflect/InvocationTargetException
    //   378	388	595	java/lang/reflect/InvocationTargetException
  }
}
