package uuuuuu;

import android.content.Context;
import com.db.pwcc.dbmobile.secure.preferences.SharedPreferencesHelper;
import javax.inject.Inject;

public class ttstss
  extends qppppp<stttss.ssttss>
  implements stttss.tsttss
{
  public static int b006E006E006En006En006En006E = 1;
  public static int b006Enn006E006En006En006E = 43;
  public static int bn006E006En006En006En006E = 0;
  public static int bnnn006E006En006En006E = 2;
  @Inject
  public SharedPreferencesHelper b006En006En006En006En006E;
  @Inject
  public Context bnn006En006En006En006E;
  
  public ttstss()
  {
    pqqppq.b006B006B006Bkkk006Bkkk().b0061a0061a006100610061006100610061(this);
  }
  
  public static int b006Bk006Bkk006Bk006B006Bk()
  {
    return 1;
  }
  
  public static int b006Bkkkk006Bk006B006Bk()
  {
    return 2;
  }
  
  public static int bk006Bkkk006Bk006B006Bk()
  {
    return 0;
  }
  
  public static int bkk006Bkk006Bk006B006Bk()
  {
    return 7;
  }
  
  /* Error */
  public void b006B006B006Bk006Bkk006B006Bk(android.net.Uri paramUri)
  {
    // Byte code:
    //   0: new 128	uuuuuu/ttstss$2
    //   3: dup
    //   4: aload_0
    //   5: aload_1
    //   6: invokespecial 131	uuuuuu/ttstss$2:<init>	(Luuuuuu/ttstss;Landroid/net/Uri;)V
    //   9: invokestatic 137	rx/Observable:fromCallable	(Ljava/util/concurrent/Callable;)Lrx/Observable;
    //   12: invokestatic 143	rx/schedulers/Schedulers:newThread	()Lrx/Scheduler;
    //   15: invokevirtual 147	rx/Observable:subscribeOn	(Lrx/Scheduler;)Lrx/Observable;
    //   18: invokestatic 152	rx/android/schedulers/AndroidSchedulers:mainThread	()Lrx/Scheduler;
    //   21: invokevirtual 155	rx/Observable:observeOn	(Lrx/Scheduler;)Lrx/Observable;
    //   24: astore_2
    //   25: getstatic 75	uuuuuu/ttstss:b006Enn006E006En006En006E	I
    //   28: getstatic 77	uuuuuu/ttstss:b006E006E006En006En006En006E	I
    //   31: iadd
    //   32: getstatic 75	uuuuuu/ttstss:b006Enn006E006En006En006E	I
    //   35: imul
    //   36: getstatic 79	uuuuuu/ttstss:bnnn006E006En006En006E	I
    //   39: irem
    //   40: getstatic 89	uuuuuu/ttstss:bn006E006En006En006En006E	I
    //   43: if_icmpeq +190 -> 233
    //   46: getstatic 75	uuuuuu/ttstss:b006Enn006E006En006En006E	I
    //   49: istore 18
    //   51: iload 18
    //   53: iload 18
    //   55: getstatic 77	uuuuuu/ttstss:b006E006E006En006En006En006E	I
    //   58: iadd
    //   59: imul
    //   60: getstatic 79	uuuuuu/ttstss:bnnn006E006En006En006E	I
    //   63: irem
    //   64: tableswitch	default:+20->84, 0:+73->137
    //   84: ldc 2
    //   86: ldc -99
    //   88: bipush 121
    //   90: bipush 63
    //   92: iconst_2
    //   93: invokestatic 87	xxxxxx/uxxxxx:bbbb0062b0062b0062b0062	(Ljava/lang/String;CCC)Ljava/lang/String;
    //   96: iconst_0
    //   97: anewarray 55	java/lang/Class
    //   100: invokevirtual 59	java/lang/Class:getMethod	(Ljava/lang/String;[Ljava/lang/Class;)Ljava/lang/reflect/Method;
    //   103: astore 24
    //   105: iconst_0
    //   106: anewarray 61	java/lang/Object
    //   109: astore 25
    //   111: aload 24
    //   113: aconst_null
    //   114: aload 25
    //   116: invokevirtual 67	java/lang/reflect/Method:invoke	(Ljava/lang/Object;[Ljava/lang/Object;)Ljava/lang/Object;
    //   119: astore 27
    //   121: aload 27
    //   123: checkcast 69	java/lang/Integer
    //   126: invokevirtual 73	java/lang/Integer:intValue	()I
    //   129: putstatic 75	uuuuuu/ttstss:b006Enn006E006En006En006E	I
    //   132: bipush 6
    //   134: putstatic 89	uuuuuu/ttstss:bn006E006En006En006En006E	I
    //   137: getstatic 75	uuuuuu/ttstss:b006Enn006E006En006En006E	I
    //   140: istore 19
    //   142: iload 19
    //   144: iload 19
    //   146: getstatic 77	uuuuuu/ttstss:b006E006E006En006En006En006E	I
    //   149: iadd
    //   150: imul
    //   151: getstatic 79	uuuuuu/ttstss:bnnn006E006En006En006E	I
    //   154: irem
    //   155: tableswitch	default:+17->172, 0:+27->182
    //   172: bipush 86
    //   174: putstatic 75	uuuuuu/ttstss:b006Enn006E006En006En006E	I
    //   177: bipush 55
    //   179: putstatic 89	uuuuuu/ttstss:bn006E006En006En006En006E	I
    //   182: ldc 2
    //   184: ldc -97
    //   186: bipush 41
    //   188: iconst_0
    //   189: invokestatic 53	xxxxxx/uxxxxx:bb00620062bb0062b0062b0062	(Ljava/lang/String;CC)Ljava/lang/String;
    //   192: iconst_0
    //   193: anewarray 55	java/lang/Class
    //   196: invokevirtual 59	java/lang/Class:getMethod	(Ljava/lang/String;[Ljava/lang/Class;)Ljava/lang/reflect/Method;
    //   199: astore 20
    //   201: iconst_0
    //   202: anewarray 61	java/lang/Object
    //   205: astore 21
    //   207: aload 20
    //   209: aconst_null
    //   210: aload 21
    //   212: invokevirtual 67	java/lang/reflect/Method:invoke	(Ljava/lang/Object;[Ljava/lang/Object;)Ljava/lang/Object;
    //   215: astore 23
    //   217: aload 23
    //   219: checkcast 69	java/lang/Integer
    //   222: invokevirtual 73	java/lang/Integer:intValue	()I
    //   225: putstatic 75	uuuuuu/ttstss:b006Enn006E006En006En006E	I
    //   228: bipush 17
    //   230: putstatic 89	uuuuuu/ttstss:bn006E006En006En006En006E	I
    //   233: getstatic 75	uuuuuu/ttstss:b006Enn006E006En006En006E	I
    //   236: istore_3
    //   237: iload_3
    //   238: iload_3
    //   239: getstatic 77	uuuuuu/ttstss:b006E006E006En006En006En006E	I
    //   242: iadd
    //   243: imul
    //   244: istore 4
    //   246: ldc 2
    //   248: ldc -95
    //   250: bipush 122
    //   252: iconst_0
    //   253: invokestatic 53	xxxxxx/uxxxxx:bb00620062bb0062b0062b0062	(Ljava/lang/String;CC)Ljava/lang/String;
    //   256: iconst_0
    //   257: anewarray 55	java/lang/Class
    //   260: invokevirtual 59	java/lang/Class:getMethod	(Ljava/lang/String;[Ljava/lang/Class;)Ljava/lang/reflect/Method;
    //   263: astore 5
    //   265: iconst_0
    //   266: anewarray 61	java/lang/Object
    //   269: astore 6
    //   271: aload 5
    //   273: aconst_null
    //   274: aload 6
    //   276: invokevirtual 67	java/lang/reflect/Method:invoke	(Ljava/lang/Object;[Ljava/lang/Object;)Ljava/lang/Object;
    //   279: astore 8
    //   281: iload 4
    //   283: aload 8
    //   285: checkcast 69	java/lang/Integer
    //   288: invokevirtual 73	java/lang/Integer:intValue	()I
    //   291: irem
    //   292: tableswitch	default:+20->312, 0:+115->407
    //   312: ldc 2
    //   314: ldc -93
    //   316: bipush 54
    //   318: sipush 216
    //   321: iconst_0
    //   322: invokestatic 87	xxxxxx/uxxxxx:bbbb0062b0062b0062b0062	(Ljava/lang/String;CCC)Ljava/lang/String;
    //   325: iconst_0
    //   326: anewarray 55	java/lang/Class
    //   329: invokevirtual 59	java/lang/Class:getMethod	(Ljava/lang/String;[Ljava/lang/Class;)Ljava/lang/reflect/Method;
    //   332: astore 10
    //   334: iconst_0
    //   335: anewarray 61	java/lang/Object
    //   338: astore 11
    //   340: aload 10
    //   342: aconst_null
    //   343: aload 11
    //   345: invokevirtual 67	java/lang/reflect/Method:invoke	(Ljava/lang/Object;[Ljava/lang/Object;)Ljava/lang/Object;
    //   348: astore 13
    //   350: aload 13
    //   352: checkcast 69	java/lang/Integer
    //   355: invokevirtual 73	java/lang/Integer:intValue	()I
    //   358: putstatic 75	uuuuuu/ttstss:b006Enn006E006En006En006E	I
    //   361: ldc 2
    //   363: ldc -91
    //   365: bipush 90
    //   367: iconst_4
    //   368: invokestatic 53	xxxxxx/uxxxxx:bb00620062bb0062b0062b0062	(Ljava/lang/String;CC)Ljava/lang/String;
    //   371: iconst_0
    //   372: anewarray 55	java/lang/Class
    //   375: invokevirtual 59	java/lang/Class:getMethod	(Ljava/lang/String;[Ljava/lang/Class;)Ljava/lang/reflect/Method;
    //   378: astore 14
    //   380: iconst_0
    //   381: anewarray 61	java/lang/Object
    //   384: astore 15
    //   386: aload 14
    //   388: aconst_null
    //   389: aload 15
    //   391: invokevirtual 67	java/lang/reflect/Method:invoke	(Ljava/lang/Object;[Ljava/lang/Object;)Ljava/lang/Object;
    //   394: astore 17
    //   396: aload 17
    //   398: checkcast 69	java/lang/Integer
    //   401: invokevirtual 73	java/lang/Integer:intValue	()I
    //   404: putstatic 89	uuuuuu/ttstss:bn006E006En006En006En006E	I
    //   407: aload_2
    //   408: new 167	uuuuuu/ttstss$1
    //   411: dup
    //   412: aload_0
    //   413: invokespecial 169	uuuuuu/ttstss$1:<init>	(Luuuuuu/ttstss;)V
    //   416: invokevirtual 173	rx/Observable:subscribe	(Lrx/functions/Action1;)Lrx/Subscription;
    //   419: pop
    //   420: return
    //   421: astore 22
    //   423: aload 22
    //   425: invokevirtual 105	java/lang/reflect/InvocationTargetException:getCause	()Ljava/lang/Throwable;
    //   428: athrow
    //   429: astore 12
    //   431: aload 12
    //   433: invokevirtual 105	java/lang/reflect/InvocationTargetException:getCause	()Ljava/lang/Throwable;
    //   436: athrow
    //   437: astore 16
    //   439: aload 16
    //   441: invokevirtual 105	java/lang/reflect/InvocationTargetException:getCause	()Ljava/lang/Throwable;
    //   444: athrow
    //   445: astore 7
    //   447: aload 7
    //   449: invokevirtual 105	java/lang/reflect/InvocationTargetException:getCause	()Ljava/lang/Throwable;
    //   452: athrow
    //   453: astore 26
    //   455: aload 26
    //   457: invokevirtual 105	java/lang/reflect/InvocationTargetException:getCause	()Ljava/lang/Throwable;
    //   460: athrow
    // Local variable table:
    //   start	length	slot	name	signature
    //   0	461	0	this	ttstss
    //   0	461	1	paramUri	android.net.Uri
    //   24	384	2	localObservable	rx.Observable
    //   236	8	3	i	int
    //   244	48	4	j	int
    //   263	9	5	localMethod1	java.lang.reflect.Method
    //   269	6	6	arrayOfObject1	Object[]
    //   445	3	7	localInvocationTargetException1	java.lang.reflect.InvocationTargetException
    //   279	5	8	localObject1	Object
    //   332	9	10	localMethod2	java.lang.reflect.Method
    //   338	6	11	arrayOfObject2	Object[]
    //   429	3	12	localInvocationTargetException2	java.lang.reflect.InvocationTargetException
    //   348	3	13	localObject2	Object
    //   378	9	14	localMethod3	java.lang.reflect.Method
    //   384	6	15	arrayOfObject3	Object[]
    //   437	3	16	localInvocationTargetException3	java.lang.reflect.InvocationTargetException
    //   394	3	17	localObject3	Object
    //   49	11	18	k	int
    //   140	11	19	m	int
    //   199	9	20	localMethod4	java.lang.reflect.Method
    //   205	6	21	arrayOfObject4	Object[]
    //   421	3	22	localInvocationTargetException4	java.lang.reflect.InvocationTargetException
    //   215	3	23	localObject4	Object
    //   103	9	24	localMethod5	java.lang.reflect.Method
    //   109	6	25	arrayOfObject5	Object[]
    //   453	3	26	localInvocationTargetException5	java.lang.reflect.InvocationTargetException
    //   119	3	27	localObject5	Object
    // Exception table:
    //   from	to	target	type
    //   207	217	421	java/lang/reflect/InvocationTargetException
    //   340	350	429	java/lang/reflect/InvocationTargetException
    //   386	396	437	java/lang/reflect/InvocationTargetException
    //   271	281	445	java/lang/reflect/InvocationTargetException
    //   111	121	453	java/lang/reflect/InvocationTargetException
  }
  
  /* Error */
  public void b006B006B006Bkk006Bk006B006Bk()
  {
    // Byte code:
    //   0: aload_0
    //   1: getfield 176	uuuuuu/ttstss:b006En006En006En006En006E	Lcom/db/pwcc/dbmobile/secure/preferences/SharedPreferencesHelper;
    //   4: astore_1
    //   5: ldc -78
    //   7: ldc -76
    //   9: bipush 64
    //   11: iconst_0
    //   12: invokestatic 53	xxxxxx/uxxxxx:bb00620062bb0062b0062b0062	(Ljava/lang/String;CC)Ljava/lang/String;
    //   15: iconst_0
    //   16: anewarray 55	java/lang/Class
    //   19: invokevirtual 59	java/lang/Class:getMethod	(Ljava/lang/String;[Ljava/lang/Class;)Ljava/lang/reflect/Method;
    //   22: astore_2
    //   23: iconst_0
    //   24: anewarray 61	java/lang/Object
    //   27: astore_3
    //   28: aload_2
    //   29: aload_1
    //   30: aload_3
    //   31: invokevirtual 67	java/lang/reflect/Method:invoke	(Ljava/lang/Object;[Ljava/lang/Object;)Ljava/lang/Object;
    //   34: astore 5
    //   36: aload 5
    //   38: checkcast 182	java/lang/String
    //   41: invokevirtual 186	java/lang/String:isEmpty	()Z
    //   44: ifeq +721 -> 765
    //   47: aload_0
    //   48: getfield 176	uuuuuu/ttstss:b006En006En006En006En006E	Lcom/db/pwcc/dbmobile/secure/preferences/SharedPreferencesHelper;
    //   51: astore 10
    //   53: ldc -78
    //   55: ldc -68
    //   57: bipush 82
    //   59: iconst_2
    //   60: invokestatic 53	xxxxxx/uxxxxx:bb00620062bb0062b0062b0062	(Ljava/lang/String;CC)Ljava/lang/String;
    //   63: iconst_0
    //   64: anewarray 55	java/lang/Class
    //   67: invokevirtual 59	java/lang/Class:getMethod	(Ljava/lang/String;[Ljava/lang/Class;)Ljava/lang/reflect/Method;
    //   70: astore 11
    //   72: iconst_0
    //   73: anewarray 61	java/lang/Object
    //   76: astore 12
    //   78: aload 11
    //   80: aload 10
    //   82: aload 12
    //   84: invokevirtual 67	java/lang/reflect/Method:invoke	(Ljava/lang/Object;[Ljava/lang/Object;)Ljava/lang/Object;
    //   87: astore 14
    //   89: aload 14
    //   91: checkcast 69	java/lang/Integer
    //   94: invokevirtual 73	java/lang/Integer:intValue	()I
    //   97: invokestatic 194	com/db/pwcc/dbmobile/foundation/utils/BackgroundChangeEnum:values	()[Lcom/db/pwcc/dbmobile/foundation/utils/BackgroundChangeEnum;
    //   100: arraylength
    //   101: if_icmpge +531 -> 632
    //   104: ldc 2
    //   106: ldc -60
    //   108: sipush 253
    //   111: sipush 154
    //   114: iconst_2
    //   115: invokestatic 87	xxxxxx/uxxxxx:bbbb0062b0062b0062b0062	(Ljava/lang/String;CCC)Ljava/lang/String;
    //   118: iconst_0
    //   119: anewarray 55	java/lang/Class
    //   122: invokevirtual 59	java/lang/Class:getMethod	(Ljava/lang/String;[Ljava/lang/Class;)Ljava/lang/reflect/Method;
    //   125: astore 22
    //   127: iconst_0
    //   128: anewarray 61	java/lang/Object
    //   131: astore 23
    //   133: aload 22
    //   135: aconst_null
    //   136: aload 23
    //   138: invokevirtual 67	java/lang/reflect/Method:invoke	(Ljava/lang/Object;[Ljava/lang/Object;)Ljava/lang/Object;
    //   141: astore 25
    //   143: aload 25
    //   145: checkcast 69	java/lang/Integer
    //   148: invokevirtual 73	java/lang/Integer:intValue	()I
    //   151: getstatic 77	uuuuuu/ttstss:b006E006E006En006En006En006E	I
    //   154: iadd
    //   155: istore 26
    //   157: ldc 2
    //   159: ldc -58
    //   161: sipush 131
    //   164: iconst_0
    //   165: invokestatic 53	xxxxxx/uxxxxx:bb00620062bb0062b0062b0062	(Ljava/lang/String;CC)Ljava/lang/String;
    //   168: iconst_0
    //   169: anewarray 55	java/lang/Class
    //   172: invokevirtual 59	java/lang/Class:getMethod	(Ljava/lang/String;[Ljava/lang/Class;)Ljava/lang/reflect/Method;
    //   175: astore 27
    //   177: iconst_0
    //   178: anewarray 61	java/lang/Object
    //   181: astore 28
    //   183: aload 27
    //   185: aconst_null
    //   186: aload 28
    //   188: invokevirtual 67	java/lang/reflect/Method:invoke	(Ljava/lang/Object;[Ljava/lang/Object;)Ljava/lang/Object;
    //   191: astore 30
    //   193: aload 30
    //   195: checkcast 69	java/lang/Integer
    //   198: invokevirtual 73	java/lang/Integer:intValue	()I
    //   201: istore 31
    //   203: getstatic 75	uuuuuu/ttstss:b006Enn006E006En006En006E	I
    //   206: istore 32
    //   208: iload 32
    //   210: iload 32
    //   212: getstatic 77	uuuuuu/ttstss:b006E006E006En006En006En006E	I
    //   215: iadd
    //   216: imul
    //   217: getstatic 79	uuuuuu/ttstss:bnnn006E006En006En006E	I
    //   220: irem
    //   221: tableswitch	default:+19->240, 0:+72->293
    //   240: ldc 2
    //   242: ldc -56
    //   244: bipush 118
    //   246: sipush 187
    //   249: iconst_3
    //   250: invokestatic 87	xxxxxx/uxxxxx:bbbb0062b0062b0062b0062	(Ljava/lang/String;CCC)Ljava/lang/String;
    //   253: iconst_0
    //   254: anewarray 55	java/lang/Class
    //   257: invokevirtual 59	java/lang/Class:getMethod	(Ljava/lang/String;[Ljava/lang/Class;)Ljava/lang/reflect/Method;
    //   260: astore 56
    //   262: iconst_0
    //   263: anewarray 61	java/lang/Object
    //   266: astore 57
    //   268: aload 56
    //   270: aconst_null
    //   271: aload 57
    //   273: invokevirtual 67	java/lang/reflect/Method:invoke	(Ljava/lang/Object;[Ljava/lang/Object;)Ljava/lang/Object;
    //   276: astore 59
    //   278: aload 59
    //   280: checkcast 69	java/lang/Integer
    //   283: invokevirtual 73	java/lang/Integer:intValue	()I
    //   286: putstatic 75	uuuuuu/ttstss:b006Enn006E006En006En006E	I
    //   289: iconst_4
    //   290: putstatic 89	uuuuuu/ttstss:bn006E006En006En006En006E	I
    //   293: iload 26
    //   295: iload 31
    //   297: imul
    //   298: getstatic 79	uuuuuu/ttstss:bnnn006E006En006En006E	I
    //   301: irem
    //   302: getstatic 89	uuuuuu/ttstss:bn006E006En006En006En006E	I
    //   305: if_icmpeq +175 -> 480
    //   308: bipush 49
    //   310: putstatic 75	uuuuuu/ttstss:b006Enn006E006En006En006E	I
    //   313: ldc 2
    //   315: ldc -54
    //   317: bipush 37
    //   319: iconst_3
    //   320: invokestatic 53	xxxxxx/uxxxxx:bb00620062bb0062b0062b0062	(Ljava/lang/String;CC)Ljava/lang/String;
    //   323: iconst_0
    //   324: anewarray 55	java/lang/Class
    //   327: invokevirtual 59	java/lang/Class:getMethod	(Ljava/lang/String;[Ljava/lang/Class;)Ljava/lang/reflect/Method;
    //   330: astore 43
    //   332: iconst_0
    //   333: anewarray 61	java/lang/Object
    //   336: astore 44
    //   338: aload 43
    //   340: aconst_null
    //   341: aload 44
    //   343: invokevirtual 67	java/lang/reflect/Method:invoke	(Ljava/lang/Object;[Ljava/lang/Object;)Ljava/lang/Object;
    //   346: astore 46
    //   348: aload 46
    //   350: checkcast 69	java/lang/Integer
    //   353: invokevirtual 73	java/lang/Integer:intValue	()I
    //   356: putstatic 89	uuuuuu/ttstss:bn006E006En006En006En006E	I
    //   359: getstatic 75	uuuuuu/ttstss:b006Enn006E006En006En006E	I
    //   362: getstatic 77	uuuuuu/ttstss:b006E006E006En006En006En006E	I
    //   365: iadd
    //   366: getstatic 75	uuuuuu/ttstss:b006Enn006E006En006En006E	I
    //   369: imul
    //   370: getstatic 79	uuuuuu/ttstss:bnnn006E006En006En006E	I
    //   373: irem
    //   374: istore 47
    //   376: ldc 2
    //   378: ldc -52
    //   380: sipush 162
    //   383: sipush 254
    //   386: iconst_2
    //   387: invokestatic 87	xxxxxx/uxxxxx:bbbb0062b0062b0062b0062	(Ljava/lang/String;CCC)Ljava/lang/String;
    //   390: iconst_0
    //   391: anewarray 55	java/lang/Class
    //   394: invokevirtual 59	java/lang/Class:getMethod	(Ljava/lang/String;[Ljava/lang/Class;)Ljava/lang/reflect/Method;
    //   397: astore 48
    //   399: iconst_0
    //   400: anewarray 61	java/lang/Object
    //   403: astore 49
    //   405: aload 48
    //   407: aconst_null
    //   408: aload 49
    //   410: invokevirtual 67	java/lang/reflect/Method:invoke	(Ljava/lang/Object;[Ljava/lang/Object;)Ljava/lang/Object;
    //   413: astore 51
    //   415: iload 47
    //   417: aload 51
    //   419: checkcast 69	java/lang/Integer
    //   422: invokevirtual 73	java/lang/Integer:intValue	()I
    //   425: if_icmpeq +55 -> 480
    //   428: bipush 29
    //   430: putstatic 75	uuuuuu/ttstss:b006Enn006E006En006En006E	I
    //   433: ldc 2
    //   435: ldc -50
    //   437: sipush 186
    //   440: iconst_2
    //   441: invokestatic 53	xxxxxx/uxxxxx:bb00620062bb0062b0062b0062	(Ljava/lang/String;CC)Ljava/lang/String;
    //   444: iconst_0
    //   445: anewarray 55	java/lang/Class
    //   448: invokevirtual 59	java/lang/Class:getMethod	(Ljava/lang/String;[Ljava/lang/Class;)Ljava/lang/reflect/Method;
    //   451: astore 52
    //   453: iconst_0
    //   454: anewarray 61	java/lang/Object
    //   457: astore 53
    //   459: aload 52
    //   461: aconst_null
    //   462: aload 53
    //   464: invokevirtual 67	java/lang/reflect/Method:invoke	(Ljava/lang/Object;[Ljava/lang/Object;)Ljava/lang/Object;
    //   467: astore 55
    //   469: aload 55
    //   471: checkcast 69	java/lang/Integer
    //   474: invokevirtual 73	java/lang/Integer:intValue	()I
    //   477: putstatic 89	uuuuuu/ttstss:bn006E006En006En006En006E	I
    //   480: aload_0
    //   481: getfield 176	uuuuuu/ttstss:b006En006En006En006En006E	Lcom/db/pwcc/dbmobile/secure/preferences/SharedPreferencesHelper;
    //   484: astore 33
    //   486: ldc -78
    //   488: ldc -48
    //   490: bipush 73
    //   492: sipush 212
    //   495: iconst_2
    //   496: invokestatic 87	xxxxxx/uxxxxx:bbbb0062b0062b0062b0062	(Ljava/lang/String;CCC)Ljava/lang/String;
    //   499: iconst_0
    //   500: anewarray 55	java/lang/Class
    //   503: invokevirtual 59	java/lang/Class:getMethod	(Ljava/lang/String;[Ljava/lang/Class;)Ljava/lang/reflect/Method;
    //   506: astore 34
    //   508: iconst_0
    //   509: anewarray 61	java/lang/Object
    //   512: astore 35
    //   514: aload 34
    //   516: aload 33
    //   518: aload 35
    //   520: invokevirtual 67	java/lang/reflect/Method:invoke	(Ljava/lang/Object;[Ljava/lang/Object;)Ljava/lang/Object;
    //   523: astore 37
    //   525: aload 37
    //   527: checkcast 69	java/lang/Integer
    //   530: invokevirtual 73	java/lang/Integer:intValue	()I
    //   533: iconst_m1
    //   534: if_icmple +98 -> 632
    //   537: aload_0
    //   538: getfield 176	uuuuuu/ttstss:b006En006En006En006En006E	Lcom/db/pwcc/dbmobile/secure/preferences/SharedPreferencesHelper;
    //   541: astore 38
    //   543: ldc -78
    //   545: ldc -46
    //   547: sipush 129
    //   550: sipush 137
    //   553: iconst_3
    //   554: invokestatic 87	xxxxxx/uxxxxx:bbbb0062b0062b0062b0062	(Ljava/lang/String;CCC)Ljava/lang/String;
    //   557: iconst_0
    //   558: anewarray 55	java/lang/Class
    //   561: invokevirtual 59	java/lang/Class:getMethod	(Ljava/lang/String;[Ljava/lang/Class;)Ljava/lang/reflect/Method;
    //   564: astore 39
    //   566: iconst_0
    //   567: anewarray 61	java/lang/Object
    //   570: astore 40
    //   572: aload 39
    //   574: aload 38
    //   576: aload 40
    //   578: invokevirtual 67	java/lang/reflect/Method:invoke	(Ljava/lang/Object;[Ljava/lang/Object;)Ljava/lang/Object;
    //   581: astore 42
    //   583: aload 42
    //   585: checkcast 69	java/lang/Integer
    //   588: invokevirtual 73	java/lang/Integer:intValue	()I
    //   591: istore 17
    //   593: aload_0
    //   594: getfield 45	uuuuuu/ttstss:bnnnnn006E006E006En	Luuuuuu/ttssst$tsssst;
    //   597: checkcast 212	uuuuuu/stttss$ssttss
    //   600: iload 17
    //   602: invokeinterface 216 2 0
    //   607: return
    //   608: astore 4
    //   610: aload 4
    //   612: invokevirtual 105	java/lang/reflect/InvocationTargetException:getCause	()Ljava/lang/Throwable;
    //   615: athrow
    //   616: astore 41
    //   618: aload 41
    //   620: invokevirtual 105	java/lang/reflect/InvocationTargetException:getCause	()Ljava/lang/Throwable;
    //   623: athrow
    //   624: astore 24
    //   626: aload 24
    //   628: invokevirtual 105	java/lang/reflect/InvocationTargetException:getCause	()Ljava/lang/Throwable;
    //   631: athrow
    //   632: getstatic 75	uuuuuu/ttstss:b006Enn006E006En006En006E	I
    //   635: istore 15
    //   637: iload 15
    //   639: iload 15
    //   641: getstatic 77	uuuuuu/ttstss:b006E006E006En006En006En006E	I
    //   644: iadd
    //   645: imul
    //   646: getstatic 79	uuuuuu/ttstss:bnnn006E006En006En006E	I
    //   649: irem
    //   650: istore 16
    //   652: iconst_0
    //   653: istore 17
    //   655: iload 16
    //   657: tableswitch	default:+19->676, 0:+-64->593
    //   676: bipush 9
    //   678: putstatic 75	uuuuuu/ttstss:b006Enn006E006En006En006E	I
    //   681: ldc 2
    //   683: ldc -38
    //   685: bipush 124
    //   687: iconst_0
    //   688: invokestatic 53	xxxxxx/uxxxxx:bb00620062bb0062b0062b0062	(Ljava/lang/String;CC)Ljava/lang/String;
    //   691: iconst_0
    //   692: anewarray 55	java/lang/Class
    //   695: invokevirtual 59	java/lang/Class:getMethod	(Ljava/lang/String;[Ljava/lang/Class;)Ljava/lang/reflect/Method;
    //   698: astore 18
    //   700: iconst_0
    //   701: anewarray 61	java/lang/Object
    //   704: astore 19
    //   706: aload 18
    //   708: aconst_null
    //   709: aload 19
    //   711: invokevirtual 67	java/lang/reflect/Method:invoke	(Ljava/lang/Object;[Ljava/lang/Object;)Ljava/lang/Object;
    //   714: astore 21
    //   716: aload 21
    //   718: checkcast 69	java/lang/Integer
    //   721: invokevirtual 73	java/lang/Integer:intValue	()I
    //   724: putstatic 89	uuuuuu/ttstss:bn006E006En006En006En006E	I
    //   727: iconst_0
    //   728: istore 17
    //   730: goto -137 -> 593
    //   733: astore 20
    //   735: aload 20
    //   737: invokevirtual 105	java/lang/reflect/InvocationTargetException:getCause	()Ljava/lang/Throwable;
    //   740: athrow
    //   741: astore 29
    //   743: aload 29
    //   745: invokevirtual 105	java/lang/reflect/InvocationTargetException:getCause	()Ljava/lang/Throwable;
    //   748: athrow
    //   749: astore 13
    //   751: aload 13
    //   753: invokevirtual 105	java/lang/reflect/InvocationTargetException:getCause	()Ljava/lang/Throwable;
    //   756: athrow
    //   757: astore 36
    //   759: aload 36
    //   761: invokevirtual 105	java/lang/reflect/InvocationTargetException:getCause	()Ljava/lang/Throwable;
    //   764: athrow
    //   765: ldc 2
    //   767: ldc -36
    //   769: sipush 160
    //   772: iconst_2
    //   773: invokestatic 53	xxxxxx/uxxxxx:bb00620062bb0062b0062b0062	(Ljava/lang/String;CC)Ljava/lang/String;
    //   776: iconst_0
    //   777: anewarray 55	java/lang/Class
    //   780: invokevirtual 59	java/lang/Class:getMethod	(Ljava/lang/String;[Ljava/lang/Class;)Ljava/lang/reflect/Method;
    //   783: astore 6
    //   785: iconst_0
    //   786: anewarray 61	java/lang/Object
    //   789: astore 7
    //   791: aload 6
    //   793: aload_0
    //   794: aload 7
    //   796: invokevirtual 67	java/lang/reflect/Method:invoke	(Ljava/lang/Object;[Ljava/lang/Object;)Ljava/lang/Object;
    //   799: pop
    //   800: return
    //   801: astore 8
    //   803: aload 8
    //   805: invokevirtual 105	java/lang/reflect/InvocationTargetException:getCause	()Ljava/lang/Throwable;
    //   808: athrow
    //   809: astore 45
    //   811: aload 45
    //   813: invokevirtual 105	java/lang/reflect/InvocationTargetException:getCause	()Ljava/lang/Throwable;
    //   816: athrow
    //   817: astore 50
    //   819: aload 50
    //   821: invokevirtual 105	java/lang/reflect/InvocationTargetException:getCause	()Ljava/lang/Throwable;
    //   824: athrow
    //   825: astore 58
    //   827: aload 58
    //   829: invokevirtual 105	java/lang/reflect/InvocationTargetException:getCause	()Ljava/lang/Throwable;
    //   832: athrow
    //   833: astore 54
    //   835: aload 54
    //   837: invokevirtual 105	java/lang/reflect/InvocationTargetException:getCause	()Ljava/lang/Throwable;
    //   840: athrow
    // Local variable table:
    //   start	length	slot	name	signature
    //   0	841	0	this	ttstss
    //   4	26	1	localSharedPreferencesHelper1	SharedPreferencesHelper
    //   22	7	2	localMethod1	java.lang.reflect.Method
    //   27	4	3	arrayOfObject1	Object[]
    //   608	3	4	localInvocationTargetException1	java.lang.reflect.InvocationTargetException
    //   34	3	5	localObject1	Object
    //   783	9	6	localMethod2	java.lang.reflect.Method
    //   789	6	7	arrayOfObject2	Object[]
    //   801	3	8	localInvocationTargetException2	java.lang.reflect.InvocationTargetException
    //   51	30	10	localSharedPreferencesHelper2	SharedPreferencesHelper
    //   70	9	11	localMethod3	java.lang.reflect.Method
    //   76	7	12	arrayOfObject3	Object[]
    //   749	3	13	localInvocationTargetException3	java.lang.reflect.InvocationTargetException
    //   87	3	14	localObject2	Object
    //   635	11	15	i	int
    //   650	6	16	j	int
    //   591	138	17	k	int
    //   698	9	18	localMethod4	java.lang.reflect.Method
    //   704	6	19	arrayOfObject4	Object[]
    //   733	3	20	localInvocationTargetException4	java.lang.reflect.InvocationTargetException
    //   714	3	21	localObject3	Object
    //   125	9	22	localMethod5	java.lang.reflect.Method
    //   131	6	23	arrayOfObject5	Object[]
    //   624	3	24	localInvocationTargetException5	java.lang.reflect.InvocationTargetException
    //   141	3	25	localObject4	Object
    //   155	143	26	m	int
    //   175	9	27	localMethod6	java.lang.reflect.Method
    //   181	6	28	arrayOfObject6	Object[]
    //   741	3	29	localInvocationTargetException6	java.lang.reflect.InvocationTargetException
    //   191	3	30	localObject5	Object
    //   201	97	31	n	int
    //   206	11	32	i1	int
    //   484	33	33	localSharedPreferencesHelper3	SharedPreferencesHelper
    //   506	9	34	localMethod7	java.lang.reflect.Method
    //   512	7	35	arrayOfObject7	Object[]
    //   757	3	36	localInvocationTargetException7	java.lang.reflect.InvocationTargetException
    //   523	3	37	localObject6	Object
    //   541	34	38	localSharedPreferencesHelper4	SharedPreferencesHelper
    //   564	9	39	localMethod8	java.lang.reflect.Method
    //   570	7	40	arrayOfObject8	Object[]
    //   616	3	41	localInvocationTargetException8	java.lang.reflect.InvocationTargetException
    //   581	3	42	localObject7	Object
    //   330	9	43	localMethod9	java.lang.reflect.Method
    //   336	6	44	arrayOfObject9	Object[]
    //   809	3	45	localInvocationTargetException9	java.lang.reflect.InvocationTargetException
    //   346	3	46	localObject8	Object
    //   374	52	47	i2	int
    //   397	9	48	localMethod10	java.lang.reflect.Method
    //   403	6	49	arrayOfObject10	Object[]
    //   817	3	50	localInvocationTargetException10	java.lang.reflect.InvocationTargetException
    //   413	5	51	localObject9	Object
    //   451	9	52	localMethod11	java.lang.reflect.Method
    //   457	6	53	arrayOfObject11	Object[]
    //   833	3	54	localInvocationTargetException11	java.lang.reflect.InvocationTargetException
    //   467	3	55	localObject10	Object
    //   260	9	56	localMethod12	java.lang.reflect.Method
    //   266	6	57	arrayOfObject12	Object[]
    //   825	3	58	localInvocationTargetException12	java.lang.reflect.InvocationTargetException
    //   276	3	59	localObject11	Object
    // Exception table:
    //   from	to	target	type
    //   28	36	608	java/lang/reflect/InvocationTargetException
    //   572	583	616	java/lang/reflect/InvocationTargetException
    //   133	143	624	java/lang/reflect/InvocationTargetException
    //   706	716	733	java/lang/reflect/InvocationTargetException
    //   183	193	741	java/lang/reflect/InvocationTargetException
    //   78	89	749	java/lang/reflect/InvocationTargetException
    //   514	525	757	java/lang/reflect/InvocationTargetException
    //   791	800	801	java/lang/reflect/InvocationTargetException
    //   338	348	809	java/lang/reflect/InvocationTargetException
    //   405	415	817	java/lang/reflect/InvocationTargetException
    //   268	278	825	java/lang/reflect/InvocationTargetException
    //   459	469	833	java/lang/reflect/InvocationTargetException
  }
  
  /* Error */
  public void b006B006Bkkk006Bk006B006Bk(stttss.ssttss paramSsttss)
  {
    // Byte code:
    //   0: ldc 2
    //   2: ldc -32
    //   4: bipush 18
    //   6: sipush 238
    //   9: iconst_2
    //   10: invokestatic 87	xxxxxx/uxxxxx:bbbb0062b0062b0062b0062	(Ljava/lang/String;CCC)Ljava/lang/String;
    //   13: iconst_0
    //   14: anewarray 55	java/lang/Class
    //   17: invokevirtual 59	java/lang/Class:getMethod	(Ljava/lang/String;[Ljava/lang/Class;)Ljava/lang/reflect/Method;
    //   20: astore_2
    //   21: iconst_0
    //   22: anewarray 61	java/lang/Object
    //   25: astore_3
    //   26: aload_2
    //   27: aconst_null
    //   28: aload_3
    //   29: invokevirtual 67	java/lang/reflect/Method:invoke	(Ljava/lang/Object;[Ljava/lang/Object;)Ljava/lang/Object;
    //   32: astore 5
    //   34: aload 5
    //   36: checkcast 69	java/lang/Integer
    //   39: invokevirtual 73	java/lang/Integer:intValue	()I
    //   42: istore 6
    //   44: ldc 2
    //   46: ldc -30
    //   48: sipush 146
    //   51: iconst_1
    //   52: invokestatic 53	xxxxxx/uxxxxx:bb00620062bb0062b0062b0062	(Ljava/lang/String;CC)Ljava/lang/String;
    //   55: iconst_0
    //   56: anewarray 55	java/lang/Class
    //   59: invokevirtual 59	java/lang/Class:getMethod	(Ljava/lang/String;[Ljava/lang/Class;)Ljava/lang/reflect/Method;
    //   62: astore 7
    //   64: iconst_0
    //   65: anewarray 61	java/lang/Object
    //   68: astore 8
    //   70: aload 7
    //   72: aconst_null
    //   73: aload 8
    //   75: invokevirtual 67	java/lang/reflect/Method:invoke	(Ljava/lang/Object;[Ljava/lang/Object;)Ljava/lang/Object;
    //   78: astore 10
    //   80: iload 6
    //   82: aload 10
    //   84: checkcast 69	java/lang/Integer
    //   87: invokevirtual 73	java/lang/Integer:intValue	()I
    //   90: iadd
    //   91: istore 11
    //   93: ldc 2
    //   95: ldc -28
    //   97: bipush 59
    //   99: iconst_4
    //   100: invokestatic 53	xxxxxx/uxxxxx:bb00620062bb0062b0062b0062	(Ljava/lang/String;CC)Ljava/lang/String;
    //   103: iconst_0
    //   104: anewarray 55	java/lang/Class
    //   107: invokevirtual 59	java/lang/Class:getMethod	(Ljava/lang/String;[Ljava/lang/Class;)Ljava/lang/reflect/Method;
    //   110: astore 12
    //   112: iconst_0
    //   113: anewarray 61	java/lang/Object
    //   116: astore 13
    //   118: aload 12
    //   120: aconst_null
    //   121: aload 13
    //   123: invokevirtual 67	java/lang/reflect/Method:invoke	(Ljava/lang/Object;[Ljava/lang/Object;)Ljava/lang/Object;
    //   126: astore 15
    //   128: iload 11
    //   130: aload 15
    //   132: checkcast 69	java/lang/Integer
    //   135: invokevirtual 73	java/lang/Integer:intValue	()I
    //   138: imul
    //   139: getstatic 79	uuuuuu/ttstss:bnnn006E006En006En006E	I
    //   142: irem
    //   143: getstatic 89	uuuuuu/ttstss:bn006E006En006En006En006E	I
    //   146: if_icmpeq +55 -> 201
    //   149: ldc 2
    //   151: ldc -54
    //   153: sipush 164
    //   156: iconst_3
    //   157: invokestatic 53	xxxxxx/uxxxxx:bb00620062bb0062b0062b0062	(Ljava/lang/String;CC)Ljava/lang/String;
    //   160: iconst_0
    //   161: anewarray 55	java/lang/Class
    //   164: invokevirtual 59	java/lang/Class:getMethod	(Ljava/lang/String;[Ljava/lang/Class;)Ljava/lang/reflect/Method;
    //   167: astore 38
    //   169: iconst_0
    //   170: anewarray 61	java/lang/Object
    //   173: astore 39
    //   175: aload 38
    //   177: aconst_null
    //   178: aload 39
    //   180: invokevirtual 67	java/lang/reflect/Method:invoke	(Ljava/lang/Object;[Ljava/lang/Object;)Ljava/lang/Object;
    //   183: astore 41
    //   185: aload 41
    //   187: checkcast 69	java/lang/Integer
    //   190: invokevirtual 73	java/lang/Integer:intValue	()I
    //   193: putstatic 75	uuuuuu/ttstss:b006Enn006E006En006En006E	I
    //   196: bipush 17
    //   198: putstatic 89	uuuuuu/ttstss:bn006E006En006En006En006E	I
    //   201: getstatic 75	uuuuuu/ttstss:b006Enn006E006En006En006E	I
    //   204: istore 16
    //   206: iload 16
    //   208: iload 16
    //   210: getstatic 77	uuuuuu/ttstss:b006E006E006En006En006En006E	I
    //   213: iadd
    //   214: imul
    //   215: getstatic 79	uuuuuu/ttstss:bnnn006E006En006En006E	I
    //   218: irem
    //   219: tableswitch	default:+17->236, 0:+264->483
    //   236: getstatic 75	uuuuuu/ttstss:b006Enn006E006En006En006E	I
    //   239: getstatic 77	uuuuuu/ttstss:b006E006E006En006En006En006E	I
    //   242: iadd
    //   243: getstatic 75	uuuuuu/ttstss:b006Enn006E006En006En006E	I
    //   246: imul
    //   247: istore 21
    //   249: ldc 2
    //   251: ldc -26
    //   253: sipush 178
    //   256: bipush 109
    //   258: iconst_3
    //   259: invokestatic 87	xxxxxx/uxxxxx:bbbb0062b0062b0062b0062	(Ljava/lang/String;CCC)Ljava/lang/String;
    //   262: iconst_0
    //   263: anewarray 55	java/lang/Class
    //   266: invokevirtual 59	java/lang/Class:getMethod	(Ljava/lang/String;[Ljava/lang/Class;)Ljava/lang/reflect/Method;
    //   269: astore 22
    //   271: iconst_0
    //   272: anewarray 61	java/lang/Object
    //   275: astore 23
    //   277: aload 22
    //   279: aconst_null
    //   280: aload 23
    //   282: invokevirtual 67	java/lang/reflect/Method:invoke	(Ljava/lang/Object;[Ljava/lang/Object;)Ljava/lang/Object;
    //   285: astore 25
    //   287: iload 21
    //   289: aload 25
    //   291: checkcast 69	java/lang/Integer
    //   294: invokevirtual 73	java/lang/Integer:intValue	()I
    //   297: irem
    //   298: getstatic 89	uuuuuu/ttstss:bn006E006En006En006En006E	I
    //   301: if_icmpeq +130 -> 431
    //   304: getstatic 75	uuuuuu/ttstss:b006Enn006E006En006En006E	I
    //   307: getstatic 77	uuuuuu/ttstss:b006E006E006En006En006En006E	I
    //   310: iadd
    //   311: getstatic 75	uuuuuu/ttstss:b006Enn006E006En006En006E	I
    //   314: imul
    //   315: getstatic 79	uuuuuu/ttstss:bnnn006E006En006En006E	I
    //   318: irem
    //   319: getstatic 89	uuuuuu/ttstss:bn006E006En006En006En006E	I
    //   322: if_icmpeq +55 -> 377
    //   325: bipush 60
    //   327: putstatic 75	uuuuuu/ttstss:b006Enn006E006En006En006E	I
    //   330: ldc 2
    //   332: ldc -24
    //   334: sipush 237
    //   337: iconst_1
    //   338: invokestatic 53	xxxxxx/uxxxxx:bb00620062bb0062b0062b0062	(Ljava/lang/String;CC)Ljava/lang/String;
    //   341: iconst_0
    //   342: anewarray 55	java/lang/Class
    //   345: invokevirtual 59	java/lang/Class:getMethod	(Ljava/lang/String;[Ljava/lang/Class;)Ljava/lang/reflect/Method;
    //   348: astore 34
    //   350: iconst_0
    //   351: anewarray 61	java/lang/Object
    //   354: astore 35
    //   356: aload 34
    //   358: aconst_null
    //   359: aload 35
    //   361: invokevirtual 67	java/lang/reflect/Method:invoke	(Ljava/lang/Object;[Ljava/lang/Object;)Ljava/lang/Object;
    //   364: astore 37
    //   366: aload 37
    //   368: checkcast 69	java/lang/Integer
    //   371: invokevirtual 73	java/lang/Integer:intValue	()I
    //   374: putstatic 89	uuuuuu/ttstss:bn006E006En006En006En006E	I
    //   377: ldc 2
    //   379: ldc -22
    //   381: sipush 153
    //   384: bipush 47
    //   386: iconst_3
    //   387: invokestatic 87	xxxxxx/uxxxxx:bbbb0062b0062b0062b0062	(Ljava/lang/String;CCC)Ljava/lang/String;
    //   390: iconst_0
    //   391: anewarray 55	java/lang/Class
    //   394: invokevirtual 59	java/lang/Class:getMethod	(Ljava/lang/String;[Ljava/lang/Class;)Ljava/lang/reflect/Method;
    //   397: astore 30
    //   399: iconst_0
    //   400: anewarray 61	java/lang/Object
    //   403: astore 31
    //   405: aload 30
    //   407: aconst_null
    //   408: aload 31
    //   410: invokevirtual 67	java/lang/reflect/Method:invoke	(Ljava/lang/Object;[Ljava/lang/Object;)Ljava/lang/Object;
    //   413: astore 33
    //   415: aload 33
    //   417: checkcast 69	java/lang/Integer
    //   420: invokevirtual 73	java/lang/Integer:intValue	()I
    //   423: putstatic 75	uuuuuu/ttstss:b006Enn006E006En006En006E	I
    //   426: bipush 86
    //   428: putstatic 89	uuuuuu/ttstss:bn006E006En006En006En006E	I
    //   431: bipush 24
    //   433: putstatic 75	uuuuuu/ttstss:b006Enn006E006En006En006E	I
    //   436: ldc 2
    //   438: ldc -20
    //   440: sipush 201
    //   443: iconst_0
    //   444: invokestatic 53	xxxxxx/uxxxxx:bb00620062bb0062b0062b0062	(Ljava/lang/String;CC)Ljava/lang/String;
    //   447: iconst_0
    //   448: anewarray 55	java/lang/Class
    //   451: invokevirtual 59	java/lang/Class:getMethod	(Ljava/lang/String;[Ljava/lang/Class;)Ljava/lang/reflect/Method;
    //   454: astore 26
    //   456: iconst_0
    //   457: anewarray 61	java/lang/Object
    //   460: astore 27
    //   462: aload 26
    //   464: aconst_null
    //   465: aload 27
    //   467: invokevirtual 67	java/lang/reflect/Method:invoke	(Ljava/lang/Object;[Ljava/lang/Object;)Ljava/lang/Object;
    //   470: astore 29
    //   472: aload 29
    //   474: checkcast 69	java/lang/Integer
    //   477: invokevirtual 73	java/lang/Integer:intValue	()I
    //   480: putstatic 89	uuuuuu/ttstss:bn006E006En006En006En006E	I
    //   483: aload_0
    //   484: aload_1
    //   485: invokespecial 240	uuuuuu/qppppp:ba0061a0061a0061a0061aa	(Luuuuuu/ttssst$tsssst;)V
    //   488: ldc 2
    //   490: ldc -14
    //   492: bipush 56
    //   494: iconst_4
    //   495: invokestatic 53	xxxxxx/uxxxxx:bb00620062bb0062b0062b0062	(Ljava/lang/String;CC)Ljava/lang/String;
    //   498: iconst_0
    //   499: anewarray 55	java/lang/Class
    //   502: invokevirtual 59	java/lang/Class:getMethod	(Ljava/lang/String;[Ljava/lang/Class;)Ljava/lang/reflect/Method;
    //   505: astore 17
    //   507: iconst_0
    //   508: anewarray 61	java/lang/Object
    //   511: astore 18
    //   513: aload 17
    //   515: aload_0
    //   516: aload 18
    //   518: invokevirtual 67	java/lang/reflect/Method:invoke	(Ljava/lang/Object;[Ljava/lang/Object;)Ljava/lang/Object;
    //   521: pop
    //   522: return
    //   523: astore 19
    //   525: aload 19
    //   527: invokevirtual 105	java/lang/reflect/InvocationTargetException:getCause	()Ljava/lang/Throwable;
    //   530: athrow
    //   531: astore 9
    //   533: aload 9
    //   535: invokevirtual 105	java/lang/reflect/InvocationTargetException:getCause	()Ljava/lang/Throwable;
    //   538: athrow
    //   539: astore 14
    //   541: aload 14
    //   543: invokevirtual 105	java/lang/reflect/InvocationTargetException:getCause	()Ljava/lang/Throwable;
    //   546: athrow
    //   547: astore 24
    //   549: aload 24
    //   551: invokevirtual 105	java/lang/reflect/InvocationTargetException:getCause	()Ljava/lang/Throwable;
    //   554: athrow
    //   555: astore 32
    //   557: aload 32
    //   559: invokevirtual 105	java/lang/reflect/InvocationTargetException:getCause	()Ljava/lang/Throwable;
    //   562: athrow
    //   563: astore 40
    //   565: aload 40
    //   567: invokevirtual 105	java/lang/reflect/InvocationTargetException:getCause	()Ljava/lang/Throwable;
    //   570: athrow
    //   571: astore 28
    //   573: aload 28
    //   575: invokevirtual 105	java/lang/reflect/InvocationTargetException:getCause	()Ljava/lang/Throwable;
    //   578: athrow
    //   579: astore 4
    //   581: aload 4
    //   583: invokevirtual 105	java/lang/reflect/InvocationTargetException:getCause	()Ljava/lang/Throwable;
    //   586: athrow
    //   587: astore 36
    //   589: aload 36
    //   591: invokevirtual 105	java/lang/reflect/InvocationTargetException:getCause	()Ljava/lang/Throwable;
    //   594: athrow
    // Local variable table:
    //   start	length	slot	name	signature
    //   0	595	0	this	ttstss
    //   0	595	1	paramSsttss	stttss.ssttss
    //   20	7	2	localMethod1	java.lang.reflect.Method
    //   25	4	3	arrayOfObject1	Object[]
    //   579	3	4	localInvocationTargetException1	java.lang.reflect.InvocationTargetException
    //   32	3	5	localObject1	Object
    //   42	49	6	i	int
    //   62	9	7	localMethod2	java.lang.reflect.Method
    //   68	6	8	arrayOfObject2	Object[]
    //   531	3	9	localInvocationTargetException2	java.lang.reflect.InvocationTargetException
    //   78	5	10	localObject2	Object
    //   91	48	11	j	int
    //   110	9	12	localMethod3	java.lang.reflect.Method
    //   116	6	13	arrayOfObject3	Object[]
    //   539	3	14	localInvocationTargetException3	java.lang.reflect.InvocationTargetException
    //   126	5	15	localObject3	Object
    //   204	11	16	k	int
    //   505	9	17	localMethod4	java.lang.reflect.Method
    //   511	6	18	arrayOfObject4	Object[]
    //   523	3	19	localInvocationTargetException4	java.lang.reflect.InvocationTargetException
    //   247	51	21	m	int
    //   269	9	22	localMethod5	java.lang.reflect.Method
    //   275	6	23	arrayOfObject5	Object[]
    //   547	3	24	localInvocationTargetException5	java.lang.reflect.InvocationTargetException
    //   285	5	25	localObject4	Object
    //   454	9	26	localMethod6	java.lang.reflect.Method
    //   460	6	27	arrayOfObject6	Object[]
    //   571	3	28	localInvocationTargetException6	java.lang.reflect.InvocationTargetException
    //   470	3	29	localObject5	Object
    //   397	9	30	localMethod7	java.lang.reflect.Method
    //   403	6	31	arrayOfObject7	Object[]
    //   555	3	32	localInvocationTargetException7	java.lang.reflect.InvocationTargetException
    //   413	3	33	localObject6	Object
    //   348	9	34	localMethod8	java.lang.reflect.Method
    //   354	6	35	arrayOfObject8	Object[]
    //   587	3	36	localInvocationTargetException8	java.lang.reflect.InvocationTargetException
    //   364	3	37	localObject7	Object
    //   167	9	38	localMethod9	java.lang.reflect.Method
    //   173	6	39	arrayOfObject9	Object[]
    //   563	3	40	localInvocationTargetException9	java.lang.reflect.InvocationTargetException
    //   183	3	41	localObject8	Object
    // Exception table:
    //   from	to	target	type
    //   513	522	523	java/lang/reflect/InvocationTargetException
    //   70	80	531	java/lang/reflect/InvocationTargetException
    //   118	128	539	java/lang/reflect/InvocationTargetException
    //   277	287	547	java/lang/reflect/InvocationTargetException
    //   405	415	555	java/lang/reflect/InvocationTargetException
    //   175	185	563	java/lang/reflect/InvocationTargetException
    //   462	472	571	java/lang/reflect/InvocationTargetException
    //   26	34	579	java/lang/reflect/InvocationTargetException
    //   356	366	587	java/lang/reflect/InvocationTargetException
  }
  
  /* Error */
  public void bk006B006Bkk006Bk006B006Bk()
  {
    // Byte code:
    //   0: aload_0
    //   1: getfield 259	uuuuuu/ttstss:bnn006En006En006En006E	Landroid/content/Context;
    //   4: invokevirtual 265	android/content/Context:getResources	()Landroid/content/res/Resources;
    //   7: astore_1
    //   8: getstatic 75	uuuuuu/ttstss:b006Enn006E006En006En006E	I
    //   11: getstatic 77	uuuuuu/ttstss:b006E006E006En006En006En006E	I
    //   14: iadd
    //   15: getstatic 75	uuuuuu/ttstss:b006Enn006E006En006En006E	I
    //   18: imul
    //   19: getstatic 79	uuuuuu/ttstss:bnnn006E006En006En006E	I
    //   22: irem
    //   23: getstatic 89	uuuuuu/ttstss:bn006E006En006En006En006E	I
    //   26: if_icmpeq +99 -> 125
    //   29: ldc 2
    //   31: ldc_w 267
    //   34: sipush 145
    //   37: iconst_0
    //   38: invokestatic 53	xxxxxx/uxxxxx:bb00620062bb0062b0062b0062	(Ljava/lang/String;CC)Ljava/lang/String;
    //   41: iconst_0
    //   42: anewarray 55	java/lang/Class
    //   45: invokevirtual 59	java/lang/Class:getMethod	(Ljava/lang/String;[Ljava/lang/Class;)Ljava/lang/reflect/Method;
    //   48: astore 29
    //   50: iconst_0
    //   51: anewarray 61	java/lang/Object
    //   54: astore 30
    //   56: aload 29
    //   58: aconst_null
    //   59: aload 30
    //   61: invokevirtual 67	java/lang/reflect/Method:invoke	(Ljava/lang/Object;[Ljava/lang/Object;)Ljava/lang/Object;
    //   64: astore 32
    //   66: aload 32
    //   68: checkcast 69	java/lang/Integer
    //   71: invokevirtual 73	java/lang/Integer:intValue	()I
    //   74: putstatic 75	uuuuuu/ttstss:b006Enn006E006En006En006E	I
    //   77: ldc 2
    //   79: ldc_w 269
    //   82: sipush 201
    //   85: iconst_5
    //   86: invokestatic 53	xxxxxx/uxxxxx:bb00620062bb0062b0062b0062	(Ljava/lang/String;CC)Ljava/lang/String;
    //   89: iconst_0
    //   90: anewarray 55	java/lang/Class
    //   93: invokevirtual 59	java/lang/Class:getMethod	(Ljava/lang/String;[Ljava/lang/Class;)Ljava/lang/reflect/Method;
    //   96: astore 33
    //   98: iconst_0
    //   99: anewarray 61	java/lang/Object
    //   102: astore 34
    //   104: aload 33
    //   106: aconst_null
    //   107: aload 34
    //   109: invokevirtual 67	java/lang/reflect/Method:invoke	(Ljava/lang/Object;[Ljava/lang/Object;)Ljava/lang/Object;
    //   112: astore 36
    //   114: aload 36
    //   116: checkcast 69	java/lang/Integer
    //   119: invokevirtual 73	java/lang/Integer:intValue	()I
    //   122: putstatic 89	uuuuuu/ttstss:bn006E006En006En006En006E	I
    //   125: aload_1
    //   126: getstatic 274	com/db/pwcc/dbmobile/foundation/R$dimen:background_thumbnail_image_size	I
    //   129: invokevirtual 280	android/content/res/Resources:getDimension	(I)F
    //   132: f2i
    //   133: istore_2
    //   134: aload_0
    //   135: getfield 176	uuuuuu/ttstss:b006En006En006En006En006E	Lcom/db/pwcc/dbmobile/secure/preferences/SharedPreferencesHelper;
    //   138: astore_3
    //   139: ldc -78
    //   141: ldc_w 282
    //   144: sipush 145
    //   147: bipush 25
    //   149: iconst_1
    //   150: invokestatic 87	xxxxxx/uxxxxx:bbbb0062b0062b0062b0062	(Ljava/lang/String;CCC)Ljava/lang/String;
    //   153: iconst_0
    //   154: anewarray 55	java/lang/Class
    //   157: invokevirtual 59	java/lang/Class:getMethod	(Ljava/lang/String;[Ljava/lang/Class;)Ljava/lang/reflect/Method;
    //   160: astore 4
    //   162: iconst_0
    //   163: anewarray 61	java/lang/Object
    //   166: astore 5
    //   168: aload 4
    //   170: aload_3
    //   171: aload 5
    //   173: invokevirtual 67	java/lang/reflect/Method:invoke	(Ljava/lang/Object;[Ljava/lang/Object;)Ljava/lang/Object;
    //   176: astore 7
    //   178: aload 7
    //   180: checkcast 182	java/lang/String
    //   183: invokestatic 288	android/graphics/BitmapFactory:decodeFile	(Ljava/lang/String;)Landroid/graphics/Bitmap;
    //   186: astore 8
    //   188: aload 8
    //   190: iload_2
    //   191: iload_2
    //   192: invokestatic 294	android/media/ThumbnailUtils:extractThumbnail	(Landroid/graphics/Bitmap;II)Landroid/graphics/Bitmap;
    //   195: astore 9
    //   197: ldc 2
    //   199: ldc_w 296
    //   202: sipush 186
    //   205: bipush 28
    //   207: iconst_2
    //   208: invokestatic 87	xxxxxx/uxxxxx:bbbb0062b0062b0062b0062	(Ljava/lang/String;CCC)Ljava/lang/String;
    //   211: iconst_0
    //   212: anewarray 55	java/lang/Class
    //   215: invokevirtual 59	java/lang/Class:getMethod	(Ljava/lang/String;[Ljava/lang/Class;)Ljava/lang/reflect/Method;
    //   218: astore 10
    //   220: iconst_0
    //   221: anewarray 61	java/lang/Object
    //   224: astore 11
    //   226: aload 10
    //   228: aconst_null
    //   229: aload 11
    //   231: invokevirtual 67	java/lang/reflect/Method:invoke	(Ljava/lang/Object;[Ljava/lang/Object;)Ljava/lang/Object;
    //   234: astore 13
    //   236: aload 13
    //   238: checkcast 69	java/lang/Integer
    //   241: invokevirtual 73	java/lang/Integer:intValue	()I
    //   244: getstatic 77	uuuuuu/ttstss:b006E006E006En006En006En006E	I
    //   247: iadd
    //   248: istore 14
    //   250: ldc 2
    //   252: ldc_w 298
    //   255: sipush 254
    //   258: iconst_0
    //   259: invokestatic 53	xxxxxx/uxxxxx:bb00620062bb0062b0062b0062	(Ljava/lang/String;CC)Ljava/lang/String;
    //   262: iconst_0
    //   263: anewarray 55	java/lang/Class
    //   266: invokevirtual 59	java/lang/Class:getMethod	(Ljava/lang/String;[Ljava/lang/Class;)Ljava/lang/reflect/Method;
    //   269: astore 15
    //   271: iconst_0
    //   272: anewarray 61	java/lang/Object
    //   275: astore 16
    //   277: aload 15
    //   279: aconst_null
    //   280: aload 16
    //   282: invokevirtual 67	java/lang/reflect/Method:invoke	(Ljava/lang/Object;[Ljava/lang/Object;)Ljava/lang/Object;
    //   285: astore 18
    //   287: iload 14
    //   289: aload 18
    //   291: checkcast 69	java/lang/Integer
    //   294: invokevirtual 73	java/lang/Integer:intValue	()I
    //   297: imul
    //   298: getstatic 79	uuuuuu/ttstss:bnnn006E006En006En006E	I
    //   301: irem
    //   302: getstatic 89	uuuuuu/ttstss:bn006E006En006En006En006E	I
    //   305: if_icmpeq +162 -> 467
    //   308: getstatic 75	uuuuuu/ttstss:b006Enn006E006En006En006E	I
    //   311: getstatic 77	uuuuuu/ttstss:b006E006E006En006En006En006E	I
    //   314: iadd
    //   315: getstatic 75	uuuuuu/ttstss:b006Enn006E006En006En006E	I
    //   318: imul
    //   319: getstatic 79	uuuuuu/ttstss:bnnn006E006En006En006E	I
    //   322: irem
    //   323: getstatic 89	uuuuuu/ttstss:bn006E006En006En006En006E	I
    //   326: if_icmpeq +131 -> 457
    //   329: ldc 2
    //   331: ldc_w 300
    //   334: bipush 113
    //   336: iconst_2
    //   337: invokestatic 53	xxxxxx/uxxxxx:bb00620062bb0062b0062b0062	(Ljava/lang/String;CC)Ljava/lang/String;
    //   340: iconst_0
    //   341: anewarray 55	java/lang/Class
    //   344: invokevirtual 59	java/lang/Class:getMethod	(Ljava/lang/String;[Ljava/lang/Class;)Ljava/lang/reflect/Method;
    //   347: astore 20
    //   349: iconst_0
    //   350: anewarray 61	java/lang/Object
    //   353: astore 21
    //   355: aload 20
    //   357: aconst_null
    //   358: aload 21
    //   360: invokevirtual 67	java/lang/reflect/Method:invoke	(Ljava/lang/Object;[Ljava/lang/Object;)Ljava/lang/Object;
    //   363: astore 23
    //   365: aload 23
    //   367: checkcast 69	java/lang/Integer
    //   370: invokevirtual 73	java/lang/Integer:intValue	()I
    //   373: getstatic 77	uuuuuu/ttstss:b006E006E006En006En006En006E	I
    //   376: iadd
    //   377: istore 24
    //   379: ldc 2
    //   381: ldc_w 302
    //   384: sipush 144
    //   387: iconst_5
    //   388: invokestatic 53	xxxxxx/uxxxxx:bb00620062bb0062b0062b0062	(Ljava/lang/String;CC)Ljava/lang/String;
    //   391: iconst_0
    //   392: anewarray 55	java/lang/Class
    //   395: invokevirtual 59	java/lang/Class:getMethod	(Ljava/lang/String;[Ljava/lang/Class;)Ljava/lang/reflect/Method;
    //   398: astore 25
    //   400: iconst_0
    //   401: anewarray 61	java/lang/Object
    //   404: astore 26
    //   406: aload 25
    //   408: aconst_null
    //   409: aload 26
    //   411: invokevirtual 67	java/lang/reflect/Method:invoke	(Ljava/lang/Object;[Ljava/lang/Object;)Ljava/lang/Object;
    //   414: astore 28
    //   416: iload 24
    //   418: aload 28
    //   420: checkcast 69	java/lang/Integer
    //   423: invokevirtual 73	java/lang/Integer:intValue	()I
    //   426: imul
    //   427: getstatic 79	uuuuuu/ttstss:bnnn006E006En006En006E	I
    //   430: irem
    //   431: getstatic 89	uuuuuu/ttstss:bn006E006En006En006En006E	I
    //   434: if_icmpeq +13 -> 447
    //   437: bipush 19
    //   439: putstatic 75	uuuuuu/ttstss:b006Enn006E006En006En006E	I
    //   442: bipush 93
    //   444: putstatic 89	uuuuuu/ttstss:bn006E006En006En006En006E	I
    //   447: bipush 61
    //   449: putstatic 75	uuuuuu/ttstss:b006Enn006E006En006En006E	I
    //   452: bipush 88
    //   454: putstatic 89	uuuuuu/ttstss:bn006E006En006En006En006E	I
    //   457: bipush 34
    //   459: putstatic 75	uuuuuu/ttstss:b006Enn006E006En006En006E	I
    //   462: bipush 67
    //   464: putstatic 89	uuuuuu/ttstss:bn006E006En006En006En006E	I
    //   467: new 304	android/graphics/drawable/BitmapDrawable
    //   470: dup
    //   471: aload_0
    //   472: getfield 259	uuuuuu/ttstss:bnn006En006En006En006E	Landroid/content/Context;
    //   475: invokevirtual 265	android/content/Context:getResources	()Landroid/content/res/Resources;
    //   478: aload 9
    //   480: invokespecial 307	android/graphics/drawable/BitmapDrawable:<init>	(Landroid/content/res/Resources;Landroid/graphics/Bitmap;)V
    //   483: astore 19
    //   485: aload 8
    //   487: ifnull +8 -> 495
    //   490: aload 8
    //   492: invokevirtual 312	android/graphics/Bitmap:recycle	()V
    //   495: aload_0
    //   496: getfield 45	uuuuuu/ttstss:bnnnnn006E006E006En	Luuuuuu/ttssst$tsssst;
    //   499: checkcast 212	uuuuuu/stttss$ssttss
    //   502: aload 19
    //   504: invokeinterface 316 2 0
    //   509: return
    //   510: astore 17
    //   512: aload 17
    //   514: invokevirtual 105	java/lang/reflect/InvocationTargetException:getCause	()Ljava/lang/Throwable;
    //   517: athrow
    //   518: astore 12
    //   520: aload 12
    //   522: invokevirtual 105	java/lang/reflect/InvocationTargetException:getCause	()Ljava/lang/Throwable;
    //   525: athrow
    //   526: astore 6
    //   528: aload 6
    //   530: invokevirtual 105	java/lang/reflect/InvocationTargetException:getCause	()Ljava/lang/Throwable;
    //   533: athrow
    //   534: astore 22
    //   536: aload 22
    //   538: invokevirtual 105	java/lang/reflect/InvocationTargetException:getCause	()Ljava/lang/Throwable;
    //   541: athrow
    //   542: astore 27
    //   544: aload 27
    //   546: invokevirtual 105	java/lang/reflect/InvocationTargetException:getCause	()Ljava/lang/Throwable;
    //   549: athrow
    //   550: astore 31
    //   552: aload 31
    //   554: invokevirtual 105	java/lang/reflect/InvocationTargetException:getCause	()Ljava/lang/Throwable;
    //   557: athrow
    //   558: astore 35
    //   560: aload 35
    //   562: invokevirtual 105	java/lang/reflect/InvocationTargetException:getCause	()Ljava/lang/Throwable;
    //   565: athrow
    // Local variable table:
    //   start	length	slot	name	signature
    //   0	566	0	this	ttstss
    //   7	119	1	localResources	android.content.res.Resources
    //   133	59	2	i	int
    //   138	33	3	localSharedPreferencesHelper	SharedPreferencesHelper
    //   160	9	4	localMethod1	java.lang.reflect.Method
    //   166	6	5	arrayOfObject1	Object[]
    //   526	3	6	localInvocationTargetException1	java.lang.reflect.InvocationTargetException
    //   176	3	7	localObject1	Object
    //   186	305	8	localBitmap1	android.graphics.Bitmap
    //   195	284	9	localBitmap2	android.graphics.Bitmap
    //   218	9	10	localMethod2	java.lang.reflect.Method
    //   224	6	11	arrayOfObject2	Object[]
    //   518	3	12	localInvocationTargetException2	java.lang.reflect.InvocationTargetException
    //   234	3	13	localObject2	Object
    //   248	50	14	j	int
    //   269	9	15	localMethod3	java.lang.reflect.Method
    //   275	6	16	arrayOfObject3	Object[]
    //   510	3	17	localInvocationTargetException3	java.lang.reflect.InvocationTargetException
    //   285	5	18	localObject3	Object
    //   483	20	19	localBitmapDrawable	android.graphics.drawable.BitmapDrawable
    //   347	9	20	localMethod4	java.lang.reflect.Method
    //   353	6	21	arrayOfObject4	Object[]
    //   534	3	22	localInvocationTargetException4	java.lang.reflect.InvocationTargetException
    //   363	3	23	localObject4	Object
    //   377	50	24	k	int
    //   398	9	25	localMethod5	java.lang.reflect.Method
    //   404	6	26	arrayOfObject5	Object[]
    //   542	3	27	localInvocationTargetException5	java.lang.reflect.InvocationTargetException
    //   414	5	28	localObject5	Object
    //   48	9	29	localMethod6	java.lang.reflect.Method
    //   54	6	30	arrayOfObject6	Object[]
    //   550	3	31	localInvocationTargetException6	java.lang.reflect.InvocationTargetException
    //   64	3	32	localObject6	Object
    //   96	9	33	localMethod7	java.lang.reflect.Method
    //   102	6	34	arrayOfObject7	Object[]
    //   558	3	35	localInvocationTargetException7	java.lang.reflect.InvocationTargetException
    //   112	3	36	localObject7	Object
    // Exception table:
    //   from	to	target	type
    //   277	287	510	java/lang/reflect/InvocationTargetException
    //   226	236	518	java/lang/reflect/InvocationTargetException
    //   168	178	526	java/lang/reflect/InvocationTargetException
    //   355	365	534	java/lang/reflect/InvocationTargetException
    //   406	416	542	java/lang/reflect/InvocationTargetException
    //   56	66	550	java/lang/reflect/InvocationTargetException
    //   104	114	558	java/lang/reflect/InvocationTargetException
  }
}
