package uuuuuu;

import android.content.Context;
import com.db.pwcc.dbmobile.ibanbic.items.AccountItem;
import com.db.pwcc.dbmobile.model.banking.FinancialOverviewData;
import com.db.pwcc.dbmobile.secure.preferences.SharedPreferencesHelper;
import java.util.ArrayList;
import java.util.List;
import javax.inject.Inject;

public class wwwnww
  extends ssssst<wnwnww.nwwnww>
  implements vpvpvp.pvvpvp, vvpvvp.ppvvvp
{
  public static int b006300630063ccc006300630063 = 17;
  public static int b0063cc0063cc006300630063 = 2;
  public static int bc0063c0063cc006300630063 = 0;
  public static int bccc0063cc006300630063 = 1;
  public fmfmfm b00630063cccc006300630063 = new fmfmfm();
  public mffffm b0063c0063ccc006300630063 = new mffffm();
  public List<AccountItem> b0063ccccc006300630063;
  @Inject
  public SharedPreferencesHelper bc00630063ccc006300630063;
  @Inject
  public Context bc0063cccc006300630063;
  public vvdddd bcc0063ccc006300630063 = new vvdddd();
  
  public wwwnww()
  {
    wwnwww.b00710071q00710071qq00710071q().bp00700070ppppppp(this);
    this.b0063ccccc006300630063 = new ArrayList();
  }
  
  public static int b00710071q0071qqq00710071q()
  {
    return 58;
  }
  
  public static int b0071q00710071qqq00710071q()
  {
    return 1;
  }
  
  /* Error */
  private AccountItem b0071qq0071qqq00710071q(String paramString, com.db.pwcc.dbmobile.ibanbic.items.AccountItem.nwwwww paramNwwwww)
  {
    // Byte code:
    //   0: new 128	com/db/pwcc/dbmobile/ibanbic/items/AccountItem
    //   3: dup
    //   4: invokespecial 129	com/db/pwcc/dbmobile/ibanbic/items/AccountItem:<init>	()V
    //   7: astore_3
    //   8: aload_3
    //   9: aload_1
    //   10: invokevirtual 133	com/db/pwcc/dbmobile/ibanbic/items/AccountItem:setHeaderLabel	(Ljava/lang/String;)V
    //   13: getstatic 78	uuuuuu/wwwnww:b006300630063ccc006300630063	I
    //   16: getstatic 80	uuuuuu/wwwnww:bccc0063cc006300630063	I
    //   19: iadd
    //   20: getstatic 78	uuuuuu/wwwnww:b006300630063ccc006300630063	I
    //   23: imul
    //   24: getstatic 82	uuuuuu/wwwnww:b0063cc0063cc006300630063	I
    //   27: irem
    //   28: istore 4
    //   30: ldc 2
    //   32: ldc -121
    //   34: sipush 153
    //   37: iconst_0
    //   38: invokestatic 118	xxxxxx/uxxxxx:bb00620062bb0062b0062b0062	(Ljava/lang/String;CC)Ljava/lang/String;
    //   41: iconst_0
    //   42: anewarray 94	java/lang/Class
    //   45: invokevirtual 98	java/lang/Class:getMethod	(Ljava/lang/String;[Ljava/lang/Class;)Ljava/lang/reflect/Method;
    //   48: astore 5
    //   50: iconst_0
    //   51: anewarray 100	java/lang/Object
    //   54: astore 6
    //   56: aload 5
    //   58: aconst_null
    //   59: aload 6
    //   61: invokevirtual 106	java/lang/reflect/Method:invoke	(Ljava/lang/Object;[Ljava/lang/Object;)Ljava/lang/Object;
    //   64: astore 8
    //   66: iload 4
    //   68: aload 8
    //   70: checkcast 108	java/lang/Integer
    //   73: invokevirtual 112	java/lang/Integer:intValue	()I
    //   76: if_icmpeq +294 -> 370
    //   79: getstatic 78	uuuuuu/wwwnww:b006300630063ccc006300630063	I
    //   82: getstatic 80	uuuuuu/wwwnww:bccc0063cc006300630063	I
    //   85: iadd
    //   86: getstatic 78	uuuuuu/wwwnww:b006300630063ccc006300630063	I
    //   89: imul
    //   90: getstatic 82	uuuuuu/wwwnww:b0063cc0063cc006300630063	I
    //   93: irem
    //   94: getstatic 84	uuuuuu/wwwnww:bc0063c0063cc006300630063	I
    //   97: if_icmpeq +100 -> 197
    //   100: bipush 93
    //   102: putstatic 78	uuuuuu/wwwnww:b006300630063ccc006300630063	I
    //   105: bipush 54
    //   107: putstatic 84	uuuuuu/wwwnww:bc0063c0063cc006300630063	I
    //   110: ldc 2
    //   112: ldc -119
    //   114: iconst_3
    //   115: bipush 42
    //   117: iconst_0
    //   118: invokestatic 92	xxxxxx/uxxxxx:bbbb0062b0062b0062b0062	(Ljava/lang/String;CCC)Ljava/lang/String;
    //   121: iconst_0
    //   122: anewarray 94	java/lang/Class
    //   125: invokevirtual 98	java/lang/Class:getMethod	(Ljava/lang/String;[Ljava/lang/Class;)Ljava/lang/reflect/Method;
    //   128: astore 22
    //   130: iconst_0
    //   131: anewarray 100	java/lang/Object
    //   134: astore 23
    //   136: aload 22
    //   138: aconst_null
    //   139: aload 23
    //   141: invokevirtual 106	java/lang/reflect/Method:invoke	(Ljava/lang/Object;[Ljava/lang/Object;)Ljava/lang/Object;
    //   144: astore 25
    //   146: aload 25
    //   148: checkcast 108	java/lang/Integer
    //   151: invokevirtual 112	java/lang/Integer:intValue	()I
    //   154: istore 26
    //   156: iload 26
    //   158: iload 26
    //   160: getstatic 80	uuuuuu/wwwnww:bccc0063cc006300630063	I
    //   163: iadd
    //   164: imul
    //   165: getstatic 82	uuuuuu/wwwnww:b0063cc0063cc006300630063	I
    //   168: irem
    //   169: tableswitch	default:+19->188, 0:+28->197
    //   188: bipush 93
    //   190: putstatic 78	uuuuuu/wwwnww:b006300630063ccc006300630063	I
    //   193: iconst_4
    //   194: putstatic 84	uuuuuu/wwwnww:bc0063c0063cc006300630063	I
    //   197: ldc 2
    //   199: ldc -117
    //   201: sipush 131
    //   204: iconst_5
    //   205: invokestatic 118	xxxxxx/uxxxxx:bb00620062bb0062b0062b0062	(Ljava/lang/String;CC)Ljava/lang/String;
    //   208: iconst_0
    //   209: anewarray 94	java/lang/Class
    //   212: invokevirtual 98	java/lang/Class:getMethod	(Ljava/lang/String;[Ljava/lang/Class;)Ljava/lang/reflect/Method;
    //   215: astore 9
    //   217: iconst_0
    //   218: anewarray 100	java/lang/Object
    //   221: astore 10
    //   223: aload 9
    //   225: aconst_null
    //   226: aload 10
    //   228: invokevirtual 106	java/lang/reflect/Method:invoke	(Ljava/lang/Object;[Ljava/lang/Object;)Ljava/lang/Object;
    //   231: astore 12
    //   233: aload 12
    //   235: checkcast 108	java/lang/Integer
    //   238: invokevirtual 112	java/lang/Integer:intValue	()I
    //   241: putstatic 78	uuuuuu/wwwnww:b006300630063ccc006300630063	I
    //   244: ldc 2
    //   246: ldc -115
    //   248: sipush 158
    //   251: sipush 204
    //   254: iconst_3
    //   255: invokestatic 92	xxxxxx/uxxxxx:bbbb0062b0062b0062b0062	(Ljava/lang/String;CCC)Ljava/lang/String;
    //   258: iconst_0
    //   259: anewarray 94	java/lang/Class
    //   262: invokevirtual 98	java/lang/Class:getMethod	(Ljava/lang/String;[Ljava/lang/Class;)Ljava/lang/reflect/Method;
    //   265: astore 13
    //   267: iconst_0
    //   268: anewarray 100	java/lang/Object
    //   271: astore 14
    //   273: aload 13
    //   275: aconst_null
    //   276: aload 14
    //   278: invokevirtual 106	java/lang/reflect/Method:invoke	(Ljava/lang/Object;[Ljava/lang/Object;)Ljava/lang/Object;
    //   281: astore 16
    //   283: aload 16
    //   285: checkcast 108	java/lang/Integer
    //   288: invokevirtual 112	java/lang/Integer:intValue	()I
    //   291: istore 17
    //   293: getstatic 78	uuuuuu/wwwnww:b006300630063ccc006300630063	I
    //   296: getstatic 80	uuuuuu/wwwnww:bccc0063cc006300630063	I
    //   299: iadd
    //   300: getstatic 78	uuuuuu/wwwnww:b006300630063ccc006300630063	I
    //   303: imul
    //   304: getstatic 82	uuuuuu/wwwnww:b0063cc0063cc006300630063	I
    //   307: irem
    //   308: getstatic 84	uuuuuu/wwwnww:bc0063c0063cc006300630063	I
    //   311: if_icmpeq +54 -> 365
    //   314: ldc 2
    //   316: ldc -113
    //   318: bipush 25
    //   320: iconst_4
    //   321: invokestatic 118	xxxxxx/uxxxxx:bb00620062bb0062b0062b0062	(Ljava/lang/String;CC)Ljava/lang/String;
    //   324: iconst_0
    //   325: anewarray 94	java/lang/Class
    //   328: invokevirtual 98	java/lang/Class:getMethod	(Ljava/lang/String;[Ljava/lang/Class;)Ljava/lang/reflect/Method;
    //   331: astore 18
    //   333: iconst_0
    //   334: anewarray 100	java/lang/Object
    //   337: astore 19
    //   339: aload 18
    //   341: aconst_null
    //   342: aload 19
    //   344: invokevirtual 106	java/lang/reflect/Method:invoke	(Ljava/lang/Object;[Ljava/lang/Object;)Ljava/lang/Object;
    //   347: astore 21
    //   349: aload 21
    //   351: checkcast 108	java/lang/Integer
    //   354: invokevirtual 112	java/lang/Integer:intValue	()I
    //   357: putstatic 78	uuuuuu/wwwnww:b006300630063ccc006300630063	I
    //   360: bipush 92
    //   362: putstatic 84	uuuuuu/wwwnww:bc0063c0063cc006300630063	I
    //   365: iload 17
    //   367: putstatic 84	uuuuuu/wwwnww:bc0063c0063cc006300630063	I
    //   370: aload_3
    //   371: aload_2
    //   372: invokevirtual 147	com/db/pwcc/dbmobile/ibanbic/items/AccountItem:setAccountType	(Lcom/db/pwcc/dbmobile/ibanbic/items/AccountItem$nwwwww;)V
    //   375: aload_3
    //   376: areturn
    //   377: astore 11
    //   379: aload 11
    //   381: invokevirtual 122	java/lang/reflect/InvocationTargetException:getCause	()Ljava/lang/Throwable;
    //   384: athrow
    //   385: astore 7
    //   387: aload 7
    //   389: invokevirtual 122	java/lang/reflect/InvocationTargetException:getCause	()Ljava/lang/Throwable;
    //   392: athrow
    //   393: astore 15
    //   395: aload 15
    //   397: invokevirtual 122	java/lang/reflect/InvocationTargetException:getCause	()Ljava/lang/Throwable;
    //   400: athrow
    //   401: astore 24
    //   403: aload 24
    //   405: invokevirtual 122	java/lang/reflect/InvocationTargetException:getCause	()Ljava/lang/Throwable;
    //   408: athrow
    //   409: astore 20
    //   411: aload 20
    //   413: invokevirtual 122	java/lang/reflect/InvocationTargetException:getCause	()Ljava/lang/Throwable;
    //   416: athrow
    // Local variable table:
    //   start	length	slot	name	signature
    //   0	417	0	this	wwwnww
    //   0	417	1	paramString	String
    //   0	417	2	paramNwwwww	com.db.pwcc.dbmobile.ibanbic.items.AccountItem.nwwwww
    //   7	369	3	localAccountItem	AccountItem
    //   28	49	4	i	int
    //   48	9	5	localMethod1	java.lang.reflect.Method
    //   54	6	6	arrayOfObject1	Object[]
    //   385	3	7	localInvocationTargetException1	java.lang.reflect.InvocationTargetException
    //   64	5	8	localObject1	Object
    //   215	9	9	localMethod2	java.lang.reflect.Method
    //   221	6	10	arrayOfObject2	Object[]
    //   377	3	11	localInvocationTargetException2	java.lang.reflect.InvocationTargetException
    //   231	3	12	localObject2	Object
    //   265	9	13	localMethod3	java.lang.reflect.Method
    //   271	6	14	arrayOfObject3	Object[]
    //   393	3	15	localInvocationTargetException3	java.lang.reflect.InvocationTargetException
    //   281	3	16	localObject3	Object
    //   291	75	17	j	int
    //   331	9	18	localMethod4	java.lang.reflect.Method
    //   337	6	19	arrayOfObject4	Object[]
    //   409	3	20	localInvocationTargetException4	java.lang.reflect.InvocationTargetException
    //   347	3	21	localObject4	Object
    //   128	9	22	localMethod5	java.lang.reflect.Method
    //   134	6	23	arrayOfObject5	Object[]
    //   401	3	24	localInvocationTargetException5	java.lang.reflect.InvocationTargetException
    //   144	3	25	localObject5	Object
    //   154	11	26	k	int
    // Exception table:
    //   from	to	target	type
    //   223	233	377	java/lang/reflect/InvocationTargetException
    //   56	66	385	java/lang/reflect/InvocationTargetException
    //   273	283	393	java/lang/reflect/InvocationTargetException
    //   136	146	401	java/lang/reflect/InvocationTargetException
    //   339	349	409	java/lang/reflect/InvocationTargetException
  }
  
  /* Error */
  private int bq007100710071qqq00710071q(com.db.pwcc.dbmobile.model.banking.Account paramAccount, String paramString)
  {
    // Byte code:
    //   0: aload_1
    //   1: invokevirtual 155	com/db/pwcc/dbmobile/model/banking/Account:getProductType	()Lcom/db/pwcc/dbmobile/model/banking/Account$ProductType;
    //   4: invokevirtual 161	com/db/pwcc/dbmobile/model/banking/Account$ProductType:name	()Ljava/lang/String;
    //   7: astore_3
    //   8: aload_3
    //   9: getstatic 165	com/db/pwcc/dbmobile/model/banking/Account$ProductType:CURRENT_ACCOUNT	Lcom/db/pwcc/dbmobile/model/banking/Account$ProductType;
    //   12: invokevirtual 161	com/db/pwcc/dbmobile/model/banking/Account$ProductType:name	()Ljava/lang/String;
    //   15: invokevirtual 171	java/lang/String:equals	(Ljava/lang/Object;)Z
    //   18: ifne +16 -> 34
    //   21: aload_3
    //   22: getstatic 174	com/db/pwcc/dbmobile/model/banking/Account$ProductType:PERSONAL_CREDIT_ACCOUNT	Lcom/db/pwcc/dbmobile/model/banking/Account$ProductType;
    //   25: invokevirtual 161	com/db/pwcc/dbmobile/model/banking/Account$ProductType:name	()Ljava/lang/String;
    //   28: invokevirtual 171	java/lang/String:equals	(Ljava/lang/Object;)Z
    //   31: ifeq +183 -> 214
    //   34: aload_2
    //   35: aload_1
    //   36: invokevirtual 177	com/db/pwcc/dbmobile/model/banking/Account:getCurrency	()Ljava/lang/String;
    //   39: invokevirtual 171	java/lang/String:equals	(Ljava/lang/Object;)Z
    //   42: ifeq +692 -> 734
    //   45: getstatic 78	uuuuuu/wwwnww:b006300630063ccc006300630063	I
    //   48: getstatic 80	uuuuuu/wwwnww:bccc0063cc006300630063	I
    //   51: iadd
    //   52: getstatic 78	uuuuuu/wwwnww:b006300630063ccc006300630063	I
    //   55: imul
    //   56: getstatic 82	uuuuuu/wwwnww:b0063cc0063cc006300630063	I
    //   59: irem
    //   60: istore 4
    //   62: ldc 2
    //   64: ldc -77
    //   66: sipush 228
    //   69: sipush 251
    //   72: iconst_3
    //   73: invokestatic 92	xxxxxx/uxxxxx:bbbb0062b0062b0062b0062	(Ljava/lang/String;CCC)Ljava/lang/String;
    //   76: iconst_0
    //   77: anewarray 94	java/lang/Class
    //   80: invokevirtual 98	java/lang/Class:getMethod	(Ljava/lang/String;[Ljava/lang/Class;)Ljava/lang/reflect/Method;
    //   83: astore 5
    //   85: iconst_0
    //   86: anewarray 100	java/lang/Object
    //   89: astore 6
    //   91: aload 5
    //   93: aconst_null
    //   94: aload 6
    //   96: invokevirtual 106	java/lang/reflect/Method:invoke	(Ljava/lang/Object;[Ljava/lang/Object;)Ljava/lang/Object;
    //   99: astore 8
    //   101: iload 4
    //   103: aload 8
    //   105: checkcast 108	java/lang/Integer
    //   108: invokevirtual 112	java/lang/Integer:intValue	()I
    //   111: if_icmpeq +99 -> 210
    //   114: ldc 2
    //   116: ldc -75
    //   118: sipush 236
    //   121: sipush 219
    //   124: iconst_2
    //   125: invokestatic 92	xxxxxx/uxxxxx:bbbb0062b0062b0062b0062	(Ljava/lang/String;CCC)Ljava/lang/String;
    //   128: iconst_0
    //   129: anewarray 94	java/lang/Class
    //   132: invokevirtual 98	java/lang/Class:getMethod	(Ljava/lang/String;[Ljava/lang/Class;)Ljava/lang/reflect/Method;
    //   135: astore 9
    //   137: iconst_0
    //   138: anewarray 100	java/lang/Object
    //   141: astore 10
    //   143: aload 9
    //   145: aconst_null
    //   146: aload 10
    //   148: invokevirtual 106	java/lang/reflect/Method:invoke	(Ljava/lang/Object;[Ljava/lang/Object;)Ljava/lang/Object;
    //   151: astore 12
    //   153: aload 12
    //   155: checkcast 108	java/lang/Integer
    //   158: invokevirtual 112	java/lang/Integer:intValue	()I
    //   161: putstatic 78	uuuuuu/wwwnww:b006300630063ccc006300630063	I
    //   164: ldc 2
    //   166: ldc -73
    //   168: bipush 126
    //   170: iconst_5
    //   171: invokestatic 118	xxxxxx/uxxxxx:bb00620062bb0062b0062b0062	(Ljava/lang/String;CC)Ljava/lang/String;
    //   174: iconst_0
    //   175: anewarray 94	java/lang/Class
    //   178: invokevirtual 98	java/lang/Class:getMethod	(Ljava/lang/String;[Ljava/lang/Class;)Ljava/lang/reflect/Method;
    //   181: astore 13
    //   183: iconst_0
    //   184: anewarray 100	java/lang/Object
    //   187: astore 14
    //   189: aload 13
    //   191: aconst_null
    //   192: aload 14
    //   194: invokevirtual 106	java/lang/reflect/Method:invoke	(Ljava/lang/Object;[Ljava/lang/Object;)Ljava/lang/Object;
    //   197: astore 16
    //   199: aload 16
    //   201: checkcast 108	java/lang/Integer
    //   204: invokevirtual 112	java/lang/Integer:intValue	()I
    //   207: putstatic 84	uuuuuu/wwwnww:bc0063c0063cc006300630063	I
    //   210: getstatic 188	com/db/pwcc/dbmobile/ibanbic/R$string:accounts	I
    //   213: ireturn
    //   214: aload_3
    //   215: getstatic 191	com/db/pwcc/dbmobile/model/banking/Account$ProductType:SAVINGS_ACCOUNT_BANK_TRANSFER_ENABLED	Lcom/db/pwcc/dbmobile/model/banking/Account$ProductType;
    //   218: invokevirtual 161	com/db/pwcc/dbmobile/model/banking/Account$ProductType:name	()Ljava/lang/String;
    //   221: invokevirtual 171	java/lang/String:equals	(Ljava/lang/Object;)Z
    //   224: ifne +16 -> 240
    //   227: aload_3
    //   228: getstatic 194	com/db/pwcc/dbmobile/model/banking/Account$ProductType:SAVINGS_ACCOUNT_BANK_TRANSFER_NOT_ENABLED	Lcom/db/pwcc/dbmobile/model/banking/Account$ProductType;
    //   231: invokevirtual 161	com/db/pwcc/dbmobile/model/banking/Account$ProductType:name	()Ljava/lang/String;
    //   234: invokevirtual 171	java/lang/String:equals	(Ljava/lang/Object;)Z
    //   237: ifeq +461 -> 698
    //   240: getstatic 197	com/db/pwcc/dbmobile/ibanbic/R$string:savings_accounts	I
    //   243: istore 17
    //   245: ldc 2
    //   247: ldc -57
    //   249: sipush 250
    //   252: iconst_5
    //   253: invokestatic 118	xxxxxx/uxxxxx:bb00620062bb0062b0062b0062	(Ljava/lang/String;CC)Ljava/lang/String;
    //   256: iconst_0
    //   257: anewarray 94	java/lang/Class
    //   260: invokevirtual 98	java/lang/Class:getMethod	(Ljava/lang/String;[Ljava/lang/Class;)Ljava/lang/reflect/Method;
    //   263: astore 18
    //   265: iconst_0
    //   266: anewarray 100	java/lang/Object
    //   269: astore 19
    //   271: aload 18
    //   273: aconst_null
    //   274: aload 19
    //   276: invokevirtual 106	java/lang/reflect/Method:invoke	(Ljava/lang/Object;[Ljava/lang/Object;)Ljava/lang/Object;
    //   279: astore 21
    //   281: aload 21
    //   283: checkcast 108	java/lang/Integer
    //   286: invokevirtual 112	java/lang/Integer:intValue	()I
    //   289: istore 22
    //   291: iload 22
    //   293: iload 22
    //   295: getstatic 80	uuuuuu/wwwnww:bccc0063cc006300630063	I
    //   298: iadd
    //   299: imul
    //   300: getstatic 82	uuuuuu/wwwnww:b0063cc0063cc006300630063	I
    //   303: irem
    //   304: tableswitch	default:+20->324, 0:+114->418
    //   324: ldc 2
    //   326: ldc -55
    //   328: sipush 253
    //   331: iconst_0
    //   332: invokestatic 118	xxxxxx/uxxxxx:bb00620062bb0062b0062b0062	(Ljava/lang/String;CC)Ljava/lang/String;
    //   335: iconst_0
    //   336: anewarray 94	java/lang/Class
    //   339: invokevirtual 98	java/lang/Class:getMethod	(Ljava/lang/String;[Ljava/lang/Class;)Ljava/lang/reflect/Method;
    //   342: astore 41
    //   344: iconst_0
    //   345: anewarray 100	java/lang/Object
    //   348: astore 42
    //   350: aload 41
    //   352: aconst_null
    //   353: aload 42
    //   355: invokevirtual 106	java/lang/reflect/Method:invoke	(Ljava/lang/Object;[Ljava/lang/Object;)Ljava/lang/Object;
    //   358: astore 44
    //   360: aload 44
    //   362: checkcast 108	java/lang/Integer
    //   365: invokevirtual 112	java/lang/Integer:intValue	()I
    //   368: putstatic 78	uuuuuu/wwwnww:b006300630063ccc006300630063	I
    //   371: ldc 2
    //   373: ldc -53
    //   375: sipush 157
    //   378: iconst_4
    //   379: invokestatic 118	xxxxxx/uxxxxx:bb00620062bb0062b0062b0062	(Ljava/lang/String;CC)Ljava/lang/String;
    //   382: iconst_0
    //   383: anewarray 94	java/lang/Class
    //   386: invokevirtual 98	java/lang/Class:getMethod	(Ljava/lang/String;[Ljava/lang/Class;)Ljava/lang/reflect/Method;
    //   389: astore 45
    //   391: iconst_0
    //   392: anewarray 100	java/lang/Object
    //   395: astore 46
    //   397: aload 45
    //   399: aconst_null
    //   400: aload 46
    //   402: invokevirtual 106	java/lang/reflect/Method:invoke	(Ljava/lang/Object;[Ljava/lang/Object;)Ljava/lang/Object;
    //   405: astore 48
    //   407: aload 48
    //   409: checkcast 108	java/lang/Integer
    //   412: invokevirtual 112	java/lang/Integer:intValue	()I
    //   415: putstatic 84	uuuuuu/wwwnww:bc0063c0063cc006300630063	I
    //   418: getstatic 78	uuuuuu/wwwnww:b006300630063ccc006300630063	I
    //   421: istore 23
    //   423: ldc 2
    //   425: ldc -51
    //   427: sipush 140
    //   430: sipush 241
    //   433: iconst_3
    //   434: invokestatic 92	xxxxxx/uxxxxx:bbbb0062b0062b0062b0062	(Ljava/lang/String;CCC)Ljava/lang/String;
    //   437: iconst_0
    //   438: anewarray 94	java/lang/Class
    //   441: invokevirtual 98	java/lang/Class:getMethod	(Ljava/lang/String;[Ljava/lang/Class;)Ljava/lang/reflect/Method;
    //   444: astore 24
    //   446: iconst_0
    //   447: anewarray 100	java/lang/Object
    //   450: astore 25
    //   452: aload 24
    //   454: aconst_null
    //   455: aload 25
    //   457: invokevirtual 106	java/lang/reflect/Method:invoke	(Ljava/lang/Object;[Ljava/lang/Object;)Ljava/lang/Object;
    //   460: astore 27
    //   462: iload 23
    //   464: iload 23
    //   466: aload 27
    //   468: checkcast 108	java/lang/Integer
    //   471: invokevirtual 112	java/lang/Integer:intValue	()I
    //   474: iadd
    //   475: imul
    //   476: getstatic 82	uuuuuu/wwwnww:b0063cc0063cc006300630063	I
    //   479: irem
    //   480: tableswitch	default:+20->500, 0:+282->762
    //   500: ldc 2
    //   502: ldc -49
    //   504: bipush 34
    //   506: iconst_3
    //   507: invokestatic 118	xxxxxx/uxxxxx:bb00620062bb0062b0062b0062	(Ljava/lang/String;CC)Ljava/lang/String;
    //   510: iconst_0
    //   511: anewarray 94	java/lang/Class
    //   514: invokevirtual 98	java/lang/Class:getMethod	(Ljava/lang/String;[Ljava/lang/Class;)Ljava/lang/reflect/Method;
    //   517: astore 28
    //   519: iconst_0
    //   520: anewarray 100	java/lang/Object
    //   523: astore 29
    //   525: aload 28
    //   527: aconst_null
    //   528: aload 29
    //   530: invokevirtual 106	java/lang/reflect/Method:invoke	(Ljava/lang/Object;[Ljava/lang/Object;)Ljava/lang/Object;
    //   533: astore 31
    //   535: aload 31
    //   537: checkcast 108	java/lang/Integer
    //   540: invokevirtual 112	java/lang/Integer:intValue	()I
    //   543: putstatic 78	uuuuuu/wwwnww:b006300630063ccc006300630063	I
    //   546: ldc 2
    //   548: ldc -115
    //   550: bipush 108
    //   552: iconst_2
    //   553: invokestatic 118	xxxxxx/uxxxxx:bb00620062bb0062b0062b0062	(Ljava/lang/String;CC)Ljava/lang/String;
    //   556: iconst_0
    //   557: anewarray 94	java/lang/Class
    //   560: invokevirtual 98	java/lang/Class:getMethod	(Ljava/lang/String;[Ljava/lang/Class;)Ljava/lang/reflect/Method;
    //   563: astore 32
    //   565: iconst_0
    //   566: anewarray 100	java/lang/Object
    //   569: astore 33
    //   571: aload 32
    //   573: aconst_null
    //   574: aload 33
    //   576: invokevirtual 106	java/lang/reflect/Method:invoke	(Ljava/lang/Object;[Ljava/lang/Object;)Ljava/lang/Object;
    //   579: astore 35
    //   581: aload 35
    //   583: checkcast 108	java/lang/Integer
    //   586: invokevirtual 112	java/lang/Integer:intValue	()I
    //   589: putstatic 84	uuuuuu/wwwnww:bc0063c0063cc006300630063	I
    //   592: getstatic 78	uuuuuu/wwwnww:b006300630063ccc006300630063	I
    //   595: getstatic 80	uuuuuu/wwwnww:bccc0063cc006300630063	I
    //   598: iadd
    //   599: getstatic 78	uuuuuu/wwwnww:b006300630063ccc006300630063	I
    //   602: imul
    //   603: getstatic 82	uuuuuu/wwwnww:b0063cc0063cc006300630063	I
    //   606: irem
    //   607: istore 36
    //   609: ldc 2
    //   611: ldc -47
    //   613: sipush 239
    //   616: sipush 160
    //   619: iconst_0
    //   620: invokestatic 92	xxxxxx/uxxxxx:bbbb0062b0062b0062b0062	(Ljava/lang/String;CCC)Ljava/lang/String;
    //   623: iconst_0
    //   624: anewarray 94	java/lang/Class
    //   627: invokevirtual 98	java/lang/Class:getMethod	(Ljava/lang/String;[Ljava/lang/Class;)Ljava/lang/reflect/Method;
    //   630: astore 37
    //   632: iconst_0
    //   633: anewarray 100	java/lang/Object
    //   636: astore 38
    //   638: aload 37
    //   640: aconst_null
    //   641: aload 38
    //   643: invokevirtual 106	java/lang/reflect/Method:invoke	(Ljava/lang/Object;[Ljava/lang/Object;)Ljava/lang/Object;
    //   646: astore 40
    //   648: iload 36
    //   650: aload 40
    //   652: checkcast 108	java/lang/Integer
    //   655: invokevirtual 112	java/lang/Integer:intValue	()I
    //   658: if_icmpeq +13 -> 671
    //   661: bipush 80
    //   663: putstatic 78	uuuuuu/wwwnww:b006300630063ccc006300630063	I
    //   666: bipush 20
    //   668: putstatic 84	uuuuuu/wwwnww:bc0063c0063cc006300630063	I
    //   671: iload 17
    //   673: ireturn
    //   674: astore 20
    //   676: aload 20
    //   678: invokevirtual 122	java/lang/reflect/InvocationTargetException:getCause	()Ljava/lang/Throwable;
    //   681: athrow
    //   682: astore 26
    //   684: aload 26
    //   686: invokevirtual 122	java/lang/reflect/InvocationTargetException:getCause	()Ljava/lang/Throwable;
    //   689: athrow
    //   690: astore 7
    //   692: aload 7
    //   694: invokevirtual 122	java/lang/reflect/InvocationTargetException:getCause	()Ljava/lang/Throwable;
    //   697: athrow
    //   698: getstatic 212	com/db/pwcc/dbmobile/ibanbic/R$string:unknown	I
    //   701: ireturn
    //   702: astore 11
    //   704: aload 11
    //   706: invokevirtual 122	java/lang/reflect/InvocationTargetException:getCause	()Ljava/lang/Throwable;
    //   709: athrow
    //   710: astore 15
    //   712: aload 15
    //   714: invokevirtual 122	java/lang/reflect/InvocationTargetException:getCause	()Ljava/lang/Throwable;
    //   717: athrow
    //   718: astore 43
    //   720: aload 43
    //   722: invokevirtual 122	java/lang/reflect/InvocationTargetException:getCause	()Ljava/lang/Throwable;
    //   725: athrow
    //   726: astore 47
    //   728: aload 47
    //   730: invokevirtual 122	java/lang/reflect/InvocationTargetException:getCause	()Ljava/lang/Throwable;
    //   733: athrow
    //   734: getstatic 215	com/db/pwcc/dbmobile/ibanbic/R$string:currency_accounts	I
    //   737: ireturn
    //   738: astore 30
    //   740: aload 30
    //   742: invokevirtual 122	java/lang/reflect/InvocationTargetException:getCause	()Ljava/lang/Throwable;
    //   745: athrow
    //   746: astore 34
    //   748: aload 34
    //   750: invokevirtual 122	java/lang/reflect/InvocationTargetException:getCause	()Ljava/lang/Throwable;
    //   753: athrow
    //   754: astore 39
    //   756: aload 39
    //   758: invokevirtual 122	java/lang/reflect/InvocationTargetException:getCause	()Ljava/lang/Throwable;
    //   761: athrow
    //   762: iload 17
    //   764: ireturn
    // Local variable table:
    //   start	length	slot	name	signature
    //   0	765	0	this	wwwnww
    //   0	765	1	paramAccount	com.db.pwcc.dbmobile.model.banking.Account
    //   0	765	2	paramString	String
    //   7	221	3	str	String
    //   60	52	4	i	int
    //   83	9	5	localMethod1	java.lang.reflect.Method
    //   89	6	6	arrayOfObject1	Object[]
    //   690	3	7	localInvocationTargetException1	java.lang.reflect.InvocationTargetException
    //   99	5	8	localObject1	Object
    //   135	9	9	localMethod2	java.lang.reflect.Method
    //   141	6	10	arrayOfObject2	Object[]
    //   702	3	11	localInvocationTargetException2	java.lang.reflect.InvocationTargetException
    //   151	3	12	localObject2	Object
    //   181	9	13	localMethod3	java.lang.reflect.Method
    //   187	6	14	arrayOfObject3	Object[]
    //   710	3	15	localInvocationTargetException3	java.lang.reflect.InvocationTargetException
    //   197	3	16	localObject3	Object
    //   243	520	17	j	int
    //   263	9	18	localMethod4	java.lang.reflect.Method
    //   269	6	19	arrayOfObject4	Object[]
    //   674	3	20	localInvocationTargetException4	java.lang.reflect.InvocationTargetException
    //   279	3	21	localObject4	Object
    //   289	11	22	k	int
    //   421	55	23	m	int
    //   444	9	24	localMethod5	java.lang.reflect.Method
    //   450	6	25	arrayOfObject5	Object[]
    //   682	3	26	localInvocationTargetException5	java.lang.reflect.InvocationTargetException
    //   460	7	27	localObject5	Object
    //   517	9	28	localMethod6	java.lang.reflect.Method
    //   523	6	29	arrayOfObject6	Object[]
    //   738	3	30	localInvocationTargetException6	java.lang.reflect.InvocationTargetException
    //   533	3	31	localObject6	Object
    //   563	9	32	localMethod7	java.lang.reflect.Method
    //   569	6	33	arrayOfObject7	Object[]
    //   746	3	34	localInvocationTargetException7	java.lang.reflect.InvocationTargetException
    //   579	3	35	localObject7	Object
    //   607	52	36	n	int
    //   630	9	37	localMethod8	java.lang.reflect.Method
    //   636	6	38	arrayOfObject8	Object[]
    //   754	3	39	localInvocationTargetException8	java.lang.reflect.InvocationTargetException
    //   646	5	40	localObject8	Object
    //   342	9	41	localMethod9	java.lang.reflect.Method
    //   348	6	42	arrayOfObject9	Object[]
    //   718	3	43	localInvocationTargetException9	java.lang.reflect.InvocationTargetException
    //   358	3	44	localObject9	Object
    //   389	9	45	localMethod10	java.lang.reflect.Method
    //   395	6	46	arrayOfObject10	Object[]
    //   726	3	47	localInvocationTargetException10	java.lang.reflect.InvocationTargetException
    //   405	3	48	localObject10	Object
    // Exception table:
    //   from	to	target	type
    //   271	281	674	java/lang/reflect/InvocationTargetException
    //   452	462	682	java/lang/reflect/InvocationTargetException
    //   91	101	690	java/lang/reflect/InvocationTargetException
    //   143	153	702	java/lang/reflect/InvocationTargetException
    //   189	199	710	java/lang/reflect/InvocationTargetException
    //   350	360	718	java/lang/reflect/InvocationTargetException
    //   397	407	726	java/lang/reflect/InvocationTargetException
    //   525	535	738	java/lang/reflect/InvocationTargetException
    //   571	581	746	java/lang/reflect/InvocationTargetException
    //   638	648	754	java/lang/reflect/InvocationTargetException
  }
  
  public static int bq0071q0071qqq00710071q()
  {
    return 0;
  }
  
  public static int bqq00710071qqq00710071q()
  {
    return 2;
  }
  
  /* Error */
  private AccountItem bqqq0071qqq00710071q(com.db.pwcc.dbmobile.model.banking.Account paramAccount, String paramString)
  {
    // Byte code:
    //   0: ldc 2
    //   2: ldc -21
    //   4: bipush 63
    //   6: sipush 152
    //   9: iconst_1
    //   10: invokestatic 92	xxxxxx/uxxxxx:bbbb0062b0062b0062b0062	(Ljava/lang/String;CCC)Ljava/lang/String;
    //   13: iconst_0
    //   14: anewarray 94	java/lang/Class
    //   17: invokevirtual 98	java/lang/Class:getMethod	(Ljava/lang/String;[Ljava/lang/Class;)Ljava/lang/reflect/Method;
    //   20: astore_3
    //   21: iconst_0
    //   22: anewarray 100	java/lang/Object
    //   25: astore 4
    //   27: aload_3
    //   28: aconst_null
    //   29: aload 4
    //   31: invokevirtual 106	java/lang/reflect/Method:invoke	(Ljava/lang/Object;[Ljava/lang/Object;)Ljava/lang/Object;
    //   34: astore 6
    //   36: aload 6
    //   38: checkcast 108	java/lang/Integer
    //   41: invokevirtual 112	java/lang/Integer:intValue	()I
    //   44: getstatic 80	uuuuuu/wwwnww:bccc0063cc006300630063	I
    //   47: iadd
    //   48: istore 7
    //   50: getstatic 78	uuuuuu/wwwnww:b006300630063ccc006300630063	I
    //   53: istore 8
    //   55: ldc 2
    //   57: ldc -19
    //   59: sipush 188
    //   62: sipush 206
    //   65: iconst_3
    //   66: invokestatic 92	xxxxxx/uxxxxx:bbbb0062b0062b0062b0062	(Ljava/lang/String;CCC)Ljava/lang/String;
    //   69: iconst_0
    //   70: anewarray 94	java/lang/Class
    //   73: invokevirtual 98	java/lang/Class:getMethod	(Ljava/lang/String;[Ljava/lang/Class;)Ljava/lang/reflect/Method;
    //   76: astore 9
    //   78: iconst_0
    //   79: anewarray 100	java/lang/Object
    //   82: astore 10
    //   84: aload 9
    //   86: aconst_null
    //   87: aload 10
    //   89: invokevirtual 106	java/lang/reflect/Method:invoke	(Ljava/lang/Object;[Ljava/lang/Object;)Ljava/lang/Object;
    //   92: astore 12
    //   94: iload 8
    //   96: iload 8
    //   98: aload 12
    //   100: checkcast 108	java/lang/Integer
    //   103: invokevirtual 112	java/lang/Integer:intValue	()I
    //   106: iadd
    //   107: imul
    //   108: getstatic 82	uuuuuu/wwwnww:b0063cc0063cc006300630063	I
    //   111: irem
    //   112: tableswitch	default:+20->132, 0:+119->231
    //   132: ldc 2
    //   134: ldc -17
    //   136: sipush 131
    //   139: sipush 166
    //   142: iconst_2
    //   143: invokestatic 92	xxxxxx/uxxxxx:bbbb0062b0062b0062b0062	(Ljava/lang/String;CCC)Ljava/lang/String;
    //   146: iconst_0
    //   147: anewarray 94	java/lang/Class
    //   150: invokevirtual 98	java/lang/Class:getMethod	(Ljava/lang/String;[Ljava/lang/Class;)Ljava/lang/reflect/Method;
    //   153: astore 46
    //   155: iconst_0
    //   156: anewarray 100	java/lang/Object
    //   159: astore 47
    //   161: aload 46
    //   163: aconst_null
    //   164: aload 47
    //   166: invokevirtual 106	java/lang/reflect/Method:invoke	(Ljava/lang/Object;[Ljava/lang/Object;)Ljava/lang/Object;
    //   169: astore 49
    //   171: aload 49
    //   173: checkcast 108	java/lang/Integer
    //   176: invokevirtual 112	java/lang/Integer:intValue	()I
    //   179: putstatic 78	uuuuuu/wwwnww:b006300630063ccc006300630063	I
    //   182: ldc 2
    //   184: ldc -15
    //   186: bipush 84
    //   188: sipush 209
    //   191: iconst_1
    //   192: invokestatic 92	xxxxxx/uxxxxx:bbbb0062b0062b0062b0062	(Ljava/lang/String;CCC)Ljava/lang/String;
    //   195: iconst_0
    //   196: anewarray 94	java/lang/Class
    //   199: invokevirtual 98	java/lang/Class:getMethod	(Ljava/lang/String;[Ljava/lang/Class;)Ljava/lang/reflect/Method;
    //   202: astore 50
    //   204: iconst_0
    //   205: anewarray 100	java/lang/Object
    //   208: astore 51
    //   210: aload 50
    //   212: aconst_null
    //   213: aload 51
    //   215: invokevirtual 106	java/lang/reflect/Method:invoke	(Ljava/lang/Object;[Ljava/lang/Object;)Ljava/lang/Object;
    //   218: astore 53
    //   220: aload 53
    //   222: checkcast 108	java/lang/Integer
    //   225: invokevirtual 112	java/lang/Integer:intValue	()I
    //   228: putstatic 84	uuuuuu/wwwnww:bc0063c0063cc006300630063	I
    //   231: ldc 2
    //   233: ldc -13
    //   235: bipush 32
    //   237: iconst_0
    //   238: invokestatic 118	xxxxxx/uxxxxx:bb00620062bb0062b0062b0062	(Ljava/lang/String;CC)Ljava/lang/String;
    //   241: iconst_0
    //   242: anewarray 94	java/lang/Class
    //   245: invokevirtual 98	java/lang/Class:getMethod	(Ljava/lang/String;[Ljava/lang/Class;)Ljava/lang/reflect/Method;
    //   248: astore 13
    //   250: iconst_0
    //   251: anewarray 100	java/lang/Object
    //   254: astore 14
    //   256: aload 13
    //   258: aconst_null
    //   259: aload 14
    //   261: invokevirtual 106	java/lang/reflect/Method:invoke	(Ljava/lang/Object;[Ljava/lang/Object;)Ljava/lang/Object;
    //   264: astore 16
    //   266: iload 7
    //   268: aload 16
    //   270: checkcast 108	java/lang/Integer
    //   273: invokevirtual 112	java/lang/Integer:intValue	()I
    //   276: imul
    //   277: istore 17
    //   279: ldc 2
    //   281: ldc -11
    //   283: sipush 130
    //   286: bipush 34
    //   288: iconst_1
    //   289: invokestatic 92	xxxxxx/uxxxxx:bbbb0062b0062b0062b0062	(Ljava/lang/String;CCC)Ljava/lang/String;
    //   292: iconst_0
    //   293: anewarray 94	java/lang/Class
    //   296: invokevirtual 98	java/lang/Class:getMethod	(Ljava/lang/String;[Ljava/lang/Class;)Ljava/lang/reflect/Method;
    //   299: astore 18
    //   301: iconst_0
    //   302: anewarray 100	java/lang/Object
    //   305: astore 19
    //   307: aload 18
    //   309: aconst_null
    //   310: aload 19
    //   312: invokevirtual 106	java/lang/reflect/Method:invoke	(Ljava/lang/Object;[Ljava/lang/Object;)Ljava/lang/Object;
    //   315: astore 21
    //   317: iload 17
    //   319: aload 21
    //   321: checkcast 108	java/lang/Integer
    //   324: invokevirtual 112	java/lang/Integer:intValue	()I
    //   327: irem
    //   328: getstatic 84	uuuuuu/wwwnww:bc0063c0063cc006300630063	I
    //   331: if_icmpeq +143 -> 474
    //   334: bipush 84
    //   336: putstatic 78	uuuuuu/wwwnww:b006300630063ccc006300630063	I
    //   339: bipush 33
    //   341: putstatic 84	uuuuuu/wwwnww:bc0063c0063cc006300630063	I
    //   344: getstatic 78	uuuuuu/wwwnww:b006300630063ccc006300630063	I
    //   347: istore 37
    //   349: iload 37
    //   351: iload 37
    //   353: getstatic 80	uuuuuu/wwwnww:bccc0063cc006300630063	I
    //   356: iadd
    //   357: imul
    //   358: getstatic 82	uuuuuu/wwwnww:b0063cc0063cc006300630063	I
    //   361: irem
    //   362: tableswitch	default:+18->380, 0:+112->474
    //   380: ldc 2
    //   382: ldc -9
    //   384: sipush 135
    //   387: iconst_0
    //   388: invokestatic 118	xxxxxx/uxxxxx:bb00620062bb0062b0062b0062	(Ljava/lang/String;CC)Ljava/lang/String;
    //   391: iconst_0
    //   392: anewarray 94	java/lang/Class
    //   395: invokevirtual 98	java/lang/Class:getMethod	(Ljava/lang/String;[Ljava/lang/Class;)Ljava/lang/reflect/Method;
    //   398: astore 38
    //   400: iconst_0
    //   401: anewarray 100	java/lang/Object
    //   404: astore 39
    //   406: aload 38
    //   408: aconst_null
    //   409: aload 39
    //   411: invokevirtual 106	java/lang/reflect/Method:invoke	(Ljava/lang/Object;[Ljava/lang/Object;)Ljava/lang/Object;
    //   414: astore 41
    //   416: aload 41
    //   418: checkcast 108	java/lang/Integer
    //   421: invokevirtual 112	java/lang/Integer:intValue	()I
    //   424: putstatic 78	uuuuuu/wwwnww:b006300630063ccc006300630063	I
    //   427: ldc 2
    //   429: ldc -7
    //   431: sipush 156
    //   434: iconst_2
    //   435: invokestatic 118	xxxxxx/uxxxxx:bb00620062bb0062b0062b0062	(Ljava/lang/String;CC)Ljava/lang/String;
    //   438: iconst_0
    //   439: anewarray 94	java/lang/Class
    //   442: invokevirtual 98	java/lang/Class:getMethod	(Ljava/lang/String;[Ljava/lang/Class;)Ljava/lang/reflect/Method;
    //   445: astore 42
    //   447: iconst_0
    //   448: anewarray 100	java/lang/Object
    //   451: astore 43
    //   453: aload 42
    //   455: aconst_null
    //   456: aload 43
    //   458: invokevirtual 106	java/lang/reflect/Method:invoke	(Ljava/lang/Object;[Ljava/lang/Object;)Ljava/lang/Object;
    //   461: astore 45
    //   463: aload 45
    //   465: checkcast 108	java/lang/Integer
    //   468: invokevirtual 112	java/lang/Integer:intValue	()I
    //   471: putstatic 84	uuuuuu/wwwnww:bc0063c0063cc006300630063	I
    //   474: new 128	com/db/pwcc/dbmobile/ibanbic/items/AccountItem
    //   477: dup
    //   478: aload_1
    //   479: invokespecial 252	com/db/pwcc/dbmobile/ibanbic/items/AccountItem:<init>	(Lcom/db/pwcc/dbmobile/model/banking/Account;)V
    //   482: astore 22
    //   484: aload 22
    //   486: aload_2
    //   487: invokevirtual 255	com/db/pwcc/dbmobile/ibanbic/items/AccountItem:setBlz	(Ljava/lang/String;)V
    //   490: getstatic 261	com/db/pwcc/dbmobile/ibanbic/items/AccountItem$nwwwww:bc0063006300630063c006300630063	Lcom/db/pwcc/dbmobile/ibanbic/items/AccountItem$nwwwww;
    //   493: astore 23
    //   495: ldc 2
    //   497: ldc_w 263
    //   500: bipush 99
    //   502: iconst_5
    //   503: invokestatic 118	xxxxxx/uxxxxx:bb00620062bb0062b0062b0062	(Ljava/lang/String;CC)Ljava/lang/String;
    //   506: iconst_0
    //   507: anewarray 94	java/lang/Class
    //   510: invokevirtual 98	java/lang/Class:getMethod	(Ljava/lang/String;[Ljava/lang/Class;)Ljava/lang/reflect/Method;
    //   513: astore 24
    //   515: iconst_0
    //   516: anewarray 100	java/lang/Object
    //   519: astore 25
    //   521: aload 24
    //   523: aconst_null
    //   524: aload 25
    //   526: invokevirtual 106	java/lang/reflect/Method:invoke	(Ljava/lang/Object;[Ljava/lang/Object;)Ljava/lang/Object;
    //   529: astore 27
    //   531: aload 27
    //   533: checkcast 108	java/lang/Integer
    //   536: invokevirtual 112	java/lang/Integer:intValue	()I
    //   539: getstatic 80	uuuuuu/wwwnww:bccc0063cc006300630063	I
    //   542: iadd
    //   543: istore 28
    //   545: ldc 2
    //   547: ldc_w 265
    //   550: bipush 24
    //   552: bipush 28
    //   554: iconst_1
    //   555: invokestatic 92	xxxxxx/uxxxxx:bbbb0062b0062b0062b0062	(Ljava/lang/String;CCC)Ljava/lang/String;
    //   558: iconst_0
    //   559: anewarray 94	java/lang/Class
    //   562: invokevirtual 98	java/lang/Class:getMethod	(Ljava/lang/String;[Ljava/lang/Class;)Ljava/lang/reflect/Method;
    //   565: astore 29
    //   567: iconst_0
    //   568: anewarray 100	java/lang/Object
    //   571: astore 30
    //   573: aload 29
    //   575: aconst_null
    //   576: aload 30
    //   578: invokevirtual 106	java/lang/reflect/Method:invoke	(Ljava/lang/Object;[Ljava/lang/Object;)Ljava/lang/Object;
    //   581: astore 32
    //   583: iload 28
    //   585: aload 32
    //   587: checkcast 108	java/lang/Integer
    //   590: invokevirtual 112	java/lang/Integer:intValue	()I
    //   593: imul
    //   594: getstatic 82	uuuuuu/wwwnww:b0063cc0063cc006300630063	I
    //   597: irem
    //   598: getstatic 84	uuuuuu/wwwnww:bc0063c0063cc006300630063	I
    //   601: if_icmpeq +57 -> 658
    //   604: bipush 23
    //   606: putstatic 78	uuuuuu/wwwnww:b006300630063ccc006300630063	I
    //   609: ldc 2
    //   611: ldc_w 267
    //   614: bipush 37
    //   616: bipush 17
    //   618: iconst_0
    //   619: invokestatic 92	xxxxxx/uxxxxx:bbbb0062b0062b0062b0062	(Ljava/lang/String;CCC)Ljava/lang/String;
    //   622: iconst_0
    //   623: anewarray 94	java/lang/Class
    //   626: invokevirtual 98	java/lang/Class:getMethod	(Ljava/lang/String;[Ljava/lang/Class;)Ljava/lang/reflect/Method;
    //   629: astore 33
    //   631: iconst_0
    //   632: anewarray 100	java/lang/Object
    //   635: astore 34
    //   637: aload 33
    //   639: aconst_null
    //   640: aload 34
    //   642: invokevirtual 106	java/lang/reflect/Method:invoke	(Ljava/lang/Object;[Ljava/lang/Object;)Ljava/lang/Object;
    //   645: astore 36
    //   647: aload 36
    //   649: checkcast 108	java/lang/Integer
    //   652: invokevirtual 112	java/lang/Integer:intValue	()I
    //   655: putstatic 84	uuuuuu/wwwnww:bc0063c0063cc006300630063	I
    //   658: aload 22
    //   660: aload 23
    //   662: invokevirtual 147	com/db/pwcc/dbmobile/ibanbic/items/AccountItem:setAccountType	(Lcom/db/pwcc/dbmobile/ibanbic/items/AccountItem$nwwwww;)V
    //   665: aload 22
    //   667: areturn
    //   668: astore 15
    //   670: aload 15
    //   672: invokevirtual 122	java/lang/reflect/InvocationTargetException:getCause	()Ljava/lang/Throwable;
    //   675: athrow
    //   676: astore 5
    //   678: aload 5
    //   680: invokevirtual 122	java/lang/reflect/InvocationTargetException:getCause	()Ljava/lang/Throwable;
    //   683: athrow
    //   684: astore 11
    //   686: aload 11
    //   688: invokevirtual 122	java/lang/reflect/InvocationTargetException:getCause	()Ljava/lang/Throwable;
    //   691: athrow
    //   692: astore 40
    //   694: aload 40
    //   696: invokevirtual 122	java/lang/reflect/InvocationTargetException:getCause	()Ljava/lang/Throwable;
    //   699: athrow
    //   700: astore 20
    //   702: aload 20
    //   704: invokevirtual 122	java/lang/reflect/InvocationTargetException:getCause	()Ljava/lang/Throwable;
    //   707: athrow
    //   708: astore 26
    //   710: aload 26
    //   712: invokevirtual 122	java/lang/reflect/InvocationTargetException:getCause	()Ljava/lang/Throwable;
    //   715: athrow
    //   716: astore 31
    //   718: aload 31
    //   720: invokevirtual 122	java/lang/reflect/InvocationTargetException:getCause	()Ljava/lang/Throwable;
    //   723: athrow
    //   724: astore 35
    //   726: aload 35
    //   728: invokevirtual 122	java/lang/reflect/InvocationTargetException:getCause	()Ljava/lang/Throwable;
    //   731: athrow
    //   732: astore 44
    //   734: aload 44
    //   736: invokevirtual 122	java/lang/reflect/InvocationTargetException:getCause	()Ljava/lang/Throwable;
    //   739: athrow
    //   740: astore 48
    //   742: aload 48
    //   744: invokevirtual 122	java/lang/reflect/InvocationTargetException:getCause	()Ljava/lang/Throwable;
    //   747: athrow
    //   748: astore 52
    //   750: aload 52
    //   752: invokevirtual 122	java/lang/reflect/InvocationTargetException:getCause	()Ljava/lang/Throwable;
    //   755: athrow
    // Local variable table:
    //   start	length	slot	name	signature
    //   0	756	0	this	wwwnww
    //   0	756	1	paramAccount	com.db.pwcc.dbmobile.model.banking.Account
    //   0	756	2	paramString	String
    //   20	8	3	localMethod1	java.lang.reflect.Method
    //   25	5	4	arrayOfObject1	Object[]
    //   676	3	5	localInvocationTargetException1	java.lang.reflect.InvocationTargetException
    //   34	3	6	localObject1	Object
    //   48	229	7	i	int
    //   53	55	8	j	int
    //   76	9	9	localMethod2	java.lang.reflect.Method
    //   82	6	10	arrayOfObject2	Object[]
    //   684	3	11	localInvocationTargetException2	java.lang.reflect.InvocationTargetException
    //   92	7	12	localObject2	Object
    //   248	9	13	localMethod3	java.lang.reflect.Method
    //   254	6	14	arrayOfObject3	Object[]
    //   668	3	15	localInvocationTargetException3	java.lang.reflect.InvocationTargetException
    //   264	5	16	localObject3	Object
    //   277	51	17	k	int
    //   299	9	18	localMethod4	java.lang.reflect.Method
    //   305	6	19	arrayOfObject4	Object[]
    //   700	3	20	localInvocationTargetException4	java.lang.reflect.InvocationTargetException
    //   315	5	21	localObject4	Object
    //   482	184	22	localAccountItem	AccountItem
    //   493	168	23	localNwwwww	com.db.pwcc.dbmobile.ibanbic.items.AccountItem.nwwwww
    //   513	9	24	localMethod5	java.lang.reflect.Method
    //   519	6	25	arrayOfObject5	Object[]
    //   708	3	26	localInvocationTargetException5	java.lang.reflect.InvocationTargetException
    //   529	3	27	localObject5	Object
    //   543	51	28	m	int
    //   565	9	29	localMethod6	java.lang.reflect.Method
    //   571	6	30	arrayOfObject6	Object[]
    //   716	3	31	localInvocationTargetException6	java.lang.reflect.InvocationTargetException
    //   581	5	32	localObject6	Object
    //   629	9	33	localMethod7	java.lang.reflect.Method
    //   635	6	34	arrayOfObject7	Object[]
    //   724	3	35	localInvocationTargetException7	java.lang.reflect.InvocationTargetException
    //   645	3	36	localObject7	Object
    //   347	11	37	n	int
    //   398	9	38	localMethod8	java.lang.reflect.Method
    //   404	6	39	arrayOfObject8	Object[]
    //   692	3	40	localInvocationTargetException8	java.lang.reflect.InvocationTargetException
    //   414	3	41	localObject8	Object
    //   445	9	42	localMethod9	java.lang.reflect.Method
    //   451	6	43	arrayOfObject9	Object[]
    //   732	3	44	localInvocationTargetException9	java.lang.reflect.InvocationTargetException
    //   461	3	45	localObject9	Object
    //   153	9	46	localMethod10	java.lang.reflect.Method
    //   159	6	47	arrayOfObject10	Object[]
    //   740	3	48	localInvocationTargetException10	java.lang.reflect.InvocationTargetException
    //   169	3	49	localObject10	Object
    //   202	9	50	localMethod11	java.lang.reflect.Method
    //   208	6	51	arrayOfObject11	Object[]
    //   748	3	52	localInvocationTargetException11	java.lang.reflect.InvocationTargetException
    //   218	3	53	localObject11	Object
    // Exception table:
    //   from	to	target	type
    //   256	266	668	java/lang/reflect/InvocationTargetException
    //   27	36	676	java/lang/reflect/InvocationTargetException
    //   84	94	684	java/lang/reflect/InvocationTargetException
    //   406	416	692	java/lang/reflect/InvocationTargetException
    //   307	317	700	java/lang/reflect/InvocationTargetException
    //   521	531	708	java/lang/reflect/InvocationTargetException
    //   573	583	716	java/lang/reflect/InvocationTargetException
    //   637	647	724	java/lang/reflect/InvocationTargetException
    //   453	463	732	java/lang/reflect/InvocationTargetException
    //   161	171	740	java/lang/reflect/InvocationTargetException
    //   210	220	748	java/lang/reflect/InvocationTargetException
  }
  
  /* Error */
  public void b0061aa00610061aaa0061a(com.db.pwcc.dbmobile.model.profile.Profile paramProfile)
  {
    // Byte code:
    //   0: aload_0
    //   1: getfield 76	uuuuuu/wwwnww:bnnnnn006E006E006En	Luuuuuu/ttssst$tsssst;
    //   4: astore_2
    //   5: getstatic 78	uuuuuu/wwwnww:b006300630063ccc006300630063	I
    //   8: istore_3
    //   9: iload_3
    //   10: iload_3
    //   11: getstatic 80	uuuuuu/wwwnww:bccc0063cc006300630063	I
    //   14: iadd
    //   15: imul
    //   16: istore 4
    //   18: getstatic 78	uuuuuu/wwwnww:b006300630063ccc006300630063	I
    //   21: istore 5
    //   23: iload 5
    //   25: iload 5
    //   27: getstatic 80	uuuuuu/wwwnww:bccc0063cc006300630063	I
    //   30: iadd
    //   31: imul
    //   32: getstatic 82	uuuuuu/wwwnww:b0063cc0063cc006300630063	I
    //   35: irem
    //   36: tableswitch	default:+20->56, 0:+72->108
    //   56: bipush 62
    //   58: putstatic 78	uuuuuu/wwwnww:b006300630063ccc006300630063	I
    //   61: ldc 2
    //   63: ldc_w 271
    //   66: bipush 28
    //   68: iconst_1
    //   69: invokestatic 118	xxxxxx/uxxxxx:bb00620062bb0062b0062b0062	(Ljava/lang/String;CC)Ljava/lang/String;
    //   72: iconst_0
    //   73: anewarray 94	java/lang/Class
    //   76: invokevirtual 98	java/lang/Class:getMethod	(Ljava/lang/String;[Ljava/lang/Class;)Ljava/lang/reflect/Method;
    //   79: astore 24
    //   81: iconst_0
    //   82: anewarray 100	java/lang/Object
    //   85: astore 25
    //   87: aload 24
    //   89: aconst_null
    //   90: aload 25
    //   92: invokevirtual 106	java/lang/reflect/Method:invoke	(Ljava/lang/Object;[Ljava/lang/Object;)Ljava/lang/Object;
    //   95: astore 27
    //   97: aload 27
    //   99: checkcast 108	java/lang/Integer
    //   102: invokevirtual 112	java/lang/Integer:intValue	()I
    //   105: putstatic 84	uuuuuu/wwwnww:bc0063c0063cc006300630063	I
    //   108: ldc 2
    //   110: ldc_w 273
    //   113: sipush 243
    //   116: iconst_4
    //   117: invokestatic 118	xxxxxx/uxxxxx:bb00620062bb0062b0062b0062	(Ljava/lang/String;CC)Ljava/lang/String;
    //   120: iconst_0
    //   121: anewarray 94	java/lang/Class
    //   124: invokevirtual 98	java/lang/Class:getMethod	(Ljava/lang/String;[Ljava/lang/Class;)Ljava/lang/reflect/Method;
    //   127: astore 6
    //   129: iconst_0
    //   130: anewarray 100	java/lang/Object
    //   133: astore 7
    //   135: aload 6
    //   137: aconst_null
    //   138: aload 7
    //   140: invokevirtual 106	java/lang/reflect/Method:invoke	(Ljava/lang/Object;[Ljava/lang/Object;)Ljava/lang/Object;
    //   143: astore 9
    //   145: iload 4
    //   147: aload 9
    //   149: checkcast 108	java/lang/Integer
    //   152: invokevirtual 112	java/lang/Integer:intValue	()I
    //   155: irem
    //   156: tableswitch	default:+20->176, 0:+161->317
    //   176: bipush 36
    //   178: putstatic 78	uuuuuu/wwwnww:b006300630063ccc006300630063	I
    //   181: bipush 99
    //   183: putstatic 84	uuuuuu/wwwnww:bc0063c0063cc006300630063	I
    //   186: getstatic 78	uuuuuu/wwwnww:b006300630063ccc006300630063	I
    //   189: istore 15
    //   191: ldc 2
    //   193: ldc_w 275
    //   196: sipush 211
    //   199: iconst_2
    //   200: invokestatic 118	xxxxxx/uxxxxx:bb00620062bb0062b0062b0062	(Ljava/lang/String;CC)Ljava/lang/String;
    //   203: iconst_0
    //   204: anewarray 94	java/lang/Class
    //   207: invokevirtual 98	java/lang/Class:getMethod	(Ljava/lang/String;[Ljava/lang/Class;)Ljava/lang/reflect/Method;
    //   210: astore 16
    //   212: iconst_0
    //   213: anewarray 100	java/lang/Object
    //   216: astore 17
    //   218: aload 16
    //   220: aconst_null
    //   221: aload 17
    //   223: invokevirtual 106	java/lang/reflect/Method:invoke	(Ljava/lang/Object;[Ljava/lang/Object;)Ljava/lang/Object;
    //   226: astore 19
    //   228: iload 15
    //   230: iload 15
    //   232: aload 19
    //   234: checkcast 108	java/lang/Integer
    //   237: invokevirtual 112	java/lang/Integer:intValue	()I
    //   240: iadd
    //   241: imul
    //   242: getstatic 82	uuuuuu/wwwnww:b0063cc0063cc006300630063	I
    //   245: irem
    //   246: tableswitch	default:+18->264, 0:+71->317
    //   264: bipush 61
    //   266: putstatic 78	uuuuuu/wwwnww:b006300630063ccc006300630063	I
    //   269: ldc 2
    //   271: ldc_w 277
    //   274: sipush 203
    //   277: iconst_0
    //   278: invokestatic 118	xxxxxx/uxxxxx:bb00620062bb0062b0062b0062	(Ljava/lang/String;CC)Ljava/lang/String;
    //   281: iconst_0
    //   282: anewarray 94	java/lang/Class
    //   285: invokevirtual 98	java/lang/Class:getMethod	(Ljava/lang/String;[Ljava/lang/Class;)Ljava/lang/reflect/Method;
    //   288: astore 20
    //   290: iconst_0
    //   291: anewarray 100	java/lang/Object
    //   294: astore 21
    //   296: aload 20
    //   298: aconst_null
    //   299: aload 21
    //   301: invokevirtual 106	java/lang/reflect/Method:invoke	(Ljava/lang/Object;[Ljava/lang/Object;)Ljava/lang/Object;
    //   304: astore 23
    //   306: aload 23
    //   308: checkcast 108	java/lang/Integer
    //   311: invokevirtual 112	java/lang/Integer:intValue	()I
    //   314: putstatic 84	uuuuuu/wwwnww:bc0063c0063cc006300630063	I
    //   317: aload_2
    //   318: checkcast 279	uuuuuu/wnwnww$nwwnww
    //   321: aload_1
    //   322: invokeinterface 282 2 0
    //   327: getstatic 78	uuuuuu/wwwnww:b006300630063ccc006300630063	I
    //   330: getstatic 80	uuuuuu/wwwnww:bccc0063cc006300630063	I
    //   333: iadd
    //   334: getstatic 78	uuuuuu/wwwnww:b006300630063ccc006300630063	I
    //   337: imul
    //   338: istore 10
    //   340: ldc 2
    //   342: ldc_w 284
    //   345: bipush 123
    //   347: iconst_0
    //   348: invokestatic 118	xxxxxx/uxxxxx:bb00620062bb0062b0062b0062	(Ljava/lang/String;CC)Ljava/lang/String;
    //   351: iconst_0
    //   352: anewarray 94	java/lang/Class
    //   355: invokevirtual 98	java/lang/Class:getMethod	(Ljava/lang/String;[Ljava/lang/Class;)Ljava/lang/reflect/Method;
    //   358: astore 11
    //   360: iconst_0
    //   361: anewarray 100	java/lang/Object
    //   364: astore 12
    //   366: aload 11
    //   368: aconst_null
    //   369: aload 12
    //   371: invokevirtual 106	java/lang/reflect/Method:invoke	(Ljava/lang/Object;[Ljava/lang/Object;)Ljava/lang/Object;
    //   374: astore 14
    //   376: iload 10
    //   378: aload 14
    //   380: checkcast 108	java/lang/Integer
    //   383: invokevirtual 112	java/lang/Integer:intValue	()I
    //   386: irem
    //   387: getstatic 84	uuuuuu/wwwnww:bc0063c0063cc006300630063	I
    //   390: if_icmpeq +13 -> 403
    //   393: bipush 70
    //   395: putstatic 78	uuuuuu/wwwnww:b006300630063ccc006300630063	I
    //   398: bipush 8
    //   400: putstatic 84	uuuuuu/wwwnww:bc0063c0063cc006300630063	I
    //   403: return
    //   404: astore 13
    //   406: aload 13
    //   408: invokevirtual 122	java/lang/reflect/InvocationTargetException:getCause	()Ljava/lang/Throwable;
    //   411: athrow
    //   412: astore 8
    //   414: aload 8
    //   416: invokevirtual 122	java/lang/reflect/InvocationTargetException:getCause	()Ljava/lang/Throwable;
    //   419: athrow
    //   420: astore 18
    //   422: aload 18
    //   424: invokevirtual 122	java/lang/reflect/InvocationTargetException:getCause	()Ljava/lang/Throwable;
    //   427: athrow
    //   428: astore 26
    //   430: aload 26
    //   432: invokevirtual 122	java/lang/reflect/InvocationTargetException:getCause	()Ljava/lang/Throwable;
    //   435: athrow
    //   436: astore 22
    //   438: aload 22
    //   440: invokevirtual 122	java/lang/reflect/InvocationTargetException:getCause	()Ljava/lang/Throwable;
    //   443: athrow
    // Local variable table:
    //   start	length	slot	name	signature
    //   0	444	0	this	wwwnww
    //   0	444	1	paramProfile	com.db.pwcc.dbmobile.model.profile.Profile
    //   4	314	2	localTsssst	ttssst.tsssst
    //   8	8	3	i	int
    //   16	140	4	j	int
    //   21	11	5	k	int
    //   127	9	6	localMethod1	java.lang.reflect.Method
    //   133	6	7	arrayOfObject1	Object[]
    //   412	3	8	localInvocationTargetException1	java.lang.reflect.InvocationTargetException
    //   143	5	9	localObject1	Object
    //   338	49	10	m	int
    //   358	9	11	localMethod2	java.lang.reflect.Method
    //   364	6	12	arrayOfObject2	Object[]
    //   404	3	13	localInvocationTargetException2	java.lang.reflect.InvocationTargetException
    //   374	5	14	localObject2	Object
    //   189	53	15	n	int
    //   210	9	16	localMethod3	java.lang.reflect.Method
    //   216	6	17	arrayOfObject3	Object[]
    //   420	3	18	localInvocationTargetException3	java.lang.reflect.InvocationTargetException
    //   226	7	19	localObject3	Object
    //   288	9	20	localMethod4	java.lang.reflect.Method
    //   294	6	21	arrayOfObject4	Object[]
    //   436	3	22	localInvocationTargetException4	java.lang.reflect.InvocationTargetException
    //   304	3	23	localObject4	Object
    //   79	9	24	localMethod5	java.lang.reflect.Method
    //   85	6	25	arrayOfObject5	Object[]
    //   428	3	26	localInvocationTargetException5	java.lang.reflect.InvocationTargetException
    //   95	3	27	localObject5	Object
    // Exception table:
    //   from	to	target	type
    //   366	376	404	java/lang/reflect/InvocationTargetException
    //   135	145	412	java/lang/reflect/InvocationTargetException
    //   218	228	420	java/lang/reflect/InvocationTargetException
    //   87	97	428	java/lang/reflect/InvocationTargetException
    //   296	306	436	java/lang/reflect/InvocationTargetException
  }
  
  /* Error */
  public void b0071007100710071qqq00710071q()
  {
    // Byte code:
    //   0: aload_0
    //   1: getfield 289	uuuuuu/wwwnww:b006E006E006E006E006En006E006En	Luuuuuu/hyhyhh;
    //   4: invokevirtual 294	uuuuuu/hyhyhh:b0070pp007000700070p007000700070	()Ljava/lang/String;
    //   7: ifnull +16 -> 23
    //   10: aload_0
    //   11: getfield 289	uuuuuu/wwwnww:b006E006E006E006E006En006E006En	Luuuuuu/hyhyhh;
    //   14: invokevirtual 294	uuuuuu/hyhyhh:b0070pp007000700070p007000700070	()Ljava/lang/String;
    //   17: invokevirtual 298	java/lang/String:isEmpty	()Z
    //   20: ifeq +4 -> 24
    //   23: return
    //   24: aload_0
    //   25: getfield 41	uuuuuu/wwwnww:b00630063cccc006300630063	Luuuuuu/fmfmfm;
    //   28: astore_1
    //   29: aload_0
    //   30: getfield 289	uuuuuu/wwwnww:b006E006E006E006E006En006E006En	Luuuuuu/hyhyhh;
    //   33: astore_2
    //   34: getstatic 78	uuuuuu/wwwnww:b006300630063ccc006300630063	I
    //   37: istore_3
    //   38: getstatic 78	uuuuuu/wwwnww:b006300630063ccc006300630063	I
    //   41: getstatic 80	uuuuuu/wwwnww:bccc0063cc006300630063	I
    //   44: iadd
    //   45: getstatic 78	uuuuuu/wwwnww:b006300630063ccc006300630063	I
    //   48: imul
    //   49: getstatic 82	uuuuuu/wwwnww:b0063cc0063cc006300630063	I
    //   52: irem
    //   53: getstatic 84	uuuuuu/wwwnww:bc0063c0063cc006300630063	I
    //   56: if_icmpeq +99 -> 155
    //   59: ldc 2
    //   61: ldc_w 300
    //   64: sipush 252
    //   67: iconst_0
    //   68: invokestatic 118	xxxxxx/uxxxxx:bb00620062bb0062b0062b0062	(Ljava/lang/String;CC)Ljava/lang/String;
    //   71: iconst_0
    //   72: anewarray 94	java/lang/Class
    //   75: invokevirtual 98	java/lang/Class:getMethod	(Ljava/lang/String;[Ljava/lang/Class;)Ljava/lang/reflect/Method;
    //   78: astore 25
    //   80: iconst_0
    //   81: anewarray 100	java/lang/Object
    //   84: astore 26
    //   86: aload 25
    //   88: aconst_null
    //   89: aload 26
    //   91: invokevirtual 106	java/lang/reflect/Method:invoke	(Ljava/lang/Object;[Ljava/lang/Object;)Ljava/lang/Object;
    //   94: astore 28
    //   96: aload 28
    //   98: checkcast 108	java/lang/Integer
    //   101: invokevirtual 112	java/lang/Integer:intValue	()I
    //   104: putstatic 78	uuuuuu/wwwnww:b006300630063ccc006300630063	I
    //   107: ldc 2
    //   109: ldc_w 302
    //   112: sipush 226
    //   115: iconst_2
    //   116: invokestatic 118	xxxxxx/uxxxxx:bb00620062bb0062b0062b0062	(Ljava/lang/String;CC)Ljava/lang/String;
    //   119: iconst_0
    //   120: anewarray 94	java/lang/Class
    //   123: invokevirtual 98	java/lang/Class:getMethod	(Ljava/lang/String;[Ljava/lang/Class;)Ljava/lang/reflect/Method;
    //   126: astore 29
    //   128: iconst_0
    //   129: anewarray 100	java/lang/Object
    //   132: astore 30
    //   134: aload 29
    //   136: aconst_null
    //   137: aload 30
    //   139: invokevirtual 106	java/lang/reflect/Method:invoke	(Ljava/lang/Object;[Ljava/lang/Object;)Ljava/lang/Object;
    //   142: astore 32
    //   144: aload 32
    //   146: checkcast 108	java/lang/Integer
    //   149: invokevirtual 112	java/lang/Integer:intValue	()I
    //   152: putstatic 84	uuuuuu/wwwnww:bc0063c0063cc006300630063	I
    //   155: iload_3
    //   156: iload_3
    //   157: getstatic 80	uuuuuu/wwwnww:bccc0063cc006300630063	I
    //   160: iadd
    //   161: imul
    //   162: getstatic 82	uuuuuu/wwwnww:b0063cc0063cc006300630063	I
    //   165: irem
    //   166: tableswitch	default:+18->184, 0:+324->490
    //   184: ldc 2
    //   186: ldc_w 304
    //   189: sipush 224
    //   192: iconst_0
    //   193: invokestatic 118	xxxxxx/uxxxxx:bb00620062bb0062b0062b0062	(Ljava/lang/String;CC)Ljava/lang/String;
    //   196: iconst_0
    //   197: anewarray 94	java/lang/Class
    //   200: invokevirtual 98	java/lang/Class:getMethod	(Ljava/lang/String;[Ljava/lang/Class;)Ljava/lang/reflect/Method;
    //   203: astore 4
    //   205: iconst_0
    //   206: anewarray 100	java/lang/Object
    //   209: astore 5
    //   211: aload 4
    //   213: aconst_null
    //   214: aload 5
    //   216: invokevirtual 106	java/lang/reflect/Method:invoke	(Ljava/lang/Object;[Ljava/lang/Object;)Ljava/lang/Object;
    //   219: astore 7
    //   221: aload 7
    //   223: checkcast 108	java/lang/Integer
    //   226: invokevirtual 112	java/lang/Integer:intValue	()I
    //   229: putstatic 78	uuuuuu/wwwnww:b006300630063ccc006300630063	I
    //   232: bipush 29
    //   234: putstatic 84	uuuuuu/wwwnww:bc0063c0063cc006300630063	I
    //   237: getstatic 78	uuuuuu/wwwnww:b006300630063ccc006300630063	I
    //   240: istore 8
    //   242: ldc 2
    //   244: ldc_w 306
    //   247: sipush 181
    //   250: sipush 156
    //   253: iconst_0
    //   254: invokestatic 92	xxxxxx/uxxxxx:bbbb0062b0062b0062b0062	(Ljava/lang/String;CCC)Ljava/lang/String;
    //   257: iconst_0
    //   258: anewarray 94	java/lang/Class
    //   261: invokevirtual 98	java/lang/Class:getMethod	(Ljava/lang/String;[Ljava/lang/Class;)Ljava/lang/reflect/Method;
    //   264: astore 9
    //   266: iconst_0
    //   267: anewarray 100	java/lang/Object
    //   270: astore 10
    //   272: aload 9
    //   274: aconst_null
    //   275: aload 10
    //   277: invokevirtual 106	java/lang/reflect/Method:invoke	(Ljava/lang/Object;[Ljava/lang/Object;)Ljava/lang/Object;
    //   280: astore 12
    //   282: iload 8
    //   284: iload 8
    //   286: aload 12
    //   288: checkcast 108	java/lang/Integer
    //   291: invokevirtual 112	java/lang/Integer:intValue	()I
    //   294: iadd
    //   295: imul
    //   296: getstatic 82	uuuuuu/wwwnww:b0063cc0063cc006300630063	I
    //   299: irem
    //   300: tableswitch	default:+20->320, 0:+114->414
    //   320: ldc 2
    //   322: ldc_w 308
    //   325: bipush 48
    //   327: iconst_3
    //   328: invokestatic 118	xxxxxx/uxxxxx:bb00620062bb0062b0062b0062	(Ljava/lang/String;CC)Ljava/lang/String;
    //   331: iconst_0
    //   332: anewarray 94	java/lang/Class
    //   335: invokevirtual 98	java/lang/Class:getMethod	(Ljava/lang/String;[Ljava/lang/Class;)Ljava/lang/reflect/Method;
    //   338: astore 17
    //   340: iconst_0
    //   341: anewarray 100	java/lang/Object
    //   344: astore 18
    //   346: aload 17
    //   348: aconst_null
    //   349: aload 18
    //   351: invokevirtual 106	java/lang/reflect/Method:invoke	(Ljava/lang/Object;[Ljava/lang/Object;)Ljava/lang/Object;
    //   354: astore 20
    //   356: aload 20
    //   358: checkcast 108	java/lang/Integer
    //   361: invokevirtual 112	java/lang/Integer:intValue	()I
    //   364: putstatic 78	uuuuuu/wwwnww:b006300630063ccc006300630063	I
    //   367: ldc 2
    //   369: ldc_w 310
    //   372: bipush 42
    //   374: iconst_1
    //   375: invokestatic 118	xxxxxx/uxxxxx:bb00620062bb0062b0062b0062	(Ljava/lang/String;CC)Ljava/lang/String;
    //   378: iconst_0
    //   379: anewarray 94	java/lang/Class
    //   382: invokevirtual 98	java/lang/Class:getMethod	(Ljava/lang/String;[Ljava/lang/Class;)Ljava/lang/reflect/Method;
    //   385: astore 21
    //   387: iconst_0
    //   388: anewarray 100	java/lang/Object
    //   391: astore 22
    //   393: aload 21
    //   395: aconst_null
    //   396: aload 22
    //   398: invokevirtual 106	java/lang/reflect/Method:invoke	(Ljava/lang/Object;[Ljava/lang/Object;)Ljava/lang/Object;
    //   401: astore 24
    //   403: aload 24
    //   405: checkcast 108	java/lang/Integer
    //   408: invokevirtual 112	java/lang/Integer:intValue	()I
    //   411: putstatic 84	uuuuuu/wwwnww:bc0063c0063cc006300630063	I
    //   414: getstatic 78	uuuuuu/wwwnww:b006300630063ccc006300630063	I
    //   417: getstatic 80	uuuuuu/wwwnww:bccc0063cc006300630063	I
    //   420: iadd
    //   421: getstatic 78	uuuuuu/wwwnww:b006300630063ccc006300630063	I
    //   424: imul
    //   425: getstatic 82	uuuuuu/wwwnww:b0063cc0063cc006300630063	I
    //   428: irem
    //   429: getstatic 84	uuuuuu/wwwnww:bc0063c0063cc006300630063	I
    //   432: if_icmpeq +58 -> 490
    //   435: ldc 2
    //   437: ldc_w 312
    //   440: sipush 189
    //   443: sipush 243
    //   446: iconst_2
    //   447: invokestatic 92	xxxxxx/uxxxxx:bbbb0062b0062b0062b0062	(Ljava/lang/String;CCC)Ljava/lang/String;
    //   450: iconst_0
    //   451: anewarray 94	java/lang/Class
    //   454: invokevirtual 98	java/lang/Class:getMethod	(Ljava/lang/String;[Ljava/lang/Class;)Ljava/lang/reflect/Method;
    //   457: astore 13
    //   459: iconst_0
    //   460: anewarray 100	java/lang/Object
    //   463: astore 14
    //   465: aload 13
    //   467: aconst_null
    //   468: aload 14
    //   470: invokevirtual 106	java/lang/reflect/Method:invoke	(Ljava/lang/Object;[Ljava/lang/Object;)Ljava/lang/Object;
    //   473: astore 16
    //   475: aload 16
    //   477: checkcast 108	java/lang/Integer
    //   480: invokevirtual 112	java/lang/Integer:intValue	()I
    //   483: putstatic 78	uuuuuu/wwwnww:b006300630063ccc006300630063	I
    //   486: iconst_3
    //   487: putstatic 84	uuuuuu/wwwnww:bc0063c0063cc006300630063	I
    //   490: aload_1
    //   491: aload_0
    //   492: aload_2
    //   493: invokevirtual 294	uuuuuu/hyhyhh:b0070pp007000700070p007000700070	()Ljava/lang/String;
    //   496: invokevirtual 316	uuuuuu/fmfmfm:b0070p007000700070pp00700070p	(Luuuuuu/vpvpvp$pvvpvp;Ljava/lang/String;)V
    //   499: return
    //   500: astore 6
    //   502: aload 6
    //   504: invokevirtual 122	java/lang/reflect/InvocationTargetException:getCause	()Ljava/lang/Throwable;
    //   507: athrow
    //   508: astore 11
    //   510: aload 11
    //   512: invokevirtual 122	java/lang/reflect/InvocationTargetException:getCause	()Ljava/lang/Throwable;
    //   515: athrow
    //   516: astore 19
    //   518: aload 19
    //   520: invokevirtual 122	java/lang/reflect/InvocationTargetException:getCause	()Ljava/lang/Throwable;
    //   523: athrow
    //   524: astore 23
    //   526: aload 23
    //   528: invokevirtual 122	java/lang/reflect/InvocationTargetException:getCause	()Ljava/lang/Throwable;
    //   531: athrow
    //   532: astore 15
    //   534: aload 15
    //   536: invokevirtual 122	java/lang/reflect/InvocationTargetException:getCause	()Ljava/lang/Throwable;
    //   539: athrow
    //   540: astore 27
    //   542: aload 27
    //   544: invokevirtual 122	java/lang/reflect/InvocationTargetException:getCause	()Ljava/lang/Throwable;
    //   547: athrow
    //   548: astore 31
    //   550: aload 31
    //   552: invokevirtual 122	java/lang/reflect/InvocationTargetException:getCause	()Ljava/lang/Throwable;
    //   555: athrow
    // Local variable table:
    //   start	length	slot	name	signature
    //   0	556	0	this	wwwnww
    //   28	463	1	localFmfmfm	fmfmfm
    //   33	460	2	localHyhyhh	hyhyhh
    //   37	125	3	i	int
    //   203	9	4	localMethod1	java.lang.reflect.Method
    //   209	6	5	arrayOfObject1	Object[]
    //   500	3	6	localInvocationTargetException1	java.lang.reflect.InvocationTargetException
    //   219	3	7	localObject1	Object
    //   240	56	8	j	int
    //   264	9	9	localMethod2	java.lang.reflect.Method
    //   270	6	10	arrayOfObject2	Object[]
    //   508	3	11	localInvocationTargetException2	java.lang.reflect.InvocationTargetException
    //   280	7	12	localObject2	Object
    //   457	9	13	localMethod3	java.lang.reflect.Method
    //   463	6	14	arrayOfObject3	Object[]
    //   532	3	15	localInvocationTargetException3	java.lang.reflect.InvocationTargetException
    //   473	3	16	localObject3	Object
    //   338	9	17	localMethod4	java.lang.reflect.Method
    //   344	6	18	arrayOfObject4	Object[]
    //   516	3	19	localInvocationTargetException4	java.lang.reflect.InvocationTargetException
    //   354	3	20	localObject4	Object
    //   385	9	21	localMethod5	java.lang.reflect.Method
    //   391	6	22	arrayOfObject5	Object[]
    //   524	3	23	localInvocationTargetException5	java.lang.reflect.InvocationTargetException
    //   401	3	24	localObject5	Object
    //   78	9	25	localMethod6	java.lang.reflect.Method
    //   84	6	26	arrayOfObject6	Object[]
    //   540	3	27	localInvocationTargetException6	java.lang.reflect.InvocationTargetException
    //   94	3	28	localObject6	Object
    //   126	9	29	localMethod7	java.lang.reflect.Method
    //   132	6	30	arrayOfObject7	Object[]
    //   548	3	31	localInvocationTargetException7	java.lang.reflect.InvocationTargetException
    //   142	3	32	localObject7	Object
    // Exception table:
    //   from	to	target	type
    //   211	221	500	java/lang/reflect/InvocationTargetException
    //   272	282	508	java/lang/reflect/InvocationTargetException
    //   346	356	516	java/lang/reflect/InvocationTargetException
    //   393	403	524	java/lang/reflect/InvocationTargetException
    //   465	475	532	java/lang/reflect/InvocationTargetException
    //   86	96	540	java/lang/reflect/InvocationTargetException
    //   134	144	548	java/lang/reflect/InvocationTargetException
  }
  
  /* Error */
  public void baaa00610061aaa0061a(com.db.pwcc.dbmobile.model.error.DbError paramDbError)
  {
    // Byte code:
    //   0: getstatic 78	uuuuuu/wwwnww:b006300630063ccc006300630063	I
    //   3: istore_2
    //   4: iload_2
    //   5: iload_2
    //   6: getstatic 80	uuuuuu/wwwnww:bccc0063cc006300630063	I
    //   9: iadd
    //   10: imul
    //   11: getstatic 82	uuuuuu/wwwnww:b0063cc0063cc006300630063	I
    //   14: irem
    //   15: tableswitch	default:+17->32, 0:+27->42
    //   32: bipush 21
    //   34: putstatic 78	uuuuuu/wwwnww:b006300630063ccc006300630063	I
    //   37: bipush 51
    //   39: putstatic 84	uuuuuu/wwwnww:bc0063c0063cc006300630063	I
    //   42: aload_0
    //   43: getfield 76	uuuuuu/wwwnww:bnnnnn006E006E006En	Luuuuuu/ttssst$tsssst;
    //   46: checkcast 279	uuuuuu/wnwnww$nwwnww
    //   49: astore_3
    //   50: getstatic 78	uuuuuu/wwwnww:b006300630063ccc006300630063	I
    //   53: istore 4
    //   55: ldc 2
    //   57: ldc_w 320
    //   60: sipush 173
    //   63: iconst_3
    //   64: invokestatic 118	xxxxxx/uxxxxx:bb00620062bb0062b0062b0062	(Ljava/lang/String;CC)Ljava/lang/String;
    //   67: iconst_0
    //   68: anewarray 94	java/lang/Class
    //   71: invokevirtual 98	java/lang/Class:getMethod	(Ljava/lang/String;[Ljava/lang/Class;)Ljava/lang/reflect/Method;
    //   74: astore 5
    //   76: iconst_0
    //   77: anewarray 100	java/lang/Object
    //   80: astore 6
    //   82: aload 5
    //   84: aconst_null
    //   85: aload 6
    //   87: invokevirtual 106	java/lang/reflect/Method:invoke	(Ljava/lang/Object;[Ljava/lang/Object;)Ljava/lang/Object;
    //   90: astore 8
    //   92: iload 4
    //   94: aload 8
    //   96: checkcast 108	java/lang/Integer
    //   99: invokevirtual 112	java/lang/Integer:intValue	()I
    //   102: iadd
    //   103: getstatic 78	uuuuuu/wwwnww:b006300630063ccc006300630063	I
    //   106: imul
    //   107: getstatic 82	uuuuuu/wwwnww:b0063cc0063cc006300630063	I
    //   110: irem
    //   111: istore 9
    //   113: getstatic 84	uuuuuu/wwwnww:bc0063c0063cc006300630063	I
    //   116: istore 10
    //   118: getstatic 78	uuuuuu/wwwnww:b006300630063ccc006300630063	I
    //   121: istore 11
    //   123: iload 11
    //   125: iload 11
    //   127: getstatic 80	uuuuuu/wwwnww:bccc0063cc006300630063	I
    //   130: iadd
    //   131: imul
    //   132: getstatic 82	uuuuuu/wwwnww:b0063cc0063cc006300630063	I
    //   135: irem
    //   136: tableswitch	default:+20->156, 0:+115->251
    //   156: ldc 2
    //   158: ldc_w 322
    //   161: bipush 67
    //   163: iconst_5
    //   164: invokestatic 118	xxxxxx/uxxxxx:bb00620062bb0062b0062b0062	(Ljava/lang/String;CC)Ljava/lang/String;
    //   167: iconst_0
    //   168: anewarray 94	java/lang/Class
    //   171: invokevirtual 98	java/lang/Class:getMethod	(Ljava/lang/String;[Ljava/lang/Class;)Ljava/lang/reflect/Method;
    //   174: astore 21
    //   176: iconst_0
    //   177: anewarray 100	java/lang/Object
    //   180: astore 22
    //   182: aload 21
    //   184: aconst_null
    //   185: aload 22
    //   187: invokevirtual 106	java/lang/reflect/Method:invoke	(Ljava/lang/Object;[Ljava/lang/Object;)Ljava/lang/Object;
    //   190: astore 24
    //   192: aload 24
    //   194: checkcast 108	java/lang/Integer
    //   197: invokevirtual 112	java/lang/Integer:intValue	()I
    //   200: putstatic 78	uuuuuu/wwwnww:b006300630063ccc006300630063	I
    //   203: ldc 2
    //   205: ldc_w 324
    //   208: sipush 134
    //   211: iconst_5
    //   212: invokestatic 118	xxxxxx/uxxxxx:bb00620062bb0062b0062b0062	(Ljava/lang/String;CC)Ljava/lang/String;
    //   215: iconst_0
    //   216: anewarray 94	java/lang/Class
    //   219: invokevirtual 98	java/lang/Class:getMethod	(Ljava/lang/String;[Ljava/lang/Class;)Ljava/lang/reflect/Method;
    //   222: astore 25
    //   224: iconst_0
    //   225: anewarray 100	java/lang/Object
    //   228: astore 26
    //   230: aload 25
    //   232: aconst_null
    //   233: aload 26
    //   235: invokevirtual 106	java/lang/reflect/Method:invoke	(Ljava/lang/Object;[Ljava/lang/Object;)Ljava/lang/Object;
    //   238: astore 28
    //   240: aload 28
    //   242: checkcast 108	java/lang/Integer
    //   245: invokevirtual 112	java/lang/Integer:intValue	()I
    //   248: putstatic 84	uuuuuu/wwwnww:bc0063c0063cc006300630063	I
    //   251: iload 9
    //   253: iload 10
    //   255: if_icmpeq +148 -> 403
    //   258: getstatic 78	uuuuuu/wwwnww:b006300630063ccc006300630063	I
    //   261: istore 12
    //   263: iload 12
    //   265: iload 12
    //   267: getstatic 80	uuuuuu/wwwnww:bccc0063cc006300630063	I
    //   270: iadd
    //   271: imul
    //   272: getstatic 82	uuuuuu/wwwnww:b0063cc0063cc006300630063	I
    //   275: irem
    //   276: tableswitch	default:+20->296, 0:+75->351
    //   296: ldc 2
    //   298: ldc_w 326
    //   301: bipush 7
    //   303: sipush 212
    //   306: iconst_2
    //   307: invokestatic 92	xxxxxx/uxxxxx:bbbb0062b0062b0062b0062	(Ljava/lang/String;CCC)Ljava/lang/String;
    //   310: iconst_0
    //   311: anewarray 94	java/lang/Class
    //   314: invokevirtual 98	java/lang/Class:getMethod	(Ljava/lang/String;[Ljava/lang/Class;)Ljava/lang/reflect/Method;
    //   317: astore 17
    //   319: iconst_0
    //   320: anewarray 100	java/lang/Object
    //   323: astore 18
    //   325: aload 17
    //   327: aconst_null
    //   328: aload 18
    //   330: invokevirtual 106	java/lang/reflect/Method:invoke	(Ljava/lang/Object;[Ljava/lang/Object;)Ljava/lang/Object;
    //   333: astore 20
    //   335: aload 20
    //   337: checkcast 108	java/lang/Integer
    //   340: invokevirtual 112	java/lang/Integer:intValue	()I
    //   343: putstatic 78	uuuuuu/wwwnww:b006300630063ccc006300630063	I
    //   346: bipush 33
    //   348: putstatic 84	uuuuuu/wwwnww:bc0063c0063cc006300630063	I
    //   351: bipush 82
    //   353: putstatic 78	uuuuuu/wwwnww:b006300630063ccc006300630063	I
    //   356: ldc 2
    //   358: ldc_w 328
    //   361: bipush 106
    //   363: iconst_4
    //   364: invokestatic 118	xxxxxx/uxxxxx:bb00620062bb0062b0062b0062	(Ljava/lang/String;CC)Ljava/lang/String;
    //   367: iconst_0
    //   368: anewarray 94	java/lang/Class
    //   371: invokevirtual 98	java/lang/Class:getMethod	(Ljava/lang/String;[Ljava/lang/Class;)Ljava/lang/reflect/Method;
    //   374: astore 13
    //   376: iconst_0
    //   377: anewarray 100	java/lang/Object
    //   380: astore 14
    //   382: aload 13
    //   384: aconst_null
    //   385: aload 14
    //   387: invokevirtual 106	java/lang/reflect/Method:invoke	(Ljava/lang/Object;[Ljava/lang/Object;)Ljava/lang/Object;
    //   390: astore 16
    //   392: aload 16
    //   394: checkcast 108	java/lang/Integer
    //   397: invokevirtual 112	java/lang/Integer:intValue	()I
    //   400: putstatic 84	uuuuuu/wwwnww:bc0063c0063cc006300630063	I
    //   403: aload_3
    //   404: invokeinterface 331 1 0
    //   409: return
    //   410: astore 15
    //   412: aload 15
    //   414: invokevirtual 122	java/lang/reflect/InvocationTargetException:getCause	()Ljava/lang/Throwable;
    //   417: athrow
    //   418: astore 7
    //   420: aload 7
    //   422: invokevirtual 122	java/lang/reflect/InvocationTargetException:getCause	()Ljava/lang/Throwable;
    //   425: athrow
    //   426: astore 19
    //   428: aload 19
    //   430: invokevirtual 122	java/lang/reflect/InvocationTargetException:getCause	()Ljava/lang/Throwable;
    //   433: athrow
    //   434: astore 23
    //   436: aload 23
    //   438: invokevirtual 122	java/lang/reflect/InvocationTargetException:getCause	()Ljava/lang/Throwable;
    //   441: athrow
    //   442: astore 27
    //   444: aload 27
    //   446: invokevirtual 122	java/lang/reflect/InvocationTargetException:getCause	()Ljava/lang/Throwable;
    //   449: athrow
    // Local variable table:
    //   start	length	slot	name	signature
    //   0	450	0	this	wwwnww
    //   0	450	1	paramDbError	com.db.pwcc.dbmobile.model.error.DbError
    //   3	8	2	i	int
    //   49	355	3	localNwwnww	wnwnww.nwwnww
    //   53	50	4	j	int
    //   74	9	5	localMethod1	java.lang.reflect.Method
    //   80	6	6	arrayOfObject1	Object[]
    //   418	3	7	localInvocationTargetException1	java.lang.reflect.InvocationTargetException
    //   90	5	8	localObject1	Object
    //   111	145	9	k	int
    //   116	140	10	m	int
    //   121	11	11	n	int
    //   261	11	12	i1	int
    //   374	9	13	localMethod2	java.lang.reflect.Method
    //   380	6	14	arrayOfObject2	Object[]
    //   410	3	15	localInvocationTargetException2	java.lang.reflect.InvocationTargetException
    //   390	3	16	localObject2	Object
    //   317	9	17	localMethod3	java.lang.reflect.Method
    //   323	6	18	arrayOfObject3	Object[]
    //   426	3	19	localInvocationTargetException3	java.lang.reflect.InvocationTargetException
    //   333	3	20	localObject3	Object
    //   174	9	21	localMethod4	java.lang.reflect.Method
    //   180	6	22	arrayOfObject4	Object[]
    //   434	3	23	localInvocationTargetException4	java.lang.reflect.InvocationTargetException
    //   190	3	24	localObject4	Object
    //   222	9	25	localMethod5	java.lang.reflect.Method
    //   228	6	26	arrayOfObject5	Object[]
    //   442	3	27	localInvocationTargetException5	java.lang.reflect.InvocationTargetException
    //   238	3	28	localObject5	Object
    // Exception table:
    //   from	to	target	type
    //   382	392	410	java/lang/reflect/InvocationTargetException
    //   82	92	418	java/lang/reflect/InvocationTargetException
    //   325	335	426	java/lang/reflect/InvocationTargetException
    //   182	192	434	java/lang/reflect/InvocationTargetException
    //   230	240	442	java/lang/reflect/InvocationTargetException
  }
  
  public void bqqqq0071qq00710071q(FinancialOverviewData paramFinancialOverviewData) {}
  
  /* Error */
  public void onGetFinancialOverviewError(com.db.pwcc.dbmobile.model.error.DbError paramDbError)
  {
    // Byte code:
    //   0: getstatic 78	uuuuuu/wwwnww:b006300630063ccc006300630063	I
    //   3: istore_2
    //   4: ldc 2
    //   6: ldc_w 336
    //   9: sipush 146
    //   12: iconst_4
    //   13: invokestatic 118	xxxxxx/uxxxxx:bb00620062bb0062b0062b0062	(Ljava/lang/String;CC)Ljava/lang/String;
    //   16: iconst_0
    //   17: anewarray 94	java/lang/Class
    //   20: invokevirtual 98	java/lang/Class:getMethod	(Ljava/lang/String;[Ljava/lang/Class;)Ljava/lang/reflect/Method;
    //   23: astore_3
    //   24: iconst_0
    //   25: anewarray 100	java/lang/Object
    //   28: astore 4
    //   30: aload_3
    //   31: aconst_null
    //   32: aload 4
    //   34: invokevirtual 106	java/lang/reflect/Method:invoke	(Ljava/lang/Object;[Ljava/lang/Object;)Ljava/lang/Object;
    //   37: astore 6
    //   39: iload_2
    //   40: iload_2
    //   41: aload 6
    //   43: checkcast 108	java/lang/Integer
    //   46: invokevirtual 112	java/lang/Integer:intValue	()I
    //   49: iadd
    //   50: imul
    //   51: getstatic 82	uuuuuu/wwwnww:b0063cc0063cc006300630063	I
    //   54: irem
    //   55: tableswitch	default:+17->72, 0:+70->125
    //   72: bipush 96
    //   74: putstatic 78	uuuuuu/wwwnww:b006300630063ccc006300630063	I
    //   77: ldc 2
    //   79: ldc_w 338
    //   82: sipush 247
    //   85: iconst_5
    //   86: invokestatic 118	xxxxxx/uxxxxx:bb00620062bb0062b0062b0062	(Ljava/lang/String;CC)Ljava/lang/String;
    //   89: iconst_0
    //   90: anewarray 94	java/lang/Class
    //   93: invokevirtual 98	java/lang/Class:getMethod	(Ljava/lang/String;[Ljava/lang/Class;)Ljava/lang/reflect/Method;
    //   96: astore 34
    //   98: iconst_0
    //   99: anewarray 100	java/lang/Object
    //   102: astore 35
    //   104: aload 34
    //   106: aconst_null
    //   107: aload 35
    //   109: invokevirtual 106	java/lang/reflect/Method:invoke	(Ljava/lang/Object;[Ljava/lang/Object;)Ljava/lang/Object;
    //   112: astore 37
    //   114: aload 37
    //   116: checkcast 108	java/lang/Integer
    //   119: invokevirtual 112	java/lang/Integer:intValue	()I
    //   122: putstatic 84	uuuuuu/wwwnww:bc0063c0063cc006300630063	I
    //   125: ldc 2
    //   127: ldc -113
    //   129: sipush 168
    //   132: sipush 136
    //   135: iconst_0
    //   136: invokestatic 92	xxxxxx/uxxxxx:bbbb0062b0062b0062b0062	(Ljava/lang/String;CCC)Ljava/lang/String;
    //   139: iconst_0
    //   140: anewarray 94	java/lang/Class
    //   143: invokevirtual 98	java/lang/Class:getMethod	(Ljava/lang/String;[Ljava/lang/Class;)Ljava/lang/reflect/Method;
    //   146: astore 7
    //   148: iconst_0
    //   149: anewarray 100	java/lang/Object
    //   152: astore 8
    //   154: aload 7
    //   156: aconst_null
    //   157: aload 8
    //   159: invokevirtual 106	java/lang/reflect/Method:invoke	(Ljava/lang/Object;[Ljava/lang/Object;)Ljava/lang/Object;
    //   162: astore 10
    //   164: aload 10
    //   166: checkcast 108	java/lang/Integer
    //   169: invokevirtual 112	java/lang/Integer:intValue	()I
    //   172: getstatic 80	uuuuuu/wwwnww:bccc0063cc006300630063	I
    //   175: iadd
    //   176: istore 11
    //   178: ldc 2
    //   180: ldc_w 340
    //   183: sipush 230
    //   186: iconst_2
    //   187: invokestatic 118	xxxxxx/uxxxxx:bb00620062bb0062b0062b0062	(Ljava/lang/String;CC)Ljava/lang/String;
    //   190: iconst_0
    //   191: anewarray 94	java/lang/Class
    //   194: invokevirtual 98	java/lang/Class:getMethod	(Ljava/lang/String;[Ljava/lang/Class;)Ljava/lang/reflect/Method;
    //   197: astore 12
    //   199: iconst_0
    //   200: anewarray 100	java/lang/Object
    //   203: astore 13
    //   205: aload 12
    //   207: aconst_null
    //   208: aload 13
    //   210: invokevirtual 106	java/lang/reflect/Method:invoke	(Ljava/lang/Object;[Ljava/lang/Object;)Ljava/lang/Object;
    //   213: astore 15
    //   215: iload 11
    //   217: aload 15
    //   219: checkcast 108	java/lang/Integer
    //   222: invokevirtual 112	java/lang/Integer:intValue	()I
    //   225: imul
    //   226: getstatic 82	uuuuuu/wwwnww:b0063cc0063cc006300630063	I
    //   229: irem
    //   230: getstatic 84	uuuuuu/wwwnww:bc0063c0063cc006300630063	I
    //   233: if_icmpeq +58 -> 291
    //   236: bipush 53
    //   238: putstatic 78	uuuuuu/wwwnww:b006300630063ccc006300630063	I
    //   241: ldc 2
    //   243: ldc_w 342
    //   246: sipush 230
    //   249: bipush 44
    //   251: iconst_0
    //   252: invokestatic 92	xxxxxx/uxxxxx:bbbb0062b0062b0062b0062	(Ljava/lang/String;CCC)Ljava/lang/String;
    //   255: iconst_0
    //   256: anewarray 94	java/lang/Class
    //   259: invokevirtual 98	java/lang/Class:getMethod	(Ljava/lang/String;[Ljava/lang/Class;)Ljava/lang/reflect/Method;
    //   262: astore 30
    //   264: iconst_0
    //   265: anewarray 100	java/lang/Object
    //   268: astore 31
    //   270: aload 30
    //   272: aconst_null
    //   273: aload 31
    //   275: invokevirtual 106	java/lang/reflect/Method:invoke	(Ljava/lang/Object;[Ljava/lang/Object;)Ljava/lang/Object;
    //   278: astore 33
    //   280: aload 33
    //   282: checkcast 108	java/lang/Integer
    //   285: invokevirtual 112	java/lang/Integer:intValue	()I
    //   288: putstatic 84	uuuuuu/wwwnww:bc0063c0063cc006300630063	I
    //   291: aload_0
    //   292: getfield 76	uuuuuu/wwwnww:bnnnnn006E006E006En	Luuuuuu/ttssst$tsssst;
    //   295: checkcast 279	uuuuuu/wnwnww$nwwnww
    //   298: astore 16
    //   300: getstatic 78	uuuuuu/wwwnww:b006300630063ccc006300630063	I
    //   303: getstatic 80	uuuuuu/wwwnww:bccc0063cc006300630063	I
    //   306: iadd
    //   307: getstatic 78	uuuuuu/wwwnww:b006300630063ccc006300630063	I
    //   310: imul
    //   311: istore 17
    //   313: ldc 2
    //   315: ldc_w 344
    //   318: bipush 114
    //   320: iconst_2
    //   321: invokestatic 118	xxxxxx/uxxxxx:bb00620062bb0062b0062b0062	(Ljava/lang/String;CC)Ljava/lang/String;
    //   324: iconst_0
    //   325: anewarray 94	java/lang/Class
    //   328: invokevirtual 98	java/lang/Class:getMethod	(Ljava/lang/String;[Ljava/lang/Class;)Ljava/lang/reflect/Method;
    //   331: astore 18
    //   333: iconst_0
    //   334: anewarray 100	java/lang/Object
    //   337: astore 19
    //   339: aload 18
    //   341: aconst_null
    //   342: aload 19
    //   344: invokevirtual 106	java/lang/reflect/Method:invoke	(Ljava/lang/Object;[Ljava/lang/Object;)Ljava/lang/Object;
    //   347: astore 21
    //   349: iload 17
    //   351: aload 21
    //   353: checkcast 108	java/lang/Integer
    //   356: invokevirtual 112	java/lang/Integer:intValue	()I
    //   359: irem
    //   360: getstatic 84	uuuuuu/wwwnww:bc0063c0063cc006300630063	I
    //   363: if_icmpeq +131 -> 494
    //   366: getstatic 78	uuuuuu/wwwnww:b006300630063ccc006300630063	I
    //   369: getstatic 80	uuuuuu/wwwnww:bccc0063cc006300630063	I
    //   372: iadd
    //   373: getstatic 78	uuuuuu/wwwnww:b006300630063ccc006300630063	I
    //   376: imul
    //   377: getstatic 82	uuuuuu/wwwnww:b0063cc0063cc006300630063	I
    //   380: irem
    //   381: getstatic 84	uuuuuu/wwwnww:bc0063c0063cc006300630063	I
    //   384: if_icmpeq +56 -> 440
    //   387: ldc 2
    //   389: ldc_w 346
    //   392: sipush 248
    //   395: iconst_0
    //   396: invokestatic 118	xxxxxx/uxxxxx:bb00620062bb0062b0062b0062	(Ljava/lang/String;CC)Ljava/lang/String;
    //   399: iconst_0
    //   400: anewarray 94	java/lang/Class
    //   403: invokevirtual 98	java/lang/Class:getMethod	(Ljava/lang/String;[Ljava/lang/Class;)Ljava/lang/reflect/Method;
    //   406: astore 26
    //   408: iconst_0
    //   409: anewarray 100	java/lang/Object
    //   412: astore 27
    //   414: aload 26
    //   416: aconst_null
    //   417: aload 27
    //   419: invokevirtual 106	java/lang/reflect/Method:invoke	(Ljava/lang/Object;[Ljava/lang/Object;)Ljava/lang/Object;
    //   422: astore 29
    //   424: aload 29
    //   426: checkcast 108	java/lang/Integer
    //   429: invokevirtual 112	java/lang/Integer:intValue	()I
    //   432: putstatic 78	uuuuuu/wwwnww:b006300630063ccc006300630063	I
    //   435: bipush 22
    //   437: putstatic 84	uuuuuu/wwwnww:bc0063c0063cc006300630063	I
    //   440: ldc 2
    //   442: ldc_w 348
    //   445: bipush 91
    //   447: bipush 37
    //   449: iconst_3
    //   450: invokestatic 92	xxxxxx/uxxxxx:bbbb0062b0062b0062b0062	(Ljava/lang/String;CCC)Ljava/lang/String;
    //   453: iconst_0
    //   454: anewarray 94	java/lang/Class
    //   457: invokevirtual 98	java/lang/Class:getMethod	(Ljava/lang/String;[Ljava/lang/Class;)Ljava/lang/reflect/Method;
    //   460: astore 22
    //   462: iconst_0
    //   463: anewarray 100	java/lang/Object
    //   466: astore 23
    //   468: aload 22
    //   470: aconst_null
    //   471: aload 23
    //   473: invokevirtual 106	java/lang/reflect/Method:invoke	(Ljava/lang/Object;[Ljava/lang/Object;)Ljava/lang/Object;
    //   476: astore 25
    //   478: aload 25
    //   480: checkcast 108	java/lang/Integer
    //   483: invokevirtual 112	java/lang/Integer:intValue	()I
    //   486: putstatic 78	uuuuuu/wwwnww:b006300630063ccc006300630063	I
    //   489: bipush 22
    //   491: putstatic 84	uuuuuu/wwwnww:bc0063c0063cc006300630063	I
    //   494: aload 16
    //   496: invokeinterface 331 1 0
    //   501: return
    //   502: astore 5
    //   504: aload 5
    //   506: invokevirtual 122	java/lang/reflect/InvocationTargetException:getCause	()Ljava/lang/Throwable;
    //   509: athrow
    //   510: astore 9
    //   512: aload 9
    //   514: invokevirtual 122	java/lang/reflect/InvocationTargetException:getCause	()Ljava/lang/Throwable;
    //   517: athrow
    //   518: astore 14
    //   520: aload 14
    //   522: invokevirtual 122	java/lang/reflect/InvocationTargetException:getCause	()Ljava/lang/Throwable;
    //   525: athrow
    //   526: astore 28
    //   528: aload 28
    //   530: invokevirtual 122	java/lang/reflect/InvocationTargetException:getCause	()Ljava/lang/Throwable;
    //   533: athrow
    //   534: astore 20
    //   536: aload 20
    //   538: invokevirtual 122	java/lang/reflect/InvocationTargetException:getCause	()Ljava/lang/Throwable;
    //   541: athrow
    //   542: astore 24
    //   544: aload 24
    //   546: invokevirtual 122	java/lang/reflect/InvocationTargetException:getCause	()Ljava/lang/Throwable;
    //   549: athrow
    //   550: astore 32
    //   552: aload 32
    //   554: invokevirtual 122	java/lang/reflect/InvocationTargetException:getCause	()Ljava/lang/Throwable;
    //   557: athrow
    //   558: astore 36
    //   560: aload 36
    //   562: invokevirtual 122	java/lang/reflect/InvocationTargetException:getCause	()Ljava/lang/Throwable;
    //   565: athrow
    // Local variable table:
    //   start	length	slot	name	signature
    //   0	566	0	this	wwwnww
    //   0	566	1	paramDbError	com.db.pwcc.dbmobile.model.error.DbError
    //   3	48	2	i	int
    //   23	8	3	localMethod1	java.lang.reflect.Method
    //   28	5	4	arrayOfObject1	Object[]
    //   502	3	5	localInvocationTargetException1	java.lang.reflect.InvocationTargetException
    //   37	5	6	localObject1	Object
    //   146	9	7	localMethod2	java.lang.reflect.Method
    //   152	6	8	arrayOfObject2	Object[]
    //   510	3	9	localInvocationTargetException2	java.lang.reflect.InvocationTargetException
    //   162	3	10	localObject2	Object
    //   176	50	11	j	int
    //   197	9	12	localMethod3	java.lang.reflect.Method
    //   203	6	13	arrayOfObject3	Object[]
    //   518	3	14	localInvocationTargetException3	java.lang.reflect.InvocationTargetException
    //   213	5	15	localObject3	Object
    //   298	197	16	localNwwnww	wnwnww.nwwnww
    //   311	49	17	k	int
    //   331	9	18	localMethod4	java.lang.reflect.Method
    //   337	6	19	arrayOfObject4	Object[]
    //   534	3	20	localInvocationTargetException4	java.lang.reflect.InvocationTargetException
    //   347	5	21	localObject4	Object
    //   460	9	22	localMethod5	java.lang.reflect.Method
    //   466	6	23	arrayOfObject5	Object[]
    //   542	3	24	localInvocationTargetException5	java.lang.reflect.InvocationTargetException
    //   476	3	25	localObject5	Object
    //   406	9	26	localMethod6	java.lang.reflect.Method
    //   412	6	27	arrayOfObject6	Object[]
    //   526	3	28	localInvocationTargetException6	java.lang.reflect.InvocationTargetException
    //   422	3	29	localObject6	Object
    //   262	9	30	localMethod7	java.lang.reflect.Method
    //   268	6	31	arrayOfObject7	Object[]
    //   550	3	32	localInvocationTargetException7	java.lang.reflect.InvocationTargetException
    //   278	3	33	localObject7	Object
    //   96	9	34	localMethod8	java.lang.reflect.Method
    //   102	6	35	arrayOfObject8	Object[]
    //   558	3	36	localInvocationTargetException8	java.lang.reflect.InvocationTargetException
    //   112	3	37	localObject8	Object
    // Exception table:
    //   from	to	target	type
    //   30	39	502	java/lang/reflect/InvocationTargetException
    //   154	164	510	java/lang/reflect/InvocationTargetException
    //   205	215	518	java/lang/reflect/InvocationTargetException
    //   414	424	526	java/lang/reflect/InvocationTargetException
    //   339	349	534	java/lang/reflect/InvocationTargetException
    //   468	478	542	java/lang/reflect/InvocationTargetException
    //   270	280	550	java/lang/reflect/InvocationTargetException
    //   104	114	558	java/lang/reflect/InvocationTargetException
  }
  
  /* Error */
  public void onGetFinancialOverviewSuccess(FinancialOverviewData paramFinancialOverviewData)
  {
    // Byte code:
    //   0: aload_1
    //   1: invokevirtual 355	com/db/pwcc/dbmobile/model/banking/FinancialOverviewData:getSortedAccounts	()Ljava/util/List;
    //   4: invokeinterface 361 1 0
    //   9: astore_2
    //   10: ldc_w 363
    //   13: astore_3
    //   14: aload_2
    //   15: invokeinterface 368 1 0
    //   20: ifeq +740 -> 760
    //   23: aload_2
    //   24: invokeinterface 372 1 0
    //   29: astore 4
    //   31: getstatic 78	uuuuuu/wwwnww:b006300630063ccc006300630063	I
    //   34: istore 5
    //   36: iload 5
    //   38: iload 5
    //   40: getstatic 80	uuuuuu/wwwnww:bccc0063cc006300630063	I
    //   43: iadd
    //   44: imul
    //   45: getstatic 82	uuuuuu/wwwnww:b0063cc0063cc006300630063	I
    //   48: irem
    //   49: tableswitch	default:+19->68, 0:+28->77
    //   68: bipush 67
    //   70: putstatic 78	uuuuuu/wwwnww:b006300630063ccc006300630063	I
    //   73: iconst_2
    //   74: putstatic 84	uuuuuu/wwwnww:bc0063c0063cc006300630063	I
    //   77: aload 4
    //   79: checkcast 151	com/db/pwcc/dbmobile/model/banking/Account
    //   82: astore 6
    //   84: aload 6
    //   86: invokevirtual 375	com/db/pwcc/dbmobile/model/banking/Account:getIban	()Ljava/lang/String;
    //   89: ifnull -75 -> 14
    //   92: aload 6
    //   94: invokevirtual 375	com/db/pwcc/dbmobile/model/banking/Account:getIban	()Ljava/lang/String;
    //   97: invokevirtual 298	java/lang/String:isEmpty	()Z
    //   100: ifne -86 -> 14
    //   103: getstatic 378	com/db/pwcc/dbmobile/model/banking/Account$ProductType:CREDIT_CARD_ACCOUNT	Lcom/db/pwcc/dbmobile/model/banking/Account$ProductType;
    //   106: aload 6
    //   108: invokevirtual 155	com/db/pwcc/dbmobile/model/banking/Account:getProductType	()Lcom/db/pwcc/dbmobile/model/banking/Account$ProductType;
    //   111: if_acmpeq -97 -> 14
    //   114: getstatic 381	com/db/pwcc/dbmobile/model/banking/Account$ProductType:SECURITIES_ACCOUNT	Lcom/db/pwcc/dbmobile/model/banking/Account$ProductType;
    //   117: aload 6
    //   119: invokevirtual 155	com/db/pwcc/dbmobile/model/banking/Account:getProductType	()Lcom/db/pwcc/dbmobile/model/banking/Account$ProductType;
    //   122: if_acmpeq -108 -> 14
    //   125: aload_0
    //   126: getfield 383	uuuuuu/wwwnww:bc0063cccc006300630063	Landroid/content/Context;
    //   129: astore 7
    //   131: aload_1
    //   132: invokevirtual 386	com/db/pwcc/dbmobile/model/banking/FinancialOverviewData:getBaseCurrency	()Ljava/lang/String;
    //   135: astore 8
    //   137: ldc 2
    //   139: ldc_w 388
    //   142: bipush 21
    //   144: bipush 121
    //   146: iconst_1
    //   147: invokestatic 92	xxxxxx/uxxxxx:bbbb0062b0062b0062b0062	(Ljava/lang/String;CCC)Ljava/lang/String;
    //   150: iconst_2
    //   151: anewarray 94	java/lang/Class
    //   154: dup
    //   155: iconst_0
    //   156: ldc -105
    //   158: aastore
    //   159: dup
    //   160: iconst_1
    //   161: ldc -89
    //   163: aastore
    //   164: invokevirtual 391	java/lang/Class:getDeclaredMethod	(Ljava/lang/String;[Ljava/lang/Class;)Ljava/lang/reflect/Method;
    //   167: astore 9
    //   169: iconst_2
    //   170: anewarray 100	java/lang/Object
    //   173: dup
    //   174: iconst_0
    //   175: aload 6
    //   177: aastore
    //   178: dup
    //   179: iconst_1
    //   180: aload 8
    //   182: aastore
    //   183: astore 10
    //   185: aload 9
    //   187: aload_0
    //   188: aload 10
    //   190: invokevirtual 106	java/lang/reflect/Method:invoke	(Ljava/lang/Object;[Ljava/lang/Object;)Ljava/lang/Object;
    //   193: astore 12
    //   195: aload 7
    //   197: aload 12
    //   199: checkcast 108	java/lang/Integer
    //   202: invokevirtual 112	java/lang/Integer:intValue	()I
    //   205: invokevirtual 397	android/content/Context:getString	(I)Ljava/lang/String;
    //   208: astore 13
    //   210: getstatic 78	uuuuuu/wwwnww:b006300630063ccc006300630063	I
    //   213: getstatic 80	uuuuuu/wwwnww:bccc0063cc006300630063	I
    //   216: iadd
    //   217: getstatic 78	uuuuuu/wwwnww:b006300630063ccc006300630063	I
    //   220: imul
    //   221: getstatic 82	uuuuuu/wwwnww:b0063cc0063cc006300630063	I
    //   224: irem
    //   225: getstatic 84	uuuuuu/wwwnww:bc0063c0063cc006300630063	I
    //   228: if_icmpeq +150 -> 378
    //   231: bipush 62
    //   233: putstatic 78	uuuuuu/wwwnww:b006300630063ccc006300630063	I
    //   236: ldc 2
    //   238: ldc_w 399
    //   241: sipush 231
    //   244: iconst_4
    //   245: invokestatic 118	xxxxxx/uxxxxx:bb00620062bb0062b0062b0062	(Ljava/lang/String;CC)Ljava/lang/String;
    //   248: iconst_0
    //   249: anewarray 94	java/lang/Class
    //   252: invokevirtual 98	java/lang/Class:getMethod	(Ljava/lang/String;[Ljava/lang/Class;)Ljava/lang/reflect/Method;
    //   255: astore 39
    //   257: iconst_0
    //   258: anewarray 100	java/lang/Object
    //   261: astore 40
    //   263: aload 39
    //   265: aconst_null
    //   266: aload 40
    //   268: invokevirtual 106	java/lang/reflect/Method:invoke	(Ljava/lang/Object;[Ljava/lang/Object;)Ljava/lang/Object;
    //   271: astore 42
    //   273: aload 42
    //   275: checkcast 108	java/lang/Integer
    //   278: invokevirtual 112	java/lang/Integer:intValue	()I
    //   281: putstatic 84	uuuuuu/wwwnww:bc0063c0063cc006300630063	I
    //   284: getstatic 78	uuuuuu/wwwnww:b006300630063ccc006300630063	I
    //   287: istore 43
    //   289: iload 43
    //   291: iload 43
    //   293: getstatic 80	uuuuuu/wwwnww:bccc0063cc006300630063	I
    //   296: iadd
    //   297: imul
    //   298: istore 44
    //   300: ldc 2
    //   302: ldc_w 284
    //   305: sipush 136
    //   308: sipush 233
    //   311: iconst_3
    //   312: invokestatic 92	xxxxxx/uxxxxx:bbbb0062b0062b0062b0062	(Ljava/lang/String;CCC)Ljava/lang/String;
    //   315: iconst_0
    //   316: anewarray 94	java/lang/Class
    //   319: invokevirtual 98	java/lang/Class:getMethod	(Ljava/lang/String;[Ljava/lang/Class;)Ljava/lang/reflect/Method;
    //   322: astore 45
    //   324: iconst_0
    //   325: anewarray 100	java/lang/Object
    //   328: astore 46
    //   330: aload 45
    //   332: aconst_null
    //   333: aload 46
    //   335: invokevirtual 106	java/lang/reflect/Method:invoke	(Ljava/lang/Object;[Ljava/lang/Object;)Ljava/lang/Object;
    //   338: astore 48
    //   340: iload 44
    //   342: aload 48
    //   344: checkcast 108	java/lang/Integer
    //   347: invokevirtual 112	java/lang/Integer:intValue	()I
    //   350: irem
    //   351: tableswitch	default:+17->368, 0:+27->378
    //   368: bipush 50
    //   370: putstatic 78	uuuuuu/wwwnww:b006300630063ccc006300630063	I
    //   373: bipush 53
    //   375: putstatic 84	uuuuuu/wwwnww:bc0063c0063cc006300630063	I
    //   378: aload 13
    //   380: invokevirtual 402	java/lang/String:toUpperCase	()Ljava/lang/String;
    //   383: astore 14
    //   385: aload_3
    //   386: aload 14
    //   388: invokevirtual 171	java/lang/String:equals	(Ljava/lang/Object;)Z
    //   391: ifne +88 -> 479
    //   394: getstatic 405	com/db/pwcc/dbmobile/ibanbic/items/AccountItem$nwwwww:b0063c006300630063c006300630063	Lcom/db/pwcc/dbmobile/ibanbic/items/AccountItem$nwwwww;
    //   397: astore 32
    //   399: ldc 2
    //   401: ldc_w 407
    //   404: sipush 129
    //   407: sipush 231
    //   410: iconst_0
    //   411: invokestatic 92	xxxxxx/uxxxxx:bbbb0062b0062b0062b0062	(Ljava/lang/String;CCC)Ljava/lang/String;
    //   414: iconst_2
    //   415: anewarray 94	java/lang/Class
    //   418: dup
    //   419: iconst_0
    //   420: ldc -89
    //   422: aastore
    //   423: dup
    //   424: iconst_1
    //   425: ldc_w 257
    //   428: aastore
    //   429: invokevirtual 391	java/lang/Class:getDeclaredMethod	(Ljava/lang/String;[Ljava/lang/Class;)Ljava/lang/reflect/Method;
    //   432: astore 33
    //   434: iconst_2
    //   435: anewarray 100	java/lang/Object
    //   438: dup
    //   439: iconst_0
    //   440: aload 14
    //   442: aastore
    //   443: dup
    //   444: iconst_1
    //   445: aload 32
    //   447: aastore
    //   448: astore 34
    //   450: aload 33
    //   452: aload_0
    //   453: aload 34
    //   455: invokevirtual 106	java/lang/reflect/Method:invoke	(Ljava/lang/Object;[Ljava/lang/Object;)Ljava/lang/Object;
    //   458: astore 36
    //   460: aload 36
    //   462: checkcast 128	com/db/pwcc/dbmobile/ibanbic/items/AccountItem
    //   465: astore 37
    //   467: aload_0
    //   468: getfield 68	uuuuuu/wwwnww:b0063ccccc006300630063	Ljava/util/List;
    //   471: aload 37
    //   473: invokeinterface 410 2 0
    //   478: pop
    //   479: aload_0
    //   480: getfield 68	uuuuuu/wwwnww:b0063ccccc006300630063	Ljava/util/List;
    //   483: astore 15
    //   485: aload_1
    //   486: invokevirtual 413	com/db/pwcc/dbmobile/model/banking/FinancialOverviewData:getBlz	()Ljava/lang/String;
    //   489: astore 16
    //   491: ldc 2
    //   493: ldc_w 415
    //   496: bipush 117
    //   498: bipush 100
    //   500: iconst_1
    //   501: invokestatic 92	xxxxxx/uxxxxx:bbbb0062b0062b0062b0062	(Ljava/lang/String;CCC)Ljava/lang/String;
    //   504: iconst_2
    //   505: anewarray 94	java/lang/Class
    //   508: dup
    //   509: iconst_0
    //   510: ldc -105
    //   512: aastore
    //   513: dup
    //   514: iconst_1
    //   515: ldc -89
    //   517: aastore
    //   518: invokevirtual 391	java/lang/Class:getDeclaredMethod	(Ljava/lang/String;[Ljava/lang/Class;)Ljava/lang/reflect/Method;
    //   521: astore 17
    //   523: iconst_2
    //   524: anewarray 100	java/lang/Object
    //   527: dup
    //   528: iconst_0
    //   529: aload 6
    //   531: aastore
    //   532: dup
    //   533: iconst_1
    //   534: aload 16
    //   536: aastore
    //   537: astore 18
    //   539: aload 17
    //   541: aload_0
    //   542: aload 18
    //   544: invokevirtual 106	java/lang/reflect/Method:invoke	(Ljava/lang/Object;[Ljava/lang/Object;)Ljava/lang/Object;
    //   547: astore 20
    //   549: aload 15
    //   551: aload 20
    //   553: checkcast 128	com/db/pwcc/dbmobile/ibanbic/items/AccountItem
    //   556: invokeinterface 410 2 0
    //   561: pop
    //   562: new 417	uuuuuu/wwwnww$nnnwww
    //   565: dup
    //   566: aload_0
    //   567: iconst_m1
    //   568: aload_0
    //   569: getfield 68	uuuuuu/wwwnww:b0063ccccc006300630063	Ljava/util/List;
    //   572: invokeinterface 420 1 0
    //   577: iadd
    //   578: invokespecial 423	uuuuuu/wwwnww$nnnwww:<init>	(Luuuuuu/wwwnww;I)V
    //   581: astore 22
    //   583: aload_0
    //   584: getfield 46	uuuuuu/wwwnww:bcc0063ccc006300630063	Luuuuuu/vvdddd;
    //   587: aload 22
    //   589: aload 6
    //   591: invokevirtual 375	com/db/pwcc/dbmobile/model/banking/Account:getIban	()Ljava/lang/String;
    //   594: invokevirtual 427	uuuuuu/vvdddd:b0071qqqq0071q00710071q	(Luuuuuu/vddddd$dvdddd;Ljava/lang/String;)V
    //   597: getstatic 78	uuuuuu/wwwnww:b006300630063ccc006300630063	I
    //   600: istore 23
    //   602: iload 23
    //   604: iload 23
    //   606: getstatic 80	uuuuuu/wwwnww:bccc0063cc006300630063	I
    //   609: iadd
    //   610: imul
    //   611: getstatic 82	uuuuuu/wwwnww:b0063cc0063cc006300630063	I
    //   614: irem
    //   615: tableswitch	default:+17->632, 0:+115->730
    //   632: ldc 2
    //   634: ldc -57
    //   636: bipush 51
    //   638: bipush 63
    //   640: iconst_1
    //   641: invokestatic 92	xxxxxx/uxxxxx:bbbb0062b0062b0062b0062	(Ljava/lang/String;CCC)Ljava/lang/String;
    //   644: iconst_0
    //   645: anewarray 94	java/lang/Class
    //   648: invokevirtual 98	java/lang/Class:getMethod	(Ljava/lang/String;[Ljava/lang/Class;)Ljava/lang/reflect/Method;
    //   651: astore 24
    //   653: iconst_0
    //   654: anewarray 100	java/lang/Object
    //   657: astore 25
    //   659: aload 24
    //   661: aconst_null
    //   662: aload 25
    //   664: invokevirtual 106	java/lang/reflect/Method:invoke	(Ljava/lang/Object;[Ljava/lang/Object;)Ljava/lang/Object;
    //   667: astore 27
    //   669: aload 27
    //   671: checkcast 108	java/lang/Integer
    //   674: invokevirtual 112	java/lang/Integer:intValue	()I
    //   677: putstatic 78	uuuuuu/wwwnww:b006300630063ccc006300630063	I
    //   680: ldc 2
    //   682: ldc_w 429
    //   685: bipush 119
    //   687: sipush 158
    //   690: iconst_1
    //   691: invokestatic 92	xxxxxx/uxxxxx:bbbb0062b0062b0062b0062	(Ljava/lang/String;CCC)Ljava/lang/String;
    //   694: iconst_0
    //   695: anewarray 94	java/lang/Class
    //   698: invokevirtual 98	java/lang/Class:getMethod	(Ljava/lang/String;[Ljava/lang/Class;)Ljava/lang/reflect/Method;
    //   701: astore 28
    //   703: iconst_0
    //   704: anewarray 100	java/lang/Object
    //   707: astore 29
    //   709: aload 28
    //   711: aconst_null
    //   712: aload 29
    //   714: invokevirtual 106	java/lang/reflect/Method:invoke	(Ljava/lang/Object;[Ljava/lang/Object;)Ljava/lang/Object;
    //   717: astore 31
    //   719: aload 31
    //   721: checkcast 108	java/lang/Integer
    //   724: invokevirtual 112	java/lang/Integer:intValue	()I
    //   727: putstatic 84	uuuuuu/wwwnww:bc0063c0063cc006300630063	I
    //   730: aload 14
    //   732: astore_3
    //   733: goto -719 -> 14
    //   736: astore 26
    //   738: aload 26
    //   740: invokevirtual 122	java/lang/reflect/InvocationTargetException:getCause	()Ljava/lang/Throwable;
    //   743: athrow
    //   744: astore 30
    //   746: aload 30
    //   748: invokevirtual 122	java/lang/reflect/InvocationTargetException:getCause	()Ljava/lang/Throwable;
    //   751: athrow
    //   752: astore 11
    //   754: aload 11
    //   756: invokevirtual 122	java/lang/reflect/InvocationTargetException:getCause	()Ljava/lang/Throwable;
    //   759: athrow
    //   760: aload_0
    //   761: getfield 76	uuuuuu/wwwnww:bnnnnn006E006E006En	Luuuuuu/ttssst$tsssst;
    //   764: checkcast 279	uuuuuu/wnwnww$nwwnww
    //   767: aload_0
    //   768: getfield 68	uuuuuu/wwwnww:b0063ccccc006300630063	Ljava/util/List;
    //   771: invokeinterface 433 2 0
    //   776: aload_0
    //   777: getfield 51	uuuuuu/wwwnww:b0063c0063ccc006300630063	Luuuuuu/mffffm;
    //   780: aload_0
    //   781: invokevirtual 437	uuuuuu/mffffm:bpp0070pp0070p00700070p	(Luuuuuu/vvpvvp$ppvvvp;)V
    //   784: return
    //   785: astore 19
    //   787: aload 19
    //   789: invokevirtual 122	java/lang/reflect/InvocationTargetException:getCause	()Ljava/lang/Throwable;
    //   792: athrow
    //   793: astore 41
    //   795: aload 41
    //   797: invokevirtual 122	java/lang/reflect/InvocationTargetException:getCause	()Ljava/lang/Throwable;
    //   800: athrow
    //   801: astore 35
    //   803: aload 35
    //   805: invokevirtual 122	java/lang/reflect/InvocationTargetException:getCause	()Ljava/lang/Throwable;
    //   808: athrow
    //   809: astore 47
    //   811: aload 47
    //   813: invokevirtual 122	java/lang/reflect/InvocationTargetException:getCause	()Ljava/lang/Throwable;
    //   816: athrow
    // Local variable table:
    //   start	length	slot	name	signature
    //   0	817	0	this	wwwnww
    //   0	817	1	paramFinancialOverviewData	FinancialOverviewData
    //   9	15	2	localIterator	java.util.Iterator
    //   13	720	3	localObject1	Object
    //   29	49	4	localObject2	Object
    //   34	11	5	i	int
    //   82	508	6	localAccount	com.db.pwcc.dbmobile.model.banking.Account
    //   129	67	7	localContext	Context
    //   135	46	8	str1	String
    //   167	19	9	localMethod1	java.lang.reflect.Method
    //   183	6	10	arrayOfObject1	Object[]
    //   752	3	11	localInvocationTargetException1	java.lang.reflect.InvocationTargetException
    //   193	5	12	localObject3	Object
    //   208	171	13	str2	String
    //   383	348	14	str3	String
    //   483	67	15	localList	List
    //   489	46	16	str4	String
    //   521	19	17	localMethod2	java.lang.reflect.Method
    //   537	6	18	arrayOfObject2	Object[]
    //   785	3	19	localInvocationTargetException2	java.lang.reflect.InvocationTargetException
    //   547	5	20	localObject4	Object
    //   581	7	22	localNnnwww	wwwnww.nnnwww
    //   600	11	23	j	int
    //   651	9	24	localMethod3	java.lang.reflect.Method
    //   657	6	25	arrayOfObject3	Object[]
    //   736	3	26	localInvocationTargetException3	java.lang.reflect.InvocationTargetException
    //   667	3	27	localObject5	Object
    //   701	9	28	localMethod4	java.lang.reflect.Method
    //   707	6	29	arrayOfObject4	Object[]
    //   744	3	30	localInvocationTargetException4	java.lang.reflect.InvocationTargetException
    //   717	3	31	localObject6	Object
    //   397	49	32	localNwwwww	com.db.pwcc.dbmobile.ibanbic.items.AccountItem.nwwwww
    //   432	19	33	localMethod5	java.lang.reflect.Method
    //   448	6	34	arrayOfObject5	Object[]
    //   801	3	35	localInvocationTargetException5	java.lang.reflect.InvocationTargetException
    //   458	3	36	localObject7	Object
    //   465	7	37	localAccountItem	AccountItem
    //   255	9	39	localMethod6	java.lang.reflect.Method
    //   261	6	40	arrayOfObject6	Object[]
    //   793	3	41	localInvocationTargetException6	java.lang.reflect.InvocationTargetException
    //   271	3	42	localObject8	Object
    //   287	11	43	k	int
    //   298	53	44	m	int
    //   322	9	45	localMethod7	java.lang.reflect.Method
    //   328	6	46	arrayOfObject7	Object[]
    //   809	3	47	localInvocationTargetException7	java.lang.reflect.InvocationTargetException
    //   338	5	48	localObject9	Object
    // Exception table:
    //   from	to	target	type
    //   659	669	736	java/lang/reflect/InvocationTargetException
    //   709	719	744	java/lang/reflect/InvocationTargetException
    //   185	195	752	java/lang/reflect/InvocationTargetException
    //   539	549	785	java/lang/reflect/InvocationTargetException
    //   263	273	793	java/lang/reflect/InvocationTargetException
    //   450	460	801	java/lang/reflect/InvocationTargetException
    //   330	340	809	java/lang/reflect/InvocationTargetException
  }
}
