package com.datami.smi;

import android.content.Context;

final class k
  implements Runnable
{
  private static final byte[] d = { 16, -122, 111, -110, 2, -11, 0, 3, -5, 7, 71, -71, 2, -15, 51, -47, 0, 29, 15, 3, -52, 1, 12, 64, -1, 9, -70, 5, -8, -3, 7, 1, 42, 26 };
  private static int e = 242;
  
  k(Context paramContext, String paramString, j paramJ) {}
  
  /* Error */
  public final void run()
  {
    // Byte code:
    //   0: aload_0
    //   1: getfield 55	com/datami/smi/k:a	Landroid/content/Context;
    //   4: aload_0
    //   5: getfield 57	com/datami/smi/k:b	Ljava/lang/String;
    //   8: invokestatic 69	com/datami/smi/b/m:b	(Landroid/content/Context;Ljava/lang/String;)V
    //   11: iconst_0
    //   12: invokestatic 75	com/datami/smi/SmiSdk:access$002	(Z)Z
    //   15: pop
    //   16: return
    //   17: astore 8
    //   19: goto +155 -> 174
    //   22: getstatic 78	com/datami/smi/SmiSdk:TAG	Ljava/lang/String;
    //   25: astore 8
    //   27: getstatic 50	com/datami/smi/k:d	[B
    //   30: bipush 6
    //   32: baload
    //   33: istore 4
    //   35: iload 4
    //   37: iconst_3
    //   38: imul
    //   39: istore_2
    //   40: iload_2
    //   41: bipush 99
    //   43: iadd
    //   44: istore_3
    //   45: getstatic 50	com/datami/smi/k:d	[B
    //   48: astore 8
    //   50: iload 4
    //   52: iconst_2
    //   53: imul
    //   54: iconst_4
    //   55: iadd
    //   56: istore 4
    //   58: bipush 31
    //   60: iload_2
    //   61: isub
    //   62: istore_2
    //   63: iload_2
    //   64: newarray byte
    //   66: astore 9
    //   68: aload 8
    //   70: ifnonnull +117 -> 187
    //   73: iload 4
    //   75: istore 6
    //   77: iconst_0
    //   78: istore 7
    //   80: iload_2
    //   81: istore 4
    //   83: iload_3
    //   84: istore 5
    //   86: iload 7
    //   88: istore_3
    //   89: goto +62 -> 151
    //   92: iload_2
    //   93: i2b
    //   94: istore_1
    //   95: iload_3
    //   96: iconst_1
    //   97: iadd
    //   98: istore 6
    //   100: aload 9
    //   102: iload_3
    //   103: iload_1
    //   104: bastore
    //   105: iload 6
    //   107: iload 5
    //   109: if_icmpne +20 -> 129
    //   112: new 80	java/lang/String
    //   115: dup
    //   116: aload 9
    //   118: iconst_0
    //   119: invokespecial 83	java/lang/String:<init>	([BI)V
    //   122: pop
    //   123: iconst_0
    //   124: invokestatic 75	com/datami/smi/SmiSdk:access$002	(Z)Z
    //   127: pop
    //   128: return
    //   129: aload 8
    //   131: iload 4
    //   133: baload
    //   134: istore 7
    //   136: iload 6
    //   138: istore_3
    //   139: iload 4
    //   141: istore 6
    //   143: iload 5
    //   145: istore 4
    //   147: iload 7
    //   149: istore 5
    //   151: iload_2
    //   152: iload 5
    //   154: ineg
    //   155: iadd
    //   156: istore_2
    //   157: iload 6
    //   159: iconst_1
    //   160: iadd
    //   161: istore 6
    //   163: iload 4
    //   165: istore 5
    //   167: iload 6
    //   169: istore 4
    //   171: goto -79 -> 92
    //   174: iconst_0
    //   175: invokestatic 75	com/datami/smi/SmiSdk:access$002	(Z)Z
    //   178: pop
    //   179: aload 8
    //   181: athrow
    //   182: astore 8
    //   184: goto -162 -> 22
    //   187: iconst_0
    //   188: istore 6
    //   190: iload_2
    //   191: istore 5
    //   193: iload_3
    //   194: istore_2
    //   195: iload 6
    //   197: istore_3
    //   198: goto -106 -> 92
    // Local variable table:
    //   start	length	slot	name	signature
    //   0	201	0	this	k
    //   94	10	1	i	int
    //   39	156	2	j	int
    //   44	154	3	k	int
    //   33	137	4	m	int
    //   84	108	5	n	int
    //   75	121	6	i1	int
    //   78	70	7	i2	int
    //   17	1	8	localObject1	Object
    //   25	155	8	localObject2	Object
    //   182	1	8	localException	Exception
    //   66	51	9	arrayOfByte	byte[]
    // Exception table:
    //   from	to	target	type
    //   0	11	17	finally
    //   22	35	17	finally
    //   45	50	17	finally
    //   63	68	17	finally
    //   112	123	17	finally
    //   0	11	182	java/lang/Exception
  }
}
