package com.db.pwcc.dbmobile.model.banking;

import uuuuuu.popopp;

public enum GVO
  implements popopp
{
  /* Error */
  static
  {
    // Byte code:
    //   0: ldc 81
    //   2: ldc 83
    //   4: bipush 105
    //   6: iconst_2
    //   7: invokestatic 89	xxxxxx/uxxxxx:bb00620062bb0062b0062b0062	(Ljava/lang/String;CC)Ljava/lang/String;
    //   10: iconst_3
    //   11: anewarray 91	java/lang/Class
    //   14: dup
    //   15: iconst_0
    //   16: ldc 93
    //   18: aastore
    //   19: dup
    //   20: iconst_1
    //   21: getstatic 99	java/lang/Character:TYPE	Ljava/lang/Class;
    //   24: aastore
    //   25: dup
    //   26: iconst_2
    //   27: getstatic 99	java/lang/Character:TYPE	Ljava/lang/Class;
    //   30: aastore
    //   31: invokevirtual 103	java/lang/Class:getMethod	(Ljava/lang/String;[Ljava/lang/Class;)Ljava/lang/reflect/Method;
    //   34: astore_1
    //   35: aload_1
    //   36: aconst_null
    //   37: iconst_3
    //   38: anewarray 105	java/lang/Object
    //   41: dup
    //   42: iconst_0
    //   43: ldc 107
    //   45: aastore
    //   46: dup
    //   47: iconst_1
    //   48: bipush 28
    //   50: invokestatic 111	java/lang/Character:valueOf	(C)Ljava/lang/Character;
    //   53: aastore
    //   54: dup
    //   55: iconst_2
    //   56: iconst_4
    //   57: invokestatic 111	java/lang/Character:valueOf	(C)Ljava/lang/Character;
    //   60: aastore
    //   61: invokevirtual 117	java/lang/reflect/Method:invoke	(Ljava/lang/Object;[Ljava/lang/Object;)Ljava/lang/Object;
    //   64: astore_1
    //   65: new 2	com/db/pwcc/dbmobile/model/banking/GVO
    //   68: dup
    //   69: aload_1
    //   70: checkcast 93	java/lang/String
    //   73: iconst_0
    //   74: invokespecial 121	com/db/pwcc/dbmobile/model/banking/GVO:<init>	(Ljava/lang/String;I)V
    //   77: putstatic 123	com/db/pwcc/dbmobile/model/banking/GVO:UNSTRUCTURED	Lcom/db/pwcc/dbmobile/model/banking/GVO;
    //   80: ldc 81
    //   82: ldc 125
    //   84: bipush 49
    //   86: sipush 245
    //   89: iconst_0
    //   90: invokestatic 129	xxxxxx/uxxxxx:bbbb0062b0062b0062b0062	(Ljava/lang/String;CCC)Ljava/lang/String;
    //   93: iconst_3
    //   94: anewarray 91	java/lang/Class
    //   97: dup
    //   98: iconst_0
    //   99: ldc 93
    //   101: aastore
    //   102: dup
    //   103: iconst_1
    //   104: getstatic 99	java/lang/Character:TYPE	Ljava/lang/Class;
    //   107: aastore
    //   108: dup
    //   109: iconst_2
    //   110: getstatic 99	java/lang/Character:TYPE	Ljava/lang/Class;
    //   113: aastore
    //   114: invokevirtual 103	java/lang/Class:getMethod	(Ljava/lang/String;[Ljava/lang/Class;)Ljava/lang/reflect/Method;
    //   117: astore_1
    //   118: aload_1
    //   119: aconst_null
    //   120: iconst_3
    //   121: anewarray 105	java/lang/Object
    //   124: dup
    //   125: iconst_0
    //   126: ldc -125
    //   128: aastore
    //   129: dup
    //   130: iconst_1
    //   131: sipush 222
    //   134: invokestatic 111	java/lang/Character:valueOf	(C)Ljava/lang/Character;
    //   137: aastore
    //   138: dup
    //   139: iconst_2
    //   140: iconst_3
    //   141: invokestatic 111	java/lang/Character:valueOf	(C)Ljava/lang/Character;
    //   144: aastore
    //   145: invokevirtual 117	java/lang/reflect/Method:invoke	(Ljava/lang/Object;[Ljava/lang/Object;)Ljava/lang/Object;
    //   148: astore_1
    //   149: new 2	com/db/pwcc/dbmobile/model/banking/GVO
    //   152: dup
    //   153: aload_1
    //   154: checkcast 93	java/lang/String
    //   157: iconst_1
    //   158: invokespecial 121	com/db/pwcc/dbmobile/model/banking/GVO:<init>	(Ljava/lang/String;I)V
    //   161: putstatic 133	com/db/pwcc/dbmobile/model/banking/GVO:SEPA_STANDING_ORDER	Lcom/db/pwcc/dbmobile/model/banking/GVO;
    //   164: ldc 81
    //   166: ldc -121
    //   168: sipush 202
    //   171: sipush 182
    //   174: iconst_3
    //   175: invokestatic 129	xxxxxx/uxxxxx:bbbb0062b0062b0062b0062	(Ljava/lang/String;CCC)Ljava/lang/String;
    //   178: iconst_4
    //   179: anewarray 91	java/lang/Class
    //   182: dup
    //   183: iconst_0
    //   184: ldc 93
    //   186: aastore
    //   187: dup
    //   188: iconst_1
    //   189: getstatic 99	java/lang/Character:TYPE	Ljava/lang/Class;
    //   192: aastore
    //   193: dup
    //   194: iconst_2
    //   195: getstatic 99	java/lang/Character:TYPE	Ljava/lang/Class;
    //   198: aastore
    //   199: dup
    //   200: iconst_3
    //   201: getstatic 99	java/lang/Character:TYPE	Ljava/lang/Class;
    //   204: aastore
    //   205: invokevirtual 103	java/lang/Class:getMethod	(Ljava/lang/String;[Ljava/lang/Class;)Ljava/lang/reflect/Method;
    //   208: astore_1
    //   209: aload_1
    //   210: aconst_null
    //   211: iconst_4
    //   212: anewarray 105	java/lang/Object
    //   215: dup
    //   216: iconst_0
    //   217: ldc -119
    //   219: aastore
    //   220: dup
    //   221: iconst_1
    //   222: bipush 36
    //   224: invokestatic 111	java/lang/Character:valueOf	(C)Ljava/lang/Character;
    //   227: aastore
    //   228: dup
    //   229: iconst_2
    //   230: sipush 210
    //   233: invokestatic 111	java/lang/Character:valueOf	(C)Ljava/lang/Character;
    //   236: aastore
    //   237: dup
    //   238: iconst_3
    //   239: iconst_2
    //   240: invokestatic 111	java/lang/Character:valueOf	(C)Ljava/lang/Character;
    //   243: aastore
    //   244: invokevirtual 117	java/lang/reflect/Method:invoke	(Ljava/lang/Object;[Ljava/lang/Object;)Ljava/lang/Object;
    //   247: astore_1
    //   248: new 2	com/db/pwcc/dbmobile/model/banking/GVO
    //   251: dup
    //   252: aload_1
    //   253: checkcast 93	java/lang/String
    //   256: iconst_2
    //   257: invokespecial 121	com/db/pwcc/dbmobile/model/banking/GVO:<init>	(Ljava/lang/String;I)V
    //   260: putstatic 139	com/db/pwcc/dbmobile/model/banking/GVO:SEPA_CREDIT_TRANSFER_DB_CLIENT_ORIGINATOR	Lcom/db/pwcc/dbmobile/model/banking/GVO;
    //   263: ldc 81
    //   265: ldc -115
    //   267: bipush 59
    //   269: sipush 242
    //   272: iconst_2
    //   273: invokestatic 129	xxxxxx/uxxxxx:bbbb0062b0062b0062b0062	(Ljava/lang/String;CCC)Ljava/lang/String;
    //   276: iconst_4
    //   277: anewarray 91	java/lang/Class
    //   280: dup
    //   281: iconst_0
    //   282: ldc 93
    //   284: aastore
    //   285: dup
    //   286: iconst_1
    //   287: getstatic 99	java/lang/Character:TYPE	Ljava/lang/Class;
    //   290: aastore
    //   291: dup
    //   292: iconst_2
    //   293: getstatic 99	java/lang/Character:TYPE	Ljava/lang/Class;
    //   296: aastore
    //   297: dup
    //   298: iconst_3
    //   299: getstatic 99	java/lang/Character:TYPE	Ljava/lang/Class;
    //   302: aastore
    //   303: invokevirtual 103	java/lang/Class:getMethod	(Ljava/lang/String;[Ljava/lang/Class;)Ljava/lang/reflect/Method;
    //   306: astore_1
    //   307: aload_1
    //   308: aconst_null
    //   309: iconst_4
    //   310: anewarray 105	java/lang/Object
    //   313: dup
    //   314: iconst_0
    //   315: ldc -113
    //   317: aastore
    //   318: dup
    //   319: iconst_1
    //   320: bipush 45
    //   322: invokestatic 111	java/lang/Character:valueOf	(C)Ljava/lang/Character;
    //   325: aastore
    //   326: dup
    //   327: iconst_2
    //   328: bipush 70
    //   330: invokestatic 111	java/lang/Character:valueOf	(C)Ljava/lang/Character;
    //   333: aastore
    //   334: dup
    //   335: iconst_3
    //   336: iconst_3
    //   337: invokestatic 111	java/lang/Character:valueOf	(C)Ljava/lang/Character;
    //   340: aastore
    //   341: invokevirtual 117	java/lang/reflect/Method:invoke	(Ljava/lang/Object;[Ljava/lang/Object;)Ljava/lang/Object;
    //   344: astore_1
    //   345: new 2	com/db/pwcc/dbmobile/model/banking/GVO
    //   348: dup
    //   349: aload_1
    //   350: checkcast 93	java/lang/String
    //   353: iconst_3
    //   354: invokespecial 121	com/db/pwcc/dbmobile/model/banking/GVO:<init>	(Ljava/lang/String;I)V
    //   357: putstatic 145	com/db/pwcc/dbmobile/model/banking/GVO:SEPA_CREDIT_TRANSFER_DB_CLIENT_RECEIVER	Lcom/db/pwcc/dbmobile/model/banking/GVO;
    //   360: ldc 81
    //   362: ldc -109
    //   364: bipush 61
    //   366: iconst_2
    //   367: invokestatic 89	xxxxxx/uxxxxx:bb00620062bb0062b0062b0062	(Ljava/lang/String;CC)Ljava/lang/String;
    //   370: iconst_4
    //   371: anewarray 91	java/lang/Class
    //   374: dup
    //   375: iconst_0
    //   376: ldc 93
    //   378: aastore
    //   379: dup
    //   380: iconst_1
    //   381: getstatic 99	java/lang/Character:TYPE	Ljava/lang/Class;
    //   384: aastore
    //   385: dup
    //   386: iconst_2
    //   387: getstatic 99	java/lang/Character:TYPE	Ljava/lang/Class;
    //   390: aastore
    //   391: dup
    //   392: iconst_3
    //   393: getstatic 99	java/lang/Character:TYPE	Ljava/lang/Class;
    //   396: aastore
    //   397: invokevirtual 103	java/lang/Class:getMethod	(Ljava/lang/String;[Ljava/lang/Class;)Ljava/lang/reflect/Method;
    //   400: astore_1
    //   401: aload_1
    //   402: aconst_null
    //   403: iconst_4
    //   404: anewarray 105	java/lang/Object
    //   407: dup
    //   408: iconst_0
    //   409: ldc -107
    //   411: aastore
    //   412: dup
    //   413: iconst_1
    //   414: sipush 220
    //   417: invokestatic 111	java/lang/Character:valueOf	(C)Ljava/lang/Character;
    //   420: aastore
    //   421: dup
    //   422: iconst_2
    //   423: sipush 151
    //   426: invokestatic 111	java/lang/Character:valueOf	(C)Ljava/lang/Character;
    //   429: aastore
    //   430: dup
    //   431: iconst_3
    //   432: iconst_3
    //   433: invokestatic 111	java/lang/Character:valueOf	(C)Ljava/lang/Character;
    //   436: aastore
    //   437: invokevirtual 117	java/lang/reflect/Method:invoke	(Ljava/lang/Object;[Ljava/lang/Object;)Ljava/lang/Object;
    //   440: astore_1
    //   441: new 2	com/db/pwcc/dbmobile/model/banking/GVO
    //   444: dup
    //   445: aload_1
    //   446: checkcast 93	java/lang/String
    //   449: iconst_4
    //   450: invokespecial 121	com/db/pwcc/dbmobile/model/banking/GVO:<init>	(Ljava/lang/String;I)V
    //   453: putstatic 151	com/db/pwcc/dbmobile/model/banking/GVO:SEPA_CREDIT_TRANSFER_BULK_OUTGOING	Lcom/db/pwcc/dbmobile/model/banking/GVO;
    //   456: ldc 81
    //   458: ldc -103
    //   460: sipush 172
    //   463: iconst_3
    //   464: invokestatic 89	xxxxxx/uxxxxx:bb00620062bb0062b0062b0062	(Ljava/lang/String;CC)Ljava/lang/String;
    //   467: iconst_3
    //   468: anewarray 91	java/lang/Class
    //   471: dup
    //   472: iconst_0
    //   473: ldc 93
    //   475: aastore
    //   476: dup
    //   477: iconst_1
    //   478: getstatic 99	java/lang/Character:TYPE	Ljava/lang/Class;
    //   481: aastore
    //   482: dup
    //   483: iconst_2
    //   484: getstatic 99	java/lang/Character:TYPE	Ljava/lang/Class;
    //   487: aastore
    //   488: invokevirtual 103	java/lang/Class:getMethod	(Ljava/lang/String;[Ljava/lang/Class;)Ljava/lang/reflect/Method;
    //   491: astore_1
    //   492: aload_1
    //   493: aconst_null
    //   494: iconst_3
    //   495: anewarray 105	java/lang/Object
    //   498: dup
    //   499: iconst_0
    //   500: ldc -101
    //   502: aastore
    //   503: dup
    //   504: iconst_1
    //   505: sipush 135
    //   508: invokestatic 111	java/lang/Character:valueOf	(C)Ljava/lang/Character;
    //   511: aastore
    //   512: dup
    //   513: iconst_2
    //   514: iconst_4
    //   515: invokestatic 111	java/lang/Character:valueOf	(C)Ljava/lang/Character;
    //   518: aastore
    //   519: invokevirtual 117	java/lang/reflect/Method:invoke	(Ljava/lang/Object;[Ljava/lang/Object;)Ljava/lang/Object;
    //   522: astore_1
    //   523: new 2	com/db/pwcc/dbmobile/model/banking/GVO
    //   526: dup
    //   527: aload_1
    //   528: checkcast 93	java/lang/String
    //   531: iconst_5
    //   532: invokespecial 121	com/db/pwcc/dbmobile/model/banking/GVO:<init>	(Ljava/lang/String;I)V
    //   535: putstatic 157	com/db/pwcc/dbmobile/model/banking/GVO:SEPA_CREDIT_TRANSFER_BULK_INCOMING	Lcom/db/pwcc/dbmobile/model/banking/GVO;
    //   538: invokestatic 161	com/db/pwcc/dbmobile/model/banking/GVO:b0071qqq00710071qq	()I
    //   541: istore_0
    //   542: iload_0
    //   543: invokestatic 164	com/db/pwcc/dbmobile/model/banking/GVO:b00710071qq00710071qq	()I
    //   546: iload_0
    //   547: iadd
    //   548: imul
    //   549: invokestatic 167	com/db/pwcc/dbmobile/model/banking/GVO:bqq0071q00710071qq	()I
    //   552: irem
    //   553: tableswitch	default:+19->572, 0:+19->572
    //   572: ldc 81
    //   574: ldc -87
    //   576: sipush 181
    //   579: iconst_1
    //   580: invokestatic 89	xxxxxx/uxxxxx:bb00620062bb0062b0062b0062	(Ljava/lang/String;CC)Ljava/lang/String;
    //   583: iconst_4
    //   584: anewarray 91	java/lang/Class
    //   587: dup
    //   588: iconst_0
    //   589: ldc 93
    //   591: aastore
    //   592: dup
    //   593: iconst_1
    //   594: getstatic 99	java/lang/Character:TYPE	Ljava/lang/Class;
    //   597: aastore
    //   598: dup
    //   599: iconst_2
    //   600: getstatic 99	java/lang/Character:TYPE	Ljava/lang/Class;
    //   603: aastore
    //   604: dup
    //   605: iconst_3
    //   606: getstatic 99	java/lang/Character:TYPE	Ljava/lang/Class;
    //   609: aastore
    //   610: invokevirtual 103	java/lang/Class:getMethod	(Ljava/lang/String;[Ljava/lang/Class;)Ljava/lang/reflect/Method;
    //   613: astore_1
    //   614: aload_1
    //   615: aconst_null
    //   616: iconst_4
    //   617: anewarray 105	java/lang/Object
    //   620: dup
    //   621: iconst_0
    //   622: ldc -85
    //   624: aastore
    //   625: dup
    //   626: iconst_1
    //   627: bipush 63
    //   629: invokestatic 111	java/lang/Character:valueOf	(C)Ljava/lang/Character;
    //   632: aastore
    //   633: dup
    //   634: iconst_2
    //   635: sipush 233
    //   638: invokestatic 111	java/lang/Character:valueOf	(C)Ljava/lang/Character;
    //   641: aastore
    //   642: dup
    //   643: iconst_3
    //   644: iconst_2
    //   645: invokestatic 111	java/lang/Character:valueOf	(C)Ljava/lang/Character;
    //   648: aastore
    //   649: invokevirtual 117	java/lang/reflect/Method:invoke	(Ljava/lang/Object;[Ljava/lang/Object;)Ljava/lang/Object;
    //   652: astore_1
    //   653: new 2	com/db/pwcc/dbmobile/model/banking/GVO
    //   656: dup
    //   657: aload_1
    //   658: checkcast 93	java/lang/String
    //   661: bipush 6
    //   663: invokespecial 121	com/db/pwcc/dbmobile/model/banking/GVO:<init>	(Ljava/lang/String;I)V
    //   666: putstatic 173	com/db/pwcc/dbmobile/model/banking/GVO:RETURNED_SEPA_CREDIT_TRANSFER	Lcom/db/pwcc/dbmobile/model/banking/GVO;
    //   669: ldc 81
    //   671: ldc -81
    //   673: sipush 197
    //   676: iconst_0
    //   677: invokestatic 89	xxxxxx/uxxxxx:bb00620062bb0062b0062b0062	(Ljava/lang/String;CC)Ljava/lang/String;
    //   680: iconst_3
    //   681: anewarray 91	java/lang/Class
    //   684: dup
    //   685: iconst_0
    //   686: ldc 93
    //   688: aastore
    //   689: dup
    //   690: iconst_1
    //   691: getstatic 99	java/lang/Character:TYPE	Ljava/lang/Class;
    //   694: aastore
    //   695: dup
    //   696: iconst_2
    //   697: getstatic 99	java/lang/Character:TYPE	Ljava/lang/Class;
    //   700: aastore
    //   701: invokevirtual 103	java/lang/Class:getMethod	(Ljava/lang/String;[Ljava/lang/Class;)Ljava/lang/reflect/Method;
    //   704: astore_1
    //   705: aload_1
    //   706: aconst_null
    //   707: iconst_3
    //   708: anewarray 105	java/lang/Object
    //   711: dup
    //   712: iconst_0
    //   713: ldc -79
    //   715: aastore
    //   716: dup
    //   717: iconst_1
    //   718: sipush 191
    //   721: invokestatic 111	java/lang/Character:valueOf	(C)Ljava/lang/Character;
    //   724: aastore
    //   725: dup
    //   726: iconst_2
    //   727: iconst_4
    //   728: invokestatic 111	java/lang/Character:valueOf	(C)Ljava/lang/Character;
    //   731: aastore
    //   732: invokevirtual 117	java/lang/reflect/Method:invoke	(Ljava/lang/Object;[Ljava/lang/Object;)Ljava/lang/Object;
    //   735: astore_1
    //   736: new 2	com/db/pwcc/dbmobile/model/banking/GVO
    //   739: dup
    //   740: aload_1
    //   741: checkcast 93	java/lang/String
    //   744: bipush 7
    //   746: invokespecial 121	com/db/pwcc/dbmobile/model/banking/GVO:<init>	(Ljava/lang/String;I)V
    //   749: putstatic 179	com/db/pwcc/dbmobile/model/banking/GVO:INCOMING_SEPA_DIRECT_DEBIT_DB_CLIENT_PAYER_B_2_B	Lcom/db/pwcc/dbmobile/model/banking/GVO;
    //   752: ldc 81
    //   754: ldc -75
    //   756: bipush 57
    //   758: iconst_3
    //   759: invokestatic 89	xxxxxx/uxxxxx:bb00620062bb0062b0062b0062	(Ljava/lang/String;CC)Ljava/lang/String;
    //   762: iconst_3
    //   763: anewarray 91	java/lang/Class
    //   766: dup
    //   767: iconst_0
    //   768: ldc 93
    //   770: aastore
    //   771: dup
    //   772: iconst_1
    //   773: getstatic 99	java/lang/Character:TYPE	Ljava/lang/Class;
    //   776: aastore
    //   777: dup
    //   778: iconst_2
    //   779: getstatic 99	java/lang/Character:TYPE	Ljava/lang/Class;
    //   782: aastore
    //   783: invokevirtual 103	java/lang/Class:getMethod	(Ljava/lang/String;[Ljava/lang/Class;)Ljava/lang/reflect/Method;
    //   786: astore_1
    //   787: aload_1
    //   788: aconst_null
    //   789: iconst_3
    //   790: anewarray 105	java/lang/Object
    //   793: dup
    //   794: iconst_0
    //   795: ldc -73
    //   797: aastore
    //   798: dup
    //   799: iconst_1
    //   800: bipush 91
    //   802: invokestatic 111	java/lang/Character:valueOf	(C)Ljava/lang/Character;
    //   805: aastore
    //   806: dup
    //   807: iconst_2
    //   808: iconst_1
    //   809: invokestatic 111	java/lang/Character:valueOf	(C)Ljava/lang/Character;
    //   812: aastore
    //   813: invokevirtual 117	java/lang/reflect/Method:invoke	(Ljava/lang/Object;[Ljava/lang/Object;)Ljava/lang/Object;
    //   816: astore_1
    //   817: new 2	com/db/pwcc/dbmobile/model/banking/GVO
    //   820: dup
    //   821: aload_1
    //   822: checkcast 93	java/lang/String
    //   825: bipush 8
    //   827: invokespecial 121	com/db/pwcc/dbmobile/model/banking/GVO:<init>	(Ljava/lang/String;I)V
    //   830: putstatic 185	com/db/pwcc/dbmobile/model/banking/GVO:INCOMING_SEPA_DIRECT_DEBIT_DB_CLIENT_PAYER_CORE	Lcom/db/pwcc/dbmobile/model/banking/GVO;
    //   833: ldc 81
    //   835: ldc -69
    //   837: sipush 253
    //   840: iconst_4
    //   841: invokestatic 89	xxxxxx/uxxxxx:bb00620062bb0062b0062b0062	(Ljava/lang/String;CC)Ljava/lang/String;
    //   844: iconst_3
    //   845: anewarray 91	java/lang/Class
    //   848: dup
    //   849: iconst_0
    //   850: ldc 93
    //   852: aastore
    //   853: dup
    //   854: iconst_1
    //   855: getstatic 99	java/lang/Character:TYPE	Ljava/lang/Class;
    //   858: aastore
    //   859: dup
    //   860: iconst_2
    //   861: getstatic 99	java/lang/Character:TYPE	Ljava/lang/Class;
    //   864: aastore
    //   865: invokevirtual 103	java/lang/Class:getMethod	(Ljava/lang/String;[Ljava/lang/Class;)Ljava/lang/reflect/Method;
    //   868: astore_1
    //   869: aload_1
    //   870: aconst_null
    //   871: iconst_3
    //   872: anewarray 105	java/lang/Object
    //   875: dup
    //   876: iconst_0
    //   877: ldc -67
    //   879: aastore
    //   880: dup
    //   881: iconst_1
    //   882: bipush 12
    //   884: invokestatic 111	java/lang/Character:valueOf	(C)Ljava/lang/Character;
    //   887: aastore
    //   888: dup
    //   889: iconst_2
    //   890: iconst_0
    //   891: invokestatic 111	java/lang/Character:valueOf	(C)Ljava/lang/Character;
    //   894: aastore
    //   895: invokevirtual 117	java/lang/reflect/Method:invoke	(Ljava/lang/Object;[Ljava/lang/Object;)Ljava/lang/Object;
    //   898: astore_1
    //   899: new 2	com/db/pwcc/dbmobile/model/banking/GVO
    //   902: dup
    //   903: aload_1
    //   904: checkcast 93	java/lang/String
    //   907: bipush 9
    //   909: invokespecial 121	com/db/pwcc/dbmobile/model/banking/GVO:<init>	(Ljava/lang/String;I)V
    //   912: putstatic 191	com/db/pwcc/dbmobile/model/banking/GVO:OUTGOING_SEPA_DIRECT_DEBIT_DB_CLIENT_BENEFICIARY_B_2_B	Lcom/db/pwcc/dbmobile/model/banking/GVO;
    //   915: ldc 81
    //   917: ldc -63
    //   919: iconst_5
    //   920: sipush 129
    //   923: iconst_2
    //   924: invokestatic 129	xxxxxx/uxxxxx:bbbb0062b0062b0062b0062	(Ljava/lang/String;CCC)Ljava/lang/String;
    //   927: iconst_3
    //   928: anewarray 91	java/lang/Class
    //   931: dup
    //   932: iconst_0
    //   933: ldc 93
    //   935: aastore
    //   936: dup
    //   937: iconst_1
    //   938: getstatic 99	java/lang/Character:TYPE	Ljava/lang/Class;
    //   941: aastore
    //   942: dup
    //   943: iconst_2
    //   944: getstatic 99	java/lang/Character:TYPE	Ljava/lang/Class;
    //   947: aastore
    //   948: invokevirtual 103	java/lang/Class:getMethod	(Ljava/lang/String;[Ljava/lang/Class;)Ljava/lang/reflect/Method;
    //   951: astore_1
    //   952: aload_1
    //   953: aconst_null
    //   954: iconst_3
    //   955: anewarray 105	java/lang/Object
    //   958: dup
    //   959: iconst_0
    //   960: ldc -61
    //   962: aastore
    //   963: dup
    //   964: iconst_1
    //   965: bipush 89
    //   967: invokestatic 111	java/lang/Character:valueOf	(C)Ljava/lang/Character;
    //   970: aastore
    //   971: dup
    //   972: iconst_2
    //   973: iconst_0
    //   974: invokestatic 111	java/lang/Character:valueOf	(C)Ljava/lang/Character;
    //   977: aastore
    //   978: invokevirtual 117	java/lang/reflect/Method:invoke	(Ljava/lang/Object;[Ljava/lang/Object;)Ljava/lang/Object;
    //   981: astore_1
    //   982: new 2	com/db/pwcc/dbmobile/model/banking/GVO
    //   985: dup
    //   986: aload_1
    //   987: checkcast 93	java/lang/String
    //   990: bipush 10
    //   992: invokespecial 121	com/db/pwcc/dbmobile/model/banking/GVO:<init>	(Ljava/lang/String;I)V
    //   995: putstatic 197	com/db/pwcc/dbmobile/model/banking/GVO:OUTGOING_SEPA_DIRECT_DEBIT_DB_CLIENT_BENEFICIARY_B_2_B_174	Lcom/db/pwcc/dbmobile/model/banking/GVO;
    //   998: ldc 81
    //   1000: ldc -57
    //   1002: bipush 116
    //   1004: iconst_2
    //   1005: invokestatic 89	xxxxxx/uxxxxx:bb00620062bb0062b0062b0062	(Ljava/lang/String;CC)Ljava/lang/String;
    //   1008: iconst_3
    //   1009: anewarray 91	java/lang/Class
    //   1012: dup
    //   1013: iconst_0
    //   1014: ldc 93
    //   1016: aastore
    //   1017: dup
    //   1018: iconst_1
    //   1019: getstatic 99	java/lang/Character:TYPE	Ljava/lang/Class;
    //   1022: aastore
    //   1023: dup
    //   1024: iconst_2
    //   1025: getstatic 99	java/lang/Character:TYPE	Ljava/lang/Class;
    //   1028: aastore
    //   1029: invokevirtual 103	java/lang/Class:getMethod	(Ljava/lang/String;[Ljava/lang/Class;)Ljava/lang/reflect/Method;
    //   1032: astore_1
    //   1033: aload_1
    //   1034: aconst_null
    //   1035: iconst_3
    //   1036: anewarray 105	java/lang/Object
    //   1039: dup
    //   1040: iconst_0
    //   1041: ldc -55
    //   1043: aastore
    //   1044: dup
    //   1045: iconst_1
    //   1046: bipush 49
    //   1048: invokestatic 111	java/lang/Character:valueOf	(C)Ljava/lang/Character;
    //   1051: aastore
    //   1052: dup
    //   1053: iconst_2
    //   1054: iconst_0
    //   1055: invokestatic 111	java/lang/Character:valueOf	(C)Ljava/lang/Character;
    //   1058: aastore
    //   1059: invokevirtual 117	java/lang/reflect/Method:invoke	(Ljava/lang/Object;[Ljava/lang/Object;)Ljava/lang/Object;
    //   1062: astore_1
    //   1063: new 2	com/db/pwcc/dbmobile/model/banking/GVO
    //   1066: dup
    //   1067: aload_1
    //   1068: checkcast 93	java/lang/String
    //   1071: bipush 11
    //   1073: invokespecial 121	com/db/pwcc/dbmobile/model/banking/GVO:<init>	(Ljava/lang/String;I)V
    //   1076: putstatic 203	com/db/pwcc/dbmobile/model/banking/GVO:BULK_SEPA_DIRECT_DEBIT_CORE	Lcom/db/pwcc/dbmobile/model/banking/GVO;
    //   1079: ldc 81
    //   1081: ldc -51
    //   1083: bipush 50
    //   1085: iconst_4
    //   1086: invokestatic 89	xxxxxx/uxxxxx:bb00620062bb0062b0062b0062	(Ljava/lang/String;CC)Ljava/lang/String;
    //   1089: iconst_3
    //   1090: anewarray 91	java/lang/Class
    //   1093: dup
    //   1094: iconst_0
    //   1095: ldc 93
    //   1097: aastore
    //   1098: dup
    //   1099: iconst_1
    //   1100: getstatic 99	java/lang/Character:TYPE	Ljava/lang/Class;
    //   1103: aastore
    //   1104: dup
    //   1105: iconst_2
    //   1106: getstatic 99	java/lang/Character:TYPE	Ljava/lang/Class;
    //   1109: aastore
    //   1110: invokevirtual 103	java/lang/Class:getMethod	(Ljava/lang/String;[Ljava/lang/Class;)Ljava/lang/reflect/Method;
    //   1113: astore_1
    //   1114: aload_1
    //   1115: aconst_null
    //   1116: iconst_3
    //   1117: anewarray 105	java/lang/Object
    //   1120: dup
    //   1121: iconst_0
    //   1122: ldc -49
    //   1124: aastore
    //   1125: dup
    //   1126: iconst_1
    //   1127: bipush 100
    //   1129: invokestatic 111	java/lang/Character:valueOf	(C)Ljava/lang/Character;
    //   1132: aastore
    //   1133: dup
    //   1134: iconst_2
    //   1135: iconst_2
    //   1136: invokestatic 111	java/lang/Character:valueOf	(C)Ljava/lang/Character;
    //   1139: aastore
    //   1140: invokevirtual 117	java/lang/reflect/Method:invoke	(Ljava/lang/Object;[Ljava/lang/Object;)Ljava/lang/Object;
    //   1143: astore_1
    //   1144: new 2	com/db/pwcc/dbmobile/model/banking/GVO
    //   1147: dup
    //   1148: aload_1
    //   1149: checkcast 93	java/lang/String
    //   1152: bipush 12
    //   1154: invokespecial 121	com/db/pwcc/dbmobile/model/banking/GVO:<init>	(Ljava/lang/String;I)V
    //   1157: putstatic 209	com/db/pwcc/dbmobile/model/banking/GVO:BULK_SEPA_DIRECT_DEBIT	Lcom/db/pwcc/dbmobile/model/banking/GVO;
    //   1160: ldc 81
    //   1162: ldc -45
    //   1164: bipush 29
    //   1166: bipush 127
    //   1168: iconst_1
    //   1169: invokestatic 129	xxxxxx/uxxxxx:bbbb0062b0062b0062b0062	(Ljava/lang/String;CCC)Ljava/lang/String;
    //   1172: iconst_3
    //   1173: anewarray 91	java/lang/Class
    //   1176: dup
    //   1177: iconst_0
    //   1178: ldc 93
    //   1180: aastore
    //   1181: dup
    //   1182: iconst_1
    //   1183: getstatic 99	java/lang/Character:TYPE	Ljava/lang/Class;
    //   1186: aastore
    //   1187: dup
    //   1188: iconst_2
    //   1189: getstatic 99	java/lang/Character:TYPE	Ljava/lang/Class;
    //   1192: aastore
    //   1193: invokevirtual 103	java/lang/Class:getMethod	(Ljava/lang/String;[Ljava/lang/Class;)Ljava/lang/reflect/Method;
    //   1196: astore_1
    //   1197: aload_1
    //   1198: aconst_null
    //   1199: iconst_3
    //   1200: anewarray 105	java/lang/Object
    //   1203: dup
    //   1204: iconst_0
    //   1205: ldc -43
    //   1207: aastore
    //   1208: dup
    //   1209: iconst_1
    //   1210: sipush 180
    //   1213: invokestatic 111	java/lang/Character:valueOf	(C)Ljava/lang/Character;
    //   1216: aastore
    //   1217: dup
    //   1218: iconst_2
    //   1219: iconst_3
    //   1220: invokestatic 111	java/lang/Character:valueOf	(C)Ljava/lang/Character;
    //   1223: aastore
    //   1224: invokevirtual 117	java/lang/reflect/Method:invoke	(Ljava/lang/Object;[Ljava/lang/Object;)Ljava/lang/Object;
    //   1227: astore_1
    //   1228: new 2	com/db/pwcc/dbmobile/model/banking/GVO
    //   1231: dup
    //   1232: aload_1
    //   1233: checkcast 93	java/lang/String
    //   1236: bipush 13
    //   1238: invokespecial 121	com/db/pwcc/dbmobile/model/banking/GVO:<init>	(Ljava/lang/String;I)V
    //   1241: putstatic 215	com/db/pwcc/dbmobile/model/banking/GVO:BULK_SEPA_DIRECT_DEBIT_B_2_B	Lcom/db/pwcc/dbmobile/model/banking/GVO;
    //   1244: ldc 81
    //   1246: ldc -39
    //   1248: bipush 83
    //   1250: bipush 112
    //   1252: iconst_0
    //   1253: invokestatic 129	xxxxxx/uxxxxx:bbbb0062b0062b0062b0062	(Ljava/lang/String;CCC)Ljava/lang/String;
    //   1256: iconst_3
    //   1257: anewarray 91	java/lang/Class
    //   1260: dup
    //   1261: iconst_0
    //   1262: ldc 93
    //   1264: aastore
    //   1265: dup
    //   1266: iconst_1
    //   1267: getstatic 99	java/lang/Character:TYPE	Ljava/lang/Class;
    //   1270: aastore
    //   1271: dup
    //   1272: iconst_2
    //   1273: getstatic 99	java/lang/Character:TYPE	Ljava/lang/Class;
    //   1276: aastore
    //   1277: invokevirtual 103	java/lang/Class:getMethod	(Ljava/lang/String;[Ljava/lang/Class;)Ljava/lang/reflect/Method;
    //   1280: astore_1
    //   1281: aload_1
    //   1282: aconst_null
    //   1283: iconst_3
    //   1284: anewarray 105	java/lang/Object
    //   1287: dup
    //   1288: iconst_0
    //   1289: ldc -37
    //   1291: aastore
    //   1292: dup
    //   1293: iconst_1
    //   1294: sipush 191
    //   1297: invokestatic 111	java/lang/Character:valueOf	(C)Ljava/lang/Character;
    //   1300: aastore
    //   1301: dup
    //   1302: iconst_2
    //   1303: iconst_0
    //   1304: invokestatic 111	java/lang/Character:valueOf	(C)Ljava/lang/Character;
    //   1307: aastore
    //   1308: invokevirtual 117	java/lang/reflect/Method:invoke	(Ljava/lang/Object;[Ljava/lang/Object;)Ljava/lang/Object;
    //   1311: astore_1
    //   1312: new 2	com/db/pwcc/dbmobile/model/banking/GVO
    //   1315: dup
    //   1316: aload_1
    //   1317: checkcast 93	java/lang/String
    //   1320: bipush 14
    //   1322: invokespecial 121	com/db/pwcc/dbmobile/model/banking/GVO:<init>	(Ljava/lang/String;I)V
    //   1325: putstatic 221	com/db/pwcc/dbmobile/model/banking/GVO:RETURNED_SEPA_DIRECT_DEBIT_B_2_B_ACTIVE	Lcom/db/pwcc/dbmobile/model/banking/GVO;
    //   1328: ldc 81
    //   1330: ldc -33
    //   1332: sipush 223
    //   1335: bipush 68
    //   1337: iconst_0
    //   1338: invokestatic 129	xxxxxx/uxxxxx:bbbb0062b0062b0062b0062	(Ljava/lang/String;CCC)Ljava/lang/String;
    //   1341: iconst_4
    //   1342: anewarray 91	java/lang/Class
    //   1345: dup
    //   1346: iconst_0
    //   1347: ldc 93
    //   1349: aastore
    //   1350: dup
    //   1351: iconst_1
    //   1352: getstatic 99	java/lang/Character:TYPE	Ljava/lang/Class;
    //   1355: aastore
    //   1356: dup
    //   1357: iconst_2
    //   1358: getstatic 99	java/lang/Character:TYPE	Ljava/lang/Class;
    //   1361: aastore
    //   1362: dup
    //   1363: iconst_3
    //   1364: getstatic 99	java/lang/Character:TYPE	Ljava/lang/Class;
    //   1367: aastore
    //   1368: invokevirtual 103	java/lang/Class:getMethod	(Ljava/lang/String;[Ljava/lang/Class;)Ljava/lang/reflect/Method;
    //   1371: astore_1
    //   1372: aload_1
    //   1373: aconst_null
    //   1374: iconst_4
    //   1375: anewarray 105	java/lang/Object
    //   1378: dup
    //   1379: iconst_0
    //   1380: ldc -31
    //   1382: aastore
    //   1383: dup
    //   1384: iconst_1
    //   1385: sipush 234
    //   1388: invokestatic 111	java/lang/Character:valueOf	(C)Ljava/lang/Character;
    //   1391: aastore
    //   1392: dup
    //   1393: iconst_2
    //   1394: sipush 195
    //   1397: invokestatic 111	java/lang/Character:valueOf	(C)Ljava/lang/Character;
    //   1400: aastore
    //   1401: dup
    //   1402: iconst_3
    //   1403: iconst_1
    //   1404: invokestatic 111	java/lang/Character:valueOf	(C)Ljava/lang/Character;
    //   1407: aastore
    //   1408: invokevirtual 117	java/lang/reflect/Method:invoke	(Ljava/lang/Object;[Ljava/lang/Object;)Ljava/lang/Object;
    //   1411: astore_1
    //   1412: new 2	com/db/pwcc/dbmobile/model/banking/GVO
    //   1415: dup
    //   1416: aload_1
    //   1417: checkcast 93	java/lang/String
    //   1420: bipush 15
    //   1422: invokespecial 121	com/db/pwcc/dbmobile/model/banking/GVO:<init>	(Ljava/lang/String;I)V
    //   1425: putstatic 227	com/db/pwcc/dbmobile/model/banking/GVO:RETURNED_SEPA_DIRECT_DEBIT_CORE	Lcom/db/pwcc/dbmobile/model/banking/GVO;
    //   1428: ldc 81
    //   1430: ldc -27
    //   1432: sipush 198
    //   1435: iconst_2
    //   1436: invokestatic 89	xxxxxx/uxxxxx:bb00620062bb0062b0062b0062	(Ljava/lang/String;CC)Ljava/lang/String;
    //   1439: iconst_3
    //   1440: anewarray 91	java/lang/Class
    //   1443: dup
    //   1444: iconst_0
    //   1445: ldc 93
    //   1447: aastore
    //   1448: dup
    //   1449: iconst_1
    //   1450: getstatic 99	java/lang/Character:TYPE	Ljava/lang/Class;
    //   1453: aastore
    //   1454: dup
    //   1455: iconst_2
    //   1456: getstatic 99	java/lang/Character:TYPE	Ljava/lang/Class;
    //   1459: aastore
    //   1460: invokevirtual 103	java/lang/Class:getMethod	(Ljava/lang/String;[Ljava/lang/Class;)Ljava/lang/reflect/Method;
    //   1463: astore_1
    //   1464: aload_1
    //   1465: aconst_null
    //   1466: iconst_3
    //   1467: anewarray 105	java/lang/Object
    //   1470: dup
    //   1471: iconst_0
    //   1472: ldc -25
    //   1474: aastore
    //   1475: dup
    //   1476: iconst_1
    //   1477: bipush 86
    //   1479: invokestatic 111	java/lang/Character:valueOf	(C)Ljava/lang/Character;
    //   1482: aastore
    //   1483: dup
    //   1484: iconst_2
    //   1485: iconst_4
    //   1486: invokestatic 111	java/lang/Character:valueOf	(C)Ljava/lang/Character;
    //   1489: aastore
    //   1490: invokevirtual 117	java/lang/reflect/Method:invoke	(Ljava/lang/Object;[Ljava/lang/Object;)Ljava/lang/Object;
    //   1493: astore_1
    //   1494: new 2	com/db/pwcc/dbmobile/model/banking/GVO
    //   1497: dup
    //   1498: aload_1
    //   1499: checkcast 93	java/lang/String
    //   1502: bipush 16
    //   1504: invokespecial 121	com/db/pwcc/dbmobile/model/banking/GVO:<init>	(Ljava/lang/String;I)V
    //   1507: putstatic 233	com/db/pwcc/dbmobile/model/banking/GVO:RETURNED_SEPA_DIRECT_DEBIT_PASSIVE	Lcom/db/pwcc/dbmobile/model/banking/GVO;
    //   1510: ldc 81
    //   1512: ldc -21
    //   1514: bipush 114
    //   1516: iconst_3
    //   1517: invokestatic 89	xxxxxx/uxxxxx:bb00620062bb0062b0062b0062	(Ljava/lang/String;CC)Ljava/lang/String;
    //   1520: iconst_4
    //   1521: anewarray 91	java/lang/Class
    //   1524: dup
    //   1525: iconst_0
    //   1526: ldc 93
    //   1528: aastore
    //   1529: dup
    //   1530: iconst_1
    //   1531: getstatic 99	java/lang/Character:TYPE	Ljava/lang/Class;
    //   1534: aastore
    //   1535: dup
    //   1536: iconst_2
    //   1537: getstatic 99	java/lang/Character:TYPE	Ljava/lang/Class;
    //   1540: aastore
    //   1541: dup
    //   1542: iconst_3
    //   1543: getstatic 99	java/lang/Character:TYPE	Ljava/lang/Class;
    //   1546: aastore
    //   1547: invokevirtual 103	java/lang/Class:getMethod	(Ljava/lang/String;[Ljava/lang/Class;)Ljava/lang/reflect/Method;
    //   1550: astore_1
    //   1551: aload_1
    //   1552: aconst_null
    //   1553: iconst_4
    //   1554: anewarray 105	java/lang/Object
    //   1557: dup
    //   1558: iconst_0
    //   1559: ldc -19
    //   1561: aastore
    //   1562: dup
    //   1563: iconst_1
    //   1564: bipush 11
    //   1566: invokestatic 111	java/lang/Character:valueOf	(C)Ljava/lang/Character;
    //   1569: aastore
    //   1570: dup
    //   1571: iconst_2
    //   1572: bipush 88
    //   1574: invokestatic 111	java/lang/Character:valueOf	(C)Ljava/lang/Character;
    //   1577: aastore
    //   1578: dup
    //   1579: iconst_3
    //   1580: iconst_2
    //   1581: invokestatic 111	java/lang/Character:valueOf	(C)Ljava/lang/Character;
    //   1584: aastore
    //   1585: invokevirtual 117	java/lang/reflect/Method:invoke	(Ljava/lang/Object;[Ljava/lang/Object;)Ljava/lang/Object;
    //   1588: astore_1
    //   1589: new 2	com/db/pwcc/dbmobile/model/banking/GVO
    //   1592: dup
    //   1593: aload_1
    //   1594: checkcast 93	java/lang/String
    //   1597: bipush 17
    //   1599: invokespecial 121	com/db/pwcc/dbmobile/model/banking/GVO:<init>	(Ljava/lang/String;I)V
    //   1602: putstatic 239	com/db/pwcc/dbmobile/model/banking/GVO:CHARITY_PAYMENT_TO	Lcom/db/pwcc/dbmobile/model/banking/GVO;
    //   1605: ldc 81
    //   1607: ldc -15
    //   1609: bipush 78
    //   1611: iconst_1
    //   1612: invokestatic 89	xxxxxx/uxxxxx:bb00620062bb0062b0062b0062	(Ljava/lang/String;CC)Ljava/lang/String;
    //   1615: iconst_4
    //   1616: anewarray 91	java/lang/Class
    //   1619: dup
    //   1620: iconst_0
    //   1621: ldc 93
    //   1623: aastore
    //   1624: dup
    //   1625: iconst_1
    //   1626: getstatic 99	java/lang/Character:TYPE	Ljava/lang/Class;
    //   1629: aastore
    //   1630: dup
    //   1631: iconst_2
    //   1632: getstatic 99	java/lang/Character:TYPE	Ljava/lang/Class;
    //   1635: aastore
    //   1636: dup
    //   1637: iconst_3
    //   1638: getstatic 99	java/lang/Character:TYPE	Ljava/lang/Class;
    //   1641: aastore
    //   1642: invokevirtual 103	java/lang/Class:getMethod	(Ljava/lang/String;[Ljava/lang/Class;)Ljava/lang/reflect/Method;
    //   1645: astore_1
    //   1646: aload_1
    //   1647: aconst_null
    //   1648: iconst_4
    //   1649: anewarray 105	java/lang/Object
    //   1652: dup
    //   1653: iconst_0
    //   1654: ldc -13
    //   1656: aastore
    //   1657: dup
    //   1658: iconst_1
    //   1659: bipush 32
    //   1661: invokestatic 111	java/lang/Character:valueOf	(C)Ljava/lang/Character;
    //   1664: aastore
    //   1665: dup
    //   1666: iconst_2
    //   1667: sipush 244
    //   1670: invokestatic 111	java/lang/Character:valueOf	(C)Ljava/lang/Character;
    //   1673: aastore
    //   1674: dup
    //   1675: iconst_3
    //   1676: iconst_1
    //   1677: invokestatic 111	java/lang/Character:valueOf	(C)Ljava/lang/Character;
    //   1680: aastore
    //   1681: invokevirtual 117	java/lang/reflect/Method:invoke	(Ljava/lang/Object;[Ljava/lang/Object;)Ljava/lang/Object;
    //   1684: astore_1
    //   1685: new 2	com/db/pwcc/dbmobile/model/banking/GVO
    //   1688: dup
    //   1689: aload_1
    //   1690: checkcast 93	java/lang/String
    //   1693: bipush 18
    //   1695: invokespecial 121	com/db/pwcc/dbmobile/model/banking/GVO:<init>	(Ljava/lang/String;I)V
    //   1698: putstatic 245	com/db/pwcc/dbmobile/model/banking/GVO:SEPA_SALARY_PENSION	Lcom/db/pwcc/dbmobile/model/banking/GVO;
    //   1701: ldc 81
    //   1703: ldc -9
    //   1705: sipush 215
    //   1708: iconst_1
    //   1709: invokestatic 89	xxxxxx/uxxxxx:bb00620062bb0062b0062b0062	(Ljava/lang/String;CC)Ljava/lang/String;
    //   1712: iconst_3
    //   1713: anewarray 91	java/lang/Class
    //   1716: dup
    //   1717: iconst_0
    //   1718: ldc 93
    //   1720: aastore
    //   1721: dup
    //   1722: iconst_1
    //   1723: getstatic 99	java/lang/Character:TYPE	Ljava/lang/Class;
    //   1726: aastore
    //   1727: dup
    //   1728: iconst_2
    //   1729: getstatic 99	java/lang/Character:TYPE	Ljava/lang/Class;
    //   1732: aastore
    //   1733: invokevirtual 103	java/lang/Class:getMethod	(Ljava/lang/String;[Ljava/lang/Class;)Ljava/lang/reflect/Method;
    //   1736: astore_1
    //   1737: aload_1
    //   1738: aconst_null
    //   1739: iconst_3
    //   1740: anewarray 105	java/lang/Object
    //   1743: dup
    //   1744: iconst_0
    //   1745: ldc -7
    //   1747: aastore
    //   1748: dup
    //   1749: iconst_1
    //   1750: bipush 7
    //   1752: invokestatic 111	java/lang/Character:valueOf	(C)Ljava/lang/Character;
    //   1755: aastore
    //   1756: dup
    //   1757: iconst_2
    //   1758: iconst_3
    //   1759: invokestatic 111	java/lang/Character:valueOf	(C)Ljava/lang/Character;
    //   1762: aastore
    //   1763: invokevirtual 117	java/lang/reflect/Method:invoke	(Ljava/lang/Object;[Ljava/lang/Object;)Ljava/lang/Object;
    //   1766: astore_1
    //   1767: new 2	com/db/pwcc/dbmobile/model/banking/GVO
    //   1770: dup
    //   1771: aload_1
    //   1772: checkcast 93	java/lang/String
    //   1775: bipush 19
    //   1777: invokespecial 121	com/db/pwcc/dbmobile/model/banking/GVO:<init>	(Ljava/lang/String;I)V
    //   1780: putstatic 251	com/db/pwcc/dbmobile/model/banking/GVO:CAPITAL_BUILDING_FRINGE_FORTUNE	Lcom/db/pwcc/dbmobile/model/banking/GVO;
    //   1783: ldc 81
    //   1785: ldc -3
    //   1787: sipush 244
    //   1790: iconst_1
    //   1791: invokestatic 89	xxxxxx/uxxxxx:bb00620062bb0062b0062b0062	(Ljava/lang/String;CC)Ljava/lang/String;
    //   1794: iconst_3
    //   1795: anewarray 91	java/lang/Class
    //   1798: dup
    //   1799: iconst_0
    //   1800: ldc 93
    //   1802: aastore
    //   1803: dup
    //   1804: iconst_1
    //   1805: getstatic 99	java/lang/Character:TYPE	Ljava/lang/Class;
    //   1808: aastore
    //   1809: dup
    //   1810: iconst_2
    //   1811: getstatic 99	java/lang/Character:TYPE	Ljava/lang/Class;
    //   1814: aastore
    //   1815: invokevirtual 103	java/lang/Class:getMethod	(Ljava/lang/String;[Ljava/lang/Class;)Ljava/lang/reflect/Method;
    //   1818: astore_1
    //   1819: aload_1
    //   1820: aconst_null
    //   1821: iconst_3
    //   1822: anewarray 105	java/lang/Object
    //   1825: dup
    //   1826: iconst_0
    //   1827: ldc -1
    //   1829: aastore
    //   1830: dup
    //   1831: iconst_1
    //   1832: bipush 48
    //   1834: invokestatic 111	java/lang/Character:valueOf	(C)Ljava/lang/Character;
    //   1837: aastore
    //   1838: dup
    //   1839: iconst_2
    //   1840: iconst_3
    //   1841: invokestatic 111	java/lang/Character:valueOf	(C)Ljava/lang/Character;
    //   1844: aastore
    //   1845: invokevirtual 117	java/lang/reflect/Method:invoke	(Ljava/lang/Object;[Ljava/lang/Object;)Ljava/lang/Object;
    //   1848: astore_1
    //   1849: new 2	com/db/pwcc/dbmobile/model/banking/GVO
    //   1852: dup
    //   1853: aload_1
    //   1854: checkcast 93	java/lang/String
    //   1857: bipush 20
    //   1859: invokespecial 121	com/db/pwcc/dbmobile/model/banking/GVO:<init>	(Ljava/lang/String;I)V
    //   1862: putstatic 257	com/db/pwcc/dbmobile/model/banking/GVO:SEPA_PAYMENT_PUBLIC_AUTH	Lcom/db/pwcc/dbmobile/model/banking/GVO;
    //   1865: ldc 81
    //   1867: ldc_w 259
    //   1870: bipush 16
    //   1872: bipush 44
    //   1874: iconst_0
    //   1875: invokestatic 129	xxxxxx/uxxxxx:bbbb0062b0062b0062b0062	(Ljava/lang/String;CCC)Ljava/lang/String;
    //   1878: iconst_3
    //   1879: anewarray 91	java/lang/Class
    //   1882: dup
    //   1883: iconst_0
    //   1884: ldc 93
    //   1886: aastore
    //   1887: dup
    //   1888: iconst_1
    //   1889: getstatic 99	java/lang/Character:TYPE	Ljava/lang/Class;
    //   1892: aastore
    //   1893: dup
    //   1894: iconst_2
    //   1895: getstatic 99	java/lang/Character:TYPE	Ljava/lang/Class;
    //   1898: aastore
    //   1899: invokevirtual 103	java/lang/Class:getMethod	(Ljava/lang/String;[Ljava/lang/Class;)Ljava/lang/reflect/Method;
    //   1902: astore_1
    //   1903: aload_1
    //   1904: aconst_null
    //   1905: iconst_3
    //   1906: anewarray 105	java/lang/Object
    //   1909: dup
    //   1910: iconst_0
    //   1911: ldc_w 261
    //   1914: aastore
    //   1915: dup
    //   1916: iconst_1
    //   1917: sipush 178
    //   1920: invokestatic 111	java/lang/Character:valueOf	(C)Ljava/lang/Character;
    //   1923: aastore
    //   1924: dup
    //   1925: iconst_2
    //   1926: iconst_0
    //   1927: invokestatic 111	java/lang/Character:valueOf	(C)Ljava/lang/Character;
    //   1930: aastore
    //   1931: invokevirtual 117	java/lang/reflect/Method:invoke	(Ljava/lang/Object;[Ljava/lang/Object;)Ljava/lang/Object;
    //   1934: astore_1
    //   1935: new 2	com/db/pwcc/dbmobile/model/banking/GVO
    //   1938: dup
    //   1939: aload_1
    //   1940: checkcast 93	java/lang/String
    //   1943: bipush 21
    //   1945: invokespecial 121	com/db/pwcc/dbmobile/model/banking/GVO:<init>	(Ljava/lang/String;I)V
    //   1948: putstatic 263	com/db/pwcc/dbmobile/model/banking/GVO:CHARITY_PAYMENT_FROM	Lcom/db/pwcc/dbmobile/model/banking/GVO;
    //   1951: ldc 81
    //   1953: ldc_w 265
    //   1956: sipush 206
    //   1959: iconst_2
    //   1960: iconst_3
    //   1961: invokestatic 129	xxxxxx/uxxxxx:bbbb0062b0062b0062b0062	(Ljava/lang/String;CCC)Ljava/lang/String;
    //   1964: iconst_3
    //   1965: anewarray 91	java/lang/Class
    //   1968: dup
    //   1969: iconst_0
    //   1970: ldc 93
    //   1972: aastore
    //   1973: dup
    //   1974: iconst_1
    //   1975: getstatic 99	java/lang/Character:TYPE	Ljava/lang/Class;
    //   1978: aastore
    //   1979: dup
    //   1980: iconst_2
    //   1981: getstatic 99	java/lang/Character:TYPE	Ljava/lang/Class;
    //   1984: aastore
    //   1985: invokevirtual 103	java/lang/Class:getMethod	(Ljava/lang/String;[Ljava/lang/Class;)Ljava/lang/reflect/Method;
    //   1988: astore_1
    //   1989: aload_1
    //   1990: aconst_null
    //   1991: iconst_3
    //   1992: anewarray 105	java/lang/Object
    //   1995: dup
    //   1996: iconst_0
    //   1997: ldc_w 267
    //   2000: aastore
    //   2001: dup
    //   2002: iconst_1
    //   2003: bipush 58
    //   2005: invokestatic 111	java/lang/Character:valueOf	(C)Ljava/lang/Character;
    //   2008: aastore
    //   2009: dup
    //   2010: iconst_2
    //   2011: iconst_1
    //   2012: invokestatic 111	java/lang/Character:valueOf	(C)Ljava/lang/Character;
    //   2015: aastore
    //   2016: invokevirtual 117	java/lang/reflect/Method:invoke	(Ljava/lang/Object;[Ljava/lang/Object;)Ljava/lang/Object;
    //   2019: astore_1
    //   2020: new 2	com/db/pwcc/dbmobile/model/banking/GVO
    //   2023: dup
    //   2024: aload_1
    //   2025: checkcast 93	java/lang/String
    //   2028: bipush 22
    //   2030: invokespecial 121	com/db/pwcc/dbmobile/model/banking/GVO:<init>	(Ljava/lang/String;I)V
    //   2033: putstatic 269	com/db/pwcc/dbmobile/model/banking/GVO:ELECTRONIC_CASH_SETTLEMENT	Lcom/db/pwcc/dbmobile/model/banking/GVO;
    //   2036: ldc 81
    //   2038: ldc_w 271
    //   2041: bipush 9
    //   2043: iconst_5
    //   2044: invokestatic 89	xxxxxx/uxxxxx:bb00620062bb0062b0062b0062	(Ljava/lang/String;CC)Ljava/lang/String;
    //   2047: iconst_4
    //   2048: anewarray 91	java/lang/Class
    //   2051: dup
    //   2052: iconst_0
    //   2053: ldc 93
    //   2055: aastore
    //   2056: dup
    //   2057: iconst_1
    //   2058: getstatic 99	java/lang/Character:TYPE	Ljava/lang/Class;
    //   2061: aastore
    //   2062: dup
    //   2063: iconst_2
    //   2064: getstatic 99	java/lang/Character:TYPE	Ljava/lang/Class;
    //   2067: aastore
    //   2068: dup
    //   2069: iconst_3
    //   2070: getstatic 99	java/lang/Character:TYPE	Ljava/lang/Class;
    //   2073: aastore
    //   2074: invokevirtual 103	java/lang/Class:getMethod	(Ljava/lang/String;[Ljava/lang/Class;)Ljava/lang/reflect/Method;
    //   2077: astore_1
    //   2078: aload_1
    //   2079: aconst_null
    //   2080: iconst_4
    //   2081: anewarray 105	java/lang/Object
    //   2084: dup
    //   2085: iconst_0
    //   2086: ldc_w 273
    //   2089: aastore
    //   2090: dup
    //   2091: iconst_1
    //   2092: sipush 135
    //   2095: invokestatic 111	java/lang/Character:valueOf	(C)Ljava/lang/Character;
    //   2098: aastore
    //   2099: dup
    //   2100: iconst_2
    //   2101: sipush 221
    //   2104: invokestatic 111	java/lang/Character:valueOf	(C)Ljava/lang/Character;
    //   2107: aastore
    //   2108: dup
    //   2109: iconst_3
    //   2110: iconst_3
    //   2111: invokestatic 111	java/lang/Character:valueOf	(C)Ljava/lang/Character;
    //   2114: aastore
    //   2115: invokevirtual 117	java/lang/reflect/Method:invoke	(Ljava/lang/Object;[Ljava/lang/Object;)Ljava/lang/Object;
    //   2118: astore_1
    //   2119: new 2	com/db/pwcc/dbmobile/model/banking/GVO
    //   2122: dup
    //   2123: aload_1
    //   2124: checkcast 93	java/lang/String
    //   2127: bipush 23
    //   2129: invokespecial 121	com/db/pwcc/dbmobile/model/banking/GVO:<init>	(Ljava/lang/String;I)V
    //   2132: putstatic 275	com/db/pwcc/dbmobile/model/banking/GVO:DEBIT_CARD_PAYMENT	Lcom/db/pwcc/dbmobile/model/banking/GVO;
    //   2135: ldc 81
    //   2137: ldc_w 277
    //   2140: sipush 130
    //   2143: sipush 140
    //   2146: iconst_3
    //   2147: invokestatic 129	xxxxxx/uxxxxx:bbbb0062b0062b0062b0062	(Ljava/lang/String;CCC)Ljava/lang/String;
    //   2150: iconst_3
    //   2151: anewarray 91	java/lang/Class
    //   2154: dup
    //   2155: iconst_0
    //   2156: ldc 93
    //   2158: aastore
    //   2159: dup
    //   2160: iconst_1
    //   2161: getstatic 99	java/lang/Character:TYPE	Ljava/lang/Class;
    //   2164: aastore
    //   2165: dup
    //   2166: iconst_2
    //   2167: getstatic 99	java/lang/Character:TYPE	Ljava/lang/Class;
    //   2170: aastore
    //   2171: invokevirtual 103	java/lang/Class:getMethod	(Ljava/lang/String;[Ljava/lang/Class;)Ljava/lang/reflect/Method;
    //   2174: astore_1
    //   2175: aload_1
    //   2176: aconst_null
    //   2177: iconst_3
    //   2178: anewarray 105	java/lang/Object
    //   2181: dup
    //   2182: iconst_0
    //   2183: ldc_w 279
    //   2186: aastore
    //   2187: dup
    //   2188: iconst_1
    //   2189: bipush 21
    //   2191: invokestatic 111	java/lang/Character:valueOf	(C)Ljava/lang/Character;
    //   2194: aastore
    //   2195: dup
    //   2196: iconst_2
    //   2197: iconst_0
    //   2198: invokestatic 111	java/lang/Character:valueOf	(C)Ljava/lang/Character;
    //   2201: aastore
    //   2202: invokevirtual 117	java/lang/reflect/Method:invoke	(Ljava/lang/Object;[Ljava/lang/Object;)Ljava/lang/Object;
    //   2205: astore_1
    //   2206: new 2	com/db/pwcc/dbmobile/model/banking/GVO
    //   2209: dup
    //   2210: aload_1
    //   2211: checkcast 93	java/lang/String
    //   2214: bipush 24
    //   2216: invokespecial 121	com/db/pwcc/dbmobile/model/banking/GVO:<init>	(Ljava/lang/String;I)V
    //   2219: putstatic 281	com/db/pwcc/dbmobile/model/banking/GVO:CASH_WITHDRAWAL	Lcom/db/pwcc/dbmobile/model/banking/GVO;
    //   2222: ldc 81
    //   2224: ldc_w 283
    //   2227: bipush 102
    //   2229: iconst_1
    //   2230: invokestatic 89	xxxxxx/uxxxxx:bb00620062bb0062b0062b0062	(Ljava/lang/String;CC)Ljava/lang/String;
    //   2233: iconst_3
    //   2234: anewarray 91	java/lang/Class
    //   2237: dup
    //   2238: iconst_0
    //   2239: ldc 93
    //   2241: aastore
    //   2242: dup
    //   2243: iconst_1
    //   2244: getstatic 99	java/lang/Character:TYPE	Ljava/lang/Class;
    //   2247: aastore
    //   2248: dup
    //   2249: iconst_2
    //   2250: getstatic 99	java/lang/Character:TYPE	Ljava/lang/Class;
    //   2253: aastore
    //   2254: invokevirtual 103	java/lang/Class:getMethod	(Ljava/lang/String;[Ljava/lang/Class;)Ljava/lang/reflect/Method;
    //   2257: astore_1
    //   2258: aload_1
    //   2259: aconst_null
    //   2260: iconst_3
    //   2261: anewarray 105	java/lang/Object
    //   2264: dup
    //   2265: iconst_0
    //   2266: ldc_w 285
    //   2269: aastore
    //   2270: dup
    //   2271: iconst_1
    //   2272: sipush 232
    //   2275: invokestatic 111	java/lang/Character:valueOf	(C)Ljava/lang/Character;
    //   2278: aastore
    //   2279: dup
    //   2280: iconst_2
    //   2281: iconst_5
    //   2282: invokestatic 111	java/lang/Character:valueOf	(C)Ljava/lang/Character;
    //   2285: aastore
    //   2286: invokevirtual 117	java/lang/reflect/Method:invoke	(Ljava/lang/Object;[Ljava/lang/Object;)Ljava/lang/Object;
    //   2289: astore_1
    //   2290: new 2	com/db/pwcc/dbmobile/model/banking/GVO
    //   2293: dup
    //   2294: aload_1
    //   2295: checkcast 93	java/lang/String
    //   2298: bipush 25
    //   2300: invokespecial 121	com/db/pwcc/dbmobile/model/banking/GVO:<init>	(Ljava/lang/String;I)V
    //   2303: putstatic 287	com/db/pwcc/dbmobile/model/banking/GVO:CHARGE_GELDKARTE	Lcom/db/pwcc/dbmobile/model/banking/GVO;
    //   2306: ldc 81
    //   2308: ldc_w 289
    //   2311: bipush 45
    //   2313: iconst_4
    //   2314: invokestatic 89	xxxxxx/uxxxxx:bb00620062bb0062b0062b0062	(Ljava/lang/String;CC)Ljava/lang/String;
    //   2317: iconst_4
    //   2318: anewarray 91	java/lang/Class
    //   2321: dup
    //   2322: iconst_0
    //   2323: ldc 93
    //   2325: aastore
    //   2326: dup
    //   2327: iconst_1
    //   2328: getstatic 99	java/lang/Character:TYPE	Ljava/lang/Class;
    //   2331: aastore
    //   2332: dup
    //   2333: iconst_2
    //   2334: getstatic 99	java/lang/Character:TYPE	Ljava/lang/Class;
    //   2337: aastore
    //   2338: dup
    //   2339: iconst_3
    //   2340: getstatic 99	java/lang/Character:TYPE	Ljava/lang/Class;
    //   2343: aastore
    //   2344: invokevirtual 103	java/lang/Class:getMethod	(Ljava/lang/String;[Ljava/lang/Class;)Ljava/lang/reflect/Method;
    //   2347: astore_1
    //   2348: aload_1
    //   2349: aconst_null
    //   2350: iconst_4
    //   2351: anewarray 105	java/lang/Object
    //   2354: dup
    //   2355: iconst_0
    //   2356: ldc_w 291
    //   2359: aastore
    //   2360: dup
    //   2361: iconst_1
    //   2362: bipush 52
    //   2364: invokestatic 111	java/lang/Character:valueOf	(C)Ljava/lang/Character;
    //   2367: aastore
    //   2368: dup
    //   2369: iconst_2
    //   2370: sipush 147
    //   2373: invokestatic 111	java/lang/Character:valueOf	(C)Ljava/lang/Character;
    //   2376: aastore
    //   2377: dup
    //   2378: iconst_3
    //   2379: iconst_0
    //   2380: invokestatic 111	java/lang/Character:valueOf	(C)Ljava/lang/Character;
    //   2383: aastore
    //   2384: invokevirtual 117	java/lang/reflect/Method:invoke	(Ljava/lang/Object;[Ljava/lang/Object;)Ljava/lang/Object;
    //   2387: astore_1
    //   2388: new 2	com/db/pwcc/dbmobile/model/banking/GVO
    //   2391: dup
    //   2392: aload_1
    //   2393: checkcast 93	java/lang/String
    //   2396: bipush 26
    //   2398: invokespecial 121	com/db/pwcc/dbmobile/model/banking/GVO:<init>	(Ljava/lang/String;I)V
    //   2401: putstatic 293	com/db/pwcc/dbmobile/model/banking/GVO:ELECTRONIC_CASH_REVERSAL	Lcom/db/pwcc/dbmobile/model/banking/GVO;
    //   2404: ldc 81
    //   2406: ldc_w 295
    //   2409: sipush 193
    //   2412: bipush 93
    //   2414: iconst_0
    //   2415: invokestatic 129	xxxxxx/uxxxxx:bbbb0062b0062b0062b0062	(Ljava/lang/String;CCC)Ljava/lang/String;
    //   2418: iconst_3
    //   2419: anewarray 91	java/lang/Class
    //   2422: dup
    //   2423: iconst_0
    //   2424: ldc 93
    //   2426: aastore
    //   2427: dup
    //   2428: iconst_1
    //   2429: getstatic 99	java/lang/Character:TYPE	Ljava/lang/Class;
    //   2432: aastore
    //   2433: dup
    //   2434: iconst_2
    //   2435: getstatic 99	java/lang/Character:TYPE	Ljava/lang/Class;
    //   2438: aastore
    //   2439: invokevirtual 103	java/lang/Class:getMethod	(Ljava/lang/String;[Ljava/lang/Class;)Ljava/lang/reflect/Method;
    //   2442: astore_1
    //   2443: aload_1
    //   2444: aconst_null
    //   2445: iconst_3
    //   2446: anewarray 105	java/lang/Object
    //   2449: dup
    //   2450: iconst_0
    //   2451: ldc_w 297
    //   2454: aastore
    //   2455: dup
    //   2456: iconst_1
    //   2457: bipush 73
    //   2459: invokestatic 111	java/lang/Character:valueOf	(C)Ljava/lang/Character;
    //   2462: aastore
    //   2463: dup
    //   2464: iconst_2
    //   2465: iconst_1
    //   2466: invokestatic 111	java/lang/Character:valueOf	(C)Ljava/lang/Character;
    //   2469: aastore
    //   2470: invokevirtual 117	java/lang/reflect/Method:invoke	(Ljava/lang/Object;[Ljava/lang/Object;)Ljava/lang/Object;
    //   2473: astore_1
    //   2474: new 2	com/db/pwcc/dbmobile/model/banking/GVO
    //   2477: dup
    //   2478: aload_1
    //   2479: checkcast 93	java/lang/String
    //   2482: bipush 27
    //   2484: invokespecial 121	com/db/pwcc/dbmobile/model/banking/GVO:<init>	(Ljava/lang/String;I)V
    //   2487: putstatic 299	com/db/pwcc/dbmobile/model/banking/GVO:ELECTRONIC_CASH_CREDIT_CORRECTION	Lcom/db/pwcc/dbmobile/model/banking/GVO;
    //   2490: ldc 81
    //   2492: ldc_w 301
    //   2495: sipush 255
    //   2498: iconst_3
    //   2499: invokestatic 89	xxxxxx/uxxxxx:bb00620062bb0062b0062b0062	(Ljava/lang/String;CC)Ljava/lang/String;
    //   2502: iconst_3
    //   2503: anewarray 91	java/lang/Class
    //   2506: dup
    //   2507: iconst_0
    //   2508: ldc 93
    //   2510: aastore
    //   2511: dup
    //   2512: iconst_1
    //   2513: getstatic 99	java/lang/Character:TYPE	Ljava/lang/Class;
    //   2516: aastore
    //   2517: dup
    //   2518: iconst_2
    //   2519: getstatic 99	java/lang/Character:TYPE	Ljava/lang/Class;
    //   2522: aastore
    //   2523: invokevirtual 103	java/lang/Class:getMethod	(Ljava/lang/String;[Ljava/lang/Class;)Ljava/lang/reflect/Method;
    //   2526: astore_1
    //   2527: aload_1
    //   2528: aconst_null
    //   2529: iconst_3
    //   2530: anewarray 105	java/lang/Object
    //   2533: dup
    //   2534: iconst_0
    //   2535: ldc_w 303
    //   2538: aastore
    //   2539: dup
    //   2540: iconst_1
    //   2541: bipush 50
    //   2543: invokestatic 111	java/lang/Character:valueOf	(C)Ljava/lang/Character;
    //   2546: aastore
    //   2547: dup
    //   2548: iconst_2
    //   2549: iconst_4
    //   2550: invokestatic 111	java/lang/Character:valueOf	(C)Ljava/lang/Character;
    //   2553: aastore
    //   2554: invokevirtual 117	java/lang/reflect/Method:invoke	(Ljava/lang/Object;[Ljava/lang/Object;)Ljava/lang/Object;
    //   2557: astore_1
    //   2558: new 2	com/db/pwcc/dbmobile/model/banking/GVO
    //   2561: dup
    //   2562: aload_1
    //   2563: checkcast 93	java/lang/String
    //   2566: bipush 28
    //   2568: invokespecial 121	com/db/pwcc/dbmobile/model/banking/GVO:<init>	(Ljava/lang/String;I)V
    //   2571: putstatic 305	com/db/pwcc/dbmobile/model/banking/GVO:SEPA_DIRECT_DEBIT_RETURN	Lcom/db/pwcc/dbmobile/model/banking/GVO;
    //   2574: ldc 81
    //   2576: ldc_w 307
    //   2579: bipush 37
    //   2581: iconst_0
    //   2582: invokestatic 89	xxxxxx/uxxxxx:bb00620062bb0062b0062b0062	(Ljava/lang/String;CC)Ljava/lang/String;
    //   2585: iconst_4
    //   2586: anewarray 91	java/lang/Class
    //   2589: dup
    //   2590: iconst_0
    //   2591: ldc 93
    //   2593: aastore
    //   2594: dup
    //   2595: iconst_1
    //   2596: getstatic 99	java/lang/Character:TYPE	Ljava/lang/Class;
    //   2599: aastore
    //   2600: dup
    //   2601: iconst_2
    //   2602: getstatic 99	java/lang/Character:TYPE	Ljava/lang/Class;
    //   2605: aastore
    //   2606: dup
    //   2607: iconst_3
    //   2608: getstatic 99	java/lang/Character:TYPE	Ljava/lang/Class;
    //   2611: aastore
    //   2612: invokevirtual 103	java/lang/Class:getMethod	(Ljava/lang/String;[Ljava/lang/Class;)Ljava/lang/reflect/Method;
    //   2615: astore_1
    //   2616: aload_1
    //   2617: aconst_null
    //   2618: iconst_4
    //   2619: anewarray 105	java/lang/Object
    //   2622: dup
    //   2623: iconst_0
    //   2624: ldc_w 309
    //   2627: aastore
    //   2628: dup
    //   2629: iconst_1
    //   2630: sipush 245
    //   2633: invokestatic 111	java/lang/Character:valueOf	(C)Ljava/lang/Character;
    //   2636: aastore
    //   2637: dup
    //   2638: iconst_2
    //   2639: sipush 242
    //   2642: invokestatic 111	java/lang/Character:valueOf	(C)Ljava/lang/Character;
    //   2645: aastore
    //   2646: dup
    //   2647: iconst_3
    //   2648: iconst_3
    //   2649: invokestatic 111	java/lang/Character:valueOf	(C)Ljava/lang/Character;
    //   2652: aastore
    //   2653: invokevirtual 117	java/lang/reflect/Method:invoke	(Ljava/lang/Object;[Ljava/lang/Object;)Ljava/lang/Object;
    //   2656: astore_1
    //   2657: new 2	com/db/pwcc/dbmobile/model/banking/GVO
    //   2660: dup
    //   2661: aload_1
    //   2662: checkcast 93	java/lang/String
    //   2665: bipush 29
    //   2667: invokespecial 121	com/db/pwcc/dbmobile/model/banking/GVO:<init>	(Ljava/lang/String;I)V
    //   2670: putstatic 311	com/db/pwcc/dbmobile/model/banking/GVO:CASH_DEPOSIT	Lcom/db/pwcc/dbmobile/model/banking/GVO;
    //   2673: ldc 81
    //   2675: ldc_w 313
    //   2678: bipush 10
    //   2680: iconst_0
    //   2681: invokestatic 89	xxxxxx/uxxxxx:bb00620062bb0062b0062b0062	(Ljava/lang/String;CC)Ljava/lang/String;
    //   2684: iconst_4
    //   2685: anewarray 91	java/lang/Class
    //   2688: dup
    //   2689: iconst_0
    //   2690: ldc 93
    //   2692: aastore
    //   2693: dup
    //   2694: iconst_1
    //   2695: getstatic 99	java/lang/Character:TYPE	Ljava/lang/Class;
    //   2698: aastore
    //   2699: dup
    //   2700: iconst_2
    //   2701: getstatic 99	java/lang/Character:TYPE	Ljava/lang/Class;
    //   2704: aastore
    //   2705: dup
    //   2706: iconst_3
    //   2707: getstatic 99	java/lang/Character:TYPE	Ljava/lang/Class;
    //   2710: aastore
    //   2711: invokevirtual 103	java/lang/Class:getMethod	(Ljava/lang/String;[Ljava/lang/Class;)Ljava/lang/reflect/Method;
    //   2714: astore_1
    //   2715: aload_1
    //   2716: aconst_null
    //   2717: iconst_4
    //   2718: anewarray 105	java/lang/Object
    //   2721: dup
    //   2722: iconst_0
    //   2723: ldc_w 315
    //   2726: aastore
    //   2727: dup
    //   2728: iconst_1
    //   2729: sipush 142
    //   2732: invokestatic 111	java/lang/Character:valueOf	(C)Ljava/lang/Character;
    //   2735: aastore
    //   2736: dup
    //   2737: iconst_2
    //   2738: sipush 144
    //   2741: invokestatic 111	java/lang/Character:valueOf	(C)Ljava/lang/Character;
    //   2744: aastore
    //   2745: dup
    //   2746: iconst_3
    //   2747: iconst_3
    //   2748: invokestatic 111	java/lang/Character:valueOf	(C)Ljava/lang/Character;
    //   2751: aastore
    //   2752: invokevirtual 117	java/lang/reflect/Method:invoke	(Ljava/lang/Object;[Ljava/lang/Object;)Ljava/lang/Object;
    //   2755: astore_1
    //   2756: new 2	com/db/pwcc/dbmobile/model/banking/GVO
    //   2759: dup
    //   2760: aload_1
    //   2761: checkcast 93	java/lang/String
    //   2764: bipush 30
    //   2766: invokespecial 121	com/db/pwcc/dbmobile/model/banking/GVO:<init>	(Ljava/lang/String;I)V
    //   2769: putstatic 317	com/db/pwcc/dbmobile/model/banking/GVO:PAYDIREKT_PAYMENT	Lcom/db/pwcc/dbmobile/model/banking/GVO;
    //   2772: ldc 81
    //   2774: ldc_w 319
    //   2777: sipush 165
    //   2780: iconst_2
    //   2781: invokestatic 89	xxxxxx/uxxxxx:bb00620062bb0062b0062b0062	(Ljava/lang/String;CC)Ljava/lang/String;
    //   2784: iconst_3
    //   2785: anewarray 91	java/lang/Class
    //   2788: dup
    //   2789: iconst_0
    //   2790: ldc 93
    //   2792: aastore
    //   2793: dup
    //   2794: iconst_1
    //   2795: getstatic 99	java/lang/Character:TYPE	Ljava/lang/Class;
    //   2798: aastore
    //   2799: dup
    //   2800: iconst_2
    //   2801: getstatic 99	java/lang/Character:TYPE	Ljava/lang/Class;
    //   2804: aastore
    //   2805: invokevirtual 103	java/lang/Class:getMethod	(Ljava/lang/String;[Ljava/lang/Class;)Ljava/lang/reflect/Method;
    //   2808: astore_1
    //   2809: aload_1
    //   2810: aconst_null
    //   2811: iconst_3
    //   2812: anewarray 105	java/lang/Object
    //   2815: dup
    //   2816: iconst_0
    //   2817: ldc_w 321
    //   2820: aastore
    //   2821: dup
    //   2822: iconst_1
    //   2823: sipush 162
    //   2826: invokestatic 111	java/lang/Character:valueOf	(C)Ljava/lang/Character;
    //   2829: aastore
    //   2830: dup
    //   2831: iconst_2
    //   2832: iconst_5
    //   2833: invokestatic 111	java/lang/Character:valueOf	(C)Ljava/lang/Character;
    //   2836: aastore
    //   2837: invokevirtual 117	java/lang/reflect/Method:invoke	(Ljava/lang/Object;[Ljava/lang/Object;)Ljava/lang/Object;
    //   2840: astore_1
    //   2841: new 2	com/db/pwcc/dbmobile/model/banking/GVO
    //   2844: dup
    //   2845: aload_1
    //   2846: checkcast 93	java/lang/String
    //   2849: bipush 31
    //   2851: invokespecial 121	com/db/pwcc/dbmobile/model/banking/GVO:<init>	(Ljava/lang/String;I)V
    //   2854: putstatic 323	com/db/pwcc/dbmobile/model/banking/GVO:PAYDIREKT_COLLECTION_CREDIT	Lcom/db/pwcc/dbmobile/model/banking/GVO;
    //   2857: ldc 81
    //   2859: ldc_w 325
    //   2862: bipush 60
    //   2864: sipush 137
    //   2867: iconst_3
    //   2868: invokestatic 129	xxxxxx/uxxxxx:bbbb0062b0062b0062b0062	(Ljava/lang/String;CCC)Ljava/lang/String;
    //   2871: iconst_4
    //   2872: anewarray 91	java/lang/Class
    //   2875: dup
    //   2876: iconst_0
    //   2877: ldc 93
    //   2879: aastore
    //   2880: dup
    //   2881: iconst_1
    //   2882: getstatic 99	java/lang/Character:TYPE	Ljava/lang/Class;
    //   2885: aastore
    //   2886: dup
    //   2887: iconst_2
    //   2888: getstatic 99	java/lang/Character:TYPE	Ljava/lang/Class;
    //   2891: aastore
    //   2892: dup
    //   2893: iconst_3
    //   2894: getstatic 99	java/lang/Character:TYPE	Ljava/lang/Class;
    //   2897: aastore
    //   2898: invokevirtual 103	java/lang/Class:getMethod	(Ljava/lang/String;[Ljava/lang/Class;)Ljava/lang/reflect/Method;
    //   2901: astore_1
    //   2902: aload_1
    //   2903: aconst_null
    //   2904: iconst_4
    //   2905: anewarray 105	java/lang/Object
    //   2908: dup
    //   2909: iconst_0
    //   2910: ldc_w 327
    //   2913: aastore
    //   2914: dup
    //   2915: iconst_1
    //   2916: sipush 229
    //   2919: invokestatic 111	java/lang/Character:valueOf	(C)Ljava/lang/Character;
    //   2922: aastore
    //   2923: dup
    //   2924: iconst_2
    //   2925: sipush 167
    //   2928: invokestatic 111	java/lang/Character:valueOf	(C)Ljava/lang/Character;
    //   2931: aastore
    //   2932: dup
    //   2933: iconst_3
    //   2934: iconst_1
    //   2935: invokestatic 111	java/lang/Character:valueOf	(C)Ljava/lang/Character;
    //   2938: aastore
    //   2939: invokevirtual 117	java/lang/reflect/Method:invoke	(Ljava/lang/Object;[Ljava/lang/Object;)Ljava/lang/Object;
    //   2942: astore_1
    //   2943: new 2	com/db/pwcc/dbmobile/model/banking/GVO
    //   2946: dup
    //   2947: aload_1
    //   2948: checkcast 93	java/lang/String
    //   2951: bipush 32
    //   2953: invokespecial 121	com/db/pwcc/dbmobile/model/banking/GVO:<init>	(Ljava/lang/String;I)V
    //   2956: putstatic 329	com/db/pwcc/dbmobile/model/banking/GVO:PAYDIREKT_INDIVIDUAL_CREDIT	Lcom/db/pwcc/dbmobile/model/banking/GVO;
    //   2959: ldc 81
    //   2961: ldc_w 331
    //   2964: sipush 165
    //   2967: sipush 240
    //   2970: iconst_3
    //   2971: invokestatic 129	xxxxxx/uxxxxx:bbbb0062b0062b0062b0062	(Ljava/lang/String;CCC)Ljava/lang/String;
    //   2974: iconst_3
    //   2975: anewarray 91	java/lang/Class
    //   2978: dup
    //   2979: iconst_0
    //   2980: ldc 93
    //   2982: aastore
    //   2983: dup
    //   2984: iconst_1
    //   2985: getstatic 99	java/lang/Character:TYPE	Ljava/lang/Class;
    //   2988: aastore
    //   2989: dup
    //   2990: iconst_2
    //   2991: getstatic 99	java/lang/Character:TYPE	Ljava/lang/Class;
    //   2994: aastore
    //   2995: invokevirtual 103	java/lang/Class:getMethod	(Ljava/lang/String;[Ljava/lang/Class;)Ljava/lang/reflect/Method;
    //   2998: astore_1
    //   2999: aload_1
    //   3000: aconst_null
    //   3001: iconst_3
    //   3002: anewarray 105	java/lang/Object
    //   3005: dup
    //   3006: iconst_0
    //   3007: ldc_w 333
    //   3010: aastore
    //   3011: dup
    //   3012: iconst_1
    //   3013: sipush 165
    //   3016: invokestatic 111	java/lang/Character:valueOf	(C)Ljava/lang/Character;
    //   3019: aastore
    //   3020: dup
    //   3021: iconst_2
    //   3022: iconst_1
    //   3023: invokestatic 111	java/lang/Character:valueOf	(C)Ljava/lang/Character;
    //   3026: aastore
    //   3027: invokevirtual 117	java/lang/reflect/Method:invoke	(Ljava/lang/Object;[Ljava/lang/Object;)Ljava/lang/Object;
    //   3030: astore_1
    //   3031: new 2	com/db/pwcc/dbmobile/model/banking/GVO
    //   3034: dup
    //   3035: aload_1
    //   3036: checkcast 93	java/lang/String
    //   3039: bipush 33
    //   3041: invokespecial 121	com/db/pwcc/dbmobile/model/banking/GVO:<init>	(Ljava/lang/String;I)V
    //   3044: putstatic 335	com/db/pwcc/dbmobile/model/banking/GVO:PAYDIREKT_BULK_REVERSAL	Lcom/db/pwcc/dbmobile/model/banking/GVO;
    //   3047: ldc 81
    //   3049: ldc_w 337
    //   3052: bipush 95
    //   3054: iconst_5
    //   3055: invokestatic 89	xxxxxx/uxxxxx:bb00620062bb0062b0062b0062	(Ljava/lang/String;CC)Ljava/lang/String;
    //   3058: iconst_3
    //   3059: anewarray 91	java/lang/Class
    //   3062: dup
    //   3063: iconst_0
    //   3064: ldc 93
    //   3066: aastore
    //   3067: dup
    //   3068: iconst_1
    //   3069: getstatic 99	java/lang/Character:TYPE	Ljava/lang/Class;
    //   3072: aastore
    //   3073: dup
    //   3074: iconst_2
    //   3075: getstatic 99	java/lang/Character:TYPE	Ljava/lang/Class;
    //   3078: aastore
    //   3079: invokevirtual 103	java/lang/Class:getMethod	(Ljava/lang/String;[Ljava/lang/Class;)Ljava/lang/reflect/Method;
    //   3082: astore_1
    //   3083: aload_1
    //   3084: aconst_null
    //   3085: iconst_3
    //   3086: anewarray 105	java/lang/Object
    //   3089: dup
    //   3090: iconst_0
    //   3091: ldc_w 339
    //   3094: aastore
    //   3095: dup
    //   3096: iconst_1
    //   3097: sipush 230
    //   3100: invokestatic 111	java/lang/Character:valueOf	(C)Ljava/lang/Character;
    //   3103: aastore
    //   3104: dup
    //   3105: iconst_2
    //   3106: iconst_5
    //   3107: invokestatic 111	java/lang/Character:valueOf	(C)Ljava/lang/Character;
    //   3110: aastore
    //   3111: invokevirtual 117	java/lang/reflect/Method:invoke	(Ljava/lang/Object;[Ljava/lang/Object;)Ljava/lang/Object;
    //   3114: astore_1
    //   3115: new 2	com/db/pwcc/dbmobile/model/banking/GVO
    //   3118: dup
    //   3119: aload_1
    //   3120: checkcast 93	java/lang/String
    //   3123: bipush 34
    //   3125: invokespecial 121	com/db/pwcc/dbmobile/model/banking/GVO:<init>	(Ljava/lang/String;I)V
    //   3128: putstatic 341	com/db/pwcc/dbmobile/model/banking/GVO:PAYDIREKT_REVERSAL	Lcom/db/pwcc/dbmobile/model/banking/GVO;
    //   3131: ldc 81
    //   3133: ldc_w 343
    //   3136: bipush 121
    //   3138: sipush 154
    //   3141: iconst_3
    //   3142: invokestatic 129	xxxxxx/uxxxxx:bbbb0062b0062b0062b0062	(Ljava/lang/String;CCC)Ljava/lang/String;
    //   3145: iconst_4
    //   3146: anewarray 91	java/lang/Class
    //   3149: dup
    //   3150: iconst_0
    //   3151: ldc 93
    //   3153: aastore
    //   3154: dup
    //   3155: iconst_1
    //   3156: getstatic 99	java/lang/Character:TYPE	Ljava/lang/Class;
    //   3159: aastore
    //   3160: dup
    //   3161: iconst_2
    //   3162: getstatic 99	java/lang/Character:TYPE	Ljava/lang/Class;
    //   3165: aastore
    //   3166: dup
    //   3167: iconst_3
    //   3168: getstatic 99	java/lang/Character:TYPE	Ljava/lang/Class;
    //   3171: aastore
    //   3172: invokevirtual 103	java/lang/Class:getMethod	(Ljava/lang/String;[Ljava/lang/Class;)Ljava/lang/reflect/Method;
    //   3175: astore_1
    //   3176: aload_1
    //   3177: aconst_null
    //   3178: iconst_4
    //   3179: anewarray 105	java/lang/Object
    //   3182: dup
    //   3183: iconst_0
    //   3184: ldc_w 345
    //   3187: aastore
    //   3188: dup
    //   3189: iconst_1
    //   3190: bipush 25
    //   3192: invokestatic 111	java/lang/Character:valueOf	(C)Ljava/lang/Character;
    //   3195: aastore
    //   3196: dup
    //   3197: iconst_2
    //   3198: sipush 177
    //   3201: invokestatic 111	java/lang/Character:valueOf	(C)Ljava/lang/Character;
    //   3204: aastore
    //   3205: dup
    //   3206: iconst_3
    //   3207: iconst_1
    //   3208: invokestatic 111	java/lang/Character:valueOf	(C)Ljava/lang/Character;
    //   3211: aastore
    //   3212: invokevirtual 117	java/lang/reflect/Method:invoke	(Ljava/lang/Object;[Ljava/lang/Object;)Ljava/lang/Object;
    //   3215: astore_1
    //   3216: new 2	com/db/pwcc/dbmobile/model/banking/GVO
    //   3219: dup
    //   3220: aload_1
    //   3221: checkcast 93	java/lang/String
    //   3224: bipush 35
    //   3226: invokespecial 121	com/db/pwcc/dbmobile/model/banking/GVO:<init>	(Ljava/lang/String;I)V
    //   3229: putstatic 347	com/db/pwcc/dbmobile/model/banking/GVO:PAYDIREKT_REFUND	Lcom/db/pwcc/dbmobile/model/banking/GVO;
    //   3232: ldc 81
    //   3234: ldc_w 349
    //   3237: bipush 47
    //   3239: iconst_1
    //   3240: invokestatic 89	xxxxxx/uxxxxx:bb00620062bb0062b0062b0062	(Ljava/lang/String;CC)Ljava/lang/String;
    //   3243: iconst_3
    //   3244: anewarray 91	java/lang/Class
    //   3247: dup
    //   3248: iconst_0
    //   3249: ldc 93
    //   3251: aastore
    //   3252: dup
    //   3253: iconst_1
    //   3254: getstatic 99	java/lang/Character:TYPE	Ljava/lang/Class;
    //   3257: aastore
    //   3258: dup
    //   3259: iconst_2
    //   3260: getstatic 99	java/lang/Character:TYPE	Ljava/lang/Class;
    //   3263: aastore
    //   3264: invokevirtual 103	java/lang/Class:getMethod	(Ljava/lang/String;[Ljava/lang/Class;)Ljava/lang/reflect/Method;
    //   3267: astore_1
    //   3268: aload_1
    //   3269: aconst_null
    //   3270: iconst_3
    //   3271: anewarray 105	java/lang/Object
    //   3274: dup
    //   3275: iconst_0
    //   3276: ldc_w 351
    //   3279: aastore
    //   3280: dup
    //   3281: iconst_1
    //   3282: sipush 166
    //   3285: invokestatic 111	java/lang/Character:valueOf	(C)Ljava/lang/Character;
    //   3288: aastore
    //   3289: dup
    //   3290: iconst_2
    //   3291: iconst_0
    //   3292: invokestatic 111	java/lang/Character:valueOf	(C)Ljava/lang/Character;
    //   3295: aastore
    //   3296: invokevirtual 117	java/lang/reflect/Method:invoke	(Ljava/lang/Object;[Ljava/lang/Object;)Ljava/lang/Object;
    //   3299: astore_1
    //   3300: new 2	com/db/pwcc/dbmobile/model/banking/GVO
    //   3303: dup
    //   3304: aload_1
    //   3305: checkcast 93	java/lang/String
    //   3308: bipush 36
    //   3310: invokespecial 121	com/db/pwcc/dbmobile/model/banking/GVO:<init>	(Ljava/lang/String;I)V
    //   3313: putstatic 353	com/db/pwcc/dbmobile/model/banking/GVO:CREDIT_TRANSFER_BULK_RETURN	Lcom/db/pwcc/dbmobile/model/banking/GVO;
    //   3316: ldc 81
    //   3318: ldc_w 355
    //   3321: bipush 95
    //   3323: iconst_1
    //   3324: invokestatic 89	xxxxxx/uxxxxx:bb00620062bb0062b0062b0062	(Ljava/lang/String;CC)Ljava/lang/String;
    //   3327: iconst_3
    //   3328: anewarray 91	java/lang/Class
    //   3331: dup
    //   3332: iconst_0
    //   3333: ldc 93
    //   3335: aastore
    //   3336: dup
    //   3337: iconst_1
    //   3338: getstatic 99	java/lang/Character:TYPE	Ljava/lang/Class;
    //   3341: aastore
    //   3342: dup
    //   3343: iconst_2
    //   3344: getstatic 99	java/lang/Character:TYPE	Ljava/lang/Class;
    //   3347: aastore
    //   3348: invokevirtual 103	java/lang/Class:getMethod	(Ljava/lang/String;[Ljava/lang/Class;)Ljava/lang/reflect/Method;
    //   3351: astore_1
    //   3352: aload_1
    //   3353: aconst_null
    //   3354: iconst_3
    //   3355: anewarray 105	java/lang/Object
    //   3358: dup
    //   3359: iconst_0
    //   3360: ldc_w 357
    //   3363: aastore
    //   3364: dup
    //   3365: iconst_1
    //   3366: sipush 217
    //   3369: invokestatic 111	java/lang/Character:valueOf	(C)Ljava/lang/Character;
    //   3372: aastore
    //   3373: dup
    //   3374: iconst_2
    //   3375: iconst_5
    //   3376: invokestatic 111	java/lang/Character:valueOf	(C)Ljava/lang/Character;
    //   3379: aastore
    //   3380: invokevirtual 117	java/lang/reflect/Method:invoke	(Ljava/lang/Object;[Ljava/lang/Object;)Ljava/lang/Object;
    //   3383: astore_1
    //   3384: new 2	com/db/pwcc/dbmobile/model/banking/GVO
    //   3387: dup
    //   3388: aload_1
    //   3389: checkcast 93	java/lang/String
    //   3392: bipush 37
    //   3394: invokespecial 121	com/db/pwcc/dbmobile/model/banking/GVO:<init>	(Ljava/lang/String;I)V
    //   3397: putstatic 359	com/db/pwcc/dbmobile/model/banking/GVO:SEPA_DIRECT_DEBIT_REVERSAL	Lcom/db/pwcc/dbmobile/model/banking/GVO;
    //   3400: ldc 81
    //   3402: ldc_w 361
    //   3405: bipush 48
    //   3407: iconst_1
    //   3408: invokestatic 89	xxxxxx/uxxxxx:bb00620062bb0062b0062b0062	(Ljava/lang/String;CC)Ljava/lang/String;
    //   3411: iconst_3
    //   3412: anewarray 91	java/lang/Class
    //   3415: dup
    //   3416: iconst_0
    //   3417: ldc 93
    //   3419: aastore
    //   3420: dup
    //   3421: iconst_1
    //   3422: getstatic 99	java/lang/Character:TYPE	Ljava/lang/Class;
    //   3425: aastore
    //   3426: dup
    //   3427: iconst_2
    //   3428: getstatic 99	java/lang/Character:TYPE	Ljava/lang/Class;
    //   3431: aastore
    //   3432: invokevirtual 103	java/lang/Class:getMethod	(Ljava/lang/String;[Ljava/lang/Class;)Ljava/lang/reflect/Method;
    //   3435: astore_1
    //   3436: aload_1
    //   3437: aconst_null
    //   3438: iconst_3
    //   3439: anewarray 105	java/lang/Object
    //   3442: dup
    //   3443: iconst_0
    //   3444: ldc_w 363
    //   3447: aastore
    //   3448: dup
    //   3449: iconst_1
    //   3450: sipush 217
    //   3453: invokestatic 111	java/lang/Character:valueOf	(C)Ljava/lang/Character;
    //   3456: aastore
    //   3457: dup
    //   3458: iconst_2
    //   3459: iconst_3
    //   3460: invokestatic 111	java/lang/Character:valueOf	(C)Ljava/lang/Character;
    //   3463: aastore
    //   3464: invokevirtual 117	java/lang/reflect/Method:invoke	(Ljava/lang/Object;[Ljava/lang/Object;)Ljava/lang/Object;
    //   3467: astore_1
    //   3468: new 2	com/db/pwcc/dbmobile/model/banking/GVO
    //   3471: dup
    //   3472: aload_1
    //   3473: checkcast 93	java/lang/String
    //   3476: bipush 38
    //   3478: invokespecial 121	com/db/pwcc/dbmobile/model/banking/GVO:<init>	(Ljava/lang/String;I)V
    //   3481: putstatic 365	com/db/pwcc/dbmobile/model/banking/GVO:SEPA_DIRECT_DEBIT_REVERSAL_B_2_B	Lcom/db/pwcc/dbmobile/model/banking/GVO;
    //   3484: ldc 81
    //   3486: ldc_w 367
    //   3489: bipush 43
    //   3491: iconst_1
    //   3492: invokestatic 89	xxxxxx/uxxxxx:bb00620062bb0062b0062b0062	(Ljava/lang/String;CC)Ljava/lang/String;
    //   3495: iconst_4
    //   3496: anewarray 91	java/lang/Class
    //   3499: dup
    //   3500: iconst_0
    //   3501: ldc 93
    //   3503: aastore
    //   3504: dup
    //   3505: iconst_1
    //   3506: getstatic 99	java/lang/Character:TYPE	Ljava/lang/Class;
    //   3509: aastore
    //   3510: dup
    //   3511: iconst_2
    //   3512: getstatic 99	java/lang/Character:TYPE	Ljava/lang/Class;
    //   3515: aastore
    //   3516: dup
    //   3517: iconst_3
    //   3518: getstatic 99	java/lang/Character:TYPE	Ljava/lang/Class;
    //   3521: aastore
    //   3522: invokevirtual 103	java/lang/Class:getMethod	(Ljava/lang/String;[Ljava/lang/Class;)Ljava/lang/reflect/Method;
    //   3525: astore_1
    //   3526: aload_1
    //   3527: aconst_null
    //   3528: iconst_4
    //   3529: anewarray 105	java/lang/Object
    //   3532: dup
    //   3533: iconst_0
    //   3534: ldc_w 369
    //   3537: aastore
    //   3538: dup
    //   3539: iconst_1
    //   3540: sipush 213
    //   3543: invokestatic 111	java/lang/Character:valueOf	(C)Ljava/lang/Character;
    //   3546: aastore
    //   3547: dup
    //   3548: iconst_2
    //   3549: bipush 109
    //   3551: invokestatic 111	java/lang/Character:valueOf	(C)Ljava/lang/Character;
    //   3554: aastore
    //   3555: dup
    //   3556: iconst_3
    //   3557: iconst_0
    //   3558: invokestatic 111	java/lang/Character:valueOf	(C)Ljava/lang/Character;
    //   3561: aastore
    //   3562: invokevirtual 117	java/lang/reflect/Method:invoke	(Ljava/lang/Object;[Ljava/lang/Object;)Ljava/lang/Object;
    //   3565: astore_1
    //   3566: new 2	com/db/pwcc/dbmobile/model/banking/GVO
    //   3569: dup
    //   3570: aload_1
    //   3571: checkcast 93	java/lang/String
    //   3574: bipush 39
    //   3576: invokespecial 121	com/db/pwcc/dbmobile/model/banking/GVO:<init>	(Ljava/lang/String;I)V
    //   3579: putstatic 371	com/db/pwcc/dbmobile/model/banking/GVO:DIRECT_DEBIT_BULK_RETURN_B_2_B	Lcom/db/pwcc/dbmobile/model/banking/GVO;
    //   3582: ldc 81
    //   3584: ldc_w 373
    //   3587: bipush 35
    //   3589: bipush 40
    //   3591: iconst_1
    //   3592: invokestatic 129	xxxxxx/uxxxxx:bbbb0062b0062b0062b0062	(Ljava/lang/String;CCC)Ljava/lang/String;
    //   3595: iconst_3
    //   3596: anewarray 91	java/lang/Class
    //   3599: dup
    //   3600: iconst_0
    //   3601: ldc 93
    //   3603: aastore
    //   3604: dup
    //   3605: iconst_1
    //   3606: getstatic 99	java/lang/Character:TYPE	Ljava/lang/Class;
    //   3609: aastore
    //   3610: dup
    //   3611: iconst_2
    //   3612: getstatic 99	java/lang/Character:TYPE	Ljava/lang/Class;
    //   3615: aastore
    //   3616: invokevirtual 103	java/lang/Class:getMethod	(Ljava/lang/String;[Ljava/lang/Class;)Ljava/lang/reflect/Method;
    //   3619: astore_1
    //   3620: aload_1
    //   3621: aconst_null
    //   3622: iconst_3
    //   3623: anewarray 105	java/lang/Object
    //   3626: dup
    //   3627: iconst_0
    //   3628: ldc_w 375
    //   3631: aastore
    //   3632: dup
    //   3633: iconst_1
    //   3634: bipush 62
    //   3636: invokestatic 111	java/lang/Character:valueOf	(C)Ljava/lang/Character;
    //   3639: aastore
    //   3640: dup
    //   3641: iconst_2
    //   3642: iconst_4
    //   3643: invokestatic 111	java/lang/Character:valueOf	(C)Ljava/lang/Character;
    //   3646: aastore
    //   3647: invokevirtual 117	java/lang/reflect/Method:invoke	(Ljava/lang/Object;[Ljava/lang/Object;)Ljava/lang/Object;
    //   3650: astore_1
    //   3651: new 2	com/db/pwcc/dbmobile/model/banking/GVO
    //   3654: dup
    //   3655: aload_1
    //   3656: checkcast 93	java/lang/String
    //   3659: bipush 40
    //   3661: invokespecial 121	com/db/pwcc/dbmobile/model/banking/GVO:<init>	(Ljava/lang/String;I)V
    //   3664: putstatic 377	com/db/pwcc/dbmobile/model/banking/GVO:DIRECT_DEBIT_BULK_RETURN	Lcom/db/pwcc/dbmobile/model/banking/GVO;
    //   3667: ldc 81
    //   3669: ldc_w 379
    //   3672: bipush 119
    //   3674: iconst_1
    //   3675: invokestatic 89	xxxxxx/uxxxxx:bb00620062bb0062b0062b0062	(Ljava/lang/String;CC)Ljava/lang/String;
    //   3678: iconst_3
    //   3679: anewarray 91	java/lang/Class
    //   3682: dup
    //   3683: iconst_0
    //   3684: ldc 93
    //   3686: aastore
    //   3687: dup
    //   3688: iconst_1
    //   3689: getstatic 99	java/lang/Character:TYPE	Ljava/lang/Class;
    //   3692: aastore
    //   3693: dup
    //   3694: iconst_2
    //   3695: getstatic 99	java/lang/Character:TYPE	Ljava/lang/Class;
    //   3698: aastore
    //   3699: invokevirtual 103	java/lang/Class:getMethod	(Ljava/lang/String;[Ljava/lang/Class;)Ljava/lang/reflect/Method;
    //   3702: astore_1
    //   3703: aload_1
    //   3704: aconst_null
    //   3705: iconst_3
    //   3706: anewarray 105	java/lang/Object
    //   3709: dup
    //   3710: iconst_0
    //   3711: ldc_w 381
    //   3714: aastore
    //   3715: dup
    //   3716: iconst_1
    //   3717: sipush 218
    //   3720: invokestatic 111	java/lang/Character:valueOf	(C)Ljava/lang/Character;
    //   3723: aastore
    //   3724: dup
    //   3725: iconst_2
    //   3726: iconst_1
    //   3727: invokestatic 111	java/lang/Character:valueOf	(C)Ljava/lang/Character;
    //   3730: aastore
    //   3731: invokevirtual 117	java/lang/reflect/Method:invoke	(Ljava/lang/Object;[Ljava/lang/Object;)Ljava/lang/Object;
    //   3734: astore_1
    //   3735: new 2	com/db/pwcc/dbmobile/model/banking/GVO
    //   3738: dup
    //   3739: aload_1
    //   3740: checkcast 93	java/lang/String
    //   3743: bipush 41
    //   3745: invokespecial 121	com/db/pwcc/dbmobile/model/banking/GVO:<init>	(Ljava/lang/String;I)V
    //   3748: putstatic 383	com/db/pwcc/dbmobile/model/banking/GVO:SEPA_DIRECT_DEBIT_RETURN_CORE	Lcom/db/pwcc/dbmobile/model/banking/GVO;
    //   3751: ldc 81
    //   3753: ldc_w 385
    //   3756: sipush 213
    //   3759: iconst_2
    //   3760: invokestatic 89	xxxxxx/uxxxxx:bb00620062bb0062b0062b0062	(Ljava/lang/String;CC)Ljava/lang/String;
    //   3763: iconst_3
    //   3764: anewarray 91	java/lang/Class
    //   3767: dup
    //   3768: iconst_0
    //   3769: ldc 93
    //   3771: aastore
    //   3772: dup
    //   3773: iconst_1
    //   3774: getstatic 99	java/lang/Character:TYPE	Ljava/lang/Class;
    //   3777: aastore
    //   3778: dup
    //   3779: iconst_2
    //   3780: getstatic 99	java/lang/Character:TYPE	Ljava/lang/Class;
    //   3783: aastore
    //   3784: invokevirtual 103	java/lang/Class:getMethod	(Ljava/lang/String;[Ljava/lang/Class;)Ljava/lang/reflect/Method;
    //   3787: astore_1
    //   3788: aload_1
    //   3789: aconst_null
    //   3790: iconst_3
    //   3791: anewarray 105	java/lang/Object
    //   3794: dup
    //   3795: iconst_0
    //   3796: ldc_w 387
    //   3799: aastore
    //   3800: dup
    //   3801: iconst_1
    //   3802: bipush 67
    //   3804: invokestatic 111	java/lang/Character:valueOf	(C)Ljava/lang/Character;
    //   3807: aastore
    //   3808: dup
    //   3809: iconst_2
    //   3810: iconst_2
    //   3811: invokestatic 111	java/lang/Character:valueOf	(C)Ljava/lang/Character;
    //   3814: aastore
    //   3815: invokevirtual 117	java/lang/reflect/Method:invoke	(Ljava/lang/Object;[Ljava/lang/Object;)Ljava/lang/Object;
    //   3818: astore_1
    //   3819: new 2	com/db/pwcc/dbmobile/model/banking/GVO
    //   3822: dup
    //   3823: aload_1
    //   3824: checkcast 93	java/lang/String
    //   3827: bipush 42
    //   3829: invokespecial 121	com/db/pwcc/dbmobile/model/banking/GVO:<init>	(Ljava/lang/String;I)V
    //   3832: putstatic 389	com/db/pwcc/dbmobile/model/banking/GVO:SEPA_DIRECT_DEBIT_RETURN_B_2_B	Lcom/db/pwcc/dbmobile/model/banking/GVO;
    //   3835: ldc 81
    //   3837: ldc_w 391
    //   3840: sipush 174
    //   3843: sipush 170
    //   3846: iconst_1
    //   3847: invokestatic 129	xxxxxx/uxxxxx:bbbb0062b0062b0062b0062	(Ljava/lang/String;CCC)Ljava/lang/String;
    //   3850: iconst_3
    //   3851: anewarray 91	java/lang/Class
    //   3854: dup
    //   3855: iconst_0
    //   3856: ldc 93
    //   3858: aastore
    //   3859: dup
    //   3860: iconst_1
    //   3861: getstatic 99	java/lang/Character:TYPE	Ljava/lang/Class;
    //   3864: aastore
    //   3865: dup
    //   3866: iconst_2
    //   3867: getstatic 99	java/lang/Character:TYPE	Ljava/lang/Class;
    //   3870: aastore
    //   3871: invokevirtual 103	java/lang/Class:getMethod	(Ljava/lang/String;[Ljava/lang/Class;)Ljava/lang/reflect/Method;
    //   3874: astore_1
    //   3875: aload_1
    //   3876: aconst_null
    //   3877: iconst_3
    //   3878: anewarray 105	java/lang/Object
    //   3881: dup
    //   3882: iconst_0
    //   3883: ldc_w 393
    //   3886: aastore
    //   3887: dup
    //   3888: iconst_1
    //   3889: bipush 44
    //   3891: invokestatic 111	java/lang/Character:valueOf	(C)Ljava/lang/Character;
    //   3894: aastore
    //   3895: dup
    //   3896: iconst_2
    //   3897: iconst_1
    //   3898: invokestatic 111	java/lang/Character:valueOf	(C)Ljava/lang/Character;
    //   3901: aastore
    //   3902: invokevirtual 117	java/lang/reflect/Method:invoke	(Ljava/lang/Object;[Ljava/lang/Object;)Ljava/lang/Object;
    //   3905: astore_1
    //   3906: new 2	com/db/pwcc/dbmobile/model/banking/GVO
    //   3909: dup
    //   3910: aload_1
    //   3911: checkcast 93	java/lang/String
    //   3914: bipush 43
    //   3916: invokespecial 121	com/db/pwcc/dbmobile/model/banking/GVO:<init>	(Ljava/lang/String;I)V
    //   3919: putstatic 395	com/db/pwcc/dbmobile/model/banking/GVO:SEPA_DIRECT_DEBIT_BULK_CORE	Lcom/db/pwcc/dbmobile/model/banking/GVO;
    //   3922: ldc 81
    //   3924: ldc_w 397
    //   3927: sipush 183
    //   3930: iconst_5
    //   3931: invokestatic 89	xxxxxx/uxxxxx:bb00620062bb0062b0062b0062	(Ljava/lang/String;CC)Ljava/lang/String;
    //   3934: iconst_3
    //   3935: anewarray 91	java/lang/Class
    //   3938: dup
    //   3939: iconst_0
    //   3940: ldc 93
    //   3942: aastore
    //   3943: dup
    //   3944: iconst_1
    //   3945: getstatic 99	java/lang/Character:TYPE	Ljava/lang/Class;
    //   3948: aastore
    //   3949: dup
    //   3950: iconst_2
    //   3951: getstatic 99	java/lang/Character:TYPE	Ljava/lang/Class;
    //   3954: aastore
    //   3955: invokevirtual 103	java/lang/Class:getMethod	(Ljava/lang/String;[Ljava/lang/Class;)Ljava/lang/reflect/Method;
    //   3958: astore_1
    //   3959: aload_1
    //   3960: aconst_null
    //   3961: iconst_3
    //   3962: anewarray 105	java/lang/Object
    //   3965: dup
    //   3966: iconst_0
    //   3967: ldc_w 399
    //   3970: aastore
    //   3971: dup
    //   3972: iconst_1
    //   3973: sipush 171
    //   3976: invokestatic 111	java/lang/Character:valueOf	(C)Ljava/lang/Character;
    //   3979: aastore
    //   3980: dup
    //   3981: iconst_2
    //   3982: iconst_1
    //   3983: invokestatic 111	java/lang/Character:valueOf	(C)Ljava/lang/Character;
    //   3986: aastore
    //   3987: invokevirtual 117	java/lang/reflect/Method:invoke	(Ljava/lang/Object;[Ljava/lang/Object;)Ljava/lang/Object;
    //   3990: astore_1
    //   3991: new 2	com/db/pwcc/dbmobile/model/banking/GVO
    //   3994: dup
    //   3995: aload_1
    //   3996: checkcast 93	java/lang/String
    //   3999: bipush 44
    //   4001: invokespecial 121	com/db/pwcc/dbmobile/model/banking/GVO:<init>	(Ljava/lang/String;I)V
    //   4004: putstatic 401	com/db/pwcc/dbmobile/model/banking/GVO:SEPA_DIRECT_DEBIT	Lcom/db/pwcc/dbmobile/model/banking/GVO;
    //   4007: ldc 81
    //   4009: ldc_w 403
    //   4012: bipush 70
    //   4014: iconst_1
    //   4015: invokestatic 89	xxxxxx/uxxxxx:bb00620062bb0062b0062b0062	(Ljava/lang/String;CC)Ljava/lang/String;
    //   4018: iconst_4
    //   4019: anewarray 91	java/lang/Class
    //   4022: dup
    //   4023: iconst_0
    //   4024: ldc 93
    //   4026: aastore
    //   4027: dup
    //   4028: iconst_1
    //   4029: getstatic 99	java/lang/Character:TYPE	Ljava/lang/Class;
    //   4032: aastore
    //   4033: dup
    //   4034: iconst_2
    //   4035: getstatic 99	java/lang/Character:TYPE	Ljava/lang/Class;
    //   4038: aastore
    //   4039: dup
    //   4040: iconst_3
    //   4041: getstatic 99	java/lang/Character:TYPE	Ljava/lang/Class;
    //   4044: aastore
    //   4045: invokevirtual 103	java/lang/Class:getMethod	(Ljava/lang/String;[Ljava/lang/Class;)Ljava/lang/reflect/Method;
    //   4048: astore_1
    //   4049: aload_1
    //   4050: aconst_null
    //   4051: iconst_4
    //   4052: anewarray 105	java/lang/Object
    //   4055: dup
    //   4056: iconst_0
    //   4057: ldc_w 405
    //   4060: aastore
    //   4061: dup
    //   4062: iconst_1
    //   4063: bipush 29
    //   4065: invokestatic 111	java/lang/Character:valueOf	(C)Ljava/lang/Character;
    //   4068: aastore
    //   4069: dup
    //   4070: iconst_2
    //   4071: bipush 51
    //   4073: invokestatic 111	java/lang/Character:valueOf	(C)Ljava/lang/Character;
    //   4076: aastore
    //   4077: dup
    //   4078: iconst_3
    //   4079: iconst_0
    //   4080: invokestatic 111	java/lang/Character:valueOf	(C)Ljava/lang/Character;
    //   4083: aastore
    //   4084: invokevirtual 117	java/lang/reflect/Method:invoke	(Ljava/lang/Object;[Ljava/lang/Object;)Ljava/lang/Object;
    //   4087: astore_1
    //   4088: new 2	com/db/pwcc/dbmobile/model/banking/GVO
    //   4091: dup
    //   4092: aload_1
    //   4093: checkcast 93	java/lang/String
    //   4096: bipush 45
    //   4098: invokespecial 121	com/db/pwcc/dbmobile/model/banking/GVO:<init>	(Ljava/lang/String;I)V
    //   4101: putstatic 407	com/db/pwcc/dbmobile/model/banking/GVO:SEPA_DIRECT_DEBIT_RETURN_B_2_B_108672	Lcom/db/pwcc/dbmobile/model/banking/GVO;
    //   4104: ldc 81
    //   4106: ldc_w 409
    //   4109: bipush 125
    //   4111: sipush 195
    //   4114: iconst_2
    //   4115: invokestatic 129	xxxxxx/uxxxxx:bbbb0062b0062b0062b0062	(Ljava/lang/String;CCC)Ljava/lang/String;
    //   4118: iconst_3
    //   4119: anewarray 91	java/lang/Class
    //   4122: dup
    //   4123: iconst_0
    //   4124: ldc 93
    //   4126: aastore
    //   4127: dup
    //   4128: iconst_1
    //   4129: getstatic 99	java/lang/Character:TYPE	Ljava/lang/Class;
    //   4132: aastore
    //   4133: dup
    //   4134: iconst_2
    //   4135: getstatic 99	java/lang/Character:TYPE	Ljava/lang/Class;
    //   4138: aastore
    //   4139: invokevirtual 103	java/lang/Class:getMethod	(Ljava/lang/String;[Ljava/lang/Class;)Ljava/lang/reflect/Method;
    //   4142: astore_1
    //   4143: aload_1
    //   4144: aconst_null
    //   4145: iconst_3
    //   4146: anewarray 105	java/lang/Object
    //   4149: dup
    //   4150: iconst_0
    //   4151: ldc_w 411
    //   4154: aastore
    //   4155: dup
    //   4156: iconst_1
    //   4157: bipush 12
    //   4159: invokestatic 111	java/lang/Character:valueOf	(C)Ljava/lang/Character;
    //   4162: aastore
    //   4163: dup
    //   4164: iconst_2
    //   4165: iconst_0
    //   4166: invokestatic 111	java/lang/Character:valueOf	(C)Ljava/lang/Character;
    //   4169: aastore
    //   4170: invokevirtual 117	java/lang/reflect/Method:invoke	(Ljava/lang/Object;[Ljava/lang/Object;)Ljava/lang/Object;
    //   4173: astore_1
    //   4174: new 2	com/db/pwcc/dbmobile/model/banking/GVO
    //   4177: dup
    //   4178: aload_1
    //   4179: checkcast 93	java/lang/String
    //   4182: bipush 46
    //   4184: invokespecial 121	com/db/pwcc/dbmobile/model/banking/GVO:<init>	(Ljava/lang/String;I)V
    //   4187: putstatic 413	com/db/pwcc/dbmobile/model/banking/GVO:SEPA_DIRECT_DEBIT_BULK_CORE_192679	Lcom/db/pwcc/dbmobile/model/banking/GVO;
    //   4190: ldc 81
    //   4192: ldc_w 415
    //   4195: sipush 213
    //   4198: bipush 84
    //   4200: iconst_3
    //   4201: invokestatic 129	xxxxxx/uxxxxx:bbbb0062b0062b0062b0062	(Ljava/lang/String;CCC)Ljava/lang/String;
    //   4204: iconst_3
    //   4205: anewarray 91	java/lang/Class
    //   4208: dup
    //   4209: iconst_0
    //   4210: ldc 93
    //   4212: aastore
    //   4213: dup
    //   4214: iconst_1
    //   4215: getstatic 99	java/lang/Character:TYPE	Ljava/lang/Class;
    //   4218: aastore
    //   4219: dup
    //   4220: iconst_2
    //   4221: getstatic 99	java/lang/Character:TYPE	Ljava/lang/Class;
    //   4224: aastore
    //   4225: invokevirtual 103	java/lang/Class:getMethod	(Ljava/lang/String;[Ljava/lang/Class;)Ljava/lang/reflect/Method;
    //   4228: astore_1
    //   4229: aload_1
    //   4230: aconst_null
    //   4231: iconst_3
    //   4232: anewarray 105	java/lang/Object
    //   4235: dup
    //   4236: iconst_0
    //   4237: ldc_w 417
    //   4240: aastore
    //   4241: dup
    //   4242: iconst_1
    //   4243: bipush 85
    //   4245: invokestatic 111	java/lang/Character:valueOf	(C)Ljava/lang/Character;
    //   4248: aastore
    //   4249: dup
    //   4250: iconst_2
    //   4251: iconst_2
    //   4252: invokestatic 111	java/lang/Character:valueOf	(C)Ljava/lang/Character;
    //   4255: aastore
    //   4256: invokevirtual 117	java/lang/reflect/Method:invoke	(Ljava/lang/Object;[Ljava/lang/Object;)Ljava/lang/Object;
    //   4259: astore_1
    //   4260: new 2	com/db/pwcc/dbmobile/model/banking/GVO
    //   4263: dup
    //   4264: aload_1
    //   4265: checkcast 93	java/lang/String
    //   4268: bipush 47
    //   4270: invokespecial 121	com/db/pwcc/dbmobile/model/banking/GVO:<init>	(Ljava/lang/String;I)V
    //   4273: putstatic 419	com/db/pwcc/dbmobile/model/banking/GVO:SEPA_DIRECT_DEBIT_ELV	Lcom/db/pwcc/dbmobile/model/banking/GVO;
    //   4276: invokestatic 161	com/db/pwcc/dbmobile/model/banking/GVO:b0071qqq00710071qq	()I
    //   4279: invokestatic 164	com/db/pwcc/dbmobile/model/banking/GVO:b00710071qq00710071qq	()I
    //   4282: iadd
    //   4283: invokestatic 161	com/db/pwcc/dbmobile/model/banking/GVO:b0071qqq00710071qq	()I
    //   4286: imul
    //   4287: invokestatic 167	com/db/pwcc/dbmobile/model/banking/GVO:bqq0071q00710071qq	()I
    //   4290: irem
    //   4291: invokestatic 422	com/db/pwcc/dbmobile/model/banking/GVO:bq0071qq00710071qq	()I
    //   4294: if_icmpeq +3 -> 4297
    //   4297: ldc 81
    //   4299: ldc_w 424
    //   4302: sipush 189
    //   4305: iconst_3
    //   4306: invokestatic 89	xxxxxx/uxxxxx:bb00620062bb0062b0062b0062	(Ljava/lang/String;CC)Ljava/lang/String;
    //   4309: iconst_4
    //   4310: anewarray 91	java/lang/Class
    //   4313: dup
    //   4314: iconst_0
    //   4315: ldc 93
    //   4317: aastore
    //   4318: dup
    //   4319: iconst_1
    //   4320: getstatic 99	java/lang/Character:TYPE	Ljava/lang/Class;
    //   4323: aastore
    //   4324: dup
    //   4325: iconst_2
    //   4326: getstatic 99	java/lang/Character:TYPE	Ljava/lang/Class;
    //   4329: aastore
    //   4330: dup
    //   4331: iconst_3
    //   4332: getstatic 99	java/lang/Character:TYPE	Ljava/lang/Class;
    //   4335: aastore
    //   4336: invokevirtual 103	java/lang/Class:getMethod	(Ljava/lang/String;[Ljava/lang/Class;)Ljava/lang/reflect/Method;
    //   4339: astore_1
    //   4340: aload_1
    //   4341: aconst_null
    //   4342: iconst_4
    //   4343: anewarray 105	java/lang/Object
    //   4346: dup
    //   4347: iconst_0
    //   4348: ldc_w 426
    //   4351: aastore
    //   4352: dup
    //   4353: iconst_1
    //   4354: bipush 33
    //   4356: invokestatic 111	java/lang/Character:valueOf	(C)Ljava/lang/Character;
    //   4359: aastore
    //   4360: dup
    //   4361: iconst_2
    //   4362: bipush 17
    //   4364: invokestatic 111	java/lang/Character:valueOf	(C)Ljava/lang/Character;
    //   4367: aastore
    //   4368: dup
    //   4369: iconst_3
    //   4370: iconst_3
    //   4371: invokestatic 111	java/lang/Character:valueOf	(C)Ljava/lang/Character;
    //   4374: aastore
    //   4375: invokevirtual 117	java/lang/reflect/Method:invoke	(Ljava/lang/Object;[Ljava/lang/Object;)Ljava/lang/Object;
    //   4378: astore_1
    //   4379: new 2	com/db/pwcc/dbmobile/model/banking/GVO
    //   4382: dup
    //   4383: aload_1
    //   4384: checkcast 93	java/lang/String
    //   4387: bipush 48
    //   4389: invokespecial 121	com/db/pwcc/dbmobile/model/banking/GVO:<init>	(Ljava/lang/String;I)V
    //   4392: putstatic 428	com/db/pwcc/dbmobile/model/banking/GVO:SEPA_DIRECT_DEBIT_BULK_ELV	Lcom/db/pwcc/dbmobile/model/banking/GVO;
    //   4395: ldc 81
    //   4397: ldc_w 415
    //   4400: sipush 204
    //   4403: sipush 220
    //   4406: iconst_3
    //   4407: invokestatic 129	xxxxxx/uxxxxx:bbbb0062b0062b0062b0062	(Ljava/lang/String;CCC)Ljava/lang/String;
    //   4410: iconst_3
    //   4411: anewarray 91	java/lang/Class
    //   4414: dup
    //   4415: iconst_0
    //   4416: ldc 93
    //   4418: aastore
    //   4419: dup
    //   4420: iconst_1
    //   4421: getstatic 99	java/lang/Character:TYPE	Ljava/lang/Class;
    //   4424: aastore
    //   4425: dup
    //   4426: iconst_2
    //   4427: getstatic 99	java/lang/Character:TYPE	Ljava/lang/Class;
    //   4430: aastore
    //   4431: invokevirtual 103	java/lang/Class:getMethod	(Ljava/lang/String;[Ljava/lang/Class;)Ljava/lang/reflect/Method;
    //   4434: astore_1
    //   4435: aload_1
    //   4436: aconst_null
    //   4437: iconst_3
    //   4438: anewarray 105	java/lang/Object
    //   4441: dup
    //   4442: iconst_0
    //   4443: ldc_w 430
    //   4446: aastore
    //   4447: dup
    //   4448: iconst_1
    //   4449: bipush 96
    //   4451: invokestatic 111	java/lang/Character:valueOf	(C)Ljava/lang/Character;
    //   4454: aastore
    //   4455: dup
    //   4456: iconst_2
    //   4457: iconst_0
    //   4458: invokestatic 111	java/lang/Character:valueOf	(C)Ljava/lang/Character;
    //   4461: aastore
    //   4462: invokevirtual 117	java/lang/reflect/Method:invoke	(Ljava/lang/Object;[Ljava/lang/Object;)Ljava/lang/Object;
    //   4465: astore_1
    //   4466: new 2	com/db/pwcc/dbmobile/model/banking/GVO
    //   4469: dup
    //   4470: aload_1
    //   4471: checkcast 93	java/lang/String
    //   4474: bipush 49
    //   4476: invokespecial 121	com/db/pwcc/dbmobile/model/banking/GVO:<init>	(Ljava/lang/String;I)V
    //   4479: putstatic 432	com/db/pwcc/dbmobile/model/banking/GVO:SEPA_DIRECT_DEBIT_REVERSAL_181647	Lcom/db/pwcc/dbmobile/model/banking/GVO;
    //   4482: ldc 81
    //   4484: ldc_w 434
    //   4487: sipush 140
    //   4490: sipush 181
    //   4493: iconst_3
    //   4494: invokestatic 129	xxxxxx/uxxxxx:bbbb0062b0062b0062b0062	(Ljava/lang/String;CCC)Ljava/lang/String;
    //   4497: iconst_3
    //   4498: anewarray 91	java/lang/Class
    //   4501: dup
    //   4502: iconst_0
    //   4503: ldc 93
    //   4505: aastore
    //   4506: dup
    //   4507: iconst_1
    //   4508: getstatic 99	java/lang/Character:TYPE	Ljava/lang/Class;
    //   4511: aastore
    //   4512: dup
    //   4513: iconst_2
    //   4514: getstatic 99	java/lang/Character:TYPE	Ljava/lang/Class;
    //   4517: aastore
    //   4518: invokevirtual 103	java/lang/Class:getMethod	(Ljava/lang/String;[Ljava/lang/Class;)Ljava/lang/reflect/Method;
    //   4521: astore_1
    //   4522: aload_1
    //   4523: aconst_null
    //   4524: iconst_3
    //   4525: anewarray 105	java/lang/Object
    //   4528: dup
    //   4529: iconst_0
    //   4530: ldc_w 436
    //   4533: aastore
    //   4534: dup
    //   4535: iconst_1
    //   4536: sipush 207
    //   4539: invokestatic 111	java/lang/Character:valueOf	(C)Ljava/lang/Character;
    //   4542: aastore
    //   4543: dup
    //   4544: iconst_2
    //   4545: iconst_5
    //   4546: invokestatic 111	java/lang/Character:valueOf	(C)Ljava/lang/Character;
    //   4549: aastore
    //   4550: invokevirtual 117	java/lang/reflect/Method:invoke	(Ljava/lang/Object;[Ljava/lang/Object;)Ljava/lang/Object;
    //   4553: astore_1
    //   4554: new 2	com/db/pwcc/dbmobile/model/banking/GVO
    //   4557: dup
    //   4558: aload_1
    //   4559: checkcast 93	java/lang/String
    //   4562: bipush 50
    //   4564: invokespecial 121	com/db/pwcc/dbmobile/model/banking/GVO:<init>	(Ljava/lang/String;I)V
    //   4567: putstatic 438	com/db/pwcc/dbmobile/model/banking/GVO:SEPA_DIRECT_DEBIT_REVERSAL_B_2_B_184	Lcom/db/pwcc/dbmobile/model/banking/GVO;
    //   4570: ldc 81
    //   4572: ldc_w 440
    //   4575: bipush 74
    //   4577: iconst_2
    //   4578: invokestatic 89	xxxxxx/uxxxxx:bb00620062bb0062b0062b0062	(Ljava/lang/String;CC)Ljava/lang/String;
    //   4581: iconst_3
    //   4582: anewarray 91	java/lang/Class
    //   4585: dup
    //   4586: iconst_0
    //   4587: ldc 93
    //   4589: aastore
    //   4590: dup
    //   4591: iconst_1
    //   4592: getstatic 99	java/lang/Character:TYPE	Ljava/lang/Class;
    //   4595: aastore
    //   4596: dup
    //   4597: iconst_2
    //   4598: getstatic 99	java/lang/Character:TYPE	Ljava/lang/Class;
    //   4601: aastore
    //   4602: invokevirtual 103	java/lang/Class:getMethod	(Ljava/lang/String;[Ljava/lang/Class;)Ljava/lang/reflect/Method;
    //   4605: astore_1
    //   4606: aload_1
    //   4607: aconst_null
    //   4608: iconst_3
    //   4609: anewarray 105	java/lang/Object
    //   4612: dup
    //   4613: iconst_0
    //   4614: ldc_w 442
    //   4617: aastore
    //   4618: dup
    //   4619: iconst_1
    //   4620: bipush 120
    //   4622: invokestatic 111	java/lang/Character:valueOf	(C)Ljava/lang/Character;
    //   4625: aastore
    //   4626: dup
    //   4627: iconst_2
    //   4628: iconst_2
    //   4629: invokestatic 111	java/lang/Character:valueOf	(C)Ljava/lang/Character;
    //   4632: aastore
    //   4633: invokevirtual 117	java/lang/reflect/Method:invoke	(Ljava/lang/Object;[Ljava/lang/Object;)Ljava/lang/Object;
    //   4636: astore_1
    //   4637: new 2	com/db/pwcc/dbmobile/model/banking/GVO
    //   4640: dup
    //   4641: aload_1
    //   4642: checkcast 93	java/lang/String
    //   4645: bipush 51
    //   4647: invokespecial 121	com/db/pwcc/dbmobile/model/banking/GVO:<init>	(Ljava/lang/String;I)V
    //   4650: putstatic 444	com/db/pwcc/dbmobile/model/banking/GVO:BILL_PAYMENT	Lcom/db/pwcc/dbmobile/model/banking/GVO;
    //   4653: ldc 81
    //   4655: ldc_w 446
    //   4658: sipush 208
    //   4661: sipush 155
    //   4664: iconst_1
    //   4665: invokestatic 129	xxxxxx/uxxxxx:bbbb0062b0062b0062b0062	(Ljava/lang/String;CCC)Ljava/lang/String;
    //   4668: iconst_4
    //   4669: anewarray 91	java/lang/Class
    //   4672: dup
    //   4673: iconst_0
    //   4674: ldc 93
    //   4676: aastore
    //   4677: dup
    //   4678: iconst_1
    //   4679: getstatic 99	java/lang/Character:TYPE	Ljava/lang/Class;
    //   4682: aastore
    //   4683: dup
    //   4684: iconst_2
    //   4685: getstatic 99	java/lang/Character:TYPE	Ljava/lang/Class;
    //   4688: aastore
    //   4689: dup
    //   4690: iconst_3
    //   4691: getstatic 99	java/lang/Character:TYPE	Ljava/lang/Class;
    //   4694: aastore
    //   4695: invokevirtual 103	java/lang/Class:getMethod	(Ljava/lang/String;[Ljava/lang/Class;)Ljava/lang/reflect/Method;
    //   4698: astore_1
    //   4699: aload_1
    //   4700: aconst_null
    //   4701: iconst_4
    //   4702: anewarray 105	java/lang/Object
    //   4705: dup
    //   4706: iconst_0
    //   4707: ldc_w 448
    //   4710: aastore
    //   4711: dup
    //   4712: iconst_1
    //   4713: sipush 179
    //   4716: invokestatic 111	java/lang/Character:valueOf	(C)Ljava/lang/Character;
    //   4719: aastore
    //   4720: dup
    //   4721: iconst_2
    //   4722: sipush 129
    //   4725: invokestatic 111	java/lang/Character:valueOf	(C)Ljava/lang/Character;
    //   4728: aastore
    //   4729: dup
    //   4730: iconst_3
    //   4731: iconst_3
    //   4732: invokestatic 111	java/lang/Character:valueOf	(C)Ljava/lang/Character;
    //   4735: aastore
    //   4736: invokevirtual 117	java/lang/reflect/Method:invoke	(Ljava/lang/Object;[Ljava/lang/Object;)Ljava/lang/Object;
    //   4739: astore_1
    //   4740: new 2	com/db/pwcc/dbmobile/model/banking/GVO
    //   4743: dup
    //   4744: aload_1
    //   4745: checkcast 93	java/lang/String
    //   4748: bipush 52
    //   4750: invokespecial 121	com/db/pwcc/dbmobile/model/banking/GVO:<init>	(Ljava/lang/String;I)V
    //   4753: putstatic 450	com/db/pwcc/dbmobile/model/banking/GVO:CHEQUE_DEPOSIT	Lcom/db/pwcc/dbmobile/model/banking/GVO;
    //   4756: ldc 81
    //   4758: ldc_w 452
    //   4761: bipush 68
    //   4763: iconst_4
    //   4764: invokestatic 89	xxxxxx/uxxxxx:bb00620062bb0062b0062b0062	(Ljava/lang/String;CC)Ljava/lang/String;
    //   4767: iconst_3
    //   4768: anewarray 91	java/lang/Class
    //   4771: dup
    //   4772: iconst_0
    //   4773: ldc 93
    //   4775: aastore
    //   4776: dup
    //   4777: iconst_1
    //   4778: getstatic 99	java/lang/Character:TYPE	Ljava/lang/Class;
    //   4781: aastore
    //   4782: dup
    //   4783: iconst_2
    //   4784: getstatic 99	java/lang/Character:TYPE	Ljava/lang/Class;
    //   4787: aastore
    //   4788: invokevirtual 103	java/lang/Class:getMethod	(Ljava/lang/String;[Ljava/lang/Class;)Ljava/lang/reflect/Method;
    //   4791: astore_1
    //   4792: aload_1
    //   4793: aconst_null
    //   4794: iconst_3
    //   4795: anewarray 105	java/lang/Object
    //   4798: dup
    //   4799: iconst_0
    //   4800: ldc_w 454
    //   4803: aastore
    //   4804: dup
    //   4805: iconst_1
    //   4806: bipush 91
    //   4808: invokestatic 111	java/lang/Character:valueOf	(C)Ljava/lang/Character;
    //   4811: aastore
    //   4812: dup
    //   4813: iconst_2
    //   4814: iconst_2
    //   4815: invokestatic 111	java/lang/Character:valueOf	(C)Ljava/lang/Character;
    //   4818: aastore
    //   4819: invokevirtual 117	java/lang/reflect/Method:invoke	(Ljava/lang/Object;[Ljava/lang/Object;)Ljava/lang/Object;
    //   4822: astore_1
    //   4823: new 2	com/db/pwcc/dbmobile/model/banking/GVO
    //   4826: dup
    //   4827: aload_1
    //   4828: checkcast 93	java/lang/String
    //   4831: bipush 53
    //   4833: invokespecial 121	com/db/pwcc/dbmobile/model/banking/GVO:<init>	(Ljava/lang/String;I)V
    //   4836: astore_1
    //   4837: invokestatic 161	com/db/pwcc/dbmobile/model/banking/GVO:b0071qqq00710071qq	()I
    //   4840: istore_0
    //   4841: iload_0
    //   4842: invokestatic 164	com/db/pwcc/dbmobile/model/banking/GVO:b00710071qq00710071qq	()I
    //   4845: iload_0
    //   4846: iadd
    //   4847: imul
    //   4848: invokestatic 167	com/db/pwcc/dbmobile/model/banking/GVO:bqq0071q00710071qq	()I
    //   4851: irem
    //   4852: tableswitch	default:+20->4872, 0:+20->4872
    //   4872: aload_1
    //   4873: putstatic 456	com/db/pwcc/dbmobile/model/banking/GVO:CHEQUE_PAYMENT	Lcom/db/pwcc/dbmobile/model/banking/GVO;
    //   4876: ldc 81
    //   4878: ldc_w 458
    //   4881: sipush 128
    //   4884: iconst_5
    //   4885: invokestatic 89	xxxxxx/uxxxxx:bb00620062bb0062b0062b0062	(Ljava/lang/String;CC)Ljava/lang/String;
    //   4888: iconst_3
    //   4889: anewarray 91	java/lang/Class
    //   4892: dup
    //   4893: iconst_0
    //   4894: ldc 93
    //   4896: aastore
    //   4897: dup
    //   4898: iconst_1
    //   4899: getstatic 99	java/lang/Character:TYPE	Ljava/lang/Class;
    //   4902: aastore
    //   4903: dup
    //   4904: iconst_2
    //   4905: getstatic 99	java/lang/Character:TYPE	Ljava/lang/Class;
    //   4908: aastore
    //   4909: invokevirtual 103	java/lang/Class:getMethod	(Ljava/lang/String;[Ljava/lang/Class;)Ljava/lang/reflect/Method;
    //   4912: astore_1
    //   4913: aload_1
    //   4914: aconst_null
    //   4915: iconst_3
    //   4916: anewarray 105	java/lang/Object
    //   4919: dup
    //   4920: iconst_0
    //   4921: ldc_w 460
    //   4924: aastore
    //   4925: dup
    //   4926: iconst_1
    //   4927: bipush 58
    //   4929: invokestatic 111	java/lang/Character:valueOf	(C)Ljava/lang/Character;
    //   4932: aastore
    //   4933: dup
    //   4934: iconst_2
    //   4935: iconst_5
    //   4936: invokestatic 111	java/lang/Character:valueOf	(C)Ljava/lang/Character;
    //   4939: aastore
    //   4940: invokevirtual 117	java/lang/reflect/Method:invoke	(Ljava/lang/Object;[Ljava/lang/Object;)Ljava/lang/Object;
    //   4943: astore_1
    //   4944: new 2	com/db/pwcc/dbmobile/model/banking/GVO
    //   4947: dup
    //   4948: aload_1
    //   4949: checkcast 93	java/lang/String
    //   4952: bipush 54
    //   4954: invokespecial 121	com/db/pwcc/dbmobile/model/banking/GVO:<init>	(Ljava/lang/String;I)V
    //   4957: putstatic 462	com/db/pwcc/dbmobile/model/banking/GVO:CHEQUE_PAYMENT_MULTICURRENCY_CHEQUE	Lcom/db/pwcc/dbmobile/model/banking/GVO;
    //   4960: ldc 81
    //   4962: ldc_w 464
    //   4965: sipush 232
    //   4968: iconst_4
    //   4969: invokestatic 89	xxxxxx/uxxxxx:bb00620062bb0062b0062b0062	(Ljava/lang/String;CC)Ljava/lang/String;
    //   4972: iconst_4
    //   4973: anewarray 91	java/lang/Class
    //   4976: dup
    //   4977: iconst_0
    //   4978: ldc 93
    //   4980: aastore
    //   4981: dup
    //   4982: iconst_1
    //   4983: getstatic 99	java/lang/Character:TYPE	Ljava/lang/Class;
    //   4986: aastore
    //   4987: dup
    //   4988: iconst_2
    //   4989: getstatic 99	java/lang/Character:TYPE	Ljava/lang/Class;
    //   4992: aastore
    //   4993: dup
    //   4994: iconst_3
    //   4995: getstatic 99	java/lang/Character:TYPE	Ljava/lang/Class;
    //   4998: aastore
    //   4999: invokevirtual 103	java/lang/Class:getMethod	(Ljava/lang/String;[Ljava/lang/Class;)Ljava/lang/reflect/Method;
    //   5002: astore_1
    //   5003: aload_1
    //   5004: aconst_null
    //   5005: iconst_4
    //   5006: anewarray 105	java/lang/Object
    //   5009: dup
    //   5010: iconst_0
    //   5011: ldc_w 466
    //   5014: aastore
    //   5015: dup
    //   5016: iconst_1
    //   5017: bipush 124
    //   5019: invokestatic 111	java/lang/Character:valueOf	(C)Ljava/lang/Character;
    //   5022: aastore
    //   5023: dup
    //   5024: iconst_2
    //   5025: sipush 235
    //   5028: invokestatic 111	java/lang/Character:valueOf	(C)Ljava/lang/Character;
    //   5031: aastore
    //   5032: dup
    //   5033: iconst_3
    //   5034: iconst_0
    //   5035: invokestatic 111	java/lang/Character:valueOf	(C)Ljava/lang/Character;
    //   5038: aastore
    //   5039: invokevirtual 117	java/lang/reflect/Method:invoke	(Ljava/lang/Object;[Ljava/lang/Object;)Ljava/lang/Object;
    //   5042: astore_1
    //   5043: new 2	com/db/pwcc/dbmobile/model/banking/GVO
    //   5046: dup
    //   5047: aload_1
    //   5048: checkcast 93	java/lang/String
    //   5051: bipush 55
    //   5053: invokespecial 121	com/db/pwcc/dbmobile/model/banking/GVO:<init>	(Ljava/lang/String;I)V
    //   5056: putstatic 468	com/db/pwcc/dbmobile/model/banking/GVO:CHEQUE_PAYMENT_TRAVELLER_CHEQUE	Lcom/db/pwcc/dbmobile/model/banking/GVO;
    //   5059: ldc 81
    //   5061: ldc_w 470
    //   5064: sipush 198
    //   5067: iconst_3
    //   5068: invokestatic 89	xxxxxx/uxxxxx:bb00620062bb0062b0062b0062	(Ljava/lang/String;CC)Ljava/lang/String;
    //   5071: iconst_4
    //   5072: anewarray 91	java/lang/Class
    //   5075: dup
    //   5076: iconst_0
    //   5077: ldc 93
    //   5079: aastore
    //   5080: dup
    //   5081: iconst_1
    //   5082: getstatic 99	java/lang/Character:TYPE	Ljava/lang/Class;
    //   5085: aastore
    //   5086: dup
    //   5087: iconst_2
    //   5088: getstatic 99	java/lang/Character:TYPE	Ljava/lang/Class;
    //   5091: aastore
    //   5092: dup
    //   5093: iconst_3
    //   5094: getstatic 99	java/lang/Character:TYPE	Ljava/lang/Class;
    //   5097: aastore
    //   5098: invokevirtual 103	java/lang/Class:getMethod	(Ljava/lang/String;[Ljava/lang/Class;)Ljava/lang/reflect/Method;
    //   5101: astore_1
    //   5102: aload_1
    //   5103: aconst_null
    //   5104: iconst_4
    //   5105: anewarray 105	java/lang/Object
    //   5108: dup
    //   5109: iconst_0
    //   5110: ldc_w 472
    //   5113: aastore
    //   5114: dup
    //   5115: iconst_1
    //   5116: sipush 214
    //   5119: invokestatic 111	java/lang/Character:valueOf	(C)Ljava/lang/Character;
    //   5122: aastore
    //   5123: dup
    //   5124: iconst_2
    //   5125: iconst_4
    //   5126: invokestatic 111	java/lang/Character:valueOf	(C)Ljava/lang/Character;
    //   5129: aastore
    //   5130: dup
    //   5131: iconst_3
    //   5132: iconst_1
    //   5133: invokestatic 111	java/lang/Character:valueOf	(C)Ljava/lang/Character;
    //   5136: aastore
    //   5137: invokevirtual 117	java/lang/reflect/Method:invoke	(Ljava/lang/Object;[Ljava/lang/Object;)Ljava/lang/Object;
    //   5140: astore_1
    //   5141: new 2	com/db/pwcc/dbmobile/model/banking/GVO
    //   5144: dup
    //   5145: aload_1
    //   5146: checkcast 93	java/lang/String
    //   5149: bipush 56
    //   5151: invokespecial 121	com/db/pwcc/dbmobile/model/banking/GVO:<init>	(Ljava/lang/String;I)V
    //   5154: putstatic 474	com/db/pwcc/dbmobile/model/banking/GVO:CHEQUE_PAYMENT_ORDER_CHEQUE	Lcom/db/pwcc/dbmobile/model/banking/GVO;
    //   5157: ldc 81
    //   5159: ldc_w 476
    //   5162: sipush 253
    //   5165: iconst_1
    //   5166: invokestatic 89	xxxxxx/uxxxxx:bb00620062bb0062b0062b0062	(Ljava/lang/String;CC)Ljava/lang/String;
    //   5169: iconst_3
    //   5170: anewarray 91	java/lang/Class
    //   5173: dup
    //   5174: iconst_0
    //   5175: ldc 93
    //   5177: aastore
    //   5178: dup
    //   5179: iconst_1
    //   5180: getstatic 99	java/lang/Character:TYPE	Ljava/lang/Class;
    //   5183: aastore
    //   5184: dup
    //   5185: iconst_2
    //   5186: getstatic 99	java/lang/Character:TYPE	Ljava/lang/Class;
    //   5189: aastore
    //   5190: invokevirtual 103	java/lang/Class:getMethod	(Ljava/lang/String;[Ljava/lang/Class;)Ljava/lang/reflect/Method;
    //   5193: astore_1
    //   5194: aload_1
    //   5195: aconst_null
    //   5196: iconst_3
    //   5197: anewarray 105	java/lang/Object
    //   5200: dup
    //   5201: iconst_0
    //   5202: ldc_w 478
    //   5205: aastore
    //   5206: dup
    //   5207: iconst_1
    //   5208: sipush 215
    //   5211: invokestatic 111	java/lang/Character:valueOf	(C)Ljava/lang/Character;
    //   5214: aastore
    //   5215: dup
    //   5216: iconst_2
    //   5217: iconst_4
    //   5218: invokestatic 111	java/lang/Character:valueOf	(C)Ljava/lang/Character;
    //   5221: aastore
    //   5222: invokevirtual 117	java/lang/reflect/Method:invoke	(Ljava/lang/Object;[Ljava/lang/Object;)Ljava/lang/Object;
    //   5225: astore_1
    //   5226: new 2	com/db/pwcc/dbmobile/model/banking/GVO
    //   5229: dup
    //   5230: aload_1
    //   5231: checkcast 93	java/lang/String
    //   5234: bipush 57
    //   5236: invokespecial 121	com/db/pwcc/dbmobile/model/banking/GVO:<init>	(Ljava/lang/String;I)V
    //   5239: putstatic 480	com/db/pwcc/dbmobile/model/banking/GVO:CHEQUE_PAYMENT_BEARER_CHEQUE	Lcom/db/pwcc/dbmobile/model/banking/GVO;
    //   5242: ldc 81
    //   5244: ldc_w 482
    //   5247: bipush 105
    //   5249: iconst_2
    //   5250: invokestatic 89	xxxxxx/uxxxxx:bb00620062bb0062b0062b0062	(Ljava/lang/String;CC)Ljava/lang/String;
    //   5253: iconst_4
    //   5254: anewarray 91	java/lang/Class
    //   5257: dup
    //   5258: iconst_0
    //   5259: ldc 93
    //   5261: aastore
    //   5262: dup
    //   5263: iconst_1
    //   5264: getstatic 99	java/lang/Character:TYPE	Ljava/lang/Class;
    //   5267: aastore
    //   5268: dup
    //   5269: iconst_2
    //   5270: getstatic 99	java/lang/Character:TYPE	Ljava/lang/Class;
    //   5273: aastore
    //   5274: dup
    //   5275: iconst_3
    //   5276: getstatic 99	java/lang/Character:TYPE	Ljava/lang/Class;
    //   5279: aastore
    //   5280: invokevirtual 103	java/lang/Class:getMethod	(Ljava/lang/String;[Ljava/lang/Class;)Ljava/lang/reflect/Method;
    //   5283: astore_1
    //   5284: aload_1
    //   5285: aconst_null
    //   5286: iconst_4
    //   5287: anewarray 105	java/lang/Object
    //   5290: dup
    //   5291: iconst_0
    //   5292: ldc_w 484
    //   5295: aastore
    //   5296: dup
    //   5297: iconst_1
    //   5298: bipush 80
    //   5300: invokestatic 111	java/lang/Character:valueOf	(C)Ljava/lang/Character;
    //   5303: aastore
    //   5304: dup
    //   5305: iconst_2
    //   5306: sipush 184
    //   5309: invokestatic 111	java/lang/Character:valueOf	(C)Ljava/lang/Character;
    //   5312: aastore
    //   5313: dup
    //   5314: iconst_3
    //   5315: iconst_0
    //   5316: invokestatic 111	java/lang/Character:valueOf	(C)Ljava/lang/Character;
    //   5319: aastore
    //   5320: invokevirtual 117	java/lang/reflect/Method:invoke	(Ljava/lang/Object;[Ljava/lang/Object;)Ljava/lang/Object;
    //   5323: astore_1
    //   5324: new 2	com/db/pwcc/dbmobile/model/banking/GVO
    //   5327: dup
    //   5328: aload_1
    //   5329: checkcast 93	java/lang/String
    //   5332: bipush 58
    //   5334: invokespecial 121	com/db/pwcc/dbmobile/model/banking/GVO:<init>	(Ljava/lang/String;I)V
    //   5337: putstatic 486	com/db/pwcc/dbmobile/model/banking/GVO:CHEQUE_PAYMENT_BULK	Lcom/db/pwcc/dbmobile/model/banking/GVO;
    //   5340: ldc 81
    //   5342: ldc_w 488
    //   5345: bipush 11
    //   5347: bipush 53
    //   5349: iconst_0
    //   5350: invokestatic 129	xxxxxx/uxxxxx:bbbb0062b0062b0062b0062	(Ljava/lang/String;CCC)Ljava/lang/String;
    //   5353: iconst_3
    //   5354: anewarray 91	java/lang/Class
    //   5357: dup
    //   5358: iconst_0
    //   5359: ldc 93
    //   5361: aastore
    //   5362: dup
    //   5363: iconst_1
    //   5364: getstatic 99	java/lang/Character:TYPE	Ljava/lang/Class;
    //   5367: aastore
    //   5368: dup
    //   5369: iconst_2
    //   5370: getstatic 99	java/lang/Character:TYPE	Ljava/lang/Class;
    //   5373: aastore
    //   5374: invokevirtual 103	java/lang/Class:getMethod	(Ljava/lang/String;[Ljava/lang/Class;)Ljava/lang/reflect/Method;
    //   5377: astore_1
    //   5378: aload_1
    //   5379: aconst_null
    //   5380: iconst_3
    //   5381: anewarray 105	java/lang/Object
    //   5384: dup
    //   5385: iconst_0
    //   5386: ldc_w 490
    //   5389: aastore
    //   5390: dup
    //   5391: iconst_1
    //   5392: sipush 179
    //   5395: invokestatic 111	java/lang/Character:valueOf	(C)Ljava/lang/Character;
    //   5398: aastore
    //   5399: dup
    //   5400: iconst_2
    //   5401: iconst_2
    //   5402: invokestatic 111	java/lang/Character:valueOf	(C)Ljava/lang/Character;
    //   5405: aastore
    //   5406: invokevirtual 117	java/lang/reflect/Method:invoke	(Ljava/lang/Object;[Ljava/lang/Object;)Ljava/lang/Object;
    //   5409: astore_1
    //   5410: new 2	com/db/pwcc/dbmobile/model/banking/GVO
    //   5413: dup
    //   5414: aload_1
    //   5415: checkcast 93	java/lang/String
    //   5418: bipush 59
    //   5420: invokespecial 121	com/db/pwcc/dbmobile/model/banking/GVO:<init>	(Ljava/lang/String;I)V
    //   5423: putstatic 492	com/db/pwcc/dbmobile/model/banking/GVO:CHEQUE_RETURN	Lcom/db/pwcc/dbmobile/model/banking/GVO;
    //   5426: ldc 81
    //   5428: ldc_w 494
    //   5431: bipush 13
    //   5433: iconst_2
    //   5434: invokestatic 89	xxxxxx/uxxxxx:bb00620062bb0062b0062b0062	(Ljava/lang/String;CC)Ljava/lang/String;
    //   5437: iconst_3
    //   5438: anewarray 91	java/lang/Class
    //   5441: dup
    //   5442: iconst_0
    //   5443: ldc 93
    //   5445: aastore
    //   5446: dup
    //   5447: iconst_1
    //   5448: getstatic 99	java/lang/Character:TYPE	Ljava/lang/Class;
    //   5451: aastore
    //   5452: dup
    //   5453: iconst_2
    //   5454: getstatic 99	java/lang/Character:TYPE	Ljava/lang/Class;
    //   5457: aastore
    //   5458: invokevirtual 103	java/lang/Class:getMethod	(Ljava/lang/String;[Ljava/lang/Class;)Ljava/lang/reflect/Method;
    //   5461: astore_1
    //   5462: aload_1
    //   5463: aconst_null
    //   5464: iconst_3
    //   5465: anewarray 105	java/lang/Object
    //   5468: dup
    //   5469: iconst_0
    //   5470: ldc_w 496
    //   5473: aastore
    //   5474: dup
    //   5475: iconst_1
    //   5476: sipush 167
    //   5479: invokestatic 111	java/lang/Character:valueOf	(C)Ljava/lang/Character;
    //   5482: aastore
    //   5483: dup
    //   5484: iconst_2
    //   5485: iconst_0
    //   5486: invokestatic 111	java/lang/Character:valueOf	(C)Ljava/lang/Character;
    //   5489: aastore
    //   5490: invokevirtual 117	java/lang/reflect/Method:invoke	(Ljava/lang/Object;[Ljava/lang/Object;)Ljava/lang/Object;
    //   5493: astore_1
    //   5494: new 2	com/db/pwcc/dbmobile/model/banking/GVO
    //   5497: dup
    //   5498: aload_1
    //   5499: checkcast 93	java/lang/String
    //   5502: bipush 60
    //   5504: invokespecial 121	com/db/pwcc/dbmobile/model/banking/GVO:<init>	(Ljava/lang/String;I)V
    //   5507: putstatic 498	com/db/pwcc/dbmobile/model/banking/GVO:CHEQUE_DENIED_CHEQUE_RETURN	Lcom/db/pwcc/dbmobile/model/banking/GVO;
    //   5510: ldc 81
    //   5512: ldc_w 500
    //   5515: bipush 65
    //   5517: iconst_3
    //   5518: invokestatic 89	xxxxxx/uxxxxx:bb00620062bb0062b0062b0062	(Ljava/lang/String;CC)Ljava/lang/String;
    //   5521: iconst_3
    //   5522: anewarray 91	java/lang/Class
    //   5525: dup
    //   5526: iconst_0
    //   5527: ldc 93
    //   5529: aastore
    //   5530: dup
    //   5531: iconst_1
    //   5532: getstatic 99	java/lang/Character:TYPE	Ljava/lang/Class;
    //   5535: aastore
    //   5536: dup
    //   5537: iconst_2
    //   5538: getstatic 99	java/lang/Character:TYPE	Ljava/lang/Class;
    //   5541: aastore
    //   5542: invokevirtual 103	java/lang/Class:getMethod	(Ljava/lang/String;[Ljava/lang/Class;)Ljava/lang/reflect/Method;
    //   5545: astore_1
    //   5546: aload_1
    //   5547: aconst_null
    //   5548: iconst_3
    //   5549: anewarray 105	java/lang/Object
    //   5552: dup
    //   5553: iconst_0
    //   5554: ldc_w 502
    //   5557: aastore
    //   5558: dup
    //   5559: iconst_1
    //   5560: bipush 51
    //   5562: invokestatic 111	java/lang/Character:valueOf	(C)Ljava/lang/Character;
    //   5565: aastore
    //   5566: dup
    //   5567: iconst_2
    //   5568: iconst_4
    //   5569: invokestatic 111	java/lang/Character:valueOf	(C)Ljava/lang/Character;
    //   5572: aastore
    //   5573: invokevirtual 117	java/lang/reflect/Method:invoke	(Ljava/lang/Object;[Ljava/lang/Object;)Ljava/lang/Object;
    //   5576: astore_1
    //   5577: new 2	com/db/pwcc/dbmobile/model/banking/GVO
    //   5580: dup
    //   5581: aload_1
    //   5582: checkcast 93	java/lang/String
    //   5585: bipush 61
    //   5587: invokespecial 121	com/db/pwcc/dbmobile/model/banking/GVO:<init>	(Ljava/lang/String;I)V
    //   5590: putstatic 504	com/db/pwcc/dbmobile/model/banking/GVO:CHEQUE_ACTIVE_RETURN	Lcom/db/pwcc/dbmobile/model/banking/GVO;
    //   5593: ldc 81
    //   5595: ldc_w 506
    //   5598: bipush 121
    //   5600: iconst_2
    //   5601: invokestatic 89	xxxxxx/uxxxxx:bb00620062bb0062b0062b0062	(Ljava/lang/String;CC)Ljava/lang/String;
    //   5604: iconst_4
    //   5605: anewarray 91	java/lang/Class
    //   5608: dup
    //   5609: iconst_0
    //   5610: ldc 93
    //   5612: aastore
    //   5613: dup
    //   5614: iconst_1
    //   5615: getstatic 99	java/lang/Character:TYPE	Ljava/lang/Class;
    //   5618: aastore
    //   5619: dup
    //   5620: iconst_2
    //   5621: getstatic 99	java/lang/Character:TYPE	Ljava/lang/Class;
    //   5624: aastore
    //   5625: dup
    //   5626: iconst_3
    //   5627: getstatic 99	java/lang/Character:TYPE	Ljava/lang/Class;
    //   5630: aastore
    //   5631: invokevirtual 103	java/lang/Class:getMethod	(Ljava/lang/String;[Ljava/lang/Class;)Ljava/lang/reflect/Method;
    //   5634: astore_1
    //   5635: aload_1
    //   5636: aconst_null
    //   5637: iconst_4
    //   5638: anewarray 105	java/lang/Object
    //   5641: dup
    //   5642: iconst_0
    //   5643: ldc_w 508
    //   5646: aastore
    //   5647: dup
    //   5648: iconst_1
    //   5649: bipush 52
    //   5651: invokestatic 111	java/lang/Character:valueOf	(C)Ljava/lang/Character;
    //   5654: aastore
    //   5655: dup
    //   5656: iconst_2
    //   5657: bipush 116
    //   5659: invokestatic 111	java/lang/Character:valueOf	(C)Ljava/lang/Character;
    //   5662: aastore
    //   5663: dup
    //   5664: iconst_3
    //   5665: iconst_1
    //   5666: invokestatic 111	java/lang/Character:valueOf	(C)Ljava/lang/Character;
    //   5669: aastore
    //   5670: invokevirtual 117	java/lang/reflect/Method:invoke	(Ljava/lang/Object;[Ljava/lang/Object;)Ljava/lang/Object;
    //   5673: astore_1
    //   5674: new 2	com/db/pwcc/dbmobile/model/banking/GVO
    //   5677: dup
    //   5678: aload_1
    //   5679: checkcast 93	java/lang/String
    //   5682: bipush 62
    //   5684: invokespecial 121	com/db/pwcc/dbmobile/model/banking/GVO:<init>	(Ljava/lang/String;I)V
    //   5687: putstatic 510	com/db/pwcc/dbmobile/model/banking/GVO:MULTI_BANKING_TRANSACTION	Lcom/db/pwcc/dbmobile/model/banking/GVO;
    //   5690: ldc 81
    //   5692: ldc_w 259
    //   5695: bipush 82
    //   5697: sipush 149
    //   5700: iconst_1
    //   5701: invokestatic 129	xxxxxx/uxxxxx:bbbb0062b0062b0062b0062	(Ljava/lang/String;CCC)Ljava/lang/String;
    //   5704: iconst_3
    //   5705: anewarray 91	java/lang/Class
    //   5708: dup
    //   5709: iconst_0
    //   5710: ldc 93
    //   5712: aastore
    //   5713: dup
    //   5714: iconst_1
    //   5715: getstatic 99	java/lang/Character:TYPE	Ljava/lang/Class;
    //   5718: aastore
    //   5719: dup
    //   5720: iconst_2
    //   5721: getstatic 99	java/lang/Character:TYPE	Ljava/lang/Class;
    //   5724: aastore
    //   5725: invokevirtual 103	java/lang/Class:getMethod	(Ljava/lang/String;[Ljava/lang/Class;)Ljava/lang/reflect/Method;
    //   5728: astore_1
    //   5729: aload_1
    //   5730: aconst_null
    //   5731: iconst_3
    //   5732: anewarray 105	java/lang/Object
    //   5735: dup
    //   5736: iconst_0
    //   5737: ldc_w 512
    //   5740: aastore
    //   5741: dup
    //   5742: iconst_1
    //   5743: sipush 202
    //   5746: invokestatic 111	java/lang/Character:valueOf	(C)Ljava/lang/Character;
    //   5749: aastore
    //   5750: dup
    //   5751: iconst_2
    //   5752: iconst_5
    //   5753: invokestatic 111	java/lang/Character:valueOf	(C)Ljava/lang/Character;
    //   5756: aastore
    //   5757: invokevirtual 117	java/lang/reflect/Method:invoke	(Ljava/lang/Object;[Ljava/lang/Object;)Ljava/lang/Object;
    //   5760: astore_1
    //   5761: new 2	com/db/pwcc/dbmobile/model/banking/GVO
    //   5764: dup
    //   5765: aload_1
    //   5766: checkcast 93	java/lang/String
    //   5769: bipush 63
    //   5771: invokespecial 121	com/db/pwcc/dbmobile/model/banking/GVO:<init>	(Ljava/lang/String;I)V
    //   5774: putstatic 514	com/db/pwcc/dbmobile/model/banking/GVO:FUTURE_DATE_TRANSACTION	Lcom/db/pwcc/dbmobile/model/banking/GVO;
    //   5777: invokestatic 161	com/db/pwcc/dbmobile/model/banking/GVO:b0071qqq00710071qq	()I
    //   5780: invokestatic 164	com/db/pwcc/dbmobile/model/banking/GVO:b00710071qq00710071qq	()I
    //   5783: iadd
    //   5784: invokestatic 161	com/db/pwcc/dbmobile/model/banking/GVO:b0071qqq00710071qq	()I
    //   5787: imul
    //   5788: invokestatic 167	com/db/pwcc/dbmobile/model/banking/GVO:bqq0071q00710071qq	()I
    //   5791: irem
    //   5792: invokestatic 422	com/db/pwcc/dbmobile/model/banking/GVO:bq0071qq00710071qq	()I
    //   5795: if_icmpeq +3 -> 5798
    //   5798: ldc 81
    //   5800: ldc_w 516
    //   5803: sipush 130
    //   5806: sipush 233
    //   5809: iconst_1
    //   5810: invokestatic 129	xxxxxx/uxxxxx:bbbb0062b0062b0062b0062	(Ljava/lang/String;CCC)Ljava/lang/String;
    //   5813: iconst_4
    //   5814: anewarray 91	java/lang/Class
    //   5817: dup
    //   5818: iconst_0
    //   5819: ldc 93
    //   5821: aastore
    //   5822: dup
    //   5823: iconst_1
    //   5824: getstatic 99	java/lang/Character:TYPE	Ljava/lang/Class;
    //   5827: aastore
    //   5828: dup
    //   5829: iconst_2
    //   5830: getstatic 99	java/lang/Character:TYPE	Ljava/lang/Class;
    //   5833: aastore
    //   5834: dup
    //   5835: iconst_3
    //   5836: getstatic 99	java/lang/Character:TYPE	Ljava/lang/Class;
    //   5839: aastore
    //   5840: invokevirtual 103	java/lang/Class:getMethod	(Ljava/lang/String;[Ljava/lang/Class;)Ljava/lang/reflect/Method;
    //   5843: astore_1
    //   5844: aload_1
    //   5845: aconst_null
    //   5846: iconst_4
    //   5847: anewarray 105	java/lang/Object
    //   5850: dup
    //   5851: iconst_0
    //   5852: ldc_w 518
    //   5855: aastore
    //   5856: dup
    //   5857: iconst_1
    //   5858: sipush 239
    //   5861: invokestatic 111	java/lang/Character:valueOf	(C)Ljava/lang/Character;
    //   5864: aastore
    //   5865: dup
    //   5866: iconst_2
    //   5867: sipush 155
    //   5870: invokestatic 111	java/lang/Character:valueOf	(C)Ljava/lang/Character;
    //   5873: aastore
    //   5874: dup
    //   5875: iconst_3
    //   5876: iconst_0
    //   5877: invokestatic 111	java/lang/Character:valueOf	(C)Ljava/lang/Character;
    //   5880: aastore
    //   5881: invokevirtual 117	java/lang/reflect/Method:invoke	(Ljava/lang/Object;[Ljava/lang/Object;)Ljava/lang/Object;
    //   5884: astore_1
    //   5885: new 2	com/db/pwcc/dbmobile/model/banking/GVO
    //   5888: dup
    //   5889: aload_1
    //   5890: checkcast 93	java/lang/String
    //   5893: bipush 64
    //   5895: invokespecial 121	com/db/pwcc/dbmobile/model/banking/GVO:<init>	(Ljava/lang/String;I)V
    //   5898: putstatic 520	com/db/pwcc/dbmobile/model/banking/GVO:MISSING_FUTURE_DATE_TRANSACTION	Lcom/db/pwcc/dbmobile/model/banking/GVO;
    //   5901: invokestatic 161	com/db/pwcc/dbmobile/model/banking/GVO:b0071qqq00710071qq	()I
    //   5904: istore_0
    //   5905: iload_0
    //   5906: invokestatic 164	com/db/pwcc/dbmobile/model/banking/GVO:b00710071qq00710071qq	()I
    //   5909: iload_0
    //   5910: iadd
    //   5911: imul
    //   5912: invokestatic 167	com/db/pwcc/dbmobile/model/banking/GVO:bqq0071q00710071qq	()I
    //   5915: irem
    //   5916: tableswitch	default:+20->5936, 0:+20->5936
    //   5936: getstatic 123	com/db/pwcc/dbmobile/model/banking/GVO:UNSTRUCTURED	Lcom/db/pwcc/dbmobile/model/banking/GVO;
    //   5939: astore_1
    //   5940: getstatic 133	com/db/pwcc/dbmobile/model/banking/GVO:SEPA_STANDING_ORDER	Lcom/db/pwcc/dbmobile/model/banking/GVO;
    //   5943: astore_2
    //   5944: getstatic 139	com/db/pwcc/dbmobile/model/banking/GVO:SEPA_CREDIT_TRANSFER_DB_CLIENT_ORIGINATOR	Lcom/db/pwcc/dbmobile/model/banking/GVO;
    //   5947: astore_3
    //   5948: getstatic 145	com/db/pwcc/dbmobile/model/banking/GVO:SEPA_CREDIT_TRANSFER_DB_CLIENT_RECEIVER	Lcom/db/pwcc/dbmobile/model/banking/GVO;
    //   5951: astore 4
    //   5953: getstatic 151	com/db/pwcc/dbmobile/model/banking/GVO:SEPA_CREDIT_TRANSFER_BULK_OUTGOING	Lcom/db/pwcc/dbmobile/model/banking/GVO;
    //   5956: astore 5
    //   5958: getstatic 157	com/db/pwcc/dbmobile/model/banking/GVO:SEPA_CREDIT_TRANSFER_BULK_INCOMING	Lcom/db/pwcc/dbmobile/model/banking/GVO;
    //   5961: astore 6
    //   5963: getstatic 173	com/db/pwcc/dbmobile/model/banking/GVO:RETURNED_SEPA_CREDIT_TRANSFER	Lcom/db/pwcc/dbmobile/model/banking/GVO;
    //   5966: astore 7
    //   5968: getstatic 179	com/db/pwcc/dbmobile/model/banking/GVO:INCOMING_SEPA_DIRECT_DEBIT_DB_CLIENT_PAYER_B_2_B	Lcom/db/pwcc/dbmobile/model/banking/GVO;
    //   5971: astore 8
    //   5973: getstatic 185	com/db/pwcc/dbmobile/model/banking/GVO:INCOMING_SEPA_DIRECT_DEBIT_DB_CLIENT_PAYER_CORE	Lcom/db/pwcc/dbmobile/model/banking/GVO;
    //   5976: astore 9
    //   5978: getstatic 191	com/db/pwcc/dbmobile/model/banking/GVO:OUTGOING_SEPA_DIRECT_DEBIT_DB_CLIENT_BENEFICIARY_B_2_B	Lcom/db/pwcc/dbmobile/model/banking/GVO;
    //   5981: astore 10
    //   5983: getstatic 197	com/db/pwcc/dbmobile/model/banking/GVO:OUTGOING_SEPA_DIRECT_DEBIT_DB_CLIENT_BENEFICIARY_B_2_B_174	Lcom/db/pwcc/dbmobile/model/banking/GVO;
    //   5986: astore 11
    //   5988: invokestatic 161	com/db/pwcc/dbmobile/model/banking/GVO:b0071qqq00710071qq	()I
    //   5991: invokestatic 164	com/db/pwcc/dbmobile/model/banking/GVO:b00710071qq00710071qq	()I
    //   5994: iadd
    //   5995: invokestatic 161	com/db/pwcc/dbmobile/model/banking/GVO:b0071qqq00710071qq	()I
    //   5998: imul
    //   5999: invokestatic 167	com/db/pwcc/dbmobile/model/banking/GVO:bqq0071q00710071qq	()I
    //   6002: irem
    //   6003: invokestatic 422	com/db/pwcc/dbmobile/model/banking/GVO:bq0071qq00710071qq	()I
    //   6006: if_icmpeq +3 -> 6009
    //   6009: bipush 65
    //   6011: anewarray 2	com/db/pwcc/dbmobile/model/banking/GVO
    //   6014: dup
    //   6015: iconst_0
    //   6016: aload_1
    //   6017: aastore
    //   6018: dup
    //   6019: iconst_1
    //   6020: aload_2
    //   6021: aastore
    //   6022: dup
    //   6023: iconst_2
    //   6024: aload_3
    //   6025: aastore
    //   6026: dup
    //   6027: iconst_3
    //   6028: aload 4
    //   6030: aastore
    //   6031: dup
    //   6032: iconst_4
    //   6033: aload 5
    //   6035: aastore
    //   6036: dup
    //   6037: iconst_5
    //   6038: aload 6
    //   6040: aastore
    //   6041: dup
    //   6042: bipush 6
    //   6044: aload 7
    //   6046: aastore
    //   6047: dup
    //   6048: bipush 7
    //   6050: aload 8
    //   6052: aastore
    //   6053: dup
    //   6054: bipush 8
    //   6056: aload 9
    //   6058: aastore
    //   6059: dup
    //   6060: bipush 9
    //   6062: aload 10
    //   6064: aastore
    //   6065: dup
    //   6066: bipush 10
    //   6068: aload 11
    //   6070: aastore
    //   6071: dup
    //   6072: bipush 11
    //   6074: getstatic 203	com/db/pwcc/dbmobile/model/banking/GVO:BULK_SEPA_DIRECT_DEBIT_CORE	Lcom/db/pwcc/dbmobile/model/banking/GVO;
    //   6077: aastore
    //   6078: dup
    //   6079: bipush 12
    //   6081: getstatic 209	com/db/pwcc/dbmobile/model/banking/GVO:BULK_SEPA_DIRECT_DEBIT	Lcom/db/pwcc/dbmobile/model/banking/GVO;
    //   6084: aastore
    //   6085: dup
    //   6086: bipush 13
    //   6088: getstatic 215	com/db/pwcc/dbmobile/model/banking/GVO:BULK_SEPA_DIRECT_DEBIT_B_2_B	Lcom/db/pwcc/dbmobile/model/banking/GVO;
    //   6091: aastore
    //   6092: dup
    //   6093: bipush 14
    //   6095: getstatic 221	com/db/pwcc/dbmobile/model/banking/GVO:RETURNED_SEPA_DIRECT_DEBIT_B_2_B_ACTIVE	Lcom/db/pwcc/dbmobile/model/banking/GVO;
    //   6098: aastore
    //   6099: dup
    //   6100: bipush 15
    //   6102: getstatic 227	com/db/pwcc/dbmobile/model/banking/GVO:RETURNED_SEPA_DIRECT_DEBIT_CORE	Lcom/db/pwcc/dbmobile/model/banking/GVO;
    //   6105: aastore
    //   6106: dup
    //   6107: bipush 16
    //   6109: getstatic 233	com/db/pwcc/dbmobile/model/banking/GVO:RETURNED_SEPA_DIRECT_DEBIT_PASSIVE	Lcom/db/pwcc/dbmobile/model/banking/GVO;
    //   6112: aastore
    //   6113: dup
    //   6114: bipush 17
    //   6116: getstatic 239	com/db/pwcc/dbmobile/model/banking/GVO:CHARITY_PAYMENT_TO	Lcom/db/pwcc/dbmobile/model/banking/GVO;
    //   6119: aastore
    //   6120: dup
    //   6121: bipush 18
    //   6123: getstatic 245	com/db/pwcc/dbmobile/model/banking/GVO:SEPA_SALARY_PENSION	Lcom/db/pwcc/dbmobile/model/banking/GVO;
    //   6126: aastore
    //   6127: dup
    //   6128: bipush 19
    //   6130: getstatic 251	com/db/pwcc/dbmobile/model/banking/GVO:CAPITAL_BUILDING_FRINGE_FORTUNE	Lcom/db/pwcc/dbmobile/model/banking/GVO;
    //   6133: aastore
    //   6134: dup
    //   6135: bipush 20
    //   6137: getstatic 257	com/db/pwcc/dbmobile/model/banking/GVO:SEPA_PAYMENT_PUBLIC_AUTH	Lcom/db/pwcc/dbmobile/model/banking/GVO;
    //   6140: aastore
    //   6141: dup
    //   6142: bipush 21
    //   6144: getstatic 263	com/db/pwcc/dbmobile/model/banking/GVO:CHARITY_PAYMENT_FROM	Lcom/db/pwcc/dbmobile/model/banking/GVO;
    //   6147: aastore
    //   6148: dup
    //   6149: bipush 22
    //   6151: getstatic 269	com/db/pwcc/dbmobile/model/banking/GVO:ELECTRONIC_CASH_SETTLEMENT	Lcom/db/pwcc/dbmobile/model/banking/GVO;
    //   6154: aastore
    //   6155: dup
    //   6156: bipush 23
    //   6158: getstatic 275	com/db/pwcc/dbmobile/model/banking/GVO:DEBIT_CARD_PAYMENT	Lcom/db/pwcc/dbmobile/model/banking/GVO;
    //   6161: aastore
    //   6162: dup
    //   6163: bipush 24
    //   6165: getstatic 281	com/db/pwcc/dbmobile/model/banking/GVO:CASH_WITHDRAWAL	Lcom/db/pwcc/dbmobile/model/banking/GVO;
    //   6168: aastore
    //   6169: dup
    //   6170: bipush 25
    //   6172: getstatic 287	com/db/pwcc/dbmobile/model/banking/GVO:CHARGE_GELDKARTE	Lcom/db/pwcc/dbmobile/model/banking/GVO;
    //   6175: aastore
    //   6176: dup
    //   6177: bipush 26
    //   6179: getstatic 293	com/db/pwcc/dbmobile/model/banking/GVO:ELECTRONIC_CASH_REVERSAL	Lcom/db/pwcc/dbmobile/model/banking/GVO;
    //   6182: aastore
    //   6183: dup
    //   6184: bipush 27
    //   6186: getstatic 299	com/db/pwcc/dbmobile/model/banking/GVO:ELECTRONIC_CASH_CREDIT_CORRECTION	Lcom/db/pwcc/dbmobile/model/banking/GVO;
    //   6189: aastore
    //   6190: dup
    //   6191: bipush 28
    //   6193: getstatic 305	com/db/pwcc/dbmobile/model/banking/GVO:SEPA_DIRECT_DEBIT_RETURN	Lcom/db/pwcc/dbmobile/model/banking/GVO;
    //   6196: aastore
    //   6197: dup
    //   6198: bipush 29
    //   6200: getstatic 311	com/db/pwcc/dbmobile/model/banking/GVO:CASH_DEPOSIT	Lcom/db/pwcc/dbmobile/model/banking/GVO;
    //   6203: aastore
    //   6204: dup
    //   6205: bipush 30
    //   6207: getstatic 317	com/db/pwcc/dbmobile/model/banking/GVO:PAYDIREKT_PAYMENT	Lcom/db/pwcc/dbmobile/model/banking/GVO;
    //   6210: aastore
    //   6211: dup
    //   6212: bipush 31
    //   6214: getstatic 323	com/db/pwcc/dbmobile/model/banking/GVO:PAYDIREKT_COLLECTION_CREDIT	Lcom/db/pwcc/dbmobile/model/banking/GVO;
    //   6217: aastore
    //   6218: dup
    //   6219: bipush 32
    //   6221: getstatic 329	com/db/pwcc/dbmobile/model/banking/GVO:PAYDIREKT_INDIVIDUAL_CREDIT	Lcom/db/pwcc/dbmobile/model/banking/GVO;
    //   6224: aastore
    //   6225: dup
    //   6226: bipush 33
    //   6228: getstatic 335	com/db/pwcc/dbmobile/model/banking/GVO:PAYDIREKT_BULK_REVERSAL	Lcom/db/pwcc/dbmobile/model/banking/GVO;
    //   6231: aastore
    //   6232: dup
    //   6233: bipush 34
    //   6235: getstatic 341	com/db/pwcc/dbmobile/model/banking/GVO:PAYDIREKT_REVERSAL	Lcom/db/pwcc/dbmobile/model/banking/GVO;
    //   6238: aastore
    //   6239: dup
    //   6240: bipush 35
    //   6242: getstatic 347	com/db/pwcc/dbmobile/model/banking/GVO:PAYDIREKT_REFUND	Lcom/db/pwcc/dbmobile/model/banking/GVO;
    //   6245: aastore
    //   6246: dup
    //   6247: bipush 36
    //   6249: getstatic 353	com/db/pwcc/dbmobile/model/banking/GVO:CREDIT_TRANSFER_BULK_RETURN	Lcom/db/pwcc/dbmobile/model/banking/GVO;
    //   6252: aastore
    //   6253: dup
    //   6254: bipush 37
    //   6256: getstatic 359	com/db/pwcc/dbmobile/model/banking/GVO:SEPA_DIRECT_DEBIT_REVERSAL	Lcom/db/pwcc/dbmobile/model/banking/GVO;
    //   6259: aastore
    //   6260: dup
    //   6261: bipush 38
    //   6263: getstatic 365	com/db/pwcc/dbmobile/model/banking/GVO:SEPA_DIRECT_DEBIT_REVERSAL_B_2_B	Lcom/db/pwcc/dbmobile/model/banking/GVO;
    //   6266: aastore
    //   6267: dup
    //   6268: bipush 39
    //   6270: getstatic 371	com/db/pwcc/dbmobile/model/banking/GVO:DIRECT_DEBIT_BULK_RETURN_B_2_B	Lcom/db/pwcc/dbmobile/model/banking/GVO;
    //   6273: aastore
    //   6274: dup
    //   6275: bipush 40
    //   6277: getstatic 377	com/db/pwcc/dbmobile/model/banking/GVO:DIRECT_DEBIT_BULK_RETURN	Lcom/db/pwcc/dbmobile/model/banking/GVO;
    //   6280: aastore
    //   6281: dup
    //   6282: bipush 41
    //   6284: getstatic 383	com/db/pwcc/dbmobile/model/banking/GVO:SEPA_DIRECT_DEBIT_RETURN_CORE	Lcom/db/pwcc/dbmobile/model/banking/GVO;
    //   6287: aastore
    //   6288: dup
    //   6289: bipush 42
    //   6291: getstatic 389	com/db/pwcc/dbmobile/model/banking/GVO:SEPA_DIRECT_DEBIT_RETURN_B_2_B	Lcom/db/pwcc/dbmobile/model/banking/GVO;
    //   6294: aastore
    //   6295: dup
    //   6296: bipush 43
    //   6298: getstatic 395	com/db/pwcc/dbmobile/model/banking/GVO:SEPA_DIRECT_DEBIT_BULK_CORE	Lcom/db/pwcc/dbmobile/model/banking/GVO;
    //   6301: aastore
    //   6302: dup
    //   6303: bipush 44
    //   6305: getstatic 401	com/db/pwcc/dbmobile/model/banking/GVO:SEPA_DIRECT_DEBIT	Lcom/db/pwcc/dbmobile/model/banking/GVO;
    //   6308: aastore
    //   6309: dup
    //   6310: bipush 45
    //   6312: getstatic 407	com/db/pwcc/dbmobile/model/banking/GVO:SEPA_DIRECT_DEBIT_RETURN_B_2_B_108672	Lcom/db/pwcc/dbmobile/model/banking/GVO;
    //   6315: aastore
    //   6316: dup
    //   6317: bipush 46
    //   6319: getstatic 413	com/db/pwcc/dbmobile/model/banking/GVO:SEPA_DIRECT_DEBIT_BULK_CORE_192679	Lcom/db/pwcc/dbmobile/model/banking/GVO;
    //   6322: aastore
    //   6323: dup
    //   6324: bipush 47
    //   6326: getstatic 419	com/db/pwcc/dbmobile/model/banking/GVO:SEPA_DIRECT_DEBIT_ELV	Lcom/db/pwcc/dbmobile/model/banking/GVO;
    //   6329: aastore
    //   6330: dup
    //   6331: bipush 48
    //   6333: getstatic 428	com/db/pwcc/dbmobile/model/banking/GVO:SEPA_DIRECT_DEBIT_BULK_ELV	Lcom/db/pwcc/dbmobile/model/banking/GVO;
    //   6336: aastore
    //   6337: dup
    //   6338: bipush 49
    //   6340: getstatic 432	com/db/pwcc/dbmobile/model/banking/GVO:SEPA_DIRECT_DEBIT_REVERSAL_181647	Lcom/db/pwcc/dbmobile/model/banking/GVO;
    //   6343: aastore
    //   6344: dup
    //   6345: bipush 50
    //   6347: getstatic 438	com/db/pwcc/dbmobile/model/banking/GVO:SEPA_DIRECT_DEBIT_REVERSAL_B_2_B_184	Lcom/db/pwcc/dbmobile/model/banking/GVO;
    //   6350: aastore
    //   6351: dup
    //   6352: bipush 51
    //   6354: getstatic 444	com/db/pwcc/dbmobile/model/banking/GVO:BILL_PAYMENT	Lcom/db/pwcc/dbmobile/model/banking/GVO;
    //   6357: aastore
    //   6358: dup
    //   6359: bipush 52
    //   6361: getstatic 450	com/db/pwcc/dbmobile/model/banking/GVO:CHEQUE_DEPOSIT	Lcom/db/pwcc/dbmobile/model/banking/GVO;
    //   6364: aastore
    //   6365: dup
    //   6366: bipush 53
    //   6368: getstatic 456	com/db/pwcc/dbmobile/model/banking/GVO:CHEQUE_PAYMENT	Lcom/db/pwcc/dbmobile/model/banking/GVO;
    //   6371: aastore
    //   6372: dup
    //   6373: bipush 54
    //   6375: getstatic 462	com/db/pwcc/dbmobile/model/banking/GVO:CHEQUE_PAYMENT_MULTICURRENCY_CHEQUE	Lcom/db/pwcc/dbmobile/model/banking/GVO;
    //   6378: aastore
    //   6379: dup
    //   6380: bipush 55
    //   6382: getstatic 468	com/db/pwcc/dbmobile/model/banking/GVO:CHEQUE_PAYMENT_TRAVELLER_CHEQUE	Lcom/db/pwcc/dbmobile/model/banking/GVO;
    //   6385: aastore
    //   6386: dup
    //   6387: bipush 56
    //   6389: getstatic 474	com/db/pwcc/dbmobile/model/banking/GVO:CHEQUE_PAYMENT_ORDER_CHEQUE	Lcom/db/pwcc/dbmobile/model/banking/GVO;
    //   6392: aastore
    //   6393: dup
    //   6394: bipush 57
    //   6396: getstatic 480	com/db/pwcc/dbmobile/model/banking/GVO:CHEQUE_PAYMENT_BEARER_CHEQUE	Lcom/db/pwcc/dbmobile/model/banking/GVO;
    //   6399: aastore
    //   6400: dup
    //   6401: bipush 58
    //   6403: getstatic 486	com/db/pwcc/dbmobile/model/banking/GVO:CHEQUE_PAYMENT_BULK	Lcom/db/pwcc/dbmobile/model/banking/GVO;
    //   6406: aastore
    //   6407: dup
    //   6408: bipush 59
    //   6410: getstatic 492	com/db/pwcc/dbmobile/model/banking/GVO:CHEQUE_RETURN	Lcom/db/pwcc/dbmobile/model/banking/GVO;
    //   6413: aastore
    //   6414: dup
    //   6415: bipush 60
    //   6417: getstatic 498	com/db/pwcc/dbmobile/model/banking/GVO:CHEQUE_DENIED_CHEQUE_RETURN	Lcom/db/pwcc/dbmobile/model/banking/GVO;
    //   6420: aastore
    //   6421: dup
    //   6422: bipush 61
    //   6424: getstatic 504	com/db/pwcc/dbmobile/model/banking/GVO:CHEQUE_ACTIVE_RETURN	Lcom/db/pwcc/dbmobile/model/banking/GVO;
    //   6427: aastore
    //   6428: dup
    //   6429: bipush 62
    //   6431: getstatic 510	com/db/pwcc/dbmobile/model/banking/GVO:MULTI_BANKING_TRANSACTION	Lcom/db/pwcc/dbmobile/model/banking/GVO;
    //   6434: aastore
    //   6435: dup
    //   6436: bipush 63
    //   6438: getstatic 514	com/db/pwcc/dbmobile/model/banking/GVO:FUTURE_DATE_TRANSACTION	Lcom/db/pwcc/dbmobile/model/banking/GVO;
    //   6441: aastore
    //   6442: dup
    //   6443: bipush 64
    //   6445: getstatic 520	com/db/pwcc/dbmobile/model/banking/GVO:MISSING_FUTURE_DATE_TRANSACTION	Lcom/db/pwcc/dbmobile/model/banking/GVO;
    //   6448: aastore
    //   6449: putstatic 522	com/db/pwcc/dbmobile/model/banking/GVO:$VALUES	[Lcom/db/pwcc/dbmobile/model/banking/GVO;
    //   6452: return
    //   6453: astore_1
    //   6454: aload_1
    //   6455: invokevirtual 526	java/lang/reflect/InvocationTargetException:getCause	()Ljava/lang/Throwable;
    //   6458: athrow
    //   6459: astore_1
    //   6460: aload_1
    //   6461: invokevirtual 526	java/lang/reflect/InvocationTargetException:getCause	()Ljava/lang/Throwable;
    //   6464: athrow
    //   6465: astore_1
    //   6466: aload_1
    //   6467: invokevirtual 526	java/lang/reflect/InvocationTargetException:getCause	()Ljava/lang/Throwable;
    //   6470: athrow
    //   6471: astore_1
    //   6472: aload_1
    //   6473: invokevirtual 526	java/lang/reflect/InvocationTargetException:getCause	()Ljava/lang/Throwable;
    //   6476: athrow
    //   6477: astore_1
    //   6478: aload_1
    //   6479: invokevirtual 526	java/lang/reflect/InvocationTargetException:getCause	()Ljava/lang/Throwable;
    //   6482: athrow
    //   6483: astore_1
    //   6484: aload_1
    //   6485: invokevirtual 526	java/lang/reflect/InvocationTargetException:getCause	()Ljava/lang/Throwable;
    //   6488: athrow
    //   6489: astore_1
    //   6490: aload_1
    //   6491: invokevirtual 526	java/lang/reflect/InvocationTargetException:getCause	()Ljava/lang/Throwable;
    //   6494: athrow
    //   6495: astore_1
    //   6496: aload_1
    //   6497: invokevirtual 526	java/lang/reflect/InvocationTargetException:getCause	()Ljava/lang/Throwable;
    //   6500: athrow
    //   6501: astore_1
    //   6502: aload_1
    //   6503: invokevirtual 526	java/lang/reflect/InvocationTargetException:getCause	()Ljava/lang/Throwable;
    //   6506: athrow
    //   6507: astore_1
    //   6508: aload_1
    //   6509: invokevirtual 526	java/lang/reflect/InvocationTargetException:getCause	()Ljava/lang/Throwable;
    //   6512: athrow
    //   6513: astore_1
    //   6514: aload_1
    //   6515: invokevirtual 526	java/lang/reflect/InvocationTargetException:getCause	()Ljava/lang/Throwable;
    //   6518: athrow
    //   6519: astore_1
    //   6520: aload_1
    //   6521: invokevirtual 526	java/lang/reflect/InvocationTargetException:getCause	()Ljava/lang/Throwable;
    //   6524: athrow
    //   6525: astore_1
    //   6526: aload_1
    //   6527: invokevirtual 526	java/lang/reflect/InvocationTargetException:getCause	()Ljava/lang/Throwable;
    //   6530: athrow
    //   6531: astore_1
    //   6532: aload_1
    //   6533: invokevirtual 526	java/lang/reflect/InvocationTargetException:getCause	()Ljava/lang/Throwable;
    //   6536: athrow
    //   6537: astore_1
    //   6538: aload_1
    //   6539: invokevirtual 526	java/lang/reflect/InvocationTargetException:getCause	()Ljava/lang/Throwable;
    //   6542: athrow
    //   6543: astore_1
    //   6544: aload_1
    //   6545: invokevirtual 526	java/lang/reflect/InvocationTargetException:getCause	()Ljava/lang/Throwable;
    //   6548: athrow
    //   6549: astore_1
    //   6550: aload_1
    //   6551: invokevirtual 526	java/lang/reflect/InvocationTargetException:getCause	()Ljava/lang/Throwable;
    //   6554: athrow
    //   6555: astore_1
    //   6556: aload_1
    //   6557: invokevirtual 526	java/lang/reflect/InvocationTargetException:getCause	()Ljava/lang/Throwable;
    //   6560: athrow
    //   6561: astore_1
    //   6562: aload_1
    //   6563: invokevirtual 526	java/lang/reflect/InvocationTargetException:getCause	()Ljava/lang/Throwable;
    //   6566: athrow
    //   6567: astore_1
    //   6568: aload_1
    //   6569: invokevirtual 526	java/lang/reflect/InvocationTargetException:getCause	()Ljava/lang/Throwable;
    //   6572: athrow
    //   6573: astore_1
    //   6574: aload_1
    //   6575: invokevirtual 526	java/lang/reflect/InvocationTargetException:getCause	()Ljava/lang/Throwable;
    //   6578: athrow
    //   6579: astore_1
    //   6580: aload_1
    //   6581: invokevirtual 526	java/lang/reflect/InvocationTargetException:getCause	()Ljava/lang/Throwable;
    //   6584: athrow
    //   6585: astore_1
    //   6586: aload_1
    //   6587: invokevirtual 526	java/lang/reflect/InvocationTargetException:getCause	()Ljava/lang/Throwable;
    //   6590: athrow
    //   6591: astore_1
    //   6592: aload_1
    //   6593: invokevirtual 526	java/lang/reflect/InvocationTargetException:getCause	()Ljava/lang/Throwable;
    //   6596: athrow
    //   6597: astore_1
    //   6598: aload_1
    //   6599: invokevirtual 526	java/lang/reflect/InvocationTargetException:getCause	()Ljava/lang/Throwable;
    //   6602: athrow
    //   6603: astore_1
    //   6604: aload_1
    //   6605: invokevirtual 526	java/lang/reflect/InvocationTargetException:getCause	()Ljava/lang/Throwable;
    //   6608: athrow
    //   6609: astore_1
    //   6610: aload_1
    //   6611: invokevirtual 526	java/lang/reflect/InvocationTargetException:getCause	()Ljava/lang/Throwable;
    //   6614: athrow
    //   6615: astore_1
    //   6616: aload_1
    //   6617: invokevirtual 526	java/lang/reflect/InvocationTargetException:getCause	()Ljava/lang/Throwable;
    //   6620: athrow
    //   6621: astore_1
    //   6622: aload_1
    //   6623: invokevirtual 526	java/lang/reflect/InvocationTargetException:getCause	()Ljava/lang/Throwable;
    //   6626: athrow
    //   6627: astore_1
    //   6628: aload_1
    //   6629: invokevirtual 526	java/lang/reflect/InvocationTargetException:getCause	()Ljava/lang/Throwable;
    //   6632: athrow
    //   6633: astore_1
    //   6634: aload_1
    //   6635: invokevirtual 526	java/lang/reflect/InvocationTargetException:getCause	()Ljava/lang/Throwable;
    //   6638: athrow
    //   6639: astore_1
    //   6640: aload_1
    //   6641: invokevirtual 526	java/lang/reflect/InvocationTargetException:getCause	()Ljava/lang/Throwable;
    //   6644: athrow
    //   6645: astore_1
    //   6646: aload_1
    //   6647: invokevirtual 526	java/lang/reflect/InvocationTargetException:getCause	()Ljava/lang/Throwable;
    //   6650: athrow
    //   6651: astore_1
    //   6652: aload_1
    //   6653: invokevirtual 526	java/lang/reflect/InvocationTargetException:getCause	()Ljava/lang/Throwable;
    //   6656: athrow
    //   6657: astore_1
    //   6658: aload_1
    //   6659: invokevirtual 526	java/lang/reflect/InvocationTargetException:getCause	()Ljava/lang/Throwable;
    //   6662: athrow
    //   6663: astore_1
    //   6664: aload_1
    //   6665: invokevirtual 526	java/lang/reflect/InvocationTargetException:getCause	()Ljava/lang/Throwable;
    //   6668: athrow
    //   6669: astore_1
    //   6670: aload_1
    //   6671: invokevirtual 526	java/lang/reflect/InvocationTargetException:getCause	()Ljava/lang/Throwable;
    //   6674: athrow
    //   6675: astore_1
    //   6676: aload_1
    //   6677: invokevirtual 526	java/lang/reflect/InvocationTargetException:getCause	()Ljava/lang/Throwable;
    //   6680: athrow
    //   6681: astore_1
    //   6682: aload_1
    //   6683: invokevirtual 526	java/lang/reflect/InvocationTargetException:getCause	()Ljava/lang/Throwable;
    //   6686: athrow
    //   6687: astore_1
    //   6688: aload_1
    //   6689: invokevirtual 526	java/lang/reflect/InvocationTargetException:getCause	()Ljava/lang/Throwable;
    //   6692: athrow
    //   6693: astore_1
    //   6694: aload_1
    //   6695: invokevirtual 526	java/lang/reflect/InvocationTargetException:getCause	()Ljava/lang/Throwable;
    //   6698: athrow
    //   6699: astore_1
    //   6700: aload_1
    //   6701: invokevirtual 526	java/lang/reflect/InvocationTargetException:getCause	()Ljava/lang/Throwable;
    //   6704: athrow
    //   6705: astore_1
    //   6706: aload_1
    //   6707: invokevirtual 526	java/lang/reflect/InvocationTargetException:getCause	()Ljava/lang/Throwable;
    //   6710: athrow
    //   6711: astore_1
    //   6712: aload_1
    //   6713: invokevirtual 526	java/lang/reflect/InvocationTargetException:getCause	()Ljava/lang/Throwable;
    //   6716: athrow
    //   6717: astore_1
    //   6718: aload_1
    //   6719: invokevirtual 526	java/lang/reflect/InvocationTargetException:getCause	()Ljava/lang/Throwable;
    //   6722: athrow
    //   6723: astore_1
    //   6724: aload_1
    //   6725: invokevirtual 526	java/lang/reflect/InvocationTargetException:getCause	()Ljava/lang/Throwable;
    //   6728: athrow
    //   6729: astore_1
    //   6730: aload_1
    //   6731: invokevirtual 526	java/lang/reflect/InvocationTargetException:getCause	()Ljava/lang/Throwable;
    //   6734: athrow
    //   6735: astore_1
    //   6736: aload_1
    //   6737: invokevirtual 526	java/lang/reflect/InvocationTargetException:getCause	()Ljava/lang/Throwable;
    //   6740: athrow
    //   6741: astore_1
    //   6742: aload_1
    //   6743: invokevirtual 526	java/lang/reflect/InvocationTargetException:getCause	()Ljava/lang/Throwable;
    //   6746: athrow
    //   6747: astore_1
    //   6748: aload_1
    //   6749: invokevirtual 526	java/lang/reflect/InvocationTargetException:getCause	()Ljava/lang/Throwable;
    //   6752: athrow
    //   6753: astore_1
    //   6754: aload_1
    //   6755: invokevirtual 526	java/lang/reflect/InvocationTargetException:getCause	()Ljava/lang/Throwable;
    //   6758: athrow
    //   6759: astore_1
    //   6760: aload_1
    //   6761: invokevirtual 526	java/lang/reflect/InvocationTargetException:getCause	()Ljava/lang/Throwable;
    //   6764: athrow
    //   6765: astore_1
    //   6766: aload_1
    //   6767: invokevirtual 526	java/lang/reflect/InvocationTargetException:getCause	()Ljava/lang/Throwable;
    //   6770: athrow
    //   6771: astore_1
    //   6772: aload_1
    //   6773: invokevirtual 526	java/lang/reflect/InvocationTargetException:getCause	()Ljava/lang/Throwable;
    //   6776: athrow
    //   6777: astore_1
    //   6778: aload_1
    //   6779: invokevirtual 526	java/lang/reflect/InvocationTargetException:getCause	()Ljava/lang/Throwable;
    //   6782: athrow
    //   6783: astore_1
    //   6784: aload_1
    //   6785: invokevirtual 526	java/lang/reflect/InvocationTargetException:getCause	()Ljava/lang/Throwable;
    //   6788: athrow
    //   6789: astore_1
    //   6790: aload_1
    //   6791: invokevirtual 526	java/lang/reflect/InvocationTargetException:getCause	()Ljava/lang/Throwable;
    //   6794: athrow
    //   6795: astore_1
    //   6796: aload_1
    //   6797: invokevirtual 526	java/lang/reflect/InvocationTargetException:getCause	()Ljava/lang/Throwable;
    //   6800: athrow
    //   6801: astore_1
    //   6802: aload_1
    //   6803: invokevirtual 526	java/lang/reflect/InvocationTargetException:getCause	()Ljava/lang/Throwable;
    //   6806: athrow
    //   6807: astore_1
    //   6808: aload_1
    //   6809: invokevirtual 526	java/lang/reflect/InvocationTargetException:getCause	()Ljava/lang/Throwable;
    //   6812: athrow
    //   6813: astore_1
    //   6814: aload_1
    //   6815: invokevirtual 526	java/lang/reflect/InvocationTargetException:getCause	()Ljava/lang/Throwable;
    //   6818: athrow
    //   6819: astore_1
    //   6820: aload_1
    //   6821: invokevirtual 526	java/lang/reflect/InvocationTargetException:getCause	()Ljava/lang/Throwable;
    //   6824: athrow
    //   6825: astore_1
    //   6826: aload_1
    //   6827: invokevirtual 526	java/lang/reflect/InvocationTargetException:getCause	()Ljava/lang/Throwable;
    //   6830: athrow
    //   6831: astore_1
    //   6832: aload_1
    //   6833: invokevirtual 526	java/lang/reflect/InvocationTargetException:getCause	()Ljava/lang/Throwable;
    //   6836: athrow
    //   6837: astore_1
    //   6838: aload_1
    //   6839: invokevirtual 526	java/lang/reflect/InvocationTargetException:getCause	()Ljava/lang/Throwable;
    //   6842: athrow
    // Local variable table:
    //   start	length	slot	name	signature
    //   541	5371	0	i	int
    //   34	5983	1	localObject	Object
    //   6453	2	1	localInvocationTargetException1	java.lang.reflect.InvocationTargetException
    //   6459	2	1	localInvocationTargetException2	java.lang.reflect.InvocationTargetException
    //   6465	2	1	localInvocationTargetException3	java.lang.reflect.InvocationTargetException
    //   6471	2	1	localInvocationTargetException4	java.lang.reflect.InvocationTargetException
    //   6477	2	1	localInvocationTargetException5	java.lang.reflect.InvocationTargetException
    //   6483	2	1	localInvocationTargetException6	java.lang.reflect.InvocationTargetException
    //   6489	2	1	localInvocationTargetException7	java.lang.reflect.InvocationTargetException
    //   6495	2	1	localInvocationTargetException8	java.lang.reflect.InvocationTargetException
    //   6501	2	1	localInvocationTargetException9	java.lang.reflect.InvocationTargetException
    //   6507	2	1	localInvocationTargetException10	java.lang.reflect.InvocationTargetException
    //   6513	2	1	localInvocationTargetException11	java.lang.reflect.InvocationTargetException
    //   6519	2	1	localInvocationTargetException12	java.lang.reflect.InvocationTargetException
    //   6525	2	1	localInvocationTargetException13	java.lang.reflect.InvocationTargetException
    //   6531	2	1	localInvocationTargetException14	java.lang.reflect.InvocationTargetException
    //   6537	2	1	localInvocationTargetException15	java.lang.reflect.InvocationTargetException
    //   6543	2	1	localInvocationTargetException16	java.lang.reflect.InvocationTargetException
    //   6549	2	1	localInvocationTargetException17	java.lang.reflect.InvocationTargetException
    //   6555	2	1	localInvocationTargetException18	java.lang.reflect.InvocationTargetException
    //   6561	2	1	localInvocationTargetException19	java.lang.reflect.InvocationTargetException
    //   6567	2	1	localInvocationTargetException20	java.lang.reflect.InvocationTargetException
    //   6573	2	1	localInvocationTargetException21	java.lang.reflect.InvocationTargetException
    //   6579	2	1	localInvocationTargetException22	java.lang.reflect.InvocationTargetException
    //   6585	2	1	localInvocationTargetException23	java.lang.reflect.InvocationTargetException
    //   6591	2	1	localInvocationTargetException24	java.lang.reflect.InvocationTargetException
    //   6597	2	1	localInvocationTargetException25	java.lang.reflect.InvocationTargetException
    //   6603	2	1	localInvocationTargetException26	java.lang.reflect.InvocationTargetException
    //   6609	2	1	localInvocationTargetException27	java.lang.reflect.InvocationTargetException
    //   6615	2	1	localInvocationTargetException28	java.lang.reflect.InvocationTargetException
    //   6621	2	1	localInvocationTargetException29	java.lang.reflect.InvocationTargetException
    //   6627	2	1	localInvocationTargetException30	java.lang.reflect.InvocationTargetException
    //   6633	2	1	localInvocationTargetException31	java.lang.reflect.InvocationTargetException
    //   6639	2	1	localInvocationTargetException32	java.lang.reflect.InvocationTargetException
    //   6645	2	1	localInvocationTargetException33	java.lang.reflect.InvocationTargetException
    //   6651	2	1	localInvocationTargetException34	java.lang.reflect.InvocationTargetException
    //   6657	2	1	localInvocationTargetException35	java.lang.reflect.InvocationTargetException
    //   6663	2	1	localInvocationTargetException36	java.lang.reflect.InvocationTargetException
    //   6669	2	1	localInvocationTargetException37	java.lang.reflect.InvocationTargetException
    //   6675	2	1	localInvocationTargetException38	java.lang.reflect.InvocationTargetException
    //   6681	2	1	localInvocationTargetException39	java.lang.reflect.InvocationTargetException
    //   6687	2	1	localInvocationTargetException40	java.lang.reflect.InvocationTargetException
    //   6693	2	1	localInvocationTargetException41	java.lang.reflect.InvocationTargetException
    //   6699	2	1	localInvocationTargetException42	java.lang.reflect.InvocationTargetException
    //   6705	2	1	localInvocationTargetException43	java.lang.reflect.InvocationTargetException
    //   6711	2	1	localInvocationTargetException44	java.lang.reflect.InvocationTargetException
    //   6717	2	1	localInvocationTargetException45	java.lang.reflect.InvocationTargetException
    //   6723	2	1	localInvocationTargetException46	java.lang.reflect.InvocationTargetException
    //   6729	2	1	localInvocationTargetException47	java.lang.reflect.InvocationTargetException
    //   6735	2	1	localInvocationTargetException48	java.lang.reflect.InvocationTargetException
    //   6741	2	1	localInvocationTargetException49	java.lang.reflect.InvocationTargetException
    //   6747	2	1	localInvocationTargetException50	java.lang.reflect.InvocationTargetException
    //   6753	2	1	localInvocationTargetException51	java.lang.reflect.InvocationTargetException
    //   6759	2	1	localInvocationTargetException52	java.lang.reflect.InvocationTargetException
    //   6765	2	1	localInvocationTargetException53	java.lang.reflect.InvocationTargetException
    //   6771	2	1	localInvocationTargetException54	java.lang.reflect.InvocationTargetException
    //   6777	2	1	localInvocationTargetException55	java.lang.reflect.InvocationTargetException
    //   6783	2	1	localInvocationTargetException56	java.lang.reflect.InvocationTargetException
    //   6789	2	1	localInvocationTargetException57	java.lang.reflect.InvocationTargetException
    //   6795	2	1	localInvocationTargetException58	java.lang.reflect.InvocationTargetException
    //   6801	2	1	localInvocationTargetException59	java.lang.reflect.InvocationTargetException
    //   6807	2	1	localInvocationTargetException60	java.lang.reflect.InvocationTargetException
    //   6813	2	1	localInvocationTargetException61	java.lang.reflect.InvocationTargetException
    //   6819	2	1	localInvocationTargetException62	java.lang.reflect.InvocationTargetException
    //   6825	2	1	localInvocationTargetException63	java.lang.reflect.InvocationTargetException
    //   6831	2	1	localInvocationTargetException64	java.lang.reflect.InvocationTargetException
    //   6837	2	1	localInvocationTargetException65	java.lang.reflect.InvocationTargetException
    //   5943	78	2	localGVO1	GVO
    //   5947	78	3	localGVO2	GVO
    //   5951	78	4	localGVO3	GVO
    //   5956	78	5	localGVO4	GVO
    //   5961	78	6	localGVO5	GVO
    //   5966	79	7	localGVO6	GVO
    //   5971	80	8	localGVO7	GVO
    //   5976	81	9	localGVO8	GVO
    //   5981	82	10	localGVO9	GVO
    //   5986	83	11	localGVO10	GVO
    // Exception table:
    //   from	to	target	type
    //   1819	1849	6453	java/lang/reflect/InvocationTargetException
    //   118	149	6459	java/lang/reflect/InvocationTargetException
    //   209	248	6465	java/lang/reflect/InvocationTargetException
    //   307	345	6471	java/lang/reflect/InvocationTargetException
    //   614	653	6477	java/lang/reflect/InvocationTargetException
    //   705	736	6483	java/lang/reflect/InvocationTargetException
    //   787	817	6489	java/lang/reflect/InvocationTargetException
    //   4913	4944	6495	java/lang/reflect/InvocationTargetException
    //   1033	1063	6501	java/lang/reflect/InvocationTargetException
    //   1197	1228	6507	java/lang/reflect/InvocationTargetException
    //   5729	5761	6513	java/lang/reflect/InvocationTargetException
    //   3176	3216	6519	java/lang/reflect/InvocationTargetException
    //   3268	3300	6525	java/lang/reflect/InvocationTargetException
    //   1464	1494	6531	java/lang/reflect/InvocationTargetException
    //   5462	5494	6537	java/lang/reflect/InvocationTargetException
    //   5546	5577	6543	java/lang/reflect/InvocationTargetException
    //   5635	5674	6549	java/lang/reflect/InvocationTargetException
    //   1646	1685	6555	java/lang/reflect/InvocationTargetException
    //   3875	3906	6561	java/lang/reflect/InvocationTargetException
    //   1372	1412	6567	java/lang/reflect/InvocationTargetException
    //   1989	2020	6573	java/lang/reflect/InvocationTargetException
    //   2078	2119	6579	java/lang/reflect/InvocationTargetException
    //   2175	2206	6585	java/lang/reflect/InvocationTargetException
    //   35	65	6591	java/lang/reflect/InvocationTargetException
    //   3620	3651	6597	java/lang/reflect/InvocationTargetException
    //   4699	4740	6603	java/lang/reflect/InvocationTargetException
    //   492	523	6609	java/lang/reflect/InvocationTargetException
    //   5284	5324	6615	java/lang/reflect/InvocationTargetException
    //   2616	2657	6621	java/lang/reflect/InvocationTargetException
    //   4049	4088	6627	java/lang/reflect/InvocationTargetException
    //   401	441	6633	java/lang/reflect/InvocationTargetException
    //   1114	1144	6639	java/lang/reflect/InvocationTargetException
    //   3526	3566	6645	java/lang/reflect/InvocationTargetException
    //   2902	2943	6651	java/lang/reflect/InvocationTargetException
    //   2999	3031	6657	java/lang/reflect/InvocationTargetException
    //   2348	2388	6663	java/lang/reflect/InvocationTargetException
    //   3436	3468	6669	java/lang/reflect/InvocationTargetException
    //   1281	1312	6675	java/lang/reflect/InvocationTargetException
    //   5003	5043	6681	java/lang/reflect/InvocationTargetException
    //   1903	1935	6687	java/lang/reflect/InvocationTargetException
    //   952	982	6693	java/lang/reflect/InvocationTargetException
    //   4435	4466	6699	java/lang/reflect/InvocationTargetException
    //   5378	5410	6705	java/lang/reflect/InvocationTargetException
    //   4522	4554	6711	java/lang/reflect/InvocationTargetException
    //   4229	4260	6717	java/lang/reflect/InvocationTargetException
    //   1551	1589	6723	java/lang/reflect/InvocationTargetException
    //   2258	2290	6729	java/lang/reflect/InvocationTargetException
    //   4792	4823	6735	java/lang/reflect/InvocationTargetException
    //   5844	5885	6741	java/lang/reflect/InvocationTargetException
    //   3083	3115	6747	java/lang/reflect/InvocationTargetException
    //   1737	1767	6753	java/lang/reflect/InvocationTargetException
    //   4143	4174	6759	java/lang/reflect/InvocationTargetException
    //   869	899	6765	java/lang/reflect/InvocationTargetException
    //   4340	4379	6771	java/lang/reflect/InvocationTargetException
    //   2809	2841	6777	java/lang/reflect/InvocationTargetException
    //   5102	5141	6783	java/lang/reflect/InvocationTargetException
    //   4606	4637	6789	java/lang/reflect/InvocationTargetException
    //   3703	3735	6795	java/lang/reflect/InvocationTargetException
    //   2443	2474	6801	java/lang/reflect/InvocationTargetException
    //   2527	2558	6807	java/lang/reflect/InvocationTargetException
    //   5194	5226	6813	java/lang/reflect/InvocationTargetException
    //   2715	2756	6819	java/lang/reflect/InvocationTargetException
    //   3352	3384	6825	java/lang/reflect/InvocationTargetException
    //   3959	3991	6831	java/lang/reflect/InvocationTargetException
    //   3788	3819	6837	java/lang/reflect/InvocationTargetException
  }
  
  private GVO() {}
  
  public static int b00710071qq00710071qq()
  {
    return 1;
  }
  
  public static int b0071qqq00710071qq()
  {
    return 15;
  }
  
  public static int bq0071qq00710071qq()
  {
    return 0;
  }
  
  public static int bqq0071q00710071qq()
  {
    return 2;
  }
}
