package kkkkkk;

import android.location.Location;
import android.location.LocationListener;
import android.os.Bundle;
import javax.annotation.Nonnull;
import javax.annotation.Nullable;

public class afaaaa
  implements LocationListener
{
  public static int b042204220422ТТ042204220422ТТ = 80;
  public static int b0422Т0422ТТ042204220422ТТ = 2;
  public static int bТ04220422ТТ042204220422ТТ = 0;
  private static final String bТ0422ТТТ042204220422ТТ;
  public static int bТТ0422ТТ042204220422ТТ = 1;
  @Nullable
  public Location b04220422ТТТ042204220422ТТ = null;
  
  /* Error */
  static
  {
    // Byte code:
    //   0: ldc 2
    //   2: invokestatic 30	kkkkkk/fafffa:b043A043A043A043Aкк043Aкк043A	(Ljava/lang/Class;)Ljava/lang/String;
    //   5: astore_1
    //   6: invokestatic 34	kkkkkk/afaaaa:bкк043Aк043Aк043A043A043Aк	()I
    //   9: istore_0
    //   10: iload_0
    //   11: getstatic 36	kkkkkk/afaaaa:bТТ0422ТТ042204220422ТТ	I
    //   14: iload_0
    //   15: iadd
    //   16: imul
    //   17: getstatic 38	kkkkkk/afaaaa:b0422Т0422ТТ042204220422ТТ	I
    //   20: irem
    //   21: tableswitch	default:+19->40, 0:+64->85
    //   40: bipush 62
    //   42: putstatic 36	kkkkkk/afaaaa:bТТ0422ТТ042204220422ТТ	I
    //   45: invokestatic 34	kkkkkk/afaaaa:bкк043Aк043Aк043A043A043Aк	()I
    //   48: istore_0
    //   49: iload_0
    //   50: getstatic 36	kkkkkk/afaaaa:bТТ0422ТТ042204220422ТТ	I
    //   53: iload_0
    //   54: iadd
    //   55: imul
    //   56: getstatic 38	kkkkkk/afaaaa:b0422Т0422ТТ042204220422ТТ	I
    //   59: irem
    //   60: tableswitch	default:+20->80, 0:+25->85
    //   80: bipush 83
    //   82: putstatic 36	kkkkkk/afaaaa:bТТ0422ТТ042204220422ТТ	I
    //   85: aload_1
    //   86: putstatic 40	kkkkkk/afaaaa:bТ0422ТТТ042204220422ТТ	Ljava/lang/String;
    //   89: return
    //   90: astore_1
    //   91: aload_1
    //   92: athrow
    //   93: astore_1
    //   94: aload_1
    //   95: athrow
    // Local variable table:
    //   start	length	slot	name	signature
    //   9	47	0	i	int
    //   5	81	1	str	String
    //   90	2	1	localException1	Exception
    //   93	2	1	localException2	Exception
    // Exception table:
    //   from	to	target	type
    //   0	6	90	java/lang/Exception
    //   85	89	93	java/lang/Exception
  }
  
  public afaaaa() {}
  
  public static int bкк043Aк043Aк043A043A043Aк()
  {
    return 18;
  }
  
  public void onLocationChanged(@Nonnull Location paramLocation)
  {
    int i1 = 1;
    switch (1)
    {
    case 0: 
    default: 
      for (;;)
      {
        switch (1)
        {
        }
      }
    }
    fafffa.b043Aккк043Aк043Aкк043A(bТ0422ТТТ042204220422ТТ, gguuuu.bк043Aккк043Aкк043A043A("OM*L?<NBGE\031=5A964vvl\006j", '¸', '', '\000') + paramLocation.getProvider() + gguuuu.bккккк043Aкк043A043A("F", '', '\000') + paramLocation.getLatitude() + gguuuu.bк043Aккк043Aкк043A043A("1", '', '', '\000') + paramLocation.getLongitude() + gguuuu.bк043Aккк043Aкк043A043A(">", 'w', 's', '\001') + paramLocation.getAccuracy());
    if ((bкк043Aк043Aк043A043A043Aк() + bТТ0422ТТ042204220422ТТ) * bкк043Aк043Aк043A043A043Aк() % b0422Т0422ТТ042204220422ТТ != bТ04220422ТТ042204220422ТТ) {
      bТ04220422ТТ042204220422ТТ = bкк043Aк043Aк043A043A043Aк();
    }
    Object localObject2 = this.b04220422ТТТ042204220422ТТ;
    int m;
    boolean bool;
    if (localObject2 == null)
    {
      m = i1;
      if (m != 0) {
        this.b04220422ТТТ042204220422ТТ = paramLocation;
      }
      return;
      if (localObject2 != null) {
        break label511;
      }
      m = b042204220422ТТ042204220422ТТ;
      switch (m * (bТТ0422ТТ042204220422ТТ + m) % b0422Т0422ТТ042204220422ТТ)
      {
      default: 
        b042204220422ТТ042204220422ТТ = 24;
        bТ04220422ТТ042204220422ТТ = bкк043Aк043Aк043A043A043Aк();
      }
      bool = true;
    }
    for (;;)
    {
      label258:
      m = i1;
      int k;
      if (k != 0) {
        break;
      }
      int i;
      if (i != 0)
      {
        m = i1;
        if (j == 0) {
          break;
        }
      }
      if ((i != 0) && (n == 0))
      {
        m = i1;
        if (bool) {
          break;
        }
      }
      label297:
      m = 0;
      break;
      label303:
      int j = 0;
      label305:
      if (m < 0)
      {
        k = 1;
        label313:
        if (m <= 200) {
          break label505;
        }
      }
      label391:
      label393:
      label405:
      label494:
      label505:
      for (int n = 1;; n = 0)
      {
        String str = paramLocation.getProvider();
        localObject2 = ((Location)localObject2).getProvider();
        if (str == null)
        {
          switch (0)
          {
          }
          for (;;)
          {
            switch (1)
            {
            }
          }
          j = 0;
          Object localObject1;
          if (localObject1 < -120000L)
          {
            k = 1;
            if (localObject1 <= 0L) {
              break label494;
            }
          }
        }
        for (i = 1;; i = 0)
        {
          m = i1;
          if (j != 0) {
            break;
          }
          if (k != 0) {
            break label297;
          }
          m = (int)(paramLocation.getAccuracy() - ((Location)localObject2).getAccuracy());
          if (m <= 0) {
            break label303;
          }
          j = 1;
          break label305;
          k = 0;
          break label405;
          long l = paramLocation.getTime() - ((Location)localObject2).getTime();
          if (l <= 120000L) {
            break label391;
          }
          j = 1;
          break label393;
          bool = str.equals(localObject2);
          break label258;
        }
        k = 0;
        break label313;
      }
      label511:
      bool = false;
    }
  }
  
  /* Error */
  public void onProviderDisabled(String paramString)
  {
    // Byte code:
    //   0: getstatic 40	kkkkkk/afaaaa:bТ0422ТТТ042204220422ТТ	Ljava/lang/String;
    //   3: new 51	java/lang/StringBuilder
    //   6: dup
    //   7: ldc -128
    //   9: sipush 137
    //   12: iconst_0
    //   13: invokestatic 78	kkkkkk/gguuuu:bккккк043Aкк043A043A	(Ljava/lang/String;CC)Ljava/lang/String;
    //   16: invokespecial 62	java/lang/StringBuilder:<init>	(Ljava/lang/String;)V
    //   19: aload_1
    //   20: invokevirtual 72	java/lang/StringBuilder:append	(Ljava/lang/String;)Ljava/lang/StringBuilder;
    //   23: invokevirtual 102	java/lang/StringBuilder:toString	()Ljava/lang/String;
    //   26: invokestatic 106	kkkkkk/fafffa:b043Aккк043Aк043Aкк043A	(Ljava/lang/String;Ljava/lang/String;)V
    //   29: getstatic 110	kkkkkk/afaaaa:b042204220422ТТ042204220422ТТ	I
    //   32: istore_2
    //   33: getstatic 36	kkkkkk/afaaaa:bТТ0422ТТ042204220422ТТ	I
    //   36: istore_3
    //   37: getstatic 38	kkkkkk/afaaaa:b0422Т0422ТТ042204220422ТТ	I
    //   40: istore 4
    //   42: iload_2
    //   43: iload_3
    //   44: iload_2
    //   45: iadd
    //   46: imul
    //   47: iload 4
    //   49: irem
    //   50: tableswitch	default:+18->68, 0:+29->79
    //   68: invokestatic 34	kkkkkk/afaaaa:bкк043Aк043Aк043A043A043Aк	()I
    //   71: putstatic 110	kkkkkk/afaaaa:b042204220422ТТ042204220422ТТ	I
    //   74: bipush 98
    //   76: putstatic 108	kkkkkk/afaaaa:bТ04220422ТТ042204220422ТТ	I
    //   79: return
    //   80: astore_1
    //   81: aload_1
    //   82: athrow
    //   83: astore_1
    //   84: aload_1
    //   85: athrow
    // Local variable table:
    //   start	length	slot	name	signature
    //   0	86	0	this	afaaaa
    //   0	86	1	paramString	String
    //   32	15	2	i	int
    //   36	10	3	j	int
    //   40	10	4	k	int
    // Exception table:
    //   from	to	target	type
    //   0	42	80	java/lang/Exception
    //   68	79	83	java/lang/Exception
  }
  
  public void onProviderEnabled(String paramString)
  {
    String str = bТ0422ТТТ042204220422ТТ;
    StringBuilder localStringBuilder = new StringBuilder(gguuuu.bк043Aккк043Aкк043A043A("qqTwu}qmo}Q{oq|vvM4", '?', 'B', '\003'));
    int i = b042204220422ТТ042204220422ТТ;
    switch (i * (bТТ0422ТТ042204220422ТТ + i) % b0422Т0422ТТ042204220422ТТ)
    {
    default: 
      b042204220422ТТ042204220422ТТ = bкк043Aк043Aк043A043A043Aк();
      bТ04220422ТТ042204220422ТТ = bкк043Aк043Aк043A043A043Aк();
    }
    paramString = paramString;
    if ((b042204220422ТТ042204220422ТТ + bТТ0422ТТ042204220422ТТ) * b042204220422ТТ042204220422ТТ % b0422Т0422ТТ042204220422ТТ != bТ04220422ТТ042204220422ТТ)
    {
      b042204220422ТТ042204220422ТТ = bкк043Aк043Aк043A043A043Aк();
      bТ04220422ТТ042204220422ТТ = bкк043Aк043Aк043A043A043Aк();
    }
    fafffa.b043Aккк043Aк043Aкк043A(str, paramString);
  }
  
  public void onStatusChanged(String paramString, int paramInt, Bundle paramBundle)
  {
    throw new Runtime("d2j fail translate: java.lang.IndexOutOfBoundsException: fromIndex < 0: -1\n\tat java.util.BitSet.nextSetBit(BitSet.java:712)\n\tat com.googlecode.dex2jar.ir.ts.array.FillArrayTransformer.makeSureAllElementAreAssigned(FillArrayTransformer.java:505)\n\tat com.googlecode.dex2jar.ir.ts.array.FillArrayTransformer.transformReportChanged(FillArrayTransformer.java:123)\n\tat com.googlecode.dex2jar.ir.ts.StatedTransformer.transform(StatedTransformer.java:10)\n\tat com.googlecode.d2j.dex.Dex2jar$2.optimize(Dex2jar.java:149)\n\tat com.googlecode.d2j.dex.Dex2Asm.convertCode(Dex2Asm.java:414)\n\tat com.googlecode.d2j.dex.ExDex2Asm.convertCode(ExDex2Asm.java:42)\n\tat com.googlecode.d2j.dex.Dex2jar$2.convertCode(Dex2jar.java:128)\n\tat com.googlecode.d2j.dex.Dex2Asm.convertMethod(Dex2Asm.java:509)\n\tat com.googlecode.d2j.dex.Dex2Asm.convertClass(Dex2Asm.java:406)\n\tat com.googlecode.d2j.dex.Dex2Asm.convertDex(Dex2Asm.java:422)\n\tat com.googlecode.d2j.dex.Dex2jar.doTranslate(Dex2jar.java:172)\n\tat com.googlecode.d2j.dex.Dex2jar.to(Dex2jar.java:272)\n\tat com.googlecode.dex2jar.tools.Dex2jarCmd.doCommandLine(Dex2jarCmd.java:108)\n\tat com.googlecode.dex2jar.tools.BaseCmd.doMain(BaseCmd.java:288)\n\tat com.googlecode.dex2jar.tools.Dex2jarCmd.main(Dex2jarCmd.java:32)\n");
  }
}
