package kkkkkk;

import android.content.Context;
import android.os.Handler;
import android.os.Looper;
import java.io.Serializable;
import java.lang.reflect.InvocationHandler;
import java.lang.reflect.Method;
import javax.annotation.Nonnull;
import javax.annotation.Nullable;

public class affaff
{
  public static int b042204220422ТТ0422ТТТ0422 = 28;
  @Nullable
  private static String b04220422ТТТ0422ТТТ0422;
  public static int b0422Т0422ТТ0422ТТТ0422 = 2;
  @Nullable
  public static final affaff.afafff b0422ТТТТ0422ТТТ0422;
  public static int bТ04220422ТТ0422ТТТ0422 = 0;
  private static final String bТ0422ТТТ0422ТТТ0422;
  public static int bТТ0422ТТ0422ТТТ0422 = 1;
  
  static
  {
    throw new Runtime("d2j fail translate: java.lang.IndexOutOfBoundsException: fromIndex < 0: -1\n\tat java.util.BitSet.nextSetBit(BitSet.java:712)\n\tat com.googlecode.dex2jar.ir.ts.array.FillArrayTransformer.makeSureAllElementAreAssigned(FillArrayTransformer.java:505)\n\tat com.googlecode.dex2jar.ir.ts.array.FillArrayTransformer.transformReportChanged(FillArrayTransformer.java:123)\n\tat com.googlecode.dex2jar.ir.ts.StatedTransformer.transform(StatedTransformer.java:10)\n\tat com.googlecode.d2j.dex.Dex2jar$2.optimize(Dex2jar.java:149)\n\tat com.googlecode.d2j.dex.Dex2Asm.convertCode(Dex2Asm.java:414)\n\tat com.googlecode.d2j.dex.ExDex2Asm.convertCode(ExDex2Asm.java:42)\n\tat com.googlecode.d2j.dex.Dex2jar$2.convertCode(Dex2jar.java:128)\n\tat com.googlecode.d2j.dex.Dex2Asm.convertMethod(Dex2Asm.java:509)\n\tat com.googlecode.d2j.dex.Dex2Asm.convertClass(Dex2Asm.java:406)\n\tat com.googlecode.d2j.dex.Dex2Asm.convertDex(Dex2Asm.java:422)\n\tat com.googlecode.d2j.dex.Dex2jar.doTranslate(Dex2jar.java:172)\n\tat com.googlecode.d2j.dex.Dex2jar.to(Dex2jar.java:272)\n\tat com.googlecode.dex2jar.tools.Dex2jarCmd.doCommandLine(Dex2jarCmd.java:108)\n\tat com.googlecode.dex2jar.tools.BaseCmd.doMain(BaseCmd.java:288)\n\tat com.googlecode.dex2jar.tools.Dex2jarCmd.main(Dex2jarCmd.java:32)\n");
  }
  
  public affaff() {}
  
  @Nullable
  public static String b043A043A043A043Aк043A043A043Aк043A(Context paramContext)
  {
    Object localObject2 = null;
    if (b04220422ТТТ0422ТТТ0422 == null)
    {
      switch (1)
      {
      case 0: 
      default: 
        for (;;)
        {
          switch (0)
          {
          }
        }
      }
      if (b043Aк043Aк043A043A043A043Aк043A(paramContext))
      {
        Object localObject4 = faaaff.b043Aк043Aк043Aк043A043Aк043A(faaaff.afaaff.while);
        if (localObject4 == null) {
          localObject1 = localObject2;
        }
        Object localObject3;
        do
        {
          do
          {
            do
            {
              return localObject1;
              localObject3 = faaaff.b043Aк043Aк043Aк043A043Aк043A(faaaff.afaaff.short);
              localObject1 = localObject2;
            } while (localObject3 == null);
            localObject3 = faaaff.bккк043A043Aк043A043Aк043A((Class)localObject3, gguuuu.bк043Aккк043Aкк043A043A(".+9\r'", '', '\033', '\002'), new Class[0]);
            localObject1 = localObject2;
          } while (localObject3 == null);
          localObject1 = gguuuu.bккккк043Aкк043A043A("RQa/SfVdg]h_e_B^Djcm", '÷', '\001');
          i = bк043Aк043Aк043A043A043Aк043A();
          switch (i * (bТТ0422ТТ0422ТТТ0422 + i) % b0422Т0422ТТ0422ТТТ0422)
          {
          default: 
            b042204220422ТТ0422ТТТ0422 = 44;
            bТ04220422ТТ0422ТТТ0422 = 61;
          }
          localObject4 = faaaff.bккк043A043Aк043A043Aк043A((Class)localObject4, (String)localObject1, new Class[] { Context.class });
          localObject1 = localObject2;
        } while (localObject4 == null);
        paramContext = faaaff.bк043A043A043A043Aк043A043Aк043A(null, (Method)localObject4, new Object[] { paramContext });
        if (paramContext != null)
        {
          paramContext = faaaff.bк043A043A043A043Aк043A043Aк043A(paramContext, (Method)localObject3, new Object[0]);
          if (paramContext != null)
          {
            paramContext = String.valueOf(paramContext);
            b04220422ТТТ0422ТТТ0422 = paramContext;
            return paramContext;
          }
        }
      }
    }
    paramContext = b04220422ТТТ0422ТТТ0422;
    int i = b042204220422ТТ0422ТТТ0422;
    Object localObject1 = paramContext;
    switch (i * (bТТ0422ТТ0422ТТТ0422 + i) % b0422Т0422ТТ0422ТТТ0422)
    {
    }
    b042204220422ТТ0422ТТТ0422 = 57;
    bТ04220422ТТ0422ТТТ0422 = 20;
    return paramContext;
  }
  
  public static int b043A043Aк043Aк043A043A043Aк043A()
  {
    return 1;
  }
  
  /* Error */
  public static void b043A043Aкк043A043A043A043Aк043A(Context paramContext, byte[] paramArrayOfByte, vvddvv.ddvdvv paramDdvdvv)
  {
    // Byte code:
    //   0: getstatic 119	kkkkkk/affaff:b0422ТТТТ0422ТТТ0422	Lkkkkkk/affaff$afafff;
    //   3: astore 8
    //   5: aload_0
    //   6: aconst_null
    //   7: aconst_null
    //   8: invokestatic 123	kkkkkk/affaff:bкккк043A043A043A043Aк043A	(Landroid/content/Context;Lkkkkkk/ffaaaa;Landroid/os/Handler;)Ljava/lang/Object;
    //   11: astore_0
    //   12: aload 8
    //   14: ifnull +179 -> 193
    //   17: aload_0
    //   18: ifnull +175 -> 193
    //   21: aload 8
    //   23: getfield 127	kkkkkk/affaff$afafff:b0422Т0422ТТТ0422ТТ0422	Ljava/lang/reflect/Field;
    //   26: invokestatic 131	kkkkkk/faaaff:bк043Aк043A043Aк043A043Aк043A	(Ljava/lang/reflect/Field;)Ljava/lang/Object;
    //   29: aload 8
    //   31: getfield 135	kkkkkk/affaff$afafff:bТ0422Т04220422Т0422ТТ0422	Ljava/lang/reflect/Method;
    //   34: iconst_2
    //   35: anewarray 4	java/lang/Object
    //   38: dup
    //   39: iconst_0
    //   40: aload_0
    //   41: aastore
    //   42: dup
    //   43: iconst_1
    //   44: aload_1
    //   45: aastore
    //   46: invokestatic 105	kkkkkk/faaaff:bк043A043A043A043Aк043A043Aк043A	(Ljava/lang/Object;Ljava/lang/reflect/Method;[Ljava/lang/Object;)Ljava/lang/Object;
    //   49: astore_0
    //   50: aload 8
    //   52: getfield 139	kkkkkk/affaff$afafff:bТ042204220422ТТ0422ТТ0422	Ljava/lang/Class;
    //   55: invokevirtual 143	java/lang/Class:getClassLoader	()Ljava/lang/ClassLoader;
    //   58: astore_1
    //   59: getstatic 97	kkkkkk/affaff:b042204220422ТТ0422ТТТ0422	I
    //   62: istore_3
    //   63: getstatic 93	kkkkkk/affaff:bТТ0422ТТ0422ТТТ0422	I
    //   66: istore 4
    //   68: getstatic 97	kkkkkk/affaff:b042204220422ТТ0422ТТТ0422	I
    //   71: istore 5
    //   73: getstatic 95	kkkkkk/affaff:b0422Т0422ТТ0422ТТТ0422	I
    //   76: istore 6
    //   78: getstatic 97	kkkkkk/affaff:b042204220422ТТ0422ТТТ0422	I
    //   81: istore 7
    //   83: iload 7
    //   85: getstatic 93	kkkkkk/affaff:bТТ0422ТТ0422ТТТ0422	I
    //   88: iload 7
    //   90: iadd
    //   91: imul
    //   92: getstatic 95	kkkkkk/affaff:b0422Т0422ТТ0422ТТТ0422	I
    //   95: irem
    //   96: tableswitch	default:+20->116, 0:+31->127
    //   116: bipush 83
    //   118: putstatic 97	kkkkkk/affaff:b042204220422ТТ0422ТТТ0422	I
    //   121: invokestatic 91	kkkkkk/affaff:bк043Aк043Aк043A043A043Aк043A	()I
    //   124: putstatic 99	kkkkkk/affaff:bТ04220422ТТ0422ТТТ0422	I
    //   127: iload_3
    //   128: iload 4
    //   130: iadd
    //   131: iload 5
    //   133: imul
    //   134: iload 6
    //   136: irem
    //   137: getstatic 99	kkkkkk/affaff:bТ04220422ТТ0422ТТТ0422	I
    //   140: if_icmpeq +13 -> 153
    //   143: bipush 44
    //   145: putstatic 97	kkkkkk/affaff:b042204220422ТТ0422ТТТ0422	I
    //   148: bipush 13
    //   150: putstatic 99	kkkkkk/affaff:bТ04220422ТТ0422ТТТ0422	I
    //   153: aload 8
    //   155: getfield 139	kkkkkk/affaff$afafff:bТ042204220422ТТ0422ТТ0422	Ljava/lang/Class;
    //   158: astore 9
    //   160: aload_1
    //   161: iconst_1
    //   162: anewarray 77	java/lang/Class
    //   165: dup
    //   166: iconst_0
    //   167: aload 9
    //   169: aastore
    //   170: aload_2
    //   171: invokestatic 147	kkkkkk/faaaff:b043Aкк043A043Aк043A043Aк043A	(Ljava/lang/ClassLoader;[Ljava/lang/Class;Ljava/lang/reflect/InvocationHandler;)Ljava/lang/Object;
    //   174: astore_1
    //   175: aload_0
    //   176: aload 8
    //   178: getfield 150	kkkkkk/affaff$afafff:b0422ТТТ0422Т0422ТТ0422	Ljava/lang/reflect/Method;
    //   181: iconst_1
    //   182: anewarray 4	java/lang/Object
    //   185: dup
    //   186: iconst_0
    //   187: aload_1
    //   188: aastore
    //   189: invokestatic 105	kkkkkk/faaaff:bк043A043A043A043Aк043A043Aк043A	(Ljava/lang/Object;Ljava/lang/reflect/Method;[Ljava/lang/Object;)Ljava/lang/Object;
    //   192: pop
    //   193: return
    //   194: astore_0
    //   195: aload_0
    //   196: athrow
    //   197: astore_0
    //   198: aload_0
    //   199: athrow
    //   200: astore_0
    //   201: aload_0
    //   202: athrow
    // Local variable table:
    //   start	length	slot	name	signature
    //   0	203	0	paramContext	Context
    //   0	203	1	paramArrayOfByte	byte[]
    //   0	203	2	paramDdvdvv	vvddvv.ddvdvv
    //   62	69	3	i	int
    //   66	65	4	j	int
    //   71	63	5	k	int
    //   76	61	6	m	int
    //   81	11	7	n	int
    //   3	174	8	localAfafff	affaff.afafff
    //   158	10	9	localClass	Class
    // Exception table:
    //   from	to	target	type
    //   0	12	194	java/lang/Exception
    //   21	59	194	java/lang/Exception
    //   160	175	194	java/lang/Exception
    //   59	78	197	java/lang/Exception
    //   127	153	197	java/lang/Exception
    //   195	197	197	java/lang/Exception
    //   201	203	197	java/lang/Exception
    //   153	160	200	java/lang/Exception
    //   175	193	200	java/lang/Exception
  }
  
  @Nullable
  public static aaafff b043Aк043A043Aк043A043A043Aк043A(Context paramContext, long paramLong1, long paramLong2, int paramInt, ffaaaa paramFfaaaa, ffaaaa.fafaaa paramFafaaa1, ffaaaa.fafaaa paramFafaaa2, Handler paramHandler)
  {
    for (;;)
    {
      try
      {
        localAfafff = b0422ТТТТ0422ТТТ0422;
        if (localAfafff != null)
        {
          paramFfaaaa = bкккк043A043A043A043Aк043A(paramContext, paramFfaaaa, paramHandler);
          if (paramFfaaaa == null) {
            return null;
          }
          paramHandler = b0422ТТТТ0422ТТТ0422;
          paramContext = Integer.valueOf(102);
          if (paramHandler != null) {
            switch (paramInt)
            {
            case 3: 
              paramContext = paramHandler.b0422Т0422Т04220422ТТТ0422;
            }
          }
        }
      }
      catch (Exception paramContext)
      {
        affaff.afafff localAfafff;
        int i;
        int j;
        int k;
        int m;
        throw paramContext;
      }
      try
      {
        paramInt = bк043Aк043Aк043A043A043Aк043A();
        i = bТТ0422ТТ0422ТТТ0422;
        j = bк043Aк043Aк043A043A043Aк043A();
        k = b0422Т0422ТТ0422ТТТ0422;
        m = bТ04220422ТТ0422ТТТ0422;
        if ((paramInt + i) * j % k != m)
        {
          if ((b042204220422ТТ0422ТТТ0422 + bТТ0422ТТ0422ТТТ0422) * b042204220422ТТ0422ТТТ0422 % bкк043A043Aк043A043A043Aк043A() != bТ04220422ТТ0422ТТТ0422)
          {
            b042204220422ТТ0422ТТТ0422 = 77;
            bТ04220422ТТ0422ТТТ0422 = 74;
          }
          bТ04220422ТТ0422ТТТ0422 = bк043Aк043Aк043A043A043Aк043A();
        }
        paramContext = bкк043Aк043A043A043A043Aк043A(paramLong1, paramLong2, ((Integer)paramContext).intValue());
        paramHandler = bкк043Aк043A043A043A043Aк043A(paramLong1, paramLong2, ((Integer)localAfafff.b0422Т04220422ТТ0422ТТ0422).intValue());
        if ((paramContext == null) || (paramHandler == null)) {
          return null;
        }
        try
        {
          paramContext = paramHandler.bТТТ04220422Т0422ТТ0422;
        }
        catch (Exception paramContext)
        {
          try
          {
            throw paramContext;
          }
          catch (Exception paramContext)
          {
            throw paramContext;
          }
        }
        paramContext = paramHandler.b0422Т0422Т04220422ТТТ0422;
        continue;
        paramContext = new aaafff(paramFfaaaa, paramContext, paramHandler, faaaff.b043Aкк043A043Aк043A043Aк043A(localAfafff.b04220422Т04220422Т0422ТТ0422.getClassLoader(), new Class[] { localAfafff.b04220422Т04220422Т0422ТТ0422 }, paramFafaaa1), faaaff.b043Aкк043A043Aк043A043Aк043A(localAfafff.b04220422Т04220422Т0422ТТ0422.getClassLoader(), new Class[] { localAfafff.b04220422Т04220422Т0422ТТ0422 }, paramFafaaa2));
        return paramContext;
      }
      catch (Exception paramContext)
      {
        throw paramContext;
      }
      return null;
    }
  }
  
  /* Error */
  private static boolean b043Aк043Aк043A043A043A043Aк043A(Context paramContext)
  {
    // Byte code:
    //   0: getstatic 119	kkkkkk/affaff:b0422ТТТТ0422ТТТ0422	Lkkkkkk/affaff$afafff;
    //   3: astore 5
    //   5: aload 5
    //   7: ifnonnull +5 -> 12
    //   10: iconst_0
    //   11: ireturn
    //   12: aconst_null
    //   13: aload 5
    //   15: getfield 186	kkkkkk/affaff$afafff:bТ04220422Т0422Т0422ТТ0422	Ljava/lang/reflect/Method;
    //   18: iconst_0
    //   19: anewarray 4	java/lang/Object
    //   22: invokestatic 105	kkkkkk/faaaff:bк043A043A043A043Aк043A043Aк043A	(Ljava/lang/Object;Ljava/lang/reflect/Method;[Ljava/lang/Object;)Ljava/lang/Object;
    //   25: astore 6
    //   27: aload 6
    //   29: ifnull +99 -> 128
    //   32: aload 6
    //   34: aload 5
    //   36: getfield 189	kkkkkk/affaff$afafff:bТ0422ТТТ04220422ТТ0422	Ljava/lang/reflect/Method;
    //   39: iconst_1
    //   40: anewarray 4	java/lang/Object
    //   43: dup
    //   44: iconst_0
    //   45: aload_0
    //   46: aastore
    //   47: invokestatic 105	kkkkkk/faaaff:bк043A043A043A043Aк043A043Aк043A	(Ljava/lang/Object;Ljava/lang/reflect/Method;[Ljava/lang/Object;)Ljava/lang/Object;
    //   50: astore 6
    //   52: aload 6
    //   54: ifnull +74 -> 128
    //   57: aload 6
    //   59: iconst_0
    //   60: invokestatic 157	java/lang/Integer:valueOf	(I)Ljava/lang/Integer;
    //   63: invokevirtual 193	java/lang/Object:equals	(Ljava/lang/Object;)Z
    //   66: istore 4
    //   68: iload 4
    //   70: ifeq +58 -> 128
    //   73: getstatic 97	kkkkkk/affaff:b042204220422ТТ0422ТТТ0422	I
    //   76: istore_1
    //   77: getstatic 93	kkkkkk/affaff:bТТ0422ТТ0422ТТТ0422	I
    //   80: istore_2
    //   81: getstatic 95	kkkkkk/affaff:b0422Т0422ТТ0422ТТТ0422	I
    //   84: istore_3
    //   85: iload_1
    //   86: iload_2
    //   87: iload_1
    //   88: iadd
    //   89: imul
    //   90: iload_3
    //   91: irem
    //   92: tableswitch	default:+20->112, 0:+121->213
    //   112: bipush 80
    //   114: putstatic 97	kkkkkk/affaff:b042204220422ТТ0422ТТТ0422	I
    //   117: invokestatic 91	kkkkkk/affaff:bк043Aк043Aк043A043A043Aк043A	()I
    //   120: putstatic 99	kkkkkk/affaff:bТ04220422ТТ0422ТТТ0422	I
    //   123: iconst_1
    //   124: ireturn
    //   125: astore_0
    //   126: aload_0
    //   127: athrow
    //   128: getstatic 97	kkkkkk/affaff:b042204220422ТТ0422ТТТ0422	I
    //   131: getstatic 93	kkkkkk/affaff:bТТ0422ТТ0422ТТТ0422	I
    //   134: iadd
    //   135: getstatic 97	kkkkkk/affaff:b042204220422ТТ0422ТТТ0422	I
    //   138: imul
    //   139: getstatic 95	kkkkkk/affaff:b0422Т0422ТТ0422ТТТ0422	I
    //   142: irem
    //   143: getstatic 99	kkkkkk/affaff:bТ04220422ТТ0422ТТТ0422	I
    //   146: if_icmpeq +15 -> 161
    //   149: invokestatic 91	kkkkkk/affaff:bк043Aк043Aк043A043A043Aк043A	()I
    //   152: putstatic 97	kkkkkk/affaff:b042204220422ТТ0422ТТТ0422	I
    //   155: invokestatic 91	kkkkkk/affaff:bк043Aк043Aк043A043A043Aк043A	()I
    //   158: putstatic 99	kkkkkk/affaff:bТ04220422ТТ0422ТТТ0422	I
    //   161: aload 5
    //   163: getfield 189	kkkkkk/affaff$afafff:bТ0422ТТТ04220422ТТ0422	Ljava/lang/reflect/Method;
    //   166: astore 5
    //   168: aconst_null
    //   169: aload 5
    //   171: iconst_1
    //   172: anewarray 4	java/lang/Object
    //   175: dup
    //   176: iconst_0
    //   177: aload_0
    //   178: aastore
    //   179: invokestatic 105	kkkkkk/faaaff:bк043A043A043A043Aк043A043Aк043A	(Ljava/lang/Object;Ljava/lang/reflect/Method;[Ljava/lang/Object;)Ljava/lang/Object;
    //   182: astore_0
    //   183: aload_0
    //   184: ifnull +18 -> 202
    //   187: aload_0
    //   188: iconst_0
    //   189: invokestatic 157	java/lang/Integer:valueOf	(I)Ljava/lang/Integer;
    //   192: invokevirtual 193	java/lang/Object:equals	(Ljava/lang/Object;)Z
    //   195: istore 4
    //   197: iload 4
    //   199: ifne +14 -> 213
    //   202: iconst_0
    //   203: ireturn
    //   204: astore_0
    //   205: aload_0
    //   206: athrow
    //   207: astore_0
    //   208: aload_0
    //   209: athrow
    //   210: astore_0
    //   211: aload_0
    //   212: athrow
    //   213: iconst_1
    //   214: ireturn
    // Local variable table:
    //   start	length	slot	name	signature
    //   0	215	0	paramContext	Context
    //   76	14	1	i	int
    //   80	9	2	j	int
    //   84	8	3	k	int
    //   66	132	4	bool	boolean
    //   3	167	5	localObject1	Object
    //   25	33	6	localObject2	Object
    // Exception table:
    //   from	to	target	type
    //   112	123	125	java/lang/Exception
    //   205	207	125	java/lang/Exception
    //   208	210	125	java/lang/Exception
    //   0	5	204	java/lang/Exception
    //   12	27	204	java/lang/Exception
    //   32	52	204	java/lang/Exception
    //   168	183	204	java/lang/Exception
    //   57	68	207	java/lang/Exception
    //   161	168	207	java/lang/Exception
    //   187	197	207	java/lang/Exception
    //   73	85	210	java/lang/Exception
  }
  
  @Nullable
  public static Serializable b043Aккк043A043A043A043Aк043A(@Nonnull InvocationHandler paramInvocationHandler, @Nonnull Method paramMethod, @Nullable Object[] paramArrayOfObject)
  {
    throw new Runtime("d2j fail translate: java.lang.IndexOutOfBoundsException: fromIndex < 0: -1\n\tat java.util.BitSet.nextSetBit(BitSet.java:712)\n\tat com.googlecode.dex2jar.ir.ts.array.FillArrayTransformer.makeSureAllElementAreAssigned(FillArrayTransformer.java:505)\n\tat com.googlecode.dex2jar.ir.ts.array.FillArrayTransformer.transformReportChanged(FillArrayTransformer.java:123)\n\tat com.googlecode.dex2jar.ir.ts.StatedTransformer.transform(StatedTransformer.java:10)\n\tat com.googlecode.d2j.dex.Dex2jar$2.optimize(Dex2jar.java:149)\n\tat com.googlecode.d2j.dex.Dex2Asm.convertCode(Dex2Asm.java:414)\n\tat com.googlecode.d2j.dex.ExDex2Asm.convertCode(ExDex2Asm.java:42)\n\tat com.googlecode.d2j.dex.Dex2jar$2.convertCode(Dex2jar.java:128)\n\tat com.googlecode.d2j.dex.Dex2Asm.convertMethod(Dex2Asm.java:509)\n\tat com.googlecode.d2j.dex.Dex2Asm.convertClass(Dex2Asm.java:406)\n\tat com.googlecode.d2j.dex.Dex2Asm.convertDex(Dex2Asm.java:422)\n\tat com.googlecode.d2j.dex.Dex2jar.doTranslate(Dex2jar.java:172)\n\tat com.googlecode.d2j.dex.Dex2jar.to(Dex2jar.java:272)\n\tat com.googlecode.dex2jar.tools.Dex2jarCmd.doCommandLine(Dex2jarCmd.java:108)\n\tat com.googlecode.dex2jar.tools.BaseCmd.doMain(BaseCmd.java:288)\n\tat com.googlecode.dex2jar.tools.Dex2jarCmd.main(Dex2jarCmd.java:32)\n");
  }
  
  public static boolean bк043A043A043Aк043A043A043Aк043A(Object paramObject)
  {
    try
    {
      affaff.afafff localAfafff = b0422ТТТТ0422ТТТ0422;
      if (localAfafff == null)
      {
        return false;
        if ((!(paramObject instanceof Boolean)) || (!((Boolean)paramObject).booleanValue())) {
          break label203;
        }
        int i = b042204220422ТТ0422ТТТ0422;
        int j = bТТ0422ТТ0422ТТТ0422;
        int k = b042204220422ТТ0422ТТТ0422;
        int m = b0422Т0422ТТ0422ТТТ0422;
        int n = bТ04220422ТТ0422ТТТ0422;
        if ((i + j) * k % m == n) {
          break label210;
        }
        try
        {
          b042204220422ТТ0422ТТТ0422 = bк043Aк043Aк043A043A043Aк043A();
          bТ04220422ТТ0422ТТТ0422 = 59;
          return true;
        }
        catch (Exception paramObject)
        {
          throw paramObject;
        }
      }
      Method localMethod = localAfafff.b04220422ТТ0422Т0422ТТ0422;
      if ((b042204220422ТТ0422ТТТ0422 + bТТ0422ТТ0422ТТТ0422) * b042204220422ТТ0422ТТТ0422 % b0422Т0422ТТ0422ТТТ0422 != bТ04220422ТТ0422ТТТ0422)
      {
        b042204220422ТТ0422ТТТ0422 = 54;
        bТ04220422ТТ0422ТТТ0422 = 28;
      }
      paramObject = faaaff.bк043A043A043A043Aк043A043Aк043A(paramObject, localMethod, new Object[0]);
      if (paramObject != null)
      {
        paramObject = faaaff.bк043A043A043A043Aк043A043Aк043A(paramObject, localAfafff.bТ0422042204220422Т0422ТТ0422, new Object[0]);
        if (paramObject != null)
        {
          switch (0)
          {
          }
          for (;;)
          {
            switch (0)
            {
            }
          }
        }
        label203:
        return false;
      }
      return false;
    }
    catch (Exception paramObject)
    {
      throw paramObject;
    }
    label210:
    return true;
  }
  
  public static int bк043Aк043Aк043A043A043Aк043A()
  {
    return 53;
  }
  
  public static int bкк043A043Aк043A043A043Aк043A()
  {
    return 2;
  }
  
  /* Error */
  private static Object bкк043Aк043A043A043A043Aк043A(long paramLong1, long paramLong2, int paramInt)
  {
    // Byte code:
    //   0: aconst_null
    //   1: astore 6
    //   3: getstatic 119	kkkkkk/affaff:b0422ТТТТ0422ТТТ0422	Lkkkkkk/affaff$afafff;
    //   6: astore 7
    //   8: aload 7
    //   10: ifnull +225 -> 235
    //   13: aload 7
    //   15: getfield 219	kkkkkk/affaff$afafff:bТТТ042204220422ТТТ0422	Ljava/lang/Class;
    //   18: aconst_null
    //   19: aconst_null
    //   20: invokestatic 223	kkkkkk/faaaff:b043Aк043A043A043Aк043A043Aк043A	(Ljava/lang/Class;[Ljava/lang/Class;[Ljava/lang/Object;)Ljava/lang/Object;
    //   23: astore 5
    //   25: getstatic 97	kkkkkk/affaff:b042204220422ТТ0422ТТТ0422	I
    //   28: invokestatic 214	kkkkkk/affaff:b043A043Aк043Aк043A043A043Aк043A	()I
    //   31: iadd
    //   32: getstatic 97	kkkkkk/affaff:b042204220422ТТ0422ТТТ0422	I
    //   35: imul
    //   36: getstatic 95	kkkkkk/affaff:b0422Т0422ТТ0422ТТТ0422	I
    //   39: irem
    //   40: getstatic 99	kkkkkk/affaff:bТ04220422ТТ0422ТТТ0422	I
    //   43: if_icmpeq +13 -> 56
    //   46: bipush 79
    //   48: putstatic 97	kkkkkk/affaff:b042204220422ТТ0422ТТТ0422	I
    //   51: bipush 48
    //   53: putstatic 99	kkkkkk/affaff:bТ04220422ТТ0422ТТТ0422	I
    //   56: aload 5
    //   58: aload 7
    //   60: getfield 226	kkkkkk/affaff$afafff:bТТ0422ТТТ0422ТТ0422	Ljava/lang/reflect/Method;
    //   63: iconst_1
    //   64: anewarray 4	java/lang/Object
    //   67: dup
    //   68: iconst_0
    //   69: lload_0
    //   70: invokestatic 231	java/lang/Long:valueOf	(J)Ljava/lang/Long;
    //   73: aastore
    //   74: invokestatic 105	kkkkkk/faaaff:bк043A043A043A043Aк043A043Aк043A	(Ljava/lang/Object;Ljava/lang/reflect/Method;[Ljava/lang/Object;)Ljava/lang/Object;
    //   77: pop
    //   78: aload 5
    //   80: aload 7
    //   82: getfield 234	kkkkkk/affaff$afafff:b042204220422Т04220422ТТТ0422	Ljava/lang/reflect/Method;
    //   85: iconst_1
    //   86: anewarray 4	java/lang/Object
    //   89: dup
    //   90: iconst_0
    //   91: lload_2
    //   92: invokestatic 231	java/lang/Long:valueOf	(J)Ljava/lang/Long;
    //   95: aastore
    //   96: invokestatic 105	kkkkkk/faaaff:bк043A043A043A043Aк043A043Aк043A	(Ljava/lang/Object;Ljava/lang/reflect/Method;[Ljava/lang/Object;)Ljava/lang/Object;
    //   99: pop
    //   100: aload 7
    //   102: getfield 237	kkkkkk/affaff$afafff:bТ0422ТТ0422Т0422ТТ0422	Ljava/lang/reflect/Method;
    //   105: astore 6
    //   107: iconst_0
    //   108: tableswitch	default:+24->132, 0:+51->159, 1:+-1->107
    //   132: iconst_1
    //   133: tableswitch	default:+23->156, 0:+-26->107, 1:+26->159
    //   156: goto -24 -> 132
    //   159: aload 5
    //   161: aload 6
    //   163: iconst_1
    //   164: anewarray 4	java/lang/Object
    //   167: dup
    //   168: iconst_0
    //   169: iload 4
    //   171: invokestatic 157	java/lang/Integer:valueOf	(I)Ljava/lang/Integer;
    //   174: aastore
    //   175: invokestatic 105	kkkkkk/faaaff:bк043A043A043A043Aк043A043Aк043A	(Ljava/lang/Object;Ljava/lang/reflect/Method;[Ljava/lang/Object;)Ljava/lang/Object;
    //   178: pop
    //   179: getstatic 97	kkkkkk/affaff:b042204220422ТТ0422ТТТ0422	I
    //   182: istore 4
    //   184: aload 5
    //   186: astore 6
    //   188: iload 4
    //   190: getstatic 93	kkkkkk/affaff:bТТ0422ТТ0422ТТТ0422	I
    //   193: iload 4
    //   195: iadd
    //   196: imul
    //   197: getstatic 95	kkkkkk/affaff:b0422Т0422ТТ0422ТТТ0422	I
    //   200: irem
    //   201: tableswitch	default:+19->220, 0:+34->235
    //   220: bipush 11
    //   222: putstatic 97	kkkkkk/affaff:b042204220422ТТ0422ТТТ0422	I
    //   225: invokestatic 91	kkkkkk/affaff:bк043Aк043Aк043A043A043Aк043A	()I
    //   228: putstatic 99	kkkkkk/affaff:bТ04220422ТТ0422ТТТ0422	I
    //   231: aload 5
    //   233: astore 6
    //   235: aload 6
    //   237: areturn
    //   238: astore 5
    //   240: aload 5
    //   242: athrow
    //   243: astore 5
    //   245: aload 5
    //   247: athrow
    // Local variable table:
    //   start	length	slot	name	signature
    //   0	248	0	paramLong1	long
    //   0	248	2	paramLong2	long
    //   0	248	4	paramInt	int
    //   23	209	5	localObject1	Object
    //   238	3	5	localException1	Exception
    //   243	3	5	localException2	Exception
    //   1	235	6	localObject2	Object
    //   6	95	7	localAfafff	affaff.afafff
    // Exception table:
    //   from	to	target	type
    //   3	8	238	java/lang/Exception
    //   13	25	238	java/lang/Exception
    //   56	78	238	java/lang/Exception
    //   159	179	238	java/lang/Exception
    //   78	107	243	java/lang/Exception
  }
  
  /* Error */
  private static Object bкккк043A043A043A043Aк043A(Context paramContext, @Nullable ffaaaa paramFfaaaa, @Nullable Handler paramHandler)
  {
    // Byte code:
    //   0: getstatic 119	kkkkkk/affaff:b0422ТТТТ0422ТТТ0422	Lkkkkkk/affaff$afafff;
    //   3: astore 4
    //   5: aload 4
    //   7: ifnull +55 -> 62
    //   10: aload_0
    //   11: invokestatic 52	kkkkkk/affaff:b043Aк043Aк043A043A043A043Aк043A	(Landroid/content/Context;)Z
    //   14: ifeq +48 -> 62
    //   17: new 11	kkkkkk/affaff$faafff
    //   20: dup
    //   21: aload_1
    //   22: invokespecial 240	kkkkkk/affaff$faafff:<init>	(Lkkkkkk/ffaaaa;)V
    //   25: astore_1
    //   26: aload 4
    //   28: getfield 243	kkkkkk/affaff$afafff:b0422ТТТТТ0422ТТ0422	Ljava/lang/Class;
    //   31: astore 5
    //   33: aload 5
    //   35: iconst_1
    //   36: anewarray 77	java/lang/Class
    //   39: dup
    //   40: iconst_0
    //   41: ldc 101
    //   43: aastore
    //   44: iconst_1
    //   45: anewarray 4	java/lang/Object
    //   48: dup
    //   49: iconst_0
    //   50: aload_0
    //   51: aastore
    //   52: invokestatic 223	kkkkkk/faaaff:b043Aк043A043A043Aк043A043Aк043A	(Ljava/lang/Class;[Ljava/lang/Class;[Ljava/lang/Object;)Ljava/lang/Object;
    //   55: astore_0
    //   56: aload_0
    //   57: ifnonnull +228 -> 285
    //   60: aconst_null
    //   61: areturn
    //   62: getstatic 97	kkkkkk/affaff:b042204220422ТТ0422ТТТ0422	I
    //   65: istore_3
    //   66: iload_3
    //   67: getstatic 93	kkkkkk/affaff:bТТ0422ТТ0422ТТТ0422	I
    //   70: iload_3
    //   71: iadd
    //   72: imul
    //   73: getstatic 95	kkkkkk/affaff:b0422Т0422ТТ0422ТТТ0422	I
    //   76: irem
    //   77: tableswitch	default:+19->96, 0:+366->443
    //   96: invokestatic 91	kkkkkk/affaff:bк043Aк043Aк043A043A043Aк043A	()I
    //   99: putstatic 97	kkkkkk/affaff:b042204220422ТТ0422ТТТ0422	I
    //   102: invokestatic 91	kkkkkk/affaff:bк043Aк043Aк043A043A043Aк043A	()I
    //   105: putstatic 99	kkkkkk/affaff:bТ04220422ТТ0422ТТТ0422	I
    //   108: aconst_null
    //   109: areturn
    //   110: aload_0
    //   111: aload 4
    //   113: getfield 246	kkkkkk/affaff$afafff:b0422Т0422Т0422Т0422ТТ0422	Ljava/lang/reflect/Method;
    //   116: iconst_0
    //   117: anewarray 4	java/lang/Object
    //   120: invokestatic 105	kkkkkk/faaaff:bк043A043A043A043Aк043A043Aк043A	(Ljava/lang/Object;Ljava/lang/reflect/Method;[Ljava/lang/Object;)Ljava/lang/Object;
    //   123: astore_0
    //   124: aload_0
    //   125: ifnonnull +70 -> 195
    //   128: aconst_null
    //   129: areturn
    //   130: aload_0
    //   131: aload 4
    //   133: getfield 249	kkkkkk/affaff$afafff:b042204220422Т0422Т0422ТТ0422	Ljava/lang/reflect/Method;
    //   136: iconst_1
    //   137: anewarray 4	java/lang/Object
    //   140: dup
    //   141: iconst_0
    //   142: aload 4
    //   144: getfield 252	kkkkkk/affaff$afafff:b0422Т0422042204220422ТТТ0422	Ljava/lang/reflect/Field;
    //   147: invokestatic 131	kkkkkk/faaaff:bк043Aк043A043Aк043A043Aк043A	(Ljava/lang/reflect/Field;)Ljava/lang/Object;
    //   150: aastore
    //   151: invokestatic 105	kkkkkk/faaaff:bк043A043A043A043Aк043A043Aк043A	(Ljava/lang/Object;Ljava/lang/reflect/Method;[Ljava/lang/Object;)Ljava/lang/Object;
    //   154: astore_1
    //   155: aload_1
    //   156: ifnonnull +5 -> 161
    //   159: aconst_null
    //   160: areturn
    //   161: aload_1
    //   162: astore_0
    //   163: aload_2
    //   164: ifnull -54 -> 110
    //   167: aload 4
    //   169: getfield 255	kkkkkk/affaff$afafff:bТТ0422Т0422Т0422ТТ0422	Ljava/lang/reflect/Method;
    //   172: astore_0
    //   173: aload_1
    //   174: aload_0
    //   175: iconst_1
    //   176: anewarray 4	java/lang/Object
    //   179: dup
    //   180: iconst_0
    //   181: aload_2
    //   182: aastore
    //   183: invokestatic 105	kkkkkk/faaaff:bк043A043A043A043Aк043A043Aк043A	(Ljava/lang/Object;Ljava/lang/reflect/Method;[Ljava/lang/Object;)Ljava/lang/Object;
    //   186: astore_1
    //   187: aload_1
    //   188: astore_0
    //   189: aload_1
    //   190: ifnonnull -80 -> 110
    //   193: aconst_null
    //   194: areturn
    //   195: aload_0
    //   196: aload 4
    //   198: getfield 258	kkkkkk/affaff$afafff:bТТТТТТ0422ТТ0422	Ljava/lang/reflect/Method;
    //   201: iconst_0
    //   202: anewarray 4	java/lang/Object
    //   205: invokestatic 105	kkkkkk/faaaff:bк043A043A043A043Aк043A043Aк043A	(Ljava/lang/Object;Ljava/lang/reflect/Method;[Ljava/lang/Object;)Ljava/lang/Object;
    //   208: pop
    //   209: aload_0
    //   210: areturn
    //   211: astore_0
    //   212: aload_0
    //   213: athrow
    //   214: aload_0
    //   215: aload 6
    //   217: iconst_1
    //   218: anewarray 4	java/lang/Object
    //   221: dup
    //   222: iconst_0
    //   223: aload 5
    //   225: aastore
    //   226: invokestatic 105	kkkkkk/faaaff:bк043A043A043A043Aк043A043Aк043A	(Ljava/lang/Object;Ljava/lang/reflect/Method;[Ljava/lang/Object;)Ljava/lang/Object;
    //   229: astore_0
    //   230: aload_0
    //   231: ifnonnull +5 -> 236
    //   234: aconst_null
    //   235: areturn
    //   236: aload 4
    //   238: getfield 261	kkkkkk/affaff$afafff:bТТ04220422ТТ0422ТТ0422	Ljava/lang/Class;
    //   241: invokevirtual 143	java/lang/Class:getClassLoader	()Ljava/lang/ClassLoader;
    //   244: iconst_1
    //   245: anewarray 77	java/lang/Class
    //   248: dup
    //   249: iconst_0
    //   250: aload 4
    //   252: getfield 261	kkkkkk/affaff$afafff:bТТ04220422ТТ0422ТТ0422	Ljava/lang/Class;
    //   255: aastore
    //   256: aload_1
    //   257: invokestatic 147	kkkkkk/faaaff:b043Aкк043A043Aк043A043Aк043A	(Ljava/lang/ClassLoader;[Ljava/lang/Class;Ljava/lang/reflect/InvocationHandler;)Ljava/lang/Object;
    //   260: astore_1
    //   261: aload_0
    //   262: aload 4
    //   264: getfield 264	kkkkkk/affaff$afafff:b0422042204220422ТТ0422ТТ0422	Ljava/lang/reflect/Method;
    //   267: iconst_1
    //   268: anewarray 4	java/lang/Object
    //   271: dup
    //   272: iconst_0
    //   273: aload_1
    //   274: aastore
    //   275: invokestatic 105	kkkkkk/faaaff:bк043A043A043A043Aк043A043Aк043A	(Ljava/lang/Object;Ljava/lang/reflect/Method;[Ljava/lang/Object;)Ljava/lang/Object;
    //   278: astore_0
    //   279: aload_0
    //   280: ifnonnull +123 -> 403
    //   283: aconst_null
    //   284: areturn
    //   285: aload 4
    //   287: getfield 267	kkkkkk/affaff$afafff:bТ0422Т0422ТТ0422ТТ0422	Ljava/lang/Class;
    //   290: invokevirtual 143	java/lang/Class:getClassLoader	()Ljava/lang/ClassLoader;
    //   293: iconst_1
    //   294: anewarray 77	java/lang/Class
    //   297: dup
    //   298: iconst_0
    //   299: aload 4
    //   301: getfield 267	kkkkkk/affaff$afafff:bТ0422Т0422ТТ0422ТТ0422	Ljava/lang/Class;
    //   304: aastore
    //   305: aload_1
    //   306: invokestatic 147	kkkkkk/faaaff:b043Aкк043A043Aк043A043Aк043A	(Ljava/lang/ClassLoader;[Ljava/lang/Class;Ljava/lang/reflect/InvocationHandler;)Ljava/lang/Object;
    //   309: astore 5
    //   311: aload 4
    //   313: getfield 270	kkkkkk/affaff$afafff:b04220422Т0422ТТ0422ТТ0422	Ljava/lang/reflect/Method;
    //   316: astore 6
    //   318: invokestatic 91	kkkkkk/affaff:bк043Aк043Aк043A043A043Aк043A	()I
    //   321: getstatic 93	kkkkkk/affaff:bТТ0422ТТ0422ТТТ0422	I
    //   324: iadd
    //   325: invokestatic 91	kkkkkk/affaff:bк043Aк043Aк043A043A043Aк043A	()I
    //   328: imul
    //   329: invokestatic 164	kkkkkk/affaff:bкк043A043Aк043A043A043Aк043A	()I
    //   332: irem
    //   333: getstatic 99	kkkkkk/affaff:bТ04220422ТТ0422ТТТ0422	I
    //   336: if_icmpeq -122 -> 214
    //   339: invokestatic 91	kkkkkk/affaff:bк043Aк043Aк043A043A043Aк043A	()I
    //   342: putstatic 97	kkkkkk/affaff:b042204220422ТТ0422ТТТ0422	I
    //   345: invokestatic 91	kkkkkk/affaff:bк043Aк043Aк043A043A043Aк043A	()I
    //   348: putstatic 99	kkkkkk/affaff:bТ04220422ТТ0422ТТТ0422	I
    //   351: iconst_0
    //   352: tableswitch	default:+24->376, 0:+-138->214, 1:+-1->351
    //   376: iconst_0
    //   377: tableswitch	default:+23->400, 0:+-163->214, 1:+-26->351
    //   400: goto -24 -> 376
    //   403: aload 4
    //   405: getfield 249	kkkkkk/affaff$afafff:b042204220422Т0422Т0422ТТ0422	Ljava/lang/reflect/Method;
    //   408: astore_1
    //   409: aload 4
    //   411: getfield 273	kkkkkk/affaff$afafff:bТ04220422042204220422ТТТ0422	Ljava/lang/reflect/Field;
    //   414: astore 5
    //   416: aload_0
    //   417: aload_1
    //   418: iconst_1
    //   419: anewarray 4	java/lang/Object
    //   422: dup
    //   423: iconst_0
    //   424: aload 5
    //   426: invokestatic 131	kkkkkk/faaaff:bк043Aк043A043Aк043A043Aк043A	(Ljava/lang/reflect/Field;)Ljava/lang/Object;
    //   429: aastore
    //   430: invokestatic 105	kkkkkk/faaaff:bк043A043A043A043Aк043A043Aк043A	(Ljava/lang/Object;Ljava/lang/reflect/Method;[Ljava/lang/Object;)Ljava/lang/Object;
    //   433: astore_0
    //   434: aload_0
    //   435: ifnonnull -305 -> 130
    //   438: aconst_null
    //   439: areturn
    //   440: astore_0
    //   441: aload_0
    //   442: athrow
    //   443: aconst_null
    //   444: areturn
    // Local variable table:
    //   start	length	slot	name	signature
    //   0	445	0	paramContext	Context
    //   0	445	1	paramFfaaaa	ffaaaa
    //   0	445	2	paramHandler	Handler
    //   65	8	3	i	int
    //   3	407	4	localAfafff	affaff.afafff
    //   31	394	5	localObject	Object
    //   215	102	6	localMethod	Method
    // Exception table:
    //   from	to	target	type
    //   0	5	211	java/lang/Exception
    //   10	33	211	java/lang/Exception
    //   167	173	211	java/lang/Exception
    //   195	209	211	java/lang/Exception
    //   214	230	211	java/lang/Exception
    //   236	279	211	java/lang/Exception
    //   285	318	211	java/lang/Exception
    //   403	416	211	java/lang/Exception
    //   33	56	440	java/lang/Exception
    //   110	124	440	java/lang/Exception
    //   130	155	440	java/lang/Exception
    //   173	187	440	java/lang/Exception
    //   416	434	440	java/lang/Exception
  }
  
  public static final class aaafff
  {
    public static int b0422042204220422Т0422ТТТ0422 = 67;
    public static int b0422Т04220422Т0422ТТТ0422 = 1;
    public static int bТ042204220422Т0422ТТТ0422 = 2;
    @Nonnull
    public final Object b04220422Т0422Т0422ТТТ0422;
    @Nonnull
    public final Object b0422ТТ0422Т0422ТТТ0422;
    @Nullable
    public final Object bТ0422Т0422Т0422ТТТ0422;
    @Nonnull
    public final Object bТТ04220422Т0422ТТТ0422;
    @Nullable
    public final Object bТТТ0422Т0422ТТТ0422;
    
    public aaafff(@Nonnull Object paramObject1, @Nonnull Object paramObject2, @Nonnull Object paramObject3, @Nullable Object paramObject4, @Nullable Object paramObject5)
    {
      this.bТТ04220422Т0422ТТТ0422 = paramObject1;
      this.b04220422Т0422Т0422ТТТ0422 = paramObject2;
      this.b0422ТТ0422Т0422ТТТ0422 = paramObject3;
      this.bТ0422Т0422Т0422ТТТ0422 = paramObject4;
      this.bТТТ0422Т0422ТТТ0422 = paramObject5;
    }
    
    public static int b043A043A043Aкк043A043A043Aк043A()
    {
      return 16;
    }
    
    public final void bккк043Aк043A043A043Aк043A(Object paramObject1, Object paramObject2, ffaaaa.aafaaa paramAafaaa, Looper paramLooper)
    {
      affaff.afafff localAfafff = affaff.b0422ТТТТ0422ТТТ0422;
      if (localAfafff != null)
      {
        Object localObject1 = faaaff.bк043Aк043A043Aк043A043Aк043A(localAfafff.b04220422Т042204220422ТТТ0422);
        Method localMethod = localAfafff.bТ04220422ТТТ0422ТТ0422;
        Object localObject2 = this.bТТ04220422Т0422ТТТ0422;
        int i = b0422042204220422Т0422ТТТ0422;
        switch (i * (b0422Т04220422Т0422ТТТ0422 + i) % bТ042204220422Т0422ТТТ0422)
        {
        default: 
          b0422042204220422Т0422ТТТ0422 = 61;
          b0422Т04220422Т0422ТТТ0422 = 6;
        }
        paramObject1 = faaaff.bк043A043A043A043Aк043A043Aк043A(localObject1, localMethod, new Object[] { localObject2, paramObject1, paramObject2, paramLooper });
        if (paramObject1 != null)
        {
          paramObject2 = faaaff.b043Aкк043A043Aк043A043Aк043A(localAfafff.bТ042204220422ТТ0422ТТ0422.getClassLoader(), new Class[] { localAfafff.bТ042204220422ТТ0422ТТ0422 }, paramAafaaa);
          faaaff.bк043A043A043A043Aк043A043Aк043A(paramObject1, localAfafff.b0422ТТТ0422Т0422ТТ0422, new Object[] { paramObject2 });
          i = b043A043A043Aкк043A043A043Aк043A();
          switch (i * (b0422Т04220422Т0422ТТТ0422 + i) % bТ042204220422Т0422ТТТ0422)
          {
          default: 
            b0422Т04220422Т0422ТТТ0422 = 60;
          }
        }
      }
    }
  }
  
  public static abstract interface fffaff
  {
    public abstract void b043A043Aк043A043Aк043A043A043Aк();
    
    public abstract void bк043Aк043A043Aк043A043A043Aк();
  }
}
