package kkkkkk;

import android.support.annotation.Nullable;
import android.view.View;
import java.lang.annotation.Annotation;
import java.lang.annotation.Retention;
import java.lang.annotation.RetentionPolicy;

public class ahahah
{
  public static final int b04430443044304430443ууу0443 = 2003;
  public static int b044304430443уу0443уу0443 = 0;
  public static final int b04430443ууу0443уу0443 = 1002;
  public static final int b0443у044304430443ууу0443 = 2004;
  public static int b0443уу0443у0443уу0443 = 2;
  public static final int b0443уууу0443уу0443 = 1001;
  public static final int bу0443044304430443ууу0443 = 2001;
  public static int bу04430443уу0443уу0443 = 33;
  public static final int bу0443ууу0443уу0443 = 1003;
  public static final int bуу044304430443ууу0443 = 2005;
  public static int bууу0443у0443уу0443 = 1;
  public static final int bууууу0443уу0443 = 2002;
  private final int b0443у0443уу0443уу0443;
  @Nullable
  private View bуу0443уу0443уу0443;
  
  @ooiiio("Trivial")
  public ahahah()
  {
    this.b0443у0443уу0443уу0443 = 1001;
  }
  
  @ooiiio("Trivial")
  public ahahah(int paramInt)
  {
    this.b0443у0443уу0443уу0443 = paramInt;
  }
  
  public static int b043F043F043Fп043Fп043Fп043F043F()
  {
    return 2;
  }
  
  public static int b043Fп043Fп043Fп043Fп043F043F()
  {
    return 0;
  }
  
  public static int bп043F043Fп043Fп043Fп043F043F()
  {
    return 1;
  }
  
  public static int bпп043Fп043Fп043Fп043F043F()
  {
    return 86;
  }
  
  /* Error */
  @ooiiio("Trivial")
  public int b043Fпп043F043Fп043Fп043F043F()
  {
    // Byte code:
    //   0: aload_0
    //   1: getfield 45	kkkkkk/ahahah:b0443у0443уу0443уу0443	I
    //   4: istore_1
    //   5: getstatic 58	kkkkkk/ahahah:bу04430443уу0443уу0443	I
    //   8: istore_2
    //   9: getstatic 60	kkkkkk/ahahah:bууу0443у0443уу0443	I
    //   12: istore_3
    //   13: getstatic 58	kkkkkk/ahahah:bу04430443уу0443уу0443	I
    //   16: istore 4
    //   18: invokestatic 62	kkkkkk/ahahah:b043F043F043Fп043Fп043Fп043F043F	()I
    //   21: istore 5
    //   23: getstatic 64	kkkkkk/ahahah:b044304430443уу0443уу0443	I
    //   26: istore 6
    //   28: iload_2
    //   29: iload_3
    //   30: iadd
    //   31: iload 4
    //   33: imul
    //   34: iload 5
    //   36: irem
    //   37: iload 6
    //   39: if_icmpeq +60 -> 99
    //   42: bipush 13
    //   44: putstatic 58	kkkkkk/ahahah:bу04430443уу0443уу0443	I
    //   47: invokestatic 66	kkkkkk/ahahah:bпп043Fп043Fп043Fп043F043F	()I
    //   50: putstatic 64	kkkkkk/ahahah:b044304430443уу0443уу0443	I
    //   53: getstatic 58	kkkkkk/ahahah:bу04430443уу0443уу0443	I
    //   56: istore_2
    //   57: iload_2
    //   58: getstatic 60	kkkkkk/ahahah:bууу0443у0443уу0443	I
    //   61: iload_2
    //   62: iadd
    //   63: imul
    //   64: getstatic 68	kkkkkk/ahahah:b0443уу0443у0443уу0443	I
    //   67: irem
    //   68: tableswitch	default:+20->88, 0:+31->99
    //   88: invokestatic 66	kkkkkk/ahahah:bпп043Fп043Fп043Fп043F043F	()I
    //   91: putstatic 58	kkkkkk/ahahah:bу04430443уу0443уу0443	I
    //   94: bipush 9
    //   96: putstatic 64	kkkkkk/ahahah:b044304430443уу0443уу0443	I
    //   99: iconst_0
    //   100: tableswitch	default:+24->124, 0:+51->151, 1:+-1->99
    //   124: iconst_0
    //   125: tableswitch	default:+23->148, 0:+26->151, 1:+-26->99
    //   148: goto -24 -> 124
    //   151: iload_1
    //   152: ireturn
    //   153: astore 7
    //   155: aload 7
    //   157: athrow
    //   158: astore 7
    //   160: aload 7
    //   162: athrow
    // Local variable table:
    //   start	length	slot	name	signature
    //   0	163	0	this	ahahah
    //   4	148	1	i	int
    //   8	56	2	j	int
    //   12	19	3	k	int
    //   16	18	4	m	int
    //   21	16	5	n	int
    //   26	14	6	i1	int
    //   153	3	7	localException1	Exception
    //   158	3	7	localException2	Exception
    // Exception table:
    //   from	to	target	type
    //   0	28	153	java/lang/Exception
    //   42	53	158	java/lang/Exception
  }
  
  public void bп043Fп043F043Fп043Fп043F043F(View paramView)
  {
    if ((bу04430443уу0443уу0443 + bууу0443у0443уу0443) * bу04430443уу0443уу0443 % b0443уу0443у0443уу0443 != b044304430443уу0443уу0443)
    {
      bу04430443уу0443уу0443 = bпп043Fп043Fп043Fп043F043F();
      switch (1)
      {
      case 0: 
      default: 
        for (;;)
        {
          switch (1)
          {
          }
        }
      }
      b044304430443уу0443уу0443 = 11;
      if ((bу04430443уу0443уу0443 + bп043F043Fп043Fп043Fп043F043F()) * bу04430443уу0443уу0443 % b043F043F043Fп043Fп043Fп043F043F() != b043Fп043Fп043Fп043Fп043F043F())
      {
        bу04430443уу0443уу0443 = bпп043Fп043Fп043Fп043F043F();
        b044304430443уу0443уу0443 = bпп043Fп043Fп043Fп043F043F();
      }
    }
    try
    {
      this.bуу0443уу0443уу0443 = paramView;
      return;
    }
    catch (Exception paramView)
    {
      throw paramView;
    }
  }
  
  @Nullable
  public View bппп043F043Fп043Fп043F043F()
  {
    switch (0)
    {
    case 1: 
    default: 
      for (;;)
      {
        switch (1)
        {
        }
      }
    }
    switch (0)
    {
    case 1: 
    default: 
      for (;;)
      {
        switch (0)
        {
        }
      }
    }
    int i = bу04430443уу0443уу0443;
    switch (i * (bууу0443у0443уу0443 + i) % b0443уу0443у0443уу0443)
    {
    default: 
      bу04430443уу0443уу0443 = bпп043Fп043Fп043Fп043F043F();
      b044304430443уу0443уу0443 = 30;
    }
    if ((bу04430443уу0443уу0443 + bууу0443у0443уу0443) * bу04430443уу0443уу0443 % b0443уу0443у0443уу0443 != b044304430443уу0443уу0443)
    {
      bу04430443уу0443уу0443 = 48;
      b044304430443уу0443уу0443 = 58;
    }
    return this.bуу0443уу0443уу0443;
  }
  
  @Retention(RetentionPolicy.SOURCE)
  public static @interface hhahah {}
}
