package kkkkkk;

import android.support.annotation.NonNull;
import com.mobile.business.common.injection.AuthGalaxyApiModule;
import dagger.Module;
import dagger.Provides;
import javax.inject.Singleton;

@Module(includes={AuthGalaxyApiModule.class})
public class ahhhaa
{
  public static int b0443044304430443ууу0443у = 81;
  public static int b0443ууу0443уу0443у = 2;
  public static int bу0443уу0443уу0443у = 0;
  public static int bуууу0443уу0443у = 1;
  private final oioooo b044304430443уууу0443у;
  public final String b04430443у0443ууу0443у;
  public final fbffbb b0443у04430443ууу0443у;
  private final cciccc b0443уу0443ууу0443у;
  public final String bу044304430443ууу0443у;
  private final dddpdp bу0443у0443ууу0443у;
  public final String bуу04430443ууу0443у;
  private final pdppdp bууу0443ууу0443у;
  
  public ahhhaa(@NonNull cciccc paramCciccc)
  {
    this.b0443уу0443ууу0443у = paramCciccc;
    this.b044304430443уууу0443у = paramCciccc.b0412ВВВВВ0412ВВВ();
    this.bу044304430443ууу0443у = paramCciccc.b041204120412ВВВ0412ВВВ();
    this.b04430443у0443ууу0443у = paramCciccc.bВВ0412ВВВ0412ВВВ();
    this.bуу04430443ууу0443у = paramCciccc.b0412В0412ВВВ0412ВВВ();
    this.bууу0443ууу0443у = paramCciccc.bВ04120412ВВВ0412ВВВ();
    this.bу0443у0443ууу0443у = new dddpdp();
    this.b0443у04430443ууу0443у = new fbffbb(this.bу0443у0443ууу0443у);
  }
  
  public static int b043F043F043Fп043Fп043F043Fп043F()
  {
    return 60;
  }
  
  public static int b043Fп043Fп043Fп043F043Fп043F()
  {
    return 0;
  }
  
  public static int bп043F043Fп043Fп043F043Fп043F()
  {
    return 2;
  }
  
  public static int bппп043F043Fп043F043Fп043F()
  {
    return 1;
  }
  
  @Provides
  public pdppdp b043F043F043F043F043Fп043F043Fп043F()
  {
    int i = b0443044304430443ууу0443у;
    switch (0)
    {
    case 1: 
    default: 
      for (;;)
      {
        switch (0)
        {
        }
      }
    }
    if ((i + bуууу0443уу0443у) * b0443044304430443ууу0443у % b0443ууу0443уу0443у != bу0443уу0443уу0443у)
    {
      i = b0443044304430443ууу0443у;
      switch (i * (bуууу0443уу0443у + i) % b0443ууу0443уу0443у)
      {
      default: 
        b0443044304430443ууу0443у = 43;
        bу0443уу0443уу0443у = 67;
      }
      b0443044304430443ууу0443у = 99;
      bу0443уу0443уу0443у = b043F043F043Fп043Fп043F043Fп043F();
    }
    try
    {
      pdppdp localPdppdp = this.bууу0443ууу0443у;
      return localPdppdp;
    }
    catch (Exception localException)
    {
      throw localException;
    }
  }
  
  @Provides
  @Singleton
  public aaaaah b043F043F043Fпп043F043F043Fп043F()
  {
    if ((b0443044304430443ууу0443у + bппп043F043Fп043F043Fп043F()) * b0443044304430443ууу0443у % b0443ууу0443уу0443у != b043Fп043Fп043Fп043F043Fп043F())
    {
      if ((b043F043F043Fп043Fп043F043Fп043F() + bуууу0443уу0443у) * b043F043F043Fп043Fп043F043Fп043F() % b0443ууу0443уу0443у != bу0443уу0443уу0443у)
      {
        b0443044304430443ууу0443у = b043F043F043Fп043Fп043F043Fп043F();
        bу0443уу0443уу0443у = b043F043F043Fп043Fп043F043Fп043F();
      }
      b0443044304430443ууу0443у = b043F043F043Fп043Fп043F043Fп043F();
      bу0443уу0443уу0443у = b043F043F043Fп043Fп043F043Fп043F();
    }
    aaaaah localAaaaah = new aaaaah(this.b0443уу0443ууу0443у, this.bу0443у0443ууу0443у);
    switch (1)
    {
    case 0: 
    default: 
      for (;;)
      {
        switch (1)
        {
        }
      }
    }
    return localAaaaah;
  }
  
  @Provides
  @Singleton
  public dppdpd b043F043Fп043F043Fп043F043Fп043F()
  {
    throw new Runtime("d2j fail translate: java.lang.IndexOutOfBoundsException: fromIndex < 0: -1\n\tat java.util.BitSet.nextSetBit(BitSet.java:712)\n\tat com.googlecode.dex2jar.ir.ts.array.FillArrayTransformer.makeSureAllElementAreAssigned(FillArrayTransformer.java:505)\n\tat com.googlecode.dex2jar.ir.ts.array.FillArrayTransformer.transformReportChanged(FillArrayTransformer.java:123)\n\tat com.googlecode.dex2jar.ir.ts.StatedTransformer.transform(StatedTransformer.java:10)\n\tat com.googlecode.d2j.dex.Dex2jar$2.optimize(Dex2jar.java:149)\n\tat com.googlecode.d2j.dex.Dex2Asm.convertCode(Dex2Asm.java:414)\n\tat com.googlecode.d2j.dex.ExDex2Asm.convertCode(ExDex2Asm.java:42)\n\tat com.googlecode.d2j.dex.Dex2jar$2.convertCode(Dex2jar.java:128)\n\tat com.googlecode.d2j.dex.Dex2Asm.convertMethod(Dex2Asm.java:509)\n\tat com.googlecode.d2j.dex.Dex2Asm.convertClass(Dex2Asm.java:406)\n\tat com.googlecode.d2j.dex.Dex2Asm.convertDex(Dex2Asm.java:422)\n\tat com.googlecode.d2j.dex.Dex2jar.doTranslate(Dex2jar.java:172)\n\tat com.googlecode.d2j.dex.Dex2jar.to(Dex2jar.java:272)\n\tat com.googlecode.dex2jar.tools.Dex2jarCmd.doCommandLine(Dex2jarCmd.java:108)\n\tat com.googlecode.dex2jar.tools.BaseCmd.doMain(BaseCmd.java:288)\n\tat com.googlecode.dex2jar.tools.Dex2jarCmd.main(Dex2jarCmd.java:32)\n");
  }
  
  /* Error */
  @Provides
  @Singleton
  public hahahh b043F043Fппп043F043F043Fп043F(dpdpdp paramDpdpdp, oiiioo paramOiiioo, ppdpdp paramPpdpdp, dppdpd paramDppdpd, aaaaah paramAaaaah)
  {
    // Byte code:
    //   0: aload_0
    //   1: getfield 46	kkkkkk/ahhhaa:b044304430443уууу0443у	Lkkkkkk/oioooo;
    //   4: invokeinterface 132 1 0
    //   9: astore 9
    //   11: aload 5
    //   13: aload 9
    //   15: aload_1
    //   16: aload_2
    //   17: aload_3
    //   18: aload 4
    //   20: invokevirtual 136	kkkkkk/aaaaah:bпп043Fппп043Fп043F043F	(Ljava/lang/String;Lkkkkkk/dpdpdp;Lkkkkkk/oiiioo;Lkkkkkk/ppdpdp;Lkkkkkk/dppdpd;)Lkkkkkk/lmlmmm;
    //   23: astore_1
    //   24: getstatic 93	kkkkkk/ahhhaa:b0443044304430443ууу0443у	I
    //   27: istore 6
    //   29: getstatic 95	kkkkkk/ahhhaa:bуууу0443уу0443у	I
    //   32: istore 7
    //   34: getstatic 97	kkkkkk/ahhhaa:b0443ууу0443уу0443у	I
    //   37: istore 8
    //   39: iload 6
    //   41: iload 7
    //   43: iload 6
    //   45: iadd
    //   46: imul
    //   47: iload 8
    //   49: irem
    //   50: tableswitch	default:+18->68, 0:+29->79
    //   68: invokestatic 101	kkkkkk/ahhhaa:b043F043F043Fп043Fп043F043Fп043F	()I
    //   71: putstatic 93	kkkkkk/ahhhaa:b0443044304430443ууу0443у	I
    //   74: bipush 56
    //   76: putstatic 99	kkkkkk/ahhhaa:bу0443уу0443уу0443у	I
    //   79: aload_1
    //   80: ldc -118
    //   82: invokevirtual 144	kkkkkk/lmlmmm:b04110411041104110411Б04110411Б0411	(Ljava/lang/Class;)Ljava/lang/Object;
    //   85: astore_1
    //   86: getstatic 93	kkkkkk/ahhhaa:b0443044304430443ууу0443у	I
    //   89: getstatic 95	kkkkkk/ahhhaa:bуууу0443уу0443у	I
    //   92: iadd
    //   93: getstatic 93	kkkkkk/ahhhaa:b0443044304430443ууу0443у	I
    //   96: imul
    //   97: getstatic 97	kkkkkk/ahhhaa:b0443ууу0443уу0443у	I
    //   100: irem
    //   101: getstatic 99	kkkkkk/ahhhaa:bу0443уу0443уу0443у	I
    //   104: if_icmpeq +14 -> 118
    //   107: invokestatic 101	kkkkkk/ahhhaa:b043F043F043Fп043Fп043F043Fп043F	()I
    //   110: putstatic 93	kkkkkk/ahhhaa:b0443044304430443ууу0443у	I
    //   113: bipush 84
    //   115: putstatic 99	kkkkkk/ahhhaa:bу0443уу0443уу0443у	I
    //   118: iconst_1
    //   119: tableswitch	default:+21->140, 0:+-1->118, 1:+48->167
    //   140: iconst_0
    //   141: tableswitch	default:+23->164, 0:+26->167, 1:+-23->118
    //   164: goto -24 -> 140
    //   167: aload_1
    //   168: checkcast 138	kkkkkk/hahahh
    //   171: astore_1
    //   172: aload_1
    //   173: areturn
    //   174: astore_1
    //   175: aload_1
    //   176: athrow
    //   177: astore_1
    //   178: aload_1
    //   179: athrow
    // Local variable table:
    //   start	length	slot	name	signature
    //   0	180	0	this	ahhhaa
    //   0	180	1	paramDpdpdp	dpdpdp
    //   0	180	2	paramOiiioo	oiiioo
    //   0	180	3	paramPpdpdp	ppdpdp
    //   0	180	4	paramDppdpd	dppdpd
    //   0	180	5	paramAaaaah	aaaaah
    //   27	20	6	i	int
    //   32	14	7	j	int
    //   37	13	8	k	int
    //   9	5	9	str	String
    // Exception table:
    //   from	to	target	type
    //   0	11	174	java/lang/Exception
    //   24	34	174	java/lang/Exception
    //   68	79	174	java/lang/Exception
    //   11	24	177	java/lang/Exception
    //   34	39	177	java/lang/Exception
    //   79	86	177	java/lang/Exception
    //   167	172	177	java/lang/Exception
  }
  
  @Provides
  @Singleton
  public aaahhh b043Fп043F043F043Fп043F043Fп043F(dpdpdp paramDpdpdp, oiiioo paramOiiioo, ppdpdp paramPpdpdp, dppdpd paramDppdpd, aaaaah paramAaaaah, oioooo paramOioooo)
  {
    int i = b0443044304430443ууу0443у;
    switch (i * (bуууу0443уу0443у + i) % b0443ууу0443уу0443у)
    {
    default: 
      b0443044304430443ууу0443у = b043F043F043Fп043Fп043F043Fп043F();
      bу0443уу0443уу0443у = b043F043F043Fп043Fп043F043Fп043F();
    }
    try
    {
      paramDpdpdp = (aaahhh)paramAaaaah.bпп043Fппп043Fп043F043F(paramOioooo.b0430а0430аааа0430аа(), paramDpdpdp, paramOiiioo, paramPpdpdp, paramDppdpd).b04110411041104110411Б04110411Б0411(aaahhh.class);
      return paramDpdpdp;
    }
    catch (Exception paramDpdpdp)
    {
      throw paramDpdpdp;
    }
  }
  
  /* Error */
  @Provides
  public fbffbb b043Fп043Fпп043F043F043Fп043F()
  {
    // Byte code:
    //   0: invokestatic 101	kkkkkk/ahhhaa:b043F043F043Fп043Fп043F043Fп043F	()I
    //   3: istore_1
    //   4: getstatic 95	kkkkkk/ahhhaa:bуууу0443уу0443у	I
    //   7: istore_2
    //   8: iload_1
    //   9: iload_2
    //   10: iload_1
    //   11: iadd
    //   12: imul
    //   13: invokestatic 155	kkkkkk/ahhhaa:bп043F043Fп043Fп043F043Fп043F	()I
    //   16: irem
    //   17: tableswitch	default:+91->108, 0:+75->92
    //   36: bipush 45
    //   38: putstatic 93	kkkkkk/ahhhaa:b0443044304430443ууу0443у	I
    //   41: bipush 26
    //   43: putstatic 99	kkkkkk/ahhhaa:bу0443уу0443уу0443у	I
    //   46: getstatic 93	kkkkkk/ahhhaa:b0443044304430443ууу0443у	I
    //   49: istore_1
    //   50: iload_1
    //   51: getstatic 95	kkkkkk/ahhhaa:bуууу0443уу0443у	I
    //   54: iload_1
    //   55: iadd
    //   56: imul
    //   57: getstatic 97	kkkkkk/ahhhaa:b0443ууу0443уу0443у	I
    //   60: irem
    //   61: tableswitch	default:+19->80, 0:+31->92
    //   80: invokestatic 101	kkkkkk/ahhhaa:b043F043F043Fп043Fп043F043Fп043F	()I
    //   83: putstatic 93	kkkkkk/ahhhaa:b0443044304430443ууу0443у	I
    //   86: invokestatic 101	kkkkkk/ahhhaa:b043F043F043Fп043Fп043F043Fп043F	()I
    //   89: putstatic 99	kkkkkk/ahhhaa:bу0443уу0443уу0443у	I
    //   92: aload_0
    //   93: getfield 80	kkkkkk/ahhhaa:b0443у04430443ууу0443у	Lkkkkkk/fbffbb;
    //   96: astore_3
    //   97: aload_3
    //   98: areturn
    //   99: astore_3
    //   100: aload_3
    //   101: athrow
    //   102: astore_3
    //   103: aload_3
    //   104: athrow
    //   105: astore_3
    //   106: aload_3
    //   107: athrow
    //   108: goto -72 -> 36
    // Local variable table:
    //   start	length	slot	name	signature
    //   0	111	0	this	ahhhaa
    //   3	54	1	i	int
    //   7	5	2	j	int
    //   96	2	3	localFbffbb	fbffbb
    //   99	2	3	localException1	Exception
    //   102	2	3	localException2	Exception
    //   105	2	3	localException3	Exception
    // Exception table:
    //   from	to	target	type
    //   92	97	99	java/lang/Exception
    //   0	8	102	java/lang/Exception
    //   100	102	102	java/lang/Exception
    //   8	36	105	java/lang/Exception
    //   36	46	105	java/lang/Exception
  }
  
  @Provides
  @Singleton
  public oiiioo b043Fпп043F043Fп043F043Fп043F()
  {
    try
    {
      oiiioo localOiiioo = new oiiioo();
      int i = b0443044304430443ууу0443у;
      int j = bуууу0443уу0443у;
      int k = b0443044304430443ууу0443у;
      int m = b0443ууу0443уу0443у;
      int n = b0443044304430443ууу0443у;
      switch (n * (bуууу0443уу0443у + n) % b0443ууу0443уу0443у)
      {
      default: 
        b0443044304430443ууу0443у = b043F043F043Fп043Fп043F043Fп043F();
        bуууу0443уу0443у = 60;
      }
      if ((i + j) * k % m != b043Fп043Fп043Fп043F043Fп043F())
      {
        b0443044304430443ууу0443у = b043F043F043Fп043Fп043F043Fп043F();
        bуууу0443уу0443у = b043F043F043Fп043Fп043F043Fп043F();
      }
      return localOiiioo;
    }
    catch (Exception localException)
    {
      throw localException;
    }
  }
  
  @Provides
  @Singleton
  public nuuuuu b043Fпппп043F043F043Fп043F(nnnnuu paramNnnnuu, nnnunu paramNnnunu)
  {
    try
    {
      paramNnnnuu = new nuuuuu(paramNnnnuu);
      paramNnnnuu.bппп043F043F043Fпп043Fп(paramNnnunu);
      if ((b0443044304430443ууу0443у + bуууу0443уу0443у) * b0443044304430443ууу0443у % b0443ууу0443уу0443у != bу0443уу0443уу0443у)
      {
        b0443044304430443ууу0443у = 27;
        bу0443уу0443уу0443у = b043F043F043Fп043Fп043F043Fп043F();
      }
      return paramNnnnuu;
    }
    catch (Exception paramNnnnuu)
    {
      throw paramNnnnuu;
    }
  }
  
  @Provides
  @Singleton
  public dpdpdp bп043F043F043F043Fп043F043Fп043F()
  {
    int i = b0443044304430443ууу0443у;
    switch (i * (bуууу0443уу0443у + i) % bп043F043Fп043Fп043F043Fп043F())
    {
    default: 
      b0443044304430443ууу0443у = b043F043F043Fп043Fп043F043Fп043F();
      bу0443уу0443уу0443у = 7;
    }
    switch (1)
    {
    case 0: 
    default: 
      for (;;)
      {
        switch (1)
        {
        }
      }
    }
    return new pddpdp(this.bу0443у0443ууу0443у);
  }
  
  @Provides
  @Singleton
  public ahahhh bп043F043Fпп043F043F043Fп043F(dpdpdp paramDpdpdp, oiiioo paramOiiioo, ppdpdp paramPpdpdp, dppdpd paramDppdpd, aaaaah paramAaaaah)
  {
    String str = this.b044304430443уууу0443у.b0430аа0430ааа0430аа();
    int i = b043F043F043Fп043Fп043F043Fп043F();
    switch (i * (bуууу0443уу0443у + i) % b0443ууу0443уу0443у)
    {
    default: 
      i = b043F043F043Fп043Fп043F043Fп043F();
      if ((b0443044304430443ууу0443у + bуууу0443уу0443у) * b0443044304430443ууу0443у % b0443ууу0443уу0443у != bу0443уу0443уу0443у)
      {
        b0443044304430443ууу0443у = 74;
        bу0443уу0443уу0443у = 68;
      }
      b0443044304430443ууу0443у = i;
      bу0443уу0443уу0443у = b043F043F043Fп043Fп043F043Fп043F();
    }
    paramDpdpdp = (ahahhh)paramAaaaah.bпп043Fппп043Fп043F043F(str, paramDpdpdp, paramOiiioo, paramPpdpdp, paramDppdpd).b04110411041104110411Б04110411Б0411(ahahhh.class);
    switch (0)
    {
    case 1: 
    default: 
      for (;;)
      {
        switch (1)
        {
        }
      }
    }
    return paramDpdpdp;
  }
  
  /* Error */
  @Provides
  public oioooo bп043Fп043F043Fп043F043Fп043F()
  {
    // Byte code:
    //   0: aload_0
    //   1: getfield 46	kkkkkk/ahhhaa:b044304430443уууу0443у	Lkkkkkk/oioooo;
    //   4: astore 6
    //   6: getstatic 93	kkkkkk/ahhhaa:b0443044304430443ууу0443у	I
    //   9: istore_1
    //   10: getstatic 95	kkkkkk/ahhhaa:bуууу0443уу0443у	I
    //   13: istore_2
    //   14: getstatic 93	kkkkkk/ahhhaa:b0443044304430443ууу0443у	I
    //   17: istore_3
    //   18: invokestatic 155	kkkkkk/ahhhaa:bп043F043Fп043Fп043F043Fп043F	()I
    //   21: istore 4
    //   23: invokestatic 109	kkkkkk/ahhhaa:b043Fп043Fп043Fп043F043Fп043F	()I
    //   26: istore 5
    //   28: iload_1
    //   29: iload_2
    //   30: iadd
    //   31: iload_3
    //   32: imul
    //   33: iload 4
    //   35: irem
    //   36: iload 5
    //   38: if_icmpeq +49 -> 87
    //   41: invokestatic 101	kkkkkk/ahhhaa:b043F043F043Fп043Fп043F043Fп043F	()I
    //   44: putstatic 93	kkkkkk/ahhhaa:b0443044304430443ууу0443у	I
    //   47: invokestatic 101	kkkkkk/ahhhaa:b043F043F043Fп043Fп043F043Fп043F	()I
    //   50: istore_1
    //   51: getstatic 93	kkkkkk/ahhhaa:b0443044304430443ууу0443у	I
    //   54: invokestatic 107	kkkkkk/ahhhaa:bппп043F043Fп043F043Fп043F	()I
    //   57: iadd
    //   58: getstatic 93	kkkkkk/ahhhaa:b0443044304430443ууу0443у	I
    //   61: imul
    //   62: getstatic 97	kkkkkk/ahhhaa:b0443ууу0443уу0443у	I
    //   65: irem
    //   66: invokestatic 109	kkkkkk/ahhhaa:b043Fп043Fп043Fп043F043Fп043F	()I
    //   69: if_icmpeq +14 -> 83
    //   72: bipush 32
    //   74: putstatic 93	kkkkkk/ahhhaa:b0443044304430443ууу0443у	I
    //   77: invokestatic 101	kkkkkk/ahhhaa:b043F043F043Fп043Fп043F043Fп043F	()I
    //   80: putstatic 95	kkkkkk/ahhhaa:bуууу0443уу0443у	I
    //   83: iload_1
    //   84: putstatic 95	kkkkkk/ahhhaa:bуууу0443уу0443у	I
    //   87: aload 6
    //   89: areturn
    //   90: astore 6
    //   92: aload 6
    //   94: athrow
    //   95: astore 6
    //   97: aload 6
    //   99: athrow
    // Local variable table:
    //   start	length	slot	name	signature
    //   0	100	0	this	ahhhaa
    //   9	75	1	i	int
    //   13	18	2	j	int
    //   17	16	3	k	int
    //   21	15	4	m	int
    //   26	13	5	n	int
    //   4	84	6	localOioooo	oioooo
    //   90	3	6	localException1	Exception
    //   95	3	6	localException2	Exception
    // Exception table:
    //   from	to	target	type
    //   0	23	90	java/lang/Exception
    //   41	51	90	java/lang/Exception
    //   83	87	90	java/lang/Exception
    //   23	28	95	java/lang/Exception
  }
  
  /* Error */
  @Provides
  public ddpddp bп043Fппп043F043F043Fп043F()
  {
    // Byte code:
    //   0: getstatic 93	kkkkkk/ahhhaa:b0443044304430443ууу0443у	I
    //   3: getstatic 95	kkkkkk/ahhhaa:bуууу0443уу0443у	I
    //   6: iadd
    //   7: getstatic 93	kkkkkk/ahhhaa:b0443044304430443ууу0443у	I
    //   10: imul
    //   11: getstatic 97	kkkkkk/ahhhaa:b0443ууу0443уу0443у	I
    //   14: irem
    //   15: getstatic 99	kkkkkk/ahhhaa:bу0443уу0443уу0443у	I
    //   18: if_icmpeq +14 -> 32
    //   21: invokestatic 101	kkkkkk/ahhhaa:b043F043F043Fп043Fп043F043Fп043F	()I
    //   24: putstatic 93	kkkkkk/ahhhaa:b0443044304430443ууу0443у	I
    //   27: bipush 42
    //   29: putstatic 99	kkkkkk/ahhhaa:bу0443уу0443уу0443у	I
    //   32: iconst_1
    //   33: tableswitch	default:+23->56, 0:+-1->32, 1:+50->83
    //   56: iconst_0
    //   57: tableswitch	default:+23->80, 0:+26->83, 1:+-25->32
    //   80: goto -24 -> 56
    //   83: getstatic 93	kkkkkk/ahhhaa:b0443044304430443ууу0443у	I
    //   86: istore_1
    //   87: getstatic 95	kkkkkk/ahhhaa:bуууу0443уу0443у	I
    //   90: istore_2
    //   91: getstatic 97	kkkkkk/ahhhaa:b0443ууу0443уу0443у	I
    //   94: istore_3
    //   95: iload_1
    //   96: iload_2
    //   97: iload_1
    //   98: iadd
    //   99: imul
    //   100: iload_3
    //   101: irem
    //   102: tableswitch	default:+18->120, 0:+28->130
    //   120: bipush 17
    //   122: putstatic 93	kkkkkk/ahhhaa:b0443044304430443ууу0443у	I
    //   125: bipush 29
    //   127: putstatic 99	kkkkkk/ahhhaa:bу0443уу0443уу0443у	I
    //   130: aload_0
    //   131: getfield 73	kkkkkk/ahhhaa:bу0443у0443ууу0443у	Lkkkkkk/dddpdp;
    //   134: astore 4
    //   136: aload 4
    //   138: areturn
    //   139: astore 4
    //   141: aload 4
    //   143: athrow
    //   144: astore 4
    //   146: aload 4
    //   148: athrow
    // Local variable table:
    //   start	length	slot	name	signature
    //   0	149	0	this	ahhhaa
    //   86	14	1	i	int
    //   90	9	2	j	int
    //   94	8	3	k	int
    //   134	3	4	localDddpdp	dddpdp
    //   139	3	4	localException1	Exception
    //   144	3	4	localException2	Exception
    // Exception table:
    //   from	to	target	type
    //   83	95	139	java/lang/Exception
    //   120	130	144	java/lang/Exception
    //   130	136	144	java/lang/Exception
  }
  
  @Provides
  @Singleton
  public ahaahh bпп043F043F043Fп043F043Fп043F(dpdpdp paramDpdpdp, oiiioo paramOiiioo, ppdpdp paramPpdpdp, dppdpd paramDppdpd, aaaaah paramAaaaah)
  {
    String str = this.b044304430443уууу0443у.bа04300430аааа0430аа();
    switch (1)
    {
    case 0: 
    default: 
      for (;;)
      {
        switch (1)
        {
        }
      }
    }
    int i = b0443044304430443ууу0443у;
    int j = bуууу0443уу0443у;
    switch (0)
    {
    case 1: 
    default: 
      for (;;)
      {
        switch (0)
        {
        }
      }
    }
    if ((i + j) * b0443044304430443ууу0443у % b0443ууу0443уу0443у != bу0443уу0443уу0443у)
    {
      b0443044304430443ууу0443у = b043F043F043Fп043Fп043F043Fп043F();
      if ((b0443044304430443ууу0443у + bуууу0443уу0443у) * b0443044304430443ууу0443у % b0443ууу0443уу0443у != bу0443уу0443уу0443у)
      {
        b0443044304430443ууу0443у = b043F043F043Fп043Fп043F043Fп043F();
        bу0443уу0443уу0443у = b043F043F043Fп043Fп043F043Fп043F();
      }
      bу0443уу0443уу0443у = 15;
    }
    return (ahaahh)paramAaaaah.bпп043Fппп043Fп043F043F(str, paramDpdpdp, paramOiiioo, paramPpdpdp, paramDppdpd).b04110411041104110411Б04110411Б0411(ahaahh.class);
  }
  
  /* Error */
  @Provides
  @Singleton
  public ppdpdp bпп043Fпп043F043F043Fп043F()
  {
    // Byte code:
    //   0: getstatic 93	kkkkkk/ahhhaa:b0443044304430443ууу0443у	I
    //   3: istore_1
    //   4: iload_1
    //   5: getstatic 95	kkkkkk/ahhhaa:bуууу0443уу0443у	I
    //   8: iload_1
    //   9: iadd
    //   10: imul
    //   11: getstatic 97	kkkkkk/ahhhaa:b0443ууу0443уу0443у	I
    //   14: irem
    //   15: tableswitch	default:+17->32, 0:+29->44
    //   32: invokestatic 101	kkkkkk/ahhhaa:b043F043F043Fп043Fп043F043Fп043F	()I
    //   35: putstatic 93	kkkkkk/ahhhaa:b0443044304430443ууу0443у	I
    //   38: invokestatic 101	kkkkkk/ahhhaa:b043F043F043Fп043Fп043F043Fп043F	()I
    //   41: putstatic 99	kkkkkk/ahhhaa:bу0443уу0443уу0443у	I
    //   44: getstatic 93	kkkkkk/ahhhaa:b0443044304430443ууу0443у	I
    //   47: istore_1
    //   48: getstatic 95	kkkkkk/ahhhaa:bуууу0443уу0443у	I
    //   51: istore_2
    //   52: getstatic 97	kkkkkk/ahhhaa:b0443ууу0443уу0443у	I
    //   55: istore_3
    //   56: iload_1
    //   57: iload_2
    //   58: iload_1
    //   59: iadd
    //   60: imul
    //   61: iload_3
    //   62: irem
    //   63: tableswitch	default:+17->80, 0:+29->92
    //   80: invokestatic 101	kkkkkk/ahhhaa:b043F043F043Fп043Fп043F043Fп043F	()I
    //   83: putstatic 93	kkkkkk/ahhhaa:b0443044304430443ууу0443у	I
    //   86: invokestatic 101	kkkkkk/ahhhaa:b043F043F043Fп043Fп043F043Fп043F	()I
    //   89: putstatic 99	kkkkkk/ahhhaa:bу0443уу0443уу0443у	I
    //   92: new 196	kkkkkk/ppdpdp
    //   95: dup
    //   96: aload_0
    //   97: getfield 46	kkkkkk/ahhhaa:b044304430443уууу0443у	Lkkkkkk/oioooo;
    //   100: aload_0
    //   101: getfield 68	kkkkkk/ahhhaa:bууу0443ууу0443у	Lkkkkkk/pdppdp;
    //   104: invokespecial 199	kkkkkk/ppdpdp:<init>	(Lkkkkkk/oioooo;Lkkkkkk/pdppdp;)V
    //   107: astore 4
    //   109: aload 4
    //   111: areturn
    //   112: astore 4
    //   114: aload 4
    //   116: athrow
    //   117: astore 4
    //   119: aload 4
    //   121: athrow
    // Local variable table:
    //   start	length	slot	name	signature
    //   0	122	0	this	ahhhaa
    //   3	58	1	i	int
    //   51	9	2	j	int
    //   55	8	3	k	int
    //   107	3	4	localPpdpdp	ppdpdp
    //   112	3	4	localException1	Exception
    //   117	3	4	localException2	Exception
    // Exception table:
    //   from	to	target	type
    //   44	56	112	java/lang/Exception
    //   92	109	112	java/lang/Exception
    //   80	92	117	java/lang/Exception
  }
  
  @Provides
  public cciccc bппп043Fп043F043F043Fп043F()
  {
    switch (0)
    {
    case 1: 
    default: 
      for (;;)
      {
        switch (1)
        {
        }
      }
    }
    int i = b0443044304430443ууу0443у;
    int j = b0443044304430443ууу0443у;
    switch (j * (bуууу0443уу0443у + j) % b0443ууу0443уу0443у)
    {
    default: 
      b0443044304430443ууу0443у = b043F043F043Fп043Fп043F043Fп043F();
      bу0443уу0443уу0443у = 72;
    }
    if ((i + bуууу0443уу0443у) * b0443044304430443ууу0443у % b0443ууу0443уу0443у != bу0443уу0443уу0443у)
    {
      b0443044304430443ууу0443у = b043F043F043Fп043Fп043F043Fп043F();
      bу0443уу0443уу0443у = 37;
    }
    return this.b0443уу0443ууу0443у;
  }
  
  @Provides
  @Singleton
  public ppppdp bппппп043F043F043Fп043F(oioooo paramOioooo)
  {
    int i = b0443044304430443ууу0443у;
    switch (i * (bуууу0443уу0443у + i) % bп043F043Fп043Fп043F043Fп043F())
    {
    default: 
      b0443044304430443ууу0443у = 90;
      bу0443уу0443уу0443у = b043F043F043Fп043Fп043F043Fп043F();
      i = b0443044304430443ууу0443у;
      switch (i * (bуууу0443уу0443у + i) % b0443ууу0443уу0443у)
      {
      default: 
        b0443044304430443ууу0443у = 88;
        bу0443уу0443уу0443у = 9;
      }
      break;
    }
    return new ddppdp(this.bу044304430443ууу0443у, this.bуу04430443ууу0443у);
  }
}
