package kkkkkk;

import android.app.Activity;
import android.app.Application.ActivityLifecycleCallbacks;
import android.os.Bundle;

public class alalal
  implements Application.ActivityLifecycleCallbacks
{
  public static int b04320432в04320432ввв04320432 = 1;
  public static int b0432вв04320432ввв04320432 = 9;
  public static int bв0432в04320432ввв04320432 = 0;
  public static int bвв043204320432ввв04320432 = 2;
  private int bввв04320432ввв04320432 = 0;
  
  public alalal() {}
  
  public static int b0435е04350435ее04350435ее()
  {
    return 31;
  }
  
  public static int bе043504350435ее04350435ее()
  {
    return 1;
  }
  
  public void onActivityCreated(Activity paramActivity, Bundle paramBundle)
  {
    switch (0)
    {
    case 1: 
    default: 
      for (;;)
      {
        if ((b0432вв04320432ввв04320432 + b04320432в04320432ввв04320432) * b0432вв04320432ввв04320432 % bвв043204320432ввв04320432 != bв0432в04320432ввв04320432)
        {
          b0432вв04320432ввв04320432 = 28;
          bв0432в04320432ввв04320432 = 93;
        }
        switch (0)
        {
        }
      }
    }
  }
  
  public void onActivityDestroyed(Activity paramActivity)
  {
    switch (1)
    {
    case 0: 
    default: 
      for (;;)
      {
        int i = b0432вв04320432ввв04320432;
        switch (i * (bе043504350435ее04350435ее() + i) % bвв043204320432ввв04320432)
        {
        default: 
          b0432вв04320432ввв04320432 = 97;
          bв0432в04320432ввв04320432 = b0435е04350435ее04350435ее();
        }
        switch (1)
        {
        }
      }
    }
  }
  
  public void onActivityPaused(Activity paramActivity) {}
  
  public void onActivityResumed(Activity paramActivity)
  {
    int i = b0432вв04320432ввв04320432;
    switch (i * (b04320432в04320432ввв04320432 + i) % bвв043204320432ввв04320432)
    {
    default: 
      b0432вв04320432ввв04320432 = 59;
      bв0432в04320432ввв04320432 = 58;
    }
  }
  
  public void onActivitySaveInstanceState(Activity paramActivity, Bundle paramBundle)
  {
    switch (1)
    {
    case 0: 
    default: 
      for (;;)
      {
        switch (1)
        {
        }
      }
    }
  }
  
  public void onActivityStarted(Activity paramActivity)
  {
    int i = b0432вв04320432ввв04320432;
    switch (i * (b04320432в04320432ввв04320432 + i) % bвв043204320432ввв04320432)
    {
    default: 
      b0432вв04320432ввв04320432 = b0435е04350435ее04350435ее();
      bв0432в04320432ввв04320432 = 40;
    }
    switch (1)
    {
    case 0: 
    default: 
      for (;;)
      {
        switch (0)
        {
        }
      }
    }
    i = this.bввв04320432ввв04320432;
    int j = b0432вв04320432ввв04320432;
    switch (j * (b04320432в04320432ввв04320432 + j) % bвв043204320432ввв04320432)
    {
    default: 
      switch (0)
      {
      case 1: 
      default: 
        for (;;)
        {
          switch (0)
          {
          }
        }
      }
      b0432вв04320432ввв04320432 = 40;
      bв0432в04320432ввв04320432 = 42;
    }
    this.bввв04320432ввв04320432 = (i + 1);
  }
  
  /* Error */
  public void onActivityStopped(Activity paramActivity)
  {
    // Byte code:
    //   0: aload_0
    //   1: aload_0
    //   2: getfield 22	kkkkkk/alalal:bввв04320432ввв04320432	I
    //   5: iconst_1
    //   6: isub
    //   7: putfield 22	kkkkkk/alalal:bввв04320432ввв04320432	I
    //   10: aload_0
    //   11: getfield 22	kkkkkk/alalal:bввв04320432ввв04320432	I
    //   14: ifne +19 -> 33
    //   17: aload_1
    //   18: instanceof 51
    //   21: istore_2
    //   22: iload_2
    //   23: ifeq +10 -> 33
    //   26: aload_1
    //   27: checkcast 51	com/mobile/ui/common/activity/AppTimeoutActivity
    //   30: invokevirtual 54	com/mobile/ui/common/activity/AppTimeoutActivity:onAppBackgrounded	()V
    //   33: return
    //   34: astore_1
    //   35: aload_1
    //   36: athrow
    //   37: astore_1
    //   38: aload_1
    //   39: athrow
    // Local variable table:
    //   start	length	slot	name	signature
    //   0	40	0	this	alalal
    //   0	40	1	paramActivity	Activity
    //   21	2	2	bool	boolean
    // Exception table:
    //   from	to	target	type
    //   0	22	34	java/lang/Exception
    //   26	33	37	java/lang/Exception
  }
}
