package kkkkkk;

import java.util.Collections;
import java.util.List;

public abstract class bbfffb
{
  public static int b042E042EЮЮ042EЮЮЮ042E = 2;
  public static int b042EЮ042EЮ042EЮЮЮ042E = 1;
  public static int bЮ042EЮЮ042EЮЮЮ042E = 32;
  public static int bЮЮ042EЮ042EЮЮЮ042E;
  private List<unnnun> b042E042E042E042EЮЮЮЮ042E;
  private String b042E042E042EЮЮЮЮЮ042E;
  private String b042E042EЮ042EЮЮЮЮ042E;
  private ffbffb b042E042EЮЮЮЮЮЮ042E;
  private String b042EЮ042E042EЮЮЮЮ042E;
  private String b042EЮ042EЮЮЮЮЮ042E;
  private boolean b042EЮЮ042EЮЮЮЮ042E;
  private String b042EЮЮЮ042EЮЮЮ042E;
  private String bЮ042E042E042EЮЮЮЮ042E;
  private String bЮ042E042EЮЮЮЮЮ042E;
  private boolean bЮ042EЮ042EЮЮЮЮ042E;
  private String bЮЮ042E042EЮЮЮЮ042E;
  private String bЮЮ042EЮЮЮЮЮ042E;
  private boolean bЮЮЮ042EЮЮЮЮ042E;
  private boolean bЮЮЮЮ042EЮЮЮ042E;
  
  @ooiiio
  public bbfffb(fbbffb paramFbbffb)
  {
    this.b042E042E042EЮЮЮЮЮ042E = paramFbbffb.b0412ВВВ041204120412В0412В();
    this.b042E042EЮ042EЮЮЮЮ042E = paramFbbffb.bВ0412ВВ041204120412В0412В();
    this.bЮЮ042E042EЮЮЮЮ042E = (this.b042E042E042EЮЮЮЮЮ042E + gguuuu.bк043Aккк043Aкк043A043A("o", 'Ô', '', '\001') + this.b042E042EЮ042EЮЮЮЮ042E);
    this.b042E042EЮЮЮЮЮЮ042E = ffbffb.bВВВ0412ВВВ04120412В(paramFbbffb.b0412В04120412В04120412В0412В());
    this.bЮ042EЮ042EЮЮЮЮ042E = paramFbbffb.b0412ВВ0412041204120412В0412В();
    this.b042EЮЮ042EЮЮЮЮ042E = paramFbbffb.bВВВ0412041204120412В0412В();
    this.bЮЮЮ042EЮЮЮЮ042E = paramFbbffb.b041204120412В041204120412В0412В();
    this.bЮЮ042EЮЮЮЮЮ042E = paramFbbffb.bВ041204120412В04120412В0412В();
    this.bЮ042E042E042EЮЮЮЮ042E = paramFbbffb.bВВ0412В041204120412В0412В();
    this.b042E042E042E042EЮЮЮЮ042E = Collections.unmodifiableList(paramFbbffb.b0412В0412В041204120412В0412В());
    this.bЮ042E042EЮЮЮЮЮ042E = paramFbbffb.bВВВВ041204120412В0412В();
    this.b042EЮ042E042EЮЮЮЮ042E = paramFbbffb.b04120412ВВ041204120412В0412В();
    this.b042EЮ042EЮЮЮЮЮ042E = paramFbbffb.b0412041204120412В04120412В0412В();
    this.b042EЮЮЮ042EЮЮЮ042E = paramFbbffb.bВ04120412В041204120412В0412В();
    this.bЮЮЮЮ042EЮЮЮ042E = paramFbbffb.bВ0412В0412041204120412В0412В();
  }
  
  public static int b041204120412В0412ВВ04120412В()
  {
    return 0;
  }
  
  public static int b0412В0412В0412ВВ04120412В()
  {
    return 1;
  }
  
  public static int bВ04120412В0412ВВ04120412В()
  {
    return 42;
  }
  
  public static int bВВ0412В0412ВВ04120412В()
  {
    return 2;
  }
  
  /* Error */
  public String b04120412041204120412ВВ04120412В()
  {
    // Byte code:
    //   0: getstatic 158	kkkkkk/bbfffb:bЮ042EЮЮ042EЮЮЮ042E	I
    //   3: istore_1
    //   4: invokestatic 160	kkkkkk/bbfffb:b0412В0412В0412ВВ04120412В	()I
    //   7: istore_2
    //   8: getstatic 162	kkkkkk/bbfffb:b042E042EЮЮ042EЮЮЮ042E	I
    //   11: istore_3
    //   12: iload_1
    //   13: iload_2
    //   14: iload_1
    //   15: iadd
    //   16: imul
    //   17: iload_3
    //   18: irem
    //   19: tableswitch	default:+17->36, 0:+27->46
    //   36: bipush 47
    //   38: putstatic 158	kkkkkk/bbfffb:bЮ042EЮЮ042EЮЮЮ042E	I
    //   41: bipush 70
    //   43: putstatic 164	kkkkkk/bbfffb:bЮЮ042EЮ042EЮЮЮ042E	I
    //   46: iconst_0
    //   47: tableswitch	default:+21->68, 0:+48->95, 1:+-1->46
    //   68: iconst_0
    //   69: tableswitch	default:+23->92, 0:+26->95, 1:+-23->46
    //   92: goto -24 -> 68
    //   95: getstatic 158	kkkkkk/bbfffb:bЮ042EЮЮ042EЮЮЮ042E	I
    //   98: istore_1
    //   99: iload_1
    //   100: getstatic 166	kkkkkk/bbfffb:b042EЮ042EЮ042EЮЮЮ042E	I
    //   103: iload_1
    //   104: iadd
    //   105: imul
    //   106: getstatic 162	kkkkkk/bbfffb:b042E042EЮЮ042EЮЮЮ042E	I
    //   109: irem
    //   110: tableswitch	default:+18->128, 0:+29->139
    //   128: invokestatic 168	kkkkkk/bbfffb:bВ04120412В0412ВВ04120412В	()I
    //   131: putstatic 158	kkkkkk/bbfffb:bЮ042EЮЮ042EЮЮЮ042E	I
    //   134: bipush 89
    //   136: putstatic 164	kkkkkk/bbfffb:bЮЮ042EЮ042EЮЮЮ042E	I
    //   139: aload_0
    //   140: getfield 131	kkkkkk/bbfffb:b042EЮ042E042EЮЮЮЮ042E	Ljava/lang/String;
    //   143: astore 4
    //   145: aload 4
    //   147: areturn
    //   148: astore 4
    //   150: aload 4
    //   152: athrow
    //   153: astore 4
    //   155: aload 4
    //   157: athrow
    // Local variable table:
    //   start	length	slot	name	signature
    //   0	158	0	this	bbfffb
    //   3	103	1	i	int
    //   7	9	2	j	int
    //   11	8	3	k	int
    //   143	3	4	str	String
    //   148	3	4	localException1	Exception
    //   153	3	4	localException2	Exception
    // Exception table:
    //   from	to	target	type
    //   0	8	148	java/lang/Exception
    //   36	41	148	java/lang/Exception
    //   8	12	153	java/lang/Exception
    //   41	46	153	java/lang/Exception
    //   139	145	153	java/lang/Exception
  }
  
  public String b04120412В04120412ВВ04120412В()
  {
    try
    {
      String str = this.bЮ042E042EЮЮЮЮЮ042E;
      if ((bЮ042EЮЮ042EЮЮЮ042E + b0412В0412В0412ВВ04120412В()) * bЮ042EЮЮ042EЮЮЮ042E % bВВ0412В0412ВВ04120412В() != bЮЮ042EЮ042EЮЮЮ042E)
      {
        bЮ042EЮЮ042EЮЮЮ042E = 23;
        bЮЮ042EЮ042EЮЮЮ042E = 42;
      }
      return str;
    }
    catch (Exception localException1)
    {
      try
      {
        throw localException1;
      }
      catch (Exception localException2)
      {
        throw localException2;
      }
    }
  }
  
  @ooiiio
  public boolean b04120412ВВ0412ВВ04120412В()
  {
    int i = bЮ042EЮЮ042EЮЮЮ042E;
    switch (i * (b0412В0412В0412ВВ04120412В() + i) % b042E042EЮЮ042EЮЮЮ042E)
    {
    default: 
      bЮ042EЮЮ042EЮЮЮ042E = 25;
      b042E042EЮЮ042EЮЮЮ042E = 41;
    }
    boolean bool = this.bЮЮЮЮ042EЮЮЮ042E;
    switch (0)
    {
    case 1: 
    default: 
      for (;;)
      {
        if ((bЮ042EЮЮ042EЮЮЮ042E + b042EЮ042EЮ042EЮЮЮ042E) * bЮ042EЮЮ042EЮЮЮ042E % b042E042EЮЮ042EЮЮЮ042E != bЮЮ042EЮ042EЮЮЮ042E)
        {
          bЮ042EЮЮ042EЮЮЮ042E = bВ04120412В0412ВВ04120412В();
          bЮЮ042EЮ042EЮЮЮ042E = 79;
        }
        switch (1)
        {
        }
      }
    }
    return bool;
  }
  
  /* Error */
  public boolean b04120412ВВВ0412В04120412В()
  {
    // Byte code:
    //   0: getstatic 158	kkkkkk/bbfffb:bЮ042EЮЮ042EЮЮЮ042E	I
    //   3: istore_1
    //   4: getstatic 166	kkkkkk/bbfffb:b042EЮ042EЮ042EЮЮЮ042E	I
    //   7: istore_2
    //   8: getstatic 158	kkkkkk/bbfffb:bЮ042EЮЮ042EЮЮЮ042E	I
    //   11: istore_3
    //   12: getstatic 162	kkkkkk/bbfffb:b042E042EЮЮ042EЮЮЮ042E	I
    //   15: istore 4
    //   17: getstatic 164	kkkkkk/bbfffb:bЮЮ042EЮ042EЮЮЮ042E	I
    //   20: istore 5
    //   22: iload_1
    //   23: iload_2
    //   24: iadd
    //   25: iload_3
    //   26: imul
    //   27: iload 4
    //   29: irem
    //   30: iload 5
    //   32: if_icmpeq +46 -> 78
    //   35: getstatic 158	kkkkkk/bbfffb:bЮ042EЮЮ042EЮЮЮ042E	I
    //   38: getstatic 166	kkkkkk/bbfffb:b042EЮ042EЮ042EЮЮЮ042E	I
    //   41: iadd
    //   42: getstatic 158	kkkkkk/bbfffb:bЮ042EЮЮ042EЮЮЮ042E	I
    //   45: imul
    //   46: getstatic 162	kkkkkk/bbfffb:b042E042EЮЮ042EЮЮЮ042E	I
    //   49: irem
    //   50: getstatic 164	kkkkkk/bbfffb:bЮЮ042EЮ042EЮЮЮ042E	I
    //   53: if_icmpeq +13 -> 66
    //   56: bipush 99
    //   58: putstatic 158	kkkkkk/bbfffb:bЮ042EЮЮ042EЮЮЮ042E	I
    //   61: bipush 94
    //   63: putstatic 164	kkkkkk/bbfffb:bЮЮ042EЮ042EЮЮЮ042E	I
    //   66: invokestatic 168	kkkkkk/bbfffb:bВ04120412В0412ВВ04120412В	()I
    //   69: putstatic 158	kkkkkk/bbfffb:bЮ042EЮЮ042EЮЮЮ042E	I
    //   72: invokestatic 168	kkkkkk/bbfffb:bВ04120412В0412ВВ04120412В	()I
    //   75: putstatic 164	kkkkkk/bbfffb:bЮЮ042EЮ042EЮЮЮ042E	I
    //   78: aload_0
    //   79: getfield 99	kkkkkk/bbfffb:bЮЮЮ042EЮЮЮЮ042E	Z
    //   82: istore 6
    //   84: iload 6
    //   86: ireturn
    //   87: astore 7
    //   89: aload 7
    //   91: athrow
    //   92: astore 7
    //   94: aload 7
    //   96: athrow
    //   97: astore 7
    //   99: aload 7
    //   101: athrow
    // Local variable table:
    //   start	length	slot	name	signature
    //   0	102	0	this	bbfffb
    //   3	22	1	i	int
    //   7	18	2	j	int
    //   11	16	3	k	int
    //   15	15	4	m	int
    //   20	13	5	n	int
    //   82	3	6	bool	boolean
    //   87	3	7	localException1	Exception
    //   92	3	7	localException2	Exception
    //   97	3	7	localException3	Exception
    // Exception table:
    //   from	to	target	type
    //   78	84	87	java/lang/Exception
    //   0	22	92	java/lang/Exception
    //   89	92	92	java/lang/Exception
    //   66	78	97	java/lang/Exception
  }
  
  public String b0412В041204120412ВВ04120412В()
  {
    String str = this.b042E042EЮ042EЮЮЮЮ042E;
    if ((bЮ042EЮЮ042EЮЮЮ042E + b042EЮ042EЮ042EЮЮЮ042E) * bЮ042EЮЮ042EЮЮЮ042E % bВВ0412В0412ВВ04120412В() != bЮЮ042EЮ042EЮЮЮ042E)
    {
      int i = bВ04120412В0412ВВ04120412В();
      switch (i * (b042EЮ042EЮ042EЮЮЮ042E + i) % b042E042EЮЮ042EЮЮЮ042E)
      {
      default: 
        bЮ042EЮЮ042EЮЮЮ042E = bВ04120412В0412ВВ04120412В();
        bЮЮ042EЮ042EЮЮЮ042E = bВ04120412В0412ВВ04120412В();
      }
      bЮ042EЮЮ042EЮЮЮ042E = 62;
      bЮЮ042EЮ042EЮЮЮ042E = bВ04120412В0412ВВ04120412В();
    }
    switch (1)
    {
    case 0: 
    default: 
      for (;;)
      {
        switch (0)
        {
        }
      }
    }
    return str;
  }
  
  public boolean b0412В0412ВВ0412В04120412В()
  {
    if ((bЮ042EЮЮ042EЮЮЮ042E + b042EЮ042EЮ042EЮЮЮ042E) * bЮ042EЮЮ042EЮЮЮ042E % b042E042EЮЮ042EЮЮЮ042E != bЮЮ042EЮ042EЮЮЮ042E)
    {
      int i = bЮ042EЮЮ042EЮЮЮ042E;
      switch (i * (b0412В0412В0412ВВ04120412В() + i) % b042E042EЮЮ042EЮЮЮ042E)
      {
      default: 
        bЮ042EЮЮ042EЮЮЮ042E = bВ04120412В0412ВВ04120412В();
        bЮЮ042EЮ042EЮЮЮ042E = 43;
      }
      bЮ042EЮЮ042EЮЮЮ042E = bВ04120412В0412ВВ04120412В();
      bЮЮ042EЮ042EЮЮЮ042E = bВ04120412В0412ВВ04120412В();
    }
    try
    {
      boolean bool = this.bЮ042EЮ042EЮЮЮЮ042E;
      return bool;
    }
    catch (Exception localException)
    {
      throw localException;
    }
  }
  
  public String b0412ВВ04120412ВВ04120412В()
  {
    String str = this.bЮЮ042EЮЮЮЮЮ042E;
    if ((bЮ042EЮЮ042EЮЮЮ042E + b042EЮ042EЮ042EЮЮЮ042E) * bЮ042EЮЮ042EЮЮЮ042E % b042E042EЮЮ042EЮЮЮ042E != b041204120412В0412ВВ04120412В())
    {
      bЮ042EЮЮ042EЮЮЮ042E = bВ04120412В0412ВВ04120412В();
      if ((bЮ042EЮЮ042EЮЮЮ042E + b042EЮ042EЮ042EЮЮЮ042E) * bЮ042EЮЮ042EЮЮЮ042E % b042E042EЮЮ042EЮЮЮ042E != bЮЮ042EЮ042EЮЮЮ042E)
      {
        bЮ042EЮЮ042EЮЮЮ042E = bВ04120412В0412ВВ04120412В();
        bЮЮ042EЮ042EЮЮЮ042E = 72;
      }
      bЮЮ042EЮ042EЮЮЮ042E = 95;
    }
    switch (1)
    {
    case 0: 
    default: 
      for (;;)
      {
        switch (1)
        {
        }
      }
    }
    return str;
  }
  
  public List<unnnun> b0412ВВВВ0412В04120412В()
  {
    switch (0)
    {
    case 1: 
    default: 
      for (;;)
      {
        i = bЮ042EЮЮ042EЮЮЮ042E;
        switch (i * (b042EЮ042EЮ042EЮЮЮ042E + i) % b042E042EЮЮ042EЮЮЮ042E)
        {
        default: 
          bЮ042EЮЮ042EЮЮЮ042E = 32;
          bЮЮ042EЮ042EЮЮЮ042E = 81;
        }
        switch (0)
        {
        case 1: 
        default: 
          for (;;)
          {
            switch (0)
            {
            }
          }
        }
        switch (0)
        {
        }
      }
    }
    int i = bЮ042EЮЮ042EЮЮЮ042E;
    switch (i * (b042EЮ042EЮ042EЮЮЮ042E + i) % b042E042EЮЮ042EЮЮЮ042E)
    {
    default: 
      bЮ042EЮЮ042EЮЮЮ042E = bВ04120412В0412ВВ04120412В();
      bЮЮ042EЮ042EЮЮЮ042E = 84;
    }
    return this.b042E042E042E042EЮЮЮЮ042E;
  }
  
  public String bВ0412041204120412ВВ04120412В()
  {
    try
    {
      int i = bВ04120412В0412ВВ04120412В();
      switch (i * (b042EЮ042EЮ042EЮЮЮ042E + i) % b042E042EЮЮ042EЮЮЮ042E)
      {
      }
      for (;;)
      {
        bЮ042EЮЮ042EЮЮЮ042E = 67;
        bЮЮ042EЮ042EЮЮЮ042E = bВ04120412В0412ВВ04120412В();
        try
        {
          String str = this.bЮЮ042E042EЮЮЮЮ042E;
          i = bЮ042EЮЮ042EЮЮЮ042E;
          switch (i * (b042EЮ042EЮ042EЮЮЮ042E + i) % b042E042EЮЮ042EЮЮЮ042E)
          {
          default: 
            bЮ042EЮЮ042EЮЮЮ042E = 78;
            bЮЮ042EЮ042EЮЮЮ042E = bВ04120412В0412ВВ04120412В();
          }
          return str;
        }
        catch (Exception localException1)
        {
          try
          {
            throw localException1;
          }
          catch (Exception localException2)
          {
            throw localException2;
          }
        }
      }
    }
    catch (Exception localException3)
    {
      throw localException3;
    }
  }
  
  public String bВ0412В04120412ВВ04120412В()
  {
    switch (1)
    {
    case 0: 
    default: 
      for (;;)
      {
        switch (1)
        {
        }
      }
    }
    String str = this.b042EЮ042EЮЮЮЮЮ042E;
    int i = bЮ042EЮЮ042EЮЮЮ042E;
    int j = bЮ042EЮЮ042EЮЮЮ042E;
    switch (j * (b042EЮ042EЮ042EЮЮЮ042E + j) % b042E042EЮЮ042EЮЮЮ042E)
    {
    default: 
      bЮ042EЮЮ042EЮЮЮ042E = 6;
      bЮЮ042EЮ042EЮЮЮ042E = bВ04120412В0412ВВ04120412В();
    }
    if ((i + b042EЮ042EЮ042EЮЮЮ042E) * bЮ042EЮЮ042EЮЮЮ042E % b042E042EЮЮ042EЮЮЮ042E != bЮЮ042EЮ042EЮЮЮ042E)
    {
      bЮ042EЮЮ042EЮЮЮ042E = 43;
      bЮЮ042EЮ042EЮЮЮ042E = 52;
    }
    return str;
  }
  
  /* Error */
  public String bВ0412ВВВ0412В04120412В()
  {
    // Byte code:
    //   0: iconst_1
    //   1: tableswitch	default:+23->24, 0:+-1->0, 1:+50->51
    //   24: iconst_1
    //   25: tableswitch	default:+23->48, 0:+-25->0, 1:+26->51
    //   48: goto -24 -> 24
    //   51: aload_0
    //   52: getfield 141	kkkkkk/bbfffb:b042EЮЮЮ042EЮЮЮ042E	Ljava/lang/String;
    //   55: astore 4
    //   57: getstatic 158	kkkkkk/bbfffb:bЮ042EЮЮ042EЮЮЮ042E	I
    //   60: istore_1
    //   61: getstatic 166	kkkkkk/bbfffb:b042EЮ042EЮ042EЮЮЮ042E	I
    //   64: istore_2
    //   65: getstatic 162	kkkkkk/bbfffb:b042E042EЮЮ042EЮЮЮ042E	I
    //   68: istore_3
    //   69: iload_1
    //   70: iload_2
    //   71: iload_1
    //   72: iadd
    //   73: imul
    //   74: iload_3
    //   75: irem
    //   76: tableswitch	default:+89->165, 0:+76->152
    //   96: invokestatic 168	kkkkkk/bbfffb:bВ04120412В0412ВВ04120412В	()I
    //   99: putstatic 158	kkkkkk/bbfffb:bЮ042EЮЮ042EЮЮЮ042E	I
    //   102: getstatic 158	kkkkkk/bbfffb:bЮ042EЮЮ042EЮЮЮ042E	I
    //   105: istore_1
    //   106: iload_1
    //   107: invokestatic 160	kkkkkk/bbfffb:b0412В0412В0412ВВ04120412В	()I
    //   110: iload_1
    //   111: iadd
    //   112: imul
    //   113: getstatic 162	kkkkkk/bbfffb:b042E042EЮЮ042EЮЮЮ042E	I
    //   116: irem
    //   117: tableswitch	default:+19->136, 0:+30->147
    //   136: invokestatic 168	kkkkkk/bbfffb:bВ04120412В0412ВВ04120412В	()I
    //   139: putstatic 158	kkkkkk/bbfffb:bЮ042EЮЮ042EЮЮЮ042E	I
    //   142: bipush 14
    //   144: putstatic 164	kkkkkk/bbfffb:bЮЮ042EЮ042EЮЮЮ042E	I
    //   147: bipush 47
    //   149: putstatic 164	kkkkkk/bbfffb:bЮЮ042EЮ042EЮЮЮ042E	I
    //   152: aload 4
    //   154: areturn
    //   155: astore 4
    //   157: aload 4
    //   159: athrow
    //   160: astore 4
    //   162: aload 4
    //   164: athrow
    //   165: goto -69 -> 96
    // Local variable table:
    //   start	length	slot	name	signature
    //   0	168	0	this	bbfffb
    //   60	53	1	i	int
    //   64	9	2	j	int
    //   68	8	3	k	int
    //   55	98	4	str	String
    //   155	3	4	localException1	Exception
    //   160	3	4	localException2	Exception
    // Exception table:
    //   from	to	target	type
    //   51	69	155	java/lang/Exception
    //   96	102	160	java/lang/Exception
    //   147	152	160	java/lang/Exception
  }
  
  public String bВВ041204120412ВВ04120412В()
  {
    if ((bЮ042EЮЮ042EЮЮЮ042E + b042EЮ042EЮ042EЮЮЮ042E) * bЮ042EЮЮ042EЮЮЮ042E % b042E042EЮЮ042EЮЮЮ042E != bЮЮ042EЮ042EЮЮЮ042E)
    {
      bЮ042EЮЮ042EЮЮЮ042E = bВ04120412В0412ВВ04120412В();
      bЮЮ042EЮ042EЮЮЮ042E = bВ04120412В0412ВВ04120412В();
    }
    try
    {
      String str = this.b042E042E042EЮЮЮЮЮ042E;
      return str;
    }
    catch (Exception localException)
    {
      throw localException;
    }
  }
  
  public boolean bВВ0412ВВ0412В04120412В()
  {
    if ((bЮ042EЮЮ042EЮЮЮ042E + b042EЮ042EЮ042EЮЮЮ042E) * bЮ042EЮЮ042EЮЮЮ042E % b042E042EЮЮ042EЮЮЮ042E != bЮЮ042EЮ042EЮЮЮ042E)
    {
      bЮ042EЮЮ042EЮЮЮ042E = bВ04120412В0412ВВ04120412В();
      bЮЮ042EЮ042EЮЮЮ042E = bВ04120412В0412ВВ04120412В();
    }
    int i = bЮ042EЮЮ042EЮЮЮ042E;
    switch (i * (b042EЮ042EЮ042EЮЮЮ042E + i) % bВВ0412В0412ВВ04120412В())
    {
    default: 
      bЮ042EЮЮ042EЮЮЮ042E = bВ04120412В0412ВВ04120412В();
      bЮЮ042EЮ042EЮЮЮ042E = bВ04120412В0412ВВ04120412В();
    }
    boolean bool = this.b042EЮЮ042EЮЮЮЮ042E;
    switch (1)
    {
    case 0: 
    default: 
      for (;;)
      {
        switch (1)
        {
        }
      }
    }
    return bool;
  }
  
  public ffbffb bВВВ04120412ВВ04120412В()
  {
    switch (1)
    {
    case 0: 
    default: 
      for (;;)
      {
        switch (0)
        {
        }
      }
    }
    int i = bЮ042EЮЮ042EЮЮЮ042E;
    switch (i * (b042EЮ042EЮ042EЮЮЮ042E + i) % b042E042EЮЮ042EЮЮЮ042E)
    {
    default: 
      bЮ042EЮЮ042EЮЮЮ042E = 79;
      bЮЮ042EЮ042EЮЮЮ042E = bВ04120412В0412ВВ04120412В();
    }
    return this.b042E042EЮЮЮЮЮЮ042E;
  }
  
  public String bВВВВВ0412В04120412В()
  {
    for (;;)
    {
      try
      {
        String str = this.bЮ042E042E042EЮЮЮЮ042E;
        int i = bЮ042EЮЮ042EЮЮЮ042E;
        switch (i * (b042EЮ042EЮ042EЮЮЮ042E + i) % b042E042EЮЮ042EЮЮЮ042E)
        {
        case 0: 
          bЮ042EЮЮ042EЮЮЮ042E = bВ04120412В0412ВВ04120412В();
          bЮЮ042EЮ042EЮЮЮ042E = 49;
          i = bЮ042EЮЮ042EЮЮЮ042E;
          switch (i * (b042EЮ042EЮ042EЮЮЮ042E + i) % b042E042EЮЮ042EЮЮЮ042E)
          {
          default: 
            bЮ042EЮЮ042EЮЮЮ042E = 4;
            bЮЮ042EЮ042EЮЮЮ042E = 13;
          }
          return str;
        }
      }
      catch (Exception localException)
      {
        throw localException;
      }
    }
  }
}
