package kkkkkk;

import java.util.concurrent.ExecutorService;
import java.util.concurrent.ScheduledThreadPoolExecutor;
import java.util.concurrent.TimeUnit;

public class bhhhbh
{
  private static final int b04490449щ044904490449044904490449 = 5;
  private static ScheduledThreadPoolExecutor b0449щ0449044904490449044904490449;
  private static final String b0449щщ044904490449044904490449;
  public static int b044C044Cььььььь = 2;
  public static int b044Cьььььььь = 0;
  public static int bщ04490449044904490449044904490449 = 87;
  private static final long bщ0449щ044904490449044904490449 = 60L;
  private static ExecutorService bщщ0449044904490449044904490449;
  public static int bь044Cььььььь = 1;
  
  static
  {
    throw new Runtime("d2j fail translate: java.lang.IndexOutOfBoundsException: fromIndex < 0: -1\n\tat java.util.BitSet.nextSetBit(BitSet.java:712)\n\tat com.googlecode.dex2jar.ir.ts.array.FillArrayTransformer.makeSureAllElementAreAssigned(FillArrayTransformer.java:505)\n\tat com.googlecode.dex2jar.ir.ts.array.FillArrayTransformer.transformReportChanged(FillArrayTransformer.java:123)\n\tat com.googlecode.dex2jar.ir.ts.StatedTransformer.transform(StatedTransformer.java:10)\n\tat com.googlecode.d2j.dex.Dex2jar$2.optimize(Dex2jar.java:149)\n\tat com.googlecode.d2j.dex.Dex2Asm.convertCode(Dex2Asm.java:414)\n\tat com.googlecode.d2j.dex.ExDex2Asm.convertCode(ExDex2Asm.java:42)\n\tat com.googlecode.d2j.dex.Dex2jar$2.convertCode(Dex2jar.java:128)\n\tat com.googlecode.d2j.dex.Dex2Asm.convertMethod(Dex2Asm.java:509)\n\tat com.googlecode.d2j.dex.Dex2Asm.convertClass(Dex2Asm.java:406)\n\tat com.googlecode.d2j.dex.Dex2Asm.convertDex(Dex2Asm.java:422)\n\tat com.googlecode.d2j.dex.Dex2jar.doTranslate(Dex2jar.java:172)\n\tat com.googlecode.d2j.dex.Dex2jar.to(Dex2jar.java:272)\n\tat com.googlecode.dex2jar.tools.Dex2jarCmd.doCommandLine(Dex2jarCmd.java:108)\n\tat com.googlecode.dex2jar.tools.BaseCmd.doMain(BaseCmd.java:288)\n\tat com.googlecode.dex2jar.tools.Dex2jarCmd.main(Dex2jarCmd.java:32)\n");
  }
  
  public bhhhbh() {}
  
  public static int b042804280428042804280428ШШШ0428()
  {
    return 2;
  }
  
  /* Error */
  private static void b04280428ШШШШ0428ШШ0428()
  {
    // Byte code:
    //   0: getstatic 47	kkkkkk/bhhhbh:b0449щ0449044904490449044904490449	Ljava/util/concurrent/ScheduledThreadPoolExecutor;
    //   3: ifnonnull +117 -> 120
    //   6: new 49	java/util/concurrent/ScheduledThreadPoolExecutor
    //   9: dup
    //   10: iconst_1
    //   11: invokespecial 52	java/util/concurrent/ScheduledThreadPoolExecutor:<init>	(I)V
    //   14: astore_3
    //   15: getstatic 54	kkkkkk/bhhhbh:bщ04490449044904490449044904490449	I
    //   18: istore_0
    //   19: getstatic 56	kkkkkk/bhhhbh:bь044Cььььььь	I
    //   22: istore_1
    //   23: getstatic 54	kkkkkk/bhhhbh:bщ04490449044904490449044904490449	I
    //   26: istore_2
    //   27: iload_2
    //   28: getstatic 56	kkkkkk/bhhhbh:bь044Cььььььь	I
    //   31: iload_2
    //   32: iadd
    //   33: imul
    //   34: getstatic 58	kkkkkk/bhhhbh:b044C044Cььььььь	I
    //   37: irem
    //   38: tableswitch	default:+18->56, 0:+28->66
    //   56: bipush 59
    //   58: putstatic 54	kkkkkk/bhhhbh:bщ04490449044904490449044904490449	I
    //   61: bipush 44
    //   63: putstatic 60	kkkkkk/bhhhbh:b044Cьььььььь	I
    //   66: iload_0
    //   67: iload_1
    //   68: iload_0
    //   69: iadd
    //   70: imul
    //   71: invokestatic 62	kkkkkk/bhhhbh:b042804280428042804280428ШШШ0428	()I
    //   74: irem
    //   75: tableswitch	default:+17->92, 0:+29->104
    //   92: invokestatic 65	kkkkkk/bhhhbh:bШ04280428042804280428ШШШ0428	()I
    //   95: putstatic 54	kkkkkk/bhhhbh:bщ04490449044904490449044904490449	I
    //   98: invokestatic 65	kkkkkk/bhhhbh:bШ04280428042804280428ШШШ0428	()I
    //   101: putstatic 60	kkkkkk/bhhhbh:b044Cьььььььь	I
    //   104: aload_3
    //   105: putstatic 47	kkkkkk/bhhhbh:b0449щ0449044904490449044904490449	Ljava/util/concurrent/ScheduledThreadPoolExecutor;
    //   108: getstatic 47	kkkkkk/bhhhbh:b0449щ0449044904490449044904490449	Ljava/util/concurrent/ScheduledThreadPoolExecutor;
    //   111: ldc2_w 20
    //   114: getstatic 71	java/util/concurrent/TimeUnit:SECONDS	Ljava/util/concurrent/TimeUnit;
    //   117: invokevirtual 75	java/util/concurrent/ScheduledThreadPoolExecutor:setKeepAliveTime	(JLjava/util/concurrent/TimeUnit;)V
    //   120: return
    //   121: astore_3
    //   122: aload_3
    //   123: athrow
    //   124: astore_3
    //   125: aload_3
    //   126: athrow
    // Local variable table:
    //   start	length	slot	name	signature
    //   18	53	0	i	int
    //   22	48	1	j	int
    //   26	8	2	k	int
    //   14	91	3	localScheduledThreadPoolExecutor	ScheduledThreadPoolExecutor
    //   121	2	3	localException1	Exception
    //   124	2	3	localException2	Exception
    // Exception table:
    //   from	to	target	type
    //   0	15	121	java/lang/Exception
    //   104	108	121	java/lang/Exception
    //   108	120	124	java/lang/Exception
  }
  
  /* Error */
  public static void b0428ШШШШШ0428ШШ0428(Runnable paramRunnable, long paramLong)
  {
    // Byte code:
    //   0: iconst_3
    //   1: istore_3
    //   2: lload_1
    //   3: lconst_0
    //   4: lcmp
    //   5: ifne +49 -> 54
    //   8: getstatic 54	kkkkkk/bhhhbh:bщ04490449044904490449044904490449	I
    //   11: getstatic 56	kkkkkk/bhhhbh:bь044Cььььььь	I
    //   14: iadd
    //   15: getstatic 54	kkkkkk/bhhhbh:bщ04490449044904490449044904490449	I
    //   18: imul
    //   19: getstatic 58	kkkkkk/bhhhbh:b044C044Cььььььь	I
    //   22: irem
    //   23: getstatic 60	kkkkkk/bhhhbh:b044Cьььььььь	I
    //   26: if_icmpeq +15 -> 41
    //   29: invokestatic 65	kkkkkk/bhhhbh:bШ04280428042804280428ШШШ0428	()I
    //   32: putstatic 54	kkkkkk/bhhhbh:bщ04490449044904490449044904490449	I
    //   35: invokestatic 65	kkkkkk/bhhhbh:bШ04280428042804280428ШШШ0428	()I
    //   38: putstatic 60	kkkkkk/bhhhbh:b044Cьььььььь	I
    //   41: aload_0
    //   42: invokestatic 81	kkkkkk/bhhhbh:bШШШШШШ0428ШШ0428	(Ljava/lang/Runnable;)V
    //   45: return
    //   46: astore_0
    //   47: invokestatic 65	kkkkkk/bhhhbh:bШ04280428042804280428ШШШ0428	()I
    //   50: putstatic 54	kkkkkk/bhhhbh:bщ04490449044904490449044904490449	I
    //   53: return
    //   54: invokestatic 83	kkkkkk/bhhhbh:b04280428ШШШШ0428ШШ0428	()V
    //   57: getstatic 47	kkkkkk/bhhhbh:b0449щ0449044904490449044904490449	Ljava/util/concurrent/ScheduledThreadPoolExecutor;
    //   60: aload_0
    //   61: lload_1
    //   62: getstatic 86	java/util/concurrent/TimeUnit:MILLISECONDS	Ljava/util/concurrent/TimeUnit;
    //   65: invokevirtual 90	java/util/concurrent/ScheduledThreadPoolExecutor:schedule	(Ljava/lang/Runnable;JLjava/util/concurrent/TimeUnit;)Ljava/util/concurrent/ScheduledFuture;
    //   68: pop
    //   69: iload_3
    //   70: iconst_0
    //   71: idiv
    //   72: istore_3
    //   73: goto -4 -> 69
    // Local variable table:
    //   start	length	slot	name	signature
    //   0	76	0	paramRunnable	Runnable
    //   0	76	1	paramLong	long
    //   1	72	3	i	int
    // Exception table:
    //   from	to	target	type
    //   69	73	46	java/lang/Exception
  }
  
  public static int bШ04280428042804280428ШШШ0428()
  {
    return 91;
  }
  
  /* Error */
  private static void bШ0428ШШШШ0428ШШ0428()
  {
    // Byte code:
    //   0: getstatic 93	kkkkkk/bhhhbh:bщщ0449044904490449044904490449	Ljava/util/concurrent/ExecutorService;
    //   3: astore_0
    //   4: getstatic 54	kkkkkk/bhhhbh:bщ04490449044904490449044904490449	I
    //   7: getstatic 56	kkkkkk/bhhhbh:bь044Cььььььь	I
    //   10: iadd
    //   11: getstatic 54	kkkkkk/bhhhbh:bщ04490449044904490449044904490449	I
    //   14: imul
    //   15: invokestatic 62	kkkkkk/bhhhbh:b042804280428042804280428ШШШ0428	()I
    //   18: irem
    //   19: getstatic 60	kkkkkk/bhhhbh:b044Cьььььььь	I
    //   22: if_icmpeq +14 -> 36
    //   25: bipush 16
    //   27: putstatic 54	kkkkkk/bhhhbh:bщ04490449044904490449044904490449	I
    //   30: invokestatic 65	kkkkkk/bhhhbh:bШ04280428042804280428ШШШ0428	()I
    //   33: putstatic 60	kkkkkk/bhhhbh:b044Cьььььььь	I
    //   36: aload_0
    //   37: ifnonnull +12 -> 49
    //   40: iconst_5
    //   41: invokestatic 99	java/util/concurrent/Executors:newFixedThreadPool	(I)Ljava/util/concurrent/ExecutorService;
    //   44: astore_0
    //   45: aload_0
    //   46: putstatic 93	kkkkkk/bhhhbh:bщщ0449044904490449044904490449	Ljava/util/concurrent/ExecutorService;
    //   49: return
    //   50: astore_0
    //   51: aload_0
    //   52: athrow
    //   53: astore_0
    //   54: aload_0
    //   55: athrow
    // Local variable table:
    //   start	length	slot	name	signature
    //   3	43	0	localExecutorService	ExecutorService
    //   50	2	0	localException1	Exception
    //   53	2	0	localException2	Exception
    // Exception table:
    //   from	to	target	type
    //   0	4	50	java/lang/Exception
    //   40	45	50	java/lang/Exception
    //   45	49	53	java/lang/Exception
  }
  
  public static void bШШ0428ШШШ0428ШШ0428()
  {
    try
    {
      if (b0449щ0449044904490449044904490449 != null)
      {
        xtxtxt.bии0438и04380438и0438ии(b0449щщ044904490449044904490449, gguuuu.bккккк043Aкк043A043A("%E1ABl746515-d1\026%)%#3)!\037~1\035\032+)#%", '', '\003'));
        b0449щ0449044904490449044904490449.shutdown();
        b0449щ0449044904490449044904490449.awaitTermination(1L, TimeUnit.SECONDS);
        b0449щ0449044904490449044904490449.shutdownNow();
        String str1 = b0449щщ044904490449044904490449;
        String str2 = gguuuu.bккккк043Aкк043A043A("a\004\b\002\013~zx3}z|{w{s+w\\kokiyogeEwc`qoik", 'õ', '\002');
        int i = bщ04490449044904490449044904490449;
        switch (i * (bь044Cььььььь + i) % b044C044Cььььььь)
        {
        default: 
          bщ04490449044904490449044904490449 = bШ04280428042804280428ШШШ0428();
          b044Cьььььььь = 40;
        }
        xtxtxt.bии0438и04380438и0438ии(str1, str2);
      }
      if (bщщ0449044904490449044904490449 != null)
      {
        xtxtxt.bии0438и04380438и0438ии(b0449щщ044904490449044904490449, gguuuu.bккккк043Aкк043A043A("w\030\004\024\025?\n\007\t\b\004\b7\004Z\rxu\007\005~\001", 'ì', '\003'));
        bщщ0449044904490449044904490449.shutdown();
        bщщ0449044904490449044904490449.awaitTermination(1L, TimeUnit.SECONDS);
        bщщ0449044904490449044904490449.shutdownNow();
        xtxtxt.bии0438и04380438и0438ии(b0449щщ044904490449044904490449, gguuuu.bк043Aккк043Aкк043A043A("l\021\027\023\036\024\022\022N\033\032\036\037\035#\035V%}2 \03722.2", '', '', '\003'));
      }
      return;
    }
    catch (InterruptedException localInterruptedException)
    {
      xtxtxt.bии0438043804380438и0438ии(b0449щщ044904490449044904490449, gguuuu.bккккк043Aкк043A043A("m\034\035\033\037M\032\031\035\036\034\"\034U{0\036\03500,02", '(', '\000'));
      return;
    }
    finally
    {
      b0449щ0449044904490449044904490449 = null;
      bщщ0449044904490449044904490449 = null;
    }
  }
  
  public static void bШШШШШШ0428ШШ0428(Runnable paramRunnable)
  {
    bШ0428ШШШШ0428ШШ0428();
    ExecutorService localExecutorService = bщщ0449044904490449044904490449;
    switch (0)
    {
    case 1: 
    default: 
      for (;;)
      {
        switch (0)
        {
        }
      }
    }
    if ((bщ04490449044904490449044904490449 + bь044Cььььььь) * bщ04490449044904490449044904490449 % b044C044Cььььььь != b044Cьььььььь)
    {
      int i = bщ04490449044904490449044904490449;
      switch (i * (bь044Cььььььь + i) % b044C044Cььььььь)
      {
      default: 
        bщ04490449044904490449044904490449 = 82;
        b044Cьььььььь = bШ04280428042804280428ШШШ0428();
      }
      bщ04490449044904490449044904490449 = bШ04280428042804280428ШШШ0428();
      b044Cьььььььь = 70;
    }
    localExecutorService.execute(paramRunnable);
  }
}
