package kkkkkk;

public enum brbrbb
{
  private final int mTabPosition;
  
  /* Error */
  static
  {
    // Byte code:
    //   0: new 2	kkkkkk/brbrbb
    //   3: dup
    //   4: ldc 18
    //   6: bipush 118
    //   8: iconst_0
    //   9: invokestatic 24	kkkkkk/gguuuu:bккккк043Aкк043A043A	(Ljava/lang/String;CC)Ljava/lang/String;
    //   12: iconst_0
    //   13: iconst_0
    //   14: invokespecial 28	kkkkkk/brbrbb:<init>	(Ljava/lang/String;II)V
    //   17: astore_1
    //   18: iconst_1
    //   19: tableswitch	default:+21->40, 0:+-1->18, 1:+48->67
    //   40: iconst_0
    //   41: tableswitch	default:+23->64, 0:+26->67, 1:+-23->18
    //   64: goto -24 -> 40
    //   67: invokestatic 32	kkkkkk/brbrbb:bъ044A044Aъъ044Aъ044Aъъ	()I
    //   70: invokestatic 35	kkkkkk/brbrbb:bъъ044Aъъ044Aъ044Aъъ	()I
    //   73: iadd
    //   74: invokestatic 32	kkkkkk/brbrbb:bъ044A044Aъъ044Aъ044Aъъ	()I
    //   77: imul
    //   78: invokestatic 38	kkkkkk/brbrbb:b044A044A044Aъъ044Aъ044Aъъ	()I
    //   81: irem
    //   82: invokestatic 41	kkkkkk/brbrbb:b044Aъ044Aъъ044Aъ044Aъъ	()I
    //   85: if_icmpeq +3 -> 88
    //   88: aload_1
    //   89: putstatic 43	kkkkkk/brbrbb:DEPOSIT_CHEQUE	Lkkkkkk/brbrbb;
    //   92: new 2	kkkkkk/brbrbb
    //   95: dup
    //   96: ldc 45
    //   98: bipush 87
    //   100: bipush 72
    //   102: iconst_3
    //   103: invokestatic 49	kkkkkk/gguuuu:bк043Aккк043Aкк043A043A	(Ljava/lang/String;CCC)Ljava/lang/String;
    //   106: iconst_1
    //   107: iconst_1
    //   108: invokespecial 28	kkkkkk/brbrbb:<init>	(Ljava/lang/String;II)V
    //   111: astore_1
    //   112: aload_1
    //   113: putstatic 51	kkkkkk/brbrbb:DEPOSIT_HISTORY	Lkkkkkk/brbrbb;
    //   116: getstatic 43	kkkkkk/brbrbb:DEPOSIT_CHEQUE	Lkkkkkk/brbrbb;
    //   119: astore_1
    //   120: getstatic 51	kkkkkk/brbrbb:DEPOSIT_HISTORY	Lkkkkkk/brbrbb;
    //   123: astore_2
    //   124: invokestatic 32	kkkkkk/brbrbb:bъ044A044Aъъ044Aъ044Aъъ	()I
    //   127: istore_0
    //   128: iload_0
    //   129: invokestatic 35	kkkkkk/brbrbb:bъъ044Aъъ044Aъ044Aъъ	()I
    //   132: iload_0
    //   133: iadd
    //   134: imul
    //   135: invokestatic 38	kkkkkk/brbrbb:b044A044A044Aъъ044Aъ044Aъъ	()I
    //   138: irem
    //   139: tableswitch	default:+17->156, 0:+17->156
    //   156: iconst_2
    //   157: anewarray 2	kkkkkk/brbrbb
    //   160: dup
    //   161: iconst_0
    //   162: aload_1
    //   163: aastore
    //   164: dup
    //   165: iconst_1
    //   166: aload_2
    //   167: aastore
    //   168: putstatic 53	kkkkkk/brbrbb:$VALUES	[Lkkkkkk/brbrbb;
    //   171: return
    //   172: astore_1
    //   173: aload_1
    //   174: athrow
    //   175: astore_1
    //   176: aload_1
    //   177: athrow
    // Local variable table:
    //   start	length	slot	name	signature
    //   127	8	0	i	int
    //   17	146	1	localBrbrbb1	brbrbb
    //   172	2	1	localException1	Exception
    //   175	2	1	localException2	Exception
    //   123	44	2	localBrbrbb2	brbrbb
    // Exception table:
    //   from	to	target	type
    //   0	18	172	java/lang/Exception
    //   112	124	172	java/lang/Exception
    //   156	171	172	java/lang/Exception
    //   88	112	175	java/lang/Exception
  }
  
  private brbrbb(int paramInt)
  {
    this.mTabPosition = paramInt;
  }
  
  public static int b044A044A044Aъъ044Aъ044Aъъ()
  {
    return 2;
  }
  
  public static int b044Aъ044Aъъ044Aъ044Aъъ()
  {
    return 0;
  }
  
  public static int bъ044A044Aъъ044Aъ044Aъъ()
  {
    return 97;
  }
  
  public static brbrbb bъ044Aъ044Aъ044Aъ044Aъъ(String paramString)
  {
    int i = bъ044A044Aъъ044Aъ044Aъъ();
    switch (i * (bъъ044Aъъ044Aъ044Aъъ() + i) % b044A044A044Aъъ044Aъ044Aъъ())
    {
    }
    try
    {
      paramString = (brbrbb)Enum.valueOf(brbrbb.class, paramString);
      return paramString;
    }
    catch (Exception paramString)
    {
      throw paramString;
    }
  }
  
  public static int bъъ044Aъъ044Aъ044Aъъ()
  {
    return 1;
  }
  
  public static brbrbb bъъъ044Aъ044Aъ044Aъъ(int paramInt)
  {
    int i = bъ044A044Aъъ044Aъ044Aъъ();
    switch (i * (bъъ044Aъъ044Aъ044Aъъ() + i) % b044A044A044Aъъ044Aъ044Aъъ())
    {
    }
    Object localObject = values();
    int j = localObject.length;
    i = 0;
    while (i < j)
    {
      brbrbb localBrbrbb = localObject[i];
      if (localBrbrbb.mTabPosition == paramInt)
      {
        paramInt = bъ044A044Aъъ044Aъ044Aъъ();
        switch (paramInt * (bъъ044Aъъ044Aъ044Aъъ() + paramInt) % b044A044A044Aъъ044Aъ044Aъъ())
        {
        }
        return localBrbrbb;
      }
      i += 1;
    }
    localObject = new IllegalArgumentException(gguuuu.bк043Aккк043Aкк043A043A("\0206?+751mC13qCCH?KAHHzOBJDCUGG", '9', '', '\003'));
    switch (1)
    {
    case 0: 
    default: 
      for (;;)
      {
        switch (0)
        {
        }
      }
    }
    throw ((Throwable)localObject);
  }
  
  public int b044Aъъ044Aъ044Aъ044Aъъ()
  {
    int i = this.mTabPosition;
    int j = bъ044A044Aъъ044Aъ044Aъъ();
    int k = bъъ044Aъъ044Aъ044Aъъ();
    int m = bъ044A044Aъъ044Aъ044Aъъ();
    int n = b044A044A044Aъъ044Aъ044Aъъ();
    int i1 = b044Aъ044Aъъ044Aъ044Aъъ();
    int i2 = bъ044A044Aъъ044Aъ044Aъъ();
    switch (i2 * (bъъ044Aъъ044Aъ044Aъъ() + i2) % b044A044A044Aъъ044Aъ044Aъъ())
    {
    }
    if ((j + k) * m % n != i1) {}
    return i;
  }
}
