package kkkkkk;

import android.support.annotation.NonNull;
import android.support.annotation.Nullable;
import com.mobile.business.statements.model.AmountDomainModel;
import java.io.Serializable;
import java.util.Iterator;
import java.util.List;
import java.util.Map;
import org.threeten.bp.ZonedDateTime;

public class cccrcc
  implements Serializable
{
  private static final String b042704270427Ч0427Ч0427Ч0427 = "\023~\013\025\006";
  private static final long serialVersionUID = -1042141477454416096L;
  private boolean b0427042704270427042704270427Ч0427;
  private ccrrcc b04270427042704270427Ч0427Ч0427 = ccrrcc.UNKNOWN;
  private AmountDomainModel b04270427042704270427ЧЧ04270427;
  private rrrrcc b0427042704270427Ч04270427Ч0427;
  private List<ooooii> b0427042704270427Ч0427Ч04270427;
  private boolean b0427042704270427ЧЧЧ04270427;
  private boolean b042704270427Ч042704270427Ч0427;
  private String b042704270427Ч0427ЧЧ04270427;
  private AmountDomainModel b042704270427ЧЧ04270427Ч0427;
  private AmountDomainModel b042704270427ЧЧ0427Ч04270427;
  private boolean b042704270427ЧЧЧЧ04270427;
  private boolean b04270427Ч0427042704270427Ч0427;
  private List<String> b04270427Ч04270427Ч0427Ч0427;
  private AmountDomainModel b04270427Ч04270427ЧЧ04270427;
  private ZonedDateTime b04270427Ч0427Ч04270427Ч0427;
  private boolean b04270427Ч0427Ч0427Ч04270427;
  private boolean b04270427Ч0427ЧЧЧ04270427;
  private boolean b04270427ЧЧ042704270427Ч0427;
  private ZonedDateTime b04270427ЧЧ0427ЧЧ04270427;
  private String b04270427ЧЧЧ04270427Ч0427;
  private String b04270427ЧЧЧ0427Ч04270427;
  private String b04270427ЧЧЧЧЧ04270427;
  private boolean b0427Ч04270427042704270427Ч0427;
  private ZonedDateTime b0427Ч042704270427Ч0427Ч0427;
  private boolean b0427Ч042704270427ЧЧ04270427;
  private int b0427Ч04270427Ч04270427Ч0427;
  private String b0427Ч04270427Ч0427Ч04270427;
  private boolean b0427Ч04270427ЧЧЧ04270427;
  private boolean b0427Ч0427Ч042704270427Ч0427;
  private List<iiiioi> b0427Ч0427Ч0427ЧЧ04270427;
  private boolean b0427Ч0427ЧЧ04270427Ч0427;
  private String b0427Ч0427ЧЧ0427Ч04270427;
  private boolean b0427Ч0427ЧЧЧЧ04270427;
  private boolean b0427ЧЧ0427042704270427Ч0427;
  private String b0427ЧЧ04270427Ч0427Ч0427;
  private boolean b0427ЧЧ04270427ЧЧ04270427;
  private boolean b0427ЧЧ0427Ч04270427Ч0427;
  private boolean b0427ЧЧ0427Ч0427Ч04270427;
  private boolean b0427ЧЧ0427ЧЧЧ04270427;
  private boolean b0427ЧЧЧ042704270427Ч0427;
  private boolean b0427ЧЧЧ04270427Ч04270427;
  private AmountDomainModel b0427ЧЧЧ0427ЧЧ04270427;
  private AmountDomainModel b0427ЧЧЧЧ04270427Ч0427;
  private List<String> b0427ЧЧЧЧ0427Ч04270427;
  private boolean b0427ЧЧЧЧЧЧ04270427;
  private boolean bЧ042704270427042704270427Ч0427;
  private boolean bЧ0427042704270427Ч0427Ч0427;
  private String bЧ0427042704270427ЧЧ04270427;
  private String bЧ042704270427Ч04270427Ч0427;
  private ZonedDateTime bЧ042704270427Ч0427Ч04270427;
  private boolean bЧ042704270427ЧЧЧ04270427;
  private boolean bЧ04270427Ч042704270427Ч0427;
  private String bЧ04270427Ч0427ЧЧ04270427;
  private AmountDomainModel bЧ04270427ЧЧ04270427Ч0427;
  private String bЧ04270427ЧЧ0427Ч04270427;
  private boolean bЧ04270427ЧЧЧЧ04270427;
  private boolean bЧ0427Ч0427042704270427Ч0427;
  private String bЧ0427Ч04270427Ч0427Ч0427;
  private boolean bЧ0427Ч04270427ЧЧ04270427;
  private boolean bЧ0427Ч0427Ч04270427Ч0427;
  private boolean bЧ0427Ч0427Ч0427Ч04270427;
  private boolean bЧ0427Ч0427ЧЧЧ04270427;
  private List<String> bЧ0427ЧЧ042704270427Ч0427;
  private AmountDomainModel bЧ0427ЧЧ0427ЧЧ04270427;
  private boolean bЧ0427ЧЧЧ04270427Ч0427;
  private List<String> bЧ0427ЧЧЧ0427Ч04270427;
  private ZonedDateTime bЧ0427ЧЧЧЧЧ04270427;
  private boolean bЧЧ04270427042704270427Ч0427;
  private String bЧЧ042704270427Ч0427Ч0427;
  private String bЧЧ042704270427ЧЧ04270427;
  private boolean bЧЧ04270427Ч04270427Ч0427;
  private boolean bЧЧ04270427Ч0427Ч04270427;
  private boolean bЧЧ04270427ЧЧЧ04270427;
  private boolean bЧЧ0427Ч042704270427Ч0427;
  private iiooii bЧЧ0427Ч0427ЧЧ04270427;
  private boolean bЧЧ0427ЧЧ04270427Ч0427;
  private String bЧЧ0427ЧЧ0427Ч04270427;
  private String bЧЧ0427ЧЧЧЧ04270427;
  private boolean bЧЧЧ0427042704270427Ч0427;
  private boolean bЧЧЧ04270427Ч0427Ч0427;
  private boolean bЧЧЧ04270427ЧЧ04270427;
  private boolean bЧЧЧ0427Ч04270427Ч0427;
  private String bЧЧЧ0427Ч0427Ч04270427;
  private boolean bЧЧЧ0427ЧЧЧ04270427;
  private crrrcc bЧЧЧЧ042704270427Ч0427;
  private boolean bЧЧЧЧ04270427Ч04270427;
  private ZonedDateTime bЧЧЧЧ0427ЧЧ04270427;
  private AmountDomainModel bЧЧЧЧЧ04270427Ч0427;
  private boolean bЧЧЧЧЧ0427Ч04270427;
  private boolean bЧЧЧЧЧЧЧ04270427;
  
  static
  {
    try
    {
      String str = b042704270427Ч0427Ч0427Ч0427;
      int i = bжж0436жжжжж04360436();
      switch (i * (b0436ж0436жжжжж04360436() + i) % b04360436жжжжжж04360436())
      {
      }
      if ((bжж0436жжжжж04360436() + b0436ж0436жжжжж04360436()) * bжж0436жжжжж04360436() % b04360436жжжжжж04360436() != bж0436жжжжжж04360436()) {}
      b042704270427Ч0427Ч0427Ч0427 = gguuuu.bккккк043Aкк043A043A(str, '^', '\001');
      return;
    }
    catch (Exception localException)
    {
      throw localException;
    }
  }
  
  public cccrcc() {}
  
  public static int b04360436жжжжжж04360436()
  {
    return 2;
  }
  
  public static int b0436ж0436жжжжж04360436()
  {
    return 1;
  }
  
  /* Error */
  public static cccrcc bж04360436жжжжж04360436(ppkkkk paramPpkkkk)
  {
    // Byte code:
    //   0: iconst_3
    //   1: istore_1
    //   2: new 2	kkkkkk/cccrcc
    //   5: dup
    //   6: invokespecial 155	kkkkkk/cccrcc:<init>	()V
    //   9: astore_3
    //   10: aload_3
    //   11: aload_0
    //   12: invokevirtual 161	kkkkkk/ppkkkk:bж04360436жжжж0436ж0436	()Ljava/lang/String;
    //   15: invokevirtual 165	kkkkkk/cccrcc:bжж04360436043604360436ж04360436	(Ljava/lang/String;)V
    //   18: aload_3
    //   19: aload_0
    //   20: invokevirtual 168	kkkkkk/ppkkkk:bжж04360436043604360436жж0436	()Ljava/lang/String;
    //   23: invokevirtual 171	kkkkkk/cccrcc:bж04360436жж04360436ж04360436	(Ljava/lang/String;)V
    //   26: aload_3
    //   27: aload_0
    //   28: invokevirtual 174	kkkkkk/ppkkkk:b0436ж04360436043604360436жж0436	()Ljava/lang/String;
    //   31: invokevirtual 177	kkkkkk/cccrcc:b043604360436жж04360436ж04360436	(Ljava/lang/String;)V
    //   34: aload_3
    //   35: aload_0
    //   36: invokevirtual 180	kkkkkk/ppkkkk:bж0436жжж0436ж0436ж0436	()Ljava/lang/String;
    //   39: invokevirtual 183	kkkkkk/cccrcc:b0436043604360436ж0436ж043604360436	(Ljava/lang/String;)V
    //   42: aload_3
    //   43: aload_0
    //   44: invokevirtual 186	kkkkkk/ppkkkk:bжж04360436жжж0436ж0436	()Ljava/lang/String;
    //   47: invokevirtual 189	kkkkkk/cccrcc:b0436ж0436жжжж043604360436	(Ljava/lang/String;)V
    //   50: aload_3
    //   51: aload_0
    //   52: invokevirtual 193	kkkkkk/ppkkkk:bжжжжжжж0436ж0436	()Lkkkkkk/pkkkkk;
    //   55: invokestatic 197	kkkkkk/ccrrcc:b043Fп043Fп043Fппппп	(Lkkkkkk/pkkkkk;)Lkkkkkk/ccrrcc;
    //   58: invokevirtual 201	kkkkkk/cccrcc:bжж04360436ж04360436ж04360436	(Lkkkkkk/ccrrcc;)V
    //   61: aload_3
    //   62: aload_0
    //   63: invokevirtual 205	kkkkkk/ppkkkk:b0436жжжжжж0436ж0436	()Lkkkkkk/crcccc;
    //   66: invokestatic 211	com/mobile/business/statements/model/AmountDomainModel:fromBalance	(Lkkkkkk/crcccc;)Lcom/mobile/business/statements/model/AmountDomainModel;
    //   69: invokevirtual 215	kkkkkk/cccrcc:b0436ж04360436ж04360436ж04360436	(Lcom/mobile/business/statements/model/AmountDomainModel;)V
    //   72: aload_3
    //   73: aload_0
    //   74: invokevirtual 218	kkkkkk/ppkkkk:bж0436жжжжж0436ж0436	()Lkkkkkk/crcccc;
    //   77: invokestatic 211	com/mobile/business/statements/model/AmountDomainModel:fromBalance	(Lkkkkkk/crcccc;)Lcom/mobile/business/statements/model/AmountDomainModel;
    //   80: invokevirtual 221	kkkkkk/cccrcc:bж043604360436ж04360436ж04360436	(Lcom/mobile/business/statements/model/AmountDomainModel;)V
    //   83: aload_3
    //   84: aload_0
    //   85: invokevirtual 224	kkkkkk/ppkkkk:b04360436жжжжж0436ж0436	()Ljava/lang/String;
    //   88: invokevirtual 227	kkkkkk/cccrcc:bжжжж043604360436ж04360436	(Ljava/lang/String;)V
    //   91: aload_3
    //   92: aload_0
    //   93: invokevirtual 231	kkkkkk/ppkkkk:b043604360436жжжж0436ж0436	()Lkkkkkk/ccrccc;
    //   96: invokestatic 237	kkkkkk/rrrrcc:bпппп043F043Fпппп	(Lkkkkkk/ccrccc;)Lkkkkkk/rrrrcc;
    //   99: invokevirtual 241	kkkkkk/cccrcc:b0436ж04360436043604360436ж04360436	(Lkkkkkk/rrrrcc;)V
    //   102: aload_3
    //   103: aload_0
    //   104: invokevirtual 244	kkkkkk/ppkkkk:b04360436ж04360436жж0436ж0436	()Lkkkkkk/crcccc;
    //   107: invokestatic 211	com/mobile/business/statements/model/AmountDomainModel:fromBalance	(Lkkkkkk/crcccc;)Lcom/mobile/business/statements/model/AmountDomainModel;
    //   110: invokevirtual 247	kkkkkk/cccrcc:bж04360436жж0436ж043604360436	(Lcom/mobile/business/statements/model/AmountDomainModel;)V
    //   113: aload_3
    //   114: aload_0
    //   115: invokevirtual 250	kkkkkk/ppkkkk:b0436ж0436жж0436ж0436ж0436	()Ljava/lang/String;
    //   118: invokevirtual 253	kkkkkk/cccrcc:bжжж043604360436ж043604360436	(Ljava/lang/String;)V
    //   121: invokestatic 126	kkkkkk/cccrcc:bжж0436жжжжж04360436	()I
    //   124: invokestatic 129	kkkkkk/cccrcc:b0436ж0436жжжжж04360436	()I
    //   127: iadd
    //   128: invokestatic 126	kkkkkk/cccrcc:bжж0436жжжжж04360436	()I
    //   131: imul
    //   132: invokestatic 132	kkkkkk/cccrcc:b04360436жжжжжж04360436	()I
    //   135: irem
    //   136: invokestatic 135	kkkkkk/cccrcc:bж0436жжжжжж04360436	()I
    //   139: if_icmpeq +3 -> 142
    //   142: aload_3
    //   143: aload_0
    //   144: invokevirtual 257	kkkkkk/ppkkkk:bж04360436жж0436ж0436ж0436	()Lorg/threeten/bp/ZonedDateTime;
    //   147: invokevirtual 261	kkkkkk/cccrcc:b0436жж043604360436ж043604360436	(Lorg/threeten/bp/ZonedDateTime;)V
    //   150: aload_3
    //   151: aload_0
    //   152: invokevirtual 264	kkkkkk/ppkkkk:bж043604360436жжж0436ж0436	()Lorg/threeten/bp/ZonedDateTime;
    //   155: invokevirtual 267	kkkkkk/cccrcc:b04360436жж0436жж043604360436	(Lorg/threeten/bp/ZonedDateTime;)V
    //   158: aload_3
    //   159: aload_0
    //   160: invokevirtual 161	kkkkkk/ppkkkk:bж04360436жжжж0436ж0436	()Ljava/lang/String;
    //   163: invokevirtual 165	kkkkkk/cccrcc:bжж04360436043604360436ж04360436	(Ljava/lang/String;)V
    //   166: aload_3
    //   167: aload_0
    //   168: invokestatic 273	kkkkkk/crrrcc:b043F043Fппп043Fпппп	(Lkkkkkk/ppkkkk;)Lkkkkkk/crrrcc;
    //   171: invokevirtual 277	kkkkkk/cccrcc:bж043604360436043604360436ж04360436	(Lkkkkkk/crrrcc;)V
    //   174: aload_3
    //   175: aload_0
    //   176: invokevirtual 280	kkkkkk/ppkkkk:b04360436жжж0436ж0436ж0436	()Lkkkkkk/crcccc;
    //   179: invokestatic 211	com/mobile/business/statements/model/AmountDomainModel:fromBalance	(Lkkkkkk/crcccc;)Lcom/mobile/business/statements/model/AmountDomainModel;
    //   182: invokevirtual 283	kkkkkk/cccrcc:bжжжж04360436ж043604360436	(Lcom/mobile/business/statements/model/AmountDomainModel;)V
    //   185: aload_3
    //   186: aload_0
    //   187: invokevirtual 286	kkkkkk/ppkkkk:bжж043604360436жж0436ж0436	()Lkkkkkk/crcccc;
    //   190: invokestatic 211	com/mobile/business/statements/model/AmountDomainModel:fromBalance	(Lkkkkkk/crcccc;)Lcom/mobile/business/statements/model/AmountDomainModel;
    //   193: invokevirtual 289	kkkkkk/cccrcc:bжж0436ж043604360436ж04360436	(Lcom/mobile/business/statements/model/AmountDomainModel;)V
    //   196: aload_3
    //   197: aload_0
    //   198: invokevirtual 292	kkkkkk/ppkkkk:b04360436ж0436жжж0436ж0436	()Lkkkkkk/crcccc;
    //   201: invokestatic 211	com/mobile/business/statements/model/AmountDomainModel:fromBalance	(Lkkkkkk/crcccc;)Lcom/mobile/business/statements/model/AmountDomainModel;
    //   204: invokevirtual 295	kkkkkk/cccrcc:b04360436жж043604360436ж04360436	(Lcom/mobile/business/statements/model/AmountDomainModel;)V
    //   207: aload_3
    //   208: aload_0
    //   209: invokevirtual 298	kkkkkk/ppkkkk:bжжж04360436жж0436ж0436	()Lkkkkkk/crcccc;
    //   212: invokestatic 211	com/mobile/business/statements/model/AmountDomainModel:fromBalance	(Lkkkkkk/crcccc;)Lcom/mobile/business/statements/model/AmountDomainModel;
    //   215: invokevirtual 301	kkkkkk/cccrcc:b0436жжжж0436ж043604360436	(Lcom/mobile/business/statements/model/AmountDomainModel;)V
    //   218: aload_3
    //   219: aload_0
    //   220: invokevirtual 304	kkkkkk/ppkkkk:bж0436жж0436жж0436ж0436	()Lkkkkkk/crcccc;
    //   223: invokestatic 211	com/mobile/business/statements/model/AmountDomainModel:fromBalance	(Lkkkkkk/crcccc;)Lcom/mobile/business/statements/model/AmountDomainModel;
    //   226: invokevirtual 307	kkkkkk/cccrcc:b0436ж0436ж0436жж043604360436	(Lcom/mobile/business/statements/model/AmountDomainModel;)V
    //   229: aload_3
    //   230: aload_0
    //   231: invokevirtual 310	kkkkkk/ppkkkk:b04360436жж0436жж0436ж0436	()Lorg/threeten/bp/ZonedDateTime;
    //   234: invokevirtual 313	kkkkkk/cccrcc:b043604360436ж0436жж043604360436	(Lorg/threeten/bp/ZonedDateTime;)V
    //   237: aload_3
    //   238: aload_0
    //   239: invokevirtual 317	kkkkkk/ppkkkk:b0436043604360436жжж0436ж0436	()Ljava/util/List;
    //   242: aload_0
    //   243: invokevirtual 320	kkkkkk/ppkkkk:bжжжж0436жж0436ж0436	()Ljava/util/List;
    //   246: invokevirtual 324	kkkkkk/cccrcc:b0436жж0436ж04360436ж04360436	(Ljava/util/List;Ljava/util/List;)V
    //   249: aload_3
    //   250: aload_0
    //   251: invokevirtual 328	kkkkkk/ppkkkk:b04360436ж0436ж0436ж0436ж0436	()Z
    //   254: invokevirtual 332	kkkkkk/cccrcc:b04360436ж0436ж04360436ж04360436	(Z)V
    //   257: aload_3
    //   258: aload_0
    //   259: invokevirtual 335	kkkkkk/ppkkkk:b0436ж0436жжж04360436ж0436	()Z
    //   262: invokevirtual 338	kkkkkk/cccrcc:bж0436043604360436жж043604360436	(Z)V
    //   265: aload_3
    //   266: aload_0
    //   267: invokevirtual 341	kkkkkk/ppkkkk:bжж0436ж04360436ж0436ж0436	()Z
    //   270: invokevirtual 344	kkkkkk/cccrcc:bж0436ж0436043604360436ж04360436	(Z)V
    //   273: aload_3
    //   274: aload_0
    //   275: invokevirtual 347	kkkkkk/ppkkkk:b0436043604360436ж0436ж0436ж0436	()Z
    //   278: invokevirtual 350	kkkkkk/cccrcc:b0436ж0436ж043604360436ж04360436	(Z)V
    //   281: aload_3
    //   282: aload_0
    //   283: invokevirtual 353	kkkkkk/ppkkkk:b043604360436ж04360436ж0436ж0436	()Z
    //   286: invokevirtual 356	kkkkkk/cccrcc:bжжж0436жжж043604360436	(Z)V
    //   289: aload_3
    //   290: aload_0
    //   291: invokevirtual 359	kkkkkk/ppkkkk:b0436жж043604360436ж0436ж0436	()Z
    //   294: invokevirtual 362	kkkkkk/cccrcc:bж0436ж0436жжж043604360436	(Z)V
    //   297: aload_3
    //   298: aload_0
    //   299: invokevirtual 365	kkkkkk/ppkkkk:bж04360436043604360436ж0436ж0436	()Z
    //   302: invokevirtual 368	kkkkkk/cccrcc:b0436043604360436жжж043604360436	(Z)V
    //   305: aload_3
    //   306: aload_0
    //   307: invokevirtual 371	kkkkkk/ppkkkk:b043604360436043604360436ж0436ж0436	()Z
    //   310: invokevirtual 374	kkkkkk/cccrcc:bжжжж0436жж043604360436	(Z)V
    //   313: aload_3
    //   314: aload_0
    //   315: invokevirtual 377	kkkkkk/ppkkkk:b0436ж04360436ж0436ж0436ж0436	()Z
    //   318: invokevirtual 380	kkkkkk/cccrcc:b0436жжж043604360436ж04360436	(Z)V
    //   321: aload_3
    //   322: aload_0
    //   323: invokevirtual 383	kkkkkk/ppkkkk:b0436ж0436ж0436ж04360436ж0436	()Z
    //   326: invokevirtual 386	kkkkkk/cccrcc:bжж0436043604360436ж043604360436	(Z)V
    //   329: aload_3
    //   330: aload_0
    //   331: invokevirtual 389	kkkkkk/ppkkkk:bжж0436043604360436ж0436ж0436	()Z
    //   334: invokevirtual 392	kkkkkk/cccrcc:b0436ж04360436жжж043604360436	(Z)V
    //   337: aload_3
    //   338: aload_0
    //   339: invokevirtual 395	kkkkkk/ppkkkk:b0436жжжжж04360436ж0436	()Z
    //   342: invokevirtual 398	kkkkkk/cccrcc:bж0436жж0436жж043604360436	(Z)V
    //   345: aload_3
    //   346: aload_0
    //   347: invokevirtual 401	kkkkkk/ppkkkk:bж04360436ж0436ж04360436ж0436	()Z
    //   350: invokevirtual 404	kkkkkk/cccrcc:b0436ж0436043604360436ж043604360436	(Z)V
    //   353: aload_3
    //   354: aload_0
    //   355: invokevirtual 407	kkkkkk/ppkkkk:bж043604360436ж0436ж0436ж0436	()Z
    //   358: invokevirtual 410	kkkkkk/cccrcc:bж0436жж043604360436ж04360436	(Z)V
    //   361: aload_3
    //   362: aload_0
    //   363: invokevirtual 413	kkkkkk/ppkkkk:b0436жжж04360436ж0436ж0436	()Z
    //   366: invokevirtual 416	kkkkkk/cccrcc:b043604360436ж043604360436ж04360436	(Z)V
    //   369: aload_3
    //   370: aload_0
    //   371: invokevirtual 419	kkkkkk/ppkkkk:bж0436жжжж04360436ж0436	()Z
    //   374: invokevirtual 422	kkkkkk/cccrcc:bж04360436ж0436жж043604360436	(Z)V
    //   377: aload_3
    //   378: aload_0
    //   379: invokevirtual 425	kkkkkk/ppkkkk:bжжж0436жж04360436ж0436	()Z
    //   382: invokevirtual 428	kkkkkk/cccrcc:b04360436жжж0436ж043604360436	(Z)V
    //   385: aload_3
    //   386: aload_0
    //   387: invokevirtual 431	kkkkkk/ppkkkk:b0436ж0436043604360436ж0436ж0436	()Z
    //   390: invokevirtual 434	kkkkkk/cccrcc:bж043604360436жжж043604360436	(Z)V
    //   393: aload_3
    //   394: aload_0
    //   395: invokevirtual 437	kkkkkk/ppkkkk:b0436ж0436ж04360436ж0436ж0436	()Z
    //   398: invokevirtual 440	kkkkkk/cccrcc:b0436043604360436043604360436ж04360436	(Z)V
    //   401: aload_3
    //   402: aload_0
    //   403: invokevirtual 443	kkkkkk/ppkkkk:b04360436ж043604360436ж0436ж0436	()Z
    //   406: invokevirtual 446	kkkkkk/cccrcc:bжж04360436жжж043604360436	(Z)V
    //   409: aload_3
    //   410: aload_0
    //   411: invokevirtual 449	kkkkkk/ppkkkk:bж0436ж0436жж04360436ж0436	()Z
    //   414: invokevirtual 452	kkkkkk/cccrcc:b043604360436жж0436ж043604360436	(Z)V
    //   417: aload_3
    //   418: aload_0
    //   419: invokevirtual 455	kkkkkk/ppkkkk:b043604360436жжж04360436ж0436	()Z
    //   422: invokevirtual 458	kkkkkk/cccrcc:bжжжжж0436ж043604360436	(Z)V
    //   425: aload_3
    //   426: aload_0
    //   427: invokevirtual 461	kkkkkk/ppkkkk:bж04360436жжж04360436ж0436	()Z
    //   430: invokevirtual 464	kkkkkk/cccrcc:b04360436043604360436жж043604360436	(Z)V
    //   433: aload_3
    //   434: aload_0
    //   435: invokevirtual 467	kkkkkk/ppkkkk:bжж04360436жж04360436ж0436	()Z
    //   438: invokevirtual 470	kkkkkk/cccrcc:bж043604360436ж0436ж043604360436	(Z)V
    //   441: aload_3
    //   442: aload_0
    //   443: invokevirtual 473	kkkkkk/ppkkkk:bж04360436ж04360436ж0436ж0436	()Z
    //   446: invokevirtual 476	kkkkkk/cccrcc:b043604360436жжжж043604360436	(Z)V
    //   449: aload_3
    //   450: aload_0
    //   451: invokevirtual 479	kkkkkk/ppkkkk:bж0436жж04360436ж0436ж0436	()Z
    //   454: invokevirtual 482	kkkkkk/cccrcc:bжжж0436043604360436ж04360436	(Z)V
    //   457: aload_3
    //   458: aload_0
    //   459: invokevirtual 485	kkkkkk/ppkkkk:b0436жж0436ж0436ж0436ж0436	()Z
    //   462: invokevirtual 488	kkkkkk/cccrcc:b0436ж0436жж04360436ж04360436	(Z)V
    //   465: aload_3
    //   466: aload_0
    //   467: invokevirtual 491	kkkkkk/ppkkkk:b0436ж04360436жж04360436ж0436	()Z
    //   470: invokevirtual 494	kkkkkk/cccrcc:bж0436жж04360436ж043604360436	(Z)V
    //   473: aload_3
    //   474: aload_0
    //   475: invokevirtual 497	kkkkkk/ppkkkk:bжжжж04360436ж0436ж0436	()Z
    //   478: invokevirtual 500	kkkkkk/cccrcc:bж04360436ж043604360436ж04360436	(Z)V
    //   481: aload_3
    //   482: aload_0
    //   483: invokevirtual 503	kkkkkk/ppkkkk:bжжжж0436ж04360436ж0436	()Z
    //   486: invokevirtual 506	kkkkkk/cccrcc:bжж0436ж04360436ж043604360436	(Z)V
    //   489: aload_3
    //   490: aload_0
    //   491: invokevirtual 509	kkkkkk/ppkkkk:bж0436ж043604360436ж0436ж0436	()Z
    //   494: invokevirtual 512	kkkkkk/cccrcc:b04360436ж0436жжж043604360436	(Z)V
    //   497: aload_3
    //   498: aload_0
    //   499: invokevirtual 515	kkkkkk/ppkkkk:bжжжжжж04360436ж0436	()Z
    //   502: invokevirtual 518	kkkkkk/cccrcc:b0436жжж0436жж043604360436	(Z)V
    //   505: aload_3
    //   506: aload_0
    //   507: invokevirtual 521	kkkkkk/ppkkkk:bжж04360436ж0436ж0436ж0436	()Z
    //   510: invokevirtual 524	kkkkkk/cccrcc:b0436043604360436ж04360436ж04360436	(Z)V
    //   513: aload_3
    //   514: aload_0
    //   515: invokevirtual 527	kkkkkk/ppkkkk:bж0436ж0436жжж0436ж0436	()Lorg/threeten/bp/ZonedDateTime;
    //   518: invokevirtual 530	kkkkkk/cccrcc:bжж0436жжжж043604360436	(Lorg/threeten/bp/ZonedDateTime;)V
    //   521: aload_3
    //   522: aload_0
    //   523: invokevirtual 533	kkkkkk/ppkkkk:bж0436ж0436ж0436ж0436ж0436	()Z
    //   526: invokevirtual 536	kkkkkk/cccrcc:b0436жжжжжж043604360436	(Z)V
    //   529: aload_3
    //   530: aload_0
    //   531: invokevirtual 539	kkkkkk/ppkkkk:bж043604360436жж04360436ж0436	()Z
    //   534: invokevirtual 542	kkkkkk/cccrcc:b04360436жжжжж043604360436	(Z)V
    //   537: aload_3
    //   538: aload_0
    //   539: invokevirtual 545	kkkkkk/ppkkkk:bжжж043604360436ж0436ж0436	()Z
    //   542: invokevirtual 548	kkkkkk/cccrcc:b0436жж0436жжж043604360436	(Z)V
    //   545: aload_3
    //   546: aload_0
    //   547: invokevirtual 551	kkkkkk/ppkkkk:b04360436ж0436жж04360436ж0436	()Z
    //   550: invokevirtual 554	kkkkkk/cccrcc:bжжж0436ж0436ж043604360436	(Z)V
    //   553: aload_3
    //   554: aload_0
    //   555: invokevirtual 557	kkkkkk/ppkkkk:bжж0436ж0436ж04360436ж0436	()Z
    //   558: invokevirtual 560	kkkkkk/cccrcc:b04360436ж043604360436ж043604360436	(Z)V
    //   561: aload_3
    //   562: aload_0
    //   563: invokevirtual 563	kkkkkk/ppkkkk:b0436жж0436жж04360436ж0436	()Z
    //   566: invokevirtual 566	kkkkkk/cccrcc:bжж0436жж0436ж043604360436	(Z)V
    //   569: aload_3
    //   570: aload_0
    //   571: invokevirtual 569	kkkkkk/ppkkkk:bж0436ж04360436жж0436ж0436	()Ljava/lang/String;
    //   574: invokevirtual 572	kkkkkk/cccrcc:b0436ж0436жж0436ж043604360436	(Ljava/lang/String;)V
    //   577: aload_3
    //   578: aload_0
    //   579: invokevirtual 575	kkkkkk/ppkkkk:bжжж0436ж0436ж0436ж0436	()Z
    //   582: invokevirtual 578	kkkkkk/cccrcc:bжж0436жж04360436ж04360436	(Z)V
    //   585: aload_3
    //   586: aload_0
    //   587: invokevirtual 581	kkkkkk/ppkkkk:b043604360436ж0436жж0436ж0436	()Ljava/lang/String;
    //   590: invokevirtual 584	kkkkkk/cccrcc:b0436ж043604360436жж043604360436	(Ljava/lang/String;)V
    //   593: aload_3
    //   594: aload_0
    //   595: invokevirtual 587	kkkkkk/ppkkkk:bжж0436жж0436ж0436ж0436	()Ljava/lang/String;
    //   598: invokevirtual 590	kkkkkk/cccrcc:b0436жжж04360436ж043604360436	(Ljava/lang/String;)V
    //   601: aload_3
    //   602: aload_0
    //   603: invokevirtual 593	kkkkkk/ppkkkk:b0436ж04360436жжж0436ж0436	()Ljava/lang/String;
    //   606: invokevirtual 596	kkkkkk/cccrcc:bж04360436жжжж043604360436	(Ljava/lang/String;)V
    //   609: aload_3
    //   610: aload_0
    //   611: invokevirtual 599	kkkkkk/ppkkkk:b0436жжж0436жж0436ж0436	()Lkkkkkk/crcccc;
    //   614: invokestatic 211	com/mobile/business/statements/model/AmountDomainModel:fromBalance	(Lkkkkkk/crcccc;)Lcom/mobile/business/statements/model/AmountDomainModel;
    //   617: invokevirtual 602	kkkkkk/cccrcc:bжж0436ж0436жж043604360436	(Lcom/mobile/business/statements/model/AmountDomainModel;)V
    //   620: aload_3
    //   621: aload_0
    //   622: invokevirtual 605	kkkkkk/ppkkkk:b0436жж04360436жж0436ж0436	()Ljava/lang/String;
    //   625: invokevirtual 608	kkkkkk/cccrcc:bж0436жжж0436ж043604360436	(Ljava/lang/String;)V
    //   628: aload_3
    //   629: aload_0
    //   630: invokevirtual 612	kkkkkk/ppkkkk:bж04360436ж0436жж0436ж0436	()Lkkkkkk/vxxvvv;
    //   633: invokestatic 618	kkkkkk/iiooii:bЙЙЙ041904190419ЙЙ04190419	(Lkkkkkk/vxxvvv;)Lkkkkkk/iiooii;
    //   636: invokevirtual 622	kkkkkk/cccrcc:bжжж04360436жж043604360436	(Lkkkkkk/iiooii;)V
    //   639: aload_3
    //   640: aload_0
    //   641: invokevirtual 625	kkkkkk/ppkkkk:b0436ж0436ж0436жж0436ж0436	()Ljava/lang/String;
    //   644: invokevirtual 628	kkkkkk/cccrcc:bжж043604360436жж043604360436	(Ljava/lang/String;)V
    //   647: aload_3
    //   648: aload_0
    //   649: invokevirtual 631	kkkkkk/ppkkkk:bжж0436жжж04360436ж0436	()Z
    //   652: invokevirtual 634	kkkkkk/cccrcc:bж0436ж04360436жж043604360436	(Z)V
    //   655: aload_3
    //   656: aload_0
    //   657: invokevirtual 637	kkkkkk/ppkkkk:b04360436жжжж04360436ж0436	()Z
    //   660: invokevirtual 640	kkkkkk/cccrcc:b0436жж04360436жж043604360436	(Z)V
    //   663: aload_3
    //   664: new 642	java/util/ArrayList
    //   667: dup
    //   668: invokespecial 643	java/util/ArrayList:<init>	()V
    //   671: putfield 645	kkkkkk/cccrcc:b0427042704270427Ч0427Ч04270427	Ljava/util/List;
    //   674: aload_0
    //   675: invokevirtual 648	kkkkkk/ppkkkk:b043604360436жж0436ж0436ж0436	()Ljava/util/List;
    //   678: ifnull +215 -> 893
    //   681: aload_0
    //   682: invokevirtual 648	kkkkkk/ppkkkk:b043604360436жж0436ж0436ж0436	()Ljava/util/List;
    //   685: invokeinterface 654 1 0
    //   690: astore 4
    //   692: aload 4
    //   694: invokeinterface 659 1 0
    //   699: ifeq +194 -> 893
    //   702: aload 4
    //   704: invokeinterface 663 1 0
    //   709: checkcast 665	kkkkkk/xvxvvv
    //   712: astore 5
    //   714: aload_3
    //   715: getfield 645	kkkkkk/cccrcc:b0427042704270427Ч0427Ч04270427	Ljava/util/List;
    //   718: aload 5
    //   720: invokestatic 671	kkkkkk/ooooii:b04190419ЙЙ041904190419Й04190419	(Lkkkkkk/xvxvvv;)Lkkkkkk/ooooii;
    //   723: invokeinterface 675 2 0
    //   728: pop
    //   729: goto -37 -> 692
    //   732: astore 4
    //   734: aload_3
    //   735: aload_0
    //   736: invokevirtual 678	kkkkkk/ppkkkk:b04360436043604360436жж0436ж0436	()Ljava/lang/String;
    //   739: invokevirtual 681	kkkkkk/cccrcc:b04360436ж0436ж0436ж043604360436	(Ljava/lang/String;)V
    //   742: aload_3
    //   743: aload_0
    //   744: invokevirtual 684	kkkkkk/ppkkkk:bжж0436жжжж0436ж0436	()Lorg/threeten/bp/ZonedDateTime;
    //   747: invokevirtual 687	kkkkkk/cccrcc:b0436жж0436043604360436ж04360436	(Lorg/threeten/bp/ZonedDateTime;)V
    //   750: aload_3
    //   751: aload_0
    //   752: invokevirtual 690	kkkkkk/ppkkkk:b0436043604360436043604360436жж0436	()Lorg/threeten/bp/ZonedDateTime;
    //   755: invokevirtual 693	kkkkkk/cccrcc:bж0436ж0436ж04360436ж04360436	(Lorg/threeten/bp/ZonedDateTime;)V
    //   758: aload_0
    //   759: invokevirtual 697	kkkkkk/ppkkkk:b0436жж0436жжж0436ж0436	()Lkkkkkk/crrccc;
    //   762: ifnull +14 -> 776
    //   765: aload_3
    //   766: aload_0
    //   767: invokevirtual 697	kkkkkk/ppkkkk:b0436жж0436жжж0436ж0436	()Lkkkkkk/crrccc;
    //   770: invokevirtual 702	kkkkkk/crrccc:b0436ж043604360436043604360436ж0436	()Ljava/util/List;
    //   773: invokevirtual 706	kkkkkk/cccrcc:bжжжжжжж043604360436	(Ljava/util/List;)V
    //   776: aload_0
    //   777: invokevirtual 709	kkkkkk/ppkkkk:b0436ж043604360436жж0436ж0436	()Lkkkkkk/crrccc;
    //   780: ifnull +14 -> 794
    //   783: aload_3
    //   784: aload_0
    //   785: invokevirtual 709	kkkkkk/ppkkkk:b0436ж043604360436жж0436ж0436	()Lkkkkkk/crrccc;
    //   788: invokevirtual 702	kkkkkk/crrccc:b0436ж043604360436043604360436ж0436	()Ljava/util/List;
    //   791: invokevirtual 712	kkkkkk/cccrcc:b0436жж0436ж0436ж043604360436	(Ljava/util/List;)V
    //   794: aload_0
    //   795: invokevirtual 715	kkkkkk/ppkkkk:bж0436043604360436жж0436ж0436	()Lkkkkkk/crrccc;
    //   798: ifnull +14 -> 812
    //   801: aload_3
    //   802: aload_0
    //   803: invokevirtual 715	kkkkkk/ppkkkk:bж0436043604360436жж0436ж0436	()Lkkkkkk/crrccc;
    //   806: invokevirtual 702	kkkkkk/crrccc:b0436ж043604360436043604360436ж0436	()Ljava/util/List;
    //   809: invokevirtual 718	kkkkkk/cccrcc:bж0436ж0436ж0436ж043604360436	(Ljava/util/List;)V
    //   812: aload_0
    //   813: invokevirtual 721	kkkkkk/ppkkkk:bж043604360436043604360436жж0436	()Lkkkkkk/crrccc;
    //   816: ifnull +14 -> 830
    //   819: aload_3
    //   820: aload_0
    //   821: invokevirtual 721	kkkkkk/ppkkkk:bж043604360436043604360436жж0436	()Lkkkkkk/crrccc;
    //   824: invokevirtual 702	kkkkkk/crrccc:b0436ж043604360436043604360436ж0436	()Ljava/util/List;
    //   827: invokevirtual 724	kkkkkk/cccrcc:bжжж0436ж04360436ж04360436	(Ljava/util/List;)V
    //   830: aload_3
    //   831: aload_0
    //   832: invokevirtual 727	kkkkkk/ppkkkk:bж0436жж0436ж04360436ж0436	()Z
    //   835: invokevirtual 730	kkkkkk/cccrcc:bж04360436ж04360436ж043604360436	(Z)V
    //   838: aload_3
    //   839: aload_0
    //   840: invokevirtual 733	kkkkkk/ppkkkk:b0436жжж0436ж04360436ж0436	()Z
    //   843: invokevirtual 736	kkkkkk/cccrcc:b0436ж0436ж04360436ж043604360436	(Z)V
    //   846: aload_3
    //   847: aload_0
    //   848: invokevirtual 739	kkkkkk/ppkkkk:b04360436жж0436ж04360436ж0436	()Z
    //   851: invokevirtual 742	kkkkkk/cccrcc:b043604360436ж04360436ж043604360436	(Z)V
    //   854: aload_3
    //   855: aload_0
    //   856: invokevirtual 745	kkkkkk/ppkkkk:b0436ж0436жжжж0436ж0436	()I
    //   859: invokevirtual 749	kkkkkk/cccrcc:b04360436ж0436043604360436ж04360436	(I)V
    //   862: aload_3
    //   863: aload_0
    //   864: invokevirtual 752	kkkkkk/ppkkkk:b04360436жж04360436ж0436ж0436	()Z
    //   867: invokevirtual 755	kkkkkk/cccrcc:bж0436жжжжж043604360436	(Z)V
    //   870: invokestatic 126	kkkkkk/cccrcc:bжж0436жжжжж04360436	()I
    //   873: invokestatic 129	kkkkkk/cccrcc:b0436ж0436жжжжж04360436	()I
    //   876: iadd
    //   877: invokestatic 126	kkkkkk/cccrcc:bжж0436жжжжж04360436	()I
    //   880: imul
    //   881: invokestatic 132	kkkkkk/cccrcc:b04360436жжжжжж04360436	()I
    //   884: irem
    //   885: invokestatic 135	kkkkkk/cccrcc:bж0436жжжжжж04360436	()I
    //   888: if_icmpeq +3 -> 891
    //   891: aload_3
    //   892: areturn
    //   893: aload_3
    //   894: new 642	java/util/ArrayList
    //   897: dup
    //   898: invokespecial 643	java/util/ArrayList:<init>	()V
    //   901: putfield 757	kkkkkk/cccrcc:b0427Ч0427Ч0427ЧЧ04270427	Ljava/util/List;
    //   904: aload_0
    //   905: invokevirtual 760	kkkkkk/ppkkkk:bжж0436ж0436жж0436ж0436	()Ljava/util/List;
    //   908: ifnull +60 -> 968
    //   911: aload_0
    //   912: invokevirtual 760	kkkkkk/ppkkkk:bжж0436ж0436жж0436ж0436	()Ljava/util/List;
    //   915: invokeinterface 654 1 0
    //   920: astore 4
    //   922: aload 4
    //   924: invokeinterface 659 1 0
    //   929: ifeq +39 -> 968
    //   932: aload 4
    //   934: invokeinterface 663 1 0
    //   939: checkcast 762	kkkkkk/vxvvvv
    //   942: astore 5
    //   944: aload_3
    //   945: getfield 757	kkkkkk/cccrcc:b0427Ч0427Ч0427ЧЧ04270427	Ljava/util/List;
    //   948: aload 5
    //   950: invokestatic 768	kkkkkk/iiiioi:bЙ04190419ЙЙЙЙ041904190419	(Lkkkkkk/vxvvvv;)Lkkkkkk/iiiioi;
    //   953: invokeinterface 675 2 0
    //   958: pop
    //   959: iload_1
    //   960: iconst_0
    //   961: idiv
    //   962: istore_2
    //   963: iload_2
    //   964: istore_1
    //   965: goto -6 -> 959
    //   968: aload_3
    //   969: aload_0
    //   970: invokevirtual 771	kkkkkk/ppkkkk:b0436043604360436жж04360436ж0436	()Z
    //   973: invokevirtual 774	kkkkkk/cccrcc:b04360436жж04360436ж043604360436	(Z)V
    //   976: aload_3
    //   977: aload_0
    //   978: invokevirtual 777	kkkkkk/ppkkkk:b0436жжжж0436ж0436ж0436	()Ljava/lang/String;
    //   981: invokevirtual 780	kkkkkk/cccrcc:b0436ж04360436ж0436ж043604360436	(Ljava/lang/String;)V
    //   984: aload_3
    //   985: aload_0
    //   986: invokevirtual 783	kkkkkk/ppkkkk:bжжжжж0436ж0436ж0436	()Ljava/lang/String;
    //   989: invokevirtual 786	kkkkkk/cccrcc:bжж04360436ж0436ж043604360436	(Ljava/lang/String;)V
    //   992: new 788	java/lang/NullPointerException
    //   995: dup
    //   996: invokespecial 789	java/lang/NullPointerException:<init>	()V
    //   999: athrow
    //   1000: astore 5
    //   1002: goto -80 -> 922
    // Local variable table:
    //   start	length	slot	name	signature
    //   0	1005	0	paramPpkkkk	ppkkkk
    //   1	964	1	i	int
    //   962	2	2	j	int
    //   9	976	3	localCccrcc	cccrcc
    //   690	13	4	localIterator1	Iterator
    //   732	1	4	localException1	Exception
    //   920	13	4	localIterator2	Iterator
    //   712	237	5	localObject	Object
    //   1000	1	5	localException2	Exception
    // Exception table:
    //   from	to	target	type
    //   992	1000	732	java/lang/Exception
    //   959	963	1000	java/lang/Exception
  }
  
  public static int bж0436жжжжжж04360436()
  {
    return 0;
  }
  
  public static int bжж0436жжжжж04360436()
  {
    return 64;
  }
  
  public void b0436043604360436043604360436ж04360436(boolean paramBoolean)
  {
    int i = bжж0436жжжжж04360436();
    int j = bжж0436жжжжж04360436();
    switch (j * (b0436ж0436жжжжж04360436() + j) % b04360436жжжжжж04360436())
    {
    }
    if ((i + b0436ж0436жжжжж04360436()) * bжж0436жжжжж04360436() % b04360436жжжжжж04360436() != bж0436жжжжжж04360436()) {}
    switch (0)
    {
    case 1: 
    default: 
      for (;;)
      {
        switch (1)
        {
        }
      }
    }
    this.b0427ЧЧЧ042704270427Ч0427 = paramBoolean;
  }
  
  /* Error */
  public boolean b043604360436043604360436жж04360436()
  {
    // Byte code:
    //   0: iconst_0
    //   1: tableswitch	default:+23->24, 0:+50->51, 1:+-1->0
    //   24: iconst_0
    //   25: tableswitch	default:+23->48, 0:+26->51, 1:+-25->0
    //   48: goto -24 -> 24
    //   51: invokestatic 126	kkkkkk/cccrcc:bжж0436жжжжж04360436	()I
    //   54: istore_1
    //   55: invokestatic 129	kkkkkk/cccrcc:b0436ж0436жжжжж04360436	()I
    //   58: istore_2
    //   59: invokestatic 132	kkkkkk/cccrcc:b04360436жжжжжж04360436	()I
    //   62: istore_3
    //   63: iload_1
    //   64: iload_2
    //   65: iload_1
    //   66: iadd
    //   67: imul
    //   68: iload_3
    //   69: irem
    //   70: tableswitch	default:+18->88, 0:+39->109
    //   88: invokestatic 126	kkkkkk/cccrcc:bжж0436жжжжж04360436	()I
    //   91: invokestatic 129	kkkkkk/cccrcc:b0436ж0436жжжжж04360436	()I
    //   94: iadd
    //   95: invokestatic 126	kkkkkk/cccrcc:bжж0436жжжжж04360436	()I
    //   98: imul
    //   99: invokestatic 132	kkkkkk/cccrcc:b04360436жжжжжж04360436	()I
    //   102: irem
    //   103: invokestatic 135	kkkkkk/cccrcc:bж0436жжжжжж04360436	()I
    //   106: if_icmpeq +3 -> 109
    //   109: aload_0
    //   110: getfield 794	kkkkkk/cccrcc:bЧ04270427Ч042704270427Ч0427	Z
    //   113: istore 4
    //   115: iload 4
    //   117: ireturn
    //   118: astore 5
    //   120: aload 5
    //   122: athrow
    //   123: astore 5
    //   125: aload 5
    //   127: athrow
    // Local variable table:
    //   start	length	slot	name	signature
    //   0	128	0	this	cccrcc
    //   54	14	1	i	int
    //   58	9	2	j	int
    //   62	8	3	k	int
    //   113	3	4	bool	boolean
    //   118	3	5	localException1	Exception
    //   123	3	5	localException2	Exception
    // Exception table:
    //   from	to	target	type
    //   55	63	118	java/lang/Exception
    //   109	115	118	java/lang/Exception
    //   51	55	123	java/lang/Exception
  }
  
  public boolean b04360436043604360436ж0436ж04360436()
  {
    if ((bжж0436жжжжж04360436() + b0436ж0436жжжжж04360436()) * bжж0436жжжжж04360436() % b04360436жжжжжж04360436() != bж0436жжжжжж04360436())
    {
      int i = bжж0436жжжжж04360436();
      switch (i * (b0436ж0436жжжжж04360436() + i) % b04360436жжжжжж04360436())
      {
      }
    }
    try
    {
      boolean bool = this.b04270427Ч0427Ч0427Ч04270427;
      return bool;
    }
    catch (Exception localException)
    {
      switch (0)
      {
      case 1: 
      default: 
        for (;;)
        {
          switch (0)
          {
          }
        }
      }
      throw localException;
    }
  }
  
  public void b04360436043604360436жж043604360436(boolean paramBoolean)
  {
    int i = bжж0436жжжжж04360436();
    switch (i * (b0436ж0436жжжжж04360436() + i) % b04360436жжжжжж04360436())
    {
    }
    switch (1)
    {
    case 0: 
    default: 
      for (;;)
      {
        switch (0)
        {
        case 1: 
        default: 
          for (;;)
          {
            switch (1)
            {
            }
          }
        }
        switch (0)
        {
        }
      }
    }
    if ((bжж0436жжжжж04360436() + b0436ж0436жжжжж04360436()) * bжж0436жжжжж04360436() % b04360436жжжжжж04360436() != bж0436жжжжжж04360436()) {}
    this.b0427ЧЧ04270427ЧЧ04270427 = paramBoolean;
  }
  
  public iiooii b04360436043604360436жжж04360436()
  {
    int i = bжж0436жжжжж04360436();
    switch (i * (b0436ж0436жжжжж04360436() + i) % b04360436жжжжжж04360436())
    {
    }
    try
    {
      iiooii localIiooii = this.bЧЧ0427Ч0427ЧЧ04270427;
      if ((bжж0436жжжжж04360436() + b0436ж0436жжжжж04360436()) * bжж0436жжжжж04360436() % b04360436жжжжжж04360436() != bж0436жжжжжж04360436()) {}
      return localIiooii;
    }
    catch (Exception localException)
    {
      throw localException;
    }
  }
  
  public void b0436043604360436ж04360436ж04360436(boolean paramBoolean)
  {
    if ((bжж0436жжжжж04360436() + b0436ж0436жжжжж04360436()) * bжж0436жжжжж04360436() % b04360436жжжжжж04360436() != bж0436жжжжжж04360436()) {}
    try
    {
      throw new NullPointerException();
    }
    catch (Exception localException)
    {
      this.bЧ0427ЧЧЧ04270427Ч0427 = paramBoolean;
    }
  }
  
  public void b0436043604360436ж0436ж043604360436(String paramString)
  {
    throw new Runtime("d2j fail translate: java.lang.IndexOutOfBoundsException: fromIndex < 0: -1\n\tat java.util.BitSet.nextSetBit(BitSet.java:712)\n\tat com.googlecode.dex2jar.ir.ts.array.FillArrayTransformer.makeSureAllElementAreAssigned(FillArrayTransformer.java:505)\n\tat com.googlecode.dex2jar.ir.ts.array.FillArrayTransformer.transformReportChanged(FillArrayTransformer.java:123)\n\tat com.googlecode.dex2jar.ir.ts.StatedTransformer.transform(StatedTransformer.java:10)\n\tat com.googlecode.d2j.dex.Dex2jar$2.optimize(Dex2jar.java:149)\n\tat com.googlecode.d2j.dex.Dex2Asm.convertCode(Dex2Asm.java:414)\n\tat com.googlecode.d2j.dex.ExDex2Asm.convertCode(ExDex2Asm.java:42)\n\tat com.googlecode.d2j.dex.Dex2jar$2.convertCode(Dex2jar.java:128)\n\tat com.googlecode.d2j.dex.Dex2Asm.convertMethod(Dex2Asm.java:509)\n\tat com.googlecode.d2j.dex.Dex2Asm.convertClass(Dex2Asm.java:406)\n\tat com.googlecode.d2j.dex.Dex2Asm.convertDex(Dex2Asm.java:422)\n\tat com.googlecode.d2j.dex.Dex2jar.doTranslate(Dex2jar.java:172)\n\tat com.googlecode.d2j.dex.Dex2jar.to(Dex2jar.java:272)\n\tat com.googlecode.dex2jar.tools.Dex2jarCmd.doCommandLine(Dex2jarCmd.java:108)\n\tat com.googlecode.dex2jar.tools.BaseCmd.doMain(BaseCmd.java:288)\n\tat com.googlecode.dex2jar.tools.Dex2jarCmd.main(Dex2jarCmd.java:32)\n");
  }
  
  public String b0436043604360436ж0436жж04360436()
  {
    if ((bжж0436жжжжж04360436() + b0436ж0436жжжжж04360436()) * bжж0436жжжжж04360436() % b04360436жжжжжж04360436() != bж0436жжжжжж04360436()) {}
    String str = this.b0427Ч04270427Ч0427Ч04270427;
    int i = bжж0436жжжжж04360436();
    switch (i * (b0436ж0436жжжжж04360436() + i) % b04360436жжжжжж04360436())
    {
    }
    switch (1)
    {
    case 0: 
    default: 
      for (;;)
      {
        switch (1)
        {
        }
      }
    }
    return str;
  }
  
  public boolean b0436043604360436жж0436ж04360436()
  {
    boolean bool = this.b0427ЧЧ0427042704270427Ч0427;
    int i = bжж0436жжжжж04360436();
    if (((bжж0436жжжжж04360436() + b0436ж0436жжжжж04360436()) * bжж0436жжжжж04360436() % b04360436жжжжжж04360436() == bж0436жжжжжж04360436()) || ((i + b0436ж0436жжжжж04360436()) * bжж0436жжжжж04360436() % b04360436жжжжжж04360436() != bж0436жжжжжж04360436())) {
      switch (1)
      {
      case 0: 
      default: 
        for (;;)
        {
          switch (1)
          {
          }
        }
      }
    }
    return bool;
  }
  
  /* Error */
  public void b0436043604360436жжж043604360436(boolean paramBoolean)
  {
    // Byte code:
    //   0: invokestatic 126	kkkkkk/cccrcc:bжж0436жжжжж04360436	()I
    //   3: istore_2
    //   4: invokestatic 129	kkkkkk/cccrcc:b0436ж0436жжжжж04360436	()I
    //   7: istore_3
    //   8: invokestatic 132	kkkkkk/cccrcc:b04360436жжжжжж04360436	()I
    //   11: istore 4
    //   13: iload_2
    //   14: iload_3
    //   15: iload_2
    //   16: iadd
    //   17: imul
    //   18: iload 4
    //   20: irem
    //   21: tableswitch	default:+19->40, 0:+19->40
    //   40: iconst_1
    //   41: tableswitch	default:+23->64, 0:+-1->40, 1:+82->123
    //   64: invokestatic 126	kkkkkk/cccrcc:bжж0436жжжжж04360436	()I
    //   67: istore_2
    //   68: iload_2
    //   69: invokestatic 129	kkkkkk/cccrcc:b0436ж0436жжжжж04360436	()I
    //   72: iload_2
    //   73: iadd
    //   74: imul
    //   75: invokestatic 132	kkkkkk/cccrcc:b04360436жжжжжж04360436	()I
    //   78: irem
    //   79: tableswitch	default:+17->96, 0:+17->96
    //   96: iconst_0
    //   97: tableswitch	default:+23->120, 0:+26->123, 1:+-57->40
    //   120: goto -56 -> 64
    //   123: aload_0
    //   124: iload_1
    //   125: putfield 821	kkkkkk/cccrcc:bЧЧ04270427ЧЧЧ04270427	Z
    //   128: return
    //   129: astore 5
    //   131: aload 5
    //   133: athrow
    //   134: astore 5
    //   136: aload 5
    //   138: athrow
    // Local variable table:
    //   start	length	slot	name	signature
    //   0	139	0	this	cccrcc
    //   0	139	1	paramBoolean	boolean
    //   3	72	2	i	int
    //   7	10	3	j	int
    //   11	10	4	k	int
    //   129	3	5	localException1	Exception
    //   134	3	5	localException2	Exception
    // Exception table:
    //   from	to	target	type
    //   4	13	129	java/lang/Exception
    //   123	128	129	java/lang/Exception
    //   0	4	134	java/lang/Exception
  }
  
  /* Error */
  public String b0436043604360436жжжж04360436()
  {
    // Byte code:
    //   0: invokestatic 126	kkkkkk/cccrcc:bжж0436жжжжж04360436	()I
    //   3: istore_1
    //   4: invokestatic 129	kkkkkk/cccrcc:b0436ж0436жжжжж04360436	()I
    //   7: istore_2
    //   8: invokestatic 126	kkkkkk/cccrcc:bжж0436жжжжж04360436	()I
    //   11: istore_3
    //   12: invokestatic 132	kkkkkk/cccrcc:b04360436жжжжжж04360436	()I
    //   15: istore 4
    //   17: invokestatic 135	kkkkkk/cccrcc:bж0436жжжжжж04360436	()I
    //   20: istore 5
    //   22: iload_1
    //   23: iload_2
    //   24: iadd
    //   25: iload_3
    //   26: imul
    //   27: iload 4
    //   29: irem
    //   30: iload 5
    //   32: if_icmpeq +24 -> 56
    //   35: invokestatic 126	kkkkkk/cccrcc:bжж0436жжжжж04360436	()I
    //   38: invokestatic 129	kkkkkk/cccrcc:b0436ж0436жжжжж04360436	()I
    //   41: iadd
    //   42: invokestatic 126	kkkkkk/cccrcc:bжж0436жжжжж04360436	()I
    //   45: imul
    //   46: invokestatic 132	kkkkkk/cccrcc:b04360436жжжжжж04360436	()I
    //   49: irem
    //   50: invokestatic 135	kkkkkk/cccrcc:bж0436жжжжжж04360436	()I
    //   53: if_icmpeq +3 -> 56
    //   56: aload_0
    //   57: getfield 824	kkkkkk/cccrcc:b04270427ЧЧЧ04270427Ч0427	Ljava/lang/String;
    //   60: astore 6
    //   62: iconst_0
    //   63: tableswitch	default:+21->84, 0:+48->111, 1:+-1->62
    //   84: iconst_1
    //   85: tableswitch	default:+23->108, 0:+-23->62, 1:+26->111
    //   108: goto -24 -> 84
    //   111: aload 6
    //   113: areturn
    //   114: astore 6
    //   116: aload 6
    //   118: athrow
    //   119: astore 6
    //   121: aload 6
    //   123: athrow
    // Local variable table:
    //   start	length	slot	name	signature
    //   0	124	0	this	cccrcc
    //   3	22	1	i	int
    //   7	18	2	j	int
    //   11	16	3	k	int
    //   15	15	4	m	int
    //   20	13	5	n	int
    //   60	52	6	str	String
    //   114	3	6	localException1	Exception
    //   119	3	6	localException2	Exception
    // Exception table:
    //   from	to	target	type
    //   0	12	114	java/lang/Exception
    //   56	62	114	java/lang/Exception
    //   12	22	119	java/lang/Exception
  }
  
  /* Error */
  public void b043604360436ж043604360436ж04360436(boolean paramBoolean)
  {
    // Byte code:
    //   0: iconst_3
    //   1: istore_2
    //   2: iload_2
    //   3: iconst_0
    //   4: idiv
    //   5: istore_3
    //   6: iload_3
    //   7: istore_2
    //   8: invokestatic 126	kkkkkk/cccrcc:bжж0436жжжжж04360436	()I
    //   11: invokestatic 129	kkkkkk/cccrcc:b0436ж0436жжжжж04360436	()I
    //   14: iadd
    //   15: invokestatic 126	kkkkkk/cccrcc:bжж0436жжжжж04360436	()I
    //   18: imul
    //   19: invokestatic 132	kkkkkk/cccrcc:b04360436жжжжжж04360436	()I
    //   22: irem
    //   23: invokestatic 135	kkkkkk/cccrcc:bж0436жжжжжж04360436	()I
    //   26: if_icmpeq -24 -> 2
    //   29: iload_3
    //   30: istore_2
    //   31: goto -29 -> 2
    //   34: astore 4
    //   36: aload_0
    //   37: iload_1
    //   38: putfield 826	kkkkkk/cccrcc:bЧ0427Ч0427Ч04270427Ч0427	Z
    //   41: return
    //   42: astore 4
    //   44: iconst_0
    //   45: tableswitch	default:+23->68, 0:+50->95, 1:+-1->44
    //   68: iconst_0
    //   69: tableswitch	default:+23->92, 0:+26->95, 1:+-25->44
    //   92: goto -24 -> 68
    //   95: aload 4
    //   97: athrow
    // Local variable table:
    //   start	length	slot	name	signature
    //   0	98	0	this	cccrcc
    //   0	98	1	paramBoolean	boolean
    //   1	30	2	i	int
    //   5	25	3	j	int
    //   34	1	4	localException1	Exception
    //   42	54	4	localException2	Exception
    // Exception table:
    //   from	to	target	type
    //   2	6	34	java/lang/Exception
    //   36	41	42	java/lang/Exception
  }
  
  public void b043604360436ж04360436ж043604360436(boolean paramBoolean)
  {
    switch (0)
    {
    case 1: 
    default: 
      for (;;)
      {
        switch (1)
        {
        }
      }
    }
    if ((bжж0436жжжжж04360436() + b0436ж0436жжжжж04360436()) * bжж0436жжжжж04360436() % b04360436жжжжжж04360436() != bж0436жжжжжж04360436())
    {
      switch (0)
      {
      case 1: 
      default: 
        for (;;)
        {
          switch (0)
          {
          }
        }
      }
      int i = bжж0436жжжжж04360436();
      switch (i * (b0436ж0436жжжжж04360436() + i) % b04360436жжжжжж04360436())
      {
      }
    }
    this.bЧЧ04270427Ч0427Ч04270427 = paramBoolean;
  }
  
  public boolean b043604360436ж04360436жж04360436()
  {
    int i = bжж0436жжжжж04360436();
    int j = b0436ж0436жжжжж04360436();
    int k = bжж0436жжжжж04360436();
    int m = b04360436жжжжжж04360436();
    switch (0)
    {
    case 1: 
    default: 
      for (;;)
      {
        switch (1)
        {
        }
      }
    }
    if ((i + j) * k % m != bж0436жжжжжж04360436())
    {
      i = bжж0436жжжжж04360436();
      switch (i * (b0436ж0436жжжжж04360436() + i) % b04360436жжжжжж04360436())
      {
      }
    }
    return this.bЧ0427ЧЧЧ04270427Ч0427;
  }
  
  /* Error */
  public boolean b043604360436ж0436ж0436ж04360436()
  {
    // Byte code:
    //   0: invokestatic 126	kkkkkk/cccrcc:bжж0436жжжжж04360436	()I
    //   3: istore_1
    //   4: iload_1
    //   5: invokestatic 129	kkkkkk/cccrcc:b0436ж0436жжжжж04360436	()I
    //   8: iload_1
    //   9: iadd
    //   10: imul
    //   11: invokestatic 132	kkkkkk/cccrcc:b04360436жжжжжж04360436	()I
    //   14: irem
    //   15: tableswitch	default:+17->32, 0:+17->32
    //   32: aload_0
    //   33: getfield 832	kkkkkk/cccrcc:bЧЧ04270427042704270427Ч0427	Z
    //   36: istore 6
    //   38: invokestatic 126	kkkkkk/cccrcc:bжж0436жжжжж04360436	()I
    //   41: istore_1
    //   42: invokestatic 129	kkkkkk/cccrcc:b0436ж0436жжжжж04360436	()I
    //   45: istore_2
    //   46: invokestatic 126	kkkkkk/cccrcc:bжж0436жжжжж04360436	()I
    //   49: istore_3
    //   50: invokestatic 132	kkkkkk/cccrcc:b04360436жжжжжж04360436	()I
    //   53: istore 4
    //   55: invokestatic 135	kkkkkk/cccrcc:bж0436жжжжжж04360436	()I
    //   58: istore 5
    //   60: iload_1
    //   61: iload_2
    //   62: iadd
    //   63: iload_3
    //   64: imul
    //   65: iload 4
    //   67: irem
    //   68: iload 5
    //   70: if_icmpeq +3 -> 73
    //   73: iload 6
    //   75: ireturn
    //   76: astore 7
    //   78: aload 7
    //   80: athrow
    //   81: astore 7
    //   83: aload 7
    //   85: athrow
    // Local variable table:
    //   start	length	slot	name	signature
    //   0	86	0	this	cccrcc
    //   3	60	1	i	int
    //   45	18	2	j	int
    //   49	16	3	k	int
    //   53	15	4	m	int
    //   58	13	5	n	int
    //   36	38	6	bool	boolean
    //   76	3	7	localException1	Exception
    //   81	3	7	localException2	Exception
    // Exception table:
    //   from	to	target	type
    //   38	60	76	java/lang/Exception
    //   32	38	81	java/lang/Exception
  }
  
  /* Error */
  public void b043604360436ж0436жж043604360436(ZonedDateTime paramZonedDateTime)
  {
    // Byte code:
    //   0: invokestatic 126	kkkkkk/cccrcc:bжж0436жжжжж04360436	()I
    //   3: istore_2
    //   4: invokestatic 129	kkkkkk/cccrcc:b0436ж0436жжжжж04360436	()I
    //   7: istore_3
    //   8: invokestatic 126	kkkkkk/cccrcc:bжж0436жжжжж04360436	()I
    //   11: istore 4
    //   13: invokestatic 132	kkkkkk/cccrcc:b04360436жжжжжж04360436	()I
    //   16: istore 5
    //   18: invokestatic 135	kkkkkk/cccrcc:bж0436жжжжжж04360436	()I
    //   21: istore 6
    //   23: iload_2
    //   24: iload_3
    //   25: iadd
    //   26: iload 4
    //   28: imul
    //   29: iload 5
    //   31: irem
    //   32: iload 6
    //   34: if_icmpeq +3 -> 37
    //   37: invokestatic 126	kkkkkk/cccrcc:bжж0436жжжжж04360436	()I
    //   40: invokestatic 129	kkkkkk/cccrcc:b0436ж0436жжжжж04360436	()I
    //   43: iadd
    //   44: invokestatic 126	kkkkkk/cccrcc:bжж0436жжжжж04360436	()I
    //   47: imul
    //   48: invokestatic 132	kkkkkk/cccrcc:b04360436жжжжжж04360436	()I
    //   51: irem
    //   52: invokestatic 135	kkkkkk/cccrcc:bж0436жжжжжж04360436	()I
    //   55: if_icmpeq +3 -> 58
    //   58: iconst_0
    //   59: tableswitch	default:+21->80, 0:+48->107, 1:+-1->58
    //   80: iconst_1
    //   81: tableswitch	default:+23->104, 0:+-23->58, 1:+26->107
    //   104: goto -24 -> 80
    //   107: aload_0
    //   108: aload_1
    //   109: putfield 834	kkkkkk/cccrcc:b04270427ЧЧ0427ЧЧ04270427	Lorg/threeten/bp/ZonedDateTime;
    //   112: return
    //   113: astore_1
    //   114: aload_1
    //   115: athrow
    //   116: astore_1
    //   117: aload_1
    //   118: athrow
    // Local variable table:
    //   start	length	slot	name	signature
    //   0	119	0	this	cccrcc
    //   0	119	1	paramZonedDateTime	ZonedDateTime
    //   3	23	2	i	int
    //   7	19	3	j	int
    //   11	18	4	k	int
    //   16	16	5	m	int
    //   21	14	6	n	int
    // Exception table:
    //   from	to	target	type
    //   0	13	113	java/lang/Exception
    //   107	112	113	java/lang/Exception
    //   13	23	116	java/lang/Exception
  }
  
  /* Error */
  public List<String> b043604360436ж0436жжж04360436()
  {
    // Byte code:
    //   0: aload_0
    //   1: getfield 837	kkkkkk/cccrcc:bЧ0427ЧЧ042704270427Ч0427	Ljava/util/List;
    //   4: astore 6
    //   6: invokestatic 126	kkkkkk/cccrcc:bжж0436жжжжж04360436	()I
    //   9: invokestatic 129	kkkkkk/cccrcc:b0436ж0436жжжжж04360436	()I
    //   12: iadd
    //   13: invokestatic 126	kkkkkk/cccrcc:bжж0436жжжжж04360436	()I
    //   16: imul
    //   17: invokestatic 132	kkkkkk/cccrcc:b04360436жжжжжж04360436	()I
    //   20: irem
    //   21: invokestatic 135	kkkkkk/cccrcc:bж0436жжжжжж04360436	()I
    //   24: if_icmpeq +3 -> 27
    //   27: invokestatic 126	kkkkkk/cccrcc:bжж0436жжжжж04360436	()I
    //   30: istore_1
    //   31: invokestatic 129	kkkkkk/cccrcc:b0436ж0436жжжжж04360436	()I
    //   34: istore_2
    //   35: invokestatic 126	kkkkkk/cccrcc:bжж0436жжжжж04360436	()I
    //   38: istore_3
    //   39: invokestatic 132	kkkkkk/cccrcc:b04360436жжжжжж04360436	()I
    //   42: istore 4
    //   44: invokestatic 135	kkkkkk/cccrcc:bж0436жжжжжж04360436	()I
    //   47: istore 5
    //   49: iload_1
    //   50: iload_2
    //   51: iadd
    //   52: iload_3
    //   53: imul
    //   54: iload 4
    //   56: irem
    //   57: iload 5
    //   59: if_icmpeq +3 -> 62
    //   62: aload 6
    //   64: areturn
    //   65: astore 6
    //   67: aload 6
    //   69: athrow
    //   70: astore 6
    //   72: aload 6
    //   74: athrow
    // Local variable table:
    //   start	length	slot	name	signature
    //   0	75	0	this	cccrcc
    //   30	22	1	i	int
    //   34	18	2	j	int
    //   38	16	3	k	int
    //   42	15	4	m	int
    //   47	13	5	n	int
    //   4	59	6	localList	List
    //   65	3	6	localException1	Exception
    //   70	3	6	localException2	Exception
    // Exception table:
    //   from	to	target	type
    //   27	49	65	java/lang/Exception
    //   0	6	70	java/lang/Exception
  }
  
  /* Error */
  public void b043604360436жж04360436ж04360436(String paramString)
  {
    // Byte code:
    //   0: invokestatic 126	kkkkkk/cccrcc:bжж0436жжжжж04360436	()I
    //   3: invokestatic 129	kkkkkk/cccrcc:b0436ж0436жжжжж04360436	()I
    //   6: iadd
    //   7: invokestatic 126	kkkkkk/cccrcc:bжж0436жжжжж04360436	()I
    //   10: imul
    //   11: invokestatic 132	kkkkkk/cccrcc:b04360436жжжжжж04360436	()I
    //   14: irem
    //   15: invokestatic 135	kkkkkk/cccrcc:bж0436жжжжжж04360436	()I
    //   18: if_icmpeq +3 -> 21
    //   21: invokestatic 126	kkkkkk/cccrcc:bжж0436жжжжж04360436	()I
    //   24: istore_2
    //   25: invokestatic 129	kkkkkk/cccrcc:b0436ж0436жжжжж04360436	()I
    //   28: istore_3
    //   29: invokestatic 132	kkkkkk/cccrcc:b04360436жжжжжж04360436	()I
    //   32: istore 4
    //   34: iload_2
    //   35: iload_3
    //   36: iload_2
    //   37: iadd
    //   38: imul
    //   39: iload 4
    //   41: irem
    //   42: tableswitch	default:+80->122, 0:+18->60
    //   60: aload_0
    //   61: aload_1
    //   62: putfield 841	kkkkkk/cccrcc:bЧ0427Ч04270427Ч0427Ч0427	Ljava/lang/String;
    //   65: iconst_1
    //   66: tableswitch	default:+22->88, 0:+-1->65, 1:+49->115
    //   88: iconst_1
    //   89: tableswitch	default:+23->112, 0:+-24->65, 1:+26->115
    //   112: goto -24 -> 88
    //   115: return
    //   116: astore_1
    //   117: aload_1
    //   118: athrow
    //   119: astore_1
    //   120: aload_1
    //   121: athrow
    //   122: goto -62 -> 60
    // Local variable table:
    //   start	length	slot	name	signature
    //   0	125	0	this	cccrcc
    //   0	125	1	paramString	String
    //   24	15	2	i	int
    //   28	10	3	j	int
    //   32	10	4	k	int
    // Exception table:
    //   from	to	target	type
    //   21	25	116	java/lang/Exception
    //   60	65	116	java/lang/Exception
    //   25	34	119	java/lang/Exception
  }
  
  /* Error */
  public void b043604360436жж0436ж043604360436(boolean paramBoolean)
  {
    // Byte code:
    //   0: iconst_1
    //   1: istore_2
    //   2: iload_2
    //   3: iconst_0
    //   4: idiv
    //   5: istore_2
    //   6: goto -4 -> 2
    //   9: astore_3
    //   10: iconst_1
    //   11: tableswitch	default:+21->32, 0:+-1->10, 1:+48->59
    //   32: iconst_1
    //   33: tableswitch	default:+23->56, 0:+-23->10, 1:+26->59
    //   56: goto -24 -> 32
    //   59: iconst_1
    //   60: tableswitch	default:+24->84, 0:+-50->10, 1:+51->111
    //   84: iconst_1
    //   85: tableswitch	default:+23->108, 0:+-75->10, 1:+26->111
    //   108: goto -24 -> 84
    //   111: aload_0
    //   112: iload_1
    //   113: putfield 843	kkkkkk/cccrcc:bЧЧЧЧЧ0427Ч04270427	Z
    //   116: return
    //   117: new 788	java/lang/NullPointerException
    //   120: dup
    //   121: invokespecial 789	java/lang/NullPointerException:<init>	()V
    //   124: athrow
    //   125: astore_3
    //   126: goto -9 -> 117
    // Local variable table:
    //   start	length	slot	name	signature
    //   0	129	0	this	cccrcc
    //   0	129	1	paramBoolean	boolean
    //   1	5	2	i	int
    //   9	1	3	localException1	Exception
    //   125	1	3	localException2	Exception
    // Exception table:
    //   from	to	target	type
    //   117	125	9	java/lang/Exception
    //   2	6	125	java/lang/Exception
  }
  
  /* Error */
  public List<String> b043604360436жж0436жж04360436()
  {
    // Byte code:
    //   0: iconst_0
    //   1: istore_1
    //   2: iload_1
    //   3: iconst_0
    //   4: idiv
    //   5: istore_2
    //   6: invokestatic 126	kkkkkk/cccrcc:bжж0436жжжжж04360436	()I
    //   9: istore_3
    //   10: iload_2
    //   11: istore_1
    //   12: iload_3
    //   13: invokestatic 129	kkkkkk/cccrcc:b0436ж0436жжжжж04360436	()I
    //   16: iload_3
    //   17: iadd
    //   18: imul
    //   19: invokestatic 132	kkkkkk/cccrcc:b04360436жжжжжж04360436	()I
    //   22: irem
    //   23: tableswitch	default:+17->40, 0:+-21->2
    //   40: iload_2
    //   41: istore_1
    //   42: goto -40 -> 2
    //   45: astore 4
    //   47: aload_0
    //   48: getfield 846	kkkkkk/cccrcc:b0427ЧЧЧЧ0427Ч04270427	Ljava/util/List;
    //   51: astore 4
    //   53: iconst_1
    //   54: tableswitch	default:+22->76, 0:+-1->53, 1:+101->155
    //   76: iconst_1
    //   77: tableswitch	default:+23->100, 0:+-1->76, 1:+50->127
    //   100: iconst_0
    //   101: tableswitch	default:+23->124, 0:+26->127, 1:+-25->76
    //   124: goto -24 -> 100
    //   127: iconst_1
    //   128: tableswitch	default:+24->152, 0:+-75->53, 1:+27->155
    //   152: goto -76 -> 76
    //   155: aload 4
    //   157: areturn
    // Local variable table:
    //   start	length	slot	name	signature
    //   0	158	0	this	cccrcc
    //   1	41	1	i	int
    //   5	36	2	j	int
    //   9	10	3	k	int
    //   45	1	4	localException	Exception
    //   51	105	4	localList	List
    // Exception table:
    //   from	to	target	type
    //   2	6	45	java/lang/Exception
  }
  
  public boolean b043604360436жжж0436ж04360436()
  {
    int i = bжж0436жжжжж04360436();
    int j = b0436ж0436жжжжж04360436();
    switch (1)
    {
    case 0: 
    default: 
      for (;;)
      {
        switch (1)
        {
        }
      }
    }
    switch (i * (j + i) % b04360436жжжжжж04360436())
    {
    default: 
      i = bжж0436жжжжж04360436();
      switch (i * (b0436ж0436жжжжж04360436() + i) % b04360436жжжжжж04360436())
      {
      }
      break;
    }
    try
    {
      boolean bool = this.b0427ЧЧ0427ЧЧЧ04270427;
      return bool;
    }
    catch (Exception localException)
    {
      throw localException;
    }
  }
  
  /* Error */
  public void b043604360436жжжж043604360436(boolean paramBoolean)
  {
    // Byte code:
    //   0: invokestatic 126	kkkkkk/cccrcc:bжж0436жжжжж04360436	()I
    //   3: istore_2
    //   4: invokestatic 129	kkkkkk/cccrcc:b0436ж0436жжжжж04360436	()I
    //   7: istore_3
    //   8: invokestatic 132	kkkkkk/cccrcc:b04360436жжжжжж04360436	()I
    //   11: istore 4
    //   13: iload_2
    //   14: iload_3
    //   15: iload_2
    //   16: iadd
    //   17: imul
    //   18: iload 4
    //   20: irem
    //   21: tableswitch	default:+19->40, 0:+19->40
    //   40: invokestatic 126	kkkkkk/cccrcc:bжж0436жжжжж04360436	()I
    //   43: istore_2
    //   44: iload_2
    //   45: invokestatic 129	kkkkkk/cccrcc:b0436ж0436жжжжж04360436	()I
    //   48: iload_2
    //   49: iadd
    //   50: imul
    //   51: invokestatic 132	kkkkkk/cccrcc:b04360436жжжжжж04360436	()I
    //   54: irem
    //   55: tableswitch	default:+17->72, 0:+17->72
    //   72: aload_0
    //   73: iload_1
    //   74: putfield 851	kkkkkk/cccrcc:b042704270427Ч042704270427Ч0427	Z
    //   77: return
    //   78: astore 5
    //   80: aload 5
    //   82: athrow
    //   83: astore 5
    //   85: aload 5
    //   87: athrow
    //   88: astore 5
    //   90: aload 5
    //   92: athrow
    // Local variable table:
    //   start	length	slot	name	signature
    //   0	93	0	this	cccrcc
    //   0	93	1	paramBoolean	boolean
    //   3	48	2	i	int
    //   7	10	3	j	int
    //   11	10	4	k	int
    //   78	3	5	localException1	Exception
    //   83	3	5	localException2	Exception
    //   88	3	5	localException3	Exception
    // Exception table:
    //   from	to	target	type
    //   72	77	78	java/lang/Exception
    //   80	83	83	java/lang/Exception
    //   0	13	88	java/lang/Exception
  }
  
  public String b043604360436жжжжж04360436()
  {
    int i = bжж0436жжжжж04360436();
    switch (i * (b0436ж0436жжжжж04360436() + i) % b04360436жжжжжж04360436())
    {
    default: 
      i = bжж0436жжжжж04360436();
      switch (i * (b0436ж0436жжжжж04360436() + i) % b04360436жжжжжж04360436())
      {
      }
      switch (1)
      {
      case 0: 
      default: 
        for (;;)
        {
          switch (0)
          {
          }
        }
      }
      break;
    }
    try
    {
      String str = this.b0427ЧЧ04270427Ч0427Ч0427;
      return str;
    }
    catch (Exception localException)
    {
      throw localException;
    }
  }
  
  /* Error */
  public void b04360436ж0436043604360436ж04360436(int paramInt)
  {
    // Byte code:
    //   0: aload_0
    //   1: iload_1
    //   2: putfield 856	kkkkkk/cccrcc:b0427Ч04270427Ч04270427Ч0427	I
    //   5: invokestatic 126	kkkkkk/cccrcc:bжж0436жжжжж04360436	()I
    //   8: istore_1
    //   9: iload_1
    //   10: invokestatic 129	kkkkkk/cccrcc:b0436ж0436жжжжж04360436	()I
    //   13: iload_1
    //   14: iadd
    //   15: imul
    //   16: invokestatic 132	kkkkkk/cccrcc:b04360436жжжжжж04360436	()I
    //   19: irem
    //   20: tableswitch	default:+20->40, 0:+20->40
    //   40: invokestatic 126	kkkkkk/cccrcc:bжж0436жжжжж04360436	()I
    //   43: istore_1
    //   44: invokestatic 129	kkkkkk/cccrcc:b0436ж0436жжжжж04360436	()I
    //   47: istore_2
    //   48: invokestatic 132	kkkkkk/cccrcc:b04360436жжжжжж04360436	()I
    //   51: istore_3
    //   52: iload_1
    //   53: iload_2
    //   54: iload_1
    //   55: iadd
    //   56: imul
    //   57: iload_3
    //   58: irem
    //   59: tableswitch	default:+17->76, 0:+17->76
    //   76: return
    //   77: astore 4
    //   79: aload 4
    //   81: athrow
    //   82: astore 4
    //   84: aload 4
    //   86: athrow
    // Local variable table:
    //   start	length	slot	name	signature
    //   0	87	0	this	cccrcc
    //   0	87	1	paramInt	int
    //   47	9	2	i	int
    //   51	8	3	j	int
    //   77	3	4	localException1	Exception
    //   82	3	4	localException2	Exception
    // Exception table:
    //   from	to	target	type
    //   0	5	77	java/lang/Exception
    //   48	52	77	java/lang/Exception
    //   40	48	82	java/lang/Exception
  }
  
  public void b04360436ж043604360436ж043604360436(boolean paramBoolean)
  {
    this.b0427ЧЧЧЧЧЧ04270427 = paramBoolean;
    if ((bжж0436жжжжж04360436() + b0436ж0436жжжжж04360436()) * bжж0436жжжжж04360436() % b04360436жжжжжж04360436() != bж0436жжжжжж04360436()) {}
    int i = bжж0436жжжжж04360436();
    switch (i * (b0436ж0436жжжжж04360436() + i) % b04360436жжжжжж04360436())
    {
    }
  }
  
  public boolean b04360436ж043604360436жж04360436()
  {
    try
    {
      boolean bool = this.bЧЧЧ0427Ч04270427Ч0427;
      return bool;
    }
    catch (Exception localException)
    {
      throw localException;
    }
  }
  
  public boolean b04360436ж04360436ж0436ж04360436()
  {
    switch (1)
    {
    case 0: 
    default: 
      for (;;)
      {
        switch (0)
        {
        case 1: 
        default: 
          for (;;)
          {
            switch (0)
            {
            }
          }
        }
        switch (0)
        {
        }
      }
    }
    int i = bжж0436жжжжж04360436();
    int j = bжж0436жжжжж04360436();
    switch (j * (b0436ж0436жжжжж04360436() + j) % b04360436жжжжжж04360436())
    {
    }
    switch (i * (b0436ж0436жжжжж04360436() + i) % b04360436жжжжжж04360436())
    {
    }
    return this.bЧЧЧЧЧЧЧ04270427;
  }
  
  public void b04360436ж04360436жж043604360436(List<iiiioi> paramList)
  {
    int i = bжж0436жжжжж04360436();
    switch (i * (b0436ж0436жжжжж04360436() + i) % b04360436жжжжжж04360436())
    {
    }
    if ((bжж0436жжжжж04360436() + b0436ж0436жжжжж04360436()) * bжж0436жжжжж04360436() % b04360436жжжжжж04360436() != bж0436жжжжжж04360436()) {}
    try
    {
      this.b0427Ч0427Ч0427ЧЧ04270427 = paramList;
      return;
    }
    catch (Exception paramList)
    {
      throw paramList;
    }
  }
  
  /* Error */
  public ZonedDateTime b04360436ж04360436жжж04360436()
  {
    // Byte code:
    //   0: invokestatic 126	kkkkkk/cccrcc:bжж0436жжжжж04360436	()I
    //   3: istore_1
    //   4: invokestatic 129	kkkkkk/cccrcc:b0436ж0436жжжжж04360436	()I
    //   7: istore_2
    //   8: invokestatic 126	kkkkkk/cccrcc:bжж0436жжжжж04360436	()I
    //   11: istore_3
    //   12: invokestatic 132	kkkkkk/cccrcc:b04360436жжжжжж04360436	()I
    //   15: istore 4
    //   17: invokestatic 135	kkkkkk/cccrcc:bж0436жжжжжж04360436	()I
    //   20: istore 5
    //   22: iload_1
    //   23: iload_2
    //   24: iadd
    //   25: iload_3
    //   26: imul
    //   27: iload 4
    //   29: irem
    //   30: iload 5
    //   32: if_icmpeq +24 -> 56
    //   35: invokestatic 126	kkkkkk/cccrcc:bжж0436жжжжж04360436	()I
    //   38: invokestatic 129	kkkkkk/cccrcc:b0436ж0436жжжжж04360436	()I
    //   41: iadd
    //   42: invokestatic 126	kkkkkk/cccrcc:bжж0436жжжжж04360436	()I
    //   45: imul
    //   46: invokestatic 132	kkkkkk/cccrcc:b04360436жжжжжж04360436	()I
    //   49: irem
    //   50: invokestatic 135	kkkkkk/cccrcc:bж0436жжжжжж04360436	()I
    //   53: if_icmpeq +3 -> 56
    //   56: aload_0
    //   57: getfield 869	kkkkkk/cccrcc:bЧЧЧЧ0427ЧЧ04270427	Lorg/threeten/bp/ZonedDateTime;
    //   60: astore 6
    //   62: aload 6
    //   64: areturn
    //   65: astore 6
    //   67: aload 6
    //   69: athrow
    //   70: astore 6
    //   72: aload 6
    //   74: athrow
    // Local variable table:
    //   start	length	slot	name	signature
    //   0	75	0	this	cccrcc
    //   3	22	1	i	int
    //   7	18	2	j	int
    //   11	16	3	k	int
    //   15	15	4	m	int
    //   20	13	5	n	int
    //   60	3	6	localZonedDateTime	ZonedDateTime
    //   65	3	6	localException1	Exception
    //   70	3	6	localException2	Exception
    // Exception table:
    //   from	to	target	type
    //   0	17	65	java/lang/Exception
    //   56	62	65	java/lang/Exception
    //   17	22	70	java/lang/Exception
  }
  
  public void b04360436ж0436ж04360436ж04360436(boolean paramBoolean)
  {
    if ((bжж0436жжжжж04360436() + b0436ж0436жжжжж04360436()) * bжж0436жжжжж04360436() % b04360436жжжжжж04360436() != bж0436жжжжжж04360436())
    {
      int i = bжж0436жжжжж04360436();
      switch (i * (b0436ж0436жжжжж04360436() + i) % b04360436жжжжжж04360436())
      {
      }
    }
    switch (0)
    {
    case 1: 
    default: 
      for (;;)
      {
        switch (0)
        {
        }
      }
    }
    this.bЧ0427042704270427Ч0427Ч0427 = paramBoolean;
  }
  
  public void b04360436ж0436ж0436ж043604360436(String paramString)
  {
    if (((bжж0436жжжжж04360436() + b0436ж0436жжжжж04360436()) * bжж0436жжжжж04360436() % b04360436жжжжжж04360436() != bж0436жжжжжж04360436()) && ((bжж0436жжжжж04360436() + b0436ж0436жжжжж04360436()) * bжж0436жжжжж04360436() % b04360436жжжжжж04360436() != bж0436жжжжжж04360436())) {}
    switch (0)
    {
    case 1: 
    default: 
      for (;;)
      {
        switch (1)
        {
        }
      }
    }
    switch (0)
    {
    case 1: 
    default: 
      for (;;)
      {
        switch (0)
        {
        }
      }
    }
    this.b04270427ЧЧЧ0427Ч04270427 = paramString;
  }
  
  public String b04360436ж0436ж0436жж04360436()
  {
    if ((bжж0436жжжжж04360436() + b0436ж0436жжжжж04360436()) * bжж0436жжжжж04360436() % b04360436жжжжжж04360436() != bж0436жжжжжж04360436()) {}
    String str = this.b0427Ч0427ЧЧ0427Ч04270427;
    int i = bжж0436жжжжж04360436();
    switch (i * (b0436ж0436жжжжж04360436() + i) % b04360436жжжжжж04360436())
    {
    }
    return str;
  }
  
  public boolean b04360436ж0436жж0436ж04360436()
  {
    if ((bжж0436жжжжж04360436() + b0436ж0436жжжжж04360436()) * bжж0436жжжжж04360436() % b04360436жжжжжж04360436() != bж0436жжжжжж04360436()) {}
    switch (1)
    {
    case 0: 
    default: 
      for (;;)
      {
        switch (0)
        {
        }
      }
    }
    return this.b0427Ч04270427ЧЧЧ04270427;
  }
  
  /* Error */
  public void b04360436ж0436жжж043604360436(boolean paramBoolean)
  {
    // Byte code:
    //   0: invokestatic 126	kkkkkk/cccrcc:bжж0436жжжжж04360436	()I
    //   3: istore_2
    //   4: invokestatic 129	kkkkkk/cccrcc:b0436ж0436жжжжж04360436	()I
    //   7: istore_3
    //   8: invokestatic 126	kkkkkk/cccrcc:bжж0436жжжжж04360436	()I
    //   11: istore 4
    //   13: invokestatic 132	kkkkkk/cccrcc:b04360436жжжжжж04360436	()I
    //   16: istore 5
    //   18: invokestatic 135	kkkkkk/cccrcc:bж0436жжжжжж04360436	()I
    //   21: istore 6
    //   23: iload_2
    //   24: iload_3
    //   25: iadd
    //   26: iload 4
    //   28: imul
    //   29: iload 5
    //   31: irem
    //   32: iload 6
    //   34: if_icmpeq +24 -> 58
    //   37: invokestatic 126	kkkkkk/cccrcc:bжж0436жжжжж04360436	()I
    //   40: invokestatic 129	kkkkkk/cccrcc:b0436ж0436жжжжж04360436	()I
    //   43: iadd
    //   44: invokestatic 126	kkkkkk/cccrcc:bжж0436жжжжж04360436	()I
    //   47: imul
    //   48: invokestatic 132	kkkkkk/cccrcc:b04360436жжжжжж04360436	()I
    //   51: irem
    //   52: invokestatic 135	kkkkkk/cccrcc:bж0436жжжжжж04360436	()I
    //   55: if_icmpeq +3 -> 58
    //   58: aload_0
    //   59: iload_1
    //   60: putfield 881	kkkkkk/cccrcc:bЧЧЧ0427ЧЧЧ04270427	Z
    //   63: return
    //   64: astore 7
    //   66: aload 7
    //   68: athrow
    //   69: astore 7
    //   71: aload 7
    //   73: athrow
    // Local variable table:
    //   start	length	slot	name	signature
    //   0	74	0	this	cccrcc
    //   0	74	1	paramBoolean	boolean
    //   3	23	2	i	int
    //   7	19	3	j	int
    //   11	18	4	k	int
    //   16	16	5	m	int
    //   21	14	6	n	int
    //   64	3	7	localException1	Exception
    //   69	3	7	localException2	Exception
    // Exception table:
    //   from	to	target	type
    //   0	23	64	java/lang/Exception
    //   58	63	69	java/lang/Exception
  }
  
  public ZonedDateTime b04360436ж0436жжжж04360436()
  {
    int i = bжж0436жжжжж04360436();
    switch (i * (b0436ж0436жжжжж04360436() + i) % b04360436жжжжжж04360436())
    {
    }
    return this.b0427Ч042704270427Ч0427Ч0427;
  }
  
  public void b04360436жж043604360436ж04360436(AmountDomainModel paramAmountDomainModel)
  {
    switch (0)
    {
    case 1: 
    default: 
      for (;;)
      {
        switch (0)
        {
        }
      }
    }
    this.bЧ04270427ЧЧ04270427Ч0427 = paramAmountDomainModel;
    int i = bжж0436жжжжж04360436();
    switch (i * (b0436ж0436жжжжж04360436() + i) % b04360436жжжжжж04360436())
    {
    }
  }
  
  public void b04360436жж04360436ж043604360436(boolean paramBoolean)
  {
    switch (1)
    {
    case 0: 
    default: 
      for (;;)
      {
        switch (0)
        {
        }
      }
    }
    int i = bжж0436жжжжж04360436();
    if (((bжж0436жжжжж04360436() + b0436ж0436жжжжж04360436()) * bжж0436жжжжж04360436() % b04360436жжжжжж04360436() == bж0436жжжжжж04360436()) || ((i + b0436ж0436жжжжж04360436()) * bжж0436жжжжж04360436() % b04360436жжжжжж04360436() != bж0436жжжжжж04360436())) {}
    this.bЧЧЧЧЧЧЧ04270427 = paramBoolean;
  }
  
  public boolean b04360436жж04360436жж04360436()
  {
    try
    {
      boolean bool = this.b04270427ЧЧ042704270427Ч0427;
      int i = bжж0436жжжжж04360436();
      int j = b0436ж0436жжжжж04360436();
      int k = bжж0436жжжжж04360436();
      switch (k * (b0436ж0436жжжжж04360436() + k) % b04360436жжжжжж04360436())
      {
      }
      if ((i + j) * bжж0436жжжжж04360436() % b04360436жжжжжж04360436() != bж0436жжжжжж04360436()) {}
      return bool;
    }
    catch (Exception localException)
    {
      throw localException;
    }
  }
  
  /* Error */
  public boolean b04360436жж0436ж0436ж04360436()
  {
    // Byte code:
    //   0: iconst_0
    //   1: istore_2
    //   2: iload_2
    //   3: istore_1
    //   4: iconst_0
    //   5: tableswitch	default:+23->28, 0:+50->55, 1:+-3->2
    //   28: iload_2
    //   29: istore_1
    //   30: iconst_1
    //   31: tableswitch	default:+21->52, 0:+-29->2, 1:+24->55
    //   52: goto -24 -> 28
    //   55: iload_1
    //   56: iconst_0
    //   57: idiv
    //   58: istore_1
    //   59: goto -4 -> 55
    //   62: astore 4
    //   64: aload_0
    //   65: getfield 892	kkkkkk/cccrcc:bЧ0427Ч04270427ЧЧ04270427	Z
    //   68: istore_3
    //   69: iload_3
    //   70: ireturn
    //   71: new 788	java/lang/NullPointerException
    //   74: dup
    //   75: invokespecial 789	java/lang/NullPointerException:<init>	()V
    //   78: athrow
    //   79: astore 4
    //   81: aload 4
    //   83: athrow
    //   84: astore 4
    //   86: goto -15 -> 71
    // Local variable table:
    //   start	length	slot	name	signature
    //   0	89	0	this	cccrcc
    //   3	56	1	i	int
    //   1	28	2	j	int
    //   68	2	3	bool	boolean
    //   62	1	4	localException1	Exception
    //   79	3	4	localException2	Exception
    //   84	1	4	localException3	Exception
    // Exception table:
    //   from	to	target	type
    //   71	79	62	java/lang/Exception
    //   64	69	79	java/lang/Exception
    //   55	59	84	java/lang/Exception
  }
  
  public void b04360436жж0436жж043604360436(ZonedDateTime paramZonedDateTime)
  {
    int i = bжж0436жжжжж04360436();
    switch (i * (b0436ж0436жжжжж04360436() + i) % b04360436жжжжжж04360436())
    {
    }
    switch (1)
    {
    case 0: 
    default: 
      for (;;)
      {
        switch (1)
        {
        }
      }
    }
    i = bжж0436жжжжж04360436();
    switch (i * (b0436ж0436жжжжж04360436() + i) % b04360436жжжжжж04360436())
    {
    default: 
      switch (0)
      {
      case 1: 
      default: 
        for (;;)
        {
          switch (1)
          {
          }
        }
      }
      break;
    }
    this.bЧЧЧЧ0427ЧЧ04270427 = paramZonedDateTime;
  }
  
  public int b04360436жж0436жжж04360436()
  {
    int i = bжж0436жжжжж04360436();
    int j = b0436ж0436жжжжж04360436();
    if (((bжж0436жжжжж04360436() + b0436ж0436жжжжж04360436()) * bжж0436жжжжж04360436() % b04360436жжжжжж04360436() == bж0436жжжжжж04360436()) || ((i + j) * bжж0436жжжжж04360436() % b04360436жжжжжж04360436() != bж0436жжжжжж04360436())) {}
    try
    {
      i = this.b0427Ч04270427Ч04270427Ч0427;
      return i;
    }
    catch (Exception localException)
    {
      switch (1)
      {
      case 0: 
      default: 
        for (;;)
        {
          switch (1)
          {
          }
        }
      }
      throw localException;
    }
  }
  
  public boolean b04360436жжж04360436ж04360436()
  {
    int i = bжж0436жжжжж04360436();
    switch (i * (b0436ж0436жжжжж04360436() + i) % b04360436жжжжжж04360436())
    {
    }
    try
    {
      boolean bool = this.b0427ЧЧЧ04270427Ч04270427;
      return bool;
    }
    catch (Exception localException)
    {
      throw localException;
    }
  }
  
  public void b04360436жжж0436ж043604360436(boolean paramBoolean)
  {
    int i = bжж0436жжжжж04360436();
    switch (i * (b0436ж0436жжжжж04360436() + i) % b04360436жжжжжж04360436())
    {
    }
    this.b0427Ч042704270427ЧЧ04270427 = paramBoolean;
    switch (1)
    {
    case 0: 
    default: 
      for (;;)
      {
        switch (0)
        {
        }
      }
    }
    i = bжж0436жжжжж04360436();
    switch (i * (b0436ж0436жжжжж04360436() + i) % b04360436жжжжжж04360436())
    {
    }
  }
  
  public AmountDomainModel b04360436жжж0436жж04360436()
  {
    if ((bжж0436жжжжж04360436() + b0436ж0436жжжжж04360436()) * bжж0436жжжжж04360436() % b04360436жжжжжж04360436() != bж0436жжжжжж04360436())
    {
      int i = bжж0436жжжжж04360436();
      switch (i * (b0436ж0436жжжжж04360436() + i) % b04360436жжжжжж04360436())
      {
      }
      switch (1)
      {
      case 0: 
      default: 
        for (;;)
        {
          switch (1)
          {
          }
        }
      }
    }
    switch (1)
    {
    case 0: 
    default: 
      for (;;)
      {
        switch (1)
        {
        }
      }
    }
    return this.b04270427Ч04270427ЧЧ04270427;
  }
  
  public boolean b04360436жжжж0436ж04360436()
  {
    boolean bool = this.b0427Ч0427ЧЧЧЧ04270427;
    switch (1)
    {
    case 0: 
    default: 
      for (;;)
      {
        switch (1)
        {
        }
      }
    }
    if ((bжж0436жжжжж04360436() + b0436ж0436жжжжж04360436()) * bжж0436жжжжж04360436() % b04360436жжжжжж04360436() != bж0436жжжжжж04360436()) {}
    return bool;
  }
  
  public void b04360436жжжжж043604360436(boolean paramBoolean)
  {
    int i = bжж0436жжжжж04360436();
    switch (i * (b0436ж0436жжжжж04360436() + i) % b04360436жжжжжж04360436())
    {
    }
    this.b0427042704270427042704270427Ч0427 = paramBoolean;
  }
  
  public void b0436ж04360436043604360436ж04360436(rrrrcc paramRrrrcc)
  {
    int i = bжж0436жжжжж04360436();
    switch (i * (b0436ж0436жжжжж04360436() + i) % b04360436жжжжжж04360436())
    {
    default: 
      switch (1)
      {
      case 0: 
      default: 
        for (;;)
        {
          switch (0)
          {
          }
        }
      }
      break;
    }
    i = bжж0436жжжжж04360436();
    switch (i * (b0436ж0436жжжжж04360436() + i) % b04360436жжжжжж04360436())
    {
    }
    switch (0)
    {
    case 1: 
    default: 
      for (;;)
      {
        switch (1)
        {
        }
      }
    }
    this.b0427042704270427Ч04270427Ч0427 = paramRrrrcc;
  }
  
  public void b0436ж0436043604360436ж043604360436(boolean paramBoolean)
  {
    switch (0)
    {
    case 1: 
    default: 
      for (;;)
      {
        switch (0)
        {
        }
      }
    }
    try
    {
      int i = bжж0436жжжжж04360436();
      int j = b0436ж0436жжжжж04360436();
      int k = b04360436жжжжжж04360436();
      switch (i * (j + i) % k)
      {
      default: 
        i = bжж0436жжжжж04360436();
        switch (i * (b0436ж0436жжжжж04360436() + i) % b04360436жжжжжж04360436())
        {
        }
        break;
      }
      this.b0427ЧЧЧ04270427Ч04270427 = paramBoolean;
      return;
    }
    catch (Exception localException)
    {
      throw localException;
    }
  }
  
  public boolean b0436ж0436043604360436жж04360436()
  {
    switch (0)
    {
    case 1: 
    default: 
      for (;;)
      {
        switch (0)
        {
        }
      }
    }
    switch (1)
    {
    case 0: 
    default: 
      for (;;)
      {
        switch (1)
        {
        }
      }
    }
    int i = bжж0436жжжжж04360436();
    switch (i * (b0436ж0436жжжжж04360436() + i) % b04360436жжжжжж04360436())
    {
    }
    boolean bool = this.bЧ0427Ч0427Ч04270427Ч0427;
    if ((bжж0436жжжжж04360436() + b0436ж0436жжжжж04360436()) * bжж0436жжжжж04360436() % b04360436жжжжжж04360436() != bж0436жжжжжж04360436()) {}
    return bool;
  }
  
  public boolean b0436ж043604360436ж0436ж04360436()
  {
    throw new Runtime("d2j fail translate: java.lang.IndexOutOfBoundsException: fromIndex < 0: -1\n\tat java.util.BitSet.nextSetBit(BitSet.java:712)\n\tat com.googlecode.dex2jar.ir.ts.array.FillArrayTransformer.makeSureAllElementAreAssigned(FillArrayTransformer.java:505)\n\tat com.googlecode.dex2jar.ir.ts.array.FillArrayTransformer.transformReportChanged(FillArrayTransformer.java:123)\n\tat com.googlecode.dex2jar.ir.ts.StatedTransformer.transform(StatedTransformer.java:10)\n\tat com.googlecode.d2j.dex.Dex2jar$2.optimize(Dex2jar.java:149)\n\tat com.googlecode.d2j.dex.Dex2Asm.convertCode(Dex2Asm.java:414)\n\tat com.googlecode.d2j.dex.ExDex2Asm.convertCode(ExDex2Asm.java:42)\n\tat com.googlecode.d2j.dex.Dex2jar$2.convertCode(Dex2jar.java:128)\n\tat com.googlecode.d2j.dex.Dex2Asm.convertMethod(Dex2Asm.java:509)\n\tat com.googlecode.d2j.dex.Dex2Asm.convertClass(Dex2Asm.java:406)\n\tat com.googlecode.d2j.dex.Dex2Asm.convertDex(Dex2Asm.java:422)\n\tat com.googlecode.d2j.dex.Dex2jar.doTranslate(Dex2jar.java:172)\n\tat com.googlecode.d2j.dex.Dex2jar.to(Dex2jar.java:272)\n\tat com.googlecode.dex2jar.tools.Dex2jarCmd.doCommandLine(Dex2jarCmd.java:108)\n\tat com.googlecode.dex2jar.tools.BaseCmd.doMain(BaseCmd.java:288)\n\tat com.googlecode.dex2jar.tools.Dex2jarCmd.main(Dex2jarCmd.java:32)\n");
  }
  
  public void b0436ж043604360436жж043604360436(String paramString)
  {
    try
    {
      int i = bжж0436жжжжж04360436();
      int j = b0436ж0436жжжжж04360436();
      int k = b04360436жжжжжж04360436();
      switch (i * (j + i) % k)
      {
      }
      switch (1)
      {
      case 0: 
      default: 
        for (;;)
        {
          switch (0)
          {
          }
        }
      }
      i = bжж0436жжжжж04360436();
      switch (i * (b0436ж0436жжжжж04360436() + i) % b04360436жжжжжж04360436())
      {
      }
      this.b042704270427Ч0427ЧЧ04270427 = paramString;
      return;
    }
    catch (Exception paramString)
    {
      throw paramString;
    }
  }
  
  public AmountDomainModel b0436ж043604360436жжж04360436()
  {
    throw new Runtime("d2j fail translate: java.lang.IndexOutOfBoundsException: fromIndex < 0: -1\n\tat java.util.BitSet.nextSetBit(BitSet.java:712)\n\tat com.googlecode.dex2jar.ir.ts.array.FillArrayTransformer.makeSureAllElementAreAssigned(FillArrayTransformer.java:505)\n\tat com.googlecode.dex2jar.ir.ts.array.FillArrayTransformer.transformReportChanged(FillArrayTransformer.java:123)\n\tat com.googlecode.dex2jar.ir.ts.StatedTransformer.transform(StatedTransformer.java:10)\n\tat com.googlecode.d2j.dex.Dex2jar$2.optimize(Dex2jar.java:149)\n\tat com.googlecode.d2j.dex.Dex2Asm.convertCode(Dex2Asm.java:414)\n\tat com.googlecode.d2j.dex.ExDex2Asm.convertCode(ExDex2Asm.java:42)\n\tat com.googlecode.d2j.dex.Dex2jar$2.convertCode(Dex2jar.java:128)\n\tat com.googlecode.d2j.dex.Dex2Asm.convertMethod(Dex2Asm.java:509)\n\tat com.googlecode.d2j.dex.Dex2Asm.convertClass(Dex2Asm.java:406)\n\tat com.googlecode.d2j.dex.Dex2Asm.convertDex(Dex2Asm.java:422)\n\tat com.googlecode.d2j.dex.Dex2jar.doTranslate(Dex2jar.java:172)\n\tat com.googlecode.d2j.dex.Dex2jar.to(Dex2jar.java:272)\n\tat com.googlecode.dex2jar.tools.Dex2jarCmd.doCommandLine(Dex2jarCmd.java:108)\n\tat com.googlecode.dex2jar.tools.BaseCmd.doMain(BaseCmd.java:288)\n\tat com.googlecode.dex2jar.tools.Dex2jarCmd.main(Dex2jarCmd.java:32)\n");
  }
  
  /* Error */
  public void b0436ж04360436ж04360436ж04360436(AmountDomainModel paramAmountDomainModel)
  {
    // Byte code:
    //   0: invokestatic 126	kkkkkk/cccrcc:bжж0436жжжжж04360436	()I
    //   3: istore_2
    //   4: invokestatic 129	kkkkkk/cccrcc:b0436ж0436жжжжж04360436	()I
    //   7: istore_3
    //   8: invokestatic 126	kkkkkk/cccrcc:bжж0436жжжжж04360436	()I
    //   11: istore 4
    //   13: invokestatic 132	kkkkkk/cccrcc:b04360436жжжжжж04360436	()I
    //   16: istore 5
    //   18: invokestatic 135	kkkkkk/cccrcc:bж0436жжжжжж04360436	()I
    //   21: istore 6
    //   23: iload_2
    //   24: iload_3
    //   25: iadd
    //   26: iload 4
    //   28: imul
    //   29: iload 5
    //   31: irem
    //   32: iload 6
    //   34: if_icmpeq +3 -> 37
    //   37: aload_0
    //   38: aload_1
    //   39: putfield 916	kkkkkk/cccrcc:bЧЧЧЧЧ04270427Ч0427	Lcom/mobile/business/statements/model/AmountDomainModel;
    //   42: return
    //   43: astore_1
    //   44: aload_1
    //   45: athrow
    //   46: astore_1
    //   47: aload_1
    //   48: athrow
    //   49: astore_1
    //   50: aload_1
    //   51: athrow
    // Local variable table:
    //   start	length	slot	name	signature
    //   0	52	0	this	cccrcc
    //   0	52	1	paramAmountDomainModel	AmountDomainModel
    //   3	23	2	i	int
    //   7	19	3	j	int
    //   11	18	4	k	int
    //   16	16	5	m	int
    //   21	14	6	n	int
    // Exception table:
    //   from	to	target	type
    //   37	42	43	java/lang/Exception
    //   0	8	46	java/lang/Exception
    //   44	46	46	java/lang/Exception
    //   8	23	49	java/lang/Exception
  }
  
  public void b0436ж04360436ж0436ж043604360436(String paramString)
  {
    int i = 0;
    int j = bжж0436жжжжж04360436();
    switch (j * (b0436ж0436жжжжж04360436() + j) % b04360436жжжжжж04360436())
    {
    }
    try
    {
      this.b0427Ч0427ЧЧ0427Ч04270427 = paramString;
      try
      {
        throw new NullPointerException();
      }
      catch (Exception paramString)
      {
        try
        {
          for (;;)
          {
            j = i / 0;
            i = j;
          }
          try
          {
            i /= 0;
          }
          catch (Exception paramString) {}
        }
        catch (Exception paramString)
        {
          switch (1)
          {
          case 0: 
          default: 
            for (;;)
            {
              switch (1)
              {
              }
            }
          }
        }
      }
      return;
    }
    catch (Exception paramString)
    {
      throw paramString;
    }
  }
  
  public AmountDomainModel b0436ж04360436ж0436жж04360436()
  {
    switch (1)
    {
    case 0: 
    default: 
      for (;;)
      {
        switch (0)
        {
        }
      }
    }
    try
    {
      AmountDomainModel localAmountDomainModel = this.b042704270427ЧЧ0427Ч04270427;
      int i = bжж0436жжжжж04360436();
      int j = b0436ж0436жжжжж04360436();
      int k = bжж0436жжжжж04360436();
      int m = b04360436жжжжжж04360436();
      int n = bж0436жжжжжж04360436();
      if (((i + j) * k % m != n) && ((bжж0436жжжжж04360436() + b0436ж0436жжжжж04360436()) * bжж0436жжжжж04360436() % b04360436жжжжжж04360436() != bж0436жжжжжж04360436())) {}
      return localAmountDomainModel;
    }
    catch (Exception localException)
    {
      throw localException;
    }
  }
  
  public boolean b0436ж04360436жж0436ж04360436()
  {
    try
    {
      throw new NullPointerException();
    }
    catch (Exception localException1)
    {
      try
      {
        boolean bool = this.b0427042704270427ЧЧЧ04270427;
        int i = bжж0436жжжжж04360436();
        switch (i * (b0436ж0436жжжжж04360436() + i) % b04360436жжжжжж04360436())
        {
        }
        return bool;
      }
      catch (Exception localException2)
      {
        throw localException2;
      }
    }
  }
  
  public void b0436ж04360436жжж043604360436(boolean paramBoolean)
  {
    if ((bжж0436жжжжж04360436() + b0436ж0436жжжжж04360436()) * bжж0436жжжжж04360436() % b04360436жжжжжж04360436() != bж0436жжжжжж04360436()) {}
    this.bЧ0427Ч0427ЧЧЧ04270427 = paramBoolean;
    if ((bжж0436жжжжж04360436() + b0436ж0436жжжжж04360436()) * bжж0436жжжжж04360436() % b04360436жжжжжж04360436() != bж0436жжжжжж04360436()) {}
  }
  
  public AmountDomainModel b0436ж04360436жжжж04360436()
  {
    return this.bЧЧЧЧЧ04270427Ч0427;
  }
  
  public void b0436ж0436ж043604360436ж04360436(boolean paramBoolean)
  {
    if ((bжж0436жжжжж04360436() + b0436ж0436жжжжж04360436()) * bжж0436жжжжж04360436() % b04360436жжжжжж04360436() != bж0436жжжжжж04360436()) {}
    switch (1)
    {
    case 0: 
    default: 
      for (;;)
      {
        int i = bжж0436жжжжж04360436();
        switch (i * (b0436ж0436жжжжж04360436() + i) % b04360436жжжжжж04360436())
        {
        }
        switch (0)
        {
        }
      }
    }
    this.bЧЧЧ0427Ч04270427Ч0427 = paramBoolean;
  }
  
  /* Error */
  public void b0436ж0436ж04360436ж043604360436(boolean paramBoolean)
  {
    // Byte code:
    //   0: invokestatic 126	kkkkkk/cccrcc:bжж0436жжжжж04360436	()I
    //   3: istore_2
    //   4: invokestatic 129	kkkkkk/cccrcc:b0436ж0436жжжжж04360436	()I
    //   7: istore_3
    //   8: invokestatic 126	kkkkkk/cccrcc:bжж0436жжжжж04360436	()I
    //   11: istore 4
    //   13: invokestatic 132	kkkkkk/cccrcc:b04360436жжжжжж04360436	()I
    //   16: istore 5
    //   18: invokestatic 135	kkkkkk/cccrcc:bж0436жжжжжж04360436	()I
    //   21: istore 6
    //   23: iload_2
    //   24: iload_3
    //   25: iadd
    //   26: iload 4
    //   28: imul
    //   29: iload 5
    //   31: irem
    //   32: iload 6
    //   34: if_icmpeq +3 -> 37
    //   37: invokestatic 126	kkkkkk/cccrcc:bжж0436жжжжж04360436	()I
    //   40: istore_2
    //   41: iload_2
    //   42: invokestatic 129	kkkkkk/cccrcc:b0436ж0436жжжжж04360436	()I
    //   45: iload_2
    //   46: iadd
    //   47: imul
    //   48: invokestatic 132	kkkkkk/cccrcc:b04360436жжжжжж04360436	()I
    //   51: irem
    //   52: tableswitch	default:+20->72, 0:+20->72
    //   72: iconst_1
    //   73: tableswitch	default:+23->96, 0:+-36->37, 1:+50->123
    //   96: iconst_0
    //   97: tableswitch	default:+23->120, 0:+26->123, 1:+-60->37
    //   120: goto -24 -> 96
    //   123: aload_0
    //   124: iload_1
    //   125: putfield 927	kkkkkk/cccrcc:bЧ0427Ч0427Ч0427Ч04270427	Z
    //   128: return
    //   129: astore 7
    //   131: aload 7
    //   133: athrow
    //   134: astore 7
    //   136: aload 7
    //   138: athrow
    // Local variable table:
    //   start	length	slot	name	signature
    //   0	139	0	this	cccrcc
    //   0	139	1	paramBoolean	boolean
    //   3	45	2	i	int
    //   7	19	3	j	int
    //   11	18	4	k	int
    //   16	16	5	m	int
    //   21	14	6	n	int
    //   129	3	7	localException1	Exception
    //   134	3	7	localException2	Exception
    // Exception table:
    //   from	to	target	type
    //   0	23	129	java/lang/Exception
    //   123	128	134	java/lang/Exception
  }
  
  @ooiiio("Trivial")
  public boolean b0436ж0436ж04360436жж04360436()
  {
    switch (0)
    {
    case 1: 
    default: 
      for (;;)
      {
        switch (0)
        {
        }
      }
    }
    boolean bool = bжж04360436жжжж04360436().bп043F043Fп043Fппппп();
    if (((bжж0436жжжжж04360436() + b0436ж0436жжжжж04360436()) * bжж0436жжжжж04360436() % b04360436жжжжжж04360436() != bж0436жжжжжж04360436()) && ((bжж0436жжжжж04360436() + b0436ж0436жжжжж04360436()) * bжж0436жжжжж04360436() % b04360436жжжжжж04360436() != bж0436жжжжжж04360436())) {}
    return bool;
  }
  
  public boolean b0436ж0436ж0436ж0436ж04360436()
  {
    switch (0)
    {
    case 1: 
    default: 
      for (;;)
      {
        switch (1)
        {
        }
      }
    }
    int i = bжж0436жжжжж04360436();
    switch (i * (b0436ж0436жжжжж04360436() + i) % b04360436жжжжжж04360436())
    {
    }
    if ((bжж0436жжжжж04360436() + b0436ж0436жжжжж04360436()) * bжж0436жжжжж04360436() % b04360436жжжжжж04360436() != bж0436жжжжжж04360436()) {}
    try
    {
      boolean bool = this.b04270427Ч0427042704270427Ч0427;
      return bool;
    }
    catch (Exception localException)
    {
      throw localException;
    }
  }
  
  public void b0436ж0436ж0436жж043604360436(AmountDomainModel paramAmountDomainModel)
  {
    if ((bжж0436жжжжж04360436() + b0436ж0436жжжжж04360436()) * bжж0436жжжжж04360436() % b04360436жжжжжж04360436() != bж0436жжжжжж04360436()) {}
    switch (0)
    {
    case 1: 
    default: 
      for (;;)
      {
        switch (0)
        {
        }
      }
    }
    for (;;)
    {
      try
      {
        int i = bжж0436жжжжж04360436();
        switch (i * (b0436ж0436жжжжж04360436() + i) % b04360436жжжжжж04360436())
        {
        case 0: 
          this.bЧ0427ЧЧ0427ЧЧ04270427 = paramAmountDomainModel;
          return;
        }
      }
      catch (Exception paramAmountDomainModel)
      {
        throw paramAmountDomainModel;
      }
    }
  }
  
  public rrrrcc b0436ж0436ж0436жжж04360436()
  {
    return this.b0427042704270427Ч04270427Ч0427;
  }
  
  public void b0436ж0436жж04360436ж04360436(boolean paramBoolean)
  {
    throw new Runtime("d2j fail translate: java.lang.IndexOutOfBoundsException: fromIndex < 0: -1\n\tat java.util.BitSet.nextSetBit(BitSet.java:712)\n\tat com.googlecode.dex2jar.ir.ts.array.FillArrayTransformer.makeSureAllElementAreAssigned(FillArrayTransformer.java:505)\n\tat com.googlecode.dex2jar.ir.ts.array.FillArrayTransformer.transformReportChanged(FillArrayTransformer.java:123)\n\tat com.googlecode.dex2jar.ir.ts.StatedTransformer.transform(StatedTransformer.java:10)\n\tat com.googlecode.d2j.dex.Dex2jar$2.optimize(Dex2jar.java:149)\n\tat com.googlecode.d2j.dex.Dex2Asm.convertCode(Dex2Asm.java:414)\n\tat com.googlecode.d2j.dex.ExDex2Asm.convertCode(ExDex2Asm.java:42)\n\tat com.googlecode.d2j.dex.Dex2jar$2.convertCode(Dex2jar.java:128)\n\tat com.googlecode.d2j.dex.Dex2Asm.convertMethod(Dex2Asm.java:509)\n\tat com.googlecode.d2j.dex.Dex2Asm.convertClass(Dex2Asm.java:406)\n\tat com.googlecode.d2j.dex.Dex2Asm.convertDex(Dex2Asm.java:422)\n\tat com.googlecode.d2j.dex.Dex2jar.doTranslate(Dex2jar.java:172)\n\tat com.googlecode.d2j.dex.Dex2jar.to(Dex2jar.java:272)\n\tat com.googlecode.dex2jar.tools.Dex2jarCmd.doCommandLine(Dex2jarCmd.java:108)\n\tat com.googlecode.dex2jar.tools.BaseCmd.doMain(BaseCmd.java:288)\n\tat com.googlecode.dex2jar.tools.Dex2jarCmd.main(Dex2jarCmd.java:32)\n");
  }
  
  public void b0436ж0436жж0436ж043604360436(String paramString)
  {
    throw new Runtime("d2j fail translate: java.lang.IndexOutOfBoundsException: fromIndex < 0: -1\n\tat java.util.BitSet.nextSetBit(BitSet.java:712)\n\tat com.googlecode.dex2jar.ir.ts.array.FillArrayTransformer.makeSureAllElementAreAssigned(FillArrayTransformer.java:505)\n\tat com.googlecode.dex2jar.ir.ts.array.FillArrayTransformer.transformReportChanged(FillArrayTransformer.java:123)\n\tat com.googlecode.dex2jar.ir.ts.StatedTransformer.transform(StatedTransformer.java:10)\n\tat com.googlecode.d2j.dex.Dex2jar$2.optimize(Dex2jar.java:149)\n\tat com.googlecode.d2j.dex.Dex2Asm.convertCode(Dex2Asm.java:414)\n\tat com.googlecode.d2j.dex.ExDex2Asm.convertCode(ExDex2Asm.java:42)\n\tat com.googlecode.d2j.dex.Dex2jar$2.convertCode(Dex2jar.java:128)\n\tat com.googlecode.d2j.dex.Dex2Asm.convertMethod(Dex2Asm.java:509)\n\tat com.googlecode.d2j.dex.Dex2Asm.convertClass(Dex2Asm.java:406)\n\tat com.googlecode.d2j.dex.Dex2Asm.convertDex(Dex2Asm.java:422)\n\tat com.googlecode.d2j.dex.Dex2jar.doTranslate(Dex2jar.java:172)\n\tat com.googlecode.d2j.dex.Dex2jar.to(Dex2jar.java:272)\n\tat com.googlecode.dex2jar.tools.Dex2jarCmd.doCommandLine(Dex2jarCmd.java:108)\n\tat com.googlecode.dex2jar.tools.BaseCmd.doMain(BaseCmd.java:288)\n\tat com.googlecode.dex2jar.tools.Dex2jarCmd.main(Dex2jarCmd.java:32)\n");
  }
  
  public String b0436ж0436жж0436жж04360436()
  {
    switch (0)
    {
    case 1: 
    default: 
      for (;;)
      {
        switch (1)
        {
        }
      }
    }
    int i = bжж0436жжжжж04360436();
    switch (i * (b0436ж0436жжжжж04360436() + i) % b04360436жжжжжж04360436())
    {
    }
    switch (1)
    {
    case 0: 
    default: 
      for (;;)
      {
        switch (1)
        {
        }
      }
    }
    String str = this.bЧ0427042704270427ЧЧ04270427;
    if ((bжж0436жжжжж04360436() + b0436ж0436жжжжж04360436()) * bжж0436жжжжж04360436() % b04360436жжжжжж04360436() != bж0436жжжжжж04360436()) {}
    return str;
  }
  
  public boolean b0436ж0436жжж0436ж04360436()
  {
    int i = 5;
    for (;;)
    {
      if ((bжж0436жжжжж04360436() + b0436ж0436жжжжж04360436()) * bжж0436жжжжж04360436() % b04360436жжжжжж04360436() != bж0436жжжжжж04360436()) {}
      try
      {
        i /= 0;
      }
      catch (Exception localException1)
      {
        try
        {
          boolean bool = this.b042704270427ЧЧЧЧ04270427;
          return bool;
        }
        catch (Exception localException2)
        {
          switch (1)
          {
          case 0: 
          default: 
            for (;;)
            {
              switch (1)
              {
              }
            }
          }
          throw localException2;
        }
      }
    }
  }
  
  public void b0436ж0436жжжж043604360436(String paramString)
  {
    switch (1)
    {
    case 0: 
    default: 
      for (;;)
      {
        switch (1)
        {
        }
      }
    }
    if ((bжж0436жжжжж04360436() + b0436ж0436жжжжж04360436()) * bжж0436жжжжж04360436() % b04360436жжжжжж04360436() != bж0436жжжжжж04360436())
    {
      int i = bжж0436жжжжж04360436();
      switch (i * (b0436ж0436жжжжж04360436() + i) % b04360436жжжжжж04360436())
      {
      }
    }
    this.b04270427ЧЧЧЧЧ04270427 = paramString;
  }
  
  public void b0436жж0436043604360436ж04360436(ZonedDateTime paramZonedDateTime)
  {
    int i = bжж0436жжжжж04360436();
    int j = b0436ж0436жжжжж04360436();
    if ((bжж0436жжжжж04360436() + b0436ж0436жжжжж04360436()) * bжж0436жжжжж04360436() % b04360436жжжжжж04360436() != bж0436жжжжжж04360436()) {}
    switch (i * (j + i) % b04360436жжжжжж04360436())
    {
    }
    try
    {
      this.b04270427Ч0427Ч04270427Ч0427 = paramZonedDateTime;
      return;
    }
    catch (Exception paramZonedDateTime)
    {
      throw paramZonedDateTime;
    }
  }
  
  public void b0436жж043604360436ж043604360436(ZonedDateTime paramZonedDateTime)
  {
    int i = bжж0436жжжжж04360436();
    switch (i * (b0436ж0436жжжжж04360436() + i) % b04360436жжжжжж04360436())
    {
    default: 
      i = bжж0436жжжжж04360436();
      switch (i * (b0436ж0436жжжжж04360436() + i) % b04360436жжжжжж04360436())
      {
      }
      break;
    }
    this.bЧ042704270427Ч0427Ч04270427 = paramZonedDateTime;
  }
  
  public boolean b0436жж043604360436жж04360436()
  {
    int i = 5;
    try
    {
      for (;;)
      {
        i /= 0;
      }
      return this.b0427Ч0427ЧЧ04270427Ч0427;
    }
    catch (Exception localException) {}
  }
  
  /* Error */
  public boolean b0436жж04360436ж0436ж04360436()
  {
    // Byte code:
    //   0: invokestatic 126	kkkkkk/cccrcc:bжж0436жжжжж04360436	()I
    //   3: istore_1
    //   4: invokestatic 129	kkkkkk/cccrcc:b0436ж0436жжжжж04360436	()I
    //   7: istore_2
    //   8: invokestatic 132	kkkkkk/cccrcc:b04360436жжжжжж04360436	()I
    //   11: istore_3
    //   12: invokestatic 126	kkkkkk/cccrcc:bжж0436жжжжж04360436	()I
    //   15: istore 4
    //   17: iload 4
    //   19: invokestatic 129	kkkkkk/cccrcc:b0436ж0436жжжжж04360436	()I
    //   22: iload 4
    //   24: iadd
    //   25: imul
    //   26: invokestatic 132	kkkkkk/cccrcc:b04360436жжжжжж04360436	()I
    //   29: irem
    //   30: tableswitch	default:+18->48, 0:+18->48
    //   48: iload_1
    //   49: iload_2
    //   50: iload_1
    //   51: iadd
    //   52: imul
    //   53: iload_3
    //   54: irem
    //   55: tableswitch	default:+17->72, 0:+17->72
    //   72: aload_0
    //   73: getfield 964	kkkkkk/cccrcc:bЧ042704270427042704270427Ч0427	Z
    //   76: istore 5
    //   78: iload 5
    //   80: ireturn
    //   81: astore 6
    //   83: aload 6
    //   85: athrow
    //   86: astore 6
    //   88: aload 6
    //   90: athrow
    // Local variable table:
    //   start	length	slot	name	signature
    //   0	91	0	this	cccrcc
    //   3	50	1	i	int
    //   7	45	2	j	int
    //   11	44	3	k	int
    //   15	11	4	m	int
    //   76	3	5	bool	boolean
    //   81	3	6	localException1	Exception
    //   86	3	6	localException2	Exception
    // Exception table:
    //   from	to	target	type
    //   72	78	81	java/lang/Exception
    //   0	12	86	java/lang/Exception
    //   83	86	86	java/lang/Exception
  }
  
  public void b0436жж04360436жж043604360436(boolean paramBoolean)
  {
    int i = bжж0436жжжжж04360436();
    switch (i * (b0436ж0436жжжжж04360436() + i) % b04360436жжжжжж04360436())
    {
    }
    this.b0427ЧЧ0427042704270427Ч0427 = paramBoolean;
  }
  
  public String b0436жж04360436жжж04360436()
  {
    int i = bжж0436жжжжж04360436();
    switch (i * (b0436ж0436жжжжж04360436() + i) % b04360436жжжжжж04360436())
    {
    }
    String str = this.b04270427ЧЧЧЧЧ04270427;
    i = bжж0436жжжжж04360436();
    switch (i * (b0436ж0436жжжжж04360436() + i) % b04360436жжжжжж04360436())
    {
    }
    return str;
  }
  
  public void b0436жж0436ж04360436ж04360436(@Nullable List<String> paramList, @Nullable List<Map<String, String>> paramList1)
  {
    if (paramList != null) {}
    try
    {
      if (!paramList.isEmpty()) {
        this.bЧЧ042704270427Ч0427Ч0427 = ((String)paramList.get(0));
      }
      while (paramList1 == null) {
        return;
      }
    }
    catch (Exception paramList)
    {
      for (;;)
      {
        try
        {
          paramList = paramList1.iterator();
          if (!paramList.hasNext()) {
            continue;
          }
          paramList1 = (Map)paramList.next();
        }
        catch (Exception paramList)
        {
          int i;
          int j;
          int k;
          int m;
          int n;
          String str;
          throw paramList;
        }
        try
        {
          i = bжж0436жжжжж04360436();
          j = b0436ж0436жжжжж04360436();
          k = bжж0436жжжжж04360436();
          m = b04360436жжжжжж04360436();
          n = bж0436жжжжжж04360436();
          if (((i + j) * k % m != n) && ((bжж0436жжжжж04360436() + b0436ж0436жжжжж04360436()) * bжж0436жжжжж04360436() % b04360436жжжжжж04360436() != bж0436жжжжжж04360436())) {}
          str = gguuuu.bккккк043Aкк043A043A("B.:D5", '\031', '\001');
          this.bЧЧ042704270427Ч0427Ч0427 = ((String)paramList1.get(str));
          paramList1 = this.bЧЧ042704270427Ч0427Ч0427;
          if (paramList1 != null) {
            return;
          }
        }
        catch (Exception paramList)
        {
          throw paramList;
        }
      }
      paramList = paramList;
      try
      {
        throw paramList;
      }
      catch (Exception paramList)
      {
        throw paramList;
      }
    }
  }
  
  /* Error */
  public void b0436жж0436ж0436ж043604360436(List<String> paramList)
  {
    // Byte code:
    //   0: aload_0
    //   1: aload_1
    //   2: putfield 846	kkkkkk/cccrcc:b0427ЧЧЧЧ0427Ч04270427	Ljava/util/List;
    //   5: invokestatic 126	kkkkkk/cccrcc:bжж0436жжжжж04360436	()I
    //   8: istore_2
    //   9: invokestatic 129	kkkkkk/cccrcc:b0436ж0436жжжжж04360436	()I
    //   12: istore_3
    //   13: invokestatic 126	kkkkkk/cccrcc:bжж0436жжжжж04360436	()I
    //   16: istore 4
    //   18: iload 4
    //   20: invokestatic 129	kkkkkk/cccrcc:b0436ж0436жжжжж04360436	()I
    //   23: iload 4
    //   25: iadd
    //   26: imul
    //   27: invokestatic 132	kkkkkk/cccrcc:b04360436жжжжжж04360436	()I
    //   30: irem
    //   31: tableswitch	default:+17->48, 0:+17->48
    //   48: invokestatic 132	kkkkkk/cccrcc:b04360436жжжжжж04360436	()I
    //   51: istore 4
    //   53: iload_2
    //   54: iload_3
    //   55: iload_2
    //   56: iadd
    //   57: imul
    //   58: iload 4
    //   60: irem
    //   61: tableswitch	default:+19->80, 0:+19->80
    //   80: return
    //   81: astore_1
    //   82: aload_1
    //   83: athrow
    //   84: astore_1
    //   85: aload_1
    //   86: athrow
    //   87: astore_1
    //   88: aload_1
    //   89: athrow
    // Local variable table:
    //   start	length	slot	name	signature
    //   0	90	0	this	cccrcc
    //   0	90	1	paramList	List<String>
    //   8	50	2	i	int
    //   12	45	3	j	int
    //   16	45	4	k	int
    // Exception table:
    //   from	to	target	type
    //   0	5	81	java/lang/Exception
    //   82	84	84	java/lang/Exception
    //   5	13	87	java/lang/Exception
    //   48	53	87	java/lang/Exception
  }
  
  public String b0436жж0436ж0436жж04360436()
  {
    int i = bжж0436жжжжж04360436();
    switch (i * (b0436ж0436жжжжж04360436() + i) % b04360436жжжжжж04360436())
    {
    }
    try
    {
      String str = this.b04270427ЧЧЧ0427Ч04270427;
      return str;
    }
    catch (Exception localException)
    {
      throw localException;
    }
  }
  
  public boolean b0436жж0436жж0436ж04360436()
  {
    try
    {
      boolean bool = this.b04270427Ч0427ЧЧЧ04270427;
      if ((bжж0436жжжжж04360436() + b0436ж0436жжжжж04360436()) * bжж0436жжжжж04360436() % b04360436жжжжжж04360436() != bж0436жжжжжж04360436()) {}
      return bool;
    }
    catch (Exception localException)
    {
      throw localException;
    }
  }
  
  public void b0436жж0436жжж043604360436(boolean paramBoolean)
  {
    switch (1)
    {
    case 0: 
    default: 
      for (;;)
      {
        switch (1)
        {
        }
      }
    }
    if (((bжж0436жжжжж04360436() + b0436ж0436жжжжж04360436()) * bжж0436жжжжж04360436() % b04360436жжжжжж04360436() != bж0436жжжжжж04360436()) && ((bжж0436жжжжж04360436() + b0436ж0436жжжжж04360436()) * bжж0436жжжжж04360436() % b04360436жжжжжж04360436() != bж0436жжжжжж04360436())) {}
    this.bЧ04270427ЧЧЧЧ04270427 = paramBoolean;
  }
  
  /* Error */
  public List<String> b0436жж0436жжжж04360436()
  {
    // Byte code:
    //   0: aload_0
    //   1: getfield 996	kkkkkk/cccrcc:b04270427Ч04270427Ч0427Ч0427	Ljava/util/List;
    //   4: astore 6
    //   6: invokestatic 126	kkkkkk/cccrcc:bжж0436жжжжж04360436	()I
    //   9: istore_1
    //   10: invokestatic 129	kkkkkk/cccrcc:b0436ж0436жжжжж04360436	()I
    //   13: istore_2
    //   14: invokestatic 126	kkkkkk/cccrcc:bжж0436жжжжж04360436	()I
    //   17: istore_3
    //   18: iload_3
    //   19: invokestatic 129	kkkkkk/cccrcc:b0436ж0436жжжжж04360436	()I
    //   22: iload_3
    //   23: iadd
    //   24: imul
    //   25: invokestatic 132	kkkkkk/cccrcc:b04360436жжжжжж04360436	()I
    //   28: irem
    //   29: tableswitch	default:+19->48, 0:+19->48
    //   48: invokestatic 126	kkkkkk/cccrcc:bжж0436жжжжж04360436	()I
    //   51: istore_3
    //   52: invokestatic 132	kkkkkk/cccrcc:b04360436жжжжжж04360436	()I
    //   55: istore 4
    //   57: invokestatic 135	kkkkkk/cccrcc:bж0436жжжжжж04360436	()I
    //   60: istore 5
    //   62: iload_1
    //   63: iload_2
    //   64: iadd
    //   65: iload_3
    //   66: imul
    //   67: iload 4
    //   69: irem
    //   70: iload 5
    //   72: if_icmpeq +3 -> 75
    //   75: aload 6
    //   77: areturn
    //   78: astore 6
    //   80: aload 6
    //   82: athrow
    //   83: astore 6
    //   85: aload 6
    //   87: athrow
    // Local variable table:
    //   start	length	slot	name	signature
    //   0	88	0	this	cccrcc
    //   9	56	1	i	int
    //   13	52	2	j	int
    //   17	50	3	k	int
    //   55	15	4	m	int
    //   60	13	5	n	int
    //   4	72	6	localList	List
    //   78	3	6	localException1	Exception
    //   83	3	6	localException2	Exception
    // Exception table:
    //   from	to	target	type
    //   0	6	78	java/lang/Exception
    //   48	62	78	java/lang/Exception
    //   6	14	83	java/lang/Exception
  }
  
  public void b0436жжж043604360436ж04360436(boolean paramBoolean)
  {
    switch (0)
    {
    case 1: 
    default: 
      for (;;)
      {
        int i = bжж0436жжжжж04360436();
        switch (i * (b0436ж0436жжжжж04360436() + i) % b04360436жжжжжж04360436())
        {
        }
        switch (1)
        {
        }
      }
    }
    try
    {
      if ((bжж0436жжжжж04360436() + b0436ж0436жжжжж04360436()) * bжж0436жжжжж04360436() % b04360436жжжжжж04360436() != bж0436жжжжжж04360436()) {}
      this.bЧЧ0427ЧЧ04270427Ч0427 = paramBoolean;
      return;
    }
    catch (Exception localException)
    {
      throw localException;
    }
  }
  
  public void b0436жжж04360436ж043604360436(String paramString)
  {
    this.bЧЧЧ0427Ч0427Ч04270427 = paramString;
    try
    {
      throw new NullPointerException();
    }
    catch (Exception paramString)
    {
      if ((bжж0436жжжжж04360436() + b0436ж0436жжжжж04360436()) * bжж0436жжжжж04360436() % b04360436жжжжжж04360436() == bж0436жжжжжж04360436()) {}
    }
  }
  
  public List<ooooii> b0436жжж04360436жж04360436()
  {
    int i = bжж0436жжжжж04360436();
    switch (i * (b0436ж0436жжжжж04360436() + i) % b04360436жжжжжж04360436())
    {
    }
    return this.b0427042704270427Ч0427Ч04270427;
  }
  
  public boolean b0436жжж0436ж0436ж04360436()
  {
    boolean bool = this.bЧЧЧ04270427ЧЧ04270427;
    switch (0)
    {
    case 1: 
    default: 
      for (;;)
      {
        switch (0)
        {
        }
      }
    }
    return bool;
  }
  
  public void b0436жжж0436жж043604360436(boolean paramBoolean)
  {
    if (((bжж0436жжжжж04360436() + b0436ж0436жжжжж04360436()) * bжж0436жжжжж04360436() % b04360436жжжжжж04360436() != bж0436жжжжжж04360436()) && ((bжж0436жжжжж04360436() + b0436ж0436жжжжж04360436()) * bжж0436жжжжж04360436() % b04360436жжжжжж04360436() != bж0436жжжжжж04360436())) {}
    this.bЧ042704270427ЧЧЧ04270427 = paramBoolean;
    switch (1)
    {
    case 0: 
    default: 
      for (;;)
      {
        switch (1)
        {
        case 0: 
        default: 
          for (;;)
          {
            switch (1)
            {
            }
          }
        }
        switch (1)
        {
        }
      }
    }
  }
  
  public AmountDomainModel b0436жжж0436жжж04360436()
  {
    switch (0)
    {
    case 1: 
    default: 
      for (;;)
      {
        switch (1)
        {
        }
      }
    }
    AmountDomainModel localAmountDomainModel = this.b042704270427ЧЧ04270427Ч0427;
    if ((bжж0436жжжжж04360436() + b0436ж0436жжжжж04360436()) * bжж0436жжжжж04360436() % b04360436жжжжжж04360436() != bж0436жжжжжж04360436())
    {
      switch (1)
      {
      case 0: 
      default: 
        for (;;)
        {
          switch (0)
          {
          }
        }
      }
      if ((bжж0436жжжжж04360436() + b0436ж0436жжжжж04360436()) * bжж0436жжжжж04360436() % b04360436жжжжжж04360436() == bж0436жжжжжж04360436()) {}
    }
    return localAmountDomainModel;
  }
  
  public boolean b0436жжжж04360436ж04360436()
  {
    if ((bжж0436жжжжж04360436() + b0436ж0436жжжжж04360436()) * bжж0436жжжжж04360436() % b04360436жжжжжж04360436() != bж0436жжжжжж04360436())
    {
      switch (0)
      {
      case 1: 
      default: 
        for (;;)
        {
          switch (0)
          {
          }
        }
      }
      int i = bжж0436жжжжж04360436();
      switch (i * (b0436ж0436жжжжж04360436() + i) % b04360436жжжжжж04360436())
      {
      }
    }
    try
    {
      boolean bool = this.b0427ЧЧЧЧЧЧ04270427;
      return bool;
    }
    catch (Exception localException)
    {
      throw localException;
    }
  }
  
  public void b0436жжжж0436ж043604360436(AmountDomainModel paramAmountDomainModel)
  {
    try
    {
      this.b04270427Ч04270427ЧЧ04270427 = paramAmountDomainModel;
      int i = bжж0436жжжжж04360436();
      int j = b0436ж0436жжжжж04360436();
      int k = b04360436жжжжжж04360436();
      switch (0)
      {
      case 1: 
      default: 
        for (;;)
        {
          switch (1)
          {
          }
        }
      }
      switch (i * (j + i) % k)
      {
      default: 
        i = bжж0436жжжжж04360436();
        switch (i * (b0436ж0436жжжжж04360436() + i) % b04360436жжжжжж04360436())
        {
        }
        break;
      }
      return;
    }
    catch (Exception paramAmountDomainModel)
    {
      throw paramAmountDomainModel;
    }
  }
  
  public String b0436жжжж0436жж04360436()
  {
    if ((bжж0436жжжжж04360436() + b0436ж0436жжжжж04360436()) * bжж0436жжжжж04360436() % b04360436жжжжжж04360436() != bж0436жжжжжж04360436()) {}
    String str = this.bЧ04270427Ч0427ЧЧ04270427;
    if ((bжж0436жжжжж04360436() + b0436ж0436жжжжж04360436()) * bжж0436жжжжж04360436() % b04360436жжжжжж04360436() != bж0436жжжжжж04360436()) {}
    return str;
  }
  
  public boolean b0436жжжжж0436ж04360436()
  {
    return this.b0427ЧЧЧ042704270427Ч0427;
  }
  
  public void b0436жжжжжж043604360436(boolean paramBoolean)
  {
    try
    {
      int i = bжж0436жжжжж04360436();
      int j = b0436ж0436жжжжж04360436();
      int k = bжж0436жжжжж04360436();
      int m = b04360436жжжжжж04360436();
      int n = bж0436жжжжжж04360436();
      int i1 = bжж0436жжжжж04360436();
      switch (i1 * (b0436ж0436жжжжж04360436() + i1) % b04360436жжжжжж04360436())
      {
      }
      if ((i + j) * k % m != n) {}
      switch (0)
      {
      case 1: 
      default: 
        for (;;)
        {
          switch (0)
          {
          }
        }
      }
      this.bЧЧ0427Ч042704270427Ч0427 = paramBoolean;
      return;
    }
    catch (Exception localException)
    {
      throw localException;
    }
  }
  
  public void bж043604360436043604360436ж04360436(crrrcc paramCrrrcc)
  {
    for (;;)
    {
      try
      {
        int i = bжж0436жжжжж04360436();
        switch (i * (b0436ж0436жжжжж04360436() + i) % b04360436жжжжжж04360436())
        {
        case 0: 
          this.bЧЧЧЧ042704270427Ч0427 = paramCrrrcc;
          i = bжж0436жжжжж04360436();
          switch (i * (b0436ж0436жжжжж04360436() + i) % b04360436жжжжжж04360436())
          {
          }
          switch (0)
          {
          case 1: 
          default: 
            switch (0)
            {
            }
            break;
          }
          return;
        }
      }
      catch (Exception paramCrrrcc)
      {
        throw paramCrrrcc;
      }
    }
  }
  
  public boolean bж04360436043604360436жж04360436()
  {
    switch (1)
    {
    case 0: 
    default: 
      for (;;)
      {
        switch (0)
        {
        }
      }
    }
    if ((bжж0436жжжжж04360436() + b0436ж0436жжжжж04360436()) * bжж0436жжжжж04360436() % b04360436жжжжжж04360436() != bж0436жжжжжж04360436())
    {
      int i = bжж0436жжжжж04360436();
      switch (i * (b0436ж0436жжжжж04360436() + i) % b04360436жжжжжж04360436())
      {
      }
    }
    try
    {
      boolean bool = this.b0427Ч0427Ч042704270427Ч0427;
      return bool;
    }
    catch (Exception localException)
    {
      throw localException;
    }
  }
  
  public boolean bж0436043604360436ж0436ж04360436()
  {
    switch (1)
    {
    case 0: 
    default: 
      for (;;)
      {
        switch (1)
        {
        }
      }
    }
    if ((bжж0436жжжжж04360436() + b0436ж0436жжжжж04360436()) * bжж0436жжжжж04360436() % b04360436жжжжжж04360436() != bж0436жжжжжж04360436()) {}
    return this.bЧ0427Ч0427Ч0427Ч04270427;
  }
  
  public void bж0436043604360436жж043604360436(boolean paramBoolean)
  {
    switch (0)
    {
    case 1: 
    default: 
      for (;;)
      {
        switch (1)
        {
        }
      }
    }
    int i = bжж0436жжжжж04360436();
    switch (i * (b0436ж0436жжжжж04360436() + i) % b04360436жжжжжж04360436())
    {
    }
    if ((bжж0436жжжжж04360436() + b0436ж0436жжжжж04360436()) * bжж0436жжжжж04360436() % b04360436жжжжжж04360436() != bж0436жжжжжж04360436()) {}
    try
    {
      this.bЧЧЧ04270427ЧЧ04270427 = paramBoolean;
      return;
    }
    catch (Exception localException)
    {
      throw localException;
    }
  }
  
  public ZonedDateTime bж0436043604360436жжж04360436()
  {
    switch (0)
    {
    case 1: 
    default: 
      for (;;)
      {
        switch (0)
        {
        }
      }
    }
    int i = bжж0436жжжжж04360436();
    switch (i * (b0436ж0436жжжжж04360436() + i) % b04360436жжжжжж04360436())
    {
    }
    switch (0)
    {
    case 1: 
    default: 
      for (;;)
      {
        switch (1)
        {
        }
      }
    }
    ZonedDateTime localZonedDateTime = this.b04270427ЧЧ0427ЧЧ04270427;
    if ((bжж0436жжжжж04360436() + b0436ж0436жжжжж04360436()) * bжж0436жжжжж04360436() % b04360436жжжжжж04360436() != bж0436жжжжжж04360436()) {}
    return localZonedDateTime;
  }
  
  public void bж043604360436ж04360436ж04360436(AmountDomainModel paramAmountDomainModel)
  {
    throw new Runtime("d2j fail translate: java.lang.IndexOutOfBoundsException: fromIndex < 0: -1\n\tat java.util.BitSet.nextSetBit(BitSet.java:712)\n\tat com.googlecode.dex2jar.ir.ts.array.FillArrayTransformer.makeSureAllElementAreAssigned(FillArrayTransformer.java:505)\n\tat com.googlecode.dex2jar.ir.ts.array.FillArrayTransformer.transformReportChanged(FillArrayTransformer.java:123)\n\tat com.googlecode.dex2jar.ir.ts.StatedTransformer.transform(StatedTransformer.java:10)\n\tat com.googlecode.d2j.dex.Dex2jar$2.optimize(Dex2jar.java:149)\n\tat com.googlecode.d2j.dex.Dex2Asm.convertCode(Dex2Asm.java:414)\n\tat com.googlecode.d2j.dex.ExDex2Asm.convertCode(ExDex2Asm.java:42)\n\tat com.googlecode.d2j.dex.Dex2jar$2.convertCode(Dex2jar.java:128)\n\tat com.googlecode.d2j.dex.Dex2Asm.convertMethod(Dex2Asm.java:509)\n\tat com.googlecode.d2j.dex.Dex2Asm.convertClass(Dex2Asm.java:406)\n\tat com.googlecode.d2j.dex.Dex2Asm.convertDex(Dex2Asm.java:422)\n\tat com.googlecode.d2j.dex.Dex2jar.doTranslate(Dex2jar.java:172)\n\tat com.googlecode.d2j.dex.Dex2jar.to(Dex2jar.java:272)\n\tat com.googlecode.dex2jar.tools.Dex2jarCmd.doCommandLine(Dex2jarCmd.java:108)\n\tat com.googlecode.dex2jar.tools.BaseCmd.doMain(BaseCmd.java:288)\n\tat com.googlecode.dex2jar.tools.Dex2jarCmd.main(Dex2jarCmd.java:32)\n");
  }
  
  public void bж043604360436ж0436ж043604360436(boolean paramBoolean)
  {
    int i = bжж0436жжжжж04360436();
    int j = b0436ж0436жжжжж04360436();
    if ((bжж0436жжжжж04360436() + b0436ж0436жжжжж04360436()) * bжж0436жжжжж04360436() % b04360436жжжжжж04360436() != bж0436жжжжжж04360436()) {}
    switch (i * (j + i) % b04360436жжжжжж04360436())
    {
    }
    this.b0427Ч04270427042704270427Ч0427 = paramBoolean;
    switch (1)
    {
    case 0: 
    default: 
      for (;;)
      {
        switch (0)
        {
        }
      }
    }
  }
  
  public String bж043604360436ж0436жж04360436()
  {
    try
    {
      String str = this.bЧЧЧ0427Ч0427Ч04270427;
      return str;
    }
    catch (Exception localException)
    {
      throw localException;
    }
  }
  
  public boolean bж043604360436жж0436ж04360436()
  {
    return this.bЧЧЧ0427042704270427Ч0427;
  }
  
  /* Error */
  public void bж043604360436жжж043604360436(boolean paramBoolean)
  {
    // Byte code:
    //   0: iconst_0
    //   1: tableswitch	default:+23->24, 0:+50->51, 1:+-1->0
    //   24: iconst_1
    //   25: tableswitch	default:+23->48, 0:+-25->0, 1:+26->51
    //   48: goto -24 -> 24
    //   51: invokestatic 126	kkkkkk/cccrcc:bжж0436жжжжж04360436	()I
    //   54: istore_2
    //   55: invokestatic 129	kkkkkk/cccrcc:b0436ж0436жжжжж04360436	()I
    //   58: istore_3
    //   59: invokestatic 126	kkkkkk/cccrcc:bжж0436жжжжж04360436	()I
    //   62: istore 4
    //   64: invokestatic 132	kkkkkk/cccrcc:b04360436жжжжжж04360436	()I
    //   67: istore 5
    //   69: invokestatic 135	kkkkkk/cccrcc:bж0436жжжжжж04360436	()I
    //   72: istore 6
    //   74: iload_2
    //   75: iload_3
    //   76: iadd
    //   77: iload 4
    //   79: imul
    //   80: iload 5
    //   82: irem
    //   83: iload 6
    //   85: if_icmpeq +24 -> 109
    //   88: invokestatic 126	kkkkkk/cccrcc:bжж0436жжжжж04360436	()I
    //   91: invokestatic 129	kkkkkk/cccrcc:b0436ж0436жжжжж04360436	()I
    //   94: iadd
    //   95: invokestatic 126	kkkkkk/cccrcc:bжж0436жжжжж04360436	()I
    //   98: imul
    //   99: invokestatic 132	kkkkkk/cccrcc:b04360436жжжжжж04360436	()I
    //   102: irem
    //   103: invokestatic 135	kkkkkk/cccrcc:bж0436жжжжжж04360436	()I
    //   106: if_icmpeq +3 -> 109
    //   109: aload_0
    //   110: iload_1
    //   111: putfield 991	kkkkkk/cccrcc:b04270427Ч0427ЧЧЧ04270427	Z
    //   114: return
    //   115: astore 7
    //   117: aload 7
    //   119: athrow
    //   120: astore 7
    //   122: aload 7
    //   124: athrow
    // Local variable table:
    //   start	length	slot	name	signature
    //   0	125	0	this	cccrcc
    //   0	125	1	paramBoolean	boolean
    //   54	23	2	i	int
    //   58	19	3	j	int
    //   62	18	4	k	int
    //   67	16	5	m	int
    //   72	14	6	n	int
    //   115	3	7	localException1	Exception
    //   120	3	7	localException2	Exception
    // Exception table:
    //   from	to	target	type
    //   109	114	115	java/lang/Exception
    //   51	74	120	java/lang/Exception
  }
  
  public AmountDomainModel bж043604360436жжжж04360436()
  {
    if ((bжж0436жжжжж04360436() + b0436ж0436жжжжж04360436()) * bжж0436жжжжж04360436() % b04360436жжжжжж04360436() != bж0436жжжжжж04360436()) {}
    return this.b0427ЧЧЧЧ04270427Ч0427;
  }
  
  public void bж04360436ж043604360436ж04360436(boolean paramBoolean)
  {
    i = 1;
    for (;;)
    {
      try
      {
        j = i / 0;
        i = j;
        continue;
        switch (1)
        {
        default: 
          continue;
        }
      }
      catch (Exception localException1)
      {
        try
        {
          int j = i / 0;
          i = j;
          if ((bжж0436жжжжж04360436() + b0436ж0436жжжжж04360436()) * bжж0436жжжжж04360436() % b04360436жжжжжж04360436() == bж0436жжжжжж04360436()) {
            continue;
          }
          i = j;
          continue;
          localException1 = localException1;
          continue;
        }
        catch (Exception localException2) {}
      }
      switch (1)
      {
      case 0: 
      default: 
        switch (1)
        {
        }
        break;
      }
      switch (1)
      {
      }
    }
    this.b0427ЧЧ0427Ч04270427Ч0427 = paramBoolean;
  }
  
  public void bж04360436ж04360436ж043604360436(boolean paramBoolean)
  {
    if ((bжж0436жжжжж04360436() + b0436ж0436жжжжж04360436()) * bжж0436жжжжж04360436() % b04360436жжжжжж04360436() != bж0436жжжжжж04360436()) {}
    switch (1)
    {
    case 0: 
    default: 
      for (;;)
      {
        switch (0)
        {
        }
      }
    }
    try
    {
      if ((bжж0436жжжжж04360436() + b0436ж0436жжжжж04360436()) * bжж0436жжжжж04360436() % b04360436жжжжжж04360436() != bж0436жжжжжж04360436()) {}
      this.b04270427Ч0427Ч0427Ч04270427 = paramBoolean;
      return;
    }
    catch (Exception localException)
    {
      throw localException;
    }
  }
  
  public boolean bж04360436ж04360436жж04360436()
  {
    if (((bжж0436жжжжж04360436() + b0436ж0436жжжжж04360436()) * bжж0436жжжжж04360436() % b04360436жжжжжж04360436() != bж0436жжжжжж04360436()) && ((bжж0436жжжжж04360436() + b0436ж0436жжжжж04360436()) * bжж0436жжжжж04360436() % b04360436жжжжжж04360436() != bж0436жжжжжж04360436())) {}
    try
    {
      boolean bool = this.bЧ0427042704270427Ч0427Ч0427;
      return bool;
    }
    catch (Exception localException)
    {
      throw localException;
    }
  }
  
  public boolean bж04360436ж0436ж0436ж04360436()
  {
    try
    {
      boolean bool = this.bЧЧЧЧЧ0427Ч04270427;
      int i = bжж0436жжжжж04360436();
      int j = b0436ж0436жжжжж04360436();
      int k = bжж0436жжжжж04360436();
      int m = b04360436жжжжжж04360436();
      int n = bж0436жжжжжж04360436();
      if ((i + j) * k % m != n)
      {
        i = bжж0436жжжжж04360436();
        switch (i * (b0436ж0436жжжжж04360436() + i) % b04360436жжжжжж04360436())
        {
        }
      }
      switch (0)
      {
      case 1: 
      default: 
        for (;;)
        {
          switch (1)
          {
          }
        }
      }
      return bool;
    }
    catch (Exception localException)
    {
      throw localException;
    }
  }
  
  public void bж04360436ж0436жж043604360436(boolean paramBoolean)
  {
    try
    {
      throw new NullPointerException();
    }
    catch (Exception localException1)
    {
      try
      {
        throw new NullPointerException();
      }
      catch (Exception localException2)
      {
        try
        {
          this.bЧЧЧ0427042704270427Ч0427 = paramBoolean;
          return;
        }
        catch (Exception localException3)
        {
          throw localException3;
        }
      }
    }
  }
  
  public crrrcc bж04360436ж0436жжж04360436()
  {
    int j = 4;
    int i = 0;
    try
    {
      for (;;)
      {
        i /= 0;
      }
      return this.bЧЧЧЧ042704270427Ч0427;
    }
    catch (Exception localException1)
    {
      i = j;
    }
    try
    {
      for (;;)
      {
        i /= 0;
      }
    }
    catch (Exception localException2)
    {
      for (;;) {}
    }
    switch (1)
    {
    }
    for (;;)
    {
      switch (0)
      {
      case 1: 
      default: 
        for (;;)
        {
          switch (1)
          {
          }
        }
      }
      switch (0)
      {
      }
    }
  }
  
  public void bж04360436жж04360436ж04360436(String paramString)
  {
    if (((bжж0436жжжжж04360436() + b0436ж0436жжжжж04360436()) * bжж0436жжжжж04360436() % b04360436жжжжжж04360436() != bж0436жжжжжж04360436()) && ((bжж0436жжжжж04360436() + b0436ж0436жжжжж04360436()) * bжж0436жжжжж04360436() % b04360436жжжжжж04360436() != bж0436жжжжжж04360436())) {}
    this.b0427ЧЧ04270427Ч0427Ч0427 = paramString;
  }
  
  public void bж04360436жж0436ж043604360436(AmountDomainModel paramAmountDomainModel)
  {
    try
    {
      this.b04270427042704270427ЧЧ04270427 = paramAmountDomainModel;
      return;
    }
    catch (Exception paramAmountDomainModel)
    {
      throw paramAmountDomainModel;
    }
  }
  
  /* Error */
  public AmountDomainModel bж04360436жж0436жж04360436()
  {
    // Byte code:
    //   0: iconst_1
    //   1: tableswitch	default:+23->24, 0:+-1->0, 1:+70->71
    //   24: invokestatic 126	kkkkkk/cccrcc:bжж0436жжжжж04360436	()I
    //   27: invokestatic 129	kkkkkk/cccrcc:b0436ж0436жжжжж04360436	()I
    //   30: iadd
    //   31: invokestatic 126	kkkkkk/cccrcc:bжж0436жжжжж04360436	()I
    //   34: imul
    //   35: invokestatic 132	kkkkkk/cccrcc:b04360436жжжжжж04360436	()I
    //   38: irem
    //   39: invokestatic 135	kkkkkk/cccrcc:bж0436жжжжжж04360436	()I
    //   42: if_icmpeq +3 -> 45
    //   45: iconst_1
    //   46: tableswitch	default:+22->68, 0:+-46->0, 1:+25->71
    //   68: goto -44 -> 24
    //   71: invokestatic 126	kkkkkk/cccrcc:bжж0436жжжжж04360436	()I
    //   74: istore_1
    //   75: invokestatic 129	kkkkkk/cccrcc:b0436ж0436жжжжж04360436	()I
    //   78: istore_2
    //   79: invokestatic 132	kkkkkk/cccrcc:b04360436жжжжжж04360436	()I
    //   82: istore_3
    //   83: iload_1
    //   84: iload_2
    //   85: iload_1
    //   86: iadd
    //   87: imul
    //   88: iload_3
    //   89: irem
    //   90: tableswitch	default:+18->108, 0:+18->108
    //   108: aload_0
    //   109: getfield 1041	kkkkkk/cccrcc:b04270427042704270427ЧЧ04270427	Lcom/mobile/business/statements/model/AmountDomainModel;
    //   112: astore 4
    //   114: aload 4
    //   116: areturn
    //   117: astore 4
    //   119: aload 4
    //   121: athrow
    //   122: astore 4
    //   124: aload 4
    //   126: athrow
    // Local variable table:
    //   start	length	slot	name	signature
    //   0	127	0	this	cccrcc
    //   74	14	1	i	int
    //   78	9	2	j	int
    //   82	8	3	k	int
    //   112	3	4	localAmountDomainModel	AmountDomainModel
    //   117	3	4	localException1	Exception
    //   122	3	4	localException2	Exception
    // Exception table:
    //   from	to	target	type
    //   71	79	117	java/lang/Exception
    //   108	114	117	java/lang/Exception
    //   79	83	122	java/lang/Exception
  }
  
  public boolean bж04360436жжж0436ж04360436()
  {
    if ((bжж0436жжжжж04360436() + b0436ж0436жжжжж04360436()) * bжж0436жжжжж04360436() % b04360436жжжжжж04360436() != bж0436жжжжжж04360436()) {}
    switch (1)
    {
    case 0: 
    default: 
      for (;;)
      {
        int i = bжж0436жжжжж04360436();
        switch (i * (b0436ж0436жжжжж04360436() + i) % b04360436жжжжжж04360436())
        {
        }
        switch (1)
        {
        }
      }
    }
    return this.bЧЧЧ0427ЧЧЧ04270427;
  }
  
  public void bж04360436жжжж043604360436(String paramString)
  {
    switch (0)
    {
    case 1: 
    default: 
      for (;;)
      {
        i = bжж0436жжжжж04360436();
        switch (i * (b0436ж0436жжжжж04360436() + i) % b04360436жжжжжж04360436())
        {
        }
        switch (0)
        {
        }
      }
    }
    this.bЧЧ0427ЧЧЧЧ04270427 = paramString;
    int i = bжж0436жжжжж04360436();
    switch (i * (b0436ж0436жжжжж04360436() + i) % b04360436жжжжжж04360436())
    {
    }
  }
  
  public void bж0436ж0436043604360436ж04360436(boolean paramBoolean)
  {
    int i = bжж0436жжжжж04360436();
    int j = bжж0436жжжжж04360436();
    switch (j * (b0436ж0436жжжжж04360436() + j) % b04360436жжжжжж04360436())
    {
    }
    switch (i * (b0436ж0436жжжжж04360436() + i) % b04360436жжжжжж04360436())
    {
    }
    try
    {
      this.bЧЧ04270427Ч04270427Ч0427 = paramBoolean;
      return;
    }
    catch (Exception localException)
    {
      throw localException;
    }
  }
  
  public void bж0436ж043604360436ж043604360436(List<ooooii> paramList)
  {
    this.b0427042704270427Ч0427Ч04270427 = paramList;
  }
  
  @ooiiio("Trivial")
  public boolean bж0436ж043604360436жж04360436()
  {
    if (bжж04360436жжжж04360436() == ccrrcc.CURRENT_ACCOUNT)
    {
      switch (0)
      {
      case 1: 
      default: 
        for (;;)
        {
          if ((bжж0436жжжжж04360436() + b0436ж0436жжжжж04360436()) * bжж0436жжжжж04360436() % b04360436жжжжжж04360436() != bж0436жжжжжж04360436()) {}
          switch (1)
          {
          }
        }
      }
      return true;
    }
    try
    {
      throw new NullPointerException();
    }
    catch (Exception localException) {}
    return false;
  }
  
  public boolean bж0436ж04360436ж0436ж04360436()
  {
    if ((bжж0436жжжжж04360436() + b0436ж0436жжжжж04360436()) * bжж0436жжжжж04360436() % b04360436жжжжжж04360436() != bж0436жжжжжж04360436()) {}
    switch (0)
    {
    case 1: 
    default: 
      for (;;)
      {
        switch (0)
        {
        }
      }
    }
    try
    {
      throw new NullPointerException();
    }
    catch (Exception localException) {}
    return this.b0427042704270427042704270427Ч0427;
  }
  
  public void bж0436ж04360436жж043604360436(boolean paramBoolean)
  {
    this.bЧ0427Ч0427042704270427Ч0427 = paramBoolean;
  }
  
  public String bж0436ж04360436жжж04360436()
  {
    try
    {
      String str = this.bЧЧ0427ЧЧЧЧ04270427;
      return str;
    }
    catch (Exception localException1)
    {
      try
      {
        throw localException1;
      }
      catch (Exception localException2)
      {
        throw localException2;
      }
    }
  }
  
  public void bж0436ж0436ж04360436ж04360436(ZonedDateTime paramZonedDateTime)
  {
    throw new Runtime("d2j fail translate: java.lang.IndexOutOfBoundsException: fromIndex < 0: -1\n\tat java.util.BitSet.nextSetBit(BitSet.java:712)\n\tat com.googlecode.dex2jar.ir.ts.array.FillArrayTransformer.makeSureAllElementAreAssigned(FillArrayTransformer.java:505)\n\tat com.googlecode.dex2jar.ir.ts.array.FillArrayTransformer.transformReportChanged(FillArrayTransformer.java:123)\n\tat com.googlecode.dex2jar.ir.ts.StatedTransformer.transform(StatedTransformer.java:10)\n\tat com.googlecode.d2j.dex.Dex2jar$2.optimize(Dex2jar.java:149)\n\tat com.googlecode.d2j.dex.Dex2Asm.convertCode(Dex2Asm.java:414)\n\tat com.googlecode.d2j.dex.ExDex2Asm.convertCode(ExDex2Asm.java:42)\n\tat com.googlecode.d2j.dex.Dex2jar$2.convertCode(Dex2jar.java:128)\n\tat com.googlecode.d2j.dex.Dex2Asm.convertMethod(Dex2Asm.java:509)\n\tat com.googlecode.d2j.dex.Dex2Asm.convertClass(Dex2Asm.java:406)\n\tat com.googlecode.d2j.dex.Dex2Asm.convertDex(Dex2Asm.java:422)\n\tat com.googlecode.d2j.dex.Dex2jar.doTranslate(Dex2jar.java:172)\n\tat com.googlecode.d2j.dex.Dex2jar.to(Dex2jar.java:272)\n\tat com.googlecode.dex2jar.tools.Dex2jarCmd.doCommandLine(Dex2jarCmd.java:108)\n\tat com.googlecode.dex2jar.tools.BaseCmd.doMain(BaseCmd.java:288)\n\tat com.googlecode.dex2jar.tools.Dex2jarCmd.main(Dex2jarCmd.java:32)\n");
  }
  
  public void bж0436ж0436ж0436ж043604360436(List<String> paramList)
  {
    int i = bжж0436жжжжж04360436();
    int j = b0436ж0436жжжжж04360436();
    if (((bжж0436жжжжж04360436() + b0436ж0436жжжжж04360436()) * bжж0436жжжжж04360436() % b04360436жжжжжж04360436() == bж0436жжжжжж04360436()) || ((i + j) * bжж0436жжжжж04360436() % b04360436жжжжжж04360436() != bж0436жжжжжж04360436())) {}
    this.bЧ0427ЧЧЧ0427Ч04270427 = paramList;
  }
  
  public String bж0436ж0436ж0436жж04360436()
  {
    try
    {
      String str = this.bЧЧ0427ЧЧ0427Ч04270427;
      int i = bжж0436жжжжж04360436();
      int j = b0436ж0436жжжжж04360436();
      int k = bжж0436жжжжж04360436();
      int m = b04360436жжжжжж04360436();
      int n = bж0436жжжжжж04360436();
      if ((i + j) * k % m != n) {}
      return str;
    }
    catch (Exception localException)
    {
      throw localException;
    }
  }
  
  /* Error */
  public boolean bж0436ж0436жж0436ж04360436()
  {
    // Byte code:
    //   0: invokestatic 126	kkkkkk/cccrcc:bжж0436жжжжж04360436	()I
    //   3: istore_1
    //   4: invokestatic 129	kkkkkk/cccrcc:b0436ж0436жжжжж04360436	()I
    //   7: istore_2
    //   8: invokestatic 132	kkkkkk/cccrcc:b04360436жжжжжж04360436	()I
    //   11: istore_3
    //   12: iload_1
    //   13: iload_2
    //   14: iload_1
    //   15: iadd
    //   16: imul
    //   17: iload_3
    //   18: irem
    //   19: tableswitch	default:+17->36, 0:+17->36
    //   36: aload_0
    //   37: getfield 821	kkkkkk/cccrcc:bЧЧ04270427ЧЧЧ04270427	Z
    //   40: istore 4
    //   42: iload 4
    //   44: ireturn
    //   45: astore 5
    //   47: aload 5
    //   49: athrow
    //   50: astore 5
    //   52: aload 5
    //   54: athrow
    //   55: astore 5
    //   57: aload 5
    //   59: athrow
    // Local variable table:
    //   start	length	slot	name	signature
    //   0	60	0	this	cccrcc
    //   3	14	1	i	int
    //   7	9	2	j	int
    //   11	8	3	k	int
    //   40	3	4	bool	boolean
    //   45	3	5	localException1	Exception
    //   50	3	5	localException2	Exception
    //   55	3	5	localException3	Exception
    // Exception table:
    //   from	to	target	type
    //   36	42	45	java/lang/Exception
    //   47	50	50	java/lang/Exception
    //   0	12	55	java/lang/Exception
  }
  
  public void bж0436ж0436жжж043604360436(boolean paramBoolean)
  {
    int i = bжж0436жжжжж04360436();
    int j = b0436ж0436жжжжж04360436();
    switch (0)
    {
    case 1: 
    default: 
      for (;;)
      {
        switch (1)
        {
        }
      }
    }
    if ((i + j) * bжж0436жжжжж04360436() % b04360436жжжжжж04360436() != bж0436жжжжжж04360436())
    {
      i = bжж0436жжжжж04360436();
      switch (i * (b0436ж0436жжжжж04360436() + i) % b04360436жжжжжж04360436())
      {
      }
    }
    this.b042704270427ЧЧЧЧ04270427 = paramBoolean;
    switch (1)
    {
    case 0: 
    default: 
      for (;;)
      {
        switch (1)
        {
        }
      }
    }
  }
  
  /* Error */
  public String bж0436ж0436жжжж04360436()
  {
    // Byte code:
    //   0: invokestatic 126	kkkkkk/cccrcc:bжж0436жжжжж04360436	()I
    //   3: istore_1
    //   4: invokestatic 129	kkkkkk/cccrcc:b0436ж0436жжжжж04360436	()I
    //   7: istore_2
    //   8: invokestatic 132	kkkkkk/cccrcc:b04360436жжжжжж04360436	()I
    //   11: istore_3
    //   12: iload_1
    //   13: iload_2
    //   14: iload_1
    //   15: iadd
    //   16: imul
    //   17: iload_3
    //   18: irem
    //   19: tableswitch	default:+17->36, 0:+17->36
    //   36: aload_0
    //   37: getfield 977	kkkkkk/cccrcc:bЧЧ042704270427Ч0427Ч0427	Ljava/lang/String;
    //   40: astore 4
    //   42: aload 4
    //   44: areturn
    //   45: astore 4
    //   47: aload 4
    //   49: athrow
    //   50: astore 4
    //   52: aload 4
    //   54: athrow
    // Local variable table:
    //   start	length	slot	name	signature
    //   0	55	0	this	cccrcc
    //   3	14	1	i	int
    //   7	9	2	j	int
    //   11	8	3	k	int
    //   40	3	4	str	String
    //   45	3	4	localException1	Exception
    //   50	3	4	localException2	Exception
    // Exception table:
    //   from	to	target	type
    //   0	4	45	java/lang/Exception
    //   36	42	45	java/lang/Exception
    //   4	12	50	java/lang/Exception
  }
  
  public void bж0436жж043604360436ж04360436(boolean paramBoolean)
  {
    int i;
    switch (1)
    {
    case 0: 
    default: 
      for (;;)
      {
        i = bжж0436жжжжж04360436();
        switch (i * (b0436ж0436жжжжж04360436() + i) % b04360436жжжжжж04360436())
        {
        }
        switch (1)
        {
        }
      }
    }
    for (;;)
    {
      try
      {
        i = bжж0436жжжжж04360436();
        switch (i * (b0436ж0436жжжжж04360436() + i) % b04360436жжжжжж04360436())
        {
        case 0: 
          this.b0427Ч0427ЧЧ04270427Ч0427 = paramBoolean;
          return;
        }
      }
      catch (Exception localException)
      {
        throw localException;
      }
    }
  }
  
  public void bж0436жж04360436ж043604360436(boolean paramBoolean)
  {
    try
    {
      int i = bжж0436жжжжж04360436();
      int j = b0436ж0436жжжжж04360436();
      int k = bжж0436жжжжж04360436();
      int m = b04360436жжжжжж04360436();
      int n = bж0436жжжжжж04360436();
      if ((i + j) * k % m != n)
      {
        i = bжж0436жжжжж04360436();
        switch (i * (b0436ж0436жжжжж04360436() + i) % b04360436жжжжжж04360436())
        {
        }
      }
      switch (0)
      {
      case 1: 
      default: 
        for (;;)
        {
          switch (1)
          {
          }
        }
      }
      this.bЧ042704270427042704270427Ч0427 = paramBoolean;
      return;
    }
    catch (Exception localException)
    {
      throw localException;
    }
  }
  
  public boolean bж0436жж04360436жж04360436()
  {
    try
    {
      boolean bool = this.bЧЧЧ04270427Ч0427Ч0427;
      if ((bжж0436жжжжж04360436() + b0436ж0436жжжжж04360436()) * bжж0436жжжжж04360436() % b04360436жжжжжж04360436() != bж0436жжжжжж04360436()) {}
      return bool;
    }
    catch (Exception localException1)
    {
      try
      {
        throw localException1;
      }
      catch (Exception localException2)
      {
        throw localException2;
      }
    }
  }
  
  public boolean bж0436жж0436ж0436ж04360436()
  {
    return this.b0427ЧЧ04270427ЧЧ04270427;
  }
  
  public void bж0436жж0436жж043604360436(boolean paramBoolean)
  {
    try
    {
      throw new NullPointerException();
    }
    catch (Exception localException1)
    {
      switch (1)
      {
      case 0: 
      default: 
        for (;;)
        {
          switch (1)
          {
          }
        }
      }
    }
    for (;;)
    {
      try
      {
        throw new NullPointerException();
      }
      catch (Exception localException3)
      {
        continue;
      }
      switch (1)
      {
      }
    }
    for (;;)
    {
      switch (1)
      {
      case 0: 
      default: 
        break;
      case 1: 
        this.b0427042704270427ЧЧЧ04270427 = paramBoolean;
        return;
        try
        {
          throw new NullPointerException();
        }
        catch (Exception localException2) {}
      }
    }
  }
  
  /* Error */
  public ZonedDateTime bж0436жж0436жжж04360436()
  {
    // Byte code:
    //   0: invokestatic 126	kkkkkk/cccrcc:bжж0436жжжжж04360436	()I
    //   3: istore_1
    //   4: invokestatic 129	kkkkkk/cccrcc:b0436ж0436жжжжж04360436	()I
    //   7: istore_2
    //   8: invokestatic 126	kkkkkk/cccrcc:bжж0436жжжжж04360436	()I
    //   11: istore_3
    //   12: invokestatic 126	kkkkkk/cccrcc:bжж0436жжжжж04360436	()I
    //   15: invokestatic 129	kkkkkk/cccrcc:b0436ж0436жжжжж04360436	()I
    //   18: iadd
    //   19: invokestatic 126	kkkkkk/cccrcc:bжж0436жжжжж04360436	()I
    //   22: imul
    //   23: invokestatic 132	kkkkkk/cccrcc:b04360436жжжжжж04360436	()I
    //   26: irem
    //   27: invokestatic 135	kkkkkk/cccrcc:bж0436жжжжжж04360436	()I
    //   30: if_icmpeq +3 -> 33
    //   33: invokestatic 132	kkkkkk/cccrcc:b04360436жжжжжж04360436	()I
    //   36: istore 4
    //   38: invokestatic 135	kkkkkk/cccrcc:bж0436жжжжжж04360436	()I
    //   41: istore 5
    //   43: iload_1
    //   44: iload_2
    //   45: iadd
    //   46: iload_3
    //   47: imul
    //   48: iload 4
    //   50: irem
    //   51: iload 5
    //   53: if_icmpeq +3 -> 56
    //   56: aload_0
    //   57: getfield 956	kkkkkk/cccrcc:b04270427Ч0427Ч04270427Ч0427	Lorg/threeten/bp/ZonedDateTime;
    //   60: astore 6
    //   62: aload 6
    //   64: areturn
    //   65: astore 6
    //   67: aload 6
    //   69: athrow
    //   70: astore 6
    //   72: aload 6
    //   74: athrow
    // Local variable table:
    //   start	length	slot	name	signature
    //   0	75	0	this	cccrcc
    //   3	43	1	i	int
    //   7	39	2	j	int
    //   11	37	3	k	int
    //   36	15	4	m	int
    //   41	13	5	n	int
    //   60	3	6	localZonedDateTime	ZonedDateTime
    //   65	3	6	localException1	Exception
    //   70	3	6	localException2	Exception
    // Exception table:
    //   from	to	target	type
    //   0	12	65	java/lang/Exception
    //   33	43	65	java/lang/Exception
    //   56	62	70	java/lang/Exception
  }
  
  public boolean bж0436жжж04360436ж04360436()
  {
    switch (1)
    {
    case 0: 
    default: 
      for (;;)
      {
        switch (1)
        {
        }
      }
    }
    try
    {
      boolean bool = this.bЧЧЧЧ04270427Ч04270427;
      int i = bжж0436жжжжж04360436();
      int j = b0436ж0436жжжжж04360436();
      int k = bжж0436жжжжж04360436();
      int m = b04360436жжжжжж04360436();
      int n = bж0436жжжжжж04360436();
      if ((i + j) * k % m != n)
      {
        i = bжж0436жжжжж04360436();
        switch (i * (b0436ж0436жжжжж04360436() + i) % b04360436жжжжжж04360436())
        {
        }
      }
      return bool;
    }
    catch (Exception localException)
    {
      throw localException;
    }
  }
  
  public void bж0436жжж0436ж043604360436(String paramString)
  {
    throw new Runtime("d2j fail translate: java.lang.IndexOutOfBoundsException: fromIndex < 0: -1\n\tat java.util.BitSet.nextSetBit(BitSet.java:712)\n\tat com.googlecode.dex2jar.ir.ts.array.FillArrayTransformer.makeSureAllElementAreAssigned(FillArrayTransformer.java:505)\n\tat com.googlecode.dex2jar.ir.ts.array.FillArrayTransformer.transformReportChanged(FillArrayTransformer.java:123)\n\tat com.googlecode.dex2jar.ir.ts.StatedTransformer.transform(StatedTransformer.java:10)\n\tat com.googlecode.d2j.dex.Dex2jar$2.optimize(Dex2jar.java:149)\n\tat com.googlecode.d2j.dex.Dex2Asm.convertCode(Dex2Asm.java:414)\n\tat com.googlecode.d2j.dex.ExDex2Asm.convertCode(ExDex2Asm.java:42)\n\tat com.googlecode.d2j.dex.Dex2jar$2.convertCode(Dex2jar.java:128)\n\tat com.googlecode.d2j.dex.Dex2Asm.convertMethod(Dex2Asm.java:509)\n\tat com.googlecode.d2j.dex.Dex2Asm.convertClass(Dex2Asm.java:406)\n\tat com.googlecode.d2j.dex.Dex2Asm.convertDex(Dex2Asm.java:422)\n\tat com.googlecode.d2j.dex.Dex2jar.doTranslate(Dex2jar.java:172)\n\tat com.googlecode.d2j.dex.Dex2jar.to(Dex2jar.java:272)\n\tat com.googlecode.dex2jar.tools.Dex2jarCmd.doCommandLine(Dex2jarCmd.java:108)\n\tat com.googlecode.dex2jar.tools.BaseCmd.doMain(BaseCmd.java:288)\n\tat com.googlecode.dex2jar.tools.Dex2jarCmd.main(Dex2jarCmd.java:32)\n");
  }
  
  public String bж0436жжж0436жж04360436()
  {
    int i = bжж0436жжжжж04360436();
    switch (i * (b0436ж0436жжжжж04360436() + i) % b04360436жжжжжж04360436())
    {
    default: 
      i = bжж0436жжжжж04360436();
      switch (i * (b0436ж0436жжжжж04360436() + i) % b04360436жжжжжж04360436())
      {
      }
      break;
    }
    try
    {
      String str = this.b042704270427Ч0427ЧЧ04270427;
      return str;
    }
    catch (Exception localException)
    {
      throw localException;
    }
  }
  
  /* Error */
  public boolean bж0436жжжж0436ж04360436()
  {
    // Byte code:
    //   0: aload_0
    //   1: getfield 851	kkkkkk/cccrcc:b042704270427Ч042704270427Ч0427	Z
    //   4: istore 4
    //   6: invokestatic 126	kkkkkk/cccrcc:bжж0436жжжжж04360436	()I
    //   9: istore_1
    //   10: invokestatic 129	kkkkkk/cccrcc:b0436ж0436жжжжж04360436	()I
    //   13: istore_2
    //   14: invokestatic 132	kkkkkk/cccrcc:b04360436жжжжжж04360436	()I
    //   17: istore_3
    //   18: invokestatic 126	kkkkkk/cccrcc:bжж0436жжжжж04360436	()I
    //   21: invokestatic 129	kkkkkk/cccrcc:b0436ж0436жжжжж04360436	()I
    //   24: iadd
    //   25: invokestatic 126	kkkkkk/cccrcc:bжж0436жжжжж04360436	()I
    //   28: imul
    //   29: invokestatic 132	kkkkkk/cccrcc:b04360436жжжжжж04360436	()I
    //   32: irem
    //   33: invokestatic 135	kkkkkk/cccrcc:bж0436жжжжжж04360436	()I
    //   36: if_icmpeq +3 -> 39
    //   39: iload_1
    //   40: iload_2
    //   41: iload_1
    //   42: iadd
    //   43: imul
    //   44: iload_3
    //   45: irem
    //   46: tableswitch	default:+18->64, 0:+18->64
    //   64: iload 4
    //   66: ireturn
    //   67: astore 5
    //   69: aload 5
    //   71: athrow
    //   72: astore 5
    //   74: aload 5
    //   76: athrow
    //   77: astore 5
    //   79: aload 5
    //   81: athrow
    // Local variable table:
    //   start	length	slot	name	signature
    //   0	82	0	this	cccrcc
    //   9	35	1	i	int
    //   13	30	2	j	int
    //   17	29	3	k	int
    //   4	61	4	bool	boolean
    //   67	3	5	localException1	Exception
    //   72	3	5	localException2	Exception
    //   77	3	5	localException3	Exception
    // Exception table:
    //   from	to	target	type
    //   0	6	67	java/lang/Exception
    //   10	18	72	java/lang/Exception
    //   69	72	72	java/lang/Exception
    //   6	10	77	java/lang/Exception
  }
  
  public void bж0436жжжжж043604360436(boolean paramBoolean)
  {
    int i = bжж0436жжжжж04360436();
    int j = b0436ж0436жжжжж04360436();
    int k = bжж0436жжжжж04360436();
    int m = b04360436жжжжжж04360436();
    int n = bж0436жжжжжж04360436();
    if (((bжж0436жжжжж04360436() + b0436ж0436жжжжж04360436()) * bжж0436жжжжж04360436() % b04360436жжжжжж04360436() == bж0436жжжжжж04360436()) || ((i + j) * k % m != n)) {}
    try
    {
      this.bЧ04270427Ч042704270427Ч0427 = paramBoolean;
      return;
    }
    catch (Exception localException)
    {
      throw localException;
    }
  }
  
  public void bжж04360436043604360436ж04360436(@NonNull String paramString)
  {
    if (((bжж0436жжжжж04360436() + b0436ж0436жжжжж04360436()) * bжж0436жжжжж04360436() % b04360436жжжжжж04360436() == bж0436жжжжжж04360436()) || ((bжж0436жжжжж04360436() + b0436ж0436жжжжж04360436()) * bжж0436жжжжж04360436() % b04360436жжжжжж04360436() != bж0436жжжжжж04360436())) {}
    switch (0)
    {
    case 1: 
    default: 
      for (;;)
      {
        switch (0)
        {
        }
      }
    }
    this.bЧ042704270427Ч04270427Ч0427 = paramString;
  }
  
  public void bжж0436043604360436ж043604360436(boolean paramBoolean)
  {
    if ((bжж0436жжжжж04360436() + b0436ж0436жжжжж04360436()) * bжж0436жжжжж04360436() % b04360436жжжжжж04360436() != bж0436жжжжжж04360436()) {}
    this.bЧЧЧЧ04270427Ч04270427 = paramBoolean;
  }
  
  /* Error */
  public boolean bжж0436043604360436жж04360436()
  {
    // Byte code:
    //   0: aload_0
    //   1: getfield 1035	kkkkkk/cccrcc:b0427ЧЧ0427Ч04270427Ч0427	Z
    //   4: istore 6
    //   6: invokestatic 126	kkkkkk/cccrcc:bжж0436жжжжж04360436	()I
    //   9: istore_1
    //   10: invokestatic 129	kkkkkk/cccrcc:b0436ж0436жжжжж04360436	()I
    //   13: istore_2
    //   14: invokestatic 126	kkkkkk/cccrcc:bжж0436жжжжж04360436	()I
    //   17: istore_3
    //   18: invokestatic 132	kkkkkk/cccrcc:b04360436жжжжжж04360436	()I
    //   21: istore 4
    //   23: invokestatic 135	kkkkkk/cccrcc:bж0436жжжжжж04360436	()I
    //   26: istore 5
    //   28: iload_1
    //   29: iload_2
    //   30: iadd
    //   31: iload_3
    //   32: imul
    //   33: iload 4
    //   35: irem
    //   36: iload 5
    //   38: if_icmpeq +38 -> 76
    //   41: invokestatic 126	kkkkkk/cccrcc:bжж0436жжжжж04360436	()I
    //   44: istore_1
    //   45: iload_1
    //   46: invokestatic 129	kkkkkk/cccrcc:b0436ж0436жжжжж04360436	()I
    //   49: iload_1
    //   50: iadd
    //   51: imul
    //   52: invokestatic 132	kkkkkk/cccrcc:b04360436жжжжжж04360436	()I
    //   55: irem
    //   56: tableswitch	default:+20->76, 0:+20->76
    //   76: iload 6
    //   78: ireturn
    //   79: astore 7
    //   81: aload 7
    //   83: athrow
    //   84: astore 7
    //   86: aload 7
    //   88: athrow
    //   89: astore 7
    //   91: aload 7
    //   93: athrow
    // Local variable table:
    //   start	length	slot	name	signature
    //   0	94	0	this	cccrcc
    //   9	43	1	i	int
    //   13	18	2	j	int
    //   17	16	3	k	int
    //   21	15	4	m	int
    //   26	13	5	n	int
    //   4	73	6	bool	boolean
    //   79	3	7	localException1	Exception
    //   84	3	7	localException2	Exception
    //   89	3	7	localException3	Exception
    // Exception table:
    //   from	to	target	type
    //   0	6	79	java/lang/Exception
    //   81	84	84	java/lang/Exception
    //   6	28	89	java/lang/Exception
  }
  
  @ooiiio("Trivial")
  public boolean bжж043604360436ж0436ж04360436()
  {
    try
    {
      int i = bжж0436жжжжж04360436();
      int j = b0436ж0436жжжжж04360436();
      int k = bжж0436жжжжж04360436();
      int m = b04360436жжжжжж04360436();
      int n = bж0436жжжжжж04360436();
      if (((i + j) * k % m != n) && ((bжж0436жжжжж04360436() + b0436ж0436жжжжж04360436()) * bжж0436жжжжж04360436() % b04360436жжжжжж04360436() != bж0436жжжжжж04360436())) {}
      ccrrcc localCcrrcc1 = bжж04360436жжжж04360436();
      ccrrcc localCcrrcc2 = ccrrcc.SAVINGS_ACCOUNT;
      return localCcrrcc1 == localCcrrcc2;
    }
    catch (Exception localException)
    {
      throw localException;
    }
  }
  
  /* Error */
  public void bжж043604360436жж043604360436(String paramString)
  {
    // Byte code:
    //   0: iconst_1
    //   1: tableswitch	default:+23->24, 0:+-1->0, 1:+50->51
    //   24: iconst_1
    //   25: tableswitch	default:+23->48, 0:+-25->0, 1:+26->51
    //   48: goto -24 -> 24
    //   51: invokestatic 126	kkkkkk/cccrcc:bжж0436жжжжж04360436	()I
    //   54: istore_2
    //   55: invokestatic 129	kkkkkk/cccrcc:b0436ж0436жжжжж04360436	()I
    //   58: istore_3
    //   59: invokestatic 126	kkkkkk/cccrcc:bжж0436жжжжж04360436	()I
    //   62: istore 4
    //   64: invokestatic 132	kkkkkk/cccrcc:b04360436жжжжжж04360436	()I
    //   67: istore 5
    //   69: invokestatic 135	kkkkkk/cccrcc:bж0436жжжжжж04360436	()I
    //   72: istore 6
    //   74: iload_2
    //   75: iload_3
    //   76: iadd
    //   77: iload 4
    //   79: imul
    //   80: iload 5
    //   82: irem
    //   83: iload 6
    //   85: if_icmpeq +35 -> 120
    //   88: invokestatic 126	kkkkkk/cccrcc:bжж0436жжжжж04360436	()I
    //   91: istore_2
    //   92: iload_2
    //   93: invokestatic 129	kkkkkk/cccrcc:b0436ж0436жжжжж04360436	()I
    //   96: iload_2
    //   97: iadd
    //   98: imul
    //   99: invokestatic 132	kkkkkk/cccrcc:b04360436жжжжжж04360436	()I
    //   102: irem
    //   103: tableswitch	default:+17->120, 0:+17->120
    //   120: aload_0
    //   121: aload_1
    //   122: putfield 1014	kkkkkk/cccrcc:bЧ04270427Ч0427ЧЧ04270427	Ljava/lang/String;
    //   125: return
    //   126: astore_1
    //   127: aload_1
    //   128: athrow
    //   129: astore_1
    //   130: aload_1
    //   131: athrow
    // Local variable table:
    //   start	length	slot	name	signature
    //   0	132	0	this	cccrcc
    //   0	132	1	paramString	String
    //   54	45	2	i	int
    //   58	19	3	j	int
    //   62	18	4	k	int
    //   67	16	5	m	int
    //   72	14	6	n	int
    // Exception table:
    //   from	to	target	type
    //   51	74	126	java/lang/Exception
    //   120	125	129	java/lang/Exception
  }
  
  public AmountDomainModel bжж043604360436жжж04360436()
  {
    switch (0)
    {
    case 1: 
    default: 
      for (;;)
      {
        switch (0)
        {
        }
      }
    }
    AmountDomainModel localAmountDomainModel = this.b0427ЧЧЧ0427ЧЧ04270427;
    if ((bжж0436жжжжж04360436() + b0436ж0436жжжжж04360436()) * bжж0436жжжжж04360436() % b04360436жжжжжж04360436() != bж0436жжжжжж04360436()) {}
    return localAmountDomainModel;
  }
  
  public void bжж04360436ж04360436ж04360436(ccrrcc paramCcrrcc)
  {
    int i = bжж0436жжжжж04360436();
    if (((bжж0436жжжжж04360436() + b0436ж0436жжжжж04360436()) * bжж0436жжжжж04360436() % b04360436жжжжжж04360436() == bж0436жжжжжж04360436()) || ((i + b0436ж0436жжжжж04360436()) * bжж0436жжжжж04360436() % b04360436жжжжжж04360436() != bж0436жжжжжж04360436())) {}
    try
    {
      this.b04270427042704270427Ч0427Ч0427 = paramCcrrcc;
      return;
    }
    catch (Exception paramCcrrcc)
    {
      throw paramCcrrcc;
    }
  }
  
  /* Error */
  public void bжж04360436ж0436ж043604360436(String paramString)
  {
    // Byte code:
    //   0: invokestatic 126	kkkkkk/cccrcc:bжж0436жжжжж04360436	()I
    //   3: istore_2
    //   4: invokestatic 129	kkkkkk/cccrcc:b0436ж0436жжжжж04360436	()I
    //   7: istore_3
    //   8: invokestatic 132	kkkkkk/cccrcc:b04360436жжжжжж04360436	()I
    //   11: istore 4
    //   13: iload_2
    //   14: iload_3
    //   15: iload_2
    //   16: iadd
    //   17: imul
    //   18: iload 4
    //   20: irem
    //   21: tableswitch	default:+19->40, 0:+19->40
    //   40: invokestatic 126	kkkkkk/cccrcc:bжж0436жжжжж04360436	()I
    //   43: istore_2
    //   44: iload_2
    //   45: invokestatic 129	kkkkkk/cccrcc:b0436ж0436жжжжж04360436	()I
    //   48: iload_2
    //   49: iadd
    //   50: imul
    //   51: invokestatic 132	kkkkkk/cccrcc:b04360436жжжжжж04360436	()I
    //   54: irem
    //   55: tableswitch	default:+17->72, 0:+17->72
    //   72: aload_0
    //   73: aload_1
    //   74: putfield 1062	kkkkkk/cccrcc:bЧЧ0427ЧЧ0427Ч04270427	Ljava/lang/String;
    //   77: return
    //   78: astore_1
    //   79: aload_1
    //   80: athrow
    //   81: astore_1
    //   82: aload_1
    //   83: athrow
    // Local variable table:
    //   start	length	slot	name	signature
    //   0	84	0	this	cccrcc
    //   0	84	1	paramString	String
    //   3	48	2	i	int
    //   7	10	3	j	int
    //   11	10	4	k	int
    // Exception table:
    //   from	to	target	type
    //   0	13	78	java/lang/Exception
    //   72	77	81	java/lang/Exception
  }
  
  public String bжж04360436ж0436жж04360436()
  {
    int i = bжж0436жжжжж04360436();
    switch (i * (b0436ж0436жжжжж04360436() + i) % b04360436жжжжжж04360436())
    {
    default: 
      i = bжж0436жжжжж04360436();
      switch (i * (b0436ж0436жжжжж04360436() + i) % b04360436жжжжжж04360436())
      {
      }
      break;
    }
    String str = this.bЧ04270427ЧЧ0427Ч04270427;
    switch (0)
    {
    case 1: 
    default: 
      for (;;)
      {
        switch (0)
        {
        case 1: 
        default: 
          for (;;)
          {
            switch (0)
            {
            }
          }
        }
        switch (1)
        {
        }
      }
    }
    return str;
  }
  
  public boolean bжж04360436жж0436ж04360436()
  {
    return this.bЧ042704270427ЧЧЧ04270427;
  }
  
  public void bжж04360436жжж043604360436(boolean paramBoolean)
  {
    switch (1)
    {
    case 0: 
    default: 
      for (;;)
      {
        switch (1)
        {
        }
      }
    }
    this.b0427ЧЧ0427ЧЧЧ04270427 = paramBoolean;
  }
  
  public ccrrcc bжж04360436жжжж04360436()
  {
    switch (0)
    {
    case 1: 
    default: 
      for (;;)
      {
        switch (1)
        {
        }
      }
    }
    int i = bжж0436жжжжж04360436();
    switch (i * (b0436ж0436жжжжж04360436() + i) % b04360436жжжжжж04360436())
    {
    default: 
      i = bжж0436жжжжж04360436();
      switch (i * (b0436ж0436жжжжж04360436() + i) % b04360436жжжжжж04360436())
      {
      }
      break;
    }
    switch (1)
    {
    case 0: 
    default: 
      for (;;)
      {
        switch (1)
        {
        }
      }
    }
    return this.b04270427042704270427Ч0427Ч0427;
  }
  
  /* Error */
  public void bжж0436ж043604360436ж04360436(AmountDomainModel paramAmountDomainModel)
  {
    // Byte code:
    //   0: invokestatic 126	kkkkkk/cccrcc:bжж0436жжжжж04360436	()I
    //   3: istore_2
    //   4: invokestatic 126	kkkkkk/cccrcc:bжж0436жжжжж04360436	()I
    //   7: invokestatic 129	kkkkkk/cccrcc:b0436ж0436жжжжж04360436	()I
    //   10: iadd
    //   11: invokestatic 126	kkkkkk/cccrcc:bжж0436жжжжж04360436	()I
    //   14: imul
    //   15: invokestatic 132	kkkkkk/cccrcc:b04360436жжжжжж04360436	()I
    //   18: irem
    //   19: invokestatic 135	kkkkkk/cccrcc:bж0436жжжжжж04360436	()I
    //   22: if_icmpeq +3 -> 25
    //   25: invokestatic 129	kkkkkk/cccrcc:b0436ж0436жжжжж04360436	()I
    //   28: istore_3
    //   29: invokestatic 132	kkkkkk/cccrcc:b04360436жжжжжж04360436	()I
    //   32: istore 4
    //   34: iload_2
    //   35: iload_3
    //   36: iload_2
    //   37: iadd
    //   38: imul
    //   39: iload 4
    //   41: irem
    //   42: tableswitch	default:+18->60, 0:+18->60
    //   60: aload_0
    //   61: aload_1
    //   62: putfield 1010	kkkkkk/cccrcc:b042704270427ЧЧ04270427Ч0427	Lcom/mobile/business/statements/model/AmountDomainModel;
    //   65: return
    //   66: astore_1
    //   67: aload_1
    //   68: athrow
    //   69: astore_1
    //   70: aload_1
    //   71: athrow
    //   72: astore_1
    //   73: aload_1
    //   74: athrow
    // Local variable table:
    //   start	length	slot	name	signature
    //   0	75	0	this	cccrcc
    //   0	75	1	paramAmountDomainModel	AmountDomainModel
    //   3	36	2	i	int
    //   28	10	3	j	int
    //   32	10	4	k	int
    // Exception table:
    //   from	to	target	type
    //   60	65	66	java/lang/Exception
    //   67	69	69	java/lang/Exception
    //   0	4	72	java/lang/Exception
    //   25	34	72	java/lang/Exception
  }
  
  public void bжж0436ж04360436ж043604360436(boolean paramBoolean)
  {
    int i = bжж0436жжжжж04360436();
    switch (i * (b0436ж0436жжжжж04360436() + i) % b04360436жжжжжж04360436())
    {
    }
    switch (1)
    {
    case 0: 
    default: 
      for (;;)
      {
        switch (0)
        {
        }
      }
    }
    i = bжж0436жжжжж04360436();
    switch (i * (b0436ж0436жжжжж04360436() + i) % b04360436жжжжжж04360436())
    {
    default: 
      switch (0)
      {
      case 1: 
      default: 
        for (;;)
        {
          switch (1)
          {
          }
        }
      }
      break;
    }
    this.b0427ЧЧ0427Ч0427Ч04270427 = paramBoolean;
  }
  
  public boolean bжж0436ж04360436жж04360436()
  {
    try
    {
      boolean bool = this.bЧЧ0427Ч042704270427Ч0427;
      switch (0)
      {
      case 1: 
      default: 
        for (;;)
        {
          switch (0)
          {
          }
        }
      }
      int i = bжж0436жжжжж04360436();
      int j = bжж0436жжжжж04360436();
      switch (j * (b0436ж0436жжжжж04360436() + j) % b04360436жжжжжж04360436())
      {
      }
      if ((i + b0436ж0436жжжжж04360436()) * bжж0436жжжжж04360436() % b04360436жжжжжж04360436() != bж0436жжжжжж04360436()) {}
      return bool;
    }
    catch (Exception localException)
    {
      throw localException;
    }
  }
  
  public boolean bжж0436ж0436ж0436ж04360436()
  {
    int i = bжж0436жжжжж04360436();
    int j = b0436ж0436жжжжж04360436();
    int k = bжж0436жжжжж04360436();
    switch (k * (b0436ж0436жжжжж04360436() + k) % b04360436жжжжжж04360436())
    {
    }
    switch (i * (j + i) % b04360436жжжжжж04360436())
    {
    default: 
      switch (0)
      {
      case 1: 
      default: 
        for (;;)
        {
          switch (1)
          {
          }
        }
      }
      break;
    }
    try
    {
      boolean bool = this.b0427Ч042704270427ЧЧ04270427;
      return bool;
    }
    catch (Exception localException)
    {
      throw localException;
    }
  }
  
  public void bжж0436ж0436жж043604360436(AmountDomainModel paramAmountDomainModel)
  {
    switch (0)
    {
    case 1: 
    default: 
      for (;;)
      {
        switch (1)
        {
        case 0: 
        default: 
          for (;;)
          {
            switch (1)
            {
            }
          }
        }
        switch (1)
        {
        }
      }
    }
    int i = bжж0436жжжжж04360436();
    switch (i * (b0436ж0436жжжжж04360436() + i) % b04360436жжжжжж04360436())
    {
    default: 
      i = bжж0436жжжжж04360436();
      switch (i * (b0436ж0436жжжжж04360436() + i) % b04360436жжжжжж04360436())
      {
      }
      break;
    }
    this.b0427ЧЧЧ0427ЧЧ04270427 = paramAmountDomainModel;
  }
  
  @NonNull
  public String bжж0436ж0436жжж04360436()
  {
    switch (0)
    {
    case 1: 
    default: 
      for (;;)
      {
        switch (0)
        {
        }
      }
    }
    String str = this.bЧ042704270427Ч04270427Ч0427;
    int i = bжж0436жжжжж04360436();
    int j = b0436ж0436жжжжж04360436();
    if ((bжж0436жжжжж04360436() + b0436ж0436жжжжж04360436()) * bжж0436жжжжж04360436() % b04360436жжжжжж04360436() != bж0436жжжжжж04360436()) {}
    switch (i * (j + i) % b04360436жжжжжж04360436())
    {
    }
    return str;
  }
  
  public void bжж0436жж04360436ж04360436(boolean paramBoolean)
  {
    this.bЧЧЧ04270427Ч0427Ч0427 = paramBoolean;
    try
    {
      throw new NullPointerException();
    }
    catch (Exception localException) {}
  }
  
  public void bжж0436жж0436ж043604360436(boolean paramBoolean)
  {
    if ((bжж0436жжжжж04360436() + b0436ж0436жжжжж04360436()) * bжж0436жжжжж04360436() % b04360436жжжжжж04360436() != bж0436жжжжжж04360436()) {}
    try
    {
      this.b04270427Ч0427042704270427Ч0427 = paramBoolean;
      return;
    }
    catch (Exception localException)
    {
      throw localException;
    }
  }
  
  public String bжж0436жж0436жж04360436()
  {
    int i = bжж0436жжжжж04360436();
    switch (i * (b0436ж0436жжжжж04360436() + i) % b04360436жжжжжж04360436())
    {
    }
    String str = this.bЧЧ042704270427ЧЧ04270427;
    i = bжж0436жжжжж04360436();
    switch (i * (b0436ж0436жжжжж04360436() + i) % b04360436жжжжжж04360436())
    {
    }
    switch (0)
    {
    case 1: 
    default: 
      for (;;)
      {
        switch (0)
        {
        }
      }
    }
    return str;
  }
  
  /* Error */
  @Deprecated
  public boolean bжж0436жжж0436ж04360436()
  {
    // Byte code:
    //   0: invokestatic 126	kkkkkk/cccrcc:bжж0436жжжжж04360436	()I
    //   3: istore_1
    //   4: invokestatic 129	kkkkkk/cccrcc:b0436ж0436жжжжж04360436	()I
    //   7: istore_2
    //   8: invokestatic 126	kkkkkk/cccrcc:bжж0436жжжжж04360436	()I
    //   11: istore_3
    //   12: invokestatic 132	kkkkkk/cccrcc:b04360436жжжжжж04360436	()I
    //   15: istore 4
    //   17: invokestatic 135	kkkkkk/cccrcc:bж0436жжжжжж04360436	()I
    //   20: istore 5
    //   22: iload_1
    //   23: iload_2
    //   24: iadd
    //   25: iload_3
    //   26: imul
    //   27: iload 4
    //   29: irem
    //   30: iload 5
    //   32: if_icmpeq +24 -> 56
    //   35: invokestatic 126	kkkkkk/cccrcc:bжж0436жжжжж04360436	()I
    //   38: invokestatic 129	kkkkkk/cccrcc:b0436ж0436жжжжж04360436	()I
    //   41: iadd
    //   42: invokestatic 126	kkkkkk/cccrcc:bжж0436жжжжж04360436	()I
    //   45: imul
    //   46: invokestatic 132	kkkkkk/cccrcc:b04360436жжжжжж04360436	()I
    //   49: irem
    //   50: invokestatic 135	kkkkkk/cccrcc:bж0436жжжжжж04360436	()I
    //   53: if_icmpeq +3 -> 56
    //   56: aload_0
    //   57: getfield 993	kkkkkk/cccrcc:bЧ04270427ЧЧЧЧ04270427	Z
    //   60: istore 6
    //   62: iload 6
    //   64: ireturn
    //   65: astore 7
    //   67: aload 7
    //   69: athrow
    //   70: astore 7
    //   72: aload 7
    //   74: athrow
    //   75: astore 7
    //   77: aload 7
    //   79: athrow
    // Local variable table:
    //   start	length	slot	name	signature
    //   0	80	0	this	cccrcc
    //   3	22	1	i	int
    //   7	18	2	j	int
    //   11	16	3	k	int
    //   15	15	4	m	int
    //   20	13	5	n	int
    //   60	3	6	bool	boolean
    //   65	3	7	localException1	Exception
    //   70	3	7	localException2	Exception
    //   75	3	7	localException3	Exception
    // Exception table:
    //   from	to	target	type
    //   56	62	65	java/lang/Exception
    //   67	70	70	java/lang/Exception
    //   0	22	75	java/lang/Exception
  }
  
  /* Error */
  public void bжж0436жжжж043604360436(ZonedDateTime paramZonedDateTime)
  {
    // Byte code:
    //   0: invokestatic 126	kkkkkk/cccrcc:bжж0436жжжжж04360436	()I
    //   3: istore_2
    //   4: invokestatic 129	kkkkkk/cccrcc:b0436ж0436жжжжж04360436	()I
    //   7: istore_3
    //   8: invokestatic 126	kkkkkk/cccrcc:bжж0436жжжжж04360436	()I
    //   11: istore 4
    //   13: invokestatic 132	kkkkkk/cccrcc:b04360436жжжжжж04360436	()I
    //   16: istore 5
    //   18: invokestatic 135	kkkkkk/cccrcc:bж0436жжжжжж04360436	()I
    //   21: istore 6
    //   23: iload_2
    //   24: iload_3
    //   25: iadd
    //   26: iload 4
    //   28: imul
    //   29: iload 5
    //   31: irem
    //   32: iload 6
    //   34: if_icmpeq +24 -> 58
    //   37: invokestatic 126	kkkkkk/cccrcc:bжж0436жжжжж04360436	()I
    //   40: invokestatic 129	kkkkkk/cccrcc:b0436ж0436жжжжж04360436	()I
    //   43: iadd
    //   44: invokestatic 126	kkkkkk/cccrcc:bжж0436жжжжж04360436	()I
    //   47: imul
    //   48: invokestatic 132	kkkkkk/cccrcc:b04360436жжжжжж04360436	()I
    //   51: irem
    //   52: invokestatic 135	kkkkkk/cccrcc:bж0436жжжжжж04360436	()I
    //   55: if_icmpeq +3 -> 58
    //   58: aload_0
    //   59: aload_1
    //   60: putfield 1102	kkkkkk/cccrcc:bЧ0427ЧЧЧЧЧ04270427	Lorg/threeten/bp/ZonedDateTime;
    //   63: return
    //   64: astore_1
    //   65: aload_1
    //   66: athrow
    //   67: astore_1
    //   68: aload_1
    //   69: athrow
    //   70: astore_1
    //   71: aload_1
    //   72: athrow
    // Local variable table:
    //   start	length	slot	name	signature
    //   0	73	0	this	cccrcc
    //   0	73	1	paramZonedDateTime	ZonedDateTime
    //   3	23	2	i	int
    //   7	19	3	j	int
    //   11	18	4	k	int
    //   16	16	5	m	int
    //   21	14	6	n	int
    // Exception table:
    //   from	to	target	type
    //   58	63	64	java/lang/Exception
    //   8	23	67	java/lang/Exception
    //   65	67	67	java/lang/Exception
    //   0	8	70	java/lang/Exception
  }
  
  public void bжжж0436043604360436ж04360436(boolean paramBoolean)
  {
    throw new Runtime("d2j fail translate: java.lang.IndexOutOfBoundsException: fromIndex < 0: -1\n\tat java.util.BitSet.nextSetBit(BitSet.java:712)\n\tat com.googlecode.dex2jar.ir.ts.array.FillArrayTransformer.makeSureAllElementAreAssigned(FillArrayTransformer.java:505)\n\tat com.googlecode.dex2jar.ir.ts.array.FillArrayTransformer.transformReportChanged(FillArrayTransformer.java:123)\n\tat com.googlecode.dex2jar.ir.ts.StatedTransformer.transform(StatedTransformer.java:10)\n\tat com.googlecode.d2j.dex.Dex2jar$2.optimize(Dex2jar.java:149)\n\tat com.googlecode.d2j.dex.Dex2Asm.convertCode(Dex2Asm.java:414)\n\tat com.googlecode.d2j.dex.ExDex2Asm.convertCode(ExDex2Asm.java:42)\n\tat com.googlecode.d2j.dex.Dex2jar$2.convertCode(Dex2jar.java:128)\n\tat com.googlecode.d2j.dex.Dex2Asm.convertMethod(Dex2Asm.java:509)\n\tat com.googlecode.d2j.dex.Dex2Asm.convertClass(Dex2Asm.java:406)\n\tat com.googlecode.d2j.dex.Dex2Asm.convertDex(Dex2Asm.java:422)\n\tat com.googlecode.d2j.dex.Dex2jar.doTranslate(Dex2jar.java:172)\n\tat com.googlecode.d2j.dex.Dex2jar.to(Dex2jar.java:272)\n\tat com.googlecode.dex2jar.tools.Dex2jarCmd.doCommandLine(Dex2jarCmd.java:108)\n\tat com.googlecode.dex2jar.tools.BaseCmd.doMain(BaseCmd.java:288)\n\tat com.googlecode.dex2jar.tools.Dex2jarCmd.main(Dex2jarCmd.java:32)\n");
  }
  
  public void bжжж043604360436ж043604360436(String paramString)
  {
    switch (0)
    {
    case 1: 
    default: 
      for (;;)
      {
        switch (1)
        {
        }
      }
    }
    switch (0)
    {
    case 1: 
    default: 
      for (;;)
      {
        switch (1)
        {
        }
      }
    }
    int i = bжж0436жжжжж04360436();
    switch (i * (b0436ж0436жжжжж04360436() + i) % b04360436жжжжжж04360436())
    {
    }
    this.b0427Ч04270427Ч0427Ч04270427 = paramString;
    if ((bжж0436жжжжж04360436() + b0436ж0436жжжжж04360436()) * bжж0436жжжжж04360436() % b04360436жжжжжж04360436() != bж0436жжжжжж04360436()) {}
  }
  
  public boolean bжжж043604360436жж04360436()
  {
    try
    {
      int i = bжж0436жжжжж04360436();
      int j = b0436ж0436жжжжж04360436();
      int k = bжж0436жжжжж04360436();
      int m = b04360436жжжжжж04360436();
      int n = bж0436жжжжжж04360436();
      if (((i + j) * k % m != n) && ((bжж0436жжжжж04360436() + b0436ж0436жжжжж04360436()) * bжж0436жжжжж04360436() % b04360436жжжжжж04360436() != bж0436жжжжжж04360436())) {}
      boolean bool = this.bЧЧ0427ЧЧ04270427Ч0427;
      return bool;
    }
    catch (Exception localException)
    {
      throw localException;
    }
  }
  
  public boolean bжжж04360436ж0436ж04360436()
  {
    return this.b0427Ч04270427042704270427Ч0427;
  }
  
  public void bжжж04360436жж043604360436(iiooii paramIiooii)
  {
    if (((bжж0436жжжжж04360436() + b0436ж0436жжжжж04360436()) * bжж0436жжжжж04360436() % b04360436жжжжжж04360436() != bж0436жжжжжж04360436()) && ((bжж0436жжжжж04360436() + b0436ж0436жжжжж04360436()) * bжж0436жжжжж04360436() % b04360436жжжжжж04360436() != bж0436жжжжжж04360436())) {}
    this.bЧЧ0427Ч0427ЧЧ04270427 = paramIiooii;
    switch (1)
    {
    case 0: 
    default: 
      for (;;)
      {
        switch (0)
        {
        }
      }
    }
  }
  
  public ZonedDateTime bжжж04360436жжж04360436()
  {
    switch (1)
    {
    case 0: 
    default: 
      for (;;)
      {
        switch (1)
        {
        }
      }
    }
    int i = bжж0436жжжжж04360436();
    int j = b0436ж0436жжжжж04360436();
    int k = b04360436жжжжжж04360436();
    if ((bжж0436жжжжж04360436() + b0436ж0436жжжжж04360436()) * bжж0436жжжжж04360436() % b04360436жжжжжж04360436() != bж0436жжжжжж04360436()) {}
    switch (i * (j + i) % k)
    {
    default: 
      switch (0)
      {
      case 1: 
      default: 
        for (;;)
        {
          switch (0)
          {
          }
        }
      }
      break;
    }
    return this.bЧ0427ЧЧЧЧЧ04270427;
  }
  
  public void bжжж0436ж04360436ж04360436(List<String> paramList)
  {
    if ((bжж0436жжжжж04360436() + b0436ж0436жжжжж04360436()) * bжж0436жжжжж04360436() % b04360436жжжжжж04360436() != bж0436жжжжжж04360436()) {}
    try
    {
      this.b04270427Ч04270427Ч0427Ч0427 = paramList;
      return;
    }
    catch (Exception paramList)
    {
      throw paramList;
    }
  }
  
  public void bжжж0436ж0436ж043604360436(boolean paramBoolean)
  {
    this.bЧЧ04270427042704270427Ч0427 = paramBoolean;
    int i = bжж0436жжжжж04360436();
    switch (i * (b0436ж0436жжжжж04360436() + i) % b04360436жжжжжж04360436())
    {
    }
  }
  
  /* Error */
  public List<String> bжжж0436ж0436жж04360436()
  {
    // Byte code:
    //   0: iconst_2
    //   1: istore_2
    //   2: iload_2
    //   3: istore_1
    //   4: iconst_0
    //   5: tableswitch	default:+23->28, 0:+74->79, 1:+-3->2
    //   28: invokestatic 126	kkkkkk/cccrcc:bжж0436жжжжж04360436	()I
    //   31: invokestatic 129	kkkkkk/cccrcc:b0436ж0436жжжжж04360436	()I
    //   34: iadd
    //   35: invokestatic 126	kkkkkk/cccrcc:bжж0436жжжжж04360436	()I
    //   38: imul
    //   39: invokestatic 132	kkkkkk/cccrcc:b04360436жжжжжж04360436	()I
    //   42: irem
    //   43: invokestatic 135	kkkkkk/cccrcc:bж0436жжжжжж04360436	()I
    //   46: if_icmpeq +3 -> 49
    //   49: iload_2
    //   50: istore_1
    //   51: iconst_1
    //   52: tableswitch	default:+24->76, 0:+-50->2, 1:+27->79
    //   76: goto -48 -> 28
    //   79: iload_1
    //   80: iconst_0
    //   81: idiv
    //   82: istore_1
    //   83: goto -4 -> 79
    //   86: astore_3
    //   87: aload_0
    //   88: getfield 1059	kkkkkk/cccrcc:bЧ0427ЧЧЧ0427Ч04270427	Ljava/util/List;
    //   91: astore_3
    //   92: aload_3
    //   93: areturn
    //   94: astore_3
    //   95: aload_3
    //   96: athrow
    // Local variable table:
    //   start	length	slot	name	signature
    //   0	97	0	this	cccrcc
    //   3	80	1	i	int
    //   1	49	2	j	int
    //   86	1	3	localException1	Exception
    //   91	2	3	localList	List
    //   94	2	3	localException2	Exception
    // Exception table:
    //   from	to	target	type
    //   79	83	86	java/lang/Exception
    //   87	92	94	java/lang/Exception
  }
  
  public boolean bжжж0436жж0436ж04360436()
  {
    if (((bжж0436жжжжж04360436() + b0436ж0436жжжжж04360436()) * bжж0436жжжжж04360436() % b04360436жжжжжж04360436() == bж0436жжжжжж04360436()) || ((bжж0436жжжжж04360436() + b0436ж0436жжжжж04360436()) * bжж0436жжжжж04360436() % b04360436жжжжжж04360436() != bж0436жжжжжж04360436())) {}
    try
    {
      boolean bool = this.bЧ0427Ч0427ЧЧЧ04270427;
      return bool;
    }
    catch (Exception localException)
    {
      throw localException;
    }
  }
  
  public void bжжж0436жжж043604360436(boolean paramBoolean)
  {
    int i = bжж0436жжжжж04360436();
    switch (i * (b0436ж0436жжжжж04360436() + i) % b04360436жжжжжж04360436())
    {
    }
    i = bжж0436жжжжж04360436();
    switch (i * (b0436ж0436жжжжж04360436() + i) % b04360436жжжжжж04360436())
    {
    }
    this.b0427Ч0427ЧЧЧЧ04270427 = paramBoolean;
  }
  
  public String bжжж0436жжжж04360436()
  {
    if ((bжж0436жжжжж04360436() + b0436ж0436жжжжж04360436()) * bжж0436жжжжж04360436() % b04360436жжжжжж04360436() != bж0436жжжжжж04360436()) {}
    switch (0)
    {
    case 1: 
    default: 
      for (;;)
      {
        switch (1)
        {
        }
      }
    }
    String str = this.bЧ0427Ч04270427Ч0427Ч0427;
    int i = bжж0436жжжжж04360436();
    switch (i * (b0436ж0436жжжжж04360436() + i) % b04360436жжжжжж04360436())
    {
    }
    return str;
  }
  
  public void bжжжж043604360436ж04360436(String paramString)
  {
    switch (0)
    {
    case 1: 
    default: 
      for (;;)
      {
        switch (1)
        {
        }
      }
    }
    try
    {
      int i = bжж0436жжжжж04360436();
      int j = b0436ж0436жжжжж04360436();
      int k = bжж0436жжжжж04360436();
      int m = b04360436жжжжжж04360436();
      int n = bж0436жжжжжж04360436();
      if ((i + j) * k % m != n)
      {
        i = bжж0436жжжжж04360436();
        switch (i * (b0436ж0436жжжжж04360436() + i) % b04360436жжжжжж04360436())
        {
        }
      }
      this.b04270427ЧЧЧ04270427Ч0427 = paramString;
      return;
    }
    catch (Exception paramString)
    {
      throw paramString;
    }
  }
  
  public void bжжжж04360436ж043604360436(AmountDomainModel paramAmountDomainModel)
  {
    int i = bжж0436жжжжж04360436();
    switch (i * (b0436ж0436жжжжж04360436() + i) % b04360436жжжжжж04360436())
    {
    default: 
      if ((bжж0436жжжжж04360436() + b0436ж0436жжжжж04360436()) * bжж0436жжжжж04360436() % b04360436жжжжжж04360436() == bж0436жжжжжж04360436()) {
        break;
      }
    }
    this.b042704270427ЧЧ0427Ч04270427 = paramAmountDomainModel;
  }
  
  public ZonedDateTime bжжжж04360436жж04360436()
  {
    try
    {
      ZonedDateTime localZonedDateTime = this.bЧ042704270427Ч0427Ч04270427;
      return localZonedDateTime;
    }
    catch (Exception localException)
    {
      throw localException;
    }
  }
  
  public boolean bжжжж0436ж0436ж04360436()
  {
    if ((bжж0436жжжжж04360436() + b0436ж0436жжжжж04360436()) * bжж0436жжжжж04360436() % b04360436жжжжжж04360436() != bж0436жжжжжж04360436()) {}
    boolean bool = this.bЧ0427Ч0427042704270427Ч0427;
    switch (0)
    {
    case 1: 
    default: 
      for (;;)
      {
        switch (1)
        {
        }
      }
    }
    return bool;
  }
  
  public void bжжжж0436жж043604360436(boolean paramBoolean)
  {
    if ((bжж0436жжжжж04360436() + b0436ж0436жжжжж04360436()) * bжж0436жжжжж04360436() % b04360436жжжжжж04360436() != bж0436жжжжжж04360436()) {}
    this.b0427Ч04270427ЧЧЧ04270427 = paramBoolean;
  }
  
  public AmountDomainModel bжжжж0436жжж04360436()
  {
    if ((bжж0436жжжжж04360436() + b0436ж0436жжжжж04360436()) * bжж0436жжжжж04360436() % b04360436жжжжжж04360436() != bж0436жжжжжж04360436()) {}
    int i = bжж0436жжжжж04360436();
    switch (i * (b0436ж0436жжжжж04360436() + i) % b04360436жжжжжж04360436())
    {
    }
    return this.bЧ04270427ЧЧ04270427Ч0427;
  }
  
  /* Error */
  public boolean bжжжжж04360436ж04360436()
  {
    // Byte code:
    //   0: invokestatic 126	kkkkkk/cccrcc:bжж0436жжжжж04360436	()I
    //   3: istore_1
    //   4: invokestatic 129	kkkkkk/cccrcc:b0436ж0436жжжжж04360436	()I
    //   7: istore_2
    //   8: invokestatic 126	kkkkkk/cccrcc:bжж0436жжжжж04360436	()I
    //   11: istore_3
    //   12: invokestatic 126	kkkkkk/cccrcc:bжж0436жжжжж04360436	()I
    //   15: invokestatic 129	kkkkkk/cccrcc:b0436ж0436жжжжж04360436	()I
    //   18: iadd
    //   19: invokestatic 126	kkkkkk/cccrcc:bжж0436жжжжж04360436	()I
    //   22: imul
    //   23: invokestatic 132	kkkkkk/cccrcc:b04360436жжжжжж04360436	()I
    //   26: irem
    //   27: invokestatic 135	kkkkkk/cccrcc:bж0436жжжжжж04360436	()I
    //   30: if_icmpeq +3 -> 33
    //   33: invokestatic 132	kkkkkk/cccrcc:b04360436жжжжжж04360436	()I
    //   36: istore 4
    //   38: invokestatic 135	kkkkkk/cccrcc:bж0436жжжжжж04360436	()I
    //   41: istore 5
    //   43: iload_1
    //   44: iload_2
    //   45: iadd
    //   46: iload_3
    //   47: imul
    //   48: iload 4
    //   50: irem
    //   51: iload 5
    //   53: if_icmpeq +3 -> 56
    //   56: iconst_1
    //   57: tableswitch	default:+23->80, 0:+-1->56, 1:+50->107
    //   80: iconst_0
    //   81: tableswitch	default:+23->104, 0:+26->107, 1:+-25->56
    //   104: goto -24 -> 80
    //   107: aload_0
    //   108: getfield 828	kkkkkk/cccrcc:bЧЧ04270427Ч0427Ч04270427	Z
    //   111: istore 6
    //   113: iload 6
    //   115: ireturn
    //   116: astore 7
    //   118: aload 7
    //   120: athrow
    //   121: astore 7
    //   123: aload 7
    //   125: athrow
    // Local variable table:
    //   start	length	slot	name	signature
    //   0	126	0	this	cccrcc
    //   3	43	1	i	int
    //   7	39	2	j	int
    //   11	37	3	k	int
    //   36	15	4	m	int
    //   41	13	5	n	int
    //   111	3	6	bool	boolean
    //   116	3	7	localException1	Exception
    //   121	3	7	localException2	Exception
    // Exception table:
    //   from	to	target	type
    //   0	12	116	java/lang/Exception
    //   33	43	116	java/lang/Exception
    //   107	113	121	java/lang/Exception
  }
  
  public void bжжжжж0436ж043604360436(boolean paramBoolean)
  {
    if ((bжж0436жжжжж04360436() + b0436ж0436жжжжж04360436()) * bжж0436жжжжж04360436() % b04360436жжжжжж04360436() != bж0436жжжжжж04360436()) {}
    this.bЧ0427Ч04270427ЧЧ04270427 = paramBoolean;
  }
  
  public List<iiiioi> bжжжжж0436жж04360436()
  {
    List localList = this.b0427Ч0427Ч0427ЧЧ04270427;
    int i = bжж0436жжжжж04360436();
    int j = bжж0436жжжжж04360436();
    switch (j * (b0436ж0436жжжжж04360436() + j) % b04360436жжжжжж04360436())
    {
    }
    if ((i + b0436ж0436жжжжж04360436()) * bжж0436жжжжж04360436() % b04360436жжжжжж04360436() != bж0436жжжжжж04360436()) {}
    return localList;
  }
  
  /* Error */
  public boolean bжжжжжж0436ж04360436()
  {
    // Byte code:
    //   0: invokestatic 126	kkkkkk/cccrcc:bжж0436жжжжж04360436	()I
    //   3: istore_1
    //   4: invokestatic 126	kkkkkk/cccrcc:bжж0436жжжжж04360436	()I
    //   7: invokestatic 129	kkkkkk/cccrcc:b0436ж0436жжжжж04360436	()I
    //   10: iadd
    //   11: invokestatic 126	kkkkkk/cccrcc:bжж0436жжжжж04360436	()I
    //   14: imul
    //   15: invokestatic 132	kkkkkk/cccrcc:b04360436жжжжжж04360436	()I
    //   18: irem
    //   19: invokestatic 135	kkkkkk/cccrcc:bж0436жжжжжж04360436	()I
    //   22: if_icmpeq +3 -> 25
    //   25: invokestatic 129	kkkkkk/cccrcc:b0436ж0436жжжжж04360436	()I
    //   28: istore_2
    //   29: invokestatic 126	kkkkkk/cccrcc:bжж0436жжжжж04360436	()I
    //   32: istore_3
    //   33: invokestatic 132	kkkkkk/cccrcc:b04360436жжжжжж04360436	()I
    //   36: istore 4
    //   38: invokestatic 135	kkkkkk/cccrcc:bж0436жжжжжж04360436	()I
    //   41: istore 5
    //   43: iload_1
    //   44: iload_2
    //   45: iadd
    //   46: iload_3
    //   47: imul
    //   48: iload 4
    //   50: irem
    //   51: iload 5
    //   53: if_icmpeq +3 -> 56
    //   56: aload_0
    //   57: getfield 1047	kkkkkk/cccrcc:bЧЧ04270427Ч04270427Ч0427	Z
    //   60: istore 6
    //   62: iload 6
    //   64: ireturn
    //   65: astore 7
    //   67: aload 7
    //   69: athrow
    //   70: astore 7
    //   72: aload 7
    //   74: athrow
    //   75: astore 7
    //   77: aload 7
    //   79: athrow
    // Local variable table:
    //   start	length	slot	name	signature
    //   0	80	0	this	cccrcc
    //   3	43	1	i	int
    //   28	18	2	j	int
    //   32	16	3	k	int
    //   36	15	4	m	int
    //   41	13	5	n	int
    //   60	3	6	bool	boolean
    //   65	3	7	localException1	Exception
    //   70	3	7	localException2	Exception
    //   75	3	7	localException3	Exception
    // Exception table:
    //   from	to	target	type
    //   56	62	65	java/lang/Exception
    //   0	4	70	java/lang/Exception
    //   25	29	70	java/lang/Exception
    //   38	43	70	java/lang/Exception
    //   67	70	70	java/lang/Exception
    //   29	38	75	java/lang/Exception
  }
  
  /* Error */
  public void bжжжжжжж043604360436(List<String> paramList)
  {
    // Byte code:
    //   0: invokestatic 126	kkkkkk/cccrcc:bжж0436жжжжж04360436	()I
    //   3: istore_2
    //   4: invokestatic 129	kkkkkk/cccrcc:b0436ж0436жжжжж04360436	()I
    //   7: istore_3
    //   8: invokestatic 126	kkkkkk/cccrcc:bжж0436жжжжж04360436	()I
    //   11: istore 4
    //   13: invokestatic 132	kkkkkk/cccrcc:b04360436жжжжжж04360436	()I
    //   16: istore 5
    //   18: invokestatic 135	kkkkkk/cccrcc:bж0436жжжжжж04360436	()I
    //   21: istore 6
    //   23: iload_2
    //   24: iload_3
    //   25: iadd
    //   26: iload 4
    //   28: imul
    //   29: iload 5
    //   31: irem
    //   32: iload 6
    //   34: if_icmpeq +38 -> 72
    //   37: invokestatic 126	kkkkkk/cccrcc:bжж0436жжжжж04360436	()I
    //   40: istore_2
    //   41: iload_2
    //   42: invokestatic 129	kkkkkk/cccrcc:b0436ж0436жжжжж04360436	()I
    //   45: iload_2
    //   46: iadd
    //   47: imul
    //   48: invokestatic 132	kkkkkk/cccrcc:b04360436жжжжжж04360436	()I
    //   51: irem
    //   52: tableswitch	default:+20->72, 0:+20->72
    //   72: aload_0
    //   73: aload_1
    //   74: putfield 837	kkkkkk/cccrcc:bЧ0427ЧЧ042704270427Ч0427	Ljava/util/List;
    //   77: return
    //   78: astore_1
    //   79: aload_1
    //   80: athrow
    //   81: astore_1
    //   82: aload_1
    //   83: athrow
    // Local variable table:
    //   start	length	slot	name	signature
    //   0	84	0	this	cccrcc
    //   0	84	1	paramList	List<String>
    //   3	45	2	i	int
    //   7	19	3	j	int
    //   11	18	4	k	int
    //   16	16	5	m	int
    //   21	14	6	n	int
    // Exception table:
    //   from	to	target	type
    //   72	77	78	java/lang/Exception
    //   0	23	81	java/lang/Exception
    //   79	81	81	java/lang/Exception
  }
}
