package kkkkkk;

import android.support.annotation.NonNull;

public final class cciccc
{
  public static int b04430443ууууу04430443 = 2;
  public static int b0443уууууу04430443 = 0;
  public static int bу0443ууууу04430443 = 1;
  public static int bууууууу04430443 = 46;
  @NonNull
  private final String b0443044304430443044304430443у0443;
  @NonNull
  private final String b04430443у0443044304430443у0443;
  @NonNull
  private final String b0443у04430443044304430443у0443;
  @NonNull
  private final oioooo b0443уу0443044304430443у0443;
  @NonNull
  private final pdppdp bу044304430443044304430443у0443;
  @NonNull
  private final String bу0443у0443044304430443у0443;
  @NonNull
  private final String bуу04430443044304430443у0443;
  
  private cciccc(@NonNull ciiccc paramCiiccc)
  {
    this.b0443уу0443044304430443у0443 = ciiccc.b0412ВВ0412В0412ВВВВ(paramCiiccc);
    this.b0443044304430443044304430443у0443 = ciiccc.bВ0412В0412В0412ВВВВ(paramCiiccc);
    this.bуу04430443044304430443у0443 = ciiccc.b04120412В0412В0412ВВВВ(paramCiiccc);
    this.b0443у04430443044304430443у0443 = ciiccc.bВВ04120412В0412ВВВВ(paramCiiccc);
    this.bу044304430443044304430443у0443 = ciiccc.b0412В04120412В0412ВВВВ(paramCiiccc);
    this.bу0443у0443044304430443у0443 = ciiccc.bВ041204120412В0412ВВВВ(paramCiiccc);
    this.b04430443у0443044304430443у0443 = ciiccc.b0412041204120412В0412ВВВВ(paramCiiccc);
  }
  
  public static int b041204120412041204120412ВВВВ()
  {
    return 0;
  }
  
  public static int b0412В0412041204120412ВВВВ()
  {
    return 1;
  }
  
  public static int bВ04120412041204120412ВВВВ()
  {
    return 2;
  }
  
  public static int bВВВВВВ0412ВВВ()
  {
    return 6;
  }
  
  @NonNull
  public String b041204120412ВВВ0412ВВВ()
  {
    return this.b0443044304430443044304430443у0443;
  }
  
  @NonNull
  public String b04120412ВВВВ0412ВВВ()
  {
    switch (1)
    {
    case 0: 
    default: 
      for (;;)
      {
        switch (1)
        {
        }
      }
    }
    if ((bууууууу04430443 + bу0443ууууу04430443) * bууууууу04430443 % b04430443ууууу04430443 != b0443уууууу04430443)
    {
      bууууууу04430443 = bВВВВВВ0412ВВВ();
      b0443уууууу04430443 = 23;
    }
    return this.b04430443у0443044304430443у0443;
  }
  
  /* Error */
  @NonNull
  public String b0412В0412ВВВ0412ВВВ()
  {
    // Byte code:
    //   0: getstatic 86	kkkkkk/cciccc:bууууууу04430443	I
    //   3: istore_1
    //   4: iload_1
    //   5: getstatic 88	kkkkkk/cciccc:bу0443ууууу04430443	I
    //   8: iload_1
    //   9: iadd
    //   10: imul
    //   11: getstatic 90	kkkkkk/cciccc:b04430443ууууу04430443	I
    //   14: irem
    //   15: tableswitch	default:+17->32, 0:+27->42
    //   32: bipush 16
    //   34: putstatic 86	kkkkkk/cciccc:bууууууу04430443	I
    //   37: bipush 69
    //   39: putstatic 92	kkkkkk/cciccc:b0443уууууу04430443	I
    //   42: getstatic 86	kkkkkk/cciccc:bууууууу04430443	I
    //   45: istore_1
    //   46: getstatic 88	kkkkkk/cciccc:bу0443ууууу04430443	I
    //   49: istore_2
    //   50: getstatic 86	kkkkkk/cciccc:bууууууу04430443	I
    //   53: istore_3
    //   54: getstatic 90	kkkkkk/cciccc:b04430443ууууу04430443	I
    //   57: istore 4
    //   59: getstatic 92	kkkkkk/cciccc:b0443уууууу04430443	I
    //   62: istore 5
    //   64: iload_1
    //   65: iload_2
    //   66: iadd
    //   67: iload_3
    //   68: imul
    //   69: iload 4
    //   71: irem
    //   72: iload 5
    //   74: if_icmpeq +13 -> 87
    //   77: bipush 7
    //   79: putstatic 86	kkkkkk/cciccc:bууууууу04430443	I
    //   82: bipush 71
    //   84: putstatic 92	kkkkkk/cciccc:b0443уууууу04430443	I
    //   87: aload_0
    //   88: getfield 54	kkkkkk/cciccc:b0443у04430443044304430443у0443	Ljava/lang/String;
    //   91: astore 6
    //   93: aload 6
    //   95: areturn
    //   96: astore 6
    //   98: aload 6
    //   100: athrow
    //   101: astore 6
    //   103: aload 6
    //   105: athrow
    // Local variable table:
    //   start	length	slot	name	signature
    //   0	106	0	this	cciccc
    //   3	64	1	i	int
    //   49	18	2	j	int
    //   53	16	3	k	int
    //   57	15	4	m	int
    //   62	13	5	n	int
    //   91	3	6	str	String
    //   96	3	6	localException1	Exception
    //   101	3	6	localException2	Exception
    // Exception table:
    //   from	to	target	type
    //   42	64	96	java/lang/Exception
    //   87	93	96	java/lang/Exception
    //   77	87	101	java/lang/Exception
  }
  
  /* Error */
  @NonNull
  public oioooo b0412ВВВВВ0412ВВВ()
  {
    // Byte code:
    //   0: iconst_0
    //   1: tableswitch	default:+23->24, 0:+50->51, 1:+-1->0
    //   24: iconst_1
    //   25: tableswitch	default:+23->48, 0:+-25->0, 1:+26->51
    //   48: goto -24 -> 24
    //   51: aload_0
    //   52: getfield 38	kkkkkk/cciccc:b0443уу0443044304430443у0443	Lkkkkkk/oioooo;
    //   55: astore 5
    //   57: getstatic 86	kkkkkk/cciccc:bууууууу04430443	I
    //   60: istore_1
    //   61: getstatic 88	kkkkkk/cciccc:bу0443ууууу04430443	I
    //   64: istore_2
    //   65: getstatic 86	kkkkkk/cciccc:bууууууу04430443	I
    //   68: getstatic 88	kkkkkk/cciccc:bу0443ууууу04430443	I
    //   71: iadd
    //   72: getstatic 86	kkkkkk/cciccc:bууууууу04430443	I
    //   75: imul
    //   76: getstatic 90	kkkkkk/cciccc:b04430443ууууу04430443	I
    //   79: irem
    //   80: getstatic 92	kkkkkk/cciccc:b0443уууууу04430443	I
    //   83: if_icmpeq +13 -> 96
    //   86: bipush 18
    //   88: putstatic 86	kkkkkk/cciccc:bууууууу04430443	I
    //   91: bipush 91
    //   93: putstatic 92	kkkkkk/cciccc:b0443уууууу04430443	I
    //   96: getstatic 86	kkkkkk/cciccc:bууууууу04430443	I
    //   99: istore_3
    //   100: getstatic 90	kkkkkk/cciccc:b04430443ууууу04430443	I
    //   103: istore 4
    //   105: iload_1
    //   106: iload_2
    //   107: iadd
    //   108: iload_3
    //   109: imul
    //   110: iload 4
    //   112: irem
    //   113: getstatic 92	kkkkkk/cciccc:b0443уууууу04430443	I
    //   116: if_icmpeq +15 -> 131
    //   119: invokestatic 94	kkkkkk/cciccc:bВВВВВВ0412ВВВ	()I
    //   122: putstatic 86	kkkkkk/cciccc:bууууууу04430443	I
    //   125: invokestatic 94	kkkkkk/cciccc:bВВВВВВ0412ВВВ	()I
    //   128: putstatic 92	kkkkkk/cciccc:b0443уууууу04430443	I
    //   131: aload 5
    //   133: areturn
    //   134: astore 5
    //   136: aload 5
    //   138: athrow
    //   139: astore 5
    //   141: aload 5
    //   143: athrow
    // Local variable table:
    //   start	length	slot	name	signature
    //   0	144	0	this	cciccc
    //   60	48	1	i	int
    //   64	44	2	j	int
    //   99	11	3	k	int
    //   103	10	4	m	int
    //   55	77	5	localOioooo	oioooo
    //   134	3	5	localException1	Exception
    //   139	3	5	localException2	Exception
    // Exception table:
    //   from	to	target	type
    //   51	65	134	java/lang/Exception
    //   105	131	134	java/lang/Exception
    //   96	105	139	java/lang/Exception
  }
  
  @NonNull
  public pdppdp bВ04120412ВВВ0412ВВВ()
  {
    switch (0)
    {
    case 1: 
    default: 
      for (;;)
      {
        switch (1)
        {
        }
      }
    }
    int i = bууууууу04430443;
    int j = bууууууу04430443;
    switch (j * (bу0443ууууу04430443 + j) % bВ04120412041204120412ВВВВ())
    {
    default: 
      bууууууу04430443 = 26;
      b0443уууууу04430443 = 11;
    }
    if ((i + bу0443ууууу04430443) * bууууууу04430443 % b04430443ууууу04430443 != b0443уууууу04430443)
    {
      bууууууу04430443 = 58;
      b0443уууууу04430443 = bВВВВВВ0412ВВВ();
    }
    pdppdp localPdppdp = this.bу044304430443044304430443у0443;
    switch (1)
    {
    case 0: 
    default: 
      for (;;)
      {
        switch (0)
        {
        }
      }
    }
    return localPdppdp;
  }
  
  /* Error */
  @NonNull
  public String bВ0412ВВВВ0412ВВВ()
  {
    // Byte code:
    //   0: aload_0
    //   1: getfield 65	kkkkkk/cciccc:bу0443у0443044304430443у0443	Ljava/lang/String;
    //   4: astore 6
    //   6: getstatic 86	kkkkkk/cciccc:bууууууу04430443	I
    //   9: istore_1
    //   10: getstatic 88	kkkkkk/cciccc:bу0443ууууу04430443	I
    //   13: istore_2
    //   14: getstatic 86	kkkkkk/cciccc:bууууууу04430443	I
    //   17: istore_3
    //   18: getstatic 90	kkkkkk/cciccc:b04430443ууууу04430443	I
    //   21: istore 4
    //   23: getstatic 86	kkkkkk/cciccc:bууууууу04430443	I
    //   26: getstatic 88	kkkkkk/cciccc:bу0443ууууу04430443	I
    //   29: iadd
    //   30: getstatic 86	kkkkkk/cciccc:bууууууу04430443	I
    //   33: imul
    //   34: invokestatic 103	kkkkkk/cciccc:bВ04120412041204120412ВВВВ	()I
    //   37: irem
    //   38: getstatic 92	kkkkkk/cciccc:b0443уууууу04430443	I
    //   41: if_icmpeq +15 -> 56
    //   44: invokestatic 94	kkkkkk/cciccc:bВВВВВВ0412ВВВ	()I
    //   47: putstatic 86	kkkkkk/cciccc:bууууууу04430443	I
    //   50: invokestatic 94	kkkkkk/cciccc:bВВВВВВ0412ВВВ	()I
    //   53: putstatic 92	kkkkkk/cciccc:b0443уууууу04430443	I
    //   56: getstatic 92	kkkkkk/cciccc:b0443уууууу04430443	I
    //   59: istore 5
    //   61: iload_1
    //   62: iload_2
    //   63: iadd
    //   64: iload_3
    //   65: imul
    //   66: iload 4
    //   68: irem
    //   69: iload 5
    //   71: if_icmpeq +13 -> 84
    //   74: invokestatic 94	kkkkkk/cciccc:bВВВВВВ0412ВВВ	()I
    //   77: putstatic 86	kkkkkk/cciccc:bууууууу04430443	I
    //   80: iconst_4
    //   81: putstatic 92	kkkkkk/cciccc:b0443уууууу04430443	I
    //   84: iconst_0
    //   85: tableswitch	default:+23->108, 0:+50->135, 1:+-1->84
    //   108: iconst_1
    //   109: tableswitch	default:+23->132, 0:+-25->84, 1:+26->135
    //   132: goto -24 -> 108
    //   135: aload 6
    //   137: areturn
    //   138: astore 6
    //   140: aload 6
    //   142: athrow
    //   143: astore 6
    //   145: aload 6
    //   147: athrow
    // Local variable table:
    //   start	length	slot	name	signature
    //   0	148	0	this	cciccc
    //   9	55	1	i	int
    //   13	51	2	j	int
    //   17	49	3	k	int
    //   21	48	4	m	int
    //   59	13	5	n	int
    //   4	132	6	str	String
    //   138	3	6	localException1	Exception
    //   143	3	6	localException2	Exception
    // Exception table:
    //   from	to	target	type
    //   0	18	138	java/lang/Exception
    //   56	61	138	java/lang/Exception
    //   18	23	143	java/lang/Exception
    //   74	84	143	java/lang/Exception
  }
  
  /* Error */
  @NonNull
  public String bВВ0412ВВВ0412ВВВ()
  {
    // Byte code:
    //   0: getstatic 86	kkkkkk/cciccc:bууууууу04430443	I
    //   3: istore_1
    //   4: getstatic 88	kkkkkk/cciccc:bу0443ууууу04430443	I
    //   7: istore_2
    //   8: getstatic 86	kkkkkk/cciccc:bууууууу04430443	I
    //   11: istore_3
    //   12: getstatic 90	kkkkkk/cciccc:b04430443ууууу04430443	I
    //   15: istore 4
    //   17: getstatic 92	kkkkkk/cciccc:b0443уууууу04430443	I
    //   20: istore 5
    //   22: iload_1
    //   23: iload_2
    //   24: iadd
    //   25: iload_3
    //   26: imul
    //   27: iload 4
    //   29: irem
    //   30: iload 5
    //   32: if_icmpeq +46 -> 78
    //   35: invokestatic 94	kkkkkk/cciccc:bВВВВВВ0412ВВВ	()I
    //   38: putstatic 86	kkkkkk/cciccc:bууууууу04430443	I
    //   41: bipush 23
    //   43: putstatic 92	kkkkkk/cciccc:b0443уууууу04430443	I
    //   46: getstatic 86	kkkkkk/cciccc:bууууууу04430443	I
    //   49: getstatic 88	kkkkkk/cciccc:bу0443ууууу04430443	I
    //   52: iadd
    //   53: getstatic 86	kkkkkk/cciccc:bууууууу04430443	I
    //   56: imul
    //   57: getstatic 90	kkkkkk/cciccc:b04430443ууууу04430443	I
    //   60: irem
    //   61: getstatic 92	kkkkkk/cciccc:b0443уууууу04430443	I
    //   64: if_icmpeq +14 -> 78
    //   67: invokestatic 94	kkkkkk/cciccc:bВВВВВВ0412ВВВ	()I
    //   70: putstatic 86	kkkkkk/cciccc:bууууууу04430443	I
    //   73: bipush 95
    //   75: putstatic 92	kkkkkk/cciccc:b0443уууууу04430443	I
    //   78: aload_0
    //   79: getfield 49	kkkkkk/cciccc:bуу04430443044304430443у0443	Ljava/lang/String;
    //   82: astore 6
    //   84: iconst_0
    //   85: tableswitch	default:+23->108, 0:+50->135, 1:+-1->84
    //   108: iconst_0
    //   109: tableswitch	default:+23->132, 0:+26->135, 1:+-25->84
    //   132: goto -24 -> 108
    //   135: aload 6
    //   137: areturn
    //   138: astore 6
    //   140: aload 6
    //   142: athrow
    //   143: astore 6
    //   145: aload 6
    //   147: athrow
    // Local variable table:
    //   start	length	slot	name	signature
    //   0	148	0	this	cciccc
    //   3	22	1	i	int
    //   7	18	2	j	int
    //   11	16	3	k	int
    //   15	15	4	m	int
    //   20	13	5	n	int
    //   82	54	6	str	String
    //   138	3	6	localException1	Exception
    //   143	3	6	localException2	Exception
    // Exception table:
    //   from	to	target	type
    //   0	22	138	java/lang/Exception
    //   35	46	143	java/lang/Exception
    //   78	84	143	java/lang/Exception
  }
  
  public static class ciiccc
  {
    public static int b04430443у0443ууу04430443 = 5;
    public static int b0443у04430443ууу04430443 = 1;
    public static int bу044304430443ууу04430443 = 2;
    public static int bуу04430443ууу04430443;
    private String b044304430443уууу04430443;
    private String b0443у0443уууу04430443;
    private pdppdp b0443уу0443ууу04430443;
    private String bу04430443уууу04430443;
    private String bу0443у0443ууу04430443;
    private oioooo bуу0443уууу04430443;
    private String bууу0443ууу04430443;
    
    public ciiccc() {}
    
    private void b04120412В041204120412ВВВВ(Object paramObject, @NonNull String paramString)
    {
      if (paramObject == null)
      {
        if ((bВ0412ВВ04120412ВВВВ() + b0443у04430443ууу04430443) * bВ0412ВВ04120412ВВВВ() % bу044304430443ууу04430443 != bуу04430443ууу04430443)
        {
          b04430443у0443ууу04430443 = 8;
          bуу04430443ууу04430443 = bВ0412ВВ04120412ВВВВ();
          int i = b04430443у0443ууу04430443;
          switch (i * (b0443у04430443ууу04430443 + i) % bу044304430443ууу04430443)
          {
          default: 
            b04430443у0443ууу04430443 = 65;
            bуу04430443ууу04430443 = bВ0412ВВ04120412ВВВВ();
          }
        }
        paramObject = new NullPointerException(String.format(gguuuu.bккккк043Aкк043A043A("MfpdzzAogJk_oe]GWgU`e+\020\024a\rY`]]\bIK\005WHV\017", '}', '\002'), new Object[] { paramString }));
        switch (1)
        {
        case 0: 
        default: 
          for (;;)
          {
            switch (0)
            {
            }
          }
        }
        try
        {
          throw paramObject;
        }
        catch (Exception paramObject)
        {
          throw paramObject;
        }
      }
    }
    
    public static int b04120412ВВ04120412ВВВВ()
    {
      return 1;
    }
    
    public static int bВ0412ВВ04120412ВВВВ()
    {
      return 58;
    }
    
    /* Error */
    private void bВВ0412041204120412ВВВВ()
    {
      // Byte code:
      //   0: aload_0
      //   1: aload_0
      //   2: getfield 83	kkkkkk/cciccc$ciiccc:bуу0443уууу04430443	Lkkkkkk/oioooo;
      //   5: ldc 95
      //   7: bipush 35
      //   9: bipush 41
      //   11: iconst_0
      //   12: invokestatic 99	kkkkkk/gguuuu:bк043Aккк043Aкк043A043A	(Ljava/lang/String;CCC)Ljava/lang/String;
      //   15: invokespecial 101	kkkkkk/cciccc$ciiccc:b04120412В041204120412ВВВВ	(Ljava/lang/Object;Ljava/lang/String;)V
      //   18: aload_0
      //   19: getfield 92	kkkkkk/cciccc$ciiccc:bу0443у0443ууу04430443	Ljava/lang/String;
      //   22: astore_2
      //   23: getstatic 38	kkkkkk/cciccc$ciiccc:b04430443у0443ууу04430443	I
      //   26: istore_1
      //   27: iload_1
      //   28: getstatic 40	kkkkkk/cciccc$ciiccc:b0443у04430443ууу04430443	I
      //   31: iload_1
      //   32: iadd
      //   33: imul
      //   34: getstatic 42	kkkkkk/cciccc$ciiccc:bу044304430443ууу04430443	I
      //   37: irem
      //   38: tableswitch	default:+18->56, 0:+29->67
      //   56: bipush 99
      //   58: putstatic 38	kkkkkk/cciccc$ciiccc:b04430443у0443ууу04430443	I
      //   61: invokestatic 48	kkkkkk/cciccc$ciiccc:bВ0412ВВ04120412ВВВВ	()I
      //   64: putstatic 44	kkkkkk/cciccc$ciiccc:bуу04430443ууу04430443	I
      //   67: aload_0
      //   68: aload_2
      //   69: ldc 103
      //   71: bipush 23
      //   73: iconst_1
      //   74: invokestatic 61	kkkkkk/gguuuu:bккккк043Aкк043A043A	(Ljava/lang/String;CC)Ljava/lang/String;
      //   77: invokespecial 101	kkkkkk/cciccc$ciiccc:b04120412В041204120412ВВВВ	(Ljava/lang/Object;Ljava/lang/String;)V
      //   80: aload_0
      //   81: aload_0
      //   82: getfield 74	kkkkkk/cciccc$ciiccc:b044304430443уууу04430443	Ljava/lang/String;
      //   85: ldc 105
      //   87: bipush 76
      //   89: iconst_4
      //   90: invokestatic 61	kkkkkk/gguuuu:bккккк043Aкк043A043A	(Ljava/lang/String;CC)Ljava/lang/String;
      //   93: invokespecial 101	kkkkkk/cciccc$ciiccc:b04120412В041204120412ВВВВ	(Ljava/lang/Object;Ljava/lang/String;)V
      //   96: aload_0
      //   97: aload_0
      //   98: getfield 107	kkkkkk/cciccc$ciiccc:bууу0443ууу04430443	Ljava/lang/String;
      //   101: ldc 109
      //   103: sipush 141
      //   106: iconst_2
      //   107: invokestatic 61	kkkkkk/gguuuu:bккккк043Aкк043A043A	(Ljava/lang/String;CC)Ljava/lang/String;
      //   110: invokespecial 101	kkkkkk/cciccc$ciiccc:b04120412В041204120412ВВВВ	(Ljava/lang/Object;Ljava/lang/String;)V
      //   113: aload_0
      //   114: aload_0
      //   115: getfield 79	kkkkkk/cciccc$ciiccc:b0443уу0443ууу04430443	Lkkkkkk/pdppdp;
      //   118: ldc 111
      //   120: bipush 16
      //   122: bipush 23
      //   124: iconst_3
      //   125: invokestatic 99	kkkkkk/gguuuu:bк043Aккк043Aкк043A043A	(Ljava/lang/String;CCC)Ljava/lang/String;
      //   128: invokespecial 101	kkkkkk/cciccc$ciiccc:b04120412В041204120412ВВВВ	(Ljava/lang/Object;Ljava/lang/String;)V
      //   131: aload_0
      //   132: aload_0
      //   133: getfield 86	kkkkkk/cciccc$ciiccc:b0443у0443уууу04430443	Ljava/lang/String;
      //   136: ldc 113
      //   138: sipush 248
      //   141: bipush 84
      //   143: iconst_1
      //   144: invokestatic 99	kkkkkk/gguuuu:bк043Aккк043Aкк043A043A	(Ljava/lang/String;CCC)Ljava/lang/String;
      //   147: invokespecial 101	kkkkkk/cciccc$ciiccc:b04120412В041204120412ВВВВ	(Ljava/lang/Object;Ljava/lang/String;)V
      //   150: getstatic 38	kkkkkk/cciccc$ciiccc:b04430443у0443ууу04430443	I
      //   153: istore_1
      //   154: iload_1
      //   155: getstatic 40	kkkkkk/cciccc$ciiccc:b0443у04430443ууу04430443	I
      //   158: iload_1
      //   159: iadd
      //   160: imul
      //   161: getstatic 42	kkkkkk/cciccc$ciiccc:bу044304430443ууу04430443	I
      //   164: irem
      //   165: tableswitch	default:+19->184, 0:+30->195
      //   184: bipush 47
      //   186: putstatic 38	kkkkkk/cciccc$ciiccc:b04430443у0443ууу04430443	I
      //   189: invokestatic 48	kkkkkk/cciccc$ciiccc:bВ0412ВВ04120412ВВВВ	()I
      //   192: putstatic 44	kkkkkk/cciccc$ciiccc:bуу04430443ууу04430443	I
      //   195: aload_0
      //   196: getfield 36	kkkkkk/cciccc$ciiccc:bу04430443уууу04430443	Ljava/lang/String;
      //   199: astore_2
      //   200: aload_0
      //   201: aload_2
      //   202: ldc 115
      //   204: sipush 177
      //   207: bipush 37
      //   209: iconst_2
      //   210: invokestatic 99	kkkkkk/gguuuu:bк043Aккк043Aкк043A043A	(Ljava/lang/String;CCC)Ljava/lang/String;
      //   213: invokespecial 101	kkkkkk/cciccc$ciiccc:b04120412В041204120412ВВВВ	(Ljava/lang/Object;Ljava/lang/String;)V
      //   216: return
      //   217: astore_2
      //   218: aload_2
      //   219: athrow
      //   220: astore_2
      //   221: aload_2
      //   222: athrow
      // Local variable table:
      //   start	length	slot	name	signature
      //   0	223	0	this	ciiccc
      //   26	135	1	i	int
      //   22	180	2	str	String
      //   217	2	2	localException1	Exception
      //   220	2	2	localException2	Exception
      // Exception table:
      //   from	to	target	type
      //   0	23	217	java/lang/Exception
      //   80	150	217	java/lang/Exception
      //   195	200	217	java/lang/Exception
      //   67	80	220	java/lang/Exception
      //   200	216	220	java/lang/Exception
    }
    
    public static int bВВВВ04120412ВВВВ()
    {
      return 2;
    }
    
    public ciiccc b041204120412В04120412ВВВВ(@NonNull String paramString)
    {
      if ((b04430443у0443ууу04430443 + b0443у04430443ууу04430443) * b04430443у0443ууу04430443 % bу044304430443ууу04430443 != bуу04430443ууу04430443)
      {
        int i = b04430443у0443ууу04430443;
        switch (i * (b0443у04430443ууу04430443 + i) % bВВВВ04120412ВВВВ())
        {
        default: 
          b04430443у0443ууу04430443 = 73;
          bуу04430443ууу04430443 = bВ0412ВВ04120412ВВВВ();
        }
        b04430443у0443ууу04430443 = 40;
        bуу04430443ууу04430443 = 53;
      }
      this.b044304430443уууу04430443 = paramString;
      return this;
    }
    
    public ciiccc b0412В0412В04120412ВВВВ(@NonNull String paramString)
    {
      if ((b04430443у0443ууу04430443 + b0443у04430443ууу04430443) * b04430443у0443ууу04430443 % bВВВВ04120412ВВВВ() != bуу04430443ууу04430443)
      {
        b04430443у0443ууу04430443 = bВ0412ВВ04120412ВВВВ();
        bуу04430443ууу04430443 = bВ0412ВВ04120412ВВВВ();
        if ((b04430443у0443ууу04430443 + b0443у04430443ууу04430443) * b04430443у0443ууу04430443 % bу044304430443ууу04430443 != bуу04430443ууу04430443)
        {
          b04430443у0443ууу04430443 = 13;
          bуу04430443ууу04430443 = bВ0412ВВ04120412ВВВВ();
        }
      }
      try
      {
        this.b0443у0443уууу04430443 = paramString;
        return this;
      }
      catch (Exception paramString)
      {
        throw paramString;
      }
    }
    
    /* Error */
    public ciiccc b0412ВВ041204120412ВВВВ(@NonNull pdppdp paramPdppdp)
    {
      // Byte code:
      //   0: getstatic 38	kkkkkk/cciccc$ciiccc:b04430443у0443ууу04430443	I
      //   3: istore_2
      //   4: getstatic 38	kkkkkk/cciccc$ciiccc:b04430443у0443ууу04430443	I
      //   7: istore_3
      //   8: iload_3
      //   9: getstatic 40	kkkkkk/cciccc$ciiccc:b0443у04430443ууу04430443	I
      //   12: iload_3
      //   13: iadd
      //   14: imul
      //   15: invokestatic 89	kkkkkk/cciccc$ciiccc:bВВВВ04120412ВВВВ	()I
      //   18: irem
      //   19: tableswitch	default:+17->36, 0:+29->48
      //   36: invokestatic 48	kkkkkk/cciccc$ciiccc:bВ0412ВВ04120412ВВВВ	()I
      //   39: putstatic 38	kkkkkk/cciccc$ciiccc:b04430443у0443ууу04430443	I
      //   42: invokestatic 48	kkkkkk/cciccc$ciiccc:bВ0412ВВ04120412ВВВВ	()I
      //   45: putstatic 44	kkkkkk/cciccc$ciiccc:bуу04430443ууу04430443	I
      //   48: getstatic 40	kkkkkk/cciccc$ciiccc:b0443у04430443ууу04430443	I
      //   51: istore_3
      //   52: getstatic 42	kkkkkk/cciccc$ciiccc:bу044304430443ууу04430443	I
      //   55: istore 4
      //   57: iload_2
      //   58: iload_3
      //   59: iload_2
      //   60: iadd
      //   61: imul
      //   62: iload 4
      //   64: irem
      //   65: tableswitch	default:+19->84, 0:+29->94
      //   84: bipush 43
      //   86: putstatic 38	kkkkkk/cciccc$ciiccc:b04430443у0443ууу04430443	I
      //   89: bipush 51
      //   91: putstatic 44	kkkkkk/cciccc$ciiccc:bуу04430443ууу04430443	I
      //   94: aload_0
      //   95: aload_1
      //   96: putfield 79	kkkkkk/cciccc$ciiccc:b0443уу0443ууу04430443	Lkkkkkk/pdppdp;
      //   99: aload_0
      //   100: areturn
      //   101: astore_1
      //   102: aload_1
      //   103: athrow
      //   104: astore_1
      //   105: aload_1
      //   106: athrow
      //   107: astore_1
      //   108: aload_1
      //   109: athrow
      // Local variable table:
      //   start	length	slot	name	signature
      //   0	110	0	this	ciiccc
      //   0	110	1	paramPdppdp	pdppdp
      //   3	59	2	i	int
      //   7	54	3	j	int
      //   55	10	4	k	int
      // Exception table:
      //   from	to	target	type
      //   94	99	101	java/lang/Exception
      //   48	52	104	java/lang/Exception
      //   84	94	104	java/lang/Exception
      //   102	104	104	java/lang/Exception
      //   0	4	107	java/lang/Exception
      //   52	57	107	java/lang/Exception
    }
    
    /* Error */
    public cciccc b0412ВВВ04120412ВВВВ()
    {
      // Byte code:
      //   0: iconst_0
      //   1: tableswitch	default:+23->24, 0:+50->51, 1:+-1->0
      //   24: iconst_0
      //   25: tableswitch	default:+23->48, 0:+26->51, 1:+-25->0
      //   48: goto -24 -> 24
      //   51: aload_0
      //   52: invokespecial 125	kkkkkk/cciccc$ciiccc:bВВ0412041204120412ВВВВ	()V
      //   55: new 6	kkkkkk/cciccc
      //   58: dup
      //   59: aload_0
      //   60: aconst_null
      //   61: invokespecial 128	kkkkkk/cciccc:<init>	(Lkkkkkk/cciccc$ciiccc;Lkkkkkk/cciccc$1;)V
      //   64: astore 6
      //   66: getstatic 38	kkkkkk/cciccc$ciiccc:b04430443у0443ууу04430443	I
      //   69: istore_1
      //   70: getstatic 40	kkkkkk/cciccc$ciiccc:b0443у04430443ууу04430443	I
      //   73: istore_2
      //   74: getstatic 38	kkkkkk/cciccc$ciiccc:b04430443у0443ууу04430443	I
      //   77: istore_3
      //   78: getstatic 42	kkkkkk/cciccc$ciiccc:bу044304430443ууу04430443	I
      //   81: istore 4
      //   83: getstatic 44	kkkkkk/cciccc$ciiccc:bуу04430443ууу04430443	I
      //   86: istore 5
      //   88: iload_1
      //   89: iload_2
      //   90: iadd
      //   91: iload_3
      //   92: imul
      //   93: iload 4
      //   95: irem
      //   96: iload 5
      //   98: if_icmpeq +57 -> 155
      //   101: bipush 70
      //   103: putstatic 38	kkkkkk/cciccc$ciiccc:b04430443у0443ууу04430443	I
      //   106: invokestatic 48	kkkkkk/cciccc$ciiccc:bВ0412ВВ04120412ВВВВ	()I
      //   109: putstatic 44	kkkkkk/cciccc$ciiccc:bуу04430443ууу04430443	I
      //   112: getstatic 38	kkkkkk/cciccc$ciiccc:b04430443у0443ууу04430443	I
      //   115: istore_1
      //   116: iload_1
      //   117: getstatic 40	kkkkkk/cciccc$ciiccc:b0443у04430443ууу04430443	I
      //   120: iload_1
      //   121: iadd
      //   122: imul
      //   123: getstatic 42	kkkkkk/cciccc$ciiccc:bу044304430443ууу04430443	I
      //   126: irem
      //   127: tableswitch	default:+17->144, 0:+28->155
      //   144: invokestatic 48	kkkkkk/cciccc$ciiccc:bВ0412ВВ04120412ВВВВ	()I
      //   147: putstatic 38	kkkkkk/cciccc$ciiccc:b04430443у0443ууу04430443	I
      //   150: bipush 78
      //   152: putstatic 44	kkkkkk/cciccc$ciiccc:bуу04430443ууу04430443	I
      //   155: aload 6
      //   157: areturn
      //   158: astore 6
      //   160: aload 6
      //   162: athrow
      //   163: astore 6
      //   165: aload 6
      //   167: athrow
      // Local variable table:
      //   start	length	slot	name	signature
      //   0	168	0	this	ciiccc
      //   69	54	1	i	int
      //   73	18	2	j	int
      //   77	16	3	k	int
      //   81	15	4	m	int
      //   86	13	5	n	int
      //   64	92	6	localCciccc	cciccc
      //   158	3	6	localException1	Exception
      //   163	3	6	localException2	Exception
      // Exception table:
      //   from	to	target	type
      //   55	88	158	java/lang/Exception
      //   51	55	163	java/lang/Exception
      //   101	112	163	java/lang/Exception
    }
    
    public ciiccc bВ04120412В04120412ВВВВ(@NonNull String paramString)
    {
      switch (0)
      {
      case 1: 
      default: 
        for (;;)
        {
          switch (0)
          {
          }
        }
      }
      this.bу04430443уууу04430443 = paramString;
      int i = b04430443у0443ууу04430443;
      switch (i * (b04120412ВВ04120412ВВВВ() + i) % bу044304430443ууу04430443)
      {
      default: 
        b04430443у0443ууу04430443 = 49;
        bуу04430443ууу04430443 = bВ0412ВВ04120412ВВВВ();
      }
      return this;
    }
    
    public ciiccc bВ0412В041204120412ВВВВ(@NonNull String paramString)
    {
      switch (0)
      {
      case 1: 
      default: 
        for (;;)
        {
          switch (0)
          {
          }
        }
      }
      if ((b04430443у0443ууу04430443 + b0443у04430443ууу04430443) * b04430443у0443ууу04430443 % bу044304430443ууу04430443 != bуу04430443ууу04430443)
      {
        int i = b04430443у0443ууу04430443;
        switch (i * (b04120412ВВ04120412ВВВВ() + i) % bу044304430443ууу04430443)
        {
        default: 
          b04430443у0443ууу04430443 = bВ0412ВВ04120412ВВВВ();
          bуу04430443ууу04430443 = bВ0412ВВ04120412ВВВВ();
        }
        b04430443у0443ууу04430443 = bВ0412ВВ04120412ВВВВ();
        bуу04430443ууу04430443 = bВ0412ВВ04120412ВВВВ();
      }
      try
      {
        this.bу0443у0443ууу04430443 = paramString;
        return this;
      }
      catch (Exception paramString)
      {
        throw paramString;
      }
    }
    
    /* Error */
    public ciiccc bВВ0412В04120412ВВВВ(@NonNull oioooo paramOioooo)
    {
      // Byte code:
      //   0: aload_0
      //   1: aload_1
      //   2: putfield 83	kkkkkk/cciccc$ciiccc:bуу0443уууу04430443	Lkkkkkk/oioooo;
      //   5: getstatic 38	kkkkkk/cciccc$ciiccc:b04430443у0443ууу04430443	I
      //   8: istore_2
      //   9: getstatic 38	kkkkkk/cciccc$ciiccc:b04430443у0443ууу04430443	I
      //   12: istore_3
      //   13: iload_3
      //   14: getstatic 40	kkkkkk/cciccc$ciiccc:b0443у04430443ууу04430443	I
      //   17: iload_3
      //   18: iadd
      //   19: imul
      //   20: getstatic 42	kkkkkk/cciccc$ciiccc:bу044304430443ууу04430443	I
      //   23: irem
      //   24: tableswitch	default:+20->44, 0:+31->55
      //   44: invokestatic 48	kkkkkk/cciccc$ciiccc:bВ0412ВВ04120412ВВВВ	()I
      //   47: putstatic 38	kkkkkk/cciccc$ciiccc:b04430443у0443ууу04430443	I
      //   50: bipush 93
      //   52: putstatic 44	kkkkkk/cciccc$ciiccc:bуу04430443ууу04430443	I
      //   55: getstatic 40	kkkkkk/cciccc$ciiccc:b0443у04430443ууу04430443	I
      //   58: istore_3
      //   59: getstatic 42	kkkkkk/cciccc$ciiccc:bу044304430443ууу04430443	I
      //   62: istore 4
      //   64: iload_2
      //   65: iload_3
      //   66: iload_2
      //   67: iadd
      //   68: imul
      //   69: iload 4
      //   71: irem
      //   72: tableswitch	default:+20->92, 0:+32->104
      //   92: invokestatic 48	kkkkkk/cciccc$ciiccc:bВ0412ВВ04120412ВВВВ	()I
      //   95: putstatic 38	kkkkkk/cciccc$ciiccc:b04430443у0443ууу04430443	I
      //   98: invokestatic 48	kkkkkk/cciccc$ciiccc:bВ0412ВВ04120412ВВВВ	()I
      //   101: putstatic 44	kkkkkk/cciccc$ciiccc:bуу04430443ууу04430443	I
      //   104: iconst_0
      //   105: tableswitch	default:+23->128, 0:+50->155, 1:+-1->104
      //   128: iconst_0
      //   129: tableswitch	default:+23->152, 0:+26->155, 1:+-25->104
      //   152: goto -24 -> 128
      //   155: aload_0
      //   156: areturn
      //   157: astore_1
      //   158: aload_1
      //   159: athrow
      //   160: astore_1
      //   161: aload_1
      //   162: athrow
      // Local variable table:
      //   start	length	slot	name	signature
      //   0	163	0	this	ciiccc
      //   0	163	1	paramOioooo	oioooo
      //   8	61	2	i	int
      //   12	56	3	j	int
      //   62	10	4	k	int
      // Exception table:
      //   from	to	target	type
      //   0	9	157	java/lang/Exception
      //   59	64	157	java/lang/Exception
      //   55	59	160	java/lang/Exception
      //   92	104	160	java/lang/Exception
    }
    
    public ciiccc bВВВ041204120412ВВВВ(@NonNull String paramString)
    {
      if ((b04430443у0443ууу04430443 + b0443у04430443ууу04430443) * b04430443у0443ууу04430443 % bу044304430443ууу04430443 != bуу04430443ууу04430443)
      {
        b04430443у0443ууу04430443 = 68;
        bуу04430443ууу04430443 = 73;
      }
      try
      {
        this.bууу0443ууу04430443 = paramString;
        int i = bВ0412ВВ04120412ВВВВ();
        switch (i * (b0443у04430443ууу04430443 + i) % bу044304430443ууу04430443)
        {
        default: 
          switch (1)
          {
          case 0: 
          default: 
            for (;;)
            {
              switch (0)
              {
              }
            }
          }
          b04430443у0443ууу04430443 = bВ0412ВВ04120412ВВВВ();
          bуу04430443ууу04430443 = bВ0412ВВ04120412ВВВВ();
        }
        return this;
      }
      catch (Exception paramString)
      {
        throw paramString;
      }
    }
  }
}
