package kkkkkk;

import com.fasterxml.jackson.annotation.JsonProperty;

public class ccrccr
{
  public static int b041C041CМ041C041CМ041CММ = 11;
  public static int b041CМ041C041C041CМ041CММ = 1;
  public static int bМ041C041C041C041CМ041CММ = 2;
  public static int bММ041C041C041CМ041CММ;
  @JsonProperty("pty")
  private String b041CММ041C041CМ041CММ;
  @JsonProperty("i")
  private String bМ041CМ041C041CМ041CММ;
  @JsonProperty("ac")
  private String bМММ041C041CМ041CММ;
  
  public ccrccr() {}
  
  public static int b043F043Fп043Fп043Fп043Fпп()
  {
    return 2;
  }
  
  public static int b043Fпп043Fп043Fп043Fпп()
  {
    return 87;
  }
  
  public static int bп043Fп043Fп043Fп043Fпп()
  {
    return 1;
  }
  
  public void b043F043F043F043Fп043Fп043Fпп(String paramString)
  {
    if ((b043Fпп043Fп043Fп043Fпп() + b041CМ041C041C041CМ041CММ) * b043Fпп043Fп043Fп043Fпп() % bМ041C041C041C041CМ041CММ != bММ041C041C041CМ041CММ)
    {
      b041C041CМ041C041CМ041CММ = 48;
      bММ041C041C041CМ041CММ = b043Fпп043Fп043Fп043Fпп();
    }
    this.bМММ041C041CМ041CММ = paramString;
    switch (1)
    {
    case 0: 
    default: 
      for (;;)
      {
        switch (1)
        {
        }
      }
    }
  }
  
  public String b043Fп043F043Fп043Fп043Fпп()
  {
    if ((b041C041CМ041C041CМ041CММ + b041CМ041C041C041CМ041CММ) * b041C041CМ041C041CМ041CММ % bМ041C041C041C041CМ041CММ != bММ041C041C041CМ041CММ)
    {
      b041C041CМ041C041CМ041CММ = b043Fпп043Fп043Fп043Fпп();
      bММ041C041C041CМ041CММ = 47;
    }
    int i = b043Fпп043Fп043Fп043Fпп();
    int j = bп043Fп043Fп043Fп043Fпп();
    int k = b043Fпп043Fп043Fп043Fпп();
    switch (1)
    {
    case 0: 
    default: 
      for (;;)
      {
        switch (1)
        {
        }
      }
    }
    if ((i + j) * k % bМ041C041C041C041CМ041CММ != bММ041C041C041CМ041CММ)
    {
      b041C041CМ041C041CМ041CММ = 90;
      bММ041C041C041CМ041CММ = 21;
    }
    try
    {
      String str = this.b041CММ041C041CМ041CММ;
      return str;
    }
    catch (Exception localException)
    {
      throw localException;
    }
  }
  
  public void b043Fппп043F043Fп043Fпп(String paramString)
  {
    if ((b043Fпп043Fп043Fп043Fпп() + b041CМ041C041C041CМ041CММ) * b043Fпп043Fп043Fп043Fпп() % bМ041C041C041C041CМ041CММ != bММ041C041C041CМ041CММ)
    {
      b041C041CМ041C041CМ041CММ = b043Fпп043Fп043Fп043Fпп();
      bММ041C041C041CМ041CММ = b043Fпп043Fп043Fп043Fпп();
    }
    this.bМ041CМ041C041CМ041CММ = paramString;
  }
  
  /* Error */
  public String bп043F043F043Fп043Fп043Fпп()
  {
    // Byte code:
    //   0: aload_0
    //   1: getfield 55	kkkkkk/ccrccr:bМ041CМ041C041CМ041CММ	Ljava/lang/String;
    //   4: astore 4
    //   6: getstatic 42	kkkkkk/ccrccr:b041C041CМ041C041CМ041CММ	I
    //   9: istore_1
    //   10: getstatic 36	kkkkkk/ccrccr:b041CМ041C041C041CМ041CММ	I
    //   13: istore_2
    //   14: getstatic 42	kkkkkk/ccrccr:b041C041CМ041C041CМ041CММ	I
    //   17: istore_3
    //   18: iload_3
    //   19: invokestatic 50	kkkkkk/ccrccr:bп043Fп043Fп043Fп043Fпп	()I
    //   22: iload_3
    //   23: iadd
    //   24: imul
    //   25: getstatic 38	kkkkkk/ccrccr:bМ041C041C041C041CМ041CММ	I
    //   28: irem
    //   29: tableswitch	default:+19->48, 0:+31->60
    //   48: invokestatic 34	kkkkkk/ccrccr:b043Fпп043Fп043Fп043Fпп	()I
    //   51: putstatic 42	kkkkkk/ccrccr:b041C041CМ041C041CМ041CММ	I
    //   54: invokestatic 34	kkkkkk/ccrccr:b043Fпп043Fп043Fп043Fпп	()I
    //   57: putstatic 40	kkkkkk/ccrccr:bММ041C041C041CМ041CММ	I
    //   60: getstatic 38	kkkkkk/ccrccr:bМ041C041C041C041CМ041CММ	I
    //   63: istore_3
    //   64: iload_1
    //   65: iload_2
    //   66: iload_1
    //   67: iadd
    //   68: imul
    //   69: iload_3
    //   70: irem
    //   71: tableswitch	default:+17->88, 0:+28->99
    //   88: invokestatic 34	kkkkkk/ccrccr:b043Fпп043Fп043Fп043Fпп	()I
    //   91: putstatic 42	kkkkkk/ccrccr:b041C041CМ041C041CМ041CММ	I
    //   94: bipush 11
    //   96: putstatic 40	kkkkkk/ccrccr:bММ041C041C041CМ041CММ	I
    //   99: aload 4
    //   101: areturn
    //   102: astore 4
    //   104: aload 4
    //   106: athrow
    //   107: astore 4
    //   109: aload 4
    //   111: athrow
    //   112: astore 4
    //   114: aload 4
    //   116: athrow
    // Local variable table:
    //   start	length	slot	name	signature
    //   0	117	0	this	ccrccr
    //   9	60	1	i	int
    //   13	55	2	j	int
    //   17	54	3	k	int
    //   4	96	4	str	String
    //   102	3	4	localException1	Exception
    //   107	3	4	localException2	Exception
    //   112	3	4	localException3	Exception
    // Exception table:
    //   from	to	target	type
    //   0	6	102	java/lang/Exception
    //   6	14	107	java/lang/Exception
    //   60	64	107	java/lang/Exception
    //   104	107	107	java/lang/Exception
    //   88	99	112	java/lang/Exception
  }
  
  /* Error */
  public String bпп043F043Fп043Fп043Fпп()
  {
    // Byte code:
    //   0: iconst_0
    //   1: tableswitch	default:+23->24, 0:+50->51, 1:+-1->0
    //   24: iconst_0
    //   25: tableswitch	default:+23->48, 0:+26->51, 1:+-25->0
    //   48: goto -24 -> 24
    //   51: aload_0
    //   52: getfield 44	kkkkkk/ccrccr:bМММ041C041CМ041CММ	Ljava/lang/String;
    //   55: astore 6
    //   57: getstatic 42	kkkkkk/ccrccr:b041C041CМ041C041CМ041CММ	I
    //   60: istore_1
    //   61: getstatic 36	kkkkkk/ccrccr:b041CМ041C041C041CМ041CММ	I
    //   64: istore_2
    //   65: getstatic 42	kkkkkk/ccrccr:b041C041CМ041C041CМ041CММ	I
    //   68: istore_3
    //   69: invokestatic 59	kkkkkk/ccrccr:b043F043Fп043Fп043Fп043Fпп	()I
    //   72: istore 4
    //   74: getstatic 40	kkkkkk/ccrccr:bММ041C041C041CМ041CММ	I
    //   77: istore 5
    //   79: iload_1
    //   80: iload_2
    //   81: iadd
    //   82: iload_3
    //   83: imul
    //   84: iload 4
    //   86: irem
    //   87: iload 5
    //   89: if_icmpeq +57 -> 146
    //   92: invokestatic 34	kkkkkk/ccrccr:b043Fпп043Fп043Fп043Fпп	()I
    //   95: putstatic 42	kkkkkk/ccrccr:b041C041CМ041C041CМ041CММ	I
    //   98: invokestatic 34	kkkkkk/ccrccr:b043Fпп043Fп043Fп043Fпп	()I
    //   101: putstatic 40	kkkkkk/ccrccr:bММ041C041C041CМ041CММ	I
    //   104: getstatic 42	kkkkkk/ccrccr:b041C041CМ041C041CМ041CММ	I
    //   107: istore_1
    //   108: iload_1
    //   109: getstatic 36	kkkkkk/ccrccr:b041CМ041C041C041CМ041CММ	I
    //   112: iload_1
    //   113: iadd
    //   114: imul
    //   115: getstatic 38	kkkkkk/ccrccr:bМ041C041C041C041CМ041CММ	I
    //   118: irem
    //   119: tableswitch	default:+17->136, 0:+27->146
    //   136: bipush 41
    //   138: putstatic 42	kkkkkk/ccrccr:b041C041CМ041C041CМ041CММ	I
    //   141: bipush 65
    //   143: putstatic 40	kkkkkk/ccrccr:bММ041C041C041CМ041CММ	I
    //   146: aload 6
    //   148: areturn
    //   149: astore 6
    //   151: aload 6
    //   153: athrow
    //   154: astore 6
    //   156: aload 6
    //   158: athrow
    // Local variable table:
    //   start	length	slot	name	signature
    //   0	159	0	this	ccrccr
    //   60	55	1	i	int
    //   64	18	2	j	int
    //   68	16	3	k	int
    //   72	15	4	m	int
    //   77	13	5	n	int
    //   55	92	6	str	String
    //   149	3	6	localException1	Exception
    //   154	3	6	localException2	Exception
    // Exception table:
    //   from	to	target	type
    //   51	79	149	java/lang/Exception
    //   92	104	154	java/lang/Exception
  }
  
  public void bпппп043F043Fп043Fпп(String paramString)
  {
    switch (0)
    {
    case 1: 
    default: 
      for (;;)
      {
        switch (0)
        {
        }
      }
    }
    if ((b041C041CМ041C041CМ041CММ + b041CМ041C041C041CМ041CММ) * b041C041CМ041C041CМ041CММ % bМ041C041C041C041CМ041CММ != bММ041C041C041CМ041CММ)
    {
      b041C041CМ041C041CМ041CММ = 21;
      bММ041C041C041CМ041CММ = 19;
    }
    int i = b043Fпп043Fп043Fп043Fпп();
    switch (i * (b041CМ041C041C041CМ041CММ + i) % bМ041C041C041C041CМ041CММ)
    {
    default: 
      b041C041CМ041C041CМ041CММ = 79;
      bММ041C041C041CМ041CММ = b043Fпп043Fп043Fп043Fпп();
    }
    this.b041CММ041C041CМ041CММ = paramString;
  }
}
