package kkkkkk;

import android.support.annotation.Nullable;

public enum ccrrcc
{
  /* Error */
  static
  {
    // Byte code:
    //   0: new 2	kkkkkk/ccrrcc
    //   3: dup
    //   4: ldc 29
    //   6: bipush 39
    //   8: bipush 53
    //   10: iconst_1
    //   11: invokestatic 35	kkkkkk/gguuuu:bк043Aккк043Aкк043A043A	(Ljava/lang/String;CCC)Ljava/lang/String;
    //   14: iconst_0
    //   15: invokespecial 39	kkkkkk/ccrrcc:<init>	(Ljava/lang/String;I)V
    //   18: putstatic 41	kkkkkk/ccrrcc:UNKNOWN	Lkkkkkk/ccrrcc;
    //   21: new 2	kkkkkk/ccrrcc
    //   24: dup
    //   25: ldc 43
    //   27: bipush 109
    //   29: iconst_5
    //   30: invokestatic 47	kkkkkk/gguuuu:bккккк043Aкк043A043A	(Ljava/lang/String;CC)Ljava/lang/String;
    //   33: iconst_1
    //   34: invokespecial 39	kkkkkk/ccrrcc:<init>	(Ljava/lang/String;I)V
    //   37: astore 5
    //   39: aload 5
    //   41: putstatic 49	kkkkkk/ccrrcc:CURRENT_ACCOUNT	Lkkkkkk/ccrrcc;
    //   44: new 2	kkkkkk/ccrrcc
    //   47: dup
    //   48: ldc 51
    //   50: bipush 47
    //   52: iconst_1
    //   53: invokestatic 47	kkkkkk/gguuuu:bккккк043Aкк043A043A	(Ljava/lang/String;CC)Ljava/lang/String;
    //   56: iconst_2
    //   57: invokespecial 39	kkkkkk/ccrrcc:<init>	(Ljava/lang/String;I)V
    //   60: putstatic 53	kkkkkk/ccrrcc:CREDITCARD_ACCOUNT	Lkkkkkk/ccrrcc;
    //   63: new 2	kkkkkk/ccrrcc
    //   66: dup
    //   67: ldc 55
    //   69: bipush 23
    //   71: iconst_3
    //   72: invokestatic 47	kkkkkk/gguuuu:bккккк043Aкк043A043A	(Ljava/lang/String;CC)Ljava/lang/String;
    //   75: iconst_3
    //   76: invokespecial 39	kkkkkk/ccrrcc:<init>	(Ljava/lang/String;I)V
    //   79: putstatic 57	kkkkkk/ccrrcc:SAVINGS_ACCOUNT	Lkkkkkk/ccrrcc;
    //   82: new 2	kkkkkk/ccrrcc
    //   85: dup
    //   86: ldc 59
    //   88: bipush 127
    //   90: bipush 86
    //   92: iconst_0
    //   93: invokestatic 35	kkkkkk/gguuuu:bк043Aккк043Aкк043A043A	(Ljava/lang/String;CCC)Ljava/lang/String;
    //   96: iconst_4
    //   97: invokespecial 39	kkkkkk/ccrrcc:<init>	(Ljava/lang/String;I)V
    //   100: astore 5
    //   102: aload 5
    //   104: putstatic 61	kkkkkk/ccrrcc:ISA_ACCOUNT	Lkkkkkk/ccrrcc;
    //   107: new 2	kkkkkk/ccrrcc
    //   110: dup
    //   111: ldc 63
    //   113: bipush 121
    //   115: iconst_0
    //   116: invokestatic 47	kkkkkk/gguuuu:bккккк043Aкк043A043A	(Ljava/lang/String;CC)Ljava/lang/String;
    //   119: iconst_5
    //   120: invokespecial 39	kkkkkk/ccrrcc:<init>	(Ljava/lang/String;I)V
    //   123: astore 5
    //   125: aload 5
    //   127: putstatic 65	kkkkkk/ccrrcc:NON_CBS_PERSONAL_LOAN_ACCOUNT	Lkkkkkk/ccrrcc;
    //   130: new 2	kkkkkk/ccrrcc
    //   133: dup
    //   134: ldc 67
    //   136: sipush 198
    //   139: sipush 185
    //   142: iconst_2
    //   143: invokestatic 35	kkkkkk/gguuuu:bк043Aккк043Aкк043A043A	(Ljava/lang/String;CCC)Ljava/lang/String;
    //   146: bipush 6
    //   148: invokespecial 39	kkkkkk/ccrrcc:<init>	(Ljava/lang/String;I)V
    //   151: astore 5
    //   153: aload 5
    //   155: putstatic 69	kkkkkk/ccrrcc:MORTGAGE_ACCOUNT	Lkkkkkk/ccrrcc;
    //   158: new 2	kkkkkk/ccrrcc
    //   161: dup
    //   162: ldc 71
    //   164: bipush 124
    //   166: iconst_4
    //   167: invokestatic 47	kkkkkk/gguuuu:bккккк043Aкк043A043A	(Ljava/lang/String;CC)Ljava/lang/String;
    //   170: bipush 7
    //   172: invokespecial 39	kkkkkk/ccrrcc:<init>	(Ljava/lang/String;I)V
    //   175: putstatic 73	kkkkkk/ccrrcc:CBS_PERSONAL_LOAN_ACCOUNT	Lkkkkkk/ccrrcc;
    //   178: new 2	kkkkkk/ccrrcc
    //   181: dup
    //   182: ldc 75
    //   184: bipush 105
    //   186: iconst_3
    //   187: invokestatic 47	kkkkkk/gguuuu:bккккк043Aкк043A043A	(Ljava/lang/String;CC)Ljava/lang/String;
    //   190: bipush 8
    //   192: invokespecial 39	kkkkkk/ccrrcc:<init>	(Ljava/lang/String;I)V
    //   195: astore 5
    //   197: aload 5
    //   199: putstatic 77	kkkkkk/ccrrcc:TERM_DEPOSIT_ACCOUNT	Lkkkkkk/ccrrcc;
    //   202: new 2	kkkkkk/ccrrcc
    //   205: dup
    //   206: ldc 79
    //   208: sipush 202
    //   211: sipush 197
    //   214: iconst_3
    //   215: invokestatic 35	kkkkkk/gguuuu:bк043Aккк043Aкк043A043A	(Ljava/lang/String;CCC)Ljava/lang/String;
    //   218: bipush 9
    //   220: invokespecial 39	kkkkkk/ccrrcc:<init>	(Ljava/lang/String;I)V
    //   223: putstatic 81	kkkkkk/ccrrcc:HTBISA_ACCOUNT	Lkkkkkk/ccrrcc;
    //   226: new 2	kkkkkk/ccrrcc
    //   229: dup
    //   230: ldc 83
    //   232: bipush 100
    //   234: iconst_5
    //   235: invokestatic 47	kkkkkk/gguuuu:bккккк043Aкк043A043A	(Ljava/lang/String;CC)Ljava/lang/String;
    //   238: bipush 10
    //   240: invokespecial 39	kkkkkk/ccrrcc:<init>	(Ljava/lang/String;I)V
    //   243: putstatic 85	kkkkkk/ccrrcc:MORTGAGE_UFSS_ACCOUNT	Lkkkkkk/ccrrcc;
    //   246: new 2	kkkkkk/ccrrcc
    //   249: dup
    //   250: ldc 87
    //   252: sipush 195
    //   255: iconst_0
    //   256: invokestatic 47	kkkkkk/gguuuu:bккккк043Aкк043A043A	(Ljava/lang/String;CC)Ljava/lang/String;
    //   259: bipush 11
    //   261: invokespecial 39	kkkkkk/ccrrcc:<init>	(Ljava/lang/String;I)V
    //   264: putstatic 89	kkkkkk/ccrrcc:INVESTMENT_ACCOUNT	Lkkkkkk/ccrrcc;
    //   267: new 2	kkkkkk/ccrrcc
    //   270: dup
    //   271: ldc 91
    //   273: iconst_5
    //   274: bipush 12
    //   276: iconst_0
    //   277: invokestatic 35	kkkkkk/gguuuu:bк043Aккк043Aкк043A043A	(Ljava/lang/String;CCC)Ljava/lang/String;
    //   280: bipush 12
    //   282: invokespecial 39	kkkkkk/ccrrcc:<init>	(Ljava/lang/String;I)V
    //   285: putstatic 93	kkkkkk/ccrrcc:HOME_INSURANCE	Lkkkkkk/ccrrcc;
    //   288: new 2	kkkkkk/ccrrcc
    //   291: dup
    //   292: ldc 95
    //   294: sipush 170
    //   297: iconst_5
    //   298: invokestatic 47	kkkkkk/gguuuu:bккккк043Aкк043A043A	(Ljava/lang/String;CC)Ljava/lang/String;
    //   301: bipush 13
    //   303: invokespecial 39	kkkkkk/ccrrcc:<init>	(Ljava/lang/String;I)V
    //   306: astore 5
    //   308: invokestatic 99	kkkkkk/ccrrcc:b043Fппп043Fппппп	()I
    //   311: istore_0
    //   312: invokestatic 102	kkkkkk/ccrrcc:bп043Fпп043Fппппп	()I
    //   315: istore_1
    //   316: invokestatic 99	kkkkkk/ccrrcc:b043Fппп043Fппппп	()I
    //   319: istore_2
    //   320: invokestatic 105	kkkkkk/ccrrcc:b043F043Fпп043Fппппп	()I
    //   323: istore_3
    //   324: invokestatic 108	kkkkkk/ccrrcc:bпп043Fп043Fппппп	()I
    //   327: istore 4
    //   329: iload_0
    //   330: iload_1
    //   331: iadd
    //   332: iload_2
    //   333: imul
    //   334: iload_3
    //   335: irem
    //   336: iload 4
    //   338: if_icmpeq +38 -> 376
    //   341: invokestatic 99	kkkkkk/ccrrcc:b043Fппп043Fппппп	()I
    //   344: istore_0
    //   345: iload_0
    //   346: invokestatic 102	kkkkkk/ccrrcc:bп043Fпп043Fппппп	()I
    //   349: iload_0
    //   350: iadd
    //   351: imul
    //   352: invokestatic 105	kkkkkk/ccrrcc:b043F043Fпп043Fппппп	()I
    //   355: irem
    //   356: tableswitch	default:+20->376, 0:+20->376
    //   376: aload 5
    //   378: putstatic 110	kkkkkk/ccrrcc:TREASURY_FTD	Lkkkkkk/ccrrcc;
    //   381: new 2	kkkkkk/ccrrcc
    //   384: dup
    //   385: ldc 112
    //   387: sipush 233
    //   390: iconst_5
    //   391: invokestatic 47	kkkkkk/gguuuu:bккккк043Aкк043A043A	(Ljava/lang/String;CC)Ljava/lang/String;
    //   394: bipush 14
    //   396: invokespecial 39	kkkkkk/ccrrcc:<init>	(Ljava/lang/String;I)V
    //   399: putstatic 114	kkkkkk/ccrrcc:TREASURY_32DCN	Lkkkkkk/ccrrcc;
    //   402: getstatic 41	kkkkkk/ccrrcc:UNKNOWN	Lkkkkkk/ccrrcc;
    //   405: astore 5
    //   407: getstatic 49	kkkkkk/ccrrcc:CURRENT_ACCOUNT	Lkkkkkk/ccrrcc;
    //   410: astore 6
    //   412: getstatic 53	kkkkkk/ccrrcc:CREDITCARD_ACCOUNT	Lkkkkkk/ccrrcc;
    //   415: astore 7
    //   417: getstatic 57	kkkkkk/ccrrcc:SAVINGS_ACCOUNT	Lkkkkkk/ccrrcc;
    //   420: astore 8
    //   422: getstatic 61	kkkkkk/ccrrcc:ISA_ACCOUNT	Lkkkkkk/ccrrcc;
    //   425: astore 9
    //   427: getstatic 65	kkkkkk/ccrrcc:NON_CBS_PERSONAL_LOAN_ACCOUNT	Lkkkkkk/ccrrcc;
    //   430: astore 10
    //   432: getstatic 69	kkkkkk/ccrrcc:MORTGAGE_ACCOUNT	Lkkkkkk/ccrrcc;
    //   435: astore 11
    //   437: getstatic 73	kkkkkk/ccrrcc:CBS_PERSONAL_LOAN_ACCOUNT	Lkkkkkk/ccrrcc;
    //   440: astore 12
    //   442: bipush 15
    //   444: anewarray 2	kkkkkk/ccrrcc
    //   447: dup
    //   448: iconst_0
    //   449: aload 5
    //   451: aastore
    //   452: dup
    //   453: iconst_1
    //   454: aload 6
    //   456: aastore
    //   457: dup
    //   458: iconst_2
    //   459: aload 7
    //   461: aastore
    //   462: dup
    //   463: iconst_3
    //   464: aload 8
    //   466: aastore
    //   467: dup
    //   468: iconst_4
    //   469: aload 9
    //   471: aastore
    //   472: dup
    //   473: iconst_5
    //   474: aload 10
    //   476: aastore
    //   477: dup
    //   478: bipush 6
    //   480: aload 11
    //   482: aastore
    //   483: dup
    //   484: bipush 7
    //   486: aload 12
    //   488: aastore
    //   489: dup
    //   490: bipush 8
    //   492: getstatic 77	kkkkkk/ccrrcc:TERM_DEPOSIT_ACCOUNT	Lkkkkkk/ccrrcc;
    //   495: aastore
    //   496: dup
    //   497: bipush 9
    //   499: getstatic 81	kkkkkk/ccrrcc:HTBISA_ACCOUNT	Lkkkkkk/ccrrcc;
    //   502: aastore
    //   503: dup
    //   504: bipush 10
    //   506: getstatic 85	kkkkkk/ccrrcc:MORTGAGE_UFSS_ACCOUNT	Lkkkkkk/ccrrcc;
    //   509: aastore
    //   510: dup
    //   511: bipush 11
    //   513: getstatic 89	kkkkkk/ccrrcc:INVESTMENT_ACCOUNT	Lkkkkkk/ccrrcc;
    //   516: aastore
    //   517: dup
    //   518: bipush 12
    //   520: getstatic 93	kkkkkk/ccrrcc:HOME_INSURANCE	Lkkkkkk/ccrrcc;
    //   523: aastore
    //   524: dup
    //   525: bipush 13
    //   527: getstatic 110	kkkkkk/ccrrcc:TREASURY_FTD	Lkkkkkk/ccrrcc;
    //   530: aastore
    //   531: dup
    //   532: bipush 14
    //   534: getstatic 114	kkkkkk/ccrrcc:TREASURY_32DCN	Lkkkkkk/ccrrcc;
    //   537: aastore
    //   538: putstatic 116	kkkkkk/ccrrcc:$VALUES	[Lkkkkkk/ccrrcc;
    //   541: return
    //   542: astore 5
    //   544: aload 5
    //   546: athrow
    //   547: astore 5
    //   549: aload 5
    //   551: athrow
    // Local variable table:
    //   start	length	slot	name	signature
    //   311	41	0	i	int
    //   315	17	1	j	int
    //   319	15	2	k	int
    //   323	13	3	m	int
    //   327	12	4	n	int
    //   37	413	5	localCcrrcc1	ccrrcc
    //   542	3	5	localException1	Exception
    //   547	3	5	localException2	Exception
    //   410	45	6	localCcrrcc2	ccrrcc
    //   415	45	7	localCcrrcc3	ccrrcc
    //   420	45	8	localCcrrcc4	ccrrcc
    //   425	45	9	localCcrrcc5	ccrrcc
    //   430	45	10	localCcrrcc6	ccrrcc
    //   435	46	11	localCcrrcc7	ccrrcc
    //   440	47	12	localCcrrcc8	ccrrcc
    // Exception table:
    //   from	to	target	type
    //   0	39	542	java/lang/Exception
    //   44	63	542	java/lang/Exception
    //   82	102	542	java/lang/Exception
    //   125	130	542	java/lang/Exception
    //   153	178	542	java/lang/Exception
    //   197	329	542	java/lang/Exception
    //   376	422	542	java/lang/Exception
    //   432	442	542	java/lang/Exception
    //   39	44	547	java/lang/Exception
    //   63	82	547	java/lang/Exception
    //   102	125	547	java/lang/Exception
    //   130	153	547	java/lang/Exception
    //   178	197	547	java/lang/Exception
    //   422	432	547	java/lang/Exception
    //   442	541	547	java/lang/Exception
  }
  
  private ccrrcc() {}
  
  public static int b043F043Fпп043Fппппп()
  {
    return 2;
  }
  
  public static ccrrcc b043Fп043Fп043Fппппп(@Nullable pkkkkk paramPkkkkk)
  {
    if (paramPkkkkk == null) {}
    try
    {
      paramPkkkkk = UNKNOWN;
      return paramPkkkkk;
    }
    catch (Exception paramPkkkkk)
    {
      try
      {
        do
        {
          localObject = bппп043F043Fппппп(paramPkkkkk.name());
          if ((b043Fппп043Fппппп() + bп043Fпп043Fппппп()) * b043Fппп043Fппппп() % b043F043Fпп043Fппппп() != bпп043Fп043Fппппп()) {}
          paramPkkkkk = (pkkkkk)localObject;
          switch (1)
          {
          }
          for (;;)
          {
            paramPkkkkk = (pkkkkk)localObject;
            switch (0)
            {
            }
          }
          if (paramPkkkkk == pkkkkk.SAVINGS_ACCOUNT) {
            break;
          }
          localObject = pkkkkk.SAVINGS_ACOUNT;
        } while (paramPkkkkk != localObject);
        Object localObject = SAVINGS_ACCOUNT;
        int i = b043Fппп043Fппппп();
        int j = bп043Fпп043Fппппп();
        int k = b043F043Fпп043Fппппп();
        paramPkkkkk = (pkkkkk)localObject;
        switch (i * (j + i) % k)
        {
        }
        return localObject;
      }
      catch (Exception paramPkkkkk)
      {
        throw paramPkkkkk;
      }
      paramPkkkkk = paramPkkkkk;
      throw paramPkkkkk;
    }
  }
  
  public static int b043Fппп043Fппппп()
  {
    return 66;
  }
  
  public static int bп043Fпп043Fппппп()
  {
    return 1;
  }
  
  public static int bпп043Fп043Fппппп()
  {
    return 0;
  }
  
  public static ccrrcc bппп043F043Fппппп(String paramString)
  {
    int i = b043Fппп043Fппппп();
    switch (i * (bп043Fпп043Fппппп() + i) % b043F043Fпп043Fппппп())
    {
    }
    paramString = (ccrrcc)Enum.valueOf(ccrrcc.class, paramString);
    i = b043Fппп043Fппппп();
    switch (i * (bп043Fпп043Fппппп() + i) % b043F043Fпп043Fппппп())
    {
    }
    switch (0)
    {
    case 1: 
    default: 
      for (;;)
      {
        switch (1)
        {
        }
      }
    }
    return paramString;
  }
  
  public boolean b043F043F043Fп043Fппппп()
  {
    int i = b043Fппп043Fппппп();
    switch (i * (bп043Fпп043Fппппп() + i) % b043F043Fпп043Fппппп())
    {
    }
    boolean bool;
    if (this == INVESTMENT_ACCOUNT) {
      bool = true;
    }
    do
    {
      return bool;
      bool = false;
    } while ((b043Fппп043Fппппп() + bп043Fпп043Fппппп()) * b043Fппп043Fппппп() % b043F043Fпп043Fппппп() == bпп043Fп043Fппппп());
    return false;
  }
  
  public boolean bп043F043Fп043Fппппп()
  {
    boolean bool = false;
    if ((this == ISA_ACCOUNT) || (this == HTBISA_ACCOUNT))
    {
      switch (0)
      {
      case 1: 
      default: 
        for (;;)
        {
          i = b043Fппп043Fппппп();
          switch (i * (bп043Fпп043Fппппп() + i) % b043F043Fпп043Fппппп())
          {
          }
          switch (1)
          {
          }
        }
      }
      int i = b043Fппп043Fппппп();
      switch (i * (bп043Fпп043Fппппп() + i) % b043F043Fпп043Fппппп())
      {
      }
      switch (0)
      {
      case 1: 
      default: 
        for (;;)
        {
          switch (0)
          {
          }
        }
      }
      bool = true;
    }
    return bool;
  }
}
