package kkkkkk;

import android.support.annotation.NonNull;
import java.io.Serializable;
import java.util.Arrays;
import shaded.org.apache.commons.lang3.builder.HashCodeBuilder;

public class daaada
  implements Serializable
{
  private String b043204320432ввв0432вв0432;
  private boolean b04320432вввв0432вв0432;
  private String b0432в0432ввв0432вв0432;
  private String bв04320432ввв0432вв0432;
  @NonNull
  private final int[] bвв0432ввв0432вв0432;
  
  public daaada(@NonNull int[] paramArrayOfInt)
  {
    this.bвв0432ввв0432вв0432 = Arrays.copyOf(paramArrayOfInt, paramArrayOfInt.length);
  }
  
  public static int b04350435е04350435еееее()
  {
    return 11;
  }
  
  public static int b0435е043504350435еееее()
  {
    return 0;
  }
  
  private String bе0435043504350435еееее(int paramInt)
  {
    Object localObject = new StringBuilder();
    switch (1)
    {
    case 0: 
    default: 
      for (;;)
      {
        switch (0)
        {
        }
      }
    }
    localObject = ((StringBuilder)localObject).append(paramInt).append(ppdppd.bааа04300430ааа0430а(paramInt));
    paramInt = b04350435е04350435еееее();
    switch (paramInt * (bее043504350435еееее() + paramInt) % bе0435е04350435еееее())
    {
    }
    localObject = ((StringBuilder)localObject).toString();
    paramInt = b04350435е04350435еееее();
    switch (paramInt * (bее043504350435еееее() + paramInt) % bе0435е04350435еееее())
    {
    }
    return localObject;
  }
  
  public static int bе0435е04350435еееее()
  {
    return 2;
  }
  
  public static int bее043504350435еееее()
  {
    return 1;
  }
  
  /* Error */
  public String[] b04350435043504350435еееее()
  {
    // Byte code:
    //   0: invokestatic 52	kkkkkk/daaada:b04350435е04350435еееее	()I
    //   3: invokestatic 55	kkkkkk/daaada:bее043504350435еееее	()I
    //   6: iadd
    //   7: invokestatic 52	kkkkkk/daaada:b04350435е04350435еееее	()I
    //   10: imul
    //   11: invokestatic 58	kkkkkk/daaada:bе0435е04350435еееее	()I
    //   14: irem
    //   15: invokestatic 68	kkkkkk/daaada:b0435е043504350435еееее	()I
    //   18: if_icmpeq +3 -> 21
    //   21: aload_0
    //   22: getfield 28	kkkkkk/daaada:bвв0432ввв0432вв0432	[I
    //   25: astore_2
    //   26: aload_0
    //   27: aload_2
    //   28: iconst_0
    //   29: iaload
    //   30: invokespecial 70	kkkkkk/daaada:bе0435043504350435еееее	(I)Ljava/lang/String;
    //   33: astore_2
    //   34: invokestatic 52	kkkkkk/daaada:b04350435е04350435еееее	()I
    //   37: istore_1
    //   38: iload_1
    //   39: invokestatic 55	kkkkkk/daaada:bее043504350435еееее	()I
    //   42: iload_1
    //   43: iadd
    //   44: imul
    //   45: invokestatic 58	kkkkkk/daaada:bе0435е04350435еееее	()I
    //   48: irem
    //   49: tableswitch	default:+19->68, 0:+19->68
    //   68: iconst_3
    //   69: anewarray 72	java/lang/String
    //   72: dup
    //   73: iconst_0
    //   74: aload_2
    //   75: aastore
    //   76: dup
    //   77: iconst_1
    //   78: aload_0
    //   79: aload_0
    //   80: getfield 28	kkkkkk/daaada:bвв0432ввв0432вв0432	[I
    //   83: iconst_1
    //   84: iaload
    //   85: invokespecial 70	kkkkkk/daaada:bе0435043504350435еееее	(I)Ljava/lang/String;
    //   88: aastore
    //   89: dup
    //   90: iconst_2
    //   91: aload_0
    //   92: aload_0
    //   93: getfield 28	kkkkkk/daaada:bвв0432ввв0432вв0432	[I
    //   96: iconst_2
    //   97: iaload
    //   98: invokespecial 70	kkkkkk/daaada:bе0435043504350435еееее	(I)Ljava/lang/String;
    //   101: aastore
    //   102: invokestatic 78	kkkkkk/pppppd:b043004300430ааааа0430а	([Ljava/lang/Object;)[Ljava/lang/Object;
    //   105: astore_2
    //   106: iconst_1
    //   107: tableswitch	default:+21->128, 0:+-1->106, 1:+48->155
    //   128: iconst_1
    //   129: tableswitch	default:+23->152, 0:+-23->106, 1:+26->155
    //   152: goto -24 -> 128
    //   155: aload_2
    //   156: checkcast 80	[Ljava/lang/String;
    //   159: astore_2
    //   160: aload_2
    //   161: areturn
    //   162: astore_2
    //   163: aload_2
    //   164: athrow
    //   165: astore_2
    //   166: aload_2
    //   167: athrow
    // Local variable table:
    //   start	length	slot	name	signature
    //   0	168	0	this	daaada
    //   37	8	1	i	int
    //   25	136	2	localObject	Object
    //   162	2	2	localException1	Exception
    //   165	2	2	localException2	Exception
    // Exception table:
    //   from	to	target	type
    //   0	21	162	java/lang/Exception
    //   26	34	162	java/lang/Exception
    //   68	106	162	java/lang/Exception
    //   21	26	165	java/lang/Exception
    //   155	160	165	java/lang/Exception
  }
  
  public void b043504350435ее0435ееее(String paramString)
  {
    int i = b04350435е04350435еееее();
    int j = bее043504350435еееее();
    int k = b04350435е04350435еееее();
    switch (k * (bее043504350435еееее() + k) % bе0435е04350435еееее())
    {
    }
    switch (i * (j + i) % bе0435е04350435еееее())
    {
    }
    try
    {
      this.bв04320432ввв0432вв0432 = paramString;
      return;
    }
    catch (Exception paramString)
    {
      throw paramString;
    }
  }
  
  public String b04350435еее0435ееее()
  {
    String str = this.b043204320432ввв0432вв0432;
    switch (0)
    {
    case 1: 
    default: 
      for (;;)
      {
        switch (0)
        {
        }
      }
    }
    if ((b04350435е04350435еееее() + bее043504350435еееее()) * b04350435е04350435еееее() % bе0435е04350435еееее() != b0435е043504350435еееее())
    {
      int i = b04350435е04350435еееее();
      switch (i * (bее043504350435еееее() + i) % bе0435е04350435еееее())
      {
      }
    }
    return str;
  }
  
  public void b0435е0435ее0435ееее(Boolean paramBoolean)
  {
    try
    {
      this.b04320432вввв0432вв0432 = paramBoolean.booleanValue();
      if ((b04350435е04350435еееее() + bее043504350435еееее()) * b04350435е04350435еееее() % bе0435е04350435еееее() != b0435е043504350435еееее()) {}
      return;
    }
    catch (Exception paramBoolean)
    {
      throw paramBoolean;
    }
  }
  
  /* Error */
  public String b0435ееее0435ееее()
  {
    // Byte code:
    //   0: aload_0
    //   1: getfield 100	kkkkkk/daaada:b0432в0432ввв0432вв0432	Ljava/lang/String;
    //   4: astore 4
    //   6: invokestatic 52	kkkkkk/daaada:b04350435е04350435еееее	()I
    //   9: istore_1
    //   10: invokestatic 52	kkkkkk/daaada:b04350435е04350435еееее	()I
    //   13: invokestatic 55	kkkkkk/daaada:bее043504350435еееее	()I
    //   16: iadd
    //   17: invokestatic 52	kkkkkk/daaada:b04350435е04350435еееее	()I
    //   20: imul
    //   21: invokestatic 58	kkkkkk/daaada:bе0435е04350435еееее	()I
    //   24: irem
    //   25: invokestatic 68	kkkkkk/daaada:b0435е043504350435еееее	()I
    //   28: if_icmpeq +3 -> 31
    //   31: invokestatic 55	kkkkkk/daaada:bее043504350435еееее	()I
    //   34: istore_2
    //   35: invokestatic 58	kkkkkk/daaada:bе0435е04350435еееее	()I
    //   38: istore_3
    //   39: iload_1
    //   40: iload_2
    //   41: iload_1
    //   42: iadd
    //   43: imul
    //   44: iload_3
    //   45: irem
    //   46: tableswitch	default:+18->64, 0:+18->64
    //   64: aload 4
    //   66: areturn
    //   67: astore 4
    //   69: aload 4
    //   71: athrow
    //   72: astore 4
    //   74: aload 4
    //   76: athrow
    // Local variable table:
    //   start	length	slot	name	signature
    //   0	77	0	this	daaada
    //   9	35	1	i	int
    //   34	9	2	j	int
    //   38	8	3	k	int
    //   4	61	4	str	String
    //   67	3	4	localException1	Exception
    //   72	3	4	localException2	Exception
    // Exception table:
    //   from	to	target	type
    //   0	6	67	java/lang/Exception
    //   31	39	67	java/lang/Exception
    //   6	10	72	java/lang/Exception
  }
  
  public void bе04350435ее0435ееее(String paramString)
  {
    switch (0)
    {
    case 1: 
    default: 
      for (;;)
      {
        switch (0)
        {
        }
      }
    }
    try
    {
      int i = b04350435е04350435еееее();
      int j = bее043504350435еееее();
      int k = b04350435е04350435еееее();
      int m = bе0435е04350435еееее();
      int n = b0435е043504350435еееее();
      if (((i + j) * k % m != n) && ((b04350435е04350435еееее() + bее043504350435еееее()) * b04350435е04350435еееее() % bе0435е04350435еееее() != b0435е043504350435еееее())) {}
      this.b0432в0432ввв0432вв0432 = paramString;
      return;
    }
    catch (Exception paramString)
    {
      throw paramString;
    }
  }
  
  /* Error */
  public String bе0435еее0435ееее()
  {
    // Byte code:
    //   0: invokestatic 52	kkkkkk/daaada:b04350435е04350435еееее	()I
    //   3: invokestatic 55	kkkkkk/daaada:bее043504350435еееее	()I
    //   6: iadd
    //   7: invokestatic 52	kkkkkk/daaada:b04350435е04350435еееее	()I
    //   10: imul
    //   11: invokestatic 58	kkkkkk/daaada:bе0435е04350435еееее	()I
    //   14: irem
    //   15: invokestatic 68	kkkkkk/daaada:b0435е043504350435еееее	()I
    //   18: if_icmpeq +3 -> 21
    //   21: aload_0
    //   22: getfield 84	kkkkkk/daaada:bв04320432ввв0432вв0432	Ljava/lang/String;
    //   25: astore 6
    //   27: invokestatic 52	kkkkkk/daaada:b04350435е04350435еееее	()I
    //   30: istore_1
    //   31: invokestatic 55	kkkkkk/daaada:bее043504350435еееее	()I
    //   34: istore_2
    //   35: invokestatic 52	kkkkkk/daaada:b04350435е04350435еееее	()I
    //   38: istore_3
    //   39: invokestatic 58	kkkkkk/daaada:bе0435е04350435еееее	()I
    //   42: istore 4
    //   44: invokestatic 68	kkkkkk/daaada:b0435е043504350435еееее	()I
    //   47: istore 5
    //   49: iload_1
    //   50: iload_2
    //   51: iadd
    //   52: iload_3
    //   53: imul
    //   54: iload 4
    //   56: irem
    //   57: iload 5
    //   59: if_icmpeq +3 -> 62
    //   62: aload 6
    //   64: areturn
    //   65: astore 6
    //   67: aload 6
    //   69: athrow
    //   70: astore 6
    //   72: aload 6
    //   74: athrow
    // Local variable table:
    //   start	length	slot	name	signature
    //   0	75	0	this	daaada
    //   30	22	1	i	int
    //   34	18	2	j	int
    //   38	16	3	k	int
    //   42	15	4	m	int
    //   47	13	5	n	int
    //   25	38	6	str	String
    //   65	3	6	localException1	Exception
    //   70	3	6	localException2	Exception
    // Exception table:
    //   from	to	target	type
    //   35	49	65	java/lang/Exception
    //   21	35	70	java/lang/Exception
  }
  
  public String[] bее0435ее0435ееее()
  {
    try
    {
      String str1 = this.b0432в0432ввв0432вв0432;
      for (;;)
      {
        try
        {
          String str2 = this.b043204320432ввв0432вв0432;
          String str3 = this.bв04320432ввв0432вв0432;
          if ((b04350435е04350435еееее() + bее043504350435еееее()) * b04350435е04350435еееее() % bе0435е04350435еееее() != b0435е043504350435еееее()) {}
          int i = b04350435е04350435еееее();
          switch (i * (bее043504350435еееее() + i) % bе0435е04350435еееее())
          {
          case 0: 
            return new String[] { str1, str2, str3 };
          }
        }
        catch (Exception localException1)
        {
          throw localException1;
        }
      }
    }
    catch (Exception localException2)
    {
      throw localException2;
    }
  }
  
  public void bеее0435е0435ееее(String paramString)
  {
    int i = b04350435е04350435еееее();
    int j = bее043504350435еееее();
    int k = bе0435е04350435еееее();
    switch (0)
    {
    case 1: 
    default: 
      for (;;)
      {
        switch (1)
        {
        }
      }
    }
    switch (i * (j + i) % k)
    {
    default: 
      if ((b04350435е04350435еееее() + bее043504350435еееее()) * b04350435е04350435еееее() % bе0435е04350435еееее() == b0435е043504350435еееее()) {
        break;
      }
    }
    try
    {
      this.b043204320432ввв0432вв0432 = paramString;
      return;
    }
    catch (Exception paramString)
    {
      throw paramString;
    }
  }
  
  public Boolean bеееее0435ееее()
  {
    switch (1)
    {
    case 0: 
    default: 
      for (;;)
      {
        switch (1)
        {
        }
      }
    }
    for (;;)
    {
      try
      {
        int i = b04350435е04350435еееее();
        switch (i * (bее043504350435еееее() + i) % bе0435е04350435еееее())
        {
        case 0: 
          boolean bool = this.b04320432вввв0432вв0432;
          i = b04350435е04350435еееее();
          switch (i * (bее043504350435еееее() + i) % bе0435е04350435еееее())
          {
          }
          return Boolean.valueOf(bool);
        }
      }
      catch (Exception localException)
      {
        throw localException;
      }
    }
  }
  
  /* Error */
  public boolean equals(Object paramObject)
  {
    // Byte code:
    //   0: iconst_0
    //   1: istore 6
    //   3: aload_0
    //   4: aload_1
    //   5: if_acmpne +9 -> 14
    //   8: iconst_1
    //   9: istore 5
    //   11: iload 5
    //   13: ireturn
    //   14: iload 6
    //   16: istore 5
    //   18: aload_1
    //   19: ifnull -8 -> 11
    //   22: iload 6
    //   24: istore 5
    //   26: aload_0
    //   27: invokevirtual 116	java/lang/Object:getClass	()Ljava/lang/Class;
    //   30: aload_1
    //   31: invokevirtual 116	java/lang/Object:getClass	()Ljava/lang/Class;
    //   34: if_acmpne -23 -> 11
    //   37: goto +160 -> 197
    //   40: aload_1
    //   41: checkcast 2	kkkkkk/daaada
    //   44: astore_1
    //   45: new 118	shaded/org/apache/commons/lang3/builder/EqualsBuilder
    //   48: dup
    //   49: invokespecial 119	shaded/org/apache/commons/lang3/builder/EqualsBuilder:<init>	()V
    //   52: astore 7
    //   54: aload_0
    //   55: invokevirtual 121	kkkkkk/daaada:b04350435043504350435еееее	()[Ljava/lang/String;
    //   58: astore 8
    //   60: aload_1
    //   61: invokevirtual 121	kkkkkk/daaada:b04350435043504350435еееее	()[Ljava/lang/String;
    //   64: astore 9
    //   66: invokestatic 52	kkkkkk/daaada:b04350435е04350435еееее	()I
    //   69: invokestatic 55	kkkkkk/daaada:bее043504350435еееее	()I
    //   72: iadd
    //   73: invokestatic 52	kkkkkk/daaada:b04350435е04350435еееее	()I
    //   76: imul
    //   77: invokestatic 58	kkkkkk/daaada:bе0435е04350435еееее	()I
    //   80: irem
    //   81: invokestatic 68	kkkkkk/daaada:b0435е043504350435еееее	()I
    //   84: if_icmpeq +3 -> 87
    //   87: aload 7
    //   89: aload 8
    //   91: aload 9
    //   93: invokevirtual 124	shaded/org/apache/commons/lang3/builder/EqualsBuilder:append	([Ljava/lang/Object;[Ljava/lang/Object;)Lshaded/org/apache/commons/lang3/builder/EqualsBuilder;
    //   96: astore 7
    //   98: aload_0
    //   99: getfield 100	kkkkkk/daaada:b0432в0432ввв0432вв0432	Ljava/lang/String;
    //   102: astore 8
    //   104: aload 7
    //   106: aload 8
    //   108: aload_1
    //   109: getfield 100	kkkkkk/daaada:b0432в0432ввв0432вв0432	Ljava/lang/String;
    //   112: invokevirtual 127	shaded/org/apache/commons/lang3/builder/EqualsBuilder:append	(Ljava/lang/Object;Ljava/lang/Object;)Lshaded/org/apache/commons/lang3/builder/EqualsBuilder;
    //   115: aload_0
    //   116: getfield 87	kkkkkk/daaada:b043204320432ввв0432вв0432	Ljava/lang/String;
    //   119: aload_1
    //   120: getfield 87	kkkkkk/daaada:b043204320432ввв0432вв0432	Ljava/lang/String;
    //   123: invokevirtual 127	shaded/org/apache/commons/lang3/builder/EqualsBuilder:append	(Ljava/lang/Object;Ljava/lang/Object;)Lshaded/org/apache/commons/lang3/builder/EqualsBuilder;
    //   126: astore 7
    //   128: aload 7
    //   130: aload_0
    //   131: getfield 84	kkkkkk/daaada:bв04320432ввв0432вв0432	Ljava/lang/String;
    //   134: aload_1
    //   135: getfield 84	kkkkkk/daaada:bв04320432ввв0432вв0432	Ljava/lang/String;
    //   138: invokevirtual 127	shaded/org/apache/commons/lang3/builder/EqualsBuilder:append	(Ljava/lang/Object;Ljava/lang/Object;)Lshaded/org/apache/commons/lang3/builder/EqualsBuilder;
    //   141: invokevirtual 130	shaded/org/apache/commons/lang3/builder/EqualsBuilder:isEquals	()Z
    //   144: istore 6
    //   146: invokestatic 52	kkkkkk/daaada:b04350435е04350435еееее	()I
    //   149: istore_2
    //   150: invokestatic 55	kkkkkk/daaada:bее043504350435еееее	()I
    //   153: istore_3
    //   154: invokestatic 58	kkkkkk/daaada:bе0435е04350435еееее	()I
    //   157: istore 4
    //   159: iload 6
    //   161: istore 5
    //   163: iload_2
    //   164: iload_3
    //   165: iload_2
    //   166: iadd
    //   167: imul
    //   168: iload 4
    //   170: irem
    //   171: tableswitch	default:+17->188, 0:+-160->11
    //   188: iload 6
    //   190: ireturn
    //   191: astore_1
    //   192: aload_1
    //   193: athrow
    //   194: astore_1
    //   195: aload_1
    //   196: athrow
    //   197: iconst_0
    //   198: tableswitch	default:+22->220, 0:+-158->40, 1:+-1->197
    //   220: iconst_0
    //   221: tableswitch	default:+23->244, 0:+-181->40, 1:+-24->197
    //   244: goto -24 -> 220
    // Local variable table:
    //   start	length	slot	name	signature
    //   0	247	0	this	daaada
    //   0	247	1	paramObject	Object
    //   149	19	2	i	int
    //   153	14	3	j	int
    //   157	14	4	k	int
    //   9	153	5	bool1	boolean
    //   1	188	6	bool2	boolean
    //   52	77	7	localEqualsBuilder	shaded.org.apache.commons.lang3.builder.EqualsBuilder
    //   58	49	8	localObject	Object
    //   64	28	9	arrayOfString	String[]
    // Exception table:
    //   from	to	target	type
    //   26	37	191	java/lang/Exception
    //   40	66	191	java/lang/Exception
    //   104	128	191	java/lang/Exception
    //   150	159	191	java/lang/Exception
    //   87	104	194	java/lang/Exception
    //   128	150	194	java/lang/Exception
  }
  
  public int hashCode()
  {
    HashCodeBuilder localHashCodeBuilder = new HashCodeBuilder(17, 37).append(b04350435043504350435еееее());
    if ((b04350435е04350435еееее() + bее043504350435еееее()) * b04350435е04350435еееее() % bе0435е04350435еееее() != b0435е043504350435еееее()) {}
    localHashCodeBuilder = localHashCodeBuilder.append(this.b0432в0432ввв0432вв0432).append(this.b043204320432ввв0432вв0432);
    int i = b04350435е04350435еееее();
    switch (i * (bее043504350435еееее() + i) % bе0435е04350435еееее())
    {
    }
    return localHashCodeBuilder.append(this.bв04320432ввв0432вв0432).toHashCode();
  }
}
