package kkkkkk;

import android.content.BroadcastReceiver;
import android.content.Context;
import android.content.Intent;
import android.support.v4.content.LocalBroadcastManager;
import java.util.ArrayList;
import java.util.List;

public class dddxdx
{
  private static final String b042A042AЪ042AЪ042AЪЪЪ;
  public static int b042A042AЪЪ042A042AЪЪЪ = 2;
  public static int b042AЪЪЪ042A042AЪЪЪ = 0;
  public static int bЪ042AЪЪ042A042AЪЪЪ = 1;
  public static int bЪЪЪЪ042A042AЪЪЪ = 41;
  private boolean b042A042A042A042AЪ042AЪЪЪ;
  private LPBroadcastReceiver b042AЪ042A042AЪ042AЪЪЪ;
  private xxdxdx bЪ042A042A042AЪ042AЪЪЪ;
  private List<String> bЪЪ042A042AЪ042AЪЪЪ;
  
  static
  {
    for (;;)
    {
      try
      {
        i = bЪЪЪЪ042A042AЪЪЪ;
        j = bЪ042AЪЪ042A042AЪЪЪ;
        k = bЪЪЪЪ042A042AЪЪЪ;
        m = b0445хх0445044504450445044504450445();
      }
      catch (Exception localException1)
      {
        int i;
        int j;
        int k;
        int m;
        int n;
        String str;
        throw localException1;
      }
      try
      {
        n = b042AЪЪЪ042A042AЪЪЪ;
        if ((i + j) * k % m != n)
        {
          i = bЪЪЪЪ042A042AЪЪЪ;
          switch (i * (bЪ042AЪЪ042A042AЪЪЪ + i) % b0445хх0445044504450445044504450445())
          {
          default: 
            bЪЪЪЪ042A042AЪЪЪ = b044504450445х044504450445044504450445();
            b042AЪЪЪ042A042AЪЪЪ = b044504450445х044504450445044504450445();
          }
          bЪЪЪЪ042A042AЪЪЪ = 42;
          b042AЪЪЪ042A042AЪЪЪ = b044504450445х044504450445044504450445();
        }
        str = dddxdx.class.getSimpleName();
      }
      catch (Exception localException2)
      {
        throw localException2;
      }
    }
    b042A042AЪ042AЪ042AЪЪЪ = str;
    return;
    switch (1)
    {
    }
    for (;;)
    {
      switch (1)
      {
      }
    }
  }
  
  private dddxdx(dxdxdx paramDxdxdx, xxdxdx paramXxdxdx)
  {
    this.b042A042A042A042AЪ042AЪЪЪ = dxdxdx.b04450445х0445х04450445044504450445(paramDxdxdx);
    this.bЪЪ042A042AЪ042AЪЪЪ = dxdxdx.bхх04450445х04450445044504450445(paramDxdxdx);
    this.bЪ042A042A042AЪ042AЪЪЪ = paramXxdxdx;
    this.b042AЪ042A042AЪ042AЪЪЪ = new LPBroadcastReceiver();
    b04450445х0445044504450445044504450445();
  }
  
  public static int b044504450445х044504450445044504450445()
  {
    return 23;
  }
  
  public static int b0445хх0445044504450445044504450445()
  {
    return 2;
  }
  
  public static int bх0445х0445044504450445044504450445()
  {
    return 0;
  }
  
  public static int bххх0445044504450445044504450445()
  {
    return 1;
  }
  
  public void b04450445х0445044504450445044504450445()
  {
    i = 5;
    for (;;)
    {
      try
      {
        int j = i / 0;
        i = j;
        continue;
      }
      catch (Exception localException1)
      {
        bЪЪЪЪ042A042AЪЪЪ = b044504450445х044504450445044504450445();
        try
        {
          i /= 0;
          continue;
          switch (1)
          {
          }
        }
        catch (Exception localException2)
        {
          bЪЪЪЪ042A042AЪЪЪ = b044504450445х044504450445044504450445();
        }
        continue;
      }
      switch (0)
      {
      }
    }
    this.b042AЪ042A042AЪ042AЪЪЪ.register();
  }
  
  public void bхх04450445044504450445044504450445()
  {
    if ((bЪЪЪЪ042A042AЪЪЪ + bххх0445044504450445044504450445()) * bЪЪЪЪ042A042AЪЪЪ % b0445хх0445044504450445044504450445() != b042AЪЪЪ042A042AЪЪЪ)
    {
      bЪЪЪЪ042A042AЪЪЪ = b044504450445х044504450445044504450445();
      b042AЪЪЪ042A042AЪЪЪ = 94;
    }
    try
    {
      this.b042AЪ042A042AЪ042AЪЪЪ.unregister();
      int i = bЪЪЪЪ042A042AЪЪЪ;
      switch (i * (bЪ042AЪЪ042A042AЪЪЪ + i) % b042A042AЪЪ042A042AЪЪЪ)
      {
      default: 
        bЪЪЪЪ042A042AЪЪЪ = b044504450445х044504450445044504450445();
        b042AЪЪЪ042A042AЪЪЪ = b044504450445х044504450445044504450445();
      }
      switch (1)
      {
      case 0: 
      default: 
        for (;;)
        {
          switch (1)
          {
          }
        }
      }
      return;
    }
    catch (Exception localException)
    {
      throw localException;
    }
  }
  
  private class LPBroadcastReceiver
    extends BroadcastReceiver
  {
    public static int b042A042A042AЪЪЪ = 2;
    public static int b042AЪ042AЪЪЪ = 0;
    public static int bЪ042A042AЪЪЪ = 1;
    public static int bЪЪ042AЪЪЪ = 5;
    private LocalBroadcastManager broadcastManager = LocalBroadcastManager.getInstance(xxdxxd.instance.bххх044504450445х044504450445());
    
    public LPBroadcastReceiver() {}
    
    public static int b042AЪЪ042AЪЪ()
    {
      return 2;
    }
    
    public static int bЪЪЪ042AЪЪ()
    {
      return 79;
    }
    
    /* Error */
    public void onReceive(Context paramContext, Intent paramIntent)
    {
      // Byte code:
      //   0: getstatic 55	kkkkkk/dddxdx$LPBroadcastReceiver:bЪЪ042AЪЪЪ	I
      //   3: getstatic 57	kkkkkk/dddxdx$LPBroadcastReceiver:bЪ042A042AЪЪЪ	I
      //   6: iadd
      //   7: getstatic 55	kkkkkk/dddxdx$LPBroadcastReceiver:bЪЪ042AЪЪЪ	I
      //   10: imul
      //   11: getstatic 59	kkkkkk/dddxdx$LPBroadcastReceiver:b042A042A042AЪЪЪ	I
      //   14: irem
      //   15: getstatic 61	kkkkkk/dddxdx$LPBroadcastReceiver:b042AЪ042AЪЪЪ	I
      //   18: if_icmpeq +15 -> 33
      //   21: invokestatic 63	kkkkkk/dddxdx$LPBroadcastReceiver:bЪЪЪ042AЪЪ	()I
      //   24: putstatic 55	kkkkkk/dddxdx$LPBroadcastReceiver:bЪЪ042AЪЪЪ	I
      //   27: invokestatic 63	kkkkkk/dddxdx$LPBroadcastReceiver:bЪЪЪ042AЪЪ	()I
      //   30: putstatic 61	kkkkkk/dddxdx$LPBroadcastReceiver:b042AЪ042AЪЪЪ	I
      //   33: aload_1
      //   34: invokestatic 69	kkkkkk/nkkkkk:bЗЗ0417З0417З0417041704170417	(Landroid/content/Context;)V
      //   37: aload_1
      //   38: invokestatic 74	kkkkkk/nnnkkk:bхх0445ххххххх	(Landroid/content/Context;)V
      //   41: aload_1
      //   42: invokestatic 79	kkkkkk/nknnkk:bх0445ххх04450445ххх	(Landroid/content/Context;)V
      //   45: aload_0
      //   46: getfield 24	kkkkkk/dddxdx$LPBroadcastReceiver:this$0	Lkkkkkk/dddxdx;
      //   49: invokestatic 83	kkkkkk/dddxdx:b0445х0445х044504450445044504450445	(Lkkkkkk/dddxdx;)Lkkkkkk/dddxdx$xxdxdx;
      //   52: astore_3
      //   53: getstatic 55	kkkkkk/dddxdx$LPBroadcastReceiver:bЪЪ042AЪЪЪ	I
      //   56: getstatic 57	kkkkkk/dddxdx$LPBroadcastReceiver:bЪ042A042AЪЪЪ	I
      //   59: iadd
      //   60: getstatic 55	kkkkkk/dddxdx$LPBroadcastReceiver:bЪЪ042AЪЪЪ	I
      //   63: imul
      //   64: invokestatic 85	kkkkkk/dddxdx$LPBroadcastReceiver:b042AЪЪ042AЪЪ	()I
      //   67: irem
      //   68: getstatic 61	kkkkkk/dddxdx$LPBroadcastReceiver:b042AЪ042AЪЪЪ	I
      //   71: if_icmpeq +15 -> 86
      //   74: invokestatic 63	kkkkkk/dddxdx$LPBroadcastReceiver:bЪЪЪ042AЪЪ	()I
      //   77: putstatic 55	kkkkkk/dddxdx$LPBroadcastReceiver:bЪЪ042AЪЪЪ	I
      //   80: invokestatic 63	kkkkkk/dddxdx$LPBroadcastReceiver:bЪЪЪ042AЪЪ	()I
      //   83: putstatic 61	kkkkkk/dddxdx$LPBroadcastReceiver:b042AЪ042AЪЪЪ	I
      //   86: iconst_1
      //   87: tableswitch	default:+21->108, 0:+-34->53, 1:+48->135
      //   108: iconst_1
      //   109: tableswitch	default:+23->132, 0:+-56->53, 1:+26->135
      //   132: goto -24 -> 108
      //   135: aload_3
      //   136: aload_1
      //   137: aload_2
      //   138: invokeinterface 90 3 0
      //   143: aload_0
      //   144: getfield 24	kkkkkk/dddxdx$LPBroadcastReceiver:this$0	Lkkkkkk/dddxdx;
      //   147: invokestatic 94	kkkkkk/dddxdx:bх04450445х044504450445044504450445	(Lkkkkkk/dddxdx;)Z
      //   150: ifeq +7 -> 157
      //   153: aload_0
      //   154: invokevirtual 97	kkkkkk/dddxdx$LPBroadcastReceiver:unregister	()V
      //   157: return
      //   158: astore_1
      //   159: aload_1
      //   160: athrow
      //   161: astore_1
      //   162: aload_1
      //   163: athrow
      // Local variable table:
      //   start	length	slot	name	signature
      //   0	164	0	this	LPBroadcastReceiver
      //   0	164	1	paramContext	Context
      //   0	164	2	paramIntent	Intent
      //   52	84	3	localXxdxdx	dddxdx.xxdxdx
      // Exception table:
      //   from	to	target	type
      //   0	33	158	java/lang/Exception
      //   45	53	158	java/lang/Exception
      //   33	45	161	java/lang/Exception
      //   135	157	161	java/lang/Exception
    }
    
    public void register()
    {
      throw new Runtime("d2j fail translate: java.lang.IndexOutOfBoundsException: fromIndex < 0: -1\n\tat java.util.BitSet.nextSetBit(BitSet.java:712)\n\tat com.googlecode.dex2jar.ir.ts.array.FillArrayTransformer.makeSureAllElementAreAssigned(FillArrayTransformer.java:505)\n\tat com.googlecode.dex2jar.ir.ts.array.FillArrayTransformer.transformReportChanged(FillArrayTransformer.java:123)\n\tat com.googlecode.dex2jar.ir.ts.StatedTransformer.transform(StatedTransformer.java:10)\n\tat com.googlecode.d2j.dex.Dex2jar$2.optimize(Dex2jar.java:149)\n\tat com.googlecode.d2j.dex.Dex2Asm.convertCode(Dex2Asm.java:414)\n\tat com.googlecode.d2j.dex.ExDex2Asm.convertCode(ExDex2Asm.java:42)\n\tat com.googlecode.d2j.dex.Dex2jar$2.convertCode(Dex2jar.java:128)\n\tat com.googlecode.d2j.dex.Dex2Asm.convertMethod(Dex2Asm.java:509)\n\tat com.googlecode.d2j.dex.Dex2Asm.convertClass(Dex2Asm.java:406)\n\tat com.googlecode.d2j.dex.Dex2Asm.convertDex(Dex2Asm.java:422)\n\tat com.googlecode.d2j.dex.Dex2jar.doTranslate(Dex2jar.java:172)\n\tat com.googlecode.d2j.dex.Dex2jar.to(Dex2jar.java:272)\n\tat com.googlecode.dex2jar.tools.Dex2jarCmd.doCommandLine(Dex2jarCmd.java:108)\n\tat com.googlecode.dex2jar.tools.BaseCmd.doMain(BaseCmd.java:288)\n\tat com.googlecode.dex2jar.tools.Dex2jarCmd.main(Dex2jarCmd.java:32)\n");
    }
    
    /* Error */
    public void unregister()
    {
      // Byte code:
      //   0: aload_0
      //   1: getfield 45	kkkkkk/dddxdx$LPBroadcastReceiver:broadcastManager	Landroid/support/v4/content/LocalBroadcastManager;
      //   4: astore 4
      //   6: goto +113 -> 119
      //   9: getstatic 55	kkkkkk/dddxdx$LPBroadcastReceiver:bЪЪ042AЪЪЪ	I
      //   12: istore_1
      //   13: getstatic 57	kkkkkk/dddxdx$LPBroadcastReceiver:bЪ042A042AЪЪЪ	I
      //   16: istore_2
      //   17: getstatic 59	kkkkkk/dddxdx$LPBroadcastReceiver:b042A042A042AЪЪЪ	I
      //   20: istore_3
      //   21: iload_1
      //   22: iload_2
      //   23: iload_1
      //   24: iadd
      //   25: imul
      //   26: iload_3
      //   27: irem
      //   28: tableswitch	default:+20->48, 0:+74->102
      //   48: bipush 94
      //   50: putstatic 55	kkkkkk/dddxdx$LPBroadcastReceiver:bЪЪ042AЪЪЪ	I
      //   53: bipush 60
      //   55: putstatic 61	kkkkkk/dddxdx$LPBroadcastReceiver:b042AЪ042AЪЪЪ	I
      //   58: getstatic 55	kkkkkk/dddxdx$LPBroadcastReceiver:bЪЪ042AЪЪЪ	I
      //   61: istore_1
      //   62: iload_1
      //   63: getstatic 57	kkkkkk/dddxdx$LPBroadcastReceiver:bЪ042A042AЪЪЪ	I
      //   66: iload_1
      //   67: iadd
      //   68: imul
      //   69: getstatic 59	kkkkkk/dddxdx$LPBroadcastReceiver:b042A042A042AЪЪЪ	I
      //   72: irem
      //   73: tableswitch	default:+19->92, 0:+29->102
      //   92: bipush 57
      //   94: putstatic 55	kkkkkk/dddxdx$LPBroadcastReceiver:bЪЪ042AЪЪЪ	I
      //   97: bipush 10
      //   99: putstatic 61	kkkkkk/dddxdx$LPBroadcastReceiver:b042AЪ042AЪЪЪ	I
      //   102: aload 4
      //   104: aload_0
      //   105: invokevirtual 111	android/support/v4/content/LocalBroadcastManager:unregisterReceiver	(Landroid/content/BroadcastReceiver;)V
      //   108: return
      //   109: astore 4
      //   111: aload 4
      //   113: athrow
      //   114: astore 4
      //   116: aload 4
      //   118: athrow
      //   119: iconst_0
      //   120: tableswitch	default:+24->144, 0:+-111->9, 1:+-1->119
      //   144: iconst_0
      //   145: tableswitch	default:+23->168, 0:+-136->9, 1:+-26->119
      //   168: goto -24 -> 144
      // Local variable table:
      //   start	length	slot	name	signature
      //   0	171	0	this	LPBroadcastReceiver
      //   12	57	1	i	int
      //   16	9	2	j	int
      //   20	8	3	k	int
      //   4	99	4	localLocalBroadcastManager	LocalBroadcastManager
      //   109	3	4	localException1	Exception
      //   114	3	4	localException2	Exception
      // Exception table:
      //   from	to	target	type
      //   0	6	109	java/lang/Exception
      //   9	17	109	java/lang/Exception
      //   48	53	109	java/lang/Exception
      //   17	21	114	java/lang/Exception
      //   53	58	114	java/lang/Exception
      //   102	108	114	java/lang/Exception
    }
  }
  
  public static class dxdxdx
  {
    public static int b042A042A042AЪ042A042AЪЪЪ = 0;
    public static int b042AЪЪ042A042A042AЪЪЪ = 2;
    public static int bЪ042A042AЪ042A042AЪЪЪ = 27;
    public static int bЪЪЪ042A042A042AЪЪЪ = 1;
    private boolean b042AЪ042AЪ042A042AЪЪЪ;
    private List<String> bЪЪ042AЪ042A042AЪЪЪ = new ArrayList();
    
    public dxdxdx() {}
    
    public static int b0445044504450445х04450445044504450445()
    {
      return 2;
    }
    
    public static int b0445ххх044504450445044504450445()
    {
      return 16;
    }
    
    public static int bх044504450445х04450445044504450445()
    {
      return 1;
    }
    
    /* Error */
    public dxdxdx b0445х04450445х04450445044504450445(String paramString)
    {
      // Byte code:
      //   0: invokestatic 57	kkkkkk/dddxdx$dxdxdx:b0445ххх044504450445044504450445	()I
      //   3: istore_2
      //   4: iload_2
      //   5: getstatic 43	kkkkkk/dddxdx$dxdxdx:bЪЪЪ042A042A042AЪЪЪ	I
      //   8: iload_2
      //   9: iadd
      //   10: imul
      //   11: getstatic 45	kkkkkk/dddxdx$dxdxdx:b042AЪЪ042A042A042AЪЪЪ	I
      //   14: irem
      //   15: tableswitch	default:+17->32, 0:+29->44
      //   32: invokestatic 57	kkkkkk/dddxdx$dxdxdx:b0445ххх044504450445044504450445	()I
      //   35: putstatic 41	kkkkkk/dddxdx$dxdxdx:bЪ042A042AЪ042A042AЪЪЪ	I
      //   38: invokestatic 57	kkkkkk/dddxdx$dxdxdx:b0445ххх044504450445044504450445	()I
      //   41: putstatic 49	kkkkkk/dddxdx$dxdxdx:b042A042A042AЪ042A042AЪЪЪ	I
      //   44: aload_0
      //   45: getfield 30	kkkkkk/dddxdx$dxdxdx:bЪЪ042AЪ042A042AЪЪЪ	Ljava/util/List;
      //   48: astore 6
      //   50: aload 6
      //   52: aload_1
      //   53: invokeinterface 63 2 0
      //   58: pop
      //   59: invokestatic 57	kkkkkk/dddxdx$dxdxdx:b0445ххх044504450445044504450445	()I
      //   62: istore_2
      //   63: getstatic 43	kkkkkk/dddxdx$dxdxdx:bЪЪЪ042A042A042AЪЪЪ	I
      //   66: istore_3
      //   67: invokestatic 57	kkkkkk/dddxdx$dxdxdx:b0445ххх044504450445044504450445	()I
      //   70: istore 4
      //   72: getstatic 45	kkkkkk/dddxdx$dxdxdx:b042AЪЪ042A042A042AЪЪЪ	I
      //   75: istore 5
      //   77: iload_2
      //   78: iload_3
      //   79: iadd
      //   80: iload 4
      //   82: imul
      //   83: iload 5
      //   85: irem
      //   86: getstatic 49	kkkkkk/dddxdx$dxdxdx:b042A042A042AЪ042A042AЪЪЪ	I
      //   89: if_icmpeq +14 -> 103
      //   92: invokestatic 57	kkkkkk/dddxdx$dxdxdx:b0445ххх044504450445044504450445	()I
      //   95: putstatic 41	kkkkkk/dddxdx$dxdxdx:bЪ042A042AЪ042A042AЪЪЪ	I
      //   98: bipush 67
      //   100: putstatic 49	kkkkkk/dddxdx$dxdxdx:b042A042A042AЪ042A042AЪЪЪ	I
      //   103: aload_0
      //   104: areturn
      //   105: astore_1
      //   106: aload_1
      //   107: athrow
      //   108: astore_1
      //   109: aload_1
      //   110: athrow
      //   111: astore_1
      //   112: aload_1
      //   113: athrow
      //   114: astore_1
      //   115: aload_1
      //   116: athrow
      // Local variable table:
      //   start	length	slot	name	signature
      //   0	117	0	this	dxdxdx
      //   0	117	1	paramString	String
      //   3	77	2	i	int
      //   66	14	3	j	int
      //   70	13	4	k	int
      //   75	11	5	m	int
      //   48	3	6	localList	List
      // Exception table:
      //   from	to	target	type
      //   50	59	105	java/lang/Exception
      //   59	67	108	java/lang/Exception
      //   77	98	108	java/lang/Exception
      //   106	108	108	java/lang/Exception
      //   44	50	111	java/lang/Exception
      //   67	77	114	java/lang/Exception
      //   98	103	114	java/lang/Exception
      //   112	114	114	java/lang/Exception
    }
    
    public dxdxdx bх0445хх044504450445044504450445()
    {
      int i = 5;
      this.b042AЪ042AЪ042A042AЪЪЪ = true;
      try
      {
        for (;;)
        {
          int j = i / 0;
          int k = bЪ042A042AЪ042A042AЪЪЪ;
          i = j;
          switch (k * (bЪЪЪ042A042A042AЪЪЪ + k) % b042AЪЪ042A042A042AЪЪЪ)
          {
          }
          bЪ042A042AЪ042A042AЪЪЪ = 38;
          b042A042A042AЪ042A042AЪЪЪ = 28;
          i = j;
        }
        return this;
      }
      catch (Exception localException)
      {
        bЪ042A042AЪ042A042AЪЪЪ = b0445ххх044504450445044504450445();
      }
    }
    
    public dddxdx bхххх044504450445044504450445(dddxdx.xxdxdx paramXxdxdx)
    {
      return new dddxdx(this, paramXxdxdx, null);
    }
  }
  
  public static abstract interface xxdxdx
  {
    public abstract void b04450445хх044504450445044504450445(Context paramContext, Intent paramIntent);
  }
}
