package kkkkkk;

import android.content.Context;
import java.util.HashMap;
import java.util.List;
import java.util.Map;
import java.util.concurrent.TimeUnit;
import java.util.concurrent.atomic.AtomicLong;
import java.util.concurrent.locks.ReentrantLock;
import javax.annotation.Nonnull;
import javax.annotation.Nullable;

public abstract class ddvddv
{
  public static int b04220422Т042204220422ТТТТ = 0;
  private static final String b04220422ТТТ0422ТТТТ;
  public static int b0422Т0422042204220422ТТТТ = 2;
  public static int bТ0422Т042204220422ТТТТ = 37;
  public static int bТТ0422042204220422ТТТТ = 1;
  public static final String bТТ0422ТТ0422ТТТТ = gguuuu.bк043Aккк043Aкк043A043A(bТТ0422ТТ0422ТТТТ, 'T', '', '\001');
  private volatile int b0422042204220422Т0422ТТТТ = 0;
  public final AtomicLong b042204220422Т04220422ТТТТ = new AtomicLong(0L);
  public volatile int b042204220422ТТ0422ТТТТ = 10000;
  @Nullable
  private volatile String b04220422Т0422Т0422ТТТТ = null;
  public final vdddvd.ddvdvd b04220422ТТ04220422ТТТТ = new vdddvd.ddvdvd();
  @Nullable
  public faafaf.aaffaf b0422Т04220422Т0422ТТТТ = null;
  private volatile boolean b0422Т0422Т04220422ТТТТ = false;
  public volatile boolean b0422Т0422ТТ0422ТТТТ = true;
  public volatile boolean b0422ТТ042204220422ТТТТ = false;
  public final ddddvv b0422ТТ0422Т0422ТТТТ = new ddddvv();
  @Nullable
  private final ddvddv.dddvdv b0422ТТТ04220422ТТТТ;
  private volatile long bТ042204220422Т0422ТТТТ = 0L;
  private final ReentrantLock bТ04220422Т04220422ТТТТ = new ReentrantLock();
  @Nonnull
  public vdvvvd bТ04220422ТТ0422ТТТТ = new vdvvvd();
  @Nullable
  private volatile affaaa bТ0422Т0422Т0422ТТТТ = null;
  @Nullable
  private final ddvddv.vvvddv bТ0422ТТ04220422ТТТТ;
  @Nullable
  private final dvvvdv bТТ04220422Т0422ТТТТ;
  @Nullable
  public vdddvd bТТ0422Т04220422ТТТТ = null;
  @Nullable
  public volatile vvvdvd bТТТ042204220422ТТТТ = null;
  @Nullable
  private volatile Thread bТТТ0422Т0422ТТТТ = null;
  @Nullable
  public ffffaa bТТТТ04220422ТТТТ = null;
  
  static
  {
    String str = fafffa.b043A043A043A043Aкк043Aкк043A(ddvddv.class);
    switch (1)
    {
    case 0: 
    default: 
      for (;;)
      {
        switch (0)
        {
        }
      }
    }
    b04220422ТТТ0422ТТТТ = str;
  }
  
  public ddvddv(@Nullable vvddvv paramVvddvv, @Nullable vddvvv paramVddvvv, @Nullable dvvvvv paramDvvvvv)
  {
    this.bТ0422ТТ04220422ТТТТ = paramVvddvv;
    this.bТТ04220422Т0422ТТТТ = paramVddvvv;
    this.b0422ТТТ04220422ТТТТ = paramDvvvvv;
  }
  
  public static int b043A043A043A043A043Aк043Aк043Aк()
  {
    return 2;
  }
  
  public static int b043Aк043A043A043Aк043Aк043Aк()
  {
    return 59;
  }
  
  public static int bк043A043A043A043Aк043Aк043Aк()
  {
    return 1;
  }
  
  public static long bк043Aккк043A043Aк043Aк(long paramLong1, long paramLong2, String paramString)
  {
    if ((paramLong1 < 0L) || ((paramLong2 != 0L) && (paramLong1 > paramLong2)))
    {
      fafffa.bкк043Aк043Aк043Aкк043A(b04220422ТТТ0422ТТТТ, gguuuu.bккккк043Aкк043A043A("DhoYc_Y\024iS]eT\016S[]\nde\023\006`a", '\005', '\005'), new String[] { paramString, String.valueOf(paramLong1) });
      paramString = new IllegalArgumentException(gguuuu.bк043Aккк043Aкк043A043A("w\034#\r\027\023\rG\035\007\021\031\bA\007\017\021=\030", 'à', 'î', '\002') + paramString + gguuuu.bккккк043Aкк043A043A("&", '§', '\000'));
      if ((bТ0422Т042204220422ТТТТ + bк043A043A043A043Aк043Aк043Aк()) * bТ0422Т042204220422ТТТТ % b0422Т0422042204220422ТТТТ != b04220422Т042204220422ТТТТ)
      {
        if ((bТ0422Т042204220422ТТТТ + bТТ0422042204220422ТТТТ) * bТ0422Т042204220422ТТТТ % b0422Т0422042204220422ТТТТ != bкк043A043A043Aк043Aк043Aк())
        {
          bТ0422Т042204220422ТТТТ = 30;
          b04220422Т042204220422ТТТТ = 22;
        }
        bТ0422Т042204220422ТТТТ = 77;
        b04220422Т042204220422ТТТТ = b043Aк043A043A043Aк043Aк043Aк();
      }
      throw paramString;
    }
    return paramLong1;
  }
  
  public static int bкк043A043A043Aк043Aк043Aк()
  {
    return 0;
  }
  
  /* Error */
  @Nullable
  private affaaa bкк043A043Aк043A043Aк043Aк()
  {
    // Byte code:
    //   0: invokestatic 250	kkkkkk/dvdddv:bк043A043A043Aк043Aкк043Aк	()Lkkkkkk/dvdddv;
    //   3: getfield 253	kkkkkk/dvdddv:b0422ТТТ0422ТТТТТ	Z
    //   6: ifeq +311 -> 317
    //   9: new 255	kkkkkk/affaaa
    //   12: dup
    //   13: invokespecial 256	kkkkkk/affaaa:<init>	()V
    //   16: astore_2
    //   17: invokestatic 250	kkkkkk/dvdddv:bк043A043A043Aк043Aкк043Aк	()Lkkkkkk/dvdddv;
    //   20: ldc_w 258
    //   23: bipush 27
    //   25: bipush 29
    //   27: iconst_0
    //   28: invokestatic 84	kkkkkk/gguuuu:bк043Aккк043Aкк043A043A	(Ljava/lang/String;CCC)Ljava/lang/String;
    //   31: invokevirtual 262	kkkkkk/dvdddv:bккк043A043A043Aкк043Aк	(Ljava/lang/String;)Ljava/lang/String;
    //   34: astore_3
    //   35: aload_3
    //   36: ifnull +11 -> 47
    //   39: aload_2
    //   40: aload_3
    //   41: invokestatic 268	java/lang/Long:parseLong	(Ljava/lang/String;)J
    //   44: putfield 271	kkkkkk/affaaa:bТ0422ТТТТТТ0422Т	J
    //   47: invokestatic 250	kkkkkk/dvdddv:bк043A043A043Aк043Aкк043Aк	()Lkkkkkk/dvdddv;
    //   50: astore_3
    //   51: getstatic 167	kkkkkk/ddvddv:bТ0422Т042204220422ТТТТ	I
    //   54: getstatic 169	kkkkkk/ddvddv:bТТ0422042204220422ТТТТ	I
    //   57: iadd
    //   58: getstatic 167	kkkkkk/ddvddv:bТ0422Т042204220422ТТТТ	I
    //   61: imul
    //   62: invokestatic 201	kkkkkk/ddvddv:b043A043A043A043A043Aк043Aк043Aк	()I
    //   65: irem
    //   66: getstatic 176	kkkkkk/ddvddv:b04220422Т042204220422ТТТТ	I
    //   69: if_icmpeq +13 -> 82
    //   72: bipush 73
    //   74: putstatic 167	kkkkkk/ddvddv:bТ0422Т042204220422ТТТТ	I
    //   77: bipush 68
    //   79: putstatic 176	kkkkkk/ddvddv:b04220422Т042204220422ТТТТ	I
    //   82: aload_3
    //   83: ldc_w 273
    //   86: bipush 126
    //   88: bipush 44
    //   90: iconst_1
    //   91: invokestatic 84	kkkkkk/gguuuu:bк043Aккк043Aкк043A043A	(Ljava/lang/String;CCC)Ljava/lang/String;
    //   94: invokevirtual 262	kkkkkk/dvdddv:bккк043A043A043Aкк043Aк	(Ljava/lang/String;)Ljava/lang/String;
    //   97: astore_3
    //   98: aload_3
    //   99: ifnull +11 -> 110
    //   102: aload_2
    //   103: aload_3
    //   104: invokestatic 268	java/lang/Long:parseLong	(Ljava/lang/String;)J
    //   107: putfield 276	kkkkkk/affaaa:b0422ТТТТТТТ0422Т	J
    //   110: invokestatic 250	kkkkkk/dvdddv:bк043A043A043Aк043Aкк043Aк	()Lkkkkkk/dvdddv;
    //   113: ldc_w 278
    //   116: bipush 32
    //   118: bipush 107
    //   120: iconst_2
    //   121: invokestatic 84	kkkkkk/gguuuu:bк043Aккк043Aкк043A043A	(Ljava/lang/String;CCC)Ljava/lang/String;
    //   124: invokevirtual 262	kkkkkk/dvdddv:bккк043A043A043Aкк043Aк	(Ljava/lang/String;)Ljava/lang/String;
    //   127: astore_3
    //   128: aload_3
    //   129: ifnull +11 -> 140
    //   132: aload_2
    //   133: aload_3
    //   134: invokestatic 284	java/lang/Integer:parseInt	(Ljava/lang/String;)I
    //   137: putfield 287	kkkkkk/affaaa:b04220422ТТТТТТ0422Т	I
    //   140: invokestatic 250	kkkkkk/dvdddv:bк043A043A043Aк043Aкк043Aк	()Lkkkkkk/dvdddv;
    //   143: astore_3
    //   144: aload_3
    //   145: ldc_w 289
    //   148: sipush 133
    //   151: sipush 145
    //   154: iconst_3
    //   155: invokestatic 84	kkkkkk/gguuuu:bк043Aккк043Aкк043A043A	(Ljava/lang/String;CCC)Ljava/lang/String;
    //   158: invokevirtual 262	kkkkkk/dvdddv:bккк043A043A043Aкк043Aк	(Ljava/lang/String;)Ljava/lang/String;
    //   161: astore_3
    //   162: aload_3
    //   163: ifnull +93 -> 256
    //   166: aload_2
    //   167: aload_3
    //   168: putfield 292	kkkkkk/affaaa:bТТ0422ТТТТТ0422Т	Ljava/lang/String;
    //   171: aload_0
    //   172: getfield 106	kkkkkk/ddvddv:b0422Т04220422Т0422ТТТТ	Lkkkkkk/faafaf$aaffaf;
    //   175: astore_3
    //   176: aload_0
    //   177: getfield 119	kkkkkk/ddvddv:b04220422Т0422Т0422ТТТТ	Ljava/lang/String;
    //   180: astore 4
    //   182: aload_2
    //   183: ifnull +37 -> 220
    //   186: aload_2
    //   187: getfield 292	kkkkkk/affaaa:bТТ0422ТТТТТ0422Т	Ljava/lang/String;
    //   190: astore 5
    //   192: aload 5
    //   194: ldc_w 294
    //   197: bipush 120
    //   199: iconst_5
    //   200: invokestatic 211	kkkkkk/gguuuu:bккккк043Aкк043A043A	(Ljava/lang/String;CC)Ljava/lang/String;
    //   203: invokevirtual 298	java/lang/String:equals	(Ljava/lang/Object;)Z
    //   206: istore_1
    //   207: iload_1
    //   208: ifne +19 -> 227
    //   211: aload_3
    //   212: ifnull +15 -> 227
    //   215: aload 4
    //   217: ifnull +10 -> 227
    //   220: aload_3
    //   221: aload 4
    //   223: invokestatic 304	kkkkkk/fafaff:bк043A043Aкк043A043A043Aк043A	(Lkkkkkk/faafaf$aaffaf;Ljava/lang/String;)Lkkkkkk/affaaa;
    //   226: pop
    //   227: aload_2
    //   228: ifnull +87 -> 315
    //   231: aload_2
    //   232: getfield 292	kkkkkk/affaaa:bТТ0422ТТТТТ0422Т	Ljava/lang/String;
    //   235: ldc_w 306
    //   238: bipush 46
    //   240: bipush 72
    //   242: iconst_3
    //   243: invokestatic 84	kkkkkk/gguuuu:bк043Aккк043Aкк043A043A	(Ljava/lang/String;CCC)Ljava/lang/String;
    //   246: invokevirtual 298	java/lang/String:equals	(Ljava/lang/Object;)Z
    //   249: istore_1
    //   250: iload_1
    //   251: ifne +64 -> 315
    //   254: aconst_null
    //   255: areturn
    //   256: getstatic 167	kkkkkk/ddvddv:bТ0422Т042204220422ТТТТ	I
    //   259: invokestatic 242	kkkkkk/ddvddv:bк043A043A043A043Aк043Aк043Aк	()I
    //   262: iadd
    //   263: getstatic 167	kkkkkk/ddvddv:bТ0422Т042204220422ТТТТ	I
    //   266: imul
    //   267: getstatic 171	kkkkkk/ddvddv:b0422Т0422042204220422ТТТТ	I
    //   270: irem
    //   271: getstatic 176	kkkkkk/ddvddv:b04220422Т042204220422ТТТТ	I
    //   274: if_icmpeq +54 -> 328
    //   277: bipush 32
    //   279: putstatic 167	kkkkkk/ddvddv:bТ0422Т042204220422ТТТТ	I
    //   282: bipush 34
    //   284: putstatic 176	kkkkkk/ddvddv:b04220422Т042204220422ТТТТ	I
    //   287: aconst_null
    //   288: astore_2
    //   289: goto -118 -> 171
    //   292: astore_2
    //   293: getstatic 92	kkkkkk/ddvddv:b04220422ТТТ0422ТТТТ	Ljava/lang/String;
    //   296: ldc_w 308
    //   299: sipush 229
    //   302: iconst_4
    //   303: invokestatic 211	kkkkkk/gguuuu:bккккк043Aкк043A043A	(Ljava/lang/String;CC)Ljava/lang/String;
    //   306: aload_2
    //   307: invokestatic 312	kkkkkk/fafffa:b043A043Aк043Aкк043Aкк043A	(Ljava/lang/String;Ljava/lang/String;Ljava/lang/Exception;)V
    //   310: aconst_null
    //   311: astore_2
    //   312: goto -141 -> 171
    //   315: aload_2
    //   316: areturn
    //   317: aconst_null
    //   318: astore_2
    //   319: goto -148 -> 171
    //   322: astore_2
    //   323: aload_2
    //   324: athrow
    //   325: astore_2
    //   326: aload_2
    //   327: athrow
    //   328: aconst_null
    //   329: astore_2
    //   330: goto -159 -> 171
    // Local variable table:
    //   start	length	slot	name	signature
    //   0	333	0	this	ddvddv
    //   206	45	1	bool	boolean
    //   16	273	2	localAffaaa1	affaaa
    //   292	15	2	localNumberFormatException	NumberFormatException
    //   311	8	2	localAffaaa2	affaaa
    //   322	2	2	localException1	Exception
    //   325	2	2	localException2	Exception
    //   329	1	2	localObject1	Object
    //   34	187	3	localObject2	Object
    //   180	42	4	str1	String
    //   190	3	5	str2	String
    // Exception table:
    //   from	to	target	type
    //   17	35	292	java/lang/NumberFormatException
    //   39	47	292	java/lang/NumberFormatException
    //   47	51	292	java/lang/NumberFormatException
    //   82	98	292	java/lang/NumberFormatException
    //   102	110	292	java/lang/NumberFormatException
    //   110	128	292	java/lang/NumberFormatException
    //   132	140	292	java/lang/NumberFormatException
    //   140	144	292	java/lang/NumberFormatException
    //   144	162	292	java/lang/NumberFormatException
    //   166	171	292	java/lang/NumberFormatException
    //   0	17	322	java/lang/Exception
    //   17	35	322	java/lang/Exception
    //   39	47	322	java/lang/Exception
    //   47	51	322	java/lang/Exception
    //   82	98	322	java/lang/Exception
    //   102	110	322	java/lang/Exception
    //   110	128	322	java/lang/Exception
    //   144	162	322	java/lang/Exception
    //   166	171	322	java/lang/Exception
    //   171	182	322	java/lang/Exception
    //   186	192	322	java/lang/Exception
    //   220	227	322	java/lang/Exception
    //   231	250	322	java/lang/Exception
    //   132	140	325	java/lang/Exception
    //   140	144	325	java/lang/Exception
    //   192	207	325	java/lang/Exception
    //   293	310	325	java/lang/Exception
  }
  
  /* Error */
  private ddvddv.vdvvdv bккк043Aк043A043Aк043Aк(@Nonnull jjjtjt.jtjtjt paramJtjtjt, tttjjt paramTttjjt, @Nonnull ddvddv.vdvvdv paramVdvvdv)
  {
    // Byte code:
    //   0: aload_0
    //   1: getfield 104	kkkkkk/ddvddv:b0422ТТ0422Т0422ТТТТ	Lkkkkkk/ddddvv;
    //   4: invokevirtual 515	kkkkkk/ddddvv:bк043Aк043A043A043A043Aк043Aк	()V
    //   7: aload_2
    //   8: ifnull +126 -> 134
    //   11: getstatic 519	kkkkkk/vdvvvd:b044Eю044E044Eю044E044E044E044E044E	Ljava/util/concurrent/Executor;
    //   14: astore 9
    //   16: invokestatic 188	kkkkkk/ddvddv:b043Aк043A043A043Aк043Aк043Aк	()I
    //   19: istore 4
    //   21: getstatic 169	kkkkkk/ddvddv:bТТ0422042204220422ТТТТ	I
    //   24: istore 5
    //   26: invokestatic 188	kkkkkk/ddvddv:b043Aк043A043A043Aк043Aк043Aк	()I
    //   29: istore 6
    //   31: getstatic 167	kkkkkk/ddvddv:bТ0422Т042204220422ТТТТ	I
    //   34: istore 7
    //   36: iload 7
    //   38: getstatic 169	kkkkkk/ddvddv:bТТ0422042204220422ТТТТ	I
    //   41: iload 7
    //   43: iadd
    //   44: imul
    //   45: getstatic 171	kkkkkk/ddvddv:b0422Т0422042204220422ТТТТ	I
    //   48: irem
    //   49: tableswitch	default:+19->68, 0:+29->78
    //   68: bipush 18
    //   70: putstatic 167	kkkkkk/ddvddv:bТ0422Т042204220422ТТТТ	I
    //   73: bipush 23
    //   75: putstatic 176	kkkkkk/ddvddv:b04220422Т042204220422ТТТТ	I
    //   78: getstatic 171	kkkkkk/ddvddv:b0422Т0422042204220422ТТТТ	I
    //   81: istore 7
    //   83: getstatic 176	kkkkkk/ddvddv:b04220422Т042204220422ТТТТ	I
    //   86: istore 8
    //   88: iload 4
    //   90: iload 5
    //   92: iadd
    //   93: iload 6
    //   95: imul
    //   96: iload 7
    //   98: irem
    //   99: iload 8
    //   101: if_icmpeq +14 -> 115
    //   104: invokestatic 188	kkkkkk/ddvddv:b043Aк043A043A043Aк043Aк043Aк	()I
    //   107: putstatic 167	kkkkkk/ddvddv:bТ0422Т042204220422ТТТТ	I
    //   110: bipush 9
    //   112: putstatic 176	kkkkkk/ddvddv:b04220422Т042204220422ТТТТ	I
    //   115: new 8	kkkkkk/ddvddv$ddvvdv
    //   118: dup
    //   119: aload_0
    //   120: aload_1
    //   121: aload_2
    //   122: invokespecial 522	kkkkkk/ddvddv$ddvvdv:<init>	(Lkkkkkk/ddvddv;Lkkkkkk/jjjtjt$jtjtjt;Lkkkkkk/tttjjt;)V
    //   125: astore_1
    //   126: aload 9
    //   128: aload_1
    //   129: invokeinterface 528 2 0
    //   134: aload_3
    //   135: areturn
    //   136: astore_1
    //   137: aload_1
    //   138: athrow
    //   139: astore_1
    //   140: aload_1
    //   141: athrow
    // Local variable table:
    //   start	length	slot	name	signature
    //   0	142	0	this	ddvddv
    //   0	142	1	paramJtjtjt	jjjtjt.jtjtjt
    //   0	142	2	paramTttjjt	tttjjt
    //   0	142	3	paramVdvvdv	ddvddv.vdvvdv
    //   19	74	4	i	int
    //   24	69	5	j	int
    //   29	67	6	k	int
    //   34	65	7	m	int
    //   86	16	8	n	int
    //   14	113	9	localExecutor	java.util.concurrent.Executor
    // Exception table:
    //   from	to	target	type
    //   0	7	136	java/lang/Exception
    //   11	31	136	java/lang/Exception
    //   78	88	136	java/lang/Exception
    //   115	126	136	java/lang/Exception
    //   104	115	139	java/lang/Exception
    //   126	134	139	java/lang/Exception
  }
  
  /* Error */
  public boolean b043A043A043Aккк043Aккк()
  {
    // Byte code:
    //   0: getstatic 537	kkkkkk/ddvddv$dvdvdv:do	Lkkkkkk/ddvddv$dvdvdv;
    //   3: astore 7
    //   5: getstatic 167	kkkkkk/ddvddv:bТ0422Т042204220422ТТТТ	I
    //   8: istore_1
    //   9: getstatic 169	kkkkkk/ddvddv:bТТ0422042204220422ТТТТ	I
    //   12: istore_2
    //   13: getstatic 167	kkkkkk/ddvddv:bТ0422Т042204220422ТТТТ	I
    //   16: istore_3
    //   17: getstatic 171	kkkkkk/ddvddv:b0422Т0422042204220422ТТТТ	I
    //   20: istore 4
    //   22: invokestatic 174	kkkkkk/ddvddv:bкк043A043A043Aк043Aк043Aк	()I
    //   25: istore 5
    //   27: iload_1
    //   28: iload_2
    //   29: iadd
    //   30: iload_3
    //   31: imul
    //   32: iload 4
    //   34: irem
    //   35: iload 5
    //   37: if_icmpeq +57 -> 94
    //   40: getstatic 167	kkkkkk/ddvddv:bТ0422Т042204220422ТТТТ	I
    //   43: istore_1
    //   44: iload_1
    //   45: getstatic 169	kkkkkk/ddvddv:bТТ0422042204220422ТТТТ	I
    //   48: iload_1
    //   49: iadd
    //   50: imul
    //   51: getstatic 171	kkkkkk/ddvddv:b0422Т0422042204220422ТТТТ	I
    //   54: irem
    //   55: tableswitch	default:+17->72, 0:+29->84
    //   72: invokestatic 188	kkkkkk/ddvddv:b043Aк043A043A043Aк043Aк043Aк	()I
    //   75: putstatic 167	kkkkkk/ddvddv:bТ0422Т042204220422ТТТТ	I
    //   78: invokestatic 188	kkkkkk/ddvddv:b043Aк043A043A043Aк043Aк043Aк	()I
    //   81: putstatic 176	kkkkkk/ddvddv:b04220422Т042204220422ТТТТ	I
    //   84: bipush 52
    //   86: putstatic 167	kkkkkk/ddvddv:bТ0422Т042204220422ТТТТ	I
    //   89: bipush 89
    //   91: putstatic 176	kkkkkk/ddvddv:b04220422Т042204220422ТТТТ	I
    //   94: aload_0
    //   95: iconst_0
    //   96: iconst_1
    //   97: aload 7
    //   99: invokevirtual 506	kkkkkk/ddvddv:bк043Aкккк043Aккк	(IZLkkkkkk/ddvddv$dvdvdv;)Z
    //   102: istore 6
    //   104: iload 6
    //   106: ireturn
    //   107: astore 7
    //   109: aload 7
    //   111: athrow
    //   112: astore 7
    //   114: aload 7
    //   116: athrow
    //   117: astore 7
    //   119: aload 7
    //   121: athrow
    //   122: astore 7
    //   124: aload 7
    //   126: athrow
    // Local variable table:
    //   start	length	slot	name	signature
    //   0	127	0	this	ddvddv
    //   8	43	1	i	int
    //   12	18	2	j	int
    //   16	16	3	k	int
    //   20	15	4	m	int
    //   25	13	5	n	int
    //   102	3	6	bool	boolean
    //   3	95	7	localDvdvdv	ddvddv.dvdvdv
    //   107	3	7	localException1	Exception
    //   112	3	7	localException2	Exception
    //   117	3	7	localException3	Exception
    //   122	3	7	localException4	Exception
    // Exception table:
    //   from	to	target	type
    //   0	5	107	java/lang/Exception
    //   13	27	112	java/lang/Exception
    //   109	112	112	java/lang/Exception
    //   119	122	112	java/lang/Exception
    //   94	104	117	java/lang/Exception
    //   5	13	122	java/lang/Exception
    //   84	94	122	java/lang/Exception
  }
  
  @Nonnull
  public final ddvddv.vvdvdv b043A043Aк043Aк043A043Aк043Aк(String paramString, @Nonnull vdvvvd paramVdvvvd)
    throws InterruptedException, ddvddv.vddvdv
  {
    for (;;)
    {
      Object localObject1;
      Object localObject2;
      Object localObject3;
      int i;
      try
      {
        localObject1 = this.bТТТТ04220422ТТТТ;
        localObject1 = gguuuu.bккккк043Aкк043A043A("R]\\WY\037\023\022", 'Û', '\002') + ((ffffaa)localObject1).b0422Т0422Т0422Т0422Т0422Т + gguuuu.bк043Aккк043Aкк043A043A("\034T_\037^aU]a[&[hha", '\r', '', '\001');
        localObject2 = this.bТТТТ04220422ТТТТ;
        localObject3 = new aaaafa();
        ((aaaafa)localObject3).bкк043A043Aккккк043A(gguuuu.bккккк043Aкк043A043A("8:.%.(", '[', '\003'), ((ffffaa)localObject2).bТ04220422Т0422Т0422Т0422Т, false);
        try
        {
          ((aaaafa)localObject3).bкк043A043Aккккк043A(gguuuu.bк043Aккк043Aкк043A043A("C6EF=DD6A=", '', '¹', '\001'), paramString, false);
          ((aaaafa)localObject3).bкк043A043Aккккк043A(gguuuu.bккккк043Aкк043A043A("03", '¾', '\005'), faafaf.b043Aккк043A043Aк043Aк043A(), false);
          ((aaaafa)localObject3).bкк043A043Aккккк043A(gguuuu.bккккк043Aкк043A043A("\001\006iy\b\n\001\b\b", 'Ç', '\004'), tttjtt.tjtttt.jttttt.b044E044E044Eююююю044E044E, false);
          if ((((ffffaa)localObject2).b042204220422Т0422Т0422Т0422Т != null) && (!((ffffaa)localObject2).b042204220422Т0422Т0422Т0422Т.isEmpty())) {
            ((aaaafa)localObject3).bкк043A043Aккккк043A(gguuuu.bккккк043Aкк043A043A("'71(50E", 'E', '\000'), ((ffffaa)localObject2).b042204220422Т0422Т0422Т0422Т, false);
          }
          ((aaaafa)localObject3).bкк043A043Aккккк043A(gguuuu.bккккк043Aкк043A043A("\"\024\034\021)\031') ''", '\027', '\004'), vdddvd.b044Eюююююю044E044E044E, false);
          localObject2 = new ffaaff(this.bТТТ042204220422ТТТТ, (String)localObject1, (aaaafa)localObject3, ffffaa.bкк043Aкккккк043A(this.bТТ0422Т04220422ТТТТ), this.b0422ТТ0422Т0422ТТТТ);
          if (paramVdvvvd.bкккк043Aккк043Aк((Runnable)localObject2) == null) {
            break label1346;
          }
          if (localObject2 != null) {
            break label1319;
          }
          paramString = b04220422ТТТ0422ТТТТ;
          paramVdvvvd = gguuuu.bккккк043Aкк043A043A("Ws|\001zz7\r\t:~\f\f\r\005\004\026B\030\024E\032\r\033 \020\036XM\020\022 $'\035#\035", 'Ç', '\004');
          if ((bТ0422Т042204220422ТТТТ + bТТ0422042204220422ТТТТ) * bТ0422Т042204220422ТТТТ % b0422Т0422042204220422ТТТТ != bкк043A043A043Aк043Aк043Aк())
          {
            bТ0422Т042204220422ТТТТ = 34;
            b04220422Т042204220422ТТТТ = 38;
          }
          fafffa.b043Aк043Aк043Aк043Aкк043A(paramString, paramVdvvvd);
          paramString = new ddvddv.vddvdv(tjjjtt.THM_ConfigurationError);
          throw paramString;
        }
        catch (Exception paramString)
        {
          throw paramString;
        }
        localObject2 = this.bТ0422ТТ04220422ТТТТ;
        l1 = this.b042204220422Т04220422ТТТТ.get();
        if (((l1 & 0x1000000) != 0L) && (localObject2 != null)) {
          ((ddvddv.vvvddv)localObject2).bк043A043Aккк043Aк043Aк(this.b0422Т04220422Т0422ТТТТ, ((aaffaa)localObject3).b0422Т0422042204220422ТТ0422Т);
        }
        localObject2 = this.bТ0422Т0422Т0422ТТТТ;
        if ((b043Aк043A043A043Aк043Aк043Aк() + bТТ0422042204220422ТТТТ) * b043Aк043A043A043Aк043Aк043Aк() % b0422Т0422042204220422ТТТТ != b04220422Т042204220422ТТТТ)
        {
          bТ0422Т042204220422ТТТТ = 7;
          b04220422Т042204220422ТТТТ = 37;
        }
        localObject4 = this.b0422Т04220422Т0422ТТТТ;
        String str = this.b04220422Т0422Т0422ТТТТ;
        if (localObject2 != null)
        {
          l1 = ((aaffaa)localObject3).bТТ0422042204220422ТТ0422Т;
          l2 = ((aaffaa)localObject3).b0422ТТ042204220422ТТ0422Т;
          i = ((aaffaa)localObject3).b0422Т0422Т04220422ТТ0422Т;
          if ((l1 != ((affaaa)localObject2).bТ0422ТТТТТТ0422Т) || (l2 != ((affaaa)localObject2).b0422ТТТТТТТ0422Т) || (!gguuuu.bккккк043Aкк043A043A("ysvt\002z", '"', '\004').equals(((affaaa)localObject2).bТТ0422ТТТТТ0422Т))) {
            break label1586;
          }
          if (i == ((affaaa)localObject2).b04220422ТТТТТТ0422Т) {
            break label1563;
          }
          break label1586;
        }
        if (localObject2 != null) {
          break label1583;
        }
        localObject2 = new affaaa();
        this.bТ0422Т0422Т0422ТТТТ = ((affaaa)localObject2);
        ((affaaa)localObject2).bТ0422ТТТТТТ0422Т = ((aaffaa)localObject3).bТТ0422042204220422ТТ0422Т;
        ((affaaa)localObject2).b0422ТТТТТТТ0422Т = ((aaffaa)localObject3).b0422ТТ042204220422ТТ0422Т;
        ((affaaa)localObject2).bТТ0422ТТТТТ0422Т = gguuuu.bккккк043Aкк043A043A("smpn{t", '¾', '\001');
        ((affaaa)localObject2).b04220422ТТТТТТ0422Т = ((aaffaa)localObject3).b0422Т0422Т04220422ТТ0422Т;
        dvdddv.bк043A043A043Aк043Aкк043Aк().b043Aккк043A043Aкк043Aк(gguuuu.bккккк043Aкк043A043A("+3%%.&\017/2&+)-", '\035', '\003'), String.valueOf(((aaffaa)localObject3).bТТ0422042204220422ТТ0422Т));
        dvdddv.bк043A043A043Aк043Aкк043Aк().b043Aккк043A043Aкк043Aк(gguuuu.bк043Aккк043Aкк043A043A("iozikvp[}\003x\006", '_', '%', '\003'), String.valueOf(((aaffaa)localObject3).b0422ТТ042204220422ТТ0422Т));
        dvdddv localDvdddv = dvdddv.bк043A043A043Aк043Aкк043Aк();
        localDvdddv.b043Aккк043A043Aкк043Aк(gguuuu.bккккк043Aкк043A043A(",\034\"\f\032&&\033 \036", 'Á', '\002'), gguuuu.bк043Aккк043Aкк043A043A("=7:8E>", 'l', 'ã', '\001'));
        dvdddv.bк043A043A043Aк043Aкк043Aк().b043Aккк043A043Aкк043Aк(gguuuu.bк043Aккк043Aкк043A043A("7:-(6\021%1', ", 'H', 'q', '\002'), String.valueOf(((aaffaa)localObject3).b0422Т0422Т04220422ТТ0422Т));
        if ((localObject4 == null) || (str == null)) {
          break label1595;
        }
        i = bТ0422Т042204220422ТТТТ;
        switch (i * (bТТ0422042204220422ТТТТ + i) % b0422Т0422042204220422ТТТТ)
        {
        default: 
          bТ0422Т042204220422ТТТТ = 71;
          b04220422Т042204220422ТТТТ = b043Aк043A043A043Aк043Aк043Aк();
        }
        fafaff.b043Aк043Aкк043A043A043Aк043A((faafaf.aaffaf)localObject4, str, (affaaa)localObject2);
      }
      catch (Exception paramString)
      {
        try
        {
          long l1;
          long l2;
          label731:
          localObject3 = this.bТТ0422Т04220422ТТТТ;
          Object localObject4 = this.b0422ТТ0422Т0422ТТТТ;
          if ((b043Aк043A043A043Aк043Aк043Aк() + bТТ0422042204220422ТТТТ) * b043Aк043A043A043Aк043Aк043Aк() % b0422Т0422042204220422ТТТТ != b04220422Т042204220422ТТТТ)
          {
            bТ0422Т042204220422ТТТТ = b043Aк043A043A043Aк043Aк043Aк();
            b04220422Т042204220422ТТТТ = 65;
          }
          localObject1 = new vdddvd.dvvdvd((vdddvd)localObject3, ((vdddvd)localObject3).bю044Eю044Eююю044E044E044E, (String)localObject1, (ddddvv)localObject4);
          ((vdddvd)localObject3).bю044Eю044Eююю044E044E044E = ((vdddvd.dvvdvd)localObject1);
          this.bТ04220422Т04220422ТТТТ.unlock();
          if ((!this.b0422ТТ0422Т0422ТТТТ.bк043Aкккк043A043Aкк()) && (!Thread.currentThread().isInterrupted())) {
            break label1434;
          }
          throw new InterruptedException();
        }
        finally
        {
          this.bТ04220422Т04220422ТТТТ.unlock();
        }
        paramString = paramString;
        throw paramString;
      }
      if (i != 0)
      {
        l1 = ((aaffaa)localObject3).b0422ТТ042204220422ТТ0422Т;
        l2 = ((aaffaa)localObject3).bТТ0422042204220422ТТ0422Т;
        this.b042204220422Т04220422ТТТТ.set((l1 & 0x7EFFFFE ^ 0xFFFFFFFFFFFFFFFF) & this.b042204220422Т04220422ТТТТ.get() | l2 & 0x7EFFFFE);
      }
      this.b0422042204220422Т0422ТТТТ = ((aaffaa)localObject3).b0422Т0422Т04220422ТТ0422Т;
      if (((this.b042204220422Т04220422ТТТТ.get() & 0x10000) != 0L) && (dvdvvd.b043Aкк043Aк043A043A043Aкк(((aaffaa)localObject3).bТТТ042204220422ТТ0422Т)))
      {
        localObject2 = ((aaffaa)localObject3).bТТТ042204220422ТТ0422Т;
        localObject4 = ffffaa.b0422042204220422ТТ0422Т0422Т;
        paramVdvvvd.bкккк043Aккк043Aк(new affffa(this.bТТТ042204220422ТТТТ, affffa.fffffa.int, (String)localObject2, new aaaafa(), (Map)localObject4, this.b0422ТТ0422Т0422ТТТТ));
      }
      l1 = this.b042204220422Т04220422ТТТТ.get();
      if ((l1 & 0x400) != 0L)
      {
        localObject2 = this.bТТТТ04220422ТТТТ;
        localObject4 = new StringBuilder();
        localObject2 = ((StringBuilder)localObject4).append(((ffffaa)localObject2).bТ04220422Т0422Т0422Т0422Т).append(gguuuu.bккккк043Aкк043A043A("W", '\016', '\001')).append(dvdvvd.b043A043A043A043Aк043A043A043Aкк(paramString));
        ((StringBuilder)localObject2).append(gguuuu.bк043Aккк043Aкк043A043A("\nIJ<", 'V', '²', '\000'));
        fafffa.b043Aккк043Aк043Aкк043A(ffffaa.b04220422ТТ0422Т0422Т0422Т, gguuuu.bк043Aккк043Aкк043A043A(",@SK?CCG?v\032#'rBC?579591h:,7:)66", '¦', 'x', '\002'));
        localObject2 = gguuuu.bк043Aккк043Aкк043A043A("d\034", '\004', '2', '\003');
        if (ffffaa.bТ0422ТТ0422Т0422Т0422Т != null)
        {
          localObject2 = new StringBuilder().append(ffffaa.bТ0422ТТ0422Т0422Т0422Т);
          localObject2 = gguuuu.bк043Aккк043Aкк043A043A(" d", 'Å', 'T', '\001');
        }
        if ((bТ0422Т042204220422ТТТТ + bТТ0422042204220422ТТТТ) * bТ0422Т042204220422ТТТТ % b0422Т0422042204220422ТТТТ != b04220422Т042204220422ТТТТ)
        {
          bТ0422Т042204220422ТТТТ = 29;
          b04220422Т042204220422ТТТТ = b043Aк043A043A043Aк043Aк043Aк();
        }
        paramVdvvvd.bкккк043Aккк043Aк(new dddvvv((String)localObject2 + gguuuu.bк043Aккк043Aкк043A043A("I{zF\007\005\002}\002w>}t\003u\0048wm{", 'J', 'e', '\000')));
      }
      if ((this.b042204220422Т04220422ТТТТ.get() & 0x40) != 0L)
      {
        localObject2 = new aafaff(this.bТТТТ04220422ТТТТ.b0422Т0422Т0422Т0422Т0422Т, this.bТТТТ04220422ТТТТ.bТ04220422Т0422Т0422Т0422Т, paramString, ((aaffaa)localObject3).b04220422Т042204220422ТТ0422Т, this.b042204220422ТТ0422ТТТТ);
        paramVdvvvd.bкккк043Aккк043Aк((Runnable)localObject2);
      }
      paramVdvvvd = this.bТТ04220422Т0422ТТТТ;
      if (paramVdvvvd == null)
      {
        paramVdvvvd = null;
        label1155:
        paramString = new ddvddv.vvdvdv((vdddvd.dvvdvd)localObject1, (aaffaa)localObject3, paramString, paramVdvvvd);
        return paramString;
        label1279:
        for (localObject1 = null;; localObject1 = ((ddvddv.dddvdv)localObject1).bккк043Aкк043Aк043Aк(this.b042204220422ТТ0422ТТТТ / 10))
        {
          if ((!this.b0422ТТ0422Т0422ТТТТ.bк043Aкккк043A043Aкк()) && (!Thread.currentThread().isInterrupted())) {
            break label1413;
          }
          throw new InterruptedException();
          label1319:
          if ((this.b0422ТТ0422Т0422ТТТТ.bк043Aкккк043A043Aкк()) || (Thread.currentThread().isInterrupted()))
          {
            throw new InterruptedException();
            label1346:
            localObject2 = null;
            break;
          }
          if (!this.bТ04220422Т04220422ТТТТ.tryLock()) {
            break label1415;
          }
          localObject1 = this.b0422ТТТ04220422ТТТТ;
          if ((localObject1 == null) || (!this.b0422Т0422Т04220422ТТТТ) || ((this.b042204220422Т04220422ТТТТ.get() & 0x20000) == 0L)) {
            break label1279;
          }
        }
        label1413:
        continue;
        label1415:
        this.bТ04220422Т04220422ТТТТ.lock();
        localObject1 = this.bТТ0422Т04220422ТТТТ.bю044Eю044Eююю044E044E044E;
        continue;
        label1434:
        localObject3 = paramVdvvvd.bк043A043A043Aкккк043Aк(false, this.b0422ТТ0422Т0422ТТТТ, this.b042204220422ТТ0422ТТТТ);
        paramVdvvvd.b043Aк043A043Aкккк043Aк();
        if (localObject3 != tjjjtt.THM_OK)
        {
          fafffa.b043Aк043Aк043Aк043Aкк043A(b04220422ТТТ0422ТТТТ, gguuuu.bккккк043Aкк043A043A("/IPRJH\003VPQCQND?O=v9DB9;8{n//;=>26.d", '\027', '\005') + ((tjjjtt)localObject3).toString());
          throw new ddvddv.vddvdv((tjjjtt)localObject3);
        }
        if (this.b0422ТТ0422Т0422ТТТТ.bк043Aкккк043A043Aкк()) {
          throw new InterruptedException();
        }
        localObject3 = ((ffaaff)localObject2).b0422Т04220422ТТТТТ0422;
        if (localObject3 == null)
        {
          fafffa.b043Aк043Aк043Aк043Aкк043A(b04220422ТТТ0422ТТТТ, gguuuu.bк043Aккк043Aкк043A043A("o\n\021\023\013\tC\027\021@\007\004\022<~\n\b~\001}A4usz|x|t,z}", 'ý', 'W', '\002'));
          throw new ddvddv.vddvdv(tjjjtt.THM_ConfigurationError);
        }
      }
      else
      {
        label1563:
        label1583:
        label1586:
        for (i = 0; i == 0; i = 1)
        {
          i = 0;
          break label731;
          paramVdvvvd = paramVdvvvd.b043A043A043Aк043Aк043Aк043Aк();
          break label1155;
          break;
        }
        continue;
        label1595:
        i = 1;
      }
    }
  }
  
  /* Error */
  public jjjtjt.tjjtjt b043A043Aк043Aкк043Aккк(@Nonnull String paramString, @Nonnull tttjjt paramTttjjt)
  {
    // Byte code:
    //   0: new 394	kkkkkk/ttjtjt
    //   3: dup
    //   4: invokespecial 753	kkkkkk/ttjtjt:<init>	()V
    //   7: astore 4
    //   9: getstatic 167	kkkkkk/ddvddv:bТ0422Т042204220422ТТТТ	I
    //   12: istore_3
    //   13: iload_3
    //   14: getstatic 169	kkkkkk/ddvddv:bТТ0422042204220422ТТТТ	I
    //   17: iload_3
    //   18: iadd
    //   19: imul
    //   20: getstatic 171	kkkkkk/ddvddv:b0422Т0422042204220422ТТТТ	I
    //   23: irem
    //   24: tableswitch	default:+20->44, 0:+62->86
    //   44: getstatic 167	kkkkkk/ddvddv:bТ0422Т042204220422ТТТТ	I
    //   47: getstatic 169	kkkkkk/ddvddv:bТТ0422042204220422ТТТТ	I
    //   50: iadd
    //   51: getstatic 167	kkkkkk/ddvddv:bТ0422Т042204220422ТТТТ	I
    //   54: imul
    //   55: getstatic 171	kkkkkk/ddvddv:b0422Т0422042204220422ТТТТ	I
    //   58: irem
    //   59: getstatic 176	kkkkkk/ddvddv:b04220422Т042204220422ТТТТ	I
    //   62: if_icmpeq +14 -> 76
    //   65: bipush 93
    //   67: putstatic 167	kkkkkk/ddvddv:bТ0422Т042204220422ТТТТ	I
    //   70: invokestatic 188	kkkkkk/ddvddv:b043Aк043A043A043Aк043Aк043Aк	()I
    //   73: putstatic 176	kkkkkk/ddvddv:b04220422Т042204220422ТТТТ	I
    //   76: bipush 14
    //   78: putstatic 167	kkkkkk/ddvddv:bТ0422Т042204220422ТТТТ	I
    //   81: bipush 98
    //   83: putstatic 176	kkkkkk/ddvddv:b04220422Т042204220422ТТТТ	I
    //   86: aload 4
    //   88: aload_1
    //   89: invokevirtual 757	kkkkkk/ttjtjt:bкк043Aкк043Aкккк	(Ljava/lang/String;)Lkkkkkk/ttjtjt;
    //   92: astore_1
    //   93: aload_0
    //   94: aload_1
    //   95: aload_2
    //   96: invokevirtual 761	kkkkkk/ddvddv:bк043Aк043Aкк043Aккк	(Lkkkkkk/ttjtjt;Lkkkkkk/tttjjt;)Lkkkkkk/jjjtjt$tjjtjt;
    //   99: astore_1
    //   100: aload_1
    //   101: areturn
    //   102: astore_1
    //   103: aload_1
    //   104: athrow
    //   105: astore_1
    //   106: aload_1
    //   107: athrow
    // Local variable table:
    //   start	length	slot	name	signature
    //   0	108	0	this	ddvddv
    //   0	108	1	paramString	String
    //   0	108	2	paramTttjjt	tttjjt
    //   12	8	3	i	int
    //   7	80	4	localTtjtjt	ttjtjt
    // Exception table:
    //   from	to	target	type
    //   0	9	102	java/lang/Exception
    //   86	93	102	java/lang/Exception
    //   93	100	105	java/lang/Exception
  }
  
  public final tjjjtt b043A043Aккк043A043Aк043Aк(@Nonnull ddvddv.vvdvdv paramVvdvdv, aaaafa paramAaaafa, @Nonnull vdvvvd paramVdvvvd)
    throws InterruptedException
  {
    int i = bТ0422Т042204220422ТТТТ;
    switch (i * (bк043A043A043A043Aк043Aк043Aк() + i) % b0422Т0422042204220422ТТТТ)
    {
    default: 
      bТ0422Т042204220422ТТТТ = b043Aк043A043A043Aк043Aк043Aк();
      b04220422Т042204220422ТТТТ = b043Aк043A043A043Aк043Aк043Aк();
    }
    HashMap localHashMap = ffffaa.bк043A043Aкккккк043A(this.bТТ0422Т04220422ТТТТ);
    paramVdvvvd.bкккк043Aккк043Aк(new affffa(this.bТТТ042204220422ТТТТ, affffa.fffffa.new, this.bТТТТ04220422ТТТТ.b043A043A043Aкккккк043A(paramVvdvdv.b0422042204220422ТТ0422ТТТ.b042204220422042204220422ТТ0422Т), paramAaaafa, localHashMap, this.b0422ТТ0422Т0422ТТТТ));
    return paramVdvvvd.bк043A043A043Aкккк043Aк(true, this.b0422ТТ0422Т0422ТТТТ, this.b042204220422ТТ0422ТТТТ);
  }
  
  public abstract vvvdvd b043A043Aкккк043Aккк(jttjjt paramJttjjt);
  
  /* Error */
  public void b043Aк043Aк043Aк043Aккк(boolean paramBoolean)
  {
    // Byte code:
    //   0: iconst_1
    //   1: istore_2
    //   2: aload_0
    //   3: getfield 154	kkkkkk/ddvddv:bТТ04220422Т0422ТТТТ	Lkkkkkk/ddvddv$dvvvdv;
    //   6: astore_3
    //   7: aload_3
    //   8: ifnonnull +47 -> 55
    //   11: getstatic 167	kkkkkk/ddvddv:bТ0422Т042204220422ТТТТ	I
    //   14: getstatic 169	kkkkkk/ddvddv:bТТ0422042204220422ТТТТ	I
    //   17: iadd
    //   18: getstatic 167	kkkkkk/ddvddv:bТ0422Т042204220422ТТТТ	I
    //   21: imul
    //   22: getstatic 171	kkkkkk/ddvddv:b0422Т0422042204220422ТТТТ	I
    //   25: irem
    //   26: getstatic 176	kkkkkk/ddvddv:b04220422Т042204220422ТТТТ	I
    //   29: if_icmpeq +15 -> 44
    //   32: invokestatic 188	kkkkkk/ddvddv:b043Aк043A043A043Aк043Aк043Aк	()I
    //   35: putstatic 167	kkkkkk/ddvddv:bТ0422Т042204220422ТТТТ	I
    //   38: invokestatic 188	kkkkkk/ddvddv:b043Aк043A043A043Aк043Aк043Aк	()I
    //   41: putstatic 176	kkkkkk/ddvddv:b04220422Т042204220422ТТТТ	I
    //   44: return
    //   45: astore_3
    //   46: bipush 30
    //   48: putstatic 167	kkkkkk/ddvddv:bТ0422Т042204220422ТТТТ	I
    //   51: return
    //   52: astore_3
    //   53: aload_3
    //   54: athrow
    //   55: iload_1
    //   56: ifeq +68 -> 124
    //   59: iconst_0
    //   60: tableswitch	default:+24->84, 0:+51->111, 1:+-1->59
    //   84: iconst_1
    //   85: tableswitch	default:+23->108, 0:+-26->59, 1:+26->111
    //   108: goto -24 -> 84
    //   111: aload_3
    //   112: invokeinterface 783 1 0
    //   117: iload_2
    //   118: iconst_0
    //   119: idiv
    //   120: istore_2
    //   121: goto -4 -> 117
    //   124: aload_3
    //   125: invokeinterface 786 1 0
    //   130: return
    //   131: astore_3
    //   132: aload_3
    //   133: athrow
    // Local variable table:
    //   start	length	slot	name	signature
    //   0	134	0	this	ddvddv
    //   0	134	1	paramBoolean	boolean
    //   1	120	2	i	int
    //   6	2	3	localDvvvdv	dvvvdv
    //   45	1	3	localException1	Exception
    //   52	73	3	localException2	Exception
    //   131	2	3	localException3	Exception
    // Exception table:
    //   from	to	target	type
    //   117	121	45	java/lang/Exception
    //   2	7	52	java/lang/Exception
    //   46	51	52	java/lang/Exception
    //   111	117	52	java/lang/Exception
    //   124	130	131	java/lang/Exception
  }
  
  public final void b043Aк043Aкк043A043Aк043Aк()
  {
    String str;
    Thread localThread1;
    boolean bool1;
    try
    {
      fafffa.b043Aккк043Aк043Aкк043A(b04220422ТТТ0422ТТТТ, gguuuu.bк043Aккк043Aкк043A043A("QP^TW_\034\036", '\035', 'Ï', '\003'));
      if (this.b0422ТТ0422Т0422ТТТТ.bк043A043Aк043A043A043Aк043Aк()) {
        break label218;
      }
      fafffa.b043A043Aкк043Aк043Aкк043A(b04220422ТТТ0422ТТТТ, gguuuu.bккккк043Aкк043A043A("Ro{opv)isxjeg{!h`nmai_]", 'ù', '\002'));
      return;
    }
    finally {}
    fafffa.b043Aккк043Aк043Aкк043A(str, gguuuu.bккккк043Aкк043A043A("TEMBFJByBFK;GFHBEoC=l<=9/13+d8+4&!#]\021\005~sX", '\037', '\005') + localThread1.getId());
    localThread1.interrupt();
    label84:
    this.bТ04220422ТТ0422ТТТТ = new vdvvvd();
    if ((localThread1 != null) && (localThread1.isAlive()))
    {
      fafffa.b043Aккк043Aк043Aкк043A(b04220422ТТТ0422ТТТТ, gguuuu.bккккк043Aкк043A043A("M8AMCIC|DNR\001RUSKOSM\t^S^ROS\020ea\023Wdcgd^n`", 'Ô', '\000'));
      vdvvvd.bкк043A043Aкккк043Aк(localThread1, this.b042204220422ТТ0422ТТТТ);
    }
    label131:
    if (bool1)
    {
      fafffa.b043Aккк043Aк043Aкк043A(b04220422ТТТ0422ТТТТ, gguuuu.bккккк043Aкк043A043A("7@GQEIAx>FHtD45<163l?.+7", '´', '\002'));
      this.b0422ТТ0422Т0422ТТТТ.bкк043Aкккк043A043Aк(false, null);
    }
    for (;;)
    {
      label164:
      fafffa.b043Aккк043Aк043Aкк043A(b04220422ТТТ0422ТТТТ, gguuuu.bккккк043Aкк043A043A("IT]i_e_\031`jn\035_my!qxxxzhvmsys-X]Y1ut\001\002\n", 'Ï', '\001'));
      dvdddv.bк043A043A043Aк043Aкк043Aк().bкк043A043A043A043Aкк043Aк();
      label218:
      boolean bool2;
      do
      {
        this.b0422ТТ0422Т0422ТТТТ.b043Aк043Aкккк043A043Aк();
        fafffa.b043Aккк043Aк043Aкк043A(b04220422ТТТ0422ТТТТ, gguuuu.bккккк043Aкк043A043A("$CQGJRSMM", '0', '\004'));
        break;
        bool1 = this.b0422ТТ0422Т0422ТТТТ.bкк043A043A043A043A043Aк043Aк();
        if (bool1) {
          fafffa.b043Aккк043Aк043Aкк043A(b04220422ТТТ0422ТТТТ, gguuuu.bккккк043Aкк043A043A("\0230<017626.e5%&-\"'$]0\037\034(", '0', '\005'));
        }
        bool2 = this.b0422ТТ0422Т0422ТТТТ.b043A043Aк043A043A043A043Aк043Aк();
        if ((bool1) || (bool2))
        {
          fafffa.b043Aккк043Aк043Aкк043A(b04220422ТТТ0422ТТТТ, gguuuu.bк043Aккк043Aкк043A043A("RO[OPVUQUM\005EQ[\001OTRPP<H=AE=t\036!\033p30:9?", '\002', '\017', '\002'));
          dvdddv.bк043A043A043Aк043Aкк043Aк().b043A043A043A043A043A043Aкк043Aк();
        }
        if (!bool2) {
          break label131;
        }
        fafffa.b043Aккк043Aк043Aкк043A(b04220422ТТТ0422ТТТТ, gguuuu.bккккк043Aкк043A043A("jgsghnmime\035]^nbn\\\026efbXZ\\X\\T\f]OZ]LYY", '§', '\002'));
        this.bТ04220422ТТ0422ТТТТ.b043A043Aк043Aкккк043Aк();
        Thread localThread2 = this.bТТТ0422Т0422ТТТТ;
        if (localThread2 == null) {
          break label84;
        }
        str = b04220422ТТТ0422ТТТТ;
        switch (0)
        {
        }
        for (;;)
        {
          switch (0)
          {
          case 1: 
          default: 
            for (;;)
            {
              switch (1)
              {
              }
            }
          }
          switch (1)
          {
          }
        }
        if (bool1) {
          break label164;
        }
      } while (!bool2);
    }
  }
  
  public jjjtjt.tjjtjt b043Aкк043Aкк043Aккк(@Nonnull tttjjt paramTttjjt)
  {
    ttjtjt localTtjtjt = new ttjtjt();
    if ((bТ0422Т042204220422ТТТТ + bТТ0422042204220422ТТТТ) * bТ0422Т042204220422ТТТТ % b0422Т0422042204220422ТТТТ != b04220422Т042204220422ТТТТ)
    {
      if ((bТ0422Т042204220422ТТТТ + bТТ0422042204220422ТТТТ) * bТ0422Т042204220422ТТТТ % b0422Т0422042204220422ТТТТ != b04220422Т042204220422ТТТТ)
      {
        bТ0422Т042204220422ТТТТ = b043Aк043A043A043Aк043Aк043Aк();
        b04220422Т042204220422ТТТТ = 22;
      }
      bТ0422Т042204220422ТТТТ = 59;
      b04220422Т042204220422ТТТТ = b043Aк043A043A043Aк043Aк043Aк();
      switch (0)
      {
      case 1: 
      default: 
        for (;;)
        {
          switch (1)
          {
          }
        }
      }
    }
    return bк043Aк043Aкк043Aккк(localTtjtjt, paramTttjjt);
  }
  
  /* Error */
  public jjjtjt.tjjtjt bк043Aк043Aкк043Aккк(@Nonnull ttjtjt paramTtjtjt, @Nonnull tttjjt paramTttjjt)
  {
    // Byte code:
    //   0: iconst_0
    //   1: istore 4
    //   3: aload_1
    //   4: getfield 849	kkkkkk/ttjtjt:bюю044E044E044E044E044Eюю044E	Ljava/lang/String;
    //   7: invokestatic 428	kkkkkk/dvdvvd:b043Aкк043Aк043A043A043Aкк	(Ljava/lang/String;)Z
    //   10: ifeq +919 -> 929
    //   13: aload_1
    //   14: getfield 849	kkkkkk/ttjtjt:bюю044E044E044E044E044Eюю044E	Ljava/lang/String;
    //   17: invokestatic 852	kkkkkk/dvdvvd:bк043Aк043Aк043A043A043Aкк	(Ljava/lang/String;)Ljava/lang/String;
    //   20: astore 14
    //   22: aload_0
    //   23: getfield 104	kkkkkk/ddvddv:b0422ТТ0422Т0422ТТТТ	Lkkkkkk/ddddvv;
    //   26: invokevirtual 334	kkkkkk/ddddvv:b043Aк043A043A043A043A043Aк043Aк	()Z
    //   29: ifne +349 -> 378
    //   32: new 363	kkkkkk/jjjtjt$jtjtjt
    //   35: dup
    //   36: new 365	kkkkkk/jjjtjt
    //   39: dup
    //   40: invokespecial 366	kkkkkk/jjjtjt:<init>	()V
    //   43: aload 14
    //   45: getstatic 376	kkkkkk/tjjjtt:THM_Internal_Error	Lkkkkkk/tjjjtt;
    //   48: invokespecial 369	kkkkkk/jjjtjt$jtjtjt:<init>	(Lkkkkkk/jjjtjt;Ljava/lang/String;Lkkkkkk/tjjjtt;)V
    //   51: astore 15
    //   53: invokestatic 188	kkkkkk/ddvddv:b043Aк043A043A043Aк043Aк043Aк	()I
    //   56: getstatic 169	kkkkkk/ddvddv:bТТ0422042204220422ТТТТ	I
    //   59: iadd
    //   60: invokestatic 188	kkkkkk/ddvddv:b043Aк043A043A043Aк043Aк043Aк	()I
    //   63: imul
    //   64: getstatic 171	kkkkkk/ddvddv:b0422Т0422042204220422ТТТТ	I
    //   67: irem
    //   68: getstatic 176	kkkkkk/ddvddv:b04220422Т042204220422ТТТТ	I
    //   71: if_icmpeq +14 -> 85
    //   74: bipush 13
    //   76: putstatic 167	kkkkkk/ddvddv:bТ0422Т042204220422ТТТТ	I
    //   79: invokestatic 188	kkkkkk/ddvddv:b043Aк043A043A043Aк043Aк043Aк	()I
    //   82: putstatic 176	kkkkkk/ddvddv:b04220422Т042204220422ТТТТ	I
    //   85: new 17	kkkkkk/ddvddv$vdvvdv
    //   88: dup
    //   89: aload_0
    //   90: aload 14
    //   92: invokespecial 855	kkkkkk/ddvddv$vdvvdv:<init>	(Lkkkkkk/ddvddv;Ljava/lang/String;)V
    //   95: astore 14
    //   97: aload 14
    //   99: astore_1
    //   100: aload_2
    //   101: ifnull +25 -> 126
    //   104: getstatic 519	kkkkkk/vdvvvd:b044Eю044E044Eю044E044E044E044E044E	Ljava/util/concurrent/Executor;
    //   107: new 8	kkkkkk/ddvddv$ddvvdv
    //   110: dup
    //   111: aload_0
    //   112: aload 15
    //   114: aload_2
    //   115: invokespecial 522	kkkkkk/ddvddv$ddvvdv:<init>	(Lkkkkkk/ddvddv;Lkkkkkk/jjjtjt$jtjtjt;Lkkkkkk/tttjjt;)V
    //   118: invokeinterface 528 2 0
    //   123: aload 14
    //   125: astore_1
    //   126: aload_1
    //   127: areturn
    //   128: invokestatic 858	kkkkkk/fafffa:bк043A043A043Aкк043Aкк043A	()I
    //   131: pop
    //   132: getstatic 92	kkkkkk/ddvddv:b04220422ТТТ0422ТТТТ	Ljava/lang/String;
    //   135: astore 16
    //   137: new 225	java/lang/StringBuilder
    //   140: dup
    //   141: ldc_w 860
    //   144: sipush 238
    //   147: iconst_5
    //   148: invokestatic 211	kkkkkk/gguuuu:bккккк043Aкк043A043A	(Ljava/lang/String;CC)Ljava/lang/String;
    //   151: invokespecial 230	java/lang/StringBuilder:<init>	(Ljava/lang/String;)V
    //   154: astore 15
    //   156: aload 15
    //   158: aload_0
    //   159: getfield 148	kkkkkk/ddvddv:b042204220422Т04220422ТТТТ	Ljava/util/concurrent/atomic/AtomicLong;
    //   162: invokevirtual 165	java/util/concurrent/atomic/AtomicLong:get	()J
    //   165: invokevirtual 802	java/lang/StringBuilder:append	(J)Ljava/lang/StringBuilder;
    //   168: ldc_w 862
    //   171: sipush 152
    //   174: iconst_5
    //   175: invokestatic 211	kkkkkk/gguuuu:bккккк043Aкк043A043A	(Ljava/lang/String;CC)Ljava/lang/String;
    //   178: invokevirtual 234	java/lang/StringBuilder:append	(Ljava/lang/String;)Ljava/lang/StringBuilder;
    //   181: aload_0
    //   182: getfield 115	kkkkkk/ddvddv:b042204220422ТТ0422ТТТТ	I
    //   185: invokevirtual 418	java/lang/StringBuilder:append	(I)Ljava/lang/StringBuilder;
    //   188: astore 15
    //   190: ldc_w 864
    //   193: sipush 219
    //   196: sipush 238
    //   199: iconst_0
    //   200: invokestatic 84	kkkkkk/gguuuu:bк043Aккк043Aкк043A043A	(Ljava/lang/String;CCC)Ljava/lang/String;
    //   203: astore 17
    //   205: aload 15
    //   207: aload 17
    //   209: invokevirtual 234	java/lang/StringBuilder:append	(Ljava/lang/String;)Ljava/lang/StringBuilder;
    //   212: astore 17
    //   214: aload_0
    //   215: getfield 150	kkkkkk/ddvddv:bТТТТ04220422ТТТТ	Lkkkkkk/ffffaa;
    //   218: ifnull +724 -> 942
    //   221: aload_0
    //   222: getfield 150	kkkkkk/ddvddv:bТТТТ04220422ТТТТ	Lkkkkkk/ffffaa;
    //   225: getfield 544	kkkkkk/ffffaa:b0422Т0422Т0422Т0422Т0422Т	Ljava/lang/String;
    //   228: astore 15
    //   230: aload 16
    //   232: aload 17
    //   234: aload 15
    //   236: invokevirtual 234	java/lang/StringBuilder:append	(Ljava/lang/String;)Ljava/lang/StringBuilder;
    //   239: ldc_w 866
    //   242: bipush 52
    //   244: iconst_4
    //   245: invokestatic 211	kkkkkk/gguuuu:bккккк043Aкк043A043A	(Ljava/lang/String;CC)Ljava/lang/String;
    //   248: invokevirtual 234	java/lang/StringBuilder:append	(Ljava/lang/String;)Ljava/lang/StringBuilder;
    //   251: ldc_w 868
    //   254: sipush 135
    //   257: iconst_2
    //   258: invokestatic 211	kkkkkk/gguuuu:bккккк043Aкк043A043A	(Ljava/lang/String;CC)Ljava/lang/String;
    //   261: invokestatic 871	java/lang/System:getProperty	(Ljava/lang/String;)Ljava/lang/String;
    //   264: invokevirtual 234	java/lang/StringBuilder:append	(Ljava/lang/String;)Ljava/lang/StringBuilder;
    //   267: invokevirtual 239	java/lang/StringBuilder:toString	()Ljava/lang/String;
    //   270: invokestatic 340	kkkkkk/fafffa:b043Aккк043Aк043Aкк043A	(Ljava/lang/String;Ljava/lang/String;)V
    //   273: new 17	kkkkkk/ddvddv$vdvvdv
    //   276: dup
    //   277: aload_0
    //   278: aload 14
    //   280: invokespecial 855	kkkkkk/ddvddv$vdvvdv:<init>	(Lkkkkkk/ddvddv;Ljava/lang/String;)V
    //   283: astore 15
    //   285: aload_0
    //   286: getfield 113	kkkkkk/ddvddv:bТ04220422ТТ0422ТТТТ	Lkkkkkk/vdvvvd;
    //   289: invokevirtual 844	kkkkkk/vdvvvd:b043A043Aк043Aкккк043Aк	()V
    //   292: aload_0
    //   293: getfield 154	kkkkkk/ddvddv:bТТ04220422Т0422ТТТТ	Lkkkkkk/ddvddv$dvvvdv;
    //   296: astore 16
    //   298: aload 16
    //   300: ifnull +14 -> 314
    //   303: aload 16
    //   305: aload_1
    //   306: getfield 875	kkkkkk/ttjtjt:b044E044Eю044E044E044E044Eюю044E	Lkkkkkk/vdddvd$vdvdvd;
    //   309: invokeinterface 879 2 0
    //   314: aload_0
    //   315: getfield 136	kkkkkk/ddvddv:b04220422ТТ04220422ТТТТ	Lkkkkkk/vdddvd$ddvdvd;
    //   318: astore 16
    //   320: aload 16
    //   322: aload 16
    //   324: getfield 882	kkkkkk/vdddvd$ddvdvd:b044Eюю044E044Eюю044E044E044E	I
    //   327: iconst_1
    //   328: iadd
    //   329: putfield 882	kkkkkk/vdddvd$ddvdvd:b044Eюю044E044Eюю044E044E044E	I
    //   332: new 345	java/lang/Thread
    //   335: dup
    //   336: new 884	kkkkkk/ddvddv$3
    //   339: dup
    //   340: aload_0
    //   341: aload 14
    //   343: aload_1
    //   344: aload_2
    //   345: invokestatic 889	kkkkkk/tttjtt$vvdvdd:b043A043Aкк043A043Aк043Aкк	()J
    //   348: aload 15
    //   350: invokespecial 891	kkkkkk/ddvddv$3:<init>	(Lkkkkkk/ddvddv;Ljava/lang/String;Lkkkkkk/ttjtjt;Lkkkkkk/tttjjt;JLkkkkkk/ddvddv$vdvvdv;)V
    //   353: invokespecial 893	java/lang/Thread:<init>	(Ljava/lang/Runnable;)V
    //   356: astore_1
    //   357: aload_0
    //   358: aload_1
    //   359: putfield 121	kkkkkk/ddvddv:bТТТ0422Т0422ТТТТ	Ljava/lang/Thread;
    //   362: aload_1
    //   363: invokevirtual 896	java/lang/Thread:start	()V
    //   366: aload 15
    //   368: areturn
    //   369: astore_1
    //   370: aload_1
    //   371: athrow
    //   372: astore_1
    //   373: aload_1
    //   374: athrow
    //   375: astore_1
    //   376: aload_1
    //   377: athrow
    //   378: aload_0
    //   379: getfield 104	kkkkkk/ddvddv:b0422ТТ0422Т0422ТТТТ	Lkkkkkk/ddddvv;
    //   382: invokevirtual 899	kkkkkk/ddddvv:b043Aкк043A043A043A043Aк043Aк	()Z
    //   385: ifne +306 -> 691
    //   388: new 363	kkkkkk/jjjtjt$jtjtjt
    //   391: dup
    //   392: new 365	kkkkkk/jjjtjt
    //   395: dup
    //   396: invokespecial 366	kkkkkk/jjjtjt:<init>	()V
    //   399: aload 14
    //   401: getstatic 323	kkkkkk/tjjjtt:THM_NotYet	Lkkkkkk/tjjjtt;
    //   404: invokespecial 369	kkkkkk/jjjtjt$jtjtjt:<init>	(Lkkkkkk/jjjtjt;Ljava/lang/String;Lkkkkkk/tjjjtt;)V
    //   407: astore 15
    //   409: new 17	kkkkkk/ddvddv$vdvvdv
    //   412: dup
    //   413: aload_0
    //   414: aload 14
    //   416: invokespecial 855	kkkkkk/ddvddv$vdvvdv:<init>	(Lkkkkkk/ddvddv;Ljava/lang/String;)V
    //   419: astore 14
    //   421: aload 14
    //   423: astore_1
    //   424: aload_2
    //   425: ifnull -299 -> 126
    //   428: getstatic 519	kkkkkk/vdvvvd:b044Eю044E044Eю044E044E044E044E044E	Ljava/util/concurrent/Executor;
    //   431: new 8	kkkkkk/ddvddv$ddvvdv
    //   434: dup
    //   435: aload_0
    //   436: aload 15
    //   438: aload_2
    //   439: invokespecial 522	kkkkkk/ddvddv$ddvvdv:<init>	(Lkkkkkk/ddvddv;Lkkkkkk/jjjtjt$jtjtjt;Lkkkkkk/tttjjt;)V
    //   442: invokeinterface 528 2 0
    //   447: aload 14
    //   449: areturn
    //   450: astore_1
    //   451: aload_1
    //   452: athrow
    //   453: iload_3
    //   454: ifne +499 -> 953
    //   457: aload_0
    //   458: getfield 125	kkkkkk/ddvddv:b0422Т0422ТТ0422ТТТТ	Z
    //   461: ifeq +476 -> 937
    //   464: goto +489 -> 953
    //   467: iload_3
    //   468: ifne +72 -> 540
    //   471: aload_0
    //   472: getfield 104	kkkkkk/ddvddv:b0422ТТ0422Т0422ТТТТ	Lkkkkkk/ddddvv;
    //   475: invokevirtual 515	kkkkkk/ddddvv:bк043Aк043A043A043A043Aк043Aк	()V
    //   478: new 363	kkkkkk/jjjtjt$jtjtjt
    //   481: dup
    //   482: new 365	kkkkkk/jjjtjt
    //   485: dup
    //   486: invokespecial 366	kkkkkk/jjjtjt:<init>	()V
    //   489: aload 14
    //   491: getstatic 902	kkkkkk/tjjjtt:THM_Blocked	Lkkkkkk/tjjjtt;
    //   494: invokespecial 369	kkkkkk/jjjtjt$jtjtjt:<init>	(Lkkkkkk/jjjtjt;Ljava/lang/String;Lkkkkkk/tjjjtt;)V
    //   497: astore 15
    //   499: new 17	kkkkkk/ddvddv$vdvvdv
    //   502: dup
    //   503: aload_0
    //   504: aload 14
    //   506: invokespecial 855	kkkkkk/ddvddv$vdvvdv:<init>	(Lkkkkkk/ddvddv;Ljava/lang/String;)V
    //   509: astore 14
    //   511: aload 14
    //   513: astore_1
    //   514: aload_2
    //   515: ifnull -389 -> 126
    //   518: getstatic 519	kkkkkk/vdvvvd:b044Eю044E044Eю044E044E044E044E044E	Ljava/util/concurrent/Executor;
    //   521: new 8	kkkkkk/ddvddv$ddvvdv
    //   524: dup
    //   525: aload_0
    //   526: aload 15
    //   528: aload_2
    //   529: invokespecial 522	kkkkkk/ddvddv$ddvvdv:<init>	(Lkkkkkk/ddvddv;Lkkkkkk/jjjtjt$jtjtjt;Lkkkkkk/tttjjt;)V
    //   532: invokeinterface 528 2 0
    //   537: aload 14
    //   539: areturn
    //   540: iload 4
    //   542: istore_3
    //   543: aload_0
    //   544: getfield 127	kkkkkk/ddvddv:bТ042204220422Т0422ТТТТ	J
    //   547: lconst_0
    //   548: lcmp
    //   549: ifeq +15 -> 564
    //   552: aload_0
    //   553: getfield 129	kkkkkk/ddvddv:b0422042204220422Т0422ТТТТ	I
    //   556: istore_3
    //   557: iload_3
    //   558: ifne +325 -> 883
    //   561: iload 4
    //   563: istore_3
    //   564: iload_3
    //   565: ifeq +276 -> 841
    //   568: aload_0
    //   569: getfield 104	kkkkkk/ddvddv:b0422ТТ0422Т0422ТТТТ	Lkkkkkk/ddddvv;
    //   572: invokevirtual 515	kkkkkk/ddddvv:bк043Aк043A043A043A043Aк043Aк	()V
    //   575: new 363	kkkkkk/jjjtjt$jtjtjt
    //   578: dup
    //   579: new 365	kkkkkk/jjjtjt
    //   582: dup
    //   583: invokespecial 366	kkkkkk/jjjtjt:<init>	()V
    //   586: aload 14
    //   588: getstatic 905	kkkkkk/tjjjtt:THM_In_Quiet_Period	Lkkkkkk/tjjjtt;
    //   591: invokespecial 369	kkkkkk/jjjtjt$jtjtjt:<init>	(Lkkkkkk/jjjtjt;Ljava/lang/String;Lkkkkkk/tjjjtt;)V
    //   594: astore 15
    //   596: new 17	kkkkkk/ddvddv$vdvvdv
    //   599: dup
    //   600: aload_0
    //   601: aload 14
    //   603: invokespecial 855	kkkkkk/ddvddv$vdvvdv:<init>	(Lkkkkkk/ddvddv;Ljava/lang/String;)V
    //   606: astore 14
    //   608: aload 14
    //   610: astore_1
    //   611: aload_2
    //   612: ifnull -486 -> 126
    //   615: getstatic 519	kkkkkk/vdvvvd:b044Eю044E044Eю044E044E044E044E044E	Ljava/util/concurrent/Executor;
    //   618: astore_1
    //   619: new 8	kkkkkk/ddvddv$ddvvdv
    //   622: dup
    //   623: aload_0
    //   624: aload 15
    //   626: aload_2
    //   627: invokespecial 522	kkkkkk/ddvddv$ddvvdv:<init>	(Lkkkkkk/ddvddv;Lkkkkkk/jjjtjt$jtjtjt;Lkkkkkk/tttjjt;)V
    //   630: astore_2
    //   631: invokestatic 188	kkkkkk/ddvddv:b043Aк043A043A043Aк043Aк043Aк	()I
    //   634: istore_3
    //   635: getstatic 169	kkkkkk/ddvddv:bТТ0422042204220422ТТТТ	I
    //   638: istore 4
    //   640: invokestatic 188	kkkkkk/ddvddv:b043Aк043A043A043Aк043Aк043Aк	()I
    //   643: istore 5
    //   645: getstatic 171	kkkkkk/ddvddv:b0422Т0422042204220422ТТТТ	I
    //   648: istore 6
    //   650: invokestatic 174	kkkkkk/ddvddv:bкк043A043A043Aк043Aк043Aк	()I
    //   653: istore 7
    //   655: iload_3
    //   656: iload 4
    //   658: iadd
    //   659: iload 5
    //   661: imul
    //   662: iload 6
    //   664: irem
    //   665: iload 7
    //   667: if_icmpeq +14 -> 681
    //   670: invokestatic 188	kkkkkk/ddvddv:b043Aк043A043A043Aк043Aк043Aк	()I
    //   673: putstatic 167	kkkkkk/ddvddv:bТ0422Т042204220422ТТТТ	I
    //   676: bipush 64
    //   678: putstatic 176	kkkkkk/ddvddv:b04220422Т042204220422ТТТТ	I
    //   681: aload_1
    //   682: aload_2
    //   683: invokeinterface 528 2 0
    //   688: aload 14
    //   690: areturn
    //   691: aload_0
    //   692: getfield 148	kkkkkk/ddvddv:b042204220422Т04220422ТТТТ	Ljava/util/concurrent/atomic/AtomicLong;
    //   695: invokevirtual 165	java/util/concurrent/atomic/AtomicLong:get	()J
    //   698: ldc2_w 906
    //   701: land
    //   702: lconst_0
    //   703: lcmp
    //   704: ifne -164 -> 540
    //   707: aload_0
    //   708: getfield 106	kkkkkk/ddvddv:b0422Т04220422Т0422ТТТТ	Lkkkkkk/faafaf$aaffaf;
    //   711: astore 15
    //   713: getstatic 167	kkkkkk/ddvddv:bТ0422Т042204220422ТТТТ	I
    //   716: getstatic 169	kkkkkk/ddvddv:bТТ0422042204220422ТТТТ	I
    //   719: iadd
    //   720: getstatic 167	kkkkkk/ddvddv:bТ0422Т042204220422ТТТТ	I
    //   723: imul
    //   724: getstatic 171	kkkkkk/ddvddv:b0422Т0422042204220422ТТТТ	I
    //   727: irem
    //   728: getstatic 176	kkkkkk/ddvddv:b04220422Т042204220422ТТТТ	I
    //   731: if_icmpeq +13 -> 744
    //   734: bipush 38
    //   736: putstatic 167	kkkkkk/ddvddv:bТ0422Т042204220422ТТТТ	I
    //   739: bipush 18
    //   741: putstatic 176	kkkkkk/ddvddv:b04220422Т042204220422ТТТТ	I
    //   744: aload 15
    //   746: ifnull +212 -> 958
    //   749: aload 15
    //   751: invokestatic 911	kkkkkk/faafaf:b043Aк043A043Aк043Aк043Aк043A	(Lkkkkkk/faafaf$aaffaf;)Z
    //   754: ifeq +209 -> 963
    //   757: goto +201 -> 958
    //   760: aload_0
    //   761: getfield 127	kkkkkk/ddvddv:bТ042204220422Т0422ТТТТ	J
    //   764: lconst_0
    //   765: lcmp
    //   766: ifne -313 -> 453
    //   769: goto -302 -> 467
    //   772: astore_1
    //   773: new 363	kkkkkk/jjjtjt$jtjtjt
    //   776: dup
    //   777: new 365	kkkkkk/jjjtjt
    //   780: dup
    //   781: invokespecial 366	kkkkkk/jjjtjt:<init>	()V
    //   784: ldc_w 913
    //   787: getstatic 358	kkkkkk/tjjjtt:THM_Interrupted_Error	Lkkkkkk/tjjjtt;
    //   790: invokespecial 369	kkkkkk/jjjtjt$jtjtjt:<init>	(Lkkkkkk/jjjtjt;Ljava/lang/String;Lkkkkkk/tjjjtt;)V
    //   793: astore 15
    //   795: new 17	kkkkkk/ddvddv$vdvvdv
    //   798: dup
    //   799: aload_0
    //   800: ldc_w 913
    //   803: invokespecial 855	kkkkkk/ddvddv$vdvvdv:<init>	(Lkkkkkk/ddvddv;Ljava/lang/String;)V
    //   806: astore 14
    //   808: aload 14
    //   810: astore_1
    //   811: aload_2
    //   812: ifnull -686 -> 126
    //   815: getstatic 519	kkkkkk/vdvvvd:b044Eю044E044Eю044E044E044E044E044E	Ljava/util/concurrent/Executor;
    //   818: astore_1
    //   819: new 8	kkkkkk/ddvddv$ddvvdv
    //   822: dup
    //   823: aload_0
    //   824: aload 15
    //   826: aload_2
    //   827: invokespecial 522	kkkkkk/ddvddv$ddvvdv:<init>	(Lkkkkkk/ddvddv;Lkkkkkk/jjjtjt$jtjtjt;Lkkkkkk/tttjjt;)V
    //   830: astore_2
    //   831: aload_1
    //   832: aload_2
    //   833: invokeinterface 528 2 0
    //   838: aload 14
    //   840: areturn
    //   841: aload_2
    //   842: ifnonnull -714 -> 128
    //   845: aload_0
    //   846: getfield 104	kkkkkk/ddvddv:b0422ТТ0422Т0422ТТТТ	Lkkkkkk/ddddvv;
    //   849: invokevirtual 515	kkkkkk/ddddvv:bк043Aк043A043A043A043Aк043Aк	()V
    //   852: new 363	kkkkkk/jjjtjt$jtjtjt
    //   855: dup
    //   856: new 365	kkkkkk/jjjtjt
    //   859: dup
    //   860: invokespecial 366	kkkkkk/jjjtjt:<init>	()V
    //   863: aload 14
    //   865: getstatic 916	kkkkkk/tjjjtt:THM_EndNotifier_NotFound	Lkkkkkk/tjjjtt;
    //   868: invokespecial 369	kkkkkk/jjjtjt$jtjtjt:<init>	(Lkkkkkk/jjjtjt;Ljava/lang/String;Lkkkkkk/tjjjtt;)V
    //   871: pop
    //   872: new 17	kkkkkk/ddvddv$vdvvdv
    //   875: dup
    //   876: aload_0
    //   877: aload 14
    //   879: invokespecial 855	kkkkkk/ddvddv$vdvvdv:<init>	(Lkkkkkk/ddvddv;Ljava/lang/String;)V
    //   882: areturn
    //   883: aload_0
    //   884: getfield 127	kkkkkk/ddvddv:bТ042204220422Т0422ТТТТ	J
    //   887: lstore 8
    //   889: getstatic 922	java/util/concurrent/TimeUnit:MILLISECONDS	Ljava/util/concurrent/TimeUnit;
    //   892: aload_0
    //   893: getfield 129	kkkkkk/ddvddv:b0422042204220422Т0422ТТТТ	I
    //   896: i2l
    //   897: getstatic 925	java/util/concurrent/TimeUnit:MINUTES	Ljava/util/concurrent/TimeUnit;
    //   900: invokevirtual 929	java/util/concurrent/TimeUnit:convert	(JLjava/util/concurrent/TimeUnit;)J
    //   903: lstore 10
    //   905: invokestatic 328	java/lang/System:currentTimeMillis	()J
    //   908: lstore 12
    //   910: iload 4
    //   912: istore_3
    //   913: lload 8
    //   915: lload 10
    //   917: ladd
    //   918: lload 12
    //   920: lcmp
    //   921: ifle -357 -> 564
    //   924: iconst_1
    //   925: istore_3
    //   926: goto -362 -> 564
    //   929: invokestatic 932	kkkkkk/dvdvvd:bккк043A043A043A043A043Aкк	()Ljava/lang/String;
    //   932: astore 14
    //   934: goto -912 -> 22
    //   937: iconst_0
    //   938: istore_3
    //   939: goto -472 -> 467
    //   942: ldc_w 913
    //   945: astore 15
    //   947: goto -717 -> 230
    //   950: astore_1
    //   951: aload_1
    //   952: athrow
    //   953: iconst_1
    //   954: istore_3
    //   955: goto -488 -> 467
    //   958: iconst_1
    //   959: istore_3
    //   960: goto -200 -> 760
    //   963: iconst_0
    //   964: istore_3
    //   965: goto -205 -> 760
    // Local variable table:
    //   start	length	slot	name	signature
    //   0	968	0	this	ddvddv
    //   0	968	1	paramTtjtjt	ttjtjt
    //   0	968	2	paramTttjjt	tttjjt
    //   453	512	3	i	int
    //   1	910	4	j	int
    //   643	19	5	k	int
    //   648	17	6	m	int
    //   653	15	7	n	int
    //   887	27	8	l1	long
    //   903	13	10	l2	long
    //   908	11	12	l3	long
    //   20	913	14	localObject1	Object
    //   51	895	15	localObject2	Object
    //   135	188	16	localObject3	Object
    //   203	30	17	localObject4	Object
    // Exception table:
    //   from	to	target	type
    //   128	156	369	java/lang/Exception
    //   205	230	369	java/lang/Exception
    //   230	298	369	java/lang/Exception
    //   303	314	369	java/lang/Exception
    //   314	366	369	java/lang/Exception
    //   378	421	369	java/lang/Exception
    //   568	608	369	java/lang/Exception
    //   831	838	369	java/lang/Exception
    //   929	934	369	java/lang/Exception
    //   370	372	372	java/lang/Exception
    //   451	453	372	java/lang/Exception
    //   670	681	372	java/lang/Exception
    //   373	375	375	java/lang/Exception
    //   951	953	375	java/lang/Exception
    //   3	22	450	java/lang/Exception
    //   22	53	450	java/lang/Exception
    //   85	97	450	java/lang/Exception
    //   104	123	450	java/lang/Exception
    //   156	205	450	java/lang/Exception
    //   428	447	450	java/lang/Exception
    //   457	464	450	java/lang/Exception
    //   471	511	450	java/lang/Exception
    //   518	537	450	java/lang/Exception
    //   543	557	450	java/lang/Exception
    //   615	631	450	java/lang/Exception
    //   681	688	450	java/lang/Exception
    //   691	713	450	java/lang/Exception
    //   749	757	450	java/lang/Exception
    //   760	769	450	java/lang/Exception
    //   773	808	450	java/lang/Exception
    //   815	831	450	java/lang/Exception
    //   845	883	450	java/lang/Exception
    //   883	910	450	java/lang/Exception
    //   929	934	772	java/lang/InterruptedException
    //   631	655	950	java/lang/Exception
  }
  
  /* Error */
  public boolean bк043Aкккк043Aккк(int paramInt, boolean paramBoolean, ddvddv.dvdvdv paramDvdvdv)
  {
    // Byte code:
    //   0: getstatic 167	kkkkkk/ddvddv:bТ0422Т042204220422ТТТТ	I
    //   3: istore_1
    //   4: getstatic 169	kkkkkk/ddvddv:bТТ0422042204220422ТТТТ	I
    //   7: istore 4
    //   9: getstatic 171	kkkkkk/ddvddv:b0422Т0422042204220422ТТТТ	I
    //   12: istore 5
    //   14: iload_1
    //   15: iload 4
    //   17: iload_1
    //   18: iadd
    //   19: imul
    //   20: iload 5
    //   22: irem
    //   23: tableswitch	default:+17->40, 0:+27->50
    //   40: bipush 62
    //   42: putstatic 167	kkkkkk/ddvddv:bТ0422Т042204220422ТТТТ	I
    //   45: bipush 19
    //   47: putstatic 176	kkkkkk/ddvddv:b04220422Т042204220422ТТТТ	I
    //   50: iconst_0
    //   51: ireturn
    //   52: astore_3
    //   53: aload_3
    //   54: athrow
    //   55: astore_3
    //   56: aload_3
    //   57: athrow
    // Local variable table:
    //   start	length	slot	name	signature
    //   0	58	0	this	ddvddv
    //   0	58	1	paramInt	int
    //   0	58	2	paramBoolean	boolean
    //   0	58	3	paramDvdvdv	ddvddv.dvdvdv
    //   7	12	4	i	int
    //   12	11	5	j	int
    // Exception table:
    //   from	to	target	type
    //   40	50	52	java/lang/Exception
    //   0	14	55	java/lang/Exception
  }
  
  public abstract void bкк043A043Aкк043Aккк(@Nonnull jttjjt paramJttjjt)
    throws IllegalArgumentException, IllegalStateException;
  
  public abstract void bкк043Aк043Aк043Aккк(faafaf.aaffaf paramAaffaf);
  
  public abstract faafaa bкк043Aккк043Aккк(faafaf.aaffaf paramAaffaf);
  
  public boolean bккк043Aкк043Aккк(int paramInt, @Nonnull TimeUnit paramTimeUnit)
  {
    int j = (int)paramTimeUnit.toMillis(paramInt);
    int i = j;
    if (j == 0)
    {
      i = j;
      if (paramInt != 0) {
        i = 1;
      }
    }
    switch (1)
    {
    case 0: 
    default: 
      for (;;)
      {
        switch (1)
        {
        }
      }
    }
    paramInt = bТ0422Т042204220422ТТТТ;
    j = bк043A043A043A043Aк043Aк043Aк();
    int k = bТ0422Т042204220422ТТТТ;
    int m = bТ0422Т042204220422ТТТТ;
    switch (m * (bТТ0422042204220422ТТТТ + m) % b043A043A043A043A043Aк043Aк043Aк())
    {
    default: 
      bТ0422Т042204220422ТТТТ = b043Aк043A043A043Aк043Aк043Aк();
      b04220422Т042204220422ТТТТ = b043Aк043A043A043Aк043Aк043Aк();
    }
    if ((paramInt + j) * k % b0422Т0422042204220422ТТТТ != b04220422Т042204220422ТТТТ)
    {
      bТ0422Т042204220422ТТТТ = 68;
      b04220422Т042204220422ТТТТ = 27;
    }
    return bк043Aкккк043Aккк(i, true, ddvddv.dvdvdv.do);
  }
  
  public void bкккк043Aк043Aккк(@Nonnull jttjjt paramJttjjt)
    throws IllegalArgumentException, IllegalStateException
  {
    int j = 0;
    faafaf.aaffaf localAaffaf;
    try
    {
      if (paramJttjjt.bюю044Eюю044E044Eюю044E != null) {
        break label243;
      }
      localAaffaf = null;
      if (localAaffaf != null) {
        break label262;
      }
      throw new IllegalArgumentException(gguuuu.bк043Aккк043Aкк043A043A("\0313:<42l@:i260:~c\f07!+'![})',\034.)", ' ', 'ñ', '\000'));
    }
    catch (Exception paramJttjjt)
    {
      throw paramJttjjt;
    }
    this.bТТТТ04220422ТТТТ = new ffffaa(paramJttjjt.bю044E044Eюю044E044Eюю044E, paramJttjjt.bю044Eююю044E044Eюю044E, paramJttjjt.b044Eюю044Eю044E044Eюю044E);
    Object localObject1 = paramJttjjt.b044E044Eююю044E044Eюю044E;
    int i;
    if (localObject1 != null) {
      i = 0;
    }
    for (;;)
    {
      Object localObject2;
      int k;
      if (i < ((List)localObject1).size())
      {
        localObject2 = (String)((List)localObject1).get(i);
        k = j;
        if (i == 0)
        {
          k = j;
          if (localObject2 != null) {
            k = ((String)localObject2).length();
          }
        }
        if ((localObject2 != null) && (dvdvvd.b043Aккккккк043Aк((String)localObject2)) && (k == ((String)localObject2).length())) {
          break label660;
        }
        fafffa.bкк043Aк043Aк043Aкк043A(b04220422ТТТ0422ТТТТ, gguuuu.bк043Aккк043Aкк043A043A("o\024\033\005\017\013\005?\002\003\017\020\004\002zw\ny3xz~vs|}sw|'\002\003$rpmy\037QE=,)L@8(**\023ScU\017OPOPZ]MK", '', '5', '\000'), new String[] { localObject2 });
        i = bТ0422Т042204220422ТТТТ;
        switch (i * (bТТ0422042204220422ТТТТ + i) % b0422Т0422042204220422ТТТТ)
        {
        default: 
          bТ0422Т042204220422ТТТТ = 23;
          b04220422Т042204220422ТТТТ = b043Aк043A043A043Aк043Aк043Aк();
        }
        this.b0422ТТ0422Т0422ТТТТ.b043Aкккккк043A043Aк(false);
        throw new IllegalArgumentException(gguuuu.bк043Aккк043Aкк043A043A("\003\037(,&&b84e062>\005k\026<E1=;7s8;ILB@D?>RDICVL\023", '-', 'ï', '\001'));
        label243:
        localAaffaf = new faafaf.aaffaf(paramJttjjt.bюю044Eюю044E044Eюю044E.getApplicationContext());
        break;
        label262:
        localObject1 = this.b0422ТТ0422Т0422ТТТТ;
      }
      label538:
      do
      {
        try
        {
          boolean bool = ((ddddvv)localObject1).b043A043A043A043A043A043A043Aк043Aк();
          if (bool) {
            break label538;
          }
          fafffa.b043Aккк043Aк043Aкк043A(b04220422ТТТ0422ТТТТ, gguuuu.bккккк043Aкк043A043A("z%*\034\027\031-R\033\037\031#T\021", '¢', '\003'));
          if ((bТ0422Т042204220422ТТТТ + bТТ0422042204220422ТТТТ) * bТ0422Т042204220422ТТТТ % b0422Т0422042204220422ТТТТ != b04220422Т042204220422ТТТТ)
          {
            bТ0422Т042204220422ТТТТ = 19;
            b04220422Т042204220422ТТТТ = b043Aк043A043A043Aк043Aк043Aк();
          }
          return;
        }
        catch (Exception paramJttjjt)
        {
          throw paramJttjjt;
        }
        fafffa.b043Aккк043Aк043Aкк043A(b04220422ТТТ0422ТТТТ, gguuuu.bк043Aккк043Aкк043A043A("q\022}\016\017\003\007~6~\003|\00799", '½', '¢', '\002'));
        this.b0422Т0422ТТ0422ТТТТ = true;
        localObject1 = this.bТТ04220422Т0422ТТТТ;
        if (localObject1 != null) {
          ((dvvvdv)localObject1).bк043Aк043A043Aк043Aк043Aк();
        }
        this.b0422Т04220422Т0422ТТТТ = localAaffaf;
        this.b042204220422ТТ0422ТТТТ = ((int)bк043Aккк043A043Aк043Aк(paramJttjjt.b044E044E044Eюю044E044Eюю044E, 2147483647L, gguuuu.bккккк043Aкк043A043A("\033\017\022\t\022\027\025", 'l', '\003')));
        localObject2 = localAaffaf.b0422042204220422Т0422042204220422Т.getPackageName();
        localObject2 = new StringBuilder().append((String)localObject2);
        localObject2 = ((StringBuilder)localObject2).append(gguuuu.bк043Aккк043Aкк043A043A("\006v\001", '', 'å', '\001'));
        this.b04220422Т0422Т0422ТТТТ = paramJttjjt.bю044Eююю044E044Eюю044E;
        this.b042204220422Т04220422ТТТТ.set(paramJttjjt.b043A043Aкккккккк());
        new Thread(new ddvddv.1(this, (dvvvdv)localObject1, paramJttjjt, localAaffaf)).start();
        return;
        while (ffffaa.b043A043Aккккккк043A(paramJttjjt.bю044E044Eюю044E044Eюю044E))
        {
          this.b0422ТТ0422Т0422ТТТТ.b043Aкккккк043A043Aк(false);
          paramJttjjt = new IllegalArgumentException(gguuuu.bккккк043Aкк043A043A(">Zcgaa\036so!kqmy@'Qw\001lxvr/v\001\005\001u\n6}\b\f:\002\006\f\006\005\023\022\025\r\023\032F\033\016\034!\021\037", 'ö', '\000'));
          throw paramJttjjt;
          try
          {
            bкк043A043Aкк043Aккк(paramJttjjt);
            if (!ffffaa.b043Aк043Aкккккк043A(paramJttjjt.bю044Eююю044E044Eюю044E))
            {
              this.b0422ТТ0422Т0422ТТТТ.b043Aкккккк043A043Aк(false);
              throw new IllegalArgumentException(gguuuu.bккккк043Aкк043A043A("\0251:>88tJFwBHDP\027}(NWCOMI\006MW[WL`\rT^b\021ae[\025_[", 'N', '\000'));
            }
          }
          catch (RuntimeException paramJttjjt)
          {
            if ((!(paramJttjjt instanceof IllegalStateException)) && (!(paramJttjjt instanceof IllegalArgumentException))) {
              break label658;
            }
            this.b0422ТТ0422Т0422ТТТТ.b043Aкккккк043A043Aк(false);
            throw paramJttjjt;
          }
        }
        this.bТТТ042204220422ТТТТ = b043A043Aкккк043Aккк(paramJttjjt);
      } while (this.bТТТ042204220422ТТТТ != null);
      this.b0422ТТ0422Т0422ТТТТ.b043Aкккккк043A043Aк(false);
      fafffa.b043Aк043Aк043Aк043Aкк043A(b04220422ТТТ0422ТТТТ, gguuuu.bккккк043Aкк043A043A("{\030!%\037\037[1-^)/57%3:0)=/j\03386CDAq6@>;EL\005yDO|RGE\001TLKMZ\007^N\\^U\\\\\017\\Z`^YY5\027He_\\ob\036booulhjx'mr~sq.\005\004z\001z4v\005\007\r\002\016<\024\004\022\024\013\022\022D\025\031G\r\023\036\r\017\032\030\036\030Q\002\037\035*+(\0333Z\035!\"(.(ap7*:\0131<+-82\035\032\030%&#{IHL=\002yOK|!NNGKJ\004THQML^\031", '<', '\001'));
      throw new IllegalStateException(gguuuu.bккккк043Aкк043A043A("Xt}\002{{8\016\n;\006\f\b\024ZA\t\005\016\022\f\fH\036\032K\026\034\"$\022 '\035\026*\034W\b%\00301.", '', '\004'));
      label658:
      label660:
      i += 1;
      j = k;
    }
  }
  
  public static abstract interface dvvvdv
  {
    public abstract vdddvd.vdvdvd b043A043A043Aк043Aк043Aк043Aк();
    
    public abstract void b043A043Aк043A043Aк043Aк043Aк(vdddvd.vdvdvd paramVdvdvd);
    
    public abstract void b043Aкк043A043Aк043Aк043Aк();
    
    public abstract void bк043Aк043A043Aк043Aк043Aк();
    
    public abstract void bккк043A043Aк043Aк043Aк(jttjjt paramJttjjt);
  }
}
