package kkkkkk;

import android.content.ContentResolver;
import com.threatmetrix.TrustDefender.NativeGathererHelper;
import java.util.ArrayList;
import java.util.Arrays;
import java.util.List;
import java.util.Random;
import java.util.concurrent.TimeUnit;
import java.util.concurrent.locks.Lock;
import java.util.concurrent.locks.ReentrantLock;
import javax.annotation.Nonnull;
import javax.annotation.Nullable;

public class dvdddv
{
  private static final Lock b0422042204220422ТТТТТТ;
  public static int b04220422Т04220422ТТТТТ = 0;
  public static int b0422Т042204220422ТТТТТ = 2;
  public static final String bТ042204220422ТТТТТТ;
  public static int bТ0422Т04220422ТТТТТ = 7;
  public static int bТТ042204220422ТТТТТ = 1;
  private static volatile dvdddv bТТТТ0422ТТТТТ;
  public int b042204220422Т0422ТТТТТ = 0;
  @Nullable
  private String[] b04220422ТТ0422ТТТТТ = null;
  public final NativeGathererHelper b0422Т0422Т0422ТТТТТ = new NativeGathererHelper();
  private final Lock b0422ТТ04220422ТТТТТ = new ReentrantLock();
  public boolean b0422ТТТ0422ТТТТТ = false;
  public boolean bТ04220422Т0422ТТТТТ = false;
  private long bТ0422ТТ0422ТТТТТ = 0L;
  @Nullable
  public String[] bТТ0422Т0422ТТТТТ = { gguuuu.bк043Aккк043Aкк043A043A("\036af__OV\027HVU", 'ò', 'á', '\000'), gguuuu.bккккк043Aкк043A043A("\035bidfXa$fiao'\\lm", 'v', '\004') };
  private boolean bТТТ04220422ТТТТТ = false;
  
  static
  {
    if ((bТ0422Т04220422ТТТТТ + bТТ042204220422ТТТТТ) * bТ0422Т04220422ТТТТТ % b0422Т042204220422ТТТТТ != b04220422Т04220422ТТТТТ)
    {
      bТ0422Т04220422ТТТТТ = 42;
      b04220422Т04220422ТТТТТ = 23;
    }
    try
    {
      localObject = fafffa.b043A043A043A043Aкк043Aкк043A(dvdddv.class);
    }
    catch (Exception localException1)
    {
      Object localObject;
      int i;
      throw localException1;
    }
    try
    {
      bТ042204220422ТТТТТТ = (String)localObject;
      localObject = new ReentrantLock();
    }
    catch (Exception localException2)
    {
      throw localException2;
    }
    b0422042204220422ТТТТТТ = (Lock)localObject;
    i = bТ0422Т04220422ТТТТТ;
    switch (i * (bТТ042204220422ТТТТТ + i) % b0422Т042204220422ТТТТТ)
    {
    default: 
      bТ0422Т04220422ТТТТТ = b043Aкккк043Aкк043Aк();
      b04220422Т04220422ТТТТТ = b043Aкккк043Aкк043Aк();
    }
    return;
    switch (1)
    {
    }
    for (;;)
    {
      switch (0)
      {
      }
    }
  }
  
  private dvdddv() {}
  
  public static int b043Aк043Aкк043Aкк043Aк()
  {
    return 0;
  }
  
  public static int b043Aкккк043Aкк043Aк()
  {
    return 60;
  }
  
  /* Error */
  public static dvdddv bк043A043A043Aк043Aкк043Aк()
  {
    // Byte code:
    //   0: getstatic 108	kkkkkk/dvdddv:bТТТТ0422ТТТТТ	Lkkkkkk/dvdddv;
    //   3: astore_0
    //   4: aload_0
    //   5: ifnonnull +68 -> 73
    //   8: getstatic 60	kkkkkk/dvdddv:b0422042204220422ТТТТТТ	Ljava/util/concurrent/locks/Lock;
    //   11: invokeinterface 113 1 0
    //   16: getstatic 39	kkkkkk/dvdddv:bТ0422Т04220422ТТТТТ	I
    //   19: getstatic 41	kkkkkk/dvdddv:bТТ042204220422ТТТТТ	I
    //   22: iadd
    //   23: getstatic 39	kkkkkk/dvdddv:bТ0422Т04220422ТТТТТ	I
    //   26: imul
    //   27: getstatic 43	kkkkkk/dvdddv:b0422Т042204220422ТТТТТ	I
    //   30: irem
    //   31: invokestatic 115	kkkkkk/dvdddv:b043Aк043Aкк043Aкк043Aк	()I
    //   34: if_icmpeq +13 -> 47
    //   37: bipush 13
    //   39: putstatic 39	kkkkkk/dvdddv:bТ0422Т04220422ТТТТТ	I
    //   42: bipush 44
    //   44: putstatic 45	kkkkkk/dvdddv:b04220422Т04220422ТТТТТ	I
    //   47: getstatic 108	kkkkkk/dvdddv:bТТТТ0422ТТТТТ	Lkkkkkk/dvdddv;
    //   50: ifnonnull +13 -> 63
    //   53: new 2	kkkkkk/dvdddv
    //   56: dup
    //   57: invokespecial 116	kkkkkk/dvdddv:<init>	()V
    //   60: putstatic 108	kkkkkk/dvdddv:bТТТТ0422ТТТТТ	Lkkkkkk/dvdddv;
    //   63: getstatic 60	kkkkkk/dvdddv:b0422042204220422ТТТТТТ	Ljava/util/concurrent/locks/Lock;
    //   66: astore_0
    //   67: aload_0
    //   68: invokeinterface 119 1 0
    //   73: getstatic 108	kkkkkk/dvdddv:bТТТТ0422ТТТТТ	Lkkkkkk/dvdddv;
    //   76: areturn
    //   77: astore_0
    //   78: getstatic 60	kkkkkk/dvdddv:b0422042204220422ТТТТТТ	Ljava/util/concurrent/locks/Lock;
    //   81: invokeinterface 119 1 0
    //   86: aload_0
    //   87: athrow
    //   88: astore_0
    //   89: aload_0
    //   90: athrow
    //   91: astore_0
    //   92: aload_0
    //   93: athrow
    // Local variable table:
    //   start	length	slot	name	signature
    //   3	65	0	localObject1	Object
    //   77	10	0	localObject2	Object
    //   88	2	0	localException1	Exception
    //   91	2	0	localException2	Exception
    // Exception table:
    //   from	to	target	type
    //   8	16	77	finally
    //   47	63	77	finally
    //   0	4	88	java/lang/Exception
    //   67	73	88	java/lang/Exception
    //   86	88	88	java/lang/Exception
    //   63	67	91	java/lang/Exception
    //   73	77	91	java/lang/Exception
    //   78	86	91	java/lang/Exception
  }
  
  public static int bк043Aккк043Aкк043Aк()
  {
    return 1;
  }
  
  public static int bкк043Aкк043Aкк043Aк()
  {
    return 2;
  }
  
  public final int b043A043A043A043A043A043Aкк043Aк()
  {
    throw new Runtime("d2j fail translate: java.lang.IndexOutOfBoundsException: fromIndex < 0: -1\n\tat java.util.BitSet.nextSetBit(BitSet.java:712)\n\tat com.googlecode.dex2jar.ir.ts.array.FillArrayTransformer.makeSureAllElementAreAssigned(FillArrayTransformer.java:505)\n\tat com.googlecode.dex2jar.ir.ts.array.FillArrayTransformer.transformReportChanged(FillArrayTransformer.java:123)\n\tat com.googlecode.dex2jar.ir.ts.StatedTransformer.transform(StatedTransformer.java:10)\n\tat com.googlecode.d2j.dex.Dex2jar$2.optimize(Dex2jar.java:149)\n\tat com.googlecode.d2j.dex.Dex2Asm.convertCode(Dex2Asm.java:414)\n\tat com.googlecode.d2j.dex.ExDex2Asm.convertCode(ExDex2Asm.java:42)\n\tat com.googlecode.d2j.dex.Dex2jar$2.convertCode(Dex2jar.java:128)\n\tat com.googlecode.d2j.dex.Dex2Asm.convertMethod(Dex2Asm.java:509)\n\tat com.googlecode.d2j.dex.Dex2Asm.convertClass(Dex2Asm.java:406)\n\tat com.googlecode.d2j.dex.Dex2Asm.convertDex(Dex2Asm.java:422)\n\tat com.googlecode.d2j.dex.Dex2jar.doTranslate(Dex2jar.java:172)\n\tat com.googlecode.d2j.dex.Dex2jar.to(Dex2jar.java:272)\n\tat com.googlecode.dex2jar.tools.Dex2jarCmd.doCommandLine(Dex2jarCmd.java:108)\n\tat com.googlecode.dex2jar.tools.BaseCmd.doMain(BaseCmd.java:288)\n\tat com.googlecode.dex2jar.tools.Dex2jarCmd.main(Dex2jarCmd.java:32)\n");
  }
  
  @Nullable
  public final String b043A043A043A043Aк043Aкк043Aк(@Nullable String paramString)
    throws InterruptedException
  {
    for (;;)
    {
      try
      {
        if ((!this.b0422ТТТ0422ТТТТТ) || (paramString == null)) {
          break label220;
        }
        paramString = this.b0422Т0422Т0422ТТТТТ.hashFile(paramString);
      }
      catch (Throwable paramString)
      {
        String str1 = bТ042204220422ТТТТТТ;
        int i = bТ0422Т04220422ТТТТТ;
        switch (i * (bк043Aккк043Aкк043Aк() + i) % b0422Т042204220422ТТТТТ)
        {
        default: 
          bТ0422Т04220422ТТТТТ = 13;
          b04220422Т04220422ТТТТТ = b043Aкккк043Aкк043Aк();
          if ((bТ0422Т04220422ТТТТТ + bк043Aккк043Aкк043Aк()) * bТ0422Т04220422ТТТТТ % b0422Т042204220422ТТТТТ != b04220422Т04220422ТТТТТ)
          {
            bТ0422Т04220422ТТТТТ = b043Aкккк043Aкк043Aк();
            b04220422Т04220422ТТТТТ = 62;
          }
          break;
        }
        switch (1)
        {
        case 0: 
        default: 
          switch (1)
          {
          }
          break;
        }
        String str2 = gguuuu.bк043Aккк043Aкк043A043A("o\004\030\016\034\fG\f\031\017\021f", ':', '\031', '\001');
        fafffa.bкк043A043Aкк043Aкк043A(str1, str2, paramString);
        paramString = null;
        continue;
      }
      catch (Exception paramString)
      {
        throw paramString;
      }
      if (Thread.interrupted())
      {
        paramString = bТ042204220422ТТТТТТ;
        try
        {
          fafffa.b043Aккк043Aк043Aкк043A(paramString, gguuuu.bк043Aккк043Aкк043A043A("\002\025\036\020\013\rG\020\024\031\t\025\024\026\020\023=\001\001\017~{\f{y@3\007y\003~\006vzr", '´', 'b', '\000'));
          throw new InterruptedException();
        }
        catch (Exception paramString)
        {
          throw paramString;
        }
      }
      return paramString;
      label220:
      paramString = null;
    }
  }
  
  public final int b043A043A043Aк043A043Aкк043Aк(@Nonnull faafaf.aaffaf paramAaffaf, int paramInt1, int paramInt2, int paramInt3)
    throws InterruptedException
  {
    for (;;)
    {
      try
      {
        if (!this.b0422ТТТ0422ТТТТТ) {
          continue;
        }
        Object localObject = null;
        if ((!this.bТТТ04220422ТТТТТ) || ((paramInt1 & 0x10) != 0))
        {
          paramAaffaf = paramAaffaf.b0422042204220422Т0422042204220422Т;
          if ((this.b04220422ТТ0422ТТТТТ == null) || (TimeUnit.SECONDS.convert(System.nanoTime() - this.bТ0422ТТ0422ТТТТТ, TimeUnit.NANOSECONDS) >= 60L)) {
            continue;
          }
          localObject = this.b04220422ТТ0422ТТТТТ;
          paramAaffaf = (faafaf.aaffaf)localObject;
          if ((bТ0422Т04220422ТТТТТ + bТТ042204220422ТТТТТ) * bТ0422Т04220422ТТТТТ % b0422Т042204220422ТТТТТ != b04220422Т04220422ТТТТТ)
          {
            int i = bТ0422Т04220422ТТТТТ;
            switch (i * (bТТ042204220422ТТТТТ + i) % b0422Т042204220422ТТТТТ)
            {
            default: 
              bТ0422Т04220422ТТТТТ = 23;
              b04220422Т04220422ТТТТТ = 91;
            }
            bТ0422Т04220422ТТТТТ = 59;
            b04220422Т04220422ТТТТТ = b043Aкккк043Aкк043Aк();
            paramAaffaf = (faafaf.aaffaf)localObject;
          }
          this.bТТ0422Т0422ТТТТТ = paramAaffaf;
          localObject = paramAaffaf;
        }
        if (!this.bТТТ04220422ТТТТТ)
        {
          this.b0422Т0422Т0422ТТТТТ.initPackageManager();
          this.bТТТ04220422ТТТТТ = true;
        }
        paramInt1 = this.b0422Т0422Т0422ТТТТТ.findPackages((String[])localObject, paramInt2, paramInt3, paramInt1);
      }
      catch (Throwable paramAaffaf)
      {
        fafffa.bкк043A043Aкк043Aкк043A(bТ042204220422ТТТТТТ, gguuuu.bк043Aккк043Aкк043A043A("N`rfr`\032\\g[[/", '#', '¢', '\000'), paramAaffaf);
        paramInt1 = 0;
        continue;
      }
      if (!Thread.interrupted()) {
        return paramInt1;
      }
      fafffa.b043Aккк043Aк043Aкк043A(bТ042204220422ТТТТТТ, gguuuu.bк043Aккк043Aкк043A043A("AT]OJL\007OSXHTSUOR|@@N>;K;9rF9B>E6:2", '', '\005', '\000'));
      throw new InterruptedException();
      fafffa.b043Aккк043Aк043Aкк043A(bТ042204220422ТТТТТТ, gguuuu.bккккк043Aкк043A043A("t\027\005\027\032\020\026\020I\033\r!\026N\026\032 \027S\033%)W\032*&", 'Ï', '\004'));
      this.bТ0422ТТ0422ТТТТТ = System.nanoTime();
      paramAaffaf = new tttjtt.tjjttt(new tttjtt(), paramAaffaf).bкк043A043A043Aк043Aккк();
      fafffa.b043Aккк043Aк043Aкк043A(bТ042204220422ТТТТТТ, gguuuu.bккккк043Aкк043A043A("\024\026\032\017jxrv\007\031\f\026A\007\017\024\f\001;T9", '¨', '\003') + paramAaffaf.size());
      this.b04220422ТТ0422ТТТТТ = ((String[])paramAaffaf.toArray(new String[paramAaffaf.size()]));
      paramAaffaf = this.b04220422ТТ0422ТТТТТ;
    }
    return paramInt1;
  }
  
  @Nullable
  public final String[] b043A043A043Aкк043Aкк043Aк()
    throws InterruptedException
  {
    Object localObject3 = null;
    Object localObject1 = localObject3;
    try
    {
      if (this.b0422ТТТ0422ТТТТТ) {
        localObject1 = this.b0422Т0422Т0422ТТТТТ.getNetworkInfo();
      }
      if (Thread.interrupted())
      {
        fafffa.b043Aккк043Aк043Aкк043A(bТ042204220422ТТТТТТ, gguuuu.bккккк043Aкк043A043A("~\022\033\r\b\nD\r\021\026\006\022\021\023\r\020:}}\f{x\txv=0\004v{\003swo", 'j', '\003'));
        throw new InterruptedException();
      }
    }
    catch (Throwable localThrowable)
    {
      Object localObject2;
      for (;;)
      {
        String str = bТ042204220422ТТТТТТ;
        int i = bТ0422Т04220422ТТТТТ;
        int j = bТТ042204220422ТТТТТ;
        int k = bТ0422Т04220422ТТТТТ;
        int m = b0422Т042204220422ТТТТТ;
        if ((b043Aкккк043Aкк043Aк() + bТТ042204220422ТТТТТ) * b043Aкккк043Aкк043Aк() % b0422Т042204220422ТТТТТ != b04220422Т04220422ТТТТТ)
        {
          bТ0422Т04220422ТТТТТ = 49;
          b04220422Т04220422ТТТТТ = 58;
        }
        if ((i + j) * k % m != b04220422Т04220422ТТТТТ)
        {
          bТ0422Т04220422ТТТТТ = 9;
          b04220422Т04220422ТТТТТ = 89;
        }
        fafffa.bкк043A043Aкк043Aкк043A(str, gguuuu.bк043Aккк043Aкк043A043A("/ASGSAz=H<<\020", '\036', '\001', '\002'), localThrowable);
        localObject2 = localObject3;
      }
      return localObject2;
    }
  }
  
  @Nullable
  public final String[] b043A043Aк043A043A043Aкк043Aк(short[] paramArrayOfShort)
  {
    try
    {
      if (this.b0422ТТТ0422ТТТТТ)
      {
        paramArrayOfShort = this.b0422Т0422Т0422ТТТТТ.findPermissions(paramArrayOfShort);
        return paramArrayOfShort;
      }
    }
    catch (Throwable paramArrayOfShort)
    {
      do
      {
        fafffa.bкк043A043Aкк043Aкк043A(bТ042204220422ТТТТТТ, gguuuu.bк043Aккк043Aкк043A043A("5GYMYG\001CNBB\026", '.', 'é', '\002'), paramArrayOfShort);
        paramArrayOfShort = null;
      } while ((bТ0422Т04220422ТТТТТ + bк043Aккк043Aкк043Aк()) * bТ0422Т04220422ТТТТТ % b0422Т042204220422ТТТТТ == b04220422Т04220422ТТТТТ);
      bТ0422Т04220422ТТТТТ = 60;
      b04220422Т04220422ТТТТТ = b043Aкккк043Aкк043Aк();
    }
    return null;
  }
  
  @Nullable
  public final String b043A043Aк043Aк043Aкк043Aк(@Nullable byte[] paramArrayOfByte)
    throws InterruptedException
  {
    for (;;)
    {
      try
      {
        if ((!this.b0422ТТТ0422ТТТТТ) || (paramArrayOfByte == null)) {
          break label160;
        }
        paramArrayOfByte = this.b0422Т0422Т0422ТТТТТ.sha1(paramArrayOfByte);
      }
      catch (Exception paramArrayOfByte)
      {
        throw paramArrayOfByte;
      }
      catch (Throwable paramArrayOfByte)
      {
        try
        {
          fafffa.bкк043A043Aкк043Aкк043A(bТ042204220422ТТТТТТ, gguuuu.bк043Aккк043Aкк043A043A(">PbVbP\nLWKK\037", 'N', 'À', '\002'), paramArrayOfByte);
          int i = bТ0422Т04220422ТТТТТ;
          switch (i * (bТТ042204220422ТТТТТ + i) % b0422Т042204220422ТТТТТ)
          {
          default: 
            bТ0422Т04220422ТТТТТ = 13;
            b04220422Т04220422ТТТТТ = 47;
            paramArrayOfByte = null;
          }
        }
        catch (Exception paramArrayOfByte)
        {
          throw paramArrayOfByte;
        }
      }
      if (Thread.interrupted())
      {
        fafffa.b043Aккк043Aк043Aкк043A(bТ042204220422ТТТТТТ, gguuuu.bк043Aккк043Aкк043A043A("dy\005xuy6\001\007\016\016\017\023\017\024@\006\b\030\n\t\033\r\rUJ \025 \036'\032 \032", 'm', '"', '\003'));
        paramArrayOfByte = new InterruptedException();
        if ((bТ0422Т04220422ТТТТТ + bТТ042204220422ТТТТТ) * bТ0422Т04220422ТТТТТ % b0422Т042204220422ТТТТТ != b04220422Т04220422ТТТТТ)
        {
          bТ0422Т04220422ТТТТТ = b043Aкккк043Aкк043Aк();
          b04220422Т04220422ТТТТТ = 0;
        }
        throw paramArrayOfByte;
      }
      return paramArrayOfByte;
      label160:
      paramArrayOfByte = null;
    }
  }
  
  @Nullable
  public final byte[] b043A043Aкк043A043Aкк043Aк(byte[] paramArrayOfByte, ContentResolver paramContentResolver)
  {
    try
    {
      if (!this.b0422ТТТ0422ТТТТТ) {
        break label88;
      }
      localNativeGathererHelper = this.b0422Т0422Т0422ТТТТТ;
    }
    catch (Throwable paramArrayOfByte)
    {
      label88:
      do
      {
        NativeGathererHelper localNativeGathererHelper;
        int i;
        fafffa.bкк043A043Aкк043Aкк043A(bТ042204220422ТТТТТТ, gguuuu.bк043Aккк043Aкк043A043A("\017!3'3!Z\035(\034\034o", '2', '', '\002'), paramArrayOfByte);
        paramContentResolver = null;
        paramArrayOfByte = paramContentResolver;
      } while ((b043Aкккк043Aкк043Aк() + bТТ042204220422ТТТТТ) * b043Aкккк043Aкк043Aк() % b0422Т042204220422ТТТТТ == b04220422Т04220422ТТТТТ);
      bТ0422Т04220422ТТТТТ = 94;
      b04220422Т04220422ТТТТТ = b043Aкккк043Aкк043Aк();
      paramArrayOfByte = paramContentResolver;
      switch (0)
      {
      }
      for (;;)
      {
        paramArrayOfByte = paramContentResolver;
        switch (1)
        {
        }
      }
      switch (0)
      {
      }
    }
    paramArrayOfByte = localNativeGathererHelper.sign(paramArrayOfByte, paramContentResolver);
    i = bТ0422Т04220422ТТТТТ;
    switch (i * (bк043Aккк043Aкк043Aк() + i) % b0422Т042204220422ТТТТТ)
    {
    default: 
      bТ0422Т04220422ТТТТТ = 38;
      b04220422Т04220422ТТТТТ = 78;
    }
    return paramArrayOfByte;
    for (;;)
    {
      switch (1)
      {
      }
    }
  }
  
  @Nullable
  public final vdddvd.dvddvd b043A043Aккк043Aкк043Aк()
    throws InterruptedException
  {
    for (;;)
    {
      try
      {
        if (!this.b0422ТТТ0422ТТТТТ) {
          break label212;
        }
        i = this.b0422Т0422Т0422ТТТТТ.getSelinuxMode();
        if (i < 0) {
          if (i > 4) {
            break label212;
          }
        }
      }
      catch (Throwable localThrowable)
      {
        vdddvd.dvddvd localDvddvd;
        str1 = bТ042204220422ТТТТТТ;
        i = bТ0422Т04220422ТТТТТ;
        switch (i * (bТТ042204220422ТТТТТ + i) % b0422Т042204220422ТТТТТ)
        {
        default: 
          bТ0422Т04220422ТТТТТ = b043Aкккк043Aкк043Aк();
          b04220422Т04220422ТТТТТ = 15;
        }
        str2 = gguuuu.bккккк043Aкк043A043A("m\002\026\f\032\nE\n\027\r\017d", 'Î', '\004');
      }
      catch (Exception localException3)
      {
        try
        {
          String str1;
          String str2;
          int i = bТ0422Т04220422ТТТТТ;
          int j = bк043Aккк043Aкк043Aк();
          int k = b0422Т042204220422ТТТТТ;
          switch (i * (j + i) % k)
          {
          default: 
            bТ0422Т04220422ТТТТТ = b043Aкккк043Aкк043Aк();
            b04220422Т04220422ТТТТТ = b043Aкккк043Aкк043Aк();
          }
          fafffa.bкк043A043Aкк043Aкк043A(str1, str2, localThrowable);
          Object localObject1 = null;
        }
        catch (Exception localException4)
        {
          throw localException4;
        }
        localException3 = localException3;
        throw localException3;
      }
      try
      {
        localDvddvd = vdddvd.dvddvd.values()[i];
        if (Thread.interrupted())
        {
          fafffa.b043Aккк043Aк043Aкк043A(bТ042204220422ТТТТТТ, gguuuu.bккккк043Aкк043A043A("r\006\017\001{}8\001\005\ny\006\005\007\001\004.qqol|lj1$wjsovgkc", 'p', '\003'));
          throw new InterruptedException();
        }
      }
      catch (Exception localException1)
      {
        try
        {
          throw localException1;
        }
        catch (Exception localException2)
        {
          throw localException2;
        }
      }
      return localException4;
      label212:
      Object localObject2 = null;
    }
  }
  
  @Nullable
  public final String b043Aк043A043A043A043Aкк043Aк(int paramInt)
    throws InterruptedException
  {
    localObject3 = null;
    Object localObject1 = localObject3;
    try
    {
      if (this.b0422ТТТ0422ТТТТТ)
      {
        localObject1 = localObject3;
        if (paramInt > 0) {
          localObject1 = this.b0422Т0422Т0422ТТТТТ.getRandomString(paramInt);
        }
      }
    }
    catch (Throwable localThrowable)
    {
      Object localObject2;
      for (;;)
      {
        String str = bТ042204220422ТТТТТТ;
        if ((bТ0422Т04220422ТТТТТ + bТТ042204220422ТТТТТ) * bТ0422Т04220422ТТТТТ % b0422Т042204220422ТТТТТ != b04220422Т04220422ТТТТТ)
        {
          bТ0422Т04220422ТТТТТ = b043Aкккк043Aкк043Aк();
          b04220422Т04220422ТТТТТ = b043Aкккк043Aкк043Aк();
        }
        fafffa.bкк043A043Aкк043Aкк043A(str, gguuuu.bк043Aккк043Aкк043A043A("\033/C9G7r7D:<\022", 'Í', '\002', '\001'), localThrowable);
        localObject2 = localObject3;
        if ((b043Aкккк043Aкк043Aк() + bТТ042204220422ТТТТТ) * b043Aкккк043Aкк043Aк() % b0422Т042204220422ТТТТТ != b04220422Т04220422ТТТТТ)
        {
          bТ0422Т04220422ТТТТТ = b043Aкккк043Aкк043Aк();
          b04220422Т04220422ТТТТТ = b043Aкккк043Aкк043Aк();
          localObject2 = localObject3;
        }
      }
      return localObject2;
    }
    if (Thread.interrupted())
    {
      fafffa.b043Aккк043Aк043Aкк043A(bТ042204220422ТТТТТТ, gguuuu.bккккк043Aкк043A043A("Tithei&pv}o}~\003~\0040uw\byx\013||E:\020\005\020\016\027\n\020\n", '', '\000'));
      throw new InterruptedException();
    }
  }
  
  /* Error */
  @Nonnull
  public final String b043Aк043A043Aк043Aкк043Aк()
  {
    // Byte code:
    //   0: aload_0
    //   1: getfield 96	kkkkkk/dvdddv:b0422ТТТ0422ТТТТТ	Z
    //   4: ifeq +159 -> 163
    //   7: aload_0
    //   8: getfield 103	kkkkkk/dvdddv:b0422Т0422Т0422ТТТТТ	Lcom/threatmetrix/TrustDefender/NativeGathererHelper;
    //   11: invokevirtual 302	com/threatmetrix/TrustDefender/NativeGathererHelper:jniDetectedDebugStatus	()I
    //   14: istore_1
    //   15: iconst_m1
    //   16: iload_1
    //   17: if_icmpne +9 -> 26
    //   20: ldc_w 304
    //   23: astore_3
    //   24: aload_3
    //   25: areturn
    //   26: iload_1
    //   27: ifle +186 -> 213
    //   30: iconst_1
    //   31: istore_2
    //   32: iconst_1
    //   33: tableswitch	default:+23->56, 0:+-1->32, 1:+50->83
    //   56: iconst_0
    //   57: tableswitch	default:+23->80, 0:+26->83, 1:+-25->32
    //   80: goto -24 -> 56
    //   83: iload_2
    //   84: invokestatic 308	java/lang/String:valueOf	(Z)Ljava/lang/String;
    //   87: astore 4
    //   89: getstatic 39	kkkkkk/dvdddv:bТ0422Т04220422ТТТТТ	I
    //   92: istore_1
    //   93: aload 4
    //   95: astore_3
    //   96: iload_1
    //   97: getstatic 41	kkkkkk/dvdddv:bТТ042204220422ТТТТТ	I
    //   100: iload_1
    //   101: iadd
    //   102: imul
    //   103: getstatic 43	kkkkkk/dvdddv:b0422Т042204220422ТТТТТ	I
    //   106: irem
    //   107: tableswitch	default:+17->124, 0:+-83->24
    //   124: invokestatic 64	kkkkkk/dvdddv:b043Aкккк043Aкк043Aк	()I
    //   127: putstatic 39	kkkkkk/dvdddv:bТ0422Т04220422ТТТТТ	I
    //   130: bipush 93
    //   132: putstatic 45	kkkkkk/dvdddv:b04220422Т04220422ТТТТТ	I
    //   135: aload 4
    //   137: areturn
    //   138: astore_3
    //   139: getstatic 53	kkkkkk/dvdddv:bТ042204220422ТТТТТТ	Ljava/lang/String;
    //   142: astore 4
    //   144: ldc_w 310
    //   147: bipush 17
    //   149: iconst_3
    //   150: invokestatic 88	kkkkkk/gguuuu:bккккк043Aкк043A043A	(Ljava/lang/String;CC)Ljava/lang/String;
    //   153: astore 5
    //   155: aload 4
    //   157: aload 5
    //   159: aload_3
    //   160: invokestatic 161	kkkkkk/fafffa:bкк043A043Aкк043Aкк043A	(Ljava/lang/String;Ljava/lang/String;Ljava/lang/Throwable;)V
    //   163: invokestatic 64	kkkkkk/dvdddv:b043Aкккк043Aкк043Aк	()I
    //   166: istore_1
    //   167: iload_1
    //   168: getstatic 41	kkkkkk/dvdddv:bТТ042204220422ТТТТТ	I
    //   171: iload_1
    //   172: iadd
    //   173: imul
    //   174: getstatic 43	kkkkkk/dvdddv:b0422Т042204220422ТТТТТ	I
    //   177: irem
    //   178: tableswitch	default:+18->196, 0:+46->224
    //   196: invokestatic 64	kkkkkk/dvdddv:b043Aкккк043Aкк043Aк	()I
    //   199: putstatic 39	kkkkkk/dvdddv:bТ0422Т04220422ТТТТТ	I
    //   202: invokestatic 64	kkkkkk/dvdddv:b043Aкккк043Aкк043Aк	()I
    //   205: putstatic 45	kkkkkk/dvdddv:b04220422Т04220422ТТТТТ	I
    //   208: iconst_m1
    //   209: istore_1
    //   210: goto -195 -> 15
    //   213: iconst_0
    //   214: istore_2
    //   215: goto -183 -> 32
    //   218: astore_3
    //   219: aload_3
    //   220: athrow
    //   221: astore_3
    //   222: aload_3
    //   223: athrow
    //   224: iconst_m1
    //   225: istore_1
    //   226: goto -211 -> 15
    // Local variable table:
    //   start	length	slot	name	signature
    //   0	229	0	this	dvdddv
    //   14	212	1	i	int
    //   31	184	2	bool	boolean
    //   23	73	3	localObject	Object
    //   138	22	3	localThrowable	Throwable
    //   218	2	3	localException1	Exception
    //   221	2	3	localException2	Exception
    //   87	69	4	str1	String
    //   153	5	5	str2	String
    // Exception table:
    //   from	to	target	type
    //   0	15	138	java/lang/Throwable
    //   0	15	218	java/lang/Exception
    //   155	163	218	java/lang/Exception
    //   139	155	221	java/lang/Exception
  }
  
  /* Error */
  @Nullable
  public final afffaf.aaaaff[] b043Aк043Aк043A043Aкк043Aк()
  {
    // Byte code:
    //   0: aload_0
    //   1: getfield 96	kkkkkk/dvdddv:b0422ТТТ0422ТТТТТ	Z
    //   4: ifeq +19 -> 23
    //   7: aload_0
    //   8: getfield 103	kkkkkk/dvdddv:b0422Т0422Т0422ТТТТТ	Lcom/threatmetrix/TrustDefender/NativeGathererHelper;
    //   11: ldc_w 314
    //   14: invokevirtual 318	com/threatmetrix/TrustDefender/NativeGathererHelper:getAddresses	(Ljava/lang/Class;)Ljava/lang/Object;
    //   17: checkcast 320	[Lkkkkkk/afffaf$aaaaff;
    //   20: astore_2
    //   21: aload_2
    //   22: areturn
    //   23: aload_0
    //   24: getfield 72	kkkkkk/dvdddv:bТТТ04220422ТТТТТ	Z
    //   27: ifeq +151 -> 178
    //   30: new 314	kkkkkk/afffaf$aaaaff
    //   33: dup
    //   34: aload_0
    //   35: iconst_1
    //   36: invokevirtual 322	kkkkkk/dvdddv:b043Aк043A043A043A043Aкк043Aк	(I)Ljava/lang/String;
    //   39: aload_0
    //   40: iconst_1
    //   41: invokevirtual 322	kkkkkk/dvdddv:b043Aк043A043A043A043Aкк043Aк	(I)Ljava/lang/String;
    //   44: ldc_w 304
    //   47: invokestatic 328	java/net/InetAddress:getAllByName	(Ljava/lang/String;)[Ljava/net/InetAddress;
    //   50: invokespecial 331	kkkkkk/afffaf$aaaaff:<init>	(Ljava/lang/String;Ljava/lang/String;[Ljava/net/InetAddress;)V
    //   53: astore_2
    //   54: getstatic 39	kkkkkk/dvdddv:bТ0422Т04220422ТТТТТ	I
    //   57: istore_1
    //   58: iload_1
    //   59: getstatic 41	kkkkkk/dvdddv:bТТ042204220422ТТТТТ	I
    //   62: iload_1
    //   63: iadd
    //   64: imul
    //   65: getstatic 43	kkkkkk/dvdddv:b0422Т042204220422ТТТТТ	I
    //   68: irem
    //   69: tableswitch	default:+19->88, 0:+31->100
    //   88: invokestatic 64	kkkkkk/dvdddv:b043Aкккк043Aкк043Aк	()I
    //   91: putstatic 39	kkkkkk/dvdddv:bТ0422Т04220422ТТТТТ	I
    //   94: invokestatic 64	kkkkkk/dvdddv:b043Aкккк043Aкк043Aк	()I
    //   97: putstatic 45	kkkkkk/dvdddv:b04220422Т04220422ТТТТТ	I
    //   100: iconst_1
    //   101: anewarray 314	kkkkkk/afffaf$aaaaff
    //   104: dup
    //   105: iconst_0
    //   106: aload_2
    //   107: aastore
    //   108: areturn
    //   109: astore_2
    //   110: getstatic 53	kkkkkk/dvdddv:bТ042204220422ТТТТТТ	Ljava/lang/String;
    //   113: astore_3
    //   114: ldc_w 333
    //   117: bipush 120
    //   119: iconst_3
    //   120: invokestatic 88	kkkkkk/gguuuu:bккккк043Aкк043A043A	(Ljava/lang/String;CC)Ljava/lang/String;
    //   123: astore 4
    //   125: aload_3
    //   126: aload 4
    //   128: aload_2
    //   129: invokestatic 161	kkkkkk/fafffa:bкк043A043Aкк043Aкк043A	(Ljava/lang/String;Ljava/lang/String;Ljava/lang/Throwable;)V
    //   132: getstatic 39	kkkkkk/dvdddv:bТ0422Т04220422ТТТТТ	I
    //   135: istore_1
    //   136: iload_1
    //   137: getstatic 41	kkkkkk/dvdddv:bТТ042204220422ТТТТТ	I
    //   140: iload_1
    //   141: iadd
    //   142: imul
    //   143: getstatic 43	kkkkkk/dvdddv:b0422Т042204220422ТТТТТ	I
    //   146: irem
    //   147: tableswitch	default:+17->164, 0:+39->186
    //   164: invokestatic 64	kkkkkk/dvdddv:b043Aкккк043Aкк043Aк	()I
    //   167: putstatic 39	kkkkkk/dvdddv:bТ0422Т04220422ТТТТТ	I
    //   170: invokestatic 64	kkkkkk/dvdddv:b043Aкккк043Aкк043Aк	()I
    //   173: putstatic 45	kkkkkk/dvdddv:b04220422Т04220422ТТТТТ	I
    //   176: aconst_null
    //   177: areturn
    //   178: aconst_null
    //   179: areturn
    //   180: astore_2
    //   181: aload_2
    //   182: athrow
    //   183: astore_2
    //   184: aload_2
    //   185: athrow
    //   186: aconst_null
    //   187: areturn
    // Local variable table:
    //   start	length	slot	name	signature
    //   0	188	0	this	dvdddv
    //   57	86	1	i	int
    //   20	87	2	localObject	Object
    //   109	20	2	localThrowable	Throwable
    //   180	2	2	localException1	Exception
    //   183	2	2	localException2	Exception
    //   113	13	3	str1	String
    //   123	4	4	str2	String
    // Exception table:
    //   from	to	target	type
    //   0	21	109	java/lang/Throwable
    //   23	30	109	java/lang/Throwable
    //   30	54	109	java/lang/Throwable
    //   0	21	180	java/lang/Exception
    //   30	54	180	java/lang/Exception
    //   110	125	180	java/lang/Exception
    //   23	30	183	java/lang/Exception
    //   125	132	183	java/lang/Exception
  }
  
  @Nullable
  public final String b043Aкк043A043A043Aкк043Aк(@Nullable String paramString1, @Nullable String paramString2)
    throws InterruptedException
  {
    Object localObject2 = null;
    Object localObject1 = localObject2;
    try
    {
      if (!this.b0422ТТТ0422ТТТТТ) {
        break label168;
      }
      localObject1 = localObject2;
      if (paramString2 == null) {
        break label168;
      }
      localObject1 = localObject2;
      if (paramString1 == null) {
        break label168;
      }
      int i = paramString2.length();
      localObject1 = localObject2;
      if (i <= 0) {
        break label168;
      }
      switch (1)
      {
      case 0: 
      default: 
        for (;;)
        {
          switch (0)
          {
          }
        }
      }
      i = b043Aкккк043Aкк043Aк();
      switch (i * (bТТ042204220422ТТТТТ + i) % b0422Т042204220422ТТТТТ)
      {
      default: 
        bТ0422Т04220422ТТТТТ = b043Aкккк043Aкк043Aк();
        b04220422Т04220422ТТТТТ = 48;
      }
      localObject1 = localObject2;
      if (paramString1.isEmpty()) {
        break label168;
      }
      localObject1 = this.b0422Т0422Т0422ТТТТТ;
    }
    catch (Throwable paramString1)
    {
      for (;;)
      {
        fafffa.bкк043A043Aкк043Aкк043A(bТ042204220422ТТТТТТ, gguuuu.bккккк043Aкк043A043A("ASeYeS\rOZNN\"", 'Å', '\003'), paramString1);
        localObject1 = localObject2;
      }
    }
    localObject1 = ((NativeGathererHelper)localObject1).xor(paramString1, paramString2);
    label168:
    if (Thread.interrupted())
    {
      fafffa.b043Aккк043Aк043Aкк043A(bТ042204220422ТТТТТТ, gguuuu.bк043Aккк043Aкк043A043A("p\004\r~y{6~\003\bw\004\003\005~\002,oo}mjzjh/\"uhqmteia", 'Å', '\035', '\002'));
      paramString1 = new InterruptedException();
      if ((bТ0422Т04220422ТТТТТ + bТТ042204220422ТТТТТ) * bТ0422Т04220422ТТТТТ % b0422Т042204220422ТТТТТ != b043Aк043Aкк043Aкк043Aк())
      {
        bТ0422Т04220422ТТТТТ = b043Aкккк043Aкк043Aк();
        b04220422Т04220422ТТТТТ = b043Aкккк043Aкк043Aк();
      }
      throw paramString1;
    }
    return localObject1;
    switch (1)
    {
    }
    for (;;)
    {
      switch (0)
      {
      }
    }
  }
  
  @Nullable
  public final ffafff[] b043Aкк043Aк043Aкк043Aк()
    throws InterruptedException
  {
    try
    {
      if (this.b0422ТТТ0422ТТТТТ) {
        ffafff[] arrayOfFfafff1 = (ffafff[])this.b0422Т0422Т0422ТТТТТ.findRunningProcs(ffafff.class);
      }
    }
    catch (Exception localException1)
    {
      try
      {
        bool = Thread.interrupted();
        if (!bool) {
          break label276;
        }
        fafffa.b043Aккк043Aк043Aкк043A(bТ042204220422ТТТТТТ, gguuuu.bккккк043Aкк043A043A("=R]QNR\017Y_fXfgkgl\031^`pbasee.#xmxvrxr", 'ç', '\000'));
        throw new InterruptedException();
      }
      catch (Exception localException2)
      {
        boolean bool;
        int i;
        int j;
        int k;
        int m;
        Object localObject1;
        String str1;
        String str2;
        long l;
        Object localObject2;
        throw localException2;
      }
      localException1 = localException1;
      throw localException1;
      i = bТ0422Т04220422ТТТТТ;
      j = bТТ042204220422ТТТТТ;
      k = b0422Т042204220422ТТТТТ;
      m = bТ0422Т04220422ТТТТТ;
      switch (m * (bТТ042204220422ТТТТТ + m) % b0422Т042204220422ТТТТТ)
      {
      default: 
        bТ0422Т04220422ТТТТТ = b043Aкккк043Aкк043Aк();
        b04220422Т04220422ТТТТТ = 86;
      }
      switch (i * (j + i) % k)
      {
      default: 
        bТ0422Т04220422ТТТТТ = b043Aкккк043Aкк043Aк();
        b04220422Т04220422ТТТТТ = 79;
      }
      localObject1 = new Random();
      bool = this.bТТТ04220422ТТТТТ;
      if (bool)
      {
        str1 = b043Aк043A043A043A043Aкк043Aк(1);
        str2 = b043Aк043A043A043A043Aкк043Aк(1);
        l = ((Random)localObject1).nextLong();
        i = ((Random)localObject1).nextInt();
        localObject1 = new ffafff(str1, str2, new short[] { 1 }, l, i);
        return new ffafff[] { localObject1 };
      }
    }
    catch (Throwable localThrowable)
    {
      for (;;)
      {
        str1 = bТ042204220422ТТТТТТ;
        fafffa.bкк043A043Aкк043Aкк043A(str1, gguuuu.bк043Aккк043Aкк043A043A("t\007\031\r\031\007@\003\016\002\002U", 'º', '', '\002'), localThrowable);
        localObject2 = null;
      }
    }
    ffafff[] arrayOfFfafff2 = null;
    label276:
    return arrayOfFfafff2;
  }
  
  public final int b043Aккк043A043Aкк043Aк(@Nullable String paramString1, @Nullable String paramString2)
    throws InterruptedException
  {
    int j = -1;
    if ((b043Aкккк043Aкк043Aк() + bТТ042204220422ТТТТТ) * b043Aкккк043Aкк043Aк() % b0422Т042204220422ТТТТТ != b04220422Т04220422ТТТТТ)
    {
      bТ0422Т04220422ТТТТТ = 94;
      b04220422Т04220422ТТТТТ = b043Aкккк043Aкк043Aк();
    }
    int i = j;
    try
    {
      if (this.b0422ТТТ0422ТТТТТ)
      {
        i = j;
        if (paramString2 != null) {
          i = this.b0422Т0422Т0422ТТТТТ.setConfig(paramString1, paramString2);
        }
      }
    }
    catch (Throwable paramString1)
    {
      for (;;)
      {
        fafffa.bкк043A043Aкк043Aкк043A(bТ042204220422ТТТТТТ, gguuuu.bк043Aккк043Aкк043A043A("7I[O[I\003EPDD\030", '«', '\025', '\000'), paramString1);
        i = j;
        if ((bТ0422Т04220422ТТТТТ + bТТ042204220422ТТТТТ) * bТ0422Т04220422ТТТТТ % b0422Т042204220422ТТТТТ != b04220422Т04220422ТТТТТ)
        {
          bТ0422Т04220422ТТТТТ = b043Aкккк043Aкк043Aк();
          b04220422Т04220422ТТТТТ = 85;
          i = j;
        }
      }
    }
    if (Thread.interrupted())
    {
      fafffa.b043Aккк043Aк043Aкк043A(bТ042204220422ТТТТТТ, gguuuu.bккккк043Aкк043A043A("?T_SPT\021[ahZhimin\033`brdcugg0%zozx\002tzt", '÷', '\001'));
      throw new InterruptedException();
    }
    return i;
  }
  
  @Nullable
  public final String b043Aккккк043Aк043Aк()
  {
    try
    {
      if (this.b0422ТТТ0422ТТТТТ)
      {
        String str = this.b0422Т0422Т0422ТТТТТ.getBinaryArch();
        return str;
      }
    }
    catch (Throwable localThrowable)
    {
      fafffa.bкк043A043Aкк043Aкк043A(bТ042204220422ТТТТТТ, gguuuu.bккккк043Aкк043A043A("bv\013\001\017~:~\f\002\004Y", '', '\004'), localThrowable);
      if ((bТ0422Т04220422ТТТТТ + bТТ042204220422ТТТТТ) * bТ0422Т04220422ТТТТТ % b0422Т042204220422ТТТТТ != b04220422Т04220422ТТТТТ)
      {
        bТ0422Т04220422ТТТТТ = 5;
        b04220422Т04220422ТТТТТ = 35;
      }
    }
    return null;
  }
  
  @Nullable
  public final String bк043A043A043A043A043Aкк043Aк(@Nullable String paramString)
    throws InterruptedException
  {
    for (;;)
    {
      try
      {
        if ((this.b0422ТТТ0422ТТТТТ) && (paramString != null))
        {
          Object localObject = this.b0422Т0422Т0422ТТТТТ;
          int i;
          return paramString;
        }
      }
      catch (Exception paramString)
      {
        try
        {
          localObject = ((NativeGathererHelper)localObject).urlEncode(paramString);
          i = bТ0422Т04220422ТТТТТ;
          paramString = (String)localObject;
          switch (i * (bТТ042204220422ТТТТТ + i) % b0422Т042204220422ТТТТТ)
          {
          default: 
            bТ0422Т04220422ТТТТТ = b043Aкккк043Aкк043Aк();
            b04220422Т04220422ТТТТТ = 4;
            paramString = (String)localObject;
          }
          if (!Thread.interrupted()) {
            break label128;
          }
          fafffa.b043Aккк043Aк043Aкк043A(bТ042204220422ТТТТТТ, gguuuu.bк043Aккк043Aкк043A043A("\"5>0+-g049)54603]!!/\037\034,\034\032`S'\032#\037&\027\033\023", 'X', '¥', '\000'));
          throw new InterruptedException();
        }
        catch (Exception paramString)
        {
          throw paramString;
        }
        paramString = paramString;
        throw paramString;
      }
      catch (Throwable paramString)
      {
        fafffa.bкк043A043Aкк043Aкк043A(bТ042204220422ТТТТТТ, gguuuu.bккккк043Aкк043A043A("\0340D:H8s8E;=\023", 'M', '\000'), paramString);
        paramString = null;
        continue;
      }
      label128:
      paramString = null;
    }
  }
  
  @Nullable
  public final ffafff[] bк043A043Aк043A043Aкк043Aк()
    throws InterruptedException
  {
    try
    {
      if (this.b0422ТТТ0422ТТТТТ)
      {
        Object localObject1 = (ffafff[])this.b0422Т0422Т0422ТТТТТ.findInstalledProcs(ffafff.class);
        if (!Thread.interrupted()) {
          break label164;
        }
        break label166;
        localObject1 = bТ042204220422ТТТТТТ;
        int i = bТ0422Т04220422ТТТТТ;
        switch (i * (bТТ042204220422ТТТТТ + i) % b0422Т042204220422ТТТТТ)
        {
        default: 
          bТ0422Т04220422ТТТТТ = 52;
          b04220422Т04220422ТТТТТ = b043Aкккк043Aкк043Aк();
        }
        fafffa.b043Aккк043Aк043Aкк043A((String)localObject1, gguuuu.bккккк043Aкк043A043A("Wlwkhl)sy\001r\001\002\006\002\0073xz\013|{\016H=\023\b\023\021\032\r\023\r", 'ÿ', '\001'));
        localObject1 = new InterruptedException();
        if ((b043Aкккк043Aкк043Aк() + bТТ042204220422ТТТТТ) * b043Aкккк043Aкк043Aк() % b0422Т042204220422ТТТТТ != b04220422Т04220422ТТТТТ)
        {
          bТ0422Т04220422ТТТТТ = 41;
          b04220422Т04220422ТТТТТ = b043Aкккк043Aкк043Aк();
        }
        throw ((Throwable)localObject1);
      }
    }
    catch (Exception localException1)
    {
      throw localException1;
    }
    catch (Throwable localThrowable)
    {
      try
      {
        fafffa.bкк043A043Aкк043Aкк043A(bТ042204220422ТТТТТТ, gguuuu.bккккк043Aкк043A043A("\034.@4@.g*5))|", '±', '\005'), localThrowable);
        Object localObject2 = null;
      }
      catch (Exception localException2)
      {
        throw localException2;
      }
      label164:
      return localException2;
    }
    label166:
    switch (0)
    {
    }
    for (;;)
    {
      switch (0)
      {
      }
    }
  }
  
  /* Error */
  @Nullable
  public final ffafff[] bк043A043Aкк043Aкк043Aк()
    throws InterruptedException
  {
    // Byte code:
    //   0: aload_0
    //   1: getfield 96	kkkkkk/dvdddv:b0422ТТТ0422ТТТТТ	Z
    //   4: ifeq +113 -> 117
    //   7: aload_0
    //   8: getfield 103	kkkkkk/dvdddv:b0422Т0422Т0422ТТТТТ	Lcom/threatmetrix/TrustDefender/NativeGathererHelper;
    //   11: ldc_w 352
    //   14: invokevirtual 408	com/threatmetrix/TrustDefender/NativeGathererHelper:findAllProcs	(Ljava/lang/Class;)Ljava/lang/Object;
    //   17: checkcast 357	[Lkkkkkk/ffafff;
    //   20: astore_3
    //   21: invokestatic 146	java/lang/Thread:interrupted	()Z
    //   24: istore_2
    //   25: iload_2
    //   26: ifeq +173 -> 199
    //   29: getstatic 53	kkkkkk/dvdddv:bТ042204220422ТТТТТТ	Ljava/lang/String;
    //   32: ldc_w 410
    //   35: sipush 255
    //   38: sipush 205
    //   41: iconst_1
    //   42: invokestatic 82	kkkkkk/gguuuu:bк043Aккк043Aкк043A043A	(Ljava/lang/String;CCC)Ljava/lang/String;
    //   45: invokestatic 152	kkkkkk/fafffa:b043Aккк043Aк043Aкк043A	(Ljava/lang/String;Ljava/lang/String;)V
    //   48: iconst_0
    //   49: tableswitch	default:+23->72, 0:+50->99, 1:+-1->48
    //   72: iconst_0
    //   73: tableswitch	default:+23->96, 0:+26->99, 1:+-25->48
    //   96: goto -24 -> 72
    //   99: new 135	java/lang/InterruptedException
    //   102: dup
    //   103: invokespecial 153	java/lang/InterruptedException:<init>	()V
    //   106: athrow
    //   107: astore_3
    //   108: aload_3
    //   109: athrow
    //   110: astore_3
    //   111: invokestatic 64	kkkkkk/dvdddv:b043Aкккк043Aкк043Aк	()I
    //   114: putstatic 39	kkkkkk/dvdddv:bТ0422Т04220422ТТТТТ	I
    //   117: aconst_null
    //   118: astore_3
    //   119: goto -98 -> 21
    //   122: astore_3
    //   123: getstatic 53	kkkkkk/dvdddv:bТ042204220422ТТТТТТ	Ljava/lang/String;
    //   126: astore 4
    //   128: getstatic 39	kkkkkk/dvdddv:bТ0422Т04220422ТТТТТ	I
    //   131: istore_1
    //   132: iload_1
    //   133: invokestatic 155	kkkkkk/dvdddv:bк043Aккк043Aкк043Aк	()I
    //   136: iload_1
    //   137: iadd
    //   138: imul
    //   139: getstatic 43	kkkkkk/dvdddv:b0422Т042204220422ТТТТТ	I
    //   142: irem
    //   143: tableswitch	default:+17->160, 0:+28->171
    //   160: bipush 87
    //   162: putstatic 39	kkkkkk/dvdddv:bТ0422Т04220422ТТТТТ	I
    //   165: invokestatic 64	kkkkkk/dvdddv:b043Aкккк043Aкк043Aк	()I
    //   168: putstatic 45	kkkkkk/dvdddv:b04220422Т04220422ТТТТТ	I
    //   171: aload 4
    //   173: ldc_w 412
    //   176: sipush 147
    //   179: iconst_3
    //   180: invokestatic 88	kkkkkk/gguuuu:bккккк043Aкк043A043A	(Ljava/lang/String;CC)Ljava/lang/String;
    //   183: aload_3
    //   184: invokestatic 161	kkkkkk/fafffa:bкк043A043Aкк043Aкк043A	(Ljava/lang/String;Ljava/lang/String;Ljava/lang/Throwable;)V
    //   187: iconst_2
    //   188: istore_1
    //   189: iload_1
    //   190: iconst_0
    //   191: idiv
    //   192: istore_1
    //   193: goto -4 -> 189
    //   196: astore_3
    //   197: aload_3
    //   198: athrow
    //   199: aload_3
    //   200: areturn
    // Local variable table:
    //   start	length	slot	name	signature
    //   0	201	0	this	dvdddv
    //   131	62	1	i	int
    //   24	2	2	bool	boolean
    //   20	1	3	arrayOfFfafff	ffafff[]
    //   107	2	3	localException1	Exception
    //   110	1	3	localException2	Exception
    //   118	1	3	localObject	Object
    //   122	62	3	localThrowable	Throwable
    //   196	4	3	localException3	Exception
    //   126	46	4	str	String
    // Exception table:
    //   from	to	target	type
    //   0	21	107	java/lang/Exception
    //   21	25	107	java/lang/Exception
    //   99	107	107	java/lang/Exception
    //   123	128	107	java/lang/Exception
    //   171	187	107	java/lang/Exception
    //   189	193	110	java/lang/Exception
    //   0	21	122	java/lang/Throwable
    //   29	48	196	java/lang/Exception
  }
  
  /* Error */
  @Nullable
  public final com.threatmetrix.TrustDefender.internal.ZL.aaffff bк043Aк043A043A043Aкк043Aк(String paramString1, String paramString2, faafaf.aaffaf paramAaffaf)
  {
    // Byte code:
    //   0: aload_0
    //   1: getfield 96	kkkkkk/dvdddv:b0422ТТТ0422ТТТТТ	Z
    //   4: ifeq +189 -> 193
    //   7: aload_0
    //   8: getfield 103	kkkkkk/dvdddv:b0422Т0422Т0422ТТТТТ	Lcom/threatmetrix/TrustDefender/NativeGathererHelper;
    //   11: aload_1
    //   12: aload_2
    //   13: aload_3
    //   14: getfield 173	kkkkkk/faafaf$aaffaf:b0422042204220422Т0422042204220422Т	Landroid/content/Context;
    //   17: invokevirtual 420	android/content/Context:getContentResolver	()Landroid/content/ContentResolver;
    //   20: invokevirtual 424	com/threatmetrix/TrustDefender/NativeGathererHelper:attestStrongID	(Ljava/lang/String;Ljava/lang/String;Landroid/content/ContentResolver;)[Ljava/lang/String;
    //   23: astore_3
    //   24: aload_3
    //   25: arraylength
    //   26: iconst_1
    //   27: if_icmpne +20 -> 47
    //   30: new 426	com/threatmetrix/TrustDefender/internal/ZL$aaffff
    //   33: dup
    //   34: invokespecial 427	com/threatmetrix/TrustDefender/internal/ZL$aaffff:<init>	()V
    //   37: astore_1
    //   38: aload_1
    //   39: aload_3
    //   40: iconst_0
    //   41: aaload
    //   42: putfield 430	com/threatmetrix/TrustDefender/internal/ZL$aaffff:bТ042204220422Т04220422ТТ0422	Ljava/lang/String;
    //   45: aload_1
    //   46: areturn
    //   47: aload_3
    //   48: arraylength
    //   49: istore 4
    //   51: iload 4
    //   53: iconst_5
    //   54: if_icmpne +141 -> 195
    //   57: new 426	com/threatmetrix/TrustDefender/internal/ZL$aaffff
    //   60: dup
    //   61: invokespecial 427	com/threatmetrix/TrustDefender/internal/ZL$aaffff:<init>	()V
    //   64: astore_2
    //   65: aload_2
    //   66: aload_3
    //   67: iconst_4
    //   68: aaload
    //   69: putfield 433	com/threatmetrix/TrustDefender/internal/ZL$aaffff:b0422042204220422Т04220422ТТ0422	Ljava/lang/String;
    //   72: aload_2
    //   73: aload_3
    //   74: iconst_0
    //   75: aaload
    //   76: putfield 436	com/threatmetrix/TrustDefender/internal/ZL$aaffff:b0422Т04220422Т04220422ТТ0422	Ljava/lang/String;
    //   79: getstatic 39	kkkkkk/dvdddv:bТ0422Т04220422ТТТТТ	I
    //   82: getstatic 41	kkkkkk/dvdddv:bТТ042204220422ТТТТТ	I
    //   85: iadd
    //   86: getstatic 39	kkkkkk/dvdddv:bТ0422Т04220422ТТТТТ	I
    //   89: imul
    //   90: getstatic 43	kkkkkk/dvdddv:b0422Т042204220422ТТТТТ	I
    //   93: irem
    //   94: invokestatic 115	kkkkkk/dvdddv:b043Aк043Aкк043Aкк043Aк	()I
    //   97: if_icmpeq +13 -> 110
    //   100: bipush 39
    //   102: putstatic 39	kkkkkk/dvdddv:bТ0422Т04220422ТТТТТ	I
    //   105: bipush 34
    //   107: putstatic 45	kkkkkk/dvdddv:b04220422Т04220422ТТТТТ	I
    //   110: aload_2
    //   111: aload_3
    //   112: iconst_2
    //   113: aaload
    //   114: putfield 439	com/threatmetrix/TrustDefender/internal/ZL$aaffff:bТТТТ042204220422ТТ0422	Ljava/lang/String;
    //   117: aload_2
    //   118: aload_3
    //   119: iconst_1
    //   120: aaload
    //   121: putfield 442	com/threatmetrix/TrustDefender/internal/ZL$aaffff:b0422ТТТ042204220422ТТ0422	Ljava/lang/String;
    //   124: aload_2
    //   125: aload_3
    //   126: iconst_3
    //   127: aaload
    //   128: putfield 445	com/threatmetrix/TrustDefender/internal/ZL$aaffff:bТТ04220422Т04220422ТТ0422	Ljava/lang/String;
    //   131: aload_2
    //   132: aconst_null
    //   133: putfield 430	com/threatmetrix/TrustDefender/internal/ZL$aaffff:bТ042204220422Т04220422ТТ0422	Ljava/lang/String;
    //   136: aload_2
    //   137: astore_1
    //   138: getstatic 39	kkkkkk/dvdddv:bТ0422Т04220422ТТТТТ	I
    //   141: invokestatic 155	kkkkkk/dvdddv:bк043Aккк043Aкк043Aк	()I
    //   144: iadd
    //   145: getstatic 39	kkkkkk/dvdddv:bТ0422Т04220422ТТТТТ	I
    //   148: imul
    //   149: getstatic 43	kkkkkk/dvdddv:b0422Т042204220422ТТТТТ	I
    //   152: irem
    //   153: getstatic 45	kkkkkk/dvdddv:b04220422Т04220422ТТТТТ	I
    //   156: if_icmpeq -111 -> 45
    //   159: bipush 69
    //   161: putstatic 39	kkkkkk/dvdddv:bТ0422Т04220422ТТТТТ	I
    //   164: bipush 61
    //   166: putstatic 45	kkkkkk/dvdddv:b04220422Т04220422ТТТТТ	I
    //   169: aload_2
    //   170: areturn
    //   171: astore_1
    //   172: getstatic 53	kkkkkk/dvdddv:bТ042204220422ТТТТТТ	Ljava/lang/String;
    //   175: astore_2
    //   176: aload_2
    //   177: ldc_w 447
    //   180: bipush 23
    //   182: sipush 179
    //   185: iconst_0
    //   186: invokestatic 82	kkkkkk/gguuuu:bк043Aккк043Aкк043A043A	(Ljava/lang/String;CCC)Ljava/lang/String;
    //   189: aload_1
    //   190: invokestatic 161	kkkkkk/fafffa:bкк043A043Aкк043Aкк043A	(Ljava/lang/String;Ljava/lang/String;Ljava/lang/Throwable;)V
    //   193: aconst_null
    //   194: areturn
    //   195: aconst_null
    //   196: areturn
    //   197: astore_1
    //   198: aload_1
    //   199: athrow
    //   200: astore_1
    //   201: aload_1
    //   202: athrow
    // Local variable table:
    //   start	length	slot	name	signature
    //   0	203	0	this	dvdddv
    //   0	203	1	paramString1	String
    //   0	203	2	paramString2	String
    //   0	203	3	paramAaffaf	faafaf.aaffaf
    //   49	6	4	i	int
    // Exception table:
    //   from	to	target	type
    //   0	45	171	java/lang/Throwable
    //   47	51	171	java/lang/Throwable
    //   57	79	171	java/lang/Throwable
    //   110	117	171	java/lang/Throwable
    //   117	124	171	java/lang/Throwable
    //   124	131	171	java/lang/Throwable
    //   131	136	171	java/lang/Throwable
    //   0	45	197	java/lang/Exception
    //   57	79	197	java/lang/Exception
    //   110	117	197	java/lang/Exception
    //   124	131	197	java/lang/Exception
    //   172	176	197	java/lang/Exception
    //   47	51	200	java/lang/Exception
    //   117	124	200	java/lang/Exception
    //   131	136	200	java/lang/Exception
    //   176	193	200	java/lang/Exception
  }
  
  @Nullable
  public final List<String> bк043Aк043Aк043Aкк043Aк(@Nullable String paramString)
    throws InterruptedException
  {
    for (;;)
    {
      try
      {
        if (this.b0422ТТТ0422ТТТТТ)
        {
          paramString = this.b0422Т0422Т0422ТТТТТ.getFontList(paramString);
          int i = bТ0422Т04220422ТТТТТ;
          int j = bТТ042204220422ТТТТТ;
          int k = b0422Т042204220422ТТТТТ;
          switch (i * (j + i) % k)
          {
          }
          boolean bool;
          String str;
          return paramString;
        }
      }
      catch (Exception paramString)
      {
        try
        {
          bТ0422Т04220422ТТТТТ = 5;
          b04220422Т04220422ТТТТТ = 3;
          if ((b043Aкккк043Aкк043Aк() + bТТ042204220422ТТТТТ) * b043Aкккк043Aкк043Aк() % b0422Т042204220422ТТТТТ != b04220422Т04220422ТТТТТ)
          {
            bТ0422Т04220422ТТТТТ = 49;
            b04220422Т04220422ТТТТТ = b043Aкккк043Aкк043Aк();
          }
          switch (0)
          {
          case 1: 
          default: 
            switch (1)
            {
            }
            break;
          }
          if (paramString == null) {
            break label235;
          }
          paramString = Arrays.asList(paramString);
          bool = Thread.interrupted();
          if (!bool) {
            break label233;
          }
          paramString = bТ042204220422ТТТТТТ;
          str = gguuuu.bккккк043Aкк043A043A("(;D613m6:?/;:<69c''5%\"2\" fY- )%,\035!\031", '«', '\005');
          fafffa.b043Aккк043Aк043Aкк043A(paramString, str);
          paramString = new InterruptedException();
          throw paramString;
        }
        catch (Exception paramString)
        {
          throw paramString;
        }
        paramString = paramString;
        throw paramString;
      }
      catch (Throwable paramString)
      {
        str = bТ042204220422ТТТТТТ;
        fafffa.bкк043A043Aкк043Aкк043A(str, gguuuu.bк043Aккк043Aкк043A043A("<N`T`N\bJUII\035", '}', '', '\002'), paramString);
        paramString = null;
        continue;
      }
      label233:
      label235:
      paramString = null;
    }
  }
  
  @Nullable
  public final String bк043Aкк043A043Aкк043Aк(@Nullable byte[] paramArrayOfByte)
    throws InterruptedException
  {
    Object localObject2 = null;
    Object localObject1;
    try
    {
      boolean bool = this.b0422ТТТ0422ТТТТТ;
      switch (0)
      {
      case 1: 
      default: 
        for (;;)
        {
          switch (0)
          {
          }
        }
      }
      if ((bТ0422Т04220422ТТТТТ + bТТ042204220422ТТТТТ) * bТ0422Т04220422ТТТТТ % bкк043Aкк043Aкк043Aк() != b04220422Т04220422ТТТТТ)
      {
        bТ0422Т04220422ТТТТТ = b043Aкккк043Aкк043Aк();
        b04220422Т04220422ТТТТТ = 28;
      }
      localObject1 = localObject2;
      if (bool)
      {
        switch (0)
        {
        case 1: 
        default: 
          for (;;)
          {
            switch (0)
            {
            }
          }
        }
        localObject1 = localObject2;
        if (paramArrayOfByte != null) {
          localObject1 = this.b0422Т0422Т0422ТТТТТ.sha256(paramArrayOfByte);
        }
      }
    }
    catch (Throwable paramArrayOfByte)
    {
      for (;;)
      {
        fafffa.bкк043A043Aкк043Aкк043A(bТ042204220422ТТТТТТ, gguuuu.bккккк043Aкк043A043A("^p\003v\003p*lwkk?", 'o', '\005'), paramArrayOfByte);
        localObject1 = localObject2;
      }
    }
    if (Thread.interrupted())
    {
      paramArrayOfByte = bТ042204220422ТТТТТТ;
      localObject1 = gguuuu.bк043Aккк043Aкк043A043A("\030-8,)-i4:A3ABFBGs9;K=<N@@\t}SHSQZMSM", 'N', 't', '\003');
      if ((bТ0422Т04220422ТТТТТ + bТТ042204220422ТТТТТ) * bТ0422Т04220422ТТТТТ % b0422Т042204220422ТТТТТ != b04220422Т04220422ТТТТТ)
      {
        bТ0422Т04220422ТТТТТ = 42;
        b04220422Т04220422ТТТТТ = 35;
      }
      fafffa.b043Aккк043Aк043Aкк043A(paramArrayOfByte, (String)localObject1);
      throw new InterruptedException();
    }
    return localObject1;
  }
  
  public final int bкк043A043A043A043Aкк043Aк()
  {
    try
    {
      if (this.b0422ТТТ0422ТТТТТ)
      {
        i = this.b0422Т0422Т0422ТТТТТ.waitUntilCancelled();
        return i;
      }
    }
    catch (Throwable localThrowable)
    {
      str1 = bТ042204220422ТТТТТТ;
      i = bТ0422Т04220422ТТТТТ;
      switch (i * (bТТ042204220422ТТТТТ + i) % b0422Т042204220422ТТТТТ)
      {
      default: 
        bТ0422Т04220422ТТТТТ = 6;
        b04220422Т04220422ТТТТТ = b043Aкккк043Aкк043Aк();
      }
      str2 = gguuuu.bк043Aккк043Aкк043A043A("<N`T`N\bJUII\035", '', '\f', '\000');
      i = bТ0422Т04220422ТТТТТ;
    }
    catch (Exception localException1)
    {
      try
      {
        int i;
        String str1;
        String str2;
        if ((i + bТТ042204220422ТТТТТ) * bТ0422Т04220422ТТТТТ % b0422Т042204220422ТТТТТ != b04220422Т04220422ТТТТТ)
        {
          bТ0422Т04220422ТТТТТ = 71;
          b04220422Т04220422ТТТТТ = 44;
        }
        switch (0)
        {
        case 1: 
        default: 
          for (;;)
          {
            switch (0)
            {
            }
          }
        }
        fafffa.bкк043A043Aкк043Aкк043A(str1, str2, localThrowable);
        return -1;
      }
      catch (Exception localException2)
      {
        throw localException2;
      }
      localException1 = localException1;
      throw localException1;
    }
  }
  
  /* Error */
  @Nullable
  public final short[] bкк043A043Aк043Aкк043Aк(String[] paramArrayOfString)
  {
    // Byte code:
    //   0: aload_0
    //   1: getfield 96	kkkkkk/dvdddv:b0422ТТТ0422ТТТТТ	Z
    //   4: ifeq +120 -> 124
    //   7: aload_0
    //   8: getfield 103	kkkkkk/dvdddv:b0422Т0422Т0422ТТТТТ	Lcom/threatmetrix/TrustDefender/NativeGathererHelper;
    //   11: astore_3
    //   12: invokestatic 64	kkkkkk/dvdddv:b043Aкккк043Aкк043Aк	()I
    //   15: getstatic 41	kkkkkk/dvdddv:bТТ042204220422ТТТТТ	I
    //   18: iadd
    //   19: invokestatic 64	kkkkkk/dvdddv:b043Aкккк043Aкк043Aк	()I
    //   22: imul
    //   23: invokestatic 468	kkkkkk/dvdddv:bкк043Aкк043Aкк043Aк	()I
    //   26: irem
    //   27: getstatic 45	kkkkkk/dvdddv:b04220422Т04220422ТТТТТ	I
    //   30: if_icmpeq +59 -> 89
    //   33: getstatic 39	kkkkkk/dvdddv:bТ0422Т04220422ТТТТТ	I
    //   36: istore_2
    //   37: iload_2
    //   38: getstatic 41	kkkkkk/dvdddv:bТТ042204220422ТТТТТ	I
    //   41: iload_2
    //   42: iadd
    //   43: imul
    //   44: invokestatic 468	kkkkkk/dvdddv:bкк043Aкк043Aкк043Aк	()I
    //   47: irem
    //   48: tableswitch	default:+20->68, 0:+31->79
    //   68: invokestatic 64	kkkkkk/dvdddv:b043Aкккк043Aкк043Aк	()I
    //   71: putstatic 39	kkkkkk/dvdddv:bТ0422Т04220422ТТТТТ	I
    //   74: bipush 18
    //   76: putstatic 45	kkkkkk/dvdddv:b04220422Т04220422ТТТТТ	I
    //   79: bipush 83
    //   81: putstatic 39	kkkkkk/dvdddv:bТ0422Т04220422ТТТТТ	I
    //   84: bipush 41
    //   86: putstatic 45	kkkkkk/dvdddv:b04220422Т04220422ТТТТТ	I
    //   89: aload_3
    //   90: aload_1
    //   91: invokevirtual 483	com/threatmetrix/TrustDefender/NativeGathererHelper:findPermissions	([Ljava/lang/String;)[S
    //   94: astore_1
    //   95: aload_1
    //   96: areturn
    //   97: astore_1
    //   98: aload_1
    //   99: athrow
    //   100: astore_1
    //   101: getstatic 53	kkkkkk/dvdddv:bТ042204220422ТТТТТТ	Ljava/lang/String;
    //   104: astore_3
    //   105: ldc_w 258
    //   108: sipush 152
    //   111: iconst_5
    //   112: invokestatic 88	kkkkkk/gguuuu:bккккк043Aкк043A043A	(Ljava/lang/String;CC)Ljava/lang/String;
    //   115: astore 4
    //   117: aload_3
    //   118: aload 4
    //   120: aload_1
    //   121: invokestatic 161	kkkkkk/fafffa:bкк043A043Aкк043Aкк043A	(Ljava/lang/String;Ljava/lang/String;Ljava/lang/Throwable;)V
    //   124: aconst_null
    //   125: areturn
    //   126: astore_1
    //   127: aload_1
    //   128: athrow
    // Local variable table:
    //   start	length	slot	name	signature
    //   0	129	0	this	dvdddv
    //   0	129	1	paramArrayOfString	String[]
    //   36	8	2	i	int
    //   11	107	3	localObject	Object
    //   115	4	4	str	String
    // Exception table:
    //   from	to	target	type
    //   117	124	97	java/lang/Exception
    //   0	12	100	java/lang/Throwable
    //   89	95	100	java/lang/Throwable
    //   0	12	126	java/lang/Exception
    //   89	95	126	java/lang/Exception
    //   101	105	126	java/lang/Exception
    //   105	117	126	java/lang/Exception
  }
  
  @Nullable
  public final String[] bкк043Aк043A043Aкк043Aк(@Nullable String[] paramArrayOfString)
    throws InterruptedException
  {
    for (;;)
    {
      try
      {
        int i = bТ0422Т04220422ТТТТТ;
        int j = bТТ042204220422ТТТТТ;
        int k = b0422Т042204220422ТТТТТ;
        switch (i * (j + i) % k)
        {
        }
        try
        {
          bТ0422Т04220422ТТТТТ = b043Aкккк043Aкк043Aк();
          b04220422Т04220422ТТТТТ = b043Aкккк043Aкк043Aк();
        }
        catch (Exception paramArrayOfString)
        {
          String str2;
          StringBuilder localStringBuilder;
          boolean bool;
          throw paramArrayOfString;
        }
        try
        {
          str2 = bТ042204220422ТТТТТТ;
          localStringBuilder = new StringBuilder();
          bool = this.b0422ТТТ0422ТТТТТ;
          if (!bool) {
            continue;
          }
        }
        catch (Throwable paramArrayOfString)
        {
          str1 = bТ042204220422ТТТТТТ;
          fafffa.bкк043A043Aкк043Aкк043A(str1, gguuuu.bккккк043Aкк043A043A("\f 4*8(c(5+-\003", '=', '\000'), paramArrayOfString);
          paramArrayOfString = null;
          continue;
        }
        catch (Exception paramArrayOfString)
        {
          throw paramArrayOfString;
        }
        try
        {
          str1 = gguuuu.bккккк043Aкк043A043A("a$:&/3)+60k", 'A', '\000');
          fafffa.b043Aккк043Aк043Aкк043A(str2, str1 + gguuuu.bк043Aккк043Aкк043A043A("6[\004\t\001u0", '', '\027', '\000') + this.b042204220422Т0422ТТТТТ);
          if ((!this.b0422ТТТ0422ТТТТТ) || (paramArrayOfString == null)) {
            break label279;
          }
          paramArrayOfString = this.b0422Т0422Т0422ТТТТТ.checkURLs(paramArrayOfString);
          if (!Thread.interrupted()) {
            break label277;
          }
          paramArrayOfString = bТ042204220422ТТТТТТ;
          i = bТ0422Т04220422ТТТТТ;
          switch (i * (bТТ042204220422ТТТТТ + i) % b0422Т042204220422ТТТТТ)
          {
          default: 
            bТ0422Т04220422ТТТТТ = b043Aкккк043Aкк043Aк();
            b04220422Т04220422ТТТТТ = 10;
          }
          fafffa.b043Aккк043Aк043Aкк043A(paramArrayOfString, gguuuu.bк043Aккк043Aкк043A043A("\t\036)\035\032\036Z%+2$23738d*,<.-?11ynD9DBK>D>", '', 'ß', '\001'));
          throw new InterruptedException();
        }
        catch (Exception paramArrayOfString)
        {
          throw paramArrayOfString;
        }
        String str1 = gguuuu.bккккк043Aкк043A043A("tv|)k\002mvzpr}w3", '', '\001');
        continue;
        return paramArrayOfString;
      }
      catch (Exception paramArrayOfString)
      {
        throw paramArrayOfString;
      }
      label277:
      label279:
      paramArrayOfString = null;
    }
  }
  
  @Nullable
  public final String bккк043A043A043Aкк043Aк(@Nullable String paramString)
  {
    if ((bТ0422Т04220422ТТТТТ + bТТ042204220422ТТТТТ) * bТ0422Т04220422ТТТТТ % b0422Т042204220422ТТТТТ != b04220422Т04220422ТТТТТ)
    {
      switch (0)
      {
      case 1: 
      default: 
        for (;;)
        {
          switch (1)
          {
          }
        }
      }
      int i = b043Aкккк043Aкк043Aк();
      switch (i * (bТТ042204220422ТТТТТ + i) % bкк043Aкк043Aкк043Aк())
      {
      default: 
        bТ0422Т04220422ТТТТТ = b043Aкккк043Aкк043Aк();
        b04220422Т04220422ТТТТТ = 14;
      }
      bТ0422Т04220422ТТТТТ = b043Aкккк043Aкк043Aк();
      b04220422Т04220422ТТТТТ = 81;
    }
    String str = null;
    try
    {
      if (this.b0422ТТТ0422ТТТТТ) {
        str = this.b0422Т0422Т0422ТТТТТ.getConfig(paramString);
      }
      return str;
    }
    catch (Throwable paramString)
    {
      str = bТ042204220422ТТТТТТ;
      switch (0)
      {
      case 1: 
      default: 
        for (;;)
        {
          switch (0)
          {
          }
        }
      }
      fafffa.bкк043A043Aкк043Aкк043A(str, gguuuu.bк043Aккк043Aкк043A043A("\025)=3A1l1>46\f", 'G', '', '\001'), paramString);
    }
    return null;
  }
  
  public final int bккк043Aк043Aкк043Aк(String paramString)
  {
    try
    {
      if (this.b0422ТТТ0422ТТТТТ)
      {
        i = this.b0422Т0422Т0422ТТТТТ.validatePackage(paramString);
        return i;
      }
    }
    catch (Throwable paramString)
    {
      String str = bТ042204220422ТТТТТТ;
      switch (0)
      {
      case 1: 
      default: 
        for (;;)
        {
          switch (0)
          {
          }
        }
      }
      fafffa.bкк043A043Aкк043Aкк043A(str, gguuuu.bк043Aккк043Aкк043A043A("H\\pftd dqgi?", '½', 'º', '\003'), paramString);
      int i = bТ0422Т04220422ТТТТТ;
      switch (i * (bТТ042204220422ТТТТТ + i) % b0422Т042204220422ТТТТТ)
      {
      default: 
        bТ0422Т04220422ТТТТТ = b043Aкккк043Aкк043Aк();
        b04220422Т04220422ТТТТТ = b043Aкккк043Aкк043Aк();
        i = bТ0422Т04220422ТТТТТ;
        switch (i * (bТТ042204220422ТТТТТ + i) % bкк043Aкк043Aкк043Aк())
        {
        default: 
          bТ0422Т04220422ТТТТТ = 85;
          b04220422Т04220422ТТТТТ = 48;
        }
        break;
      }
    }
    return -1;
  }
  
  /* Error */
  public final boolean bкккк043A043Aкк043Aк(String paramString, int paramInt)
  {
    // Byte code:
    //   0: aload_0
    //   1: getfield 96	kkkkkk/dvdddv:b0422ТТТ0422ТТТТТ	Z
    //   4: ifeq +171 -> 175
    //   7: iconst_1
    //   8: ireturn
    //   9: astore_1
    //   10: aload_0
    //   11: getfield 98	kkkkkk/dvdddv:b0422ТТ04220422ТТТТТ	Ljava/util/concurrent/locks/Lock;
    //   14: invokeinterface 119 1 0
    //   19: aload_1
    //   20: athrow
    //   21: astore_1
    //   22: aload_1
    //   23: athrow
    //   24: aload_0
    //   25: getfield 96	kkkkkk/dvdddv:b0422ТТТ0422ТТТТТ	Z
    //   28: ifeq +47 -> 75
    //   31: aload_0
    //   32: getfield 96	kkkkkk/dvdddv:b0422ТТТ0422ТТТТТ	Z
    //   35: istore 5
    //   37: aload_0
    //   38: getfield 98	kkkkkk/dvdddv:b0422ТТ04220422ТТТТТ	Ljava/util/concurrent/locks/Lock;
    //   41: invokeinterface 119 1 0
    //   46: iload 5
    //   48: ireturn
    //   49: astore_1
    //   50: aload_0
    //   51: iconst_0
    //   52: putfield 96	kkkkkk/dvdddv:b0422ТТТ0422ТТТТТ	Z
    //   55: aload_0
    //   56: getfield 98	kkkkkk/dvdddv:b0422ТТ04220422ТТТТТ	Ljava/util/concurrent/locks/Lock;
    //   59: astore_1
    //   60: aload_1
    //   61: invokeinterface 119 1 0
    //   66: aload_0
    //   67: getfield 96	kkkkkk/dvdddv:b0422ТТТ0422ТТТТТ	Z
    //   70: istore 5
    //   72: iload 5
    //   74: ireturn
    //   75: aload_0
    //   76: getfield 103	kkkkkk/dvdddv:b0422Т0422Т0422ТТТТТ	Lcom/threatmetrix/TrustDefender/NativeGathererHelper;
    //   79: astore 6
    //   81: ldc_w 521
    //   84: bipush 84
    //   86: bipush 24
    //   88: iconst_3
    //   89: invokestatic 82	kkkkkk/gguuuu:bк043Aккк043Aкк043A043A	(Ljava/lang/String;CCC)Ljava/lang/String;
    //   92: invokestatic 524	java/lang/System:loadLibrary	(Ljava/lang/String;)V
    //   95: aload_0
    //   96: aload 6
    //   98: getstatic 530	kkkkkk/vvdvvd:b044Eюююю044E044E044E044E044E	Ljava/lang/Integer;
    //   101: invokevirtual 535	java/lang/Integer:intValue	()I
    //   104: aload_1
    //   105: iload_2
    //   106: invokevirtual 539	com/threatmetrix/TrustDefender/NativeGathererHelper:init	(ILjava/lang/String;I)Z
    //   109: putfield 96	kkkkkk/dvdddv:b0422ТТТ0422ТТТТТ	Z
    //   112: goto -57 -> 55
    //   115: astore_1
    //   116: iconst_4
    //   117: istore_2
    //   118: iload_2
    //   119: iconst_0
    //   120: idiv
    //   121: istore_3
    //   122: getstatic 39	kkkkkk/dvdddv:bТ0422Т04220422ТТТТТ	I
    //   125: istore 4
    //   127: iload_3
    //   128: istore_2
    //   129: iload 4
    //   131: getstatic 41	kkkkkk/dvdddv:bТТ042204220422ТТТТТ	I
    //   134: iload 4
    //   136: iadd
    //   137: imul
    //   138: getstatic 43	kkkkkk/dvdddv:b0422Т042204220422ТТТТТ	I
    //   141: irem
    //   142: tableswitch	default:+18->160, 0:+-24->118
    //   160: bipush 67
    //   162: putstatic 39	kkkkkk/dvdddv:bТ0422Т04220422ТТТТТ	I
    //   165: bipush 56
    //   167: putstatic 45	kkkkkk/dvdddv:b04220422Т04220422ТТТТТ	I
    //   170: iload_3
    //   171: istore_2
    //   172: goto -54 -> 118
    //   175: aload_0
    //   176: getfield 98	kkkkkk/dvdddv:b0422ТТ04220422ТТТТТ	Ljava/util/concurrent/locks/Lock;
    //   179: invokeinterface 113 1 0
    //   184: iconst_1
    //   185: tableswitch	default:+23->208, 0:+-1->184, 1:+-161->24
    //   208: iconst_1
    //   209: tableswitch	default:+23->232, 0:+-25->184, 1:+-185->24
    //   232: goto -24 -> 208
    //   235: astore_1
    //   236: invokestatic 64	kkkkkk/dvdddv:b043Aкккк043Aкк043Aк	()I
    //   239: putstatic 39	kkkkkk/dvdddv:bТ0422Т04220422ТТТТТ	I
    //   242: aload_0
    //   243: iconst_0
    //   244: putfield 96	kkkkkk/dvdddv:b0422ТТТ0422ТТТТТ	Z
    //   247: goto -192 -> 55
    //   250: astore_1
    //   251: aload_1
    //   252: athrow
    //   253: astore_1
    //   254: invokestatic 64	kkkkkk/dvdddv:b043Aкккк043Aкк043Aк	()I
    //   257: putstatic 39	kkkkkk/dvdddv:bТ0422Т04220422ТТТТТ	I
    //   260: new 541	java/lang/NullPointerException
    //   263: dup
    //   264: invokespecial 542	java/lang/NullPointerException:<init>	()V
    //   267: athrow
    // Local variable table:
    //   start	length	slot	name	signature
    //   0	268	0	this	dvdddv
    //   0	268	1	paramString	String
    //   0	268	2	paramInt	int
    //   121	50	3	i	int
    //   125	13	4	j	int
    //   35	38	5	bool	boolean
    //   79	18	6	localNativeGathererHelper	NativeGathererHelper
    // Exception table:
    //   from	to	target	type
    //   24	37	9	finally
    //   50	55	9	finally
    //   75	112	9	finally
    //   175	184	9	finally
    //   242	247	9	finally
    //   0	7	21	java/lang/Exception
    //   10	21	21	java/lang/Exception
    //   37	46	21	java/lang/Exception
    //   60	72	21	java/lang/Exception
    //   75	112	49	java/lang/UnsatisfiedLinkError
    //   75	112	115	java/lang/Throwable
    //   260	268	235	java/lang/Exception
    //   55	60	250	java/lang/Exception
    //   118	122	253	java/lang/Exception
  }
  
  /* Error */
  @Nullable
  public final String bкккккк043Aк043Aк(@Nullable String paramString)
  {
    // Byte code:
    //   0: aconst_null
    //   1: astore 8
    //   3: aload 8
    //   5: astore 7
    //   7: aload_0
    //   8: getfield 96	kkkkkk/dvdddv:b0422ТТТ0422ТТТТТ	Z
    //   11: ifeq +72 -> 83
    //   14: aload 8
    //   16: astore 7
    //   18: aload_1
    //   19: ifnull +64 -> 83
    //   22: aload_0
    //   23: getfield 103	kkkkkk/dvdddv:b0422Т0422Т0422ТТТТТ	Lcom/threatmetrix/TrustDefender/NativeGathererHelper;
    //   26: astore 7
    //   28: getstatic 39	kkkkkk/dvdddv:bТ0422Т04220422ТТТТТ	I
    //   31: istore_2
    //   32: getstatic 41	kkkkkk/dvdddv:bТТ042204220422ТТТТТ	I
    //   35: istore_3
    //   36: getstatic 39	kkkkkk/dvdddv:bТ0422Т04220422ТТТТТ	I
    //   39: istore 4
    //   41: getstatic 43	kkkkkk/dvdddv:b0422Т042204220422ТТТТТ	I
    //   44: istore 5
    //   46: getstatic 45	kkkkkk/dvdddv:b04220422Т04220422ТТТТТ	I
    //   49: istore 6
    //   51: iload_2
    //   52: iload_3
    //   53: iadd
    //   54: iload 4
    //   56: imul
    //   57: iload 5
    //   59: irem
    //   60: iload 6
    //   62: if_icmpeq +13 -> 75
    //   65: bipush 38
    //   67: putstatic 39	kkkkkk/dvdddv:bТ0422Т04220422ТТТТТ	I
    //   70: bipush 86
    //   72: putstatic 45	kkkkkk/dvdddv:b04220422Т04220422ТТТТТ	I
    //   75: aload 7
    //   77: aload_1
    //   78: invokevirtual 546	com/threatmetrix/TrustDefender/NativeGathererHelper:md5	(Ljava/lang/String;)Ljava/lang/String;
    //   81: astore 7
    //   83: aload 7
    //   85: areturn
    //   86: astore_1
    //   87: getstatic 53	kkkkkk/dvdddv:bТ042204220422ТТТТТТ	Ljava/lang/String;
    //   90: ldc_w 548
    //   93: sipush 171
    //   96: iconst_2
    //   97: invokestatic 88	kkkkkk/gguuuu:bккккк043Aкк043A043A	(Ljava/lang/String;CC)Ljava/lang/String;
    //   100: aload_1
    //   101: invokestatic 161	kkkkkk/fafffa:bкк043A043Aкк043Aкк043A	(Ljava/lang/String;Ljava/lang/String;Ljava/lang/Throwable;)V
    //   104: aload 8
    //   106: astore 7
    //   108: getstatic 39	kkkkkk/dvdddv:bТ0422Т04220422ТТТТТ	I
    //   111: getstatic 41	kkkkkk/dvdddv:bТТ042204220422ТТТТТ	I
    //   114: iadd
    //   115: getstatic 39	kkkkkk/dvdddv:bТ0422Т04220422ТТТТТ	I
    //   118: imul
    //   119: getstatic 43	kkkkkk/dvdddv:b0422Т042204220422ТТТТТ	I
    //   122: irem
    //   123: getstatic 45	kkkkkk/dvdddv:b04220422Т04220422ТТТТТ	I
    //   126: if_icmpeq -43 -> 83
    //   129: invokestatic 64	kkkkkk/dvdddv:b043Aкккк043Aкк043Aк	()I
    //   132: putstatic 39	kkkkkk/dvdddv:bТ0422Т04220422ТТТТТ	I
    //   135: bipush 66
    //   137: putstatic 45	kkkkkk/dvdddv:b04220422Т04220422ТТТТТ	I
    //   140: aconst_null
    //   141: areturn
    //   142: astore_1
    //   143: aload_1
    //   144: athrow
    //   145: astore_1
    //   146: aload_1
    //   147: athrow
    //   148: astore_1
    //   149: aload_1
    //   150: athrow
    //   151: astore_1
    //   152: aload_1
    //   153: athrow
    // Local variable table:
    //   start	length	slot	name	signature
    //   0	154	0	this	dvdddv
    //   0	154	1	paramString	String
    //   31	23	2	i	int
    //   35	19	3	j	int
    //   39	18	4	k	int
    //   44	16	5	m	int
    //   49	14	6	n	int
    //   5	102	7	localObject1	Object
    //   1	104	8	localObject2	Object
    // Exception table:
    //   from	to	target	type
    //   7	14	86	java/lang/Throwable
    //   22	28	86	java/lang/Throwable
    //   75	83	86	java/lang/Throwable
    //   7	14	142	java/lang/Exception
    //   22	28	142	java/lang/Exception
    //   75	83	142	java/lang/Exception
    //   65	75	145	java/lang/Exception
    //   143	145	145	java/lang/Exception
    //   149	151	145	java/lang/Exception
    //   87	104	148	java/lang/Exception
    //   28	51	151	java/lang/Exception
  }
}
