package kkkkkk;

import android.text.TextUtils;

public class dxdddx
{
  private static final String b042A042A042A042AЪЪЪЪЪ = "w\034\026 v\023\037\rv\013\027\027\022\020p\022\016\016\002\016\017\003}\013";
  public static int b042A042A042AЪ042AЪЪЪЪ = 2;
  public static int b042AЪ042AЪ042AЪЪЪЪ = 0;
  public static int bЪ042A042AЪ042AЪЪЪЪ = 1;
  public static int bЪЪ042AЪ042AЪЪЪЪ = 25;
  private ddxxdx b042A042AЪЪ042AЪЪЪЪ;
  private String b042AЪЪЪ042AЪЪЪЪ;
  private xdxxdx bЪ042AЪЪ042AЪЪЪЪ;
  private String bЪЪЪЪ042AЪЪЪЪ;
  
  static
  {
    String str = b042A042A042A042AЪЪЪЪЪ;
    if ((bЪЪ042AЪ042AЪЪЪЪ + bЪ042A042AЪ042AЪЪЪЪ) * bЪЪ042AЪ042AЪЪЪЪ % b042A042A042AЪ042AЪЪЪЪ != b042AЪ042AЪ042AЪЪЪЪ)
    {
      bЪЪ042AЪ042AЪЪЪЪ = 26;
      b042AЪ042AЪ042AЪЪЪЪ = b0445х04450445хх0445044504450445();
    }
    b042A042A042A042AЪЪЪЪЪ = gguuuu.bк043Aккк043Aкк043A043A(str, '|', 'T', '\002');
    switch (0)
    {
    case 1: 
    default: 
      for (;;)
      {
        if ((bЪЪ042AЪ042AЪЪЪЪ + bЪ042A042AЪ042AЪЪЪЪ) * bЪЪ042AЪ042AЪЪЪЪ % b042A042A042AЪ042AЪЪЪЪ != b042AЪ042AЪ042AЪЪЪЪ)
        {
          bЪЪ042AЪ042AЪЪЪЪ = 57;
          b042AЪ042AЪ042AЪЪЪЪ = 24;
        }
        switch (1)
        {
        }
      }
    }
  }
  
  public dxdddx(String paramString1, String paramString2, ddxxdx paramDdxxdx, xdxxdx paramXdxxdx)
  {
    this(paramString1, paramString2, paramXdxxdx);
    this.b042A042AЪЪ042AЪЪЪЪ = paramDdxxdx;
  }
  
  public dxdddx(String paramString1, String paramString2, xdxxdx paramXdxxdx)
  {
    this.b042AЪЪЪ042AЪЪЪЪ = paramString1;
    this.bЪ042AЪЪ042AЪЪЪЪ = paramXdxxdx;
    this.bЪЪЪЪ042AЪЪЪЪ = paramString2;
    this.b042A042AЪЪ042AЪЪЪЪ = null;
  }
  
  public static int b0445х04450445хх0445044504450445()
  {
    return 92;
  }
  
  public static int bх044504450445хх0445044504450445()
  {
    return 0;
  }
  
  public static int bхх04450445хх0445044504450445()
  {
    return 1;
  }
  
  public static boolean bхх0445х0445х0445044504450445(dxdddx paramDxdddx)
  {
    if (paramDxdddx != null)
    {
      String str = paramDxdddx.bхххх0445х0445044504450445();
      int i = bЪЪ042AЪ042AЪЪЪЪ;
      switch (i * (bЪ042A042AЪ042AЪЪЪЪ + i) % b042A042A042AЪ042AЪЪЪЪ)
      {
      default: 
        bЪЪ042AЪ042AЪЪЪЪ = 8;
        b042AЪ042AЪ042AЪЪЪЪ = b0445х04450445хх0445044504450445();
      }
      switch (1)
      {
      case 0: 
      default: 
        for (;;)
        {
          switch (0)
          {
          }
        }
      }
      if (!TextUtils.isEmpty(str))
      {
        paramDxdddx = paramDxdddx.b0445044504450445хх0445044504450445();
        if ((bЪЪ042AЪ042AЪЪЪЪ + bЪ042A042AЪ042AЪЪЪЪ) * bЪЪ042AЪ042AЪЪЪЪ % b042A042A042AЪ042AЪЪЪЪ != b042AЪ042AЪ042AЪЪЪЪ)
        {
          bЪЪ042AЪ042AЪЪЪЪ = b0445х04450445хх0445044504450445();
          b042AЪ042AЪ042AЪЪЪЪ = 96;
        }
        switch (0)
        {
        case 1: 
        default: 
          for (;;)
          {
            switch (1)
            {
            }
          }
        }
        if (!TextUtils.isEmpty(paramDxdddx)) {
          return true;
        }
      }
    }
    return false;
  }
  
  public String b0445044504450445хх0445044504450445()
  {
    switch (0)
    {
    case 1: 
    default: 
      for (;;)
      {
        switch (0)
        {
        }
      }
    }
    switch (1)
    {
    case 0: 
    default: 
      for (;;)
      {
        switch (0)
        {
        }
      }
    }
    if ((bЪЪ042AЪ042AЪЪЪЪ + bЪ042A042AЪ042AЪЪЪЪ) * bЪЪ042AЪ042AЪЪЪЪ % b042A042A042AЪ042AЪЪЪЪ != b042AЪ042AЪ042AЪЪЪЪ)
    {
      bЪЪ042AЪ042AЪЪЪЪ = b0445х04450445хх0445044504450445();
      int i = bЪЪ042AЪ042AЪЪЪЪ;
      switch (i * (bхх04450445хх0445044504450445() + i) % b042A042A042AЪ042AЪЪЪЪ)
      {
      default: 
        bЪЪ042AЪ042AЪЪЪЪ = 51;
        b042AЪ042AЪ042AЪЪЪЪ = b0445х04450445хх0445044504450445();
      }
      b042AЪ042AЪ042AЪЪЪЪ = 24;
    }
    return this.bЪЪЪЪ042AЪЪЪЪ;
  }
  
  public boolean b04450445хх0445х0445044504450445()
  {
    if ((this.b042A042AЪЪ042AЪЪЪЪ != null) && (!TextUtils.isEmpty(bх0445хх0445х0445044504450445().bх044504450445044504450445044504450445())))
    {
      switch (0)
      {
      case 1: 
      default: 
        for (;;)
        {
          switch (0)
          {
          }
        }
      }
      try
      {
        throw new NullPointerException();
      }
      catch (Exception localException)
      {
        bЪЪ042AЪ042AЪЪЪЪ = 34;
        return true;
      }
    }
    if ((bЪЪ042AЪ042AЪЪЪЪ + bЪ042A042AЪ042AЪЪЪЪ) * bЪЪ042AЪ042AЪЪЪЪ % b042A042A042AЪ042AЪЪЪЪ != bх044504450445хх0445044504450445())
    {
      bЪЪ042AЪ042AЪЪЪЪ = 99;
      b042AЪ042AЪ042AЪЪЪЪ = b0445х04450445хх0445044504450445();
      return false;
    }
    return false;
  }
  
  /* Error */
  public void b0445х0445х0445х0445044504450445(xdxxdx paramXdxxdx)
  {
    // Byte code:
    //   0: aload_0
    //   1: aload_1
    //   2: putfield 59	kkkkkk/dxdddx:bЪ042AЪЪ042AЪЪЪЪ	Lkkkkkk/xdxxdx;
    //   5: getstatic 29	kkkkkk/dxdddx:bЪЪ042AЪ042AЪЪЪЪ	I
    //   8: getstatic 31	kkkkkk/dxdddx:bЪ042A042AЪ042AЪЪЪЪ	I
    //   11: iadd
    //   12: getstatic 29	kkkkkk/dxdddx:bЪЪ042AЪ042AЪЪЪЪ	I
    //   15: imul
    //   16: getstatic 33	kkkkkk/dxdddx:b042A042A042AЪ042AЪЪЪЪ	I
    //   19: irem
    //   20: getstatic 35	kkkkkk/dxdddx:b042AЪ042AЪ042AЪЪЪЪ	I
    //   23: if_icmpeq +15 -> 38
    //   26: invokestatic 39	kkkkkk/dxdddx:b0445х04450445хх0445044504450445	()I
    //   29: putstatic 29	kkkkkk/dxdddx:bЪЪ042AЪ042AЪЪЪЪ	I
    //   32: invokestatic 39	kkkkkk/dxdddx:b0445х04450445хх0445044504450445	()I
    //   35: putstatic 35	kkkkkk/dxdddx:b042AЪ042AЪ042AЪЪЪЪ	I
    //   38: getstatic 29	kkkkkk/dxdddx:bЪЪ042AЪ042AЪЪЪЪ	I
    //   41: istore_2
    //   42: getstatic 31	kkkkkk/dxdddx:bЪ042A042AЪ042AЪЪЪЪ	I
    //   45: istore_3
    //   46: iload_2
    //   47: iload_3
    //   48: iadd
    //   49: getstatic 29	kkkkkk/dxdddx:bЪЪ042AЪ042AЪЪЪЪ	I
    //   52: imul
    //   53: getstatic 33	kkkkkk/dxdddx:b042A042A042AЪ042AЪЪЪЪ	I
    //   56: irem
    //   57: getstatic 35	kkkkkk/dxdddx:b042AЪ042AЪ042AЪЪЪЪ	I
    //   60: if_icmpeq +27 -> 87
    //   63: invokestatic 39	kkkkkk/dxdddx:b0445х04450445хх0445044504450445	()I
    //   66: istore_2
    //   67: iload_2
    //   68: putstatic 29	kkkkkk/dxdddx:bЪЪ042AЪ042AЪЪЪЪ	I
    //   71: invokestatic 39	kkkkkk/dxdddx:b0445х04450445хх0445044504450445	()I
    //   74: putstatic 35	kkkkkk/dxdddx:b042AЪ042AЪ042AЪЪЪЪ	I
    //   77: return
    //   78: astore_1
    //   79: aload_1
    //   80: athrow
    //   81: astore_1
    //   82: aload_1
    //   83: athrow
    //   84: astore_1
    //   85: aload_1
    //   86: athrow
    //   87: return
    // Local variable table:
    //   start	length	slot	name	signature
    //   0	88	0	this	dxdddx
    //   0	88	1	paramXdxxdx	xdxxdx
    //   41	27	2	i	int
    //   45	4	3	j	int
    // Exception table:
    //   from	to	target	type
    //   0	5	78	java/lang/Exception
    //   38	46	81	java/lang/Exception
    //   67	77	81	java/lang/Exception
    //   79	81	81	java/lang/Exception
    //   46	67	84	java/lang/Exception
  }
  
  public xdxxdx b0445ххх0445х0445044504450445()
  {
    int i = bЪЪ042AЪ042AЪЪЪЪ;
    switch (i * (bЪ042A042AЪ042AЪЪЪЪ + i) % b042A042A042AЪ042AЪЪЪЪ)
    {
    default: 
      bЪЪ042AЪ042AЪЪЪЪ = 15;
      b042AЪ042AЪ042AЪЪЪЪ = b0445х04450445хх0445044504450445();
    }
    xdxxdx localXdxxdx = this.bЪ042AЪЪ042AЪЪЪЪ;
    switch (1)
    {
    case 0: 
    default: 
      for (;;)
      {
        switch (1)
        {
        }
      }
    }
    return localXdxxdx;
  }
  
  /* Error */
  public ddxxdx bх0445хх0445х0445044504450445()
  {
    // Byte code:
    //   0: getstatic 29	kkkkkk/dxdddx:bЪЪ042AЪ042AЪЪЪЪ	I
    //   3: invokestatic 80	kkkkkk/dxdddx:bхх04450445хх0445044504450445	()I
    //   6: iadd
    //   7: getstatic 29	kkkkkk/dxdddx:bЪЪ042AЪ042AЪЪЪЪ	I
    //   10: imul
    //   11: getstatic 33	kkkkkk/dxdddx:b042A042A042AЪ042AЪЪЪЪ	I
    //   14: irem
    //   15: getstatic 35	kkkkkk/dxdddx:b042AЪ042AЪ042AЪЪЪЪ	I
    //   18: if_icmpeq +14 -> 32
    //   21: bipush 43
    //   23: putstatic 29	kkkkkk/dxdddx:bЪЪ042AЪ042AЪЪЪЪ	I
    //   26: invokestatic 39	kkkkkk/dxdddx:b0445х04450445хх0445044504450445	()I
    //   29: putstatic 35	kkkkkk/dxdddx:b042AЪ042AЪ042AЪЪЪЪ	I
    //   32: aload_0
    //   33: getfield 53	kkkkkk/dxdddx:b042A042AЪЪ042AЪЪЪЪ	Lkkkkkk/ddxxdx;
    //   36: astore 6
    //   38: getstatic 29	kkkkkk/dxdddx:bЪЪ042AЪ042AЪЪЪЪ	I
    //   41: istore_1
    //   42: getstatic 31	kkkkkk/dxdddx:bЪ042A042AЪ042AЪЪЪЪ	I
    //   45: istore_2
    //   46: getstatic 29	kkkkkk/dxdddx:bЪЪ042AЪ042AЪЪЪЪ	I
    //   49: istore_3
    //   50: getstatic 33	kkkkkk/dxdddx:b042A042A042AЪ042AЪЪЪЪ	I
    //   53: istore 4
    //   55: getstatic 35	kkkkkk/dxdddx:b042AЪ042AЪ042AЪЪЪЪ	I
    //   58: istore 5
    //   60: iload_1
    //   61: iload_2
    //   62: iadd
    //   63: iload_3
    //   64: imul
    //   65: iload 4
    //   67: irem
    //   68: iload 5
    //   70: if_icmpeq +14 -> 84
    //   73: invokestatic 39	kkkkkk/dxdddx:b0445х04450445хх0445044504450445	()I
    //   76: putstatic 29	kkkkkk/dxdddx:bЪЪ042AЪ042AЪЪЪЪ	I
    //   79: bipush 53
    //   81: putstatic 35	kkkkkk/dxdddx:b042AЪ042AЪ042AЪЪЪЪ	I
    //   84: iconst_0
    //   85: tableswitch	default:+23->108, 0:+50->135, 1:+-1->84
    //   108: iconst_1
    //   109: tableswitch	default:+23->132, 0:+-25->84, 1:+26->135
    //   132: goto -24 -> 108
    //   135: aload 6
    //   137: areturn
    //   138: astore 6
    //   140: aload 6
    //   142: athrow
    //   143: astore 6
    //   145: aload 6
    //   147: athrow
    // Local variable table:
    //   start	length	slot	name	signature
    //   0	148	0	this	dxdddx
    //   41	22	1	i	int
    //   45	18	2	j	int
    //   49	16	3	k	int
    //   53	15	4	m	int
    //   58	13	5	n	int
    //   36	100	6	localDdxxdx	ddxxdx
    //   138	3	6	localException1	Exception
    //   143	3	6	localException2	Exception
    // Exception table:
    //   from	to	target	type
    //   32	55	138	java/lang/Exception
    //   55	60	138	java/lang/Exception
    //   73	84	143	java/lang/Exception
  }
  
  public String bхххх0445х0445044504450445()
  {
    String str = this.b042AЪЪЪ042AЪЪЪЪ;
    int i = bЪЪ042AЪ042AЪЪЪЪ;
    int j = bЪ042A042AЪ042AЪЪЪЪ;
    int k = bЪЪ042AЪ042AЪЪЪЪ;
    switch (1)
    {
    case 0: 
    default: 
      for (;;)
      {
        switch (1)
        {
        }
      }
    }
    if ((i + j) * k % b042A042A042AЪ042AЪЪЪЪ != b042AЪ042AЪ042AЪЪЪЪ)
    {
      if ((b0445х04450445хх0445044504450445() + bЪ042A042AЪ042AЪЪЪЪ) * b0445х04450445хх0445044504450445() % b042A042A042AЪ042AЪЪЪЪ != b042AЪ042AЪ042AЪЪЪЪ)
      {
        bЪЪ042AЪ042AЪЪЪЪ = b0445х04450445хх0445044504450445();
        b042AЪ042AЪ042AЪЪЪЪ = b0445х04450445хх0445044504450445();
      }
      bЪЪ042AЪ042AЪЪЪЪ = b0445х04450445хх0445044504450445();
      b042AЪ042AЪ042AЪЪЪЪ = 40;
    }
    switch (1)
    {
    case 0: 
    default: 
      for (;;)
      {
        switch (0)
        {
        }
      }
    }
    return str;
  }
}
