package kkkkkk;

import java.util.HashSet;

public class dxxdxd
  implements vvovov, xxxdxd
{
  private static final String b044B044B044B044B044Bы044B044B044B;
  public static final String b044B044Bы044B044Bы044B044B044B = "\022\003\023\007\b\022$\f\026\032\016\021\035\033\"\034\023/\022\025'\035$$";
  public static int b044B044Bыыы044B044B044B044B = 0;
  public static final String b044Bы044B044B044Bы044B044B044B = "V_JPXZLMWSXPE";
  public static int b044Bы044Bыы044B044B044B044B = 2;
  public static final String bы044B044B044B044Bы044B044B044B = "_K[OLZDMG";
  private static volatile dxxdxd bы044Bы044B044Bы044B044B044B;
  public static int bы044Bыыы044B044B044B044B = 7;
  public static final String bыы044B044B044Bы044B044B044B = "\021\001\017\006\002\r\t";
  public static int bыы044Bыы044B044B044B044B = 1;
  private HashSet<String> b044Bыыыы044B044B044B044B = new HashSet();
  private HashSet<String> bыыыыы044B044B044B044B = new HashSet();
  
  static
  {
    try
    {
      b044B044Bы044B044Bы044B044B044B = gguuuu.bккккк043Aкк043A043A(b044B044Bы044B044Bы044B044B044B, '>', '\000');
      str = bыы044B044B044Bы044B044B044B;
      int i = bы044Bыыы044B044B044B044B;
      switch (i * (bыы044Bыы044B044B044B044B + i) % b044Bы044Bыы044B044B044B044B)
      {
      default: 
        bы044Bыыы044B044B044B044B = 17;
        b044B044Bыыы044B044B044B044B = b044504450445хххх044504450445();
      }
      if ((bы044Bыыы044B044B044B044B + bыы044Bыы044B044B044B044B) * bы044Bыыы044B044B044B044B % b044Bы044Bыы044B044B044B044B != b044B044Bыыы044B044B044B044B)
      {
        bы044Bыыы044B044B044B044B = b044504450445хххх044504450445();
        b044B044Bыыы044B044B044B044B = b044504450445хххх044504450445();
      }
      bыы044B044B044Bы044B044B044B = gguuuu.bккккк043Aкк043A043A(str, 'N', '\004');
      str = b044Bы044B044B044Bы044B044B044B;
    }
    catch (Exception localException1)
    {
      String str;
      throw localException1;
    }
    try
    {
      b044Bы044B044B044Bы044B044B044B = gguuuu.bк043Aккк043Aкк043A043A(str, 'É', '7', '\000');
      str = bы044B044B044B044Bы044B044B044B;
      bы044B044B044B044Bы044B044B044B = gguuuu.bк043Aккк043Aкк043A043A(str, 'ø', 'd', '\000');
      b044B044B044B044B044Bы044B044B044B = dxxdxd.class.getSimpleName();
    }
    catch (Exception localException2)
    {
      throw localException2;
    }
    bы044Bы044B044Bы044B044B044B = null;
    return;
    switch (1)
    {
    }
    for (;;)
    {
      switch (0)
      {
      }
    }
  }
  
  private dxxdxd() {}
  
  public static int b044504450445хххх044504450445()
  {
    return 30;
  }
  
  public static dxxdxd b04450445х0445ххх044504450445()
  {
    if (bы044Bы044B044Bы044B044B044B == null) {}
    try
    {
      if (bы044Bы044B044Bы044B044B044B == null) {
        bы044Bы044B044Bы044B044B044B = new dxxdxd();
      }
      return bы044Bы044B044Bы044B044B044B;
    }
    finally {}
  }
  
  public static int b0445хх0445ххх044504450445()
  {
    return 0;
  }
  
  public static int bх04450445хххх044504450445()
  {
    return 2;
  }
  
  public static int bххх0445ххх044504450445()
  {
    return 1;
  }
  
  /* Error */
  public void b0445044504450445ххх044504450445(String paramString1, String paramString2)
  {
    // Byte code:
    //   0: iconst_0
    //   1: istore 5
    //   3: iconst_1
    //   4: istore 4
    //   6: getstatic 79	kkkkkk/dxxdxd:b044B044B044B044B044Bы044B044B044B	Ljava/lang/String;
    //   9: astore 7
    //   11: aload 7
    //   13: new 102	java/lang/StringBuilder
    //   16: dup
    //   17: invokespecial 103	java/lang/StringBuilder:<init>	()V
    //   20: ldc 105
    //   22: bipush 81
    //   24: iconst_2
    //   25: invokestatic 49	kkkkkk/gguuuu:bккккк043Aкк043A043A	(Ljava/lang/String;CC)Ljava/lang/String;
    //   28: invokevirtual 109	java/lang/StringBuilder:append	(Ljava/lang/String;)Ljava/lang/StringBuilder;
    //   31: aload_1
    //   32: invokevirtual 109	java/lang/StringBuilder:append	(Ljava/lang/String;)Ljava/lang/StringBuilder;
    //   35: invokevirtual 112	java/lang/StringBuilder:toString	()Ljava/lang/String;
    //   38: invokestatic 117	kkkkkk/xtxtxt:bиии043804380438и0438ии	(Ljava/lang/String;Ljava/lang/String;)V
    //   41: iload 5
    //   43: istore_3
    //   44: aload_2
    //   45: invokestatic 123	android/text/TextUtils:isEmpty	(Ljava/lang/CharSequence;)Z
    //   48: ifne +36 -> 84
    //   51: aload_0
    //   52: getfield 92	kkkkkk/dxxdxd:b044Bыыыы044B044B044B044B	Ljava/util/HashSet;
    //   55: astore 7
    //   57: aload 7
    //   59: aload_2
    //   60: invokevirtual 127	java/util/HashSet:contains	(Ljava/lang/Object;)Z
    //   63: istore 6
    //   65: iload 5
    //   67: istore_3
    //   68: iload 6
    //   70: ifne +14 -> 84
    //   73: aload_0
    //   74: getfield 92	kkkkkk/dxxdxd:b044Bыыыы044B044B044B044B	Ljava/util/HashSet;
    //   77: aload_2
    //   78: invokevirtual 130	java/util/HashSet:add	(Ljava/lang/Object;)Z
    //   81: pop
    //   82: iconst_1
    //   83: istore_3
    //   84: aload_1
    //   85: invokestatic 123	android/text/TextUtils:isEmpty	(Ljava/lang/CharSequence;)Z
    //   88: ifne +144 -> 232
    //   91: aload_0
    //   92: getfield 90	kkkkkk/dxxdxd:bыыыыы044B044B044B044B	Ljava/util/HashSet;
    //   95: aload_1
    //   96: invokevirtual 127	java/util/HashSet:contains	(Ljava/lang/Object;)Z
    //   99: ifne +133 -> 232
    //   102: aload_0
    //   103: getfield 90	kkkkkk/dxxdxd:bыыыыы044B044B044B044B	Ljava/util/HashSet;
    //   106: aload_1
    //   107: invokevirtual 130	java/util/HashSet:add	(Ljava/lang/Object;)Z
    //   110: pop
    //   111: iload 4
    //   113: istore_3
    //   114: iload_3
    //   115: ifeq +110 -> 225
    //   118: new 132	android/os/Bundle
    //   121: dup
    //   122: invokespecial 133	android/os/Bundle:<init>	()V
    //   125: astore 7
    //   127: aload 7
    //   129: ldc -121
    //   131: sipush 172
    //   134: sipush 169
    //   137: iconst_1
    //   138: invokestatic 69	kkkkkk/gguuuu:bк043Aккк043Aкк043A043A	(Ljava/lang/String;CCC)Ljava/lang/String;
    //   141: aload_1
    //   142: invokevirtual 138	android/os/Bundle:putString	(Ljava/lang/String;Ljava/lang/String;)V
    //   145: aload 7
    //   147: ldc -116
    //   149: sipush 240
    //   152: iconst_0
    //   153: invokestatic 49	kkkkkk/gguuuu:bккккк043Aкк043A043A	(Ljava/lang/String;CC)Ljava/lang/String;
    //   156: aload_2
    //   157: invokevirtual 138	android/os/Bundle:putString	(Ljava/lang/String;Ljava/lang/String;)V
    //   160: aload 7
    //   162: ldc -114
    //   164: bipush 56
    //   166: sipush 253
    //   169: iconst_2
    //   170: invokestatic 69	kkkkkk/gguuuu:bк043Aккк043Aкк043A043A	(Ljava/lang/String;CCC)Ljava/lang/String;
    //   173: iconst_1
    //   174: invokevirtual 146	android/os/Bundle:putBoolean	(Ljava/lang/String;Z)V
    //   177: getstatic 53	kkkkkk/dxxdxd:bы044Bыыы044B044B044B044B	I
    //   180: getstatic 55	kkkkkk/dxxdxd:bыы044Bыы044B044B044B044B	I
    //   183: iadd
    //   184: getstatic 53	kkkkkk/dxxdxd:bы044Bыыы044B044B044B044B	I
    //   187: imul
    //   188: invokestatic 148	kkkkkk/dxxdxd:bх04450445хххх044504450445	()I
    //   191: irem
    //   192: getstatic 63	kkkkkk/dxxdxd:b044B044Bыыы044B044B044B044B	I
    //   195: if_icmpeq +14 -> 209
    //   198: bipush 33
    //   200: putstatic 53	kkkkkk/dxxdxd:bы044Bыыы044B044B044B044B	I
    //   203: invokestatic 61	kkkkkk/dxxdxd:b044504450445хххх044504450445	()I
    //   206: putstatic 63	kkkkkk/dxxdxd:b044B044Bыыы044B044B044B044B	I
    //   209: ldc -106
    //   211: sipush 250
    //   214: bipush 21
    //   216: iconst_2
    //   217: invokestatic 69	kkkkkk/gguuuu:bк043Aккк043Aкк043A043A	(Ljava/lang/String;CCC)Ljava/lang/String;
    //   220: aload 7
    //   222: invokestatic 156	kkkkkk/hbhbbh:bШ042804280428Ш0428042804280428Ш	(Ljava/lang/String;Landroid/os/Bundle;)V
    //   225: return
    //   226: astore_1
    //   227: aload_1
    //   228: athrow
    //   229: astore_1
    //   230: aload_1
    //   231: athrow
    //   232: goto -118 -> 114
    // Local variable table:
    //   start	length	slot	name	signature
    //   0	235	0	this	dxxdxd
    //   0	235	1	paramString1	String
    //   0	235	2	paramString2	String
    //   43	72	3	i	int
    //   4	108	4	j	int
    //   1	65	5	k	int
    //   63	6	6	bool	boolean
    //   9	212	7	localObject	Object
    // Exception table:
    //   from	to	target	type
    //   6	11	226	java/lang/Exception
    //   44	57	226	java/lang/Exception
    //   73	82	226	java/lang/Exception
    //   84	111	226	java/lang/Exception
    //   118	177	226	java/lang/Exception
    //   11	41	229	java/lang/Exception
    //   57	65	229	java/lang/Exception
    //   209	225	229	java/lang/Exception
  }
  
  /* Error */
  public void b04450445хх0445хх044504450445(String paramString)
  {
    // Byte code:
    //   0: getstatic 79	kkkkkk/dxxdxd:b044B044B044B044B044Bы044B044B044B	Ljava/lang/String;
    //   3: astore_3
    //   4: new 102	java/lang/StringBuilder
    //   7: dup
    //   8: invokespecial 103	java/lang/StringBuilder:<init>	()V
    //   11: astore 4
    //   13: getstatic 53	kkkkkk/dxxdxd:bы044Bыыы044B044B044B044B	I
    //   16: getstatic 55	kkkkkk/dxxdxd:bыы044Bыы044B044B044B044B	I
    //   19: iadd
    //   20: getstatic 53	kkkkkk/dxxdxd:bы044Bыыы044B044B044B044B	I
    //   23: imul
    //   24: getstatic 57	kkkkkk/dxxdxd:b044Bы044Bыы044B044B044B044B	I
    //   27: irem
    //   28: getstatic 63	kkkkkk/dxxdxd:b044B044Bыыы044B044B044B044B	I
    //   31: if_icmpeq +14 -> 45
    //   34: bipush 68
    //   36: putstatic 53	kkkkkk/dxxdxd:bы044Bыыы044B044B044B044B	I
    //   39: invokestatic 61	kkkkkk/dxxdxd:b044504450445хххх044504450445	()I
    //   42: putstatic 63	kkkkkk/dxxdxd:b044B044Bыыы044B044B044B044B	I
    //   45: aload 4
    //   47: ldc -96
    //   49: iconst_3
    //   50: sipush 235
    //   53: iconst_1
    //   54: invokestatic 69	kkkkkk/gguuuu:bк043Aккк043Aкк043A043A	(Ljava/lang/String;CCC)Ljava/lang/String;
    //   57: invokevirtual 109	java/lang/StringBuilder:append	(Ljava/lang/String;)Ljava/lang/StringBuilder;
    //   60: astore 4
    //   62: getstatic 53	kkkkkk/dxxdxd:bы044Bыыы044B044B044B044B	I
    //   65: istore_2
    //   66: iload_2
    //   67: getstatic 55	kkkkkk/dxxdxd:bыы044Bыы044B044B044B044B	I
    //   70: iload_2
    //   71: iadd
    //   72: imul
    //   73: getstatic 57	kkkkkk/dxxdxd:b044Bы044Bыы044B044B044B044B	I
    //   76: irem
    //   77: tableswitch	default:+19->96, 0:+30->107
    //   96: invokestatic 61	kkkkkk/dxxdxd:b044504450445хххх044504450445	()I
    //   99: putstatic 53	kkkkkk/dxxdxd:bы044Bыыы044B044B044B044B	I
    //   102: bipush 57
    //   104: putstatic 63	kkkkkk/dxxdxd:b044B044Bыыы044B044B044B044B	I
    //   107: aload_3
    //   108: aload 4
    //   110: aload_1
    //   111: invokevirtual 109	java/lang/StringBuilder:append	(Ljava/lang/String;)Ljava/lang/StringBuilder;
    //   114: invokevirtual 112	java/lang/StringBuilder:toString	()Ljava/lang/String;
    //   117: invokestatic 117	kkkkkk/xtxtxt:bиии043804380438и0438ии	(Ljava/lang/String;Ljava/lang/String;)V
    //   120: aload_1
    //   121: invokestatic 123	android/text/TextUtils:isEmpty	(Ljava/lang/CharSequence;)Z
    //   124: ifne +78 -> 202
    //   127: aload_0
    //   128: getfield 90	kkkkkk/dxxdxd:bыыыыы044B044B044B044B	Ljava/util/HashSet;
    //   131: aload_1
    //   132: invokevirtual 127	java/util/HashSet:contains	(Ljava/lang/Object;)Z
    //   135: ifeq +67 -> 202
    //   138: aload_0
    //   139: getfield 90	kkkkkk/dxxdxd:bыыыыы044B044B044B044B	Ljava/util/HashSet;
    //   142: aload_1
    //   143: invokevirtual 163	java/util/HashSet:remove	(Ljava/lang/Object;)Z
    //   146: pop
    //   147: new 132	android/os/Bundle
    //   150: dup
    //   151: invokespecial 133	android/os/Bundle:<init>	()V
    //   154: astore_3
    //   155: goto +54 -> 209
    //   158: aload_3
    //   159: ldc -91
    //   161: bipush 25
    //   163: bipush 83
    //   165: iconst_2
    //   166: invokestatic 69	kkkkkk/gguuuu:bк043Aккк043Aкк043A043A	(Ljava/lang/String;CCC)Ljava/lang/String;
    //   169: aload_1
    //   170: invokevirtual 138	android/os/Bundle:putString	(Ljava/lang/String;Ljava/lang/String;)V
    //   173: aload_3
    //   174: ldc -89
    //   176: iconst_2
    //   177: bipush 100
    //   179: iconst_3
    //   180: invokestatic 69	kkkkkk/gguuuu:bк043Aккк043Aкк043A043A	(Ljava/lang/String;CCC)Ljava/lang/String;
    //   183: iconst_0
    //   184: invokevirtual 146	android/os/Bundle:putBoolean	(Ljava/lang/String;Z)V
    //   187: ldc -87
    //   189: sipush 170
    //   192: iconst_2
    //   193: invokestatic 49	kkkkkk/gguuuu:bккккк043Aкк043A043A	(Ljava/lang/String;CC)Ljava/lang/String;
    //   196: astore_1
    //   197: aload_1
    //   198: aload_3
    //   199: invokestatic 156	kkkkkk/hbhbbh:bШ042804280428Ш0428042804280428Ш	(Ljava/lang/String;Landroid/os/Bundle;)V
    //   202: return
    //   203: astore_1
    //   204: aload_1
    //   205: athrow
    //   206: astore_1
    //   207: aload_1
    //   208: athrow
    //   209: iconst_1
    //   210: tableswitch	default:+22->232, 0:+-1->209, 1:+-52->158
    //   232: iconst_0
    //   233: tableswitch	default:+23->256, 0:+-75->158, 1:+-24->209
    //   256: goto -24 -> 232
    // Local variable table:
    //   start	length	slot	name	signature
    //   0	259	0	this	dxxdxd
    //   0	259	1	paramString	String
    //   65	8	2	i	int
    //   3	196	3	localObject	Object
    //   11	98	4	localStringBuilder	StringBuilder
    // Exception table:
    //   from	to	target	type
    //   0	13	203	java/lang/Exception
    //   120	155	203	java/lang/Exception
    //   158	173	203	java/lang/Exception
    //   187	197	203	java/lang/Exception
    //   45	62	206	java/lang/Exception
    //   107	120	206	java/lang/Exception
    //   173	187	206	java/lang/Exception
    //   197	202	206	java/lang/Exception
  }
  
  /* Error */
  public boolean b0445х04450445ххх044504450445(String paramString)
  {
    // Byte code:
    //   0: aload_0
    //   1: getfield 90	kkkkkk/dxxdxd:bыыыыы044B044B044B044B	Ljava/util/HashSet;
    //   4: astore 8
    //   6: aload 8
    //   8: aload_1
    //   9: invokevirtual 127	java/util/HashSet:contains	(Ljava/lang/Object;)Z
    //   12: istore 7
    //   14: getstatic 53	kkkkkk/dxxdxd:bы044Bыыы044B044B044B044B	I
    //   17: istore_2
    //   18: getstatic 55	kkkkkk/dxxdxd:bыы044Bыы044B044B044B044B	I
    //   21: istore_3
    //   22: getstatic 53	kkkkkk/dxxdxd:bы044Bыыы044B044B044B044B	I
    //   25: istore 4
    //   27: getstatic 57	kkkkkk/dxxdxd:b044Bы044Bыы044B044B044B044B	I
    //   30: istore 5
    //   32: getstatic 63	kkkkkk/dxxdxd:b044B044Bыыы044B044B044B044B	I
    //   35: istore 6
    //   37: iload_2
    //   38: iload_3
    //   39: iadd
    //   40: iload 4
    //   42: imul
    //   43: iload 5
    //   45: irem
    //   46: iload 6
    //   48: if_icmpeq +60 -> 108
    //   51: getstatic 53	kkkkkk/dxxdxd:bы044Bыыы044B044B044B044B	I
    //   54: istore_2
    //   55: iload_2
    //   56: getstatic 55	kkkkkk/dxxdxd:bыы044Bыы044B044B044B044B	I
    //   59: iload_2
    //   60: iadd
    //   61: imul
    //   62: getstatic 57	kkkkkk/dxxdxd:b044Bы044Bыы044B044B044B044B	I
    //   65: irem
    //   66: tableswitch	default:+18->84, 0:+30->96
    //   84: invokestatic 61	kkkkkk/dxxdxd:b044504450445хххх044504450445	()I
    //   87: putstatic 53	kkkkkk/dxxdxd:bы044Bыыы044B044B044B044B	I
    //   90: invokestatic 61	kkkkkk/dxxdxd:b044504450445хххх044504450445	()I
    //   93: putstatic 63	kkkkkk/dxxdxd:b044B044Bыыы044B044B044B044B	I
    //   96: invokestatic 61	kkkkkk/dxxdxd:b044504450445хххх044504450445	()I
    //   99: putstatic 53	kkkkkk/dxxdxd:bы044Bыыы044B044B044B044B	I
    //   102: invokestatic 61	kkkkkk/dxxdxd:b044504450445хххх044504450445	()I
    //   105: putstatic 63	kkkkkk/dxxdxd:b044B044Bыыы044B044B044B044B	I
    //   108: iload 7
    //   110: ireturn
    //   111: astore_1
    //   112: aload_1
    //   113: athrow
    //   114: astore_1
    //   115: aload_1
    //   116: athrow
    //   117: astore_1
    //   118: aload_1
    //   119: athrow
    //   120: astore_1
    //   121: aload_1
    //   122: athrow
    // Local variable table:
    //   start	length	slot	name	signature
    //   0	123	0	this	dxxdxd
    //   0	123	1	paramString	String
    //   17	45	2	i	int
    //   21	19	3	j	int
    //   25	18	4	k	int
    //   30	16	5	m	int
    //   35	14	6	n	int
    //   12	97	7	bool	boolean
    //   4	3	8	localHashSet	HashSet
    // Exception table:
    //   from	to	target	type
    //   0	6	111	java/lang/Exception
    //   14	37	114	java/lang/Exception
    //   112	114	114	java/lang/Exception
    //   118	120	114	java/lang/Exception
    //   6	14	117	java/lang/Exception
    //   96	108	120	java/lang/Exception
  }
  
  public void b0445ххх0445хх044504450445()
  {
    if ((bы044Bыыы044B044B044B044B + bыы044Bыы044B044B044B044B) * bы044Bыыы044B044B044B044B % bх04450445хххх044504450445() != b0445хх0445ххх044504450445())
    {
      if ((bы044Bыыы044B044B044B044B + bыы044Bыы044B044B044B044B) * bы044Bыыы044B044B044B044B % bх04450445хххх044504450445() != b044B044Bыыы044B044B044B044B)
      {
        bы044Bыыы044B044B044B044B = b044504450445хххх044504450445();
        b044B044Bыыы044B044B044B044B = b044504450445хххх044504450445();
      }
      bы044Bыыы044B044B044B044B = b044504450445хххх044504450445();
      b044B044Bыыы044B044B044B044B = b044504450445хххх044504450445();
    }
    switch (1)
    {
    case 0: 
    default: 
      for (;;)
      {
        switch (1)
        {
        }
      }
    }
    bх0445хх0445хх044504450445();
  }
  
  public boolean bх044504450445ххх044504450445(String paramString)
  {
    HashSet localHashSet = this.b044Bыыыы044B044B044B044B;
    if ((bы044Bыыы044B044B044B044B + bыы044Bыы044B044B044B044B) * bы044Bыыы044B044B044B044B % bх04450445хххх044504450445() != b0445хх0445ххх044504450445())
    {
      bы044Bыыы044B044B044B044B = 60;
      b044B044Bыыы044B044B044B044B = b044504450445хххх044504450445();
    }
    if ((bы044Bыыы044B044B044B044B + bыы044Bыы044B044B044B044B) * bы044Bыыы044B044B044B044B % b044Bы044Bыы044B044B044B044B != b044B044Bыыы044B044B044B044B)
    {
      bы044Bыыы044B044B044B044B = 97;
      b044B044Bыыы044B044B044B044B = b044504450445хххх044504450445();
    }
    return localHashSet.contains(paramString);
  }
  
  /* Error */
  public HashSet<String> bх0445х0445ххх044504450445()
  {
    // Byte code:
    //   0: getstatic 53	kkkkkk/dxxdxd:bы044Bыыы044B044B044B044B	I
    //   3: istore_1
    //   4: getstatic 55	kkkkkk/dxxdxd:bыы044Bыы044B044B044B044B	I
    //   7: istore_2
    //   8: getstatic 53	kkkkkk/dxxdxd:bы044Bыыы044B044B044B044B	I
    //   11: istore_3
    //   12: getstatic 57	kkkkkk/dxxdxd:b044Bы044Bыы044B044B044B044B	I
    //   15: istore 4
    //   17: getstatic 63	kkkkkk/dxxdxd:b044B044Bыыы044B044B044B044B	I
    //   20: istore 5
    //   22: iload_1
    //   23: iload_2
    //   24: iadd
    //   25: iload_3
    //   26: imul
    //   27: iload 4
    //   29: irem
    //   30: iload 5
    //   32: if_icmpeq +57 -> 89
    //   35: getstatic 53	kkkkkk/dxxdxd:bы044Bыыы044B044B044B044B	I
    //   38: istore_1
    //   39: iload_1
    //   40: getstatic 55	kkkkkk/dxxdxd:bыы044Bыы044B044B044B044B	I
    //   43: iload_1
    //   44: iadd
    //   45: imul
    //   46: getstatic 57	kkkkkk/dxxdxd:b044Bы044Bыы044B044B044B044B	I
    //   49: irem
    //   50: tableswitch	default:+18->68, 0:+28->78
    //   68: invokestatic 61	kkkkkk/dxxdxd:b044504450445хххх044504450445	()I
    //   71: putstatic 53	kkkkkk/dxxdxd:bы044Bыыы044B044B044B044B	I
    //   74: iconst_3
    //   75: putstatic 63	kkkkkk/dxxdxd:b044B044Bыыы044B044B044B044B	I
    //   78: bipush 92
    //   80: putstatic 53	kkkkkk/dxxdxd:bы044Bыыы044B044B044B044B	I
    //   83: invokestatic 61	kkkkkk/dxxdxd:b044504450445хххх044504450445	()I
    //   86: putstatic 63	kkkkkk/dxxdxd:b044B044Bыыы044B044B044B044B	I
    //   89: aload_0
    //   90: getfield 90	kkkkkk/dxxdxd:bыыыыы044B044B044B044B	Ljava/util/HashSet;
    //   93: astore 6
    //   95: iconst_1
    //   96: tableswitch	default:+24->120, 0:+-1->95, 1:+51->147
    //   120: iconst_0
    //   121: tableswitch	default:+23->144, 0:+26->147, 1:+-26->95
    //   144: goto -24 -> 120
    //   147: aload 6
    //   149: areturn
    //   150: astore 6
    //   152: aload 6
    //   154: athrow
    //   155: astore 6
    //   157: aload 6
    //   159: athrow
    // Local variable table:
    //   start	length	slot	name	signature
    //   0	160	0	this	dxxdxd
    //   3	43	1	i	int
    //   7	18	2	j	int
    //   11	16	3	k	int
    //   15	15	4	m	int
    //   20	13	5	n	int
    //   93	55	6	localHashSet	HashSet
    //   150	3	6	localException1	Exception
    //   155	3	6	localException2	Exception
    // Exception table:
    //   from	to	target	type
    //   0	4	150	java/lang/Exception
    //   89	95	150	java/lang/Exception
    //   4	22	155	java/lang/Exception
    //   78	89	155	java/lang/Exception
  }
  
  /* Error */
  public void bх0445хх0445хх044504450445()
  {
    // Byte code:
    //   0: aload_0
    //   1: getfield 90	kkkkkk/dxxdxd:bыыыыы044B044B044B044B	Ljava/util/HashSet;
    //   4: invokevirtual 186	java/util/HashSet:iterator	()Ljava/util/Iterator;
    //   7: astore_3
    //   8: getstatic 53	kkkkkk/dxxdxd:bы044Bыыы044B044B044B044B	I
    //   11: istore_1
    //   12: iload_1
    //   13: invokestatic 188	kkkkkk/dxxdxd:bххх0445ххх044504450445	()I
    //   16: iload_1
    //   17: iadd
    //   18: imul
    //   19: getstatic 57	kkkkkk/dxxdxd:b044Bы044Bыы044B044B044B044B	I
    //   22: irem
    //   23: tableswitch	default:+153->176, 0:+28->51
    //   40: bipush 17
    //   42: putstatic 53	kkkkkk/dxxdxd:bы044Bыыы044B044B044B044B	I
    //   45: invokestatic 61	kkkkkk/dxxdxd:b044504450445хххх044504450445	()I
    //   48: putstatic 63	kkkkkk/dxxdxd:b044B044Bыыы044B044B044B044B	I
    //   51: aload_3
    //   52: invokeinterface 194 1 0
    //   57: istore_2
    //   58: iload_2
    //   59: ifeq +78 -> 137
    //   62: getstatic 53	kkkkkk/dxxdxd:bы044Bыыы044B044B044B044B	I
    //   65: istore_1
    //   66: iload_1
    //   67: getstatic 55	kkkkkk/dxxdxd:bыы044Bыы044B044B044B044B	I
    //   70: iload_1
    //   71: iadd
    //   72: imul
    //   73: getstatic 57	kkkkkk/dxxdxd:b044Bы044Bыы044B044B044B044B	I
    //   76: irem
    //   77: tableswitch	default:+19->96, 0:+30->107
    //   96: invokestatic 61	kkkkkk/dxxdxd:b044504450445хххх044504450445	()I
    //   99: putstatic 53	kkkkkk/dxxdxd:bы044Bыыы044B044B044B044B	I
    //   102: bipush 97
    //   104: putstatic 63	kkkkkk/dxxdxd:b044B044Bыыы044B044B044B044B	I
    //   107: aload_0
    //   108: aload_3
    //   109: invokeinterface 198 1 0
    //   114: checkcast 200	java/lang/String
    //   117: invokevirtual 202	kkkkkk/dxxdxd:b04450445хх0445хх044504450445	(Ljava/lang/String;)V
    //   120: goto -69 -> 51
    //   123: astore_3
    //   124: aload_3
    //   125: athrow
    //   126: astore_3
    //   127: aload_3
    //   128: athrow
    //   129: aload_0
    //   130: getfield 90	kkkkkk/dxxdxd:bыыыыы044B044B044B044B	Ljava/util/HashSet;
    //   133: invokevirtual 205	java/util/HashSet:clear	()V
    //   136: return
    //   137: aload_0
    //   138: getfield 92	kkkkkk/dxxdxd:b044Bыыыы044B044B044B044B	Ljava/util/HashSet;
    //   141: invokevirtual 186	java/util/HashSet:iterator	()Ljava/util/Iterator;
    //   144: astore_3
    //   145: aload_3
    //   146: invokeinterface 194 1 0
    //   151: ifeq -22 -> 129
    //   154: aload_0
    //   155: aload_3
    //   156: invokeinterface 198 1 0
    //   161: checkcast 200	java/lang/String
    //   164: invokevirtual 202	kkkkkk/dxxdxd:b04450445хх0445хх044504450445	(Ljava/lang/String;)V
    //   167: goto -22 -> 145
    //   170: astore_3
    //   171: aload_3
    //   172: athrow
    //   173: astore_3
    //   174: aload_3
    //   175: athrow
    //   176: goto -136 -> 40
    // Local variable table:
    //   start	length	slot	name	signature
    //   0	179	0	this	dxxdxd
    //   11	62	1	i	int
    //   57	2	2	bool	boolean
    //   7	102	3	localIterator1	java.util.Iterator
    //   123	2	3	localException1	Exception
    //   126	2	3	localException2	Exception
    //   144	12	3	localIterator2	java.util.Iterator
    //   170	2	3	localException3	Exception
    //   173	2	3	localException4	Exception
    // Exception table:
    //   from	to	target	type
    //   0	8	123	java/lang/Exception
    //   51	58	123	java/lang/Exception
    //   107	120	123	java/lang/Exception
    //   129	136	123	java/lang/Exception
    //   12	40	126	java/lang/Exception
    //   40	51	126	java/lang/Exception
    //   124	126	126	java/lang/Exception
    //   171	173	126	java/lang/Exception
    //   137	145	170	java/lang/Exception
    //   145	167	170	java/lang/Exception
    //   8	12	173	java/lang/Exception
  }
  
  public boolean bхх04450445ххх044504450445()
  {
    if ((bы044Bыыы044B044B044B044B + bыы044Bыы044B044B044B044B) * bы044Bыыы044B044B044B044B % b044Bы044Bыы044B044B044B044B != b044B044Bыыы044B044B044B044B)
    {
      bы044Bыыы044B044B044B044B = b044504450445хххх044504450445();
      b044B044Bыыы044B044B044B044B = b044504450445хххх044504450445();
    }
    try
    {
      if (!this.bыыыыы044B044B044B044B.isEmpty()) {
        return true;
      }
      int i = b044504450445хххх044504450445();
      int j = bыы044Bыы044B044B044B044B;
      int k = b044504450445хххх044504450445();
      int m = b044Bы044Bыы044B044B044B044B;
      int n = b044B044Bыыы044B044B044B044B;
      if ((i + j) * k % m != n) {
        try
        {
          bы044Bыыы044B044B044B044B = 35;
          b044B044Bыыы044B044B044B044B = b044504450445хххх044504450445();
          return false;
        }
        catch (Exception localException1)
        {
          throw localException1;
        }
      }
      return false;
    }
    catch (Exception localException2)
    {
      throw localException2;
    }
  }
  
  /* Error */
  public void bхх0445х0445хх044504450445(String paramString)
  {
    // Byte code:
    //   0: getstatic 79	kkkkkk/dxxdxd:b044B044B044B044B044Bы044B044B044B	Ljava/lang/String;
    //   3: astore_3
    //   4: new 102	java/lang/StringBuilder
    //   7: dup
    //   8: invokespecial 103	java/lang/StringBuilder:<init>	()V
    //   11: ldc -45
    //   13: sipush 225
    //   16: iconst_5
    //   17: invokestatic 49	kkkkkk/gguuuu:bккккк043Aкк043A043A	(Ljava/lang/String;CC)Ljava/lang/String;
    //   20: invokevirtual 109	java/lang/StringBuilder:append	(Ljava/lang/String;)Ljava/lang/StringBuilder;
    //   23: aload_1
    //   24: invokevirtual 109	java/lang/StringBuilder:append	(Ljava/lang/String;)Ljava/lang/StringBuilder;
    //   27: astore 4
    //   29: getstatic 53	kkkkkk/dxxdxd:bы044Bыыы044B044B044B044B	I
    //   32: getstatic 55	kkkkkk/dxxdxd:bыы044Bыы044B044B044B044B	I
    //   35: iadd
    //   36: getstatic 53	kkkkkk/dxxdxd:bы044Bыыы044B044B044B044B	I
    //   39: imul
    //   40: getstatic 57	kkkkkk/dxxdxd:b044Bы044Bыы044B044B044B044B	I
    //   43: irem
    //   44: getstatic 63	kkkkkk/dxxdxd:b044B044Bыыы044B044B044B044B	I
    //   47: if_icmpeq +13 -> 60
    //   50: bipush 22
    //   52: putstatic 53	kkkkkk/dxxdxd:bы044Bыыы044B044B044B044B	I
    //   55: bipush 95
    //   57: putstatic 63	kkkkkk/dxxdxd:b044B044Bыыы044B044B044B044B	I
    //   60: aload_3
    //   61: aload 4
    //   63: invokevirtual 112	java/lang/StringBuilder:toString	()Ljava/lang/String;
    //   66: invokestatic 117	kkkkkk/xtxtxt:bиии043804380438и0438ии	(Ljava/lang/String;Ljava/lang/String;)V
    //   69: aload_1
    //   70: invokestatic 123	android/text/TextUtils:isEmpty	(Ljava/lang/CharSequence;)Z
    //   73: ifne +60 -> 133
    //   76: aload_0
    //   77: getfield 92	kkkkkk/dxxdxd:b044Bыыыы044B044B044B044B	Ljava/util/HashSet;
    //   80: astore_3
    //   81: getstatic 53	kkkkkk/dxxdxd:bы044Bыыы044B044B044B044B	I
    //   84: getstatic 55	kkkkkk/dxxdxd:bыы044Bыы044B044B044B044B	I
    //   87: iadd
    //   88: getstatic 53	kkkkkk/dxxdxd:bы044Bыыы044B044B044B044B	I
    //   91: imul
    //   92: getstatic 57	kkkkkk/dxxdxd:b044Bы044Bыы044B044B044B044B	I
    //   95: irem
    //   96: getstatic 63	kkkkkk/dxxdxd:b044B044Bыыы044B044B044B044B	I
    //   99: if_icmpeq +17 -> 116
    //   102: invokestatic 61	kkkkkk/dxxdxd:b044504450445хххх044504450445	()I
    //   105: istore_2
    //   106: iload_2
    //   107: putstatic 53	kkkkkk/dxxdxd:bы044Bыыы044B044B044B044B	I
    //   110: invokestatic 61	kkkkkk/dxxdxd:b044504450445хххх044504450445	()I
    //   113: putstatic 63	kkkkkk/dxxdxd:b044B044Bыыы044B044B044B044B	I
    //   116: aload_3
    //   117: aload_1
    //   118: invokevirtual 127	java/util/HashSet:contains	(Ljava/lang/Object;)Z
    //   121: ifeq +12 -> 133
    //   124: aload_0
    //   125: getfield 92	kkkkkk/dxxdxd:b044Bыыыы044B044B044B044B	Ljava/util/HashSet;
    //   128: aload_1
    //   129: invokevirtual 163	java/util/HashSet:remove	(Ljava/lang/Object;)Z
    //   132: pop
    //   133: return
    //   134: astore_1
    //   135: aload_1
    //   136: athrow
    //   137: astore_1
    //   138: aload_1
    //   139: athrow
    //   140: astore_1
    //   141: aload_1
    //   142: athrow
    //   143: astore_1
    //   144: aload_1
    //   145: athrow
    // Local variable table:
    //   start	length	slot	name	signature
    //   0	146	0	this	dxxdxd
    //   0	146	1	paramString	String
    //   105	2	2	i	int
    //   3	114	3	localObject	Object
    //   27	35	4	localStringBuilder	StringBuilder
    // Exception table:
    //   from	to	target	type
    //   0	29	134	java/lang/Exception
    //   116	133	134	java/lang/Exception
    //   106	116	137	java/lang/Exception
    //   135	137	137	java/lang/Exception
    //   141	143	137	java/lang/Exception
    //   60	81	140	java/lang/Exception
    //   81	106	143	java/lang/Exception
  }
  
  public void bхххх0445хх044504450445()
  {
    throw new Runtime("d2j fail translate: java.lang.IndexOutOfBoundsException: fromIndex < 0: -1\n\tat java.util.BitSet.nextSetBit(BitSet.java:712)\n\tat com.googlecode.dex2jar.ir.ts.array.FillArrayTransformer.makeSureAllElementAreAssigned(FillArrayTransformer.java:505)\n\tat com.googlecode.dex2jar.ir.ts.array.FillArrayTransformer.transformReportChanged(FillArrayTransformer.java:123)\n\tat com.googlecode.dex2jar.ir.ts.StatedTransformer.transform(StatedTransformer.java:10)\n\tat com.googlecode.d2j.dex.Dex2jar$2.optimize(Dex2jar.java:149)\n\tat com.googlecode.d2j.dex.Dex2Asm.convertCode(Dex2Asm.java:414)\n\tat com.googlecode.d2j.dex.ExDex2Asm.convertCode(ExDex2Asm.java:42)\n\tat com.googlecode.d2j.dex.Dex2jar$2.convertCode(Dex2jar.java:128)\n\tat com.googlecode.d2j.dex.Dex2Asm.convertMethod(Dex2Asm.java:509)\n\tat com.googlecode.d2j.dex.Dex2Asm.convertClass(Dex2Asm.java:406)\n\tat com.googlecode.d2j.dex.Dex2Asm.convertDex(Dex2Asm.java:422)\n\tat com.googlecode.d2j.dex.Dex2jar.doTranslate(Dex2jar.java:172)\n\tat com.googlecode.d2j.dex.Dex2jar.to(Dex2jar.java:272)\n\tat com.googlecode.dex2jar.tools.Dex2jarCmd.doCommandLine(Dex2jarCmd.java:108)\n\tat com.googlecode.dex2jar.tools.BaseCmd.doMain(BaseCmd.java:288)\n\tat com.googlecode.dex2jar.tools.Dex2jarCmd.main(Dex2jarCmd.java:32)\n");
  }
}
