package kkkkkk;

import android.content.ContentValues;
import android.content.Context;
import android.content.res.Resources;
import android.database.Cursor;
import android.os.Bundle;
import android.support.annotation.NonNull;
import android.text.TextUtils;
import com.liveperson.infra.messaging.R.integer;
import java.util.ArrayList;
import java.util.HashMap;
import java.util.HashSet;
import java.util.Iterator;
import java.util.List;
import java.util.Map;
import java.util.concurrent.TimeUnit;
import org.jetbrains.annotations.NotNull;
import org.jetbrains.annotations.Nullable;

public class eeefee
  extends xxxdxx
  implements vvovov, xxddxd
{
  public static final String b04420442044204420442тт0442т = "przp\n\021\007|\001\002\026\017\001~\t";
  public static int b0442044204420442т0442т0442т = 1;
  public static final String b044204420442т0442тт0442т = gguuuu.bккккк043Aкк043A043A(b044204420442т0442тт0442т, '!', '\002');
  public static final String b044204420442тт0442т0442т = "\002z\016\023\nv|r}zq\013mxv}kwwdvjom}f`";
  public static final String b04420442т04420442тт0442т = "\020\037\033\f\016\f\t\032\032$\031\023\006\002\024\004\035\017{\016\030z\006\004\013x\005\005q\004w|z";
  public static final String b04420442ттт0442т0442т = "LG\\cHUU^N\\^MaW^^pe[cl[[w\\m\\p";
  public static final String b0442т044204420442тт0442т = "XgcTVTQbbla[NJ\\LeSIZaDOMTBNN;MAFDTAF9";
  public static int b0442т04420442т0442т0442т = 17;
  public static final String b0442т0442тт0442т0442т = "[VkrWddm]km\\pfmmucukjz\007qm";
  public static final String b0442тт04420442тт0442т = "w\007\003susp\002\002\f\001zmi{k\005grpweqq^pdigwf\\[s[afbb";
  public static final String b0442тттт0442т0442т = "72GN3@@I9GI8LBII[>QRIHPHHdGNMW^";
  public static final String bт0442044204420442тт0442т = "7FB3530AAK@:-);+D914&!#=*/\"";
  public static int bт044204420442т0442т0442т = 0;
  public static final String bт04420442тт0442т0442т = "+&;B'44=-;=,@6==OEFESI?D=";
  public static final String bт0442т04420442тт0442т = "\n\031\025\006\b\006\003\024\024\036\023\r{\016}\027y\005\003\nw\004\004p\003v{y\n}|y";
  public static final String bт0442ттт0442т0442т = "\030\023(/\024!!*\032(*\031-#**<'#";
  public static final String bтт044204420442тт0442т = "\026'%\030\034\034\033.0<3/$\"6(C+595H?=8";
  public static final String bтт0442тт0442т0442т = "ngzbmkr`llYk_dbreeQcS";
  public static final String bттт04420442тт0442т = gguuuu.bккккк043Aкк043A043A(bттт04420442тт0442т, 'é', '\005');
  private static final String bттт0442т0442т0442т = eeefee.class.getSimpleName();
  public static int bтттт04420442т0442т = 2;
  public static final String bттттт0442т0442т = "\033\033!\025,1%\031\033\032,#\023\017\027'\n\016\006\022\n\007\005";
  public Map<String, nfnfnn> b04420442т0442т0442т0442т = new HashMap();
  public HashSet<Integer> b0442тт0442т0442т0442т = new HashSet();
  public final kkyykk bт0442т0442т0442т0442т;
  public Map<String, nfnfnn> bтт04420442т0442т0442т = new HashMap();
  
  static
  {
    b0442тт04420442тт0442т = gguuuu.bк043Aккк043Aкк043A043A(b0442тт04420442тт0442т, '', '¹', '\002');
    bт0442т04420442тт0442т = gguuuu.bккккк043Aкк043A043A(bт0442т04420442тт0442т, '¼', '\002');
    b04420442т04420442тт0442т = gguuuu.bккккк043Aкк043A043A(b04420442т04420442тт0442т, ';', '\002');
    bтт044204420442тт0442т = gguuuu.bккккк043Aкк043A043A(bтт044204420442тт0442т, 'Å', '\001');
    b0442т044204420442тт0442т = gguuuu.bк043Aккк043Aкк043A043A(b0442т044204420442тт0442т, '\035', 'Ë', '\002');
    bт0442044204420442тт0442т = gguuuu.bк043Aккк043Aкк043A043A(bт0442044204420442тт0442т, 'ï', 'e', '\000');
    String str = b04420442044204420442тт0442т;
    switch (1)
    {
    case 0: 
    default: 
      for (;;)
      {
        switch (1)
        {
        }
      }
    }
    if ((b0442т04420442т0442т0442т + b0442044204420442т0442т0442т) * b0442т04420442т0442т0442т % bтттт04420442т0442т != bт044204420442т0442т0442т)
    {
      int i = b0442т04420442т0442т0442т;
      switch (i * (b0442044204420442т0442т0442т + i) % bтттт04420442т0442т)
      {
      default: 
        b0442т04420442т0442т0442т = b04240424ФФФ04240424042404240424();
        bт044204420442т0442т0442т = b04240424ФФФ04240424042404240424();
      }
      b0442т04420442т0442т0442т = b04240424ФФФ04240424042404240424();
      bт044204420442т0442т0442т = b04240424ФФФ04240424042404240424();
    }
    b04420442044204420442тт0442т = gguuuu.bк043Aккк043Aкк043A043A(str, 'ô', '6', '\003');
    bттттт0442т0442т = gguuuu.bккккк043Aкк043A043A(bттттт0442т0442т, '¨', '\005');
    b0442тттт0442т0442т = gguuuu.bк043Aккк043Aкк043A043A(b0442тттт0442т0442т, '­', 'Á', '\001');
    bт0442ттт0442т0442т = gguuuu.bк043Aккк043Aкк043A043A(bт0442ттт0442т0442т, '', 'Ã', '\001');
    b04420442ттт0442т0442т = gguuuu.bккккк043Aкк043A043A(b04420442ттт0442т0442т, 'Ô', '\001');
    bтт0442тт0442т0442т = gguuuu.bккккк043Aкк043A043A(bтт0442тт0442т0442т, 'Û', '\005');
    b0442т0442тт0442т0442т = gguuuu.bккккк043Aкк043A043A(b0442т0442тт0442т0442т, 'Z', '\001');
    bт04420442тт0442т0442т = gguuuu.bккккк043Aкк043A043A(bт04420442тт0442т0442т, 'o', '\004');
    str = b044204420442тт0442т0442т;
    switch (0)
    {
    case 1: 
    default: 
      for (;;)
      {
        switch (1)
        {
        }
      }
    }
    b044204420442тт0442т0442т = gguuuu.bккккк043Aкк043A043A(str, 'I', '\005');
  }
  
  public eeefee(kkyykk paramKkyykk)
  {
    super(gguuuu.bккккк043Aкк043A043A("`kip^jjWi]b`d", 'À', '\003'));
    this.bт0442т0442т0442т0442т = paramKkyykk;
  }
  
  private static ContentValues b0424042404240424Ф04240424042404240424(nfnfnn paramNfnfnn)
  {
    int j = -1;
    try
    {
      ContentValues localContentValues = new ContentValues();
      String str1 = gguuuu.bк043Aккк043Aкк043A043A("_jho]iiVh\\a_9S", '©', '&', '\000');
      try
      {
        localContentValues.put(str1, paramNfnfnn.b044D044Dээ044Dэ044Dэ044Dэ());
      }
      catch (Exception paramNfnfnn)
      {
        int i;
        throw paramNfnfnn;
      }
      str1 = gguuuu.bк043Aккк043Aкк043A043A("*;+90\0262", '¤', '"', '\003');
      localContentValues.put(str1, paramNfnfnn.bээээ044Dэ044Dэ044Dэ());
      localContentValues.put(gguuuu.bк043Aккк043Aкк043A043A("\013x\013\001\020e\002", 'X', '=', '\003'), paramNfnfnn.b044D044Dэ044D044Dэ044Dэ044Dэ());
      if (paramNfnfnn.b044Dээ044D044Dэ044Dэ044Dэ() != null)
      {
        i = paramNfnfnn.b044Dээ044D044Dэ044Dэ044Dэ().ordinal();
        str1 = gguuuu.bк043Aккк043Aкк043A043A("vvbtd", 'í', 'ð', '\000');
        localContentValues.put(str1, Integer.valueOf(i));
        if (paramNfnfnn.bээ044Dэ044Dэ044Dэ044Dэ() == null) {
          break label389;
        }
      }
      label389:
      for (i = paramNfnfnn.bээ044Dэ044Dэ044Dэ044Dэ().ordinal();; i = -1)
      {
        if ((b0442т04420442т0442т0442т + b0442044204420442т0442т0442т) * b0442т04420442т0442т0442т % bтттт04420442т0442т != bт044204420442т0442т0442т)
        {
          b0442т04420442т0442т0442т = b04240424ФФФ04240424042404240424();
          bт044204420442т0442т0442т = b04240424ФФФ04240424042404240424();
        }
        localContentValues.put(gguuuu.bккккк043Aкк043A043A("polXlpfZ", 'Õ', '\002'), Integer.valueOf(i));
        localContentValues.put(gguuuu.bк043Aккк043Aкк043A043A("^qrihphhFmlv}So", '', '', '\001'), paramNfnfnn.b044D044D044D044Dээ044Dэ044Dэ());
        localContentValues.put(gguuuu.bк043Aккк043Aкк043A043A("ZLWZIVV@IC", '\005', '', '\002'), Long.valueOf(paramNfnfnn.b044D044D044Dэ044Dэ044Dэ044Dэ()));
        i = j;
        if (paramNfnfnn.b044Dэээ044Dэ044Dэ044Dэ() != null) {
          i = paramNfnfnn.b044Dэээ044Dэ044Dэ044Dэ().ordinal();
        }
        str1 = gguuuu.bккккк043Aкк043A043A("<DFI:3E72C><", 'S', '\003');
        localContentValues.put(str1, Integer.valueOf(i));
        try
        {
          throw new NullPointerException();
        }
        catch (Exception localException1)
        {
          b0442т04420442т0442т0442т = 74;
          try
          {
            throw new NullPointerException();
          }
          catch (Exception localException2)
          {
            b0442т04420442т0442т0442т = 7;
            localContentValues.put(gguuuu.bккккк043Aкк043A043A("\\dfiZSg[^U", '\007', '\005'), Long.valueOf(paramNfnfnn.bэ044Dээ044Dэ044Dэ044Dэ()));
            localContentValues.put(gguuuu.bккккк043Aкк043A043A(";19B11-2C2F", 'B', '\001'), Integer.valueOf(paramNfnfnn.b044D044D044D044D044Dэ044Dэ044Dэ().b0445х04450445хх0445х04450445()));
            String str2 = gguuuu.bккккк043Aкк043A043A("\020\b\013|wys\001\006x", 'ä', '\005');
            localContentValues.put(str2, Integer.valueOf(paramNfnfnn.bээ044D044D044Dэ044Dэ044Dэ()));
            localContentValues.put(gguuuu.bк043Aккк043Aкк043A043A("77#34\0362&) ", 'ß', '£', '\000'), Long.valueOf(paramNfnfnn.bэээ044D044Dэ044Dэ044Dэ()));
            return localContentValues;
          }
        }
        i = -1;
        break;
      }
      switch (1)
      {
      }
    }
    catch (Exception paramNfnfnn)
    {
      throw paramNfnfnn;
    }
    for (;;)
    {
      switch (0)
      {
      }
    }
  }
  
  private long b042404240424Ф042404240424042404240424(String paramString)
  {
    try
    {
      int i = b0424Ф0424Ф042404240424042404240424(paramString).b044Dэ044Dэ044Dэ044Dэ044Dэ();
      if ((b0442т04420442т0442т0442т + b0442044204420442т0442т0442т) * b0442т04420442т0442т0442т % bтттт04420442т0442т != bт044204420442т0442т0442т)
      {
        b0442т04420442т0442т0442т = b04240424ФФФ04240424042404240424();
        bт044204420442т0442т0442т = b04240424ФФФ04240424042404240424();
        int j = b0442т04420442т0442т0442т;
        switch (j * (b0442044204420442т0442т0442т + j) % bтттт04420442т0442т)
        {
        default: 
          b0442т04420442т0442т0442т = 16;
          bт044204420442т0442т0442т = b04240424ФФФ04240424042404240424();
        }
      }
      return i;
    }
    catch (Exception paramString)
    {
      throw paramString;
    }
  }
  
  @NonNull
  private xddxxx<Boolean> b04240424Ф0424042404240424042404240424(String paramString, int paramInt1, int paramInt2, boolean paramBoolean, nfnfnn paramNfnfnn)
  {
    paramString = new xddxxx(new eeefee.11(this, paramInt1, paramInt2, paramString, paramNfnfnn, paramBoolean));
    paramInt1 = b0442т04420442т0442т0442т;
    if ((b0442т04420442т0442т0442т + b0442044204420442т0442т0442т) * b0442т04420442т0442т0442т % bтттт04420442т0442т != bт044204420442т0442т0442т)
    {
      b0442т04420442т0442т0442т = b04240424ФФФ04240424042404240424();
      bт044204420442т0442т0442т = 64;
    }
    switch (paramInt1 * (b0442044204420442т0442т0442т + paramInt1) % bтттт04420442т0442т)
    {
    default: 
      b0442т04420442т0442т0442т = 2;
      bт044204420442т0442т0442т = b04240424ФФФ04240424042404240424();
    }
    return paramString;
  }
  
  public static int b04240424ФФФ04240424042404240424()
  {
    return 11;
  }
  
  private xxxddd.dddxdd b0424Ф0424ФФ04240424042404240424(ffnfnn paramFfnfnn, boolean paramBoolean)
  {
    try
    {
      xxxddd.dddxdd localDddxdd = xxxddd.dddxdd.NOT_SHOWN;
      if (paramBoolean)
      {
        xxxddd localXxxddd = paramFfnfnn.b043Cмм043Cм043C043C043Cм;
        if (localXxxddd != null)
        {
          int i = 3;
          try
          {
            for (;;)
            {
              i /= 0;
            }
            try
            {
              b0442т04420442т0442т0442т = b04240424ФФФ04240424042404240424();
              return paramFfnfnn.b043Cмм043Cм043C043C043Cм.b04450445хх0445х0445х04450445();
            }
            catch (Exception paramFfnfnn)
            {
              throw paramFfnfnn;
            }
          }
          catch (Exception localException) {}
        }
      }
      else
      {
        paramFfnfnn = xxxddd.dddxdd.NO_NEED_TO_SHOW;
        return paramFfnfnn;
      }
    }
    catch (Exception paramFfnfnn)
    {
      throw paramFfnfnn;
    }
    return localException;
  }
  
  private Cursor b0424ФФ0424042404240424042404240424(String paramString)
  {
    dddxxx localDddxxx = b04380438и0438и0438ииии();
    String str = gguuuu.bккккк043Aкк043A043A("remgfx%0'n{yx,p}}\007v\005\007u\n\007\007\r:\023\005\003\021\005@\026\004\026\f\013\033p\rIgKkM\020\036\025Q\037\025(*\026+\036,1!/\0352%27(2(+f\005hv{k<@35Cq5MtIK9KN:PFKD%'6'\005RPUR^\013\035", '¾', '\004');
    if ((b0442т04420442т0442т0442т + b0442044204420442т0442т0442т) * b0442т04420442т0442т0442т % bФФФФФ04240424042404240424() != bт044204420442т0442т0442т)
    {
      int i = b0442т04420442т0442т0442т;
      switch (i * (b0442044204420442т0442т0442т + i) % bтттт04420442т0442т)
      {
      default: 
        b0442т04420442т0442т0442т = 98;
        bт044204420442т0442т0442т = 62;
      }
      b0442т04420442т0442т0442т = b04240424ФФФ04240424042404240424();
      bт044204420442т0442т0442т = 81;
    }
    return localDddxxx.b043804380438и04380438ииии(str, new Object[] { paramString });
  }
  
  public static int b0424ФФФФ04240424042404240424()
  {
    return 0;
  }
  
  /* Error */
  private void b044D044D044D044D044Dэээээ(nfnfnn paramNfnfnn)
  {
    // Byte code:
    //   0: iconst_2
    //   1: istore_2
    //   2: new 392	kkkkkk/eeefee$10
    //   5: dup
    //   6: aload_0
    //   7: aload_1
    //   8: invokespecial 395	kkkkkk/eeefee$10:<init>	(Lkkkkkk/eeefee;Lkkkkkk/nfnfnn;)V
    //   11: astore_1
    //   12: aload_1
    //   13: invokestatic 401	kkkkkk/dxxxxx:bиии04380438и0438иии	(Ljava/lang/Runnable;)V
    //   16: iload_2
    //   17: iconst_0
    //   18: idiv
    //   19: istore_3
    //   20: iload_3
    //   21: istore_2
    //   22: getstatic 111	kkkkkk/eeefee:b0442т04420442т0442т0442т	I
    //   25: getstatic 113	kkkkkk/eeefee:b0442044204420442т0442т0442т	I
    //   28: iadd
    //   29: getstatic 111	kkkkkk/eeefee:b0442т04420442т0442т0442т	I
    //   32: imul
    //   33: getstatic 115	kkkkkk/eeefee:bтттт04420442т0442т	I
    //   36: irem
    //   37: getstatic 117	kkkkkk/eeefee:bт044204420442т0442т0442т	I
    //   40: if_icmpeq -24 -> 16
    //   43: invokestatic 121	kkkkkk/eeefee:b04240424ФФФ04240424042404240424	()I
    //   46: putstatic 111	kkkkkk/eeefee:b0442т04420442т0442т0442т	I
    //   49: invokestatic 121	kkkkkk/eeefee:b04240424ФФФ04240424042404240424	()I
    //   52: putstatic 117	kkkkkk/eeefee:bт044204420442т0442т0442т	I
    //   55: iload_3
    //   56: istore_2
    //   57: goto -41 -> 16
    //   60: astore_1
    //   61: invokestatic 121	kkkkkk/eeefee:b04240424ФФФ04240424042404240424	()I
    //   64: putstatic 111	kkkkkk/eeefee:b0442т04420442т0442т0442т	I
    //   67: return
    //   68: astore_1
    //   69: aload_1
    //   70: athrow
    //   71: astore_1
    //   72: aload_1
    //   73: athrow
    //   74: astore_1
    //   75: aload_1
    //   76: athrow
    // Local variable table:
    //   start	length	slot	name	signature
    //   0	77	0	this	eeefee
    //   0	77	1	paramNfnfnn	nfnfnn
    //   1	56	2	i	int
    //   19	37	3	j	int
    // Exception table:
    //   from	to	target	type
    //   16	20	60	java/lang/Exception
    //   2	12	68	java/lang/Exception
    //   61	67	71	java/lang/Exception
    //   69	71	71	java/lang/Exception
    //   75	77	71	java/lang/Exception
    //   12	16	74	java/lang/Exception
  }
  
  /* Error */
  public static void b044D044D044D044Dээээээ(nfnfnn paramNfnfnn)
  {
    // Byte code:
    //   0: new 404	android/os/Bundle
    //   3: dup
    //   4: invokespecial 405	android/os/Bundle:<init>	()V
    //   7: astore 4
    //   9: aload 4
    //   11: ldc_w 407
    //   14: sipush 147
    //   17: bipush 25
    //   19: iconst_0
    //   20: invokestatic 97	kkkkkk/gguuuu:bк043Aккк043Aкк043A043A	(Ljava/lang/String;CCC)Ljava/lang/String;
    //   23: aload_0
    //   24: invokevirtual 205	kkkkkk/nfnfnn:b044D044Dэ044D044Dэ044Dэ044Dэ	()Ljava/lang/String;
    //   27: invokevirtual 410	android/os/Bundle:putString	(Ljava/lang/String;Ljava/lang/String;)V
    //   30: ldc_w 412
    //   33: bipush 101
    //   35: iconst_0
    //   36: invokestatic 89	kkkkkk/gguuuu:bккккк043Aкк043A043A	(Ljava/lang/String;CC)Ljava/lang/String;
    //   39: astore 5
    //   41: aload_0
    //   42: invokevirtual 191	kkkkkk/nfnfnn:b044D044Dээ044Dэ044Dэ044Dэ	()Ljava/lang/String;
    //   45: astore 6
    //   47: aload 4
    //   49: aload 5
    //   51: aload 6
    //   53: invokevirtual 410	android/os/Bundle:putString	(Ljava/lang/String;Ljava/lang/String;)V
    //   56: aload 4
    //   58: ldc_w 414
    //   61: sipush 205
    //   64: iconst_0
    //   65: invokestatic 89	kkkkkk/gguuuu:bккккк043Aкк043A043A	(Ljava/lang/String;CC)Ljava/lang/String;
    //   68: aload_0
    //   69: invokevirtual 209	kkkkkk/nfnfnn:b044Dээ044D044Dэ044Dэ044Dэ	()Lkkkkkk/dxdxdd;
    //   72: invokevirtual 214	kkkkkk/dxdxdd:ordinal	()I
    //   75: invokevirtual 418	android/os/Bundle:putInt	(Ljava/lang/String;I)V
    //   78: ldc_w 420
    //   81: bipush 77
    //   83: iconst_0
    //   84: invokestatic 89	kkkkkk/gguuuu:bккккк043Aкк043A043A	(Ljava/lang/String;CC)Ljava/lang/String;
    //   87: astore 5
    //   89: getstatic 111	kkkkkk/eeefee:b0442т04420442т0442т0442т	I
    //   92: getstatic 113	kkkkkk/eeefee:b0442044204420442т0442т0442т	I
    //   95: iadd
    //   96: getstatic 111	kkkkkk/eeefee:b0442т04420442т0442т0442т	I
    //   99: imul
    //   100: invokestatic 337	kkkkkk/eeefee:bФФФФФ04240424042404240424	()I
    //   103: irem
    //   104: getstatic 117	kkkkkk/eeefee:bт044204420442т0442т0442т	I
    //   107: if_icmpeq +14 -> 121
    //   110: bipush 96
    //   112: putstatic 111	kkkkkk/eeefee:b0442т04420442т0442т0442т	I
    //   115: invokestatic 121	kkkkkk/eeefee:b04240424ФФФ04240424042404240424	()I
    //   118: putstatic 117	kkkkkk/eeefee:bт044204420442т0442т0442т	I
    //   121: aload 4
    //   123: aload 5
    //   125: aload_0
    //   126: invokevirtual 239	kkkkkk/nfnfnn:b044D044D044D044Dээ044Dэ044Dэ	()Ljava/lang/String;
    //   129: invokevirtual 410	android/os/Bundle:putString	(Ljava/lang/String;Ljava/lang/String;)V
    //   132: getstatic 145	kkkkkk/eeefee:bттт0442т0442т0442т	Ljava/lang/String;
    //   135: astore_0
    //   136: new 422	java/lang/StringBuilder
    //   139: dup
    //   140: invokespecial 423	java/lang/StringBuilder:<init>	()V
    //   143: ldc_w 425
    //   146: sipush 150
    //   149: bipush 93
    //   151: iconst_1
    //   152: invokestatic 97	kkkkkk/gguuuu:bк043Aккк043Aкк043A043A	(Ljava/lang/String;CCC)Ljava/lang/String;
    //   155: invokevirtual 429	java/lang/StringBuilder:append	(Ljava/lang/String;)Ljava/lang/StringBuilder;
    //   158: aload 4
    //   160: invokevirtual 432	java/lang/StringBuilder:append	(Ljava/lang/Object;)Ljava/lang/StringBuilder;
    //   163: invokevirtual 435	java/lang/StringBuilder:toString	()Ljava/lang/String;
    //   166: astore 5
    //   168: aload_0
    //   169: aload 5
    //   171: invokestatic 440	kkkkkk/xtxtxt:bии0438и04380438и0438ии	(Ljava/lang/String;Ljava/lang/String;)V
    //   174: getstatic 111	kkkkkk/eeefee:b0442т04420442т0442т0442т	I
    //   177: istore_1
    //   178: getstatic 113	kkkkkk/eeefee:b0442044204420442т0442т0442т	I
    //   181: istore_2
    //   182: getstatic 115	kkkkkk/eeefee:bтттт04420442т0442т	I
    //   185: istore_3
    //   186: iload_1
    //   187: iload_2
    //   188: iload_1
    //   189: iadd
    //   190: imul
    //   191: iload_3
    //   192: irem
    //   193: tableswitch	default:+19->212, 0:+31->224
    //   212: invokestatic 121	kkkkkk/eeefee:b04240424ФФФ04240424042404240424	()I
    //   215: putstatic 111	kkkkkk/eeefee:b0442т04420442т0442т0442т	I
    //   218: invokestatic 121	kkkkkk/eeefee:b04240424ФФФ04240424042404240424	()I
    //   221: putstatic 117	kkkkkk/eeefee:bт044204420442т0442т0442т	I
    //   224: ldc_w 442
    //   227: iconst_3
    //   228: sipush 165
    //   231: iconst_1
    //   232: invokestatic 97	kkkkkk/gguuuu:bк043Aккк043Aкк043A043A	(Ljava/lang/String;CCC)Ljava/lang/String;
    //   235: aload 4
    //   237: invokestatic 448	kkkkkk/hbhbbh:bШ042804280428Ш0428042804280428Ш	(Ljava/lang/String;Landroid/os/Bundle;)V
    //   240: return
    //   241: astore_0
    //   242: aload_0
    //   243: athrow
    //   244: astore_0
    //   245: aload_0
    //   246: athrow
    //   247: astore_0
    //   248: aload_0
    //   249: athrow
    //   250: astore_0
    //   251: aload_0
    //   252: athrow
    // Local variable table:
    //   start	length	slot	name	signature
    //   0	253	0	paramNfnfnn	nfnfnn
    //   177	14	1	i	int
    //   181	9	2	j	int
    //   185	8	3	k	int
    //   7	229	4	localBundle	Bundle
    //   39	131	5	str1	String
    //   45	7	6	str2	String
    // Exception table:
    //   from	to	target	type
    //   0	9	241	java/lang/Exception
    //   47	89	241	java/lang/Exception
    //   121	168	241	java/lang/Exception
    //   224	240	241	java/lang/Exception
    //   212	224	244	java/lang/Exception
    //   242	244	244	java/lang/Exception
    //   248	250	244	java/lang/Exception
    //   9	47	247	java/lang/Exception
    //   168	174	247	java/lang/Exception
    //   174	186	250	java/lang/Exception
  }
  
  private void b044D044D044Dэээээээ(String paramString1, String paramString2)
  {
    try
    {
      localObject = (nfnfnn)this.b04420442т0442т0442т0442т.get(paramString1);
      i = b0442т04420442т0442т0442т;
      switch (i * (b0442044204420442т0442т0442т + i) % bтттт04420442т0442т)
      {
      default: 
        b0442т04420442т0442т0442т = b04240424ФФФ04240424042404240424();
        bт044204420442т0442т0442т = b04240424ФФФ04240424042404240424();
      }
      if (localObject != null)
      {
        boolean bool = ((nfnfnn)localObject).b044D044Dээ044Dэ044Dэ044Dэ().equals(paramString2);
        if (!bool) {}
      }
    }
    catch (Exception paramString1)
    {
      Object localObject;
      int i;
      StringBuilder localStringBuilder;
      int j;
      int k;
      int m;
      throw paramString1;
    }
    try
    {
      this.b04420442т0442т0442т0442т.remove(paramString1);
      localObject = this.bтт04420442т0442т0442т;
      ((Map)localObject).remove(paramString2);
      localObject = bттт0442т0442т0442т;
      localStringBuilder = new StringBuilder();
    }
    catch (Exception paramString1)
    {
      throw paramString1;
    }
    paramString2 = localStringBuilder.append(gguuuu.bккккк043Aкк043A043A("Ymvy\002u{u/s\001\001\ny\b\nx\r\003\n\n<f\003Y@", 'C', '\004')).append(paramString2);
    i = b0442т04420442т0442т0442т;
    j = b0442044204420442т0442т0442т;
    k = b0442т04420442т0442т0442т;
    m = bтттт04420442т0442т;
    if ((i + j) * k % m != bт044204420442т0442т0442т)
    {
      b0442т04420442т0442т0442т = 44;
      bт044204420442т0442т0442т = b04240424ФФФ04240424042404240424();
    }
    paramString1 = paramString2.append(gguuuu.bккккк043Aкк043A043A("\031lXh\\Yg;U*\017", 'Ö', '\002')).append(paramString1);
    xtxtxt.bии0438и04380438и0438ии((String)localObject, paramString1.toString());
    return;
    switch (0)
    {
    }
    for (;;)
    {
      switch (1)
      {
      }
    }
  }
  
  private void b044D044Dэ044Dээээээ(nfnfnn paramNfnfnn, ArrayList<gggjjg> paramArrayList, boolean paramBoolean, dddxxd<nfnfnn, Exception> paramDddxxd)
  {
    switch (1)
    {
    case 0: 
    default: 
      for (;;)
      {
        switch (1)
        {
        }
      }
    }
    boolean bool = paramNfnfnn.bэ044D044D044D044Dэ044Dэ044Dэ();
    if (paramArrayList.size() == 0)
    {
      xtxtxt.bии0438и04380438и0438ии(bттт0442т0442т0442т, gguuuu.bк043Aккк043Aкк043A043A("<^\020^WfgV]\\k\031ci\034nsdrz\"uixvvv|o9", '\005', '', '\001'));
      if (paramNfnfnn.b044Dэ044Dэ044Dэ044Dэ044Dэ() == -1)
      {
        i = 0;
        paramNfnfnn = bээ044D044D044Dэээээ(paramNfnfnn.b044D044Dээ044Dэ044Dэ044Dэ(), i, 1, bool);
        if ((b04240424ФФФ04240424042404240424() + b0442044204420442т0442т0442т) * b04240424ФФФ04240424042404240424() % bтттт04420442т0442т != bт044204420442т0442т0442т)
        {
          b0442т04420442т0442т0442т = b04240424ФФФ04240424042404240424();
          bт044204420442т0442т0442т = 63;
        }
        if (paramNfnfnn != null) {
          paramNfnfnn.b0438ии0438ии0438иии();
        }
        paramDddxxd.b0445х0445х0445хх044504450445(new Exception(gguuuu.bккккк043Aкк043A043A("Ipruy\037pbopfmk\027#\025bb\022^UbaNSP]", 'ü', '\003')));
        return;
        label177:
        do
        {
          i -= 1;
          if (i < 0) {
            break;
          }
        } while (((gggjjg)paramArrayList.get(i)).b044Bы044Bы044Bыыы044B <= -1);
      }
    }
    for (int i = ((gggjjg)paramArrayList.get(i)).b044Bы044Bы044Bыыы044B;; i = -1)
    {
      Object localObject = bттт0442т0442т0442т;
      StringBuilder localStringBuilder = new StringBuilder();
      String str = paramNfnfnn.b044D044Dээ044Dэ044Dэ044Dэ();
      if ((b0442т04420442т0442т0442т + b0442044204420442т0442т0442т) * b0442т04420442т0442т0442т % bФФФФФ04240424042404240424() != b0424ФФФФ04240424042404240424())
      {
        b0442т04420442т0442т0442т = 5;
        bт044204420442т0442т0442т = 42;
      }
      xtxtxt.bии0438и04380438и0438ии((String)localObject, str + gguuuu.bк043Aккк043Aкк043A043A(")7+Xn\002\0040\005w\005\nz\005z}9\022\002\f\023?\023\007\006\t\016\034\f\fH\023\031K\036#\024\"*Q \031()\030\037\036-Z.\"1///5(}d", '0', 'X', '\003') + i);
      if ((i == -1) || (i < paramNfnfnn.b044Dэ044Dэ044Dэ044Dэ044Dэ()))
      {
        xtxtxt.bии0438и04380438и0438ии(bттт0442т0442т0442т, paramNfnfnn.b044D044Dээ044Dэ044Dэ044Dэ() + gguuuu.bккккк043Aкк043A043A("t\003v<B>I\003Q}QEDGLZJ\006HVb\nYQd\016bUbgXbX[\027", '*', '\004') + i);
        paramDddxxd.bх04450445х0445хх044504450445(paramNfnfnn);
        return;
        i = paramNfnfnn.b044Dэ044Dэ044Dэ044Dэ044Dэ();
        break;
      }
      localObject = bээ044D044D044Dэээээ(paramNfnfnn.b044D044Dээ044Dэ044Dэ044Dэ(), i, i - paramNfnfnn.b044Dэ044Dэ044Dэ044Dэ044Dэ(), bool);
      ((xddxxx)localObject).b04380438и0438ии0438иии(new eeefee.26(this, paramNfnfnn, paramArrayList, paramBoolean, bool, paramDddxxd));
      ((xddxxx)localObject).b0438ии0438ии0438иии();
      return;
      i = paramArrayList.size() - 1;
      break label177;
    }
  }
  
  /* Error */
  private boolean b044D044Dээ044Dэээээ(xddxdd paramXddxdd, String paramString, long paramLong, boolean paramBoolean)
  {
    // Byte code:
    //   0: invokestatic 121	kkkkkk/eeefee:b04240424ФФФ04240424042404240424	()I
    //   3: getstatic 113	kkkkkk/eeefee:b0442044204420442т0442т0442т	I
    //   6: iadd
    //   7: invokestatic 121	kkkkkk/eeefee:b04240424ФФФ04240424042404240424	()I
    //   10: imul
    //   11: getstatic 115	kkkkkk/eeefee:bтттт04420442т0442т	I
    //   14: irem
    //   15: getstatic 117	kkkkkk/eeefee:bт044204420442т0442т0442т	I
    //   18: if_icmpeq +45 -> 63
    //   21: getstatic 111	kkkkkk/eeefee:b0442т04420442т0442т0442т	I
    //   24: getstatic 113	kkkkkk/eeefee:b0442044204420442т0442т0442т	I
    //   27: iadd
    //   28: getstatic 111	kkkkkk/eeefee:b0442т04420442т0442т0442т	I
    //   31: imul
    //   32: getstatic 115	kkkkkk/eeefee:bтттт04420442т0442т	I
    //   35: irem
    //   36: getstatic 117	kkkkkk/eeefee:bт044204420442т0442т0442т	I
    //   39: if_icmpeq +13 -> 52
    //   42: bipush 83
    //   44: putstatic 111	kkkkkk/eeefee:b0442т04420442т0442т0442т	I
    //   47: bipush 40
    //   49: putstatic 117	kkkkkk/eeefee:bт044204420442т0442т0442т	I
    //   52: bipush 67
    //   54: putstatic 111	kkkkkk/eeefee:b0442т04420442т0442т0442т	I
    //   57: invokestatic 121	kkkkkk/eeefee:b04240424ФФФ04240424042404240424	()I
    //   60: putstatic 117	kkkkkk/eeefee:bт044204420442т0442т0442т	I
    //   63: iload 5
    //   65: istore 6
    //   67: iload 5
    //   69: ifeq +36 -> 105
    //   72: aload_0
    //   73: aload_1
    //   74: invokespecial 528	kkkkkk/eeefee:bФФ04240424042404240424042404240424	(Lkkkkkk/xddxdd;)Z
    //   77: istore 6
    //   79: goto +48 -> 127
    //   82: iload 6
    //   84: ifeq +27 -> 111
    //   87: getstatic 145	kkkkkk/eeefee:bттт0442т0442т0442т	Ljava/lang/String;
    //   90: ldc_w 530
    //   93: bipush 42
    //   95: iconst_4
    //   96: invokestatic 89	kkkkkk/gguuuu:bккккк043Aкк043A043A	(Ljava/lang/String;CC)Ljava/lang/String;
    //   99: invokestatic 440	kkkkkk/xtxtxt:bии0438и04380438и0438ии	(Ljava/lang/String;Ljava/lang/String;)V
    //   102: iconst_0
    //   103: istore 6
    //   105: iload 6
    //   107: ireturn
    //   108: astore_1
    //   109: aload_1
    //   110: athrow
    //   111: aload_0
    //   112: aload_2
    //   113: lload_3
    //   114: iload 5
    //   116: invokespecial 534	kkkkkk/eeefee:bФ04240424ФФ04240424042404240424	(Ljava/lang/String;JZ)Z
    //   119: istore 5
    //   121: iload 5
    //   123: ireturn
    //   124: astore_1
    //   125: aload_1
    //   126: athrow
    //   127: iconst_0
    //   128: tableswitch	default:+24->152, 0:+-46->82, 1:+-1->127
    //   152: iconst_1
    //   153: tableswitch	default:+23->176, 0:+-26->127, 1:+-71->82
    //   176: goto -24 -> 152
    // Local variable table:
    //   start	length	slot	name	signature
    //   0	179	0	this	eeefee
    //   0	179	1	paramXddxdd	xddxdd
    //   0	179	2	paramString	String
    //   0	179	3	paramLong	long
    //   0	179	5	paramBoolean	boolean
    //   65	41	6	bool	boolean
    // Exception table:
    //   from	to	target	type
    //   111	121	108	java/lang/Exception
    //   72	79	124	java/lang/Exception
    //   87	102	124	java/lang/Exception
  }
  
  private boolean b044Dэ044D044D044Dэээээ(nfnfnn paramNfnfnn, boolean paramBoolean)
  {
    try
    {
      int i = paramNfnfnn.b044Dэ044Dэ044Dэ044Dэ044Dэ();
      i += 1;
      HashSet localHashSet;
      String str1;
      StringBuilder localStringBuilder;
      String str2;
      int j;
      int k;
      int m;
      int n;
      int i1;
      switch (1)
      {
      }
    }
    catch (Exception paramNfnfnn)
    {
      try
      {
        localHashSet = new HashSet();
        while (this.b0442тт0442т0442т0442т.contains(Integer.valueOf(i)))
        {
          str1 = bттт0442т0442т0442т;
          localStringBuilder = new StringBuilder();
          if ((b0442т04420442т0442т0442т + b0442044204420442т0442т0442т) * b0442т04420442т0442т0442т % bтттт04420442т0442т != bт044204420442т0442т0442т)
          {
            b0442т04420442т0442т0442т = b04240424ФФФ04240424042404240424();
            bт044204420442т0442т0442т = b04240424ФФФ04240424042404240424();
          }
          str2 = gguuuu.bк043Aккк043Aкк043A043A("%09E77sH;HM>H>A|", 'u', '(', '\001');
          j = b04240424ФФФ04240424042404240424();
          k = b0442044204420442т0442т0442т;
          m = b04240424ФФФ04240424042404240424();
          n = bтттт04420442т0442т;
          i1 = bт044204420442т0442т0442т;
          if ((j + k) * m % n != i1)
          {
            b0442т04420442т0442т0442т = 32;
            bт044204420442т0442т0442т = 76;
          }
          xtxtxt.bии0438и04380438и0438ии(str1, str2 + i + gguuuu.bк043Aккк043Aкк043A043A("/\003uu~*r{'zmi#pfw\037j^oo\032l]ilZf\023eVadS[OP\013", 'ÿ', 'o', '\002'));
          localHashSet.add(Integer.valueOf(i));
          paramNfnfnn.b044Dэ044Dээ044D044Dэ044Dэ(i);
          i += 1;
          paramBoolean = true;
        }
        if (!localHashSet.isEmpty())
        {
          break label232;
          paramNfnfnn = this.b0442тт0442т0442т0442т;
          paramNfnfnn.removeAll(localHashSet);
        }
        return paramBoolean;
      }
      catch (Exception paramNfnfnn)
      {
        throw paramNfnfnn;
      }
      paramNfnfnn = paramNfnfnn;
      throw paramNfnfnn;
    }
    for (;;)
    {
      label232:
      switch (1)
      {
      }
    }
  }
  
  public static void b044Dэ044D044Dээээээ(nfnfnn paramNfnfnn)
  {
    Bundle localBundle = new Bundle();
    localBundle.putString(gguuuu.bккккк043Aкк043A043A("fav}booxhvxg{qxx\013\001n\001vu\006\022|x", '', '\000'), paramNfnfnn.b044D044Dэ044D044Dэ044Dэ044Dэ());
    localBundle.putString(gguuuu.bк043Aккк043Aкк043A043A("aZmrU`^eS__L^RWUeNH", 'i', '', '\000'), paramNfnfnn.b044D044Dээ044Dэ044Dэ044Dэ());
    localBundle.putInt(gguuuu.bк043Aккк043Aкк043A043A("\r\006\031\036\001\f\n\021~\013\013w\n}\003\001\021\004\004o\002q", '', 'R', '\000'), paramNfnfnn.b044Dээ044D044Dэ044Dэ044Dэ().ordinal());
    localBundle.putString(gguuuu.bк043Aккк043Aкк043A043A(".':?\"-+2 ,,\031+\037$\"2\023$#\030\025\033\021\017)\n\017\f\024\031", '¾', ']', '\002'), paramNfnfnn.b044D044D044D044Dээ044Dэ044Dэ());
    Object localObject = gguuuu.bк043Aккк043Aкк043A043A("\035\026).\021\034\032!\017\033\033\b\032\016\023\021!\024\b\016\025\002\032|\fx\013", 'ó', '9', '\002');
    int i = paramNfnfnn.b044D044D044D044D044Dэ044Dэ044Dэ().b0445х04450445хх0445х04450445();
    if ((b0442т04420442т0442т0442т + b0442044204420442т0442т0442т) * b0442т04420442т0442т0442т % bтттт04420442т0442т != b0424ФФФФ04240424042404240424())
    {
      switch (0)
      {
      case 1: 
      default: 
        for (;;)
        {
          switch (1)
          {
          }
        }
      }
      b0442т04420442т0442т0442т = 34;
      bт044204420442т0442т0442т = 41;
    }
    localBundle.putInt((String)localObject, i);
    paramNfnfnn = bттт0442т0442т0442т;
    localObject = new StringBuilder();
    i = b0442т04420442т0442т0442т;
    switch (i * (b0442044204420442т0442т0442т + i) % bтттт04420442т0442т)
    {
    default: 
      b0442т04420442т0442т0442т = b04240424ФФФ04240424042404240424();
      bт044204420442т0442т0442т = b04240424ФФФ04240424042404240424();
    }
    xtxtxt.bии0438и04380438и0438ии(paramNfnfnn, gguuuu.bккккк043Aкк043A043A("Whpeime\035?jho]iiVh\\a_\0202A.@\013_YLHZJ\004ZKUH~\030|", '}', '\003') + localBundle);
    hbhbbh.bШ042804280428Ш0428042804280428Ш(gguuuu.bк043Aккк043Aкк043A043A("s\003~oqol}}\b|viewg\001cr_q{^ign\\hhUg[`^", 'ö', 'V', '\002'), localBundle);
  }
  
  /* Error */
  private static nfnfnn b044Dэ044Dэээээээ(Cursor paramCursor)
  {
    // Byte code:
    //   0: aload_0
    //   1: ifnull +205 -> 206
    //   4: aload_0
    //   5: invokeinterface 579 1 0
    //   10: ifeq +167 -> 177
    //   13: new 188	kkkkkk/nfnfnn
    //   16: dup
    //   17: aload_0
    //   18: invokespecial 582	kkkkkk/nfnfnn:<init>	(Landroid/database/Cursor;)V
    //   21: astore 4
    //   23: iconst_0
    //   24: tableswitch	default:+24->48, 0:+51->75, 1:+-1->23
    //   48: iconst_0
    //   49: tableswitch	default:+23->72, 0:+26->75, 1:+-26->23
    //   72: goto -24 -> 48
    //   75: aload_0
    //   76: invokeinterface 585 1 0
    //   81: getstatic 111	kkkkkk/eeefee:b0442т04420442т0442т0442т	I
    //   84: istore_1
    //   85: invokestatic 295	kkkkkk/eeefee:bФ0424ФФФ04240424042404240424	()I
    //   88: istore_2
    //   89: getstatic 111	kkkkkk/eeefee:b0442т04420442т0442т0442т	I
    //   92: istore_3
    //   93: iload_3
    //   94: getstatic 113	kkkkkk/eeefee:b0442044204420442т0442т0442т	I
    //   97: iload_3
    //   98: iadd
    //   99: imul
    //   100: getstatic 115	kkkkkk/eeefee:bтттт04420442т0442т	I
    //   103: irem
    //   104: tableswitch	default:+20->124, 0:+31->135
    //   124: invokestatic 121	kkkkkk/eeefee:b04240424ФФФ04240424042404240424	()I
    //   127: putstatic 111	kkkkkk/eeefee:b0442т04420442т0442т0442т	I
    //   130: bipush 47
    //   132: putstatic 117	kkkkkk/eeefee:bт044204420442т0442т0442т	I
    //   135: iload_1
    //   136: iload_2
    //   137: iload_1
    //   138: iadd
    //   139: imul
    //   140: getstatic 115	kkkkkk/eeefee:bтттт04420442т0442т	I
    //   143: irem
    //   144: tableswitch	default:+59->203, 0:+30->174
    //   164: bipush 8
    //   166: putstatic 111	kkkkkk/eeefee:b0442т04420442т0442т0442т	I
    //   169: bipush 22
    //   171: putstatic 117	kkkkkk/eeefee:bт044204420442т0442т0442т	I
    //   174: aload 4
    //   176: areturn
    //   177: aload_0
    //   178: invokeinterface 585 1 0
    //   183: goto +23 -> 206
    //   186: astore 4
    //   188: aload_0
    //   189: invokeinterface 585 1 0
    //   194: aload 4
    //   196: athrow
    //   197: astore_0
    //   198: aload_0
    //   199: athrow
    //   200: astore_0
    //   201: aload_0
    //   202: athrow
    //   203: goto -39 -> 164
    //   206: aconst_null
    //   207: areturn
    // Local variable table:
    //   start	length	slot	name	signature
    //   0	208	0	paramCursor	Cursor
    //   84	56	1	i	int
    //   88	51	2	j	int
    //   92	8	3	k	int
    //   21	154	4	localNfnfnn	nfnfnn
    //   186	9	4	localObject	Object
    // Exception table:
    //   from	to	target	type
    //   4	23	186	finally
    //   75	89	197	java/lang/Exception
    //   177	183	197	java/lang/Exception
    //   188	197	197	java/lang/Exception
    //   135	164	200	java/lang/Exception
    //   164	174	200	java/lang/Exception
  }
  
  private void b044Dэээ044Dэээээ(String paramString, nfnfnn paramNfnfnn)
  {
    int i = b0442т04420442т0442т0442т;
    switch (i * (b0442044204420442т0442т0442т + i) % bтттт04420442т0442т)
    {
    default: 
      b0442т04420442т0442т0442т = b04240424ФФФ04240424042404240424();
      bт044204420442т0442т0442т = b04240424ФФФ04240424042404240424();
    }
    if ((b0424Ф0424Ф042404240424042404240424(paramString) == null) && (paramNfnfnn == null)) {}
    for (;;)
    {
      switch (1)
      {
      case 0: 
      default: 
        for (;;)
        {
          switch (0)
          {
          }
        }
      }
      return;
      bФ0424042404240424Ф0424042404240424(paramString, paramNfnfnn);
      if ((b0442т04420442т0442т0442т + b0442044204420442т0442т0442т) * b0442т04420442т0442т0442т % bтттт04420442т0442т != bт044204420442т0442т0442т)
      {
        b0442т04420442т0442т0442т = 67;
        bт044204420442т0442т0442т = 59;
      }
      b044D044D044D044Dээээээ(paramNfnfnn);
    }
  }
  
  private boolean bФ04240424ФФ04240424042404240424(String paramString, long paramLong, boolean paramBoolean)
  {
    int i = xxdxxd.instance.bххх044504450445х044504450445().getResources().getInteger(R.integer.csatSurveyExpirationInMinutes);
    boolean bool = paramBoolean;
    if (i != 0)
    {
      Object localObject = this.bт0442т0442т0442т0442т;
      switch (1)
      {
      case 0: 
      default: 
        for (;;)
        {
          switch (0)
          {
          }
        }
      }
      localObject = ((kkyykk)localObject).bььььь044Cь044Cь;
      int j = b0442т04420442т0442т0442т;
      switch (j * (b0442044204420442т0442т0442т + j) % bтттт04420442т0442т)
      {
      default: 
        b0442т04420442т0442т0442т = b04240424ФФФ04240424042404240424();
        bт044204420442т0442т0442т = b04240424ФФФ04240424042404240424();
      }
      long l2 = ((mcmccc)localObject).bФФ0424042404240424042404240424Ф(paramString);
      long l1 = System.currentTimeMillis();
      if ((b0442т04420442т0442т0442т + b0442044204420442т0442т0442т) * b0442т04420442т0442т0442т % bтттт04420442т0442т != b0424ФФФФ04240424042404240424())
      {
        b0442т04420442т0442т0442т = b04240424ФФФ04240424042404240424();
        bт044204420442т0442т0442т = 14;
      }
      paramLong = l2 + paramLong;
      bool = paramBoolean;
      if (l1 - paramLong > TimeUnit.MINUTES.toMillis(i))
      {
        xtxtxt.bии0438и04380438и0438ии(bттт0442т0442т0442т, gguuuu.bккккк043Aкк043A043A("\\\007\013\020\007\r\007@\005\022\022\033\013\031\033\n\036\024\033\033ZN$\032\037\030S\032.'!+\037\037[#-1_\004\025\004\030re,6-\036492m\fo", '', '\000') + paramLong + gguuuu.bк043Aккк043Aкк043A043A("C\n\036\027\021\033\013\037\025\034\034w\036}\033!))\033*WuY", '\030', 't', '\001') + i);
        bool = false;
      }
    }
    return bool;
  }
  
  public static int bФ0424ФФФ04240424042404240424()
  {
    return 1;
  }
  
  private boolean bФФ04240424042404240424042404240424(xddxdd paramXddxdd)
  {
    if ((paramXddxdd == xddxdd.TIMEOUT) || (paramXddxdd == xddxdd.SYSTEM))
    {
      boolean bool2 = true;
      bool1 = bool2;
      if ((b0442т04420442т0442т0442т + b0442044204420442т0442т0442т) * b0442т04420442т0442т0442т % bтттт04420442т0442т != b0424ФФФФ04240424042404240424())
      {
        b0442т04420442т0442т0442т = b04240424ФФФ04240424042404240424();
        bт044204420442т0442т0442т = b04240424ФФФ04240424042404240424();
        bool1 = bool2;
      }
      return bool1;
    }
    boolean bool1 = false;
    int i = b0442т04420442т0442т0442т;
    switch (i * (b0442044204420442т0442т0442т + i) % bтттт04420442т0442т)
    {
    }
    b0442т04420442т0442т0442т = b04240424ФФФ04240424042404240424();
    bт044204420442т0442т0442т = 19;
    return false;
  }
  
  public static int bФФФФФ04240424042404240424()
  {
    return 2;
  }
  
  private void bэ044D044D044D044Dэээээ(String paramString, int paramInt)
  {
    throw new Runtime("d2j fail translate: java.lang.IndexOutOfBoundsException: fromIndex < 0: -1\n\tat java.util.BitSet.nextSetBit(BitSet.java:712)\n\tat com.googlecode.dex2jar.ir.ts.array.FillArrayTransformer.makeSureAllElementAreAssigned(FillArrayTransformer.java:505)\n\tat com.googlecode.dex2jar.ir.ts.array.FillArrayTransformer.transformReportChanged(FillArrayTransformer.java:123)\n\tat com.googlecode.dex2jar.ir.ts.StatedTransformer.transform(StatedTransformer.java:10)\n\tat com.googlecode.d2j.dex.Dex2jar$2.optimize(Dex2jar.java:149)\n\tat com.googlecode.d2j.dex.Dex2Asm.convertCode(Dex2Asm.java:414)\n\tat com.googlecode.d2j.dex.ExDex2Asm.convertCode(ExDex2Asm.java:42)\n\tat com.googlecode.d2j.dex.Dex2jar$2.convertCode(Dex2jar.java:128)\n\tat com.googlecode.d2j.dex.Dex2Asm.convertMethod(Dex2Asm.java:509)\n\tat com.googlecode.d2j.dex.Dex2Asm.convertClass(Dex2Asm.java:406)\n\tat com.googlecode.d2j.dex.Dex2Asm.convertDex(Dex2Asm.java:422)\n\tat com.googlecode.d2j.dex.Dex2jar.doTranslate(Dex2jar.java:172)\n\tat com.googlecode.d2j.dex.Dex2jar.to(Dex2jar.java:272)\n\tat com.googlecode.dex2jar.tools.Dex2jarCmd.doCommandLine(Dex2jarCmd.java:108)\n\tat com.googlecode.dex2jar.tools.BaseCmd.doMain(BaseCmd.java:288)\n\tat com.googlecode.dex2jar.tools.Dex2jarCmd.main(Dex2jarCmd.java:32)\n");
  }
  
  /* Error */
  public static void bэ044D044D044Dээээээ(nfnfnn paramNfnfnn)
  {
    // Byte code:
    //   0: new 404	android/os/Bundle
    //   3: dup
    //   4: invokespecial 405	android/os/Bundle:<init>	()V
    //   7: astore_1
    //   8: aload_1
    //   9: ldc_w 690
    //   12: sipush 156
    //   15: iconst_1
    //   16: invokestatic 89	kkkkkk/gguuuu:bккккк043Aкк043A043A	(Ljava/lang/String;CC)Ljava/lang/String;
    //   19: aload_0
    //   20: invokevirtual 205	kkkkkk/nfnfnn:b044D044Dэ044D044Dэ044Dэ044Dэ	()Ljava/lang/String;
    //   23: invokevirtual 410	android/os/Bundle:putString	(Ljava/lang/String;Ljava/lang/String;)V
    //   26: ldc_w 692
    //   29: sipush 153
    //   32: iconst_5
    //   33: invokestatic 89	kkkkkk/gguuuu:bккккк043Aкк043A043A	(Ljava/lang/String;CC)Ljava/lang/String;
    //   36: astore_2
    //   37: getstatic 111	kkkkkk/eeefee:b0442т04420442т0442т0442т	I
    //   40: invokestatic 295	kkkkkk/eeefee:bФ0424ФФФ04240424042404240424	()I
    //   43: iadd
    //   44: getstatic 111	kkkkkk/eeefee:b0442т04420442т0442т0442т	I
    //   47: imul
    //   48: getstatic 115	kkkkkk/eeefee:bтттт04420442т0442т	I
    //   51: irem
    //   52: getstatic 117	kkkkkk/eeefee:bт044204420442т0442т0442т	I
    //   55: if_icmpeq +15 -> 70
    //   58: invokestatic 121	kkkkkk/eeefee:b04240424ФФФ04240424042404240424	()I
    //   61: putstatic 111	kkkkkk/eeefee:b0442т04420442т0442т0442т	I
    //   64: invokestatic 121	kkkkkk/eeefee:b04240424ФФФ04240424042404240424	()I
    //   67: putstatic 117	kkkkkk/eeefee:bт044204420442т0442т0442т	I
    //   70: aload_1
    //   71: aload_2
    //   72: aload_0
    //   73: invokevirtual 191	kkkkkk/nfnfnn:b044D044Dээ044Dэ044Dэ044Dэ	()Ljava/lang/String;
    //   76: invokevirtual 410	android/os/Bundle:putString	(Ljava/lang/String;Ljava/lang/String;)V
    //   79: getstatic 145	kkkkkk/eeefee:bттт0442т0442т0442т	Ljava/lang/String;
    //   82: astore_0
    //   83: aload_0
    //   84: new 422	java/lang/StringBuilder
    //   87: dup
    //   88: invokespecial 423	java/lang/StringBuilder:<init>	()V
    //   91: ldc_w 694
    //   94: bipush 125
    //   96: iconst_5
    //   97: invokestatic 89	kkkkkk/gguuuu:bккккк043Aкк043A043A	(Ljava/lang/String;CC)Ljava/lang/String;
    //   100: invokevirtual 429	java/lang/StringBuilder:append	(Ljava/lang/String;)Ljava/lang/StringBuilder;
    //   103: aload_1
    //   104: invokevirtual 432	java/lang/StringBuilder:append	(Ljava/lang/Object;)Ljava/lang/StringBuilder;
    //   107: invokevirtual 435	java/lang/StringBuilder:toString	()Ljava/lang/String;
    //   110: invokestatic 440	kkkkkk/xtxtxt:bии0438и04380438и0438ии	(Ljava/lang/String;Ljava/lang/String;)V
    //   113: ldc_w 696
    //   116: bipush 74
    //   118: iconst_1
    //   119: invokestatic 89	kkkkkk/gguuuu:bккккк043Aкк043A043A	(Ljava/lang/String;CC)Ljava/lang/String;
    //   122: aload_1
    //   123: invokestatic 448	kkkkkk/hbhbbh:bШ042804280428Ш0428042804280428Ш	(Ljava/lang/String;Landroid/os/Bundle;)V
    //   126: getstatic 111	kkkkkk/eeefee:b0442т04420442т0442т0442т	I
    //   129: getstatic 113	kkkkkk/eeefee:b0442044204420442т0442т0442т	I
    //   132: iadd
    //   133: getstatic 111	kkkkkk/eeefee:b0442т04420442т0442т0442т	I
    //   136: imul
    //   137: getstatic 115	kkkkkk/eeefee:bтттт04420442т0442т	I
    //   140: irem
    //   141: getstatic 117	kkkkkk/eeefee:bт044204420442т0442т0442т	I
    //   144: if_icmpeq +14 -> 158
    //   147: bipush 82
    //   149: putstatic 111	kkkkkk/eeefee:b0442т04420442т0442т0442т	I
    //   152: invokestatic 121	kkkkkk/eeefee:b04240424ФФФ04240424042404240424	()I
    //   155: putstatic 117	kkkkkk/eeefee:bт044204420442т0442т0442т	I
    //   158: return
    //   159: astore_0
    //   160: aload_0
    //   161: athrow
    //   162: astore_0
    //   163: aload_0
    //   164: athrow
    // Local variable table:
    //   start	length	slot	name	signature
    //   0	165	0	paramNfnfnn	nfnfnn
    //   7	116	1	localBundle	Bundle
    //   36	36	2	str	String
    // Exception table:
    //   from	to	target	type
    //   0	37	159	java/lang/Exception
    //   70	83	159	java/lang/Exception
    //   83	126	162	java/lang/Exception
  }
  
  private void bэ044D044Dэээээээ(String paramString)
  {
    try
    {
      if (b0424Ф04240424042404240424042404240424(paramString))
      {
        localObject1 = bттт0442т0442т0442т;
        localObject2 = new StringBuilder();
      }
      do
      {
        try
        {
          paramString = ((StringBuilder)localObject2).append(gguuuu.bк043Aккк043Aкк043A043A("\b{\005\b\020\\\t\na\017\017\030\b\026\030\007\033\021\030\030\036q\037\035\034|\022\"&mT\031,*+\037)0\\!..7'57&:077i1><;n2C3A8t", '', '', '\001')).append(paramString);
          xtxtxt.bии0438043804380438и0438ии((String)localObject1, gguuuu.bккккк043Aкк043A043A("\013S\\\bHIYMYG\017#GA{IIMwI;BCI7", 'É', '\003'));
          int i = b0442т04420442т0442т0442т;
          switch (i * (b0442044204420442т0442т0442т + i) % bтттт04420442т0442т)
          {
          default: 
            b0442т04420442т0442т0442т = b04240424ФФФ04240424042404240424();
            bт044204420442т0442т0442т = 53;
          }
          return;
        }
        catch (Exception paramString)
        {
          throw paramString;
        }
        localObject1 = (nfnfnn)this.b04420442т0442т0442т0442т.get(paramString);
      } while (localObject1 == null);
      Object localObject2 = ((nfnfnn)localObject1).b044D044Dээ044Dэ044Dэ044Dэ();
      this.bтт04420442т0442т0442т.remove(localObject2);
      Object localObject1 = bттт0442т0442т0442т;
      localObject2 = gguuuu.bк043Aккк043Aкк043A043A("pdmpxhEqrJww\001p~\001o\004y\001\001\007Z\b\006\005ez\013\017V=p\005\016\021\031\r\023\rF\013\030\030!\021\037!\020$\032!!S}y", '', 'ü', '\003') + (String)localObject2;
      xtxtxt.bии0438и04380438и0438ии((String)localObject1, (String)localObject2);
      this.b04420442т0442т0442т0442т.remove(paramString);
      localObject1 = bттт0442т0442т0442т;
      localObject2 = new StringBuilder().append(gguuuu.bккккк043Aкк043A043A("\006\032#&.\036\036Z\037,,5%35$8.55;h91kA/A76F\0348\017u", 'Y', '\004'));
      if ((b0442т04420442т0442т0442т + b0442044204420442т0442т0442т) * b0442т04420442т0442т0442т % bтттт04420442т0442т != bт044204420442т0442т0442т)
      {
        b0442т04420442т0442т0442т = b04240424ФФФ04240424042404240424();
        bт044204420442т0442т0442т = b04240424ФФФ04240424042404240424();
      }
      xtxtxt.bии0438и04380438и0438ии((String)localObject1, paramString);
      return;
    }
    catch (Exception paramString)
    {
      throw paramString;
    }
  }
  
  private void bэээ044Dээээээ(int paramInt)
  {
    for (;;)
    {
      try
      {
        HashSet localHashSet = new HashSet();
        Iterator localIterator = this.b0442тт0442т0442т0442т.iterator();
        try
        {
          Object localObject;
          String str;
          StringBuilder localStringBuilder;
          int i;
          if (localIterator.hasNext())
          {
            localObject = localIterator.next();
            if ((b0442т04420442т0442т0442т + b0442044204420442т0442т0442т) * b0442т04420442т0442т0442т % bтттт04420442т0442т != bт044204420442т0442т0442т)
            {
              b0442т04420442т0442т0442т = 7;
              bт044204420442т0442т0442т = 41;
            }
            localObject = (Integer)localObject;
            if (((Integer)localObject).intValue() > paramInt) {
              continue;
            }
            str = bттт0442т0442т0442т;
            localStringBuilder = new StringBuilder().append(gguuuu.bк043Aккк043Aкк043A043A("?HOYIG\002TEPSBJ>?x", 'c', '³', '\002')).append(localObject);
            i = b0442т04420442т0442т0442т;
          }
          switch (i * (b0442044204420442т0442т0442т + i) % bтттт04420442т0442т)
          {
          case 0: 
            b0442т04420442т0442т0442т = 37;
            bт044204420442т0442т0442т = 97;
            xtxtxt.bии0438и04380438и0438ии(str, gguuuu.bккккк043Aкк043A043A("\nMMSKYIG\002BFSCO{LO>JPuB9FE274Am", '\026', '\005'));
            localHashSet.add(localObject);
            continue;
            if (localException1.isEmpty()) {
              continue;
            }
          }
        }
        catch (Exception localException1)
        {
          throw localException1;
        }
        this.b0442тт0442т0442т0442т.removeAll(localException1);
        return;
      }
      catch (Exception localException2)
      {
        throw localException2;
      }
    }
  }
  
  /* Error */
  public static void bээээ044Dэээээ(nfnfnn paramNfnfnn)
  {
    // Byte code:
    //   0: iconst_1
    //   1: tableswitch	default:+23->24, 0:+-1->0, 1:+50->51
    //   24: iconst_1
    //   25: tableswitch	default:+23->48, 0:+-25->0, 1:+26->51
    //   48: goto -24 -> 24
    //   51: new 404	android/os/Bundle
    //   54: dup
    //   55: invokespecial 405	android/os/Bundle:<init>	()V
    //   58: astore_2
    //   59: aload_2
    //   60: ldc_w 736
    //   63: sipush 231
    //   66: iconst_4
    //   67: invokestatic 89	kkkkkk/gguuuu:bккккк043Aкк043A043A	(Ljava/lang/String;CC)Ljava/lang/String;
    //   70: aload_0
    //   71: invokevirtual 205	kkkkkk/nfnfnn:b044D044Dэ044D044Dэ044Dэ044Dэ	()Ljava/lang/String;
    //   74: invokevirtual 410	android/os/Bundle:putString	(Ljava/lang/String;Ljava/lang/String;)V
    //   77: getstatic 111	kkkkkk/eeefee:b0442т04420442т0442т0442т	I
    //   80: getstatic 113	kkkkkk/eeefee:b0442044204420442т0442т0442т	I
    //   83: iadd
    //   84: getstatic 111	kkkkkk/eeefee:b0442т04420442т0442т0442т	I
    //   87: imul
    //   88: getstatic 115	kkkkkk/eeefee:bтттт04420442т0442т	I
    //   91: irem
    //   92: getstatic 117	kkkkkk/eeefee:bт044204420442т0442т0442т	I
    //   95: if_icmpeq +60 -> 155
    //   98: invokestatic 121	kkkkkk/eeefee:b04240424ФФФ04240424042404240424	()I
    //   101: istore_1
    //   102: iload_1
    //   103: getstatic 113	kkkkkk/eeefee:b0442044204420442т0442т0442т	I
    //   106: iload_1
    //   107: iadd
    //   108: imul
    //   109: getstatic 115	kkkkkk/eeefee:bтттт04420442т0442т	I
    //   112: irem
    //   113: tableswitch	default:+19->132, 0:+31->144
    //   132: invokestatic 121	kkkkkk/eeefee:b04240424ФФФ04240424042404240424	()I
    //   135: putstatic 111	kkkkkk/eeefee:b0442т04420442т0442т0442т	I
    //   138: invokestatic 121	kkkkkk/eeefee:b04240424ФФФ04240424042404240424	()I
    //   141: putstatic 117	kkkkkk/eeefee:bт044204420442т0442т0442т	I
    //   144: bipush 79
    //   146: putstatic 111	kkkkkk/eeefee:b0442т04420442т0442т0442т	I
    //   149: invokestatic 121	kkkkkk/eeefee:b04240424ФФФ04240424042404240424	()I
    //   152: putstatic 117	kkkkkk/eeefee:bт044204420442т0442т0442т	I
    //   155: getstatic 145	kkkkkk/eeefee:bттт0442т0442т0442т	Ljava/lang/String;
    //   158: new 422	java/lang/StringBuilder
    //   161: dup
    //   162: invokespecial 423	java/lang/StringBuilder:<init>	()V
    //   165: ldc_w 738
    //   168: bipush 7
    //   170: iconst_0
    //   171: invokestatic 89	kkkkkk/gguuuu:bккккк043Aкк043A043A	(Ljava/lang/String;CC)Ljava/lang/String;
    //   174: invokevirtual 429	java/lang/StringBuilder:append	(Ljava/lang/String;)Ljava/lang/StringBuilder;
    //   177: aload_2
    //   178: invokevirtual 432	java/lang/StringBuilder:append	(Ljava/lang/Object;)Ljava/lang/StringBuilder;
    //   181: invokevirtual 435	java/lang/StringBuilder:toString	()Ljava/lang/String;
    //   184: invokestatic 440	kkkkkk/xtxtxt:bии0438и04380438и0438ии	(Ljava/lang/String;Ljava/lang/String;)V
    //   187: ldc_w 740
    //   190: bipush 11
    //   192: iconst_2
    //   193: invokestatic 89	kkkkkk/gguuuu:bккккк043Aкк043A043A	(Ljava/lang/String;CC)Ljava/lang/String;
    //   196: astore_0
    //   197: aload_0
    //   198: aload_2
    //   199: invokestatic 448	kkkkkk/hbhbbh:bШ042804280428Ш0428042804280428Ш	(Ljava/lang/String;Landroid/os/Bundle;)V
    //   202: return
    //   203: astore_0
    //   204: aload_0
    //   205: athrow
    //   206: astore_0
    //   207: aload_0
    //   208: athrow
    // Local variable table:
    //   start	length	slot	name	signature
    //   0	209	0	paramNfnfnn	nfnfnn
    //   101	8	1	i	int
    //   58	141	2	localBundle	Bundle
    // Exception table:
    //   from	to	target	type
    //   51	59	203	java/lang/Exception
    //   155	197	203	java/lang/Exception
    //   59	77	206	java/lang/Exception
    //   197	202	206	java/lang/Exception
  }
  
  public void b04240424042404240424Ф0424042404240424(String paramString)
  {
    nfnfnn localNfnfnn = bФФФФ042404240424042404240424(paramString);
    if (localNfnfnn != null)
    {
      int i = localNfnfnn.b044Dэ044D044D044Dэ044Dэ044Dэ() + 1;
      String str = bттт0442т0442т0442т;
      StringBuilder localStringBuilder = new StringBuilder();
      switch (1)
      {
      case 0: 
      default: 
        for (;;)
        {
          int j = b0442т04420442т0442т0442т;
          switch (j * (b0442044204420442т0442т0442т + j) % bтттт04420442т0442т)
          {
          default: 
            b0442т04420442т0442т0442т = b04240424ФФФ04240424042404240424();
            bт044204420442т0442т0442т = b04240424ФФФ04240424042404240424();
          }
          switch (0)
          {
          }
        }
      }
      localStringBuilder = localStringBuilder.append(gguuuu.bккккк043Aкк043A043A("\016\020\017\023\027\017F\033\025\b\004\026\006?\021\003\016\021\r\r7\0044\004\005\001w\002s\001+pxz'itrygss`rfki4\031", 'Å', '\002')).append(paramString).append(gguuuu.bккккк043Aкк043A043A("WJ\034\016\031\034\013\030\030\026A\n\016>\016\017\013\002\f}\013\nO4", '', '\002'));
      if ((b04240424ФФФ04240424042404240424() + b0442044204420442т0442т0442т) * b04240424ФФФ04240424042404240424() % bтттт04420442т0442т != bт044204420442т0442т0442т)
      {
        b0442т04420442т0442т0442т = b04240424ФФФ04240424042404240424();
        bт044204420442т0442т0442т = 49;
      }
      xtxtxt.bии0438и04380438и0438ии(str, i);
      localNfnfnn.bээ044D044Dэ044D044Dэ044Dэ(i);
    }
    bэ044D044D044D044Dэээээ(paramString, 1);
  }
  
  public xddxxx<Integer> b042404240424ФФ04240424042404240424(String paramString)
  {
    int j = 2;
    bэ044D044Dэээээээ(paramString);
    int i = j;
    switch (0)
    {
    case 1: 
    default: 
      for (;;)
      {
        i = j;
        switch (1)
        {
        }
      }
    }
    try
    {
      for (;;)
      {
        i /= 0;
      }
      return paramString;
    }
    catch (Exception localException)
    {
      b0442т04420442т0442т0442т = b04240424ФФФ04240424042404240424();
      paramString = new xddxxx(new eeefee.17(this, paramString));
      if ((b0442т04420442т0442т0442т + b0442044204420442т0442т0442т) * b0442т04420442т0442т0442т % bтттт04420442т0442т != bт044204420442т0442т0442т)
      {
        b0442т04420442т0442т0442т = b04240424ФФФ04240424042404240424();
        bт044204420442т0442т0442т = b04240424ФФФ04240424042404240424();
      }
    }
  }
  
  /* Error */
  public void b04240424Ф0424Ф04240424042404240424(String paramString1, String paramString2, String paramString3, long paramLong)
  {
    // Byte code:
    //   0: new 188	kkkkkk/nfnfnn
    //   3: dup
    //   4: aload_1
    //   5: aload_2
    //   6: invokespecial 770	kkkkkk/nfnfnn:<init>	(Ljava/lang/String;Ljava/lang/String;)V
    //   9: astore 6
    //   11: aload 6
    //   13: aload_3
    //   14: invokevirtual 773	kkkkkk/nfnfnn:b044D044D044Dээ044D044Dэ044Dэ	(Ljava/lang/String;)V
    //   17: aload 6
    //   19: getstatic 777	kkkkkk/dxdxdd:PENDING	Lkkkkkk/dxdxdd;
    //   22: invokevirtual 781	kkkkkk/nfnfnn:bэ044Dэ044Dэ044D044Dэ044Dэ	(Lkkkkkk/dxdxdd;)V
    //   25: aload 6
    //   27: getstatic 785	kkkkkk/xdxxdd:NORMAL	Lkkkkkk/xdxxdd;
    //   30: invokevirtual 789	kkkkkk/nfnfnn:bээ044Dээ044D044Dэ044Dэ	(Lkkkkkk/xdxxdd;)V
    //   33: aload 6
    //   35: lload 4
    //   37: invokevirtual 793	kkkkkk/nfnfnn:bэ044D044Dээ044D044Dэ044Dэ	(J)V
    //   40: new 264	java/lang/NullPointerException
    //   43: dup
    //   44: invokespecial 265	java/lang/NullPointerException:<init>	()V
    //   47: athrow
    //   48: astore 7
    //   50: bipush 16
    //   52: putstatic 111	kkkkkk/eeefee:b0442т04420442т0442т0442т	I
    //   55: aload_0
    //   56: aload_1
    //   57: aload 6
    //   59: invokevirtual 588	kkkkkk/eeefee:bФ0424042404240424Ф0424042404240424	(Ljava/lang/String;Lkkkkkk/nfnfnn;)V
    //   62: new 795	kkkkkk/eeefee$7
    //   65: dup
    //   66: aload_0
    //   67: aload_2
    //   68: aload_1
    //   69: aload_3
    //   70: lload 4
    //   72: aload 6
    //   74: invokespecial 798	kkkkkk/eeefee$7:<init>	(Lkkkkkk/eeefee;Ljava/lang/String;Ljava/lang/String;Ljava/lang/String;JLkkkkkk/nfnfnn;)V
    //   77: invokestatic 401	kkkkkk/dxxxxx:bиии04380438и0438иии	(Ljava/lang/Runnable;)V
    //   80: return
    //   81: astore_1
    //   82: aload_1
    //   83: athrow
    //   84: astore_1
    //   85: aload_1
    //   86: athrow
    // Local variable table:
    //   start	length	slot	name	signature
    //   0	87	0	this	eeefee
    //   0	87	1	paramString1	String
    //   0	87	2	paramString2	String
    //   0	87	3	paramString3	String
    //   0	87	4	paramLong	long
    //   9	64	6	localNfnfnn	nfnfnn
    //   48	1	7	localException	Exception
    // Exception table:
    //   from	to	target	type
    //   40	48	48	java/lang/Exception
    //   0	11	81	java/lang/Exception
    //   25	40	81	java/lang/Exception
    //   50	80	81	java/lang/Exception
    //   11	25	84	java/lang/Exception
  }
  
  public nfnfnn b04240424ФФ042404240424042404240424(String paramString)
  {
    Map localMap = this.b04420442т0442т0442т0442т;
    switch (1)
    {
    case 0: 
    default: 
      for (;;)
      {
        switch (1)
        {
        }
      }
    }
    paramString = (nfnfnn)localMap.get(paramString);
    if (paramString != null) {
      try
      {
        throw new NullPointerException();
      }
      catch (Exception localException)
      {
        b0442т04420442т0442т0442т = b04240424ФФФ04240424042404240424();
        String str = paramString.b044D044Dээ044Dэ044Dэ044Dэ();
        if ((str != null) && (this.bтт04420442т0442т0442т.get(str) == null))
        {
          if ((b0442т04420442т0442т0442т + bФ0424ФФФ04240424042404240424()) * b0442т04420442т0442т0442т % bтттт04420442т0442т != bт044204420442т0442т0442т)
          {
            b0442т04420442т0442т0442т = b04240424ФФФ04240424042404240424();
            bт044204420442т0442т0442т = b04240424ФФФ04240424042404240424();
          }
          this.bтт04420442т0442т0442т.put(str, paramString);
        }
      }
    }
    return paramString;
  }
  
  public boolean b0424Ф04240424042404240424042404240424(String paramString)
  {
    try
    {
      paramString = b0424Ф0424Ф042404240424042404240424(paramString);
      if ((paramString != null) && (paramString.b044Dээ044D044Dэ044Dэ044Dэ() == dxdxdd.OPEN))
      {
        int i = b0442т04420442т0442т0442т;
        int j = b0442044204420442т0442т0442т;
        int k = b0442т04420442т0442т0442т;
        int m = bтттт04420442т0442т;
        int n = b0424ФФФФ04240424042404240424();
        if ((i + j) * k % m != n) {
          if ((b0442т04420442т0442т0442т + b0442044204420442т0442т0442т) * b0442т04420442т0442т0442т % bФФФФФ04240424042404240424() != bт044204420442т0442т0442т)
          {
            b0442т04420442т0442т0442т = 39;
            bт044204420442т0442т0442т = 27;
          }
        }
      }
    }
    catch (Exception paramString)
    {
      throw paramString;
    }
    try
    {
      b0442т04420442т0442т0442т = 55;
      bт044204420442т0442т0442т = b04240424ФФФ04240424042404240424();
      return true;
    }
    catch (Exception paramString)
    {
      throw paramString;
    }
    return false;
  }
  
  public xddxxx<nfnfnn> b0424Ф04240424Ф04240424042404240424(String paramString)
  {
    throw new Runtime("d2j fail translate: java.lang.IndexOutOfBoundsException: fromIndex < 0: -1\n\tat java.util.BitSet.nextSetBit(BitSet.java:712)\n\tat com.googlecode.dex2jar.ir.ts.array.FillArrayTransformer.makeSureAllElementAreAssigned(FillArrayTransformer.java:505)\n\tat com.googlecode.dex2jar.ir.ts.array.FillArrayTransformer.transformReportChanged(FillArrayTransformer.java:123)\n\tat com.googlecode.dex2jar.ir.ts.StatedTransformer.transform(StatedTransformer.java:10)\n\tat com.googlecode.d2j.dex.Dex2jar$2.optimize(Dex2jar.java:149)\n\tat com.googlecode.d2j.dex.Dex2Asm.convertCode(Dex2Asm.java:414)\n\tat com.googlecode.d2j.dex.ExDex2Asm.convertCode(ExDex2Asm.java:42)\n\tat com.googlecode.d2j.dex.Dex2jar$2.convertCode(Dex2jar.java:128)\n\tat com.googlecode.d2j.dex.Dex2Asm.convertMethod(Dex2Asm.java:509)\n\tat com.googlecode.d2j.dex.Dex2Asm.convertClass(Dex2Asm.java:406)\n\tat com.googlecode.d2j.dex.Dex2Asm.convertDex(Dex2Asm.java:422)\n\tat com.googlecode.d2j.dex.Dex2jar.doTranslate(Dex2jar.java:172)\n\tat com.googlecode.d2j.dex.Dex2jar.to(Dex2jar.java:272)\n\tat com.googlecode.dex2jar.tools.Dex2jarCmd.doCommandLine(Dex2jarCmd.java:108)\n\tat com.googlecode.dex2jar.tools.BaseCmd.doMain(BaseCmd.java:288)\n\tat com.googlecode.dex2jar.tools.Dex2jarCmd.main(Dex2jarCmd.java:32)\n");
  }
  
  public nfnfnn b0424Ф0424Ф042404240424042404240424(String paramString)
  {
    paramString = this.b04420442т0442т0442т0442т.get(paramString);
    int i = b0442т04420442т0442т0442т;
    switch (i * (b0442044204420442т0442т0442т + i) % bтттт04420442т0442т)
    {
    default: 
      b0442т04420442т0442т0442т = b04240424ФФФ04240424042404240424();
      bт044204420442т0442т0442т = 12;
    }
    paramString = (nfnfnn)paramString;
    if (paramString != null)
    {
      String str = paramString.b044D044Dээ044Dэ044Dэ044Dэ();
      if ((str != null) && (this.bтт04420442т0442т0442т.get(str) == null)) {
        this.bтт04420442т0442т0442т.put(str, paramString);
      }
    }
    return paramString;
  }
  
  public void b0424ФФ0424Ф04240424042404240424(String paramString1, String paramString2, String paramString3, long paramLong)
  {
    throw new Runtime("d2j fail translate: java.lang.IndexOutOfBoundsException: fromIndex < 0: -1\n\tat java.util.BitSet.nextSetBit(BitSet.java:712)\n\tat com.googlecode.dex2jar.ir.ts.array.FillArrayTransformer.makeSureAllElementAreAssigned(FillArrayTransformer.java:505)\n\tat com.googlecode.dex2jar.ir.ts.array.FillArrayTransformer.transformReportChanged(FillArrayTransformer.java:123)\n\tat com.googlecode.dex2jar.ir.ts.StatedTransformer.transform(StatedTransformer.java:10)\n\tat com.googlecode.d2j.dex.Dex2jar$2.optimize(Dex2jar.java:149)\n\tat com.googlecode.d2j.dex.Dex2Asm.convertCode(Dex2Asm.java:414)\n\tat com.googlecode.d2j.dex.ExDex2Asm.convertCode(ExDex2Asm.java:42)\n\tat com.googlecode.d2j.dex.Dex2jar$2.convertCode(Dex2jar.java:128)\n\tat com.googlecode.d2j.dex.Dex2Asm.convertMethod(Dex2Asm.java:509)\n\tat com.googlecode.d2j.dex.Dex2Asm.convertClass(Dex2Asm.java:406)\n\tat com.googlecode.d2j.dex.Dex2Asm.convertDex(Dex2Asm.java:422)\n\tat com.googlecode.d2j.dex.Dex2jar.doTranslate(Dex2jar.java:172)\n\tat com.googlecode.d2j.dex.Dex2jar.to(Dex2jar.java:272)\n\tat com.googlecode.dex2jar.tools.Dex2jarCmd.doCommandLine(Dex2jarCmd.java:108)\n\tat com.googlecode.dex2jar.tools.BaseCmd.doMain(BaseCmd.java:288)\n\tat com.googlecode.dex2jar.tools.Dex2jarCmd.main(Dex2jarCmd.java:32)\n");
  }
  
  /* Error */
  public xddxxx<nfnfnn> b0424ФФФ042404240424042404240424(String paramString1, String paramString2)
  {
    // Byte code:
    //   0: new 264	java/lang/NullPointerException
    //   3: dup
    //   4: invokespecial 265	java/lang/NullPointerException:<init>	()V
    //   7: athrow
    //   8: astore 4
    //   10: bipush 39
    //   12: putstatic 111	kkkkkk/eeefee:b0442т04420442т0442т0442т	I
    //   15: new 316	kkkkkk/xddxxx
    //   18: dup
    //   19: new 812	kkkkkk/eeefee$2
    //   22: dup
    //   23: aload_0
    //   24: aload_2
    //   25: aload_1
    //   26: invokespecial 815	kkkkkk/eeefee$2:<init>	(Lkkkkkk/eeefee;Ljava/lang/String;Ljava/lang/String;)V
    //   29: invokespecial 324	kkkkkk/xddxxx:<init>	(Lkkkkkk/xddxxx$xdxxxx;)V
    //   32: astore_1
    //   33: getstatic 111	kkkkkk/eeefee:b0442т04420442т0442т0442т	I
    //   36: istore_3
    //   37: iload_3
    //   38: getstatic 113	kkkkkk/eeefee:b0442044204420442т0442т0442т	I
    //   41: iload_3
    //   42: iadd
    //   43: imul
    //   44: getstatic 115	kkkkkk/eeefee:bтттт04420442т0442т	I
    //   47: irem
    //   48: tableswitch	default:+20->68, 0:+30->78
    //   68: bipush 67
    //   70: putstatic 111	kkkkkk/eeefee:b0442т04420442т0442т0442т	I
    //   73: bipush 85
    //   75: putstatic 117	kkkkkk/eeefee:bт044204420442т0442т0442т	I
    //   78: aload_1
    //   79: areturn
    //   80: astore_1
    //   81: aload_1
    //   82: athrow
    //   83: astore_1
    //   84: aload_1
    //   85: athrow
    // Local variable table:
    //   start	length	slot	name	signature
    //   0	86	0	this	eeefee
    //   0	86	1	paramString1	String
    //   0	86	2	paramString2	String
    //   36	8	3	i	int
    //   8	1	4	localException	Exception
    // Exception table:
    //   from	to	target	type
    //   0	8	8	java/lang/Exception
    //   15	33	80	java/lang/Exception
    //   10	15	83	java/lang/Exception
  }
  
  /* Error */
  public void b0445044504450445044504450445х04450445()
  {
    // Byte code:
    //   0: getstatic 111	kkkkkk/eeefee:b0442т04420442т0442т0442т	I
    //   3: invokestatic 295	kkkkkk/eeefee:bФ0424ФФФ04240424042404240424	()I
    //   6: iadd
    //   7: getstatic 111	kkkkkk/eeefee:b0442т04420442т0442т0442т	I
    //   10: imul
    //   11: getstatic 115	kkkkkk/eeefee:bтттт04420442т0442т	I
    //   14: irem
    //   15: getstatic 117	kkkkkk/eeefee:bт044204420442т0442т0442т	I
    //   18: if_icmpeq +14 -> 32
    //   21: invokestatic 121	kkkkkk/eeefee:b04240424ФФФ04240424042404240424	()I
    //   24: putstatic 111	kkkkkk/eeefee:b0442т04420442т0442т0442т	I
    //   27: bipush 17
    //   29: putstatic 117	kkkkkk/eeefee:bт044204420442т0442т0442т	I
    //   32: aload_0
    //   33: getfield 159	kkkkkk/eeefee:b04420442т0442т0442т0442т	Ljava/util/Map;
    //   36: invokeinterface 820 1 0
    //   41: aload_0
    //   42: getfield 161	kkkkkk/eeefee:bтт04420442т0442т0442т	Ljava/util/Map;
    //   45: invokeinterface 820 1 0
    //   50: aload_0
    //   51: getfield 166	kkkkkk/eeefee:b0442тт0442т0442т0442т	Ljava/util/HashSet;
    //   54: invokevirtual 821	java/util/HashSet:clear	()V
    //   57: aload_0
    //   58: getfield 159	kkkkkk/eeefee:b04420442т0442т0442т0442т	Ljava/util/Map;
    //   61: invokeinterface 825 1 0
    //   66: invokeinterface 828 1 0
    //   71: astore_2
    //   72: getstatic 111	kkkkkk/eeefee:b0442т04420442т0442т0442т	I
    //   75: istore_1
    //   76: iload_1
    //   77: getstatic 113	kkkkkk/eeefee:b0442044204420442т0442т0442т	I
    //   80: iload_1
    //   81: iadd
    //   82: imul
    //   83: getstatic 115	kkkkkk/eeefee:bтттт04420442т0442т	I
    //   86: irem
    //   87: tableswitch	default:+17->104, 0:+27->114
    //   104: bipush 22
    //   106: putstatic 111	kkkkkk/eeefee:b0442т04420442т0442т0442т	I
    //   109: bipush 60
    //   111: putstatic 117	kkkkkk/eeefee:bт044204420442т0442т0442т	I
    //   114: aload_2
    //   115: invokeinterface 722 1 0
    //   120: ifeq +81 -> 201
    //   123: aload_2
    //   124: invokeinterface 726 1 0
    //   129: checkcast 188	kkkkkk/nfnfnn
    //   132: invokevirtual 832	kkkkkk/nfnfnn:bэ044Dэ044D044Dэ044Dэ044Dэ	()Lkkkkkk/nfffnf;
    //   135: astore_3
    //   136: aload_3
    //   137: invokevirtual 836	kkkkkk/nfffnf:b0445044504450445044504450445х04450445	()V
    //   140: goto -26 -> 114
    //   143: astore_2
    //   144: aload_2
    //   145: athrow
    //   146: astore_2
    //   147: iconst_1
    //   148: tableswitch	default:+24->172, 0:+-1->147, 1:+51->199
    //   172: iconst_1
    //   173: tableswitch	default:+23->196, 0:+-26->147, 1:+26->199
    //   196: goto -24 -> 172
    //   199: aload_2
    //   200: athrow
    //   201: return
    // Local variable table:
    //   start	length	slot	name	signature
    //   0	202	0	this	eeefee
    //   75	8	1	i	int
    //   71	53	2	localIterator	Iterator
    //   143	2	2	localException1	Exception
    //   146	54	2	localException2	Exception
    //   135	2	3	localNfffnf	nfffnf
    // Exception table:
    //   from	to	target	type
    //   50	72	143	java/lang/Exception
    //   136	140	143	java/lang/Exception
    //   32	50	146	java/lang/Exception
    //   114	136	146	java/lang/Exception
  }
  
  public void b0445ххх0445хх044504450445()
  {
    throw new Runtime("d2j fail translate: java.lang.IndexOutOfBoundsException: fromIndex < 0: -1\n\tat java.util.BitSet.nextSetBit(BitSet.java:712)\n\tat com.googlecode.dex2jar.ir.ts.array.FillArrayTransformer.makeSureAllElementAreAssigned(FillArrayTransformer.java:505)\n\tat com.googlecode.dex2jar.ir.ts.array.FillArrayTransformer.transformReportChanged(FillArrayTransformer.java:123)\n\tat com.googlecode.dex2jar.ir.ts.StatedTransformer.transform(StatedTransformer.java:10)\n\tat com.googlecode.d2j.dex.Dex2jar$2.optimize(Dex2jar.java:149)\n\tat com.googlecode.d2j.dex.Dex2Asm.convertCode(Dex2Asm.java:414)\n\tat com.googlecode.d2j.dex.ExDex2Asm.convertCode(ExDex2Asm.java:42)\n\tat com.googlecode.d2j.dex.Dex2jar$2.convertCode(Dex2jar.java:128)\n\tat com.googlecode.d2j.dex.Dex2Asm.convertMethod(Dex2Asm.java:509)\n\tat com.googlecode.d2j.dex.Dex2Asm.convertClass(Dex2Asm.java:406)\n\tat com.googlecode.d2j.dex.Dex2Asm.convertDex(Dex2Asm.java:422)\n\tat com.googlecode.d2j.dex.Dex2jar.doTranslate(Dex2jar.java:172)\n\tat com.googlecode.d2j.dex.Dex2jar.to(Dex2jar.java:272)\n\tat com.googlecode.dex2jar.tools.Dex2jarCmd.doCommandLine(Dex2jarCmd.java:108)\n\tat com.googlecode.dex2jar.tools.BaseCmd.doMain(BaseCmd.java:288)\n\tat com.googlecode.dex2jar.tools.Dex2jarCmd.main(Dex2jarCmd.java:32)\n");
  }
  
  /* Error */
  public void b044D044D044Dэ044Dэээээ(String paramString1, String paramString2, dxdxdd paramDxdxdd)
  {
    // Byte code:
    //   0: aload_0
    //   1: aload_1
    //   2: invokevirtual 744	kkkkkk/eeefee:bФФФФ042404240424042404240424	(Ljava/lang/String;)Lkkkkkk/nfnfnn;
    //   5: astore_1
    //   6: aload_1
    //   7: ifnull +148 -> 155
    //   10: getstatic 145	kkkkkk/eeefee:bттт0442т0442т0442т	Ljava/lang/String;
    //   13: astore 7
    //   15: new 422	java/lang/StringBuilder
    //   18: dup
    //   19: invokespecial 423	java/lang/StringBuilder:<init>	()V
    //   22: astore 8
    //   24: ldc_w 841
    //   27: bipush 56
    //   29: sipush 212
    //   32: iconst_2
    //   33: invokestatic 97	kkkkkk/gguuuu:bк043Aккк043Aкк043A043A	(Ljava/lang/String;CCC)Ljava/lang/String;
    //   36: astore 9
    //   38: getstatic 111	kkkkkk/eeefee:b0442т04420442т0442т0442т	I
    //   41: getstatic 113	kkkkkk/eeefee:b0442044204420442т0442т0442т	I
    //   44: iadd
    //   45: getstatic 111	kkkkkk/eeefee:b0442т04420442т0442т0442т	I
    //   48: imul
    //   49: getstatic 115	kkkkkk/eeefee:bтттт04420442т0442т	I
    //   52: irem
    //   53: getstatic 117	kkkkkk/eeefee:bт044204420442т0442т0442т	I
    //   56: if_icmpeq +14 -> 70
    //   59: invokestatic 121	kkkkkk/eeefee:b04240424ФФФ04240424042404240424	()I
    //   62: putstatic 111	kkkkkk/eeefee:b0442т04420442т0442т0442т	I
    //   65: bipush 15
    //   67: putstatic 117	kkkkkk/eeefee:bт044204420442т0442т0442т	I
    //   70: aload 8
    //   72: aload 9
    //   74: invokevirtual 429	java/lang/StringBuilder:append	(Ljava/lang/String;)Ljava/lang/StringBuilder;
    //   77: aload_3
    //   78: invokevirtual 432	java/lang/StringBuilder:append	(Ljava/lang/Object;)Ljava/lang/StringBuilder;
    //   81: astore 8
    //   83: getstatic 111	kkkkkk/eeefee:b0442т04420442т0442т0442т	I
    //   86: istore 4
    //   88: getstatic 113	kkkkkk/eeefee:b0442044204420442т0442т0442т	I
    //   91: istore 5
    //   93: getstatic 115	kkkkkk/eeefee:bтттт04420442т0442т	I
    //   96: istore 6
    //   98: iload 4
    //   100: iload 5
    //   102: iload 4
    //   104: iadd
    //   105: imul
    //   106: iload 6
    //   108: irem
    //   109: tableswitch	default:+19->128, 0:+31->140
    //   128: invokestatic 121	kkkkkk/eeefee:b04240424ФФФ04240424042404240424	()I
    //   131: putstatic 111	kkkkkk/eeefee:b0442т04420442т0442т0442т	I
    //   134: invokestatic 121	kkkkkk/eeefee:b04240424ФФФ04240424042404240424	()I
    //   137: putstatic 117	kkkkkk/eeefee:bт044204420442т0442т0442т	I
    //   140: aload 7
    //   142: aload 8
    //   144: invokevirtual 435	java/lang/StringBuilder:toString	()Ljava/lang/String;
    //   147: invokestatic 440	kkkkkk/xtxtxt:bии0438и04380438и0438ии	(Ljava/lang/String;Ljava/lang/String;)V
    //   150: aload_1
    //   151: aload_3
    //   152: invokevirtual 781	kkkkkk/nfnfnn:bэ044Dэ044Dэ044D044Dэ044Dэ	(Lkkkkkk/dxdxdd;)V
    //   155: new 843	kkkkkk/eeefee$21
    //   158: dup
    //   159: aload_0
    //   160: aload_2
    //   161: aload_3
    //   162: invokespecial 846	kkkkkk/eeefee$21:<init>	(Lkkkkkk/eeefee;Ljava/lang/String;Lkkkkkk/dxdxdd;)V
    //   165: astore_1
    //   166: aload_1
    //   167: invokestatic 401	kkkkkk/dxxxxx:bиии04380438и0438иии	(Ljava/lang/Runnable;)V
    //   170: return
    //   171: astore_1
    //   172: aload_1
    //   173: athrow
    //   174: astore_1
    //   175: aload_1
    //   176: athrow
    // Local variable table:
    //   start	length	slot	name	signature
    //   0	177	0	this	eeefee
    //   0	177	1	paramString1	String
    //   0	177	2	paramString2	String
    //   0	177	3	paramDxdxdd	dxdxdd
    //   86	20	4	i	int
    //   91	14	5	j	int
    //   96	13	6	k	int
    //   13	128	7	str1	String
    //   22	121	8	localStringBuilder	StringBuilder
    //   36	37	9	str2	String
    // Exception table:
    //   from	to	target	type
    //   0	6	171	java/lang/Exception
    //   10	38	171	java/lang/Exception
    //   70	98	171	java/lang/Exception
    //   140	150	171	java/lang/Exception
    //   166	170	171	java/lang/Exception
    //   128	140	174	java/lang/Exception
    //   150	155	174	java/lang/Exception
    //   155	166	174	java/lang/Exception
  }
  
  /* Error */
  public void b044D044Dэ044D044Dэээээ(String paramString, int paramInt)
  {
    // Byte code:
    //   0: iconst_0
    //   1: istore_3
    //   2: getstatic 111	kkkkkk/eeefee:b0442т04420442т0442т0442т	I
    //   5: getstatic 113	kkkkkk/eeefee:b0442044204420442т0442т0442т	I
    //   8: iadd
    //   9: getstatic 111	kkkkkk/eeefee:b0442т04420442т0442т0442т	I
    //   12: imul
    //   13: getstatic 115	kkkkkk/eeefee:bтттт04420442т0442т	I
    //   16: irem
    //   17: getstatic 117	kkkkkk/eeefee:bт044204420442т0442т0442т	I
    //   20: if_icmpeq +14 -> 34
    //   23: invokestatic 121	kkkkkk/eeefee:b04240424ФФФ04240424042404240424	()I
    //   26: putstatic 111	kkkkkk/eeefee:b0442т04420442т0442т0442т	I
    //   29: bipush 74
    //   31: putstatic 117	kkkkkk/eeefee:bт044204420442т0442т0442т	I
    //   34: aload_0
    //   35: aload_1
    //   36: invokevirtual 850	kkkkkk/eeefee:bФФ0424Ф042404240424042404240424	(Ljava/lang/String;)Lkkkkkk/nfnfnn;
    //   39: astore_1
    //   40: aload_1
    //   41: ifnull +180 -> 221
    //   44: aload_1
    //   45: invokevirtual 304	kkkkkk/nfnfnn:b044Dэ044Dэ044Dэ044Dэ044Dэ	()I
    //   48: iload_2
    //   49: if_icmpeq +172 -> 221
    //   52: aload_1
    //   53: invokevirtual 304	kkkkkk/nfnfnn:b044Dэ044Dэ044Dэ044Dэ044Dэ	()I
    //   56: i2l
    //   57: lstore 4
    //   59: lconst_1
    //   60: lload 4
    //   62: ladd
    //   63: iload_2
    //   64: i2l
    //   65: lcmp
    //   66: ifne +156 -> 222
    //   69: aload_1
    //   70: iload_2
    //   71: invokevirtual 550	kkkkkk/nfnfnn:b044Dэ044Dээ044D044Dэ044Dэ	(I)V
    //   74: getstatic 145	kkkkkk/eeefee:bттт0442т0442т0442т	Ljava/lang/String;
    //   77: new 422	java/lang/StringBuilder
    //   80: dup
    //   81: invokespecial 423	java/lang/StringBuilder:<init>	()V
    //   84: ldc_w 852
    //   87: sipush 149
    //   90: iconst_0
    //   91: invokestatic 89	kkkkkk/gguuuu:bккккк043Aкк043A043A	(Ljava/lang/String;CC)Ljava/lang/String;
    //   94: invokevirtual 429	java/lang/StringBuilder:append	(Ljava/lang/String;)Ljava/lang/StringBuilder;
    //   97: lload 4
    //   99: invokevirtual 654	java/lang/StringBuilder:append	(J)Ljava/lang/StringBuilder;
    //   102: ldc_w 854
    //   105: sipush 160
    //   108: iconst_3
    //   109: invokestatic 89	kkkkkk/gguuuu:bккккк043Aкк043A043A	(Ljava/lang/String;CC)Ljava/lang/String;
    //   112: invokevirtual 429	java/lang/StringBuilder:append	(Ljava/lang/String;)Ljava/lang/StringBuilder;
    //   115: iload_2
    //   116: invokevirtual 508	java/lang/StringBuilder:append	(I)Ljava/lang/StringBuilder;
    //   119: invokevirtual 435	java/lang/StringBuilder:toString	()Ljava/lang/String;
    //   122: invokestatic 440	kkkkkk/xtxtxt:bии0438и04380438и0438ии	(Ljava/lang/String;Ljava/lang/String;)V
    //   125: iconst_1
    //   126: istore_3
    //   127: aload_0
    //   128: aload_1
    //   129: iload_3
    //   130: invokespecial 856	kkkkkk/eeefee:b044Dэ044D044D044Dэээээ	(Lkkkkkk/nfnfnn;Z)Z
    //   133: ifeq +88 -> 221
    //   136: getstatic 145	kkkkkk/eeefee:bттт0442т0442т0442т	Ljava/lang/String;
    //   139: astore 6
    //   141: new 422	java/lang/StringBuilder
    //   144: dup
    //   145: invokespecial 423	java/lang/StringBuilder:<init>	()V
    //   148: astore 7
    //   150: getstatic 111	kkkkkk/eeefee:b0442т04420442т0442т0442т	I
    //   153: getstatic 113	kkkkkk/eeefee:b0442044204420442т0442т0442т	I
    //   156: iadd
    //   157: getstatic 111	kkkkkk/eeefee:b0442т04420442т0442т0442т	I
    //   160: imul
    //   161: getstatic 115	kkkkkk/eeefee:bтттт04420442т0442т	I
    //   164: irem
    //   165: getstatic 117	kkkkkk/eeefee:bт044204420442т0442т0442т	I
    //   168: if_icmpeq +15 -> 183
    //   171: invokestatic 121	kkkkkk/eeefee:b04240424ФФФ04240424042404240424	()I
    //   174: putstatic 111	kkkkkk/eeefee:b0442т04420442т0442т0442т	I
    //   177: invokestatic 121	kkkkkk/eeefee:b04240424ФФФ04240424042404240424	()I
    //   180: putstatic 117	kkkkkk/eeefee:bт044204420442т0442т0442т	I
    //   183: aload 6
    //   185: aload 7
    //   187: ldc_w 858
    //   190: sipush 198
    //   193: sipush 133
    //   196: iconst_3
    //   197: invokestatic 97	kkkkkk/gguuuu:bк043Aккк043Aкк043A043A	(Ljava/lang/String;CCC)Ljava/lang/String;
    //   200: invokevirtual 429	java/lang/StringBuilder:append	(Ljava/lang/String;)Ljava/lang/StringBuilder;
    //   203: aload_1
    //   204: invokevirtual 304	kkkkkk/nfnfnn:b044Dэ044Dэ044Dэ044Dэ044Dэ	()I
    //   207: invokevirtual 508	java/lang/StringBuilder:append	(I)Ljava/lang/StringBuilder;
    //   210: invokevirtual 435	java/lang/StringBuilder:toString	()Ljava/lang/String;
    //   213: invokestatic 440	kkkkkk/xtxtxt:bии0438и04380438и0438ии	(Ljava/lang/String;Ljava/lang/String;)V
    //   216: aload_0
    //   217: aload_1
    //   218: invokespecial 860	kkkkkk/eeefee:b044D044D044D044D044Dэээээ	(Lkkkkkk/nfnfnn;)V
    //   221: return
    //   222: getstatic 145	kkkkkk/eeefee:bттт0442т0442т0442т	Ljava/lang/String;
    //   225: astore 6
    //   227: new 422	java/lang/StringBuilder
    //   230: dup
    //   231: invokespecial 423	java/lang/StringBuilder:<init>	()V
    //   234: astore 7
    //   236: aload 6
    //   238: aload 7
    //   240: ldc_w 862
    //   243: bipush 59
    //   245: iconst_4
    //   246: invokestatic 89	kkkkkk/gguuuu:bккккк043Aкк043A043A	(Ljava/lang/String;CC)Ljava/lang/String;
    //   249: invokevirtual 429	java/lang/StringBuilder:append	(Ljava/lang/String;)Ljava/lang/StringBuilder;
    //   252: lload 4
    //   254: invokevirtual 654	java/lang/StringBuilder:append	(J)Ljava/lang/StringBuilder;
    //   257: ldc_w 864
    //   260: bipush 78
    //   262: iconst_5
    //   263: invokestatic 89	kkkkkk/gguuuu:bккккк043Aкк043A043A	(Ljava/lang/String;CC)Ljava/lang/String;
    //   266: invokevirtual 429	java/lang/StringBuilder:append	(Ljava/lang/String;)Ljava/lang/StringBuilder;
    //   269: iload_2
    //   270: invokevirtual 508	java/lang/StringBuilder:append	(I)Ljava/lang/StringBuilder;
    //   273: invokevirtual 435	java/lang/StringBuilder:toString	()Ljava/lang/String;
    //   276: invokestatic 440	kkkkkk/xtxtxt:bии0438и04380438и0438ии	(Ljava/lang/String;Ljava/lang/String;)V
    //   279: aload_0
    //   280: getfield 166	kkkkkk/eeefee:b0442тт0442т0442т0442т	Ljava/util/HashSet;
    //   283: astore 6
    //   285: aload 6
    //   287: iload_2
    //   288: invokestatic 222	java/lang/Integer:valueOf	(I)Ljava/lang/Integer;
    //   291: invokevirtual 546	java/util/HashSet:add	(Ljava/lang/Object;)Z
    //   294: pop
    //   295: goto -168 -> 127
    //   298: astore_1
    //   299: aload_1
    //   300: athrow
    //   301: astore_1
    //   302: aload_1
    //   303: athrow
    // Local variable table:
    //   start	length	slot	name	signature
    //   0	304	0	this	eeefee
    //   0	304	1	paramString	String
    //   0	304	2	paramInt	int
    //   1	129	3	bool	boolean
    //   57	196	4	l	long
    //   139	147	6	localObject	Object
    //   148	91	7	localStringBuilder	StringBuilder
    // Exception table:
    //   from	to	target	type
    //   183	221	298	java/lang/Exception
    //   236	279	298	java/lang/Exception
    //   285	295	298	java/lang/Exception
    //   34	40	301	java/lang/Exception
    //   44	59	301	java/lang/Exception
    //   69	125	301	java/lang/Exception
    //   127	150	301	java/lang/Exception
    //   222	236	301	java/lang/Exception
    //   279	285	301	java/lang/Exception
  }
  
  public void b044D044Dээээээээ(String paramString)
  {
    try
    {
      dxxxxx.bиии04380438и0438иии(new eeefee.13(this, paramString));
      int i = b0442т04420442т0442т0442т;
      switch (i * (b0442044204420442т0442т0442т + i) % bтттт04420442т0442т)
      {
      default: 
        b0442т04420442т0442т0442т = 65;
        if ((b0442т04420442т0442т0442т + b0442044204420442т0442т0442т) * b0442т04420442т0442т0442т % bтттт04420442т0442т != bт044204420442т0442т0442т)
        {
          b0442т04420442т0442т0442т = b04240424ФФФ04240424042404240424();
          bт044204420442т0442т0442т = 66;
        }
        bт044204420442т0442т0442т = 97;
        switch (1)
        {
        case 0: 
        default: 
          for (;;)
          {
            switch (1)
            {
            }
          }
        }
        break;
      }
      return;
    }
    catch (Exception paramString)
    {
      throw paramString;
    }
  }
  
  public void b044Dэ044Dэ044Dэээээ(String paramString1, String paramString2)
  {
    int i = b0442т04420442т0442т0442т;
    switch (i * (b0442044204420442т0442т0442т + i) % bтттт04420442т0442т)
    {
    default: 
      b0442т04420442т0442т0442т = 24;
      bт044204420442т0442т0442т = 53;
    }
    paramString1 = b0424Ф0424Ф042404240424042404240424(paramString1);
    i = b0442т04420442т0442т0442т;
    switch (i * (b0442044204420442т0442т0442т + i) % bтттт04420442т0442т)
    {
    default: 
      b0442т04420442т0442т0442т = b04240424ФФФ04240424042404240424();
      bт044204420442т0442т0442т = 70;
    }
    if (paramString1 != null)
    {
      String str = paramString1.b044D044Dээ044Dэ044Dэ044Dэ();
      switch (0)
      {
      case 1: 
      default: 
        for (;;)
        {
          switch (1)
          {
          }
        }
      }
      if (paramString2.equals(str)) {
        paramString1.bэээ044Dэ044D044Dэ044Dэ(xxxddd.dddxdd.SHOWN);
      }
    }
    dxxxxx.bиии04380438и0438иии(new eeefee.15(this, paramString2));
  }
  
  /* Error */
  public xddxxx<nfnfnn> b044Dээ044D044Dэээээ(String paramString, ffnfnn paramFfnfnn)
  {
    // Byte code:
    //   0: aload_0
    //   1: aload_1
    //   2: invokevirtual 850	kkkkkk/eeefee:bФФ0424Ф042404240424042404240424	(Ljava/lang/String;)Lkkkkkk/nfnfnn;
    //   5: astore_3
    //   6: aload_0
    //   7: aload_2
    //   8: getfield 884	kkkkkk/ffnfnn:b043C043Cмм043C043C043C043Cм	Ljava/lang/String;
    //   11: aload_1
    //   12: invokespecial 886	kkkkkk/eeefee:b044D044D044Dэээээээ	(Ljava/lang/String;Ljava/lang/String;)V
    //   15: goto +94 -> 109
    //   18: aload_3
    //   19: aload_2
    //   20: getfield 889	kkkkkk/ffnfnn:bм043Cмм043C043C043C043Cм	Lkkkkkk/dxdxdd;
    //   23: invokevirtual 781	kkkkkk/nfnfnn:bэ044Dэ044Dэ044D044Dэ044Dэ	(Lkkkkkk/dxdxdd;)V
    //   26: aload_2
    //   27: getfield 892	kkkkkk/ffnfnn:bммм043Cм043C043C043Cм	Lkkkkkk/xdxxdd;
    //   30: astore_1
    //   31: aload_3
    //   32: aload_1
    //   33: invokevirtual 789	kkkkkk/nfnfnn:bээ044Dээ044D044Dэ044Dэ	(Lkkkkkk/xdxxdd;)V
    //   36: aload_3
    //   37: aload_2
    //   38: getfield 896	kkkkkk/ffnfnn:b043C043C043C043Cм043C043C043Cм	J
    //   41: invokevirtual 793	kkkkkk/nfnfnn:bэ044D044Dээ044D044Dэ044Dэ	(J)V
    //   44: aload_3
    //   45: aload_2
    //   46: getfield 899	kkkkkk/ffnfnn:b043C043C043Cмм043C043C043Cм	Ljava/lang/String;
    //   49: invokevirtual 773	kkkkkk/nfnfnn:b044D044D044Dээ044D044Dэ044Dэ	(Ljava/lang/String;)V
    //   52: aload_3
    //   53: aload_2
    //   54: getfield 902	kkkkkk/ffnfnn:b043C043Cммм043C043C043Cм	Ljava/lang/String;
    //   57: invokevirtual 905	kkkkkk/nfnfnn:bэээээ044D044Dэ044Dэ	(Ljava/lang/String;)V
    //   60: aload_0
    //   61: aload_2
    //   62: getfield 884	kkkkkk/ffnfnn:b043C043Cмм043C043C043C043Cм	Ljava/lang/String;
    //   65: aload_3
    //   66: invokevirtual 588	kkkkkk/eeefee:bФ0424042404240424Ф0424042404240424	(Ljava/lang/String;Lkkkkkk/nfnfnn;)V
    //   69: new 264	java/lang/NullPointerException
    //   72: dup
    //   73: invokespecial 265	java/lang/NullPointerException:<init>	()V
    //   76: athrow
    //   77: astore_1
    //   78: invokestatic 121	kkkkkk/eeefee:b04240424ФФФ04240424042404240424	()I
    //   81: putstatic 111	kkkkkk/eeefee:b0442т04420442т0442т0442т	I
    //   84: new 316	kkkkkk/xddxxx
    //   87: dup
    //   88: new 907	kkkkkk/eeefee$5
    //   91: dup
    //   92: aload_0
    //   93: aload_3
    //   94: invokespecial 908	kkkkkk/eeefee$5:<init>	(Lkkkkkk/eeefee;Lkkkkkk/nfnfnn;)V
    //   97: invokespecial 324	kkkkkk/xddxxx:<init>	(Lkkkkkk/xddxxx$xdxxxx;)V
    //   100: astore_1
    //   101: aload_1
    //   102: areturn
    //   103: astore_1
    //   104: aload_1
    //   105: athrow
    //   106: astore_1
    //   107: aload_1
    //   108: athrow
    //   109: iconst_1
    //   110: tableswitch	default:+22->132, 0:+-1->109, 1:+-92->18
    //   132: iconst_1
    //   133: tableswitch	default:+23->156, 0:+-24->109, 1:+-115->18
    //   156: goto -24 -> 132
    // Local variable table:
    //   start	length	slot	name	signature
    //   0	159	0	this	eeefee
    //   0	159	1	paramString	String
    //   0	159	2	paramFfnfnn	ffnfnn
    //   5	89	3	localNfnfnn	nfnfnn
    // Exception table:
    //   from	to	target	type
    //   69	77	77	java/lang/Exception
    //   0	15	103	java/lang/Exception
    //   18	26	103	java/lang/Exception
    //   31	36	103	java/lang/Exception
    //   44	69	103	java/lang/Exception
    //   26	31	106	java/lang/Exception
    //   36	44	106	java/lang/Exception
    //   84	101	106	java/lang/Exception
  }
  
  public void b044Dээ044Dээээээ(String paramString)
  {
    nfnfnn localNfnfnn = bФФФФ042404240424042404240424(paramString);
    if (localNfnfnn != null)
    {
      int i = localNfnfnn.b044Dэ044D044D044Dэ044Dэ044Dэ() - 1;
      String str = bттт0442т0442т0442т;
      StringBuilder localStringBuilder = new StringBuilder();
      switch (0)
      {
      case 1: 
      default: 
        for (;;)
        {
          switch (1)
          {
          }
        }
      }
      int j = b04240424ФФФ04240424042404240424();
      switch (j * (b0442044204420442т0442т0442т + j) % bтттт04420442т0442т)
      {
      default: 
        b0442т04420442т0442т0442т = b04240424ФФФ04240424042404240424();
        bт044204420442т0442т0442т = b04240424ФФФ04240424042404240424();
      }
      switch (0)
      {
      case 1: 
      default: 
        for (;;)
        {
          switch (0)
          {
          }
        }
      }
      localStringBuilder = localStringBuilder.append(gguuuu.bккккк043Aкк043A043A("4(14<060i@<1/C5pD8EJ;JLx@JN|ANNWGUWFZPWW$\013", '¿', '\001'));
      if ((b0442т04420442т0442т0442т + b0442044204420442т0442т0442т) * b0442т04420442т0442т0442т % bтттт04420442т0442т != bт044204420442т0442т0442т)
      {
        b0442т04420442т0442т0442т = 81;
        bт044204420442т0442т0442т = 6;
      }
      xtxtxt.bии0438и04380438и0438ии(str, paramString + gguuuu.bк043Aккк043Aкк043A043A("8-\001t\002\007w\007\t\t6\001\0079\013\016\f\005\021\005\024\025\\C", 'Ì', 'A', '\001') + i);
      localNfnfnn.bээ044D044Dэ044D044Dэ044Dэ(i);
    }
    bэ044D044D044D044Dэээээ(paramString, -1);
  }
  
  public void b044Dэээээээээ(String paramString)
  {
    paramString = new eeefee.3(this, paramString);
    int i = b0442т04420442т0442т0442т;
    switch (i * (b0442044204420442т0442т0442т + i) % bтттт04420442т0442т)
    {
    default: 
      b0442т04420442т0442т0442т = b04240424ФФФ04240424042404240424();
      bт044204420442т0442т0442т = b04240424ФФФ04240424042404240424();
    }
    if ((b0442т04420442т0442т0442т + bФ0424ФФФ04240424042404240424()) * b0442т04420442т0442т0442т % bтттт04420442т0442т != bт044204420442т0442т0442т)
    {
      b0442т04420442т0442т0442т = 38;
      bт044204420442т0442т0442т = 1;
    }
    dxxxxx.bиии04380438и0438иии(paramString);
  }
  
  /* Error */
  public boolean bФ042404240424042404240424042404240424(String paramString)
  {
    // Byte code:
    //   0: iconst_1
    //   1: istore 7
    //   3: iconst_1
    //   4: istore 9
    //   6: iconst_0
    //   7: istore 8
    //   9: aload_0
    //   10: getfield 168	kkkkkk/eeefee:bт0442т0442т0442т0442т	Lkkkkkk/kkyykk;
    //   13: invokevirtual 923	kkkkkk/kkyykk:b042804280428Ш0428042804280428Ш0428	()Lcom/liveperson/infra/ConversationViewParams;
    //   16: astore 17
    //   18: aload 17
    //   20: invokevirtual 929	com/liveperson/infra/ConversationViewParams:getHistoryConversationsStateToDisplay	()Lkkkkkk/dxxddx;
    //   23: getstatic 934	kkkkkk/dxxddx:OPEN	Lkkkkkk/dxxddx;
    //   26: if_acmpne +5 -> 31
    //   29: iconst_0
    //   30: ireturn
    //   31: aload_0
    //   32: aload_1
    //   33: invokespecial 595	kkkkkk/eeefee:b0424ФФ0424042404240424042404240424	(Ljava/lang/String;)Landroid/database/Cursor;
    //   36: astore_1
    //   37: aload_1
    //   38: ifnull +276 -> 314
    //   41: aload_1
    //   42: invokeinterface 579 1 0
    //   47: istore 10
    //   49: iload 10
    //   51: ifeq +263 -> 314
    //   54: aload_1
    //   55: invokeinterface 937 1 0
    //   60: iconst_1
    //   61: if_icmpne +242 -> 303
    //   64: aload_1
    //   65: invokestatic 671	kkkkkk/eeefee:b044Dэ044Dэээээээ	(Landroid/database/Cursor;)Lkkkkkk/nfnfnn;
    //   68: astore 18
    //   70: aload 17
    //   72: invokevirtual 940	com/liveperson/infra/ConversationViewParams:isFilterOn	()Z
    //   75: ifeq +210 -> 285
    //   78: aload 17
    //   80: invokevirtual 943	com/liveperson/infra/ConversationViewParams:getHistoryConversationsMaxDays	()I
    //   83: i2l
    //   84: ldc2_w 944
    //   87: lmul
    //   88: lstore 11
    //   90: getstatic 951	kkkkkk/eeefee$27:bт0442т044204420442тт0442	[I
    //   93: astore 19
    //   95: getstatic 111	kkkkkk/eeefee:b0442т04420442т0442т0442т	I
    //   98: istore_2
    //   99: getstatic 113	kkkkkk/eeefee:b0442044204420442т0442т0442т	I
    //   102: istore_3
    //   103: getstatic 111	kkkkkk/eeefee:b0442т04420442т0442т0442т	I
    //   106: istore 4
    //   108: getstatic 115	kkkkkk/eeefee:bтттт04420442т0442т	I
    //   111: istore 5
    //   113: getstatic 117	kkkkkk/eeefee:bт044204420442т0442т0442т	I
    //   116: istore 6
    //   118: iload_2
    //   119: iload_3
    //   120: iadd
    //   121: iload 4
    //   123: imul
    //   124: iload 5
    //   126: irem
    //   127: iload 6
    //   129: if_icmpeq +14 -> 143
    //   132: invokestatic 121	kkkkkk/eeefee:b04240424ФФФ04240424042404240424	()I
    //   135: putstatic 111	kkkkkk/eeefee:b0442т04420442т0442т0442т	I
    //   138: bipush 20
    //   140: putstatic 117	kkkkkk/eeefee:bт044204420442т0442т0442т	I
    //   143: aload 19
    //   145: aload 17
    //   147: invokevirtual 955	com/liveperson/infra/ConversationViewParams:getHistoryConversationMaxDaysType	()Lkkkkkk/xdxddx;
    //   150: invokevirtual 958	kkkkkk/xdxddx:ordinal	()I
    //   153: iaload
    //   154: istore_2
    //   155: iload 9
    //   157: istore 7
    //   159: iload_2
    //   160: tableswitch	default:+24->184, 1:+39->199, 2:+61->221
    //   184: iconst_1
    //   185: istore 8
    //   187: aload_1
    //   188: invokeinterface 585 1 0
    //   193: iload 8
    //   195: ireturn
    //   196: astore_1
    //   197: aload_1
    //   198: athrow
    //   199: iload 9
    //   201: istore 7
    //   203: aload 18
    //   205: invokevirtual 270	kkkkkk/nfnfnn:bэ044Dээ044Dэ044Dэ044Dэ	()J
    //   208: invokestatic 639	java/lang/System:currentTimeMillis	()J
    //   211: lload 11
    //   213: lsub
    //   214: lcmp
    //   215: ifge +6 -> 221
    //   218: iconst_0
    //   219: istore 7
    //   221: aload 18
    //   223: invokevirtual 291	kkkkkk/nfnfnn:bэээ044D044Dэ044Dэ044Dэ	()J
    //   226: lstore 13
    //   228: getstatic 111	kkkkkk/eeefee:b0442т04420442т0442т0442т	I
    //   231: istore_2
    //   232: iload_2
    //   233: invokestatic 295	kkkkkk/eeefee:bФ0424ФФФ04240424042404240424	()I
    //   236: iload_2
    //   237: iadd
    //   238: imul
    //   239: getstatic 115	kkkkkk/eeefee:bтттт04420442т0442т	I
    //   242: irem
    //   243: tableswitch	default:+17->260, 0:+26->269
    //   260: iconst_2
    //   261: putstatic 111	kkkkkk/eeefee:b0442т04420442т0442т0442т	I
    //   264: bipush 16
    //   266: putstatic 117	kkkkkk/eeefee:bт044204420442т0442т0442т	I
    //   269: invokestatic 639	java/lang/System:currentTimeMillis	()J
    //   272: lstore 15
    //   274: lload 13
    //   276: lload 15
    //   278: lload 11
    //   280: lsub
    //   281: lcmp
    //   282: iflt -95 -> 187
    //   285: iload 7
    //   287: istore 8
    //   289: goto -102 -> 187
    //   292: astore 17
    //   294: aload_1
    //   295: invokeinterface 585 1 0
    //   300: aload 17
    //   302: athrow
    //   303: aload_1
    //   304: invokeinterface 585 1 0
    //   309: iconst_0
    //   310: ireturn
    //   311: astore_1
    //   312: aload_1
    //   313: athrow
    //   314: iconst_0
    //   315: ireturn
    // Local variable table:
    //   start	length	slot	name	signature
    //   0	316	0	this	eeefee
    //   0	316	1	paramString	String
    //   98	141	2	i	int
    //   102	19	3	j	int
    //   106	18	4	k	int
    //   111	16	5	m	int
    //   116	14	6	n	int
    //   1	285	7	bool1	boolean
    //   7	281	8	bool2	boolean
    //   4	196	9	bool3	boolean
    //   47	3	10	bool4	boolean
    //   88	191	11	l1	long
    //   226	49	13	l2	long
    //   272	5	15	l3	long
    //   16	130	17	localConversationViewParams	com.liveperson.infra.ConversationViewParams
    //   292	9	17	localObject	Object
    //   68	154	18	localNfnfnn	nfnfnn
    //   93	51	19	arrayOfInt	int[]
    // Exception table:
    //   from	to	target	type
    //   18	29	196	java/lang/Exception
    //   31	37	196	java/lang/Exception
    //   41	49	196	java/lang/Exception
    //   95	118	196	java/lang/Exception
    //   187	193	196	java/lang/Exception
    //   294	303	196	java/lang/Exception
    //   54	70	292	finally
    //   70	95	292	finally
    //   143	155	292	finally
    //   203	218	292	finally
    //   221	228	292	finally
    //   269	274	292	finally
    //   9	18	311	java/lang/Exception
    //   132	143	311	java/lang/Exception
    //   303	309	311	java/lang/Exception
  }
  
  /* Error */
  public void bФ0424042404240424Ф0424042404240424(String paramString, nfnfnn paramNfnfnn)
  {
    // Byte code:
    //   0: aload_0
    //   1: getfield 159	kkkkkk/eeefee:b04420442т0442т0442т0442т	Ljava/util/Map;
    //   4: aload_1
    //   5: aload_2
    //   6: invokeinterface 802 3 0
    //   11: pop
    //   12: aload_0
    //   13: getfield 161	kkkkkk/eeefee:bтт04420442т0442т0442т	Ljava/util/Map;
    //   16: astore_1
    //   17: aload_2
    //   18: invokevirtual 191	kkkkkk/nfnfnn:b044D044Dээ044Dэ044Dэ044Dэ	()Ljava/lang/String;
    //   21: astore 6
    //   23: aload_1
    //   24: aload 6
    //   26: aload_2
    //   27: invokeinterface 802 3 0
    //   32: pop
    //   33: getstatic 145	kkkkkk/eeefee:bттт0442т0442т0442т	Ljava/lang/String;
    //   36: astore_1
    //   37: new 422	java/lang/StringBuilder
    //   40: dup
    //   41: invokespecial 423	java/lang/StringBuilder:<init>	()V
    //   44: astore 6
    //   46: getstatic 111	kkkkkk/eeefee:b0442т04420442т0442т0442т	I
    //   49: istore_3
    //   50: iload_3
    //   51: getstatic 113	kkkkkk/eeefee:b0442044204420442т0442т0442т	I
    //   54: iload_3
    //   55: iadd
    //   56: imul
    //   57: getstatic 115	kkkkkk/eeefee:bтттт04420442т0442т	I
    //   60: irem
    //   61: tableswitch	default:+19->80, 0:+31->92
    //   80: invokestatic 121	kkkkkk/eeefee:b04240424ФФФ04240424042404240424	()I
    //   83: putstatic 111	kkkkkk/eeefee:b0442т04420442т0442т0442т	I
    //   86: invokestatic 121	kkkkkk/eeefee:b04240424ФФФ04240424042404240424	()I
    //   89: putstatic 117	kkkkkk/eeefee:bт044204420442т0442т0442т	I
    //   92: aload 6
    //   94: ldc_w 960
    //   97: bipush 58
    //   99: sipush 231
    //   102: iconst_1
    //   103: invokestatic 97	kkkkkk/gguuuu:bк043Aккк043Aкк043A043A	(Ljava/lang/String;CCC)Ljava/lang/String;
    //   106: invokevirtual 429	java/lang/StringBuilder:append	(Ljava/lang/String;)Ljava/lang/StringBuilder;
    //   109: aload_2
    //   110: invokevirtual 191	kkkkkk/nfnfnn:b044D044Dээ044Dэ044Dэ044Dэ	()Ljava/lang/String;
    //   113: invokevirtual 429	java/lang/StringBuilder:append	(Ljava/lang/String;)Ljava/lang/StringBuilder;
    //   116: ldc_w 962
    //   119: sipush 169
    //   122: iconst_3
    //   123: invokestatic 89	kkkkkk/gguuuu:bккккк043Aкк043A043A	(Ljava/lang/String;CC)Ljava/lang/String;
    //   126: invokevirtual 429	java/lang/StringBuilder:append	(Ljava/lang/String;)Ljava/lang/StringBuilder;
    //   129: astore 6
    //   131: aload 6
    //   133: aload_2
    //   134: invokevirtual 205	kkkkkk/nfnfnn:b044D044Dэ044D044Dэ044Dэ044Dэ	()Ljava/lang/String;
    //   137: invokevirtual 429	java/lang/StringBuilder:append	(Ljava/lang/String;)Ljava/lang/StringBuilder;
    //   140: astore_2
    //   141: invokestatic 121	kkkkkk/eeefee:b04240424ФФФ04240424042404240424	()I
    //   144: istore_3
    //   145: getstatic 113	kkkkkk/eeefee:b0442044204420442т0442т0442т	I
    //   148: istore 4
    //   150: invokestatic 121	kkkkkk/eeefee:b04240424ФФФ04240424042404240424	()I
    //   153: istore 5
    //   155: iload_3
    //   156: iload 4
    //   158: iadd
    //   159: iload 5
    //   161: imul
    //   162: getstatic 115	kkkkkk/eeefee:bтттт04420442т0442т	I
    //   165: irem
    //   166: getstatic 117	kkkkkk/eeefee:bт044204420442т0442т0442т	I
    //   169: if_icmpeq +14 -> 183
    //   172: invokestatic 121	kkkkkk/eeefee:b04240424ФФФ04240424042404240424	()I
    //   175: putstatic 111	kkkkkk/eeefee:b0442т04420442т0442т0442т	I
    //   178: bipush 19
    //   180: putstatic 117	kkkkkk/eeefee:bт044204420442т0442т0442т	I
    //   183: aload_1
    //   184: aload_2
    //   185: invokevirtual 435	java/lang/StringBuilder:toString	()Ljava/lang/String;
    //   188: invokestatic 440	kkkkkk/xtxtxt:bии0438и04380438и0438ии	(Ljava/lang/String;Ljava/lang/String;)V
    //   191: return
    //   192: astore_1
    //   193: aload_1
    //   194: athrow
    //   195: astore_1
    //   196: aload_1
    //   197: athrow
    //   198: astore_1
    //   199: aload_1
    //   200: athrow
    //   201: astore_1
    //   202: aload_1
    //   203: athrow
    // Local variable table:
    //   start	length	slot	name	signature
    //   0	204	0	this	eeefee
    //   0	204	1	paramString	String
    //   0	204	2	paramNfnfnn	nfnfnn
    //   49	110	3	i	int
    //   148	11	4	j	int
    //   153	9	5	k	int
    //   21	111	6	localObject	Object
    // Exception table:
    //   from	to	target	type
    //   0	23	192	java/lang/Exception
    //   92	131	192	java/lang/Exception
    //   183	191	192	java/lang/Exception
    //   155	183	195	java/lang/Exception
    //   193	195	195	java/lang/Exception
    //   199	201	195	java/lang/Exception
    //   23	46	198	java/lang/Exception
    //   131	141	198	java/lang/Exception
    //   141	155	201	java/lang/Exception
  }
  
  public xddxxx<nfnfnn> bФ042404240424Ф04240424042404240424(String paramString)
  {
    paramString = new xddxxx(new eeefee.1(this, paramString));
    int i = b0442т04420442т0442т0442т;
    int j = b0442044204420442т0442т0442т;
    int k = bтттт04420442т0442т;
    int m = b0442т04420442т0442т0442т;
    switch (m * (b0442044204420442т0442т0442т + m) % bтттт04420442т0442т)
    {
    default: 
      b0442т04420442т0442т0442т = 79;
      bт044204420442т0442т0442т = 72;
    }
    switch (i * (j + i) % k)
    {
    default: 
      b0442т04420442т0442т0442т = b04240424ФФФ04240424042404240424();
      bт044204420442т0442т0442т = 17;
    }
    return paramString;
  }
  
  @NonNull
  public ccmcmm bФ04240424Ф042404240424042404240424()
  {
    int i = b04240424ФФФ04240424042404240424();
    int j = b0442044204420442т0442т0442т;
    int k = b04240424ФФФ04240424042404240424();
    int m = bтттт04420442т0442т;
    switch (0)
    {
    case 1: 
    default: 
      for (;;)
      {
        switch (0)
        {
        }
      }
    }
    if ((i + j) * k % m != bт044204420442т0442т0442т)
    {
      b0442т04420442т0442т0442т = b04240424ФФФ04240424042404240424();
      bт044204420442т0442т0442т = b04240424ФФФ04240424042404240424();
      i = b0442т04420442т0442т0442т;
      switch (i * (bФ0424ФФФ04240424042404240424() + i) % bтттт04420442т0442т)
      {
      default: 
        b0442т04420442т0442т0442т = b04240424ФФФ04240424042404240424();
        bт044204420442т0442т0442т = 85;
      }
    }
    return new ccmcmm(this.bт0442т0442т0442т0442т);
  }
  
  public xddxxx<List<nfnfnn>> bФ0424Ф0424042404240424042404240424(String paramString)
  {
    try
    {
      paramString = new xddxxx(new eeefee.22(this, paramString));
    }
    catch (Exception paramString)
    {
      try
      {
        int i;
        int j;
        int k;
        int m;
        int n;
        b0442т04420442т0442т0442т = 3;
        bт044204420442т0442т0442т = b04240424ФФФ04240424042404240424();
        return paramString;
      }
      catch (Exception paramString)
      {
        throw paramString;
      }
      paramString = paramString;
      throw paramString;
    }
    i = b0442т04420442т0442т0442т;
    j = bФ0424ФФФ04240424042404240424();
    k = b0442т04420442т0442т0442т;
    m = bтттт04420442т0442т;
    n = bт044204420442т0442т0442т;
    if ((i + j) * k % m != n)
    {
      i = b0442т04420442т0442т0442т;
      switch (i * (b0442044204420442т0442т0442т + i) % bтттт04420442т0442т)
      {
      default: 
        b0442т04420442т0442т0442т = 65;
        bт044204420442т0442т0442т = 0;
      }
    }
    switch (1)
    {
    }
    for (;;)
    {
      switch (1)
      {
      }
    }
  }
  
  /* Error */
  public nfnfnn bФ0424Ф0424Ф04240424042404240424(ffnfnn paramFfnfnn)
  {
    // Byte code:
    //   0: new 188	kkkkkk/nfnfnn
    //   3: dup
    //   4: aload_1
    //   5: invokespecial 982	kkkkkk/nfnfnn:<init>	(Lkkkkkk/ffnfnn;)V
    //   8: astore_3
    //   9: getstatic 111	kkkkkk/eeefee:b0442т04420442т0442т0442т	I
    //   12: istore_2
    //   13: iload_2
    //   14: getstatic 113	kkkkkk/eeefee:b0442044204420442т0442т0442т	I
    //   17: iload_2
    //   18: iadd
    //   19: imul
    //   20: getstatic 115	kkkkkk/eeefee:bтттт04420442т0442т	I
    //   23: irem
    //   24: tableswitch	default:+20->44, 0:+31->55
    //   44: bipush 89
    //   46: putstatic 111	kkkkkk/eeefee:b0442т04420442т0442т0442т	I
    //   49: invokestatic 121	kkkkkk/eeefee:b04240424ФФФ04240424042404240424	()I
    //   52: putstatic 117	kkkkkk/eeefee:bт044204420442т0442т0442т	I
    //   55: aload_0
    //   56: aload_1
    //   57: getfield 884	kkkkkk/ffnfnn:b043C043Cмм043C043C043C043Cм	Ljava/lang/String;
    //   60: aload_3
    //   61: invokevirtual 588	kkkkkk/eeefee:bФ0424042404240424Ф0424042404240424	(Ljava/lang/String;Lkkkkkk/nfnfnn;)V
    //   64: new 984	kkkkkk/eeefee$9
    //   67: dup
    //   68: aload_0
    //   69: aload_3
    //   70: aload_1
    //   71: invokespecial 987	kkkkkk/eeefee$9:<init>	(Lkkkkkk/eeefee;Lkkkkkk/nfnfnn;Lkkkkkk/ffnfnn;)V
    //   74: astore_1
    //   75: iconst_0
    //   76: tableswitch	default:+24->100, 0:+51->127, 1:+-1->75
    //   100: iconst_1
    //   101: tableswitch	default:+23->124, 0:+-26->75, 1:+26->127
    //   124: goto -24 -> 100
    //   127: getstatic 111	kkkkkk/eeefee:b0442т04420442т0442т0442т	I
    //   130: istore_2
    //   131: iload_2
    //   132: getstatic 113	kkkkkk/eeefee:b0442044204420442т0442т0442т	I
    //   135: iload_2
    //   136: iadd
    //   137: imul
    //   138: getstatic 115	kkkkkk/eeefee:bтттт04420442т0442т	I
    //   141: irem
    //   142: tableswitch	default:+18->160, 0:+28->170
    //   160: bipush 83
    //   162: putstatic 111	kkkkkk/eeefee:b0442т04420442т0442т0442т	I
    //   165: bipush 37
    //   167: putstatic 117	kkkkkk/eeefee:bт044204420442т0442т0442т	I
    //   170: aload_1
    //   171: invokestatic 401	kkkkkk/dxxxxx:bиии04380438и0438иии	(Ljava/lang/Runnable;)V
    //   174: aload_3
    //   175: areturn
    //   176: astore_1
    //   177: aload_1
    //   178: athrow
    //   179: astore_1
    //   180: aload_1
    //   181: athrow
    // Local variable table:
    //   start	length	slot	name	signature
    //   0	182	0	this	eeefee
    //   0	182	1	paramFfnfnn	ffnfnn
    //   12	126	2	i	int
    //   8	167	3	localNfnfnn	nfnfnn
    // Exception table:
    //   from	to	target	type
    //   55	75	176	java/lang/Exception
    //   0	9	179	java/lang/Exception
    //   170	174	179	java/lang/Exception
  }
  
  public xddxxx<nfnfnn> bФ0424ФФ042404240424042404240424(String paramString)
  {
    int i = b0442т04420442т0442т0442т;
    int j = b0442044204420442т0442т0442т;
    switch (0)
    {
    case 1: 
    default: 
      for (;;)
      {
        switch (0)
        {
        }
      }
    }
    switch (i * (j + i) % bтттт04420442т0442т)
    {
    default: 
      i = b0442т04420442т0442т0442т;
      switch (i * (bФ0424ФФФ04240424042404240424() + i) % bтттт04420442т0442т)
      {
      default: 
        b0442т04420442т0442т0442т = b04240424ФФФ04240424042404240424();
        bт044204420442т0442т0442т = 83;
      }
      b0442т04420442т0442т0442т = 12;
      bт044204420442т0442т0442т = b04240424ФФФ04240424042404240424();
    }
    return new xddxxx(new eeefee.16(this, paramString));
  }
  
  /* Error */
  public xddxxx<Void> bФФ04240424Ф04240424042404240424(String paramString)
  {
    // Byte code:
    //   0: new 316	kkkkkk/xddxxx
    //   3: dup
    //   4: new 994	kkkkkk/eeefee$6
    //   7: dup
    //   8: aload_0
    //   9: aload_1
    //   10: invokespecial 995	kkkkkk/eeefee$6:<init>	(Lkkkkkk/eeefee;Ljava/lang/String;)V
    //   13: invokespecial 324	kkkkkk/xddxxx:<init>	(Lkkkkkk/xddxxx$xdxxxx;)V
    //   16: astore_1
    //   17: getstatic 111	kkkkkk/eeefee:b0442т04420442т0442т0442т	I
    //   20: istore_2
    //   21: getstatic 113	kkkkkk/eeefee:b0442044204420442т0442т0442т	I
    //   24: istore_3
    //   25: getstatic 111	kkkkkk/eeefee:b0442т04420442т0442т0442т	I
    //   28: istore 4
    //   30: getstatic 115	kkkkkk/eeefee:bтттт04420442т0442т	I
    //   33: istore 5
    //   35: getstatic 117	kkkkkk/eeefee:bт044204420442т0442т0442т	I
    //   38: istore 6
    //   40: iload_2
    //   41: iload_3
    //   42: iadd
    //   43: iload 4
    //   45: imul
    //   46: iload 5
    //   48: irem
    //   49: iload 6
    //   51: if_icmpeq +62 -> 113
    //   54: invokestatic 121	kkkkkk/eeefee:b04240424ФФФ04240424042404240424	()I
    //   57: istore_2
    //   58: invokestatic 121	kkkkkk/eeefee:b04240424ФФФ04240424042404240424	()I
    //   61: istore_3
    //   62: iload_3
    //   63: getstatic 113	kkkkkk/eeefee:b0442044204420442т0442т0442т	I
    //   66: iload_3
    //   67: iadd
    //   68: imul
    //   69: invokestatic 337	kkkkkk/eeefee:bФФФФФ04240424042404240424	()I
    //   72: irem
    //   73: tableswitch	default:+19->92, 0:+31->104
    //   92: invokestatic 121	kkkkkk/eeefee:b04240424ФФФ04240424042404240424	()I
    //   95: putstatic 111	kkkkkk/eeefee:b0442т04420442т0442т0442т	I
    //   98: invokestatic 121	kkkkkk/eeefee:b04240424ФФФ04240424042404240424	()I
    //   101: putstatic 117	kkkkkk/eeefee:bт044204420442т0442т0442т	I
    //   104: iload_2
    //   105: putstatic 111	kkkkkk/eeefee:b0442т04420442т0442т0442т	I
    //   108: bipush 19
    //   110: putstatic 117	kkkkkk/eeefee:bт044204420442т0442т0442т	I
    //   113: aload_1
    //   114: areturn
    //   115: astore_1
    //   116: aload_1
    //   117: athrow
    //   118: astore_1
    //   119: aload_1
    //   120: athrow
    // Local variable table:
    //   start	length	slot	name	signature
    //   0	121	0	this	eeefee
    //   0	121	1	paramString	String
    //   20	85	2	i	int
    //   24	45	3	j	int
    //   28	18	4	k	int
    //   33	16	5	m	int
    //   38	14	6	n	int
    // Exception table:
    //   from	to	target	type
    //   0	40	115	java/lang/Exception
    //   54	58	118	java/lang/Exception
    //   104	113	118	java/lang/Exception
  }
  
  /* Error */
  public nfnfnn bФФ0424Ф042404240424042404240424(String paramString)
  {
    // Byte code:
    //   0: aload_0
    //   1: getfield 161	kkkkkk/eeefee:bтт04420442т0442т0442т	Ljava/util/Map;
    //   4: aload_1
    //   5: invokeinterface 455 2 0
    //   10: checkcast 188	kkkkkk/nfnfnn
    //   13: astore_3
    //   14: aload_3
    //   15: ifnonnull +122 -> 137
    //   18: aload_0
    //   19: getfield 159	kkkkkk/eeefee:b04420442т0442т0442т0442т	Ljava/util/Map;
    //   22: invokeinterface 1000 1 0
    //   27: invokeinterface 1003 1 0
    //   32: astore 4
    //   34: goto +127 -> 161
    //   37: aload 4
    //   39: invokeinterface 722 1 0
    //   44: ifeq +93 -> 137
    //   47: aload 4
    //   49: invokeinterface 726 1 0
    //   54: astore 5
    //   56: getstatic 111	kkkkkk/eeefee:b0442т04420442т0442т0442т	I
    //   59: getstatic 113	kkkkkk/eeefee:b0442044204420442т0442т0442т	I
    //   62: iadd
    //   63: getstatic 111	kkkkkk/eeefee:b0442т04420442т0442т0442т	I
    //   66: imul
    //   67: getstatic 115	kkkkkk/eeefee:bтттт04420442т0442т	I
    //   70: irem
    //   71: getstatic 117	kkkkkk/eeefee:bт044204420442т0442т0442т	I
    //   74: if_icmpeq +14 -> 88
    //   77: bipush 14
    //   79: putstatic 111	kkkkkk/eeefee:b0442т04420442т0442т0442т	I
    //   82: invokestatic 121	kkkkkk/eeefee:b04240424ФФФ04240424042404240424	()I
    //   85: putstatic 117	kkkkkk/eeefee:bт044204420442т0442т0442т	I
    //   88: aload 5
    //   90: checkcast 1005	java/util/Map$Entry
    //   93: invokeinterface 1008 1 0
    //   98: astore 5
    //   100: aload 5
    //   102: checkcast 188	kkkkkk/nfnfnn
    //   105: astore 5
    //   107: aload_1
    //   108: aload 5
    //   110: invokevirtual 191	kkkkkk/nfnfnn:b044D044Dээ044Dэ044Dэ044Dэ	()Ljava/lang/String;
    //   113: invokevirtual 461	java/lang/String:equals	(Ljava/lang/Object;)Z
    //   116: ifeq +45 -> 161
    //   119: aload_0
    //   120: getfield 161	kkkkkk/eeefee:bтт04420442т0442т0442т	Ljava/util/Map;
    //   123: astore_3
    //   124: aload_3
    //   125: aload_1
    //   126: aload 5
    //   128: invokeinterface 802 3 0
    //   133: pop
    //   134: aload 5
    //   136: areturn
    //   137: iconst_4
    //   138: istore_2
    //   139: iload_2
    //   140: iconst_0
    //   141: idiv
    //   142: istore_2
    //   143: goto -4 -> 139
    //   146: astore_1
    //   147: aload_1
    //   148: athrow
    //   149: astore_1
    //   150: aload_1
    //   151: athrow
    //   152: astore_1
    //   153: invokestatic 121	kkkkkk/eeefee:b04240424ФФФ04240424042404240424	()I
    //   156: putstatic 111	kkkkkk/eeefee:b0442т04420442т0442т0442т	I
    //   159: aload_3
    //   160: areturn
    //   161: iconst_1
    //   162: tableswitch	default:+22->184, 0:+-1->161, 1:+-125->37
    //   184: iconst_1
    //   185: tableswitch	default:+23->208, 0:+-24->161, 1:+-148->37
    //   208: goto -24 -> 184
    // Local variable table:
    //   start	length	slot	name	signature
    //   0	211	0	this	eeefee
    //   0	211	1	paramString	String
    //   138	5	2	i	int
    //   13	147	3	localObject1	Object
    //   32	16	4	localIterator	Iterator
    //   54	81	5	localObject2	Object
    // Exception table:
    //   from	to	target	type
    //   0	14	146	java/lang/Exception
    //   18	34	146	java/lang/Exception
    //   37	56	146	java/lang/Exception
    //   88	100	146	java/lang/Exception
    //   124	134	146	java/lang/Exception
    //   100	124	149	java/lang/Exception
    //   139	143	152	java/lang/Exception
  }
  
  /* Error */
  public long bФФ0424ФФ04240424042404240424(String paramString, xdxxdd paramXdxxdd, long paramLong1, long paramLong2, long paramLong3, long paramLong4)
  {
    // Byte code:
    //   0: ldc2_w 1011
    //   3: lstore 16
    //   5: aload_0
    //   6: aload_1
    //   7: invokevirtual 301	kkkkkk/eeefee:b0424Ф0424Ф042404240424042404240424	(Ljava/lang/String;)Lkkkkkk/nfnfnn;
    //   10: astore_2
    //   11: getstatic 111	kkkkkk/eeefee:b0442т04420442т0442т0442т	I
    //   14: getstatic 113	kkkkkk/eeefee:b0442044204420442т0442т0442т	I
    //   17: iadd
    //   18: getstatic 111	kkkkkk/eeefee:b0442т04420442т0442т0442т	I
    //   21: imul
    //   22: getstatic 115	kkkkkk/eeefee:bтттт04420442т0442т	I
    //   25: irem
    //   26: getstatic 117	kkkkkk/eeefee:bт044204420442т0442т0442т	I
    //   29: if_icmpeq +15 -> 44
    //   32: invokestatic 121	kkkkkk/eeefee:b04240424ФФФ04240424042404240424	()I
    //   35: putstatic 111	kkkkkk/eeefee:b0442т04420442т0442т0442т	I
    //   38: invokestatic 121	kkkkkk/eeefee:b04240424ФФФ04240424042404240424	()I
    //   41: putstatic 117	kkkkkk/eeefee:bт044204420442т0442т0442т	I
    //   44: aload_2
    //   45: ifnull +74 -> 119
    //   48: aload_2
    //   49: invokevirtual 832	kkkkkk/nfnfnn:bэ044Dэ044D044Dэ044Dэ044Dэ	()Lkkkkkk/nfffnf;
    //   52: astore_2
    //   53: getstatic 111	kkkkkk/eeefee:b0442т04420442т0442т0442т	I
    //   56: istore 11
    //   58: getstatic 113	kkkkkk/eeefee:b0442044204420442т0442т0442т	I
    //   61: istore 12
    //   63: getstatic 111	kkkkkk/eeefee:b0442т04420442т0442т0442т	I
    //   66: istore 13
    //   68: getstatic 115	kkkkkk/eeefee:bтттт04420442т0442т	I
    //   71: istore 14
    //   73: getstatic 117	kkkkkk/eeefee:bт044204420442т0442т0442т	I
    //   76: istore 15
    //   78: iload 11
    //   80: iload 12
    //   82: iadd
    //   83: iload 13
    //   85: imul
    //   86: iload 14
    //   88: irem
    //   89: iload 15
    //   91: if_icmpeq +14 -> 105
    //   94: bipush 96
    //   96: putstatic 111	kkkkkk/eeefee:b0442т04420442т0442т0442т	I
    //   99: invokestatic 121	kkkkkk/eeefee:b04240424ФФФ04240424042404240424	()I
    //   102: putstatic 117	kkkkkk/eeefee:bт044204420442т0442т0442т	I
    //   105: aload_2
    //   106: aload_1
    //   107: lload_3
    //   108: lload 5
    //   110: lload 7
    //   112: lload 9
    //   114: invokevirtual 1016	kkkkkk/nfffnf:bээ044D044Dээ044Dээ044D	(Ljava/lang/String;JJJJ)J
    //   117: lstore 16
    //   119: lload 16
    //   121: lreturn
    //   122: astore_1
    //   123: aload_1
    //   124: athrow
    //   125: astore_1
    //   126: aload_1
    //   127: athrow
    //   128: astore_1
    //   129: aload_1
    //   130: athrow
    //   131: astore_1
    //   132: aload_1
    //   133: athrow
    // Local variable table:
    //   start	length	slot	name	signature
    //   0	134	0	this	eeefee
    //   0	134	1	paramString	String
    //   0	134	2	paramXdxxdd	xdxxdd
    //   0	134	3	paramLong1	long
    //   0	134	5	paramLong2	long
    //   0	134	7	paramLong3	long
    //   0	134	9	paramLong4	long
    //   56	27	11	i	int
    //   61	22	12	j	int
    //   66	20	13	k	int
    //   71	18	14	m	int
    //   76	16	15	n	int
    //   3	117	16	l	long
    // Exception table:
    //   from	to	target	type
    //   48	53	122	java/lang/Exception
    //   53	68	125	java/lang/Exception
    //   94	105	125	java/lang/Exception
    //   123	125	125	java/lang/Exception
    //   5	11	128	java/lang/Exception
    //   105	119	128	java/lang/Exception
    //   68	78	131	java/lang/Exception
    //   129	131	131	java/lang/Exception
  }
  
  public nfnfnn bФФФ0424042404240424042404240424(String paramString)
  {
    int i = b0442т04420442т0442т0442т;
    switch (i * (b0442044204420442т0442т0442т + i) % bФФФФФ04240424042404240424())
    {
    default: 
      b0442т04420442т0442т0442т = 23;
      bт044204420442т0442т0442т = b04240424ФФФ04240424042404240424();
    }
    try
    {
      Object localObject1 = b04380438и0438и0438ииии();
      try
      {
        paramString = ((dddxxx)localObject1).b043804380438и04380438ииии(gguuuu.bккккк043Aкк043A043A(".\037%\035\032*T]R\030#\037\034M\020\033\031 \016\032\032\007\031\r\022\020\024?\026\006\002\0169\rx\t|y\b[u0L.L,lxm(zzfxh\"> >\036ln__k\030Yo\025W_adUNbVYP\n--:)\005PLOJT~\017", '', '\002'), new Object[] { paramString, Integer.valueOf(dxdxdd.CLOSE.ordinal()) });
        if (paramString == null) {
          break label254;
        }
        boolean bool = paramString.moveToFirst();
        if (!bool) {
          break label254;
        }
        try
        {
          i = paramString.getCount();
          int j = b0442т04420442т0442т0442т;
          int k = b0442044204420442т0442т0442т;
          int m = b0442т04420442т0442т0442т;
          int n = bФФФФФ04240424042404240424();
          if ((j + k) * m % n != bт044204420442т0442т0442т)
          {
            b0442т04420442т0442т0442т = b04240424ФФФ04240424042404240424();
            bт044204420442т0442т0442т = 60;
          }
          if (i != 1) {
            break label202;
          }
          localObject1 = new nfnfnn(paramString);
          return localObject1;
        }
        finally
        {
          paramString.close();
        }
        paramString.close();
      }
      catch (Exception paramString)
      {
        throw paramString;
      }
      label202:
      switch (0)
      {
      }
      for (;;)
      {
        switch (0)
        {
        }
      }
      return null;
    }
    catch (Exception paramString)
    {
      throw paramString;
    }
  }
  
  public void bФФФ0424Ф04240424042404240424(String paramString1, String paramString2, String paramString3, long paramLong1, long paramLong2)
  {
    throw new Runtime("d2j fail translate: java.lang.IndexOutOfBoundsException: fromIndex < 0: -1\n\tat java.util.BitSet.nextSetBit(BitSet.java:712)\n\tat com.googlecode.dex2jar.ir.ts.array.FillArrayTransformer.makeSureAllElementAreAssigned(FillArrayTransformer.java:505)\n\tat com.googlecode.dex2jar.ir.ts.array.FillArrayTransformer.transformReportChanged(FillArrayTransformer.java:123)\n\tat com.googlecode.dex2jar.ir.ts.StatedTransformer.transform(StatedTransformer.java:10)\n\tat com.googlecode.d2j.dex.Dex2jar$2.optimize(Dex2jar.java:149)\n\tat com.googlecode.d2j.dex.Dex2Asm.convertCode(Dex2Asm.java:414)\n\tat com.googlecode.d2j.dex.ExDex2Asm.convertCode(ExDex2Asm.java:42)\n\tat com.googlecode.d2j.dex.Dex2jar$2.convertCode(Dex2jar.java:128)\n\tat com.googlecode.d2j.dex.Dex2Asm.convertMethod(Dex2Asm.java:509)\n\tat com.googlecode.d2j.dex.Dex2Asm.convertClass(Dex2Asm.java:406)\n\tat com.googlecode.d2j.dex.Dex2Asm.convertDex(Dex2Asm.java:422)\n\tat com.googlecode.d2j.dex.Dex2jar.doTranslate(Dex2jar.java:172)\n\tat com.googlecode.d2j.dex.Dex2jar.to(Dex2jar.java:272)\n\tat com.googlecode.dex2jar.tools.Dex2jarCmd.doCommandLine(Dex2jarCmd.java:108)\n\tat com.googlecode.dex2jar.tools.BaseCmd.doMain(BaseCmd.java:288)\n\tat com.googlecode.dex2jar.tools.Dex2jarCmd.main(Dex2jarCmd.java:32)\n");
  }
  
  public nfnfnn bФФФФ042404240424042404240424(String paramString)
  {
    switch (0)
    {
    case 1: 
    default: 
      for (;;)
      {
        switch (0)
        {
        }
      }
    }
    int i = b0442т04420442т0442т0442т;
    int j = b0442044204420442т0442т0442т;
    int k = b0442т04420442т0442т0442т;
    int m = bтттт04420442т0442т;
    int n = b0442т04420442т0442т0442т;
    switch (n * (b0442044204420442т0442т0442т + n) % bтттт04420442т0442т)
    {
    default: 
      b0442т04420442т0442т0442т = 13;
      bт044204420442т0442т0442т = 29;
    }
    if ((i + j) * k % m != b0424ФФФФ04240424042404240424())
    {
      b0442т04420442т0442т0442т = 33;
      bт044204420442т0442т0442т = 25;
    }
    return b0424Ф0424Ф042404240424042404240424(paramString);
  }
  
  /* Error */
  public xddxxx<nfnfnn> bэ044D044Dэ044Dэээээ(ffnfnn paramFfnfnn, boolean paramBoolean)
  {
    // Byte code:
    //   0: aload_0
    //   1: aload_1
    //   2: getfield 884	kkkkkk/ffnfnn:b043C043Cмм043C043C043C043Cм	Ljava/lang/String;
    //   5: invokevirtual 301	kkkkkk/eeefee:b0424Ф0424Ф042404240424042404240424	(Ljava/lang/String;)Lkkkkkk/nfnfnn;
    //   8: astore 8
    //   10: aload_0
    //   11: aload_1
    //   12: getfield 1029	kkkkkk/ffnfnn:b043Cм043Cмм043C043C043Cм	Lkkkkkk/xddxdd;
    //   15: aload_1
    //   16: getfield 1032	kkkkkk/ffnfnn:bмм043Cмм043C043C043Cм	Ljava/lang/String;
    //   19: aload_1
    //   20: getfield 1035	kkkkkk/ffnfnn:bмм043C043Cм043C043C043Cм	J
    //   23: iload_2
    //   24: invokespecial 386	kkkkkk/eeefee:b044D044Dээ044Dэээээ	(Lkkkkkk/xddxdd;Ljava/lang/String;JZ)Z
    //   27: istore_2
    //   28: aload_0
    //   29: aload_1
    //   30: iload_2
    //   31: invokespecial 1037	kkkkkk/eeefee:b0424Ф0424ФФ04240424042404240424	(Lkkkkkk/ffnfnn;Z)Lkkkkkk/xxxddd$dddxdd;
    //   34: astore 9
    //   36: aload 8
    //   38: ifnull +227 -> 265
    //   41: aload_1
    //   42: getfield 899	kkkkkk/ffnfnn:b043C043C043Cмм043C043C043Cм	Ljava/lang/String;
    //   45: aload 8
    //   47: invokevirtual 191	kkkkkk/nfnfnn:b044D044Dээ044Dэ044Dэ044Dэ	()Ljava/lang/String;
    //   50: invokevirtual 461	java/lang/String:equals	(Ljava/lang/Object;)Z
    //   53: ifeq +212 -> 265
    //   56: aload 8
    //   58: invokevirtual 209	kkkkkk/nfnfnn:b044Dээ044D044Dэ044Dэ044Dэ	()Lkkkkkk/dxdxdd;
    //   61: getstatic 1022	kkkkkk/dxdxdd:CLOSE	Lkkkkkk/dxdxdd;
    //   64: if_acmpeq +143 -> 207
    //   67: getstatic 145	kkkkkk/eeefee:bттт0442т0442т0442т	Ljava/lang/String;
    //   70: astore 10
    //   72: new 422	java/lang/StringBuilder
    //   75: dup
    //   76: invokespecial 423	java/lang/StringBuilder:<init>	()V
    //   79: astore 11
    //   81: aload 11
    //   83: ldc_w 1039
    //   86: bipush 19
    //   88: bipush 123
    //   90: iconst_3
    //   91: invokestatic 97	kkkkkk/gguuuu:bк043Aккк043Aкк043A043A	(Ljava/lang/String;CCC)Ljava/lang/String;
    //   94: invokevirtual 429	java/lang/StringBuilder:append	(Ljava/lang/String;)Ljava/lang/StringBuilder;
    //   97: aload_1
    //   98: getfield 899	kkkkkk/ffnfnn:b043C043C043Cмм043C043C043Cм	Ljava/lang/String;
    //   101: invokevirtual 429	java/lang/StringBuilder:append	(Ljava/lang/String;)Ljava/lang/StringBuilder;
    //   104: astore 11
    //   106: aload 10
    //   108: aload 11
    //   110: ldc_w 1041
    //   113: sipush 252
    //   116: iconst_3
    //   117: invokestatic 89	kkkkkk/gguuuu:bккккк043Aкк043A043A	(Ljava/lang/String;CC)Ljava/lang/String;
    //   120: invokevirtual 429	java/lang/StringBuilder:append	(Ljava/lang/String;)Ljava/lang/StringBuilder;
    //   123: aload_1
    //   124: getfield 1029	kkkkkk/ffnfnn:b043Cм043Cмм043C043C043Cм	Lkkkkkk/xddxdd;
    //   127: invokevirtual 432	java/lang/StringBuilder:append	(Ljava/lang/Object;)Ljava/lang/StringBuilder;
    //   130: ldc_w 1043
    //   133: sipush 203
    //   136: iconst_2
    //   137: invokestatic 89	kkkkkk/gguuuu:bккккк043Aкк043A043A	(Ljava/lang/String;CC)Ljava/lang/String;
    //   140: invokevirtual 429	java/lang/StringBuilder:append	(Ljava/lang/String;)Ljava/lang/StringBuilder;
    //   143: aload_1
    //   144: getfield 1035	kkkkkk/ffnfnn:bмм043C043Cм043C043C043Cм	J
    //   147: invokevirtual 654	java/lang/StringBuilder:append	(J)Ljava/lang/StringBuilder;
    //   150: invokevirtual 435	java/lang/StringBuilder:toString	()Ljava/lang/String;
    //   153: invokestatic 1046	kkkkkk/xtxtxt:bиии043804380438и0438ии	(Ljava/lang/String;Ljava/lang/String;)V
    //   156: aload 8
    //   158: getstatic 1022	kkkkkk/dxdxdd:CLOSE	Lkkkkkk/dxdxdd;
    //   161: invokevirtual 781	kkkkkk/nfnfnn:bэ044Dэ044Dэ044D044Dэ044Dэ	(Lkkkkkk/dxdxdd;)V
    //   164: aload 8
    //   166: invokevirtual 832	kkkkkk/nfnfnn:bэ044Dэ044D044Dэ044Dэ044Dэ	()Lkkkkkk/nfffnf;
    //   169: astore 10
    //   171: aload 10
    //   173: invokevirtual 1049	kkkkkk/nfffnf:b044Dэ044D044Dээ044Dээ044D	()V
    //   176: aload 8
    //   178: aload_1
    //   179: getfield 1029	kkkkkk/ffnfnn:b043Cм043Cмм043C043C043Cм	Lkkkkkk/xddxdd;
    //   182: invokevirtual 1053	kkkkkk/nfnfnn:bэ044Dэээ044D044Dэ044Dэ	(Lkkkkkk/xddxdd;)V
    //   185: aload 8
    //   187: aload_1
    //   188: getfield 1035	kkkkkk/ffnfnn:bмм043C043Cм043C043C043Cм	J
    //   191: invokevirtual 1056	kkkkkk/nfnfnn:b044D044Dэээ044D044Dэ044Dэ	(J)V
    //   194: aload_1
    //   195: getfield 902	kkkkkk/ffnfnn:b043C043Cммм043C043C043Cм	Ljava/lang/String;
    //   198: astore 10
    //   200: aload 8
    //   202: aload 10
    //   204: invokevirtual 905	kkkkkk/nfnfnn:bэээээ044D044Dэ044Dэ	(Ljava/lang/String;)V
    //   207: aload 8
    //   209: aload 9
    //   211: invokevirtual 876	kkkkkk/nfnfnn:bэээ044Dэ044D044Dэ044Dэ	(Lkkkkkk/xxxddd$dddxdd;)V
    //   214: getstatic 111	kkkkkk/eeefee:b0442т04420442т0442т0442т	I
    //   217: istore_3
    //   218: getstatic 113	kkkkkk/eeefee:b0442044204420442т0442т0442т	I
    //   221: istore 4
    //   223: getstatic 111	kkkkkk/eeefee:b0442т04420442т0442т0442т	I
    //   226: istore 5
    //   228: getstatic 115	kkkkkk/eeefee:bтттт04420442т0442т	I
    //   231: istore 6
    //   233: getstatic 117	kkkkkk/eeefee:bт044204420442т0442т0442т	I
    //   236: istore 7
    //   238: iload_3
    //   239: iload 4
    //   241: iadd
    //   242: iload 5
    //   244: imul
    //   245: iload 6
    //   247: irem
    //   248: iload 7
    //   250: if_icmpeq +15 -> 265
    //   253: invokestatic 121	kkkkkk/eeefee:b04240424ФФФ04240424042404240424	()I
    //   256: putstatic 111	kkkkkk/eeefee:b0442т04420442т0442т0442т	I
    //   259: invokestatic 121	kkkkkk/eeefee:b04240424ФФФ04240424042404240424	()I
    //   262: putstatic 117	kkkkkk/eeefee:bт044204420442т0442т0442т	I
    //   265: new 316	kkkkkk/xddxxx
    //   268: dup
    //   269: new 1058	kkkkkk/eeefee$12
    //   272: dup
    //   273: aload_0
    //   274: aload_1
    //   275: aload 9
    //   277: iload_2
    //   278: invokespecial 1061	kkkkkk/eeefee$12:<init>	(Lkkkkkk/eeefee;Lkkkkkk/ffnfnn;Lkkkkkk/xxxddd$dddxdd;Z)V
    //   281: invokespecial 324	kkkkkk/xddxxx:<init>	(Lkkkkkk/xddxxx$xdxxxx;)V
    //   284: astore_1
    //   285: getstatic 111	kkkkkk/eeefee:b0442т04420442т0442т0442т	I
    //   288: istore_3
    //   289: iload_3
    //   290: getstatic 113	kkkkkk/eeefee:b0442044204420442т0442т0442т	I
    //   293: iload_3
    //   294: iadd
    //   295: imul
    //   296: getstatic 115	kkkkkk/eeefee:bтттт04420442т0442т	I
    //   299: irem
    //   300: tableswitch	default:+20->320, 0:+31->331
    //   320: bipush 30
    //   322: putstatic 111	kkkkkk/eeefee:b0442т04420442т0442т0442т	I
    //   325: invokestatic 121	kkkkkk/eeefee:b04240424ФФФ04240424042404240424	()I
    //   328: putstatic 117	kkkkkk/eeefee:bт044204420442т0442т0442т	I
    //   331: iconst_0
    //   332: tableswitch	default:+24->356, 0:+51->383, 1:+-47->285
    //   356: iconst_0
    //   357: tableswitch	default:+23->380, 0:+26->383, 1:+-72->285
    //   380: goto -24 -> 356
    //   383: aload_1
    //   384: areturn
    //   385: astore_1
    //   386: aload_1
    //   387: athrow
    //   388: astore_1
    //   389: aload_1
    //   390: athrow
    // Local variable table:
    //   start	length	slot	name	signature
    //   0	391	0	this	eeefee
    //   0	391	1	paramFfnfnn	ffnfnn
    //   0	391	2	paramBoolean	boolean
    //   217	79	3	i	int
    //   221	21	4	j	int
    //   226	19	5	k	int
    //   231	17	6	m	int
    //   236	15	7	n	int
    //   8	200	8	localNfnfnn	nfnfnn
    //   34	242	9	localDddxdd	xxxddd.dddxdd
    //   70	133	10	localObject	Object
    //   79	30	11	localStringBuilder	StringBuilder
    // Exception table:
    //   from	to	target	type
    //   0	36	385	java/lang/Exception
    //   41	81	385	java/lang/Exception
    //   106	171	385	java/lang/Exception
    //   185	200	385	java/lang/Exception
    //   207	238	385	java/lang/Exception
    //   81	106	388	java/lang/Exception
    //   171	185	388	java/lang/Exception
    //   200	207	388	java/lang/Exception
    //   253	265	388	java/lang/Exception
    //   265	285	388	java/lang/Exception
  }
  
  public void bэ044Dэ044D044Dэээээ(String paramString, int paramInt)
  {
    switch (1)
    {
    case 0: 
    default: 
      for (;;)
      {
        switch (1)
        {
        }
      }
    }
    if ((b04240424ФФФ04240424042404240424() + b0442044204420442т0442т0442т) * b04240424ФФФ04240424042404240424() % bтттт04420442т0442т != bт044204420442т0442т0442т)
    {
      b0442т04420442т0442т0442т = 15;
      bт044204420442т0442т0442т = 56;
    }
    paramString = String.valueOf(b0424Ф0424Ф042404240424042404240424(paramString).b044D044Dээ044Dэ044Dэ044Dэ());
    if ((b0442т04420442т0442т0442т + b0442044204420442т0442т0442т) * b0442т04420442т0442т0442т % bФФФФФ04240424042404240424() != bт044204420442т0442т0442т)
    {
      b0442т04420442т0442т0442т = 19;
      bт044204420442т0442т0442т = b04240424ФФФ04240424042404240424();
    }
    b044D044Dэ044D044Dэээээ(paramString, paramInt);
  }
  
  public void bэ044Dэ044Dээээээ(String paramString)
  {
    switch (0)
    {
    case 1: 
    default: 
      for (;;)
      {
        switch (1)
        {
        }
      }
    }
    if ((b0442т04420442т0442т0442т + b0442044204420442т0442т0442т) * b0442т04420442т0442т0442т % bтттт04420442т0442т != bт044204420442т0442т0442т)
    {
      b0442т04420442т0442т0442т = b04240424ФФФ04240424042404240424();
      bт044204420442т0442т0442т = 33;
    }
    paramString = b0424Ф0424Ф042404240424042404240424(paramString);
    if (paramString != null)
    {
      paramString = paramString.bэ044Dэ044D044Dэ044Dэ044Dэ();
      if ((b0442т04420442т0442т0442т + b0442044204420442т0442т0442т) * b0442т04420442т0442т0442т % bтттт04420442т0442т != bт044204420442т0442т0442т)
      {
        b0442т04420442т0442т0442т = 30;
        bт044204420442т0442т0442т = 84;
      }
      paramString.bээ044Dэ044Dэ044Dээ044D();
    }
  }
  
  public void bэ044Dээ044Dэээээ(String paramString, int paramInt)
  {
    if ((b04240424ФФФ04240424042404240424() + b0442044204420442т0442т0442т) * b04240424ФФФ04240424042404240424() % bтттт04420442т0442т != bт044204420442т0442т0442т)
    {
      b0442т04420442т0442т0442т = b04240424ФФФ04240424042404240424();
      bт044204420442т0442т0442т = 45;
    }
    if ((b0442т04420442т0442т0442т + b0442044204420442т0442т0442т) * b0442т04420442т0442т0442т % bтттт04420442т0442т != bт044204420442т0442т0442т)
    {
      b0442т04420442т0442т0442т = b04240424ФФФ04240424042404240424();
      bт044204420442т0442т0442т = b04240424ФФФ04240424042404240424();
    }
    try
    {
      nfnfnn localNfnfnn = bФФФФ042404240424042404240424(paramString);
      String str;
      StringBuilder localStringBuilder;
      if (localNfnfnn != null)
      {
        str = bттт0442т0442т0442т;
        localStringBuilder = new StringBuilder().append(gguuuu.bккккк043Aкк043A043A("qsrvzr*~xkgyi#tfqtcpp\033cg\030ghd[eWdc\017T\\^\013MXV]KWWDVJOM\030|", 'ö', '\003'));
        break label169;
        localStringBuilder = localStringBuilder.append(paramString);
      }
      switch (0)
      {
      }
    }
    catch (Exception paramString)
    {
      try
      {
        xtxtxt.bии0438и04380438и0438ии(str, gguuuu.bк043Aккк043Aкк043A043A("A6\n}\013\020\001\020\022\022?\n\020B\024\027\025\016\032\016\035\036eL", '', '\013', '\003') + paramInt);
        localNfnfnn.bээ044D044Dэ044D044Dэ044Dэ(paramInt);
        paramString = new eeefee.19(this, paramString, paramInt);
        dxxxxx.bиии04380438и0438иии(paramString);
        return;
      }
      catch (Exception paramString)
      {
        throw paramString;
      }
      paramString = paramString;
      throw paramString;
    }
    for (;;)
    {
      label169:
      switch (0)
      {
      }
    }
  }
  
  /* Error */
  public void bэ044Dээээээээ(String paramString)
  {
    // Byte code:
    //   0: aload_0
    //   1: aload_1
    //   2: invokevirtual 301	kkkkkk/eeefee:b0424Ф0424Ф042404240424042404240424	(Ljava/lang/String;)Lkkkkkk/nfnfnn;
    //   5: astore_2
    //   6: aload_2
    //   7: ifnull +80 -> 87
    //   10: aload_2
    //   11: invokevirtual 209	kkkkkk/nfnfnn:b044Dээ044D044Dэ044Dэ044Dэ	()Lkkkkkk/dxdxdd;
    //   14: astore_3
    //   15: getstatic 777	kkkkkk/dxdxdd:PENDING	Lkkkkkk/dxdxdd;
    //   18: astore 4
    //   20: aload_3
    //   21: aload 4
    //   23: if_acmpeq +50 -> 73
    //   26: aload_2
    //   27: invokevirtual 209	kkkkkk/nfnfnn:b044Dээ044D044Dэ044Dэ044Dэ	()Lkkkkkk/dxdxdd;
    //   30: astore_3
    //   31: getstatic 1086	kkkkkk/dxdxdd:QUEUED	Lkkkkkk/dxdxdd;
    //   34: astore 4
    //   36: aload_3
    //   37: aload 4
    //   39: if_acmpne +48 -> 87
    //   42: getstatic 111	kkkkkk/eeefee:b0442т04420442т0442т0442т	I
    //   45: getstatic 113	kkkkkk/eeefee:b0442044204420442т0442т0442т	I
    //   48: iadd
    //   49: getstatic 111	kkkkkk/eeefee:b0442т04420442т0442т0442т	I
    //   52: imul
    //   53: getstatic 115	kkkkkk/eeefee:bтттт04420442т0442т	I
    //   56: irem
    //   57: getstatic 117	kkkkkk/eeefee:bт044204420442т0442т0442т	I
    //   60: if_icmpeq +13 -> 73
    //   63: bipush 9
    //   65: putstatic 111	kkkkkk/eeefee:b0442т04420442т0442т0442т	I
    //   68: bipush 30
    //   70: putstatic 117	kkkkkk/eeefee:bт044204420442т0442т0442т	I
    //   73: aload_2
    //   74: getstatic 1022	kkkkkk/dxdxdd:CLOSE	Lkkkkkk/dxdxdd;
    //   77: invokevirtual 781	kkkkkk/nfnfnn:bэ044Dэ044Dэ044D044Dэ044Dэ	(Lkkkkkk/dxdxdd;)V
    //   80: aload_2
    //   81: invokestatic 639	java/lang/System:currentTimeMillis	()J
    //   84: invokevirtual 1056	kkkkkk/nfnfnn:b044D044Dэээ044D044Dэ044Dэ	(J)V
    //   87: new 1088	kkkkkk/eeefee$23
    //   90: dup
    //   91: aload_0
    //   92: aload_1
    //   93: invokespecial 1089	kkkkkk/eeefee$23:<init>	(Lkkkkkk/eeefee;Ljava/lang/String;)V
    //   96: astore_1
    //   97: getstatic 111	kkkkkk/eeefee:b0442т04420442т0442т0442т	I
    //   100: getstatic 113	kkkkkk/eeefee:b0442044204420442т0442т0442т	I
    //   103: iadd
    //   104: getstatic 111	kkkkkk/eeefee:b0442т04420442т0442т0442т	I
    //   107: imul
    //   108: getstatic 115	kkkkkk/eeefee:bтттт04420442т0442т	I
    //   111: irem
    //   112: getstatic 117	kkkkkk/eeefee:bт044204420442т0442т0442т	I
    //   115: if_icmpeq +13 -> 128
    //   118: iconst_4
    //   119: putstatic 111	kkkkkk/eeefee:b0442т04420442т0442т0442т	I
    //   122: invokestatic 121	kkkkkk/eeefee:b04240424ФФФ04240424042404240424	()I
    //   125: putstatic 117	kkkkkk/eeefee:bт044204420442т0442т0442т	I
    //   128: aload_1
    //   129: invokestatic 401	kkkkkk/dxxxxx:bиии04380438и0438иии	(Ljava/lang/Runnable;)V
    //   132: return
    //   133: astore_1
    //   134: aload_1
    //   135: athrow
    //   136: astore_1
    //   137: aload_1
    //   138: athrow
    // Local variable table:
    //   start	length	slot	name	signature
    //   0	139	0	this	eeefee
    //   0	139	1	paramString	String
    //   5	76	2	localNfnfnn	nfnfnn
    //   14	23	3	localDxdxdd1	dxdxdd
    //   18	20	4	localDxdxdd2	dxdxdd
    // Exception table:
    //   from	to	target	type
    //   0	6	133	java/lang/Exception
    //   26	36	133	java/lang/Exception
    //   73	87	133	java/lang/Exception
    //   87	97	133	java/lang/Exception
    //   10	20	136	java/lang/Exception
    //   128	132	136	java/lang/Exception
  }
  
  /* Error */
  public xddxxx<Boolean> bээ044D044D044Dэээээ(String paramString, int paramInt1, int paramInt2, boolean paramBoolean)
  {
    // Byte code:
    //   0: aload_0
    //   1: aload_1
    //   2: invokevirtual 850	kkkkkk/eeefee:bФФ0424Ф042404240424042404240424	(Ljava/lang/String;)Lkkkkkk/nfnfnn;
    //   5: astore 10
    //   7: aload 10
    //   9: ifnull +159 -> 168
    //   12: aload 10
    //   14: invokevirtual 304	kkkkkk/nfnfnn:b044Dэ044Dэ044Dэ044Dэ044Dэ	()I
    //   17: i2l
    //   18: lstore 8
    //   20: iload_3
    //   21: i2l
    //   22: lload 8
    //   24: ladd
    //   25: iload_2
    //   26: i2l
    //   27: lcmp
    //   28: ifne +152 -> 180
    //   31: aload 10
    //   33: iload_2
    //   34: invokevirtual 550	kkkkkk/nfnfnn:b044Dэ044Dээ044D044Dэ044Dэ	(I)V
    //   37: getstatic 145	kkkkkk/eeefee:bттт0442т0442т0442т	Ljava/lang/String;
    //   40: new 422	java/lang/StringBuilder
    //   43: dup
    //   44: invokespecial 423	java/lang/StringBuilder:<init>	()V
    //   47: ldc_w 1091
    //   50: sipush 133
    //   53: iconst_0
    //   54: invokestatic 89	kkkkkk/gguuuu:bккккк043Aкк043A043A	(Ljava/lang/String;CC)Ljava/lang/String;
    //   57: invokevirtual 429	java/lang/StringBuilder:append	(Ljava/lang/String;)Ljava/lang/StringBuilder;
    //   60: lload 8
    //   62: invokevirtual 654	java/lang/StringBuilder:append	(J)Ljava/lang/StringBuilder;
    //   65: ldc_w 1093
    //   68: bipush 67
    //   70: sipush 162
    //   73: iconst_2
    //   74: invokestatic 97	kkkkkk/gguuuu:bк043Aккк043Aкк043A043A	(Ljava/lang/String;CCC)Ljava/lang/String;
    //   77: invokevirtual 429	java/lang/StringBuilder:append	(Ljava/lang/String;)Ljava/lang/StringBuilder;
    //   80: iload_3
    //   81: invokevirtual 508	java/lang/StringBuilder:append	(I)Ljava/lang/StringBuilder;
    //   84: ldc_w 1095
    //   87: bipush 48
    //   89: sipush 252
    //   92: iconst_0
    //   93: invokestatic 97	kkkkkk/gguuuu:bк043Aккк043Aкк043A043A	(Ljava/lang/String;CCC)Ljava/lang/String;
    //   96: invokevirtual 429	java/lang/StringBuilder:append	(Ljava/lang/String;)Ljava/lang/StringBuilder;
    //   99: iload_2
    //   100: invokevirtual 508	java/lang/StringBuilder:append	(I)Ljava/lang/StringBuilder;
    //   103: invokevirtual 435	java/lang/StringBuilder:toString	()Ljava/lang/String;
    //   106: invokestatic 440	kkkkkk/xtxtxt:bии0438и04380438и0438ии	(Ljava/lang/String;Ljava/lang/String;)V
    //   109: getstatic 111	kkkkkk/eeefee:b0442т04420442т0442т0442т	I
    //   112: istore 5
    //   114: getstatic 113	kkkkkk/eeefee:b0442044204420442т0442т0442т	I
    //   117: istore 6
    //   119: getstatic 115	kkkkkk/eeefee:bтттт04420442т0442т	I
    //   122: istore 7
    //   124: iload 5
    //   126: iload 6
    //   128: iload 5
    //   130: iadd
    //   131: imul
    //   132: iload 7
    //   134: irem
    //   135: tableswitch	default:+17->152, 0:+28->163
    //   152: bipush 56
    //   154: putstatic 111	kkkkkk/eeefee:b0442т04420442т0442т0442т	I
    //   157: invokestatic 121	kkkkkk/eeefee:b04240424ФФФ04240424042404240424	()I
    //   160: putstatic 117	kkkkkk/eeefee:bт044204420442т0442т0442т	I
    //   163: aload_0
    //   164: iload_2
    //   165: invokespecial 1097	kkkkkk/eeefee:bэээ044Dээээээ	(I)V
    //   168: aload_0
    //   169: aload_1
    //   170: iload_2
    //   171: iload_3
    //   172: iload 4
    //   174: aload 10
    //   176: invokespecial 1099	kkkkkk/eeefee:b04240424Ф0424042404240424042404240424	(Ljava/lang/String;IIZLkkkkkk/nfnfnn;)Lkkkkkk/xddxxx;
    //   179: areturn
    //   180: getstatic 145	kkkkkk/eeefee:bттт0442т0442т0442т	Ljava/lang/String;
    //   183: astore_1
    //   184: new 422	java/lang/StringBuilder
    //   187: dup
    //   188: invokespecial 423	java/lang/StringBuilder:<init>	()V
    //   191: astore 10
    //   193: aload_1
    //   194: aload 10
    //   196: ldc_w 1101
    //   199: sipush 135
    //   202: bipush 65
    //   204: iconst_0
    //   205: invokestatic 97	kkkkkk/gguuuu:bк043Aккк043Aкк043A043A	(Ljava/lang/String;CCC)Ljava/lang/String;
    //   208: invokevirtual 429	java/lang/StringBuilder:append	(Ljava/lang/String;)Ljava/lang/StringBuilder;
    //   211: lload 8
    //   213: invokevirtual 654	java/lang/StringBuilder:append	(J)Ljava/lang/StringBuilder;
    //   216: ldc_w 1103
    //   219: bipush 112
    //   221: bipush 41
    //   223: iconst_1
    //   224: invokestatic 97	kkkkkk/gguuuu:bк043Aккк043Aкк043A043A	(Ljava/lang/String;CCC)Ljava/lang/String;
    //   227: invokevirtual 429	java/lang/StringBuilder:append	(Ljava/lang/String;)Ljava/lang/StringBuilder;
    //   230: iload_3
    //   231: invokevirtual 508	java/lang/StringBuilder:append	(I)Ljava/lang/StringBuilder;
    //   234: ldc_w 1105
    //   237: bipush 78
    //   239: sipush 194
    //   242: iconst_1
    //   243: invokestatic 97	kkkkkk/gguuuu:bк043Aккк043Aкк043A043A	(Ljava/lang/String;CCC)Ljava/lang/String;
    //   246: invokevirtual 429	java/lang/StringBuilder:append	(Ljava/lang/String;)Ljava/lang/StringBuilder;
    //   249: iload_2
    //   250: invokevirtual 508	java/lang/StringBuilder:append	(I)Ljava/lang/StringBuilder;
    //   253: invokevirtual 435	java/lang/StringBuilder:toString	()Ljava/lang/String;
    //   256: invokestatic 440	kkkkkk/xtxtxt:bии0438и04380438и0438ии	(Ljava/lang/String;Ljava/lang/String;)V
    //   259: getstatic 111	kkkkkk/eeefee:b0442т04420442т0442т0442т	I
    //   262: istore_2
    //   263: iload_2
    //   264: getstatic 113	kkkkkk/eeefee:b0442044204420442т0442т0442т	I
    //   267: iload_2
    //   268: iadd
    //   269: imul
    //   270: getstatic 115	kkkkkk/eeefee:bтттт04420442т0442т	I
    //   273: irem
    //   274: tableswitch	default:+18->292, 0:+28->302
    //   292: bipush 82
    //   294: putstatic 111	kkkkkk/eeefee:b0442т04420442т0442т0442т	I
    //   297: bipush 37
    //   299: putstatic 117	kkkkkk/eeefee:bт044204420442т0442т0442т	I
    //   302: aconst_null
    //   303: areturn
    //   304: astore_1
    //   305: aload_1
    //   306: athrow
    //   307: astore_1
    //   308: aload_1
    //   309: athrow
    //   310: astore_1
    //   311: aload_1
    //   312: athrow
    //   313: astore_1
    //   314: aload_1
    //   315: athrow
    // Local variable table:
    //   start	length	slot	name	signature
    //   0	316	0	this	eeefee
    //   0	316	1	paramString	String
    //   0	316	2	paramInt1	int
    //   0	316	3	paramInt2	int
    //   0	316	4	paramBoolean	boolean
    //   112	20	5	i	int
    //   117	14	6	j	int
    //   122	13	7	k	int
    //   18	194	8	l	long
    //   5	190	10	localObject	Object
    // Exception table:
    //   from	to	target	type
    //   0	7	304	java/lang/Exception
    //   37	109	304	java/lang/Exception
    //   163	168	304	java/lang/Exception
    //   168	180	304	java/lang/Exception
    //   180	193	304	java/lang/Exception
    //   152	163	307	java/lang/Exception
    //   305	307	307	java/lang/Exception
    //   311	313	307	java/lang/Exception
    //   12	20	310	java/lang/Exception
    //   31	37	310	java/lang/Exception
    //   193	259	310	java/lang/Exception
    //   109	124	313	java/lang/Exception
  }
  
  public void bээ044D044Dээээээ(@Nullable String paramString, @NotNull ArrayList<gggjjg> paramArrayList, boolean paramBoolean, @NotNull dddxxd<nfnfnn, Exception> paramDddxxd)
  {
    nfnfnn localNfnfnn = bФФ0424Ф042404240424042404240424(paramString);
    if (localNfnfnn == null)
    {
      paramString = bФ0424ФФ042404240424042404240424(paramString);
      paramArrayList = new eeefee.25(this, paramArrayList, paramBoolean, paramDddxxd);
      switch (1)
      {
      case 0: 
      default: 
        for (;;)
        {
          switch (1)
          {
          }
        }
      }
      paramString = paramString.b04380438и0438ии0438иии(paramArrayList);
      switch (1)
      {
      case 0: 
      default: 
        for (;;)
        {
          if ((b04240424ФФФ04240424042404240424() + bФ0424ФФФ04240424042404240424()) * b04240424ФФФ04240424042404240424() % bтттт04420442т0442т != bт044204420442т0442т0442т)
          {
            b0442т04420442т0442т0442т = b04240424ФФФ04240424042404240424();
            bт044204420442т0442т0442т = b04240424ФФФ04240424042404240424();
          }
          switch (0)
          {
          }
        }
      }
      if ((b0442т04420442т0442т0442т + b0442044204420442т0442т0442т) * b0442т04420442т0442т0442т % bтттт04420442т0442т != b0424ФФФФ04240424042404240424())
      {
        b0442т04420442т0442т0442т = b04240424ФФФ04240424042404240424();
        bт044204420442т0442т0442т = b04240424ФФФ04240424042404240424();
      }
      paramString.b0438ии0438ии0438иии();
      return;
    }
    b044D044Dэ044Dээээээ(localNfnfnn, paramArrayList, paramBoolean, paramDddxxd);
  }
  
  public void bээ044Dэ044Dэээээ(String paramString)
  {
    nfnfnn localNfnfnn = b0424Ф0424Ф042404240424042404240424(paramString);
    int i = b04240424ФФФ04240424042404240424();
    switch (i * (b0442044204420442т0442т0442т + i) % bтттт04420442т0442т)
    {
    default: 
      b0442т04420442т0442т0442т = b04240424ФФФ04240424042404240424();
      bт044204420442т0442т0442т = 8;
    }
    if (localNfnfnn != null)
    {
      switch (1)
      {
      case 0: 
      default: 
        for (;;)
        {
          switch (0)
          {
          }
        }
      }
      i = b0442т04420442т0442т0442т;
      switch (i * (b0442044204420442т0442т0442т + i) % bтттт04420442т0442т)
      {
      default: 
        b0442т04420442т0442т0442т = b04240424ФФФ04240424042404240424();
        bт044204420442т0442т0442т = 45;
      }
      localNfnfnn.bэ044Dэ044D044Dэ044Dэ044Dэ().bэ044D044Dэ044Dэ044Dээ044D(paramString);
    }
  }
  
  public void bээ044Dэээээээ(String paramString)
  {
    nfnfnn localNfnfnn = b04240424ФФ042404240424042404240424(paramString);
    if (localNfnfnn != null)
    {
      int i = b0442т04420442т0442т0442т;
      switch (i * (b0442044204420442т0442т0442т + i) % bтттт04420442т0442т)
      {
      default: 
        b0442т04420442т0442т0442т = b04240424ФФФ04240424042404240424();
        bт044204420442т0442т0442т = 82;
      }
      localNfnfnn.bэ044Dэ044D044Dэ044Dэ044Dэ().b044D044D044Dэ044Dэ044Dээ044D(paramString);
    }
  }
  
  public void bэээ044D044Dэээээ(ffnfnn paramFfnfnn)
  {
    try
    {
      nfnfnn localNfnfnn = b0424Ф0424Ф042404240424042404240424(paramFfnfnn.b043C043Cмм043C043C043C043Cм);
      ContentValues localContentValues = new ContentValues();
      int i;
      Object localObject1;
      Object localObject2;
      if (localNfnfnn.b044Dээ044D044Dэ044Dэ044Dэ() != paramFfnfnn.bм043Cмм043C043C043C043Cм)
      {
        localNfnfnn.bэ044Dэ044Dэ044D044Dэ044Dэ(paramFfnfnn.bм043Cмм043C043C043C043Cм);
        if (paramFfnfnn.bм043Cмм043C043C043C043Cм != null)
        {
          i = paramFfnfnn.bм043Cмм043C043C043C043Cм.ordinal();
          localContentValues.put(gguuuu.bккккк043Aкк043A043A(">@.B4", '%', '\004'), Integer.valueOf(i));
        }
      }
      else
      {
        localObject1 = localNfnfnn.bээ044Dэ044Dэ044Dэ044Dэ();
        localObject2 = paramFfnfnn.bммм043Cм043C043C043Cм;
        if ((b0442т04420442т0442т0442т + b0442044204420442т0442т0442т) * b0442т04420442т0442т0442т % bтттт04420442т0442т != bт044204420442т0442т0442т)
        {
          b0442т04420442т0442т0442т = b04240424ФФФ04240424042404240424();
          bт044204420442т0442т0442т = b04240424ФФФ04240424042404240424();
        }
        if (localObject1 != localObject2)
        {
          localNfnfnn.bээ044Dээ044D044Dэ044Dэ(paramFfnfnn.bммм043Cм043C043C043Cм);
          localObject1 = eeefee.27.b0442тт044204420442тт0442;
          i = paramFfnfnn.bммм043Cм043C043C043Cм.ordinal();
          switch (localObject1[i])
          {
          }
        }
      }
      for (;;)
      {
        try
        {
          localObject1 = gguuuu.bккккк043Aкк043A043A("-.-\03317/%", '', '\004');
          i = paramFfnfnn.bммм043Cм043C043C043Cм.ordinal();
          localContentValues.put((String)localObject1, Integer.valueOf(i));
          if (localNfnfnn.b044D044D044Dэ044Dэ044Dэ044Dэ() != paramFfnfnn.b043C043C043C043Cм043C043C043Cм)
          {
            localNfnfnn.bэ044D044Dээ044D044Dэ044Dэ(paramFfnfnn.b043C043C043C043Cм043C043C043Cм);
            localContentValues.put(gguuuu.bккккк043Aкк043A043A("|p}\003s\003\005p{w", '', '\004'), Long.valueOf(paramFfnfnn.b043C043C043C043Cм043C043C043Cм));
          }
          boolean bool = TextUtils.equals(localNfnfnn.b044D044Dээ044Dэ044Dэ044Dэ(), localNfnfnn.b044D044Dээ044Dэ044Dэ044Dэ());
          if (!bool)
          {
            localNfnfnn.b044D044D044Dээ044D044Dэ044Dэ(paramFfnfnn.b043C043C043Cмм043C043C043Cм);
            switch (1)
            {
            case 0: 
            default: 
              switch (1)
              {
              }
              break;
            }
            localContentValues.put(gguuuu.bк043Aккк043Aкк043A043A("0==F6DF5I?FF\">", '©', 'Ü', '\001'), paramFfnfnn.b043C043C043Cмм043C043C043Cм);
          }
          if (!TextUtils.equals(localNfnfnn.b044D044D044D044Dээ044Dэ044Dэ(), paramFfnfnn.b043C043Cммм043C043C043Cм))
          {
            localNfnfnn.bэээээ044D044Dэ044Dэ(paramFfnfnn.b043C043Cммм043C043C043Cм);
            localObject1 = gguuuu.bккккк043Aкк043A043A("EXYPOWOO-TS]d:V", '!', '\001');
            localObject2 = paramFfnfnn.b043C043Cммм043C043C043Cм;
            localContentValues.put((String)localObject1, (String)localObject2);
          }
          if (localNfnfnn.bээ044D044D044Dэ044Dэ044Dэ() != paramFfnfnn.b043Cм043Cм043C043C043C043Cм)
          {
            localNfnfnn.b044D044Dэ044Dэ044D044Dэ044Dэ(paramFfnfnn.b043Cм043Cм043C043C043C043Cм);
            localContentValues.put(gguuuu.bк043Aккк043Aкк043A043A("+%*\036\033\037\033*1&", '\006', '®', '\003'), Integer.valueOf(paramFfnfnn.b043Cм043Cм043C043C043C043Cм));
            bээээ044Dэээээ(localNfnfnn);
          }
          if (localNfnfnn.bэээ044D044Dэ044Dэ044Dэ() != paramFfnfnn.b043Cммм043C043C043C043Cм)
          {
            localNfnfnn.b044Dээ044Dэ044D044Dэ044Dэ(paramFfnfnn.b043Cммм043C043C043C043Cм);
            localContentValues.put(gguuuu.bк043Aккк043Aкк043A043A("`bPbeQg]b[", '>', 'Ð', '\001'), Long.valueOf(paramFfnfnn.b043Cммм043C043C043C043Cм));
          }
          if (localContentValues.size() > 0) {
            dxxxxx.bиии04380438и0438иии(new eeefee.4(this, localContentValues, paramFfnfnn, localNfnfnn));
          }
          return;
        }
        catch (Exception paramFfnfnn)
        {
          throw paramFfnfnn;
        }
        this.bт0442т0442т0442т0442т.b044C044Cььь044Cь044Cь.onConversationMarkedAsNormal();
        continue;
        i = -1;
        break;
        this.bт0442т0442т0442т0442т.b044C044Cььь044Cь044Cь.onConversationMarkedAsUrgent();
        if ((b0442т04420442т0442т0442т + b0442044204420442т0442т0442т) * b0442т04420442т0442т0442т % bтттт04420442т0442т != bт044204420442т0442т0442т)
        {
          b0442т04420442т0442т0442т = 30;
          bт044204420442т0442т0442т = b04240424ФФФ04240424042404240424();
        }
      }
    }
    catch (Exception paramFfnfnn)
    {
      throw paramFfnfnn;
    }
  }
  
  public void bэээээ044Dээээ(String paramString, xdxxdd paramXdxxdd, long paramLong1, long paramLong2, long paramLong3)
  {
    nfnfnn localNfnfnn = b0424Ф0424Ф042404240424042404240424(paramString);
    if (localNfnfnn != null)
    {
      localNfnfnn.bэ044Dэ044D044Dэ044Dэ044Dэ().bэээ044D044Dэ044Dээ044D(paramString, paramLong1, paramLong2, paramLong3);
      if (paramXdxxdd != localNfnfnn.bээ044Dэ044Dэ044Dэ044Dэ())
      {
        switch (0)
        {
        case 1: 
        default: 
          for (;;)
          {
            switch (1)
            {
            }
          }
        }
        localNfnfnn.bээ044Dээ044D044Dэ044Dэ(paramXdxxdd);
        dxxxxx.bиии04380438и0438иии(new eeefee.14(this, paramXdxxdd, localNfnfnn));
      }
    }
  }
}
