package kkkkkk;

import com.fasterxml.jackson.annotation.JsonValue;

public enum eieiei
{
  private final String mJsonName;
  
  static
  {
    try
    {
      HOME_PAGE = new eieiei(gguuuu.bккккк043Aкк043A043A("ekh_xhX]Z", '1', '\003'), 0, gguuuu.bк043Aккк043Aкк043A043A("vngUVQRR", '²', 'Ú', '\000'));
      ACCOUNT_OVERVIEW = new eieiei(gguuuu.bккккк043Aкк043A043A("uvu\001\006}\003\r{\002o{~pk|", 'ä', '\003'), 1, gguuuu.bккккк043Aкк043A043A("^XSCHCFHEIK", '\b', '\004'));
      localEieiei = new eieiei(gguuuu.bккккк043Aкк043A043A("Y[I]OXQ[bn`RYX", '', '\001'), 2, gguuuu.bккккк043Aкк043A043A("zrkY`UVV\006", 'F', '\002'));
      if ((bфф04440444фф0444ффф() + b04440444ф0444фф0444ффф()) * bфф04440444фф0444ффф() % bф044404440444фф0444ффф() == b0444ф04440444фф0444ффф()) {}
    }
    catch (Exception localException1)
    {
      eieiei localEieiei;
      int i;
      throw localException1;
    }
    try
    {
      STATEMENT_PAGE = localEieiei;
      TRANSFER_UNAVAILABLE = new eieiei(gguuuu.bккккк043Aкк043A043A("wtbnrdbnzogYmW^`TT]U", 'Û', '\005'), 3, gguuuu.bк043Aккк043Aкк043A043A("\002yr`h\\]]\022WYY", 'þ', 'Ë', '\002'));
      TRANSFER_SUCCESS = new eieiei(gguuuu.bккккк043Aкк043A043A("\r\f{\n\020\004\004\022 \025\030\007\b\013\032\033", '=', '\001'), 4, gguuuu.bккккк043Aкк043A043A("(\"\035\r\027\r\020\030\017\023\025", 'Ø', '\000'));
      PAYMENT_UNAVAILABLE = new eieiei(gguuuu.bккккк043Aкк043A043A("9+D92<COF@4J6?C9;F@", 'M', '\001'), 5, gguuuu.bккккк043Aкк043A043A("\017\007nlijj\037dff", '_', '\003'));
      PAYMENT_SUCCESS = new eieiei(gguuuu.bккккк043Aкк043A043A("8*C81;BNCF569HI", 'æ', '\000'), 6, gguuuu.bккккк043Aкк043A043A("`ZUFFEHQGKM", '\022', '\000'));
      localEieiei = new eieiei(gguuuu.bк043Aккк043Aкк043A043A("5;8O?@<9;>", 'ì', '`', '\000'), 7, gguuuu.bк043Aккк043Aкк043A043A("\003zseb]^c", '\027', '4', '\002'));
    }
    catch (Exception localException2)
    {
      throw localException2;
    }
    BIG_PROMPT = localEieiei;
    localEieiei = new eieiei(gguuuu.bккккк043Aкк043A043A("DLKdVYWVZ_kaOZU`hXf", '\001', '\004'), 8, gguuuu.bккккк043Aкк043A043A("\021\t\002spklqZfX\031\033%%(\030\026P\034\024\017\021", 'Ý', '\003'));
    BIG_PROMPT_TAKEOVER = localEieiei;
    localEieiei = new eieiei(gguuuu.bккккк043Aкк043A043A("\036)&", '&', '\005'), 9, gguuuu.bккккк043Aкк043A043A("<61!%A\"*", 'ø', '\001'));
    i = bфф04440444фф0444ффф();
    switch (i * (b04440444ф0444фф0444ффф() + i) % bф044404440444фф0444ффф())
    {
    }
    DPN = localEieiei;
    $VALUES = new eieiei[] { HOME_PAGE, ACCOUNT_OVERVIEW, STATEMENT_PAGE, TRANSFER_UNAVAILABLE, TRANSFER_SUCCESS, PAYMENT_UNAVAILABLE, PAYMENT_SUCCESS, BIG_PROMPT, BIG_PROMPT_TAKEOVER, DPN };
    return;
    switch (0)
    {
    }
    for (;;)
    {
      switch (1)
      {
      }
    }
  }
  
  private eieiei(String paramString)
  {
    this.mJsonName = paramString;
  }
  
  /* Error */
  public static eieiei b0444044404440444фф0444ффф(String paramString)
  {
    // Byte code:
    //   0: invokestatic 58	kkkkkk/eieiei:bфф04440444фф0444ффф	()I
    //   3: istore_1
    //   4: invokestatic 61	kkkkkk/eieiei:b04440444ф0444фф0444ффф	()I
    //   7: istore_2
    //   8: invokestatic 64	kkkkkk/eieiei:bф044404440444фф0444ффф	()I
    //   11: istore_3
    //   12: iload_1
    //   13: iload_2
    //   14: iload_1
    //   15: iadd
    //   16: imul
    //   17: iload_3
    //   18: irem
    //   19: tableswitch	default:+17->36, 0:+17->36
    //   36: ldc 2
    //   38: aload_0
    //   39: invokestatic 127	java/lang/Enum:valueOf	(Ljava/lang/Class;Ljava/lang/String;)Ljava/lang/Enum;
    //   42: astore_0
    //   43: invokestatic 58	kkkkkk/eieiei:bфф04440444фф0444ффф	()I
    //   46: istore_1
    //   47: iload_1
    //   48: invokestatic 61	kkkkkk/eieiei:b04440444ф0444фф0444ффф	()I
    //   51: iload_1
    //   52: iadd
    //   53: imul
    //   54: invokestatic 64	kkkkkk/eieiei:bф044404440444фф0444ффф	()I
    //   57: irem
    //   58: tableswitch	default:+18->76, 0:+18->76
    //   76: aload_0
    //   77: checkcast 2	kkkkkk/eieiei
    //   80: astore_0
    //   81: aload_0
    //   82: areturn
    //   83: astore_0
    //   84: aload_0
    //   85: athrow
    //   86: astore_0
    //   87: aload_0
    //   88: athrow
    //   89: astore_0
    //   90: aload_0
    //   91: athrow
    //   92: astore_0
    //   93: aload_0
    //   94: athrow
    // Local variable table:
    //   start	length	slot	name	signature
    //   0	95	0	paramString	String
    //   3	51	1	i	int
    //   7	9	2	j	int
    //   11	8	3	k	int
    // Exception table:
    //   from	to	target	type
    //   36	43	83	java/lang/Exception
    //   0	12	86	java/lang/Exception
    //   84	86	86	java/lang/Exception
    //   76	81	89	java/lang/Exception
    //   90	92	92	java/lang/Exception
  }
  
  public static int b04440444ф0444фф0444ффф()
  {
    return 1;
  }
  
  public static int b0444ф04440444фф0444ффф()
  {
    return 0;
  }
  
  public static int bф044404440444фф0444ффф()
  {
    return 2;
  }
  
  public static int bфф04440444фф0444ффф()
  {
    return 22;
  }
  
  @JsonValue
  public String toString()
  {
    switch (1)
    {
    case 0: 
    default: 
      for (;;)
      {
        switch (1)
        {
        }
      }
    }
    int i = bфф04440444фф0444ффф();
    int j = b04440444ф0444фф0444ффф();
    int k = bф044404440444фф0444ффф();
    int m = bфф04440444фф0444ффф();
    switch (m * (b04440444ф0444фф0444ффф() + m) % bф044404440444фф0444ффф())
    {
    }
    switch (i * (j + i) % k)
    {
    }
    return this.mJsonName;
  }
}
