package kkkkkk;

import android.os.CountDownTimer;
import android.support.annotation.Nullable;
import android.support.annotation.VisibleForTesting;
import io.reactivex.Completable;
import io.reactivex.Single;
import io.reactivex.disposables.CompositeDisposable;
import io.reactivex.disposables.Disposable;
import io.reactivex.functions.Action;
import io.reactivex.functions.Consumer;
import javax.inject.Inject;
import javax.inject.Singleton;

@Singleton
public class eiieie
{
  public static final long b044604460446044604460446ццц;
  public static int b04460446ц0446цц0446цц = 0;
  public static final long b0446ц0446044604460446ццц;
  public static int b0446ц04460446цц0446цц = 2;
  public static final long bц04460446044604460446ццц;
  public static int bц0446ц0446цц0446цц = 98;
  public static int bцц04460446цц0446цц = 1;
  private eieiee b044604460446ццц0446цц = eieiee.USER_INITIATED_LOG_OFF;
  private final xvvvxx b04460446цццц0446цц;
  private final ieiiee b0446ц0446ццц0446цц;
  private eiiiee b0446цц0446цц0446цц;
  private final CompositeDisposable b0446ццццц0446цц = new CompositeDisposable();
  private boolean bц04460446ццц0446цц;
  @Nullable
  private CountDownTimer bц0446цццц0446цц;
  private boolean bцц0446ццц0446цц;
  private final ffbfbb bццц0446цц0446цц;
  private boolean bцццццц0446цц;
  
  /* Error */
  static
  {
    // Byte code:
    //   0: getstatic 47	java/util/concurrent/TimeUnit:SECONDS	Ljava/util/concurrent/TimeUnit;
    //   3: astore 5
    //   5: aload 5
    //   7: lconst_1
    //   8: invokevirtual 51	java/util/concurrent/TimeUnit:toMillis	(J)J
    //   11: putstatic 53	kkkkkk/eiieie:bц04460446044604460446ццц	J
    //   14: getstatic 47	java/util/concurrent/TimeUnit:SECONDS	Ljava/util/concurrent/TimeUnit;
    //   17: astore 5
    //   19: getstatic 55	kkkkkk/eiieie:bц0446ц0446цц0446цц	I
    //   22: istore_0
    //   23: getstatic 57	kkkkkk/eiieie:bцц04460446цц0446цц	I
    //   26: istore_1
    //   27: getstatic 55	kkkkkk/eiieie:bц0446ц0446цц0446цц	I
    //   30: istore_2
    //   31: getstatic 59	kkkkkk/eiieie:b0446ц04460446цц0446цц	I
    //   34: istore_3
    //   35: getstatic 61	kkkkkk/eiieie:b04460446ц0446цц0446цц	I
    //   38: istore 4
    //   40: iload_0
    //   41: iload_1
    //   42: iadd
    //   43: iload_2
    //   44: imul
    //   45: iload_3
    //   46: irem
    //   47: iload 4
    //   49: if_icmpeq +47 -> 96
    //   52: bipush 10
    //   54: putstatic 55	kkkkkk/eiieie:bц0446ц0446цц0446цц	I
    //   57: invokestatic 65	kkkkkk/eiieie:bф0444ф0444ф044404440444фф	()I
    //   60: putstatic 61	kkkkkk/eiieie:b04460446ц0446цц0446цц	I
    //   63: getstatic 55	kkkkkk/eiieie:bц0446ц0446цц0446цц	I
    //   66: getstatic 57	kkkkkk/eiieie:bцц04460446цц0446цц	I
    //   69: iadd
    //   70: getstatic 55	kkkkkk/eiieie:bц0446ц0446цц0446цц	I
    //   73: imul
    //   74: getstatic 59	kkkkkk/eiieie:b0446ц04460446цц0446цц	I
    //   77: irem
    //   78: getstatic 61	kkkkkk/eiieie:b04460446ц0446цц0446цц	I
    //   81: if_icmpeq +15 -> 96
    //   84: invokestatic 65	kkkkkk/eiieie:bф0444ф0444ф044404440444фф	()I
    //   87: putstatic 55	kkkkkk/eiieie:bц0446ц0446цц0446цц	I
    //   90: invokestatic 65	kkkkkk/eiieie:bф0444ф0444ф044404440444фф	()I
    //   93: putstatic 61	kkkkkk/eiieie:b04460446ц0446цц0446цц	I
    //   96: aload 5
    //   98: ldc2_w 66
    //   101: invokevirtual 51	java/util/concurrent/TimeUnit:toMillis	(J)J
    //   104: putstatic 69	kkkkkk/eiieie:b0446ц0446044604460446ццц	J
    //   107: getstatic 72	java/util/concurrent/TimeUnit:MINUTES	Ljava/util/concurrent/TimeUnit;
    //   110: ldc2_w 73
    //   113: invokevirtual 51	java/util/concurrent/TimeUnit:toMillis	(J)J
    //   116: putstatic 76	kkkkkk/eiieie:b044604460446044604460446ццц	J
    //   119: iconst_0
    //   120: tableswitch	default:+24->144, 0:+51->171, 1:+-1->119
    //   144: iconst_0
    //   145: tableswitch	default:+23->168, 0:+26->171, 1:+-26->119
    //   168: goto -24 -> 144
    //   171: return
    //   172: astore 5
    //   174: aload 5
    //   176: athrow
    //   177: astore 5
    //   179: aload 5
    //   181: athrow
    // Local variable table:
    //   start	length	slot	name	signature
    //   22	21	0	i	int
    //   26	17	1	j	int
    //   30	15	2	k	int
    //   34	13	3	m	int
    //   38	12	4	n	int
    //   3	94	5	localTimeUnit	java.util.concurrent.TimeUnit
    //   172	3	5	localException1	Exception
    //   177	3	5	localException2	Exception
    // Exception table:
    //   from	to	target	type
    //   0	5	172	java/lang/Exception
    //   31	40	172	java/lang/Exception
    //   96	119	172	java/lang/Exception
    //   5	31	177	java/lang/Exception
    //   52	63	177	java/lang/Exception
  }
  
  @Inject
  public eiieie(ieiiee paramIeiiee, xvvvxx paramXvvvxx, ffbfbb paramFfbfbb)
  {
    this.b0446ц0446ццц0446цц = paramIeiiee;
    this.b04460446цццц0446цц = paramXvvvxx;
    this.bццц0446цц0446цц = paramFfbfbb;
  }
  
  public static int b04440444ф0444ф044404440444фф()
  {
    return 2;
  }
  
  @ooiiio("TODO: MOB3-6414 - Proper separation and tests")
  private void b04440444фф0444044404440444фф()
  {
    for (;;)
    {
      try
      {
        localObject1 = this.b0446ц0446ццц0446цц;
        i = bц0446ц0446цц0446цц;
        j = bцц04460446цц0446цц;
      }
      catch (Exception localException1)
      {
        Object localObject1;
        int i;
        int j;
        int k;
        int m;
        int n;
        Object localObject2;
        eiieie.5 local5;
        throw localException1;
      }
      try
      {
        k = bц0446ц0446цц0446цц;
        m = b0446ц04460446цц0446цц;
        n = b04460446ц0446цц0446цц;
        if ((i + j) * k % m != n)
        {
          bц0446ц0446цц0446цц = 2;
          b04460446ц0446цц0446цц = 7;
        }
        localObject1 = ((ieiiee)localObject1).b0444ф0444ф0444ффф0444ф();
        localObject2 = fffbbb.b042EЮ042EЮЮЮЮ042EЮ;
        local5 = new eiieie.5(this);
      }
      catch (Exception localException2)
      {
        throw localException2;
      }
    }
    localObject1 = ((Completable)localObject1).subscribe((Action)localObject2, local5);
    if ((bц0446ц0446цц0446цц + bцц04460446цц0446цц) * bц0446ц0446цц0446цц % b0446ц04460446цц0446цц != b04460446ц0446цц0446цц)
    {
      bц0446ц0446цц0446цц = 7;
      b04460446ц0446цц0446цц = bф0444ф0444ф044404440444фф();
    }
    localObject2 = this.b0446ццццц0446цц;
    ((CompositeDisposable)localObject2).add((Disposable)localObject1);
    return;
    switch (0)
    {
    }
    for (;;)
    {
      switch (0)
      {
      }
    }
  }
  
  public static int b0444фф0444ф044404440444фф()
  {
    return 1;
  }
  
  public static int bф0444ф0444ф044404440444фф()
  {
    return 45;
  }
  
  public static int bфф04440444ф044404440444фф()
  {
    return 0;
  }
  
  @ooiiio("TODO: MOB3-6414 - Proper separation and tests")
  private void bфффф0444044404440444фф()
  {
    Object localObject1 = this.b0446ц0446ццц0446цц.bф044404440444фффф0444ф();
    Object localObject2 = new eiieie.4(this);
    int i = bц0446ц0446цц0446цц;
    switch (i * (bцц04460446цц0446цц + i) % b0446ц04460446цц0446цц)
    {
    default: 
      bц0446ц0446цц0446цц = 45;
      b04460446ц0446цц0446цц = 91;
    }
    localObject1 = ((Single)localObject1).doFinally((Action)localObject2);
    localObject2 = new eiieie.2(this);
    eiieie.3 local3 = new eiieie.3(this);
    switch (1)
    {
    case 0: 
    default: 
      for (;;)
      {
        switch (1)
        {
        }
      }
    }
    if ((bф0444ф0444ф044404440444фф() + bцц04460446цц0446цц) * bф0444ф0444ф044404440444фф() % b0446ц04460446цц0446цц != b04460446ц0446цц0446цц)
    {
      bц0446ц0446цц0446цц = 89;
      b04460446ц0446цц0446цц = 48;
    }
    localObject1 = ((Single)localObject1).subscribe((Consumer)localObject2, local3);
    this.b0446ццццц0446цц.add((Disposable)localObject1);
  }
  
  /* Error */
  @ooiiio("TODO: MOB3-6414 - Proper separation and tests")
  public void b04440444044404440444044404440444фф()
  {
    // Byte code:
    //   0: getstatic 55	kkkkkk/eiieie:bц0446ц0446цц0446цц	I
    //   3: invokestatic 162	kkkkkk/eiieie:b0444фф0444ф044404440444фф	()I
    //   6: iadd
    //   7: getstatic 55	kkkkkk/eiieie:bц0446ц0446цц0446цц	I
    //   10: imul
    //   11: getstatic 59	kkkkkk/eiieie:b0446ц04460446цц0446цц	I
    //   14: irem
    //   15: getstatic 61	kkkkkk/eiieie:b04460446ц0446цц0446цц	I
    //   18: if_icmpeq +13 -> 31
    //   21: bipush 21
    //   23: putstatic 55	kkkkkk/eiieie:bц0446ц0446цц0446цц	I
    //   26: bipush 56
    //   28: putstatic 61	kkkkkk/eiieie:b04460446ц0446цц0446цц	I
    //   31: ldc -59
    //   33: bipush 37
    //   35: iconst_5
    //   36: invokestatic 203	kkkkkk/gguuuu:bккккк043Aкк043A043A	(Ljava/lang/String;CC)Ljava/lang/String;
    //   39: astore_1
    //   40: aload_1
    //   41: iconst_0
    //   42: anewarray 4	java/lang/Object
    //   45: invokestatic 209	kkkkkk/ooooio:bа04300430аа04300430ааа	(Ljava/lang/String;[Ljava/lang/Object;)V
    //   48: aload_0
    //   49: getfield 211	kkkkkk/eiieie:bц0446цццц0446цц	Landroid/os/CountDownTimer;
    //   52: ifnull +12 -> 64
    //   55: aload_0
    //   56: getfield 211	kkkkkk/eiieie:bц0446цццц0446цц	Landroid/os/CountDownTimer;
    //   59: astore_1
    //   60: aload_1
    //   61: invokevirtual 216	android/os/CountDownTimer:cancel	()V
    //   64: return
    //   65: astore_1
    //   66: aload_1
    //   67: athrow
    //   68: astore_1
    //   69: aload_1
    //   70: athrow
    // Local variable table:
    //   start	length	slot	name	signature
    //   0	71	0	this	eiieie
    //   39	22	1	localObject	Object
    //   65	2	1	localException1	Exception
    //   68	2	1	localException2	Exception
    // Exception table:
    //   from	to	target	type
    //   31	40	65	java/lang/Exception
    //   60	64	65	java/lang/Exception
    //   40	60	68	java/lang/Exception
  }
  
  @ooiiio("Delegate")
  public void b0444044404440444ф044404440444фф()
  {
    this.b0446ц0446ццц0446цц.b0444ф04440444фффф0444ф();
    bффф04440444044404440444фф();
  }
  
  @ooiiio("TODO: MOB3-6414 - Proper separation and tests")
  public void b044404440444ф0444044404440444фф()
  {
    this.bц04460446ццц0446цц = false;
    this.bцццццц0446цц = false;
    if (this.b0446цц0446цц0446цц.isTimeoutDialogShowing()) {
      this.b0446цц0446цц0446цц.hideTimeoutDialog();
    }
    this.b0446цц0446цц0446цц.startLoading();
    b04440444044404440444044404440444фф();
    bфффф0444044404440444фф();
  }
  
  @ooiiio("Delegate")
  public void b04440444ф04440444044404440444фф(eieiee paramEieiee)
  {
    int i = bц0446ц0446цц0446цц;
    switch (i * (bцц04460446цц0446цц + i) % b0446ц04460446цц0446цц)
    {
    default: 
      bц0446ц0446цц0446цц = 92;
      b04460446ц0446цц0446цц = 14;
    }
    this.b044604460446ццц0446цц = paramEieiee;
    switch (1)
    {
    case 0: 
    default: 
      for (;;)
      {
        switch (1)
        {
        }
      }
    }
    b044404440444ф0444044404440444фф();
  }
  
  @ooiiio("Delegate")
  public void b0444ф044404440444044404440444фф()
  {
    ieiiee localIeiiee = this.b0446ц0446ццц0446цц;
    long l = b044604460446044604460446ццц;
    int i = bц0446ц0446цц0446цц;
    switch (i * (bцц04460446цц0446цц + i) % b0446ц04460446цц0446цц)
    {
    default: 
      bц0446ц0446цц0446цц = 71;
      b04460446ц0446цц0446цц = 92;
    }
    localIeiiee.b04440444ф04440444ффф0444ф(Long.valueOf(l));
    bффф04440444044404440444фф();
    i = bц0446ц0446цц0446цц;
    switch (i * (bцц04460446цц0446цц + i) % b0446ц04460446цц0446цц)
    {
    default: 
      bц0446ц0446цц0446цц = 3;
      b04460446ц0446цц0446цц = bф0444ф0444ф044404440444фф();
    }
  }
  
  @ooiiio("Delegate")
  public void b0444ф04440444ф044404440444фф()
  {
    ieiiee localIeiiee = this.b0446ц0446ццц0446цц;
    if ((bц0446ц0446цц0446цц + bцц04460446цц0446цц) * bц0446ц0446цц0446цц % b0446ц04460446цц0446цц != b04460446ц0446цц0446цц)
    {
      bц0446ц0446цц0446цц = bф0444ф0444ф044404440444фф();
      b04460446ц0446цц0446цц = bф0444ф0444ф044404440444фф();
      int i = bц0446ц0446цц0446цц;
      switch (i * (bцц04460446цц0446цц + i) % b0446ц04460446цц0446цц)
      {
      default: 
        bц0446ц0446цц0446цц = 13;
        b04460446ц0446цц0446цц = bф0444ф0444ф044404440444фф();
      }
    }
    localIeiiee.b04440444ф0444фффф0444ф();
  }
  
  /* Error */
  @ooiiio("TODO: MOB3-6414 - Proper separation and tests")
  public void b0444ф0444ф0444044404440444фф(eiiiee paramEiiiee)
  {
    // Byte code:
    //   0: new 264	java/lang/StringBuilder
    //   3: dup
    //   4: invokespecial 265	java/lang/StringBuilder:<init>	()V
    //   7: ldc_w 267
    //   10: bipush 103
    //   12: iconst_5
    //   13: invokestatic 203	kkkkkk/gguuuu:bккккк043Aкк043A043A	(Ljava/lang/String;CC)Ljava/lang/String;
    //   16: invokevirtual 271	java/lang/StringBuilder:append	(Ljava/lang/String;)Ljava/lang/StringBuilder;
    //   19: astore 4
    //   21: aload_1
    //   22: invokevirtual 275	java/lang/Object:getClass	()Ljava/lang/Class;
    //   25: invokevirtual 281	java/lang/Class:getSimpleName	()Ljava/lang/String;
    //   28: astore 5
    //   30: getstatic 55	kkkkkk/eiieie:bц0446ц0446цц0446цц	I
    //   33: istore_2
    //   34: iload_2
    //   35: getstatic 57	kkkkkk/eiieie:bцц04460446цц0446цц	I
    //   38: iload_2
    //   39: iadd
    //   40: imul
    //   41: getstatic 59	kkkkkk/eiieie:b0446ц04460446цц0446цц	I
    //   44: irem
    //   45: tableswitch	default:+19->64, 0:+30->75
    //   64: invokestatic 65	kkkkkk/eiieie:bф0444ф0444ф044404440444фф	()I
    //   67: putstatic 55	kkkkkk/eiieie:bц0446ц0446цц0446цц	I
    //   70: bipush 95
    //   72: putstatic 61	kkkkkk/eiieie:b04460446ц0446цц0446цц	I
    //   75: aload 4
    //   77: aload 5
    //   79: invokevirtual 271	java/lang/StringBuilder:append	(Ljava/lang/String;)Ljava/lang/StringBuilder;
    //   82: astore 4
    //   84: aload 4
    //   86: invokevirtual 284	java/lang/StringBuilder:toString	()Ljava/lang/String;
    //   89: iconst_0
    //   90: anewarray 4	java/lang/Object
    //   93: invokestatic 209	kkkkkk/ooooio:bа04300430аа04300430ааа	(Ljava/lang/String;[Ljava/lang/Object;)V
    //   96: aload_0
    //   97: aload_1
    //   98: putfield 105	kkkkkk/eiieie:b0446цц0446цц0446цц	Lkkkkkk/eiiiee;
    //   101: aload_0
    //   102: getfield 164	kkkkkk/eiieie:bц04460446ццц0446цц	Z
    //   105: ifeq +29 -> 134
    //   108: ldc_w 286
    //   111: bipush 45
    //   113: iconst_0
    //   114: invokestatic 203	kkkkkk/gguuuu:bккккк043Aкк043A043A	(Ljava/lang/String;CC)Ljava/lang/String;
    //   117: iconst_0
    //   118: anewarray 4	java/lang/Object
    //   121: invokestatic 209	kkkkkk/ooooio:bа04300430аа04300430ааа	(Ljava/lang/String;[Ljava/lang/Object;)V
    //   124: aload_0
    //   125: invokevirtual 245	kkkkkk/eiieie:b044404440444ф0444044404440444фф	()V
    //   128: aload_0
    //   129: iconst_0
    //   130: putfield 157	kkkkkk/eiieie:bцц0446ццц0446цц	Z
    //   133: return
    //   134: aload_0
    //   135: getfield 157	kkkkkk/eiieie:bцц0446ццц0446цц	Z
    //   138: istore_3
    //   139: iload_3
    //   140: ifne -12 -> 128
    //   143: aload_0
    //   144: invokevirtual 224	kkkkkk/eiieie:bффф04440444044404440444фф	()V
    //   147: getstatic 55	kkkkkk/eiieie:bц0446ц0446цц0446цц	I
    //   150: istore_2
    //   151: iload_2
    //   152: getstatic 57	kkkkkk/eiieie:bцц04460446цц0446цц	I
    //   155: iload_2
    //   156: iadd
    //   157: imul
    //   158: invokestatic 144	kkkkkk/eiieie:b04440444ф0444ф044404440444фф	()I
    //   161: irem
    //   162: tableswitch	default:+37->199, 0:+-34->128
    //   180: iconst_2
    //   181: putstatic 55	kkkkkk/eiieie:bц0446ц0446цц0446цц	I
    //   184: invokestatic 65	kkkkkk/eiieie:bф0444ф0444ф044404440444фф	()I
    //   187: putstatic 61	kkkkkk/eiieie:b04460446ц0446цц0446цц	I
    //   190: goto -62 -> 128
    //   193: astore_1
    //   194: aload_1
    //   195: athrow
    //   196: astore_1
    //   197: aload_1
    //   198: athrow
    //   199: goto -19 -> 180
    // Local variable table:
    //   start	length	slot	name	signature
    //   0	202	0	this	eiieie
    //   0	202	1	paramEiiiee	eiiiee
    //   33	125	2	i	int
    //   138	2	3	bool	boolean
    //   19	66	4	localStringBuilder	StringBuilder
    //   28	50	5	str	String
    // Exception table:
    //   from	to	target	type
    //   84	96	193	java/lang/Exception
    //   143	180	193	java/lang/Exception
    //   180	190	193	java/lang/Exception
    //   0	30	196	java/lang/Exception
    //   75	84	196	java/lang/Exception
    //   96	128	196	java/lang/Exception
    //   128	133	196	java/lang/Exception
    //   134	139	196	java/lang/Exception
  }
  
  /* Error */
  @ooiiio("TODO: MOB3-6414 - Proper separation and tests")
  public void b0444фф04440444044404440444фф()
  {
    // Byte code:
    //   0: ldc_w 289
    //   3: sipush 153
    //   6: sipush 255
    //   9: iconst_0
    //   10: invokestatic 293	kkkkkk/gguuuu:bк043Aккк043Aкк043A043A	(Ljava/lang/String;CCC)Ljava/lang/String;
    //   13: iconst_0
    //   14: anewarray 4	java/lang/Object
    //   17: invokestatic 209	kkkkkk/ooooio:bа04300430аа04300430ааа	(Ljava/lang/String;[Ljava/lang/Object;)V
    //   20: aload_0
    //   21: getfield 211	kkkkkk/eiieie:bц0446цццц0446цц	Landroid/os/CountDownTimer;
    //   24: astore_1
    //   25: aload_1
    //   26: ifnull +80 -> 106
    //   29: getstatic 55	kkkkkk/eiieie:bц0446ц0446цц0446цц	I
    //   32: getstatic 57	kkkkkk/eiieie:bцц04460446цц0446цц	I
    //   35: iadd
    //   36: getstatic 55	kkkkkk/eiieie:bц0446ц0446цц0446цц	I
    //   39: imul
    //   40: getstatic 59	kkkkkk/eiieie:b0446ц04460446цц0446цц	I
    //   43: irem
    //   44: getstatic 61	kkkkkk/eiieie:b04460446ц0446цц0446цц	I
    //   47: if_icmpeq +13 -> 60
    //   50: bipush 52
    //   52: putstatic 55	kkkkkk/eiieie:bц0446ц0446цц0446цц	I
    //   55: bipush 20
    //   57: putstatic 61	kkkkkk/eiieie:b04460446ц0446цц0446цц	I
    //   60: aload_0
    //   61: getfield 211	kkkkkk/eiieie:bц0446цццц0446цц	Landroid/os/CountDownTimer;
    //   64: invokevirtual 216	android/os/CountDownTimer:cancel	()V
    //   67: aload_0
    //   68: getfield 211	kkkkkk/eiieie:bц0446цццц0446цц	Landroid/os/CountDownTimer;
    //   71: invokevirtual 297	android/os/CountDownTimer:start	()Landroid/os/CountDownTimer;
    //   74: pop
    //   75: getstatic 55	kkkkkk/eiieie:bц0446ц0446цц0446цц	I
    //   78: getstatic 57	kkkkkk/eiieie:bцц04460446цц0446цц	I
    //   81: iadd
    //   82: getstatic 55	kkkkkk/eiieie:bц0446ц0446цц0446цц	I
    //   85: imul
    //   86: getstatic 59	kkkkkk/eiieie:b0446ц04460446цц0446цц	I
    //   89: irem
    //   90: getstatic 61	kkkkkk/eiieie:b04460446ц0446цц0446цц	I
    //   93: if_icmpeq +13 -> 106
    //   96: iconst_3
    //   97: putstatic 55	kkkkkk/eiieie:bц0446ц0446цц0446цц	I
    //   100: invokestatic 65	kkkkkk/eiieie:bф0444ф0444ф044404440444фф	()I
    //   103: putstatic 61	kkkkkk/eiieie:b04460446ц0446цц0446цц	I
    //   106: return
    //   107: astore_1
    //   108: aload_1
    //   109: athrow
    //   110: astore_1
    //   111: aload_1
    //   112: athrow
    // Local variable table:
    //   start	length	slot	name	signature
    //   0	113	0	this	eiieie
    //   24	2	1	localCountDownTimer	CountDownTimer
    //   107	2	1	localException1	Exception
    //   110	2	1	localException2	Exception
    // Exception table:
    //   from	to	target	type
    //   0	20	107	java/lang/Exception
    //   60	75	107	java/lang/Exception
    //   20	25	110	java/lang/Exception
  }
  
  @ooiiio("Delegate")
  public void b0444ффф0444044404440444фф(boolean paramBoolean)
  {
    if ((bц0446ц0446цц0446цц + bцц04460446цц0446цц) * bц0446ц0446цц0446цц % b0446ц04460446цц0446цц != b04460446ц0446цц0446цц)
    {
      bц0446ц0446цц0446цц = bф0444ф0444ф044404440444фф();
      b04460446ц0446цц0446цц = 46;
    }
    switch (1)
    {
    case 0: 
    default: 
      for (;;)
      {
        switch (1)
        {
        }
      }
    }
    this.bцццццц0446цц = paramBoolean;
  }
  
  @VisibleForTesting
  public void bф0444044404440444044404440444фф(long paramLong)
  {
    if ((bц0446ц0446цц0446цц + bцц04460446цц0446цц) * bц0446ц0446цц0446цц % b0446ц04460446цц0446цц != b04460446ц0446цц0446цц)
    {
      bц0446ц0446цц0446цц = 24;
      b04460446ц0446цц0446цц = 73;
    }
    if ((paramLong <= b0446ц0446044604460446ццц) && (!this.bцц0446ццц0446цц))
    {
      switch (1)
      {
      case 0: 
      default: 
        for (;;)
        {
          switch (0)
          {
          }
        }
      }
      boolean bool = this.b0446цц0446цц0446цц.isTimeoutDialogShowing();
      int i = bц0446ц0446цц0446цц;
      switch (i * (bцц04460446цц0446цц + i) % b0446ц04460446цц0446цц)
      {
      default: 
        bц0446ц0446цц0446цц = 84;
        b04460446ц0446цц0446цц = 65;
      }
      if (!bool) {
        this.b0446цц0446цц0446цц.showTimeoutDialog();
      }
    }
    switch (0)
    {
    case 1: 
    default: 
      for (;;)
      {
        switch (0)
        {
        }
      }
    }
  }
  
  /* Error */
  @ooiiio("Delegate")
  public void bф044404440444ф044404440444фф()
  {
    // Byte code:
    //   0: iconst_0
    //   1: tableswitch	default:+23->24, 0:+50->51, 1:+-1->0
    //   24: iconst_0
    //   25: tableswitch	default:+23->48, 0:+26->51, 1:+-25->0
    //   48: goto -24 -> 24
    //   51: getstatic 55	kkkkkk/eiieie:bц0446ц0446цц0446цц	I
    //   54: getstatic 57	kkkkkk/eiieie:bцц04460446цц0446цц	I
    //   57: iadd
    //   58: getstatic 55	kkkkkk/eiieie:bц0446ц0446цц0446цц	I
    //   61: imul
    //   62: getstatic 59	kkkkkk/eiieie:b0446ц04460446цц0446цц	I
    //   65: irem
    //   66: getstatic 61	kkkkkk/eiieie:b04460446ц0446цц0446цц	I
    //   69: if_icmpeq +13 -> 82
    //   72: bipush 37
    //   74: putstatic 55	kkkkkk/eiieie:bц0446ц0446цц0446цц	I
    //   77: bipush 94
    //   79: putstatic 61	kkkkkk/eiieie:b04460446ц0446цц0446цц	I
    //   82: getstatic 55	kkkkkk/eiieie:bц0446ц0446цц0446цц	I
    //   85: istore_1
    //   86: getstatic 57	kkkkkk/eiieie:bцц04460446цц0446цц	I
    //   89: istore_2
    //   90: getstatic 59	kkkkkk/eiieie:b0446ц04460446цц0446цц	I
    //   93: istore_3
    //   94: iload_1
    //   95: iload_2
    //   96: iload_1
    //   97: iadd
    //   98: imul
    //   99: iload_3
    //   100: irem
    //   101: tableswitch	default:+19->120, 0:+30->131
    //   120: bipush 44
    //   122: putstatic 55	kkkkkk/eiieie:bц0446ц0446цц0446цц	I
    //   125: invokestatic 65	kkkkkk/eiieie:bф0444ф0444ф044404440444фф	()I
    //   128: putstatic 61	kkkkkk/eiieie:b04460446ц0446цц0446цц	I
    //   131: aload_0
    //   132: getfield 96	kkkkkk/eiieie:b0446ц0446ццц0446цц	Lkkkkkk/ieiiee;
    //   135: invokevirtual 309	kkkkkk/ieiiee:bфф04440444фффф0444ф	()V
    //   138: return
    //   139: astore 4
    //   141: aload 4
    //   143: athrow
    //   144: astore 4
    //   146: aload 4
    //   148: athrow
    // Local variable table:
    //   start	length	slot	name	signature
    //   0	149	0	this	eiieie
    //   85	14	1	i	int
    //   89	9	2	j	int
    //   93	8	3	k	int
    //   139	3	4	localException1	Exception
    //   144	3	4	localException2	Exception
    // Exception table:
    //   from	to	target	type
    //   82	94	139	java/lang/Exception
    //   131	138	139	java/lang/Exception
    //   120	131	144	java/lang/Exception
  }
  
  @ooiiio("TODO: MOB3-6414 - Proper separation and tests")
  public void bф04440444ф0444044404440444фф()
  {
    throw new Runtime("d2j fail translate: java.lang.IndexOutOfBoundsException: fromIndex < 0: -1\n\tat java.util.BitSet.nextSetBit(BitSet.java:712)\n\tat com.googlecode.dex2jar.ir.ts.array.FillArrayTransformer.makeSureAllElementAreAssigned(FillArrayTransformer.java:505)\n\tat com.googlecode.dex2jar.ir.ts.array.FillArrayTransformer.transformReportChanged(FillArrayTransformer.java:123)\n\tat com.googlecode.dex2jar.ir.ts.StatedTransformer.transform(StatedTransformer.java:10)\n\tat com.googlecode.d2j.dex.Dex2jar$2.optimize(Dex2jar.java:149)\n\tat com.googlecode.d2j.dex.Dex2Asm.convertCode(Dex2Asm.java:414)\n\tat com.googlecode.d2j.dex.ExDex2Asm.convertCode(ExDex2Asm.java:42)\n\tat com.googlecode.d2j.dex.Dex2jar$2.convertCode(Dex2jar.java:128)\n\tat com.googlecode.d2j.dex.Dex2Asm.convertMethod(Dex2Asm.java:509)\n\tat com.googlecode.d2j.dex.Dex2Asm.convertClass(Dex2Asm.java:406)\n\tat com.googlecode.d2j.dex.Dex2Asm.convertDex(Dex2Asm.java:422)\n\tat com.googlecode.d2j.dex.Dex2jar.doTranslate(Dex2jar.java:172)\n\tat com.googlecode.d2j.dex.Dex2jar.to(Dex2jar.java:272)\n\tat com.googlecode.dex2jar.tools.Dex2jarCmd.doCommandLine(Dex2jarCmd.java:108)\n\tat com.googlecode.dex2jar.tools.BaseCmd.doMain(BaseCmd.java:288)\n\tat com.googlecode.dex2jar.tools.Dex2jarCmd.main(Dex2jarCmd.java:32)\n");
  }
  
  @ooiiio("Delegate")
  public void bф0444ф04440444044404440444фф()
  {
    int i = bц0446ц0446цц0446цц;
    int j = bц0446ц0446цц0446цц;
    switch (j * (bцц04460446цц0446цц + j) % b04440444ф0444ф044404440444фф())
    {
    default: 
      bц0446ц0446цц0446цц = bф0444ф0444ф044404440444фф();
      b04460446ц0446цц0446цц = bф0444ф0444ф044404440444фф();
    }
    switch (i * (bцц04460446цц0446цц + i) % b0446ц04460446цц0446цц)
    {
    default: 
      bц0446ц0446цц0446цц = 85;
      b04460446ц0446цц0446цц = 62;
    }
    this.b0446ц0446ццц0446цц.b0444фф04440444ффф0444ф();
    switch (0)
    {
    case 1: 
    default: 
      for (;;)
      {
        switch (1)
        {
        }
      }
    }
  }
  
  public boolean bф0444фф0444044404440444фф()
  {
    boolean bool2 = false;
    try
    {
      long l1 = this.b0446ц0446ццц0446цц.b044404440444ф0444ффф0444ф();
      long l2 = b044604460446044604460446ццц;
      boolean bool1;
      if (l1 < l2) {
        bool1 = true;
      }
      do
      {
        do
        {
          return bool1;
          bool1 = bool2;
        } while ((bц0446ц0446цц0446цц + bцц04460446цц0446цц) * bц0446ц0446цц0446цц % b04440444ф0444ф044404440444фф() == b04460446ц0446цц0446цц);
        bц0446ц0446цц0446цц = bф0444ф0444ф044404440444фф();
        b04460446ц0446цц0446цц = bф0444ф0444ф044404440444фф();
        bool1 = bool2;
      } while ((bц0446ц0446цц0446цц + b0444фф0444ф044404440444фф()) * bц0446ц0446цц0446цц % b0446ц04460446цц0446цц == b04460446ц0446цц0446цц);
      bц0446ц0446цц0446цц = 27;
      b04460446ц0446цц0446цц = 0;
      return false;
    }
    catch (Exception localException)
    {
      switch (1)
      {
      case 0: 
      default: 
        for (;;)
        {
          switch (1)
          {
          }
        }
      }
      throw localException;
    }
  }
  
  /* Error */
  @ooiiio("Delegate")
  public void bфф044404440444044404440444фф()
  {
    // Byte code:
    //   0: iconst_2
    //   1: istore_1
    //   2: getstatic 55	kkkkkk/eiieie:bц0446ц0446цц0446цц	I
    //   5: istore_2
    //   6: iload_2
    //   7: getstatic 57	kkkkkk/eiieie:bцц04460446цц0446цц	I
    //   10: iload_2
    //   11: iadd
    //   12: imul
    //   13: getstatic 59	kkkkkk/eiieie:b0446ц04460446цц0446цц	I
    //   16: irem
    //   17: tableswitch	default:+19->36, 0:+29->46
    //   36: invokestatic 65	kkkkkk/eiieie:bф0444ф0444ф044404440444фф	()I
    //   39: putstatic 55	kkkkkk/eiieie:bц0446ц0446цц0446цц	I
    //   42: iconst_1
    //   43: putstatic 61	kkkkkk/eiieie:b04460446ц0446цц0446цц	I
    //   46: aload_0
    //   47: getfield 96	kkkkkk/eiieie:b0446ц0446ццц0446цц	Lkkkkkk/ieiiee;
    //   50: astore_3
    //   51: aload_3
    //   52: invokevirtual 332	kkkkkk/ieiiee:bф0444ф04440444ффф0444ф	()V
    //   55: iload_1
    //   56: iconst_0
    //   57: idiv
    //   58: istore_1
    //   59: goto -4 -> 55
    //   62: astore_3
    //   63: invokestatic 65	kkkkkk/eiieie:bф0444ф0444ф044404440444фф	()I
    //   66: putstatic 55	kkkkkk/eiieie:bц0446ц0446цц0446цц	I
    //   69: return
    //   70: astore_3
    //   71: aload_3
    //   72: athrow
    //   73: astore_3
    //   74: aload_3
    //   75: athrow
    //   76: astore_3
    //   77: aload_3
    //   78: athrow
    //   79: astore_3
    //   80: aload_3
    //   81: athrow
    // Local variable table:
    //   start	length	slot	name	signature
    //   0	82	0	this	eiieie
    //   1	58	1	i	int
    //   5	8	2	j	int
    //   50	2	3	localIeiiee	ieiiee
    //   62	1	3	localException1	Exception
    //   70	2	3	localException2	Exception
    //   73	2	3	localException3	Exception
    //   76	2	3	localException4	Exception
    //   79	2	3	localException5	Exception
    // Exception table:
    //   from	to	target	type
    //   55	59	62	java/lang/Exception
    //   46	51	70	java/lang/Exception
    //   71	73	73	java/lang/Exception
    //   77	79	73	java/lang/Exception
    //   51	55	76	java/lang/Exception
    //   63	69	79	java/lang/Exception
  }
  
  @ooiiio("TODO: MOB3-6414 - Proper separation and tests")
  public void bфф0444ф0444044404440444фф()
  {
    ooooio.bа04300430аа04300430ааа(gguuuu.bк043Aккк043Aкк043A043A("''z+,~\037\"+(4293*,,", 'ò', 'Â', '\003'), new Object[0]);
    this.bцц0446ццц0446цц = true;
    if ((this.b0446ц0446ццц0446цц.bф0444фф0444ффф0444ф()) && (!this.b0446ц0446ццц0446цц.b0444ффф0444ффф0444ф()) && (!this.b0446ц0446ццц0446цц.bфф0444ф0444ффф0444ф())) {
      this.bц04460446ццц0446цц = true;
    }
  }
  
  @ooiiio("TODO: MOB3-6414 - Proper separation and tests")
  public void bффф04440444044404440444фф()
  {
    try
    {
      b04440444044404440444044404440444фф();
      l = this.b0446ц0446ццц0446цц.b044404440444ф0444ффф0444ф();
      if (l <= 0L) {
        break label123;
      }
    }
    catch (Exception localException1)
    {
      try
      {
        long l;
        int i;
        int j;
        int k;
        bц0446ц0446цц0446цц = 5;
        b04460446ц0446цц0446цц = 6;
        this.bц0446цццц0446цц = new eiieie.1(this, l, bц04460446044604460446ццц);
        b0444фф04440444044404440444фф();
        if ((bц0446ц0446цц0446цц + bцц04460446цц0446цц) * bц0446ц0446цц0446цц % b0446ц04460446цц0446цц != b04460446ц0446цц0446цц)
        {
          bц0446ц0446цц0446цц = bф0444ф0444ф044404440444фф();
          b04460446ц0446цц0446цц = bф0444ф0444ф044404440444фф();
        }
        label123:
        return;
      }
      catch (Exception localException2)
      {
        throw localException2;
      }
      localException1 = localException1;
      throw localException1;
    }
    i = bф0444ф0444ф044404440444фф();
    j = bцц04460446цц0446цц;
    k = b0446ц04460446цц0446цц;
    switch (i * (j + i) % k)
    {
    }
    switch (1)
    {
    }
    for (;;)
    {
      switch (1)
      {
      }
    }
  }
  
  /* Error */
  @ooiiio("Delegate")
  public void bфффффффф0444ф(boolean paramBoolean)
  {
    // Byte code:
    //   0: iload_1
    //   1: ifeq +128 -> 129
    //   4: iconst_1
    //   5: tableswitch	default:+23->28, 0:+-1->4, 1:+50->55
    //   28: iconst_0
    //   29: tableswitch	default:+23->52, 0:+26->55, 1:+-25->4
    //   52: goto -24 -> 28
    //   55: aload_0
    //   56: invokevirtual 354	kkkkkk/eiieie:b0444ф044404440444044404440444фф	()V
    //   59: getstatic 55	kkkkkk/eiieie:bц0446ц0446цц0446цц	I
    //   62: getstatic 57	kkkkkk/eiieie:bцц04460446цц0446цц	I
    //   65: iadd
    //   66: getstatic 55	kkkkkk/eiieie:bц0446ц0446цц0446цц	I
    //   69: imul
    //   70: getstatic 59	kkkkkk/eiieie:b0446ц04460446цц0446цц	I
    //   73: irem
    //   74: getstatic 61	kkkkkk/eiieie:b04460446ц0446цц0446цц	I
    //   77: if_icmpeq +45 -> 122
    //   80: bipush 95
    //   82: putstatic 55	kkkkkk/eiieie:bц0446ц0446цц0446цц	I
    //   85: bipush 20
    //   87: putstatic 61	kkkkkk/eiieie:b04460446ц0446цц0446цц	I
    //   90: getstatic 55	kkkkkk/eiieie:bц0446ц0446цц0446цц	I
    //   93: getstatic 57	kkkkkk/eiieie:bцц04460446цц0446цц	I
    //   96: iadd
    //   97: getstatic 55	kkkkkk/eiieie:bц0446ц0446цц0446цц	I
    //   100: imul
    //   101: getstatic 59	kkkkkk/eiieie:b0446ц04460446цц0446цц	I
    //   104: irem
    //   105: getstatic 61	kkkkkk/eiieie:b04460446ц0446цц0446цц	I
    //   108: if_icmpeq +14 -> 122
    //   111: bipush 92
    //   113: putstatic 55	kkkkkk/eiieie:bц0446ц0446цц0446цц	I
    //   116: invokestatic 65	kkkkkk/eiieie:bф0444ф0444ф044404440444фф	()I
    //   119: putstatic 61	kkkkkk/eiieie:b04460446ц0446цц0446цц	I
    //   122: return
    //   123: astore_2
    //   124: aload_2
    //   125: athrow
    //   126: astore_2
    //   127: aload_2
    //   128: athrow
    //   129: aload_0
    //   130: invokevirtual 356	kkkkkk/eiieie:b0444044404440444ф044404440444фф	()V
    //   133: return
    // Local variable table:
    //   start	length	slot	name	signature
    //   0	134	0	this	eiieie
    //   0	134	1	paramBoolean	boolean
    //   123	2	2	localException1	Exception
    //   126	2	2	localException2	Exception
    // Exception table:
    //   from	to	target	type
    //   55	59	123	java/lang/Exception
    //   129	133	126	java/lang/Exception
  }
}
