package kkkkkk;

import android.annotation.TargetApi;
import android.bluetooth.BluetoothAdapter;
import android.content.Context;
import android.content.pm.ApplicationInfo;
import android.content.pm.PackageInfo;
import android.content.pm.PackageManager;
import android.location.Location;
import android.os.Build;
import android.os.Environment;
import android.os.Looper;
import android.provider.Settings.Secure;
import android.provider.Settings.System;
import android.util.SparseIntArray;
import java.io.File;
import java.lang.reflect.Method;
import java.net.URI;
import java.net.URISyntaxException;
import java.security.MessageDigest;
import java.security.NoSuchAlgorithmException;
import java.util.ArrayList;
import java.util.Collections;
import java.util.HashMap;
import java.util.Iterator;
import java.util.List;
import java.util.Locale;
import java.util.Map;
import java.util.Map.Entry;
import java.util.Set;
import javax.annotation.Nonnull;
import javax.annotation.Nullable;

public class faafaf
{
  @Nullable
  private static final Method b042204220422ТТ0422042204220422Т = faaaff.b043A043Aк043A043Aк043A043Aк043A(faaaff.b043Aк043Aк043Aк043A043Aк043A(faaaff.afaaff.L), gguuuu.bккккк043Aкк043A043A("54D", 'M', '\000'), new Class[] { String.class });
  public static int b04220422Т0422Т0422042204220422Т = 1;
  public static int b0422ТТ0422Т0422042204220422Т = 7;
  private static final String bТ04220422ТТ0422042204220422Т = fafffa.b043A043A043A043Aкк043Aкк043A(faafaf.class);
  public static int bТ0422Т0422Т0422042204220422Т = 0;
  public static int bТТ04220422Т0422042204220422Т = 2;
  @Nonnull
  private static final SparseIntArray bТТТ0422Т0422042204220422Т = new SparseIntArray(5);
  
  static
  {
    Object localObject1 = faaaff.b043Aк043Aк043Aк043A043Aк043A(faaaff.afaaff.float);
    Object localObject2 = faaaff.bкк043A043A043Aк043A043Aк043A((Class)localObject1, gguuuu.bк043Aккк043Aкк043A043A(",6,<D<A7>>PEG5IKJWNHNQMNNRUGG", '', 'ß', '\003'));
    if (localObject2 != null) {
      bТТТ0422Т0422042204220422Т.put(((Integer)localObject2).intValue(), 1);
    }
    localObject2 = faaaff.bкк043A043A043Aк043A043Aк043A((Class)localObject1, gguuuu.bккккк043Aкк043A043A(".8.>F>C9@@RGI7KMLYDJ>ASIWG", 'ç', '\000'));
    if (localObject2 != null) {
      bТТТ0422Т0422042204220422Т.put(((Integer)localObject2).intValue(), 2);
    }
    localObject2 = faaaff.bкк043A043A043Aк043A043Aк043A((Class)localObject1, gguuuu.bккккк043Aкк043A043A("\035%\031'-#&\032\037\035-  \f\036\036\033&\007\b\030\f\030\002\024\b\f\004", '', '\003'));
    if (localObject2 != null)
    {
      SparseIntArray localSparseIntArray = bТТТ0422Т0422042204220422Т;
      switch (0)
      {
      case 1: 
      default: 
        for (;;)
        {
          switch (0)
          {
          }
        }
      }
      int i = ((Integer)localObject2).intValue();
      if ((b0422ТТ0422Т0422042204220422Т + b04220422Т0422Т0422042204220422Т) * b0422ТТ0422Т0422042204220422Т % bТТ04220422Т0422042204220422Т != bТ0422Т0422Т0422042204220422Т)
      {
        b0422ТТ0422Т0422042204220422Т = bк043Aкк043Aкк043Aк043A();
        bТ0422Т0422Т0422042204220422Т = 94;
      }
      localSparseIntArray.put(i, 4);
    }
    localObject2 = faaaff.bкк043A043A043Aк043A043Aк043A((Class)localObject1, gguuuu.bккккк043Aкк043A043A("\023\035\023#+#(\036%%7,.\034021>!$6,:*", 'f', '\004'));
    if (localObject2 != null) {
      bТТТ0422Т0422042204220422Т.put(((Integer)localObject2).intValue(), 8);
    }
    localObject2 = faaaff.bкк043A043A043Aк043A043Aк043A((Class)localObject1, gguuuu.bккккк043Aкк043A043A("\031#\031)1).$++=24\"687D'*<2@0K1351F>GS@;P", 'i', '\004'));
    if (localObject2 != null) {
      bТТТ0422Т0422042204220422Т.put(((Integer)localObject2).intValue(), 32);
    }
    localObject1 = faaaff.bкк043A043A043Aк043A043Aк043A((Class)localObject1, gguuuu.bк043Aккк043Aкк043A043A("HRHX`X]SZZlacQegfsVYkao_zlbp~utgu", '¨', '¥', '\001'));
    if ((b0422ТТ0422Т0422042204220422Т + b04220422Т0422Т0422042204220422Т) * b0422ТТ0422Т0422042204220422Т % bТТ04220422Т0422042204220422Т != bТ0422Т0422Т0422042204220422Т)
    {
      b0422ТТ0422Т0422042204220422Т = bк043Aкк043Aкк043Aк043A();
      bТ0422Т0422Т0422042204220422Т = 91;
    }
    switch (1)
    {
    case 0: 
    default: 
      for (;;)
      {
        switch (1)
        {
        }
      }
    }
    if (localObject1 != null) {
      bТТТ0422Т0422042204220422Т.put(((Integer)localObject1).intValue(), 64);
    }
  }
  
  public faafaf() {}
  
  /* Error */
  @Nonnull
  public static afffaf b043A043A043A043A043Aкк043Aк043A(@Nonnull aaffaf paramAaffaf)
    throws InterruptedException
  {
    // Byte code:
    //   0: aload_0
    //   1: getfield 133	kkkkkk/faafaf$aaffaf:b0422042204220422Т0422042204220422Т	Landroid/content/Context;
    //   4: astore_0
    //   5: getstatic 90	kkkkkk/faafaf:b0422ТТ0422Т0422042204220422Т	I
    //   8: istore_1
    //   9: getstatic 92	kkkkkk/faafaf:b04220422Т0422Т0422042204220422Т	I
    //   12: istore_2
    //   13: getstatic 90	kkkkkk/faafaf:b0422ТТ0422Т0422042204220422Т	I
    //   16: istore_3
    //   17: invokestatic 136	kkkkkk/faafaf:b043Aккк043Aкк043Aк043A	()I
    //   20: istore 4
    //   22: getstatic 96	kkkkkk/faafaf:bТ0422Т0422Т0422042204220422Т	I
    //   25: istore 5
    //   27: iload_1
    //   28: iload_2
    //   29: iadd
    //   30: iload_3
    //   31: imul
    //   32: iload 4
    //   34: irem
    //   35: iload 5
    //   37: if_icmpeq +48 -> 85
    //   40: getstatic 90	kkkkkk/faafaf:b0422ТТ0422Т0422042204220422Т	I
    //   43: getstatic 92	kkkkkk/faafaf:b04220422Т0422Т0422042204220422Т	I
    //   46: iadd
    //   47: getstatic 90	kkkkkk/faafaf:b0422ТТ0422Т0422042204220422Т	I
    //   50: imul
    //   51: getstatic 94	kkkkkk/faafaf:bТТ04220422Т0422042204220422Т	I
    //   54: irem
    //   55: getstatic 96	kkkkkk/faafaf:bТ0422Т0422Т0422042204220422Т	I
    //   58: if_icmpeq +14 -> 72
    //   61: bipush 87
    //   63: putstatic 90	kkkkkk/faafaf:b0422ТТ0422Т0422042204220422Т	I
    //   66: invokestatic 99	kkkkkk/faafaf:bк043Aкк043Aкк043Aк043A	()I
    //   69: putstatic 96	kkkkkk/faafaf:bТ0422Т0422Т0422042204220422Т	I
    //   72: invokestatic 99	kkkkkk/faafaf:bк043Aкк043Aкк043Aк043A	()I
    //   75: istore_1
    //   76: iload_1
    //   77: putstatic 90	kkkkkk/faafaf:b0422ТТ0422Т0422042204220422Т	I
    //   80: bipush 22
    //   82: putstatic 96	kkkkkk/faafaf:bТ0422Т0422Т0422042204220422Т	I
    //   85: aload_0
    //   86: invokestatic 142	kkkkkk/aaafaf:bккккккк043Aк043A	(Landroid/content/Context;)Lkkkkkk/afffaf;
    //   89: astore_0
    //   90: aload_0
    //   91: areturn
    //   92: astore_0
    //   93: aload_0
    //   94: athrow
    //   95: astore_0
    //   96: aload_0
    //   97: athrow
    // Local variable table:
    //   start	length	slot	name	signature
    //   0	98	0	paramAaffaf	aaffaf
    //   8	69	1	i	int
    //   12	18	2	j	int
    //   16	16	3	k	int
    //   20	15	4	m	int
    //   25	13	5	n	int
    // Exception table:
    //   from	to	target	type
    //   5	27	92	java/lang/Exception
    //   72	76	92	java/lang/Exception
    //   85	90	92	java/lang/Exception
    //   0	5	95	java/lang/Exception
    //   76	85	95	java/lang/Exception
  }
  
  @TargetApi(11)
  public static int b043A043A043A043Aк043Aк043Aк043A(aaffaf paramAaffaf)
  {
    for (;;)
    {
      try
      {
        i = tttjtt.tjtttt.jttttt.bююю044Eюююю044E044E;
        j = tttjtt.tjtttt.vddddd.b044Eюю044E044Eююю044E044E;
        if (i < j) {}
      }
      catch (Exception paramAaffaf)
      {
        int i;
        int j;
        SparseIntArray localSparseIntArray;
        int k;
        throw paramAaffaf;
      }
      try
      {
        localSparseIntArray = bТТТ0422Т0422042204220422Т;
        i = localSparseIntArray.get(dvvdvv.bк043Aк043Aк043Aк043A043Aк(paramAaffaf.b0422042204220422Т0422042204220422Т));
        if (i != 0) {
          return i;
        }
        i = b0422ТТ0422Т0422042204220422Т;
        j = b04220422Т0422Т0422042204220422Т;
        k = bТТ04220422Т0422042204220422Т;
        switch (i * (j + i) % k)
        {
        default: 
          b0422ТТ0422Т0422042204220422Т = 55;
          bТ0422Т0422Т0422042204220422Т = bк043Aкк043Aкк043Aк043A();
        }
        return 16;
      }
      catch (Exception paramAaffaf)
      {
        throw paramAaffaf;
      }
    }
    i = b0422ТТ0422Т0422042204220422Т;
    switch (i * (b04220422Т0422Т0422042204220422Т + i) % bТТ04220422Т0422042204220422Т)
    {
    default: 
      b0422ТТ0422Т0422042204220422Т = 16;
      bТ0422Т0422Т0422042204220422Т = bк043Aкк043Aкк043Aк043A();
      return 1;
    }
    return 1;
  }
  
  public static String b043A043A043A043Aккк043Aк043A()
  {
    int i = b0422ТТ0422Т0422042204220422Т;
    switch (i * (b04220422Т0422Т0422042204220422Т + i) % bТТ04220422Т0422042204220422Т)
    {
    default: 
      b0422ТТ0422Т0422042204220422Т = 79;
      i = bк043Aкк043Aкк043Aк043A();
      switch (0)
      {
      case 1: 
      default: 
        for (;;)
        {
          switch (0)
          {
          }
        }
      }
      bТ0422Т0422Т0422042204220422Т = i;
    }
    try
    {
      String str = gguuuu.bк043Aккк043Aкк043A043A("\037K@MIB<", '#', '\001', '\000');
      return str;
    }
    catch (Exception localException)
    {
      throw localException;
    }
  }
  
  /* Error */
  public static String b043A043A043Aк043Aкк043Aк043A(@Nonnull aaffaf paramAaffaf)
  {
    // Byte code:
    //   0: invokestatic 185	kkkkkk/tttjtt$jtjttt:bк043Aк043Aк043A043Aккк	()Z
    //   3: ifne +5 -> 8
    //   6: aconst_null
    //   7: areturn
    //   8: aload_0
    //   9: getfield 133	kkkkkk/faafaf$aaffaf:b0422042204220422Т0422042204220422Т	Landroid/content/Context;
    //   12: invokevirtual 191	android/content/Context:getApplicationContext	()Landroid/content/Context;
    //   15: ldc -63
    //   17: bipush 123
    //   19: sipush 214
    //   22: iconst_3
    //   23: invokestatic 66	kkkkkk/gguuuu:bк043Aккк043Aкк043A043A	(Ljava/lang/String;CCC)Ljava/lang/String;
    //   26: invokevirtual 197	android/content/Context:getSystemService	(Ljava/lang/String;)Ljava/lang/Object;
    //   29: astore 5
    //   31: aload 5
    //   33: ifnull -27 -> 6
    //   36: getstatic 90	kkkkkk/faafaf:b0422ТТ0422Т0422042204220422Т	I
    //   39: istore_1
    //   40: iload_1
    //   41: getstatic 92	kkkkkk/faafaf:b04220422Т0422Т0422042204220422Т	I
    //   44: iload_1
    //   45: iadd
    //   46: imul
    //   47: getstatic 94	kkkkkk/faafaf:bТТ04220422Т0422042204220422Т	I
    //   50: irem
    //   51: tableswitch	default:+17->68, 0:+27->78
    //   68: bipush 87
    //   70: putstatic 90	kkkkkk/faafaf:b0422ТТ0422Т0422042204220422Т	I
    //   73: bipush 43
    //   75: putstatic 96	kkkkkk/faafaf:bТ0422Т0422Т0422042204220422Т	I
    //   78: aload 5
    //   80: instanceof 199
    //   83: ifeq -77 -> 6
    //   86: aload 5
    //   88: checkcast 199	android/telephony/TelephonyManager
    //   91: astore 6
    //   93: new 201	java/util/HashMap
    //   96: dup
    //   97: invokespecial 202	java/util/HashMap:<init>	()V
    //   100: astore 5
    //   102: aload 6
    //   104: invokevirtual 205	android/telephony/TelephonyManager:getNetworkOperator	()Ljava/lang/String;
    //   107: astore 7
    //   109: aload 6
    //   111: invokevirtual 208	android/telephony/TelephonyManager:getNetworkCountryIso	()Ljava/lang/String;
    //   114: astore 8
    //   116: getstatic 90	kkkkkk/faafaf:b0422ТТ0422Т0422042204220422Т	I
    //   119: getstatic 92	kkkkkk/faafaf:b04220422Т0422Т0422042204220422Т	I
    //   122: iadd
    //   123: getstatic 90	kkkkkk/faafaf:b0422ТТ0422Т0422042204220422Т	I
    //   126: imul
    //   127: getstatic 94	kkkkkk/faafaf:bТТ04220422Т0422042204220422Т	I
    //   130: irem
    //   131: getstatic 96	kkkkkk/faafaf:bТ0422Т0422Т0422042204220422Т	I
    //   134: if_icmpeq +13 -> 147
    //   137: bipush 25
    //   139: putstatic 90	kkkkkk/faafaf:b0422ТТ0422Т0422042204220422Т	I
    //   142: bipush 71
    //   144: putstatic 96	kkkkkk/faafaf:bТ0422Т0422Т0422042204220422Т	I
    //   147: aload 6
    //   149: invokevirtual 211	android/telephony/TelephonyManager:getNetworkOperatorName	()Ljava/lang/String;
    //   152: astore 9
    //   154: aload 7
    //   156: ifnull +37 -> 193
    //   159: ldc -43
    //   161: aload 7
    //   163: invokevirtual 216	java/lang/String:trim	()Ljava/lang/String;
    //   166: invokevirtual 220	java/lang/String:equals	(Ljava/lang/Object;)Z
    //   169: ifne +24 -> 193
    //   172: aload 5
    //   174: ldc -34
    //   176: sipush 142
    //   179: bipush 109
    //   181: iconst_1
    //   182: invokestatic 66	kkkkkk/gguuuu:bк043Aккк043Aкк043A043A	(Ljava/lang/String;CCC)Ljava/lang/String;
    //   185: aload 7
    //   187: invokeinterface 227 3 0
    //   192: pop
    //   193: aload 9
    //   195: ifnull +37 -> 232
    //   198: ldc -43
    //   200: aload 9
    //   202: invokevirtual 216	java/lang/String:trim	()Ljava/lang/String;
    //   205: invokevirtual 220	java/lang/String:equals	(Ljava/lang/Object;)Z
    //   208: ifne +24 -> 232
    //   211: aload 5
    //   213: ldc -27
    //   215: bipush 92
    //   217: sipush 188
    //   220: iconst_3
    //   221: invokestatic 66	kkkkkk/gguuuu:bк043Aккк043Aкк043A043A	(Ljava/lang/String;CCC)Ljava/lang/String;
    //   224: aload 9
    //   226: invokeinterface 227 3 0
    //   231: pop
    //   232: aload 8
    //   234: ifnull +34 -> 268
    //   237: ldc -43
    //   239: aload 8
    //   241: invokevirtual 216	java/lang/String:trim	()Ljava/lang/String;
    //   244: invokevirtual 220	java/lang/String:equals	(Ljava/lang/Object;)Z
    //   247: ifne +21 -> 268
    //   250: aload 5
    //   252: ldc -25
    //   254: bipush 125
    //   256: iconst_3
    //   257: invokestatic 86	kkkkkk/gguuuu:bккккк043Aкк043A043A	(Ljava/lang/String;CC)Ljava/lang/String;
    //   260: aload 8
    //   262: invokeinterface 227 3 0
    //   267: pop
    //   268: new 233	kkkkkk/tttjtt$tjjttt
    //   271: dup
    //   272: new 235	kkkkkk/tttjtt
    //   275: dup
    //   276: invokespecial 236	kkkkkk/tttjtt:<init>	()V
    //   279: aload_0
    //   280: getfield 133	kkkkkk/faafaf$aaffaf:b0422042204220422Т0422042204220422Т	Landroid/content/Context;
    //   283: invokespecial 239	kkkkkk/tttjtt$tjjttt:<init>	(Lkkkkkk/tttjtt;Landroid/content/Context;)V
    //   286: astore 7
    //   288: aload 7
    //   290: ldc -15
    //   292: bipush 97
    //   294: sipush 166
    //   297: iconst_1
    //   298: invokestatic 66	kkkkkk/gguuuu:bк043Aккк043Aкк043A043A	(Ljava/lang/String;CCC)Ljava/lang/String;
    //   301: aload_0
    //   302: getfield 133	kkkkkk/faafaf$aaffaf:b0422042204220422Т0422042204220422Т	Landroid/content/Context;
    //   305: invokevirtual 244	android/content/Context:getPackageName	()Ljava/lang/String;
    //   308: invokevirtual 248	kkkkkk/tttjtt$tjjttt:bк043Aк043A043Aк043Aккк	(Ljava/lang/String;Ljava/lang/String;)Z
    //   311: istore_3
    //   312: aload 7
    //   314: ldc -6
    //   316: sipush 180
    //   319: iconst_2
    //   320: invokestatic 86	kkkkkk/gguuuu:bккккк043Aкк043A043A	(Ljava/lang/String;CC)Ljava/lang/String;
    //   323: aload_0
    //   324: getfield 133	kkkkkk/faafaf$aaffaf:b0422042204220422Т0422042204220422Т	Landroid/content/Context;
    //   327: invokevirtual 244	android/content/Context:getPackageName	()Ljava/lang/String;
    //   330: invokevirtual 248	kkkkkk/tttjtt$tjjttt:bк043Aк043A043Aк043Aккк	(Ljava/lang/String;Ljava/lang/String;)Z
    //   333: istore 4
    //   335: iload_3
    //   336: ifne +8 -> 344
    //   339: iload 4
    //   341: ifeq +653 -> 994
    //   344: getstatic 155	kkkkkk/tttjtt$tjtttt$jttttt:bююю044Eюююю044E044E	I
    //   347: getstatic 253	kkkkkk/tttjtt$tjtttt$vddddd:bюю044E044E044Eююю044E044E	I
    //   350: if_icmplt +23 -> 373
    //   353: aload_0
    //   354: getfield 133	kkkkkk/faafaf$aaffaf:b0422042204220422Т0422042204220422Т	Landroid/content/Context;
    //   357: invokestatic 259	com/threatmetrix/TrustDefender/internal/R:for	(Landroid/content/Context;)Ljava/util/HashMap;
    //   360: astore_0
    //   361: aload_0
    //   362: ifnull +11 -> 373
    //   365: aload 5
    //   367: aload_0
    //   368: invokeinterface 263 2 0
    //   373: invokestatic 266	kkkkkk/tttjtt$jtjttt:b043Aкк043Aк043A043Aккк	()Z
    //   376: ifne +9 -> 385
    //   379: invokestatic 269	kkkkkk/tttjtt$jtjttt:b043A043Aк043Aк043A043Aккк	()Z
    //   382: ifeq +126 -> 508
    //   385: aload 6
    //   387: invokevirtual 273	android/telephony/TelephonyManager:getCellLocation	()Landroid/telephony/CellLocation;
    //   390: astore_0
    //   391: aload_0
    //   392: ifnull +116 -> 508
    //   395: aload_0
    //   396: instanceof 275
    //   399: ifeq +378 -> 777
    //   402: aload 6
    //   404: invokevirtual 273	android/telephony/TelephonyManager:getCellLocation	()Landroid/telephony/CellLocation;
    //   407: checkcast 275	android/telephony/gsm/GsmCellLocation
    //   410: astore_0
    //   411: aload_0
    //   412: invokevirtual 278	android/telephony/gsm/GsmCellLocation:getLac	()I
    //   415: istore_1
    //   416: iload_1
    //   417: iconst_m1
    //   418: if_icmpeq +24 -> 442
    //   421: aload 5
    //   423: ldc_w 280
    //   426: bipush 80
    //   428: iconst_1
    //   429: invokestatic 86	kkkkkk/gguuuu:bккккк043Aкк043A043A	(Ljava/lang/String;CC)Ljava/lang/String;
    //   432: iload_1
    //   433: invokestatic 284	java/lang/String:valueOf	(I)Ljava/lang/String;
    //   436: invokeinterface 227 3 0
    //   441: pop
    //   442: aload_0
    //   443: invokevirtual 287	android/telephony/gsm/GsmCellLocation:getCid	()I
    //   446: istore_1
    //   447: iload_1
    //   448: iconst_m1
    //   449: if_icmpeq +28 -> 477
    //   452: aload 5
    //   454: ldc_w 289
    //   457: sipush 162
    //   460: sipush 215
    //   463: iconst_3
    //   464: invokestatic 66	kkkkkk/gguuuu:bк043Aккк043Aкк043A043A	(Ljava/lang/String;CCC)Ljava/lang/String;
    //   467: iload_1
    //   468: invokestatic 284	java/lang/String:valueOf	(I)Ljava/lang/String;
    //   471: invokeinterface 227 3 0
    //   476: pop
    //   477: aload_0
    //   478: invokevirtual 292	android/telephony/gsm/GsmCellLocation:getPsc	()I
    //   481: istore_1
    //   482: iload_1
    //   483: iconst_m1
    //   484: if_icmpeq +24 -> 508
    //   487: aload 5
    //   489: ldc_w 294
    //   492: bipush 117
    //   494: iconst_2
    //   495: invokestatic 86	kkkkkk/gguuuu:bккккк043Aкк043A043A	(Ljava/lang/String;CC)Ljava/lang/String;
    //   498: iload_1
    //   499: invokestatic 284	java/lang/String:valueOf	(I)Ljava/lang/String;
    //   502: invokeinterface 227 3 0
    //   507: pop
    //   508: invokestatic 297	kkkkkk/tttjtt$jtjttt:b043Aк043Aкк043A043Aккк	()Z
    //   511: ifeq +483 -> 994
    //   514: ldc_w 299
    //   517: bipush 31
    //   519: sipush 139
    //   522: iconst_3
    //   523: invokestatic 66	kkkkkk/gguuuu:bк043Aккк043Aкк043A043A	(Ljava/lang/String;CCC)Ljava/lang/String;
    //   526: astore_0
    //   527: goto +551 -> 1078
    //   530: ldc -57
    //   532: aload_0
    //   533: iconst_0
    //   534: anewarray 112	java/lang/Class
    //   537: invokestatic 118	kkkkkk/faaaff:b043A043Aк043A043Aк043A043Aк043A	(Ljava/lang/Class;Ljava/lang/String;[Ljava/lang/Class;)Ljava/lang/reflect/Method;
    //   540: astore_0
    //   541: aload_0
    //   542: ifnull +507 -> 1049
    //   545: invokestatic 99	kkkkkk/faafaf:bк043Aкк043Aкк043Aк043A	()I
    //   548: istore_1
    //   549: iload_1
    //   550: getstatic 92	kkkkkk/faafaf:b04220422Т0422Т0422042204220422Т	I
    //   553: iload_1
    //   554: iadd
    //   555: imul
    //   556: getstatic 94	kkkkkk/faafaf:bТТ04220422Т0422042204220422Т	I
    //   559: irem
    //   560: tableswitch	default:+20->580, 0:+32->592
    //   580: invokestatic 99	kkkkkk/faafaf:bк043Aкк043Aкк043Aк043A	()I
    //   583: putstatic 90	kkkkkk/faafaf:b0422ТТ0422Т0422042204220422Т	I
    //   586: invokestatic 99	kkkkkk/faafaf:bк043Aкк043Aкк043Aк043A	()I
    //   589: putstatic 96	kkkkkk/faafaf:bТ0422Т0422Т0422042204220422Т	I
    //   592: aload 6
    //   594: aload_0
    //   595: iconst_0
    //   596: anewarray 4	java/lang/Object
    //   599: invokestatic 303	kkkkkk/faaaff:bк043A043A043A043Aк043A043Aк043A	(Ljava/lang/Object;Ljava/lang/reflect/Method;[Ljava/lang/Object;)Ljava/lang/Object;
    //   602: astore_0
    //   603: aload_0
    //   604: ifnull +445 -> 1049
    //   607: aload_0
    //   608: instanceof 305
    //   611: ifeq +438 -> 1049
    //   614: aload_0
    //   615: checkcast 305	java/util/List
    //   618: astore_0
    //   619: aload_0
    //   620: ifnull +374 -> 994
    //   623: aload_0
    //   624: invokeinterface 308 1 0
    //   629: ifle +365 -> 994
    //   632: aload_0
    //   633: invokeinterface 312 1 0
    //   638: astore_0
    //   639: aload_0
    //   640: invokeinterface 317 1 0
    //   645: ifeq +349 -> 994
    //   648: aload_0
    //   649: invokeinterface 321 1 0
    //   654: checkcast 323	android/telephony/NeighboringCellInfo
    //   657: astore 6
    //   659: aload 6
    //   661: invokevirtual 324	android/telephony/NeighboringCellInfo:getCid	()I
    //   664: iconst_m1
    //   665: if_icmpeq -26 -> 639
    //   668: aload 6
    //   670: invokevirtual 327	android/telephony/NeighboringCellInfo:getRssi	()I
    //   673: bipush 99
    //   675: if_icmpeq -36 -> 639
    //   678: aload 6
    //   680: invokevirtual 324	android/telephony/NeighboringCellInfo:getCid	()I
    //   683: invokestatic 284	java/lang/String:valueOf	(I)Ljava/lang/String;
    //   686: aload 5
    //   688: ldc_w 329
    //   691: sipush 169
    //   694: sipush 242
    //   697: iconst_3
    //   698: invokestatic 66	kkkkkk/gguuuu:bк043Aккк043Aкк043A043A	(Ljava/lang/String;CCC)Ljava/lang/String;
    //   701: invokeinterface 332 2 0
    //   706: checkcast 114	java/lang/String
    //   709: invokevirtual 336	java/lang/String:equalsIgnoreCase	(Ljava/lang/String;)Z
    //   712: ifne +36 -> 748
    //   715: aload 6
    //   717: invokevirtual 324	android/telephony/NeighboringCellInfo:getCid	()I
    //   720: invokestatic 284	java/lang/String:valueOf	(I)Ljava/lang/String;
    //   723: aload 5
    //   725: ldc_w 338
    //   728: bipush 33
    //   730: iconst_5
    //   731: invokestatic 86	kkkkkk/gguuuu:bккккк043Aкк043A043A	(Ljava/lang/String;CC)Ljava/lang/String;
    //   734: invokeinterface 332 2 0
    //   739: checkcast 114	java/lang/String
    //   742: invokevirtual 336	java/lang/String:equalsIgnoreCase	(Ljava/lang/String;)Z
    //   745: ifeq -106 -> 639
    //   748: aload 5
    //   750: ldc_w 340
    //   753: sipush 245
    //   756: iconst_0
    //   757: invokestatic 86	kkkkkk/gguuuu:bккккк043Aкк043A043A	(Ljava/lang/String;CC)Ljava/lang/String;
    //   760: aload 6
    //   762: invokevirtual 327	android/telephony/NeighboringCellInfo:getRssi	()I
    //   765: invokestatic 284	java/lang/String:valueOf	(I)Ljava/lang/String;
    //   768: invokeinterface 227 3 0
    //   773: pop
    //   774: goto -135 -> 639
    //   777: aload_0
    //   778: instanceof 342
    //   781: ifeq -273 -> 508
    //   784: aload 6
    //   786: invokevirtual 273	android/telephony/TelephonyManager:getCellLocation	()Landroid/telephony/CellLocation;
    //   789: checkcast 342	android/telephony/cdma/CdmaCellLocation
    //   792: astore_0
    //   793: aload_0
    //   794: invokevirtual 345	android/telephony/cdma/CdmaCellLocation:getSystemId	()I
    //   797: istore_1
    //   798: iload_1
    //   799: iconst_m1
    //   800: if_icmpeq +27 -> 827
    //   803: aload 5
    //   805: ldc_w 347
    //   808: sipush 176
    //   811: bipush 42
    //   813: iconst_3
    //   814: invokestatic 66	kkkkkk/gguuuu:bк043Aккк043Aкк043A043A	(Ljava/lang/String;CCC)Ljava/lang/String;
    //   817: iload_1
    //   818: invokestatic 284	java/lang/String:valueOf	(I)Ljava/lang/String;
    //   821: invokeinterface 227 3 0
    //   826: pop
    //   827: aload_0
    //   828: invokevirtual 350	android/telephony/cdma/CdmaCellLocation:getBaseStationId	()I
    //   831: istore_1
    //   832: iload_1
    //   833: iconst_m1
    //   834: if_icmpeq +28 -> 862
    //   837: aload 5
    //   839: ldc_w 352
    //   842: sipush 255
    //   845: sipush 246
    //   848: iconst_3
    //   849: invokestatic 66	kkkkkk/gguuuu:bк043Aккк043Aкк043A043A	(Ljava/lang/String;CCC)Ljava/lang/String;
    //   852: iload_1
    //   853: invokestatic 284	java/lang/String:valueOf	(I)Ljava/lang/String;
    //   856: invokeinterface 227 3 0
    //   861: pop
    //   862: aload_0
    //   863: invokevirtual 355	android/telephony/cdma/CdmaCellLocation:getBaseStationLatitude	()I
    //   866: istore_1
    //   867: iload_1
    //   868: ldc_w 356
    //   871: if_icmpeq +24 -> 895
    //   874: aload 5
    //   876: ldc_w 358
    //   879: bipush 55
    //   881: iconst_1
    //   882: invokestatic 86	kkkkkk/gguuuu:bккккк043Aкк043A043A	(Ljava/lang/String;CC)Ljava/lang/String;
    //   885: iload_1
    //   886: invokestatic 284	java/lang/String:valueOf	(I)Ljava/lang/String;
    //   889: invokeinterface 227 3 0
    //   894: pop
    //   895: aload_0
    //   896: invokevirtual 361	android/telephony/cdma/CdmaCellLocation:getBaseStationLongitude	()I
    //   899: istore_1
    //   900: iload_1
    //   901: ldc_w 356
    //   904: if_icmpeq -396 -> 508
    //   907: getstatic 90	kkkkkk/faafaf:b0422ТТ0422Т0422042204220422Т	I
    //   910: istore_2
    //   911: iload_2
    //   912: getstatic 92	kkkkkk/faafaf:b04220422Т0422Т0422042204220422Т	I
    //   915: iload_2
    //   916: iadd
    //   917: imul
    //   918: getstatic 94	kkkkkk/faafaf:bТТ04220422Т0422042204220422Т	I
    //   921: irem
    //   922: tableswitch	default:+18->940, 0:+28->950
    //   940: bipush 10
    //   942: putstatic 90	kkkkkk/faafaf:b0422ТТ0422Т0422042204220422Т	I
    //   945: bipush 89
    //   947: putstatic 96	kkkkkk/faafaf:bТ0422Т0422Т0422042204220422Т	I
    //   950: aload 5
    //   952: ldc_w 363
    //   955: sipush 166
    //   958: iconst_5
    //   959: invokestatic 86	kkkkkk/gguuuu:bккккк043Aкк043A043A	(Ljava/lang/String;CC)Ljava/lang/String;
    //   962: iload_1
    //   963: invokestatic 284	java/lang/String:valueOf	(I)Ljava/lang/String;
    //   966: invokeinterface 227 3 0
    //   971: pop
    //   972: goto -464 -> 508
    //   975: astore_0
    //   976: aconst_null
    //   977: astore_0
    //   978: goto -587 -> 391
    //   981: astore_0
    //   982: getstatic 38	kkkkkk/faafaf:bТ04220422ТТ0422042204220422Т	Ljava/lang/String;
    //   985: aload_0
    //   986: invokevirtual 366	java/lang/Exception:toString	()Ljava/lang/String;
    //   989: invokestatic 370	kkkkkk/fafffa:b043Aккк043Aк043Aкк043A	(Ljava/lang/String;Ljava/lang/String;)V
    //   992: aconst_null
    //   993: areturn
    //   994: aload 5
    //   996: invokeinterface 371 1 0
    //   1001: iconst_3
    //   1002: if_icmplt -996 -> 6
    //   1005: aload 5
    //   1007: invokevirtual 372	java/lang/Object:toString	()Ljava/lang/String;
    //   1010: areturn
    //   1011: astore 7
    //   1013: getstatic 38	kkkkkk/faafaf:bТ04220422ТТ0422042204220422Т	Ljava/lang/String;
    //   1016: aload 7
    //   1018: invokevirtual 366	java/lang/Exception:toString	()Ljava/lang/String;
    //   1021: invokestatic 370	kkkkkk/fafffa:b043Aккк043Aк043Aкк043A	(Ljava/lang/String;Ljava/lang/String;)V
    //   1024: goto -756 -> 268
    //   1027: astore_0
    //   1028: aload_0
    //   1029: invokevirtual 375	java/lang/SecurityException:getMessage	()Ljava/lang/String;
    //   1032: pop
    //   1033: aconst_null
    //   1034: astore_0
    //   1035: goto -416 -> 619
    //   1038: astore_0
    //   1039: getstatic 38	kkkkkk/faafaf:bТ04220422ТТ0422042204220422Т	Ljava/lang/String;
    //   1042: aload_0
    //   1043: invokevirtual 366	java/lang/Exception:toString	()Ljava/lang/String;
    //   1046: invokestatic 370	kkkkkk/fafffa:b043Aккк043Aк043Aкк043A	(Ljava/lang/String;Ljava/lang/String;)V
    //   1049: aconst_null
    //   1050: astore_0
    //   1051: goto -432 -> 619
    //   1054: astore_0
    //   1055: getstatic 38	kkkkkk/faafaf:bТ04220422ТТ0422042204220422Т	Ljava/lang/String;
    //   1058: aload_0
    //   1059: invokevirtual 366	java/lang/Exception:toString	()Ljava/lang/String;
    //   1062: invokestatic 370	kkkkkk/fafffa:b043Aккк043Aк043Aкк043A	(Ljava/lang/String;Ljava/lang/String;)V
    //   1065: aconst_null
    //   1066: astore_0
    //   1067: goto -676 -> 391
    //   1070: astore_0
    //   1071: aconst_null
    //   1072: areturn
    //   1073: astore 7
    //   1075: goto -807 -> 268
    //   1078: iconst_0
    //   1079: tableswitch	default:+21->1100, 0:+-549->530, 1:+-1->1078
    //   1100: iconst_1
    //   1101: tableswitch	default:+23->1124, 0:+-23->1078, 1:+-571->530
    //   1124: goto -24 -> 1100
    // Local variable table:
    //   start	length	slot	name	signature
    //   0	1127	0	paramAaffaf	aaffaf
    //   39	924	1	i	int
    //   910	8	2	j	int
    //   311	25	3	bool1	boolean
    //   333	7	4	bool2	boolean
    //   29	977	5	localObject1	Object
    //   91	694	6	localObject2	Object
    //   107	206	7	localObject3	Object
    //   1011	6	7	localException	Exception
    //   1073	1	7	localSecurityException	SecurityException
    //   114	147	8	str1	String
    //   152	73	9	str2	String
    // Exception table:
    //   from	to	target	type
    //   385	391	975	java/lang/SecurityException
    //   8	31	981	java/lang/Exception
    //   78	93	981	java/lang/Exception
    //   102	116	1011	java/lang/Exception
    //   147	154	1011	java/lang/Exception
    //   159	193	1011	java/lang/Exception
    //   198	232	1011	java/lang/Exception
    //   237	268	1011	java/lang/Exception
    //   514	527	1027	java/lang/SecurityException
    //   530	541	1027	java/lang/SecurityException
    //   592	603	1027	java/lang/SecurityException
    //   607	619	1027	java/lang/SecurityException
    //   514	527	1038	java/lang/Exception
    //   530	541	1038	java/lang/Exception
    //   592	603	1038	java/lang/Exception
    //   607	619	1038	java/lang/Exception
    //   385	391	1054	java/lang/Exception
    //   8	31	1070	java/lang/SecurityException
    //   78	93	1070	java/lang/SecurityException
    //   102	116	1073	java/lang/SecurityException
    //   147	154	1073	java/lang/SecurityException
    //   159	193	1073	java/lang/SecurityException
    //   198	232	1073	java/lang/SecurityException
    //   237	268	1073	java/lang/SecurityException
  }
  
  public static long b043A043A043Aкк043Aк043Aк043A()
  {
    long l3 = 0L;
    faffff localFaffff = new faffff(Environment.getDataDirectory().getPath());
    Object localObject;
    long l1;
    if (faffff.bТТ0422Т042204220422ТТ0422 != null)
    {
      localObject = (Long)faffff.bк043A043A043A043Aк043A043Aк043A(localFaffff.bТ0422Т0422042204220422ТТ0422, faffff.bТТ0422Т042204220422ТТ0422, new Object[0]);
      if (localObject != null) {
        l1 = ((Long)localObject).longValue();
      }
    }
    for (;;)
    {
      long l4 = localFaffff.b043Aк043A043A043A043A043A043Aк043A();
      if ((b0422ТТ0422Т0422042204220422Т + b04220422Т0422Т0422042204220422Т) * b0422ТТ0422Т0422042204220422Т % bТТ04220422Т0422042204220422Т != bТ0422Т0422Т0422042204220422Т)
      {
        b0422ТТ0422Т0422042204220422Т = bк043Aкк043Aкк043Aк043A();
        bТ0422Т0422Т0422042204220422Т = bк043Aкк043Aкк043Aк043A();
      }
      long l2 = l3;
      if (l1 != 0L)
      {
        l2 = l3;
        if (l4 != 0L) {
          l2 = (l1 * l4 >> 20 << 20) / 10L * 10L;
        }
      }
      fafffa.b043Aккк043Aк043Aкк043A(bТ04220422ТТ0422042204220422Т, gguuuu.bккккк043Aкк043A043A("Tqp*|xhij$rp!tgc\035lcig]\027", '÷', '\003') + l2);
      if ((b0422ТТ0422Т0422042204220422Т + b04220422Т0422Т0422042204220422Т) * b0422ТТ0422Т0422042204220422Т % bТТ04220422Т0422042204220422Т != bТ0422Т0422Т0422042204220422Т)
      {
        b0422ТТ0422Т0422042204220422Т = 10;
        bТ0422Т0422Т0422042204220422Т = bк043Aкк043Aкк043Aк043A();
      }
      return l2;
      if (faffff.bТТТ0422042204220422ТТ0422 != null)
      {
        localObject = (Integer)faffff.bк043A043A043A043Aк043A043Aк043A(localFaffff.bТ0422Т0422042204220422ТТ0422, faffff.bТТТ0422042204220422ТТ0422, new Object[0]);
        if (localObject != null)
        {
          l1 = ((Integer)localObject).intValue();
          continue;
        }
      }
      l1 = 0L;
    }
  }
  
  /* Error */
  public static String b043A043Aк043A043Aкк043Aк043A()
  {
    // Byte code:
    //   0: iconst_1
    //   1: tableswitch	default:+23->24, 0:+-1->0, 1:+50->51
    //   24: iconst_1
    //   25: tableswitch	default:+23->48, 0:+-25->0, 1:+26->51
    //   48: goto -24 -> 24
    //   51: getstatic 90	kkkkkk/faafaf:b0422ТТ0422Т0422042204220422Т	I
    //   54: istore_0
    //   55: getstatic 92	kkkkkk/faafaf:b04220422Т0422Т0422042204220422Т	I
    //   58: istore_1
    //   59: getstatic 90	kkkkkk/faafaf:b0422ТТ0422Т0422042204220422Т	I
    //   62: istore_2
    //   63: invokestatic 136	kkkkkk/faafaf:b043Aккк043Aкк043Aк043A	()I
    //   66: istore_3
    //   67: getstatic 96	kkkkkk/faafaf:bТ0422Т0422Т0422042204220422Т	I
    //   70: istore 4
    //   72: iload_0
    //   73: iload_1
    //   74: iadd
    //   75: iload_2
    //   76: imul
    //   77: iload_3
    //   78: irem
    //   79: iload 4
    //   81: if_icmpeq +57 -> 138
    //   84: getstatic 90	kkkkkk/faafaf:b0422ТТ0422Т0422042204220422Т	I
    //   87: istore_0
    //   88: iload_0
    //   89: getstatic 92	kkkkkk/faafaf:b04220422Т0422Т0422042204220422Т	I
    //   92: iload_0
    //   93: iadd
    //   94: imul
    //   95: getstatic 94	kkkkkk/faafaf:bТТ04220422Т0422042204220422Т	I
    //   98: irem
    //   99: tableswitch	default:+17->116, 0:+28->127
    //   116: invokestatic 99	kkkkkk/faafaf:bк043Aкк043Aкк043Aк043A	()I
    //   119: putstatic 90	kkkkkk/faafaf:b0422ТТ0422Т0422042204220422Т	I
    //   122: bipush 93
    //   124: putstatic 96	kkkkkk/faafaf:bТ0422Т0422Т0422042204220422Т	I
    //   127: invokestatic 99	kkkkkk/faafaf:bк043Aкк043Aкк043Aк043A	()I
    //   130: putstatic 90	kkkkkk/faafaf:b0422ТТ0422Т0422042204220422Т	I
    //   133: bipush 78
    //   135: putstatic 96	kkkkkk/faafaf:bТ0422Т0422Т0422042204220422Т	I
    //   138: ldc_w 429
    //   141: ldc_w 431
    //   144: sipush 164
    //   147: bipush 34
    //   149: iconst_0
    //   150: invokestatic 436	jjjjjj/kjjjjj:b0411ББ0411041104110411Б04110411	(Ljava/lang/String;CCC)Ljava/lang/String;
    //   153: iconst_0
    //   154: anewarray 112	java/lang/Class
    //   157: invokevirtual 440	java/lang/Class:getMethod	(Ljava/lang/String;[Ljava/lang/Class;)Ljava/lang/reflect/Method;
    //   160: astore 6
    //   162: aload 6
    //   164: aconst_null
    //   165: iconst_0
    //   166: anewarray 4	java/lang/Object
    //   169: invokevirtual 446	java/lang/reflect/Method:invoke	(Ljava/lang/Object;[Ljava/lang/Object;)Ljava/lang/Object;
    //   172: astore 6
    //   174: aload 6
    //   176: checkcast 448	java/lang/Boolean
    //   179: invokevirtual 451	java/lang/Boolean:booleanValue	()Z
    //   182: istore 5
    //   184: iload 5
    //   186: invokestatic 454	java/lang/String:valueOf	(Z)Ljava/lang/String;
    //   189: areturn
    //   190: astore 6
    //   192: aload 6
    //   194: invokevirtual 458	java/lang/reflect/InvocationTargetException:getCause	()Ljava/lang/Throwable;
    //   197: athrow
    //   198: astore 6
    //   200: aload 6
    //   202: athrow
    //   203: astore 6
    //   205: aload 6
    //   207: athrow
    // Local variable table:
    //   start	length	slot	name	signature
    //   54	41	0	i	int
    //   58	17	1	j	int
    //   62	15	2	k	int
    //   66	13	3	m	int
    //   70	12	4	n	int
    //   182	3	5	bool	boolean
    //   160	15	6	localObject	Object
    //   190	3	6	localInvocationTargetException	java.lang.reflect.InvocationTargetException
    //   198	3	6	localException1	Exception
    //   203	3	6	localException2	Exception
    // Exception table:
    //   from	to	target	type
    //   162	174	190	java/lang/reflect/InvocationTargetException
    //   51	72	198	java/lang/Exception
    //   162	174	198	java/lang/Exception
    //   184	190	198	java/lang/Exception
    //   192	198	198	java/lang/Exception
    //   127	138	203	java/lang/Exception
  }
  
  public static String b043A043Aк043Aк043Aк043Aк043A(aaffaf paramAaffaf)
  {
    Object localObject = new tttjtt.jjtttt(paramAaffaf);
    int i;
    label68:
    label122:
    StringBuilder localStringBuilder1;
    StringBuilder localStringBuilder2;
    if (((tttjtt.jjtttt)localObject).bюююю044E044E044E044Eю044E != null)
    {
      localObject = ((tttjtt.jjtttt)localObject).bюююю044E044E044E044Eю044E.packageName;
      paramAaffaf = new tttjtt.jjjttt(new tttjtt(), paramAaffaf.b0422042204220422Т0422042204220422Т, (String)localObject, tttjtt.ddvddd.bюю044Eю044E044Eюю044E044E);
      if ((!tttjtt.ddvddd.bккк043Aккк043Aкк()) || (paramAaffaf.b044E044Eю044Eюю044E044Eю044E == null)) {
        break label435;
      }
      i = paramAaffaf.b044E044Eю044Eюю044E044Eю044E.versionCode;
      if (!tttjtt.ddvddd.b043Aк043Aкккк043Aкк()) {
        break label440;
      }
      if ((b0422ТТ0422Т0422042204220422Т + b04220422Т0422Т0422042204220422Т) * b0422ТТ0422Т0422042204220422Т % bТТ04220422Т0422042204220422Т != bТ0422Т0422Т0422042204220422Т)
      {
        b0422ТТ0422Т0422042204220422Т = bк043Aкк043Aкк043Aк043A();
        bТ0422Т0422Т0422042204220422Т = bк043Aкк043Aкк043Aк043A();
      }
      if (paramAaffaf.b044E044Eю044Eюю044E044Eю044E == null) {
        break label440;
      }
      paramAaffaf = paramAaffaf.b044E044Eю044Eюю044E044Eю044E.versionName;
      localStringBuilder1 = new StringBuilder();
      localStringBuilder2 = localStringBuilder1.append((String)localObject).append(gguuuu.bккккк043Aкк043A043A("9", '¿', '\003'));
      localObject = paramAaffaf;
      if (paramAaffaf == null) {
        localObject = gguuuu.bк043Aккк043Aкк043A043A("A", '¸', 'M', '\000');
      }
      localObject = localStringBuilder2.append((String)localObject).append(gguuuu.bк043Aккк043Aкк043A043A("H", '?', 'Ì', '\000'));
      if (i != -1) {
        break label445;
      }
    }
    label435:
    label440:
    label445:
    for (paramAaffaf = gguuuu.bккккк043Aкк043A043A("n", '½', '\005');; paramAaffaf = Integer.valueOf(i))
    {
      ((StringBuilder)localObject).append(paramAaffaf);
      localObject = dvdddv.bк043A043A043Aк043Aкк043Aк().b043Aккккк043Aк043Aк();
      if ((b0422ТТ0422Т0422042204220422Т + b04220422Т0422Т0422042204220422Т) * b0422ТТ0422Т0422042204220422Т % bТТ04220422Т0422042204220422Т != bТ0422Т0422Т0422042204220422Т)
      {
        b0422ТТ0422Т0422042204220422Т = bк043Aкк043Aкк043Aк043A();
        bТ0422Т0422Т0422042204220422Т = 81;
      }
      localStringBuilder2 = localStringBuilder1.append(gguuuu.bккккк043Aкк043A043A("-", '¸', '\004'));
      paramAaffaf = (aaffaf)localObject;
      if (localObject == null) {
        paramAaffaf = gguuuu.bккккк043Aкк043A043A("5", '\004', '\004');
      }
      switch (1)
      {
      case 0: 
      default: 
        for (;;)
        {
          switch (1)
          {
          }
        }
      }
      localStringBuilder2.append(paramAaffaf);
      switch (1)
      {
      case 0: 
      default: 
        for (;;)
        {
          switch (0)
          {
          }
        }
      }
      fafffa.b043Aккк043Aк043Aкк043A(bТ04220422ТТ0422042204220422Т, gguuuu.bккккк043Aкк043A043A("\0055631,+?5<<n\031?8Bs", 'ê', '\001') + localStringBuilder1.toString());
      return localStringBuilder1.toString();
      localObject = "";
      break;
      i = -1;
      break label68;
      paramAaffaf = null;
      break label122;
    }
  }
  
  public static int b043A043Aк043Aккк043Aк043A()
  {
    return 1;
  }
  
  /* Error */
  @Nonnull
  private static String b043A043Aкк043A043Aк043Aк043A()
  {
    // Byte code:
    //   0: new 538	java/util/ArrayList
    //   3: dup
    //   4: invokespecial 539	java/util/ArrayList:<init>	()V
    //   7: astore_1
    //   8: getstatic 90	kkkkkk/faafaf:b0422ТТ0422Т0422042204220422Т	I
    //   11: getstatic 92	kkkkkk/faafaf:b04220422Т0422Т0422042204220422Т	I
    //   14: iadd
    //   15: getstatic 90	kkkkkk/faafaf:b0422ТТ0422Т0422042204220422Т	I
    //   18: imul
    //   19: getstatic 94	kkkkkk/faafaf:bТТ04220422Т0422042204220422Т	I
    //   22: irem
    //   23: getstatic 96	kkkkkk/faafaf:bТ0422Т0422Т0422042204220422Т	I
    //   26: if_icmpeq +14 -> 40
    //   29: bipush 59
    //   31: putstatic 90	kkkkkk/faafaf:b0422ТТ0422Т0422042204220422Т	I
    //   34: invokestatic 99	kkkkkk/faafaf:bк043Aкк043Aкк043Aк043A	()I
    //   37: putstatic 96	kkkkkk/faafaf:bТ0422Т0422Т0422042204220422Т	I
    //   40: aload_1
    //   41: iconst_3
    //   42: anewarray 114	java/lang/String
    //   45: dup
    //   46: iconst_0
    //   47: ldc_w 541
    //   50: bipush 25
    //   52: iconst_0
    //   53: invokestatic 86	kkkkkk/gguuuu:bккккк043Aкк043A043A	(Ljava/lang/String;CC)Ljava/lang/String;
    //   56: aastore
    //   57: dup
    //   58: iconst_1
    //   59: ldc_w 543
    //   62: bipush 64
    //   64: bipush 122
    //   66: iconst_1
    //   67: invokestatic 66	kkkkkk/gguuuu:bк043Aккк043Aкк043A043A	(Ljava/lang/String;CCC)Ljava/lang/String;
    //   70: aastore
    //   71: dup
    //   72: iconst_2
    //   73: ldc_w 545
    //   76: bipush 29
    //   78: bipush 42
    //   80: iconst_2
    //   81: invokestatic 66	kkkkkk/gguuuu:bк043Aккк043Aкк043A043A	(Ljava/lang/String;CCC)Ljava/lang/String;
    //   84: aastore
    //   85: invokestatic 551	java/util/Collections:addAll	(Ljava/util/Collection;[Ljava/lang/Object;)Z
    //   88: pop
    //   89: new 553	java/util/HashSet
    //   92: dup
    //   93: invokespecial 554	java/util/HashSet:<init>	()V
    //   96: astore_2
    //   97: aload_2
    //   98: aload_1
    //   99: invokeinterface 559 2 0
    //   104: pop
    //   105: ldc_w 561
    //   108: sipush 233
    //   111: sipush 164
    //   114: iconst_0
    //   115: invokestatic 66	kkkkkk/gguuuu:bк043Aккк043Aкк043A043A	(Ljava/lang/String;CCC)Ljava/lang/String;
    //   118: astore_3
    //   119: ldc_w 563
    //   122: sipush 164
    //   125: iconst_0
    //   126: invokestatic 86	kkkkkk/gguuuu:bккккк043Aкк043A043A	(Ljava/lang/String;CC)Ljava/lang/String;
    //   129: astore 4
    //   131: aload_3
    //   132: aload_2
    //   133: aload 4
    //   135: invokestatic 567	kkkkkk/faafaf:b043Aк043Aкк043Aк043Aк043A	(Ljava/lang/String;Ljava/util/Set;Ljava/lang/String;)Ljava/util/HashMap;
    //   138: astore_2
    //   139: getstatic 38	kkkkkk/faafaf:bТ04220422ТТ0422042204220422Т	Ljava/lang/String;
    //   142: astore_3
    //   143: new 413	java/lang/StringBuilder
    //   146: dup
    //   147: ldc_w 569
    //   150: bipush 120
    //   152: sipush 205
    //   155: iconst_2
    //   156: invokestatic 66	kkkkkk/gguuuu:bк043Aккк043Aкк043A043A	(Ljava/lang/String;CCC)Ljava/lang/String;
    //   159: invokespecial 416	java/lang/StringBuilder:<init>	(Ljava/lang/String;)V
    //   162: astore 4
    //   164: aload_3
    //   165: aload 4
    //   167: aload_2
    //   168: invokevirtual 516	java/lang/StringBuilder:append	(Ljava/lang/Object;)Ljava/lang/StringBuilder;
    //   171: invokevirtual 421	java/lang/StringBuilder:toString	()Ljava/lang/String;
    //   174: invokestatic 370	kkkkkk/fafffa:b043Aккк043Aк043Aкк043A	(Ljava/lang/String;Ljava/lang/String;)V
    //   177: new 413	java/lang/StringBuilder
    //   180: dup
    //   181: invokespecial 502	java/lang/StringBuilder:<init>	()V
    //   184: astore_3
    //   185: aload_1
    //   186: invokevirtual 570	java/util/ArrayList:iterator	()Ljava/util/Iterator;
    //   189: astore_1
    //   190: iconst_1
    //   191: istore_0
    //   192: aload_1
    //   193: invokeinterface 317 1 0
    //   198: ifeq +69 -> 267
    //   201: aload_1
    //   202: invokeinterface 321 1 0
    //   207: checkcast 114	java/lang/String
    //   210: astore 4
    //   212: iload_0
    //   213: ifne +18 -> 231
    //   216: aload_3
    //   217: ldc_w 572
    //   220: sipush 173
    //   223: iconst_1
    //   224: invokestatic 86	kkkkkk/gguuuu:bккккк043Aкк043A043A	(Ljava/lang/String;CC)Ljava/lang/String;
    //   227: invokevirtual 505	java/lang/StringBuilder:append	(Ljava/lang/String;)Ljava/lang/StringBuilder;
    //   230: pop
    //   231: aload_2
    //   232: aload 4
    //   234: invokeinterface 332 2 0
    //   239: checkcast 114	java/lang/String
    //   242: astore 4
    //   244: aload 4
    //   246: ifnull +10 -> 256
    //   249: aload_3
    //   250: aload 4
    //   252: invokevirtual 505	java/lang/StringBuilder:append	(Ljava/lang/String;)Ljava/lang/StringBuilder;
    //   255: pop
    //   256: iconst_0
    //   257: istore_0
    //   258: goto -66 -> 192
    //   261: astore_1
    //   262: aload_1
    //   263: athrow
    //   264: astore_1
    //   265: aload_1
    //   266: athrow
    //   267: aload_3
    //   268: invokevirtual 421	java/lang/StringBuilder:toString	()Ljava/lang/String;
    //   271: astore_1
    //   272: aload_1
    //   273: areturn
    // Local variable table:
    //   start	length	slot	name	signature
    //   191	67	0	i	int
    //   7	195	1	localObject1	Object
    //   261	2	1	localException1	Exception
    //   264	2	1	localException2	Exception
    //   271	2	1	str	String
    //   96	136	2	localObject2	Object
    //   118	150	3	localObject3	Object
    //   129	122	4	localObject4	Object
    // Exception table:
    //   from	to	target	type
    //   0	8	261	java/lang/Exception
    //   40	131	261	java/lang/Exception
    //   164	190	261	java/lang/Exception
    //   192	212	261	java/lang/Exception
    //   131	164	264	java/lang/Exception
    //   216	231	264	java/lang/Exception
    //   231	244	264	java/lang/Exception
    //   249	256	264	java/lang/Exception
    //   267	272	264	java/lang/Exception
  }
  
  @Nonnull
  public static vdddvd.vvddvd b043A043Aкк043Aкк043Aк043A()
  {
    try
    {
      vdddvd.vvddvd localVvddvd = afaaaf.b043Aкк043Aк043A043Aкк043A();
      if ((b0422ТТ0422Т0422042204220422Т + b04220422Т0422Т0422042204220422Т) * b0422ТТ0422Т0422042204220422Т % bТТ04220422Т0422042204220422Т != bТ0422Т0422Т0422042204220422Т)
      {
        int i = b0422ТТ0422Т0422042204220422Т;
        switch (i * (b04220422Т0422Т0422042204220422Т + i) % bТТ04220422Т0422042204220422Т)
        {
        default: 
          b0422ТТ0422Т0422042204220422Т = 57;
          bТ0422Т0422Т0422042204220422Т = bк043Aкк043Aкк043Aк043A();
        }
        b0422ТТ0422Т0422042204220422Т = bк043Aкк043Aкк043Aк043A();
        bТ0422Т0422Т0422042204220422Т = bк043Aкк043Aкк043Aк043A();
      }
      return localVvddvd;
    }
    catch (Exception localException)
    {
      throw localException;
    }
  }
  
  /* Error */
  public static String b043A043Aккк043Aк043Aк043A()
  {
    // Byte code:
    //   0: invokestatic 586	java/util/Locale:getDefault	()Ljava/util/Locale;
    //   3: astore_2
    //   4: new 413	java/lang/StringBuilder
    //   7: dup
    //   8: invokespecial 502	java/lang/StringBuilder:<init>	()V
    //   11: astore_1
    //   12: getstatic 90	kkkkkk/faafaf:b0422ТТ0422Т0422042204220422Т	I
    //   15: istore_0
    //   16: iload_0
    //   17: getstatic 92	kkkkkk/faafaf:b04220422Т0422Т0422042204220422Т	I
    //   20: iload_0
    //   21: iadd
    //   22: imul
    //   23: getstatic 94	kkkkkk/faafaf:bТТ04220422Т0422042204220422Т	I
    //   26: irem
    //   27: tableswitch	default:+17->44, 0:+71->98
    //   44: bipush 49
    //   46: putstatic 90	kkkkkk/faafaf:b0422ТТ0422Т0422042204220422Т	I
    //   49: bipush 86
    //   51: putstatic 96	kkkkkk/faafaf:bТ0422Т0422Т0422042204220422Т	I
    //   54: getstatic 90	kkkkkk/faafaf:b0422ТТ0422Т0422042204220422Т	I
    //   57: istore_0
    //   58: iload_0
    //   59: getstatic 92	kkkkkk/faafaf:b04220422Т0422Т0422042204220422Т	I
    //   62: iload_0
    //   63: iadd
    //   64: imul
    //   65: getstatic 94	kkkkkk/faafaf:bТТ04220422Т0422042204220422Т	I
    //   68: irem
    //   69: tableswitch	default:+19->88, 0:+29->98
    //   88: bipush 64
    //   90: putstatic 90	kkkkkk/faafaf:b0422ТТ0422Т0422042204220422Т	I
    //   93: bipush 19
    //   95: putstatic 96	kkkkkk/faafaf:bТ0422Т0422Т0422042204220422Т	I
    //   98: aload_2
    //   99: invokevirtual 589	java/util/Locale:getLanguage	()Ljava/lang/String;
    //   102: astore_3
    //   103: aload_3
    //   104: ifnull +38 -> 142
    //   107: aload_1
    //   108: aload_3
    //   109: invokevirtual 505	java/lang/StringBuilder:append	(Ljava/lang/String;)Ljava/lang/StringBuilder;
    //   112: pop
    //   113: aload_2
    //   114: invokevirtual 592	java/util/Locale:getCountry	()Ljava/lang/String;
    //   117: astore_2
    //   118: aload_2
    //   119: ifnull +23 -> 142
    //   122: aload_1
    //   123: ldc_w 594
    //   126: bipush 122
    //   128: iconst_5
    //   129: invokestatic 86	kkkkkk/gguuuu:bккккк043Aкк043A043A	(Ljava/lang/String;CC)Ljava/lang/String;
    //   132: invokevirtual 505	java/lang/StringBuilder:append	(Ljava/lang/String;)Ljava/lang/StringBuilder;
    //   135: pop
    //   136: aload_1
    //   137: aload_2
    //   138: invokevirtual 505	java/lang/StringBuilder:append	(Ljava/lang/String;)Ljava/lang/StringBuilder;
    //   141: pop
    //   142: aload_1
    //   143: invokevirtual 421	java/lang/StringBuilder:toString	()Ljava/lang/String;
    //   146: astore_1
    //   147: aload_1
    //   148: areturn
    //   149: astore_1
    //   150: aload_1
    //   151: athrow
    //   152: astore_1
    //   153: aload_1
    //   154: athrow
    // Local variable table:
    //   start	length	slot	name	signature
    //   15	50	0	i	int
    //   11	137	1	localObject1	Object
    //   149	2	1	localException1	Exception
    //   152	2	1	localException2	Exception
    //   3	135	2	localObject2	Object
    //   102	7	3	str	String
    // Exception table:
    //   from	to	target	type
    //   0	12	149	java/lang/Exception
    //   107	118	149	java/lang/Exception
    //   122	142	149	java/lang/Exception
    //   98	103	152	java/lang/Exception
    //   142	147	152	java/lang/Exception
  }
  
  public static String b043Aк043A043A043Aкк043Aк043A(@Nonnull aaffaf paramAaffaf)
  {
    throw new Runtime("d2j fail translate: java.lang.IndexOutOfBoundsException: fromIndex < 0: -1\n\tat java.util.BitSet.nextSetBit(BitSet.java:712)\n\tat com.googlecode.dex2jar.ir.ts.array.FillArrayTransformer.makeSureAllElementAreAssigned(FillArrayTransformer.java:505)\n\tat com.googlecode.dex2jar.ir.ts.array.FillArrayTransformer.transformReportChanged(FillArrayTransformer.java:123)\n\tat com.googlecode.dex2jar.ir.ts.StatedTransformer.transform(StatedTransformer.java:10)\n\tat com.googlecode.d2j.dex.Dex2jar$2.optimize(Dex2jar.java:149)\n\tat com.googlecode.d2j.dex.Dex2Asm.convertCode(Dex2Asm.java:414)\n\tat com.googlecode.d2j.dex.ExDex2Asm.convertCode(ExDex2Asm.java:42)\n\tat com.googlecode.d2j.dex.Dex2jar$2.convertCode(Dex2jar.java:128)\n\tat com.googlecode.d2j.dex.Dex2Asm.convertMethod(Dex2Asm.java:509)\n\tat com.googlecode.d2j.dex.Dex2Asm.convertClass(Dex2Asm.java:406)\n\tat com.googlecode.d2j.dex.Dex2Asm.convertDex(Dex2Asm.java:422)\n\tat com.googlecode.d2j.dex.Dex2jar.doTranslate(Dex2jar.java:172)\n\tat com.googlecode.d2j.dex.Dex2jar.to(Dex2jar.java:272)\n\tat com.googlecode.dex2jar.tools.Dex2jarCmd.doCommandLine(Dex2jarCmd.java:108)\n\tat com.googlecode.dex2jar.tools.BaseCmd.doMain(BaseCmd.java:288)\n\tat com.googlecode.dex2jar.tools.Dex2jarCmd.main(Dex2jarCmd.java:32)\n");
  }
  
  /* Error */
  public static boolean b043Aк043A043Aк043Aк043Aк043A(@Nonnull aaffaf paramAaffaf)
  {
    // Byte code:
    //   0: aload_0
    //   1: getfield 133	kkkkkk/faafaf$aaffaf:b0422042204220422Т0422042204220422Т	Landroid/content/Context;
    //   4: astore_0
    //   5: getstatic 155	kkkkkk/tttjtt$tjtttt$jttttt:bююю044Eюююю044E044E	I
    //   8: getstatic 607	kkkkkk/tttjtt$tjtttt$vddddd:b044E044E044Eю044Eююю044E044E	I
    //   11: if_icmplt +86 -> 97
    //   14: aload_0
    //   15: invokestatic 613	kkkkkk/vvvvdd:bкк043Aккк043A043Aкк	(Landroid/content/Context;)Z
    //   18: istore_1
    //   19: getstatic 90	kkkkkk/faafaf:b0422ТТ0422Т0422042204220422Т	I
    //   22: getstatic 92	kkkkkk/faafaf:b04220422Т0422Т0422042204220422Т	I
    //   25: iadd
    //   26: getstatic 90	kkkkkk/faafaf:b0422ТТ0422Т0422042204220422Т	I
    //   29: imul
    //   30: getstatic 94	kkkkkk/faafaf:bТТ04220422Т0422042204220422Т	I
    //   33: irem
    //   34: getstatic 96	kkkkkk/faafaf:bТ0422Т0422Т0422042204220422Т	I
    //   37: if_icmpeq +14 -> 51
    //   40: bipush 62
    //   42: putstatic 90	kkkkkk/faafaf:b0422ТТ0422Т0422042204220422Т	I
    //   45: invokestatic 99	kkkkkk/faafaf:bк043Aкк043Aкк043Aк043A	()I
    //   48: putstatic 96	kkkkkk/faafaf:bТ0422Т0422Т0422042204220422Т	I
    //   51: iload_1
    //   52: ireturn
    //   53: astore_0
    //   54: bipush 32
    //   56: putstatic 90	kkkkkk/faafaf:b0422ТТ0422Т0422042204220422Т	I
    //   59: goto +98 -> 157
    //   62: aload_2
    //   63: invokevirtual 366	java/lang/Exception:toString	()Ljava/lang/String;
    //   66: astore_2
    //   67: aload_0
    //   68: aload_2
    //   69: invokestatic 370	kkkkkk/fafffa:b043Aккк043Aк043Aкк043A	(Ljava/lang/String;Ljava/lang/String;)V
    //   72: goto +85 -> 157
    //   75: astore_0
    //   76: aload_0
    //   77: athrow
    //   78: aload_0
    //   79: checkcast 615	android/os/PowerManager
    //   82: invokevirtual 618	android/os/PowerManager:isScreenOn	()Z
    //   85: istore_1
    //   86: goto -67 -> 19
    //   89: astore_2
    //   90: getstatic 38	kkkkkk/faafaf:bТ04220422ТТ0422042204220422Т	Ljava/lang/String;
    //   93: astore_0
    //   94: goto +93 -> 187
    //   97: invokestatic 623	kkkkkk/tttjtt$ddvvdd:bккк043A043A043Aк043Aкк	()Z
    //   100: istore_1
    //   101: iload_1
    //   102: ifne +16 -> 118
    //   105: iconst_1
    //   106: istore_1
    //   107: goto -88 -> 19
    //   110: new 625	java/lang/NullPointerException
    //   113: dup
    //   114: invokespecial 626	java/lang/NullPointerException:<init>	()V
    //   117: athrow
    //   118: aload_0
    //   119: ldc_w 628
    //   122: bipush 49
    //   124: iconst_4
    //   125: invokestatic 86	kkkkkk/gguuuu:bккккк043Aкк043A043A	(Ljava/lang/String;CC)Ljava/lang/String;
    //   128: invokevirtual 197	android/content/Context:getSystemService	(Ljava/lang/String;)Ljava/lang/Object;
    //   131: astore_0
    //   132: aload_0
    //   133: ifnull +12 -> 145
    //   136: aload_0
    //   137: instanceof 615
    //   140: istore_1
    //   141: iload_1
    //   142: ifne -64 -> 78
    //   145: iconst_1
    //   146: istore_1
    //   147: goto -128 -> 19
    //   150: astore_0
    //   151: aload_0
    //   152: athrow
    //   153: astore_0
    //   154: goto -44 -> 110
    //   157: iconst_1
    //   158: istore_1
    //   159: goto -140 -> 19
    //   162: iconst_1
    //   163: tableswitch	default:+21->184, 0:+24->187, 1:+-101->62
    //   184: goto -22 -> 162
    //   187: iconst_0
    //   188: tableswitch	default:+24->212, 0:+-126->62, 1:+-1->187
    //   212: goto -50 -> 162
    // Local variable table:
    //   start	length	slot	name	signature
    //   0	215	0	paramAaffaf	aaffaf
    //   18	141	1	bool	boolean
    //   62	7	2	str	String
    //   89	1	2	localException	Exception
    // Exception table:
    //   from	to	target	type
    //   110	118	53	java/lang/Exception
    //   67	72	75	java/lang/Exception
    //   78	86	89	java/lang/Exception
    //   118	132	89	java/lang/Exception
    //   136	141	89	java/lang/Exception
    //   0	19	150	java/lang/Exception
    //   54	59	150	java/lang/Exception
    //   62	67	150	java/lang/Exception
    //   90	94	150	java/lang/Exception
    //   97	101	150	java/lang/Exception
    //   78	86	153	java/lang/SecurityException
    //   118	132	153	java/lang/SecurityException
    //   136	141	153	java/lang/SecurityException
  }
  
  public static vdddvd.dvddvd b043Aк043A043Aккк043Aк043A()
    throws InterruptedException
  {
    Object localObject = dvdddv.bк043A043A043Aк043Aкк043Aк().b043A043Aккк043Aкк043Aк();
    if (localObject != null) {}
    vdddvd.dvddvd localDvddvd;
    do
    {
      return localObject;
      localDvddvd = vdvvdd.b043A043A043A043A043A043Aк043Aкк();
      localObject = localDvddvd;
    } while ((b0422ТТ0422Т0422042204220422Т + b04220422Т0422Т0422042204220422Т) * b0422ТТ0422Т0422042204220422Т % bТТ04220422Т0422042204220422Т == bкк043A043Aккк043Aк043A());
    if ((b0422ТТ0422Т0422042204220422Т + b04220422Т0422Т0422042204220422Т) * b0422ТТ0422Т0422042204220422Т % bТТ04220422Т0422042204220422Т != bТ0422Т0422Т0422042204220422Т)
    {
      b0422ТТ0422Т0422042204220422Т = bк043Aкк043Aкк043Aк043A();
      bТ0422Т0422Т0422042204220422Т = 63;
    }
    b0422ТТ0422Т0422042204220422Т = 95;
    bТ0422Т0422Т0422042204220422Т = 59;
    return localDvddvd;
  }
  
  public static String b043Aк043Aк043Aкк043Aк043A(@Nonnull aaffaf paramAaffaf)
  {
    try
    {
      i = tttjtt.tjtttt.jttttt.bююю044Eюююю044E044E;
      j = tttjtt.tjtttt.vddddd.bюююю044Eююю044E044E;
      if (i < j) {}
    }
    catch (Exception paramAaffaf)
    {
      int i;
      int j;
      throw paramAaffaf;
    }
    try
    {
      paramAaffaf = paramAaffaf.b0422042204220422Т0422042204220422Т.getContentResolver();
      i = b0422ТТ0422Т0422042204220422Т;
      switch (i * (b04220422Т0422Т0422042204220422Т + i) % bТТ04220422Т0422042204220422Т)
      {
      default: 
        b0422ТТ0422Т0422042204220422Т = bк043Aкк043Aкк043Aк043A();
        bТ0422Т0422Т0422042204220422Т = 32;
      }
      paramAaffaf = tttjtt.ttjttt.bк043Aкк043A043A043Aккк(paramAaffaf, gguuuu.bк043Aккк043Aкк043A043A("=?QAIMOMFPWCXK[\\RXR_LS]QS^XX", '4', '[', '\001'));
      return paramAaffaf;
    }
    catch (Exception paramAaffaf)
    {
      throw paramAaffaf;
    }
    i = tttjtt.tjtttt.jttttt.bююю044Eюююю044E044E;
    j = tttjtt.tjtttt.vddddd.b044Eю044E044E044Eююю044E044E;
    if (i == j) {
      return tttjtt.ttjttt.b043Aккк043A043A043Aккк(paramAaffaf.b0422042204220422Т0422042204220422Т.getContentResolver(), gguuuu.bккккк043Aкк043A043A("kk{ioqqmdlq[n_ml`d\\gRW_QQZRP", '<', '\003'));
    }
    return "";
  }
  
  /* Error */
  @Nonnull
  private static Map<String, String> b043Aк043Aкк043Aк043Aк043A(@Nullable String paramString1, @Nullable Set<String> paramSet, @Nonnull String paramString2)
  {
    // Byte code:
    //   0: new 201	java/util/HashMap
    //   3: dup
    //   4: invokespecial 202	java/util/HashMap:<init>	()V
    //   7: astore 6
    //   9: aload_1
    //   10: ifnull +202 -> 212
    //   13: new 387	java/io/File
    //   16: dup
    //   17: aload_0
    //   18: invokespecial 668	java/io/File:<init>	(Ljava/lang/String;)V
    //   21: astore_0
    //   22: aload_0
    //   23: invokevirtual 671	java/io/File:exists	()Z
    //   26: istore 4
    //   28: iload 4
    //   30: ifeq +182 -> 212
    //   33: new 673	java/io/BufferedReader
    //   36: dup
    //   37: new 675	java/io/FileReader
    //   40: dup
    //   41: aload_0
    //   42: invokespecial 678	java/io/FileReader:<init>	(Ljava/io/File;)V
    //   45: invokespecial 681	java/io/BufferedReader:<init>	(Ljava/io/Reader;)V
    //   48: astore_0
    //   49: aload_0
    //   50: invokevirtual 684	java/io/BufferedReader:readLine	()Ljava/lang/String;
    //   53: astore 5
    //   55: aload 5
    //   57: ifnull +174 -> 231
    //   60: aload 5
    //   62: aload_2
    //   63: invokestatic 690	kkkkkk/dvdvvd:b043Aк043A043A043A043A043A043Aкк	(Ljava/lang/String;Ljava/lang/String;)Ljava/util/ArrayList;
    //   66: astore 5
    //   68: aload 5
    //   70: invokeinterface 693 1 0
    //   75: ifne -26 -> 49
    //   78: aload 5
    //   80: iconst_0
    //   81: invokeinterface 696 2 0
    //   86: checkcast 114	java/lang/String
    //   89: invokevirtual 216	java/lang/String:trim	()Ljava/lang/String;
    //   92: astore 7
    //   94: aload 7
    //   96: invokevirtual 699	java/lang/String:length	()I
    //   99: istore_3
    //   100: iload_3
    //   101: ifeq -52 -> 49
    //   104: getstatic 90	kkkkkk/faafaf:b0422ТТ0422Т0422042204220422Т	I
    //   107: istore_3
    //   108: iload_3
    //   109: getstatic 92	kkkkkk/faafaf:b04220422Т0422Т0422042204220422Т	I
    //   112: iload_3
    //   113: iadd
    //   114: imul
    //   115: getstatic 94	kkkkkk/faafaf:bТТ04220422Т0422042204220422Т	I
    //   118: irem
    //   119: tableswitch	default:+17->136, 0:+28->147
    //   136: bipush 99
    //   138: putstatic 90	kkkkkk/faafaf:b0422ТТ0422Т0422042204220422Т	I
    //   141: invokestatic 99	kkkkkk/faafaf:bк043Aкк043Aкк043Aк043A	()I
    //   144: putstatic 96	kkkkkk/faafaf:bТ0422Т0422Т0422042204220422Т	I
    //   147: aload_1
    //   148: aload 7
    //   150: invokeinterface 702 2 0
    //   155: ifeq -106 -> 49
    //   158: goto +132 -> 290
    //   161: aload 5
    //   163: invokeinterface 308 1 0
    //   168: iconst_1
    //   169: if_icmple +110 -> 279
    //   172: aload 5
    //   174: iconst_1
    //   175: invokeinterface 696 2 0
    //   180: checkcast 114	java/lang/String
    //   183: invokevirtual 216	java/lang/String:trim	()Ljava/lang/String;
    //   186: astore 5
    //   188: aload 6
    //   190: aload 7
    //   192: aload 5
    //   194: invokeinterface 227 3 0
    //   199: pop
    //   200: goto -151 -> 49
    //   203: astore_1
    //   204: aload_0
    //   205: ifnull +7 -> 212
    //   208: aload_0
    //   209: invokevirtual 705	java/io/BufferedReader:close	()V
    //   212: aload 6
    //   214: areturn
    //   215: astore_0
    //   216: aconst_null
    //   217: astore_1
    //   218: aload_1
    //   219: ifnull +7 -> 226
    //   222: aload_1
    //   223: invokevirtual 705	java/io/BufferedReader:close	()V
    //   226: aload_0
    //   227: athrow
    //   228: astore_0
    //   229: aload_0
    //   230: athrow
    //   231: aload_0
    //   232: invokevirtual 705	java/io/BufferedReader:close	()V
    //   235: aload 6
    //   237: areturn
    //   238: astore_0
    //   239: aload 6
    //   241: areturn
    //   242: astore_1
    //   243: iconst_4
    //   244: istore_3
    //   245: iload_3
    //   246: iconst_0
    //   247: idiv
    //   248: istore_3
    //   249: goto -4 -> 245
    //   252: astore_2
    //   253: aload_0
    //   254: astore_1
    //   255: aload_2
    //   256: astore_0
    //   257: goto -39 -> 218
    //   260: astore_0
    //   261: aload_0
    //   262: athrow
    //   263: astore_1
    //   264: invokestatic 99	kkkkkk/faafaf:bк043Aкк043Aкк043Aк043A	()I
    //   267: putstatic 90	kkkkkk/faafaf:b0422ТТ0422Т0422042204220422Т	I
    //   270: goto -44 -> 226
    //   273: astore_0
    //   274: aconst_null
    //   275: astore_0
    //   276: goto -72 -> 204
    //   279: ldc -43
    //   281: astore 5
    //   283: goto -95 -> 188
    //   286: astore_0
    //   287: aload 6
    //   289: areturn
    //   290: iconst_0
    //   291: tableswitch	default:+21->312, 0:+-130->161, 1:+-1->290
    //   312: iconst_1
    //   313: tableswitch	default:+23->336, 0:+-23->290, 1:+-152->161
    //   336: goto -24 -> 312
    // Local variable table:
    //   start	length	slot	name	signature
    //   0	339	0	paramString1	String
    //   0	339	1	paramSet	Set<String>
    //   0	339	2	paramString2	String
    //   99	150	3	i	int
    //   26	3	4	bool	boolean
    //   53	229	5	localObject	Object
    //   7	281	6	localHashMap	HashMap
    //   92	99	7	str	String
    // Exception table:
    //   from	to	target	type
    //   49	55	203	java/io/IOException
    //   60	100	203	java/io/IOException
    //   147	158	203	java/io/IOException
    //   161	188	203	java/io/IOException
    //   188	200	203	java/io/IOException
    //   33	49	215	finally
    //   0	9	228	java/lang/Exception
    //   13	28	228	java/lang/Exception
    //   222	226	228	java/lang/Exception
    //   226	228	228	java/lang/Exception
    //   231	235	238	java/io/IOException
    //   222	226	242	java/io/IOException
    //   49	55	252	finally
    //   60	100	252	finally
    //   147	158	252	finally
    //   161	188	252	finally
    //   188	200	252	finally
    //   208	212	260	java/lang/Exception
    //   231	235	260	java/lang/Exception
    //   245	249	263	java/lang/Exception
    //   33	49	273	java/io/IOException
    //   208	212	286	java/io/IOException
  }
  
  public static String b043Aкк043A043Aкк043Aк043A()
  {
    Object localObject = Locale.getDefault();
    StringBuilder localStringBuilder = new StringBuilder();
    String str = ((Locale)localObject).getLanguage();
    if (str != null)
    {
      int i = b0422ТТ0422Т0422042204220422Т;
      switch (i * (b04220422Т0422Т0422042204220422Т + i) % bТТ04220422Т0422042204220422Т)
      {
      default: 
        b0422ТТ0422Т0422042204220422Т = 8;
        bТ0422Т0422Т0422042204220422Т = 56;
      }
      localStringBuilder.append(str);
      localObject = ((Locale)localObject).getCountry();
      if (localObject != null)
      {
        localStringBuilder.append(gguuuu.bк043Aккк043Aкк043A043A("@", '\024', 'ÿ', '\001'));
        localStringBuilder.append((String)localObject);
      }
    }
    return localStringBuilder.toString();
  }
  
  public static vdddvd.vdvdvd b043Aкк043Aк043Aк043Aк043A(@Nullable Location paramLocation, boolean paramBoolean)
  {
    Object localObject = null;
    if (paramLocation == null)
    {
      switch (0)
      {
      case 1: 
      default: 
        for (;;)
        {
          switch (1)
          {
          }
        }
      }
      paramLocation = null;
      return paramLocation;
    }
    boolean bool = vvvvvd.bкк043Aк043Aккк043Aк(paramLocation);
    double d1 = paramLocation.getLatitude();
    double d2 = paramLocation.getLongitude();
    int i = b0422ТТ0422Т0422042204220422Т;
    switch (i * (b04220422Т0422Т0422042204220422Т + i) % bТТ04220422Т0422042204220422Т)
    {
    default: 
      b0422ТТ0422Т0422042204220422Т = bк043Aкк043Aкк043Aк043A();
      bТ0422Т0422Т0422042204220422Т = 34;
    }
    if (paramLocation.hasAccuracy()) {
      localObject = Float.valueOf(paramLocation.getAccuracy());
    }
    localObject = new vdddvd.vdvdvd(d1, d2, (Float)localObject, bool, paramBoolean);
    i = b0422ТТ0422Т0422042204220422Т;
    paramLocation = (Location)localObject;
    switch (i * (b04220422Т0422Т0422042204220422Т + i) % bТТ04220422Т0422042204220422Т)
    {
    }
    b0422ТТ0422Т0422042204220422Т = 52;
    bТ0422Т0422Т0422042204220422Т = 54;
    return localObject;
  }
  
  public static String b043Aккк043A043Aк043Aк043A()
  {
    int i = b0422ТТ0422Т0422042204220422Т;
    switch (i * (b04220422Т0422Т0422042204220422Т + i) % bТТ04220422Т0422042204220422Т)
    {
    default: 
      b0422ТТ0422Т0422042204220422Т = 51;
      bТ0422Т0422Т0422042204220422Т = 86;
    }
    return gguuuu.bккккк043Aкк043A043A("&4+:83/", 'À', '\001');
  }
  
  public static int b043Aккк043Aкк043Aк043A()
  {
    return 2;
  }
  
  /* Error */
  public static String b043Aкккк043Aк043Aк043A()
  {
    // Byte code:
    //   0: invokestatic 753	kkkkkk/dddvvd:b043Aкккк043A043A043Aкк	()Ljava/lang/String;
    //   3: astore 4
    //   5: getstatic 90	kkkkkk/faafaf:b0422ТТ0422Т0422042204220422Т	I
    //   8: istore_0
    //   9: getstatic 92	kkkkkk/faafaf:b04220422Т0422Т0422042204220422Т	I
    //   12: istore_1
    //   13: getstatic 94	kkkkkk/faafaf:bТТ04220422Т0422042204220422Т	I
    //   16: istore_2
    //   17: getstatic 90	kkkkkk/faafaf:b0422ТТ0422Т0422042204220422Т	I
    //   20: istore_3
    //   21: iload_3
    //   22: invokestatic 755	kkkkkk/faafaf:b043A043Aк043Aккк043Aк043A	()I
    //   25: iload_3
    //   26: iadd
    //   27: imul
    //   28: getstatic 94	kkkkkk/faafaf:bТТ04220422Т0422042204220422Т	I
    //   31: irem
    //   32: tableswitch	default:+20->52, 0:+31->63
    //   52: invokestatic 99	kkkkkk/faafaf:bк043Aкк043Aкк043Aк043A	()I
    //   55: putstatic 90	kkkkkk/faafaf:b0422ТТ0422Т0422042204220422Т	I
    //   58: bipush 15
    //   60: putstatic 96	kkkkkk/faafaf:bТ0422Т0422Т0422042204220422Т	I
    //   63: iload_0
    //   64: iload_1
    //   65: iload_0
    //   66: iadd
    //   67: imul
    //   68: iload_2
    //   69: irem
    //   70: tableswitch	default:+18->88, 0:+29->99
    //   88: bipush 86
    //   90: putstatic 90	kkkkkk/faafaf:b0422ТТ0422Т0422042204220422Т	I
    //   93: invokestatic 99	kkkkkk/faafaf:bк043Aкк043Aкк043Aк043A	()I
    //   96: putstatic 96	kkkkkk/faafaf:bТ0422Т0422Т0422042204220422Т	I
    //   99: aload 4
    //   101: areturn
    //   102: astore 4
    //   104: aload 4
    //   106: athrow
    //   107: astore 4
    //   109: aload 4
    //   111: athrow
    // Local variable table:
    //   start	length	slot	name	signature
    //   8	60	0	i	int
    //   12	55	1	j	int
    //   16	54	2	k	int
    //   20	8	3	m	int
    //   3	97	4	str	String
    //   102	3	4	localException1	Exception
    //   107	3	4	localException2	Exception
    // Exception table:
    //   from	to	target	type
    //   0	17	102	java/lang/Exception
    //   88	99	107	java/lang/Exception
  }
  
  public static long bк043A043A043A043Aкк043Aк043A()
  {
    if ((b0422ТТ0422Т0422042204220422Т + b04220422Т0422Т0422042204220422Т) * b0422ТТ0422Т0422042204220422Т % bТТ04220422Т0422042204220422Т != bТ0422Т0422Т0422042204220422Т)
    {
      b0422ТТ0422Т0422042204220422Т = bк043Aкк043Aкк043Aк043A();
      bТ0422Т0422Т0422042204220422Т = bк043Aкк043Aкк043Aк043A();
    }
    try
    {
      faffff localFaffff = new faffff(Environment.getDataDirectory().getPath());
      long l1 = localFaffff.bк043A043A043A043A043A043A043Aк043A();
      long l2 = localFaffff.b043Aк043A043A043A043A043A043Aк043A();
      return l2 * l1;
    }
    catch (Exception localException)
    {
      throw localException;
    }
  }
  
  /* Error */
  public static long bк043A043A043Aк043Aк043Aк043A()
  {
    // Byte code:
    //   0: invokestatic 765	java/lang/System:currentTimeMillis	()J
    //   3: invokestatic 770	kkkkkk/tttjtt$vvdvdd:bк043Aкк043A043Aк043Aкк	()J
    //   6: lsub
    //   7: ldc2_w 771
    //   10: ldiv
    //   11: lstore 5
    //   13: getstatic 38	kkkkkk/faafaf:bТ04220422ТТ0422042204220422Т	Ljava/lang/String;
    //   16: astore 7
    //   18: new 413	java/lang/StringBuilder
    //   21: dup
    //   22: ldc_w 774
    //   25: sipush 210
    //   28: iconst_1
    //   29: invokestatic 86	kkkkkk/gguuuu:bккккк043Aкк043A043A	(Ljava/lang/String;CC)Ljava/lang/String;
    //   32: invokespecial 416	java/lang/StringBuilder:<init>	(Ljava/lang/String;)V
    //   35: astore 8
    //   37: getstatic 90	kkkkkk/faafaf:b0422ТТ0422Т0422042204220422Т	I
    //   40: getstatic 92	kkkkkk/faafaf:b04220422Т0422Т0422042204220422Т	I
    //   43: iadd
    //   44: getstatic 90	kkkkkk/faafaf:b0422ТТ0422Т0422042204220422Т	I
    //   47: imul
    //   48: getstatic 94	kkkkkk/faafaf:bТТ04220422Т0422042204220422Т	I
    //   51: irem
    //   52: getstatic 96	kkkkkk/faafaf:bТ0422Т0422Т0422042204220422Т	I
    //   55: if_icmpeq +14 -> 69
    //   58: bipush 98
    //   60: putstatic 90	kkkkkk/faafaf:b0422ТТ0422Т0422042204220422Т	I
    //   63: invokestatic 99	kkkkkk/faafaf:bк043Aкк043Aкк043Aк043A	()I
    //   66: putstatic 96	kkkkkk/faafaf:bТ0422Т0422Т0422042204220422Т	I
    //   69: iconst_1
    //   70: tableswitch	default:+22->92, 0:+-33->37, 1:+49->119
    //   92: iconst_0
    //   93: tableswitch	default:+23->116, 0:+26->119, 1:+-56->37
    //   116: goto -24 -> 92
    //   119: getstatic 90	kkkkkk/faafaf:b0422ТТ0422Т0422042204220422Т	I
    //   122: istore_0
    //   123: getstatic 92	kkkkkk/faafaf:b04220422Т0422Т0422042204220422Т	I
    //   126: istore_1
    //   127: getstatic 90	kkkkkk/faafaf:b0422ТТ0422Т0422042204220422Т	I
    //   130: istore_2
    //   131: getstatic 94	kkkkkk/faafaf:bТТ04220422Т0422042204220422Т	I
    //   134: istore_3
    //   135: getstatic 96	kkkkkk/faafaf:bТ0422Т0422Т0422042204220422Т	I
    //   138: istore 4
    //   140: iload_0
    //   141: iload_1
    //   142: iadd
    //   143: iload_2
    //   144: imul
    //   145: iload_3
    //   146: irem
    //   147: iload 4
    //   149: if_icmpeq +14 -> 163
    //   152: bipush 17
    //   154: putstatic 90	kkkkkk/faafaf:b0422ТТ0422Т0422042204220422Т	I
    //   157: invokestatic 99	kkkkkk/faafaf:bк043Aкк043Aкк043Aк043A	()I
    //   160: putstatic 96	kkkkkk/faafaf:bТ0422Т0422Т0422042204220422Т	I
    //   163: aload 7
    //   165: aload 8
    //   167: lload 5
    //   169: invokevirtual 420	java/lang/StringBuilder:append	(J)Ljava/lang/StringBuilder;
    //   172: invokevirtual 421	java/lang/StringBuilder:toString	()Ljava/lang/String;
    //   175: invokestatic 370	kkkkkk/fafffa:b043Aккк043Aк043Aкк043A	(Ljava/lang/String;Ljava/lang/String;)V
    //   178: lload 5
    //   180: lreturn
    //   181: astore 7
    //   183: aload 7
    //   185: athrow
    //   186: astore 7
    //   188: aload 7
    //   190: athrow
    // Local variable table:
    //   start	length	slot	name	signature
    //   122	21	0	i	int
    //   126	17	1	j	int
    //   130	15	2	k	int
    //   134	13	3	m	int
    //   138	12	4	n	int
    //   11	168	5	l	long
    //   16	148	7	str	String
    //   181	3	7	localException1	Exception
    //   186	3	7	localException2	Exception
    //   35	131	8	localStringBuilder	StringBuilder
    // Exception table:
    //   from	to	target	type
    //   0	37	181	java/lang/Exception
    //   119	140	181	java/lang/Exception
    //   163	178	181	java/lang/Exception
    //   152	163	186	java/lang/Exception
  }
  
  public static String bк043A043A043Aккк043Aк043A(@Nonnull aaffaf paramAaffaf)
  {
    if (tttjtt.tjtttt.jttttt.bююю044Eюююю044E044E >= tttjtt.tjtttt.vddddd.bюююю044Eююю044E044E) {}
    String str;
    for (paramAaffaf = tttjtt.ttjttt.bк043Aкк043A043A043Aккк(paramAaffaf.b0422042204220422Т0422042204220422Т.getContentResolver(), gguuuu.bк043Aккк043Aкк043A043A("|\001}\005\017\003\005\020\n\n", '¯', '\025', '\001'));; paramAaffaf = str)
    {
      switch (1)
      {
      case 0: 
      default: 
        for (;;)
        {
          switch (1)
          {
          }
        }
      }
      return paramAaffaf;
      str = tttjtt.ttjttt.b043Aккк043A043A043Aккк(paramAaffaf.b0422042204220422Т0422042204220422Т.getContentResolver(), gguuuu.bккккк043Aкк043A043A("\033\035\032\026\033#\025\025\036\026\024", 'l', '\002'));
      int i = b0422ТТ0422Т0422042204220422Т;
      paramAaffaf = str;
      switch (i * (b04220422Т0422Т0422042204220422Т + i) % b043Aккк043Aкк043Aк043A())
      {
      }
      b0422ТТ0422Т0422042204220422Т = bк043Aкк043Aкк043Aк043A();
      bТ0422Т0422Т0422042204220422Т = 32;
    }
  }
  
  @Nullable
  public static String bк043A043Aк043Aкк043Aк043A()
  {
    int i = b0422ТТ0422Т0422042204220422Т;
    switch (i * (b04220422Т0422Т0422042204220422Т + i) % bТТ04220422Т0422042204220422Т)
    {
    default: 
      b0422ТТ0422Т0422042204220422Т = bк043Aкк043Aкк043Aк043A();
      bТ0422Т0422Т0422042204220422Т = 0;
    }
    Object localObject = Looper.getMainLooper().getThread().getStackTrace();
    if (localObject.length > 0)
    {
      localObject = localObject[(localObject.length - 1)].getClassName();
      if ((!((String)localObject).equals(gguuuu.bк043Aккк043Aкк043A043A("S`_!UcZigb^)ekrdroco2ty5b\003qz\001rW}y\006", 'Â', 'Ò', '\001'))) && (!((String)localObject).equals(gguuuu.bккккк043Aкк043A043A("FBLUGH\nNSLL<C\003\"4F:F4!A-=>", '\n', '\002')))) {}
    }
    else
    {
      return null;
    }
    i = ((String)localObject).lastIndexOf(gguuuu.bк043Aккк043Aкк043A043A("%", 'Ò', '\\', '\001'));
    if (i != -1) {
      return ((String)localObject).substring(i + 1, ((String)localObject).length());
    }
    return localObject;
  }
  
  @Nullable
  public static String bк043A043Aкк043Aк043Aк043A(@Nonnull StringBuilder paramStringBuilder)
    throws InterruptedException
  {
    try
    {
      Object localObject1;
      int i;
      Object localObject2;
      Object localObject3;
      if (dvdddv.bк043A043A043Aк043Aкк043Aк().b0422ТТТ0422ТТТТТ)
      {
        localObject1 = dvdddv.bк043A043A043Aк043Aкк043Aк();
        i = b0422ТТ0422Т0422042204220422Т;
        switch (i * (b04220422Т0422Т0422042204220422Т + i) % bТТ04220422Т0422042204220422Т)
        {
        default: 
          b0422ТТ0422Т0422042204220422Т = 3;
          bТ0422Т0422Т0422042204220422Т = bк043Aкк043Aкк043Aк043A();
        }
        localObject1 = ((dvdddv)localObject1).bк043Aк043Aк043Aкк043Aк(gguuuu.bк043Aккк043Aкк043A043A("s9@;=/8z3==DD", 'ü', '9', '\001'));
        if ((localObject1 != null) && (!((List)localObject1).isEmpty()) && (((List)localObject1).size() == 2))
        {
          localObject2 = (String)((List)localObject1).get(0);
          paramStringBuilder.append((String)((List)localObject1).get(1));
          return localObject2;
          if (((String)localObject3).endsWith(gguuuu.bккккк043Aкк043A043A("\001HI<", ')', '\004')))
          {
            localObject3 = new StringBuilder((String)localObject3);
            ((List)localObject1).add(((StringBuilder)localObject3).substring(0, ((StringBuilder)localObject3).length() - 4));
          }
          label184:
          i += 1;
        }
      }
      else
      {
        for (;;)
        {
          if (i < j) {
            localObject3 = localObject2[i];
          }
          do
          {
            try
            {
              if ((bк043Aкк043Aкк043Aк043A() + b04220422Т0422Т0422042204220422Т) * bк043Aкк043Aкк043Aк043A() % bТТ04220422Т0422042204220422Т != bТ0422Т0422Т0422042204220422Т)
              {
                b0422ТТ0422Т0422042204220422Т = 8;
                bТ0422Т0422Т0422042204220422Т = 34;
              }
              if (localObject3 == null) {
                break label184;
              }
            }
            catch (Exception paramStringBuilder)
            {
              throw paramStringBuilder;
            }
            localObject2 = new StringBuilder();
            localObject3 = ((List)localObject1).iterator();
            for (;;)
            {
              boolean bool = ((Iterator)localObject3).hasNext();
              if (!bool) {
                break;
              }
              ((StringBuilder)localObject2).append((String)((Iterator)localObject3).next());
            }
            localObject1 = new ArrayList();
            break label370;
            localObject2 = new File(gguuuu.bккккк043Aкк043A043A("7zxxho0fnlqo*", 'Ñ', '\002'));
            localObject2 = ((File)localObject2).list();
          } while (localObject2 == null);
          int j = localObject2.length;
          i = 0;
        }
        paramStringBuilder.append(((List)localObject1).size());
        paramStringBuilder = dvdvvd.bкк043A043A043A043A043A043Aкк(((StringBuilder)localObject2).toString());
        return paramStringBuilder;
      }
    }
    catch (Exception paramStringBuilder)
    {
      throw paramStringBuilder;
    }
    return null;
    label370:
    switch (0)
    {
    }
    for (;;)
    {
      switch (1)
      {
      }
    }
  }
  
  /* Error */
  @Nullable
  public static String bк043Aк043A043Aкк043Aк043A(@Nonnull aaffaf paramAaffaf)
    throws InterruptedException
  {
    // Byte code:
    //   0: new 413	java/lang/StringBuilder
    //   3: dup
    //   4: invokespecial 502	java/lang/StringBuilder:<init>	()V
    //   7: astore 13
    //   9: invokestatic 854	java/lang/Thread:currentThread	()Ljava/lang/Thread;
    //   12: invokevirtual 857	java/lang/Thread:isInterrupted	()Z
    //   15: ifeq +545 -> 560
    //   18: ldc -43
    //   20: areturn
    //   21: aload 12
    //   23: checkcast 199	android/telephony/TelephonyManager
    //   26: astore 14
    //   28: ldc_w 859
    //   31: bipush 18
    //   33: sipush 134
    //   36: iconst_2
    //   37: invokestatic 66	kkkkkk/gguuuu:bк043Aккк043Aкк043A043A	(Ljava/lang/String;CCC)Ljava/lang/String;
    //   40: astore 12
    //   42: getstatic 90	kkkkkk/faafaf:b0422ТТ0422Т0422042204220422Т	I
    //   45: istore_2
    //   46: getstatic 92	kkkkkk/faafaf:b04220422Т0422Т0422042204220422Т	I
    //   49: istore_3
    //   50: getstatic 90	kkkkkk/faafaf:b0422ТТ0422Т0422042204220422Т	I
    //   53: istore 4
    //   55: getstatic 94	kkkkkk/faafaf:bТТ04220422Т0422042204220422Т	I
    //   58: istore 5
    //   60: getstatic 96	kkkkkk/faafaf:bТ0422Т0422Т0422042204220422Т	I
    //   63: istore 6
    //   65: iload_2
    //   66: iload_3
    //   67: iadd
    //   68: iload 4
    //   70: imul
    //   71: iload 5
    //   73: irem
    //   74: iload 6
    //   76: if_icmpeq +14 -> 90
    //   79: invokestatic 99	kkkkkk/faafaf:bк043Aкк043Aкк043Aк043A	()I
    //   82: putstatic 90	kkkkkk/faafaf:b0422ТТ0422Т0422042204220422Т	I
    //   85: bipush 66
    //   87: putstatic 96	kkkkkk/faafaf:bТ0422Т0422Т0422042204220422Т	I
    //   90: aload 14
    //   92: invokevirtual 862	android/telephony/TelephonyManager:getPhoneType	()I
    //   95: iconst_1
    //   96: if_icmpne +10 -> 106
    //   99: aload 14
    //   101: invokevirtual 211	android/telephony/TelephonyManager:getNetworkOperatorName	()Ljava/lang/String;
    //   104: astore 12
    //   106: aload 13
    //   108: aload 12
    //   110: invokevirtual 505	java/lang/StringBuilder:append	(Ljava/lang/String;)Ljava/lang/StringBuilder;
    //   113: pop
    //   114: aload 13
    //   116: aload 14
    //   118: invokevirtual 865	android/telephony/TelephonyManager:getSimCountryIso	()Ljava/lang/String;
    //   121: invokevirtual 505	java/lang/StringBuilder:append	(Ljava/lang/String;)Ljava/lang/StringBuilder;
    //   124: pop
    //   125: new 379	kkkkkk/faffff
    //   128: dup
    //   129: invokestatic 385	android/os/Environment:getDataDirectory	()Ljava/io/File;
    //   132: invokevirtual 390	java/io/File:getPath	()Ljava/lang/String;
    //   135: invokespecial 393	kkkkkk/faffff:<init>	(Ljava/lang/String;)V
    //   138: astore 12
    //   140: aload 12
    //   142: invokevirtual 759	kkkkkk/faffff:bк043A043A043A043A043A043A043Aк043A	()J
    //   145: lstore 7
    //   147: aload 12
    //   149: invokevirtual 409	kkkkkk/faffff:b043Aк043A043A043A043A043A043Aк043A	()J
    //   152: lstore 9
    //   154: lload 9
    //   156: lload 7
    //   158: lmul
    //   159: l2f
    //   160: ldc_w 866
    //   163: fdiv
    //   164: fstore_1
    //   165: getstatic 90	kkkkkk/faafaf:b0422ТТ0422Т0422042204220422Т	I
    //   168: getstatic 92	kkkkkk/faafaf:b04220422Т0422Т0422042204220422Т	I
    //   171: iadd
    //   172: getstatic 90	kkkkkk/faafaf:b0422ТТ0422Т0422042204220422Т	I
    //   175: imul
    //   176: invokestatic 136	kkkkkk/faafaf:b043Aккк043Aкк043Aк043A	()I
    //   179: irem
    //   180: getstatic 96	kkkkkk/faafaf:bТ0422Т0422Т0422042204220422Т	I
    //   183: if_icmpeq +14 -> 197
    //   186: invokestatic 99	kkkkkk/faafaf:bк043Aкк043Aкк043Aк043A	()I
    //   189: putstatic 90	kkkkkk/faafaf:b0422ТТ0422Т0422042204220422Т	I
    //   192: bipush 91
    //   194: putstatic 96	kkkkkk/faafaf:bТ0422Т0422Т0422042204220422Т	I
    //   197: fload_1
    //   198: ldc_w 866
    //   201: fdiv
    //   202: ldc_w 866
    //   205: fdiv
    //   206: fstore_1
    //   207: aload 13
    //   209: fload_1
    //   210: invokevirtual 869	java/lang/StringBuilder:append	(F)Ljava/lang/StringBuilder;
    //   213: pop
    //   214: new 871	kkkkkk/faaafa
    //   217: dup
    //   218: aload_0
    //   219: invokespecial 872	kkkkkk/faaafa:<init>	(Lkkkkkk/faafaf$aaffaf;)V
    //   222: astore_0
    //   223: aload_0
    //   224: invokevirtual 875	kkkkkk/faaafa:b043A043Aкк043Aкккк043A	()I
    //   227: istore_2
    //   228: aload_0
    //   229: invokevirtual 878	kkkkkk/faaafa:bкк043Aк043Aкккк043A	()I
    //   232: istore_3
    //   233: iload_2
    //   234: iload_3
    //   235: if_icmplt +291 -> 526
    //   238: aload 13
    //   240: iload_2
    //   241: invokevirtual 846	java/lang/StringBuilder:append	(I)Ljava/lang/StringBuilder;
    //   244: ldc_w 880
    //   247: bipush 121
    //   249: iconst_0
    //   250: invokestatic 86	kkkkkk/gguuuu:bккккк043Aкк043A043A	(Ljava/lang/String;CC)Ljava/lang/String;
    //   253: invokevirtual 505	java/lang/StringBuilder:append	(Ljava/lang/String;)Ljava/lang/StringBuilder;
    //   256: iload_3
    //   257: invokevirtual 846	java/lang/StringBuilder:append	(I)Ljava/lang/StringBuilder;
    //   260: pop
    //   261: aload 13
    //   263: invokestatic 882	kkkkkk/faafaf:b043A043Aкк043A043Aк043Aк043A	()Ljava/lang/String;
    //   266: invokevirtual 505	java/lang/StringBuilder:append	(Ljava/lang/String;)Ljava/lang/StringBuilder;
    //   269: pop
    //   270: new 553	java/util/HashSet
    //   273: dup
    //   274: invokespecial 554	java/util/HashSet:<init>	()V
    //   277: astore_0
    //   278: aload_0
    //   279: iconst_1
    //   280: anewarray 114	java/lang/String
    //   283: dup
    //   284: iconst_0
    //   285: ldc_w 884
    //   288: sipush 191
    //   291: iconst_3
    //   292: invokestatic 86	kkkkkk/gguuuu:bккккк043Aкк043A043A	(Ljava/lang/String;CC)Ljava/lang/String;
    //   295: aastore
    //   296: invokestatic 551	java/util/Collections:addAll	(Ljava/util/Collection;[Ljava/lang/Object;)Z
    //   299: pop
    //   300: ldc_w 886
    //   303: bipush 67
    //   305: iconst_3
    //   306: invokestatic 86	kkkkkk/gguuuu:bккккк043Aкк043A043A	(Ljava/lang/String;CC)Ljava/lang/String;
    //   309: aload_0
    //   310: ldc_w 888
    //   313: sipush 153
    //   316: iconst_2
    //   317: invokestatic 86	kkkkkk/gguuuu:bккккк043Aкк043A043A	(Ljava/lang/String;CC)Ljava/lang/String;
    //   320: invokestatic 567	kkkkkk/faafaf:b043Aк043Aкк043Aк043Aк043A	(Ljava/lang/String;Ljava/util/Set;Ljava/lang/String;)Ljava/util/HashMap;
    //   323: astore_0
    //   324: getstatic 38	kkkkkk/faafaf:bТ04220422ТТ0422042204220422Т	Ljava/lang/String;
    //   327: astore 12
    //   329: aload 12
    //   331: new 413	java/lang/StringBuilder
    //   334: dup
    //   335: ldc_w 890
    //   338: bipush 29
    //   340: iconst_4
    //   341: invokestatic 86	kkkkkk/gguuuu:bккккк043Aкк043A043A	(Ljava/lang/String;CC)Ljava/lang/String;
    //   344: invokespecial 416	java/lang/StringBuilder:<init>	(Ljava/lang/String;)V
    //   347: aload_0
    //   348: invokevirtual 516	java/lang/StringBuilder:append	(Ljava/lang/Object;)Ljava/lang/StringBuilder;
    //   351: invokevirtual 421	java/lang/StringBuilder:toString	()Ljava/lang/String;
    //   354: invokestatic 370	kkkkkk/fafffa:b043Aккк043Aк043Aкк043A	(Ljava/lang/String;Ljava/lang/String;)V
    //   357: aload_0
    //   358: ldc_w 892
    //   361: sipush 178
    //   364: sipush 219
    //   367: iconst_2
    //   368: invokestatic 66	kkkkkk/gguuuu:bк043Aккк043Aкк043A043A	(Ljava/lang/String;CCC)Ljava/lang/String;
    //   371: invokeinterface 332 2 0
    //   376: checkcast 114	java/lang/String
    //   379: astore 12
    //   381: aload 12
    //   383: astore_0
    //   384: aload 12
    //   386: ifnonnull +6 -> 392
    //   389: ldc -43
    //   391: astore_0
    //   392: aload 13
    //   394: aload_0
    //   395: invokevirtual 505	java/lang/StringBuilder:append	(Ljava/lang/String;)Ljava/lang/StringBuilder;
    //   398: pop
    //   399: aload 13
    //   401: getstatic 897	kkkkkk/tttjtt$tjtttt:bюююююююю044E044E	Ljava/lang/String;
    //   404: invokevirtual 505	java/lang/StringBuilder:append	(Ljava/lang/String;)Ljava/lang/StringBuilder;
    //   407: astore_0
    //   408: ldc_w 899
    //   411: bipush 23
    //   413: sipush 234
    //   416: iconst_2
    //   417: invokestatic 66	kkkkkk/gguuuu:bк043Aккк043Aкк043A043A	(Ljava/lang/String;CCC)Ljava/lang/String;
    //   420: astore 12
    //   422: aload_0
    //   423: aload 12
    //   425: invokevirtual 505	java/lang/StringBuilder:append	(Ljava/lang/String;)Ljava/lang/StringBuilder;
    //   428: getstatic 902	kkkkkk/tttjtt$tjtttt:b044E044Eюю044E044E044E044Eю044E	Ljava/lang/String;
    //   431: invokevirtual 505	java/lang/StringBuilder:append	(Ljava/lang/String;)Ljava/lang/StringBuilder;
    //   434: ldc_w 904
    //   437: bipush 123
    //   439: iconst_3
    //   440: invokestatic 86	kkkkkk/gguuuu:bккккк043Aкк043A043A	(Ljava/lang/String;CC)Ljava/lang/String;
    //   443: invokevirtual 505	java/lang/StringBuilder:append	(Ljava/lang/String;)Ljava/lang/StringBuilder;
    //   446: getstatic 907	kkkkkk/tttjtt$tjtttt:bю044Eю044E044E044E044E044Eю044E	Ljava/lang/String;
    //   449: invokevirtual 505	java/lang/StringBuilder:append	(Ljava/lang/String;)Ljava/lang/StringBuilder;
    //   452: astore_0
    //   453: aload_0
    //   454: ldc_w 909
    //   457: bipush 102
    //   459: bipush 6
    //   461: iconst_3
    //   462: invokestatic 66	kkkkkk/gguuuu:bк043Aккк043Aкк043A043A	(Ljava/lang/String;CCC)Ljava/lang/String;
    //   465: invokevirtual 505	java/lang/StringBuilder:append	(Ljava/lang/String;)Ljava/lang/StringBuilder;
    //   468: getstatic 912	kkkkkk/tttjtt$tjtttt:b044Eююююююю044E044E	Ljava/lang/String;
    //   471: invokevirtual 505	java/lang/StringBuilder:append	(Ljava/lang/String;)Ljava/lang/StringBuilder;
    //   474: astore_0
    //   475: aload_0
    //   476: ldc_w 914
    //   479: bipush 58
    //   481: iconst_5
    //   482: invokestatic 86	kkkkkk/gguuuu:bккккк043Aкк043A043A	(Ljava/lang/String;CC)Ljava/lang/String;
    //   485: invokevirtual 505	java/lang/StringBuilder:append	(Ljava/lang/String;)Ljava/lang/StringBuilder;
    //   488: astore_0
    //   489: getstatic 917	kkkkkk/tttjtt$tjtttt$jttttt:b044E044E044Eююююю044E044E	Ljava/lang/String;
    //   492: astore 12
    //   494: aload_0
    //   495: aload 12
    //   497: invokevirtual 505	java/lang/StringBuilder:append	(Ljava/lang/String;)Ljava/lang/StringBuilder;
    //   500: pop
    //   501: aload 13
    //   503: invokevirtual 421	java/lang/StringBuilder:toString	()Ljava/lang/String;
    //   506: astore_0
    //   507: aload_0
    //   508: invokestatic 850	kkkkkk/dvdvvd:bкк043A043A043A043A043A043Aкк	(Ljava/lang/String;)Ljava/lang/String;
    //   511: areturn
    //   512: astore_0
    //   513: getstatic 38	kkkkkk/faafaf:bТ04220422ТТ0422042204220422Т	Ljava/lang/String;
    //   516: aload_0
    //   517: invokevirtual 366	java/lang/Exception:toString	()Ljava/lang/String;
    //   520: invokestatic 370	kkkkkk/fafffa:b043Aккк043Aк043Aкк043A	(Ljava/lang/String;Ljava/lang/String;)V
    //   523: ldc -43
    //   525: areturn
    //   526: aload 13
    //   528: iload_3
    //   529: invokevirtual 846	java/lang/StringBuilder:append	(I)Ljava/lang/StringBuilder;
    //   532: astore_0
    //   533: aload_0
    //   534: ldc_w 919
    //   537: bipush 15
    //   539: iconst_1
    //   540: invokestatic 86	kkkkkk/gguuuu:bккккк043Aкк043A043A	(Ljava/lang/String;CC)Ljava/lang/String;
    //   543: invokevirtual 505	java/lang/StringBuilder:append	(Ljava/lang/String;)Ljava/lang/StringBuilder;
    //   546: iload_2
    //   547: invokevirtual 846	java/lang/StringBuilder:append	(I)Ljava/lang/StringBuilder;
    //   550: pop
    //   551: goto -290 -> 261
    //   554: astore_0
    //   555: aload_0
    //   556: athrow
    //   557: astore_0
    //   558: aload_0
    //   559: athrow
    //   560: aload_0
    //   561: getfield 133	kkkkkk/faafaf$aaffaf:b0422042204220422Т0422042204220422Т	Landroid/content/Context;
    //   564: invokevirtual 191	android/content/Context:getApplicationContext	()Landroid/content/Context;
    //   567: ldc_w 921
    //   570: bipush 80
    //   572: bipush 121
    //   574: iconst_0
    //   575: invokestatic 66	kkkkkk/gguuuu:bк043Aккк043Aкк043A043A	(Ljava/lang/String;CCC)Ljava/lang/String;
    //   578: invokevirtual 197	android/content/Context:getSystemService	(Ljava/lang/String;)Ljava/lang/Object;
    //   581: astore 12
    //   583: aload 12
    //   585: ifnull +15 -> 600
    //   588: aload 12
    //   590: instanceof 199
    //   593: istore 11
    //   595: iload 11
    //   597: ifne -576 -> 21
    //   600: ldc -43
    //   602: areturn
    //   603: astore_0
    //   604: aload_0
    //   605: athrow
    //   606: astore_0
    //   607: aload_0
    //   608: athrow
    //   609: astore_0
    //   610: ldc -43
    //   612: areturn
    // Local variable table:
    //   start	length	slot	name	signature
    //   0	613	0	paramAaffaf	aaffaf
    //   164	46	1	f	float
    //   45	502	2	i	int
    //   49	480	3	j	int
    //   53	18	4	k	int
    //   58	16	5	m	int
    //   63	14	6	n	int
    //   145	12	7	l1	long
    //   152	3	9	l2	long
    //   593	3	11	bool	boolean
    //   21	568	12	localObject	Object
    //   7	520	13	localStringBuilder	StringBuilder
    //   26	91	14	localTelephonyManager	android.telephony.TelephonyManager
    // Exception table:
    //   from	to	target	type
    //   21	28	512	java/lang/Exception
    //   90	106	512	java/lang/Exception
    //   106	125	512	java/lang/Exception
    //   560	583	512	java/lang/Exception
    //   588	595	512	java/lang/Exception
    //   0	18	554	java/lang/Exception
    //   329	381	554	java/lang/Exception
    //   392	422	554	java/lang/Exception
    //   453	475	554	java/lang/Exception
    //   494	507	554	java/lang/Exception
    //   533	551	554	java/lang/Exception
    //   79	90	557	java/lang/Exception
    //   555	557	557	java/lang/Exception
    //   604	606	557	java/lang/Exception
    //   28	42	603	java/lang/Exception
    //   125	154	603	java/lang/Exception
    //   207	233	603	java/lang/Exception
    //   238	261	603	java/lang/Exception
    //   261	278	603	java/lang/Exception
    //   278	329	603	java/lang/Exception
    //   422	453	603	java/lang/Exception
    //   475	494	603	java/lang/Exception
    //   507	512	603	java/lang/Exception
    //   513	523	603	java/lang/Exception
    //   526	533	603	java/lang/Exception
    //   42	65	606	java/lang/Exception
    //   21	28	609	java/lang/SecurityException
    //   90	106	609	java/lang/SecurityException
    //   106	125	609	java/lang/SecurityException
    //   560	583	609	java/lang/SecurityException
    //   588	595	609	java/lang/SecurityException
  }
  
  /* Error */
  public static boolean bк043Aк043Aк043Aк043Aк043A(@Nullable faafaf.afafaf paramAfafaf)
  {
    // Byte code:
    //   0: iconst_0
    //   1: istore 6
    //   3: invokestatic 928	java/util/TimeZone:getDefault	()Ljava/util/TimeZone;
    //   6: astore 7
    //   8: aload 7
    //   10: ifnull +100 -> 110
    //   13: aload_0
    //   14: aload 7
    //   16: invokevirtual 931	java/util/TimeZone:getRawOffset	()I
    //   19: ldc_w 932
    //   22: idiv
    //   23: putfield 935	kkkkkk/faafaf$afafaf:b0422Т04220422Т0422042204220422Т	I
    //   26: aload_0
    //   27: aload 7
    //   29: invokevirtual 938	java/util/TimeZone:getDSTSavings	()I
    //   32: ldc_w 932
    //   35: idiv
    //   36: putfield 941	kkkkkk/faafaf$afafaf:bТ042204220422Т0422042204220422Т	I
    //   39: getstatic 38	kkkkkk/faafaf:bТ04220422ТТ0422042204220422Т	Ljava/lang/String;
    //   42: astore 7
    //   44: new 413	java/lang/StringBuilder
    //   47: dup
    //   48: ldc_w 943
    //   51: bipush 93
    //   53: iconst_0
    //   54: invokestatic 86	kkkkkk/gguuuu:bккккк043Aкк043A043A	(Ljava/lang/String;CC)Ljava/lang/String;
    //   57: invokespecial 416	java/lang/StringBuilder:<init>	(Ljava/lang/String;)V
    //   60: aload_0
    //   61: getfield 941	kkkkkk/faafaf$afafaf:bТ042204220422Т0422042204220422Т	I
    //   64: invokevirtual 846	java/lang/StringBuilder:append	(I)Ljava/lang/StringBuilder;
    //   67: astore 8
    //   69: aload 8
    //   71: ldc_w 945
    //   74: bipush 88
    //   76: iconst_5
    //   77: invokestatic 86	kkkkkk/gguuuu:bккккк043Aкк043A043A	(Ljava/lang/String;CC)Ljava/lang/String;
    //   80: invokevirtual 505	java/lang/StringBuilder:append	(Ljava/lang/String;)Ljava/lang/StringBuilder;
    //   83: astore 8
    //   85: aload 8
    //   87: aload_0
    //   88: getfield 935	kkkkkk/faafaf$afafaf:b0422Т04220422Т0422042204220422Т	I
    //   91: invokevirtual 846	java/lang/StringBuilder:append	(I)Ljava/lang/StringBuilder;
    //   94: astore_0
    //   95: aload 7
    //   97: aload_0
    //   98: invokevirtual 421	java/lang/StringBuilder:toString	()Ljava/lang/String;
    //   101: invokestatic 370	kkkkkk/fafffa:b043Aккк043Aк043Aкк043A	(Ljava/lang/String;Ljava/lang/String;)V
    //   104: iconst_1
    //   105: istore 6
    //   107: iload 6
    //   109: ireturn
    //   110: getstatic 90	kkkkkk/faafaf:b0422ТТ0422Т0422042204220422Т	I
    //   113: istore_1
    //   114: iload_1
    //   115: getstatic 92	kkkkkk/faafaf:b04220422Т0422Т0422042204220422Т	I
    //   118: iload_1
    //   119: iadd
    //   120: imul
    //   121: getstatic 94	kkkkkk/faafaf:bТТ04220422Т0422042204220422Т	I
    //   124: irem
    //   125: tableswitch	default:+19->144, 0:+30->155
    //   144: invokestatic 99	kkkkkk/faafaf:bк043Aкк043Aкк043Aк043A	()I
    //   147: putstatic 90	kkkkkk/faafaf:b0422ТТ0422Т0422042204220422Т	I
    //   150: bipush 43
    //   152: putstatic 96	kkkkkk/faafaf:bТ0422Т0422Т0422042204220422Т	I
    //   155: getstatic 90	kkkkkk/faafaf:b0422ТТ0422Т0422042204220422Т	I
    //   158: istore_1
    //   159: getstatic 92	kkkkkk/faafaf:b04220422Т0422Т0422042204220422Т	I
    //   162: istore_2
    //   163: getstatic 90	kkkkkk/faafaf:b0422ТТ0422Т0422042204220422Т	I
    //   166: istore_3
    //   167: getstatic 94	kkkkkk/faafaf:bТТ04220422Т0422042204220422Т	I
    //   170: istore 4
    //   172: getstatic 96	kkkkkk/faafaf:bТ0422Т0422Т0422042204220422Т	I
    //   175: istore 5
    //   177: iload_1
    //   178: iload_2
    //   179: iadd
    //   180: iload_3
    //   181: imul
    //   182: iload 4
    //   184: irem
    //   185: iload 5
    //   187: if_icmpeq -80 -> 107
    //   190: invokestatic 99	kkkkkk/faafaf:bк043Aкк043Aкк043Aк043A	()I
    //   193: putstatic 90	kkkkkk/faafaf:b0422ТТ0422Т0422042204220422Т	I
    //   196: bipush 60
    //   198: putstatic 96	kkkkkk/faafaf:bТ0422Т0422Т0422042204220422Т	I
    //   201: iconst_0
    //   202: ireturn
    //   203: astore_0
    //   204: aload_0
    //   205: athrow
    //   206: astore_0
    //   207: aload_0
    //   208: athrow
    //   209: astore_0
    //   210: aload_0
    //   211: athrow
    //   212: astore_0
    //   213: aload_0
    //   214: athrow
    // Local variable table:
    //   start	length	slot	name	signature
    //   0	215	0	paramAfafaf	faafaf.afafaf
    //   113	67	1	i	int
    //   162	18	2	j	int
    //   166	16	3	k	int
    //   170	15	4	m	int
    //   175	13	5	n	int
    //   1	107	6	bool	boolean
    //   6	90	7	localObject	Object
    //   67	19	8	localStringBuilder	StringBuilder
    // Exception table:
    //   from	to	target	type
    //   190	201	203	java/lang/Exception
    //   3	8	206	java/lang/Exception
    //   13	69	206	java/lang/Exception
    //   85	95	206	java/lang/Exception
    //   155	177	209	java/lang/Exception
    //   207	209	209	java/lang/Exception
    //   213	215	209	java/lang/Exception
    //   69	85	212	java/lang/Exception
    //   95	104	212	java/lang/Exception
  }
  
  @Nonnull
  public static String bк043Aкк043A043Aк043Aк043A(aaffaf paramAaffaf)
  {
    throw new Runtime("d2j fail translate: java.lang.IndexOutOfBoundsException: fromIndex < 0: -1\n\tat java.util.BitSet.nextSetBit(BitSet.java:712)\n\tat com.googlecode.dex2jar.ir.ts.array.FillArrayTransformer.makeSureAllElementAreAssigned(FillArrayTransformer.java:505)\n\tat com.googlecode.dex2jar.ir.ts.array.FillArrayTransformer.transformReportChanged(FillArrayTransformer.java:123)\n\tat com.googlecode.dex2jar.ir.ts.StatedTransformer.transform(StatedTransformer.java:10)\n\tat com.googlecode.d2j.dex.Dex2jar$2.optimize(Dex2jar.java:149)\n\tat com.googlecode.d2j.dex.Dex2Asm.convertCode(Dex2Asm.java:414)\n\tat com.googlecode.d2j.dex.ExDex2Asm.convertCode(ExDex2Asm.java:42)\n\tat com.googlecode.d2j.dex.Dex2jar$2.convertCode(Dex2jar.java:128)\n\tat com.googlecode.d2j.dex.Dex2Asm.convertMethod(Dex2Asm.java:509)\n\tat com.googlecode.d2j.dex.Dex2Asm.convertClass(Dex2Asm.java:406)\n\tat com.googlecode.d2j.dex.Dex2Asm.convertDex(Dex2Asm.java:422)\n\tat com.googlecode.d2j.dex.Dex2jar.doTranslate(Dex2jar.java:172)\n\tat com.googlecode.d2j.dex.Dex2jar.to(Dex2jar.java:272)\n\tat com.googlecode.dex2jar.tools.Dex2jarCmd.doCommandLine(Dex2jarCmd.java:108)\n\tat com.googlecode.dex2jar.tools.BaseCmd.doMain(BaseCmd.java:288)\n\tat com.googlecode.dex2jar.tools.Dex2jarCmd.main(Dex2jarCmd.java:32)\n");
  }
  
  public static int bк043Aкк043Aкк043Aк043A()
  {
    return 42;
  }
  
  @Nullable
  public static String bк043Aккк043Aк043Aк043A(@Nonnull aaffaf paramAaffaf)
  {
    tttjtt.jjtttt localJjtttt = new tttjtt.jjtttt(paramAaffaf);
    String str;
    if (localJjtttt.bюююю044E044E044E044Eю044E != null)
    {
      str = localJjtttt.bюююю044E044E044E044Eю044E.dataDir;
      if (dvdddv.bк043A043A043Aк043Aкк043Aк().bккк043Aк043Aкк043Aк(str) == 1)
      {
        paramAaffaf = gguuuu.bккккк043Aкк043A043A("\t377//", '\027', '\001');
        return paramAaffaf;
        label50:
        i += 1;
      }
      for (;;)
      {
        int j;
        if (i < j)
        {
          str = arrayOfString[i];
          if ((!str.contains(gguuuu.bккккк043Aкк043A043A("7", 'õ', '\005'))) || (str.equalsIgnoreCase(paramAaffaf.b0422042204220422Т0422042204220422Т.getPackageName()))) {
            break label50;
          }
          str = gguuuu.bккккк043Aкк043A043A("Aiki_]", '+', '\002');
          paramAaffaf = str;
          if ((b0422ТТ0422Т0422042204220422Т + b04220422Т0422Т0422042204220422Т) * b0422ТТ0422Т0422042204220422Т % bТТ04220422Т0422042204220422Т == bТ0422Т0422Т0422042204220422Т) {
            break;
          }
          if ((b0422ТТ0422Т0422042204220422Т + b04220422Т0422Т0422042204220422Т) * b0422ТТ0422Т0422042204220422Т % bТТ04220422Т0422042204220422Т != bТ0422Т0422Т0422042204220422Т)
          {
            b0422ТТ0422Т0422042204220422Т = bк043Aкк043Aкк043Aк043A();
            bТ0422Т0422Т0422042204220422Т = bк043Aкк043Aкк043Aк043A();
          }
          b0422ТТ0422Т0422042204220422Т = 18;
          bТ0422Т0422Т0422042204220422Т = bк043Aкк043Aкк043Aк043A();
          return str;
          String[] arrayOfString = str.split(gguuuu.bккккк043Aкк043A043A("\031", 'ó', '\004'));
          j = arrayOfString.length;
          i = 0;
          continue;
          if (paramAaffaf.length <= 1) {
            break label313;
          }
          return gguuuu.bккккк043Aкк043A043A("8`b`VT", 'Ä', '\003');
        }
      }
    }
    label216:
    for (int i = -1;; i = localJjtttt.bюююю044E044E044E044Eю044E.uid)
    {
      paramAaffaf = paramAaffaf.getPackagesForUid(i);
      if (paramAaffaf == null) {
        break label313;
      }
      switch (0)
      {
      }
      for (;;)
      {
        switch (0)
        {
        }
      }
      str = "";
      break;
      paramAaffaf = paramAaffaf.b0422042204220422Т0422042204220422Т.getPackageManager();
      if (localJjtttt.bюююю044E044E044E044Eю044E == null) {
        break label216;
      }
    }
    label313:
    return gguuuu.bккккк043Aкк043A043A("1SY\006*TXXPP", 'b', '\000');
  }
  
  /* Error */
  public static String bкк043A043A043Aкк043Aк043A(@Nonnull aaffaf paramAaffaf)
  {
    // Byte code:
    //   0: invokestatic 185	kkkkkk/tttjtt$jtjttt:bк043Aк043Aк043A043Aккк	()Z
    //   3: ifne +179 -> 182
    //   6: aconst_null
    //   7: areturn
    //   8: aload_0
    //   9: instanceof 342
    //   12: ifeq +536 -> 548
    //   15: aload 7
    //   17: invokevirtual 273	android/telephony/TelephonyManager:getCellLocation	()Landroid/telephony/CellLocation;
    //   20: checkcast 342	android/telephony/cdma/CdmaCellLocation
    //   23: astore_0
    //   24: aload_0
    //   25: invokevirtual 350	android/telephony/cdma/CdmaCellLocation:getBaseStationId	()I
    //   28: istore_1
    //   29: aload_0
    //   30: invokevirtual 345	android/telephony/cdma/CdmaCellLocation:getSystemId	()I
    //   33: istore_2
    //   34: aload_0
    //   35: invokevirtual 987	android/telephony/cdma/CdmaCellLocation:getNetworkId	()I
    //   38: istore_3
    //   39: iload_1
    //   40: iconst_m1
    //   41: if_icmpne +13 -> 54
    //   44: iload_2
    //   45: iconst_m1
    //   46: if_icmpne +8 -> 54
    //   49: iload_3
    //   50: iconst_m1
    //   51: if_icmpeq -45 -> 6
    //   54: aload 8
    //   56: ldc_w 989
    //   59: sipush 138
    //   62: sipush 229
    //   65: iconst_3
    //   66: invokestatic 66	kkkkkk/gguuuu:bк043Aккк043Aкк043A043A	(Ljava/lang/String;CCC)Ljava/lang/String;
    //   69: invokevirtual 505	java/lang/StringBuilder:append	(Ljava/lang/String;)Ljava/lang/StringBuilder;
    //   72: pop
    //   73: iload_1
    //   74: iconst_m1
    //   75: if_icmpeq +10 -> 85
    //   78: aload 8
    //   80: iload_1
    //   81: invokevirtual 846	java/lang/StringBuilder:append	(I)Ljava/lang/StringBuilder;
    //   84: pop
    //   85: aload 8
    //   87: ldc_w 991
    //   90: sipush 206
    //   93: iconst_2
    //   94: invokestatic 86	kkkkkk/gguuuu:bккккк043Aкк043A043A	(Ljava/lang/String;CC)Ljava/lang/String;
    //   97: invokevirtual 505	java/lang/StringBuilder:append	(Ljava/lang/String;)Ljava/lang/StringBuilder;
    //   100: pop
    //   101: getstatic 90	kkkkkk/faafaf:b0422ТТ0422Т0422042204220422Т	I
    //   104: getstatic 92	kkkkkk/faafaf:b04220422Т0422Т0422042204220422Т	I
    //   107: iadd
    //   108: getstatic 90	kkkkkk/faafaf:b0422ТТ0422Т0422042204220422Т	I
    //   111: imul
    //   112: getstatic 94	kkkkkk/faafaf:bТТ04220422Т0422042204220422Т	I
    //   115: irem
    //   116: getstatic 96	kkkkkk/faafaf:bТ0422Т0422Т0422042204220422Т	I
    //   119: if_icmpeq +14 -> 133
    //   122: invokestatic 99	kkkkkk/faafaf:bк043Aкк043Aкк043Aк043A	()I
    //   125: putstatic 90	kkkkkk/faafaf:b0422ТТ0422Т0422042204220422Т	I
    //   128: bipush 10
    //   130: putstatic 96	kkkkkk/faafaf:bТ0422Т0422Т0422042204220422Т	I
    //   133: iload_2
    //   134: iconst_m1
    //   135: if_icmpeq +10 -> 145
    //   138: aload 8
    //   140: iload_2
    //   141: invokevirtual 846	java/lang/StringBuilder:append	(I)Ljava/lang/StringBuilder;
    //   144: pop
    //   145: aload 8
    //   147: ldc_w 993
    //   150: bipush 31
    //   152: bipush 94
    //   154: iconst_2
    //   155: invokestatic 66	kkkkkk/gguuuu:bк043Aккк043Aкк043A043A	(Ljava/lang/String;CCC)Ljava/lang/String;
    //   158: invokevirtual 505	java/lang/StringBuilder:append	(Ljava/lang/String;)Ljava/lang/StringBuilder;
    //   161: pop
    //   162: iload_3
    //   163: iconst_m1
    //   164: if_icmpeq +10 -> 174
    //   167: aload 8
    //   169: iload_3
    //   170: invokevirtual 846	java/lang/StringBuilder:append	(I)Ljava/lang/StringBuilder;
    //   173: pop
    //   174: aload 8
    //   176: invokevirtual 421	java/lang/StringBuilder:toString	()Ljava/lang/String;
    //   179: astore_0
    //   180: aload_0
    //   181: areturn
    //   182: new 233	kkkkkk/tttjtt$tjjttt
    //   185: dup
    //   186: new 235	kkkkkk/tttjtt
    //   189: dup
    //   190: invokespecial 236	kkkkkk/tttjtt:<init>	()V
    //   193: aload_0
    //   194: getfield 133	kkkkkk/faafaf$aaffaf:b0422042204220422Т0422042204220422Т	Landroid/content/Context;
    //   197: invokespecial 239	kkkkkk/tttjtt$tjjttt:<init>	(Lkkkkkk/tttjtt;Landroid/content/Context;)V
    //   200: astore 6
    //   202: aload 6
    //   204: ldc_w 995
    //   207: sipush 190
    //   210: iconst_1
    //   211: invokestatic 86	kkkkkk/gguuuu:bккккк043Aкк043A043A	(Ljava/lang/String;CC)Ljava/lang/String;
    //   214: aload_0
    //   215: getfield 133	kkkkkk/faafaf$aaffaf:b0422042204220422Т0422042204220422Т	Landroid/content/Context;
    //   218: invokevirtual 244	android/content/Context:getPackageName	()Ljava/lang/String;
    //   221: invokevirtual 248	kkkkkk/tttjtt$tjjttt:bк043Aк043A043Aк043Aккк	(Ljava/lang/String;Ljava/lang/String;)Z
    //   224: istore 4
    //   226: aload 6
    //   228: ldc_w 997
    //   231: sipush 254
    //   234: bipush 99
    //   236: iconst_3
    //   237: invokestatic 66	kkkkkk/gguuuu:bк043Aккк043Aкк043A043A	(Ljava/lang/String;CCC)Ljava/lang/String;
    //   240: aload_0
    //   241: getfield 133	kkkkkk/faafaf$aaffaf:b0422042204220422Т0422042204220422Т	Landroid/content/Context;
    //   244: invokevirtual 244	android/content/Context:getPackageName	()Ljava/lang/String;
    //   247: invokevirtual 248	kkkkkk/tttjtt$tjjttt:bк043Aк043A043Aк043Aккк	(Ljava/lang/String;Ljava/lang/String;)Z
    //   250: istore 5
    //   252: iload 4
    //   254: ifne +8 -> 262
    //   257: iload 5
    //   259: ifeq -253 -> 6
    //   262: getstatic 155	kkkkkk/tttjtt$tjtttt$jttttt:bююю044Eюююю044E044E	I
    //   265: getstatic 253	kkkkkk/tttjtt$tjtttt$vddddd:bюю044E044E044Eююю044E044E	I
    //   268: if_icmplt +252 -> 520
    //   271: aload_0
    //   272: getfield 133	kkkkkk/faafaf$aaffaf:b0422042204220422Т0422042204220422Т	Landroid/content/Context;
    //   275: invokestatic 1001	com/threatmetrix/TrustDefender/internal/R:do	(Landroid/content/Context;)Ljava/lang/String;
    //   278: astore 6
    //   280: aload 6
    //   282: invokestatic 1004	kkkkkk/dvdvvd:b043A043Aк043Aк043A043A043Aкк	(Ljava/lang/String;)Z
    //   285: ifeq +263 -> 548
    //   288: invokestatic 266	kkkkkk/tttjtt$jtjttt:b043Aкк043Aк043A043Aккк	()Z
    //   291: ifne +9 -> 300
    //   294: invokestatic 269	kkkkkk/tttjtt$jtjttt:b043A043Aк043Aк043A043Aккк	()Z
    //   297: ifeq +251 -> 548
    //   300: aload_0
    //   301: getfield 133	kkkkkk/faafaf$aaffaf:b0422042204220422Т0422042204220422Т	Landroid/content/Context;
    //   304: invokevirtual 191	android/content/Context:getApplicationContext	()Landroid/content/Context;
    //   307: ldc_w 1006
    //   310: bipush 13
    //   312: iconst_2
    //   313: invokestatic 86	kkkkkk/gguuuu:bккккк043Aкк043A043A	(Ljava/lang/String;CC)Ljava/lang/String;
    //   316: invokevirtual 197	android/content/Context:getSystemService	(Ljava/lang/String;)Ljava/lang/Object;
    //   319: astore_0
    //   320: aload_0
    //   321: ifnull -315 -> 6
    //   324: goto +227 -> 551
    //   327: aload_0
    //   328: instanceof 199
    //   331: istore 4
    //   333: getstatic 90	kkkkkk/faafaf:b0422ТТ0422Т0422042204220422Т	I
    //   336: getstatic 92	kkkkkk/faafaf:b04220422Т0422Т0422042204220422Т	I
    //   339: iadd
    //   340: getstatic 90	kkkkkk/faafaf:b0422ТТ0422Т0422042204220422Т	I
    //   343: imul
    //   344: getstatic 94	kkkkkk/faafaf:bТТ04220422Т0422042204220422Т	I
    //   347: irem
    //   348: getstatic 96	kkkkkk/faafaf:bТ0422Т0422Т0422042204220422Т	I
    //   351: if_icmpeq +14 -> 365
    //   354: bipush 46
    //   356: putstatic 90	kkkkkk/faafaf:b0422ТТ0422Т0422042204220422Т	I
    //   359: invokestatic 99	kkkkkk/faafaf:bк043Aкк043Aкк043Aк043A	()I
    //   362: putstatic 96	kkkkkk/faafaf:bТ0422Т0422Т0422042204220422Т	I
    //   365: iload 4
    //   367: ifeq -361 -> 6
    //   370: aload_0
    //   371: checkcast 199	android/telephony/TelephonyManager
    //   374: astore 7
    //   376: aload 7
    //   378: invokevirtual 273	android/telephony/TelephonyManager:getCellLocation	()Landroid/telephony/CellLocation;
    //   381: astore_0
    //   382: aload_0
    //   383: ifnull +165 -> 548
    //   386: new 413	java/lang/StringBuilder
    //   389: dup
    //   390: invokespecial 502	java/lang/StringBuilder:<init>	()V
    //   393: astore 8
    //   395: aload_0
    //   396: instanceof 275
    //   399: ifeq -391 -> 8
    //   402: aload 7
    //   404: invokevirtual 273	android/telephony/TelephonyManager:getCellLocation	()Landroid/telephony/CellLocation;
    //   407: checkcast 275	android/telephony/gsm/GsmCellLocation
    //   410: astore_0
    //   411: aload_0
    //   412: invokevirtual 287	android/telephony/gsm/GsmCellLocation:getCid	()I
    //   415: istore_1
    //   416: aload_0
    //   417: invokevirtual 278	android/telephony/gsm/GsmCellLocation:getLac	()I
    //   420: istore_2
    //   421: iload_1
    //   422: iconst_m1
    //   423: if_icmpne +8 -> 431
    //   426: iload_2
    //   427: iconst_m1
    //   428: if_icmpeq -422 -> 6
    //   431: aload 8
    //   433: ldc_w 1008
    //   436: bipush 92
    //   438: sipush 207
    //   441: iconst_2
    //   442: invokestatic 66	kkkkkk/gguuuu:bк043Aккк043Aкк043A043A	(Ljava/lang/String;CCC)Ljava/lang/String;
    //   445: invokevirtual 505	java/lang/StringBuilder:append	(Ljava/lang/String;)Ljava/lang/StringBuilder;
    //   448: pop
    //   449: iload_1
    //   450: iconst_m1
    //   451: if_icmpeq +10 -> 461
    //   454: aload 8
    //   456: iload_1
    //   457: invokevirtual 846	java/lang/StringBuilder:append	(I)Ljava/lang/StringBuilder;
    //   460: pop
    //   461: aload 8
    //   463: ldc_w 1010
    //   466: sipush 144
    //   469: iconst_2
    //   470: invokestatic 86	kkkkkk/gguuuu:bккккк043Aкк043A043A	(Ljava/lang/String;CC)Ljava/lang/String;
    //   473: invokevirtual 505	java/lang/StringBuilder:append	(Ljava/lang/String;)Ljava/lang/StringBuilder;
    //   476: pop
    //   477: iload_2
    //   478: iconst_m1
    //   479: if_icmpeq +10 -> 489
    //   482: aload 8
    //   484: iload_2
    //   485: invokevirtual 846	java/lang/StringBuilder:append	(I)Ljava/lang/StringBuilder;
    //   488: pop
    //   489: aload 8
    //   491: invokevirtual 421	java/lang/StringBuilder:toString	()Ljava/lang/String;
    //   494: astore_0
    //   495: aload_0
    //   496: areturn
    //   497: astore_0
    //   498: aload_0
    //   499: invokevirtual 375	java/lang/SecurityException:getMessage	()Ljava/lang/String;
    //   502: pop
    //   503: aload 6
    //   505: areturn
    //   506: astore_0
    //   507: getstatic 38	kkkkkk/faafaf:bТ04220422ТТ0422042204220422Т	Ljava/lang/String;
    //   510: aload_0
    //   511: invokevirtual 366	java/lang/Exception:toString	()Ljava/lang/String;
    //   514: invokestatic 370	kkkkkk/fafffa:b043Aккк043Aк043Aкк043A	(Ljava/lang/String;Ljava/lang/String;)V
    //   517: aload 6
    //   519: areturn
    //   520: aconst_null
    //   521: astore 6
    //   523: goto -243 -> 280
    //   526: astore_0
    //   527: aconst_null
    //   528: astore_0
    //   529: goto -147 -> 382
    //   532: astore_0
    //   533: getstatic 38	kkkkkk/faafaf:bТ04220422ТТ0422042204220422Т	Ljava/lang/String;
    //   536: aload_0
    //   537: invokevirtual 366	java/lang/Exception:toString	()Ljava/lang/String;
    //   540: invokestatic 370	kkkkkk/fafffa:b043Aккк043Aк043Aкк043A	(Ljava/lang/String;Ljava/lang/String;)V
    //   543: aconst_null
    //   544: astore_0
    //   545: goto -163 -> 382
    //   548: aload 6
    //   550: areturn
    //   551: iconst_0
    //   552: tableswitch	default:+24->576, 0:+-225->327, 1:+-1->551
    //   576: iconst_1
    //   577: tableswitch	default:+23->600, 0:+-26->551, 1:+-250->327
    //   600: goto -24 -> 576
    // Local variable table:
    //   start	length	slot	name	signature
    //   0	603	0	paramAaffaf	aaffaf
    //   28	429	1	i	int
    //   33	452	2	j	int
    //   38	132	3	k	int
    //   224	142	4	bool1	boolean
    //   250	8	5	bool2	boolean
    //   200	349	6	localObject	Object
    //   15	388	7	localTelephonyManager	android.telephony.TelephonyManager
    //   54	436	8	localStringBuilder	StringBuilder
    // Exception table:
    //   from	to	target	type
    //   8	39	497	java/lang/SecurityException
    //   54	73	497	java/lang/SecurityException
    //   78	85	497	java/lang/SecurityException
    //   85	101	497	java/lang/SecurityException
    //   138	145	497	java/lang/SecurityException
    //   145	162	497	java/lang/SecurityException
    //   167	174	497	java/lang/SecurityException
    //   174	180	497	java/lang/SecurityException
    //   300	320	497	java/lang/SecurityException
    //   327	333	497	java/lang/SecurityException
    //   370	376	497	java/lang/SecurityException
    //   386	421	497	java/lang/SecurityException
    //   431	449	497	java/lang/SecurityException
    //   454	461	497	java/lang/SecurityException
    //   461	477	497	java/lang/SecurityException
    //   482	489	497	java/lang/SecurityException
    //   489	495	497	java/lang/SecurityException
    //   533	543	497	java/lang/SecurityException
    //   8	39	506	java/lang/Exception
    //   54	73	506	java/lang/Exception
    //   78	85	506	java/lang/Exception
    //   85	101	506	java/lang/Exception
    //   138	145	506	java/lang/Exception
    //   145	162	506	java/lang/Exception
    //   167	174	506	java/lang/Exception
    //   174	180	506	java/lang/Exception
    //   300	320	506	java/lang/Exception
    //   327	333	506	java/lang/Exception
    //   370	376	506	java/lang/Exception
    //   386	421	506	java/lang/Exception
    //   431	449	506	java/lang/Exception
    //   454	461	506	java/lang/Exception
    //   461	477	506	java/lang/Exception
    //   482	489	506	java/lang/Exception
    //   489	495	506	java/lang/Exception
    //   533	543	506	java/lang/Exception
    //   376	382	526	java/lang/SecurityException
    //   376	382	532	java/lang/Exception
  }
  
  @Nonnull
  public static List<String> bкк043A043Aк043Aк043Aк043A(@Nonnull aaffaf paramAaffaf, @Nullable List<String> paramList)
    throws InterruptedException
  {
    ArrayList localArrayList;
    boolean bool;
    int k;
    try
    {
      localArrayList = new ArrayList();
      if (paramList == null) {
        break label1716;
      }
      bool = paramList.isEmpty();
    }
    catch (Exception paramAaffaf)
    {
      String str1;
      Object localObject3;
      throw paramAaffaf;
    }
    if (k < paramList.size())
    {
      str1 = (String)paramList.get(k);
      try
      {
        if (!Thread.currentThread().isInterrupted()) {
          break label859;
        }
        throw new InterruptedException();
      }
      catch (Exception paramAaffaf)
      {
        throw paramAaffaf;
      }
      if (str1.startsWith(gguuuu.bк043Aккк043Aкк043A043A("H6=J\022\b\t", '\034', '¶', '\003')))
      {
        paramAaffaf = str1.substring(7);
        if ((localObject3 == null) || (!dvdvvd.b043Aкк043Aк043A043A043Aкк(paramAaffaf))) {
          break label1637;
        }
        bool = ((String)localObject3).contains(paramAaffaf);
        break label1729;
      }
    }
    for (;;)
    {
      label119:
      tttjtt.tjjttt localTjjttt;
      if (bool)
      {
        localArrayList.add(str1);
        break label1720;
        if (str1.startsWith(gguuuu.bк043Aккк043Aкк043A043A("kgd8./", 'D', 'È', '\001')))
        {
          bool = localTjjttt.b043A043Aк043A043Aк043Aккк(str1.substring(6), tttjtt.ddvddd.b044Eююю044E044Eюю044E044E);
          j = 0;
          continue;
        }
      }
      label291:
      label304:
      label389:
      label391:
      label397:
      label427:
      label652:
      label685:
      label859:
      label916:
      label952:
      label1396:
      label1480:
      label1556:
      label1634:
      label1637:
      label1654:
      do
      {
        String[] arrayOfString = dvdddv.bк043A043A043Aк043Aкк043Aк().bкк043Aк043A043Aкк043Aк((String[])paramList.toArray(new String[paramList.size()]));
        Object localObject2 = bккккк043Aк043Aк043A(paramAaffaf, false);
        break label1734;
        localObject3 = tttjtt.tjtttt.b044E044Eю044E044E044E044E044Eю044E;
        localTjjttt = new tttjtt.tjjttt(new tttjtt(), paramAaffaf.b0422042204220422Т0422042204220422Т);
        Object localObject4 = new HashMap();
        int i = 0;
        k = 0;
        break;
        for (;;)
        {
          localArrayList.add(gguuuu.bк043Aккк043Aкк043A043A("5", ' ', '', '\002') + paramAaffaf);
          i += 1;
          if (i >= j) {
            break;
          }
          paramAaffaf = arrayOfString[i];
        }
        String str2;
        bool = str2.equals(gguuuu.bк043Aккк043Aкк043A043A("\023\017L\022\005\007}F{w\nyA\b\006s", '', 'B', '\002'));
        String str3;
        if (bool)
        {
          j = b0422ТТ0422Т0422042204220422Т;
          switch (j * (b04220422Т0422Т0422042204220422Т + j) % bТТ04220422Т0422042204220422Т)
          {
          default: 
            b0422ТТ0422Т0422042204220422Т = bк043Aкк043Aкк043Aк043A();
            bТ0422Т0422Т0422042204220422Т = 84;
          }
          bool = str3.equalsIgnoreCase(String.valueOf(tttjtt.tjtttt.bюю044E044E044E044E044E044Eю044E));
          if (!bool)
          {
            j = 0;
            bool = false;
            break label119;
          }
        }
        Object localObject1;
        try
        {
          new StringBuilder(gguuuu.bккккк043Aкк043A043A("=Ybf``\035rn hgw$zxs(|msqzs/v\004\002\001N5", 'û', '\001')).append(paramAaffaf);
          bool = false;
          j = 0;
        }
        catch (URISyntaxException paramAaffaf) {}
        if (str1.startsWith(gguuuu.bккккк043Aкк043A043A("njA78", ',', '\001')))
        {
          localObject1 = str1.substring(5).split(gguuuu.bк043Aккк043Aкк043A043A("\035\001", 'ñ', 'Ì', '\003'), 2);
          if ((localObject1.length == 2) && (((Map)localObject2).size() > 0))
          {
            paramAaffaf = localObject1[0];
            localObject1 = localObject1[1];
            str2 = (String)((Map)localObject2).get(gguuuu.bккккк043Aкк043A043A("WZ", '÷', '\001'));
            str3 = (String)((Map)localObject2).get(gguuuu.bккккк043Aкк043A043A(".%", '\035', '\004'));
            String str4 = (String)((Map)localObject2).get(gguuuu.bк043Aккк043Aкк043A043A("FL", '#', '½', '\003'));
            if (((!gguuuu.bккккк043Aкк043A043A("i`fdZ", 'Ö', '\002').equalsIgnoreCase(paramAaffaf)) || (!((String)localObject1).equalsIgnoreCase(str2))) && ((!gguuuu.bк043Aккк043Aкк043A043A("Z_f]", '', '\037', '\001').equalsIgnoreCase(paramAaffaf)) || (!((String)localObject1).equalsIgnoreCase(str3))))
            {
              if (gguuuu.bк043Aккк043Aкк043A043A("z}tw", '\037', 'O', '\002').equalsIgnoreCase(paramAaffaf))
              {
                bool = ((String)localObject1).equalsIgnoreCase(str4);
                if (!bool) {}
              }
            }
            else
            {
              bool = true;
              j = 0;
              break label119;
              paramAaffaf = (String)faaaff.bк043A043A043A043Aк043A043Aк043A(null, (Method)localObject4, new Object[] { paramAaffaf });
              if (dvdvvd.b043Aкк043Aк043A043A043Aкк(paramAaffaf)) {
                if (paramAaffaf != null)
                {
                  paramAaffaf = (String)((Map)((Map.Entry)localObject2).getValue()).get(paramAaffaf);
                  if (paramAaffaf == null) {
                    break label1654;
                  }
                  j = 1;
                  localArrayList.add(paramAaffaf);
                }
              }
            }
          }
        }
        for (;;)
        {
          paramAaffaf = (String)((Map)((Map.Entry)localObject2).getValue()).get(gguuuu.bккккк043Aкк043A043A("gcg", '§', '\001'));
          k = j;
          if (paramAaffaf != null)
          {
            k = j + 1;
            localArrayList.add(paramAaffaf);
          }
          i += ((Map)((Map.Entry)localObject2).getValue()).size() - k;
          for (;;)
          {
            j = i;
            if (!((Iterator)localObject3).hasNext()) {
              break label1480;
            }
            localObject2 = (Map.Entry)((Iterator)localObject3).next();
            k = 0;
            paramAaffaf = (String)((Map)localObject1).get(((Map.Entry)localObject2).getKey());
            if (paramAaffaf != null) {
              break label1556;
            }
            paramAaffaf = (String)((Map.Entry)localObject2).getKey();
            localObject4 = b042204220422ТТ0422042204220422Т;
            break label1783;
            bool = str1.startsWith(gguuuu.bккккк043Aкк043A043A("quysI?@", '', '\000'));
            if (!bool) {
              break;
            }
            paramAaffaf = new URI(str1);
            if (paramAaffaf.getScheme() == null) {
              break label397;
            }
            bool = new File(paramAaffaf).exists();
            j = 0;
            break label119;
            if (!str2.equals(gguuuu.bккккк043Aкк043A043A("86u+?481{7?DF", 'Ä', '\000'))) {
              break label1396;
            }
            bool = str3.equalsIgnoreCase(tttjtt.tjtttt.b044Eюю044E044E044E044E044Eю044E);
            if (!bool) {
              break label389;
            }
            break label652;
            if (str2.equals(gguuuu.bк043Aккк043Aкк043A043A("ZV\024GYLNE\016HB", 'È', 'Í', '\002')))
            {
              if (!str3.equalsIgnoreCase(tttjtt.tjtttt.bю044Eюю044E044E044E044Eю044E)) {
                break label389;
              }
              break label652;
              if (!str1.startsWith(gguuuu.bккккк043Aкк043A043A("iljl7-.", '»', '\004'))) {
                break label427;
              }
              paramAaffaf = str1.substring(7).split(gguuuu.bккккк043Aкк043A043A("&\b", '', '\003'), 2);
              if (paramAaffaf.length < 2) {
                break label1634;
              }
              str2 = paramAaffaf[0];
              str3 = paramAaffaf[1];
              if (!str2.equals(gguuuu.bк043Aккк043Aкк043A043A("xv6ktxq<\006u\004\006|\004\004Dz\b}\n}\013\004", 'ý', '\007', '\003'))) {
                break label304;
              }
              if (!str3.equalsIgnoreCase(tttjtt.tjtttt.jttttt.bю044E044Eююююю044E044E)) {
                break label389;
              }
              break label652;
            }
            localObject1 = (Map)((Map)localObject4).get(str2);
            paramAaffaf = (aaffaf)localObject1;
            if (localObject1 == null)
            {
              paramAaffaf = new HashMap();
              ((Map)localObject4).put(str2, paramAaffaf);
            }
            paramAaffaf.put(str3, str1);
            j = 1;
            break label391;
            bool = ((Map)localObject4).isEmpty();
            j = i;
            if (bool) {
              break label1480;
            }
            localObject1 = b043Aк043Aкк043Aк043Aк043A(gguuuu.bк043Aккк043Aкк043A043A("H|||v\n\007?\001\002}}", 'Í', '', '\002'), ((Map)localObject4).keySet(), gguuuu.bк043Aккк043Aкк043A043A(">", 'æ', '', '\002'));
            ((Map)localObject1).putAll(b043Aк043Aкк043Aк043Aк043A(gguuuu.bккккк043Aкк043A043A("7zxxho0btgi`)jkgg", 'R', '\002'), ((Map)localObject4).keySet(), gguuuu.bк043Aккк043Aкк043A043A("\t", 'í', '#', '\001')));
            localObject3 = ((Map)localObject4).entrySet().iterator();
          }
          do
          {
            Collections.sort(localArrayList);
            if ((!localArrayList.isEmpty()) && (fafffa.bк043Aкк043Aк043Aкк043A())) {
              dvdvvd.b043Aк043A043Aк043A043A043Aкк(localArrayList, gguuuu.bккккк043Aкк043A043A("y", '¿', '\002'));
            }
            if ((bк043Aкк043Aкк043Aк043A() + b04220422Т0422Т0422042204220422Т) * bк043Aкк043Aкк043Aк043A() % b043Aккк043Aкк043Aк043A() == bТ0422Т0422Т0422042204220422Т) {
              break label1716;
            }
            b0422ТТ0422Т0422042204220422Т = 88;
            bТ0422Т0422Т0422042204220422Т = 37;
            i = b0422ТТ0422Т0422042204220422Т;
            switch (i * (b04220422Т0422Т0422042204220422Т + i) % bТТ04220422Т0422042204220422Т)
            {
            default: 
              b0422ТТ0422Т0422042204220422Т = bк043Aкк043Aкк043Aк043A();
              bТ0422Т0422Т0422042204220422Т = bк043Aкк043Aкк043Aк043A();
              return localArrayList;
              if (str2.equals(gguuuu.bк043Aккк043Aкк043A043A("OM\rBVKOH\023Z`XN", 'V', '\006', '\003')))
              {
                bool = str3.equalsIgnoreCase(tttjtt.tjtttt.bю044E044E044E044E044E044E044Eю044E);
                if (!bool) {
                  break label389;
                }
                break label652;
                if (!str2.equals(gguuuu.bккккк043Aкк043A043A("\005\001>q\004vxo8~{lx", 'ì', '\005'))) {
                  break label952;
                }
                if (!str3.equalsIgnoreCase(tttjtt.tjtttt.bюю044Eю044E044E044E044Eю044E)) {
                  break label389;
                }
                break label652;
              }
              if (!str2.equals(gguuuu.bккккк043Aкк043A043A("64s)=26/yA/6C", 'ê', '\001'))) {
                break label916;
              }
              bool = str3.equalsIgnoreCase(tttjtt.tjtttt.b044E044Eю044E044E044E044E044Eю044E);
              if (!bool) {
                break label389;
              }
              break label652;
              if (j != 0) {
                break label1634;
              }
              i += 1;
              break label1720;
              paramAaffaf = null;
              break label685;
              fafffa.b043Aккк043Aк043Aкк043A(bТ04220422ТТ0422042204220422Т, gguuuu.bк043Aккк043Aкк043A043A("7,@0644p", '`', 'h', '\003') + j + gguuuu.bккккк043Aкк043A043A("3", '', '\004') + paramList.size());
            }
          } while ((arrayOfString == null) || (arrayOfString.length <= 0));
          j = arrayOfString.length;
          i = 0;
          break label291;
          if ((b0422ТТ0422Т0422042204220422Т + b04220422Т0422Т0422042204220422Т) * b0422ТТ0422Т0422042204220422Т % bТТ04220422Т0422042204220422Т != bТ0422Т0422Т0422042204220422Т)
          {
            b0422ТТ0422Т0422042204220422Т = 93;
            j = b0422ТТ0422Т0422042204220422Т;
            switch (j * (b04220422Т0422Т0422042204220422Т + j) % bТТ04220422Т0422042204220422Т)
            {
            default: 
              b0422ТТ0422Т0422042204220422Т = 15;
              bТ0422Т0422Т0422042204220422Т = 79;
            }
            bТ0422Т0422Т0422042204220422Т = 84;
            break label685;
            break label1720;
            bool = false;
            break label1729;
            bool = false;
            j = 0;
            break label119;
          }
          break label685;
          j = 0;
        }
        switch (1)
        {
        case 0: 
        default: 
          for (;;)
          {
            switch (0)
            {
            }
          }
        }
      } while (!bool);
      label1716:
      return localArrayList;
      label1720:
      k += 1;
      break;
      label1729:
      int j = 0;
    }
    label1734:
    switch (0)
    {
    }
    for (;;)
    {
      switch (1)
      {
      }
    }
    label1783:
    switch (0)
    {
    }
    for (;;)
    {
      switch (1)
      {
      }
    }
  }
  
  public static int bкк043A043Aккк043Aк043A()
  {
    return 0;
  }
  
  public static byte[] bкк043Aк043A043Aк043Aк043A(@Nonnull aaffaf paramAaffaf)
  {
    StringBuilder localStringBuilder = new StringBuilder();
    if (dvdvvd.b043Aкк043Aк043A043A043Aкк(tttjtt.tjtttt.b044E044E044Eю044E044E044E044Eю044E)) {
      localStringBuilder.append(tttjtt.tjtttt.b044E044E044Eю044E044E044E044Eю044E);
    }
    boolean bool = dvdvvd.b043Aкк043Aк043A043A043Aкк(tttjtt.tjtttt.bю044Eю044E044E044E044E044Eю044E);
    if ((bк043Aкк043Aкк043Aк043A() + b04220422Т0422Т0422042204220422Т) * bк043Aкк043Aкк043Aк043A() % bТТ04220422Т0422042204220422Т != bТ0422Т0422Т0422042204220422Т)
    {
      b0422ТТ0422Т0422042204220422Т = bк043Aкк043Aкк043Aк043A();
      bТ0422Т0422Т0422042204220422Т = bк043Aкк043Aкк043Aк043A();
    }
    if (bool) {
      localStringBuilder.append(Build.PRODUCT);
    }
    if (dvdvvd.b043Aкк043Aк043A043A043Aкк(tttjtt.tjtttt.b044E044E044E044E044E044E044E044Eю044E)) {
      localStringBuilder.append(Build.BOARD);
    }
    if (dvdvvd.b043Aкк043Aк043A043A043Aкк(faffaf.bкккккк043A043Aк043A(paramAaffaf))) {
      localStringBuilder.append(faffaf.bкккккк043A043Aк043A(paramAaffaf));
    }
    if (dvdvvd.b043Aкк043Aк043A043A043Aкк(faffaf.b043Aкк043A043A043Aк043Aк043A(paramAaffaf))) {
      localStringBuilder.append(faffaf.b043Aкк043A043A043Aк043Aк043A(paramAaffaf));
    }
    try
    {
      paramAaffaf = MessageDigest.getInstance(gguuuu.bккккк043Aкк043A043A("&\034\f", 'Ò', '\003'));
      paramAaffaf.update(localStringBuilder.toString().getBytes());
      paramAaffaf = paramAaffaf.digest();
      return paramAaffaf;
    }
    catch (NoSuchAlgorithmException paramAaffaf)
    {
      paramAaffaf = null;
      int i = b0422ТТ0422Т0422042204220422Т;
      int j = b04220422Т0422Т0422042204220422Т;
      switch (1)
      {
      case 0: 
      default: 
        for (;;)
        {
          switch (0)
          {
          }
        }
      }
      switch (i * (j + i) % bТТ04220422Т0422042204220422Т)
      {
      }
      b0422ТТ0422Т0422042204220422Т = bк043Aкк043Aкк043Aк043A();
      bТ0422Т0422Т0422042204220422Т = bк043Aкк043Aкк043Aк043A();
    }
    return null;
  }
  
  /* Error */
  public static String bкк043Aк043Aкк043Aк043A(@Nonnull aaffaf paramAaffaf)
  {
    // Byte code:
    //   0: aload_0
    //   1: iconst_1
    //   2: invokestatic 1049	kkkkkk/faafaf:bккккк043Aк043Aк043A	(Lkkkkkk/faafaf$aaffaf;Z)Ljava/util/HashMap;
    //   5: astore_0
    //   6: aload_0
    //   7: invokeinterface 371 1 0
    //   12: ifle +10 -> 22
    //   15: aload_0
    //   16: invokestatic 1220	kkkkkk/dvdvvd:bк043A043A043A043A043A043A043Aкк	(Ljava/util/AbstractMap;)Ljava/lang/String;
    //   19: astore_0
    //   20: aload_0
    //   21: areturn
    //   22: ldc -43
    //   24: astore_0
    //   25: getstatic 90	kkkkkk/faafaf:b0422ТТ0422Т0422042204220422Т	I
    //   28: istore_1
    //   29: iload_1
    //   30: getstatic 92	kkkkkk/faafaf:b04220422Т0422Т0422042204220422Т	I
    //   33: iload_1
    //   34: iadd
    //   35: imul
    //   36: getstatic 94	kkkkkk/faafaf:bТТ04220422Т0422042204220422Т	I
    //   39: irem
    //   40: tableswitch	default:+20->60, 0:+30->70
    //   60: bipush 45
    //   62: putstatic 90	kkkkkk/faafaf:b0422ТТ0422Т0422042204220422Т	I
    //   65: bipush 83
    //   67: putstatic 96	kkkkkk/faafaf:bТ0422Т0422Т0422042204220422Т	I
    //   70: getstatic 90	kkkkkk/faafaf:b0422ТТ0422Т0422042204220422Т	I
    //   73: istore_1
    //   74: getstatic 92	kkkkkk/faafaf:b04220422Т0422Т0422042204220422Т	I
    //   77: istore_2
    //   78: getstatic 94	kkkkkk/faafaf:bТТ04220422Т0422042204220422Т	I
    //   81: istore_3
    //   82: iload_1
    //   83: iload_2
    //   84: iload_1
    //   85: iadd
    //   86: imul
    //   87: iload_3
    //   88: irem
    //   89: tableswitch	default:+19->108, 0:+-69->20
    //   108: invokestatic 99	kkkkkk/faafaf:bк043Aкк043Aкк043Aк043A	()I
    //   111: putstatic 90	kkkkkk/faafaf:b0422ТТ0422Т0422042204220422Т	I
    //   114: invokestatic 99	kkkkkk/faafaf:bк043Aкк043Aкк043Aк043A	()I
    //   117: putstatic 96	kkkkkk/faafaf:bТ0422Т0422Т0422042204220422Т	I
    //   120: ldc -43
    //   122: areturn
    //   123: astore_0
    //   124: aload_0
    //   125: athrow
    //   126: astore_0
    //   127: aload_0
    //   128: athrow
    // Local variable table:
    //   start	length	slot	name	signature
    //   0	129	0	paramAaffaf	aaffaf
    //   28	59	1	i	int
    //   77	9	2	j	int
    //   81	8	3	k	int
    // Exception table:
    //   from	to	target	type
    //   108	120	123	java/lang/Exception
    //   0	20	126	java/lang/Exception
    //   70	82	126	java/lang/Exception
  }
  
  /* Error */
  public static boolean bкк043Aкк043Aк043Aк043A(@Nonnull aaffaf paramAaffaf)
  {
    // Byte code:
    //   0: aload_0
    //   1: getfield 133	kkkkkk/faafaf$aaffaf:b0422042204220422Т0422042204220422Т	Landroid/content/Context;
    //   4: invokevirtual 649	android/content/Context:getContentResolver	()Landroid/content/ContentResolver;
    //   7: ldc_w 1223
    //   10: sipush 172
    //   13: sipush 242
    //   16: iconst_2
    //   17: invokestatic 66	kkkkkk/gguuuu:bк043Aккк043Aкк043A043A	(Ljava/lang/String;CCC)Ljava/lang/String;
    //   20: invokestatic 665	kkkkkk/tttjtt$ttjttt:b043Aккк043A043A043Aккк	(Landroid/content/ContentResolver;Ljava/lang/String;)Ljava/lang/String;
    //   23: astore_0
    //   24: new 625	java/lang/NullPointerException
    //   27: dup
    //   28: invokespecial 626	java/lang/NullPointerException:<init>	()V
    //   31: athrow
    //   32: astore_2
    //   33: invokestatic 99	kkkkkk/faafaf:bк043Aкк043Aкк043Aк043A	()I
    //   36: putstatic 90	kkkkkk/faafaf:b0422ТТ0422Т0422042204220422Т	I
    //   39: new 625	java/lang/NullPointerException
    //   42: dup
    //   43: invokespecial 626	java/lang/NullPointerException:<init>	()V
    //   46: athrow
    //   47: astore_2
    //   48: bipush 62
    //   50: putstatic 90	kkkkkk/faafaf:b0422ТТ0422Т0422042204220422Т	I
    //   53: new 625	java/lang/NullPointerException
    //   56: dup
    //   57: invokespecial 626	java/lang/NullPointerException:<init>	()V
    //   60: athrow
    //   61: astore_2
    //   62: bipush 72
    //   64: putstatic 90	kkkkkk/faafaf:b0422ТТ0422Т0422042204220422Т	I
    //   67: aload_0
    //   68: ifnull +23 -> 91
    //   71: aload_0
    //   72: ldc_w 1225
    //   75: bipush 98
    //   77: iconst_5
    //   78: invokestatic 86	kkkkkk/gguuuu:bккккк043Aкк043A043A	(Ljava/lang/String;CC)Ljava/lang/String;
    //   81: invokevirtual 220	java/lang/String:equals	(Ljava/lang/Object;)Z
    //   84: istore_1
    //   85: iload_1
    //   86: ifeq +5 -> 91
    //   89: iconst_1
    //   90: ireturn
    //   91: getstatic 90	kkkkkk/faafaf:b0422ТТ0422Т0422042204220422Т	I
    //   94: getstatic 92	kkkkkk/faafaf:b04220422Т0422Т0422042204220422Т	I
    //   97: iadd
    //   98: getstatic 90	kkkkkk/faafaf:b0422ТТ0422Т0422042204220422Т	I
    //   101: imul
    //   102: getstatic 94	kkkkkk/faafaf:bТТ04220422Т0422042204220422Т	I
    //   105: irem
    //   106: getstatic 96	kkkkkk/faafaf:bТ0422Т0422Т0422042204220422Т	I
    //   109: if_icmpeq +14 -> 123
    //   112: invokestatic 99	kkkkkk/faafaf:bк043Aкк043Aкк043Aк043A	()I
    //   115: putstatic 90	kkkkkk/faafaf:b0422ТТ0422Т0422042204220422Т	I
    //   118: bipush 16
    //   120: putstatic 96	kkkkkk/faafaf:bТ0422Т0422Т0422042204220422Т	I
    //   123: iconst_0
    //   124: ireturn
    //   125: astore_0
    //   126: aload_0
    //   127: athrow
    //   128: astore_0
    //   129: aload_0
    //   130: athrow
    // Local variable table:
    //   start	length	slot	name	signature
    //   0	131	0	paramAaffaf	aaffaf
    //   84	2	1	bool	boolean
    //   32	1	2	localException1	Exception
    //   47	1	2	localException2	Exception
    //   61	1	2	localException3	Exception
    // Exception table:
    //   from	to	target	type
    //   24	32	32	java/lang/Exception
    //   39	47	47	java/lang/Exception
    //   53	61	61	java/lang/Exception
    //   0	24	125	java/lang/Exception
    //   71	85	125	java/lang/Exception
    //   33	39	128	java/lang/Exception
    //   48	53	128	java/lang/Exception
    //   62	67	128	java/lang/Exception
  }
  
  public static String bккк043A043Aкк043Aк043A(aaffaf paramAaffaf)
  {
    int i = bк043Aкк043Aкк043Aк043A();
    switch (i * (b04220422Т0422Т0422042204220422Т + i) % b043Aккк043Aкк043Aк043A())
    {
    default: 
      b0422ТТ0422Т0422042204220422Т = bк043Aкк043Aкк043Aк043A();
      bТ0422Т0422Т0422042204220422Т = 75;
    }
    paramAaffaf = new tttjtt.jjtttt(paramAaffaf);
    switch (1)
    {
    case 0: 
    default: 
      for (;;)
      {
        switch (1)
        {
        }
      }
    }
    i = bк043Aкк043Aкк043Aк043A();
    switch (i * (b04220422Т0422Т0422042204220422Т + i) % bТТ04220422Т0422042204220422Т)
    {
    default: 
      b0422ТТ0422Т0422042204220422Т = 78;
      bТ0422Т0422Т0422042204220422Т = bк043Aкк043Aкк043Aк043A();
    }
    if (paramAaffaf.bюююю044E044E044E044Eю044E != null) {}
    for (paramAaffaf = paramAaffaf.bюююю044E044E044E044Eю044E.sourceDir;; paramAaffaf = "")
    {
      switch (1)
      {
      case 0: 
      default: 
        for (;;)
        {
          switch (1)
          {
          }
        }
      }
      return paramAaffaf;
    }
  }
  
  /* Error */
  @Nullable
  public static String bккк043Aк043Aк043Aк043A(long paramLong1, long paramLong2)
    throws InterruptedException
  {
    // Byte code:
    //   0: new 413	java/lang/StringBuilder
    //   3: dup
    //   4: invokespecial 502	java/lang/StringBuilder:<init>	()V
    //   7: astore 4
    //   9: aload 4
    //   11: lload_0
    //   12: invokestatic 1061	java/lang/String:valueOf	(J)Ljava/lang/String;
    //   15: invokevirtual 505	java/lang/StringBuilder:append	(Ljava/lang/String;)Ljava/lang/StringBuilder;
    //   18: ldc_w 1233
    //   21: sipush 173
    //   24: iconst_2
    //   25: invokestatic 86	kkkkkk/gguuuu:bккккк043Aкк043A043A	(Ljava/lang/String;CC)Ljava/lang/String;
    //   28: invokevirtual 505	java/lang/StringBuilder:append	(Ljava/lang/String;)Ljava/lang/StringBuilder;
    //   31: astore 4
    //   33: aload 4
    //   35: lload_2
    //   36: invokevirtual 420	java/lang/StringBuilder:append	(J)Ljava/lang/StringBuilder;
    //   39: invokevirtual 421	java/lang/StringBuilder:toString	()Ljava/lang/String;
    //   42: astore 4
    //   44: getstatic 90	kkkkkk/faafaf:b0422ТТ0422Т0422042204220422Т	I
    //   47: getstatic 92	kkkkkk/faafaf:b04220422Т0422Т0422042204220422Т	I
    //   50: iadd
    //   51: getstatic 90	kkkkkk/faafaf:b0422ТТ0422Т0422042204220422Т	I
    //   54: imul
    //   55: getstatic 94	kkkkkk/faafaf:bТТ04220422Т0422042204220422Т	I
    //   58: irem
    //   59: getstatic 96	kkkkkk/faafaf:bТ0422Т0422Т0422042204220422Т	I
    //   62: if_icmpeq +97 -> 159
    //   65: bipush 66
    //   67: putstatic 90	kkkkkk/faafaf:b0422ТТ0422Т0422042204220422Т	I
    //   70: invokestatic 99	kkkkkk/faafaf:bк043Aкк043Aкк043Aк043A	()I
    //   73: putstatic 96	kkkkkk/faafaf:bТ0422Т0422Т0422042204220422Т	I
    //   76: getstatic 90	kkkkkk/faafaf:b0422ТТ0422Т0422042204220422Т	I
    //   79: getstatic 92	kkkkkk/faafaf:b04220422Т0422Т0422042204220422Т	I
    //   82: iadd
    //   83: getstatic 90	kkkkkk/faafaf:b0422ТТ0422Т0422042204220422Т	I
    //   86: imul
    //   87: getstatic 94	kkkkkk/faafaf:bТТ04220422Т0422042204220422Т	I
    //   90: irem
    //   91: invokestatic 641	kkkkkk/faafaf:bкк043A043Aккк043Aк043A	()I
    //   94: if_icmpeq +15 -> 109
    //   97: invokestatic 99	kkkkkk/faafaf:bк043Aкк043Aкк043Aк043A	()I
    //   100: putstatic 90	kkkkkk/faafaf:b0422ТТ0422Т0422042204220422Т	I
    //   103: invokestatic 99	kkkkkk/faafaf:bк043Aкк043Aкк043Aк043A	()I
    //   106: putstatic 96	kkkkkk/faafaf:bТ0422Т0422Т0422042204220422Т	I
    //   109: iconst_0
    //   110: tableswitch	default:+22->132, 0:+49->159, 1:+-1->109
    //   132: iconst_0
    //   133: tableswitch	default:+23->156, 0:+26->159, 1:+-24->109
    //   156: goto -24 -> 132
    //   159: aload 4
    //   161: invokestatic 850	kkkkkk/dvdvvd:bкк043A043A043A043A043A043Aкк	(Ljava/lang/String;)Ljava/lang/String;
    //   164: astore 4
    //   166: getstatic 38	kkkkkk/faafaf:bТ04220422ТТ0422042204220422Т	Ljava/lang/String;
    //   169: astore 5
    //   171: new 413	java/lang/StringBuilder
    //   174: dup
    //   175: ldc_w 1235
    //   178: bipush 113
    //   180: sipush 167
    //   183: iconst_3
    //   184: invokestatic 66	kkkkkk/gguuuu:bк043Aккк043Aкк043A043A	(Ljava/lang/String;CCC)Ljava/lang/String;
    //   187: invokespecial 416	java/lang/StringBuilder:<init>	(Ljava/lang/String;)V
    //   190: astore 6
    //   192: aload 5
    //   194: aload 6
    //   196: aload 4
    //   198: invokevirtual 505	java/lang/StringBuilder:append	(Ljava/lang/String;)Ljava/lang/StringBuilder;
    //   201: invokevirtual 421	java/lang/StringBuilder:toString	()Ljava/lang/String;
    //   204: invokestatic 370	kkkkkk/fafffa:b043Aккк043Aк043Aкк043A	(Ljava/lang/String;Ljava/lang/String;)V
    //   207: aload 4
    //   209: areturn
    //   210: astore 4
    //   212: aload 4
    //   214: athrow
    //   215: astore 4
    //   217: aload 4
    //   219: athrow
    // Local variable table:
    //   start	length	slot	name	signature
    //   0	220	0	paramLong1	long
    //   0	220	2	paramLong2	long
    //   7	201	4	localObject	Object
    //   210	3	4	localException1	Exception
    //   215	3	4	localException2	Exception
    //   169	24	5	str	String
    //   190	5	6	localStringBuilder	StringBuilder
    // Exception table:
    //   from	to	target	type
    //   0	9	210	java/lang/Exception
    //   33	44	210	java/lang/Exception
    //   159	192	210	java/lang/Exception
    //   9	33	215	java/lang/Exception
    //   192	207	215	java/lang/Exception
  }
  
  @Nullable
  public static String bкккк043A043Aк043Aк043A(@Nonnull aaffaf paramAaffaf)
  {
    try
    {
      String str = Settings.System.getString(paramAaffaf.b0422042204220422Т0422042204220422Т.getContentResolver(), gguuuu.bккккк043Aкк043A043A("77G923,:,7.", '\017', '\002'));
      if (str != null) {
        return str;
      }
    }
    catch (RuntimeException localRuntimeException) {}
    for (;;)
    {
      try
      {
        paramAaffaf = paramAaffaf.b0422042204220422Т0422042204220422Т.getContentResolver();
        Object localObject = gguuuu.bккккк043Aкк043A043A("FOWFTNMQD:H:E<", '\034', '\005');
        switch (1)
        {
        case 0: 
        default: 
          if ((b0422ТТ0422Т0422042204220422Т + b04220422Т0422Т0422042204220422Т) * b0422ТТ0422Т0422042204220422Т % bТТ04220422Т0422042204220422Т != bТ0422Т0422Т0422042204220422Т)
          {
            b0422ТТ0422Т0422042204220422Т = 40;
            bТ0422Т0422Т0422042204220422Т = 92;
          }
          switch (1)
          {
          }
          break;
        }
        if ((b0422ТТ0422Т0422042204220422Т + b04220422Т0422Т0422042204220422Т) * b0422ТТ0422Т0422042204220422Т % b043Aккк043Aкк043Aк043A() != bТ0422Т0422Т0422042204220422Т)
        {
          b0422ТТ0422Т0422042204220422Т = bк043Aкк043Aкк043Aк043A();
          bТ0422Т0422Т0422042204220422Т = 13;
        }
        paramAaffaf = Settings.Secure.getString(paramAaffaf, (String)localObject);
        localObject = paramAaffaf;
        if (paramAaffaf != null) {
          break;
        }
      }
      catch (RuntimeException paramAaffaf)
      {
        continue;
      }
      try
      {
        paramAaffaf = BluetoothAdapter.getDefaultAdapter();
        if (paramAaffaf != null)
        {
          paramAaffaf = paramAaffaf.getName();
          return paramAaffaf;
        }
      }
      catch (Exception paramAaffaf) {}
    }
    return null;
  }
  
  public static String bкккк043Aкк043Aк043A(aaffaf paramAaffaf)
  {
    new affaff();
    if ((b0422ТТ0422Т0422042204220422Т + b04220422Т0422Т0422042204220422Т) * b0422ТТ0422Т0422042204220422Т % bТТ04220422Т0422042204220422Т != bТ0422Т0422Т0422042204220422Т)
    {
      b0422ТТ0422Т0422042204220422Т = 82;
      bТ0422Т0422Т0422042204220422Т = 56;
    }
    return affaff.b043A043A043A043Aк043A043A043Aк043A(paramAaffaf.b0422042204220422Т0422042204220422Т);
  }
  
  /* Error */
  @Nonnull
  @android.annotation.SuppressLint({"HardwareIds"})
  private static Map<String, String> bккккк043Aк043Aк043A(@Nonnull aaffaf paramAaffaf, boolean paramBoolean)
  {
    // Byte code:
    //   0: new 201	java/util/HashMap
    //   3: dup
    //   4: invokespecial 202	java/util/HashMap:<init>	()V
    //   7: astore_3
    //   8: new 233	kkkkkk/tttjtt$tjjttt
    //   11: dup
    //   12: new 235	kkkkkk/tttjtt
    //   15: dup
    //   16: invokespecial 236	kkkkkk/tttjtt:<init>	()V
    //   19: aload_0
    //   20: getfield 133	kkkkkk/faafaf$aaffaf:b0422042204220422Т0422042204220422Т	Landroid/content/Context;
    //   23: invokespecial 239	kkkkkk/tttjtt$tjjttt:<init>	(Lkkkkkk/tttjtt;Landroid/content/Context;)V
    //   26: ldc_w 1268
    //   29: sipush 192
    //   32: sipush 174
    //   35: iconst_2
    //   36: invokestatic 66	kkkkkk/gguuuu:bк043Aккк043Aкк043A043A	(Ljava/lang/String;CCC)Ljava/lang/String;
    //   39: aload_0
    //   40: getfield 133	kkkkkk/faafaf$aaffaf:b0422042204220422Т0422042204220422Т	Landroid/content/Context;
    //   43: invokevirtual 244	android/content/Context:getPackageName	()Ljava/lang/String;
    //   46: invokevirtual 248	kkkkkk/tttjtt$tjjttt:bк043Aк043A043Aк043Aккк	(Ljava/lang/String;Ljava/lang/String;)Z
    //   49: istore_2
    //   50: iload_2
    //   51: ifeq +318 -> 369
    //   54: aload_0
    //   55: getfield 133	kkkkkk/faafaf$aaffaf:b0422042204220422Т0422042204220422Т	Landroid/content/Context;
    //   58: invokevirtual 191	android/content/Context:getApplicationContext	()Landroid/content/Context;
    //   61: ldc_w 1270
    //   64: bipush 110
    //   66: sipush 166
    //   69: iconst_2
    //   70: invokestatic 66	kkkkkk/gguuuu:bк043Aккк043Aкк043A043A	(Ljava/lang/String;CCC)Ljava/lang/String;
    //   73: invokevirtual 197	android/content/Context:getSystemService	(Ljava/lang/String;)Ljava/lang/Object;
    //   76: astore 4
    //   78: aload 4
    //   80: ifnull +289 -> 369
    //   83: aload 4
    //   85: instanceof 199
    //   88: ifeq +281 -> 369
    //   91: aload 4
    //   93: checkcast 199	android/telephony/TelephonyManager
    //   96: astore 4
    //   98: aload 4
    //   100: invokevirtual 1273	android/telephony/TelephonyManager:getDeviceId	()Ljava/lang/String;
    //   103: iload_1
    //   104: ldc_w 1275
    //   107: bipush 21
    //   109: iconst_2
    //   110: invokestatic 86	kkkkkk/gguuuu:bккккк043Aкк043A043A	(Ljava/lang/String;CC)Ljava/lang/String;
    //   113: aload_3
    //   114: invokestatic 1279	kkkkkk/dvdvvd:bкк043A043Aк043A043A043Aкк	(Ljava/lang/String;ZLjava/lang/String;Ljava/util/HashMap;)V
    //   117: aload 4
    //   119: invokevirtual 1282	android/telephony/TelephonyManager:getLine1Number	()Ljava/lang/String;
    //   122: iload_1
    //   123: ldc_w 1284
    //   126: bipush 86
    //   128: iconst_2
    //   129: invokestatic 86	kkkkkk/gguuuu:bккккк043Aкк043A043A	(Ljava/lang/String;CC)Ljava/lang/String;
    //   132: aload_3
    //   133: invokestatic 1279	kkkkkk/dvdvvd:bкк043A043Aк043A043A043Aкк	(Ljava/lang/String;ZLjava/lang/String;Ljava/util/HashMap;)V
    //   136: aload 4
    //   138: invokevirtual 1287	android/telephony/TelephonyManager:getSimSerialNumber	()Ljava/lang/String;
    //   141: astore 5
    //   143: ldc_w 1289
    //   146: sipush 135
    //   149: bipush 84
    //   151: iconst_1
    //   152: invokestatic 66	kkkkkk/gguuuu:bк043Aккк043Aкк043A043A	(Ljava/lang/String;CCC)Ljava/lang/String;
    //   155: astore 6
    //   157: getstatic 90	kkkkkk/faafaf:b0422ТТ0422Т0422042204220422Т	I
    //   160: getstatic 92	kkkkkk/faafaf:b04220422Т0422Т0422042204220422Т	I
    //   163: iadd
    //   164: getstatic 90	kkkkkk/faafaf:b0422ТТ0422Т0422042204220422Т	I
    //   167: imul
    //   168: getstatic 94	kkkkkk/faafaf:bТТ04220422Т0422042204220422Т	I
    //   171: irem
    //   172: invokestatic 641	kkkkkk/faafaf:bкк043A043Aккк043Aк043A	()I
    //   175: if_icmpeq +13 -> 188
    //   178: bipush 30
    //   180: putstatic 90	kkkkkk/faafaf:b0422ТТ0422Т0422042204220422Т	I
    //   183: bipush 31
    //   185: putstatic 96	kkkkkk/faafaf:bТ0422Т0422Т0422042204220422Т	I
    //   188: aload 5
    //   190: iload_1
    //   191: aload 6
    //   193: aload_3
    //   194: invokestatic 1279	kkkkkk/dvdvvd:bкк043A043Aк043A043A043Aкк	(Ljava/lang/String;ZLjava/lang/String;Ljava/util/HashMap;)V
    //   197: aload 4
    //   199: invokevirtual 1292	android/telephony/TelephonyManager:getSubscriberId	()Ljava/lang/String;
    //   202: astore 5
    //   204: getstatic 90	kkkkkk/faafaf:b0422ТТ0422Т0422042204220422Т	I
    //   207: getstatic 92	kkkkkk/faafaf:b04220422Т0422Т0422042204220422Т	I
    //   210: iadd
    //   211: getstatic 90	kkkkkk/faafaf:b0422ТТ0422Т0422042204220422Т	I
    //   214: imul
    //   215: getstatic 94	kkkkkk/faafaf:bТТ04220422Т0422042204220422Т	I
    //   218: irem
    //   219: getstatic 96	kkkkkk/faafaf:bТ0422Т0422Т0422042204220422Т	I
    //   222: if_icmpeq +13 -> 235
    //   225: bipush 58
    //   227: putstatic 90	kkkkkk/faafaf:b0422ТТ0422Т0422042204220422Т	I
    //   230: bipush 16
    //   232: putstatic 96	kkkkkk/faafaf:bТ0422Т0422Т0422042204220422Т	I
    //   235: aload 5
    //   237: iload_1
    //   238: ldc_w 1294
    //   241: bipush 46
    //   243: bipush 102
    //   245: iconst_2
    //   246: invokestatic 66	kkkkkk/gguuuu:bк043Aккк043Aкк043A043A	(Ljava/lang/String;CCC)Ljava/lang/String;
    //   249: aload_3
    //   250: invokestatic 1279	kkkkkk/dvdvvd:bкк043A043Aк043A043A043Aкк	(Ljava/lang/String;ZLjava/lang/String;Ljava/util/HashMap;)V
    //   253: aload 4
    //   255: invokevirtual 1297	android/telephony/TelephonyManager:getVoiceMailNumber	()Ljava/lang/String;
    //   258: iload_1
    //   259: ldc_w 1299
    //   262: bipush 36
    //   264: iconst_5
    //   265: invokestatic 86	kkkkkk/gguuuu:bккккк043Aкк043A043A	(Ljava/lang/String;CC)Ljava/lang/String;
    //   268: aload_3
    //   269: invokestatic 1279	kkkkkk/dvdvvd:bкк043A043Aк043A043A043Aкк	(Ljava/lang/String;ZLjava/lang/String;Ljava/util/HashMap;)V
    //   272: aload 4
    //   274: invokevirtual 1302	android/telephony/TelephonyManager:getDeviceSoftwareVersion	()Ljava/lang/String;
    //   277: iconst_0
    //   278: ldc_w 1304
    //   281: sipush 200
    //   284: iconst_3
    //   285: invokestatic 86	kkkkkk/gguuuu:bккккк043Aкк043A043A	(Ljava/lang/String;CC)Ljava/lang/String;
    //   288: aload_3
    //   289: invokestatic 1279	kkkkkk/dvdvvd:bкк043A043Aк043A043A043Aкк	(Ljava/lang/String;ZLjava/lang/String;Ljava/util/HashMap;)V
    //   292: aload 4
    //   294: invokevirtual 1307	android/telephony/TelephonyManager:getVoiceMailAlphaTag	()Ljava/lang/String;
    //   297: astore 4
    //   299: aload 4
    //   301: invokestatic 1025	kkkkkk/dvdvvd:b043Aкк043Aк043A043A043Aкк	(Ljava/lang/String;)Z
    //   304: ifeq +43 -> 347
    //   307: aload 4
    //   309: ldc_w 1309
    //   312: sipush 213
    //   315: sipush 241
    //   318: iconst_3
    //   319: invokestatic 66	kkkkkk/gguuuu:bк043Aккк043Aкк043A043A	(Ljava/lang/String;CCC)Ljava/lang/String;
    //   322: invokevirtual 336	java/lang/String:equalsIgnoreCase	(Ljava/lang/String;)Z
    //   325: ifne +22 -> 347
    //   328: aload_3
    //   329: ldc_w 1311
    //   332: sipush 206
    //   335: iconst_0
    //   336: invokestatic 86	kkkkkk/gguuuu:bккккк043Aкк043A043A	(Ljava/lang/String;CC)Ljava/lang/String;
    //   339: aload 4
    //   341: invokeinterface 227 3 0
    //   346: pop
    //   347: getstatic 155	kkkkkk/tttjtt$tjtttt$jttttt:bююю044Eюююю044E044E	I
    //   350: bipush 22
    //   352: if_icmplt +17 -> 369
    //   355: aload_3
    //   356: aload_0
    //   357: getfield 133	kkkkkk/faafaf$aaffaf:b0422042204220422Т0422042204220422Т	Landroid/content/Context;
    //   360: iload_1
    //   361: invokestatic 1317	kkkkkk/afffaa:b043A043A043A043A043A043A043A043A043Aк	(Landroid/content/Context;Z)Ljava/util/HashMap;
    //   364: invokeinterface 263 2 0
    //   369: aload_3
    //   370: areturn
    //   371: astore_0
    //   372: getstatic 38	kkkkkk/faafaf:bТ04220422ТТ0422042204220422Т	Ljava/lang/String;
    //   375: aload_0
    //   376: invokevirtual 366	java/lang/Exception:toString	()Ljava/lang/String;
    //   379: invokestatic 370	kkkkkk/fafffa:b043Aккк043Aк043Aкк043A	(Ljava/lang/String;Ljava/lang/String;)V
    //   382: aload_3
    //   383: areturn
    //   384: astore_0
    //   385: aload_0
    //   386: athrow
    //   387: astore_0
    //   388: aload_0
    //   389: athrow
    //   390: astore_0
    //   391: aload_3
    //   392: areturn
    // Local variable table:
    //   start	length	slot	name	signature
    //   0	393	0	paramAaffaf	aaffaf
    //   0	393	1	paramBoolean	boolean
    //   49	2	2	bool	boolean
    //   7	385	3	localHashMap	HashMap
    //   76	264	4	localObject	Object
    //   141	95	5	str1	String
    //   155	37	6	str2	String
    // Exception table:
    //   from	to	target	type
    //   54	78	371	java/lang/Exception
    //   83	157	371	java/lang/Exception
    //   188	204	371	java/lang/Exception
    //   235	347	371	java/lang/Exception
    //   347	369	371	java/lang/Exception
    //   372	382	384	java/lang/Exception
    //   0	50	387	java/lang/Exception
    //   54	78	390	java/lang/SecurityException
    //   83	157	390	java/lang/SecurityException
    //   188	204	390	java/lang/SecurityException
    //   235	347	390	java/lang/SecurityException
    //   347	369	390	java/lang/SecurityException
  }
  
  public static final class aaffaf
  {
    @Nonnull
    public final Context b0422042204220422Т0422042204220422Т;
    
    public aaffaf(@Nonnull Context paramContext)
    {
      this.b0422042204220422Т0422042204220422Т = paramContext;
    }
  }
}
