package kkkkkk;

import android.util.Log;
import java.security.InvalidParameterException;
import java.util.regex.Matcher;
import java.util.regex.Pattern;
import javax.annotation.Nullable;

public final class fafffa
{
  public static int b04220422042204220422ТТ04220422Т = 81;
  private static final boolean b0422Т042204220422ТТ04220422Т;
  public static int b0422ТТТТ0422Т04220422Т = 1;
  private static final Pattern bТ0422042204220422ТТ04220422Т;
  public static int bТ0422ТТТ0422Т04220422Т = 2;
  public static int bТТТТТ0422Т04220422Т;
  
  static
  {
    for (boolean bool = true;; bool = false)
    {
      try
      {
        if (vvdvvd.b044Eюююю044E044E044E044E044E.intValue() == -1)
        {
          b0422Т042204220422ТТ04220422Т = bool;
          localPattern = Pattern.compile(gguuuu.bк043Aккк043Aкк043A043A("*J,N", '', 'Q', '\001'));
        }
      }
      catch (Exception localException1)
      {
        Pattern localPattern;
        throw localException1;
      }
      try
      {
        bТ0422042204220422ТТ04220422Т = localPattern;
        return;
      }
      catch (Exception localException2)
      {
        throw localException2;
      }
    }
  }
  
  public fafffa() {}
  
  /* Error */
  @javax.annotation.Nonnull
  public static String b043A043A043A043Aкк043Aкк043A(@javax.annotation.Nonnull Class paramClass)
  {
    // Byte code:
    //   0: new 59	java/lang/StringBuilder
    //   3: dup
    //   4: ldc 61
    //   6: bipush 120
    //   8: iconst_5
    //   9: invokestatic 65	kkkkkk/gguuuu:bккккк043Aкк043A043A	(Ljava/lang/String;CC)Ljava/lang/String;
    //   12: invokespecial 68	java/lang/StringBuilder:<init>	(Ljava/lang/String;)V
    //   15: astore_2
    //   16: getstatic 70	kkkkkk/fafffa:b04220422042204220422ТТ04220422Т	I
    //   19: getstatic 72	kkkkkk/fafffa:b0422ТТТТ0422Т04220422Т	I
    //   22: iadd
    //   23: getstatic 70	kkkkkk/fafffa:b04220422042204220422ТТ04220422Т	I
    //   26: imul
    //   27: getstatic 74	kkkkkk/fafffa:bТ0422ТТТ0422Т04220422Т	I
    //   30: irem
    //   31: getstatic 76	kkkkkk/fafffa:bТТТТТ0422Т04220422Т	I
    //   34: if_icmpeq +45 -> 79
    //   37: bipush 19
    //   39: putstatic 70	kkkkkk/fafffa:b04220422042204220422ТТ04220422Т	I
    //   42: invokestatic 79	kkkkkk/fafffa:b043Aкк043Aкк043Aкк043A	()I
    //   45: putstatic 76	kkkkkk/fafffa:bТТТТТ0422Т04220422Т	I
    //   48: getstatic 70	kkkkkk/fafffa:b04220422042204220422ТТ04220422Т	I
    //   51: getstatic 72	kkkkkk/fafffa:b0422ТТТТ0422Т04220422Т	I
    //   54: iadd
    //   55: getstatic 70	kkkkkk/fafffa:b04220422042204220422ТТ04220422Т	I
    //   58: imul
    //   59: getstatic 74	kkkkkk/fafffa:bТ0422ТТТ0422Т04220422Т	I
    //   62: irem
    //   63: invokestatic 82	kkkkkk/fafffa:bккк043Aкк043Aкк043A	()I
    //   66: if_icmpeq +13 -> 79
    //   69: bipush 12
    //   71: putstatic 70	kkkkkk/fafffa:b04220422042204220422ТТ04220422Т	I
    //   74: bipush 35
    //   76: putstatic 76	kkkkkk/fafffa:bТТТТТ0422Т04220422Т	I
    //   79: aload_2
    //   80: aload_0
    //   81: invokevirtual 88	java/lang/Class:getSimpleName	()Ljava/lang/String;
    //   84: invokevirtual 92	java/lang/StringBuilder:append	(Ljava/lang/String;)Ljava/lang/StringBuilder;
    //   87: invokevirtual 95	java/lang/StringBuilder:toString	()Ljava/lang/String;
    //   90: astore_2
    //   91: aload_2
    //   92: invokevirtual 100	java/lang/String:length	()I
    //   95: istore_1
    //   96: aload_2
    //   97: astore_0
    //   98: iload_1
    //   99: bipush 23
    //   101: if_icmple +11 -> 112
    //   104: aload_2
    //   105: iconst_0
    //   106: bipush 23
    //   108: invokevirtual 104	java/lang/String:substring	(II)Ljava/lang/String;
    //   111: astore_0
    //   112: aload_0
    //   113: areturn
    //   114: astore_0
    //   115: aload_0
    //   116: athrow
    //   117: astore_0
    //   118: aload_0
    //   119: athrow
    // Local variable table:
    //   start	length	slot	name	signature
    //   0	120	0	paramClass	Class
    //   95	7	1	i	int
    //   15	90	2	localObject	Object
    // Exception table:
    //   from	to	target	type
    //   0	16	114	java/lang/Exception
    //   104	112	114	java/lang/Exception
    //   79	96	117	java/lang/Exception
  }
  
  /* Error */
  public static void b043A043A043Aк043Aк043Aкк043A(String paramString1, String paramString2, String... paramVarArgs)
  {
    // Byte code:
    //   0: getstatic 34	kkkkkk/fafffa:b0422Т042204220422ТТ04220422Т	Z
    //   3: ifne +11 -> 14
    //   6: aload_0
    //   7: iconst_5
    //   8: invokestatic 114	android/util/Log:isLoggable	(Ljava/lang/String;I)Z
    //   11: ifeq +96 -> 107
    //   14: aload_0
    //   15: aload_1
    //   16: aload_2
    //   17: checkcast 116	[Ljava/lang/Object;
    //   20: invokestatic 120	kkkkkk/fafffa:bкккк043Aк043Aкк043A	(Ljava/lang/String;[Ljava/lang/Object;)Ljava/lang/String;
    //   23: invokestatic 124	android/util/Log:w	(Ljava/lang/String;Ljava/lang/String;)I
    //   26: pop
    //   27: invokestatic 79	kkkkkk/fafffa:b043Aкк043Aкк043Aкк043A	()I
    //   30: istore_3
    //   31: getstatic 72	kkkkkk/fafffa:b0422ТТТТ0422Т04220422Т	I
    //   34: istore 4
    //   36: invokestatic 79	kkkkkk/fafffa:b043Aкк043Aкк043Aкк043A	()I
    //   39: getstatic 72	kkkkkk/fafffa:b0422ТТТТ0422Т04220422Т	I
    //   42: iadd
    //   43: invokestatic 79	kkkkkk/fafffa:b043Aкк043Aкк043Aкк043A	()I
    //   46: imul
    //   47: invokestatic 127	kkkkkk/fafffa:bк043Aк043Aкк043Aкк043A	()I
    //   50: irem
    //   51: getstatic 76	kkkkkk/fafffa:bТТТТТ0422Т04220422Т	I
    //   54: if_icmpeq +15 -> 69
    //   57: invokestatic 79	kkkkkk/fafffa:b043Aкк043Aкк043Aкк043A	()I
    //   60: putstatic 70	kkkkkk/fafffa:b04220422042204220422ТТ04220422Т	I
    //   63: invokestatic 79	kkkkkk/fafffa:b043Aкк043Aкк043Aкк043A	()I
    //   66: putstatic 76	kkkkkk/fafffa:bТТТТТ0422Т04220422Т	I
    //   69: iload_3
    //   70: iload 4
    //   72: iload_3
    //   73: iadd
    //   74: imul
    //   75: getstatic 74	kkkkkk/fafffa:bТ0422ТТТ0422Т04220422Т	I
    //   78: irem
    //   79: tableswitch	default:+35->114, 0:+28->107
    //   96: invokestatic 79	kkkkkk/fafffa:b043Aкк043Aкк043Aкк043A	()I
    //   99: putstatic 70	kkkkkk/fafffa:b04220422042204220422ТТ04220422Т	I
    //   102: bipush 87
    //   104: putstatic 76	kkkkkk/fafffa:bТТТТТ0422Т04220422Т	I
    //   107: return
    //   108: astore_0
    //   109: aload_0
    //   110: athrow
    //   111: astore_0
    //   112: aload_0
    //   113: athrow
    //   114: goto -18 -> 96
    // Local variable table:
    //   start	length	slot	name	signature
    //   0	117	0	paramString1	String
    //   0	117	1	paramString2	String
    //   0	117	2	paramVarArgs	String[]
    //   30	45	3	i	int
    //   34	40	4	j	int
    // Exception table:
    //   from	to	target	type
    //   0	14	108	java/lang/Exception
    //   14	36	108	java/lang/Exception
    //   69	96	111	java/lang/Exception
    //   96	107	111	java/lang/Exception
  }
  
  public static int b043A043A043Aккк043Aкк043A()
  {
    return 1;
  }
  
  /* Error */
  public static void b043A043Aк043Aкк043Aкк043A(String paramString1, String paramString2, Exception paramException)
  {
    // Byte code:
    //   0: iconst_1
    //   1: istore_3
    //   2: getstatic 34	kkkkkk/fafffa:b0422Т042204220422ТТ04220422Т	Z
    //   5: istore 4
    //   7: iload 4
    //   9: ifne +62 -> 71
    //   12: iload_3
    //   13: iconst_0
    //   14: idiv
    //   15: istore_3
    //   16: goto -4 -> 12
    //   19: astore 5
    //   21: invokestatic 79	kkkkkk/fafffa:b043Aкк043Aкк043Aкк043A	()I
    //   24: putstatic 70	kkkkkk/fafffa:b04220422042204220422ТТ04220422Т	I
    //   27: aload_0
    //   28: iconst_4
    //   29: invokestatic 114	android/util/Log:isLoggable	(Ljava/lang/String;I)Z
    //   32: istore 4
    //   34: getstatic 70	kkkkkk/fafffa:b04220422042204220422ТТ04220422Т	I
    //   37: getstatic 72	kkkkkk/fafffa:b0422ТТТТ0422Т04220422Т	I
    //   40: iadd
    //   41: getstatic 70	kkkkkk/fafffa:b04220422042204220422ТТ04220422Т	I
    //   44: imul
    //   45: getstatic 74	kkkkkk/fafffa:bТ0422ТТТ0422Т04220422Т	I
    //   48: irem
    //   49: getstatic 76	kkkkkk/fafffa:bТТТТТ0422Т04220422Т	I
    //   52: if_icmpeq +14 -> 66
    //   55: invokestatic 79	kkkkkk/fafffa:b043Aкк043Aкк043Aкк043A	()I
    //   58: putstatic 70	kkkkkk/fafffa:b04220422042204220422ТТ04220422Т	I
    //   61: bipush 59
    //   63: putstatic 76	kkkkkk/fafffa:bТТТТТ0422Т04220422Т	I
    //   66: iload 4
    //   68: ifeq +10 -> 78
    //   71: aload_0
    //   72: aload_1
    //   73: aload_2
    //   74: invokestatic 134	android/util/Log:i	(Ljava/lang/String;Ljava/lang/String;Ljava/lang/Throwable;)I
    //   77: pop
    //   78: return
    //   79: astore_0
    //   80: aload_0
    //   81: athrow
    //   82: astore_0
    //   83: aload_0
    //   84: athrow
    //   85: astore_0
    //   86: aload_0
    //   87: athrow
    // Local variable table:
    //   start	length	slot	name	signature
    //   0	88	0	paramString1	String
    //   0	88	1	paramString2	String
    //   0	88	2	paramException	Exception
    //   1	15	3	i	int
    //   5	62	4	bool	boolean
    //   19	1	5	localException	Exception
    // Exception table:
    //   from	to	target	type
    //   12	16	19	java/lang/Exception
    //   2	7	79	java/lang/Exception
    //   27	34	79	java/lang/Exception
    //   21	27	82	java/lang/Exception
    //   80	82	82	java/lang/Exception
    //   86	88	82	java/lang/Exception
    //   71	78	85	java/lang/Exception
  }
  
  /* Error */
  public static void b043A043Aкк043Aк043Aкк043A(String paramString1, String paramString2)
  {
    // Byte code:
    //   0: getstatic 34	kkkkkk/fafffa:b0422Т042204220422ТТ04220422Т	Z
    //   3: ifne +45 -> 48
    //   6: aload_0
    //   7: iconst_5
    //   8: invokestatic 114	android/util/Log:isLoggable	(Ljava/lang/String;I)Z
    //   11: istore_2
    //   12: getstatic 70	kkkkkk/fafffa:b04220422042204220422ТТ04220422Т	I
    //   15: getstatic 72	kkkkkk/fafffa:b0422ТТТТ0422Т04220422Т	I
    //   18: iadd
    //   19: getstatic 70	kkkkkk/fafffa:b04220422042204220422ТТ04220422Т	I
    //   22: imul
    //   23: getstatic 74	kkkkkk/fafffa:bТ0422ТТТ0422Т04220422Т	I
    //   26: irem
    //   27: getstatic 76	kkkkkk/fafffa:bТТТТТ0422Т04220422Т	I
    //   30: if_icmpeq +14 -> 44
    //   33: bipush 83
    //   35: putstatic 70	kkkkkk/fafffa:b04220422042204220422ТТ04220422Т	I
    //   38: invokestatic 79	kkkkkk/fafffa:b043Aкк043Aкк043Aкк043A	()I
    //   41: putstatic 76	kkkkkk/fafffa:bТТТТТ0422Т04220422Т	I
    //   44: iload_2
    //   45: ifeq +9 -> 54
    //   48: aload_0
    //   49: aload_1
    //   50: invokestatic 124	android/util/Log:w	(Ljava/lang/String;Ljava/lang/String;)I
    //   53: pop
    //   54: return
    //   55: astore_0
    //   56: aload_0
    //   57: athrow
    //   58: astore_0
    //   59: aload_0
    //   60: athrow
    // Local variable table:
    //   start	length	slot	name	signature
    //   0	61	0	paramString1	String
    //   0	61	1	paramString2	String
    //   11	34	2	bool	boolean
    // Exception table:
    //   from	to	target	type
    //   0	12	55	java/lang/Exception
    //   48	54	58	java/lang/Exception
  }
  
  /* Error */
  public static void b043Aк043A043Aкк043Aкк043A(String paramString1, String paramString2, String... paramVarArgs)
  {
    // Byte code:
    //   0: getstatic 34	kkkkkk/fafffa:b0422Т042204220422ТТ04220422Т	Z
    //   3: ifne +47 -> 50
    //   6: aload_0
    //   7: iconst_4
    //   8: invokestatic 114	android/util/Log:isLoggable	(Ljava/lang/String;I)Z
    //   11: istore 6
    //   13: iload 6
    //   15: ifeq +101 -> 116
    //   18: getstatic 70	kkkkkk/fafffa:b04220422042204220422ТТ04220422Т	I
    //   21: getstatic 72	kkkkkk/fafffa:b0422ТТТТ0422Т04220422Т	I
    //   24: iadd
    //   25: getstatic 70	kkkkkk/fafffa:b04220422042204220422ТТ04220422Т	I
    //   28: imul
    //   29: getstatic 74	kkkkkk/fafffa:bТ0422ТТТ0422Т04220422Т	I
    //   32: irem
    //   33: getstatic 76	kkkkkk/fafffa:bТТТТТ0422Т04220422Т	I
    //   36: if_icmpeq +14 -> 50
    //   39: bipush 24
    //   41: putstatic 70	kkkkkk/fafffa:b04220422042204220422ТТ04220422Т	I
    //   44: invokestatic 79	kkkkkk/fafffa:b043Aкк043Aкк043Aкк043A	()I
    //   47: putstatic 76	kkkkkk/fafffa:bТТТТТ0422Т04220422Т	I
    //   50: aload_2
    //   51: checkcast 116	[Ljava/lang/Object;
    //   54: astore_2
    //   55: getstatic 70	kkkkkk/fafffa:b04220422042204220422ТТ04220422Т	I
    //   58: istore_3
    //   59: invokestatic 139	kkkkkk/fafffa:b043A043A043Aккк043Aкк043A	()I
    //   62: istore 4
    //   64: getstatic 74	kkkkkk/fafffa:bТ0422ТТТ0422Т04220422Т	I
    //   67: istore 5
    //   69: iload_3
    //   70: iload 4
    //   72: iload_3
    //   73: iadd
    //   74: imul
    //   75: iload 5
    //   77: irem
    //   78: tableswitch	default:+18->96, 0:+28->106
    //   96: bipush 57
    //   98: putstatic 70	kkkkkk/fafffa:b04220422042204220422ТТ04220422Т	I
    //   101: bipush 52
    //   103: putstatic 76	kkkkkk/fafffa:bТТТТТ0422Т04220422Т	I
    //   106: aload_0
    //   107: aload_1
    //   108: aload_2
    //   109: invokestatic 120	kkkkkk/fafffa:bкккк043Aк043Aкк043A	(Ljava/lang/String;[Ljava/lang/Object;)Ljava/lang/String;
    //   112: invokestatic 141	android/util/Log:i	(Ljava/lang/String;Ljava/lang/String;)I
    //   115: pop
    //   116: return
    //   117: astore_0
    //   118: aload_0
    //   119: athrow
    //   120: astore_0
    //   121: aload_0
    //   122: athrow
    // Local variable table:
    //   start	length	slot	name	signature
    //   0	123	0	paramString1	String
    //   0	123	1	paramString2	String
    //   0	123	2	paramVarArgs	String[]
    //   58	17	3	i	int
    //   62	12	4	j	int
    //   67	11	5	k	int
    //   11	3	6	bool	boolean
    // Exception table:
    //   from	to	target	type
    //   0	13	117	java/lang/Exception
    //   50	69	117	java/lang/Exception
    //   96	106	120	java/lang/Exception
    //   106	116	120	java/lang/Exception
  }
  
  public static void b043Aк043Aк043Aк043Aкк043A(String paramString1, String paramString2)
  {
    if (!b0422Т042204220422ТТ04220422Т)
    {
      if ((b04220422042204220422ТТ04220422Т + b0422ТТТТ0422Т04220422Т) * b04220422042204220422ТТ04220422Т % bТ0422ТТТ0422Т04220422Т != bТТТТТ0422Т04220422Т)
      {
        b04220422042204220422ТТ04220422Т = b043Aкк043Aкк043Aкк043A();
        bТТТТТ0422Т04220422Т = 77;
      }
      boolean bool = Log.isLoggable(paramString1, 6);
      switch (0)
      {
      case 1: 
      default: 
        for (;;)
        {
          switch (1)
          {
          }
        }
      }
      switch (0)
      {
      case 1: 
      default: 
        for (;;)
        {
          switch (0)
          {
          }
        }
      }
      if (!bool) {}
    }
    else
    {
      int i = b04220422042204220422ТТ04220422Т;
      switch (i * (b0422ТТТТ0422Т04220422Т + i) % bТ0422ТТТ0422Т04220422Т)
      {
      default: 
        b04220422042204220422ТТ04220422Т = 24;
        bТТТТТ0422Т04220422Т = b043Aкк043Aкк043Aкк043A();
      }
      Log.e(paramString1, paramString2);
    }
  }
  
  public static int b043Aкк043Aкк043Aкк043A()
  {
    return 84;
  }
  
  public static void b043Aккк043Aк043Aкк043A(String paramString1, String paramString2)
  {
    for (;;)
    {
      boolean bool;
      try
      {
        if (!b0422Т042204220422ТТ04220422Т)
        {
          int i = b04220422042204220422ТТ04220422Т;
          int j = b0422ТТТТ0422Т04220422Т;
          int k = bк043Aк043Aкк043Aкк043A();
          switch (i * (j + i) % k)
          {
          }
        }
      }
      catch (Exception paramString1)
      {
        throw paramString1;
      }
      try
      {
        b04220422042204220422ТТ04220422Т = 15;
        bТТТТТ0422Т04220422Т = 52;
        bool = Log.isLoggable(paramString1, 4);
      }
      catch (Exception paramString1)
      {
        throw paramString1;
      }
      Log.i(paramString1, paramString2);
      if ((b04220422042204220422ТТ04220422Т + b0422ТТТТ0422Т04220422Т) * b04220422042204220422ТТ04220422Т % bТ0422ТТТ0422Т04220422Т != bТТТТТ0422Т04220422Т)
      {
        b04220422042204220422ТТ04220422Т = b043Aкк043Aкк043Aкк043A();
        bТТТТТ0422Т04220422Т = b043Aкк043Aкк043Aкк043A();
      }
      return;
      switch (0)
      {
      case 1: 
      default: 
        for (;;)
        {
          switch (0)
          {
          }
        }
      }
      if (!bool) {}
    }
  }
  
  /* Error */
  public static int bк043A043A043Aкк043Aкк043A()
  {
    // Byte code:
    //   0: ldc -105
    //   2: sipush 131
    //   5: bipush 115
    //   7: iconst_3
    //   8: invokestatic 42	kkkkkk/gguuuu:bк043Aккк043Aкк043A043A	(Ljava/lang/String;CCC)Ljava/lang/String;
    //   11: iconst_2
    //   12: invokestatic 114	android/util/Log:isLoggable	(Ljava/lang/String;I)Z
    //   15: ifeq +189 -> 204
    //   18: invokestatic 157	kkkkkk/dvdddv:bк043A043A043Aк043Aкк043Aк	()Lkkkkkk/dvdddv;
    //   21: astore_1
    //   22: aload_1
    //   23: getfield 160	kkkkkk/dvdddv:b0422ТТТ0422ТТТТТ	Z
    //   26: ifeq +14 -> 40
    //   29: goto +199 -> 228
    //   32: aload_1
    //   33: getfield 164	kkkkkk/dvdddv:b0422Т0422Т0422ТТТТТ	Lcom/threatmetrix/TrustDefender/NativeGathererHelper;
    //   36: iconst_1
    //   37: invokevirtual 170	com/threatmetrix/TrustDefender/NativeGathererHelper:setInfoLogging	(I)V
    //   40: iconst_1
    //   41: ireturn
    //   42: astore_1
    //   43: getstatic 174	kkkkkk/dvdddv:bТ042204220422ТТТТТТ	Ljava/lang/String;
    //   46: astore_2
    //   47: getstatic 34	kkkkkk/fafffa:b0422Т042204220422ТТ04220422Т	Z
    //   50: ifne +12 -> 62
    //   53: aload_2
    //   54: bipush 6
    //   56: invokestatic 114	android/util/Log:isLoggable	(Ljava/lang/String;I)Z
    //   59: ifeq +18 -> 77
    //   62: aload_2
    //   63: ldc -80
    //   65: sipush 205
    //   68: iconst_5
    //   69: invokestatic 65	kkkkkk/gguuuu:bккккк043Aкк043A043A	(Ljava/lang/String;CC)Ljava/lang/String;
    //   72: aload_1
    //   73: invokestatic 178	android/util/Log:e	(Ljava/lang/String;Ljava/lang/String;Ljava/lang/Throwable;)I
    //   76: pop
    //   77: getstatic 70	kkkkkk/fafffa:b04220422042204220422ТТ04220422Т	I
    //   80: istore_0
    //   81: iload_0
    //   82: getstatic 72	kkkkkk/fafffa:b0422ТТТТ0422Т04220422Т	I
    //   85: iload_0
    //   86: iadd
    //   87: imul
    //   88: getstatic 74	kkkkkk/fafffa:bТ0422ТТТ0422Т04220422Т	I
    //   91: irem
    //   92: tableswitch	default:+20->112, 0:+134->226
    //   112: invokestatic 79	kkkkkk/fafffa:b043Aкк043Aкк043Aкк043A	()I
    //   115: putstatic 70	kkkkkk/fafffa:b04220422042204220422ТТ04220422Т	I
    //   118: bipush 53
    //   120: putstatic 76	kkkkkk/fafffa:bТТТТТ0422Т04220422Т	I
    //   123: iconst_0
    //   124: ireturn
    //   125: astore_1
    //   126: getstatic 174	kkkkkk/dvdddv:bТ042204220422ТТТТТТ	Ljava/lang/String;
    //   129: astore_2
    //   130: getstatic 34	kkkkkk/fafffa:b0422Т042204220422ТТ04220422Т	Z
    //   133: ifne +54 -> 187
    //   136: getstatic 70	kkkkkk/fafffa:b04220422042204220422ТТ04220422Т	I
    //   139: istore_0
    //   140: iload_0
    //   141: getstatic 72	kkkkkk/fafffa:b0422ТТТТ0422Т04220422Т	I
    //   144: iload_0
    //   145: iadd
    //   146: imul
    //   147: getstatic 74	kkkkkk/fafffa:bТ0422ТТТ0422Т04220422Т	I
    //   150: irem
    //   151: tableswitch	default:+17->168, 0:+27->178
    //   168: invokestatic 79	kkkkkk/fafffa:b043Aкк043Aкк043Aкк043A	()I
    //   171: putstatic 70	kkkkkk/fafffa:b04220422042204220422ТТ04220422Т	I
    //   174: iconst_2
    //   175: putstatic 76	kkkkkk/fafffa:bТТТТТ0422Т04220422Т	I
    //   178: aload_2
    //   179: bipush 6
    //   181: invokestatic 114	android/util/Log:isLoggable	(Ljava/lang/String;I)Z
    //   184: ifeq -144 -> 40
    //   187: aload_2
    //   188: ldc -76
    //   190: sipush 140
    //   193: iconst_5
    //   194: invokestatic 65	kkkkkk/gguuuu:bккккк043Aкк043A043A	(Ljava/lang/String;CC)Ljava/lang/String;
    //   197: aload_1
    //   198: invokestatic 178	android/util/Log:e	(Ljava/lang/String;Ljava/lang/String;Ljava/lang/Throwable;)I
    //   201: pop
    //   202: iconst_1
    //   203: ireturn
    //   204: invokestatic 157	kkkkkk/dvdddv:bк043A043A043Aк043Aкк043Aк	()Lkkkkkk/dvdddv;
    //   207: astore_1
    //   208: aload_1
    //   209: getfield 160	kkkkkk/dvdddv:b0422ТТТ0422ТТТТТ	Z
    //   212: ifeq -135 -> 77
    //   215: aload_1
    //   216: getfield 164	kkkkkk/dvdddv:b0422Т0422Т0422ТТТТТ	Lcom/threatmetrix/TrustDefender/NativeGathererHelper;
    //   219: iconst_0
    //   220: invokevirtual 170	com/threatmetrix/TrustDefender/NativeGathererHelper:setInfoLogging	(I)V
    //   223: goto -146 -> 77
    //   226: iconst_0
    //   227: ireturn
    //   228: iconst_1
    //   229: tableswitch	default:+23->252, 0:+-1->228, 1:+-197->32
    //   252: iconst_0
    //   253: tableswitch	default:+23->276, 0:+-221->32, 1:+-25->228
    //   276: goto -24 -> 252
    // Local variable table:
    //   start	length	slot	name	signature
    //   80	67	0	i	int
    //   21	12	1	localDvdddv1	dvdddv
    //   42	31	1	localThrowable1	Throwable
    //   125	73	1	localThrowable2	Throwable
    //   207	9	1	localDvdddv2	dvdddv
    //   46	142	2	str	String
    // Exception table:
    //   from	to	target	type
    //   208	223	42	java/lang/Throwable
    //   22	29	125	java/lang/Throwable
    //   32	40	125	java/lang/Throwable
  }
  
  public static void bк043A043Aк043Aк043Aкк043A(String paramString1, String paramString2, Exception paramException)
  {
    try
    {
      boolean bool = b0422Т042204220422ТТ04220422Т;
      int i;
      for (;;) {}
    }
    catch (Exception paramString1)
    {
      try
      {
        i = b043Aкк043Aкк043Aкк043A();
        switch (i * (b0422ТТТТ0422Т04220422Т + i) % bТ0422ТТТ0422Т04220422Т)
        {
        case 0: 
          b04220422042204220422ТТ04220422Т = b043Aкк043Aкк043Aкк043A();
          bТТТТТ0422Т04220422Т = 79;
          if ((bool) || (Log.isLoggable(paramString1, 5)))
          {
            Log.w(paramString1, paramString2, paramException);
            if ((b04220422042204220422ТТ04220422Т + b0422ТТТТ0422Т04220422Т) * b04220422042204220422ТТ04220422Т % bк043Aк043Aкк043Aкк043A() != bТТТТТ0422Т04220422Т)
            {
              b04220422042204220422ТТ04220422Т = 3;
              bТТТТТ0422Т04220422Т = 87;
            }
          }
          return;
        }
      }
      catch (Exception paramString1)
      {
        throw paramString1;
      }
      paramString1 = paramString1;
      throw paramString1;
    }
  }
  
  public static int bк043Aк043Aкк043Aкк043A()
  {
    return 2;
  }
  
  public static boolean bк043Aкк043Aк043Aкк043A()
  {
    switch (0)
    {
    case 1: 
    default: 
      for (;;)
      {
        switch (1)
        {
        }
      }
    }
    int i = b04220422042204220422ТТ04220422Т;
    int j = b0422ТТТТ0422Т04220422Т;
    int k = b04220422042204220422ТТ04220422Т;
    int m = bТ0422ТТТ0422Т04220422Т;
    switch (1)
    {
    case 0: 
    default: 
      for (;;)
      {
        switch (1)
        {
        }
      }
    }
    if ((i + j) * k % m != bТТТТТ0422Т04220422Т)
    {
      b04220422042204220422ТТ04220422Т = 84;
      bТТТТТ0422Т04220422Т = 22;
      i = b04220422042204220422ТТ04220422Т;
      switch (i * (b0422ТТТТ0422Т04220422Т + i) % bТ0422ТТТ0422Т04220422Т)
      {
      default: 
        b04220422042204220422ТТ04220422Т = 60;
        bТТТТТ0422Т04220422Т = b043Aкк043Aкк043Aкк043A();
      }
    }
    return b0422Т042204220422ТТ04220422Т;
  }
  
  /* Error */
  public static void bкк043A043Aкк043Aкк043A(String paramString1, String paramString2, Throwable paramThrowable)
  {
    // Byte code:
    //   0: getstatic 34	kkkkkk/fafffa:b0422Т042204220422ТТ04220422Т	Z
    //   3: ifne +60 -> 63
    //   6: aload_0
    //   7: bipush 6
    //   9: invokestatic 114	android/util/Log:isLoggable	(Ljava/lang/String;I)Z
    //   12: istore 4
    //   14: iload 4
    //   16: ifeq +85 -> 101
    //   19: invokestatic 79	kkkkkk/fafffa:b043Aкк043Aкк043Aкк043A	()I
    //   22: istore_3
    //   23: iload_3
    //   24: invokestatic 139	kkkkkk/fafffa:b043A043A043Aккк043Aкк043A	()I
    //   27: iload_3
    //   28: iadd
    //   29: imul
    //   30: invokestatic 127	kkkkkk/fafffa:bк043Aк043Aкк043Aкк043A	()I
    //   33: irem
    //   34: tableswitch	default:+18->52, 0:+29->63
    //   52: invokestatic 79	kkkkkk/fafffa:b043Aкк043Aкк043Aкк043A	()I
    //   55: putstatic 70	kkkkkk/fafffa:b04220422042204220422ТТ04220422Т	I
    //   58: bipush 52
    //   60: putstatic 76	kkkkkk/fafffa:bТТТТТ0422Т04220422Т	I
    //   63: aload_0
    //   64: aload_1
    //   65: aload_2
    //   66: invokestatic 178	android/util/Log:e	(Ljava/lang/String;Ljava/lang/String;Ljava/lang/Throwable;)I
    //   69: pop
    //   70: getstatic 70	kkkkkk/fafffa:b04220422042204220422ТТ04220422Т	I
    //   73: getstatic 72	kkkkkk/fafffa:b0422ТТТТ0422Т04220422Т	I
    //   76: iadd
    //   77: getstatic 70	kkkkkk/fafffa:b04220422042204220422ТТ04220422Т	I
    //   80: imul
    //   81: getstatic 74	kkkkkk/fafffa:bТ0422ТТТ0422Т04220422Т	I
    //   84: irem
    //   85: getstatic 76	kkkkkk/fafffa:bТТТТТ0422Т04220422Т	I
    //   88: if_icmpeq +13 -> 101
    //   91: bipush 55
    //   93: putstatic 70	kkkkkk/fafffa:b04220422042204220422ТТ04220422Т	I
    //   96: bipush 55
    //   98: putstatic 76	kkkkkk/fafffa:bТТТТТ0422Т04220422Т	I
    //   101: return
    //   102: astore_0
    //   103: aload_0
    //   104: athrow
    //   105: astore_0
    //   106: aload_0
    //   107: athrow
    // Local variable table:
    //   start	length	slot	name	signature
    //   0	108	0	paramString1	String
    //   0	108	1	paramString2	String
    //   0	108	2	paramThrowable	Throwable
    //   22	8	3	i	int
    //   12	3	4	bool	boolean
    // Exception table:
    //   from	to	target	type
    //   0	14	102	java/lang/Exception
    //   63	70	105	java/lang/Exception
  }
  
  public static void bкк043Aк043Aк043Aкк043A(String paramString1, String paramString2, String... paramVarArgs)
  {
    if (!b0422Т042204220422ТТ04220422Т)
    {
      switch (1)
      {
      case 0: 
      default: 
        for (;;)
        {
          switch (0)
          {
          }
        }
      }
      if ((b04220422042204220422ТТ04220422Т + b043A043A043Aккк043Aкк043A()) * b04220422042204220422ТТ04220422Т % bТ0422ТТТ0422Т04220422Т != bТТТТТ0422Т04220422Т)
      {
        b04220422042204220422ТТ04220422Т = 45;
        bТТТТТ0422Т04220422Т = b043Aкк043Aкк043Aкк043A();
        if ((b04220422042204220422ТТ04220422Т + b0422ТТТТ0422Т04220422Т) * b04220422042204220422ТТ04220422Т % bТ0422ТТТ0422Т04220422Т != bккк043Aкк043Aкк043A())
        {
          b04220422042204220422ТТ04220422Т = 97;
          bТТТТТ0422Т04220422Т = b043Aкк043Aкк043Aкк043A();
        }
      }
      if (!Log.isLoggable(paramString1, 6)) {}
    }
    else
    {
      Log.e(paramString1, bкккк043Aк043Aкк043A(paramString2, (Object[])paramVarArgs));
    }
  }
  
  public static int bккк043Aкк043Aкк043A()
  {
    return 0;
  }
  
  private static String bкккк043Aк043Aкк043A(@Nullable String paramString, @Nullable Object... paramVarArgs)
  {
    if ((paramString == null) || (paramVarArgs == null))
    {
      return "";
      try
      {
        throw new InvalidParameterException(gguuuu.bк043Aккк043Aкк043A043A("\024:0=AB65GsCKD:>LzKC}@RHWPISZZ\bOY]\faVXc\021XbfbWk\030lnmeke", '_', '', '\001'));
      }
      catch (Exception paramString)
      {
        try
        {
          throw paramString;
        }
        catch (Exception paramString)
        {
          throw paramString;
        }
      }
    }
    for (;;)
    {
      boolean bool = paramString.find();
      if (!bool) {
        break;
      }
      if (localObject != null) {}
      try
      {
        if ((b043Aкк043Aкк043Aкк043A() + b0422ТТТТ0422Т04220422Т) * b043Aкк043Aкк043Aкк043A() % bТ0422ТТТ0422Т04220422Т != bТТТТТ0422Т04220422Т)
        {
          b04220422042204220422ТТ04220422Т = b043Aкк043Aкк043Aкк043A();
          bТТТТТ0422Т04220422Т = b043Aкк043Aкк043Aкк043A();
        }
        try
        {
          localObject = String.valueOf(localObject);
          paramString.appendReplacement(localStringBuffer, (String)localObject);
        }
        catch (Exception paramString)
        {
          throw paramString;
        }
        paramString.appendReplacement(localStringBuffer, gguuuu.bккккк043Aкк043A043A("\033!\027\026", 'i', '\003'));
      }
      catch (Exception paramString)
      {
        StringBuffer localStringBuffer;
        throw paramString;
      }
      paramString = bТ0422042204220422ТТ04220422Т.matcher(paramString);
      localStringBuffer = new StringBuffer();
      int j = paramVarArgs.length;
      int i = 0;
      while (i >= j)
      {
        bool = paramString.find();
        if (bool)
        {
          paramString = new InvalidParameterException(gguuuu.bккккк043Aкк043A043A("Qwmz~sr\0051\001\t\002w{\n8\t\001;}\020\006\025\016\007\021\030\030E\r\027\033I\037\024\026!N\026 $ \025)U*,+#)#", '¬', '\001'));
          i = b043Aкк043Aкк043Aкк043A();
          switch (i * (b0422ТТТТ0422Т04220422Т + i) % bТ0422ТТТ0422Т04220422Т)
          {
          default: 
            b04220422042204220422ТТ04220422Т = 94;
            bТТТТТ0422Т04220422Т = b043Aкк043Aкк043Aкк043A();
          }
          throw paramString;
        }
        paramString = paramString.appendTail(localStringBuffer).toString();
        return paramString;
        i += 1;
      }
      Object localObject = paramVarArgs[i];
    }
  }
}
