package kkkkkk;

public abstract class fbbfff
{
  public static int b042E042EЮ042EЮ042EЮ042E042E = 0;
  public static int b042EЮЮ042EЮ042EЮ042E042E = 1;
  public static int bЮ042EЮ042EЮ042EЮ042E042E = 2;
  public static int bЮЮЮ042EЮ042EЮ042E042E = 99;
  public final String[] b042E042E042EЮЮ042EЮ042E042E = { gguuuu.bккккк043Aкк043A043A("Yb70?0XJJSKI", '', '\003'), gguuuu.bк043Aккк043Aкк043A043A("\r\026hdopb\013||\006}{", '@', '\034', '\002'), gguuuu.bккккк043Aкк043A043A("\034%v%##\037\021n\013\035\r\013u\006\035\020\007\017\024\022b\013||\006}{", 'Ã', '\002'), gguuuu.bк043Aккк043Aкк043A043A("W`/]OJ\\L9YEQFJNF-O@@L\036F88A97", ')', 'h', '\002'), gguuuu.bк043Aккк043Aкк043A043A("q|K}~n|vu~w\002\ti\020\b}[\020\017\006\f\004\023\024f\021\005\007\022\f\f", '#', '\033', '\001'), gguuuu.bккккк043Aкк043A043A("\f\025a\022\021~\013\003\007}\006\013i\016\004wZcPS{mmvnl", ']', '\005'), gguuuu.bккккк043Aкк043A043A("6A\020BC3A;:C<FM.TLB%(!&PDFQKK", 'n', '\001'), gguuuu.bккккк043Aкк043A043A("AJ\027GF4@85<3;@\037C9-\024578*#(%\004,\036\036'\037\035", '\024', '\003'), gguuuu.bккккк043Aкк043A043A("z\004P\001myqnultyX|rfMnpqc\\a^M=IH9aSS\\TR", 'í', '\005'), gguuuu.bккккк043Aкк043A043A("\033$p! \016\032\022\017\026\r\025\032x\035\023\007i\016\025\003\020\020\b~\007\f[\004uu~vt", 'N', '\005'), gguuuu.bккккк043Aкк043A043A("t}JzygskhofnsRvl`MZn\\ZAcT`6^PPYQO", 'Q', '\002'), gguuuu.bк043Aккк043Aкк043A043A("T_.`aQ_YXaZdkLrj`Oe_qeEgdpntnMwkmxrr", 'B', '§', '\003'), gguuuu.bк043Aккк043Aкк043A043A("z\006T\007\bw\006~\b\001\013\022r\031\021\007j\023\022\013o\026\034\037\035\r\033\021\024t\037\023\025 \032\032", 'Ç', '7', '\001'), gguuuu.bк043Aккк043Aкк043A043A("1<\013=>.<65>7AH)OG=!?GL1M!UZ'QEGRLL", '§', '', '\003'), gguuuu.bккккк043Aкк043A043A(" )u&%\023\037\027\024\033\022\032\037}\"\030\fy\027\t\004\025\026\022\030c\006\024}l|\t\003Xx\003\001\004x\003Rzllumk", 'ã', '\003'), gguuuu.bккккк043Aкк043A043A("IT#UVFTNMVOY`Ag_UEdXUhkiq,,?]vqMoukfiJthjuoo", 'î', '\004'), gguuuu.bк043Aккк043Aкк043A043A("{\005S\002sn\001pWrWuLnvvvMofgkAi[[d\\Z", 'V', '\027', '\002'), gguuuu.bккккк043Aкк043A043A("\003\016_}\020\nt\023\016g\022\031\030 l\027\013\r\030\022\022", ']', '\001'), gguuuu.bк043Aккк043Aкк043A043A("IT%:%/G]I\\M]U]b1bZVZY:dXZe__", 'ð', '', '\001'), gguuuu.bккккк043Aкк043A043A("?J\031,''A>BR%OCEPJJ", 'U', '\000'), gguuuu.bк043Aккк043Aкк043A043A("s~_\002o\004u~w\002\t\tXx\007\b\016h\003\004\024f\021\005\007\022\f\f", 'U', '4', '\003'), gguuuu.bккккк043Aкк043A043A("r{UgymygDh`ldaJ`:\\[hZgf7_QQZRP", '|', '\002'), gguuuu.bккккк043Aкк043A043A("\f\025t\005\013\nq\017_\byy\003zx", ']', '\005'), gguuuu.bккккк043Aкк043A043A("\024\037o\032\030\023\034\023\025 \032\006\034&\035#)#\0210 .4#&8.55;\0168,.933", '', '\001'), gguuuu.bк043Aккк043Aкк043A043A("gpLpmaFfj^Z\\URdX][_0XJJSKI", 'õ', 'ó', '\000'), gguuuu.bк043Aккк043Aкк043A043A("\026\037l\017\035\tl\013\n\b\005\003\004\013c\f}}\007~|", '\005', 'Í', '\002'), gguuuu.bк043Aккк043Aкк043A043A("QZ.TQH+OSTP>J>?/A<M%C?;4I\0233A-46<\r5''0(&", 'Y', 'A', '\000'), gguuuu.bк043Aккк043Aкк043A043A("AJ$DH<8:30B6;9\r.6;8*\t1##,$\"", 'æ', '@', '\002'), gguuuu.bккккк043Aкк043A043A("\f\027e\024\b!\025\036\024\017 |\037$y w\"\026\030#\035\035", '\021', '\004'), gguuuu.bк043Aккк043Aкк043A043A(")4\022$=\b8,,2>\016-?2\021I\02575=I\0318J=\037I=?JDD", '¿', 'ÿ', '\001'), gguuuu.bк043Aккк043Aкк043A043A("Q\\5D/2\\PR]WW", 'ð', 'ô', '\003'), gguuuu.bккккк043Aкк043A043A("T_:]QY]W6\\Vj<fZ\\gaa", 'x', '\001'), gguuuu.bккккк043Aкк043A043A("lwWg{m]rpM}~Syr~\003{Z\005xz\006", 'A', '\004'), gguuuu.bк043Aккк043Aкк043A043A("x\004a\b\007|c\006\f\002\004~}\022\b\017\017\025q\024\031n\025l\027\013\r\030\022\022", '«', '\035', '\001'), gguuuu.bк043Aккк043Aкк043A043A("@K)OND+MSIGKFEYOVV\\=P`aW]Wd7aUWb\\\\", '|', '¥', '\001'), gguuuu.bккккк043Aкк043A043A("8A\035A>2\0277;/+-&#5).,0~*(\037$ \031)x!\023\023\034\024\022", 'ä', '\002') };
  
  public fbbfff() {}
  
  public static int b041204120412В0412ВВВВ0412()
  {
    return 2;
  }
  
  public static int b0412В0412В0412ВВВВ0412()
  {
    return 54;
  }
  
  public static int bВ04120412В0412ВВВВ0412()
  {
    return 0;
  }
  
  public static int bВВ0412В0412ВВВВ0412()
  {
    return 1;
  }
  
  /* Error */
  public boolean b04120412041204120412ВВВВ0412()
  {
    // Byte code:
    //   0: iconst_1
    //   1: tableswitch	default:+23->24, 0:+-1->0, 1:+50->51
    //   24: iconst_0
    //   25: tableswitch	default:+23->48, 0:+26->51, 1:+-25->0
    //   48: goto -24 -> 24
    //   51: ldc 117
    //   53: bipush 89
    //   55: iconst_1
    //   56: invokestatic 29	kkkkkk/gguuuu:bккккк043Aкк043A043A	(Ljava/lang/String;CC)Ljava/lang/String;
    //   59: astore 7
    //   61: getstatic 119	kkkkkk/fbbfff:bЮЮЮ042EЮ042EЮ042E042E	I
    //   64: istore_1
    //   65: getstatic 121	kkkkkk/fbbfff:b042EЮЮ042EЮ042EЮ042E042E	I
    //   68: istore_2
    //   69: getstatic 119	kkkkkk/fbbfff:bЮЮЮ042EЮ042EЮ042E042E	I
    //   72: istore_3
    //   73: invokestatic 123	kkkkkk/fbbfff:b041204120412В0412ВВВВ0412	()I
    //   76: istore 4
    //   78: getstatic 125	kkkkkk/fbbfff:b042E042EЮ042EЮ042EЮ042E042E	I
    //   81: istore 5
    //   83: iload_1
    //   84: iload_2
    //   85: iadd
    //   86: iload_3
    //   87: imul
    //   88: iload 4
    //   90: irem
    //   91: iload 5
    //   93: if_icmpeq +60 -> 153
    //   96: invokestatic 127	kkkkkk/fbbfff:b0412В0412В0412ВВВВ0412	()I
    //   99: putstatic 119	kkkkkk/fbbfff:bЮЮЮ042EЮ042EЮ042E042E	I
    //   102: invokestatic 127	kkkkkk/fbbfff:b0412В0412В0412ВВВВ0412	()I
    //   105: istore_1
    //   106: iload_1
    //   107: getstatic 121	kkkkkk/fbbfff:b042EЮЮ042EЮ042EЮ042E042E	I
    //   110: iload_1
    //   111: iadd
    //   112: imul
    //   113: getstatic 129	kkkkkk/fbbfff:bЮ042EЮ042EЮ042EЮ042E042E	I
    //   116: irem
    //   117: tableswitch	default:+19->136, 0:+30->147
    //   136: invokestatic 127	kkkkkk/fbbfff:b0412В0412В0412ВВВВ0412	()I
    //   139: putstatic 119	kkkkkk/fbbfff:bЮЮЮ042EЮ042EЮ042E042E	I
    //   142: bipush 85
    //   144: putstatic 125	kkkkkk/fbbfff:b042E042EЮ042EЮ042EЮ042E042E	I
    //   147: invokestatic 127	kkkkkk/fbbfff:b0412В0412В0412ВВВВ0412	()I
    //   150: putstatic 125	kkkkkk/fbbfff:b042E042EЮ042EЮ042EЮ042E042E	I
    //   153: aload_0
    //   154: aload 7
    //   156: iconst_1
    //   157: invokestatic 135	java/lang/Boolean:valueOf	(Z)Ljava/lang/Boolean;
    //   160: invokevirtual 139	kkkkkk/fbbfff:bВВВ04120412ВВВВ0412	(Ljava/lang/String;Ljava/lang/Object;)Ljava/lang/Object;
    //   163: checkcast 131	java/lang/Boolean
    //   166: invokevirtual 142	java/lang/Boolean:booleanValue	()Z
    //   169: istore 6
    //   171: iload 6
    //   173: ireturn
    //   174: astore 7
    //   176: aload 7
    //   178: athrow
    //   179: astore 7
    //   181: aload 7
    //   183: athrow
    // Local variable table:
    //   start	length	slot	name	signature
    //   0	184	0	this	fbbfff
    //   64	49	1	i	int
    //   68	18	2	j	int
    //   72	16	3	k	int
    //   76	15	4	m	int
    //   81	13	5	n	int
    //   169	3	6	bool	boolean
    //   59	96	7	str	String
    //   174	3	7	localException1	Exception
    //   179	3	7	localException2	Exception
    // Exception table:
    //   from	to	target	type
    //   51	78	174	java/lang/Exception
    //   96	102	174	java/lang/Exception
    //   78	83	179	java/lang/Exception
    //   147	153	179	java/lang/Exception
    //   153	171	179	java/lang/Exception
  }
  
  public boolean b0412041204120412В0412ВВВ0412()
  {
    if ((b0412В0412В0412ВВВВ0412() + b042EЮЮ042EЮ042EЮ042E042E) * b0412В0412В0412ВВВВ0412() % bЮ042EЮ042EЮ042EЮ042E042E != b042E042EЮ042EЮ042EЮ042E042E)
    {
      bЮЮЮ042EЮ042EЮ042E042E = b0412В0412В0412ВВВВ0412();
      b042E042EЮ042EЮ042EЮ042E042E = b0412В0412В0412ВВВВ0412();
    }
    Object localObject = bВВВ04120412ВВВВ0412(gguuuu.bккккк043Aкк043A043A("Wb8`_X=ciljZh^aSgdwQqomhKm}ktx\001S}qs~xx", 'y', '\001'), Boolean.valueOf(true));
    int i = bЮЮЮ042EЮ042EЮ042E042E;
    switch (i * (b042EЮЮ042EЮ042EЮ042E042E + i) % bЮ042EЮ042EЮ042EЮ042E042E)
    {
    default: 
      bЮЮЮ042EЮ042EЮ042E042E = b0412В0412В0412ВВВВ0412();
      b042E042EЮ042EЮ042EЮ042E042E = 5;
    }
    return ((Boolean)localObject).booleanValue();
  }
  
  public boolean b041204120412В04120412ВВВ0412()
  {
    Object localObject = bВВВ04120412ВВВВ0412(gguuuu.bк043Aккк043Aкк043A043A("/8\02485)\016.2&\"$\035\032, %#'w \022\022\033\023\021", '#', 'h', '\000'), Boolean.valueOf(false));
    int i = bЮЮЮ042EЮ042EЮ042E042E;
    int j = b042EЮЮ042EЮ042EЮ042E042E;
    switch (1)
    {
    case 0: 
    default: 
      for (;;)
      {
        switch (0)
        {
        }
      }
    }
    if ((i + j) * bЮЮЮ042EЮ042EЮ042E042E % b041204120412В0412ВВВВ0412() != b042E042EЮ042EЮ042EЮ042E042E)
    {
      bЮЮЮ042EЮ042EЮ042E042E = b0412В0412В0412ВВВВ0412();
      b042E042EЮ042EЮ042EЮ042E042E = 12;
    }
    localObject = (Boolean)localObject;
    if ((bЮЮЮ042EЮ042EЮ042E042E + b042EЮЮ042EЮ042EЮ042E042E) * bЮЮЮ042EЮ042EЮ042E042E % bЮ042EЮ042EЮ042EЮ042E042E != bВ04120412В0412ВВВВ0412())
    {
      bЮЮЮ042EЮ042EЮ042E042E = 36;
      b042E042EЮ042EЮ042EЮ042E042E = b0412В0412В0412ВВВВ0412();
    }
    return ((Boolean)localObject).booleanValue();
  }
  
  /* Error */
  public boolean b041204120412ВВ0412ВВВ0412()
  {
    // Byte code:
    //   0: ldc -103
    //   2: sipush 211
    //   5: iconst_2
    //   6: invokestatic 29	kkkkkk/gguuuu:bккккк043Aкк043A043A	(Ljava/lang/String;CC)Ljava/lang/String;
    //   9: astore 7
    //   11: aload_0
    //   12: aload 7
    //   14: iconst_0
    //   15: invokestatic 135	java/lang/Boolean:valueOf	(Z)Ljava/lang/Boolean;
    //   18: invokevirtual 139	kkkkkk/fbbfff:bВВВ04120412ВВВВ0412	(Ljava/lang/String;Ljava/lang/Object;)Ljava/lang/Object;
    //   21: checkcast 131	java/lang/Boolean
    //   24: invokevirtual 142	java/lang/Boolean:booleanValue	()Z
    //   27: istore 6
    //   29: getstatic 119	kkkkkk/fbbfff:bЮЮЮ042EЮ042EЮ042E042E	I
    //   32: istore_1
    //   33: getstatic 121	kkkkkk/fbbfff:b042EЮЮ042EЮ042EЮ042E042E	I
    //   36: istore_2
    //   37: getstatic 119	kkkkkk/fbbfff:bЮЮЮ042EЮ042EЮ042E042E	I
    //   40: istore_3
    //   41: getstatic 129	kkkkkk/fbbfff:bЮ042EЮ042EЮ042EЮ042E042E	I
    //   44: istore 4
    //   46: invokestatic 127	kkkkkk/fbbfff:b0412В0412В0412ВВВВ0412	()I
    //   49: istore 5
    //   51: iload 5
    //   53: getstatic 121	kkkkkk/fbbfff:b042EЮЮ042EЮ042EЮ042E042E	I
    //   56: iload 5
    //   58: iadd
    //   59: imul
    //   60: invokestatic 123	kkkkkk/fbbfff:b041204120412В0412ВВВВ0412	()I
    //   63: irem
    //   64: tableswitch	default:+20->84, 0:+30->94
    //   84: bipush 56
    //   86: putstatic 119	kkkkkk/fbbfff:bЮЮЮ042EЮ042EЮ042E042E	I
    //   89: bipush 93
    //   91: putstatic 125	kkkkkk/fbbfff:b042E042EЮ042EЮ042EЮ042E042E	I
    //   94: getstatic 125	kkkkkk/fbbfff:b042E042EЮ042EЮ042EЮ042E042E	I
    //   97: istore 5
    //   99: iload_1
    //   100: iload_2
    //   101: iadd
    //   102: iload_3
    //   103: imul
    //   104: iload 4
    //   106: irem
    //   107: iload 5
    //   109: if_icmpeq +38 -> 147
    //   112: invokestatic 127	kkkkkk/fbbfff:b0412В0412В0412ВВВВ0412	()I
    //   115: putstatic 119	kkkkkk/fbbfff:bЮЮЮ042EЮ042EЮ042E042E	I
    //   118: invokestatic 127	kkkkkk/fbbfff:b0412В0412В0412ВВВВ0412	()I
    //   121: putstatic 125	kkkkkk/fbbfff:b042E042EЮ042EЮ042EЮ042E042E	I
    //   124: iload 6
    //   126: ireturn
    //   127: astore 7
    //   129: aload 7
    //   131: athrow
    //   132: astore 7
    //   134: aload 7
    //   136: athrow
    //   137: astore 7
    //   139: aload 7
    //   141: athrow
    //   142: astore 7
    //   144: aload 7
    //   146: athrow
    //   147: iload 6
    //   149: ireturn
    // Local variable table:
    //   start	length	slot	name	signature
    //   0	150	0	this	fbbfff
    //   32	70	1	i	int
    //   36	66	2	j	int
    //   40	64	3	k	int
    //   44	63	4	m	int
    //   49	61	5	n	int
    //   27	121	6	bool	boolean
    //   9	4	7	str	String
    //   127	3	7	localException1	Exception
    //   132	3	7	localException2	Exception
    //   137	3	7	localException3	Exception
    //   142	3	7	localException4	Exception
    // Exception table:
    //   from	to	target	type
    //   11	29	127	java/lang/Exception
    //   112	124	132	java/lang/Exception
    //   129	132	132	java/lang/Exception
    //   139	142	132	java/lang/Exception
    //   0	11	137	java/lang/Exception
    //   29	46	142	java/lang/Exception
    //   94	99	142	java/lang/Exception
  }
  
  /* Error */
  public boolean b04120412В041204120412ВВВ0412()
  {
    // Byte code:
    //   0: aload_0
    //   1: ldc -100
    //   3: sipush 206
    //   6: sipush 210
    //   9: iconst_1
    //   10: invokestatic 35	kkkkkk/gguuuu:bк043Aккк043Aкк043A043A	(Ljava/lang/String;CCC)Ljava/lang/String;
    //   13: iconst_0
    //   14: invokestatic 135	java/lang/Boolean:valueOf	(Z)Ljava/lang/Boolean;
    //   17: invokevirtual 139	kkkkkk/fbbfff:bВВВ04120412ВВВВ0412	(Ljava/lang/String;Ljava/lang/Object;)Ljava/lang/Object;
    //   20: astore 7
    //   22: getstatic 119	kkkkkk/fbbfff:bЮЮЮ042EЮ042EЮ042E042E	I
    //   25: getstatic 121	kkkkkk/fbbfff:b042EЮЮ042EЮ042EЮ042E042E	I
    //   28: iadd
    //   29: getstatic 119	kkkkkk/fbbfff:bЮЮЮ042EЮ042EЮ042E042E	I
    //   32: imul
    //   33: getstatic 129	kkkkkk/fbbfff:bЮ042EЮ042EЮ042EЮ042E042E	I
    //   36: irem
    //   37: getstatic 125	kkkkkk/fbbfff:b042E042EЮ042EЮ042EЮ042E042E	I
    //   40: if_icmpeq +15 -> 55
    //   43: invokestatic 127	kkkkkk/fbbfff:b0412В0412В0412ВВВВ0412	()I
    //   46: putstatic 119	kkkkkk/fbbfff:bЮЮЮ042EЮ042EЮ042E042E	I
    //   49: invokestatic 127	kkkkkk/fbbfff:b0412В0412В0412ВВВВ0412	()I
    //   52: putstatic 125	kkkkkk/fbbfff:b042E042EЮ042EЮ042EЮ042E042E	I
    //   55: aload 7
    //   57: checkcast 131	java/lang/Boolean
    //   60: astore 7
    //   62: getstatic 119	kkkkkk/fbbfff:bЮЮЮ042EЮ042EЮ042E042E	I
    //   65: istore_1
    //   66: getstatic 121	kkkkkk/fbbfff:b042EЮЮ042EЮ042EЮ042E042E	I
    //   69: istore_2
    //   70: getstatic 119	kkkkkk/fbbfff:bЮЮЮ042EЮ042EЮ042E042E	I
    //   73: istore_3
    //   74: getstatic 129	kkkkkk/fbbfff:bЮ042EЮ042EЮ042EЮ042E042E	I
    //   77: istore 4
    //   79: getstatic 125	kkkkkk/fbbfff:b042E042EЮ042EЮ042EЮ042E042E	I
    //   82: istore 5
    //   84: iload_1
    //   85: iload_2
    //   86: iadd
    //   87: iload_3
    //   88: imul
    //   89: iload 4
    //   91: irem
    //   92: iload 5
    //   94: if_icmpeq +13 -> 107
    //   97: bipush 85
    //   99: putstatic 119	kkkkkk/fbbfff:bЮЮЮ042EЮ042EЮ042E042E	I
    //   102: bipush 20
    //   104: putstatic 125	kkkkkk/fbbfff:b042E042EЮ042EЮ042EЮ042E042E	I
    //   107: aload 7
    //   109: invokevirtual 142	java/lang/Boolean:booleanValue	()Z
    //   112: istore 6
    //   114: iload 6
    //   116: ireturn
    //   117: astore 7
    //   119: aload 7
    //   121: athrow
    //   122: astore 7
    //   124: aload 7
    //   126: athrow
    // Local variable table:
    //   start	length	slot	name	signature
    //   0	127	0	this	fbbfff
    //   65	22	1	i	int
    //   69	18	2	j	int
    //   73	16	3	k	int
    //   77	15	4	m	int
    //   82	13	5	n	int
    //   112	3	6	bool	boolean
    //   20	88	7	localObject	Object
    //   117	3	7	localException1	Exception
    //   122	3	7	localException2	Exception
    // Exception table:
    //   from	to	target	type
    //   0	22	117	java/lang/Exception
    //   55	62	117	java/lang/Exception
    //   74	84	117	java/lang/Exception
    //   107	114	117	java/lang/Exception
    //   62	74	122	java/lang/Exception
    //   97	107	122	java/lang/Exception
  }
  
  /* Error */
  public boolean b04120412В04120412ВВВВ0412()
  {
    // Byte code:
    //   0: getstatic 119	kkkkkk/fbbfff:bЮЮЮ042EЮ042EЮ042E042E	I
    //   3: getstatic 121	kkkkkk/fbbfff:b042EЮЮ042EЮ042EЮ042E042E	I
    //   6: iadd
    //   7: getstatic 119	kkkkkk/fbbfff:bЮЮЮ042EЮ042EЮ042E042E	I
    //   10: imul
    //   11: getstatic 129	kkkkkk/fbbfff:bЮ042EЮ042EЮ042EЮ042E042E	I
    //   14: irem
    //   15: getstatic 125	kkkkkk/fbbfff:b042E042EЮ042EЮ042EЮ042E042E	I
    //   18: if_icmpeq +108 -> 126
    //   21: getstatic 119	kkkkkk/fbbfff:bЮЮЮ042EЮ042EЮ042E042E	I
    //   24: istore_1
    //   25: iload_1
    //   26: getstatic 121	kkkkkk/fbbfff:b042EЮЮ042EЮ042EЮ042E042E	I
    //   29: iload_1
    //   30: iadd
    //   31: imul
    //   32: invokestatic 123	kkkkkk/fbbfff:b041204120412В0412ВВВВ0412	()I
    //   35: irem
    //   36: tableswitch	default:+20->56, 0:+30->66
    //   56: bipush 34
    //   58: putstatic 119	kkkkkk/fbbfff:bЮЮЮ042EЮ042EЮ042E042E	I
    //   61: bipush 9
    //   63: putstatic 125	kkkkkk/fbbfff:b042E042EЮ042EЮ042EЮ042E042E	I
    //   66: iconst_1
    //   67: tableswitch	default:+21->88, 0:+-1->66, 1:+48->115
    //   88: iconst_1
    //   89: tableswitch	default:+23->112, 0:+-23->66, 1:+26->115
    //   112: goto -24 -> 88
    //   115: bipush 44
    //   117: putstatic 119	kkkkkk/fbbfff:bЮЮЮ042EЮ042EЮ042E042E	I
    //   120: invokestatic 127	kkkkkk/fbbfff:b0412В0412В0412ВВВВ0412	()I
    //   123: putstatic 125	kkkkkk/fbbfff:b042E042EЮ042EЮ042EЮ042E042E	I
    //   126: ldc -97
    //   128: bipush 43
    //   130: iconst_3
    //   131: invokestatic 29	kkkkkk/gguuuu:bккккк043Aкк043A043A	(Ljava/lang/String;CC)Ljava/lang/String;
    //   134: astore_3
    //   135: aload_0
    //   136: aload_3
    //   137: iconst_0
    //   138: invokestatic 135	java/lang/Boolean:valueOf	(Z)Ljava/lang/Boolean;
    //   141: invokevirtual 139	kkkkkk/fbbfff:bВВВ04120412ВВВВ0412	(Ljava/lang/String;Ljava/lang/Object;)Ljava/lang/Object;
    //   144: checkcast 131	java/lang/Boolean
    //   147: invokevirtual 142	java/lang/Boolean:booleanValue	()Z
    //   150: istore_2
    //   151: iload_2
    //   152: ireturn
    //   153: astore_3
    //   154: aload_3
    //   155: athrow
    //   156: astore_3
    //   157: aload_3
    //   158: athrow
    // Local variable table:
    //   start	length	slot	name	signature
    //   0	159	0	this	fbbfff
    //   24	8	1	i	int
    //   150	2	2	bool	boolean
    //   134	3	3	str	String
    //   153	2	3	localException1	Exception
    //   156	2	3	localException2	Exception
    // Exception table:
    //   from	to	target	type
    //   126	135	153	java/lang/Exception
    //   135	151	156	java/lang/Exception
  }
  
  public boolean b04120412В0412В0412ВВВ0412()
  {
    switch (1)
    {
    case 0: 
    default: 
      for (;;)
      {
        switch (1)
        {
        }
      }
    }
    boolean bool = ((Boolean)bВВВ04120412ВВВВ0412(gguuuu.bккккк043Aкк043A043A("juFvjg{m\\~lzqw}w`\005wy\b[\006y{\007\001\001", '\001', '\000'), Boolean.valueOf(true))).booleanValue();
    if ((bЮЮЮ042EЮ042EЮ042E042E + bВВ0412В0412ВВВВ0412()) * bЮЮЮ042EЮ042EЮ042E042E % b041204120412В0412ВВВВ0412() != b042E042EЮ042EЮ042EЮ042E042E)
    {
      int i = bЮЮЮ042EЮ042EЮ042E042E;
      switch (i * (b042EЮЮ042EЮ042EЮ042E042E + i) % bЮ042EЮ042EЮ042EЮ042E042E)
      {
      default: 
        bЮЮЮ042EЮ042EЮ042E042E = b0412В0412В0412ВВВВ0412();
        b042E042EЮ042EЮ042EЮ042E042E = b0412В0412В0412ВВВВ0412();
      }
      bЮЮЮ042EЮ042EЮ042E042E = 16;
      b042E042EЮ042EЮ042EЮ042E042E = b0412В0412В0412ВВВВ0412();
    }
    return bool;
  }
  
  /* Error */
  public boolean b04120412ВВ04120412ВВВ0412()
  {
    // Byte code:
    //   0: getstatic 119	kkkkkk/fbbfff:bЮЮЮ042EЮ042EЮ042E042E	I
    //   3: istore_1
    //   4: getstatic 121	kkkkkk/fbbfff:b042EЮЮ042EЮ042EЮ042E042E	I
    //   7: istore_2
    //   8: getstatic 119	kkkkkk/fbbfff:bЮЮЮ042EЮ042EЮ042E042E	I
    //   11: istore_3
    //   12: getstatic 129	kkkkkk/fbbfff:bЮ042EЮ042EЮ042EЮ042E042E	I
    //   15: istore 4
    //   17: getstatic 119	kkkkkk/fbbfff:bЮЮЮ042EЮ042EЮ042E042E	I
    //   20: getstatic 121	kkkkkk/fbbfff:b042EЮЮ042EЮ042EЮ042E042E	I
    //   23: iadd
    //   24: getstatic 119	kkkkkk/fbbfff:bЮЮЮ042EЮ042EЮ042E042E	I
    //   27: imul
    //   28: getstatic 129	kkkkkk/fbbfff:bЮ042EЮ042EЮ042EЮ042E042E	I
    //   31: irem
    //   32: getstatic 125	kkkkkk/fbbfff:b042E042EЮ042EЮ042EЮ042E042E	I
    //   35: if_icmpeq +14 -> 49
    //   38: bipush 42
    //   40: putstatic 119	kkkkkk/fbbfff:bЮЮЮ042EЮ042EЮ042E042E	I
    //   43: invokestatic 127	kkkkkk/fbbfff:b0412В0412В0412ВВВВ0412	()I
    //   46: putstatic 125	kkkkkk/fbbfff:b042E042EЮ042EЮ042EЮ042E042E	I
    //   49: getstatic 125	kkkkkk/fbbfff:b042E042EЮ042EЮ042EЮ042E042E	I
    //   52: istore 5
    //   54: iload_1
    //   55: iload_2
    //   56: iadd
    //   57: iload_3
    //   58: imul
    //   59: iload 4
    //   61: irem
    //   62: iload 5
    //   64: if_icmpeq +13 -> 77
    //   67: bipush 51
    //   69: putstatic 119	kkkkkk/fbbfff:bЮЮЮ042EЮ042EЮ042E042E	I
    //   72: bipush 64
    //   74: putstatic 125	kkkkkk/fbbfff:b042E042EЮ042EЮ042EЮ042E042E	I
    //   77: ldc -89
    //   79: bipush 73
    //   81: bipush 109
    //   83: iconst_0
    //   84: invokestatic 35	kkkkkk/gguuuu:bк043Aккк043Aкк043A043A	(Ljava/lang/String;CCC)Ljava/lang/String;
    //   87: astore 7
    //   89: aload_0
    //   90: aload 7
    //   92: iconst_0
    //   93: invokestatic 135	java/lang/Boolean:valueOf	(Z)Ljava/lang/Boolean;
    //   96: invokevirtual 139	kkkkkk/fbbfff:bВВВ04120412ВВВВ0412	(Ljava/lang/String;Ljava/lang/Object;)Ljava/lang/Object;
    //   99: checkcast 131	java/lang/Boolean
    //   102: invokevirtual 142	java/lang/Boolean:booleanValue	()Z
    //   105: istore 6
    //   107: iload 6
    //   109: ireturn
    //   110: astore 7
    //   112: aload 7
    //   114: athrow
    //   115: astore 7
    //   117: aload 7
    //   119: athrow
    //   120: astore 7
    //   122: aload 7
    //   124: athrow
    //   125: astore 7
    //   127: aload 7
    //   129: athrow
    // Local variable table:
    //   start	length	slot	name	signature
    //   0	130	0	this	fbbfff
    //   3	54	1	i	int
    //   7	50	2	j	int
    //   11	48	3	k	int
    //   15	47	4	m	int
    //   52	13	5	n	int
    //   105	3	6	bool	boolean
    //   87	4	7	str	String
    //   110	3	7	localException1	Exception
    //   115	3	7	localException2	Exception
    //   120	3	7	localException3	Exception
    //   125	3	7	localException4	Exception
    // Exception table:
    //   from	to	target	type
    //   77	89	110	java/lang/Exception
    //   67	77	115	java/lang/Exception
    //   112	115	115	java/lang/Exception
    //   122	125	115	java/lang/Exception
    //   89	107	120	java/lang/Exception
    //   0	17	125	java/lang/Exception
    //   49	54	125	java/lang/Exception
  }
  
  public boolean b04120412ВВВ0412ВВВ0412()
  {
    Boolean localBoolean = (Boolean)bВВВ04120412ВВВВ0412(gguuuu.bк043Aккк043Aкк043A043A("\tU\006\005r~vszqy~]\002wkXeygeLn_kAi[[d\\Z", '+', 'A', '\000'), Boolean.valueOf(false));
    int i = bЮЮЮ042EЮ042EЮ042E042E;
    switch (i * (b042EЮЮ042EЮ042EЮ042E042E + i) % bЮ042EЮ042EЮ042EЮ042E042E)
    {
    default: 
      bЮЮЮ042EЮ042EЮ042E042E = b0412В0412В0412ВВВВ0412();
      b042E042EЮ042EЮ042EЮ042E042E = 95;
      i = bЮЮЮ042EЮ042EЮ042E042E;
      switch (i * (b042EЮЮ042EЮ042EЮ042E042E + i) % bЮ042EЮ042EЮ042EЮ042E042E)
      {
      default: 
        bЮЮЮ042EЮ042EЮ042E042E = b0412В0412В0412ВВВВ0412();
        b042E042EЮ042EЮ042EЮ042E042E = b0412В0412В0412ВВВВ0412();
      }
      break;
    }
    return localBoolean.booleanValue();
  }
  
  public boolean b0412В041204120412ВВВВ0412()
  {
    return ((Boolean)bВВВ04120412ВВВВ0412(gguuuu.bк043Aккк043Aкк043A043A("8A\016>=+7/,3*27\026:0$\006\"(+\016(y,/y\"\024\024\035\025\023", '\024', '', '\002'), Boolean.valueOf(true))).booleanValue();
  }
  
  /* Error */
  public boolean b0412В04120412В0412ВВВ0412()
  {
    // Byte code:
    //   0: getstatic 119	kkkkkk/fbbfff:bЮЮЮ042EЮ042EЮ042E042E	I
    //   3: getstatic 121	kkkkkk/fbbfff:b042EЮЮ042EЮ042EЮ042E042E	I
    //   6: iadd
    //   7: getstatic 119	kkkkkk/fbbfff:bЮЮЮ042EЮ042EЮ042E042E	I
    //   10: imul
    //   11: getstatic 129	kkkkkk/fbbfff:bЮ042EЮ042EЮ042EЮ042E042E	I
    //   14: irem
    //   15: invokestatic 150	kkkkkk/fbbfff:bВ04120412В0412ВВВВ0412	()I
    //   18: if_icmpeq +14 -> 32
    //   21: invokestatic 127	kkkkkk/fbbfff:b0412В0412В0412ВВВВ0412	()I
    //   24: putstatic 119	kkkkkk/fbbfff:bЮЮЮ042EЮ042EЮ042E042E	I
    //   27: bipush 10
    //   29: putstatic 125	kkkkkk/fbbfff:b042E042EЮ042EЮ042EЮ042E042E	I
    //   32: aload_0
    //   33: ldc -80
    //   35: sipush 157
    //   38: iconst_1
    //   39: invokestatic 29	kkkkkk/gguuuu:bккккк043Aкк043A043A	(Ljava/lang/String;CC)Ljava/lang/String;
    //   42: iconst_1
    //   43: invokestatic 135	java/lang/Boolean:valueOf	(Z)Ljava/lang/Boolean;
    //   46: invokevirtual 139	kkkkkk/fbbfff:bВВВ04120412ВВВВ0412	(Ljava/lang/String;Ljava/lang/Object;)Ljava/lang/Object;
    //   49: astore_3
    //   50: invokestatic 127	kkkkkk/fbbfff:b0412В0412В0412ВВВВ0412	()I
    //   53: istore_1
    //   54: iload_1
    //   55: getstatic 121	kkkkkk/fbbfff:b042EЮЮ042EЮ042EЮ042E042E	I
    //   58: iload_1
    //   59: iadd
    //   60: imul
    //   61: getstatic 129	kkkkkk/fbbfff:bЮ042EЮ042EЮ042EЮ042E042E	I
    //   64: irem
    //   65: tableswitch	default:+19->84, 0:+30->95
    //   84: bipush 91
    //   86: putstatic 119	kkkkkk/fbbfff:bЮЮЮ042EЮ042EЮ042E042E	I
    //   89: invokestatic 127	kkkkkk/fbbfff:b0412В0412В0412ВВВВ0412	()I
    //   92: putstatic 125	kkkkkk/fbbfff:b042E042EЮ042EЮ042EЮ042E042E	I
    //   95: aload_3
    //   96: checkcast 131	java/lang/Boolean
    //   99: invokevirtual 142	java/lang/Boolean:booleanValue	()Z
    //   102: istore_2
    //   103: iload_2
    //   104: ireturn
    //   105: astore_3
    //   106: aload_3
    //   107: athrow
    //   108: astore_3
    //   109: aload_3
    //   110: athrow
    // Local variable table:
    //   start	length	slot	name	signature
    //   0	111	0	this	fbbfff
    //   53	8	1	i	int
    //   102	2	2	bool	boolean
    //   49	47	3	localObject	Object
    //   105	2	3	localException1	Exception
    //   108	2	3	localException2	Exception
    // Exception table:
    //   from	to	target	type
    //   32	50	105	java/lang/Exception
    //   95	103	108	java/lang/Exception
  }
  
  public boolean b0412В0412В04120412ВВВ0412()
  {
    try
    {
      Boolean localBoolean = (Boolean)bВВВ04120412ВВВВ0412(gguuuu.bккккк043Aкк043A043A("\020\033x\013$n\037\023\023\031%t\024&\031w0{\036\034$0\0371$\0060$&1++", '&', '\000'), Boolean.valueOf(false));
      int i = bЮЮЮ042EЮ042EЮ042E042E;
      switch (i * (b042EЮЮ042EЮ042EЮ042E042E + i) % bЮ042EЮ042EЮ042EЮ042E042E)
      {
      default: 
        bЮЮЮ042EЮ042EЮ042E042E = b0412В0412В0412ВВВВ0412();
        b042E042EЮ042EЮ042EЮ042E042E = 35;
      }
      boolean bool = localBoolean.booleanValue();
      return bool;
    }
    catch (Exception localException)
    {
      throw localException;
    }
  }
  
  public boolean b0412В0412ВВ0412ВВВ0412()
  {
    int i = bЮЮЮ042EЮ042EЮ042E042E;
    switch (i * (b042EЮЮ042EЮ042EЮ042E042E + i) % bЮ042EЮ042EЮ042EЮ042E042E)
    {
    default: 
      bЮЮЮ042EЮ042EЮ042E042E = 56;
      b042E042EЮ042EЮ042EЮ042E042E = 10;
    }
    return ((Boolean)bВВВ04120412ВВВВ0412(gguuuu.bк043Aккк043Aкк043A043A("7@\r=<*6.+2)16\0259/#\021. \033,-)/gev\023*#|\035!\025\016\017m\026\b\b\021\t\007", '', '±', '\002'), Boolean.valueOf(false))).booleanValue();
  }
  
  public boolean b0412ВВ041204120412ВВВ0412()
  {
    switch (0)
    {
    case 1: 
    default: 
      for (;;)
      {
        switch (0)
        {
        }
      }
    }
    switch (1)
    {
    case 0: 
    default: 
      for (;;)
      {
        switch (1)
        {
        }
      }
    }
    String str = gguuuu.bккккк043Aкк043A043A("dmImj^Ccg[WYROaUZX\\;LZYMQIT%M??H@>", '\005', '\005');
    if ((bЮЮЮ042EЮ042EЮ042E042E + b042EЮЮ042EЮ042EЮ042E042E) * bЮЮЮ042EЮ042EЮ042E042E % bЮ042EЮ042EЮ042EЮ042E042E != b042E042EЮ042EЮ042EЮ042E042E)
    {
      bЮЮЮ042EЮ042EЮ042E042E = b0412В0412В0412ВВВВ0412();
      b042E042EЮ042EЮ042EЮ042E042E = 55;
      if ((bЮЮЮ042EЮ042EЮ042E042E + bВВ0412В0412ВВВВ0412()) * bЮЮЮ042EЮ042EЮ042E042E % b041204120412В0412ВВВВ0412() != b042E042EЮ042EЮ042EЮ042E042E)
      {
        bЮЮЮ042EЮ042EЮ042E042E = 13;
        b042E042EЮ042EЮ042EЮ042E042E = b0412В0412В0412ВВВВ0412();
      }
    }
    return ((Boolean)bВВВ04120412ВВВВ0412(str, Boolean.valueOf(false))).booleanValue();
  }
  
  public boolean b0412ВВ04120412ВВВВ0412()
  {
    Object localObject = gguuuu.bккккк043Aкк043A043A("NW$5.,D?AO H::C;9", '', '\005');
    switch (1)
    {
    case 0: 
    default: 
      for (;;)
      {
        switch (0)
        {
        }
      }
    }
    int i = bЮЮЮ042EЮ042EЮ042E042E;
    switch (i * (b042EЮЮ042EЮ042EЮ042E042E + i) % bЮ042EЮ042EЮ042EЮ042E042E)
    {
    default: 
      bЮЮЮ042EЮ042EЮ042E042E = 56;
      b042EЮЮ042EЮ042EЮ042E042E = 91;
    }
    localObject = bВВВ04120412ВВВВ0412((String)localObject, Boolean.valueOf(true));
    i = bЮЮЮ042EЮ042EЮ042E042E;
    switch (i * (b042EЮЮ042EЮ042EЮ042E042E + i) % bЮ042EЮ042EЮ042EЮ042E042E)
    {
    default: 
      bЮЮЮ042EЮ042EЮ042E042E = b0412В0412В0412ВВВВ0412();
      b042EЮЮ042EЮ042EЮ042E042E = 59;
    }
    return ((Boolean)localObject).booleanValue();
  }
  
  /* Error */
  public boolean b0412ВВ0412В0412ВВВ0412()
  {
    // Byte code:
    //   0: getstatic 119	kkkkkk/fbbfff:bЮЮЮ042EЮ042EЮ042E042E	I
    //   3: istore_1
    //   4: iload_1
    //   5: getstatic 121	kkkkkk/fbbfff:b042EЮЮ042EЮ042EЮ042E042E	I
    //   8: iload_1
    //   9: iadd
    //   10: imul
    //   11: invokestatic 123	kkkkkk/fbbfff:b041204120412В0412ВВВВ0412	()I
    //   14: irem
    //   15: tableswitch	default:+17->32, 0:+29->44
    //   32: invokestatic 127	kkkkkk/fbbfff:b0412В0412В0412ВВВВ0412	()I
    //   35: putstatic 119	kkkkkk/fbbfff:bЮЮЮ042EЮ042EЮ042E042E	I
    //   38: invokestatic 127	kkkkkk/fbbfff:b0412В0412В0412ВВВВ0412	()I
    //   41: putstatic 125	kkkkkk/fbbfff:b042E042EЮ042EЮ042EЮ042E042E	I
    //   44: ldc -65
    //   46: sipush 185
    //   49: sipush 192
    //   52: iconst_0
    //   53: invokestatic 35	kkkkkk/gguuuu:bк043Aккк043Aкк043A043A	(Ljava/lang/String;CCC)Ljava/lang/String;
    //   56: astore_3
    //   57: getstatic 119	kkkkkk/fbbfff:bЮЮЮ042EЮ042EЮ042E042E	I
    //   60: istore_1
    //   61: iload_1
    //   62: getstatic 121	kkkkkk/fbbfff:b042EЮЮ042EЮ042EЮ042E042E	I
    //   65: iload_1
    //   66: iadd
    //   67: imul
    //   68: getstatic 129	kkkkkk/fbbfff:bЮ042EЮ042EЮ042EЮ042E042E	I
    //   71: irem
    //   72: tableswitch	default:+20->92, 0:+30->102
    //   92: bipush 72
    //   94: putstatic 119	kkkkkk/fbbfff:bЮЮЮ042EЮ042EЮ042E042E	I
    //   97: bipush 86
    //   99: putstatic 125	kkkkkk/fbbfff:b042E042EЮ042EЮ042EЮ042E042E	I
    //   102: aload_0
    //   103: aload_3
    //   104: iconst_1
    //   105: invokestatic 135	java/lang/Boolean:valueOf	(Z)Ljava/lang/Boolean;
    //   108: invokevirtual 139	kkkkkk/fbbfff:bВВВ04120412ВВВВ0412	(Ljava/lang/String;Ljava/lang/Object;)Ljava/lang/Object;
    //   111: checkcast 131	java/lang/Boolean
    //   114: invokevirtual 142	java/lang/Boolean:booleanValue	()Z
    //   117: istore_2
    //   118: iload_2
    //   119: ireturn
    //   120: astore_3
    //   121: aload_3
    //   122: athrow
    //   123: astore_3
    //   124: aload_3
    //   125: athrow
    // Local variable table:
    //   start	length	slot	name	signature
    //   0	126	0	this	fbbfff
    //   3	65	1	i	int
    //   117	2	2	bool	boolean
    //   56	48	3	str	String
    //   120	2	3	localException1	Exception
    //   123	2	3	localException2	Exception
    // Exception table:
    //   from	to	target	type
    //   102	118	120	java/lang/Exception
    //   44	57	123	java/lang/Exception
  }
  
  /* Error */
  public boolean b0412ВВВ04120412ВВВ0412()
  {
    // Byte code:
    //   0: ldc -62
    //   2: sipush 245
    //   5: iconst_1
    //   6: invokestatic 29	kkkkkk/gguuuu:bккккк043Aкк043A043A	(Ljava/lang/String;CC)Ljava/lang/String;
    //   9: astore_2
    //   10: getstatic 119	kkkkkk/fbbfff:bЮЮЮ042EЮ042EЮ042E042E	I
    //   13: invokestatic 164	kkkkkk/fbbfff:bВВ0412В0412ВВВВ0412	()I
    //   16: iadd
    //   17: getstatic 119	kkkkkk/fbbfff:bЮЮЮ042EЮ042EЮ042E042E	I
    //   20: imul
    //   21: getstatic 129	kkkkkk/fbbfff:bЮ042EЮ042EЮ042EЮ042E042E	I
    //   24: irem
    //   25: getstatic 125	kkkkkk/fbbfff:b042E042EЮ042EЮ042EЮ042E042E	I
    //   28: if_icmpeq +13 -> 41
    //   31: bipush 8
    //   33: putstatic 119	kkkkkk/fbbfff:bЮЮЮ042EЮ042EЮ042E042E	I
    //   36: bipush 86
    //   38: putstatic 125	kkkkkk/fbbfff:b042E042EЮ042EЮ042EЮ042E042E	I
    //   41: aload_0
    //   42: aload_2
    //   43: iconst_0
    //   44: invokestatic 135	java/lang/Boolean:valueOf	(Z)Ljava/lang/Boolean;
    //   47: invokevirtual 139	kkkkkk/fbbfff:bВВВ04120412ВВВВ0412	(Ljava/lang/String;Ljava/lang/Object;)Ljava/lang/Object;
    //   50: checkcast 131	java/lang/Boolean
    //   53: invokevirtual 142	java/lang/Boolean:booleanValue	()Z
    //   56: istore_1
    //   57: iload_1
    //   58: ireturn
    //   59: astore_2
    //   60: aload_2
    //   61: athrow
    //   62: astore_2
    //   63: aload_2
    //   64: athrow
    // Local variable table:
    //   start	length	slot	name	signature
    //   0	65	0	this	fbbfff
    //   56	2	1	bool	boolean
    //   9	34	2	str	String
    //   59	2	2	localException1	Exception
    //   62	2	2	localException2	Exception
    // Exception table:
    //   from	to	target	type
    //   0	10	59	java/lang/Exception
    //   41	57	62	java/lang/Exception
  }
  
  public boolean b0412ВВВВ0412ВВВ0412()
  {
    return ((Boolean)bВВВ04120412ВВВВ0412(gguuuu.bккккк043Aкк043A043A("\002\r[\016\017~\r\007\006\017\b\022\031y \030\016v\032\036!\025\020\027\026v!\025\027\"\034\034", '', '\000'), Boolean.valueOf(true))).booleanValue();
  }
  
  /* Error */
  public boolean bВ0412041204120412ВВВВ0412()
  {
    // Byte code:
    //   0: iconst_1
    //   1: tableswitch	default:+23->24, 0:+-1->0, 1:+50->51
    //   24: iconst_0
    //   25: tableswitch	default:+23->48, 0:+26->51, 1:+-25->0
    //   48: goto -24 -> 24
    //   51: getstatic 119	kkkkkk/fbbfff:bЮЮЮ042EЮ042EЮ042E042E	I
    //   54: getstatic 121	kkkkkk/fbbfff:b042EЮЮ042EЮ042EЮ042E042E	I
    //   57: iadd
    //   58: getstatic 119	kkkkkk/fbbfff:bЮЮЮ042EЮ042EЮ042E042E	I
    //   61: imul
    //   62: getstatic 129	kkkkkk/fbbfff:bЮ042EЮ042EЮ042EЮ042E042E	I
    //   65: irem
    //   66: invokestatic 150	kkkkkk/fbbfff:bВ04120412В0412ВВВВ0412	()I
    //   69: if_icmpeq +13 -> 82
    //   72: invokestatic 127	kkkkkk/fbbfff:b0412В0412В0412ВВВВ0412	()I
    //   75: putstatic 119	kkkkkk/fbbfff:bЮЮЮ042EЮ042EЮ042E042E	I
    //   78: iconst_4
    //   79: putstatic 125	kkkkkk/fbbfff:b042E042EЮ042EЮ042EЮ042E042E	I
    //   82: ldc -56
    //   84: bipush 78
    //   86: sipush 200
    //   89: iconst_3
    //   90: invokestatic 35	kkkkkk/gguuuu:bк043Aккк043Aкк043A043A	(Ljava/lang/String;CCC)Ljava/lang/String;
    //   93: astore_2
    //   94: invokestatic 127	kkkkkk/fbbfff:b0412В0412В0412ВВВВ0412	()I
    //   97: getstatic 121	kkkkkk/fbbfff:b042EЮЮ042EЮ042EЮ042E042E	I
    //   100: iadd
    //   101: invokestatic 127	kkkkkk/fbbfff:b0412В0412В0412ВВВВ0412	()I
    //   104: imul
    //   105: getstatic 129	kkkkkk/fbbfff:bЮ042EЮ042EЮ042EЮ042E042E	I
    //   108: irem
    //   109: getstatic 125	kkkkkk/fbbfff:b042E042EЮ042EЮ042EЮ042E042E	I
    //   112: if_icmpeq +15 -> 127
    //   115: invokestatic 127	kkkkkk/fbbfff:b0412В0412В0412ВВВВ0412	()I
    //   118: putstatic 119	kkkkkk/fbbfff:bЮЮЮ042EЮ042EЮ042E042E	I
    //   121: invokestatic 127	kkkkkk/fbbfff:b0412В0412В0412ВВВВ0412	()I
    //   124: putstatic 125	kkkkkk/fbbfff:b042E042EЮ042EЮ042EЮ042E042E	I
    //   127: aload_0
    //   128: aload_2
    //   129: iconst_1
    //   130: invokestatic 135	java/lang/Boolean:valueOf	(Z)Ljava/lang/Boolean;
    //   133: invokevirtual 139	kkkkkk/fbbfff:bВВВ04120412ВВВВ0412	(Ljava/lang/String;Ljava/lang/Object;)Ljava/lang/Object;
    //   136: checkcast 131	java/lang/Boolean
    //   139: invokevirtual 142	java/lang/Boolean:booleanValue	()Z
    //   142: istore_1
    //   143: iload_1
    //   144: ireturn
    //   145: astore_2
    //   146: aload_2
    //   147: athrow
    //   148: astore_2
    //   149: aload_2
    //   150: athrow
    // Exception table:
    //   from	to	target	type
    //   82	94	145	java/lang/Exception
    //   127	143	145	java/lang/Exception
  }
  
  /* Error */
  public boolean bВ041204120412В0412ВВВ0412()
  {
    // Byte code:
    //   0: ldc -53
    //   2: bipush 106
    //   4: sipush 155
    //   7: iconst_0
    //   8: invokestatic 35	kkkkkk/gguuuu:bк043Aккк043Aкк043A043A	(Ljava/lang/String;CCC)Ljava/lang/String;
    //   11: astore 6
    //   13: aload_0
    //   14: aload 6
    //   16: iconst_1
    //   17: invokestatic 135	java/lang/Boolean:valueOf	(Z)Ljava/lang/Boolean;
    //   20: invokevirtual 139	kkkkkk/fbbfff:bВВВ04120412ВВВВ0412	(Ljava/lang/String;Ljava/lang/Object;)Ljava/lang/Object;
    //   23: checkcast 131	java/lang/Boolean
    //   26: astore 6
    //   28: getstatic 119	kkkkkk/fbbfff:bЮЮЮ042EЮ042EЮ042E042E	I
    //   31: istore_1
    //   32: getstatic 121	kkkkkk/fbbfff:b042EЮЮ042EЮ042EЮ042E042E	I
    //   35: istore_2
    //   36: getstatic 119	kkkkkk/fbbfff:bЮЮЮ042EЮ042EЮ042E042E	I
    //   39: istore_3
    //   40: invokestatic 127	kkkkkk/fbbfff:b0412В0412В0412ВВВВ0412	()I
    //   43: istore 4
    //   45: iload 4
    //   47: getstatic 121	kkkkkk/fbbfff:b042EЮЮ042EЮ042EЮ042E042E	I
    //   50: iload 4
    //   52: iadd
    //   53: imul
    //   54: getstatic 129	kkkkkk/fbbfff:bЮ042EЮ042EЮ042EЮ042E042E	I
    //   57: irem
    //   58: tableswitch	default:+18->76, 0:+28->86
    //   76: bipush 71
    //   78: putstatic 119	kkkkkk/fbbfff:bЮЮЮ042EЮ042EЮ042E042E	I
    //   81: bipush 41
    //   83: putstatic 125	kkkkkk/fbbfff:b042E042EЮ042EЮ042EЮ042E042E	I
    //   86: iload_1
    //   87: iload_2
    //   88: iadd
    //   89: iload_3
    //   90: imul
    //   91: getstatic 129	kkkkkk/fbbfff:bЮ042EЮ042EЮ042EЮ042E042E	I
    //   94: irem
    //   95: getstatic 125	kkkkkk/fbbfff:b042E042EЮ042EЮ042EЮ042E042E	I
    //   98: if_icmpeq +14 -> 112
    //   101: invokestatic 127	kkkkkk/fbbfff:b0412В0412В0412ВВВВ0412	()I
    //   104: putstatic 119	kkkkkk/fbbfff:bЮЮЮ042EЮ042EЮ042E042E	I
    //   107: bipush 44
    //   109: putstatic 125	kkkkkk/fbbfff:b042E042EЮ042EЮ042EЮ042E042E	I
    //   112: aload 6
    //   114: invokevirtual 142	java/lang/Boolean:booleanValue	()Z
    //   117: istore 5
    //   119: iload 5
    //   121: ireturn
    //   122: astore 6
    //   124: aload 6
    //   126: athrow
    //   127: astore 6
    //   129: aload 6
    //   131: athrow
    // Local variable table:
    //   start	length	slot	name	signature
    //   0	132	0	this	fbbfff
    //   31	58	1	i	int
    //   35	54	2	j	int
    //   39	52	3	k	int
    //   43	11	4	m	int
    //   117	3	5	bool	boolean
    //   11	102	6	localObject	Object
    //   122	3	6	localException1	Exception
    //   127	3	6	localException2	Exception
    // Exception table:
    //   from	to	target	type
    //   13	28	122	java/lang/Exception
    //   0	13	127	java/lang/Exception
    //   112	119	127	java/lang/Exception
  }
  
  public boolean bВ04120412В04120412ВВВ0412()
  {
    Object localObject = bВВВ04120412ВВВВ0412(gguuuu.bккккк043Aкк043A043A("\b\023p\027\026\fr\025\033\021\017\023\016\r!\027\036\036$t\"\"\033\" \033-~)\035\037*$$", '', '\000'), Boolean.valueOf(false));
    int i = bЮЮЮ042EЮ042EЮ042E042E;
    switch (i * (b042EЮЮ042EЮ042EЮ042E042E + i) % bЮ042EЮ042EЮ042EЮ042E042E)
    {
    default: 
      bЮЮЮ042EЮ042EЮ042E042E = 59;
      b042E042EЮ042EЮ042EЮ042E042E = 72;
    }
    i = bЮЮЮ042EЮ042EЮ042E042E;
    int j = bВВ0412В0412ВВВВ0412();
    int k = bЮ042EЮ042EЮ042EЮ042E042E;
    switch (0)
    {
    case 1: 
    default: 
      for (;;)
      {
        switch (1)
        {
        }
      }
    }
    switch (i * (j + i) % k)
    {
    default: 
      bЮЮЮ042EЮ042EЮ042E042E = 84;
      b042E042EЮ042EЮ042EЮ042E042E = 13;
    }
    switch (0)
    {
    case 1: 
    default: 
      for (;;)
      {
        switch (1)
        {
        }
      }
    }
    return ((Boolean)localObject).booleanValue();
  }
  
  /* Error */
  public boolean bВ04120412ВВ0412ВВВ0412()
  {
    // Byte code:
    //   0: ldc -47
    //   2: bipush 19
    //   4: iconst_3
    //   5: invokestatic 29	kkkkkk/gguuuu:bккккк043Aкк043A043A	(Ljava/lang/String;CC)Ljava/lang/String;
    //   8: astore 7
    //   10: invokestatic 127	kkkkkk/fbbfff:b0412В0412В0412ВВВВ0412	()I
    //   13: istore_1
    //   14: iload_1
    //   15: getstatic 121	kkkkkk/fbbfff:b042EЮЮ042EЮ042EЮ042E042E	I
    //   18: iload_1
    //   19: iadd
    //   20: imul
    //   21: getstatic 129	kkkkkk/fbbfff:bЮ042EЮ042EЮ042EЮ042E042E	I
    //   24: irem
    //   25: tableswitch	default:+19->44, 0:+30->55
    //   44: invokestatic 127	kkkkkk/fbbfff:b0412В0412В0412ВВВВ0412	()I
    //   47: putstatic 119	kkkkkk/fbbfff:bЮЮЮ042EЮ042EЮ042E042E	I
    //   50: bipush 45
    //   52: putstatic 125	kkkkkk/fbbfff:b042E042EЮ042EЮ042EЮ042E042E	I
    //   55: iconst_1
    //   56: tableswitch	default:+24->80, 0:+-1->55, 1:+51->107
    //   80: iconst_0
    //   81: tableswitch	default:+23->104, 0:+26->107, 1:+-26->55
    //   104: goto -24 -> 80
    //   107: aload_0
    //   108: aload 7
    //   110: iconst_0
    //   111: invokestatic 135	java/lang/Boolean:valueOf	(Z)Ljava/lang/Boolean;
    //   114: invokevirtual 139	kkkkkk/fbbfff:bВВВ04120412ВВВВ0412	(Ljava/lang/String;Ljava/lang/Object;)Ljava/lang/Object;
    //   117: checkcast 131	java/lang/Boolean
    //   120: astore 7
    //   122: aload 7
    //   124: invokevirtual 142	java/lang/Boolean:booleanValue	()Z
    //   127: istore 6
    //   129: getstatic 119	kkkkkk/fbbfff:bЮЮЮ042EЮ042EЮ042E042E	I
    //   132: istore_1
    //   133: getstatic 121	kkkkkk/fbbfff:b042EЮЮ042EЮ042EЮ042E042E	I
    //   136: istore_2
    //   137: getstatic 119	kkkkkk/fbbfff:bЮЮЮ042EЮ042EЮ042E042E	I
    //   140: istore_3
    //   141: getstatic 129	kkkkkk/fbbfff:bЮ042EЮ042EЮ042EЮ042E042E	I
    //   144: istore 4
    //   146: invokestatic 150	kkkkkk/fbbfff:bВ04120412В0412ВВВВ0412	()I
    //   149: istore 5
    //   151: iload_1
    //   152: iload_2
    //   153: iadd
    //   154: iload_3
    //   155: imul
    //   156: iload 4
    //   158: irem
    //   159: iload 5
    //   161: if_icmpeq +13 -> 174
    //   164: bipush 11
    //   166: putstatic 119	kkkkkk/fbbfff:bЮЮЮ042EЮ042EЮ042E042E	I
    //   169: bipush 73
    //   171: putstatic 125	kkkkkk/fbbfff:b042E042EЮ042EЮ042EЮ042E042E	I
    //   174: iload 6
    //   176: ireturn
    //   177: astore 7
    //   179: aload 7
    //   181: athrow
    //   182: astore 7
    //   184: aload 7
    //   186: athrow
    // Local variable table:
    //   start	length	slot	name	signature
    //   0	187	0	this	fbbfff
    //   13	141	1	i	int
    //   136	18	2	j	int
    //   140	16	3	k	int
    //   144	15	4	m	int
    //   149	13	5	n	int
    //   127	48	6	bool	boolean
    //   8	115	7	localObject	Object
    //   177	3	7	localException1	Exception
    //   182	3	7	localException2	Exception
    // Exception table:
    //   from	to	target	type
    //   0	10	177	java/lang/Exception
    //   122	151	177	java/lang/Exception
    //   107	122	182	java/lang/Exception
    //   164	174	182	java/lang/Exception
  }
  
  public boolean bВ0412В041204120412ВВВ0412()
  {
    switch (1)
    {
    case 0: 
    default: 
      for (;;)
      {
        switch (1)
        {
        }
      }
    }
    switch (0)
    {
    case 1: 
    default: 
      for (;;)
      {
        switch (1)
        {
        }
      }
    }
    if ((bЮЮЮ042EЮ042EЮ042E042E + b042EЮЮ042EЮ042EЮ042E042E) * bЮЮЮ042EЮ042EЮ042E042E % bЮ042EЮ042EЮ042EЮ042E042E != b042E042EЮ042EЮ042EЮ042E042E)
    {
      bЮЮЮ042EЮ042EЮ042E042E = 83;
      b042E042EЮ042EЮ042EЮ042E042E = 0;
      int i = bЮЮЮ042EЮ042EЮ042E042E;
      switch (i * (b042EЮЮ042EЮ042EЮ042E042E + i) % bЮ042EЮ042EЮ042EЮ042E042E)
      {
      default: 
        bЮЮЮ042EЮ042EЮ042E042E = b0412В0412В0412ВВВВ0412();
        b042E042EЮ042EЮ042EЮ042E042E = 84;
      }
    }
    return ((Boolean)bВВВ04120412ВВВВ0412(gguuuu.bк043Aккк043Aкк043A043A("\001\fk{\020\002q\007\005a\022\023g\016\007\023\027\020n\031\r\017\032\024\024", '4', 'á', '\003'), Boolean.valueOf(true))).booleanValue();
  }
  
  public boolean bВ0412В04120412ВВВВ0412()
  {
    switch (0)
    {
    case 1: 
    default: 
      for (;;)
      {
        switch (0)
        {
        }
      }
    }
    switch (0)
    {
    case 1: 
    default: 
      for (;;)
      {
        switch (0)
        {
        }
      }
    }
    String str = gguuuu.bк043Aккк043Aкк043A043A("CN\035K?XLUKFW4V[1W/YMOZTT", 'Ù', 'ý', '\003');
    if ((bЮЮЮ042EЮ042EЮ042E042E + bВВ0412В0412ВВВВ0412()) * bЮЮЮ042EЮ042EЮ042E042E % bЮ042EЮ042EЮ042EЮ042E042E != b042E042EЮ042EЮ042EЮ042E042E)
    {
      bЮЮЮ042EЮ042EЮ042E042E = 46;
      b042E042EЮ042EЮ042EЮ042E042E = 30;
    }
    int i = bЮЮЮ042EЮ042EЮ042E042E;
    switch (i * (b042EЮЮ042EЮ042EЮ042E042E + i) % bЮ042EЮ042EЮ042EЮ042E042E)
    {
    default: 
      bЮЮЮ042EЮ042EЮ042E042E = 30;
      b042EЮЮ042EЮ042EЮ042E042E = 80;
    }
    return ((Boolean)bВВВ04120412ВВВВ0412(str, Boolean.valueOf(true))).booleanValue();
  }
  
  public boolean bВ0412В0412В0412ВВВ0412()
  {
    try
    {
      Object localObject = bВВВ04120412ВВВВ0412(gguuuu.bк043Aккк043Aкк043A043A("#,z)\033\026(\030~\032~\035s\026\036\036\036t\027\016\017\023h\021\003\003\f\004\002", 'b', '\034', '\000'), Boolean.valueOf(true));
      int i = bЮЮЮ042EЮ042EЮ042E042E;
      switch (i * (b042EЮЮ042EЮ042EЮ042E042E + i) % bЮ042EЮ042EЮ042EЮ042E042E)
      {
      default: 
        bЮЮЮ042EЮ042EЮ042E042E = b0412В0412В0412ВВВВ0412();
        b042E042EЮ042EЮ042EЮ042E042E = 72;
        i = b0412В0412В0412ВВВВ0412();
        switch (i * (bВВ0412В0412ВВВВ0412() + i) % bЮ042EЮ042EЮ042EЮ042E042E)
        {
        default: 
          bЮЮЮ042EЮ042EЮ042E042E = 24;
          b042E042EЮ042EЮ042EЮ042E042E = b0412В0412В0412ВВВВ0412();
        }
        break;
      }
      try
      {
        localObject = (Boolean)localObject;
      }
      catch (Exception localException1)
      {
        boolean bool;
        throw localException1;
      }
      bool = ((Boolean)localObject).booleanValue();
      return bool;
    }
    catch (Exception localException2)
    {
      throw localException2;
    }
    switch (1)
    {
    }
    for (;;)
    {
      switch (1)
      {
      }
    }
  }
  
  /* Error */
  public boolean bВ0412ВВ04120412ВВВ0412()
  {
    // Byte code:
    //   0: invokestatic 127	kkkkkk/fbbfff:b0412В0412В0412ВВВВ0412	()I
    //   3: istore_1
    //   4: iload_1
    //   5: getstatic 121	kkkkkk/fbbfff:b042EЮЮ042EЮ042EЮ042E042E	I
    //   8: iload_1
    //   9: iadd
    //   10: imul
    //   11: getstatic 129	kkkkkk/fbbfff:bЮ042EЮ042EЮ042EЮ042E042E	I
    //   14: irem
    //   15: tableswitch	default:+17->32, 0:+71->86
    //   32: getstatic 119	kkkkkk/fbbfff:bЮЮЮ042EЮ042EЮ042E042E	I
    //   35: istore_1
    //   36: iload_1
    //   37: invokestatic 164	kkkkkk/fbbfff:bВВ0412В0412ВВВВ0412	()I
    //   40: iload_1
    //   41: iadd
    //   42: imul
    //   43: invokestatic 123	kkkkkk/fbbfff:b041204120412В0412ВВВВ0412	()I
    //   46: irem
    //   47: tableswitch	default:+17->64, 0:+28->75
    //   64: bipush 64
    //   66: putstatic 119	kkkkkk/fbbfff:bЮЮЮ042EЮ042EЮ042E042E	I
    //   69: invokestatic 127	kkkkkk/fbbfff:b0412В0412В0412ВВВВ0412	()I
    //   72: putstatic 125	kkkkkk/fbbfff:b042E042EЮ042EЮ042EЮ042E042E	I
    //   75: invokestatic 127	kkkkkk/fbbfff:b0412В0412В0412ВВВВ0412	()I
    //   78: putstatic 119	kkkkkk/fbbfff:bЮЮЮ042EЮ042EЮ042E042E	I
    //   81: bipush 20
    //   83: putstatic 125	kkkkkk/fbbfff:b042E042EЮ042EЮ042EЮ042E042E	I
    //   86: ldc -35
    //   88: sipush 247
    //   91: bipush 76
    //   93: iconst_1
    //   94: invokestatic 35	kkkkkk/gguuuu:bк043Aккк043Aкк043A043A	(Ljava/lang/String;CCC)Ljava/lang/String;
    //   97: astore_3
    //   98: aload_0
    //   99: aload_3
    //   100: iconst_0
    //   101: invokestatic 135	java/lang/Boolean:valueOf	(Z)Ljava/lang/Boolean;
    //   104: invokevirtual 139	kkkkkk/fbbfff:bВВВ04120412ВВВВ0412	(Ljava/lang/String;Ljava/lang/Object;)Ljava/lang/Object;
    //   107: checkcast 131	java/lang/Boolean
    //   110: invokevirtual 142	java/lang/Boolean:booleanValue	()Z
    //   113: istore_2
    //   114: iload_2
    //   115: ireturn
    //   116: astore_3
    //   117: aload_3
    //   118: athrow
    //   119: astore_3
    //   120: aload_3
    //   121: athrow
    // Local variable table:
    //   start	length	slot	name	signature
    //   0	122	0	this	fbbfff
    //   3	40	1	i	int
    //   113	2	2	bool	boolean
    //   97	3	3	str	String
    //   116	2	3	localException1	Exception
    //   119	2	3	localException2	Exception
    // Exception table:
    //   from	to	target	type
    //   86	98	116	java/lang/Exception
    //   98	114	119	java/lang/Exception
  }
  
  public boolean bВ0412ВВВ0412ВВВ0412()
  {
    return ((Boolean)bВВВ04120412ВВВВ0412(gguuuu.bккккк043Aкк043A043A(" )u&%\023\037\027\024\033\022\032\037}\"\030\fr\024\026\027\t\002\007\004rbnm^\007xx\002yw", 'I', '\005'), Boolean.valueOf(true))).booleanValue();
  }
  
  public boolean bВВ0412041204120412ВВВ0412()
  {
    String str = gguuuu.bккккк043Aкк043A043A("9D&8@A+J\035G;=HBB", 'æ', '\004');
    switch (0)
    {
    case 1: 
    default: 
      for (;;)
      {
        switch (1)
        {
        case 0: 
        default: 
          for (;;)
          {
            switch (0)
            {
            }
          }
        }
        if ((bЮЮЮ042EЮ042EЮ042E042E + b042EЮЮ042EЮ042EЮ042E042E) * bЮЮЮ042EЮ042EЮ042E042E % bЮ042EЮ042EЮ042EЮ042E042E != b042E042EЮ042EЮ042EЮ042E042E)
        {
          bЮЮЮ042EЮ042EЮ042E042E = b0412В0412В0412ВВВВ0412();
          b042E042EЮ042EЮ042EЮ042E042E = 56;
        }
        switch (1)
        {
        }
      }
    }
    boolean bool = ((Boolean)bВВВ04120412ВВВВ0412(str, Boolean.valueOf(true))).booleanValue();
    if ((bЮЮЮ042EЮ042EЮ042E042E + bВВ0412В0412ВВВВ0412()) * bЮЮЮ042EЮ042EЮ042E042E % bЮ042EЮ042EЮ042EЮ042E042E != b042E042EЮ042EЮ042EЮ042E042E)
    {
      bЮЮЮ042EЮ042EЮ042E042E = b0412В0412В0412ВВВВ0412();
      b042E042EЮ042EЮ042EЮ042E042E = b0412В0412В0412ВВВВ0412();
    }
    return bool;
  }
  
  public boolean bВВ041204120412ВВВВ0412()
  {
    int i = bЮЮЮ042EЮ042EЮ042E042E;
    switch (i * (b042EЮЮ042EЮ042EЮ042E042E + i) % bЮ042EЮ042EЮ042EЮ042E042E)
    {
    default: 
      bЮЮЮ042EЮ042EЮ042E042E = 38;
      b042E042EЮ042EЮ042EЮ042E042E = b0412В0412В0412ВВВВ0412();
      i = bЮЮЮ042EЮ042EЮ042E042E;
      switch (i * (b042EЮЮ042EЮ042EЮ042E042E + i) % bЮ042EЮ042EЮ042EЮ042E042E)
      {
      default: 
        bЮЮЮ042EЮ042EЮ042E042E = b0412В0412В0412ВВВВ0412();
        b042E042EЮ042EЮ042EЮ042E042E = 61;
      }
      break;
    }
    return ((Boolean)bВВВ04120412ВВВВ0412(gguuuu.bккккк043Aкк043A043A("<E\022BA/;307.6;\032>4(\t\n\001\004,\036\036'\037\035", '\017', '\002'), Boolean.valueOf(false))).booleanValue();
  }
  
  /* Error */
  public boolean bВВ04120412В0412ВВВ0412()
  {
    // Byte code:
    //   0: ldc -23
    //   2: sipush 145
    //   5: bipush 116
    //   7: iconst_3
    //   8: invokestatic 35	kkkkkk/gguuuu:bк043Aккк043Aкк043A043A	(Ljava/lang/String;CCC)Ljava/lang/String;
    //   11: astore_2
    //   12: getstatic 119	kkkkkk/fbbfff:bЮЮЮ042EЮ042EЮ042E042E	I
    //   15: getstatic 121	kkkkkk/fbbfff:b042EЮЮ042EЮ042EЮ042E042E	I
    //   18: iadd
    //   19: getstatic 119	kkkkkk/fbbfff:bЮЮЮ042EЮ042EЮ042E042E	I
    //   22: imul
    //   23: invokestatic 123	kkkkkk/fbbfff:b041204120412В0412ВВВВ0412	()I
    //   26: irem
    //   27: getstatic 125	kkkkkk/fbbfff:b042E042EЮ042EЮ042EЮ042E042E	I
    //   30: if_icmpeq +47 -> 77
    //   33: getstatic 119	kkkkkk/fbbfff:bЮЮЮ042EЮ042EЮ042E042E	I
    //   36: invokestatic 164	kkkkkk/fbbfff:bВВ0412В0412ВВВВ0412	()I
    //   39: iadd
    //   40: getstatic 119	kkkkkk/fbbfff:bЮЮЮ042EЮ042EЮ042E042E	I
    //   43: imul
    //   44: getstatic 129	kkkkkk/fbbfff:bЮ042EЮ042EЮ042EЮ042E042E	I
    //   47: irem
    //   48: getstatic 125	kkkkkk/fbbfff:b042E042EЮ042EЮ042EЮ042E042E	I
    //   51: if_icmpeq +14 -> 65
    //   54: bipush 75
    //   56: putstatic 119	kkkkkk/fbbfff:bЮЮЮ042EЮ042EЮ042E042E	I
    //   59: invokestatic 127	kkkkkk/fbbfff:b0412В0412В0412ВВВВ0412	()I
    //   62: putstatic 125	kkkkkk/fbbfff:b042E042EЮ042EЮ042EЮ042E042E	I
    //   65: invokestatic 127	kkkkkk/fbbfff:b0412В0412В0412ВВВВ0412	()I
    //   68: putstatic 119	kkkkkk/fbbfff:bЮЮЮ042EЮ042EЮ042E042E	I
    //   71: invokestatic 127	kkkkkk/fbbfff:b0412В0412В0412ВВВВ0412	()I
    //   74: putstatic 125	kkkkkk/fbbfff:b042E042EЮ042EЮ042EЮ042E042E	I
    //   77: aload_0
    //   78: aload_2
    //   79: iconst_0
    //   80: invokestatic 135	java/lang/Boolean:valueOf	(Z)Ljava/lang/Boolean;
    //   83: invokevirtual 139	kkkkkk/fbbfff:bВВВ04120412ВВВВ0412	(Ljava/lang/String;Ljava/lang/Object;)Ljava/lang/Object;
    //   86: checkcast 131	java/lang/Boolean
    //   89: invokevirtual 142	java/lang/Boolean:booleanValue	()Z
    //   92: istore_1
    //   93: iload_1
    //   94: ireturn
    //   95: astore_2
    //   96: iconst_0
    //   97: tableswitch	default:+23->120, 0:+50->147, 1:+-1->96
    //   120: iconst_0
    //   121: tableswitch	default:+23->144, 0:+26->147, 1:+-25->96
    //   144: goto -24 -> 120
    //   147: aload_2
    //   148: athrow
    //   149: astore_2
    //   150: aload_2
    //   151: athrow
    // Local variable table:
    //   start	length	slot	name	signature
    //   0	152	0	this	fbbfff
    //   92	2	1	bool	boolean
    //   11	68	2	str	String
    //   95	53	2	localException1	Exception
    //   149	2	2	localException2	Exception
    // Exception table:
    //   from	to	target	type
    //   0	12	95	java/lang/Exception
    //   77	93	149	java/lang/Exception
  }
  
  /* Error */
  public boolean bВВ0412В04120412ВВВ0412()
  {
    // Byte code:
    //   0: ldc -20
    //   2: iconst_1
    //   3: sipush 150
    //   6: iconst_1
    //   7: invokestatic 35	kkkkkk/gguuuu:bк043Aккк043Aкк043A043A	(Ljava/lang/String;CCC)Ljava/lang/String;
    //   10: astore 5
    //   12: iconst_0
    //   13: tableswitch	default:+23->36, 0:+82->95, 1:+-1->12
    //   36: getstatic 119	kkkkkk/fbbfff:bЮЮЮ042EЮ042EЮ042E042E	I
    //   39: invokestatic 164	kkkkkk/fbbfff:bВВ0412В0412ВВВВ0412	()I
    //   42: iadd
    //   43: getstatic 119	kkkkkk/fbbfff:bЮЮЮ042EЮ042EЮ042E042E	I
    //   46: imul
    //   47: getstatic 129	kkkkkk/fbbfff:bЮ042EЮ042EЮ042EЮ042E042E	I
    //   50: irem
    //   51: getstatic 125	kkkkkk/fbbfff:b042E042EЮ042EЮ042EЮ042E042E	I
    //   54: if_icmpeq +13 -> 67
    //   57: bipush 94
    //   59: putstatic 119	kkkkkk/fbbfff:bЮЮЮ042EЮ042EЮ042E042E	I
    //   62: bipush 60
    //   64: putstatic 125	kkkkkk/fbbfff:b042E042EЮ042EЮ042EЮ042E042E	I
    //   67: iconst_0
    //   68: tableswitch	default:+24->92, 0:+27->95, 1:+-56->12
    //   92: goto -56 -> 36
    //   95: aload_0
    //   96: aload 5
    //   98: iconst_0
    //   99: invokestatic 135	java/lang/Boolean:valueOf	(Z)Ljava/lang/Boolean;
    //   102: invokevirtual 139	kkkkkk/fbbfff:bВВВ04120412ВВВВ0412	(Ljava/lang/String;Ljava/lang/Object;)Ljava/lang/Object;
    //   105: astore 5
    //   107: getstatic 119	kkkkkk/fbbfff:bЮЮЮ042EЮ042EЮ042E042E	I
    //   110: istore_1
    //   111: getstatic 121	kkkkkk/fbbfff:b042EЮЮ042EЮ042EЮ042E042E	I
    //   114: istore_2
    //   115: getstatic 129	kkkkkk/fbbfff:bЮ042EЮ042EЮ042EЮ042E042E	I
    //   118: istore_3
    //   119: iload_1
    //   120: iload_2
    //   121: iload_1
    //   122: iadd
    //   123: imul
    //   124: iload_3
    //   125: irem
    //   126: tableswitch	default:+18->144, 0:+30->156
    //   144: invokestatic 127	kkkkkk/fbbfff:b0412В0412В0412ВВВВ0412	()I
    //   147: putstatic 119	kkkkkk/fbbfff:bЮЮЮ042EЮ042EЮ042E042E	I
    //   150: invokestatic 127	kkkkkk/fbbfff:b0412В0412В0412ВВВВ0412	()I
    //   153: putstatic 125	kkkkkk/fbbfff:b042E042EЮ042EЮ042EЮ042E042E	I
    //   156: aload 5
    //   158: checkcast 131	java/lang/Boolean
    //   161: invokevirtual 142	java/lang/Boolean:booleanValue	()Z
    //   164: istore 4
    //   166: iload 4
    //   168: ireturn
    //   169: astore 5
    //   171: aload 5
    //   173: athrow
    //   174: astore 5
    //   176: aload 5
    //   178: athrow
    // Local variable table:
    //   start	length	slot	name	signature
    //   0	179	0	this	fbbfff
    //   110	14	1	i	int
    //   114	9	2	j	int
    //   118	8	3	k	int
    //   164	3	4	bool	boolean
    //   10	147	5	localObject	Object
    //   169	3	5	localException1	Exception
    //   174	3	5	localException2	Exception
    // Exception table:
    //   from	to	target	type
    //   0	12	169	java/lang/Exception
    //   95	107	169	java/lang/Exception
    //   144	156	169	java/lang/Exception
    //   156	166	169	java/lang/Exception
    //   107	119	174	java/lang/Exception
  }
  
  public boolean bВВ0412ВВ0412ВВВ0412()
  {
    int i = bЮЮЮ042EЮ042EЮ042E042E;
    switch (i * (b042EЮЮ042EЮ042EЮ042E042E + i) % bЮ042EЮ042EЮ042EЮ042E042E)
    {
    default: 
      bЮЮЮ042EЮ042EЮ042E042E = b0412В0412В0412ВВВВ0412();
      b042E042EЮ042EЮ042EЮ042E042E = 65;
    }
    try
    {
      boolean bool = ((Boolean)bВВВ04120412ВВВВ0412(gguuuu.bк043Aккк043Aкк043A043A("?J\031KL<JDCLEOV7]UK:PJ\\P0RO[Y_Y8bVXc]]", '#', '±', '\003'), Boolean.valueOf(false))).booleanValue();
      return bool;
    }
    catch (Exception localException)
    {
      throw localException;
    }
  }
  
  /* Error */
  public boolean bВВВ041204120412ВВВ0412()
  {
    // Byte code:
    //   0: getstatic 119	kkkkkk/fbbfff:bЮЮЮ042EЮ042EЮ042E042E	I
    //   3: istore_1
    //   4: getstatic 121	kkkkkk/fbbfff:b042EЮЮ042EЮ042EЮ042E042E	I
    //   7: istore_2
    //   8: getstatic 119	kkkkkk/fbbfff:bЮЮЮ042EЮ042EЮ042E042E	I
    //   11: istore_3
    //   12: getstatic 129	kkkkkk/fbbfff:bЮ042EЮ042EЮ042EЮ042E042E	I
    //   15: istore 4
    //   17: getstatic 125	kkkkkk/fbbfff:b042E042EЮ042EЮ042EЮ042E042E	I
    //   20: istore 5
    //   22: iload_1
    //   23: iload_2
    //   24: iadd
    //   25: iload_3
    //   26: imul
    //   27: iload 4
    //   29: irem
    //   30: iload 5
    //   32: if_icmpeq +56 -> 88
    //   35: getstatic 119	kkkkkk/fbbfff:bЮЮЮ042EЮ042EЮ042E042E	I
    //   38: istore_1
    //   39: iload_1
    //   40: getstatic 121	kkkkkk/fbbfff:b042EЮЮ042EЮ042EЮ042E042E	I
    //   43: iload_1
    //   44: iadd
    //   45: imul
    //   46: getstatic 129	kkkkkk/fbbfff:bЮ042EЮ042EЮ042EЮ042E042E	I
    //   49: irem
    //   50: tableswitch	default:+18->68, 0:+27->77
    //   68: bipush 46
    //   70: putstatic 119	kkkkkk/fbbfff:bЮЮЮ042EЮ042EЮ042E042E	I
    //   73: iconst_2
    //   74: putstatic 125	kkkkkk/fbbfff:b042E042EЮ042EЮ042EЮ042E042E	I
    //   77: invokestatic 127	kkkkkk/fbbfff:b0412В0412В0412ВВВВ0412	()I
    //   80: putstatic 119	kkkkkk/fbbfff:bЮЮЮ042EЮ042EЮ042E042E	I
    //   83: bipush 42
    //   85: putstatic 125	kkkkkk/fbbfff:b042E042EЮ042EЮ042EЮ042E042E	I
    //   88: aload_0
    //   89: ldc -14
    //   91: bipush 104
    //   93: iconst_4
    //   94: invokestatic 29	kkkkkk/gguuuu:bккккк043Aкк043A043A	(Ljava/lang/String;CC)Ljava/lang/String;
    //   97: iconst_0
    //   98: invokestatic 135	java/lang/Boolean:valueOf	(Z)Ljava/lang/Boolean;
    //   101: invokevirtual 139	kkkkkk/fbbfff:bВВВ04120412ВВВВ0412	(Ljava/lang/String;Ljava/lang/Object;)Ljava/lang/Object;
    //   104: checkcast 131	java/lang/Boolean
    //   107: astore 7
    //   109: aload 7
    //   111: invokevirtual 142	java/lang/Boolean:booleanValue	()Z
    //   114: istore 6
    //   116: iload 6
    //   118: ireturn
    //   119: astore 7
    //   121: aload 7
    //   123: athrow
    //   124: astore 7
    //   126: aload 7
    //   128: athrow
    // Local variable table:
    //   start	length	slot	name	signature
    //   0	129	0	this	fbbfff
    //   3	43	1	i	int
    //   7	18	2	j	int
    //   11	16	3	k	int
    //   15	15	4	m	int
    //   20	13	5	n	int
    //   114	3	6	bool	boolean
    //   107	3	7	localBoolean	Boolean
    //   119	3	7	localException1	Exception
    //   124	3	7	localException2	Exception
    // Exception table:
    //   from	to	target	type
    //   8	22	119	java/lang/Exception
    //   77	88	119	java/lang/Exception
    //   88	109	119	java/lang/Exception
    //   0	8	124	java/lang/Exception
    //   109	116	124	java/lang/Exception
  }
  
  public abstract <T> T bВВВ04120412ВВВВ0412(String paramString, T paramT);
  
  /* Error */
  public boolean bВВВ0412В0412ВВВ0412()
  {
    // Byte code:
    //   0: getstatic 119	kkkkkk/fbbfff:bЮЮЮ042EЮ042EЮ042E042E	I
    //   3: istore_1
    //   4: getstatic 121	kkkkkk/fbbfff:b042EЮЮ042EЮ042EЮ042E042E	I
    //   7: istore_2
    //   8: getstatic 119	kkkkkk/fbbfff:bЮЮЮ042EЮ042EЮ042E042E	I
    //   11: istore_3
    //   12: getstatic 129	kkkkkk/fbbfff:bЮ042EЮ042EЮ042EЮ042E042E	I
    //   15: istore 4
    //   17: getstatic 125	kkkkkk/fbbfff:b042E042EЮ042EЮ042EЮ042E042E	I
    //   20: istore 5
    //   22: iload_1
    //   23: iload_2
    //   24: iadd
    //   25: iload_3
    //   26: imul
    //   27: iload 4
    //   29: irem
    //   30: iload 5
    //   32: if_icmpeq +14 -> 46
    //   35: invokestatic 127	kkkkkk/fbbfff:b0412В0412В0412ВВВВ0412	()I
    //   38: putstatic 119	kkkkkk/fbbfff:bЮЮЮ042EЮ042EЮ042E042E	I
    //   41: bipush 34
    //   43: putstatic 125	kkkkkk/fbbfff:b042E042EЮ042EЮ042EЮ042E042E	I
    //   46: getstatic 119	kkkkkk/fbbfff:bЮЮЮ042EЮ042EЮ042E042E	I
    //   49: istore_1
    //   50: iload_1
    //   51: getstatic 121	kkkkkk/fbbfff:b042EЮЮ042EЮ042EЮ042E042E	I
    //   54: iload_1
    //   55: iadd
    //   56: imul
    //   57: getstatic 129	kkkkkk/fbbfff:bЮ042EЮ042EЮ042EЮ042E042E	I
    //   60: irem
    //   61: tableswitch	default:+19->80, 0:+29->90
    //   80: bipush 65
    //   82: putstatic 119	kkkkkk/fbbfff:bЮЮЮ042EЮ042EЮ042E042E	I
    //   85: bipush 18
    //   87: putstatic 125	kkkkkk/fbbfff:b042E042EЮ042EЮ042EЮ042E042E	I
    //   90: ldc -11
    //   92: sipush 237
    //   95: iconst_4
    //   96: invokestatic 29	kkkkkk/gguuuu:bккккк043Aкк043A043A	(Ljava/lang/String;CC)Ljava/lang/String;
    //   99: astore 7
    //   101: aload_0
    //   102: aload 7
    //   104: iconst_1
    //   105: invokestatic 135	java/lang/Boolean:valueOf	(Z)Ljava/lang/Boolean;
    //   108: invokevirtual 139	kkkkkk/fbbfff:bВВВ04120412ВВВВ0412	(Ljava/lang/String;Ljava/lang/Object;)Ljava/lang/Object;
    //   111: checkcast 131	java/lang/Boolean
    //   114: invokevirtual 142	java/lang/Boolean:booleanValue	()Z
    //   117: istore 6
    //   119: iload 6
    //   121: ireturn
    //   122: astore 7
    //   124: aload 7
    //   126: athrow
    //   127: astore 7
    //   129: aload 7
    //   131: athrow
    // Local variable table:
    //   start	length	slot	name	signature
    //   0	132	0	this	fbbfff
    //   3	54	1	i	int
    //   7	18	2	j	int
    //   11	16	3	k	int
    //   15	15	4	m	int
    //   20	13	5	n	int
    //   117	3	6	bool	boolean
    //   99	4	7	str	String
    //   122	3	7	localException1	Exception
    //   127	3	7	localException2	Exception
    // Exception table:
    //   from	to	target	type
    //   0	22	122	java/lang/Exception
    //   90	101	122	java/lang/Exception
    //   101	119	122	java/lang/Exception
    //   35	46	127	java/lang/Exception
  }
  
  public boolean bВВВВ04120412ВВВ0412()
  {
    Object localObject = bВВВ04120412ВВВВ0412(gguuuu.bккккк043Aкк043A043A("IR' / H::C;9", '\020', '\003'), Boolean.valueOf(true));
    int i = b0412В0412В0412ВВВВ0412();
    int j = b042EЮЮ042EЮ042EЮ042E042E;
    int k = b0412В0412В0412ВВВВ0412();
    if ((bЮЮЮ042EЮ042EЮ042E042E + b042EЮЮ042EЮ042EЮ042E042E) * bЮЮЮ042EЮ042EЮ042E042E % bЮ042EЮ042EЮ042EЮ042E042E != b042E042EЮ042EЮ042EЮ042E042E)
    {
      bЮЮЮ042EЮ042EЮ042E042E = b0412В0412В0412ВВВВ0412();
      b042E042EЮ042EЮ042EЮ042E042E = 10;
    }
    if ((i + j) * k % bЮ042EЮ042EЮ042EЮ042E042E != b042E042EЮ042EЮ042EЮ042E042E)
    {
      bЮЮЮ042EЮ042EЮ042E042E = b0412В0412В0412ВВВВ0412();
      b042E042EЮ042EЮ042EЮ042E042E = 10;
    }
    return ((Boolean)localObject).booleanValue();
  }
  
  public boolean bВВВВВ0412ВВВ0412()
  {
    int i = bЮЮЮ042EЮ042EЮ042E042E;
    switch (i * (b042EЮЮ042EЮ042EЮ042E042E + i) % bЮ042EЮ042EЮ042EЮ042E042E)
    {
    default: 
      bЮЮЮ042EЮ042EЮ042E042E = b0412В0412В0412ВВВВ0412();
      b042E042EЮ042EЮ042EЮ042E042E = b0412В0412В0412ВВВВ0412();
    }
    Boolean localBoolean = (Boolean)bВВВ04120412ВВВВ0412(gguuuu.bккккк043Aкк043A043A("2;\b87%1)&-$,1\0204*\036\001%,\032''\037\026\036#r\033\r\r\026\016\f", '[', '\003'), Boolean.valueOf(false));
    i = bЮЮЮ042EЮ042EЮ042E042E;
    switch (i * (b042EЮЮ042EЮ042EЮ042E042E + i) % bЮ042EЮ042EЮ042EЮ042E042E)
    {
    default: 
      bЮЮЮ042EЮ042EЮ042E042E = b0412В0412В0412ВВВВ0412();
      b042E042EЮ042EЮ042EЮ042E042E = 78;
    }
    return localBoolean.booleanValue();
  }
}
