package kkkkkk;

import io.reactivex.Completable;
import io.reactivex.Single;
import javax.inject.Inject;

public class fbfbfb
{
  public static int b042E042EЮЮ042EЮ042E042EЮ = 1;
  public static int b042EЮЮЮ042EЮ042E042EЮ = 0;
  public static int bЮ042EЮЮ042EЮ042E042EЮ = 2;
  public static int bЮЮЮЮ042EЮ042E042EЮ = 6;
  private final fbbbfb b042E042E042E042EЮЮ042E042EЮ;
  
  @Inject
  public fbfbfb(fbbbfb paramFbbbfb)
  {
    this.b042E042E042E042EЮЮ042E042EЮ = paramFbbbfb;
  }
  
  public static int b041204120412В0412В0412В0412В()
  {
    return 2;
  }
  
  public static int b0412ВВ04120412В0412В0412В()
  {
    return 0;
  }
  
  public static int bВ0412В04120412В0412В0412В()
  {
    return 41;
  }
  
  public static int bВВВ04120412В0412В0412В()
  {
    return 1;
  }
  
  /* Error */
  public fbfffb b04120412В04120412В0412В0412В()
  {
    // Byte code:
    //   0: aload_0
    //   1: getfield 23	kkkkkk/fbfbfb:b042E042E042E042EЮЮ042E042EЮ	Lkkkkkk/fbbbfb;
    //   4: astore 6
    //   6: getstatic 36	kkkkkk/fbfbfb:bЮЮЮЮ042EЮ042E042EЮ	I
    //   9: istore_1
    //   10: getstatic 38	kkkkkk/fbfbfb:b042E042EЮЮ042EЮ042E042EЮ	I
    //   13: istore_2
    //   14: getstatic 36	kkkkkk/fbfbfb:bЮЮЮЮ042EЮ042E042EЮ	I
    //   17: istore_3
    //   18: getstatic 40	kkkkkk/fbfbfb:bЮ042EЮЮ042EЮ042E042EЮ	I
    //   21: istore 4
    //   23: invokestatic 42	kkkkkk/fbfbfb:b0412ВВ04120412В0412В0412В	()I
    //   26: istore 5
    //   28: iload_1
    //   29: iload_2
    //   30: iadd
    //   31: iload_3
    //   32: imul
    //   33: iload 4
    //   35: irem
    //   36: iload 5
    //   38: if_icmpeq +46 -> 84
    //   41: getstatic 36	kkkkkk/fbfbfb:bЮЮЮЮ042EЮ042E042EЮ	I
    //   44: getstatic 38	kkkkkk/fbfbfb:b042E042EЮЮ042EЮ042E042EЮ	I
    //   47: iadd
    //   48: getstatic 36	kkkkkk/fbfbfb:bЮЮЮЮ042EЮ042E042EЮ	I
    //   51: imul
    //   52: getstatic 40	kkkkkk/fbfbfb:bЮ042EЮЮ042EЮ042E042EЮ	I
    //   55: irem
    //   56: getstatic 44	kkkkkk/fbfbfb:b042EЮЮЮ042EЮ042E042EЮ	I
    //   59: if_icmpeq +13 -> 72
    //   62: bipush 31
    //   64: putstatic 36	kkkkkk/fbfbfb:bЮЮЮЮ042EЮ042E042EЮ	I
    //   67: bipush 97
    //   69: putstatic 44	kkkkkk/fbfbfb:b042EЮЮЮ042EЮ042E042EЮ	I
    //   72: invokestatic 46	kkkkkk/fbfbfb:bВ0412В04120412В0412В0412В	()I
    //   75: putstatic 36	kkkkkk/fbfbfb:bЮЮЮЮ042EЮ042E042EЮ	I
    //   78: invokestatic 46	kkkkkk/fbfbfb:bВ0412В04120412В0412В0412В	()I
    //   81: putstatic 44	kkkkkk/fbfbfb:b042EЮЮЮ042EЮ042E042EЮ	I
    //   84: aload 6
    //   86: invokevirtual 51	kkkkkk/fbbbfb:b0412041204120412ВВ0412В0412В	()Lkkkkkk/fbfffb;
    //   89: astore 6
    //   91: aload 6
    //   93: areturn
    //   94: astore 6
    //   96: aload 6
    //   98: athrow
    //   99: astore 6
    //   101: aload 6
    //   103: athrow
    //   104: astore 6
    //   106: aload 6
    //   108: athrow
    //   109: astore 6
    //   111: aload 6
    //   113: athrow
    // Local variable table:
    //   start	length	slot	name	signature
    //   0	114	0	this	fbfbfb
    //   9	22	1	i	int
    //   13	18	2	j	int
    //   17	16	3	k	int
    //   21	15	4	m	int
    //   26	13	5	n	int
    //   4	88	6	localObject	Object
    //   94	3	6	localException1	Exception
    //   99	3	6	localException2	Exception
    //   104	3	6	localException3	Exception
    //   109	3	6	localException4	Exception
    // Exception table:
    //   from	to	target	type
    //   84	91	94	java/lang/Exception
    //   6	28	99	java/lang/Exception
    //   72	78	99	java/lang/Exception
    //   96	99	99	java/lang/Exception
    //   0	6	104	java/lang/Exception
    //   78	84	109	java/lang/Exception
    //   106	109	109	java/lang/Exception
  }
  
  /* Error */
  public Single<fbfffb> b0412В041204120412В0412В0412В(boolean paramBoolean)
  {
    // Byte code:
    //   0: aload_0
    //   1: getfield 23	kkkkkk/fbfbfb:b042E042E042E042EЮЮ042E042EЮ	Lkkkkkk/fbbbfb;
    //   4: astore 7
    //   6: aload 7
    //   8: iload_1
    //   9: invokevirtual 56	kkkkkk/fbbbfb:bВВВВ0412В0412В0412В	(Z)Lio/reactivex/Single;
    //   12: astore 7
    //   14: getstatic 36	kkkkkk/fbfbfb:bЮЮЮЮ042EЮ042E042EЮ	I
    //   17: istore_2
    //   18: invokestatic 58	kkkkkk/fbfbfb:bВВВ04120412В0412В0412В	()I
    //   21: istore_3
    //   22: getstatic 36	kkkkkk/fbfbfb:bЮЮЮЮ042EЮ042E042EЮ	I
    //   25: istore 4
    //   27: invokestatic 60	kkkkkk/fbfbfb:b041204120412В0412В0412В0412В	()I
    //   30: istore 5
    //   32: getstatic 44	kkkkkk/fbfbfb:b042EЮЮЮ042EЮ042E042EЮ	I
    //   35: istore 6
    //   37: iload_2
    //   38: iload_3
    //   39: iadd
    //   40: iload 4
    //   42: imul
    //   43: iload 5
    //   45: irem
    //   46: iload 6
    //   48: if_icmpeq +45 -> 93
    //   51: getstatic 36	kkkkkk/fbfbfb:bЮЮЮЮ042EЮ042E042EЮ	I
    //   54: getstatic 38	kkkkkk/fbfbfb:b042E042EЮЮ042EЮ042E042EЮ	I
    //   57: iadd
    //   58: getstatic 36	kkkkkk/fbfbfb:bЮЮЮЮ042EЮ042E042EЮ	I
    //   61: imul
    //   62: getstatic 40	kkkkkk/fbfbfb:bЮ042EЮЮ042EЮ042E042EЮ	I
    //   65: irem
    //   66: getstatic 44	kkkkkk/fbfbfb:b042EЮЮЮ042EЮ042E042EЮ	I
    //   69: if_icmpeq +14 -> 83
    //   72: bipush 13
    //   74: putstatic 36	kkkkkk/fbfbfb:bЮЮЮЮ042EЮ042E042EЮ	I
    //   77: invokestatic 46	kkkkkk/fbfbfb:bВ0412В04120412В0412В0412В	()I
    //   80: putstatic 44	kkkkkk/fbfbfb:b042EЮЮЮ042EЮ042E042EЮ	I
    //   83: iconst_4
    //   84: putstatic 36	kkkkkk/fbfbfb:bЮЮЮЮ042EЮ042E042EЮ	I
    //   87: invokestatic 46	kkkkkk/fbfbfb:bВ0412В04120412В0412В0412В	()I
    //   90: putstatic 44	kkkkkk/fbfbfb:b042EЮЮЮ042EЮ042E042EЮ	I
    //   93: aload 7
    //   95: areturn
    //   96: astore 7
    //   98: aload 7
    //   100: athrow
    //   101: astore 7
    //   103: aload 7
    //   105: athrow
    //   106: astore 7
    //   108: aload 7
    //   110: athrow
    //   111: astore 7
    //   113: aload 7
    //   115: athrow
    // Local variable table:
    //   start	length	slot	name	signature
    //   0	116	0	this	fbfbfb
    //   0	116	1	paramBoolean	boolean
    //   17	23	2	i	int
    //   21	19	3	j	int
    //   25	18	4	k	int
    //   30	16	5	m	int
    //   35	14	6	n	int
    //   4	90	7	localObject	Object
    //   96	3	7	localException1	Exception
    //   101	3	7	localException2	Exception
    //   106	3	7	localException3	Exception
    //   111	3	7	localException4	Exception
    // Exception table:
    //   from	to	target	type
    //   0	6	96	java/lang/Exception
    //   14	37	101	java/lang/Exception
    //   98	101	101	java/lang/Exception
    //   6	14	106	java/lang/Exception
    //   83	93	111	java/lang/Exception
    //   108	111	111	java/lang/Exception
  }
  
  public Completable bВ04120412В0412В0412В0412В()
  {
    return this.b042E042E042E042EЮЮ042E042EЮ.b041204120412ВВВ0412В0412В();
  }
  
  public Single<fbfffb> bВВ041204120412В0412В0412В()
  {
    int i = bЮЮЮЮ042EЮ042E042EЮ;
    int j = b042E042EЮЮ042EЮ042E042EЮ;
    int k = bЮЮЮЮ042EЮ042E042EЮ;
    int m = bЮЮЮЮ042EЮ042E042EЮ;
    switch (m * (b042E042EЮЮ042EЮ042E042EЮ + m) % bЮ042EЮЮ042EЮ042E042EЮ)
    {
    default: 
      bЮЮЮЮ042EЮ042E042EЮ = 48;
      b042EЮЮЮ042EЮ042E042EЮ = bВ0412В04120412В0412В0412В();
    }
    if ((i + j) * k % bЮ042EЮЮ042EЮ042E042EЮ != b042EЮЮЮ042EЮ042E042EЮ)
    {
      switch (1)
      {
      case 0: 
      default: 
        for (;;)
        {
          switch (1)
          {
          }
        }
      }
      bЮЮЮЮ042EЮ042E042EЮ = 97;
      b042EЮЮЮ042EЮ042E042EЮ = 3;
    }
    try
    {
      Single localSingle = this.b042E042E042E042EЮЮ042E042EЮ.bВВВВ0412В0412В0412В(false);
      return localSingle;
    }
    catch (Exception localException)
    {
      throw localException;
    }
  }
}
