package kkkkkk;

import io.reactivex.disposables.CompositeDisposable;
import io.reactivex.disposables.Disposable;
import io.reactivex.functions.Action;

public abstract class gggggr<T extends grrrrg>
{
  public static int b04280428Ш0428Ш042804280428Ш = 2;
  public static int b0428ШШ0428Ш042804280428Ш = 0;
  public static int bШ0428Ш0428Ш042804280428Ш = 1;
  public static int bШШШ0428Ш042804280428Ш = 31;
  public T b042804280428ШШ042804280428Ш;
  private ffbfbb b0428Ш0428ШШ042804280428Ш;
  public final CompositeDisposable bШ04280428ШШ042804280428Ш = new CompositeDisposable();
  private boolean bШШ0428ШШ042804280428Ш;
  
  public gggggr() {}
  
  public static int b0418И04180418ИИИ0418ИИ()
  {
    return 2;
  }
  
  public static int bИ041804180418ИИИ0418ИИ()
  {
    return 23;
  }
  
  public static int bИИ04180418ИИИ0418ИИ()
  {
    return 0;
  }
  
  @ooiiio
  public Action b0418041804180418ИИИ0418ИИ()
  {
    if ((bШШШ0428Ш042804280428Ш + bШ0428Ш0428Ш042804280428Ш) * bШШШ0428Ш042804280428Ш % b04280428Ш0428Ш042804280428Ш != bИИ04180418ИИИ0418ИИ())
    {
      bШШШ0428Ш042804280428Ш = 27;
      int i = bШШШ0428Ш042804280428Ш;
      switch (i * (bШ0428Ш0428Ш042804280428Ш + i) % b04280428Ш0428Ш042804280428Ш)
      {
      default: 
        bШШШ0428Ш042804280428Ш = 28;
        b0428ШШ0428Ш042804280428Ш = 59;
      }
      b0428ШШ0428Ш042804280428Ш = 66;
    }
    Action local1 = new Action()
    {
      public static int b0428042804280428Ш042804280428Ш = 1;
      public static int b0428Ш04280428Ш042804280428Ш = 79;
      public static int bШ042804280428Ш042804280428Ш = 0;
      public static int bШШШШ0428042804280428Ш = 2;
      
      public static int b0418ИИ0418ИИИ0418ИИ()
      {
        return 2;
      }
      
      public static int bИИИ0418ИИИ0418ИИ()
      {
        return 66;
      }
      
      public void run()
        throws Exception
      {
        gggggr.bИ0418И0418ИИИ0418ИИ(gggggr.this).b041204120412ВВ0412ВВ0412В();
        if ((b0428Ш04280428Ш042804280428Ш + b0428042804280428Ш042804280428Ш) * b0428Ш04280428Ш042804280428Ш % bШШШШ0428042804280428Ш != bШ042804280428Ш042804280428Ш)
        {
          b0428Ш04280428Ш042804280428Ш = bИИИ0418ИИИ0418ИИ();
          bШ042804280428Ш042804280428Ш = bИИИ0418ИИИ0418ИИ();
          if ((b0428Ш04280428Ш042804280428Ш + b0428042804280428Ш042804280428Ш) * b0428Ш04280428Ш042804280428Ш % b0418ИИ0418ИИИ0418ИИ() != bШ042804280428Ш042804280428Ш)
          {
            b0428Ш04280428Ш042804280428Ш = bИИИ0418ИИИ0418ИИ();
            bШ042804280428Ш042804280428Ш = bИИИ0418ИИИ0418ИИ();
          }
        }
        switch (1)
        {
        case 0: 
        default: 
          for (;;)
          {
            switch (0)
            {
            case 1: 
            default: 
              for (;;)
              {
                switch (0)
                {
                }
              }
            }
            switch (0)
            {
            }
          }
        }
      }
    };
    switch (0)
    {
    case 1: 
    default: 
      for (;;)
      {
        switch (0)
        {
        }
      }
    }
    return local1;
  }
  
  public void b04180418И0418ИИИ0418ИИ(Disposable paramDisposable)
  {
    this.bШ04280428ШШ042804280428Ш.add(paramDisposable);
    if ((bШШШ0428Ш042804280428Ш + bШ0428Ш0428Ш042804280428Ш) * bШШШ0428Ш042804280428Ш % b04280428Ш0428Ш042804280428Ш != b0428ШШ0428Ш042804280428Ш)
    {
      bШШШ0428Ш042804280428Ш = 70;
      b0428ШШ0428Ш042804280428Ш = bИ041804180418ИИИ0418ИИ();
    }
  }
  
  /* Error */
  @android.support.annotation.CallSuper
  public void b0418И0418ИИИ0418ИИИ(T paramT)
  {
    // Byte code:
    //   0: getstatic 54	kkkkkk/gggggr:bШШШ0428Ш042804280428Ш	I
    //   3: istore_2
    //   4: iload_2
    //   5: getstatic 50	kkkkkk/gggggr:bШ0428Ш0428Ш042804280428Ш	I
    //   8: iload_2
    //   9: iadd
    //   10: imul
    //   11: getstatic 52	kkkkkk/gggggr:b04280428Ш0428Ш042804280428Ш	I
    //   14: irem
    //   15: tableswitch	default:+17->32, 0:+27->42
    //   32: bipush 38
    //   34: putstatic 54	kkkkkk/gggggr:bШШШ0428Ш042804280428Ш	I
    //   37: bipush 57
    //   39: putstatic 56	kkkkkk/gggggr:b0428ШШ0428Ш042804280428Ш	I
    //   42: getstatic 54	kkkkkk/gggggr:bШШШ0428Ш042804280428Ш	I
    //   45: istore_2
    //   46: iload_2
    //   47: getstatic 50	kkkkkk/gggggr:bШ0428Ш0428Ш042804280428Ш	I
    //   50: iload_2
    //   51: iadd
    //   52: imul
    //   53: invokestatic 79	kkkkkk/gggggr:b0418И04180418ИИИ0418ИИ	()I
    //   56: irem
    //   57: tableswitch	default:+19->76, 0:+31->88
    //   76: invokestatic 48	kkkkkk/gggggr:bИ041804180418ИИИ0418ИИ	()I
    //   79: putstatic 54	kkkkkk/gggggr:bШШШ0428Ш042804280428Ш	I
    //   82: invokestatic 48	kkkkkk/gggggr:bИ041804180418ИИИ0418ИИ	()I
    //   85: putstatic 56	kkkkkk/gggggr:b0428ШШ0428Ш042804280428Ш	I
    //   88: aload_0
    //   89: invokevirtual 83	java/lang/Object:getClass	()Ljava/lang/Class;
    //   92: astore_3
    //   93: aload_3
    //   94: invokevirtual 89	java/lang/Class:getSimpleName	()Ljava/lang/String;
    //   97: invokestatic 95	kkkkkk/ooooio:b0430а0430аа04300430ааа	(Ljava/lang/String;)V
    //   100: ldc 97
    //   102: bipush 60
    //   104: iconst_2
    //   105: invokestatic 103	kkkkkk/gguuuu:bккккк043Aкк043A043A	(Ljava/lang/String;CC)Ljava/lang/String;
    //   108: iconst_0
    //   109: anewarray 5	java/lang/Object
    //   112: invokestatic 107	kkkkkk/ooooio:bа04300430аа04300430ааа	(Ljava/lang/String;[Ljava/lang/Object;)V
    //   115: aload_0
    //   116: aload_1
    //   117: putfield 109	kkkkkk/gggggr:b042804280428ШШ042804280428Ш	Lkkkkkk/gggggr$grrrrg;
    //   120: aload_0
    //   121: iconst_1
    //   122: putfield 111	kkkkkk/gggggr:bШШ0428ШШ042804280428Ш	Z
    //   125: return
    //   126: astore_1
    //   127: aload_1
    //   128: athrow
    //   129: astore_1
    //   130: aload_1
    //   131: athrow
    // Local variable table:
    //   start	length	slot	name	signature
    //   0	132	0	this	gggggr
    //   0	132	1	paramT	T
    //   3	50	2	i	int
    //   92	2	3	localClass	Class
    // Exception table:
    //   from	to	target	type
    //   93	100	126	java/lang/Exception
    //   88	93	129	java/lang/Exception
    //   100	125	129	java/lang/Exception
  }
  
  /* Error */
  @android.support.annotation.CallSuper
  public void b0418ИИИ0418ИИ0418ИИ()
  {
    // Byte code:
    //   0: aload_0
    //   1: iconst_0
    //   2: putfield 111	kkkkkk/gggggr:bШШ0428ШШ042804280428Ш	Z
    //   5: aload_0
    //   6: invokevirtual 83	java/lang/Object:getClass	()Ljava/lang/Class;
    //   9: invokevirtual 89	java/lang/Class:getSimpleName	()Ljava/lang/String;
    //   12: invokestatic 95	kkkkkk/ooooio:b0430а0430аа04300430ааа	(Ljava/lang/String;)V
    //   15: iconst_1
    //   16: tableswitch	default:+24->40, 0:+-1->15, 1:+83->99
    //   40: getstatic 54	kkkkkk/gggggr:bШШШ0428Ш042804280428Ш	I
    //   43: getstatic 50	kkkkkk/gggggr:bШ0428Ш0428Ш042804280428Ш	I
    //   46: iadd
    //   47: getstatic 54	kkkkkk/gggggr:bШШШ0428Ш042804280428Ш	I
    //   50: imul
    //   51: invokestatic 79	kkkkkk/gggggr:b0418И04180418ИИИ0418ИИ	()I
    //   54: irem
    //   55: getstatic 56	kkkkkk/gggggr:b0428ШШ0428Ш042804280428Ш	I
    //   58: if_icmpeq +15 -> 73
    //   61: invokestatic 48	kkkkkk/gggggr:bИ041804180418ИИИ0418ИИ	()I
    //   64: putstatic 54	kkkkkk/gggggr:bШШШ0428Ш042804280428Ш	I
    //   67: invokestatic 48	kkkkkk/gggggr:bИ041804180418ИИИ0418ИИ	()I
    //   70: putstatic 56	kkkkkk/gggggr:b0428ШШ0428Ш042804280428Ш	I
    //   73: iconst_0
    //   74: tableswitch	default:+22->96, 0:+25->99, 1:+-59->15
    //   96: goto -56 -> 40
    //   99: getstatic 54	kkkkkk/gggggr:bШШШ0428Ш042804280428Ш	I
    //   102: istore_1
    //   103: getstatic 50	kkkkkk/gggggr:bШ0428Ш0428Ш042804280428Ш	I
    //   106: istore_2
    //   107: getstatic 54	kkkkkk/gggggr:bШШШ0428Ш042804280428Ш	I
    //   110: istore_3
    //   111: getstatic 52	kkkkkk/gggggr:b04280428Ш0428Ш042804280428Ш	I
    //   114: istore 4
    //   116: getstatic 56	kkkkkk/gggggr:b0428ШШ0428Ш042804280428Ш	I
    //   119: istore 5
    //   121: iload_1
    //   122: iload_2
    //   123: iadd
    //   124: iload_3
    //   125: imul
    //   126: iload 4
    //   128: irem
    //   129: iload 5
    //   131: if_icmpeq +14 -> 145
    //   134: invokestatic 48	kkkkkk/gggggr:bИ041804180418ИИИ0418ИИ	()I
    //   137: putstatic 54	kkkkkk/gggggr:bШШШ0428Ш042804280428Ш	I
    //   140: bipush 40
    //   142: putstatic 56	kkkkkk/gggggr:b0428ШШ0428Ш042804280428Ш	I
    //   145: ldc 116
    //   147: sipush 227
    //   150: sipush 143
    //   153: iconst_2
    //   154: invokestatic 120	kkkkkk/gguuuu:bк043Aккк043Aкк043A043A	(Ljava/lang/String;CCC)Ljava/lang/String;
    //   157: iconst_0
    //   158: anewarray 5	java/lang/Object
    //   161: invokestatic 107	kkkkkk/ooooio:bа04300430аа04300430ааа	(Ljava/lang/String;[Ljava/lang/Object;)V
    //   164: aload_0
    //   165: getfield 38	kkkkkk/gggggr:bШ04280428ШШ042804280428Ш	Lio/reactivex/disposables/CompositeDisposable;
    //   168: invokevirtual 123	io/reactivex/disposables/CompositeDisposable:clear	()V
    //   171: aload_0
    //   172: aconst_null
    //   173: putfield 109	kkkkkk/gggggr:b042804280428ШШ042804280428Ш	Lkkkkkk/gggggr$grrrrg;
    //   176: return
    //   177: astore 6
    //   179: aload 6
    //   181: athrow
    //   182: astore 6
    //   184: aload 6
    //   186: athrow
    // Local variable table:
    //   start	length	slot	name	signature
    //   0	187	0	this	gggggr
    //   102	22	1	i	int
    //   106	18	2	j	int
    //   110	16	3	k	int
    //   114	15	4	m	int
    //   119	13	5	n	int
    //   177	3	6	localException1	Exception
    //   182	3	6	localException2	Exception
    // Exception table:
    //   from	to	target	type
    //   0	15	177	java/lang/Exception
    //   99	121	177	java/lang/Exception
    //   145	176	177	java/lang/Exception
    //   134	145	182	java/lang/Exception
  }
  
  public void bИ0418ИИ0418ИИ0418ИИ(ffbfbb paramFfbfbb)
  {
    int i = 3;
    this.b0428Ш0428ШШ042804280428Ш = paramFfbfbb;
    try
    {
      for (;;)
      {
        i /= 0;
      }
      return;
    }
    catch (Exception paramFfbfbb)
    {
      bШШШ0428Ш042804280428Ш = 24;
    }
  }
  
  public boolean bИИИИ0418ИИ0418ИИ()
  {
    boolean bool = this.bШШ0428ШШ042804280428Ш;
    int i = bШШШ0428Ш042804280428Ш;
    switch (i * (bШ0428Ш0428Ш042804280428Ш + i) % b0418И04180418ИИИ0418ИИ())
    {
    default: 
      bШШШ0428Ш042804280428Ш = bИ041804180418ИИИ0418ИИ();
      b0428ШШ0428Ш042804280428Ш = 21;
    }
    if ((bШШШ0428Ш042804280428Ш + bШ0428Ш0428Ш042804280428Ш) * bШШШ0428Ш042804280428Ш % b04280428Ш0428Ш042804280428Ш != b0428ШШ0428Ш042804280428Ш)
    {
      bШШШ0428Ш042804280428Ш = 81;
      b0428ШШ0428Ш042804280428Ш = 21;
    }
    return bool;
  }
  
  public static abstract interface grrrrg {}
}
