package kkkkkk;

import java.util.ArrayList;

public class gguuuu
{
  public static int b04220422042204220422ТТ0422Т0422 = 0;
  private static ArrayList<gugguu> b04220422Т04220422ТТ0422Т0422;
  private static boolean b0422Т042204220422ТТ0422Т0422 = false;
  public static int b0422ТТТТ0422Т0422Т0422 = 2;
  public static int bТ0422042204220422ТТ0422Т0422 = 1;
  private static ArrayList<ggguuu> bТ0422Т04220422ТТ0422Т0422;
  private static int bТТ042204220422ТТ0422Т0422 = 0;
  public static int bТТТТТ0422Т0422Т0422 = 1;
  
  static
  {
    try
    {
      bТТ042204220422ТТ0422Т0422 = 54;
      if ((bТ0422042204220422ТТ0422Т0422 + bТТТТТ0422Т0422Т0422) * bТ0422042204220422ТТ0422Т0422 % b0422ТТТТ0422Т0422Т0422 != b04220422042204220422ТТ0422Т0422)
      {
        bТ0422042204220422ТТ0422Т0422 = 47;
        b04220422042204220422ТТ0422Т0422 = bкк043Aкк043Aкк043A043A();
        int i = bТ0422042204220422ТТ0422Т0422;
        switch (i * (bТТТТТ0422Т0422Т0422 + i) % b0422ТТТТ0422Т0422Т0422)
        {
        default: 
          bТ0422042204220422ТТ0422Т0422 = bкк043Aкк043Aкк043A043A();
          b04220422042204220422ТТ0422Т0422 = 14;
        }
      }
      b0422Т042204220422ТТ0422Т0422 = true;
      return;
    }
    catch (Exception localException)
    {
      throw localException;
    }
  }
  
  public gguuuu() {}
  
  public static int b043A043A043A043A043Aккк043A043A()
  {
    return 1;
  }
  
  public static String b043A043A043Aкк043Aкк043A043A(String paramString, char paramChar1, char paramChar2)
  {
    
    String str;
    try
    {
      str = ((ggguuu)bТ0422Т04220422ТТ0422Т0422.get(paramChar2)).b043Aккк043Aккк043A043A(paramString, new Character(paramChar1).charValue());
      paramChar2 = bТ0422042204220422ТТ0422Т0422;
      paramString = str;
      switch (paramChar2 * (bТТТТТ0422Т0422Т0422 + paramChar2) % b0422ТТТТ0422Т0422Т0422)
      {
      default: 
        bТ0422042204220422ТТ0422Т0422 = bкк043Aкк043Aкк043A043A();
        b04220422042204220422ТТ0422Т0422 = 42;
        paramString = str;
      }
      return paramString;
    }
    catch (Exception paramString)
    {
      str = new String("");
      paramString = str;
      switch (0)
      {
      }
    }
    for (;;)
    {
      paramString = str;
      switch (0)
      {
      }
    }
  }
  
  public static int b043A043Aккк043Aкк043A043A()
  {
    return 2;
  }
  
  /* Error */
  public static String b043Aк043Aкк043Aкк043A043A(String paramString, char paramChar1, char paramChar2, char paramChar3)
  {
    // Byte code:
    //   0: invokestatic 86	kkkkkk/gguuuu:b043Aкккк043Aкк043A043A	()V
    //   3: getstatic 119	kkkkkk/gguuuu:b04220422Т04220422ТТ0422Т0422	Ljava/util/ArrayList;
    //   6: iload_3
    //   7: invokevirtual 94	java/util/ArrayList:get	(I)Ljava/lang/Object;
    //   10: checkcast 15	kkkkkk/gguuuu$gugguu
    //   13: astore 8
    //   15: new 96	java/lang/Character
    //   18: dup
    //   19: iload_1
    //   20: invokespecial 99	java/lang/Character:<init>	(C)V
    //   23: invokevirtual 103	java/lang/Character:charValue	()C
    //   26: istore_1
    //   27: new 96	java/lang/Character
    //   30: dup
    //   31: iload_2
    //   32: invokespecial 99	java/lang/Character:<init>	(C)V
    //   35: astore 9
    //   37: invokestatic 74	kkkkkk/gguuuu:bкк043Aкк043Aкк043A043A	()I
    //   40: istore_3
    //   41: invokestatic 121	kkkkkk/gguuuu:b043A043A043A043A043Aккк043A043A	()I
    //   44: istore 4
    //   46: invokestatic 74	kkkkkk/gguuuu:bкк043Aкк043Aкк043A043A	()I
    //   49: istore 5
    //   51: getstatic 68	kkkkkk/gguuuu:b0422ТТТТ0422Т0422Т0422	I
    //   54: istore 6
    //   56: getstatic 70	kkkkkk/gguuuu:b04220422042204220422ТТ0422Т0422	I
    //   59: istore 7
    //   61: iload_3
    //   62: iload 4
    //   64: iadd
    //   65: iload 5
    //   67: imul
    //   68: iload 6
    //   70: irem
    //   71: iload 7
    //   73: if_icmpeq +14 -> 87
    //   76: invokestatic 74	kkkkkk/gguuuu:bкк043Aкк043Aкк043A043A	()I
    //   79: putstatic 64	kkkkkk/gguuuu:bТ0422042204220422ТТ0422Т0422	I
    //   82: bipush 70
    //   84: putstatic 70	kkkkkk/gguuuu:b04220422042204220422ТТ0422Т0422	I
    //   87: aload 8
    //   89: aload_0
    //   90: iload_1
    //   91: aload 9
    //   93: invokevirtual 103	java/lang/Character:charValue	()C
    //   96: invokevirtual 124	kkkkkk/gguuuu$gugguu:b043Aк043Aк043Aккк043A043A	(Ljava/lang/String;CC)Ljava/lang/String;
    //   99: astore_0
    //   100: aload_0
    //   101: areturn
    //   102: astore_0
    //   103: new 109	java/lang/String
    //   106: dup
    //   107: ldc 111
    //   109: invokespecial 114	java/lang/String:<init>	(Ljava/lang/String;)V
    //   112: astore_0
    //   113: aload_0
    //   114: areturn
    //   115: astore_0
    //   116: aload_0
    //   117: athrow
    //   118: astore_0
    //   119: aload_0
    //   120: athrow
    // Local variable table:
    //   start	length	slot	name	signature
    //   0	121	0	paramString	String
    //   0	121	1	paramChar1	char
    //   0	121	2	paramChar2	char
    //   0	121	3	paramChar3	char
    //   44	21	4	c	char
    //   49	19	5	i	int
    //   54	17	6	j	int
    //   59	15	7	k	int
    //   13	75	8	localGugguu	gugguu
    //   35	57	9	localCharacter	Character
    // Exception table:
    //   from	to	target	type
    //   3	37	102	java/lang/Exception
    //   87	100	102	java/lang/Exception
    //   0	3	115	java/lang/Exception
    //   37	46	115	java/lang/Exception
    //   56	61	115	java/lang/Exception
    //   103	113	115	java/lang/Exception
    //   46	56	118	java/lang/Exception
    //   76	87	118	java/lang/Exception
  }
  
  /* Error */
  private static void b043Aкккк043Aкк043A043A()
  {
    // Byte code:
    //   0: ldc 2
    //   2: monitorenter
    //   3: getstatic 76	kkkkkk/gguuuu:b0422Т042204220422ТТ0422Т0422	Z
    //   6: ifeq +287 -> 293
    //   9: iconst_0
    //   10: putstatic 76	kkkkkk/gguuuu:b0422Т042204220422ТТ0422Т0422	Z
    //   13: new 90	java/util/ArrayList
    //   16: dup
    //   17: bipush 7
    //   19: invokespecial 127	java/util/ArrayList:<init>	(I)V
    //   22: putstatic 88	kkkkkk/gguuuu:bТ0422Т04220422ТТ0422Т0422	Ljava/util/ArrayList;
    //   25: new 90	java/util/ArrayList
    //   28: dup
    //   29: iconst_4
    //   30: invokespecial 127	java/util/ArrayList:<init>	(I)V
    //   33: astore_1
    //   34: getstatic 64	kkkkkk/gguuuu:bТ0422042204220422ТТ0422Т0422	I
    //   37: getstatic 66	kkkkkk/gguuuu:bТТТТТ0422Т0422Т0422	I
    //   40: iadd
    //   41: getstatic 64	kkkkkk/gguuuu:bТ0422042204220422ТТ0422Т0422	I
    //   44: imul
    //   45: getstatic 68	kkkkkk/gguuuu:b0422ТТТТ0422Т0422Т0422	I
    //   48: irem
    //   49: getstatic 70	kkkkkk/gguuuu:b04220422042204220422ТТ0422Т0422	I
    //   52: if_icmpeq +14 -> 66
    //   55: bipush 51
    //   57: putstatic 64	kkkkkk/gguuuu:bТ0422042204220422ТТ0422Т0422	I
    //   60: invokestatic 74	kkkkkk/gguuuu:bкк043Aкк043Aкк043A043A	()I
    //   63: putstatic 70	kkkkkk/gguuuu:b04220422042204220422ТТ0422Т0422	I
    //   66: aload_1
    //   67: putstatic 119	kkkkkk/gguuuu:b04220422Т04220422ТТ0422Т0422	Ljava/util/ArrayList;
    //   70: getstatic 88	kkkkkk/gguuuu:bТ0422Т04220422ТТ0422Т0422	Ljava/util/ArrayList;
    //   73: astore_1
    //   74: new 18	kkkkkk/gguuuu$guguuu
    //   77: dup
    //   78: invokespecial 128	kkkkkk/gguuuu$guguuu:<init>	()V
    //   81: astore_2
    //   82: invokestatic 74	kkkkkk/gguuuu:bкк043Aкк043Aкк043A043A	()I
    //   85: istore_0
    //   86: iload_0
    //   87: invokestatic 121	kkkkkk/gguuuu:b043A043A043A043A043Aккк043A043A	()I
    //   90: iadd
    //   91: invokestatic 74	kkkkkk/gguuuu:bкк043Aкк043Aкк043A043A	()I
    //   94: imul
    //   95: invokestatic 130	kkkkkk/gguuuu:b043A043Aккк043Aкк043A043A	()I
    //   98: irem
    //   99: getstatic 70	kkkkkk/gguuuu:b04220422042204220422ТТ0422Т0422	I
    //   102: if_icmpeq +15 -> 117
    //   105: invokestatic 74	kkkkkk/gguuuu:bкк043Aкк043Aкк043A043A	()I
    //   108: putstatic 64	kkkkkk/gguuuu:bТ0422042204220422ТТ0422Т0422	I
    //   111: invokestatic 74	kkkkkk/gguuuu:bкк043Aкк043Aкк043A043A	()I
    //   114: putstatic 70	kkkkkk/gguuuu:b04220422042204220422ТТ0422Т0422	I
    //   117: aload_1
    //   118: aload_2
    //   119: invokevirtual 134	java/util/ArrayList:add	(Ljava/lang/Object;)Z
    //   122: pop
    //   123: getstatic 88	kkkkkk/gguuuu:bТ0422Т04220422ТТ0422Т0422	Ljava/util/ArrayList;
    //   126: new 12	kkkkkk/gguuuu$gguguu
    //   129: dup
    //   130: invokespecial 135	kkkkkk/gguuuu$gguguu:<init>	()V
    //   133: invokevirtual 134	java/util/ArrayList:add	(Ljava/lang/Object;)Z
    //   136: pop
    //   137: getstatic 88	kkkkkk/gguuuu:bТ0422Т04220422ТТ0422Т0422	Ljava/util/ArrayList;
    //   140: new 21	kkkkkk/gguuuu$guuguu
    //   143: dup
    //   144: invokespecial 136	kkkkkk/gguuuu$guuguu:<init>	()V
    //   147: invokevirtual 134	java/util/ArrayList:add	(Ljava/lang/Object;)Z
    //   150: pop
    //   151: getstatic 88	kkkkkk/gguuuu:bТ0422Т04220422ТТ0422Т0422	Ljava/util/ArrayList;
    //   154: new 6	kkkkkk/gguuuu$gggguu
    //   157: dup
    //   158: invokespecial 137	kkkkkk/gguuuu$gggguu:<init>	()V
    //   161: invokevirtual 134	java/util/ArrayList:add	(Ljava/lang/Object;)Z
    //   164: pop
    //   165: getstatic 88	kkkkkk/gguuuu:bТ0422Т04220422ТТ0422Т0422	Ljava/util/ArrayList;
    //   168: new 36	kkkkkk/gguuuu$uuguuu
    //   171: dup
    //   172: invokespecial 138	kkkkkk/gguuuu$uuguuu:<init>	()V
    //   175: invokevirtual 134	java/util/ArrayList:add	(Ljava/lang/Object;)Z
    //   178: pop
    //   179: getstatic 88	kkkkkk/gguuuu:bТ0422Т04220422ТТ0422Т0422	Ljava/util/ArrayList;
    //   182: astore_1
    //   183: new 30	kkkkkk/gguuuu$uguguu
    //   186: dup
    //   187: invokespecial 139	kkkkkk/gguuuu$uguguu:<init>	()V
    //   190: astore_2
    //   191: aload_1
    //   192: aload_2
    //   193: invokevirtual 134	java/util/ArrayList:add	(Ljava/lang/Object;)Z
    //   196: pop
    //   197: getstatic 119	kkkkkk/gguuuu:b04220422Т04220422ТТ0422Т0422	Ljava/util/ArrayList;
    //   200: new 39	kkkkkk/gguuuu$uuuguu
    //   203: dup
    //   204: invokespecial 140	kkkkkk/gguuuu$uuuguu:<init>	()V
    //   207: invokevirtual 134	java/util/ArrayList:add	(Ljava/lang/Object;)Z
    //   210: pop
    //   211: getstatic 119	kkkkkk/gguuuu:b04220422Т04220422ТТ0422Т0422	Ljava/util/ArrayList;
    //   214: astore_1
    //   215: aload_1
    //   216: new 24	kkkkkk/gguuuu$uggguu
    //   219: dup
    //   220: invokespecial 141	kkkkkk/gguuuu$uggguu:<init>	()V
    //   223: invokevirtual 134	java/util/ArrayList:add	(Ljava/lang/Object;)Z
    //   226: pop
    //   227: getstatic 119	kkkkkk/gguuuu:b04220422Т04220422ТТ0422Т0422	Ljava/util/ArrayList;
    //   230: new 27	kkkkkk/gguuuu$ugguuu
    //   233: dup
    //   234: invokespecial 142	kkkkkk/gguuuu$ugguuu:<init>	()V
    //   237: invokevirtual 134	java/util/ArrayList:add	(Ljava/lang/Object;)Z
    //   240: pop
    //   241: getstatic 119	kkkkkk/gguuuu:b04220422Т04220422ТТ0422Т0422	Ljava/util/ArrayList;
    //   244: new 33	kkkkkk/gguuuu$uugguu
    //   247: dup
    //   248: invokespecial 143	kkkkkk/gguuuu$uugguu:<init>	()V
    //   251: invokevirtual 134	java/util/ArrayList:add	(Ljava/lang/Object;)Z
    //   254: pop
    //   255: getstatic 88	kkkkkk/gguuuu:bТ0422Т04220422ТТ0422Т0422	Ljava/util/ArrayList;
    //   258: astore_1
    //   259: new 145	java/util/Random
    //   262: dup
    //   263: getstatic 62	kkkkkk/gguuuu:bТТ042204220422ТТ0422Т0422	I
    //   266: i2l
    //   267: invokespecial 148	java/util/Random:<init>	(J)V
    //   270: astore_2
    //   271: aload_1
    //   272: aload_2
    //   273: invokestatic 154	java/util/Collections:shuffle	(Ljava/util/List;Ljava/util/Random;)V
    //   276: getstatic 119	kkkkkk/gguuuu:b04220422Т04220422ТТ0422Т0422	Ljava/util/ArrayList;
    //   279: new 145	java/util/Random
    //   282: dup
    //   283: getstatic 62	kkkkkk/gguuuu:bТТ042204220422ТТ0422Т0422	I
    //   286: i2l
    //   287: invokespecial 148	java/util/Random:<init>	(J)V
    //   290: invokestatic 154	java/util/Collections:shuffle	(Ljava/util/List;Ljava/util/Random;)V
    //   293: ldc 2
    //   295: monitorexit
    //   296: return
    //   297: astore_1
    //   298: aload_1
    //   299: athrow
    //   300: astore_1
    //   301: aload_1
    //   302: athrow
    //   303: astore_1
    //   304: ldc 2
    //   306: monitorexit
    //   307: aload_1
    //   308: athrow
    //   309: astore_1
    //   310: aload_1
    //   311: athrow
    //   312: astore_1
    //   313: aload_1
    //   314: athrow
    // Local variable table:
    //   start	length	slot	name	signature
    //   85	6	0	i	int
    //   33	239	1	localArrayList	ArrayList
    //   297	2	1	localException1	Exception
    //   300	2	1	localException2	Exception
    //   303	5	1	localObject1	Object
    //   309	2	1	localException3	Exception
    //   312	2	1	localException4	Exception
    //   81	192	2	localObject2	Object
    // Exception table:
    //   from	to	target	type
    //   3	34	297	java/lang/Exception
    //   66	82	297	java/lang/Exception
    //   117	137	297	java/lang/Exception
    //   191	211	297	java/lang/Exception
    //   215	271	297	java/lang/Exception
    //   82	86	300	java/lang/Exception
    //   298	300	300	java/lang/Exception
    //   3	34	303	finally
    //   34	66	303	finally
    //   66	82	303	finally
    //   82	86	303	finally
    //   86	117	303	finally
    //   117	137	303	finally
    //   137	191	303	finally
    //   191	211	303	finally
    //   211	215	303	finally
    //   215	271	303	finally
    //   271	293	303	finally
    //   298	300	303	finally
    //   301	303	303	finally
    //   310	312	303	finally
    //   313	315	303	finally
    //   137	191	309	java/lang/Exception
    //   211	215	309	java/lang/Exception
    //   271	293	309	java/lang/Exception
    //   86	117	312	java/lang/Exception
    //   310	312	312	java/lang/Exception
  }
  
  public static int bк043A043A043A043Aккк043A043A()
  {
    return 0;
  }
  
  public static void bк043A043Aкк043Aкк043A043A(int paramInt)
  {
    if ((bТ0422042204220422ТТ0422Т0422 + bТТТТТ0422Т0422Т0422) * bТ0422042204220422ТТ0422Т0422 % b0422ТТТТ0422Т0422Т0422 != b04220422042204220422ТТ0422Т0422)
    {
      bТ0422042204220422ТТ0422Т0422 = 44;
      b04220422042204220422ТТ0422Т0422 = 72;
    }
    int i;
    if (paramInt <= 128)
    {
      i = bТ0422042204220422ТТ0422Т0422;
      switch (i * (bТТТТТ0422Т0422Т0422 + i) % b0422ТТТТ0422Т0422Т0422)
      {
      default: 
        bТ0422042204220422ТТ0422Т0422 = bкк043Aкк043Aкк043A043A();
        b04220422042204220422ТТ0422Т0422 = bкк043Aкк043Aкк043A043A();
      }
      i = paramInt;
      if (paramInt >= 0) {}
    }
    else
    {
      i = 0;
    }
    try
    {
      bТТ042204220422ТТ0422Т0422 = i;
      return;
    }
    catch (Exception localException)
    {
      throw localException;
    }
  }
  
  public static String bк043Aккк043Aкк043A043A(String paramString, char paramChar1, char paramChar2, char paramChar3)
  {
    int i = bТ0422042204220422ТТ0422Т0422;
    int j = bТТТТТ0422Т0422Т0422;
    int k = bТ0422042204220422ТТ0422Т0422;
    switch (0)
    {
    case 1: 
    default: 
      for (;;)
      {
        switch (0)
        {
        }
      }
    }
    if ((i + j) * k % b0422ТТТТ0422Т0422Т0422 != b04220422042204220422ТТ0422Т0422)
    {
      bТ0422042204220422ТТ0422Т0422 = bкк043Aкк043Aкк043A043A();
      b04220422042204220422ТТ0422Т0422 = 77;
      if ((bТ0422042204220422ТТ0422Т0422 + bТТТТТ0422Т0422Т0422) * bТ0422042204220422ТТ0422Т0422 % b0422ТТТТ0422Т0422Т0422 != bк043A043A043A043Aккк043A043A())
      {
        bТ0422042204220422ТТ0422Т0422 = bкк043Aкк043Aкк043A043A();
        b04220422042204220422ТТ0422Т0422 = 28;
      }
    }
    try
    {
      paramString = b043Aк043Aкк043Aкк043A043A(paramString, paramChar1, paramChar2, paramChar3).intern();
      return paramString;
    }
    catch (Exception paramString)
    {
      throw paramString;
    }
  }
  
  public static int bкк043Aкк043Aкк043A043A()
  {
    return 8;
  }
  
  /* Error */
  public static String bккккк043Aкк043A043A(String paramString, char paramChar1, char paramChar2)
  {
    // Byte code:
    //   0: invokestatic 74	kkkkkk/gguuuu:bкк043Aкк043Aкк043A043A	()I
    //   3: getstatic 66	kkkkkk/gguuuu:bТТТТТ0422Т0422Т0422	I
    //   6: iadd
    //   7: invokestatic 74	kkkkkk/gguuuu:bкк043Aкк043Aкк043A043A	()I
    //   10: imul
    //   11: getstatic 68	kkkkkk/gguuuu:b0422ТТТТ0422Т0422Т0422	I
    //   14: irem
    //   15: getstatic 70	kkkkkk/gguuuu:b04220422042204220422ТТ0422Т0422	I
    //   18: if_icmpeq +14 -> 32
    //   21: bipush 26
    //   23: putstatic 64	kkkkkk/gguuuu:bТ0422042204220422ТТ0422Т0422	I
    //   26: invokestatic 74	kkkkkk/gguuuu:bкк043Aкк043Aкк043A043A	()I
    //   29: putstatic 70	kkkkkk/gguuuu:b04220422042204220422ТТ0422Т0422	I
    //   32: getstatic 64	kkkkkk/gguuuu:bТ0422042204220422ТТ0422Т0422	I
    //   35: getstatic 66	kkkkkk/gguuuu:bТТТТТ0422Т0422Т0422	I
    //   38: iadd
    //   39: getstatic 64	kkkkkk/gguuuu:bТ0422042204220422ТТ0422Т0422	I
    //   42: imul
    //   43: getstatic 68	kkkkkk/gguuuu:b0422ТТТТ0422Т0422Т0422	I
    //   46: irem
    //   47: getstatic 70	kkkkkk/gguuuu:b04220422042204220422ТТ0422Т0422	I
    //   50: if_icmpeq +17 -> 67
    //   53: invokestatic 74	kkkkkk/gguuuu:bкк043Aкк043Aкк043A043A	()I
    //   56: istore_3
    //   57: iload_3
    //   58: putstatic 64	kkkkkk/gguuuu:bТ0422042204220422ТТ0422Т0422	I
    //   61: invokestatic 74	kkkkkk/gguuuu:bкк043Aкк043Aкк043A043A	()I
    //   64: putstatic 70	kkkkkk/gguuuu:b04220422042204220422ТТ0422Т0422	I
    //   67: aload_0
    //   68: iload_1
    //   69: iload_2
    //   70: invokestatic 168	kkkkkk/gguuuu:b043A043A043Aкк043Aкк043A043A	(Ljava/lang/String;CC)Ljava/lang/String;
    //   73: astore_0
    //   74: iconst_1
    //   75: tableswitch	default:+21->96, 0:+-1->74, 1:+48->123
    //   96: iconst_0
    //   97: tableswitch	default:+23->120, 0:+26->123, 1:+-23->74
    //   120: goto -24 -> 96
    //   123: aload_0
    //   124: invokevirtual 165	java/lang/String:intern	()Ljava/lang/String;
    //   127: astore_0
    //   128: aload_0
    //   129: areturn
    //   130: astore_0
    //   131: aload_0
    //   132: athrow
    //   133: astore_0
    //   134: aload_0
    //   135: athrow
    // Local variable table:
    //   start	length	slot	name	signature
    //   0	136	0	paramString	String
    //   0	136	1	paramChar1	char
    //   0	136	2	paramChar2	char
    //   56	2	3	i	int
    // Exception table:
    //   from	to	target	type
    //   32	57	130	java/lang/Exception
    //   67	74	130	java/lang/Exception
    //   57	67	133	java/lang/Exception
    //   123	128	133	java/lang/Exception
  }
  
  public static class gggguu
    extends gguuuu.ggguuu
  {
    public static int b0422Т0422ТТТ04220422Т0422 = 1;
    public static int bТ04220422ТТТ04220422Т0422 = 2;
    public static int bТТ0422ТТТ04220422Т0422 = 19;
    
    public gggguu() {}
    
    public static int b043Aк043A043A043Aккк043A043A()
    {
      return 5;
    }
    
    public String b043Aккк043Aккк043A043A(String paramString, char paramChar)
    {
      for (;;)
      {
        try
        {
          arrayOfInt = new int[paramString.length()];
          paramString = new uguuuu(paramString);
          c = '\000';
          boolean bool = paramString.bкк043A043Aкккк043A043A();
          i = bТТ0422ТТТ04220422Т0422;
          switch (i * (b0422Т0422ТТТ04220422Т0422 + i) % bТ04220422ТТТ04220422Т0422)
          {
          default: 
            bТТ0422ТТТ04220422Т0422 = 42;
            b0422Т0422ТТТ04220422Т0422 = b043Aк043A043A043Aккк043A043A();
          }
          if (bool)
          {
            i = paramString.bк043A043A043Aкккк043A043A();
            localUguugu = uguugu.b043A043A043A043Aк043Aкк043A043A(i);
            i = localUguugu.b043Aккккккк043A043A(i);
            int j = bТТ0422ТТТ04220422Т0422;
            switch (j * (b0422Т0422ТТТ04220422Т0422 + j) % bТ04220422ТТТ04220422Т0422)
            {
            default: 
              bТТ0422ТТТ04220422Т0422 = 22;
              b0422Т0422ТТТ04220422Т0422 = 47;
            }
          }
        }
        catch (Exception paramString)
        {
          int[] arrayOfInt;
          char c;
          int i;
          uguugu localUguugu;
          switch (1)
          {
          case 0: 
          default: 
            switch (0)
            {
            }
            break;
          }
          throw paramString;
        }
        try
        {
          i = localUguugu.bк043A043Aккккк043A043A(i + (paramChar + c));
          arrayOfInt[c] = i;
          c += '\001';
        }
        catch (Exception paramString)
        {
          throw paramString;
        }
      }
      paramString = new String(arrayOfInt, 0, c);
      return paramString;
    }
  }
  
  public static abstract class ggguuu
  {
    public ggguuu() {}
    
    public abstract String b043Aккк043Aккк043A043A(String paramString, char paramChar);
  }
  
  public static class gguguu
    extends gguuuu.ggguuu
  {
    public static int b04220422Т042204220422Т0422Т0422 = 2;
    public static int b0422ТТ042204220422Т0422Т0422 = 13;
    public static int bТ0422Т042204220422Т0422Т0422 = 1;
    public static int bТТ0422042204220422Т0422Т0422;
    
    public gguguu() {}
    
    public static int bк043Aк043A043Aккк043A043A()
    {
      return 73;
    }
    
    public String b043Aккк043Aккк043A043A(String paramString, char paramChar)
    {
      int i = 0;
      for (;;)
      {
        try
        {
          arrayOfInt = new int[paramString.length()];
          paramString = new uguuuu(paramString);
          if (paramString.bкк043A043Aкккк043A043A())
          {
            j = paramString.bк043A043A043Aкккк043A043A();
            localUguugu = uguugu.b043A043A043A043Aк043Aкк043A043A(j);
            int k = b0422ТТ042204220422Т0422Т0422;
            switch (k * (bТ0422Т042204220422Т0422Т0422 + k) % b04220422Т042204220422Т0422Т0422)
            {
            default: 
              b0422ТТ042204220422Т0422Т0422 = bк043Aк043A043Aккк043A043A();
              bТ0422Т042204220422Т0422Т0422 = 12;
            }
            j = localUguugu.b043Aккккккк043A043A(j);
            if ((b0422ТТ042204220422Т0422Т0422 + bТ0422Т042204220422Т0422Т0422) * b0422ТТ042204220422Т0422Т0422 % b04220422Т042204220422Т0422Т0422 != bТТ0422042204220422Т0422Т0422)
            {
              b0422ТТ042204220422Т0422Т0422 = bк043Aк043A043Aккк043A043A();
              bТТ0422042204220422Т0422Т0422 = bк043Aк043A043Aккк043A043A();
            }
          }
        }
        catch (Exception paramString)
        {
          int[] arrayOfInt;
          int j;
          uguugu localUguugu;
          throw paramString;
        }
        try
        {
          arrayOfInt[i] = localUguugu.bк043A043Aккккк043A043A(j - (paramChar + paramChar + i));
          i += 1;
        }
        catch (Exception paramString)
        {
          throw paramString;
        }
      }
      paramString = new String(arrayOfInt, 0, i);
      return paramString;
    }
  }
  
  public static abstract class gugguu
  {
    public gugguu() {}
    
    public abstract String b043Aк043Aк043Aккк043A043A(String paramString, char paramChar1, char paramChar2);
  }
  
  public static class guguuu
    extends gguuuu.ggguuu
  {
    public static int b042204220422ТТ0422Т0422Т0422 = 2;
    public static int bТ04220422ТТ0422Т0422Т0422 = 62;
    public static int bТТТ0422Т0422Т0422Т0422;
    
    public guguuu() {}
    
    public static int b043A043Aкк043Aккк043A043A()
    {
      return 49;
    }
    
    public static int bк043Aкк043Aккк043A043A()
    {
      return 1;
    }
    
    public String b043Aккк043Aккк043A043A(String paramString, char paramChar)
    {
      int[] arrayOfInt = new int[paramString.length()];
      char c = bТ04220422ТТ0422Т0422Т0422;
      switch (c * (bк043Aкк043Aккк043A043A() + c) % b042204220422ТТ0422Т0422Т0422)
      {
      default: 
        bТ04220422ТТ0422Т0422Т0422 = 3;
        b042204220422ТТ0422Т0422Т0422 = b043A043Aкк043Aккк043A043A();
        if ((bТ04220422ТТ0422Т0422Т0422 + bк043Aкк043Aккк043A043A()) * bТ04220422ТТ0422Т0422Т0422 % b042204220422ТТ0422Т0422Т0422 != bТТТ0422Т0422Т0422Т0422)
        {
          bТ04220422ТТ0422Т0422Т0422 = b043A043Aкк043Aккк043A043A();
          bТТТ0422Т0422Т0422Т0422 = 5;
        }
        break;
      }
      paramString = new uguuuu(paramString);
      c = '\000';
      while (paramString.bкк043A043Aкккк043A043A())
      {
        int i = paramString.bк043A043A043Aкккк043A043A();
        uguugu localUguugu = uguugu.b043A043A043A043Aк043Aкк043A043A(i);
        arrayOfInt[c] = localUguugu.bк043A043Aккккк043A043A(localUguugu.b043Aккккккк043A043A(i) - (paramChar + c));
        c += '\001';
      }
      paramString = new String(arrayOfInt, 0, c);
      switch (0)
      {
      case 1: 
      default: 
        for (;;)
        {
          switch (1)
          {
          }
        }
      }
      return paramString;
    }
  }
  
  public static class guuguu
    extends gguuuu.ggguuu
  {
    public static int b04220422ТТ04220422Т0422Т0422 = 1;
    public static int b0422ТТТ04220422Т0422Т0422 = 69;
    public static int bТ0422ТТ04220422Т0422Т0422 = 0;
    public static int bТТ0422Т04220422Т0422Т0422 = 2;
    
    public guuguu() {}
    
    public static int bккк043A043Aккк043A043A()
    {
      return 28;
    }
    
    public String b043Aккк043Aккк043A043A(String paramString, char paramChar)
    {
      switch (0)
      {
      case 1: 
      default: 
        for (;;)
        {
          switch (1)
          {
          }
        }
      }
      int[] arrayOfInt = new int[paramString.length()];
      paramString = new uguuuu(paramString);
      int i = 0;
      for (;;)
      {
        boolean bool = paramString.bкк043A043Aкккк043A043A();
        switch (0)
        {
        case 1: 
        default: 
          for (;;)
          {
            switch (0)
            {
            }
          }
        }
        if (!bool) {
          break;
        }
        int j = paramString.bк043A043A043Aкккк043A043A();
        int k = b0422ТТТ04220422Т0422Т0422;
        int m = b04220422ТТ04220422Т0422Т0422;
        int n = b0422ТТТ04220422Т0422Т0422;
        int i1 = bТТ0422Т04220422Т0422Т0422;
        int i2 = bТ0422ТТ04220422Т0422Т0422;
        int i3 = b0422ТТТ04220422Т0422Т0422;
        switch (i3 * (b04220422ТТ04220422Т0422Т0422 + i3) % bТТ0422Т04220422Т0422Т0422)
        {
        default: 
          b0422ТТТ04220422Т0422Т0422 = 41;
          bТ0422ТТ04220422Т0422Т0422 = bккк043A043Aккк043A043A();
        }
        if ((k + m) * n % i1 != i2)
        {
          b0422ТТТ04220422Т0422Т0422 = 45;
          bТ0422ТТ04220422Т0422Т0422 = 18;
        }
        uguugu localUguugu = uguugu.b043A043A043A043Aк043Aкк043A043A(j);
        arrayOfInt[i] = localUguugu.bк043A043Aккккк043A043A(localUguugu.b043Aккккккк043A043A(j) - (paramChar + paramChar + paramChar + i));
        i += 1;
      }
      return new String(arrayOfInt, 0, i);
    }
  }
  
  public static class uggguu
    extends gguuuu.gugguu
  {
    public static int b04220422ТТТТ04220422Т0422 = 1;
    public static int b0422ТТТТТ04220422Т0422 = 49;
    public static int bТ0422ТТТТ04220422Т0422 = 2;
    
    public uggguu() {}
    
    public static int bкк043A043A043Aккк043A043A()
    {
      return 1;
    }
    
    public String b043Aк043Aк043Aккк043A043A(String paramString, char paramChar1, char paramChar2)
    {
      char c = b0422ТТТТТ04220422Т0422;
      switch (c * (b04220422ТТТТ04220422Т0422 + c) % bТ0422ТТТТ04220422Т0422)
      {
      default: 
        b0422ТТТТТ04220422Т0422 = 12;
        b04220422ТТТТ04220422Т0422 = 56;
      }
      for (;;)
      {
        try
        {
          arrayOfInt = new int[paramString.length()];
          paramString = new uguuuu(paramString);
          c = '\000';
          if (paramString.bкк043A043Aкккк043A043A())
          {
            i = paramString.bк043A043A043Aкккк043A043A();
            localUguugu = uguugu.b043A043A043A043Aк043Aкк043A043A(i);
          }
        }
        catch (Exception paramString)
        {
          int[] arrayOfInt;
          int i;
          uguugu localUguugu;
          throw paramString;
        }
        try
        {
          i = localUguugu.bк043A043Aккккк043A043A(localUguugu.b043Aккккккк043A043A(i) + (paramChar1 + c) - paramChar2);
          arrayOfInt[c] = i;
          c += '\001';
        }
        catch (Exception paramString)
        {
          throw paramString;
        }
      }
      paramString = new String(arrayOfInt, 0, c);
      paramChar1 = b0422ТТТТТ04220422Т0422;
      switch (paramChar1 * (bкк043A043A043Aккк043A043A() + paramChar1) % bТ0422ТТТТ04220422Т0422)
      {
      default: 
        b0422ТТТТТ04220422Т0422 = 36;
        bТ0422ТТТТ04220422Т0422 = 67;
      }
      switch (1)
      {
      case 0: 
      default: 
        for (;;)
        {
          switch (0)
          {
          }
        }
      }
      return paramString;
    }
  }
  
  public static class ugguuu
    extends gguuuu.gugguu
  {
    public static int b04220422Т0422Т0422Т0422Т0422 = 1;
    public static int b0422ТТ0422Т0422Т0422Т0422 = 80;
    public static int bТ0422Т0422Т0422Т0422Т0422 = 0;
    public static int bТТ04220422Т0422Т0422Т0422 = 2;
    
    public ugguuu() {}
    
    public static int bкк043Aк043Aккк043A043A()
    {
      return 76;
    }
    
    public String b043Aк043Aк043Aккк043A043A(String paramString, char paramChar1, char paramChar2)
    {
      for (;;)
      {
        try
        {
          arrayOfInt = new int[paramString.length()];
          paramString = new uguuuu(paramString);
          c = '\000';
          if (paramString.bкк043A043Aкккк043A043A())
          {
            i = paramString.bк043A043A043Aкккк043A043A();
            localUguugu = uguugu.b043A043A043A043Aк043Aкк043A043A(i);
            i = localUguugu.b043Aккккккк043A043A(i);
          }
        }
        catch (Exception paramString)
        {
          int[] arrayOfInt;
          char c;
          int i;
          uguugu localUguugu;
          throw paramString;
        }
        try
        {
          i = localUguugu.bк043A043Aккккк043A043A(i - (paramChar1 + c) - paramChar2);
          arrayOfInt[c] = i;
          c += '\001';
        }
        catch (Exception paramString)
        {
          throw paramString;
        }
      }
      paramString = new String(arrayOfInt, 0, c);
      switch (1)
      {
      case 0: 
      default: 
        for (;;)
        {
          switch (0)
          {
          }
        }
      }
      if ((b0422ТТ0422Т0422Т0422Т0422 + b04220422Т0422Т0422Т0422Т0422) * b0422ТТ0422Т0422Т0422Т0422 % bТТ04220422Т0422Т0422Т0422 != bТ0422Т0422Т0422Т0422Т0422)
      {
        b0422ТТ0422Т0422Т0422Т0422 = 44;
        bТ0422Т0422Т0422Т0422Т0422 = bкк043Aк043Aккк043A043A();
        if ((b0422ТТ0422Т0422Т0422Т0422 + b04220422Т0422Т0422Т0422Т0422) * b0422ТТ0422Т0422Т0422Т0422 % bТТ04220422Т0422Т0422Т0422 != bТ0422Т0422Т0422Т0422Т0422)
        {
          b0422ТТ0422Т0422Т0422Т0422 = bкк043Aк043Aккк043A043A();
          bТ0422Т0422Т0422Т0422Т0422 = 91;
        }
      }
      return paramString;
    }
  }
  
  public static class uguguu
    extends gguuuu.ggguuu
  {
    public static int b042204220422Т04220422Т0422Т0422 = 1;
    public static int b0422Т0422Т04220422Т0422Т0422 = 5;
    public static int bТ04220422Т04220422Т0422Т0422 = 0;
    public static int bТТТ042204220422Т0422Т0422 = 2;
    
    public uguguu() {}
    
    public static int b043Aкк043A043Aккк043A043A()
    {
      return 63;
    }
    
    public String b043Aккк043Aккк043A043A(String paramString, char paramChar)
    {
      int[] arrayOfInt = new int[paramString.length()];
      paramString = new uguuuu(paramString);
      switch (1)
      {
      case 0: 
      default: 
        for (;;)
        {
          switch (1)
          {
          }
        }
      }
      int i = 0;
      while (paramString.bкк043A043Aкккк043A043A())
      {
        int j = paramString.bк043A043A043Aкккк043A043A();
        if ((b0422Т0422Т04220422Т0422Т0422 + b042204220422Т04220422Т0422Т0422) * b0422Т0422Т04220422Т0422Т0422 % bТТТ042204220422Т0422Т0422 != bТ04220422Т04220422Т0422Т0422)
        {
          b0422Т0422Т04220422Т0422Т0422 = b043Aкк043A043Aккк043A043A();
          bТ04220422Т04220422Т0422Т0422 = b043Aкк043A043Aккк043A043A();
        }
        uguugu localUguugu = uguugu.b043A043A043A043Aк043Aкк043A043A(j);
        j = localUguugu.b043Aккккккк043A043A(j);
        switch (1)
        {
        case 0: 
        default: 
          for (;;)
          {
            switch (1)
            {
            }
          }
        }
        arrayOfInt[i] = localUguugu.bк043A043Aккккк043A043A(j + (paramChar + paramChar + paramChar + i));
        if ((b0422Т0422Т04220422Т0422Т0422 + b042204220422Т04220422Т0422Т0422) * b0422Т0422Т04220422Т0422Т0422 % bТТТ042204220422Т0422Т0422 != bТ04220422Т04220422Т0422Т0422)
        {
          b0422Т0422Т04220422Т0422Т0422 = b043Aкк043A043Aккк043A043A();
          bТ04220422Т04220422Т0422Т0422 = 84;
        }
        i += 1;
      }
      return new String(arrayOfInt, 0, i);
    }
  }
  
  public static class uugguu
    extends gguuuu.gugguu
  {
    public static int b042204220422042204220422Т0422Т0422 = 1;
    public static int b0422Т0422042204220422Т0422Т0422 = 12;
    public static int bТ04220422042204220422Т0422Т0422 = 0;
    public static int bТТТТТТ04220422Т0422 = 2;
    
    public uugguu() {}
    
    public static int b043A043Aк043A043Aккк043A043A()
    {
      return 85;
    }
    
    /* Error */
    public String b043Aк043Aк043Aккк043A043A(String paramString, char paramChar1, char paramChar2)
    {
      // Byte code:
      //   0: iconst_0
      //   1: istore 5
      //   3: aload_1
      //   4: invokevirtual 32	java/lang/String:length	()I
      //   7: newarray int
      //   9: astore 11
      //   11: new 34	kkkkkk/uguuuu
      //   14: dup
      //   15: aload_1
      //   16: invokespecial 37	kkkkkk/uguuuu:<init>	(Ljava/lang/String;)V
      //   19: astore_1
      //   20: getstatic 39	kkkkkk/gguuuu$uugguu:b0422Т0422042204220422Т0422Т0422	I
      //   23: istore 6
      //   25: getstatic 41	kkkkkk/gguuuu$uugguu:b042204220422042204220422Т0422Т0422	I
      //   28: istore 7
      //   30: getstatic 39	kkkkkk/gguuuu$uugguu:b0422Т0422042204220422Т0422Т0422	I
      //   33: istore 8
      //   35: getstatic 43	kkkkkk/gguuuu$uugguu:bТТТТТТ04220422Т0422	I
      //   38: istore 9
      //   40: getstatic 45	kkkkkk/gguuuu$uugguu:bТ04220422042204220422Т0422Т0422	I
      //   43: istore 10
      //   45: iload 5
      //   47: istore 4
      //   49: iload 6
      //   51: iload 7
      //   53: iadd
      //   54: iload 8
      //   56: imul
      //   57: iload 9
      //   59: irem
      //   60: iload 10
      //   62: if_icmpeq +54 -> 116
      //   65: bipush 48
      //   67: putstatic 39	kkkkkk/gguuuu$uugguu:b0422Т0422042204220422Т0422Т0422	I
      //   70: invokestatic 47	kkkkkk/gguuuu$uugguu:b043A043Aк043A043Aккк043A043A	()I
      //   73: istore 4
      //   75: getstatic 39	kkkkkk/gguuuu$uugguu:b0422Т0422042204220422Т0422Т0422	I
      //   78: getstatic 41	kkkkkk/gguuuu$uugguu:b042204220422042204220422Т0422Т0422	I
      //   81: iadd
      //   82: getstatic 39	kkkkkk/gguuuu$uugguu:b0422Т0422042204220422Т0422Т0422	I
      //   85: imul
      //   86: getstatic 43	kkkkkk/gguuuu$uugguu:bТТТТТТ04220422Т0422	I
      //   89: irem
      //   90: getstatic 45	kkkkkk/gguuuu$uugguu:bТ04220422042204220422Т0422Т0422	I
      //   93: if_icmpeq +14 -> 107
      //   96: invokestatic 47	kkkkkk/gguuuu$uugguu:b043A043Aк043A043Aккк043A043A	()I
      //   99: putstatic 39	kkkkkk/gguuuu$uugguu:b0422Т0422042204220422Т0422Т0422	I
      //   102: bipush 17
      //   104: putstatic 45	kkkkkk/gguuuu$uugguu:bТ04220422042204220422Т0422Т0422	I
      //   107: iload 4
      //   109: putstatic 45	kkkkkk/gguuuu$uugguu:bТ04220422042204220422Т0422Т0422	I
      //   112: iload 5
      //   114: istore 4
      //   116: aload_1
      //   117: invokevirtual 51	kkkkkk/uguuuu:bкк043A043Aкккк043A043A	()Z
      //   120: ifeq +58 -> 178
      //   123: aload_1
      //   124: invokevirtual 54	kkkkkk/uguuuu:bк043A043A043Aкккк043A043A	()I
      //   127: istore 5
      //   129: iload 5
      //   131: invokestatic 60	kkkkkk/uguugu:b043A043A043A043Aк043Aкк043A043A	(I)Lkkkkkk/uguugu;
      //   134: astore 12
      //   136: aload 11
      //   138: iload 4
      //   140: aload 12
      //   142: aload 12
      //   144: iload 5
      //   146: invokevirtual 64	kkkkkk/uguugu:b043Aккккккк043A043A	(I)I
      //   149: iload_2
      //   150: iload 4
      //   152: iadd
      //   153: iadd
      //   154: iload_3
      //   155: iadd
      //   156: invokevirtual 67	kkkkkk/uguugu:bк043A043Aккккк043A043A	(I)I
      //   159: iastore
      //   160: iload 4
      //   162: iconst_1
      //   163: iadd
      //   164: istore 4
      //   166: goto -50 -> 116
      //   169: astore_1
      //   170: aload_1
      //   171: athrow
      //   172: astore_1
      //   173: aload_1
      //   174: athrow
      //   175: astore_1
      //   176: aload_1
      //   177: athrow
      //   178: new 29	java/lang/String
      //   181: dup
      //   182: aload 11
      //   184: iconst_0
      //   185: iload 4
      //   187: invokespecial 70	java/lang/String:<init>	([III)V
      //   190: astore_1
      //   191: aload_1
      //   192: areturn
      //   193: astore_1
      //   194: aload_1
      //   195: athrow
      // Local variable table:
      //   start	length	slot	name	signature
      //   0	196	0	this	uugguu
      //   0	196	1	paramString	String
      //   0	196	2	paramChar1	char
      //   0	196	3	paramChar2	char
      //   47	139	4	c1	char
      //   1	144	5	c2	char
      //   23	31	6	i	int
      //   28	26	7	j	int
      //   33	24	8	k	int
      //   38	22	9	m	int
      //   43	20	10	n	int
      //   9	174	11	arrayOfInt	int[]
      //   134	9	12	localUguugu	uguugu
      // Exception table:
      //   from	to	target	type
      //   3	20	169	java/lang/Exception
      //   116	136	169	java/lang/Exception
      //   178	191	169	java/lang/Exception
      //   65	75	172	java/lang/Exception
      //   170	172	172	java/lang/Exception
      //   176	178	172	java/lang/Exception
      //   136	160	175	java/lang/Exception
      //   20	45	193	java/lang/Exception
      //   107	112	193	java/lang/Exception
    }
  }
  
  public static class uuguuu
    extends gguuuu.ggguuu
  {
    public static int b04220422ТТТ0422Т0422Т0422 = 1;
    public static int b0422Т0422ТТ0422Т0422Т0422 = 0;
    public static int bТ0422ТТТ0422Т0422Т0422 = 86;
    public static int bТТ0422ТТ0422Т0422Т0422 = 2;
    
    public uuguuu() {}
    
    public static int b043A043A043A043Aкккк043A043A()
    {
      return 0;
    }
    
    public static int bкккк043Aккк043A043A()
    {
      return 19;
    }
    
    /* Error */
    public String b043Aккк043Aккк043A043A(String paramString, char paramChar)
    {
      // Byte code:
      //   0: iconst_0
      //   1: istore_3
      //   2: getstatic 30	kkkkkk/gguuuu$uuguuu:bТ0422ТТТ0422Т0422Т0422	I
      //   5: istore 4
      //   7: getstatic 32	kkkkkk/gguuuu$uuguuu:b04220422ТТТ0422Т0422Т0422	I
      //   10: istore 5
      //   12: getstatic 30	kkkkkk/gguuuu$uuguuu:bТ0422ТТТ0422Т0422Т0422	I
      //   15: istore 6
      //   17: getstatic 34	kkkkkk/gguuuu$uuguuu:bТТ0422ТТ0422Т0422Т0422	I
      //   20: istore 7
      //   22: invokestatic 36	kkkkkk/gguuuu$uuguuu:b043A043A043A043Aкккк043A043A	()I
      //   25: istore 8
      //   27: getstatic 30	kkkkkk/gguuuu$uuguuu:bТ0422ТТТ0422Т0422Т0422	I
      //   30: getstatic 32	kkkkkk/gguuuu$uuguuu:b04220422ТТТ0422Т0422Т0422	I
      //   33: iadd
      //   34: getstatic 30	kkkkkk/gguuuu$uuguuu:bТ0422ТТТ0422Т0422Т0422	I
      //   37: imul
      //   38: getstatic 34	kkkkkk/gguuuu$uuguuu:bТТ0422ТТ0422Т0422Т0422	I
      //   41: irem
      //   42: getstatic 38	kkkkkk/gguuuu$uuguuu:b0422Т0422ТТ0422Т0422Т0422	I
      //   45: if_icmpeq +15 -> 60
      //   48: invokestatic 40	kkkkkk/gguuuu$uuguuu:bкккк043Aккк043A043A	()I
      //   51: putstatic 30	kkkkkk/gguuuu$uuguuu:bТ0422ТТТ0422Т0422Т0422	I
      //   54: invokestatic 40	kkkkkk/gguuuu$uuguuu:bкккк043Aккк043A043A	()I
      //   57: putstatic 38	kkkkkk/gguuuu$uuguuu:b0422Т0422ТТ0422Т0422Т0422	I
      //   60: iload 4
      //   62: iload 5
      //   64: iadd
      //   65: iload 6
      //   67: imul
      //   68: iload 7
      //   70: irem
      //   71: iload 8
      //   73: if_icmpeq +13 -> 86
      //   76: bipush 36
      //   78: putstatic 30	kkkkkk/gguuuu$uuguuu:bТ0422ТТТ0422Т0422Т0422	I
      //   81: bipush 16
      //   83: putstatic 32	kkkkkk/gguuuu$uuguuu:b04220422ТТТ0422Т0422Т0422	I
      //   86: aload_1
      //   87: invokevirtual 45	java/lang/String:length	()I
      //   90: newarray int
      //   92: astore 9
      //   94: new 47	kkkkkk/uguuuu
      //   97: dup
      //   98: aload_1
      //   99: invokespecial 50	kkkkkk/uguuuu:<init>	(Ljava/lang/String;)V
      //   102: astore_1
      //   103: aload_1
      //   104: invokevirtual 54	kkkkkk/uguuuu:bкк043A043Aкккк043A043A	()Z
      //   107: ifeq +45 -> 152
      //   110: aload_1
      //   111: invokevirtual 57	kkkkkk/uguuuu:bк043A043A043Aкккк043A043A	()I
      //   114: istore 4
      //   116: iload 4
      //   118: invokestatic 63	kkkkkk/uguugu:b043A043A043A043Aк043Aкк043A043A	(I)Lkkkkkk/uguugu;
      //   121: astore 10
      //   123: aload 9
      //   125: iload_3
      //   126: aload 10
      //   128: aload 10
      //   130: iload 4
      //   132: invokevirtual 67	kkkkkk/uguugu:b043Aккккккк043A043A	(I)I
      //   135: iload_2
      //   136: iload_2
      //   137: iadd
      //   138: iload_3
      //   139: iadd
      //   140: iadd
      //   141: invokevirtual 70	kkkkkk/uguugu:bк043A043Aккккк043A043A	(I)I
      //   144: iastore
      //   145: iload_3
      //   146: iconst_1
      //   147: iadd
      //   148: istore_3
      //   149: goto -46 -> 103
      //   152: new 42	java/lang/String
      //   155: dup
      //   156: aload 9
      //   158: iconst_0
      //   159: iload_3
      //   160: invokespecial 73	java/lang/String:<init>	([III)V
      //   163: astore_1
      //   164: aload_1
      //   165: areturn
      //   166: astore_1
      //   167: aload_1
      //   168: athrow
      //   169: astore_1
      //   170: aload_1
      //   171: athrow
      // Local variable table:
      //   start	length	slot	name	signature
      //   0	172	0	this	uuguuu
      //   0	172	1	paramString	String
      //   0	172	2	paramChar	char
      //   1	159	3	i	int
      //   5	126	4	j	int
      //   10	55	5	k	int
      //   15	53	6	m	int
      //   20	51	7	n	int
      //   25	49	8	i1	int
      //   92	65	9	arrayOfInt	int[]
      //   121	8	10	localUguugu	uguugu
      // Exception table:
      //   from	to	target	type
      //   2	27	166	java/lang/Exception
      //   86	103	166	java/lang/Exception
      //   103	145	166	java/lang/Exception
      //   152	164	166	java/lang/Exception
      //   76	86	169	java/lang/Exception
    }
  }
  
  public static class uuuguu
    extends gguuuu.gugguu
  {
    public static int b0422042204220422Т0422Т0422Т0422 = 2;
    public static int b0422Т04220422Т0422Т0422Т0422 = 38;
    public static int bТ042204220422Т0422Т0422Т0422 = 1;
    public static int bТТТТ04220422Т0422Т0422;
    
    public uuuguu() {}
    
    public static int b043A043A043Aк043Aккк043A043A()
    {
      return 77;
    }
    
    public static int bк043A043Aк043Aккк043A043A()
    {
      return 0;
    }
    
    public String b043Aк043Aк043Aккк043A043A(String paramString, char paramChar1, char paramChar2)
    {
      int[] arrayOfInt = new int[paramString.length()];
      paramString = new uguuuu(paramString);
      char c;
      if ((b0422Т04220422Т0422Т0422Т0422 + bТ042204220422Т0422Т0422Т0422) * b0422Т04220422Т0422Т0422Т0422 % b0422042204220422Т0422Т0422Т0422 != bк043A043Aк043Aккк043A043A())
      {
        b0422Т04220422Т0422Т0422Т0422 = 8;
        bТ042204220422Т0422Т0422Т0422 = 20;
        c = '\000';
      }
      for (;;)
      {
        if (paramString.bкк043A043Aкккк043A043A())
        {
          int i = paramString.bк043A043A043Aкккк043A043A();
          uguugu localUguugu = uguugu.b043A043A043A043Aк043Aкк043A043A(i);
          i = localUguugu.b043Aккккккк043A043A(i);
          switch (1)
          {
          case 0: 
          default: 
            for (;;)
            {
              switch (1)
              {
              }
            }
          }
          if ((b0422Т04220422Т0422Т0422Т0422 + bТ042204220422Т0422Т0422Т0422) * b0422Т04220422Т0422Т0422Т0422 % b0422042204220422Т0422Т0422Т0422 != bТТТТ04220422Т0422Т0422)
          {
            b0422Т04220422Т0422Т0422Т0422 = b043A043A043Aк043Aккк043A043A();
            bТТТТ04220422Т0422Т0422 = b043A043A043Aк043Aккк043A043A();
          }
          arrayOfInt[c] = localUguugu.bк043A043Aккккк043A043A(i - (paramChar1 + c) + paramChar2);
          c += '\001';
        }
        else
        {
          return new String(arrayOfInt, 0, c);
          c = '\000';
        }
      }
    }
  }
}
