package kkkkkk;

public class hbhbbh
{
  public static int b04490449щщ0449щщ04490449 = 0;
  public static int b0449щ0449щ0449щщ04490449 = 2;
  public static int bщ0449щщ0449щщ04490449 = 94;
  public static int bщщ0449щ0449щщ04490449 = 1;
  
  public hbhbbh() {}
  
  public static int b04280428Ш0428Ш0428042804280428Ш()
  {
    return 75;
  }
  
  /* Error */
  public static void b0428Ш04280428Ш0428042804280428Ш(String paramString)
  {
    // Byte code:
    //   0: new 26	android/content/Intent
    //   3: dup
    //   4: aload_0
    //   5: invokespecial 28	android/content/Intent:<init>	(Ljava/lang/String;)V
    //   8: astore_0
    //   9: getstatic 30	kkkkkk/hbhbbh:bщ0449щщ0449щщ04490449	I
    //   12: getstatic 32	kkkkkk/hbhbbh:bщщ0449щ0449щщ04490449	I
    //   15: iadd
    //   16: getstatic 30	kkkkkk/hbhbbh:bщ0449щщ0449щщ04490449	I
    //   19: imul
    //   20: getstatic 34	kkkkkk/hbhbbh:b0449щ0449щ0449щщ04490449	I
    //   23: irem
    //   24: getstatic 36	kkkkkk/hbhbbh:b04490449щщ0449щщ04490449	I
    //   27: if_icmpeq +112 -> 139
    //   30: invokestatic 38	kkkkkk/hbhbbh:b04280428Ш0428Ш0428042804280428Ш	()I
    //   33: istore_1
    //   34: invokestatic 38	kkkkkk/hbhbbh:b04280428Ш0428Ш0428042804280428Ш	()I
    //   37: istore_2
    //   38: iload_2
    //   39: getstatic 32	kkkkkk/hbhbbh:bщщ0449щ0449щщ04490449	I
    //   42: iload_2
    //   43: iadd
    //   44: imul
    //   45: getstatic 34	kkkkkk/hbhbbh:b0449щ0449щ0449щщ04490449	I
    //   48: irem
    //   49: tableswitch	default:+19->68, 0:+29->78
    //   68: bipush 78
    //   70: putstatic 30	kkkkkk/hbhbbh:bщ0449щщ0449щщ04490449	I
    //   73: bipush 73
    //   75: putstatic 36	kkkkkk/hbhbbh:b04490449щщ0449щщ04490449	I
    //   78: iload_1
    //   79: putstatic 30	kkkkkk/hbhbbh:bщ0449щщ0449щщ04490449	I
    //   82: invokestatic 38	kkkkkk/hbhbbh:b04280428Ш0428Ш0428042804280428Ш	()I
    //   85: putstatic 36	kkkkkk/hbhbbh:b04490449щщ0449щщ04490449	I
    //   88: iconst_1
    //   89: tableswitch	default:+23->112, 0:+-1->88, 1:+50->139
    //   112: iconst_1
    //   113: tableswitch	default:+23->136, 0:+-25->88, 1:+26->139
    //   136: goto -24 -> 112
    //   139: getstatic 44	kkkkkk/xxdxxd:instance	Lkkkkkk/xxdxxd;
    //   142: invokevirtual 48	kkkkkk/xxdxxd:bххх044504450445х044504450445	()Landroid/content/Context;
    //   145: invokestatic 54	android/support/v4/content/LocalBroadcastManager:getInstance	(Landroid/content/Context;)Landroid/support/v4/content/LocalBroadcastManager;
    //   148: astore_3
    //   149: aload_3
    //   150: aload_0
    //   151: invokevirtual 58	android/support/v4/content/LocalBroadcastManager:sendBroadcast	(Landroid/content/Intent;)Z
    //   154: pop
    //   155: return
    //   156: astore_0
    //   157: aload_0
    //   158: athrow
    //   159: astore_0
    //   160: aload_0
    //   161: athrow
    // Local variable table:
    //   start	length	slot	name	signature
    //   0	162	0	paramString	String
    //   33	46	1	i	int
    //   37	8	2	j	int
    //   148	2	3	localLocalBroadcastManager	android.support.v4.content.LocalBroadcastManager
    // Exception table:
    //   from	to	target	type
    //   0	9	156	java/lang/Exception
    //   139	149	156	java/lang/Exception
    //   149	155	159	java/lang/Exception
  }
  
  /* Error */
  public static void bШ042804280428Ш0428042804280428Ш(String paramString, android.os.Bundle paramBundle)
  {
    // Byte code:
    //   0: new 26	android/content/Intent
    //   3: dup
    //   4: aload_0
    //   5: invokespecial 28	android/content/Intent:<init>	(Ljava/lang/String;)V
    //   8: astore_0
    //   9: aload_0
    //   10: aload_1
    //   11: invokevirtual 64	android/content/Intent:putExtras	(Landroid/os/Bundle;)Landroid/content/Intent;
    //   14: pop
    //   15: getstatic 30	kkkkkk/hbhbbh:bщ0449щщ0449щщ04490449	I
    //   18: istore_2
    //   19: invokestatic 67	kkkkkk/hbhbbh:bШШ04280428Ш0428042804280428Ш	()I
    //   22: istore_3
    //   23: iconst_0
    //   24: tableswitch	default:+24->48, 0:+51->75, 1:+-1->23
    //   48: iconst_1
    //   49: tableswitch	default:+23->72, 0:+-26->23, 1:+26->75
    //   72: goto -24 -> 48
    //   75: iload_2
    //   76: iload_3
    //   77: iadd
    //   78: getstatic 30	kkkkkk/hbhbbh:bщ0449щщ0449щщ04490449	I
    //   81: imul
    //   82: getstatic 34	kkkkkk/hbhbbh:b0449щ0449щ0449щщ04490449	I
    //   85: irem
    //   86: getstatic 36	kkkkkk/hbhbbh:b04490449щщ0449щщ04490449	I
    //   89: if_icmpeq +57 -> 146
    //   92: invokestatic 38	kkkkkk/hbhbbh:b04280428Ш0428Ш0428042804280428Ш	()I
    //   95: istore_2
    //   96: iload_2
    //   97: getstatic 32	kkkkkk/hbhbbh:bщщ0449щ0449щщ04490449	I
    //   100: iload_2
    //   101: iadd
    //   102: imul
    //   103: getstatic 34	kkkkkk/hbhbbh:b0449щ0449щ0449щщ04490449	I
    //   106: irem
    //   107: tableswitch	default:+17->124, 0:+28->135
    //   124: invokestatic 38	kkkkkk/hbhbbh:b04280428Ш0428Ш0428042804280428Ш	()I
    //   127: putstatic 30	kkkkkk/hbhbbh:bщ0449щщ0449щщ04490449	I
    //   130: bipush 84
    //   132: putstatic 36	kkkkkk/hbhbbh:b04490449щщ0449щщ04490449	I
    //   135: bipush 76
    //   137: putstatic 30	kkkkkk/hbhbbh:bщ0449щщ0449щщ04490449	I
    //   140: invokestatic 38	kkkkkk/hbhbbh:b04280428Ш0428Ш0428042804280428Ш	()I
    //   143: putstatic 36	kkkkkk/hbhbbh:b04490449щщ0449щщ04490449	I
    //   146: getstatic 44	kkkkkk/xxdxxd:instance	Lkkkkkk/xxdxxd;
    //   149: invokevirtual 48	kkkkkk/xxdxxd:bххх044504450445х044504450445	()Landroid/content/Context;
    //   152: astore_1
    //   153: aload_1
    //   154: invokestatic 54	android/support/v4/content/LocalBroadcastManager:getInstance	(Landroid/content/Context;)Landroid/support/v4/content/LocalBroadcastManager;
    //   157: aload_0
    //   158: invokevirtual 58	android/support/v4/content/LocalBroadcastManager:sendBroadcast	(Landroid/content/Intent;)Z
    //   161: pop
    //   162: return
    //   163: astore_0
    //   164: aload_0
    //   165: athrow
    //   166: astore_0
    //   167: aload_0
    //   168: athrow
    // Local variable table:
    //   start	length	slot	name	signature
    //   0	169	0	paramString	String
    //   0	169	1	paramBundle	android.os.Bundle
    //   18	85	2	i	int
    //   22	56	3	j	int
    // Exception table:
    //   from	to	target	type
    //   153	162	163	java/lang/Exception
    //   0	15	166	java/lang/Exception
    //   146	153	166	java/lang/Exception
  }
  
  public static int bШШ04280428Ш0428042804280428Ш()
  {
    return 1;
  }
}
