package kkkkkk;

import android.content.Context;
import android.content.pm.ApplicationInfo;
import android.graphics.Bitmap;
import android.graphics.BitmapFactory;
import android.graphics.BitmapFactory.Options;
import android.net.Uri;
import android.support.annotation.NonNull;
import android.support.annotation.Nullable;
import android.support.v4.content.FileProvider;
import android.util.Base64;
import com.squareup.picasso.Picasso;
import com.squareup.picasso.RequestCreator;
import java.io.File;
import java.io.IOException;

public class hhhhhb
{
  public static int b0449044904490449044904490449щ0449 = 2;
  public static final String b044904490449щ044904490449щ0449 = gguuuu.bккккк043Aкк043A043A(b044904490449щ044904490449щ0449, 'û', '\004');
  public static final String b04490449щ0449044904490449щ0449 = hhhhhb.class.getSimpleName();
  private static final float b04490449щщ044904490449щ0449 = 0.4F;
  public static int b0449щ04490449044904490449щ0449 = 0;
  public static String b0449щ0449щ044904490449щ0449;
  public static String b0449щщ0449044904490449щ0449;
  public static int bщ044904490449044904490449щ0449 = 1;
  public static String bщ04490449щ044904490449щ0449;
  public static final String bщ0449щ0449044904490449щ0449 = "Q@MTWQK";
  public static int bщщ04490449044904490449щ0449 = 58;
  private static final float bщщ0449щ044904490449щ0449 = 7.5F;
  public static final String bщщщ0449044904490449щ0449 = gguuuu.bк043Aккк043Aкк043A043A(bщщщ0449044904490449щ0449, 'r', '4', '\000');
  
  /* Error */
  static
  {
    // Byte code:
    //   0: getstatic 40	kkkkkk/hhhhhb:b044904490449щ044904490449щ0449	Ljava/lang/String;
    //   3: sipush 251
    //   6: iconst_4
    //   7: invokestatic 46	kkkkkk/gguuuu:bккккк043Aкк043A043A	(Ljava/lang/String;CC)Ljava/lang/String;
    //   10: putstatic 40	kkkkkk/hhhhhb:b044904490449щ044904490449щ0449	Ljava/lang/String;
    //   13: getstatic 48	kkkkkk/hhhhhb:bщщщ0449044904490449щ0449	Ljava/lang/String;
    //   16: bipush 114
    //   18: bipush 52
    //   20: iconst_0
    //   21: invokestatic 52	kkkkkk/gguuuu:bк043Aккк043Aкк043A043A	(Ljava/lang/String;CCC)Ljava/lang/String;
    //   24: putstatic 48	kkkkkk/hhhhhb:bщщщ0449044904490449щ0449	Ljava/lang/String;
    //   27: getstatic 54	kkkkkk/hhhhhb:bщ0449щ0449044904490449щ0449	Ljava/lang/String;
    //   30: astore_2
    //   31: getstatic 56	kkkkkk/hhhhhb:bщщ04490449044904490449щ0449	I
    //   34: istore_0
    //   35: getstatic 56	kkkkkk/hhhhhb:bщщ04490449044904490449щ0449	I
    //   38: istore_1
    //   39: iload_1
    //   40: getstatic 58	kkkkkk/hhhhhb:bщ044904490449044904490449щ0449	I
    //   43: iload_1
    //   44: iadd
    //   45: imul
    //   46: invokestatic 62	kkkkkk/hhhhhb:b042804280428ШШШ042804280428Ш	()I
    //   49: irem
    //   50: tableswitch	default:+18->68, 0:+30->80
    //   68: invokestatic 65	kkkkkk/hhhhhb:bШ042804280428ШШ042804280428Ш	()I
    //   71: putstatic 56	kkkkkk/hhhhhb:bщщ04490449044904490449щ0449	I
    //   74: invokestatic 65	kkkkkk/hhhhhb:bШ042804280428ШШ042804280428Ш	()I
    //   77: putstatic 67	kkkkkk/hhhhhb:b0449щ04490449044904490449щ0449	I
    //   80: iload_0
    //   81: getstatic 58	kkkkkk/hhhhhb:bщ044904490449044904490449щ0449	I
    //   84: iadd
    //   85: getstatic 56	kkkkkk/hhhhhb:bщщ04490449044904490449щ0449	I
    //   88: imul
    //   89: getstatic 69	kkkkkk/hhhhhb:b0449044904490449044904490449щ0449	I
    //   92: irem
    //   93: getstatic 67	kkkkkk/hhhhhb:b0449щ04490449044904490449щ0449	I
    //   96: if_icmpeq +14 -> 110
    //   99: invokestatic 65	kkkkkk/hhhhhb:bШ042804280428ШШ042804280428Ш	()I
    //   102: putstatic 56	kkkkkk/hhhhhb:bщщ04490449044904490449щ0449	I
    //   105: bipush 18
    //   107: putstatic 67	kkkkkk/hhhhhb:b0449щ04490449044904490449щ0449	I
    //   110: aload_2
    //   111: sipush 237
    //   114: bipush 17
    //   116: iconst_1
    //   117: invokestatic 52	kkkkkk/gguuuu:bк043Aккк043Aкк043A043A	(Ljava/lang/String;CCC)Ljava/lang/String;
    //   120: putstatic 54	kkkkkk/hhhhhb:bщ0449щ0449044904490449щ0449	Ljava/lang/String;
    //   123: ldc 2
    //   125: invokevirtual 75	java/lang/Class:getSimpleName	()Ljava/lang/String;
    //   128: putstatic 77	kkkkkk/hhhhhb:b04490449щ0449044904490449щ0449	Ljava/lang/String;
    //   131: ldc 79
    //   133: bipush 65
    //   135: bipush 113
    //   137: iconst_1
    //   138: invokestatic 52	kkkkkk/gguuuu:bк043Aккк043Aкк043A043A	(Ljava/lang/String;CCC)Ljava/lang/String;
    //   141: astore_2
    //   142: aload_2
    //   143: putstatic 81	kkkkkk/hhhhhb:bщ04490449щ044904490449щ0449	Ljava/lang/String;
    //   146: ldc 83
    //   148: sipush 138
    //   151: iconst_4
    //   152: invokestatic 46	kkkkkk/gguuuu:bккккк043Aкк043A043A	(Ljava/lang/String;CC)Ljava/lang/String;
    //   155: putstatic 85	kkkkkk/hhhhhb:b0449щ0449щ044904490449щ0449	Ljava/lang/String;
    //   158: ldc 87
    //   160: sipush 153
    //   163: sipush 187
    //   166: iconst_2
    //   167: invokestatic 52	kkkkkk/gguuuu:bк043Aккк043Aкк043A043A	(Ljava/lang/String;CCC)Ljava/lang/String;
    //   170: putstatic 89	kkkkkk/hhhhhb:b0449щщ0449044904490449щ0449	Ljava/lang/String;
    //   173: return
    //   174: astore_2
    //   175: aload_2
    //   176: athrow
    //   177: astore_2
    //   178: aload_2
    //   179: athrow
    // Local variable table:
    //   start	length	slot	name	signature
    //   34	51	0	i	int
    //   38	8	1	j	int
    //   30	113	2	str	String
    //   174	2	2	localException1	Exception
    //   177	2	2	localException2	Exception
    // Exception table:
    //   from	to	target	type
    //   0	31	174	java/lang/Exception
    //   110	142	174	java/lang/Exception
    //   142	173	177	java/lang/Exception
  }
  
  public hhhhhb() {}
  
  public static String b04280428042804280428Ш042804280428Ш(Context paramContext, String paramString1, String paramString2)
  {
    Object localObject2 = null;
    int i = bщщ04490449044904490449щ0449;
    switch (i * (bщ044904490449044904490449щ0449 + i) % b0449044904490449044904490449щ0449)
    {
    default: 
      bщщ04490449044904490449щ0449 = bШ042804280428ШШ042804280428Ш();
      b0449щ04490449044904490449щ0449 = bШ042804280428ШШ042804280428Ш();
    }
    Object localObject1 = localObject2;
    if (paramString1 != null) {}
    try
    {
      paramString1 = bШ0428Ш0428ШШ042804280428Ш(paramString1);
      localObject1 = localObject2;
      if (paramString1 != null)
      {
        i = bщщ04490449044904490449щ0449;
        switch (i * (bщ044904490449044904490449щ0449 + i) % b0449044904490449044904490449щ0449)
        {
        default: 
          bщщ04490449044904490449щ0449 = 14;
          b0449щ04490449044904490449щ0449 = bШ042804280428ШШ042804280428Ш();
        }
        paramContext = bШШШШШ0428042804280428Ш(paramContext, paramString1, paramString2, hhhhhb.hbbbbh.PREVIEW, null);
        localObject1 = paramContext;
        switch (1)
        {
        case 0: 
        default: 
          for (;;)
          {
            localObject1 = paramContext;
            switch (1)
            {
            }
          }
        }
      }
      return localObject1;
    }
    catch (Exception paramContext)
    {
      throw paramContext;
    }
  }
  
  public static int b0428042804280428ШШ042804280428Ш()
  {
    return 1;
  }
  
  private static void b042804280428Ш0428Ш042804280428Ш(File paramFile)
  {
    for (;;)
    {
      try
      {
        if (paramFile.isDirectory())
        {
          xtxtxt.bии0438и04380438и0438ии(b04490449щ0449044904490449щ0449, gguuuu.bккккк043Aкк043A043A("\037!)#3%\023'&9790>.\004j02:4D:@:s9?I=<NJNV\030~", 'h', '\001') + paramFile.getAbsolutePath());
          File[] arrayOfFile = paramFile.listFiles();
          int j = arrayOfFile.length;
          i = 0;
          if (i < j) {
            localFile = arrayOfFile[i];
          }
        }
      }
      catch (Exception paramFile)
      {
        int i;
        File localFile;
        String str;
        StringBuilder localStringBuilder;
        throw paramFile;
      }
      try
      {
        str = b04490449щ0449044904490449щ0449;
        localStringBuilder = new StringBuilder();
        xtxtxt.bии0438и04380438и0438ии(str, gguuuu.bккккк043Aкк043A043A(".082B4\"65HFH?M=\023y?AICSIOI\003JNRL\"\t", 'ì', '\001') + localFile.getAbsolutePath());
        b042804280428Ш0428Ш042804280428Ш(localFile);
        i += 1;
      }
      catch (Exception paramFile)
      {
        throw paramFile;
      }
    }
    paramFile.delete();
  }
  
  public static int b042804280428ШШШ042804280428Ш()
  {
    return 2;
  }
  
  /* Error */
  public static String b04280428Ш04280428Ш042804280428Ш(Context paramContext, Uri paramUri, String paramString)
  {
    // Byte code:
    //   0: iconst_1
    //   1: tableswitch	default:+23->24, 0:+-1->0, 1:+50->51
    //   24: iconst_0
    //   25: tableswitch	default:+23->48, 0:+26->51, 1:+-25->0
    //   48: goto -24 -> 24
    //   51: aload_1
    //   52: invokevirtual 155	android/net/Uri:getScheme	()Ljava/lang/String;
    //   55: ldc -99
    //   57: bipush 107
    //   59: iconst_2
    //   60: invokestatic 46	kkkkkk/gguuuu:bккккк043Aкк043A043A	(Ljava/lang/String;CC)Ljava/lang/String;
    //   63: invokevirtual 163	java/lang/String:equals	(Ljava/lang/Object;)Z
    //   66: istore 4
    //   68: iload 4
    //   70: ifeq +279 -> 349
    //   73: aload_1
    //   74: invokevirtual 166	android/net/Uri:getAuthority	()Ljava/lang/String;
    //   77: new 118	java/lang/StringBuilder
    //   80: dup
    //   81: invokespecial 119	java/lang/StringBuilder:<init>	()V
    //   84: invokestatic 171	kkkkkk/xxdxxd:b04450445х044504450445х044504450445	()Ljava/lang/String;
    //   87: invokevirtual 125	java/lang/StringBuilder:append	(Ljava/lang/String;)Ljava/lang/StringBuilder;
    //   90: aload_0
    //   91: invokevirtual 177	android/content/Context:getApplicationInfo	()Landroid/content/pm/ApplicationInfo;
    //   94: getfield 182	android/content/pm/ApplicationInfo:packageName	Ljava/lang/String;
    //   97: invokevirtual 125	java/lang/StringBuilder:append	(Ljava/lang/String;)Ljava/lang/StringBuilder;
    //   100: invokevirtual 131	java/lang/StringBuilder:toString	()Ljava/lang/String;
    //   103: invokevirtual 163	java/lang/String:equals	(Ljava/lang/Object;)Z
    //   106: ifeq +59 -> 165
    //   109: new 112	java/io/File
    //   112: dup
    //   113: aload_0
    //   114: invokevirtual 186	android/content/Context:getFilesDir	()Ljava/io/File;
    //   117: aload_1
    //   118: invokevirtual 189	android/net/Uri:getPath	()Ljava/lang/String;
    //   121: invokespecial 192	java/io/File:<init>	(Ljava/io/File;Ljava/lang/String;)V
    //   124: invokevirtual 128	java/io/File:getAbsolutePath	()Ljava/lang/String;
    //   127: astore_0
    //   128: getstatic 77	kkkkkk/hhhhhb:b04490449щ0449044904490449щ0449	Ljava/lang/String;
    //   131: astore_1
    //   132: new 118	java/lang/StringBuilder
    //   135: dup
    //   136: invokespecial 119	java/lang/StringBuilder:<init>	()V
    //   139: ldc -62
    //   141: bipush 65
    //   143: iconst_5
    //   144: invokestatic 46	kkkkkk/gguuuu:bккккк043Aкк043A043A	(Ljava/lang/String;CC)Ljava/lang/String;
    //   147: invokevirtual 125	java/lang/StringBuilder:append	(Ljava/lang/String;)Ljava/lang/StringBuilder;
    //   150: astore_2
    //   151: aload_1
    //   152: aload_2
    //   153: aload_0
    //   154: invokevirtual 125	java/lang/StringBuilder:append	(Ljava/lang/String;)Ljava/lang/StringBuilder;
    //   157: invokevirtual 131	java/lang/StringBuilder:toString	()Ljava/lang/String;
    //   160: invokestatic 137	kkkkkk/xtxtxt:bии0438и04380438и0438ии	(Ljava/lang/String;Ljava/lang/String;)V
    //   163: aload_0
    //   164: areturn
    //   165: iconst_1
    //   166: anewarray 159	java/lang/String
    //   169: astore_2
    //   170: aload_2
    //   171: iconst_0
    //   172: ldc -60
    //   174: bipush 34
    //   176: iconst_0
    //   177: invokestatic 46	kkkkkk/gguuuu:bккккк043Aкк043A043A	(Ljava/lang/String;CC)Ljava/lang/String;
    //   180: aastore
    //   181: getstatic 56	kkkkkk/hhhhhb:bщщ04490449044904490449щ0449	I
    //   184: istore_3
    //   185: iload_3
    //   186: getstatic 58	kkkkkk/hhhhhb:bщ044904490449044904490449щ0449	I
    //   189: iload_3
    //   190: iadd
    //   191: imul
    //   192: getstatic 69	kkkkkk/hhhhhb:b0449044904490449044904490449щ0449	I
    //   195: irem
    //   196: tableswitch	default:+20->216, 0:+31->227
    //   216: bipush 79
    //   218: putstatic 56	kkkkkk/hhhhhb:bщщ04490449044904490449щ0449	I
    //   221: invokestatic 65	kkkkkk/hhhhhb:bШ042804280428ШШ042804280428Ш	()I
    //   224: putstatic 67	kkkkkk/hhhhhb:b0449щ04490449044904490449щ0449	I
    //   227: aload_0
    //   228: invokevirtual 200	android/content/Context:getContentResolver	()Landroid/content/ContentResolver;
    //   231: aload_1
    //   232: aload_2
    //   233: aconst_null
    //   234: aconst_null
    //   235: aconst_null
    //   236: invokevirtual 206	android/content/ContentResolver:query	(Landroid/net/Uri;[Ljava/lang/String;Ljava/lang/String;[Ljava/lang/String;Ljava/lang/String;)Landroid/database/Cursor;
    //   239: astore_0
    //   240: aload_0
    //   241: ifnull +154 -> 395
    //   244: aload_0
    //   245: invokeinterface 211 1 0
    //   250: pop
    //   251: aload_0
    //   252: aload_0
    //   253: aload_2
    //   254: iconst_0
    //   255: aaload
    //   256: invokeinterface 215 2 0
    //   261: invokeinterface 219 2 0
    //   266: astore_2
    //   267: aload_0
    //   268: invokeinterface 222 1 0
    //   273: aload_2
    //   274: astore_0
    //   275: aload_2
    //   276: invokestatic 228	android/text/TextUtils:isEmpty	(Ljava/lang/CharSequence;)Z
    //   279: ifeq -151 -> 128
    //   282: aload_1
    //   283: invokevirtual 229	android/net/Uri:toString	()Ljava/lang/String;
    //   286: astore_1
    //   287: aload_1
    //   288: astore_0
    //   289: getstatic 56	kkkkkk/hhhhhb:bщщ04490449044904490449щ0449	I
    //   292: getstatic 58	kkkkkk/hhhhhb:bщ044904490449044904490449щ0449	I
    //   295: iadd
    //   296: getstatic 56	kkkkkk/hhhhhb:bщщ04490449044904490449щ0449	I
    //   299: imul
    //   300: invokestatic 62	kkkkkk/hhhhhb:b042804280428ШШШ042804280428Ш	()I
    //   303: irem
    //   304: getstatic 67	kkkkkk/hhhhhb:b0449щ04490449044904490449щ0449	I
    //   307: if_icmpeq -179 -> 128
    //   310: bipush 98
    //   312: putstatic 56	kkkkkk/hhhhhb:bщщ04490449044904490449щ0449	I
    //   315: invokestatic 65	kkkkkk/hhhhhb:bШ042804280428ШШ042804280428Ш	()I
    //   318: putstatic 67	kkkkkk/hhhhhb:b0449щ04490449044904490449щ0449	I
    //   321: aload_1
    //   322: astore_0
    //   323: goto -195 -> 128
    //   326: getstatic 77	kkkkkk/hhhhhb:b04490449щ0449044904490449щ0449	Ljava/lang/String;
    //   329: astore_0
    //   330: aload_0
    //   331: ldc -25
    //   333: bipush 49
    //   335: bipush 55
    //   337: iconst_0
    //   338: invokestatic 52	kkkkkk/gguuuu:bк043Aккк043Aкк043A043A	(Ljava/lang/String;CCC)Ljava/lang/String;
    //   341: invokestatic 234	kkkkkk/xtxtxt:b0438и0438и04380438и0438ии	(Ljava/lang/String;Ljava/lang/String;)V
    //   344: aconst_null
    //   345: astore_0
    //   346: goto -218 -> 128
    //   349: aload_1
    //   350: invokevirtual 155	android/net/Uri:getScheme	()Ljava/lang/String;
    //   353: ldc -20
    //   355: bipush 10
    //   357: iconst_0
    //   358: invokestatic 46	kkkkkk/gguuuu:bккккк043Aкк043A043A	(Ljava/lang/String;CC)Ljava/lang/String;
    //   361: invokevirtual 163	java/lang/String:equals	(Ljava/lang/Object;)Z
    //   364: ifeq -38 -> 326
    //   367: getstatic 77	kkkkkk/hhhhhb:b04490449щ0449044904490449щ0449	Ljava/lang/String;
    //   370: ldc -18
    //   372: bipush 24
    //   374: iconst_4
    //   375: invokestatic 46	kkkkkk/gguuuu:bккккк043Aкк043A043A	(Ljava/lang/String;CC)Ljava/lang/String;
    //   378: invokestatic 137	kkkkkk/xtxtxt:bии0438и04380438и0438ии	(Ljava/lang/String;Ljava/lang/String;)V
    //   381: aload_1
    //   382: invokevirtual 189	android/net/Uri:getPath	()Ljava/lang/String;
    //   385: astore_0
    //   386: goto -258 -> 128
    //   389: astore_0
    //   390: aload_0
    //   391: athrow
    //   392: astore_0
    //   393: aload_0
    //   394: athrow
    //   395: aconst_null
    //   396: astore_0
    //   397: goto -269 -> 128
    // Local variable table:
    //   start	length	slot	name	signature
    //   0	400	0	paramContext	Context
    //   0	400	1	paramUri	Uri
    //   0	400	2	paramString	String
    //   184	8	3	i	int
    //   66	3	4	bool	boolean
    // Exception table:
    //   from	to	target	type
    //   73	128	389	java/lang/Exception
    //   128	151	389	java/lang/Exception
    //   170	181	389	java/lang/Exception
    //   227	240	389	java/lang/Exception
    //   251	267	389	java/lang/Exception
    //   275	287	389	java/lang/Exception
    //   326	330	389	java/lang/Exception
    //   349	386	389	java/lang/Exception
    //   51	68	392	java/lang/Exception
    //   151	163	392	java/lang/Exception
    //   165	170	392	java/lang/Exception
    //   244	251	392	java/lang/Exception
    //   267	273	392	java/lang/Exception
    //   330	344	392	java/lang/Exception
  }
  
  /* Error */
  public static String b04280428Ш0428ШШ042804280428Ш(Bitmap paramBitmap)
  {
    // Byte code:
    //   0: new 242	java/io/ByteArrayOutputStream
    //   3: dup
    //   4: invokespecial 243	java/io/ByteArrayOutputStream:<init>	()V
    //   7: astore 6
    //   9: getstatic 56	kkkkkk/hhhhhb:bщщ04490449044904490449щ0449	I
    //   12: istore_1
    //   13: iload_1
    //   14: getstatic 58	kkkkkk/hhhhhb:bщ044904490449044904490449щ0449	I
    //   17: iload_1
    //   18: iadd
    //   19: imul
    //   20: getstatic 69	kkkkkk/hhhhhb:b0449044904490449044904490449щ0449	I
    //   23: irem
    //   24: tableswitch	default:+20->44, 0:+30->54
    //   44: bipush 78
    //   46: putstatic 56	kkkkkk/hhhhhb:bщщ04490449044904490449щ0449	I
    //   49: bipush 9
    //   51: putstatic 67	kkkkkk/hhhhhb:b0449щ04490449044904490449щ0449	I
    //   54: aload_0
    //   55: getstatic 249	android/graphics/Bitmap$CompressFormat:PNG	Landroid/graphics/Bitmap$CompressFormat;
    //   58: bipush 100
    //   60: aload 6
    //   62: invokevirtual 255	android/graphics/Bitmap:compress	(Landroid/graphics/Bitmap$CompressFormat;ILjava/io/OutputStream;)Z
    //   65: pop
    //   66: aload 6
    //   68: invokevirtual 259	java/io/ByteArrayOutputStream:toByteArray	()[B
    //   71: astore_0
    //   72: getstatic 77	kkkkkk/hhhhhb:b04490449щ0449044904490449щ0449	Ljava/lang/String;
    //   75: astore 6
    //   77: new 118	java/lang/StringBuilder
    //   80: dup
    //   81: invokespecial 119	java/lang/StringBuilder:<init>	()V
    //   84: astore 7
    //   86: aload 7
    //   88: ldc_w 261
    //   91: bipush 44
    //   93: iconst_1
    //   94: invokestatic 46	kkkkkk/gguuuu:bккккк043Aкк043A043A	(Ljava/lang/String;CC)Ljava/lang/String;
    //   97: invokevirtual 125	java/lang/StringBuilder:append	(Ljava/lang/String;)Ljava/lang/StringBuilder;
    //   100: astore 7
    //   102: invokestatic 65	kkkkkk/hhhhhb:bШ042804280428ШШ042804280428Ш	()I
    //   105: istore_1
    //   106: getstatic 58	kkkkkk/hhhhhb:bщ044904490449044904490449щ0449	I
    //   109: istore_2
    //   110: invokestatic 65	kkkkkk/hhhhhb:bШ042804280428ШШ042804280428Ш	()I
    //   113: istore_3
    //   114: getstatic 69	kkkkkk/hhhhhb:b0449044904490449044904490449щ0449	I
    //   117: istore 4
    //   119: getstatic 67	kkkkkk/hhhhhb:b0449щ04490449044904490449щ0449	I
    //   122: istore 5
    //   124: iload_1
    //   125: iload_2
    //   126: iadd
    //   127: iload_3
    //   128: imul
    //   129: iload 4
    //   131: irem
    //   132: iload 5
    //   134: if_icmpeq +14 -> 148
    //   137: invokestatic 65	kkkkkk/hhhhhb:bШ042804280428ШШ042804280428Ш	()I
    //   140: putstatic 56	kkkkkk/hhhhhb:bщщ04490449044904490449щ0449	I
    //   143: bipush 39
    //   145: putstatic 67	kkkkkk/hhhhhb:b0449щ04490449044904490449щ0449	I
    //   148: aload 7
    //   150: aload_0
    //   151: arraylength
    //   152: sipush 1000
    //   155: idiv
    //   156: invokevirtual 264	java/lang/StringBuilder:append	(I)Ljava/lang/StringBuilder;
    //   159: astore 7
    //   161: ldc_w 266
    //   164: sipush 159
    //   167: iconst_1
    //   168: invokestatic 46	kkkkkk/gguuuu:bккккк043Aкк043A043A	(Ljava/lang/String;CC)Ljava/lang/String;
    //   171: astore 8
    //   173: aload 6
    //   175: aload 7
    //   177: aload 8
    //   179: invokevirtual 125	java/lang/StringBuilder:append	(Ljava/lang/String;)Ljava/lang/StringBuilder;
    //   182: invokevirtual 131	java/lang/StringBuilder:toString	()Ljava/lang/String;
    //   185: invokestatic 137	kkkkkk/xtxtxt:bии0438и04380438и0438ии	(Ljava/lang/String;Ljava/lang/String;)V
    //   188: aload_0
    //   189: iconst_0
    //   190: invokestatic 272	android/util/Base64:encodeToString	([BI)Ljava/lang/String;
    //   193: astore_0
    //   194: aload_0
    //   195: areturn
    //   196: astore_0
    //   197: aload_0
    //   198: athrow
    //   199: astore_0
    //   200: aload_0
    //   201: athrow
    // Local variable table:
    //   start	length	slot	name	signature
    //   0	202	0	paramBitmap	Bitmap
    //   12	115	1	i	int
    //   109	18	2	j	int
    //   113	16	3	k	int
    //   117	15	4	m	int
    //   122	13	5	n	int
    //   7	167	6	localObject	Object
    //   84	92	7	localStringBuilder	StringBuilder
    //   171	7	8	str	String
    // Exception table:
    //   from	to	target	type
    //   0	9	196	java/lang/Exception
    //   54	86	196	java/lang/Exception
    //   102	119	196	java/lang/Exception
    //   137	148	196	java/lang/Exception
    //   161	173	196	java/lang/Exception
    //   188	194	196	java/lang/Exception
    //   86	102	199	java/lang/Exception
    //   119	124	199	java/lang/Exception
    //   148	161	199	java/lang/Exception
    //   173	188	199	java/lang/Exception
  }
  
  public static Bitmap b04280428ШШ0428Ш042804280428Ш(Uri paramUri, int paramInt1, int paramInt2, boolean paramBoolean)
    throws IOException
  {
    throw new Runtime("d2j fail translate: java.lang.IndexOutOfBoundsException: fromIndex < 0: -1\n\tat java.util.BitSet.nextSetBit(BitSet.java:712)\n\tat com.googlecode.dex2jar.ir.ts.array.FillArrayTransformer.makeSureAllElementAreAssigned(FillArrayTransformer.java:505)\n\tat com.googlecode.dex2jar.ir.ts.array.FillArrayTransformer.transformReportChanged(FillArrayTransformer.java:123)\n\tat com.googlecode.dex2jar.ir.ts.StatedTransformer.transform(StatedTransformer.java:10)\n\tat com.googlecode.d2j.dex.Dex2jar$2.optimize(Dex2jar.java:149)\n\tat com.googlecode.d2j.dex.Dex2Asm.convertCode(Dex2Asm.java:414)\n\tat com.googlecode.d2j.dex.ExDex2Asm.convertCode(ExDex2Asm.java:42)\n\tat com.googlecode.d2j.dex.Dex2jar$2.convertCode(Dex2jar.java:128)\n\tat com.googlecode.d2j.dex.Dex2Asm.convertMethod(Dex2Asm.java:509)\n\tat com.googlecode.d2j.dex.Dex2Asm.convertClass(Dex2Asm.java:406)\n\tat com.googlecode.d2j.dex.Dex2Asm.convertDex(Dex2Asm.java:422)\n\tat com.googlecode.d2j.dex.Dex2jar.doTranslate(Dex2jar.java:172)\n\tat com.googlecode.d2j.dex.Dex2jar.to(Dex2jar.java:272)\n\tat com.googlecode.dex2jar.tools.Dex2jarCmd.doCommandLine(Dex2jarCmd.java:108)\n\tat com.googlecode.dex2jar.tools.BaseCmd.doMain(BaseCmd.java:288)\n\tat com.googlecode.dex2jar.tools.Dex2jarCmd.main(Dex2jarCmd.java:32)\n");
  }
  
  /* Error */
  public static byte[] b0428Ш042804280428Ш042804280428Ш(Bitmap paramBitmap, int paramInt, String paramString)
  {
    // Byte code:
    //   0: getstatic 77	kkkkkk/hhhhhb:b04490449щ0449044904490449щ0449	Ljava/lang/String;
    //   3: astore 8
    //   5: new 118	java/lang/StringBuilder
    //   8: dup
    //   9: invokespecial 119	java/lang/StringBuilder:<init>	()V
    //   12: astore 9
    //   14: aload 9
    //   16: ldc_w 290
    //   19: sipush 210
    //   22: iconst_5
    //   23: invokestatic 46	kkkkkk/gguuuu:bккккк043Aкк043A043A	(Ljava/lang/String;CC)Ljava/lang/String;
    //   26: invokevirtual 125	java/lang/StringBuilder:append	(Ljava/lang/String;)Ljava/lang/StringBuilder;
    //   29: astore 9
    //   31: aload 8
    //   33: aload 9
    //   35: aload_2
    //   36: invokevirtual 125	java/lang/StringBuilder:append	(Ljava/lang/String;)Ljava/lang/StringBuilder;
    //   39: invokevirtual 131	java/lang/StringBuilder:toString	()Ljava/lang/String;
    //   42: invokestatic 137	kkkkkk/xtxtxt:bии0438и04380438и0438ии	(Ljava/lang/String;Ljava/lang/String;)V
    //   45: getstatic 293	android/graphics/Bitmap$CompressFormat:JPEG	Landroid/graphics/Bitmap$CompressFormat;
    //   48: astore 8
    //   50: aload_2
    //   51: invokevirtual 296	java/lang/String:toLowerCase	()Ljava/lang/String;
    //   54: astore 9
    //   56: aload 8
    //   58: astore_2
    //   59: aload 9
    //   61: ldc_w 298
    //   64: sipush 138
    //   67: iconst_5
    //   68: invokestatic 46	kkkkkk/gguuuu:bккккк043Aкк043A043A	(Ljava/lang/String;CC)Ljava/lang/String;
    //   71: invokevirtual 163	java/lang/String:equals	(Ljava/lang/Object;)Z
    //   74: ifeq +7 -> 81
    //   77: getstatic 249	android/graphics/Bitmap$CompressFormat:PNG	Landroid/graphics/Bitmap$CompressFormat;
    //   80: astore_2
    //   81: getstatic 77	kkkkkk/hhhhhb:b04490449щ0449044904490449щ0449	Ljava/lang/String;
    //   84: astore 8
    //   86: aload 8
    //   88: ldc_w 300
    //   91: sipush 183
    //   94: iconst_2
    //   95: invokestatic 46	kkkkkk/gguuuu:bккккк043Aкк043A043A	(Ljava/lang/String;CC)Ljava/lang/String;
    //   98: invokestatic 137	kkkkkk/xtxtxt:bии0438и04380438и0438ии	(Ljava/lang/String;Ljava/lang/String;)V
    //   101: getstatic 56	kkkkkk/hhhhhb:bщщ04490449044904490449щ0449	I
    //   104: istore_3
    //   105: getstatic 58	kkkkkk/hhhhhb:bщ044904490449044904490449щ0449	I
    //   108: istore 4
    //   110: getstatic 56	kkkkkk/hhhhhb:bщщ04490449044904490449щ0449	I
    //   113: istore 5
    //   115: getstatic 69	kkkkkk/hhhhhb:b0449044904490449044904490449щ0449	I
    //   118: istore 6
    //   120: getstatic 67	kkkkkk/hhhhhb:b0449щ04490449044904490449щ0449	I
    //   123: istore 7
    //   125: iload_3
    //   126: iload 4
    //   128: iadd
    //   129: iload 5
    //   131: imul
    //   132: iload 6
    //   134: irem
    //   135: iload 7
    //   137: if_icmpeq +15 -> 152
    //   140: invokestatic 65	kkkkkk/hhhhhb:bШ042804280428ШШ042804280428Ш	()I
    //   143: putstatic 56	kkkkkk/hhhhhb:bщщ04490449044904490449щ0449	I
    //   146: invokestatic 65	kkkkkk/hhhhhb:bШ042804280428ШШ042804280428Ш	()I
    //   149: putstatic 67	kkkkkk/hhhhhb:b0449щ04490449044904490449щ0449	I
    //   152: new 242	java/io/ByteArrayOutputStream
    //   155: dup
    //   156: invokespecial 243	java/io/ByteArrayOutputStream:<init>	()V
    //   159: astore 8
    //   161: aload_0
    //   162: aload_2
    //   163: iload_1
    //   164: aload 8
    //   166: invokevirtual 255	android/graphics/Bitmap:compress	(Landroid/graphics/Bitmap$CompressFormat;ILjava/io/OutputStream;)Z
    //   169: pop
    //   170: aload 8
    //   172: invokevirtual 259	java/io/ByteArrayOutputStream:toByteArray	()[B
    //   175: astore_0
    //   176: aload 8
    //   178: invokevirtual 301	java/io/ByteArrayOutputStream:close	()V
    //   181: getstatic 56	kkkkkk/hhhhhb:bщщ04490449044904490449щ0449	I
    //   184: istore_1
    //   185: iload_1
    //   186: getstatic 58	kkkkkk/hhhhhb:bщ044904490449044904490449щ0449	I
    //   189: iload_1
    //   190: iadd
    //   191: imul
    //   192: getstatic 69	kkkkkk/hhhhhb:b0449044904490449044904490449щ0449	I
    //   195: irem
    //   196: tableswitch	default:+20->216, 0:+31->227
    //   216: bipush 36
    //   218: putstatic 56	kkkkkk/hhhhhb:bщщ04490449044904490449щ0449	I
    //   221: invokestatic 65	kkkkkk/hhhhhb:bШ042804280428ШШ042804280428Ш	()I
    //   224: putstatic 67	kkkkkk/hhhhhb:b0449щ04490449044904490449щ0449	I
    //   227: aload_0
    //   228: areturn
    //   229: astore_2
    //   230: aconst_null
    //   231: astore_0
    //   232: getstatic 77	kkkkkk/hhhhhb:b04490449щ0449044904490449щ0449	Ljava/lang/String;
    //   235: astore 8
    //   237: aload 8
    //   239: new 118	java/lang/StringBuilder
    //   242: dup
    //   243: invokespecial 119	java/lang/StringBuilder:<init>	()V
    //   246: ldc_w 303
    //   249: bipush 8
    //   251: bipush 73
    //   253: iconst_3
    //   254: invokestatic 52	kkkkkk/gguuuu:bк043Aккк043Aкк043A043A	(Ljava/lang/String;CCC)Ljava/lang/String;
    //   257: invokevirtual 125	java/lang/StringBuilder:append	(Ljava/lang/String;)Ljava/lang/StringBuilder;
    //   260: aload_2
    //   261: invokevirtual 306	java/io/IOException:getMessage	()Ljava/lang/String;
    //   264: invokevirtual 125	java/lang/StringBuilder:append	(Ljava/lang/String;)Ljava/lang/StringBuilder;
    //   267: invokevirtual 131	java/lang/StringBuilder:toString	()Ljava/lang/String;
    //   270: invokestatic 309	kkkkkk/xtxtxt:bии0438043804380438и0438ии	(Ljava/lang/String;Ljava/lang/String;)V
    //   273: goto -92 -> 181
    //   276: astore_0
    //   277: aload_0
    //   278: athrow
    //   279: astore_0
    //   280: aload_0
    //   281: athrow
    //   282: astore_2
    //   283: goto -51 -> 232
    // Local variable table:
    //   start	length	slot	name	signature
    //   0	286	0	paramBitmap	Bitmap
    //   0	286	1	paramInt	int
    //   0	286	2	paramString	String
    //   104	25	3	i	int
    //   108	21	4	j	int
    //   113	19	5	k	int
    //   118	17	6	m	int
    //   123	15	7	n	int
    //   3	235	8	localObject1	Object
    //   12	48	9	localObject2	Object
    // Exception table:
    //   from	to	target	type
    //   0	14	229	java/io/IOException
    //   14	31	229	java/io/IOException
    //   31	45	229	java/io/IOException
    //   45	56	229	java/io/IOException
    //   59	81	229	java/io/IOException
    //   81	86	229	java/io/IOException
    //   86	101	229	java/io/IOException
    //   152	176	229	java/io/IOException
    //   0	14	276	java/lang/Exception
    //   31	45	276	java/lang/Exception
    //   59	81	276	java/lang/Exception
    //   81	86	276	java/lang/Exception
    //   101	125	276	java/lang/Exception
    //   152	176	276	java/lang/Exception
    //   176	181	276	java/lang/Exception
    //   237	273	276	java/lang/Exception
    //   14	31	279	java/lang/Exception
    //   45	56	279	java/lang/Exception
    //   86	101	279	java/lang/Exception
    //   140	152	279	java/lang/Exception
    //   232	237	279	java/lang/Exception
    //   176	181	282	java/io/IOException
  }
  
  /* Error */
  @android.annotation.TargetApi(17)
  public static Bitmap b0428Ш04280428ШШ042804280428Ш(Context paramContext, Bitmap paramBitmap, int paramInt)
  {
    // Byte code:
    //   0: aload_1
    //   1: iload_2
    //   2: iload_2
    //   3: iconst_0
    //   4: invokestatic 318	android/graphics/Bitmap:createScaledBitmap	(Landroid/graphics/Bitmap;IIZ)Landroid/graphics/Bitmap;
    //   7: astore_3
    //   8: aload_3
    //   9: invokestatic 322	android/graphics/Bitmap:createBitmap	(Landroid/graphics/Bitmap;)Landroid/graphics/Bitmap;
    //   12: astore_1
    //   13: aload_0
    //   14: invokestatic 328	android/renderscript/RenderScript:create	(Landroid/content/Context;)Landroid/renderscript/RenderScript;
    //   17: astore 4
    //   19: iconst_0
    //   20: tableswitch	default:+24->44, 0:+51->71, 1:+-1->19
    //   44: iconst_1
    //   45: tableswitch	default:+23->68, 0:+-26->19, 1:+26->71
    //   68: goto -24 -> 44
    //   71: aload 4
    //   73: aload 4
    //   75: invokestatic 334	android/renderscript/Element:U8_4	(Landroid/renderscript/RenderScript;)Landroid/renderscript/Element;
    //   78: invokestatic 339	android/renderscript/ScriptIntrinsicBlur:create	(Landroid/renderscript/RenderScript;Landroid/renderscript/Element;)Landroid/renderscript/ScriptIntrinsicBlur;
    //   81: astore_0
    //   82: getstatic 56	kkkkkk/hhhhhb:bщщ04490449044904490449щ0449	I
    //   85: getstatic 58	kkkkkk/hhhhhb:bщ044904490449044904490449щ0449	I
    //   88: iadd
    //   89: getstatic 56	kkkkkk/hhhhhb:bщщ04490449044904490449щ0449	I
    //   92: imul
    //   93: getstatic 69	kkkkkk/hhhhhb:b0449044904490449044904490449щ0449	I
    //   96: irem
    //   97: invokestatic 342	kkkkkk/hhhhhb:bШШШ0428ШШ042804280428Ш	()I
    //   100: if_icmpeq +14 -> 114
    //   103: invokestatic 65	kkkkkk/hhhhhb:bШ042804280428ШШ042804280428Ш	()I
    //   106: putstatic 56	kkkkkk/hhhhhb:bщщ04490449044904490449щ0449	I
    //   109: bipush 81
    //   111: putstatic 67	kkkkkk/hhhhhb:b0449щ04490449044904490449щ0449	I
    //   114: aload 4
    //   116: aload_3
    //   117: invokestatic 348	android/renderscript/Allocation:createFromBitmap	(Landroid/renderscript/RenderScript;Landroid/graphics/Bitmap;)Landroid/renderscript/Allocation;
    //   120: astore_3
    //   121: aload 4
    //   123: aload_1
    //   124: invokestatic 348	android/renderscript/Allocation:createFromBitmap	(Landroid/renderscript/RenderScript;Landroid/graphics/Bitmap;)Landroid/renderscript/Allocation;
    //   127: astore 4
    //   129: aload_0
    //   130: ldc 31
    //   132: invokevirtual 352	android/renderscript/ScriptIntrinsicBlur:setRadius	(F)V
    //   135: getstatic 56	kkkkkk/hhhhhb:bщщ04490449044904490449щ0449	I
    //   138: getstatic 58	kkkkkk/hhhhhb:bщ044904490449044904490449щ0449	I
    //   141: iadd
    //   142: getstatic 56	kkkkkk/hhhhhb:bщщ04490449044904490449щ0449	I
    //   145: imul
    //   146: getstatic 69	kkkkkk/hhhhhb:b0449044904490449044904490449щ0449	I
    //   149: irem
    //   150: getstatic 67	kkkkkk/hhhhhb:b0449щ04490449044904490449щ0449	I
    //   153: if_icmpeq +13 -> 166
    //   156: iconst_1
    //   157: putstatic 56	kkkkkk/hhhhhb:bщщ04490449044904490449щ0449	I
    //   160: invokestatic 65	kkkkkk/hhhhhb:bШ042804280428ШШ042804280428Ш	()I
    //   163: putstatic 67	kkkkkk/hhhhhb:b0449щ04490449044904490449щ0449	I
    //   166: aload_0
    //   167: aload_3
    //   168: invokevirtual 356	android/renderscript/ScriptIntrinsicBlur:setInput	(Landroid/renderscript/Allocation;)V
    //   171: aload_0
    //   172: aload 4
    //   174: invokevirtual 359	android/renderscript/ScriptIntrinsicBlur:forEach	(Landroid/renderscript/Allocation;)V
    //   177: aload 4
    //   179: aload_1
    //   180: invokevirtual 363	android/renderscript/Allocation:copyTo	(Landroid/graphics/Bitmap;)V
    //   183: aload_1
    //   184: areturn
    //   185: astore_0
    //   186: aload_0
    //   187: athrow
    //   188: astore_0
    //   189: aload_0
    //   190: athrow
    // Local variable table:
    //   start	length	slot	name	signature
    //   0	191	0	paramContext	Context
    //   0	191	1	paramBitmap	Bitmap
    //   0	191	2	paramInt	int
    //   7	161	3	localObject1	Object
    //   17	161	4	localObject2	Object
    // Exception table:
    //   from	to	target	type
    //   0	19	185	java/lang/Exception
    //   82	114	185	java/lang/Exception
    //   121	135	185	java/lang/Exception
    //   171	183	185	java/lang/Exception
    //   71	82	188	java/lang/Exception
    //   114	121	188	java/lang/Exception
    //   166	171	188	java/lang/Exception
  }
  
  public static int b0428Ш0428Ш0428Ш042804280428Ш(int paramInt, boolean paramBoolean)
  {
    int j = 0;
    int i = j;
    switch (paramInt)
    {
    default: 
      i = j;
    }
    for (;;)
    {
      if ((bщщ04490449044904490449щ0449 + bщ044904490449044904490449щ0449) * bщщ04490449044904490449щ0449 % b0449044904490449044904490449щ0449 != b0449щ04490449044904490449щ0449)
      {
        bщщ04490449044904490449щ0449 = bШ042804280428ШШ042804280428Ш();
        b0449щ04490449044904490449щ0449 = 79;
      }
      return bШ0428042804280428Ш042804280428Ш(paramBoolean, i);
      i = 90;
      continue;
      i = 180;
      continue;
      i = j;
      if ((bщщ04490449044904490449щ0449 + bщ044904490449044904490449щ0449) * bщщ04490449044904490449щ0449 % b0449044904490449044904490449щ0449 != b0449щ04490449044904490449щ0449)
      {
        bщщ04490449044904490449щ0449 = 98;
        b0449щ04490449044904490449щ0449 = bШ042804280428ШШ042804280428Ш();
        i = j;
        continue;
        i = 270;
      }
    }
  }
  
  /* Error */
  @NonNull
  private static BitmapFactory.Options b0428ШШ04280428Ш042804280428Ш(String paramString)
  {
    // Byte code:
    //   0: new 375	android/graphics/BitmapFactory$Options
    //   3: dup
    //   4: invokespecial 376	android/graphics/BitmapFactory$Options:<init>	()V
    //   7: astore_2
    //   8: aload_2
    //   9: iconst_1
    //   10: putfield 380	android/graphics/BitmapFactory$Options:inJustDecodeBounds	Z
    //   13: getstatic 56	kkkkkk/hhhhhb:bщщ04490449044904490449щ0449	I
    //   16: istore_1
    //   17: iload_1
    //   18: getstatic 58	kkkkkk/hhhhhb:bщ044904490449044904490449щ0449	I
    //   21: iload_1
    //   22: iadd
    //   23: imul
    //   24: getstatic 69	kkkkkk/hhhhhb:b0449044904490449044904490449щ0449	I
    //   27: irem
    //   28: tableswitch	default:+20->48, 0:+126->154
    //   48: invokestatic 65	kkkkkk/hhhhhb:bШ042804280428ШШ042804280428Ш	()I
    //   51: istore_1
    //   52: iload_1
    //   53: getstatic 58	kkkkkk/hhhhhb:bщ044904490449044904490449щ0449	I
    //   56: iload_1
    //   57: iadd
    //   58: imul
    //   59: getstatic 69	kkkkkk/hhhhhb:b0449044904490449044904490449щ0449	I
    //   62: irem
    //   63: tableswitch	default:+17->80, 0:+28->91
    //   80: bipush 33
    //   82: putstatic 56	kkkkkk/hhhhhb:bщщ04490449044904490449щ0449	I
    //   85: invokestatic 65	kkkkkk/hhhhhb:bШ042804280428ШШ042804280428Ш	()I
    //   88: putstatic 67	kkkkkk/hhhhhb:b0449щ04490449044904490449щ0449	I
    //   91: iconst_0
    //   92: tableswitch	default:+24->116, 0:+51->143, 1:+-1->91
    //   116: iconst_1
    //   117: tableswitch	default:+23->140, 0:+-26->91, 1:+26->143
    //   140: goto -24 -> 116
    //   143: invokestatic 65	kkkkkk/hhhhhb:bШ042804280428ШШ042804280428Ш	()I
    //   146: putstatic 56	kkkkkk/hhhhhb:bщщ04490449044904490449щ0449	I
    //   149: bipush 73
    //   151: putstatic 67	kkkkkk/hhhhhb:b0449щ04490449044904490449щ0449	I
    //   154: aload_0
    //   155: aload_2
    //   156: invokestatic 386	android/graphics/BitmapFactory:decodeFile	(Ljava/lang/String;Landroid/graphics/BitmapFactory$Options;)Landroid/graphics/Bitmap;
    //   159: pop
    //   160: aload_2
    //   161: areturn
    //   162: astore_0
    //   163: aload_0
    //   164: athrow
    //   165: astore_0
    //   166: aload_0
    //   167: athrow
    // Local variable table:
    //   start	length	slot	name	signature
    //   0	168	0	paramString	String
    //   16	43	1	i	int
    //   7	154	2	localOptions	BitmapFactory.Options
    // Exception table:
    //   from	to	target	type
    //   0	13	162	java/lang/Exception
    //   154	160	165	java/lang/Exception
  }
  
  public static Bitmap b0428ШШ0428ШШ042804280428Ш(String paramString)
  {
    if ((bщщ04490449044904490449щ0449 + b0428042804280428ШШ042804280428Ш()) * bщщ04490449044904490449щ0449 % b0449044904490449044904490449щ0449 != b0449щ04490449044904490449щ0449)
    {
      bщщ04490449044904490449щ0449 = 70;
      b0449щ04490449044904490449щ0449 = 17;
    }
    switch (1)
    {
    case 0: 
    default: 
      for (;;)
      {
        switch (0)
        {
        }
      }
    }
    paramString = Base64.decode(paramString.getBytes(), 0);
    return BitmapFactory.decodeByteArray(paramString, 0, paramString.length);
  }
  
  /* Error */
  public static Bitmap b0428ШШШ0428Ш042804280428Ш(Context paramContext, String paramString, int paramInt1, int paramInt2)
  {
    // Byte code:
    //   0: aload_1
    //   1: invokestatic 228	android/text/TextUtils:isEmpty	(Ljava/lang/CharSequence;)Z
    //   4: ifeq +56 -> 60
    //   7: aconst_null
    //   8: areturn
    //   9: astore 4
    //   11: aload_0
    //   12: invokestatic 409	com/squareup/picasso/Picasso:with	(Landroid/content/Context;)Lcom/squareup/picasso/Picasso;
    //   15: aload_1
    //   16: invokevirtual 413	com/squareup/picasso/Picasso:load	(Ljava/lang/String;)Lcom/squareup/picasso/RequestCreator;
    //   19: invokevirtual 419	com/squareup/picasso/RequestCreator:get	()Landroid/graphics/Bitmap;
    //   22: astore_0
    //   23: aload_0
    //   24: areturn
    //   25: aload 4
    //   27: iload_2
    //   28: sipush 250
    //   31: invokestatic 425	java/lang/Math:max	(II)I
    //   34: iload_3
    //   35: sipush 250
    //   38: invokestatic 425	java/lang/Math:max	(II)I
    //   41: invokevirtual 429	com/squareup/picasso/RequestCreator:resize	(II)Lcom/squareup/picasso/RequestCreator;
    //   44: invokevirtual 433	com/squareup/picasso/RequestCreator:onlyScaleDown	()Lcom/squareup/picasso/RequestCreator;
    //   47: invokevirtual 419	com/squareup/picasso/RequestCreator:get	()Landroid/graphics/Bitmap;
    //   50: astore 4
    //   52: new 435	java/lang/NullPointerException
    //   55: dup
    //   56: invokespecial 436	java/lang/NullPointerException:<init>	()V
    //   59: athrow
    //   60: aload_0
    //   61: invokestatic 409	com/squareup/picasso/Picasso:with	(Landroid/content/Context;)Lcom/squareup/picasso/Picasso;
    //   64: aload_1
    //   65: invokevirtual 413	com/squareup/picasso/Picasso:load	(Ljava/lang/String;)Lcom/squareup/picasso/RequestCreator;
    //   68: astore 4
    //   70: iconst_0
    //   71: tableswitch	default:+21->92, 0:+-46->25, 1:+-1->70
    //   92: iconst_1
    //   93: tableswitch	default:+23->116, 0:+-23->70, 1:+-68->25
    //   116: goto -24 -> 92
    //   119: astore_0
    //   120: bipush 20
    //   122: putstatic 56	kkkkkk/hhhhhb:bщщ04490449044904490449щ0449	I
    //   125: aload 4
    //   127: areturn
    //   128: astore_0
    //   129: aconst_null
    //   130: areturn
    // Local variable table:
    //   start	length	slot	name	signature
    //   0	131	0	paramContext	Context
    //   0	131	1	paramString	String
    //   0	131	2	paramInt1	int
    //   0	131	3	paramInt2	int
    //   9	17	4	localException	Exception
    //   50	76	4	localObject	Object
    // Exception table:
    //   from	to	target	type
    //   25	52	9	java/lang/Exception
    //   60	70	9	java/lang/Exception
    //   52	60	119	java/lang/Exception
    //   11	23	128	java/lang/Exception
  }
  
  public static String b0428ШШШШ0428042804280428Ш(Context paramContext, byte[] paramArrayOfByte, String paramString1, String paramString2, hhhhhb.hbbbbh paramHbbbbh)
  {
    throw new Runtime("d2j fail translate: java.lang.IndexOutOfBoundsException: fromIndex < 0: -1\n\tat java.util.BitSet.nextSetBit(BitSet.java:712)\n\tat com.googlecode.dex2jar.ir.ts.array.FillArrayTransformer.makeSureAllElementAreAssigned(FillArrayTransformer.java:505)\n\tat com.googlecode.dex2jar.ir.ts.array.FillArrayTransformer.transformReportChanged(FillArrayTransformer.java:123)\n\tat com.googlecode.dex2jar.ir.ts.StatedTransformer.transform(StatedTransformer.java:10)\n\tat com.googlecode.d2j.dex.Dex2jar$2.optimize(Dex2jar.java:149)\n\tat com.googlecode.d2j.dex.Dex2Asm.convertCode(Dex2Asm.java:414)\n\tat com.googlecode.d2j.dex.ExDex2Asm.convertCode(ExDex2Asm.java:42)\n\tat com.googlecode.d2j.dex.Dex2jar$2.convertCode(Dex2jar.java:128)\n\tat com.googlecode.d2j.dex.Dex2Asm.convertMethod(Dex2Asm.java:509)\n\tat com.googlecode.d2j.dex.Dex2Asm.convertClass(Dex2Asm.java:406)\n\tat com.googlecode.d2j.dex.Dex2Asm.convertDex(Dex2Asm.java:422)\n\tat com.googlecode.d2j.dex.Dex2jar.doTranslate(Dex2jar.java:172)\n\tat com.googlecode.d2j.dex.Dex2jar.to(Dex2jar.java:272)\n\tat com.googlecode.dex2jar.tools.Dex2jarCmd.doCommandLine(Dex2jarCmd.java:108)\n\tat com.googlecode.dex2jar.tools.BaseCmd.doMain(BaseCmd.java:288)\n\tat com.googlecode.dex2jar.tools.Dex2jarCmd.main(Dex2jarCmd.java:32)\n");
  }
  
  /* Error */
  private static int bШ0428042804280428Ш042804280428Ш(boolean paramBoolean, int paramInt)
  {
    // Byte code:
    //   0: getstatic 443	android/os/Build:MANUFACTURER	Ljava/lang/String;
    //   3: astore_3
    //   4: iload_1
    //   5: istore_2
    //   6: iload_0
    //   7: ifne +146 -> 153
    //   10: ldc_w 445
    //   13: sipush 196
    //   16: iconst_2
    //   17: invokestatic 46	kkkkkk/gguuuu:bккккк043Aкк043A043A	(Ljava/lang/String;CC)Ljava/lang/String;
    //   20: astore 4
    //   22: getstatic 56	kkkkkk/hhhhhb:bщщ04490449044904490449щ0449	I
    //   25: getstatic 58	kkkkkk/hhhhhb:bщ044904490449044904490449щ0449	I
    //   28: iadd
    //   29: getstatic 56	kkkkkk/hhhhhb:bщщ04490449044904490449щ0449	I
    //   32: imul
    //   33: getstatic 69	kkkkkk/hhhhhb:b0449044904490449044904490449щ0449	I
    //   36: irem
    //   37: invokestatic 342	kkkkkk/hhhhhb:bШШШ0428ШШ042804280428Ш	()I
    //   40: if_icmpeq +98 -> 138
    //   43: getstatic 56	kkkkkk/hhhhhb:bщщ04490449044904490449щ0449	I
    //   46: getstatic 58	kkkkkk/hhhhhb:bщ044904490449044904490449щ0449	I
    //   49: iadd
    //   50: getstatic 56	kkkkkk/hhhhhb:bщщ04490449044904490449щ0449	I
    //   53: imul
    //   54: getstatic 69	kkkkkk/hhhhhb:b0449044904490449044904490449щ0449	I
    //   57: irem
    //   58: getstatic 67	kkkkkk/hhhhhb:b0449щ04490449044904490449щ0449	I
    //   61: if_icmpeq +14 -> 75
    //   64: invokestatic 65	kkkkkk/hhhhhb:bШ042804280428ШШ042804280428Ш	()I
    //   67: putstatic 56	kkkkkk/hhhhhb:bщщ04490449044904490449щ0449	I
    //   70: bipush 47
    //   72: putstatic 67	kkkkkk/hhhhhb:b0449щ04490449044904490449щ0449	I
    //   75: iconst_0
    //   76: tableswitch	default:+24->100, 0:+51->127, 1:+-1->75
    //   100: iconst_0
    //   101: tableswitch	default:+23->124, 0:+26->127, 1:+-26->75
    //   124: goto -24 -> 100
    //   127: invokestatic 65	kkkkkk/hhhhhb:bШ042804280428ШШ042804280428Ш	()I
    //   130: putstatic 56	kkkkkk/hhhhhb:bщщ04490449044904490449щ0449	I
    //   133: bipush 42
    //   135: putstatic 67	kkkkkk/hhhhhb:b0449щ04490449044904490449щ0449	I
    //   138: aload_3
    //   139: aload 4
    //   141: invokevirtual 449	java/lang/String:equalsIgnoreCase	(Ljava/lang/String;)Z
    //   144: istore_0
    //   145: iload_1
    //   146: istore_2
    //   147: iload_0
    //   148: ifeq +5 -> 153
    //   151: iconst_0
    //   152: istore_2
    //   153: iload_2
    //   154: ireturn
    //   155: astore_3
    //   156: aload_3
    //   157: athrow
    //   158: astore_3
    //   159: aload_3
    //   160: athrow
    // Local variable table:
    //   start	length	slot	name	signature
    //   0	161	0	paramBoolean	boolean
    //   0	161	1	paramInt	int
    //   5	149	2	i	int
    //   3	136	3	str1	String
    //   155	2	3	localException1	Exception
    //   158	2	3	localException2	Exception
    //   20	120	4	str2	String
    // Exception table:
    //   from	to	target	type
    //   0	4	155	java/lang/Exception
    //   10	22	155	java/lang/Exception
    //   138	145	158	java/lang/Exception
  }
  
  public static int bШ042804280428ШШ042804280428Ш()
  {
    return 9;
  }
  
  /* Error */
  public static void bШ04280428Ш0428Ш042804280428Ш()
  {
    // Byte code:
    //   0: new 112	java/io/File
    //   3: dup
    //   4: new 118	java/lang/StringBuilder
    //   7: dup
    //   8: invokespecial 119	java/lang/StringBuilder:<init>	()V
    //   11: getstatic 454	kkkkkk/xxdxxd:instance	Lkkkkkk/xxdxxd;
    //   14: invokevirtual 458	kkkkkk/xxdxxd:bххх044504450445х044504450445	()Landroid/content/Context;
    //   17: invokevirtual 186	android/content/Context:getFilesDir	()Ljava/io/File;
    //   20: invokevirtual 461	java/lang/StringBuilder:append	(Ljava/lang/Object;)Ljava/lang/StringBuilder;
    //   23: ldc_w 463
    //   26: sipush 243
    //   29: iconst_3
    //   30: invokestatic 46	kkkkkk/gguuuu:bккккк043Aкк043A043A	(Ljava/lang/String;CC)Ljava/lang/String;
    //   33: invokevirtual 125	java/lang/StringBuilder:append	(Ljava/lang/String;)Ljava/lang/StringBuilder;
    //   36: getstatic 81	kkkkkk/hhhhhb:bщ04490449щ044904490449щ0449	Ljava/lang/String;
    //   39: invokevirtual 125	java/lang/StringBuilder:append	(Ljava/lang/String;)Ljava/lang/StringBuilder;
    //   42: invokevirtual 131	java/lang/StringBuilder:toString	()Ljava/lang/String;
    //   45: invokespecial 464	java/io/File:<init>	(Ljava/lang/String;)V
    //   48: astore 5
    //   50: invokestatic 65	kkkkkk/hhhhhb:bШ042804280428ШШ042804280428Ш	()I
    //   53: getstatic 58	kkkkkk/hhhhhb:bщ044904490449044904490449щ0449	I
    //   56: iadd
    //   57: invokestatic 65	kkkkkk/hhhhhb:bШ042804280428ШШ042804280428Ш	()I
    //   60: imul
    //   61: getstatic 69	kkkkkk/hhhhhb:b0449044904490449044904490449щ0449	I
    //   64: irem
    //   65: getstatic 67	kkkkkk/hhhhhb:b0449щ04490449044904490449щ0449	I
    //   68: if_icmpeq +14 -> 82
    //   71: bipush 19
    //   73: putstatic 56	kkkkkk/hhhhhb:bщщ04490449044904490449щ0449	I
    //   76: invokestatic 65	kkkkkk/hhhhhb:bШ042804280428ШШ042804280428Ш	()I
    //   79: putstatic 67	kkkkkk/hhhhhb:b0449щ04490449044904490449щ0449	I
    //   82: getstatic 56	kkkkkk/hhhhhb:bщщ04490449044904490449щ0449	I
    //   85: istore_0
    //   86: getstatic 58	kkkkkk/hhhhhb:bщ044904490449044904490449щ0449	I
    //   89: istore_1
    //   90: getstatic 56	kkkkkk/hhhhhb:bщщ04490449044904490449щ0449	I
    //   93: istore_2
    //   94: invokestatic 62	kkkkkk/hhhhhb:b042804280428ШШШ042804280428Ш	()I
    //   97: istore_3
    //   98: getstatic 67	kkkkkk/hhhhhb:b0449щ04490449044904490449щ0449	I
    //   101: istore 4
    //   103: iload_0
    //   104: iload_1
    //   105: iadd
    //   106: iload_2
    //   107: imul
    //   108: iload_3
    //   109: irem
    //   110: iload 4
    //   112: if_icmpeq +14 -> 126
    //   115: bipush 22
    //   117: putstatic 56	kkkkkk/hhhhhb:bщщ04490449044904490449щ0449	I
    //   120: invokestatic 65	kkkkkk/hhhhhb:bШ042804280428ШШ042804280428Ш	()I
    //   123: putstatic 67	kkkkkk/hhhhhb:b0449щ04490449044904490449щ0449	I
    //   126: getstatic 77	kkkkkk/hhhhhb:b04490449щ0449044904490449щ0449	Ljava/lang/String;
    //   129: astore 6
    //   131: new 118	java/lang/StringBuilder
    //   134: dup
    //   135: invokespecial 119	java/lang/StringBuilder:<init>	()V
    //   138: ldc_w 466
    //   141: bipush 21
    //   143: iconst_1
    //   144: invokestatic 46	kkkkkk/gguuuu:bккккк043Aкк043A043A	(Ljava/lang/String;CC)Ljava/lang/String;
    //   147: invokevirtual 125	java/lang/StringBuilder:append	(Ljava/lang/String;)Ljava/lang/StringBuilder;
    //   150: astore 7
    //   152: aload 5
    //   154: invokevirtual 128	java/io/File:getAbsolutePath	()Ljava/lang/String;
    //   157: astore 8
    //   159: aload 7
    //   161: aload 8
    //   163: invokevirtual 125	java/lang/StringBuilder:append	(Ljava/lang/String;)Ljava/lang/StringBuilder;
    //   166: invokevirtual 131	java/lang/StringBuilder:toString	()Ljava/lang/String;
    //   169: astore 7
    //   171: iconst_1
    //   172: tableswitch	default:+24->196, 0:+-1->171, 1:+51->223
    //   196: iconst_1
    //   197: tableswitch	default:+23->220, 0:+-26->171, 1:+26->223
    //   220: goto -24 -> 196
    //   223: aload 6
    //   225: aload 7
    //   227: invokestatic 137	kkkkkk/xtxtxt:bии0438и04380438и0438ии	(Ljava/lang/String;Ljava/lang/String;)V
    //   230: aload 5
    //   232: invokestatic 145	kkkkkk/hhhhhb:b042804280428Ш0428Ш042804280428Ш	(Ljava/io/File;)V
    //   235: return
    //   236: astore 5
    //   238: aload 5
    //   240: athrow
    //   241: astore 5
    //   243: aload 5
    //   245: athrow
    // Local variable table:
    //   start	length	slot	name	signature
    //   85	21	0	i	int
    //   89	17	1	j	int
    //   93	15	2	k	int
    //   97	13	3	m	int
    //   101	12	4	n	int
    //   48	183	5	localFile	File
    //   236	3	5	localException1	Exception
    //   241	3	5	localException2	Exception
    //   129	95	6	str1	String
    //   150	76	7	localObject	Object
    //   157	5	8	str2	String
    // Exception table:
    //   from	to	target	type
    //   0	50	236	java/lang/Exception
    //   82	103	236	java/lang/Exception
    //   131	159	236	java/lang/Exception
    //   223	235	236	java/lang/Exception
    //   115	126	241	java/lang/Exception
    //   126	131	241	java/lang/Exception
    //   159	171	241	java/lang/Exception
  }
  
  @Nullable
  public static File bШ0428Ш04280428Ш042804280428Ш(Context paramContext, String paramString1, String paramString2)
  {
    File localFile = new File(paramContext.getApplicationContext().getFilesDir() + paramString1);
    switch (0)
    {
    case 1: 
    default: 
      for (;;)
      {
        switch (0)
        {
        }
      }
    }
    int i = bщщ04490449044904490449щ0449;
    switch (i * (bщ044904490449044904490449щ0449 + i) % b0449044904490449044904490449щ0449)
    {
    default: 
      bщщ04490449044904490449щ0449 = 77;
      b0449щ04490449044904490449щ0449 = bШ042804280428ШШ042804280428Ш();
      if ((bщщ04490449044904490449щ0449 + bщ044904490449044904490449щ0449) * bщщ04490449044904490449щ0449 % b0449044904490449044904490449щ0449 != b0449щ04490449044904490449щ0449)
      {
        bщщ04490449044904490449щ0449 = 8;
        b0449щ04490449044904490449щ0449 = bШ042804280428ШШ042804280428Ш();
      }
      break;
    }
    paramString1 = new File(localFile, paramString2);
    switch (0)
    {
    case 1: 
    default: 
      for (;;)
      {
        switch (1)
        {
        }
      }
    }
    paramContext = paramString1;
    if (!localFile.exists())
    {
      paramContext = paramString1;
      if (!localFile.mkdirs())
      {
        xtxtxt.b0438и0438и04380438и0438ии(b04490449щ0449044904490449щ0449, gguuuu.bккккк043Aкк043A043A("\005s\nyW\f\006z\013o\fa\b\023\f[Bl\022\007\016\rH\020\032\030\021\023!O\024!( \031U%'-Y\035!\\!1%\"6((", 'Ç', '\004'));
        paramContext = null;
      }
    }
    return paramContext;
  }
  
  /* Error */
  public static byte[] bШ0428Ш0428ШШ042804280428Ш(String paramString)
  {
    // Byte code:
    //   0: getstatic 56	kkkkkk/hhhhhb:bщщ04490449044904490449щ0449	I
    //   3: getstatic 58	kkkkkk/hhhhhb:bщ044904490449044904490449щ0449	I
    //   6: iadd
    //   7: getstatic 56	kkkkkk/hhhhhb:bщщ04490449044904490449щ0449	I
    //   10: imul
    //   11: getstatic 69	kkkkkk/hhhhhb:b0449044904490449044904490449щ0449	I
    //   14: irem
    //   15: getstatic 67	kkkkkk/hhhhhb:b0449щ04490449044904490449щ0449	I
    //   18: if_icmpeq +13 -> 31
    //   21: bipush 73
    //   23: putstatic 56	kkkkkk/hhhhhb:bщщ04490449044904490449щ0449	I
    //   26: bipush 95
    //   28: putstatic 67	kkkkkk/hhhhhb:b0449щ04490449044904490449щ0449	I
    //   31: aload_0
    //   32: ifnull +44 -> 76
    //   35: getstatic 77	kkkkkk/hhhhhb:b04490449щ0449044904490449щ0449	Ljava/lang/String;
    //   38: ldc_w 482
    //   41: bipush 45
    //   43: iconst_1
    //   44: invokestatic 46	kkkkkk/gguuuu:bккккк043Aкк043A043A	(Ljava/lang/String;CC)Ljava/lang/String;
    //   47: invokestatic 137	kkkkkk/xtxtxt:bии0438и04380438и0438ии	(Ljava/lang/String;Ljava/lang/String;)V
    //   50: aload_0
    //   51: ldc_w 484
    //   54: sipush 229
    //   57: iconst_3
    //   58: invokestatic 46	kkkkkk/gguuuu:bккккк043Aкк043A043A	(Ljava/lang/String;CC)Ljava/lang/String;
    //   61: ldc_w 486
    //   64: invokevirtual 490	java/lang/String:replaceFirst	(Ljava/lang/String;Ljava/lang/String;)Ljava/lang/String;
    //   67: astore_0
    //   68: aload_0
    //   69: iconst_0
    //   70: invokestatic 493	android/util/Base64:decode	(Ljava/lang/String;I)[B
    //   73: astore_0
    //   74: aload_0
    //   75: areturn
    //   76: aconst_null
    //   77: astore_0
    //   78: getstatic 56	kkkkkk/hhhhhb:bщщ04490449044904490449щ0449	I
    //   81: istore_1
    //   82: getstatic 58	kkkkkk/hhhhhb:bщ044904490449044904490449щ0449	I
    //   85: istore_2
    //   86: getstatic 56	kkkkkk/hhhhhb:bщщ04490449044904490449щ0449	I
    //   89: istore_3
    //   90: iload_1
    //   91: iload_2
    //   92: iadd
    //   93: iload_3
    //   94: imul
    //   95: getstatic 69	kkkkkk/hhhhhb:b0449044904490449044904490449щ0449	I
    //   98: irem
    //   99: getstatic 67	kkkkkk/hhhhhb:b0449щ04490449044904490449щ0449	I
    //   102: if_icmpeq -28 -> 74
    //   105: bipush 60
    //   107: putstatic 56	kkkkkk/hhhhhb:bщщ04490449044904490449щ0449	I
    //   110: bipush 57
    //   112: putstatic 67	kkkkkk/hhhhhb:b0449щ04490449044904490449щ0449	I
    //   115: aconst_null
    //   116: areturn
    //   117: astore_0
    //   118: aload_0
    //   119: athrow
    //   120: astore_0
    //   121: aload_0
    //   122: athrow
    //   123: astore_0
    //   124: aload_0
    //   125: athrow
    //   126: astore_0
    //   127: aload_0
    //   128: athrow
    // Local variable table:
    //   start	length	slot	name	signature
    //   0	129	0	paramString	String
    //   81	12	1	i	int
    //   85	8	2	j	int
    //   89	6	3	k	int
    // Exception table:
    //   from	to	target	type
    //   90	115	117	java/lang/Exception
    //   121	123	117	java/lang/Exception
    //   124	126	117	java/lang/Exception
    //   35	50	120	java/lang/Exception
    //   50	68	120	java/lang/Exception
    //   68	74	123	java/lang/Exception
    //   78	90	126	java/lang/Exception
  }
  
  public static Uri bШ0428ШШ0428Ш042804280428Ш(Context paramContext, String paramString)
    throws IOException
  {
    paramString = new File(paramContext.getFilesDir(), bщ04490449щ044904490449щ0449 + paramString + gguuuu.bккккк043Aкк043A043A("*", 'Ò', '\001') + b0449щ0449щ044904490449щ0449);
    paramString.mkdirs();
    Object localObject = new StringBuilder().append(xxdxxd.b04450445х044504450445х044504450445()).append(paramContext.getApplicationInfo().packageName);
    if ((bщщ04490449044904490449щ0449 + bщ044904490449044904490449щ0449) * bщщ04490449044904490449щ0449 % b042804280428ШШШ042804280428Ш() != b0449щ04490449044904490449щ0449)
    {
      switch (0)
      {
      case 1: 
      default: 
        for (;;)
        {
          switch (0)
          {
          }
        }
      }
      bщщ04490449044904490449щ0449 = 81;
      b0449щ04490449044904490449щ0449 = 83;
    }
    localObject = ((StringBuilder)localObject).toString();
    int i = bщщ04490449044904490449щ0449;
    switch (i * (b0428042804280428ШШ042804280428Ш() + i) % b0449044904490449044904490449щ0449)
    {
    default: 
      bщщ04490449044904490449щ0449 = 43;
      b0449щ04490449044904490449щ0449 = 89;
    }
    return FileProvider.getUriForFile(paramContext, (String)localObject, File.createTempFile(gguuuu.bккккк043Aкк043A043A("AF;BA", 'k', '\004'), gguuuu.bккккк043Aкк043A043A("$_dZ", '\005', '\003'), paramString));
  }
  
  /* Error */
  public static String bШ0428ШШШ0428042804280428Ш(byte[] paramArrayOfByte, File paramFile)
  {
    // Byte code:
    //   0: aconst_null
    //   1: astore 5
    //   3: getstatic 77	kkkkkk/hhhhhb:b04490449щ0449044904490449щ0449	Ljava/lang/String;
    //   6: new 118	java/lang/StringBuilder
    //   9: dup
    //   10: invokespecial 119	java/lang/StringBuilder:<init>	()V
    //   13: ldc_w 517
    //   16: sipush 244
    //   19: iconst_1
    //   20: invokestatic 46	kkkkkk/gguuuu:bккккк043Aкк043A043A	(Ljava/lang/String;CC)Ljava/lang/String;
    //   23: invokevirtual 125	java/lang/StringBuilder:append	(Ljava/lang/String;)Ljava/lang/StringBuilder;
    //   26: aload_1
    //   27: invokevirtual 128	java/io/File:getAbsolutePath	()Ljava/lang/String;
    //   30: invokevirtual 125	java/lang/StringBuilder:append	(Ljava/lang/String;)Ljava/lang/StringBuilder;
    //   33: invokevirtual 131	java/lang/StringBuilder:toString	()Ljava/lang/String;
    //   36: invokestatic 137	kkkkkk/xtxtxt:bии0438и04380438и0438ии	(Ljava/lang/String;Ljava/lang/String;)V
    //   39: new 519	java/io/FileOutputStream
    //   42: dup
    //   43: aload_1
    //   44: invokespecial 521	java/io/FileOutputStream:<init>	(Ljava/io/File;)V
    //   47: astore_3
    //   48: aload_3
    //   49: aload_0
    //   50: invokevirtual 525	java/io/FileOutputStream:write	([B)V
    //   53: aload_3
    //   54: ifnull +7 -> 61
    //   57: aload_3
    //   58: invokevirtual 526	java/io/FileOutputStream:close	()V
    //   61: getstatic 77	kkkkkk/hhhhhb:b04490449щ0449044904490449щ0449	Ljava/lang/String;
    //   64: new 118	java/lang/StringBuilder
    //   67: dup
    //   68: invokespecial 119	java/lang/StringBuilder:<init>	()V
    //   71: ldc_w 528
    //   74: bipush 71
    //   76: iconst_0
    //   77: invokestatic 46	kkkkkk/gguuuu:bккккк043Aкк043A043A	(Ljava/lang/String;CC)Ljava/lang/String;
    //   80: invokevirtual 125	java/lang/StringBuilder:append	(Ljava/lang/String;)Ljava/lang/StringBuilder;
    //   83: aload_1
    //   84: invokevirtual 128	java/io/File:getAbsolutePath	()Ljava/lang/String;
    //   87: invokevirtual 125	java/lang/StringBuilder:append	(Ljava/lang/String;)Ljava/lang/StringBuilder;
    //   90: invokevirtual 131	java/lang/StringBuilder:toString	()Ljava/lang/String;
    //   93: invokestatic 137	kkkkkk/xtxtxt:bии0438и04380438и0438ии	(Ljava/lang/String;Ljava/lang/String;)V
    //   96: aload_1
    //   97: invokevirtual 128	java/io/File:getAbsolutePath	()Ljava/lang/String;
    //   100: astore_0
    //   101: aload_0
    //   102: areturn
    //   103: astore_0
    //   104: ldc_w 530
    //   107: sipush 150
    //   110: iconst_1
    //   111: invokestatic 46	kkkkkk/gguuuu:bккккк043Aкк043A043A	(Ljava/lang/String;CC)Ljava/lang/String;
    //   114: astore_1
    //   115: getstatic 56	kkkkkk/hhhhhb:bщщ04490449044904490449щ0449	I
    //   118: getstatic 58	kkkkkk/hhhhhb:bщ044904490449044904490449щ0449	I
    //   121: iadd
    //   122: getstatic 56	kkkkkk/hhhhhb:bщщ04490449044904490449щ0449	I
    //   125: imul
    //   126: invokestatic 62	kkkkkk/hhhhhb:b042804280428ШШШ042804280428Ш	()I
    //   129: irem
    //   130: invokestatic 342	kkkkkk/hhhhhb:bШШШ0428ШШ042804280428Ш	()I
    //   133: if_icmpeq +13 -> 146
    //   136: bipush 23
    //   138: putstatic 56	kkkkkk/hhhhhb:bщщ04490449044904490449щ0449	I
    //   141: bipush 38
    //   143: putstatic 67	kkkkkk/hhhhhb:b0449щ04490449044904490449щ0449	I
    //   146: aload_1
    //   147: aload_0
    //   148: invokestatic 534	kkkkkk/xtxtxt:bи04380438и04380438и0438ии	(Ljava/lang/String;Ljava/lang/Throwable;)V
    //   151: aconst_null
    //   152: areturn
    //   153: astore_1
    //   154: aconst_null
    //   155: astore_3
    //   156: aload_3
    //   157: astore_0
    //   158: ldc_w 536
    //   161: bipush 47
    //   163: iconst_5
    //   164: invokestatic 46	kkkkkk/gguuuu:bккккк043Aкк043A043A	(Ljava/lang/String;CC)Ljava/lang/String;
    //   167: aload_1
    //   168: invokestatic 534	kkkkkk/xtxtxt:bи04380438и04380438и0438ии	(Ljava/lang/String;Ljava/lang/Throwable;)V
    //   171: aload 5
    //   173: astore_0
    //   174: aload_3
    //   175: ifnull -74 -> 101
    //   178: aload_3
    //   179: invokevirtual 526	java/io/FileOutputStream:close	()V
    //   182: aconst_null
    //   183: areturn
    //   184: astore_0
    //   185: ldc_w 538
    //   188: bipush 50
    //   190: iconst_0
    //   191: invokestatic 46	kkkkkk/gguuuu:bккккк043Aкк043A043A	(Ljava/lang/String;CC)Ljava/lang/String;
    //   194: aload_0
    //   195: invokestatic 534	kkkkkk/xtxtxt:bи04380438и04380438и0438ии	(Ljava/lang/String;Ljava/lang/Throwable;)V
    //   198: aconst_null
    //   199: areturn
    //   200: astore 4
    //   202: aconst_null
    //   203: astore_3
    //   204: aload_3
    //   205: astore_0
    //   206: aload 4
    //   208: invokevirtual 541	java/io/IOException:printStackTrace	()V
    //   211: aload_3
    //   212: ifnull -151 -> 61
    //   215: iconst_0
    //   216: tableswitch	default:+24->240, 0:+51->267, 1:+-1->215
    //   240: iconst_0
    //   241: tableswitch	default:+23->264, 0:+26->267, 1:+-26->215
    //   264: goto -24 -> 240
    //   267: aload_3
    //   268: invokevirtual 526	java/io/FileOutputStream:close	()V
    //   271: goto -210 -> 61
    //   274: astore_0
    //   275: ldc_w 543
    //   278: sipush 132
    //   281: iconst_2
    //   282: invokestatic 46	kkkkkk/gguuuu:bккккк043Aкк043A043A	(Ljava/lang/String;CC)Ljava/lang/String;
    //   285: aload_0
    //   286: invokestatic 534	kkkkkk/xtxtxt:bи04380438и04380438и0438ии	(Ljava/lang/String;Ljava/lang/Throwable;)V
    //   289: aconst_null
    //   290: areturn
    //   291: astore_1
    //   292: aload_3
    //   293: astore_0
    //   294: aload_0
    //   295: ifnull +7 -> 302
    //   298: aload_0
    //   299: invokevirtual 526	java/io/FileOutputStream:close	()V
    //   302: aload_1
    //   303: athrow
    //   304: astore_0
    //   305: ldc_w 545
    //   308: sipush 183
    //   311: iconst_2
    //   312: invokestatic 46	kkkkkk/gguuuu:bккккк043Aкк043A043A	(Ljava/lang/String;CC)Ljava/lang/String;
    //   315: aload_0
    //   316: invokestatic 534	kkkkkk/xtxtxt:bи04380438и04380438и0438ии	(Ljava/lang/String;Ljava/lang/Throwable;)V
    //   319: getstatic 56	kkkkkk/hhhhhb:bщщ04490449044904490449щ0449	I
    //   322: istore_2
    //   323: aload 5
    //   325: astore_0
    //   326: iload_2
    //   327: getstatic 58	kkkkkk/hhhhhb:bщ044904490449044904490449щ0449	I
    //   330: iload_2
    //   331: iadd
    //   332: imul
    //   333: getstatic 69	kkkkkk/hhhhhb:b0449044904490449044904490449щ0449	I
    //   336: irem
    //   337: tableswitch	default:+19->356, 0:+-236->101
    //   356: bipush 75
    //   358: putstatic 56	kkkkkk/hhhhhb:bщщ04490449044904490449щ0449	I
    //   361: bipush 84
    //   363: putstatic 67	kkkkkk/hhhhhb:b0449щ04490449044904490449щ0449	I
    //   366: aconst_null
    //   367: areturn
    //   368: astore_1
    //   369: goto -213 -> 156
    //   372: astore 4
    //   374: goto -170 -> 204
    //   377: astore_1
    //   378: aconst_null
    //   379: astore_0
    //   380: goto -86 -> 294
    //   383: astore_1
    //   384: goto -90 -> 294
    // Local variable table:
    //   start	length	slot	name	signature
    //   0	387	0	paramArrayOfByte	byte[]
    //   0	387	1	paramFile	File
    //   322	11	2	i	int
    //   47	246	3	localFileOutputStream	java.io.FileOutputStream
    //   200	7	4	localIOException1	IOException
    //   372	1	4	localIOException2	IOException
    //   1	323	5	localObject	Object
    // Exception table:
    //   from	to	target	type
    //   57	61	103	java/io/IOException
    //   39	48	153	java/io/FileNotFoundException
    //   178	182	184	java/io/IOException
    //   39	48	200	java/io/IOException
    //   267	271	274	java/io/IOException
    //   48	53	291	finally
    //   298	302	304	java/io/IOException
    //   48	53	368	java/io/FileNotFoundException
    //   48	53	372	java/io/IOException
    //   39	48	377	finally
    //   158	171	383	finally
    //   206	211	383	finally
  }
  
  /* Error */
  public static int bШШ042804280428Ш042804280428Ш(String paramString, boolean paramBoolean)
  {
    // Byte code:
    //   0: iconst_5
    //   1: istore_3
    //   2: new 549	android/media/ExifInterface
    //   5: dup
    //   6: aload_0
    //   7: invokespecial 550	android/media/ExifInterface:<init>	(Ljava/lang/String;)V
    //   10: ldc_w 552
    //   13: bipush 103
    //   15: sipush 252
    //   18: iconst_2
    //   19: invokestatic 52	kkkkkk/gguuuu:bк043Aккк043Aкк043A043A	(Ljava/lang/String;CCC)Ljava/lang/String;
    //   22: iconst_1
    //   23: invokevirtual 556	android/media/ExifInterface:getAttributeInt	(Ljava/lang/String;I)I
    //   26: iload_1
    //   27: invokestatic 558	kkkkkk/hhhhhb:b0428Ш0428Ш0428Ш042804280428Ш	(IZ)I
    //   30: istore_2
    //   31: iload_2
    //   32: ireturn
    //   33: astore_0
    //   34: getstatic 77	kkkkkk/hhhhhb:b04490449щ0449044904490449щ0449	Ljava/lang/String;
    //   37: ldc_w 560
    //   40: sipush 188
    //   43: iconst_0
    //   44: invokestatic 46	kkkkkk/gguuuu:bккккк043Aкк043A043A	(Ljava/lang/String;CC)Ljava/lang/String;
    //   47: invokestatic 563	kkkkkk/xtxtxt:bиии043804380438и0438ии	(Ljava/lang/String;Ljava/lang/String;)V
    //   50: invokestatic 65	kkkkkk/hhhhhb:bШ042804280428ШШ042804280428Ш	()I
    //   53: istore 4
    //   55: iload_3
    //   56: istore_2
    //   57: iload 4
    //   59: getstatic 58	kkkkkk/hhhhhb:bщ044904490449044904490449щ0449	I
    //   62: iload 4
    //   64: iadd
    //   65: imul
    //   66: invokestatic 62	kkkkkk/hhhhhb:b042804280428ШШШ042804280428Ш	()I
    //   69: irem
    //   70: tableswitch	default:+18->88, 0:+31->101
    //   88: bipush 7
    //   90: putstatic 56	kkkkkk/hhhhhb:bщщ04490449044904490449щ0449	I
    //   93: invokestatic 65	kkkkkk/hhhhhb:bШ042804280428ШШ042804280428Ш	()I
    //   96: putstatic 67	kkkkkk/hhhhhb:b0449щ04490449044904490449щ0449	I
    //   99: iload_3
    //   100: istore_2
    //   101: iload_2
    //   102: iconst_0
    //   103: idiv
    //   104: istore_3
    //   105: iload_3
    //   106: istore_2
    //   107: goto -6 -> 101
    //   110: astore_0
    //   111: bipush 23
    //   113: putstatic 56	kkkkkk/hhhhhb:bщщ04490449044904490449щ0449	I
    //   116: iload_2
    //   117: iconst_0
    //   118: idiv
    //   119: istore_2
    //   120: goto -4 -> 116
    //   123: astore_0
    //   124: invokestatic 65	kkkkkk/hhhhhb:bШ042804280428ШШ042804280428Ш	()I
    //   127: putstatic 56	kkkkkk/hhhhhb:bщщ04490449044904490449щ0449	I
    //   130: iconst_0
    //   131: ireturn
    // Local variable table:
    //   start	length	slot	name	signature
    //   0	132	0	paramString	String
    //   0	132	1	paramBoolean	boolean
    //   30	90	2	i	int
    //   1	105	3	j	int
    //   53	13	4	k	int
    // Exception table:
    //   from	to	target	type
    //   2	31	33	java/io/IOException
    //   101	105	110	java/lang/Exception
    //   116	120	123	java/lang/Exception
  }
  
  public static String bШШ04280428ШШ042804280428Ш(byte[] paramArrayOfByte)
  {
    String str = b04490449щ0449044904490449щ0449;
    StringBuilder localStringBuilder = new StringBuilder().append(gguuuu.bккккк043Aкк043A043A("QWaYLZ=W)GXI\031\026\033!GQI<JxK@P:\016r", '0', '\002'));
    if ((bщщ04490449044904490449щ0449 + bщ044904490449044904490449щ0449) * bщщ04490449044904490449щ0449 % b0449044904490449044904490449щ0449 != b0449щ04490449044904490449щ0449)
    {
      bщщ04490449044904490449щ0449 = 63;
      b0449щ04490449044904490449щ0449 = 94;
    }
    localStringBuilder = localStringBuilder.append(paramArrayOfByte.length / 1000).append(gguuuu.bк043Aккк043Aкк043A043A("\007QG", '', '~', '\000'));
    if ((bщщ04490449044904490449щ0449 + bщ044904490449044904490449щ0449) * bщщ04490449044904490449щ0449 % b0449044904490449044904490449щ0449 != b0449щ04490449044904490449щ0449)
    {
      bщщ04490449044904490449щ0449 = 53;
      b0449щ04490449044904490449щ0449 = 38;
    }
    xtxtxt.bии0438и04380438и0438ии(str, localStringBuilder.toString());
    return Base64.encodeToString(paramArrayOfByte, 0);
  }
  
  public static Bitmap bШШ0428Ш0428Ш042804280428Ш(Uri paramUri, int paramInt1, int paramInt2)
    throws IOException
  {
    Context localContext = xxdxxd.instance.bххх044504450445х044504450445();
    switch (0)
    {
    case 1: 
    default: 
      for (;;)
      {
        switch (1)
        {
        }
      }
    }
    int i = bщщ04490449044904490449щ0449;
    switch (i * (bщ044904490449044904490449щ0449 + i) % b0449044904490449044904490449щ0449)
    {
    default: 
      bщщ04490449044904490449щ0449 = bШ042804280428ШШ042804280428Ш();
      b0449щ04490449044904490449щ0449 = 68;
    }
    paramUri = Picasso.with(localContext).load(paramUri);
    i = bщщ04490449044904490449щ0449;
    switch (i * (bщ044904490449044904490449щ0449 + i) % b0449044904490449044904490449щ0449)
    {
    default: 
      bщщ04490449044904490449щ0449 = 68;
      b0449щ04490449044904490449щ0449 = bШ042804280428ШШ042804280428Ш();
    }
    return paramUri.resize(paramInt1, paramInt2).onlyScaleDown().get();
  }
  
  @NonNull
  public static Bitmap bШШШ04280428Ш042804280428Ш(String paramString)
  {
    paramString = BitmapFactory.decodeFile(paramString, new BitmapFactory.Options());
    switch (0)
    {
    case 1: 
    default: 
      for (;;)
      {
        switch (0)
        {
        }
      }
    }
    int i = paramString.getWidth();
    if ((bщщ04490449044904490449щ0449 + b0428042804280428ШШ042804280428Ш()) * bщщ04490449044904490449щ0449 % b0449044904490449044904490449щ0449 != b0449щ04490449044904490449щ0449)
    {
      bщщ04490449044904490449щ0449 = 34;
      b0449щ04490449044904490449щ0449 = 75;
    }
    int j = paramString.getHeight();
    if ((bщщ04490449044904490449щ0449 + bщ044904490449044904490449щ0449) * bщщ04490449044904490449щ0449 % b0449044904490449044904490449щ0449 != bШШШ0428ШШ042804280428Ш())
    {
      bщщ04490449044904490449щ0449 = 61;
      switch (0)
      {
      case 1: 
      default: 
        for (;;)
        {
          switch (0)
          {
          }
        }
      }
      b0449щ04490449044904490449щ0449 = bШ042804280428ШШ042804280428Ш();
    }
    return Bitmap.createScaledBitmap(paramString, i, j, true);
  }
  
  public static int bШШШ0428ШШ042804280428Ш()
  {
    return 0;
  }
  
  /* Error */
  public static Bitmap bШШШШ0428Ш042804280428Ш(Uri paramUri)
    throws IOException
  {
    // Byte code:
    //   0: getstatic 454	kkkkkk/xxdxxd:instance	Lkkkkkk/xxdxxd;
    //   3: invokevirtual 458	kkkkkk/xxdxxd:bххх044504450445х044504450445	()Landroid/content/Context;
    //   6: astore_1
    //   7: invokestatic 65	kkkkkk/hhhhhb:bШ042804280428ШШ042804280428Ш	()I
    //   10: getstatic 58	kkkkkk/hhhhhb:bщ044904490449044904490449щ0449	I
    //   13: iadd
    //   14: invokestatic 65	kkkkkk/hhhhhb:bШ042804280428ШШ042804280428Ш	()I
    //   17: imul
    //   18: getstatic 69	kkkkkk/hhhhhb:b0449044904490449044904490449щ0449	I
    //   21: irem
    //   22: getstatic 67	kkkkkk/hhhhhb:b0449щ04490449044904490449щ0449	I
    //   25: if_icmpeq +14 -> 39
    //   28: bipush 13
    //   30: putstatic 56	kkkkkk/hhhhhb:bщщ04490449044904490449щ0449	I
    //   33: invokestatic 65	kkkkkk/hhhhhb:bШ042804280428ШШ042804280428Ш	()I
    //   36: putstatic 67	kkkkkk/hhhhhb:b0449щ04490449044904490449щ0449	I
    //   39: aload_1
    //   40: invokestatic 409	com/squareup/picasso/Picasso:with	(Landroid/content/Context;)Lcom/squareup/picasso/Picasso;
    //   43: astore_1
    //   44: invokestatic 65	kkkkkk/hhhhhb:bШ042804280428ШШ042804280428Ш	()I
    //   47: getstatic 58	kkkkkk/hhhhhb:bщ044904490449044904490449щ0449	I
    //   50: iadd
    //   51: invokestatic 65	kkkkkk/hhhhhb:bШ042804280428ШШ042804280428Ш	()I
    //   54: imul
    //   55: getstatic 69	kkkkkk/hhhhhb:b0449044904490449044904490449щ0449	I
    //   58: irem
    //   59: invokestatic 342	kkkkkk/hhhhhb:bШШШ0428ШШ042804280428Ш	()I
    //   62: if_icmpeq +14 -> 76
    //   65: invokestatic 65	kkkkkk/hhhhhb:bШ042804280428ШШ042804280428Ш	()I
    //   68: putstatic 56	kkkkkk/hhhhhb:bщщ04490449044904490449щ0449	I
    //   71: bipush 68
    //   73: putstatic 67	kkkkkk/hhhhhb:b0449щ04490449044904490449щ0449	I
    //   76: aload_1
    //   77: aload_0
    //   78: invokevirtual 574	com/squareup/picasso/Picasso:load	(Landroid/net/Uri;)Lcom/squareup/picasso/RequestCreator;
    //   81: invokevirtual 419	com/squareup/picasso/RequestCreator:get	()Landroid/graphics/Bitmap;
    //   84: astore_0
    //   85: aload_0
    //   86: areturn
    //   87: astore_0
    //   88: iconst_1
    //   89: tableswitch	default:+23->112, 0:+-1->88, 1:+50->139
    //   112: iconst_1
    //   113: tableswitch	default:+23->136, 0:+-25->88, 1:+26->139
    //   136: goto -24 -> 112
    //   139: aload_0
    //   140: athrow
    //   141: astore_0
    //   142: aload_0
    //   143: athrow
    // Local variable table:
    //   start	length	slot	name	signature
    //   0	144	0	paramUri	Uri
    //   6	71	1	localObject	Object
    // Exception table:
    //   from	to	target	type
    //   0	7	87	java/lang/Exception
    //   76	85	87	java/lang/Exception
    //   39	44	141	java/lang/Exception
  }
  
  /* Error */
  public static String bШШШШШ0428042804280428Ш(Context paramContext, byte[] paramArrayOfByte, String paramString1, hhhhhb.hbbbbh paramHbbbbh, String paramString2)
  {
    // Byte code:
    //   0: aload 4
    //   2: astore 8
    //   4: aload 4
    //   6: ifnonnull +14 -> 20
    //   9: ldc_w 585
    //   12: bipush 115
    //   14: iconst_4
    //   15: invokestatic 46	kkkkkk/gguuuu:bккккк043Aкк043A043A	(Ljava/lang/String;CC)Ljava/lang/String;
    //   18: astore 8
    //   20: new 118	java/lang/StringBuilder
    //   23: dup
    //   24: invokespecial 119	java/lang/StringBuilder:<init>	()V
    //   27: astore 4
    //   29: aload 4
    //   31: invokestatic 591	java/util/UUID:randomUUID	()Ljava/util/UUID;
    //   34: invokevirtual 592	java/util/UUID:toString	()Ljava/lang/String;
    //   37: invokevirtual 125	java/lang/StringBuilder:append	(Ljava/lang/String;)Ljava/lang/StringBuilder;
    //   40: ldc_w 594
    //   43: bipush 80
    //   45: iconst_3
    //   46: invokestatic 46	kkkkkk/gguuuu:bккккк043Aкк043A043A	(Ljava/lang/String;CC)Ljava/lang/String;
    //   49: invokevirtual 125	java/lang/StringBuilder:append	(Ljava/lang/String;)Ljava/lang/StringBuilder;
    //   52: aload 8
    //   54: invokevirtual 125	java/lang/StringBuilder:append	(Ljava/lang/String;)Ljava/lang/StringBuilder;
    //   57: invokevirtual 131	java/lang/StringBuilder:toString	()Ljava/lang/String;
    //   60: astore 4
    //   62: aload_0
    //   63: aload_1
    //   64: aload_2
    //   65: aload 4
    //   67: aload_3
    //   68: invokestatic 596	kkkkkk/hhhhhb:b0428ШШШШ0428042804280428Ш	(Landroid/content/Context;[BLjava/lang/String;Ljava/lang/String;Lkkkkkk/hhhhhb$hbbbbh;)Ljava/lang/String;
    //   71: astore_0
    //   72: getstatic 56	kkkkkk/hhhhhb:bщщ04490449044904490449щ0449	I
    //   75: istore 5
    //   77: getstatic 58	kkkkkk/hhhhhb:bщ044904490449044904490449щ0449	I
    //   80: istore 6
    //   82: getstatic 56	kkkkkk/hhhhhb:bщщ04490449044904490449щ0449	I
    //   85: istore 7
    //   87: getstatic 56	kkkkkk/hhhhhb:bщщ04490449044904490449щ0449	I
    //   90: invokestatic 390	kkkkkk/hhhhhb:b0428042804280428ШШ042804280428Ш	()I
    //   93: iadd
    //   94: getstatic 56	kkkkkk/hhhhhb:bщщ04490449044904490449щ0449	I
    //   97: imul
    //   98: getstatic 69	kkkkkk/hhhhhb:b0449044904490449044904490449щ0449	I
    //   101: irem
    //   102: getstatic 67	kkkkkk/hhhhhb:b0449щ04490449044904490449щ0449	I
    //   105: if_icmpeq +15 -> 120
    //   108: invokestatic 65	kkkkkk/hhhhhb:bШ042804280428ШШ042804280428Ш	()I
    //   111: putstatic 56	kkkkkk/hhhhhb:bщщ04490449044904490449щ0449	I
    //   114: invokestatic 65	kkkkkk/hhhhhb:bШ042804280428ШШ042804280428Ш	()I
    //   117: putstatic 67	kkkkkk/hhhhhb:b0449щ04490449044904490449щ0449	I
    //   120: iload 5
    //   122: iload 6
    //   124: iadd
    //   125: iload 7
    //   127: imul
    //   128: getstatic 69	kkkkkk/hhhhhb:b0449044904490449044904490449щ0449	I
    //   131: irem
    //   132: getstatic 67	kkkkkk/hhhhhb:b0449щ04490449044904490449щ0449	I
    //   135: if_icmpeq +13 -> 148
    //   138: bipush 79
    //   140: putstatic 56	kkkkkk/hhhhhb:bщщ04490449044904490449щ0449	I
    //   143: bipush 31
    //   145: putstatic 67	kkkkkk/hhhhhb:b0449щ04490449044904490449щ0449	I
    //   148: aload_0
    //   149: areturn
    //   150: astore_0
    //   151: aload_0
    //   152: athrow
    //   153: astore_0
    //   154: aload_0
    //   155: athrow
    // Local variable table:
    //   start	length	slot	name	signature
    //   0	156	0	paramContext	Context
    //   0	156	1	paramArrayOfByte	byte[]
    //   0	156	2	paramString1	String
    //   0	156	3	paramHbbbbh	hhhhhb.hbbbbh
    //   0	156	4	paramString2	String
    //   75	50	5	i	int
    //   80	45	6	j	int
    //   85	43	7	k	int
    //   2	51	8	str	String
    // Exception table:
    //   from	to	target	type
    //   9	20	150	java/lang/Exception
    //   29	62	150	java/lang/Exception
    //   20	29	153	java/lang/Exception
    //   62	72	153	java/lang/Exception
  }
}
