package kkkkkk;

import android.content.Context;
import android.support.annotation.DrawableRes;
import android.support.annotation.NonNull;
import android.support.annotation.Nullable;
import android.support.annotation.StringRes;
import com.mobile.business.statements.model.AmountDomainModel;
import com.mobile.ui.R.drawable;
import com.mobile.ui.R.string;
import java.util.List;
import shaded.org.apache.commons.lang3.StringUtils;

public abstract class iippii
{
  public static int b043D043D043Dннн043D043Dн = 2;
  public static int b043Dн043Dннн043D043Dн = 15;
  private static final String b043Dнн043D043Dнн043Dн = "~\035)%X'\035U\b\027\"&\035\021\035\022";
  public static int bн043D043Dннн043D043Dн = 1;
  private static final String bн043Dн043D043Dнн043Dн = "\fk|";
  public static int bннн043Dнн043D043Dн;
  private String b043D043D043D043D043D043Dн043Dн;
  private String b043D043D043D043D043Dнн043Dн;
  private String b043D043D043D043Dн043Dн043Dн;
  private String b043D043D043Dн043D043Dн043Dн;
  private String b043D043D043Dнн043Dн043Dн;
  private String b043D043Dн043D043D043Dн043Dн;
  private String b043D043Dн043D043Dнн043Dн;
  private boolean b043D043Dн043Dн043Dн043Dн;
  private boolean b043D043Dнн043D043Dн043Dн;
  @Nullable
  private ippiip b043D043Dннн043Dн043Dн;
  private String b043D043Dнннн043D043Dн;
  @DrawableRes
  private int b043Dн043D043D043D043Dн043Dн;
  private String b043Dн043D043D043Dнн043Dн;
  private int b043Dн043D043Dн043Dн043Dн;
  private boolean b043Dн043Dн043D043Dн043Dн;
  private String b043Dн043Dнн043Dн043Dн;
  private String b043Dнн043D043D043Dн043Dн;
  private String b043Dнн043Dн043Dн043Dн;
  private boolean b043Dннн043D043Dн043Dн;
  private String b043Dнннн043Dн043Dн;
  private String b043Dннннн043D043Dн;
  private String bн043D043D043D043D043Dн043Dн;
  private String bн043D043D043D043Dнн043Dн;
  private String bн043D043D043Dн043Dн043Dн;
  private boolean bн043D043Dн043D043Dн043Dн;
  private String bн043D043Dнн043Dн043Dн;
  private String bн043Dн043D043D043Dн043Dн;
  private String bн043Dн043Dн043Dн043Dн;
  private boolean bн043Dнн043D043Dн043Dн;
  private List<String> bн043Dннн043Dн043Dн;
  private String bн043Dнннн043D043Dн;
  private String bнн043D043D043D043Dн043Dн;
  @StringRes
  private int bнн043D043D043Dнн043Dн;
  private boolean bнн043D043Dн043Dн043Dн;
  private boolean bнн043Dн043D043Dн043Dн;
  private ccrrcc bнн043Dнн043Dн043Dн;
  private String bнн043Dннн043D043Dн;
  private String bннн043D043D043Dн043Dн;
  private String bннн043Dн043Dн043Dн;
  private boolean bнннн043D043Dн043Dн;
  private String bннннн043Dн043Dн;
  private String bнннннн043D043Dн;
  
  /* Error */
  static
  {
    // Byte code:
    //   0: getstatic 75	kkkkkk/iippii:b043Dнн043D043Dнн043Dн	Ljava/lang/String;
    //   3: astore 5
    //   5: aload 5
    //   7: sipush 135
    //   10: sipush 195
    //   13: iconst_0
    //   14: invokestatic 81	kkkkkk/gguuuu:bк043Aккк043Aкк043A043A	(Ljava/lang/String;CCC)Ljava/lang/String;
    //   17: putstatic 75	kkkkkk/iippii:b043Dнн043D043Dнн043Dн	Ljava/lang/String;
    //   20: getstatic 83	kkkkkk/iippii:bн043Dн043D043Dнн043Dн	Ljava/lang/String;
    //   23: bipush 66
    //   25: iconst_5
    //   26: invokestatic 87	kkkkkk/gguuuu:bккккк043Aкк043A043A	(Ljava/lang/String;CC)Ljava/lang/String;
    //   29: astore 5
    //   31: getstatic 89	kkkkkk/iippii:b043Dн043Dннн043D043Dн	I
    //   34: istore_0
    //   35: getstatic 91	kkkkkk/iippii:bн043D043Dннн043D043Dн	I
    //   38: istore_1
    //   39: getstatic 89	kkkkkk/iippii:b043Dн043Dннн043D043Dн	I
    //   42: istore_2
    //   43: getstatic 89	kkkkkk/iippii:b043Dн043Dннн043D043Dн	I
    //   46: istore_3
    //   47: iload_3
    //   48: getstatic 91	kkkkkk/iippii:bн043D043Dннн043D043Dн	I
    //   51: iload_3
    //   52: iadd
    //   53: imul
    //   54: invokestatic 95	kkkkkk/iippii:b0430043004300430а0430а0430а0430	()I
    //   57: irem
    //   58: tableswitch	default:+18->76, 0:+30->88
    //   76: invokestatic 98	kkkkkk/iippii:bаааа04300430а0430а0430	()I
    //   79: putstatic 89	kkkkkk/iippii:b043Dн043Dннн043D043Dн	I
    //   82: invokestatic 98	kkkkkk/iippii:bаааа04300430а0430а0430	()I
    //   85: putstatic 100	kkkkkk/iippii:bннн043Dнн043D043Dн	I
    //   88: getstatic 102	kkkkkk/iippii:b043D043D043Dннн043D043Dн	I
    //   91: istore_3
    //   92: getstatic 100	kkkkkk/iippii:bннн043Dнн043D043Dн	I
    //   95: istore 4
    //   97: iload_0
    //   98: iload_1
    //   99: iadd
    //   100: iload_2
    //   101: imul
    //   102: iload_3
    //   103: irem
    //   104: iload 4
    //   106: if_icmpeq +14 -> 120
    //   109: invokestatic 98	kkkkkk/iippii:bаааа04300430а0430а0430	()I
    //   112: putstatic 89	kkkkkk/iippii:b043Dн043Dннн043D043Dн	I
    //   115: bipush 63
    //   117: putstatic 100	kkkkkk/iippii:bннн043Dнн043D043Dн	I
    //   120: aload 5
    //   122: putstatic 83	kkkkkk/iippii:bн043Dн043D043Dнн043Dн	Ljava/lang/String;
    //   125: return
    //   126: astore 5
    //   128: aload 5
    //   130: athrow
    //   131: astore 5
    //   133: aload 5
    //   135: athrow
    // Local variable table:
    //   start	length	slot	name	signature
    //   34	66	0	i	int
    //   38	62	1	j	int
    //   42	60	2	k	int
    //   46	58	3	m	int
    //   95	12	4	n	int
    //   3	118	5	str	String
    //   126	3	5	localException1	Exception
    //   131	3	5	localException2	Exception
    // Exception table:
    //   from	to	target	type
    //   5	43	126	java/lang/Exception
    //   88	97	126	java/lang/Exception
    //   120	125	126	java/lang/Exception
    //   0	5	131	java/lang/Exception
    //   109	120	131	java/lang/Exception
  }
  
  public iippii(Context paramContext, cccrcc paramCccrcc, boolean paramBoolean)
  {
    this.bнн043D043Dн043Dн043Dн = paramBoolean;
    this.bн043D043D043Dн043Dн043Dн = paramCccrcc.bжж0436ж0436жжж04360436();
    this.bннннн043Dн043Dн = paramCccrcc.b043604360436жжжжж04360436();
    this.b043Dнннн043Dн043Dн = paramCccrcc.bжжж0436жжжж04360436();
    this.bнн043Dнн043Dн043Dн = paramCccrcc.bжж04360436жжжж04360436();
    this.b043Dн043Dнн043Dн043Dн = b04300430аа04300430а0430а0430(paramContext, paramCccrcc.b0436ж04360436жжжж04360436(), mnmnmn.mmmnmn.NEGATIVE_ONLY);
    this.bн043D043Dнн043Dн043Dн = b04300430аа04300430а0430а0430(paramContext, paramCccrcc.bж043604360436жжжж04360436(), mnmnmn.mmmnmn.NEGATIVE_ONLY);
    this.bн043D043D043D043D043Dн043Dн = bа0430аа04300430а0430а0430(paramContext, paramCccrcc.bж04360436жж0436жж04360436(), mnmnmn.mmmnmn.NEGATIVE_ONLY);
    this.b043D043Dнннн043D043Dн = mnmnmn.b0418И0418И04180418ИИ04180418(paramCccrcc.b0436043604360436ж0436жж04360436());
    this.b043D043D043D043Dн043Dн043Dн = mnmnmn.b04180418ИИ04180418ИИ04180418(paramCccrcc.bж04360436ж0436жжж04360436());
    this.bн043Dнннн043D043Dн = bа0430аа04300430а0430а0430(paramContext, paramCccrcc.b0436ж04360436ж0436жж04360436(), mnmnmn.mmmnmn.NEGATIVE_ONLY);
    this.b043D043D043Dнн043Dн043Dн = b04300430аа04300430а0430а0430(paramContext, paramCccrcc.bж043604360436жжжж04360436(), mnmnmn.mmmnmn.CREDIT_AND_DEBIT);
    this.b043D043Dн043D043Dнн043Dн = mnmnmn.bИ0418И0418И0418ИИ04180418(paramCccrcc.bж043604360436жжжж04360436());
    Object localObject;
    if ((paramCccrcc.bж043604360436жжжж04360436() != null) && (paramCccrcc.bж043604360436жжжж04360436().getAmount() != null) && (paramCccrcc.bж043604360436жжжж04360436().getAmount().doubleValue() < 0.0D))
    {
      i = R.string.accessibility_arrangementtile_creditcard_balance_in_credit;
      this.bнн043D043D043Dнн043Dн = i;
      this.bннн043Dн043Dн043Dн = bа0430аа04300430а0430а0430(paramContext, paramCccrcc.bжжжж0436жжж04360436(), mnmnmn.mmmnmn.NEGATIVE_ONLY);
      this.b043Dнн043Dн043Dн043Dн = mnmnmn.bИИ04180418И0418ИИ04180418(paramCccrcc.b0436043604360436жжжж04360436());
      localObject = paramCccrcc.b0436жжж0436жжж04360436();
      if ((localObject == null) || (((AmountDomainModel)localObject).getAmount() == null) || (((AmountDomainModel)localObject).getAmount().doubleValue() <= 0.0D)) {
        break label564;
      }
      localObject = mnmnmn.bИИИ0418И0418ИИ04180418((AmountDomainModel)localObject);
      label266:
      this.b043D043D043D043D043D043Dн043Dн = ((String)localObject);
      this.b043D043D043Dн043D043Dн043Dн = mnmnmn.bИИ0418И04180418ИИ04180418(paramCccrcc.b0436жж04360436жжж04360436());
      this.bнн043D043D043D043Dн043Dн = bа0430аа04300430а0430а0430(paramContext, paramCccrcc.b04360436жжж0436жж04360436(), mnmnmn.mmmnmn.NEGATIVE_ONLY);
      this.b043Dн043D043D043Dнн043Dн = wbbwww.b04180418ИИИИ04180418И0418(paramCccrcc.b0436жж04360436жжж04360436());
      this.b043D043Dн043D043D043Dн043Dн = mnmnmn.bИИ0418И04180418ИИ04180418(paramCccrcc.bжж04360436ж0436жж04360436());
      this.b043Dнн043D043D043Dн043Dн = bа0430аа04300430а0430а0430(paramContext, paramCccrcc.b0436ж043604360436жжж04360436(), mnmnmn.mmmnmn.NEGATIVE_ONLY);
      this.bн043Dн043D043D043Dн043Dн = mnmnmn.b0418И04180418И0418ИИ04180418(paramCccrcc.bж0436043604360436жжж04360436());
      this.bннн043D043D043Dн043Dн = mnmnmn.b0418И04180418И0418ИИ04180418(paramCccrcc.b04360436ж04360436жжж04360436());
      if ((StringUtils.isEmpty(paramCccrcc.b0436ж0436жж0436жж04360436())) || (!paramCccrcc.b0436ж0436ж0436ж0436ж04360436())) {
        break label578;
      }
      paramBoolean = true;
      label378:
      this.b043D043Dнн043D043Dн043Dн = paramBoolean;
      if (!gguuuu.bккккк043Aкк043A043A("Nn|z0\001x3gx\006\f\005z\t", '\006', '\004').equals(paramCccrcc.b0436ж0436жж0436жж04360436())) {
        break label583;
      }
    }
    label564:
    label578:
    label583:
    for (int i = R.drawable.all_brand_bos_icon;; i = R.drawable.all_brand_halifax_icon)
    {
      this.b043Dн043D043D043D043Dн043Dн = i;
      paramBoolean = bool;
      if (paramCccrcc.bж04360436ж0436жжж04360436() != null)
      {
        paramBoolean = bool;
        if (paramCccrcc.bж04360436ж0436жжж04360436().b043F043F043Fпп043Fпппп()) {
          paramBoolean = true;
        }
      }
      this.b043Dннн043D043Dн043Dн = paramBoolean;
      bаа0430аа043004300430а0430(true);
      this.b043Dннннн043D043Dн = paramCccrcc.b04360436ж0436ж0436жж04360436();
      this.bн043Dннн043Dн043Dн = paramCccrcc.b0436жж0436жжжж04360436();
      this.bнннннн043D043Dн = paramCccrcc.bж0436ж0436ж0436жж04360436();
      this.bнн043Dннн043D043Dн = mnmnmn.b0418И04180418И0418ИИ04180418(paramCccrcc.bжжжж04360436жж04360436());
      this.bн043Dн043Dн043Dн043Dн = mnmnmn.b0418И04180418И0418ИИ04180418(paramCccrcc.bж0436жж0436жжж04360436());
      this.bнннн043D043Dн043Dн = paramCccrcc.bж043604360436жж0436ж04360436();
      this.b043Dн043D043Dн043Dн043Dн = paramCccrcc.b04360436жж0436жжж04360436();
      this.bн043D043D043D043Dнн043Dн = paramCccrcc.bж0436ж0436жжжж04360436();
      this.b043D043Dннн043Dн043Dн = bаа0430а04300430а0430а0430(paramCccrcc);
      this.bн043Dнн043D043Dн043Dн = paramCccrcc.b0436043604360436жж0436ж04360436();
      this.bнн043Dн043D043Dн043Dн = paramCccrcc.bжжжж0436ж0436ж04360436();
      this.b043D043Dн043Dн043Dн043Dн = bа0430а04300430а04300430а0430(paramCccrcc.bж04360436ж0436жжж04360436());
      return;
      i = R.string.accessibility_arrangementtile_creditcard_balance;
      break;
      localObject = gguuuu.bккккк043Aкк043A043A("{]p", 'V', '\004');
      break label266;
      paramBoolean = false;
      break label378;
    }
  }
  
  public iippii(String paramString)
  {
    this.b043D043D043D043D043Dнн043Dн = paramString;
  }
  
  public static int b0430043004300430а0430а0430а0430()
  {
    return 2;
  }
  
  private String b04300430аа04300430а0430а0430(Context paramContext, AmountDomainModel paramAmountDomainModel, mnmnmn.mmmnmn paramMmmnmn)
  {
    if (paramAmountDomainModel != null) {}
    try
    {
      if (paramAmountDomainModel.getAmount() == null) {
        break label84;
      }
      double d = paramAmountDomainModel.getAmount().doubleValue();
      int i = b043Dн043Dннн043D043Dн;
      switch (i * (bн043D043Dннн043D043Dн + i) % b043D043D043Dннн043D043Dн)
      {
      default: 
        b043Dн043Dннн043D043Dн = bаааа04300430а0430а0430();
        bннн043Dнн043D043Dн = 10;
      }
      if (d != 0.0D) {
        break label84;
      }
      paramContext = paramContext.getString(R.string.tile_arrangement_balance_zero);
    }
    catch (Exception paramContext)
    {
      try
      {
        do
        {
          paramAmountDomainModel = bа0430аа04300430а0430а0430(paramContext, paramAmountDomainModel, paramMmmnmn);
          paramContext = paramAmountDomainModel;
        } while ((bаааа04300430а0430а0430() + bн043D043Dннн043D043Dн) * bаааа04300430а0430а0430() % b0430043004300430а0430а0430а0430() == bннн043Dнн043D043Dн);
        b043Dн043Dннн043D043Dн = bаааа04300430а0430а0430();
        bннн043Dнн043D043Dн = 45;
        return paramAmountDomainModel;
      }
      catch (Exception paramContext)
      {
        throw paramContext;
      }
      paramContext = paramContext;
      throw paramContext;
    }
    return paramContext;
  }
  
  public static int b0430ааа04300430а0430а0430()
  {
    return 1;
  }
  
  public static int bа043004300430а0430а0430а0430()
  {
    return 0;
  }
  
  private boolean bа0430а04300430а04300430а0430(@Nullable crrrcc paramCrrrcc)
  {
    if (paramCrrrcc != null)
    {
      bool = paramCrrrcc.bп043F043Fпп043Fпппп();
      if ((b043Dн043Dннн043D043Dн + bн043D043Dннн043D043Dн) * b043Dн043Dннн043D043Dн % b043D043D043Dннн043D043Dн != bннн043Dнн043D043Dн)
      {
        b043Dн043Dннн043D043Dн = bаааа04300430а0430а0430();
        bннн043Dнн043D043Dн = bаааа04300430а0430а0430();
      }
      if (bool) {}
    }
    for (boolean bool = true;; bool = false)
    {
      switch (0)
      {
      case 1: 
      default: 
        for (;;)
        {
          switch (1)
          {
          }
        }
      }
      return bool;
      int i = b043Dн043Dннн043D043Dн;
      switch (i * (bн043D043Dннн043D043Dн + i) % b043D043D043Dннн043D043Dн)
      {
      default: 
        b043Dн043Dннн043D043Dн = bаааа04300430а0430а0430();
        bннн043Dнн043D043Dн = bаааа04300430а0430а0430();
      }
    }
  }
  
  private String bа0430аа04300430а0430а0430(Context paramContext, AmountDomainModel paramAmountDomainModel, mnmnmn.mmmnmn paramMmmnmn)
  {
    if (paramAmountDomainModel == null)
    {
      paramContext = paramContext.getString(R.string.tile_arrangement_balance_not_available);
      return paramContext;
    }
    paramAmountDomainModel = mnmnmn.b0418ИИ0418И0418ИИ04180418(paramAmountDomainModel, paramMmmnmn);
    int i = b043Dн043Dннн043D043Dн;
    paramContext = paramAmountDomainModel;
    switch (i * (bн043D043Dннн043D043Dн + i) % b043D043D043Dннн043D043Dн)
    {
    }
    b043Dн043Dннн043D043Dн = 33;
    bн043D043Dннн043D043Dн = bаааа04300430а0430а0430();
    return paramAmountDomainModel;
  }
  
  @Nullable
  private ippiip bаа0430а04300430а0430а0430(cccrcc paramCccrcc)
  {
    int j = 0;
    try
    {
      int i;
      if ((paramCccrcc.b0436ж0436ж04360436жж04360436()) && (paramCccrcc.bжжж04360436ж0436ж04360436())) {
        i = 1;
      }
      while (i != 0)
      {
        paramCccrcc = bаа0430а0430а04300430а0430(paramCccrcc);
        return paramCccrcc;
        i = j;
        if ((b043Dн043Dннн043D043Dн + bн043D043Dннн043D043Dн) * b043Dн043Dннн043D043Dн % b043D043D043Dннн043D043Dн != bннн043Dнн043D043Dн)
        {
          b043Dн043Dннн043D043Dн = 40;
          bннн043Dнн043D043Dн = bаааа04300430а0430а0430();
          switch (0)
          {
          case 1: 
          default: 
            for (;;)
            {
              switch (0)
              {
              }
            }
          }
          i = j;
          if ((bаааа04300430а0430а0430() + bн043D043Dннн043D043Dн) * bаааа04300430а0430а0430() % b043D043D043Dннн043D043Dн != bа043004300430а0430а0430а0430())
          {
            b043Dн043Dннн043D043Dн = bаааа04300430а0430а0430();
            bннн043Dнн043D043Dн = 40;
            i = j;
          }
        }
      }
      return null;
    }
    catch (Exception paramCccrcc)
    {
      throw paramCccrcc;
    }
  }
  
  @NonNull
  private static ipipii bаа0430а0430а04300430а0430(cccrcc paramCccrcc)
  {
    try
    {
      paramCccrcc = new ipipii(R.string.tile_arrangement_alert_dialog_reactivate_isa_title, paramCccrcc.bж0436ж0436жжжж04360436(), R.string.tile_arrangement_alert_dialog_reactivate_isa_negative_button, R.string.tile_arrangement_alert_dialog_reactivate_isa_positive_button);
      return paramCccrcc;
    }
    catch (Exception paramCccrcc)
    {
      throw paramCccrcc;
    }
  }
  
  public static int bаааа04300430а0430а0430()
  {
    return 40;
  }
  
  public ccrrcc b043004300430043004300430а0430а0430()
  {
    switch (1)
    {
    case 0: 
    default: 
      for (;;)
      {
        switch (1)
        {
        }
      }
    }
    if ((b043Dн043Dннн043D043Dн + bн043D043Dннн043D043Dн) * b043Dн043Dннн043D043Dн % b043D043D043Dннн043D043Dн != bннн043Dнн043D043Dн)
    {
      if ((b043Dн043Dннн043D043Dн + bн043D043Dннн043D043Dн) * b043Dн043Dннн043D043Dн % b0430043004300430а0430а0430а0430() != bннн043Dнн043D043Dн)
      {
        b043Dн043Dннн043D043Dн = 90;
        bннн043Dнн043D043Dн = 28;
      }
      b043Dн043Dннн043D043Dн = 23;
      bннн043Dнн043D043Dн = bаааа04300430а0430а0430();
    }
    switch (0)
    {
    case 1: 
    default: 
      for (;;)
      {
        switch (1)
        {
        }
      }
    }
    return this.bнн043Dнн043Dн043Dн;
  }
  
  public boolean b04300430043004300430а04300430а0430()
  {
    switch (0)
    {
    case 1: 
    default: 
      for (;;)
      {
        switch (0)
        {
        case 1: 
        default: 
          for (;;)
          {
            switch (0)
            {
            }
          }
        }
        switch (1)
        {
        }
      }
    }
    int i = bаааа04300430а0430а0430();
    switch (i * (b0430ааа04300430а0430а0430() + i) % b043D043D043Dннн043D043Dн)
    {
    default: 
      b043Dн043Dннн043D043Dн = bаааа04300430а0430а0430();
      bннн043Dнн043D043Dн = bаааа04300430а0430а0430();
    }
    boolean bool = this.bн043Dнн043D043Dн043Dн;
    i = b043Dн043Dннн043D043Dн;
    switch (i * (bн043D043Dннн043D043Dн + i) % b0430043004300430а0430а0430а0430())
    {
    default: 
      b043Dн043Dннн043D043Dн = 50;
      bннн043Dнн043D043Dн = 23;
    }
    return bool;
  }
  
  /* Error */
  @DrawableRes
  public int b0430043004300430аа04300430а0430()
  {
    // Byte code:
    //   0: aload_0
    //   1: getfield 314	kkkkkk/iippii:b043Dн043D043D043D043Dн043Dн	I
    //   4: istore_1
    //   5: getstatic 89	kkkkkk/iippii:b043Dн043Dннн043D043Dн	I
    //   8: istore_2
    //   9: getstatic 91	kkkkkk/iippii:bн043D043Dннн043D043Dн	I
    //   12: istore_3
    //   13: getstatic 102	kkkkkk/iippii:b043D043D043Dннн043D043Dн	I
    //   16: istore 4
    //   18: iload_2
    //   19: iload_3
    //   20: iload_2
    //   21: iadd
    //   22: imul
    //   23: iload 4
    //   25: irem
    //   26: tableswitch	default:+18->44, 0:+29->55
    //   44: invokestatic 98	kkkkkk/iippii:bаааа04300430а0430а0430	()I
    //   47: putstatic 89	kkkkkk/iippii:b043Dн043Dннн043D043Dн	I
    //   50: bipush 87
    //   52: putstatic 100	kkkkkk/iippii:bннн043Dнн043D043Dн	I
    //   55: iload_1
    //   56: ireturn
    //   57: astore 5
    //   59: aload 5
    //   61: athrow
    //   62: astore 5
    //   64: aload 5
    //   66: athrow
    // Local variable table:
    //   start	length	slot	name	signature
    //   0	67	0	this	iippii
    //   4	52	1	i	int
    //   8	15	2	j	int
    //   12	10	3	k	int
    //   16	10	4	m	int
    //   57	3	5	localException1	Exception
    //   62	3	5	localException2	Exception
    // Exception table:
    //   from	to	target	type
    //   0	18	57	java/lang/Exception
    //   44	55	62	java/lang/Exception
  }
  
  @StringRes
  public int b043004300430а04300430а0430а0430()
  {
    int i = b043Dн043Dннн043D043Dн;
    int j = bн043D043Dннн043D043Dн;
    if ((b043Dн043Dннн043D043Dн + bн043D043Dннн043D043Dн) * b043Dн043Dннн043D043Dн % b043D043D043Dннн043D043Dн != bннн043Dнн043D043Dн)
    {
      b043Dн043Dннн043D043Dн = 96;
      bннн043Dнн043D043Dн = 40;
    }
    switch (i * (j + i) % b043D043D043Dннн043D043Dн)
    {
    default: 
      b043Dн043Dннн043D043Dн = 98;
      bннн043Dнн043D043Dн = bаааа04300430а0430а0430();
    }
    try
    {
      i = this.bнн043D043D043Dнн043Dн;
      return i;
    }
    catch (Exception localException)
    {
      throw localException;
    }
  }
  
  public String b043004300430а0430а04300430а0430()
  {
    int i = b043Dн043Dннн043D043Dн;
    switch (i * (bн043D043Dннн043D043Dн + i) % b043D043D043Dннн043D043Dн)
    {
    default: 
      b043Dн043Dннн043D043Dн = 80;
      bннн043Dнн043D043Dн = 86;
    }
    return this.b043D043Dнннн043D043Dн;
  }
  
  public int b043004300430ааа04300430а0430()
  {
    int i = this.b043Dн043D043Dн043Dн043Dн;
    switch (1)
    {
    case 0: 
    default: 
      for (;;)
      {
        switch (1)
        {
        }
      }
    }
    int j = b043Dн043Dннн043D043Dн;
    int k = bн043D043Dннн043D043Dн;
    switch (1)
    {
    case 0: 
    default: 
      for (;;)
      {
        switch (0)
        {
        }
      }
    }
    int m = b043Dн043Dннн043D043Dн;
    switch (m * (bн043D043Dннн043D043Dн + m) % b043D043D043Dннн043D043Dн)
    {
    default: 
      b043Dн043Dннн043D043Dн = 27;
      bннн043Dнн043D043Dн = bаааа04300430а0430а0430();
    }
    if ((j + k) * b043Dн043Dннн043D043Dн % b0430043004300430а0430а0430а0430() != bннн043Dнн043D043Dн)
    {
      b043Dн043Dннн043D043Dн = 8;
      bннн043Dнн043D043Dн = bаааа04300430а0430а0430();
    }
    return i;
  }
  
  /* Error */
  @Nullable
  public String b04300430а043004300430а0430а0430()
  {
    // Byte code:
    //   0: aload_0
    //   1: getfield 399	kkkkkk/iippii:b043D043D043D043D043Dнн043Dн	Ljava/lang/String;
    //   4: astore 4
    //   6: invokestatic 98	kkkkkk/iippii:bаааа04300430а0430а0430	()I
    //   9: istore_1
    //   10: getstatic 91	kkkkkk/iippii:bн043D043Dннн043D043Dн	I
    //   13: istore_2
    //   14: getstatic 102	kkkkkk/iippii:b043D043D043Dннн043D043Dн	I
    //   17: istore_3
    //   18: iload_1
    //   19: iload_2
    //   20: iload_1
    //   21: iadd
    //   22: imul
    //   23: iload_3
    //   24: irem
    //   25: tableswitch	default:+19->44, 0:+74->99
    //   44: bipush 28
    //   46: putstatic 89	kkkkkk/iippii:b043Dн043Dннн043D043Dн	I
    //   49: bipush 68
    //   51: putstatic 100	kkkkkk/iippii:bннн043Dнн043D043Dн	I
    //   54: getstatic 89	kkkkkk/iippii:b043Dн043Dннн043D043Dн	I
    //   57: istore_1
    //   58: iload_1
    //   59: invokestatic 453	kkkkkk/iippii:b0430ааа04300430а0430а0430	()I
    //   62: iload_1
    //   63: iadd
    //   64: imul
    //   65: getstatic 102	kkkkkk/iippii:b043D043D043Dннн043D043Dн	I
    //   68: irem
    //   69: tableswitch	default:+19->88, 0:+30->99
    //   88: bipush 92
    //   90: putstatic 89	kkkkkk/iippii:b043Dн043Dннн043D043Dн	I
    //   93: invokestatic 98	kkkkkk/iippii:bаааа04300430а0430а0430	()I
    //   96: putstatic 100	kkkkkk/iippii:bннн043Dнн043D043Dн	I
    //   99: aload 4
    //   101: areturn
    //   102: astore 4
    //   104: aload 4
    //   106: athrow
    //   107: astore 4
    //   109: aload 4
    //   111: athrow
    // Local variable table:
    //   start	length	slot	name	signature
    //   0	112	0	this	iippii
    //   9	56	1	i	int
    //   13	9	2	j	int
    //   17	8	3	k	int
    //   4	96	4	str	String
    //   102	3	4	localException1	Exception
    //   107	3	4	localException2	Exception
    // Exception table:
    //   from	to	target	type
    //   0	18	102	java/lang/Exception
    //   44	54	107	java/lang/Exception
  }
  
  public boolean b04300430а04300430а04300430а0430()
  {
    switch (0)
    {
    case 1: 
    default: 
      for (;;)
      {
        switch (0)
        {
        }
      }
    }
    int i = b043Dн043Dннн043D043Dн;
    switch (i * (bн043D043Dннн043D043Dн + i) % b043D043D043Dннн043D043Dн)
    {
    default: 
      b043Dн043Dннн043D043Dн = 35;
      bннн043Dнн043D043Dн = bаааа04300430а0430а0430();
    }
    switch (0)
    {
    case 1: 
    default: 
      for (;;)
      {
        switch (1)
        {
        }
      }
    }
    i = b043Dн043Dннн043D043Dн;
    switch (i * (bн043D043Dннн043D043Dн + i) % b043D043D043Dннн043D043Dн)
    {
    default: 
      b043Dн043Dннн043D043Dн = bаааа04300430а0430а0430();
      bннн043Dнн043D043Dн = 69;
    }
    return this.bнн043D043Dн043Dн043Dн;
  }
  
  public String b04300430а0430аа04300430а0430()
  {
    return this.b043Dнн043D043D043Dн043Dн;
  }
  
  public String b04300430аа0430а04300430а0430()
  {
    String str = this.b043Dннннн043D043Dн;
    if ((b043Dн043Dннн043D043Dн + bн043D043Dннн043D043Dн) * b043Dн043Dннн043D043Dн % b043D043D043Dннн043D043Dн != bннн043Dнн043D043Dн)
    {
      b043Dн043Dннн043D043Dн = bаааа04300430а0430а0430();
      bннн043Dнн043D043Dн = 2;
    }
    return str;
  }
  
  public boolean b04300430ааа043004300430а0430()
  {
    int i = b043Dн043Dннн043D043Dн;
    int j = b0430ааа04300430а0430а0430();
    int k = b043D043D043Dннн043D043Dн;
    switch (0)
    {
    case 1: 
    default: 
      for (;;)
      {
        switch (0)
        {
        }
      }
    }
    switch (i * (j + i) % k)
    {
    default: 
      b043Dн043Dннн043D043Dн = 52;
      i = bаааа04300430а0430а0430();
      j = b043Dн043Dннн043D043Dн;
      switch (j * (bн043D043Dннн043D043Dн + j) % b0430043004300430а0430а0430а0430())
      {
      default: 
        b043Dн043Dннн043D043Dн = bаааа04300430а0430а0430();
        bннн043Dнн043D043Dн = bаааа04300430а0430а0430();
      }
      bннн043Dнн043D043Dн = i;
    }
    try
    {
      boolean bool = this.bн043D043Dн043D043Dн043Dн;
      return bool;
    }
    catch (Exception localException)
    {
      throw localException;
    }
  }
  
  public String b04300430аааа04300430а0430()
  {
    try
    {
      String str = this.bннн043Dн043Dн043Dн;
      int i = b043Dн043Dннн043D043Dн;
      switch (i * (b0430ааа04300430а0430а0430() + i) % b043D043D043Dннн043D043Dн)
      {
      default: 
        b043Dн043Dннн043D043Dн = bаааа04300430а0430а0430();
        switch (1)
        {
        case 0: 
        default: 
          for (;;)
          {
            switch (0)
            {
            }
          }
        }
        i = bаааа04300430а0430а0430();
        switch (i * (bн043D043Dннн043D043Dн + i) % b043D043D043Dннн043D043Dн)
        {
        default: 
          b043Dн043Dннн043D043Dн = bаааа04300430а0430а0430();
          bннн043Dнн043D043Dн = 76;
        }
        bннн043Dнн043D043Dн = 49;
      }
      return str;
    }
    catch (Exception localException)
    {
      throw localException;
    }
  }
  
  public String b0430а0430043004300430а0430а0430()
  {
    int i = b043Dн043Dннн043D043Dн;
    switch (i * (bн043D043Dннн043D043Dн + i) % b043D043D043Dннн043D043Dн)
    {
    default: 
      b043Dн043Dннн043D043Dн = bаааа04300430а0430а0430();
      bннн043Dнн043D043Dн = bаааа04300430а0430а0430();
    }
    String str = this.b043Dнннн043Dн043Dн;
    switch (0)
    {
    case 1: 
    default: 
      for (;;)
      {
        if ((bаааа04300430а0430а0430() + bн043D043Dннн043D043Dн) * bаааа04300430а0430а0430() % b043D043D043Dннн043D043Dн != bннн043Dнн043D043Dн)
        {
          b043Dн043Dннн043D043Dн = bаааа04300430а0430а0430();
          bннн043Dнн043D043Dн = 83;
        }
        switch (1)
        {
        }
      }
    }
    return str;
  }
  
  /* Error */
  public boolean b0430а043004300430а04300430а0430()
  {
    // Byte code:
    //   0: iconst_1
    //   1: tableswitch	default:+23->24, 0:+-1->0, 1:+50->51
    //   24: iconst_1
    //   25: tableswitch	default:+23->48, 0:+-25->0, 1:+26->51
    //   48: goto -24 -> 24
    //   51: getstatic 89	kkkkkk/iippii:b043Dн043Dннн043D043Dн	I
    //   54: istore_1
    //   55: getstatic 91	kkkkkk/iippii:bн043D043Dннн043D043Dн	I
    //   58: istore_2
    //   59: getstatic 102	kkkkkk/iippii:b043D043D043Dннн043D043Dн	I
    //   62: istore_3
    //   63: iload_1
    //   64: iload_2
    //   65: iload_1
    //   66: iadd
    //   67: imul
    //   68: iload_3
    //   69: irem
    //   70: tableswitch	default:+18->88, 0:+73->143
    //   88: bipush 22
    //   90: putstatic 89	kkkkkk/iippii:b043Dн043Dннн043D043Dн	I
    //   93: iconst_3
    //   94: putstatic 100	kkkkkk/iippii:bннн043Dнн043D043Dн	I
    //   97: getstatic 89	kkkkkk/iippii:b043Dн043Dннн043D043Dн	I
    //   100: istore_1
    //   101: iload_1
    //   102: getstatic 91	kkkkkk/iippii:bн043D043Dннн043D043Dн	I
    //   105: iload_1
    //   106: iadd
    //   107: imul
    //   108: invokestatic 95	kkkkkk/iippii:b0430043004300430а0430а0430а0430	()I
    //   111: irem
    //   112: tableswitch	default:+20->132, 0:+31->143
    //   132: bipush 37
    //   134: putstatic 89	kkkkkk/iippii:b043Dн043Dннн043D043Dн	I
    //   137: invokestatic 98	kkkkkk/iippii:bаааа04300430а0430а0430	()I
    //   140: putstatic 100	kkkkkk/iippii:bннн043Dнн043D043Dн	I
    //   143: aload_0
    //   144: getfield 356	kkkkkk/iippii:bнннн043D043Dн043Dн	Z
    //   147: istore 4
    //   149: iload 4
    //   151: ireturn
    //   152: astore 5
    //   154: aload 5
    //   156: athrow
    //   157: astore 5
    //   159: aload 5
    //   161: athrow
    // Local variable table:
    //   start	length	slot	name	signature
    //   0	162	0	this	iippii
    //   54	54	1	i	int
    //   58	9	2	j	int
    //   62	8	3	k	int
    //   147	3	4	bool	boolean
    //   152	3	5	localException1	Exception
    //   157	3	5	localException2	Exception
    // Exception table:
    //   from	to	target	type
    //   51	55	152	java/lang/Exception
    //   143	149	152	java/lang/Exception
    //   55	63	157	java/lang/Exception
    //   88	97	157	java/lang/Exception
  }
  
  /* Error */
  public String b0430а04300430аа04300430а0430()
  {
    // Byte code:
    //   0: iconst_3
    //   1: istore_2
    //   2: iload_2
    //   3: istore_1
    //   4: iconst_0
    //   5: tableswitch	default:+23->28, 0:+50->55, 1:+-3->2
    //   28: iload_2
    //   29: istore_1
    //   30: iconst_1
    //   31: tableswitch	default:+21->52, 0:+-29->2, 1:+24->55
    //   52: goto -24 -> 28
    //   55: iload_1
    //   56: iconst_0
    //   57: idiv
    //   58: istore_1
    //   59: goto -4 -> 55
    //   62: astore_3
    //   63: getstatic 89	kkkkkk/iippii:b043Dн043Dннн043D043Dн	I
    //   66: getstatic 91	kkkkkk/iippii:bн043D043Dннн043D043Dн	I
    //   69: iadd
    //   70: getstatic 89	kkkkkk/iippii:b043Dн043Dннн043D043Dн	I
    //   73: imul
    //   74: getstatic 102	kkkkkk/iippii:b043D043D043Dннн043D043Dн	I
    //   77: irem
    //   78: getstatic 100	kkkkkk/iippii:bннн043Dнн043D043Dн	I
    //   81: if_icmpeq +13 -> 94
    //   84: bipush 43
    //   86: putstatic 89	kkkkkk/iippii:b043Dн043Dннн043D043Dн	I
    //   89: bipush 24
    //   91: putstatic 100	kkkkkk/iippii:bннн043Dнн043D043Dн	I
    //   94: invokestatic 98	kkkkkk/iippii:bаааа04300430а0430а0430	()I
    //   97: putstatic 89	kkkkkk/iippii:b043Dн043Dннн043D043Dн	I
    //   100: aload_0
    //   101: getfield 264	kkkkkk/iippii:b043D043Dн043D043D043Dн043Dн	Ljava/lang/String;
    //   104: astore_3
    //   105: aload_3
    //   106: areturn
    //   107: astore_3
    //   108: aload_3
    //   109: athrow
    //   110: astore_3
    //   111: aload_3
    //   112: athrow
    // Local variable table:
    //   start	length	slot	name	signature
    //   0	113	0	this	iippii
    //   3	56	1	i	int
    //   1	28	2	j	int
    //   62	1	3	localException1	Exception
    //   104	2	3	str	String
    //   107	2	3	localException2	Exception
    //   110	2	3	localException3	Exception
    // Exception table:
    //   from	to	target	type
    //   55	59	62	java/lang/Exception
    //   100	105	107	java/lang/Exception
    //   94	100	110	java/lang/Exception
  }
  
  /* Error */
  public String b0430а0430а04300430а0430а0430()
  {
    // Byte code:
    //   0: getstatic 89	kkkkkk/iippii:b043Dн043Dннн043D043Dн	I
    //   3: istore_1
    //   4: getstatic 91	kkkkkk/iippii:bн043D043Dннн043D043Dн	I
    //   7: istore_2
    //   8: getstatic 89	kkkkkk/iippii:b043Dн043Dннн043D043Dн	I
    //   11: istore_3
    //   12: getstatic 102	kkkkkk/iippii:b043D043D043Dннн043D043Dн	I
    //   15: istore 4
    //   17: getstatic 89	kkkkkk/iippii:b043Dн043Dннн043D043Dн	I
    //   20: getstatic 91	kkkkkk/iippii:bн043D043Dннн043D043Dн	I
    //   23: iadd
    //   24: getstatic 89	kkkkkk/iippii:b043Dн043Dннн043D043Dн	I
    //   27: imul
    //   28: getstatic 102	kkkkkk/iippii:b043D043D043Dннн043D043Dн	I
    //   31: irem
    //   32: getstatic 100	kkkkkk/iippii:bннн043Dнн043D043Dн	I
    //   35: if_icmpeq +13 -> 48
    //   38: bipush 23
    //   40: putstatic 89	kkkkkk/iippii:b043Dн043Dннн043D043Dн	I
    //   43: bipush 31
    //   45: putstatic 100	kkkkkk/iippii:bннн043Dнн043D043Dн	I
    //   48: iload_1
    //   49: iload_2
    //   50: iadd
    //   51: iload_3
    //   52: imul
    //   53: iload 4
    //   55: irem
    //   56: getstatic 100	kkkkkk/iippii:bннн043Dнн043D043Dн	I
    //   59: if_icmpeq +14 -> 73
    //   62: invokestatic 98	kkkkkk/iippii:bаааа04300430а0430а0430	()I
    //   65: putstatic 89	kkkkkk/iippii:b043Dн043Dннн043D043Dн	I
    //   68: bipush 76
    //   70: putstatic 100	kkkkkk/iippii:bннн043Dнн043D043Dн	I
    //   73: aload_0
    //   74: invokevirtual 471	kkkkkk/iippii:b0430а0430043004300430а0430а0430	()Ljava/lang/String;
    //   77: astore 5
    //   79: aload 5
    //   81: invokestatic 257	kkkkkk/wbbwww:b04180418ИИИИ04180418И0418	(Ljava/lang/String;)Ljava/lang/String;
    //   84: astore 5
    //   86: aload 5
    //   88: areturn
    //   89: astore 5
    //   91: aload 5
    //   93: athrow
    //   94: astore 5
    //   96: aload 5
    //   98: athrow
    //   99: astore 5
    //   101: aload 5
    //   103: athrow
    //   104: astore 5
    //   106: aload 5
    //   108: athrow
    // Local variable table:
    //   start	length	slot	name	signature
    //   0	109	0	this	iippii
    //   3	48	1	i	int
    //   7	44	2	j	int
    //   11	42	3	k	int
    //   15	41	4	m	int
    //   77	10	5	str	String
    //   89	3	5	localException1	Exception
    //   94	3	5	localException2	Exception
    //   99	3	5	localException3	Exception
    //   104	3	5	localException4	Exception
    // Exception table:
    //   from	to	target	type
    //   73	79	89	java/lang/Exception
    //   0	17	94	java/lang/Exception
    //   91	94	94	java/lang/Exception
    //   79	86	99	java/lang/Exception
    //   48	73	104	java/lang/Exception
    //   101	104	104	java/lang/Exception
  }
  
  /* Error */
  public String b0430а0430а0430а04300430а0430()
  {
    // Byte code:
    //   0: iconst_1
    //   1: tableswitch	default:+23->24, 0:+-1->0, 1:+50->51
    //   24: iconst_0
    //   25: tableswitch	default:+23->48, 0:+26->51, 1:+-25->0
    //   48: goto -24 -> 24
    //   51: getstatic 89	kkkkkk/iippii:b043Dн043Dннн043D043Dн	I
    //   54: istore_1
    //   55: getstatic 91	kkkkkk/iippii:bн043D043Dннн043D043Dн	I
    //   58: istore_2
    //   59: getstatic 89	kkkkkk/iippii:b043Dн043Dннн043D043Dн	I
    //   62: istore_3
    //   63: iload_1
    //   64: iload_2
    //   65: iadd
    //   66: iload_3
    //   67: imul
    //   68: getstatic 102	kkkkkk/iippii:b043D043D043Dннн043D043Dн	I
    //   71: irem
    //   72: getstatic 100	kkkkkk/iippii:bннн043Dнн043D043Dн	I
    //   75: if_icmpeq +56 -> 131
    //   78: bipush 73
    //   80: putstatic 89	kkkkkk/iippii:b043Dн043Dннн043D043Dн	I
    //   83: bipush 60
    //   85: putstatic 100	kkkkkk/iippii:bннн043Dнн043D043Dн	I
    //   88: getstatic 89	kkkkkk/iippii:b043Dн043Dннн043D043Dн	I
    //   91: istore_1
    //   92: iload_1
    //   93: getstatic 91	kkkkkk/iippii:bн043D043Dннн043D043Dн	I
    //   96: iload_1
    //   97: iadd
    //   98: imul
    //   99: getstatic 102	kkkkkk/iippii:b043D043D043Dннн043D043Dн	I
    //   102: irem
    //   103: tableswitch	default:+17->120, 0:+28->131
    //   120: bipush 54
    //   122: putstatic 89	kkkkkk/iippii:b043Dн043Dннн043D043Dн	I
    //   125: invokestatic 98	kkkkkk/iippii:bаааа04300430а0430а0430	()I
    //   128: putstatic 100	kkkkkk/iippii:bннн043Dнн043D043Dн	I
    //   131: aload_0
    //   132: getfield 188	kkkkkk/iippii:bн043Dнннн043D043Dн	Ljava/lang/String;
    //   135: astore 4
    //   137: aload 4
    //   139: areturn
    //   140: astore 4
    //   142: aload 4
    //   144: athrow
    //   145: astore 4
    //   147: aload 4
    //   149: athrow
    // Local variable table:
    //   start	length	slot	name	signature
    //   0	150	0	this	iippii
    //   54	45	1	i	int
    //   58	8	2	j	int
    //   62	6	3	k	int
    //   135	3	4	str	String
    //   140	3	4	localException1	Exception
    //   145	3	4	localException2	Exception
    // Exception table:
    //   from	to	target	type
    //   51	63	140	java/lang/Exception
    //   63	88	145	java/lang/Exception
    //   131	137	145	java/lang/Exception
  }
  
  public void b0430а0430аа043004300430а0430(boolean paramBoolean)
  {
    this.bн043D043Dн043D043Dн043Dн = paramBoolean;
    if ((b043Dн043Dннн043D043Dн + bн043D043Dннн043D043Dн) * b043Dн043Dннн043D043Dн % b043D043D043Dннн043D043Dн != bа043004300430а0430а0430а0430())
    {
      b043Dн043Dннн043D043Dн = 93;
      int i = b043Dн043Dннн043D043Dн;
      switch (i * (bн043D043Dннн043D043Dн + i) % b043D043D043Dннн043D043Dн)
      {
      default: 
        b043Dн043Dннн043D043Dн = bаааа04300430а0430а0430();
        bннн043Dнн043D043Dн = 55;
      }
      bннн043Dнн043D043Dн = 27;
    }
  }
  
  @Nullable
  public ippiip b0430а0430ааа04300430а0430()
  {
    try
    {
      ippiip localIppiip = this.b043D043Dннн043Dн043Dн;
      return localIppiip;
    }
    catch (Exception localException)
    {
      throw localException;
    }
  }
  
  public String b0430аа043004300430а0430а0430()
  {
    switch (1)
    {
    case 0: 
    default: 
      for (;;)
      {
        switch (1)
        {
        }
      }
    }
    int i = b043Dн043Dннн043D043Dн;
    int j = bн043D043Dннн043D043Dн;
    int k = b043Dн043Dннн043D043Dн;
    int m = b043D043D043Dннн043D043Dн;
    int n = bннн043Dнн043D043Dн;
    switch (0)
    {
    case 1: 
    default: 
      for (;;)
      {
        switch (0)
        {
        }
      }
    }
    if ((i + j) * k % m != n)
    {
      b043Dн043Dннн043D043Dн = 46;
      bннн043Dнн043D043Dн = 22;
      if ((b043Dн043Dннн043D043Dн + bн043D043Dннн043D043Dн) * b043Dн043Dннн043D043Dн % b043D043D043Dннн043D043Dн != bннн043Dнн043D043Dн)
      {
        b043Dн043Dннн043D043Dн = 31;
        bннн043Dнн043D043Dн = 18;
      }
    }
    return this.b043Dн043D043D043Dнн043Dн;
  }
  
  public piipii b0430аа04300430а04300430а0430(Context paramContext)
  {
    paramContext = new piipii(paramContext, this.bнн043Dнн043Dн043Dн);
    switch (1)
    {
    case 0: 
    default: 
      for (;;)
      {
        switch (0)
        {
        }
      }
    }
    int i = b043Dн043Dннн043D043Dн;
    int j = bн043D043Dннн043D043Dн;
    int k = b043Dн043Dннн043D043Dн;
    switch (k * (bн043D043Dннн043D043Dн + k) % b043D043D043Dннн043D043Dн)
    {
    default: 
      b043Dн043Dннн043D043Dн = bаааа04300430а0430а0430();
      bннн043Dнн043D043Dн = 39;
    }
    if ((i + j) * b043Dн043Dннн043D043Dн % b043D043D043Dннн043D043Dн != bннн043Dнн043D043Dн)
    {
      b043Dн043Dннн043D043Dн = 9;
      bннн043Dнн043D043Dн = bаааа04300430а0430а0430();
    }
    return paramContext;
  }
  
  /* Error */
  public String b0430аа0430аа04300430а0430()
  {
    // Byte code:
    //   0: getstatic 89	kkkkkk/iippii:b043Dн043Dннн043D043Dн	I
    //   3: istore_1
    //   4: invokestatic 453	kkkkkk/iippii:b0430ааа04300430а0430а0430	()I
    //   7: istore_2
    //   8: getstatic 89	kkkkkk/iippii:b043Dн043Dннн043D043Dн	I
    //   11: istore_3
    //   12: getstatic 102	kkkkkk/iippii:b043D043D043Dннн043D043Dн	I
    //   15: istore 4
    //   17: getstatic 100	kkkkkk/iippii:bннн043Dнн043D043Dн	I
    //   20: istore 5
    //   22: iload_1
    //   23: iload_2
    //   24: iadd
    //   25: iload_3
    //   26: imul
    //   27: iload 4
    //   29: irem
    //   30: iload 5
    //   32: if_icmpeq +46 -> 78
    //   35: getstatic 89	kkkkkk/iippii:b043Dн043Dннн043D043Dн	I
    //   38: getstatic 91	kkkkkk/iippii:bн043D043Dннн043D043Dн	I
    //   41: iadd
    //   42: getstatic 89	kkkkkk/iippii:b043Dн043Dннн043D043Dн	I
    //   45: imul
    //   46: getstatic 102	kkkkkk/iippii:b043D043D043Dннн043D043Dн	I
    //   49: irem
    //   50: invokestatic 433	kkkkkk/iippii:bа043004300430а0430а0430а0430	()I
    //   53: if_icmpeq +14 -> 67
    //   56: invokestatic 98	kkkkkk/iippii:bаааа04300430а0430а0430	()I
    //   59: putstatic 89	kkkkkk/iippii:b043Dн043Dннн043D043Dн	I
    //   62: bipush 17
    //   64: putstatic 100	kkkkkk/iippii:bннн043Dнн043D043Dн	I
    //   67: invokestatic 98	kkkkkk/iippii:bаааа04300430а0430а0430	()I
    //   70: putstatic 89	kkkkkk/iippii:b043Dн043Dннн043D043Dн	I
    //   73: bipush 62
    //   75: putstatic 100	kkkkkk/iippii:bннн043Dнн043D043Dн	I
    //   78: aload_0
    //   79: getfield 247	kkkkkk/iippii:b043D043D043Dн043D043Dн043Dн	Ljava/lang/String;
    //   82: astore 6
    //   84: aload 6
    //   86: areturn
    //   87: astore 6
    //   89: aload 6
    //   91: athrow
    //   92: astore 6
    //   94: aload 6
    //   96: athrow
    //   97: astore 6
    //   99: aload 6
    //   101: athrow
    // Local variable table:
    //   start	length	slot	name	signature
    //   0	102	0	this	iippii
    //   3	22	1	i	int
    //   7	18	2	j	int
    //   11	16	3	k	int
    //   15	15	4	m	int
    //   20	13	5	n	int
    //   82	3	6	str	String
    //   87	3	6	localException1	Exception
    //   92	3	6	localException2	Exception
    //   97	3	6	localException3	Exception
    // Exception table:
    //   from	to	target	type
    //   78	84	87	java/lang/Exception
    //   0	17	92	java/lang/Exception
    //   89	92	92	java/lang/Exception
    //   17	22	97	java/lang/Exception
    //   67	78	97	java/lang/Exception
  }
  
  public String b0430ааа0430а04300430а0430()
  {
    if ((b043Dн043Dннн043D043Dн + bн043D043Dннн043D043Dн) * b043Dн043Dннн043D043Dн % b043D043D043Dннн043D043Dн != bннн043Dнн043D043Dн)
    {
      b043Dн043Dннн043D043Dн = 47;
      bннн043Dнн043D043Dн = 18;
      int i = b043Dн043Dннн043D043Dн;
      switch (i * (bн043D043Dннн043D043Dн + i) % b043D043D043Dннн043D043Dн)
      {
      default: 
        b043Dн043Dннн043D043Dн = bаааа04300430а0430а0430();
        bннн043Dнн043D043Dн = 83;
      }
    }
    return this.b043D043D043D043D043D043Dн043Dн;
  }
  
  public boolean b0430аааа043004300430а0430()
  {
    switch (1)
    {
    case 0: 
    default: 
      for (;;)
      {
        switch (0)
        {
        }
      }
    }
    int i = b043Dн043Dннн043D043Dн;
    switch (i * (bн043D043Dннн043D043Dн + i) % b043D043D043Dннн043D043Dн)
    {
    default: 
      b043Dн043Dннн043D043Dн = bаааа04300430а0430а0430();
      bннн043Dнн043D043Dн = 10;
    }
    if ((b043Dн043Dннн043D043Dн + bн043D043Dннн043D043Dн) * b043Dн043Dннн043D043Dн % b043D043D043Dннн043D043Dн != bннн043Dнн043D043Dн)
    {
      b043Dн043Dннн043D043Dн = 61;
      bннн043Dнн043D043Dн = bаааа04300430а0430а0430();
    }
    switch (0)
    {
    case 1: 
    default: 
      for (;;)
      {
        switch (1)
        {
        }
      }
    }
    return this.bнн043Dн043D043Dн043Dн;
  }
  
  /* Error */
  public String b0430ааааа04300430а0430()
  {
    // Byte code:
    //   0: getstatic 89	kkkkkk/iippii:b043Dн043Dннн043D043Dн	I
    //   3: getstatic 91	kkkkkk/iippii:bн043D043Dннн043D043Dн	I
    //   6: iadd
    //   7: getstatic 89	kkkkkk/iippii:b043Dн043Dннн043D043Dн	I
    //   10: imul
    //   11: getstatic 102	kkkkkk/iippii:b043D043D043Dннн043D043Dн	I
    //   14: irem
    //   15: getstatic 100	kkkkkk/iippii:bннн043Dнн043D043Dн	I
    //   18: if_icmpeq +13 -> 31
    //   21: bipush 81
    //   23: putstatic 89	kkkkkk/iippii:b043Dн043Dннн043D043Dн	I
    //   26: bipush 18
    //   28: putstatic 100	kkkkkk/iippii:bннн043Dнн043D043Dн	I
    //   31: getstatic 89	kkkkkk/iippii:b043Dн043Dннн043D043Dн	I
    //   34: istore_1
    //   35: getstatic 91	kkkkkk/iippii:bн043D043Dннн043D043Dн	I
    //   38: istore_2
    //   39: getstatic 89	kkkkkk/iippii:b043Dн043Dннн043D043Dн	I
    //   42: istore_3
    //   43: getstatic 102	kkkkkk/iippii:b043D043D043Dннн043D043Dн	I
    //   46: istore 4
    //   48: invokestatic 433	kkkkkk/iippii:bа043004300430а0430а0430а0430	()I
    //   51: istore 5
    //   53: iload_1
    //   54: iload_2
    //   55: iadd
    //   56: iload_3
    //   57: imul
    //   58: iload 4
    //   60: irem
    //   61: iload 5
    //   63: if_icmpeq +15 -> 78
    //   66: invokestatic 98	kkkkkk/iippii:bаааа04300430а0430а0430	()I
    //   69: putstatic 89	kkkkkk/iippii:b043Dн043Dннн043D043Dн	I
    //   72: invokestatic 98	kkkkkk/iippii:bаааа04300430а0430а0430	()I
    //   75: putstatic 100	kkkkkk/iippii:bннн043Dнн043D043Dн	I
    //   78: aload_0
    //   79: getfield 154	kkkkkk/iippii:bн043D043Dнн043Dн043Dн	Ljava/lang/String;
    //   82: astore 6
    //   84: aload 6
    //   86: areturn
    //   87: astore 6
    //   89: aload 6
    //   91: athrow
    //   92: astore 6
    //   94: aload 6
    //   96: athrow
    //   97: astore 6
    //   99: aload 6
    //   101: athrow
    // Local variable table:
    //   start	length	slot	name	signature
    //   0	102	0	this	iippii
    //   34	22	1	i	int
    //   38	18	2	j	int
    //   42	16	3	k	int
    //   46	15	4	m	int
    //   51	13	5	n	int
    //   82	3	6	str	String
    //   87	3	6	localException1	Exception
    //   92	3	6	localException2	Exception
    //   97	3	6	localException3	Exception
    // Exception table:
    //   from	to	target	type
    //   78	84	87	java/lang/Exception
    //   31	39	92	java/lang/Exception
    //   66	78	92	java/lang/Exception
    //   89	92	92	java/lang/Exception
    //   39	53	97	java/lang/Exception
  }
  
  /* Error */
  public List<String> bа04300430043004300430а0430а0430()
  {
    // Byte code:
    //   0: aload_0
    //   1: getfield 336	kkkkkk/iippii:bн043Dннн043Dн043Dн	Ljava/util/List;
    //   4: astore 6
    //   6: getstatic 89	kkkkkk/iippii:b043Dн043Dннн043D043Dн	I
    //   9: istore_1
    //   10: getstatic 91	kkkkkk/iippii:bн043D043Dннн043D043Dн	I
    //   13: istore_2
    //   14: getstatic 89	kkkkkk/iippii:b043Dн043Dннн043D043Dн	I
    //   17: istore_3
    //   18: getstatic 102	kkkkkk/iippii:b043D043D043Dннн043D043Dн	I
    //   21: istore 4
    //   23: getstatic 100	kkkkkk/iippii:bннн043Dнн043D043Dн	I
    //   26: istore 5
    //   28: iload_1
    //   29: iload_2
    //   30: iadd
    //   31: iload_3
    //   32: imul
    //   33: iload 4
    //   35: irem
    //   36: iload 5
    //   38: if_icmpeq +62 -> 100
    //   41: getstatic 89	kkkkkk/iippii:b043Dн043Dннн043D043Dн	I
    //   44: getstatic 91	kkkkkk/iippii:bн043D043Dннн043D043Dн	I
    //   47: iadd
    //   48: getstatic 89	kkkkkk/iippii:b043Dн043Dннн043D043Dн	I
    //   51: imul
    //   52: getstatic 102	kkkkkk/iippii:b043D043D043Dннн043D043Dн	I
    //   55: irem
    //   56: getstatic 100	kkkkkk/iippii:bннн043Dнн043D043Dн	I
    //   59: if_icmpeq +13 -> 72
    //   62: bipush 94
    //   64: putstatic 89	kkkkkk/iippii:b043Dн043Dннн043D043Dн	I
    //   67: bipush 31
    //   69: putstatic 100	kkkkkk/iippii:bннн043Dнн043D043Dн	I
    //   72: bipush 37
    //   74: putstatic 89	kkkkkk/iippii:b043Dн043Dннн043D043Dн	I
    //   77: bipush 35
    //   79: putstatic 100	kkkkkk/iippii:bннн043Dнн043D043Dн	I
    //   82: aload 6
    //   84: areturn
    //   85: astore 6
    //   87: aload 6
    //   89: athrow
    //   90: astore 6
    //   92: aload 6
    //   94: athrow
    //   95: astore 6
    //   97: aload 6
    //   99: athrow
    //   100: aload 6
    //   102: areturn
    // Local variable table:
    //   start	length	slot	name	signature
    //   0	103	0	this	iippii
    //   9	22	1	i	int
    //   13	18	2	j	int
    //   17	16	3	k	int
    //   21	15	4	m	int
    //   26	13	5	n	int
    //   4	79	6	localList	List
    //   85	3	6	localException1	Exception
    //   90	3	6	localException2	Exception
    //   95	6	6	localException3	Exception
    // Exception table:
    //   from	to	target	type
    //   0	6	85	java/lang/Exception
    //   77	82	90	java/lang/Exception
    //   87	90	90	java/lang/Exception
    //   6	28	95	java/lang/Exception
    //   72	77	95	java/lang/Exception
  }
  
  /* Error */
  public boolean bа0430043004300430а04300430а0430()
  {
    // Byte code:
    //   0: aload_0
    //   1: getfield 321	kkkkkk/iippii:b043Dннн043D043Dн043Dн	Z
    //   4: istore 6
    //   6: getstatic 89	kkkkkk/iippii:b043Dн043Dннн043D043Dн	I
    //   9: istore_1
    //   10: getstatic 91	kkkkkk/iippii:bн043D043Dннн043D043Dн	I
    //   13: istore_2
    //   14: getstatic 89	kkkkkk/iippii:b043Dн043Dннн043D043Dн	I
    //   17: istore_3
    //   18: getstatic 102	kkkkkk/iippii:b043D043D043Dннн043D043Dн	I
    //   21: istore 4
    //   23: getstatic 100	kkkkkk/iippii:bннн043Dнн043D043Dн	I
    //   26: istore 5
    //   28: iload_1
    //   29: iload_2
    //   30: iadd
    //   31: iload_3
    //   32: imul
    //   33: iload 4
    //   35: irem
    //   36: iload 5
    //   38: if_icmpeq +46 -> 84
    //   41: invokestatic 98	kkkkkk/iippii:bаааа04300430а0430а0430	()I
    //   44: getstatic 91	kkkkkk/iippii:bн043D043Dннн043D043Dн	I
    //   47: iadd
    //   48: invokestatic 98	kkkkkk/iippii:bаааа04300430а0430а0430	()I
    //   51: imul
    //   52: getstatic 102	kkkkkk/iippii:b043D043D043Dннн043D043Dн	I
    //   55: irem
    //   56: getstatic 100	kkkkkk/iippii:bннн043Dнн043D043Dн	I
    //   59: if_icmpeq +14 -> 73
    //   62: bipush 56
    //   64: putstatic 89	kkkkkk/iippii:b043Dн043Dннн043D043Dн	I
    //   67: invokestatic 98	kkkkkk/iippii:bаааа04300430а0430а0430	()I
    //   70: putstatic 100	kkkkkk/iippii:bннн043Dнн043D043Dн	I
    //   73: bipush 30
    //   75: putstatic 89	kkkkkk/iippii:b043Dн043Dннн043D043Dн	I
    //   78: invokestatic 98	kkkkkk/iippii:bаааа04300430а0430а0430	()I
    //   81: putstatic 100	kkkkkk/iippii:bннн043Dнн043D043Dн	I
    //   84: iload 6
    //   86: ireturn
    //   87: astore 7
    //   89: aload 7
    //   91: athrow
    //   92: astore 7
    //   94: aload 7
    //   96: athrow
    // Local variable table:
    //   start	length	slot	name	signature
    //   0	97	0	this	iippii
    //   9	22	1	i	int
    //   13	18	2	j	int
    //   17	16	3	k	int
    //   21	15	4	m	int
    //   26	13	5	n	int
    //   4	81	6	bool	boolean
    //   87	3	7	localException1	Exception
    //   92	3	7	localException2	Exception
    // Exception table:
    //   from	to	target	type
    //   0	6	87	java/lang/Exception
    //   73	84	87	java/lang/Exception
    //   6	28	92	java/lang/Exception
  }
  
  public String bа043004300430аа04300430а0430()
  {
    try
    {
      String str = this.bнн043D043D043D043Dн043Dн;
      int i = b043Dн043Dннн043D043Dн;
      int j = bн043D043Dннн043D043Dн;
      int k = b043D043D043Dннн043D043Dн;
      if ((b043Dн043Dннн043D043Dн + bн043D043Dннн043D043Dн) * b043Dн043Dннн043D043Dн % b043D043D043Dннн043D043Dн != bннн043Dнн043D043Dн)
      {
        b043Dн043Dннн043D043Dн = bаааа04300430а0430а0430();
        bннн043Dнн043D043Dн = bаааа04300430а0430а0430();
      }
      switch (i * (j + i) % k)
      {
      default: 
        b043Dн043Dннн043D043Dн = bаааа04300430а0430а0430();
        bннн043Dнн043D043Dн = bаааа04300430а0430а0430();
      }
      return str;
    }
    catch (Exception localException)
    {
      throw localException;
    }
  }
  
  public String bа04300430а04300430а0430а0430()
  {
    int i = b043Dн043Dннн043D043Dн;
    switch (i * (bн043D043Dннн043D043Dн + i) % b0430043004300430а0430а0430а0430())
    {
    default: 
      b043Dн043Dннн043D043Dн = bаааа04300430а0430а0430();
      bннн043Dнн043D043Dн = 49;
      if ((b043Dн043Dннн043D043Dн + bн043D043Dннн043D043Dн) * b043Dн043Dннн043D043Dн % b043D043D043Dннн043D043Dн != bннн043Dнн043D043Dн)
      {
        b043Dн043Dннн043D043Dн = bаааа04300430а0430а0430();
        bннн043Dнн043D043Dн = 11;
      }
      break;
    }
    try
    {
      String str = this.b043D043Dн043D043Dнн043Dн;
      return str;
    }
    catch (Exception localException)
    {
      throw localException;
    }
  }
  
  public String bа04300430а0430а04300430а0430()
  {
    try
    {
      String str = this.b043D043D043D043Dн043Dн043Dн;
      int i = b043Dн043Dннн043D043Dн;
      int j = b0430ааа04300430а0430а0430();
      switch (1)
      {
      case 0: 
      default: 
        for (;;)
        {
          switch (1)
          {
          }
        }
      }
      int k = b043Dн043Dннн043D043Dн;
      switch (k * (bн043D043Dннн043D043Dн + k) % b043D043D043Dннн043D043Dн)
      {
      default: 
        b043Dн043Dннн043D043Dн = 70;
        bннн043Dнн043D043Dн = bаааа04300430а0430а0430();
      }
      switch (i * (j + i) % b043D043D043Dннн043D043Dн)
      {
      default: 
        b043Dн043Dннн043D043Dн = 59;
        bннн043Dнн043D043Dн = bаааа04300430а0430а0430();
      }
      return str;
    }
    catch (Exception localException)
    {
      throw localException;
    }
  }
  
  public String bа04300430ааа04300430а0430()
  {
    switch (1)
    {
    case 0: 
    default: 
      for (;;)
      {
        i = b043Dн043Dннн043D043Dн;
        switch (i * (bн043D043Dннн043D043Dн + i) % b043D043D043Dннн043D043Dн)
        {
        default: 
          b043Dн043Dннн043D043Dн = 45;
          bннн043Dнн043D043Dн = bаааа04300430а0430а0430();
        }
        switch (1)
        {
        }
      }
    }
    String str = this.bн043Dн043Dн043Dн043Dн;
    int i = b043Dн043Dннн043D043Dн;
    switch (i * (bн043D043Dннн043D043Dн + i) % b043D043D043Dннн043D043Dн)
    {
    default: 
      b043Dн043Dннн043D043Dн = bаааа04300430а0430а0430();
      bннн043Dнн043D043Dн = 78;
    }
    return str;
  }
  
  /* Error */
  @Nullable
  public String bа0430а043004300430а0430а0430()
  {
    // Byte code:
    //   0: aload_0
    //   1: invokevirtual 498	kkkkkk/iippii:b043004300430а0430а04300430а0430	()Ljava/lang/String;
    //   4: astore 6
    //   6: getstatic 89	kkkkkk/iippii:b043Dн043Dннн043D043Dн	I
    //   9: istore_1
    //   10: getstatic 91	kkkkkk/iippii:bн043D043Dннн043D043Dн	I
    //   13: istore_2
    //   14: getstatic 89	kkkkkk/iippii:b043Dн043Dннн043D043Dн	I
    //   17: istore_3
    //   18: getstatic 102	kkkkkk/iippii:b043D043D043Dннн043D043Dн	I
    //   21: istore 4
    //   23: getstatic 100	kkkkkk/iippii:bннн043Dнн043D043Dн	I
    //   26: istore 5
    //   28: iload_1
    //   29: iload_2
    //   30: iadd
    //   31: iload_3
    //   32: imul
    //   33: iload 4
    //   35: irem
    //   36: iload 5
    //   38: if_icmpeq +15 -> 53
    //   41: invokestatic 98	kkkkkk/iippii:bаааа04300430а0430а0430	()I
    //   44: putstatic 89	kkkkkk/iippii:b043Dн043Dннн043D043Dн	I
    //   47: invokestatic 98	kkkkkk/iippii:bаааа04300430а0430а0430	()I
    //   50: putstatic 100	kkkkkk/iippii:bннн043Dнн043D043Dн	I
    //   53: aload 6
    //   55: invokestatic 501	kkkkkk/wbbwww:b041804180418041804180418И0418И0418	(Ljava/lang/String;)Ljava/lang/String;
    //   58: astore 6
    //   60: getstatic 89	kkkkkk/iippii:b043Dн043Dннн043D043Dн	I
    //   63: istore_1
    //   64: iload_1
    //   65: getstatic 91	kkkkkk/iippii:bн043D043Dннн043D043Dн	I
    //   68: iload_1
    //   69: iadd
    //   70: imul
    //   71: getstatic 102	kkkkkk/iippii:b043D043D043Dннн043D043Dн	I
    //   74: irem
    //   75: tableswitch	default:+17->92, 0:+29->104
    //   92: invokestatic 98	kkkkkk/iippii:bаааа04300430а0430а0430	()I
    //   95: putstatic 89	kkkkkk/iippii:b043Dн043Dннн043D043Dн	I
    //   98: invokestatic 98	kkkkkk/iippii:bаааа04300430а0430а0430	()I
    //   101: putstatic 100	kkkkkk/iippii:bннн043Dнн043D043Dн	I
    //   104: iconst_0
    //   105: tableswitch	default:+23->128, 0:+50->155, 1:+-45->60
    //   128: iconst_1
    //   129: tableswitch	default:+23->152, 0:+-69->60, 1:+26->155
    //   152: goto -24 -> 128
    //   155: aload 6
    //   157: areturn
    //   158: astore 6
    //   160: aload 6
    //   162: athrow
    //   163: astore 6
    //   165: aload 6
    //   167: athrow
    // Local variable table:
    //   start	length	slot	name	signature
    //   0	168	0	this	iippii
    //   9	62	1	i	int
    //   13	18	2	j	int
    //   17	16	3	k	int
    //   21	15	4	m	int
    //   26	13	5	n	int
    //   4	152	6	str	String
    //   158	3	6	localException1	Exception
    //   163	3	6	localException2	Exception
    // Exception table:
    //   from	to	target	type
    //   0	28	158	java/lang/Exception
    //   53	60	158	java/lang/Exception
    //   41	53	163	java/lang/Exception
  }
  
  /* Error */
  public String bа0430а0430аа04300430а0430()
  {
    // Byte code:
    //   0: getstatic 89	kkkkkk/iippii:b043Dн043Dннн043D043Dн	I
    //   3: istore_1
    //   4: getstatic 91	kkkkkk/iippii:bн043D043Dннн043D043Dн	I
    //   7: istore_2
    //   8: getstatic 89	kkkkkk/iippii:b043Dн043Dннн043D043Dн	I
    //   11: istore_3
    //   12: getstatic 102	kkkkkk/iippii:b043D043D043Dннн043D043Dн	I
    //   15: istore 4
    //   17: invokestatic 433	kkkkkk/iippii:bа043004300430а0430а0430а0430	()I
    //   20: istore 5
    //   22: iload_1
    //   23: iload_2
    //   24: iadd
    //   25: iload_3
    //   26: imul
    //   27: iload 4
    //   29: irem
    //   30: iload 5
    //   32: if_icmpeq +59 -> 91
    //   35: invokestatic 98	kkkkkk/iippii:bаааа04300430а0430а0430	()I
    //   38: putstatic 89	kkkkkk/iippii:b043Dн043Dннн043D043Dн	I
    //   41: bipush 42
    //   43: putstatic 100	kkkkkk/iippii:bннн043Dнн043D043Dн	I
    //   46: getstatic 89	kkkkkk/iippii:b043Dн043Dннн043D043Dн	I
    //   49: istore_1
    //   50: iload_1
    //   51: getstatic 91	kkkkkk/iippii:bн043D043Dннн043D043Dн	I
    //   54: iload_1
    //   55: iadd
    //   56: imul
    //   57: getstatic 102	kkkkkk/iippii:b043D043D043Dннн043D043Dн	I
    //   60: irem
    //   61: tableswitch	default:+19->80, 0:+30->91
    //   80: bipush 27
    //   82: putstatic 89	kkkkkk/iippii:b043Dн043Dннн043D043Dн	I
    //   85: invokestatic 98	kkkkkk/iippii:bаааа04300430а0430а0430	()I
    //   88: putstatic 100	kkkkkk/iippii:bннн043Dнн043D043Dн	I
    //   91: aload_0
    //   92: getfield 284	kkkkkk/iippii:bннн043D043D043Dн043Dн	Ljava/lang/String;
    //   95: astore 6
    //   97: aload 6
    //   99: areturn
    //   100: astore 6
    //   102: aload 6
    //   104: athrow
    //   105: astore 6
    //   107: aload 6
    //   109: athrow
    // Local variable table:
    //   start	length	slot	name	signature
    //   0	110	0	this	iippii
    //   3	54	1	i	int
    //   7	18	2	j	int
    //   11	16	3	k	int
    //   15	15	4	m	int
    //   20	13	5	n	int
    //   95	3	6	str	String
    //   100	3	6	localException1	Exception
    //   105	3	6	localException2	Exception
    // Exception table:
    //   from	to	target	type
    //   0	22	100	java/lang/Exception
    //   91	97	100	java/lang/Exception
    //   35	46	105	java/lang/Exception
  }
  
  public String bа0430аа0430а04300430а0430()
  {
    if ((b043Dн043Dннн043D043Dн + b0430ааа04300430а0430а0430()) * b043Dн043Dннн043D043Dн % b0430043004300430а0430а0430а0430() != bннн043Dнн043D043Dн)
    {
      b043Dн043Dннн043D043Dн = bаааа04300430а0430а0430();
      bннн043Dнн043D043Dн = 98;
      switch (1)
      {
      case 0: 
      default: 
        for (;;)
        {
          switch (1)
          {
          }
        }
      }
      if ((b043Dн043Dннн043D043Dн + bн043D043Dннн043D043Dн) * b043Dн043Dннн043D043Dн % b043D043D043Dннн043D043Dн != bннн043Dнн043D043Dн)
      {
        b043Dн043Dннн043D043Dн = bаааа04300430а0430а0430();
        bннн043Dнн043D043Dн = bаааа04300430а0430а0430();
      }
    }
    try
    {
      String str = this.bнннннн043D043Dн;
      return str;
    }
    catch (Exception localException)
    {
      throw localException;
    }
  }
  
  public boolean bа0430ааа043004300430а0430()
  {
    boolean bool = this.b043Dн043Dн043D043Dн043Dн;
    int i = b043Dн043Dннн043D043Dн;
    switch (i * (bн043D043Dннн043D043Dн + i) % b043D043D043Dннн043D043Dн)
    {
    default: 
      i = b043Dн043Dннн043D043Dн;
      switch (i * (bн043D043Dннн043D043Dн + i) % b043D043D043Dннн043D043Dн)
      {
      default: 
        b043Dн043Dннн043D043Dн = 76;
        bннн043Dнн043D043Dн = bаааа04300430а0430а0430();
      }
      b043Dн043Dннн043D043Dн = 99;
      bннн043Dнн043D043Dн = bаааа04300430а0430а0430();
    }
    switch (0)
    {
    case 1: 
    default: 
      for (;;)
      {
        switch (1)
        {
        }
      }
    }
    return bool;
  }
  
  public String bа0430аааа04300430а0430()
  {
    switch (1)
    {
    case 0: 
    default: 
      for (;;)
      {
        switch (1)
        {
        }
      }
    }
    int i = b043Dн043Dннн043D043Dн;
    switch (i * (bн043D043Dннн043D043Dн + i) % b043D043D043Dннн043D043Dн)
    {
    default: 
      b043Dн043Dннн043D043Dн = 62;
      bннн043Dнн043D043Dн = bаааа04300430а0430а0430();
      i = b043Dн043Dннн043D043Dн;
      switch (i * (bн043D043Dннн043D043Dн + i) % b0430043004300430а0430а0430а0430())
      {
      default: 
        b043Dн043Dннн043D043Dн = 35;
        bннн043Dнн043D043Dн = bаааа04300430а0430а0430();
      }
      break;
    }
    return this.b043D043D043Dнн043Dн043Dн;
  }
  
  /* Error */
  public String bаа0430043004300430а0430а0430()
  {
    // Byte code:
    //   0: iconst_0
    //   1: tableswitch	default:+23->24, 0:+50->51, 1:+-1->0
    //   24: iconst_0
    //   25: tableswitch	default:+23->48, 0:+26->51, 1:+-25->0
    //   48: goto -24 -> 24
    //   51: getstatic 89	kkkkkk/iippii:b043Dн043Dннн043D043Dн	I
    //   54: istore_1
    //   55: invokestatic 453	kkkkkk/iippii:b0430ааа04300430а0430а0430	()I
    //   58: istore_2
    //   59: getstatic 89	kkkkkk/iippii:b043Dн043Dннн043D043Dн	I
    //   62: istore_3
    //   63: iload_3
    //   64: getstatic 91	kkkkkk/iippii:bн043D043Dннн043D043Dн	I
    //   67: iload_3
    //   68: iadd
    //   69: imul
    //   70: getstatic 102	kkkkkk/iippii:b043D043D043Dннн043D043Dн	I
    //   73: irem
    //   74: tableswitch	default:+18->92, 0:+28->102
    //   92: bipush 8
    //   94: putstatic 89	kkkkkk/iippii:b043Dн043Dннн043D043Dн	I
    //   97: bipush 34
    //   99: putstatic 100	kkkkkk/iippii:bннн043Dнн043D043Dн	I
    //   102: invokestatic 95	kkkkkk/iippii:b0430043004300430а0430а0430а0430	()I
    //   105: istore_3
    //   106: iload_1
    //   107: iload_2
    //   108: iload_1
    //   109: iadd
    //   110: imul
    //   111: iload_3
    //   112: irem
    //   113: tableswitch	default:+19->132, 0:+30->143
    //   132: invokestatic 98	kkkkkk/iippii:bаааа04300430а0430а0430	()I
    //   135: putstatic 89	kkkkkk/iippii:b043Dн043Dннн043D043Dн	I
    //   138: bipush 52
    //   140: putstatic 100	kkkkkk/iippii:bннн043Dнн043D043Dн	I
    //   143: aload_0
    //   144: getfield 122	kkkkkk/iippii:bннннн043Dн043Dн	Ljava/lang/String;
    //   147: astore 4
    //   149: aload 4
    //   151: areturn
    //   152: astore 4
    //   154: aload 4
    //   156: athrow
    //   157: astore 4
    //   159: aload 4
    //   161: athrow
    // Local variable table:
    //   start	length	slot	name	signature
    //   0	162	0	this	iippii
    //   54	57	1	i	int
    //   58	52	2	j	int
    //   62	51	3	k	int
    //   147	3	4	str	String
    //   152	3	4	localException1	Exception
    //   157	3	4	localException2	Exception
    // Exception table:
    //   from	to	target	type
    //   51	55	152	java/lang/Exception
    //   102	106	152	java/lang/Exception
    //   55	59	157	java/lang/Exception
    //   132	143	157	java/lang/Exception
    //   143	149	157	java/lang/Exception
  }
  
  public boolean bаа043004300430а04300430а0430()
  {
    if ((b043Dн043Dннн043D043Dн + bн043D043Dннн043D043Dн) * b043Dн043Dннн043D043Dн % b043D043D043Dннн043D043Dн != bннн043Dнн043D043Dн)
    {
      b043Dн043Dннн043D043Dн = bаааа04300430а0430а0430();
      bннн043Dнн043D043Dн = 72;
    }
    return this.b043D043Dн043Dн043Dн043Dн;
  }
  
  public String bаа04300430аа04300430а0430()
  {
    switch (0)
    {
    case 1: 
    default: 
      for (;;)
      {
        switch (1)
        {
        }
      }
    }
    try
    {
      String str = this.bн043Dн043D043D043Dн043Dн;
      if ((b043Dн043Dннн043D043Dн + bн043D043Dннн043D043Dн) * b043Dн043Dннн043D043Dн % b0430043004300430а0430а0430а0430() != bннн043Dнн043D043Dн)
      {
        if ((b043Dн043Dннн043D043Dн + bн043D043Dннн043D043Dн) * b043Dн043Dннн043D043Dн % b043D043D043Dннн043D043Dн != bннн043Dнн043D043Dн)
        {
          b043Dн043Dннн043D043Dн = 76;
          bннн043Dнн043D043Dн = bаааа04300430а0430а0430();
        }
        b043Dн043Dннн043D043Dн = 21;
        bннн043Dнн043D043Dн = 6;
      }
      return str;
    }
    catch (Exception localException)
    {
      throw localException;
    }
  }
  
  public String bаа0430а0430аа0430а0430()
  {
    String str = this.bн043D043D043D043Dнн043Dн;
    int i = b043Dн043Dннн043D043Dн;
    int j = bн043D043Dннн043D043Dн;
    int k = b043Dн043Dннн043D043Dн;
    int m = b043D043D043Dннн043D043Dн;
    if ((b043Dн043Dннн043D043Dн + bн043D043Dннн043D043Dн) * b043Dн043Dннн043D043Dн % b043D043D043Dннн043D043Dн != bа043004300430а0430а0430а0430())
    {
      b043Dн043Dннн043D043Dн = 6;
      bннн043Dнн043D043Dн = bаааа04300430а0430а0430();
    }
    if ((i + j) * k % m != bа043004300430а0430а0430а0430())
    {
      b043Dн043Dннн043D043Dн = bаааа04300430а0430а0430();
      bннн043Dнн043D043Dн = bаааа04300430а0430а0430();
    }
    return str;
  }
  
  /* Error */
  public void bаа0430аа043004300430а0430(boolean paramBoolean)
  {
    // Byte code:
    //   0: getstatic 89	kkkkkk/iippii:b043Dн043Dннн043D043Dн	I
    //   3: istore_2
    //   4: getstatic 91	kkkkkk/iippii:bн043D043Dннн043D043Dн	I
    //   7: istore_3
    //   8: getstatic 89	kkkkkk/iippii:b043Dн043Dннн043D043Dн	I
    //   11: istore 4
    //   13: getstatic 102	kkkkkk/iippii:b043D043D043Dннн043D043Dн	I
    //   16: istore 5
    //   18: getstatic 100	kkkkkk/iippii:bннн043Dнн043D043Dн	I
    //   21: istore 6
    //   23: iload_2
    //   24: iload_3
    //   25: iadd
    //   26: iload 4
    //   28: imul
    //   29: iload 5
    //   31: irem
    //   32: iload 6
    //   34: if_icmpeq +45 -> 79
    //   37: getstatic 89	kkkkkk/iippii:b043Dн043Dннн043D043Dн	I
    //   40: getstatic 91	kkkkkk/iippii:bн043D043Dннн043D043Dн	I
    //   43: iadd
    //   44: getstatic 89	kkkkkk/iippii:b043Dн043Dннн043D043Dн	I
    //   47: imul
    //   48: getstatic 102	kkkkkk/iippii:b043D043D043Dннн043D043Dн	I
    //   51: irem
    //   52: invokestatic 433	kkkkkk/iippii:bа043004300430а0430а0430а0430	()I
    //   55: if_icmpeq +14 -> 69
    //   58: invokestatic 98	kkkkkk/iippii:bаааа04300430а0430а0430	()I
    //   61: putstatic 89	kkkkkk/iippii:b043Dн043Dннн043D043Dн	I
    //   64: bipush 11
    //   66: putstatic 100	kkkkkk/iippii:bннн043Dнн043D043Dн	I
    //   69: bipush 19
    //   71: putstatic 89	kkkkkk/iippii:b043Dн043Dннн043D043Dн	I
    //   74: bipush 49
    //   76: putstatic 100	kkkkkk/iippii:bннн043Dнн043D043Dн	I
    //   79: aload_0
    //   80: iload_1
    //   81: putfield 506	kkkkkk/iippii:b043Dн043Dн043D043Dн043Dн	Z
    //   84: return
    //   85: astore 7
    //   87: aload 7
    //   89: athrow
    //   90: astore 7
    //   92: aload 7
    //   94: athrow
    //   95: astore 7
    //   97: aload 7
    //   99: athrow
    // Local variable table:
    //   start	length	slot	name	signature
    //   0	100	0	this	iippii
    //   0	100	1	paramBoolean	boolean
    //   3	23	2	i	int
    //   7	19	3	j	int
    //   11	18	4	k	int
    //   16	16	5	m	int
    //   21	14	6	n	int
    //   85	3	7	localException1	Exception
    //   90	3	7	localException2	Exception
    //   95	3	7	localException3	Exception
    // Exception table:
    //   from	to	target	type
    //   79	84	85	java/lang/Exception
    //   18	23	90	java/lang/Exception
    //   74	79	90	java/lang/Exception
    //   87	90	90	java/lang/Exception
    //   0	18	95	java/lang/Exception
    //   69	74	95	java/lang/Exception
  }
  
  public String bаа0430ааа04300430а0430()
  {
    return this.b043Dнн043Dн043Dн043Dн;
  }
  
  /* Error */
  public String bааа043004300430а0430а0430()
  {
    // Byte code:
    //   0: getstatic 89	kkkkkk/iippii:b043Dн043Dннн043D043Dн	I
    //   3: invokestatic 453	kkkkkk/iippii:b0430ааа04300430а0430а0430	()I
    //   6: iadd
    //   7: getstatic 89	kkkkkk/iippii:b043Dн043Dннн043D043Dн	I
    //   10: imul
    //   11: getstatic 102	kkkkkk/iippii:b043D043D043Dннн043D043Dн	I
    //   14: irem
    //   15: getstatic 100	kkkkkk/iippii:bннн043Dнн043D043Dн	I
    //   18: if_icmpeq +45 -> 63
    //   21: bipush 23
    //   23: putstatic 89	kkkkkk/iippii:b043Dн043Dннн043D043Dн	I
    //   26: bipush 51
    //   28: putstatic 100	kkkkkk/iippii:bннн043Dнн043D043Dн	I
    //   31: getstatic 89	kkkkkk/iippii:b043Dн043Dннн043D043Dн	I
    //   34: getstatic 91	kkkkkk/iippii:bн043D043Dннн043D043Dн	I
    //   37: iadd
    //   38: getstatic 89	kkkkkk/iippii:b043Dн043Dннн043D043Dн	I
    //   41: imul
    //   42: getstatic 102	kkkkkk/iippii:b043D043D043Dннн043D043Dн	I
    //   45: irem
    //   46: getstatic 100	kkkkkk/iippii:bннн043Dнн043D043Dн	I
    //   49: if_icmpeq +14 -> 63
    //   52: invokestatic 98	kkkkkk/iippii:bаааа04300430а0430а0430	()I
    //   55: putstatic 89	kkkkkk/iippii:b043Dн043Dннн043D043Dн	I
    //   58: bipush 53
    //   60: putstatic 100	kkkkkk/iippii:bннн043Dнн043D043Dн	I
    //   63: aload_0
    //   64: invokevirtual 515	kkkkkk/iippii:bаа0430ааа04300430а0430	()Ljava/lang/String;
    //   67: astore_1
    //   68: aload_1
    //   69: invokestatic 257	kkkkkk/wbbwww:b04180418ИИИИ04180418И0418	(Ljava/lang/String;)Ljava/lang/String;
    //   72: astore_1
    //   73: aload_1
    //   74: areturn
    //   75: astore_1
    //   76: aload_1
    //   77: athrow
    //   78: astore_1
    //   79: aload_1
    //   80: athrow
    // Local variable table:
    //   start	length	slot	name	signature
    //   0	81	0	this	iippii
    //   67	7	1	str	String
    //   75	2	1	localException1	Exception
    //   78	2	1	localException2	Exception
    // Exception table:
    //   from	to	target	type
    //   68	73	75	java/lang/Exception
    //   63	68	78	java/lang/Exception
  }
  
  /* Error */
  public String bааа04300430а04300430а0430()
  {
    // Byte code:
    //   0: aload_0
    //   1: getfield 346	kkkkkk/iippii:bнн043Dннн043D043Dн	Ljava/lang/String;
    //   4: astore 6
    //   6: invokestatic 98	kkkkkk/iippii:bаааа04300430а0430а0430	()I
    //   9: istore_1
    //   10: getstatic 91	kkkkkk/iippii:bн043D043Dннн043D043Dн	I
    //   13: istore_2
    //   14: invokestatic 98	kkkkkk/iippii:bаааа04300430а0430а0430	()I
    //   17: istore_3
    //   18: getstatic 102	kkkkkk/iippii:b043D043D043Dннн043D043Dн	I
    //   21: istore 4
    //   23: getstatic 100	kkkkkk/iippii:bннн043Dнн043D043Dн	I
    //   26: istore 5
    //   28: iload_1
    //   29: iload_2
    //   30: iadd
    //   31: iload_3
    //   32: imul
    //   33: iload 4
    //   35: irem
    //   36: iload 5
    //   38: if_icmpeq +14 -> 52
    //   41: bipush 17
    //   43: putstatic 89	kkkkkk/iippii:b043Dн043Dннн043D043Dн	I
    //   46: invokestatic 98	kkkkkk/iippii:bаааа04300430а0430а0430	()I
    //   49: putstatic 100	kkkkkk/iippii:bннн043Dнн043D043Dн	I
    //   52: aload 6
    //   54: areturn
    //   55: astore 6
    //   57: aload 6
    //   59: athrow
    //   60: astore 6
    //   62: aload 6
    //   64: athrow
    // Local variable table:
    //   start	length	slot	name	signature
    //   0	65	0	this	iippii
    //   9	22	1	i	int
    //   13	18	2	j	int
    //   17	16	3	k	int
    //   21	15	4	m	int
    //   26	13	5	n	int
    //   4	49	6	str	String
    //   55	3	6	localException1	Exception
    //   60	3	6	localException2	Exception
    // Exception table:
    //   from	to	target	type
    //   6	10	55	java/lang/Exception
    //   18	28	55	java/lang/Exception
    //   0	6	60	java/lang/Exception
    //   10	18	60	java/lang/Exception
    //   41	52	60	java/lang/Exception
  }
  
  public String bааа0430аа04300430а0430()
  {
    throw new Runtime("d2j fail translate: java.lang.IndexOutOfBoundsException: fromIndex < 0: -1\n\tat java.util.BitSet.nextSetBit(BitSet.java:712)\n\tat com.googlecode.dex2jar.ir.ts.array.FillArrayTransformer.makeSureAllElementAreAssigned(FillArrayTransformer.java:505)\n\tat com.googlecode.dex2jar.ir.ts.array.FillArrayTransformer.transformReportChanged(FillArrayTransformer.java:123)\n\tat com.googlecode.dex2jar.ir.ts.StatedTransformer.transform(StatedTransformer.java:10)\n\tat com.googlecode.d2j.dex.Dex2jar$2.optimize(Dex2jar.java:149)\n\tat com.googlecode.d2j.dex.Dex2Asm.convertCode(Dex2Asm.java:414)\n\tat com.googlecode.d2j.dex.ExDex2Asm.convertCode(ExDex2Asm.java:42)\n\tat com.googlecode.d2j.dex.Dex2jar$2.convertCode(Dex2jar.java:128)\n\tat com.googlecode.d2j.dex.Dex2Asm.convertMethod(Dex2Asm.java:509)\n\tat com.googlecode.d2j.dex.Dex2Asm.convertClass(Dex2Asm.java:406)\n\tat com.googlecode.d2j.dex.Dex2Asm.convertDex(Dex2Asm.java:422)\n\tat com.googlecode.d2j.dex.Dex2jar.doTranslate(Dex2jar.java:172)\n\tat com.googlecode.d2j.dex.Dex2jar.to(Dex2jar.java:272)\n\tat com.googlecode.dex2jar.tools.Dex2jarCmd.doCommandLine(Dex2jarCmd.java:108)\n\tat com.googlecode.dex2jar.tools.BaseCmd.doMain(BaseCmd.java:288)\n\tat com.googlecode.dex2jar.tools.Dex2jarCmd.main(Dex2jarCmd.java:32)\n");
  }
  
  public String bаааа0430а04300430а0430()
  {
    int i = b043Dн043Dннн043D043Dн;
    switch (i * (bн043D043Dннн043D043Dн + i) % b0430043004300430а0430а0430а0430())
    {
    default: 
      b043Dн043Dннн043D043Dн = bаааа04300430а0430а0430();
      bннн043Dнн043D043Dн = 42;
      if ((b043Dн043Dннн043D043Dн + bн043D043Dннн043D043Dн) * b043Dн043Dннн043D043Dн % b043D043D043Dннн043D043Dн != bннн043Dнн043D043Dн)
      {
        b043Dн043Dннн043D043Dн = 14;
        bннн043Dнн043D043Dн = bаааа04300430а0430а0430();
      }
      break;
    }
    try
    {
      String str = this.bн043D043D043D043D043Dн043Dн;
      return str;
    }
    catch (Exception localException)
    {
      throw localException;
    }
  }
  
  public boolean bааааа043004300430а0430()
  {
    boolean bool = this.b043D043Dнн043D043Dн043Dн;
    switch (1)
    {
    case 0: 
    default: 
      for (;;)
      {
        if ((bаааа04300430а0430а0430() + bн043D043Dннн043D043Dн) * bаааа04300430а0430а0430() % b043D043D043Dннн043D043Dн != bннн043Dнн043D043Dн)
        {
          b043Dн043Dннн043D043Dн = 42;
          bннн043Dнн043D043Dн = bаааа04300430а0430а0430();
        }
        switch (1)
        {
        }
      }
    }
    int i = b043Dн043Dннн043D043Dн;
    switch (i * (b0430ааа04300430а0430а0430() + i) % b043D043D043Dннн043D043Dн)
    {
    default: 
      b043Dн043Dннн043D043Dн = 62;
      bннн043Dнн043D043Dн = 27;
    }
    return bool;
  }
  
  public String bаааааа04300430а0430()
  {
    if ((b043Dн043Dннн043D043Dн + bн043D043Dннн043D043Dн) * b043Dн043Dннн043D043Dн % b043D043D043Dннн043D043Dн != bннн043Dнн043D043Dн)
    {
      b043Dн043Dннн043D043Dн = bаааа04300430а0430а0430();
      bннн043Dнн043D043Dн = 11;
    }
    if ((b043Dн043Dннн043D043Dн + bн043D043Dннн043D043Dн) * b043Dн043Dннн043D043Dн % b0430043004300430а0430а0430а0430() != bннн043Dнн043D043Dн)
    {
      b043Dн043Dннн043D043Dн = 82;
      bннн043Dнн043D043Dн = 16;
    }
    switch (1)
    {
    case 0: 
    default: 
      for (;;)
      {
        switch (1)
        {
        }
      }
    }
    return this.b043Dн043Dнн043Dн043Dн;
  }
}
