package kkkkkk;

public class ipippi
{
  public static int b043D043D043Dнн043D043Dнн = 37;
  public static int b043Dнн043Dн043D043Dнн = 1;
  public static int bн043Dн043Dн043D043Dнн = 2;
  public static int bннн043Dн043D043Dнн;
  private final kkkkpk b043Dн043Dнн043D043Dнн;
  private final ppipii bн043D043Dнн043D043Dнн;
  private final iiiipi bнн043Dнн043D043Dнн;
  
  public ipippi(iiiipi paramIiiipi, ppipii paramPpipii, kkkkpk paramKkkkpk)
  {
    this.bнн043Dнн043D043Dнн = paramIiiipi;
    this.bн043D043Dнн043D043Dнн = paramPpipii;
    this.b043Dн043Dнн043D043Dнн = paramKkkkpk;
  }
  
  public static int b043004300430а043004300430аа0430()
  {
    return 2;
  }
  
  public static int b0430аа0430043004300430аа0430()
  {
    return 1;
  }
  
  public static int bааа0430043004300430аа0430()
  {
    return 94;
  }
  
  public ppipii b0430043004300430043004300430аа0430()
  {
    ppipii localPpipii = this.bн043D043Dнн043D043Dнн;
    if ((b043D043D043Dнн043D043Dнн + b0430аа0430043004300430аа0430()) * b043D043D043Dнн043D043Dнн % bн043Dн043Dн043D043Dнн != bннн043Dн043D043Dнн)
    {
      if ((b043D043D043Dнн043D043Dнн + b043Dнн043Dн043D043Dнн) * b043D043D043Dнн043D043Dнн % bн043Dн043Dн043D043Dнн != bннн043Dн043D043Dнн)
      {
        b043D043D043Dнн043D043Dнн = 1;
        bннн043Dн043D043Dнн = bааа0430043004300430аа0430();
      }
      int i = bааа0430043004300430аа0430();
      switch (1)
      {
      case 0: 
      default: 
        for (;;)
        {
          switch (1)
          {
          }
        }
      }
      b043D043D043Dнн043D043Dнн = i;
      bннн043Dн043D043Dнн = 59;
    }
    return localPpipii;
  }
  
  /* Error */
  public ippiip b04300430а0430043004300430аа0430()
  {
    // Byte code:
    //   0: aload_0
    //   1: getfield 27	kkkkkk/ipippi:bнн043Dнн043D043Dнн	Lkkkkkk/iiiipi;
    //   4: astore 6
    //   6: getstatic 40	kkkkkk/ipippi:b043D043D043Dнн043D043Dнн	I
    //   9: istore_1
    //   10: iload_1
    //   11: getstatic 48	kkkkkk/ipippi:b043Dнн043Dн043D043Dнн	I
    //   14: iload_1
    //   15: iadd
    //   16: imul
    //   17: invokestatic 56	kkkkkk/ipippi:b043004300430а043004300430аа0430	()I
    //   20: irem
    //   21: tableswitch	default:+19->40, 0:+31->52
    //   40: invokestatic 50	kkkkkk/ipippi:bааа0430043004300430аа0430	()I
    //   43: putstatic 40	kkkkkk/ipippi:b043D043D043Dнн043D043Dнн	I
    //   46: invokestatic 50	kkkkkk/ipippi:bааа0430043004300430аа0430	()I
    //   49: putstatic 46	kkkkkk/ipippi:bннн043Dн043D043Dнн	I
    //   52: iconst_1
    //   53: tableswitch	default:+23->76, 0:+-47->6, 1:+50->103
    //   76: iconst_0
    //   77: tableswitch	default:+23->100, 0:+26->103, 1:+-71->6
    //   100: goto -24 -> 76
    //   103: getstatic 40	kkkkkk/ipippi:b043D043D043Dнн043D043Dнн	I
    //   106: istore_1
    //   107: getstatic 48	kkkkkk/ipippi:b043Dнн043Dн043D043Dнн	I
    //   110: istore_2
    //   111: getstatic 40	kkkkkk/ipippi:b043D043D043Dнн043D043Dнн	I
    //   114: istore_3
    //   115: getstatic 44	kkkkkk/ipippi:bн043Dн043Dн043D043Dнн	I
    //   118: istore 4
    //   120: getstatic 46	kkkkkk/ipippi:bннн043Dн043D043Dнн	I
    //   123: istore 5
    //   125: iload_1
    //   126: iload_2
    //   127: iadd
    //   128: iload_3
    //   129: imul
    //   130: iload 4
    //   132: irem
    //   133: iload 5
    //   135: if_icmpeq +16 -> 151
    //   138: bipush 16
    //   140: putstatic 40	kkkkkk/ipippi:b043D043D043Dнн043D043Dнн	I
    //   143: invokestatic 50	kkkkkk/ipippi:bааа0430043004300430аа0430	()I
    //   146: istore_1
    //   147: iload_1
    //   148: putstatic 46	kkkkkk/ipippi:bннн043Dн043D043Dнн	I
    //   151: aload 6
    //   153: invokevirtual 61	kkkkkk/iiiipi:b0430а0430ааа04300430а0430	()Lkkkkkk/ippiip;
    //   156: astore 6
    //   158: aload 6
    //   160: areturn
    //   161: astore 6
    //   163: aload 6
    //   165: athrow
    //   166: astore 6
    //   168: aload 6
    //   170: athrow
    // Local variable table:
    //   start	length	slot	name	signature
    //   0	171	0	this	ipippi
    //   9	139	1	i	int
    //   110	18	2	j	int
    //   114	16	3	k	int
    //   118	15	4	m	int
    //   123	13	5	n	int
    //   4	155	6	localObject	Object
    //   161	3	6	localException1	Exception
    //   166	3	6	localException2	Exception
    // Exception table:
    //   from	to	target	type
    //   0	6	161	java/lang/Exception
    //   103	125	161	java/lang/Exception
    //   147	151	161	java/lang/Exception
    //   151	158	161	java/lang/Exception
    //   138	147	166	java/lang/Exception
  }
  
  /* Error */
  public kkkkpk b0430а04300430043004300430аа0430()
  {
    // Byte code:
    //   0: iconst_0
    //   1: istore_1
    //   2: iconst_1
    //   3: istore_2
    //   4: iload_2
    //   5: iconst_0
    //   6: idiv
    //   7: istore_2
    //   8: iload_1
    //   9: iconst_0
    //   10: idiv
    //   11: istore_3
    //   12: iload_3
    //   13: istore_1
    //   14: goto -6 -> 8
    //   17: astore 4
    //   19: bipush 51
    //   21: putstatic 40	kkkkkk/ipippi:b043D043D043Dнн043D043Dнн	I
    //   24: aload_0
    //   25: getfield 31	kkkkkk/ipippi:b043Dн043Dнн043D043Dнн	Lkkkkkk/kkkkpk;
    //   28: astore 4
    //   30: aload 4
    //   32: areturn
    //   33: astore 4
    //   35: aload 4
    //   37: athrow
    //   38: astore 4
    //   40: aload 4
    //   42: athrow
    //   43: astore 4
    //   45: aload 4
    //   47: athrow
    //   48: astore 4
    //   50: bipush 80
    //   52: putstatic 40	kkkkkk/ipippi:b043D043D043Dнн043D043Dнн	I
    //   55: new 65	java/lang/NullPointerException
    //   58: dup
    //   59: invokespecial 66	java/lang/NullPointerException:<init>	()V
    //   62: athrow
    //   63: astore 4
    //   65: invokestatic 50	kkkkkk/ipippi:bааа0430043004300430аа0430	()I
    //   68: putstatic 40	kkkkkk/ipippi:b043D043D043Dнн043D043Dнн	I
    //   71: new 65	java/lang/NullPointerException
    //   74: dup
    //   75: invokespecial 66	java/lang/NullPointerException:<init>	()V
    //   78: athrow
    //   79: astore 4
    //   81: invokestatic 50	kkkkkk/ipippi:bааа0430043004300430аа0430	()I
    //   84: putstatic 40	kkkkkk/ipippi:b043D043D043Dнн043D043Dнн	I
    //   87: goto -83 -> 4
    // Local variable table:
    //   start	length	slot	name	signature
    //   0	90	0	this	ipippi
    //   1	13	1	i	int
    //   3	5	2	j	int
    //   11	2	3	k	int
    //   17	1	4	localException1	Exception
    //   28	3	4	localKkkkpk	kkkkpk
    //   33	3	4	localException2	Exception
    //   38	3	4	localException3	Exception
    //   43	3	4	localException4	Exception
    //   48	1	4	localException5	Exception
    //   63	1	4	localException6	Exception
    //   79	1	4	localException7	Exception
    // Exception table:
    //   from	to	target	type
    //   4	8	17	java/lang/Exception
    //   24	30	33	java/lang/Exception
    //   35	38	38	java/lang/Exception
    //   19	24	43	java/lang/Exception
    //   8	12	48	java/lang/Exception
    //   55	63	63	java/lang/Exception
    //   71	79	79	java/lang/Exception
  }
  
  public ipippi.piippi bа043004300430043004300430аа0430()
  {
    if (b0430043004300430043004300430аа0430() != null)
    {
      ipippi.piippi localPiippi = ipippi.piippi.LEAD;
      int i = b043D043D043Dнн043D043Dнн;
      switch (i * (b043Dнн043Dн043D043Dнн + i) % b043004300430а043004300430аа0430())
      {
      default: 
        b043D043D043Dнн043D043Dнн = bааа0430043004300430аа0430();
        bннн043Dн043D043Dнн = 82;
      }
      return localPiippi;
    }
    if (b04300430а0430043004300430аа0430() != null) {
      return ipippi.piippi.CUSTOM_ALERT;
    }
    while (bа0430а0430043004300430аа0430() == null) {
      return ipippi.piippi.NONE;
    }
    return ipippi.piippi.ACCOUNT_ALERT;
  }
  
  public String bа0430а0430043004300430аа0430()
  {
    try
    {
      int i = b043D043D043Dнн043D043Dнн;
      int j = b043Dнн043Dн043D043Dнн;
      int k = b043D043D043Dнн043D043Dнн;
      int m = bн043Dн043Dн043D043Dнн;
      int n = bннн043Dн043D043Dнн;
      if ((i + j) * k % m == n) {
        break label115;
      }
      i = bааа0430043004300430аа0430();
      switch (i * (b043Dнн043Dн043D043Dнн + i) % bн043Dн043Dн043D043Dнн)
      {
      default: 
        b043D043D043Dнн043D043Dнн = bааа0430043004300430аа0430();
        bннн043Dн043D043Dнн = bааа0430043004300430аа0430();
      }
    }
    catch (Exception localException1)
    {
      String str;
      throw localException1;
    }
    try
    {
      b043D043D043Dнн043D043Dнн = 63;
      bннн043Dн043D043Dнн = 88;
    }
    catch (Exception localException2)
    {
      throw localException2;
    }
    str = this.bнн043Dнн043D043Dнн.bаа0430а0430аа0430а0430();
    return str;
    label115:
    switch (1)
    {
    }
    for (;;)
    {
      switch (0)
      {
      }
    }
  }
  
  public iiiipi bаа04300430043004300430аа0430()
  {
    throw new Runtime("d2j fail translate: java.lang.IndexOutOfBoundsException: fromIndex < 0: -1\n\tat java.util.BitSet.nextSetBit(BitSet.java:712)\n\tat com.googlecode.dex2jar.ir.ts.array.FillArrayTransformer.makeSureAllElementAreAssigned(FillArrayTransformer.java:505)\n\tat com.googlecode.dex2jar.ir.ts.array.FillArrayTransformer.transformReportChanged(FillArrayTransformer.java:123)\n\tat com.googlecode.dex2jar.ir.ts.StatedTransformer.transform(StatedTransformer.java:10)\n\tat com.googlecode.d2j.dex.Dex2jar$2.optimize(Dex2jar.java:149)\n\tat com.googlecode.d2j.dex.Dex2Asm.convertCode(Dex2Asm.java:414)\n\tat com.googlecode.d2j.dex.ExDex2Asm.convertCode(ExDex2Asm.java:42)\n\tat com.googlecode.d2j.dex.Dex2jar$2.convertCode(Dex2jar.java:128)\n\tat com.googlecode.d2j.dex.Dex2Asm.convertMethod(Dex2Asm.java:509)\n\tat com.googlecode.d2j.dex.Dex2Asm.convertClass(Dex2Asm.java:406)\n\tat com.googlecode.d2j.dex.Dex2Asm.convertDex(Dex2Asm.java:422)\n\tat com.googlecode.d2j.dex.Dex2jar.doTranslate(Dex2jar.java:172)\n\tat com.googlecode.d2j.dex.Dex2jar.to(Dex2jar.java:272)\n\tat com.googlecode.dex2jar.tools.Dex2jarCmd.doCommandLine(Dex2jarCmd.java:108)\n\tat com.googlecode.dex2jar.tools.BaseCmd.doMain(BaseCmd.java:288)\n\tat com.googlecode.dex2jar.tools.Dex2jarCmd.main(Dex2jarCmd.java:32)\n");
  }
}
