package kkkkkk;

import android.support.annotation.NonNull;
import android.support.annotation.StringRes;

public class ippiip
{
  public static int b043D043D043Dн043D043Dннн = 2;
  public static int b043Dн043Dн043D043Dннн = 0;
  public static int bн043D043Dн043D043Dннн = 1;
  public static int bнн043Dн043D043Dннн = 97;
  @NonNull
  private ippiip.pipiip b043D043D043D043Dн043Dннн;
  @StringRes
  private final int b043D043Dнн043D043Dннн;
  @StringRes
  private int b043Dннн043D043Dннн;
  @StringRes
  private int bн043Dнн043D043Dннн;
  @NonNull
  private String bнннн043D043Dннн;
  
  public ippiip(@StringRes int paramInt1, @NonNull String paramString, @StringRes int paramInt2, @StringRes int paramInt3, @NonNull ippiip.pipiip paramPipiip)
  {
    this.b043D043Dнн043D043Dннн = paramInt1;
    this.bнннн043D043Dннн = paramString;
    this.b043D043D043D043Dн043Dннн = paramPipiip;
    this.b043Dннн043D043Dннн = paramInt2;
    this.bн043Dнн043D043Dннн = paramInt3;
  }
  
  public static int b043004300430ааа0430аа0430()
  {
    return 1;
  }
  
  public static int b0430аа0430аа0430аа0430()
  {
    return 98;
  }
  
  public static int bа0430а0430аа0430аа0430()
  {
    return 0;
  }
  
  public static int bааа0430аа0430аа0430()
  {
    return 2;
  }
  
  @StringRes
  public int b0430043004300430аа0430аа0430()
  {
    int i = this.b043D043Dнн043D043Dннн;
    if ((bнн043Dн043D043Dннн + b043004300430ааа0430аа0430()) * bнн043Dн043D043Dннн % b043D043D043Dн043D043Dннн != b043Dн043Dн043D043Dннн)
    {
      bнн043Dн043D043Dннн = b0430аа0430аа0430аа0430();
      b043Dн043Dн043D043Dннн = 93;
    }
    return i;
  }
  
  @NonNull
  public ippiip.pipiip b04300430а0430аа0430аа0430()
  {
    if ((bнн043Dн043D043Dннн + bн043D043Dн043D043Dннн) * bнн043Dн043D043Dннн % b043D043D043Dн043D043Dннн != b043Dн043Dн043D043Dннн)
    {
      bнн043Dн043D043Dннн = 70;
      b043Dн043Dн043D043Dннн = 34;
    }
    return this.b043D043D043D043Dн043Dннн;
  }
  
  /* Error */
  @StringRes
  public int b0430а04300430аа0430аа0430()
  {
    // Byte code:
    //   0: aload_0
    //   1: getfield 37	kkkkkk/ippiip:b043Dннн043D043Dннн	I
    //   4: istore_1
    //   5: getstatic 49	kkkkkk/ippiip:bнн043Dн043D043Dннн	I
    //   8: istore_2
    //   9: getstatic 62	kkkkkk/ippiip:bн043D043Dн043D043Dннн	I
    //   12: istore_3
    //   13: getstatic 49	kkkkkk/ippiip:bнн043Dн043D043Dннн	I
    //   16: istore 4
    //   18: getstatic 53	kkkkkk/ippiip:b043D043D043Dн043D043Dннн	I
    //   21: istore 5
    //   23: getstatic 55	kkkkkk/ippiip:b043Dн043Dн043D043Dннн	I
    //   26: istore 6
    //   28: iload_2
    //   29: iload_3
    //   30: iadd
    //   31: iload 4
    //   33: imul
    //   34: iload 5
    //   36: irem
    //   37: iload 6
    //   39: if_icmpeq +58 -> 97
    //   42: getstatic 49	kkkkkk/ippiip:bнн043Dн043D043Dннн	I
    //   45: istore_2
    //   46: iload_2
    //   47: getstatic 62	kkkkkk/ippiip:bн043D043Dн043D043Dннн	I
    //   50: iload_2
    //   51: iadd
    //   52: imul
    //   53: getstatic 53	kkkkkk/ippiip:b043D043D043Dн043D043Dннн	I
    //   56: irem
    //   57: tableswitch	default:+19->76, 0:+29->86
    //   76: bipush 12
    //   78: putstatic 49	kkkkkk/ippiip:bнн043Dн043D043Dннн	I
    //   81: bipush 37
    //   83: putstatic 55	kkkkkk/ippiip:b043Dн043Dн043D043Dннн	I
    //   86: bipush 96
    //   88: putstatic 49	kkkkkk/ippiip:bнн043Dн043D043Dннн	I
    //   91: invokestatic 57	kkkkkk/ippiip:b0430аа0430аа0430аа0430	()I
    //   94: putstatic 55	kkkkkk/ippiip:b043Dн043Dн043D043Dннн	I
    //   97: iconst_0
    //   98: tableswitch	default:+22->120, 0:+49->147, 1:+-1->97
    //   120: iconst_0
    //   121: tableswitch	default:+23->144, 0:+26->147, 1:+-24->97
    //   144: goto -24 -> 120
    //   147: iload_1
    //   148: ireturn
    //   149: astore 7
    //   151: aload 7
    //   153: athrow
    //   154: astore 7
    //   156: aload 7
    //   158: athrow
    // Local variable table:
    //   start	length	slot	name	signature
    //   0	159	0	this	ippiip
    //   4	144	1	i	int
    //   8	45	2	j	int
    //   12	19	3	k	int
    //   16	18	4	m	int
    //   21	16	5	n	int
    //   26	14	6	i1	int
    //   149	3	7	localException1	Exception
    //   154	3	7	localException2	Exception
    // Exception table:
    //   from	to	target	type
    //   0	28	149	java/lang/Exception
    //   86	97	154	java/lang/Exception
  }
  
  @StringRes
  public int bа043004300430аа0430аа0430()
  {
    switch (1)
    {
    case 0: 
    default: 
      for (;;)
      {
        switch (0)
        {
        }
      }
    }
    int i = bнн043Dн043D043Dннн;
    int j = b043004300430ааа0430аа0430();
    switch (0)
    {
    case 1: 
    default: 
      for (;;)
      {
        switch (1)
        {
        }
      }
    }
    if ((i + j) * bнн043Dн043D043Dннн % b043D043D043Dн043D043Dннн != b043Dн043Dн043D043Dннн)
    {
      bнн043Dн043D043Dннн = b0430аа0430аа0430аа0430();
      b043Dн043Dн043D043Dннн = 96;
      if ((bнн043Dн043D043Dннн + bн043D043Dн043D043Dннн) * bнн043Dн043D043Dннн % b043D043D043Dн043D043Dннн != b043Dн043Dн043D043Dннн)
      {
        bнн043Dн043D043Dннн = 98;
        b043Dн043Dн043D043Dннн = 72;
      }
    }
    return this.bн043Dнн043D043Dннн;
  }
  
  @NonNull
  public String bаа04300430аа0430аа0430()
  {
    return this.bнннн043D043Dннн;
  }
}
