package kkkkkk;

import android.app.Activity;
import android.app.Notification.Builder;
import android.content.Context;
import android.content.pm.ApplicationInfo;
import android.os.Bundle;
import android.support.annotation.Nullable;
import android.support.v4.app.Fragment;
import android.text.TextUtils;
import com.liveperson.infra.ConversationViewParams;
import com.liveperson.infra.LPAuthenticationParams;
import com.liveperson.messaging.model.AgentData;
import com.liveperson.messaging.sdk.R.drawable;
import java.util.Map;

public class jaajaa
{
  public static int b043104310431б0431б0431бб = 2;
  private static final String b04310431бб0431б0431бб = jaajaa.class.getSimpleName();
  public static xxxddx b0431б0431б0431б0431бб;
  public static int b0431бб04310431б0431бб = 0;
  public static final String b0431ббб0431б0431бб = "56F:?=M9<J?9,(:*C17.?4,/!\034\0368%\034)(\025\032\027$/\020\021!\025\032\030";
  public static int bб04310431б0431б0431бб = 1;
  public static final String bб0431бб0431б0431бб = "EFVJOM]ILZOI<8J:SAG>OD<?1,.H5,98%*'4?$61.\034";
  private static String bбб0431б0431б0431бб;
  public static int bббб04310431б0431бб = 11;
  
  static
  {
    int i = b0436жж043604360436жжжж();
    switch (i * (bб04310431б0431б0431бб + i) % b043104310431б0431б0431бб)
    {
    default: 
      bб04310431б0431б0431бб = 91;
    }
    String str = gguuuu.bккккк043Aкк043A043A(b0431ббб0431б0431бб, '', '\002');
    if ((bббб04310431б0431бб + bб04310431б0431б0431бб) * bббб04310431б0431бб % b043104310431б0431б0431бб != b0431бб04310431б0431бб)
    {
      bббб04310431б0431бб = 8;
      b0431бб04310431б0431бб = b0436жж043604360436жжжж();
    }
    b0431ббб0431б0431бб = str;
    bб0431бб0431б0431бб = gguuuu.bк043Aккк043Aкк043A043A(bб0431бб0431б0431бб, '', '$', '\000');
    switch (0)
    {
    case 1: 
    default: 
      for (;;)
      {
        switch (1)
        {
        case 0: 
        default: 
          for (;;)
          {
            switch (1)
            {
            }
          }
        }
        switch (1)
        {
        }
      }
    }
  }
  
  private jaajaa() {}
  
  /* Error */
  public static boolean b043604360436043604360436жжжж()
  {
    // Byte code:
    //   0: invokestatic 71	kkkkkk/jaajaa:b04360436ж0436жж0436жжж	()Z
    //   3: ifeq +98 -> 101
    //   6: invokestatic 77	kkkkkk/ykykky:bШШ0428Ш0428ШШШ04280428	()Lkkkkkk/ykykky;
    //   9: astore_3
    //   10: getstatic 44	kkkkkk/jaajaa:bббб04310431б0431бб	I
    //   13: getstatic 32	kkkkkk/jaajaa:bб04310431б0431б0431бб	I
    //   16: iadd
    //   17: getstatic 44	kkkkkk/jaajaa:bббб04310431б0431бб	I
    //   20: imul
    //   21: getstatic 34	kkkkkk/jaajaa:b043104310431б0431б0431бб	I
    //   24: irem
    //   25: getstatic 46	kkkkkk/jaajaa:b0431бб04310431б0431бб	I
    //   28: if_icmpeq +14 -> 42
    //   31: bipush 22
    //   33: putstatic 44	kkkkkk/jaajaa:bббб04310431б0431бб	I
    //   36: invokestatic 30	kkkkkk/jaajaa:b0436жж043604360436жжжж	()I
    //   39: putstatic 46	kkkkkk/jaajaa:b0431бб04310431б0431бб	I
    //   42: aload_3
    //   43: invokevirtual 81	kkkkkk/ykykky:b04280428ШШ0428ШШШ04280428	()Lkkkkkk/kkyykk;
    //   46: getstatic 83	kkkkkk/jaajaa:bбб0431б0431б0431бб	Ljava/lang/String;
    //   49: invokevirtual 89	kkkkkk/kkyykk:bШШШ0428Ш04280428ШШ0428	(Ljava/lang/String;)Z
    //   52: istore_2
    //   53: iload_2
    //   54: ifeq +47 -> 101
    //   57: iconst_1
    //   58: ireturn
    //   59: iload_0
    //   60: iload_1
    //   61: iload_0
    //   62: iadd
    //   63: imul
    //   64: getstatic 34	kkkkkk/jaajaa:b043104310431б0431б0431бб	I
    //   67: irem
    //   68: tableswitch	default:+20->88, 0:+97->165
    //   88: bipush 9
    //   90: putstatic 44	kkkkkk/jaajaa:bббб04310431б0431бб	I
    //   93: invokestatic 30	kkkkkk/jaajaa:b0436жж043604360436жжжж	()I
    //   96: putstatic 46	kkkkkk/jaajaa:b0431бб04310431б0431бб	I
    //   99: iconst_0
    //   100: ireturn
    //   101: getstatic 44	kkkkkk/jaajaa:bббб04310431б0431бб	I
    //   104: istore_0
    //   105: invokestatic 92	kkkkkk/jaajaa:bж0436ж043604360436жжжж	()I
    //   108: istore_1
    //   109: iconst_0
    //   110: tableswitch	default:+22->132, 0:+-51->59, 1:+-1->109
    //   132: iconst_1
    //   133: tableswitch	default:+23->156, 0:+-24->109, 1:+-74->59
    //   156: goto -24 -> 132
    //   159: astore_3
    //   160: aload_3
    //   161: athrow
    //   162: astore_3
    //   163: aload_3
    //   164: athrow
    //   165: iconst_0
    //   166: ireturn
    // Local variable table:
    //   start	length	slot	name	signature
    //   59	46	0	i	int
    //   60	49	1	j	int
    //   52	2	2	bool	boolean
    //   9	34	3	localYkykky	ykykky
    //   159	2	3	localException1	Exception
    //   162	2	3	localException2	Exception
    // Exception table:
    //   from	to	target	type
    //   0	10	159	java/lang/Exception
    //   42	53	162	java/lang/Exception
  }
  
  @Deprecated
  public static void b04360436043604360436ж0436жжж()
  {
    int i = b0436жж043604360436жжжж();
    int j = bб04310431б0431б0431бб;
    int k = b0436жж043604360436жжжж();
    int m = b043104310431б0431б0431бб;
    if ((bббб04310431б0431бб + bб04310431б0431б0431бб) * bббб04310431б0431бб % b043104310431б0431б0431бб != b0431бб04310431б0431бб)
    {
      bббб04310431б0431бб = 38;
      b0431бб04310431б0431бб = b0436жж043604360436жжжж();
    }
    if ((i + j) * k % m != b0431бб04310431б0431бб)
    {
      bббб04310431б0431бб = 87;
      b0431бб04310431б0431бб = 13;
    }
    try
    {
      bжжжжж04360436жжж(null);
      return;
    }
    catch (Exception localException)
    {
      throw localException;
    }
  }
  
  /* Error */
  public static void b0436043604360436жж0436жжж(LPAuthenticationParams paramLPAuthenticationParams)
  {
    // Byte code:
    //   0: invokestatic 71	kkkkkk/jaajaa:b04360436ж0436жж0436жжж	()Z
    //   3: istore 4
    //   5: iload 4
    //   7: ifne +4 -> 11
    //   10: return
    //   11: invokestatic 77	kkkkkk/ykykky:bШШ0428Ш0428ШШШ04280428	()Lkkkkkk/ykykky;
    //   14: invokevirtual 81	kkkkkk/ykykky:b04280428ШШ0428ШШШ04280428	()Lkkkkkk/kkyykk;
    //   17: astore 5
    //   19: aload 5
    //   21: getstatic 83	kkkkkk/jaajaa:bбб0431б0431б0431бб	Ljava/lang/String;
    //   24: aload_0
    //   25: invokevirtual 105	kkkkkk/kkyykk:b0428ШШ0428042804280428ШШ0428	(Ljava/lang/String;Lcom/liveperson/infra/LPAuthenticationParams;)V
    //   28: getstatic 44	kkkkkk/jaajaa:bббб04310431б0431бб	I
    //   31: istore_1
    //   32: getstatic 32	kkkkkk/jaajaa:bб04310431б0431б0431бб	I
    //   35: istore_2
    //   36: getstatic 34	kkkkkk/jaajaa:b043104310431б0431б0431бб	I
    //   39: istore_3
    //   40: iload_1
    //   41: iload_2
    //   42: iload_1
    //   43: iadd
    //   44: imul
    //   45: iload_3
    //   46: irem
    //   47: tableswitch	default:+17->64, 0:+-37->10
    //   64: invokestatic 30	kkkkkk/jaajaa:b0436жж043604360436жжжж	()I
    //   67: putstatic 44	kkkkkk/jaajaa:bббб04310431б0431бб	I
    //   70: bipush 60
    //   72: putstatic 46	kkkkkk/jaajaa:b0431бб04310431б0431бб	I
    //   75: getstatic 44	kkkkkk/jaajaa:bббб04310431б0431бб	I
    //   78: istore_1
    //   79: iload_1
    //   80: getstatic 32	kkkkkk/jaajaa:bб04310431б0431б0431бб	I
    //   83: iload_1
    //   84: iadd
    //   85: imul
    //   86: getstatic 34	kkkkkk/jaajaa:b043104310431б0431б0431бб	I
    //   89: irem
    //   90: tableswitch	default:+18->108, 0:+-80->10
    //   108: invokestatic 30	kkkkkk/jaajaa:b0436жж043604360436жжжж	()I
    //   111: putstatic 44	kkkkkk/jaajaa:bббб04310431б0431бб	I
    //   114: bipush 41
    //   116: putstatic 46	kkkkkk/jaajaa:b0431бб04310431б0431бб	I
    //   119: return
    //   120: astore_0
    //   121: aload_0
    //   122: athrow
    //   123: astore_0
    //   124: aload_0
    //   125: athrow
    // Local variable table:
    //   start	length	slot	name	signature
    //   0	126	0	paramLPAuthenticationParams	LPAuthenticationParams
    //   31	55	1	i	int
    //   35	9	2	j	int
    //   39	8	3	k	int
    //   3	3	4	bool	boolean
    //   17	3	5	localKkyykk	kkyykk
    // Exception table:
    //   from	to	target	type
    //   0	5	120	java/lang/Exception
    //   19	36	120	java/lang/Exception
    //   64	70	120	java/lang/Exception
    //   11	19	123	java/lang/Exception
    //   36	40	123	java/lang/Exception
    //   70	75	123	java/lang/Exception
  }
  
  /* Error */
  public static void b043604360436ж0436ж0436жжж(android.app.PendingIntent paramPendingIntent)
  {
    // Byte code:
    //   0: aload_0
    //   1: ifnull +133 -> 134
    //   4: invokestatic 77	kkkkkk/ykykky:bШШ0428Ш0428ШШШ04280428	()Lkkkkkk/ykykky;
    //   7: astore_1
    //   8: getstatic 44	kkkkkk/jaajaa:bббб04310431б0431бб	I
    //   11: getstatic 32	kkkkkk/jaajaa:bб04310431б0431б0431бб	I
    //   14: iadd
    //   15: getstatic 44	kkkkkk/jaajaa:bббб04310431б0431бб	I
    //   18: imul
    //   19: getstatic 34	kkkkkk/jaajaa:b043104310431б0431б0431бб	I
    //   22: irem
    //   23: getstatic 46	kkkkkk/jaajaa:b0431бб04310431б0431бб	I
    //   26: if_icmpeq +98 -> 124
    //   29: invokestatic 30	kkkkkk/jaajaa:b0436жж043604360436жжжж	()I
    //   32: putstatic 44	kkkkkk/jaajaa:bббб04310431б0431бб	I
    //   35: iconst_0
    //   36: tableswitch	default:+24->60, 0:+51->87, 1:+-1->35
    //   60: iconst_1
    //   61: tableswitch	default:+23->84, 0:+-26->35, 1:+26->87
    //   84: goto -24 -> 60
    //   87: bipush 27
    //   89: putstatic 46	kkkkkk/jaajaa:b0431бб04310431б0431бб	I
    //   92: getstatic 44	kkkkkk/jaajaa:bббб04310431б0431бб	I
    //   95: getstatic 32	kkkkkk/jaajaa:bб04310431б0431б0431бб	I
    //   98: iadd
    //   99: getstatic 44	kkkkkk/jaajaa:bббб04310431б0431бб	I
    //   102: imul
    //   103: getstatic 34	kkkkkk/jaajaa:b043104310431б0431б0431бб	I
    //   106: irem
    //   107: getstatic 46	kkkkkk/jaajaa:b0431бб04310431б0431бб	I
    //   110: if_icmpeq +14 -> 124
    //   113: bipush 16
    //   115: putstatic 44	kkkkkk/jaajaa:bббб04310431б0431бб	I
    //   118: invokestatic 30	kkkkkk/jaajaa:b0436жж043604360436жжжж	()I
    //   121: putstatic 46	kkkkkk/jaajaa:b0431бб04310431б0431бб	I
    //   124: aload_1
    //   125: invokevirtual 81	kkkkkk/ykykky:b04280428ШШ0428ШШШ04280428	()Lkkkkkk/kkyykk;
    //   128: astore_1
    //   129: aload_1
    //   130: aload_0
    //   131: invokevirtual 114	kkkkkk/kkyykk:b0428Ш04280428ШШШШ04280428	(Landroid/app/PendingIntent;)V
    //   134: return
    //   135: astore_0
    //   136: aload_0
    //   137: athrow
    //   138: astore_0
    //   139: aload_0
    //   140: athrow
    // Local variable table:
    //   start	length	slot	name	signature
    //   0	141	0	paramPendingIntent	android.app.PendingIntent
    //   7	123	1	localObject	Object
    // Exception table:
    //   from	to	target	type
    //   4	8	135	java/lang/Exception
    //   124	129	135	java/lang/Exception
    //   129	134	138	java/lang/Exception
  }
  
  @Nullable
  public static mmmjjj b043604360436жжж0436жжж(Context paramContext, Map<String, String> paramMap, String paramString, boolean paramBoolean)
  {
    if (TextUtils.isEmpty(paramString))
    {
      xtxtxt.b0438и0438и04380438и0438ии(b04310431бб0431б0431бб, gguuuu.bккккк043Aкк043A043A("k\f;\\\fy\006z64|y\002w{s+z~{o&rivubgd=", 'K', '\002'));
      paramMap = null;
    }
    for (;;)
    {
      int i = bббб04310431б0431бб;
      switch (i * (bб04310431б0431б0431бб + i) % b043104310431б0431б0431бб)
      {
      default: 
        bббб04310431б0431бб = b0436жж043604360436жжжж();
        b0431бб04310431б0431бб = b0436жж043604360436жжжж();
      }
      switch (0)
      {
      case 1: 
      default: 
        for (;;)
        {
          switch (1)
          {
          }
        }
      }
      return paramMap;
      mmmjjj localMmmjjj = rnrnrn.bии0438и0438и043804380438и(paramString, paramMap);
      paramMap = localMmmjjj;
      if (localMmmjjj != null)
      {
        nrrrnr.instance.bии04380438иии04380438и(paramContext, paramString, localMmmjjj, paramBoolean, R.drawable.liveperson_icon);
        switch (1)
        {
        case 0: 
        default: 
          for (;;)
          {
            switch (0)
            {
            }
          }
        }
        i = bббб04310431б0431бб;
        paramMap = localMmmjjj;
        switch (i * (bб04310431б0431б0431бб + i) % b043104310431б0431б0431бб)
        {
        }
        bббб04310431б0431бб = 4;
        b0431бб04310431б0431бб = b0436жж043604360436жжжж();
        paramMap = localMmmjjj;
      }
    }
  }
  
  public static int b04360436ж043604360436жжжж()
  {
    return 0;
  }
  
  @Deprecated
  public static void b04360436ж04360436ж0436жжж(String paramString1, String paramString2, String paramString3, String paramString4)
  {
    if (!b04360436ж0436жж0436жжж()) {
      return;
    }
    paramString1 = new ajaaja.aajaja().b0436жжж043604360436жжж(paramString2).bж0436жж043604360436жжж(paramString3);
    switch (1)
    {
    case 0: 
    default: 
      for (;;)
      {
        if ((bббб04310431б0431бб + bб04310431б0431б0431бб) * bббб04310431б0431бб % b043104310431б0431б0431бб != b0431бб04310431б0431бб)
        {
          bббб04310431б0431бб = b0436жж043604360436жжжж();
          b0431бб04310431б0431бб = b0436жж043604360436жжжж();
        }
        switch (1)
        {
        }
      }
    }
    int i = bббб04310431б0431бб;
    switch (i * (bб04310431б0431б0431бб + i) % b043104310431б0431б0431бб)
    {
    default: 
      bббб04310431б0431бб = b0436жж043604360436жжжж();
      b0431бб04310431б0431бб = b0436жж043604360436жжжж();
    }
    bж0436ж04360436ж0436жжж(paramString1.bжж0436ж043604360436жжж(paramString4).bж043604360436ж04360436жжж());
  }
  
  /* Error */
  private static boolean b04360436ж0436жж0436жжж()
  {
    // Byte code:
    //   0: invokestatic 185	kkkkkk/ttxttx:bи0438и04380438иии0438и	()Lkkkkkk/ttxttx;
    //   3: invokevirtual 188	kkkkkk/ttxttx:b0438043804380438ииии0438и	()Z
    //   6: istore_1
    //   7: getstatic 83	kkkkkk/jaajaa:bбб0431б0431б0431бб	Ljava/lang/String;
    //   10: invokestatic 123	android/text/TextUtils:isEmpty	(Ljava/lang/CharSequence;)Z
    //   13: istore_2
    //   14: iload_1
    //   15: ifeq +80 -> 95
    //   18: iconst_1
    //   19: istore_0
    //   20: iload_0
    //   21: iconst_0
    //   22: idiv
    //   23: istore_0
    //   24: goto -4 -> 20
    //   27: astore_3
    //   28: invokestatic 30	kkkkkk/jaajaa:b0436жж043604360436жжжж	()I
    //   31: putstatic 44	kkkkkk/jaajaa:bббб04310431б0431бб	I
    //   34: iload_2
    //   35: ifeq +60 -> 95
    //   38: getstatic 44	kkkkkk/jaajaa:bббб04310431б0431бб	I
    //   41: istore_0
    //   42: iload_0
    //   43: getstatic 32	kkkkkk/jaajaa:bб04310431б0431б0431бб	I
    //   46: iload_0
    //   47: iadd
    //   48: imul
    //   49: getstatic 34	kkkkkk/jaajaa:b043104310431б0431б0431бб	I
    //   52: irem
    //   53: tableswitch	default:+19->72, 0:+30->83
    //   72: bipush 19
    //   74: putstatic 44	kkkkkk/jaajaa:bббб04310431б0431бб	I
    //   77: invokestatic 30	kkkkkk/jaajaa:b0436жж043604360436жжжж	()I
    //   80: putstatic 46	kkkkkk/jaajaa:b0431бб04310431б0431бб	I
    //   83: invokestatic 185	kkkkkk/ttxttx:bи0438и04380438иии0438и	()Lkkkkkk/ttxttx;
    //   86: invokevirtual 192	kkkkkk/ttxttx:b04380438и04380438иии0438и	()Lkkkkkk/xtxttx;
    //   89: invokevirtual 197	kkkkkk/xtxttx:b0438и04380438и0438ии0438и	()Ljava/lang/String;
    //   92: putstatic 83	kkkkkk/jaajaa:bбб0431б0431б0431бб	Ljava/lang/String;
    //   95: getstatic 60	kkkkkk/jaajaa:b04310431бб0431б0431бб	Ljava/lang/String;
    //   98: astore_3
    //   99: new 199	java/lang/StringBuilder
    //   102: dup
    //   103: invokespecial 200	java/lang/StringBuilder:<init>	()V
    //   106: ldc -54
    //   108: bipush 40
    //   110: iconst_4
    //   111: invokestatic 42	kkkkkk/gguuuu:bккккк043Aкк043A043A	(Ljava/lang/String;CC)Ljava/lang/String;
    //   114: invokevirtual 206	java/lang/StringBuilder:append	(Ljava/lang/String;)Ljava/lang/StringBuilder;
    //   117: astore 4
    //   119: aload 4
    //   121: iload_1
    //   122: invokevirtual 209	java/lang/StringBuilder:append	(Z)Ljava/lang/StringBuilder;
    //   125: ldc -45
    //   127: bipush 41
    //   129: sipush 165
    //   132: iconst_3
    //   133: invokestatic 52	kkkkkk/gguuuu:bк043Aккк043Aкк043A043A	(Ljava/lang/String;CCC)Ljava/lang/String;
    //   136: invokevirtual 206	java/lang/StringBuilder:append	(Ljava/lang/String;)Ljava/lang/StringBuilder;
    //   139: astore 4
    //   141: getstatic 83	kkkkkk/jaajaa:bбб0431б0431б0431бб	Ljava/lang/String;
    //   144: astore 5
    //   146: aload_3
    //   147: aload 4
    //   149: aload 5
    //   151: invokevirtual 206	java/lang/StringBuilder:append	(Ljava/lang/String;)Ljava/lang/StringBuilder;
    //   154: invokevirtual 214	java/lang/StringBuilder:toString	()Ljava/lang/String;
    //   157: invokestatic 217	kkkkkk/xtxtxt:bии0438и04380438и0438ии	(Ljava/lang/String;Ljava/lang/String;)V
    //   160: iload_1
    //   161: ifeq +16 -> 177
    //   164: getstatic 83	kkkkkk/jaajaa:bбб0431б0431б0431бб	Ljava/lang/String;
    //   167: invokestatic 123	android/text/TextUtils:isEmpty	(Ljava/lang/CharSequence;)Z
    //   170: istore_1
    //   171: iload_1
    //   172: ifne +5 -> 177
    //   175: iconst_1
    //   176: ireturn
    //   177: iconst_0
    //   178: ireturn
    //   179: astore_3
    //   180: aload_3
    //   181: athrow
    //   182: astore_3
    //   183: aload_3
    //   184: athrow
    //   185: astore_3
    //   186: aload_3
    //   187: athrow
    // Local variable table:
    //   start	length	slot	name	signature
    //   19	30	0	i	int
    //   6	166	1	bool1	boolean
    //   13	22	2	bool2	boolean
    //   27	1	3	localException1	Exception
    //   98	49	3	str1	String
    //   179	2	3	localException2	Exception
    //   182	2	3	localException3	Exception
    //   185	2	3	localException4	Exception
    //   117	31	4	localStringBuilder	StringBuilder
    //   144	6	5	str2	String
    // Exception table:
    //   from	to	target	type
    //   20	24	27	java/lang/Exception
    //   0	14	179	java/lang/Exception
    //   83	95	179	java/lang/Exception
    //   95	119	179	java/lang/Exception
    //   146	160	179	java/lang/Exception
    //   164	171	179	java/lang/Exception
    //   28	34	182	java/lang/Exception
    //   180	182	182	java/lang/Exception
    //   186	188	182	java/lang/Exception
    //   119	146	185	java/lang/Exception
  }
  
  /* Error */
  private static void b04360436жж0436ж0436жжж()
  {
    // Byte code:
    //   0: invokestatic 30	kkkkkk/jaajaa:b0436жж043604360436жжжж	()I
    //   3: istore_0
    //   4: iload_0
    //   5: getstatic 32	kkkkkk/jaajaa:bб04310431б0431б0431бб	I
    //   8: iload_0
    //   9: iadd
    //   10: imul
    //   11: getstatic 34	kkkkkk/jaajaa:b043104310431б0431б0431бб	I
    //   14: irem
    //   15: tableswitch	default:+17->32, 0:+29->44
    //   32: invokestatic 30	kkkkkk/jaajaa:b0436жж043604360436жжжж	()I
    //   35: putstatic 44	kkkkkk/jaajaa:bббб04310431б0431бб	I
    //   38: invokestatic 30	kkkkkk/jaajaa:b0436жж043604360436жжжж	()I
    //   41: putstatic 46	kkkkkk/jaajaa:b0431бб04310431б0431бб	I
    //   44: aconst_null
    //   45: putstatic 83	kkkkkk/jaajaa:bбб0431б0431б0431бб	Ljava/lang/String;
    //   48: getstatic 44	kkkkkk/jaajaa:bббб04310431б0431бб	I
    //   51: istore_0
    //   52: getstatic 32	kkkkkk/jaajaa:bб04310431б0431б0431бб	I
    //   55: istore_1
    //   56: getstatic 44	kkkkkk/jaajaa:bббб04310431б0431бб	I
    //   59: istore_2
    //   60: invokestatic 220	kkkkkk/jaajaa:bжжж043604360436жжжж	()I
    //   63: istore_3
    //   64: getstatic 46	kkkkkk/jaajaa:b0431бб04310431б0431бб	I
    //   67: istore 4
    //   69: iload_0
    //   70: iload_1
    //   71: iadd
    //   72: iload_2
    //   73: imul
    //   74: iload_3
    //   75: irem
    //   76: iload 4
    //   78: if_icmpeq +14 -> 92
    //   81: bipush 42
    //   83: putstatic 44	kkkkkk/jaajaa:bббб04310431б0431бб	I
    //   86: invokestatic 30	kkkkkk/jaajaa:b0436жж043604360436жжжж	()I
    //   89: putstatic 46	kkkkkk/jaajaa:b0431бб04310431б0431бб	I
    //   92: return
    //   93: astore 5
    //   95: aload 5
    //   97: athrow
    //   98: astore 5
    //   100: aload 5
    //   102: athrow
    // Local variable table:
    //   start	length	slot	name	signature
    //   3	69	0	i	int
    //   55	17	1	j	int
    //   59	15	2	k	int
    //   63	13	3	m	int
    //   67	12	4	n	int
    //   93	3	5	localException1	Exception
    //   98	3	5	localException2	Exception
    // Exception table:
    //   from	to	target	type
    //   44	69	93	java/lang/Exception
    //   86	92	93	java/lang/Exception
    //   81	86	98	java/lang/Exception
  }
  
  public static int b04360436жжжж0436жжж(String paramString)
  {
    if (TextUtils.isEmpty(paramString))
    {
      xtxtxt.b0438и0438и04380438и0438ии(b04310431бб0431б0431бб, gguuuu.bккккк043Aкк043A043A("\0211`\0021\037+ [Y+\035++'\"\034 \030O[^", 'Ý', '\003'));
      i = -1;
      return i;
    }
    nrrrnr localNrrrnr = nrrrnr.instance;
    int i = bббб04310431б0431бб;
    switch (i * (bб04310431б0431б0431бб + i) % b043104310431б0431б0431бб)
    {
    default: 
      bббб04310431б0431бб = 40;
      b0431бб04310431б0431бб = 37;
    }
    int j = localNrrrnr.b0438и0438и0438ии04380438и(paramString);
    int k = bббб04310431б0431бб;
    i = j;
    switch (k * (bб04310431б0431б0431бб + k) % b043104310431б0431б0431бб)
    {
    }
    bббб04310431б0431бб = 24;
    b0431бб04310431б0431бб = b0436жж043604360436жжжж();
    return j;
  }
  
  public static void b0436ж0436043604360436жжжж(dddxxd<AgentData, Exception> paramDddxxd)
  {
    for (;;)
    {
      try
      {
        if (!b04360436ж0436жж0436жжж()) {
          localObject = new Exception(gguuuu.bк043Aккк043Aкк043A043A(":,4\nY[a\016X^Zf\\Ua_q]]", 'Æ', '', '\003'));
        }
        try
        {
          paramDddxxd.b0445х0445х0445хх044504450445((Throwable)localObject);
          return;
        }
        catch (Exception paramDddxxd)
        {
          int i;
          throw paramDddxxd;
        }
        Object localObject = ykykky.bШШ0428Ш0428ШШШ04280428();
        i = b0436жж043604360436жжжж();
        switch (i * (bб04310431б0431б0431бб + i) % b043104310431б0431б0431бб)
        {
        case 0: 
          bббб04310431б0431бб = 94;
          i = bббб04310431б0431бб;
          switch (i * (bб04310431б0431б0431бб + i) % bжжж043604360436жжжж())
          {
          default: 
            bббб04310431б0431бб = b0436жж043604360436жжжж();
            b0431бб04310431б0431бб = b0436жж043604360436жжжж();
          }
          b0431бб04310431б0431бб = b0436жж043604360436жжжж();
          localObject = ((ykykky)localObject).b04280428ШШ0428ШШШ04280428();
          String str = bбб0431б0431б0431бб;
          ((kkyykk)localObject).bШ04280428ШШ04280428ШШ0428(str, paramDddxxd);
          return;
        }
      }
      catch (Exception paramDddxxd)
      {
        throw paramDddxxd;
      }
    }
  }
  
  public static boolean b0436ж043604360436ж0436жжж(Activity paramActivity, LPAuthenticationParams paramLPAuthenticationParams, ConversationViewParams paramConversationViewParams)
  {
    throw new Runtime("d2j fail translate: java.lang.IndexOutOfBoundsException: fromIndex < 0: -1\n\tat java.util.BitSet.nextSetBit(BitSet.java:712)\n\tat com.googlecode.dex2jar.ir.ts.array.FillArrayTransformer.makeSureAllElementAreAssigned(FillArrayTransformer.java:505)\n\tat com.googlecode.dex2jar.ir.ts.array.FillArrayTransformer.transformReportChanged(FillArrayTransformer.java:123)\n\tat com.googlecode.dex2jar.ir.ts.StatedTransformer.transform(StatedTransformer.java:10)\n\tat com.googlecode.d2j.dex.Dex2jar$2.optimize(Dex2jar.java:149)\n\tat com.googlecode.d2j.dex.Dex2Asm.convertCode(Dex2Asm.java:414)\n\tat com.googlecode.d2j.dex.ExDex2Asm.convertCode(ExDex2Asm.java:42)\n\tat com.googlecode.d2j.dex.Dex2jar$2.convertCode(Dex2jar.java:128)\n\tat com.googlecode.d2j.dex.Dex2Asm.convertMethod(Dex2Asm.java:509)\n\tat com.googlecode.d2j.dex.Dex2Asm.convertClass(Dex2Asm.java:406)\n\tat com.googlecode.d2j.dex.Dex2Asm.convertDex(Dex2Asm.java:422)\n\tat com.googlecode.d2j.dex.Dex2jar.doTranslate(Dex2jar.java:172)\n\tat com.googlecode.d2j.dex.Dex2jar.to(Dex2jar.java:272)\n\tat com.googlecode.dex2jar.tools.Dex2jarCmd.doCommandLine(Dex2jarCmd.java:108)\n\tat com.googlecode.dex2jar.tools.BaseCmd.doMain(BaseCmd.java:288)\n\tat com.googlecode.dex2jar.tools.Dex2jarCmd.main(Dex2jarCmd.java:32)\n");
  }
  
  public static void b0436ж04360436жж0436жжж()
  {
    if (!b04360436ж0436жж0436жжж()) {
      return;
    }
    kkyykk localKkyykk = ykykky.bШШ0428Ш0428ШШШ04280428().b04280428ШШ0428ШШШ04280428();
    String str1 = bбб0431б0431б0431бб;
    String str2 = bбб0431б0431б0431бб;
    int i = bббб04310431б0431бб;
    switch (i * (bж0436ж043604360436жжжж() + i) % b043104310431б0431б0431бб)
    {
    default: 
      bббб04310431б0431бб = 97;
      b0431бб04310431б0431бб = 46;
    }
    switch (1)
    {
    case 0: 
    default: 
      for (;;)
      {
        switch (1)
        {
        }
      }
    }
    localKkyykk.b0428Ш0428Ш042804280428ШШ0428(str1, str2);
    try
    {
      throw new NullPointerException();
    }
    catch (Exception localException)
    {
      bббб04310431б0431бб = b0436жж043604360436жжжж();
    }
  }
  
  /* Error */
  public static void b0436ж0436ж0436ж0436жжж(wnwnwn paramWnwnwn)
  {
    // Byte code:
    //   0: invokestatic 71	kkkkkk/jaajaa:b04360436ж0436жж0436жжж	()Z
    //   3: istore_1
    //   4: iload_1
    //   5: ifne +4 -> 9
    //   8: return
    //   9: invokestatic 77	kkkkkk/ykykky:bШШ0428Ш0428ШШШ04280428	()Lkkkkkk/ykykky;
    //   12: invokevirtual 81	kkkkkk/ykykky:b04280428ШШ0428ШШШ04280428	()Lkkkkkk/kkyykk;
    //   15: astore_2
    //   16: getstatic 44	kkkkkk/jaajaa:bббб04310431б0431бб	I
    //   19: getstatic 32	kkkkkk/jaajaa:bб04310431б0431б0431бб	I
    //   22: iadd
    //   23: getstatic 44	kkkkkk/jaajaa:bббб04310431б0431бб	I
    //   26: imul
    //   27: getstatic 34	kkkkkk/jaajaa:b043104310431б0431б0431бб	I
    //   30: irem
    //   31: getstatic 46	kkkkkk/jaajaa:b0431бб04310431б0431бб	I
    //   34: if_icmpeq +15 -> 49
    //   37: invokestatic 30	kkkkkk/jaajaa:b0436жж043604360436жжжж	()I
    //   40: putstatic 44	kkkkkk/jaajaa:bббб04310431б0431бб	I
    //   43: invokestatic 30	kkkkkk/jaajaa:b0436жж043604360436жжжж	()I
    //   46: putstatic 46	kkkkkk/jaajaa:b0431бб04310431б0431бб	I
    //   49: aload_2
    //   50: aload_0
    //   51: invokevirtual 268	kkkkkk/kkyykk:bШШШ0428ШШШ0428Ш0428	(Lkkkkkk/wnwnwn;)V
    //   54: return
    //   55: astore_0
    //   56: aload_0
    //   57: athrow
    //   58: astore_0
    //   59: aload_0
    //   60: athrow
    // Local variable table:
    //   start	length	slot	name	signature
    //   0	61	0	paramWnwnwn	wnwnwn
    //   3	2	1	bool	boolean
    //   15	35	2	localKkyykk	kkyykk
    // Exception table:
    //   from	to	target	type
    //   0	4	55	java/lang/Exception
    //   49	54	55	java/lang/Exception
    //   9	16	58	java/lang/Exception
  }
  
  public static String b0436ж0436жжж0436жжж()
  {
    String str = gguuuu.bк043Aккк043Aкк043A043A("a]a_c", '', 'n', '\001');
    if ((bббб04310431б0431бб + bб04310431б0431б0431бб) * bббб04310431б0431бб % b043104310431б0431б0431бб != b0431бб04310431б0431бб)
    {
      bббб04310431б0431бб = 59;
      b0431бб04310431б0431бб = 51;
    }
    return str;
  }
  
  public static int b0436жж043604360436жжжж()
  {
    return 18;
  }
  
  private static void b0436жж04360436ж0436жжж(Context paramContext)
  {
    for (;;)
    {
      try
      {
        if ((paramContext.getApplicationInfo().flags & 0x2) != 0)
        {
          bool1 = true;
          int i = bббб04310431б0431бб;
          int j = bб04310431б0431б0431бб;
          int k = b043104310431б0431б0431бб;
          switch (i * (j + i) % k)
          {
          }
        }
      }
      catch (Exception paramContext)
      {
        boolean bool1;
        boolean bool2;
        throw paramContext;
      }
      try
      {
        bббб04310431б0431бб = b0436жж043604360436жжжж();
        b0431бб04310431б0431бб = b0436жж043604360436жжжж();
        xtxtxt.bи0438и043804380438и0438ии(bool1);
        return;
      }
      catch (Exception paramContext)
      {
        throw paramContext;
      }
      bool2 = false;
      bool1 = bool2;
      if ((bббб04310431б0431бб + bб04310431б0431б0431бб) * bббб04310431б0431бб % b043104310431б0431б0431бб != b0431бб04310431б0431бб)
      {
        bббб04310431б0431бб = b0436жж043604360436жжжж();
        b0431бб04310431б0431бб = b0436жж043604360436жжжж();
        bool1 = bool2;
      }
    }
  }
  
  /* Error */
  public static void b0436жж0436жж0436жжж(Context paramContext, dxdddx paramDxdddx)
  {
    // Byte code:
    //   0: aload_0
    //   1: invokevirtual 294	android/content/Context:getApplicationContext	()Landroid/content/Context;
    //   4: astore_0
    //   5: aload_1
    //   6: invokevirtual 300	kkkkkk/dxdddx:b0445ххх0445х0445044504450445	()Lkkkkkk/xdxxdx;
    //   9: astore 6
    //   11: new 302	kkkkkk/jaajaa$1
    //   14: dup
    //   15: aload_1
    //   16: aload 6
    //   18: aload_0
    //   19: invokespecial 305	kkkkkk/jaajaa$1:<init>	(Lkkkkkk/dxdddx;Lkkkkkk/xdxxdx;Landroid/content/Context;)V
    //   22: astore 7
    //   24: getstatic 44	kkkkkk/jaajaa:bббб04310431б0431бб	I
    //   27: istore_2
    //   28: getstatic 32	kkkkkk/jaajaa:bб04310431б0431б0431бб	I
    //   31: istore_3
    //   32: getstatic 34	kkkkkk/jaajaa:b043104310431б0431б0431бб	I
    //   35: istore 4
    //   37: iload_2
    //   38: iload_3
    //   39: iload_2
    //   40: iadd
    //   41: imul
    //   42: iload 4
    //   44: irem
    //   45: tableswitch	default:+19->64, 0:+30->75
    //   64: invokestatic 30	kkkkkk/jaajaa:b0436жж043604360436жжжж	()I
    //   67: putstatic 44	kkkkkk/jaajaa:bббб04310431б0431бб	I
    //   70: bipush 75
    //   72: putstatic 46	kkkkkk/jaajaa:b0431бб04310431б0431бб	I
    //   75: aload_1
    //   76: aload 7
    //   78: invokevirtual 309	kkkkkk/dxdddx:b0445х0445х0445х0445044504450445	(Lkkkkkk/xdxxdx;)V
    //   81: aload_1
    //   82: invokestatic 313	kkkkkk/dxdddx:bхх0445х0445х0445044504450445	(Lkkkkkk/dxdddx;)Z
    //   85: istore 5
    //   87: iload 5
    //   89: ifne +49 -> 138
    //   92: aload 6
    //   94: ifnull +26 -> 120
    //   97: aload 6
    //   99: new 68	java/lang/Exception
    //   102: dup
    //   103: ldc_w 315
    //   106: bipush 69
    //   108: iconst_5
    //   109: invokestatic 42	kkkkkk/gguuuu:bккккк043Aкк043A043A	(Ljava/lang/String;CC)Ljava/lang/String;
    //   112: invokespecial 234	java/lang/Exception:<init>	(Ljava/lang/String;)V
    //   115: invokeinterface 321 2 0
    //   120: getstatic 60	kkkkkk/jaajaa:b04310431бб0431б0431бб	Ljava/lang/String;
    //   123: astore_0
    //   124: aload_0
    //   125: ldc_w 323
    //   128: bipush 65
    //   130: iconst_0
    //   131: invokestatic 42	kkkkkk/gguuuu:bккккк043Aкк043A043A	(Ljava/lang/String;CC)Ljava/lang/String;
    //   134: invokestatic 326	kkkkkk/xtxtxt:bии0438043804380438и0438ии	(Ljava/lang/String;Ljava/lang/String;)V
    //   137: return
    //   138: invokestatic 71	kkkkkk/jaajaa:b04360436ж0436жж0436жжж	()Z
    //   141: ifne +163 -> 304
    //   144: aload_1
    //   145: invokevirtual 329	kkkkkk/dxdddx:bхххх0445х0445044504450445	()Ljava/lang/String;
    //   148: putstatic 83	kkkkkk/jaajaa:bбб0431б0431б0431бб	Ljava/lang/String;
    //   151: aload_0
    //   152: invokestatic 331	kkkkkk/jaajaa:b0436жж04360436ж0436жжж	(Landroid/content/Context;)V
    //   155: aload_0
    //   156: invokestatic 336	kkkkkk/xtxxtx:bи04380438иии0438и0438и	(Landroid/content/Context;)V
    //   159: new 338	kkkkkk/xxxddx
    //   162: dup
    //   163: aconst_null
    //   164: invokespecial 341	kkkkkk/xxxddx:<init>	(Ljava/util/HashMap;)V
    //   167: putstatic 343	kkkkkk/jaajaa:b0431б0431б0431б0431бб	Lkkkkkk/xxxddx;
    //   170: invokestatic 185	kkkkkk/ttxttx:bи0438и04380438иии0438и	()Lkkkkkk/ttxttx;
    //   173: astore 6
    //   175: new 345	kkkkkk/xxtxtx
    //   178: dup
    //   179: aload_1
    //   180: invokestatic 347	kkkkkk/jaajaa:b0436ж0436жжж0436жжж	()Ljava/lang/String;
    //   183: invokespecial 350	kkkkkk/xxtxtx:<init>	(Lkkkkkk/dxdddx;Ljava/lang/String;)V
    //   186: astore_1
    //   187: new 352	kkkkkk/txtxtx
    //   190: dup
    //   191: aconst_null
    //   192: invokespecial 353	kkkkkk/txtxtx:<init>	(Ljava/util/HashMap;)V
    //   195: astore 7
    //   197: iconst_1
    //   198: tableswitch	default:+22->220, 0:+-1->197, 1:+93->291
    //   220: getstatic 44	kkkkkk/jaajaa:bббб04310431б0431бб	I
    //   223: istore_2
    //   224: iload_2
    //   225: getstatic 32	kkkkkk/jaajaa:bб04310431б0431б0431бб	I
    //   228: iload_2
    //   229: iadd
    //   230: imul
    //   231: getstatic 34	kkkkkk/jaajaa:b043104310431б0431б0431бб	I
    //   234: irem
    //   235: tableswitch	default:+17->252, 0:+29->264
    //   252: invokestatic 30	kkkkkk/jaajaa:b0436жж043604360436жжжж	()I
    //   255: putstatic 44	kkkkkk/jaajaa:bббб04310431б0431бб	I
    //   258: invokestatic 30	kkkkkk/jaajaa:b0436жж043604360436жжжж	()I
    //   261: putstatic 46	kkkkkk/jaajaa:b0431бб04310431б0431бб	I
    //   264: iconst_1
    //   265: tableswitch	default:+23->288, 0:+-68->197, 1:+26->291
    //   288: goto -68 -> 220
    //   291: aload 6
    //   293: aload_0
    //   294: aload_1
    //   295: aload 7
    //   297: invokevirtual 357	kkkkkk/ttxttx:bи043804380438ииии0438и	(Landroid/content/Context;Lkkkkkk/xxtxtx;Lkkkkkk/txtxtx;)V
    //   300: return
    //   301: astore_0
    //   302: aload_0
    //   303: athrow
    //   304: aload 6
    //   306: invokeinterface 360 1 0
    //   311: invokestatic 185	kkkkkk/ttxttx:bи0438и04380438иии0438и	()Lkkkkkk/ttxttx;
    //   314: astore_0
    //   315: new 352	kkkkkk/txtxtx
    //   318: dup
    //   319: aconst_null
    //   320: invokespecial 353	kkkkkk/txtxtx:<init>	(Ljava/util/HashMap;)V
    //   323: astore_1
    //   324: aload_0
    //   325: aload_1
    //   326: invokevirtual 364	kkkkkk/ttxttx:bи0438ии0438иии0438и	(Lkkkkkk/txtxtx;)V
    //   329: return
    //   330: astore_0
    //   331: aload_0
    //   332: athrow
    // Local variable table:
    //   start	length	slot	name	signature
    //   0	333	0	paramContext	Context
    //   0	333	1	paramDxdddx	dxdddx
    //   27	204	2	i	int
    //   31	10	3	j	int
    //   35	10	4	k	int
    //   85	3	5	bool	boolean
    //   9	296	6	localObject1	Object
    //   22	274	7	localObject2	Object
    // Exception table:
    //   from	to	target	type
    //   0	37	301	java/lang/Exception
    //   75	87	301	java/lang/Exception
    //   124	137	301	java/lang/Exception
    //   138	151	301	java/lang/Exception
    //   175	197	301	java/lang/Exception
    //   291	300	301	java/lang/Exception
    //   304	324	301	java/lang/Exception
    //   64	75	330	java/lang/Exception
    //   97	120	330	java/lang/Exception
    //   120	124	330	java/lang/Exception
    //   151	175	330	java/lang/Exception
    //   324	329	330	java/lang/Exception
  }
  
  public static void b0436жжж0436ж0436жжж(String paramString1, String paramString2, String paramString3)
  {
    if (!b04360436ж0436жж0436жжж()) {
      return;
    }
    ykykky.bШШ0428Ш0428ШШШ04280428().b04280428ШШ0428ШШШ04280428().bШ0428Ш0428042804280428ШШ0428(paramString1, paramString2, paramString3);
    int i = bббб04310431б0431бб;
    switch (i * (bб04310431б0431б0431бб + i) % b043104310431б0431б0431бб)
    {
    }
    bббб04310431б0431бб = b0436жж043604360436жжжж();
    b0431бб04310431б0431бб = b0436жж043604360436жжжж();
  }
  
  /* Error */
  public static void b0436жжжж04360436жжж(String paramString1, String paramString2)
  {
    // Byte code:
    //   0: invokestatic 71	kkkkkk/jaajaa:b04360436ж0436жж0436жжж	()Z
    //   3: ifne +4 -> 7
    //   6: return
    //   7: invokestatic 77	kkkkkk/ykykky:bШШ0428Ш0428ШШШ04280428	()Lkkkkkk/ykykky;
    //   10: astore_2
    //   11: aload_2
    //   12: invokevirtual 81	kkkkkk/ykykky:b04280428ШШ0428ШШШ04280428	()Lkkkkkk/kkyykk;
    //   15: aload_0
    //   16: aload_1
    //   17: aconst_null
    //   18: iconst_0
    //   19: invokevirtual 374	kkkkkk/kkyykk:bШ0428Ш0428ШШШ0428Ш0428	(Ljava/lang/String;Ljava/lang/String;Lkkkkkk/dddxxd;Z)V
    //   22: return
    //   23: astore_0
    //   24: aload_0
    //   25: athrow
    //   26: astore_0
    //   27: aload_0
    //   28: athrow
    // Local variable table:
    //   start	length	slot	name	signature
    //   0	29	0	paramString1	String
    //   0	29	1	paramString2	String
    //   10	2	2	localYkykky	ykykky
    // Exception table:
    //   from	to	target	type
    //   11	22	23	java/lang/Exception
    //   0	6	26	java/lang/Exception
    //   7	11	26	java/lang/Exception
  }
  
  /* Error */
  public static Fragment b0436жжжжж0436жжж(LPAuthenticationParams paramLPAuthenticationParams, ConversationViewParams paramConversationViewParams)
  {
    // Byte code:
    //   0: invokestatic 71	kkkkkk/jaajaa:b04360436ж0436жж0436жжж	()Z
    //   3: ifne +44 -> 47
    //   6: getstatic 60	kkkkkk/jaajaa:b04310431бб0431б0431бб	Ljava/lang/String;
    //   9: new 199	java/lang/StringBuilder
    //   12: dup
    //   13: invokespecial 200	java/lang/StringBuilder:<init>	()V
    //   16: ldc_w 378
    //   19: bipush 60
    //   21: sipush 183
    //   24: iconst_0
    //   25: invokestatic 52	kkkkkk/gguuuu:bк043Aккк043Aкк043A043A	(Ljava/lang/String;CCC)Ljava/lang/String;
    //   28: invokevirtual 206	java/lang/StringBuilder:append	(Ljava/lang/String;)Ljava/lang/StringBuilder;
    //   31: getstatic 83	kkkkkk/jaajaa:bбб0431б0431б0431бб	Ljava/lang/String;
    //   34: invokevirtual 206	java/lang/StringBuilder:append	(Ljava/lang/String;)Ljava/lang/StringBuilder;
    //   37: invokevirtual 214	java/lang/StringBuilder:toString	()Ljava/lang/String;
    //   40: invokestatic 131	kkkkkk/xtxtxt:b0438и0438и04380438и0438ии	(Ljava/lang/String;Ljava/lang/String;)V
    //   43: aconst_null
    //   44: astore_0
    //   45: aload_0
    //   46: areturn
    //   47: invokestatic 185	kkkkkk/ttxttx:bи0438и04380438иии0438и	()Lkkkkkk/ttxttx;
    //   50: getstatic 83	kkkkkk/jaajaa:bбб0431б0431б0431бб	Ljava/lang/String;
    //   53: aload_0
    //   54: aload_1
    //   55: invokevirtual 382	kkkkkk/ttxttx:bии04380438ииии0438и	(Ljava/lang/String;Lcom/liveperson/infra/LPAuthenticationParams;Lcom/liveperson/infra/ConversationViewParams;)Landroid/support/v4/app/Fragment;
    //   58: astore_1
    //   59: getstatic 44	kkkkkk/jaajaa:bббб04310431б0431бб	I
    //   62: istore_2
    //   63: getstatic 44	kkkkkk/jaajaa:bббб04310431б0431бб	I
    //   66: istore_3
    //   67: iload_3
    //   68: getstatic 32	kkkkkk/jaajaa:bб04310431б0431б0431бб	I
    //   71: iload_3
    //   72: iadd
    //   73: imul
    //   74: invokestatic 220	kkkkkk/jaajaa:bжжж043604360436жжжж	()I
    //   77: irem
    //   78: tableswitch	default:+18->96, 0:+29->107
    //   96: invokestatic 30	kkkkkk/jaajaa:b0436жж043604360436жжжж	()I
    //   99: putstatic 44	kkkkkk/jaajaa:bббб04310431б0431бб	I
    //   102: bipush 58
    //   104: putstatic 46	kkkkkk/jaajaa:b0431бб04310431б0431бб	I
    //   107: getstatic 32	kkkkkk/jaajaa:bб04310431б0431б0431бб	I
    //   110: istore_3
    //   111: getstatic 44	kkkkkk/jaajaa:bббб04310431б0431бб	I
    //   114: istore 4
    //   116: getstatic 34	kkkkkk/jaajaa:b043104310431б0431б0431бб	I
    //   119: istore 5
    //   121: getstatic 46	kkkkkk/jaajaa:b0431бб04310431б0431бб	I
    //   124: istore 6
    //   126: aload_1
    //   127: astore_0
    //   128: iload_2
    //   129: iload_3
    //   130: iadd
    //   131: iload 4
    //   133: imul
    //   134: iload 5
    //   136: irem
    //   137: iload 6
    //   139: if_icmpeq -94 -> 45
    //   142: bipush 63
    //   144: putstatic 44	kkkkkk/jaajaa:bббб04310431б0431бб	I
    //   147: bipush 28
    //   149: putstatic 46	kkkkkk/jaajaa:b0431бб04310431б0431бб	I
    //   152: aload_1
    //   153: areturn
    //   154: astore_0
    //   155: aload_0
    //   156: athrow
    //   157: astore_0
    //   158: aload_0
    //   159: athrow
    //   160: astore_0
    //   161: aload_0
    //   162: athrow
    //   163: astore_0
    //   164: aload_0
    //   165: athrow
    // Local variable table:
    //   start	length	slot	name	signature
    //   0	166	0	paramLPAuthenticationParams	LPAuthenticationParams
    //   0	166	1	paramConversationViewParams	ConversationViewParams
    //   62	69	2	i	int
    //   66	65	3	j	int
    //   114	20	4	k	int
    //   119	18	5	m	int
    //   124	16	6	n	int
    // Exception table:
    //   from	to	target	type
    //   142	152	154	java/lang/Exception
    //   0	43	157	java/lang/Exception
    //   59	63	160	java/lang/Exception
    //   107	126	160	java/lang/Exception
    //   158	160	160	java/lang/Exception
    //   164	166	160	java/lang/Exception
    //   47	59	163	java/lang/Exception
  }
  
  /* Error */
  public static void bж04360436043604360436жжжж(dddxxd<Boolean, Exception> paramDddxxd)
  {
    // Byte code:
    //   0: invokestatic 71	kkkkkk/jaajaa:b04360436ж0436жж0436жжж	()Z
    //   3: ifne +30 -> 33
    //   6: aload_0
    //   7: new 68	java/lang/Exception
    //   10: dup
    //   11: ldc_w 385
    //   14: sipush 144
    //   17: sipush 202
    //   20: iconst_3
    //   21: invokestatic 52	kkkkkk/gguuuu:bк043Aккк043Aкк043A043A	(Ljava/lang/String;CCC)Ljava/lang/String;
    //   24: invokespecial 234	java/lang/Exception:<init>	(Ljava/lang/String;)V
    //   27: invokeinterface 240 2 0
    //   32: return
    //   33: invokestatic 77	kkkkkk/ykykky:bШШ0428Ш0428ШШШ04280428	()Lkkkkkk/ykykky;
    //   36: invokevirtual 81	kkkkkk/ykykky:b04280428ШШ0428ШШШ04280428	()Lkkkkkk/kkyykk;
    //   39: getstatic 83	kkkkkk/jaajaa:bбб0431б0431б0431бб	Ljava/lang/String;
    //   42: aload_0
    //   43: invokevirtual 388	kkkkkk/kkyykk:b042804280428ШШ04280428ШШ0428	(Ljava/lang/String;Lkkkkkk/dddxxd;)V
    //   46: invokestatic 30	kkkkkk/jaajaa:b0436жж043604360436жжжж	()I
    //   49: istore_1
    //   50: iload_1
    //   51: getstatic 32	kkkkkk/jaajaa:bб04310431б0431б0431бб	I
    //   54: iload_1
    //   55: iadd
    //   56: imul
    //   57: getstatic 34	kkkkkk/jaajaa:b043104310431б0431б0431бб	I
    //   60: irem
    //   61: tableswitch	default:+19->80, 0:+-29->32
    //   80: invokestatic 30	kkkkkk/jaajaa:b0436жж043604360436жжжж	()I
    //   83: putstatic 44	kkkkkk/jaajaa:bббб04310431б0431бб	I
    //   86: getstatic 44	kkkkkk/jaajaa:bббб04310431б0431бб	I
    //   89: istore_1
    //   90: iload_1
    //   91: getstatic 32	kkkkkk/jaajaa:bб04310431б0431б0431бб	I
    //   94: iload_1
    //   95: iadd
    //   96: imul
    //   97: getstatic 34	kkkkkk/jaajaa:b043104310431б0431б0431бб	I
    //   100: irem
    //   101: tableswitch	default:+19->120, 0:+29->130
    //   120: bipush 22
    //   122: putstatic 44	kkkkkk/jaajaa:bббб04310431б0431бб	I
    //   125: bipush 87
    //   127: putstatic 46	kkkkkk/jaajaa:b0431бб04310431б0431бб	I
    //   130: bipush 47
    //   132: putstatic 46	kkkkkk/jaajaa:b0431бб04310431б0431бб	I
    //   135: return
    //   136: astore_0
    //   137: aload_0
    //   138: athrow
    //   139: astore_0
    //   140: aload_0
    //   141: athrow
    // Local variable table:
    //   start	length	slot	name	signature
    //   0	142	0	paramDddxxd	dddxxd<Boolean, Exception>
    //   49	48	1	i	int
    // Exception table:
    //   from	to	target	type
    //   0	32	136	java/lang/Exception
    //   33	46	139	java/lang/Exception
  }
  
  /* Error */
  @Deprecated
  public static boolean bж0436043604360436ж0436жжж(Activity paramActivity, String paramString)
  {
    // Byte code:
    //   0: new 393	com/liveperson/infra/LPAuthenticationParams
    //   3: dup
    //   4: invokespecial 394	com/liveperson/infra/LPAuthenticationParams:<init>	()V
    //   7: aload_1
    //   8: invokevirtual 398	com/liveperson/infra/LPAuthenticationParams:setAuthKey	(Ljava/lang/String;)Lcom/liveperson/infra/LPAuthenticationParams;
    //   11: astore_1
    //   12: new 400	com/liveperson/infra/ConversationViewParams
    //   15: dup
    //   16: iconst_0
    //   17: invokespecial 402	com/liveperson/infra/ConversationViewParams:<init>	(Z)V
    //   20: astore 7
    //   22: getstatic 44	kkkkkk/jaajaa:bббб04310431б0431бб	I
    //   25: istore_2
    //   26: getstatic 32	kkkkkk/jaajaa:bб04310431б0431б0431бб	I
    //   29: istore_3
    //   30: getstatic 44	kkkkkk/jaajaa:bббб04310431б0431бб	I
    //   33: istore 4
    //   35: getstatic 34	kkkkkk/jaajaa:b043104310431б0431б0431бб	I
    //   38: istore 5
    //   40: getstatic 44	kkkkkk/jaajaa:bббб04310431б0431бб	I
    //   43: getstatic 32	kkkkkk/jaajaa:bб04310431б0431б0431бб	I
    //   46: iadd
    //   47: getstatic 44	kkkkkk/jaajaa:bббб04310431б0431бб	I
    //   50: imul
    //   51: getstatic 34	kkkkkk/jaajaa:b043104310431б0431б0431бб	I
    //   54: irem
    //   55: getstatic 46	kkkkkk/jaajaa:b0431бб04310431б0431бб	I
    //   58: if_icmpeq +15 -> 73
    //   61: invokestatic 30	kkkkkk/jaajaa:b0436жж043604360436жжжж	()I
    //   64: putstatic 44	kkkkkk/jaajaa:bббб04310431б0431бб	I
    //   67: invokestatic 30	kkkkkk/jaajaa:b0436жж043604360436жжжж	()I
    //   70: putstatic 46	kkkkkk/jaajaa:b0431бб04310431б0431бб	I
    //   73: iload_2
    //   74: iload_3
    //   75: iadd
    //   76: iload 4
    //   78: imul
    //   79: iload 5
    //   81: irem
    //   82: getstatic 46	kkkkkk/jaajaa:b0431бб04310431б0431бб	I
    //   85: if_icmpeq +14 -> 99
    //   88: invokestatic 30	kkkkkk/jaajaa:b0436жж043604360436жжжж	()I
    //   91: putstatic 44	kkkkkk/jaajaa:bббб04310431б0431бб	I
    //   94: bipush 62
    //   96: putstatic 46	kkkkkk/jaajaa:b0431бб04310431б0431бб	I
    //   99: aload_0
    //   100: aload_1
    //   101: aload 7
    //   103: invokestatic 404	kkkkkk/jaajaa:b0436ж043604360436ж0436жжж	(Landroid/app/Activity;Lcom/liveperson/infra/LPAuthenticationParams;Lcom/liveperson/infra/ConversationViewParams;)Z
    //   106: istore 6
    //   108: iload 6
    //   110: ireturn
    //   111: astore_0
    //   112: aload_0
    //   113: athrow
    //   114: astore_0
    //   115: aload_0
    //   116: athrow
    // Local variable table:
    //   start	length	slot	name	signature
    //   0	117	0	paramActivity	Activity
    //   0	117	1	paramString	String
    //   25	51	2	i	int
    //   29	47	3	j	int
    //   33	46	4	k	int
    //   38	44	5	m	int
    //   106	3	6	bool	boolean
    //   20	82	7	localConversationViewParams	ConversationViewParams
    // Exception table:
    //   from	to	target	type
    //   0	12	111	java/lang/Exception
    //   99	108	111	java/lang/Exception
    //   12	22	114	java/lang/Exception
  }
  
  public static void bж043604360436жж0436жжж()
  {
    if (!b04360436ж0436жж0436жжж()) {}
    do
    {
      return;
      ykykky.bШШ0428Ш0428ШШШ04280428().b04280428ШШ0428ШШШ04280428().bШ04280428Ш042804280428ШШ0428(bбб0431б0431б0431бб, bбб0431б0431б0431бб);
    } while ((bббб04310431б0431бб + bб04310431б0431б0431бб) * bббб04310431б0431бб % b043104310431б0431б0431бб == b0431бб04310431б0431бб);
    bббб04310431б0431бб = 44;
    b0431бб04310431б0431бб = 4;
  }
  
  public static void bж04360436ж0436ж0436жжж(Notification.Builder paramBuilder)
  {
    if (paramBuilder != null)
    {
      kkyykk localKkyykk = ykykky.bШШ0428Ш0428ШШШ04280428().b04280428ШШ0428ШШШ04280428();
      int i = bббб04310431б0431бб;
      switch (i * (bб04310431б0431б0431бб + i) % b043104310431б0431б0431бб)
      {
      default: 
        bббб04310431б0431бб = b0436жж043604360436жжжж();
        b0431бб04310431б0431бб = 96;
        i = bббб04310431б0431бб;
        switch (i * (bб04310431б0431б0431бб + i) % b043104310431б0431б0431бб)
        {
        default: 
          bббб04310431б0431бб = b0436жж043604360436жжжж();
          b0431бб04310431б0431бб = b0436жж043604360436жжжж();
        }
        break;
      }
      localKkyykk.b04280428Ш0428ШШШШ04280428(paramBuilder);
    }
    switch (1)
    {
    case 0: 
    default: 
      for (;;)
      {
        switch (0)
        {
        case 1: 
        default: 
          for (;;)
          {
            switch (1)
            {
            }
          }
        }
        switch (0)
        {
        }
      }
    }
  }
  
  @Deprecated
  public static void bж04360436жжж0436жжж(Context paramContext, Bundle paramBundle, String paramString, boolean paramBoolean)
  {
    if (TextUtils.isEmpty(paramString))
    {
      xtxtxt.b0438и0438и04380438и0438ии(b04310431бб0431б0431бб, gguuuu.bккккк043Aкк043A043A("2R\002#R@LA|zC@FFH>B:qAEB6l90=<).+\004", '^', '\002'));
      do
      {
        return;
        if ((bббб04310431б0431бб + bб04310431б0431б0431бб) * bббб04310431б0431бб % b043104310431б0431б0431бб != b0431бб04310431б0431бб)
        {
          bббб04310431б0431бб = 51;
          b0431бб04310431б0431бб = 25;
        }
        switch (0)
        {
        case 1: 
        default: 
          for (;;)
          {
            switch (0)
            {
            }
          }
        }
        paramBundle = rnrnrn.b0438и0438и0438и043804380438и(paramString, paramBundle);
        if ((bббб04310431б0431бб + bб04310431б0431б0431бб) * bббб04310431б0431бб % b043104310431б0431б0431бб != b0431бб04310431б0431бб)
        {
          bббб04310431б0431бб = b0436жж043604360436жжжж();
          b0431бб04310431б0431бб = 40;
        }
      } while (paramBundle == null);
      nrrrnr.instance.bии04380438иии04380438и(paramContext, paramString, paramBundle, paramBoolean, R.drawable.liveperson_icon);
      return;
    }
    switch (1)
    {
    }
    for (;;)
    {
      switch (1)
      {
      }
    }
  }
  
  public static int bж0436ж043604360436жжжж()
  {
    return 1;
  }
  
  /* Error */
  public static void bж0436ж04360436ж0436жжж(ajaaja paramAjaaja)
  {
    // Byte code:
    //   0: invokestatic 71	kkkkkk/jaajaa:b04360436ж0436жж0436жжж	()Z
    //   3: ifne +4 -> 7
    //   6: return
    //   7: new 424	kkkkkk/fnnnff$ffnnff
    //   10: dup
    //   11: invokespecial 425	kkkkkk/fnnnff$ffnnff:<init>	()V
    //   14: aload_0
    //   15: invokevirtual 430	kkkkkk/ajaaja:b0436жж0436043604360436жжж	()Ljava/lang/String;
    //   18: invokevirtual 434	kkkkkk/fnnnff$ffnnff:b044Dээ044Dэ044D044Dээ044D	(Ljava/lang/String;)Lkkkkkk/fnnnff$ffnnff;
    //   21: astore 4
    //   23: getstatic 44	kkkkkk/jaajaa:bббб04310431б0431бб	I
    //   26: istore_1
    //   27: getstatic 44	kkkkkk/jaajaa:bббб04310431б0431бб	I
    //   30: getstatic 32	kkkkkk/jaajaa:bб04310431б0431б0431бб	I
    //   33: iadd
    //   34: getstatic 44	kkkkkk/jaajaa:bббб04310431б0431бб	I
    //   37: imul
    //   38: getstatic 34	kkkkkk/jaajaa:b043104310431б0431б0431бб	I
    //   41: irem
    //   42: invokestatic 436	kkkkkk/jaajaa:b04360436ж043604360436жжжж	()I
    //   45: if_icmpeq +14 -> 59
    //   48: bipush 98
    //   50: putstatic 44	kkkkkk/jaajaa:bббб04310431б0431бб	I
    //   53: invokestatic 30	kkkkkk/jaajaa:b0436жж043604360436жжжж	()I
    //   56: putstatic 46	kkkkkk/jaajaa:b0431бб04310431б0431бб	I
    //   59: getstatic 32	kkkkkk/jaajaa:bб04310431б0431б0431бб	I
    //   62: istore_2
    //   63: getstatic 34	kkkkkk/jaajaa:b043104310431б0431б0431бб	I
    //   66: istore_3
    //   67: iload_1
    //   68: iload_2
    //   69: iload_1
    //   70: iadd
    //   71: imul
    //   72: iload_3
    //   73: irem
    //   74: tableswitch	default:+18->92, 0:+29->103
    //   92: bipush 11
    //   94: putstatic 44	kkkkkk/jaajaa:bббб04310431б0431бб	I
    //   97: invokestatic 30	kkkkkk/jaajaa:b0436жж043604360436жжжж	()I
    //   100: putstatic 46	kkkkkk/jaajaa:b0431бб04310431б0431бб	I
    //   103: aload 4
    //   105: aload_0
    //   106: invokevirtual 439	kkkkkk/ajaaja:bж0436ж0436043604360436жжж	()Ljava/lang/String;
    //   109: invokevirtual 442	kkkkkk/fnnnff$ffnnff:bэ044Dэ044Dэ044D044Dээ044D	(Ljava/lang/String;)Lkkkkkk/fnnnff$ffnnff;
    //   112: astore 4
    //   114: aload 4
    //   116: aload_0
    //   117: invokevirtual 445	kkkkkk/ajaaja:bжж04360436043604360436жжж	()Ljava/lang/String;
    //   120: invokevirtual 448	kkkkkk/fnnnff$ffnnff:bээ044D044Dэ044D044Dээ044D	(Ljava/lang/String;)Lkkkkkk/fnnnff$ffnnff;
    //   123: aload_0
    //   124: invokevirtual 451	kkkkkk/ajaaja:b04360436ж0436043604360436жжж	()Ljava/lang/String;
    //   127: invokevirtual 454	kkkkkk/fnnnff$ffnnff:b044D044Dэ044Dэ044D044Dээ044D	(Ljava/lang/String;)Lkkkkkk/fnnnff$ffnnff;
    //   130: astore 4
    //   132: aload 4
    //   134: aload_0
    //   135: invokevirtual 457	kkkkkk/ajaaja:bжжж0436043604360436жжж	()Ljava/lang/String;
    //   138: invokevirtual 460	kkkkkk/fnnnff$ffnnff:bэээ044Dэ044D044Dээ044D	(Ljava/lang/String;)Lkkkkkk/fnnnff$ffnnff;
    //   141: invokevirtual 464	kkkkkk/fnnnff$ffnnff:bээ044Dээ044D044Dээ044D	()Lkkkkkk/fnnnff;
    //   144: astore_0
    //   145: invokestatic 77	kkkkkk/ykykky:bШШ0428Ш0428ШШШ04280428	()Lkkkkkk/ykykky;
    //   148: invokevirtual 81	kkkkkk/ykykky:b04280428ШШ0428ШШШ04280428	()Lkkkkkk/kkyykk;
    //   151: getstatic 83	kkkkkk/jaajaa:bбб0431б0431б0431бб	Ljava/lang/String;
    //   154: aload_0
    //   155: invokevirtual 468	kkkkkk/kkyykk:b0428Ш0428ШШШШ0428Ш0428	(Ljava/lang/String;Lkkkkkk/fnnnff;)V
    //   158: return
    //   159: astore_0
    //   160: aload_0
    //   161: athrow
    //   162: astore_0
    //   163: aload_0
    //   164: athrow
    // Local variable table:
    //   start	length	slot	name	signature
    //   0	165	0	paramAjaaja	ajaaja
    //   26	46	1	i	int
    //   62	9	2	j	int
    //   66	8	3	k	int
    //   21	112	4	localFfnnff	fnnnff.ffnnff
    // Exception table:
    //   from	to	target	type
    //   0	6	159	java/lang/Exception
    //   7	27	159	java/lang/Exception
    //   63	67	159	java/lang/Exception
    //   103	114	159	java/lang/Exception
    //   132	158	159	java/lang/Exception
    //   59	63	162	java/lang/Exception
    //   92	103	162	java/lang/Exception
    //   114	132	162	java/lang/Exception
  }
  
  @Deprecated
  public static void bж0436ж0436жж0436жжж(Context paramContext, String paramString, xdxxdx paramXdxxdx)
  {
    int i = bббб04310431б0431бб;
    switch (i * (bб04310431б0431б0431бб + i) % b043104310431б0431б0431бб)
    {
    default: 
      bббб04310431б0431бб = 29;
      b0431бб04310431б0431бб = b0436жж043604360436жжжж();
    }
    paramString = new dxdddx(paramString, paramContext.getApplicationInfo().packageName, paramXdxxdx);
    switch (1)
    {
    case 0: 
    default: 
      for (;;)
      {
        switch (0)
        {
        }
      }
    }
    b0436жж0436жж0436жжж(paramContext, paramString);
    if ((bббб04310431б0431бб + bб04310431б0431б0431бб) * bббб04310431б0431бб % bжжж043604360436жжжж() != b0431бб04310431б0431бб)
    {
      switch (1)
      {
      case 0: 
      default: 
        for (;;)
        {
          switch (0)
          {
          }
        }
      }
      bббб04310431б0431бб = 94;
      b0431бб04310431б0431бб = 92;
    }
  }
  
  /* Error */
  public static void bж0436жж0436ж0436жжж()
  {
    // Byte code:
    //   0: invokestatic 71	kkkkkk/jaajaa:b04360436ж0436жж0436жжж	()Z
    //   3: istore 5
    //   5: iload 5
    //   7: ifne +19 -> 26
    //   10: return
    //   11: astore 6
    //   13: aload 6
    //   15: athrow
    //   16: astore 6
    //   18: aload 6
    //   20: athrow
    //   21: astore 6
    //   23: aload 6
    //   25: athrow
    //   26: invokestatic 77	kkkkkk/ykykky:bШШ0428Ш0428ШШШ04280428	()Lkkkkkk/ykykky;
    //   29: astore 6
    //   31: getstatic 44	kkkkkk/jaajaa:bббб04310431б0431бб	I
    //   34: getstatic 32	kkkkkk/jaajaa:bб04310431б0431б0431бб	I
    //   37: iadd
    //   38: getstatic 44	kkkkkk/jaajaa:bббб04310431б0431бб	I
    //   41: imul
    //   42: getstatic 34	kkkkkk/jaajaa:b043104310431б0431б0431бб	I
    //   45: irem
    //   46: getstatic 46	kkkkkk/jaajaa:b0431бб04310431б0431бб	I
    //   49: if_icmpeq +14 -> 63
    //   52: bipush 96
    //   54: putstatic 44	kkkkkk/jaajaa:bббб04310431б0431бб	I
    //   57: invokestatic 30	kkkkkk/jaajaa:b0436жж043604360436жжжж	()I
    //   60: putstatic 46	kkkkkk/jaajaa:b0431бб04310431б0431бб	I
    //   63: aload 6
    //   65: invokevirtual 81	kkkkkk/ykykky:b04280428ШШ0428ШШШ04280428	()Lkkkkkk/kkyykk;
    //   68: astore 6
    //   70: aload 6
    //   72: invokevirtual 482	kkkkkk/kkyykk:b04280428Ш0428042804280428ШШ0428	()V
    //   75: getstatic 44	kkkkkk/jaajaa:bббб04310431б0431бб	I
    //   78: istore_0
    //   79: invokestatic 92	kkkkkk/jaajaa:bж0436ж043604360436жжжж	()I
    //   82: istore_1
    //   83: getstatic 44	kkkkkk/jaajaa:bббб04310431б0431бб	I
    //   86: istore_2
    //   87: invokestatic 220	kkkkkk/jaajaa:bжжж043604360436жжжж	()I
    //   90: istore_3
    //   91: getstatic 46	kkkkkk/jaajaa:b0431бб04310431б0431бб	I
    //   94: istore 4
    //   96: iload_0
    //   97: iload_1
    //   98: iadd
    //   99: iload_2
    //   100: imul
    //   101: iload_3
    //   102: irem
    //   103: iload 4
    //   105: if_icmpeq -95 -> 10
    //   108: invokestatic 30	kkkkkk/jaajaa:b0436жж043604360436жжжж	()I
    //   111: putstatic 44	kkkkkk/jaajaa:bббб04310431б0431бб	I
    //   114: invokestatic 30	kkkkkk/jaajaa:b0436жж043604360436жжжж	()I
    //   117: putstatic 46	kkkkkk/jaajaa:b0431бб04310431б0431бб	I
    //   120: return
    //   121: astore 6
    //   123: aload 6
    //   125: athrow
    // Local variable table:
    //   start	length	slot	name	signature
    //   78	21	0	i	int
    //   82	17	1	j	int
    //   86	15	2	k	int
    //   90	13	3	m	int
    //   94	12	4	n	int
    //   3	3	5	bool	boolean
    //   11	3	6	localException1	Exception
    //   16	3	6	localException2	Exception
    //   21	3	6	localException3	Exception
    //   29	42	6	localObject	Object
    //   121	3	6	localException4	Exception
    // Exception table:
    //   from	to	target	type
    //   0	5	11	java/lang/Exception
    //   26	31	11	java/lang/Exception
    //   63	70	11	java/lang/Exception
    //   13	16	16	java/lang/Exception
    //   23	26	16	java/lang/Exception
    //   75	87	16	java/lang/Exception
    //   91	96	16	java/lang/Exception
    //   70	75	21	java/lang/Exception
    //   87	91	121	java/lang/Exception
    //   108	120	121	java/lang/Exception
  }
  
  @Deprecated
  public static Fragment bж0436жжжж0436жжж(String paramString)
  {
    paramString = new LPAuthenticationParams().setAuthKey(paramString);
    ConversationViewParams localConversationViewParams = new ConversationViewParams(false);
    int i = bббб04310431б0431бб;
    switch (i * (bб04310431б0431б0431бб + i) % b043104310431б0431б0431бб)
    {
    default: 
      i = bббб04310431б0431бб;
      switch (i * (bж0436ж043604360436жжжж() + i) % b043104310431б0431б0431бб)
      {
      default: 
        bббб04310431б0431бб = 58;
        b0431бб04310431б0431бб = 1;
      }
      bббб04310431б0431бб = b0436жж043604360436жжжж();
      b0431бб04310431б0431бб = 93;
    }
    return b0436жжжжж0436жжж(paramString, localConversationViewParams);
  }
  
  public static void bжж0436043604360436жжжж(dddxxd<Boolean, Exception> paramDddxxd)
  {
    if (!b04360436ж0436жж0436жжж())
    {
      if ((bббб04310431б0431бб + bб04310431б0431б0431бб) * bббб04310431б0431бб % b043104310431б0431б0431бб != b0431бб04310431б0431бб)
      {
        bббб04310431б0431бб = b0436жж043604360436жжжж();
        b0431бб04310431б0431бб = 60;
      }
      paramDddxxd.b0445х0445х0445хх044504450445(new Exception(gguuuu.bккккк043Aкк043A043A("\tx~R  $N\027\033\025\037\023\n\024\020 \n\b", '¤', '\003')));
      return;
    }
    ykykky.bШШ0428Ш0428ШШШ04280428().b04280428ШШ0428ШШШ04280428().b0428Ш0428ШШ04280428ШШ0428(bбб0431б0431б0431бб, paramDddxxd);
  }
  
  @Deprecated
  public static boolean bжж043604360436ж0436жжж(Activity paramActivity)
  {
    LPAuthenticationParams localLPAuthenticationParams = new LPAuthenticationParams();
    ConversationViewParams localConversationViewParams = new ConversationViewParams(false);
    int i = bббб04310431б0431бб;
    switch (i * (bб04310431б0431б0431бб + i) % b043104310431б0431б0431бб)
    {
    default: 
      bббб04310431б0431бб = 10;
      b0431бб04310431б0431бб = 35;
    }
    return b0436ж043604360436ж0436жжж(paramActivity, localLPAuthenticationParams, localConversationViewParams);
  }
  
  /* Error */
  public static void bжж04360436жж0436жжж(Context paramContext, String paramString1, String paramString2, aaaaja paramAaaaja)
  {
    // Byte code:
    //   0: aload_1
    //   1: putstatic 83	kkkkkk/jaajaa:bбб0431б0431б0431бб	Ljava/lang/String;
    //   4: getstatic 44	kkkkkk/jaajaa:bббб04310431б0431бб	I
    //   7: istore 4
    //   9: getstatic 32	kkkkkk/jaajaa:bб04310431б0431б0431бб	I
    //   12: istore 5
    //   14: getstatic 44	kkkkkk/jaajaa:bббб04310431б0431бб	I
    //   17: istore 6
    //   19: getstatic 34	kkkkkk/jaajaa:b043104310431б0431б0431бб	I
    //   22: istore 7
    //   24: getstatic 46	kkkkkk/jaajaa:b0431бб04310431б0431бб	I
    //   27: istore 8
    //   29: iload 4
    //   31: iload 5
    //   33: iadd
    //   34: iload 6
    //   36: imul
    //   37: iload 7
    //   39: irem
    //   40: iload 8
    //   42: if_icmpeq +48 -> 90
    //   45: getstatic 44	kkkkkk/jaajaa:bббб04310431б0431бб	I
    //   48: getstatic 32	kkkkkk/jaajaa:bб04310431б0431б0431бб	I
    //   51: iadd
    //   52: getstatic 44	kkkkkk/jaajaa:bббб04310431б0431бб	I
    //   55: imul
    //   56: getstatic 34	kkkkkk/jaajaa:b043104310431б0431б0431бб	I
    //   59: irem
    //   60: getstatic 46	kkkkkk/jaajaa:b0431бб04310431б0431бб	I
    //   63: if_icmpeq +15 -> 78
    //   66: invokestatic 30	kkkkkk/jaajaa:b0436жж043604360436жжжж	()I
    //   69: putstatic 44	kkkkkk/jaajaa:bббб04310431б0431бб	I
    //   72: invokestatic 30	kkkkkk/jaajaa:b0436жж043604360436жжжж	()I
    //   75: putstatic 46	kkkkkk/jaajaa:b0431бб04310431б0431бб	I
    //   78: invokestatic 30	kkkkkk/jaajaa:b0436жж043604360436жжжж	()I
    //   81: putstatic 44	kkkkkk/jaajaa:bббб04310431б0431бб	I
    //   84: invokestatic 30	kkkkkk/jaajaa:b0436жж043604360436жжжж	()I
    //   87: putstatic 46	kkkkkk/jaajaa:b0431бб04310431б0431бб	I
    //   90: new 498	android/os/Handler
    //   93: dup
    //   94: invokespecial 499	android/os/Handler:<init>	()V
    //   97: astore 9
    //   99: new 345	kkkkkk/xxtxtx
    //   102: dup
    //   103: new 296	kkkkkk/dxdddx
    //   106: dup
    //   107: aload_1
    //   108: aload_2
    //   109: aconst_null
    //   110: invokespecial 476	kkkkkk/dxdddx:<init>	(Ljava/lang/String;Ljava/lang/String;Lkkkkkk/xdxxdx;)V
    //   113: invokestatic 347	kkkkkk/jaajaa:b0436ж0436жжж0436жжж	()Ljava/lang/String;
    //   116: invokespecial 350	kkkkkk/xxtxtx:<init>	(Lkkkkkk/dxdddx;Ljava/lang/String;)V
    //   119: astore_1
    //   120: invokestatic 185	kkkkkk/ttxttx:bи0438и04380438иии0438и	()Lkkkkkk/ttxttx;
    //   123: aload_0
    //   124: aload_1
    //   125: new 501	kkkkkk/jaajaa$3
    //   128: dup
    //   129: aload_0
    //   130: aload 9
    //   132: aload_3
    //   133: invokespecial 504	kkkkkk/jaajaa$3:<init>	(Landroid/content/Context;Landroid/os/Handler;Lkkkkkk/aaaaja;)V
    //   136: invokevirtual 508	kkkkkk/ttxttx:bииии0438иии0438и	(Landroid/content/Context;Lkkkkkk/xxtxtx;Lkkkkkk/dxxxdx;)V
    //   139: return
    //   140: astore_0
    //   141: aload_0
    //   142: athrow
    //   143: astore_0
    //   144: aload_0
    //   145: athrow
    //   146: astore_0
    //   147: aload_0
    //   148: athrow
    //   149: astore_0
    //   150: aload_0
    //   151: athrow
    // Local variable table:
    //   start	length	slot	name	signature
    //   0	152	0	paramContext	Context
    //   0	152	1	paramString1	String
    //   0	152	2	paramString2	String
    //   0	152	3	paramAaaaja	aaaaja
    //   7	27	4	i	int
    //   12	22	5	j	int
    //   17	20	6	k	int
    //   22	18	7	m	int
    //   27	16	8	n	int
    //   97	34	9	localHandler	android.os.Handler
    // Exception table:
    //   from	to	target	type
    //   0	4	140	java/lang/Exception
    //   90	120	140	java/lang/Exception
    //   4	19	143	java/lang/Exception
    //   141	143	143	java/lang/Exception
    //   147	149	143	java/lang/Exception
    //   120	139	146	java/lang/Exception
    //   19	29	149	java/lang/Exception
    //   78	90	149	java/lang/Exception
  }
  
  /* Error */
  public static void bжж0436ж0436ж0436жжж()
  {
    // Byte code:
    //   0: invokestatic 71	kkkkkk/jaajaa:b04360436ж0436жж0436жжж	()Z
    //   3: ifne +4 -> 7
    //   6: return
    //   7: invokestatic 77	kkkkkk/ykykky:bШШ0428Ш0428ШШШ04280428	()Lkkkkkk/ykykky;
    //   10: astore 5
    //   12: getstatic 44	kkkkkk/jaajaa:bббб04310431б0431бб	I
    //   15: istore_0
    //   16: getstatic 32	kkkkkk/jaajaa:bб04310431б0431б0431бб	I
    //   19: istore_1
    //   20: getstatic 44	kkkkkk/jaajaa:bббб04310431б0431бб	I
    //   23: istore_2
    //   24: getstatic 34	kkkkkk/jaajaa:b043104310431б0431б0431бб	I
    //   27: istore_3
    //   28: getstatic 46	kkkkkk/jaajaa:b0431бб04310431б0431бб	I
    //   31: istore 4
    //   33: iload_0
    //   34: iload_1
    //   35: iadd
    //   36: iload_2
    //   37: imul
    //   38: iload_3
    //   39: irem
    //   40: iload 4
    //   42: if_icmpeq +59 -> 101
    //   45: getstatic 44	kkkkkk/jaajaa:bббб04310431б0431бб	I
    //   48: istore_0
    //   49: iload_0
    //   50: getstatic 32	kkkkkk/jaajaa:bб04310431б0431б0431бб	I
    //   53: iload_0
    //   54: iadd
    //   55: imul
    //   56: getstatic 34	kkkkkk/jaajaa:b043104310431б0431б0431бб	I
    //   59: irem
    //   60: tableswitch	default:+20->80, 0:+30->90
    //   80: bipush 49
    //   82: putstatic 44	kkkkkk/jaajaa:bббб04310431б0431бб	I
    //   85: bipush 91
    //   87: putstatic 46	kkkkkk/jaajaa:b0431бб04310431б0431бб	I
    //   90: invokestatic 30	kkkkkk/jaajaa:b0436жж043604360436жжжж	()I
    //   93: putstatic 44	kkkkkk/jaajaa:bббб04310431б0431бб	I
    //   96: bipush 92
    //   98: putstatic 46	kkkkkk/jaajaa:b0431бб04310431б0431бб	I
    //   101: aload 5
    //   103: invokevirtual 81	kkkkkk/ykykky:b04280428ШШ0428ШШШ04280428	()Lkkkkkk/kkyykk;
    //   106: astore 5
    //   108: aload 5
    //   110: getstatic 83	kkkkkk/jaajaa:bбб0431б0431б0431бб	Ljava/lang/String;
    //   113: getstatic 83	kkkkkk/jaajaa:bбб0431б0431б0431бб	Ljava/lang/String;
    //   116: invokevirtual 512	kkkkkk/kkyykk:b0428042804280428042804280428ШШ0428	(Ljava/lang/String;Ljava/lang/String;)Lkkkkkk/bbhbhh;
    //   119: pop
    //   120: return
    //   121: astore 5
    //   123: aload 5
    //   125: athrow
    //   126: astore 5
    //   128: aload 5
    //   130: athrow
    //   131: astore 5
    //   133: aload 5
    //   135: athrow
    //   136: astore 5
    //   138: aload 5
    //   140: athrow
    // Local variable table:
    //   start	length	slot	name	signature
    //   15	41	0	i	int
    //   19	17	1	j	int
    //   23	15	2	k	int
    //   27	13	3	m	int
    //   31	12	4	n	int
    //   10	99	5	localObject	Object
    //   121	3	5	localException1	Exception
    //   126	3	5	localException2	Exception
    //   131	3	5	localException3	Exception
    //   136	3	5	localException4	Exception
    // Exception table:
    //   from	to	target	type
    //   0	6	121	java/lang/Exception
    //   7	12	121	java/lang/Exception
    //   108	120	121	java/lang/Exception
    //   12	33	126	java/lang/Exception
    //   123	126	126	java/lang/Exception
    //   133	136	126	java/lang/Exception
    //   101	108	131	java/lang/Exception
    //   90	101	136	java/lang/Exception
  }
  
  /* Error */
  public static void bжж0436жжж0436жжж(String paramString, dddxxd<Integer, Exception> paramDddxxd)
  {
    // Byte code:
    //   0: invokestatic 71	kkkkkk/jaajaa:b04360436ж0436жж0436жжж	()Z
    //   3: ifne +29 -> 32
    //   6: aload_1
    //   7: new 68	java/lang/Exception
    //   10: dup
    //   11: ldc_w 515
    //   14: sipush 205
    //   17: bipush 18
    //   19: iconst_2
    //   20: invokestatic 52	kkkkkk/gguuuu:bк043Aккк043Aкк043A043A	(Ljava/lang/String;CCC)Ljava/lang/String;
    //   23: invokespecial 234	java/lang/Exception:<init>	(Ljava/lang/String;)V
    //   26: invokeinterface 240 2 0
    //   31: return
    //   32: invokestatic 77	kkkkkk/ykykky:bШШ0428Ш0428ШШШ04280428	()Lkkkkkk/ykykky;
    //   35: astore 7
    //   37: getstatic 44	kkkkkk/jaajaa:bббб04310431б0431бб	I
    //   40: istore_2
    //   41: getstatic 32	kkkkkk/jaajaa:bб04310431б0431б0431бб	I
    //   44: istore_3
    //   45: getstatic 44	kkkkkk/jaajaa:bббб04310431б0431бб	I
    //   48: istore 4
    //   50: getstatic 34	kkkkkk/jaajaa:b043104310431б0431б0431бб	I
    //   53: istore 5
    //   55: invokestatic 436	kkkkkk/jaajaa:b04360436ж043604360436жжжж	()I
    //   58: istore 6
    //   60: iload_2
    //   61: iload_3
    //   62: iadd
    //   63: iload 4
    //   65: imul
    //   66: iload 5
    //   68: irem
    //   69: iload 6
    //   71: if_icmpeq +45 -> 116
    //   74: getstatic 44	kkkkkk/jaajaa:bббб04310431б0431бб	I
    //   77: getstatic 32	kkkkkk/jaajaa:bб04310431б0431б0431бб	I
    //   80: iadd
    //   81: getstatic 44	kkkkkk/jaajaa:bббб04310431б0431бб	I
    //   84: imul
    //   85: getstatic 34	kkkkkk/jaajaa:b043104310431б0431б0431бб	I
    //   88: irem
    //   89: getstatic 46	kkkkkk/jaajaa:b0431бб04310431б0431бб	I
    //   92: if_icmpeq +13 -> 105
    //   95: bipush 94
    //   97: putstatic 44	kkkkkk/jaajaa:bббб04310431б0431бб	I
    //   100: bipush 68
    //   102: putstatic 46	kkkkkk/jaajaa:b0431бб04310431б0431бб	I
    //   105: bipush 78
    //   107: putstatic 44	kkkkkk/jaajaa:bббб04310431б0431бб	I
    //   110: invokestatic 30	kkkkkk/jaajaa:b0436жж043604360436жжжж	()I
    //   113: putstatic 46	kkkkkk/jaajaa:b0431бб04310431б0431бб	I
    //   116: aload 7
    //   118: invokevirtual 81	kkkkkk/ykykky:b04280428ШШ0428ШШШ04280428	()Lkkkkkk/kkyykk;
    //   121: getstatic 83	kkkkkk/jaajaa:bбб0431б0431б0431бб	Ljava/lang/String;
    //   124: aload_0
    //   125: aload_1
    //   126: invokevirtual 519	kkkkkk/kkyykk:bШ042804280428Ш04280428ШШ0428	(Ljava/lang/String;Ljava/lang/String;Lkkkkkk/dddxxd;)V
    //   129: return
    //   130: astore_0
    //   131: aload_0
    //   132: athrow
    //   133: astore_0
    //   134: aload_0
    //   135: athrow
    //   136: astore_0
    //   137: aload_0
    //   138: athrow
    //   139: astore_0
    //   140: aload_0
    //   141: athrow
    // Local variable table:
    //   start	length	slot	name	signature
    //   0	142	0	paramString	String
    //   0	142	1	paramDddxxd	dddxxd<Integer, Exception>
    //   40	23	2	i	int
    //   44	19	3	j	int
    //   48	18	4	k	int
    //   53	16	5	m	int
    //   58	14	6	n	int
    //   35	82	7	localYkykky	ykykky
    // Exception table:
    //   from	to	target	type
    //   116	129	130	java/lang/Exception
    //   37	60	133	java/lang/Exception
    //   131	133	133	java/lang/Exception
    //   137	139	133	java/lang/Exception
    //   0	31	136	java/lang/Exception
    //   32	37	136	java/lang/Exception
    //   105	116	139	java/lang/Exception
  }
  
  public static int bжжж043604360436жжжж()
  {
    return 2;
  }
  
  public static void bжжж04360436ж0436жжж(Notification.Builder paramBuilder)
  {
    if (paramBuilder != null) {}
    try
    {
      int i = bббб04310431б0431бб;
      switch (i * (bб04310431б0431б0431бб + i) % b043104310431б0431б0431бб)
      {
      }
      ykykky localYkykky;
      for (;;)
      {
        bббб04310431б0431бб = b0436жж043604360436жжжж();
        b0431бб04310431б0431бб = b0436жж043604360436жжжж();
        localYkykky = ykykky.bШШ0428Ш0428ШШШ04280428();
      }
    }
    catch (Exception paramBuilder)
    {
      try
      {
        localYkykky.b04280428ШШ0428ШШШ04280428().bШШ04280428ШШШШ04280428(paramBuilder);
        return;
      }
      catch (Exception paramBuilder)
      {
        throw paramBuilder;
      }
      paramBuilder = paramBuilder;
      throw paramBuilder;
    }
  }
  
  public static void bжжж0436жж0436жжж(Activity paramActivity)
  {
    if (!b04360436ж0436жж0436жжж())
    {
      int i = bббб04310431б0431бб;
      switch (i * (bб04310431б0431б0431бб + i) % b043104310431б0431б0431бб)
      {
      default: 
        bббб04310431б0431бб = 26;
        b0431бб04310431б0431бб = b0436жж043604360436жжжж();
      }
      switch (0)
      {
      case 1: 
      default: 
        for (;;)
        {
          switch (1)
          {
          }
        }
      }
      return;
    }
    ttxttx localTtxttx = ttxttx.bи0438и04380438иии0438и();
    if ((b0436жж043604360436жжжж() + bб04310431б0431б0431бб) * b0436жж043604360436жжжж() % b043104310431б0431б0431бб != b0431бб04310431б0431бб)
    {
      bббб04310431б0431бб = b0436жж043604360436жжжж();
      b0431бб04310431б0431бб = 99;
    }
    localTtxttx.b0438и04380438ииии0438и(paramActivity);
  }
  
  @Deprecated
  public static void bжжжж0436ж0436жжж(String paramString)
  {
    try
    {
      throw new NullPointerException();
    }
    catch (Exception localException)
    {
      bббб04310431б0431бб = b0436жж043604360436жжжж();
      if (!b04360436ж0436жж0436жжж())
      {
        do
        {
          return;
          localKkyykk.b0428ШШ0428042804280428ШШ0428(str, localException.setAuthKey(paramString));
          switch (0)
          {
          case 1: 
          default: 
            for (;;)
            {
              switch (0)
              {
              }
            }
          }
        } while ((bббб04310431б0431бб + bб04310431б0431б0431бб) * bббб04310431б0431бб % b043104310431б0431б0431бб == b0431бб04310431б0431бб);
        bббб04310431б0431бб = b0436жж043604360436жжжж();
        b0431бб04310431б0431бб = b0436жж043604360436жжжж();
        return;
      }
      kkyykk localKkyykk = ykykky.bШШ0428Ш0428ШШШ04280428().b04280428ШШ0428ШШШ04280428();
      String str = bбб0431б0431б0431бб;
      LPAuthenticationParams localLPAuthenticationParams = new LPAuthenticationParams();
      switch (1)
      {
      }
    }
    for (;;)
    {
      switch (1)
      {
      }
    }
  }
  
  public static void bжжжжж04360436жжж(jaaaja paramJaaaja)
  {
    for (;;)
    {
      try
      {
        if (!b04360436ж0436жж0436жжж()) {
          return;
        }
        ttxttx localTtxttx = ttxttx.bи0438и04380438иии0438и();
        int i = bббб04310431б0431бб;
        switch (i * (bб04310431б0431б0431бб + i) % b043104310431б0431б0431бб)
        {
        default: 
          bббб04310431б0431бб = 87;
          b0431бб04310431б0431бб = b0436жж043604360436жжжж();
        }
        try
        {
          paramJaaaja = new jaajaa.2(paramJaaaja);
          localTtxttx.bии0438и0438иии0438и(paramJaaaja);
          i = bббб04310431б0431бб;
          switch (i * (bб04310431б0431б0431бб + i) % b043104310431б0431б0431бб)
          {
          case 0: 
            bббб04310431б0431бб = 31;
            b0431бб04310431б0431бб = 77;
            return;
          }
        }
        catch (Exception paramJaaaja)
        {
          throw paramJaaaja;
        }
        return;
      }
      catch (Exception paramJaaaja)
      {
        throw paramJaaaja;
      }
    }
  }
  
  @Deprecated
  public static Fragment bжжжжжж0436жжж()
  {
    Object localObject = new LPAuthenticationParams();
    ConversationViewParams localConversationViewParams = new ConversationViewParams(false);
    switch (0)
    {
    case 1: 
    default: 
      for (;;)
      {
        switch (1)
        {
        }
      }
    }
    localObject = b0436жжжжж0436жжж((LPAuthenticationParams)localObject, localConversationViewParams);
    int i = bббб04310431б0431бб;
    int j = bб04310431б0431б0431бб;
    int k = bббб04310431б0431бб;
    int m = b043104310431б0431б0431бб;
    int n = b0431бб04310431б0431бб;
    int i1 = bббб04310431б0431бб;
    switch (i1 * (bб04310431б0431б0431бб + i1) % bжжж043604360436жжжж())
    {
    default: 
      bббб04310431б0431бб = 65;
      b0431бб04310431б0431бб = b0436жж043604360436жжжж();
    }
    if ((i + j) * k % m != n)
    {
      bббб04310431б0431бб = b0436жж043604360436жжжж();
      b0431бб04310431б0431бб = 61;
    }
    return localObject;
  }
}
