package kkkkkk;

import android.support.annotation.NonNull;
import java.io.Serializable;

public class jjjjee
  implements Serializable
{
  private static final long serialVersionUID = -644442564943375312L;
  private final String b0446ц04460446цццц0446;
  private final eeeeje bц044604460446цццц0446;
  
  public jjjjee(@NonNull String paramString)
  {
    this(paramString, eeeeje.NOT_SPECIFIED);
  }
  
  public jjjjee(@NonNull String paramString, @NonNull eeeeje paramEeeeje)
  {
    this.b0446ц04460446цццц0446 = paramString;
    this.bц044604460446цццц0446 = paramEeeeje;
  }
  
  public static int b0444ф0444044404440444ф04440444ф()
  {
    return 2;
  }
  
  public static int bф04440444044404440444ф04440444ф()
  {
    return 53;
  }
  
  public static int bфф0444044404440444ф04440444ф()
  {
    return 1;
  }
  
  public String b044404440444044404440444ф04440444ф()
  {
    switch (0)
    {
    case 1: 
    default: 
      for (;;)
      {
        switch (1)
        {
        }
      }
    }
    int i = bф04440444044404440444ф04440444ф();
    int j = bфф0444044404440444ф04440444ф();
    int k = b0444ф0444044404440444ф04440444ф();
    int m = bф04440444044404440444ф04440444ф();
    switch (m * (bфф0444044404440444ф04440444ф() + m) % b0444ф0444044404440444ф04440444ф())
    {
    }
    switch (i * (j + i) % k)
    {
    }
    return this.b0446ц04460446цццц0446;
  }
  
  /* Error */
  public eeeeje bфффффф044404440444ф()
  {
    // Byte code:
    //   0: invokestatic 43	kkkkkk/jjjjee:bф04440444044404440444ф04440444ф	()I
    //   3: istore_1
    //   4: invokestatic 45	kkkkkk/jjjjee:bфф0444044404440444ф04440444ф	()I
    //   7: istore_2
    //   8: invokestatic 47	kkkkkk/jjjjee:b0444ф0444044404440444ф04440444ф	()I
    //   11: istore_3
    //   12: iload_1
    //   13: iload_2
    //   14: iload_1
    //   15: iadd
    //   16: imul
    //   17: iload_3
    //   18: irem
    //   19: tableswitch	default:+17->36, 0:+49->68
    //   36: invokestatic 43	kkkkkk/jjjjee:bф04440444044404440444ф04440444ф	()I
    //   39: istore_1
    //   40: iload_1
    //   41: invokestatic 45	kkkkkk/jjjjee:bфф0444044404440444ф04440444ф	()I
    //   44: iload_1
    //   45: iadd
    //   46: imul
    //   47: invokestatic 47	kkkkkk/jjjjee:b0444ф0444044404440444ф04440444ф	()I
    //   50: irem
    //   51: tableswitch	default:+17->68, 0:+17->68
    //   68: aload_0
    //   69: getfield 35	kkkkkk/jjjjee:bц044604460446цццц0446	Lkkkkkk/jjjjee$eeeeje;
    //   72: astore 4
    //   74: aload 4
    //   76: areturn
    //   77: astore 4
    //   79: aload 4
    //   81: athrow
    //   82: astore 4
    //   84: aload 4
    //   86: athrow
    // Local variable table:
    //   start	length	slot	name	signature
    //   0	87	0	this	jjjjee
    //   3	44	1	i	int
    //   7	9	2	j	int
    //   11	8	3	k	int
    //   72	3	4	localEeeeje	eeeeje
    //   77	3	4	localException1	Exception
    //   82	3	4	localException2	Exception
    // Exception table:
    //   from	to	target	type
    //   0	12	77	java/lang/Exception
    //   68	74	82	java/lang/Exception
  }
  
  public static enum eeeeje
  {
    static
    {
      GLOBAL_MENU_MOVE_MONEY = new eeeeje(gguuuu.bк043Aккк043Aкк043A043A("5;?33?SB;EMXGJRB]LOOG\\", '', 'ç', '\003'), 1);
      TILE_ACTION_MENU_PAY_CREDIT_CARD = new eeeeje(gguuuu.bккккк043Aкк043A043A("OEIC^ADVLSSeTMW_j\\NgnScWW]iuZYk^", 'Ò', '\001'), 2);
      TILE_ACTION_MENU_TOP_UP_ISA = new eeeeje(gguuuu.bк043Aккк043Aкк043A043A("\t~\003|\030z}\020\006\r\r\037\016\007\021\031$\032\026\030(\037\033+\026!\020", 'ë', 'Æ', '\003'), 3);
      TILE_ACTION_MENU_PAYMENTS_AND_TRANSFERS = new eeeeje(gguuuu.bккккк043Aкк043A043A("F<@:U8;MCJJ\\KDNVaSE^SLV]]jM[RndcSag[[ik", 'Ï', '\001'), 4);
      IN_ACTIVITY_BUTTON = new eeeeje(gguuuu.bккккк043Aкк043A043A("'+;\034\035-!-\037)-2\024&$#\035\033", '¡', '\005'), 5);
      eeeeje localEeeeje = new eeeeje(gguuuu.bк043Aккк043Aкк043A043A("\006yv\n\023\t\bw\006\fz}\020\006\r\r\037\005\007\027\005\016\022\032", '@', 'í', '\003'), 6);
      int i = b044404440444ф04440444ф04440444ф();
      switch (i * (bф0444ф044404440444ф04440444ф() + i) % bффф044404440444ф04440444ф())
      {
      }
      VIEW_TRANSACTION_DETAILS = localEeeeje;
      NOT_SPECIFIED = new eeeeje(gguuuu.bк043Aккк043Aкк043A043A("vx~\013}sryw{xx", ':', '', '\001'), 7);
      $VALUES = new eeeeje[] { HOME_SCREEN_TRANSFERS_AND_PAYMENT, GLOBAL_MENU_MOVE_MONEY, TILE_ACTION_MENU_PAY_CREDIT_CARD, TILE_ACTION_MENU_TOP_UP_ISA, TILE_ACTION_MENU_PAYMENTS_AND_TRANSFERS, IN_ACTIVITY_BUTTON, VIEW_TRANSACTION_DETAILS, NOT_SPECIFIED };
      i = b044404440444ф04440444ф04440444ф();
      switch (i * (bф0444ф044404440444ф04440444ф() + i) % bффф044404440444ф04440444ф())
      {
      }
      switch (0)
      {
      case 1: 
      default: 
        for (;;)
        {
          switch (0)
          {
          }
        }
      }
    }
    
    private eeeeje() {}
    
    public static int b044404440444ф04440444ф04440444ф()
    {
      return 41;
    }
    
    public static eeeeje b04440444ф044404440444ф04440444ф(String paramString)
    {
      if ((b044404440444ф04440444ф04440444ф() + bф0444ф044404440444ф04440444ф()) * b044404440444ф04440444ф04440444ф() % bффф044404440444ф04440444ф() != b0444фф044404440444ф04440444ф()) {}
      return (eeeeje)Enum.valueOf(eeeeje.class, paramString);
    }
    
    public static int b0444фф044404440444ф04440444ф()
    {
      return 0;
    }
    
    public static int bф0444ф044404440444ф04440444ф()
    {
      return 1;
    }
    
    public static int bффф044404440444ф04440444ф()
    {
      return 2;
    }
  }
}
