package kkkkkk;

import android.content.Context;
import android.os.Bundle;
import java.lang.reflect.Method;
import java.util.Map;
import java.util.Timer;
import java.util.TimerTask;
import java.util.concurrent.Executor;
import java.util.concurrent.atomic.AtomicLong;
import javax.annotation.Nonnull;
import javax.annotation.Nullable;

public class jtjjtt
  extends ddvddv
{
  private static final boolean b044E044E044Eю044Eюю044Eю044E;
  public static int b044E044Eююю044Eю044Eю044E = 84;
  public static int b044Eю044Eюю044Eю044Eю044E = 1;
  @Nullable
  private static volatile jtjjtt b044Eюю044E044Eюю044Eю044E;
  private static final boolean bю044E044Eю044Eюю044Eю044E;
  public static int bю044E044Eюю044Eю044Eю044E = 2;
  public static int bюю044Eюю044Eю044Eю044E;
  public static final String bююю044E044Eюю044Eю044E;
  public volatile boolean b044E044E044E044E044Eюю044Eю044E = true;
  private boolean b044E044Eю044E044Eюю044Eю044E = false;
  private volatile int b044Eю044E044E044Eюю044Eю044E = 0;
  private volatile int b044Eюююю044Eю044Eю044E = 10000;
  private int bю044E044E044E044Eюю044Eю044E = 0;
  private int bю044Eю044E044Eюю044Eю044E = 30000;
  private volatile boolean bю044Eююю044Eю044Eю044E = false;
  public int bюю044E044E044Eюю044Eю044E;
  public Timer bююююю044Eю044Eю044E;
  
  static
  {
    for (;;)
    {
      try
      {
        bююю044E044Eюю044Eю044E = fafffa.b043A043A043A043Aкк043Aкк043A(jtjjtt.class);
        if (faaaff.b043Aк043Aк043Aк043A043Aк043A(faaaff.afaaff.p) != null)
        {
          bool = true;
          bю044E044Eю044Eюю044Eю044E = bool;
          if (faaaff.b043Aк043Aк043Aк043A043Aк043A(faaaff.afaaff.m) != null)
          {
            bool = true;
            b044E044E044Eю044Eюю044Eю044E = bool;
            if ((b044E044Eююю044Eю044Eю044E + b044Eю044Eюю044Eю044Eю044E) * b044E044Eююю044Eю044Eю044E % bю044E044Eюю044Eю044Eю044E != bюю044Eюю044Eю044Eю044E)
            {
              b044E044Eююю044Eю044Eю044E = bкккккк043Aккк();
              bюю044Eюю044Eю044Eю044E = bкккккк043Aккк();
            }
            b044Eюю044E044Eюю044Eю044E = null;
            break;
          }
          int i = b044E044Eююю044Eю044Eю044E;
          int j = b044Eю044Eюю044Eю044Eю044E;
          int k = b044E044Eююю044Eю044Eю044E;
          int m = bю044E044Eюю044Eю044Eю044E;
          int n = bюю044Eюю044Eю044Eю044E;
          if ((i + j) * k % m == n) {
            break label148;
          }
        }
      }
      catch (Exception localException1)
      {
        throw localException1;
      }
      try
      {
        b044E044Eююю044Eю044Eю044E = 99;
        bюю044Eюю044Eю044Eю044E = bкккккк043Aккк();
        bool = false;
      }
      catch (Exception localException2)
      {
        throw localException2;
      }
      boolean bool = false;
      continue;
      label148:
      bool = false;
    }
    switch (0)
    {
    case 1: 
    default: 
      for (;;)
      {
        switch (1)
        {
        }
      }
    }
  }
  
  private jtjjtt()
  {
    super(new vvddvv(), new vddvvv(), new dvvvvv());
  }
  
  public static int b043A043A043A043A043A043Aкккк()
  {
    return 0;
  }
  
  @Nonnull
  public static jtjjtt b043Aк043A043Aкк043Aккк()
  {
    try
    {
      localObject = b044Eюю044E044Eюю044Eю044E;
      if ((b044E044Eююю044Eю044Eю044E + b044Eю044Eюю044Eю044Eю044E) * b044E044Eююю044Eю044Eю044E % bк043A043A043A043A043Aкккк() != bюю044Eюю044Eю044Eю044E)
      {
        b044E044Eююю044Eю044Eю044E = 7;
        bюю044Eюю044Eю044Eю044E = bкккккк043Aккк();
      }
      if (localObject == null) {
        break label42;
      }
    }
    catch (Exception localException1)
    {
      try
      {
        label42:
        jtjjtt localJtjjtt;
        do
        {
          localJtjjtt = b043Aккк043Aк043Aккк();
          Object localObject = localJtjjtt;
        } while ((b044E044Eююю044Eю044Eю044E + b044Eю044Eюю044Eю044Eю044E) * b044E044Eююю044Eю044Eю044E % bю044E044Eюю044Eю044Eю044E == bюю044Eюю044Eю044Eю044E);
        b044E044Eююю044Eю044Eю044E = 80;
        bюю044Eюю044Eю044Eю044E = bкккккк043Aккк();
        return localJtjjtt;
      }
      catch (Exception localException2)
      {
        throw localException2;
      }
      localException1 = localException1;
      throw localException1;
    }
    return localObject;
  }
  
  /* Error */
  private String b043Aк043Aккк043Aккк(@Nonnull String paramString1, @Nullable String paramString2, @Nonnull String paramString3, @Nonnull String paramString4, @Nonnull String paramString5, @Nonnull jjttjt.jtttjt paramJtttjt, @Nullable tttjjt paramTttjjt, boolean paramBoolean)
  {
    // Byte code:
    //   0: aload_1
    //   1: invokestatic 133	kkkkkk/dvdvvd:b043A043A043Aкк043A043A043Aкк	(Ljava/lang/String;)Ljava/lang/String;
    //   4: astore 10
    //   6: aload 10
    //   8: aload_1
    //   9: invokevirtual 139	java/lang/String:equals	(Ljava/lang/Object;)Z
    //   12: ifne +60 -> 72
    //   15: getstatic 45	kkkkkk/jtjjtt:bююю044E044Eюю044Eю044E	Ljava/lang/String;
    //   18: ldc -115
    //   20: bipush 51
    //   22: iconst_4
    //   23: invokestatic 147	kkkkkk/gguuuu:bккккк043Aкк043A043A	(Ljava/lang/String;CC)Ljava/lang/String;
    //   26: iconst_1
    //   27: anewarray 135	java/lang/String
    //   30: dup
    //   31: iconst_0
    //   32: aload_1
    //   33: aastore
    //   34: invokestatic 151	kkkkkk/fafffa:b043Aк043A043Aкк043Aкк043A	(Ljava/lang/String;Ljava/lang/String;[Ljava/lang/String;)V
    //   37: getstatic 157	kkkkkk/tjjjtt:THM_StrongAuth_Failed	Lkkkkkk/tjjjtt;
    //   40: astore_3
    //   41: aload 7
    //   43: ifnull +187 -> 230
    //   46: getstatic 163	kkkkkk/vdvvvd:b044Eю044E044Eю044E044E044E044E044E	Ljava/util/concurrent/Executor;
    //   49: astore_2
    //   50: new 165	kkkkkk/jtjjtt$3
    //   53: dup
    //   54: aload_0
    //   55: aload 7
    //   57: aload_1
    //   58: aload_3
    //   59: invokespecial 168	kkkkkk/jtjjtt$3:<init>	(Lkkkkkk/jtjjtt;Lkkkkkk/tttjjt;Ljava/lang/String;Lkkkkkk/tjjjtt;)V
    //   62: astore_3
    //   63: aload_2
    //   64: aload_3
    //   65: invokeinterface 174 2 0
    //   70: aload_1
    //   71: areturn
    //   72: new 176	java/lang/Thread
    //   75: dup
    //   76: new 178	kkkkkk/jtjjtt$5
    //   79: dup
    //   80: aload_0
    //   81: aload 10
    //   83: aload_2
    //   84: aload_3
    //   85: aload 4
    //   87: aload 5
    //   89: invokestatic 184	kkkkkk/afaafa$aaaffa:b043A043A043Aкк043Aккк043A	(Ljava/lang/String;)Lkkkkkk/afaafa$aaaffa;
    //   92: aload 6
    //   94: aload 7
    //   96: iload 8
    //   98: invokespecial 187	kkkkkk/jtjjtt$5:<init>	(Lkkkkkk/jtjjtt;Ljava/lang/String;Ljava/lang/String;Ljava/lang/String;Ljava/lang/String;Lkkkkkk/afaafa$aaaffa;Lkkkkkk/jjttjt$jtttjt;Lkkkkkk/tttjjt;Z)V
    //   101: invokespecial 189	java/lang/Thread:<init>	(Ljava/lang/Runnable;)V
    //   104: astore_1
    //   105: invokestatic 76	kkkkkk/jtjjtt:bкккккк043Aккк	()I
    //   108: istore 9
    //   110: iload 9
    //   112: getstatic 68	kkkkkk/jtjjtt:b044Eю044Eюю044Eю044Eю044E	I
    //   115: iload 9
    //   117: iadd
    //   118: imul
    //   119: invokestatic 121	kkkkkk/jtjjtt:bк043A043A043A043A043Aкккк	()I
    //   122: irem
    //   123: tableswitch	default:+17->140, 0:+27->150
    //   140: bipush 72
    //   142: putstatic 66	kkkkkk/jtjjtt:b044E044Eююю044Eю044Eю044E	I
    //   145: bipush 94
    //   147: putstatic 72	kkkkkk/jtjjtt:bюю044Eюю044Eю044Eю044E	I
    //   150: iconst_0
    //   151: tableswitch	default:+21->172, 0:+48->199, 1:+-46->105
    //   172: iconst_1
    //   173: tableswitch	default:+23->196, 0:+-68->105, 1:+26->199
    //   196: goto -24 -> 172
    //   199: aload_1
    //   200: invokevirtual 192	java/lang/Thread:start	()V
    //   203: iconst_5
    //   204: istore 9
    //   206: iload 9
    //   208: iconst_0
    //   209: idiv
    //   210: istore 9
    //   212: goto -6 -> 206
    //   215: astore_1
    //   216: bipush 56
    //   218: putstatic 66	kkkkkk/jtjjtt:b044E044Eююю044Eю044Eю044E	I
    //   221: aload 10
    //   223: areturn
    //   224: astore_1
    //   225: aload_1
    //   226: athrow
    //   227: astore_1
    //   228: aload_1
    //   229: athrow
    //   230: aload_1
    //   231: areturn
    // Local variable table:
    //   start	length	slot	name	signature
    //   0	232	0	this	jtjjtt
    //   0	232	1	paramString1	String
    //   0	232	2	paramString2	String
    //   0	232	3	paramString3	String
    //   0	232	4	paramString4	String
    //   0	232	5	paramString5	String
    //   0	232	6	paramJtttjt	jjttjt.jtttjt
    //   0	232	7	paramTttjjt	tttjjt
    //   0	232	8	paramBoolean	boolean
    //   108	103	9	i	int
    //   4	218	10	str	String
    // Exception table:
    //   from	to	target	type
    //   206	212	215	java/lang/Exception
    //   0	41	224	java/lang/Exception
    //   46	50	224	java/lang/Exception
    //   63	70	224	java/lang/Exception
    //   72	105	224	java/lang/Exception
    //   199	203	224	java/lang/Exception
    //   50	63	227	java/lang/Exception
    //   216	221	227	java/lang/Exception
  }
  
  /* Error */
  @Nonnull
  private static jtjjtt b043Aккк043Aк043Aккк()
  {
    // Byte code:
    //   0: iconst_0
    //   1: tableswitch	default:+23->24, 0:+50->51, 1:+-1->0
    //   24: iconst_0
    //   25: tableswitch	default:+23->48, 0:+26->51, 1:+-25->0
    //   48: goto -24 -> 24
    //   51: ldc 2
    //   53: monitorenter
    //   54: getstatic 78	kkkkkk/jtjjtt:b044Eюю044E044Eюю044Eю044E	Lkkkkkk/jtjjtt;
    //   57: astore_0
    //   58: aload_0
    //   59: ifnull +8 -> 67
    //   62: ldc 2
    //   64: monitorexit
    //   65: aload_0
    //   66: areturn
    //   67: new 2	kkkkkk/jtjjtt
    //   70: dup
    //   71: invokespecial 194	kkkkkk/jtjjtt:<init>	()V
    //   74: astore_0
    //   75: aload_0
    //   76: putstatic 78	kkkkkk/jtjjtt:b044Eюю044E044Eюю044Eю044E	Lkkkkkk/jtjjtt;
    //   79: goto -17 -> 62
    //   82: astore_0
    //   83: ldc 2
    //   85: monitorexit
    //   86: aload_0
    //   87: athrow
    // Local variable table:
    //   start	length	slot	name	signature
    //   57	19	0	localJtjjtt	jtjjtt
    //   82	5	0	localObject	Object
    // Exception table:
    //   from	to	target	type
    //   54	58	82	finally
    //   67	79	82	finally
  }
  
  public static int b043Aккккк043Aккк()
  {
    return 1;
  }
  
  public static int bк043A043A043A043A043Aкккк()
  {
    return 2;
  }
  
  /* Error */
  private vvvdvd bк043A043Aккк043Aккк(@Nullable java.util.List<String> paramList)
  {
    // Byte code:
    //   0: new 204	java/lang/StringBuilder
    //   3: dup
    //   4: ldc -50
    //   6: sipush 249
    //   9: iconst_1
    //   10: invokestatic 147	kkkkkk/gguuuu:bккккк043Aкк043A043A	(Ljava/lang/String;CC)Ljava/lang/String;
    //   13: invokespecial 209	java/lang/StringBuilder:<init>	(Ljava/lang/String;)V
    //   16: astore_3
    //   17: iconst_1
    //   18: tableswitch	default:+22->40, 0:+-1->17, 1:+49->67
    //   40: iconst_0
    //   41: tableswitch	default:+23->64, 0:+26->67, 1:+-24->17
    //   64: goto -24 -> 40
    //   67: getstatic 66	kkkkkk/jtjjtt:b044E044Eююю044Eю044Eю044E	I
    //   70: istore_2
    //   71: iload_2
    //   72: getstatic 68	kkkkkk/jtjjtt:b044Eю044Eюю044Eю044Eю044E	I
    //   75: iload_2
    //   76: iadd
    //   77: imul
    //   78: getstatic 70	kkkkkk/jtjjtt:bю044E044Eюю044Eю044Eю044E	I
    //   81: irem
    //   82: tableswitch	default:+18->100, 0:+29->111
    //   100: invokestatic 76	kkkkkk/jtjjtt:bкккккк043Aккк	()I
    //   103: putstatic 66	kkkkkk/jtjjtt:b044E044Eююю044Eю044Eю044E	I
    //   106: bipush 58
    //   108: putstatic 72	kkkkkk/jtjjtt:bюю044Eюю044Eю044Eю044E	I
    //   111: aload_3
    //   112: aload_1
    //   113: invokevirtual 213	java/lang/StringBuilder:append	(Ljava/lang/Object;)Ljava/lang/StringBuilder;
    //   116: pop
    //   117: getstatic 59	kkkkkk/jtjjtt:bю044E044Eю044Eюю044Eю044E	Z
    //   120: ifeq +44 -> 164
    //   123: getstatic 64	kkkkkk/jtjjtt:b044E044E044Eю044Eюю044Eю044E	Z
    //   126: ifeq +38 -> 164
    //   129: new 215	kkkkkk/faaffa
    //   132: dup
    //   133: aload_1
    //   134: invokespecial 218	kkkkkk/faaffa:<init>	(Ljava/util/List;)V
    //   137: astore_1
    //   138: aload_1
    //   139: aload_0
    //   140: getfield 221	kkkkkk/jtjjtt:b042204220422ТТ0422ТТТТ	I
    //   143: iconst_1
    //   144: invokevirtual 225	kkkkkk/faaffa:bк043Aк043A043Aк043A043Aкк	(IZ)V
    //   147: aload_1
    //   148: areturn
    //   149: astore_1
    //   150: getstatic 45	kkkkkk/jtjjtt:bююю044E044Eюю044Eю044E	Ljava/lang/String;
    //   153: ldc -29
    //   155: bipush 25
    //   157: iconst_0
    //   158: invokestatic 147	kkkkkk/gguuuu:bккккк043Aкк043A043A	(Ljava/lang/String;CC)Ljava/lang/String;
    //   161: invokestatic 231	kkkkkk/fafffa:b043Aккк043Aк043Aкк043A	(Ljava/lang/String;Ljava/lang/String;)V
    //   164: aconst_null
    //   165: astore_1
    //   166: getstatic 66	kkkkkk/jtjjtt:b044E044Eююю044Eю044Eю044E	I
    //   169: istore_2
    //   170: iload_2
    //   171: getstatic 68	kkkkkk/jtjjtt:b044Eю044Eюю044Eю044Eю044E	I
    //   174: iload_2
    //   175: iadd
    //   176: imul
    //   177: getstatic 70	kkkkkk/jtjjtt:bю044E044Eюю044Eю044Eю044E	I
    //   180: irem
    //   181: tableswitch	default:+19->200, 0:+-34->147
    //   200: iconst_0
    //   201: putstatic 66	kkkkkk/jtjjtt:b044E044Eююю044Eю044Eю044E	I
    //   204: bipush 29
    //   206: putstatic 72	kkkkkk/jtjjtt:bюю044Eюю044Eю044Eю044E	I
    //   209: aconst_null
    //   210: areturn
    //   211: astore_1
    //   212: aload_1
    //   213: athrow
    //   214: astore_3
    //   215: getstatic 45	kkkkkk/jtjjtt:bююю044E044Eюю044Eю044E	Ljava/lang/String;
    //   218: astore_3
    //   219: ldc -23
    //   221: sipush 129
    //   224: sipush 138
    //   227: iconst_2
    //   228: invokestatic 237	kkkkkk/gguuuu:bк043Aккк043Aкк043A043A	(Ljava/lang/String;CCC)Ljava/lang/String;
    //   231: astore 4
    //   233: aload_3
    //   234: aload 4
    //   236: invokestatic 240	kkkkkk/fafffa:b043Aк043Aк043Aк043Aкк043A	(Ljava/lang/String;Ljava/lang/String;)V
    //   239: aload_0
    //   240: getfield 221	kkkkkk/jtjjtt:b042204220422ТТ0422ТТТТ	I
    //   243: istore_2
    //   244: aload_1
    //   245: iload_2
    //   246: iconst_0
    //   247: invokevirtual 225	kkkkkk/faaffa:bк043Aк043A043Aк043A043Aкк	(IZ)V
    //   250: aload_1
    //   251: areturn
    //   252: astore_1
    //   253: aload_1
    //   254: athrow
    // Local variable table:
    //   start	length	slot	name	signature
    //   0	255	0	this	jtjjtt
    //   0	255	1	paramList	java.util.List<String>
    //   70	176	2	i	int
    //   16	96	3	localStringBuilder	StringBuilder
    //   214	1	3	localIllegalStateException	IllegalStateException
    //   218	16	3	str1	String
    //   231	4	4	str2	String
    // Exception table:
    //   from	to	target	type
    //   215	219	149	java/lang/RuntimeException
    //   219	233	149	java/lang/RuntimeException
    //   233	244	149	java/lang/RuntimeException
    //   244	250	149	java/lang/RuntimeException
    //   0	17	211	java/lang/Exception
    //   111	138	211	java/lang/Exception
    //   138	147	211	java/lang/Exception
    //   215	219	211	java/lang/Exception
    //   233	244	211	java/lang/Exception
    //   138	147	214	java/lang/IllegalStateException
    //   150	164	252	java/lang/Exception
    //   219	233	252	java/lang/Exception
    //   244	250	252	java/lang/Exception
  }
  
  public static int bкккккк043Aккк()
  {
    return 10;
  }
  
  public void b043A043A043A043Aкк043Aккк(Context paramContext, String paramString)
  {
    switch (1)
    {
    case 0: 
    default: 
      for (;;)
      {
        switch (0)
        {
        }
      }
    }
    jttjjt localJttjjt = new jttjjt();
    int i = b044E044Eююю044Eю044Eю044E;
    switch (i * (b044Eю044Eюю044Eю044Eю044E + i) % bк043A043A043A043A043Aкккк())
    {
    default: 
      b044E044Eююю044Eю044Eю044E = bкккккк043Aккк();
      bюю044Eюю044Eю044Eю044E = bкккккк043Aккк();
    }
    paramContext = localJttjjt.b043A043A043Aккккккк(paramContext).bк043Aкк043Aккккк(paramString);
    if ((b044E044Eююю044Eю044Eю044E + b044Eю044Eюю044Eю044Eю044E) * b044E044Eююю044Eю044Eю044E % bю044E044Eюю044Eю044Eю044E != bюю044Eюю044Eю044Eю044E)
    {
      b044E044Eююю044Eю044Eю044E = bкккккк043Aккк();
      bюю044Eюю044Eю044Eю044E = 17;
    }
    bкккк043Aк043Aккк(paramContext);
  }
  
  public String b043A043A043Aк043Aк043Aккк(@Nonnull Object paramObject, @Nonnull jjttjt.jtttjt paramJtttjt, @Nullable tttjjt paramTttjjt)
  {
    boolean bool = false;
    Object localObject1 = null;
    if ((paramObject instanceof Bundle))
    {
      paramObject = (Bundle)paramObject;
      localObject1 = new jjttjt.ttttjt();
      ((jjttjt.ttttjt)localObject1).bкккк043A043Aкккк(paramObject.getString(gguuuu.bк043Aккк043Aкк043A043A("dyynfun~s{q", '?', '<', '\001')));
      ((jjttjt.ttttjt)localObject1).bк043A043A043Aк043Aкккк(paramObject.getString(gguuuu.bккккк043Aкк043A043A("k\001\001umps\006{\003\003", '\n', '\000')));
      ((jjttjt.ttttjt)localObject1).b043A043A043A043Aк043Aкккк(paramObject.getString(gguuuu.bккккк043Aкк043A043A("+@@5-2??F8LI", 'È', '\000')));
      ((jjttjt.ttttjt)localObject1).bк043Aкк043A043Aкккк(paramObject.getString(gguuuu.bк043Aккк043Aкк043A043A("Ylj]SfWdcX][", '\003', 'ù', '\000')));
      ((jjttjt.ttttjt)localObject1).b043Aккк043A043Aкккк(paramObject.getString(gguuuu.bк043Aккк043Aкк043A043A("Ylj]Scd`]_b", 'D', 'C', '\002')));
      ((jjttjt.ttttjt)localObject1).b043A043Aкк043A043Aкккк(paramObject.getString(gguuuu.bккккк043Aкк043A043A("vlxqk", '\002', '\000')));
      paramObject = bк043A043Aк043Aк043Aккк((jjttjt.ttttjt)localObject1, paramJtttjt, paramTttjjt);
    }
    do
    {
      Object localObject2;
      int i;
      do
      {
        return paramObject;
        localObject2 = paramObject.getClass();
        i = b044E044Eююю044Eю044Eю044E;
        switch (i * (b044Eю044Eюю044Eю044Eю044E + i) % bю044E044Eюю044Eю044Eю044E)
        {
        default: 
          b044E044Eююю044Eю044Eю044E = 8;
          bюю044Eюю044Eю044Eю044E = bкккккк043Aккк();
        }
        localObject2 = faaaff.bккк043A043Aк043A043Aк043A((Class)localObject2, gguuuu.bккккк043Aкк043A043A("30>\r);'", '4', '\005'), new Class[0]);
        if (localObject2 != null) {
          break;
        }
        fafffa.b043Aккк043Aк043Aкк043A(bююю044E044Eюю044Eю044E, gguuuu.bккккк043Aкк043A043A("Nerq^c`\032iYiWbYgWc\020S]R_\013XX\\\007NFZH\002\003GDR!=O;zwD;I<B6", '¾', '\003'));
        switch (1)
        {
        case 0: 
        default: 
          for (;;)
          {
            switch (0)
            {
            }
          }
        }
        paramJtttjt = tjjjtt.THM_StrongAuth_Failed;
        paramObject = localObject1;
      } while (paramTttjjt == null);
      vdvvvd.b044Eю044E044Eю044E044E044E044E044E.execute(new jtjjtt.3(this, paramTttjjt, null, paramJtttjt));
      return null;
      do
      {
        Object localObject3 = (Map)paramObject;
        localObject1 = (String)((Map)localObject3).get(gguuuu.bккккк043Aкк043A043A("\001\026\026\013\003\030\013\032\033\022\031\031", 'O', '\004'));
        paramObject = (String)((Map)localObject3).get(gguuuu.bккккк043Aкк043A043A("\023\021\004yz{\f\005\003", 'ï', '\003'));
        localObject2 = (String)((Map)localObject3).get(gguuuu.bккккк043Aкк043A043A("\001\026\026\013\003\b\025\025\034\016\"\037", 'O', '\004'));
        String str1 = (String)((Map)localObject3).get(gguuuu.bккккк043Aкк043A043A("s\007\005wmzqrxl", 'y', '\002'));
        String str2 = (String)((Map)localObject3).get(gguuuu.bккккк043Aкк043A043A("k\001\001um\003\001\004\t", 'X', '\001'));
        localObject3 = (String)((Map)localObject3).get(gguuuu.bк043Aккк043Aкк043A043A("tjvoi", '', '\007', '\001'));
        if ((dvdvvd.b043A043Aк043Aк043A043A043Aкк(paramObject)) || (dvdvvd.b043A043Aк043Aк043A043A043Aкк(str1)) || (dvdvvd.b043A043Aк043Aк043A043A043Aкк((String)localObject2)) || (dvdvvd.b043A043Aк043Aк043A043A043Aкк(str2)) || (dvdvvd.b043A043Aк043Aк043A043A043Aкк((String)localObject1)))
        {
          paramJtttjt = tjjjtt.THM_StrongAuth_Failed;
          paramObject = localObject1;
          if (paramTttjjt == null) {
            break;
          }
          vdvvvd.b044Eю044E044Eю044E044E044E044E044E.execute(new jtjjtt.3(this, paramTttjjt, (String)localObject1, paramJtttjt));
          return localObject1;
        }
        if (gguuuu.bк043Aккк043Aкк043A043A(")\035 #.0\"0", 'b', ',', '\001').equals(paramObject)) {
          bool = true;
        }
        while (gguuuu.bккккк043Aкк043A043A("`bT`fb", 'l', '\000').equals(paramObject)) {
          return b043Aк043Aккк043Aккк((String)localObject1, (String)localObject3, str2, (String)localObject2, str1, paramJtttjt, paramTttjjt, bool);
        }
        fafffa.b043Aккк043Aк043Aкк043A(bююю044E044Eюю044Eю044E, gguuuu.bк043Aккк043Aкк043A043A("#64'\035\036\037/#(&V\037(S \033$#\030\034\024WJ\r\n\026M\032D\024\025\021\004\005\004\002", 'c', 'Z', '\002'));
        paramJtttjt = tjjjtt.THM_StrongAuth_Failed;
        paramObject = localObject1;
        if (paramTttjjt == null) {
          break;
        }
        paramObject = vdvvvd.b044Eю044E044Eю044E044E044E044E044E;
        paramJtttjt = new jtjjtt.3(this, paramTttjjt, (String)localObject1, paramJtttjt);
        i = b044E044Eююю044Eю044Eю044E;
        switch (i * (b043Aккккк043Aккк() + i) % bю044E044Eюю044Eю044Eю044E)
        {
        default: 
          b044E044Eююю044Eю044Eю044E = bкккккк043Aккк();
          bюю044Eюю044Eю044Eю044E = bкккккк043Aккк();
        }
        paramObject.execute(paramJtttjt);
        return localObject1;
        paramObject = faaaff.bк043A043A043A043Aк043A043Aк043A(paramObject, (Method)localObject2, new Object[0]);
      } while ((paramObject instanceof Map));
      fafffa.b043Aккк043Aк043Aкк043A(bююю044E044Eюю044Eю044E, gguuuu.bккккк043Aкк043A043A("7}|\r]{\020}?>\022\006\026\030\026\023\031F\037\033\031\031\023L\"( \026", 'J', '\004'));
      paramJtttjt = tjjjtt.THM_StrongAuth_Failed;
      paramObject = localObject1;
    } while (paramTttjjt == null);
    vdvvvd.b044Eю044E044Eю044E044E044E044E044E.execute(new jtjjtt.3(this, paramTttjjt, null, paramJtttjt));
    return null;
  }
  
  public final vvvdvd b043A043Aкккк043Aккк(jttjjt paramJttjjt)
  {
    try
    {
      if (!paramJttjjt.bююююю044E044Eюю044E) {
        break label112;
      }
      return bк043A043Aккк043Aккк(paramJttjjt.b044E044Eююю044E044Eюю044E);
    }
    catch (Exception paramJttjjt)
    {
      try
      {
        if ((i + b044Eю044Eюю044Eю044Eю044E) * b044E044Eююю044Eю044Eю044E % bю044E044Eюю044Eю044Eю044E != bюю044Eюю044Eю044Eю044E)
        {
          b044E044Eююю044Eю044Eю044E = bкккккк043Aккк();
          bюю044Eюю044Eю044Eю044E = 64;
        }
        int i = this.b042204220422ТТ0422ТТТТ;
        if ((b044E044Eююю044Eю044Eю044E + b044Eю044Eюю044Eю044Eю044E) * b044E044Eююю044Eю044Eю044E % bю044E044Eюю044Eю044Eю044E != bюю044Eюю044Eю044Eю044E)
        {
          b044E044Eююю044Eю044Eю044E = 74;
          bюю044Eюю044Eю044Eю044E = 99;
        }
        paramJttjjt.bк043Aк043A043Aк043A043Aкк(i, true);
        return paramJttjjt;
      }
      catch (Exception paramJttjjt)
      {
        StringBuilder localStringBuilder;
        throw paramJttjjt;
      }
      paramJttjjt = paramJttjjt;
      throw paramJttjjt;
    }
    localStringBuilder.append(paramJttjjt);
    paramJttjjt = new aaaaaf(paramJttjjt);
    i = b044E044Eююю044Eю044Eю044E;
    label112:
    paramJttjjt = paramJttjjt.b044E044Eююю044E044Eюю044E;
    localStringBuilder = new StringBuilder(gguuuu.bккккк043Aкк043A043A("o7/@40=h<6e5-1a}_", '', '\002'));
    switch (1)
    {
    }
    for (;;)
    {
      switch (0)
      {
      }
    }
  }
  
  public String bк043A043Aк043Aк043Aккк(@Nonnull jjttjt.ttttjt paramTtttjt, @Nonnull jjttjt.jtttjt paramJtttjt, @Nullable tttjjt paramTttjjt)
  {
    boolean bool1 = false;
    String str1;
    for (;;)
    {
      try
      {
        str1 = paramTtttjt.bюююю044Eюю044Eю044E;
        str2 = paramTtttjt.bюю044E044Eююю044Eю044E;
        String str3 = paramTtttjt.bю044E044E044Eююю044Eю044E;
        String str4 = paramTtttjt.b044Eююю044Eюю044Eю044E;
        String str5 = paramTtttjt.b044E044E044E044Eююю044Eю044E;
        paramTtttjt = paramTtttjt.b044Eю044E044Eююю044Eю044E;
        if ((b044E044Eююю044Eю044Eю044E + b044Eю044Eюю044Eю044Eю044E) * b044E044Eююю044Eю044Eю044E % bю044E044Eюю044Eю044Eю044E != b043A043A043A043A043A043Aкккк())
        {
          b044E044Eююю044Eю044Eю044E = bкккккк043Aккк();
          bюю044Eюю044Eю044Eю044E = 95;
        }
        try
        {
          if (!dvdvvd.b043A043Aк043Aк043A043A043Aкк(str2))
          {
            bool2 = dvdvvd.b043A043Aк043Aк043A043A043Aкк(str3);
            if ((!bool2) && (!dvdvvd.b043A043Aк043Aк043A043A043Aкк(paramTtttjt)) && (!dvdvvd.b043A043Aк043Aк043A043A043Aкк(str5)) && (!dvdvvd.b043A043Aк043Aк043A043A043Aкк(str1))) {}
          }
          else
          {
            paramTtttjt = tjjjtt.THM_StrongAuth_Failed;
            if (paramTttjjt == null) {
              break;
            }
            vdvvvd.b044Eю044E044Eю044E044E044E044E044E.execute(new jtjjtt.3(this, paramTttjjt, str1, paramTtttjt));
            return str1;
          }
          bool2 = gguuuu.bккккк043Aкк043A043A("\031\r\020\023\036 \022 ", '7', '\001').equals(str2);
          if (!bool2) {
            continue;
          }
          bool1 = true;
          switch (1)
          {
          case 0: 
          default: 
            switch (1)
            {
            }
            break;
          }
          return b043Aк043Aккк043Aккк(str1, str4, str5, paramTtttjt, str3, paramJtttjt, paramTttjjt, bool1);
        }
        catch (Exception paramTtttjt)
        {
          int i;
          throw paramTtttjt;
        }
        paramTtttjt = bююю044E044Eюю044Eю044E;
        paramJtttjt = gguuuu.bккккк043Aкк043A043A("7LLA9<?QGNN\001KV\004NT]IUSO\030\rQP^\030f\023dgeZ]^^", 'U', '\000');
        fafffa.b043Aккк043Aк043Aкк043A(paramTtttjt, paramJtttjt);
        paramTtttjt = tjjjtt.THM_StrongAuth_Failed;
        i = b044E044Eююю044Eю044Eю044E;
        switch (i * (b044Eю044Eюю044Eю044Eю044E + i) % bю044E044Eюю044Eю044Eю044E)
        {
        default: 
          b044E044Eююю044Eю044Eю044E = 63;
          bюю044Eюю044Eю044Eю044E = bкккккк043Aккк();
        }
        if (paramTttjjt == null) {
          break;
        }
        vdvvvd.b044Eю044E044Eю044E044E044E044E044E.execute(new jtjjtt.3(this, paramTttjjt, null, paramTtttjt));
        return str1;
      }
      catch (Exception paramTtttjt)
      {
        String str2;
        boolean bool2;
        throw paramTtttjt;
      }
      bool2 = gguuuu.bккккк043Aкк043A043A("<<,6:4", '[', '\003').equals(str2);
      if (!bool2) {}
    }
    return str1;
  }
  
  public final boolean bк043Aкккк043Aккк(int paramInt, boolean paramBoolean, ddvddv.dvdvdv paramDvdvdv)
  {
    if (paramDvdvdv == ddvddv.dvdvdv.int)
    {
      if (this.b044E044Eю044E044Eюю044Eю044E) {
        return false;
      }
      paramInt = this.bю044Eю044E044Eюю044Eю044E;
    }
    label456:
    label465:
    label473:
    for (;;)
    {
      fafffa.b043Aккк043Aк043Aкк043A(bююю044E044Eюю044Eю044E, gguuuu.bккккк043Aкк043A043A("\036(\b\030\031 \025\032\027\004\023\020\034T", 'Å', '\005') + paramDvdvdv + gguuuu.bккккк043Aкк043A043A("\035-\022^QaYVZR\n\\KHT\005EV\002TT@PQA?", '', '\002'));
      long l;
      if (((paramBoolean) && (!this.b0422ТТ0422Т0422ТТТТ.bк043Aккккк043A043Aк())) || ((!paramBoolean) && (!this.b0422ТТ0422Т0422ТТТТ.b043Aк043A043A043A043A043Aк043Aк())))
      {
        fafffa.b043Aк043Aк043Aк043Aкк043A(bююю044E044Eюю044Eю044E, gguuuu.bккккк043Aкк043A043A(">H(89@5:7$30<t", '\023', '\003') + paramDvdvdv + gguuuu.bк043Aккк043Aкк043A043A("{\016t79GKN@@}}MOU\002LRNZLL", ' ', 'M', '\001'));
        return false;
        if ((b044E044Eююю044Eю044Eю044E + b044Eю044Eюю044Eю044Eю044E) * b044E044Eююю044Eю044Eю044E % bю044E044Eюю044Eю044Eю044E != bюю044Eюю044Eю044Eю044E)
        {
          b044E044Eююю044Eю044Eю044E = 61;
          bюю044Eюю044Eю044Eю044E = 87;
        }
        if (!this.b0422ТТ0422Т0422ТТТТ.b043A043Aккккк043A043Aк(paramBoolean))
        {
          fafffa.b043A043Aкк043Aк043Aкк043A(bююю044E044Eюю044Eю044E, gguuuu.bк043Aккк043Aкк043A043A("bqnz+kuzlgi}#ko oplcm_lk\027eg\024VS_STZ\r^P[^MZZJH\017\002BBNPQEIA", 'Ö', 'f', '\000'));
          return false;
        }
      }
      else if ((paramDvdvdv == ddvddv.dvdvdv.if) || (paramDvdvdv == ddvddv.dvdvdv.int))
      {
        l = this.b042204220422Т04220422ТТТТ.get() & 0x4000;
        if (paramDvdvdv != ddvddv.dvdvdv.int) {
          break label456;
        }
      }
      for (int i = this.bю044E044E044E044Eюю044Eю044E;; i = this.b044Eю044E044E044Eюю044Eю044E)
      {
        paramBoolean = true;
        for (;;)
        {
          if ((0x7000 & l) != 0L)
          {
            switch (1)
            {
            case 0: 
            default: 
              for (;;)
              {
                switch (1)
                {
                }
              }
            }
            switch (1)
            {
            }
            for (;;)
            {
              switch (1)
              {
              }
            }
            if (paramDvdvdv != ddvddv.dvdvdv.if) {
              break label473;
            }
            aaafaf.bкк043Aкккк043Aк043A(this.b0422Т04220422Т0422ТТТТ.b0422042204220422Т0422042204220422Т);
            if (!this.bю044Eююю044Eю044Eю044E) {
              break label465;
            }
            if ((b044E044Eююю044Eю044Eю044E + b043Aккккк043Aккк()) * b044E044Eююю044Eю044Eю044E % bк043A043A043A043A043Aкккк() == bюю044Eюю044Eю044Eю044E) {
              break;
            }
            b044E044Eююю044Eю044Eю044E = 25;
            bюю044Eюю044Eю044Eю044E = 7;
            return false;
            l = this.b042204220422Т04220422ТТТТ.get();
            i = 0;
            paramBoolean = false;
            continue;
            new Thread(new jtjjtt.4(this, l, paramBoolean, i, paramInt, paramDvdvdv)).start();
          }
        }
        return true;
      }
      paramInt = this.b044Eюююю044Eю044Eю044E;
    }
  }
  
  public final void bкк043A043Aкк043Aккк(@Nonnull jttjjt paramJttjjt)
  {
    if (bю044E044Eю044Eюю044Eю044E)
    {
      i = b044E044Eююю044Eю044Eю044E;
      switch (i * (b044Eю044Eюю044Eю044Eю044E + i) % bю044E044Eюю044Eю044Eю044E)
      {
      default: 
        b044E044Eююю044Eю044Eю044E = bкккккк043Aккк();
        bюю044Eюю044Eю044Eю044E = 23;
      }
      if (b044E044E044Eю044Eюю044Eю044E) {}
    }
    else if (paramJttjjt.bююююю044E044Eюю044E)
    {
      fafffa.b043Aк043Aк043Aк043Aкк043A(bююю044E044Eюю044Eю044E, gguuuu.bккккк043Aкк043A043A("2O-Z[X\tVTN_Oai\021`bh\025WmYbf\\^ic+ qnhexk'qwmw\002qs/\005yw3\001~x\ny\f\024I<c\016\022@\013\021\n\024\030\024\t\035\023\032\032L\017\021\037&&R\034$-V,(Y$* *4$&a7,*e31+<,>FmB56q;HIF\021\007\bMLQ>PD\016HKWLZH\025QX\031ZWUbc` ", 'Ê', '\001'));
      throw new IllegalStateException(gguuuu.bк043Aккк043Aкк043A043A("Mgnphf!tn\036fjdn3\030K^^fW\022aQabf\f\0239T0[ZU\004\026\r\nKG?N<LRw@ItBBFp6>C;0", '', '', '\000'));
    }
    this.b044Eю044E044E044Eюю044Eю044E = ((int)ddvddv.bк043Aккк043A043Aк043Aк(paramJttjjt.b044Eю044E044E044Eю044Eюю044E, 0L, gguuuu.bккккк043Aкк043A043A("3#$+ %\"[.\035\032&V\"\036!\034&", '¼', '\005')));
    this.b044Eюююю044Eю044Eю044E = ((int)ddvddv.bк043Aккк043A043Aк043Aк(paramJttjjt.bю044Eюю044Eю044Eюю044E, 0L, gguuuu.bккккк043Aкк043A043A("uefmbgd\036p_\\h\031l`cZchf", 'Ò', '\002')));
    this.bю044Eю044E044Eюю044Eю044E = ((int)ddvddv.bк043Aккк043A043Aк043Aк(paramJttjjt.b044E044Eюю044Eю044Eюю044E, 0L, gguuuu.bккккк043Aкк043A043A("VZT^\tXHIPEJG\001SB?K{OCF=FKI", '\023', '\005')));
    this.b0422ТТ042204220422ТТТТ = paramJttjjt.b044Eюю044E044Eю044Eюю044E;
    int i = b044E044Eююю044Eю044Eю044E;
    switch (i * (b044Eю044Eюю044Eю044Eю044E + i) % bю044E044Eюю044Eю044Eю044E)
    {
    default: 
      b044E044Eююю044Eю044Eю044E = 38;
      bюю044Eюю044Eю044Eю044E = bкккккк043Aккк();
    }
    this.bю044E044E044E044Eюю044Eю044E = ((int)ddvddv.bк043Aккк043A043Aк043Aк(paramJttjjt.b044Eю044Eю044Eю044Eюю044E, 0L, gguuuu.bк043Aккк043Aкк043A043A("\006\f\b\024@\022\004\007\020\007\016\rH\035\016\r\033M\033\031\036\033'", '¥', '\n', '\001')));
    this.bю044Eююю044Eю044Eю044E = paramJttjjt.b044Eю044Eюю044E044Eюю044E;
    this.b044E044Eю044E044Eюю044Eю044E = paramJttjjt.bюю044E044E044Eю044Eюю044E;
    this.b044E044E044E044E044Eюю044Eю044E = true;
    i = paramJttjjt.bююю044Eю044E044Eюю044E;
    int j = jttjjt.bю044E044E044Eюю044Eюю044E;
    this.bюю044E044E044Eюю044Eю044E = ((int)ddvddv.bк043Aккк043A043Aк043Aк(i, j, gguuuu.bккккк043Aкк043A043A(",\035-!\",\016&'\026,1*5<<", '¼', '\001')));
    if (this.bююююю044Eю044Eю044E != null) {
      this.bююююю044Eю044Eю044E.cancel();
    }
    ddvddv.bк043Aккк043A043Aк043Aк(paramJttjjt.bю044Eю044E044Eю044Eюю044E, 0L, gguuuu.bккккк043Aкк043A043A("c\b\021j\013\024\003\021t\021\006\004\030\ny\020\025\016", '\027', '\000'));
    ddvddv.bк043Aккк043A043Aк043Aк(paramJttjjt.b044E044E044Eю044Eю044Eюю044E, 0L, gguuuu.bккккк043Aкк043A043A("\026633\0328?,8\0324'#5%\023'*!", ';', '\002'));
    ddvddv.bк043Aккк043A043Aк043Aк(paramJttjjt.bюю044Eю044Eю044Eюю044E, 2L, gguuuu.bккккк043Aкк043A043A("\036\"\027\026* ''Y\034\037 31!$;", 'e', '\001'));
  }
  
  /* Error */
  public final void bкк043Aк043Aк043Aккк(faafaf.aaffaf paramAaffaf)
  {
    // Byte code:
    //   0: getstatic 66	kkkkkk/jtjjtt:b044E044Eююю044Eю044Eю044E	I
    //   3: getstatic 68	kkkkkk/jtjjtt:b044Eю044Eюю044Eю044Eю044E	I
    //   6: iadd
    //   7: getstatic 66	kkkkkk/jtjjtt:b044E044Eююю044Eю044Eю044E	I
    //   10: imul
    //   11: getstatic 70	kkkkkk/jtjjtt:bю044E044Eюю044Eю044Eю044E	I
    //   14: irem
    //   15: invokestatic 115	kkkkkk/jtjjtt:b043A043A043A043A043A043Aкккк	()I
    //   18: if_icmpeq +13 -> 31
    //   21: bipush 29
    //   23: putstatic 66	kkkkkk/jtjjtt:b044E044Eююю044Eю044Eю044E	I
    //   26: bipush 77
    //   28: putstatic 72	kkkkkk/jtjjtt:bюю044Eюю044Eю044Eю044E	I
    //   31: aload_0
    //   32: getfield 700	kkkkkk/jtjjtt:bюю044E044E044Eюю044Eю044E	I
    //   35: istore_2
    //   36: iload_2
    //   37: ifle +8 -> 45
    //   40: aload_0
    //   41: aload_1
    //   42: invokestatic 732	com/threatmetrix/TrustDefender/internal/J6:int	(Lkkkkkk/jtjjtt;Lkkkkkk/faafaf$aaffaf;)V
    //   45: return
    //   46: astore_1
    //   47: aload_1
    //   48: athrow
    //   49: astore_1
    //   50: aload_1
    //   51: athrow
    // Local variable table:
    //   start	length	slot	name	signature
    //   0	52	0	this	jtjjtt
    //   0	52	1	paramAaffaf	faafaf.aaffaf
    //   35	2	2	i	int
    // Exception table:
    //   from	to	target	type
    //   40	45	46	java/lang/Exception
    //   31	36	49	java/lang/Exception
  }
  
  public final faafaa bкк043Aккк043Aккк(faafaf.aaffaf paramAaffaf)
  {
    
    int i;
    if ((this.b042204220422Т04220422ТТТТ.get() & 0x26) != 0L)
    {
      i = 1;
      if ((!tttjtt.dvdddd.bкк043A043A043A043A043Aккк()) || (i == 0)) {
        break label174;
      }
      break label179;
    }
    for (;;)
    {
      try
      {
        ffaaaf localFfaaaf = new ffaaaf(paramAaffaf, this.b042204220422Т04220422ТТТТ.get());
        Object localObject2 = localFfaaaf;
        if (localFfaaaf == null)
        {
          localObject2 = new faafaa();
          i = b044E044Eююю044Eю044Eю044E;
          switch (i * (b044Eю044Eюю044Eю044Eю044E + i) % bю044E044Eюю044Eю044Eю044E)
          {
          default: 
            b044E044Eююю044Eю044Eю044E = bкккккк043Aккк();
            bюю044Eюю044Eю044Eю044E = bкккккк043Aккк();
          }
          i = b044E044Eююю044Eю044Eю044E;
          switch (i * (b044Eю044Eюю044Eю044Eю044E + i) % bк043A043A043A043A043Aкккк())
          {
          default: 
            b044E044Eююю044Eю044Eю044E = bкккккк043Aккк();
            bюю044Eюю044Eю044Eю044E = bкккккк043Aккк();
          }
          ((faafaa)localObject2).b042204220422Т0422ТТТ0422Т = ffafaa.b043A043A043A043Aк043A043A043A043Aк(paramAaffaf);
        }
        return localObject2;
      }
      catch (InterruptedException localInterruptedException) {}
      i = 0;
      break;
      label174:
      Object localObject1 = null;
    }
    label179:
    switch (1)
    {
    }
    for (;;)
    {
      switch (0)
      {
      }
    }
  }
}
