package kkkkkk;

import android.content.Context;
import java.util.ArrayList;
import java.util.List;
import java.util.concurrent.TimeUnit;
import javax.annotation.Nonnull;
import javax.annotation.Nullable;

public class jttjjt
  extends vvdvvv
{
  private static final String b044E044E044E044Eюю044Eюю044E;
  public static int b044E044Eю044Eю044E044Eюю044E = 0;
  public static final long b044E044Eю044Eюю044Eюю044E;
  public static int b044Eю044E044Eю044E044Eюю044E = 1;
  public static final int b044Eю044E044Eюю044Eюю044E;
  public static final int b044Eююю044Eю044Eюю044E;
  public static final int bю044E044E044Eюю044Eюю044E;
  public static int bю044Eю044Eю044E044Eюю044E = 47;
  public static int bюю044E044Eю044E044Eюю044E = 2;
  public static final long bюю044E044Eюю044Eюю044E;
  public static final int bюююю044Eю044Eюю044E;
  private boolean b044E044E044E044E044Eю044Eюю044E = false;
  public long b044E044E044Eю044Eю044Eюю044E = b044E044Eю044Eюю044Eюю044E;
  public int b044E044E044Eюю044E044Eюю044E = b044Eююю044Eю044Eюю044E;
  public boolean b044E044Eю044E044Eю044Eюю044E = false;
  public int b044E044Eюю044Eю044Eюю044E = b044Eю044E044Eюю044Eюю044E;
  @Nullable
  public List<String> b044E044Eююю044E044Eюю044E = null;
  public int b044Eю044E044E044Eю044Eюю044E = 0;
  public int b044Eю044Eю044Eю044Eюю044E = 0;
  public boolean b044Eю044Eюю044E044Eюю044E = false;
  public boolean b044Eюю044E044Eю044Eюю044E = true;
  @Nullable
  public String b044Eюю044Eю044E044Eюю044E = null;
  private long b044Eюююю044E044Eюю044E = 133168638L;
  private boolean bю044E044E044E044Eю044Eюю044E = false;
  public boolean bю044E044Eю044Eю044Eюю044E = false;
  public String bю044E044Eюю044E044Eюю044E = gguuuu.bк043Aккк043Aкк043A043A("5zB4<BBA?E=\006G@POGW\016OGW", ';', 'í', '\001');
  public long bю044Eю044E044Eю044Eюю044E = bюю044E044Eюю044Eюю044E;
  public int bю044Eюю044Eю044Eюю044E = b044Eю044E044Eюю044Eюю044E;
  @Nullable
  public String bю044Eююю044E044Eюю044E = null;
  public boolean bюю044E044E044Eю044Eюю044E = false;
  public int bюю044Eю044Eю044Eюю044E = 1;
  @Nullable
  public Context bюю044Eюю044E044Eюю044E = null;
  public boolean bююю044E044Eю044Eюю044E = false;
  public int bююю044Eю044E044Eюю044E = bюююю044Eю044Eюю044E;
  public boolean bююююю044E044Eюю044E = false;
  
  /* Error */
  static
  {
    // Byte code:
    //   0: getstatic 57	kkkkkk/jttjjt:bю044Eю044Eю044E044Eюю044E	I
    //   3: invokestatic 61	kkkkkk/jttjjt:b043Dнн043D043D043D043D043D043D043D	()I
    //   6: iadd
    //   7: getstatic 57	kkkkkk/jttjjt:bю044Eю044Eю044E044Eюю044E	I
    //   10: imul
    //   11: getstatic 63	kkkkkk/jttjjt:bюю044E044Eю044E044Eюю044E	I
    //   14: irem
    //   15: getstatic 65	kkkkkk/jttjjt:b044E044Eю044Eю044E044Eюю044E	I
    //   18: if_icmpeq +14 -> 32
    //   21: invokestatic 68	kkkkkk/jttjjt:bн043Dн043D043D043D043D043D043D043D	()I
    //   24: putstatic 57	kkkkkk/jttjjt:bю044Eю044Eю044E044Eюю044E	I
    //   27: bipush 14
    //   29: putstatic 65	kkkkkk/jttjjt:b044E044Eю044Eю044E044Eюю044E	I
    //   32: ldc 2
    //   34: invokestatic 74	kkkkkk/fafffa:b043A043A043A043Aкк043Aкк043A	(Ljava/lang/Class;)Ljava/lang/String;
    //   37: astore_1
    //   38: aload_1
    //   39: putstatic 76	kkkkkk/jttjjt:b044E044E044E044Eюю044Eюю044E	Ljava/lang/String;
    //   42: getstatic 82	java/util/concurrent/TimeUnit:MINUTES	Ljava/util/concurrent/TimeUnit;
    //   45: ldc2_w 83
    //   48: invokevirtual 88	java/util/concurrent/TimeUnit:toMillis	(J)J
    //   51: l2i
    //   52: putstatic 90	kkkkkk/jttjjt:bю044E044E044Eюю044Eюю044E	I
    //   55: getstatic 82	java/util/concurrent/TimeUnit:MINUTES	Ljava/util/concurrent/TimeUnit;
    //   58: ldc2_w 91
    //   61: invokevirtual 88	java/util/concurrent/TimeUnit:toMillis	(J)J
    //   64: l2i
    //   65: putstatic 94	kkkkkk/jttjjt:bюююю044Eю044Eюю044E	I
    //   68: getstatic 97	java/util/concurrent/TimeUnit:SECONDS	Ljava/util/concurrent/TimeUnit;
    //   71: ldc2_w 83
    //   74: invokevirtual 88	java/util/concurrent/TimeUnit:toMillis	(J)J
    //   77: l2i
    //   78: putstatic 99	kkkkkk/jttjjt:b044Eююю044Eю044Eюю044E	I
    //   81: getstatic 97	java/util/concurrent/TimeUnit:SECONDS	Ljava/util/concurrent/TimeUnit;
    //   84: ldc2_w 83
    //   87: invokevirtual 88	java/util/concurrent/TimeUnit:toMillis	(J)J
    //   90: l2i
    //   91: putstatic 101	kkkkkk/jttjjt:b044Eю044E044Eюю044Eюю044E	I
    //   94: getstatic 82	java/util/concurrent/TimeUnit:MINUTES	Ljava/util/concurrent/TimeUnit;
    //   97: astore_1
    //   98: aload_1
    //   99: ldc2_w 102
    //   102: invokevirtual 88	java/util/concurrent/TimeUnit:toMillis	(J)J
    //   105: putstatic 105	kkkkkk/jttjjt:bюю044E044Eюю044Eюю044E	J
    //   108: invokestatic 68	kkkkkk/jttjjt:bн043Dн043D043D043D043D043D043D043D	()I
    //   111: istore_0
    //   112: iload_0
    //   113: invokestatic 61	kkkkkk/jttjjt:b043Dнн043D043D043D043D043D043D043D	()I
    //   116: iload_0
    //   117: iadd
    //   118: imul
    //   119: invokestatic 108	kkkkkk/jttjjt:b043D043Dн043D043D043D043D043D043D043D	()I
    //   122: irem
    //   123: tableswitch	default:+17->140, 0:+27->150
    //   140: bipush 20
    //   142: putstatic 57	kkkkkk/jttjjt:bю044Eю044Eю044E044Eюю044E	I
    //   145: bipush 6
    //   147: putstatic 65	kkkkkk/jttjjt:b044E044Eю044Eю044E044Eюю044E	I
    //   150: getstatic 82	java/util/concurrent/TimeUnit:MINUTES	Ljava/util/concurrent/TimeUnit;
    //   153: ldc2_w 109
    //   156: invokevirtual 88	java/util/concurrent/TimeUnit:toMillis	(J)J
    //   159: putstatic 112	kkkkkk/jttjjt:b044E044Eю044Eюю044Eюю044E	J
    //   162: return
    //   163: astore_1
    //   164: aload_1
    //   165: athrow
    //   166: astore_1
    //   167: aload_1
    //   168: athrow
    // Local variable table:
    //   start	length	slot	name	signature
    //   111	8	0	i	int
    //   37	62	1	localObject	Object
    //   163	2	1	localException1	Exception
    //   166	2	1	localException2	Exception
    // Exception table:
    //   from	to	target	type
    //   38	98	163	java/lang/Exception
    //   32	38	166	java/lang/Exception
    //   98	108	166	java/lang/Exception
    //   150	162	166	java/lang/Exception
  }
  
  public jttjjt() {}
  
  public static int b043D043Dн043D043D043D043D043D043D043D()
  {
    return 2;
  }
  
  public static int b043Dнн043D043D043D043D043D043D043D()
  {
    return 1;
  }
  
  public static int bн043Dн043D043D043D043D043D043D043D()
  {
    return 39;
  }
  
  public static int bнн043D043D043D043D043D043D043D043D()
  {
    return 0;
  }
  
  @Nonnull
  public jttjjt b043A043A043A043Aкккккк(int paramInt, @Nonnull TimeUnit paramTimeUnit)
  {
    this.b044E044Eюю044Eю044Eюю044E = ((int)paramTimeUnit.toMillis(paramInt));
    int i = this.b044E044Eюю044Eю044Eюю044E;
    if ((bю044Eю044Eю044E044Eюю044E + b044Eю044E044Eю044E044Eюю044E) * bю044Eю044Eю044E044Eюю044E % bюю044E044Eю044E044Eюю044E != bнн043D043D043D043D043D043D043D043D())
    {
      int j = bю044Eю044Eю044E044Eюю044E;
      switch (j * (b044Eю044E044Eю044E044Eюю044E + j) % bюю044E044Eю044E044Eюю044E)
      {
      default: 
        bю044Eю044Eю044E044Eюю044E = bн043Dн043D043D043D043D043D043D043D();
        b044E044Eю044Eю044E044Eюю044E = 42;
      }
      bю044Eю044Eю044E044Eюю044E = 2;
      b044E044Eю044Eю044E044Eюю044E = bн043Dн043D043D043D043D043D043D043D();
    }
    if ((i == 0) && (paramInt != 0)) {
      this.b044E044Eюю044Eю044Eюю044E = 1;
    }
    return this;
  }
  
  @Nonnull
  public jttjjt b043A043A043Aк043Aккккк(int paramInt, @Nonnull TimeUnit paramTimeUnit)
  {
    long l = paramInt;
    switch (1)
    {
    case 0: 
    default: 
      for (;;)
      {
        switch (0)
        {
        }
      }
    }
    if ((bю044Eю044Eю044E044Eюю044E + b044Eю044E044Eю044E044Eюю044E) * bю044Eю044Eю044E044Eюю044E % bюю044E044Eю044E044Eюю044E != b044E044Eю044Eю044E044Eюю044E)
    {
      bю044Eю044Eю044E044Eюю044E = bн043Dн043D043D043D043D043D043D043D();
      b044E044Eю044Eю044E044Eюю044E = bн043Dн043D043D043D043D043D043D043D();
    }
    this.b044E044E044Eюю044E044Eюю044E = ((int)paramTimeUnit.toMillis(l));
    if ((this.b044E044E044Eюю044E044Eюю044E == 0) && (paramInt != 0))
    {
      switch (1)
      {
      case 0: 
      default: 
        for (;;)
        {
          switch (1)
          {
          }
        }
      }
      paramInt = bю044Eю044Eю044E044Eюю044E;
      switch (paramInt * (b044Eю044E044Eю044E044Eюю044E + paramInt) % bюю044E044Eю044E044Eюю044E)
      {
      default: 
        bю044Eю044Eю044E044Eюю044E = 55;
        b044E044Eю044Eю044E044Eюю044E = 48;
      }
      this.b044E044E044Eюю044E044Eюю044E = 1;
    }
    return this;
  }
  
  @Nonnull
  public jttjjt b043A043A043Aккккккк(Context paramContext)
  {
    int i = bн043Dн043D043D043D043D043D043D043D();
    int j = b044Eю044E044Eю044E044Eюю044E;
    int k = bн043Dн043D043D043D043D043D043D043D();
    if ((bю044Eю044Eю044E044Eюю044E + b044Eю044E044Eю044E044Eюю044E) * bю044Eю044Eю044E044Eюю044E % bюю044E044Eю044E044Eюю044E != b044E044Eю044Eю044E044Eюю044E)
    {
      bю044Eю044Eю044E044Eюю044E = 34;
      b044E044Eю044Eю044E044Eюю044E = bн043Dн043D043D043D043D043D043D043D();
    }
    if ((i + j) * k % bюю044E044Eю044E044Eюю044E != b044E044Eю044Eю044E044Eюю044E)
    {
      bю044Eю044Eю044E044Eюю044E = 57;
      b044E044Eю044Eю044E044Eюю044E = bн043Dн043D043D043D043D043D043D043D();
    }
    this.bюю044Eюю044E044Eюю044E = paramContext;
    return this;
  }
  
  @Nonnull
  public jttjjt b043A043Aк043Aкккккк(boolean paramBoolean)
  {
    switch (1)
    {
    case 0: 
    default: 
      for (;;)
      {
        switch (1)
        {
        case 0: 
        default: 
          for (;;)
          {
            switch (1)
            {
            }
          }
        }
        switch (1)
        {
        }
      }
    }
    if ((bю044Eю044Eю044E044Eюю044E + b044Eю044E044Eю044E044Eюю044E) * bю044Eю044Eю044E044Eюю044E % bюю044E044Eю044E044Eюю044E != b044E044Eю044Eю044E044Eюю044E)
    {
      bю044Eю044Eю044E044Eюю044E = bн043Dн043D043D043D043D043D043D043D();
      b044E044Eю044Eю044E044Eюю044E = 48;
    }
    this.b044Eю044Eюю044E044Eюю044E = paramBoolean;
    if ((bю044Eю044Eю044E044Eюю044E + b044Eю044E044Eю044E044Eюю044E) * bю044Eю044Eю044E044Eюю044E % bюю044E044Eю044E044Eюю044E != b044E044Eю044Eю044E044Eюю044E)
    {
      bю044Eю044Eю044E044Eюю044E = 47;
      b044E044Eю044Eю044E044Eюю044E = 29;
    }
    return this;
  }
  
  @Nonnull
  public jttjjt b043A043Aкк043Aккккк(int paramInt, @Nonnull TimeUnit paramTimeUnit)
  {
    long l = paramInt;
    try
    {
      this.bю044Eюю044Eю044Eюю044E = ((int)paramTimeUnit.toMillis(l));
      int i = this.bю044Eюю044Eю044Eюю044E;
      if ((i == 0) && (paramInt != 0))
      {
        if ((bю044Eю044Eю044E044Eюю044E + b044Eю044E044Eю044E044Eюю044E) * bю044Eю044Eю044E044Eюю044E % b043D043Dн043D043D043D043D043D043D043D() != b044E044Eю044Eю044E044Eюю044E)
        {
          if ((bю044Eю044Eю044E044Eюю044E + b044Eю044E044Eю044E044Eюю044E) * bю044Eю044Eю044E044Eюю044E % bюю044E044Eю044E044Eюю044E != b044E044Eю044Eю044E044Eюю044E)
          {
            bю044Eю044Eю044E044Eюю044E = bн043Dн043D043D043D043D043D043D043D();
            b044E044Eю044Eю044E044Eюю044E = bн043Dн043D043D043D043D043D043D043D();
          }
          bю044Eю044Eю044E044Eюю044E = bн043Dн043D043D043D043D043D043D043D();
          b044E044Eю044Eю044E044Eюю044E = 89;
        }
        this.bю044Eюю044Eю044Eюю044E = 1;
      }
      return this;
    }
    catch (Exception paramTimeUnit)
    {
      throw paramTimeUnit;
    }
  }
  
  public final long b043A043Aкккккккк()
  {
    long l2 = this.b044Eюююю044E044Eюю044E;
    long l1 = l2;
    if (this.b044E044E044E044E044Eю044Eюю044E)
    {
      l2 &= 0xFFFFFFFFFFFFFFD9;
      int i = bю044Eю044Eю044E044Eюю044E;
      int j = b044Eю044E044Eю044E044Eюю044E;
      int k = bю044Eю044Eю044E044Eюю044E;
      switch (1)
      {
      case 0: 
      default: 
        for (;;)
        {
          switch (0)
          {
          }
        }
      }
      l1 = l2;
      if ((i + j) * k % bюю044E044Eю044E044Eюю044E != b044E044Eю044Eю044E044Eюю044E)
      {
        bю044Eю044Eю044E044Eюю044E = 25;
        b044E044Eю044Eю044E044Eюю044E = 15;
        l1 = l2;
      }
    }
    if ((bю044Eю044Eю044E044Eюю044E + b044Eю044E044Eю044E044Eюю044E) * bю044Eю044Eю044E044Eюю044E % bюю044E044Eю044E044Eюю044E != bнн043D043D043D043D043D043D043D043D())
    {
      bю044Eю044Eю044E044Eюю044E = bн043Dн043D043D043D043D043D043D043D();
      b044E044Eю044Eю044E044Eюю044E = bн043Dн043D043D043D043D043D043D043D();
    }
    l2 = l1;
    if (this.bю044E044E044E044Eю044Eюю044E) {
      l2 = l1 & 0xFFFFFFFFFFFFCFFF;
    }
    return l2;
  }
  
  /* Error */
  @Nonnull
  public jttjjt b043Aк043A043Aкккккк(String paramString)
  {
    // Byte code:
    //   0: getstatic 57	kkkkkk/jttjjt:bю044Eю044Eю044E044Eюю044E	I
    //   3: istore_2
    //   4: getstatic 180	kkkkkk/jttjjt:b044Eю044E044Eю044E044Eюю044E	I
    //   7: istore_3
    //   8: getstatic 57	kkkkkk/jttjjt:bю044Eю044Eю044E044Eюю044E	I
    //   11: istore 4
    //   13: getstatic 63	kkkkkk/jttjjt:bюю044E044Eю044E044Eюю044E	I
    //   16: istore 5
    //   18: getstatic 65	kkkkkk/jttjjt:b044E044Eю044Eю044E044Eюю044E	I
    //   21: istore 6
    //   23: iload_2
    //   24: iload_3
    //   25: iadd
    //   26: iload 4
    //   28: imul
    //   29: iload 5
    //   31: irem
    //   32: iload 6
    //   34: if_icmpeq +14 -> 48
    //   37: invokestatic 68	kkkkkk/jttjjt:bн043Dн043D043D043D043D043D043D043D	()I
    //   40: putstatic 57	kkkkkk/jttjjt:bю044Eю044Eю044E044Eюю044E	I
    //   43: bipush 34
    //   45: putstatic 65	kkkkkk/jttjjt:b044E044Eю044Eю044E044Eюю044E	I
    //   48: aload_0
    //   49: aload_1
    //   50: putfield 166	kkkkkk/jttjjt:bю044E044Eюю044E044Eюю044E	Ljava/lang/String;
    //   53: aload_0
    //   54: areturn
    //   55: astore_1
    //   56: aload_1
    //   57: athrow
    //   58: astore_1
    //   59: aload_1
    //   60: athrow
    // Local variable table:
    //   start	length	slot	name	signature
    //   0	61	0	this	jttjjt
    //   0	61	1	paramString	String
    //   3	23	2	i	int
    //   7	19	3	j	int
    //   11	18	4	k	int
    //   16	16	5	m	int
    //   21	14	6	n	int
    // Exception table:
    //   from	to	target	type
    //   0	23	55	java/lang/Exception
    //   48	53	55	java/lang/Exception
    //   37	48	58	java/lang/Exception
  }
  
  @Nonnull
  public jttjjt b043Aк043Aк043Aккккк(boolean paramBoolean)
  {
    int i = bн043Dн043D043D043D043D043D043D043D();
    switch (i * (b044Eю044E044Eю044E044Eюю044E + i) % bюю044E044Eю044E044Eюю044E)
    {
    default: 
      bю044Eю044Eю044E044Eюю044E = bн043Dн043D043D043D043D043D043D043D();
      b044E044Eю044Eю044E044Eюю044E = bн043Dн043D043D043D043D043D043D043D();
    }
    try
    {
      this.bююю044E044Eю044Eюю044E = paramBoolean;
      i = bю044Eю044Eю044E044Eюю044E;
      switch (i * (b043Dнн043D043D043D043D043D043D043D() + i) % bюю044E044Eю044E044Eюю044E)
      {
      default: 
        bю044Eю044Eю044E044Eюю044E = bн043Dн043D043D043D043D043D043D043D();
        b044E044Eю044Eю044E044Eюю044E = bн043Dн043D043D043D043D043D043D043D();
      }
      return this;
    }
    catch (Exception localException)
    {
      throw localException;
    }
  }
  
  @Nonnull
  public jttjjt b043Aк043Aккккккк(String paramString)
  {
    ArrayList localArrayList = new ArrayList();
    int i = bю044Eю044Eю044E044Eюю044E;
    switch (i * (b044Eю044E044Eю044E044Eюю044E + i) % bюю044E044Eю044E044Eюю044E)
    {
    default: 
      bю044Eю044Eю044E044Eюю044E = 8;
      b044E044Eю044Eю044E044Eюю044E = 88;
    }
    if ((bю044Eю044Eю044E044Eюю044E + b044Eю044E044Eю044E044Eюю044E) * bю044Eю044Eю044E044Eюю044E % bюю044E044Eю044E044Eюю044E != b044E044Eю044Eю044E044Eюю044E)
    {
      switch (1)
      {
      case 0: 
      default: 
        for (;;)
        {
          switch (0)
          {
          }
        }
      }
      bю044Eю044Eю044E044Eюю044E = bн043Dн043D043D043D043D043D043D043D();
      b044E044Eю044Eю044E044Eюю044E = bн043Dн043D043D043D043D043D043D043D();
    }
    localArrayList.add(paramString);
    switch (0)
    {
    case 1: 
    default: 
      for (;;)
      {
        switch (1)
        {
        }
      }
    }
    this.b044E044Eююю044E044Eюю044E = localArrayList;
    return this;
  }
  
  /* Error */
  @Nonnull
  public jttjjt b043Aкк043Aкккккк(boolean paramBoolean)
  {
    // Byte code:
    //   0: getstatic 57	kkkkkk/jttjjt:bю044Eю044Eю044E044Eюю044E	I
    //   3: getstatic 180	kkkkkk/jttjjt:b044Eю044E044Eю044E044Eюю044E	I
    //   6: iadd
    //   7: getstatic 57	kkkkkk/jttjjt:bю044Eю044Eю044E044Eюю044E	I
    //   10: imul
    //   11: invokestatic 108	kkkkkk/jttjjt:b043D043Dн043D043D043D043D043D043D043D	()I
    //   14: irem
    //   15: getstatic 65	kkkkkk/jttjjt:b044E044Eю044Eю044E044Eюю044E	I
    //   18: if_icmpeq +15 -> 33
    //   21: invokestatic 68	kkkkkk/jttjjt:bн043Dн043D043D043D043D043D043D043D	()I
    //   24: putstatic 57	kkkkkk/jttjjt:bю044Eю044Eю044E044Eюю044E	I
    //   27: invokestatic 68	kkkkkk/jttjjt:bн043Dн043D043D043D043D043D043D043D	()I
    //   30: putstatic 65	kkkkkk/jttjjt:b044E044Eю044Eю044E044Eюю044E	I
    //   33: getstatic 57	kkkkkk/jttjjt:bю044Eю044Eю044E044Eюю044E	I
    //   36: istore_2
    //   37: getstatic 180	kkkkkk/jttjjt:b044Eю044E044Eю044E044Eюю044E	I
    //   40: istore_3
    //   41: getstatic 63	kkkkkk/jttjjt:bюю044E044Eю044E044Eюю044E	I
    //   44: istore 4
    //   46: iload_2
    //   47: iload_3
    //   48: iload_2
    //   49: iadd
    //   50: imul
    //   51: iload 4
    //   53: irem
    //   54: tableswitch	default:+18->72, 0:+28->82
    //   72: bipush 54
    //   74: putstatic 57	kkkkkk/jttjjt:bю044Eю044Eю044E044Eюю044E	I
    //   77: bipush 71
    //   79: putstatic 65	kkkkkk/jttjjt:b044E044Eю044Eю044E044Eюю044E	I
    //   82: aload_0
    //   83: iload_1
    //   84: putfield 126	kkkkkk/jttjjt:bюю044E044E044Eю044Eюю044E	Z
    //   87: aload_0
    //   88: areturn
    //   89: astore 5
    //   91: aload 5
    //   93: athrow
    //   94: astore 5
    //   96: aload 5
    //   98: athrow
    //   99: astore 5
    //   101: aload 5
    //   103: athrow
    // Local variable table:
    //   start	length	slot	name	signature
    //   0	104	0	this	jttjjt
    //   0	104	1	paramBoolean	boolean
    //   36	15	2	i	int
    //   40	10	3	j	int
    //   44	10	4	k	int
    //   89	3	5	localException1	Exception
    //   94	3	5	localException2	Exception
    //   99	3	5	localException3	Exception
    // Exception table:
    //   from	to	target	type
    //   82	87	89	java/lang/Exception
    //   37	46	94	java/lang/Exception
    //   91	94	94	java/lang/Exception
    //   33	37	99	java/lang/Exception
    //   72	82	99	java/lang/Exception
  }
  
  @Nonnull
  public jttjjt b043Aккк043Aккккк(long paramLong, @Nonnull TimeUnit paramTimeUnit)
  {
    switch (0)
    {
    case 1: 
    default: 
      for (;;)
      {
        switch (0)
        {
        }
      }
    }
    int i = bю044Eю044Eю044E044Eюю044E;
    switch (i * (b044Eю044E044Eю044E044Eюю044E + i) % bюю044E044Eю044E044Eюю044E)
    {
    default: 
      bю044Eю044Eю044E044Eюю044E = bн043Dн043D043D043D043D043D043D043D();
      b044E044Eю044Eю044E044Eюю044E = 5;
    }
    try
    {
      this.bю044Eю044E044Eю044Eюю044E = paramTimeUnit.toMillis(paramLong);
      return this;
    }
    catch (Exception paramTimeUnit)
    {
      throw paramTimeUnit;
    }
  }
  
  @Nonnull
  public jttjjt b043Aккккккккк()
  {
    int i = bю044Eю044Eю044E044Eюю044E;
    switch (i * (b044Eю044E044Eю044E044Eюю044E + i) % bюю044E044Eю044E044Eюю044E)
    {
    default: 
      bю044Eю044Eю044E044Eюю044E = 21;
      b044E044Eю044Eю044E044Eюю044E = bн043Dн043D043D043D043D043D043D043D();
    }
    i = bн043Dн043D043D043D043D043D043D043D();
    switch (i * (b044Eю044E044Eю044E044Eюю044E + i) % bюю044E044Eю044E044Eюю044E)
    {
    default: 
      bю044Eю044Eю044E044Eюю044E = 46;
      b044E044Eю044Eю044E044Eюю044E = bн043Dн043D043D043D043D043D043D043D();
    }
    switch (1)
    {
    case 0: 
    default: 
      for (;;)
      {
        switch (0)
        {
        }
      }
    }
    this.bю044Eюю044Eю044Eюю044E = 0;
    return this;
  }
  
  @Nonnull
  public jttjjt b043Dн043D043D043D043D043D043D043D043D()
  {
    if ((bн043Dн043D043D043D043D043D043D043D() + b044Eю044E044Eю044E044Eюю044E) * bн043Dн043D043D043D043D043D043D043D() % bюю044E044Eю044E044Eюю044E != b044E044Eю044Eю044E044Eюю044E)
    {
      bю044Eю044Eю044E044Eюю044E = bн043Dн043D043D043D043D043D043D043D();
      b044E044Eю044Eю044E044Eюю044E = bн043Dн043D043D043D043D043D043D043D();
    }
    try
    {
      throw new NullPointerException();
    }
    catch (Exception localException)
    {
      bю044Eю044Eю044E044Eюю044E = 54;
      switch (0)
      {
      case 1: 
      default: 
        for (;;)
        {
          switch (0)
          {
          }
        }
      }
      switch (0)
      {
      case 1: 
      default: 
        for (;;)
        {
          switch (1)
          {
          }
        }
      }
      this.b044E044Eюю044Eю044Eюю044E = 0;
    }
    return this;
  }
  
  /* Error */
  @Nonnull
  public jttjjt bк043A043A043Aкккккк(long paramLong, @Nonnull TimeUnit paramTimeUnit)
  {
    // Byte code:
    //   0: aload_0
    //   1: aload_3
    //   2: lload_1
    //   3: invokevirtual 88	java/util/concurrent/TimeUnit:toMillis	(J)J
    //   6: putfield 144	kkkkkk/jttjjt:b044E044E044Eю044Eю044Eюю044E	J
    //   9: getstatic 57	kkkkkk/jttjjt:bю044Eю044Eю044E044Eюю044E	I
    //   12: istore 4
    //   14: getstatic 180	kkkkkk/jttjjt:b044Eю044E044Eю044E044Eюю044E	I
    //   17: istore 5
    //   19: getstatic 57	kkkkkk/jttjjt:bю044Eю044Eю044E044Eюю044E	I
    //   22: istore 6
    //   24: getstatic 63	kkkkkk/jttjjt:bюю044E044Eю044E044Eюю044E	I
    //   27: istore 7
    //   29: getstatic 65	kkkkkk/jttjjt:b044E044Eю044Eю044E044Eюю044E	I
    //   32: istore 8
    //   34: iload 4
    //   36: iload 5
    //   38: iadd
    //   39: iload 6
    //   41: imul
    //   42: iload 7
    //   44: irem
    //   45: iload 8
    //   47: if_icmpeq +14 -> 61
    //   50: invokestatic 68	kkkkkk/jttjjt:bн043Dн043D043D043D043D043D043D043D	()I
    //   53: putstatic 57	kkkkkk/jttjjt:bю044Eю044Eю044E044Eюю044E	I
    //   56: bipush 45
    //   58: putstatic 65	kkkkkk/jttjjt:b044E044Eю044Eю044E044Eюю044E	I
    //   61: aload_0
    //   62: areturn
    //   63: astore_3
    //   64: aload_3
    //   65: athrow
    //   66: astore_3
    //   67: aload_3
    //   68: athrow
    // Local variable table:
    //   start	length	slot	name	signature
    //   0	69	0	this	jttjjt
    //   0	69	1	paramLong	long
    //   0	69	3	paramTimeUnit	TimeUnit
    //   12	27	4	i	int
    //   17	22	5	j	int
    //   22	20	6	k	int
    //   27	18	7	m	int
    //   32	16	8	n	int
    // Exception table:
    //   from	to	target	type
    //   0	9	63	java/lang/Exception
    //   50	61	63	java/lang/Exception
    //   9	34	66	java/lang/Exception
  }
  
  @Nonnull
  public jttjjt bк043A043Aк043Aккккк(int paramInt, @Nonnull TimeUnit paramTimeUnit)
  {
    long l = paramTimeUnit.toMillis(paramInt);
    if ((bю044Eю044Eю044E044Eюю044E + b044Eю044E044Eю044E044Eюю044E) * bю044Eю044Eю044E044Eюю044E % bюю044E044Eю044E044Eюю044E != b044E044Eю044Eю044E044Eюю044E)
    {
      bю044Eю044Eю044E044Eюю044E = bн043Dн043D043D043D043D043D043D043D();
      b044E044Eю044Eю044E044Eюю044E = 38;
    }
    this.bююю044Eю044E044Eюю044E = ((int)l);
    if ((bю044Eю044Eю044E044Eюю044E + b044Eю044E044Eю044E044Eюю044E) * bю044Eю044Eю044E044Eюю044E % bюю044E044Eю044E044Eюю044E != b044E044Eю044Eю044E044Eюю044E)
    {
      bю044Eю044Eю044E044Eюю044E = 82;
      b044E044Eю044Eю044E044Eюю044E = 83;
    }
    return this;
  }
  
  @Nonnull
  public jttjjt bк043A043Aккккккк(List<String> paramList)
  {
    try
    {
      this.b044E044Eююю044E044Eюю044E = paramList;
      if ((bю044Eю044Eю044E044Eюю044E + b043Dнн043D043D043D043D043D043D043D()) * bю044Eю044Eю044E044Eюю044E % b043D043Dн043D043D043D043D043D043D043D() != b044E044Eю044Eю044E044Eюю044E)
      {
        bю044Eю044Eю044E044Eюю044E = 93;
        b044E044Eю044Eю044E044Eюю044E = 9;
      }
      int i = bю044Eю044Eю044E044Eюю044E;
      switch (i * (b044Eю044E044Eю044E044Eюю044E + i) % bюю044E044Eю044E044Eюю044E)
      {
      default: 
        bю044Eю044Eю044E044Eюю044E = bн043Dн043D043D043D043D043D043D043D();
        b044E044Eю044Eю044E044Eюю044E = bн043Dн043D043D043D043D043D043D043D();
      }
      return this;
    }
    catch (Exception paramList)
    {
      throw paramList;
    }
  }
  
  @Nonnull
  public jttjjt bк043Aк043Aкккккк(boolean paramBoolean)
  {
    switch (0)
    {
    case 1: 
    default: 
      for (;;)
      {
        if ((bю044Eю044Eю044E044Eюю044E + b044Eю044E044Eю044E044Eюю044E) * bю044Eю044Eю044E044Eюю044E % bюю044E044Eю044E044Eюю044E != b044E044Eю044Eю044E044Eюю044E)
        {
          bю044Eю044Eю044E044Eюю044E = 15;
          b044E044Eю044Eю044E044Eюю044E = 45;
        }
        switch (1)
        {
        }
      }
    }
    int i = bн043Dн043D043D043D043D043D043D043D();
    switch (i * (b044Eю044E044Eю044E044Eюю044E + i) % bюю044E044Eю044E044Eюю044E)
    {
    default: 
      bю044Eю044Eю044E044Eюю044E = bн043Dн043D043D043D043D043D043D043D();
      b044E044Eю044Eю044E044Eюю044E = 52;
    }
    this.b044E044Eю044E044Eю044Eюю044E = paramBoolean;
    return this;
  }
  
  @Nonnull
  public jttjjt bк043Aкк043Aккккк(String paramString)
  {
    if ((bю044Eю044Eю044E044Eюю044E + b044Eю044E044Eю044E044Eюю044E) * bю044Eю044Eю044E044Eюю044E % bюю044E044Eю044E044Eюю044E != b044E044Eю044Eю044E044Eюю044E)
    {
      bю044Eю044Eю044E044Eюю044E = bн043Dн043D043D043D043D043D043D043D();
      b044E044Eю044Eю044E044Eюю044E = bн043Dн043D043D043D043D043D043D043D();
    }
    this.bю044Eююю044E044Eюю044E = paramString;
    if ((bю044Eю044Eю044E044Eюю044E + b044Eю044E044Eю044E044Eюю044E) * bю044Eю044Eю044E044Eюю044E % bюю044E044Eю044E044Eюю044E != b044E044Eю044Eю044E044Eюю044E)
    {
      bю044Eю044Eю044E044Eюю044E = bн043Dн043D043D043D043D043D043D043D();
      b044E044Eю044Eю044E044Eюю044E = 73;
    }
    return this;
  }
  
  @Nonnull
  public jttjjt bк043Aкккккккк(long paramLong)
  {
    int i = bн043Dн043D043D043D043D043D043D043D();
    switch (i * (b044Eю044E044Eю044E044Eюю044E + i) % bюю044E044Eю044E044Eюю044E)
    {
    default: 
      bю044Eю044Eю044E044Eюю044E = 27;
      b044E044Eю044Eю044E044Eюю044E = bн043Dн043D043D043D043D043D043D043D();
    }
    long l = this.b044Eюююю044E044Eюю044E;
    switch (0)
    {
    case 1: 
    default: 
      for (;;)
      {
        switch (0)
        {
        }
      }
    }
    switch (1)
    {
    case 0: 
    default: 
      for (;;)
      {
        switch (1)
        {
        }
      }
    }
    i = bю044Eю044Eю044E044Eюю044E;
    switch (i * (b044Eю044E044Eю044E044Eюю044E + i) % bюю044E044Eю044E044Eюю044E)
    {
    default: 
      bю044Eю044Eю044E044Eюю044E = 76;
      b044E044Eю044Eю044E044Eюю044E = bн043Dн043D043D043D043D043D043D043D();
    }
    this.b044Eюююю044E044Eюю044E = (l | paramLong);
    return this;
  }
  
  /* Error */
  @Nonnull
  public jttjjt bкк043A043Aкккккк(boolean paramBoolean)
  {
    // Byte code:
    //   0: getstatic 57	kkkkkk/jttjjt:bю044Eю044Eю044E044Eюю044E	I
    //   3: istore_2
    //   4: invokestatic 61	kkkkkk/jttjjt:b043Dнн043D043D043D043D043D043D043D	()I
    //   7: istore_3
    //   8: getstatic 57	kkkkkk/jttjjt:bю044Eю044Eю044E044Eюю044E	I
    //   11: istore 4
    //   13: getstatic 63	kkkkkk/jttjjt:bюю044E044Eю044E044Eюю044E	I
    //   16: istore 5
    //   18: getstatic 65	kkkkkk/jttjjt:b044E044Eю044Eю044E044Eюю044E	I
    //   21: istore 6
    //   23: iload_2
    //   24: iload_3
    //   25: iadd
    //   26: iload 4
    //   28: imul
    //   29: iload 5
    //   31: irem
    //   32: iload 6
    //   34: if_icmpeq +15 -> 49
    //   37: invokestatic 68	kkkkkk/jttjjt:bн043Dн043D043D043D043D043D043D043D	()I
    //   40: putstatic 57	kkkkkk/jttjjt:bю044Eю044Eю044E044Eюю044E	I
    //   43: invokestatic 68	kkkkkk/jttjjt:bн043Dн043D043D043D043D043D043D043D	()I
    //   46: putstatic 65	kkkkkk/jttjjt:b044E044Eю044Eю044E044Eюю044E	I
    //   49: aload_0
    //   50: iload_1
    //   51: putfield 150	kkkkkk/jttjjt:b044E044E044E044E044Eю044Eюю044E	Z
    //   54: getstatic 57	kkkkkk/jttjjt:bю044Eю044Eю044E044Eюю044E	I
    //   57: getstatic 180	kkkkkk/jttjjt:b044Eю044E044Eю044E044Eюю044E	I
    //   60: iadd
    //   61: getstatic 57	kkkkkk/jttjjt:bю044Eю044Eю044E044Eюю044E	I
    //   64: imul
    //   65: getstatic 63	kkkkkk/jttjjt:bюю044E044Eю044E044Eюю044E	I
    //   68: irem
    //   69: getstatic 65	kkkkkk/jttjjt:b044E044Eю044Eю044E044Eюю044E	I
    //   72: if_icmpeq +14 -> 86
    //   75: bipush 14
    //   77: putstatic 57	kkkkkk/jttjjt:bю044Eю044Eю044E044Eюю044E	I
    //   80: invokestatic 68	kkkkkk/jttjjt:bн043Dн043D043D043D043D043D043D043D	()I
    //   83: putstatic 65	kkkkkk/jttjjt:b044E044Eю044Eю044E044Eюю044E	I
    //   86: iconst_0
    //   87: tableswitch	default:+21->108, 0:+48->135, 1:+-33->54
    //   108: iconst_0
    //   109: tableswitch	default:+23->132, 0:+26->135, 1:+-55->54
    //   132: goto -24 -> 108
    //   135: aload_0
    //   136: areturn
    //   137: astore 7
    //   139: aload 7
    //   141: athrow
    //   142: astore 7
    //   144: aload 7
    //   146: athrow
    // Local variable table:
    //   start	length	slot	name	signature
    //   0	147	0	this	jttjjt
    //   0	147	1	paramBoolean	boolean
    //   3	23	2	i	int
    //   7	19	3	j	int
    //   11	18	4	k	int
    //   16	16	5	m	int
    //   21	14	6	n	int
    //   137	3	7	localException1	Exception
    //   142	3	7	localException2	Exception
    // Exception table:
    //   from	to	target	type
    //   0	23	137	java/lang/Exception
    //   49	54	137	java/lang/Exception
    //   37	49	142	java/lang/Exception
  }
  
  /* Error */
  @Nonnull
  public jttjjt bкк043Aк043Aккккк(boolean paramBoolean)
  {
    // Byte code:
    //   0: iconst_0
    //   1: istore_2
    //   2: iconst_2
    //   3: istore_3
    //   4: aload_0
    //   5: iload_1
    //   6: putfield 146	kkkkkk/jttjjt:bю044E044Eю044Eю044Eюю044E	Z
    //   9: iload_2
    //   10: iconst_0
    //   11: idiv
    //   12: istore 4
    //   14: iload 4
    //   16: istore_2
    //   17: goto -8 -> 9
    //   20: astore 5
    //   22: aload 5
    //   24: athrow
    //   25: astore 5
    //   27: aload 5
    //   29: athrow
    //   30: astore 5
    //   32: invokestatic 68	kkkkkk/jttjjt:bн043Dн043D043D043D043D043D043D043D	()I
    //   35: putstatic 57	kkkkkk/jttjjt:bю044Eю044Eю044E044Eюю044E	I
    //   38: iload_2
    //   39: iconst_0
    //   40: idiv
    //   41: istore_2
    //   42: goto -4 -> 38
    //   45: astore 5
    //   47: invokestatic 68	kkkkkk/jttjjt:bн043Dн043D043D043D043D043D043D043D	()I
    //   50: putstatic 57	kkkkkk/jttjjt:bю044Eю044Eю044E044Eюю044E	I
    //   53: iload_3
    //   54: istore_2
    //   55: iload_2
    //   56: iconst_0
    //   57: idiv
    //   58: istore_2
    //   59: goto -4 -> 55
    //   62: astore 5
    //   64: aload 5
    //   66: athrow
    //   67: astore 5
    //   69: invokestatic 68	kkkkkk/jttjjt:bн043Dн043D043D043D043D043D043D043D	()I
    //   72: putstatic 57	kkkkkk/jttjjt:bю044Eю044Eю044E044Eюю044E	I
    //   75: new 215	java/lang/NullPointerException
    //   78: dup
    //   79: invokespecial 216	java/lang/NullPointerException:<init>	()V
    //   82: athrow
    //   83: astore 5
    //   85: bipush 80
    //   87: putstatic 57	kkkkkk/jttjjt:bю044Eю044Eю044E044Eюю044E	I
    //   90: aload_0
    //   91: areturn
    // Local variable table:
    //   start	length	slot	name	signature
    //   0	92	0	this	jttjjt
    //   0	92	1	paramBoolean	boolean
    //   1	58	2	i	int
    //   3	51	3	j	int
    //   12	3	4	k	int
    //   20	3	5	localException1	Exception
    //   25	3	5	localException2	Exception
    //   30	1	5	localException3	Exception
    //   45	1	5	localException4	Exception
    //   62	3	5	localException5	Exception
    //   67	1	5	localException6	Exception
    //   83	1	5	localException7	Exception
    // Exception table:
    //   from	to	target	type
    //   4	9	20	java/lang/Exception
    //   22	25	25	java/lang/Exception
    //   32	38	25	java/lang/Exception
    //   9	14	30	java/lang/Exception
    //   38	42	45	java/lang/Exception
    //   47	53	62	java/lang/Exception
    //   55	59	67	java/lang/Exception
    //   75	83	83	java/lang/Exception
  }
  
  @Nonnull
  public jttjjt bкк043Aккккккк(String paramString)
  {
    this.b044Eюю044Eю044E044Eюю044E = paramString;
    if ((bю044Eю044Eю044E044Eюю044E + b044Eю044E044Eю044E044Eюю044E) * bю044Eю044Eю044E044Eюю044E % bюю044E044Eю044E044Eюю044E != b044E044Eю044Eю044E044Eюю044E)
    {
      bю044Eю044Eю044E044Eюю044E = 89;
      int i = bн043Dн043D043D043D043D043D043D043D();
      if ((bю044Eю044Eю044E044Eюю044E + b043Dнн043D043D043D043D043D043D043D()) * bю044Eю044Eю044E044Eюю044E % bюю044E044Eю044E044Eюю044E != b044E044Eю044Eю044E044Eюю044E)
      {
        bю044Eю044Eю044E044Eюю044E = bн043Dн043D043D043D043D043D043D043D();
        b044E044Eю044Eю044E044Eюю044E = 20;
      }
      b044E044Eю044Eю044E044Eюю044E = i;
    }
    return this;
  }
  
  /* Error */
  @Nonnull
  public jttjjt bккк043A043Aккккк(boolean paramBoolean)
  {
    // Byte code:
    //   0: getstatic 57	kkkkkk/jttjjt:bю044Eю044Eю044E044Eюю044E	I
    //   3: istore_2
    //   4: invokestatic 61	kkkkkk/jttjjt:b043Dнн043D043D043D043D043D043D043D	()I
    //   7: istore_3
    //   8: getstatic 57	kkkkkk/jttjjt:bю044Eю044Eю044E044Eюю044E	I
    //   11: istore 4
    //   13: getstatic 63	kkkkkk/jttjjt:bюю044E044Eю044E044Eюю044E	I
    //   16: istore 5
    //   18: invokestatic 182	kkkkkk/jttjjt:bнн043D043D043D043D043D043D043D043D	()I
    //   21: istore 6
    //   23: iload_2
    //   24: iload_3
    //   25: iadd
    //   26: iload 4
    //   28: imul
    //   29: iload 5
    //   31: irem
    //   32: iload 6
    //   34: if_icmpeq +13 -> 47
    //   37: bipush 78
    //   39: putstatic 57	kkkkkk/jttjjt:bю044Eю044Eю044E044Eюю044E	I
    //   42: bipush 29
    //   44: putstatic 65	kkkkkk/jttjjt:b044E044Eю044Eю044E044Eюю044E	I
    //   47: aload_0
    //   48: iload_1
    //   49: putfield 174	kkkkkk/jttjjt:bююююю044E044Eюю044E	Z
    //   52: getstatic 57	kkkkkk/jttjjt:bю044Eю044Eю044E044Eюю044E	I
    //   55: istore_2
    //   56: iload_2
    //   57: getstatic 180	kkkkkk/jttjjt:b044Eю044E044Eю044E044Eюю044E	I
    //   60: iload_2
    //   61: iadd
    //   62: imul
    //   63: getstatic 63	kkkkkk/jttjjt:bюю044E044Eю044E044Eюю044E	I
    //   66: irem
    //   67: tableswitch	default:+17->84, 0:+29->96
    //   84: invokestatic 68	kkkkkk/jttjjt:bн043Dн043D043D043D043D043D043D043D	()I
    //   87: putstatic 57	kkkkkk/jttjjt:bю044Eю044Eю044E044Eюю044E	I
    //   90: invokestatic 68	kkkkkk/jttjjt:bн043Dн043D043D043D043D043D043D043D	()I
    //   93: putstatic 65	kkkkkk/jttjjt:b044E044Eю044Eю044E044Eюю044E	I
    //   96: iconst_1
    //   97: tableswitch	default:+23->120, 0:+-1->96, 1:+50->147
    //   120: iconst_0
    //   121: tableswitch	default:+23->144, 0:+26->147, 1:+-25->96
    //   144: goto -24 -> 120
    //   147: aload_0
    //   148: areturn
    //   149: astore 7
    //   151: aload 7
    //   153: athrow
    //   154: astore 7
    //   156: aload 7
    //   158: athrow
    // Local variable table:
    //   start	length	slot	name	signature
    //   0	159	0	this	jttjjt
    //   0	159	1	paramBoolean	boolean
    //   3	60	2	i	int
    //   7	19	3	j	int
    //   11	18	4	k	int
    //   16	16	5	m	int
    //   21	14	6	n	int
    //   149	3	7	localException1	Exception
    //   154	3	7	localException2	Exception
    // Exception table:
    //   from	to	target	type
    //   0	23	149	java/lang/Exception
    //   47	52	149	java/lang/Exception
    //   37	47	154	java/lang/Exception
  }
  
  @Nonnull
  public jttjjt bккк043Aкккккк(boolean paramBoolean)
  {
    this.bю044E044E044E044Eю044Eюю044E = paramBoolean;
    return this;
  }
  
  @Nonnull
  public jttjjt bкккк043Aккккк(int paramInt)
  {
    if ((bю044Eю044Eю044E044Eюю044E + b044Eю044E044Eю044E044Eюю044E) * bю044Eю044Eю044E044Eюю044E % bюю044E044Eю044E044Eюю044E != b044E044Eю044Eю044E044Eюю044E)
    {
      bю044Eю044Eю044E044Eюю044E = bн043Dн043D043D043D043D043D043D043D();
      b044E044Eю044Eю044E044Eюю044E = bн043Dн043D043D043D043D043D043D043D();
    }
    if ((bн043Dн043D043D043D043D043D043D043D() + b044Eю044E044Eю044E044Eюю044E) * bн043Dн043D043D043D043D043D043D043D() % bюю044E044Eю044E044Eюю044E != b044E044Eю044Eю044E044Eюю044E)
    {
      bю044Eю044Eю044E044Eюю044E = 56;
      b044E044Eю044Eю044E044Eюю044E = bн043Dн043D043D043D043D043D043D043D();
      switch (1)
      {
      case 0: 
      default: 
        for (;;)
        {
          switch (0)
          {
          }
        }
      }
    }
    this.bюю044Eю044Eю044Eюю044E = paramInt;
    switch (0)
    {
    case 1: 
    default: 
      for (;;)
      {
        switch (1)
        {
        }
      }
    }
    return this;
  }
  
  /* Error */
  @Nonnull
  public jttjjt bн043D043D043D043D043D043D043D043D043D(long paramLong)
  {
    // Byte code:
    //   0: aload_0
    //   1: getfield 140	kkkkkk/jttjjt:b044Eюююю044E044Eюю044E	J
    //   4: lstore 8
    //   6: getstatic 57	kkkkkk/jttjjt:bю044Eю044Eю044E044Eюю044E	I
    //   9: istore_3
    //   10: getstatic 180	kkkkkk/jttjjt:b044Eю044E044Eю044E044Eюю044E	I
    //   13: istore 4
    //   15: getstatic 57	kkkkkk/jttjjt:bю044Eю044Eю044E044Eюю044E	I
    //   18: istore 5
    //   20: getstatic 63	kkkkkk/jttjjt:bюю044E044Eю044E044Eюю044E	I
    //   23: istore 6
    //   25: getstatic 65	kkkkkk/jttjjt:b044E044Eю044Eю044E044Eюю044E	I
    //   28: istore 7
    //   30: iload_3
    //   31: iload 4
    //   33: iadd
    //   34: iload 5
    //   36: imul
    //   37: iload 6
    //   39: irem
    //   40: iload 7
    //   42: if_icmpeq +15 -> 57
    //   45: invokestatic 68	kkkkkk/jttjjt:bн043Dн043D043D043D043D043D043D043D	()I
    //   48: putstatic 57	kkkkkk/jttjjt:bю044Eю044Eю044E044Eюю044E	I
    //   51: invokestatic 68	kkkkkk/jttjjt:bн043Dн043D043D043D043D043D043D043D	()I
    //   54: putstatic 65	kkkkkk/jttjjt:b044E044Eю044Eю044E044Eюю044E	I
    //   57: aload_0
    //   58: lload 8
    //   60: ldc2_w 235
    //   63: lload_1
    //   64: lxor
    //   65: land
    //   66: putfield 140	kkkkkk/jttjjt:b044Eюююю044E044Eюю044E	J
    //   69: aload_0
    //   70: areturn
    //   71: astore 10
    //   73: aload 10
    //   75: athrow
    //   76: astore 10
    //   78: aload 10
    //   80: athrow
    // Local variable table:
    //   start	length	slot	name	signature
    //   0	81	0	this	jttjjt
    //   0	81	1	paramLong	long
    //   9	25	3	i	int
    //   13	21	4	j	int
    //   18	19	5	k	int
    //   23	17	6	m	int
    //   28	15	7	n	int
    //   4	55	8	l	long
    //   71	3	10	localException1	Exception
    //   76	3	10	localException2	Exception
    // Exception table:
    //   from	to	target	type
    //   0	30	71	java/lang/Exception
    //   57	69	71	java/lang/Exception
    //   45	57	76	java/lang/Exception
  }
}
