package kkkkkk;

import javax.inject.Inject;

public class kkjkjj
{
  public static int b042E042E042EЮ042EЮ042EЮ042EЮ = 1;
  private static final String b042E042EЮЮ042EЮ042EЮ042EЮ = "Wnus\"Dghu|v}}";
  private static final String b042EЮ042EЮ042EЮ042EЮ042EЮ = "\022)0.\\~\"#07188";
  public static int b042EЮЮ042E042EЮ042EЮ042EЮ = 46;
  public static int bЮ042EЮ042E042EЮ042EЮ042EЮ = 2;
  private static final String bЮЮ042EЮ042EЮ042EЮ042EЮ = "sZEH";
  public static int bЮЮЮ042E042EЮ042EЮ042EЮ = 97;
  private final nuuuuu bЮ042E042EЮ042EЮ042EЮ042EЮ;
  
  /* Error */
  static
  {
    // Byte code:
    //   0: getstatic 31	kkkkkk/kkjkjj:b042E042EЮЮ042EЮ042EЮ042EЮ	Ljava/lang/String;
    //   3: sipush 253
    //   6: iconst_4
    //   7: invokestatic 37	kkkkkk/gguuuu:bккккк043Aкк043A043A	(Ljava/lang/String;CC)Ljava/lang/String;
    //   10: astore 5
    //   12: getstatic 39	kkkkkk/kkjkjj:bЮЮЮ042E042EЮ042EЮ042EЮ	I
    //   15: getstatic 41	kkkkkk/kkjkjj:b042E042E042EЮ042EЮ042EЮ042EЮ	I
    //   18: iadd
    //   19: getstatic 39	kkkkkk/kkjkjj:bЮЮЮ042E042EЮ042EЮ042EЮ	I
    //   22: imul
    //   23: getstatic 43	kkkkkk/kkjkjj:bЮ042EЮ042E042EЮ042EЮ042EЮ	I
    //   26: irem
    //   27: getstatic 45	kkkkkk/kkjkjj:b042EЮЮ042E042EЮ042EЮ042EЮ	I
    //   30: if_icmpeq +14 -> 44
    //   33: invokestatic 49	kkkkkk/kkjkjj:bАА0410АА0410А0410А0410	()I
    //   36: putstatic 39	kkkkkk/kkjkjj:bЮЮЮ042E042EЮ042EЮ042EЮ	I
    //   39: bipush 46
    //   41: putstatic 45	kkkkkk/kkjkjj:b042EЮЮ042E042EЮ042EЮ042EЮ	I
    //   44: getstatic 39	kkkkkk/kkjkjj:bЮЮЮ042E042EЮ042EЮ042EЮ	I
    //   47: istore_0
    //   48: getstatic 41	kkkkkk/kkjkjj:b042E042E042EЮ042EЮ042EЮ042EЮ	I
    //   51: istore_1
    //   52: getstatic 39	kkkkkk/kkjkjj:bЮЮЮ042E042EЮ042EЮ042EЮ	I
    //   55: istore_2
    //   56: getstatic 43	kkkkkk/kkjkjj:bЮ042EЮ042E042EЮ042EЮ042EЮ	I
    //   59: istore_3
    //   60: getstatic 45	kkkkkk/kkjkjj:b042EЮЮ042E042EЮ042EЮ042EЮ	I
    //   63: istore 4
    //   65: iload_0
    //   66: iload_1
    //   67: iadd
    //   68: iload_2
    //   69: imul
    //   70: iload_3
    //   71: irem
    //   72: iload 4
    //   74: if_icmpeq +14 -> 88
    //   77: invokestatic 49	kkkkkk/kkjkjj:bАА0410АА0410А0410А0410	()I
    //   80: putstatic 39	kkkkkk/kkjkjj:bЮЮЮ042E042EЮ042EЮ042EЮ	I
    //   83: bipush 34
    //   85: putstatic 45	kkkkkk/kkjkjj:b042EЮЮ042E042EЮ042EЮ042EЮ	I
    //   88: aload 5
    //   90: putstatic 31	kkkkkk/kkjkjj:b042E042EЮЮ042EЮ042EЮ042EЮ	Ljava/lang/String;
    //   93: getstatic 51	kkkkkk/kkjkjj:bЮЮ042EЮ042EЮ042EЮ042EЮ	Ljava/lang/String;
    //   96: astore 5
    //   98: aload 5
    //   100: sipush 228
    //   103: iconst_5
    //   104: invokestatic 37	kkkkkk/gguuuu:bккккк043Aкк043A043A	(Ljava/lang/String;CC)Ljava/lang/String;
    //   107: putstatic 51	kkkkkk/kkjkjj:bЮЮ042EЮ042EЮ042EЮ042EЮ	Ljava/lang/String;
    //   110: getstatic 53	kkkkkk/kkjkjj:b042EЮ042EЮ042EЮ042EЮ042EЮ	Ljava/lang/String;
    //   113: astore 5
    //   115: aload 5
    //   117: sipush 170
    //   120: sipush 140
    //   123: iconst_3
    //   124: invokestatic 57	kkkkkk/gguuuu:bк043Aккк043Aкк043A043A	(Ljava/lang/String;CCC)Ljava/lang/String;
    //   127: putstatic 53	kkkkkk/kkjkjj:b042EЮ042EЮ042EЮ042EЮ042EЮ	Ljava/lang/String;
    //   130: return
    //   131: astore 5
    //   133: aload 5
    //   135: athrow
    //   136: astore 5
    //   138: aload 5
    //   140: athrow
    //   141: astore 5
    //   143: aload 5
    //   145: athrow
    //   146: astore 5
    //   148: aload 5
    //   150: athrow
    // Local variable table:
    //   start	length	slot	name	signature
    //   47	21	0	i	int
    //   51	17	1	j	int
    //   55	15	2	k	int
    //   59	13	3	m	int
    //   63	12	4	n	int
    //   10	106	5	str	String
    //   131	3	5	localException1	Exception
    //   136	3	5	localException2	Exception
    //   141	3	5	localException3	Exception
    //   146	3	5	localException4	Exception
    // Exception table:
    //   from	to	target	type
    //   0	12	131	java/lang/Exception
    //   88	98	131	java/lang/Exception
    //   110	115	131	java/lang/Exception
    //   60	65	136	java/lang/Exception
    //   83	88	136	java/lang/Exception
    //   133	136	136	java/lang/Exception
    //   143	146	136	java/lang/Exception
    //   98	110	141	java/lang/Exception
    //   115	130	141	java/lang/Exception
    //   44	60	146	java/lang/Exception
    //   77	83	146	java/lang/Exception
  }
  
  @Inject
  public kkjkjj(nuuuuu paramNuuuuu)
  {
    this.bЮ042E042EЮ042EЮ042EЮ042EЮ = paramNuuuuu;
  }
  
  public static int b04100410ААА0410А0410А0410()
  {
    return 2;
  }
  
  public static int bАА0410АА0410А0410А0410()
  {
    return 43;
  }
  
  /* Error */
  @ooiiio
  public void b0410А0410АА0410А0410А0410()
  {
    // Byte code:
    //   0: aload_0
    //   1: getfield 65	kkkkkk/kkjkjj:bЮ042E042EЮ042EЮ042EЮ042EЮ	Lkkkkkk/nuuuuu;
    //   4: astore_2
    //   5: getstatic 75	kkkkkk/uunnuu:SERVICE	Lkkkkkk/uunnuu;
    //   8: astore_3
    //   9: getstatic 81	kkkkkk/nunnuu:YOUR_ACCOUNTS	Lkkkkkk/nunnuu;
    //   12: astore 4
    //   14: getstatic 86	kkkkkk/nnnuuu$ununuu:YOUR_ACCOUNTS	Lkkkkkk/nnnuuu$ununuu;
    //   17: astore 5
    //   19: getstatic 92	kkkkkk/nuuunu:N3_20	Lkkkkkk/nuuunu;
    //   22: astore 6
    //   24: getstatic 98	kkkkkk/nnnuuu$nnunuu:ONE	Lkkkkkk/nnnuuu$nnunuu;
    //   27: astore 7
    //   29: ldc 100
    //   31: sipush 249
    //   34: bipush 48
    //   36: iconst_3
    //   37: invokestatic 57	kkkkkk/gguuuu:bк043Aккк043Aкк043A043A	(Ljava/lang/String;CCC)Ljava/lang/String;
    //   40: astore 8
    //   42: getstatic 106	kkkkkk/unuunu:SCREEN_ID	Lkkkkkk/unuunu;
    //   45: astore 9
    //   47: getstatic 39	kkkkkk/kkjkjj:bЮЮЮ042E042EЮ042EЮ042EЮ	I
    //   50: getstatic 41	kkkkkk/kkjkjj:b042E042E042EЮ042EЮ042EЮ042EЮ	I
    //   53: iadd
    //   54: getstatic 39	kkkkkk/kkjkjj:bЮЮЮ042E042EЮ042EЮ042EЮ	I
    //   57: imul
    //   58: getstatic 43	kkkkkk/kkjkjj:bЮ042EЮ042E042EЮ042EЮ042EЮ	I
    //   61: irem
    //   62: getstatic 45	kkkkkk/kkjkjj:b042EЮЮ042E042EЮ042EЮ042EЮ	I
    //   65: if_icmpeq +14 -> 79
    //   68: invokestatic 49	kkkkkk/kkjkjj:bАА0410АА0410А0410А0410	()I
    //   71: putstatic 39	kkkkkk/kkjkjj:bЮЮЮ042E042EЮ042EЮ042EЮ	I
    //   74: bipush 42
    //   76: putstatic 45	kkkkkk/kkjkjj:b042EЮЮ042E042EЮ042EЮ042EЮ	I
    //   79: aload 9
    //   81: ldc 108
    //   83: bipush 88
    //   85: sipush 189
    //   88: iconst_2
    //   89: invokestatic 57	kkkkkk/gguuuu:bк043Aккк043Aкк043A043A	(Ljava/lang/String;CCC)Ljava/lang/String;
    //   92: invokestatic 114	kkkkkk/nuuuuu$unuuuu:b043F043F043Fп043F043Fпп043Fп	(Lkkkkkk/unuunu;Ljava/lang/String;)Lkkkkkk/nuuuuu$unuuuu;
    //   95: astore 9
    //   97: getstatic 117	kkkkkk/unuunu:SCREEN_NAME	Lkkkkkk/unuunu;
    //   100: astore 10
    //   102: invokestatic 49	kkkkkk/kkjkjj:bАА0410АА0410А0410А0410	()I
    //   105: istore_1
    //   106: iload_1
    //   107: getstatic 41	kkkkkk/kkjkjj:b042E042E042EЮ042EЮ042EЮ042EЮ	I
    //   110: iload_1
    //   111: iadd
    //   112: imul
    //   113: invokestatic 119	kkkkkk/kkjkjj:b04100410ААА0410А0410А0410	()I
    //   116: irem
    //   117: tableswitch	default:+75->192, 0:+24->141
    //   136: bipush 81
    //   138: putstatic 41	kkkkkk/kkjkjj:b042E042E042EЮ042EЮ042EЮ042EЮ	I
    //   141: aload_2
    //   142: aload_3
    //   143: aload 4
    //   145: aload 5
    //   147: aload 6
    //   149: aload 7
    //   151: aload 8
    //   153: iconst_2
    //   154: anewarray 110	kkkkkk/nuuuuu$unuuuu
    //   157: dup
    //   158: iconst_0
    //   159: aload 9
    //   161: aastore
    //   162: dup
    //   163: iconst_1
    //   164: aload 10
    //   166: ldc 121
    //   168: iconst_5
    //   169: bipush 31
    //   171: iconst_1
    //   172: invokestatic 57	kkkkkk/gguuuu:bк043Aккк043Aкк043A043A	(Ljava/lang/String;CCC)Ljava/lang/String;
    //   175: invokestatic 114	kkkkkk/nuuuuu$unuuuu:b043F043F043Fп043F043Fпп043Fп	(Lkkkkkk/unuunu;Ljava/lang/String;)Lkkkkkk/nuuuuu$unuuuu;
    //   178: aastore
    //   179: invokevirtual 127	kkkkkk/nuuuuu:b043Fп043Fппп043Fп043Fп	(Lkkkkkk/uunnuu;Lkkkkkk/nunnuu;Lkkkkkk/nnnuuu$ununuu;Lkkkkkk/nuuunu;Lkkkkkk/nnnuuu$nnunuu;Ljava/lang/String;[Lkkkkkk/nuuuuu$unuuuu;)V
    //   182: return
    //   183: astore_2
    //   184: aload_2
    //   185: athrow
    //   186: astore_2
    //   187: aload_2
    //   188: athrow
    //   189: astore_2
    //   190: aload_2
    //   191: athrow
    //   192: goto -56 -> 136
    // Local variable table:
    //   start	length	slot	name	signature
    //   0	195	0	this	kkjkjj
    //   105	8	1	i	int
    //   4	138	2	localNuuuuu	nuuuuu
    //   183	2	2	localException1	Exception
    //   186	2	2	localException2	Exception
    //   189	2	2	localException3	Exception
    //   8	135	3	localUunnuu	uunnuu
    //   12	132	4	localNunnuu	nunnuu
    //   17	129	5	localUnunuu	nnnuuu.ununuu
    //   22	126	6	localNuuunu	nuuunu
    //   27	123	7	localNnunuu	nnnuuu.nnunuu
    //   40	112	8	str	String
    //   45	115	9	localObject	Object
    //   100	65	10	localUnuunu	unuunu
    // Exception table:
    //   from	to	target	type
    //   0	42	183	java/lang/Exception
    //   79	102	183	java/lang/Exception
    //   102	136	186	java/lang/Exception
    //   136	141	186	java/lang/Exception
    //   184	186	186	java/lang/Exception
    //   190	192	186	java/lang/Exception
    //   42	47	189	java/lang/Exception
    //   141	182	189	java/lang/Exception
  }
}
