package kkkkkk;

import javax.inject.Inject;

public class kkkjjj
{
  private static final String b042E042E042E042E042E042EЮЮ042EЮ = "t\035\034\025P\"\024\033\032";
  public static int b042E042EЮЮЮЮ042EЮ042EЮ = 2;
  public static int b042EЮЮЮЮЮ042EЮ042EЮ = 89;
  private static final String bЮ042E042E042E042E042EЮЮ042EЮ = "Ltsl(Ykrq";
  public static int bЮ042EЮЮЮЮ042EЮ042EЮ = 1;
  public static int bЮЮ042EЮЮЮ042EЮ042EЮ;
  private final nuuuuu bЮЮЮЮЮЮ042EЮ042EЮ;
  
  /* Error */
  static
  {
    // Byte code:
    //   0: getstatic 27	kkkkkk/kkkjjj:bЮ042E042E042E042E042EЮЮ042EЮ	Ljava/lang/String;
    //   3: astore 5
    //   5: aload 5
    //   7: sipush 241
    //   10: bipush 17
    //   12: iconst_3
    //   13: invokestatic 33	kkkkkk/gguuuu:bк043Aккк043Aкк043A043A	(Ljava/lang/String;CCC)Ljava/lang/String;
    //   16: putstatic 27	kkkkkk/kkkjjj:bЮ042E042E042E042E042EЮЮ042EЮ	Ljava/lang/String;
    //   19: getstatic 35	kkkkkk/kkkjjj:b042E042E042E042E042E042EЮЮ042EЮ	Ljava/lang/String;
    //   22: astore 5
    //   24: getstatic 37	kkkkkk/kkkjjj:b042EЮЮЮЮЮ042EЮ042EЮ	I
    //   27: istore_0
    //   28: getstatic 39	kkkkkk/kkkjjj:bЮ042EЮЮЮЮ042EЮ042EЮ	I
    //   31: istore_1
    //   32: getstatic 37	kkkkkk/kkkjjj:b042EЮЮЮЮЮ042EЮ042EЮ	I
    //   35: istore_2
    //   36: getstatic 41	kkkkkk/kkkjjj:b042E042EЮЮЮЮ042EЮ042EЮ	I
    //   39: istore_3
    //   40: getstatic 43	kkkkkk/kkkjjj:bЮЮ042EЮЮЮ042EЮ042EЮ	I
    //   43: istore 4
    //   45: iload_0
    //   46: iload_1
    //   47: iadd
    //   48: iload_2
    //   49: imul
    //   50: iload_3
    //   51: irem
    //   52: iload 4
    //   54: if_icmpeq +45 -> 99
    //   57: getstatic 37	kkkkkk/kkkjjj:b042EЮЮЮЮЮ042EЮ042EЮ	I
    //   60: getstatic 39	kkkkkk/kkkjjj:bЮ042EЮЮЮЮ042EЮ042EЮ	I
    //   63: iadd
    //   64: getstatic 37	kkkkkk/kkkjjj:b042EЮЮЮЮЮ042EЮ042EЮ	I
    //   67: imul
    //   68: getstatic 41	kkkkkk/kkkjjj:b042E042EЮЮЮЮ042EЮ042EЮ	I
    //   71: irem
    //   72: getstatic 43	kkkkkk/kkkjjj:bЮЮ042EЮЮЮ042EЮ042EЮ	I
    //   75: if_icmpeq +13 -> 88
    //   78: bipush 37
    //   80: putstatic 37	kkkkkk/kkkjjj:b042EЮЮЮЮЮ042EЮ042EЮ	I
    //   83: bipush 59
    //   85: putstatic 43	kkkkkk/kkkjjj:bЮЮ042EЮЮЮ042EЮ042EЮ	I
    //   88: invokestatic 47	kkkkkk/kkkjjj:bА04100410А0410АА0410А0410	()I
    //   91: putstatic 37	kkkkkk/kkkjjj:b042EЮЮЮЮЮ042EЮ042EЮ	I
    //   94: bipush 90
    //   96: putstatic 43	kkkkkk/kkkjjj:bЮЮ042EЮЮЮ042EЮ042EЮ	I
    //   99: aload 5
    //   101: bipush 44
    //   103: iconst_0
    //   104: invokestatic 51	kkkkkk/gguuuu:bккккк043Aкк043A043A	(Ljava/lang/String;CC)Ljava/lang/String;
    //   107: putstatic 35	kkkkkk/kkkjjj:b042E042E042E042E042E042EЮЮ042EЮ	Ljava/lang/String;
    //   110: return
    //   111: astore 5
    //   113: aload 5
    //   115: athrow
    //   116: astore 5
    //   118: aload 5
    //   120: athrow
    // Local variable table:
    //   start	length	slot	name	signature
    //   27	21	0	i	int
    //   31	17	1	j	int
    //   35	15	2	k	int
    //   39	13	3	m	int
    //   43	12	4	n	int
    //   3	97	5	str	String
    //   111	3	5	localException1	Exception
    //   116	3	5	localException2	Exception
    // Exception table:
    //   from	to	target	type
    //   0	5	111	java/lang/Exception
    //   24	45	111	java/lang/Exception
    //   99	110	111	java/lang/Exception
    //   5	24	116	java/lang/Exception
    //   88	99	116	java/lang/Exception
  }
  
  @Inject
  public kkkjjj(nuuuuu paramNuuuuu)
  {
    this.bЮЮЮЮЮЮ042EЮ042EЮ = paramNuuuuu;
  }
  
  public static int b0410А0410А0410АА0410А0410()
  {
    return 1;
  }
  
  public static int bА04100410А0410АА0410А0410()
  {
    return 29;
  }
  
  public static int bАА0410А0410АА0410А0410()
  {
    return 2;
  }
  
  /* Error */
  @ooiiio
  public void b041004100410А0410АА0410А0410()
  {
    // Byte code:
    //   0: aload_0
    //   1: getfield 59	kkkkkk/kkkjjj:bЮЮЮЮЮЮ042EЮ042EЮ	Lkkkkkk/nuuuuu;
    //   4: astore_1
    //   5: getstatic 70	kkkkkk/uunnuu:SERVICE	Lkkkkkk/uunnuu;
    //   8: astore_2
    //   9: getstatic 76	kkkkkk/nunnuu:HOMEPAGE	Lkkkkkk/nunnuu;
    //   12: astore_3
    //   13: getstatic 82	kkkkkk/nnnuuu$ununuu:HOME_PAGE	Lkkkkkk/nnnuuu$ununuu;
    //   16: astore 4
    //   18: getstatic 88	kkkkkk/nuuunu:N3_20	Lkkkkkk/nuuunu;
    //   21: astore 5
    //   23: getstatic 94	kkkkkk/nnnuuu$nnunuu:ONE	Lkkkkkk/nnnuuu$nnunuu;
    //   26: astore 6
    //   28: ldc 96
    //   30: bipush 86
    //   32: iconst_4
    //   33: invokestatic 51	kkkkkk/gguuuu:bккккк043Aкк043A043A	(Ljava/lang/String;CC)Ljava/lang/String;
    //   36: astore 7
    //   38: getstatic 102	kkkkkk/unuunu:SCREEN_NAME	Lkkkkkk/unuunu;
    //   41: astore 8
    //   43: aload_1
    //   44: aload_2
    //   45: aload_3
    //   46: aload 4
    //   48: aload 5
    //   50: aload 6
    //   52: aload 7
    //   54: iconst_1
    //   55: anewarray 104	kkkkkk/nuuuuu$unuuuu
    //   58: dup
    //   59: iconst_0
    //   60: aload 8
    //   62: ldc 106
    //   64: bipush 65
    //   66: iconst_0
    //   67: invokestatic 51	kkkkkk/gguuuu:bккккк043Aкк043A043A	(Ljava/lang/String;CC)Ljava/lang/String;
    //   70: invokestatic 110	kkkkkk/nuuuuu$unuuuu:b043F043F043Fп043F043Fпп043Fп	(Lkkkkkk/unuunu;Ljava/lang/String;)Lkkkkkk/nuuuuu$unuuuu;
    //   73: aastore
    //   74: invokevirtual 116	kkkkkk/nuuuuu:b043Fп043Fппп043Fп043Fп	(Lkkkkkk/uunnuu;Lkkkkkk/nunnuu;Lkkkkkk/nnnuuu$ununuu;Lkkkkkk/nuuunu;Lkkkkkk/nnnuuu$nnunuu;Ljava/lang/String;[Lkkkkkk/nuuuuu$unuuuu;)V
    //   77: return
    //   78: astore_1
    //   79: aload_1
    //   80: athrow
    //   81: astore_1
    //   82: aload_1
    //   83: athrow
    // Local variable table:
    //   start	length	slot	name	signature
    //   0	84	0	this	kkkjjj
    //   4	40	1	localNuuuuu	nuuuuu
    //   78	2	1	localException1	Exception
    //   81	2	1	localException2	Exception
    //   8	37	2	localUunnuu	uunnuu
    //   12	34	3	localNunnuu	nunnuu
    //   16	31	4	localUnunuu	nnnuuu.ununuu
    //   21	28	5	localNuuunu	nuuunu
    //   26	25	6	localNnunuu	nnnuuu.nnunuu
    //   36	17	7	str	String
    //   41	20	8	localUnuunu	unuunu
    // Exception table:
    //   from	to	target	type
    //   0	18	78	java/lang/Exception
    //   23	38	78	java/lang/Exception
    //   43	77	78	java/lang/Exception
    //   18	23	81	java/lang/Exception
    //   38	43	81	java/lang/Exception
  }
}
