package kkkkkk;

import android.app.Notification.Builder;
import android.app.PendingIntent;
import android.content.Context;
import android.content.Intent;
import android.content.res.Resources;
import android.support.annotation.Nullable;
import com.liveperson.infra.ConversationViewParams;
import com.liveperson.infra.LPAuthenticationParams;
import com.liveperson.infra.messaging.R.bool;
import com.liveperson.infra.messaging.R.string;
import com.liveperson.messaging.background.BackgroundActionsService;
import com.liveperson.messaging.model.AgentData;
import java.util.ArrayList;

public class kkyykk
  implements bhhbhh, ovovov, xxddxd
{
  public static final String b044C044C044Cь044Cьь044Cь = "MP>JGRSJQQ-I";
  public static int b044C044Cь044Cь044Cь044Cь = 47;
  public static int b044Cь044C044Cь044Cь044Cь = 1;
  public static final String b044Cь044Cь044Cьь044Cь = "DJSGSAUKRR.J";
  public static int bь044C044C044Cь044Cь044Cь = 2;
  public static final int bь044C044Cь044Cьь044Cь = -1;
  public static int bьь044C044Cь044Cь044Cь = 0;
  public static final String bьь044Cь044Cьь044Cь = gguuuu.bк043Aккк043Aкк043A043A(bьь044Cь044Cьь044Cь, '_', 'Ö', '\000');
  private static final String bььь044C044Cьь044Cь;
  public mmcmcc b044C044C044C044C044Cьь044Cь;
  private hhhbbh b044C044C044Cьь044Cь044Cь;
  public ggggga b044C044Cь044C044Cьь044Cь;
  public hhhbhh b044C044Cььь044Cь044Cь = new hhhbhh();
  public ffnnnn b044Cь044C044C044Cьь044Cь;
  private Notification.Builder b044Cь044Cьь044Cь044Cь = null;
  public eeefee b044Cьь044C044Cьь044Cь;
  private boolean b044Cьь044Cь044Cь044Cь;
  private ConversationViewParams b044Cьььь044Cь044Cь;
  public cmmmcc bь044C044C044C044Cьь044Cь;
  private PendingIntent bь044C044Cьь044Cь044Cь = null;
  public aggaga bь044Cь044C044Cьь044Cь;
  private ykykyy bь044Cь044Cь044Cь044Cь;
  private boolean bь044Cььь044Cь044Cь;
  public mcmmcc bьь044C044C044Cьь044Cь;
  private Notification.Builder bьь044Cьь044Cь044Cь = null;
  private mmcmmc bььь044Cь044Cь044Cь;
  public mcmccc bььььь044Cь044Cь;
  
  /* Error */
  static
  {
    // Byte code:
    //   0: getstatic 72	kkkkkk/kkyykk:bьь044Cь044Cьь044Cь	Ljava/lang/String;
    //   3: bipush 95
    //   5: sipush 214
    //   8: iconst_0
    //   9: invokestatic 78	kkkkkk/gguuuu:bк043Aккк043Aкк043A043A	(Ljava/lang/String;CCC)Ljava/lang/String;
    //   12: putstatic 72	kkkkkk/kkyykk:bьь044Cь044Cьь044Cь	Ljava/lang/String;
    //   15: getstatic 80	kkkkkk/kkyykk:b044Cь044Cь044Cьь044Cь	Ljava/lang/String;
    //   18: sipush 157
    //   21: iconst_1
    //   22: invokestatic 84	kkkkkk/gguuuu:bккккк043Aкк043A043A	(Ljava/lang/String;CC)Ljava/lang/String;
    //   25: astore 5
    //   27: getstatic 86	kkkkkk/kkyykk:b044C044Cь044Cь044Cь044Cь	I
    //   30: istore_0
    //   31: getstatic 88	kkkkkk/kkyykk:b044Cь044C044Cь044Cь044Cь	I
    //   34: istore_1
    //   35: getstatic 86	kkkkkk/kkyykk:b044C044Cь044Cь044Cь044Cь	I
    //   38: istore_2
    //   39: getstatic 90	kkkkkk/kkyykk:bь044C044C044Cь044Cь044Cь	I
    //   42: istore_3
    //   43: getstatic 92	kkkkkk/kkyykk:bьь044C044Cь044Cь044Cь	I
    //   46: istore 4
    //   48: iload_0
    //   49: iload_1
    //   50: iadd
    //   51: iload_2
    //   52: imul
    //   53: iload_3
    //   54: irem
    //   55: iload 4
    //   57: if_icmpeq +47 -> 104
    //   60: invokestatic 96	kkkkkk/kkyykk:b0428Ш0428Ш0428042804280428Ш0428	()I
    //   63: putstatic 86	kkkkkk/kkyykk:b044C044Cь044Cь044Cь044Cь	I
    //   66: invokestatic 96	kkkkkk/kkyykk:b0428Ш0428Ш0428042804280428Ш0428	()I
    //   69: putstatic 92	kkkkkk/kkyykk:bьь044C044Cь044Cь044Cь	I
    //   72: getstatic 86	kkkkkk/kkyykk:b044C044Cь044Cь044Cь044Cь	I
    //   75: getstatic 88	kkkkkk/kkyykk:b044Cь044C044Cь044Cь044Cь	I
    //   78: iadd
    //   79: getstatic 86	kkkkkk/kkyykk:b044C044Cь044Cь044Cь044Cь	I
    //   82: imul
    //   83: getstatic 90	kkkkkk/kkyykk:bь044C044C044Cь044Cь044Cь	I
    //   86: irem
    //   87: getstatic 92	kkkkkk/kkyykk:bьь044C044Cь044Cь044Cь	I
    //   90: if_icmpeq +14 -> 104
    //   93: bipush 50
    //   95: putstatic 86	kkkkkk/kkyykk:b044C044Cь044Cь044Cь044Cь	I
    //   98: invokestatic 96	kkkkkk/kkyykk:b0428Ш0428Ш0428042804280428Ш0428	()I
    //   101: putstatic 92	kkkkkk/kkyykk:bьь044C044Cь044Cь044Cь	I
    //   104: aload 5
    //   106: putstatic 80	kkkkkk/kkyykk:b044Cь044Cь044Cьь044Cь	Ljava/lang/String;
    //   109: getstatic 98	kkkkkk/kkyykk:b044C044C044Cь044Cьь044Cь	Ljava/lang/String;
    //   112: astore 5
    //   114: aload 5
    //   116: sipush 216
    //   119: iconst_0
    //   120: invokestatic 84	kkkkkk/gguuuu:bккккк043Aкк043A043A	(Ljava/lang/String;CC)Ljava/lang/String;
    //   123: putstatic 98	kkkkkk/kkyykk:b044C044C044Cь044Cьь044Cь	Ljava/lang/String;
    //   126: ldc 2
    //   128: invokevirtual 104	java/lang/Class:getSimpleName	()Ljava/lang/String;
    //   131: astore 5
    //   133: aload 5
    //   135: putstatic 106	kkkkkk/kkyykk:bььь044C044Cьь044Cь	Ljava/lang/String;
    //   138: return
    //   139: astore 5
    //   141: aload 5
    //   143: athrow
    //   144: astore 5
    //   146: aload 5
    //   148: athrow
    //   149: astore 5
    //   151: aload 5
    //   153: athrow
    //   154: astore 5
    //   156: aload 5
    //   158: athrow
    // Local variable table:
    //   start	length	slot	name	signature
    //   30	21	0	i	int
    //   34	17	1	j	int
    //   38	15	2	k	int
    //   42	13	3	m	int
    //   46	12	4	n	int
    //   25	109	5	str	String
    //   139	3	5	localException1	Exception
    //   144	3	5	localException2	Exception
    //   149	3	5	localException3	Exception
    //   154	3	5	localException4	Exception
    // Exception table:
    //   from	to	target	type
    //   0	27	139	java/lang/Exception
    //   104	114	139	java/lang/Exception
    //   133	138	139	java/lang/Exception
    //   27	39	144	java/lang/Exception
    //   60	72	144	java/lang/Exception
    //   141	144	144	java/lang/Exception
    //   151	154	144	java/lang/Exception
    //   114	133	149	java/lang/Exception
    //   39	48	154	java/lang/Exception
  }
  
  public kkyykk() {}
  
  public static int b0428Ш0428Ш0428042804280428Ш0428()
  {
    return 40;
  }
  
  private void b0428Ш0428ШШШШШ04280428(voovov paramVoovov)
  {
    try
    {
      paramVoovov = new kkyykk.15(this, paramVoovov);
      localMcmccc = this.bььььь044Cь044Cь;
    }
    catch (Exception paramVoovov)
    {
      try
      {
        mcmccc localMcmccc;
        int i;
        int j;
        int k;
        b044C044Cь044Cь044Cь044Cь = 46;
        bьь044C044Cь044Cь044Cь = b0428Ш0428Ш0428042804280428Ш0428();
        localMcmccc.bШ04280428ШШШ04280428ШШ(paramVoovov);
        this.bьь044C044C044Cьь044Cь.b0445ххх0445хх044504450445();
        this.b044C044Cь044C044Cьь044Cь.b0445ххх0445хх044504450445();
        this.b044Cьь044C044Cьь044Cь.b0445ххх0445хх044504450445();
        return;
      }
      catch (Exception paramVoovov)
      {
        throw paramVoovov;
      }
      paramVoovov = paramVoovov;
      throw paramVoovov;
    }
    i = b044C044Cь044Cь044Cь044Cь;
    j = b044Cь044C044Cь044Cь044Cь;
    k = bь044C044C044Cь044Cь044Cь;
    if ((b0428Ш0428Ш0428042804280428Ш0428() + b044Cь044C044Cь044Cь044Cь) * b0428Ш0428Ш0428042804280428Ш0428() % bь044C044C044Cь044Cь044Cь != bьь044C044Cь044Cь044Cь)
    {
      b044C044Cь044Cь044Cь044Cь = 37;
      bьь044C044Cь044Cь044Cь = 6;
    }
    switch (i * (j + i) % k)
    {
    }
    switch (0)
    {
    }
    for (;;)
    {
      switch (0)
      {
      }
    }
  }
  
  public static int b0428ШШШ0428042804280428Ш0428()
  {
    return 2;
  }
  
  private void b0428ШШШШШШШ04280428(Context paramContext)
  {
    this.bььььь044Cь044Cь = new mcmccc(this);
    this.bь044C044C044C044Cьь044Cь = new cmmmcc(this.b044C044C044C044C044Cьь044Cь);
    this.b044C044Cь044C044Cьь044Cь = new ggggga(this);
    this.b044Cьь044C044Cьь044Cь = new eeefee(this);
    this.b044Cь044C044C044Cьь044Cь = new ffnnnn();
    this.bь044Cь044C044Cьь044Cь = new aggaga();
    this.bьь044C044C044Cьь044Cь = new mcmmcc(this);
    this.b044Cьь044Cь044Cь044Cь = paramContext.getResources().getBoolean(R.bool.upload_photo_using_service);
    ykykyy localYkykyy = new ykykyy(this, paramContext);
    int i = b044C044Cь044Cь044Cь044Cь;
    switch (i * (b044Cь044C044Cь044Cь044Cь + i) % bь044C044C044Cь044Cь044Cь)
    {
    default: 
      b044C044Cь044Cь044Cь044Cь = 2;
      bьь044C044Cь044Cь044Cь = 20;
    }
    this.bь044Cь044Cь044Cь044Cь = localYkykyy;
    paramContext = paramContext.getResources();
    i = R.bool.enable_structured_content;
    if ((b044C044Cь044Cь044Cь044Cь + b044Cь044C044Cь044Cь044Cь) * b044C044Cь044Cь044Cь044Cь % bь044C044C044Cь044Cь044Cь != bьь044C044Cь044Cь044Cь)
    {
      b044C044Cь044Cь044Cь044Cь = 42;
      bьь044C044Cь044Cь044Cь = b0428Ш0428Ш0428042804280428Ш0428();
    }
    this.bь044Cььь044Cь044Cь = paramContext.getBoolean(i);
    paramContext = new mmcmmc();
    switch (0)
    {
    case 1: 
    default: 
      for (;;)
      {
        switch (0)
        {
        }
      }
    }
    this.bььь044Cь044Cь044Cь = paramContext;
  }
  
  /* Error */
  private void bШ042804280428ШШШШ04280428(kyykky paramKyykky)
  {
    // Byte code:
    //   0: aload_1
    //   1: ifnull +23 -> 24
    //   4: aload_0
    //   5: new 238	kkkkkk/mmcmcc
    //   8: dup
    //   9: aload_1
    //   10: invokevirtual 243	kkkkkk/kyykky:bШШ042804280428ШШШ04280428	()Ljava/lang/String;
    //   13: aload_1
    //   14: invokevirtual 246	kkkkkk/kyykky:b0428ШШШШШ04280428ШШ	()Ljava/lang/String;
    //   17: invokespecial 249	kkkkkk/mmcmcc:<init>	(Ljava/lang/String;Ljava/lang/String;)V
    //   20: putfield 171	kkkkkk/kkyykk:b044C044C044C044C044Cьь044Cь	Lkkkkkk/mmcmcc;
    //   23: return
    //   24: aload_0
    //   25: getfield 171	kkkkkk/kkyykk:b044C044C044C044C044Cьь044Cь	Lkkkkkk/mmcmcc;
    //   28: ifnonnull -5 -> 23
    //   31: new 238	kkkkkk/mmcmcc
    //   34: dup
    //   35: invokespecial 250	kkkkkk/mmcmcc:<init>	()V
    //   38: astore_1
    //   39: getstatic 86	kkkkkk/kkyykk:b044C044Cь044Cь044Cь044Cь	I
    //   42: istore_2
    //   43: getstatic 88	kkkkkk/kkyykk:b044Cь044C044Cь044Cь044Cь	I
    //   46: istore_3
    //   47: getstatic 86	kkkkkk/kkyykk:b044C044Cь044Cь044Cь044Cь	I
    //   50: istore 4
    //   52: getstatic 90	kkkkkk/kkyykk:bь044C044C044Cь044Cь044Cь	I
    //   55: istore 5
    //   57: getstatic 92	kkkkkk/kkyykk:bьь044C044Cь044Cь044Cь	I
    //   60: istore 6
    //   62: iload_2
    //   63: iload_3
    //   64: iadd
    //   65: iload 4
    //   67: imul
    //   68: iload 5
    //   70: irem
    //   71: iload 6
    //   73: if_icmpeq +56 -> 129
    //   76: getstatic 86	kkkkkk/kkyykk:b044C044Cь044Cь044Cь044Cь	I
    //   79: istore_2
    //   80: iload_2
    //   81: getstatic 88	kkkkkk/kkyykk:b044Cь044C044Cь044Cь044Cь	I
    //   84: iload_2
    //   85: iadd
    //   86: imul
    //   87: invokestatic 125	kkkkkk/kkyykk:b0428ШШШ0428042804280428Ш0428	()I
    //   90: irem
    //   91: tableswitch	default:+17->108, 0:+27->118
    //   108: bipush 37
    //   110: putstatic 86	kkkkkk/kkyykk:b044C044Cь044Cь044Cь044Cь	I
    //   113: bipush 84
    //   115: putstatic 92	kkkkkk/kkyykk:bьь044C044Cь044Cь044Cь	I
    //   118: invokestatic 96	kkkkkk/kkyykk:b0428Ш0428Ш0428042804280428Ш0428	()I
    //   121: putstatic 86	kkkkkk/kkyykk:b044C044Cь044Cь044Cь044Cь	I
    //   124: bipush 81
    //   126: putstatic 92	kkkkkk/kkyykk:bьь044C044Cь044Cь044Cь	I
    //   129: aload_0
    //   130: aload_1
    //   131: putfield 171	kkkkkk/kkyykk:b044C044C044C044C044Cьь044Cь	Lkkkkkk/mmcmcc;
    //   134: return
    //   135: astore_1
    //   136: aload_1
    //   137: athrow
    //   138: astore_1
    //   139: aload_1
    //   140: athrow
    //   141: astore_1
    //   142: aload_1
    //   143: athrow
    //   144: astore_1
    //   145: aload_1
    //   146: athrow
    // Local variable table:
    //   start	length	slot	name	signature
    //   0	147	0	this	kkyykk
    //   0	147	1	paramKyykky	kyykky
    //   42	45	2	i	int
    //   46	19	3	j	int
    //   50	18	4	k	int
    //   55	16	5	m	int
    //   60	14	6	n	int
    // Exception table:
    //   from	to	target	type
    //   4	23	135	java/lang/Exception
    //   129	134	135	java/lang/Exception
    //   47	62	138	java/lang/Exception
    //   118	124	138	java/lang/Exception
    //   136	138	138	java/lang/Exception
    //   142	144	138	java/lang/Exception
    //   24	39	141	java/lang/Exception
    //   39	47	144	java/lang/Exception
    //   124	129	144	java/lang/Exception
  }
  
  @Nullable
  private bbhbhh bШ04280428Ш0428042804280428Ш0428(String paramString1, String paramString2)
  {
    if (!this.bььььь044Cь044Cь.b0424Ф0424ФФФФФФ0424(paramString2)) {
      paramString1 = bbhbhh.NO_NETWORK;
    }
    do
    {
      return paramString1;
      if ((b044C044Cь044Cь044Cь044Cь + b044Cь044C044Cь044Cь044Cь) * b044C044Cь044Cь044Cь044Cь % b0428ШШШ0428042804280428Ш0428() != bьь044C044Cь044Cь044Cь)
      {
        b044C044Cь044Cь044Cь044Cь = 62;
        bьь044C044Cь044Cь044Cь = 56;
      }
      if (!this.b044Cьь044C044Cьь044Cь.b0424Ф04240424042404240424042404240424(paramString1)) {
        return bbhbhh.CONVERSATION_NOT_ACTIVE;
      }
      paramString1 = null;
      switch (0)
      {
      case 1: 
      default: 
        for (;;)
        {
          switch (0)
          {
          case 1: 
          default: 
            for (;;)
            {
              switch (1)
              {
              }
            }
          }
          switch (0)
          {
          }
        }
      }
    } while ((b0428Ш0428Ш0428042804280428Ш0428() + b044Cь044C044Cь044Cь044Cь) * b0428Ш0428Ш0428042804280428Ш0428() % bь044C044C044Cь044Cь044Cь == bьь044C044Cь044Cь044Cь);
    b044C044Cь044Cь044Cь044Cь = b0428Ш0428Ш0428042804280428Ш0428();
    bьь044C044Cь044Cь044Cь = 70;
    return null;
  }
  
  public static int bШ0428ШШ0428042804280428Ш0428()
  {
    return 0;
  }
  
  private void bШ0428ШШШШШШ04280428(Context paramContext, kyykky paramKyykky)
  {
    try
    {
      throw new NullPointerException();
    }
    catch (Exception localException)
    {
      b044C044Cь044Cь044Cь044Cь = b0428Ш0428Ш0428042804280428Ш0428();
      int i = b0428Ш0428Ш0428042804280428Ш0428();
      switch (i * (b044Cь044C044Cь044Cь044Cь + i) % bь044C044C044Cь044Cь044Cь)
      {
      default: 
        b044C044Cь044Cь044Cь044Cь = b0428Ш0428Ш0428042804280428Ш0428();
        bьь044C044Cь044Cь044Cь = b0428Ш0428Ш0428042804280428Ш0428();
      }
      xtxtxt.bии0438и04380438и0438ии(bььь044C044Cьь044Cь, gguuuu.bккккк043Aкк043A043A("u\034\030$\032\023\037\035/\037%\037fgh", '', '\004'));
      bШ042804280428ШШШШ04280428(paramKyykky);
      b0428ШШШШШШШ04280428(paramContext);
      switch (0)
      {
      case 1: 
      default: 
        for (;;)
        {
          switch (0)
          {
          }
        }
      }
      switch (1)
      {
      case 0: 
      default: 
        for (;;)
        {
          switch (0)
          {
          }
        }
      }
      this.bььььь044Cь044Cь.bФФФФФФФФФ0424();
      b04280428ШШ0428042804280428Ш0428();
    }
  }
  
  public static int bШШ0428Ш0428042804280428Ш0428()
  {
    return 1;
  }
  
  /* Error */
  private void bШШШ0428ШШШШ04280428(String paramString1, String paramString2, String paramString3, String paramString4, long paramLong1, long paramLong2)
  {
    // Byte code:
    //   0: getstatic 297	kkkkkk/xxdxxd:instance	Lkkkkkk/xxdxxd;
    //   3: invokevirtual 301	kkkkkk/xxdxxd:bххх044504450445х044504450445	()Landroid/content/Context;
    //   6: astore 9
    //   8: aload_0
    //   9: getfield 208	kkkkkk/kkyykk:b044Cьь044Cь044Cь044Cь	Z
    //   12: ifne +47 -> 59
    //   15: getstatic 106	kkkkkk/kkyykk:bььь044C044Cьь044Cь	Ljava/lang/String;
    //   18: astore 9
    //   20: aload 9
    //   22: ldc_w 303
    //   25: bipush 46
    //   27: iconst_2
    //   28: invokestatic 84	kkkkkk/gguuuu:bккккк043Aкк043A043A	(Ljava/lang/String;CC)Ljava/lang/String;
    //   31: invokestatic 281	kkkkkk/xtxtxt:bии0438и04380438и0438ии	(Ljava/lang/String;Ljava/lang/String;)V
    //   34: aload_0
    //   35: getfield 215	kkkkkk/kkyykk:bь044Cь044Cь044Cь044Cь	Lkkkkkk/ykykyy;
    //   38: aload_1
    //   39: aload_2
    //   40: aload 4
    //   42: aload_3
    //   43: lload 5
    //   45: lload 7
    //   47: new 305	kkkkkk/kkyykk$4
    //   50: dup
    //   51: aload_0
    //   52: invokespecial 306	kkkkkk/kkyykk$4:<init>	(Lkkkkkk/kkyykk;)V
    //   55: invokevirtual 310	kkkkkk/ykykyy:b0428Ш0428Ш04280428Ш042804280428	(Ljava/lang/String;Ljava/lang/String;Ljava/lang/String;Ljava/lang/String;JJLkkkkkk/ykykyy$yjjyyy;)V
    //   58: return
    //   59: getstatic 106	kkkkkk/kkyykk:bььь044C044Cьь044Cь	Ljava/lang/String;
    //   62: ldc_w 312
    //   65: bipush 77
    //   67: bipush 51
    //   69: iconst_2
    //   70: invokestatic 78	kkkkkk/gguuuu:bк043Aккк043Aкк043A043A	(Ljava/lang/String;CCC)Ljava/lang/String;
    //   73: invokestatic 281	kkkkkk/xtxtxt:bии0438и04380438и0438ии	(Ljava/lang/String;Ljava/lang/String;)V
    //   76: getstatic 86	kkkkkk/kkyykk:b044C044Cь044Cь044Cь044Cь	I
    //   79: getstatic 88	kkkkkk/kkyykk:b044Cь044C044Cь044Cь044Cь	I
    //   82: iadd
    //   83: getstatic 86	kkkkkk/kkyykk:b044C044Cь044Cь044Cь044Cь	I
    //   86: imul
    //   87: invokestatic 125	kkkkkk/kkyykk:b0428ШШШ0428042804280428Ш0428	()I
    //   90: irem
    //   91: getstatic 92	kkkkkk/kkyykk:bьь044C044Cь044Cь044Cь	I
    //   94: if_icmpeq +14 -> 108
    //   97: bipush 27
    //   99: putstatic 86	kkkkkk/kkyykk:b044C044Cь044Cь044Cь044Cь	I
    //   102: invokestatic 96	kkkkkk/kkyykk:b0428Ш0428Ш0428042804280428Ш0428	()I
    //   105: putstatic 92	kkkkkk/kkyykk:bьь044C044Cь044Cь044Cь	I
    //   108: new 314	android/content/Intent
    //   111: dup
    //   112: aload 9
    //   114: ldc_w 316
    //   117: invokespecial 319	android/content/Intent:<init>	(Landroid/content/Context;Ljava/lang/Class;)V
    //   120: astore 10
    //   122: aload 10
    //   124: ldc_w 321
    //   127: sipush 175
    //   130: iconst_0
    //   131: invokestatic 84	kkkkkk/gguuuu:bккккк043Aкк043A043A	(Ljava/lang/String;CC)Ljava/lang/String;
    //   134: iconst_3
    //   135: invokevirtual 325	android/content/Intent:putExtra	(Ljava/lang/String;I)Landroid/content/Intent;
    //   138: pop
    //   139: aload 10
    //   141: ldc_w 327
    //   144: bipush 87
    //   146: iconst_1
    //   147: invokestatic 84	kkkkkk/gguuuu:bккккк043Aкк043A043A	(Ljava/lang/String;CC)Ljava/lang/String;
    //   150: aload_1
    //   151: invokevirtual 330	android/content/Intent:putExtra	(Ljava/lang/String;Ljava/lang/String;)Landroid/content/Intent;
    //   154: pop
    //   155: aload 10
    //   157: ldc_w 332
    //   160: bipush 83
    //   162: iconst_5
    //   163: invokestatic 84	kkkkkk/gguuuu:bккккк043Aкк043A043A	(Ljava/lang/String;CC)Ljava/lang/String;
    //   166: aload_2
    //   167: invokevirtual 330	android/content/Intent:putExtra	(Ljava/lang/String;Ljava/lang/String;)Landroid/content/Intent;
    //   170: pop
    //   171: aload 10
    //   173: ldc_w 334
    //   176: sipush 209
    //   179: bipush 74
    //   181: iconst_0
    //   182: invokestatic 78	kkkkkk/gguuuu:bк043Aккк043Aкк043A043A	(Ljava/lang/String;CCC)Ljava/lang/String;
    //   185: aload 4
    //   187: invokevirtual 330	android/content/Intent:putExtra	(Ljava/lang/String;Ljava/lang/String;)Landroid/content/Intent;
    //   190: pop
    //   191: aload 10
    //   193: ldc_w 336
    //   196: sipush 188
    //   199: bipush 125
    //   201: iconst_0
    //   202: invokestatic 78	kkkkkk/gguuuu:bк043Aккк043Aкк043A043A	(Ljava/lang/String;CCC)Ljava/lang/String;
    //   205: aload_3
    //   206: invokevirtual 330	android/content/Intent:putExtra	(Ljava/lang/String;Ljava/lang/String;)Landroid/content/Intent;
    //   209: pop
    //   210: aload 10
    //   212: ldc_w 338
    //   215: sipush 217
    //   218: bipush 126
    //   220: iconst_0
    //   221: invokestatic 78	kkkkkk/gguuuu:bк043Aккк043Aкк043A043A	(Ljava/lang/String;CCC)Ljava/lang/String;
    //   224: lload 5
    //   226: invokevirtual 341	android/content/Intent:putExtra	(Ljava/lang/String;J)Landroid/content/Intent;
    //   229: pop
    //   230: invokestatic 96	kkkkkk/kkyykk:b0428Ш0428Ш0428042804280428Ш0428	()I
    //   233: getstatic 88	kkkkkk/kkyykk:b044Cь044C044Cь044Cь044Cь	I
    //   236: iadd
    //   237: invokestatic 96	kkkkkk/kkyykk:b0428Ш0428Ш0428042804280428Ш0428	()I
    //   240: imul
    //   241: invokestatic 125	kkkkkk/kkyykk:b0428ШШШ0428042804280428Ш0428	()I
    //   244: irem
    //   245: getstatic 92	kkkkkk/kkyykk:bьь044C044Cь044Cь044Cь	I
    //   248: if_icmpeq +15 -> 263
    //   251: invokestatic 96	kkkkkk/kkyykk:b0428Ш0428Ш0428042804280428Ш0428	()I
    //   254: putstatic 86	kkkkkk/kkyykk:b044C044Cь044Cь044Cь044Cь	I
    //   257: invokestatic 96	kkkkkk/kkyykk:b0428Ш0428Ш0428042804280428Ш0428	()I
    //   260: putstatic 92	kkkkkk/kkyykk:bьь044C044Cь044Cь044Cь	I
    //   263: aload 10
    //   265: ldc_w 343
    //   268: sipush 175
    //   271: iconst_2
    //   272: invokestatic 84	kkkkkk/gguuuu:bккккк043Aкк043A043A	(Ljava/lang/String;CC)Ljava/lang/String;
    //   275: lload 7
    //   277: invokevirtual 341	android/content/Intent:putExtra	(Ljava/lang/String;J)Landroid/content/Intent;
    //   280: pop
    //   281: aload 9
    //   283: aload 10
    //   285: invokevirtual 347	android/content/Context:startService	(Landroid/content/Intent;)Landroid/content/ComponentName;
    //   288: pop
    //   289: return
    //   290: astore_1
    //   291: aload_1
    //   292: athrow
    //   293: astore_1
    //   294: aload_1
    //   295: athrow
    // Local variable table:
    //   start	length	slot	name	signature
    //   0	296	0	this	kkyykk
    //   0	296	1	paramString1	String
    //   0	296	2	paramString2	String
    //   0	296	3	paramString3	String
    //   0	296	4	paramString4	String
    //   0	296	5	paramLong1	long
    //   0	296	7	paramLong2	long
    //   6	276	9	localObject	Object
    //   120	164	10	localIntent	Intent
    // Exception table:
    //   from	to	target	type
    //   108	155	290	java/lang/Exception
    //   281	289	290	java/lang/Exception
    //   0	20	293	java/lang/Exception
    //   20	58	293	java/lang/Exception
    //   59	76	293	java/lang/Exception
    //   155	230	293	java/lang/Exception
    //   263	281	293	java/lang/Exception
  }
  
  public ykykyy b04280428042804280428042804280428Ш0428()
  {
    int i = b044C044Cь044Cь044Cь044Cь;
    switch (i * (b044Cь044C044Cь044Cь044Cь + i) % b0428ШШШ0428042804280428Ш0428())
    {
    default: 
      b044C044Cь044Cь044Cь044Cь = b0428Ш0428Ш0428042804280428Ш0428();
      bьь044C044Cь044Cь044Cь = b0428Ш0428Ш0428042804280428Ш0428();
    }
    return this.bь044Cь044Cь044Cь044Cь;
  }
  
  /* Error */
  public bbhbhh b0428042804280428042804280428ШШ0428(String paramString1, String paramString2)
  {
    // Byte code:
    //   0: aload_0
    //   1: aload_1
    //   2: aload_2
    //   3: invokespecial 355	kkkkkk/kkyykk:bШ04280428Ш0428042804280428Ш0428	(Ljava/lang/String;Ljava/lang/String;)Lkkkkkk/bbhbhh;
    //   6: astore 4
    //   8: aload 4
    //   10: ifnull +98 -> 108
    //   13: aload 4
    //   15: areturn
    //   16: aload_1
    //   17: invokevirtual 360	kkkkkk/yjjyyj:bххххххх044504450445	()V
    //   20: getstatic 86	kkkkkk/kkyykk:b044C044Cь044Cь044Cь044Cь	I
    //   23: istore_3
    //   24: iload_3
    //   25: getstatic 88	kkkkkk/kkyykk:b044Cь044C044Cь044Cь044Cь	I
    //   28: iload_3
    //   29: iadd
    //   30: imul
    //   31: getstatic 90	kkkkkk/kkyykk:bь044C044C044Cь044Cь044Cь	I
    //   34: irem
    //   35: tableswitch	default:+17->52, 0:+150->185
    //   52: invokestatic 96	kkkkkk/kkyykk:b0428Ш0428Ш0428042804280428Ш0428	()I
    //   55: putstatic 86	kkkkkk/kkyykk:b044C044Cь044Cь044Cь044Cь	I
    //   58: invokestatic 96	kkkkkk/kkyykk:b0428Ш0428Ш0428042804280428Ш0428	()I
    //   61: putstatic 92	kkkkkk/kkyykk:bьь044C044Cь044Cь044Cь	I
    //   64: getstatic 86	kkkkkk/kkyykk:b044C044Cь044Cь044Cь044Cь	I
    //   67: istore_3
    //   68: iload_3
    //   69: getstatic 88	kkkkkk/kkyykk:b044Cь044C044Cь044Cь044Cь	I
    //   72: iload_3
    //   73: iadd
    //   74: imul
    //   75: getstatic 90	kkkkkk/kkyykk:bь044C044C044Cь044Cь044Cь	I
    //   78: irem
    //   79: tableswitch	default:+17->96, 0:+106->185
    //   96: bipush 64
    //   98: putstatic 86	kkkkkk/kkyykk:b044C044Cь044Cь044Cь044Cь	I
    //   101: bipush 74
    //   103: putstatic 92	kkkkkk/kkyykk:bьь044C044Cь044Cь044Cь	I
    //   106: aconst_null
    //   107: areturn
    //   108: new 357	kkkkkk/yjjyyj
    //   111: dup
    //   112: aload_0
    //   113: getfield 159	kkkkkk/kkyykk:b044Cьь044C044Cьь044Cь	Lkkkkkk/eeefee;
    //   116: aload_1
    //   117: aload_0
    //   118: getfield 176	kkkkkk/kkyykk:bь044C044C044C044Cьь044Cь	Lkkkkkk/cmmmcc;
    //   121: aload_2
    //   122: invokevirtual 364	kkkkkk/cmmmcc:b0424ФФ042404240424Ф04240424Ф	(Ljava/lang/String;)Ljava/lang/String;
    //   125: invokespecial 367	kkkkkk/yjjyyj:<init>	(Lkkkkkk/eeefee;Ljava/lang/String;Ljava/lang/String;)V
    //   128: astore_1
    //   129: iconst_1
    //   130: tableswitch	default:+22->152, 0:+-1->129, 1:+-114->16
    //   152: iconst_1
    //   153: tableswitch	default:+23->176, 0:+-24->129, 1:+-137->16
    //   176: goto -24 -> 152
    //   179: astore_1
    //   180: aload_1
    //   181: athrow
    //   182: astore_1
    //   183: aload_1
    //   184: athrow
    //   185: aconst_null
    //   186: areturn
    // Local variable table:
    //   start	length	slot	name	signature
    //   0	187	0	this	kkyykk
    //   0	187	1	paramString1	String
    //   0	187	2	paramString2	String
    //   23	52	3	i	int
    //   6	8	4	localBbhbhh	bbhbhh
    // Exception table:
    //   from	to	target	type
    //   0	8	179	java/lang/Exception
    //   16	20	179	java/lang/Exception
    //   108	129	182	java/lang/Exception
  }
  
  public void b0428042804280428Ш04280428ШШ0428(Context paramContext, kyykky paramKyykky, xdxxdx paramXdxxdx)
  {
    int i = b044C044Cь044Cь044Cь044Cь;
    switch (i * (b044Cь044C044Cь044Cь044Cь + i) % b0428ШШШ0428042804280428Ш0428())
    {
    default: 
      b044C044Cь044Cь044Cь044Cь = 95;
      bьь044C044Cь044Cь044Cь = b0428Ш0428Ш0428042804280428Ш0428();
    }
    paramXdxxdx = new kkyykk.1(this, paramContext, paramKyykky, paramXdxxdx);
    switch (0)
    {
    case 1: 
    default: 
      for (;;)
      {
        i = b044C044Cь044Cь044Cь044Cь;
        switch (i * (b044Cь044C044Cь044Cь044Cь + i) % bь044C044C044Cь044Cь044Cь)
        {
        default: 
          b044C044Cь044Cь044Cь044Cь = b0428Ш0428Ш0428042804280428Ш0428();
          bьь044C044Cь044Cь044Cь = 80;
        }
        switch (1)
        {
        }
      }
    }
    bШШШШ042804280428ШШ0428(paramContext, paramKyykky, paramXdxxdx);
  }
  
  public ConversationViewParams b042804280428Ш0428042804280428Ш0428()
  {
    throw new Runtime("d2j fail translate: java.lang.IndexOutOfBoundsException: fromIndex < 0: -1\n\tat java.util.BitSet.nextSetBit(BitSet.java:712)\n\tat com.googlecode.dex2jar.ir.ts.array.FillArrayTransformer.makeSureAllElementAreAssigned(FillArrayTransformer.java:505)\n\tat com.googlecode.dex2jar.ir.ts.array.FillArrayTransformer.transformReportChanged(FillArrayTransformer.java:123)\n\tat com.googlecode.dex2jar.ir.ts.StatedTransformer.transform(StatedTransformer.java:10)\n\tat com.googlecode.d2j.dex.Dex2jar$2.optimize(Dex2jar.java:149)\n\tat com.googlecode.d2j.dex.Dex2Asm.convertCode(Dex2Asm.java:414)\n\tat com.googlecode.d2j.dex.ExDex2Asm.convertCode(ExDex2Asm.java:42)\n\tat com.googlecode.d2j.dex.Dex2jar$2.convertCode(Dex2jar.java:128)\n\tat com.googlecode.d2j.dex.Dex2Asm.convertMethod(Dex2Asm.java:509)\n\tat com.googlecode.d2j.dex.Dex2Asm.convertClass(Dex2Asm.java:406)\n\tat com.googlecode.d2j.dex.Dex2Asm.convertDex(Dex2Asm.java:422)\n\tat com.googlecode.d2j.dex.Dex2jar.doTranslate(Dex2jar.java:172)\n\tat com.googlecode.d2j.dex.Dex2jar.to(Dex2jar.java:272)\n\tat com.googlecode.dex2jar.tools.Dex2jarCmd.doCommandLine(Dex2jarCmd.java:108)\n\tat com.googlecode.dex2jar.tools.BaseCmd.doMain(BaseCmd.java:288)\n\tat com.googlecode.dex2jar.tools.Dex2jarCmd.main(Dex2jarCmd.java:32)\n");
  }
  
  public void b042804280428Ш042804280428ШШ0428(String paramString, long paramLong)
  {
    try
    {
      mcmccc localMcmccc = this.bььььь044Cь044Cь;
      int i = b044C044Cь044Cь044Cь044Cь;
      switch (i * (b044Cь044C044Cь044Cь044Cь + i) % bь044C044C044Cь044Cь044Cь)
      {
      default: 
        b044C044Cь044Cь044Cь044Cь = 23;
        bьь044C044Cь044Cь044Cь = b0428Ш0428Ш0428042804280428Ш0428();
      }
      if ((b044C044Cь044Cь044Cь044Cь + b044Cь044C044Cь044Cь044Cь) * b044C044Cь044Cь044Cь044Cь % bь044C044C044Cь044Cь044Cь != bьь044C044Cь044Cь044Cь)
      {
        b044C044Cь044Cь044Cь044Cь = 84;
        bьь044C044Cь044Cь044Cь = 83;
      }
      localMcmccc.b042404240424ФФФФФФ0424(paramString, paramLong);
      return;
    }
    catch (Exception paramString)
    {
      throw paramString;
    }
  }
  
  public void b042804280428ШШ04280428ШШ0428(String paramString, dddxxd<Boolean, Exception> paramDddxxd)
  {
    try
    {
      paramString = this.b044Cьь044C044Cьь044Cь.bФ042404240424Ф04240424042404240424(paramString);
      paramDddxxd = new kkyykk.10(this, paramDddxxd);
      if ((b044C044Cь044Cь044Cь044Cь + b044Cь044C044Cь044Cь044Cь) * b044C044Cь044Cь044Cь044Cь % bь044C044C044Cь044Cь044Cь != bьь044C044Cь044Cь044Cь)
      {
        b044C044Cь044Cь044Cь044Cь = 70;
        bьь044C044Cь044Cь044Cь = 29;
      }
      paramString.b04380438и0438ии0438иии(paramDddxxd).b0438ии0438ии0438иии();
      return;
    }
    catch (Exception paramString)
    {
      throw paramString;
    }
  }
  
  public void b042804280428ШШШШ0428Ш0428(String paramString)
  {
    Object localObject = bььь044C044Cьь044Cь;
    StringBuilder localStringBuilder = new StringBuilder().append(gguuuu.bккккк043Aкк043A043A("\001s\002\007zuxg\n\006\b\t~~U<\021\001\017\006k\bDbF", 'F', '\004'));
    int i = b044C044Cь044Cь044Cь044Cь;
    switch (i * (b044Cь044C044Cь044Cь044Cь + i) % b0428ШШШ0428042804280428Ш0428())
    {
    default: 
      b044C044Cь044Cь044Cь044Cь = b0428Ш0428Ш0428042804280428Ш0428();
      switch (1)
      {
      case 0: 
      default: 
        for (;;)
        {
          switch (0)
          {
          }
        }
      }
      bьь044C044Cь044Cь044Cь = b0428Ш0428Ш0428042804280428Ш0428();
    }
    xtxtxt.bии0438и04380438и0438ии((String)localObject, paramString);
    localObject = this.bььььь044Cь044Cь;
    if ((b044C044Cь044Cь044Cь044Cь + b044Cь044C044Cь044Cь044Cь) * b044C044Cь044Cь044Cь044Cь % bь044C044C044Cь044Cь044Cь != bьь044C044Cь044Cь044Cь)
    {
      b044C044Cь044Cь044Cь044Cь = 73;
      bьь044C044Cь044Cь044Cь = 35;
    }
    ((mcmccc)localObject).bФ042404240424ФФФФФ0424(paramString);
  }
  
  public void b042804280428ШШШШШ04280428(String paramString)
  {
    mcmccc localMcmccc = this.bььььь044Cь044Cь;
    if ((b044C044Cь044Cь044Cь044Cь + b044Cь044C044Cь044Cь044Cь) * b044C044Cь044Cь044Cь044Cь % b0428ШШШ0428042804280428Ш0428() != bьь044C044Cь044Cь044Cь)
    {
      b044C044Cь044Cь044Cь044Cь = b0428Ш0428Ш0428042804280428Ш0428();
      bьь044C044Cь044Cь044Cь = b0428Ш0428Ш0428042804280428Ш0428();
    }
    localMcmccc.b0424ФФ042404240424042404240424Ф(paramString);
  }
  
  public String b04280428Ш04280428042804280428Ш0428()
  {
    int i = 2;
    try
    {
      for (;;)
      {
        i /= 0;
      }
      String str;
      return this.bь044Cь044Cь044Cь044Cь.bШ0428ШШ04280428Ш042804280428();
    }
    catch (Exception localException)
    {
      b044C044Cь044Cь044Cь044Cь = b0428Ш0428Ш0428042804280428Ш0428();
      str = bььь044C044Cьь044Cь;
      switch (0)
      {
      case 1: 
      default: 
        for (;;)
        {
          switch (0)
          {
          }
        }
      }
      xtxtxt.bии0438и04380438и0438ии(str, gguuuu.bк043Aккк043Aкк043A043A("KJZ0V9\\ZS_SbcFb_cVZD]lm\\cbPnwJfvWyxpvpD+pv\001ts\0062vu\002\0037@\b\n;\020\003\021\026\n\005\bL", '7', 'Ò', '\001'));
    }
  }
  
  public void b04280428Ш0428042804280428ШШ0428()
  {
    switch (0)
    {
    case 1: 
    default: 
      for (;;)
      {
        switch (0)
        {
        }
      }
    }
    if ((b0428Ш0428Ш0428042804280428Ш0428() + b044Cь044C044Cь044Cь044Cь) * b0428Ш0428Ш0428042804280428Ш0428() % bь044C044C044Cь044Cь044Cь != bьь044C044Cь044Cь044Cь)
    {
      b044C044Cь044Cь044Cь044Cь = b0428Ш0428Ш0428042804280428Ш0428();
      bьь044C044Cь044Cь044Cь = b0428Ш0428Ш0428042804280428Ш0428();
    }
    this.b044C044Cььь044Cь044Cь.b0428ШШ0428Ш0428Ш0428Ш0428();
  }
  
  public void b04280428Ш0428Ш04280428ШШ0428(String paramString1, String paramString2, String paramString3, long paramLong1, long paramLong2)
  {
    for (;;)
    {
      try
      {
        localObject = xxdxxd.instance.bххх044504450445х044504450445();
        if (this.b044Cьь044Cь044Cь044Cь)
        {
          xtxtxt.bии0438и04380438и0438ии(bььь044C044Cьь044Cь, gguuuu.bккккк043Aкк043A043A("__K[\\<VQSDF1HNRL\026zOIDF79=A9p@7=A;j?<15-d%b5&25' !", '', '\005'));
          localIntent = new Intent((Context)localObject, BackgroundActionsService.class);
          str = gguuuu.bк043Aккк043Aкк043A043A("Ugb_MJ^bXL", '', 'ü', '\002');
        }
      }
      catch (Exception paramString1)
      {
        Object localObject;
        Intent localIntent;
        String str;
        int i;
        int j;
        int k;
        int m;
        int n;
        throw paramString1;
      }
      try
      {
        localIntent.putExtra(str, 2);
        localIntent.putExtra(gguuuu.bккккк043Aкк043A043A("K>LQE@C>EYVUEDHYIWNJUQ", 'Ö', '\000'), paramString1);
        localIntent.putExtra(gguuuu.bккккк043Aкк043A043A("}nz}ohibgytq_\\p\\l`]kU^X", 'u', '\005'), paramString2);
        localIntent.putExtra(gguuuu.bк043Aккк043Aкк043A043A("^Q_dXSVQXlihXWbg\\cb]trj", ']', '', '\003'), paramString3);
        if ((b044C044Cь044Cь044Cь044Cь + b044Cь044C044Cь044Cь044Cь) * b044C044Cь044Cь044Cь044Cь % bь044C044C044Cь044Cь044Cь != bьь044C044Cь044Cь044Cь)
        {
          b044C044Cь044Cь044Cь044Cь = 41;
          bьь044C044Cь044Cь044Cь = b0428Ш0428Ш0428042804280428Ш0428();
        }
      }
      catch (Exception paramString1)
      {
        throw paramString1;
      }
    }
    localIntent.putExtra(gguuuu.bккккк043Aкк043A043A("\023\006\024\031\r\b\013\006\r!\036\035\r\f\024\030\034\026\021%#,\025 \034", '', '\000'), paramLong2);
    localIntent.putExtra(gguuuu.bккккк043Aкк043A043A("UFRUG@A:?QLI74A8ED163,>:A(1+", '\036', '\005'), paramLong1);
    ((Context)localObject).startService(localIntent);
    i = b044C044Cь044Cь044Cь044Cь;
    j = b044Cь044C044Cь044Cь044Cь;
    k = b044C044Cь044Cь044Cь044Cь;
    m = bь044C044C044Cь044Cь044Cь;
    n = bьь044C044Cь044Cь044Cь;
    if ((i + j) * k % m != n)
    {
      b044C044Cь044Cь044Cь044Cь = b0428Ш0428Ш0428042804280428Ш0428();
      bьь044C044Cь044Cь044Cь = b0428Ш0428Ш0428042804280428Ш0428();
      return;
      localObject = this.bь044Cь044Cь044Cь044Cь;
      ((ykykyy)localObject).bШШШШ04280428Ш042804280428(paramString1, paramString2, paramString3, paramLong1, paramLong2, new kkyykk.6(this));
      return;
      switch (0)
      {
      }
      for (;;)
      {
        switch (0)
        {
        }
      }
    }
  }
  
  public void b04280428Ш0428ШШШ0428Ш0428(String paramString1, String paramString2, nnnnnf.ffnnnf paramFfnnnf, nnnnnf.nfnnnf paramNfnnnf)
  {
    paramString1 = this.b044C044Cь044C044Cьь044Cь.b0442т0442044204420442т04420442.bээ044Dэээ044D044D044Dэ(paramString1);
    if (paramString1 == null)
    {
      xtxtxt.bиии043804380438и0438ии(bььь044C044Cьь044Cь, gguuuu.bк043Aккк043Aкк043A043A("eY`\030nj_]qc\037mfuvelk4(oy}y-r~u\0052\002\004\n6|\021\003\016\020\020=\016\022@\005\017\023\030\013\013U", 'D', 'Î', '\001'));
      return;
    }
    do
    {
      paramString2 = new ArrayList();
      paramString2.add(paramString1.bээээ044D044Dэ044D044Dэ());
      paramFfnnnf = bььь044C044Cьь044Cь;
      Object localObject = new StringBuilder();
      if ((b044C044Cь044Cь044Cь044Cь + b044Cь044C044Cь044Cь044Cь) * b044C044Cь044Cь044Cь044Cь % bь044C044C044Cь044Cь044Cь != bьь044C044Cь044Cь044Cь)
      {
        b044C044Cь044Cь044Cь044Cь = b0428Ш0428Ш0428042804280428Ш0428();
        bьь044C044Cь044Cь044Cь = b0428Ш0428Ш0428042804280428Ш0428();
      }
      localObject = gguuuu.bккккк043Aкк043A043A("UGL\002VPC?QAzG>KJ7<9qH9C6l1A/7<\020\nd", 'Ì', '\003') + paramString1.bээээ044D044Dэ044D044Dэ() + gguuuu.bк043Aккк043Aкк043A043A("({u%wwcue9\036", '¥', 'Q', '\002') + paramNfnnnf;
      if ((b044C044Cь044Cь044Cь044Cь + bШШ0428Ш0428042804280428Ш0428()) * b044C044Cь044Cь044Cь044Cь % bь044C044C044Cь044Cь044Cь != bьь044C044Cь044Cь044Cь)
      {
        switch (0)
        {
        case 1: 
        default: 
          for (;;)
          {
            switch (1)
            {
            }
          }
        }
        b044C044Cь044Cь044Cь044Cь = 77;
        bьь044C044Cь044Cь044Cь = b0428Ш0428Ш0428042804280428Ш0428();
      }
      xtxtxt.bиии043804380438и0438ии(paramFfnnnf, (String)localObject);
      this.b044C044Cь044C044Cьь044Cь.bэ044D044D044D044Dэээ044Dэ(paramString2, paramString1.b044Dээ044D044D044Dэ044D044Dэ(), paramString1.b044D044D044D044Dэ044Dэ044D044Dэ(), paramNfnnnf);
      return;
      paramString2 = this.b044Cьь044C044Cьь044Cь.bФФ0424Ф042404240424042404240424(paramString2);
    } while ((paramString2 != null) && (paramString2.b044Dээ044D044Dэ044Dэ044Dэ() != dxdxdd.CLOSE));
    xtxtxt.bиии043804380438и0438ии(bььь044C044Cьь044Cь, gguuuu.bккккк043Aкк043A043A("\b{\003:\021\r\002\024\006A\020\t\030\031\b\017\016VJ\017\034\034%\025#%\024(\036%%W\035) /\\,.4`';-8::g8<j/9=B55", '2', '\001'));
  }
  
  public void b04280428Ш0428ШШШШ04280428(Notification.Builder paramBuilder)
  {
    int i = b044C044Cь044Cь044Cь044Cь;
    switch (i * (b044Cь044C044Cь044Cь044Cь + i) % bь044C044C044Cь044Cь044Cь)
    {
    default: 
      b044C044Cь044Cь044Cь044Cь = b0428Ш0428Ш0428042804280428Ш0428();
      bьь044C044Cь044Cь044Cь = b0428Ш0428Ш0428042804280428Ш0428();
    }
    i = b044C044Cь044Cь044Cь044Cь;
    switch (i * (b044Cь044C044Cь044Cь044Cь + i) % b0428ШШШ0428042804280428Ш0428())
    {
    default: 
      b044C044Cь044Cь044Cь044Cь = 71;
      switch (1)
      {
      case 0: 
      default: 
        for (;;)
        {
          switch (1)
          {
          }
        }
      }
      bьь044C044Cь044Cь044Cь = b0428Ш0428Ш0428042804280428Ш0428();
    }
    switch (0)
    {
    case 1: 
    default: 
      for (;;)
      {
        switch (0)
        {
        }
      }
    }
    this.bьь044Cьь044Cь044Cь = paramBuilder;
  }
  
  /* Error */
  public void b04280428ШШ0428042804280428Ш0428()
  {
    // Byte code:
    //   0: invokestatic 541	kkkkkk/mrmrmm:bШ04280428Ш0428Ш0428ШШШ	()Lkkkkkk/mrmrmm;
    //   3: astore 4
    //   5: aload 4
    //   7: new 543	kkkkkk/hbhbhh
    //   10: dup
    //   11: aload_0
    //   12: invokespecial 544	kkkkkk/hbhbhh:<init>	(Lkkkkkk/kkyykk;)V
    //   15: invokevirtual 548	kkkkkk/mrmrmm:b04280428Ш04280428Ш0428ШШШ	(Lkkkkkk/mrmrrm;)V
    //   18: invokestatic 96	kkkkkk/kkyykk:b0428Ш0428Ш0428042804280428Ш0428	()I
    //   21: istore_1
    //   22: getstatic 88	kkkkkk/kkyykk:b044Cь044C044Cь044Cь044Cь	I
    //   25: istore_2
    //   26: getstatic 90	kkkkkk/kkyykk:bь044C044C044Cь044Cь044Cь	I
    //   29: istore_3
    //   30: iconst_1
    //   31: tableswitch	default:+21->52, 0:+-1->30, 1:+48->79
    //   52: iconst_0
    //   53: tableswitch	default:+23->76, 0:+26->79, 1:+-23->30
    //   76: goto -24 -> 52
    //   79: iload_1
    //   80: iload_2
    //   81: iload_1
    //   82: iadd
    //   83: imul
    //   84: iload_3
    //   85: irem
    //   86: tableswitch	default:+18->104, 0:+61->147
    //   104: invokestatic 96	kkkkkk/kkyykk:b0428Ш0428Ш0428042804280428Ш0428	()I
    //   107: putstatic 86	kkkkkk/kkyykk:b044C044Cь044Cь044Cь044Cь	I
    //   110: bipush 86
    //   112: putstatic 92	kkkkkk/kkyykk:bьь044C044Cь044Cь044Cь	I
    //   115: getstatic 86	kkkkkk/kkyykk:b044C044Cь044Cь044Cь044Cь	I
    //   118: getstatic 88	kkkkkk/kkyykk:b044Cь044C044Cь044Cь044Cь	I
    //   121: iadd
    //   122: getstatic 86	kkkkkk/kkyykk:b044C044Cь044Cь044Cь044Cь	I
    //   125: imul
    //   126: getstatic 90	kkkkkk/kkyykk:bь044C044C044Cь044Cь044Cь	I
    //   129: irem
    //   130: getstatic 92	kkkkkk/kkyykk:bьь044C044Cь044Cь044Cь	I
    //   133: if_icmpeq +14 -> 147
    //   136: bipush 46
    //   138: putstatic 86	kkkkkk/kkyykk:b044C044Cь044Cь044Cь044Cь	I
    //   141: invokestatic 96	kkkkkk/kkyykk:b0428Ш0428Ш0428042804280428Ш0428	()I
    //   144: putstatic 92	kkkkkk/kkyykk:bьь044C044Cь044Cь044Cь	I
    //   147: return
    //   148: astore 4
    //   150: aload 4
    //   152: athrow
    //   153: astore 4
    //   155: aload 4
    //   157: athrow
    // Local variable table:
    //   start	length	slot	name	signature
    //   0	158	0	this	kkyykk
    //   21	63	1	i	int
    //   25	58	2	j	int
    //   29	57	3	k	int
    //   3	3	4	localMrmrmm	mrmrmm
    //   148	3	4	localException1	Exception
    //   153	3	4	localException2	Exception
    // Exception table:
    //   from	to	target	type
    //   0	5	148	java/lang/Exception
    //   5	18	153	java/lang/Exception
  }
  
  public void b04280428ШШ042804280428ШШ0428(Context paramContext, kyykky paramKyykky, dxxxdx paramDxxxdx)
  {
    bШШ0428Ш042804280428ШШ0428(paramContext, paramKyykky, new kkyykk.16(this, paramDxxxdx));
    int i = b044C044Cь044Cь044Cь044Cь;
    switch (i * (bШШ0428Ш0428042804280428Ш0428() + i) % bь044C044C044Cь044Cь044Cь)
    {
    default: 
      b044C044Cь044Cь044Cь044Cь = 95;
      bьь044C044Cь044Cь044Cь = 33;
    }
  }
  
  public void b04280428ШШШШШ0428Ш0428(String paramString1, String paramString2, String paramString3)
  {
    for (;;)
    {
      try
      {
        i = b044C044Cь044Cь044Cь044Cь;
        j = bШШ0428Ш0428042804280428Ш0428();
      }
      catch (Exception paramString1)
      {
        int i;
        int j;
        throw paramString1;
      }
      try
      {
        if ((i + j) * b044C044Cь044Cь044Cь044Cь % bь044C044C044Cь044Cь044Cь != bьь044C044Cь044Cь044Cь)
        {
          b044C044Cь044Cь044Cь044Cь = b0428Ш0428Ш0428042804280428Ш0428();
          bьь044C044Cь044Cь044Cь = b0428Ш0428Ш0428042804280428Ш0428();
          if ((b044C044Cь044Cь044Cь044Cь + bШШ0428Ш0428042804280428Ш0428()) * b044C044Cь044Cь044Cь044Cь % bь044C044C044Cь044Cь044Cь != bьь044C044Cь044Cь044Cь)
          {
            b044C044Cь044Cь044Cь044Cь = 56;
            bьь044C044Cь044Cь044Cь = 75;
          }
        }
        paramString1 = new yyyyjj(this, paramString1, paramString2, bШШ042804280428042804280428Ш0428(paramString2).bШ04280428042804280428042804280428Ш(paramString3));
      }
      catch (Exception paramString1)
      {
        throw paramString1;
      }
    }
    paramString1.bххххххх044504450445();
    return;
    switch (1)
    {
    }
    for (;;)
    {
      switch (1)
      {
      }
    }
  }
  
  public boolean b04280428ШШШШШШ04280428(String paramString)
  {
    int i = b044C044Cь044Cь044Cь044Cь;
    switch (i * (b044Cь044C044Cь044Cь044Cь + i) % bь044C044C044Cь044Cь044Cь)
    {
    default: 
      b044C044Cь044Cь044Cь044Cь = b0428Ш0428Ш0428042804280428Ш0428();
      bьь044C044Cь044Cь044Cь = 9;
    }
    try
    {
      paramString = this.b044Cьь044C044Cьь044Cь.bФФ0424Ф042404240424042404240424(paramString);
      if ((paramString == null) || (paramString.b044Dээ044D044Dэ044Dэ044Dэ() == dxdxdd.CLOSE)) {
        paramString = bььь044C044Cьь044Cь;
      }
    }
    catch (Exception paramString)
    {
      boolean bool;
      throw paramString;
    }
    try
    {
      xtxtxt.bии0438и04380438и0438ии(paramString, gguuuu.bккккк043Aкк043A043A("\035(x&&/\037-/\0362(//\005/38++th-::C3AC2F<CCu;G>MzJLR~EYKVXX\006VZ\tMW[`SS\036", 'Y', '\004'));
      bool = true;
      return bool;
    }
    catch (Exception paramString)
    {
      throw paramString;
    }
    bool = false;
    for (;;)
    {
      try
      {
        i = b044C044Cь044Cь044Cь044Cь;
        switch (i * (b044Cь044C044Cь044Cь044Cь + i) % bь044C044C044Cь044Cь044Cь)
        {
        case 0: 
          b044C044Cь044Cь044Cь044Cь = 2;
          bьь044C044Cь044Cь044Cь = b0428Ш0428Ш0428042804280428Ш0428();
          return false;
        }
      }
      catch (Exception paramString)
      {
        throw paramString;
      }
    }
  }
  
  /* Error */
  public mmcmmc b0428Ш042804280428042804280428Ш0428()
  {
    // Byte code:
    //   0: getstatic 86	kkkkkk/kkyykk:b044C044Cь044Cь044Cь044Cь	I
    //   3: istore_1
    //   4: getstatic 88	kkkkkk/kkyykk:b044Cь044C044Cь044Cь044Cь	I
    //   7: istore_2
    //   8: getstatic 86	kkkkkk/kkyykk:b044C044Cь044Cь044Cь044Cь	I
    //   11: istore_3
    //   12: getstatic 90	kkkkkk/kkyykk:bь044C044C044Cь044Cь044Cь	I
    //   15: istore 4
    //   17: getstatic 92	kkkkkk/kkyykk:bьь044C044Cь044Cь044Cь	I
    //   20: istore 5
    //   22: iload_1
    //   23: iload_2
    //   24: iadd
    //   25: iload_3
    //   26: imul
    //   27: iload 4
    //   29: irem
    //   30: iload 5
    //   32: if_icmpeq +13 -> 45
    //   35: bipush 52
    //   37: putstatic 86	kkkkkk/kkyykk:b044C044Cь044Cь044Cь044Cь	I
    //   40: bipush 6
    //   42: putstatic 92	kkkkkk/kkyykk:bьь044C044Cь044Cь044Cь	I
    //   45: aload_0
    //   46: getfield 225	kkkkkk/kkyykk:bььь044Cь044Cь044Cь	Lkkkkkk/mmcmmc;
    //   49: astore 6
    //   51: aload 6
    //   53: areturn
    //   54: astore 6
    //   56: aload 6
    //   58: athrow
    //   59: astore 6
    //   61: aload 6
    //   63: athrow
    // Local variable table:
    //   start	length	slot	name	signature
    //   0	64	0	this	kkyykk
    //   3	22	1	i	int
    //   7	18	2	j	int
    //   11	16	3	k	int
    //   15	15	4	m	int
    //   20	13	5	n	int
    //   49	3	6	localMmcmmc	mmcmmc
    //   54	3	6	localException1	Exception
    //   59	3	6	localException2	Exception
    // Exception table:
    //   from	to	target	type
    //   0	22	54	java/lang/Exception
    //   45	51	54	java/lang/Exception
    //   35	45	59	java/lang/Exception
  }
  
  public int b0428Ш04280428042804280428ШШ0428(String paramString1, String paramString2, long paramLong, nnnnnf.ffnnnf paramFfnnnf)
  {
    do
    {
      try
      {
        if (b04280428ШШШШШШ04280428(paramString2))
        {
          paramString1 = bььь044C044Cьь044Cь;
          xtxtxt.bиии043804380438и0438ии(paramString1, gguuuu.bк043Aккк043Aкк043A043A("y\f\031\n\022\007A\016\005\022\021}\003F8z\006\004\013x\005\005q\004w|z+nxmz&ssw\"fxhqqo\033ik\030ZbdgXV\037", 'V', 'ü', '\000'));
          return R.string.lp_resend_failed_conversation_closed;
          localObject = this.b044C044Cь044C044Cьь044Cь;
          if ((b044C044Cь044Cь044Cь044Cь + bШШ0428Ш0428042804280428Ш0428()) * b044C044Cь044Cь044Cь044Cь % bь044C044C044Cь044Cь044Cь != bьь044C044Cь044Cь044Cь)
          {
            b044C044Cь044Cь044Cь044Cь = 70;
            bьь044C044Cь044Cь044Cь = b0428Ш0428Ш0428042804280428Ш0428();
          }
        }
      }
      catch (Exception paramString1)
      {
        Object localObject;
        int i;
        throw paramString1;
      }
      try
      {
        localObject = ((ggggga)localObject).bээ044D044Dэ044D044D044Dээ(paramString1);
        paramString1 = new kkyykk.3(this, paramString2, paramFfnnnf, paramString1, paramLong);
        i = b044C044Cь044Cь044Cь044Cь;
        switch (i * (b044Cь044C044Cь044Cь044Cь + i) % bь044C044C044Cь044Cь044Cь)
        {
        default: 
          b044C044Cь044Cь044Cь044Cь = b0428Ш0428Ш0428042804280428Ш0428();
          bьь044C044Cь044Cь044Cь = 58;
        }
        ((xddxxx)localObject).b04380438и0438ии0438иии(paramString1).b0438ии0438ии0438иии();
        return -1;
      }
      catch (Exception paramString1)
      {
        throw paramString1;
      }
    } while (!nnnnnf.ffnnnf.bэээээээээ044D(paramFfnnnf));
    xtxtxt.bиии043804380438и0438ии(bььь044C044Cьь044Cь, gguuuu.bккккк043Aкк043A043A("}\022!\024\036\025Q \031()\030\037\036fZ)\"12!('b-8e4)<500xmA5D7A8t?JwGIO{>T@IMCEPJ\024", 'U', '\004'));
    i = R.string.lp_resend_failed_masked_message;
    return i;
  }
  
  public bhhbbh b0428Ш04280428Ш04280428ШШ0428(String paramString1, String paramString2)
  {
    if ((b044C044Cь044Cь044Cь044Cь + b044Cь044C044Cь044Cь044Cь) * b044C044Cь044Cь044Cь044Cь % bь044C044C044Cь044Cь044Cь != bьь044C044Cь044Cь044Cь)
    {
      b044C044Cь044Cь044Cь044Cь = b0428Ш0428Ш0428042804280428Ш0428();
      bьь044C044Cь044Cь044Cь = b0428Ш0428Ш0428042804280428Ш0428();
    }
    paramString1 = bШШ042804280428042804280428Ш0428(paramString1).bШ04280428042804280428042804280428Ш(paramString2);
    int i = b044C044Cь044Cь044Cь044Cь;
    switch (i * (bШШ0428Ш0428042804280428Ш0428() + i) % bь044C044C044Cь044Cь044Cь)
    {
    default: 
      b044C044Cь044Cь044Cь044Cь = 59;
      bьь044C044Cь044Cь044Cь = b0428Ш0428Ш0428042804280428Ш0428();
    }
    return paramString1;
  }
  
  /* Error */
  public void b0428Ш04280428ШШШШ04280428(PendingIntent paramPendingIntent)
  {
    // Byte code:
    //   0: getstatic 86	kkkkkk/kkyykk:b044C044Cь044Cь044Cь044Cь	I
    //   3: getstatic 88	kkkkkk/kkyykk:b044Cь044C044Cь044Cь044Cь	I
    //   6: iadd
    //   7: getstatic 86	kkkkkk/kkyykk:b044C044Cь044Cь044Cь044Cь	I
    //   10: imul
    //   11: getstatic 90	kkkkkk/kkyykk:bь044C044C044Cь044Cь044Cь	I
    //   14: irem
    //   15: getstatic 92	kkkkkk/kkyykk:bьь044C044Cь044Cь044Cь	I
    //   18: if_icmpeq +13 -> 31
    //   21: invokestatic 96	kkkkkk/kkyykk:b0428Ш0428Ш0428042804280428Ш0428	()I
    //   24: putstatic 86	kkkkkk/kkyykk:b044C044Cь044Cь044Cь044Cь	I
    //   27: iconst_0
    //   28: putstatic 92	kkkkkk/kkyykk:bьь044C044Cь044Cь044Cь	I
    //   31: aload_0
    //   32: aload_1
    //   33: putfield 112	kkkkkk/kkyykk:bь044C044Cьь044Cь044Cь	Landroid/app/PendingIntent;
    //   36: getstatic 86	kkkkkk/kkyykk:b044C044Cь044Cь044Cь044Cь	I
    //   39: istore_2
    //   40: getstatic 88	kkkkkk/kkyykk:b044Cь044C044Cь044Cь044Cь	I
    //   43: istore_3
    //   44: getstatic 90	kkkkkk/kkyykk:bь044C044C044Cь044Cь044Cь	I
    //   47: istore 4
    //   49: iload_2
    //   50: iload_3
    //   51: iload_2
    //   52: iadd
    //   53: imul
    //   54: iload 4
    //   56: irem
    //   57: tableswitch	default:+19->76, 0:+30->87
    //   76: bipush 10
    //   78: putstatic 86	kkkkkk/kkyykk:b044C044Cь044Cь044Cь044Cь	I
    //   81: invokestatic 96	kkkkkk/kkyykk:b0428Ш0428Ш0428042804280428Ш0428	()I
    //   84: putstatic 92	kkkkkk/kkyykk:bьь044C044Cь044Cь044Cь	I
    //   87: return
    //   88: astore_1
    //   89: aload_1
    //   90: athrow
    //   91: astore_1
    //   92: aload_1
    //   93: athrow
    //   94: astore_1
    //   95: aload_1
    //   96: athrow
    // Local variable table:
    //   start	length	slot	name	signature
    //   0	97	0	this	kkyykk
    //   0	97	1	paramPendingIntent	PendingIntent
    //   39	15	2	i	int
    //   43	10	3	j	int
    //   47	10	4	k	int
    // Exception table:
    //   from	to	target	type
    //   31	36	88	java/lang/Exception
    //   36	49	91	java/lang/Exception
    //   89	91	91	java/lang/Exception
    //   76	87	94	java/lang/Exception
  }
  
  public bbhbhh b0428Ш0428Ш042804280428ШШ0428(String paramString1, String paramString2)
  {
    bbhbhh localBbhbhh = bШ04280428Ш0428042804280428Ш0428(paramString1, paramString2);
    if (localBbhbhh != null) {}
    for (paramString1 = localBbhbhh;; paramString1 = null)
    {
      if ((b044C044Cь044Cь044Cь044Cь + bШШ0428Ш0428042804280428Ш0428()) * b044C044Cь044Cь044Cь044Cь % bь044C044C044Cь044Cь044Cь != bьь044C044Cь044Cь044Cь)
      {
        if ((b044C044Cь044Cь044Cь044Cь + b044Cь044C044Cь044Cь044Cь) * b044C044Cь044Cь044Cь044Cь % bь044C044C044Cь044Cь044Cь != bьь044C044Cь044Cь044Cь)
        {
          b044C044Cь044Cь044Cь044Cь = 9;
          bьь044C044Cь044Cь044Cь = 62;
        }
        b044C044Cь044Cь044Cь044Cь = 22;
        bьь044C044Cь044Cь044Cь = b0428Ш0428Ш0428042804280428Ш0428();
      }
      return paramString1;
      new yjyyjy(this.b044Cьь044C044Cьь044Cь, paramString1, this.bь044C044C044C044Cьь044Cь.b0424ФФ042404240424Ф04240424Ф(paramString2), xdxxdd.NORMAL).bххххххх044504450445();
      switch (0)
      {
      case 1: 
      default: 
        for (;;)
        {
          switch (1)
          {
          }
        }
      }
    }
  }
  
  public void b0428Ш0428ШШ04280428ШШ0428(String paramString, dddxxd<Boolean, Exception> paramDddxxd)
  {
    switch (1)
    {
    case 0: 
    default: 
      for (;;)
      {
        switch (0)
        {
        }
      }
    }
    switch (1)
    {
    case 0: 
    default: 
      for (;;)
      {
        switch (0)
        {
        }
      }
    }
    paramString = this.b044Cьь044C044Cьь044Cь.bФ042404240424Ф04240424042404240424(paramString);
    paramDddxxd = new kkyykk.9(this, paramDddxxd);
    int i = b044C044Cь044Cь044Cь044Cь;
    int j = b0428Ш0428Ш0428042804280428Ш0428();
    switch (j * (bШШ0428Ш0428042804280428Ш0428() + j) % bь044C044C044Cь044Cь044Cь)
    {
    default: 
      b044C044Cь044Cь044Cь044Cь = 91;
      bьь044C044Cь044Cь044Cь = b0428Ш0428Ш0428042804280428Ш0428();
    }
    if ((i + bШШ0428Ш0428042804280428Ш0428()) * b044C044Cь044Cь044Cь044Cь % bь044C044C044Cь044Cь044Cь != bьь044C044Cь044Cь044Cь)
    {
      b044C044Cь044Cь044Cь044Cь = 19;
      bьь044C044Cь044Cь044Cь = b0428Ш0428Ш0428042804280428Ш0428();
    }
    paramString.b04380438и0438ии0438иии(paramDddxxd).b0438ии0438ии0438иии();
  }
  
  /* Error */
  public void b0428Ш0428ШШШШ0428Ш0428(String paramString, fnnnff paramFnnnff)
  {
    // Byte code:
    //   0: new 637	kkkkkk/jyjyjj
    //   3: dup
    //   4: aload_0
    //   5: aload_1
    //   6: aload_2
    //   7: invokespecial 640	kkkkkk/jyjyjj:<init>	(Lkkkkkk/kkyykk;Ljava/lang/String;Lkkkkkk/fnnnff;)V
    //   10: astore_1
    //   11: aload_1
    //   12: invokevirtual 641	kkkkkk/jyjyjj:bххххххх044504450445	()V
    //   15: getstatic 86	kkkkkk/kkyykk:b044C044Cь044Cь044Cь044Cь	I
    //   18: istore_3
    //   19: getstatic 88	kkkkkk/kkyykk:b044Cь044C044Cь044Cь044Cь	I
    //   22: istore 4
    //   24: getstatic 90	kkkkkk/kkyykk:bь044C044C044Cь044Cь044Cь	I
    //   27: istore 5
    //   29: iload_3
    //   30: iload 4
    //   32: iload_3
    //   33: iadd
    //   34: imul
    //   35: iload 5
    //   37: irem
    //   38: tableswitch	default:+18->56, 0:+62->100
    //   56: invokestatic 96	kkkkkk/kkyykk:b0428Ш0428Ш0428042804280428Ш0428	()I
    //   59: putstatic 86	kkkkkk/kkyykk:b044C044Cь044Cь044Cь044Cь	I
    //   62: invokestatic 96	kkkkkk/kkyykk:b0428Ш0428Ш0428042804280428Ш0428	()I
    //   65: istore_3
    //   66: getstatic 86	kkkkkk/kkyykk:b044C044Cь044Cь044Cь044Cь	I
    //   69: getstatic 88	kkkkkk/kkyykk:b044Cь044C044Cь044Cь044Cь	I
    //   72: iadd
    //   73: getstatic 86	kkkkkk/kkyykk:b044C044Cь044Cь044Cь044Cь	I
    //   76: imul
    //   77: getstatic 90	kkkkkk/kkyykk:bь044C044C044Cь044Cь044Cь	I
    //   80: irem
    //   81: invokestatic 643	kkkkkk/kkyykk:bШ0428ШШ0428042804280428Ш0428	()I
    //   84: if_icmpeq +12 -> 96
    //   87: iconst_5
    //   88: putstatic 86	kkkkkk/kkyykk:b044C044Cь044Cь044Cь044Cь	I
    //   91: bipush 18
    //   93: putstatic 92	kkkkkk/kkyykk:bьь044C044Cь044Cь044Cь	I
    //   96: iload_3
    //   97: putstatic 92	kkkkkk/kkyykk:bьь044C044Cь044Cь044Cь	I
    //   100: return
    //   101: astore_1
    //   102: aload_1
    //   103: athrow
    //   104: astore_1
    //   105: aload_1
    //   106: athrow
    //   107: astore_1
    //   108: aload_1
    //   109: athrow
    // Local variable table:
    //   start	length	slot	name	signature
    //   0	110	0	this	kkyykk
    //   0	110	1	paramString	String
    //   0	110	2	paramFnnnff	fnnnff
    //   18	79	3	i	int
    //   22	12	4	j	int
    //   27	11	5	k	int
    // Exception table:
    //   from	to	target	type
    //   11	15	101	java/lang/Exception
    //   0	11	104	java/lang/Exception
    //   15	24	104	java/lang/Exception
    //   56	62	104	java/lang/Exception
    //   102	104	104	java/lang/Exception
    //   24	29	107	java/lang/Exception
    //   62	66	107	java/lang/Exception
    //   96	100	107	java/lang/Exception
  }
  
  public Notification.Builder b0428ШШ04280428042804280428Ш0428()
  {
    if ((b044C044Cь044Cь044Cь044Cь + bШШ0428Ш0428042804280428Ш0428()) * b044C044Cь044Cь044Cь044Cь % bь044C044C044Cь044Cь044Cь != bьь044C044Cь044Cь044Cь)
    {
      b044C044Cь044Cь044Cь044Cь = 57;
      bьь044C044Cь044Cь044Cь = b0428Ш0428Ш0428042804280428Ш0428();
    }
    return this.b044Cь044Cьь044Cь044Cь;
  }
  
  /* Error */
  public void b0428ШШ0428042804280428ШШ0428(String paramString, LPAuthenticationParams paramLPAuthenticationParams)
  {
    // Byte code:
    //   0: getstatic 106	kkkkkk/kkyykk:bььь044C044Cьь044Cь	Ljava/lang/String;
    //   3: astore_3
    //   4: new 419	java/lang/StringBuilder
    //   7: dup
    //   8: invokespecial 420	java/lang/StringBuilder:<init>	()V
    //   11: ldc_w 649
    //   14: bipush 117
    //   16: iconst_5
    //   17: invokestatic 84	kkkkkk/gguuuu:bккккк043Aкк043A043A	(Ljava/lang/String;CC)Ljava/lang/String;
    //   20: invokevirtual 426	java/lang/StringBuilder:append	(Ljava/lang/String;)Ljava/lang/StringBuilder;
    //   23: aload_1
    //   24: invokevirtual 426	java/lang/StringBuilder:append	(Ljava/lang/String;)Ljava/lang/StringBuilder;
    //   27: ldc_w 651
    //   30: sipush 181
    //   33: bipush 23
    //   35: iconst_0
    //   36: invokestatic 78	kkkkkk/gguuuu:bк043Aккк043Aкк043A043A	(Ljava/lang/String;CCC)Ljava/lang/String;
    //   39: invokevirtual 426	java/lang/StringBuilder:append	(Ljava/lang/String;)Ljava/lang/StringBuilder;
    //   42: astore 4
    //   44: aload_3
    //   45: aload 4
    //   47: aload_2
    //   48: invokevirtual 505	java/lang/StringBuilder:append	(Ljava/lang/Object;)Ljava/lang/StringBuilder;
    //   51: invokevirtual 429	java/lang/StringBuilder:toString	()Ljava/lang/String;
    //   54: invokestatic 281	kkkkkk/xtxtxt:bии0438и04380438и0438ии	(Ljava/lang/String;Ljava/lang/String;)V
    //   57: aload_0
    //   58: getfield 176	kkkkkk/kkyykk:bь044C044C044C044Cьь044Cь	Lkkkkkk/cmmmcc;
    //   61: aload_1
    //   62: aconst_null
    //   63: invokevirtual 654	kkkkkk/cmmmcc:b042404240424ФФФ042404240424Ф	(Ljava/lang/String;Ljava/lang/String;)V
    //   66: getstatic 86	kkkkkk/kkyykk:b044C044Cь044Cь044Cь044Cь	I
    //   69: getstatic 88	kkkkkk/kkyykk:b044Cь044C044Cь044Cь044Cь	I
    //   72: iadd
    //   73: getstatic 86	kkkkkk/kkyykk:b044C044Cь044Cь044Cь044Cь	I
    //   76: imul
    //   77: getstatic 90	kkkkkk/kkyykk:bь044C044C044Cь044Cь044Cь	I
    //   80: irem
    //   81: invokestatic 643	kkkkkk/kkyykk:bШ0428ШШ0428042804280428Ш0428	()I
    //   84: if_icmpeq +14 -> 98
    //   87: bipush 33
    //   89: putstatic 86	kkkkkk/kkyykk:b044C044Cь044Cь044Cь044Cь	I
    //   92: invokestatic 96	kkkkkk/kkyykk:b0428Ш0428Ш0428042804280428Ш0428	()I
    //   95: putstatic 92	kkkkkk/kkyykk:bьь044C044Cь044Cь044Cь	I
    //   98: aload_0
    //   99: aload_1
    //   100: aload_2
    //   101: aconst_null
    //   102: invokevirtual 658	kkkkkk/kkyykk:b0428ШШ0428Ш04280428ШШ0428	(Ljava/lang/String;Lcom/liveperson/infra/LPAuthenticationParams;Lcom/liveperson/infra/ConversationViewParams;)V
    //   105: return
    //   106: astore_1
    //   107: aload_1
    //   108: athrow
    //   109: astore_1
    //   110: aload_1
    //   111: athrow
    // Local variable table:
    //   start	length	slot	name	signature
    //   0	112	0	this	kkyykk
    //   0	112	1	paramString	String
    //   0	112	2	paramLPAuthenticationParams	LPAuthenticationParams
    //   3	42	3	str	String
    //   42	4	4	localStringBuilder	StringBuilder
    // Exception table:
    //   from	to	target	type
    //   0	44	106	java/lang/Exception
    //   98	105	106	java/lang/Exception
    //   44	66	109	java/lang/Exception
  }
  
  public void b0428ШШ0428Ш04280428ШШ0428(String paramString, LPAuthenticationParams paramLPAuthenticationParams, @Nullable ConversationViewParams paramConversationViewParams)
  {
    try
    {
      bШШШШШШШШ04280428(paramString, paramLPAuthenticationParams, paramConversationViewParams);
      paramLPAuthenticationParams = bььь044C044Cьь044Cь;
      paramConversationViewParams = gguuuu.bк043Aккк043Aкк043A043A("\020==>65G=C=vLHy=N>LC", 'Ç', '', '\003') + paramString;
    }
    catch (Exception paramString)
    {
      try
      {
        int j;
        int k;
        int m;
        int n;
        b044C044Cь044Cь044Cь044Cь = b0428Ш0428Ш0428042804280428Ш0428();
        bьь044C044Cь044Cь044Cь = b0428Ш0428Ш0428042804280428Ш0428();
        int i = b044C044Cь044Cь044Cь044Cь;
        switch (i * (b044Cь044C044Cь044Cь044Cь + i) % bь044C044C044Cь044Cь044Cь)
        {
        default: 
          b044C044Cь044Cь044Cь044Cь = 90;
          bьь044C044Cь044Cь044Cь = 50;
        }
        xtxtxt.bии0438и04380438и0438ии(paramLPAuthenticationParams, paramConversationViewParams);
        paramLPAuthenticationParams = this.bььььь044Cь044Cь;
        paramLPAuthenticationParams.b0424ФФ042404240424042404240424Ф(paramString);
        return;
      }
      catch (Exception paramString)
      {
        throw paramString;
      }
      paramString = paramString;
      throw paramString;
    }
    i = b044C044Cь044Cь044Cь044Cь;
    j = bШШ0428Ш0428042804280428Ш0428();
    k = b044C044Cь044Cь044Cь044Cь;
    m = bь044C044C044Cь044Cь044Cь;
    n = bШ0428ШШ0428042804280428Ш0428();
    if ((i + j) * k % m != n) {}
    switch (1)
    {
    }
    for (;;)
    {
      switch (0)
      {
      }
    }
  }
  
  public void b0428ШШ0428ШШШ0428Ш0428(ovooov paramOvooov)
  {
    xxdxxd localXxdxxd = xxdxxd.instance;
    if ((b044C044Cь044Cь044Cь044Cь + b044Cь044C044Cь044Cь044Cь) * b044C044Cь044Cь044Cь044Cь % bь044C044C044Cь044Cь044Cь != bьь044C044Cь044Cь044Cь)
    {
      int i = b0428Ш0428Ш0428042804280428Ш0428();
      switch (i * (b044Cь044C044Cь044Cь044Cь + i) % bь044C044C044Cь044Cь044Cь)
      {
      default: 
        b044C044Cь044Cь044Cь044Cь = 34;
        bьь044C044Cь044Cь044Cь = 24;
      }
      b044C044Cь044Cь044Cь044Cь = 18;
      bьь044C044Cь044Cь044Cь = 98;
    }
    localXxdxxd.b0445хх0445хх0445044504450445(new kkyykk.14(this, paramOvooov));
  }
  
  public void b0428ШШ0428ШШШШ04280428(String paramString1, String paramString2, int paramInt, ddxxdd paramDdxxdd, ggjjgg paramGgjjgg)
  {
    try
    {
      paramString1 = new jjyyjy(this.bь044C044C044C044Cьь044Cь.b0424ФФ042404240424Ф04240424Ф(paramString1), paramString1, paramString2, paramInt, paramDdxxdd, paramGgjjgg);
    }
    catch (Exception paramString1)
    {
      throw paramString1;
    }
    paramString1.bххххххх044504450445();
    try
    {
      throw new NullPointerException();
    }
    catch (Exception paramString1)
    {
      try
      {
        b044C044Cь044Cь044Cь044Cь = b0428Ш0428Ш0428042804280428Ш0428();
        return;
      }
      catch (Exception paramString1)
      {
        throw paramString1;
      }
    }
    switch (0)
    {
    }
    for (;;)
    {
      switch (1)
      {
      }
    }
  }
  
  public boolean b0428ШШШ042804280428ШШ0428()
  {
    try
    {
      boolean bool = xxdxxd.instance.bхх0445ххх0445044504450445();
      int i = b044C044Cь044Cь044Cь044Cь;
      switch (i * (b044Cь044C044Cь044Cь044Cь + i) % bь044C044C044Cь044Cь044Cь)
      {
      default: 
        switch (1)
        {
        case 0: 
        default: 
          for (;;)
          {
            switch (0)
            {
            }
          }
        }
        b044C044Cь044Cь044Cь044Cь = 78;
        i = b0428Ш0428Ш0428042804280428Ш0428();
        switch (i * (b044Cь044C044Cь044Cь044Cь + i) % bь044C044C044Cь044Cь044Cь)
        {
        default: 
          b044C044Cь044Cь044Cь044Cь = b0428Ш0428Ш0428042804280428Ш0428();
          bьь044C044Cь044Cь044Cь = 32;
        }
        bьь044C044Cь044Cь044Cь = 3;
      }
      return bool;
    }
    catch (Exception localException)
    {
      throw localException;
    }
  }
  
  /* Error */
  public void b0428ШШШШШШ0428Ш0428(String paramString)
  {
    // Byte code:
    //   0: aload_0
    //   1: getfield 154	kkkkkk/kkyykk:b044C044Cь044C044Cьь044Cь	Lkkkkkk/ggggga;
    //   4: getfield 475	kkkkkk/ggggga:b0442т0442044204420442т04420442	Lkkkkkk/fffnfn;
    //   7: aload_1
    //   8: invokevirtual 481	kkkkkk/fffnfn:bээ044Dэээ044D044D044Dэ	(Ljava/lang/String;)Lkkkkkk/fnfnfn;
    //   11: astore_1
    //   12: new 692	org/json/JSONObject
    //   15: dup
    //   16: invokespecial 693	org/json/JSONObject:<init>	()V
    //   19: astore 7
    //   21: aload 7
    //   23: ldc_w 695
    //   26: bipush 24
    //   28: iconst_2
    //   29: invokestatic 84	kkkkkk/gguuuu:bккккк043Aкк043A043A	(Ljava/lang/String;CC)Ljava/lang/String;
    //   32: aload_1
    //   33: invokevirtual 698	kkkkkk/fnfnfn:bэ044Dэ044D044D044Dэ044D044Dэ	()Ljava/lang/String;
    //   36: invokevirtual 702	org/json/JSONObject:put	(Ljava/lang/String;Ljava/lang/Object;)Lorg/json/JSONObject;
    //   39: pop
    //   40: aload 7
    //   42: ldc_w 704
    //   45: bipush 39
    //   47: sipush 221
    //   50: iconst_2
    //   51: invokestatic 78	kkkkkk/gguuuu:bк043Aккк043Aкк043A043A	(Ljava/lang/String;CCC)Ljava/lang/String;
    //   54: aload_1
    //   55: invokevirtual 707	kkkkkk/fnfnfn:bээ044Dэ044D044Dэ044D044Dэ	()Ljava/lang/String;
    //   58: invokevirtual 702	org/json/JSONObject:put	(Ljava/lang/String;Ljava/lang/Object;)Lorg/json/JSONObject;
    //   61: pop
    //   62: aload_0
    //   63: getfield 154	kkkkkk/kkyykk:b044C044Cь044C044Cьь044Cь	Lkkkkkk/ggggga;
    //   66: getfield 475	kkkkkk/ggggga:b0442т0442044204420442т04420442	Lkkkkkk/fffnfn;
    //   69: aload_1
    //   70: invokevirtual 707	kkkkkk/fnfnfn:bээ044Dэ044D044Dэ044D044Dэ	()Ljava/lang/String;
    //   73: aload_1
    //   74: invokevirtual 698	kkkkkk/fnfnfn:bэ044Dэ044D044D044Dэ044D044Dэ	()Ljava/lang/String;
    //   77: invokevirtual 710	kkkkkk/fffnfn:bэ044D044Dэээ044D044D044Dэ	(Ljava/lang/String;Ljava/lang/String;)V
    //   80: aload_0
    //   81: getfield 159	kkkkkk/kkyykk:b044Cьь044C044Cьь044Cь	Lkkkkkk/eeefee;
    //   84: astore 8
    //   86: aload_0
    //   87: aload 8
    //   89: aload_1
    //   90: invokevirtual 511	kkkkkk/fnfnfn:b044D044D044D044Dэ044Dэ044D044Dэ	()Ljava/lang/String;
    //   93: invokevirtual 519	kkkkkk/eeefee:bФФ0424Ф042404240424042404240424	(Ljava/lang/String;)Lkkkkkk/nfnfnn;
    //   96: invokevirtual 713	kkkkkk/nfnfnn:bээээ044Dэ044Dэ044Dэ	()Ljava/lang/String;
    //   99: invokevirtual 567	kkkkkk/kkyykk:bШШ042804280428042804280428Ш0428	(Ljava/lang/String;)Lkkkkkk/hhhbbh;
    //   102: aload 7
    //   104: invokevirtual 714	org/json/JSONObject:toString	()Ljava/lang/String;
    //   107: invokevirtual 573	kkkkkk/hhhbbh:bШ04280428042804280428042804280428Ш	(Ljava/lang/String;)Lkkkkkk/bhhbbh;
    //   110: astore 8
    //   112: aload 8
    //   114: ifnonnull +29 -> 143
    //   117: aload_1
    //   118: getstatic 720	kkkkkk/fnfnfn$nffnfn:ERROR	Lkkkkkk/fnfnfn$nffnfn;
    //   121: invokevirtual 724	kkkkkk/fnfnfn:bээ044D044D044D044Dэ044D044Dэ	(Lkkkkkk/fnfnfn$nffnfn;)V
    //   124: aload_0
    //   125: aload_1
    //   126: invokevirtual 707	kkkkkk/fnfnfn:bээ044Dэ044D044Dэ044D044Dэ	()Ljava/lang/String;
    //   129: aload_1
    //   130: invokevirtual 511	kkkkkk/fnfnfn:b044D044D044D044Dэ044Dэ044D044Dэ	()Ljava/lang/String;
    //   133: getstatic 728	kkkkkk/nnnnnf$ffnnnf:AGENT_FORM	Lkkkkkk/nnnnnf$ffnnnf;
    //   136: getstatic 733	kkkkkk/nnnnnf$nfnnnf:ERROR	Lkkkkkk/nnnnnf$nfnnnf;
    //   139: invokevirtual 735	kkkkkk/kkyykk:b04280428Ш0428ШШШ0428Ш0428	(Ljava/lang/String;Ljava/lang/String;Lkkkkkk/nnnnnf$ffnnnf;Lkkkkkk/nnnnnf$nfnnnf;)V
    //   142: return
    //   143: aload 7
    //   145: invokevirtual 714	org/json/JSONObject:toString	()Ljava/lang/String;
    //   148: astore 9
    //   150: aload 8
    //   152: aload 9
    //   154: invokevirtual 740	kkkkkk/bhhbbh:bШШШ042804280428042804280428Ш	(Ljava/lang/String;)V
    //   157: getstatic 86	kkkkkk/kkyykk:b044C044Cь044Cь044Cь044Cь	I
    //   160: istore_2
    //   161: iload_2
    //   162: getstatic 88	kkkkkk/kkyykk:b044Cь044C044Cь044Cь044Cь	I
    //   165: iload_2
    //   166: iadd
    //   167: imul
    //   168: getstatic 90	kkkkkk/kkyykk:bь044C044C044Cь044Cь044Cь	I
    //   171: irem
    //   172: tableswitch	default:+20->192, 0:+32->204
    //   192: invokestatic 96	kkkkkk/kkyykk:b0428Ш0428Ш0428042804280428Ш0428	()I
    //   195: putstatic 86	kkkkkk/kkyykk:b044C044Cь044Cь044Cь044Cь	I
    //   198: invokestatic 96	kkkkkk/kkyykk:b0428Ш0428Ш0428042804280428Ш0428	()I
    //   201: putstatic 92	kkkkkk/kkyykk:bьь044C044Cь044Cь044Cь	I
    //   204: getstatic 86	kkkkkk/kkyykk:b044C044Cь044Cь044Cь044Cь	I
    //   207: istore_2
    //   208: getstatic 88	kkkkkk/kkyykk:b044Cь044C044Cь044Cь044Cь	I
    //   211: istore_3
    //   212: getstatic 86	kkkkkk/kkyykk:b044C044Cь044Cь044Cь044Cь	I
    //   215: istore 4
    //   217: getstatic 90	kkkkkk/kkyykk:bь044C044C044Cь044Cь044Cь	I
    //   220: istore 5
    //   222: getstatic 92	kkkkkk/kkyykk:bьь044C044Cь044Cь044Cь	I
    //   225: istore 6
    //   227: iload_2
    //   228: iload_3
    //   229: iadd
    //   230: iload 4
    //   232: imul
    //   233: iload 5
    //   235: irem
    //   236: iload 6
    //   238: if_icmpeq +14 -> 252
    //   241: bipush 24
    //   243: putstatic 86	kkkkkk/kkyykk:b044C044Cь044Cь044Cь044Cь	I
    //   246: invokestatic 96	kkkkkk/kkyykk:b0428Ш0428Ш0428042804280428Ш0428	()I
    //   249: putstatic 92	kkkkkk/kkyykk:bьь044C044Cь044Cь044Cь	I
    //   252: aload 7
    //   254: ldc_w 742
    //   257: bipush 101
    //   259: bipush 22
    //   261: iconst_3
    //   262: invokestatic 78	kkkkkk/gguuuu:bк043Aккк043Aкк043A043A	(Ljava/lang/String;CCC)Ljava/lang/String;
    //   265: aload_1
    //   266: invokevirtual 745	kkkkkk/fnfnfn:b044D044Dээ044D044Dэ044D044Dэ	()Ljava/lang/String;
    //   269: invokevirtual 702	org/json/JSONObject:put	(Ljava/lang/String;Ljava/lang/Object;)Lorg/json/JSONObject;
    //   272: pop
    //   273: aload 8
    //   275: aload 7
    //   277: invokevirtual 714	org/json/JSONObject:toString	()Ljava/lang/String;
    //   280: invokevirtual 748	kkkkkk/bhhbbh:b042804280428Ш04280428042804280428Ш	(Ljava/lang/String;)V
    //   283: new 750	kkkkkk/yyyjyj
    //   286: dup
    //   287: aload_1
    //   288: aload 8
    //   290: aload_0
    //   291: invokespecial 753	kkkkkk/yyyjyj:<init>	(Lkkkkkk/fnfnfn;Lkkkkkk/bhhbbh;Lkkkkkk/kkyykk;)V
    //   294: astore 7
    //   296: aload 7
    //   298: invokevirtual 754	kkkkkk/yyyjyj:bххххххх044504450445	()V
    //   301: aload_0
    //   302: aload_1
    //   303: invokevirtual 707	kkkkkk/fnfnfn:bээ044Dэ044D044Dэ044D044Dэ	()Ljava/lang/String;
    //   306: aload_1
    //   307: invokevirtual 511	kkkkkk/fnfnfn:b044D044D044D044Dэ044Dэ044D044Dэ	()Ljava/lang/String;
    //   310: getstatic 728	kkkkkk/nnnnnf$ffnnnf:AGENT_FORM	Lkkkkkk/nnnnnf$ffnnnf;
    //   313: getstatic 757	kkkkkk/nnnnnf$nfnnnf:SUBMITTED	Lkkkkkk/nnnnnf$nfnnnf;
    //   316: invokevirtual 735	kkkkkk/kkyykk:b04280428Ш0428ШШШ0428Ш0428	(Ljava/lang/String;Ljava/lang/String;Lkkkkkk/nnnnnf$ffnnnf;Lkkkkkk/nnnnnf$nfnnnf;)V
    //   319: return
    //   320: astore_1
    //   321: aload_1
    //   322: invokevirtual 760	org/json/JSONException:printStackTrace	()V
    //   325: return
    //   326: astore_1
    //   327: aload_1
    //   328: athrow
    //   329: astore_1
    //   330: aload_1
    //   331: athrow
    // Local variable table:
    //   start	length	slot	name	signature
    //   0	332	0	this	kkyykk
    //   0	332	1	paramString	String
    //   160	70	2	i	int
    //   211	19	3	j	int
    //   215	18	4	k	int
    //   220	16	5	m	int
    //   225	14	6	n	int
    //   19	278	7	localObject1	Object
    //   84	205	8	localObject2	Object
    //   148	5	9	str	String
    // Exception table:
    //   from	to	target	type
    //   12	62	320	org/json/JSONException
    //   62	86	320	org/json/JSONException
    //   86	112	320	org/json/JSONException
    //   117	142	320	org/json/JSONException
    //   143	150	320	org/json/JSONException
    //   150	157	320	org/json/JSONException
    //   252	273	320	org/json/JSONException
    //   273	283	320	org/json/JSONException
    //   283	296	320	org/json/JSONException
    //   296	319	320	org/json/JSONException
    //   62	86	326	java/lang/Exception
    //   143	150	326	java/lang/Exception
    //   241	252	326	java/lang/Exception
    //   273	283	326	java/lang/Exception
    //   296	319	326	java/lang/Exception
    //   321	325	326	java/lang/Exception
    //   0	12	329	java/lang/Exception
    //   12	62	329	java/lang/Exception
    //   86	112	329	java/lang/Exception
    //   117	142	329	java/lang/Exception
    //   150	157	329	java/lang/Exception
    //   204	227	329	java/lang/Exception
    //   252	273	329	java/lang/Exception
    //   283	296	329	java/lang/Exception
  }
  
  public void b0445044504450445044504450445х04450445()
  {
    throw new Runtime("d2j fail translate: java.lang.IndexOutOfBoundsException: fromIndex < 0: -1\n\tat java.util.BitSet.nextSetBit(BitSet.java:712)\n\tat com.googlecode.dex2jar.ir.ts.array.FillArrayTransformer.makeSureAllElementAreAssigned(FillArrayTransformer.java:505)\n\tat com.googlecode.dex2jar.ir.ts.array.FillArrayTransformer.transformReportChanged(FillArrayTransformer.java:123)\n\tat com.googlecode.dex2jar.ir.ts.StatedTransformer.transform(StatedTransformer.java:10)\n\tat com.googlecode.d2j.dex.Dex2jar$2.optimize(Dex2jar.java:149)\n\tat com.googlecode.d2j.dex.Dex2Asm.convertCode(Dex2Asm.java:414)\n\tat com.googlecode.d2j.dex.ExDex2Asm.convertCode(ExDex2Asm.java:42)\n\tat com.googlecode.d2j.dex.Dex2jar$2.convertCode(Dex2jar.java:128)\n\tat com.googlecode.d2j.dex.Dex2Asm.convertMethod(Dex2Asm.java:509)\n\tat com.googlecode.d2j.dex.Dex2Asm.convertClass(Dex2Asm.java:406)\n\tat com.googlecode.d2j.dex.Dex2Asm.convertDex(Dex2Asm.java:422)\n\tat com.googlecode.d2j.dex.Dex2jar.doTranslate(Dex2jar.java:172)\n\tat com.googlecode.d2j.dex.Dex2jar.to(Dex2jar.java:272)\n\tat com.googlecode.dex2jar.tools.Dex2jarCmd.doCommandLine(Dex2jarCmd.java:108)\n\tat com.googlecode.dex2jar.tools.BaseCmd.doMain(BaseCmd.java:288)\n\tat com.googlecode.dex2jar.tools.Dex2jarCmd.main(Dex2jarCmd.java:32)\n");
  }
  
  public String bШ0428042804280428042804280428Ш0428(String paramString)
  {
    try
    {
      paramString = this.b044Cь044C044C044Cьь044Cь.b044D044D044D044D044D044Dээ044Dэ(paramString);
      if ((b044C044Cь044Cь044Cь044Cь + b044Cь044C044Cь044Cь044Cь) * b044C044Cь044Cь044Cь044Cь % bь044C044C044Cь044Cь044Cь != bьь044C044Cь044Cь044Cь)
      {
        b044C044Cь044Cь044Cь044Cь = 63;
        bьь044C044Cь044Cь044Cь = 64;
      }
      return paramString;
    }
    catch (Exception paramString)
    {
      throw paramString;
    }
  }
  
  public int bШ042804280428042804280428ШШ0428(String paramString1, String paramString2, nnnnnf.ffnnnf paramFfnnnf)
  {
    return b0428Ш04280428042804280428ШШ0428(paramString1, paramString2, -1L, paramFfnnnf);
  }
  
  public void bШ042804280428Ш04280428ШШ0428(String paramString1, String paramString2, dddxxd<Integer, Exception> paramDddxxd)
  {
    paramString1 = new yyjyjy(this, paramString1, paramString2, new kkyykk.8(this, paramDddxxd));
    int i = b044C044Cь044Cь044Cь044Cь;
    switch (i * (b044Cь044C044Cь044Cь044Cь + i) % b0428ШШШ0428042804280428Ш0428())
    {
    default: 
      b044C044Cь044Cь044Cь044Cь = b0428Ш0428Ш0428042804280428Ш0428();
      bьь044C044Cь044Cь044Cь = 48;
    }
    paramString1.bххххххх044504450445();
    i = b044C044Cь044Cь044Cь044Cь;
    switch (i * (b044Cь044C044Cь044Cь044Cь + i) % b0428ШШШ0428042804280428Ш0428())
    {
    default: 
      b044C044Cь044Cь044Cь044Cь = b0428Ш0428Ш0428042804280428Ш0428();
      bьь044C044Cь044Cь044Cь = 31;
    }
  }
  
  public bbhbhh bШ04280428Ш042804280428ШШ0428(String paramString1, String paramString2)
  {
    bbhbhh localBbhbhh = bШ04280428Ш0428042804280428Ш0428(paramString1, paramString2);
    if (localBbhbhh != null) {
      return localBbhbhh;
    }
    paramString1 = new yjyyjy(this.b044Cьь044C044Cьь044Cь, paramString1, this.bь044C044C044C044Cьь044Cь.b0424ФФ042404240424Ф04240424Ф(paramString2), xdxxdd.URGENT);
    if ((b044C044Cь044Cь044Cь044Cь + b044Cь044C044Cь044Cь044Cь) * b044C044Cь044Cь044Cь044Cь % bь044C044C044Cь044Cь044Cь != bьь044C044Cь044Cь044Cь)
    {
      b044C044Cь044Cь044Cь044Cь = 5;
      bьь044C044Cь044Cь044Cь = b0428Ш0428Ш0428042804280428Ш0428();
      int i = b044C044Cь044Cь044Cь044Cь;
      switch (i * (b044Cь044C044Cь044Cь044Cь + i) % bь044C044C044Cь044Cь044Cь)
      {
      default: 
        b044C044Cь044Cь044Cь044Cь = 1;
        bьь044C044Cь044Cь044Cь = b0428Ш0428Ш0428042804280428Ш0428();
      }
    }
    paramString1.bххххххх044504450445();
    return null;
  }
  
  public void bШ04280428ШШ04280428ШШ0428(String paramString, dddxxd<AgentData, Exception> paramDddxxd)
  {
    paramString = this.b044Cьь044C044Cьь044Cь.bФ042404240424Ф04240424042404240424(paramString);
    int i = b044C044Cь044Cь044Cь044Cь;
    switch (i * (b044Cь044C044Cь044Cь044Cь + i) % bь044C044C044Cь044Cь044Cь)
    {
    default: 
      b044C044Cь044Cь044Cь044Cь = 68;
      bьь044C044Cь044Cь044Cь = 53;
    }
    paramDddxxd = new kkyykk.11(this, paramDddxxd);
    switch (1)
    {
    case 0: 
    default: 
      for (;;)
      {
        switch (0)
        {
        }
      }
    }
    paramString = paramString.b04380438и0438ии0438иии(paramDddxxd);
    if ((b044C044Cь044Cь044Cь044Cь + b044Cь044C044Cь044Cь044Cь) * b044C044Cь044Cь044Cь044Cь % bь044C044C044Cь044Cь044Cь != bьь044C044Cь044Cь044Cь)
    {
      b044C044Cь044Cь044Cь044Cь = 21;
      bьь044C044Cь044Cь044Cь = 84;
    }
    paramString.b0438ии0438ии0438иии();
  }
  
  public void bШ04280428ШШШ04280428ШШ(voovov paramVoovov)
  {
    try
    {
      xtxtxt.bии0438и04380438и0438ии(bььь044C044Cьь044Cь, gguuuu.bк043Aккк043Aкк043A043A("$:HHI?E?x>JSK\f\r\016", 'T', '\004', '\001'));
      switch (1)
      {
      case 0: 
      default: 
        for (;;)
        {
          switch (0)
          {
          }
        }
      }
      if ((b044C044Cь044Cь044Cь044Cь + b044Cь044C044Cь044Cь044Cь) * b044C044Cь044Cь044Cь044Cь % bь044C044C044Cь044Cь044Cь != bьь044C044Cь044Cь044Cь)
      {
        b044C044Cь044Cь044Cь044Cь = b0428Ш0428Ш0428042804280428Ш0428();
        bьь044C044Cь044Cь044Cь = 55;
      }
      if ((b044C044Cь044Cь044Cь044Cь + b044Cь044C044Cь044Cь044Cь) * b044C044Cь044Cь044Cь044Cь % bь044C044C044Cь044Cь044Cь != bьь044C044Cь044Cь044Cь)
      {
        b044C044Cь044Cь044Cь044Cь = 18;
        bьь044C044Cь044Cь044Cь = b0428Ш0428Ш0428042804280428Ш0428();
      }
      b0428Ш0428ШШШШШ04280428(paramVoovov);
      return;
    }
    catch (Exception paramVoovov)
    {
      throw paramVoovov;
    }
  }
  
  public void bШ04280428ШШШШ0428Ш0428(String paramString)
  {
    String str = bььь044C044Cьь044Cь;
    StringBuilder localStringBuilder = new StringBuilder();
    if ((b044C044Cь044Cь044Cь044Cь + b044Cь044C044Cь044Cь044Cь) * b044C044Cь044Cь044Cь044Cь % bь044C044C044Cь044Cь044Cь != bьь044C044Cь044Cь044Cь)
    {
      int i = b044C044Cь044Cь044Cь044Cь;
      switch (i * (b044Cь044C044Cь044Cь044Cь + i) % bь044C044C044Cь044Cь044Cь)
      {
      default: 
        b044C044Cь044Cь044Cь044Cь = b0428Ш0428Ш0428042804280428Ш0428();
        bьь044C044Cь044Cь044Cь = b0428Ш0428Ш0428042804280428Ш0428();
      }
      switch (1)
      {
      case 0: 
      default: 
        for (;;)
        {
          switch (1)
          {
          }
        }
      }
      b044C044Cь044Cь044Cь044Cь = 62;
      bьь044C044Cь044Cь044Cь = 90;
    }
    xtxtxt.bии0438и04380438и0438ии(str, gguuuu.bккккк043Aкк043A043A("8+9>2-0\037A/AD66\rs7H8F=#?{\032}", '¡', '\004') + paramString);
    switch (1)
    {
    case 0: 
    default: 
      for (;;)
      {
        switch (0)
        {
        }
      }
    }
    this.bььььь044Cь044Cь.b0424Ф04240424ФФФФФ0424(paramString);
  }
  
  public void bШ04280428ШШШШШ04280428(fnfnnf paramFnfnnf, boolean paramBoolean)
  {
    Object localObject = xxdxxd.instance.bххх044504450445х044504450445();
    if (localObject == null) {}
    while ((!((Context)localObject).getResources().getBoolean(R.bool.send_agent_profile_updates_when_conversation_closed)) && (!paramBoolean)) {
      return;
    }
    localObject = null;
    if (paramFnfnnf != null)
    {
      localObject = new AgentData();
      switch (1)
      {
      case 0: 
      default: 
        for (;;)
        {
          switch (0)
          {
          }
        }
      }
      String str = paramFnfnnf.b0445ххх04450445хх04450445();
      if ((b044C044Cь044Cь044Cь044Cь + b044Cь044C044Cь044Cь044Cь) * b044C044Cь044Cь044Cь044Cь % bь044C044C044Cь044Cь044Cь != bьь044C044Cь044Cь044Cь)
      {
        b044C044Cь044Cь044Cь044Cь = 43;
        bьь044C044Cь044Cь044Cь = 74;
      }
      ((AgentData)localObject).mFirstName = str;
      switch (1)
      {
      case 0: 
      default: 
        for (;;)
        {
          switch (1)
          {
          }
        }
      }
      ((AgentData)localObject).mLastName = paramFnfnnf.b04450445хх04450445хх04450445();
      ((AgentData)localObject).mAvatarURL = paramFnfnnf.b0445х04450445х0445хх04450445();
      str = paramFnfnnf.b0445044504450445х0445хх04450445();
      if ((b044C044Cь044Cь044Cь044Cь + b044Cь044C044Cь044Cь044Cь) * b044C044Cь044Cь044Cь044Cь % bь044C044C044Cь044Cь044Cь != bьь044C044Cь044Cь044Cь)
      {
        b044C044Cь044Cь044Cь044Cь = b0428Ш0428Ш0428042804280428Ш0428();
        bьь044C044Cь044Cь044Cь = b0428Ш0428Ш0428042804280428Ш0428();
      }
      ((AgentData)localObject).mEmployeeId = str;
      ((AgentData)localObject).mNickName = paramFnfnnf.b0445х0445х04450445хх04450445();
    }
    this.b044C044Cььь044Cь044Cь.onAgentDetailsChanged((AgentData)localObject);
  }
  
  public PendingIntent bШ0428Ш04280428042804280428Ш0428()
  {
    try
    {
      PendingIntent localPendingIntent = this.bь044C044Cьь044Cь044Cь;
      return localPendingIntent;
    }
    catch (Exception localException)
    {
      throw localException;
    }
  }
  
  public void bШ0428Ш0428042804280428ШШ0428(String paramString1, String paramString2, String paramString3)
  {
    paramString1 = new yjyyyj(this, paramString1, paramString2, paramString3);
    if ((b044C044Cь044Cь044Cь044Cь + bШШ0428Ш0428042804280428Ш0428()) * b044C044Cь044Cь044Cь044Cь % bь044C044C044Cь044Cь044Cь != bьь044C044Cь044Cь044Cь)
    {
      if ((b044C044Cь044Cь044Cь044Cь + b044Cь044C044Cь044Cь044Cь) * b044C044Cь044Cь044Cь044Cь % bь044C044C044Cь044Cь044Cь != bьь044C044Cь044Cь044Cь)
      {
        b044C044Cь044Cь044Cь044Cь = b0428Ш0428Ш0428042804280428Ш0428();
        bьь044C044Cь044Cь044Cь = 94;
      }
      b044C044Cь044Cь044Cь044Cь = b0428Ш0428Ш0428042804280428Ш0428();
      bьь044C044Cь044Cь044Cь = b0428Ш0428Ш0428042804280428Ш0428();
    }
    paramString1.bххххххх044504450445();
    switch (0)
    {
    case 1: 
    default: 
      for (;;)
      {
        switch (0)
        {
        }
      }
    }
  }
  
  public void bШ0428Ш0428Ш04280428ШШ0428(String paramString)
  {
    xtxtxt.bии0438и04380438и0438ии(bььь044C044Cьь044Cь, gguuuu.bккккк043Aкк043A043A("&LWHUUVNM_U[U\017Vca`\024WhXf]\032", 'p', '\004') + paramString);
    this.bььььь044Cь044Cь.bФ0424Ф042404240424042404240424Ф(paramString);
  }
  
  /* Error */
  public void bШ0428Ш0428ШШШ0428Ш0428(String paramString1, String paramString2, dddxxd<Void, Exception> paramDddxxd, boolean paramBoolean)
  {
    // Byte code:
    //   0: new 863	kkkkkk/jjjyjj
    //   3: dup
    //   4: aload_0
    //   5: getfield 176	kkkkkk/kkyykk:bь044C044C044C044Cьь044Cь	Lkkkkkk/cmmmcc;
    //   8: aload_0
    //   9: getfield 183	kkkkkk/kkyykk:b044Cь044C044C044Cьь044Cь	Lkkkkkk/ffnnnn;
    //   12: aload_1
    //   13: aload_2
    //   14: aload_3
    //   15: iload 4
    //   17: invokespecial 866	kkkkkk/jjjyjj:<init>	(Lkkkkkk/cmmmcc;Lkkkkkk/ffnnnn;Ljava/lang/String;Ljava/lang/String;Lkkkkkk/dddxxd;Z)V
    //   20: astore_1
    //   21: getstatic 86	kkkkkk/kkyykk:b044C044Cь044Cь044Cь044Cь	I
    //   24: istore 5
    //   26: getstatic 88	kkkkkk/kkyykk:b044Cь044C044Cь044Cь044Cь	I
    //   29: istore 6
    //   31: getstatic 86	kkkkkk/kkyykk:b044C044Cь044Cь044Cь044Cь	I
    //   34: istore 7
    //   36: invokestatic 125	kkkkkk/kkyykk:b0428ШШШ0428042804280428Ш0428	()I
    //   39: istore 8
    //   41: getstatic 86	kkkkkk/kkyykk:b044C044Cь044Cь044Cь044Cь	I
    //   44: istore 9
    //   46: iload 9
    //   48: getstatic 88	kkkkkk/kkyykk:b044Cь044C044Cь044Cь044Cь	I
    //   51: iload 9
    //   53: iadd
    //   54: imul
    //   55: getstatic 90	kkkkkk/kkyykk:bь044C044C044Cь044Cь044Cь	I
    //   58: irem
    //   59: tableswitch	default:+17->76, 0:+28->87
    //   76: invokestatic 96	kkkkkk/kkyykk:b0428Ш0428Ш0428042804280428Ш0428	()I
    //   79: putstatic 86	kkkkkk/kkyykk:b044C044Cь044Cь044Cь044Cь	I
    //   82: bipush 92
    //   84: putstatic 92	kkkkkk/kkyykk:bьь044C044Cь044Cь044Cь	I
    //   87: getstatic 92	kkkkkk/kkyykk:bьь044C044Cь044Cь044Cь	I
    //   90: istore 9
    //   92: iload 5
    //   94: iload 6
    //   96: iadd
    //   97: iload 7
    //   99: imul
    //   100: iload 8
    //   102: irem
    //   103: iload 9
    //   105: if_icmpeq +14 -> 119
    //   108: bipush 15
    //   110: putstatic 86	kkkkkk/kkyykk:b044C044Cь044Cь044Cь044Cь	I
    //   113: invokestatic 96	kkkkkk/kkyykk:b0428Ш0428Ш0428042804280428Ш0428	()I
    //   116: putstatic 92	kkkkkk/kkyykk:bьь044C044Cь044Cь044Cь	I
    //   119: aload_1
    //   120: invokevirtual 867	kkkkkk/jjjyjj:bххххххх044504450445	()V
    //   123: iconst_0
    //   124: tableswitch	default:+24->148, 0:+51->175, 1:+-1->123
    //   148: iconst_1
    //   149: tableswitch	default:+23->172, 0:+-26->123, 1:+26->175
    //   172: goto -24 -> 148
    //   175: return
    //   176: astore_1
    //   177: aload_1
    //   178: athrow
    //   179: astore_1
    //   180: aload_1
    //   181: athrow
    // Local variable table:
    //   start	length	slot	name	signature
    //   0	182	0	this	kkyykk
    //   0	182	1	paramString1	String
    //   0	182	2	paramString2	String
    //   0	182	3	paramDddxxd	dddxxd<Void, Exception>
    //   0	182	4	paramBoolean	boolean
    //   24	73	5	i	int
    //   29	68	6	j	int
    //   34	66	7	k	int
    //   39	64	8	m	int
    //   44	62	9	n	int
    // Exception table:
    //   from	to	target	type
    //   0	41	176	java/lang/Exception
    //   108	119	176	java/lang/Exception
    //   87	92	179	java/lang/Exception
    //   119	123	179	java/lang/Exception
  }
  
  public void bШ0428Ш0428ШШШШ04280428(ConversationViewParams paramConversationViewParams)
  {
    int i = 1;
    String str = bььь044C044Cьь044Cь;
    StringBuilder localStringBuilder = new StringBuilder();
    switch (1)
    {
    case 0: 
    default: 
      for (;;)
      {
        switch (0)
        {
        }
      }
    }
    xtxtxt.bии0438и04380438и0438ии(str, gguuuu.bк043Aккк043Aкк043A043A("_r\003\004yy3w\005\005\016}\f\016|\021\007\016\016@\030\f\t\034E\027\t\033\013\030\037LgN", '¨', 'á', '\003') + paramConversationViewParams);
    this.b044Cьььь044Cь044Cь = paramConversationViewParams;
    try
    {
      for (;;)
      {
        i /= 0;
      }
      return;
    }
    catch (Exception paramConversationViewParams)
    {
      b044C044Cь044Cь044Cь044Cь = b0428Ш0428Ш0428042804280428Ш0428();
    }
  }
  
  public boolean bШ0428ШШ042804280428ШШ0428(String paramString)
  {
    try
    {
      boolean bool = this.bььььь044Cь044Cь.bФФ0424ФФФФФФ0424(paramString);
      return bool;
    }
    catch (Exception paramString)
    {
      throw paramString;
    }
  }
  
  public void bШ0428ШШШШШ0428Ш0428(String paramString1, String paramString2, String paramString3, String paramString4, boolean paramBoolean)
  {
    Context localContext = xxdxxd.instance.bххх044504450445х044504450445();
    if (this.b044Cьь044Cь044Cь044Cь)
    {
      Object localObject = bььь044C044Cьь044Cь;
      switch (1)
      {
      case 0: 
      default: 
        for (;;)
        {
          switch (0)
          {
          }
        }
      }
      xtxtxt.bии0438и04380438и0438ии((String)localObject, gguuuu.bккккк043Aкк043A043A("np^psUqnreiVow}yE,\003~{rv|\003|6\b\001\t\017\013<\023\022\t\017\tB\005D\031\f\032\037\023\016\021", 'ù', '\000'));
      localObject = new Intent(localContext, BackgroundActionsService.class);
      int i = b044C044Cь044Cь044Cь044Cь;
      switch (i * (b044Cь044C044Cь044Cь044Cь + i) % b0428ШШШ0428042804280428Ш0428())
      {
      default: 
        b044C044Cь044Cь044Cь044Cь = 58;
        bьь044C044Cь044Cь044Cь = b0428Ш0428Ш0428042804280428Ш0428();
      }
      ((Intent)localObject).putExtra(gguuuu.bккккк043Aкк043A043A("\017# \037\017\016$*\"\030", 'T', '\004'), 1);
      ((Intent)localObject).putExtra(gguuuu.bккккк043Aкк043A043A("M>JM?8927IDA/,.=+7,&/)", '7', '\002'), paramString1);
      ((Intent)localObject).putExtra(gguuuu.bк043Aккк043Aкк043A043A("i\\joc^a\\cwtscbxfxnm}itp", 'R', '\\', '\001'), paramString2);
      i = b044C044Cь044Cь044Cь044Cь;
      switch (i * (b044Cь044C044Cь044Cь044Cь + i) % bь044C044C044Cь044Cь044Cь)
      {
      default: 
        b044C044Cь044Cь044Cь044Cь = 1;
        bьь044C044Cь044Cь044Cь = b0428Ш0428Ш0428042804280428Ш0428();
      }
      ((Intent)localObject).putExtra(gguuuu.bк043Aккк043Aкк043A043A("zm{\001tormt\t\006\005ts~\004x~y\021\017\007", 'Ñ', '4', '\003'), paramString3);
      switch (1)
      {
      case 0: 
      default: 
        for (;;)
        {
          switch (0)
          {
          }
        }
      }
      ((Intent)localObject).putExtra(gguuuu.bккккк043Aкк043A043A("WHTWIBC<ASNK96?B5:7030>A5:8", 'Ý', '\002'), paramString4);
      ((Intent)localObject).putExtra(gguuuu.bккккк043Aкк043A043A("7*8=1,/*1EBA10;@5<;6>KIH;@?LESC", 'Â', '\000'), paramBoolean);
      localContext.startService((Intent)localObject);
      return;
    }
    xtxtxt.bии0438и04380438и0438ии(bььь044C044Cьь044Cь, gguuuu.bккккк043Aкк043A043A("eeQabB\\WYJL7NTXR\034\001UOJL=?CG?vF=CGApG8B5;@>h)f9*69+$%", '/', '\002'));
    this.bь044Cь044Cь044Cь044Cь.b04280428ШШШШ0428042804280428(paramString1, paramString2, paramString3, paramString4, paramBoolean, new kkyykk.5(this));
  }
  
  public hhhbbh bШШ042804280428042804280428Ш0428(String paramString)
  {
    Object localObject = this.b044C044C044Cьь044Cь044Cь;
    switch (0)
    {
    case 1: 
    default: 
      for (;;)
      {
        switch (0)
        {
        }
      }
    }
    if (localObject == null)
    {
      int i = b0428Ш0428Ш0428042804280428Ш0428();
      if ((b044C044Cь044Cь044Cь044Cь + b044Cь044C044Cь044Cь044Cь) * b044C044Cь044Cь044Cь044Cь % bь044C044C044Cь044Cь044Cь != bьь044C044Cь044Cь044Cь)
      {
        b044C044Cь044Cь044Cь044Cь = b0428Ш0428Ш0428042804280428Ш0428();
        bьь044C044Cь044Cь044Cь = 95;
      }
      int j = b044Cь044C044Cь044Cь044Cь;
      switch (1)
      {
      case 0: 
      default: 
        for (;;)
        {
          switch (1)
          {
          }
        }
      }
      if ((i + j) * b0428Ш0428Ш0428042804280428Ш0428() % bь044C044C044Cь044Cь044Cь != bШ0428ШШ0428042804280428Ш0428())
      {
        b044C044Cь044Cь044Cь044Cь = 60;
        bьь044C044Cь044Cь044Cь = 99;
      }
      localObject = xxdxxd.instance.bххх044504450445х044504450445();
      if (this.bь044C044C044C044Cьь044Cь.b0424Ф0424Ф04240424Ф04240424Ф(paramString) == null) {
        return null;
      }
      this.b044C044C044Cьь044Cь044Cь = new hhhbbh((Context)localObject, this.bь044C044C044C044Cьь044Cь.b0424Ф0424Ф04240424Ф04240424Ф(paramString).bФФ042404240424ФФФ04240424());
    }
    return this.b044C044C044Cьь044Cь044Cь;
  }
  
  public void bШШ04280428042804280428ШШ0428(Context paramContext, String paramString1, String paramString2)
  {
    paramContext = bььь044C044Cьь044Cь;
    if ((b044C044Cь044Cь044Cь044Cь + b044Cь044C044Cь044Cь044Cь) * b044C044Cь044Cь044Cь044Cь % bь044C044C044Cь044Cь044Cь != bьь044C044Cь044Cь044Cь)
    {
      b044C044Cь044Cь044Cь044Cь = b0428Ш0428Ш0428042804280428Ш0428();
      bьь044C044Cь044Cь044Cь = b0428Ш0428Ш0428042804280428Ш0428();
      int i = b044C044Cь044Cь044Cь044Cь;
      switch (i * (b044Cь044C044Cь044Cь044Cь + i) % bь044C044C044Cь044Cь044Cь)
      {
      default: 
        b044C044Cь044Cь044Cь044Cь = b0428Ш0428Ш0428042804280428Ш0428();
        bьь044C044Cь044Cь044Cь = 74;
      }
    }
    xtxtxt.bии0438и04380438и0438ии(paramContext, gguuuu.bккккк043Aкк043A043A("]QZ]eU>g_h^fc]Hf_aoGlahgv$|o{px,\001s\002\007zux", 'x', '\001'));
    this.bь044Cь044Cь044Cь044Cь.b042804280428Ш04280428Ш042804280428(paramString1);
  }
  
  public void bШШ04280428Ш04280428ШШ0428(String paramString1, String paramString2, String paramString3)
  {
    paramString1 = new jyyjyj(this.bь044C044C044C044Cьь044Cь.b0424ФФ042404240424Ф04240424Ф(paramString2), paramString1, this.b044Cьь044C044Cьь044Cь.bФФФФ042404240424042404240424(paramString2).b044D044Dээ044Dэ044Dэ044Dэ(), paramString3, new kkyykk.7(this, paramString3));
    int i = b044C044Cь044Cь044Cь044Cь;
    switch (i * (b044Cь044C044Cь044Cь044Cь + i) % bь044C044C044Cь044Cь044Cь)
    {
    default: 
      b044C044Cь044Cь044Cь044Cь = 77;
      bьь044C044Cь044Cь044Cь = 66;
    }
    if ((b044C044Cь044Cь044Cь044Cь + b044Cь044C044Cь044Cь044Cь) * b044C044Cь044Cь044Cь044Cь % bь044C044C044Cь044Cь044Cь != bьь044C044Cь044Cь044Cь)
    {
      switch (0)
      {
      case 1: 
      default: 
        for (;;)
        {
          switch (0)
          {
          }
        }
      }
      b044C044Cь044Cь044Cь044Cь = 78;
      bьь044C044Cь044Cь044Cь = 37;
    }
    try
    {
      paramString1.bххххххх044504450445();
      return;
    }
    catch (Exception paramString1)
    {
      throw paramString1;
    }
  }
  
  /* Error */
  public void bШШ04280428ШШШШ04280428(Notification.Builder paramBuilder)
  {
    // Byte code:
    //   0: iconst_5
    //   1: istore_2
    //   2: getstatic 86	kkkkkk/kkyykk:b044C044Cь044Cь044Cь044Cь	I
    //   5: istore_3
    //   6: iload_3
    //   7: getstatic 88	kkkkkk/kkyykk:b044Cь044C044Cь044Cь044Cь	I
    //   10: iload_3
    //   11: iadd
    //   12: imul
    //   13: getstatic 90	kkkkkk/kkyykk:bь044C044C044Cь044Cь044Cь	I
    //   16: irem
    //   17: tableswitch	default:+19->36, 0:+30->47
    //   36: invokestatic 96	kkkkkk/kkyykk:b0428Ш0428Ш0428042804280428Ш0428	()I
    //   39: putstatic 86	kkkkkk/kkyykk:b044C044Cь044Cь044Cь044Cь	I
    //   42: bipush 33
    //   44: putstatic 92	kkkkkk/kkyykk:bьь044C044Cь044Cь044Cь	I
    //   47: iload_2
    //   48: iconst_0
    //   49: idiv
    //   50: istore_2
    //   51: goto -49 -> 2
    //   54: astore_1
    //   55: aload_1
    //   56: athrow
    //   57: astore 4
    //   59: bipush 54
    //   61: putstatic 86	kkkkkk/kkyykk:b044C044Cь044Cь044Cь044Cь	I
    //   64: new 273	java/lang/NullPointerException
    //   67: dup
    //   68: invokespecial 274	java/lang/NullPointerException:<init>	()V
    //   71: athrow
    //   72: astore 4
    //   74: invokestatic 96	kkkkkk/kkyykk:b0428Ш0428Ш0428042804280428Ш0428	()I
    //   77: putstatic 86	kkkkkk/kkyykk:b044C044Cь044Cь044Cь044Cь	I
    //   80: new 273	java/lang/NullPointerException
    //   83: dup
    //   84: invokespecial 274	java/lang/NullPointerException:<init>	()V
    //   87: athrow
    //   88: astore 4
    //   90: invokestatic 96	kkkkkk/kkyykk:b0428Ш0428Ш0428042804280428Ш0428	()I
    //   93: putstatic 86	kkkkkk/kkyykk:b044C044Cь044Cь044Cь044Cь	I
    //   96: aload_0
    //   97: aload_1
    //   98: putfield 114	kkkkkk/kkyykk:b044Cь044Cьь044Cь044Cь	Landroid/app/Notification$Builder;
    //   101: return
    // Local variable table:
    //   start	length	slot	name	signature
    //   0	102	0	this	kkyykk
    //   0	102	1	paramBuilder	Notification.Builder
    //   1	50	2	i	int
    //   5	8	3	j	int
    //   57	1	4	localException1	Exception
    //   72	1	4	localException2	Exception
    //   88	1	4	localException3	Exception
    // Exception table:
    //   from	to	target	type
    //   96	101	54	java/lang/Exception
    //   47	51	57	java/lang/Exception
    //   64	72	72	java/lang/Exception
    //   80	88	88	java/lang/Exception
  }
  
  /* Error */
  public void bШШ0428Ш042804280428ШШ0428(Context paramContext, kyykky paramKyykky, vvooov paramVvooov)
  {
    // Byte code:
    //   0: getstatic 86	kkkkkk/kkyykk:b044C044Cь044Cь044Cь044Cь	I
    //   3: istore 4
    //   5: getstatic 88	kkkkkk/kkyykk:b044Cь044C044Cь044Cь044Cь	I
    //   8: istore 5
    //   10: getstatic 86	kkkkkk/kkyykk:b044C044Cь044Cь044Cь044Cь	I
    //   13: istore 6
    //   15: getstatic 90	kkkkkk/kkyykk:bь044C044C044Cь044Cь044Cь	I
    //   18: istore 7
    //   20: getstatic 92	kkkkkk/kkyykk:bьь044C044Cь044Cь044Cь	I
    //   23: istore 8
    //   25: iload 4
    //   27: iload 5
    //   29: iadd
    //   30: iload 6
    //   32: imul
    //   33: iload 7
    //   35: irem
    //   36: iload 8
    //   38: if_icmpeq +65 -> 103
    //   41: invokestatic 96	kkkkkk/kkyykk:b0428Ш0428Ш0428042804280428Ш0428	()I
    //   44: istore 4
    //   46: iload 4
    //   48: getstatic 88	kkkkkk/kkyykk:b044Cь044C044Cь044Cь044Cь	I
    //   51: iload 4
    //   53: iadd
    //   54: imul
    //   55: getstatic 90	kkkkkk/kkyykk:bь044C044C044Cь044Cь044Cь	I
    //   58: irem
    //   59: tableswitch	default:+17->76, 0:+29->88
    //   76: invokestatic 96	kkkkkk/kkyykk:b0428Ш0428Ш0428042804280428Ш0428	()I
    //   79: putstatic 86	kkkkkk/kkyykk:b044C044Cь044Cь044Cь044Cь	I
    //   82: invokestatic 96	kkkkkk/kkyykk:b0428Ш0428Ш0428042804280428Ш0428	()I
    //   85: putstatic 92	kkkkkk/kkyykk:bьь044C044Cь044Cь044Cь	I
    //   88: invokestatic 96	kkkkkk/kkyykk:b0428Ш0428Ш0428042804280428Ш0428	()I
    //   91: istore 4
    //   93: iload 4
    //   95: putstatic 86	kkkkkk/kkyykk:b044C044Cь044Cь044Cь044Cь	I
    //   98: bipush 36
    //   100: putstatic 92	kkkkkk/kkyykk:bьь044C044Cь044Cь044Cь	I
    //   103: getstatic 297	kkkkkk/xxdxxd:instance	Lkkkkkk/xxdxxd;
    //   106: aload_1
    //   107: aload_2
    //   108: new 948	kkkkkk/kkyykk$17
    //   111: dup
    //   112: aload_0
    //   113: aload_1
    //   114: aload_2
    //   115: aload_3
    //   116: invokespecial 951	kkkkkk/kkyykk$17:<init>	(Lkkkkkk/kkyykk;Landroid/content/Context;Lkkkkkk/kyykky;Lkkkkkk/vvooov;)V
    //   119: invokevirtual 955	kkkkkk/xxdxxd:b0445х0445ххх0445044504450445	(Landroid/content/Context;Lkkkkkk/vvvvov;Lkkkkkk/vvooov;)V
    //   122: return
    //   123: astore_1
    //   124: aload_1
    //   125: athrow
    //   126: astore_1
    //   127: aload_1
    //   128: athrow
    //   129: astore_1
    //   130: aload_1
    //   131: athrow
    // Local variable table:
    //   start	length	slot	name	signature
    //   0	132	0	this	kkyykk
    //   0	132	1	paramContext	Context
    //   0	132	2	paramKyykky	kyykky
    //   0	132	3	paramVvooov	vvooov
    //   3	91	4	i	int
    //   8	22	5	j	int
    //   13	20	6	k	int
    //   18	18	7	m	int
    //   23	16	8	n	int
    // Exception table:
    //   from	to	target	type
    //   103	122	123	java/lang/Exception
    //   93	103	126	java/lang/Exception
    //   124	126	126	java/lang/Exception
    //   0	25	129	java/lang/Exception
    //   88	93	129	java/lang/Exception
  }
  
  public bbhbhh bШШ0428ШШ04280428ШШ0428(String paramString1, String paramString2, jjmjjj paramJjmjjj)
  {
    if ((b0428Ш0428Ш0428042804280428Ш0428() + b044Cь044C044Cь044Cь044Cь) * b0428Ш0428Ш0428042804280428Ш0428() % bь044C044C044Cь044Cь044Cь != bьь044C044Cь044Cь044Cь)
    {
      b044C044Cь044Cь044Cь044Cь = 32;
      bьь044C044Cь044Cь044Cь = b0428Ш0428Ш0428042804280428Ш0428();
    }
    bbhbhh localBbhbhh = bШ04280428Ш0428042804280428Ш0428(paramString1, paramString2);
    if (localBbhbhh != null) {
      return localBbhbhh;
    }
    paramString1 = new yyyyjy(this.b044Cьь044C044Cьь044Cь, paramString1, this.bь044C044C044C044Cьь044Cь.b0424ФФ042404240424Ф04240424Ф(paramString2), paramJjmjjj);
    if ((b044C044Cь044Cь044Cь044Cь + b044Cь044C044Cь044Cь044Cь) * b044C044Cь044Cь044Cь044Cь % bь044C044C044Cь044Cь044Cь != bьь044C044Cь044Cь044Cь)
    {
      b044C044Cь044Cь044Cь044Cь = b0428Ш0428Ш0428042804280428Ш0428();
      bьь044C044Cь044Cь044Cь = 76;
    }
    paramString1.bххххххх044504450445();
    return null;
  }
  
  public void bШШ0428ШШШШ0428Ш0428(String paramString1, String paramString2, String paramString3, String paramString4, String paramString5, String paramString6, String paramString7, String paramString8)
  {
    paramString1 = new jjyyjj(this, paramString1, paramString2, bШШ042804280428042804280428Ш0428(paramString2).bШ04280428042804280428042804280428Ш(paramString3), paramString4, paramString5, paramString6, paramString7, paramString8);
    if ((b0428Ш0428Ш0428042804280428Ш0428() + b044Cь044C044Cь044Cь044Cь) * b0428Ш0428Ш0428042804280428Ш0428() % b0428ШШШ0428042804280428Ш0428() != bьь044C044Cь044Cь044Cь)
    {
      b044C044Cь044Cь044Cь044Cь = 45;
      bьь044C044Cь044Cь044Cь = 15;
    }
    switch (0)
    {
    case 1: 
    default: 
      for (;;)
      {
        switch (0)
        {
        }
      }
    }
    paramString1.bххххххх044504450445();
    int i = b044C044Cь044Cь044Cь044Cь;
    switch (i * (b044Cь044C044Cь044Cь044Cь + i) % bь044C044C044Cь044Cь044Cь)
    {
    default: 
      b044C044Cь044Cь044Cь044Cь = 54;
      bьь044C044Cь044Cь044Cь = b0428Ш0428Ш0428042804280428Ш0428();
    }
  }
  
  /* Error */
  public boolean bШШ0428ШШШШШ04280428()
  {
    // Byte code:
    //   0: aload_0
    //   1: getfield 220	kkkkkk/kkyykk:bь044Cььь044Cь044Cь	Z
    //   4: istore_3
    //   5: getstatic 86	kkkkkk/kkyykk:b044C044Cь044Cь044Cь044Cь	I
    //   8: istore_1
    //   9: getstatic 88	kkkkkk/kkyykk:b044Cь044C044Cь044Cь044Cь	I
    //   12: istore_2
    //   13: iload_1
    //   14: iload_2
    //   15: iload_1
    //   16: iadd
    //   17: imul
    //   18: getstatic 90	kkkkkk/kkyykk:bь044C044C044Cь044Cь044Cь	I
    //   21: irem
    //   22: tableswitch	default:+81->103, 0:+64->86
    //   40: invokestatic 96	kkkkkk/kkyykk:b0428Ш0428Ш0428042804280428Ш0428	()I
    //   43: putstatic 86	kkkkkk/kkyykk:b044C044Cь044Cь044Cь044Cь	I
    //   46: invokestatic 96	kkkkkk/kkyykk:b0428Ш0428Ш0428042804280428Ш0428	()I
    //   49: istore_1
    //   50: iload_1
    //   51: putstatic 92	kkkkkk/kkyykk:bьь044C044Cь044Cь044Cь	I
    //   54: getstatic 86	kkkkkk/kkyykk:b044C044Cь044Cь044Cь044Cь	I
    //   57: invokestatic 230	kkkkkk/kkyykk:bШШ0428Ш0428042804280428Ш0428	()I
    //   60: iadd
    //   61: getstatic 86	kkkkkk/kkyykk:b044C044Cь044Cь044Cь044Cь	I
    //   64: imul
    //   65: invokestatic 125	kkkkkk/kkyykk:b0428ШШШ0428042804280428Ш0428	()I
    //   68: irem
    //   69: getstatic 92	kkkkkk/kkyykk:bьь044C044Cь044Cь044Cь	I
    //   72: if_icmpeq +14 -> 86
    //   75: invokestatic 96	kkkkkk/kkyykk:b0428Ш0428Ш0428042804280428Ш0428	()I
    //   78: putstatic 86	kkkkkk/kkyykk:b044C044Cь044Cь044Cь044Cь	I
    //   81: bipush 49
    //   83: putstatic 92	kkkkkk/kkyykk:bьь044C044Cь044Cь044Cь	I
    //   86: iload_3
    //   87: ireturn
    //   88: astore 4
    //   90: aload 4
    //   92: athrow
    //   93: astore 4
    //   95: aload 4
    //   97: athrow
    //   98: astore 4
    //   100: aload 4
    //   102: athrow
    //   103: goto -63 -> 40
    // Local variable table:
    //   start	length	slot	name	signature
    //   0	106	0	this	kkyykk
    //   8	43	1	i	int
    //   12	5	2	j	int
    //   4	83	3	bool	boolean
    //   88	3	4	localException1	Exception
    //   93	3	4	localException2	Exception
    //   98	3	4	localException3	Exception
    // Exception table:
    //   from	to	target	type
    //   0	5	88	java/lang/Exception
    //   13	40	93	java/lang/Exception
    //   40	50	93	java/lang/Exception
    //   90	93	93	java/lang/Exception
    //   5	13	98	java/lang/Exception
    //   50	54	98	java/lang/Exception
  }
  
  public Notification.Builder bШШШ04280428042804280428Ш0428()
  {
    try
    {
      throw new NullPointerException();
    }
    catch (Exception localException)
    {
      b044C044Cь044Cь044Cь044Cь = b0428Ш0428Ш0428042804280428Ш0428();
      switch (0)
      {
      case 1: 
      default: 
        for (;;)
        {
          switch (0)
          {
          }
        }
      }
    }
    return this.bьь044Cьь044Cь044Cь;
  }
  
  /* Error */
  public void bШШШ0428042804280428ШШ0428(String paramString, LPAuthenticationParams paramLPAuthenticationParams, @Nullable ConversationViewParams paramConversationViewParams)
  {
    // Byte code:
    //   0: getstatic 106	kkkkkk/kkyykk:bььь044C044Cьь044Cь	Ljava/lang/String;
    //   3: astore 5
    //   5: new 419	java/lang/StringBuilder
    //   8: dup
    //   9: invokespecial 420	java/lang/StringBuilder:<init>	()V
    //   12: astore 6
    //   14: invokestatic 96	kkkkkk/kkyykk:b0428Ш0428Ш0428042804280428Ш0428	()I
    //   17: istore 4
    //   19: iload 4
    //   21: getstatic 88	kkkkkk/kkyykk:b044Cь044C044Cь044Cь044Cь	I
    //   24: iload 4
    //   26: iadd
    //   27: imul
    //   28: getstatic 90	kkkkkk/kkyykk:bь044C044C044Cь044Cь044Cь	I
    //   31: irem
    //   32: tableswitch	default:+20->52, 0:+31->63
    //   52: invokestatic 96	kkkkkk/kkyykk:b0428Ш0428Ш0428042804280428Ш0428	()I
    //   55: putstatic 86	kkkkkk/kkyykk:b044C044Cь044Cь044Cь044Cь	I
    //   58: bipush 62
    //   60: putstatic 92	kkkkkk/kkyykk:bьь044C044Cь044Cь044Cь	I
    //   63: ldc_w 976
    //   66: bipush 79
    //   68: iconst_0
    //   69: invokestatic 84	kkkkkk/gguuuu:bккккк043Aкк043A043A	(Ljava/lang/String;CC)Ljava/lang/String;
    //   72: astore 7
    //   74: aload 5
    //   76: aload 6
    //   78: aload 7
    //   80: invokevirtual 426	java/lang/StringBuilder:append	(Ljava/lang/String;)Ljava/lang/StringBuilder;
    //   83: aload_1
    //   84: invokevirtual 426	java/lang/StringBuilder:append	(Ljava/lang/String;)Ljava/lang/StringBuilder;
    //   87: invokevirtual 429	java/lang/StringBuilder:toString	()Ljava/lang/String;
    //   90: invokestatic 281	kkkkkk/xtxtxt:bии0438и04380438и0438ии	(Ljava/lang/String;Ljava/lang/String;)V
    //   93: invokestatic 96	kkkkkk/kkyykk:b0428Ш0428Ш0428042804280428Ш0428	()I
    //   96: getstatic 88	kkkkkk/kkyykk:b044Cь044C044Cь044Cь044Cь	I
    //   99: iadd
    //   100: invokestatic 96	kkkkkk/kkyykk:b0428Ш0428Ш0428042804280428Ш0428	()I
    //   103: imul
    //   104: getstatic 90	kkkkkk/kkyykk:bь044C044C044Cь044Cь044Cь	I
    //   107: irem
    //   108: getstatic 92	kkkkkk/kkyykk:bьь044C044Cь044Cь044Cь	I
    //   111: if_icmpeq +12 -> 123
    //   114: bipush 13
    //   116: putstatic 86	kkkkkk/kkyykk:b044C044Cь044Cь044Cь044Cь	I
    //   119: iconst_0
    //   120: putstatic 92	kkkkkk/kkyykk:bьь044C044Cь044Cь044Cь	I
    //   123: aload_0
    //   124: aload_1
    //   125: aload_2
    //   126: aload_3
    //   127: invokevirtual 661	kkkkkk/kkyykk:bШШШШШШШШ04280428	(Ljava/lang/String;Lcom/liveperson/infra/LPAuthenticationParams;Lcom/liveperson/infra/ConversationViewParams;)V
    //   130: aload_0
    //   131: getfield 140	kkkkkk/kkyykk:bььььь044Cь044Cь	Lkkkkkk/mcmccc;
    //   134: astore_2
    //   135: aload_2
    //   136: aload_1
    //   137: invokevirtual 979	kkkkkk/mcmccc:bФФФ0424ФФФФФ0424	(Ljava/lang/String;)V
    //   140: return
    //   141: astore_1
    //   142: aload_1
    //   143: athrow
    //   144: astore_1
    //   145: aload_1
    //   146: athrow
    // Local variable table:
    //   start	length	slot	name	signature
    //   0	147	0	this	kkyykk
    //   0	147	1	paramString	String
    //   0	147	2	paramLPAuthenticationParams	LPAuthenticationParams
    //   0	147	3	paramConversationViewParams	ConversationViewParams
    //   17	11	4	i	int
    //   3	72	5	str1	String
    //   12	65	6	localStringBuilder	StringBuilder
    //   72	7	7	str2	String
    // Exception table:
    //   from	to	target	type
    //   0	14	141	java/lang/Exception
    //   74	93	141	java/lang/Exception
    //   123	135	141	java/lang/Exception
    //   63	74	144	java/lang/Exception
    //   135	140	144	java/lang/Exception
  }
  
  /* Error */
  public boolean bШШШ0428Ш04280428ШШ0428(String paramString)
  {
    // Byte code:
    //   0: iconst_0
    //   1: istore 7
    //   3: aload_0
    //   4: getfield 159	kkkkkk/kkyykk:b044Cьь044C044Cьь044Cь	Lkkkkkk/eeefee;
    //   7: aload_1
    //   8: invokevirtual 266	kkkkkk/eeefee:b0424Ф04240424042404240424042404240424	(Ljava/lang/String;)Z
    //   11: ifeq +24 -> 35
    //   14: getstatic 106	kkkkkk/kkyykk:bььь044C044Cьь044Cь	Ljava/lang/String;
    //   17: ldc_w 982
    //   20: bipush 79
    //   22: sipush 242
    //   25: iconst_3
    //   26: invokestatic 78	kkkkkk/gguuuu:bк043Aккк043Aкк043A043A	(Ljava/lang/String;CCC)Ljava/lang/String;
    //   29: invokestatic 985	kkkkkk/xtxtxt:bии0438043804380438и0438ии	(Ljava/lang/String;Ljava/lang/String;)V
    //   32: iload 7
    //   34: ireturn
    //   35: aload_0
    //   36: getfield 154	kkkkkk/kkyykk:b044C044Cь044C044Cьь044Cь	Lkkkkkk/ggggga;
    //   39: aload_1
    //   40: invokevirtual 988	kkkkkk/ggggga:bэ044Dэээ044D044D044Dээ	(Ljava/lang/String;)Lkkkkkk/xddxxx;
    //   43: new 990	kkkkkk/kkyykk$12
    //   46: dup
    //   47: aload_0
    //   48: invokespecial 991	kkkkkk/kkyykk$12:<init>	(Lkkkkkk/kkyykk;)V
    //   51: invokevirtual 411	kkkkkk/xddxxx:b04380438и0438ии0438иии	(Lkkkkkk/xddxxx$ddxxxx;)Lkkkkkk/xddxxx;
    //   54: astore 9
    //   56: aload 9
    //   58: invokevirtual 414	kkkkkk/xddxxx:b0438ии0438ии0438иии	()V
    //   61: aload_0
    //   62: getfield 159	kkkkkk/kkyykk:b044Cьь044C044Cьь044Cь	Lkkkkkk/eeefee;
    //   65: aload_1
    //   66: invokevirtual 994	kkkkkk/eeefee:b042404240424ФФ04240424042404240424	(Ljava/lang/String;)Lkkkkkk/xddxxx;
    //   69: new 996	kkkkkk/kkyykk$13
    //   72: dup
    //   73: aload_0
    //   74: invokespecial 997	kkkkkk/kkyykk$13:<init>	(Lkkkkkk/kkyykk;)V
    //   77: invokevirtual 411	kkkkkk/xddxxx:b04380438и0438ии0438иии	(Lkkkkkk/xddxxx$ddxxxx;)Lkkkkkk/xddxxx;
    //   80: invokevirtual 414	kkkkkk/xddxxx:b0438ии0438ии0438иии	()V
    //   83: iconst_1
    //   84: istore 8
    //   86: getstatic 86	kkkkkk/kkyykk:b044C044Cь044Cь044Cь044Cь	I
    //   89: istore_2
    //   90: getstatic 88	kkkkkk/kkyykk:b044Cь044C044Cь044Cь044Cь	I
    //   93: istore_3
    //   94: getstatic 86	kkkkkk/kkyykk:b044C044Cь044Cь044Cь044Cь	I
    //   97: istore 4
    //   99: getstatic 90	kkkkkk/kkyykk:bь044C044C044Cь044Cь044Cь	I
    //   102: istore 5
    //   104: getstatic 92	kkkkkk/kkyykk:bьь044C044Cь044Cь044Cь	I
    //   107: istore 6
    //   109: iload 8
    //   111: istore 7
    //   113: iload_2
    //   114: iload_3
    //   115: iadd
    //   116: iload 4
    //   118: imul
    //   119: iload 5
    //   121: irem
    //   122: iload 6
    //   124: if_icmpeq -92 -> 32
    //   127: iconst_0
    //   128: putstatic 86	kkkkkk/kkyykk:b044C044Cь044Cь044Cь044Cь	I
    //   131: invokestatic 96	kkkkkk/kkyykk:b0428Ш0428Ш0428042804280428Ш0428	()I
    //   134: putstatic 92	kkkkkk/kkyykk:bьь044C044Cь044Cь044Cь	I
    //   137: iload 8
    //   139: istore 7
    //   141: getstatic 86	kkkkkk/kkyykk:b044C044Cь044Cь044Cь044Cь	I
    //   144: getstatic 88	kkkkkk/kkyykk:b044Cь044C044Cь044Cь044Cь	I
    //   147: iadd
    //   148: getstatic 86	kkkkkk/kkyykk:b044C044Cь044Cь044Cь044Cь	I
    //   151: imul
    //   152: getstatic 90	kkkkkk/kkyykk:bь044C044C044Cь044Cь044Cь	I
    //   155: irem
    //   156: getstatic 92	kkkkkk/kkyykk:bьь044C044Cь044Cь044Cь	I
    //   159: if_icmpeq -127 -> 32
    //   162: bipush 54
    //   164: putstatic 86	kkkkkk/kkyykk:b044C044Cь044Cь044Cь044Cь	I
    //   167: invokestatic 96	kkkkkk/kkyykk:b0428Ш0428Ш0428042804280428Ш0428	()I
    //   170: putstatic 92	kkkkkk/kkyykk:bьь044C044Cь044Cь044Cь	I
    //   173: iconst_1
    //   174: ireturn
    //   175: astore_1
    //   176: aload_1
    //   177: athrow
    //   178: astore_1
    //   179: aload_1
    //   180: athrow
    //   181: astore_1
    //   182: aload_1
    //   183: athrow
    //   184: astore_1
    //   185: aload_1
    //   186: athrow
    // Local variable table:
    //   start	length	slot	name	signature
    //   0	187	0	this	kkyykk
    //   0	187	1	paramString	String
    //   89	27	2	i	int
    //   93	23	3	j	int
    //   97	22	4	k	int
    //   102	20	5	m	int
    //   107	18	6	n	int
    //   1	139	7	bool1	boolean
    //   84	54	8	bool2	boolean
    //   54	3	9	localXddxxx	xddxxx
    // Exception table:
    //   from	to	target	type
    //   3	32	175	java/lang/Exception
    //   56	83	175	java/lang/Exception
    //   127	137	178	java/lang/Exception
    //   176	178	178	java/lang/Exception
    //   182	184	178	java/lang/Exception
    //   35	56	181	java/lang/Exception
    //   86	109	184	java/lang/Exception
  }
  
  /* Error */
  public void bШШШ0428ШШШ0428Ш0428(wnwnwn paramWnwnwn)
  {
    // Byte code:
    //   0: aload_0
    //   1: getfield 121	kkkkkk/kkyykk:b044C044Cььь044Cь044Cь	Lkkkkkk/hhhbhh;
    //   4: astore 7
    //   6: getstatic 86	kkkkkk/kkyykk:b044C044Cь044Cь044Cь044Cь	I
    //   9: istore_2
    //   10: getstatic 88	kkkkkk/kkyykk:b044Cь044C044Cь044Cь044Cь	I
    //   13: istore_3
    //   14: getstatic 86	kkkkkk/kkyykk:b044C044Cь044Cь044Cь044Cь	I
    //   17: istore 4
    //   19: getstatic 90	kkkkkk/kkyykk:bь044C044C044Cь044Cь044Cь	I
    //   22: istore 5
    //   24: getstatic 92	kkkkkk/kkyykk:bьь044C044Cь044Cь044Cь	I
    //   27: istore 6
    //   29: iload_2
    //   30: iload_3
    //   31: iadd
    //   32: iload 4
    //   34: imul
    //   35: iload 5
    //   37: irem
    //   38: iload 6
    //   40: if_icmpeq +57 -> 97
    //   43: getstatic 86	kkkkkk/kkyykk:b044C044Cь044Cь044Cь044Cь	I
    //   46: istore_2
    //   47: iload_2
    //   48: invokestatic 230	kkkkkk/kkyykk:bШШ0428Ш0428042804280428Ш0428	()I
    //   51: iload_2
    //   52: iadd
    //   53: imul
    //   54: getstatic 90	kkkkkk/kkyykk:bь044C044C044Cь044Cь044Cь	I
    //   57: irem
    //   58: tableswitch	default:+18->76, 0:+28->86
    //   76: bipush 69
    //   78: putstatic 86	kkkkkk/kkyykk:b044C044Cь044Cь044Cь044Cь	I
    //   81: bipush 69
    //   83: putstatic 92	kkkkkk/kkyykk:bьь044C044Cь044Cь044Cь	I
    //   86: invokestatic 96	kkkkkk/kkyykk:b0428Ш0428Ш0428042804280428Ш0428	()I
    //   89: putstatic 86	kkkkkk/kkyykk:b044C044Cь044Cь044Cь044Cь	I
    //   92: bipush 49
    //   94: putstatic 92	kkkkkk/kkyykk:bьь044C044Cь044Cь044Cь	I
    //   97: aload 7
    //   99: aload_1
    //   100: invokevirtual 1002	kkkkkk/hhhbhh:bШ0428Ш0428Ш0428Ш0428Ш0428	(Lkkkkkk/wnwnwn;)V
    //   103: return
    //   104: astore_1
    //   105: aload_1
    //   106: athrow
    //   107: astore_1
    //   108: aload_1
    //   109: athrow
    // Local variable table:
    //   start	length	slot	name	signature
    //   0	110	0	this	kkyykk
    //   0	110	1	paramWnwnwn	wnwnwn
    //   9	45	2	i	int
    //   13	19	3	j	int
    //   17	18	4	k	int
    //   22	16	5	m	int
    //   27	14	6	n	int
    //   4	94	7	localHhhbhh	hhhbhh
    // Exception table:
    //   from	to	target	type
    //   0	29	104	java/lang/Exception
    //   86	92	104	java/lang/Exception
    //   97	103	104	java/lang/Exception
    //   92	97	107	java/lang/Exception
  }
  
  public void bШШШШ042804280428ШШ0428(Context paramContext, kyykky paramKyykky, vovoov paramVovoov)
  {
    xxdxxd localXxdxxd = xxdxxd.instance;
    switch (0)
    {
    case 1: 
    default: 
      for (;;)
      {
        switch (0)
        {
        }
      }
    }
    switch (1)
    {
    case 0: 
    default: 
      for (;;)
      {
        switch (0)
        {
        }
      }
    }
    paramVovoov = new kkyykk.2(this, paramVovoov, paramContext, paramKyykky);
    if ((b0428Ш0428Ш0428042804280428Ш0428() + b044Cь044C044Cь044Cь044Cь) * b0428Ш0428Ш0428042804280428Ш0428() % bь044C044C044Cь044Cь044Cь != bШ0428ШШ0428042804280428Ш0428())
    {
      b044C044Cь044Cь044Cь044Cь = 73;
      bьь044C044Cь044Cь044Cь = b0428Ш0428Ш0428042804280428Ш0428();
    }
    if ((b044C044Cь044Cь044Cь044Cь + b044Cь044C044Cь044Cь044Cь) * b044C044Cь044Cь044Cь044Cь % bь044C044C044Cь044Cь044Cь != bьь044C044Cь044Cь044Cь)
    {
      b044C044Cь044Cь044Cь044Cь = b0428Ш0428Ш0428042804280428Ш0428();
      bьь044C044Cь044Cь044Cь = b0428Ш0428Ш0428042804280428Ш0428();
    }
    localXxdxxd.bхххххх0445044504450445(paramContext, paramKyykky, paramVovoov);
  }
  
  public void bШШШШШШШ0428Ш0428(String paramString1, String paramString2, int paramInt1, int paramInt2)
  {
    paramString1 = new jjjyyj(this.bь044C044C044C044Cьь044Cь.b0424ФФ042404240424Ф04240424Ф(paramString1), paramString2, paramInt1, paramInt2);
    try
    {
      paramString1.bххххххх044504450445();
      if ((b044C044Cь044Cь044Cь044Cь + b044Cь044C044Cь044Cь044Cь) * b044C044Cь044Cь044Cь044Cь % bь044C044C044Cь044Cь044Cь != bьь044C044Cь044Cь044Cь)
      {
        b044C044Cь044Cь044Cь044Cь = 92;
        bьь044C044Cь044Cь044Cь = 93;
      }
      return;
    }
    catch (Exception paramString1)
    {
      throw paramString1;
    }
  }
  
  public void bШШШШШШШШ04280428(String paramString, LPAuthenticationParams paramLPAuthenticationParams, @Nullable ConversationViewParams paramConversationViewParams)
  {
    String str = bььь044C044Cьь044Cь;
    StringBuilder localStringBuilder = new StringBuilder();
    int i = b044C044Cь044Cь044Cь044Cь;
    switch (i * (b044Cь044C044Cь044Cь044Cь + i) % bь044C044C044Cь044Cь044Cь)
    {
    default: 
      b044C044Cь044Cь044Cь044Cь = b0428Ш0428Ш0428042804280428Ш0428();
      bьь044C044Cь044Cь044Cь = b0428Ш0428Ш0428042804280428Ш0428();
    }
    localStringBuilder = localStringBuilder.append(gguuuu.bккккк043Aкк043A043A("w\034\026 J\f\033\t\025\nD", '', '\002'));
    if ((b044C044Cь044Cь044Cь044Cь + b044Cь044C044Cь044Cь044Cь) * b044C044Cь044Cь044Cь044Cь % bь044C044C044Cь044Cь044Cь != bьь044C044Cь044Cь044Cь)
    {
      b044C044Cь044Cь044Cь044Cь = b0428Ш0428Ш0428042804280428Ш0428();
      bьь044C044Cь044Cь044Cь = 66;
    }
    xtxtxt.bии0438и04380438и0438ии(str, paramString);
    this.bь044C044C044C044Cьь044Cь.bФФФФ04240424Ф04240424Ф(paramString);
    this.bь044C044C044C044Cьь044Cь.bФ04240424ФФФ042404240424Ф(paramString, paramLPAuthenticationParams);
    if (paramConversationViewParams != null)
    {
      switch (0)
      {
      case 1: 
      default: 
        for (;;)
        {
          switch (1)
          {
          }
        }
      }
      bШ0428Ш0428ШШШШ04280428(paramConversationViewParams);
    }
    this.bььььь044Cь044Cь.bФФ0424Ф04240424042404240424Ф(paramString);
  }
}
