package kkkkkk;

import android.content.Context;
import java.io.BufferedInputStream;
import java.io.File;
import java.io.IOException;
import java.util.ArrayList;
import java.util.List;
import java.util.zip.ZipFile;

public final class knkkkk
{
  public static int b041E041E041E041EОО041E041EО = 5;
  private static final String b041E041EО041EОО041E041EО = ":\006sy";
  private static final int b041EО041E041EОО041E041EО = 16384;
  public static int b041EООО041EО041E041EО = 0;
  private static final long bО041E041E041EОО041E041EО = -1L;
  public static int bО041EОО041EО041E041EО = 2;
  private static final int bОО041E041EОО041E041EО = 3;
  public static int bОООО041EО041E041EО = 1;
  
  /* Error */
  static
  {
    // Byte code:
    //   0: getstatic 31	kkkkkk/knkkkk:b041E041EО041EОО041E041EО	Ljava/lang/String;
    //   3: astore_3
    //   4: aload_3
    //   5: sipush 250
    //   8: iconst_2
    //   9: invokestatic 37	kkkkkk/gguuuu:bккккк043Aкк043A043A	(Ljava/lang/String;CC)Ljava/lang/String;
    //   12: putstatic 31	kkkkkk/knkkkk:b041E041EО041EОО041E041EО	Ljava/lang/String;
    //   15: getstatic 39	kkkkkk/knkkkk:b041E041E041E041EОО041E041EО	I
    //   18: istore_0
    //   19: iload_0
    //   20: getstatic 41	kkkkkk/knkkkk:bОООО041EО041E041EО	I
    //   23: iload_0
    //   24: iadd
    //   25: imul
    //   26: getstatic 43	kkkkkk/knkkkk:bО041EОО041EО041E041EО	I
    //   29: irem
    //   30: tableswitch	default:+18->48, 0:+29->59
    //   48: invokestatic 47	kkkkkk/knkkkk:bЗ04170417З0417З0417041704170417	()I
    //   51: putstatic 39	kkkkkk/knkkkk:b041E041E041E041EОО041E041EО	I
    //   54: bipush 65
    //   56: putstatic 49	kkkkkk/knkkkk:b041EООО041EО041E041EО	I
    //   59: iconst_1
    //   60: tableswitch	default:+24->84, 0:+-45->15, 1:+51->111
    //   84: iconst_1
    //   85: tableswitch	default:+23->108, 0:+-70->15, 1:+26->111
    //   108: goto -24 -> 84
    //   111: getstatic 39	kkkkkk/knkkkk:b041E041E041E041EОО041E041EО	I
    //   114: istore_0
    //   115: getstatic 41	kkkkkk/knkkkk:bОООО041EО041E041EО	I
    //   118: istore_1
    //   119: invokestatic 52	kkkkkk/knkkkk:b041704170417З0417З0417041704170417	()I
    //   122: istore_2
    //   123: iload_0
    //   124: iload_1
    //   125: iload_0
    //   126: iadd
    //   127: imul
    //   128: iload_2
    //   129: irem
    //   130: tableswitch	default:+18->148, 0:+29->159
    //   148: invokestatic 47	kkkkkk/knkkkk:bЗ04170417З0417З0417041704170417	()I
    //   151: putstatic 39	kkkkkk/knkkkk:b041E041E041E041EОО041E041EО	I
    //   154: bipush 26
    //   156: putstatic 49	kkkkkk/knkkkk:b041EООО041EО041E041EО	I
    //   159: return
    //   160: astore_3
    //   161: aload_3
    //   162: athrow
    //   163: astore_3
    //   164: aload_3
    //   165: athrow
    // Local variable table:
    //   start	length	slot	name	signature
    //   18	110	0	i	int
    //   118	9	1	j	int
    //   122	8	2	k	int
    //   3	2	3	str	String
    //   160	2	3	localException1	Exception
    //   163	2	3	localException2	Exception
    // Exception table:
    //   from	to	target	type
    //   4	15	160	java/lang/Exception
    //   111	123	160	java/lang/Exception
    //   0	4	163	java/lang/Exception
    //   148	159	163	java/lang/Exception
  }
  
  public knkkkk() {}
  
  public static int b041704170417З0417З0417041704170417()
  {
    return 2;
  }
  
  public static List<File> b04170417З04170417З0417041704170417(Context paramContext, String[] paramArrayOfString, File paramFile)
    throws IOException
  {
    ArrayList localArrayList;
    for (;;)
    {
      int i;
      try
      {
        paramContext = paramContext.getAssets();
        bЗЗ041704170417З0417041704170417(paramFile);
        localArrayList = new ArrayList();
        int m = paramArrayOfString.length;
        i = 0;
        switch (0)
        {
        case 1: 
        default: 
          switch (0)
          {
          }
          break;
        }
        if (i >= m) {
          break;
        }
        String str = paramArrayOfString[i];
        BufferedInputStream localBufferedInputStream = new BufferedInputStream(nknnkk.bххххх04450445ххх(paramContext, str, 2));
        int j = b041E041E041E041EОО041E041EО;
        switch (j * (bОООО041EО041E041EО + j) % b041704170417З0417З0417041704170417())
        {
        default: 
          b041E041E041E041EОО041E041EО = bЗ04170417З0417З0417041704170417();
          bОООО041EО041E041EО = bЗ04170417З0417З0417041704170417();
        }
        File localFile = new File(paramFile, str + gguuuu.bккккк043Aкк043A043A("k9)1", '^', '\004'));
        if ((bЗ04170417З0417З0417041704170417() + b0417З0417З0417З0417041704170417()) * bЗ04170417З0417З0417041704170417() % bО041EОО041EО041E041EО != b041EООО041EО041E041EО)
        {
          b041E041E041E041EОО041E041EО = 44;
          b041EООО041EО041E041EО = bЗ04170417З0417З0417041704170417();
        }
        localArrayList.add(localFile);
        int n = 0;
        j = 0;
        if ((j < 3) && (n == 0))
        {
          int k = j + 1;
          try
          {
            b0417ЗЗ04170417З0417041704170417(localBufferedInputStream, localFile);
            boolean bool = b0417З041704170417З0417041704170417(localFile);
            n = bool;
            j = k;
            if (bool) {
              continue;
            }
            localFile.delete();
            n = bool;
            j = k;
          }
          catch (Exception paramContext)
          {
            throw paramContext;
          }
        }
        if (n == 0)
        {
          paramContext = new IOException(gguuuu.bккккк043Aкк043A043A("g\025\034\024\rI\031\033!M\022\"\026\023'\031T0 (X $(\"]", '', '\001') + localFile.getAbsolutePath() + gguuuu.bккккк043Aкк043A043A(";\003\r\021?\005\007\033C", '', '\001') + str + gguuuu.bк043Aккк043Aкк043A043A("e", 'Ô', '\022', '\000'));
          throw paramContext;
        }
      }
      catch (Exception paramContext)
      {
        throw paramContext;
      }
      i += 1;
    }
    return localArrayList;
  }
  
  public static boolean b0417З041704170417З0417041704170417(File paramFile)
  {
    try
    {
      paramFile = new ZipFile(paramFile);
      if ((b041E041E041E041EОО041E041EО + bОООО041EО041E041EО) * b041E041E041E041EОО041E041EО % b041704170417З0417З0417041704170417() != b041EООО041EО041E041EО)
      {
        b041E041E041E041EОО041E041EО = bЗ04170417З0417З0417041704170417();
        b041EООО041EО041E041EО = 12;
        int i = b041E041E041E041EОО041E041EО;
        switch (i * (bОООО041EО041E041EО + i) % bО041EОО041EО041E041EО)
        {
        default: 
          b041E041E041E041EОО041E041EО = 58;
          b041EООО041EО041E041EО = bЗ04170417З0417З0417041704170417();
        }
      }
      paramFile.close();
      return true;
    }
    catch (Exception paramFile) {}
    return false;
  }
  
  public static int b0417З0417З0417З0417041704170417()
  {
    return 1;
  }
  
  /* Error */
  private static void b0417ЗЗ04170417З0417041704170417(java.io.InputStream paramInputStream, File paramFile)
    throws IOException, java.io.FileNotFoundException
  {
    // Byte code:
    //   0: invokestatic 157	java/lang/System:currentTimeMillis	()J
    //   3: ldc2_w 158
    //   6: ldiv
    //   7: lstore_3
    //   8: new 161	java/util/zip/ZipOutputStream
    //   11: dup
    //   12: new 163	java/io/BufferedOutputStream
    //   15: dup
    //   16: new 165	java/io/FileOutputStream
    //   19: dup
    //   20: aload_1
    //   21: invokespecial 166	java/io/FileOutputStream:<init>	(Ljava/io/File;)V
    //   24: invokespecial 169	java/io/BufferedOutputStream:<init>	(Ljava/io/OutputStream;)V
    //   27: invokespecial 170	java/util/zip/ZipOutputStream:<init>	(Ljava/io/OutputStream;)V
    //   30: astore_1
    //   31: getstatic 39	kkkkkk/knkkkk:b041E041E041E041EОО041E041EО	I
    //   34: istore_2
    //   35: iload_2
    //   36: invokestatic 105	kkkkkk/knkkkk:b0417З0417З0417З0417041704170417	()I
    //   39: iload_2
    //   40: iadd
    //   41: imul
    //   42: getstatic 43	kkkkkk/knkkkk:bО041EОО041EО041E041EО	I
    //   45: irem
    //   46: tableswitch	default:+18->64, 0:+28->74
    //   64: invokestatic 47	kkkkkk/knkkkk:bЗ04170417З0417З0417041704170417	()I
    //   67: putstatic 39	kkkkkk/knkkkk:b041E041E041E041EОО041E041EО	I
    //   70: iconst_4
    //   71: putstatic 49	kkkkkk/knkkkk:b041EООО041EО041E041EО	I
    //   74: new 172	java/util/zip/ZipEntry
    //   77: dup
    //   78: ldc -82
    //   80: bipush 9
    //   82: sipush 181
    //   85: iconst_2
    //   86: invokestatic 136	kkkkkk/gguuuu:bк043Aккк043Aкк043A043A	(Ljava/lang/String;CCC)Ljava/lang/String;
    //   89: invokespecial 175	java/util/zip/ZipEntry:<init>	(Ljava/lang/String;)V
    //   92: astore 5
    //   94: aload 5
    //   96: lload_3
    //   97: invokevirtual 179	java/util/zip/ZipEntry:setTime	(J)V
    //   100: aload_1
    //   101: aload 5
    //   103: invokevirtual 183	java/util/zip/ZipOutputStream:putNextEntry	(Ljava/util/zip/ZipEntry;)V
    //   106: sipush 16384
    //   109: newarray byte
    //   111: astore 5
    //   113: aload_0
    //   114: aload 5
    //   116: invokevirtual 189	java/io/InputStream:read	([B)I
    //   119: istore_2
    //   120: iload_2
    //   121: iconst_m1
    //   122: if_icmpeq +68 -> 190
    //   125: aload_1
    //   126: aload 5
    //   128: iconst_0
    //   129: iload_2
    //   130: invokevirtual 193	java/util/zip/ZipOutputStream:write	([BII)V
    //   133: getstatic 39	kkkkkk/knkkkk:b041E041E041E041EОО041E041EО	I
    //   136: istore_2
    //   137: iload_2
    //   138: invokestatic 105	kkkkkk/knkkkk:b0417З0417З0417З0417041704170417	()I
    //   141: iload_2
    //   142: iadd
    //   143: imul
    //   144: getstatic 43	kkkkkk/knkkkk:bО041EОО041EО041E041EО	I
    //   147: irem
    //   148: tableswitch	default:+20->168, 0:+32->180
    //   168: invokestatic 47	kkkkkk/knkkkk:bЗ04170417З0417З0417041704170417	()I
    //   171: putstatic 39	kkkkkk/knkkkk:b041E041E041E041EОО041E041EО	I
    //   174: invokestatic 47	kkkkkk/knkkkk:bЗ04170417З0417З0417041704170417	()I
    //   177: putstatic 49	kkkkkk/knkkkk:b041EООО041EО041E041EО	I
    //   180: aload_0
    //   181: aload 5
    //   183: invokevirtual 189	java/io/InputStream:read	([B)I
    //   186: istore_2
    //   187: goto -67 -> 120
    //   190: aload_1
    //   191: invokevirtual 196	java/util/zip/ZipOutputStream:closeEntry	()V
    //   194: aload_1
    //   195: invokevirtual 197	java/util/zip/ZipOutputStream:close	()V
    //   198: aload_0
    //   199: invokestatic 201	kkkkkk/knkkkk:bЗЗЗ04170417З0417041704170417	(Ljava/io/Closeable;)V
    //   202: return
    //   203: astore 5
    //   205: aload_1
    //   206: invokevirtual 197	java/util/zip/ZipOutputStream:close	()V
    //   209: aload 5
    //   211: athrow
    //   212: astore_1
    //   213: aload_0
    //   214: invokestatic 201	kkkkkk/knkkkk:bЗЗЗ04170417З0417041704170417	(Ljava/io/Closeable;)V
    //   217: aload_1
    //   218: athrow
    // Local variable table:
    //   start	length	slot	name	signature
    //   0	219	0	paramInputStream	java.io.InputStream
    //   0	219	1	paramFile	File
    //   34	153	2	i	int
    //   7	90	3	l	long
    //   92	90	5	localObject1	Object
    //   203	7	5	localObject2	Object
    // Exception table:
    //   from	to	target	type
    //   74	120	203	finally
    //   125	133	203	finally
    //   180	187	203	finally
    //   190	194	203	finally
    //   8	31	212	finally
    //   194	198	212	finally
    //   205	212	212	finally
  }
  
  public static int bЗ04170417З0417З0417041704170417()
  {
    return 27;
  }
  
  /* Error */
  private static void bЗ0417З04170417З0417041704170417(File paramFile)
    throws IOException
  {
    // Byte code:
    //   0: getstatic 39	kkkkkk/knkkkk:b041E041E041E041EОО041E041EО	I
    //   3: istore_1
    //   4: iload_1
    //   5: getstatic 41	kkkkkk/knkkkk:bОООО041EО041E041EО	I
    //   8: iload_1
    //   9: iadd
    //   10: imul
    //   11: getstatic 43	kkkkkk/knkkkk:bО041EОО041EО041E041EО	I
    //   14: irem
    //   15: tableswitch	default:+189->204, 0:+31->46
    //   32: invokestatic 47	kkkkkk/knkkkk:bЗ04170417З0417З0417041704170417	()I
    //   35: istore_1
    //   36: iload_1
    //   37: putstatic 39	kkkkkk/knkkkk:b041E041E041E041EОО041E041EО	I
    //   40: invokestatic 47	kkkkkk/knkkkk:bЗ04170417З0417З0417041704170417	()I
    //   43: putstatic 49	kkkkkk/knkkkk:b041EООО041EО041E041EО	I
    //   46: aload_0
    //   47: invokevirtual 205	java/io/File:mkdir	()Z
    //   50: pop
    //   51: aload_0
    //   52: invokevirtual 208	java/io/File:isDirectory	()Z
    //   55: ifne +148 -> 203
    //   58: aload_0
    //   59: invokevirtual 212	java/io/File:getParentFile	()Ljava/io/File;
    //   62: pop
    //   63: new 60	java/io/IOException
    //   66: dup
    //   67: new 88	java/lang/StringBuilder
    //   70: dup
    //   71: invokespecial 89	java/lang/StringBuilder:<init>	()V
    //   74: ldc -42
    //   76: sipush 182
    //   79: iconst_2
    //   80: invokestatic 37	kkkkkk/gguuuu:bккккк043Aкк043A043A	(Ljava/lang/String;CC)Ljava/lang/String;
    //   83: invokevirtual 93	java/lang/StringBuilder:append	(Ljava/lang/String;)Ljava/lang/StringBuilder;
    //   86: aload_0
    //   87: invokevirtual 217	java/io/File:getPath	()Ljava/lang/String;
    //   90: invokevirtual 93	java/lang/StringBuilder:append	(Ljava/lang/String;)Ljava/lang/StringBuilder;
    //   93: invokevirtual 99	java/lang/StringBuilder:toString	()Ljava/lang/String;
    //   96: invokespecial 139	java/io/IOException:<init>	(Ljava/lang/String;)V
    //   99: astore_0
    //   100: getstatic 39	kkkkkk/knkkkk:b041E041E041E041EОО041E041EО	I
    //   103: istore_1
    //   104: iload_1
    //   105: getstatic 41	kkkkkk/knkkkk:bОООО041EО041E041EО	I
    //   108: iload_1
    //   109: iadd
    //   110: imul
    //   111: getstatic 43	kkkkkk/knkkkk:bО041EОО041EО041E041EО	I
    //   114: irem
    //   115: tableswitch	default:+17->132, 0:+28->143
    //   132: bipush 42
    //   134: putstatic 39	kkkkkk/knkkkk:b041E041E041E041EОО041E041EО	I
    //   137: invokestatic 47	kkkkkk/knkkkk:bЗ04170417З0417З0417041704170417	()I
    //   140: putstatic 49	kkkkkk/knkkkk:b041EООО041EО041E041EО	I
    //   143: iconst_1
    //   144: tableswitch	default:+24->168, 0:+-44->100, 1:+51->195
    //   168: iconst_1
    //   169: tableswitch	default:+23->192, 0:+-69->100, 1:+26->195
    //   192: goto -24 -> 168
    //   195: aload_0
    //   196: athrow
    //   197: astore_0
    //   198: aload_0
    //   199: athrow
    //   200: astore_0
    //   201: aload_0
    //   202: athrow
    //   203: return
    //   204: goto -172 -> 32
    // Local variable table:
    //   start	length	slot	name	signature
    //   0	207	0	paramFile	File
    //   3	108	1	i	int
    // Exception table:
    //   from	to	target	type
    //   0	32	197	java/lang/Exception
    //   32	36	197	java/lang/Exception
    //   51	100	197	java/lang/Exception
    //   195	197	197	java/lang/Exception
    //   36	46	200	java/lang/Exception
    //   46	51	200	java/lang/Exception
  }
  
  /* Error */
  private static void bЗЗ041704170417З0417041704170417(File paramFile)
    throws IOException
  {
    // Byte code:
    //   0: iconst_0
    //   1: istore_2
    //   2: aload_0
    //   3: invokevirtual 212	java/io/File:getParentFile	()Ljava/io/File;
    //   6: invokestatic 219	kkkkkk/knkkkk:bЗ0417З04170417З0417041704170417	(Ljava/io/File;)V
    //   9: aload_0
    //   10: invokestatic 219	kkkkkk/knkkkk:bЗ0417З04170417З0417041704170417	(Ljava/io/File;)V
    //   13: aload_0
    //   14: invokevirtual 223	java/io/File:listFiles	()[Ljava/io/File;
    //   17: astore_0
    //   18: aload_0
    //   19: ifnonnull +85 -> 104
    //   22: getstatic 39	kkkkkk/knkkkk:b041E041E041E041EОО041E041EО	I
    //   25: getstatic 41	kkkkkk/knkkkk:bОООО041EО041E041EО	I
    //   28: iadd
    //   29: getstatic 39	kkkkkk/knkkkk:b041E041E041E041EОО041E041EО	I
    //   32: imul
    //   33: getstatic 43	kkkkkk/knkkkk:bО041EОО041EО041E041EО	I
    //   36: irem
    //   37: getstatic 49	kkkkkk/knkkkk:b041EООО041EО041E041EО	I
    //   40: if_icmpeq +14 -> 54
    //   43: bipush 81
    //   45: putstatic 39	kkkkkk/knkkkk:b041E041E041E041EОО041E041EО	I
    //   48: invokestatic 47	kkkkkk/knkkkk:bЗ04170417З0417З0417041704170417	()I
    //   51: putstatic 49	kkkkkk/knkkkk:b041EООО041EО041E041EО	I
    //   54: iconst_1
    //   55: tableswitch	default:+21->76, 0:+-33->22, 1:+48->103
    //   76: iconst_0
    //   77: tableswitch	default:+23->100, 0:+26->103, 1:+-55->22
    //   100: goto -24 -> 76
    //   103: return
    //   104: aload_0
    //   105: arraylength
    //   106: istore_3
    //   107: invokestatic 47	kkkkkk/knkkkk:bЗ04170417З0417З0417041704170417	()I
    //   110: istore 4
    //   112: getstatic 41	kkkkkk/knkkkk:bОООО041EО041E041EО	I
    //   115: istore 5
    //   117: invokestatic 47	kkkkkk/knkkkk:bЗ04170417З0417З0417041704170417	()I
    //   120: istore 6
    //   122: getstatic 43	kkkkkk/knkkkk:bО041EОО041EО041E041EО	I
    //   125: istore 7
    //   127: getstatic 49	kkkkkk/knkkkk:b041EООО041EО041E041EО	I
    //   130: istore 8
    //   132: iload_2
    //   133: istore_1
    //   134: iload 4
    //   136: iload 5
    //   138: iadd
    //   139: iload 6
    //   141: imul
    //   142: iload 7
    //   144: irem
    //   145: iload 8
    //   147: if_icmpeq +17 -> 164
    //   150: invokestatic 47	kkkkkk/knkkkk:bЗ04170417З0417З0417041704170417	()I
    //   153: putstatic 39	kkkkkk/knkkkk:b041E041E041E041EОО041E041EО	I
    //   156: invokestatic 47	kkkkkk/knkkkk:bЗ04170417З0417З0417041704170417	()I
    //   159: putstatic 49	kkkkkk/knkkkk:b041EООО041EО041E041EО	I
    //   162: iload_2
    //   163: istore_1
    //   164: iload_1
    //   165: iload_3
    //   166: if_icmpge -63 -> 103
    //   169: aload_0
    //   170: iload_1
    //   171: aaload
    //   172: astore 9
    //   174: aload 9
    //   176: invokevirtual 226	java/io/File:isFile	()Z
    //   179: ifeq +9 -> 188
    //   182: aload 9
    //   184: invokevirtual 123	java/io/File:delete	()Z
    //   187: pop
    //   188: iload_1
    //   189: iconst_1
    //   190: iadd
    //   191: istore_1
    //   192: goto -28 -> 164
    //   195: astore_0
    //   196: aload_0
    //   197: athrow
    //   198: astore_0
    //   199: aload_0
    //   200: athrow
    // Local variable table:
    //   start	length	slot	name	signature
    //   0	201	0	paramFile	File
    //   133	59	1	i	int
    //   1	162	2	j	int
    //   106	61	3	k	int
    //   110	29	4	m	int
    //   115	24	5	n	int
    //   120	22	6	i1	int
    //   125	20	7	i2	int
    //   130	18	8	i3	int
    //   172	11	9	localObject	Object
    // Exception table:
    //   from	to	target	type
    //   2	18	195	java/lang/Exception
    //   104	132	195	java/lang/Exception
    //   174	188	195	java/lang/Exception
    //   150	162	198	java/lang/Exception
  }
  
  /* Error */
  private static void bЗЗЗ04170417З0417041704170417(java.io.Closeable paramCloseable)
  {
    // Byte code:
    //   0: aload_0
    //   1: invokeinterface 229 1 0
    //   6: return
    //   7: astore_0
    //   8: invokestatic 47	kkkkkk/knkkkk:bЗ04170417З0417З0417041704170417	()I
    //   11: istore_1
    //   12: invokestatic 105	kkkkkk/knkkkk:b0417З0417З0417З0417041704170417	()I
    //   15: istore_2
    //   16: invokestatic 47	kkkkkk/knkkkk:bЗ04170417З0417З0417041704170417	()I
    //   19: istore_3
    //   20: getstatic 43	kkkkkk/knkkkk:bО041EОО041EО041E041EО	I
    //   23: istore 4
    //   25: getstatic 39	kkkkkk/knkkkk:b041E041E041E041EОО041E041EО	I
    //   28: getstatic 41	kkkkkk/knkkkk:bОООО041EО041E041EО	I
    //   31: iadd
    //   32: getstatic 39	kkkkkk/knkkkk:b041E041E041E041EОО041E041EО	I
    //   35: imul
    //   36: getstatic 43	kkkkkk/knkkkk:bО041EОО041EО041E041EО	I
    //   39: irem
    //   40: getstatic 49	kkkkkk/knkkkk:b041EООО041EО041E041EО	I
    //   43: if_icmpeq +15 -> 58
    //   46: invokestatic 47	kkkkkk/knkkkk:bЗ04170417З0417З0417041704170417	()I
    //   49: putstatic 39	kkkkkk/knkkkk:b041E041E041E041EОО041E041EО	I
    //   52: invokestatic 47	kkkkkk/knkkkk:bЗ04170417З0417З0417041704170417	()I
    //   55: putstatic 49	kkkkkk/knkkkk:b041EООО041EО041E041EО	I
    //   58: iload_1
    //   59: iload_2
    //   60: iadd
    //   61: iload_3
    //   62: imul
    //   63: iload 4
    //   65: irem
    //   66: getstatic 49	kkkkkk/knkkkk:b041EООО041EО041E041EО	I
    //   69: if_icmpeq -63 -> 6
    //   72: invokestatic 47	kkkkkk/knkkkk:bЗ04170417З0417З0417041704170417	()I
    //   75: putstatic 39	kkkkkk/knkkkk:b041E041E041E041EОО041E041EО	I
    //   78: invokestatic 47	kkkkkk/knkkkk:bЗ04170417З0417З0417041704170417	()I
    //   81: putstatic 49	kkkkkk/knkkkk:b041EООО041EО041E041EО	I
    //   84: return
    //   85: astore_0
    //   86: aload_0
    //   87: athrow
    //   88: astore_0
    //   89: aload_0
    //   90: athrow
    //   91: astore_0
    //   92: aload_0
    //   93: athrow
    // Local variable table:
    //   start	length	slot	name	signature
    //   0	94	0	paramCloseable	java.io.Closeable
    //   11	50	1	i	int
    //   15	46	2	j	int
    //   19	44	3	k	int
    //   23	43	4	m	int
    // Exception table:
    //   from	to	target	type
    //   0	6	7	java/io/IOException
    //   58	84	85	java/lang/Exception
    //   0	6	88	java/lang/Exception
    //   8	25	91	java/lang/Exception
    //   89	91	91	java/lang/Exception
  }
}
