package kkkkkk;

import android.content.Context;
import javax.inject.Inject;

public class laalal
{
  public static int b04320432043204320432ввв04320432 = 16;
  public static int b0432вввв0432вв04320432 = 2;
  public static int bв0432ввв0432вв04320432 = 1;
  public static int bввввв0432вв04320432;
  private final Context b0432в043204320432ввв04320432;
  private final ahhhah bв0432043204320432ввв04320432;
  
  @Inject
  public laalal(Context paramContext, ahhhah paramAhhhah)
  {
    this.b0432в043204320432ввв04320432 = paramContext;
    this.bв0432043204320432ввв04320432 = paramAhhhah;
  }
  
  public static int b0435043504350435ее04350435ее()
  {
    return 1;
  }
  
  public static int b0435еее0435е04350435ее()
  {
    return 31;
  }
  
  public static int bееее0435е04350435ее()
  {
    return 2;
  }
  
  public boolean b04350435ее0435е04350435ее()
  {
    boolean bool1 = false;
    if (nnmnnn.b041804180418И0418И04180418И0418(this.b0432в043204320432ввв04320432))
    {
      boolean bool2 = this.bв0432043204320432ввв04320432.bп043F043F043Fп043F043Fп043F043F(nuuunn.MARKETING_HUB_LLOYDS_ENABLED);
      i = b04320432043204320432ввв04320432;
      switch (i * (bв0432ввв0432вв04320432 + i) % b0432вввв0432вв04320432)
      {
      default: 
        b04320432043204320432ввв04320432 = 76;
        bввввв0432вв04320432 = 18;
      }
      if (bool2) {}
    }
    else if ((!nnmnnn.bИ04180418И0418И04180418И0418(this.b0432в043204320432ввв04320432)) || (!this.bв0432043204320432ввв04320432.bп043F043F043Fп043F043Fп043F043F(nuuunn.MARKETING_HUB_HALIFAX_ENABLED)))
    {
      if (!nnmnnn.b0418И0418И0418И04180418И0418(this.b0432в043204320432ввв04320432)) {
        break label177;
      }
      ahhhah localAhhhah = this.bв0432043204320432ввв04320432;
      nuuunn localNuuunn = nuuunn.MARKETING_HUB_BOS_ENABLED;
      switch (0)
      {
      case 1: 
      default: 
        for (;;)
        {
          switch (0)
          {
          }
        }
      }
      if (!localAhhhah.bп043F043F043Fп043F043Fп043F043F(localNuuunn)) {
        break label177;
      }
    }
    bool1 = true;
    return bool1;
    label177:
    int i = b04320432043204320432ввв04320432;
    switch (i * (bв0432ввв0432вв04320432 + i) % b0432вввв0432вв04320432)
    {
    }
    b04320432043204320432ввв04320432 = 40;
    bввввв0432вв04320432 = 30;
    return false;
  }
  
  /* Error */
  public boolean bе0435ее0435е04350435ее(boolean paramBoolean1, boolean paramBoolean2)
  {
    // Byte code:
    //   0: aload_0
    //   1: getfield 24	kkkkkk/laalal:b0432в043204320432ввв04320432	Landroid/content/Context;
    //   4: invokevirtual 82	android/content/Context:getResources	()Landroid/content/res/Resources;
    //   7: getstatic 87	com/mobile/ui/R$bool:is_retail_app	I
    //   10: invokevirtual 93	android/content/res/Resources:getBoolean	(I)Z
    //   13: ifeq +76 -> 89
    //   16: iload_1
    //   17: ifne +72 -> 89
    //   20: aload_0
    //   21: invokevirtual 95	kkkkkk/laalal:b04350435ее0435е04350435ее	()Z
    //   24: ifne +16 -> 40
    //   27: iload_2
    //   28: ifeq +61 -> 89
    //   31: aload_0
    //   32: invokevirtual 98	kkkkkk/laalal:bее0435е0435е04350435ее	()Z
    //   35: istore_1
    //   36: iload_1
    //   37: ifeq +52 -> 89
    //   40: iconst_1
    //   41: istore_1
    //   42: getstatic 54	kkkkkk/laalal:b04320432043204320432ввв04320432	I
    //   45: istore_3
    //   46: iload_3
    //   47: getstatic 56	kkkkkk/laalal:bв0432ввв0432вв04320432	I
    //   50: iload_3
    //   51: iadd
    //   52: imul
    //   53: getstatic 58	kkkkkk/laalal:b0432вввв0432вв04320432	I
    //   56: irem
    //   57: tableswitch	default:+19->76, 0:+30->87
    //   76: invokestatic 100	kkkkkk/laalal:b0435еее0435е04350435ее	()I
    //   79: putstatic 54	kkkkkk/laalal:b04320432043204320432ввв04320432	I
    //   82: bipush 15
    //   84: putstatic 60	kkkkkk/laalal:bввввв0432вв04320432	I
    //   87: iload_1
    //   88: ireturn
    //   89: iconst_0
    //   90: istore_2
    //   91: getstatic 54	kkkkkk/laalal:b04320432043204320432ввв04320432	I
    //   94: istore_3
    //   95: invokestatic 102	kkkkkk/laalal:b0435043504350435ее04350435ее	()I
    //   98: istore 4
    //   100: getstatic 54	kkkkkk/laalal:b04320432043204320432ввв04320432	I
    //   103: istore 5
    //   105: iload_2
    //   106: istore_1
    //   107: iload_3
    //   108: iload 4
    //   110: iadd
    //   111: iload 5
    //   113: imul
    //   114: getstatic 58	kkkkkk/laalal:b0432вввв0432вв04320432	I
    //   117: irem
    //   118: getstatic 60	kkkkkk/laalal:bввввв0432вв04320432	I
    //   121: if_icmpeq -79 -> 42
    //   124: invokestatic 100	kkkkkk/laalal:b0435еее0435е04350435ее	()I
    //   127: istore_3
    //   128: iload_3
    //   129: putstatic 54	kkkkkk/laalal:b04320432043204320432ввв04320432	I
    //   132: bipush 13
    //   134: putstatic 60	kkkkkk/laalal:bввввв0432вв04320432	I
    //   137: iload_2
    //   138: istore_1
    //   139: goto -97 -> 42
    //   142: astore 6
    //   144: aload 6
    //   146: athrow
    //   147: astore 6
    //   149: aload 6
    //   151: athrow
    // Local variable table:
    //   start	length	slot	name	signature
    //   0	152	0	this	laalal
    //   0	152	1	paramBoolean1	boolean
    //   0	152	2	paramBoolean2	boolean
    //   45	84	3	i	int
    //   98	13	4	j	int
    //   103	11	5	k	int
    //   142	3	6	localException1	Exception
    //   147	3	6	localException2	Exception
    // Exception table:
    //   from	to	target	type
    //   107	128	142	java/lang/Exception
    //   132	137	142	java/lang/Exception
    //   0	16	147	java/lang/Exception
    //   20	27	147	java/lang/Exception
    //   31	36	147	java/lang/Exception
    //   91	105	147	java/lang/Exception
    //   128	132	147	java/lang/Exception
  }
  
  /* Error */
  public boolean bее0435е0435е04350435ее()
  {
    // Byte code:
    //   0: aload_0
    //   1: getfield 24	kkkkkk/laalal:b0432в043204320432ввв04320432	Landroid/content/Context;
    //   4: invokestatic 63	kkkkkk/nnmnnn:bИ04180418И0418И04180418И0418	(Landroid/content/Context;)Z
    //   7: ifeq +16 -> 23
    //   10: aload_0
    //   11: getfield 26	kkkkkk/laalal:bв0432043204320432ввв04320432	Lkkkkkk/ahhhah;
    //   14: getstatic 72	kkkkkk/nuuunn:MARKETING_HUB_BOS_ENABLED	Lkkkkkk/nuuunn;
    //   17: invokevirtual 52	kkkkkk/ahhhah:bп043F043F043Fп043F043Fп043F043F	(Lkkkkkk/nuuunn;)Z
    //   20: ifne +110 -> 130
    //   23: aload_0
    //   24: getfield 24	kkkkkk/laalal:b0432в043204320432ввв04320432	Landroid/content/Context;
    //   27: invokestatic 69	kkkkkk/nnmnnn:b0418И0418И0418И04180418И0418	(Landroid/content/Context;)Z
    //   30: istore 6
    //   32: getstatic 54	kkkkkk/laalal:b04320432043204320432ввв04320432	I
    //   35: getstatic 56	kkkkkk/laalal:bв0432ввв0432вв04320432	I
    //   38: iadd
    //   39: getstatic 54	kkkkkk/laalal:b04320432043204320432ввв04320432	I
    //   42: imul
    //   43: invokestatic 104	kkkkkk/laalal:bееее0435е04350435ее	()I
    //   46: irem
    //   47: getstatic 60	kkkkkk/laalal:bввввв0432вв04320432	I
    //   50: if_icmpeq +13 -> 63
    //   53: bipush 51
    //   55: putstatic 54	kkkkkk/laalal:b04320432043204320432ввв04320432	I
    //   58: bipush 24
    //   60: putstatic 60	kkkkkk/laalal:bввввв0432вв04320432	I
    //   63: iload 6
    //   65: ifeq +77 -> 142
    //   68: invokestatic 100	kkkkkk/laalal:b0435еее0435е04350435ее	()I
    //   71: istore_1
    //   72: getstatic 56	kkkkkk/laalal:bв0432ввв0432вв04320432	I
    //   75: istore_2
    //   76: invokestatic 100	kkkkkk/laalal:b0435еее0435е04350435ее	()I
    //   79: istore_3
    //   80: getstatic 58	kkkkkk/laalal:b0432вввв0432вв04320432	I
    //   83: istore 4
    //   85: getstatic 60	kkkkkk/laalal:bввввв0432вв04320432	I
    //   88: istore 5
    //   90: iload_1
    //   91: iload_2
    //   92: iadd
    //   93: iload_3
    //   94: imul
    //   95: iload 4
    //   97: irem
    //   98: iload 5
    //   100: if_icmpeq +13 -> 113
    //   103: iconst_3
    //   104: putstatic 54	kkkkkk/laalal:b04320432043204320432ввв04320432	I
    //   107: invokestatic 100	kkkkkk/laalal:b0435еее0435е04350435ее	()I
    //   110: putstatic 60	kkkkkk/laalal:bввввв0432вв04320432	I
    //   113: aload_0
    //   114: getfield 26	kkkkkk/laalal:bв0432043204320432ввв04320432	Lkkkkkk/ahhhah;
    //   117: getstatic 66	kkkkkk/nuuunn:MARKETING_HUB_HALIFAX_ENABLED	Lkkkkkk/nuuunn;
    //   120: invokevirtual 52	kkkkkk/ahhhah:bп043F043F043Fп043F043Fп043F043F	(Lkkkkkk/nuuunn;)Z
    //   123: istore 6
    //   125: iload 6
    //   127: ifeq +15 -> 142
    //   130: iconst_1
    //   131: ireturn
    //   132: astore 7
    //   134: aload 7
    //   136: athrow
    //   137: astore 7
    //   139: aload 7
    //   141: athrow
    //   142: iconst_0
    //   143: ireturn
    //   144: astore 7
    //   146: aload 7
    //   148: athrow
    // Local variable table:
    //   start	length	slot	name	signature
    //   0	149	0	this	laalal
    //   71	22	1	i	int
    //   75	18	2	j	int
    //   79	16	3	k	int
    //   83	15	4	m	int
    //   88	13	5	n	int
    //   30	96	6	bool	boolean
    //   132	3	7	localException1	Exception
    //   137	3	7	localException2	Exception
    //   144	3	7	localException3	Exception
    // Exception table:
    //   from	to	target	type
    //   0	23	132	java/lang/Exception
    //   23	32	132	java/lang/Exception
    //   113	125	132	java/lang/Exception
    //   68	90	137	java/lang/Exception
    //   134	137	137	java/lang/Exception
    //   103	113	144	java/lang/Exception
  }
}
