package kkkkkk;

import android.content.Context;
import android.content.res.Resources;
import com.mobile.ui.R.bool;
import com.mobile.ui.R.string;
import javax.inject.Inject;

public class mmmwmw
{
  public static int b043D043D043D043D043D043D043Dн043D = 57;
  private static final String b043Dн043D043D043D043D043Dн043D = "\036\026\022\024\024\033\021A\025\031\017\003V;";
  public static int b043Dнннннн043D043D = 1;
  public static int bн043Dннннн043D043D = 2;
  private static final String bнн043D043D043D043D043Dн043D = "";
  public static int bннннннн043D043D;
  private Context bн043D043D043D043D043D043Dн043D;
  
  static
  {
    String str = b043Dн043D043D043D043D043Dн043D;
    if ((b043D043D043D043D043D043D043Dн043D + b043Dнннннн043D043D) * b043D043D043D043D043D043D043Dн043D % bн043Dннннн043D043D != bннннннн043D043D)
    {
      b043D043D043D043D043D043D043Dн043D = 35;
      bннннннн043D043D = 24;
    }
    str = gguuuu.bккккк043Aкк043A043A(str, '', '\002');
    switch (1)
    {
    case 0: 
    default: 
      for (;;)
      {
        switch (1)
        {
        }
      }
    }
    b043Dн043D043D043D043D043Dн043D = str;
  }
  
  @Inject
  public mmmwmw(Context paramContext)
  {
    this.bн043D043D043D043D043D043Dн043D = paramContext;
  }
  
  @ooiiio("Mapping code")
  private String b043004300430а043004300430а04300430(rcrccr paramRcrccr)
  {
    switch (mmmwmw.1.b043D043Dннннн043D043D[paramRcrccr.ordinal()])
    {
    default: 
      throw new IllegalArgumentException(gguuuu.bккккк043Aкк043A043A("\007~z||\004y*}\002wk?$", 'Î', '\002') + paramRcrccr);
    case 1: 
      return this.bн043D043D043D043D043D043Dн043D.getString(R.string.click_to_call_textphone_number_arrangements);
    case 2: 
      if ((b043D043D043D043D043D043D043Dн043D + b043Dнннннн043D043D) * b043D043D043D043D043D043D043Dн043D % bн043Dннннн043D043D != bааа0430а04300430а04300430())
      {
        b043D043D043D043D043D043D043Dн043D = b043004300430аа04300430а04300430();
        bннннннн043D043D = b043004300430аа04300430а04300430();
      }
      return this.bн043D043D043D043D043D043Dн043D.getString(R.string.click_to_call_textphone_number_suspected_fraud);
    case 3: 
      return this.bн043D043D043D043D043D043Dн043D.getString(R.string.click_to_call_textphone_number_lost_or_stolen_card);
    case 4: 
      return this.bн043D043D043D043D043D043Dн043D.getString(R.string.click_to_call_textphone_number_emergency_cash_abroad);
    case 5: 
      return this.bн043D043D043D043D043D043Dн043D.getString(R.string.click_to_call_textphone_number_medical_assistance_abroad);
    case 6: 
    case 15: 
      return this.bн043D043D043D043D043D043Dн043D.getString(R.string.click_to_call_textphone_number_other_banking_queries);
    case 7: 
      return this.bн043D043D043D043D043D043Dн043D.getString(R.string.click_to_call_textphone_number_internet_banking);
    }
    return this.bн043D043D043D043D043D043Dн043D.getString(R.string.click_to_call_textphone_number_sales);
  }
  
  public static int b043004300430аа04300430а04300430()
  {
    return 10;
  }
  
  @ooiiio("Trivial")
  private String b04300430аа043004300430а04300430(String paramString)
  {
    StringBuilder localStringBuilder = new StringBuilder();
    int i = 0;
    while (i < paramString.length())
    {
      localStringBuilder.append(paramString.charAt(i));
      if (i < paramString.length() - 1) {
        localStringBuilder.append(gguuuu.bк043Aккк043Aкк043A043A("U", '±', 'æ', '\000'));
      }
      switch (1)
      {
      case 0: 
      default: 
        for (;;)
        {
          switch (1)
          {
          }
        }
      }
      i += 1;
    }
    return localStringBuilder.toString();
  }
  
  public static int b0430аа0430а04300430а04300430()
  {
    return 1;
  }
  
  public static int bа04300430аа04300430а04300430()
  {
    return 2;
  }
  
  public static int bааа0430а04300430а04300430()
  {
    return 0;
  }
  
  public String b0430043004300430а04300430а04300430()
  {
    throw new Runtime("d2j fail translate: java.lang.IndexOutOfBoundsException: fromIndex < 0: -1\n\tat java.util.BitSet.nextSetBit(BitSet.java:712)\n\tat com.googlecode.dex2jar.ir.ts.array.FillArrayTransformer.makeSureAllElementAreAssigned(FillArrayTransformer.java:505)\n\tat com.googlecode.dex2jar.ir.ts.array.FillArrayTransformer.transformReportChanged(FillArrayTransformer.java:123)\n\tat com.googlecode.dex2jar.ir.ts.StatedTransformer.transform(StatedTransformer.java:10)\n\tat com.googlecode.d2j.dex.Dex2jar$2.optimize(Dex2jar.java:149)\n\tat com.googlecode.d2j.dex.Dex2Asm.convertCode(Dex2Asm.java:414)\n\tat com.googlecode.d2j.dex.ExDex2Asm.convertCode(ExDex2Asm.java:42)\n\tat com.googlecode.d2j.dex.Dex2jar$2.convertCode(Dex2jar.java:128)\n\tat com.googlecode.d2j.dex.Dex2Asm.convertMethod(Dex2Asm.java:509)\n\tat com.googlecode.d2j.dex.Dex2Asm.convertClass(Dex2Asm.java:406)\n\tat com.googlecode.d2j.dex.Dex2Asm.convertDex(Dex2Asm.java:422)\n\tat com.googlecode.d2j.dex.Dex2jar.doTranslate(Dex2jar.java:172)\n\tat com.googlecode.d2j.dex.Dex2jar.to(Dex2jar.java:272)\n\tat com.googlecode.dex2jar.tools.Dex2jarCmd.doCommandLine(Dex2jarCmd.java:108)\n\tat com.googlecode.dex2jar.tools.BaseCmd.doMain(BaseCmd.java:288)\n\tat com.googlecode.dex2jar.tools.Dex2jarCmd.main(Dex2jarCmd.java:32)\n");
  }
  
  public String b04300430а0430а04300430а04300430(rcrccr paramRcrccr)
  {
    Context localContext = this.bн043D043D043D043D043D043Dн043D;
    int i = b043D043D043D043D043D043D043Dн043D;
    switch (i * (b043Dнннннн043D043D + i) % bн043Dннннн043D043D)
    {
    default: 
      b043D043D043D043D043D043D043Dн043D = b043004300430аа04300430а04300430();
      bннннннн043D043D = 51;
    }
    i = R.string.click_to_call_call_us_textphone_content_restricted_sales_accessible;
    paramRcrccr = b04300430аа043004300430а04300430(b043004300430а043004300430а04300430(paramRcrccr));
    int j = b043004300430аа04300430а04300430();
    switch (j * (b043Dнннннн043D043D + j) % bн043Dннннн043D043D)
    {
    default: 
      b043D043D043D043D043D043D043Dн043D = b043004300430аа04300430а04300430();
      bннннннн043D043D = b043004300430аа04300430а04300430();
    }
    return localContext.getString(i, new Object[] { paramRcrccr });
  }
  
  @ooiiio("Mapping code")
  public String b0430а04300430а04300430а04300430(rcrccr paramRcrccr)
  {
    for (;;)
    {
      try
      {
        switch (mmmwmw.1.b043D043Dннннн043D043D[paramRcrccr.ordinal()])
        {
        case 15: 
          throw new IllegalArgumentException(gguuuu.bк043Aккк043Aкк043A043A("\023\013\007\t\t\020\0066\n\016\004wK0", 'è', '÷', '\002') + paramRcrccr);
        }
      }
      catch (Exception paramRcrccr)
      {
        throw paramRcrccr;
      }
      try
      {
        paramRcrccr = this.bн043D043D043D043D043D043Dн043D.getString(R.string.click_to_call_change_of_address_copy);
        return paramRcrccr;
      }
      catch (Exception paramRcrccr)
      {
        String str;
        int i;
        throw paramRcrccr;
      }
      if ((b043D043D043D043D043D043D043Dн043D + b043Dнннннн043D043D) * b043D043D043D043D043D043D043Dн043D % bн043Dннннн043D043D != bннннннн043D043D)
      {
        b043D043D043D043D043D043D043Dн043D = 33;
        bннннннн043D043D = 84;
      }
      paramRcrccr = this.bн043D043D043D043D043D043Dн043D.getString(R.string.click_to_call_lost_stolen_supporting_copy);
      return paramRcrccr;
      paramRcrccr = this.bн043D043D043D043D043D043Dн043D.getString(R.string.click_to_call_new_loan_supporting_copy);
      return paramRcrccr;
      paramRcrccr = this.bн043D043D043D043D043D043Dн043D.getString(R.string.click_to_call_internet_banking_supporting_copy);
      return paramRcrccr;
      paramRcrccr = this.bн043D043D043D043D043D043Dн043D;
      paramRcrccr = paramRcrccr.getString(R.string.click_to_call_personal_account_supporting_copy);
      return paramRcrccr;
      return this.bн043D043D043D043D043D043Dн043D.getString(R.string.click_to_call_new_mortgage_supporting_copy);
      str = this.bн043D043D043D043D043D043Dн043D.getString(R.string.click_to_call_emergency_cash_supporting_copy);
      i = b043D043D043D043D043D043D043Dн043D;
      paramRcrccr = str;
      switch (i * (b043Dнннннн043D043D + i) % bн043Dннннн043D043D)
      {
      }
      b043D043D043D043D043D043D043Dн043D = 79;
      bннннннн043D043D = b043004300430аа04300430а04300430();
      return str;
      return this.bн043D043D043D043D043D043Dн043D.getString(R.string.click_to_call_new_isa_account_supporting_copy);
      paramRcrccr = this.bн043D043D043D043D043D043Dн043D.getString(R.string.click_to_call_new_credit_card_supporting_copy);
      return paramRcrccr;
      return this.bн043D043D043D043D043D043Dн043D.getString(R.string.click_to_call_new_current_account_supporting_copy);
      paramRcrccr = this.bн043D043D043D043D043D043Dн043D.getString(R.string.click_to_call_new_savings_account_supporting_copy);
      return paramRcrccr;
      return this.bн043D043D043D043D043D043Dн043D.getString(R.string.click_to_call_medical_assistance_supporting_copy);
      return this.bн043D043D043D043D043D043Dн043D.getString(R.string.click_to_call_other_banking_query_supporting_copy);
      paramRcrccr = this.bн043D043D043D043D043D043Dн043D.getString(R.string.click_to_call_suspected_fraud_supporting_copy);
      return paramRcrccr;
    }
    return "";
  }
  
  public String b0430а0430а043004300430а04300430(rcrccr paramRcrccr)
  {
    if ((b043D043D043D043D043D043D043Dн043D + b043Dнннннн043D043D) * b043D043D043D043D043D043D043Dн043D % bн043Dннннн043D043D != bннннннн043D043D)
    {
      b043D043D043D043D043D043D043Dн043D = b043004300430аа04300430а04300430();
      bннннннн043D043D = b043004300430аа04300430а04300430();
    }
    int i = b043D043D043D043D043D043D043Dн043D;
    switch (i * (b043Dнннннн043D043D + i) % bн043Dннннн043D043D)
    {
    default: 
      b043D043D043D043D043D043D043Dн043D = b043004300430аа04300430а04300430();
      bннннннн043D043D = 7;
    }
    return this.bн043D043D043D043D043D043Dн043D.getString(R.string.click_to_call_call_us_textphone_content_restricted_sales, new Object[] { b043004300430а043004300430а04300430(paramRcrccr) });
  }
  
  @ooiiio("Trivial")
  public boolean b0430аа0430043004300430а04300430()
  {
    int i = b043D043D043D043D043D043D043Dн043D;
    switch (i * (b043Dнннннн043D043D + i) % bа04300430аа04300430а04300430())
    {
    default: 
      i = b043D043D043D043D043D043D043Dн043D;
      switch (i * (b043Dнннннн043D043D + i) % bн043Dннннн043D043D)
      {
      default: 
        b043D043D043D043D043D043D043Dн043D = 53;
        bннннннн043D043D = 99;
      }
      b043D043D043D043D043D043D043Dн043D = 81;
      bннннннн043D043D = b043004300430аа04300430а04300430();
    }
    try
    {
      boolean bool = this.bн043D043D043D043D043D043Dн043D.getResources().getBoolean(R.bool.click_to_call_sales_journeys_textphone_open_all_hours);
      return bool;
    }
    catch (Exception localException)
    {
      throw localException;
    }
  }
  
  @ooiiio("Mapping code")
  public String b0430ааа043004300430а04300430(rcrccr paramRcrccr)
  {
    switch (mmmwmw.1.b043D043Dннннн043D043D[paramRcrccr.ordinal()])
    {
    default: 
      throw new IllegalArgumentException(gguuuu.bккккк043Aкк043A043A("|vtxz\004{.\004\n\002wM4", '', '\000') + paramRcrccr);
      paramRcrccr = this.bн043D043D043D043D043D043Dн043D;
      int i = b043D043D043D043D043D043D043Dн043D;
      int j = b043Dнннннн043D043D;
      int k = b043D043D043D043D043D043D043Dн043D;
      switch (k * (b0430аа0430а04300430а04300430() + k) % bа04300430аа04300430а04300430())
      {
      default: 
        b043D043D043D043D043D043D043Dн043D = b043004300430аа04300430а04300430();
        bннннннн043D043D = b043004300430аа04300430а04300430();
      }
      switch (i * (j + i) % bн043Dннннн043D043D)
      {
      default: 
        b043D043D043D043D043D043D043Dн043D = b043004300430аа04300430а04300430();
        bннннннн043D043D = b043004300430аа04300430а04300430();
      }
      return paramRcrccr.getString(R.string.click_to_call_opening_hours_new_account);
    case 2: 
    case 3: 
    case 4: 
    case 5: 
    case 6: 
    case 7: 
    case 14: 
    case 15: 
      return "";
    case 8: 
    case 9: 
    case 10: 
    case 11: 
    case 12: 
      switch (0)
      {
      }
      for (;;)
      {
        switch (0)
        {
        }
      }
    }
    return this.bн043D043D043D043D043D043Dн043D.getString(R.string.click_to_call_opening_hours_mortgage);
  }
  
  public String bа043004300430а04300430а04300430()
  {
    try
    {
      String str = this.bн043D043D043D043D043D043Dн043D.getString(R.string.click_to_call_opening_hours_for_change_of_address);
      return str;
    }
    catch (Exception localException)
    {
      throw localException;
    }
  }
  
  public String bа04300430а043004300430а04300430()
  {
    try
    {
      localObject = this.bн043D043D043D043D043D043Dн043D;
    }
    catch (Exception localException1)
    {
      try
      {
        Object localObject;
        int j;
        int k;
        int m;
        int n;
        b043D043D043D043D043D043D043Dн043D = 8;
        bннннннн043D043D = 98;
        int i = b043D043D043D043D043D043D043Dн043D;
        switch (i * (b043Dнннннн043D043D + i) % bн043Dннннн043D043D)
        {
        default: 
          b043D043D043D043D043D043D043Dн043D = b043004300430аа04300430а04300430();
          bннннннн043D043D = b043004300430аа04300430а04300430();
        }
        return localObject;
      }
      catch (Exception localException2)
      {
        throw localException2;
      }
      localException1 = localException1;
      throw localException1;
    }
    localObject = ((Context)localObject).getString(R.string.click_to_call_call_us_medical_assistance_abroad_textphone_content);
    i = b043D043D043D043D043D043D043Dн043D;
    j = b043Dнннннн043D043D;
    k = b043D043D043D043D043D043D043Dн043D;
    m = bн043Dннннн043D043D;
    n = bннннннн043D043D;
    if ((i + j) * k % m != n) {}
    switch (1)
    {
    }
    for (;;)
    {
      switch (1)
      {
      }
    }
  }
  
  public String bа0430а0430а04300430а04300430(rcrccr paramRcrccr)
  {
    Context localContext = this.bн043D043D043D043D043D043Dн043D;
    int i = R.string.click_to_call_call_us_textphone_content_accessible;
    paramRcrccr = b04300430аа043004300430а04300430(b043004300430а043004300430а04300430(paramRcrccr));
    int j = b043004300430аа04300430а04300430();
    switch (0)
    {
    case 1: 
    default: 
      for (;;)
      {
        switch (0)
        {
        }
      }
    }
    int k = b043Dнннннн043D043D;
    int m = b043004300430аа04300430а04300430();
    int n = bн043Dннннн043D043D;
    if ((b043D043D043D043D043D043D043Dн043D + b043Dнннннн043D043D) * b043D043D043D043D043D043D043Dн043D % bа04300430аа04300430а04300430() != bннннннн043D043D)
    {
      b043D043D043D043D043D043D043Dн043D = b043004300430аа04300430а04300430();
      bннннннн043D043D = b043004300430аа04300430а04300430();
    }
    if ((j + k) * m % n != bннннннн043D043D)
    {
      b043D043D043D043D043D043D043Dн043D = 48;
      bннннннн043D043D = 61;
    }
    switch (1)
    {
    case 0: 
    default: 
      for (;;)
      {
        switch (1)
        {
        }
      }
    }
    return localContext.getString(i, new Object[] { paramRcrccr });
  }
  
  @ooiiio("Mapping code")
  public String bа0430аа043004300430а04300430(rcrccr paramRcrccr)
  {
    for (;;)
    {
      try
      {
        switch (mmmwmw.1.b043D043Dннннн043D043D[paramRcrccr.ordinal()])
        {
        case 1: 
          throw new IllegalArgumentException(gguuuu.bккккк043Aкк043A043A("=759;D<nDJB8\016t", 'c', '\004') + paramRcrccr);
        }
      }
      catch (Exception paramRcrccr)
      {
        throw paramRcrccr;
      }
      paramRcrccr = paramRcrccr.getString(R.string.click_to_call_opening_hours_new_account_accessible);
      for (;;)
      {
        return paramRcrccr;
        try
        {
          String str = this.bн043D043D043D043D043D043Dн043D.getString(R.string.click_to_call_opening_hours_mortgage_accessible);
          int i = b043D043D043D043D043D043D043Dн043D;
          int j = b043Dнннннн043D043D;
          int k = b043D043D043D043D043D043D043Dн043D;
          int m = b043D043D043D043D043D043D043Dн043D;
          switch (m * (b043Dнннннн043D043D + m) % bн043Dннннн043D043D)
          {
          default: 
            b043D043D043D043D043D043D043Dн043D = b043004300430аа04300430а04300430();
            bннннннн043D043D = 88;
          }
          m = bн043Dннннн043D043D;
          int n = bннннннн043D043D;
          paramRcrccr = str;
          if ((i + j) * k % m != n)
          {
            b043D043D043D043D043D043D043Dн043D = b043004300430аа04300430а04300430();
            bннннннн043D043D = b043004300430аа04300430а04300430();
            return str;
          }
        }
        catch (Exception paramRcrccr)
        {
          throw paramRcrccr;
        }
      }
      paramRcrccr = this.bн043D043D043D043D043D043Dн043D;
      break;
      return "";
    }
    switch (1)
    {
    }
    for (;;)
    {
      switch (0)
      {
      }
    }
  }
  
  /* Error */
  public String bаа04300430а04300430а04300430()
  {
    // Byte code:
    //   0: invokestatic 103	kkkkkk/mmmwmw:b043004300430аа04300430а04300430	()I
    //   3: istore_1
    //   4: invokestatic 242	kkkkkk/mmmwmw:b0430аа0430а04300430а04300430	()I
    //   7: istore_2
    //   8: getstatic 31	kkkkkk/mmmwmw:bн043Dннннн043D043D	I
    //   11: istore_3
    //   12: iload_1
    //   13: iload_2
    //   14: iload_1
    //   15: iadd
    //   16: imul
    //   17: iload_3
    //   18: irem
    //   19: tableswitch	default:+17->36, 0:+93->112
    //   36: getstatic 27	kkkkkk/mmmwmw:b043D043D043D043D043D043D043Dн043D	I
    //   39: invokestatic 242	kkkkkk/mmmwmw:b0430аа0430а04300430а04300430	()I
    //   42: iadd
    //   43: getstatic 27	kkkkkk/mmmwmw:b043D043D043D043D043D043D043Dн043D	I
    //   46: imul
    //   47: getstatic 31	kkkkkk/mmmwmw:bн043Dннннн043D043D	I
    //   50: irem
    //   51: getstatic 33	kkkkkk/mmmwmw:bннннннн043D043D	I
    //   54: if_icmpeq +15 -> 69
    //   57: invokestatic 103	kkkkkk/mmmwmw:b043004300430аа04300430а04300430	()I
    //   60: putstatic 27	kkkkkk/mmmwmw:b043D043D043D043D043D043D043Dн043D	I
    //   63: invokestatic 103	kkkkkk/mmmwmw:b043004300430аа04300430а04300430	()I
    //   66: putstatic 33	kkkkkk/mmmwmw:bннннннн043D043D	I
    //   69: invokestatic 103	kkkkkk/mmmwmw:b043004300430аа04300430а04300430	()I
    //   72: putstatic 27	kkkkkk/mmmwmw:b043D043D043D043D043D043D043Dн043D	I
    //   75: bipush 57
    //   77: putstatic 33	kkkkkk/mmmwmw:bннннннн043D043D	I
    //   80: goto +32 -> 112
    //   83: aload_0
    //   84: getfield 47	kkkkkk/mmmwmw:bн043D043D043D043D043D043Dн043D	Landroid/content/Context;
    //   87: astore 4
    //   89: aload 4
    //   91: getstatic 273	com/mobile/ui/R$string:click_to_call_call_us_medical_assistance_abroad_textphone_content_accessible	I
    //   94: invokevirtual 97	android/content/Context:getString	(I)Ljava/lang/String;
    //   97: astore 4
    //   99: aload 4
    //   101: areturn
    //   102: astore 4
    //   104: aload 4
    //   106: athrow
    //   107: astore 4
    //   109: aload 4
    //   111: athrow
    //   112: iconst_1
    //   113: tableswitch	default:+23->136, 0:+-1->112, 1:+-30->83
    //   136: iconst_0
    //   137: tableswitch	default:+23->160, 0:+-54->83, 1:+-25->112
    //   160: goto -24 -> 136
    // Local variable table:
    //   start	length	slot	name	signature
    //   0	163	0	this	mmmwmw
    //   3	14	1	i	int
    //   7	9	2	j	int
    //   11	8	3	k	int
    //   87	13	4	localObject	Object
    //   102	3	4	localException1	Exception
    //   107	3	4	localException2	Exception
    // Exception table:
    //   from	to	target	type
    //   0	12	102	java/lang/Exception
    //   89	99	102	java/lang/Exception
    //   69	80	107	java/lang/Exception
    //   83	89	107	java/lang/Exception
  }
  
  public String bаа0430а043004300430а04300430(rcrccr paramRcrccr)
  {
    switch (0)
    {
    case 1: 
    default: 
      for (;;)
      {
        switch (1)
        {
        }
      }
    }
    Context localContext = this.bн043D043D043D043D043D043Dн043D;
    int i = R.string.click_to_call_call_us_textphone_content;
    if ((b043004300430аа04300430а04300430() + b0430аа0430а04300430а04300430()) * b043004300430аа04300430а04300430() % bн043Dннннн043D043D != bннннннн043D043D)
    {
      b043D043D043D043D043D043D043Dн043D = b043004300430аа04300430а04300430();
      bннннннн043D043D = b043004300430аа04300430а04300430();
      int j = b043004300430аа04300430а04300430();
      switch (j * (b043Dнннннн043D043D + j) % bн043Dннннн043D043D)
      {
      default: 
        b043D043D043D043D043D043D043Dн043D = 64;
        bннннннн043D043D = b043004300430аа04300430а04300430();
      }
    }
    return localContext.getString(i, new Object[] { b043004300430а043004300430а04300430(paramRcrccr), gguuuu.bккккк043Aкк043A043A("H", '\017', '\004') });
  }
  
  @ooiiio("Mapping code")
  public String bааа0430043004300430а04300430(rcrccr paramRcrccr)
  {
    for (;;)
    {
      try
      {
        int[] arrayOfInt = mmmwmw.1.b043D043Dннннн043D043D;
        if ((b043D043D043D043D043D043D043Dн043D + b043Dнннннн043D043D) * b043D043D043D043D043D043D043Dн043D % bн043Dннннн043D043D != bннннннн043D043D)
        {
          b043D043D043D043D043D043D043Dн043D = 49;
          bннннннн043D043D = 43;
        }
        switch (arrayOfInt[paramRcrccr.ordinal()])
        {
        case 4: 
          throw new IllegalArgumentException(gguuuu.bккккк043Aкк043A043A("& \036\"$-%W-3+!v]", '\030', '\004') + paramRcrccr);
        }
      }
      catch (Exception paramRcrccr)
      {
        throw paramRcrccr;
      }
      paramRcrccr = this.bн043D043D043D043D043D043Dн043D.getString(R.string.click_to_call_emergency_cash_abroad_title);
      int i = b043D043D043D043D043D043D043Dн043D;
      switch (i * (b043Dнннннн043D043D + i) % bн043Dннннн043D043D)
      {
      default: 
        b043D043D043D043D043D043D043Dн043D = 84;
        bннннннн043D043D = 6;
      }
      return paramRcrccr;
      return this.bн043D043D043D043D043D043Dн043D.getString(R.string.click_to_call_medical_assistance_abroad_title);
      paramRcrccr = this.bн043D043D043D043D043D043Dн043D.getString(R.string.click_to_call_lost_or_stolen_cards_title);
      return paramRcrccr;
      try
      {
        return this.bн043D043D043D043D043D043Dн043D.getString(R.string.click_to_call_other_banking_query_title);
      }
      catch (Exception paramRcrccr)
      {
        throw paramRcrccr;
      }
      paramRcrccr = this.bн043D043D043D043D043D043Dн043D.getString(R.string.click_to_call_internet_banking_title);
      return paramRcrccr;
      return this.bн043D043D043D043D043D043Dн043D.getString(R.string.click_to_call_new_isa_account_title);
      return this.bн043D043D043D043D043D043Dн043D.getString(R.string.click_to_call_change_of_address_title);
      return this.bн043D043D043D043D043D043Dн043D.getString(R.string.click_to_call_new_current_account_title);
      return this.bн043D043D043D043D043D043Dн043D.getString(R.string.click_to_call_new_savings_account_title);
      paramRcrccr = this.bн043D043D043D043D043D043Dн043D.getString(R.string.click_to_call_suspected_fraud_title);
      return paramRcrccr;
      return this.bн043D043D043D043D043D043Dн043D.getString(R.string.click_to_call_personal_account_title);
      return this.bн043D043D043D043D043D043Dн043D.getString(R.string.click_to_call_new_credit_card_title);
      return this.bн043D043D043D043D043D043Dн043D.getString(R.string.click_to_call_new_loan_title);
      paramRcrccr = this.bн043D043D043D043D043D043Dн043D.getString(R.string.click_to_call_new_mortgage_title);
      return paramRcrccr;
    }
    return "";
  }
  
  public String bаааа043004300430а04300430()
  {
    switch (1)
    {
    case 0: 
    default: 
      for (;;)
      {
        switch (0)
        {
        }
      }
    }
    Context localContext = this.bн043D043D043D043D043D043Dн043D;
    int i = b043D043D043D043D043D043D043Dн043D;
    switch (i * (b043Dнннннн043D043D + i) % bн043Dннннн043D043D)
    {
    default: 
      b043D043D043D043D043D043D043Dн043D = b043004300430аа04300430а04300430();
      bннннннн043D043D = 21;
      i = b043D043D043D043D043D043D043Dн043D;
      switch (i * (b043Dнннннн043D043D + i) % bа04300430аа04300430а04300430())
      {
      default: 
        b043D043D043D043D043D043D043Dн043D = b043004300430аа04300430а04300430();
        bннннннн043D043D = 43;
      }
      break;
    }
    return localContext.getString(R.string.click_to_call_opening_hours_24_7_accessible);
  }
}
