package kkkkkk;

import android.content.Context;
import android.os.Build.VERSION;
import android.support.annotation.NonNull;
import android.support.annotation.Nullable;
import android.support.annotation.StyleRes;
import android.text.Html;
import android.text.Spannable;
import android.text.SpannableString;
import android.text.Spanned;
import android.view.View.OnClickListener;
import android.widget.TextView;

public class mnnmmn
{
  public static int b041A041A041A041A041AККК041AК = 0;
  public static int b041AК041A041A041AККК041AК = 1;
  public static int bК041A041A041A041AККК041AК = 2;
  public static int bКК041A041A041AККК041AК = 51;
  
  private mnnmmn() {}
  
  /* Error */
  public static void b041804180418ИИИ0418И04180418(@NonNull Context paramContext, @NonNull Spannable paramSpannable, int paramInt1, int paramInt2, @NonNull android.graphics.Typeface paramTypeface, @android.support.annotation.ColorRes int paramInt3, @android.support.annotation.DimenRes int paramInt4)
  {
    // Byte code:
    //   0: new 27	kkkkkk/mnnmmn$2
    //   3: dup
    //   4: aload 4
    //   6: aload_0
    //   7: iload 5
    //   9: iload 6
    //   11: invokespecial 30	kkkkkk/mnnmmn$2:<init>	(Landroid/graphics/Typeface;Landroid/content/Context;II)V
    //   14: astore_0
    //   15: aload_1
    //   16: aload_0
    //   17: iload_2
    //   18: iload_3
    //   19: bipush 18
    //   21: invokeinterface 36 5 0
    //   26: return
    //   27: astore_0
    //   28: aload_0
    //   29: athrow
    //   30: astore_0
    //   31: aload_0
    //   32: athrow
    // Local variable table:
    //   start	length	slot	name	signature
    //   0	33	0	paramContext	Context
    //   0	33	1	paramSpannable	Spannable
    //   0	33	2	paramInt1	int
    //   0	33	3	paramInt2	int
    //   0	33	4	paramTypeface	android.graphics.Typeface
    //   0	33	5	paramInt3	int
    //   0	33	6	paramInt4	int
    // Exception table:
    //   from	to	target	type
    //   0	15	27	java/lang/Exception
    //   15	26	30	java/lang/Exception
  }
  
  public static int b04180418И0418ИИ0418И04180418()
  {
    return 1;
  }
  
  public static void b04180418ИИИИ0418И04180418(@NonNull Context paramContext, @NonNull Spannable paramSpannable, @NonNull String paramString1, @NonNull String paramString2, @NonNull View.OnClickListener paramOnClickListener)
  {
    int i = bКК041A041A041AККК041AК;
    if ((bКК041A041A041AККК041AК + b041AК041A041A041AККК041AК) * bКК041A041A041AККК041AК % bК041A041A041A041AККК041AК != b041A041A041A041A041AККК041AК)
    {
      bКК041A041A041AККК041AК = 10;
      b041A041A041A041A041AККК041AК = b0418ИИ0418ИИ0418И04180418();
    }
    switch (i * (b041AК041A041A041AККК041AК + i) % bК041A041A041A041AККК041AК)
    {
    default: 
      bКК041A041A041AККК041AК = 59;
      switch (0)
      {
      case 1: 
      default: 
        for (;;)
        {
          switch (0)
          {
          }
        }
      }
      b041AК041A041A041AККК041AК = b0418ИИ0418ИИ0418И04180418();
    }
    try
    {
      bИИ0418ИИИ0418И04180418(paramContext, paramSpannable, paramString1, paramString2, paramOnClickListener, true);
      return;
    }
    catch (Exception paramContext)
    {
      throw paramContext;
    }
  }
  
  public static void b0418И0418ИИИ0418И04180418(@NonNull TextView paramTextView, @NonNull String paramString, @StyleRes int paramInt)
  {
    int i = bКК041A041A041AККК041AК;
    switch (i * (b041AК041A041A041AККК041AК + i) % bК041A041A041A041AККК041AК)
    {
    default: 
      bКК041A041A041AККК041AК = b0418ИИ0418ИИ0418И04180418();
      b041A041A041A041A041AККК041AК = 45;
    }
    if ((bКК041A041A041AККК041AК + b041AК041A041A041AККК041AК) * bКК041A041A041AККК041AК % bК041A041A041A041AККК041AК != b041A041A041A041A041AККК041AК)
    {
      switch (1)
      {
      case 0: 
      default: 
        for (;;)
        {
          switch (0)
          {
          }
        }
      }
      bКК041A041A041AККК041AК = 12;
      b041A041A041A041A041AККК041AК = b0418ИИ0418ИИ0418И04180418();
    }
    switch (0)
    {
    case 1: 
    default: 
      for (;;)
      {
        switch (0)
        {
        }
      }
    }
    bИ04180418ИИИ0418И04180418(paramTextView, paramString, paramInt, true);
  }
  
  public static int b0418ИИ0418ИИ0418И04180418()
  {
    return 41;
  }
  
  public static void bИ04180418ИИИ0418И04180418(@NonNull TextView paramTextView, @NonNull String paramString, @StyleRes int paramInt, boolean paramBoolean)
  {
    String str = paramTextView.getText().toString();
    int i = bКК041A041A041AККК041AК;
    switch (i * (b041AК041A041A041AККК041AК + i) % bК041A041A041A041AККК041AК)
    {
    default: 
      bКК041A041A041AККК041AК = b0418ИИ0418ИИ0418И04180418();
      b041A041A041A041A041AККК041AК = 13;
    }
    i = str.toLowerCase(nmnnmn.b0418И04180418ИИИИ04180418()).indexOf(paramString.toLowerCase(nmnnmn.b0418И04180418ИИИИ04180418()));
    int j = paramString.length();
    if (i != -1)
    {
      paramString = new SpannableString(paramTextView.getText().toString());
      paramString.setSpan(new mnnmmn.1(paramTextView.getContext(), paramInt, paramBoolean), i, j + i, 0);
      paramTextView.setText(paramString);
      paramTextView.setTransformationMethod(paramTextView.getTransformationMethod());
      return;
    }
    ooooio.bа0430043004300430а0430ааа(gguuuu.bккккк043Aкк043A043A("n\032\037\025\f\025L\031C\004\022\021\f\030=\020\f{\b", '*', '\003'), new Object[0]);
  }
  
  public static int bИ0418И0418ИИ0418И04180418()
  {
    return 0;
  }
  
  public static Spanned bИИ04180418ИИ0418И04180418(@Nullable String paramString)
  {
    if ((bКК041A041A041AККК041AК + b041AК041A041A041AККК041AК) * bКК041A041A041AККК041AК % bК041A041A041A041AККК041AК != b041A041A041A041A041AККК041AК)
    {
      bКК041A041A041AККК041AК = b0418ИИ0418ИИ0418И04180418();
      b041A041A041A041A041AККК041AК = b0418ИИ0418ИИ0418И04180418();
    }
    if (Build.VERSION.SDK_INT >= 24)
    {
      int i = bКК041A041A041AККК041AК;
      switch (i * (b041AК041A041A041AККК041AК + i) % bК041A041A041A041AККК041AК)
      {
      default: 
        bКК041A041A041AККК041AК = b0418ИИ0418ИИ0418И04180418();
        b041A041A041A041A041AККК041AК = 99;
      }
      switch (1)
      {
      case 0: 
      default: 
        for (;;)
        {
          switch (1)
          {
          case 0: 
          default: 
            for (;;)
            {
              switch (0)
              {
              }
            }
          }
          switch (1)
          {
          }
        }
      }
      return Html.fromHtml(paramString, 0);
    }
    return Html.fromHtml(paramString);
  }
  
  /* Error */
  public static void bИИ0418ИИИ0418И04180418(@NonNull Context paramContext, @NonNull Spannable paramSpannable, @NonNull String paramString1, @NonNull String paramString2, @NonNull View.OnClickListener paramOnClickListener, boolean paramBoolean)
  {
    // Byte code:
    //   0: getstatic 43	kkkkkk/mnnmmn:bКК041A041A041AККК041AК	I
    //   3: istore 6
    //   5: iload 6
    //   7: getstatic 45	kkkkkk/mnnmmn:b041AК041A041A041AККК041AК	I
    //   10: iload 6
    //   12: iadd
    //   13: imul
    //   14: getstatic 47	kkkkkk/mnnmmn:bК041A041A041A041AККК041AК	I
    //   17: irem
    //   18: tableswitch	default:+18->36, 0:+29->47
    //   36: invokestatic 52	kkkkkk/mnnmmn:b0418ИИ0418ИИ0418И04180418	()I
    //   39: putstatic 43	kkkkkk/mnnmmn:bКК041A041A041AККК041AК	I
    //   42: bipush 16
    //   44: putstatic 49	kkkkkk/mnnmmn:b041A041A041A041A041AККК041AК	I
    //   47: aload_0
    //   48: invokevirtual 156	android/content/Context:getAssets	()Landroid/content/res/AssetManager;
    //   51: aload_0
    //   52: getstatic 161	com/mobile/ui/R$string:highlight_span_font	I
    //   55: invokevirtual 165	android/content/Context:getString	(I)Ljava/lang/String;
    //   58: invokestatic 171	uk/co/chrisjenx/calligraphy/TypefaceUtils:load	(Landroid/content/res/AssetManager;Ljava/lang/String;)Landroid/graphics/Typeface;
    //   61: astore 10
    //   63: aload_2
    //   64: aload_3
    //   65: invokevirtual 91	java/lang/String:indexOf	(Ljava/lang/String;)I
    //   68: istore 6
    //   70: aload_2
    //   71: aload_3
    //   72: invokevirtual 91	java/lang/String:indexOf	(Ljava/lang/String;)I
    //   75: aload_3
    //   76: invokevirtual 94	java/lang/String:length	()I
    //   79: iadd
    //   80: istore 7
    //   82: aload_1
    //   83: new 173	kkkkkk/mnnmmn$3
    //   86: dup
    //   87: aload 4
    //   89: iload 5
    //   91: invokespecial 176	kkkkkk/mnnmmn$3:<init>	(Landroid/view/View$OnClickListener;Z)V
    //   94: iload 6
    //   96: iload 7
    //   98: bipush 18
    //   100: invokeinterface 36 5 0
    //   105: getstatic 181	com/mobile/ui/R$color:highlight_text_color	I
    //   108: istore 8
    //   110: getstatic 43	kkkkkk/mnnmmn:bКК041A041A041AККК041AК	I
    //   113: istore 9
    //   115: iload 9
    //   117: getstatic 45	kkkkkk/mnnmmn:b041AК041A041A041AККК041AК	I
    //   120: iload 9
    //   122: iadd
    //   123: imul
    //   124: getstatic 47	kkkkkk/mnnmmn:bК041A041A041A041AККК041AК	I
    //   127: irem
    //   128: tableswitch	default:+20->148, 0:+31->159
    //   148: invokestatic 52	kkkkkk/mnnmmn:b0418ИИ0418ИИ0418И04180418	()I
    //   151: putstatic 43	kkkkkk/mnnmmn:bКК041A041A041AККК041AК	I
    //   154: bipush 22
    //   156: putstatic 49	kkkkkk/mnnmmn:b041A041A041A041A041AККК041AК	I
    //   159: aload_0
    //   160: aload_1
    //   161: iload 6
    //   163: iload 7
    //   165: aload 10
    //   167: iload 8
    //   169: iconst_m1
    //   170: invokestatic 183	kkkkkk/mnnmmn:b041804180418ИИИ0418И04180418	(Landroid/content/Context;Landroid/text/Spannable;IILandroid/graphics/Typeface;II)V
    //   173: return
    //   174: astore_0
    //   175: aload_0
    //   176: athrow
    //   177: astore_0
    //   178: aload_0
    //   179: athrow
    // Local variable table:
    //   start	length	slot	name	signature
    //   0	180	0	paramContext	Context
    //   0	180	1	paramSpannable	Spannable
    //   0	180	2	paramString1	String
    //   0	180	3	paramString2	String
    //   0	180	4	paramOnClickListener	View.OnClickListener
    //   0	180	5	paramBoolean	boolean
    //   3	159	6	i	int
    //   80	84	7	j	int
    //   108	60	8	k	int
    //   113	11	9	m	int
    //   61	105	10	localTypeface	android.graphics.Typeface
    // Exception table:
    //   from	to	target	type
    //   47	105	174	java/lang/Exception
    //   105	110	177	java/lang/Exception
    //   159	173	177	java/lang/Exception
  }
  
  /* Error */
  public static void bИИИ0418ИИ0418И04180418(@NonNull Context paramContext, @NonNull Spannable paramSpannable, @NonNull String paramString1, @NonNull String paramString2, @NonNull android.graphics.Typeface paramTypeface, @android.support.annotation.ColorRes int paramInt1, @android.support.annotation.DimenRes int paramInt2)
  {
    // Byte code:
    //   0: aload_2
    //   1: aload_3
    //   2: invokevirtual 91	java/lang/String:indexOf	(Ljava/lang/String;)I
    //   5: istore 7
    //   7: aload_2
    //   8: aload_3
    //   9: invokevirtual 91	java/lang/String:indexOf	(Ljava/lang/String;)I
    //   12: istore 8
    //   14: aload_3
    //   15: invokevirtual 94	java/lang/String:length	()I
    //   18: istore 9
    //   20: getstatic 43	kkkkkk/mnnmmn:bКК041A041A041AККК041AК	I
    //   23: getstatic 45	kkkkkk/mnnmmn:b041AК041A041A041AККК041AК	I
    //   26: iadd
    //   27: getstatic 43	kkkkkk/mnnmmn:bКК041A041A041AККК041AК	I
    //   30: imul
    //   31: getstatic 47	kkkkkk/mnnmmn:bК041A041A041A041AККК041AК	I
    //   34: irem
    //   35: getstatic 49	kkkkkk/mnnmmn:b041A041A041A041A041AККК041AК	I
    //   38: if_icmpeq +62 -> 100
    //   41: invokestatic 52	kkkkkk/mnnmmn:b0418ИИ0418ИИ0418И04180418	()I
    //   44: putstatic 43	kkkkkk/mnnmmn:bКК041A041A041AККК041AК	I
    //   47: getstatic 43	kkkkkk/mnnmmn:bКК041A041A041AККК041AК	I
    //   50: istore 10
    //   52: iload 10
    //   54: getstatic 45	kkkkkk/mnnmmn:b041AК041A041A041AККК041AК	I
    //   57: iload 10
    //   59: iadd
    //   60: imul
    //   61: getstatic 47	kkkkkk/mnnmmn:bК041A041A041A041AККК041AК	I
    //   64: irem
    //   65: tableswitch	default:+19->84, 0:+30->95
    //   84: invokestatic 52	kkkkkk/mnnmmn:b0418ИИ0418ИИ0418И04180418	()I
    //   87: putstatic 43	kkkkkk/mnnmmn:bКК041A041A041AККК041AК	I
    //   90: bipush 18
    //   92: putstatic 49	kkkkkk/mnnmmn:b041A041A041A041A041AККК041AК	I
    //   95: bipush 17
    //   97: putstatic 49	kkkkkk/mnnmmn:b041A041A041A041A041AККК041AК	I
    //   100: iconst_0
    //   101: tableswitch	default:+23->124, 0:+50->151, 1:+-1->100
    //   124: iconst_0
    //   125: tableswitch	default:+23->148, 0:+26->151, 1:+-25->100
    //   148: goto -24 -> 124
    //   151: aload_0
    //   152: aload_1
    //   153: iload 7
    //   155: iload 8
    //   157: iload 9
    //   159: iadd
    //   160: aload 4
    //   162: iload 5
    //   164: iload 6
    //   166: invokestatic 183	kkkkkk/mnnmmn:b041804180418ИИИ0418И04180418	(Landroid/content/Context;Landroid/text/Spannable;IILandroid/graphics/Typeface;II)V
    //   169: return
    //   170: astore_0
    //   171: aload_0
    //   172: athrow
    //   173: astore_0
    //   174: aload_0
    //   175: athrow
    // Local variable table:
    //   start	length	slot	name	signature
    //   0	176	0	paramContext	Context
    //   0	176	1	paramSpannable	Spannable
    //   0	176	2	paramString1	String
    //   0	176	3	paramString2	String
    //   0	176	4	paramTypeface	android.graphics.Typeface
    //   0	176	5	paramInt1	int
    //   0	176	6	paramInt2	int
    //   5	149	7	i	int
    //   12	148	8	j	int
    //   18	142	9	k	int
    //   50	11	10	m	int
    // Exception table:
    //   from	to	target	type
    //   0	47	170	java/lang/Exception
    //   95	100	170	java/lang/Exception
    //   151	169	173	java/lang/Exception
  }
}
