package kkkkkk;

import android.text.TextUtils;
import java.util.HashMap;
import java.util.Iterator;
import java.util.Map;
import java.util.Set;

public class mrmrmm
  implements vvovov
{
  public static int b044104410441ссс044104410441 = 1;
  public static int b0441сс0441сс044104410441 = 0;
  private static volatile mrmrmm b0441ссссс044104410441;
  public static int bс04410441ссс044104410441 = 36;
  private static final String bс0441сссс044104410441;
  public static int bссс0441сс044104410441 = 2;
  private final rmrmrm b04410441сссс044104410441 = new rmrmrm();
  private final Object b0441с0441ссс044104410441 = new Object();
  private Map<String, rrmmrm> bсс0441ссс044104410441 = new HashMap();
  
  /* Error */
  static
  {
    // Byte code:
    //   0: iconst_1
    //   1: istore_0
    //   2: iload_0
    //   3: iconst_0
    //   4: idiv
    //   5: istore_0
    //   6: goto -4 -> 2
    //   9: iconst_0
    //   10: tableswitch	default:+22->32, 0:+49->59, 1:+-1->9
    //   32: iconst_1
    //   33: tableswitch	default:+23->56, 0:+-24->9, 1:+26->59
    //   56: goto -24 -> 32
    //   59: ldc 2
    //   61: invokevirtual 36	java/lang/Class:getSimpleName	()Ljava/lang/String;
    //   64: putstatic 38	kkkkkk/mrmrmm:bс0441сссс044104410441	Ljava/lang/String;
    //   67: iload_0
    //   68: iconst_0
    //   69: idiv
    //   70: istore_0
    //   71: goto -4 -> 67
    //   74: astore_1
    //   75: iconst_3
    //   76: istore_0
    //   77: iconst_1
    //   78: tableswitch	default:+22->100, 0:+-1->77, 1:+-69->9
    //   100: iconst_0
    //   101: tableswitch	default:+23->124, 0:+-92->9, 1:+-24->77
    //   124: goto -24 -> 100
    //   127: astore_1
    //   128: aconst_null
    //   129: putstatic 40	kkkkkk/mrmrmm:b0441ссссс044104410441	Lkkkkkk/mrmrmm;
    //   132: return
    // Local variable table:
    //   start	length	slot	name	signature
    //   1	76	0	i	int
    //   74	1	1	localException1	Exception
    //   127	1	1	localException2	Exception
    // Exception table:
    //   from	to	target	type
    //   2	6	74	java/lang/Exception
    //   67	71	127	java/lang/Exception
  }
  
  private mrmrmm() {}
  
  public static int b0428042804280428ШШ0428ШШШ()
  {
    return 1;
  }
  
  private rrmmrm b042804280428Ш0428Ш0428ШШШ(rrmrrm paramRrmrrm)
  {
    if (paramRrmrrm == null) {}
    do
    {
      try
      {
        paramRrmrrm = bс0441сссс044104410441;
        try
        {
          xtxtxt.b0438и0438и04380438и0438ии(paramRrmrrm, gguuuu.bк043Aккк043Aкк043A043A("76D}LxA@P|1NCLGW,FTKTN\\\013cVbW\020_g_`\025h\\in_np", 't', '!', '\001'));
          return null;
        }
        catch (Exception paramRrmrrm)
        {
          mmrrrm localMmrrrm;
          Object localObject;
          long l;
          int i;
          int j;
          int k;
          throw paramRrmrrm;
        }
        localMmrrrm.bШШ0428ШШШШШШШ(paramRrmrrm);
        localObject = this.b04410441сссс044104410441;
        l = paramRrmrrm.bШ042804280428ШШШШШШ();
        ((rmrmrm)localObject).b04280428ШШШ0428ШШШШ(l, localMmrrrm);
        i = bс04410441ссс044104410441;
        j = b044104410441ссс044104410441;
        k = bссс0441сс044104410441;
        switch (i * (j + i) % k)
        {
        default: 
          bс04410441ссс044104410441 = bШШШШ0428Ш0428ШШШ();
          b044104410441ссс044104410441 = 15;
        }
        paramRrmrrm = bШ0428Ш04280428Ш0428ШШШ(paramRrmrrm.bхх0445хх0445ххх0445());
        return paramRrmrrm;
      }
      catch (Exception paramRrmrrm)
      {
        throw paramRrmrrm;
      }
      localObject = bс0441сссс044104410441;
      xtxtxt.bии0438и04380438и0438ии((String)localObject, gguuuu.bккккк043Aкк043A043A("\037\034*\b#\026\035\026$v\017\033\020\027\017\033G\031\013\026C\f\006@", 'Ç', '\005') + paramRrmrrm.bШ042804280428ШШШШШШ());
      localMmrrrm = paramRrmrrm.bхх04450445хх0445хх0445();
      if ((bШШШШ0428Ш0428ШШШ() + b044104410441ссс044104410441) * bШШШШ0428Ш0428ШШШ() % bссс0441сс044104410441 != b0441сс0441сс044104410441)
      {
        bс04410441ссс044104410441 = bШШШШ0428Ш0428ШШШ();
        b0441сс0441сс044104410441 = 14;
      }
    } while (localMmrrrm == null);
    xtxtxt.bии0438и04380438и0438ии(bс0441сссс044104410441, gguuuu.bк043Aккк043Aкк043A043A("ML\\;O^\\\\\\bU9SaXa[i\030_im\034ocpufuw$", '0', 'J', '\001') + paramRrmrrm.bШ042804280428ШШШШШШ() + gguuuu.bк043Aккк043Aкк043A043A("e.7b004^,2('", '\025', 'Ù', '\000'));
    switch (1)
    {
    }
    for (;;)
    {
      switch (0)
      {
      }
    }
  }
  
  public static int b0428ШШШ0428Ш0428ШШШ()
  {
    return 2;
  }
  
  public static int bШ042804280428ШШ0428ШШШ()
  {
    return 0;
  }
  
  public static mrmrmm bШ04280428Ш0428Ш0428ШШШ()
  {
    if (b0441ссссс044104410441 == null) {}
    try
    {
      if (b0441ссссс044104410441 == null) {
        b0441ссссс044104410441 = new mrmrmm();
      }
      return b0441ссссс044104410441;
    }
    finally
    {
      Object localObject1;
      switch (0)
      {
      }
    }
    switch (0)
    {
    case 1: 
    default: 
      for (;;)
      {
        switch (0)
        {
        }
      }
    }
    throw localObject1;
    for (;;)
    {
      switch (0)
      {
      }
    }
  }
  
  private rrmmrm bШ0428Ш04280428Ш0428ШШШ(String paramString)
  {
    if (TextUtils.isEmpty(paramString))
    {
      xtxtxt.b0438и0438и04380438и0438ии(bс0441сссс044104410441, gguuuu.bккккк043Aкк043A043A("d\002\016E\022<\013|\016y\001\0055\b\003u|u\004/-\002}v)qz&jqsvz", 'ó', '\002'));
      return null;
      rrmmrm localRrmmrm1 = localRrmmrm2;
      if (localRrmmrm2 == null) {
        break label143;
      }
      try
      {
        localRrmmrm1 = new rrmmrm(this.b04410441сссс044104410441);
        this.bсс0441ссс044104410441.put(paramString, localRrmmrm1);
        return localRrmmrm1;
      }
      finally {}
    }
    Object localObject = this.b0441с0441ссс044104410441;
    rrmmrm localRrmmrm2 = (rrmmrm)this.bсс0441ссс044104410441.get(paramString);
    switch (0)
    {
    }
    for (;;)
    {
      switch (0)
      {
      }
    }
    label143:
    switch (1)
    {
    }
    for (;;)
    {
      switch (1)
      {
      }
    }
  }
  
  public static int bШШШШ0428Ш0428ШШШ()
  {
    return 78;
  }
  
  public void b04280428042804280428Ш0428ШШШ(String paramString, mrmmmm paramMrmmmm)
  {
    switch (1)
    {
    case 0: 
    default: 
      for (;;)
      {
        switch (0)
        {
        }
      }
    }
    Object localObject = this.b0441с0441ссс044104410441;
    switch (0)
    {
    case 1: 
    default: 
      for (;;)
      {
        switch (0)
        {
        }
      }
    }
    try
    {
      paramString = (rrmmrm)this.bсс0441ссс044104410441.get(paramString);
      if (paramString != null) {
        paramString.bШШШ0428ШШ0428ШШШ().bШ0428Ш0428Ш04280428ШШШ(paramMrmmmm);
      }
      return;
    }
    finally {}
  }
  
  /* Error */
  public void b04280428Ш04280428Ш0428ШШШ(mrmrrm paramMrmrrm)
  {
    // Byte code:
    //   0: aload_0
    //   1: getfield 51	kkkkkk/mrmrmm:b04410441сссс044104410441	Lkkkkkk/rmrmrm;
    //   4: astore 7
    //   6: getstatic 92	kkkkkk/mrmrmm:bс04410441ссс044104410441	I
    //   9: istore_2
    //   10: getstatic 94	kkkkkk/mrmrmm:b044104410441ссс044104410441	I
    //   13: istore_3
    //   14: getstatic 92	kkkkkk/mrmrmm:bс04410441ссс044104410441	I
    //   17: istore 4
    //   19: getstatic 96	kkkkkk/mrmrmm:bссс0441сс044104410441	I
    //   22: istore 5
    //   24: getstatic 134	kkkkkk/mrmrmm:b0441сс0441сс044104410441	I
    //   27: istore 6
    //   29: iload_2
    //   30: iload_3
    //   31: iadd
    //   32: iload 4
    //   34: imul
    //   35: iload 5
    //   37: irem
    //   38: iload 6
    //   40: if_icmpeq +14 -> 54
    //   43: bipush 71
    //   45: putstatic 92	kkkkkk/mrmrmm:bс04410441ссс044104410441	I
    //   48: invokestatic 99	kkkkkk/mrmrmm:bШШШШ0428Ш0428ШШШ	()I
    //   51: putstatic 134	kkkkkk/mrmrmm:b0441сс0441сс044104410441	I
    //   54: iconst_0
    //   55: tableswitch	default:+21->76, 0:+92->147, 1:+-1->54
    //   76: getstatic 92	kkkkkk/mrmrmm:bс04410441ссс044104410441	I
    //   79: istore_2
    //   80: iload_2
    //   81: getstatic 94	kkkkkk/mrmrmm:b044104410441ссс044104410441	I
    //   84: iload_2
    //   85: iadd
    //   86: imul
    //   87: getstatic 96	kkkkkk/mrmrmm:bссс0441сс044104410441	I
    //   90: irem
    //   91: tableswitch	default:+17->108, 0:+28->119
    //   108: invokestatic 99	kkkkkk/mrmrmm:bШШШШ0428Ш0428ШШШ	()I
    //   111: putstatic 92	kkkkkk/mrmrmm:bс04410441ссс044104410441	I
    //   114: bipush 56
    //   116: putstatic 134	kkkkkk/mrmrmm:b0441сс0441сс044104410441	I
    //   119: iconst_1
    //   120: tableswitch	default:+24->144, 0:+-66->54, 1:+27->147
    //   144: goto -68 -> 76
    //   147: aload 7
    //   149: aload_1
    //   150: invokevirtual 183	kkkkkk/rmrmrm:b0428ШШШШ0428ШШШШ	(Lkkkkkk/mrmrrm;)V
    //   153: return
    //   154: astore_1
    //   155: aload_1
    //   156: athrow
    //   157: astore_1
    //   158: aload_1
    //   159: athrow
    // Local variable table:
    //   start	length	slot	name	signature
    //   0	160	0	this	mrmrmm
    //   0	160	1	paramMrmrrm	mrmrrm
    //   9	78	2	i	int
    //   13	19	3	j	int
    //   17	18	4	k	int
    //   22	16	5	m	int
    //   27	14	6	n	int
    //   4	144	7	localRmrmrm	rmrmrm
    // Exception table:
    //   from	to	target	type
    //   0	10	154	java/lang/Exception
    //   19	29	154	java/lang/Exception
    //   147	153	154	java/lang/Exception
    //   10	19	157	java/lang/Exception
    //   43	54	157	java/lang/Exception
  }
  
  public void b04280428ШШ0428Ш0428ШШШ(jmmjjj paramJmmjjj)
  {
    if (TextUtils.isEmpty(paramJmmjjj.b0438и0438и0438и0438и04380438()))
    {
      xtxtxt.b0438и0438и04380438и0438ии(bс0441сссс044104410441, gguuuu.bккккк043Aкк043A043A("<Ye\035i\024Va_^TQa\f_Y\tMTVY]\003WSL", 'W', '\002'));
      return;
      xtxtxt.bиии043804380438и0438ии(bс0441сссс044104410441, gguuuu.bккккк043Aкк043A043A("LYYZRQcY_Y\023hd\026jg\\e`p", 'h', '\000'));
      switch (0)
      {
      case 1: 
      default: 
        for (;;)
        {
          switch (0)
          {
          }
        }
      }
      bШ0428Ш04280428Ш0428ШШШ(paramJmmjjj.b0438и0438и0438и0438и04380438()).b0428Ш0428ШШШ0428ШШШ(paramJmmjjj);
      int i = bс04410441ссс044104410441;
      switch (i * (b044104410441ссс044104410441 + i) % bссс0441сс044104410441)
      {
      }
      bс04410441ссс044104410441 = bШШШШ0428Ш0428ШШШ();
      b0441сс0441сс044104410441 = 66;
      i = bШШШШ0428Ш0428ШШШ();
      switch (i * (b044104410441ссс044104410441 + i) % bссс0441сс044104410441)
      {
      }
      bс04410441ссс044104410441 = bШШШШ0428Ш0428ШШШ();
      b0441сс0441сс044104410441 = 51;
      return;
    }
    switch (1)
    {
    }
    for (;;)
    {
      switch (1)
      {
      }
    }
  }
  
  /* Error */
  public void b0428Ш042804280428Ш0428ШШШ(rrmrrm paramRrmrrm)
  {
    // Byte code:
    //   0: aload_0
    //   1: aload_1
    //   2: invokespecial 203	kkkkkk/mrmrmm:b042804280428Ш0428Ш0428ШШШ	(Lkkkkkk/rrmrrm;)Lkkkkkk/rrmmrm;
    //   5: astore_2
    //   6: aload_2
    //   7: ifnull +122 -> 129
    //   10: getstatic 38	kkkkkk/mrmrmm:bс0441сссс044104410441	Ljava/lang/String;
    //   13: astore_3
    //   14: getstatic 92	kkkkkk/mrmrmm:bс04410441ссс044104410441	I
    //   17: getstatic 94	kkkkkk/mrmrmm:b044104410441ссс044104410441	I
    //   20: iadd
    //   21: getstatic 92	kkkkkk/mrmrmm:bс04410441ссс044104410441	I
    //   24: imul
    //   25: getstatic 96	kkkkkk/mrmrmm:bссс0441сс044104410441	I
    //   28: irem
    //   29: getstatic 134	kkkkkk/mrmrmm:b0441сс0441сс044104410441	I
    //   32: if_icmpeq +15 -> 47
    //   35: invokestatic 99	kkkkkk/mrmrmm:bШШШШ0428Ш0428ШШШ	()I
    //   38: putstatic 92	kkkkkk/mrmrmm:bс04410441ссс044104410441	I
    //   41: invokestatic 99	kkkkkk/mrmrmm:bШШШШ0428Ш0428ШШШ	()I
    //   44: putstatic 134	kkkkkk/mrmrmm:b0441сс0441сс044104410441	I
    //   47: new 108	java/lang/StringBuilder
    //   50: dup
    //   51: invokespecial 109	java/lang/StringBuilder:<init>	()V
    //   54: astore 4
    //   56: getstatic 92	kkkkkk/mrmrmm:bс04410441ссс044104410441	I
    //   59: getstatic 94	kkkkkk/mrmrmm:b044104410441ссс044104410441	I
    //   62: iadd
    //   63: getstatic 92	kkkkkk/mrmrmm:bс04410441ссс044104410441	I
    //   66: imul
    //   67: getstatic 96	kkkkkk/mrmrmm:bссс0441сс044104410441	I
    //   70: irem
    //   71: getstatic 134	kkkkkk/mrmrmm:b0441сс0441сс044104410441	I
    //   74: if_icmpeq +14 -> 88
    //   77: invokestatic 99	kkkkkk/mrmrmm:bШШШШ0428Ш0428ШШШ	()I
    //   80: putstatic 92	kkkkkk/mrmrmm:bс04410441ссс044104410441	I
    //   83: bipush 32
    //   85: putstatic 134	kkkkkk/mrmrmm:b0441сс0441сс044104410441	I
    //   88: aload 4
    //   90: ldc -51
    //   92: bipush 111
    //   94: bipush 11
    //   96: iconst_1
    //   97: invokestatic 68	kkkkkk/gguuuu:bк043Aккк043Aкк043A043A	(Ljava/lang/String;CCC)Ljava/lang/String;
    //   100: invokevirtual 119	java/lang/StringBuilder:append	(Ljava/lang/String;)Ljava/lang/StringBuilder;
    //   103: astore 4
    //   105: aload_3
    //   106: aload 4
    //   108: aload_1
    //   109: invokevirtual 208	kkkkkk/rrmrrm:b04450445х0445хх0445хх0445	()Ljava/lang/String;
    //   112: invokevirtual 119	java/lang/StringBuilder:append	(Ljava/lang/String;)Ljava/lang/StringBuilder;
    //   115: invokevirtual 125	java/lang/StringBuilder:toString	()Ljava/lang/String;
    //   118: invokestatic 197	kkkkkk/xtxtxt:bиии043804380438и0438ии	(Ljava/lang/String;Ljava/lang/String;)V
    //   121: aload_2
    //   122: aload_1
    //   123: invokevirtual 211	kkkkkk/rrmrrm:bх0445х0445хх0445хх0445	()Ljava/lang/String;
    //   126: invokevirtual 215	kkkkkk/rrmmrm:bШШ04280428ШШ0428ШШШ	(Ljava/lang/String;)V
    //   129: return
    //   130: astore_1
    //   131: aload_1
    //   132: athrow
    //   133: astore_1
    //   134: aload_1
    //   135: athrow
    // Local variable table:
    //   start	length	slot	name	signature
    //   0	136	0	this	mrmrmm
    //   0	136	1	paramRrmrrm	rrmrrm
    //   5	117	2	localRrmmrm	rrmmrm
    //   13	93	3	str	String
    //   54	53	4	localStringBuilder	StringBuilder
    // Exception table:
    //   from	to	target	type
    //   0	6	130	java/lang/Exception
    //   10	14	130	java/lang/Exception
    //   47	56	130	java/lang/Exception
    //   105	129	130	java/lang/Exception
    //   88	105	133	java/lang/Exception
  }
  
  public void b0428Ш0428Ш0428Ш0428ШШШ(String paramString)
  {
    xtxtxt.bии0438и04380438и0438ии(bс0441сссс044104410441, gguuuu.bк043Aккк043Aкк043A043A("8<E4?=<2/?i", '£', '', '\002') + paramString);
    synchronized (this.b0441с0441ссс044104410441)
    {
      paramString = (rrmmrm)this.bсс0441ссс044104410441.get(paramString);
      if (paramString == null) {
        return;
      }
    }
    paramString.bШ04280428ШШШ0428ШШШ();
  }
  
  public void b0428ШШ04280428Ш0428ШШШ(String paramString)
  {
    xtxtxt.bиии043804380438и0438ии(bс0441сссс044104410441, gguuuu.bк043Aккк043Aкк043A043A("*')(Z-(\033\"\033)", '', ']', '\000'));
    Object localObject = this.b0441с0441ссс044104410441;
    switch (1)
    {
    case 0: 
    default: 
      for (;;)
      {
        switch (1)
        {
        }
      }
    }
    try
    {
      paramString = (rrmmrm)this.bсс0441ссс044104410441.get(paramString);
      if (paramString == null) {
        return;
      }
      paramString.bШ04280428ШШШ0428ШШШ();
      paramString.b044504450445х0445хх044504450445();
      return;
    }
    finally {}
  }
  
  public void b0445ххх0445хх044504450445()
  {
    xtxtxt.bиии043804380438и0438ии(bс0441сссс044104410441, gguuuu.bк043Aккк043Aкк043A043A("Xn||}sys-r~\b2t\001\002", 'å', '', '\003'));
    Iterator localIterator = this.bсс0441ссс044104410441.keySet().iterator();
    while (localIterator.hasNext())
    {
      switch (1)
      {
      case 0: 
      default: 
        for (;;)
        {
          switch (0)
          {
          }
        }
      }
      int i = bс04410441ссс044104410441;
      switch (i * (b044104410441ссс044104410441 + i) % b0428ШШШ0428Ш0428ШШШ())
      {
      default: 
        bс04410441ссс044104410441 = bШШШШ0428Ш0428ШШШ();
        b0441сс0441сс044104410441 = 43;
      }
      b0428ШШ04280428Ш0428ШШШ((String)localIterator.next());
    }
    this.bсс0441ссс044104410441.clear();
    this.b04410441сссс044104410441.b0445ххх0445хх044504450445();
    b0441ссссс044104410441 = null;
  }
  
  public Runnable bШ0428042804280428Ш0428ШШШ(rrmrrm paramRrmrrm, long paramLong)
  {
    Object localObject = b042804280428Ш0428Ш0428ШШШ(paramRrmrrm);
    if (localObject != null)
    {
      localObject = ((rrmmrm)localObject).b0428Ш04280428ШШ0428ШШШ(paramRrmrrm.bх0445х0445хх0445хх0445(), paramLong);
      paramRrmrrm = (rrmrrm)localObject;
      if ((bс04410441ссс044104410441 + b0428042804280428ШШ0428ШШШ()) * bс04410441ссс044104410441 % bссс0441сс044104410441 != bШ042804280428ШШ0428ШШШ())
      {
        bс04410441ссс044104410441 = bШШШШ0428Ш0428ШШШ();
        b0441сс0441сс044104410441 = bШШШШ0428Ш0428ШШШ();
        paramRrmrrm = (rrmrrm)localObject;
      }
      return paramRrmrrm;
    }
    for (;;)
    {
      switch (0)
      {
      default: 
        break;
      case 0: 
        int i = bШШШШ0428Ш0428ШШШ();
        switch (i * (b044104410441ссс044104410441 + i) % bссс0441сс044104410441)
        {
        }
        bс04410441ссс044104410441 = bШШШШ0428Ш0428ШШШ();
        b0441сс0441сс044104410441 = 60;
        return null;
        xtxtxt.bии0438и04380438и0438ии(bс0441сссс044104410441, gguuuu.bк043Aккк043Aкк043A043A("\035)`-W*\031\035\031\027'\035\025N!\022\032\017I\r\r\023\007\036\t\007As\017\002\t\002\020l~\n\r{\t\t", 'D', '\001', '\000'));
        paramRrmrrm = null;
      case 1: 
        switch (0)
        {
        }
        break;
      }
    }
  }
  
  public void bШ0428ШШ0428Ш0428ШШШ(rrmrrm paramRrmrrm, Runnable paramRunnable)
  {
    if (paramRrmrrm == null) {}
    try
    {
      xtxtxt.b0438и0438и04380438и0438ии(bс0441сссс044104410441, gguuuu.bккккк043Aкк043A043A("\003 ,c0Z,.&V$* \037Q#\025 #\022\037\037J", '¿', '\005'));
      return;
    }
    catch (Exception paramRrmrrm)
    {
      throw paramRrmrrm;
    }
    bШ0428Ш04280428Ш0428ШШШ(paramRrmrrm.bхх0445хх0445ххх0445());
  }
  
  public void bШШ042804280428Ш0428ШШШ(String paramString, mrmmmm paramMrmmmm)
  {
    int i = 2;
    paramString = bШ0428Ш04280428Ш0428ШШШ(paramString);
    if (paramString != null)
    {
      paramString.bШШШ0428ШШ0428ШШШ().bШШШ0428Ш04280428ШШШ(paramMrmmmm);
      for (;;)
      {
        if ((bс04410441ссс044104410441 + b044104410441ссс044104410441) * bс04410441ссс044104410441 % bссс0441сс044104410441 != b0441сс0441сс044104410441)
        {
          bс04410441ссс044104410441 = bШШШШ0428Ш0428ШШШ();
          b0441сс0441сс044104410441 = 89;
        }
        try
        {
          i /= 0;
        }
        catch (Exception paramString)
        {
          switch (1)
          {
          case 0: 
          default: 
            for (;;)
            {
              switch (1)
              {
              }
            }
          }
          bс04410441ссс044104410441 = bШШШШ0428Ш0428ШШШ();
        }
      }
    }
  }
  
  public void bШШ0428Ш0428Ш0428ШШШ(String paramString, int paramInt)
  {
    if (TextUtils.isEmpty(paramString))
    {
      xtxtxt.b0438и0438и04380438и0438ии(bс0441сссс044104410441, gguuuu.bк043Aккк043Aкк043A043A("0O]\027e\022Vccd\\[m\032ok\035clpu{#ywr", 'é', 'ü', '\001'));
      return;
    }
    String str = bс0441сссс044104410441;
    if ((bс04410441ссс044104410441 + b044104410441ссс044104410441) * bс04410441ссс044104410441 % b0428ШШШ0428Ш0428ШШШ() != b0441сс0441сс044104410441)
    {
      bс04410441ссс044104410441 = bШШШШ0428Ш0428ШШШ();
      b0441сс0441сс044104410441 = 78;
    }
    switch (1)
    {
    case 0: 
    default: 
      for (;;)
      {
        switch (1)
        {
        }
      }
    }
    xtxtxt.bиии043804380438и0438ии(str, gguuuu.bк043Aккк043Aкк043A043A("ERRSKJ\\RXR\fa]\017c`U^Yi", '`', 'ÿ', '\003'));
    b04280428ШШ0428Ш0428ШШШ(new jmmjjj(paramString, paramInt));
    paramInt = bс04410441ссс044104410441;
    switch (paramInt * (b0428042804280428ШШ0428ШШШ() + paramInt) % b0428ШШШ0428Ш0428ШШШ())
    {
    }
    bс04410441ссс044104410441 = bШШШШ0428Ш0428ШШШ();
    b0441сс0441сс044104410441 = bШШШШ0428Ш0428ШШШ();
  }
  
  public rmmrmm bШШШ04280428Ш0428ШШШ(String paramString)
  {
    synchronized (this.b0441с0441ссс044104410441)
    {
      paramString = (rrmmrm)this.bсс0441ссс044104410441.get(paramString);
      if (paramString == null)
      {
        paramString = rmmrmm.INIT;
        return paramString;
      }
    }
    do
    {
      paramString = paramString.b042804280428ШШ04280428ШШШ();
      return paramString;
      paramString = paramString.bШШШ0428ШШ0428ШШШ();
      break;
    } while (paramString != null);
    paramString = rmmrmm.INIT;
    return paramString;
    switch (0)
    {
    }
    for (;;)
    {
      switch (0)
      {
      }
    }
  }
}
