package kkkkkk;

import javax.inject.Inject;

public class mwwmww
{
  private static final String b043D043D043D043D043Dннн043D = "o\002qOq$%\025#\035\034%\036(/[\t'24";
  public static int b043D043D043D043Dн043Dнн043D = 2;
  private static final String b043D043D043Dнн043Dнн043D = "\016$5\\\f-)\035-\032*Tx!#&\031!\027\022\037";
  private static final String b043D043Dн043D043Dннн043D = "SeU3U\b\tx\007\001\t\002\f\023?c\003\017\020Dz\032";
  private static final String b043D043Dннн043Dнн043D = "7YX\023@Vg\017<bYMO[";
  private static final String b043Dн043D043D043Dннн043D = "e|\004\0020Ruv\004\013\005\f\f";
  public static int b043Dн043D043Dн043Dнн043D = 0;
  private static final String b043Dн043Dнн043Dнн043D = "EWG%Nvun*S\002o";
  private static final String b043Dнн043Dн043Dнн043D = "DTB\036Kar\032IjfZjWge";
  private static final String b043Dнннн043Dнн043D = ".>,\b*GQP\0037T";
  private static final String bн043D043D043D043Dннн043D = "Y|}\013\022\f\023?l\013\026\030";
  public static int bн043D043D043Dн043Dнн043D = 1;
  private static final String bн043D043Dнн043Dнн043D = ";M=\033Jbu\037psqgyhzz(Lkwx-c\003";
  private static final String bн043Dннн043Dнн043D = "";
  private static final String bнн043D043D043Dннн043D = "\00134$2,+4-7>>";
  public static int bнн043D043Dн043Dнн043D = 62;
  private static final String bнн043Dнн043Dнн043D = "\01641(a)5!";
  private static final String bннн043Dн043Dнн043D = "\006)'\035/\0360\\\n(35";
  private static final String bннннн043Dнн043D = "]z\005\0046j\b";
  private final rgrggg b043D043Dн043Dн043Dнн043D;
  private final nuuuuu bн043Dн043Dн043Dнн043D;
  
  static
  {
    for (;;)
    {
      try
      {
        b043D043Dн043D043Dннн043D = gguuuu.bк043Aккк043Aкк043A043A(b043D043Dн043D043Dннн043D, '+', 'ã', '\003');
      }
      catch (Exception localException1)
      {
        String str;
        int i;
        int j;
        throw localException1;
      }
      try
      {
        str = bнн043D043D043Dннн043D;
        bнн043D043D043Dннн043D = gguuuu.bк043Aккк043Aкк043A043A(str, 'g', 'Ö', '\003');
        str = gguuuu.bк043Aккк043Aкк043A043A(b043Dн043D043D043Dннн043D, 'Ã', '·', '\001');
        i = bнн043D043Dн043Dнн043D;
        switch (i * (bн043D043D043Dн043Dнн043D + i) % b043D043D043D043Dн043Dнн043D)
        {
        default: 
          bнн043D043Dн043Dнн043D = 34;
          b043Dн043D043Dн043Dнн043D = 21;
        }
        b043Dн043D043D043Dннн043D = str;
        bн043D043D043D043Dннн043D = gguuuu.bккккк043Aкк043A043A(bн043D043D043D043Dннн043D, '', '\001');
        b043D043D043D043D043Dннн043D = gguuuu.bккккк043Aкк043A043A(b043D043D043D043D043Dннн043D, ',', '\000');
        str = bннннн043Dнн043D;
        i = bнн043D043Dн043Dнн043D;
        j = bн043D043D043Dн043Dнн043D;
        if ((i + j) * bнн043D043Dн043Dнн043D % b043D043D043D043Dн043Dнн043D != b043Dн043D043Dн043Dнн043D)
        {
          bнн043D043Dн043Dнн043D = 37;
          b043Dн043D043Dн043Dнн043D = 8;
        }
        str = gguuuu.bк043Aккк043Aкк043A043A(str, '+', '¹', '\002');
        bннннн043Dнн043D = str;
        str = b043Dнннн043Dнн043D;
      }
      catch (Exception localException2)
      {
        throw localException2;
      }
    }
    b043Dнннн043Dнн043D = gguuuu.bккккк043Aкк043A043A(str, '\007', '\002');
    b043D043Dннн043Dнн043D = gguuuu.bк043Aккк043Aкк043A043A(b043D043Dннн043Dнн043D, '¾', 'J', '\002');
    bнн043Dнн043Dнн043D = gguuuu.bккккк043Aкк043A043A(bнн043Dнн043Dнн043D, '', '\003');
    b043Dн043Dнн043Dнн043D = gguuuu.bккккк043Aкк043A043A(b043Dн043Dнн043Dнн043D, '\001', '\004');
    bн043D043Dнн043Dнн043D = gguuuu.bк043Aккк043Aкк043A043A(bн043D043Dнн043Dнн043D, '&', 'Ð', '\003');
    str = b043D043D043Dнн043Dнн043D;
    b043D043D043Dнн043Dнн043D = gguuuu.bккккк043Aкк043A043A(str, '', '\003');
    str = bннн043Dн043Dнн043D;
    bннн043Dн043Dнн043D = gguuuu.bк043Aккк043Aкк043A043A(str, 'Ä', '', '\001');
    b043Dнн043Dн043Dнн043D = gguuuu.bккккк043Aкк043A043A(b043Dнн043Dн043Dнн043D, '~', '\005');
    return;
    switch (0)
    {
    }
    for (;;)
    {
      switch (1)
      {
      }
    }
  }
  
  @Inject
  public mwwmww(nuuuuu paramNuuuuu, rgrggg paramRgrggg)
  {
    this.bн043Dн043Dн043Dнн043D = paramNuuuuu;
    this.b043D043Dн043Dн043Dнн043D = paramRgrggg;
  }
  
  /* Error */
  private String b04300430ааа0430аа04300430(rcrccr paramRcrccr)
  {
    // Byte code:
    //   0: getstatic 81	kkkkkk/mwwmww:bнн043D043Dн043Dнн043D	I
    //   3: istore_2
    //   4: getstatic 83	kkkkkk/mwwmww:bн043D043D043Dн043Dнн043D	I
    //   7: istore_3
    //   8: getstatic 81	kkkkkk/mwwmww:bнн043D043Dн043Dнн043D	I
    //   11: istore 4
    //   13: getstatic 85	kkkkkk/mwwmww:b043D043D043D043Dн043Dнн043D	I
    //   16: istore 5
    //   18: getstatic 87	kkkkkk/mwwmww:b043Dн043D043Dн043Dнн043D	I
    //   21: istore 6
    //   23: iload_2
    //   24: iload_3
    //   25: iadd
    //   26: iload 4
    //   28: imul
    //   29: iload 5
    //   31: irem
    //   32: iload 6
    //   34: if_icmpeq +15 -> 49
    //   37: invokestatic 130	kkkkkk/mwwmww:bааааа0430аа04300430	()I
    //   40: putstatic 81	kkkkkk/mwwmww:bнн043D043Dн043Dнн043D	I
    //   43: invokestatic 130	kkkkkk/mwwmww:bааааа0430аа04300430	()I
    //   46: putstatic 87	kkkkkk/mwwmww:b043Dн043D043Dн043Dнн043D	I
    //   49: iconst_1
    //   50: tableswitch	default:+22->72, 0:+-1->49, 1:+49->99
    //   72: iconst_1
    //   73: tableswitch	default:+23->96, 0:+-24->49, 1:+26->99
    //   96: goto -24 -> 72
    //   99: ldc -124
    //   101: sipush 147
    //   104: sipush 133
    //   107: iconst_3
    //   108: invokestatic 75	kkkkkk/gguuuu:bк043Aккк043Aкк043A043A	(Ljava/lang/String;CCC)Ljava/lang/String;
    //   111: astore 7
    //   113: aload_1
    //   114: invokevirtual 138	kkkkkk/rcrccr:toString	()Ljava/lang/String;
    //   117: astore_1
    //   118: getstatic 81	kkkkkk/mwwmww:bнн043D043Dн043Dнн043D	I
    //   121: istore_2
    //   122: iload_2
    //   123: invokestatic 141	kkkkkk/mwwmww:bа0430ааа0430аа04300430	()I
    //   126: iload_2
    //   127: iadd
    //   128: imul
    //   129: getstatic 85	kkkkkk/mwwmww:b043D043D043D043Dн043Dнн043D	I
    //   132: irem
    //   133: tableswitch	default:+19->152, 0:+30->163
    //   152: bipush 55
    //   154: putstatic 81	kkkkkk/mwwmww:bнн043D043Dн043Dнн043D	I
    //   157: invokestatic 130	kkkkkk/mwwmww:bааааа0430аа04300430	()I
    //   160: putstatic 87	kkkkkk/mwwmww:b043Dн043D043Dн043Dнн043D	I
    //   163: aload 7
    //   165: iconst_1
    //   166: anewarray 4	java/lang/Object
    //   169: dup
    //   170: iconst_0
    //   171: aload_1
    //   172: ldc -113
    //   174: sipush 193
    //   177: bipush 119
    //   179: iconst_3
    //   180: invokestatic 75	kkkkkk/gguuuu:bк043Aккк043Aкк043A043A	(Ljava/lang/String;CCC)Ljava/lang/String;
    //   183: ldc 45
    //   185: invokevirtual 149	java/lang/String:replaceAll	(Ljava/lang/String;Ljava/lang/String;)Ljava/lang/String;
    //   188: aastore
    //   189: invokestatic 153	java/lang/String:format	(Ljava/lang/String;[Ljava/lang/Object;)Ljava/lang/String;
    //   192: astore_1
    //   193: aload_1
    //   194: areturn
    //   195: astore_1
    //   196: aload_1
    //   197: athrow
    //   198: astore_1
    //   199: aload_1
    //   200: athrow
    // Local variable table:
    //   start	length	slot	name	signature
    //   0	201	0	this	mwwmww
    //   0	201	1	paramRcrccr	rcrccr
    //   3	126	2	i	int
    //   7	19	3	j	int
    //   11	18	4	k	int
    //   16	16	5	m	int
    //   21	14	6	n	int
    //   111	53	7	str	String
    // Exception table:
    //   from	to	target	type
    //   8	23	195	java/lang/Exception
    //   113	118	195	java/lang/Exception
    //   163	193	195	java/lang/Exception
    //   0	8	198	java/lang/Exception
    //   37	49	198	java/lang/Exception
    //   99	113	198	java/lang/Exception
  }
  
  public static int b0430аааа0430аа04300430()
  {
    return 2;
  }
  
  public static int bа0430ааа0430аа04300430()
  {
    return 1;
  }
  
  public static int bааааа0430аа04300430()
  {
    return 22;
  }
  
  /* Error */
  public void b043004300430аа0430аа04300430(rcrccr paramRcrccr)
  {
    // Byte code:
    //   0: invokestatic 130	kkkkkk/mwwmww:bааааа0430аа04300430	()I
    //   3: istore_2
    //   4: getstatic 83	kkkkkk/mwwmww:bн043D043D043Dн043Dнн043D	I
    //   7: istore_3
    //   8: getstatic 85	kkkkkk/mwwmww:b043D043D043D043Dн043Dнн043D	I
    //   11: istore 4
    //   13: iload_2
    //   14: iload_3
    //   15: iload_2
    //   16: iadd
    //   17: imul
    //   18: iload 4
    //   20: irem
    //   21: tableswitch	default:+19->40, 0:+30->51
    //   40: bipush 83
    //   42: putstatic 81	kkkkkk/mwwmww:bнн043D043Dн043Dнн043D	I
    //   45: invokestatic 130	kkkkkk/mwwmww:bааааа0430аа04300430	()I
    //   48: putstatic 87	kkkkkk/mwwmww:b043Dн043D043Dн043Dнн043D	I
    //   51: aload_0
    //   52: getfield 121	kkkkkk/mwwmww:bн043Dн043Dн043Dнн043D	Lkkkkkk/nuuuuu;
    //   55: astore 5
    //   57: getstatic 162	kkkkkk/uunnuu:SERVICE	Lkkkkkk/uunnuu;
    //   60: astore 6
    //   62: getstatic 168	kkkkkk/nunnuu:CLICK_TO_CALL	Lkkkkkk/nunnuu;
    //   65: astore 7
    //   67: getstatic 173	kkkkkk/nnnuuu$ununuu:CLICK_TO_CALL	Lkkkkkk/nnnuuu$ununuu;
    //   70: astore 8
    //   72: getstatic 179	kkkkkk/nuuunu:N3_20	Lkkkkkk/nuuunu;
    //   75: astore 9
    //   77: getstatic 185	kkkkkk/nnnuuu$nnunuu:TWO	Lkkkkkk/nnnuuu$nnunuu;
    //   80: astore 10
    //   82: ldc -69
    //   84: sipush 162
    //   87: iconst_3
    //   88: invokestatic 93	kkkkkk/gguuuu:bккккк043Aкк043A043A	(Ljava/lang/String;CC)Ljava/lang/String;
    //   91: astore 11
    //   93: getstatic 193	kkkkkk/unuunu:JOURNEY_PRODUCT	Lkkkkkk/unuunu;
    //   96: astore 12
    //   98: getstatic 81	kkkkkk/mwwmww:bнн043D043Dн043Dнн043D	I
    //   101: invokestatic 141	kkkkkk/mwwmww:bа0430ааа0430аа04300430	()I
    //   104: iadd
    //   105: getstatic 81	kkkkkk/mwwmww:bнн043D043Dн043Dнн043D	I
    //   108: imul
    //   109: invokestatic 195	kkkkkk/mwwmww:b0430аааа0430аа04300430	()I
    //   112: irem
    //   113: getstatic 87	kkkkkk/mwwmww:b043Dн043D043Dн043Dнн043D	I
    //   116: if_icmpeq +14 -> 130
    //   119: bipush 62
    //   121: putstatic 81	kkkkkk/mwwmww:bнн043D043Dн043Dнн043D	I
    //   124: invokestatic 130	kkkkkk/mwwmww:bааааа0430аа04300430	()I
    //   127: putstatic 87	kkkkkk/mwwmww:b043Dн043D043Dн043Dнн043D	I
    //   130: aload_1
    //   131: invokevirtual 138	kkkkkk/rcrccr:toString	()Ljava/lang/String;
    //   134: astore_1
    //   135: aload 12
    //   137: aload_1
    //   138: invokestatic 201	kkkkkk/nuuuuu$unuuuu:b043F043F043Fп043F043Fпп043Fп	(Lkkkkkk/unuunu;Ljava/lang/String;)Lkkkkkk/nuuuuu$unuuuu;
    //   141: astore_1
    //   142: getstatic 204	kkkkkk/unuunu:SCREEN_NAME	Lkkkkkk/unuunu;
    //   145: ldc -50
    //   147: sipush 176
    //   150: iconst_3
    //   151: invokestatic 93	kkkkkk/gguuuu:bккккк043Aкк043A043A	(Ljava/lang/String;CC)Ljava/lang/String;
    //   154: invokestatic 201	kkkkkk/nuuuuu$unuuuu:b043F043F043Fп043F043Fпп043Fп	(Lkkkkkk/unuunu;Ljava/lang/String;)Lkkkkkk/nuuuuu$unuuuu;
    //   157: astore 12
    //   159: aload 5
    //   161: aload 6
    //   163: aload 7
    //   165: aload 8
    //   167: aload 9
    //   169: aload 10
    //   171: aload 11
    //   173: iconst_2
    //   174: anewarray 197	kkkkkk/nuuuuu$unuuuu
    //   177: dup
    //   178: iconst_0
    //   179: aload_1
    //   180: aastore
    //   181: dup
    //   182: iconst_1
    //   183: aload 12
    //   185: aastore
    //   186: invokevirtual 212	kkkkkk/nuuuuu:b043Fп043Fппп043Fп043Fп	(Lkkkkkk/uunnuu;Lkkkkkk/nunnuu;Lkkkkkk/nnnuuu$ununuu;Lkkkkkk/nuuunu;Lkkkkkk/nnnuuu$nnunuu;Ljava/lang/String;[Lkkkkkk/nuuuuu$unuuuu;)V
    //   189: return
    //   190: astore_1
    //   191: aload_1
    //   192: athrow
    //   193: astore_1
    //   194: aload_1
    //   195: athrow
    //   196: astore_1
    //   197: aload_1
    //   198: athrow
    //   199: astore_1
    //   200: aload_1
    //   201: athrow
    // Local variable table:
    //   start	length	slot	name	signature
    //   0	202	0	this	mwwmww
    //   0	202	1	paramRcrccr	rcrccr
    //   3	15	2	i	int
    //   7	10	3	j	int
    //   11	10	4	k	int
    //   55	105	5	localNuuuuu	nuuuuu
    //   60	102	6	localUunnuu	uunnuu
    //   65	99	7	localNunnuu	nunnuu
    //   70	96	8	localUnunuu	nnnuuu.ununuu
    //   75	93	9	localNuuunu	nuuunu
    //   80	90	10	localNnunuu	nnnuuu.nnunuu
    //   91	81	11	str	String
    //   96	88	12	localObject	Object
    // Exception table:
    //   from	to	target	type
    //   77	98	190	java/lang/Exception
    //   130	135	190	java/lang/Exception
    //   142	159	190	java/lang/Exception
    //   0	13	193	java/lang/Exception
    //   191	193	193	java/lang/Exception
    //   51	77	196	java/lang/Exception
    //   135	142	196	java/lang/Exception
    //   159	189	196	java/lang/Exception
    //   40	51	199	java/lang/Exception
    //   197	199	199	java/lang/Exception
  }
  
  public void b04300430а0430а0430аа04300430()
  {
    nuuuuu localNuuuuu = this.bн043Dн043Dн043Dнн043D;
    uunnuu localUunnuu = uunnuu.SERVICE;
    nunnuu localNunnuu = nunnuu.CLICK_TO_CALL;
    nnnuuu.ununuu localUnunuu = nnnuuu.ununuu.CLICK_TO_CALL;
    nuuunu localNuuunu = nuuunu.N3_20;
    nnnuuu.nnunuu localNnunuu = nnnuuu.nnunuu.TWO;
    String str = gguuuu.bккккк043Aкк043A043A("j\f\b{\fx\t3^z\004\004", 'e', '\005');
    nuuuuu.unuuuu localUnuuuu1 = nuuuuu.unuuuu.b043F043F043Fп043F043Fпп043Fп(unuunu.JOURNEY_PRODUCT, gguuuu.bк043Aккк043Aкк043A043A("|\023$Kz\034\030\f\034\t\031Cg\020\022\025\b\020\006\001\016", '½', '\023', '\002'));
    nuuuuu.unuuuu localUnuuuu2 = nuuuuu.unuuuu.b043F043F043Fп043F043Fпп043Fп(unuunu.SCREEN_NAME, gguuuu.bккккк043Aкк043A043A("DTB\036Kar\032IjfZjWge", '©', '\002'));
    if ((bнн043D043Dн043Dнн043D + bа0430ааа0430аа04300430()) * bнн043D043Dн043Dнн043D % b043D043D043D043Dн043Dнн043D != b043Dн043D043Dн043Dнн043D)
    {
      bнн043D043Dн043Dнн043D = 31;
      b043Dн043D043Dн043Dнн043D = bааааа0430аа04300430();
    }
    localNuuuuu.b043Fп043Fппп043Fп043Fп(localUunnuu, localNunnuu, localUnunuu, localNuuunu, localNnunuu, str, new nuuuuu.unuuuu[] { localUnuuuu1, localUnuuuu2 });
  }
  
  public void b0430а0430аа0430аа04300430()
  {
    switch (0)
    {
    case 1: 
    default: 
      for (;;)
      {
        switch (0)
        {
        }
      }
    }
    nuuuuu localNuuuuu = this.bн043Dн043Dн043Dнн043D;
    uunnuu localUunnuu = uunnuu.SERVICE;
    nunnuu localNunnuu = nunnuu.CLICK_TO_CALL;
    nnnuuu.ununuu localUnunuu = nnnuuu.ununuu.CLICK_TO_CALL;
    nuuunu localNuuunu = nuuunu.N3_20;
    nnnuuu.nnunuu localNnunuu = nnnuuu.nnunuu.TWO;
    String str = gguuuu.bккккк043Aкк043A043A("Qrq|\002y~)Tpyy", 'w', '\003');
    nuuuuu.unuuuu localUnuuuu = nuuuuu.unuuuu.b043F043F043Fп043F043Fпп043Fп(unuunu.JOURNEY_PRODUCT, gguuuu.bк043Aккк043Aкк043A043A("(?FDr\02589FMGNN", '$', 'Ô', '\001'));
    int i = bнн043D043Dн043Dнн043D;
    int j = bн043D043D043Dн043Dнн043D;
    int k = bааааа0430аа04300430();
    switch (k * (bн043D043D043Dн043Dнн043D + k) % b043D043D043D043Dн043Dнн043D)
    {
    default: 
      bнн043D043Dн043Dнн043D = bааааа0430аа04300430();
      b043Dн043D043Dн043Dнн043D = bааааа0430аа04300430();
    }
    switch (i * (j + i) % b043D043D043D043Dн043Dнн043D)
    {
    default: 
      bнн043D043Dн043Dнн043D = bааааа0430аа04300430();
      b043Dн043D043Dн043Dнн043D = bааааа0430аа04300430();
    }
    localNuuuuu.b043Fп043Fппп043Fп043Fп(localUunnuu, localNunnuu, localUnunuu, localNuuunu, localNnunuu, str, new nuuuuu.unuuuu[] { localUnuuuu, nuuuuu.unuuuu.b043F043F043Fп043F043Fпп043Fп(unuunu.SCREEN_NAME, gguuuu.bккккк043Aкк043A043A("[m];]\020\021\001\017\t\b\021\n\024\033Gt\023\036 ", '', '\000')) });
  }
  
  public void b0430аа0430а0430аа04300430(rcrccr paramRcrccr)
  {
    nuuuuu localNuuuuu = this.bн043Dн043Dн043Dнн043D;
    uunnuu localUunnuu = uunnuu.SERVICE;
    nunnuu localNunnuu = nunnuu.CLICK_TO_CALL;
    nnnuuu.ununuu localUnunuu = nnnuuu.ununuu.CLICK_TO_CALL;
    nuuunu localNuuunu = nuuunu.N3_20;
    nnnuuu.nnunuu localNnunuu = nnnuuu.nnunuu.THREE;
    String str = gguuuu.bк043Aккк043Aкк043A043A("w\031\025\t\031\006\026@k\b\021\021", 'D', '', '\002');
    switch (1)
    {
    case 0: 
    default: 
      for (;;)
      {
        switch (1)
        {
        }
      }
    }
    int i = bнн043D043Dн043Dнн043D;
    switch (i * (bн043D043D043Dн043Dнн043D + i) % b043D043D043D043Dн043Dнн043D)
    {
    default: 
      bнн043D043Dн043Dнн043D = 4;
      b043Dн043D043Dн043Dнн043D = 25;
    }
    localNuuuuu.b043Fп043Fппп043Fп043Fп(localUunnuu, localNunnuu, localUnunuu, localNuuunu, localNnunuu, str, new nuuuuu.unuuuu[] { nuuuuu.unuuuu.b043F043F043Fп043F043Fпп043Fп(unuunu.JOURNEY_PRODUCT, gguuuu.bккккк043Aкк043A043A("\004\034/X\n-+!3\"4`\00715:/91.=", 'Z', '\004')), nuuuuu.unuuuu.b043F043F043Fп043F043Fпп043Fп(unuunu.JOURNEY_TARIFF, paramRcrccr.toString()), nuuuuu.unuuuu.b043F043F043Fп043F043Fпп043Fп(unuunu.SCREEN_NAME, gguuuu.bккккк043Aкк043A043A("JZH$Qgx opl`p]mk\0279V`_\022Fc", '»', '\003')) });
    i = bнн043D043Dн043Dнн043D;
    switch (i * (bн043D043D043Dн043Dнн043D + i) % b043D043D043D043Dн043Dнн043D)
    {
    default: 
      bнн043D043Dн043Dнн043D = bааааа0430аа04300430();
      b043Dн043D043Dн043Dнн043D = bааааа0430аа04300430();
    }
  }
  
  public void bа04300430аа0430аа04300430(rcrccr paramRcrccr, int paramInt, rrrccr paramRrrccr)
  {
    Object localObject1;
    if (paramInt == 1)
    {
      localObject1 = nnnuuu.uuunuu.SECURE_CALL;
      if (paramRrrccr != null) {
        break label213;
      }
    }
    label213:
    for (paramRrrccr = "";; paramRrrccr = paramRrrccr.toString())
    {
      Object localObject2 = this.bн043Dн043Dн043Dнн043D;
      nnnuuu.nuunuu localNuunuu = nnnuuu.nuunuu.TAP;
      unnuuu localUnnuuu = unnuuu.CORE;
      paramInt = bнн043D043Dн043Dнн043D;
      switch (paramInt * (bн043D043D043Dн043Dнн043D + paramInt) % b0430аааа0430аа04300430())
      {
      default: 
        bнн043D043Dн043Dнн043D = bааааа0430аа04300430();
        b043Dн043D043Dн043Dнн043D = 66;
      }
      paramRcrccr = nuuuuu.unuuuu.b043F043F043Fп043F043Fпп043Fп(unuunu.LINK_VALUE, b04300430ааа0430аа04300430(paramRcrccr));
      switch (0)
      {
      case 1: 
      default: 
        for (;;)
        {
          switch (1)
          {
          }
        }
      }
      ((nuuuuu)localObject2).b043F043F043F043F043F043Fпп043Fп(localNuunuu, (nnnuuu.uuunuu)localObject1, paramRrrccr, localUnnuuu, new nuuuuu.unuuuu[] { paramRcrccr });
      return;
      localObject2 = nnnuuu.uuunuu.UNSECURE_CALL;
      localObject1 = localObject2;
      if ((bнн043D043Dн043Dнн043D + bа0430ааа0430аа04300430()) * bнн043D043Dн043Dнн043D % b0430аааа0430аа04300430() == b043Dн043D043Dн043Dнн043D) {
        break;
      }
      bнн043D043Dн043Dнн043D = bааааа0430аа04300430();
      b043Dн043D043Dн043Dнн043D = bааааа0430аа04300430();
      localObject1 = localObject2;
      break;
    }
  }
  
  /* Error */
  public void bа0430а0430а0430аа04300430()
  {
    // Byte code:
    //   0: aload_0
    //   1: getfield 121	kkkkkk/mwwmww:bн043Dн043Dн043Dнн043D	Lkkkkkk/nuuuuu;
    //   4: astore 4
    //   6: getstatic 162	kkkkkk/uunnuu:SERVICE	Lkkkkkk/uunnuu;
    //   9: astore 5
    //   11: getstatic 168	kkkkkk/nunnuu:CLICK_TO_CALL	Lkkkkkk/nunnuu;
    //   14: astore 6
    //   16: getstatic 173	kkkkkk/nnnuuu$ununuu:CLICK_TO_CALL	Lkkkkkk/nnnuuu$ununuu;
    //   19: astore 7
    //   21: getstatic 179	kkkkkk/nuuunu:N3_20	Lkkkkkk/nuuunu;
    //   24: astore 8
    //   26: getstatic 81	kkkkkk/mwwmww:bнн043D043Dн043Dнн043D	I
    //   29: istore_1
    //   30: getstatic 83	kkkkkk/mwwmww:bн043D043D043Dн043Dнн043D	I
    //   33: istore_2
    //   34: getstatic 85	kkkkkk/mwwmww:b043D043D043D043Dн043Dнн043D	I
    //   37: istore_3
    //   38: iload_1
    //   39: iload_2
    //   40: iload_1
    //   41: iadd
    //   42: imul
    //   43: iload_3
    //   44: irem
    //   45: tableswitch	default:+19->64, 0:+29->74
    //   64: invokestatic 130	kkkkkk/mwwmww:bааааа0430аа04300430	()I
    //   67: putstatic 81	kkkkkk/mwwmww:bнн043D043Dн043Dнн043D	I
    //   70: iconst_1
    //   71: putstatic 87	kkkkkk/mwwmww:b043Dн043D043Dн043Dнн043D	I
    //   74: getstatic 276	kkkkkk/nnnuuu$nnunuu:ONE	Lkkkkkk/nnnuuu$nnunuu;
    //   77: astore 9
    //   79: ldc_w 278
    //   82: bipush 66
    //   84: iconst_0
    //   85: invokestatic 93	kkkkkk/gguuuu:bккккк043Aкк043A043A	(Ljava/lang/String;CC)Ljava/lang/String;
    //   88: astore 10
    //   90: getstatic 204	kkkkkk/unuunu:SCREEN_NAME	Lkkkkkk/unuunu;
    //   93: astore 11
    //   95: ldc_w 280
    //   98: bipush 92
    //   100: sipush 208
    //   103: iconst_1
    //   104: invokestatic 75	kkkkkk/gguuuu:bк043Aккк043Aкк043A043A	(Ljava/lang/String;CCC)Ljava/lang/String;
    //   107: astore 12
    //   109: invokestatic 130	kkkkkk/mwwmww:bааааа0430аа04300430	()I
    //   112: invokestatic 141	kkkkkk/mwwmww:bа0430ааа0430аа04300430	()I
    //   115: iadd
    //   116: invokestatic 130	kkkkkk/mwwmww:bааааа0430аа04300430	()I
    //   119: imul
    //   120: getstatic 85	kkkkkk/mwwmww:b043D043D043D043Dн043Dнн043D	I
    //   123: irem
    //   124: getstatic 87	kkkkkk/mwwmww:b043Dн043D043Dн043Dнн043D	I
    //   127: if_icmpeq +15 -> 142
    //   130: invokestatic 130	kkkkkk/mwwmww:bааааа0430аа04300430	()I
    //   133: putstatic 81	kkkkkk/mwwmww:bнн043D043Dн043Dнн043D	I
    //   136: invokestatic 130	kkkkkk/mwwmww:bааааа0430аа04300430	()I
    //   139: putstatic 87	kkkkkk/mwwmww:b043Dн043D043Dн043Dнн043D	I
    //   142: aload 11
    //   144: aload 12
    //   146: invokestatic 201	kkkkkk/nuuuuu$unuuuu:b043F043F043Fп043F043Fпп043Fп	(Lkkkkkk/unuunu;Ljava/lang/String;)Lkkkkkk/nuuuuu$unuuuu;
    //   149: astore 11
    //   151: aload 4
    //   153: aload 5
    //   155: aload 6
    //   157: aload 7
    //   159: aload 8
    //   161: aload 9
    //   163: aload 10
    //   165: iconst_1
    //   166: anewarray 197	kkkkkk/nuuuuu$unuuuu
    //   169: dup
    //   170: iconst_0
    //   171: aload 11
    //   173: aastore
    //   174: invokevirtual 212	kkkkkk/nuuuuu:b043Fп043Fппп043Fп043Fп	(Lkkkkkk/uunnuu;Lkkkkkk/nunnuu;Lkkkkkk/nnnuuu$ununuu;Lkkkkkk/nuuunu;Lkkkkkk/nnnuuu$nnunuu;Ljava/lang/String;[Lkkkkkk/nuuuuu$unuuuu;)V
    //   177: return
    //   178: astore 4
    //   180: aload 4
    //   182: athrow
    //   183: astore 4
    //   185: aload 4
    //   187: athrow
    //   188: astore 4
    //   190: aload 4
    //   192: athrow
    //   193: astore 4
    //   195: aload 4
    //   197: athrow
    // Local variable table:
    //   start	length	slot	name	signature
    //   0	198	0	this	mwwmww
    //   29	14	1	i	int
    //   33	9	2	j	int
    //   37	8	3	k	int
    //   4	148	4	localNuuuuu	nuuuuu
    //   178	3	4	localException1	Exception
    //   183	3	4	localException2	Exception
    //   188	3	4	localException3	Exception
    //   193	3	4	localException4	Exception
    //   9	145	5	localUunnuu	uunnuu
    //   14	142	6	localNunnuu	nunnuu
    //   19	139	7	localUnunuu	nnnuuu.ununuu
    //   24	136	8	localNuuunu	nuuunu
    //   77	85	9	localNnunuu	nnnuuu.nnunuu
    //   88	76	10	str1	String
    //   93	79	11	localObject	Object
    //   107	38	12	str2	String
    // Exception table:
    //   from	to	target	type
    //   90	95	178	java/lang/Exception
    //   151	177	178	java/lang/Exception
    //   26	38	183	java/lang/Exception
    //   180	183	183	java/lang/Exception
    //   0	26	188	java/lang/Exception
    //   74	90	188	java/lang/Exception
    //   95	109	188	java/lang/Exception
    //   142	151	188	java/lang/Exception
    //   64	74	193	java/lang/Exception
    //   190	193	193	java/lang/Exception
  }
  
  public void bаа04300430а0430аа04300430()
  {
    nuuuuu localNuuuuu = this.bн043Dн043Dн043Dнн043D;
    nnnuuu.nuunuu localNuunuu = nnnuuu.nuunuu.OVERLAY;
    nnnuuu.uuunuu localUuunuu = nnnuuu.uuunuu.MORE_INFO_NEEDED;
    String str = gguuuu.bк043Aккк043Aкк043A043A("Txy6e}\021:i\022\013\001\005\023", 'U', '=', '\003');
    unnuuu localUnnuuu = unnuuu.CORE;
    switch (1)
    {
    case 0: 
    default: 
      for (;;)
      {
        switch (0)
        {
        }
      }
    }
    if ((bааааа0430аа04300430() + bа0430ааа0430аа04300430()) * bааааа0430аа04300430() % b043D043D043D043Dн043Dнн043D != b043Dн043D043Dн043Dнн043D)
    {
      bнн043D043Dн043Dнн043D = 44;
      b043Dн043D043Dн043Dнн043D = bааааа0430аа04300430();
      if ((bнн043D043Dн043Dнн043D + bа0430ааа0430аа04300430()) * bнн043D043Dн043Dнн043D % b043D043D043D043Dн043Dнн043D != b043Dн043D043Dн043Dнн043D)
      {
        bнн043D043Dн043Dнн043D = 47;
        b043Dн043D043Dн043Dнн043D = bааааа0430аа04300430();
      }
    }
    localNuuuuu.b043F043F043F043F043F043Fпп043Fп(localNuunuu, localUuunuu, str, localUnnuuu, new nuuuuu.unuuuu[0]);
  }
  
  public void bаа0430аа0430аа04300430(String paramString)
  {
    switch (0)
    {
    case 1: 
    default: 
      for (;;)
      {
        switch (1)
        {
        }
      }
    }
    rgrggg localRgrggg = this.b043D043Dн043Dн043Dнн043D;
    switch (1)
    {
    case 0: 
    default: 
      for (;;)
      {
        switch (1)
        {
        }
      }
    }
    if ((bнн043D043Dн043Dнн043D + bн043D043D043Dн043Dнн043D) * bнн043D043Dн043Dнн043D % b043D043D043D043Dн043Dнн043D != b043Dн043D043Dн043Dнн043D)
    {
      bнн043D043Dн043Dнн043D = bааааа0430аа04300430();
      b043Dн043D043Dн043Dнн043D = bааааа0430аа04300430();
      int i = bнн043D043Dн043Dнн043D;
      switch (i * (bа0430ааа0430аа04300430() + i) % b0430аааа0430аа04300430())
      {
      default: 
        bнн043D043Dн043Dнн043D = bааааа0430аа04300430();
        b043Dн043D043Dн043Dнн043D = 34;
      }
    }
    localRgrggg.bИИ041804180418041804180418ИИ(paramString, gguuuu.bккккк043Aкк043A043A("Brq_kc`g^fki", 'ý', '\005'));
  }
  
  /* Error */
  public void bааа0430а0430аа04300430(ccrrcc paramCcrrcc)
  {
    // Byte code:
    //   0: aload_0
    //   1: getfield 121	kkkkkk/mwwmww:bн043Dн043Dн043Dнн043D	Lkkkkkk/nuuuuu;
    //   4: astore 5
    //   6: getstatic 81	kkkkkk/mwwmww:bнн043D043Dн043Dнн043D	I
    //   9: getstatic 83	kkkkkk/mwwmww:bн043D043D043Dн043Dнн043D	I
    //   12: iadd
    //   13: getstatic 81	kkkkkk/mwwmww:bнн043D043Dн043Dнн043D	I
    //   16: imul
    //   17: getstatic 85	kkkkkk/mwwmww:b043D043D043D043Dн043Dнн043D	I
    //   20: irem
    //   21: getstatic 87	kkkkkk/mwwmww:b043Dн043D043Dн043Dнн043D	I
    //   24: if_icmpeq +15 -> 39
    //   27: invokestatic 130	kkkkkk/mwwmww:bааааа0430аа04300430	()I
    //   30: putstatic 81	kkkkkk/mwwmww:bнн043D043Dн043Dнн043D	I
    //   33: invokestatic 130	kkkkkk/mwwmww:bааааа0430аа04300430	()I
    //   36: putstatic 87	kkkkkk/mwwmww:b043Dн043D043Dн043Dнн043D	I
    //   39: getstatic 162	kkkkkk/uunnuu:SERVICE	Lkkkkkk/uunnuu;
    //   42: astore 6
    //   44: getstatic 168	kkkkkk/nunnuu:CLICK_TO_CALL	Lkkkkkk/nunnuu;
    //   47: astore 7
    //   49: getstatic 173	kkkkkk/nnnuuu$ununuu:CLICK_TO_CALL	Lkkkkkk/nnnuuu$ununuu;
    //   52: astore 8
    //   54: getstatic 179	kkkkkk/nuuunu:N3_20	Lkkkkkk/nuuunu;
    //   57: astore 9
    //   59: iconst_1
    //   60: tableswitch	default:+24->84, 0:+-1->59, 1:+51->111
    //   84: iconst_0
    //   85: tableswitch	default:+23->108, 0:+26->111, 1:+-26->59
    //   108: goto -24 -> 84
    //   111: invokestatic 130	kkkkkk/mwwmww:bааааа0430аа04300430	()I
    //   114: istore_2
    //   115: getstatic 83	kkkkkk/mwwmww:bн043D043D043Dн043Dнн043D	I
    //   118: istore_3
    //   119: getstatic 85	kkkkkk/mwwmww:b043D043D043D043Dн043Dнн043D	I
    //   122: istore 4
    //   124: iload_2
    //   125: iload_3
    //   126: iload_2
    //   127: iadd
    //   128: imul
    //   129: iload 4
    //   131: irem
    //   132: tableswitch	default:+20->152, 0:+30->162
    //   152: bipush 13
    //   154: putstatic 81	kkkkkk/mwwmww:bнн043D043Dн043Dнн043D	I
    //   157: bipush 58
    //   159: putstatic 87	kkkkkk/mwwmww:b043Dн043D043Dн043Dнн043D	I
    //   162: getstatic 228	kkkkkk/nnnuuu$nnunuu:THREE	Lkkkkkk/nnnuuu$nnunuu;
    //   165: astore 10
    //   167: ldc_w 303
    //   170: sipush 153
    //   173: iconst_4
    //   174: invokestatic 93	kkkkkk/gguuuu:bккккк043Aкк043A043A	(Ljava/lang/String;CC)Ljava/lang/String;
    //   177: astore 11
    //   179: getstatic 193	kkkkkk/unuunu:JOURNEY_PRODUCT	Lkkkkkk/unuunu;
    //   182: astore 12
    //   184: ldc_w 305
    //   187: sipush 142
    //   190: iconst_1
    //   191: invokestatic 93	kkkkkk/gguuuu:bккккк043Aкк043A043A	(Ljava/lang/String;CC)Ljava/lang/String;
    //   194: astore 13
    //   196: aload 12
    //   198: aload 13
    //   200: invokestatic 201	kkkkkk/nuuuuu$unuuuu:b043F043F043Fп043F043Fпп043Fп	(Lkkkkkk/unuunu;Ljava/lang/String;)Lkkkkkk/nuuuuu$unuuuu;
    //   203: astore 12
    //   205: aload 5
    //   207: aload 6
    //   209: aload 7
    //   211: aload 8
    //   213: aload 9
    //   215: aload 10
    //   217: aload 11
    //   219: iconst_3
    //   220: anewarray 197	kkkkkk/nuuuuu$unuuuu
    //   223: dup
    //   224: iconst_0
    //   225: aload 12
    //   227: aastore
    //   228: dup
    //   229: iconst_1
    //   230: getstatic 235	kkkkkk/unuunu:JOURNEY_TARIFF	Lkkkkkk/unuunu;
    //   233: aload_1
    //   234: invokevirtual 308	kkkkkk/ccrrcc:toString	()Ljava/lang/String;
    //   237: invokestatic 201	kkkkkk/nuuuuu$unuuuu:b043F043F043Fп043F043Fпп043Fп	(Lkkkkkk/unuunu;Ljava/lang/String;)Lkkkkkk/nuuuuu$unuuuu;
    //   240: aastore
    //   241: dup
    //   242: iconst_2
    //   243: getstatic 204	kkkkkk/unuunu:SCREEN_NAME	Lkkkkkk/unuunu;
    //   246: ldc_w 310
    //   249: sipush 136
    //   252: iconst_1
    //   253: invokestatic 93	kkkkkk/gguuuu:bккккк043Aкк043A043A	(Ljava/lang/String;CC)Ljava/lang/String;
    //   256: invokestatic 201	kkkkkk/nuuuuu$unuuuu:b043F043F043Fп043F043Fпп043Fп	(Lkkkkkk/unuunu;Ljava/lang/String;)Lkkkkkk/nuuuuu$unuuuu;
    //   259: aastore
    //   260: invokevirtual 212	kkkkkk/nuuuuu:b043Fп043Fппп043Fп043Fп	(Lkkkkkk/uunnuu;Lkkkkkk/nunnuu;Lkkkkkk/nnnuuu$ununuu;Lkkkkkk/nuuunu;Lkkkkkk/nnnuuu$nnunuu;Ljava/lang/String;[Lkkkkkk/nuuuuu$unuuuu;)V
    //   263: return
    //   264: astore_1
    //   265: aload_1
    //   266: athrow
    //   267: astore_1
    //   268: aload_1
    //   269: athrow
    // Local variable table:
    //   start	length	slot	name	signature
    //   0	270	0	this	mwwmww
    //   0	270	1	paramCcrrcc	ccrrcc
    //   114	15	2	i	int
    //   118	10	3	j	int
    //   122	10	4	k	int
    //   4	202	5	localNuuuuu	nuuuuu
    //   42	166	6	localUunnuu	uunnuu
    //   47	163	7	localNunnuu	nunnuu
    //   52	160	8	localUnunuu	nnnuuu.ununuu
    //   57	157	9	localNuuunu	nuuunu
    //   165	51	10	localNnunuu	nnnuuu.nnunuu
    //   177	41	11	str1	String
    //   182	44	12	localObject	Object
    //   194	5	13	str2	String
    // Exception table:
    //   from	to	target	type
    //   0	6	264	java/lang/Exception
    //   111	124	264	java/lang/Exception
    //   157	162	264	java/lang/Exception
    //   162	167	264	java/lang/Exception
    //   184	196	264	java/lang/Exception
    //   205	263	264	java/lang/Exception
    //   39	59	267	java/lang/Exception
    //   152	157	267	java/lang/Exception
    //   167	179	267	java/lang/Exception
    //   179	184	267	java/lang/Exception
    //   196	205	267	java/lang/Exception
  }
}
