package kkkkkk;

import android.database.Cursor;

public class nfnfnn
{
  public static int b043C043C043C043C043Cм043C043Cм = 1;
  private static final String b043Cм043C043Cмм043C043Cм;
  public static int b043Cмммм043C043C043Cм = 0;
  public static int bм043C043C043C043Cм043C043Cм = 66;
  public static int bммммм043C043C043Cм = 2;
  private String b043C043C043C043Cмм043C043Cм;
  private long b043C043C043Cм043Cм043C043Cм;
  private String b043C043Cм043C043Cм043C043Cм;
  private dxdxdd b043C043Cмм043Cм043C043Cм;
  private int b043Cм043C043C043Cм043C043Cм = 0;
  private int b043Cм043Cм043Cм043C043Cм = -1;
  private long b043Cмм043C043Cм043C043Cм;
  private long b043Cммм043Cм043C043Cм = -1L;
  private String bм043C043C043Cмм043C043Cм;
  private fffnnf bм043C043Cм043Cм043C043Cм = new fffnnf();
  private nfffnf bм043Cм043C043Cм043C043Cм;
  private String bм043Cмм043Cм043C043Cм;
  private int bмм043C043C043Cм043C043Cм;
  private xdxxdd bмм043Cм043Cм043C043Cм = xdxxdd.NORMAL;
  private xxxddd.dddxdd bммм043C043Cм043C043Cм = xxxddd.dddxdd.NO_VALUE;
  private xddxdd bмммм043Cм043C043Cм = null;
  
  static
  {
    throw new Runtime("d2j fail translate: java.lang.IndexOutOfBoundsException: fromIndex < 0: -1\n\tat java.util.BitSet.nextSetBit(BitSet.java:712)\n\tat com.googlecode.dex2jar.ir.ts.array.FillArrayTransformer.makeSureAllElementAreAssigned(FillArrayTransformer.java:505)\n\tat com.googlecode.dex2jar.ir.ts.array.FillArrayTransformer.transformReportChanged(FillArrayTransformer.java:123)\n\tat com.googlecode.dex2jar.ir.ts.StatedTransformer.transform(StatedTransformer.java:10)\n\tat com.googlecode.d2j.dex.Dex2jar$2.optimize(Dex2jar.java:149)\n\tat com.googlecode.d2j.dex.Dex2Asm.convertCode(Dex2Asm.java:414)\n\tat com.googlecode.d2j.dex.ExDex2Asm.convertCode(ExDex2Asm.java:42)\n\tat com.googlecode.d2j.dex.Dex2jar$2.convertCode(Dex2jar.java:128)\n\tat com.googlecode.d2j.dex.Dex2Asm.convertMethod(Dex2Asm.java:509)\n\tat com.googlecode.d2j.dex.Dex2Asm.convertClass(Dex2Asm.java:406)\n\tat com.googlecode.d2j.dex.Dex2Asm.convertDex(Dex2Asm.java:422)\n\tat com.googlecode.d2j.dex.Dex2jar.doTranslate(Dex2jar.java:172)\n\tat com.googlecode.d2j.dex.Dex2jar.to(Dex2jar.java:272)\n\tat com.googlecode.dex2jar.tools.Dex2jarCmd.doCommandLine(Dex2jarCmd.java:108)\n\tat com.googlecode.dex2jar.tools.BaseCmd.doMain(BaseCmd.java:288)\n\tat com.googlecode.dex2jar.tools.Dex2jarCmd.main(Dex2jarCmd.java:32)\n");
  }
  
  public nfnfnn(Cursor paramCursor)
  {
    xtxtxt.bии0438и04380438и0438ии(gguuuu.bк043Aккк043Aкк043A043A("\026CJ\033HHQAOQ@TJQQ", '', 'È', '\001'), gguuuu.bк043Aккк043Aкк043A043A("\037*(,,)+\030(\"$b", '', '>', '\000'));
    this.bм043Cмм043Cм043C043Cм = paramCursor.getString(paramCursor.getColumnIndex(gguuuu.bккккк043Aкк043A043A("~\f\f\025\005\023\025\004\030\016\025\025p\r", '\t', '\001')));
    this.b043C043C043C043Cмм043C043Cм = paramCursor.getString(paramCursor.getColumnIndex(gguuuu.bк043Aккк043Aкк043A043A("ap^j_C]", '«', 'Ó', '\002')));
    this.b043C043Cм043C043Cм043C043Cм = paramCursor.getString(paramCursor.getColumnIndex(gguuuu.bккккк043Aкк043A043A("5!1%\"0\004\036", '\025', '\002')));
    int i = paramCursor.getInt(paramCursor.getColumnIndex(gguuuu.bк043Aккк043Aкк043A043A("hjXl^", '~', 'u', '\003')));
    this.b043C043Cмм043Cм043C043Cм = dxdxdd.values()[i];
    this.b043C043C043Cм043Cм043C043Cм = paramCursor.getLong(paramCursor.getColumnIndex(gguuuu.bк043Aккк043Aкк043A043A("`TafWfhT_[", '%', 'Ç', '\003')));
    this.b043Cм043Cм043Cм043C043Cм = paramCursor.getInt(paramCursor.getColumnIndex(gguuuu.bккккк043Aкк043A043A("\b}\021\023~\024\007\025\032\n\030\006\033\016\033 \021\033\021\024", '\t', '\001')));
    this.bм043C043C043Cмм043C043Cм = paramCursor.getString(paramCursor.getColumnIndex(gguuuu.bк043Aккк043Aкк043A043A("3FG>=E==\033BAKR(D", '¡', 'P', '\001')));
    i = paramCursor.getInt(paramCursor.getColumnIndex(gguuuu.bккккк043Aкк043A043A("%&%\023)/'\035", '0', '\000')));
    if (i != -1) {
      this.bмм043Cм043Cм043C043Cм = xdxxdd.values()[i];
    }
    this.bммм043C043Cм043C043Cм = xxxddd.dddxdd.bх044504450445хх0445х04450445(paramCursor.getInt(paramCursor.getColumnIndex(gguuuu.bккккк043Aкк043A043A("UIOVCA;>M:L", '\n', '\002'))));
    this.b043Cммм043Cм043C043Cм = paramCursor.getLong(paramCursor.getColumnIndex(gguuuu.bк043Aккк043Aкк043A043A("T^bgZUkaf_", '@', 'O', '\001')));
    i = paramCursor.getInt(paramCursor.getColumnIndex(gguuuu.bккккк043Aкк043A043A("\035'+0#\0362&#633", '9', '\000')));
    if (i != -1) {
      this.bмммм043Cм043C043Cм = xddxdd.values()[i];
    }
    this.bмм043C043C043Cм043C043Cм = paramCursor.getInt(paramCursor.getColumnIndex(gguuuu.bк043Aккк043Aкк043A043A("_WZLGICPUH", '|', 'f', '\000')));
    this.b043Cмм043C043Cм043C043Cм = paramCursor.getLong(paramCursor.getColumnIndex(gguuuu.bккккк043Aкк043A043A("[]K]`LbX]V", 'g', '\000')));
    this.b043Cм043C043C043Cм043C043Cм = paramCursor.getInt(paramCursor.getColumnIndex(gguuuu.bк043Aккк043Aкк043A043A("WSHFZPVPITZL^a_XdXghUj]f[kdlpd", '½', 'Û', '\001')));
    this.bм043Cм043C043Cм043C043Cм = new nfffnf(this.b043C043Cм043C043Cм043C043Cм);
  }
  
  public nfnfnn(String paramString1, String paramString2)
  {
    xtxtxt.bии0438и04380438и0438ии(gguuuu.bк043Aккк043Aкк043A043A("\033HO MMVFTVEYOVV", '1', '(', '\003'), gguuuu.bккккк043Aкк043A043A("z\006\004\b\b\005\007s\004}=", '³', '\003'));
    this.b043C043Cм043C043Cм043C043Cм = paramString1;
    this.b043C043C043C043Cмм043C043Cм = paramString2;
    this.bм043Cм043C043Cм043C043Cм = new nfffnf(this.b043C043Cм043C043Cм043C043Cм);
  }
  
  public nfnfnn(ffnfnn paramFfnfnn)
  {
    this.b043C043Cм043C043Cм043C043Cм = paramFfnfnn.b043C043Cмм043C043C043C043Cм;
    this.b043C043C043C043Cмм043C043Cм = paramFfnfnn.bмм043Cмм043C043C043Cм;
    this.bм043Cмм043Cм043C043Cм = paramFfnfnn.b043C043C043Cмм043C043C043Cм;
    this.b043C043C043Cм043Cм043C043Cм = paramFfnfnn.b043C043C043C043Cм043C043C043Cм;
    this.b043C043Cмм043Cм043C043Cм = paramFfnfnn.bм043Cмм043C043C043C043Cм;
    this.bмм043Cм043Cм043C043Cм = paramFfnfnn.bммм043Cм043C043C043Cм;
    this.bм043C043C043Cмм043C043Cм = paramFfnfnn.b043C043Cммм043C043C043Cм;
    this.b043Cмм043C043Cм043C043Cм = paramFfnfnn.b043Cммм043C043C043C043Cм;
    this.bмм043C043C043Cм043C043Cм = paramFfnfnn.b043Cм043Cм043C043C043C043Cм;
    this.bмммм043Cм043C043Cм = paramFfnfnn.b043Cм043Cмм043C043C043Cм;
    this.b043Cммм043Cм043C043Cм = paramFfnfnn.bмм043C043Cм043C043C043Cм;
    this.bм043Cм043C043Cм043C043Cм = new nfffnf(this.b043C043Cм043C043Cм043C043Cм);
  }
  
  public static int b044D044Dэ044Dээ044Dэ044Dэ()
  {
    return 1;
  }
  
  public static int b044Dэ044D044Dээ044Dэ044Dэ()
  {
    return 0;
  }
  
  public static int bэ044D044D044Dээ044Dэ044Dэ()
  {
    return 2;
  }
  
  public static int bээ044D044Dээ044Dэ044Dэ()
  {
    return 46;
  }
  
  public xxxddd.dddxdd b044D044D044D044D044Dэ044Dэ044Dэ()
  {
    String str = b043Cм043C043Cмм043C043Cм;
    StringBuilder localStringBuilder = new StringBuilder();
    if ((bм043C043C043C043Cм043C043Cм + b043C043C043C043C043Cм043C043Cм) * bм043C043C043C043Cм043C043Cм % bммммм043C043C043Cм != b043Cмммм043C043C043Cм)
    {
      bм043C043C043C043Cм043C043Cм = 56;
      b043Cмммм043C043C043Cм = 64;
    }
    xtxtxt.bии0438и04380438и0438ии(str, gguuuu.bк043Aккк043Aкк043A043A("R[:NT[HF$3 2\027", '', 'p', '\000') + this.bммм043C043Cм043C043Cм);
    int i = bм043C043C043C043Cм043C043Cм;
    switch (i * (b043C043C043C043C043Cм043C043Cм + i) % bммммм043C043C043Cм)
    {
    default: 
      bм043C043C043C043Cм043C043Cм = bээ044D044Dээ044Dэ044Dэ();
      b043Cмммм043C043C043Cм = bээ044D044Dээ044Dэ044Dэ();
    }
    switch (1)
    {
    case 0: 
    default: 
      for (;;)
      {
        switch (0)
        {
        case 1: 
        default: 
          for (;;)
          {
            switch (0)
            {
            }
          }
        }
        switch (0)
        {
        }
      }
    }
    return this.bммм043C043Cм043C043Cм;
  }
  
  public String b044D044D044D044Dээ044Dэ044Dэ()
  {
    if ((bм043C043C043C043Cм043C043Cм + b043C043C043C043C043Cм043C043Cм) * bм043C043C043C043Cм043C043Cм % bммммм043C043C043Cм != b043Cмммм043C043C043Cм)
    {
      bм043C043C043C043Cм043C043Cм = bээ044D044Dээ044Dэ044Dэ();
      b043Cмммм043C043C043Cм = bээ044D044Dээ044Dэ044Dэ();
    }
    try
    {
      throw new NullPointerException();
    }
    catch (Exception localException)
    {
      bм043C043C043C043Cм043C043Cм = bээ044D044Dээ044Dэ044Dэ();
      String str = this.bм043C043C043Cмм043C043Cм;
      switch (0)
      {
      case 1: 
      default: 
        for (;;)
        {
          switch (0)
          {
          }
        }
      }
      return str;
    }
  }
  
  public long b044D044D044Dэ044Dэ044Dэ044Dэ()
  {
    int i = bм043C043C043C043Cм043C043Cм;
    switch (i * (b043C043C043C043C043Cм043C043Cм + i) % bммммм043C043C043Cм)
    {
    default: 
      bм043C043C043C043Cм043C043Cм = 54;
      b043Cмммм043C043C043Cм = 56;
    }
    try
    {
      long l = this.b043C043C043Cм043Cм043C043Cм;
      if ((bм043C043C043C043Cм043C043Cм + b043C043C043C043C043Cм043C043Cм) * bм043C043C043C043Cм043C043Cм % bммммм043C043C043Cм != b043Cмммм043C043C043Cм)
      {
        bм043C043C043C043Cм043C043Cм = bээ044D044Dээ044Dэ044Dэ();
        b043Cмммм043C043C043Cм = bээ044D044Dээ044Dэ044Dэ();
      }
      return l;
    }
    catch (Exception localException)
    {
      throw localException;
    }
  }
  
  /* Error */
  public void b044D044D044Dээ044D044Dэ044Dэ(String paramString)
  {
    // Byte code:
    //   0: invokestatic 263	kkkkkk/nfnfnn:bээ044D044Dээ044Dэ044Dэ	()I
    //   3: istore_2
    //   4: getstatic 244	kkkkkk/nfnfnn:b043C043C043C043C043Cм043C043Cм	I
    //   7: istore_3
    //   8: invokestatic 263	kkkkkk/nfnfnn:bээ044D044Dээ044Dэ044Dэ	()I
    //   11: istore 4
    //   13: getstatic 246	kkkkkk/nfnfnn:bммммм043C043C043Cм	I
    //   16: istore 5
    //   18: getstatic 248	kkkkkk/nfnfnn:b043Cмммм043C043C043Cм	I
    //   21: istore 6
    //   23: iload_2
    //   24: iload_3
    //   25: iadd
    //   26: iload 4
    //   28: imul
    //   29: iload 5
    //   31: irem
    //   32: iload 6
    //   34: if_icmpeq +61 -> 95
    //   37: getstatic 242	kkkkkk/nfnfnn:bм043C043C043C043Cм043C043Cм	I
    //   40: istore_2
    //   41: iload_2
    //   42: getstatic 244	kkkkkk/nfnfnn:b043C043C043C043C043Cм043C043Cм	I
    //   45: iload_2
    //   46: iadd
    //   47: imul
    //   48: getstatic 246	kkkkkk/nfnfnn:bммммм043C043C043Cм	I
    //   51: irem
    //   52: tableswitch	default:+20->72, 0:+32->84
    //   72: invokestatic 263	kkkkkk/nfnfnn:bээ044D044Dээ044Dэ044Dэ	()I
    //   75: putstatic 242	kkkkkk/nfnfnn:bм043C043C043C043Cм043C043Cм	I
    //   78: invokestatic 263	kkkkkk/nfnfnn:bээ044D044Dээ044Dэ044Dэ	()I
    //   81: putstatic 248	kkkkkk/nfnfnn:b043Cмммм043C043C043Cм	I
    //   84: invokestatic 263	kkkkkk/nfnfnn:bээ044D044Dээ044Dэ044Dэ	()I
    //   87: putstatic 242	kkkkkk/nfnfnn:bм043C043C043C043Cм043C043Cм	I
    //   90: bipush 81
    //   92: putstatic 248	kkkkkk/nfnfnn:b043Cмммм043C043C043Cм	I
    //   95: aload_0
    //   96: aload_1
    //   97: putfield 117	kkkkkk/nfnfnn:bм043Cмм043Cм043C043Cм	Ljava/lang/String;
    //   100: return
    //   101: astore_1
    //   102: aload_1
    //   103: athrow
    //   104: astore_1
    //   105: aload_1
    //   106: athrow
    //   107: astore_1
    //   108: aload_1
    //   109: athrow
    // Local variable table:
    //   start	length	slot	name	signature
    //   0	110	0	this	nfnfnn
    //   0	110	1	paramString	String
    //   3	45	2	i	int
    //   7	19	3	j	int
    //   11	18	4	k	int
    //   16	16	5	m	int
    //   21	14	6	n	int
    // Exception table:
    //   from	to	target	type
    //   95	100	101	java/lang/Exception
    //   4	23	104	java/lang/Exception
    //   102	104	104	java/lang/Exception
    //   0	4	107	java/lang/Exception
    //   84	95	107	java/lang/Exception
  }
  
  public String b044D044Dэ044D044Dэ044Dэ044Dэ()
  {
    return this.b043C043Cм043C043Cм043C043Cм;
  }
  
  /* Error */
  public void b044D044Dэ044Dэ044D044Dэ044Dэ(int paramInt)
  {
    // Byte code:
    //   0: getstatic 242	kkkkkk/nfnfnn:bм043C043C043C043Cм043C043Cм	I
    //   3: istore_2
    //   4: iload_2
    //   5: getstatic 244	kkkkkk/nfnfnn:b043C043C043C043C043Cм043C043Cм	I
    //   8: iload_2
    //   9: iadd
    //   10: imul
    //   11: getstatic 246	kkkkkk/nfnfnn:bммммм043C043C043Cм	I
    //   14: irem
    //   15: tableswitch	default:+17->32, 0:+29->44
    //   32: invokestatic 263	kkkkkk/nfnfnn:bээ044D044Dээ044Dэ044Dэ	()I
    //   35: putstatic 242	kkkkkk/nfnfnn:bм043C043C043C043Cм043C043Cм	I
    //   38: invokestatic 263	kkkkkk/nfnfnn:bээ044D044Dээ044Dэ044Dэ	()I
    //   41: putstatic 248	kkkkkk/nfnfnn:b043Cмммм043C043C043Cм	I
    //   44: getstatic 242	kkkkkk/nfnfnn:bм043C043C043C043Cм043C043Cм	I
    //   47: istore_2
    //   48: getstatic 244	kkkkkk/nfnfnn:b043C043C043C043C043Cм043C043Cм	I
    //   51: istore_3
    //   52: getstatic 242	kkkkkk/nfnfnn:bм043C043C043C043Cм043C043Cм	I
    //   55: istore 4
    //   57: iload_2
    //   58: iload_3
    //   59: iadd
    //   60: iload 4
    //   62: imul
    //   63: getstatic 246	kkkkkk/nfnfnn:bммммм043C043C043Cм	I
    //   66: irem
    //   67: getstatic 248	kkkkkk/nfnfnn:b043Cмммм043C043C043Cм	I
    //   70: if_icmpeq +15 -> 85
    //   73: invokestatic 263	kkkkkk/nfnfnn:bээ044D044Dээ044Dэ044Dэ	()I
    //   76: putstatic 242	kkkkkk/nfnfnn:bм043C043C043C043Cм043C043Cм	I
    //   79: invokestatic 263	kkkkkk/nfnfnn:bээ044D044Dээ044Dэ044Dэ	()I
    //   82: putstatic 248	kkkkkk/nfnfnn:b043Cмммм043C043C043Cм	I
    //   85: aload_0
    //   86: iload_1
    //   87: putfield 177	kkkkkk/nfnfnn:bмм043C043C043Cм043C043Cм	I
    //   90: return
    //   91: astore 5
    //   93: aload 5
    //   95: athrow
    //   96: astore 5
    //   98: aload 5
    //   100: athrow
    // Local variable table:
    //   start	length	slot	name	signature
    //   0	101	0	this	nfnfnn
    //   0	101	1	paramInt	int
    //   3	57	2	i	int
    //   51	9	3	j	int
    //   55	8	4	k	int
    //   91	3	5	localException1	Exception
    //   96	3	5	localException2	Exception
    // Exception table:
    //   from	to	target	type
    //   44	57	91	java/lang/Exception
    //   85	90	91	java/lang/Exception
    //   57	85	96	java/lang/Exception
  }
  
  /* Error */
  public String b044D044Dээ044Dэ044Dэ044Dэ()
  {
    // Byte code:
    //   0: getstatic 242	kkkkkk/nfnfnn:bм043C043C043C043Cм043C043Cм	I
    //   3: istore_1
    //   4: getstatic 244	kkkkkk/nfnfnn:b043C043C043C043C043Cм043C043Cм	I
    //   7: istore_2
    //   8: getstatic 242	kkkkkk/nfnfnn:bм043C043C043C043Cм043C043Cм	I
    //   11: istore_3
    //   12: getstatic 246	kkkkkk/nfnfnn:bммммм043C043C043Cм	I
    //   15: istore 4
    //   17: getstatic 248	kkkkkk/nfnfnn:b043Cмммм043C043C043Cм	I
    //   20: istore 5
    //   22: iload_1
    //   23: iload_2
    //   24: iadd
    //   25: iload_3
    //   26: imul
    //   27: iload 4
    //   29: irem
    //   30: iload 5
    //   32: if_icmpeq +14 -> 46
    //   35: invokestatic 263	kkkkkk/nfnfnn:bээ044D044Dээ044Dэ044Dэ	()I
    //   38: putstatic 242	kkkkkk/nfnfnn:bм043C043C043C043Cм043C043Cм	I
    //   41: bipush 8
    //   43: putstatic 248	kkkkkk/nfnfnn:b043Cмммм043C043C043Cм	I
    //   46: aload_0
    //   47: getfield 117	kkkkkk/nfnfnn:bм043Cмм043Cм043C043Cм	Ljava/lang/String;
    //   50: astore 6
    //   52: invokestatic 263	kkkkkk/nfnfnn:bээ044D044Dээ044Dэ044Dэ	()I
    //   55: istore_1
    //   56: iload_1
    //   57: getstatic 244	kkkkkk/nfnfnn:b043C043C043C043C043Cм043C043Cм	I
    //   60: iload_1
    //   61: iadd
    //   62: imul
    //   63: invokestatic 278	kkkkkk/nfnfnn:bэ044D044D044Dээ044Dэ044Dэ	()I
    //   66: irem
    //   67: tableswitch	default:+17->84, 0:+28->95
    //   84: bipush 83
    //   86: putstatic 242	kkkkkk/nfnfnn:bм043C043C043C043Cм043C043Cм	I
    //   89: invokestatic 263	kkkkkk/nfnfnn:bээ044D044Dээ044Dэ044Dэ	()I
    //   92: putstatic 248	kkkkkk/nfnfnn:b043Cмммм043C043C043Cм	I
    //   95: aload 6
    //   97: areturn
    //   98: astore 6
    //   100: aload 6
    //   102: athrow
    //   103: astore 6
    //   105: aload 6
    //   107: athrow
    //   108: astore 6
    //   110: aload 6
    //   112: athrow
    // Local variable table:
    //   start	length	slot	name	signature
    //   0	113	0	this	nfnfnn
    //   3	60	1	i	int
    //   7	18	2	j	int
    //   11	16	3	k	int
    //   15	15	4	m	int
    //   20	13	5	n	int
    //   50	46	6	str	String
    //   98	3	6	localException1	Exception
    //   103	3	6	localException2	Exception
    //   108	3	6	localException3	Exception
    // Exception table:
    //   from	to	target	type
    //   46	52	98	java/lang/Exception
    //   4	22	103	java/lang/Exception
    //   100	103	103	java/lang/Exception
    //   0	4	108	java/lang/Exception
    //   35	46	108	java/lang/Exception
  }
  
  public void b044D044Dэээ044D044Dэ044Dэ(long paramLong)
  {
    int i = bм043C043C043C043Cм043C043Cм;
    switch (i * (b043C043C043C043C043Cм043C043Cм + i) % bммммм043C043C043Cм)
    {
    default: 
      bм043C043C043C043Cм043C043Cм = 67;
      i = bээ044D044Dээ044Dэ044Dэ();
      if ((bм043C043C043C043Cм043C043Cм + b043C043C043C043C043Cм043C043Cм) * bм043C043C043C043Cм043C043Cм % bммммм043C043C043Cм != b043Cмммм043C043C043Cм)
      {
        bм043C043C043C043Cм043C043Cм = 76;
        b043Cмммм043C043C043Cм = bээ044D044Dээ044Dэ044Dэ();
      }
      b043Cмммм043C043C043Cм = i;
    }
    switch (0)
    {
    case 1: 
    default: 
      for (;;)
      {
        switch (1)
        {
        }
      }
    }
    switch (0)
    {
    case 1: 
    default: 
      for (;;)
      {
        switch (0)
        {
        }
      }
    }
    this.b043Cммм043Cм043C043Cм = paramLong;
  }
  
  public int b044Dэ044D044D044Dэ044Dэ044Dэ()
  {
    int i = this.b043Cм043C043C043Cм043C043Cм;
    switch (1)
    {
    case 0: 
    default: 
      for (;;)
      {
        switch (0)
        {
        }
      }
    }
    return i;
  }
  
  public int b044Dэ044Dэ044Dэ044Dэ044Dэ()
  {
    int i = this.b043Cм043Cм043Cм043C043Cм;
    int j = bм043C043C043C043Cм043C043Cм;
    switch (j * (b043C043C043C043C043Cм043C043Cм + j) % bммммм043C043C043Cм)
    {
    default: 
      bм043C043C043C043Cм043C043Cм = 3;
      b043Cмммм043C043C043Cм = bээ044D044Dээ044Dэ044Dэ();
    }
    return i;
  }
  
  /* Error */
  public void b044Dэ044Dээ044D044Dэ044Dэ(int paramInt)
  {
    // Byte code:
    //   0: getstatic 242	kkkkkk/nfnfnn:bм043C043C043C043Cм043C043Cм	I
    //   3: istore_2
    //   4: iload_2
    //   5: getstatic 244	kkkkkk/nfnfnn:b043C043C043C043C043Cм043C043Cм	I
    //   8: iload_2
    //   9: iadd
    //   10: imul
    //   11: getstatic 246	kkkkkk/nfnfnn:bммммм043C043C043Cм	I
    //   14: irem
    //   15: tableswitch	default:+17->32, 0:+29->44
    //   32: invokestatic 263	kkkkkk/nfnfnn:bээ044D044Dээ044Dэ044Dэ	()I
    //   35: putstatic 242	kkkkkk/nfnfnn:bм043C043C043C043Cм043C043Cм	I
    //   38: invokestatic 263	kkkkkk/nfnfnn:bээ044D044Dээ044Dэ044Dэ	()I
    //   41: putstatic 248	kkkkkk/nfnfnn:b043Cмммм043C043C043Cм	I
    //   44: aload_0
    //   45: getfield 63	kkkkkk/nfnfnn:b043Cм043Cм043Cм043C043Cм	I
    //   48: istore_2
    //   49: iload_1
    //   50: iload_2
    //   51: if_icmple +77 -> 128
    //   54: aload_0
    //   55: iload_1
    //   56: putfield 63	kkkkkk/nfnfnn:b043Cм043Cм043Cм043C043Cм	I
    //   59: getstatic 242	kkkkkk/nfnfnn:bм043C043C043C043Cм043C043Cм	I
    //   62: istore_1
    //   63: getstatic 244	kkkkkk/nfnfnn:b043C043C043C043C043Cм043C043Cм	I
    //   66: istore_2
    //   67: getstatic 246	kkkkkk/nfnfnn:bммммм043C043C043Cм	I
    //   70: istore_3
    //   71: iload_1
    //   72: iload_2
    //   73: iload_1
    //   74: iadd
    //   75: imul
    //   76: iload_3
    //   77: irem
    //   78: tableswitch	default:+18->96, 0:+50->128
    //   96: invokestatic 263	kkkkkk/nfnfnn:bээ044D044Dээ044Dэ044Dэ	()I
    //   99: putstatic 242	kkkkkk/nfnfnn:bм043C043C043C043Cм043C043Cм	I
    //   102: bipush 14
    //   104: putstatic 248	kkkkkk/nfnfnn:b043Cмммм043C043C043Cм	I
    //   107: return
    //   108: astore 4
    //   110: aload 4
    //   112: athrow
    //   113: astore 4
    //   115: aload 4
    //   117: athrow
    //   118: astore 4
    //   120: aload 4
    //   122: athrow
    //   123: astore 4
    //   125: aload 4
    //   127: athrow
    //   128: return
    // Local variable table:
    //   start	length	slot	name	signature
    //   0	129	0	this	nfnfnn
    //   0	129	1	paramInt	int
    //   3	72	2	i	int
    //   70	8	3	j	int
    //   108	3	4	localException1	Exception
    //   113	3	4	localException2	Exception
    //   118	3	4	localException3	Exception
    //   123	3	4	localException4	Exception
    // Exception table:
    //   from	to	target	type
    //   44	49	108	java/lang/Exception
    //   96	107	113	java/lang/Exception
    //   110	113	113	java/lang/Exception
    //   120	123	113	java/lang/Exception
    //   54	59	118	java/lang/Exception
    //   59	71	123	java/lang/Exception
  }
  
  public dxdxdd b044Dээ044D044Dэ044Dэ044Dэ()
  {
    if ((bээ044D044Dээ044Dэ044Dэ() + b044D044Dэ044Dээ044Dэ044Dэ()) * bээ044D044Dээ044Dэ044Dэ() % bммммм043C043C043Cм != b043Cмммм043C043C043Cм)
    {
      bм043C043C043C043Cм043C043Cм = 19;
      b043Cмммм043C043C043Cм = bээ044D044Dээ044Dэ044Dэ();
    }
    int i = bм043C043C043C043Cм043C043Cм;
    int j = b043C043C043C043C043Cм043C043Cм;
    switch (0)
    {
    case 1: 
    default: 
      for (;;)
      {
        switch (0)
        {
        }
      }
    }
    if ((i + j) * bм043C043C043C043Cм043C043Cм % bммммм043C043C043Cм != b043Cмммм043C043C043Cм)
    {
      bм043C043C043C043Cм043C043Cм = bээ044D044Dээ044Dэ044Dэ();
      b043Cмммм043C043C043Cм = bээ044D044Dээ044Dэ044Dэ();
    }
    try
    {
      dxdxdd localDxdxdd = this.b043C043Cмм043Cм043C043Cм;
      return localDxdxdd;
    }
    catch (Exception localException)
    {
      throw localException;
    }
  }
  
  public void b044Dээ044Dэ044D044Dэ044Dэ(long paramLong)
  {
    this.b043Cмм043C043Cм043C043Cм = paramLong;
  }
  
  public xddxdd b044Dэээ044Dэ044Dэ044Dэ()
  {
    try
    {
      xddxdd localXddxdd = this.bмммм043Cм043C043Cм;
      if ((bм043C043C043C043Cм043C043Cм + b043C043C043C043C043Cм043C043Cм) * bм043C043C043C043Cм043C043Cм % bммммм043C043C043Cм != b043Cмммм043C043C043Cм)
      {
        bм043C043C043C043Cм043C043Cм = 50;
        b043Cмммм043C043C043Cм = 57;
      }
      return localXddxdd;
    }
    catch (Exception localException)
    {
      throw localException;
    }
  }
  
  /* Error */
  public void b044Dээээ044D044Dэ044Dэ(String paramString)
  {
    // Byte code:
    //   0: getstatic 242	kkkkkk/nfnfnn:bм043C043C043C043Cм043C043Cм	I
    //   3: istore_2
    //   4: getstatic 244	kkkkkk/nfnfnn:b043C043C043C043C043Cм043C043Cм	I
    //   7: istore_3
    //   8: getstatic 242	kkkkkk/nfnfnn:bм043C043C043C043Cм043C043Cм	I
    //   11: istore 4
    //   13: getstatic 246	kkkkkk/nfnfnn:bммммм043C043C043Cм	I
    //   16: istore 5
    //   18: getstatic 248	kkkkkk/nfnfnn:b043Cмммм043C043C043Cм	I
    //   21: istore 6
    //   23: iload_2
    //   24: iload_3
    //   25: iadd
    //   26: iload 4
    //   28: imul
    //   29: iload 5
    //   31: irem
    //   32: iload 6
    //   34: if_icmpeq +47 -> 81
    //   37: bipush 62
    //   39: putstatic 242	kkkkkk/nfnfnn:bм043C043C043C043Cм043C043Cм	I
    //   42: invokestatic 263	kkkkkk/nfnfnn:bээ044D044Dээ044Dэ044Dэ	()I
    //   45: putstatic 248	kkkkkk/nfnfnn:b043Cмммм043C043C043Cм	I
    //   48: getstatic 242	kkkkkk/nfnfnn:bм043C043C043C043Cм043C043Cм	I
    //   51: getstatic 244	kkkkkk/nfnfnn:b043C043C043C043C043Cм043C043Cм	I
    //   54: iadd
    //   55: getstatic 242	kkkkkk/nfnfnn:bм043C043C043C043Cм043C043Cм	I
    //   58: imul
    //   59: getstatic 246	kkkkkk/nfnfnn:bммммм043C043C043Cм	I
    //   62: irem
    //   63: getstatic 248	kkkkkk/nfnfnn:b043Cмммм043C043C043Cм	I
    //   66: if_icmpeq +15 -> 81
    //   69: invokestatic 263	kkkkkk/nfnfnn:bээ044D044Dээ044Dэ044Dэ	()I
    //   72: putstatic 242	kkkkkk/nfnfnn:bм043C043C043C043Cм043C043Cм	I
    //   75: invokestatic 263	kkkkkk/nfnfnn:bээ044D044Dээ044Dэ044Dэ	()I
    //   78: putstatic 248	kkkkkk/nfnfnn:b043Cмммм043C043C043Cм	I
    //   81: aload_0
    //   82: aload_1
    //   83: putfield 121	kkkkkk/nfnfnn:b043C043C043C043Cмм043C043Cм	Ljava/lang/String;
    //   86: return
    //   87: astore_1
    //   88: aload_1
    //   89: athrow
    //   90: astore_1
    //   91: aload_1
    //   92: athrow
    //   93: astore_1
    //   94: aload_1
    //   95: athrow
    // Local variable table:
    //   start	length	slot	name	signature
    //   0	96	0	this	nfnfnn
    //   0	96	1	paramString	String
    //   3	23	2	i	int
    //   7	19	3	j	int
    //   11	18	4	k	int
    //   16	16	5	m	int
    //   21	14	6	n	int
    // Exception table:
    //   from	to	target	type
    //   81	86	87	java/lang/Exception
    //   0	23	90	java/lang/Exception
    //   88	90	90	java/lang/Exception
    //   37	48	93	java/lang/Exception
  }
  
  public boolean bэ044D044D044D044Dэ044Dэ044Dэ()
  {
    boolean bool = false;
    int i = bм043C043C043C043Cм043C043Cм;
    switch (i * (b043C043C043C043C043Cм043C043Cм + i) % bммммм043C043C043Cм)
    {
    default: 
      bм043C043C043C043Cм043C043Cм = 7;
      b043Cмммм043C043C043Cм = bээ044D044Dээ044Dэ044Dэ();
    }
    dxdxdd localDxdxdd1 = this.b043C043Cмм043Cм043C043Cм;
    dxdxdd localDxdxdd2 = dxdxdd.OPEN;
    switch (1)
    {
    case 0: 
    default: 
      for (;;)
      {
        switch (1)
        {
        case 0: 
        default: 
          for (;;)
          {
            switch (1)
            {
            }
          }
        }
        switch (0)
        {
        }
      }
    }
    if (localDxdxdd1 == localDxdxdd2)
    {
      bool = true;
      return bool;
    }
    i = bм043C043C043C043Cм043C043Cм;
    switch (i * (b043C043C043C043C043Cм043C043Cм + i) % bммммм043C043C043Cм)
    {
    }
    bм043C043C043C043Cм043C043Cм = bээ044D044Dээ044Dэ044Dэ();
    b043Cмммм043C043C043Cм = 90;
    return false;
  }
  
  public fffnnf bэ044D044Dэ044Dэ044Dэ044Dэ()
  {
    switch (0)
    {
    case 1: 
    default: 
      for (;;)
      {
        switch (1)
        {
        }
      }
    }
    if ((bм043C043C043C043Cм043C043Cм + b043C043C043C043C043Cм043C043Cм) * bм043C043C043C043Cм043C043Cм % bммммм043C043C043Cм != b043Cмммм043C043C043Cм)
    {
      bм043C043C043C043Cм043C043Cм = bээ044D044Dээ044Dэ044Dэ();
      b043Cмммм043C043C043Cм = bээ044D044Dээ044Dэ044Dэ();
    }
    switch (1)
    {
    case 0: 
    default: 
      for (;;)
      {
        switch (1)
        {
        }
      }
    }
    fffnnf localFffnnf = this.bм043C043Cм043Cм043C043Cм;
    if ((bээ044D044Dээ044Dэ044Dэ() + b043C043C043C043C043Cм043C043Cм) * bээ044D044Dээ044Dэ044Dэ() % bммммм043C043C043Cм != b043Cмммм043C043C043Cм)
    {
      bм043C043C043C043Cм043C043Cм = bээ044D044Dээ044Dэ044Dэ();
      b043Cмммм043C043C043Cм = 68;
    }
    return localFffnnf;
  }
  
  public void bэ044D044Dээ044D044Dэ044Dэ(long paramLong)
  {
    int i = bм043C043C043C043Cм043C043Cм;
    int j = b043C043C043C043C043Cм043C043Cм;
    int k = bммммм043C043C043Cм;
    switch (0)
    {
    case 1: 
    default: 
      for (;;)
      {
        switch (0)
        {
        }
      }
    }
    switch (i * (j + i) % k)
    {
    default: 
      bм043C043C043C043Cм043C043Cм = bээ044D044Dээ044Dэ044Dэ();
      i = bээ044D044Dээ044Dэ044Dэ();
      j = bм043C043C043C043Cм043C043Cм;
      switch (j * (b043C043C043C043C043Cм043C043Cм + j) % bммммм043C043C043Cм)
      {
      default: 
        bм043C043C043C043Cм043C043Cм = bээ044D044Dээ044Dэ044Dэ();
        b043Cмммм043C043C043Cм = 17;
      }
      b043Cмммм043C043C043Cм = i;
    }
    try
    {
      this.b043C043C043Cм043Cм043C043Cм = paramLong;
      return;
    }
    catch (Exception localException)
    {
      throw localException;
    }
  }
  
  /* Error */
  public nfffnf bэ044Dэ044D044Dэ044Dэ044Dэ()
  {
    // Byte code:
    //   0: invokestatic 263	kkkkkk/nfnfnn:bээ044D044Dээ044Dэ044Dэ	()I
    //   3: istore_1
    //   4: getstatic 244	kkkkkk/nfnfnn:b043C043C043C043C043Cм043C043Cм	I
    //   7: istore_2
    //   8: getstatic 246	kkkkkk/nfnfnn:bммммм043C043C043Cм	I
    //   11: istore_3
    //   12: iload_1
    //   13: iload_2
    //   14: iload_1
    //   15: iadd
    //   16: imul
    //   17: iload_3
    //   18: irem
    //   19: tableswitch	default:+17->36, 0:+60->79
    //   36: getstatic 242	kkkkkk/nfnfnn:bм043C043C043C043Cм043C043Cм	I
    //   39: getstatic 244	kkkkkk/nfnfnn:b043C043C043C043C043Cм043C043Cм	I
    //   42: iadd
    //   43: getstatic 242	kkkkkk/nfnfnn:bм043C043C043C043Cм043C043Cм	I
    //   46: imul
    //   47: getstatic 246	kkkkkk/nfnfnn:bммммм043C043C043Cм	I
    //   50: irem
    //   51: getstatic 248	kkkkkk/nfnfnn:b043Cмммм043C043C043Cм	I
    //   54: if_icmpeq +14 -> 68
    //   57: invokestatic 263	kkkkkk/nfnfnn:bээ044D044Dээ044Dэ044Dэ	()I
    //   60: putstatic 242	kkkkkk/nfnfnn:bм043C043C043C043Cм043C043Cм	I
    //   63: bipush 93
    //   65: putstatic 248	kkkkkk/nfnfnn:b043Cмммм043C043C043Cм	I
    //   68: invokestatic 263	kkkkkk/nfnfnn:bээ044D044Dээ044Dэ044Dэ	()I
    //   71: putstatic 242	kkkkkk/nfnfnn:bм043C043C043C043Cм043C043Cм	I
    //   74: bipush 89
    //   76: putstatic 248	kkkkkk/nfnfnn:b043Cмммм043C043C043Cм	I
    //   79: aload_0
    //   80: getfield 188	kkkkkk/nfnfnn:bм043Cм043C043Cм043C043Cм	Lkkkkkk/nfffnf;
    //   83: astore 4
    //   85: iconst_0
    //   86: tableswitch	default:+22->108, 0:+49->135, 1:+-1->85
    //   108: iconst_0
    //   109: tableswitch	default:+23->132, 0:+26->135, 1:+-24->85
    //   132: goto -24 -> 108
    //   135: aload 4
    //   137: areturn
    //   138: astore 4
    //   140: aload 4
    //   142: athrow
    //   143: astore 4
    //   145: aload 4
    //   147: athrow
    // Local variable table:
    //   start	length	slot	name	signature
    //   0	148	0	this	nfnfnn
    //   3	14	1	i	int
    //   7	9	2	j	int
    //   11	8	3	k	int
    //   83	53	4	localNfffnf	nfffnf
    //   138	3	4	localException1	Exception
    //   143	3	4	localException2	Exception
    // Exception table:
    //   from	to	target	type
    //   0	12	138	java/lang/Exception
    //   79	85	138	java/lang/Exception
    //   68	79	143	java/lang/Exception
  }
  
  public void bэ044Dэ044Dэ044D044Dэ044Dэ(dxdxdd paramDxdxdd)
  {
    int i = bм043C043C043C043Cм043C043Cм;
    switch (i * (b043C043C043C043C043Cм043C043Cм + i) % bммммм043C043C043Cм)
    {
    default: 
      bм043C043C043C043Cм043C043Cм = 52;
      b043Cмммм043C043C043Cм = 64;
    }
    try
    {
      this.b043C043Cмм043Cм043C043Cм = paramDxdxdd;
      return;
    }
    catch (Exception paramDxdxdd)
    {
      throw paramDxdxdd;
    }
  }
  
  public long bэ044Dээ044Dэ044Dэ044Dэ()
  {
    try
    {
      long l = this.b043Cммм043Cм043C043Cм;
      return l;
    }
    catch (Exception localException)
    {
      throw localException;
    }
  }
  
  /* Error */
  public void bэ044Dэээ044D044Dэ044Dэ(xddxdd paramXddxdd)
  {
    // Byte code:
    //   0: getstatic 242	kkkkkk/nfnfnn:bм043C043C043C043Cм043C043Cм	I
    //   3: istore_2
    //   4: iload_2
    //   5: getstatic 244	kkkkkk/nfnfnn:b043C043C043C043C043Cм043C043Cм	I
    //   8: iload_2
    //   9: iadd
    //   10: imul
    //   11: getstatic 246	kkkkkk/nfnfnn:bммммм043C043C043Cм	I
    //   14: irem
    //   15: tableswitch	default:+123->138, 0:+30->45
    //   32: invokestatic 263	kkkkkk/nfnfnn:bээ044D044Dээ044Dэ044Dэ	()I
    //   35: istore_2
    //   36: iload_2
    //   37: putstatic 242	kkkkkk/nfnfnn:bм043C043C043C043Cм043C043Cм	I
    //   40: bipush 94
    //   42: putstatic 248	kkkkkk/nfnfnn:b043Cмммм043C043C043Cм	I
    //   45: aload_0
    //   46: aload_1
    //   47: putfield 78	kkkkkk/nfnfnn:bмммм043Cм043C043Cм	Lkkkkkk/xddxdd;
    //   50: getstatic 242	kkkkkk/nfnfnn:bм043C043C043C043Cм043C043Cм	I
    //   53: getstatic 244	kkkkkk/nfnfnn:b043C043C043C043C043Cм043C043Cм	I
    //   56: iadd
    //   57: getstatic 242	kkkkkk/nfnfnn:bм043C043C043C043Cм043C043Cм	I
    //   60: imul
    //   61: getstatic 246	kkkkkk/nfnfnn:bммммм043C043C043Cм	I
    //   64: irem
    //   65: getstatic 248	kkkkkk/nfnfnn:b043Cмммм043C043C043Cм	I
    //   68: if_icmpeq +13 -> 81
    //   71: bipush 95
    //   73: putstatic 242	kkkkkk/nfnfnn:bм043C043C043C043Cм043C043Cм	I
    //   76: bipush 87
    //   78: putstatic 248	kkkkkk/nfnfnn:b043Cмммм043C043C043Cм	I
    //   81: iconst_0
    //   82: tableswitch	default:+22->104, 0:+49->131, 1:+-32->50
    //   104: iconst_1
    //   105: tableswitch	default:+23->128, 0:+-55->50, 1:+26->131
    //   128: goto -24 -> 104
    //   131: return
    //   132: astore_1
    //   133: aload_1
    //   134: athrow
    //   135: astore_1
    //   136: aload_1
    //   137: athrow
    //   138: goto -106 -> 32
    // Local variable table:
    //   start	length	slot	name	signature
    //   0	141	0	this	nfnfnn
    //   0	141	1	paramXddxdd	xddxdd
    //   3	34	2	i	int
    // Exception table:
    //   from	to	target	type
    //   0	32	132	java/lang/Exception
    //   32	36	132	java/lang/Exception
    //   45	50	132	java/lang/Exception
    //   36	45	135	java/lang/Exception
  }
  
  public int bээ044D044D044Dэ044Dэ044Dэ()
  {
    int i = bм043C043C043C043Cм043C043Cм;
    switch (i * (b043C043C043C043C043Cм043C043Cм + i) % bммммм043C043C043Cм)
    {
    default: 
      bм043C043C043C043Cм043C043Cм = bээ044D044Dээ044Dэ044Dэ();
      b043Cмммм043C043C043Cм = bээ044D044Dээ044Dэ044Dэ();
    }
    try
    {
      if ((bм043C043C043C043Cм043C043Cм + b043C043C043C043C043Cм043C043Cм) * bм043C043C043C043Cм043C043Cм % bммммм043C043C043Cм != b043Cмммм043C043C043Cм)
      {
        bм043C043C043C043Cм043C043Cм = 55;
        b043Cмммм043C043C043Cм = 83;
      }
      i = this.bмм043C043C043Cм043C043Cм;
      return i;
    }
    catch (Exception localException)
    {
      throw localException;
    }
  }
  
  public void bээ044D044Dэ044D044Dэ044Dэ(int paramInt)
  {
    this.b043Cм043C043C043Cм043C043Cм = paramInt;
    switch (1)
    {
    case 0: 
    default: 
      for (;;)
      {
        switch (1)
        {
        }
      }
    }
    paramInt = bм043C043C043C043Cм043C043Cм;
    switch (paramInt * (b043C043C043C043C043Cм043C043Cм + paramInt) % bммммм043C043C043Cм)
    {
    default: 
      bм043C043C043C043Cм043C043Cм = bээ044D044Dээ044Dэ044Dэ();
      b043Cмммм043C043C043Cм = 85;
    }
  }
  
  public xdxxdd bээ044Dэ044Dэ044Dэ044Dэ()
  {
    if ((bм043C043C043C043Cм043C043Cм + b044D044Dэ044Dээ044Dэ044Dэ()) * bм043C043C043C043Cм043C043Cм % bммммм043C043C043Cм != b043Cмммм043C043C043Cм)
    {
      bм043C043C043C043Cм043C043Cм = 43;
      int i = bм043C043C043C043Cм043C043Cм;
      switch (i * (b043C043C043C043C043Cм043C043Cм + i) % bммммм043C043C043Cм)
      {
      default: 
        bм043C043C043C043Cм043C043Cм = 49;
        b043Cмммм043C043C043Cм = bээ044D044Dээ044Dэ044Dэ();
      }
      b043Cмммм043C043C043Cм = bээ044D044Dээ044Dэ044Dэ();
    }
    switch (0)
    {
    case 1: 
    default: 
      for (;;)
      {
        switch (0)
        {
        }
      }
    }
    switch (1)
    {
    case 0: 
    default: 
      for (;;)
      {
        switch (1)
        {
        }
      }
    }
    return this.bмм043Cм043Cм043C043Cм;
  }
  
  public void bээ044Dээ044D044Dэ044Dэ(xdxxdd paramXdxxdd)
  {
    String str = b043Cм043C043Cмм043C043Cм;
    StringBuilder localStringBuilder = new StringBuilder();
    switch (1)
    {
    case 0: 
    default: 
      for (;;)
      {
        switch (1)
        {
        }
      }
    }
    xtxtxt.bии0438и04380438и0438ии(str, gguuuu.bккккк043Aкк043A043A("fy\n\013\001\007\001:~\f\f\025\005\023\025\004\030\016\025\025G\035\036\035K!'\037\025jQ", '\023', '\000') + paramXdxxdd);
    int i = bм043C043C043C043Cм043C043Cм;
    switch (i * (b043C043C043C043C043Cм043C043Cм + i) % bммммм043C043C043Cм)
    {
    default: 
      bм043C043C043C043Cм043C043Cм = 47;
      b043Cмммм043C043C043Cм = bээ044D044Dээ044Dэ044Dэ();
      if ((bм043C043C043C043Cм043C043Cм + b043C043C043C043C043Cм043C043Cм) * bм043C043C043C043Cм043C043Cм % bэ044D044D044Dээ044Dэ044Dэ() != b043Cмммм043C043C043Cм)
      {
        bм043C043C043C043Cм043C043Cм = 87;
        b043Cмммм043C043C043Cм = bээ044D044Dээ044Dэ044Dэ();
      }
      break;
    }
    this.bмм043Cм043Cм043C043Cм = paramXdxxdd;
  }
  
  public long bэээ044D044Dэ044Dэ044Dэ()
  {
    throw new Runtime("d2j fail translate: java.lang.IndexOutOfBoundsException: fromIndex < 0: -1\n\tat java.util.BitSet.nextSetBit(BitSet.java:712)\n\tat com.googlecode.dex2jar.ir.ts.array.FillArrayTransformer.makeSureAllElementAreAssigned(FillArrayTransformer.java:505)\n\tat com.googlecode.dex2jar.ir.ts.array.FillArrayTransformer.transformReportChanged(FillArrayTransformer.java:123)\n\tat com.googlecode.dex2jar.ir.ts.StatedTransformer.transform(StatedTransformer.java:10)\n\tat com.googlecode.d2j.dex.Dex2jar$2.optimize(Dex2jar.java:149)\n\tat com.googlecode.d2j.dex.Dex2Asm.convertCode(Dex2Asm.java:414)\n\tat com.googlecode.d2j.dex.ExDex2Asm.convertCode(ExDex2Asm.java:42)\n\tat com.googlecode.d2j.dex.Dex2jar$2.convertCode(Dex2jar.java:128)\n\tat com.googlecode.d2j.dex.Dex2Asm.convertMethod(Dex2Asm.java:509)\n\tat com.googlecode.d2j.dex.Dex2Asm.convertClass(Dex2Asm.java:406)\n\tat com.googlecode.d2j.dex.Dex2Asm.convertDex(Dex2Asm.java:422)\n\tat com.googlecode.d2j.dex.Dex2jar.doTranslate(Dex2jar.java:172)\n\tat com.googlecode.d2j.dex.Dex2jar.to(Dex2jar.java:272)\n\tat com.googlecode.dex2jar.tools.Dex2jarCmd.doCommandLine(Dex2jarCmd.java:108)\n\tat com.googlecode.dex2jar.tools.BaseCmd.doMain(BaseCmd.java:288)\n\tat com.googlecode.dex2jar.tools.Dex2jarCmd.main(Dex2jarCmd.java:32)\n");
  }
  
  public void bэээ044Dэ044D044Dэ044Dэ(xxxddd.dddxdd paramDddxdd)
  {
    switch (1)
    {
    case 0: 
    default: 
      for (;;)
      {
        switch (1)
        {
        }
      }
    }
    xtxtxt.bии0438и04380438и0438ии(b043Cм043C043Cмм043C043Cм, gguuuu.bккккк043Aкк043A043A("whvThnub`>M:L1", '¨', '\002') + paramDddxdd);
    this.bммм043C043Cм043C043Cм = paramDddxdd;
  }
  
  /* Error */
  public String bээээ044Dэ044Dэ044Dэ()
  {
    // Byte code:
    //   0: invokestatic 263	kkkkkk/nfnfnn:bээ044D044Dээ044Dэ044Dэ	()I
    //   3: istore_1
    //   4: getstatic 244	kkkkkk/nfnfnn:b043C043C043C043C043Cм043C043Cм	I
    //   7: istore_2
    //   8: getstatic 246	kkkkkk/nfnfnn:bммммм043C043C043Cм	I
    //   11: istore_3
    //   12: iload_1
    //   13: iload_2
    //   14: iload_1
    //   15: iadd
    //   16: imul
    //   17: iload_3
    //   18: irem
    //   19: tableswitch	default:+17->36, 0:+28->47
    //   36: invokestatic 263	kkkkkk/nfnfnn:bээ044D044Dээ044Dэ044Dэ	()I
    //   39: putstatic 242	kkkkkk/nfnfnn:bм043C043C043C043Cм043C043Cм	I
    //   42: bipush 12
    //   44: putstatic 248	kkkkkk/nfnfnn:b043Cмммм043C043C043Cм	I
    //   47: aload_0
    //   48: getfield 121	kkkkkk/nfnfnn:b043C043C043C043Cмм043C043Cм	Ljava/lang/String;
    //   51: astore 4
    //   53: invokestatic 263	kkkkkk/nfnfnn:bээ044D044Dээ044Dэ044Dэ	()I
    //   56: istore_1
    //   57: iload_1
    //   58: getstatic 244	kkkkkk/nfnfnn:b043C043C043C043C043Cм043C043Cм	I
    //   61: iload_1
    //   62: iadd
    //   63: imul
    //   64: getstatic 246	kkkkkk/nfnfnn:bммммм043C043C043Cм	I
    //   67: irem
    //   68: tableswitch	default:+20->88, 0:+31->99
    //   88: bipush 88
    //   90: putstatic 242	kkkkkk/nfnfnn:bм043C043C043C043Cм043C043Cм	I
    //   93: invokestatic 263	kkkkkk/nfnfnn:bээ044D044Dээ044Dэ044Dэ	()I
    //   96: putstatic 248	kkkkkk/nfnfnn:b043Cмммм043C043C043Cм	I
    //   99: aload 4
    //   101: areturn
    //   102: astore 4
    //   104: aload 4
    //   106: athrow
    //   107: astore 4
    //   109: aload 4
    //   111: athrow
    // Local variable table:
    //   start	length	slot	name	signature
    //   0	112	0	this	nfnfnn
    //   3	61	1	i	int
    //   7	9	2	j	int
    //   11	8	3	k	int
    //   51	49	4	str	String
    //   102	3	4	localException1	Exception
    //   107	3	4	localException2	Exception
    // Exception table:
    //   from	to	target	type
    //   0	12	102	java/lang/Exception
    //   47	53	102	java/lang/Exception
    //   36	47	107	java/lang/Exception
  }
  
  public void bэээээ044D044Dэ044Dэ(String paramString)
  {
    this.bм043C043C043Cмм043C043Cм = paramString;
  }
}
