package kkkkkk;

import android.content.Context;
import android.content.res.AssetManager;
import java.io.IOException;
import java.io.InputStream;
import java.util.Map;
import java.util.TreeMap;

public class nknnkk
{
  private static Map<String, Integer> b041E041E041E041EО041EОО041E;
  public static int b041E041EОО041E041EОО041E = 2;
  private static String b041EО041E041EО041EОО041E;
  public static int b041EООО041E041EОО041E = 1;
  private static String bО041E041E041EО041EОО041E;
  public static int bО041EОО041E041EОО041E = 38;
  private static Context bОО041E041EО041EОО041E;
  public static int bОООО041E041EОО041E;
  
  /* Error */
  static
  {
    // Byte code:
    //   0: invokestatic 27	kkkkkk/nknnkk:bхх044504450445х0445ххх	()V
    //   3: getstatic 29	kkkkkk/nknnkk:bО041EОО041E041EОО041E	I
    //   6: getstatic 31	kkkkkk/nknnkk:b041EООО041E041EОО041E	I
    //   9: iadd
    //   10: getstatic 29	kkkkkk/nknnkk:bО041EОО041E041EОО041E	I
    //   13: imul
    //   14: getstatic 33	kkkkkk/nknnkk:b041E041EОО041E041EОО041E	I
    //   17: irem
    //   18: getstatic 35	kkkkkk/nknnkk:bОООО041E041EОО041E	I
    //   21: if_icmpeq +50 -> 71
    //   24: invokestatic 39	kkkkkk/nknnkk:bххх04450445х0445ххх	()I
    //   27: istore_0
    //   28: getstatic 29	kkkkkk/nknnkk:bО041EОО041E041EОО041E	I
    //   31: getstatic 31	kkkkkk/nknnkk:b041EООО041E041EОО041E	I
    //   34: iadd
    //   35: getstatic 29	kkkkkk/nknnkk:bО041EОО041E041EОО041E	I
    //   38: imul
    //   39: getstatic 33	kkkkkk/nknnkk:b041E041EОО041E041EОО041E	I
    //   42: irem
    //   43: getstatic 35	kkkkkk/nknnkk:bОООО041E041EОО041E	I
    //   46: if_icmpeq +15 -> 61
    //   49: invokestatic 39	kkkkkk/nknnkk:bххх04450445х0445ххх	()I
    //   52: putstatic 29	kkkkkk/nknnkk:bО041EОО041E041EОО041E	I
    //   55: invokestatic 39	kkkkkk/nknnkk:bххх04450445х0445ххх	()I
    //   58: putstatic 35	kkkkkk/nknnkk:bОООО041E041EОО041E	I
    //   61: iload_0
    //   62: putstatic 29	kkkkkk/nknnkk:bО041EОО041E041EОО041E	I
    //   65: invokestatic 39	kkkkkk/nknnkk:bххх04450445х0445ххх	()I
    //   68: putstatic 35	kkkkkk/nknnkk:bОООО041E041EОО041E	I
    //   71: invokestatic 42	kkkkkk/nknnkk:b0445х044504450445х0445ххх	()V
    //   74: invokestatic 45	kkkkkk/nknnkk:bх0445044504450445х0445ххх	()V
    //   77: iconst_0
    //   78: tableswitch	default:+22->100, 0:+49->127, 1:+-1->77
    //   100: iconst_1
    //   101: tableswitch	default:+23->124, 0:+-24->77, 1:+26->127
    //   124: goto -24 -> 100
    //   127: return
    //   128: astore_1
    //   129: aload_1
    //   130: athrow
    //   131: astore_1
    //   132: aload_1
    //   133: athrow
    // Local variable table:
    //   start	length	slot	name	signature
    //   27	35	0	i	int
    //   128	2	1	localException1	Exception
    //   131	2	1	localException2	Exception
    // Exception table:
    //   from	to	target	type
    //   0	3	128	java/lang/Exception
    //   61	71	128	java/lang/Exception
    //   71	77	128	java/lang/Exception
    //   3	28	131	java/lang/Exception
  }
  
  public nknnkk() {}
  
  public static InputStream b04450445044504450445х0445ххх(AssetManager paramAssetManager, String paramString)
    throws IOException
  {
    InputStream localInputStream = paramAssetManager.open(paramString);
    Map localMap = b041E041E041E041EО041EОО041E;
    int i = bО041EОО041E041EОО041E;
    switch (i * (b041EООО041E041EОО041E + i) % b041E041EОО041E041EОО041E)
    {
    default: 
      bО041EОО041E041EОО041E = 82;
      bОООО041E041EОО041E = bххх04450445х0445ххх();
    }
    paramAssetManager = localInputStream;
    if (localMap.containsKey(paramString)) {
      paramAssetManager = knnnkk.b0445х0445хх04450445ххх(localInputStream, b041EО041E041EО041EОО041E.getBytes(), bО041E041E041EО041EОО041E.getBytes());
    }
    return paramAssetManager;
  }
  
  public static int b044504450445х0445х0445ххх()
  {
    return 1;
  }
  
  private static void b04450445х04450445х0445ххх() {}
  
  private static void b0445х044504450445х0445ххх()
  {
    b041EО041E041EО041EОО041E = gguuuu.bккккк043Aкк043A043A("\016\nM\021\013ALIJ\022[\\E\025X\036", '+', '\004');
  }
  
  public static int b0445хх04450445х0445ххх()
  {
    return 0;
  }
  
  /* Error */
  public static android.content.res.AssetFileDescriptor b0445хххх04450445ххх(AssetManager paramAssetManager, String paramString)
    throws IOException
  {
    // Byte code:
    //   0: aload_0
    //   1: aload_1
    //   2: invokevirtual 101	android/content/res/AssetManager:openFd	(Ljava/lang/String;)Landroid/content/res/AssetFileDescriptor;
    //   5: astore_0
    //   6: getstatic 61	kkkkkk/nknnkk:b041E041E041E041EО041EОО041E	Ljava/util/Map;
    //   9: aload_1
    //   10: invokeinterface 67 2 0
    //   15: ifeq +133 -> 148
    //   18: new 103	kkkkkk/kknnkk
    //   21: dup
    //   22: aload_0
    //   23: getstatic 105	kkkkkk/nknnkk:bОО041E041EО041EОО041E	Landroid/content/Context;
    //   26: invokespecial 108	kkkkkk/kknnkk:<init>	(Landroid/content/res/AssetFileDescriptor;Landroid/content/Context;)V
    //   29: astore_0
    //   30: getstatic 29	kkkkkk/nknnkk:bО041EОО041E041EОО041E	I
    //   33: getstatic 31	kkkkkk/nknnkk:b041EООО041E041EОО041E	I
    //   36: iadd
    //   37: getstatic 29	kkkkkk/nknnkk:bО041EОО041E041EОО041E	I
    //   40: imul
    //   41: invokestatic 111	kkkkkk/nknnkk:bх0445х04450445х0445ххх	()I
    //   44: irem
    //   45: invokestatic 113	kkkkkk/nknnkk:b0445хх04450445х0445ххх	()I
    //   48: if_icmpeq +14 -> 62
    //   51: invokestatic 39	kkkkkk/nknnkk:bххх04450445х0445ххх	()I
    //   54: putstatic 29	kkkkkk/nknnkk:bО041EОО041E041EОО041E	I
    //   57: bipush 52
    //   59: putstatic 35	kkkkkk/nknnkk:bОООО041E041EОО041E	I
    //   62: getstatic 69	kkkkkk/nknnkk:b041EО041E041EО041EОО041E	Ljava/lang/String;
    //   65: invokevirtual 75	java/lang/String:getBytes	()[B
    //   68: astore_1
    //   69: getstatic 77	kkkkkk/nknnkk:bО041E041E041EО041EОО041E	Ljava/lang/String;
    //   72: astore 7
    //   74: aload 7
    //   76: invokevirtual 75	java/lang/String:getBytes	()[B
    //   79: astore 7
    //   81: getstatic 29	kkkkkk/nknnkk:bО041EОО041E041EОО041E	I
    //   84: istore_2
    //   85: getstatic 31	kkkkkk/nknnkk:b041EООО041E041EОО041E	I
    //   88: istore_3
    //   89: getstatic 29	kkkkkk/nknnkk:bО041EОО041E041EОО041E	I
    //   92: istore 4
    //   94: getstatic 33	kkkkkk/nknnkk:b041E041EОО041E041EОО041E	I
    //   97: istore 5
    //   99: getstatic 35	kkkkkk/nknnkk:bОООО041E041EОО041E	I
    //   102: istore 6
    //   104: iload_2
    //   105: iload_3
    //   106: iadd
    //   107: iload 4
    //   109: imul
    //   110: iload 5
    //   112: irem
    //   113: iload 6
    //   115: if_icmpeq +15 -> 130
    //   118: invokestatic 39	kkkkkk/nknnkk:bххх04450445х0445ххх	()I
    //   121: putstatic 29	kkkkkk/nknnkk:bО041EОО041E041EОО041E	I
    //   124: invokestatic 39	kkkkkk/nknnkk:bххх04450445х0445ххх	()I
    //   127: putstatic 35	kkkkkk/nknnkk:bОООО041E041EОО041E	I
    //   130: aload_0
    //   131: aload_1
    //   132: aload 7
    //   134: invokevirtual 117	kkkkkk/kknnkk:bх04450445х0445х0445ххх	([B[B)V
    //   137: aload_0
    //   138: areturn
    //   139: astore_0
    //   140: aload_0
    //   141: athrow
    //   142: astore_0
    //   143: aload_0
    //   144: athrow
    //   145: astore_0
    //   146: aload_0
    //   147: athrow
    //   148: aload_0
    //   149: areturn
    //   150: astore_0
    //   151: aload_0
    //   152: athrow
    // Local variable table:
    //   start	length	slot	name	signature
    //   0	153	0	paramAssetManager	AssetManager
    //   0	153	1	paramString	String
    //   84	23	2	i	int
    //   88	19	3	j	int
    //   92	18	4	k	int
    //   97	16	5	m	int
    //   102	14	6	n	int
    //   72	61	7	localObject	Object
    // Exception table:
    //   from	to	target	type
    //   0	30	139	java/lang/Exception
    //   62	74	139	java/lang/Exception
    //   81	104	142	java/lang/Exception
    //   140	142	142	java/lang/Exception
    //   146	148	142	java/lang/Exception
    //   74	81	145	java/lang/Exception
    //   130	137	145	java/lang/Exception
    //   118	130	150	java/lang/Exception
  }
  
  private static void bх0445044504450445х0445ххх()
  {
    bО041E041E041EО041EОО041E = gguuuu.bккккк043Aкк043A043A("9vz|A~r\003o\003{w~\tz", '', '\000');
  }
  
  public static int bх0445х04450445х0445ххх()
  {
    return 2;
  }
  
  public static void bх0445ххх04450445ххх(Context paramContext)
  {
    int i = bО041EОО041E041EОО041E;
    switch (i * (b041EООО041E041EОО041E + i) % b041E041EОО041E041EОО041E)
    {
    default: 
      bО041EОО041E041EОО041E = bххх04450445х0445ххх();
      bОООО041E041EОО041E = bххх04450445х0445ххх();
    }
    try
    {
      bОО041E041EО041EОО041E = paramContext;
      if ((bххх04450445х0445ххх() + b041EООО041E041EОО041E) * bххх04450445х0445ххх() % bх0445х04450445х0445ххх() != bОООО041E041EОО041E)
      {
        switch (1)
        {
        case 0: 
        default: 
          for (;;)
          {
            switch (0)
            {
            }
          }
        }
        bОООО041E041EОО041E = 8;
      }
      return;
    }
    catch (Exception paramContext)
    {
      throw paramContext;
    }
  }
  
  private static void bхх044504450445х0445ххх()
  {
    TreeMap localTreeMap = new TreeMap();
    localTreeMap.put(gguuuu.bккккк043Aкк043A043A("OMRU96673:17//--++'J8M", '¹', '\003'), Integer.valueOf(0));
    localTreeMap.put(gguuuu.bккккк043Aкк043A043A("[[bgMLNROYSSSUUWWYW|l\004", 'Ê', '\004'), Integer.valueOf(1));
    localTreeMap.put(gguuuu.bккккк043Aкк043A043A("<<CH.-/3122446688:8TYT", 'ö', '\000'), Integer.valueOf(2));
    localTreeMap.put(gguuuu.bккккк043Aкк043A043A("/2+\023\031\0170-%", '\032', '\005'), Integer.valueOf(3));
    localTreeMap.put(gguuuu.bккккк043Aкк043A043A("$)$\020\027\020\027\024\023\025\031\024WVP", 'Z', '\000'), Integer.valueOf(4));
    localTreeMap.put(gguuuu.bк043Aккк043Aкк043A043A("1;8@7\004\r\004GF@", 'Ð', '|', '\003'), Integer.valueOf(5));
    localTreeMap.put(gguuuu.bк043Aккк043Aкк043A043A("EI@H\005\007\b\003\fM", '<', '\030', '\000'), Integer.valueOf(6));
    localTreeMap.put(gguuuu.bк043Aккк043Aкк043A043A("AG@J\t\016\f\027Z", 'Ì', '\n', '\003'), Integer.valueOf(7));
    localTreeMap.put(gguuuu.bккккк043Aкк043A043A("ce\\c%%!)!\036\036 \031ZWO", 'D', '\003'), Integer.valueOf(8));
    localTreeMap.put(gguuuu.bк043Aккк043Aкк043A043A(";50\003\001\001\004\003\005\t\004'& ", '=', 'ñ', '\001'), Integer.valueOf(9));
    localTreeMap.put(gguuuu.bк043Aккк043Aкк043A043A("'#\034\016\036\037\033\017\t\f\027\025\f\016\013P\f\024\017\r", 'v', '§', '\000'), Integer.valueOf(10));
    b041E041E041E041EО041EОО041E = localTreeMap;
  }
  
  public static int bххх04450445х0445ххх()
  {
    return 78;
  }
  
  /* Error */
  public static InputStream bххххх04450445ххх(AssetManager paramAssetManager, String paramString, int paramInt)
    throws IOException
  {
    // Byte code:
    //   0: aload_0
    //   1: aload_1
    //   2: iload_2
    //   3: invokevirtual 165	android/content/res/AssetManager:open	(Ljava/lang/String;I)Ljava/io/InputStream;
    //   6: astore 8
    //   8: getstatic 61	kkkkkk/nknnkk:b041E041E041E041EО041EОО041E	Ljava/util/Map;
    //   11: aload_1
    //   12: invokeinterface 67 2 0
    //   17: istore 7
    //   19: aload 8
    //   21: astore_0
    //   22: iload 7
    //   24: ifeq +107 -> 131
    //   27: getstatic 29	kkkkkk/nknnkk:bО041EОО041E041EОО041E	I
    //   30: istore_2
    //   31: invokestatic 167	kkkkkk/nknnkk:b044504450445х0445х0445ххх	()I
    //   34: istore_3
    //   35: getstatic 29	kkkkkk/nknnkk:bО041EОО041E041EОО041E	I
    //   38: istore 4
    //   40: getstatic 33	kkkkkk/nknnkk:b041E041EОО041E041EОО041E	I
    //   43: istore 5
    //   45: getstatic 35	kkkkkk/nknnkk:bОООО041E041EОО041E	I
    //   48: istore 6
    //   50: iload_2
    //   51: iload_3
    //   52: iadd
    //   53: iload 4
    //   55: imul
    //   56: iload 5
    //   58: irem
    //   59: iload 6
    //   61: if_icmpeq +46 -> 107
    //   64: getstatic 29	kkkkkk/nknnkk:bО041EОО041E041EОО041E	I
    //   67: getstatic 31	kkkkkk/nknnkk:b041EООО041E041EОО041E	I
    //   70: iadd
    //   71: getstatic 29	kkkkkk/nknnkk:bО041EОО041E041EОО041E	I
    //   74: imul
    //   75: getstatic 33	kkkkkk/nknnkk:b041E041EОО041E041EОО041E	I
    //   78: irem
    //   79: getstatic 35	kkkkkk/nknnkk:bОООО041E041EОО041E	I
    //   82: if_icmpeq +13 -> 95
    //   85: bipush 29
    //   87: putstatic 29	kkkkkk/nknnkk:bО041EОО041E041EОО041E	I
    //   90: bipush 77
    //   92: putstatic 35	kkkkkk/nknnkk:bОООО041E041EОО041E	I
    //   95: invokestatic 39	kkkkkk/nknnkk:bххх04450445х0445ххх	()I
    //   98: putstatic 29	kkkkkk/nknnkk:bО041EОО041E041EОО041E	I
    //   101: invokestatic 39	kkkkkk/nknnkk:bххх04450445х0445ххх	()I
    //   104: putstatic 35	kkkkkk/nknnkk:bОООО041E041EОО041E	I
    //   107: getstatic 69	kkkkkk/nknnkk:b041EО041E041EО041EОО041E	Ljava/lang/String;
    //   110: astore_0
    //   111: aload_0
    //   112: invokevirtual 75	java/lang/String:getBytes	()[B
    //   115: astore_0
    //   116: getstatic 77	kkkkkk/nknnkk:bО041E041E041EО041EОО041E	Ljava/lang/String;
    //   119: invokevirtual 75	java/lang/String:getBytes	()[B
    //   122: astore_1
    //   123: aload 8
    //   125: aload_0
    //   126: aload_1
    //   127: invokestatic 83	kkkkkk/knnnkk:b0445х0445хх04450445ххх	(Ljava/io/InputStream;[B[B)Ljava/io/InputStream;
    //   130: astore_0
    //   131: aload_0
    //   132: areturn
    //   133: astore_0
    //   134: aload_0
    //   135: athrow
    //   136: astore_0
    //   137: aload_0
    //   138: athrow
    //   139: astore_0
    //   140: aload_0
    //   141: athrow
    //   142: astore_0
    //   143: aload_0
    //   144: athrow
    // Local variable table:
    //   start	length	slot	name	signature
    //   0	145	0	paramAssetManager	AssetManager
    //   0	145	1	paramString	String
    //   0	145	2	paramInt	int
    //   34	19	3	i	int
    //   38	18	4	j	int
    //   43	16	5	k	int
    //   48	14	6	m	int
    //   17	6	7	bool	boolean
    //   6	118	8	localInputStream	InputStream
    // Exception table:
    //   from	to	target	type
    //   0	19	133	java/lang/Exception
    //   107	111	133	java/lang/Exception
    //   123	131	133	java/lang/Exception
    //   95	107	136	java/lang/Exception
    //   134	136	136	java/lang/Exception
    //   140	142	136	java/lang/Exception
    //   111	123	139	java/lang/Exception
    //   27	50	142	java/lang/Exception
  }
}
