package kkkkkk;

import java.io.InputStream;
import javax.crypto.Cipher;
import javax.crypto.CipherInputStream;

public class nnnnkk
  extends CipherInputStream
{
  public static int b041E041EО041E041E041EОО041E = 2;
  public static int b041EОО041E041E041EОО041E = 0;
  public static int bО041EО041E041E041EОО041E = 1;
  public static int bООО041E041E041EОО041E = 90;
  
  public nnnnkk(InputStream paramInputStream, Cipher paramCipher)
  {
    super(paramInputStream, paramCipher);
  }
  
  public static int bх04450445хх04450445ххх()
  {
    return 33;
  }
  
  /* Error */
  public int available()
    throws java.io.IOException
  {
    // Byte code:
    //   0: getstatic 27	kkkkkk/nnnnkk:bООО041E041E041EОО041E	I
    //   3: istore_1
    //   4: iload_1
    //   5: getstatic 29	kkkkkk/nnnnkk:bО041EО041E041E041EОО041E	I
    //   8: iload_1
    //   9: iadd
    //   10: imul
    //   11: getstatic 31	kkkkkk/nnnnkk:b041E041EО041E041E041EОО041E	I
    //   14: irem
    //   15: tableswitch	default:+17->32, 0:+28->43
    //   32: bipush 31
    //   34: putstatic 27	kkkkkk/nnnnkk:bООО041E041E041EОО041E	I
    //   37: invokestatic 33	kkkkkk/nnnnkk:bх04450445хх04450445ххх	()I
    //   40: putstatic 35	kkkkkk/nnnnkk:b041EОО041E041E041EОО041E	I
    //   43: getstatic 27	kkkkkk/nnnnkk:bООО041E041E041EОО041E	I
    //   46: istore_1
    //   47: getstatic 29	kkkkkk/nnnnkk:bО041EО041E041E041EОО041E	I
    //   50: istore_2
    //   51: getstatic 27	kkkkkk/nnnnkk:bООО041E041E041EОО041E	I
    //   54: istore_3
    //   55: getstatic 31	kkkkkk/nnnnkk:b041E041EО041E041E041EОО041E	I
    //   58: istore 4
    //   60: getstatic 35	kkkkkk/nnnnkk:b041EОО041E041E041EОО041E	I
    //   63: istore 5
    //   65: iload_1
    //   66: iload_2
    //   67: iadd
    //   68: iload_3
    //   69: imul
    //   70: iload 4
    //   72: irem
    //   73: iload 5
    //   75: if_icmpeq +13 -> 88
    //   78: bipush 77
    //   80: putstatic 27	kkkkkk/nnnnkk:bООО041E041E041EОО041E	I
    //   83: bipush 78
    //   85: putstatic 35	kkkkkk/nnnnkk:b041EОО041E041E041EОО041E	I
    //   88: aload_0
    //   89: getfield 39	kkkkkk/nnnnkk:in	Ljava/io/InputStream;
    //   92: astore 6
    //   94: aload 6
    //   96: invokevirtual 43	java/io/InputStream:available	()I
    //   99: istore_1
    //   100: iload_1
    //   101: ireturn
    //   102: astore 6
    //   104: aload 6
    //   106: athrow
    //   107: astore 6
    //   109: aload 6
    //   111: athrow
    //   112: astore 6
    //   114: aload 6
    //   116: athrow
    //   117: astore 6
    //   119: aload 6
    //   121: athrow
    // Local variable table:
    //   start	length	slot	name	signature
    //   0	122	0	this	nnnnkk
    //   3	98	1	i	int
    //   50	18	2	j	int
    //   54	16	3	k	int
    //   58	15	4	m	int
    //   63	13	5	n	int
    //   92	3	6	localInputStream	InputStream
    //   102	3	6	localException1	Exception
    //   107	3	6	localException2	Exception
    //   112	3	6	localException3	Exception
    //   117	3	6	localException4	Exception
    // Exception table:
    //   from	to	target	type
    //   94	100	102	java/lang/Exception
    //   78	88	107	java/lang/Exception
    //   104	107	107	java/lang/Exception
    //   114	117	107	java/lang/Exception
    //   88	94	112	java/lang/Exception
    //   43	65	117	java/lang/Exception
  }
}
