package kkkkkk;

public class ooooov
  implements voovvo
{
  public static int b044904490449щ044904490449щщ = 19;
  public static int b0449щщ0449044904490449щщ = 1;
  public static int bщ0449щ0449044904490449щщ = 2;
  public static int bщщщ0449044904490449щщ;
  private hhhbhb b0449щ0449щ044904490449щщ;
  private final ovovvo bщ04490449щ044904490449щщ;
  private final String bщщ0449щ044904490449щщ;
  
  public ooooov(String paramString, ovovvo paramOvovvo)
  {
    this.bщщ0449щ044904490449щщ = paramString;
    this.bщ04490449щ044904490449щщ = paramOvovvo;
    this.b0449щ0449щ044904490449щщ = new hhhbhb(paramString);
  }
  
  public static int b042804280428ШШ042804280428ШШ()
  {
    return 4;
  }
  
  public static int b0428Ш0428ШШ042804280428ШШ()
  {
    return 2;
  }
  
  public static int bШ04280428ШШ042804280428ШШ()
  {
    return 1;
  }
  
  private boolean bШ0428Ш0428Ш042804280428ШШ()
  {
    boolean bool = false;
    if (!this.b0449щ0449щ044904490449щщ.isAlive())
    {
      String str1 = this.bщщ0449щ044904490449щщ;
      switch (1)
      {
      case 0: 
      default: 
        for (;;)
        {
          switch (0)
          {
          case 1: 
          default: 
            for (;;)
            {
              switch (1)
              {
              }
            }
          }
          switch (0)
          {
          }
        }
      }
      String str2 = gguuuu.bккккк043Aкк043A043A("6VBTD}*=>BBF<u\031=FB2D26\036A0?.g09d((#%m", 'N', '\003');
      if ((b044904490449щ044904490449щщ + b0449щщ0449044904490449щщ) * b044904490449щ044904490449щщ % bщ0449щ0449044904490449щщ != bщщщ0449044904490449щщ)
      {
        if ((b044904490449щ044904490449щщ + b0449щщ0449044904490449щщ) * b044904490449щ044904490449щщ % bщ0449щ0449044904490449щщ != bщщщ0449044904490449щщ)
        {
          b044904490449щ044904490449щщ = b042804280428ШШ042804280428ШШ();
          bщщщ0449044904490449щщ = 60;
        }
        b044904490449щ044904490449щщ = 90;
        bщщщ0449044904490449щщ = 81;
      }
      xtxtxt.bии0438043804380438и0438ии(str1, str2);
      bool = true;
    }
    return bool;
  }
  
  public void b04280428Ш0428Ш042804280428ШШ(ovvvvo paramOvvvvo)
  {
    throw new Runtime("d2j fail translate: java.lang.IndexOutOfBoundsException: fromIndex < 0: -1\n\tat java.util.BitSet.nextSetBit(BitSet.java:712)\n\tat com.googlecode.dex2jar.ir.ts.array.FillArrayTransformer.makeSureAllElementAreAssigned(FillArrayTransformer.java:505)\n\tat com.googlecode.dex2jar.ir.ts.array.FillArrayTransformer.transformReportChanged(FillArrayTransformer.java:123)\n\tat com.googlecode.dex2jar.ir.ts.StatedTransformer.transform(StatedTransformer.java:10)\n\tat com.googlecode.d2j.dex.Dex2jar$2.optimize(Dex2jar.java:149)\n\tat com.googlecode.d2j.dex.Dex2Asm.convertCode(Dex2Asm.java:414)\n\tat com.googlecode.d2j.dex.ExDex2Asm.convertCode(ExDex2Asm.java:42)\n\tat com.googlecode.d2j.dex.Dex2jar$2.convertCode(Dex2jar.java:128)\n\tat com.googlecode.d2j.dex.Dex2Asm.convertMethod(Dex2Asm.java:509)\n\tat com.googlecode.d2j.dex.Dex2Asm.convertClass(Dex2Asm.java:406)\n\tat com.googlecode.d2j.dex.Dex2Asm.convertDex(Dex2Asm.java:422)\n\tat com.googlecode.d2j.dex.Dex2jar.doTranslate(Dex2jar.java:172)\n\tat com.googlecode.d2j.dex.Dex2jar.to(Dex2jar.java:272)\n\tat com.googlecode.dex2jar.tools.Dex2jarCmd.doCommandLine(Dex2jarCmd.java:108)\n\tat com.googlecode.dex2jar.tools.BaseCmd.doMain(BaseCmd.java:288)\n\tat com.googlecode.dex2jar.tools.Dex2jarCmd.main(Dex2jarCmd.java:32)\n");
  }
  
  public void b0428Ш04280428Ш042804280428ШШ()
  {
    try
    {
      int i = b044904490449щ044904490449щщ;
      int j = b0449щщ0449044904490449щщ;
      int k = b044904490449щ044904490449щщ;
      int m = bщ0449щ0449044904490449щщ;
      int n = bщщщ0449044904490449щщ;
      if ((i + j) * k % m != n)
      {
        if ((b044904490449щ044904490449щщ + bШ04280428ШШ042804280428ШШ()) * b044904490449щ044904490449щщ % bщ0449щ0449044904490449щщ != bщщщ0449044904490449щщ)
        {
          b044904490449щ044904490449щщ = b042804280428ШШ042804280428ШШ();
          bщщщ0449044904490449щщ = b042804280428ШШ042804280428ШШ();
        }
        b044904490449щ044904490449щщ = 63;
        bщщщ0449044904490449щщ = b042804280428ШШ042804280428ШШ();
      }
      this.b0449щ0449щ044904490449щщ.b044504450445х0445хх044504450445();
      switch (1)
      {
      case 0: 
      default: 
        for (;;)
        {
          switch (0)
          {
          }
        }
      }
      return;
    }
    catch (Exception localException)
    {
      throw localException;
    }
  }
  
  public boolean b0428ШШ0428Ш042804280428ШШ()
  {
    try
    {
      if (!bШ0428Ш0428Ш042804280428ШШ())
      {
        break label111;
        int i = b044904490449щ044904490449щщ;
        int j = b0449щщ0449044904490449щщ;
        int k = b044904490449щ044904490449щщ;
        int m = bщ0449щ0449044904490449щщ;
        int n = bщщщ0449044904490449щщ;
        if ((i + j) * k % m != n)
        {
          i = b044904490449щ044904490449щщ;
          switch (i * (b0449щщ0449044904490449щщ + i) % bщ0449щ0449044904490449щщ)
          {
          default: 
            b044904490449щ044904490449щщ = b042804280428ШШ042804280428ШШ();
            bщщщ0449044904490449щщ = b042804280428ШШ042804280428ШШ();
          }
          b044904490449щ044904490449щщ = 33;
          bщщщ0449044904490449щщ = 99;
        }
        return true;
      }
      else
      {
        return false;
      }
    }
    catch (Exception localException)
    {
      throw localException;
    }
    label111:
    switch (0)
    {
    }
    for (;;)
    {
      switch (1)
      {
      }
    }
  }
  
  public Runnable bШШ04280428Ш042804280428ШШ(ovvvvo paramOvvvvo, long paramLong)
  {
    boolean bool = bШ0428Ш0428Ш042804280428ШШ();
    switch (0)
    {
    case 1: 
    default: 
      for (;;)
      {
        switch (0)
        {
        }
      }
    }
    int i = b044904490449щ044904490449щщ;
    switch (i * (b0449щщ0449044904490449щщ + i) % bщ0449щ0449044904490449щщ)
    {
    default: 
      b044904490449щ044904490449щщ = 49;
      bщщщ0449044904490449щщ = 22;
    }
    i = b044904490449щ044904490449щщ;
    switch (i * (b0449щщ0449044904490449щщ + i) % bщ0449щ0449044904490449щщ)
    {
    default: 
      b044904490449щ044904490449щщ = b042804280428ШШ042804280428ШШ();
      bщщщ0449044904490449щщ = b042804280428ШШ042804280428ШШ();
    }
    if (bool) {
      return null;
    }
    paramOvvvvo = new vvvvvo(paramOvvvvo);
    this.b0449щ0449щ044904490449щщ.b0428ШШ0428Ш0428Ш04280428Ш(paramOvvvvo, paramLong);
    return paramOvvvvo;
  }
  
  public void bШШШ0428Ш042804280428ШШ(Runnable paramRunnable)
  {
    if ((b044904490449щ044904490449щщ + b0449щщ0449044904490449щщ) * b044904490449щ044904490449щщ % bщ0449щ0449044904490449щщ != bщщщ0449044904490449щщ)
    {
      b044904490449щ044904490449щщ = b042804280428ШШ042804280428ШШ();
      bщщщ0449044904490449щщ = b042804280428ШШ042804280428ШШ();
    }
    try
    {
      boolean bool = bШ0428Ш0428Ш042804280428ШШ();
      if (bool)
      {
        int i = b044904490449щ044904490449щщ;
        switch (i * (b0449щщ0449044904490449щщ + i) % b0428Ш0428ШШ042804280428ШШ())
        {
        default: 
          b044904490449щ044904490449щщ = 59;
          bщщщ0449044904490449щщ = b042804280428ШШ042804280428ШШ();
        }
        return;
      }
      this.b0449щ0449щ044904490449щщ.b04280428Ш0428Ш0428Ш04280428Ш(paramRunnable);
      return;
    }
    catch (Exception paramRunnable)
    {
      throw paramRunnable;
    }
  }
  
  public class vvvvvo
    implements Runnable
  {
    public static int b0449044904490449044904490449щщ = 2;
    public static int b0449щ04490449044904490449щщ = 87;
    public static int bщ044904490449044904490449щщ = 0;
    public static int bщщщщщщщ0449щ = 1;
    public final ovvvvo b04490449щ0449044904490449щщ;
    
    public vvvvvo(ovvvvo paramOvvvvo)
    {
      this.b04490449щ0449044904490449щщ = paramOvvvvo;
    }
    
    public static int b0428ШШШШ042804280428ШШ()
    {
      return 1;
    }
    
    public static int bШ0428ШШШ042804280428ШШ()
    {
      return 46;
    }
    
    /* Error */
    public void run()
    {
      // Byte code:
      //   0: getstatic 40	kkkkkk/ooooov$vvvvvo:b0449щ04490449044904490449щщ	I
      //   3: getstatic 42	kkkkkk/ooooov$vvvvvo:bщщщщщщщ0449щ	I
      //   6: iadd
      //   7: getstatic 40	kkkkkk/ooooov$vvvvvo:b0449щ04490449044904490449щщ	I
      //   10: imul
      //   11: getstatic 44	kkkkkk/ooooov$vvvvvo:b0449044904490449044904490449щщ	I
      //   14: irem
      //   15: getstatic 46	kkkkkk/ooooov$vvvvvo:bщ044904490449044904490449щщ	I
      //   18: if_icmpeq +14 -> 32
      //   21: bipush 10
      //   23: putstatic 40	kkkkkk/ooooov$vvvvvo:b0449щ04490449044904490449щщ	I
      //   26: invokestatic 48	kkkkkk/ooooov$vvvvvo:bШ0428ШШШ042804280428ШШ	()I
      //   29: putstatic 46	kkkkkk/ooooov$vvvvvo:bщ044904490449044904490449щщ	I
      //   32: aload_0
      //   33: getfield 26	kkkkkk/ooooov$vvvvvo:bщщ04490449044904490449щщ	Lkkkkkk/ooooov;
      //   36: invokestatic 52	kkkkkk/ooooov:b04280428ШШШ042804280428ШШ	(Lkkkkkk/ooooov;)Ljava/lang/String;
      //   39: astore 6
      //   41: new 54	java/lang/StringBuilder
      //   44: dup
      //   45: invokespecial 55	java/lang/StringBuilder:<init>	()V
      //   48: astore 7
      //   50: getstatic 40	kkkkkk/ooooov$vvvvvo:b0449щ04490449044904490449щщ	I
      //   53: istore_1
      //   54: invokestatic 57	kkkkkk/ooooov$vvvvvo:b0428ШШШШ042804280428ШШ	()I
      //   57: istore_2
      //   58: getstatic 40	kkkkkk/ooooov$vvvvvo:b0449щ04490449044904490449щщ	I
      //   61: istore_3
      //   62: getstatic 44	kkkkkk/ooooov$vvvvvo:b0449044904490449044904490449щщ	I
      //   65: istore 4
      //   67: getstatic 46	kkkkkk/ooooov$vvvvvo:bщ044904490449044904490449щщ	I
      //   70: istore 5
      //   72: iload_1
      //   73: iload_2
      //   74: iadd
      //   75: iload_3
      //   76: imul
      //   77: iload 4
      //   79: irem
      //   80: iload 5
      //   82: if_icmpeq +14 -> 96
      //   85: invokestatic 48	kkkkkk/ooooov$vvvvvo:bШ0428ШШШ042804280428ШШ	()I
      //   88: putstatic 40	kkkkkk/ooooov$vvvvvo:b0449щ04490449044904490449щщ	I
      //   91: bipush 86
      //   93: putstatic 46	kkkkkk/ooooov$vvvvvo:bщ044904490449044904490449щщ	I
      //   96: aload 7
      //   98: aload_0
      //   99: getfield 26	kkkkkk/ooooov$vvvvvo:bщщ04490449044904490449щщ	Lkkkkkk/ooooov;
      //   102: invokestatic 61	kkkkkk/ooooov:bШШ0428ШШ042804280428ШШ	(Lkkkkkk/ooooov;)Lkkkkkk/ovovvo;
      //   105: invokeinterface 67 1 0
      //   110: invokevirtual 71	java/lang/Object:toString	()Ljava/lang/String;
      //   113: invokevirtual 75	java/lang/StringBuilder:append	(Ljava/lang/String;)Ljava/lang/StringBuilder;
      //   116: ldc 77
      //   118: sipush 254
      //   121: iconst_4
      //   122: invokestatic 83	kkkkkk/gguuuu:bккккк043Aкк043A043A	(Ljava/lang/String;CC)Ljava/lang/String;
      //   125: invokevirtual 75	java/lang/StringBuilder:append	(Ljava/lang/String;)Ljava/lang/StringBuilder;
      //   128: astore 7
      //   130: aload 6
      //   132: aload 7
      //   134: aload_0
      //   135: getfield 31	kkkkkk/ooooov$vvvvvo:b04490449щ0449044904490449щщ	Lkkkkkk/ovvvvo;
      //   138: invokevirtual 71	java/lang/Object:toString	()Ljava/lang/String;
      //   141: invokevirtual 75	java/lang/StringBuilder:append	(Ljava/lang/String;)Ljava/lang/StringBuilder;
      //   144: invokevirtual 84	java/lang/StringBuilder:toString	()Ljava/lang/String;
      //   147: invokestatic 90	kkkkkk/xtxtxt:bии0438и04380438и0438ии	(Ljava/lang/String;Ljava/lang/String;)V
      //   150: aload_0
      //   151: getfield 31	kkkkkk/ooooov$vvvvvo:b04490449щ0449044904490449щщ	Lkkkkkk/ovvvvo;
      //   154: aload_0
      //   155: getfield 26	kkkkkk/ooooov$vvvvvo:bщщ04490449044904490449щщ	Lkkkkkk/ooooov;
      //   158: invokestatic 61	kkkkkk/ooooov:bШШ0428ШШ042804280428ШШ	(Lkkkkkk/ooooov;)Lkkkkkk/ovovvo;
      //   161: invokeinterface 67 1 0
      //   166: invokeinterface 96 2 0
      //   171: return
      //   172: astore 6
      //   174: aload 6
      //   176: athrow
      //   177: astore 6
      //   179: aload 6
      //   181: athrow
      //   182: astore 6
      //   184: aload 6
      //   186: athrow
      //   187: astore 6
      //   189: aload 6
      //   191: athrow
      // Local variable table:
      //   start	length	slot	name	signature
      //   0	192	0	this	vvvvvo
      //   53	22	1	i	int
      //   57	18	2	j	int
      //   61	16	3	k	int
      //   65	15	4	m	int
      //   70	13	5	n	int
      //   39	92	6	str	String
      //   172	3	6	localException1	Exception
      //   177	3	6	localException2	Exception
      //   182	3	6	localException3	Exception
      //   187	3	6	localException4	Exception
      //   48	85	7	localStringBuilder	StringBuilder
      // Exception table:
      //   from	to	target	type
      //   32	50	172	java/lang/Exception
      //   96	130	172	java/lang/Exception
      //   85	96	177	java/lang/Exception
      //   174	177	177	java/lang/Exception
      //   184	187	177	java/lang/Exception
      //   130	171	182	java/lang/Exception
      //   50	72	187	java/lang/Exception
    }
  }
}
