package kkkkkk;

import java.util.ArrayList;
import java.util.Collections;
import java.util.List;

public class ooooio
{
  public static int b041FПППППППП = 2;
  private static volatile iiiioo[] b043A043Aк043A043A043A043A043A043A;
  public static int b043Aк043A043A043A043A043A043A043A = 0;
  private static final List<iiiioo> b043Aкк043A043A043A043A043A043A;
  public static int bк043A043A043A043A043A043A043A043A = 1;
  private static final iiiioo[] bк043Aк043A043A043A043A043A043A;
  public static int bкк043A043A043A043A043A043A043A = 60;
  
  static
  {
    try
    {
      bк043Aк043A043A043A043A043A043A = new iiiioo[0];
      if ((bкк043A043A043A043A043A043A043A + bк043A043A043A043A043A043A043A043A) * bкк043A043A043A043A043A043A043A % b041FПППППППП != b043Aк043A043A043A043A043A043A043A)
      {
        bкк043A043A043A043A043A043A043A = 72;
        b043Aк043A043A043A043A043A043A043A = 78;
      }
      b043Aкк043A043A043A043A043A043A = new ArrayList();
      b043A043Aк043A043A043A043A043A043A = bк043Aк043A043A043A043A043A043A;
      return;
    }
    catch (Exception localException)
    {
      throw localException;
    }
  }
  
  @ooiiio
  private ooooio()
  {
    throw new AssertionError(gguuuu.bккккк043Aкк043A043A("=]\rUY]]IUIJW\021", '', '\005'));
  }
  
  public static void b04300430043004300430а0430ааа(int paramInt, String paramString, Object... paramVarArgs)
  {
    iiiioo[] arrayOfIiiioo = b043A043Aк043A043A043A043A043A043A;
    int j = arrayOfIiiioo.length;
    int i = 0;
    for (;;)
    {
      if ((bкк043A043A043A043A043A043A043A + bк043A043A043A043A043A043A043A043A) * bкк043A043A043A043A043A043A043A % b041FПППППППП != b043Aк043A043A043A043A043A043A043A)
      {
        bкк043A043A043A043A043A043A043A = bааа04300430а0430ааа();
        b043Aк043A043A043A043A043A043A043A = 90;
      }
      if (i >= j) {
        break;
      }
      arrayOfIiiioo[i].bаа0430а043004300430ааа(paramInt, paramString, paramVarArgs);
      i += 1;
    }
  }
  
  public static int b043004300430а0430а0430ааа()
  {
    return 2;
  }
  
  public static void b043004300430аа04300430ааа(String paramString, Object... paramVarArgs)
  {
    throw new Runtime("d2j fail translate: java.lang.IndexOutOfBoundsException: fromIndex < 0: -1\n\tat java.util.BitSet.nextSetBit(BitSet.java:712)\n\tat com.googlecode.dex2jar.ir.ts.array.FillArrayTransformer.makeSureAllElementAreAssigned(FillArrayTransformer.java:505)\n\tat com.googlecode.dex2jar.ir.ts.array.FillArrayTransformer.transformReportChanged(FillArrayTransformer.java:123)\n\tat com.googlecode.dex2jar.ir.ts.StatedTransformer.transform(StatedTransformer.java:10)\n\tat com.googlecode.d2j.dex.Dex2jar$2.optimize(Dex2jar.java:149)\n\tat com.googlecode.d2j.dex.Dex2Asm.convertCode(Dex2Asm.java:414)\n\tat com.googlecode.d2j.dex.ExDex2Asm.convertCode(ExDex2Asm.java:42)\n\tat com.googlecode.d2j.dex.Dex2jar$2.convertCode(Dex2jar.java:128)\n\tat com.googlecode.d2j.dex.Dex2Asm.convertMethod(Dex2Asm.java:509)\n\tat com.googlecode.d2j.dex.Dex2Asm.convertClass(Dex2Asm.java:406)\n\tat com.googlecode.d2j.dex.Dex2Asm.convertDex(Dex2Asm.java:422)\n\tat com.googlecode.d2j.dex.Dex2jar.doTranslate(Dex2jar.java:172)\n\tat com.googlecode.d2j.dex.Dex2jar.to(Dex2jar.java:272)\n\tat com.googlecode.dex2jar.tools.Dex2jarCmd.doCommandLine(Dex2jarCmd.java:108)\n\tat com.googlecode.dex2jar.tools.BaseCmd.doMain(BaseCmd.java:288)\n\tat com.googlecode.dex2jar.tools.Dex2jarCmd.main(Dex2jarCmd.java:32)\n");
  }
  
  public static void b04300430а04300430а0430ааа(String paramString, Object... paramVarArgs)
  {
    iiiioo[] arrayOfIiiioo = b043A043Aк043A043A043A043A043A043A;
    int j = arrayOfIiiioo.length;
    int i = 0;
    for (;;)
    {
      switch (1)
      {
      case 0: 
      default: 
        for (;;)
        {
          switch (0)
          {
          }
        }
      }
      if (i >= j) {
        break;
      }
      iiiioo localIiiioo = arrayOfIiiioo[i];
      int k = bкк043A043A043A043A043A043A043A;
      int m = bк043A043A043A043A043A043A043A043A;
      int n = bкк043A043A043A043A043A043A043A;
      int i1 = b041FПППППППП;
      int i2 = b043Aк043A043A043A043A043A043A043A;
      if ((bкк043A043A043A043A043A043A043A + bк043A043A043A043A043A043A043A043A) * bкк043A043A043A043A043A043A043A % b041FПППППППП != b043Aк043A043A043A043A043A043A043A)
      {
        bкк043A043A043A043A043A043A043A = 12;
        b043Aк043A043A043A043A043A043A043A = 28;
      }
      if ((k + m) * n % i1 != i2)
      {
        bкк043A043A043A043A043A043A043A = 1;
        b043Aк043A043A043A043A043A043A043A = 0;
      }
      localIiiioo.bа043004300430а04300430ааа(paramString, paramVarArgs);
      i += 1;
    }
  }
  
  public static void b04300430ааа04300430ааа(iiiioo paramIiiioo)
  {
    List localList = b043Aкк043A043A043A043A043A043A;
    switch (0)
    {
    case 1: 
    default: 
      for (;;)
      {
        switch (1)
        {
        }
      }
    }
    try
    {
      if (!b043Aкк043A043A043A043A043A043A.remove(paramIiiioo)) {
        throw new IllegalArgumentException(gguuuu.bккккк043Aкк043A043A("?^lmou\"uiru}m)vzsts\0020\tz|w}6y\r:\n\f\022>\002\006\007\021C\006\n\013\r\rcJ", 'ü', '\004') + paramIiiioo);
      }
    }
    finally {}
    b043A043Aк043A043A043A043A043A043A = (iiiioo[])b043Aкк043A043A043A043A043A043A.toArray(new iiiioo[b043Aкк043A043A043A043A043A043A.size()]);
  }
  
  public static void b0430а043004300430а0430ааа(Throwable paramThrowable, String paramString, Object... paramVarArgs)
  {
    try
    {
      iiiioo[] arrayOfIiiioo = b043A043Aк043A043A043A043A043A043A;
      int j = arrayOfIiiioo.length;
      int i = 0;
      for (;;)
      {
        int k = bкк043A043A043A043A043A043A043A;
        switch (k * (bк043A043A043A043A043A043A043A043A + k) % b041FПППППППП)
        {
        default: 
          bкк043A043A043A043A043A043A043A = bааа04300430а0430ааа();
          b043Aк043A043A043A043A043A043A043A = bааа04300430а0430ааа();
        }
        if (i >= j) {
          break;
        }
        iiiioo localIiiioo = arrayOfIiiioo[i];
        localIiiioo.bаааа043004300430ааа(paramThrowable, paramString, paramVarArgs);
        if ((bкк043A043A043A043A043A043A043A + bк043A043A043A043A043A043A043A043A) * bкк043A043A043A043A043A043A043A % b041FПППППППП != b043Aк043A043A043A043A043A043A043A)
        {
          bкк043A043A043A043A043A043A043A = bааа04300430а0430ааа();
          b043Aк043A043A043A043A043A043A043A = 61;
        }
        i += 1;
      }
      return;
    }
    catch (Exception paramThrowable)
    {
      throw paramThrowable;
    }
  }
  
  public static void b0430а0430а0430а0430ааа(iiiioo... paramVarArgs)
  {
    int i = 0;
    if (paramVarArgs == null)
    {
      paramVarArgs = new NullPointerException(gguuuu.bккккк043Aкк043A043A("\030\034\025\026\031\037\031v\031!\033\036\031-\037.[yz^.6./", 'Ô', '\004'));
      switch (1)
      {
      case 0: 
      default: 
        for (;;)
        {
          switch (0)
          {
          }
        }
      }
      throw paramVarArgs;
      i += 1;
    }
    for (;;)
    {
      int j;
      if (i < j)
      {
        if (paramVarArgs[i] != null) {
          break;
        }
        throw new NullPointerException(gguuuu.bккккк043Aкк043A043A("\024\026\r\f\r\021\td\005\013\003\004|\017~\f7y\005\003\bsz~\003.{\002wv", 'X', '\005'));
      }
      synchronized (b043Aкк043A043A043A043A043A043A)
      {
        Collections.addAll(b043Aкк043A043A043A043A043A043A, paramVarArgs);
        b043A043Aк043A043A043A043A043A043A = (iiiioo[])b043Aкк043A043A043A043A043A043A.toArray(new iiiioo[b043Aкк043A043A043A043A043A043A.size()]);
        return;
        j = paramVarArgs.length;
      }
    }
  }
  
  public static void b0430а0430аа04300430ааа(String paramString)
  {
    try
    {
      arrayOfIiiioo = b043A043Aк043A043A043A043A043A043A;
      k = arrayOfIiiioo.length;
      int j = 0;
      i = j;
      if ((bкк043A043A043A043A043A043A043A + bк043A043A043A043A043A043A043A043A) * bкк043A043A043A043A043A043A043A % b041FПППППППП != b043Aк043A043A043A043A043A043A043A)
      {
        if ((bкк043A043A043A043A043A043A043A + bк043A043A043A043A043A043A043A043A) * bкк043A043A043A043A043A043A043A % b041FПППППППП != b043Aк043A043A043A043A043A043A043A)
        {
          bкк043A043A043A043A043A043A043A = bааа04300430а0430ааа();
          b043Aк043A043A043A043A043A043A043A = 33;
        }
        bкк043A043A043A043A043A043A043A = 6;
        b043Aк043A043A043A043A043A043A043A = bааа04300430а0430ааа();
        i = j;
      }
    }
    catch (Exception paramString)
    {
      try
      {
        iiiioo[] arrayOfIiiioo;
        int k;
        int i;
        arrayOfIiiioo[i].bП041FППППППП.set(paramString);
        i += 1;
      }
      catch (Exception paramString)
      {
        switch (1)
        {
        case 0: 
        default: 
          for (;;)
          {
            switch (1)
            {
            }
          }
        }
        throw paramString;
      }
      paramString = paramString;
      throw paramString;
    }
    if (i < k) {}
  }
  
  public static int b0430аа04300430а0430ааа()
  {
    return 0;
  }
  
  public static void b0430аа0430а04300430ааа(Throwable paramThrowable, String paramString, Object... paramVarArgs)
  {
    int j = 0;
    int i = 2;
    try
    {
      arrayOfIiiioo = b043A043Aк043A043A043A043A043A043A;
      for (;;)
      {
        try
        {
          i /= 0;
          continue;
          i += 1;
        }
        catch (Exception localException)
        {
          bкк043A043A043A043A043A043A043A = bааа04300430а0430ааа();
          int k = arrayOfIiiioo.length;
          i = j;
          continue;
        }
        j = bааа04300430а0430ааа();
        switch (j * (bк043A043A043A043A043A043A043A043A + j) % b041FПППППППП)
        {
        default: 
          bкк043A043A043A043A043A043A043A = bааа04300430а0430ааа();
          b043Aк043A043A043A043A043A043A043A = bааа04300430а0430ааа();
        }
        if (i < k) {
          try
          {
            arrayOfIiiioo[i].b04300430а0430043004300430ааа(paramThrowable, paramString, paramVarArgs);
          }
          catch (Exception paramThrowable)
          {
            throw paramThrowable;
          }
        }
      }
      switch (1)
      {
      case 0: 
      default: 
        for (;;)
        {
          switch (1)
          {
          }
        }
      }
      return;
    }
    catch (Exception paramThrowable)
    {
      iiiioo[] arrayOfIiiioo;
      throw paramThrowable;
    }
  }
  
  /* Error */
  public static void b0430аааа04300430ааа(int paramInt, Throwable paramThrowable, String paramString, Object... paramVarArgs)
  {
    // Byte code:
    //   0: getstatic 44	kkkkkk/ooooio:b043A043Aк043A043A043A043A043A043A	[Lkkkkkk/iiiioo;
    //   3: astore 6
    //   5: aload 6
    //   7: arraylength
    //   8: istore 5
    //   10: iconst_0
    //   11: istore 4
    //   13: iload 4
    //   15: iload 5
    //   17: if_icmpge +98 -> 115
    //   20: aload 6
    //   22: iload 4
    //   24: aaload
    //   25: astore 7
    //   27: getstatic 29	kkkkkk/ooooio:bкк043A043A043A043A043A043A043A	I
    //   30: invokestatic 161	kkkkkk/ooooio:bа04300430а0430а0430ааа	()I
    //   33: iadd
    //   34: getstatic 29	kkkkkk/ooooio:bкк043A043A043A043A043A043A043A	I
    //   37: imul
    //   38: getstatic 33	kkkkkk/ooooio:b041FПППППППП	I
    //   41: irem
    //   42: getstatic 35	kkkkkk/ooooio:b043Aк043A043A043A043A043A043A043A	I
    //   45: if_icmpeq +46 -> 91
    //   48: invokestatic 67	kkkkkk/ooooio:bааа04300430а0430ааа	()I
    //   51: putstatic 29	kkkkkk/ooooio:bкк043A043A043A043A043A043A043A	I
    //   54: bipush 30
    //   56: putstatic 35	kkkkkk/ooooio:b043Aк043A043A043A043A043A043A043A	I
    //   59: getstatic 29	kkkkkk/ooooio:bкк043A043A043A043A043A043A043A	I
    //   62: getstatic 31	kkkkkk/ooooio:bк043A043A043A043A043A043A043A043A	I
    //   65: iadd
    //   66: getstatic 29	kkkkkk/ooooio:bкк043A043A043A043A043A043A043A	I
    //   69: imul
    //   70: getstatic 33	kkkkkk/ooooio:b041FПППППППП	I
    //   73: irem
    //   74: invokestatic 163	kkkkkk/ooooio:b0430аа04300430а0430ааа	()I
    //   77: if_icmpeq +14 -> 91
    //   80: bipush 34
    //   82: putstatic 29	kkkkkk/ooooio:bкк043A043A043A043A043A043A043A	I
    //   85: invokestatic 67	kkkkkk/ooooio:bааа04300430а0430ааа	()I
    //   88: putstatic 35	kkkkkk/ooooio:b043Aк043A043A043A043A043A043A043A	I
    //   91: aload 7
    //   93: iload_0
    //   94: aload_1
    //   95: aload_2
    //   96: aload_3
    //   97: invokevirtual 166	kkkkkk/iiiioo:bа04300430а043004300430ааа	(ILjava/lang/Throwable;Ljava/lang/String;[Ljava/lang/Object;)V
    //   100: iload 4
    //   102: iconst_1
    //   103: iadd
    //   104: istore 4
    //   106: goto -93 -> 13
    //   109: astore_1
    //   110: aload_1
    //   111: athrow
    //   112: astore_1
    //   113: aload_1
    //   114: athrow
    //   115: return
    // Local variable table:
    //   start	length	slot	name	signature
    //   0	116	0	paramInt	int
    //   0	116	1	paramThrowable	Throwable
    //   0	116	2	paramString	String
    //   0	116	3	paramVarArgs	Object[]
    //   11	94	4	i	int
    //   8	10	5	j	int
    //   3	18	6	arrayOfIiiioo	iiiioo[]
    //   25	67	7	localIiiioo	iiiioo
    // Exception table:
    //   from	to	target	type
    //   5	10	109	java/lang/Exception
    //   27	59	109	java/lang/Exception
    //   0	5	112	java/lang/Exception
    //   91	100	112	java/lang/Exception
  }
  
  public static void bа0430043004300430а0430ааа(String paramString, Object... paramVarArgs)
  {
    iiiioo[] arrayOfIiiioo = b043A043Aк043A043A043A043A043A043A;
    int j = arrayOfIiiioo.length;
    int i;
    if ((bааа04300430а0430ааа() + bк043A043A043A043A043A043A043A043A) * bааа04300430а0430ааа() % b041FПППППППП != b043Aк043A043A043A043A043A043A043A)
    {
      if ((bкк043A043A043A043A043A043A043A + bк043A043A043A043A043A043A043A043A) * bкк043A043A043A043A043A043A043A % b041FПППППППП != b043Aк043A043A043A043A043A043A043A)
      {
        bкк043A043A043A043A043A043A043A = 51;
        b043Aк043A043A043A043A043A043A043A = bааа04300430а0430ааа();
      }
      bкк043A043A043A043A043A043A043A = 22;
      b043Aк043A043A043A043A043A043A043A = bааа04300430а0430ааа();
      i = 0;
    }
    for (;;)
    {
      switch (0)
      {
      case 1: 
      default: 
        for (;;)
        {
          switch (1)
          {
          }
        }
      }
      if (i < j)
      {
        arrayOfIiiioo[i].bа0430аа043004300430ааа(paramString, paramVarArgs);
        i += 1;
      }
      else
      {
        return;
        i = 0;
      }
    }
  }
  
  public static int bа04300430а0430а0430ааа()
  {
    return 1;
  }
  
  public static void bа04300430аа04300430ааа(String paramString, Object... paramVarArgs)
  {
    try
    {
      iiiioo[] arrayOfIiiioo = b043A043Aк043A043A043A043A043A043A;
      int k = arrayOfIiiioo.length;
      int i = 0;
      while (i < k)
      {
        arrayOfIiiioo[i].bааа0430043004300430ааа(paramString, paramVarArgs);
        int j = i + 1;
        i = j;
        if ((bкк043A043A043A043A043A043A043A + bк043A043A043A043A043A043A043A043A) * bкк043A043A043A043A043A043A043A % b043004300430а0430а0430ааа() != b043Aк043A043A043A043A043A043A043A)
        {
          bкк043A043A043A043A043A043A043A = bааа04300430а0430ааа();
          b043Aк043A043A043A043A043A043A043A = bааа04300430а0430ааа();
          i = j;
        }
      }
      return;
    }
    catch (Exception paramString)
    {
      throw paramString;
    }
  }
  
  public static void bа0430а04300430а0430ааа(String paramString, Object... paramVarArgs)
  {
    throw new Runtime("d2j fail translate: java.lang.IndexOutOfBoundsException: fromIndex < 0: -1\n\tat java.util.BitSet.nextSetBit(BitSet.java:712)\n\tat com.googlecode.dex2jar.ir.ts.array.FillArrayTransformer.makeSureAllElementAreAssigned(FillArrayTransformer.java:505)\n\tat com.googlecode.dex2jar.ir.ts.array.FillArrayTransformer.transformReportChanged(FillArrayTransformer.java:123)\n\tat com.googlecode.dex2jar.ir.ts.StatedTransformer.transform(StatedTransformer.java:10)\n\tat com.googlecode.d2j.dex.Dex2jar$2.optimize(Dex2jar.java:149)\n\tat com.googlecode.d2j.dex.Dex2Asm.convertCode(Dex2Asm.java:414)\n\tat com.googlecode.d2j.dex.ExDex2Asm.convertCode(ExDex2Asm.java:42)\n\tat com.googlecode.d2j.dex.Dex2jar$2.convertCode(Dex2jar.java:128)\n\tat com.googlecode.d2j.dex.Dex2Asm.convertMethod(Dex2Asm.java:509)\n\tat com.googlecode.d2j.dex.Dex2Asm.convertClass(Dex2Asm.java:406)\n\tat com.googlecode.d2j.dex.Dex2Asm.convertDex(Dex2Asm.java:422)\n\tat com.googlecode.d2j.dex.Dex2jar.doTranslate(Dex2jar.java:172)\n\tat com.googlecode.d2j.dex.Dex2jar.to(Dex2jar.java:272)\n\tat com.googlecode.dex2jar.tools.Dex2jarCmd.doCommandLine(Dex2jarCmd.java:108)\n\tat com.googlecode.dex2jar.tools.BaseCmd.doMain(BaseCmd.java:288)\n\tat com.googlecode.dex2jar.tools.Dex2jarCmd.main(Dex2jarCmd.java:32)\n");
  }
  
  @ooiiio("Ignored because of the synchronized")
  public static int bа0430ааа04300430ааа()
  {
    synchronized (b043Aкк043A043A043A043A043A043A)
    {
      int i = b043Aкк043A043A043A043A043A043A.size();
      return i;
    }
  }
  
  public static void bаа043004300430а0430ааа(Throwable paramThrowable)
  {
    iiiioo[] arrayOfIiiioo = b043A043Aк043A043A043A043A043A043A;
    int j = arrayOfIiiioo.length;
    int i = 0;
    for (;;)
    {
      switch (0)
      {
      case 1: 
      default: 
        for (;;)
        {
          switch (1)
          {
          }
        }
      }
      if (i >= j) {
        break;
      }
      if ((bкк043A043A043A043A043A043A043A + bк043A043A043A043A043A043A043A043A) * bкк043A043A043A043A043A043A043A % b041FПППППППП != b043Aк043A043A043A043A043A043A043A)
      {
        bкк043A043A043A043A043A043A043A = 93;
        b043Aк043A043A043A043A043A043A043A = 25;
      }
      iiiioo localIiiioo = arrayOfIiiioo[i];
      if ((bкк043A043A043A043A043A043A043A + bк043A043A043A043A043A043A043A043A) * bкк043A043A043A043A043A043A043A % b043004300430а0430а0430ааа() != b043Aк043A043A043A043A043A043A043A)
      {
        bкк043A043A043A043A043A043A043A = bааа04300430а0430ааа();
        switch (0)
        {
        case 1: 
        default: 
          for (;;)
          {
            switch (1)
            {
            }
          }
        }
        b043Aк043A043A043A043A043A043A043A = 23;
      }
      localIiiioo.b0430043004300430а04300430ааа(paramThrowable);
      i += 1;
    }
  }
  
  /* Error */
  public static void bаа0430а0430а0430ааа(iiiioo paramIiiioo)
  {
    // Byte code:
    //   0: aload_0
    //   1: ifnonnull +81 -> 82
    //   4: new 130	java/lang/NullPointerException
    //   7: dup
    //   8: ldc -68
    //   10: sipush 138
    //   13: iconst_1
    //   14: invokestatic 57	kkkkkk/gguuuu:bккккк043Aкк043A043A	(Ljava/lang/String;CC)Ljava/lang/String;
    //   17: invokespecial 133	java/lang/NullPointerException:<init>	(Ljava/lang/String;)V
    //   20: athrow
    //   21: astore_0
    //   22: aload_1
    //   23: monitorexit
    //   24: aload_0
    //   25: athrow
    //   26: iconst_1
    //   27: tableswitch	default:+21->48, 0:+24->51, 1:+52->79
    //   48: goto -22 -> 26
    //   51: iconst_1
    //   52: tableswitch	default:+24->76, 0:+-1->51, 1:+27->79
    //   76: goto -50 -> 26
    //   79: aload_1
    //   80: monitorexit
    //   81: return
    //   82: getstatic 42	kkkkkk/ooooio:b043Aкк043A043A043A043A043A043A	Ljava/util/List;
    //   85: astore_1
    //   86: aload_1
    //   87: monitorenter
    //   88: getstatic 42	kkkkkk/ooooio:b043Aкк043A043A043A043A043A043A	Ljava/util/List;
    //   91: aload_0
    //   92: invokeinterface 191 2 0
    //   97: pop
    //   98: getstatic 42	kkkkkk/ooooio:b043Aкк043A043A043A043A043A043A	Ljava/util/List;
    //   101: getstatic 42	kkkkkk/ooooio:b043Aкк043A043A043A043A043A043A	Ljava/util/List;
    //   104: invokeinterface 116 1 0
    //   109: anewarray 25	kkkkkk/iiiioo
    //   112: invokeinterface 120 2 0
    //   117: checkcast 121	[Lkkkkkk/iiiioo;
    //   120: astore_0
    //   121: goto +10 -> 131
    //   124: aload_0
    //   125: putstatic 44	kkkkkk/ooooio:b043A043Aк043A043A043A043A043A043A	[Lkkkkkk/iiiioo;
    //   128: goto -77 -> 51
    //   131: iconst_0
    //   132: tableswitch	default:+24->156, 0:+-8->124, 1:+-1->131
    //   156: iconst_1
    //   157: tableswitch	default:+23->180, 0:+-26->131, 1:+-33->124
    //   180: goto -24 -> 156
    // Local variable table:
    //   start	length	slot	name	signature
    //   0	183	0	paramIiiioo	iiiioo
    //   22	65	1	localList	List
    // Exception table:
    //   from	to	target	type
    //   22	24	21	finally
    //   79	81	21	finally
    //   88	121	21	finally
    //   124	128	21	finally
  }
  
  public static void bаа0430аа04300430ааа()
  {
    synchronized (b043Aкк043A043A043A043A043A043A)
    {
      b043Aкк043A043A043A043A043A043A.clear();
      b043A043Aк043A043A043A043A043A043A = bк043Aк043A043A043A043A043A043A;
      return;
    }
  }
  
  public static int bааа04300430а0430ааа()
  {
    return 90;
  }
  
  /* Error */
  public static void bааа0430а04300430ааа(Throwable paramThrowable)
  {
    // Byte code:
    //   0: getstatic 44	kkkkkk/ooooio:b043A043Aк043A043A043A043A043A043A	[Lkkkkkk/iiiioo;
    //   3: astore 6
    //   5: aload 6
    //   7: arraylength
    //   8: istore_2
    //   9: iconst_0
    //   10: istore_1
    //   11: iload_1
    //   12: iload_2
    //   13: if_icmpge +128 -> 141
    //   16: aload 6
    //   18: iload_1
    //   19: aaload
    //   20: astore 7
    //   22: getstatic 29	kkkkkk/ooooio:bкк043A043A043A043A043A043A043A	I
    //   25: istore_3
    //   26: getstatic 31	kkkkkk/ooooio:bк043A043A043A043A043A043A043A043A	I
    //   29: istore 4
    //   31: getstatic 33	kkkkkk/ooooio:b041FПППППППП	I
    //   34: istore 5
    //   36: iload_3
    //   37: iload 4
    //   39: iload_3
    //   40: iadd
    //   41: imul
    //   42: iload 5
    //   44: irem
    //   45: tableswitch	default:+19->64, 0:+74->119
    //   64: bipush 46
    //   66: putstatic 29	kkkkkk/ooooio:bкк043A043A043A043A043A043A043A	I
    //   69: invokestatic 67	kkkkkk/ooooio:bааа04300430а0430ааа	()I
    //   72: putstatic 35	kkkkkk/ooooio:b043Aк043A043A043A043A043A043A043A	I
    //   75: getstatic 29	kkkkkk/ooooio:bкк043A043A043A043A043A043A043A	I
    //   78: istore_3
    //   79: iload_3
    //   80: getstatic 31	kkkkkk/ooooio:bк043A043A043A043A043A043A043A043A	I
    //   83: iload_3
    //   84: iadd
    //   85: imul
    //   86: getstatic 33	kkkkkk/ooooio:b041FПППППППП	I
    //   89: irem
    //   90: tableswitch	default:+18->108, 0:+29->119
    //   108: bipush 42
    //   110: putstatic 29	kkkkkk/ooooio:bкк043A043A043A043A043A043A043A	I
    //   113: invokestatic 67	kkkkkk/ooooio:bааа04300430а0430ааа	()I
    //   116: putstatic 35	kkkkkk/ooooio:b043Aк043A043A043A043A043A043A043A	I
    //   119: aload 7
    //   121: aload_0
    //   122: invokevirtual 199	kkkkkk/iiiioo:bа0430а0430043004300430ааа	(Ljava/lang/Throwable;)V
    //   125: iload_1
    //   126: iconst_1
    //   127: iadd
    //   128: istore_1
    //   129: goto -118 -> 11
    //   132: astore_0
    //   133: aload_0
    //   134: athrow
    //   135: astore_0
    //   136: aload_0
    //   137: athrow
    //   138: astore_0
    //   139: aload_0
    //   140: athrow
    //   141: return
    // Local variable table:
    //   start	length	slot	name	signature
    //   0	142	0	paramThrowable	Throwable
    //   10	119	1	i	int
    //   8	6	2	j	int
    //   25	61	3	k	int
    //   29	12	4	m	int
    //   34	11	5	n	int
    //   3	14	6	arrayOfIiiioo	iiiioo[]
    //   20	100	7	localIiiioo	iiiioo
    // Exception table:
    //   from	to	target	type
    //   0	9	132	java/lang/Exception
    //   119	125	132	java/lang/Exception
    //   64	75	135	java/lang/Exception
    //   133	135	135	java/lang/Exception
    //   22	36	138	java/lang/Exception
  }
  
  public static void bааааа04300430ааа(int paramInt, Throwable paramThrowable)
  {
    iiiioo[] arrayOfIiiioo = b043A043Aк043A043A043A043A043A043A;
    int j = arrayOfIiiioo.length;
    int i;
    if ((bааа04300430а0430ааа() + bк043A043A043A043A043A043A043A043A) * bааа04300430а0430ааа() % b041FПППППППП != b043Aк043A043A043A043A043A043A043A)
    {
      bкк043A043A043A043A043A043A043A = 27;
      b043Aк043A043A043A043A043A043A043A = 72;
      i = 0;
    }
    for (;;)
    {
      if (i < j)
      {
        arrayOfIiiioo[i].b0430а0430а043004300430ааа(paramInt, paramThrowable);
        if ((bааа04300430а0430ааа() + bк043A043A043A043A043A043A043A043A) * bааа04300430а0430ааа() % b041FПППППППП != b043Aк043A043A043A043A043A043A043A)
        {
          bкк043A043A043A043A043A043A043A = 21;
          b043Aк043A043A043A043A043A043A043A = 40;
        }
        i += 1;
      }
      else
      {
        switch (0)
        {
        case 1: 
        default: 
          for (;;)
          {
            switch (1)
            {
            }
          }
        }
        return;
        i = 0;
      }
    }
  }
}
