package kkkkkk;

public abstract class ovvoov<STATE extends vvovvo>
  implements ovovvo<STATE>, vvovov
{
  public static int b04490449044904490449щ0449щщ = 1;
  private static String b04490449щ04490449щ0449щщ;
  public static int b0449щщщщ04490449щщ = 0;
  public static int bщ0449044904490449щ0449щщ = 57;
  public static int bщщщщщ04490449щщ = 2;
  private voovvo b0449щ044904490449щ0449щщ;
  public STATE bщщ044904490449щ0449щщ = null;
  
  public ovvoov(String paramString)
  {
    b04490449щ04490449щ0449щщ = paramString;
  }
  
  public static int b0428042804280428ШШ04280428ШШ()
  {
    return 2;
  }
  
  public static int b0428Ш04280428ШШ04280428ШШ()
  {
    return 0;
  }
  
  public static int bШ042804280428ШШ04280428ШШ()
  {
    return 27;
  }
  
  public static int bШШШШ0428Ш04280428ШШ()
  {
    return 1;
  }
  
  public Runnable b042804280428Ш0428Ш04280428ШШ(ovvvvo paramOvvvvo, long paramLong)
  {
    return this.b0449щ044904490449щ0449щщ.bШШ04280428Ш042804280428ШШ(paramOvvvvo, paramLong);
  }
  
  public STATE b04280428Ш0428ШШ04280428ШШ()
  {
    switch (0)
    {
    case 1: 
    default: 
      for (;;)
      {
        switch (1)
        {
        }
      }
    }
    switch (0)
    {
    case 1: 
    default: 
      for (;;)
      {
        switch (1)
        {
        }
      }
    }
    int i = bщ0449044904490449щ0449щщ;
    switch (i * (b04490449044904490449щ0449щщ + i) % bщщщщщ04490449щщ)
    {
    default: 
      if ((bщ0449044904490449щ0449щщ + b04490449044904490449щ0449щщ) * bщ0449044904490449щ0449щщ % bщщщщщ04490449щщ != b0449щщщщ04490449щщ)
      {
        bщ0449044904490449щ0449щщ = bШ042804280428ШШ04280428ШШ();
        b0449щщщщ04490449щщ = 32;
      }
      bщ0449044904490449щ0449щщ = 58;
      b04490449044904490449щ0449щщ = bШ042804280428ШШ04280428ШШ();
    }
    return this.bщщ044904490449щ0449щщ;
  }
  
  /* Error */
  public void b04280428ШШ0428Ш04280428ШШ(STATE paramSTATE, ovvvvo paramOvvvvo)
  {
    // Byte code:
    //   0: aload_0
    //   1: aload_1
    //   2: invokevirtual 71	kkkkkk/ovvoov:bШ0428ШШ0428Ш04280428ШШ	(Lkkkkkk/vvovvo;)V
    //   5: invokestatic 61	kkkkkk/ovvoov:bШ042804280428ШШ04280428ШШ	()I
    //   8: istore_3
    //   9: getstatic 55	kkkkkk/ovvoov:b04490449044904490449щ0449щщ	I
    //   12: istore 4
    //   14: invokestatic 61	kkkkkk/ovvoov:bШ042804280428ШШ04280428ШШ	()I
    //   17: istore 5
    //   19: getstatic 57	kkkkkk/ovvoov:bщщщщщ04490449щщ	I
    //   22: istore 6
    //   24: getstatic 59	kkkkkk/ovvoov:b0449щщщщ04490449щщ	I
    //   27: istore 7
    //   29: getstatic 53	kkkkkk/ovvoov:bщ0449044904490449щ0449щщ	I
    //   32: istore 8
    //   34: iload 8
    //   36: invokestatic 73	kkkkkk/ovvoov:bШШШШ0428Ш04280428ШШ	()I
    //   39: iload 8
    //   41: iadd
    //   42: imul
    //   43: getstatic 57	kkkkkk/ovvoov:bщщщщщ04490449щщ	I
    //   46: irem
    //   47: tableswitch	default:+17->64, 0:+29->76
    //   64: invokestatic 61	kkkkkk/ovvoov:bШ042804280428ШШ04280428ШШ	()I
    //   67: putstatic 53	kkkkkk/ovvoov:bщ0449044904490449щ0449щщ	I
    //   70: invokestatic 61	kkkkkk/ovvoov:bШ042804280428ШШ04280428ШШ	()I
    //   73: putstatic 59	kkkkkk/ovvoov:b0449щщщщ04490449щщ	I
    //   76: iload_3
    //   77: iload 4
    //   79: iadd
    //   80: iload 5
    //   82: imul
    //   83: iload 6
    //   85: irem
    //   86: iload 7
    //   88: if_icmpeq +15 -> 103
    //   91: invokestatic 61	kkkkkk/ovvoov:bШ042804280428ШШ04280428ШШ	()I
    //   94: putstatic 53	kkkkkk/ovvoov:bщ0449044904490449щ0449щщ	I
    //   97: invokestatic 61	kkkkkk/ovvoov:bШ042804280428ШШ04280428ШШ	()I
    //   100: putstatic 59	kkkkkk/ovvoov:b0449щщщщ04490449щщ	I
    //   103: aload_0
    //   104: aload_2
    //   105: invokevirtual 77	kkkkkk/ovvoov:bШШ04280428ШШ04280428ШШ	(Lkkkkkk/ovvvvo;)V
    //   108: return
    //   109: astore_1
    //   110: aload_1
    //   111: athrow
    //   112: astore_1
    //   113: aload_1
    //   114: athrow
    // Local variable table:
    //   start	length	slot	name	signature
    //   0	115	0	this	ovvoov
    //   0	115	1	paramSTATE	STATE
    //   0	115	2	paramOvvvvo	ovvvvo
    //   8	72	3	i	int
    //   12	68	4	j	int
    //   17	66	5	k	int
    //   22	64	6	m	int
    //   27	62	7	n	int
    //   32	11	8	i1	int
    // Exception table:
    //   from	to	target	type
    //   19	24	109	java/lang/Exception
    //   103	108	109	java/lang/Exception
    //   0	19	112	java/lang/Exception
    //   24	29	112	java/lang/Exception
    //   91	103	112	java/lang/Exception
  }
  
  public void b0428Ш0428Ш0428Ш04280428ШШ(STATE paramSTATE)
  {
    switch (1)
    {
    case 0: 
    default: 
      for (;;)
      {
        switch (1)
        {
        case 0: 
        default: 
          for (;;)
          {
            switch (0)
            {
            }
          }
        }
        switch (1)
        {
        }
      }
    }
    if ((bШ042804280428ШШ04280428ШШ() + b04490449044904490449щ0449щщ) * bШ042804280428ШШ04280428ШШ() % b0428042804280428ШШ04280428ШШ() != b0449щщщщ04490449щщ)
    {
      bщ0449044904490449щ0449щщ = 50;
      b0449щщщщ04490449щщ = 53;
    }
    if ((bщ0449044904490449щ0449щщ + b04490449044904490449щ0449щщ) * bщ0449044904490449щ0449щщ % bщщщщщ04490449щщ != b0449щщщщ04490449щщ)
    {
      bщ0449044904490449щ0449щщ = 70;
      b0449щщщщ04490449щщ = 85;
    }
    this.bщщ044904490449щ0449щщ = paramSTATE;
  }
  
  public void b0428ШШ04280428Ш04280428ШШ(voovvo paramVoovvo)
  {
    try
    {
      this.b0449щ044904490449щ0449щщ = paramVoovvo;
      return;
    }
    catch (Exception paramVoovvo)
    {
      throw paramVoovvo;
    }
  }
  
  public void b0428ШШШ0428Ш04280428ШШ(Runnable paramRunnable)
  {
    voovvo localVoovvo = this.b0449щ044904490449щ0449щщ;
    switch (1)
    {
    case 0: 
    default: 
      for (;;)
      {
        switch (1)
        {
        case 0: 
        default: 
          for (;;)
          {
            switch (1)
            {
            }
          }
        }
        switch (1)
        {
        }
      }
    }
    if ((bщ0449044904490449щ0449щщ + b04490449044904490449щ0449щщ) * bщ0449044904490449щ0449щщ % bщщщщщ04490449щщ != b0449щщщщ04490449щщ)
    {
      bщ0449044904490449щ0449щщ = bШ042804280428ШШ04280428ШШ();
      b0449щщщщ04490449щщ = 22;
    }
    localVoovvo.bШШШ0428Ш042804280428ШШ(paramRunnable);
    int i = bщ0449044904490449щ0449щщ;
    switch (i * (b04490449044904490449щ0449щщ + i) % bщщщщщ04490449щщ)
    {
    default: 
      bщ0449044904490449щ0449щщ = 30;
      b0449щщщщ04490449щщ = bШ042804280428ШШ04280428ШШ();
    }
  }
  
  public void b0445ххх0445хх044504450445()
  {
    int i = bШ042804280428ШШ04280428ШШ();
    switch (i * (b04490449044904490449щ0449щщ + i) % bщщщщщ04490449щщ)
    {
    default: 
      bщ0449044904490449щ0449щщ = bШ042804280428ШШ04280428ШШ();
      b0449щщщщ04490449щщ = bШ042804280428ШШ04280428ШШ();
    }
    switch (1)
    {
    case 0: 
    default: 
      for (;;)
      {
        switch (1)
        {
        }
      }
    }
    this.b0449щ044904490449щ0449щщ.b0428Ш04280428Ш042804280428ШШ();
  }
  
  public boolean bШ04280428Ш0428Ш04280428ШШ()
  {
    switch (0)
    {
    case 1: 
    default: 
      for (;;)
      {
        switch (1)
        {
        }
      }
    }
    if ((bщ0449044904490449щ0449щщ + b04490449044904490449щ0449щщ) * bщ0449044904490449щ0449щщ % bщщщщщ04490449щщ != b0449щщщщ04490449щщ)
    {
      bщ0449044904490449щ0449щщ = 54;
      b0449щщщщ04490449щщ = bШ042804280428ШШ04280428ШШ();
    }
    try
    {
      boolean bool = this.b0449щ044904490449щ0449щщ.b0428ШШ0428Ш042804280428ШШ();
      int i = bщ0449044904490449щ0449щщ;
      switch (i * (b04490449044904490449щ0449щщ + i) % bщщщщщ04490449щщ)
      {
      default: 
        bщ0449044904490449щ0449щщ = bШ042804280428ШШ04280428ШШ();
        b0449щщщщ04490449щщ = bШ042804280428ШШ04280428ШШ();
      }
      return bool;
    }
    catch (Exception localException)
    {
      throw localException;
    }
  }
  
  public void bШ0428ШШ0428Ш04280428ШШ(STATE paramSTATE)
  {
    this.bщщ044904490449щ0449щщ.b0428042804280428042804280428ШШШ();
    String str = b04490449щ04490449щ0449щщ;
    StringBuilder localStringBuilder = new StringBuilder();
    switch (0)
    {
    case 1: 
    default: 
      for (;;)
      {
        switch (0)
        {
        }
      }
    }
    xtxtxt.bии0438и04380438и0438ии(str, this.bщщ044904490449щ0449щщ + gguuuu.bккккк043Aкк043A043A(")5E&", 'º', '\003') + paramSTATE);
    this.bщщ044904490449щ0449щщ = paramSTATE;
    this.bщщ044904490449щ0449щщ.bШ042804280428042804280428ШШШ();
    int i = bШ042804280428ШШ04280428ШШ();
    int j = b04490449044904490449щ0449щщ;
    int k = bщщщщщ04490449щщ;
    int m = bщ0449044904490449щ0449щщ;
    switch (m * (b04490449044904490449щ0449щщ + m) % bщщщщщ04490449щщ)
    {
    default: 
      bщ0449044904490449щ0449щщ = 21;
      b0449щщщщ04490449щщ = bШ042804280428ШШ04280428ШШ();
    }
    switch (i * (j + i) % k)
    {
    default: 
      bщ0449044904490449щ0449щщ = bШ042804280428ШШ04280428ШШ();
      b0449щщщщ04490449щщ = bШ042804280428ШШ04280428ШШ();
    }
  }
  
  public void bШШ04280428ШШ04280428ШШ(ovvvvo paramOvvvvo)
  {
    String str1 = b04490449щ04490449щ0449щщ;
    StringBuilder localStringBuilder = new StringBuilder().append(b04280428Ш0428ШШ04280428ШШ().toString());
    if ((bщ0449044904490449щ0449щщ + b04490449044904490449щ0449щщ) * bщ0449044904490449щ0449щщ % b0428042804280428ШШ04280428ШШ() != b0449щщщщ04490449щщ)
    {
      bщ0449044904490449щ0449щщ = 18;
      b0449щщщщ04490449щщ = bШ042804280428ШШ04280428ШШ();
      int i = bщ0449044904490449щ0449щщ;
      switch (i * (b04490449044904490449щ0449щщ + i) % bщщщщщ04490449щщ)
      {
      default: 
        bщ0449044904490449щ0449щщ = 67;
        b0449щщщщ04490449щщ = 34;
      }
    }
    String str2 = gguuuu.bк043Aккк043Aкк043A043A("$A3C5)", '', '\t', '\001');
    switch (1)
    {
    case 0: 
    default: 
      for (;;)
      {
        switch (0)
        {
        }
      }
    }
    xtxtxt.bии0438и04380438и0438ии(str1, str2 + paramOvvvvo.toString());
    paramOvvvvo.b04280428Ш0428Ш0428Ш0428ШШ(b04280428Ш0428ШШ04280428ШШ());
  }
  
  public String bШШ0428Ш0428Ш04280428ШШ()
  {
    String str = b04490449щ04490449щ0449щщ;
    switch (1)
    {
    case 0: 
    default: 
      for (;;)
      {
        switch (1)
        {
        }
      }
    }
    if ((bщ0449044904490449щ0449щщ + b04490449044904490449щ0449щщ) * bщ0449044904490449щ0449щщ % bщщщщщ04490449щщ != b0428Ш04280428ШШ04280428ШШ())
    {
      if ((bщ0449044904490449щ0449щщ + bШШШШ0428Ш04280428ШШ()) * bщ0449044904490449щ0449щщ % bщщщщщ04490449щщ != b0428Ш04280428ШШ04280428ШШ())
      {
        bщ0449044904490449щ0449щщ = 34;
        b0449щщщщ04490449щщ = bШ042804280428ШШ04280428ШШ();
      }
      bщ0449044904490449щ0449щщ = 35;
      switch (0)
      {
      case 1: 
      default: 
        for (;;)
        {
          switch (1)
          {
          }
        }
      }
      b0449щщщщ04490449щщ = 41;
    }
    return str;
  }
  
  /* Error */
  public void bШШШ04280428Ш04280428ШШ(ovvvvo paramOvvvvo)
  {
    // Byte code:
    //   0: getstatic 53	kkkkkk/ovvoov:bщ0449044904490449щ0449щщ	I
    //   3: istore_2
    //   4: getstatic 55	kkkkkk/ovvoov:b04490449044904490449щ0449щщ	I
    //   7: istore_3
    //   8: getstatic 53	kkkkkk/ovvoov:bщ0449044904490449щ0449щщ	I
    //   11: istore 4
    //   13: getstatic 57	kkkkkk/ovvoov:bщщщщщ04490449щщ	I
    //   16: istore 5
    //   18: getstatic 59	kkkkkk/ovvoov:b0449щщщщ04490449щщ	I
    //   21: istore 6
    //   23: iload_2
    //   24: iload_3
    //   25: iadd
    //   26: iload 4
    //   28: imul
    //   29: iload 5
    //   31: irem
    //   32: iload 6
    //   34: if_icmpeq +61 -> 95
    //   37: getstatic 53	kkkkkk/ovvoov:bщ0449044904490449щ0449щщ	I
    //   40: istore_2
    //   41: iload_2
    //   42: getstatic 55	kkkkkk/ovvoov:b04490449044904490449щ0449щщ	I
    //   45: iload_2
    //   46: iadd
    //   47: imul
    //   48: getstatic 57	kkkkkk/ovvoov:bщщщщщ04490449щщ	I
    //   51: irem
    //   52: tableswitch	default:+20->72, 0:+32->84
    //   72: invokestatic 61	kkkkkk/ovvoov:bШ042804280428ШШ04280428ШШ	()I
    //   75: putstatic 53	kkkkkk/ovvoov:bщ0449044904490449щ0449щщ	I
    //   78: invokestatic 61	kkkkkk/ovvoov:bШ042804280428ШШ04280428ШШ	()I
    //   81: putstatic 59	kkkkkk/ovvoov:b0449щщщщ04490449щщ	I
    //   84: invokestatic 61	kkkkkk/ovvoov:bШ042804280428ШШ04280428ШШ	()I
    //   87: putstatic 53	kkkkkk/ovvoov:bщ0449044904490449щ0449щщ	I
    //   90: bipush 39
    //   92: putstatic 59	kkkkkk/ovvoov:b0449щщщщ04490449щщ	I
    //   95: aload_0
    //   96: getfield 44	kkkkkk/ovvoov:b0449щ044904490449щ0449щщ	Lkkkkkk/voovvo;
    //   99: aload_1
    //   100: invokeinterface 155 2 0
    //   105: return
    //   106: astore_1
    //   107: aload_1
    //   108: athrow
    //   109: astore_1
    //   110: aload_1
    //   111: athrow
    // Local variable table:
    //   start	length	slot	name	signature
    //   0	112	0	this	ovvoov
    //   0	112	1	paramOvvvvo	ovvvvo
    //   3	45	2	i	int
    //   7	19	3	j	int
    //   11	18	4	k	int
    //   16	16	5	m	int
    //   21	14	6	n	int
    // Exception table:
    //   from	to	target	type
    //   18	23	106	java/lang/Exception
    //   95	105	106	java/lang/Exception
    //   0	18	109	java/lang/Exception
    //   84	95	109	java/lang/Exception
  }
}
