package kkkkkk;

public class ovvvvv
  extends ovvoov
{
  private static final String b04410441с0441с0441044104410441;
  public static int b04410441сс04410441044104410441 = 2;
  public static int b0441ссс04410441044104410441 = 34;
  public static int bс0441сс04410441044104410441 = 1;
  public static int bсс0441с04410441044104410441;
  private final voovvv b0441044104410441с0441044104410441 = new voovvv(gguuuu.bк043Aккк043Aкк043A043A("r\025\f\023\030\026", 'u', '\034', '\000'), b04410441с0441с0441044104410441);
  private final vvovvv b0441с04410441с0441044104410441 = new vvovvv(gguuuu.bк043Aккк043Aкк043A043A(")OKWMFRPbNN", '', 'Ð', '\003'), b04410441с0441с0441044104410441);
  private final ovovvv bс044104410441с0441044104410441 = new ovovvv(gguuuu.bккккк043Aкк043A043A("Hlfpd[eaq_c[", '\001', '\005'), b04410441с0441с0441044104410441);
  private final vovvvv bсс04410441с0441044104410441 = new vovvvv(gguuuu.bккккк043Aкк043A043A("[u|ta\002mo", 'õ', '\003'), b04410441с0441с0441044104410441 + gguuuu.bк043Aккк043Aкк043A043A("\026\001\035& ", '', '­', '\003'));
  private final ovvovv bсссс04410441044104410441 = new ovvovv(gguuuu.bккккк043Aкк043A043A("h|\t\007\006y}uQ{\003x", '÷', '\002'), b04410441с0441с0441044104410441);
  
  static
  {
    String str = ovvvvv.class.getSimpleName();
    switch (0)
    {
    case 1: 
    default: 
      for (;;)
      {
        switch (1)
        {
        }
      }
    }
    int i = b0441ссс04410441044104410441;
    switch (i * (bс0441сс04410441044104410441 + i) % b04410441сс04410441044104410441)
    {
    default: 
      b0441ссс04410441044104410441 = 5;
      bс0441сс04410441044104410441 = 17;
    }
    b04410441с0441с0441044104410441 = str;
    i = b0441ссс04410441044104410441;
    switch (i * (bШ04280428ШШ0428Ш0428ШШ() + i) % b04410441сс04410441044104410441)
    {
    default: 
      b0441ссс04410441044104410441 = b0428Ш0428ШШ0428Ш0428ШШ();
      bс0441сс04410441044104410441 = b0428Ш0428ШШ0428Ш0428ШШ();
    }
  }
  
  public ovvvvv()
  {
    super(b04410441с0441с0441044104410441);
    b0428Ш0428Ш0428Ш04280428ШШ(this.bсс04410441с0441044104410441);
  }
  
  public static int b0428Ш0428ШШ0428Ш0428ШШ()
  {
    return 97;
  }
  
  public static int bШ04280428ШШ0428Ш0428ШШ()
  {
    return 1;
  }
  
  public static int bШШ0428ШШ0428Ш0428ШШ()
  {
    return 0;
  }
  
  public void b042804280428ШШ0428Ш0428ШШ(vovoov paramVovoov)
  {
    switch (0)
    {
    case 1: 
    default: 
      for (;;)
      {
        switch (0)
        {
        }
      }
    }
    if (paramVovoov == null)
    {
      xtxtxt.b0438и0438и04380438и0438ии(b04410441с0441с0441044104410441, gguuuu.bккккк043Aкк043A043A("\025\022 s\030\022\034v\030\024\007\b\025\024GG=\006\017:\b\016\004\003653w\004\003~\001.", 'p', '\002'));
      i = b0441ссс04410441044104410441;
      switch (i * (bс0441сс04410441044104410441 + i) % b04410441сс04410441044104410441)
      {
      default: 
        b0441ссс04410441044104410441 = b0428Ш0428ШШ0428Ш0428ШШ();
        bсс0441с04410441044104410441 = b0428Ш0428ШШ0428Ш0428ШШ();
      }
      return;
    }
    int i = b0428Ш0428ШШ0428Ш0428ШШ();
    switch (i * (bс0441сс04410441044104410441 + i) % b04410441сс04410441044104410441)
    {
    default: 
      b0441ссс04410441044104410441 = 61;
      bсс0441с04410441044104410441 = b0428Ш0428ШШ0428Ш0428ШШ();
    }
    bШШШ04280428Ш04280428ШШ(new oovovv(paramVovoov));
  }
  
  public void b0428ШШ0428Ш0428Ш0428ШШ(vvooov paramVvooov)
  {
    int i = b0441ссс04410441044104410441;
    switch (i * (bс0441сс04410441044104410441 + i) % b04410441сс04410441044104410441)
    {
    default: 
      b0441ссс04410441044104410441 = b0428Ш0428ШШ0428Ш0428ШШ();
      bсс0441с04410441044104410441 = 43;
    }
    if (paramVvooov == null) {}
    do
    {
      try
      {
        paramVvooov = b04410441с0441с0441044104410441;
      }
      catch (Exception paramVvooov)
      {
        throw paramVvooov;
      }
      try
      {
        xtxtxt.b0438и0438и04380438и0438ии(paramVvooov, gguuuu.bккккк043Aкк043A043A("AC:AFD\037@</0=<g09d28.-`_]\".-)+X", 'ª', '\005'));
        return;
      }
      catch (Exception paramVvooov)
      {
        throw paramVvooov;
      }
      paramVvooov = new vvoovv(paramVvooov);
      bШШШ04280428Ш04280428ШШ(paramVvooov);
    } while ((b0441ссс04410441044104410441 + bШ04280428ШШ0428Ш0428ШШ()) * b0441ссс04410441044104410441 % b04410441сс04410441044104410441 == bсс0441с04410441044104410441);
    b0441ссс04410441044104410441 = b0428Ш0428ШШ0428Ш0428ШШ();
    bсс0441с04410441044104410441 = 15;
  }
  
  public void bШ0428Ш0428Ш0428Ш0428ШШ(ovooov paramOvooov)
  {
    int i = b0441ссс04410441044104410441;
    switch (i * (bШ04280428ШШ0428Ш0428ШШ() + i) % b04410441сс04410441044104410441)
    {
    default: 
      b0441ссс04410441044104410441 = 77;
      bсс0441с04410441044104410441 = 95;
    }
    if (paramOvooov == null)
    {
      xtxtxt.b0438и0438и04380438и0438ии(b04410441с0441с0441044104410441, gguuuu.bк043Aккк043Aкк043A043A("gdrFjdnIjfYZgf\032\032\020Xa\rZ`VU\t\b\006JVUQS\001", '\024', 'k', '\002'));
      return;
    }
    bШШШ04280428Ш04280428ШШ(new oooovv(paramOvooov));
  }
  
  /* Error */
  public boolean bШШШ0428Ш0428Ш0428ШШ()
  {
    // Byte code:
    //   0: aload_0
    //   1: invokevirtual 190	kkkkkk/ovvvvv:b04280428Ш0428ШШ04280428ШШ	()Lkkkkkk/vvovvo;
    //   4: ifnull +77 -> 81
    //   7: aload_0
    //   8: invokevirtual 190	kkkkkk/ovvvvv:b04280428Ш0428ШШ04280428ШШ	()Lkkkkkk/vvovvo;
    //   11: aload_0
    //   12: getfield 114	kkkkkk/ovvvvv:b0441с04410441с0441044104410441	Lkkkkkk/ovvvvv$vvovvv;
    //   15: invokevirtual 196	java/lang/Object:equals	(Ljava/lang/Object;)Z
    //   18: istore 4
    //   20: iload 4
    //   22: ifeq +59 -> 81
    //   25: getstatic 61	kkkkkk/ovvvvv:b0441ссс04410441044104410441	I
    //   28: istore_1
    //   29: invokestatic 71	kkkkkk/ovvvvv:bШ04280428ШШ0428Ш0428ШШ	()I
    //   32: istore_2
    //   33: getstatic 65	kkkkkk/ovvvvv:b04410441сс04410441044104410441	I
    //   36: istore_3
    //   37: iload_1
    //   38: iload_2
    //   39: iload_1
    //   40: iadd
    //   41: imul
    //   42: iload_3
    //   43: irem
    //   44: tableswitch	default:+20->64, 0:+31->75
    //   64: invokestatic 74	kkkkkk/ovvvvv:b0428Ш0428ШШ0428Ш0428ШШ	()I
    //   67: putstatic 61	kkkkkk/ovvvvv:b0441ссс04410441044104410441	I
    //   70: bipush 78
    //   72: putstatic 141	kkkkkk/ovvvvv:bсс0441с04410441044104410441	I
    //   75: iconst_1
    //   76: istore 4
    //   78: iload 4
    //   80: ireturn
    //   81: iconst_0
    //   82: istore 4
    //   84: getstatic 61	kkkkkk/ovvvvv:b0441ссс04410441044104410441	I
    //   87: istore_1
    //   88: iload_1
    //   89: getstatic 63	kkkkkk/ovvvvv:bс0441сс04410441044104410441	I
    //   92: iload_1
    //   93: iadd
    //   94: imul
    //   95: getstatic 65	kkkkkk/ovvvvv:b04410441сс04410441044104410441	I
    //   98: irem
    //   99: tableswitch	default:+17->116, 0:+-21->78
    //   116: invokestatic 74	kkkkkk/ovvvvv:b0428Ш0428ШШ0428Ш0428ШШ	()I
    //   119: putstatic 61	kkkkkk/ovvvvv:b0441ссс04410441044104410441	I
    //   122: invokestatic 74	kkkkkk/ovvvvv:b0428Ш0428ШШ0428Ш0428ШШ	()I
    //   125: putstatic 141	kkkkkk/ovvvvv:bсс0441с04410441044104410441	I
    //   128: iconst_0
    //   129: ireturn
    //   130: astore 5
    //   132: aload 5
    //   134: athrow
    //   135: astore 5
    //   137: aload 5
    //   139: athrow
    //   140: astore 5
    //   142: aload 5
    //   144: athrow
    // Local variable table:
    //   start	length	slot	name	signature
    //   0	145	0	this	ovvvvv
    //   28	67	1	i	int
    //   32	9	2	j	int
    //   36	8	3	k	int
    //   18	65	4	bool	boolean
    //   130	3	5	localException1	Exception
    //   135	3	5	localException2	Exception
    //   140	3	5	localException3	Exception
    // Exception table:
    //   from	to	target	type
    //   0	20	130	java/lang/Exception
    //   64	75	135	java/lang/Exception
    //   132	135	135	java/lang/Exception
    //   25	37	140	java/lang/Exception
  }
  
  public abstract class oovvvv
    extends rmmmmm
  {
    public static int b0441с0441044104410441044104410441 = 1;
    public static int b0449щщщщщщщщ = 0;
    public static int bс04410441044104410441044104410441 = 2;
    public static int bсс0441044104410441044104410441 = 33;
    public vvoovv bс0441с044104410441044104410441 = null;
    
    public oovvvv(String paramString1, String paramString2)
    {
      super(paramString2);
    }
    
    public static int b04280428Ш0428ШШШ0428ШШ()
    {
      return 92;
    }
    
    public static int bШ0428Ш0428ШШШ0428ШШ()
    {
      return 2;
    }
    
    /* Error */
    public void b042804280428ШШШШ0428ШШ(oooovv paramOooovv)
    {
      // Byte code:
      //   0: aload_0
      //   1: getfield 29	kkkkkk/ovvvvv$oovvvv:bс0441с044104410441044104410441	Lkkkkkk/vvoovv;
      //   4: astore_1
      //   5: getstatic 39	kkkkkk/ovvvvv$oovvvv:bсс0441044104410441044104410441	I
      //   8: getstatic 41	kkkkkk/ovvvvv$oovvvv:b0441с0441044104410441044104410441	I
      //   11: iadd
      //   12: getstatic 39	kkkkkk/ovvvvv$oovvvv:bсс0441044104410441044104410441	I
      //   15: imul
      //   16: getstatic 43	kkkkkk/ovvvvv$oovvvv:bс04410441044104410441044104410441	I
      //   19: irem
      //   20: getstatic 45	kkkkkk/ovvvvv$oovvvv:b0449щщщщщщщщ	I
      //   23: if_icmpeq +14 -> 37
      //   26: invokestatic 47	kkkkkk/ovvvvv$oovvvv:b04280428Ш0428ШШШ0428ШШ	()I
      //   29: putstatic 39	kkkkkk/ovvvvv$oovvvv:bсс0441044104410441044104410441	I
      //   32: bipush 41
      //   34: putstatic 45	kkkkkk/ovvvvv$oovvvv:b0449щщщщщщщщ	I
      //   37: aload_1
      //   38: ifnull +28 -> 66
      //   41: aload_0
      //   42: getfield 29	kkkkkk/ovvvvv$oovvvv:bс0441с044104410441044104410441	Lkkkkkk/vvoovv;
      //   45: aconst_null
      //   46: invokevirtual 53	kkkkkk/vvoovv:bШШ0428Ш04280428Ш0428ШШ	(Lkkkkkk/oovovv;)V
      //   49: aload_0
      //   50: getfield 57	kkkkkk/ovvvvv$oovvvv:b0441с0441сс0441044104410441	Ljava/lang/String;
      //   53: astore_1
      //   54: aload_1
      //   55: ldc 59
      //   57: bipush 92
      //   59: iconst_1
      //   60: invokestatic 65	kkkkkk/gguuuu:bккккк043Aкк043A043A	(Ljava/lang/String;CC)Ljava/lang/String;
      //   63: invokestatic 70	kkkkkk/xtxtxt:bии0438и04380438и0438ии	(Ljava/lang/String;Ljava/lang/String;)V
      //   66: return
      //   67: astore_1
      //   68: aload_1
      //   69: athrow
      //   70: astore_1
      //   71: aload_1
      //   72: athrow
      // Local variable table:
      //   start	length	slot	name	signature
      //   0	73	0	this	oovvvv
      //   0	73	1	paramOooovv	oooovv
      // Exception table:
      //   from	to	target	type
      //   0	5	67	java/lang/Exception
      //   41	54	67	java/lang/Exception
      //   54	66	70	java/lang/Exception
    }
    
    public void b04280428ШШШШШ0428ШШ(oovovv paramOovovv)
    {
      if (this.bс0441с044104410441044104410441 != null)
      {
        this.bс0441с044104410441044104410441.bШШ0428Ш04280428Ш0428ШШ(paramOovovv);
        xtxtxt.bии0438и04380438и0438ии(this.b0441с0441сс0441044104410441, gguuuu.bк043Aккк043Aкк043A043A(" D=FMMy@RBLSXCLXNTN\024\tSYUa\016PVeWe\024ae^gnn\033ep\036MOU\"qyqr'", 'Z', '', '\001'));
      }
    }
    
    public void bШ042804280428042804280428ШШШ()
    {
      try
      {
        this.bс0441с044104410441044104410441 = null;
        return;
      }
      catch (Exception localException)
      {
        throw localException;
      }
    }
    
    public void bШШ0428ШШШШ0428ШШ(vvoovv paramVvoovv)
    {
      this.bс0441с044104410441044104410441 = paramVvoovv;
      this.bс0441с044104410441044104410441.bШШ0428Ш04280428Ш0428ШШ(null);
      paramVvoovv = this.b0441с0441сс0441044104410441;
      if ((bсс0441044104410441044104410441 + b0441с0441044104410441044104410441) * bсс0441044104410441044104410441 % bс04410441044104410441044104410441 != b0449щщщщщщщщ)
      {
        bсс0441044104410441044104410441 = b04280428Ш0428ШШШ0428ШШ();
        b0449щщщщщщщщ = 55;
      }
      xtxtxt.bии0438и04380438и0438ии(paramVvoovv, gguuuu.bккккк043Aкк043A043A("u\030\017\026\033\031C\b\030\006\016\023=\024|\004\016\002\006}A4|\001z\005/os\001p|)tvmtyw\"js\037lrhg\032", 'G', '\002'));
    }
  }
  
  public class ovovvv
    extends ovvvvv.oovvvv
  {
    public static int b04490449щ0449щщщщщ = 0;
    public static int b0449щщ0449щщщщщ = 2;
    public static int bщ0449щ0449щщщщщ = 46;
    public static int bщщщ0449щщщщщ = 1;
    
    public ovovvv(String paramString1, String paramString2)
    {
      super(paramString1, paramString2);
    }
    
    public static int bШ042804280428ШШШ0428ШШ()
    {
      return 89;
    }
    
    /* Error */
    public void b04280428ШШШШШ0428ШШ(oovovv paramOovovv)
    {
      // Byte code:
      //   0: aload_1
      //   1: invokevirtual 37	kkkkkk/oovovv:bШ042804280428Ш0428Ш0428ШШ	()Lkkkkkk/vovoov;
      //   4: astore_3
      //   5: aload_3
      //   6: invokevirtual 43	kkkkkk/vovoov:b04450445х04450445хх044504450445	()V
      //   9: aload_0
      //   10: getfield 47	kkkkkk/ovvvvv$ovovvv:b0441с0441сс0441044104410441	Ljava/lang/String;
      //   13: ldc 49
      //   15: sipush 171
      //   18: bipush 86
      //   20: iconst_0
      //   21: invokestatic 55	kkkkkk/gguuuu:bк043Aккк043Aкк043A043A	(Ljava/lang/String;CCC)Ljava/lang/String;
      //   24: invokestatic 61	kkkkkk/xtxtxt:bии0438и04380438и0438ии	(Ljava/lang/String;Ljava/lang/String;)V
      //   27: aload_0
      //   28: getfield 22	kkkkkk/ovvvvv$ovovvv:b044904490449щщщщщщ	Lkkkkkk/ovvvvv;
      //   31: aload_0
      //   32: getfield 22	kkkkkk/ovvvvv$ovovvv:b044904490449щщщщщщ	Lkkkkkk/ovvvvv;
      //   35: invokestatic 65	kkkkkk/ovvvvv:b0428ШШШШ0428Ш0428ШШ	(Lkkkkkk/ovvvvv;)Lkkkkkk/ovvvvv$vvovvv;
      //   38: aload_1
      //   39: invokevirtual 69	kkkkkk/ovvvvv:b04280428ШШ0428Ш04280428ШШ	(Lkkkkkk/vvovvo;Lkkkkkk/ovvvvo;)V
      //   42: return
      //   43: astore_1
      //   44: aload_1
      //   45: invokevirtual 72	java/lang/Exception:printStackTrace	()V
      //   48: invokestatic 74	kkkkkk/ovvvvv$ovovvv:bШ042804280428ШШШ0428ШШ	()I
      //   51: istore_2
      //   52: iload_2
      //   53: getstatic 76	kkkkkk/ovvvvv$ovovvv:bщщщ0449щщщщщ	I
      //   56: iload_2
      //   57: iadd
      //   58: imul
      //   59: getstatic 78	kkkkkk/ovvvvv$ovovvv:b0449щщ0449щщщщщ	I
      //   62: irem
      //   63: tableswitch	default:+17->80, 0:+54->117
      //   80: invokestatic 74	kkkkkk/ovvvvv$ovovvv:bШ042804280428ШШШ0428ШШ	()I
      //   83: putstatic 76	kkkkkk/ovvvvv$ovovvv:bщщщ0449щщщщщ	I
      //   86: getstatic 80	kkkkkk/ovvvvv$ovovvv:bщ0449щ0449щщщщщ	I
      //   89: getstatic 76	kkkkkk/ovvvvv$ovovvv:bщщщ0449щщщщщ	I
      //   92: iadd
      //   93: getstatic 80	kkkkkk/ovvvvv$ovovvv:bщ0449щ0449щщщщщ	I
      //   96: imul
      //   97: getstatic 78	kkkkkk/ovvvvv$ovovvv:b0449щщ0449щщщщщ	I
      //   100: irem
      //   101: getstatic 82	kkkkkk/ovvvvv$ovovvv:b04490449щ0449щщщщщ	I
      //   104: if_icmpeq +13 -> 117
      //   107: bipush 90
      //   109: putstatic 80	kkkkkk/ovvvvv$ovovvv:bщ0449щ0449щщщщщ	I
      //   112: bipush 60
      //   114: putstatic 82	kkkkkk/ovvvvv$ovovvv:b04490449щ0449щщщщщ	I
      //   117: aload_3
      //   118: invokevirtual 86	kkkkkk/vovoov:bх0445х04450445хх044504450445	()Lkkkkkk/xdxxdx;
      //   121: aload_1
      //   122: invokeinterface 92 2 0
      //   127: aload_0
      //   128: getfield 22	kkkkkk/ovvvvv$ovovvv:b044904490449щщщщщщ	Lkkkkkk/ovvvvv;
      //   131: aload_0
      //   132: getfield 22	kkkkkk/ovvvvv$ovovvv:b044904490449щщщщщщ	Lkkkkkk/ovvvvv;
      //   135: invokestatic 96	kkkkkk/ovvvvv:bШ0428ШШШ0428Ш0428ШШ	(Lkkkkkk/ovvvvv;)Lkkkkkk/ovvvvv$vovvvv;
      //   138: invokevirtual 100	kkkkkk/ovvvvv:bШ0428ШШ0428Ш04280428ШШ	(Lkkkkkk/vvovvo;)V
      //   141: return
      //   142: astore_1
      //   143: aload_1
      //   144: athrow
      //   145: astore_1
      //   146: aload_1
      //   147: athrow
      // Local variable table:
      //   start	length	slot	name	signature
      //   0	148	0	this	ovovvv
      //   0	148	1	paramOovovv	oovovv
      //   51	8	2	i	int
      //   4	114	3	localVovoov	vovoov
      // Exception table:
      //   from	to	target	type
      //   5	42	43	java/lang/Exception
      //   0	5	142	java/lang/Exception
      //   117	141	142	java/lang/Exception
      //   44	48	145	java/lang/Exception
    }
  }
  
  public class ovvovv
    extends ovvvvv.oovvvv
  {
    public static int b04490449щщщ0449щщщ = 2;
    public static int b0449щщщщ0449щщщ = 0;
    public static int bщ0449щщщ0449щщщ = 1;
    public static int bщщщщщ0449щщщ = 77;
    private oovovv b0449щ044904490449щщщщ = null;
    private ovooov bщ0449044904490449щщщщ = null;
    
    public ovvovv(String paramString1, String paramString2)
    {
      super(paramString1, paramString2);
    }
    
    public static int b0428Ш042804280428ШШ0428ШШ()
    {
      return 24;
    }
    
    public static int bШ0428042804280428ШШ0428ШШ()
    {
      return 0;
    }
    
    public static int bШШ042804280428ШШ0428ШШ()
    {
      return 1;
    }
    
    /* Error */
    public void b042804280428ШШШШ0428ШШ(oooovv paramOooovv)
    {
      // Byte code:
      //   0: aload_0
      //   1: aload_1
      //   2: invokespecial 46	kkkkkk/ovvvvv$oovvvv:b042804280428ШШШШ0428ШШ	(Lkkkkkk/oooovv;)V
      //   5: aload_0
      //   6: getfield 33	kkkkkk/ovvvvv$ovvovv:bщ0449044904490449щщщщ	Lkkkkkk/ovooov;
      //   9: ifnonnull +27 -> 36
      //   12: aload_0
      //   13: aload_1
      //   14: invokevirtual 52	kkkkkk/oooovv:bШ04280428042804280428Ш0428ШШ	()Lkkkkkk/ovooov;
      //   17: putfield 33	kkkkkk/ovvvvv$ovvovv:bщ0449044904490449щщщщ	Lkkkkkk/ovooov;
      //   20: aload_0
      //   21: getfield 33	kkkkkk/ovvvvv$ovvovv:bщ0449044904490449щщщщ	Lkkkkkk/ovooov;
      //   24: new 9	kkkkkk/ovvvvv$ovvovv$1
      //   27: dup
      //   28: aload_0
      //   29: invokespecial 55	kkkkkk/ovvvvv$ovvovv$1:<init>	(Lkkkkkk/ovvvvv$ovvovv;)V
      //   32: invokevirtual 61	kkkkkk/ovooov:bхххх04450445х044504450445	(Lkkkkkk/voovov;)V
      //   35: return
      //   36: getstatic 63	kkkkkk/ovvvvv$ovvovv:bщщщщщ0449щщщ	I
      //   39: istore_2
      //   40: invokestatic 65	kkkkkk/ovvvvv$ovvovv:bШШ042804280428ШШ0428ШШ	()I
      //   43: istore_3
      //   44: getstatic 63	kkkkkk/ovvvvv$ovvovv:bщщщщщ0449щщщ	I
      //   47: istore 4
      //   49: getstatic 67	kkkkkk/ovvvvv$ovvovv:b04490449щщщ0449щщщ	I
      //   52: istore 5
      //   54: getstatic 69	kkkkkk/ovvvvv$ovvovv:b0449щщщщ0449щщщ	I
      //   57: istore 6
      //   59: iload_2
      //   60: iload_3
      //   61: iadd
      //   62: iload 4
      //   64: imul
      //   65: iload 5
      //   67: irem
      //   68: iload 6
      //   70: if_icmpeq +61 -> 131
      //   73: getstatic 63	kkkkkk/ovvvvv$ovvovv:bщщщщщ0449щщщ	I
      //   76: istore_2
      //   77: iload_2
      //   78: getstatic 71	kkkkkk/ovvvvv$ovvovv:bщ0449щщщ0449щщщ	I
      //   81: iload_2
      //   82: iadd
      //   83: imul
      //   84: getstatic 67	kkkkkk/ovvvvv$ovvovv:b04490449щщщ0449щщщ	I
      //   87: irem
      //   88: tableswitch	default:+20->108, 0:+30->118
      //   108: bipush 69
      //   110: putstatic 63	kkkkkk/ovvvvv$ovvovv:bщщщщщ0449щщщ	I
      //   113: bipush 23
      //   115: putstatic 69	kkkkkk/ovvvvv$ovvovv:b0449щщщщ0449щщщ	I
      //   118: bipush 11
      //   120: putstatic 63	kkkkkk/ovvvvv$ovvovv:bщщщщщ0449щщщ	I
      //   123: invokestatic 73	kkkkkk/ovvvvv$ovvovv:b0428Ш042804280428ШШ0428ШШ	()I
      //   126: istore_2
      //   127: iload_2
      //   128: putstatic 69	kkkkkk/ovvvvv$ovvovv:b0449щщщщ0449щщщ	I
      //   131: aload_0
      //   132: getfield 77	kkkkkk/ovvvvv$ovvovv:b0441с0441сс0441044104410441	Ljava/lang/String;
      //   135: astore_1
      //   136: aload_1
      //   137: ldc 79
      //   139: bipush 110
      //   141: bipush 103
      //   143: iconst_2
      //   144: invokestatic 85	kkkkkk/gguuuu:bк043Aккк043Aкк043A043A	(Ljava/lang/String;CCC)Ljava/lang/String;
      //   147: invokestatic 91	kkkkkk/xtxtxt:bии0438и04380438и0438ии	(Ljava/lang/String;Ljava/lang/String;)V
      //   150: aload_0
      //   151: aconst_null
      //   152: putfield 35	kkkkkk/ovvvvv$ovvovv:b0449щ044904490449щщщщ	Lkkkkkk/oovovv;
      //   155: return
      //   156: astore_1
      //   157: aload_1
      //   158: athrow
      //   159: astore_1
      //   160: aload_1
      //   161: athrow
      //   162: astore_1
      //   163: aload_1
      //   164: athrow
      //   165: astore_1
      //   166: aload_1
      //   167: athrow
      // Local variable table:
      //   start	length	slot	name	signature
      //   0	168	0	this	ovvovv
      //   0	168	1	paramOooovv	oooovv
      //   39	89	2	i	int
      //   43	19	3	j	int
      //   47	18	4	k	int
      //   52	16	5	m	int
      //   57	14	6	n	int
      // Exception table:
      //   from	to	target	type
      //   136	155	156	java/lang/Exception
      //   118	127	159	java/lang/Exception
      //   157	159	159	java/lang/Exception
      //   163	165	159	java/lang/Exception
      //   0	35	162	java/lang/Exception
      //   131	136	162	java/lang/Exception
      //   36	59	165	java/lang/Exception
      //   127	131	165	java/lang/Exception
    }
    
    public void b04280428ШШШШШ0428ШШ(oovovv paramOovovv)
    {
      throw new Runtime("d2j fail translate: java.lang.IndexOutOfBoundsException: fromIndex < 0: -1\n\tat java.util.BitSet.nextSetBit(BitSet.java:712)\n\tat com.googlecode.dex2jar.ir.ts.array.FillArrayTransformer.makeSureAllElementAreAssigned(FillArrayTransformer.java:505)\n\tat com.googlecode.dex2jar.ir.ts.array.FillArrayTransformer.transformReportChanged(FillArrayTransformer.java:123)\n\tat com.googlecode.dex2jar.ir.ts.StatedTransformer.transform(StatedTransformer.java:10)\n\tat com.googlecode.d2j.dex.Dex2jar$2.optimize(Dex2jar.java:149)\n\tat com.googlecode.d2j.dex.Dex2Asm.convertCode(Dex2Asm.java:414)\n\tat com.googlecode.d2j.dex.ExDex2Asm.convertCode(ExDex2Asm.java:42)\n\tat com.googlecode.d2j.dex.Dex2jar$2.convertCode(Dex2jar.java:128)\n\tat com.googlecode.d2j.dex.Dex2Asm.convertMethod(Dex2Asm.java:509)\n\tat com.googlecode.d2j.dex.Dex2Asm.convertClass(Dex2Asm.java:406)\n\tat com.googlecode.d2j.dex.Dex2Asm.convertDex(Dex2Asm.java:422)\n\tat com.googlecode.d2j.dex.Dex2jar.doTranslate(Dex2jar.java:172)\n\tat com.googlecode.d2j.dex.Dex2jar.to(Dex2jar.java:272)\n\tat com.googlecode.dex2jar.tools.Dex2jarCmd.doCommandLine(Dex2jarCmd.java:108)\n\tat com.googlecode.dex2jar.tools.BaseCmd.doMain(BaseCmd.java:288)\n\tat com.googlecode.dex2jar.tools.Dex2jarCmd.main(Dex2jarCmd.java:32)\n");
    }
    
    public void bШ042804280428042804280428ШШШ()
    {
      int i = bщщщщщ0449щщщ;
      int j = bщ0449щщщ0449щщщ;
      int k = bщщщщщ0449щщщ;
      switch (k * (bщ0449щщщ0449щщщ + k) % b04490449щщщ0449щщщ)
      {
      default: 
        bщщщщщ0449щщщ = b0428Ш042804280428ШШ0428ШШ();
        b0449щщщщ0449щщщ = 6;
      }
      if ((i + j) * bщщщщщ0449щщщ % b04490449щщщ0449щщщ != b0449щщщщ0449щщщ)
      {
        bщщщщщ0449щщщ = b0428Ш042804280428ШШ0428ШШ();
        b0449щщщщ0449щщщ = 91;
      }
      switch (0)
      {
      case 1: 
      default: 
        for (;;)
        {
          switch (1)
          {
          }
        }
      }
      super.bШ042804280428042804280428ШШШ();
      this.bщ0449044904490449щщщщ = null;
      this.b0449щ044904490449щщщщ = null;
    }
    
    /* Error */
    public void bШ04280428ШШШШ0428ШШ(vooovv paramVooovv)
    {
      // Byte code:
      //   0: aload_0
      //   1: getfield 77	kkkkkk/ovvvvv$ovvovv:b0441с0441сс0441044104410441	Ljava/lang/String;
      //   4: astore_1
      //   5: aload_1
      //   6: ldc 110
      //   8: iconst_1
      //   9: bipush 60
      //   11: iconst_0
      //   12: invokestatic 85	kkkkkk/gguuuu:bк043Aккк043Aкк043A043A	(Ljava/lang/String;CCC)Ljava/lang/String;
      //   15: invokestatic 91	kkkkkk/xtxtxt:bии0438и04380438и0438ии	(Ljava/lang/String;Ljava/lang/String;)V
      //   18: aload_0
      //   19: getfield 33	kkkkkk/ovvvvv$ovvovv:bщ0449044904490449щщщщ	Lkkkkkk/ovooov;
      //   22: astore_1
      //   23: aload_1
      //   24: invokevirtual 114	kkkkkk/ovooov:bШШШШШ042804280428ШШ	()Lkkkkkk/xxxxdx;
      //   27: invokeinterface 119 1 0
      //   32: aload_0
      //   33: getfield 123	kkkkkk/ovvvvv$ovvovv:bс0441с044104410441044104410441	Lkkkkkk/vvoovv;
      //   36: ifnull +90 -> 126
      //   39: aload_0
      //   40: getfield 77	kkkkkk/ovvvvv$ovvovv:b0441с0441сс0441044104410441	Ljava/lang/String;
      //   43: astore_1
      //   44: ldc 125
      //   46: bipush 43
      //   48: bipush 89
      //   50: iconst_3
      //   51: invokestatic 85	kkkkkk/gguuuu:bк043Aккк043Aкк043A043A	(Ljava/lang/String;CCC)Ljava/lang/String;
      //   54: astore 7
      //   56: aload_1
      //   57: aload 7
      //   59: invokestatic 91	kkkkkk/xtxtxt:bии0438и04380438и0438ии	(Ljava/lang/String;Ljava/lang/String;)V
      //   62: getstatic 63	kkkkkk/ovvvvv$ovvovv:bщщщщщ0449щщщ	I
      //   65: istore_2
      //   66: iload_2
      //   67: getstatic 71	kkkkkk/ovvvvv$ovvovv:bщ0449щщщ0449щщщ	I
      //   70: iload_2
      //   71: iadd
      //   72: imul
      //   73: getstatic 67	kkkkkk/ovvvvv$ovvovv:b04490449щщщ0449щщщ	I
      //   76: irem
      //   77: tableswitch	default:+19->96, 0:+30->107
      //   96: invokestatic 73	kkkkkk/ovvvvv$ovvovv:b0428Ш042804280428ШШ0428ШШ	()I
      //   99: putstatic 63	kkkkkk/ovvvvv$ovvovv:bщщщщщ0449щщщ	I
      //   102: bipush 65
      //   104: putstatic 69	kkkkkk/ovvvvv$ovvovv:b0449щщщщ0449щщщ	I
      //   107: aload_0
      //   108: getfield 29	kkkkkk/ovvvvv$ovvovv:b04490449044904490449щщщщ	Lkkkkkk/ovvvvv;
      //   111: aload_0
      //   112: getfield 29	kkkkkk/ovvvvv$ovvovv:b04490449044904490449щщщщ	Lkkkkkk/ovvvvv;
      //   115: invokestatic 129	kkkkkk/ovvvvv:bШШШШШ0428Ш0428ШШ	(Lkkkkkk/ovvvvv;)Lkkkkkk/ovvvvv$voovvv;
      //   118: aload_0
      //   119: getfield 123	kkkkkk/ovvvvv$ovvovv:bс0441с044104410441044104410441	Lkkkkkk/vvoovv;
      //   122: invokevirtual 133	kkkkkk/ovvvvv:b04280428ШШ0428Ш04280428ШШ	(Lkkkkkk/vvovvo;Lkkkkkk/ovvvvo;)V
      //   125: return
      //   126: aload_0
      //   127: getfield 35	kkkkkk/ovvvvv$ovvovv:b0449щ044904490449щщщщ	Lkkkkkk/oovovv;
      //   130: ifnull +89 -> 219
      //   133: aload_0
      //   134: getfield 77	kkkkkk/ovvvvv$ovvovv:b0441с0441сс0441044104410441	Ljava/lang/String;
      //   137: ldc -121
      //   139: bipush 118
      //   141: iconst_5
      //   142: invokestatic 139	kkkkkk/gguuuu:bккккк043Aкк043A043A	(Ljava/lang/String;CC)Ljava/lang/String;
      //   145: invokestatic 91	kkkkkk/xtxtxt:bии0438и04380438и0438ии	(Ljava/lang/String;Ljava/lang/String;)V
      //   148: aload_0
      //   149: getfield 29	kkkkkk/ovvvvv$ovvovv:b04490449044904490449щщщщ	Lkkkkkk/ovvvvv;
      //   152: aload_0
      //   153: getfield 29	kkkkkk/ovvvvv$ovvovv:b04490449044904490449щщщщ	Lkkkkkk/ovvvvv;
      //   156: invokestatic 143	kkkkkk/ovvvvv:b04280428042804280428ШШ0428ШШ	(Lkkkkkk/ovvvvv;)Lkkkkkk/ovvvvv$ovovvv;
      //   159: aload_0
      //   160: getfield 35	kkkkkk/ovvvvv$ovvovv:b0449щ044904490449щщщщ	Lkkkkkk/oovovv;
      //   163: invokevirtual 133	kkkkkk/ovvvvv:b04280428ШШ0428Ш04280428ШШ	(Lkkkkkk/vvovvo;Lkkkkkk/ovvvvo;)V
      //   166: getstatic 63	kkkkkk/ovvvvv$ovvovv:bщщщщщ0449щщщ	I
      //   169: istore_2
      //   170: getstatic 71	kkkkkk/ovvvvv$ovvovv:bщ0449щщщ0449щщщ	I
      //   173: istore_3
      //   174: getstatic 63	kkkkkk/ovvvvv$ovvovv:bщщщщщ0449щщщ	I
      //   177: istore 4
      //   179: getstatic 67	kkkkkk/ovvvvv$ovvovv:b04490449щщщ0449щщщ	I
      //   182: istore 5
      //   184: getstatic 69	kkkkkk/ovvvvv$ovvovv:b0449щщщщ0449щщщ	I
      //   187: istore 6
      //   189: iload_2
      //   190: iload_3
      //   191: iadd
      //   192: iload 4
      //   194: imul
      //   195: iload 5
      //   197: irem
      //   198: iload 6
      //   200: if_icmpeq +39 -> 239
      //   203: invokestatic 73	kkkkkk/ovvvvv$ovvovv:b0428Ш042804280428ШШ0428ШШ	()I
      //   206: putstatic 63	kkkkkk/ovvvvv$ovvovv:bщщщщщ0449щщщ	I
      //   209: invokestatic 73	kkkkkk/ovvvvv$ovvovv:b0428Ш042804280428ШШ0428ШШ	()I
      //   212: putstatic 69	kkkkkk/ovvvvv$ovvovv:b0449щщщщ0449щщщ	I
      //   215: return
      //   216: astore_1
      //   217: aload_1
      //   218: athrow
      //   219: aload_0
      //   220: getfield 29	kkkkkk/ovvvvv$ovvovv:b04490449044904490449щщщщ	Lkkkkkk/ovvvvv;
      //   223: astore_1
      //   224: aload_1
      //   225: aload_0
      //   226: getfield 29	kkkkkk/ovvvvv$ovvovv:b04490449044904490449щщщщ	Lkkkkkk/ovvvvv;
      //   229: invokestatic 147	kkkkkk/ovvvvv:bШ0428ШШШ0428Ш0428ШШ	(Lkkkkkk/ovvvvv;)Lkkkkkk/ovvvvv$vovvvv;
      //   232: invokevirtual 151	kkkkkk/ovvvvv:bШ0428ШШ0428Ш04280428ШШ	(Lkkkkkk/vvovvo;)V
      //   235: return
      //   236: astore_1
      //   237: aload_1
      //   238: athrow
      //   239: return
      // Local variable table:
      //   start	length	slot	name	signature
      //   0	240	0	this	ovvovv
      //   0	240	1	paramVooovv	vooovv
      //   65	127	2	i	int
      //   173	19	3	j	int
      //   177	18	4	k	int
      //   182	16	5	m	int
      //   187	14	6	n	int
      //   54	4	7	str	String
      // Exception table:
      //   from	to	target	type
      //   0	5	216	java/lang/Exception
      //   23	32	216	java/lang/Exception
      //   56	62	216	java/lang/Exception
      //   203	215	216	java/lang/Exception
      //   224	235	216	java/lang/Exception
      //   5	23	236	java/lang/Exception
      //   32	56	236	java/lang/Exception
      //   107	125	236	java/lang/Exception
      //   126	189	236	java/lang/Exception
      //   219	224	236	java/lang/Exception
    }
    
    public void bШШ0428ШШШШ0428ШШ(vvoovv paramVvoovv)
    {
      int i = bщщщщщ0449щщщ;
      switch (i * (bщ0449щщщ0449щщщ + i) % b04490449щщщ0449щщщ)
      {
      default: 
        bщщщщщ0449щщщ = 98;
        b0449щщщщ0449щщщ = b0428Ш042804280428ШШ0428ШШ();
      }
      super.bШШ0428ШШШШ0428ШШ(paramVvoovv);
      paramVvoovv = this.b0441с0441сс0441044104410441;
      i = bщщщщщ0449щщщ;
      switch (i * (bщ0449щщщ0449щщщ + i) % b04490449щщщ0449щщщ)
      {
      default: 
        bщщщщщ0449щщщ = b0428Ш042804280428ШШ0428ШШ();
        b0449щщщщ0449щщщ = 31;
      }
      xtxtxt.bии0438и04380438и0438ии(paramVvoovv, gguuuu.bккккк043Aкк043A043A("\01326`,.%,1/Y\036.\034$)S*\032\032\034\024M\035\036\032\r\016\033\032\017\023\013Bt\t\025\023\022\006\n\0029\\\007\016\004BA@1\003t{|\003txp(ptnx#ybisgkc\033_o]ej", '\024', '\002'));
      this.b0449щ044904490449щщщщ = null;
    }
  }
  
  public class voovvv
    extends rmmmmm
  {
    public static int b0449044904490449щщщщщ = 28;
    public static int b0449щщщ0449щщщщ = 2;
    public static int bщ0449щщ0449щщщщ = 0;
    public static int bщщщщ0449щщщщ = 1;
    private vvoovv b0449щ04490449щщщщщ;
    private oovovv bщщ04490449щщщщщ = null;
    
    public voovvv(String paramString1, String paramString2)
    {
      super(paramString2);
    }
    
    private void b042804280428Ш0428ШШ0428ШШ()
    {
      if (this.bщщ04490449щщщщщ != null)
      {
        localOvvvvv = ovvvvv.this;
        localObject = ovvvvv.bШ0428ШШШ0428Ш0428ШШ(ovvvvv.this);
        if ((b0449044904490449щщщщщ + bщщщщ0449щщщщ) * b0449044904490449щщщщщ % b0449щщщ0449щщщщ != b04280428ШШ0428ШШ0428ШШ())
        {
          b0449044904490449щщщщщ = 87;
          int i = b0449044904490449щщщщщ;
          switch (i * (bщщщщ0449щщщщ + i) % b0449щщщ0449щщщщ)
          {
          default: 
            b0449044904490449щщщщщ = 17;
            bщ0449щщ0449щщщщ = bШ04280428Ш0428ШШ0428ШШ();
          }
          bщ0449щщ0449щщщщ = 21;
        }
        localOvvvvv.b04280428ШШ0428Ш04280428ШШ((vvovvo)localObject, this.bщщ04490449щщщщщ);
        return;
        localOvvvvv.bШ0428ШШ0428Ш04280428ШШ(ovvvvv.bШ0428ШШШ0428Ш0428ШШ((ovvvvv)localObject));
        return;
      }
      ovvvvv localOvvvvv = ovvvvv.this;
      Object localObject = ovvvvv.this;
      switch (1)
      {
      }
      for (;;)
      {
        switch (1)
        {
        case 0: 
        default: 
          for (;;)
          {
            switch (1)
            {
            }
          }
        }
        switch (1)
        {
        }
      }
    }
    
    public static int b04280428ШШ0428ШШ0428ШШ()
    {
      return 0;
    }
    
    public static int b0428Ш0428Ш0428ШШ0428ШШ()
    {
      return 1;
    }
    
    private void b0428ШШ04280428ШШ0428ШШ(Exception paramException, vvooov paramVvooov)
    {
      try
      {
        paramVvooov = paramVvooov.b0445хх0445х0445х044504450445();
        if ((bШ04280428Ш0428ШШ0428ШШ() + bщщщщ0449щщщщ) * bШ04280428Ш0428ШШ0428ШШ() % b0449щщщ0449щщщщ != bщ0449щщ0449щщщщ)
        {
          b0449044904490449щщщщщ = 63;
          bщ0449щщ0449щщщщ = 12;
        }
        if ((b0449044904490449щщщщщ + bщщщщ0449щщщщ) * b0449044904490449щщщщщ % b0449щщщ0449щщщщ != bщ0449щщ0449щщщщ)
        {
          b0449044904490449щщщщщ = 12;
          bщ0449щщ0449щщщщ = 36;
        }
        paramVvooov.bии0438иииииии(paramException);
        b042804280428Ш0428ШШ0428ШШ();
        return;
      }
      catch (Exception paramException)
      {
        throw paramException;
      }
    }
    
    public static int bШ04280428Ш0428ШШ0428ШШ()
    {
      return 86;
    }
    
    private void bШ0428Ш04280428ШШ0428ШШ(vvooov paramVvooov)
    {
      throw new Runtime("d2j fail translate: java.lang.IndexOutOfBoundsException: fromIndex < 0: -1\n\tat java.util.BitSet.nextSetBit(BitSet.java:712)\n\tat com.googlecode.dex2jar.ir.ts.array.FillArrayTransformer.makeSureAllElementAreAssigned(FillArrayTransformer.java:505)\n\tat com.googlecode.dex2jar.ir.ts.array.FillArrayTransformer.transformReportChanged(FillArrayTransformer.java:123)\n\tat com.googlecode.dex2jar.ir.ts.StatedTransformer.transform(StatedTransformer.java:10)\n\tat com.googlecode.d2j.dex.Dex2jar$2.optimize(Dex2jar.java:149)\n\tat com.googlecode.d2j.dex.Dex2Asm.convertCode(Dex2Asm.java:414)\n\tat com.googlecode.d2j.dex.ExDex2Asm.convertCode(ExDex2Asm.java:42)\n\tat com.googlecode.d2j.dex.Dex2jar$2.convertCode(Dex2jar.java:128)\n\tat com.googlecode.d2j.dex.Dex2Asm.convertMethod(Dex2Asm.java:509)\n\tat com.googlecode.d2j.dex.Dex2Asm.convertClass(Dex2Asm.java:406)\n\tat com.googlecode.d2j.dex.Dex2Asm.convertDex(Dex2Asm.java:422)\n\tat com.googlecode.d2j.dex.Dex2jar.doTranslate(Dex2jar.java:172)\n\tat com.googlecode.d2j.dex.Dex2jar.to(Dex2jar.java:272)\n\tat com.googlecode.dex2jar.tools.Dex2jarCmd.doCommandLine(Dex2jarCmd.java:108)\n\tat com.googlecode.dex2jar.tools.BaseCmd.doMain(BaseCmd.java:288)\n\tat com.googlecode.dex2jar.tools.Dex2jarCmd.main(Dex2jarCmd.java:32)\n");
    }
    
    public static int bШШ0428Ш0428ШШ0428ШШ()
    {
      return 2;
    }
    
    private void bШШШ04280428ШШ0428ШШ()
    {
      throw new Runtime("d2j fail translate: java.lang.IndexOutOfBoundsException: fromIndex < 0: -1\n\tat java.util.BitSet.nextSetBit(BitSet.java:712)\n\tat com.googlecode.dex2jar.ir.ts.array.FillArrayTransformer.makeSureAllElementAreAssigned(FillArrayTransformer.java:505)\n\tat com.googlecode.dex2jar.ir.ts.array.FillArrayTransformer.transformReportChanged(FillArrayTransformer.java:123)\n\tat com.googlecode.dex2jar.ir.ts.StatedTransformer.transform(StatedTransformer.java:10)\n\tat com.googlecode.d2j.dex.Dex2jar$2.optimize(Dex2jar.java:149)\n\tat com.googlecode.d2j.dex.Dex2Asm.convertCode(Dex2Asm.java:414)\n\tat com.googlecode.d2j.dex.ExDex2Asm.convertCode(ExDex2Asm.java:42)\n\tat com.googlecode.d2j.dex.Dex2jar$2.convertCode(Dex2jar.java:128)\n\tat com.googlecode.d2j.dex.Dex2Asm.convertMethod(Dex2Asm.java:509)\n\tat com.googlecode.d2j.dex.Dex2Asm.convertClass(Dex2Asm.java:406)\n\tat com.googlecode.d2j.dex.Dex2Asm.convertDex(Dex2Asm.java:422)\n\tat com.googlecode.d2j.dex.Dex2jar.doTranslate(Dex2jar.java:172)\n\tat com.googlecode.d2j.dex.Dex2jar.to(Dex2jar.java:272)\n\tat com.googlecode.dex2jar.tools.Dex2jarCmd.doCommandLine(Dex2jarCmd.java:108)\n\tat com.googlecode.dex2jar.tools.BaseCmd.doMain(BaseCmd.java:288)\n\tat com.googlecode.dex2jar.tools.Dex2jarCmd.main(Dex2jarCmd.java:32)\n");
    }
    
    public void b042804280428ШШШШ0428ШШ(oooovv paramOooovv)
    {
      int i = b0449044904490449щщщщщ;
      switch (i * (bщщщщ0449щщщщ + i) % b0449щщщ0449щщщщ)
      {
      default: 
        b0449044904490449щщщщщ = 56;
        bщ0449щщ0449щщщщ = bШ04280428Ш0428ШШ0428ШШ();
      }
      if ((b0449044904490449щщщщщ + b0428Ш0428Ш0428ШШ0428ШШ()) * b0449044904490449щщщщщ % b0449щщщ0449щщщщ != bщ0449щщ0449щщщщ)
      {
        b0449044904490449щщщщщ = bШ04280428Ш0428ШШ0428ШШ();
        bщ0449щщ0449щщщщ = 82;
      }
      try
      {
        this.bщщ04490449щщщщщ = null;
        return;
      }
      catch (Exception paramOooovv)
      {
        throw paramOooovv;
      }
    }
    
    public void b04280428ШШШШШ0428ШШ(oovovv paramOovovv)
    {
      int i = b0449044904490449щщщщщ;
      switch (i * (bщщщщ0449щщщщ + i) % bШШ0428Ш0428ШШ0428ШШ())
      {
      default: 
        b0449044904490449щщщщщ = bШ04280428Ш0428ШШ0428ШШ();
        bщ0449щщ0449щщщщ = 1;
      }
      try
      {
        this.bщщ04490449щщщщщ = paramOovovv;
        return;
      }
      catch (Exception paramOovovv)
      {
        throw paramOovovv;
      }
    }
    
    /* Error */
    public void b0428Ш0428ШШШШ0428ШШ(ovoovv paramOvoovv)
    {
      // Byte code:
      //   0: aload_0
      //   1: getfield 117	kkkkkk/ovvvvv$voovvv:b0441с0441сс0441044104410441	Ljava/lang/String;
      //   4: astore_1
      //   5: aload_1
      //   6: ldc 119
      //   8: sipush 195
      //   11: iconst_2
      //   12: invokestatic 125	kkkkkk/gguuuu:bккккк043Aкк043A043A	(Ljava/lang/String;CC)Ljava/lang/String;
      //   15: invokestatic 130	kkkkkk/xtxtxt:bии0438и04380438и0438ии	(Ljava/lang/String;Ljava/lang/String;)V
      //   18: aload_0
      //   19: getfield 132	kkkkkk/ovvvvv$voovvv:b0449щ04490449щщщщщ	Lkkkkkk/vvoovv;
      //   22: invokevirtual 138	kkkkkk/vvoovv:b04280428ШШ04280428Ш0428ШШ	()Lkkkkkk/vvooov;
      //   25: astore_1
      //   26: new 9	kkkkkk/ovvvvv$voovvv$1
      //   29: dup
      //   30: aload_0
      //   31: invokespecial 141	kkkkkk/ovvvvv$voovvv$1:<init>	(Lkkkkkk/ovvvvv$voovvv;)V
      //   34: astore_3
      //   35: getstatic 46	kkkkkk/ovvvvv$voovvv:b0449044904490449щщщщщ	I
      //   38: istore_2
      //   39: iload_2
      //   40: getstatic 48	kkkkkk/ovvvvv$voovvv:bщщщщ0449щщщщ	I
      //   43: iload_2
      //   44: iadd
      //   45: imul
      //   46: getstatic 50	kkkkkk/ovvvvv$voovvv:b0449щщщ0449щщщщ	I
      //   49: irem
      //   50: tableswitch	default:+18->68, 0:+29->79
      //   68: invokestatic 57	kkkkkk/ovvvvv$voovvv:bШ04280428Ш0428ШШ0428ШШ	()I
      //   71: putstatic 46	kkkkkk/ovvvvv$voovvv:b0449044904490449щщщщщ	I
      //   74: bipush 78
      //   76: putstatic 59	kkkkkk/ovvvvv$voovvv:bщ0449щщ0449щщщщ	I
      //   79: aload_1
      //   80: aload_3
      //   81: invokevirtual 145	kkkkkk/vvooov:b0445х04450445х0445х044504450445	(Lkkkkkk/voovov;)V
      //   84: return
      //   85: astore_1
      //   86: aload_1
      //   87: athrow
      //   88: astore_1
      //   89: aload_1
      //   90: athrow
      // Local variable table:
      //   start	length	slot	name	signature
      //   0	91	0	this	voovvv
      //   0	91	1	paramOvoovv	ovoovv
      //   38	8	2	i	int
      //   34	47	3	local1	1
      // Exception table:
      //   from	to	target	type
      //   5	35	85	java/lang/Exception
      //   79	84	85	java/lang/Exception
      //   0	5	88	java/lang/Exception
    }
    
    public void bШ042804280428042804280428ШШШ()
    {
      switch (1)
      {
      case 0: 
      default: 
        for (;;)
        {
          switch (0)
          {
          }
        }
      }
      super.bШ042804280428042804280428ШШШ();
      switch (1)
      {
      case 0: 
      default: 
        for (;;)
        {
          switch (1)
          {
          }
        }
      }
      if ((bШ04280428Ш0428ШШ0428ШШ() + bщщщщ0449щщщщ) * bШ04280428Ш0428ШШ0428ШШ() % b0449щщщ0449щщщщ != bщ0449щщ0449щщщщ)
      {
        b0449044904490449щщщщщ = 29;
        bщ0449щщ0449щщщщ = bШ04280428Ш0428ШШ0428ШШ();
      }
      this.bщщ04490449щщщщщ = null;
      if ((bШ04280428Ш0428ШШ0428ШШ() + b0428Ш0428Ш0428ШШ0428ШШ()) * bШ04280428Ш0428ШШ0428ШШ() % b0449щщщ0449щщщщ != bщ0449щщ0449щщщщ)
      {
        b0449044904490449щщщщщ = 14;
        bщ0449щщ0449щщщщ = bШ04280428Ш0428ШШ0428ШШ();
      }
      this.b0449щ04490449щщщщщ = null;
    }
    
    /* Error */
    public void bШ04280428ШШШШ0428ШШ(vooovv paramVooovv)
    {
      // Byte code:
      //   0: aload_0
      //   1: getfield 117	kkkkkk/ovvvvv$voovvv:b0441с0441сс0441044104410441	Ljava/lang/String;
      //   4: ldc -104
      //   6: bipush 51
      //   8: sipush 174
      //   11: iconst_0
      //   12: invokestatic 156	kkkkkk/gguuuu:bк043Aккк043Aкк043A043A	(Ljava/lang/String;CCC)Ljava/lang/String;
      //   15: invokestatic 130	kkkkkk/xtxtxt:bии0438и04380438и0438ии	(Ljava/lang/String;Ljava/lang/String;)V
      //   18: aload_0
      //   19: getfield 132	kkkkkk/ovvvvv$voovvv:b0449щ04490449щщщщщ	Lkkkkkk/vvoovv;
      //   22: invokevirtual 138	kkkkkk/vvoovv:b04280428ШШ04280428Ш0428ШШ	()Lkkkkkk/vvooov;
      //   25: astore_1
      //   26: aload_1
      //   27: invokevirtual 159	kkkkkk/vvooov:b04450445х0445х0445х044504450445	()V
      //   30: aload_0
      //   31: aload_1
      //   32: invokespecial 161	kkkkkk/ovvvvv$voovvv:bШ0428Ш04280428ШШ0428ШШ	(Lkkkkkk/vvooov;)V
      //   35: return
      //   36: astore_1
      //   37: aload_1
      //   38: athrow
      //   39: astore_1
      //   40: aload_1
      //   41: athrow
      // Local variable table:
      //   start	length	slot	name	signature
      //   0	42	0	this	voovvv
      //   0	42	1	paramVooovv	vooovv
      // Exception table:
      //   from	to	target	type
      //   0	30	36	java/lang/Exception
      //   30	35	39	java/lang/Exception
    }
    
    /* Error */
    public void bШШ0428ШШШШ0428ШШ(vvoovv paramVvoovv)
    {
      // Byte code:
      //   0: aload_0
      //   1: getfield 132	kkkkkk/ovvvvv$voovvv:b0449щ04490449щщщщщ	Lkkkkkk/vvoovv;
      //   4: ifnonnull +52 -> 56
      //   7: aload_0
      //   8: aload_1
      //   9: putfield 132	kkkkkk/ovvvvv$voovvv:b0449щ04490449щщщщщ	Lkkkkkk/vvoovv;
      //   12: aload_0
      //   13: aload_1
      //   14: invokevirtual 167	kkkkkk/vvoovv:bШ0428ШШ04280428Ш0428ШШ	()Lkkkkkk/oovovv;
      //   17: putfield 37	kkkkkk/ovvvvv$voovvv:bщщ04490449щщщщщ	Lkkkkkk/oovovv;
      //   20: getstatic 46	kkkkkk/ovvvvv$voovvv:b0449044904490449щщщщщ	I
      //   23: getstatic 48	kkkkkk/ovvvvv$voovvv:bщщщщ0449щщщщ	I
      //   26: iadd
      //   27: getstatic 46	kkkkkk/ovvvvv$voovvv:b0449044904490449щщщщщ	I
      //   30: imul
      //   31: getstatic 50	kkkkkk/ovvvvv$voovvv:b0449щщщ0449щщщщ	I
      //   34: irem
      //   35: getstatic 59	kkkkkk/ovvvvv$voovvv:bщ0449щщ0449щщщщ	I
      //   38: if_icmpeq +13 -> 51
      //   41: bipush 23
      //   43: putstatic 46	kkkkkk/ovvvvv$voovvv:b0449044904490449щщщщщ	I
      //   46: bipush 42
      //   48: putstatic 59	kkkkkk/ovvvvv$voovvv:bщ0449щщ0449щщщщ	I
      //   51: aload_0
      //   52: invokespecial 169	kkkkkk/ovvvvv$voovvv:bШШШ04280428ШШ0428ШШ	()V
      //   55: return
      //   56: aload_0
      //   57: getfield 117	kkkkkk/ovvvvv$voovvv:b0441с0441сс0441044104410441	Ljava/lang/String;
      //   60: astore_1
      //   61: getstatic 46	kkkkkk/ovvvvv$voovvv:b0449044904490449щщщщщ	I
      //   64: istore_2
      //   65: getstatic 48	kkkkkk/ovvvvv$voovvv:bщщщщ0449щщщщ	I
      //   68: istore_3
      //   69: getstatic 50	kkkkkk/ovvvvv$voovvv:b0449щщщ0449щщщщ	I
      //   72: istore 4
      //   74: iload_2
      //   75: iload_3
      //   76: iload_2
      //   77: iadd
      //   78: imul
      //   79: iload 4
      //   81: irem
      //   82: tableswitch	default:+18->100, 0:+28->110
      //   100: bipush 79
      //   102: putstatic 46	kkkkkk/ovvvvv$voovvv:b0449044904490449щщщщщ	I
      //   105: bipush 32
      //   107: putstatic 59	kkkkkk/ovvvvv$voovvv:bщ0449щщ0449щщщщ	I
      //   110: aload_1
      //   111: ldc -85
      //   113: bipush 100
      //   115: sipush 194
      //   118: iconst_1
      //   119: invokestatic 156	kkkkkk/gguuuu:bк043Aккк043Aкк043A043A	(Ljava/lang/String;CCC)Ljava/lang/String;
      //   122: invokestatic 130	kkkkkk/xtxtxt:bии0438и04380438и0438ии	(Ljava/lang/String;Ljava/lang/String;)V
      //   125: return
      //   126: astore_1
      //   127: aload_1
      //   128: athrow
      //   129: astore_1
      //   130: aload_1
      //   131: athrow
      //   132: astore_1
      //   133: aload_1
      //   134: athrow
      //   135: astore_1
      //   136: aload_1
      //   137: athrow
      // Local variable table:
      //   start	length	slot	name	signature
      //   0	138	0	this	voovvv
      //   0	138	1	paramVvoovv	vvoovv
      //   64	15	2	i	int
      //   68	10	3	j	int
      //   72	10	4	k	int
      // Exception table:
      //   from	to	target	type
      //   51	55	126	java/lang/Exception
      //   110	125	126	java/lang/Exception
      //   61	74	129	java/lang/Exception
      //   127	129	129	java/lang/Exception
      //   133	135	129	java/lang/Exception
      //   0	20	132	java/lang/Exception
      //   56	61	132	java/lang/Exception
      //   100	110	135	java/lang/Exception
    }
  }
  
  public class vovvvv
    extends rmmmmm
  {
    public static int b044104410441с04410441044104410441 = 2;
    public static int b0441сс044104410441044104410441 = 1;
    public static int bс04410441с04410441044104410441 = 83;
    public static int bссс044104410441044104410441;
    
    public vovvvv(String paramString1, String paramString2)
    {
      super(paramString2);
    }
    
    public static int b0428ШШ0428ШШШ0428ШШ()
    {
      return 1;
    }
    
    public static int bШШШ0428ШШШ0428ШШ()
    {
      return 4;
    }
    
    public void b042804280428ШШШШ0428ШШ(oooovv paramOooovv)
    {
      paramOooovv = this.b0441с0441сс0441044104410441;
      switch (0)
      {
      case 1: 
      default: 
        for (;;)
        {
          switch (1)
          {
          }
        }
      }
      String str = gguuuu.bккккк043Aкк043A043A("\003v\003\001Oy\001vL|jrw\"pn\037gkeo(\031a^ddfX ", '·', '\003');
      int i = bс04410441с04410441044104410441;
      int j = b0441сс044104410441044104410441;
      int k = b044104410441с04410441044104410441;
      if ((bс04410441с04410441044104410441 + b0441сс044104410441044104410441) * bс04410441с04410441044104410441 % b044104410441с04410441044104410441 != bссс044104410441044104410441)
      {
        bс04410441с04410441044104410441 = bШШШ0428ШШШ0428ШШ();
        bссс044104410441044104410441 = bШШШ0428ШШШ0428ШШ();
      }
      switch (i * (j + i) % k)
      {
      default: 
        bс04410441с04410441044104410441 = 61;
        switch (0)
        {
        case 1: 
        default: 
          for (;;)
          {
            switch (0)
            {
            }
          }
        }
        bссс044104410441044104410441 = 32;
      }
      xtxtxt.bии0438и04380438и0438ии(paramOooovv, str);
    }
    
    /* Error */
    public void b04280428ШШШШШ0428ШШ(oovovv paramOovovv)
    {
      // Byte code:
      //   0: getstatic 44	kkkkkk/ovvvvv$vovvvv:bс04410441с04410441044104410441	I
      //   3: istore_2
      //   4: invokestatic 63	kkkkkk/ovvvvv$vovvvv:b0428ШШ0428ШШШ0428ШШ	()I
      //   7: istore_3
      //   8: getstatic 44	kkkkkk/ovvvvv$vovvvv:bс04410441с04410441044104410441	I
      //   11: getstatic 46	kkkkkk/ovvvvv$vovvvv:b0441сс044104410441044104410441	I
      //   14: iadd
      //   15: getstatic 44	kkkkkk/ovvvvv$vovvvv:bс04410441с04410441044104410441	I
      //   18: imul
      //   19: getstatic 48	kkkkkk/ovvvvv$vovvvv:b044104410441с04410441044104410441	I
      //   22: irem
      //   23: getstatic 50	kkkkkk/ovvvvv$vovvvv:bссс044104410441044104410441	I
      //   26: if_icmpeq +14 -> 40
      //   29: invokestatic 52	kkkkkk/ovvvvv$vovvvv:bШШШ0428ШШШ0428ШШ	()I
      //   32: putstatic 44	kkkkkk/ovvvvv$vovvvv:bс04410441с04410441044104410441	I
      //   35: bipush 43
      //   37: putstatic 50	kkkkkk/ovvvvv$vovvvv:bссс044104410441044104410441	I
      //   40: iload_2
      //   41: iload_3
      //   42: iload_2
      //   43: iadd
      //   44: imul
      //   45: getstatic 48	kkkkkk/ovvvvv$vovvvv:b044104410441с04410441044104410441	I
      //   48: irem
      //   49: tableswitch	default:+67->116, 0:+31->80
      //   68: invokestatic 52	kkkkkk/ovvvvv$vovvvv:bШШШ0428ШШШ0428ШШ	()I
      //   71: putstatic 44	kkkkkk/ovvvvv$vovvvv:bс04410441с04410441044104410441	I
      //   74: invokestatic 52	kkkkkk/ovvvvv$vovvvv:bШШШ0428ШШШ0428ШШ	()I
      //   77: putstatic 48	kkkkkk/ovvvvv$vovvvv:b044104410441с04410441044104410441	I
      //   80: aload_0
      //   81: getfield 21	kkkkkk/ovvvvv$vovvvv:b0441с0441с04410441044104410441	Lkkkkkk/ovvvvv;
      //   84: astore 4
      //   86: aload_0
      //   87: getfield 21	kkkkkk/ovvvvv$vovvvv:b0441с0441с04410441044104410441	Lkkkkkk/ovvvvv;
      //   90: astore 5
      //   92: aload 4
      //   94: aload 5
      //   96: invokestatic 67	kkkkkk/ovvvvv:b04280428042804280428ШШ0428ШШ	(Lkkkkkk/ovvvvv;)Lkkkkkk/ovvvvv$ovovvv;
      //   99: aload_1
      //   100: invokevirtual 71	kkkkkk/ovvvvv:b04280428ШШ0428Ш04280428ШШ	(Lkkkkkk/vvovvo;Lkkkkkk/ovvvvo;)V
      //   103: return
      //   104: astore_1
      //   105: aload_1
      //   106: athrow
      //   107: astore_1
      //   108: aload_1
      //   109: athrow
      //   110: astore_1
      //   111: aload_1
      //   112: athrow
      //   113: astore_1
      //   114: aload_1
      //   115: athrow
      //   116: goto -48 -> 68
      // Local variable table:
      //   start	length	slot	name	signature
      //   0	119	0	this	vovvvv
      //   0	119	1	paramOovovv	oovovv
      //   3	42	2	i	int
      //   7	37	3	j	int
      //   84	9	4	localOvvvvv1	ovvvvv
      //   90	5	5	localOvvvvv2	ovvvvv
      // Exception table:
      //   from	to	target	type
      //   80	92	104	java/lang/Exception
      //   0	8	107	java/lang/Exception
      //   105	107	107	java/lang/Exception
      //   111	113	107	java/lang/Exception
      //   92	103	110	java/lang/Exception
      //   40	68	113	java/lang/Exception
      //   68	80	113	java/lang/Exception
    }
    
    /* Error */
    public void bШШ0428ШШШШ0428ШШ(vvoovv paramVvoovv)
    {
      // Byte code:
      //   0: aload_0
      //   1: getfield 21	kkkkkk/ovvvvv$vovvvv:b0441с0441с04410441044104410441	Lkkkkkk/ovvvvv;
      //   4: astore 7
      //   6: aload_0
      //   7: getfield 21	kkkkkk/ovvvvv$vovvvv:b0441с0441с04410441044104410441	Lkkkkkk/ovvvvv;
      //   10: astore 8
      //   12: getstatic 44	kkkkkk/ovvvvv$vovvvv:bс04410441с04410441044104410441	I
      //   15: istore_2
      //   16: getstatic 46	kkkkkk/ovvvvv$vovvvv:b0441сс044104410441044104410441	I
      //   19: istore_3
      //   20: getstatic 44	kkkkkk/ovvvvv$vovvvv:bс04410441с04410441044104410441	I
      //   23: istore 4
      //   25: getstatic 48	kkkkkk/ovvvvv$vovvvv:b044104410441с04410441044104410441	I
      //   28: istore 5
      //   30: getstatic 50	kkkkkk/ovvvvv$vovvvv:bссс044104410441044104410441	I
      //   33: istore 6
      //   35: iload_2
      //   36: iload_3
      //   37: iadd
      //   38: iload 4
      //   40: imul
      //   41: iload 5
      //   43: irem
      //   44: iload 6
      //   46: if_icmpeq +13 -> 59
      //   49: bipush 43
      //   51: putstatic 44	kkkkkk/ovvvvv$vovvvv:bс04410441с04410441044104410441	I
      //   54: bipush 71
      //   56: putstatic 50	kkkkkk/ovvvvv$vovvvv:bссс044104410441044104410441	I
      //   59: getstatic 44	kkkkkk/ovvvvv$vovvvv:bс04410441с04410441044104410441	I
      //   62: getstatic 46	kkkkkk/ovvvvv$vovvvv:b0441сс044104410441044104410441	I
      //   65: iadd
      //   66: getstatic 44	kkkkkk/ovvvvv$vovvvv:bс04410441с04410441044104410441	I
      //   69: imul
      //   70: getstatic 48	kkkkkk/ovvvvv$vovvvv:b044104410441с04410441044104410441	I
      //   73: irem
      //   74: getstatic 50	kkkkkk/ovvvvv$vovvvv:bссс044104410441044104410441	I
      //   77: if_icmpeq +14 -> 91
      //   80: invokestatic 52	kkkkkk/ovvvvv$vovvvv:bШШШ0428ШШШ0428ШШ	()I
      //   83: putstatic 44	kkkkkk/ovvvvv$vovvvv:bс04410441с04410441044104410441	I
      //   86: bipush 21
      //   88: putstatic 50	kkkkkk/ovvvvv$vovvvv:bссс044104410441044104410441	I
      //   91: iconst_0
      //   92: tableswitch	default:+24->116, 0:+51->143, 1:+-33->59
      //   116: iconst_0
      //   117: tableswitch	default:+23->140, 0:+26->143, 1:+-58->59
      //   140: goto -24 -> 116
      //   143: aload 7
      //   145: aload 8
      //   147: invokestatic 77	kkkkkk/ovvvvv:bШШШШШ0428Ш0428ШШ	(Lkkkkkk/ovvvvv;)Lkkkkkk/ovvvvv$voovvv;
      //   150: aload_1
      //   151: invokevirtual 71	kkkkkk/ovvvvv:b04280428ШШ0428Ш04280428ШШ	(Lkkkkkk/vvovvo;Lkkkkkk/ovvvvo;)V
      //   154: return
      //   155: astore_1
      //   156: aload_1
      //   157: athrow
      //   158: astore_1
      //   159: aload_1
      //   160: athrow
      // Local variable table:
      //   start	length	slot	name	signature
      //   0	161	0	this	vovvvv
      //   0	161	1	paramVvoovv	vvoovv
      //   15	23	2	i	int
      //   19	19	3	j	int
      //   23	18	4	k	int
      //   28	16	5	m	int
      //   33	14	6	n	int
      //   4	140	7	localOvvvvv1	ovvvvv
      //   10	136	8	localOvvvvv2	ovvvvv
      // Exception table:
      //   from	to	target	type
      //   0	35	155	java/lang/Exception
      //   143	154	155	java/lang/Exception
      //   49	59	158	java/lang/Exception
    }
  }
  
  public class vvovvv
    extends rmmmmm
  {
    public static int b04490449щщщщщщщ = 97;
    public static int b0449щ0449щщщщщщ = 1;
    public static int bщ04490449щщщщщщ = 2;
    public static int bщщ0449щщщщщщ;
    
    public vvovvv(String paramString1, String paramString2)
    {
      super(paramString2);
    }
    
    public static int b0428Ш04280428ШШШ0428ШШ()
    {
      return 7;
    }
    
    public static int bШШ04280428ШШШ0428ШШ()
    {
      return 1;
    }
    
    public void b042804280428ШШШШ0428ШШ(oooovv paramOooovv)
    {
      throw new Runtime("d2j fail translate: java.lang.IndexOutOfBoundsException: fromIndex < 0: -1\n\tat java.util.BitSet.nextSetBit(BitSet.java:712)\n\tat com.googlecode.dex2jar.ir.ts.array.FillArrayTransformer.makeSureAllElementAreAssigned(FillArrayTransformer.java:505)\n\tat com.googlecode.dex2jar.ir.ts.array.FillArrayTransformer.transformReportChanged(FillArrayTransformer.java:123)\n\tat com.googlecode.dex2jar.ir.ts.StatedTransformer.transform(StatedTransformer.java:10)\n\tat com.googlecode.d2j.dex.Dex2jar$2.optimize(Dex2jar.java:149)\n\tat com.googlecode.d2j.dex.Dex2Asm.convertCode(Dex2Asm.java:414)\n\tat com.googlecode.d2j.dex.ExDex2Asm.convertCode(ExDex2Asm.java:42)\n\tat com.googlecode.d2j.dex.Dex2jar$2.convertCode(Dex2jar.java:128)\n\tat com.googlecode.d2j.dex.Dex2Asm.convertMethod(Dex2Asm.java:509)\n\tat com.googlecode.d2j.dex.Dex2Asm.convertClass(Dex2Asm.java:406)\n\tat com.googlecode.d2j.dex.Dex2Asm.convertDex(Dex2Asm.java:422)\n\tat com.googlecode.d2j.dex.Dex2jar.doTranslate(Dex2jar.java:172)\n\tat com.googlecode.d2j.dex.Dex2jar.to(Dex2jar.java:272)\n\tat com.googlecode.dex2jar.tools.Dex2jarCmd.doCommandLine(Dex2jarCmd.java:108)\n\tat com.googlecode.dex2jar.tools.BaseCmd.doMain(BaseCmd.java:288)\n\tat com.googlecode.dex2jar.tools.Dex2jarCmd.main(Dex2jarCmd.java:32)\n");
    }
    
    /* Error */
    public void b04280428ШШШШШ0428ШШ(oovovv paramOovovv)
    {
      // Byte code:
      //   0: aload_0
      //   1: getfield 47	kkkkkk/ovvvvv$vvovvv:b0441с0441сс0441044104410441	Ljava/lang/String;
      //   4: astore_2
      //   5: aload_2
      //   6: ldc 49
      //   8: sipush 203
      //   11: iconst_5
      //   12: invokestatic 55	kkkkkk/gguuuu:bккккк043Aкк043A043A	(Ljava/lang/String;CC)Ljava/lang/String;
      //   15: invokestatic 60	kkkkkk/xtxtxt:bии0438и04380438и0438ии	(Ljava/lang/String;Ljava/lang/String;)V
      //   18: aload_1
      //   19: invokevirtual 66	kkkkkk/oovovv:bШ042804280428Ш0428Ш0428ШШ	()Lkkkkkk/vovoov;
      //   22: invokevirtual 72	kkkkkk/vovoov:bх0445х04450445хх044504450445	()Lkkkkkk/xdxxdx;
      //   25: invokeinterface 78 1 0
      //   30: getstatic 80	kkkkkk/ovvvvv$vvovvv:b04490449щщщщщщщ	I
      //   33: getstatic 82	kkkkkk/ovvvvv$vvovvv:b0449щ0449щщщщщщ	I
      //   36: iadd
      //   37: getstatic 80	kkkkkk/ovvvvv$vvovvv:b04490449щщщщщщщ	I
      //   40: imul
      //   41: getstatic 84	kkkkkk/ovvvvv$vvovvv:bщ04490449щщщщщщ	I
      //   44: irem
      //   45: getstatic 86	kkkkkk/ovvvvv$vvovvv:bщщ0449щщщщщщ	I
      //   48: if_icmpeq +14 -> 62
      //   51: bipush 94
      //   53: putstatic 80	kkkkkk/ovvvvv$vvovvv:b04490449щщщщщщщ	I
      //   56: invokestatic 88	kkkkkk/ovvvvv$vvovvv:b0428Ш04280428ШШШ0428ШШ	()I
      //   59: putstatic 86	kkkkkk/ovvvvv$vvovvv:bщщ0449щщщщщщ	I
      //   62: return
      //   63: astore_1
      //   64: aload_1
      //   65: athrow
      //   66: astore_1
      //   67: aload_1
      //   68: athrow
      // Local variable table:
      //   start	length	slot	name	signature
      //   0	69	0	this	vvovvv
      //   0	69	1	paramOovovv	oovovv
      //   4	2	2	str	String
      // Exception table:
      //   from	to	target	type
      //   5	30	63	java/lang/Exception
      //   0	5	66	java/lang/Exception
    }
    
    /* Error */
    public void bШШ0428ШШШШ0428ШШ(vvoovv paramVvoovv)
    {
      // Byte code:
      //   0: aload_1
      //   1: iconst_1
      //   2: invokevirtual 96	kkkkkk/vvoovv:b0428Ш0428Ш04280428Ш0428ШШ	(Z)V
      //   5: getstatic 80	kkkkkk/ovvvvv$vvovvv:b04490449щщщщщщщ	I
      //   8: istore_2
      //   9: iload_2
      //   10: getstatic 82	kkkkkk/ovvvvv$vvovvv:b0449щ0449щщщщщщ	I
      //   13: iload_2
      //   14: iadd
      //   15: imul
      //   16: getstatic 84	kkkkkk/ovvvvv$vvovvv:bщ04490449щщщщщщ	I
      //   19: irem
      //   20: tableswitch	default:+20->40, 0:+30->50
      //   40: bipush 22
      //   42: putstatic 80	kkkkkk/ovvvvv$vvovvv:b04490449щщщщщщщ	I
      //   45: bipush 32
      //   47: putstatic 86	kkkkkk/ovvvvv$vvovvv:bщщ0449щщщщщщ	I
      //   50: iconst_1
      //   51: tableswitch	default:+21->72, 0:+-1->50, 1:+48->99
      //   72: iconst_0
      //   73: tableswitch	default:+23->96, 0:+26->99, 1:+-23->50
      //   96: goto -24 -> 72
      //   99: aload_0
      //   100: getfield 21	kkkkkk/ovvvvv$vvovvv:bщ0449щщщщщщщ	Lkkkkkk/ovvvvv;
      //   103: astore_3
      //   104: getstatic 80	kkkkkk/ovvvvv$vvovvv:b04490449щщщщщщщ	I
      //   107: istore_2
      //   108: iload_2
      //   109: invokestatic 98	kkkkkk/ovvvvv$vvovvv:bШШ04280428ШШШ0428ШШ	()I
      //   112: iload_2
      //   113: iadd
      //   114: imul
      //   115: getstatic 84	kkkkkk/ovvvvv$vvovvv:bщ04490449щщщщщщ	I
      //   118: irem
      //   119: tableswitch	default:+17->136, 0:+28->147
      //   136: invokestatic 88	kkkkkk/ovvvvv$vvovvv:b0428Ш04280428ШШШ0428ШШ	()I
      //   139: putstatic 80	kkkkkk/ovvvvv$vvovvv:b04490449щщщщщщщ	I
      //   142: bipush 89
      //   144: putstatic 86	kkkkkk/ovvvvv$vvovvv:bщщ0449щщщщщщ	I
      //   147: aload_0
      //   148: getfield 21	kkkkkk/ovvvvv$vvovvv:bщ0449щщщщщщщ	Lkkkkkk/ovvvvv;
      //   151: invokestatic 102	kkkkkk/ovvvvv:bШШШШШ0428Ш0428ШШ	(Lkkkkkk/ovvvvv;)Lkkkkkk/ovvvvv$voovvv;
      //   154: astore 4
      //   156: aload_3
      //   157: aload 4
      //   159: aload_1
      //   160: invokevirtual 106	kkkkkk/ovvvvv:b04280428ШШ0428Ш04280428ШШ	(Lkkkkkk/vvovvo;Lkkkkkk/ovvvvo;)V
      //   163: return
      //   164: astore_1
      //   165: aload_1
      //   166: athrow
      //   167: astore_1
      //   168: aload_1
      //   169: athrow
      // Local variable table:
      //   start	length	slot	name	signature
      //   0	170	0	this	vvovvv
      //   0	170	1	paramVvoovv	vvoovv
      //   8	107	2	i	int
      //   103	54	3	localOvvvvv	ovvvvv
      //   154	4	4	localVoovvv	ovvvvv.voovvv
      // Exception table:
      //   from	to	target	type
      //   0	5	164	java/lang/Exception
      //   99	104	164	java/lang/Exception
      //   147	156	164	java/lang/Exception
      //   156	163	167	java/lang/Exception
    }
  }
}
