package kkkkkk;

import android.app.Activity;
import android.app.Application.ActivityLifecycleCallbacks;
import android.os.Bundle;
import android.support.annotation.Nullable;

public class pdpdpd
  implements Application.ActivityLifecycleCallbacks
{
  public static int b041F041F041F041FП041F041F041FП = 50;
  public static int b041FППП041F041F041F041FП = 1;
  public static int bП041FПП041F041F041F041FП = 2;
  public static int bПППП041F041F041F041FП;
  private boolean b041FП041F041FП041F041F041FП;
  private int bП041F041F041FП041F041F041FП = 0;
  @Nullable
  private pdppdp bПП041F041FП041F041F041FП;
  
  public pdpdpd() {}
  
  public static int b043004300430аа0430аа0430а()
  {
    return 2;
  }
  
  public static int bааа0430а0430аа0430а()
  {
    return 51;
  }
  
  public void b0430аа0430а0430аа0430а(@Nullable pdppdp paramPdppdp)
  {
    switch (0)
    {
    case 1: 
    default: 
      for (;;)
      {
        switch (0)
        {
        }
      }
    }
    try
    {
      this.bПП041F041FП041F041F041FП = paramPdppdp;
      if ((b041F041F041F041FП041F041F041FП + b041FППП041F041F041F041FП) * b041F041F041F041FП041F041F041FП % bП041FПП041F041F041F041FП != bПППП041F041F041F041FП)
      {
        b041F041F041F041FП041F041F041FП = bааа0430а0430аа0430а();
        bПППП041F041F041F041FП = 89;
      }
      return;
    }
    catch (Exception paramPdppdp)
    {
      throw paramPdppdp;
    }
  }
  
  @ooiiio("Unused")
  public void onActivityCreated(Activity paramActivity, Bundle paramBundle)
  {
    if ((b041F041F041F041FП041F041F041FП + b041FППП041F041F041F041FП) * b041F041F041F041FП041F041F041FП % bП041FПП041F041F041F041FП != bПППП041F041F041F041FП)
    {
      b041F041F041F041FП041F041F041FП = bааа0430а0430аа0430а();
      bПППП041F041F041F041FП = 51;
    }
    switch (1)
    {
    case 0: 
    default: 
      for (;;)
      {
        switch (0)
        {
        }
      }
    }
  }
  
  @ooiiio("Unused")
  public void onActivityDestroyed(Activity paramActivity)
  {
    switch (0)
    {
    case 1: 
    default: 
      for (;;)
      {
        if ((b041F041F041F041FП041F041F041FП + b041FППП041F041F041F041FП) * b041F041F041F041FП041F041F041FП % bП041FПП041F041F041F041FП != bПППП041F041F041F041FП)
        {
          b041F041F041F041FП041F041F041FП = bааа0430а0430аа0430а();
          bПППП041F041F041F041FП = 14;
        }
        switch (1)
        {
        }
      }
    }
  }
  
  @ooiiio("Unused")
  public void onActivityPaused(Activity paramActivity)
  {
    switch (1)
    {
    case 0: 
    default: 
      for (;;)
      {
        int i = b041F041F041F041FП041F041F041FП;
        switch (i * (b041FППП041F041F041F041FП + i) % b043004300430аа0430аа0430а())
        {
        default: 
          b041F041F041F041FП041F041F041FП = bааа0430а0430аа0430а();
          bПППП041F041F041F041FП = 67;
        }
        switch (1)
        {
        }
      }
    }
  }
  
  @ooiiio("Unused")
  public void onActivityResumed(Activity paramActivity)
  {
    int i = b041F041F041F041FП041F041F041FП;
    switch (i * (b041FППП041F041F041F041FП + i) % bП041FПП041F041F041F041FП)
    {
    default: 
      b041F041F041F041FП041F041F041FП = bааа0430а0430аа0430а();
      bПППП041F041F041F041FП = bааа0430а0430аа0430а();
    }
    switch (0)
    {
    case 1: 
    default: 
      for (;;)
      {
        switch (0)
        {
        }
      }
    }
  }
  
  @ooiiio("Unused")
  public void onActivitySaveInstanceState(Activity paramActivity, Bundle paramBundle) {}
  
  /* Error */
  @ooiiio("Impossible to cover all branches because private fields are used")
  public void onActivityStarted(Activity paramActivity)
  {
    // Byte code:
    //   0: ldc 64
    //   2: sipush 140
    //   5: iconst_4
    //   6: invokestatic 70	kkkkkk/gguuuu:bккккк043Aкк043A043A	(Ljava/lang/String;CC)Ljava/lang/String;
    //   9: iconst_1
    //   10: anewarray 4	java/lang/Object
    //   13: dup
    //   14: iconst_0
    //   15: aload_1
    //   16: invokevirtual 74	java/lang/Object:getClass	()Ljava/lang/Class;
    //   19: invokevirtual 80	java/lang/Class:getSimpleName	()Ljava/lang/String;
    //   22: aastore
    //   23: invokestatic 86	kkkkkk/ooooio:bа04300430аа04300430ааа	(Ljava/lang/String;[Ljava/lang/Object;)V
    //   26: aload_0
    //   27: getfield 26	kkkkkk/pdpdpd:bП041F041F041FП041F041F041FП	I
    //   30: istore_2
    //   31: aload_0
    //   32: iload_2
    //   33: iconst_1
    //   34: iadd
    //   35: putfield 26	kkkkkk/pdpdpd:bП041F041F041FП041F041F041FП	I
    //   38: aload_0
    //   39: getfield 36	kkkkkk/pdpdpd:bПП041F041FП041F041F041FП	Lkkkkkk/pdppdp;
    //   42: ifnull +140 -> 182
    //   45: aload_0
    //   46: getfield 26	kkkkkk/pdpdpd:bП041F041F041FП041F041F041FП	I
    //   49: ifle +133 -> 182
    //   52: aload_0
    //   53: getfield 36	kkkkkk/pdpdpd:bПП041F041FП041F041F041FП	Lkkkkkk/pdppdp;
    //   56: invokevirtual 92	kkkkkk/pdppdp:b043004300430а0430а04300430аа	()Z
    //   59: istore_3
    //   60: iload_3
    //   61: ifeq +121 -> 182
    //   64: aload_0
    //   65: getfield 94	kkkkkk/pdpdpd:b041FП041F041FП041F041F041FП	Z
    //   68: istore_3
    //   69: iload_3
    //   70: ifne +112 -> 182
    //   73: getstatic 38	kkkkkk/pdpdpd:b041F041F041F041FП041F041F041FП	I
    //   76: istore_2
    //   77: iload_2
    //   78: getstatic 40	kkkkkk/pdpdpd:b041FППП041F041F041F041FП	I
    //   81: iload_2
    //   82: iadd
    //   83: imul
    //   84: getstatic 42	kkkkkk/pdpdpd:bП041FПП041F041F041F041FП	I
    //   87: irem
    //   88: tableswitch	default:+20->108, 0:+32->120
    //   108: invokestatic 46	kkkkkk/pdpdpd:bааа0430а0430аа0430а	()I
    //   111: putstatic 38	kkkkkk/pdpdpd:b041F041F041F041FП041F041F041FП	I
    //   114: invokestatic 46	kkkkkk/pdpdpd:bааа0430а0430аа0430а	()I
    //   117: putstatic 44	kkkkkk/pdpdpd:bПППП041F041F041F041FП	I
    //   120: aload_0
    //   121: iconst_1
    //   122: putfield 94	kkkkkk/pdpdpd:b041FП041F041FП041F041F041FП	Z
    //   125: aload_0
    //   126: getfield 36	kkkkkk/pdpdpd:bПП041F041FП041F041F041FП	Lkkkkkk/pdppdp;
    //   129: astore_1
    //   130: getstatic 38	kkkkkk/pdpdpd:b041F041F041F041FП041F041F041FП	I
    //   133: istore_2
    //   134: iload_2
    //   135: getstatic 40	kkkkkk/pdpdpd:b041FППП041F041F041F041FП	I
    //   138: iload_2
    //   139: iadd
    //   140: imul
    //   141: invokestatic 58	kkkkkk/pdpdpd:b043004300430аа0430аа0430а	()I
    //   144: irem
    //   145: tableswitch	default:+19->164, 0:+29->174
    //   164: iconst_1
    //   165: putstatic 38	kkkkkk/pdpdpd:b041F041F041F041FП041F041F041FП	I
    //   168: invokestatic 46	kkkkkk/pdpdpd:bааа0430а0430аа0430а	()I
    //   171: putstatic 44	kkkkkk/pdpdpd:bПППП041F041F041F041FП	I
    //   174: aload_1
    //   175: invokevirtual 98	kkkkkk/pdppdp:b0430а0430а0430а04300430аа	()Lkkkkkk/knknnk;
    //   178: invokevirtual 104	kkkkkk/knknnk:b044504450445х04450445х0445хх	()Lkkkkkk/kknnnk;
    //   181: pop
    //   182: return
    //   183: astore_1
    //   184: aload_1
    //   185: athrow
    //   186: astore_1
    //   187: aload_1
    //   188: athrow
    // Local variable table:
    //   start	length	slot	name	signature
    //   0	189	0	this	pdpdpd
    //   0	189	1	paramActivity	Activity
    //   30	111	2	i	int
    //   59	11	3	bool	boolean
    // Exception table:
    //   from	to	target	type
    //   0	31	183	java/lang/Exception
    //   64	69	183	java/lang/Exception
    //   120	130	183	java/lang/Exception
    //   174	182	183	java/lang/Exception
    //   31	60	186	java/lang/Exception
  }
  
  /* Error */
  @ooiiio("Impossible to cover all branches because private fields are used")
  public void onActivityStopped(Activity paramActivity)
  {
    // Byte code:
    //   0: getstatic 38	kkkkkk/pdpdpd:b041F041F041F041FП041F041F041FП	I
    //   3: istore_2
    //   4: getstatic 40	kkkkkk/pdpdpd:b041FППП041F041F041F041FП	I
    //   7: istore_3
    //   8: getstatic 42	kkkkkk/pdpdpd:bП041FПП041F041F041F041FП	I
    //   11: istore 4
    //   13: iload_2
    //   14: iload_3
    //   15: iload_2
    //   16: iadd
    //   17: imul
    //   18: iload 4
    //   20: irem
    //   21: tableswitch	default:+19->40, 0:+29->50
    //   40: bipush 83
    //   42: putstatic 38	kkkkkk/pdpdpd:b041F041F041F041FП041F041F041FП	I
    //   45: bipush 61
    //   47: putstatic 44	kkkkkk/pdpdpd:bПППП041F041F041F041FП	I
    //   50: getstatic 38	kkkkkk/pdpdpd:b041F041F041F041FП041F041F041FП	I
    //   53: getstatic 40	kkkkkk/pdpdpd:b041FППП041F041F041F041FП	I
    //   56: iadd
    //   57: getstatic 38	kkkkkk/pdpdpd:b041F041F041F041FП041F041F041FП	I
    //   60: imul
    //   61: getstatic 42	kkkkkk/pdpdpd:bП041FПП041F041F041F041FП	I
    //   64: irem
    //   65: getstatic 44	kkkkkk/pdpdpd:bПППП041F041F041F041FП	I
    //   68: if_icmpeq +15 -> 83
    //   71: invokestatic 46	kkkkkk/pdpdpd:bааа0430а0430аа0430а	()I
    //   74: putstatic 38	kkkkkk/pdpdpd:b041F041F041F041FП041F041F041FП	I
    //   77: invokestatic 46	kkkkkk/pdpdpd:bааа0430а0430аа0430а	()I
    //   80: putstatic 44	kkkkkk/pdpdpd:bПППП041F041F041F041FП	I
    //   83: ldc 107
    //   85: bipush 75
    //   87: bipush 38
    //   89: iconst_1
    //   90: invokestatic 111	kkkkkk/gguuuu:bк043Aккк043Aкк043A043A	(Ljava/lang/String;CCC)Ljava/lang/String;
    //   93: astore 6
    //   95: aload_1
    //   96: invokevirtual 74	java/lang/Object:getClass	()Ljava/lang/Class;
    //   99: astore_1
    //   100: aload 6
    //   102: iconst_1
    //   103: anewarray 4	java/lang/Object
    //   106: dup
    //   107: iconst_0
    //   108: aload_1
    //   109: invokevirtual 80	java/lang/Class:getSimpleName	()Ljava/lang/String;
    //   112: aastore
    //   113: invokestatic 86	kkkkkk/ooooio:bа04300430аа04300430ааа	(Ljava/lang/String;[Ljava/lang/Object;)V
    //   116: aload_0
    //   117: getfield 26	kkkkkk/pdpdpd:bП041F041F041FП041F041F041FП	I
    //   120: istore_2
    //   121: aload_0
    //   122: iload_2
    //   123: iconst_1
    //   124: isub
    //   125: putfield 26	kkkkkk/pdpdpd:bП041F041F041FП041F041F041FП	I
    //   128: aload_0
    //   129: getfield 36	kkkkkk/pdpdpd:bПП041F041FП041F041F041FП	Lkkkkkk/pdppdp;
    //   132: ifnull +98 -> 230
    //   135: aload_0
    //   136: getfield 26	kkkkkk/pdpdpd:bП041F041F041FП041F041F041FП	I
    //   139: ifne +91 -> 230
    //   142: aload_0
    //   143: getfield 36	kkkkkk/pdpdpd:bПП041F041FП041F041F041FП	Lkkkkkk/pdppdp;
    //   146: invokevirtual 92	kkkkkk/pdppdp:b043004300430а0430а04300430аа	()Z
    //   149: istore 5
    //   151: iload 5
    //   153: ifeq +77 -> 230
    //   156: aload_0
    //   157: getfield 94	kkkkkk/pdpdpd:b041FП041F041FП041F041F041FП	Z
    //   160: ifeq +70 -> 230
    //   163: aload_0
    //   164: iconst_0
    //   165: putfield 94	kkkkkk/pdpdpd:b041FП041F041FП041F041F041FП	Z
    //   168: iconst_0
    //   169: tableswitch	default:+23->192, 0:+50->219, 1:+-1->168
    //   192: iconst_0
    //   193: tableswitch	default:+23->216, 0:+26->219, 1:+-25->168
    //   216: goto -24 -> 192
    //   219: aload_0
    //   220: getfield 36	kkkkkk/pdpdpd:bПП041F041FП041F041F041FП	Lkkkkkk/pdppdp;
    //   223: invokevirtual 98	kkkkkk/pdppdp:b0430а0430а0430а04300430аа	()Lkkkkkk/knknnk;
    //   226: invokevirtual 114	kkkkkk/knknnk:bх0445хх04450445х0445хх	()Lkkkkkk/kknnnk;
    //   229: pop
    //   230: return
    //   231: astore_1
    //   232: aload_1
    //   233: athrow
    //   234: astore_1
    //   235: aload_1
    //   236: athrow
    // Local variable table:
    //   start	length	slot	name	signature
    //   0	237	0	this	pdpdpd
    //   0	237	1	paramActivity	Activity
    //   3	122	2	i	int
    //   7	10	3	j	int
    //   11	10	4	k	int
    //   149	3	5	bool	boolean
    //   93	8	6	str	String
    // Exception table:
    //   from	to	target	type
    //   0	13	231	java/lang/Exception
    //   83	100	231	java/lang/Exception
    //   116	121	231	java/lang/Exception
    //   128	151	231	java/lang/Exception
    //   219	230	231	java/lang/Exception
    //   40	50	234	java/lang/Exception
    //   100	116	234	java/lang/Exception
    //   121	128	234	java/lang/Exception
    //   156	168	234	java/lang/Exception
  }
}
