package kkkkkk;

import android.content.Context;

public class pdppdp
{
  public static int b041F041F041FПППП041FП = 9;
  public static int b041FПП041FППП041FП = 2;
  private static knknnk bП041F041FПППП041FП;
  public static int bП041FП041FППП041FП = 0;
  public static int bППП041FППП041FП = 1;
  
  public pdppdp()
  {
    bаа0430а0430а04300430аа();
  }
  
  public static int b04300430аа0430а04300430аа()
  {
    return 0;
  }
  
  public static int b0430ааа0430а04300430аа()
  {
    return 2;
  }
  
  public static int bа0430аа0430а04300430аа()
  {
    return 1;
  }
  
  private void bаа0430а0430а04300430аа()
  {
    bП041F041FПППП041FП = null;
  }
  
  public static int bаааа0430а04300430аа()
  {
    return 67;
  }
  
  /* Error */
  @ooiiio("This is a third party component (GoogleApiClient) that will not be tested")
  public void b0430043004300430аа04300430аа(Context paramContext, knknnk paramKnknnk)
  {
    // Byte code:
    //   0: new 39	com/google/android/gms/common/api/GoogleApiClient$Builder
    //   3: dup
    //   4: aload_1
    //   5: invokespecial 42	com/google/android/gms/common/api/GoogleApiClient$Builder:<init>	(Landroid/content/Context;)V
    //   8: astore_1
    //   9: getstatic 48	com/google/android/gms/safetynet/SafetyNet:API	Lcom/google/android/gms/common/api/Api;
    //   12: astore 4
    //   14: getstatic 50	kkkkkk/pdppdp:b041F041F041FПППП041FП	I
    //   17: getstatic 52	kkkkkk/pdppdp:bППП041FППП041FП	I
    //   20: iadd
    //   21: getstatic 50	kkkkkk/pdppdp:b041F041F041FПППП041FП	I
    //   24: imul
    //   25: getstatic 54	kkkkkk/pdppdp:b041FПП041FППП041FП	I
    //   28: irem
    //   29: getstatic 56	kkkkkk/pdppdp:bП041FП041FППП041FП	I
    //   32: if_icmpeq +59 -> 91
    //   35: getstatic 50	kkkkkk/pdppdp:b041F041F041FПППП041FП	I
    //   38: istore_3
    //   39: iload_3
    //   40: getstatic 52	kkkkkk/pdppdp:bППП041FППП041FП	I
    //   43: iload_3
    //   44: iadd
    //   45: imul
    //   46: invokestatic 58	kkkkkk/pdppdp:b0430ааа0430а04300430аа	()I
    //   49: irem
    //   50: tableswitch	default:+18->68, 0:+30->80
    //   68: invokestatic 60	kkkkkk/pdppdp:bаааа0430а04300430аа	()I
    //   71: putstatic 50	kkkkkk/pdppdp:b041F041F041FПППП041FП	I
    //   74: invokestatic 60	kkkkkk/pdppdp:bаааа0430а04300430аа	()I
    //   77: putstatic 56	kkkkkk/pdppdp:bП041FП041FППП041FП	I
    //   80: invokestatic 60	kkkkkk/pdppdp:bаааа0430а04300430аа	()I
    //   83: putstatic 50	kkkkkk/pdppdp:b041F041F041FПППП041FП	I
    //   86: bipush 39
    //   88: putstatic 56	kkkkkk/pdppdp:bП041FП041FППП041FП	I
    //   91: aload_2
    //   92: aload_1
    //   93: aload 4
    //   95: invokevirtual 64	com/google/android/gms/common/api/GoogleApiClient$Builder:addApi	(Lcom/google/android/gms/common/api/Api;)Lcom/google/android/gms/common/api/GoogleApiClient$Builder;
    //   98: invokevirtual 68	com/google/android/gms/common/api/GoogleApiClient$Builder:build	()Lcom/google/android/gms/common/api/GoogleApiClient;
    //   101: invokevirtual 74	kkkkkk/knknnk:b0445х0445ххх04450445хх	(Lcom/google/android/gms/common/api/GoogleApiClient;)Lkkkkkk/kknnnk;
    //   104: pop
    //   105: return
    //   106: astore_1
    //   107: aload_1
    //   108: athrow
    //   109: astore_1
    //   110: aload_1
    //   111: athrow
    // Local variable table:
    //   start	length	slot	name	signature
    //   0	112	0	this	pdppdp
    //   0	112	1	paramContext	Context
    //   0	112	2	paramKnknnk	knknnk
    //   38	8	3	i	int
    //   12	82	4	localApi	com.google.android.gms.common.api.Api
    // Exception table:
    //   from	to	target	type
    //   91	105	106	java/lang/Exception
    //   0	14	109	java/lang/Exception
  }
  
  public boolean b043004300430а0430а04300430аа()
  {
    knknnk localKnknnk = bП041F041FПППП041FП;
    int i = b041F041F041FПППП041FП;
    switch (i * (bа0430аа0430а04300430аа() + i) % b041FПП041FППП041FП)
    {
    default: 
      i = bаааа0430а04300430аа();
      switch (1)
      {
      case 0: 
      default: 
        for (;;)
        {
          switch (1)
          {
          }
        }
      }
      b041F041F041FПППП041FП = i;
      bП041FП041FППП041FП = bаааа0430а04300430аа();
    }
    switch (0)
    {
    case 1: 
    default: 
      for (;;)
      {
        if ((b041F041F041FПППП041FП + bППП041FППП041FП) * b041F041F041FПППП041FП % b041FПП041FППП041FП != bП041FП041FППП041FП)
        {
          b041F041F041FПППП041FП = bаааа0430а04300430аа();
          bП041FП041FППП041FП = bаааа0430а04300430аа();
        }
        switch (1)
        {
        }
      }
    }
    return localKnknnk != null;
  }
  
  public knknnk b0430а0430а0430а04300430аа()
  {
    switch (0)
    {
    case 1: 
    default: 
      for (;;)
      {
        switch (1)
        {
        }
      }
    }
    int i = b041F041F041FПППП041FП;
    switch (i * (bа0430аа0430а04300430аа() + i) % b041FПП041FППП041FП)
    {
    default: 
      b041F041F041FПППП041FП = bаааа0430а04300430аа();
      bП041FП041FППП041FП = bаааа0430а04300430аа();
    }
    if (bП041F041FПППП041FП == null)
    {
      if ((b041F041F041FПППП041FП + bППП041FППП041FП) * b041F041F041FПППП041FП % b041FПП041FППП041FП != bП041FП041FППП041FП)
      {
        b041F041F041FПППП041FП = bаааа0430а04300430аа();
        bП041FП041FППП041FП = 45;
      }
      throw new NullPointerException(gguuuu.bккккк043Aкк043A043A("\031DF8q??Cm6:4>2)3/8)'o`\020+#\036/ Y\034\031#\"T\035!\033%\031\020\032\026\037\020QQG\t\013\013\023\025\007@\003\n\t\005\t\0018~{\nW\003\005v88", '', '\003'));
    }
    return bП041F041FПППП041FП;
  }
  
  public void bа04300430а0430а04300430аа(Context paramContext, ppppdp paramPpppdp)
    throws dpppdp, nnwwwn
  {
    try
    {
      if (bП041F041FПППП041FП == null) {
        break label31;
      }
      paramContext = new IllegalStateException(gguuuu.bккккк043Aкк043A043A("\b.*6,%1/:-h-,8933o3GGs>Iv9EL@=AW~IOKWMFRP[NN", '½', '\000'));
    }
    catch (Exception paramContext)
    {
      throw paramContext;
    }
    throw paramContext;
    try
    {
      label31:
      paramPpppdp = paramPpppdp.bа043004300430аа04300430аа(paramContext);
      nkknkn localNkknkn = paramPpppdp.b0445х0445х0445хх0445хх().b0445ххх0445х04450445хх().b0445044504450445х0445хх0445х();
      if (localNkknkn != nkknkn.SUCCESS) {
        throw new dpppdp(localNkknkn);
      }
      if ((b041F041F041FПППП041FП + bППП041FППП041FП) * b041F041F041FПППП041FП % b041FПП041FППП041FП != bП041FП041FППП041FП)
      {
        b041F041F041FПППП041FП = 19;
        bП041FП041FППП041FП = 30;
      }
      int i = b041F041F041FПППП041FП;
      int j = bППП041FППП041FП;
      int k = b041FПП041FППП041FП;
      switch (i * (j + i) % k)
      {
      default: 
        b041F041F041FПППП041FП = bаааа0430а04300430аа();
        bП041FП041FППП041FП = 13;
      }
      b0430043004300430аа04300430аа(paramContext, paramPpppdp);
      bП041F041FПППП041FП = paramPpppdp;
      return;
    }
    catch (Exception paramContext)
    {
      throw paramContext;
    }
    switch (0)
    {
    }
    for (;;)
    {
      switch (1)
      {
      }
    }
  }
}
