package kkkkkk;

import android.support.annotation.NonNull;

public class ppipii
{
  public static int b043D043Dн043Dнн043D043Dн = 85;
  public static int b043Dн043D043Dнн043D043Dн = 2;
  public static int bн043D043D043Dнн043D043Dн = 0;
  public static int bнн043D043Dнн043D043Dн = 1;
  @NonNull
  private final luuuuu b043Dнн043Dнн043D043Dн;
  private boolean bн043Dн043Dнн043D043Dн;
  
  public ppipii(@NonNull luuuuu paramLuuuuu)
  {
    this.b043Dнн043Dнн043D043Dн = paramLuuuuu;
    this.bн043Dн043Dнн043D043Dн = false;
  }
  
  public static int b043004300430аа043004300430а0430()
  {
    return 2;
  }
  
  public static int bа04300430аа043004300430а0430()
  {
    return 68;
  }
  
  public boolean b0430аа0430а043004300430а0430()
  {
    try
    {
      boolean bool = this.bн043Dн043Dнн043D043Dн;
      return bool;
    }
    catch (Exception localException)
    {
      throw localException;
    }
  }
  
  public void bа0430а0430а043004300430а0430(boolean paramBoolean)
  {
    if ((b043D043Dн043Dнн043D043Dн + bнн043D043Dнн043D043Dн) * b043D043Dн043Dнн043D043Dн % b043004300430аа043004300430а0430() != bн043D043D043Dнн043D043Dн)
    {
      b043D043Dн043Dнн043D043Dн = bа04300430аа043004300430а0430();
      bн043D043D043Dнн043D043Dн = 19;
    }
    switch (1)
    {
    case 0: 
    default: 
      for (;;)
      {
        switch (1)
        {
        case 0: 
        default: 
          for (;;)
          {
            switch (1)
            {
            }
          }
        }
        switch (0)
        {
        }
      }
    }
    int i = b043D043Dн043Dнн043D043Dн;
    switch (i * (bнн043D043Dнн043D043Dн + i) % b043Dн043D043Dнн043D043Dн)
    {
    default: 
      b043D043Dн043Dнн043D043Dн = bа04300430аа043004300430а0430();
      bнн043D043Dнн043D043Dн = bа04300430аа043004300430а0430();
    }
    this.bн043Dн043Dнн043D043Dн = paramBoolean;
  }
  
  /* Error */
  @NonNull
  public luuuuu bааа0430а043004300430а0430()
  {
    // Byte code:
    //   0: iconst_0
    //   1: istore_1
    //   2: iconst_0
    //   3: tableswitch	default:+21->24, 0:+48->51, 1:+-1->2
    //   24: iconst_0
    //   25: tableswitch	default:+23->48, 0:+26->51, 1:+-23->2
    //   48: goto -24 -> 24
    //   51: new 54	java/lang/NullPointerException
    //   54: dup
    //   55: invokespecial 55	java/lang/NullPointerException:<init>	()V
    //   58: athrow
    //   59: astore_2
    //   60: iload_1
    //   61: iconst_0
    //   62: idiv
    //   63: istore_1
    //   64: goto -4 -> 60
    //   67: astore_2
    //   68: aload_0
    //   69: getfield 25	kkkkkk/ppipii:b043Dнн043Dнн043D043Dн	Lkkkkkk/luuuuu;
    //   72: astore_2
    //   73: aload_2
    //   74: areturn
    //   75: astore_2
    //   76: aload_2
    //   77: athrow
    // Local variable table:
    //   start	length	slot	name	signature
    //   0	78	0	this	ppipii
    //   1	63	1	i	int
    //   59	1	2	localException1	Exception
    //   67	1	2	localException2	Exception
    //   72	2	2	localLuuuuu	luuuuu
    //   75	2	2	localException3	Exception
    // Exception table:
    //   from	to	target	type
    //   51	59	59	java/lang/Exception
    //   60	64	67	java/lang/Exception
    //   68	73	75	java/lang/Exception
  }
}
