package kkkkkk;

import android.support.annotation.Nullable;
import io.reactivex.Single;
import io.reactivex.annotations.NonNull;
import io.reactivex.functions.Function;
import java.util.ArrayList;
import java.util.Collection;
import java.util.Iterator;
import java.util.List;
import java.util.Map;

public abstract class ppkpkk
{
  private static final int b04270427042704270427ЧЧ0427Ч = 0;
  public static int b042704270427ЧЧ0427Ч0427Ч = 0;
  public static int b0427ЧЧ0427Ч0427Ч0427Ч = 1;
  public static int bЧ04270427ЧЧ0427Ч0427Ч = 66;
  public static int bЧЧЧ0427Ч0427Ч0427Ч = 2;
  private static final int bЧЧЧЧЧ0427Ч0427Ч = 50;
  private boolean b04270427ЧЧЧ0427Ч0427Ч;
  private String b0427Ч0427ЧЧ0427Ч0427Ч;
  public final aaaahh b0427ЧЧЧЧ0427Ч0427Ч;
  private final rrcrcc bЧ0427ЧЧЧ0427Ч0427Ч;
  private int bЧЧ0427ЧЧ0427Ч0427Ч = 0;
  
  public ppkpkk(aaaahh paramAaaahh)
  {
    this.b0427ЧЧЧЧ0427Ч0427Ч = paramAaaahh;
    this.bЧ0427ЧЧЧ0427Ч0427Ч = new rrcrcc();
  }
  
  private Single<rrcrcc> b0436043604360436ж04360436жж0436(int paramInt)
  {
    int i = bЧ04270427ЧЧ0427Ч0427Ч;
    switch (i * (b0427ЧЧ0427Ч0427Ч0427Ч + i) % bЧЧЧ0427Ч0427Ч0427Ч)
    {
    default: 
      bЧ04270427ЧЧ0427Ч0427Ч = 36;
      b042704270427ЧЧ0427Ч0427Ч = bжж0436жж04360436жж0436();
    }
    Object localObject = new rrcrcc();
    if ((bЧ04270427ЧЧ0427Ч0427Ч + b0427ЧЧ0427Ч0427Ч0427Ч) * bЧ04270427ЧЧ0427Ч0427Ч % bЧЧЧ0427Ч0427Ч0427Ч != b042704270427ЧЧ0427Ч0427Ч)
    {
      bЧ04270427ЧЧ0427Ч0427Ч = 11;
      b042704270427ЧЧ0427Ч0427Ч = 52;
    }
    switch (0)
    {
    case 1: 
    default: 
      for (;;)
      {
        switch (0)
        {
        }
      }
    }
    localObject = bжжжж043604360436жж0436(paramInt, (rrcrcc)localObject);
    switch (0)
    {
    case 1: 
    default: 
      for (;;)
      {
        switch (0)
        {
        }
      }
    }
    return localObject;
  }
  
  private void b04360436жж043604360436жж0436(Map<String, cccrcc> paramMap)
  {
    label68:
    cccrcc localCccrcc;
    if (!paramMap.values().isEmpty())
    {
      bool = true;
      this.b04270427ЧЧЧ0427Ч0427Ч = bool;
      paramMap = paramMap.values();
      if ((bЧ04270427ЧЧ0427Ч0427Ч + bж0436жжж04360436жж0436()) * bЧ04270427ЧЧ0427Ч0427Ч % bЧЧЧ0427Ч0427Ч0427Ч != b042704270427ЧЧ0427Ч0427Ч)
      {
        bЧ04270427ЧЧ0427Ч0427Ч = bжж0436жж04360436жж0436();
        b042704270427ЧЧ0427Ч0427Ч = bжж0436жж04360436жж0436();
      }
      paramMap = paramMap.iterator();
      if (!paramMap.hasNext()) {
        return;
      }
      localCccrcc = (cccrcc)paramMap.next();
      if ((!this.b04270427ЧЧЧ0427Ч0427Ч) || (!localCccrcc.bжж0436043604360436жж04360436())) {
        break label274;
      }
    }
    label274:
    for (boolean bool = true;; bool = false)
    {
      this.b04270427ЧЧЧ0427Ч0427Ч = bool;
      switch (1)
      {
      case 0: 
      default: 
        for (;;)
        {
          switch (0)
          {
          }
        }
      }
      switch (1)
      {
      case 0: 
      default: 
        for (;;)
        {
          switch (1)
          {
          }
        }
      }
      rrcrcc localRrcrcc = this.bЧ0427ЧЧЧ0427Ч0427Ч;
      if ((bЧ04270427ЧЧ0427Ч0427Ч + b0427ЧЧ0427Ч0427Ч0427Ч) * bЧ04270427ЧЧ0427Ч0427Ч % bЧЧЧ0427Ч0427Ч0427Ч != b042704270427ЧЧ0427Ч0427Ч)
      {
        bЧ04270427ЧЧ0427Ч0427Ч = bжж0436жж04360436жж0436();
        b042704270427ЧЧ0427Ч0427Ч = bжж0436жж04360436жж0436();
      }
      localRrcrcc.b043F043F043F043Fпппппп().put(localCccrcc.bжж0436ж0436жжж04360436(), localCccrcc);
      break label68;
      bool = false;
      break;
    }
  }
  
  public static int b04360436жжж04360436жж0436()
  {
    return 0;
  }
  
  public static int b0436ж0436жж04360436жж0436()
  {
    return 2;
  }
  
  private void b0436жжж043604360436жж0436(kpkkkk paramKpkkkk, Map<String, cccrcc> paramMap)
  {
    paramKpkkkk = paramKpkkkk.b0436жж04360436ж04360436ж0436().bж0436жжж043604360436ж0436();
    int i = bЧ04270427ЧЧ0427Ч0427Ч;
    switch (i * (bж0436жжж04360436жж0436() + i) % bЧЧЧ0427Ч0427Ч0427Ч)
    {
    default: 
      bЧ04270427ЧЧ0427Ч0427Ч = bжж0436жж04360436жж0436();
      b042704270427ЧЧ0427Ч0427Ч = bжж0436жж04360436жж0436();
    }
    paramKpkkkk = paramKpkkkk.iterator();
    for (;;)
    {
      switch (0)
      {
      case 1: 
      default: 
        for (;;)
        {
          switch (0)
          {
          case 1: 
          default: 
            for (;;)
            {
              switch (0)
              {
              }
            }
          }
          switch (0)
          {
          }
        }
      }
      if (!paramKpkkkk.hasNext()) {
        break;
      }
      Object localObject = paramKpkkkk.next();
      i = bЧ04270427ЧЧ0427Ч0427Ч;
      switch (i * (b0427ЧЧ0427Ч0427Ч0427Ч + i) % bЧЧЧ0427Ч0427Ч0427Ч)
      {
      default: 
        bЧ04270427ЧЧ0427Ч0427Ч = 8;
        b042704270427ЧЧ0427Ч0427Ч = 53;
      }
      localObject = cccrcc.bж04360436жжжжж04360436((ppkkkk)localObject);
      paramMap.put(((cccrcc)localObject).bжж0436ж0436жжж04360436(), localObject);
    }
  }
  
  /* Error */
  private boolean bж04360436ж043604360436жж0436(kpkkkk paramKpkkkk, Map<String, cccrcc> paramMap)
  {
    // Byte code:
    //   0: iconst_0
    //   1: istore 8
    //   3: getstatic 46	kkkkkk/ppkpkk:bЧ04270427ЧЧ0427Ч0427Ч	I
    //   6: istore_3
    //   7: getstatic 48	kkkkkk/ppkpkk:b0427ЧЧ0427Ч0427Ч0427Ч	I
    //   10: istore 4
    //   12: getstatic 46	kkkkkk/ppkpkk:bЧ04270427ЧЧ0427Ч0427Ч	I
    //   15: istore 5
    //   17: getstatic 50	kkkkkk/ppkpkk:bЧЧЧ0427Ч0427Ч0427Ч	I
    //   20: istore 6
    //   22: invokestatic 158	kkkkkk/ppkpkk:b04360436жжж04360436жж0436	()I
    //   25: istore 7
    //   27: iload_3
    //   28: iload 4
    //   30: iadd
    //   31: iload 5
    //   33: imul
    //   34: iload 6
    //   36: irem
    //   37: iload 7
    //   39: if_icmpeq +46 -> 85
    //   42: bipush 81
    //   44: putstatic 46	kkkkkk/ppkpkk:bЧ04270427ЧЧ0427Ч0427Ч	I
    //   47: bipush 18
    //   49: putstatic 52	kkkkkk/ppkpkk:b042704270427ЧЧ0427Ч0427Ч	I
    //   52: getstatic 46	kkkkkk/ppkpkk:bЧ04270427ЧЧ0427Ч0427Ч	I
    //   55: getstatic 48	kkkkkk/ppkpkk:b0427ЧЧ0427Ч0427Ч0427Ч	I
    //   58: iadd
    //   59: getstatic 46	kkkkkk/ppkpkk:bЧ04270427ЧЧ0427Ч0427Ч	I
    //   62: imul
    //   63: getstatic 50	kkkkkk/ppkpkk:bЧЧЧ0427Ч0427Ч0427Ч	I
    //   66: irem
    //   67: getstatic 52	kkkkkk/ppkpkk:b042704270427ЧЧ0427Ч0427Ч	I
    //   70: if_icmpeq +15 -> 85
    //   73: invokestatic 56	kkkkkk/ppkpkk:bжж0436жж04360436жж0436	()I
    //   76: putstatic 46	kkkkkk/ppkpkk:bЧ04270427ЧЧ0427Ч0427Ч	I
    //   79: invokestatic 56	kkkkkk/ppkpkk:bжж0436жж04360436жж0436	()I
    //   82: putstatic 52	kkkkkk/ppkpkk:b042704270427ЧЧ0427Ч0427Ч	I
    //   85: aload_1
    //   86: invokevirtual 136	kkkkkk/kpkkkk:b0436жж04360436ж04360436ж0436	()Lkkkkkk/rccccc;
    //   89: invokevirtual 161	kkkkkk/rccccc:b0436ж0436жж043604360436ж0436	()I
    //   92: istore_3
    //   93: aload_2
    //   94: invokeinterface 164 1 0
    //   99: istore 4
    //   101: iconst_0
    //   102: tableswitch	default:+22->124, 0:+49->151, 1:+-1->101
    //   124: iconst_0
    //   125: tableswitch	default:+23->148, 0:+26->151, 1:+-24->101
    //   148: goto -24 -> 124
    //   151: iload_3
    //   152: iload 4
    //   154: if_icmple +6 -> 160
    //   157: iconst_1
    //   158: istore 8
    //   160: iload 8
    //   162: ireturn
    //   163: astore_1
    //   164: aload_1
    //   165: athrow
    //   166: astore_1
    //   167: aload_1
    //   168: athrow
    // Local variable table:
    //   start	length	slot	name	signature
    //   0	169	0	this	ppkpkk
    //   0	169	1	paramKpkkkk	kpkkkk
    //   0	169	2	paramMap	Map<String, cccrcc>
    //   6	149	3	i	int
    //   10	145	4	j	int
    //   15	19	5	k	int
    //   20	17	6	m	int
    //   25	15	7	n	int
    //   1	160	8	bool	boolean
    // Exception table:
    //   from	to	target	type
    //   3	27	163	java/lang/Exception
    //   85	101	163	java/lang/Exception
    //   42	52	166	java/lang/Exception
  }
  
  public static int bж0436жжж04360436жж0436()
  {
    return 1;
  }
  
  private void bжж0436ж043604360436жж0436(List<String> paramList)
  {
    this.bЧ0427ЧЧЧ0427Ч0427Ч.b043F043Fп043Fпппппп(paramList);
    switch (1)
    {
    case 0: 
    default: 
      for (;;)
      {
        switch (1)
        {
        }
      }
    }
    if ((bжж0436жж04360436жж0436() + b0427ЧЧ0427Ч0427Ч0427Ч) * bжж0436жж04360436жж0436() % bЧЧЧ0427Ч0427Ч0427Ч != b042704270427ЧЧ0427Ч0427Ч)
    {
      if ((bЧ04270427ЧЧ0427Ч0427Ч + bж0436жжж04360436жж0436()) * bЧ04270427ЧЧ0427Ч0427Ч % bЧЧЧ0427Ч0427Ч0427Ч != b042704270427ЧЧ0427Ч0427Ч)
      {
        bЧ04270427ЧЧ0427Ч0427Ч = bжж0436жж04360436жж0436();
        b042704270427ЧЧ0427Ч0427Ч = bжж0436жж04360436жж0436();
      }
      switch (1)
      {
      case 0: 
      default: 
        for (;;)
        {
          switch (1)
          {
          }
        }
      }
      bЧ04270427ЧЧ0427Ч0427Ч = bжж0436жж04360436жж0436();
      b042704270427ЧЧ0427Ч0427Ч = bжж0436жж04360436жж0436();
    }
  }
  
  public static int bжж0436жж04360436жж0436()
  {
    return 89;
  }
  
  /* Error */
  private Single<rrcrcc> bжжжж043604360436жж0436(int paramInt, rrcrcc paramRrcrcc)
  {
    // Byte code:
    //   0: getstatic 46	kkkkkk/ppkpkk:bЧ04270427ЧЧ0427Ч0427Ч	I
    //   3: istore_3
    //   4: getstatic 48	kkkkkk/ppkpkk:b0427ЧЧ0427Ч0427Ч0427Ч	I
    //   7: istore 4
    //   9: getstatic 50	kkkkkk/ppkpkk:bЧЧЧ0427Ч0427Ч0427Ч	I
    //   12: istore 5
    //   14: iload_3
    //   15: iload 4
    //   17: iload_3
    //   18: iadd
    //   19: imul
    //   20: iload 5
    //   22: irem
    //   23: tableswitch	default:+17->40, 0:+73->96
    //   40: invokestatic 56	kkkkkk/ppkpkk:bжж0436жж04360436жж0436	()I
    //   43: putstatic 46	kkkkkk/ppkpkk:bЧ04270427ЧЧ0427Ч0427Ч	I
    //   46: invokestatic 56	kkkkkk/ppkpkk:bжж0436жж04360436жж0436	()I
    //   49: putstatic 52	kkkkkk/ppkpkk:b042704270427ЧЧ0427Ч0427Ч	I
    //   52: getstatic 46	kkkkkk/ppkpkk:bЧ04270427ЧЧ0427Ч0427Ч	I
    //   55: istore_3
    //   56: iload_3
    //   57: getstatic 48	kkkkkk/ppkpkk:b0427ЧЧ0427Ч0427Ч0427Ч	I
    //   60: iload_3
    //   61: iadd
    //   62: imul
    //   63: getstatic 50	kkkkkk/ppkpkk:bЧЧЧ0427Ч0427Ч0427Ч	I
    //   66: irem
    //   67: tableswitch	default:+17->84, 0:+29->96
    //   84: invokestatic 56	kkkkkk/ppkpkk:bжж0436жж04360436жж0436	()I
    //   87: putstatic 46	kkkkkk/ppkpkk:bЧ04270427ЧЧ0427Ч0427Ч	I
    //   90: invokestatic 56	kkkkkk/ppkpkk:bжж0436жж04360436жж0436	()I
    //   93: putstatic 52	kkkkkk/ppkpkk:b042704270427ЧЧ0427Ч0427Ч	I
    //   96: aload_0
    //   97: iload_1
    //   98: bipush 50
    //   100: invokevirtual 177	kkkkkk/ppkpkk:b04360436жж0436жжжж0436	(II)Lio/reactivex/Single;
    //   103: astore 6
    //   105: new 179	kkkkkk/ppkpkk$4
    //   108: dup
    //   109: aload_0
    //   110: aload_2
    //   111: iload_1
    //   112: invokespecial 182	kkkkkk/ppkpkk$4:<init>	(Lkkkkkk/ppkpkk;Lkkkkkk/rrcrcc;I)V
    //   115: astore_2
    //   116: aload 6
    //   118: aload_2
    //   119: invokevirtual 188	io/reactivex/Single:flatMap	(Lio/reactivex/functions/Function;)Lio/reactivex/Single;
    //   122: astore_2
    //   123: aload_2
    //   124: areturn
    //   125: astore_2
    //   126: aload_2
    //   127: athrow
    //   128: astore_2
    //   129: aload_2
    //   130: athrow
    //   131: astore_2
    //   132: aload_2
    //   133: athrow
    //   134: astore_2
    //   135: aload_2
    //   136: athrow
    // Local variable table:
    //   start	length	slot	name	signature
    //   0	137	0	this	ppkpkk
    //   0	137	1	paramInt	int
    //   0	137	2	paramRrcrcc	rrcrcc
    //   3	60	3	i	int
    //   7	12	4	j	int
    //   12	11	5	k	int
    //   103	14	6	localSingle	Single
    // Exception table:
    //   from	to	target	type
    //   96	105	125	java/lang/Exception
    //   116	123	125	java/lang/Exception
    //   0	14	128	java/lang/Exception
    //   126	128	128	java/lang/Exception
    //   105	116	131	java/lang/Exception
    //   40	52	134	java/lang/Exception
    //   132	134	134	java/lang/Exception
  }
  
  /* Error */
  public Single<cccrcc> b043604360436ж043604360436жж0436(String paramString)
  {
    // Byte code:
    //   0: iconst_0
    //   1: tableswitch	default:+23->24, 0:+50->51, 1:+-1->0
    //   24: iconst_0
    //   25: tableswitch	default:+23->48, 0:+26->51, 1:+-25->0
    //   48: goto -24 -> 24
    //   51: aload_0
    //   52: getfield 34	kkkkkk/ppkpkk:b0427ЧЧЧЧ0427Ч0427Ч	Lkkkkkk/aaaahh;
    //   55: aload_1
    //   56: invokevirtual 200	kkkkkk/aaaahh:bпп043F043F043F043F043Fп043F043F	(Ljava/lang/String;)Lio/reactivex/Single;
    //   59: astore_1
    //   60: new 202	kkkkkk/ppkpkk$3
    //   63: dup
    //   64: aload_0
    //   65: invokespecial 205	kkkkkk/ppkpkk$3:<init>	(Lkkkkkk/ppkpkk;)V
    //   68: astore_2
    //   69: getstatic 46	kkkkkk/ppkpkk:bЧ04270427ЧЧ0427Ч0427Ч	I
    //   72: getstatic 48	kkkkkk/ppkpkk:b0427ЧЧ0427Ч0427Ч0427Ч	I
    //   75: iadd
    //   76: getstatic 46	kkkkkk/ppkpkk:bЧ04270427ЧЧ0427Ч0427Ч	I
    //   79: imul
    //   80: getstatic 50	kkkkkk/ppkpkk:bЧЧЧ0427Ч0427Ч0427Ч	I
    //   83: irem
    //   84: getstatic 52	kkkkkk/ppkpkk:b042704270427ЧЧ0427Ч0427Ч	I
    //   87: if_icmpeq +14 -> 101
    //   90: bipush 50
    //   92: putstatic 46	kkkkkk/ppkpkk:bЧ04270427ЧЧ0427Ч0427Ч	I
    //   95: invokestatic 56	kkkkkk/ppkpkk:bжж0436жж04360436жж0436	()I
    //   98: putstatic 52	kkkkkk/ppkpkk:b042704270427ЧЧ0427Ч0427Ч	I
    //   101: aload_1
    //   102: aload_2
    //   103: invokevirtual 208	io/reactivex/Single:map	(Lio/reactivex/functions/Function;)Lio/reactivex/Single;
    //   106: astore_1
    //   107: getstatic 46	kkkkkk/ppkpkk:bЧ04270427ЧЧ0427Ч0427Ч	I
    //   110: getstatic 48	kkkkkk/ppkpkk:b0427ЧЧ0427Ч0427Ч0427Ч	I
    //   113: iadd
    //   114: getstatic 46	kkkkkk/ppkpkk:bЧ04270427ЧЧ0427Ч0427Ч	I
    //   117: imul
    //   118: getstatic 50	kkkkkk/ppkpkk:bЧЧЧ0427Ч0427Ч0427Ч	I
    //   121: irem
    //   122: getstatic 52	kkkkkk/ppkpkk:b042704270427ЧЧ0427Ч0427Ч	I
    //   125: if_icmpeq +13 -> 138
    //   128: bipush 75
    //   130: putstatic 46	kkkkkk/ppkpkk:bЧ04270427ЧЧ0427Ч0427Ч	I
    //   133: bipush 59
    //   135: putstatic 52	kkkkkk/ppkpkk:b042704270427ЧЧ0427Ч0427Ч	I
    //   138: aload_1
    //   139: areturn
    //   140: astore_1
    //   141: aload_1
    //   142: athrow
    //   143: astore_1
    //   144: aload_1
    //   145: athrow
    // Local variable table:
    //   start	length	slot	name	signature
    //   0	146	0	this	ppkpkk
    //   0	146	1	paramString	String
    //   68	35	2	local3	ppkpkk.3
    // Exception table:
    //   from	to	target	type
    //   51	60	140	java/lang/Exception
    //   101	107	140	java/lang/Exception
    //   60	69	143	java/lang/Exception
  }
  
  @ooiiio("Trivial")
  public String b043604360436жж04360436жж0436()
  {
    if (this.bЧ0427ЧЧЧ0427Ч0427Ч.bпппп043Fппппп() != null)
    {
      Object localObject = this.bЧ0427ЧЧЧ0427Ч0427Ч;
      switch (1)
      {
      case 0: 
      default: 
        for (;;)
        {
          switch (1)
          {
          }
        }
      }
      if (((rrcrcc)localObject).bпппп043Fппппп().size() > this.bЧЧ0427ЧЧ0427Ч0427Ч)
      {
        localObject = this.bЧ0427ЧЧЧ0427Ч0427Ч.bпппп043Fппппп();
        if ((bЧ04270427ЧЧ0427Ч0427Ч + b0427ЧЧ0427Ч0427Ч0427Ч) * bЧ04270427ЧЧ0427Ч0427Ч % bЧЧЧ0427Ч0427Ч0427Ч != b042704270427ЧЧ0427Ч0427Ч)
        {
          bЧ04270427ЧЧ0427Ч0427Ч = bжж0436жж04360436жж0436();
          b042704270427ЧЧ0427Ч0427Ч = 67;
        }
        return (String)((List)localObject).get(this.bЧЧ0427ЧЧ0427Ч0427Ч);
      }
    }
    return null;
  }
  
  @NonNull
  public List<cccrcc> b04360436ж0436ж04360436жж0436()
  {
    switch (0)
    {
    case 1: 
    default: 
      for (;;)
      {
        switch (1)
        {
        }
      }
    }
    ArrayList localArrayList = new ArrayList(this.bЧ0427ЧЧЧ0427Ч0427Ч.b043F043F043F043Fпппппп().values());
    int i = bЧ04270427ЧЧ0427Ч0427Ч;
    int j = b0427ЧЧ0427Ч0427Ч0427Ч;
    int k = bЧ04270427ЧЧ0427Ч0427Ч;
    if ((bЧ04270427ЧЧ0427Ч0427Ч + bж0436жжж04360436жж0436()) * bЧ04270427ЧЧ0427Ч0427Ч % bЧЧЧ0427Ч0427Ч0427Ч != b042704270427ЧЧ0427Ч0427Ч)
    {
      bЧ04270427ЧЧ0427Ч0427Ч = bжж0436жж04360436жж0436();
      b042704270427ЧЧ0427Ч0427Ч = 12;
    }
    if ((i + j) * k % bЧЧЧ0427Ч0427Ч0427Ч != b042704270427ЧЧ0427Ч0427Ч)
    {
      bЧ04270427ЧЧ0427Ч0427Ч = bжж0436жж04360436жж0436();
      b042704270427ЧЧ0427Ч0427Ч = bжж0436жж04360436жж0436();
    }
    return localArrayList;
  }
  
  public abstract Single<kpkkkk> b04360436жж0436жжжж0436(int paramInt1, int paramInt2);
  
  @Nullable
  public String b0436ж04360436ж04360436жж0436()
  {
    for (;;)
    {
      try
      {
        int i = bЧ04270427ЧЧ0427Ч0427Ч;
        switch (i * (b0427ЧЧ0427Ч0427Ч0427Ч + i) % bЧЧЧ0427Ч0427Ч0427Ч)
        {
        default: 
          bЧ04270427ЧЧ0427Ч0427Ч = bжж0436жж04360436жж0436();
          i = bЧ04270427ЧЧ0427Ч0427Ч;
          switch (i * (b0427ЧЧ0427Ч0427Ч0427Ч + i) % b0436ж0436жж04360436жж0436())
          {
          default: 
            bЧ04270427ЧЧ0427Ч0427Ч = 29;
            b042704270427ЧЧ0427Ч0427Ч = bжж0436жж04360436жж0436();
          }
          b042704270427ЧЧ0427Ч0427Ч = 84;
        }
      }
      catch (Exception localException)
      {
        String str;
        throw localException;
      }
      str = this.b0427Ч0427ЧЧ0427Ч0427Ч;
      return str;
    }
    switch (1)
    {
    }
    for (;;)
    {
      switch (1)
      {
      }
    }
  }
  
  /* Error */
  @ooiiio("trivial")
  public void b0436ж0436ж043604360436жж0436(@Nullable String paramString)
  {
    // Byte code:
    //   0: getstatic 46	kkkkkk/ppkpkk:bЧ04270427ЧЧ0427Ч0427Ч	I
    //   3: istore_2
    //   4: getstatic 48	kkkkkk/ppkpkk:b0427ЧЧ0427Ч0427Ч0427Ч	I
    //   7: istore_3
    //   8: getstatic 50	kkkkkk/ppkpkk:bЧЧЧ0427Ч0427Ч0427Ч	I
    //   11: istore 4
    //   13: iload_2
    //   14: iload_3
    //   15: iload_2
    //   16: iadd
    //   17: imul
    //   18: iload 4
    //   20: irem
    //   21: tableswitch	default:+19->40, 0:+30->51
    //   40: invokestatic 56	kkkkkk/ppkpkk:bжж0436жж04360436жж0436	()I
    //   43: putstatic 46	kkkkkk/ppkpkk:bЧ04270427ЧЧ0427Ч0427Ч	I
    //   46: bipush 46
    //   48: putstatic 52	kkkkkk/ppkpkk:b042704270427ЧЧ0427Ч0427Ч	I
    //   51: aload_0
    //   52: aload_1
    //   53: putfield 239	kkkkkk/ppkpkk:b0427Ч0427ЧЧ0427Ч0427Ч	Ljava/lang/String;
    //   56: iconst_1
    //   57: tableswitch	default:+23->80, 0:+-1->56, 1:+90->147
    //   80: getstatic 46	kkkkkk/ppkpkk:bЧ04270427ЧЧ0427Ч0427Ч	I
    //   83: istore_2
    //   84: iload_2
    //   85: getstatic 48	kkkkkk/ppkpkk:b0427ЧЧ0427Ч0427Ч0427Ч	I
    //   88: iload_2
    //   89: iadd
    //   90: imul
    //   91: getstatic 50	kkkkkk/ppkpkk:bЧЧЧ0427Ч0427Ч0427Ч	I
    //   94: irem
    //   95: tableswitch	default:+17->112, 0:+27->122
    //   112: bipush 78
    //   114: putstatic 46	kkkkkk/ppkpkk:bЧ04270427ЧЧ0427Ч0427Ч	I
    //   117: bipush 16
    //   119: putstatic 52	kkkkkk/ppkpkk:b042704270427ЧЧ0427Ч0427Ч	I
    //   122: iconst_0
    //   123: tableswitch	default:+21->144, 0:+24->147, 1:+-67->56
    //   144: goto -64 -> 80
    //   147: return
    //   148: astore_1
    //   149: aload_1
    //   150: athrow
    //   151: astore_1
    //   152: aload_1
    //   153: athrow
    // Local variable table:
    //   start	length	slot	name	signature
    //   0	154	0	this	ppkpkk
    //   0	154	1	paramString	String
    //   3	88	2	i	int
    //   7	10	3	j	int
    //   11	10	4	k	int
    // Exception table:
    //   from	to	target	type
    //   0	13	148	java/lang/Exception
    //   51	56	148	java/lang/Exception
    //   40	51	151	java/lang/Exception
  }
  
  public Single<rrcrcc> b0436жж0436ж04360436жж0436()
  {
    Single localSingle = Single.just(this.bЧ0427ЧЧЧ0427Ч0427Ч);
    Object localObject = new ppkpkk.2(this);
    if ((bЧ04270427ЧЧ0427Ч0427Ч + b0427ЧЧ0427Ч0427Ч0427Ч) * bЧ04270427ЧЧ0427Ч0427Ч % bЧЧЧ0427Ч0427Ч0427Ч != b042704270427ЧЧ0427Ч0427Ч)
    {
      bЧ04270427ЧЧ0427Ч0427Ч = 2;
      b042704270427ЧЧ0427Ч0427Ч = 54;
    }
    localSingle = localSingle.flatMap((Function)localObject);
    if ((bЧ04270427ЧЧ0427Ч0427Ч + b0427ЧЧ0427Ч0427Ч0427Ч) * bЧ04270427ЧЧ0427Ч0427Ч % bЧЧЧ0427Ч0427Ч0427Ч != b042704270427ЧЧ0427Ч0427Ч)
    {
      bЧ04270427ЧЧ0427Ч0427Ч = bжж0436жж04360436жж0436();
      b042704270427ЧЧ0427Ч0427Ч = bжж0436жж04360436жж0436();
    }
    localObject = new ppkpkk.1(this);
    switch (0)
    {
    case 1: 
    default: 
      for (;;)
      {
        switch (1)
        {
        }
      }
    }
    return localSingle.map((Function)localObject);
  }
  
  public boolean bж043604360436ж04360436жж0436()
  {
    try
    {
      boolean bool = this.b04270427ЧЧЧ0427Ч0427Ч;
      int i = bжж0436жж04360436жж0436();
      int j = b0427ЧЧ0427Ч0427Ч0427Ч;
      if ((bЧ04270427ЧЧ0427Ч0427Ч + b0427ЧЧ0427Ч0427Ч0427Ч) * bЧ04270427ЧЧ0427Ч0427Ч % bЧЧЧ0427Ч0427Ч0427Ч != b04360436жжж04360436жж0436())
      {
        bЧ04270427ЧЧ0427Ч0427Ч = 92;
        b042704270427ЧЧ0427Ч0427Ч = 0;
      }
      switch (i * (j + i) % bЧЧЧ0427Ч0427Ч0427Ч)
      {
      default: 
        bЧ04270427ЧЧ0427Ч0427Ч = bжж0436жж04360436жж0436();
        b042704270427ЧЧ0427Ч0427Ч = bжж0436жж04360436жж0436();
      }
      return bool;
    }
    catch (Exception localException)
    {
      throw localException;
    }
  }
  
  /* Error */
  @ooiiio("Trivial")
  public void bж04360436жж04360436жж0436()
  {
    // Byte code:
    //   0: getstatic 46	kkkkkk/ppkpkk:bЧ04270427ЧЧ0427Ч0427Ч	I
    //   3: getstatic 48	kkkkkk/ppkpkk:b0427ЧЧ0427Ч0427Ч0427Ч	I
    //   6: iadd
    //   7: getstatic 46	kkkkkk/ppkpkk:bЧ04270427ЧЧ0427Ч0427Ч	I
    //   10: imul
    //   11: getstatic 50	kkkkkk/ppkpkk:bЧЧЧ0427Ч0427Ч0427Ч	I
    //   14: irem
    //   15: getstatic 52	kkkkkk/ppkpkk:b042704270427ЧЧ0427Ч0427Ч	I
    //   18: if_icmpeq +13 -> 31
    //   21: bipush 35
    //   23: putstatic 46	kkkkkk/ppkpkk:bЧ04270427ЧЧ0427Ч0427Ч	I
    //   26: bipush 49
    //   28: putstatic 52	kkkkkk/ppkpkk:b042704270427ЧЧ0427Ч0427Ч	I
    //   31: aload_0
    //   32: getfield 32	kkkkkk/ppkpkk:bЧЧ0427ЧЧ0427Ч0427Ч	I
    //   35: istore_1
    //   36: getstatic 46	kkkkkk/ppkpkk:bЧ04270427ЧЧ0427Ч0427Ч	I
    //   39: istore_2
    //   40: iload_2
    //   41: getstatic 48	kkkkkk/ppkpkk:b0427ЧЧ0427Ч0427Ч0427Ч	I
    //   44: iload_2
    //   45: iadd
    //   46: imul
    //   47: getstatic 50	kkkkkk/ppkpkk:bЧЧЧ0427Ч0427Ч0427Ч	I
    //   50: irem
    //   51: tableswitch	default:+17->68, 0:+26->77
    //   68: iconst_2
    //   69: putstatic 46	kkkkkk/ppkpkk:bЧ04270427ЧЧ0427Ч0427Ч	I
    //   72: bipush 33
    //   74: putstatic 52	kkkkkk/ppkpkk:b042704270427ЧЧ0427Ч0427Ч	I
    //   77: aload_0
    //   78: iload_1
    //   79: iconst_1
    //   80: iadd
    //   81: putfield 32	kkkkkk/ppkpkk:bЧЧ0427ЧЧ0427Ч0427Ч	I
    //   84: return
    //   85: astore_3
    //   86: aload_3
    //   87: athrow
    //   88: astore_3
    //   89: aload_3
    //   90: athrow
    // Local variable table:
    //   start	length	slot	name	signature
    //   0	91	0	this	ppkpkk
    //   35	46	1	i	int
    //   39	8	2	j	int
    //   85	2	3	localException1	Exception
    //   88	2	3	localException2	Exception
    // Exception table:
    //   from	to	target	type
    //   31	36	85	java/lang/Exception
    //   77	84	88	java/lang/Exception
  }
  
  @NonNull
  @ooiiio("trivial")
  public cccrcc bж0436ж0436ж04360436жж0436(String paramString)
  {
    Map localMap;
    int i;
    try
    {
      localMap = this.bЧ0427ЧЧЧ0427Ч0427Ч.b043F043F043F043Fпппппп();
      boolean bool = localMap.containsKey(paramString);
      if (bool) {
        break label102;
      }
      i = bЧ04270427ЧЧ0427Ч0427Ч;
      switch (i * (b0427ЧЧ0427Ч0427Ч0427Ч + i) % bЧЧЧ0427Ч0427Ч0427Ч)
      {
      default: 
        bЧ04270427ЧЧ0427Ч0427Ч = 27;
        b042704270427ЧЧ0427Ч0427Ч = 43;
      }
      paramString = new IllegalStateException(String.format(gguuuu.bккккк043Aкк043A043A("\033:2//kA=n76Fr5GH8F@?HAKR~WJVK\004ZTRVXaY\f62)\020\026e", 'F', '\000'), new Object[] { paramString }));
    }
    catch (Exception paramString)
    {
      throw paramString;
    }
    throw paramString;
    label102:
    paramString = (cccrcc)localMap.get(paramString);
    try
    {
      i = bЧ04270427ЧЧ0427Ч0427Ч;
      int j = bж0436жжж04360436жж0436();
      int k = bЧ04270427ЧЧ0427Ч0427Ч;
      int m = bЧЧЧ0427Ч0427Ч0427Ч;
      int n = b04360436жжж04360436жж0436();
      if ((i + j) * k % m != n)
      {
        bЧ04270427ЧЧ0427Ч0427Ч = bжж0436жж04360436жж0436();
        b042704270427ЧЧ0427Ч0427Ч = bжж0436жж04360436жж0436();
      }
      return paramString;
    }
    catch (Exception paramString)
    {
      throw paramString;
    }
    switch (0)
    {
    }
    for (;;)
    {
      switch (1)
      {
      }
    }
  }
  
  /* Error */
  public io.reactivex.Completable bж0436жж043604360436жж0436()
  {
    // Byte code:
    //   0: aload_0
    //   1: iconst_0
    //   2: invokespecial 154	kkkkkk/ppkpkk:b0436043604360436ж04360436жж0436	(I)Lio/reactivex/Single;
    //   5: astore 6
    //   7: new 287	kkkkkk/ppkpkk$6
    //   10: dup
    //   11: aload_0
    //   12: invokespecial 288	kkkkkk/ppkpkk$6:<init>	(Lkkkkkk/ppkpkk;)V
    //   15: astore 7
    //   17: aload 6
    //   19: aload 7
    //   21: invokevirtual 292	io/reactivex/Single:flatMapCompletable	(Lio/reactivex/functions/Function;)Lio/reactivex/Completable;
    //   24: astore 6
    //   26: getstatic 46	kkkkkk/ppkpkk:bЧ04270427ЧЧ0427Ч0427Ч	I
    //   29: istore_1
    //   30: getstatic 48	kkkkkk/ppkpkk:b0427ЧЧ0427Ч0427Ч0427Ч	I
    //   33: istore_2
    //   34: getstatic 46	kkkkkk/ppkpkk:bЧ04270427ЧЧ0427Ч0427Ч	I
    //   37: istore_3
    //   38: getstatic 50	kkkkkk/ppkpkk:bЧЧЧ0427Ч0427Ч0427Ч	I
    //   41: istore 4
    //   43: invokestatic 158	kkkkkk/ppkpkk:b04360436жжж04360436жж0436	()I
    //   46: istore 5
    //   48: iload_1
    //   49: iload_2
    //   50: iadd
    //   51: iload_3
    //   52: imul
    //   53: iload 4
    //   55: irem
    //   56: iload 5
    //   58: if_icmpeq +60 -> 118
    //   61: getstatic 46	kkkkkk/ppkpkk:bЧ04270427ЧЧ0427Ч0427Ч	I
    //   64: istore_1
    //   65: iload_1
    //   66: getstatic 48	kkkkkk/ppkpkk:b0427ЧЧ0427Ч0427Ч0427Ч	I
    //   69: iload_1
    //   70: iadd
    //   71: imul
    //   72: getstatic 50	kkkkkk/ppkpkk:bЧЧЧ0427Ч0427Ч0427Ч	I
    //   75: irem
    //   76: tableswitch	default:+20->96, 0:+31->107
    //   96: invokestatic 56	kkkkkk/ppkpkk:bжж0436жж04360436жж0436	()I
    //   99: putstatic 46	kkkkkk/ppkpkk:bЧ04270427ЧЧ0427Ч0427Ч	I
    //   102: bipush 40
    //   104: putstatic 52	kkkkkk/ppkpkk:b042704270427ЧЧ0427Ч0427Ч	I
    //   107: invokestatic 56	kkkkkk/ppkpkk:bжж0436жж04360436жж0436	()I
    //   110: putstatic 46	kkkkkk/ppkpkk:bЧ04270427ЧЧ0427Ч0427Ч	I
    //   113: bipush 32
    //   115: putstatic 52	kkkkkk/ppkpkk:b042704270427ЧЧ0427Ч0427Ч	I
    //   118: aload 6
    //   120: areturn
    //   121: astore 6
    //   123: aload 6
    //   125: athrow
    //   126: astore 6
    //   128: aload 6
    //   130: athrow
    // Local variable table:
    //   start	length	slot	name	signature
    //   0	131	0	this	ppkpkk
    //   29	43	1	i	int
    //   33	18	2	j	int
    //   37	16	3	k	int
    //   41	15	4	m	int
    //   46	13	5	n	int
    //   5	114	6	localObject	Object
    //   121	3	6	localException1	Exception
    //   126	3	6	localException2	Exception
    //   15	5	7	local6	ppkpkk.6
    // Exception table:
    //   from	to	target	type
    //   7	17	121	java/lang/Exception
    //   107	118	121	java/lang/Exception
    //   0	7	126	java/lang/Exception
    //   17	48	126	java/lang/Exception
  }
  
  @Nullable
  public String bжж04360436ж04360436жж0436()
  {
    int i = bжж0436жж04360436жж0436();
    switch (i * (b0427ЧЧ0427Ч0427Ч0427Ч + i) % bЧЧЧ0427Ч0427Ч0427Ч)
    {
    default: 
      bЧ04270427ЧЧ0427Ч0427Ч = 73;
      b042704270427ЧЧ0427Ч0427Ч = bжж0436жж04360436жж0436();
    }
    try
    {
      localObject = b04360436ж0436ж04360436жж0436().iterator();
      while (((Iterator)localObject).hasNext())
      {
        localCccrcc = (cccrcc)((Iterator)localObject).next();
        boolean bool = ejejjj.b0444044404440444044404440444фф0444(localCccrcc);
        if (bool)
        {
          i = bЧ04270427ЧЧ0427Ч0427Ч;
          switch (i * (b0427ЧЧ0427Ч0427Ч0427Ч + i) % bЧЧЧ0427Ч0427Ч0427Ч)
          {
          default: 
            bЧ04270427ЧЧ0427Ч0427Ч = 19;
            b042704270427ЧЧ0427Ч0427Ч = bжж0436жж04360436жж0436();
          }
        }
      }
    }
    catch (Exception localException1)
    {
      Object localObject;
      cccrcc localCccrcc;
      throw localException1;
    }
    try
    {
      localObject = localCccrcc.bжж0436ж0436жжж04360436();
      return localObject;
    }
    catch (Exception localException2)
    {
      throw localException2;
    }
    switch (0)
    {
    case 1: 
    default: 
      for (;;)
      {
        switch (0)
        {
        }
      }
    }
    return null;
  }
  
  /* Error */
  public Single<cccrcc> bжжж0436ж04360436жж0436(String paramString)
  {
    // Byte code:
    //   0: aload_0
    //   1: invokevirtual 305	kkkkkk/ppkpkk:b0436жж0436ж04360436жж0436	()Lio/reactivex/Single;
    //   4: astore 5
    //   6: getstatic 46	kkkkkk/ppkpkk:bЧ04270427ЧЧ0427Ч0427Ч	I
    //   9: istore_2
    //   10: getstatic 48	kkkkkk/ppkpkk:b0427ЧЧ0427Ч0427Ч0427Ч	I
    //   13: istore_3
    //   14: getstatic 50	kkkkkk/ppkpkk:bЧЧЧ0427Ч0427Ч0427Ч	I
    //   17: istore 4
    //   19: iload_2
    //   20: iload_3
    //   21: iload_2
    //   22: iadd
    //   23: imul
    //   24: iload 4
    //   26: irem
    //   27: tableswitch	default:+17->44, 0:+29->56
    //   44: invokestatic 56	kkkkkk/ppkpkk:bжж0436жж04360436жж0436	()I
    //   47: putstatic 46	kkkkkk/ppkpkk:bЧ04270427ЧЧ0427Ч0427Ч	I
    //   50: invokestatic 56	kkkkkk/ppkpkk:bжж0436жж04360436жж0436	()I
    //   53: putstatic 52	kkkkkk/ppkpkk:b042704270427ЧЧ0427Ч0427Ч	I
    //   56: aload 5
    //   58: new 307	kkkkkk/ppkpkk$5
    //   61: dup
    //   62: aload_0
    //   63: aload_1
    //   64: invokespecial 310	kkkkkk/ppkpkk$5:<init>	(Lkkkkkk/ppkpkk;Ljava/lang/String;)V
    //   67: invokevirtual 208	io/reactivex/Single:map	(Lio/reactivex/functions/Function;)Lio/reactivex/Single;
    //   70: astore_1
    //   71: aload_1
    //   72: areturn
    //   73: astore_1
    //   74: aload_1
    //   75: athrow
    //   76: astore_1
    //   77: aload_1
    //   78: athrow
    // Local variable table:
    //   start	length	slot	name	signature
    //   0	79	0	this	ppkpkk
    //   0	79	1	paramString	String
    //   9	15	2	i	int
    //   13	10	3	j	int
    //   17	10	4	k	int
    //   4	53	5	localSingle	Single
    // Exception table:
    //   from	to	target	type
    //   0	6	73	java/lang/Exception
    //   14	19	73	java/lang/Exception
    //   56	71	73	java/lang/Exception
    //   6	14	76	java/lang/Exception
    //   44	56	76	java/lang/Exception
  }
}
