package kkkkkk;

import android.content.Context;
import android.support.annotation.Nullable;
import android.support.annotation.VisibleForTesting;
import android.webkit.WebView;
import io.reactivex.Completable;
import io.reactivex.Single;
import io.reactivex.functions.Action;
import java.util.ArrayList;
import java.util.Iterator;
import java.util.List;
import java.util.Map;
import shaded.org.apache.commons.lang3.StringUtils;

public abstract class ppppii
  extends rgrrrg<pipppi>
  implements jqqjjq
{
  public static int b043D043Dн043Dннн043Dн = 1;
  public static int b043Dн043D043Dннн043Dн = 92;
  public static int bн043D043D043Dннн043Dн = 0;
  public static int bнн043D043Dннн043Dн = 2;
  public final kpkkpk b043D043D043Dнннн043Dн;
  private final qqqqjq b043Dн043Dнннн043Dн;
  private final yyuyuy b043Dнн043Dннн043Dн;
  public final kkkppk bн043D043Dнннн043Dн;
  public final ciciic bн043Dн043Dннн043Dн = new ppppii.1(this);
  public final Context bннн043Dннн043Dн;
  
  public ppppii(kkkppk paramKkkppk, Context paramContext, qqqqjq paramQqqqjq, yyuyuy paramYyuyuy, kpkkpk paramKpkkpk)
  {
    this.bн043D043Dнннн043Dн = paramKkkppk;
    this.bннн043Dннн043Dн = paramContext;
    this.b043Dн043Dнннн043Dн = paramQqqqjq;
    this.b043Dнн043Dннн043Dн = paramYyuyuy;
    this.b043D043D043Dнннн043Dн = paramKpkkpk;
  }
  
  public static int b04300430043004300430аа0430а0430()
  {
    return 1;
  }
  
  /* Error */
  @Nullable
  @ooiiio("Trivial")
  private ppipii b04300430ааа0430а0430а0430(@Nullable luuuuu paramLuuuuu)
  {
    // Byte code:
    //   0: aload_1
    //   1: ifnull +61 -> 62
    //   4: getstatic 59	kkkkkk/ppppii:b043Dн043D043Dннн043Dн	I
    //   7: istore_2
    //   8: getstatic 81	kkkkkk/ppppii:b043D043Dн043Dннн043Dн	I
    //   11: istore_3
    //   12: getstatic 59	kkkkkk/ppppii:b043Dн043D043Dннн043Dн	I
    //   15: istore 4
    //   17: getstatic 83	kkkkkk/ppppii:bнн043D043Dннн043Dн	I
    //   20: istore 5
    //   22: getstatic 69	kkkkkk/ppppii:bн043D043D043Dннн043Dн	I
    //   25: istore 6
    //   27: iload_2
    //   28: iload_3
    //   29: iadd
    //   30: iload 4
    //   32: imul
    //   33: iload 5
    //   35: irem
    //   36: iload 6
    //   38: if_icmpeq +13 -> 51
    //   41: iconst_0
    //   42: putstatic 59	kkkkkk/ppppii:b043Dн043D043Dннн043Dн	I
    //   45: invokestatic 67	kkkkkk/ppppii:b0430аааа0430а0430а0430	()I
    //   48: putstatic 69	kkkkkk/ppppii:bн043D043D043Dннн043Dн	I
    //   51: new 85	kkkkkk/ppipii
    //   54: dup
    //   55: aload_1
    //   56: invokespecial 88	kkkkkk/ppipii:<init>	(Lkkkkkk/luuuuu;)V
    //   59: astore_1
    //   60: aload_1
    //   61: areturn
    //   62: aconst_null
    //   63: astore_1
    //   64: getstatic 59	kkkkkk/ppppii:b043Dн043D043Dннн043Dн	I
    //   67: istore_2
    //   68: iload_2
    //   69: getstatic 81	kkkkkk/ppppii:b043D043Dн043Dннн043Dн	I
    //   72: iload_2
    //   73: iadd
    //   74: imul
    //   75: getstatic 83	kkkkkk/ppppii:bнн043D043Dннн043Dн	I
    //   78: irem
    //   79: tableswitch	default:+17->96, 0:+-19->60
    //   96: bipush 61
    //   98: putstatic 59	kkkkkk/ppppii:b043Dн043D043Dннн043Dн	I
    //   101: bipush 31
    //   103: putstatic 69	kkkkkk/ppppii:bн043D043D043Dннн043Dн	I
    //   106: aconst_null
    //   107: areturn
    //   108: astore_1
    //   109: aload_1
    //   110: athrow
    //   111: astore_1
    //   112: aload_1
    //   113: athrow
    //   114: astore_1
    //   115: aload_1
    //   116: athrow
    // Local variable table:
    //   start	length	slot	name	signature
    //   0	117	0	this	ppppii
    //   0	117	1	paramLuuuuu	luuuuu
    //   7	68	2	i	int
    //   11	19	3	j	int
    //   15	18	4	k	int
    //   20	16	5	m	int
    //   25	14	6	n	int
    // Exception table:
    //   from	to	target	type
    //   51	60	108	java/lang/Exception
    //   41	51	111	java/lang/Exception
    //   109	111	111	java/lang/Exception
    //   4	27	114	java/lang/Exception
  }
  
  private void b0430а0430аа0430а0430а0430(luuuuu paramLuuuuu)
  {
    this.b043Dнн043Dннн043Dн.bъъ044Aъъ044Aъ044Aъ044A(paramLuuuuu);
    int i = b043Dн043D043Dннн043Dн;
    switch (i * (b043D043Dн043Dннн043Dн + i) % bнн043D043Dннн043Dн)
    {
    default: 
      b043Dн043D043Dннн043Dн = b0430аааа0430а0430а0430();
      bн043D043D043Dннн043Dн = b0430аааа0430а0430а0430();
    }
    paramLuuuuu = this.bн043D043Dнннн043Dн.bж0436ж0436жжжжж0436(paramLuuuuu, iieiei.DISPLAYED);
    Action localAction = fffbbb.b042EЮ042EЮЮЮЮ042EЮ;
    i = b043Dн043D043Dннн043Dн;
    switch (i * (b043D043Dн043Dннн043Dн + i) % bнн043D043Dннн043Dн)
    {
    default: 
      b043Dн043D043Dннн043Dн = b0430аааа0430а0430а0430();
      bн043D043D043Dннн043Dн = 92;
    }
    switch (1)
    {
    case 0: 
    default: 
      for (;;)
      {
        switch (0)
        {
        }
      }
    }
    b04180418И0418ИИИ0418ИИ(paramLuuuuu.subscribe(localAction, b0418041804180418И0418И0418ИИ()));
    switch (1)
    {
    case 0: 
    default: 
      for (;;)
      {
        switch (1)
        {
        }
      }
    }
  }
  
  public static int b0430аааа0430а0430а0430()
  {
    return 99;
  }
  
  public static int bа0430043004300430аа0430а0430()
  {
    return 0;
  }
  
  private List<ipippi> bа0430ааа0430а0430а0430(List<luuuuu> paramList)
  {
    try
    {
      ArrayList localArrayList = new ArrayList();
      switch (0)
      {
      case 1: 
      default: 
        for (;;)
        {
          switch (1)
          {
          }
        }
      }
      int i = b043Dн043D043Dннн043Dн;
      switch (i * (b043D043Dн043Dннн043Dн + i) % bнн043D043Dннн043Dн)
      {
      default: 
        b043Dн043D043Dннн043Dн = 86;
        bн043D043D043Dннн043Dн = 86;
      }
      paramList = paramList.iterator();
      for (;;)
      {
        boolean bool = paramList.hasNext();
        if (bool) {
          try
          {
            ipippi localIpippi = new ipippi(null, new ppipii((luuuuu)paramList.next()), kkkkpk.ACCOUNT_STYLE_MODULE_LEAD);
            if ((b043Dн043D043Dннн043Dн + b043D043Dн043Dннн043Dн) * b043Dн043D043Dннн043Dн % bнн043D043Dннн043Dн != bн043D043D043Dннн043Dн)
            {
              b043Dн043D043Dннн043Dн = b0430аааа0430а0430а0430();
              bн043D043D043Dннн043Dн = b0430аааа0430а0430а0430();
            }
            localArrayList.add(localIpippi);
          }
          catch (Exception paramList)
          {
            throw paramList;
          }
        }
      }
      return localArrayList;
    }
    catch (Exception paramList)
    {
      throw paramList;
    }
  }
  
  public static int bааааа0430а0430а0430()
  {
    return 2;
  }
  
  /* Error */
  @ooiiio("Trivial")
  public void b043004300430аа0430043004300430а(int paramInt)
  {
    // Byte code:
    //   0: aload_0
    //   1: getfield 183	kkkkkk/ppppii:b042804280428ШШ042804280428Ш	Lkkkkkk/gggggr$grrrrg;
    //   4: checkcast 187	kkkkkk/pipppi
    //   7: iload_1
    //   8: invokeinterface 190 2 0
    //   13: getstatic 59	kkkkkk/ppppii:b043Dн043D043Dннн043Dн	I
    //   16: istore_1
    //   17: getstatic 81	kkkkkk/ppppii:b043D043Dн043Dннн043Dн	I
    //   20: istore_2
    //   21: getstatic 59	kkkkkk/ppppii:b043Dн043D043Dннн043Dн	I
    //   24: istore_3
    //   25: getstatic 83	kkkkkk/ppppii:bнн043D043Dннн043Dн	I
    //   28: istore 4
    //   30: getstatic 69	kkkkkk/ppppii:bн043D043D043Dннн043Dн	I
    //   33: istore 5
    //   35: iload_1
    //   36: iload_2
    //   37: iadd
    //   38: iload_3
    //   39: imul
    //   40: iload 4
    //   42: irem
    //   43: iload 5
    //   45: if_icmpeq +57 -> 102
    //   48: invokestatic 67	kkkkkk/ppppii:b0430аааа0430а0430а0430	()I
    //   51: putstatic 59	kkkkkk/ppppii:b043Dн043D043Dннн043Dн	I
    //   54: bipush 61
    //   56: putstatic 69	kkkkkk/ppppii:bн043D043D043Dннн043Dн	I
    //   59: getstatic 59	kkkkkk/ppppii:b043Dн043D043Dннн043Dн	I
    //   62: istore_1
    //   63: iload_1
    //   64: invokestatic 61	kkkkkk/ppppii:b04300430043004300430аа0430а0430	()I
    //   67: iload_1
    //   68: iadd
    //   69: imul
    //   70: getstatic 83	kkkkkk/ppppii:bнн043D043Dннн043Dн	I
    //   73: irem
    //   74: tableswitch	default:+18->92, 0:+28->102
    //   92: bipush 8
    //   94: putstatic 59	kkkkkk/ppppii:b043Dн043D043Dннн043Dн	I
    //   97: bipush 44
    //   99: putstatic 69	kkkkkk/ppppii:bн043D043D043Dннн043Dн	I
    //   102: return
    //   103: astore 6
    //   105: aload 6
    //   107: athrow
    //   108: astore 6
    //   110: aload 6
    //   112: athrow
    //   113: astore 6
    //   115: aload 6
    //   117: athrow
    // Local variable table:
    //   start	length	slot	name	signature
    //   0	118	0	this	ppppii
    //   0	118	1	paramInt	int
    //   20	18	2	i	int
    //   24	16	3	j	int
    //   28	15	4	k	int
    //   33	13	5	m	int
    //   103	3	6	localException1	Exception
    //   108	3	6	localException2	Exception
    //   113	3	6	localException3	Exception
    // Exception table:
    //   from	to	target	type
    //   0	13	103	java/lang/Exception
    //   13	35	108	java/lang/Exception
    //   105	108	108	java/lang/Exception
    //   48	59	113	java/lang/Exception
  }
  
  public abstract void b043004300430аа04300430аа0430();
  
  public void b043004300430аа0430а0430а0430(String paramString, boolean paramBoolean)
  {
    this.bн043D043Dнннн043Dн.b0436жж0436жжжжж0436(paramString);
    if (paramBoolean) {
      ((pipppi)this.b042804280428ШШ042804280428Ш).notifyParentOfArrangementScrolledTo(paramString);
    }
  }
  
  /* Error */
  public void b04300430а0430а0430а0430а0430()
  {
    // Byte code:
    //   0: aload_0
    //   1: invokevirtual 204	kkkkkk/ppppii:b0430аа0430а04300430аа0430	()Lkkkkkk/luuuuu;
    //   4: astore 4
    //   6: aload 4
    //   8: ifnull +120 -> 128
    //   11: new 85	kkkkkk/ppipii
    //   14: dup
    //   15: aload 4
    //   17: invokespecial 88	kkkkkk/ppipii:<init>	(Lkkkkkk/luuuuu;)V
    //   20: astore_2
    //   21: aload_0
    //   22: getfield 183	kkkkkk/ppppii:b042804280428ШШ042804280428Ш	Lkkkkkk/gggggr$grrrrg;
    //   25: checkcast 187	kkkkkk/pipppi
    //   28: astore_3
    //   29: aload 4
    //   31: invokevirtual 208	kkkkkk/luuuuu:b0412В0412В0412В0412041204120412	()Ljava/lang/String;
    //   34: astore 4
    //   36: aload_0
    //   37: getfield 40	kkkkkk/ppppii:bн043Dн043Dннн043Dн	Lkkkkkk/ciciic;
    //   40: astore 5
    //   42: getstatic 59	kkkkkk/ppppii:b043Dн043D043Dннн043Dн	I
    //   45: getstatic 81	kkkkkk/ppppii:b043D043Dн043Dннн043Dн	I
    //   48: iadd
    //   49: getstatic 59	kkkkkk/ppppii:b043Dн043D043Dннн043Dн	I
    //   52: imul
    //   53: getstatic 83	kkkkkk/ppppii:bнн043D043Dннн043Dн	I
    //   56: irem
    //   57: getstatic 69	kkkkkk/ppppii:bн043D043D043Dннн043Dн	I
    //   60: if_icmpeq +57 -> 117
    //   63: getstatic 59	kkkkkk/ppppii:b043Dн043D043Dннн043Dн	I
    //   66: istore_1
    //   67: iload_1
    //   68: getstatic 81	kkkkkk/ppppii:b043D043Dн043Dннн043Dн	I
    //   71: iload_1
    //   72: iadd
    //   73: imul
    //   74: getstatic 83	kkkkkk/ppppii:bнн043D043Dннн043Dн	I
    //   77: irem
    //   78: tableswitch	default:+18->96, 0:+29->107
    //   96: bipush 23
    //   98: putstatic 59	kkkkkk/ppppii:b043Dн043D043Dннн043Dн	I
    //   101: invokestatic 67	kkkkkk/ppppii:b0430аааа0430а0430а0430	()I
    //   104: putstatic 69	kkkkkk/ppppii:bн043D043D043Dннн043Dн	I
    //   107: bipush 99
    //   109: putstatic 59	kkkkkk/ppppii:b043Dн043D043Dннн043Dн	I
    //   112: bipush 80
    //   114: putstatic 69	kkkkkk/ppppii:bн043D043D043Dннн043Dн	I
    //   117: aload_3
    //   118: aload 4
    //   120: aload_2
    //   121: aload 5
    //   123: invokeinterface 212 4 0
    //   128: return
    //   129: astore_2
    //   130: aload_2
    //   131: athrow
    //   132: astore_2
    //   133: aload_2
    //   134: athrow
    // Local variable table:
    //   start	length	slot	name	signature
    //   0	135	0	this	ppppii
    //   66	8	1	i	int
    //   20	101	2	localPpipii	ppipii
    //   129	2	2	localException1	Exception
    //   132	2	2	localException2	Exception
    //   28	90	3	localPipppi	pipppi
    //   4	115	4	localObject	Object
    //   40	82	5	localCiciic	ciciic
    // Exception table:
    //   from	to	target	type
    //   11	42	129	java/lang/Exception
    //   0	6	132	java/lang/Exception
    //   117	128	132	java/lang/Exception
  }
  
  @VisibleForTesting
  public List<ipippi> b0430а043004300430аа0430а0430(List<iiiipi> paramList, rccrcc paramRccrcc)
  {
    List localList = paramRccrcc.bж0436жжжж0436043604360436();
    Map localMap = paramRccrcc.b0436жжжжж0436043604360436();
    ArrayList localArrayList = new ArrayList();
    Object localObject = (iiiipi)paramList.remove(0);
    paramRccrcc = ((iiiipi)localObject).b043004300430043004300430а0430а0430();
    localArrayList.add(new ipippi((iiiipi)localObject, b04300430ааа0430а0430а0430((luuuuu)localMap.get(paramRccrcc)), kkkkpk.b043604360436жж0436жжж0436(paramRccrcc)));
    if (!localList.isEmpty()) {
      localArrayList.add(new ipippi(null, new ppipii((luuuuu)localList.remove(0)), kkkkpk.ACCOUNT_STYLE_MODULE_LEAD));
    }
    if (!paramList.isEmpty())
    {
      localObject = ((iiiipi)paramList.get(0)).b043004300430043004300430а0430а0430();
      int i = b043Dн043D043Dннн043Dн;
      paramRccrcc = (rccrcc)localObject;
      switch (i * (b043D043Dн043Dннн043Dн + i) % bааааа0430а0430а0430())
      {
      default: 
        b043Dн043D043Dннн043Dн = b0430аааа0430а0430а0430();
        bн043D043D043Dннн043Dн = b0430аааа0430а0430а0430();
        paramRccrcc = (rccrcc)localObject;
      }
    }
    for (;;)
    {
      Iterator localIterator = paramList.iterator();
      switch (1)
      {
      case 0: 
      default: 
        for (;;)
        {
          switch (0)
          {
          }
        }
      }
      paramList = paramRccrcc;
      iiiipi localIiiipi;
      if (localIterator.hasNext())
      {
        localIiiipi = (iiiipi)localIterator.next();
        localObject = localIiiipi.b043004300430043004300430а0430а0430();
        if (paramList == localObject) {
          break label498;
        }
        if (!localList.isEmpty()) {
          localArrayList.add(new ipippi(null, new ppipii((luuuuu)localList.remove(0)), kkkkpk.ACCOUNT_STYLE_MODULE_LEAD));
        }
        paramRccrcc = b04300430ааа0430а0430а0430((luuuuu)localMap.get(localObject));
        paramList = (List<iiiipi>)localObject;
      }
      for (;;)
      {
        localArrayList.add(new ipippi(localIiiipi, paramRccrcc, kkkkpk.b043604360436жж0436жжж0436((ccrrcc)localObject)));
        switch (0)
        {
        case 1: 
        default: 
          for (;;)
          {
            switch (1)
            {
            }
          }
        }
        break;
        if (!localList.isEmpty())
        {
          localArrayList.addAll(bа0430ааа0430а0430а0430(localList));
          if ((b043Dн043D043Dннн043Dн + b043D043Dн043Dннн043Dн) * b043Dн043D043Dннн043Dн % bнн043D043Dннн043Dн != bн043D043D043Dннн043Dн)
          {
            b043Dн043D043Dннн043Dн = b0430аааа0430а0430а0430();
            bн043D043D043Dннн043Dн = b0430аааа0430а0430а0430();
          }
        }
        return localArrayList;
        label498:
        paramRccrcc = null;
      }
    }
  }
  
  @ooiiio("Trivial")
  public void b0430а04300430а0430а0430а0430(int paramInt, String paramString)
  {
    try
    {
      qqqqjq localQqqqjq = this.b043Dн043Dнннн043Dн;
      int i = b043Dн043D043Dннн043Dн;
      switch (i * (b043D043Dн043Dннн043Dн + i) % bнн043D043Dннн043Dн)
      {
      default: 
        b043Dн043D043Dннн043Dн = 40;
        bн043D043D043Dннн043Dн = b0430аааа0430а0430а0430();
      }
      localQqqqjq.bа04300430043004300430043004300430а(paramInt, paramString);
      paramInt = b043Dн043D043Dннн043Dн;
      switch (paramInt * (b043D043Dн043Dннн043Dн + paramInt) % bнн043D043Dннн043Dн)
      {
      default: 
        switch (0)
        {
        case 1: 
        default: 
          for (;;)
          {
            switch (1)
            {
            }
          }
        }
        b043Dн043D043Dннн043Dн = 1;
        bн043D043D043Dннн043Dн = 8;
      }
      return;
    }
    catch (Exception paramString)
    {
      throw paramString;
    }
  }
  
  @Nullable
  public abstract luuuuu b0430аа0430а04300430аа0430();
  
  /* Error */
  @ooiiio("Trivial")
  public void b0430аа0430а0430а0430а0430(ppipii paramPpipii)
  {
    // Byte code:
    //   0: invokestatic 67	kkkkkk/ppppii:b0430аааа0430а0430а0430	()I
    //   3: getstatic 81	kkkkkk/ppppii:b043D043Dн043Dннн043Dн	I
    //   6: iadd
    //   7: invokestatic 67	kkkkkk/ppppii:b0430аааа0430а0430а0430	()I
    //   10: imul
    //   11: getstatic 83	kkkkkk/ppppii:bнн043D043Dннн043Dн	I
    //   14: irem
    //   15: getstatic 69	kkkkkk/ppppii:bн043D043D043Dннн043Dн	I
    //   18: if_icmpeq +46 -> 64
    //   21: getstatic 59	kkkkkk/ppppii:b043Dн043D043Dннн043Dн	I
    //   24: getstatic 81	kkkkkk/ppppii:b043D043Dн043Dннн043Dн	I
    //   27: iadd
    //   28: getstatic 59	kkkkkk/ppppii:b043Dн043D043Dннн043Dн	I
    //   31: imul
    //   32: getstatic 83	kkkkkk/ppppii:bнн043D043Dннн043Dн	I
    //   35: irem
    //   36: getstatic 69	kkkkkk/ppppii:bн043D043D043Dннн043Dн	I
    //   39: if_icmpeq +14 -> 53
    //   42: invokestatic 67	kkkkkk/ppppii:b0430аааа0430а0430а0430	()I
    //   45: putstatic 59	kkkkkk/ppppii:b043Dн043D043Dннн043Dн	I
    //   48: bipush 52
    //   50: putstatic 69	kkkkkk/ppppii:bн043D043D043Dннн043Dн	I
    //   53: bipush 77
    //   55: putstatic 59	kkkkkk/ppppii:b043Dн043D043Dннн043Dн	I
    //   58: invokestatic 67	kkkkkk/ppppii:b0430аааа0430а0430а0430	()I
    //   61: putstatic 69	kkkkkk/ppppii:bн043D043D043Dннн043Dн	I
    //   64: aload_1
    //   65: invokevirtual 271	kkkkkk/ppipii:b0430аа0430а043004300430а0430	()Z
    //   68: istore_2
    //   69: iload_2
    //   70: ifeq +11 -> 81
    //   73: aload_0
    //   74: aload_1
    //   75: invokevirtual 274	kkkkkk/ppipii:bааа0430а043004300430а0430	()Lkkkkkk/luuuuu;
    //   78: invokespecial 276	kkkkkk/ppppii:b0430а0430аа0430а0430а0430	(Lkkkkkk/luuuuu;)V
    //   81: return
    //   82: astore_1
    //   83: aload_1
    //   84: athrow
    //   85: astore_1
    //   86: aload_1
    //   87: athrow
    // Local variable table:
    //   start	length	slot	name	signature
    //   0	88	0	this	ppppii
    //   0	88	1	paramPpipii	ppipii
    //   68	2	2	bool	boolean
    // Exception table:
    //   from	to	target	type
    //   64	69	82	java/lang/Exception
    //   73	81	85	java/lang/Exception
  }
  
  public void bа04300430аа0430043004300430а(int paramInt, ipippi.piippi paramPiippi)
  {
    try
    {
      iiiipi localIiiipi = ((pipppi)this.b042804280428ШШ042804280428Ш).getArrangementTileViewModelForPosition(paramInt);
      try
      {
        localObject = ipippi.piippi.ACCOUNT_ALERT;
        if (paramPiippi == localObject)
        {
          paramInt = b043Dн043D043Dннн043Dн;
          switch (paramInt * (b04300430043004300430аа0430а0430() + paramInt) % bааааа0430а0430а0430())
          {
          default: 
            b043Dн043D043Dннн043Dн = 66;
            bн043D043D043Dннн043Dн = 87;
          }
          paramPiippi = localIiiipi.bаа0430а0430аа0430а0430();
          ((pipppi)this.b042804280428ШШ042804280428Ш).showAccountAlert(paramPiippi);
          return;
        }
        localObject = ipippi.piippi.CUSTOM_ALERT;
      }
      catch (Exception paramPiippi)
      {
        Object localObject;
        int i;
        int j;
        throw paramPiippi;
      }
      if (paramPiippi == localObject)
      {
        paramPiippi = localIiiipi.b0430а0430ааа04300430а0430();
        if (paramPiippi.b04300430а0430аа0430аа0430() == ippiip.pipiip.REACTIVATE_ISA)
        {
          paramInt = b043Dн043D043Dннн043Dн;
          i = b043D043Dн043Dннн043Dн;
          j = b043Dн043D043Dннн043Dн;
          if ((paramInt + i) * j % bнн043D043Dннн043Dн != bн043D043D043Dннн043Dн)
          {
            b043Dн043D043Dннн043Dн = 47;
            bн043D043D043Dннн043Dн = b0430аааа0430а0430а0430();
          }
          localObject = (pipppi)this.b042804280428ШШ042804280428Ш;
          ((pipppi)localObject).showReactivateIsaDialog(paramPiippi, localIiiipi.bааа0430аа04300430а0430());
          return;
        }
      }
    }
    catch (Exception paramPiippi)
    {
      throw paramPiippi;
    }
    return;
    switch (0)
    {
    }
    for (;;)
    {
      switch (1)
      {
      }
    }
  }
  
  /* Error */
  public void bа04300430аа0430а0430а0430()
  {
    // Byte code:
    //   0: aload_0
    //   1: getfield 42	kkkkkk/ppppii:bн043D043Dнннн043Dн	Lkkkkkk/kkkppk;
    //   4: invokeinterface 324 1 0
    //   9: getstatic 59	kkkkkk/ppppii:b043Dн043D043Dннн043Dн	I
    //   12: istore_1
    //   13: iload_1
    //   14: getstatic 81	kkkkkk/ppppii:b043D043Dн043Dннн043Dн	I
    //   17: iload_1
    //   18: iadd
    //   19: imul
    //   20: getstatic 83	kkkkkk/ppppii:bнн043D043Dннн043Dн	I
    //   23: irem
    //   24: tableswitch	default:+20->44, 0:+61->85
    //   44: bipush 52
    //   46: putstatic 59	kkkkkk/ppppii:b043Dн043D043Dннн043Dн	I
    //   49: bipush 59
    //   51: putstatic 69	kkkkkk/ppppii:bн043D043D043Dннн043Dн	I
    //   54: getstatic 59	kkkkkk/ppppii:b043Dн043D043Dннн043Dн	I
    //   57: getstatic 81	kkkkkk/ppppii:b043D043Dн043Dннн043Dн	I
    //   60: iadd
    //   61: getstatic 59	kkkkkk/ppppii:b043Dн043D043Dннн043Dн	I
    //   64: imul
    //   65: getstatic 83	kkkkkk/ppppii:bнн043D043Dннн043Dн	I
    //   68: irem
    //   69: getstatic 69	kkkkkk/ppppii:bн043D043D043Dннн043Dн	I
    //   72: if_icmpeq +13 -> 85
    //   75: bipush 82
    //   77: putstatic 59	kkkkkk/ppppii:b043Dн043D043Dннн043Dн	I
    //   80: bipush 23
    //   82: putstatic 69	kkkkkk/ppppii:bн043D043D043Dннн043Dн	I
    //   85: aload_0
    //   86: invokevirtual 327	kkkkkk/ppppii:bа0430а0430а0430а0430а0430	()V
    //   89: return
    //   90: astore_2
    //   91: aload_2
    //   92: athrow
    //   93: astore_2
    //   94: iconst_1
    //   95: tableswitch	default:+21->116, 0:+-1->94, 1:+48->143
    //   116: iconst_1
    //   117: tableswitch	default:+23->140, 0:+-23->94, 1:+26->143
    //   140: goto -24 -> 116
    //   143: aload_2
    //   144: athrow
    // Local variable table:
    //   start	length	slot	name	signature
    //   0	145	0	this	ppppii
    //   12	8	1	i	int
    //   90	2	2	localException1	Exception
    //   93	51	2	localException2	Exception
    // Exception table:
    //   from	to	target	type
    //   0	9	90	java/lang/Exception
    //   85	89	93	java/lang/Exception
  }
  
  public void bа0430а0430а0430а0430а0430()
  {
    String str = this.bн043D043Dнннн043Dн.b04360436жжжжжжж0436();
    switch (1)
    {
    case 0: 
    default: 
      for (;;)
      {
        switch (1)
        {
        case 0: 
        default: 
          for (;;)
          {
            switch (0)
            {
            }
          }
        }
        switch (0)
        {
        }
      }
    }
    if ((b043Dн043D043Dннн043Dн + b043D043Dн043Dннн043Dн) * b043Dн043D043Dннн043Dн % bнн043D043Dннн043Dн != bн043D043D043Dннн043Dн)
    {
      b043Dн043D043Dннн043Dн = b0430аааа0430а0430а0430();
      bн043D043D043Dннн043Dн = 17;
    }
    int i = b043Dн043D043Dннн043Dн;
    switch (i * (b043D043Dн043Dннн043Dн + i) % bнн043D043Dннн043Dн)
    {
    default: 
      b043Dн043D043Dннн043Dн = b0430аааа0430а0430а0430();
      bн043D043D043Dннн043Dн = b0430аааа0430а0430а0430();
    }
    if (StringUtils.isNoneEmpty(new CharSequence[] { str })) {
      ((pipppi)this.b042804280428ШШ042804280428Ш).showMessage(str);
    }
  }
  
  @ooiiio("Trivial")
  public void bаа04300430а0430а0430а0430(String paramString)
  {
    if ((b043Dн043D043Dннн043Dн + b043D043Dн043Dннн043Dн) * b043Dн043D043Dннн043Dн % bнн043D043Dннн043Dн != bа0430043004300430аа0430а0430())
    {
      b043Dн043D043Dннн043Dн = 46;
      bн043D043D043Dннн043Dн = 7;
    }
    int i = b043Dн043D043Dннн043Dн;
    switch (i * (b043D043Dн043Dннн043Dн + i) % bнн043D043Dннн043Dн)
    {
    default: 
      b043Dн043D043Dннн043Dн = b0430аааа0430а0430а0430();
      bн043D043D043Dннн043Dн = b0430аааа0430а0430а0430();
    }
    this.b043Dн043Dнннн043Dн.b0430а0430043004300430043004300430а(paramString);
  }
  
  /* Error */
  @ooiiio("Trivial")
  public void bаа0430аа0430а0430а0430()
  {
    // Byte code:
    //   0: aload_0
    //   1: getfield 183	kkkkkk/ppppii:b042804280428ШШ042804280428Ш	Lkkkkkk/gggggr$grrrrg;
    //   4: checkcast 187	kkkkkk/pipppi
    //   7: astore_1
    //   8: getstatic 59	kkkkkk/ppppii:b043Dн043D043Dннн043Dн	I
    //   11: getstatic 81	kkkkkk/ppppii:b043D043Dн043Dннн043Dн	I
    //   14: iadd
    //   15: getstatic 59	kkkkkk/ppppii:b043Dн043D043Dннн043Dн	I
    //   18: imul
    //   19: getstatic 83	kkkkkk/ppppii:bнн043D043Dннн043Dн	I
    //   22: irem
    //   23: getstatic 69	kkkkkk/ppppii:bн043D043D043Dннн043Dн	I
    //   26: if_icmpeq +46 -> 72
    //   29: invokestatic 67	kkkkkk/ppppii:b0430аааа0430а0430а0430	()I
    //   32: putstatic 59	kkkkkk/ppppii:b043Dн043D043Dннн043Dн	I
    //   35: bipush 43
    //   37: putstatic 69	kkkkkk/ppppii:bн043D043D043Dннн043Dн	I
    //   40: getstatic 59	kkkkkk/ppppii:b043Dн043D043Dннн043Dн	I
    //   43: getstatic 81	kkkkkk/ppppii:b043D043Dн043Dннн043Dн	I
    //   46: iadd
    //   47: getstatic 59	kkkkkk/ppppii:b043Dн043D043Dннн043Dн	I
    //   50: imul
    //   51: getstatic 83	kkkkkk/ppppii:bнн043D043Dннн043Dн	I
    //   54: irem
    //   55: invokestatic 344	kkkkkk/ppppii:bа0430043004300430аа0430а0430	()I
    //   58: if_icmpeq +14 -> 72
    //   61: invokestatic 67	kkkkkk/ppppii:b0430аааа0430а0430а0430	()I
    //   64: putstatic 59	kkkkkk/ppppii:b043Dн043D043Dннн043Dн	I
    //   67: bipush 73
    //   69: putstatic 69	kkkkkk/ppppii:bн043D043D043Dннн043Dн	I
    //   72: aload_1
    //   73: invokeinterface 351 1 0
    //   78: return
    //   79: astore_1
    //   80: aload_1
    //   81: athrow
    //   82: astore_1
    //   83: aload_1
    //   84: athrow
    // Local variable table:
    //   start	length	slot	name	signature
    //   0	85	0	this	ppppii
    //   7	66	1	localPipppi	pipppi
    //   79	2	1	localException1	Exception
    //   82	2	1	localException2	Exception
    // Exception table:
    //   from	to	target	type
    //   0	8	79	java/lang/Exception
    //   72	78	82	java/lang/Exception
  }
  
  @ooiiio("Trivial")
  public void bааа0430а0430043004300430а(int paramInt)
  {
    iiiipi localIiiipi = ((pipppi)this.b042804280428ШШ042804280428Ш).getArrangementTileViewModelForPosition(paramInt);
    this.bн043D043Dнннн043Dн.bжж0436жжжжжж0436(localIiiipi.bааа0430аа04300430а0430()).subscribe(new ppppii.2(this));
  }
  
  public void bааа0430а0430а0430а0430(boolean paramBoolean)
  {
    if (!paramBoolean) {}
    for (paramBoolean = true;; paramBoolean = false)
    {
      ((pipppi)this.b042804280428ШШ042804280428Ш).setStatementsCallToActionEnabled(paramBoolean);
      return;
    }
  }
  
  public void onPageFinished(WebView paramWebView, String paramString)
  {
    super.onPageFinished(paramWebView, paramString);
    if ((b043Dн043D043Dннн043Dн + b043D043Dн043Dннн043Dн) * b043Dн043D043Dннн043Dн % bнн043D043Dннн043Dн != bн043D043D043Dннн043Dн)
    {
      b043Dн043D043Dннн043Dн = 36;
      bн043D043D043Dннн043Dн = 10;
    }
    paramWebView = (ppipii)paramWebView.getTag();
    luuuuu localLuuuuu;
    Object localObject;
    if (paramWebView != null)
    {
      paramWebView.bа0430а0430а043004300430а0430(true);
      localLuuuuu = paramWebView.bааа0430а043004300430а0430();
      localObject = localLuuuuu.b0412В0412В0412В0412041204120412();
      if ((bИИИИ0418ИИ0418ИИ()) && (localObject != null) && (paramString.equals(localObject)))
      {
        if (localLuuuuu.b0412ВВ04120412В0412041204120412() != eiiiei.STICKY_FOOTER) {
          break label114;
        }
        ((pipppi)this.b042804280428ШШ042804280428Ш).showStickyFooter();
        b0430а0430аа0430а0430а0430(localLuuuuu);
      }
    }
    label114:
    do
    {
      do
      {
        return;
        paramString = (pipppi)this.b042804280428ШШ042804280428Ш;
        localObject = (pipppi)this.b042804280428ШШ042804280428Ш;
        switch (0)
        {
        case 1: 
        default: 
          for (;;)
          {
            switch (1)
            {
            }
          }
        }
      } while (paramString.getArrangementTileLeadsModelForPosition(((pipppi)localObject).getSelectedPosition()).b0430043004300430043004300430аа0430() != paramWebView);
      b0430а0430аа0430а0430а0430(localLuuuuu);
    } while ((b043Dн043D043Dннн043Dн + b043D043Dн043Dннн043Dн) * b043Dн043D043Dннн043Dн % bнн043D043Dннн043Dн == bн043D043D043Dннн043Dн);
    b043Dн043D043Dннн043Dн = b0430аааа0430а0430а0430();
    bн043D043D043Dннн043Dн = 44;
  }
}
