package kkkkkk;

import android.content.Context;

public class qqjjqj
{
  public static int b042B042B042B042BЫ042B042B042BЫ = 1;
  public static int bЫ042B042B042BЫ042B042B042BЫ = 1;
  public static int bЫЫЫЫ042B042B042B042BЫ = 2;
  private final vvxxvx b042BЫ042B042BЫ042B042B042BЫ;
  private final dppppd bЫЫ042B042BЫ042B042B042BЫ;
  
  public qqjjqj(Context paramContext)
  {
    this.bЫЫ042B042BЫ042B042B042BЫ = new dppppd(paramContext);
    this.b042BЫ042B042BЫ042B042B042BЫ = new vvxxvx(new dddpdp());
  }
  
  public static int b04300430а04300430аа04300430а()
  {
    return 7;
  }
  
  /* Error */
  public oioooo bаа043004300430аа04300430а()
  {
    // Byte code:
    //   0: aload_0
    //   1: getfield 25	kkkkkk/qqjjqj:bЫЫ042B042BЫ042B042B042BЫ	Lkkkkkk/dppppd;
    //   4: astore 4
    //   6: getstatic 48	kkkkkk/qqjjqj:bЫ042B042B042BЫ042B042B042BЫ	I
    //   9: istore_1
    //   10: iload_1
    //   11: getstatic 50	kkkkkk/qqjjqj:b042B042B042B042BЫ042B042B042BЫ	I
    //   14: iload_1
    //   15: iadd
    //   16: imul
    //   17: getstatic 52	kkkkkk/qqjjqj:bЫЫЫЫ042B042B042B042BЫ	I
    //   20: irem
    //   21: tableswitch	default:+19->40, 0:+31->52
    //   40: invokestatic 54	kkkkkk/qqjjqj:b04300430а04300430аа04300430а	()I
    //   43: putstatic 48	kkkkkk/qqjjqj:bЫ042B042B042BЫ042B042B042BЫ	I
    //   46: invokestatic 54	kkkkkk/qqjjqj:b04300430а04300430аа04300430а	()I
    //   49: putstatic 50	kkkkkk/qqjjqj:b042B042B042B042BЫ042B042B042BЫ	I
    //   52: aload 4
    //   54: ldc 56
    //   56: bipush 88
    //   58: bipush 19
    //   60: iconst_0
    //   61: invokestatic 62	kkkkkk/gguuuu:bк043Aккк043Aкк043A043A	(Ljava/lang/String;CCC)Ljava/lang/String;
    //   64: invokevirtual 66	kkkkkk/dppppd:b0430а04300430аааа0430а	(Ljava/lang/String;)Ljava/lang/String;
    //   67: astore 4
    //   69: new 68	kkkkkk/iooooo
    //   72: dup
    //   73: aload_0
    //   74: getfield 35	kkkkkk/qqjjqj:b042BЫ042B042BЫ042B042B042BЫ	Lkkkkkk/vvxxvx;
    //   77: aload 4
    //   79: invokevirtual 72	kkkkkk/vvxxvx:bЙ041904190419Й0419041904190419Й	(Ljava/lang/String;)Lkkkkkk/ppdppp;
    //   82: invokespecial 75	kkkkkk/iooooo:<init>	(Lkkkkkk/ppdppp;)V
    //   85: astore 4
    //   87: aload 4
    //   89: areturn
    //   90: astore 5
    //   92: getstatic 48	kkkkkk/qqjjqj:bЫ042B042B042BЫ042B042B042BЫ	I
    //   95: istore_1
    //   96: getstatic 50	kkkkkk/qqjjqj:b042B042B042B042BЫ042B042B042BЫ	I
    //   99: istore_2
    //   100: getstatic 52	kkkkkk/qqjjqj:bЫЫЫЫ042B042B042B042BЫ	I
    //   103: istore_3
    //   104: aload 5
    //   106: astore 4
    //   108: iload_1
    //   109: iload_2
    //   110: iload_1
    //   111: iadd
    //   112: imul
    //   113: iload_3
    //   114: irem
    //   115: tableswitch	default:+17->132, 0:+32->147
    //   132: invokestatic 54	kkkkkk/qqjjqj:b04300430а04300430аа04300430а	()I
    //   135: putstatic 48	kkkkkk/qqjjqj:bЫ042B042B042BЫ042B042B042BЫ	I
    //   138: bipush 77
    //   140: putstatic 50	kkkkkk/qqjjqj:b042B042B042B042BЫ042B042B042BЫ	I
    //   143: aload 5
    //   145: astore 4
    //   147: new 77	java/lang/RuntimeException
    //   150: dup
    //   151: ldc 79
    //   153: bipush 103
    //   155: sipush 231
    //   158: iconst_2
    //   159: invokestatic 62	kkkkkk/gguuuu:bк043Aккк043Aкк043A043A	(Ljava/lang/String;CCC)Ljava/lang/String;
    //   162: aload 4
    //   164: invokespecial 82	java/lang/RuntimeException:<init>	(Ljava/lang/String;Ljava/lang/Throwable;)V
    //   167: athrow
    //   168: astore 4
    //   170: aload 4
    //   172: athrow
    //   173: astore 4
    //   175: aload 4
    //   177: athrow
    //   178: astore 4
    //   180: aload 4
    //   182: athrow
    //   183: astore 4
    //   185: aload 4
    //   187: athrow
    //   188: astore 4
    //   190: goto -43 -> 147
    // Local variable table:
    //   start	length	slot	name	signature
    //   0	193	0	this	qqjjqj
    //   9	104	1	i	int
    //   99	13	2	j	int
    //   103	12	3	k	int
    //   4	159	4	localObject	Object
    //   168	3	4	localException1	Exception
    //   173	3	4	localException2	Exception
    //   178	3	4	localException3	Exception
    //   183	3	4	localException4	Exception
    //   188	1	4	localIOException	java.io.IOException
    //   90	54	5	localPpdddp	ppdddp
    // Exception table:
    //   from	to	target	type
    //   0	6	90	kkkkkk/ppdddp
    //   52	87	90	kkkkkk/ppdddp
    //   147	168	168	java/lang/Exception
    //   92	104	173	java/lang/Exception
    //   170	173	173	java/lang/Exception
    //   180	183	173	java/lang/Exception
    //   0	6	178	java/lang/Exception
    //   52	87	178	java/lang/Exception
    //   132	143	183	java/lang/Exception
    //   0	6	188	java/io/IOException
    //   52	87	188	java/io/IOException
  }
}
