package kkkkkk;

import android.content.res.Resources;
import android.support.annotation.NonNull;
import android.support.annotation.StringRes;
import com.mobile.ui.App;
import com.mobile.ui.R.drawable;
import com.mobile.ui.R.string;

public class qqqqqj
{
  public static int b042B042BЫ042B042BЫЫЫ042B = 1;
  public static int b042BЫЫ042B042BЫЫЫ042B = 49;
  public static int bЫ042BЫ042B042BЫЫЫ042B = 0;
  public static int bЫЫ042B042B042BЫЫЫ042B = 2;
  public static final qjjjjq bЫЫ042BЫ042BЫЫЫ042B;
  private final boolean b042B042B042BЫ042BЫЫЫ042B;
  private final qjjjjq b042BЫ042BЫ042BЫЫЫ042B;
  private final cccrcc bЫ042B042BЫ042BЫЫЫ042B;
  private final boolean bЫЫЫ042B042BЫЫЫ042B;
  
  static
  {
    if ((b042BЫЫ042B042BЫЫЫ042B + b042B042BЫ042B042BЫЫЫ042B) * b042BЫЫ042B042BЫЫЫ042B % bЫЫ042B042B042BЫЫЫ042B != bЫ042BЫ042B042BЫЫЫ042B)
    {
      b042BЫЫ042B042BЫЫЫ042B = 34;
      bЫ042BЫ042B042BЫЫЫ042B = b0430аа0430аа043004300430а();
    }
    bЫЫ042BЫ042BЫЫЫ042B = new qjjjjq(false, 0, R.string.accessibility_arrangementsummary_account_name_suffix_for_button);
    switch (1)
    {
    case 0: 
    default: 
      for (;;)
      {
        switch (1)
        {
        }
      }
    }
  }
  
  public qqqqqj(cccrcc paramCccrcc)
  {
    this(paramCccrcc, new qjjjjq(false, 0, R.string.accessibility_arrangementsummary_account_name_suffix_for_button));
  }
  
  public qqqqqj(cccrcc paramCccrcc, qjjjjq paramQjjjjq)
  {
    this(paramCccrcc, true, paramQjjjjq);
  }
  
  public qqqqqj(cccrcc paramCccrcc, boolean paramBoolean, qjjjjq paramQjjjjq)
  {
    this(paramCccrcc, paramBoolean, true, paramQjjjjq);
  }
  
  public qqqqqj(cccrcc paramCccrcc, boolean paramBoolean1, boolean paramBoolean2, qjjjjq paramQjjjjq)
  {
    this.bЫ042B042BЫ042BЫЫЫ042B = paramCccrcc;
    this.b042B042B042BЫ042BЫЫЫ042B = paramBoolean1;
    this.bЫЫЫ042B042BЫЫЫ042B = paramBoolean2;
    this.b042BЫ042BЫ042BЫЫЫ042B = paramQjjjjq;
  }
  
  /* Error */
  @NonNull
  private static String b043004300430а0430а043004300430а(Resources paramResources, @StringRes int paramInt)
  {
    // Byte code:
    //   0: invokestatic 38	kkkkkk/qqqqqj:b0430аа0430аа043004300430а	()I
    //   3: istore_2
    //   4: getstatic 30	kkkkkk/qqqqqj:b042B042BЫ042B042BЫЫЫ042B	I
    //   7: istore_3
    //   8: invokestatic 38	kkkkkk/qqqqqj:b0430аа0430аа043004300430а	()I
    //   11: istore 4
    //   13: iload_2
    //   14: iload_3
    //   15: iadd
    //   16: iload 4
    //   18: imul
    //   19: getstatic 32	kkkkkk/qqqqqj:bЫЫ042B042B042BЫЫЫ042B	I
    //   22: irem
    //   23: getstatic 34	kkkkkk/qqqqqj:bЫ042BЫ042B042BЫЫЫ042B	I
    //   26: if_icmpeq +59 -> 85
    //   29: invokestatic 38	kkkkkk/qqqqqj:b0430аа0430аа043004300430а	()I
    //   32: putstatic 28	kkkkkk/qqqqqj:b042BЫЫ042B042BЫЫЫ042B	I
    //   35: invokestatic 38	kkkkkk/qqqqqj:b0430аа0430аа043004300430а	()I
    //   38: putstatic 34	kkkkkk/qqqqqj:bЫ042BЫ042B042BЫЫЫ042B	I
    //   41: getstatic 28	kkkkkk/qqqqqj:b042BЫЫ042B042BЫЫЫ042B	I
    //   44: istore_2
    //   45: iload_2
    //   46: getstatic 30	kkkkkk/qqqqqj:b042B042BЫ042B042BЫЫЫ042B	I
    //   49: iload_2
    //   50: iadd
    //   51: imul
    //   52: getstatic 32	kkkkkk/qqqqqj:bЫЫ042B042B042BЫЫЫ042B	I
    //   55: irem
    //   56: tableswitch	default:+20->76, 0:+29->85
    //   76: iconst_4
    //   77: putstatic 28	kkkkkk/qqqqqj:b042BЫЫ042B042BЫЫЫ042B	I
    //   80: bipush 60
    //   82: putstatic 34	kkkkkk/qqqqqj:bЫ042BЫ042B042BЫЫЫ042B	I
    //   85: aload_0
    //   86: iload_1
    //   87: invokevirtual 82	android/content/res/Resources:getString	(I)Ljava/lang/String;
    //   90: astore_0
    //   91: aload_0
    //   92: areturn
    //   93: astore_0
    //   94: aload_0
    //   95: athrow
    //   96: astore_0
    //   97: aload_0
    //   98: athrow
    //   99: astore_0
    //   100: aload_0
    //   101: athrow
    // Local variable table:
    //   start	length	slot	name	signature
    //   0	102	0	paramResources	Resources
    //   0	102	1	paramInt	int
    //   3	49	2	i	int
    //   7	9	3	j	int
    //   11	8	4	k	int
    // Exception table:
    //   from	to	target	type
    //   85	91	93	java/lang/Exception
    //   0	13	96	java/lang/Exception
    //   94	96	96	java/lang/Exception
    //   13	41	99	java/lang/Exception
  }
  
  public static int b043004300430ааа043004300430а()
  {
    return 1;
  }
  
  @NonNull
  private String b0430а04300430аа043004300430а(Resources paramResources)
  {
    for (;;)
    {
      try
      {
        i = qqqqqj.1.b042BЫ042B042B042BЫЫЫ042B[bа04300430а0430а043004300430а().ordinal()];
        switch (i)
        {
        default: 
          localObject = "";
        }
      }
      catch (Exception paramResources)
      {
        int j;
        int k;
        int m;
        int n;
        throw paramResources;
      }
      try
      {
        return paramResources.getString(R.string.arrangement_type, new Object[] { localObject });
      }
      catch (Exception paramResources)
      {
        throw paramResources;
      }
      Object localObject = b043004300430а0430а043004300430а(paramResources, R.string.accessibility_arrangement_investment_account);
      continue;
      localObject = b043004300430а0430а043004300430а(paramResources, R.string.accessibility_arrangement_home_insurance_account);
      continue;
      String str = b043004300430а0430а043004300430а(paramResources, R.string.accessibility_arrangement_non_cbs_personal_loan_account);
      int i = b042BЫЫ042B042BЫЫЫ042B;
      j = b042B042BЫ042B042BЫЫЫ042B;
      k = b042BЫЫ042B042BЫЫЫ042B;
      m = bЫЫ042B042B042BЫЫЫ042B;
      n = bЫ042BЫ042B042BЫЫЫ042B;
      localObject = str;
      if ((i + j) * k % m != n)
      {
        b042BЫЫ042B042BЫЫЫ042B = 95;
        bЫ042BЫ042B042BЫЫЫ042B = 26;
        localObject = str;
        continue;
        localObject = b043004300430а0430а043004300430а(paramResources, R.string.accessibility_arrangement_credit_card_account);
        continue;
        localObject = b043004300430а0430а043004300430а(paramResources, R.string.accessibility_arrangement_savings_account);
        continue;
        localObject = b043004300430а0430а043004300430а(paramResources, R.string.accessibility_arrangement_cbs_personal_loan_account);
        continue;
        localObject = b043004300430а0430а043004300430а(paramResources, R.string.accessibility_arrangement_isa_account);
        continue;
        i = R.string.accessibility_arrangement_treasury_ftd_account;
        localObject = b043004300430а0430а043004300430а(paramResources, i);
        continue;
        localObject = b043004300430а0430а043004300430а(paramResources, R.string.accessibility_arrangement_mortgage_account);
        continue;
        localObject = b043004300430а0430а043004300430а(paramResources, R.string.accessibility_arrangement_term_deposit_account);
        continue;
        str = b043004300430а0430а043004300430а(paramResources, R.string.accessibility_arrangement_htb_isa_account);
        localObject = str;
        if ((b0430аа0430аа043004300430а() + b042B042BЫ042B042BЫЫЫ042B) * b0430аа0430аа043004300430а() % bЫЫ042B042B042BЫЫЫ042B != bЫ042BЫ042B042BЫЫЫ042B)
        {
          b042BЫЫ042B042BЫЫЫ042B = 62;
          bЫ042BЫ042B042BЫЫЫ042B = 29;
          localObject = str;
          continue;
          localObject = b043004300430а0430а043004300430а(paramResources, R.string.accessibility_arrangement_treasury_32dcn_account);
          continue;
          localObject = b043004300430а0430а043004300430а(paramResources, R.string.accessibility_arrangement_mortgage_ufss_account);
          continue;
          localObject = b043004300430а0430а043004300430а(paramResources, R.string.accessibility_arrangement_current_account);
        }
      }
    }
  }
  
  public static int b0430аа0430аа043004300430а()
  {
    return 18;
  }
  
  public static int bа0430а0430аа043004300430а()
  {
    return 0;
  }
  
  public static int bааа0430аа043004300430а()
  {
    return 2;
  }
  
  /* Error */
  private int bаааа0430а043004300430а()
  {
    // Byte code:
    //   0: getstatic 93	kkkkkk/qqqqqj$1:b042BЫ042B042B042BЫЫЫ042B	[I
    //   3: astore_2
    //   4: aload_0
    //   5: getfield 64	kkkkkk/qqqqqj:bЫ042B042BЫ042BЫЫЫ042B	Lkkkkkk/cccrcc;
    //   8: astore_3
    //   9: getstatic 28	kkkkkk/qqqqqj:b042BЫЫ042B042BЫЫЫ042B	I
    //   12: getstatic 30	kkkkkk/qqqqqj:b042B042BЫ042B042BЫЫЫ042B	I
    //   15: iadd
    //   16: getstatic 28	kkkkkk/qqqqqj:b042BЫЫ042B042BЫЫЫ042B	I
    //   19: imul
    //   20: getstatic 32	kkkkkk/qqqqqj:bЫЫ042B042B042BЫЫЫ042B	I
    //   23: irem
    //   24: getstatic 34	kkkkkk/qqqqqj:bЫ042BЫ042B042BЫЫЫ042B	I
    //   27: if_icmpeq +14 -> 41
    //   30: invokestatic 38	kkkkkk/qqqqqj:b0430аа0430аа043004300430а	()I
    //   33: putstatic 28	kkkkkk/qqqqqj:b042BЫЫ042B042BЫЫЫ042B	I
    //   36: bipush 85
    //   38: putstatic 34	kkkkkk/qqqqqj:bЫ042BЫ042B042BЫЫЫ042B	I
    //   41: aload_2
    //   42: aload_3
    //   43: invokevirtual 162	kkkkkk/cccrcc:bжж04360436жжжж04360436	()Lkkkkkk/ccrrcc;
    //   46: invokevirtual 102	kkkkkk/ccrrcc:ordinal	()I
    //   49: iaload
    //   50: istore_1
    //   51: getstatic 28	kkkkkk/qqqqqj:b042BЫЫ042B042BЫЫЫ042B	I
    //   54: invokestatic 164	kkkkkk/qqqqqj:b043004300430ааа043004300430а	()I
    //   57: iadd
    //   58: getstatic 28	kkkkkk/qqqqqj:b042BЫЫ042B042BЫЫЫ042B	I
    //   61: imul
    //   62: getstatic 32	kkkkkk/qqqqqj:bЫЫ042B042B042BЫЫЫ042B	I
    //   65: irem
    //   66: getstatic 34	kkkkkk/qqqqqj:bЫ042BЫ042B042BЫЫЫ042B	I
    //   69: if_icmpeq +15 -> 84
    //   72: invokestatic 38	kkkkkk/qqqqqj:b0430аа0430аа043004300430а	()I
    //   75: putstatic 28	kkkkkk/qqqqqj:b042BЫЫ042B042BЫЫЫ042B	I
    //   78: invokestatic 38	kkkkkk/qqqqqj:b0430аа0430аа043004300430а	()I
    //   81: putstatic 34	kkkkkk/qqqqqj:bЫ042BЫ042B042BЫЫЫ042B	I
    //   84: iload_1
    //   85: tableswitch	default:+31->116, 9:+37->122, 10:+37->122, 11:+37->122, 12:+37->122
    //   116: getstatic 167	com/mobile/ui/R$string:accessibility_arrangementsummary_other_balance	I
    //   119: istore_1
    //   120: iload_1
    //   121: ireturn
    //   122: getstatic 170	com/mobile/ui/R$string:accessibility_arrangementtile_current_balance	I
    //   125: istore_1
    //   126: iload_1
    //   127: ireturn
    //   128: astore_2
    //   129: aload_2
    //   130: athrow
    //   131: astore_2
    //   132: aload_2
    //   133: athrow
    // Local variable table:
    //   start	length	slot	name	signature
    //   0	134	0	this	qqqqqj
    //   50	77	1	i	int
    //   3	39	2	arrayOfInt	int[]
    //   128	2	2	localException1	Exception
    //   131	2	2	localException2	Exception
    //   8	35	3	localCccrcc	cccrcc
    // Exception table:
    //   from	to	target	type
    //   0	9	128	java/lang/Exception
    //   41	51	128	java/lang/Exception
    //   116	120	128	java/lang/Exception
    //   122	126	131	java/lang/Exception
  }
  
  public boolean b04300430043004300430а043004300430а()
  {
    int i = b042BЫЫ042B042BЫЫЫ042B;
    switch (i * (b043004300430ааа043004300430а() + i) % bЫЫ042B042B042BЫЫЫ042B)
    {
    default: 
      b042BЫЫ042B042BЫЫЫ042B = 5;
      bЫ042BЫ042B042BЫЫЫ042B = b0430аа0430аа043004300430а();
    }
    cccrcc localCccrcc = this.bЫ042B042BЫ042BЫЫЫ042B;
    switch (1)
    {
    case 0: 
    default: 
      for (;;)
      {
        switch (1)
        {
        }
      }
    }
    boolean bool = localCccrcc.b043604360436ж0436ж0436ж04360436();
    i = b042BЫЫ042B042BЫЫЫ042B;
    switch (i * (b043004300430ааа043004300430а() + i) % bЫЫ042B042B042BЫЫЫ042B)
    {
    default: 
      b042BЫЫ042B042BЫЫЫ042B = 41;
      bЫ042BЫ042B042BЫЫЫ042B = b0430аа0430аа043004300430а();
    }
    return bool;
  }
  
  public String b0430043004300430аа043004300430а()
  {
    int i = b042BЫЫ042B042BЫЫЫ042B;
    int j = b042B042BЫ042B042BЫЫЫ042B;
    int k = b042BЫЫ042B042BЫЫЫ042B;
    if ((b042BЫЫ042B042BЫЫЫ042B + b042B042BЫ042B042BЫЫЫ042B) * b042BЫЫ042B042BЫЫЫ042B % bЫЫ042B042B042BЫЫЫ042B != bЫ042BЫ042B042BЫЫЫ042B)
    {
      b042BЫЫ042B042BЫЫЫ042B = 6;
      bЫ042BЫ042B042BЫЫЫ042B = 3;
    }
    if ((i + j) * k % bЫЫ042B042B042BЫЫЫ042B != bЫ042BЫ042B042BЫЫЫ042B)
    {
      b042BЫЫ042B042BЫЫЫ042B = 54;
      bЫ042BЫ042B042BЫЫЫ042B = b0430аа0430аа043004300430а();
    }
    try
    {
      localObject = App.get().getResources();
    }
    catch (Exception localException1)
    {
      Object localObject;
      throw localException1;
    }
    switch (qqqqqj.1.b042BЫ042B042B042BЫЫЫ042B[this.bЫ042B042BЫ042BЫЫЫ042B.bжж04360436жжжж04360436().ordinal()])
    {
    case 1: 
      return ((Resources)localObject).getString(R.string.accessibility_arrangementsummary_available_funds, new Object[] { mnmnmn.bИИИ0418И0418ИИ04180418(this.bЫ042B042BЫ042BЫЫЫ042B.b0436ж04360436жжжж04360436()) });
    case 11: 
    case 12: 
      return ((Resources)localObject).getString(R.string.accessibility_arrangementsummary_not_a_final_figure);
    case 4: 
    case 5: 
    case 6: 
      return ((Resources)localObject).getString(R.string.accessibility_arrangementsummary_maturity_date, new Object[] { mnmnmn.b0418И04180418И0418ИИ04180418(this.bЫ042B042BЫ042BЫЫЫ042B.b04360436ж04360436жжж04360436()) });
    case 2: 
      i = R.string.accessibility_arrangementsummary_available_credit;
    case 7: 
    case 9: 
      try
      {
        return ((Resources)localObject).getString(i, new Object[] { mnmnmn.bИ0418И0418И0418ИИ04180418(this.bЫ042B042BЫ042BЫЫЫ042B.b0436ж04360436жжжж04360436()) });
      }
      catch (Exception localException2)
      {
        String str;
        throw localException2;
      }
      i = R.string.accessibility_arrangementsummary_remaining_allowance;
      str = mnmnmn.bИИИ0418И0418ИИ04180418(this.bЫ042B042BЫ042BЫЫЫ042B.b0436ж04360436ж0436жж04360436());
      localObject = ((Resources)localObject).getString(i, new Object[] { str });
      return localObject;
      localObject = ((Resources)localObject).getString(R.string.accessibility_arrangementsummary_original_loan_amount, new Object[] { mnmnmn.bИ0418И0418И0418ИИ04180418(this.bЫ042B042BЫ042BЫЫЫ042B.b04360436жжж0436жж04360436()) });
      return localObject;
      switch (1)
      {
      }
      for (;;)
      {
        switch (1)
        {
        }
      }
    }
    return "";
  }
  
  public String b04300430а04300430а043004300430а()
  {
    Resources localResources = App.get().getResources();
    int j;
    switch (qqqqqj.1.b042BЫ042B042B042BЫЫЫ042B[this.bЫ042B042BЫ042BЫЫЫ042B.bжж04360436жжжж04360436().ordinal()])
    {
    case 8: 
    case 10: 
    default: 
      return "";
      int i = R.string.arrangement_available_balance;
      j = b042BЫЫ042B042BЫЫЫ042B;
      switch (j * (b042B042BЫ042B042BЫЫЫ042B + j) % bЫЫ042B042B042BЫЫЫ042B)
      {
      default: 
        b042BЫЫ042B042BЫЫЫ042B = b0430аа0430аа043004300430а();
        bЫ042BЫ042B042BЫЫЫ042B = 36;
      }
      return localResources.getString(i, new Object[] { mnmnmn.bИИИ0418И0418ИИ04180418(this.bЫ042B042BЫ042BЫЫЫ042B.b0436ж04360436жжжж04360436()) });
      i = b042BЫЫ042B042BЫЫЫ042B;
      switch (i * (b042B042BЫ042B042BЫЫЫ042B + i) % bЫЫ042B042B042BЫЫЫ042B)
      {
      default: 
        b042BЫЫ042B042BЫЫЫ042B = 71;
        bЫ042BЫ042B042BЫЫЫ042B = b0430аа0430аа043004300430а();
      }
      return localResources.getString(j, new Object[] { mnmnmn.bИИИ0418И0418ИИ04180418(this.bЫ042B042BЫ042BЫЫЫ042B.b0436ж04360436ж0436жж04360436()) });
    case 4: 
    case 5: 
    case 6: 
      return localResources.getString(R.string.arrangement_maturity_date, new Object[] { mnmnmn.b0418И04180418И0418ИИ04180418(this.bЫ042B042BЫ042BЫЫЫ042B.b04360436ж04360436жжж04360436()) });
      for (;;)
      {
        switch (1)
        {
        }
      }
    case 7: 
      for (;;)
      {
        switch (1)
        {
        }
        break;
        j = R.string.arrangement_remaining_allowance;
      }
    case 2: 
      return localResources.getString(R.string.arrangement_available_credit, new Object[] { mnmnmn.bИ0418И0418И0418ИИ04180418(this.bЫ042B042BЫ042BЫЫЫ042B.b0436ж04360436жжжж04360436()) });
    case 1: 
    case 3: 
      switch (0)
      {
      }
      for (;;)
      {
        switch (1)
        {
        }
      }
    case 9: 
      return localResources.getString(R.string.arrangement_original_loan, new Object[] { mnmnmn.bИ0418И0418И0418ИИ04180418(this.bЫ042B042BЫ042BЫЫЫ042B.b04360436жжж0436жж04360436()) });
    }
    return localResources.getString(R.string.arrangement_not_a_final_figure);
  }
  
  /* Error */
  public String b04300430а0430аа043004300430а()
  {
    // Byte code:
    //   0: invokestatic 183	com/mobile/ui/App:get	()Lcom/mobile/ui/App;
    //   3: invokevirtual 187	com/mobile/ui/App:getResources	()Landroid/content/res/Resources;
    //   6: astore 6
    //   8: getstatic 28	kkkkkk/qqqqqj:b042BЫЫ042B042BЫЫЫ042B	I
    //   11: getstatic 30	kkkkkk/qqqqqj:b042B042BЫ042B042BЫЫЫ042B	I
    //   14: iadd
    //   15: getstatic 28	kkkkkk/qqqqqj:b042BЫЫ042B042BЫЫЫ042B	I
    //   18: imul
    //   19: getstatic 32	kkkkkk/qqqqqj:bЫЫ042B042B042BЫЫЫ042B	I
    //   22: irem
    //   23: getstatic 34	kkkkkk/qqqqqj:bЫ042BЫ042B042BЫЫЫ042B	I
    //   26: if_icmpeq +14 -> 40
    //   29: invokestatic 38	kkkkkk/qqqqqj:b0430аа0430аа043004300430а	()I
    //   32: putstatic 28	kkkkkk/qqqqqj:b042BЫЫ042B042BЫЫЫ042B	I
    //   35: bipush 48
    //   37: putstatic 34	kkkkkk/qqqqqj:bЫ042BЫ042B042BЫЫЫ042B	I
    //   40: aload_0
    //   41: getfield 70	kkkkkk/qqqqqj:b042BЫ042BЫ042BЫЫЫ042B	Lkkkkkk/qqqqqj$qjjjjq;
    //   44: aload 6
    //   46: invokestatic 256	kkkkkk/qqqqqj$qjjjjq:b043004300430043004300430а04300430а	(Lkkkkkk/qqqqqj$qjjjjq;Landroid/content/res/Resources;)Ljava/lang/String;
    //   49: aload_0
    //   50: invokevirtual 259	kkkkkk/qqqqqj:b04300430аа0430а043004300430а	()Ljava/lang/String;
    //   53: invokevirtual 265	java/lang/String:concat	(Ljava/lang/String;)Ljava/lang/String;
    //   56: astore 7
    //   58: aload 7
    //   60: ldc_w 267
    //   63: bipush 119
    //   65: iconst_3
    //   66: invokestatic 273	kkkkkk/gguuuu:bккккк043Aкк043A043A	(Ljava/lang/String;CC)Ljava/lang/String;
    //   69: invokevirtual 265	java/lang/String:concat	(Ljava/lang/String;)Ljava/lang/String;
    //   72: astore 7
    //   74: aload 7
    //   76: aload_0
    //   77: aload 6
    //   79: invokespecial 275	kkkkkk/qqqqqj:b0430а04300430аа043004300430а	(Landroid/content/res/Resources;)Ljava/lang/String;
    //   82: invokevirtual 265	java/lang/String:concat	(Ljava/lang/String;)Ljava/lang/String;
    //   85: astore 7
    //   87: invokestatic 38	kkkkkk/qqqqqj:b0430аа0430аа043004300430а	()I
    //   90: istore_1
    //   91: getstatic 30	kkkkkk/qqqqqj:b042B042BЫ042B042BЫЫЫ042B	I
    //   94: istore_2
    //   95: invokestatic 38	kkkkkk/qqqqqj:b0430аа0430аа043004300430а	()I
    //   98: istore_3
    //   99: getstatic 32	kkkkkk/qqqqqj:bЫЫ042B042B042BЫЫЫ042B	I
    //   102: istore 4
    //   104: invokestatic 277	kkkkkk/qqqqqj:bа0430а0430аа043004300430а	()I
    //   107: istore 5
    //   109: iload_1
    //   110: iload_2
    //   111: iadd
    //   112: iload_3
    //   113: imul
    //   114: iload 4
    //   116: irem
    //   117: iload 5
    //   119: if_icmpeq +14 -> 133
    //   122: invokestatic 38	kkkkkk/qqqqqj:b0430аа0430аа043004300430а	()I
    //   125: putstatic 28	kkkkkk/qqqqqj:b042BЫЫ042B042BЫЫЫ042B	I
    //   128: bipush 23
    //   130: putstatic 34	kkkkkk/qqqqqj:bЫ042BЫ042B042BЫЫЫ042B	I
    //   133: aload 7
    //   135: aload_0
    //   136: getfield 70	kkkkkk/qqqqqj:b042BЫ042BЫ042BЫЫЫ042B	Lkkkkkk/qqqqqj$qjjjjq;
    //   139: aload 6
    //   141: invokestatic 280	kkkkkk/qqqqqj$qjjjjq:bа04300430043004300430а04300430а	(Lkkkkkk/qqqqqj$qjjjjq;Landroid/content/res/Resources;)Ljava/lang/String;
    //   144: invokevirtual 265	java/lang/String:concat	(Ljava/lang/String;)Ljava/lang/String;
    //   147: astore 6
    //   149: aload 6
    //   151: areturn
    //   152: astore 6
    //   154: aload 6
    //   156: athrow
    //   157: astore 6
    //   159: aload 6
    //   161: athrow
    //   162: astore 6
    //   164: aload 6
    //   166: athrow
    //   167: astore 6
    //   169: aload 6
    //   171: athrow
    // Local variable table:
    //   start	length	slot	name	signature
    //   0	172	0	this	qqqqqj
    //   90	22	1	i	int
    //   94	18	2	j	int
    //   98	16	3	k	int
    //   102	15	4	m	int
    //   107	13	5	n	int
    //   6	144	6	localObject	Object
    //   152	3	6	localException1	Exception
    //   157	3	6	localException2	Exception
    //   162	3	6	localException3	Exception
    //   167	3	6	localException4	Exception
    //   56	78	7	str	String
    // Exception table:
    //   from	to	target	type
    //   0	8	152	java/lang/Exception
    //   40	58	152	java/lang/Exception
    //   74	87	152	java/lang/Exception
    //   87	99	157	java/lang/Exception
    //   104	109	157	java/lang/Exception
    //   154	157	157	java/lang/Exception
    //   164	167	157	java/lang/Exception
    //   58	74	162	java/lang/Exception
    //   133	149	162	java/lang/Exception
    //   99	104	167	java/lang/Exception
    //   122	133	167	java/lang/Exception
  }
  
  public String b04300430аа0430а043004300430а()
  {
    int i = b042BЫЫ042B042BЫЫЫ042B;
    switch (i * (b043004300430ааа043004300430а() + i) % bЫЫ042B042B042BЫЫЫ042B)
    {
    default: 
      b042BЫЫ042B042BЫЫЫ042B = b0430аа0430аа043004300430а();
      bЫ042BЫ042B042BЫЫЫ042B = b0430аа0430аа043004300430а();
    }
    try
    {
      String str = this.bЫ042B042BЫ042BЫЫЫ042B.b043604360436жжжжж04360436();
      i = b042BЫЫ042B042BЫЫЫ042B;
      int j = b042B042BЫ042B042BЫЫЫ042B;
      int k = b042BЫЫ042B042BЫЫЫ042B;
      int m = bЫЫ042B042B042BЫЫЫ042B;
      int n = bЫ042BЫ042B042BЫЫЫ042B;
      switch (1)
      {
      case 0: 
      default: 
        for (;;)
        {
          switch (0)
          {
          }
        }
      }
      if ((i + j) * k % m != n)
      {
        b042BЫЫ042B042BЫЫЫ042B = b0430аа0430аа043004300430а();
        bЫ042BЫ042B042BЫЫЫ042B = 34;
      }
      return str;
    }
    catch (Exception localException)
    {
      throw localException;
    }
  }
  
  public boolean b04300430ааа0430043004300430а()
  {
    switch (1)
    {
    case 0: 
    default: 
      for (;;)
      {
        switch (0)
        {
        }
      }
    }
    int i = b042BЫЫ042B042BЫЫЫ042B;
    switch (i * (b042B042BЫ042B042BЫЫЫ042B + i) % bааа0430аа043004300430а())
    {
    default: 
      b042BЫЫ042B042BЫЫЫ042B = 12;
      bЫ042BЫ042B042BЫЫЫ042B = 31;
    }
    try
    {
      boolean bool = this.bЫЫЫ042B042BЫЫЫ042B;
      return bool;
    }
    catch (Exception localException)
    {
      throw localException;
    }
  }
  
  public String b0430а043004300430а043004300430а()
  {
    int i = b042BЫЫ042B042BЫЫЫ042B;
    switch (i * (b042B042BЫ042B042BЫЫЫ042B + i) % bЫЫ042B042B042BЫЫЫ042B)
    {
    default: 
      b042BЫЫ042B042BЫЫЫ042B = b0430аа0430аа043004300430а();
      bЫ042BЫ042B042BЫЫЫ042B = 77;
    }
    for (;;)
    {
      try
      {
        localObject = App.get().getResources();
        switch (qqqqqj.1.b042BЫ042B042B042BЫЫЫ042B[bа04300430а0430а043004300430а().ordinal()])
        {
        case 2: 
          i = b0430аа0430аа043004300430а();
          switch (i * (b042B042BЫ042B042BЫЫЫ042B + i) % bЫЫ042B042B042BЫЫЫ042B)
          {
          default: 
            b042BЫЫ042B042BЫЫЫ042B = b0430аа0430аа043004300430а();
            bЫ042BЫ042B042BЫЫЫ042B = 80;
          }
          return "";
        }
      }
      catch (Exception localException2)
      {
        Object localObject;
        throw localException2;
      }
      try
      {
        return mnmnmn.bИИ04180418И0418ИИ04180418(this.bЫ042B042BЫ042BЫЫЫ042B.b0436043604360436жжжж04360436());
      }
      catch (Exception localException1)
      {
        switch (0)
        {
        case 1: 
        default: 
          switch (0)
          {
          }
          break;
        }
        throw localException1;
      }
      return ((Resources)localObject).getString(R.string.arrangement_reference, new Object[] { this.bЫ042B042BЫ042BЫЫЫ042B.bжж04360436ж0436жж04360436() });
      localObject = ((Resources)localObject).getString(R.string.arrangement_reference, new Object[] { this.bЫ042B042BЫ042BЫЫЫ042B.b0436жж04360436жжж04360436() });
      return localObject;
    }
  }
  
  /* Error */
  @NonNull
  public String b0430а0430а0430а043004300430а()
  {
    // Byte code:
    //   0: aload_0
    //   1: getfield 64	kkkkkk/qqqqqj:bЫ042B042BЫ042BЫЫЫ042B	Lkkkkkk/cccrcc;
    //   4: astore 4
    //   6: aload 4
    //   8: invokevirtual 306	kkkkkk/cccrcc:bжж0436ж0436жжж04360436	()Ljava/lang/String;
    //   11: astore 4
    //   13: getstatic 28	kkkkkk/qqqqqj:b042BЫЫ042B042BЫЫЫ042B	I
    //   16: istore_1
    //   17: getstatic 30	kkkkkk/qqqqqj:b042B042BЫ042B042BЫЫЫ042B	I
    //   20: istore_2
    //   21: getstatic 28	kkkkkk/qqqqqj:b042BЫЫ042B042BЫЫЫ042B	I
    //   24: istore_3
    //   25: getstatic 28	kkkkkk/qqqqqj:b042BЫЫ042B042BЫЫЫ042B	I
    //   28: getstatic 30	kkkkkk/qqqqqj:b042B042BЫ042B042BЫЫЫ042B	I
    //   31: iadd
    //   32: getstatic 28	kkkkkk/qqqqqj:b042BЫЫ042B042BЫЫЫ042B	I
    //   35: imul
    //   36: invokestatic 286	kkkkkk/qqqqqj:bааа0430аа043004300430а	()I
    //   39: irem
    //   40: getstatic 34	kkkkkk/qqqqqj:bЫ042BЫ042B042BЫЫЫ042B	I
    //   43: if_icmpeq +14 -> 57
    //   46: invokestatic 38	kkkkkk/qqqqqj:b0430аа0430аа043004300430а	()I
    //   49: putstatic 28	kkkkkk/qqqqqj:b042BЫЫ042B042BЫЫЫ042B	I
    //   52: bipush 85
    //   54: putstatic 34	kkkkkk/qqqqqj:bЫ042BЫ042B042BЫЫЫ042B	I
    //   57: iload_1
    //   58: iload_2
    //   59: iadd
    //   60: iload_3
    //   61: imul
    //   62: getstatic 32	kkkkkk/qqqqqj:bЫЫ042B042B042BЫЫЫ042B	I
    //   65: irem
    //   66: getstatic 34	kkkkkk/qqqqqj:bЫ042BЫ042B042BЫЫЫ042B	I
    //   69: if_icmpeq +14 -> 83
    //   72: invokestatic 38	kkkkkk/qqqqqj:b0430аа0430аа043004300430а	()I
    //   75: putstatic 28	kkkkkk/qqqqqj:b042BЫЫ042B042BЫЫЫ042B	I
    //   78: bipush 35
    //   80: putstatic 34	kkkkkk/qqqqqj:bЫ042BЫ042B042BЫЫЫ042B	I
    //   83: aload 4
    //   85: areturn
    //   86: astore 4
    //   88: aload 4
    //   90: athrow
    //   91: astore 4
    //   93: aload 4
    //   95: athrow
    // Local variable table:
    //   start	length	slot	name	signature
    //   0	96	0	this	qqqqqj
    //   16	44	1	i	int
    //   20	40	2	j	int
    //   24	38	3	k	int
    //   4	80	4	localObject	Object
    //   86	3	4	localException1	Exception
    //   91	3	4	localException2	Exception
    // Exception table:
    //   from	to	target	type
    //   0	6	86	java/lang/Exception
    //   6	13	91	java/lang/Exception
  }
  
  public String b0430аа04300430а043004300430а()
  {
    Object localObject;
    if (bа04300430а0430а043004300430а().bп043F043Fп043Fппппп()) {
      localObject = mnmnmn.bИИИ0418И0418ИИ04180418(this.bЫ042B042BЫ042BЫЫЫ042B.bж043604360436жжжж04360436());
    }
    for (;;)
    {
      switch (0)
      {
      case 1: 
      default: 
        for (;;)
        {
          switch (1)
          {
          }
        }
      }
      int i = b042BЫЫ042B042BЫЫЫ042B;
      switch (i * (b042B042BЫ042B042BЫЫЫ042B + i) % bЫЫ042B042B042BЫЫЫ042B)
      {
      default: 
        b042BЫЫ042B042BЫЫЫ042B = 63;
        bЫ042BЫ042B042BЫЫЫ042B = 53;
      }
      return localObject;
      String str = mnmnmn.bИИИ0418И0418ИИ04180418(this.bЫ042B042BЫ042BЫЫЫ042B.b0436ж04360436жжжж04360436());
      localObject = str;
      if ((b042BЫЫ042B042BЫЫЫ042B + b042B042BЫ042B042BЫЫЫ042B) * b042BЫЫ042B042BЫЫЫ042B % bЫЫ042B042B042BЫЫЫ042B != bЫ042BЫ042B042BЫЫЫ042B)
      {
        b042BЫЫ042B042BЫЫЫ042B = 41;
        bЫ042BЫ042B042BЫЫЫ042B = b0430аа0430аа043004300430а();
        localObject = str;
      }
    }
  }
  
  public String b0430ааа0430а043004300430а()
  {
    try
    {
      localObject1 = App.get().getResources();
      switch (qqqqqj.1.b042BЫ042B042B042BЫЫЫ042B[bа04300430а0430а043004300430а().ordinal()])
      {
      case 2: 
        i = R.string.accessibility_arrangementtile_creditcard_cardnumber;
        j = b042BЫЫ042B042BЫЫЫ042B;
        switch (j * (b043004300430ааа043004300430а() + j) % bЫЫ042B042B042BЫЫЫ042B)
        {
        default: 
          b042BЫЫ042B042BЫЫЫ042B = 58;
          bЫ042BЫ042B042BЫЫЫ042B = b0430аа0430аа043004300430а();
        }
        break;
      }
    }
    catch (Exception localException1)
    {
      Object localObject1;
      int i;
      int j;
      Object localObject2;
      throw localException1;
    }
    try
    {
      localObject2 = this.bЫ042B042BЫ042BЫЫЫ042B;
      return ((Resources)localObject1).getString(i, new Object[] { wbbwww.b04180418ИИИИ04180418И0418(mnmnmn.bИИ04180418И0418ИИ04180418(((cccrcc)localObject2).b0436043604360436жжжж04360436())) });
    }
    catch (Exception localException2)
    {
      throw localException2;
    }
    i = R.string.accessibility_arrangementtile_loan_reference;
    localObject2 = this.bЫ042B042BЫ042BЫЫЫ042B.b0436жж04360436жжж04360436();
    j = b042BЫЫ042B042BЫЫЫ042B;
    switch (j * (b042B042BЫ042B042BЫЫЫ042B + j) % bЫЫ042B042B042BЫЫЫ042B)
    {
    default: 
      b042BЫЫ042B042BЫЫЫ042B = b0430аа0430аа043004300430а();
      bЫ042BЫ042B042BЫЫЫ042B = 86;
    }
    localObject1 = ((Resources)localObject1).getString(i, new Object[] { wbbwww.b04180418ИИИИ04180418И0418((String)localObject2) });
    return localObject1;
    i = R.string.accessibility_arrangementtile_mortgage_reference;
    localObject2 = wbbwww.b04180418ИИИИ04180418И0418(this.bЫ042B042BЫ042BЫЫЫ042B.bжж04360436ж0436жж04360436());
    break label260;
    localObject1 = ((Resources)localObject1).getString(i, new Object[] { localObject2 });
    return localObject1;
    return "";
    label260:
    switch (1)
    {
    }
    for (;;)
    {
      switch (1)
      {
      }
    }
  }
  
  /* Error */
  public boolean b0430аааа0430043004300430а()
  {
    // Byte code:
    //   0: aload_0
    //   1: getfield 70	kkkkkk/qqqqqj:b042BЫ042BЫ042BЫЫЫ042B	Lkkkkkk/qqqqqj$qjjjjq;
    //   4: astore 7
    //   6: aload 7
    //   8: invokestatic 333	kkkkkk/qqqqqj$qjjjjq:bаааааа043004300430а	(Lkkkkkk/qqqqqj$qjjjjq;)Z
    //   11: istore 6
    //   13: getstatic 28	kkkkkk/qqqqqj:b042BЫЫ042B042BЫЫЫ042B	I
    //   16: istore_1
    //   17: getstatic 30	kkkkkk/qqqqqj:b042B042BЫ042B042BЫЫЫ042B	I
    //   20: istore_2
    //   21: getstatic 28	kkkkkk/qqqqqj:b042BЫЫ042B042BЫЫЫ042B	I
    //   24: istore_3
    //   25: getstatic 32	kkkkkk/qqqqqj:bЫЫ042B042B042BЫЫЫ042B	I
    //   28: istore 4
    //   30: getstatic 34	kkkkkk/qqqqqj:bЫ042BЫ042B042BЫЫЫ042B	I
    //   33: istore 5
    //   35: getstatic 28	kkkkkk/qqqqqj:b042BЫЫ042B042BЫЫЫ042B	I
    //   38: getstatic 30	kkkkkk/qqqqqj:b042B042BЫ042B042BЫЫЫ042B	I
    //   41: iadd
    //   42: getstatic 28	kkkkkk/qqqqqj:b042BЫЫ042B042BЫЫЫ042B	I
    //   45: imul
    //   46: getstatic 32	kkkkkk/qqqqqj:bЫЫ042B042B042BЫЫЫ042B	I
    //   49: irem
    //   50: getstatic 34	kkkkkk/qqqqqj:bЫ042BЫ042B042BЫЫЫ042B	I
    //   53: if_icmpeq +14 -> 67
    //   56: invokestatic 38	kkkkkk/qqqqqj:b0430аа0430аа043004300430а	()I
    //   59: putstatic 28	kkkkkk/qqqqqj:b042BЫЫ042B042BЫЫЫ042B	I
    //   62: bipush 31
    //   64: putstatic 34	kkkkkk/qqqqqj:bЫ042BЫ042B042BЫЫЫ042B	I
    //   67: iload_1
    //   68: iload_2
    //   69: iadd
    //   70: iload_3
    //   71: imul
    //   72: iload 4
    //   74: irem
    //   75: iload 5
    //   77: if_icmpeq +66 -> 143
    //   80: iconst_0
    //   81: tableswitch	default:+23->104, 0:+50->131, 1:+-1->80
    //   104: iconst_0
    //   105: tableswitch	default:+23->128, 0:+26->131, 1:+-25->80
    //   128: goto -24 -> 104
    //   131: invokestatic 38	kkkkkk/qqqqqj:b0430аа0430аа043004300430а	()I
    //   134: putstatic 28	kkkkkk/qqqqqj:b042BЫЫ042B042BЫЫЫ042B	I
    //   137: invokestatic 38	kkkkkk/qqqqqj:b0430аа0430аа043004300430а	()I
    //   140: putstatic 34	kkkkkk/qqqqqj:bЫ042BЫ042B042BЫЫЫ042B	I
    //   143: iload 6
    //   145: ireturn
    //   146: astore 7
    //   148: aload 7
    //   150: athrow
    //   151: astore 7
    //   153: aload 7
    //   155: athrow
    // Local variable table:
    //   start	length	slot	name	signature
    //   0	156	0	this	qqqqqj
    //   16	54	1	i	int
    //   20	50	2	j	int
    //   24	48	3	k	int
    //   28	47	4	m	int
    //   33	45	5	n	int
    //   11	133	6	bool	boolean
    //   4	3	7	localQjjjjq	qjjjjq
    //   146	3	7	localException1	Exception
    //   151	3	7	localException2	Exception
    // Exception table:
    //   from	to	target	type
    //   0	6	146	java/lang/Exception
    //   6	13	151	java/lang/Exception
  }
  
  public String bа0430043004300430а043004300430а()
  {
    i = 3;
    for (;;)
    {
      try
      {
        i /= 0;
        continue;
      }
      catch (Exception localException1)
      {
        Object localObject;
        i = b042BЫЫ042B042BЫЫЫ042B;
        switch (i * (b042B042BЫ042B042BЫЫЫ042B + i) % bЫЫ042B042B042BЫЫЫ042B)
        {
        default: 
          b042BЫЫ042B042BЫЫЫ042B = b0430аа0430аа043004300430а();
          bЫ042BЫ042B042BЫЫЫ042B = b0430аа0430аа043004300430а();
        }
        b042BЫЫ042B042BЫЫЫ042B = 41;
        continue;
      }
      try
      {
        localObject = this.bЫ042B042BЫ042BЫЫЫ042B;
      }
      catch (Exception localException2)
      {
        throw localException2;
      }
      try
      {
        localObject = mnmnmn.b0418И0418И04180418ИИ04180418(((cccrcc)localObject).b0436043604360436ж0436жж04360436());
        return localObject;
      }
      catch (Exception localException3)
      {
        throw localException3;
      }
      switch (0)
      {
      case 0: 
      default: 
        break;
      case 1: 
        switch (0)
        {
        }
        break;
      }
    }
  }
  
  public String bа043004300430аа043004300430а()
  {
    Resources localResources = App.get().getResources();
    int i = b042BЫЫ042B042BЫЫЫ042B;
    switch (i * (b042B042BЫ042B042BЫЫЫ042B + i) % bЫЫ042B042B042BЫЫЫ042B)
    {
    default: 
      b042BЫЫ042B042BЫЫЫ042B = b0430аа0430аа043004300430а();
      bЫ042BЫ042B042BЫЫЫ042B = b0430аа0430аа043004300430а();
    }
    i = bаааа0430а043004300430а();
    if ((b042BЫЫ042B042BЫЫЫ042B + b042B042BЫ042B042BЫЫЫ042B) * b042BЫЫ042B042BЫЫЫ042B % bааа0430аа043004300430а() != bЫ042BЫ042B042BЫЫЫ042B)
    {
      b042BЫЫ042B042BЫЫЫ042B = b0430аа0430аа043004300430а();
      bЫ042BЫ042B042BЫЫЫ042B = b0430аа0430аа043004300430а();
    }
    return localResources.getString(i, new Object[] { bа0430а04300430а043004300430а() });
  }
  
  /* Error */
  public ccrrcc bа04300430а0430а043004300430а()
  {
    // Byte code:
    //   0: iconst_0
    //   1: tableswitch	default:+23->24, 0:+50->51, 1:+-1->0
    //   24: iconst_1
    //   25: tableswitch	default:+23->48, 0:+-25->0, 1:+26->51
    //   48: goto -24 -> 24
    //   51: aload_0
    //   52: getfield 64	kkkkkk/qqqqqj:bЫ042B042BЫ042BЫЫЫ042B	Lkkkkkk/cccrcc;
    //   55: invokevirtual 162	kkkkkk/cccrcc:bжж04360436жжжж04360436	()Lkkkkkk/ccrrcc;
    //   58: astore 6
    //   60: getstatic 28	kkkkkk/qqqqqj:b042BЫЫ042B042BЫЫЫ042B	I
    //   63: istore_1
    //   64: getstatic 30	kkkkkk/qqqqqj:b042B042BЫ042B042BЫЫЫ042B	I
    //   67: istore_2
    //   68: getstatic 28	kkkkkk/qqqqqj:b042BЫЫ042B042BЫЫЫ042B	I
    //   71: istore_3
    //   72: getstatic 32	kkkkkk/qqqqqj:bЫЫ042B042B042BЫЫЫ042B	I
    //   75: istore 4
    //   77: getstatic 34	kkkkkk/qqqqqj:bЫ042BЫ042B042BЫЫЫ042B	I
    //   80: istore 5
    //   82: iload_1
    //   83: iload_2
    //   84: iadd
    //   85: iload_3
    //   86: imul
    //   87: iload 4
    //   89: irem
    //   90: iload 5
    //   92: if_icmpeq +44 -> 136
    //   95: invokestatic 38	kkkkkk/qqqqqj:b0430аа0430аа043004300430а	()I
    //   98: getstatic 30	kkkkkk/qqqqqj:b042B042BЫ042B042BЫЫЫ042B	I
    //   101: iadd
    //   102: invokestatic 38	kkkkkk/qqqqqj:b0430аа0430аа043004300430а	()I
    //   105: imul
    //   106: getstatic 32	kkkkkk/qqqqqj:bЫЫ042B042B042BЫЫЫ042B	I
    //   109: irem
    //   110: getstatic 34	kkkkkk/qqqqqj:bЫ042BЫ042B042BЫЫЫ042B	I
    //   113: if_icmpeq +13 -> 126
    //   116: bipush 26
    //   118: putstatic 28	kkkkkk/qqqqqj:b042BЫЫ042B042BЫЫЫ042B	I
    //   121: bipush 33
    //   123: putstatic 34	kkkkkk/qqqqqj:bЫ042BЫ042B042BЫЫЫ042B	I
    //   126: bipush 47
    //   128: putstatic 28	kkkkkk/qqqqqj:b042BЫЫ042B042BЫЫЫ042B	I
    //   131: bipush 91
    //   133: putstatic 34	kkkkkk/qqqqqj:bЫ042BЫ042B042BЫЫЫ042B	I
    //   136: aload 6
    //   138: areturn
    //   139: astore 6
    //   141: aload 6
    //   143: athrow
    //   144: astore 6
    //   146: aload 6
    //   148: athrow
    // Local variable table:
    //   start	length	slot	name	signature
    //   0	149	0	this	qqqqqj
    //   63	22	1	i	int
    //   67	18	2	j	int
    //   71	16	3	k	int
    //   75	15	4	m	int
    //   80	13	5	n	int
    //   58	79	6	localCcrrcc	ccrrcc
    //   139	3	6	localException1	Exception
    //   144	3	6	localException2	Exception
    // Exception table:
    //   from	to	target	type
    //   51	82	139	java/lang/Exception
    //   126	136	144	java/lang/Exception
  }
  
  public String bа0430а04300430а043004300430а()
  {
    Object localObject = qqqqqj.1.b042BЫ042B042B042BЫЫЫ042B;
    int i = b042BЫЫ042B042BЫЫЫ042B;
    switch (i * (b042B042BЫ042B042BЫЫЫ042B + i) % bааа0430аа043004300430а())
    {
    default: 
      b042BЫЫ042B042BЫЫЫ042B = 64;
      bЫ042BЫ042B042BЫЫЫ042B = 36;
    }
    switch (localObject[this.bЫ042B042BЫ042BЫЫЫ042B.bжж04360436жжжж04360436().ordinal()])
    {
    default: 
      localObject = mnmnmn.bИИИ0418И0418ИИ04180418(this.bЫ042B042BЫ042BЫЫЫ042B.bж043604360436жжжж04360436());
      if ((b042BЫЫ042B042BЫЫЫ042B + b042B042BЫ042B042BЫЫЫ042B) * b042BЫЫ042B042BЫЫЫ042B % bааа0430аа043004300430а() != bа0430а0430аа043004300430а())
      {
        b042BЫЫ042B042BЫЫЫ042B = 78;
        bЫ042BЫ042B042BЫЫЫ042B = b0430аа0430аа043004300430а();
      }
      switch (0)
      {
      case 1: 
      default: 
        for (;;)
        {
          switch (1)
          {
          }
        }
      }
      return localObject;
    case 2: 
      switch (0)
      {
      case 1: 
      default: 
        for (;;)
        {
          switch (0)
          {
          }
        }
      }
      return mnmnmn.b0418ИИ0418И0418ИИ04180418(this.bЫ042B042BЫ042BЫЫЫ042B.bж043604360436жжжж04360436(), mnmnmn.mmmnmn.CREDIT_AND_DEBIT);
    }
    return mnmnmn.bИ0418И0418И0418ИИ04180418(this.bЫ042B042BЫ042BЫЫЫ042B.bж043604360436жжжж04360436());
  }
  
  /* Error */
  public String bа0430аа0430а043004300430а()
  {
    // Byte code:
    //   0: aload_0
    //   1: getfield 64	kkkkkk/qqqqqj:bЫ042B042BЫ042BЫЫЫ042B	Lkkkkkk/cccrcc;
    //   4: astore_2
    //   5: getstatic 28	kkkkkk/qqqqqj:b042BЫЫ042B042BЫЫЫ042B	I
    //   8: getstatic 30	kkkkkk/qqqqqj:b042B042BЫ042B042BЫЫЫ042B	I
    //   11: iadd
    //   12: getstatic 28	kkkkkk/qqqqqj:b042BЫЫ042B042BЫЫЫ042B	I
    //   15: imul
    //   16: getstatic 32	kkkkkk/qqqqqj:bЫЫ042B042B042BЫЫЫ042B	I
    //   19: irem
    //   20: getstatic 34	kkkkkk/qqqqqj:bЫ042BЫ042B042BЫЫЫ042B	I
    //   23: if_icmpeq +55 -> 78
    //   26: bipush 23
    //   28: putstatic 28	kkkkkk/qqqqqj:b042BЫЫ042B042BЫЫЫ042B	I
    //   31: bipush 49
    //   33: putstatic 34	kkkkkk/qqqqqj:bЫ042BЫ042B042BЫЫЫ042B	I
    //   36: getstatic 28	kkkkkk/qqqqqj:b042BЫЫ042B042BЫЫЫ042B	I
    //   39: istore_1
    //   40: iload_1
    //   41: getstatic 30	kkkkkk/qqqqqj:b042B042BЫ042B042BЫЫЫ042B	I
    //   44: iload_1
    //   45: iadd
    //   46: imul
    //   47: getstatic 32	kkkkkk/qqqqqj:bЫЫ042B042B042BЫЫЫ042B	I
    //   50: irem
    //   51: tableswitch	default:+17->68, 0:+27->78
    //   68: bipush 47
    //   70: putstatic 28	kkkkkk/qqqqqj:b042BЫЫ042B042BЫЫЫ042B	I
    //   73: bipush 16
    //   75: putstatic 34	kkkkkk/qqqqqj:bЫ042BЫ042B042BЫЫЫ042B	I
    //   78: aload_2
    //   79: invokevirtual 337	kkkkkk/cccrcc:b0436043604360436ж0436жж04360436	()Ljava/lang/String;
    //   82: invokestatic 360	kkkkkk/wbbwww:b041804180418041804180418И0418И0418	(Ljava/lang/String;)Ljava/lang/String;
    //   85: astore_2
    //   86: iconst_0
    //   87: tableswitch	default:+21->108, 0:+48->135, 1:+-1->86
    //   108: iconst_1
    //   109: tableswitch	default:+23->132, 0:+-23->86, 1:+26->135
    //   132: goto -24 -> 108
    //   135: aload_2
    //   136: areturn
    //   137: astore_2
    //   138: aload_2
    //   139: athrow
    //   140: astore_2
    //   141: aload_2
    //   142: athrow
    // Local variable table:
    //   start	length	slot	name	signature
    //   0	143	0	this	qqqqqj
    //   39	8	1	i	int
    //   4	132	2	localObject	Object
    //   137	2	2	localException1	Exception
    //   140	2	2	localException2	Exception
    // Exception table:
    //   from	to	target	type
    //   5	36	137	java/lang/Exception
    //   0	5	140	java/lang/Exception
    //   78	86	140	java/lang/Exception
  }
  
  public boolean bа0430ааа0430043004300430а()
  {
    switch (1)
    {
    case 0: 
    default: 
      for (;;)
      {
        switch (0)
        {
        }
      }
    }
    boolean bool = this.b042B042B042BЫ042BЫЫЫ042B;
    if ((b042BЫЫ042B042BЫЫЫ042B + b042B042BЫ042B042BЫЫЫ042B) * b042BЫЫ042B042BЫЫЫ042B % bЫЫ042B042B042BЫЫЫ042B != bЫ042BЫ042B042BЫЫЫ042B)
    {
      b042BЫЫ042B042BЫЫЫ042B = b0430аа0430аа043004300430а();
      bЫ042BЫ042B042BЫЫЫ042B = b0430аа0430аа043004300430а();
    }
    return bool;
  }
  
  public int bаа043004300430а043004300430а()
  {
    int i = 0;
    switch (1)
    {
    case 0: 
    default: 
      for (;;)
      {
        switch (0)
        {
        }
      }
    }
    try
    {
      int[] arrayOfInt = qqqqqj.1.b042BЫ042B042B042BЫЫЫ042B;
      if ((b042BЫЫ042B042BЫЫЫ042B + b042B042BЫ042B042BЫЫЫ042B) * b042BЫЫ042B042BЫЫЫ042B % bЫЫ042B042B042BЫЫЫ042B != bЫ042BЫ042B042BЫЫЫ042B)
      {
        b042BЫЫ042B042BЫЫЫ042B = b0430аа0430аа043004300430а();
        bЫ042BЫ042B042BЫЫЫ042B = 59;
      }
      int j = arrayOfInt[this.bЫ042B042BЫ042BЫЫЫ042B.bжж04360436жжжж04360436().ordinal()];
      switch (j)
      {
      default: 
      case 3: 
      case 4: 
      case 5: 
      case 6: 
        for (;;)
        {
          return i;
          try
          {
            j = R.drawable.arrangement_savings_icon;
            int k = b042BЫЫ042B042BЫЫЫ042B;
            int m = b042B042BЫ042B042BЫЫЫ042B;
            int n = b042BЫЫ042B042BЫЫЫ042B;
            int i1 = bЫЫ042B042B042BЫЫЫ042B;
            int i2 = bа0430а0430аа043004300430а();
            i = j;
            if ((k + m) * n % i1 != i2)
            {
              b042BЫЫ042B042BЫЫЫ042B = b0430аа0430аа043004300430а();
              bЫ042BЫ042B042BЫЫЫ042B = 94;
              return j;
            }
          }
          catch (Exception localException1)
          {
            throw localException1;
          }
        }
      case 7: 
      case 8: 
        return R.drawable.arrangement_isa_icon;
      case 11: 
      case 12: 
        return R.drawable.arrangement_mortgage_icon;
      case 9: 
      case 10: 
        return R.drawable.arrangement_loan_icon;
      case 1: 
        i = R.drawable.arrangement_current_icon;
        return i;
      }
      i = R.drawable.arrangement_credit_card_icon;
      return i;
    }
    catch (Exception localException2)
    {
      throw localException2;
    }
  }
  
  public String bаа04300430аа043004300430а()
  {
    switch (0)
    {
    case 1: 
    default: 
      for (;;)
      {
        switch (1)
        {
        }
      }
    }
    int i = b042BЫЫ042B042BЫЫЫ042B;
    switch (i * (b042B042BЫ042B042BЫЫЫ042B + i) % bЫЫ042B042B042BЫЫЫ042B)
    {
    default: 
      b042BЫЫ042B042BЫЫЫ042B = 36;
      bЫ042BЫ042B042BЫЫЫ042B = b0430аа0430аа043004300430а();
    }
    String str = wbbwww.b04180418ИИИИ04180418И0418(this.bЫ042B042BЫ042BЫЫЫ042B.bжжж0436жжжж04360436());
    if ((b042BЫЫ042B042BЫЫЫ042B + b042B042BЫ042B042BЫЫЫ042B) * b042BЫЫ042B042BЫЫЫ042B % bЫЫ042B042B042BЫЫЫ042B != bЫ042BЫ042B042BЫЫЫ042B)
    {
      b042BЫЫ042B042BЫЫЫ042B = 93;
      bЫ042BЫ042B042BЫЫЫ042B = b0430аа0430аа043004300430а();
    }
    return str;
  }
  
  public String bаа0430а0430а043004300430а()
  {
    switch (1)
    {
    case 0: 
    default: 
      for (;;)
      {
        switch (0)
        {
        }
      }
    }
    try
    {
      String str = this.bЫ042B042BЫ042BЫЫЫ042B.bжжж0436жжжж04360436();
      int i = b042BЫЫ042B042BЫЫЫ042B;
      switch (i * (b042B042BЫ042B042BЫЫЫ042B + i) % bЫЫ042B042B042BЫЫЫ042B)
      {
      }
      for (;;)
      {
        i = b0430аа0430аа043004300430а();
      }
    }
    catch (Exception localException1)
    {
      try
      {
        b042BЫЫ042B042BЫЫЫ042B = i;
        bЫ042BЫ042B042BЫЫЫ042B = 11;
        i = b042BЫЫ042B042BЫЫЫ042B;
        switch (i * (b042B042BЫ042B042BЫЫЫ042B + i) % bЫЫ042B042B042BЫЫЫ042B)
        {
        default: 
          b042BЫЫ042B042BЫЫЫ042B = 35;
          bЫ042BЫ042B042BЫЫЫ042B = 89;
        }
        return str;
      }
      catch (Exception localException2)
      {
        throw localException2;
      }
      localException1 = localException1;
      throw localException1;
    }
  }
  
  public String bааа04300430а043004300430а()
  {
    String str;
    switch (qqqqqj.1.b042BЫ042B042B042BЫЫЫ042B[this.bЫ042B042BЫ042BЫЫЫ042B.bжж04360436жжжж04360436().ordinal()])
    {
    default: 
      str = "";
    }
    for (;;)
    {
      int i = b042BЫЫ042B042BЫЫЫ042B;
      switch (i * (b043004300430ааа043004300430а() + i) % bЫЫ042B042B042BЫЫЫ042B)
      {
      default: 
        i = b042BЫЫ042B042BЫЫЫ042B;
        switch (i * (b042B042BЫ042B042BЫЫЫ042B + i) % bЫЫ042B042B042BЫЫЫ042B)
        {
        default: 
          b042BЫЫ042B042BЫЫЫ042B = 9;
          bЫ042BЫ042B042BЫЫЫ042B = b0430аа0430аа043004300430а();
        }
        b042BЫЫ042B042BЫЫЫ042B = b0430аа0430аа043004300430а();
        bЫ042BЫ042B042BЫЫЫ042B = 6;
      }
      return str;
      for (;;)
      {
        switch (0)
        {
        default: 
          break;
        case 0: 
          str = gguuuu.bккккк043Aкк043A043A("|\003\f{\013\r\007\n\021^\002\003\020\027\021\030", '[', '\001');
          break;
          str = gguuuu.bккккк043Aкк043A043A("89;<.',)\030(43! +0(-", '´', '\005');
          break;
        case 1: 
          switch (0)
          {
          }
          break;
        }
      }
      str = gguuuu.bккккк043Aкк043A043A("5@-\023<)\b)(3805", '', '\002');
      continue;
      str = gguuuu.bккккк043Aкк043A043A("\033!\036\025w\034 !\035\013\027\013\f", 'å', '\003');
      continue;
      str = gguuuu.bккккк043Aкк043A043A("UfbaS[`,MLW\\TY", '', '\003');
      continue;
      str = gguuuu.bккккк043Aкк043A043A("r\001rpt~Jkjuzrw", 'p', '\005');
      continue;
      str = gguuuu.bк043Aккк043Aкк043A043A("\027\032\036!\025\020\027\026r\026\027$+%,", '£', 'ù', '\001');
      continue;
      str = gguuuu.bк043Aккк043Aкк043A043A("YWgCWcc^\\NX7YJV(IHSXPU", '²', '¨', '\000');
      continue;
      str = gguuuu.bккккк043Aкк043A043A("l\\hb8Xb`cXb.ONY^V[", '\b', '\005');
      continue;
      str = gguuuu.bк043Aккк043Aкк043A043A(";(<.2*5\002#\"-2*/", '´', '|', '\000');
      continue;
      switch (0)
      {
      case 1: 
      default: 
        for (;;)
        {
          switch (0)
          {
          }
        }
      }
      str = gguuuu.bккккк043Aкк043A043A("cbVSfig[**=]i", 'n', '\000');
      continue;
      str = gguuuu.bк043Aккк043Aкк043A043A("! \024\021$'%\031z*\033", '{', '0', '\003');
      continue;
      str = gguuuu.bккккк043Aкк043A043A("\t\022~]~}\t\016\006\013", 'ß', '\005');
      continue;
      str = gguuuu.bк043Aккк043Aкк043A043A("\036  u\026(\006\034*,))\035)\n.!/\003&'4;5<", 'Ð', '¡', '\001');
    }
  }
  
  /* Error */
  public boolean bааааа0430043004300430а()
  {
    // Byte code:
    //   0: getstatic 28	kkkkkk/qqqqqj:b042BЫЫ042B042BЫЫЫ042B	I
    //   3: istore_1
    //   4: iload_1
    //   5: invokestatic 164	kkkkkk/qqqqqj:b043004300430ааа043004300430а	()I
    //   8: iload_1
    //   9: iadd
    //   10: imul
    //   11: getstatic 32	kkkkkk/qqqqqj:bЫЫ042B042B042BЫЫЫ042B	I
    //   14: irem
    //   15: tableswitch	default:+17->32, 0:+29->44
    //   32: invokestatic 38	kkkkkk/qqqqqj:b0430аа0430аа043004300430а	()I
    //   35: putstatic 28	kkkkkk/qqqqqj:b042BЫЫ042B042BЫЫЫ042B	I
    //   38: invokestatic 38	kkkkkk/qqqqqj:b0430аа0430аа043004300430а	()I
    //   41: putstatic 34	kkkkkk/qqqqqj:bЫ042BЫ042B042BЫЫЫ042B	I
    //   44: aload_0
    //   45: getfield 64	kkkkkk/qqqqqj:bЫ042B042BЫ042BЫЫЫ042B	Lkkkkkk/cccrcc;
    //   48: astore_3
    //   49: getstatic 28	kkkkkk/qqqqqj:b042BЫЫ042B042BЫЫЫ042B	I
    //   52: getstatic 30	kkkkkk/qqqqqj:b042B042BЫ042B042BЫЫЫ042B	I
    //   55: iadd
    //   56: getstatic 28	kkkkkk/qqqqqj:b042BЫЫ042B042BЫЫЫ042B	I
    //   59: imul
    //   60: getstatic 32	kkkkkk/qqqqqj:bЫЫ042B042B042BЫЫЫ042B	I
    //   63: irem
    //   64: getstatic 34	kkkkkk/qqqqqj:bЫ042BЫ042B042BЫЫЫ042B	I
    //   67: if_icmpeq +13 -> 80
    //   70: bipush 21
    //   72: putstatic 28	kkkkkk/qqqqqj:b042BЫЫ042B042BЫЫЫ042B	I
    //   75: bipush 12
    //   77: putstatic 34	kkkkkk/qqqqqj:bЫ042BЫ042B042BЫЫЫ042B	I
    //   80: aload_3
    //   81: invokevirtual 424	kkkkkk/cccrcc:b0436жжжж04360436ж04360436	()Z
    //   84: istore_2
    //   85: iload_2
    //   86: ireturn
    //   87: astore_3
    //   88: aload_3
    //   89: athrow
    //   90: astore_3
    //   91: aload_3
    //   92: athrow
    // Local variable table:
    //   start	length	slot	name	signature
    //   0	93	0	this	qqqqqj
    //   3	8	1	i	int
    //   84	2	2	bool	boolean
    //   48	33	3	localCccrcc	cccrcc
    //   87	2	3	localException1	Exception
    //   90	2	3	localException2	Exception
    // Exception table:
    //   from	to	target	type
    //   44	49	87	java/lang/Exception
    //   80	85	90	java/lang/Exception
  }
  
  public static class qjjjjq
  {
    public static int b042B042B042BЫЫ042BЫЫ042B = 0;
    public static int b042BЫ042BЫЫ042BЫЫ042B = 2;
    public static int bЫ042B042BЫЫ042BЫЫ042B = 1;
    public static int bЫЫ042BЫЫ042BЫЫ042B = 63;
    @StringRes
    private final int b042B042BЫЫЫ042BЫЫ042B;
    @StringRes
    private final int b042BЫЫЫЫ042BЫЫ042B;
    private final boolean bЫ042BЫЫЫ042BЫЫ042B;
    
    public qjjjjq(boolean paramBoolean, @StringRes int paramInt1, @StringRes int paramInt2)
    {
      this.bЫ042BЫЫЫ042BЫЫ042B = paramBoolean;
      this.b042BЫЫЫЫ042BЫЫ042B = paramInt1;
      this.b042B042BЫЫЫ042BЫЫ042B = paramInt2;
    }
    
    public static int b04300430аааа043004300430а()
    {
      return 1;
    }
    
    /* Error */
    private String b0430а0430ааа043004300430а(Resources paramResources)
    {
      // Byte code:
      //   0: aload_0
      //   1: getfield 30	kkkkkk/qqqqqj$qjjjjq:b042BЫЫЫЫ042BЫЫ042B	I
      //   4: ifne +99 -> 103
      //   7: ldc 57
      //   9: astore_1
      //   10: aload_1
      //   11: areturn
      //   12: astore_1
      //   13: aload_1
      //   14: athrow
      //   15: astore_1
      //   16: aload_1
      //   17: athrow
      //   18: iload_2
      //   19: iload_3
      //   20: iadd
      //   21: iload 4
      //   23: imul
      //   24: iload 5
      //   26: irem
      //   27: invokestatic 60	kkkkkk/qqqqqj$qjjjjq:bа0430аааа043004300430а	()I
      //   30: if_icmpeq +13 -> 43
      //   33: invokestatic 40	kkkkkk/qqqqqj$qjjjjq:b0430ааааа043004300430а	()I
      //   36: putstatic 48	kkkkkk/qqqqqj$qjjjjq:bЫЫ042BЫЫ042BЫЫ042B	I
      //   39: iconst_2
      //   40: putstatic 46	kkkkkk/qqqqqj$qjjjjq:b042B042B042BЫЫ042BЫЫ042B	I
      //   43: aload_1
      //   44: aload_0
      //   45: getfield 30	kkkkkk/qqqqqj$qjjjjq:b042BЫЫЫЫ042BЫЫ042B	I
      //   48: invokevirtual 66	android/content/res/Resources:getString	(I)Ljava/lang/String;
      //   51: astore 6
      //   53: getstatic 48	kkkkkk/qqqqqj$qjjjjq:bЫЫ042BЫЫ042BЫЫ042B	I
      //   56: istore_2
      //   57: aload 6
      //   59: astore_1
      //   60: iload_2
      //   61: getstatic 42	kkkkkk/qqqqqj$qjjjjq:bЫ042B042BЫЫ042BЫЫ042B	I
      //   64: iload_2
      //   65: iadd
      //   66: imul
      //   67: invokestatic 69	kkkkkk/qqqqqj$qjjjjq:bаа0430ааа043004300430а	()I
      //   70: irem
      //   71: tableswitch	default:+17->88, 0:+-61->10
      //   88: invokestatic 40	kkkkkk/qqqqqj$qjjjjq:b0430ааааа043004300430а	()I
      //   91: putstatic 48	kkkkkk/qqqqqj$qjjjjq:bЫЫ042BЫЫ042BЫЫ042B	I
      //   94: invokestatic 40	kkkkkk/qqqqqj$qjjjjq:b0430ааааа043004300430а	()I
      //   97: putstatic 46	kkkkkk/qqqqqj$qjjjjq:b042B042B042BЫЫ042BЫЫ042B	I
      //   100: aload 6
      //   102: areturn
      //   103: getstatic 48	kkkkkk/qqqqqj$qjjjjq:bЫЫ042BЫЫ042BЫЫ042B	I
      //   106: istore_2
      //   107: getstatic 42	kkkkkk/qqqqqj$qjjjjq:bЫ042B042BЫЫ042BЫЫ042B	I
      //   110: istore_3
      //   111: getstatic 48	kkkkkk/qqqqqj$qjjjjq:bЫЫ042BЫЫ042BЫЫ042B	I
      //   114: istore 4
      //   116: getstatic 44	kkkkkk/qqqqqj$qjjjjq:b042BЫ042BЫЫ042BЫЫ042B	I
      //   119: istore 5
      //   121: iconst_0
      //   122: tableswitch	default:+22->144, 0:+-104->18, 1:+-1->121
      //   144: iconst_0
      //   145: tableswitch	default:+23->168, 0:+-127->18, 1:+-24->121
      //   168: goto -24 -> 144
      // Local variable table:
      //   start	length	slot	name	signature
      //   0	171	0	this	qjjjjq
      //   0	171	1	paramResources	Resources
      //   18	89	2	i	int
      //   19	92	3	j	int
      //   21	94	4	k	int
      //   24	96	5	m	int
      //   51	50	6	str	String
      // Exception table:
      //   from	to	target	type
      //   0	7	12	java/lang/Exception
      //   43	53	15	java/lang/Exception
    }
    
    public static int b0430ааааа043004300430а()
    {
      return 99;
    }
    
    /* Error */
    private String bа04300430ааа043004300430а(Resources paramResources)
    {
      // Byte code:
      //   0: iconst_1
      //   1: istore_2
      //   2: aload_0
      //   3: getfield 32	kkkkkk/qqqqqj$qjjjjq:b042B042BЫЫЫ042BЫЫ042B	I
      //   6: istore_3
      //   7: getstatic 48	kkkkkk/qqqqqj$qjjjjq:bЫЫ042BЫЫ042BЫЫ042B	I
      //   10: invokestatic 72	kkkkkk/qqqqqj$qjjjjq:b04300430аааа043004300430а	()I
      //   13: iadd
      //   14: getstatic 48	kkkkkk/qqqqqj$qjjjjq:bЫЫ042BЫЫ042BЫЫ042B	I
      //   17: imul
      //   18: getstatic 44	kkkkkk/qqqqqj$qjjjjq:b042BЫ042BЫЫ042BЫЫ042B	I
      //   21: irem
      //   22: invokestatic 60	kkkkkk/qqqqqj$qjjjjq:bа0430аааа043004300430а	()I
      //   25: if_icmpeq +15 -> 40
      //   28: invokestatic 40	kkkkkk/qqqqqj$qjjjjq:b0430ааааа043004300430а	()I
      //   31: putstatic 48	kkkkkk/qqqqqj$qjjjjq:bЫЫ042BЫЫ042BЫЫ042B	I
      //   34: invokestatic 40	kkkkkk/qqqqqj$qjjjjq:b0430ааааа043004300430а	()I
      //   37: putstatic 46	kkkkkk/qqqqqj$qjjjjq:b042B042B042BЫЫ042BЫЫ042B	I
      //   40: iload_3
      //   41: ifne +84 -> 125
      //   44: new 77	java/lang/NullPointerException
      //   47: dup
      //   48: invokespecial 78	java/lang/NullPointerException:<init>	()V
      //   51: athrow
      //   52: astore_1
      //   53: bipush 70
      //   55: putstatic 48	kkkkkk/qqqqqj$qjjjjq:bЫЫ042BЫЫ042BЫЫ042B	I
      //   58: iload_2
      //   59: iconst_0
      //   60: idiv
      //   61: istore_2
      //   62: goto -4 -> 58
      //   65: iconst_1
      //   66: tableswitch	default:+22->88, 0:+25->91, 1:+53->119
      //   88: goto -23 -> 65
      //   91: iconst_1
      //   92: tableswitch	default:+24->116, 0:+-1->91, 1:+27->119
      //   116: goto -51 -> 65
      //   119: aload_1
      //   120: iload_2
      //   121: invokevirtual 66	android/content/res/Resources:getString	(I)Ljava/lang/String;
      //   124: areturn
      //   125: aload_0
      //   126: getfield 32	kkkkkk/qqqqqj$qjjjjq:b042B042BЫЫЫ042BЫЫ042B	I
      //   129: istore_2
      //   130: goto -39 -> 91
      //   133: astore_1
      //   134: invokestatic 40	kkkkkk/qqqqqj$qjjjjq:b0430ааааа043004300430а	()I
      //   137: putstatic 48	kkkkkk/qqqqqj$qjjjjq:bЫЫ042BЫЫ042BЫЫ042B	I
      //   140: ldc 57
      //   142: areturn
      //   143: astore_1
      //   144: aload_1
      //   145: athrow
      //   146: astore_1
      //   147: aload_1
      //   148: athrow
      // Local variable table:
      //   start	length	slot	name	signature
      //   0	149	0	this	qjjjjq
      //   0	149	1	paramResources	Resources
      //   1	129	2	i	int
      //   6	35	3	j	int
      // Exception table:
      //   from	to	target	type
      //   44	52	52	java/lang/Exception
      //   58	62	133	java/lang/Exception
      //   53	58	143	java/lang/Exception
      //   134	140	143	java/lang/Exception
      //   2	7	146	java/lang/Exception
      //   119	125	146	java/lang/Exception
      //   125	130	146	java/lang/Exception
    }
    
    public static int bа0430аааа043004300430а()
    {
      return 0;
    }
    
    public static int bаа0430ааа043004300430а()
    {
      return 2;
    }
  }
}
