package kkkkkk;

import com.fasterxml.jackson.annotation.JsonEnumDefaultValue;

public enum rccrcr
{
  private final String mRoutingCode;
  
  static
  {
    EXISTING_CURRENT_ACCOUNT = new rccrcr(gguuuu.bк043Aккк043Aкк043A043A("4H:EG=C=V;NLMAKR^ADERYSZ", 'ó', 'ø', '\003'), 1, gguuuu.bк043Aккк043Aкк043A043A(":)D'XTSEMR0AMPB;<", '', 's', '\000'));
    EXISTING_SAVINGS_ACCOUNT = new rccrcr(gguuuu.bккккк043Aкк043A043A("hzjssgkczmZn`d\\grSTS^c[`", '\\', '\005'), 2, gguuuu.bк043Aккк043Aкк043A043A("A2ODSi]c]jK^lqe`c", '\035', 'Ï', '\003'));
    EXISTING_ISA_ACCOUNT = new rccrcr(gguuuu.bккккк043Aкк043A043A("@TFQSIOIbMXGfILMZa[b", '¼', '\004'), 3, gguuuu.bккккк043Aкк043A043A("n_|grat\b\026\033\017\n\r", 'M', '\004'));
    EXISTING_CREDIT_CARD_ACCOUNT = new rccrcr(gguuuu.bккккк043Aкк043A043A("\f \022\035\037\025\033\025.\023#\027\027\035)5\032\031+\036:\035 !.5/6", 'Å', '\000'), 4, gguuuu.bк043Aккк043Aкк043A043A("\025\006#\b8,,2>\0361?D836", ';', '', '\003'));
    EXISTING_LOAN_ACCOUNT = new rccrcr(gguuuu.bккккк043Aкк043A043A("\021%\027\"$\032 \0323!%\030&8\033\036\037,3-4", 'Ê', '\000'), 5, gguuuu.bккккк043Aкк043A043A("\037\016)\0257(4\030)58*#$", '', '\003'));
    NEW_CURRENT_ACCOUNT = new rccrcr(gguuuu.bк043Aккк043Aкк043A043A("<4GP5HFG;ELX;>?LSMT", '1', '<', '\003'), 6, gguuuu.bк043Aккк043Aкк043A043A("C2M;Qb-^ZYKSX", '7', 'X', '\002'));
    NEW_SAVINGS_ACCOUNT = new rccrcr(gguuuu.bк043Aккк043Aкк043A043A("}s\005\f~kqumx\004dedotlq", 'ß', 'o', '\002'), 7, gguuuu.bккккк043Aкк043A043A("M>[KcvSbxlrl", 'ü', '\001'));
    NEW_ISA_ACCOUNT = new rccrcr(gguuuu.bккккк043Aкк043A043A("zr\006\017y\005s\023uxy\007\016\b\017", ',', '\000'), 8, gguuuu.bк043Aккк043Aкк043A043A("5$?-CT%.\033", 'z', '\\', '\000'));
    NEW_CREDIT_CARD_ACCOUNT = new rccrcr(gguuuu.bккккк043Aкк043A043A("H@S\\AQEEKWcHGYLhKNO\\c]d", 'ø', '\000'), 9, gguuuu.bккккк043Aкк043A043A("\021\033\t\0370z)\033\031\035'", '\026', '\002'));
    NEW_LOAN_ACCOUNT = new rccrcr(gguuuu.bк043Aккк043Aкк043A043A("\030\020#,\032\036\021\0371\024\027\030%,&-", '|', 'L', '\003'), 10, gguuuu.bккккк043Aкк043A043A("VE`NduIk\\h", '>', '\003'));
    INTERNET_BANKING = new rccrcr(gguuuu.bк043Aккк043Aкк043A043A("QW^P^[ScoSSa_^d^", 'Q', 'È', '\001'), 11, gguuuu.bккккк043Aкк043A043A("rc\001kel", 'Þ', '\001'));
    int i = b043F043F043Fппп043F043Fпп();
    switch (i * (bппп043Fпп043F043Fпп() + i) % bп043F043Fппп043F043Fпп())
    {
    }
    OTHER_BANKING_QUERY = new rccrcr(gguuuu.bк043Aккк043Aкк043A043A("39.,:H,,:87=7PCH9GO", 'B', 'Ý', '\001'), 12, gguuuu.bккккк043Aкк043A043A("]LgNksiucm", 'z', '\003'));
    rccrcr localRccrcr1 = new rccrcr(gguuuu.bк043Aккк043Aкк043A043A("z}|zpo\002ss\020w\005t\ny", '3', '\f', '\001'), 13, gguuuu.bк043Aккк043Aкк043A043A("p\016u#\023(\030", '', '\035', '\003'));
    i = b043F043F043Fппп043F043Fпп();
    switch (i * (bппп043Fпп043F043Fпп() + i) % bп043F043Fппп043F043Fпп())
    {
    }
    SUSPECTED_FRAUD = localRccrcr1;
    localRccrcr1 = new rccrcr(gguuuu.bккккк043Aкк043A043A("gillvegsff`\\T\\lOL\\M[", 'v', '\002'), 14, gguuuu.bккккк043Aкк043A043A("yj\bu\032\037!\001#\037\035\027!", '&', '\000'));
    if ((b043F043F043Fппп043F043Fпп() + bппп043Fпп043F043Fпп()) * b043F043F043Fппп043F043Fпп() % bп043F043Fппп043F043Fпп() != b043Fпп043Fпп043F043Fпп()) {}
    LOST_OR_STOLEN_CARDS = localRccrcr1;
    EMERGENCY_CASH_ABROAD = new rccrcr(gguuuu.bккккк043Aкк043A043A("\026\037\030&\034\033%\03329\036\0350&>!#42%)", 'E', '\001'), 15, gguuuu.bккккк043Aкк043A043A("gXu\\\006~\r\003\002\f\002\031c\003\026\f", '', '\000'));
    NO_ROUTING_CODE = new rccrcr(gguuuu.bк043Aккк043Aкк043A043A("79J><CC9?9R7D:<", '', '', '\001'), 16, "");
    localRccrcr1 = UNKNOWN;
    rccrcr localRccrcr2 = EXISTING_CURRENT_ACCOUNT;
    rccrcr localRccrcr3 = EXISTING_SAVINGS_ACCOUNT;
    rccrcr localRccrcr4 = EXISTING_ISA_ACCOUNT;
    rccrcr localRccrcr5 = EXISTING_CREDIT_CARD_ACCOUNT;
    rccrcr localRccrcr6 = EXISTING_LOAN_ACCOUNT;
    rccrcr localRccrcr7 = NEW_CURRENT_ACCOUNT;
    rccrcr localRccrcr8 = NEW_SAVINGS_ACCOUNT;
    rccrcr localRccrcr9 = NEW_ISA_ACCOUNT;
    switch (1)
    {
    case 0: 
    default: 
      for (;;)
      {
        switch (0)
        {
        }
      }
    }
    $VALUES = new rccrcr[] { localRccrcr1, localRccrcr2, localRccrcr3, localRccrcr4, localRccrcr5, localRccrcr6, localRccrcr7, localRccrcr8, localRccrcr9, NEW_CREDIT_CARD_ACCOUNT, NEW_LOAN_ACCOUNT, INTERNET_BANKING, OTHER_BANKING_QUERY, SUSPECTED_FRAUD, LOST_OR_STOLEN_CARDS, EMERGENCY_CASH_ABROAD, NO_ROUTING_CODE };
  }
  
  @ooiiio
  private rccrcr(String paramString)
  {
    this.mRoutingCode = paramString;
  }
  
  public static int b043F043F043Fппп043F043Fпп()
  {
    return 25;
  }
  
  /* Error */
  @ooiiio("Mapping code")
  public static rccrcr b043F043Fп043Fпп043F043Fпп(rcrccr paramRcrccr)
  {
    // Byte code:
    //   0: getstatic 183	kkkkkk/rccrcr$1:bМ041CМ041CМ041C041CММ	[I
    //   3: aload_0
    //   4: invokevirtual 188	kkkkkk/rcrccr:ordinal	()I
    //   7: iaload
    //   8: tableswitch	default:+213->221, 1:+125->133, 2:+129->137, 3:+129->137, 4:+196->204, 5:+200->208, 6:+109->117, 7:+121->129, 8:+113->121, 9:+117->125, 10:+138->146, 11:+167->175, 12:+207->215, 13:+207->215, 14:+207->215
    //   80: new 190	java/lang/IllegalArgumentException
    //   83: dup
    //   84: new 192	java/lang/StringBuilder
    //   87: dup
    //   88: invokespecial 194	java/lang/StringBuilder:<init>	()V
    //   91: ldc -60
    //   93: sipush 146
    //   96: iconst_1
    //   97: invokestatic 44	kkkkkk/gguuuu:bккккк043Aкк043A043A	(Ljava/lang/String;CC)Ljava/lang/String;
    //   100: invokevirtual 200	java/lang/StringBuilder:append	(Ljava/lang/String;)Ljava/lang/StringBuilder;
    //   103: aload_0
    //   104: invokevirtual 203	java/lang/StringBuilder:append	(Ljava/lang/Object;)Ljava/lang/StringBuilder;
    //   107: invokevirtual 207	java/lang/StringBuilder:toString	()Ljava/lang/String;
    //   110: invokespecial 209	java/lang/IllegalArgumentException:<init>	(Ljava/lang/String;)V
    //   113: athrow
    //   114: astore_0
    //   115: aload_0
    //   116: athrow
    //   117: getstatic 153	kkkkkk/rccrcr:EMERGENCY_CASH_ABROAD	Lkkkkkk/rccrcr;
    //   120: areturn
    //   121: getstatic 92	kkkkkk/rccrcr:NEW_SAVINGS_ACCOUNT	Lkkkkkk/rccrcr;
    //   124: areturn
    //   125: getstatic 104	kkkkkk/rccrcr:NEW_CREDIT_CARD_ACCOUNT	Lkkkkkk/rccrcr;
    //   128: areturn
    //   129: getstatic 86	kkkkkk/rccrcr:NEW_CURRENT_ACCOUNT	Lkkkkkk/rccrcr;
    //   132: areturn
    //   133: getstatic 116	kkkkkk/rccrcr:INTERNET_BANKING	Lkkkkkk/rccrcr;
    //   136: areturn
    //   137: getstatic 132	kkkkkk/rccrcr:OTHER_BANKING_QUERY	Lkkkkkk/rccrcr;
    //   140: astore_0
    //   141: aload_0
    //   142: areturn
    //   143: astore_0
    //   144: aload_0
    //   145: athrow
    //   146: getstatic 98	kkkkkk/rccrcr:NEW_ISA_ACCOUNT	Lkkkkkk/rccrcr;
    //   149: astore_1
    //   150: aload_1
    //   151: astore_0
    //   152: invokestatic 120	kkkkkk/rccrcr:b043F043F043Fппп043F043Fпп	()I
    //   155: invokestatic 123	kkkkkk/rccrcr:bппп043Fпп043F043Fпп	()I
    //   158: iadd
    //   159: invokestatic 120	kkkkkk/rccrcr:b043F043F043Fппп043F043Fпп	()I
    //   162: imul
    //   163: invokestatic 126	kkkkkk/rccrcr:bп043F043Fппп043F043Fпп	()I
    //   166: irem
    //   167: invokestatic 145	kkkkkk/rccrcr:b043Fпп043Fпп043F043Fпп	()I
    //   170: if_icmpeq +54 -> 224
    //   173: aload_1
    //   174: areturn
    //   175: getstatic 110	kkkkkk/rccrcr:NEW_LOAN_ACCOUNT	Lkkkkkk/rccrcr;
    //   178: astore_1
    //   179: aload_1
    //   180: astore_0
    //   181: invokestatic 120	kkkkkk/rccrcr:b043F043F043Fппп043F043Fпп	()I
    //   184: invokestatic 123	kkkkkk/rccrcr:bппп043Fпп043F043Fпп	()I
    //   187: iadd
    //   188: invokestatic 120	kkkkkk/rccrcr:b043F043F043Fппп043F043Fпп	()I
    //   191: imul
    //   192: invokestatic 126	kkkkkk/rccrcr:bп043F043Fппп043F043Fпп	()I
    //   195: irem
    //   196: invokestatic 145	kkkkkk/rccrcr:b043Fпп043Fпп043F043Fпп	()I
    //   199: if_icmpeq +25 -> 224
    //   202: aload_1
    //   203: areturn
    //   204: getstatic 147	kkkkkk/rccrcr:LOST_OR_STOLEN_CARDS	Lkkkkkk/rccrcr;
    //   207: areturn
    //   208: getstatic 138	kkkkkk/rccrcr:SUSPECTED_FRAUD	Lkkkkkk/rccrcr;
    //   211: astore_1
    //   212: goto +14 -> 226
    //   215: getstatic 159	kkkkkk/rccrcr:NO_ROUTING_CODE	Lkkkkkk/rccrcr;
    //   218: astore_0
    //   219: aload_0
    //   220: areturn
    //   221: goto -141 -> 80
    //   224: aload_0
    //   225: areturn
    //   226: aload_1
    //   227: astore_0
    //   228: iconst_1
    //   229: tableswitch	default:+23->252, 0:+-3->226, 1:+-5->224
    //   252: aload_1
    //   253: astore_0
    //   254: iconst_0
    //   255: tableswitch	default:+21->276, 0:+-31->224, 1:+-29->226
    //   276: goto -24 -> 252
    // Local variable table:
    //   start	length	slot	name	signature
    //   0	279	0	paramRcrccr	rcrccr
    //   149	104	1	localRccrcr	rccrcr
    // Exception table:
    //   from	to	target	type
    //   0	80	114	java/lang/Exception
    //   80	114	114	java/lang/Exception
    //   117	121	114	java/lang/Exception
    //   121	125	114	java/lang/Exception
    //   125	129	114	java/lang/Exception
    //   129	133	114	java/lang/Exception
    //   133	137	114	java/lang/Exception
    //   137	141	114	java/lang/Exception
    //   146	150	143	java/lang/Exception
    //   175	179	143	java/lang/Exception
    //   204	208	143	java/lang/Exception
    //   208	212	143	java/lang/Exception
    //   215	219	143	java/lang/Exception
  }
  
  public static int b043Fпп043Fпп043F043Fпп()
  {
    return 0;
  }
  
  public static int bп043F043Fппп043F043Fпп()
  {
    return 2;
  }
  
  public static rccrcr bп043Fп043Fпп043F043Fпп(cccrcc paramCccrcc)
  {
    paramCccrcc = paramCccrcc.bжж04360436жжжж04360436();
    rccrcr localRccrcr;
    switch (rccrcr.1.b041CММ041CМ041C041CММ[paramCccrcc.ordinal()])
    {
    default: 
      throw new IllegalArgumentException(gguuuu.bккккк043Aкк043A043A("\024\f\b\n\n\021\0077\013\017\005xL1", 'p', '\003') + paramCccrcc);
    case 6: 
    case 7: 
      paramCccrcc = EXISTING_ISA_ACCOUNT;
    case 11: 
    case 12: 
      do
      {
        return paramCccrcc;
        localRccrcr = NO_ROUTING_CODE;
        paramCccrcc = localRccrcr;
      } while ((b043F043F043Fппп043F043Fпп() + bппп043Fпп043F043Fпп()) * b043F043F043Fппп043F043Fпп() % bп043F043Fппп043F043Fпп() == b043Fпп043Fпп043F043Fпп());
      return localRccrcr;
    case 1: 
      return EXISTING_CURRENT_ACCOUNT;
    case 8: 
      localRccrcr = EXISTING_CREDIT_CARD_ACCOUNT;
      try
      {
        throw new NullPointerException();
      }
      catch (Exception paramCccrcc)
      {
        return localRccrcr;
      }
    case 9: 
    case 10: 
      localRccrcr = EXISTING_LOAN_ACCOUNT;
      paramCccrcc = localRccrcr;
      switch (1)
      {
      }
      for (;;)
      {
        paramCccrcc = localRccrcr;
        switch (0)
        {
        }
      }
    }
    return EXISTING_SAVINGS_ACCOUNT;
  }
  
  public static rccrcr bпп043F043Fпп043F043Fпп(String paramString)
  {
    return (rccrcr)Enum.valueOf(rccrcr.class, paramString);
  }
  
  public static int bппп043Fпп043F043Fпп()
  {
    return 1;
  }
  
  @ooiiio("Trivial")
  public String toString()
  {
    try
    {
      int i = b043F043F043Fппп043F043Fпп();
      int j = bппп043Fпп043F043Fпп();
      int k = b043F043F043Fппп043F043Fпп();
      int m = bп043F043Fппп043F043Fпп();
      int n = b043Fпп043Fпп043F043Fпп();
      if (((i + j) * k % m != n) && ((b043F043F043Fппп043F043Fпп() + bппп043Fпп043F043Fпп()) * b043F043F043Fппп043F043Fпп() % bп043F043Fппп043F043Fпп() != b043Fпп043Fпп043F043Fпп())) {}
      String str = this.mRoutingCode;
      switch (0)
      {
      case 1: 
      default: 
        for (;;)
        {
          switch (0)
          {
          }
        }
      }
      return str;
    }
    catch (Exception localException)
    {
      throw localException;
    }
  }
}
