package kkkkkk;

import com.fasterxml.jackson.annotation.JsonEnumDefaultValue;

public enum rcrccr
{
  private final String mValue;
  
  static
  {
    ARRANGEMENTS = new rcrccr(gguuuu.bккккк043Aкк043A043A("\b\030\027\005\021\t\006\r\004\f\021\017", '9', '\005'), 1, gguuuu.bккккк043Aкк043A043A("i\032\031\007\023\013\b\017\006\016\023\021", 'W', '\005'));
    rcrccr localRcrccr1 = new rcrccr(gguuuu.bккккк043Aкк043A043A("wzywml~pp\rt\002q\007v", '£', '\000'), 2, gguuuu.bккккк043Aкк043A043A("6YXVLK]OO\f3`PeU", '°', '\004'));
    switch (0)
    {
    case 1: 
    default: 
      for (;;)
      {
        switch (0)
        {
        }
      }
    }
    SUSPECTED_FRAUD = localRcrccr1;
    LOST_OR_STOLEN_CARDS = new rcrccr(gguuuu.bк043Aккк043Aкк043A043A("\024\026\031\031#\022\024 \023\023\r\t\001\t\031{x\ty\b", '\023', 'Ù', '\000'), 3, gguuuu.bккккк043Aкк043A043A("[\005\0073\004\b6j\r\t\007\001\013=a\001\023\006\026", '', '\000'));
    EMERGENCY_CASH_ABROAD = new rcrccr(gguuuu.bк043Aккк043Aкк043A043A("kriuifnbw|_\\mawXXgcTV", '', 'R', '\002'), 4, gguuuu.bк043Aккк043Aкк043A043A("Cjama^fZo\0257TeY\0200P_[LN", 'º', '9', '\000'));
    MEDICAL_ASSISTANCE_ABROAD = new rcrccr(gguuuu.bккккк043Aкк043A043A("OHHNIHThK^_VacQ_UXsVXigZ^", '\001', '\004'), 5, gguuuu.bккккк043Aкк043A043A("]vv|wv\0037Y\r\016\005\020\022\016\004\007Bd\007\030\026\t\r", '\b', '\004'));
    localRcrccr1 = new rcrccr(gguuuu.bккккк043Aкк043A043A("im`\\htVT`\\Y]Ul]`O[a", 'e', '\005'), 6, gguuuu.bк043Aккк043Aкк043A043A("Hl_[g\0245S_[X\\T\f<_NZ`", '\031', 'm', '\002'));
    switch (0)
    {
    case 1: 
    default: 
      for (;;)
      {
        switch (0)
        {
        }
      }
    }
    OTHER_BANKING_QUERY = localRcrccr1;
    INTERNET_BANKING = new rcrccr(gguuuu.bккккк043Aкк043A043A("\001\005\ny\006\001v\005\017pnzvswo", '$', '\003'), 7, gguuuu.bк043Aккк043Aкк043A043A("2X_Q_\\Td\0214Tb`_e_", '¤', '<', '\001'));
    NEW_CURRENT_ACCOUNT = new rcrccr(gguuuu.bккккк043Aкк043A043A("dZkrUfbaS[`jKLKV[SX", '¢', '\002'), 8, gguuuu.bк043Aккк043Aкк043A043A("`v\b/Q\003~}ow|'Ghgrwot", '', 'æ', '\002'));
    NEW_SAVINGS_ACCOUNT = new rcrccr(gguuuu.bккккк043Aкк043A043A("'\0372;0\0375)/)6C&)*7>8?", ',', '\004'), 9, gguuuu.bк043Aккк043Aкк043A043A("F\\m\025GThZ^Va\r-NMX]UZ", '', '\b', '\000'));
    NEW_ISA_ACCOUNT = new rcrccr(gguuuu.bккккк043Aкк043A043A("zp\002\tqzg\005efepumr", 'Ò', '\005'), 10, gguuuu.bк043Aккк043Aкк043A043A("f~\022;e\021?a\005\006\023\032\024\033", '9', 'Ý', '\003'));
    localRcrccr1 = new rcrccr(gguuuu.bккккк043Aкк043A043A("&\034-4\027%\027\025\031#-\020\r\035\016", 'b', '\002'), 11, gguuuu.bккккк043Aкк043A043A("\004\034/X|-!!'3_\004#5(", '´', '\000'));
    if ((b043F043F043Fп043F043Fп043Fпп() + bппп043F043F043Fп043Fпп()) * b043F043F043Fп043F043Fп043Fпп() % bп043F043Fп043F043Fп043Fпп() != b043Fп043Fп043F043Fп043Fпп()) {}
    NEW_CREDIT_CARD = localRcrccr1;
    NEW_LOAN = new rcrccr(gguuuu.bккккк043Aкк043A043A("[Sfo]aTb", 'F', '\004'), 12, gguuuu.bккккк043Aкк043A043A("1GX+M>J", '', '\005'));
    NEW_MORTGAGE = new rcrccr(gguuuu.bк043Aккк043Aкк043A043A("|r\004\013wxz{mfkh", 'Z', '\t', '\000'), 13, gguuuu.bк043Aккк043Aкк043A043A("~\027*S\002%), \033\"!", 'A', '\021', '\001'));
    PERSONAL_ACCOUNTS = new rcrccr(gguuuu.bккккк043Aкк043A043A("8,8831#-? ! +0(-+", '', '\002'), 14, gguuuu.bк043Aккк043Aкк043A043A("Mcqsppdp%Gjkxy\001\001", 'ô', '\007', '\003'));
    CHANGE_OF_ADDRESS = new rcrccr(gguuuu.bк043Aккк043Aкк043A043A("$*$2,+F7/I,01@4CD", 'Ë', '', '\003'), 15, gguuuu.bккккк043Aкк043A043A("c\n\004\022\f\013F\027\017Ik\020\021 \024#$", '5', '\001'));
    localRcrccr1 = UNKNOWN;
    rcrccr localRcrccr2 = ARRANGEMENTS;
    rcrccr localRcrccr3 = SUSPECTED_FRAUD;
    rcrccr localRcrccr4 = LOST_OR_STOLEN_CARDS;
    rcrccr localRcrccr5 = EMERGENCY_CASH_ABROAD;
    rcrccr localRcrccr6 = MEDICAL_ASSISTANCE_ABROAD;
    rcrccr localRcrccr7 = OTHER_BANKING_QUERY;
    rcrccr localRcrccr8 = INTERNET_BANKING;
    rcrccr localRcrccr9 = NEW_CURRENT_ACCOUNT;
    rcrccr localRcrccr10 = NEW_SAVINGS_ACCOUNT;
    rcrccr localRcrccr11 = NEW_ISA_ACCOUNT;
    rcrccr localRcrccr12 = NEW_CREDIT_CARD;
    rcrccr localRcrccr13 = NEW_LOAN;
    rcrccr localRcrccr14 = NEW_MORTGAGE;
    rcrccr localRcrccr15 = PERSONAL_ACCOUNTS;
    if ((b043F043F043Fп043F043Fп043Fпп() + bппп043F043F043Fп043Fпп()) * b043F043F043Fп043F043Fп043Fпп() % bп043F043Fп043F043Fп043Fпп() != b043Fп043Fп043F043Fп043Fпп()) {}
    $VALUES = new rcrccr[] { localRcrccr1, localRcrccr2, localRcrccr3, localRcrccr4, localRcrccr5, localRcrccr6, localRcrccr7, localRcrccr8, localRcrccr9, localRcrccr10, localRcrccr11, localRcrccr12, localRcrccr13, localRcrccr14, localRcrccr15, CHANGE_OF_ADDRESS };
  }
  
  private rcrccr(String paramString)
  {
    this.mValue = paramString;
  }
  
  public static int b043F043F043Fп043F043Fп043Fпп()
  {
    return 33;
  }
  
  public static int b043Fп043Fп043F043Fп043Fпп()
  {
    return 0;
  }
  
  public static int bп043F043Fп043F043Fп043Fпп()
  {
    return 2;
  }
  
  /* Error */
  public static rcrccr bп043Fп043F043F043Fп043Fпп(String paramString)
  {
    // Byte code:
    //   0: invokestatic 117	kkkkkk/rcrccr:b043F043F043Fп043F043Fп043Fпп	()I
    //   3: invokestatic 120	kkkkkk/rcrccr:bппп043F043F043Fп043Fпп	()I
    //   6: iadd
    //   7: invokestatic 117	kkkkkk/rcrccr:b043F043F043Fп043F043Fп043Fпп	()I
    //   10: imul
    //   11: invokestatic 123	kkkkkk/rcrccr:bп043F043Fп043F043Fп043Fпп	()I
    //   14: irem
    //   15: invokestatic 126	kkkkkk/rcrccr:b043Fп043Fп043F043Fп043Fпп	()I
    //   18: if_icmpeq +3 -> 21
    //   21: ldc 2
    //   23: aload_0
    //   24: invokestatic 170	java/lang/Enum:valueOf	(Ljava/lang/Class;Ljava/lang/String;)Ljava/lang/Enum;
    //   27: astore_0
    //   28: aload_0
    //   29: checkcast 2	kkkkkk/rcrccr
    //   32: astore_0
    //   33: aload_0
    //   34: areturn
    //   35: astore_0
    //   36: aload_0
    //   37: athrow
    //   38: astore_0
    //   39: aload_0
    //   40: athrow
    // Local variable table:
    //   start	length	slot	name	signature
    //   0	41	0	paramString	String
    // Exception table:
    //   from	to	target	type
    //   21	28	35	java/lang/Exception
    //   28	33	38	java/lang/Exception
  }
  
  public static int bппп043F043F043Fп043Fпп()
  {
    return 1;
  }
  
  @ooiiio("Mapping code")
  public String b043Fпп043F043F043Fп043Fпп()
  {
    Object localObject;
    int i;
    switch (rcrccr.1.b041C041C041C041C041CМ041CММ[ordinal()])
    {
    default: 
      throw new IllegalArgumentException(gguuuu.bккккк043Aкк043A043A("ga_cenf\031ntlb8\037", '÷', '\004') + this);
    case 1: 
      localObject = gguuuu.bккккк043Aкк043A043A("L}~r|\0040ruv\004\013\005\f8~\t\r\022\007\021\031@\022\004\013\n", '\003', '\001');
      return localObject;
    case 4: 
      return gguuuu.bккккк043Aкк043A043A("l\035\021\021\027#O\024\023%\030T\033%).#-5\\. '&", 'T', '\004');
    case 5: 
      return gguuuu.bккккк043Aкк043A043A("Swjx~,r|\001\006z\005\r4\006w~}", '\007', '\000');
      return gguuuu.bккккк043Aкк043A043A("z\b\034\016\022\n\025@\005\r\017\022\005\r\0238\bw|y", 'r', '\002');
    case 2: 
      switch (0)
      {
      }
      for (;;)
      {
        switch (0)
        {
        }
      }
    case 9: 
    case 10: 
    case 11: 
    case 12: 
    case 13: 
    case 14: 
      i = b043F043F043Fп043F043Fп043Fпп();
      switch (i * (bппп043F043F043Fп043Fпп() + i) % bп043F043Fп043F043Fп043Fпп())
      {
      }
      return String.format(gguuuu.bккккк043Aкк043A043A("yGrB274", 'ª', '\005'), new Object[] { this.mValue });
    case 7: 
      return gguuuu.bк043Aккк043Aкк043A043A("\016$2411%1e(+,9@:Am4>BG<FNuG9@?", 'i', 'Ò', '\003');
    case 6: 
      return gguuuu.bк043Aккк043Aкк043A043A("9Z\\]OHMJ\004HPRUHPV{K;@=", 'u', 'a', '\000');
    case 15: 
      return null;
    case 8: 
      String str = gguuuu.bккккк043Aкк043A043A("Rncaug#}t{y(jno~r\002\0030\002szy", 'û', '\000');
      i = b043F043F043Fп043F043Fп043Fпп();
      localObject = str;
      switch (i * (bппп043F043F043Fп043Fпп() + i) % bп043F043Fп043F043Fп043Fпп())
      {
      }
      return str;
    }
    return gguuuu.bккккк043Aкк043A043A("n\f\035\021G\020\031\006C\b\020\022\025\b\020\026;\013z|", '©', '\003');
  }
  
  /* Error */
  public String toString()
  {
    // Byte code:
    //   0: invokestatic 117	kkkkkk/rcrccr:b043F043F043Fп043F043Fп043Fпп	()I
    //   3: istore_1
    //   4: invokestatic 120	kkkkkk/rcrccr:bппп043F043F043Fп043Fпп	()I
    //   7: istore_2
    //   8: invokestatic 117	kkkkkk/rcrccr:b043F043F043Fп043F043Fп043Fпп	()I
    //   11: istore_3
    //   12: invokestatic 123	kkkkkk/rcrccr:bп043F043Fп043F043Fп043Fпп	()I
    //   15: istore 4
    //   17: invokestatic 126	kkkkkk/rcrccr:b043Fп043Fп043F043Fп043Fпп	()I
    //   20: istore 5
    //   22: iload_1
    //   23: iload_2
    //   24: iadd
    //   25: iload_3
    //   26: imul
    //   27: iload 4
    //   29: irem
    //   30: iload 5
    //   32: if_icmpeq +3 -> 35
    //   35: aload_0
    //   36: getfield 160	kkkkkk/rcrccr:mValue	Ljava/lang/String;
    //   39: astore 6
    //   41: invokestatic 117	kkkkkk/rcrccr:b043F043F043Fп043F043Fп043Fпп	()I
    //   44: invokestatic 120	kkkkkk/rcrccr:bппп043F043F043Fп043Fпп	()I
    //   47: iadd
    //   48: invokestatic 117	kkkkkk/rcrccr:b043F043F043Fп043F043Fп043Fпп	()I
    //   51: imul
    //   52: invokestatic 123	kkkkkk/rcrccr:bп043F043Fп043F043Fп043Fпп	()I
    //   55: irem
    //   56: invokestatic 126	kkkkkk/rcrccr:b043Fп043Fп043F043Fп043Fпп	()I
    //   59: if_icmpeq +3 -> 62
    //   62: aload 6
    //   64: areturn
    //   65: astore 6
    //   67: aload 6
    //   69: athrow
    //   70: astore 6
    //   72: aload 6
    //   74: athrow
    //   75: astore 6
    //   77: aload 6
    //   79: athrow
    // Local variable table:
    //   start	length	slot	name	signature
    //   0	80	0	this	rcrccr
    //   3	22	1	i	int
    //   7	18	2	j	int
    //   11	16	3	k	int
    //   15	15	4	m	int
    //   20	13	5	n	int
    //   39	24	6	str	String
    //   65	3	6	localException1	Exception
    //   70	3	6	localException2	Exception
    //   75	3	6	localException3	Exception
    // Exception table:
    //   from	to	target	type
    //   35	41	65	java/lang/Exception
    //   67	70	70	java/lang/Exception
    //   0	22	75	java/lang/Exception
  }
}
