package kkkkkk;

import javax.inject.Inject;

public class rgrggg
{
  public static int b04280428042804280428Ш0428Ш0428 = 0;
  public static int b0428Ш042804280428Ш0428Ш0428 = 1;
  private static final String b0428ШШ04280428Ш0428Ш0428 = "Iiicvls";
  public static int bШ0428042804280428Ш0428Ш0428 = 2;
  private static final String bШ0428Ш04280428Ш0428Ш0428 = "#D>=;=>26.e2%7'3) *";
  public static int bШШ042804280428Ш0428Ш0428 = 30;
  private final nuuuuu b04280428Ш04280428Ш0428Ш0428;
  
  static
  {
    throw new Runtime("d2j fail translate: java.lang.IndexOutOfBoundsException: fromIndex < 0: -1\n\tat java.util.BitSet.nextSetBit(BitSet.java:712)\n\tat com.googlecode.dex2jar.ir.ts.array.FillArrayTransformer.makeSureAllElementAreAssigned(FillArrayTransformer.java:505)\n\tat com.googlecode.dex2jar.ir.ts.array.FillArrayTransformer.transformReportChanged(FillArrayTransformer.java:123)\n\tat com.googlecode.dex2jar.ir.ts.StatedTransformer.transform(StatedTransformer.java:10)\n\tat com.googlecode.d2j.dex.Dex2jar$2.optimize(Dex2jar.java:149)\n\tat com.googlecode.d2j.dex.Dex2Asm.convertCode(Dex2Asm.java:414)\n\tat com.googlecode.d2j.dex.ExDex2Asm.convertCode(ExDex2Asm.java:42)\n\tat com.googlecode.d2j.dex.Dex2jar$2.convertCode(Dex2jar.java:128)\n\tat com.googlecode.d2j.dex.Dex2Asm.convertMethod(Dex2Asm.java:509)\n\tat com.googlecode.d2j.dex.Dex2Asm.convertClass(Dex2Asm.java:406)\n\tat com.googlecode.d2j.dex.Dex2Asm.convertDex(Dex2Asm.java:422)\n\tat com.googlecode.d2j.dex.Dex2jar.doTranslate(Dex2jar.java:172)\n\tat com.googlecode.d2j.dex.Dex2jar.to(Dex2jar.java:272)\n\tat com.googlecode.dex2jar.tools.Dex2jarCmd.doCommandLine(Dex2jarCmd.java:108)\n\tat com.googlecode.dex2jar.tools.BaseCmd.doMain(BaseCmd.java:288)\n\tat com.googlecode.dex2jar.tools.Dex2jarCmd.main(Dex2jarCmd.java:32)\n");
  }
  
  @Inject
  public rgrggg(nuuuuu paramNuuuuu)
  {
    this.b04280428Ш04280428Ш0428Ш0428 = paramNuuuuu;
  }
  
  public static int b0418041804180418И041804180418ИИ()
  {
    return 1;
  }
  
  public static int b0418И04180418И041804180418ИИ()
  {
    return 57;
  }
  
  public static int bИ041804180418И041804180418ИИ()
  {
    return 2;
  }
  
  public static int bИИ04180418И041804180418ИИ()
  {
    return 0;
  }
  
  private String bИИИИ0418041804180418ИИ(CharSequence paramCharSequence, String paramString)
  {
    int i = bШШ042804280428Ш0428Ш0428;
    switch (i * (b0428Ш042804280428Ш0428Ш0428 + i) % bШ0428042804280428Ш0428Ш0428)
    {
    default: 
      bШШ042804280428Ш0428Ш0428 = b0418И04180418И041804180418ИИ();
      b0428Ш042804280428Ш0428Ш0428 = b0418И04180418И041804180418ИИ();
    }
    paramCharSequence = String.format(gguuuu.bккккк043Aкк043A043A("xl\003\\S#_V&", '©', '\000'), new Object[] { paramString, paramCharSequence });
    if ((bШШ042804280428Ш0428Ш0428 + b0428Ш042804280428Ш0428Ш0428) * bШШ042804280428Ш0428Ш0428 % bИ041804180418И041804180418ИИ() != b04280428042804280428Ш0428Ш0428)
    {
      bШШ042804280428Ш0428Ш0428 = 77;
      b04280428042804280428Ш0428Ш0428 = b0418И04180418И041804180418ИИ();
    }
    switch (0)
    {
    case 1: 
    default: 
      for (;;)
      {
        switch (0)
        {
        }
      }
    }
    return paramCharSequence;
  }
  
  /* Error */
  public void b04180418041804180418041804180418ИИ(CharSequence paramCharSequence, String paramString)
  {
    // Byte code:
    //   0: aload_0
    //   1: getfield 41	kkkkkk/rgrggg:b04280428Ш04280428Ш0428Ш0428	Lkkkkkk/nuuuuu;
    //   4: astore 7
    //   6: getstatic 85	kkkkkk/nnuunu:LONG_PRESS_TO_NAVIGATE_TO_NEW_SCREEN	Lkkkkkk/nnuunu;
    //   9: astore 8
    //   11: getstatic 91	kkkkkk/nnnuuu$nuunuu:LONG_PRESS	Lkkkkkk/nnnuuu$nuunuu;
    //   14: invokevirtual 95	kkkkkk/nnnuuu$nuunuu:toString	()Ljava/lang/String;
    //   17: astore 9
    //   19: getstatic 101	kkkkkk/unnuuu:DEFER	Lkkkkkk/unnuuu;
    //   22: invokevirtual 102	kkkkkk/unnuuu:toString	()Ljava/lang/String;
    //   25: astore 10
    //   27: getstatic 108	kkkkkk/unuunu:LINK_VALUE	Lkkkkkk/unuunu;
    //   30: astore 11
    //   32: aload_0
    //   33: aload_1
    //   34: aload_2
    //   35: invokespecial 110	kkkkkk/rgrggg:bИИИИ0418041804180418ИИ	(Ljava/lang/CharSequence;Ljava/lang/String;)Ljava/lang/String;
    //   38: astore_1
    //   39: getstatic 51	kkkkkk/rgrggg:bШШ042804280428Ш0428Ш0428	I
    //   42: istore_3
    //   43: getstatic 53	kkkkkk/rgrggg:b0428Ш042804280428Ш0428Ш0428	I
    //   46: istore 4
    //   48: getstatic 51	kkkkkk/rgrggg:bШШ042804280428Ш0428Ш0428	I
    //   51: istore 5
    //   53: getstatic 55	kkkkkk/rgrggg:bШ0428042804280428Ш0428Ш0428	I
    //   56: istore 6
    //   58: iload_3
    //   59: iload 4
    //   61: iadd
    //   62: iload 5
    //   64: imul
    //   65: iload 6
    //   67: irem
    //   68: getstatic 75	kkkkkk/rgrggg:b04280428042804280428Ш0428Ш0428	I
    //   71: if_icmpeq +60 -> 131
    //   74: invokestatic 57	kkkkkk/rgrggg:b0418И04180418И041804180418ИИ	()I
    //   77: putstatic 51	kkkkkk/rgrggg:bШШ042804280428Ш0428Ш0428	I
    //   80: bipush 6
    //   82: putstatic 75	kkkkkk/rgrggg:b04280428042804280428Ш0428Ш0428	I
    //   85: getstatic 51	kkkkkk/rgrggg:bШШ042804280428Ш0428Ш0428	I
    //   88: istore_3
    //   89: iload_3
    //   90: getstatic 53	kkkkkk/rgrggg:b0428Ш042804280428Ш0428Ш0428	I
    //   93: iload_3
    //   94: iadd
    //   95: imul
    //   96: getstatic 55	kkkkkk/rgrggg:bШ0428042804280428Ш0428Ш0428	I
    //   99: irem
    //   100: tableswitch	default:+20->120, 0:+31->131
    //   120: bipush 14
    //   122: putstatic 51	kkkkkk/rgrggg:bШШ042804280428Ш0428Ш0428	I
    //   125: invokestatic 57	kkkkkk/rgrggg:b0418И04180418И041804180418ИИ	()I
    //   128: putstatic 75	kkkkkk/rgrggg:b04280428042804280428Ш0428Ш0428	I
    //   131: aload 7
    //   133: aload 8
    //   135: aload 9
    //   137: aload 10
    //   139: iconst_1
    //   140: anewarray 112	kkkkkk/nuuuuu$unuuuu
    //   143: dup
    //   144: iconst_0
    //   145: aload 11
    //   147: aload_1
    //   148: invokestatic 116	kkkkkk/nuuuuu$unuuuu:b043F043F043Fп043F043Fпп043Fп	(Lkkkkkk/unuunu;Ljava/lang/String;)Lkkkkkk/nuuuuu$unuuuu;
    //   151: aastore
    //   152: invokevirtual 122	kkkkkk/nuuuuu:b043F043Fпппп043Fп043Fп	(Lkkkkkk/nnuunu;Ljava/lang/String;Ljava/lang/String;[Lkkkkkk/nuuuuu$unuuuu;)V
    //   155: return
    //   156: astore_1
    //   157: aload_1
    //   158: athrow
    //   159: astore_1
    //   160: aload_1
    //   161: athrow
    //   162: astore_1
    //   163: aload_1
    //   164: athrow
    //   165: astore_1
    //   166: aload_1
    //   167: athrow
    // Local variable table:
    //   start	length	slot	name	signature
    //   0	168	0	this	rgrggg
    //   0	168	1	paramCharSequence	CharSequence
    //   0	168	2	paramString	String
    //   42	54	3	i	int
    //   46	16	4	j	int
    //   51	14	5	k	int
    //   56	12	6	m	int
    //   4	128	7	localNuuuuu	nuuuuu
    //   9	125	8	localNnuunu	nnuunu
    //   17	119	9	str1	String
    //   25	113	10	str2	String
    //   30	116	11	localUnuunu	unuunu
    // Exception table:
    //   from	to	target	type
    //   0	27	156	java/lang/Exception
    //   131	155	156	java/lang/Exception
    //   58	85	159	java/lang/Exception
    //   157	159	159	java/lang/Exception
    //   163	165	159	java/lang/Exception
    //   27	39	162	java/lang/Exception
    //   39	58	165	java/lang/Exception
  }
  
  public void b041804180418И0418041804180418ИИ(String paramString1, String paramString2)
  {
    this.b04280428Ш04280428Ш0428Ш0428.b043F043Fпппп043Fп043Fп(nnuunu.TAP_BUTTON_TO_CANCEL_JOURNEY, nnnuuu.nuunuu.TAP.toString(), unnuuu.CONFIRM.toString(), new nuuuuu.unuuuu[] { nuuuuu.unuuuu.b043F043F043Fп043F043Fпп043Fп(unuunu.LINK_VALUE, bИИИИ0418041804180418ИИ(paramString1, paramString2)) });
  }
  
  public void b04180418И04180418041804180418ИИ(CharSequence paramCharSequence)
  {
    switch (0)
    {
    case 1: 
    default: 
      for (;;)
      {
        switch (0)
        {
        }
      }
    }
    if ((bШШ042804280428Ш0428Ш0428 + b0428Ш042804280428Ш0428Ш0428) * bШШ042804280428Ш0428Ш0428 % bШ0428042804280428Ш0428Ш0428 != b04280428042804280428Ш0428Ш0428)
    {
      bШШ042804280428Ш0428Ш0428 = b0418И04180418И041804180418ИИ();
      b04280428042804280428Ш0428Ш0428 = 74;
    }
    switch (0)
    {
    case 1: 
    default: 
      for (;;)
      {
        switch (0)
        {
        }
      }
    }
    if ((bШШ042804280428Ш0428Ш0428 + b0428Ш042804280428Ш0428Ш0428) * bШШ042804280428Ш0428Ш0428 % bШ0428042804280428Ш0428Ш0428 != bИИ04180418И041804180418ИИ())
    {
      bШШ042804280428Ш0428Ш0428 = 30;
      b04280428042804280428Ш0428Ш0428 = b0418И04180418И041804180418ИИ();
    }
    bИИ041804180418041804180418ИИ(paramCharSequence, gguuuu.bккккк043Aкк043A043A("+MOK`Xa", 'f', '\000'));
  }
  
  /* Error */
  public void b04180418ИИ0418041804180418ИИ(String paramString1, String paramString2)
  {
    // Byte code:
    //   0: aload_0
    //   1: getfield 41	kkkkkk/rgrggg:b04280428Ш04280428Ш0428Ш0428	Lkkkkkk/nuuuuu;
    //   4: astore 8
    //   6: getstatic 146	kkkkkk/nnuunu:TAP_TO_INVOKE_BROWSER_INFORMATION_PAGE	Lkkkkkk/nnuunu;
    //   9: astore 9
    //   11: getstatic 149	kkkkkk/nnnuuu$nuunuu:EXTERNAL_LINK	Lkkkkkk/nnnuuu$nuunuu;
    //   14: invokevirtual 95	kkkkkk/nnnuuu$nuunuu:toString	()Ljava/lang/String;
    //   17: astore 10
    //   19: getstatic 152	kkkkkk/unnuuu:CORE	Lkkkkkk/unnuuu;
    //   22: invokevirtual 102	kkkkkk/unnuuu:toString	()Ljava/lang/String;
    //   25: astore 11
    //   27: getstatic 51	kkkkkk/rgrggg:bШШ042804280428Ш0428Ш0428	I
    //   30: istore_3
    //   31: getstatic 53	kkkkkk/rgrggg:b0428Ш042804280428Ш0428Ш0428	I
    //   34: istore 4
    //   36: getstatic 51	kkkkkk/rgrggg:bШШ042804280428Ш0428Ш0428	I
    //   39: istore 5
    //   41: getstatic 55	kkkkkk/rgrggg:bШ0428042804280428Ш0428Ш0428	I
    //   44: istore 6
    //   46: getstatic 75	kkkkkk/rgrggg:b04280428042804280428Ш0428Ш0428	I
    //   49: istore 7
    //   51: iload_3
    //   52: iload 4
    //   54: iadd
    //   55: iload 5
    //   57: imul
    //   58: iload 6
    //   60: irem
    //   61: iload 7
    //   63: if_icmpeq +49 -> 112
    //   66: invokestatic 57	kkkkkk/rgrggg:b0418И04180418И041804180418ИИ	()I
    //   69: istore_3
    //   70: getstatic 51	kkkkkk/rgrggg:bШШ042804280428Ш0428Ш0428	I
    //   73: getstatic 53	kkkkkk/rgrggg:b0428Ш042804280428Ш0428Ш0428	I
    //   76: iadd
    //   77: getstatic 51	kkkkkk/rgrggg:bШШ042804280428Ш0428Ш0428	I
    //   80: imul
    //   81: getstatic 55	kkkkkk/rgrggg:bШ0428042804280428Ш0428Ш0428	I
    //   84: irem
    //   85: getstatic 75	kkkkkk/rgrggg:b04280428042804280428Ш0428Ш0428	I
    //   88: if_icmpeq +14 -> 102
    //   91: bipush 37
    //   93: putstatic 51	kkkkkk/rgrggg:bШШ042804280428Ш0428Ш0428	I
    //   96: invokestatic 57	kkkkkk/rgrggg:b0418И04180418И041804180418ИИ	()I
    //   99: putstatic 75	kkkkkk/rgrggg:b04280428042804280428Ш0428Ш0428	I
    //   102: iload_3
    //   103: putstatic 51	kkkkkk/rgrggg:bШШ042804280428Ш0428Ш0428	I
    //   106: invokestatic 57	kkkkkk/rgrggg:b0418И04180418И041804180418ИИ	()I
    //   109: putstatic 75	kkkkkk/rgrggg:b04280428042804280428Ш0428Ш0428	I
    //   112: getstatic 155	kkkkkk/unuunu:EVENT_ACTION	Lkkkkkk/unuunu;
    //   115: ldc -99
    //   117: sipush 155
    //   120: iconst_3
    //   121: invokestatic 65	kkkkkk/gguuuu:bккккк043Aкк043A043A	(Ljava/lang/String;CC)Ljava/lang/String;
    //   124: invokestatic 116	kkkkkk/nuuuuu$unuuuu:b043F043F043Fп043F043Fпп043Fп	(Lkkkkkk/unuunu;Ljava/lang/String;)Lkkkkkk/nuuuuu$unuuuu;
    //   127: astore 12
    //   129: getstatic 160	kkkkkk/unuunu:EVENT_NARRATIVE	Lkkkkkk/unuunu;
    //   132: aload_1
    //   133: invokestatic 116	kkkkkk/nuuuuu$unuuuu:b043F043F043Fп043F043Fпп043Fп	(Lkkkkkk/unuunu;Ljava/lang/String;)Lkkkkkk/nuuuuu$unuuuu;
    //   136: astore 13
    //   138: iconst_0
    //   139: tableswitch	default:+21->160, 0:+48->187, 1:+-1->138
    //   160: iconst_0
    //   161: tableswitch	default:+23->184, 0:+26->187, 1:+-23->138
    //   184: goto -24 -> 160
    //   187: aload 8
    //   189: aload 9
    //   191: aload 10
    //   193: aload 11
    //   195: iconst_3
    //   196: anewarray 112	kkkkkk/nuuuuu$unuuuu
    //   199: dup
    //   200: iconst_0
    //   201: aload 12
    //   203: aastore
    //   204: dup
    //   205: iconst_1
    //   206: aload 13
    //   208: aastore
    //   209: dup
    //   210: iconst_2
    //   211: getstatic 108	kkkkkk/unuunu:LINK_VALUE	Lkkkkkk/unuunu;
    //   214: aload_0
    //   215: aload_1
    //   216: aload_2
    //   217: invokespecial 110	kkkkkk/rgrggg:bИИИИ0418041804180418ИИ	(Ljava/lang/CharSequence;Ljava/lang/String;)Ljava/lang/String;
    //   220: invokestatic 116	kkkkkk/nuuuuu$unuuuu:b043F043F043Fп043F043Fпп043Fп	(Lkkkkkk/unuunu;Ljava/lang/String;)Lkkkkkk/nuuuuu$unuuuu;
    //   223: aastore
    //   224: invokevirtual 122	kkkkkk/nuuuuu:b043F043Fпппп043Fп043Fп	(Lkkkkkk/nnuunu;Ljava/lang/String;Ljava/lang/String;[Lkkkkkk/nuuuuu$unuuuu;)V
    //   227: return
    //   228: astore_1
    //   229: aload_1
    //   230: athrow
    //   231: astore_1
    //   232: aload_1
    //   233: athrow
    // Local variable table:
    //   start	length	slot	name	signature
    //   0	234	0	this	rgrggg
    //   0	234	1	paramString1	String
    //   0	234	2	paramString2	String
    //   30	73	3	i	int
    //   34	21	4	j	int
    //   39	19	5	k	int
    //   44	17	6	m	int
    //   49	15	7	n	int
    //   4	184	8	localNuuuuu	nuuuuu
    //   9	181	9	localNnuunu	nnuunu
    //   17	175	10	str1	String
    //   25	169	11	str2	String
    //   127	75	12	localUnuuuu1	nuuuuu.unuuuu
    //   136	71	13	localUnuuuu2	nuuuuu.unuuuu
    // Exception table:
    //   from	to	target	type
    //   0	51	228	java/lang/Exception
    //   112	138	228	java/lang/Exception
    //   187	227	228	java/lang/Exception
    //   66	70	231	java/lang/Exception
    //   102	112	231	java/lang/Exception
  }
  
  /* Error */
  @ooiiio
  public void b04180418ИИИИИИ0418И()
  {
    // Byte code:
    //   0: iconst_2
    //   1: istore_1
    //   2: iload_1
    //   3: istore_2
    //   4: iload_2
    //   5: istore_1
    //   6: iconst_0
    //   7: tableswitch	default:+21->28, 0:+48->55, 1:+-5->2
    //   28: iload_2
    //   29: istore_1
    //   30: iconst_0
    //   31: tableswitch	default:+21->52, 0:+24->55, 1:+-29->2
    //   52: goto -24 -> 28
    //   55: iload_2
    //   56: iconst_0
    //   57: idiv
    //   58: istore_1
    //   59: goto -57 -> 2
    //   62: astore_3
    //   63: invokestatic 57	kkkkkk/rgrggg:b0418И04180418И041804180418ИИ	()I
    //   66: putstatic 51	kkkkkk/rgrggg:bШШ042804280428Ш0428Ш0428	I
    //   69: aload_0
    //   70: getfield 41	kkkkkk/rgrggg:b04280428Ш04280428Ш0428Ш0428	Lkkkkkk/nuuuuu;
    //   73: astore 7
    //   75: getstatic 165	kkkkkk/nnuunu:SWIPE_LEFT	Lkkkkkk/nnuunu;
    //   78: astore 6
    //   80: getstatic 51	kkkkkk/rgrggg:bШШ042804280428Ш0428Ш0428	I
    //   83: getstatic 53	kkkkkk/rgrggg:b0428Ш042804280428Ш0428Ш0428	I
    //   86: iadd
    //   87: getstatic 51	kkkkkk/rgrggg:bШШ042804280428Ш0428Ш0428	I
    //   90: imul
    //   91: getstatic 55	kkkkkk/rgrggg:bШ0428042804280428Ш0428Ш0428	I
    //   94: irem
    //   95: invokestatic 137	kkkkkk/rgrggg:bИИ04180418И041804180418ИИ	()I
    //   98: if_icmpeq +13 -> 111
    //   101: bipush 8
    //   103: putstatic 51	kkkkkk/rgrggg:bШШ042804280428Ш0428Ш0428	I
    //   106: bipush 91
    //   108: putstatic 75	kkkkkk/rgrggg:b04280428042804280428Ш0428Ш0428	I
    //   111: getstatic 167	kkkkkk/nnnuuu$nuunuu:SWIPE_LEFT	Lkkkkkk/nnnuuu$nuunuu;
    //   114: invokevirtual 95	kkkkkk/nnnuuu$nuunuu:toString	()Ljava/lang/String;
    //   117: astore_3
    //   118: getstatic 101	kkkkkk/unnuuu:DEFER	Lkkkkkk/unnuuu;
    //   121: invokevirtual 102	kkkkkk/unnuuu:toString	()Ljava/lang/String;
    //   124: astore 5
    //   126: getstatic 108	kkkkkk/unuunu:LINK_VALUE	Lkkkkkk/unuunu;
    //   129: astore 4
    //   131: ldc -87
    //   133: bipush 121
    //   135: bipush 37
    //   137: iconst_1
    //   138: invokestatic 173	kkkkkk/gguuuu:bк043Aккк043Aкк043A043A	(Ljava/lang/String;CCC)Ljava/lang/String;
    //   141: astore 8
    //   143: aload 7
    //   145: aload 6
    //   147: aload_3
    //   148: aload 5
    //   150: iconst_1
    //   151: anewarray 112	kkkkkk/nuuuuu$unuuuu
    //   154: dup
    //   155: iconst_0
    //   156: aload 4
    //   158: aload 8
    //   160: invokestatic 116	kkkkkk/nuuuuu$unuuuu:b043F043F043Fп043F043Fпп043Fп	(Lkkkkkk/unuunu;Ljava/lang/String;)Lkkkkkk/nuuuuu$unuuuu;
    //   163: aastore
    //   164: invokevirtual 122	kkkkkk/nuuuuu:b043F043Fпппп043Fп043Fп	(Lkkkkkk/nnuunu;Ljava/lang/String;Ljava/lang/String;[Lkkkkkk/nuuuuu$unuuuu;)V
    //   167: return
    //   168: astore_3
    //   169: bipush 89
    //   171: putstatic 51	kkkkkk/rgrggg:bШШ042804280428Ш0428Ш0428	I
    //   174: iload_2
    //   175: iconst_0
    //   176: idiv
    //   177: istore_2
    //   178: goto -4 -> 174
    //   181: astore_3
    //   182: bipush 53
    //   184: putstatic 51	kkkkkk/rgrggg:bШШ042804280428Ш0428Ш0428	I
    //   187: new 175	java/lang/NullPointerException
    //   190: dup
    //   191: invokespecial 176	java/lang/NullPointerException:<init>	()V
    //   194: athrow
    //   195: astore_3
    //   196: aload_3
    //   197: athrow
    //   198: astore_3
    //   199: aload_3
    //   200: athrow
    // Local variable table:
    //   start	length	slot	name	signature
    //   0	201	0	this	rgrggg
    //   1	58	1	i	int
    //   3	175	2	j	int
    //   62	1	3	localException1	Exception
    //   117	31	3	str1	String
    //   168	1	3	localException2	Exception
    //   181	1	3	localException3	Exception
    //   195	2	3	localException4	Exception
    //   198	2	3	localException5	Exception
    //   129	28	4	localUnuunu	unuunu
    //   124	25	5	str2	String
    //   78	68	6	localNnuunu	nnuunu
    //   73	71	7	localNuuuuu	nuuuuu
    //   141	18	8	str3	String
    // Exception table:
    //   from	to	target	type
    //   174	178	62	java/lang/Exception
    //   187	195	168	java/lang/Exception
    //   55	59	181	java/lang/Exception
    //   111	143	195	java/lang/Exception
    //   69	80	198	java/lang/Exception
    //   143	167	198	java/lang/Exception
  }
  
  /* Error */
  public void b0418И041804180418041804180418ИИ(CharSequence paramCharSequence, String paramString1, String paramString2)
  {
    // Byte code:
    //   0: iconst_1
    //   1: tableswitch	default:+23->24, 0:+-1->0, 1:+50->51
    //   24: iconst_1
    //   25: tableswitch	default:+23->48, 0:+-25->0, 1:+26->51
    //   48: goto -24 -> 24
    //   51: aload_0
    //   52: getfield 41	kkkkkk/rgrggg:b04280428Ш04280428Ш0428Ш0428	Lkkkkkk/nuuuuu;
    //   55: astore 9
    //   57: getstatic 182	kkkkkk/nnuunu:TAP_BUTTON_TO_NAVIGATE_TO_NEW_SCREEN	Lkkkkkk/nnuunu;
    //   60: astore 10
    //   62: getstatic 130	kkkkkk/nnnuuu$nuunuu:TAP	Lkkkkkk/nnnuuu$nuunuu;
    //   65: invokevirtual 95	kkkkkk/nnnuuu$nuunuu:toString	()Ljava/lang/String;
    //   68: astore 11
    //   70: getstatic 152	kkkkkk/unnuuu:CORE	Lkkkkkk/unnuuu;
    //   73: invokevirtual 102	kkkkkk/unnuuu:toString	()Ljava/lang/String;
    //   76: astore 12
    //   78: getstatic 51	kkkkkk/rgrggg:bШШ042804280428Ш0428Ш0428	I
    //   81: istore 4
    //   83: getstatic 53	kkkkkk/rgrggg:b0428Ш042804280428Ш0428Ш0428	I
    //   86: istore 5
    //   88: getstatic 51	kkkkkk/rgrggg:bШШ042804280428Ш0428Ш0428	I
    //   91: istore 6
    //   93: getstatic 55	kkkkkk/rgrggg:bШ0428042804280428Ш0428Ш0428	I
    //   96: istore 7
    //   98: getstatic 75	kkkkkk/rgrggg:b04280428042804280428Ш0428Ш0428	I
    //   101: istore 8
    //   103: iload 4
    //   105: iload 5
    //   107: iadd
    //   108: iload 6
    //   110: imul
    //   111: iload 7
    //   113: irem
    //   114: iload 8
    //   116: if_icmpeq +62 -> 178
    //   119: getstatic 51	kkkkkk/rgrggg:bШШ042804280428Ш0428Ш0428	I
    //   122: istore 4
    //   124: iload 4
    //   126: getstatic 53	kkkkkk/rgrggg:b0428Ш042804280428Ш0428Ш0428	I
    //   129: iload 4
    //   131: iadd
    //   132: imul
    //   133: getstatic 55	kkkkkk/rgrggg:bШ0428042804280428Ш0428Ш0428	I
    //   136: irem
    //   137: tableswitch	default:+19->156, 0:+31->168
    //   156: invokestatic 57	kkkkkk/rgrggg:b0418И04180418И041804180418ИИ	()I
    //   159: putstatic 51	kkkkkk/rgrggg:bШШ042804280428Ш0428Ш0428	I
    //   162: invokestatic 57	kkkkkk/rgrggg:b0418И04180418И041804180418ИИ	()I
    //   165: putstatic 75	kkkkkk/rgrggg:b04280428042804280428Ш0428Ш0428	I
    //   168: bipush 84
    //   170: putstatic 51	kkkkkk/rgrggg:bШШ042804280428Ш0428Ш0428	I
    //   173: bipush 13
    //   175: putstatic 75	kkkkkk/rgrggg:b04280428042804280428Ш0428Ш0428	I
    //   178: getstatic 155	kkkkkk/unuunu:EVENT_ACTION	Lkkkkkk/unuunu;
    //   181: ldc -72
    //   183: sipush 134
    //   186: bipush 101
    //   188: iconst_1
    //   189: invokestatic 173	kkkkkk/gguuuu:bк043Aккк043Aкк043A043A	(Ljava/lang/String;CCC)Ljava/lang/String;
    //   192: invokestatic 116	kkkkkk/nuuuuu$unuuuu:b043F043F043Fп043F043Fпп043Fп	(Lkkkkkk/unuunu;Ljava/lang/String;)Lkkkkkk/nuuuuu$unuuuu;
    //   195: astore 13
    //   197: getstatic 160	kkkkkk/unuunu:EVENT_NARRATIVE	Lkkkkkk/unuunu;
    //   200: aload_3
    //   201: invokestatic 116	kkkkkk/nuuuuu$unuuuu:b043F043F043Fп043F043Fпп043Fп	(Lkkkkkk/unuunu;Ljava/lang/String;)Lkkkkkk/nuuuuu$unuuuu;
    //   204: astore_3
    //   205: getstatic 108	kkkkkk/unuunu:LINK_VALUE	Lkkkkkk/unuunu;
    //   208: astore 14
    //   210: aload_0
    //   211: aload_1
    //   212: aload_2
    //   213: invokespecial 110	kkkkkk/rgrggg:bИИИИ0418041804180418ИИ	(Ljava/lang/CharSequence;Ljava/lang/String;)Ljava/lang/String;
    //   216: astore_1
    //   217: aload 9
    //   219: aload 10
    //   221: aload 11
    //   223: aload 12
    //   225: iconst_3
    //   226: anewarray 112	kkkkkk/nuuuuu$unuuuu
    //   229: dup
    //   230: iconst_0
    //   231: aload 13
    //   233: aastore
    //   234: dup
    //   235: iconst_1
    //   236: aload_3
    //   237: aastore
    //   238: dup
    //   239: iconst_2
    //   240: aload 14
    //   242: aload_1
    //   243: invokestatic 116	kkkkkk/nuuuuu$unuuuu:b043F043F043Fп043F043Fпп043Fп	(Lkkkkkk/unuunu;Ljava/lang/String;)Lkkkkkk/nuuuuu$unuuuu;
    //   246: aastore
    //   247: invokevirtual 122	kkkkkk/nuuuuu:b043F043Fпппп043Fп043Fп	(Lkkkkkk/nnuunu;Ljava/lang/String;Ljava/lang/String;[Lkkkkkk/nuuuuu$unuuuu;)V
    //   250: return
    //   251: astore_1
    //   252: aload_1
    //   253: athrow
    //   254: astore_1
    //   255: aload_1
    //   256: athrow
    // Local variable table:
    //   start	length	slot	name	signature
    //   0	257	0	this	rgrggg
    //   0	257	1	paramCharSequence	CharSequence
    //   0	257	2	paramString1	String
    //   0	257	3	paramString2	String
    //   81	52	4	i	int
    //   86	22	5	j	int
    //   91	20	6	k	int
    //   96	18	7	m	int
    //   101	16	8	n	int
    //   55	163	9	localNuuuuu	nuuuuu
    //   60	160	10	localNnuunu	nnuunu
    //   68	154	11	str1	String
    //   76	148	12	str2	String
    //   195	37	13	localUnuuuu	nuuuuu.unuuuu
    //   208	33	14	localUnuunu	unuunu
    // Exception table:
    //   from	to	target	type
    //   51	103	251	java/lang/Exception
    //   178	217	251	java/lang/Exception
    //   168	178	254	java/lang/Exception
    //   217	250	254	java/lang/Exception
  }
  
  public void b0418И0418И0418041804180418ИИ(String paramString1, String paramString2)
  {
    nuuuuu localNuuuuu = this.b04280428Ш04280428Ш0428Ш0428;
    nnuunu localNnuunu = nnuunu.TAP_TO_INVOKE_BROWSER_JOURNEY;
    String str1 = nnnuuu.nuunuu.EXTERNAL_LINK.toString();
    String str2 = unnuuu.CONFIRM.toString();
    nuuuuu.unuuuu localUnuuuu1 = nuuuuu.unuuuu.b043F043F043Fп043F043Fпп043Fп(unuunu.EVENT_ACTION, gguuuu.bк043Aккк043Aкк043A043A("~)0 ,'\031+\037+\031R{ %!\034\022%", '\036', 'Ú', '\000'));
    int i = b0418И04180418И041804180418ИИ();
    switch (i * (b0418041804180418И041804180418ИИ() + i) % bШ0428042804280428Ш0428Ш0428)
    {
    default: 
      bШШ042804280428Ш0428Ш0428 = 85;
      b04280428042804280428Ш0428Ш0428 = b0418И04180418И041804180418ИИ();
    }
    nuuuuu.unuuuu localUnuuuu2 = nuuuuu.unuuuu.b043F043F043Fп043F043Fпп043Fп(unuunu.EVENT_NARRATIVE, paramString1);
    switch (1)
    {
    case 0: 
    default: 
      for (;;)
      {
        switch (0)
        {
        case 1: 
        default: 
          for (;;)
          {
            switch (1)
            {
            }
          }
        }
        switch (1)
        {
        }
      }
    }
    unuunu localUnuunu = unuunu.LINK_VALUE;
    if ((b0418И04180418И041804180418ИИ() + b0428Ш042804280428Ш0428Ш0428) * b0418И04180418И041804180418ИИ() % bИ041804180418И041804180418ИИ() != b04280428042804280428Ш0428Ш0428)
    {
      bШШ042804280428Ш0428Ш0428 = 73;
      b04280428042804280428Ш0428Ш0428 = b0418И04180418И041804180418ИИ();
    }
    localNuuuuu.b043F043Fпппп043Fп043Fп(localNnuunu, str1, str2, new nuuuuu.unuuuu[] { localUnuuuu1, localUnuuuu2, nuuuuu.unuuuu.b043F043F043Fп043F043Fпп043Fп(localUnuunu, bИИИИ0418041804180418ИИ(paramString1, paramString2)) });
  }
  
  public void b0418И0418ИИИИИ0418И(String paramString)
  {
    nuuuuu localNuuuuu = this.b04280428Ш04280428Ш0428Ш0428;
    nnuunu localNnuunu = nnuunu.SWIPE_TO_DISMISS;
    String str1 = nnnuuu.nuunuu.SWIPE_DISMISS.toString();
    String str2 = unnuuu.CORE.toString();
    unuunu localUnuunu = unuunu.EVENT_ACTION;
    if ((bШШ042804280428Ш0428Ш0428 + b0428Ш042804280428Ш0428Ш0428) * bШШ042804280428Ш0428Ш0428 % bШ0428042804280428Ш0428Ш0428 != bИИ04180418И041804180418ИИ())
    {
      bШШ042804280428Ш0428Ш0428 = 23;
      b04280428042804280428Ш0428Ш0428 = b0418И04180418И041804180418ИИ();
      int i = bШШ042804280428Ш0428Ш0428;
      switch (i * (b0428Ш042804280428Ш0428Ш0428 + i) % bИ041804180418И041804180418ИИ())
      {
      default: 
        bШШ042804280428Ш0428Ш0428 = 15;
        b04280428042804280428Ш0428Ш0428 = 75;
      }
    }
    localNuuuuu.b043F043Fпппп043Fп043Fп(localNnuunu, str1, str2, new nuuuuu.unuuuu[] { nuuuuu.unuuuu.b043F043F043Fп043F043Fпп043Fп(localUnuunu, gguuuu.bккккк043Aкк043A043A("Fjslgpo", '~', '\003')), nuuuuu.unuuuu.b043F043F043Fп043F043Fпп043Fп(unuunu.EVENT_NARRATIVE, paramString), nuuuuu.unuuuu.b043F043F043Fп043F043Fпп043Fп(unuunu.LINK_VALUE, gguuuu.bк043Aккк043Aкк043A043A("/!5\r0SDJ>\034@IB=FE", '8', 'å', '\002')) });
  }
  
  public void b0418ИИ04180418041804180418ИИ(String paramString)
  {
    nuuuuu localNuuuuu = this.b04280428Ш04280428Ш0428Ш0428;
    nnuunu localNnuunu = nnuunu.INPUT_FIELD_COMPLETE_ENTRY;
    String str1 = nnnuuu.nuunuu.FORM_ENTRY.toString();
    String str2 = unnuuu.SAMPLE.toString();
    Object localObject = unuunu.EVENT_ACTION;
    int i = bШШ042804280428Ш0428Ш0428;
    switch (i * (b0428Ш042804280428Ш0428Ш0428 + i) % bШ0428042804280428Ш0428Ш0428)
    {
    default: 
      bШШ042804280428Ш0428Ш0428 = b0418И04180418И041804180418ИИ();
      b04280428042804280428Ш0428Ш0428 = 87;
    }
    localObject = nuuuuu.unuuuu.b043F043F043Fп043F043Fпп043Fп((unuunu)localObject, gguuuu.bккккк043Aкк043A043A("Vxsyp+_ylhzj", '¤', '\002'));
    i = bШШ042804280428Ш0428Ш0428;
    switch (i * (b0428Ш042804280428Ш0428Ш0428 + i) % bШ0428042804280428Ш0428Ш0428)
    {
    default: 
      bШШ042804280428Ш0428Ш0428 = b0418И04180418И041804180418ИИ();
      b04280428042804280428Ш0428Ш0428 = b0418И04180418И041804180418ИИ();
    }
    switch (1)
    {
    case 0: 
    default: 
      for (;;)
      {
        switch (0)
        {
        }
      }
    }
    localNuuuuu.b043F043Fпппп043Fп043Fп(localNnuunu, str1, str2, new nuuuuu.unuuuu[] { localObject, nuuuuu.unuuuu.b043F043F043Fп043F043Fпп043Fп(unuunu.EVENT_NARRATIVE, paramString) });
  }
  
  @ooiiio
  public void b0418ИИИ0418041804180418ИИ()
  {
    nuuuuu localNuuuuu = this.b04280428Ш04280428Ш0428Ш0428;
    nnuunu localNnuunu = nnuunu.CLICK_YES_ARE_YOU_SURE;
    String str = unnuuu.CORE.toString();
    int i = bШШ042804280428Ш0428Ш0428;
    switch (i * (b0428Ш042804280428Ш0428Ш0428 + i) % bШ0428042804280428Ш0428Ш0428)
    {
    default: 
      bШШ042804280428Ш0428Ш0428 = b0418И04180418И041804180418ИИ();
      b04280428042804280428Ш0428Ш0428 = b0418И04180418И041804180418ИИ();
    }
    localNuuuuu.bпп043Fппп043Fп043Fп(localNnuunu, str, new nuuuuu.unuuuu[0]);
  }
  
  public void b0418ИИИИИИИ0418И(String paramString1, String paramString2, String paramString3)
  {
    int i = bШШ042804280428Ш0428Ш0428;
    switch (i * (b0428Ш042804280428Ш0428Ш0428 + i) % bИ041804180418И041804180418ИИ())
    {
    default: 
      bШШ042804280428Ш0428Ш0428 = b0418И04180418И041804180418ИИ();
      b04280428042804280428Ш0428Ш0428 = 2;
    }
    nuuuuu localNuuuuu = this.b04280428Ш04280428Ш0428Ш0428;
    nnuunu localNnuunu = nnuunu.TAP_LINK_TO_OPEN_OVERLAY;
    String str1 = nnnuuu.nuunuu.OVERLAY.toString();
    if ((b0418И04180418И041804180418ИИ() + b0428Ш042804280428Ш0428Ш0428) * b0418И04180418И041804180418ИИ() % bИ041804180418И041804180418ИИ() != b04280428042804280428Ш0428Ш0428)
    {
      bШШ042804280428Ш0428Ш0428 = 80;
      b04280428042804280428Ш0428Ш0428 = 36;
    }
    String str2 = unnuuu.CORE.toString();
    switch (1)
    {
    case 0: 
    default: 
      for (;;)
      {
        switch (0)
        {
        }
      }
    }
    nuuuuu.unuuuu localUnuuuu = nuuuuu.unuuuu.b043F043F043Fп043F043Fпп043Fп(unuunu.EVENT_ACTION, gguuuu.bккккк043Aкк043A043A("\033<65356*.&]*\035/\037+!\030\"", '¼', '\002'));
    paramString1 = nuuuuu.unuuuu.b043F043F043Fп043F043Fпп043Fп(unuunu.EVENT_NARRATIVE, paramString1);
    unuunu localUnuunu = unuunu.LINK_VALUE;
    switch (0)
    {
    case 1: 
    default: 
      for (;;)
      {
        switch (0)
        {
        }
      }
    }
    localNuuuuu.b043F043Fпппп043Fп043Fп(localNnuunu, str1, str2, new nuuuuu.unuuuu[] { localUnuuuu, paramString1, nuuuuu.unuuuu.b043F043F043Fп043F043Fпп043Fп(localUnuunu, bИИИИ0418041804180418ИИ(paramString2, paramString3)) });
  }
  
  public void bИ0418041804180418041804180418ИИ(CharSequence paramCharSequence)
  {
    String str = gguuuu.bккккк043Aкк043A043A("\r--':07", 'Ú', '\003');
    if ((bШШ042804280428Ш0428Ш0428 + b0418041804180418И041804180418ИИ()) * bШШ042804280428Ш0428Ш0428 % bШ0428042804280428Ш0428Ш0428 != b04280428042804280428Ш0428Ш0428)
    {
      bШШ042804280428Ш0428Ш0428 = 60;
      b04280428042804280428Ш0428Ш0428 = 60;
    }
    switch (0)
    {
    case 1: 
    default: 
      for (;;)
      {
        switch (1)
        {
        }
      }
    }
    if ((bШШ042804280428Ш0428Ш0428 + b0428Ш042804280428Ш0428Ш0428) * bШШ042804280428Ш0428Ш0428 % bШ0428042804280428Ш0428Ш0428 != b04280428042804280428Ш0428Ш0428)
    {
      bШШ042804280428Ш0428Ш0428 = b0418И04180418И041804180418ИИ();
      b04280428042804280428Ш0428Ш0428 = b0418И04180418И041804180418ИИ();
    }
    b04180418041804180418041804180418ИИ(paramCharSequence, str);
  }
  
  public void bИ04180418И0418041804180418ИИ(String paramString)
  {
    int i = bШШ042804280428Ш0428Ш0428;
    int j = b0418041804180418И041804180418ИИ();
    switch (0)
    {
    case 1: 
    default: 
      for (;;)
      {
        switch (0)
        {
        }
      }
    }
    switch (i * (j + i) % bШ0428042804280428Ш0428Ш0428)
    {
    default: 
      if ((bШШ042804280428Ш0428Ш0428 + b0428Ш042804280428Ш0428Ш0428) * bШШ042804280428Ш0428Ш0428 % bШ0428042804280428Ш0428Ш0428 != b04280428042804280428Ш0428Ш0428)
      {
        bШШ042804280428Ш0428Ш0428 = b0418И04180418И041804180418ИИ();
        b04280428042804280428Ш0428Ш0428 = b0418И04180418И041804180418ИИ();
      }
      bШШ042804280428Ш0428Ш0428 = 90;
      b04280428042804280428Ш0428Ш0428 = 20;
    }
    switch (1)
    {
    case 0: 
    default: 
      for (;;)
      {
        switch (0)
        {
        }
      }
    }
    b041804180418И0418041804180418ИИ(paramString, gguuuu.bккккк043Aкк043A043A("0PPJ]SZ", '1', '\002'));
  }
  
  /* Error */
  public void bИ0418И04180418041804180418ИИ(String paramString)
  {
    // Byte code:
    //   0: aload_0
    //   1: getfield 41	kkkkkk/rgrggg:b04280428Ш04280428Ш0428Ш0428	Lkkkkkk/nuuuuu;
    //   4: astore_2
    //   5: getstatic 245	kkkkkk/nnuunu:INPUT_FIELD_FOCUS	Lkkkkkk/nnuunu;
    //   8: astore_3
    //   9: getstatic 210	kkkkkk/nnnuuu$nuunuu:FORM_ENTRY	Lkkkkkk/nnnuuu$nuunuu;
    //   12: invokevirtual 95	kkkkkk/nnnuuu$nuunuu:toString	()Ljava/lang/String;
    //   15: astore 4
    //   17: getstatic 248	kkkkkk/unnuuu:NONE	Lkkkkkk/unnuuu;
    //   20: invokevirtual 102	kkkkkk/unnuuu:toString	()Ljava/lang/String;
    //   23: astore 5
    //   25: getstatic 155	kkkkkk/unuunu:EVENT_ACTION	Lkkkkkk/unuunu;
    //   28: astore 6
    //   30: iconst_1
    //   31: tableswitch	default:+21->52, 0:+-1->30, 1:+48->79
    //   52: iconst_0
    //   53: tableswitch	default:+23->76, 0:+26->79, 1:+-23->30
    //   76: goto -24 -> 52
    //   79: aload 6
    //   81: ldc -6
    //   83: bipush 81
    //   85: iconst_5
    //   86: invokestatic 65	kkkkkk/gguuuu:bккккк043Aкк043A043A	(Ljava/lang/String;CC)Ljava/lang/String;
    //   89: invokestatic 116	kkkkkk/nuuuuu$unuuuu:b043F043F043Fп043F043Fпп043Fп	(Lkkkkkk/unuunu;Ljava/lang/String;)Lkkkkkk/nuuuuu$unuuuu;
    //   92: astore 6
    //   94: getstatic 51	kkkkkk/rgrggg:bШШ042804280428Ш0428Ш0428	I
    //   97: getstatic 53	kkkkkk/rgrggg:b0428Ш042804280428Ш0428Ш0428	I
    //   100: iadd
    //   101: getstatic 51	kkkkkk/rgrggg:bШШ042804280428Ш0428Ш0428	I
    //   104: imul
    //   105: getstatic 55	kkkkkk/rgrggg:bШ0428042804280428Ш0428Ш0428	I
    //   108: irem
    //   109: getstatic 75	kkkkkk/rgrggg:b04280428042804280428Ш0428Ш0428	I
    //   112: if_icmpeq +44 -> 156
    //   115: bipush 62
    //   117: putstatic 51	kkkkkk/rgrggg:bШШ042804280428Ш0428Ш0428	I
    //   120: bipush 22
    //   122: putstatic 75	kkkkkk/rgrggg:b04280428042804280428Ш0428Ш0428	I
    //   125: getstatic 51	kkkkkk/rgrggg:bШШ042804280428Ш0428Ш0428	I
    //   128: invokestatic 192	kkkkkk/rgrggg:b0418041804180418И041804180418ИИ	()I
    //   131: iadd
    //   132: getstatic 51	kkkkkk/rgrggg:bШШ042804280428Ш0428Ш0428	I
    //   135: imul
    //   136: getstatic 55	kkkkkk/rgrggg:bШ0428042804280428Ш0428Ш0428	I
    //   139: irem
    //   140: getstatic 75	kkkkkk/rgrggg:b04280428042804280428Ш0428Ш0428	I
    //   143: if_icmpeq +13 -> 156
    //   146: bipush 8
    //   148: putstatic 51	kkkkkk/rgrggg:bШШ042804280428Ш0428Ш0428	I
    //   151: bipush 32
    //   153: putstatic 75	kkkkkk/rgrggg:b04280428042804280428Ш0428Ш0428	I
    //   156: aload_2
    //   157: aload_3
    //   158: aload 4
    //   160: aload 5
    //   162: iconst_2
    //   163: anewarray 112	kkkkkk/nuuuuu$unuuuu
    //   166: dup
    //   167: iconst_0
    //   168: aload 6
    //   170: aastore
    //   171: dup
    //   172: iconst_1
    //   173: getstatic 160	kkkkkk/unuunu:EVENT_NARRATIVE	Lkkkkkk/unuunu;
    //   176: aload_1
    //   177: invokestatic 116	kkkkkk/nuuuuu$unuuuu:b043F043F043Fп043F043Fпп043Fп	(Lkkkkkk/unuunu;Ljava/lang/String;)Lkkkkkk/nuuuuu$unuuuu;
    //   180: aastore
    //   181: invokevirtual 122	kkkkkk/nuuuuu:b043F043Fпппп043Fп043Fп	(Lkkkkkk/nnuunu;Ljava/lang/String;Ljava/lang/String;[Lkkkkkk/nuuuuu$unuuuu;)V
    //   184: return
    //   185: astore_1
    //   186: aload_1
    //   187: athrow
    //   188: astore_1
    //   189: aload_1
    //   190: athrow
    // Local variable table:
    //   start	length	slot	name	signature
    //   0	191	0	this	rgrggg
    //   0	191	1	paramString	String
    //   4	153	2	localNuuuuu	nuuuuu
    //   8	150	3	localNnuunu	nnuunu
    //   15	144	4	str1	String
    //   23	138	5	str2	String
    //   28	141	6	localObject	Object
    // Exception table:
    //   from	to	target	type
    //   0	30	185	java/lang/Exception
    //   156	184	185	java/lang/Exception
    //   79	125	188	java/lang/Exception
  }
  
  /* Error */
  public void bИ0418ИИ0418041804180418ИИ(String paramString)
  {
    // Byte code:
    //   0: getstatic 51	kkkkkk/rgrggg:bШШ042804280428Ш0428Ш0428	I
    //   3: istore_2
    //   4: getstatic 53	kkkkkk/rgrggg:b0428Ш042804280428Ш0428Ш0428	I
    //   7: istore_3
    //   8: getstatic 51	kkkkkk/rgrggg:bШШ042804280428Ш0428Ш0428	I
    //   11: getstatic 53	kkkkkk/rgrggg:b0428Ш042804280428Ш0428Ш0428	I
    //   14: iadd
    //   15: getstatic 51	kkkkkk/rgrggg:bШШ042804280428Ш0428Ш0428	I
    //   18: imul
    //   19: getstatic 55	kkkkkk/rgrggg:bШ0428042804280428Ш0428Ш0428	I
    //   22: irem
    //   23: getstatic 75	kkkkkk/rgrggg:b04280428042804280428Ш0428Ш0428	I
    //   26: if_icmpeq +14 -> 40
    //   29: invokestatic 57	kkkkkk/rgrggg:b0418И04180418И041804180418ИИ	()I
    //   32: putstatic 51	kkkkkk/rgrggg:bШШ042804280428Ш0428Ш0428	I
    //   35: bipush 30
    //   37: putstatic 75	kkkkkk/rgrggg:b04280428042804280428Ш0428Ш0428	I
    //   40: getstatic 51	kkkkkk/rgrggg:bШШ042804280428Ш0428Ш0428	I
    //   43: istore 4
    //   45: getstatic 55	kkkkkk/rgrggg:bШ0428042804280428Ш0428Ш0428	I
    //   48: istore 5
    //   50: getstatic 75	kkkkkk/rgrggg:b04280428042804280428Ш0428Ш0428	I
    //   53: istore 6
    //   55: iload_2
    //   56: iload_3
    //   57: iadd
    //   58: iload 4
    //   60: imul
    //   61: iload 5
    //   63: irem
    //   64: iload 6
    //   66: if_icmpeq +13 -> 79
    //   69: bipush 94
    //   71: putstatic 51	kkkkkk/rgrggg:bШШ042804280428Ш0428Ш0428	I
    //   74: bipush 51
    //   76: putstatic 75	kkkkkk/rgrggg:b04280428042804280428Ш0428Ш0428	I
    //   79: aload_0
    //   80: aload_1
    //   81: ldc -3
    //   83: bipush 69
    //   85: sipush 254
    //   88: iconst_3
    //   89: invokestatic 173	kkkkkk/gguuuu:bк043Aккк043Aкк043A043A	(Ljava/lang/String;CCC)Ljava/lang/String;
    //   92: invokevirtual 255	kkkkkk/rgrggg:b04180418ИИ0418041804180418ИИ	(Ljava/lang/String;Ljava/lang/String;)V
    //   95: return
    //   96: astore_1
    //   97: aload_1
    //   98: athrow
    //   99: astore_1
    //   100: aload_1
    //   101: athrow
    //   102: astore_1
    //   103: aload_1
    //   104: athrow
    // Local variable table:
    //   start	length	slot	name	signature
    //   0	105	0	this	rgrggg
    //   0	105	1	paramString	String
    //   3	55	2	i	int
    //   7	51	3	j	int
    //   43	18	4	k	int
    //   48	16	5	m	int
    //   53	14	6	n	int
    // Exception table:
    //   from	to	target	type
    //   79	95	96	java/lang/Exception
    //   69	79	99	java/lang/Exception
    //   97	99	99	java/lang/Exception
    //   0	8	102	java/lang/Exception
    //   40	55	102	java/lang/Exception
  }
  
  public void bИ0418ИИИИИИ0418И(String paramString)
  {
    nuuuuu localNuuuuu = this.b04280428Ш04280428Ш0428Ш0428;
    nnnuuu.nuunuu localNuunuu = nnnuuu.nuunuu.OVERLAY;
    int i = bШШ042804280428Ш0428Ш0428;
    int j = b0428Ш042804280428Ш0428Ш0428;
    int k = bШШ042804280428Ш0428Ш0428;
    switch (k * (b0428Ш042804280428Ш0428Ш0428 + k) % bШ0428042804280428Ш0428Ш0428)
    {
    default: 
      bШШ042804280428Ш0428Ш0428 = b0418И04180418И041804180418ИИ();
      b04280428042804280428Ш0428Ш0428 = b0418И04180418И041804180418ИИ();
    }
    switch (i * (j + i) % bШ0428042804280428Ш0428Ш0428)
    {
    default: 
      switch (0)
      {
      case 1: 
      default: 
        for (;;)
        {
          switch (1)
          {
          }
        }
      }
      bШШ042804280428Ш0428Ш0428 = b0418И04180418И041804180418ИИ();
      b04280428042804280428Ш0428Ш0428 = 18;
    }
    localNuuuuu.bпппппп043Fп043Fп(localNuunuu, paramString, unnuuu.CORE, new nuuuuu.unuuuu[0]);
  }
  
  public void bИИ041804180418041804180418ИИ(CharSequence paramCharSequence, String paramString)
  {
    nuuuuu localNuuuuu = this.b04280428Ш04280428Ш0428Ш0428;
    nnuunu localNnuunu = nnuunu.TAP_BUTTON_TO_NAVIGATE_TO_NEW_SCREEN;
    String str1 = nnnuuu.nuunuu.TAP.toString();
    String str2 = unnuuu.DEFER.toString();
    unuunu localUnuunu = unuunu.LINK_VALUE;
    int i = bШШ042804280428Ш0428Ш0428;
    switch (i * (b0428Ш042804280428Ш0428Ш0428 + i) % bШ0428042804280428Ш0428Ш0428)
    {
    default: 
      bШШ042804280428Ш0428Ш0428 = 38;
      b04280428042804280428Ш0428Ш0428 = 21;
    }
    localNuuuuu.b043F043Fпппп043Fп043Fп(localNnuunu, str1, str2, new nuuuuu.unuuuu[] { nuuuuu.unuuuu.b043F043F043Fп043F043Fпп043Fп(localUnuunu, bИИИИ0418041804180418ИИ(paramCharSequence, paramString)) });
  }
  
  public void bИИ0418И0418041804180418ИИ(String paramString)
  {
    b0418И0418И0418041804180418ИИ(paramString, gguuuu.bк043Aккк043Aкк043A043A("[{{u\t~\006", '©', '½', '\002'));
  }
  
  @ooiiio
  public void bИИ0418ИИИИИ0418И()
  {
    nuuuuu localNuuuuu = this.b04280428Ш04280428Ш0428Ш0428;
    nnuunu localNnuunu = nnuunu.SWIPE_RIGHT;
    String str1 = nnnuuu.nuunuu.SWIPE_RIGHT.toString();
    String str2 = unnuuu.DEFER.toString();
    if ((bШШ042804280428Ш0428Ш0428 + b0428Ш042804280428Ш0428Ш0428) * bШШ042804280428Ш0428Ш0428 % bШ0428042804280428Ш0428Ш0428 != b04280428042804280428Ш0428Ш0428)
    {
      bШШ042804280428Ш0428Ш0428 = 0;
      b04280428042804280428Ш0428Ш0428 = 71;
      if ((bШШ042804280428Ш0428Ш0428 + b0428Ш042804280428Ш0428Ш0428) * bШШ042804280428Ш0428Ш0428 % bШ0428042804280428Ш0428Ш0428 != bИИ04180418И041804180418ИИ())
      {
        bШШ042804280428Ш0428Ш0428 = b0418И04180418И041804180418ИИ();
        b04280428042804280428Ш0428Ш0428 = 75;
      }
    }
    unuunu localUnuunu = unuunu.LINK_VALUE;
    switch (0)
    {
    case 1: 
    default: 
      for (;;)
      {
        switch (1)
        {
        }
      }
    }
    localNuuuuu.b043F043Fпппп043Fп043Fп(localNnuunu, str1, str2, new nuuuuu.unuuuu[] { nuuuuu.unuuuu.b043F043F043Fп043F043Fпп043Fп(localUnuunu, gguuuu.bккккк043Aкк043A043A("\030\n\036u\031<-3'\023)&&1", '', '\003')) });
  }
  
  public void bИИИ04180418041804180418ИИ(String paramString)
  {
    try
    {
      this.b04280428Ш04280428Ш0428Ш0428.b043F043Fпппп043Fп043Fп(nnuunu.INPUT_ERROR_POPUP, nnnuuu.nuunuu.FORM_ENTRY.toString(), unnuuu.CORE.toString(), new nuuuuu.unuuuu[] { nuuuuu.unuuuu.b043F043F043Fп043F043Fпп043Fп(unuunu.EVENT_ACTION, gguuuu.bккккк043Aкк043A043A("kw\004\002}{\020\006\r\r?f\003\f\020\n\n", '', '\000')), nuuuuu.unuuuu.b043F043F043Fп043F043Fпп043Fп(unuunu.EVENT_NARRATIVE, paramString) });
      return;
    }
    catch (Exception paramString)
    {
      throw paramString;
    }
  }
  
  /* Error */
  public void bИИИИИИИИ0418И(String paramString1, String paramString2)
  {
    // Byte code:
    //   0: getstatic 51	kkkkkk/rgrggg:bШШ042804280428Ш0428Ш0428	I
    //   3: istore_3
    //   4: getstatic 53	kkkkkk/rgrggg:b0428Ш042804280428Ш0428Ш0428	I
    //   7: istore 4
    //   9: getstatic 51	kkkkkk/rgrggg:bШШ042804280428Ш0428Ш0428	I
    //   12: istore 5
    //   14: getstatic 51	kkkkkk/rgrggg:bШШ042804280428Ш0428Ш0428	I
    //   17: getstatic 53	kkkkkk/rgrggg:b0428Ш042804280428Ш0428Ш0428	I
    //   20: iadd
    //   21: getstatic 51	kkkkkk/rgrggg:bШШ042804280428Ш0428Ш0428	I
    //   24: imul
    //   25: getstatic 55	kkkkkk/rgrggg:bШ0428042804280428Ш0428Ш0428	I
    //   28: irem
    //   29: getstatic 75	kkkkkk/rgrggg:b04280428042804280428Ш0428Ш0428	I
    //   32: if_icmpeq +13 -> 45
    //   35: bipush 83
    //   37: putstatic 51	kkkkkk/rgrggg:bШШ042804280428Ш0428Ш0428	I
    //   40: bipush 50
    //   42: putstatic 75	kkkkkk/rgrggg:b04280428042804280428Ш0428Ш0428	I
    //   45: getstatic 55	kkkkkk/rgrggg:bШ0428042804280428Ш0428Ш0428	I
    //   48: istore 6
    //   50: invokestatic 137	kkkkkk/rgrggg:bИИ04180418И041804180418ИИ	()I
    //   53: istore 7
    //   55: iload_3
    //   56: iload 4
    //   58: iadd
    //   59: iload 5
    //   61: imul
    //   62: iload 6
    //   64: irem
    //   65: iload 7
    //   67: if_icmpeq +14 -> 81
    //   70: invokestatic 57	kkkkkk/rgrggg:b0418И04180418И041804180418ИИ	()I
    //   73: putstatic 51	kkkkkk/rgrggg:bШШ042804280428Ш0428Ш0428	I
    //   76: bipush 91
    //   78: putstatic 75	kkkkkk/rgrggg:b04280428042804280428Ш0428Ш0428	I
    //   81: aload_0
    //   82: aload_1
    //   83: aload_2
    //   84: ldc_w 282
    //   87: bipush 66
    //   89: iconst_1
    //   90: invokestatic 65	kkkkkk/gguuuu:bккккк043Aкк043A043A	(Ljava/lang/String;CC)Ljava/lang/String;
    //   93: invokevirtual 284	kkkkkk/rgrggg:b0418ИИИИИИИ0418И	(Ljava/lang/String;Ljava/lang/String;Ljava/lang/String;)V
    //   96: return
    //   97: astore_1
    //   98: aload_1
    //   99: athrow
    //   100: astore_1
    //   101: aload_1
    //   102: athrow
    // Local variable table:
    //   start	length	slot	name	signature
    //   0	103	0	this	rgrggg
    //   0	103	1	paramString1	String
    //   0	103	2	paramString2	String
    //   3	56	3	i	int
    //   7	52	4	j	int
    //   12	50	5	k	int
    //   48	17	6	m	int
    //   53	15	7	n	int
    // Exception table:
    //   from	to	target	type
    //   0	9	97	java/lang/Exception
    //   45	55	97	java/lang/Exception
    //   81	96	97	java/lang/Exception
    //   9	14	100	java/lang/Exception
    //   70	81	100	java/lang/Exception
  }
}
