package kkkkkk;

import android.graphics.Bitmap;
import android.support.annotation.Nullable;
import android.support.annotation.StringRes;
import android.webkit.WebView;
import io.reactivex.Completable;
import io.reactivex.CompletableTransformer;
import io.reactivex.Single;
import io.reactivex.annotations.NonNull;
import io.reactivex.disposables.Disposable;
import io.reactivex.functions.Action;
import io.reactivex.functions.Consumer;
import java.util.concurrent.CountDownLatch;

public abstract class rgrrrg<T extends ggrgrg>
  extends gggggr<T>
  implements iciiic
{
  public static int b04280428ШШ0428042804280428Ш = 2;
  public static int b0428ШШШ0428042804280428Ш = 45;
  public static int bШ0428ШШ0428042804280428Ш = 1;
  public static int bШШ0428Ш0428042804280428Ш;
  
  public rgrrrg() {}
  
  public static int b0418И04180418И0418И0418ИИ()
  {
    return 62;
  }
  
  public static int bИ041804180418И0418И0418ИИ()
  {
    return 0;
  }
  
  public Consumer<Throwable> b0418041804180418И0418И0418ИИ()
  {
    rgrgrg localRgrgrg = new rgrgrg();
    switch (1)
    {
    case 0: 
    default: 
      for (;;)
      {
        switch (1)
        {
        case 0: 
        default: 
          for (;;)
          {
            switch (1)
            {
            }
          }
        }
        switch (0)
        {
        }
      }
    }
    if ((b0428ШШШ0428042804280428Ш + bШ0428ШШ0428042804280428Ш) * b0428ШШШ0428042804280428Ш % b04280428ШШ0428042804280428Ш != bИ041804180418И0418И0418ИИ())
    {
      int i = b0428ШШШ0428042804280428Ш;
      switch (i * (bШ0428ШШ0428042804280428Ш + i) % b04280428ШШ0428042804280428Ш)
      {
      default: 
        b0428ШШШ0428042804280428Ш = 0;
        bШ0428ШШ0428042804280428Ш = b0418И04180418И0418И0418ИИ();
      }
      b0428ШШШ0428042804280428Ш = 4;
      bШ0428ШШ0428042804280428Ш = 23;
    }
    return localRgrgrg;
  }
  
  public <U> Single<U> b04180418ИИ04180418И0418ИИ(Single<U> paramSingle)
  {
    try
    {
      paramSingle = paramSingle.doOnSubscribe(new Consumer()
      {
        public static int b042804280428ШШШШШ0428 = 2;
        public static int b0428Ш0428ШШШШШ0428 = 8;
        public static int bШ04280428ШШШШШ0428 = 1;
        
        public static int b0418И041804180418ИИ0418ИИ()
        {
          return 2;
        }
        
        public static int bИИ041804180418ИИ0418ИИ()
        {
          return 94;
        }
        
        public void b04180418И04180418ИИ0418ИИ(Disposable paramAnonymousDisposable)
          throws Exception
        {
          try
          {
            paramAnonymousDisposable = rgrrrg.this;
            int i = b0428Ш0428ШШШШШ0428;
            int j = bШ04280428ШШШШШ0428;
            int k = b042804280428ШШШШШ0428;
            switch (i * (j + i) % k)
            {
            default: 
              i = b0428Ш0428ШШШШШ0428;
              switch (i * (bШ04280428ШШШШШ0428 + i) % b042804280428ШШШШШ0428)
              {
              default: 
                b0428Ш0428ШШШШШ0428 = bИИ041804180418ИИ0418ИИ();
                bШ04280428ШШШШШ0428 = 67;
              }
              b0428Ш0428ШШШШШ0428 = bИИ041804180418ИИ0418ИИ();
              bШ04280428ШШШШШ0428 = 63;
            }
            ((rgrrrg.ggrgrg)paramAnonymousDisposable.b042804280428ШШ042804280428Ш).showLoading();
            return;
          }
          catch (Exception paramAnonymousDisposable)
          {
            throw paramAnonymousDisposable;
          }
        }
      });
      local3 = new Action()
      {
        public static int b04280428ШШШШШШ0428 = 1;
        public static int b0428ШШШШШШШ0428 = 2;
        public static int bШ0428ШШШШШШ0428 = 0;
        public static int bШШШШШШШШ0428 = 11;
        
        public static int b0418ИИ04180418ИИ0418ИИ()
        {
          return 55;
        }
        
        public static int bИ0418И04180418ИИ0418ИИ()
        {
          return 1;
        }
        
        /* Error */
        public void run()
          throws Exception
        {
          // Byte code:
          //   0: aload_0
          //   1: getfield 24	kkkkkk/rgrrrg$3:b04280428042804280428042804280428Ш	Lkkkkkk/rgrrrg;
          //   4: getfield 38	kkkkkk/rgrrrg:b042804280428ШШ042804280428Ш	Lkkkkkk/gggggr$grrrrg;
          //   7: astore_3
          //   8: aload_3
          //   9: checkcast 40	kkkkkk/rgrrrg$ggrgrg
          //   12: invokeinterface 43 1 0
          //   17: getstatic 45	kkkkkk/rgrrrg$3:bШШШШШШШШ0428	I
          //   20: istore_1
          //   21: invokestatic 47	kkkkkk/rgrrrg$3:bИ0418И04180418ИИ0418ИИ	()I
          //   24: istore_2
          //   25: iconst_1
          //   26: tableswitch	default:+22->48, 0:+-1->25, 1:+49->75
          //   48: iconst_1
          //   49: tableswitch	default:+23->72, 0:+-24->25, 1:+26->75
          //   72: goto -24 -> 48
          //   75: iload_1
          //   76: iload_2
          //   77: iload_1
          //   78: iadd
          //   79: imul
          //   80: getstatic 49	kkkkkk/rgrrrg$3:b0428ШШШШШШШ0428	I
          //   83: irem
          //   84: tableswitch	default:+20->104, 0:+63->147
          //   104: bipush 73
          //   106: putstatic 45	kkkkkk/rgrrrg$3:bШШШШШШШШ0428	I
          //   109: invokestatic 51	kkkkkk/rgrrrg$3:b0418ИИ04180418ИИ0418ИИ	()I
          //   112: putstatic 49	kkkkkk/rgrrrg$3:b0428ШШШШШШШ0428	I
          //   115: getstatic 45	kkkkkk/rgrrrg$3:bШШШШШШШШ0428	I
          //   118: getstatic 53	kkkkkk/rgrrrg$3:b04280428ШШШШШШ0428	I
          //   121: iadd
          //   122: getstatic 45	kkkkkk/rgrrrg$3:bШШШШШШШШ0428	I
          //   125: imul
          //   126: getstatic 49	kkkkkk/rgrrrg$3:b0428ШШШШШШШ0428	I
          //   129: irem
          //   130: getstatic 55	kkkkkk/rgrrrg$3:bШ0428ШШШШШШ0428	I
          //   133: if_icmpeq +14 -> 147
          //   136: invokestatic 51	kkkkkk/rgrrrg$3:b0418ИИ04180418ИИ0418ИИ	()I
          //   139: putstatic 45	kkkkkk/rgrrrg$3:bШШШШШШШШ0428	I
          //   142: bipush 8
          //   144: putstatic 55	kkkkkk/rgrrrg$3:bШ0428ШШШШШШ0428	I
          //   147: return
          //   148: astore_3
          //   149: aload_3
          //   150: athrow
          //   151: astore_3
          //   152: aload_3
          //   153: athrow
          // Local variable table:
          //   start	length	slot	name	signature
          //   0	154	0	this	3
          //   20	60	1	i	int
          //   24	55	2	j	int
          //   7	2	3	localGrrrrg	gggggr.grrrrg
          //   148	2	3	localException1	Exception
          //   151	2	3	localException2	Exception
          // Exception table:
          //   from	to	target	type
          //   8	17	148	java/lang/Exception
          //   0	8	151	java/lang/Exception
        }
      };
    }
    catch (Exception paramSingle)
    {
      try
      {
        Action local3;
        int j;
        int k;
        int m;
        int n;
        b0428ШШШ0428042804280428Ш = 8;
        int i = b0418И04180418И0418И0418ИИ();
        bШШ0428Ш0428042804280428Ш = i;
        paramSingle = paramSingle.doAfterTerminate(local3);
        return paramSingle;
      }
      catch (Exception paramSingle)
      {
        throw paramSingle;
      }
      paramSingle = paramSingle;
      throw paramSingle;
    }
    i = b0428ШШШ0428042804280428Ш;
    j = bШ0428ШШ0428042804280428Ш;
    k = b0428ШШШ0428042804280428Ш;
    m = b04280428ШШ0428042804280428Ш;
    n = bШШ0428Ш0428042804280428Ш;
    if ((i + j) * k % m != n)
    {
      i = b0428ШШШ0428042804280428Ш;
      switch (i * (bШ0428ШШ0428042804280428Ш + i) % b04280428ШШ0428042804280428Ш)
      {
      default: 
        b0428ШШШ0428042804280428Ш = 70;
        bШШ0428Ш0428042804280428Ш = 68;
      }
    }
    switch (1)
    {
    }
    for (;;)
    {
      switch (0)
      {
      }
    }
  }
  
  public Completable b0418ИИИ04180418И0418ИИ(Completable paramCompletable)
  {
    paramCompletable = paramCompletable.doOnSubscribe(new Consumer()
    {
      public static int b04280428Ш04280428042804280428Ш = 99;
      public static int b0428Ш042804280428042804280428Ш = 2;
      public static int bШ0428042804280428042804280428Ш = 0;
      public static int bШШ042804280428042804280428Ш = 1;
      
      public static int b041804180418И0418ИИ0418ИИ()
      {
        return 4;
      }
      
      public static int bИ04180418И0418ИИ0418ИИ()
      {
        return 2;
      }
      
      public static int bИИИ04180418ИИ0418ИИ()
      {
        return 0;
      }
      
      public void b0418И0418И0418ИИ0418ИИ(Disposable paramAnonymousDisposable)
        throws Exception
      {
        paramAnonymousDisposable = rgrrrg.this;
        int i = b04280428Ш04280428042804280428Ш;
        int j = bШШ042804280428042804280428Ш;
        int k = b04280428Ш04280428042804280428Ш;
        if ((b04280428Ш04280428042804280428Ш + bШШ042804280428042804280428Ш) * b04280428Ш04280428042804280428Ш % bИ04180418И0418ИИ0418ИИ() != bШ0428042804280428042804280428Ш)
        {
          b04280428Ш04280428042804280428Ш = b041804180418И0418ИИ0418ИИ();
          bШ0428042804280428042804280428Ш = b041804180418И0418ИИ0418ИИ();
        }
        if ((i + j) * k % b0428Ш042804280428042804280428Ш != bИИИ04180418ИИ0418ИИ())
        {
          b04280428Ш04280428042804280428Ш = 68;
          bШШ042804280428042804280428Ш = b041804180418И0418ИИ0418ИИ();
        }
        ((rgrrrg.ggrgrg)paramAnonymousDisposable.b042804280428ШШ042804280428Ш).showLoading();
      }
    }).doAfterTerminate(new Action()
    {
      public static int b042804280428Ш0428042804280428Ш = 0;
      public static int b0428ШШ04280428042804280428Ш = 2;
      public static int bШ04280428Ш0428042804280428Ш = 61;
      public static int bШШШ04280428042804280428Ш = 1;
      
      public static int b04180418ИИ0418ИИ0418ИИ()
      {
        return 52;
      }
      
      public static int bИИ0418И0418ИИ0418ИИ()
      {
        return 1;
      }
      
      /* Error */
      public void run()
        throws Exception
      {
        // Byte code:
        //   0: getstatic 36	kkkkkk/rgrrrg$1:bШ04280428Ш0428042804280428Ш	I
        //   3: istore_1
        //   4: iload_1
        //   5: invokestatic 38	kkkkkk/rgrrrg$1:bИИ0418И0418ИИ0418ИИ	()I
        //   8: iload_1
        //   9: iadd
        //   10: imul
        //   11: getstatic 40	kkkkkk/rgrrrg$1:b0428ШШ04280428042804280428Ш	I
        //   14: irem
        //   15: tableswitch	default:+17->32, 0:+29->44
        //   32: invokestatic 42	kkkkkk/rgrrrg$1:b04180418ИИ0418ИИ0418ИИ	()I
        //   35: putstatic 36	kkkkkk/rgrrrg$1:bШ04280428Ш0428042804280428Ш	I
        //   38: invokestatic 42	kkkkkk/rgrrrg$1:b04180418ИИ0418ИИ0418ИИ	()I
        //   41: putstatic 44	kkkkkk/rgrrrg$1:b042804280428Ш0428042804280428Ш	I
        //   44: aload_0
        //   45: getfield 24	kkkkkk/rgrrrg$1:b0428Ш0428Ш0428042804280428Ш	Lkkkkkk/rgrrrg;
        //   48: getfield 48	kkkkkk/rgrrrg:b042804280428ШШ042804280428Ш	Lkkkkkk/gggggr$grrrrg;
        //   51: checkcast 50	kkkkkk/rgrrrg$ggrgrg
        //   54: astore_2
        //   55: getstatic 36	kkkkkk/rgrrrg$1:bШ04280428Ш0428042804280428Ш	I
        //   58: getstatic 52	kkkkkk/rgrrrg$1:bШШШ04280428042804280428Ш	I
        //   61: iadd
        //   62: getstatic 36	kkkkkk/rgrrrg$1:bШ04280428Ш0428042804280428Ш	I
        //   65: imul
        //   66: getstatic 40	kkkkkk/rgrrrg$1:b0428ШШ04280428042804280428Ш	I
        //   69: irem
        //   70: getstatic 44	kkkkkk/rgrrrg$1:b042804280428Ш0428042804280428Ш	I
        //   73: if_icmpeq +65 -> 138
        //   76: iconst_1
        //   77: tableswitch	default:+23->100, 0:+-1->76, 1:+50->127
        //   100: iconst_1
        //   101: tableswitch	default:+23->124, 0:+-25->76, 1:+26->127
        //   124: goto -24 -> 100
        //   127: bipush 36
        //   129: putstatic 36	kkkkkk/rgrrrg$1:bШ04280428Ш0428042804280428Ш	I
        //   132: invokestatic 42	kkkkkk/rgrrrg$1:b04180418ИИ0418ИИ0418ИИ	()I
        //   135: putstatic 44	kkkkkk/rgrrrg$1:b042804280428Ш0428042804280428Ш	I
        //   138: aload_2
        //   139: invokeinterface 55 1 0
        //   144: return
        //   145: astore_2
        //   146: aload_2
        //   147: athrow
        //   148: astore_2
        //   149: aload_2
        //   150: athrow
        // Local variable table:
        //   start	length	slot	name	signature
        //   0	151	0	this	1
        //   3	8	1	i	int
        //   54	85	2	localGgrgrg	rgrrrg.ggrgrg
        //   145	2	2	localException1	Exception
        //   148	2	2	localException2	Exception
        // Exception table:
        //   from	to	target	type
        //   44	55	145	java/lang/Exception
        //   138	144	148	java/lang/Exception
      }
    });
    if ((b0428ШШШ0428042804280428Ш + bШ0428ШШ0428042804280428Ш) * b0428ШШШ0428042804280428Ш % b04280428ШШ0428042804280428Ш != bШШ0428Ш0428042804280428Ш)
    {
      if ((b0418И04180418И0418И0418ИИ() + bШ0428ШШ0428042804280428Ш) * b0418И04180418И0418И0418ИИ() % b04280428ШШ0428042804280428Ш != bШШ0428Ш0428042804280428Ш)
      {
        b0428ШШШ0428042804280428Ш = 38;
        bШШ0428Ш0428042804280428Ш = 10;
      }
      b0428ШШШ0428042804280428Ш = b0418И04180418И0418И0418ИИ();
      bШШ0428Ш0428042804280428Ш = b0418И04180418И0418И0418ИИ();
    }
    return paramCompletable;
  }
  
  public final CompletableTransformer bИ0418ИИ04180418И0418ИИ(@Nullable final CountDownLatch paramCountDownLatch)
  {
    try
    {
      paramCountDownLatch = new CompletableTransformer()
      {
        public static int b04280428Ш0428ШШШШ0428 = 0;
        public static int b0428Ш04280428ШШШШ0428 = 2;
        public static int bШ0428Ш0428ШШШШ0428 = 48;
        public static int bШШ04280428ШШШШ0428 = 1;
        
        public static int b04180418ИИИ0418И0418ИИ()
        {
          return 1;
        }
        
        public static int bИ0418ИИИ0418И0418ИИ()
        {
          return 51;
        }
        
        /* Error */
        public io.reactivex.CompletableSource apply(Completable paramAnonymousCompletable)
        {
          // Byte code:
          //   0: aload_1
          //   1: new 14	kkkkkk/rgrrrg$5$2
          //   4: dup
          //   5: aload_0
          //   6: invokespecial 48	kkkkkk/rgrrrg$5$2:<init>	(Lkkkkkk/rgrrrg$5;)V
          //   9: invokevirtual 54	io/reactivex/Completable:doOnSubscribe	(Lio/reactivex/functions/Consumer;)Lio/reactivex/Completable;
          //   12: astore_1
          //   13: getstatic 56	kkkkkk/rgrrrg$5:bШ0428Ш0428ШШШШ0428	I
          //   16: istore_2
          //   17: iload_2
          //   18: invokestatic 58	kkkkkk/rgrrrg$5:b04180418ИИИ0418И0418ИИ	()I
          //   21: iload_2
          //   22: iadd
          //   23: imul
          //   24: getstatic 60	kkkkkk/rgrrrg$5:b0428Ш04280428ШШШШ0428	I
          //   27: irem
          //   28: tableswitch	default:+20->48, 0:+30->58
          //   48: bipush 64
          //   50: putstatic 56	kkkkkk/rgrrrg$5:bШ0428Ш0428ШШШШ0428	I
          //   53: bipush 7
          //   55: putstatic 62	kkkkkk/rgrrrg$5:b04280428Ш0428ШШШШ0428	I
          //   58: new 11	kkkkkk/rgrrrg$5$1
          //   61: dup
          //   62: aload_0
          //   63: invokespecial 63	kkkkkk/rgrrrg$5$1:<init>	(Lkkkkkk/rgrrrg$5;)V
          //   66: astore 7
          //   68: getstatic 56	kkkkkk/rgrrrg$5:bШ0428Ш0428ШШШШ0428	I
          //   71: istore_2
          //   72: getstatic 65	kkkkkk/rgrrrg$5:bШШ04280428ШШШШ0428	I
          //   75: istore_3
          //   76: getstatic 56	kkkkkk/rgrrrg$5:bШ0428Ш0428ШШШШ0428	I
          //   79: istore 4
          //   81: getstatic 60	kkkkkk/rgrrrg$5:b0428Ш04280428ШШШШ0428	I
          //   84: istore 5
          //   86: getstatic 62	kkkkkk/rgrrrg$5:b04280428Ш0428ШШШШ0428	I
          //   89: istore 6
          //   91: iload_2
          //   92: iload_3
          //   93: iadd
          //   94: iload 4
          //   96: imul
          //   97: iload 5
          //   99: irem
          //   100: iload 6
          //   102: if_icmpeq +15 -> 117
          //   105: invokestatic 67	kkkkkk/rgrrrg$5:bИ0418ИИИ0418И0418ИИ	()I
          //   108: putstatic 56	kkkkkk/rgrrrg$5:bШ0428Ш0428ШШШШ0428	I
          //   111: invokestatic 67	kkkkkk/rgrrrg$5:bИ0418ИИИ0418И0418ИИ	()I
          //   114: putstatic 62	kkkkkk/rgrrrg$5:b04280428Ш0428ШШШШ0428	I
          //   117: aload_1
          //   118: aload 7
          //   120: invokevirtual 71	io/reactivex/Completable:doAfterTerminate	(Lio/reactivex/functions/Action;)Lio/reactivex/Completable;
          //   123: astore_1
          //   124: aload_1
          //   125: areturn
          //   126: astore_1
          //   127: aload_1
          //   128: athrow
          //   129: astore_1
          //   130: aload_1
          //   131: athrow
          //   132: astore_1
          //   133: aload_1
          //   134: athrow
          //   135: astore_1
          //   136: aload_1
          //   137: athrow
          // Local variable table:
          //   start	length	slot	name	signature
          //   0	138	0	this	5
          //   0	138	1	paramAnonymousCompletable	Completable
          //   16	78	2	i	int
          //   75	19	3	j	int
          //   79	18	4	k	int
          //   84	16	5	m	int
          //   89	14	6	n	int
          //   66	53	7	local1	1
          // Exception table:
          //   from	to	target	type
          //   0	13	126	java/lang/Exception
          //   117	124	126	java/lang/Exception
          //   68	72	129	java/lang/Exception
          //   81	91	129	java/lang/Exception
          //   127	129	129	java/lang/Exception
          //   133	135	129	java/lang/Exception
          //   58	68	132	java/lang/Exception
          //   72	81	135	java/lang/Exception
          //   105	117	135	java/lang/Exception
        }
      };
      int i = b0428ШШШ0428042804280428Ш;
      int j = bШ0428ШШ0428042804280428Ш;
      int k = b0428ШШШ0428042804280428Ш;
      int m = b0428ШШШ0428042804280428Ш;
      switch (m * (bШ0428ШШ0428042804280428Ш + m) % b04280428ШШ0428042804280428Ш)
      {
      default: 
        b0428ШШШ0428042804280428Ш = 57;
        bШШ0428Ш0428042804280428Ш = b0418И04180418И0418И0418ИИ();
      }
      if ((i + j) * k % b04280428ШШ0428042804280428Ш != bИ041804180418И0418И0418ИИ())
      {
        b0428ШШШ0428042804280428Ш = 66;
        bШШ0428Ш0428042804280428Ш = 53;
      }
      return paramCountDownLatch;
    }
    catch (Exception paramCountDownLatch)
    {
      throw paramCountDownLatch;
    }
  }
  
  /* Error */
  public final CompletableTransformer bИИИИ04180418И0418ИИ()
  {
    // Byte code:
    //   0: getstatic 57	kkkkkk/rgrrrg:b0428ШШШ0428042804280428Ш	I
    //   3: istore_1
    //   4: getstatic 59	kkkkkk/rgrrrg:bШ0428ШШ0428042804280428Ш	I
    //   7: istore_2
    //   8: getstatic 57	kkkkkk/rgrrrg:b0428ШШШ0428042804280428Ш	I
    //   11: istore_3
    //   12: getstatic 61	kkkkkk/rgrrrg:b04280428ШШ0428042804280428Ш	I
    //   15: istore 4
    //   17: getstatic 81	kkkkkk/rgrrrg:bШШ0428Ш0428042804280428Ш	I
    //   20: istore 5
    //   22: iload_1
    //   23: iload_2
    //   24: iadd
    //   25: iload_3
    //   26: imul
    //   27: iload 4
    //   29: irem
    //   30: iload 5
    //   32: if_icmpeq +14 -> 46
    //   35: invokestatic 65	kkkkkk/rgrrrg:b0418И04180418И0418И0418ИИ	()I
    //   38: putstatic 57	kkkkkk/rgrrrg:b0428ШШШ0428042804280428Ш	I
    //   41: bipush 73
    //   43: putstatic 81	kkkkkk/rgrrrg:bШШ0428Ш0428042804280428Ш	I
    //   46: aload_0
    //   47: aconst_null
    //   48: invokevirtual 109	kkkkkk/rgrrrg:bИ0418ИИ04180418И0418ИИ	(Ljava/util/concurrent/CountDownLatch;)Lio/reactivex/CompletableTransformer;
    //   51: astore 6
    //   53: aload 6
    //   55: areturn
    //   56: astore 6
    //   58: aload 6
    //   60: athrow
    //   61: astore 6
    //   63: aload 6
    //   65: athrow
    //   66: astore 6
    //   68: aload 6
    //   70: athrow
    // Local variable table:
    //   start	length	slot	name	signature
    //   0	71	0	this	rgrrrg
    //   3	22	1	i	int
    //   7	18	2	j	int
    //   11	16	3	k	int
    //   15	15	4	m	int
    //   20	13	5	n	int
    //   51	3	6	localCompletableTransformer	CompletableTransformer
    //   56	3	6	localException1	Exception
    //   61	3	6	localException2	Exception
    //   66	3	6	localException3	Exception
    // Exception table:
    //   from	to	target	type
    //   46	53	56	java/lang/Exception
    //   0	22	61	java/lang/Exception
    //   58	61	61	java/lang/Exception
    //   35	46	66	java/lang/Exception
  }
  
  @ooiiio("Callback method from Fragment")
  public void onDialogRequested(WebView paramWebView, String paramString, iiciic paramIiciic)
  {
    if ((b0428ШШШ0428042804280428Ш + bШ0428ШШ0428042804280428Ш) * b0428ШШШ0428042804280428Ш % b04280428ШШ0428042804280428Ш != bШШ0428Ш0428042804280428Ш)
    {
      b0428ШШШ0428042804280428Ш = 3;
      bШШ0428Ш0428042804280428Ш = 31;
    }
    switch (0)
    {
    case 1: 
    default: 
      for (;;)
      {
        switch (1)
        {
        }
      }
    }
  }
  
  @ooiiio("Callback method from Fragment")
  public void onPageFinished(WebView paramWebView, String paramString) {}
  
  @ooiiio("Callback method from Fragment")
  public void onPageStarted(WebView paramWebView, String paramString, @Nullable Bitmap paramBitmap)
  {
    switch (1)
    {
    case 0: 
    default: 
      for (;;)
      {
        if ((b0428ШШШ0428042804280428Ш + bШ0428ШШ0428042804280428Ш) * b0428ШШШ0428042804280428Ш % b04280428ШШ0428042804280428Ш != bШШ0428Ш0428042804280428Ш)
        {
          b0428ШШШ0428042804280428Ш = b0418И04180418И0418И0418ИИ();
          bШШ0428Ш0428042804280428Ш = 92;
        }
        switch (1)
        {
        }
      }
    }
  }
  
  public static abstract interface ggrgrg
    extends gggggr.grrrrg
  {
    public abstract void addLatchToLoadingDialog(@Nullable CountDownLatch paramCountDownLatch);
    
    public abstract void hideLoading();
    
    public abstract void showAppVersionBannedScreen(String paramString);
    
    public abstract void showConnectionErrorNotification();
    
    public abstract void showLoading();
    
    public abstract void showLoggedInErrorScreen(String paramString1, String paramString2);
    
    public abstract void showLoggedOutErrorScreen(@StringRes int paramInt);
    
    public abstract void showLoggedOutErrorScreen(String paramString);
    
    public abstract void showLoggedOutErrorScreen(String paramString1, String paramString2);
  }
  
  public class rgrgrg
    implements Consumer<Throwable>
  {
    public static int b04280428Ш04280428ШШШ0428 = 1;
    public static int b0428ШШ04280428ШШШ0428 = 37;
    public static int bШ0428Ш04280428ШШШ0428 = 0;
    public static int bШШ042804280428ШШШ0428 = 2;
    
    public rgrgrg() {}
    
    public static int b041804180418ИИ0418И0418ИИ()
    {
      return 80;
    }
    
    private boolean b04180418И0418И0418И0418ИИ(@NonNull pdddpp paramPdddpp)
    {
      try
      {
        if (paramPdddpp.b0430аа0430аа04300430аа() == nkknkn.CONNECTION_ERROR)
        {
          paramPdddpp = rgrrrg.this;
          if ((b0428ШШ04280428ШШШ0428 + b04280428Ш04280428ШШШ0428) * b0428ШШ04280428ШШШ0428 % bШШ042804280428ШШШ0428 != bШ0428Ш04280428ШШШ0428)
          {
            b0428ШШ04280428ШШШ0428 = 72;
            bШ0428Ш04280428ШШШ0428 = 65;
            int i = b0428ШШ04280428ШШШ0428;
            switch (i * (b04280428Ш04280428ШШШ0428 + i) % bШШ042804280428ШШШ0428)
            {
            default: 
              b0428ШШ04280428ШШШ0428 = b041804180418ИИ0418И0418ИИ();
              bШ0428Ш04280428ШШШ0428 = 49;
            }
          }
          ((rgrrrg.ggrgrg)paramPdddpp.b042804280428ШШ042804280428Ш).showConnectionErrorNotification();
          return true;
        }
      }
      catch (Exception paramPdddpp)
      {
        throw paramPdddpp;
      }
      return false;
    }
    
    public static int b0418И0418ИИ0418И0418ИИ()
    {
      return 0;
    }
    
    public static int bИ04180418ИИ0418И0418ИИ()
    {
      return 1;
    }
    
    private boolean bИ0418И0418И0418И0418ИИ(@NonNull hhaahh paramHhaahh)
    {
      paramHhaahh = paramHhaahh.bп043F043Fппп043F043F043F043F();
      ununun localUnunun = paramHhaahh.bп043Fпп043F043F043F043F043Fп();
      boolean bool1 = localUnunun.b043F043Fп043F043F043F043F043F043Fп();
      if ((b0428ШШ04280428ШШШ0428 + b04280428Ш04280428ШШШ0428) * b0428ШШ04280428ШШШ0428 % bШШ042804280428ШШШ0428 != bШ0428Ш04280428ШШШ0428)
      {
        b0428ШШ04280428ШШШ0428 = b041804180418ИИ0418И0418ИИ();
        bШ0428Ш04280428ШШШ0428 = b041804180418ИИ0418И0418ИИ();
      }
      if (bool1)
      {
        ((rgrrrg.ggrgrg)rgrrrg.this.b042804280428ШШ042804280428Ш).showAppVersionBannedScreen(paramHhaahh.b043F043Fпп043F043F043F043F043Fп());
        bool1 = true;
        return bool1;
        do
        {
          boolean bool2 = b04300430ааааа043004300430(paramHhaahh);
          bool1 = bool2;
          if ((b0428ШШ04280428ШШШ0428 + b04280428Ш04280428ШШШ0428) * b0428ШШ04280428ШШШ0428 % bШШ042804280428ШШШ0428 == bШ0428Ш04280428ШШШ0428) {
            break;
          }
          b0428ШШ04280428ШШШ0428 = b041804180418ИИ0418И0418ИИ();
          bШ0428Ш04280428ШШШ0428 = b041804180418ИИ0418И0418ИИ();
          return bool2;
        } while (localUnunun != ununun.CONCURRENT_SESSION_LOG_OFF);
        ((rgrrrg.ggrgrg)rgrrrg.this.b042804280428ШШ042804280428Ш).showLoggedOutErrorScreen(paramHhaahh.b043F043Fпп043F043F043F043F043Fп());
        return true;
      }
      switch (0)
      {
      }
      for (;;)
      {
        switch (0)
        {
        }
      }
    }
    
    /* Error */
    public final boolean b0418ИИ0418И0418И0418ИИ(@NonNull Throwable paramThrowable)
    {
      // Byte code:
      //   0: aload_1
      //   1: invokestatic 124	kkkkkk/hhaahh:b043Fп043Fппп043F043F043F043F	(Ljava/lang/Throwable;)Lkkkkkk/hhaahh;
      //   4: astore 4
      //   6: aload 4
      //   8: ifnull +60 -> 68
      //   11: aload_0
      //   12: aload 4
      //   14: invokespecial 126	kkkkkk/rgrrrg$rgrgrg:bИ0418И0418И0418И0418ИИ	(Lkkkkkk/hhaahh;)Z
      //   17: istore_3
      //   18: iload_3
      //   19: ifeq +49 -> 68
      //   22: invokestatic 58	kkkkkk/rgrrrg$rgrgrg:b041804180418ИИ0418И0418ИИ	()I
      //   25: istore_2
      //   26: iload_2
      //   27: getstatic 52	kkkkkk/rgrrrg$rgrgrg:b04280428Ш04280428ШШШ0428	I
      //   30: iload_2
      //   31: iadd
      //   32: imul
      //   33: getstatic 54	kkkkkk/rgrrrg$rgrgrg:bШШ042804280428ШШШ0428	I
      //   36: irem
      //   37: tableswitch	default:+19->56, 0:+29->66
      //   56: bipush 8
      //   58: putstatic 50	kkkkkk/rgrrrg$rgrgrg:b0428ШШ04280428ШШШ0428	I
      //   61: bipush 42
      //   63: putstatic 56	kkkkkk/rgrrrg$rgrgrg:bШ0428Ш04280428ШШШ0428	I
      //   66: iconst_1
      //   67: ireturn
      //   68: aload_1
      //   69: invokestatic 130	kkkkkk/pdddpp:b043004300430ааа04300430аа	(Ljava/lang/Throwable;)Lkkkkkk/pdddpp;
      //   72: astore 4
      //   74: aload 4
      //   76: ifnull +93 -> 169
      //   79: aload 4
      //   81: invokevirtual 133	kkkkkk/pdddpp:bа0430а0430аа04300430аа	()Z
      //   84: istore_3
      //   85: iload_3
      //   86: ifeq +22 -> 108
      //   89: aload 4
      //   91: invokevirtual 137	kkkkkk/pdddpp:bааа0430аа04300430аа	()Lkkkkkk/ddpppp;
      //   94: astore_1
      //   95: aload_0
      //   96: aload_1
      //   97: invokestatic 141	kkkkkk/hhaahh:bпп043Fппп043F043F043F043F	(Lkkkkkk/ddpppp;)Lkkkkkk/hhaahh;
      //   100: invokespecial 126	kkkkkk/rgrrrg$rgrgrg:bИ0418И0418И0418И0418ИИ	(Lkkkkkk/hhaahh;)Z
      //   103: istore_3
      //   104: iload_3
      //   105: ifne -39 -> 66
      //   108: getstatic 50	kkkkkk/rgrrrg$rgrgrg:b0428ШШ04280428ШШШ0428	I
      //   111: istore_2
      //   112: iload_2
      //   113: getstatic 52	kkkkkk/rgrrrg$rgrgrg:b04280428Ш04280428ШШШ0428	I
      //   116: iload_2
      //   117: iadd
      //   118: imul
      //   119: getstatic 54	kkkkkk/rgrrrg$rgrgrg:bШШ042804280428ШШШ0428	I
      //   122: irem
      //   123: tableswitch	default:+17->140, 0:+28->151
      //   140: invokestatic 58	kkkkkk/rgrrrg$rgrgrg:b041804180418ИИ0418И0418ИИ	()I
      //   143: putstatic 50	kkkkkk/rgrrrg$rgrgrg:b0428ШШ04280428ШШШ0428	I
      //   146: bipush 89
      //   148: putstatic 56	kkkkkk/rgrrrg$rgrgrg:bШ0428Ш04280428ШШШ0428	I
      //   151: aload_0
      //   152: aload 4
      //   154: invokevirtual 144	kkkkkk/rgrrrg$rgrgrg:bИИИ0418И0418И0418ИИ	(Lkkkkkk/pdddpp;)Z
      //   157: ifne -91 -> 66
      //   160: aload_0
      //   161: aload 4
      //   163: invokespecial 146	kkkkkk/rgrrrg$rgrgrg:b04180418И0418И0418И0418ИИ	(Lkkkkkk/pdddpp;)Z
      //   166: istore_3
      //   167: iload_3
      //   168: ireturn
      //   169: aload_0
      //   170: aload_1
      //   171: invokevirtual 149	kkkkkk/rgrrrg$rgrgrg:bИИ04180418И0418И0418ИИ	(Ljava/lang/Throwable;)Z
      //   174: istore_3
      //   175: iload_3
      //   176: ireturn
      //   177: astore_1
      //   178: aload_1
      //   179: athrow
      //   180: astore_1
      //   181: aload_1
      //   182: athrow
      // Local variable table:
      //   start	length	slot	name	signature
      //   0	183	0	this	rgrgrg
      //   0	183	1	paramThrowable	Throwable
      //   25	94	2	i	int
      //   17	159	3	bool	boolean
      //   4	158	4	localObject	Object
      // Exception table:
      //   from	to	target	type
      //   0	6	177	java/lang/Exception
      //   68	74	177	java/lang/Exception
      //   79	85	177	java/lang/Exception
      //   95	104	177	java/lang/Exception
      //   151	167	177	java/lang/Exception
      //   11	18	180	java/lang/Exception
      //   89	95	180	java/lang/Exception
      //   169	175	180	java/lang/Exception
    }
    
    public boolean b04300430ааааа043004300430(@NonNull uuunun paramUuunun)
    {
      int i = b0428ШШ04280428ШШШ0428;
      switch (i * (b04280428Ш04280428ШШШ0428 + i) % bШШ042804280428ШШШ0428)
      {
      default: 
        b0428ШШ04280428ШШШ0428 = 61;
        bШ0428Ш04280428ШШШ0428 = 30;
      }
      i = b0428ШШ04280428ШШШ0428;
      switch (i * (b04280428Ш04280428ШШШ0428 + i) % bШШ042804280428ШШШ0428)
      {
      default: 
        b0428ШШ04280428ШШШ0428 = 91;
        bШ0428Ш04280428ШШШ0428 = 6;
      }
      return false;
    }
    
    public boolean bИИ04180418И0418И0418ИИ(@NonNull Throwable paramThrowable)
    {
      if ((b0428ШШ04280428ШШШ0428 + b04280428Ш04280428ШШШ0428) * b0428ШШ04280428ШШШ0428 % bШШ042804280428ШШШ0428 != bШ0428Ш04280428ШШШ0428)
      {
        b0428ШШ04280428ШШШ0428 = 34;
        bШ0428Ш04280428ШШШ0428 = b041804180418ИИ0418И0418ИИ();
        int i = b0428ШШ04280428ШШШ0428;
        switch (i * (bИ04180418ИИ0418И0418ИИ() + i) % bШШ042804280428ШШШ0428)
        {
        default: 
          b0428ШШ04280428ШШШ0428 = 5;
          bШ0428Ш04280428ШШШ0428 = b041804180418ИИ0418И0418ИИ();
        }
      }
      return false;
    }
    
    /* Error */
    public final void bИИ0418ИИ0418И0418ИИ(@NonNull Throwable paramThrowable)
    {
      // Byte code:
      //   0: aload_0
      //   1: aload_1
      //   2: invokevirtual 153	kkkkkk/rgrrrg$rgrgrg:b0418ИИ0418И0418И0418ИИ	(Ljava/lang/Throwable;)Z
      //   5: ifne +88 -> 93
      //   8: invokestatic 58	kkkkkk/rgrrrg$rgrgrg:b041804180418ИИ0418И0418ИИ	()I
      //   11: istore_2
      //   12: getstatic 52	kkkkkk/rgrrrg$rgrgrg:b04280428Ш04280428ШШШ0428	I
      //   15: istore_3
      //   16: invokestatic 58	kkkkkk/rgrrrg$rgrgrg:b041804180418ИИ0418И0418ИИ	()I
      //   19: istore 4
      //   21: getstatic 54	kkkkkk/rgrrrg$rgrgrg:bШШ042804280428ШШШ0428	I
      //   24: istore 5
      //   26: getstatic 56	kkkkkk/rgrrrg$rgrgrg:bШ0428Ш04280428ШШШ0428	I
      //   29: istore 6
      //   31: iload_2
      //   32: iload_3
      //   33: iadd
      //   34: iload 4
      //   36: imul
      //   37: iload 5
      //   39: irem
      //   40: iload 6
      //   42: if_icmpeq +13 -> 55
      //   45: bipush 91
      //   47: putstatic 50	kkkkkk/rgrrrg$rgrgrg:b0428ШШ04280428ШШШ0428	I
      //   50: bipush 58
      //   52: putstatic 56	kkkkkk/rgrrrg$rgrgrg:bШ0428Ш04280428ШШШ0428	I
      //   55: ldc -101
      //   57: bipush 118
      //   59: iconst_2
      //   60: invokestatic 161	kkkkkk/gguuuu:bккккк043Aкк043A043A	(Ljava/lang/String;CC)Ljava/lang/String;
      //   63: astore 7
      //   65: aload_1
      //   66: aload 7
      //   68: iconst_0
      //   69: anewarray 5	java/lang/Object
      //   72: invokestatic 167	kkkkkk/ooooio:b0430аа0430а04300430ааа	(Ljava/lang/Throwable;Ljava/lang/String;[Ljava/lang/Object;)V
      //   75: aload_0
      //   76: getfield 25	kkkkkk/rgrrrg$rgrgrg:bШШШ04280428ШШШ0428	Lkkkkkk/rgrrrg;
      //   79: getfield 62	kkkkkk/rgrrrg:b042804280428ШШ042804280428Ш	Lkkkkkk/gggggr$grrrrg;
      //   82: checkcast 64	kkkkkk/rgrrrg$ggrgrg
      //   85: getstatic 172	com/mobile/ui/R$string:message_hc_029	I
      //   88: invokeinterface 175 2 0
      //   93: return
      //   94: astore_1
      //   95: aload_1
      //   96: athrow
      //   97: astore_1
      //   98: aload_1
      //   99: athrow
      // Local variable table:
      //   start	length	slot	name	signature
      //   0	100	0	this	rgrgrg
      //   0	100	1	paramThrowable	Throwable
      //   11	23	2	i	int
      //   15	19	3	j	int
      //   19	18	4	k	int
      //   24	16	5	m	int
      //   29	14	6	n	int
      //   63	4	7	str	String
      // Exception table:
      //   from	to	target	type
      //   0	31	94	java/lang/Exception
      //   65	93	94	java/lang/Exception
      //   45	55	97	java/lang/Exception
      //   55	65	97	java/lang/Exception
    }
    
    public boolean bИИИ0418И0418И0418ИИ(@NonNull pdddpp paramPdddpp)
    {
      int i = b0428ШШ04280428ШШШ0428;
      switch (i * (b04280428Ш04280428ШШШ0428 + i) % bШШ042804280428ШШШ0428)
      {
      default: 
        b0428ШШ04280428ШШШ0428 = b041804180418ИИ0418И0418ИИ();
        bШ0428Ш04280428ШШШ0428 = 91;
      }
      switch (0)
      {
      case 1: 
      default: 
        for (;;)
        {
          switch (1)
          {
          }
        }
      }
      switch (0)
      {
      case 1: 
      default: 
        for (;;)
        {
          i = b0428ШШ04280428ШШШ0428;
          switch (i * (b04280428Ш04280428ШШШ0428 + i) % bШШ042804280428ШШШ0428)
          {
          default: 
            b0428ШШ04280428ШШШ0428 = b041804180418ИИ0418И0418ИИ();
            bШ0428Ш04280428ШШШ0428 = b041804180418ИИ0418И0418ИИ();
          }
          switch (0)
          {
          }
        }
      }
      return false;
    }
  }
}
