package kkkkkk;

public abstract class rmmmmm
  implements vvovvo
{
  public static int b044104410441сс0441044104410441 = 88;
  public static int b0441сс0441с0441044104410441 = 2;
  public static int bс0441с0441с0441044104410441 = 0;
  public static int bссс0441с0441044104410441 = 1;
  public final String b0441с0441сс0441044104410441;
  public final String bс04410441сс0441044104410441;
  
  public rmmmmm(String paramString1, String paramString2)
  {
    this.bс04410441сс0441044104410441 = paramString1;
    this.b0441с0441сс0441044104410441 = paramString2;
  }
  
  public static int b0428ШШШШШШ0428ШШ()
  {
    return 53;
  }
  
  public static int bШ0428ШШШШШ0428ШШ()
  {
    return 2;
  }
  
  public static int bШШШШШШШ0428ШШ()
  {
    return 1;
  }
  
  public void b0428042804280428042804280428ШШШ()
  {
    if ((b044104410441сс0441044104410441 + bссс0441с0441044104410441) * b044104410441сс0441044104410441 % b0441сс0441с0441044104410441 != bс0441с0441с0441044104410441)
    {
      b044104410441сс0441044104410441 = 96;
      bс0441с0441с0441044104410441 = 89;
    }
    switch (1)
    {
    case 0: 
    default: 
      for (;;)
      {
        switch (1)
        {
        }
      }
    }
  }
  
  public void b042804280428ШШШШ0428ШШ(oooovv paramOooovv) {}
  
  public void b04280428ШШШШШ0428ШШ(oovovv paramOovovv)
  {
    switch (1)
    {
    case 0: 
    default: 
      for (;;)
      {
        if ((b0428ШШШШШШ0428ШШ() + bШШШШШШШ0428ШШ()) * b0428ШШШШШШ0428ШШ() % b0441сс0441с0441044104410441 != bс0441с0441с0441044104410441)
        {
          b044104410441сс0441044104410441 = 94;
          bс0441с0441с0441044104410441 = 49;
        }
        switch (0)
        {
        case 1: 
        default: 
          for (;;)
          {
            switch (0)
            {
            }
          }
        }
        switch (1)
        {
        }
      }
    }
  }
  
  public void b0428Ш0428ШШШШ0428ШШ(ovoovv paramOvoovv)
  {
    int i = b044104410441сс0441044104410441;
    switch (i * (bШШШШШШШ0428ШШ() + i) % b0441сс0441с0441044104410441)
    {
    default: 
      b044104410441сс0441044104410441 = 25;
      bс0441с0441с0441044104410441 = 73;
    }
    switch (0)
    {
    case 1: 
    default: 
      for (;;)
      {
        switch (1)
        {
        case 0: 
        default: 
          for (;;)
          {
            switch (1)
            {
            }
          }
        }
        switch (0)
        {
        }
      }
    }
  }
  
  public void bШ042804280428042804280428ШШШ() {}
  
  public void bШ04280428ШШШШ0428ШШ(vooovv paramVooovv)
  {
    int i = b0428ШШШШШШ0428ШШ();
    switch (i * (bШШШШШШШ0428ШШ() + i) % bШ0428ШШШШШ0428ШШ())
    {
    default: 
      b044104410441сс0441044104410441 = b0428ШШШШШШ0428ШШ();
      bс0441с0441с0441044104410441 = 96;
    }
    switch (1)
    {
    case 0: 
    default: 
      for (;;)
      {
        switch (1)
        {
        }
      }
    }
    switch (0)
    {
    case 1: 
    default: 
      for (;;)
      {
        switch (0)
        {
        }
      }
    }
  }
  
  public void bШШ0428ШШШШ0428ШШ(vvoovv paramVvoovv)
  {
    switch (1)
    {
    case 0: 
    default: 
      for (;;)
      {
        if ((b044104410441сс0441044104410441 + bссс0441с0441044104410441) * b044104410441сс0441044104410441 % b0441сс0441с0441044104410441 != bс0441с0441с0441044104410441)
        {
          b044104410441сс0441044104410441 = b0428ШШШШШШ0428ШШ();
          bс0441с0441с0441044104410441 = 48;
        }
        switch (1)
        {
        }
      }
    }
  }
  
  /* Error */
  public String toString()
  {
    // Byte code:
    //   0: getstatic 35	kkkkkk/rmmmmm:b044104410441сс0441044104410441	I
    //   3: istore_1
    //   4: getstatic 37	kkkkkk/rmmmmm:bссс0441с0441044104410441	I
    //   7: istore_2
    //   8: getstatic 35	kkkkkk/rmmmmm:b044104410441сс0441044104410441	I
    //   11: istore_3
    //   12: getstatic 39	kkkkkk/rmmmmm:b0441сс0441с0441044104410441	I
    //   15: istore 4
    //   17: getstatic 41	kkkkkk/rmmmmm:bс0441с0441с0441044104410441	I
    //   20: istore 5
    //   22: iload_1
    //   23: iload_2
    //   24: iadd
    //   25: iload_3
    //   26: imul
    //   27: iload 4
    //   29: irem
    //   30: iload 5
    //   32: if_icmpeq +47 -> 79
    //   35: invokestatic 47	kkkkkk/rmmmmm:b0428ШШШШШШ0428ШШ	()I
    //   38: getstatic 37	kkkkkk/rmmmmm:bссс0441с0441044104410441	I
    //   41: iadd
    //   42: invokestatic 47	kkkkkk/rmmmmm:b0428ШШШШШШ0428ШШ	()I
    //   45: imul
    //   46: getstatic 39	kkkkkk/rmmmmm:b0441сс0441с0441044104410441	I
    //   49: irem
    //   50: getstatic 41	kkkkkk/rmmmmm:bс0441с0441с0441044104410441	I
    //   53: if_icmpeq +13 -> 66
    //   56: bipush 40
    //   58: putstatic 35	kkkkkk/rmmmmm:b044104410441сс0441044104410441	I
    //   61: bipush 86
    //   63: putstatic 41	kkkkkk/rmmmmm:bс0441с0441с0441044104410441	I
    //   66: invokestatic 47	kkkkkk/rmmmmm:b0428ШШШШШШ0428ШШ	()I
    //   69: istore_1
    //   70: iload_1
    //   71: putstatic 35	kkkkkk/rmmmmm:b044104410441сс0441044104410441	I
    //   74: bipush 56
    //   76: putstatic 41	kkkkkk/rmmmmm:bс0441с0441с0441044104410441	I
    //   79: aload_0
    //   80: getfield 25	kkkkkk/rmmmmm:bс04410441сс0441044104410441	Ljava/lang/String;
    //   83: astore 6
    //   85: aload 6
    //   87: areturn
    //   88: astore 6
    //   90: aload 6
    //   92: athrow
    //   93: astore 6
    //   95: aload 6
    //   97: athrow
    //   98: astore 6
    //   100: aload 6
    //   102: athrow
    // Local variable table:
    //   start	length	slot	name	signature
    //   0	103	0	this	rmmmmm
    //   3	68	1	i	int
    //   7	18	2	j	int
    //   11	16	3	k	int
    //   15	15	4	m	int
    //   20	13	5	n	int
    //   83	3	6	str	String
    //   88	3	6	localException1	Exception
    //   93	3	6	localException2	Exception
    //   98	3	6	localException3	Exception
    // Exception table:
    //   from	to	target	type
    //   79	85	88	java/lang/Exception
    //   70	79	93	java/lang/Exception
    //   90	93	93	java/lang/Exception
    //   0	22	98	java/lang/Exception
    //   66	70	98	java/lang/Exception
  }
}
