package kkkkkk;

import android.app.AlertDialog;
import android.content.Context;
import android.widget.Toast;
import com.liveperson.infra.messaging_ui.R.string;

public class rnrrrn
{
  public static int b04370437043704370437зз0437з = 97;
  public static int b0437зззз0437з0437з = 2;
  public static int bз0437ззз0437з0437з = 0;
  public static int bззззз0437з0437з = 1;
  private kkyykk bз0437043704370437зз0437з;
  
  public rnrrrn(kkyykk paramKkyykk)
  {
    this.bз0437043704370437зз0437з = paramKkyykk;
  }
  
  private void b0438043804380438ии043804380438и(Context paramContext, bbhbhh paramBbhbhh)
  {
    if (paramBbhbhh == null) {}
    do
    {
      return;
      switch (rnrrrn.7.b043704370437ззз04370437з[paramBbhbhh.ordinal()])
      {
      }
    } while ((b04370437043704370437зз0437з + bззззз0437з0437з) * b04370437043704370437зз0437з % b0438ии0438ии043804380438и() == bз0437ззз0437з0437з);
    b04370437043704370437зз0437з = bиии0438ии043804380438и();
    bз0437ззз0437з0437з = 58;
    int i = b04370437043704370437зз0437з;
    switch (i * (bззззз0437з0437з + i) % b0437зззз0437з0437з)
    {
    }
    b04370437043704370437зз0437з = bиии0438ии043804380438и();
    bз0437ззз0437з0437з = bиии0438ии043804380438и();
    return;
    b04380438и0438ии043804380438и(paramContext);
    return;
    bи043804380438ии043804380438и(paramContext);
  }
  
  public static int b043804380438иии043804380438и()
  {
    return 1;
  }
  
  public static int b0438ии0438ии043804380438и()
  {
    return 2;
  }
  
  private boolean bи0438и0438ии043804380438и(String paramString, Context paramContext)
  {
    try
    {
      mcmccc localMcmccc = this.bз0437043704370437зз0437з.bььььь044Cь044Cь;
      if ((b04370437043704370437зз0437з + bззззз0437з0437з) * b04370437043704370437зз0437з % b0437зззз0437з0437з != bз0437ззз0437з0437з)
      {
        b04370437043704370437зз0437з = bиии0438ии043804380438и();
        bз0437ззз0437з0437з = bиии0438ии043804380438и();
        if ((b04370437043704370437зз0437з + bззззз0437з0437з) * b04370437043704370437зз0437з % b0437зззз0437з0437з != bз0437ззз0437з0437з)
        {
          b04370437043704370437зз0437з = 49;
          bз0437ззз0437з0437з = bиии0438ии043804380438и();
        }
      }
      try
      {
        boolean bool = localMcmccc.b0424Ф0424ФФФФФФ0424(paramString);
        if (!bool)
        {
          bи043804380438ии043804380438и(paramContext);
          return true;
        }
        bool = this.bз0437043704370437зз0437з.b044Cьь044C044Cьь044Cь.b0424Ф04240424042404240424042404240424(paramString);
        if (!bool)
        {
          switch (1)
          {
          case 0: 
          default: 
            for (;;)
            {
              switch (1)
              {
              }
            }
          }
          b04380438и0438ии043804380438и(paramContext);
          return true;
        }
      }
      catch (Exception paramString)
      {
        throw paramString;
      }
      return false;
    }
    catch (Exception paramString)
    {
      throw paramString;
    }
  }
  
  public static int bиии0438ии043804380438и()
  {
    return 31;
  }
  
  public void b04380438и0438ии043804380438и(Context paramContext)
  {
    if ((b04370437043704370437зз0437з + bззззз0437з0437з) * b04370437043704370437зз0437з % b0437зззз0437з0437з != bз0437ззз0437з0437з)
    {
      b04370437043704370437зз0437з = bиии0438ии043804380438и();
      bз0437ззз0437з0437з = 91;
    }
    switch (0)
    {
    case 1: 
    default: 
      for (;;)
      {
        switch (0)
        {
        }
      }
    }
    paramContext = Toast.makeText(paramContext, R.string.lp_no_action_not_available_toast_message, 1);
    int i = b04370437043704370437зз0437з;
    switch (i * (bззззз0437з0437з + i) % b0437зззз0437з0437з)
    {
    default: 
      b04370437043704370437зз0437з = 47;
      bз0437ззз0437з0437з = bиии0438ии043804380438и();
    }
    paramContext.show();
  }
  
  /* Error */
  public void b0438и04380438ии043804380438и(Context paramContext, String paramString1, String paramString2)
  {
    // Byte code:
    //   0: aload_0
    //   1: aload_3
    //   2: aload_1
    //   3: invokespecial 108	kkkkkk/rnrrrn:bи0438и0438ии043804380438и	(Ljava/lang/String;Landroid/content/Context;)Z
    //   6: ifeq +4 -> 10
    //   9: return
    //   10: getstatic 111	com/liveperson/infra/messaging_ui/R$string:lp_mark_as_urgent_dialog_header	I
    //   13: istore 4
    //   15: invokestatic 49	kkkkkk/rnrrrn:bиии0438ии043804380438и	()I
    //   18: istore 5
    //   20: iload 5
    //   22: getstatic 41	kkkkkk/rnrrrn:bззззз0437з0437з	I
    //   25: iload 5
    //   27: iadd
    //   28: imul
    //   29: getstatic 51	kkkkkk/rnrrrn:b0437зззз0437з0437з	I
    //   32: irem
    //   33: tableswitch	default:+19->52, 0:+29->62
    //   52: bipush 16
    //   54: putstatic 39	kkkkkk/rnrrrn:b04370437043704370437зз0437з	I
    //   57: bipush 75
    //   59: putstatic 46	kkkkkk/rnrrrn:bз0437ззз0437з0437з	I
    //   62: aload_1
    //   63: iload 4
    //   65: invokevirtual 117	android/content/Context:getString	(I)Ljava/lang/String;
    //   68: astore 6
    //   70: getstatic 39	kkkkkk/rnrrrn:b04370437043704370437зз0437з	I
    //   73: getstatic 41	kkkkkk/rnrrrn:bззззз0437з0437з	I
    //   76: iadd
    //   77: getstatic 39	kkkkkk/rnrrrn:b04370437043704370437зз0437з	I
    //   80: imul
    //   81: invokestatic 44	kkkkkk/rnrrrn:b0438ии0438ии043804380438и	()I
    //   84: irem
    //   85: getstatic 46	kkkkkk/rnrrrn:bз0437ззз0437з0437з	I
    //   88: if_icmpeq +14 -> 102
    //   91: bipush 53
    //   93: putstatic 39	kkkkkk/rnrrrn:b04370437043704370437зз0437з	I
    //   96: invokestatic 49	kkkkkk/rnrrrn:bиии0438ии043804380438и	()I
    //   99: putstatic 46	kkkkkk/rnrrrn:bз0437ззз0437з0437з	I
    //   102: getstatic 120	com/liveperson/infra/messaging_ui/R$string:lp_mark_as_urgent_dialog_message	I
    //   105: istore 4
    //   107: aload_1
    //   108: iload 4
    //   110: invokevirtual 117	android/content/Context:getString	(I)Ljava/lang/String;
    //   113: astore 7
    //   115: aload_1
    //   116: getstatic 123	com/liveperson/infra/messaging_ui/R$string:lp_ok	I
    //   119: invokevirtual 117	android/content/Context:getString	(I)Ljava/lang/String;
    //   122: astore 8
    //   124: new 125	kkkkkk/rnrrrn$1
    //   127: dup
    //   128: aload_0
    //   129: aload_2
    //   130: aload_3
    //   131: aload_1
    //   132: invokespecial 128	kkkkkk/rnrrrn$1:<init>	(Lkkkkkk/rnrrrn;Ljava/lang/String;Ljava/lang/String;Landroid/content/Context;)V
    //   135: astore_2
    //   136: getstatic 131	com/liveperson/infra/messaging_ui/R$string:lp_cancel	I
    //   139: istore 4
    //   141: aload_1
    //   142: iload 4
    //   144: invokevirtual 117	android/content/Context:getString	(I)Ljava/lang/String;
    //   147: astore_3
    //   148: new 133	kkkkkk/rnrrrn$2
    //   151: dup
    //   152: aload_0
    //   153: invokespecial 136	kkkkkk/rnrrrn$2:<init>	(Lkkkkkk/rnrrrn;)V
    //   156: astore 9
    //   158: aload_1
    //   159: aload 6
    //   161: aload 7
    //   163: aload 8
    //   165: aload_2
    //   166: aload_3
    //   167: aload 9
    //   169: invokestatic 142	kkkkkk/hbbbhb:bШШШШ042804280428Ш0428Ш	(Landroid/content/Context;Ljava/lang/String;Ljava/lang/String;Ljava/lang/String;Landroid/content/DialogInterface$OnClickListener;Ljava/lang/String;Landroid/content/DialogInterface$OnClickListener;)Landroid/app/AlertDialog;
    //   172: invokevirtual 145	android/app/AlertDialog:show	()V
    //   175: return
    //   176: astore_1
    //   177: aload_1
    //   178: athrow
    //   179: astore_1
    //   180: aload_1
    //   181: athrow
    // Local variable table:
    //   start	length	slot	name	signature
    //   0	182	0	this	rnrrrn
    //   0	182	1	paramContext	Context
    //   0	182	2	paramString1	String
    //   0	182	3	paramString2	String
    //   13	130	4	i	int
    //   18	11	5	j	int
    //   68	92	6	str1	String
    //   113	49	7	str2	String
    //   122	42	8	str3	String
    //   156	12	9	local2	rnrrrn.2
    // Exception table:
    //   from	to	target	type
    //   107	124	176	java/lang/Exception
    //   136	141	176	java/lang/Exception
    //   158	175	176	java/lang/Exception
    //   0	9	179	java/lang/Exception
    //   10	15	179	java/lang/Exception
    //   62	70	179	java/lang/Exception
    //   102	107	179	java/lang/Exception
    //   124	136	179	java/lang/Exception
    //   141	158	179	java/lang/Exception
  }
  
  public void bи043804380438ии043804380438и(Context paramContext)
  {
    int i = R.string.lp_no_network_toast_message;
    switch (1)
    {
    case 0: 
    default: 
      for (;;)
      {
        switch (0)
        {
        }
      }
    }
    int j = b04370437043704370437зз0437з;
    switch (j * (bззззз0437з0437з + j) % b0437зззз0437з0437з)
    {
    default: 
      b04370437043704370437зз0437з = 39;
      bз0437ззз0437з0437з = 83;
    }
    Toast.makeText(paramContext, i, 1).show();
  }
  
  public void bии04380438ии043804380438и(Context paramContext, String paramString1, String paramString2)
  {
    boolean bool = bи0438и0438ии043804380438и(paramString2, paramContext);
    int i = bиии0438ии043804380438и();
    int j = b043804380438иии043804380438и();
    int k = bиии0438ии043804380438и();
    int m = b0437зззз0437з0437з;
    int n = bз0437ззз0437з0437з;
    switch (1)
    {
    case 0: 
    default: 
      for (;;)
      {
        switch (1)
        {
        }
      }
    }
    if ((i + j) * k % m != n)
    {
      b04370437043704370437зз0437з = bиии0438ии043804380438и();
      bз0437ззз0437з0437з = 40;
    }
    if (bool) {
      return;
    }
    String str1 = paramContext.getString(R.string.lp_dismiss_urgent_dialog_header);
    String str2 = paramContext.getString(R.string.lp_dismiss_urgent_dialog_message);
    String str3 = paramContext.getString(R.string.lp_ok);
    paramString1 = new rnrrrn.3(this, paramString1, paramString2, paramContext);
    if ((b04370437043704370437зз0437з + b043804380438иии043804380438и()) * b04370437043704370437зз0437з % b0437зззз0437з0437з != bз0437ззз0437з0437з)
    {
      b04370437043704370437зз0437з = bиии0438ии043804380438и();
      bз0437ззз0437з0437з = bиии0438ии043804380438и();
    }
    hbbbhb.bШШШШ042804280428Ш0428Ш(paramContext, str1, str2, str3, paramString1, paramContext.getString(R.string.lp_cancel), new rnrrrn.4(this)).show();
  }
  
  /* Error */
  public void bииии0438и043804380438и(Context paramContext, String paramString1, String paramString2)
  {
    // Byte code:
    //   0: getstatic 39	kkkkkk/rnrrrn:b04370437043704370437зз0437з	I
    //   3: getstatic 41	kkkkkk/rnrrrn:bззззз0437з0437з	I
    //   6: iadd
    //   7: getstatic 39	kkkkkk/rnrrrn:b04370437043704370437зз0437з	I
    //   10: imul
    //   11: getstatic 51	kkkkkk/rnrrrn:b0437зззз0437з0437з	I
    //   14: irem
    //   15: getstatic 46	kkkkkk/rnrrrn:bз0437ззз0437з0437з	I
    //   18: if_icmpeq +14 -> 32
    //   21: invokestatic 49	kkkkkk/rnrrrn:bиии0438ии043804380438и	()I
    //   24: putstatic 39	kkkkkk/rnrrrn:b04370437043704370437зз0437з	I
    //   27: bipush 72
    //   29: putstatic 46	kkkkkk/rnrrrn:bз0437ззз0437з0437з	I
    //   32: aload_0
    //   33: aload_3
    //   34: aload_1
    //   35: invokespecial 108	kkkkkk/rnrrrn:bи0438и0438ии043804380438и	(Ljava/lang/String;Landroid/content/Context;)Z
    //   38: ifeq +12 -> 50
    //   41: return
    //   42: astore_1
    //   43: invokestatic 49	kkkkkk/rnrrrn:bиии0438ии043804380438и	()I
    //   46: putstatic 39	kkkkkk/rnrrrn:b04370437043704370437зз0437з	I
    //   49: return
    //   50: aload_1
    //   51: getstatic 167	com/liveperson/infra/messaging_ui/R$string:lp_end_conversation	I
    //   54: invokevirtual 117	android/content/Context:getString	(I)Ljava/lang/String;
    //   57: astore 5
    //   59: aload_1
    //   60: getstatic 170	com/liveperson/infra/messaging_ui/R$string:lp_mark_as_resolved_dialog_message	I
    //   63: invokevirtual 117	android/content/Context:getString	(I)Ljava/lang/String;
    //   66: astore 6
    //   68: aload_1
    //   69: getstatic 173	com/liveperson/infra/messaging_ui/R$string:lp_end	I
    //   72: invokevirtual 117	android/content/Context:getString	(I)Ljava/lang/String;
    //   75: astore 7
    //   77: new 175	kkkkkk/rnrrrn$5
    //   80: dup
    //   81: aload_0
    //   82: aload_2
    //   83: aload_3
    //   84: aload_1
    //   85: invokespecial 176	kkkkkk/rnrrrn$5:<init>	(Lkkkkkk/rnrrrn;Ljava/lang/String;Ljava/lang/String;Landroid/content/Context;)V
    //   88: astore_2
    //   89: aload_1
    //   90: getstatic 131	com/liveperson/infra/messaging_ui/R$string:lp_cancel	I
    //   93: invokevirtual 117	android/content/Context:getString	(I)Ljava/lang/String;
    //   96: astore_3
    //   97: new 178	kkkkkk/rnrrrn$6
    //   100: dup
    //   101: aload_0
    //   102: invokespecial 179	kkkkkk/rnrrrn$6:<init>	(Lkkkkkk/rnrrrn;)V
    //   105: astore 8
    //   107: iconst_1
    //   108: tableswitch	default:+24->132, 0:+-1->107, 1:+51->159
    //   132: iconst_1
    //   133: tableswitch	default:+23->156, 0:+-26->107, 1:+26->159
    //   156: goto -24 -> 132
    //   159: aload_1
    //   160: aload 5
    //   162: aload 6
    //   164: aload 7
    //   166: aload_2
    //   167: aload_3
    //   168: aload 8
    //   170: invokestatic 142	kkkkkk/hbbbhb:bШШШШ042804280428Ш0428Ш	(Landroid/content/Context;Ljava/lang/String;Ljava/lang/String;Ljava/lang/String;Landroid/content/DialogInterface$OnClickListener;Ljava/lang/String;Landroid/content/DialogInterface$OnClickListener;)Landroid/app/AlertDialog;
    //   173: invokevirtual 145	android/app/AlertDialog:show	()V
    //   176: iconst_0
    //   177: istore 4
    //   179: iload 4
    //   181: iconst_0
    //   182: idiv
    //   183: istore 4
    //   185: goto -6 -> 179
    // Local variable table:
    //   start	length	slot	name	signature
    //   0	188	0	this	rnrrrn
    //   0	188	1	paramContext	Context
    //   0	188	2	paramString1	String
    //   0	188	3	paramString2	String
    //   177	7	4	i	int
    //   57	104	5	str1	String
    //   66	97	6	str2	String
    //   75	90	7	str3	String
    //   105	64	8	local6	rnrrrn.6
    // Exception table:
    //   from	to	target	type
    //   179	185	42	java/lang/Exception
  }
}
