package kkkkkk;

import javax.inject.Inject;

public class rrffff
{
  private static final String b0442044204420442044204420442т04420442 = "\f\032\017z060>87\030A6?C\031=>MAPQ\016#PPIMWS";
  private static final String b0442044204420442ттт044204420442 = "4ZTb\\[\027Haiia\035Ltmcgu$X{jkn}~";
  private static final String b044204420442т044204420442т04420442 = "3SYe";
  public static int b044204420442т0442тт044204420442 = 0;
  private static final String b044204420442тттт044204420442 = "W\001u~\0037Y}~\016\002\021\022";
  private static final String b04420442т0442044204420442т04420442 = "HnhvpoLpq\001t\004\005";
  private static final String b04420442т0442ттт044204420442 = "1UMYQN\b7NTRH\002/UL@BNz :ACKG9";
  private static final String b04420442ттттт044204420442 = "q}pZ\016\022\n\026\016\013i\021\004\013\r`\003\002\017\001\016\rGj\fxwx\006\005";
  private static final String b0442т04420442044204420442т04420442 = "[\002{\n\004\003>`\005\006\025\t\030\031";
  private static final String b0442т04420442ттт044204420442 = "6ZR^VS\r<SYWM\0074ZQEGS%?FHPL>";
  private static final String b0442т0442т044204420442т04420442 = gguuuu.bк043Aккк043Aкк043A043A(b0442т0442т044204420442т04420442, 'V', 'Ù', '\001');
  public static int b0442т0442т0442тт044204420442 = 1;
  private static final String b0442т0442тттт044204420442 = "Hldphe\037Neki_\031FlcWYe";
  private static final String b0442тт0442044204420442т04420442 = "\004/-$&.(Y\t &$\032S\001'\036\022\024 ";
  private static final String b0442тт0442ттт044204420442 = "'KCOGD}-AMMHF8Bt\0308F29;Al\024:7.";
  private static final String b0442ттт0442тт044204420442 = "\0237/;30i\031064*c\0217.\"$0\\\0170\035\034\035*)";
  private static final String b0442тттттт044204420442 = "\003'\037+# Y}%\030\037!Ss\026\025\"\024! ";
  private static final String bт044204420442044204420442т04420442 = "\025BB;?IEx/K@>RD&ODMQ\006(LM\\P_`";
  private static final String bт044204420442ттт044204420442 = "p\025\r\031\021\016Gv\016\024\022\bAn\025\f\002\016:k}\013\f\002\t";
  private static final String bт04420442т044204420442т04420442 = gguuuu.bк043Aккк043Aкк043A043A(bт04420442т044204420442т04420442, ',', 'Ò', '\003');
  public static int bт04420442т0442тт044204420442 = 2;
  private static final String bт04420442тттт044204420442 = "u\030\027$\026#\"";
  private static final String bт0442т0442044204420442т04420442 = "r  \031\035'#V\b!))!\\\f4-#'5";
  private static final String bт0442т0442ттт044204420442 = "g{\b\b\003\001r|/Rr\001lsu{";
  private static final String bт0442ттттт044204420442 = "\021:/8<p'C86J<w,O>?BQR%KVTQG`";
  private static final String bтт04420442044204420442т04420442 = "\006,&4.-h\013/0?3BC";
  private static final String bтт04420442ттт044204420442 = "E_fhpl^";
  public static int bтт0442т0442тт044204420442 = 58;
  private static final String bтт0442тттт044204420442 = "v\035\027%\037\036Y\013$,,$_\01770&*8";
  private static final String bттт0442044204420442т04420442 = "z\007yc\027\033\023\037\027\024}\025\033\031\017v\035\024\b\n\026Qf\005\t\023";
  private static final String bттт0442ттт044204420442 = "Xqyyq";
  private static final String bтттт0442тт044204420442 = ",O>?BQR";
  private static final String bттттттт044204420442 = "Fjbnfc\035Ah[bd\0277YXeWdc";
  private final rgrggg b04420442тт0442тт044204420442;
  private final nuuuuu bт0442тт0442тт044204420442;
  
  static
  {
    b044204420442т044204420442т04420442 = gguuuu.bк043Aккк043Aкк043A043A(b044204420442т044204420442т04420442, 'g', '', '\003');
    bттт0442044204420442т04420442 = gguuuu.bккккк043Aкк043A043A(bттт0442044204420442т04420442, '£', '\003');
    b0442тт0442044204420442т04420442 = gguuuu.bккккк043Aкк043A043A(b0442тт0442044204420442т04420442, '\025', '\002');
    bт0442т0442044204420442т04420442 = gguuuu.bк043Aккк043Aкк043A043A(bт0442т0442044204420442т04420442, '', '§', '\003');
    b04420442т0442044204420442т04420442 = gguuuu.bк043Aккк043Aкк043A043A(b04420442т0442044204420442т04420442, 'G', 'B', '\001');
    bтт04420442044204420442т04420442 = gguuuu.bк043Aккк043Aкк043A043A(bтт04420442044204420442т04420442, '\t', 'Å', '\001');
    b0442т04420442044204420442т04420442 = gguuuu.bккккк043Aкк043A043A(b0442т04420442044204420442т04420442, '\b', '\001');
    bт044204420442044204420442т04420442 = gguuuu.bк043Aккк043Aкк043A043A(bт044204420442044204420442т04420442, 'å', '', '\001');
    b0442044204420442044204420442т04420442 = gguuuu.bк043Aккк043Aкк043A043A(b0442044204420442044204420442т04420442, '«', 'â', '\001');
    bттттттт044204420442 = gguuuu.bккккк043Aкк043A043A(bттттттт044204420442, '>', '\003');
    b0442тттттт044204420442 = gguuuu.bккккк043Aкк043A043A(b0442тттттт044204420442, ' ', '\003');
    bт0442ттттт044204420442 = gguuuu.bккккк043Aкк043A043A(bт0442ттттт044204420442, 'K', '\000');
    b04420442ттттт044204420442 = gguuuu.bккккк043Aкк043A043A(b04420442ттттт044204420442, '', '\002');
    bтт0442тттт044204420442 = gguuuu.bккккк043Aкк043A043A(bтт0442тттт044204420442, '\021', '\001');
    b0442т0442тттт044204420442 = gguuuu.bккккк043Aкк043A043A(b0442т0442тттт044204420442, 'S', '\002');
    bт04420442тттт044204420442 = gguuuu.bккккк043Aкк043A043A(bт04420442тттт044204420442, 'ä', '\003');
    b044204420442тттт044204420442 = gguuuu.bккккк043Aкк043A043A(b044204420442тттт044204420442, '\006', '\001');
    bттт0442ттт044204420442 = gguuuu.bккккк043Aкк043A043A(bттт0442ттт044204420442, '-', '\001');
    b0442тт0442ттт044204420442 = gguuuu.bккккк043Aкк043A043A(b0442тт0442ттт044204420442, '\016', '\003');
    String str = gguuuu.bк043Aккк043Aкк043A043A(bт0442т0442ттт044204420442, 'k', '\003', '\000');
    switch (1)
    {
    case 0: 
    default: 
      for (;;)
      {
        switch (0)
        {
        }
      }
    }
    bт0442т0442ттт044204420442 = str;
    b04420442т0442ттт044204420442 = gguuuu.bккккк043Aкк043A043A(b04420442т0442ттт044204420442, '\006', '\002');
    bтт04420442ттт044204420442 = gguuuu.bккккк043Aкк043A043A(bтт04420442ттт044204420442, '\001', '\005');
    b0442т04420442ттт044204420442 = gguuuu.bккккк043Aкк043A043A(b0442т04420442ттт044204420442, 'F', '\003');
    str = gguuuu.bккккк043Aкк043A043A(bт044204420442ттт044204420442, 'ï', '\002');
    if ((bтт0442т0442тт044204420442 + b0442т0442т0442тт044204420442) * bтт0442т0442тт044204420442 % bт04420442т0442тт044204420442 != b044204420442т0442тт044204420442)
    {
      bтт0442т0442тт044204420442 = b0448шшшш0448шш0448ш();
      b044204420442т0442тт044204420442 = b0448шшшш0448шш0448ш();
    }
    bт044204420442ттт044204420442 = str;
    b0442044204420442ттт044204420442 = gguuuu.bккккк043Aкк043A043A(b0442044204420442ттт044204420442, '·', '\004');
    bтттт0442тт044204420442 = gguuuu.bккккк043Aкк043A043A(bтттт0442тт044204420442, '«', '\004');
    b0442ттт0442тт044204420442 = gguuuu.bк043Aккк043Aкк043A043A(b0442ттт0442тт044204420442, '', '', '\002');
    int i = bтт0442т0442тт044204420442;
    switch (i * (b0442т0442т0442тт044204420442 + i) % bш0448шшш0448шш0448ш())
    {
    default: 
      bтт0442т0442тт044204420442 = b0448шшшш0448шш0448ш();
      b044204420442т0442тт044204420442 = 22;
    }
  }
  
  @Inject
  public rrffff(nuuuuu paramNuuuuu, rgrggg paramRgrggg)
  {
    this.bт0442тт0442тт044204420442 = paramNuuuuu;
    this.b04420442тт0442тт044204420442 = paramRgrggg;
  }
  
  public static int b04480448шшш0448шш0448ш()
  {
    return 1;
  }
  
  public static int b0448шшшш0448шш0448ш()
  {
    return 18;
  }
  
  public static int bш0448шшш0448шш0448ш()
  {
    return 2;
  }
  
  public static int bшшшшш0448шш0448ш()
  {
    return 0;
  }
  
  /* Error */
  public void b044804480448шш0448шш0448ш()
  {
    // Byte code:
    //   0: getstatic 171	kkkkkk/rrffff:bтт0442т0442тт044204420442	I
    //   3: istore_1
    //   4: getstatic 173	kkkkkk/rrffff:b0442т0442т0442тт044204420442	I
    //   7: istore_2
    //   8: getstatic 175	kkkkkk/rrffff:bт04420442т0442тт044204420442	I
    //   11: istore_3
    //   12: iload_1
    //   13: iload_2
    //   14: iload_1
    //   15: iadd
    //   16: imul
    //   17: iload_3
    //   18: irem
    //   19: tableswitch	default:+17->36, 0:+72->91
    //   36: invokestatic 181	kkkkkk/rrffff:b0448шшшш0448шш0448ш	()I
    //   39: putstatic 171	kkkkkk/rrffff:bтт0442т0442тт044204420442	I
    //   42: invokestatic 181	kkkkkk/rrffff:b0448шшшш0448шш0448ш	()I
    //   45: putstatic 177	kkkkkk/rrffff:b044204420442т0442тт044204420442	I
    //   48: getstatic 171	kkkkkk/rrffff:bтт0442т0442тт044204420442	I
    //   51: istore_1
    //   52: iload_1
    //   53: getstatic 173	kkkkkk/rrffff:b0442т0442т0442тт044204420442	I
    //   56: iload_1
    //   57: iadd
    //   58: imul
    //   59: getstatic 175	kkkkkk/rrffff:bт04420442т0442тт044204420442	I
    //   62: irem
    //   63: tableswitch	default:+17->80, 0:+28->91
    //   80: invokestatic 181	kkkkkk/rrffff:b0448шшшш0448шш0448ш	()I
    //   83: putstatic 171	kkkkkk/rrffff:bтт0442т0442тт044204420442	I
    //   86: bipush 97
    //   88: putstatic 177	kkkkkk/rrffff:b044204420442т0442тт044204420442	I
    //   91: aload_0
    //   92: getfield 200	kkkkkk/rrffff:b04420442тт0442тт044204420442	Lkkkkkk/rgrggg;
    //   95: astore 4
    //   97: aload 4
    //   99: ldc -48
    //   101: bipush 70
    //   103: iconst_4
    //   104: invokestatic 125	kkkkkk/gguuuu:bккккк043Aкк043A043A	(Ljava/lang/String;CC)Ljava/lang/String;
    //   107: invokevirtual 214	kkkkkk/rgrggg:b04180418И04180418041804180418ИИ	(Ljava/lang/CharSequence;)V
    //   110: return
    //   111: astore 4
    //   113: aload 4
    //   115: athrow
    //   116: astore 4
    //   118: aload 4
    //   120: athrow
    //   121: astore 4
    //   123: aload 4
    //   125: athrow
    //   126: astore 4
    //   128: aload 4
    //   130: athrow
    // Local variable table:
    //   start	length	slot	name	signature
    //   0	131	0	this	rrffff
    //   3	56	1	i	int
    //   7	9	2	j	int
    //   11	8	3	k	int
    //   95	3	4	localRgrggg	rgrggg
    //   111	3	4	localException1	Exception
    //   116	3	4	localException2	Exception
    //   121	3	4	localException3	Exception
    //   126	3	4	localException4	Exception
    // Exception table:
    //   from	to	target	type
    //   97	110	111	java/lang/Exception
    //   0	12	116	java/lang/Exception
    //   113	116	116	java/lang/Exception
    //   91	97	121	java/lang/Exception
    //   36	48	126	java/lang/Exception
    //   123	126	126	java/lang/Exception
  }
  
  @ooiiio
  public void b04480448ш0448ш0448шш0448ш()
  {
    nuuuuu localNuuuuu = this.bт0442тт0442тт044204420442;
    uunnuu localUunnuu = uunnuu.SERVICE;
    nunnuu localNunnuu = nunnuu.SETTINGS;
    int i = bтт0442т0442тт044204420442;
    switch (i * (b0442т0442т0442тт044204420442 + i) % bт04420442т0442тт044204420442)
    {
    default: 
      bтт0442т0442тт044204420442 = b0448шшшш0448шш0448ш();
      b044204420442т0442тт044204420442 = b0448шшшш0448шш0448ш();
    }
    nnnuuu.ununuu localUnunuu = nnnuuu.ununuu.CHANGE_PERSONAL_DETAILS;
    nuuunu localNuuunu = nuuunu.N3_20;
    nnnuuu.nnunuu localNnunuu = nnnuuu.nnunuu.TWO;
    String str = gguuuu.bк043Aккк043Aкк043A043A(")OIWQP\f=V^^V\022AibX\\j", 'Ã', 'Ý', '\001');
    switch (1)
    {
    case 0: 
    default: 
      for (;;)
      {
        switch (1)
        {
        case 0: 
        default: 
          for (;;)
          {
            switch (0)
            {
            }
          }
        }
        switch (1)
        {
        }
      }
    }
    nuuuuu.unuuuu localUnuuuu = nuuuuu.unuuuu.b043F043F043Fп043F043Fпп043Fп(unuunu.SCREEN_NAME, gguuuu.bк043Aккк043Aкк043A043A("Lphtli#Riomc\035Jpg[]i", 'þ', 'õ', '\002'));
    i = bтт0442т0442тт044204420442;
    switch (i * (b0442т0442т0442тт044204420442 + i) % bт04420442т0442тт044204420442)
    {
    default: 
      bтт0442т0442тт044204420442 = b0448шшшш0448шш0448ш();
      b044204420442т0442тт044204420442 = b0448шшшш0448шш0448ш();
    }
    localNuuuuu.b043Fп043Fппп043Fп043Fп(localUunnuu, localNunnuu, localUnunuu, localNuuunu, localNnunuu, str, new nuuuuu.unuuuu[] { localUnuuuu, nuuuuu.unuuuu.b043F043F043Fп043F043Fпп043Fп(unuunu.JOURNEY_PRODUCT, gguuuu.bккккк043Aкк043A043A("!:BB:", '(', '\004')) });
  }
  
  @ooiiio
  public void b0448ш04480448ш0448шш0448ш(boolean paramBoolean)
  {
    if (paramBoolean) {
      if ((bтт0442т0442тт044204420442 + b0442т0442т0442тт044204420442) * bтт0442т0442тт044204420442 % bт04420442т0442тт044204420442 != b044204420442т0442тт044204420442)
      {
        bтт0442т0442тт044204420442 = b0448шшшш0448шш0448ш();
        b044204420442т0442тт044204420442 = b0448шшшш0448шш0448ш();
      }
    }
    for (Object localObject = gguuuu.bккккк043Aкк043A043A("\002#\020\017\020\035\034", 'Ð', '\005');; localObject = gguuuu.bккккк043Aкк043A043A("Ysz|\005\001r", '£', '\002'))
    {
      if (paramBoolean) {}
      for (String str1 = gguuuu.bккккк043Aкк043A043A("V|v\005~}9j\004\f\f\004?n\027\020\006\n\030Fz\036\r\016\021 !", 'I', '\004');; str1 = gguuuu.bк043Aккк043Aкк043A043A("2VNZRO\t8OUSI\0030VMACO{!;BDLH:", '\037', '', '\000'))
      {
        if (paramBoolean) {
          switch (0)
          {
          case 1: 
          default: 
            for (;;)
            {
              switch (1)
              {
              }
            }
          }
        }
        for (String str2 = gguuuu.bккккк043Aкк043A043A("0TLXPM\0076MSQG\001.TK?AMy,M:9:GF", 'Ú', '\002');; str2 = gguuuu.bккккк043Aкк043A043A("Dh`lda\033Jage[\025Bh_SUa\0163MTV^ZL", '¾', '\003'))
        {
          nuuuuu localNuuuuu = this.bт0442тт0442тт044204420442;
          uunnuu localUunnuu = uunnuu.SERVICE;
          nunnuu localNunnuu = nunnuu.SETTINGS;
          nnnuuu.ununuu localUnunuu = nnnuuu.ununuu.CHANGE_PERSONAL_DETAILS;
          nuuunu localNuuunu = nuuunu.N3_20;
          nnnuuu.nnunuu localNnunuu = nnnuuu.nnunuu.FOUR;
          nuuuuu.unuuuu localUnuuuu1 = nuuuuu.unuuuu.b043F043F043Fп043F043Fпп043Fп(unuunu.SCREEN_NAME, gguuuu.bк043Aккк043Aкк043A043A("-QIUMJ\0043JPND}+QH<>Jv(:GH>E", 'd', 'N', '\000'));
          nuuuuu.unuuuu localUnuuuu2 = nuuuuu.unuuuu.b043F043F043Fп043F043Fпп043Fп(unuunu.JOURNEY_PRODUCT, gguuuu.bккккк043Aкк043A043A("Kdlld", '=', '\004'));
          localObject = nuuuuu.unuuuu.b043F043F043Fп043F043Fпп043Fп(unuunu.JOURNEY_ACTION, (String)localObject);
          if ((bтт0442т0442тт044204420442 + b0442т0442т0442тт044204420442) * bтт0442т0442тт044204420442 % bт04420442т0442тт044204420442 != b044204420442т0442тт044204420442)
          {
            bтт0442т0442тт044204420442 = 2;
            b044204420442т0442тт044204420442 = b0448шшшш0448шш0448ш();
          }
          localNuuuuu.b043Fп043Fппп043Fп043Fп(localUunnuu, localNunnuu, localUnunuu, localNuuunu, localNnunuu, str2, new nuuuuu.unuuuu[] { localUnuuuu1, localUnuuuu2, localObject, nuuuuu.unuuuu.b043F043F043Fп043F043Fпп043Fп(unuunu.JOURNEY_ACTION_NARRATIVE, str1) });
          return;
        }
      }
    }
  }
  
  public void b0448ш0448шш0448шш0448ш()
  {
    throw new Runtime("d2j fail translate: java.lang.IndexOutOfBoundsException: fromIndex < 0: -1\n\tat java.util.BitSet.nextSetBit(BitSet.java:712)\n\tat com.googlecode.dex2jar.ir.ts.array.FillArrayTransformer.makeSureAllElementAreAssigned(FillArrayTransformer.java:505)\n\tat com.googlecode.dex2jar.ir.ts.array.FillArrayTransformer.transformReportChanged(FillArrayTransformer.java:123)\n\tat com.googlecode.dex2jar.ir.ts.StatedTransformer.transform(StatedTransformer.java:10)\n\tat com.googlecode.d2j.dex.Dex2jar$2.optimize(Dex2jar.java:149)\n\tat com.googlecode.d2j.dex.Dex2Asm.convertCode(Dex2Asm.java:414)\n\tat com.googlecode.d2j.dex.ExDex2Asm.convertCode(ExDex2Asm.java:42)\n\tat com.googlecode.d2j.dex.Dex2jar$2.convertCode(Dex2jar.java:128)\n\tat com.googlecode.d2j.dex.Dex2Asm.convertMethod(Dex2Asm.java:509)\n\tat com.googlecode.d2j.dex.Dex2Asm.convertClass(Dex2Asm.java:406)\n\tat com.googlecode.d2j.dex.Dex2Asm.convertDex(Dex2Asm.java:422)\n\tat com.googlecode.d2j.dex.Dex2jar.doTranslate(Dex2jar.java:172)\n\tat com.googlecode.d2j.dex.Dex2jar.to(Dex2jar.java:272)\n\tat com.googlecode.dex2jar.tools.Dex2jarCmd.doCommandLine(Dex2jarCmd.java:108)\n\tat com.googlecode.dex2jar.tools.BaseCmd.doMain(BaseCmd.java:288)\n\tat com.googlecode.dex2jar.tools.Dex2jarCmd.main(Dex2jarCmd.java:32)\n");
  }
  
  public void b0448шш0448ш0448шш0448ш()
  {
    nuuuuu localNuuuuu = this.bт0442тт0442тт044204420442;
    nnnuuu.nuunuu localNuunuu = nnnuuu.nuunuu.TAP;
    nnnuuu.uuunuu localUuunuu = nnnuuu.uuunuu.EMAIL_UPDATE;
    if ((bтт0442т0442тт044204420442 + b04480448шшш0448шш0448ш()) * bтт0442т0442тт044204420442 % bт04420442т0442тт044204420442 != b044204420442т0442тт044204420442)
    {
      bтт0442т0442тт044204420442 = 87;
      b044204420442т0442тт044204420442 = b0448шшшш0448шш0448ш();
    }
    String str = gguuuu.bк043Aккк043Aкк043A043A("!LJACKEv+E84F6o\024;.57i\n,+8*76", '', 'a', '\000');
    unnuuu localUnnuuu = unnuuu.CORE;
    unuunu localUnuunu = unuunu.LINK_VALUE;
    int i = bтт0442т0442тт044204420442;
    switch (i * (b0442т0442т0442тт044204420442 + i) % bт04420442т0442тт044204420442)
    {
    default: 
      bтт0442т0442тт044204420442 = b0448шшшш0448шш0448ш();
      b044204420442т0442тт044204420442 = b0448шшшш0448шш0448ш();
    }
    switch (0)
    {
    case 1: 
    default: 
      for (;;)
      {
        switch (0)
        {
        }
      }
    }
    localNuuuuu.b043F043F043F043F043F043Fпп043Fп(localNuunuu, localUuunuu, str, localUnnuuu, new nuuuuu.unuuuu[] { nuuuuu.unuuuu.b043F043F043Fп043F043Fпп043Fп(localUnuunu, gguuuu.bк043Aккк043Aкк043A043A("nzmW\013\017\007\023\013\bf\016\001\b\n]~\f}\013\nDW\003\001wy\002{", 'È', 't', '\000')) });
  }
  
  @ooiiio
  public void bш044804480448ш0448шш0448ш()
  {
    nuuuuu localNuuuuu = this.bт0442тт0442тт044204420442;
    nnnuuu.nuunuu localNuunuu = nnnuuu.nuunuu.OVERLAY;
    switch (1)
    {
    case 0: 
    default: 
      for (;;)
      {
        switch (0)
        {
        }
      }
    }
    int i = bтт0442т0442тт044204420442;
    switch (i * (b0442т0442т0442тт044204420442 + i) % bт04420442т0442тт044204420442)
    {
    default: 
      bтт0442т0442тт044204420442 = 50;
      b044204420442т0442тт044204420442 = 96;
    }
    nnnuuu.uuunuu localUuunuu = nnnuuu.uuunuu.INFORMATION;
    String str = gguuuu.bккккк043Aкк043A043A("j\024\t\022\026J\001\035\022\020$\026Q\006)\030\031\034+,Y~%0.+!:", 'Ñ', '\004');
    switch (0)
    {
    case 1: 
    default: 
      for (;;)
      {
        switch (1)
        {
        }
      }
    }
    unnuuu localUnnuuu = unnuuu.CORE;
    nuuuuu.unuuuu localUnuuuu = nuuuuu.unuuuu.b043F043F043Fп043F043Fпп043Fп(unuunu.LINK_VALUE, gguuuu.bк043Aккк043Aкк043A043A("aodP\006\f\006\024\016\rm\027\f\025\031n\023\024#\027&'c\t,\033\034\037./", 'Ð', '3', '\001'));
    i = bтт0442т0442тт044204420442;
    switch (i * (b0442т0442т0442тт044204420442 + i) % bш0448шшш0448шш0448ш())
    {
    default: 
      bтт0442т0442тт044204420442 = b0448шшшш0448шш0448ш();
      b044204420442т0442тт044204420442 = b0448шшшш0448шш0448ш();
    }
    localNuuuuu.b043F043F043F043F043F043Fпп043Fп(localNuunuu, localUuunuu, str, localUnnuuu, new nuuuuu.unuuuu[] { localUnuuuu });
  }
  
  @ooiiio
  public void bш04480448шш0448шш0448ш()
  {
    nuuuuu localNuuuuu = this.bт0442тт0442тт044204420442;
    uunnuu localUunnuu = uunnuu.SERVICE;
    nunnuu localNunnuu = nunnuu.SETTINGS;
    nnnuuu.ununuu localUnunuu = nnnuuu.ununuu.CHANGE_PERSONAL_DETAILS;
    if ((bтт0442т0442тт044204420442 + b0442т0442т0442тт044204420442) * bтт0442т0442тт044204420442 % bт04420442т0442тт044204420442 != b044204420442т0442тт044204420442)
    {
      if ((bтт0442т0442тт044204420442 + b04480448шшш0448шш0448ш()) * bтт0442т0442тт044204420442 % bт04420442т0442тт044204420442 != b044204420442т0442тт044204420442)
      {
        bтт0442т0442тт044204420442 = 38;
        b044204420442т0442тт044204420442 = 58;
      }
      bтт0442т0442тт044204420442 = 77;
      b044204420442т0442тт044204420442 = b0448шшшш0448шш0448ш();
    }
    nuuunu localNuuunu = nuuunu.N3_20;
    nnnuuu.nnunuu localNnunuu = nnnuuu.nnunuu.THREE;
    String str1 = gguuuu.bккккк043Aкк043A043A("\020==6:D@s%>FF>y)QJ@DR", 'n', '\001');
    unuunu localUnuunu = unuunu.SCREEN_NAME;
    String str2 = gguuuu.bккккк043Aкк043A043A("!LJACKEv&=CA7p\036D;/1=", '¡', '\005');
    switch (1)
    {
    case 0: 
    default: 
      for (;;)
      {
        switch (1)
        {
        }
      }
    }
    switch (1)
    {
    case 0: 
    default: 
      for (;;)
      {
        switch (0)
        {
        }
      }
    }
    localNuuuuu.b043Fп043Fппп043Fп043Fп(localUunnuu, localNunnuu, localUnunuu, localNuuunu, localNnunuu, str1, new nuuuuu.unuuuu[] { nuuuuu.unuuuu.b043F043F043Fп043F043Fпп043Fп(localUnuunu, str2), nuuuuu.unuuuu.b043F043F043Fп043F043Fпп043Fп(unuunu.JOURNEY_PRODUCT, gguuuu.bккккк043Aкк043A043A("\0376<:0", 'e', '\002')) });
  }
  
  @ooiiio
  public void bш0448ш0448ш0448шш0448ш()
  {
    try
    {
      localNuuuuu = this.bт0442тт0442тт044204420442;
      localUunnuu = uunnuu.SERVICE;
      localNunnuu = nunnuu.SETTINGS;
    }
    catch (Exception localException1)
    {
      try
      {
        nuuuuu localNuuuuu;
        uunnuu localUunnuu;
        nunnuu localNunnuu;
        nnnuuu.ununuu localUnunuu;
        nuuunu localNuuunu;
        int i;
        nnnuuu.nnunuu localNnunuu;
        String str;
        Object localObject = nuuuuu.unuuuu.b043F043F043Fп043F043Fпп043Fп((unuunu)localObject, gguuuu.bккккк043Aкк043A043A(".TN\\VU\0217`U^b\0279]^mapq", '÷', '\001'));
        if ((bтт0442т0442тт044204420442 + b0442т0442т0442тт044204420442) * bтт0442т0442тт044204420442 % bт04420442т0442тт044204420442 != bшшшшш0448шш0448ш())
        {
          bтт0442т0442тт044204420442 = b0448шшшш0448шш0448ш();
          b044204420442т0442тт044204420442 = 80;
        }
        unuunu localUnuunu = unuunu.JOURNEY_PRODUCT;
        localNuuuuu.b043Fп043Fппп043Fп043Fп(localUunnuu, localNunnuu, localUnunuu, localNuuunu, localNnunuu, str, new nuuuuu.unuuuu[] { localObject, nuuuuu.unuuuu.b043F043F043Fп043F043Fпп043Fп(localUnuunu, gguuuu.bк043Aккк043Aкк043A043A("[\005y\003\007;]\002\003\022\006\025\026", '', 'y', '\003')) });
        return;
      }
      catch (Exception localException2)
      {
        throw localException2;
      }
      localException1 = localException1;
      throw localException1;
    }
    localUnunuu = nnnuuu.ununuu.CHANGE_PERSONAL_DETAILS;
    localNuuunu = nuuunu.N3_20;
    i = bтт0442т0442тт044204420442;
    switch (i * (b0442т0442т0442тт044204420442 + i) % bт04420442т0442тт044204420442)
    {
    default: 
      bтт0442т0442тт044204420442 = b0448шшшш0448шш0448ш();
      b044204420442т0442тт044204420442 = 71;
    }
    localNnunuu = nnnuuu.nnunuu.TWO;
    str = gguuuu.bк043Aккк043Aкк043A043A("[\002{\n\004\003>d\016\003\f\020Df\013\f\033\017\036\037", '\004', 'k', '\001');
    localObject = unuunu.SCREEN_NAME;
    switch (0)
    {
    }
    for (;;)
    {
      switch (0)
      {
      }
    }
  }
  
  @ooiiio
  public void bшш04480448ш0448шш0448ш()
  {
    nuuuuu localNuuuuu = this.bт0442тт0442тт044204420442;
    if ((bтт0442т0442тт044204420442 + b0442т0442т0442тт044204420442) * bтт0442т0442тт044204420442 % bт04420442т0442тт044204420442 != b044204420442т0442тт044204420442)
    {
      bтт0442т0442тт044204420442 = 44;
      b044204420442т0442тт044204420442 = b0448шшшш0448шш0448ш();
      if ((bтт0442т0442тт044204420442 + b0442т0442т0442тт044204420442) * bтт0442т0442тт044204420442 % bт04420442т0442тт044204420442 != b044204420442т0442тт044204420442)
      {
        bтт0442т0442тт044204420442 = 93;
        b044204420442т0442тт044204420442 = b0448шшшш0448шш0448ш();
      }
    }
    uunnuu localUunnuu = uunnuu.SERVICE;
    nunnuu localNunnuu = nunnuu.SETTINGS;
    nnnuuu.ununuu localUnunuu = nnnuuu.ununuu.CHANGE_PERSONAL_DETAILS;
    nuuunu localNuuunu = nuuunu.N3_20;
    nnnuuu.nnunuu localNnunuu = nnnuuu.nnunuu.ONE;
    String str = gguuuu.bк043Aккк043Aкк043A043A(">d^lfe!Rhvxuuiu*Oq\002ox|\0052[\004\003{", 'Ü', '', '\003');
    switch (1)
    {
    case 0: 
    default: 
      for (;;)
      {
        switch (0)
        {
        }
      }
    }
    localNuuuuu.b043Fп043Fппп043Fп043Fп(localUunnuu, localNunnuu, localUnunuu, localNuuunu, localNnunuu, str, new nuuuuu.unuuuu[] { nuuuuu.unuuuu.b043F043F043Fп043F043Fпп043Fп(unuunu.SCREEN_NAME, gguuuu.bккккк043Aкк043A043A(".DRTQQEQ\006+M]KTX`", '\037', '\001')) });
  }
  
  public void bшш0448шш0448шш0448ш()
  {
    nuuuuu localNuuuuu = this.bт0442тт0442тт044204420442;
    nnnuuu.nuunuu localNuunuu = nnnuuu.nuunuu.TAP;
    nnnuuu.uuunuu localUuunuu = nnnuuu.uuunuu.PHONE_UPDATE;
    String str1 = gguuuu.bккккк043Aкк043A043A("j\030\030\021\025\037\033N\005!\026\024(\032U\007 (( [\0133,\"&4", 'S', '\004');
    unnuuu localUnnuuu = unnuuu.CORE;
    unuunu localUnuunu = unuunu.LINK_VALUE;
    int i = bтт0442т0442тт044204420442;
    switch (i * (b0442т0442т0442тт044204420442 + i) % bт04420442т0442тт044204420442)
    {
    default: 
      bтт0442т0442тт044204420442 = b0448шшшш0448шш0448ш();
      b0442т0442т0442тт044204420442 = 62;
    }
    String str2 = gguuuu.bккккк043Aкк043A043A("q}pZ\016\022\n\026\016\013t\f\022\020\006m\024\013~\001\rH[\007\005{}\006", '\033', '\002');
    switch (1)
    {
    case 0: 
    default: 
      for (;;)
      {
        switch (1)
        {
        }
      }
    }
    i = bтт0442т0442тт044204420442;
    switch (i * (b0442т0442т0442тт044204420442 + i) % bт04420442т0442тт044204420442)
    {
    default: 
      bтт0442т0442тт044204420442 = b0448шшшш0448шш0448ш();
      b0442т0442т0442тт044204420442 = 15;
    }
    localNuuuuu.b043F043F043F043F043F043Fпп043Fп(localNuunuu, localUuunuu, str1, localUnnuuu, new nuuuuu.unuuuu[] { nuuuuu.unuuuu.b043F043F043Fп043F043Fпп043Fп(localUnuunu, str2) });
  }
  
  @ooiiio
  public void bшшш0448ш0448шш0448ш()
  {
    this.bт0442тт0442тт044204420442.b043Fп043Fппп043Fп043Fп(uunnuu.SERVICE, nunnuu.SETTINGS, nnnuuu.ununuu.CHANGE_PERSONAL_DETAILS, nuuunu.N3_20, nnnuuu.nnunuu.TWO, gguuuu.bк043Aккк043Aкк043A043A("\0204,80-f\007)(5'43", 'é', 'Ç', '\002'), new nuuuuu.unuuuu[] { nuuuuu.unuuuu.b043F043F043Fп043F043Fпп043Fп(unuunu.SCREEN_NAME, gguuuu.bккккк043Aкк043A043A("{\"\034*$#^\001%&5)89", '·', '\000')), nuuuuu.unuuuu.b043F043F043Fп043F043Fпп043Fп(unuunu.JOURNEY_PRODUCT, gguuuu.bккккк043Aкк043A043A("g\n\t\026\b\025\024", 'Ç', '\002')) });
  }
}
