package kkkkkk;

import javax.inject.Inject;

public class rrggrg
{
  public static int b04280428042804280428ШШШ0428 = 1;
  public static int b0428Ш042804280428ШШШ0428 = 38;
  public static int bШ0428042804280428ШШШ0428 = 0;
  public static int bШШШШШ0428ШШ0428 = 2;
  
  @Inject
  public rrggrg() {}
  
  public static int b0418И0418И04180418И0418ИИ()
  {
    return 35;
  }
  
  public static int bИ04180418И04180418И0418ИИ()
  {
    return 2;
  }
  
  /* Error */
  public void bИИ0418И04180418И0418ИИ(android.content.Context paramContext, String paramString)
  {
    // Byte code:
    //   0: getstatic 29	kkkkkk/rrggrg:b0428Ш042804280428ШШШ0428	I
    //   3: istore_3
    //   4: iload_3
    //   5: getstatic 31	kkkkkk/rrggrg:b04280428042804280428ШШШ0428	I
    //   8: iload_3
    //   9: iadd
    //   10: imul
    //   11: invokestatic 33	kkkkkk/rrggrg:bИ04180418И04180418И0418ИИ	()I
    //   14: irem
    //   15: tableswitch	default:+17->32, 0:+29->44
    //   32: invokestatic 35	kkkkkk/rrggrg:b0418И0418И04180418И0418ИИ	()I
    //   35: putstatic 29	kkkkkk/rrggrg:b0428Ш042804280428ШШШ0428	I
    //   38: invokestatic 35	kkkkkk/rrggrg:b0418И0418И04180418И0418ИИ	()I
    //   41: putstatic 37	kkkkkk/rrggrg:bШ0428042804280428ШШШ0428	I
    //   44: aload_1
    //   45: ldc 39
    //   47: sipush 221
    //   50: iconst_1
    //   51: invokestatic 45	kkkkkk/gguuuu:bккккк043Aкк043A043A	(Ljava/lang/String;CC)Ljava/lang/String;
    //   54: invokevirtual 51	android/content/Context:getSystemService	(Ljava/lang/String;)Ljava/lang/Object;
    //   57: checkcast 53	android/view/accessibility/AccessibilityManager
    //   60: astore_1
    //   61: getstatic 29	kkkkkk/rrggrg:b0428Ш042804280428ШШШ0428	I
    //   64: getstatic 31	kkkkkk/rrggrg:b04280428042804280428ШШШ0428	I
    //   67: iadd
    //   68: getstatic 29	kkkkkk/rrggrg:b0428Ш042804280428ШШШ0428	I
    //   71: imul
    //   72: getstatic 55	kkkkkk/rrggrg:bШШШШШ0428ШШ0428	I
    //   75: irem
    //   76: getstatic 37	kkkkkk/rrggrg:bШ0428042804280428ШШШ0428	I
    //   79: if_icmpeq +14 -> 93
    //   82: bipush 34
    //   84: putstatic 29	kkkkkk/rrggrg:b0428Ш042804280428ШШШ0428	I
    //   87: invokestatic 35	kkkkkk/rrggrg:b0418И0418И04180418И0418ИИ	()I
    //   90: putstatic 37	kkkkkk/rrggrg:bШ0428042804280428ШШШ0428	I
    //   93: aload_1
    //   94: ifnull +36 -> 130
    //   97: aload_1
    //   98: invokevirtual 59	android/view/accessibility/AccessibilityManager:isEnabled	()Z
    //   101: ifeq +29 -> 130
    //   104: sipush 16384
    //   107: invokestatic 65	android/view/accessibility/AccessibilityEvent:obtain	(I)Landroid/view/accessibility/AccessibilityEvent;
    //   110: astore 4
    //   112: aload 4
    //   114: invokevirtual 69	android/view/accessibility/AccessibilityEvent:getText	()Ljava/util/List;
    //   117: aload_2
    //   118: invokeinterface 75 2 0
    //   123: pop
    //   124: aload_1
    //   125: aload 4
    //   127: invokevirtual 79	android/view/accessibility/AccessibilityManager:sendAccessibilityEvent	(Landroid/view/accessibility/AccessibilityEvent;)V
    //   130: return
    //   131: astore_1
    //   132: aload_1
    //   133: athrow
    //   134: astore_1
    //   135: aload_1
    //   136: athrow
    // Local variable table:
    //   start	length	slot	name	signature
    //   0	137	0	this	rrggrg
    //   0	137	1	paramContext	android.content.Context
    //   0	137	2	paramString	String
    //   3	8	3	i	int
    //   110	16	4	localAccessibilityEvent	android.view.accessibility.AccessibilityEvent
    // Exception table:
    //   from	to	target	type
    //   44	61	131	java/lang/Exception
    //   97	112	131	java/lang/Exception
    //   124	130	131	java/lang/Exception
    //   112	124	134	java/lang/Exception
  }
}
