package kkkkkk;

import org.json.JSONArray;

public class rrmmrr
  extends mmrmrr
{
  private static final String b044104410441ссс04410441с = ">NOLJEDXNUU\027S]ZZ";
  public static int b04410441с0441сс04410441с = bи043804380438иии043804380438();
  public static int b0441с04410441сс04410441с = 2;
  public static int bс0441с0441сс04410441с = 69;
  public static int bсс04410441сс04410441с = 1;
  private static final String bссс0441сс04410441с;
  private JSONArray b0441сс0441сс04410441с;
  
  /* Error */
  static
  {
    // Byte code:
    //   0: getstatic 26	kkkkkk/rrmmrr:b044104410441ссс04410441с	Ljava/lang/String;
    //   3: astore_0
    //   4: iconst_1
    //   5: tableswitch	default:+23->28, 0:+-1->4, 1:+50->55
    //   28: iconst_0
    //   29: tableswitch	default:+23->52, 0:+26->55, 1:+-25->4
    //   52: goto -24 -> 28
    //   55: getstatic 28	kkkkkk/rrmmrr:bс0441с0441сс04410441с	I
    //   58: getstatic 30	kkkkkk/rrmmrr:bсс04410441сс04410441с	I
    //   61: iadd
    //   62: getstatic 28	kkkkkk/rrmmrr:bс0441с0441сс04410441с	I
    //   65: imul
    //   66: getstatic 32	kkkkkk/rrmmrr:b0441с04410441сс04410441с	I
    //   69: irem
    //   70: getstatic 34	kkkkkk/rrmmrr:b04410441с0441сс04410441с	I
    //   73: if_icmpeq +48 -> 121
    //   76: getstatic 28	kkkkkk/rrmmrr:bс0441с0441сс04410441с	I
    //   79: getstatic 30	kkkkkk/rrmmrr:bсс04410441сс04410441с	I
    //   82: iadd
    //   83: getstatic 28	kkkkkk/rrmmrr:bс0441с0441сс04410441с	I
    //   86: imul
    //   87: getstatic 32	kkkkkk/rrmmrr:b0441с04410441сс04410441с	I
    //   90: irem
    //   91: getstatic 34	kkkkkk/rrmmrr:b04410441с0441сс04410441с	I
    //   94: if_icmpeq +15 -> 109
    //   97: invokestatic 38	kkkkkk/rrmmrr:bи043804380438иии043804380438	()I
    //   100: putstatic 28	kkkkkk/rrmmrr:bс0441с0441сс04410441с	I
    //   103: invokestatic 38	kkkkkk/rrmmrr:bи043804380438иии043804380438	()I
    //   106: putstatic 34	kkkkkk/rrmmrr:b04410441с0441сс04410441с	I
    //   109: invokestatic 38	kkkkkk/rrmmrr:bи043804380438иии043804380438	()I
    //   112: putstatic 28	kkkkkk/rrmmrr:bс0441с0441сс04410441с	I
    //   115: invokestatic 38	kkkkkk/rrmmrr:bи043804380438иии043804380438	()I
    //   118: putstatic 34	kkkkkk/rrmmrr:b04410441с0441сс04410441с	I
    //   121: aload_0
    //   122: sipush 239
    //   125: bipush 20
    //   127: iconst_1
    //   128: invokestatic 44	kkkkkk/gguuuu:bк043Aккк043Aкк043A043A	(Ljava/lang/String;CCC)Ljava/lang/String;
    //   131: astore_0
    //   132: aload_0
    //   133: putstatic 26	kkkkkk/rrmmrr:b044104410441ссс04410441с	Ljava/lang/String;
    //   136: ldc 2
    //   138: invokevirtual 50	java/lang/Class:getSimpleName	()Ljava/lang/String;
    //   141: putstatic 52	kkkkkk/rrmmrr:bссс0441сс04410441с	Ljava/lang/String;
    //   144: return
    //   145: astore_0
    //   146: aload_0
    //   147: athrow
    //   148: astore_0
    //   149: aload_0
    //   150: athrow
    // Local variable table:
    //   start	length	slot	name	signature
    //   3	130	0	str	String
    //   145	2	0	localException1	Exception
    //   148	2	0	localException2	Exception
    // Exception table:
    //   from	to	target	type
    //   0	4	145	java/lang/Exception
    //   121	132	145	java/lang/Exception
    //   132	144	148	java/lang/Exception
  }
  
  public rrmmrr(JSONArray paramJSONArray)
  {
    this.b0441сс0441сс04410441с = paramJSONArray;
  }
  
  public static int bи043804380438иии043804380438()
  {
    return 88;
  }
  
  public String b04380438и0438иии043804380438()
  {
    int i = bс0441с0441сс04410441с;
    int j = bсс04410441сс04410441с;
    if ((bс0441с0441сс04410441с + bсс04410441сс04410441с) * bс0441с0441сс04410441с % b0441с04410441сс04410441с != b04410441с0441сс04410441с)
    {
      bс0441с0441сс04410441с = 22;
      b04410441с0441сс04410441с = 89;
    }
    switch (i * (j + i) % b0441с04410441сс04410441с)
    {
    default: 
      bс0441с0441сс04410441с = bи043804380438иии043804380438();
      b04410441с0441сс04410441с = bи043804380438иии043804380438();
    }
    switch (0)
    {
    case 1: 
    default: 
      for (;;)
      {
        switch (0)
        {
        }
      }
    }
    try
    {
      String str = gguuuu.bк043Aккк043Aкк043A043A("`nmhd]Zl`ec#]e`^", '^', ']', '\000');
      return str;
    }
    catch (Exception localException)
    {
      throw localException;
    }
  }
  
  /* Error */
  public String b0438и04380438иии043804380438()
  {
    // Byte code:
    //   0: aload_0
    //   1: getfield 59	kkkkkk/rrmmrr:b0441сс0441сс04410441с	Lorg/json/JSONArray;
    //   4: astore 4
    //   6: aload 4
    //   8: ifnull +99 -> 107
    //   11: invokestatic 38	kkkkkk/rrmmrr:bи043804380438иии043804380438	()I
    //   14: getstatic 30	kkkkkk/rrmmrr:bсс04410441сс04410441с	I
    //   17: iadd
    //   18: invokestatic 38	kkkkkk/rrmmrr:bи043804380438иии043804380438	()I
    //   21: imul
    //   22: getstatic 32	kkkkkk/rrmmrr:b0441с04410441сс04410441с	I
    //   25: irem
    //   26: getstatic 34	kkkkkk/rrmmrr:b04410441с0441сс04410441с	I
    //   29: if_icmpeq +14 -> 43
    //   32: bipush 57
    //   34: putstatic 28	kkkkkk/rrmmrr:bс0441с0441сс04410441с	I
    //   37: invokestatic 38	kkkkkk/rrmmrr:bи043804380438иии043804380438	()I
    //   40: putstatic 34	kkkkkk/rrmmrr:b04410441с0441сс04410441с	I
    //   43: getstatic 28	kkkkkk/rrmmrr:bс0441с0441сс04410441с	I
    //   46: istore_1
    //   47: getstatic 30	kkkkkk/rrmmrr:bсс04410441сс04410441с	I
    //   50: istore_2
    //   51: getstatic 32	kkkkkk/rrmmrr:b0441с04410441сс04410441с	I
    //   54: istore_3
    //   55: iload_1
    //   56: iload_2
    //   57: iload_1
    //   58: iadd
    //   59: imul
    //   60: iload_3
    //   61: irem
    //   62: tableswitch	default:+18->80, 0:+29->91
    //   80: bipush 83
    //   82: putstatic 28	kkkkkk/rrmmrr:bс0441с0441сс04410441с	I
    //   85: invokestatic 38	kkkkkk/rrmmrr:bи043804380438иии043804380438	()I
    //   88: putstatic 34	kkkkkk/rrmmrr:b04410441с0441сс04410441с	I
    //   91: aload_0
    //   92: getfield 59	kkkkkk/rrmmrr:b0441сс0441сс04410441с	Lorg/json/JSONArray;
    //   95: astore 4
    //   97: aload 4
    //   99: invokevirtual 68	org/json/JSONArray:toString	()Ljava/lang/String;
    //   102: astore 4
    //   104: aload 4
    //   106: areturn
    //   107: ldc 70
    //   109: areturn
    //   110: astore 4
    //   112: aload 4
    //   114: athrow
    //   115: astore 4
    //   117: aload 4
    //   119: athrow
    //   120: astore 4
    //   122: aload 4
    //   124: athrow
    //   125: astore 4
    //   127: aload 4
    //   129: athrow
    // Local variable table:
    //   start	length	slot	name	signature
    //   0	130	0	this	rrmmrr
    //   46	14	1	i	int
    //   50	9	2	j	int
    //   54	8	3	k	int
    //   4	101	4	localObject	Object
    //   110	3	4	localException1	Exception
    //   115	3	4	localException2	Exception
    //   120	3	4	localException3	Exception
    //   125	3	4	localException4	Exception
    // Exception table:
    //   from	to	target	type
    //   0	6	110	java/lang/Exception
    //   91	97	110	java/lang/Exception
    //   43	55	115	java/lang/Exception
    //   112	115	115	java/lang/Exception
    //   122	125	115	java/lang/Exception
    //   97	104	120	java/lang/Exception
    //   80	91	125	java/lang/Exception
  }
}
