package kkkkkk;

public class rrmrrr
{
  public static int b04410441с0441с0441с0441с = 0;
  public static int b0441с04410441с0441с0441с = 2;
  private static final String b0441сс0441с0441с0441с;
  public static int bс0441с0441с0441с0441с = 46;
  public static int bсс04410441с0441с0441с = 1;
  
  /* Error */
  static
  {
    // Byte code:
    //   0: getstatic 23	kkkkkk/rrmrrr:bс0441с0441с0441с0441с	I
    //   3: getstatic 25	kkkkkk/rrmrrr:bсс04410441с0441с0441с	I
    //   6: iadd
    //   7: getstatic 23	kkkkkk/rrmrrr:bс0441с0441с0441с0441с	I
    //   10: imul
    //   11: getstatic 27	kkkkkk/rrmrrr:b0441с04410441с0441с0441с	I
    //   14: irem
    //   15: getstatic 29	kkkkkk/rrmrrr:b04410441с0441с0441с0441с	I
    //   18: if_icmpeq +13 -> 31
    //   21: bipush 67
    //   23: putstatic 23	kkkkkk/rrmrrr:bс0441с0441с0441с0441с	I
    //   26: bipush 17
    //   28: putstatic 29	kkkkkk/rrmrrr:b04410441с0441с0441с0441с	I
    //   31: iconst_0
    //   32: tableswitch	default:+24->56, 0:+51->83, 1:+-1->31
    //   56: iconst_1
    //   57: tableswitch	default:+23->80, 0:+-26->31, 1:+26->83
    //   80: goto -24 -> 56
    //   83: ldc 2
    //   85: invokevirtual 35	java/lang/Class:getSimpleName	()Ljava/lang/String;
    //   88: astore 5
    //   90: getstatic 23	kkkkkk/rrmrrr:bс0441с0441с0441с0441с	I
    //   93: istore_0
    //   94: getstatic 25	kkkkkk/rrmrrr:bсс04410441с0441с0441с	I
    //   97: istore_1
    //   98: getstatic 23	kkkkkk/rrmrrr:bс0441с0441с0441с0441с	I
    //   101: istore_2
    //   102: invokestatic 39	kkkkkk/rrmrrr:b0438043804380438043804380438и04380438	()I
    //   105: istore_3
    //   106: getstatic 29	kkkkkk/rrmrrr:b04410441с0441с0441с0441с	I
    //   109: istore 4
    //   111: iload_0
    //   112: iload_1
    //   113: iadd
    //   114: iload_2
    //   115: imul
    //   116: iload_3
    //   117: irem
    //   118: iload 4
    //   120: if_icmpeq +14 -> 134
    //   123: invokestatic 42	kkkkkk/rrmrrr:b0438ииииии043804380438	()I
    //   126: putstatic 23	kkkkkk/rrmrrr:bс0441с0441с0441с0441с	I
    //   129: bipush 73
    //   131: putstatic 29	kkkkkk/rrmrrr:b04410441с0441с0441с0441с	I
    //   134: aload 5
    //   136: putstatic 44	kkkkkk/rrmrrr:b0441сс0441с0441с0441с	Ljava/lang/String;
    //   139: return
    //   140: astore 5
    //   142: aload 5
    //   144: athrow
    //   145: astore 5
    //   147: aload 5
    //   149: athrow
    // Local variable table:
    //   start	length	slot	name	signature
    //   93	21	0	i	int
    //   97	17	1	j	int
    //   101	15	2	k	int
    //   105	13	3	m	int
    //   109	12	4	n	int
    //   88	47	5	str	String
    //   140	3	5	localException1	Exception
    //   145	3	5	localException2	Exception
    // Exception table:
    //   from	to	target	type
    //   83	90	140	java/lang/Exception
    //   102	111	140	java/lang/Exception
    //   134	139	140	java/lang/Exception
    //   90	102	145	java/lang/Exception
    //   123	134	145	java/lang/Exception
  }
  
  public rrmrrr() {}
  
  public static int b0438043804380438043804380438и04380438()
  {
    return 2;
  }
  
  public static void b04380438иииии043804380438(rrmrmr paramRrmrmr)
  {
    try
    {
      bии0438ииии043804380438(paramRrmrmr, 0L);
      return;
    }
    catch (Exception paramRrmrmr)
    {
      throw paramRrmrmr;
    }
  }
  
  public static int b0438ииииии043804380438()
  {
    return 32;
  }
  
  public static int bи043804380438043804380438и04380438()
  {
    return 0;
  }
  
  public static int bи0438иииии043804380438()
  {
    return 1;
  }
  
  public static void bии0438ииии043804380438(rrmrmr paramRrmrmr, long paramLong)
  {
    int i = bс0441с0441с0441с0441с;
    int j = bсс04410441с0441с0441с;
    switch (0)
    {
    case 1: 
    default: 
      for (;;)
      {
        switch (1)
        {
        }
      }
    }
    if ((i + j) * bс0441с0441с0441с0441с % b0441с04410441с0441с0441с != bи043804380438043804380438и04380438())
    {
      bс0441с0441с0441с0441с = 39;
      b04410441с0441с0441с0441с = b0438ииииии043804380438();
      i = bс0441с0441с0441с0441с;
      switch (i * (bсс04410441с0441с0441с + i) % b0441с04410441с0441с0441с)
      {
      default: 
        bс0441с0441с0441с0441с = b0438ииииии043804380438();
        b04410441с0441с0441с0441с = b0438ииииии043804380438();
      }
    }
    switch (1)
    {
    case 0: 
    default: 
      for (;;)
      {
        switch (0)
        {
        }
      }
    }
    bhhhbh.b0428ШШШШШ0428ШШ0428(bиииииии043804380438(paramRrmrmr), paramLong);
  }
  
  private static Runnable bиииииии043804380438(rrmrmr paramRrmrmr)
  {
    switch (0)
    {
    case 1: 
    default: 
      for (;;)
      {
        switch (0)
        {
        }
      }
    }
    if ((bс0441с0441с0441с0441с + bсс04410441с0441с0441с) * bс0441с0441с0441с0441с % b0441с04410441с0441с0441с != b04410441с0441с0441с0441с)
    {
      bс0441с0441с0441с0441с = 73;
      b04410441с0441с0441с0441с = 72;
    }
    paramRrmrmr = new rrmrrr.1(paramRrmrmr);
    switch (0)
    {
    case 1: 
    default: 
      for (;;)
      {
        switch (1)
        {
        }
      }
    }
    if ((bс0441с0441с0441с0441с + bсс04410441с0441с0441с) * bс0441с0441с0441с0441с % b0441с04410441с0441с0441с != b04410441с0441с0441с0441с)
    {
      bс0441с0441с0441с0441с = 54;
      b04410441с0441с0441с0441с = 75;
    }
    return paramRrmrmr;
  }
}
