package kkkkkk;

import android.util.Pair;
import java.io.IOException;
import java.util.ArrayList;
import java.util.List;

public abstract class rrmrmr
{
  public static int b04410441сссссс0441 = 1;
  public static int b0441с0441ссссс0441 = 0;
  private static final String b0441сс04410441044104410441с;
  public static int bс0441сссссс0441 = 61;
  public static int bсс0441ссссс0441 = 2;
  private static final int bссс04410441044104410441с = 30000;
  public rmrmrr b04410441044104410441044104410441с;
  private List<String> b04410441с04410441044104410441с;
  private List<Pair<String, String>> b0441с044104410441044104410441с;
  private String b0441ссссссс0441;
  private rrmrmr.mrmrmr bс0441044104410441044104410441с;
  public dddxxd bс0441с04410441044104410441с;
  private boolean bсс044104410441044104410441с = true;
  private int bсссссссс0441 = 30000;
  
  static
  {
    int i = bс0441сссссс0441;
    int j = b04410441сссссс0441;
    switch (0)
    {
    case 1: 
    default: 
      for (;;)
      {
        switch (1)
        {
        }
      }
    }
    if ((i + j) * bс0441сссссс0441 % bсс0441ссссс0441 != b04380438и0438и0438и043804380438())
    {
      i = bс0441сссссс0441;
      switch (i * (b04410441сссссс0441 + i) % bсс0441ссссс0441)
      {
      default: 
        bс0441сссссс0441 = 94;
        b04410441сссссс0441 = 62;
      }
      bс0441сссссс0441 = bи0438и0438и0438и043804380438();
      b04410441сссссс0441 = 11;
    }
    try
    {
      b0441сс04410441044104410441с = rrmrmr.class.getSimpleName();
      return;
    }
    catch (Exception localException)
    {
      throw localException;
    }
  }
  
  public rrmrmr(String paramString, rrmrmr.mrmrmr paramMrmrmr)
  {
    this.b0441ссссссс0441 = paramString;
    this.bс0441044104410441044104410441с = paramMrmrmr;
    this.b0441с044104410441044104410441с = new ArrayList();
  }
  
  public static int b04380438и0438и0438и043804380438()
  {
    return 0;
  }
  
  public static int b0438ии0438и0438и043804380438()
  {
    return 1;
  }
  
  public static int bи0438и0438и0438и043804380438()
  {
    return 7;
  }
  
  /* Error */
  public List<Pair<String, String>> b0438043804380438и0438и043804380438()
  {
    // Byte code:
    //   0: aload_0
    //   1: getfield 77	kkkkkk/rrmrmr:b0441с044104410441044104410441с	Ljava/util/List;
    //   4: astore 6
    //   6: getstatic 40	kkkkkk/rrmrmr:bс0441сссссс0441	I
    //   9: istore_1
    //   10: getstatic 42	kkkkkk/rrmrmr:b04410441сссссс0441	I
    //   13: istore_2
    //   14: getstatic 40	kkkkkk/rrmrmr:bс0441сссссс0441	I
    //   17: istore_3
    //   18: getstatic 44	kkkkkk/rrmrmr:bсс0441ссссс0441	I
    //   21: istore 4
    //   23: getstatic 82	kkkkkk/rrmrmr:b0441с0441ссссс0441	I
    //   26: istore 5
    //   28: iload_1
    //   29: iload_2
    //   30: iadd
    //   31: iload_3
    //   32: imul
    //   33: iload 4
    //   35: irem
    //   36: iload 5
    //   38: if_icmpeq +43 -> 81
    //   41: iconst_0
    //   42: putstatic 40	kkkkkk/rrmrmr:bс0441сссссс0441	I
    //   45: bipush 99
    //   47: putstatic 82	kkkkkk/rrmrmr:b0441с0441ссссс0441	I
    //   50: getstatic 40	kkkkkk/rrmrmr:bс0441сссссс0441	I
    //   53: getstatic 42	kkkkkk/rrmrmr:b04410441сссссс0441	I
    //   56: iadd
    //   57: getstatic 40	kkkkkk/rrmrmr:bс0441сссссс0441	I
    //   60: imul
    //   61: getstatic 44	kkkkkk/rrmrmr:bсс0441ссссс0441	I
    //   64: irem
    //   65: invokestatic 48	kkkkkk/rrmrmr:b04380438и0438и0438и043804380438	()I
    //   68: if_icmpeq +13 -> 81
    //   71: iconst_3
    //   72: putstatic 40	kkkkkk/rrmrmr:bс0441сссссс0441	I
    //   75: invokestatic 51	kkkkkk/rrmrmr:bи0438и0438и0438и043804380438	()I
    //   78: putstatic 82	kkkkkk/rrmrmr:b0441с0441ссссс0441	I
    //   81: aload 6
    //   83: areturn
    //   84: astore 6
    //   86: aload 6
    //   88: athrow
    //   89: astore 6
    //   91: aload 6
    //   93: athrow
    //   94: astore 6
    //   96: aload 6
    //   98: athrow
    // Local variable table:
    //   start	length	slot	name	signature
    //   0	99	0	this	rrmrmr
    //   9	22	1	i	int
    //   13	18	2	j	int
    //   17	16	3	k	int
    //   21	15	4	m	int
    //   26	13	5	n	int
    //   4	78	6	localList	List
    //   84	3	6	localException1	Exception
    //   89	3	6	localException2	Exception
    //   94	3	6	localException3	Exception
    // Exception table:
    //   from	to	target	type
    //   0	6	84	java/lang/Exception
    //   6	28	89	java/lang/Exception
    //   86	89	89	java/lang/Exception
    //   41	50	94	java/lang/Exception
  }
  
  public void b043804380438и04380438и043804380438(List<String> paramList)
  {
    throw new Runtime("d2j fail translate: java.lang.IndexOutOfBoundsException: fromIndex < 0: -1\n\tat java.util.BitSet.nextSetBit(BitSet.java:712)\n\tat com.googlecode.dex2jar.ir.ts.array.FillArrayTransformer.makeSureAllElementAreAssigned(FillArrayTransformer.java:505)\n\tat com.googlecode.dex2jar.ir.ts.array.FillArrayTransformer.transformReportChanged(FillArrayTransformer.java:123)\n\tat com.googlecode.dex2jar.ir.ts.StatedTransformer.transform(StatedTransformer.java:10)\n\tat com.googlecode.d2j.dex.Dex2jar$2.optimize(Dex2jar.java:149)\n\tat com.googlecode.d2j.dex.Dex2Asm.convertCode(Dex2Asm.java:414)\n\tat com.googlecode.d2j.dex.ExDex2Asm.convertCode(ExDex2Asm.java:42)\n\tat com.googlecode.d2j.dex.Dex2jar$2.convertCode(Dex2jar.java:128)\n\tat com.googlecode.d2j.dex.Dex2Asm.convertMethod(Dex2Asm.java:509)\n\tat com.googlecode.d2j.dex.Dex2Asm.convertClass(Dex2Asm.java:406)\n\tat com.googlecode.d2j.dex.Dex2Asm.convertDex(Dex2Asm.java:422)\n\tat com.googlecode.d2j.dex.Dex2jar.doTranslate(Dex2jar.java:172)\n\tat com.googlecode.d2j.dex.Dex2jar.to(Dex2jar.java:272)\n\tat com.googlecode.dex2jar.tools.Dex2jarCmd.doCommandLine(Dex2jarCmd.java:108)\n\tat com.googlecode.dex2jar.tools.BaseCmd.doMain(BaseCmd.java:288)\n\tat com.googlecode.dex2jar.tools.Dex2jarCmd.main(Dex2jarCmd.java:32)\n");
  }
  
  public boolean b04380438ии04380438и043804380438(oqooqo paramOqooqo)
  {
    if ((paramOqooqo != null) && (paramOqooqo.bооо043Eо043Eо043E043Eо())) {}
    boolean bool2;
    for (boolean bool1 = true;; bool1 = bool2)
    {
      switch (1)
      {
      case 0: 
      default: 
        for (;;)
        {
          switch (1)
          {
          }
        }
      }
      return bool1;
      bool2 = false;
      int i = bс0441сссссс0441;
      if ((bс0441сссссс0441 + b04410441сссссс0441) * bс0441сссссс0441 % bсс0441ссссс0441 != b0441с0441ссссс0441)
      {
        bс0441сссссс0441 = 56;
        b0441с0441ссссс0441 = 60;
      }
      bool1 = bool2;
      switch (i * (b0438ии0438и0438и043804380438() + i) % bсс0441ссссс0441)
      {
      }
      switch (1)
      {
      case 0: 
      default: 
        for (;;)
        {
          switch (1)
          {
          }
        }
      }
      bс0441сссссс0441 = 57;
      b0441с0441ссссс0441 = bи0438и0438и0438и043804380438();
    }
  }
  
  public List<String> b0438и04380438и0438и043804380438()
  {
    if ((bс0441сссссс0441 + b04410441сссссс0441) * bс0441сссссс0441 % bсс0441ссссс0441 != b0441с0441ссссс0441)
    {
      bс0441сссссс0441 = bи0438и0438и0438и043804380438();
      b0441с0441ссссс0441 = 59;
      switch (0)
      {
      case 1: 
      default: 
        for (;;)
        {
          switch (1)
          {
          }
        }
      }
      if ((bс0441сссссс0441 + b04410441сссссс0441) * bс0441сссссс0441 % bсс0441ссссс0441 != b0441с0441ссссс0441)
      {
        bс0441сссссс0441 = 32;
        b0441с0441ссссс0441 = 7;
      }
    }
    try
    {
      List localList = this.b04410441с04410441044104410441с;
      return localList;
    }
    catch (Exception localException)
    {
      throw localException;
    }
  }
  
  public void b0438и0438и04380438и043804380438(oqooqo paramOqooqo)
  {
    int i = bс0441сссссс0441;
    switch (i * (b04410441сссссс0441 + i) % bсс0441ссссс0441)
    {
    default: 
      bс0441сссссс0441 = 92;
      b0441с0441ссссс0441 = 34;
    }
    try
    {
      boolean bool = b04380438ии04380438и043804380438(paramOqooqo);
      if (!bool) {}
    }
    catch (IOException paramOqooqo)
    {
      for (;;)
      {
        StringBuilder localStringBuilder1;
        bии0438и04380438и043804380438(paramOqooqo);
        return;
        StringBuilder localStringBuilder2 = new StringBuilder().append(gguuuu.bккккк043Aкк043A043A("\020cWfdddj]\031]j`b8\037", 'î', '\000')).append(paramOqooqo.b043Eоооо043Eо043E043Eо());
        i = bс0441сссссс0441;
        int j = b04410441сссссс0441;
        int k = bс0441сссссс0441;
        int m = bсс0441ссссс0441;
        int n = b04380438и0438и0438и043804380438();
        if ((i + j) * k % m != n)
        {
          bс0441сссссс0441 = bи0438и0438и0438и043804380438();
          b0441с0441ссссс0441 = bи0438и0438и0438и043804380438();
        }
        paramOqooqo = gguuuu.bк043Aккк043Aкк043A043A("3t\001t\tH-", '@', 'S', '\000') + paramOqooqo.b043E043Eо043E043Eоо043E043Eо().b043E043Eоооо043E043E043Eо();
      }
    }
    catch (Exception paramOqooqo)
    {
      throw paramOqooqo;
    }
    try
    {
      xtxtxt.bиии043804380438и0438ии(b0441сс04410441044104410441с, gguuuu.bккккк043Aкк043A043A("22\030;*+.=>ll", '\026', '\001') + paramOqooqo.b043Eоооо043Eо043E043Eо());
      if (this.bс0441с04410441044104410441с == null) {
        return;
      }
      bи0438043804380438ии043804380438(paramOqooqo);
      return;
    }
    catch (Exception paramOqooqo)
    {
      throw paramOqooqo;
    }
    xtxtxt.bиии043804380438и0438ии(b0441сс04410441044104410441с, gguuuu.bккккк043Aкк043A043A("ljM_lhfdhY9SZ\\d`R\f", 'ÿ', '\002') + paramOqooqo);
    if (this.bс0441с04410441044104410441с != null)
    {
      localStringBuilder1 = new StringBuilder().append(gguuuu.bк043Aккк043Aкк043A043A("s\024Fy\016\035\033\033\033!\024Ou$%#'UpW", '', '\007', '\003'));
      if (paramOqooqo == null)
      {
        paramOqooqo = gguuuu.bк043Aккк043Aкк043A043A(",._\023'6444:-", '­', 'ï', '\001');
        bии0438и04380438и043804380438(new Exception(paramOqooqo));
        return;
      }
    }
  }
  
  public void b0438ии043804380438и043804380438(int paramInt)
  {
    int i = bи0438и0438и0438и043804380438();
    switch (i * (b04410441сссссс0441 + i) % bсс0441ссссс0441)
    {
    default: 
      bс0441сссссс0441 = bи0438и0438и0438и043804380438();
      b0441с0441ссссс0441 = bи0438и0438и0438и043804380438();
    }
    i = bс0441сссссс0441;
    switch (i * (b04410441сссссс0441 + i) % bсс0441ссссс0441)
    {
    default: 
      bс0441сссссс0441 = 19;
      b0441с0441ссссс0441 = bи0438и0438и0438и043804380438();
    }
    try
    {
      this.bсссссссс0441 = paramInt;
      return;
    }
    catch (Exception localException)
    {
      throw localException;
    }
  }
  
  public abstract void b0438ии04380438ии043804380438(rmrmrr paramRmrmrr);
  
  public int b0438иии04380438и043804380438()
  {
    try
    {
      int i = this.bсссссссс0441;
      if ((bс0441сссссс0441 + b04410441сссссс0441) * bс0441сссссс0441 % bсс0441ссссс0441 != b0441с0441ссссс0441)
      {
        int j = bс0441сссссс0441;
        switch (j * (b04410441сссссс0441 + j) % bсс0441ссссс0441)
        {
        default: 
          bс0441сссссс0441 = 99;
          b0441с0441ссссс0441 = 71;
        }
        bс0441сссссс0441 = 7;
        b0441с0441ссссс0441 = 59;
      }
      return i;
    }
    catch (Exception localException)
    {
      switch (1)
      {
      case 0: 
      default: 
        for (;;)
        {
          switch (1)
          {
          }
        }
      }
      throw localException;
    }
  }
  
  public void bи0438043804380438ии043804380438(oqooqo paramOqooqo)
    throws IOException
  {
    int i = bс0441сссссс0441;
    switch (i * (b04410441сссссс0441 + i) % bсс0441ссссс0441)
    {
    default: 
      bс0441сссссс0441 = 10;
      b0441с0441ссссс0441 = bи0438и0438и0438и043804380438();
    }
    for (;;)
    {
      try
      {
        localDddxxd = this.bс0441с04410441044104410441с;
        if (paramOqooqo == null) {
          paramOqooqo = "";
        }
      }
      catch (Exception paramOqooqo)
      {
        dddxxd localDddxxd;
        throw paramOqooqo;
      }
      try
      {
        localDddxxd.bх04450445х0445хх044504450445(paramOqooqo);
        return;
      }
      catch (Exception paramOqooqo)
      {
        throw paramOqooqo;
      }
      i = bс0441сссссс0441;
      switch (i * (b04410441сссссс0441 + i) % bсс0441ссссс0441)
      {
      default: 
        bс0441сссссс0441 = bи0438и0438и0438и043804380438();
        b0441с0441ссссс0441 = 93;
      }
      switch (1)
      {
      case 0: 
      default: 
        switch (0)
        {
        }
        break;
      }
      paramOqooqo = paramOqooqo.b043E043Eо043E043Eоо043E043Eо().b043E043Eоооо043E043E043Eо();
    }
  }
  
  public boolean bи043804380438и0438и043804380438()
  {
    return this.bсс044104410441044104410441с;
  }
  
  public void bи04380438и04380438и043804380438(dddxxd paramDddxxd)
  {
    int i = bс0441сссссс0441;
    int j = b04410441сссссс0441;
    int k = bс0441сссссс0441;
    if ((bс0441сссссс0441 + b04410441сссссс0441) * bс0441сссссс0441 % bсс0441ссссс0441 != b04380438и0438и0438и043804380438())
    {
      bс0441сссссс0441 = bи0438и0438и0438и043804380438();
      b0441с0441ссссс0441 = bи0438и0438и0438и043804380438();
    }
    if ((i + j) * k % bсс0441ссссс0441 != b0441с0441ссссс0441)
    {
      bс0441сссссс0441 = bи0438и0438и0438и043804380438();
      b0441с0441ссссс0441 = bи0438и0438и0438и043804380438();
    }
    this.bс0441с04410441044104410441с = paramDddxxd;
    switch (0)
    {
    case 1: 
    default: 
      for (;;)
      {
        switch (0)
        {
        }
      }
    }
  }
  
  public String bи0438ии04380438и043804380438()
  {
    switch (1)
    {
    case 0: 
    default: 
      for (;;)
      {
        switch (0)
        {
        }
      }
    }
    switch (0)
    {
    case 1: 
    default: 
      for (;;)
      {
        switch (0)
        {
        }
      }
    }
    int i = bс0441сссссс0441;
    switch (i * (b04410441сссссс0441 + i) % bсс0441ссссс0441)
    {
    default: 
      bс0441сссссс0441 = bи0438и0438и0438и043804380438();
      b0441с0441ссссс0441 = bи0438и0438и0438и043804380438();
    }
    i = bс0441сссссс0441;
    switch (i * (b04410441сссссс0441 + i) % bсс0441ссссс0441)
    {
    default: 
      bс0441сссссс0441 = 75;
      b0441с0441ссссс0441 = 40;
    }
    return this.b0441ссссссс0441;
  }
  
  public dddxxd bии04380438и0438и043804380438()
  {
    return this.bс0441с04410441044104410441с;
  }
  
  public void bии0438и04380438и043804380438(Exception paramException)
  {
    throw new Runtime("d2j fail translate: java.lang.IndexOutOfBoundsException: fromIndex < 0: -1\n\tat java.util.BitSet.nextSetBit(BitSet.java:712)\n\tat com.googlecode.dex2jar.ir.ts.array.FillArrayTransformer.makeSureAllElementAreAssigned(FillArrayTransformer.java:505)\n\tat com.googlecode.dex2jar.ir.ts.array.FillArrayTransformer.transformReportChanged(FillArrayTransformer.java:123)\n\tat com.googlecode.dex2jar.ir.ts.StatedTransformer.transform(StatedTransformer.java:10)\n\tat com.googlecode.d2j.dex.Dex2jar$2.optimize(Dex2jar.java:149)\n\tat com.googlecode.d2j.dex.Dex2Asm.convertCode(Dex2Asm.java:414)\n\tat com.googlecode.d2j.dex.ExDex2Asm.convertCode(ExDex2Asm.java:42)\n\tat com.googlecode.d2j.dex.Dex2jar$2.convertCode(Dex2jar.java:128)\n\tat com.googlecode.d2j.dex.Dex2Asm.convertMethod(Dex2Asm.java:509)\n\tat com.googlecode.d2j.dex.Dex2Asm.convertClass(Dex2Asm.java:406)\n\tat com.googlecode.d2j.dex.Dex2Asm.convertDex(Dex2Asm.java:422)\n\tat com.googlecode.d2j.dex.Dex2jar.doTranslate(Dex2jar.java:172)\n\tat com.googlecode.d2j.dex.Dex2jar.to(Dex2jar.java:272)\n\tat com.googlecode.dex2jar.tools.Dex2jarCmd.doCommandLine(Dex2jarCmd.java:108)\n\tat com.googlecode.dex2jar.tools.BaseCmd.doMain(BaseCmd.java:288)\n\tat com.googlecode.dex2jar.tools.Dex2jarCmd.main(Dex2jarCmd.java:32)\n");
  }
  
  public void bиии043804380438и043804380438(boolean paramBoolean)
  {
    int i = bс0441сссссс0441;
    switch (i * (b04410441сссссс0441 + i) % bсс0441ссссс0441)
    {
    default: 
      bс0441сссссс0441 = 58;
      b0441с0441ссссс0441 = bи0438и0438и0438и043804380438();
    }
    if ((bс0441сссссс0441 + b04410441сссссс0441) * bс0441сссссс0441 % bсс0441ссссс0441 != b0441с0441ссссс0441)
    {
      bс0441сссссс0441 = 50;
      b0441с0441ссссс0441 = bи0438и0438и0438и043804380438();
    }
    this.bсс044104410441044104410441с = paramBoolean;
    switch (0)
    {
    case 1: 
    default: 
      for (;;)
      {
        switch (0)
        {
        }
      }
    }
  }
  
  public abstract rmrmrr bиии04380438ии043804380438();
  
  public void bиии0438и0438и043804380438(String paramString1, String paramString2)
  {
    int i = 4;
    try
    {
      for (;;)
      {
        i /= 0;
      }
      List localList;
      return;
    }
    catch (Exception localException)
    {
      bс0441сссссс0441 = bи0438и0438и0438и043804380438();
      localList = this.b0441с044104410441044104410441с;
      i = bс0441сссссс0441;
      switch (i * (b04410441сссссс0441 + i) % bсс0441ссссс0441)
      {
      default: 
        bс0441сссссс0441 = 67;
        b04410441сссссс0441 = 92;
      }
      switch (1)
      {
      case 0: 
      default: 
        for (;;)
        {
          switch (0)
          {
          }
        }
      }
      localList.add(Pair.create(paramString1, paramString2));
    }
  }
  
  public rrmrmr.mrmrmr bииии04380438и043804380438()
  {
    if ((bи0438и0438и0438и043804380438() + b0438ии0438и0438и043804380438()) * bи0438и0438и0438и043804380438() % bсс0441ссссс0441 != b0441с0441ссссс0441)
    {
      bс0441сссссс0441 = 62;
      b0441с0441ссссс0441 = 24;
    }
    return this.bс0441044104410441044104410441с;
  }
}
