package kkkkkk;

public enum rrrccr
{
  private final String mValue;
  
  static
  {
    rrrccr localRrrccr1 = new rrrccr(gguuuu.bк043Aккк043Aкк043A043A(",,;\034,+\031%\035\032!\030 %/!\023\023\021\035\017\027\013\f", '!', 'ÿ', '\002'), 0, gguuuu.bк043Aккк043Aкк043A043A("[{+K{zhtlipgot\037Pbb`l^fZ[", 'r', '', '\002'));
    switch (1)
    {
    case 0: 
    default: 
      for (;;)
      {
        switch (1)
        {
        }
      }
    }
    NO_ARRANGEMENT_REFERENCE = localRrrccr1;
    IN_GRACE_PERIOD = new rrrccr(gguuuu.bк043Aккк043Aкк043A043A("\034\"4\035)\031\034\037:,\"0(/%", '1', '!', '\003'), 1, gguuuu.bккккк043Aкк043A043A(",P\001'Q?@Az*>J@E9", '4', '\002'));
    GALAXY_ERROR = new rrrccr(gguuuu.bк043Aккк043Aкк043A043A(".'1%;;@%10,.", ']', 'º', '\002'), 2, gguuuu.bк043Aккк043Aкк043A043A("~\030\"\026,,Qu\"!\035\037", '°', 'ç', '\000'));
    NO_REGISTERED_NUMBER = new rrrccr(gguuuu.bккккк043Aкк043A043A("qs\005xlor}qss\020\b\001vz\t", '6', '\001'), 3, gguuuu.bккккк043Aкк043A043A("\007)Z\016\"%(35'5))e\025=6,0>", '¼', '\001'));
    OTHER = new rrrccr(gguuuu.bккккк043Aкк043A043A("ytr\001", '', '\004'), 4, gguuuu.bккккк043Aкк043A043A("2XMKY", '1', '\004'));
    int i = b043F043Fп043F043F043Fп043Fпп();
    switch (i * (bпп043F043F043F043Fп043Fпп() + i) % b043Fп043F043F043F043Fп043Fпп())
    {
    }
    localRrrccr1 = NO_ARRANGEMENT_REFERENCE;
    rrrccr localRrrccr2 = IN_GRACE_PERIOD;
    rrrccr localRrrccr3 = GALAXY_ERROR;
    rrrccr localRrrccr4 = NO_REGISTERED_NUMBER;
    if ((b043F043Fп043F043F043Fп043Fпп() + bпп043F043F043F043Fп043Fпп()) * b043F043Fп043F043F043Fп043Fпп() % b043Fп043F043F043F043Fп043Fпп() != bп043F043F043F043F043Fп043Fпп()) {}
    $VALUES = new rrrccr[] { localRrrccr1, localRrrccr2, localRrrccr3, localRrrccr4, OTHER };
  }
  
  private rrrccr(String paramString)
  {
    this.mValue = paramString;
  }
  
  /* Error */
  public static rrrccr b043F043F043F043F043F043Fп043Fпп(String paramString)
  {
    // Byte code:
    //   0: invokestatic 65	kkkkkk/rrrccr:b043F043Fп043F043F043Fп043Fпп	()I
    //   3: invokestatic 68	kkkkkk/rrrccr:bпп043F043F043F043Fп043Fпп	()I
    //   6: iadd
    //   7: invokestatic 65	kkkkkk/rrrccr:b043F043Fп043F043F043Fп043Fпп	()I
    //   10: imul
    //   11: invokestatic 71	kkkkkk/rrrccr:b043Fп043F043F043F043Fп043Fпп	()I
    //   14: irem
    //   15: invokestatic 74	kkkkkk/rrrccr:bп043F043F043F043F043Fп043Fпп	()I
    //   18: if_icmpeq +3 -> 21
    //   21: ldc 2
    //   23: aload_0
    //   24: invokestatic 92	java/lang/Enum:valueOf	(Ljava/lang/Class;Ljava/lang/String;)Ljava/lang/Enum;
    //   27: astore_0
    //   28: aload_0
    //   29: checkcast 2	kkkkkk/rrrccr
    //   32: astore_0
    //   33: invokestatic 65	kkkkkk/rrrccr:b043F043Fп043F043F043Fп043Fпп	()I
    //   36: invokestatic 68	kkkkkk/rrrccr:bпп043F043F043F043Fп043Fпп	()I
    //   39: iadd
    //   40: invokestatic 65	kkkkkk/rrrccr:b043F043Fп043F043F043Fп043Fпп	()I
    //   43: imul
    //   44: invokestatic 71	kkkkkk/rrrccr:b043Fп043F043F043F043Fп043Fпп	()I
    //   47: irem
    //   48: invokestatic 74	kkkkkk/rrrccr:bп043F043F043F043F043Fп043Fпп	()I
    //   51: if_icmpeq +17 -> 68
    //   54: aload_0
    //   55: areturn
    //   56: astore_0
    //   57: aload_0
    //   58: athrow
    //   59: astore_0
    //   60: aload_0
    //   61: athrow
    //   62: astore_0
    //   63: aload_0
    //   64: athrow
    //   65: astore_0
    //   66: aload_0
    //   67: athrow
    //   68: aload_0
    //   69: areturn
    // Local variable table:
    //   start	length	slot	name	signature
    //   0	70	0	paramString	String
    // Exception table:
    //   from	to	target	type
    //   21	28	56	java/lang/Exception
    //   33	54	59	java/lang/Exception
    //   57	59	59	java/lang/Exception
    //   28	33	62	java/lang/Exception
    //   63	65	65	java/lang/Exception
  }
  
  public static int b043F043Fп043F043F043Fп043Fпп()
  {
    return 21;
  }
  
  public static int b043Fп043F043F043F043Fп043Fпп()
  {
    return 2;
  }
  
  public static int bп043F043F043F043F043Fп043Fпп()
  {
    return 0;
  }
  
  public static int bпп043F043F043F043Fп043Fпп()
  {
    return 1;
  }
  
  public String toString()
  {
    String str = this.mValue;
    int i = b043F043Fп043F043F043Fп043Fпп();
    switch (i * (bпп043F043F043F043Fп043Fпп() + i) % b043Fп043F043F043F043Fп043Fпп())
    {
    }
    return str;
  }
}
