package kkkkkk;

import io.reactivex.Maybe;
import io.reactivex.Single;
import javax.inject.Inject;

public class rrrrrc
{
  public static int b041C041CМ041C041C041CМММ = 1;
  public static int b041CМ041C041C041C041CМММ = 0;
  public static int bМ041CМ041C041C041CМММ = 2;
  public static int bММ041C041C041C041CМММ = 2;
  private final ddpddp b041C041C041CМ041C041CМММ;
  private final aaaahh b041CМ041CМ041C041CМММ;
  private final ahhhah b041CММ041C041C041CМММ;
  private final rrcrrc bМ041C041CМ041C041CМММ;
  private final ppdpdp bМММ041C041C041CМММ;
  
  @Inject
  public rrrrrc(rrcrrc paramRrcrrc, aaaahh paramAaaahh, ddpddp paramDdpddp, ahhhah paramAhhhah, ppdpdp paramPpdpdp)
  {
    this.bМ041C041CМ041C041CМММ = paramRrcrrc;
    this.b041CМ041CМ041C041CМММ = paramAaaahh;
    this.b041C041C041CМ041C041CМММ = paramDdpddp;
    this.b041CММ041C041C041CМММ = paramAhhhah;
    this.bМММ041C041C041CМММ = paramPpdpdp;
  }
  
  /* Error */
  private boolean b043F043F043F043F043Fпп043Fпп()
  {
    // Byte code:
    //   0: invokestatic 48	kkkkkk/rrrrrc:b043Fпп043F043Fпп043Fпп	()I
    //   3: istore_1
    //   4: iload_1
    //   5: invokestatic 51	kkkkkk/rrrrrc:bп043Fп043F043Fпп043Fпп	()I
    //   8: iload_1
    //   9: iadd
    //   10: imul
    //   11: invokestatic 54	kkkkkk/rrrrrc:bппп043F043Fпп043Fпп	()I
    //   14: irem
    //   15: tableswitch	default:+17->32, 0:+28->43
    //   32: bipush 69
    //   34: putstatic 56	kkkkkk/rrrrrc:bМ041CМ041C041C041CМММ	I
    //   37: invokestatic 48	kkkkkk/rrrrrc:b043Fпп043F043Fпп043Fпп	()I
    //   40: putstatic 58	kkkkkk/rrrrrc:b041CМ041C041C041C041CМММ	I
    //   43: aload_0
    //   44: getfield 38	kkkkkk/rrrrrc:bМММ041C041C041CМММ	Lkkkkkk/ppdpdp;
    //   47: astore_3
    //   48: getstatic 56	kkkkkk/rrrrrc:bМ041CМ041C041C041CМММ	I
    //   51: istore_1
    //   52: iload_1
    //   53: getstatic 60	kkkkkk/rrrrrc:b041C041CМ041C041C041CМММ	I
    //   56: iload_1
    //   57: iadd
    //   58: imul
    //   59: getstatic 62	kkkkkk/rrrrrc:bММ041C041C041C041CМММ	I
    //   62: irem
    //   63: tableswitch	default:+17->80, 0:+29->92
    //   80: invokestatic 48	kkkkkk/rrrrrc:b043Fпп043F043Fпп043Fпп	()I
    //   83: putstatic 56	kkkkkk/rrrrrc:bМ041CМ041C041C041CМММ	I
    //   86: invokestatic 48	kkkkkk/rrrrrc:b043Fпп043F043Fпп043Fпп	()I
    //   89: putstatic 58	kkkkkk/rrrrrc:b041CМ041C041C041C041CМММ	I
    //   92: aload_3
    //   93: invokevirtual 67	kkkkkk/ppdpdp:bа0430ааа043004300430аа	()Z
    //   96: istore_2
    //   97: iload_2
    //   98: ireturn
    //   99: astore_3
    //   100: aload_3
    //   101: athrow
    //   102: astore_3
    //   103: aload_3
    //   104: athrow
    // Local variable table:
    //   start	length	slot	name	signature
    //   0	105	0	this	rrrrrc
    //   3	56	1	i	int
    //   96	2	2	bool	boolean
    //   47	46	3	localPpdpdp	ppdpdp
    //   99	2	3	localException1	Exception
    //   102	2	3	localException2	Exception
    // Exception table:
    //   from	to	target	type
    //   92	97	99	java/lang/Exception
    //   43	48	102	java/lang/Exception
  }
  
  /* Error */
  private boolean b043F043Fппп043Fп043Fпп()
  {
    // Byte code:
    //   0: getstatic 56	kkkkkk/rrrrrc:bМ041CМ041C041C041CМММ	I
    //   3: istore_1
    //   4: getstatic 60	kkkkkk/rrrrrc:b041C041CМ041C041C041CМММ	I
    //   7: istore_2
    //   8: getstatic 56	kkkkkk/rrrrrc:bМ041CМ041C041C041CМММ	I
    //   11: istore_3
    //   12: getstatic 62	kkkkkk/rrrrrc:bММ041C041C041C041CМММ	I
    //   15: istore 4
    //   17: getstatic 58	kkkkkk/rrrrrc:b041CМ041C041C041C041CМММ	I
    //   20: istore 5
    //   22: iload_1
    //   23: iload_2
    //   24: iadd
    //   25: iload_3
    //   26: imul
    //   27: iload 4
    //   29: irem
    //   30: iload 5
    //   32: if_icmpeq +45 -> 77
    //   35: bipush 43
    //   37: putstatic 56	kkkkkk/rrrrrc:bМ041CМ041C041C041CМММ	I
    //   40: bipush 98
    //   42: putstatic 58	kkkkkk/rrrrrc:b041CМ041C041C041C041CМММ	I
    //   45: getstatic 56	kkkkkk/rrrrrc:bМ041CМ041C041C041CМММ	I
    //   48: getstatic 60	kkkkkk/rrrrrc:b041C041CМ041C041C041CМММ	I
    //   51: iadd
    //   52: getstatic 56	kkkkkk/rrrrrc:bМ041CМ041C041C041CМММ	I
    //   55: imul
    //   56: getstatic 62	kkkkkk/rrrrrc:bММ041C041C041C041CМММ	I
    //   59: irem
    //   60: getstatic 58	kkkkkk/rrrrrc:b041CМ041C041C041C041CМММ	I
    //   63: if_icmpeq +14 -> 77
    //   66: bipush 86
    //   68: putstatic 56	kkkkkk/rrrrrc:bМ041CМ041C041C041CМММ	I
    //   71: invokestatic 48	kkkkkk/rrrrrc:b043Fпп043F043Fпп043Fпп	()I
    //   74: putstatic 58	kkkkkk/rrrrrc:b041CМ041C041C041C041CМММ	I
    //   77: aload_0
    //   78: getfield 36	kkkkkk/rrrrrc:b041CММ041C041C041CМММ	Lkkkkkk/ahhhah;
    //   81: getstatic 85	kkkkkk/nuuunn:SECURE_CALL_ENABLED	Lkkkkkk/nuuunn;
    //   84: invokevirtual 91	kkkkkk/ahhhah:bп043F043F043Fп043F043Fп043F043F	(Lkkkkkk/nuuunn;)Z
    //   87: istore 6
    //   89: iconst_1
    //   90: tableswitch	default:+22->112, 0:+-1->89, 1:+49->139
    //   112: iconst_1
    //   113: tableswitch	default:+23->136, 0:+-24->89, 1:+26->139
    //   136: goto -24 -> 112
    //   139: iload 6
    //   141: ireturn
    //   142: astore 7
    //   144: aload 7
    //   146: athrow
    //   147: astore 7
    //   149: aload 7
    //   151: athrow
    // Local variable table:
    //   start	length	slot	name	signature
    //   0	152	0	this	rrrrrc
    //   3	22	1	i	int
    //   7	18	2	j	int
    //   11	16	3	k	int
    //   15	15	4	m	int
    //   20	13	5	n	int
    //   87	53	6	bool	boolean
    //   142	3	7	localException1	Exception
    //   147	3	7	localException2	Exception
    // Exception table:
    //   from	to	target	type
    //   0	22	142	java/lang/Exception
    //   77	89	142	java/lang/Exception
    //   35	45	147	java/lang/Exception
  }
  
  public static int b043Fпп043F043Fпп043Fпп()
  {
    return 52;
  }
  
  public static int bп043Fп043F043Fпп043Fпп()
  {
    return 1;
  }
  
  private boolean bп043Fппп043Fп043Fпп()
  {
    int i = bМ041CМ041C041C041CМММ;
    switch (i * (b041C041CМ041C041C041CМММ + i) % bММ041C041C041C041CМММ)
    {
    default: 
      bМ041CМ041C041C041CМММ = b043Fпп043F043Fпп043Fпп();
      b041CМ041C041C041C041CМММ = b043Fпп043F043Fпп043Fпп();
    }
    try
    {
      localAhhhah = this.b041CММ041C041C041CМММ;
      localNuuunn = nuuunn.LIGHT_LOGON_ENABLED;
    }
    catch (Exception localException1)
    {
      try
      {
        ahhhah localAhhhah;
        nuuunn localNuuunn;
        int j;
        int k;
        bМ041CМ041C041C041CМММ = 80;
        b041CМ041C041C041C041CМММ = b043Fпп043F043Fпп043Fпп();
        boolean bool = localAhhhah.bп043F043F043Fп043F043Fп043F043F(localNuuunn);
        return bool;
      }
      catch (Exception localException2)
      {
        throw localException2;
      }
      localException1 = localException1;
      throw localException1;
    }
    i = bМ041CМ041C041C041CМММ;
    j = b041C041CМ041C041C041CМММ;
    k = bММ041C041C041C041CМММ;
    switch (i * (j + i) % k)
    {
    }
    switch (0)
    {
    }
    for (;;)
    {
      switch (0)
      {
      }
    }
  }
  
  private unnnun bпп043F043F043Fпп043Fпп(fbfffb paramFbfffb)
  {
    throw new Runtime("d2j fail translate: java.lang.IndexOutOfBoundsException: fromIndex < 0: -1\n\tat java.util.BitSet.nextSetBit(BitSet.java:712)\n\tat com.googlecode.dex2jar.ir.ts.array.FillArrayTransformer.makeSureAllElementAreAssigned(FillArrayTransformer.java:505)\n\tat com.googlecode.dex2jar.ir.ts.array.FillArrayTransformer.transformReportChanged(FillArrayTransformer.java:123)\n\tat com.googlecode.dex2jar.ir.ts.StatedTransformer.transform(StatedTransformer.java:10)\n\tat com.googlecode.d2j.dex.Dex2jar$2.optimize(Dex2jar.java:149)\n\tat com.googlecode.d2j.dex.Dex2Asm.convertCode(Dex2Asm.java:414)\n\tat com.googlecode.d2j.dex.ExDex2Asm.convertCode(ExDex2Asm.java:42)\n\tat com.googlecode.d2j.dex.Dex2jar$2.convertCode(Dex2jar.java:128)\n\tat com.googlecode.d2j.dex.Dex2Asm.convertMethod(Dex2Asm.java:509)\n\tat com.googlecode.d2j.dex.Dex2Asm.convertClass(Dex2Asm.java:406)\n\tat com.googlecode.d2j.dex.Dex2Asm.convertDex(Dex2Asm.java:422)\n\tat com.googlecode.d2j.dex.Dex2jar.doTranslate(Dex2jar.java:172)\n\tat com.googlecode.d2j.dex.Dex2jar.to(Dex2jar.java:272)\n\tat com.googlecode.dex2jar.tools.Dex2jarCmd.doCommandLine(Dex2jarCmd.java:108)\n\tat com.googlecode.dex2jar.tools.BaseCmd.doMain(BaseCmd.java:288)\n\tat com.googlecode.dex2jar.tools.Dex2jarCmd.main(Dex2jarCmd.java:32)\n");
  }
  
  public static int bппп043F043Fпп043Fпп()
  {
    return 2;
  }
  
  @ooiiio("Trivial")
  public Maybe<String> b043F043Fп043F043Fпп043Fпп(cccrcc paramCccrcc)
  {
    try
    {
      paramCccrcc = this.bМ041C041CМ041C041CМММ.b043Fп043Fпппп043Fпп(paramCccrcc);
      int i = b043Fпп043F043Fпп043Fпп();
      int j = b041C041CМ041C041C041CМММ;
      int k = bММ041C041C041C041CМММ;
      if ((bМ041CМ041C041C041CМММ + bп043Fп043F043Fпп043Fпп()) * bМ041CМ041C041C041CМММ % bММ041C041C041C041CМММ != b041CМ041C041C041C041CМММ)
      {
        bМ041CМ041C041C041CМММ = 81;
        b041CМ041C041C041C041CМММ = b043Fпп043F043Fпп043Fпп();
      }
      switch (i * (j + i) % k)
      {
      default: 
        bМ041CМ041C041C041CМММ = 36;
        b041CМ041C041C041C041CМММ = b043Fпп043F043Fпп043Fпп();
      }
      return paramCccrcc;
    }
    catch (Exception paramCccrcc)
    {
      throw paramCccrcc;
    }
  }
  
  /* Error */
  @ooiiio("Trivial")
  public Maybe<String> b043Fп043F043F043Fпп043Fпп()
  {
    // Byte code:
    //   0: aload_0
    //   1: getfield 30	kkkkkk/rrrrrc:bМ041C041CМ041C041CМММ	Lkkkkkk/rrcrrc;
    //   4: astore_1
    //   5: getstatic 56	kkkkkk/rrrrrc:bМ041CМ041C041C041CМММ	I
    //   8: getstatic 60	kkkkkk/rrrrrc:b041C041CМ041C041C041CМММ	I
    //   11: iadd
    //   12: getstatic 56	kkkkkk/rrrrrc:bМ041CМ041C041C041CМММ	I
    //   15: imul
    //   16: getstatic 62	kkkkkk/rrrrrc:bММ041C041C041C041CМММ	I
    //   19: irem
    //   20: getstatic 58	kkkkkk/rrrrrc:b041CМ041C041C041C041CМММ	I
    //   23: if_icmpeq +14 -> 37
    //   26: invokestatic 48	kkkkkk/rrrrrc:b043Fпп043F043Fпп043Fпп	()I
    //   29: putstatic 56	kkkkkk/rrrrrc:bМ041CМ041C041C041CМММ	I
    //   32: bipush 21
    //   34: putstatic 58	kkkkkk/rrrrrc:b041CМ041C041C041C041CМММ	I
    //   37: aload_1
    //   38: invokevirtual 120	kkkkkk/rrcrrc:bп043F043Fпппп043Fпп	()Lio/reactivex/Maybe;
    //   41: astore_1
    //   42: aload_1
    //   43: areturn
    //   44: astore_1
    //   45: aload_1
    //   46: athrow
    //   47: astore_1
    //   48: aload_1
    //   49: athrow
    // Local variable table:
    //   start	length	slot	name	signature
    //   0	50	0	this	rrrrrc
    //   4	39	1	localObject	Object
    //   44	2	1	localException1	Exception
    //   47	2	1	localException2	Exception
    // Exception table:
    //   from	to	target	type
    //   0	5	44	java/lang/Exception
    //   37	42	47	java/lang/Exception
  }
  
  /* Error */
  public boolean b043Fпппп043Fп043Fпп(fbfffb paramFbfffb)
  {
    // Byte code:
    //   0: iconst_0
    //   1: istore_2
    //   2: aload_0
    //   3: aload_1
    //   4: invokespecial 125	kkkkkk/rrrrrc:bпп043F043F043Fпп043Fпп	(Lkkkkkk/fbfffb;)Lkkkkkk/unnnun;
    //   7: astore_1
    //   8: aload_1
    //   9: ifnull +24 -> 33
    //   12: aload_1
    //   13: invokevirtual 130	kkkkkk/unnnun:bпппп043Fпппп043F	()Z
    //   16: ifeq +28 -> 44
    //   19: iload_2
    //   20: iconst_0
    //   21: idiv
    //   22: istore_2
    //   23: goto -4 -> 19
    //   26: astore_1
    //   27: invokestatic 48	kkkkkk/rrrrrc:b043Fпп043F043Fпп043Fпп	()I
    //   30: putstatic 56	kkkkkk/rrrrrc:bМ041CМ041C041C041CМММ	I
    //   33: iconst_1
    //   34: ireturn
    //   35: astore_1
    //   36: invokestatic 48	kkkkkk/rrrrrc:b043Fпп043F043Fпп043Fпп	()I
    //   39: putstatic 56	kkkkkk/rrrrrc:bМ041CМ041C041C041CМММ	I
    //   42: iconst_0
    //   43: ireturn
    //   44: new 95	java/lang/NullPointerException
    //   47: dup
    //   48: invokespecial 96	java/lang/NullPointerException:<init>	()V
    //   51: athrow
    // Local variable table:
    //   start	length	slot	name	signature
    //   0	52	0	this	rrrrrc
    //   0	52	1	paramFbfffb	fbfffb
    //   1	22	2	i	int
    // Exception table:
    //   from	to	target	type
    //   19	23	26	java/lang/Exception
    //   44	52	35	java/lang/Exception
  }
  
  public boolean bп043F043F043F043Fпп043Fпп(fbfffb paramFbfffb)
  {
    if ((bМ041CМ041C041C041CМММ + b041C041CМ041C041C041CМММ) * bМ041CМ041C041C041CМММ % bММ041C041C041C041CМММ != b041CМ041C041C041C041CМММ)
    {
      bМ041CМ041C041C041CМММ = b043Fпп043F043Fпп043Fпп();
      if ((bМ041CМ041C041C041CМММ + b041C041CМ041C041C041CМММ) * bМ041CМ041C041C041CМММ % bММ041C041C041C041CМММ != b041CМ041C041C041C041CМММ)
      {
        bМ041CМ041C041C041CМММ = 86;
        b041CМ041C041C041C041CМММ = b043Fпп043F043Fпп043Fпп();
      }
      b041CМ041C041C041C041CМММ = 27;
    }
    if (bпп043F043F043Fпп043Fпп(paramFbfffb) != null)
    {
      return true;
      return false;
    }
    switch (0)
    {
    }
    for (;;)
    {
      switch (0)
      {
      case 1: 
      default: 
        for (;;)
        {
          switch (1)
          {
          }
        }
      }
      switch (1)
      {
      }
    }
  }
  
  public Single<ccrrcr> bпп043Fпп043Fп043Fпп(rrcrcr paramRrcrcr)
  {
    Single localSingle = Single.fromCallable(new rrrrrc.2(this, paramRrcrcr));
    paramRrcrcr = new rrrrrc.1(this, paramRrcrcr);
    switch (1)
    {
    case 0: 
    default: 
      for (;;)
      {
        switch (0)
        {
        }
      }
    }
    paramRrcrcr = localSingle.flatMap(paramRrcrcr);
    if ((bМ041CМ041C041C041CМММ + b041C041CМ041C041C041CМММ) * bМ041CМ041C041C041CМММ % bппп043F043Fпп043Fпп() != b041CМ041C041C041C041CМММ)
    {
      int i = bМ041CМ041C041C041CМММ;
      switch (i * (bп043Fп043F043Fпп043Fпп() + i) % bММ041C041C041C041CМММ)
      {
      default: 
        bМ041CМ041C041C041CМММ = b043Fпп043F043Fпп043Fпп();
        b041CМ041C041C041C041CМММ = 68;
      }
      bМ041CМ041C041C041CМММ = 41;
      b041CМ041C041C041C041CМММ = 99;
    }
    return paramRrcrcr;
  }
  
  public boolean bппппп043Fп043Fпп(fbfffb paramFbfffb)
  {
    boolean bool1;
    if ((bп043Fппп043Fп043Fпп()) && (b043F043F043F043F043Fпп043Fпп()) && (b043F043Fппп043Fп043Fпп()) && (!b043Fпппп043Fп043Fпп(paramFbfffb)))
    {
      boolean bool2 = true;
      int i = bМ041CМ041C041C041CМММ;
      bool1 = bool2;
      switch (i * (b041C041CМ041C041C041CМММ + i) % bММ041C041C041C041CМММ)
      {
      default: 
        bМ041CМ041C041C041CМММ = b043Fпп043F043Fпп043Fпп();
        b041CМ041C041C041C041CМММ = b043Fпп043F043Fпп043Fпп();
        bool1 = bool2;
      }
    }
    do
    {
      return bool1;
      bool1 = false;
    } while ((bМ041CМ041C041C041CМММ + b041C041CМ041C041C041CМММ) * bМ041CМ041C041C041CМММ % bММ041C041C041C041CМММ == b041CМ041C041C041C041CМММ);
    bМ041CМ041C041C041CМММ = b043Fпп043F043Fпп043Fпп();
    b041CМ041C041C041C041CМММ = 13;
    return false;
  }
}
