package kkkkkk;

import java.io.Serializable;
import java.util.List;
import java.util.UUID;

public class ttktkk
  implements Serializable
{
  private String b041A041A041A041AК041AК041AК041A;
  private UUID b041A041AКК041A041AК041AК041A;
  private String b041AККК041A041AК041AК041A;
  private String bК041AКК041A041AК041AК041A;
  private final List<aahhah> bКККК041A041AК041AК041A;
  
  public ttktkk(bbbfbf paramBbbfbf)
  {
    this.b041A041AКК041A041AК041AК041A = paramBbbfbf.bВ0412В04120412В041204120412В();
    this.bКККК041A041AК041AК041A = paramBbbfbf.b0412ВВ04120412В041204120412В();
  }
  
  public static int b04100410ААА0410А0410АА()
  {
    return 71;
  }
  
  public static int b0410А0410АА0410А0410АА()
  {
    return 2;
  }
  
  public static int bА0410ААА0410А0410АА()
  {
    return 1;
  }
  
  public static int bАА0410АА0410А0410АА()
  {
    return 0;
  }
  
  public List<aahhah> b041004100410АА0410А0410АА()
  {
    int i = b04100410ААА0410А0410АА();
    switch (i * (bА0410ААА0410А0410АА() + i) % b0410А0410АА0410А0410АА())
    {
    default: 
      switch (1)
      {
      case 0: 
      default: 
        for (;;)
        {
          switch (1)
          {
          }
        }
      }
      if ((b04100410ААА0410А0410АА() + bА0410ААА0410А0410АА()) * b04100410ААА0410А0410АА() % b0410А0410АА0410А0410АА() == bАА0410АА0410А0410АА()) {
        break;
      }
    }
    try
    {
      List localList = this.bКККК041A041AК041AК041A;
      return localList;
    }
    catch (Exception localException)
    {
      throw localException;
    }
  }
  
  public void b04100410А0410А0410А0410АА(String paramString)
  {
    this.b041A041A041A041AК041AК041AК041A = paramString;
    if ((b04100410ААА0410А0410АА() + bА0410ААА0410А0410АА()) * b04100410ААА0410А0410АА() % b0410А0410АА0410А0410АА() != bАА0410АА0410А0410АА()) {}
  }
  
  /* Error */
  public void b0410А04100410А0410А0410АА(String paramString)
  {
    // Byte code:
    //   0: invokestatic 45	kkkkkk/ttktkk:b04100410ААА0410А0410АА	()I
    //   3: istore_2
    //   4: invokestatic 47	kkkkkk/ttktkk:bА0410ААА0410А0410АА	()I
    //   7: istore_3
    //   8: invokestatic 45	kkkkkk/ttktkk:b04100410ААА0410А0410АА	()I
    //   11: istore 4
    //   13: invokestatic 49	kkkkkk/ttktkk:b0410А0410АА0410А0410АА	()I
    //   16: istore 5
    //   18: iload_2
    //   19: iload_3
    //   20: iadd
    //   21: iload 4
    //   23: imul
    //   24: iload 5
    //   26: irem
    //   27: invokestatic 51	kkkkkk/ttktkk:bАА0410АА0410А0410АА	()I
    //   30: if_icmpeq +3 -> 33
    //   33: aload_0
    //   34: aload_1
    //   35: putfield 60	kkkkkk/ttktkk:bК041AКК041A041AК041AК041A	Ljava/lang/String;
    //   38: iconst_0
    //   39: tableswitch	default:+21->60, 0:+48->87, 1:+-1->38
    //   60: iconst_0
    //   61: tableswitch	default:+23->84, 0:+26->87, 1:+-23->38
    //   84: goto -24 -> 60
    //   87: invokestatic 45	kkkkkk/ttktkk:b04100410ААА0410А0410АА	()I
    //   90: istore_2
    //   91: iload_2
    //   92: invokestatic 47	kkkkkk/ttktkk:bА0410ААА0410А0410АА	()I
    //   95: iload_2
    //   96: iadd
    //   97: imul
    //   98: invokestatic 49	kkkkkk/ttktkk:b0410А0410АА0410А0410АА	()I
    //   101: irem
    //   102: tableswitch	default:+18->120, 0:+18->120
    //   120: return
    //   121: astore_1
    //   122: aload_1
    //   123: athrow
    //   124: astore_1
    //   125: aload_1
    //   126: athrow
    // Local variable table:
    //   start	length	slot	name	signature
    //   0	127	0	this	ttktkk
    //   0	127	1	paramString	String
    //   3	95	2	i	int
    //   7	14	3	j	int
    //   11	13	4	k	int
    //   16	11	5	m	int
    // Exception table:
    //   from	to	target	type
    //   0	18	121	java/lang/Exception
    //   18	33	124	java/lang/Exception
    //   33	38	124	java/lang/Exception
  }
  
  public String b0410АА0410А0410А0410АА()
  {
    int i = b04100410ААА0410А0410АА();
    int j = bА0410ААА0410А0410АА();
    int k = b0410А0410АА0410А0410АА();
    int m = b04100410ААА0410А0410АА();
    switch (m * (bА0410ААА0410А0410АА() + m) % b0410А0410АА0410А0410АА())
    {
    }
    switch (i * (j + i) % k)
    {
    }
    String str = this.bК041AКК041A041AК041AК041A;
    switch (1)
    {
    case 0: 
    default: 
      for (;;)
      {
        switch (1)
        {
        }
      }
    }
    switch (1)
    {
    case 0: 
    default: 
      for (;;)
      {
        switch (0)
        {
        }
      }
    }
    return str;
  }
  
  public String bА04100410АА0410А0410АА()
  {
    int i = b04100410ААА0410А0410АА();
    int j = b04100410ААА0410А0410АА();
    switch (j * (bА0410ААА0410А0410АА() + j) % b0410А0410АА0410А0410АА())
    {
    }
    if ((i + bА0410ААА0410А0410АА()) * b04100410ААА0410А0410АА() % b0410А0410АА0410А0410АА() != bАА0410АА0410А0410АА()) {}
    try
    {
      String str = this.b041A041A041A041AК041AК041AК041A;
      return str;
    }
    catch (Exception localException)
    {
      throw localException;
    }
  }
  
  public UUID bА0410А0410А0410А0410АА()
  {
    return this.b041A041AКК041A041AК041AК041A;
  }
  
  /* Error */
  public void bАА04100410А0410А0410АА(String paramString)
  {
    // Byte code:
    //   0: iconst_3
    //   1: istore_3
    //   2: iload_3
    //   3: istore_2
    //   4: iconst_1
    //   5: tableswitch	default:+23->28, 0:+-3->2, 1:+50->55
    //   28: iload_3
    //   29: istore_2
    //   30: iconst_0
    //   31: tableswitch	default:+21->52, 0:+24->55, 1:+-29->2
    //   52: goto -24 -> 28
    //   55: iload_2
    //   56: iconst_0
    //   57: idiv
    //   58: istore_3
    //   59: iload_3
    //   60: istore_2
    //   61: goto -6 -> 55
    //   64: iload_2
    //   65: iconst_0
    //   66: idiv
    //   67: istore_3
    //   68: iload_3
    //   69: istore_2
    //   70: invokestatic 45	kkkkkk/ttktkk:b04100410ААА0410А0410АА	()I
    //   73: invokestatic 47	kkkkkk/ttktkk:bА0410ААА0410А0410АА	()I
    //   76: iadd
    //   77: invokestatic 45	kkkkkk/ttktkk:b04100410ААА0410А0410АА	()I
    //   80: imul
    //   81: invokestatic 49	kkkkkk/ttktkk:b0410А0410АА0410А0410АА	()I
    //   84: irem
    //   85: invokestatic 51	kkkkkk/ttktkk:bАА0410АА0410А0410АА	()I
    //   88: if_icmpeq -24 -> 64
    //   91: iload_3
    //   92: istore_2
    //   93: goto -29 -> 64
    //   96: astore 4
    //   98: aload_0
    //   99: aload_1
    //   100: putfield 67	kkkkkk/ttktkk:b041AККК041A041AК041AК041A	Ljava/lang/String;
    //   103: return
    //   104: astore_1
    //   105: aload_1
    //   106: athrow
    //   107: new 69	java/lang/NullPointerException
    //   110: dup
    //   111: invokespecial 70	java/lang/NullPointerException:<init>	()V
    //   114: athrow
    //   115: astore 4
    //   117: goto -53 -> 64
    //   120: astore 4
    //   122: goto -15 -> 107
    // Local variable table:
    //   start	length	slot	name	signature
    //   0	125	0	this	ttktkk
    //   0	125	1	paramString	String
    //   3	90	2	i	int
    //   1	91	3	j	int
    //   96	1	4	localException1	Exception
    //   115	1	4	localException2	Exception
    //   120	1	4	localException3	Exception
    // Exception table:
    //   from	to	target	type
    //   107	115	96	java/lang/Exception
    //   98	103	104	java/lang/Exception
    //   55	59	115	java/lang/Exception
    //   64	68	120	java/lang/Exception
  }
  
  public String bААА0410А0410А0410АА()
  {
    int i = b04100410ААА0410А0410АА();
    int j = bА0410ААА0410А0410АА();
    int k = b04100410ААА0410А0410АА();
    int m = b04100410ААА0410А0410АА();
    switch (m * (bА0410ААА0410А0410АА() + m) % b0410А0410АА0410А0410АА())
    {
    }
    switch (0)
    {
    case 1: 
    default: 
      for (;;)
      {
        switch (0)
        {
        }
      }
    }
    if ((i + j) * k % b0410А0410АА0410А0410АА() != bАА0410АА0410А0410АА()) {}
    return this.b041AККК041A041AК041AК041A;
  }
}
