package kkkkkk;

import java.text.SimpleDateFormat;
import org.json.JSONException;
import org.json.JSONObject;

public class tttxxt
{
  public static final String b042A042A042AЪ042AЪ042AЪ042A = tttxxt.class.getSimpleName();
  public static final String b042A042AЪЪ042AЪ042AЪ042A = "_`ab\027XY\032RS\0209:-AB0JK%MNO";
  public static int b042A042AЪЪЪ042A042AЪ042A = 0;
  public static final String b042AЪ042AЪ042AЪ042AЪ042A = "*/\"";
  public static int b042AЪ042AЪЪ042A042AЪ042A = 2;
  public static final String b042AЪЪ042A042AЪ042AЪ042A = "LJE";
  public static final String b042AЪЪЪ042AЪ042AЪ042A = gguuuu.bккккк043Aкк043A043A(b042AЪЪЪ042AЪ042AЪ042A, 'U', '\000');
  public static final String bЪ042A042AЪ042AЪ042AЪ042A = "zlwn{wghi";
  public static final String bЪ042AЪЪ042AЪ042AЪ042A = gguuuu.bк043Aккк043Aкк043A043A(bЪ042AЪЪ042AЪ042AЪ042A, 'µ', 'ÿ', '\002');
  public static int bЪ042AЪЪЪ042A042AЪ042A = 18;
  public static final String bЪЪ042AЪ042AЪ042AЪ042A = "(*!\005\035-\033!";
  public static int bЪЪ042AЪЪ042A042AЪ042A = 1;
  public static final String bЪЪЪ042A042AЪ042AЪ042A = "nbe\\";
  private String b042A042A042A042A042AЪ042AЪ042A;
  private SimpleDateFormat b042A042AЪ042A042AЪ042AЪ042A;
  private String b042AЪ042A042A042AЪ042AЪ042A;
  private String b042AЪЪЪЪ042A042AЪ042A;
  private String bЪ042A042A042A042AЪ042AЪ042A;
  private String bЪ042AЪ042A042AЪ042AЪ042A;
  private String bЪЪ042A042A042AЪ042AЪ042A;
  private String bЪЪЪЪЪ042A042AЪ042A;
  
  static
  {
    b042A042AЪЪ042AЪ042AЪ042A = gguuuu.bккккк043Aкк043A043A(b042A042AЪЪ042AЪ042AЪ042A, 'ä', '\000');
    bЪЪ042AЪ042AЪ042AЪ042A = gguuuu.bккккк043Aкк043A043A(bЪЪ042AЪ042AЪ042AЪ042A, 'D', '\005');
    b042AЪ042AЪ042AЪ042AЪ042A = gguuuu.bккккк043Aкк043A043A(b042AЪ042AЪ042AЪ042AЪ042A, 'à', '\003');
    bЪ042A042AЪ042AЪ042AЪ042A = gguuuu.bк043Aккк043Aкк043A043A(bЪ042A042AЪ042AЪ042AЪ042A, ';', 'Æ', '\000');
    if ((bЪ042AЪЪЪ042A042AЪ042A + bЪЪ042AЪЪ042A042AЪ042A) * bЪ042AЪЪЪ042A042AЪ042A % b042AЪ042AЪЪ042A042AЪ042A != b042A042AЪЪЪ042A042AЪ042A)
    {
      bЪ042AЪЪЪ042A042AЪ042A = bии0438и0438и04380438ии();
      b042A042AЪЪЪ042A042AЪ042A = bии0438и0438и04380438ии();
    }
    bЪЪЪ042A042AЪ042AЪ042A = gguuuu.bк043Aккк043Aкк043A043A(bЪЪЪ042A042AЪ042AЪ042A, 'Y', ',', '\002');
    b042AЪЪ042A042AЪ042AЪ042A = gguuuu.bк043Aккк043Aкк043A043A(b042AЪЪ042A042AЪ042AЪ042A, 'É', '', '\003');
  }
  
  public tttxxt(String paramString1, String paramString2, String paramString3, String paramString4)
  {
    this.bЪЪ042A042A042AЪ042AЪ042A = paramString1;
    this.b042AЪ042A042A042AЪ042AЪ042A = paramString2;
    this.bЪ042A042A042A042AЪ042AЪ042A = paramString3;
    this.b042A042A042A042A042AЪ042AЪ042A = paramString4;
  }
  
  public tttxxt(String paramString1, String paramString2, String paramString3, String paramString4, String paramString5)
  {
    this(paramString1, paramString2, paramString3, paramString4);
    this.bЪ042AЪ042A042AЪ042AЪ042A = paramString5;
    this.b042A042AЪ042A042AЪ042AЪ042A = new SimpleDateFormat(gguuuu.bккккк043Aкк043A043A(">=<;m-,j! Z\002\001q\004\003n\007\006]\004\003\002", ']', '\003'));
  }
  
  public tttxxt(JSONObject paramJSONObject)
  {
    try
    {
      this.bЪЪ042A042A042AЪ042AЪ042A = paramJSONObject.getString(gguuuu.bккккк043Aкк043A043A("\004\b\001f\001\023\003\013", '2', '\001'));
      this.b042AЪ042A042A042AЪ042AЪ042A = paramJSONObject.getString(gguuuu.bк043Aккк043Aкк043A043A("\037,,3%96", '', 'Ý', '\001'));
      this.bЪ042A042A042A042AЪ042AЪ042A = paramJSONObject.getString(gguuuu.bк043Aккк043Aкк043A043A("KPC", 'U', 'L', '\002'));
      this.b042A042A042A042A042AЪ042AЪ042A = paramJSONObject.getString(gguuuu.bк043Aккк043Aкк043A043A("cWd]lj\\_b", '`', '', '\003'));
      this.bЪ042AЪ042A042AЪ042AЪ042A = paramJSONObject.getString(gguuuu.bк043Aккк043Aкк043A043A("\030\031\030#( %x\023", '}', '4', '\000'));
      this.b042AЪЪЪЪ042A042AЪ042A = paramJSONObject.getString(gguuuu.bк043Aккк043Aкк043A043A("!\037\032", 'Î', '[', '\003'));
      this.bЪЪЪЪЪ042A042AЪ042A = paramJSONObject.getString(gguuuu.bккккк043Aкк043A043A("0&+$", 'Ü', '\004'));
      return;
    }
    catch (JSONException paramJSONObject)
    {
      xtxtxt.bии0438и04380438и0438ии(b042A042A042AЪ042AЪ042AЪ042A, gguuuu.bк043Aккк043Aкк043A043A("#\035v\037\032\030w\n\021\013\b\030\\Ajrmka\024}~\t\f\005\0033", '', 'Ê', '\002') + paramJSONObject.getMessage());
    }
  }
  
  public static int b043804380438и0438и04380438ии()
  {
    return 2;
  }
  
  public static int b0438и0438и0438и04380438ии()
  {
    return 1;
  }
  
  public static int bи04380438и0438и04380438ии()
  {
    return 0;
  }
  
  public static int bии0438и0438и04380438ии()
  {
    return 71;
  }
  
  /* Error */
  public tttxxt b04380438043804380438и04380438ии(String paramString)
  {
    // Byte code:
    //   0: getstatic 74	kkkkkk/tttxxt:bЪ042AЪЪЪ042A042AЪ042A	I
    //   3: istore_2
    //   4: getstatic 76	kkkkkk/tttxxt:bЪЪ042AЪЪ042A042AЪ042A	I
    //   7: istore_3
    //   8: getstatic 74	kkkkkk/tttxxt:bЪ042AЪЪЪ042A042AЪ042A	I
    //   11: istore 4
    //   13: getstatic 78	kkkkkk/tttxxt:b042AЪ042AЪЪ042A042AЪ042A	I
    //   16: istore 5
    //   18: getstatic 74	kkkkkk/tttxxt:bЪ042AЪЪЪ042A042AЪ042A	I
    //   21: getstatic 76	kkkkkk/tttxxt:bЪЪ042AЪЪ042A042AЪ042A	I
    //   24: iadd
    //   25: getstatic 74	kkkkkk/tttxxt:bЪ042AЪЪЪ042A042AЪ042A	I
    //   28: imul
    //   29: getstatic 78	kkkkkk/tttxxt:b042AЪ042AЪЪ042A042AЪ042A	I
    //   32: irem
    //   33: invokestatic 180	kkkkkk/tttxxt:bи04380438и0438и04380438ии	()I
    //   36: if_icmpeq +13 -> 49
    //   39: bipush 97
    //   41: putstatic 74	kkkkkk/tttxxt:bЪ042AЪЪЪ042A042AЪ042A	I
    //   44: bipush 33
    //   46: putstatic 80	kkkkkk/tttxxt:b042A042AЪЪЪ042A042AЪ042A	I
    //   49: getstatic 80	kkkkkk/tttxxt:b042A042AЪЪЪ042A042AЪ042A	I
    //   52: istore 6
    //   54: iload_2
    //   55: iload_3
    //   56: iadd
    //   57: iload 4
    //   59: imul
    //   60: iload 5
    //   62: irem
    //   63: iload 6
    //   65: if_icmpeq +13 -> 78
    //   68: bipush 92
    //   70: putstatic 74	kkkkkk/tttxxt:bЪ042AЪЪЪ042A042AЪ042A	I
    //   73: bipush 51
    //   75: putstatic 80	kkkkkk/tttxxt:b042A042AЪЪЪ042A042AЪ042A	I
    //   78: aload_0
    //   79: aload_1
    //   80: putfield 114	kkkkkk/tttxxt:bЪ042AЪ042A042AЪ042AЪ042A	Ljava/lang/String;
    //   83: aload_0
    //   84: areturn
    //   85: astore_1
    //   86: aload_1
    //   87: athrow
    //   88: astore_1
    //   89: aload_1
    //   90: athrow
    //   91: astore_1
    //   92: aload_1
    //   93: athrow
    // Local variable table:
    //   start	length	slot	name	signature
    //   0	94	0	this	tttxxt
    //   0	94	1	paramString	String
    //   3	54	2	i	int
    //   7	50	3	j	int
    //   11	49	4	k	int
    //   16	47	5	m	int
    //   52	14	6	n	int
    // Exception table:
    //   from	to	target	type
    //   78	83	85	java/lang/Exception
    //   68	78	88	java/lang/Exception
    //   86	88	88	java/lang/Exception
    //   0	18	91	java/lang/Exception
    //   49	54	91	java/lang/Exception
  }
  
  public JSONObject b043804380438ии043804380438ии()
  {
    throw new Runtime("d2j fail translate: java.lang.IndexOutOfBoundsException: fromIndex < 0: -1\n\tat java.util.BitSet.nextSetBit(BitSet.java:712)\n\tat com.googlecode.dex2jar.ir.ts.array.FillArrayTransformer.makeSureAllElementAreAssigned(FillArrayTransformer.java:505)\n\tat com.googlecode.dex2jar.ir.ts.array.FillArrayTransformer.transformReportChanged(FillArrayTransformer.java:123)\n\tat com.googlecode.dex2jar.ir.ts.StatedTransformer.transform(StatedTransformer.java:10)\n\tat com.googlecode.d2j.dex.Dex2jar$2.optimize(Dex2jar.java:149)\n\tat com.googlecode.d2j.dex.Dex2Asm.convertCode(Dex2Asm.java:414)\n\tat com.googlecode.d2j.dex.ExDex2Asm.convertCode(ExDex2Asm.java:42)\n\tat com.googlecode.d2j.dex.Dex2jar$2.convertCode(Dex2jar.java:128)\n\tat com.googlecode.d2j.dex.Dex2Asm.convertMethod(Dex2Asm.java:509)\n\tat com.googlecode.d2j.dex.Dex2Asm.convertClass(Dex2Asm.java:406)\n\tat com.googlecode.d2j.dex.Dex2Asm.convertDex(Dex2Asm.java:422)\n\tat com.googlecode.d2j.dex.Dex2jar.doTranslate(Dex2jar.java:172)\n\tat com.googlecode.d2j.dex.Dex2jar.to(Dex2jar.java:272)\n\tat com.googlecode.dex2jar.tools.Dex2jarCmd.doCommandLine(Dex2jarCmd.java:108)\n\tat com.googlecode.dex2jar.tools.BaseCmd.doMain(BaseCmd.java:288)\n\tat com.googlecode.dex2jar.tools.Dex2jarCmd.main(Dex2jarCmd.java:32)\n");
  }
  
  /* Error */
  public String b04380438и04380438и04380438ии()
  {
    // Byte code:
    //   0: aload_0
    //   1: getfield 107	kkkkkk/tttxxt:bЪ042A042A042A042AЪ042AЪ042A	Ljava/lang/String;
    //   4: astore 6
    //   6: invokestatic 84	kkkkkk/tttxxt:bии0438и0438и04380438ии	()I
    //   9: istore_1
    //   10: getstatic 76	kkkkkk/tttxxt:bЪЪ042AЪЪ042A042AЪ042A	I
    //   13: istore_2
    //   14: invokestatic 84	kkkkkk/tttxxt:bии0438и0438и04380438ии	()I
    //   17: istore_3
    //   18: getstatic 74	kkkkkk/tttxxt:bЪ042AЪЪЪ042A042AЪ042A	I
    //   21: istore 4
    //   23: iload 4
    //   25: getstatic 76	kkkkkk/tttxxt:bЪЪ042AЪЪ042A042AЪ042A	I
    //   28: iload 4
    //   30: iadd
    //   31: imul
    //   32: getstatic 78	kkkkkk/tttxxt:b042AЪ042AЪЪ042A042AЪ042A	I
    //   35: irem
    //   36: tableswitch	default:+20->56, 0:+32->68
    //   56: invokestatic 84	kkkkkk/tttxxt:bии0438и0438и04380438ии	()I
    //   59: putstatic 74	kkkkkk/tttxxt:bЪ042AЪЪЪ042A042AЪ042A	I
    //   62: invokestatic 84	kkkkkk/tttxxt:bии0438и0438и04380438ии	()I
    //   65: putstatic 80	kkkkkk/tttxxt:b042A042AЪЪЪ042A042AЪ042A	I
    //   68: getstatic 78	kkkkkk/tttxxt:b042AЪ042AЪЪ042A042AЪ042A	I
    //   71: istore 4
    //   73: getstatic 80	kkkkkk/tttxxt:b042A042AЪЪЪ042A042AЪ042A	I
    //   76: istore 5
    //   78: iload_1
    //   79: iload_2
    //   80: iadd
    //   81: iload_3
    //   82: imul
    //   83: iload 4
    //   85: irem
    //   86: iload 5
    //   88: if_icmpeq +15 -> 103
    //   91: invokestatic 84	kkkkkk/tttxxt:bии0438и0438и04380438ии	()I
    //   94: putstatic 74	kkkkkk/tttxxt:bЪ042AЪЪЪ042A042AЪ042A	I
    //   97: invokestatic 84	kkkkkk/tttxxt:bии0438и0438и04380438ии	()I
    //   100: putstatic 80	kkkkkk/tttxxt:b042A042AЪЪЪ042A042AЪ042A	I
    //   103: aload 6
    //   105: areturn
    //   106: astore 6
    //   108: aload 6
    //   110: athrow
    //   111: astore 6
    //   113: aload 6
    //   115: athrow
    //   116: astore 6
    //   118: aload 6
    //   120: athrow
    // Local variable table:
    //   start	length	slot	name	signature
    //   0	121	0	this	tttxxt
    //   9	72	1	i	int
    //   13	68	2	j	int
    //   17	66	3	k	int
    //   21	65	4	m	int
    //   76	13	5	n	int
    //   4	100	6	str	String
    //   106	3	6	localException1	Exception
    //   111	3	6	localException2	Exception
    //   116	3	6	localException3	Exception
    // Exception table:
    //   from	to	target	type
    //   0	6	106	java/lang/Exception
    //   6	18	111	java/lang/Exception
    //   73	78	111	java/lang/Exception
    //   108	111	111	java/lang/Exception
    //   68	73	116	java/lang/Exception
    //   91	103	116	java/lang/Exception
  }
  
  /* Error */
  public tttxxt b04380438иии043804380438ии(String paramString)
  {
    // Byte code:
    //   0: getstatic 74	kkkkkk/tttxxt:bЪ042AЪЪЪ042A042AЪ042A	I
    //   3: istore_2
    //   4: iload_2
    //   5: getstatic 76	kkkkkk/tttxxt:bЪЪ042AЪЪ042A042AЪ042A	I
    //   8: iload_2
    //   9: iadd
    //   10: imul
    //   11: getstatic 78	kkkkkk/tttxxt:b042AЪ042AЪЪ042A042AЪ042A	I
    //   14: irem
    //   15: tableswitch	default:+17->32, 0:+27->42
    //   32: bipush 53
    //   34: putstatic 74	kkkkkk/tttxxt:bЪ042AЪЪЪ042A042AЪ042A	I
    //   37: bipush 13
    //   39: putstatic 80	kkkkkk/tttxxt:b042A042AЪЪЪ042A042AЪ042A	I
    //   42: getstatic 74	kkkkkk/tttxxt:bЪ042AЪЪЪ042A042AЪ042A	I
    //   45: istore_2
    //   46: getstatic 76	kkkkkk/tttxxt:bЪЪ042AЪЪ042A042AЪ042A	I
    //   49: istore_3
    //   50: getstatic 74	kkkkkk/tttxxt:bЪ042AЪЪЪ042A042AЪ042A	I
    //   53: istore 4
    //   55: getstatic 78	kkkkkk/tttxxt:b042AЪ042AЪЪ042A042AЪ042A	I
    //   58: istore 5
    //   60: getstatic 80	kkkkkk/tttxxt:b042A042AЪЪЪ042A042AЪ042A	I
    //   63: istore 6
    //   65: iload_2
    //   66: iload_3
    //   67: iadd
    //   68: iload 4
    //   70: imul
    //   71: iload 5
    //   73: irem
    //   74: iload 6
    //   76: if_icmpeq +14 -> 90
    //   79: invokestatic 84	kkkkkk/tttxxt:bии0438и0438и04380438ии	()I
    //   82: putstatic 74	kkkkkk/tttxxt:bЪ042AЪЪЪ042A042AЪ042A	I
    //   85: bipush 9
    //   87: putstatic 80	kkkkkk/tttxxt:b042A042AЪЪЪ042A042AЪ042A	I
    //   90: aload_0
    //   91: aload_1
    //   92: putfield 109	kkkkkk/tttxxt:b042A042A042A042A042AЪ042AЪ042A	Ljava/lang/String;
    //   95: aload_0
    //   96: areturn
    //   97: astore_1
    //   98: aload_1
    //   99: athrow
    //   100: astore_1
    //   101: aload_1
    //   102: athrow
    // Local variable table:
    //   start	length	slot	name	signature
    //   0	103	0	this	tttxxt
    //   0	103	1	paramString	String
    //   3	65	2	i	int
    //   49	19	3	j	int
    //   53	18	4	k	int
    //   58	16	5	m	int
    //   63	14	6	n	int
    // Exception table:
    //   from	to	target	type
    //   42	65	97	java/lang/Exception
    //   90	95	97	java/lang/Exception
    //   79	90	100	java/lang/Exception
  }
  
  public String b0438и043804380438и04380438ии()
  {
    String str = this.bЪЪЪЪЪ042A042AЪ042A;
    int i = bии0438и0438и04380438ии();
    int j = bии0438и0438и04380438ии();
    switch (j * (bЪЪ042AЪЪ042A042AЪ042A + j) % b042AЪ042AЪЪ042A042AЪ042A)
    {
    default: 
      bЪ042AЪЪЪ042A042AЪ042A = 4;
      b042A042AЪЪЪ042A042AЪ042A = 69;
    }
    if ((i + bЪЪ042AЪЪ042A042AЪ042A) * bии0438и0438и04380438ии() % b042AЪ042AЪЪ042A042AЪ042A != b042A042AЪЪЪ042A042AЪ042A)
    {
      bЪ042AЪЪЪ042A042AЪ042A = bии0438и0438и04380438ии();
      b042A042AЪЪЪ042A042AЪ042A = bии0438и0438и04380438ии();
    }
    switch (0)
    {
    case 1: 
    default: 
      for (;;)
      {
        switch (1)
        {
        }
      }
    }
    return str;
  }
  
  /* Error */
  public tttxxt b0438и0438ии043804380438ии(String paramString)
  {
    // Byte code:
    //   0: getstatic 74	kkkkkk/tttxxt:bЪ042AЪЪЪ042A042AЪ042A	I
    //   3: istore_2
    //   4: getstatic 76	kkkkkk/tttxxt:bЪЪ042AЪЪ042A042AЪ042A	I
    //   7: istore_3
    //   8: getstatic 74	kkkkkk/tttxxt:bЪ042AЪЪЪ042A042AЪ042A	I
    //   11: istore 4
    //   13: getstatic 78	kkkkkk/tttxxt:b042AЪ042AЪЪ042A042AЪ042A	I
    //   16: istore 5
    //   18: getstatic 80	kkkkkk/tttxxt:b042A042AЪЪЪ042A042AЪ042A	I
    //   21: istore 6
    //   23: iload_2
    //   24: iload_3
    //   25: iadd
    //   26: iload 4
    //   28: imul
    //   29: iload 5
    //   31: irem
    //   32: iload 6
    //   34: if_icmpeq +15 -> 49
    //   37: invokestatic 84	kkkkkk/tttxxt:bии0438и0438и04380438ии	()I
    //   40: putstatic 74	kkkkkk/tttxxt:bЪ042AЪЪЪ042A042AЪ042A	I
    //   43: invokestatic 84	kkkkkk/tttxxt:bии0438и0438и04380438ии	()I
    //   46: putstatic 80	kkkkkk/tttxxt:b042A042AЪЪЪ042A042AЪ042A	I
    //   49: aload_0
    //   50: aload_1
    //   51: putfield 150	kkkkkk/tttxxt:bЪЪЪЪЪ042A042AЪ042A	Ljava/lang/String;
    //   54: iconst_0
    //   55: tableswitch	default:+21->76, 0:+92->147, 1:+-1->54
    //   76: getstatic 74	kkkkkk/tttxxt:bЪ042AЪЪЪ042A042AЪ042A	I
    //   79: istore_2
    //   80: iload_2
    //   81: getstatic 76	kkkkkk/tttxxt:bЪЪ042AЪЪ042A042AЪ042A	I
    //   84: iload_2
    //   85: iadd
    //   86: imul
    //   87: getstatic 78	kkkkkk/tttxxt:b042AЪ042AЪЪ042A042AЪ042A	I
    //   90: irem
    //   91: tableswitch	default:+17->108, 0:+28->119
    //   108: bipush 16
    //   110: putstatic 74	kkkkkk/tttxxt:bЪ042AЪЪЪ042A042AЪ042A	I
    //   113: invokestatic 84	kkkkkk/tttxxt:bии0438и0438и04380438ии	()I
    //   116: putstatic 80	kkkkkk/tttxxt:b042A042AЪЪЪ042A042AЪ042A	I
    //   119: iconst_0
    //   120: tableswitch	default:+24->144, 0:+27->147, 1:+-66->54
    //   144: goto -68 -> 76
    //   147: aload_0
    //   148: areturn
    //   149: astore_1
    //   150: aload_1
    //   151: athrow
    //   152: astore_1
    //   153: aload_1
    //   154: athrow
    // Local variable table:
    //   start	length	slot	name	signature
    //   0	155	0	this	tttxxt
    //   0	155	1	paramString	String
    //   3	84	2	i	int
    //   7	19	3	j	int
    //   11	18	4	k	int
    //   16	16	5	m	int
    //   21	14	6	n	int
    // Exception table:
    //   from	to	target	type
    //   0	23	149	java/lang/Exception
    //   49	54	149	java/lang/Exception
    //   37	49	152	java/lang/Exception
  }
  
  public String b0438ии04380438и04380438ии()
  {
    switch (1)
    {
    case 0: 
    default: 
      for (;;)
      {
        if ((bЪ042AЪЪЪ042A042AЪ042A + bЪЪ042AЪЪ042A042AЪ042A) * bЪ042AЪЪЪ042A042AЪ042A % b042AЪ042AЪЪ042A042AЪ042A != b042A042AЪЪЪ042A042AЪ042A)
        {
          bЪ042AЪЪЪ042A042AЪ042A = 76;
          b042A042AЪЪЪ042A042AЪ042A = bии0438и0438и04380438ии();
        }
        switch (0)
        {
        }
      }
    }
    String str = this.bЪЪ042A042A042AЪ042AЪ042A;
    if ((bЪ042AЪЪЪ042A042AЪ042A + bЪЪ042AЪЪ042A042AЪ042A) * bЪ042AЪЪЪ042A042AЪ042A % b043804380438и0438и04380438ии() != b042A042AЪЪЪ042A042AЪ042A)
    {
      bЪ042AЪЪЪ042A042AЪ042A = bии0438и0438и04380438ии();
      b042A042AЪЪЪ042A042AЪ042A = 20;
    }
    return str;
  }
  
  /* Error */
  public tttxxt b0438ииии043804380438ии(String paramString)
  {
    // Byte code:
    //   0: getstatic 74	kkkkkk/tttxxt:bЪ042AЪЪЪ042A042AЪ042A	I
    //   3: istore_2
    //   4: getstatic 76	kkkkkk/tttxxt:bЪЪ042AЪЪ042A042AЪ042A	I
    //   7: istore_3
    //   8: getstatic 74	kkkkkk/tttxxt:bЪ042AЪЪЪ042A042AЪ042A	I
    //   11: istore 4
    //   13: getstatic 78	kkkkkk/tttxxt:b042AЪ042AЪЪ042A042AЪ042A	I
    //   16: istore 5
    //   18: getstatic 80	kkkkkk/tttxxt:b042A042AЪЪЪ042A042AЪ042A	I
    //   21: istore 6
    //   23: iload_2
    //   24: iload_3
    //   25: iadd
    //   26: iload 4
    //   28: imul
    //   29: iload 5
    //   31: irem
    //   32: iload 6
    //   34: if_icmpeq +47 -> 81
    //   37: invokestatic 84	kkkkkk/tttxxt:bии0438и0438и04380438ии	()I
    //   40: putstatic 74	kkkkkk/tttxxt:bЪ042AЪЪЪ042A042AЪ042A	I
    //   43: bipush 71
    //   45: putstatic 80	kkkkkk/tttxxt:b042A042AЪЪЪ042A042AЪ042A	I
    //   48: getstatic 74	kkkkkk/tttxxt:bЪ042AЪЪЪ042A042AЪ042A	I
    //   51: getstatic 76	kkkkkk/tttxxt:bЪЪ042AЪЪ042A042AЪ042A	I
    //   54: iadd
    //   55: getstatic 74	kkkkkk/tttxxt:bЪ042AЪЪЪ042A042AЪ042A	I
    //   58: imul
    //   59: getstatic 78	kkkkkk/tttxxt:b042AЪ042AЪЪ042A042AЪ042A	I
    //   62: irem
    //   63: getstatic 80	kkkkkk/tttxxt:b042A042AЪЪЪ042A042AЪ042A	I
    //   66: if_icmpeq +15 -> 81
    //   69: invokestatic 84	kkkkkk/tttxxt:bии0438и0438и04380438ии	()I
    //   72: putstatic 74	kkkkkk/tttxxt:bЪ042AЪЪЪ042A042AЪ042A	I
    //   75: invokestatic 84	kkkkkk/tttxxt:bии0438и0438и04380438ии	()I
    //   78: putstatic 80	kkkkkk/tttxxt:b042A042AЪЪЪ042A042AЪ042A	I
    //   81: aload_0
    //   82: aload_1
    //   83: putfield 105	kkkkkk/tttxxt:b042AЪ042A042A042AЪ042AЪ042A	Ljava/lang/String;
    //   86: iconst_1
    //   87: tableswitch	default:+21->108, 0:+-1->86, 1:+48->135
    //   108: iconst_1
    //   109: tableswitch	default:+23->132, 0:+-23->86, 1:+26->135
    //   132: goto -24 -> 108
    //   135: aload_0
    //   136: areturn
    //   137: astore_1
    //   138: aload_1
    //   139: athrow
    //   140: astore_1
    //   141: aload_1
    //   142: athrow
    // Local variable table:
    //   start	length	slot	name	signature
    //   0	143	0	this	tttxxt
    //   0	143	1	paramString	String
    //   3	23	2	i	int
    //   7	19	3	j	int
    //   11	18	4	k	int
    //   16	16	5	m	int
    //   21	14	6	n	int
    // Exception table:
    //   from	to	target	type
    //   0	23	137	java/lang/Exception
    //   81	86	137	java/lang/Exception
    //   37	48	140	java/lang/Exception
  }
  
  public String bи0438043804380438и04380438ии()
  {
    String str = this.b042AЪЪЪЪ042A042AЪ042A;
    if ((bЪ042AЪЪЪ042A042AЪ042A + bЪЪ042AЪЪ042A042AЪ042A) * bЪ042AЪЪЪ042A042AЪ042A % b043804380438и0438и04380438ии() != b042A042AЪЪЪ042A042AЪ042A)
    {
      int i = bЪ042AЪЪЪ042A042AЪ042A;
      switch (i * (b0438и0438и0438и04380438ии() + i) % b043804380438и0438и04380438ии())
      {
      default: 
        bЪ042AЪЪЪ042A042AЪ042A = 69;
        b042A042AЪЪЪ042A042AЪ042A = bии0438и0438и04380438ии();
      }
      bЪ042AЪЪЪ042A042AЪ042A = bии0438и0438и04380438ии();
      b042A042AЪЪЪ042A042AЪ042A = 23;
    }
    switch (1)
    {
    case 0: 
    default: 
      for (;;)
      {
        switch (1)
        {
        }
      }
    }
    return str;
  }
  
  public tttxxt bи04380438ии043804380438ии(String paramString)
  {
    int i = bЪ042AЪЪЪ042A042AЪ042A;
    switch (i * (bЪЪ042AЪЪ042A042AЪ042A + i) % b043804380438и0438и04380438ии())
    {
    default: 
      bЪ042AЪЪЪ042A042AЪ042A = bии0438и0438и04380438ии();
      b042A042AЪЪЪ042A042AЪ042A = 27;
      switch (0)
      {
      case 1: 
      default: 
        for (;;)
        {
          switch (1)
          {
          }
        }
      }
      break;
    }
    this.b042AЪЪЪЪ042A042AЪ042A = paramString;
    return this;
  }
  
  public String bи0438и04380438и04380438ии()
  {
    int i = bЪ042AЪЪЪ042A042AЪ042A;
    switch (i * (bЪЪ042AЪЪ042A042AЪ042A + i) % b042AЪ042AЪЪ042A042AЪ042A)
    {
    default: 
      bЪ042AЪЪЪ042A042AЪ042A = bии0438и0438и04380438ии();
      b042A042AЪЪЪ042A042AЪ042A = bии0438и0438и04380438ии();
    }
    try
    {
      String str = this.b042AЪ042A042A042AЪ042AЪ042A;
      i = bЪ042AЪЪЪ042A042AЪ042A;
      int j = b0438и0438и0438и04380438ии();
      int k = b042AЪ042AЪЪ042A042AЪ042A;
      switch (0)
      {
      case 1: 
      default: 
        for (;;)
        {
          switch (0)
          {
          }
        }
      }
      switch (i * (j + i) % k)
      {
      default: 
        bЪ042AЪЪЪ042A042AЪ042A = 64;
        b042A042AЪЪЪ042A042AЪ042A = bии0438и0438и04380438ии();
      }
      return str;
    }
    catch (Exception localException)
    {
      throw localException;
    }
  }
  
  public tttxxt bи0438иии043804380438ии(String paramString)
  {
    throw new Runtime("d2j fail translate: java.lang.IndexOutOfBoundsException: fromIndex < 0: -1\n\tat java.util.BitSet.nextSetBit(BitSet.java:712)\n\tat com.googlecode.dex2jar.ir.ts.array.FillArrayTransformer.makeSureAllElementAreAssigned(FillArrayTransformer.java:505)\n\tat com.googlecode.dex2jar.ir.ts.array.FillArrayTransformer.transformReportChanged(FillArrayTransformer.java:123)\n\tat com.googlecode.dex2jar.ir.ts.StatedTransformer.transform(StatedTransformer.java:10)\n\tat com.googlecode.d2j.dex.Dex2jar$2.optimize(Dex2jar.java:149)\n\tat com.googlecode.d2j.dex.Dex2Asm.convertCode(Dex2Asm.java:414)\n\tat com.googlecode.d2j.dex.ExDex2Asm.convertCode(ExDex2Asm.java:42)\n\tat com.googlecode.d2j.dex.Dex2jar$2.convertCode(Dex2jar.java:128)\n\tat com.googlecode.d2j.dex.Dex2Asm.convertMethod(Dex2Asm.java:509)\n\tat com.googlecode.d2j.dex.Dex2Asm.convertClass(Dex2Asm.java:406)\n\tat com.googlecode.d2j.dex.Dex2Asm.convertDex(Dex2Asm.java:422)\n\tat com.googlecode.d2j.dex.Dex2jar.doTranslate(Dex2jar.java:172)\n\tat com.googlecode.d2j.dex.Dex2jar.to(Dex2jar.java:272)\n\tat com.googlecode.dex2jar.tools.Dex2jarCmd.doCommandLine(Dex2jarCmd.java:108)\n\tat com.googlecode.dex2jar.tools.BaseCmd.doMain(BaseCmd.java:288)\n\tat com.googlecode.dex2jar.tools.Dex2jarCmd.main(Dex2jarCmd.java:32)\n");
  }
  
  public String bии043804380438и04380438ии()
  {
    switch (1)
    {
    case 0: 
    default: 
      for (;;)
      {
        switch (0)
        {
        case 1: 
        default: 
          for (;;)
          {
            switch (1)
            {
            }
          }
        }
        switch (1)
        {
        }
      }
    }
    int i = bЪ042AЪЪЪ042A042AЪ042A;
    switch (i * (bЪЪ042AЪЪ042A042AЪ042A + i) % b042AЪ042AЪЪ042A042AЪ042A)
    {
    default: 
      bЪ042AЪЪЪ042A042AЪ042A = bии0438и0438и04380438ии();
      if ((bии0438и0438и04380438ии() + bЪЪ042AЪЪ042A042AЪ042A) * bии0438и0438и04380438ии() % b042AЪ042AЪЪ042A042AЪ042A != b042A042AЪЪЪ042A042AЪ042A)
      {
        bЪ042AЪЪЪ042A042AЪ042A = 70;
        b042A042AЪЪЪ042A042AЪ042A = bии0438и0438и04380438ии();
      }
      b042A042AЪЪЪ042A042AЪ042A = bии0438и0438и04380438ии();
    }
    return this.b042A042A042A042A042AЪ042AЪ042A;
  }
  
  /* Error */
  public tttxxt bии0438ии043804380438ии(long paramLong)
  {
    // Byte code:
    //   0: aload_0
    //   1: getfield 123	kkkkkk/tttxxt:b042A042AЪ042A042AЪ042AЪ042A	Ljava/text/SimpleDateFormat;
    //   4: lload_1
    //   5: invokestatic 212	java/lang/Long:valueOf	(J)Ljava/lang/Long;
    //   8: invokevirtual 216	java/text/SimpleDateFormat:format	(Ljava/lang/Object;)Ljava/lang/String;
    //   11: astore 6
    //   13: invokestatic 84	kkkkkk/tttxxt:bии0438и0438и04380438ии	()I
    //   16: istore_3
    //   17: getstatic 76	kkkkkk/tttxxt:bЪЪ042AЪЪ042A042AЪ042A	I
    //   20: istore 4
    //   22: getstatic 74	kkkkkk/tttxxt:bЪ042AЪЪЪ042A042AЪ042A	I
    //   25: invokestatic 200	kkkkkk/tttxxt:b0438и0438и0438и04380438ии	()I
    //   28: iadd
    //   29: getstatic 74	kkkkkk/tttxxt:bЪ042AЪЪЪ042A042AЪ042A	I
    //   32: imul
    //   33: getstatic 78	kkkkkk/tttxxt:b042AЪ042AЪЪ042A042AЪ042A	I
    //   36: irem
    //   37: getstatic 80	kkkkkk/tttxxt:b042A042AЪЪЪ042A042AЪ042A	I
    //   40: if_icmpeq +13 -> 53
    //   43: iconst_3
    //   44: putstatic 74	kkkkkk/tttxxt:bЪ042AЪЪЪ042A042AЪ042A	I
    //   47: invokestatic 84	kkkkkk/tttxxt:bии0438и0438и04380438ии	()I
    //   50: putstatic 80	kkkkkk/tttxxt:b042A042AЪЪЪ042A042AЪ042A	I
    //   53: getstatic 78	kkkkkk/tttxxt:b042AЪ042AЪЪ042A042AЪ042A	I
    //   56: istore 5
    //   58: iload_3
    //   59: iload 4
    //   61: iload_3
    //   62: iadd
    //   63: imul
    //   64: iload 5
    //   66: irem
    //   67: tableswitch	default:+17->84, 0:+28->95
    //   84: invokestatic 84	kkkkkk/tttxxt:bии0438и0438и04380438ии	()I
    //   87: putstatic 74	kkkkkk/tttxxt:bЪ042AЪЪЪ042A042AЪ042A	I
    //   90: bipush 54
    //   92: putstatic 80	kkkkkk/tttxxt:b042A042AЪЪЪ042A042AЪ042A	I
    //   95: aload_0
    //   96: aload 6
    //   98: putfield 150	kkkkkk/tttxxt:bЪЪЪЪЪ042A042AЪ042A	Ljava/lang/String;
    //   101: aload_0
    //   102: areturn
    //   103: astore 6
    //   105: aload 6
    //   107: athrow
    //   108: astore 6
    //   110: aload 6
    //   112: athrow
    // Local variable table:
    //   start	length	slot	name	signature
    //   0	113	0	this	tttxxt
    //   0	113	1	paramLong	long
    //   16	48	3	i	int
    //   20	43	4	j	int
    //   56	11	5	k	int
    //   11	86	6	str	String
    //   103	3	6	localException1	Exception
    //   108	3	6	localException2	Exception
    // Exception table:
    //   from	to	target	type
    //   0	22	103	java/lang/Exception
    //   53	58	103	java/lang/Exception
    //   95	101	103	java/lang/Exception
    //   84	95	108	java/lang/Exception
  }
  
  public String bиии04380438и04380438ии()
  {
    switch (1)
    {
    case 0: 
    default: 
      for (;;)
      {
        switch (1)
        {
        }
      }
    }
    String str = this.bЪ042AЪ042A042AЪ042AЪ042A;
    switch (0)
    {
    case 1: 
    default: 
      for (;;)
      {
        switch (1)
        {
        }
      }
    }
    int i = bЪ042AЪЪЪ042A042AЪ042A;
    int j = bЪЪ042AЪЪ042A042AЪ042A;
    if ((bЪ042AЪЪЪ042A042AЪ042A + bЪЪ042AЪЪ042A042AЪ042A) * bЪ042AЪЪЪ042A042AЪ042A % b042AЪ042AЪЪ042A042AЪ042A != b042A042AЪЪЪ042A042AЪ042A)
    {
      bЪ042AЪЪЪ042A042AЪ042A = 24;
      b042A042AЪЪЪ042A042AЪ042A = 2;
    }
    if ((i + j) * bЪ042AЪЪЪ042A042AЪ042A % b042AЪ042AЪЪ042A042AЪ042A != b042A042AЪЪЪ042A042AЪ042A)
    {
      bЪ042AЪЪЪ042A042AЪ042A = bии0438и0438и04380438ии();
      b042A042AЪЪЪ042A042AЪ042A = bии0438и0438и04380438ии();
    }
    return str;
  }
  
  public tttxxt bиииии043804380438ии(String paramString)
  {
    try
    {
      this.bЪЪ042A042A042AЪ042AЪ042A = paramString;
      int i = bЪ042AЪЪЪ042A042AЪ042A;
      switch (i * (bЪЪ042AЪЪ042A042AЪ042A + i) % b042AЪ042AЪЪ042A042AЪ042A)
      {
      default: 
        bЪ042AЪЪЪ042A042AЪ042A = 80;
        b042A042AЪЪЪ042A042AЪ042A = 80;
      }
      return this;
    }
    catch (Exception paramString)
    {
      throw paramString;
    }
  }
}
