package kkkkkk;

import android.app.Activity;
import android.content.Context;
import android.support.annotation.NonNull;
import android.support.v4.app.Fragment;
import com.liveperson.infra.ConversationViewParams;
import com.liveperson.infra.LPAuthenticationParams;

public class ttxttx
  implements xxtttx, xxddxd
{
  public static int b042A042A042A042AЪ042AЪ042A042A = 0;
  public static int b042AЪ042A042AЪ042AЪ042A042A = 1;
  public static int bЪ042A042A042AЪ042AЪ042A042A = 2;
  public static ttxttx bЪ042AЪ042AЪ042AЪ042A042A;
  public static int bЪЪ042A042AЪ042AЪ042A042A = 59;
  public xtxttx b042A042AЪ042AЪ042AЪ042A042A;
  
  public ttxttx() {}
  
  public static int b043804380438и0438иии0438и()
  {
    return 1;
  }
  
  public static int b0438и0438и0438иии0438и()
  {
    return 2;
  }
  
  public static int bи04380438и0438иии0438и()
  {
    return 34;
  }
  
  public static ttxttx bи0438и04380438иии0438и()
  {
    if (bЪ042AЪ042AЪ042AЪ042A042A == null) {}
    try
    {
      if (bЪ042AЪ042AЪ042AЪ042A042A != null) {
        break label41;
      }
      bЪ042AЪ042AЪ042AЪ042A042A = new ttxttx();
    }
    finally {}
    return bЪ042AЪ042AЪ042AЪ042A042A;
    label41:
    switch (0)
    {
    }
    for (;;)
    {
      switch (0)
      {
      }
    }
  }
  
  private void bии043804380438иии0438и()
  {
    if (this.b042A042AЪ042AЪ042AЪ042A042A == null)
    {
      switch (1)
      {
      case 0: 
      default: 
        for (;;)
        {
          switch (1)
          {
          }
        }
      }
      this.b042A042AЪ042AЪ042AЪ042A042A = new xtxttx();
    }
  }
  
  /* Error */
  public boolean b0438043804380438ииии0438и()
  {
    // Byte code:
    //   0: aload_0
    //   1: getfield 38	kkkkkk/ttxttx:b042A042AЪ042AЪ042AЪ042A042A	Lkkkkkk/xtxttx;
    //   4: ifnull +149 -> 153
    //   7: aload_0
    //   8: getfield 38	kkkkkk/ttxttx:b042A042AЪ042AЪ042AЪ042A042A	Lkkkkkk/xtxttx;
    //   11: astore_3
    //   12: getstatic 47	kkkkkk/ttxttx:bЪЪ042A042AЪ042AЪ042A042A	I
    //   15: istore_1
    //   16: iload_1
    //   17: getstatic 49	kkkkkk/ttxttx:b042AЪ042A042AЪ042AЪ042A042A	I
    //   20: iload_1
    //   21: iadd
    //   22: imul
    //   23: invokestatic 51	kkkkkk/ttxttx:b0438и0438и0438иии0438и	()I
    //   26: irem
    //   27: tableswitch	default:+17->44, 0:+28->55
    //   44: invokestatic 53	kkkkkk/ttxttx:bи04380438и0438иии0438и	()I
    //   47: putstatic 47	kkkkkk/ttxttx:bЪЪ042A042AЪ042AЪ042A042A	I
    //   50: bipush 69
    //   52: putstatic 55	kkkkkk/ttxttx:b042A042A042A042AЪ042AЪ042A042A	I
    //   55: aload_3
    //   56: invokevirtual 57	kkkkkk/xtxttx:b0438043804380438ииии0438и	()Z
    //   59: istore_2
    //   60: iload_2
    //   61: ifeq +92 -> 153
    //   64: iconst_1
    //   65: istore_2
    //   66: getstatic 47	kkkkkk/ttxttx:bЪЪ042A042AЪ042AЪ042A042A	I
    //   69: getstatic 49	kkkkkk/ttxttx:b042AЪ042A042AЪ042AЪ042A042A	I
    //   72: iadd
    //   73: getstatic 47	kkkkkk/ttxttx:bЪЪ042A042AЪ042AЪ042A042A	I
    //   76: imul
    //   77: getstatic 59	kkkkkk/ttxttx:bЪ042A042A042AЪ042AЪ042A042A	I
    //   80: irem
    //   81: getstatic 55	kkkkkk/ttxttx:b042A042A042A042AЪ042AЪ042A042A	I
    //   84: if_icmpeq +15 -> 99
    //   87: invokestatic 53	kkkkkk/ttxttx:bи04380438и0438иии0438и	()I
    //   90: putstatic 47	kkkkkk/ttxttx:bЪЪ042A042AЪ042AЪ042A042A	I
    //   93: invokestatic 53	kkkkkk/ttxttx:bи04380438и0438иии0438и	()I
    //   96: putstatic 55	kkkkkk/ttxttx:b042A042A042A042AЪ042AЪ042A042A	I
    //   99: iconst_1
    //   100: tableswitch	default:+24->124, 0:+-1->99, 1:+51->151
    //   124: iconst_0
    //   125: tableswitch	default:+23->148, 0:+26->151, 1:+-26->99
    //   148: goto -24 -> 124
    //   151: iload_2
    //   152: ireturn
    //   153: iconst_0
    //   154: istore_2
    //   155: goto -89 -> 66
    //   158: astore_3
    //   159: aload_3
    //   160: athrow
    // Local variable table:
    //   start	length	slot	name	signature
    //   0	161	0	this	ttxttx
    //   15	8	1	i	int
    //   59	96	2	bool	boolean
    //   11	45	3	localXtxttx	xtxttx
    //   158	2	3	localException	Exception
    // Exception table:
    //   from	to	target	type
    //   0	12	158	java/lang/Exception
    //   55	60	158	java/lang/Exception
  }
  
  public xtxttx b04380438и04380438иии0438и()
  {
    throw new Runtime("d2j fail translate: java.lang.IndexOutOfBoundsException: fromIndex < 0: -1\n\tat java.util.BitSet.nextSetBit(BitSet.java:712)\n\tat com.googlecode.dex2jar.ir.ts.array.FillArrayTransformer.makeSureAllElementAreAssigned(FillArrayTransformer.java:505)\n\tat com.googlecode.dex2jar.ir.ts.array.FillArrayTransformer.transformReportChanged(FillArrayTransformer.java:123)\n\tat com.googlecode.dex2jar.ir.ts.StatedTransformer.transform(StatedTransformer.java:10)\n\tat com.googlecode.d2j.dex.Dex2jar$2.optimize(Dex2jar.java:149)\n\tat com.googlecode.d2j.dex.Dex2Asm.convertCode(Dex2Asm.java:414)\n\tat com.googlecode.d2j.dex.ExDex2Asm.convertCode(ExDex2Asm.java:42)\n\tat com.googlecode.d2j.dex.Dex2jar$2.convertCode(Dex2jar.java:128)\n\tat com.googlecode.d2j.dex.Dex2Asm.convertMethod(Dex2Asm.java:509)\n\tat com.googlecode.d2j.dex.Dex2Asm.convertClass(Dex2Asm.java:406)\n\tat com.googlecode.d2j.dex.Dex2Asm.convertDex(Dex2Asm.java:422)\n\tat com.googlecode.d2j.dex.Dex2jar.doTranslate(Dex2jar.java:172)\n\tat com.googlecode.d2j.dex.Dex2jar.to(Dex2jar.java:272)\n\tat com.googlecode.dex2jar.tools.Dex2jarCmd.doCommandLine(Dex2jarCmd.java:108)\n\tat com.googlecode.dex2jar.tools.BaseCmd.doMain(BaseCmd.java:288)\n\tat com.googlecode.dex2jar.tools.Dex2jarCmd.main(Dex2jarCmd.java:32)\n");
  }
  
  public boolean b04380438ии0438иии0438и(Activity paramActivity, String paramString, LPAuthenticationParams paramLPAuthenticationParams, ConversationViewParams paramConversationViewParams)
  {
    try
    {
      xtxttx localXtxttx = this.b042A042AЪ042AЪ042AЪ042A042A;
      if ((bЪЪ042A042AЪ042AЪ042A042A + b042AЪ042A042AЪ042AЪ042A042A) * bЪЪ042A042AЪ042AЪ042A042A % bЪ042A042A042AЪ042AЪ042A042A != b042A042A042A042AЪ042AЪ042A042A)
      {
        switch (0)
        {
        case 1: 
        default: 
          for (;;)
          {
            switch (1)
            {
            }
          }
        }
        int i = bи04380438и0438иии0438и();
        switch (i * (b042AЪ042A042AЪ042AЪ042A042A + i) % bЪ042A042A042AЪ042AЪ042A042A)
        {
        default: 
          bЪЪ042A042AЪ042AЪ042A042A = bи04380438и0438иии0438и();
          b042A042A042A042AЪ042AЪ042A042A = 38;
        }
        bЪЪ042A042AЪ042AЪ042A042A = bи04380438и0438иии0438и();
        b042A042A042A042AЪ042AЪ042A042A = bи04380438и0438иии0438и();
      }
      boolean bool = localXtxttx.b04380438ии0438иии0438и(paramActivity, paramString, paramLPAuthenticationParams, paramConversationViewParams);
      return bool;
    }
    catch (Exception paramActivity)
    {
      throw paramActivity;
    }
  }
  
  public void b0438и043804380438иии0438и()
  {
    throw new Runtime("d2j fail translate: java.lang.IndexOutOfBoundsException: fromIndex < 0: -1\n\tat java.util.BitSet.nextSetBit(BitSet.java:712)\n\tat com.googlecode.dex2jar.ir.ts.array.FillArrayTransformer.makeSureAllElementAreAssigned(FillArrayTransformer.java:505)\n\tat com.googlecode.dex2jar.ir.ts.array.FillArrayTransformer.transformReportChanged(FillArrayTransformer.java:123)\n\tat com.googlecode.dex2jar.ir.ts.StatedTransformer.transform(StatedTransformer.java:10)\n\tat com.googlecode.d2j.dex.Dex2jar$2.optimize(Dex2jar.java:149)\n\tat com.googlecode.d2j.dex.Dex2Asm.convertCode(Dex2Asm.java:414)\n\tat com.googlecode.d2j.dex.ExDex2Asm.convertCode(ExDex2Asm.java:42)\n\tat com.googlecode.d2j.dex.Dex2jar$2.convertCode(Dex2jar.java:128)\n\tat com.googlecode.d2j.dex.Dex2Asm.convertMethod(Dex2Asm.java:509)\n\tat com.googlecode.d2j.dex.Dex2Asm.convertClass(Dex2Asm.java:406)\n\tat com.googlecode.d2j.dex.Dex2Asm.convertDex(Dex2Asm.java:422)\n\tat com.googlecode.d2j.dex.Dex2jar.doTranslate(Dex2jar.java:172)\n\tat com.googlecode.d2j.dex.Dex2jar.to(Dex2jar.java:272)\n\tat com.googlecode.dex2jar.tools.Dex2jarCmd.doCommandLine(Dex2jarCmd.java:108)\n\tat com.googlecode.dex2jar.tools.BaseCmd.doMain(BaseCmd.java:288)\n\tat com.googlecode.dex2jar.tools.Dex2jarCmd.main(Dex2jarCmd.java:32)\n");
  }
  
  /* Error */
  public void b0438и04380438ииии0438и(Activity paramActivity)
  {
    // Byte code:
    //   0: getstatic 47	kkkkkk/ttxttx:bЪЪ042A042AЪ042AЪ042A042A	I
    //   3: istore_2
    //   4: getstatic 49	kkkkkk/ttxttx:b042AЪ042A042AЪ042AЪ042A042A	I
    //   7: istore_3
    //   8: getstatic 47	kkkkkk/ttxttx:bЪЪ042A042AЪ042AЪ042A042A	I
    //   11: getstatic 49	kkkkkk/ttxttx:b042AЪ042A042AЪ042AЪ042A042A	I
    //   14: iadd
    //   15: getstatic 47	kkkkkk/ttxttx:bЪЪ042A042AЪ042AЪ042A042A	I
    //   18: imul
    //   19: getstatic 59	kkkkkk/ttxttx:bЪ042A042A042AЪ042AЪ042A042A	I
    //   22: irem
    //   23: getstatic 55	kkkkkk/ttxttx:b042A042A042A042AЪ042AЪ042A042A	I
    //   26: if_icmpeq +14 -> 40
    //   29: bipush 9
    //   31: putstatic 47	kkkkkk/ttxttx:bЪЪ042A042AЪ042AЪ042A042A	I
    //   34: invokestatic 53	kkkkkk/ttxttx:bи04380438и0438иии0438и	()I
    //   37: putstatic 55	kkkkkk/ttxttx:b042A042A042A042AЪ042AЪ042A042A	I
    //   40: iload_2
    //   41: iload_3
    //   42: iload_2
    //   43: iadd
    //   44: imul
    //   45: getstatic 59	kkkkkk/ttxttx:bЪ042A042A042AЪ042AЪ042A042A	I
    //   48: irem
    //   49: tableswitch	default:+19->68, 0:+30->79
    //   68: invokestatic 53	kkkkkk/ttxttx:bи04380438и0438иии0438и	()I
    //   71: putstatic 47	kkkkkk/ttxttx:bЪЪ042A042AЪ042AЪ042A042A	I
    //   74: bipush 14
    //   76: putstatic 55	kkkkkk/ttxttx:b042A042A042A042AЪ042AЪ042A042A	I
    //   79: aload_0
    //   80: getfield 38	kkkkkk/ttxttx:b042A042AЪ042AЪ042AЪ042A042A	Lkkkkkk/xtxttx;
    //   83: astore 4
    //   85: aload 4
    //   87: aload_1
    //   88: invokevirtual 79	kkkkkk/xtxttx:b0438и04380438ииии0438и	(Landroid/app/Activity;)V
    //   91: return
    //   92: astore_1
    //   93: aload_1
    //   94: athrow
    //   95: astore_1
    //   96: aload_1
    //   97: athrow
    // Local variable table:
    //   start	length	slot	name	signature
    //   0	98	0	this	ttxttx
    //   0	98	1	paramActivity	Activity
    //   3	42	2	i	int
    //   7	37	3	j	int
    //   83	3	4	localXtxttx	xtxttx
    // Exception table:
    //   from	to	target	type
    //   79	85	92	java/lang/Exception
    //   85	91	95	java/lang/Exception
  }
  
  /* Error */
  public xtxxtx b0438ии04380438иии0438и()
  {
    // Byte code:
    //   0: new 83	java/lang/NullPointerException
    //   3: dup
    //   4: invokespecial 84	java/lang/NullPointerException:<init>	()V
    //   7: athrow
    //   8: astore_1
    //   9: getstatic 47	kkkkkk/ttxttx:bЪЪ042A042AЪ042AЪ042A042A	I
    //   12: getstatic 49	kkkkkk/ttxttx:b042AЪ042A042AЪ042AЪ042A042A	I
    //   15: iadd
    //   16: getstatic 47	kkkkkk/ttxttx:bЪЪ042A042AЪ042AЪ042A042A	I
    //   19: imul
    //   20: getstatic 59	kkkkkk/ttxttx:bЪ042A042A042AЪ042AЪ042A042A	I
    //   23: irem
    //   24: getstatic 55	kkkkkk/ttxttx:b042A042A042A042AЪ042AЪ042A042A	I
    //   27: if_icmpeq +13 -> 40
    //   30: bipush 24
    //   32: putstatic 47	kkkkkk/ttxttx:bЪЪ042A042AЪ042AЪ042A042A	I
    //   35: bipush 66
    //   37: putstatic 55	kkkkkk/ttxttx:b042A042A042A042AЪ042AЪ042A042A	I
    //   40: invokestatic 53	kkkkkk/ttxttx:bи04380438и0438иии0438и	()I
    //   43: putstatic 47	kkkkkk/ttxttx:bЪЪ042A042AЪ042AЪ042A042A	I
    //   46: new 86	kkkkkk/xtxxtx
    //   49: dup
    //   50: invokespecial 87	kkkkkk/xtxxtx:<init>	()V
    //   53: astore_1
    //   54: aload_1
    //   55: areturn
    //   56: astore_1
    //   57: aload_1
    //   58: athrow
    //   59: astore_1
    //   60: aload_1
    //   61: athrow
    //   62: astore_1
    //   63: aload_1
    //   64: athrow
    // Local variable table:
    //   start	length	slot	name	signature
    //   0	65	0	this	ttxttx
    //   8	1	1	localException1	Exception
    //   53	2	1	localXtxxtx	xtxxtx
    //   56	2	1	localException2	Exception
    //   59	2	1	localException3	Exception
    //   62	2	1	localException4	Exception
    // Exception table:
    //   from	to	target	type
    //   0	8	8	java/lang/Exception
    //   46	54	56	java/lang/Exception
    //   57	59	59	java/lang/Exception
    //   40	46	62	java/lang/Exception
  }
  
  public void b0438иии0438иии0438и(String paramString)
  {
    xtxttx localXtxttx = this.b042A042AЪ042AЪ042AЪ042A042A;
    if ((bи04380438и0438иии0438и() + b042AЪ042A042AЪ042AЪ042A042A) * bи04380438и0438иии0438и() % bЪ042A042A042AЪ042AЪ042A042A != b042A042A042A042AЪ042AЪ042A042A)
    {
      bЪЪ042A042AЪ042AЪ042A042A = bи04380438и0438иии0438и();
      b042A042A042A042AЪ042AЪ042A042A = 19;
    }
    localXtxttx.b0438иии0438иии0438и(paramString);
  }
  
  public void b0445044504450445044504450445х04450445()
  {
    int i = bЪЪ042A042AЪ042AЪ042A042A;
    switch (i * (b043804380438и0438иии0438и() + i) % b0438и0438и0438иии0438и())
    {
    default: 
      bЪЪ042A042AЪ042AЪ042A042A = 35;
      b042A042A042A042AЪ042AЪ042A042A = bи04380438и0438иии0438и();
    }
    switch (0)
    {
    case 1: 
    default: 
      for (;;)
      {
        switch (1)
        {
        }
      }
    }
    if ((bЪЪ042A042AЪ042AЪ042A042A + b042AЪ042A042AЪ042AЪ042A042A) * bЪЪ042A042AЪ042AЪ042A042A % bЪ042A042A042AЪ042AЪ042A042A != b042A042A042A042AЪ042AЪ042A042A)
    {
      bЪЪ042A042AЪ042AЪ042A042A = 79;
      b042A042A042A042AЪ042AЪ042A042A = bи04380438и0438иии0438и();
    }
    this.b042A042AЪ042AЪ042AЪ042A042A.b0445044504450445044504450445х04450445();
  }
  
  public void bи043804380438ииии0438и(Context paramContext, xxtxtx paramXxtxtx, txtxtx paramTxtxtx)
  {
    try
    {
      bии043804380438иии0438и();
      this.b042A042AЪ042AЪ042AЪ042A042A.bи043804380438ииии0438и(paramContext, paramXxtxtx, paramTxtxtx);
      return;
    }
    finally {}
    throw paramContext;
    for (;;)
    {
      switch (0)
      {
      }
    }
  }
  
  public void bи0438ии0438иии0438и(txtxtx paramTxtxtx)
  {
    xtxttx localXtxttx = this.b042A042AЪ042AЪ042AЪ042A042A;
    if ((bЪЪ042A042AЪ042AЪ042A042A + b042AЪ042A042AЪ042AЪ042A042A) * bЪЪ042A042AЪ042AЪ042A042A % bЪ042A042A042AЪ042AЪ042A042A != b042A042A042A042AЪ042AЪ042A042A)
    {
      bЪЪ042A042AЪ042AЪ042A042A = bи04380438и0438иии0438и();
      b042A042A042A042AЪ042AЪ042A042A = bи04380438и0438иии0438и();
    }
    int i = bЪЪ042A042AЪ042AЪ042A042A;
    switch (i * (b042AЪ042A042AЪ042AЪ042A042A + i) % bЪ042A042A042AЪ042AЪ042A042A)
    {
    default: 
      bЪЪ042A042AЪ042AЪ042A042A = 63;
      b042A042A042A042AЪ042AЪ042A042A = 3;
    }
    localXtxttx.bи0438ии0438иии0438и(paramTxtxtx);
  }
  
  public Fragment bии04380438ииии0438и(String paramString, LPAuthenticationParams paramLPAuthenticationParams, ConversationViewParams paramConversationViewParams)
  {
    xtxttx localXtxttx = this.b042A042AЪ042AЪ042AЪ042A042A;
    int i = bЪЪ042A042AЪ042AЪ042A042A;
    int j = b043804380438и0438иии0438и();
    int k = bЪЪ042A042AЪ042AЪ042A042A;
    switch (k * (b042AЪ042A042AЪ042AЪ042A042A + k) % bЪ042A042A042AЪ042AЪ042A042A)
    {
    default: 
      bЪЪ042A042AЪ042AЪ042A042A = 67;
      b042A042A042A042AЪ042AЪ042A042A = bи04380438и0438иии0438и();
    }
    switch (i * (j + i) % bЪ042A042A042AЪ042AЪ042A042A)
    {
    default: 
      bЪЪ042A042AЪ042AЪ042A042A = bи04380438и0438иии0438и();
      b042A042A042A042AЪ042AЪ042A042A = 27;
    }
    switch (0)
    {
    case 1: 
    default: 
      for (;;)
      {
        switch (0)
        {
        case 1: 
        default: 
          for (;;)
          {
            switch (1)
            {
            }
          }
        }
        switch (0)
        {
        }
      }
    }
    return localXtxttx.bии04380438ииии0438и(paramString, paramLPAuthenticationParams, paramConversationViewParams);
  }
  
  /* Error */
  public void bии0438и0438иии0438и(voovov paramVoovov)
  {
    // Byte code:
    //   0: aload_0
    //   1: getfield 38	kkkkkk/ttxttx:b042A042AЪ042AЪ042AЪ042A042A	Lkkkkkk/xtxttx;
    //   4: astore_2
    //   5: aload_2
    //   6: aload_1
    //   7: invokevirtual 113	kkkkkk/xtxttx:bии0438и0438иии0438и	(Lkkkkkk/voovov;)V
    //   10: return
    //   11: astore_1
    //   12: aload_1
    //   13: athrow
    //   14: astore_1
    //   15: aload_1
    //   16: athrow
    // Local variable table:
    //   start	length	slot	name	signature
    //   0	17	0	this	ttxttx
    //   0	17	1	paramVoovov	voovov
    //   4	2	2	localXtxttx	xtxttx
    // Exception table:
    //   from	to	target	type
    //   0	5	11	java/lang/Exception
    //   5	10	14	java/lang/Exception
  }
  
  @NonNull
  public xtxttx bиии04380438иии0438и()
  {
    xtxttx localXtxttx = new xtxttx();
    if ((bЪЪ042A042AЪ042AЪ042A042A + b042AЪ042A042AЪ042AЪ042A042A) * bЪЪ042A042AЪ042AЪ042A042A % bЪ042A042A042AЪ042AЪ042A042A != b042A042A042A042AЪ042AЪ042A042A)
    {
      bЪЪ042A042AЪ042AЪ042A042A = bи04380438и0438иии0438и();
      b042A042A042A042AЪ042AЪ042A042A = 74;
      if ((bЪЪ042A042AЪ042AЪ042A042A + b042AЪ042A042AЪ042AЪ042A042A) * bЪЪ042A042AЪ042AЪ042A042A % bЪ042A042A042AЪ042AЪ042A042A != b042A042A042A042AЪ042AЪ042A042A)
      {
        bЪЪ042A042AЪ042AЪ042A042A = 72;
        b042A042A042A042AЪ042AЪ042A042A = 98;
      }
    }
    switch (0)
    {
    case 1: 
    default: 
      for (;;)
      {
        switch (1)
        {
        }
      }
    }
    return localXtxttx;
  }
  
  public void bииии0438иии0438и(Context paramContext, xxtxtx paramXxtxtx, dxxxdx paramDxxxdx)
  {
    switch (0)
    {
    case 1: 
    default: 
      for (;;)
      {
        switch (0)
        {
        }
      }
    }
    int i = bЪЪ042A042AЪ042AЪ042A042A;
    switch (i * (b042AЪ042A042AЪ042AЪ042A042A + i) % bЪ042A042A042AЪ042AЪ042A042A)
    {
    default: 
      bЪЪ042A042AЪ042AЪ042A042A = bи04380438и0438иии0438и();
      b042A042A042A042AЪ042AЪ042A042A = 77;
    }
    bии043804380438иии0438и();
    xtxttx localXtxttx = this.b042A042AЪ042AЪ042AЪ042A042A;
    switch (1)
    {
    case 0: 
    default: 
      for (;;)
      {
        if ((bЪЪ042A042AЪ042AЪ042A042A + b042AЪ042A042AЪ042AЪ042A042A) * bЪЪ042A042AЪ042AЪ042A042A % bЪ042A042A042AЪ042AЪ042A042A != b042A042A042A042AЪ042AЪ042A042A)
        {
          bЪЪ042A042AЪ042AЪ042A042A = bи04380438и0438иии0438и();
          b042A042A042A042AЪ042AЪ042A042A = 66;
        }
        switch (1)
        {
        }
      }
    }
    localXtxttx.bииии0438иии0438и(paramContext, paramXxtxtx, paramDxxxdx);
  }
}
