package kkkkkk;

import android.support.annotation.NonNull;
import android.support.annotation.Nullable;
import com.mobile.business.arrangement.dto.CurrencyCode;
import java.io.Serializable;
import java.util.List;
import org.threeten.bp.ZonedDateTime;

public class ttyytt
  implements Serializable
{
  private static final long serialVersionUID = 7635625048035231232L;
  private boolean b042904290429042904290429ЩЩ04290429;
  @Nullable
  private aababa b0429042904290429ЩЩ0429Щ04290429;
  @Nullable
  private aabaaa b042904290429Щ04290429ЩЩ04290429;
  @Nullable
  private String b042904290429ЩЩЩ0429Щ04290429;
  @Nullable
  private String b04290429Щ042904290429ЩЩ04290429;
  @NonNull
  private String b04290429Щ0429ЩЩ0429Щ04290429;
  @NonNull
  private final String b04290429ЩЩЩЩ0429Щ04290429;
  @NonNull
  private final String b0429Щ0429042904290429ЩЩ04290429;
  @Nullable
  private final String b0429Щ04290429ЩЩ0429Щ04290429;
  @Nullable
  private String b0429Щ0429ЩЩЩ0429Щ04290429;
  @Nullable
  private String b0429ЩЩ042904290429ЩЩ04290429;
  private boolean b0429ЩЩ0429ЩЩ0429Щ04290429;
  private boolean b0429ЩЩЩЩЩ0429Щ04290429;
  private boolean bЩ04290429042904290429ЩЩ04290429;
  private yyyhyh bЩ042904290429ЩЩ0429Щ04290429 = yyyhyh.UNHANDLED;
  @NonNull
  private String bЩ04290429Щ04290429ЩЩ04290429;
  @Nullable
  private List<String> bЩ04290429ЩЩЩ0429Щ04290429;
  @Nullable
  private String bЩ0429Щ042904290429ЩЩ04290429;
  @NonNull
  private String bЩ0429Щ0429ЩЩ0429Щ04290429;
  @Nullable
  private ZonedDateTime bЩ0429ЩЩЩЩ0429Щ04290429;
  @NonNull
  private ZonedDateTime bЩЩ0429042904290429ЩЩ04290429;
  @NonNull
  private String bЩЩ04290429ЩЩ0429Щ04290429;
  @NonNull
  private ZonedDateTime bЩЩ0429ЩЩЩ0429Щ04290429;
  @Nullable
  private baabaa bЩЩЩ042904290429ЩЩ04290429;
  @NonNull
  private final abbaba bЩЩЩ0429ЩЩ0429Щ04290429;
  private boolean bЩЩЩЩЩЩ0429Щ04290429;
  
  private ttyytt(@NonNull String paramString1, @Nullable String paramString2, @NonNull ZonedDateTime paramZonedDateTime, @NonNull abbaba paramAbbaba, @NonNull String paramString3)
  {
    this.b0429Щ0429042904290429ЩЩ04290429 = paramString1;
    this.b0429Щ04290429ЩЩ0429Щ04290429 = paramString2;
    this.bЩЩ0429ЩЩЩ0429Щ04290429 = paramZonedDateTime;
    this.bЩЩЩ0429ЩЩ0429Щ04290429 = paramAbbaba;
    this.b04290429ЩЩЩЩ0429Щ04290429 = paramString3;
  }
  
  public static int b043B043B043Bллллл043Bл()
  {
    return 1;
  }
  
  public static int b043Bл043Bллллл043Bл()
  {
    return 2;
  }
  
  public static int bл043B043Bллллл043Bл()
  {
    return 0;
  }
  
  public static int bллл043Bлллл043Bл()
  {
    return 76;
  }
  
  @NonNull
  public yyyhyh b043B043B043B043B043Bллл043Bл()
  {
    if ((bллл043Bлллл043Bл() + b043B043B043Bллллл043Bл()) * bллл043Bлллл043Bл() % b043Bл043Bллллл043Bл() != bл043B043Bллллл043Bл()) {}
    try
    {
      int i = bллл043Bлллл043Bл();
      switch (i * (b043B043B043Bллллл043Bл() + i) % b043Bл043Bллллл043Bл())
      {
      case 0: 
        yyyhyh localYyyhyh = this.bЩ042904290429ЩЩ0429Щ04290429;
        return localYyyhyh;
      }
    }
    catch (Exception localException)
    {
      throw localException;
    }
    switch (0)
    {
    }
    for (;;)
    {
      switch (0)
      {
      }
    }
  }
  
  @NonNull
  public ZonedDateTime b043B043B043B043Bлллл043Bл()
  {
    int i = bллл043Bлллл043Bл();
    switch (i * (b043B043B043Bллллл043Bл() + i) % b043Bл043Bллллл043Bл())
    {
    default: 
      if ((bллл043Bлллл043Bл() + b043B043B043Bллллл043Bл()) * bллл043Bлллл043Bл() % b043Bл043Bллллл043Bл() == bл043B043Bллллл043Bл()) {
        break;
      }
    }
    try
    {
      ZonedDateTime localZonedDateTime = this.bЩЩ0429042904290429ЩЩ04290429;
      return localZonedDateTime;
    }
    catch (Exception localException)
    {
      throw localException;
    }
  }
  
  @Nullable
  public List<String> b043B043B043Bл043Bллл043Bл()
  {
    switch (0)
    {
    case 1: 
    default: 
      for (;;)
      {
        switch (1)
        {
        }
      }
    }
    int i = bллл043Bлллл043Bл();
    int j = b043B043B043Bллллл043Bл();
    int k = bллл043Bлллл043Bл();
    int m = b043Bл043Bллллл043Bл();
    if (((bллл043Bлллл043Bл() + b043B043B043Bллллл043Bл()) * bллл043Bлллл043Bл() % b043Bл043Bллллл043Bл() == bл043B043Bллллл043Bл()) || ((i + j) * k % m != bл043B043Bллллл043Bл())) {}
    return this.bЩ04290429ЩЩЩ0429Щ04290429;
  }
  
  @NonNull
  public String b043B043Bл043B043Bллл043Bл()
  {
    int i = bллл043Bлллл043Bл();
    int j = b043B043B043Bллллл043Bл();
    if (((bллл043Bлллл043Bл() + b043B043B043Bллллл043Bл()) * bллл043Bлллл043Bл() % b043Bл043Bллллл043Bл() == bл043B043Bллллл043Bл()) || ((i + j) * bллл043Bлллл043Bл() % b043Bл043Bллллл043Bл() != bл043B043Bллллл043Bл())) {}
    String str = this.bЩ0429Щ0429ЩЩ0429Щ04290429;
    switch (1)
    {
    case 0: 
    default: 
      for (;;)
      {
        switch (0)
        {
        }
      }
    }
    return str;
  }
  
  @Nullable
  public baabaa b043B043Bл043Bлллл043Bл()
  {
    if ((bллл043Bлллл043Bл() + b043B043B043Bллллл043Bл()) * bллл043Bлллл043Bл() % b043Bл043Bллллл043Bл() != bл043B043Bллллл043Bл()) {}
    return this.bЩЩЩ042904290429ЩЩ04290429;
  }
  
  @Nullable
  public String b043B043Bлл043Bллл043Bл()
  {
    String str = this.b04290429ЩЩЩЩ0429Щ04290429;
    switch (0)
    {
    case 1: 
    default: 
      for (;;)
      {
        switch (1)
        {
        }
      }
    }
    return mnmnmn.b0418ИИИ04180418ИИ04180418(mnmnmn.b04180418И041804180418ИИ04180418(str, CurrencyCode.getDefaultCurrencyCode()));
  }
  
  @NonNull
  public String b043Bл043B043B043Bллл043Bл()
  {
    switch (1)
    {
    case 0: 
    default: 
      for (;;)
      {
        switch (1)
        {
        }
      }
    }
    try
    {
      String str = this.bЩЩ04290429ЩЩ0429Щ04290429;
      int i = bллл043Bлллл043Bл();
      switch (i * (b043B043B043Bллллл043Bл() + i) % b043Bл043Bллллл043Bл())
      {
      default: 
        i = bллл043Bлллл043Bл();
        switch (i * (b043B043B043Bллллл043Bл() + i) % b043Bл043Bллллл043Bл())
        {
        }
        break;
      }
      return str;
    }
    catch (Exception localException)
    {
      throw localException;
    }
  }
  
  @Nullable
  public String b043Bл043B043Bлллл043Bл()
  {
    switch (1)
    {
    case 0: 
    default: 
      for (;;)
      {
        switch (0)
        {
        }
      }
    }
    switch (0)
    {
    case 1: 
    default: 
      for (;;)
      {
        switch (1)
        {
        }
      }
    }
    String str = this.bЩ0429Щ042904290429ЩЩ04290429;
    int i = bллл043Bлллл043Bл();
    int j = b043B043B043Bллллл043Bл();
    int k = bллл043Bлллл043Bл();
    switch (k * (b043B043B043Bллллл043Bл() + k) % b043Bл043Bллллл043Bл())
    {
    }
    if ((i + j) * bллл043Bлллл043Bл() % b043Bл043Bллллл043Bл() != bл043B043Bллллл043Bл()) {}
    return str;
  }
  
  @Nullable
  public ZonedDateTime b043Bл043Bл043Bллл043Bл()
  {
    if ((bллл043Bлллл043Bл() + b043B043B043Bллллл043Bл()) * bллл043Bлллл043Bл() % b043Bл043Bллллл043Bл() != bл043B043Bллллл043Bл()) {}
    try
    {
      ZonedDateTime localZonedDateTime = this.bЩЩ0429ЩЩЩ0429Щ04290429;
      int i = bллл043Bлллл043Bл();
      switch (i * (b043B043B043Bллллл043Bл() + i) % b043Bл043Bллллл043Bл())
      {
      }
      return localZonedDateTime;
    }
    catch (Exception localException)
    {
      throw localException;
    }
  }
  
  public boolean b043Bлл043B043Bллл043Bл()
  {
    boolean bool = this.b0429ЩЩ0429ЩЩ0429Щ04290429;
    switch (0)
    {
    case 1: 
    default: 
      for (;;)
      {
        switch (0)
        {
        case 1: 
        default: 
          for (;;)
          {
            switch (1)
            {
            }
          }
        }
        switch (0)
        {
        }
      }
    }
    int i = bллл043Bлллл043Bл();
    int j = bллл043Bлллл043Bл();
    switch (j * (b043B043B043Bллллл043Bл() + j) % b043Bл043Bллллл043Bл())
    {
    }
    switch (i * (b043B043B043Bллллл043Bл() + i) % b043Bл043Bллллл043Bл())
    {
    }
    return bool;
  }
  
  /* Error */
  @NonNull
  public String b043Bлл043Bлллл043Bл()
  {
    // Byte code:
    //   0: invokestatic 85	kkkkkk/ttyytt:bллл043Bлллл043Bл	()I
    //   3: istore_1
    //   4: invokestatic 88	kkkkkk/ttyytt:b043B043B043Bллллл043Bл	()I
    //   7: istore_2
    //   8: iload_1
    //   9: iload_2
    //   10: iload_1
    //   11: iadd
    //   12: imul
    //   13: invokestatic 91	kkkkkk/ttyytt:b043Bл043Bллллл043Bл	()I
    //   16: irem
    //   17: tableswitch	default:+114->131, 0:+19->36
    //   36: aload_0
    //   37: getfield 164	kkkkkk/ttyytt:bЩ04290429Щ04290429ЩЩ04290429	Ljava/lang/String;
    //   40: astore_3
    //   41: iconst_0
    //   42: tableswitch	default:+22->64, 0:+81->123, 1:+-1->41
    //   64: invokestatic 85	kkkkkk/ttyytt:bллл043Bлллл043Bл	()I
    //   67: istore_1
    //   68: iload_1
    //   69: invokestatic 88	kkkkkk/ttyytt:b043B043B043Bллллл043Bл	()I
    //   72: iload_1
    //   73: iadd
    //   74: imul
    //   75: invokestatic 91	kkkkkk/ttyytt:b043Bл043Bллллл043Bл	()I
    //   78: irem
    //   79: tableswitch	default:+17->96, 0:+17->96
    //   96: iconst_0
    //   97: tableswitch	default:+23->120, 0:+26->123, 1:+-56->41
    //   120: goto -56 -> 64
    //   123: aload_3
    //   124: areturn
    //   125: astore_3
    //   126: aload_3
    //   127: athrow
    //   128: astore_3
    //   129: aload_3
    //   130: athrow
    //   131: goto -95 -> 36
    // Local variable table:
    //   start	length	slot	name	signature
    //   0	134	0	this	ttyytt
    //   3	72	1	i	int
    //   7	5	2	j	int
    //   40	84	3	str	String
    //   125	2	3	localException1	Exception
    //   128	2	3	localException2	Exception
    // Exception table:
    //   from	to	target	type
    //   0	8	125	java/lang/Exception
    //   8	36	128	java/lang/Exception
    //   36	41	128	java/lang/Exception
  }
  
  public boolean b043Bллл043Bллл043Bл()
  {
    if ((bллл043Bлллл043Bл() + b043B043B043Bллллл043Bл()) * bллл043Bлллл043Bл() % b043Bл043Bллллл043Bл() != bл043B043Bллллл043Bл()) {}
    try
    {
      boolean bool = this.bЩ04290429042904290429ЩЩ04290429;
      int i = bллл043Bлллл043Bл();
      switch (i * (b043B043B043Bллллл043Bл() + i) % b043Bл043Bллллл043Bл())
      {
      }
      return bool;
    }
    catch (Exception localException)
    {
      throw localException;
    }
  }
  
  /* Error */
  @Nullable
  public boolean b043Bлллл043Bлл043Bл()
  {
    // Byte code:
    //   0: aload_0
    //   1: getfield 148	kkkkkk/ttyytt:b042904290429042904290429ЩЩ04290429	Z
    //   4: istore 6
    //   6: invokestatic 85	kkkkkk/ttyytt:bллл043Bлллл043Bл	()I
    //   9: istore_1
    //   10: invokestatic 88	kkkkkk/ttyytt:b043B043B043Bллллл043Bл	()I
    //   13: istore_2
    //   14: invokestatic 85	kkkkkk/ttyytt:bллл043Bлллл043Bл	()I
    //   17: istore_3
    //   18: invokestatic 91	kkkkkk/ttyytt:b043Bл043Bллллл043Bл	()I
    //   21: istore 4
    //   23: invokestatic 97	kkkkkk/ttyytt:bл043B043Bллллл043Bл	()I
    //   26: istore 5
    //   28: iload_1
    //   29: iload_2
    //   30: iadd
    //   31: iload_3
    //   32: imul
    //   33: iload 4
    //   35: irem
    //   36: iload 5
    //   38: if_icmpeq +24 -> 62
    //   41: invokestatic 85	kkkkkk/ttyytt:bллл043Bлллл043Bл	()I
    //   44: invokestatic 88	kkkkkk/ttyytt:b043B043B043Bллллл043Bл	()I
    //   47: iadd
    //   48: invokestatic 85	kkkkkk/ttyytt:bллл043Bлллл043Bл	()I
    //   51: imul
    //   52: invokestatic 91	kkkkkk/ttyytt:b043Bл043Bллллл043Bл	()I
    //   55: irem
    //   56: invokestatic 97	kkkkkk/ttyytt:bл043B043Bллллл043Bл	()I
    //   59: if_icmpeq +3 -> 62
    //   62: iload 6
    //   64: ireturn
    //   65: astore 7
    //   67: aload 7
    //   69: athrow
    //   70: astore 7
    //   72: aload 7
    //   74: athrow
    // Local variable table:
    //   start	length	slot	name	signature
    //   0	75	0	this	ttyytt
    //   9	22	1	i	int
    //   13	18	2	j	int
    //   17	16	3	k	int
    //   21	15	4	m	int
    //   26	13	5	n	int
    //   4	59	6	bool	boolean
    //   65	3	7	localException1	Exception
    //   70	3	7	localException2	Exception
    // Exception table:
    //   from	to	target	type
    //   0	14	65	java/lang/Exception
    //   14	28	70	java/lang/Exception
  }
  
  @Nullable
  public String bл043B043B043B043Bллл043Bл()
  {
    if (((bллл043Bлллл043Bл() + b043B043B043Bллллл043Bл()) * bллл043Bлллл043Bл() % b043Bл043Bллллл043Bл() != bл043B043Bллллл043Bл()) && ((bллл043Bлллл043Bл() + b043B043B043Bллллл043Bл()) * bллл043Bлллл043Bл() % b043Bл043Bллллл043Bл() != bл043B043Bллллл043Bл())) {}
    String str = this.b0429Щ04290429ЩЩ0429Щ04290429;
    switch (0)
    {
    case 1: 
    default: 
      for (;;)
      {
        switch (1)
        {
        }
      }
    }
    return str;
  }
  
  @Nullable
  public String bл043B043B043Bлллл043Bл()
  {
    try
    {
      String str = this.b04290429Щ042904290429ЩЩ04290429;
      int i = bллл043Bлллл043Bл();
      int j = b043B043B043Bллллл043Bл();
      int k = bллл043Bлллл043Bл();
      int m = b043Bл043Bллллл043Bл();
      int n = bл043B043Bллллл043Bл();
      if ((i + j) * k % m != n) {}
      return str;
    }
    catch (Exception localException)
    {
      throw localException;
    }
  }
  
  /* Error */
  @Nullable
  public String bл043B043Bл043Bллл043Bл()
  {
    // Byte code:
    //   0: invokestatic 85	kkkkkk/ttyytt:bллл043Bлллл043Bл	()I
    //   3: istore_1
    //   4: invokestatic 88	kkkkkk/ttyytt:b043B043B043Bллллл043Bл	()I
    //   7: istore_2
    //   8: invokestatic 91	kkkkkk/ttyytt:b043Bл043Bллллл043Bл	()I
    //   11: istore_3
    //   12: iload_1
    //   13: iload_2
    //   14: iload_1
    //   15: iadd
    //   16: imul
    //   17: iload_3
    //   18: irem
    //   19: tableswitch	default:+17->36, 0:+17->36
    //   36: aload_0
    //   37: getfield 106	kkkkkk/ttyytt:b0429Щ0429ЩЩЩ0429Щ04290429	Ljava/lang/String;
    //   40: astore 4
    //   42: invokestatic 85	kkkkkk/ttyytt:bллл043Bлллл043Bл	()I
    //   45: invokestatic 88	kkkkkk/ttyytt:b043B043B043Bллллл043Bл	()I
    //   48: iadd
    //   49: invokestatic 85	kkkkkk/ttyytt:bллл043Bлллл043Bл	()I
    //   52: imul
    //   53: invokestatic 91	kkkkkk/ttyytt:b043Bл043Bллллл043Bл	()I
    //   56: irem
    //   57: invokestatic 97	kkkkkk/ttyytt:bл043B043Bллллл043Bл	()I
    //   60: if_icmpeq +3 -> 63
    //   63: aload 4
    //   65: areturn
    //   66: astore 4
    //   68: aload 4
    //   70: athrow
    //   71: astore 4
    //   73: aload 4
    //   75: athrow
    //   76: astore 4
    //   78: aload 4
    //   80: athrow
    // Local variable table:
    //   start	length	slot	name	signature
    //   0	81	0	this	ttyytt
    //   3	14	1	i	int
    //   7	9	2	j	int
    //   11	8	3	k	int
    //   40	24	4	str	String
    //   66	3	4	localException1	Exception
    //   71	3	4	localException2	Exception
    //   76	3	4	localException3	Exception
    // Exception table:
    //   from	to	target	type
    //   36	42	66	java/lang/Exception
    //   68	71	71	java/lang/Exception
    //   0	12	76	java/lang/Exception
  }
  
  @NonNull
  public abbaba bл043Bл043B043Bллл043Bл()
  {
    if (((bллл043Bлллл043Bл() + b043B043B043Bллллл043Bл()) * bллл043Bлллл043Bл() % b043Bл043Bллллл043Bл() == bл043B043Bллллл043Bл()) || ((bллл043Bлллл043Bл() + b043B043B043Bллллл043Bл()) * bллл043Bлллл043Bл() % b043Bл043Bллллл043Bл() != bл043B043Bллллл043Bл())) {
      switch (1)
      {
      case 0: 
      default: 
        for (;;)
        {
          switch (0)
          {
          }
        }
      }
    }
    try
    {
      abbaba localAbbaba = this.bЩЩЩ0429ЩЩ0429Щ04290429;
      return localAbbaba;
    }
    catch (Exception localException)
    {
      throw localException;
    }
  }
  
  @Nullable
  public aabaaa bл043Bл043Bлллл043Bл()
  {
    if ((bллл043Bлллл043Bл() + b043B043B043Bллллл043Bл()) * bллл043Bлллл043Bл() % b043Bл043Bллллл043Bл() != bл043B043Bллллл043Bл()) {}
    switch (0)
    {
    case 1: 
    default: 
      for (;;)
      {
        switch (0)
        {
        }
      }
    }
    aabaaa localAabaaa = this.b042904290429Щ04290429ЩЩ04290429;
    if ((bллл043Bлллл043Bл() + b043B043B043Bллллл043Bл()) * bллл043Bлллл043Bл() % b043Bл043Bллллл043Bл() != bл043B043Bллллл043Bл()) {}
    return localAabaaa;
  }
  
  /* Error */
  @Nullable
  public ZonedDateTime bл043Bлл043Bллл043Bл()
  {
    // Byte code:
    //   0: aload_0
    //   1: getfield 103	kkkkkk/ttyytt:bЩ0429ЩЩЩЩ0429Щ04290429	Lorg/threeten/bp/ZonedDateTime;
    //   4: astore 6
    //   6: invokestatic 85	kkkkkk/ttyytt:bллл043Bлллл043Bл	()I
    //   9: istore_1
    //   10: invokestatic 88	kkkkkk/ttyytt:b043B043B043Bллллл043Bл	()I
    //   13: istore_2
    //   14: invokestatic 85	kkkkkk/ttyytt:bллл043Bлллл043Bл	()I
    //   17: istore_3
    //   18: invokestatic 91	kkkkkk/ttyytt:b043Bл043Bллллл043Bл	()I
    //   21: istore 4
    //   23: invokestatic 97	kkkkkk/ttyytt:bл043B043Bллллл043Bл	()I
    //   26: istore 5
    //   28: iload_1
    //   29: iload_2
    //   30: iadd
    //   31: iload_3
    //   32: imul
    //   33: iload 4
    //   35: irem
    //   36: iload 5
    //   38: if_icmpeq +24 -> 62
    //   41: invokestatic 85	kkkkkk/ttyytt:bллл043Bлллл043Bл	()I
    //   44: invokestatic 88	kkkkkk/ttyytt:b043B043B043Bллллл043Bл	()I
    //   47: iadd
    //   48: invokestatic 85	kkkkkk/ttyytt:bллл043Bлллл043Bл	()I
    //   51: imul
    //   52: invokestatic 91	kkkkkk/ttyytt:b043Bл043Bллллл043Bл	()I
    //   55: irem
    //   56: invokestatic 97	kkkkkk/ttyytt:bл043B043Bллллл043Bл	()I
    //   59: if_icmpeq +3 -> 62
    //   62: aload 6
    //   64: areturn
    //   65: astore 6
    //   67: aload 6
    //   69: athrow
    //   70: astore 6
    //   72: aload 6
    //   74: athrow
    // Local variable table:
    //   start	length	slot	name	signature
    //   0	75	0	this	ttyytt
    //   9	22	1	i	int
    //   13	18	2	j	int
    //   17	16	3	k	int
    //   21	15	4	m	int
    //   26	13	5	n	int
    //   4	59	6	localZonedDateTime	ZonedDateTime
    //   65	3	6	localException1	Exception
    //   70	3	6	localException2	Exception
    // Exception table:
    //   from	to	target	type
    //   0	6	65	java/lang/Exception
    //   6	28	70	java/lang/Exception
    //   67	70	70	java/lang/Exception
  }
  
  public boolean bл043Bллл043Bлл043Bл()
  {
    int i = bллл043Bлллл043Bл();
    int j = b043B043B043Bллллл043Bл();
    switch (0)
    {
    case 1: 
    default: 
      for (;;)
      {
        switch (1)
        {
        }
      }
    }
    switch (i * (j + i) % b043Bл043Bллллл043Bл())
    {
    }
    try
    {
      boolean bool = this.bЩЩЩЩЩЩ0429Щ04290429;
      return bool;
    }
    catch (Exception localException)
    {
      throw localException;
    }
  }
  
  @NonNull
  public String bлл043B043B043Bллл043Bл()
  {
    throw new Runtime("d2j fail translate: java.lang.IndexOutOfBoundsException: fromIndex < 0: -1\n\tat java.util.BitSet.nextSetBit(BitSet.java:712)\n\tat com.googlecode.dex2jar.ir.ts.array.FillArrayTransformer.makeSureAllElementAreAssigned(FillArrayTransformer.java:505)\n\tat com.googlecode.dex2jar.ir.ts.array.FillArrayTransformer.transformReportChanged(FillArrayTransformer.java:123)\n\tat com.googlecode.dex2jar.ir.ts.StatedTransformer.transform(StatedTransformer.java:10)\n\tat com.googlecode.d2j.dex.Dex2jar$2.optimize(Dex2jar.java:149)\n\tat com.googlecode.d2j.dex.Dex2Asm.convertCode(Dex2Asm.java:414)\n\tat com.googlecode.d2j.dex.ExDex2Asm.convertCode(ExDex2Asm.java:42)\n\tat com.googlecode.d2j.dex.Dex2jar$2.convertCode(Dex2jar.java:128)\n\tat com.googlecode.d2j.dex.Dex2Asm.convertMethod(Dex2Asm.java:509)\n\tat com.googlecode.d2j.dex.Dex2Asm.convertClass(Dex2Asm.java:406)\n\tat com.googlecode.d2j.dex.Dex2Asm.convertDex(Dex2Asm.java:422)\n\tat com.googlecode.d2j.dex.Dex2jar.doTranslate(Dex2jar.java:172)\n\tat com.googlecode.d2j.dex.Dex2jar.to(Dex2jar.java:272)\n\tat com.googlecode.dex2jar.tools.Dex2jarCmd.doCommandLine(Dex2jarCmd.java:108)\n\tat com.googlecode.dex2jar.tools.BaseCmd.doMain(BaseCmd.java:288)\n\tat com.googlecode.dex2jar.tools.Dex2jarCmd.main(Dex2jarCmd.java:32)\n");
  }
  
  @Nullable
  public String bлл043B043Bлллл043Bл()
  {
    switch (1)
    {
    case 0: 
    default: 
      for (;;)
      {
        switch (1)
        {
        }
      }
    }
    int i = bллл043Bлллл043Bл();
    if ((bллл043Bлллл043Bл() + b043B043B043Bллллл043Bл()) * bллл043Bлллл043Bл() % b043Bл043Bллллл043Bл() != bл043B043Bллллл043Bл()) {}
    switch (i * (b043B043B043Bллллл043Bл() + i) % b043Bл043Bллллл043Bл())
    {
    }
    return this.b0429ЩЩ042904290429ЩЩ04290429;
  }
  
  @NonNull
  public String bлл043Bл043Bллл043Bл()
  {
    switch (0)
    {
    case 1: 
    default: 
      for (;;)
      {
        switch (0)
        {
        }
      }
    }
    switch (1)
    {
    case 0: 
    default: 
      for (;;)
      {
        switch (0)
        {
        }
      }
    }
    if (((bллл043Bлллл043Bл() + b043B043B043Bллллл043Bл()) * bллл043Bлллл043Bл() % b043Bл043Bллллл043Bл() != bл043B043Bллллл043Bл()) && ((bллл043Bлллл043Bл() + b043B043B043Bллллл043Bл()) * bллл043Bлллл043Bл() % b043Bл043Bллллл043Bл() != bл043B043Bллллл043Bл())) {}
    return this.b04290429ЩЩЩЩ0429Щ04290429;
  }
  
  /* Error */
  @Nullable
  public String bллл043B043Bллл043Bл()
  {
    // Byte code:
    //   0: invokestatic 85	kkkkkk/ttyytt:bллл043Bлллл043Bл	()I
    //   3: invokestatic 88	kkkkkk/ttyytt:b043B043B043Bллллл043Bл	()I
    //   6: iadd
    //   7: invokestatic 85	kkkkkk/ttyytt:bллл043Bлллл043Bл	()I
    //   10: imul
    //   11: invokestatic 91	kkkkkk/ttyytt:b043Bл043Bллллл043Bл	()I
    //   14: irem
    //   15: invokestatic 97	kkkkkk/ttyytt:bл043B043Bллллл043Bл	()I
    //   18: if_icmpeq +3 -> 21
    //   21: iconst_1
    //   22: tableswitch	default:+22->44, 0:+-22->0, 1:+49->71
    //   44: iconst_1
    //   45: tableswitch	default:+23->68, 0:+-45->0, 1:+26->71
    //   68: goto -24 -> 44
    //   71: aload_0
    //   72: getfield 154	kkkkkk/ttyytt:b042904290429ЩЩЩ0429Щ04290429	Ljava/lang/String;
    //   75: astore 6
    //   77: invokestatic 85	kkkkkk/ttyytt:bллл043Bлллл043Bл	()I
    //   80: istore_1
    //   81: invokestatic 88	kkkkkk/ttyytt:b043B043B043Bллллл043Bл	()I
    //   84: istore_2
    //   85: invokestatic 85	kkkkkk/ttyytt:bллл043Bлллл043Bл	()I
    //   88: istore_3
    //   89: invokestatic 91	kkkkkk/ttyytt:b043Bл043Bллллл043Bл	()I
    //   92: istore 4
    //   94: invokestatic 97	kkkkkk/ttyytt:bл043B043Bллллл043Bл	()I
    //   97: istore 5
    //   99: iload_1
    //   100: iload_2
    //   101: iadd
    //   102: iload_3
    //   103: imul
    //   104: iload 4
    //   106: irem
    //   107: iload 5
    //   109: if_icmpeq +3 -> 112
    //   112: aload 6
    //   114: areturn
    //   115: astore 6
    //   117: aload 6
    //   119: athrow
    //   120: astore 6
    //   122: aload 6
    //   124: athrow
    // Local variable table:
    //   start	length	slot	name	signature
    //   0	125	0	this	ttyytt
    //   80	22	1	i	int
    //   84	18	2	j	int
    //   88	16	3	k	int
    //   92	15	4	m	int
    //   97	13	5	n	int
    //   75	38	6	str	String
    //   115	3	6	localException1	Exception
    //   120	3	6	localException2	Exception
    // Exception table:
    //   from	to	target	type
    //   71	77	115	java/lang/Exception
    //   77	99	120	java/lang/Exception
  }
  
  @NonNull
  public String bлллл043Bллл043Bл()
  {
    String str = this.b0429Щ0429042904290429ЩЩ04290429;
    if ((bллл043Bлллл043Bл() + b043B043B043Bллллл043Bл()) * bллл043Bлллл043Bл() % b043Bл043Bллллл043Bл() != bл043B043Bллллл043Bл()) {}
    switch (0)
    {
    case 1: 
    default: 
      for (;;)
      {
        switch (1)
        {
        case 0: 
        default: 
          for (;;)
          {
            switch (0)
            {
            }
          }
        }
        if ((bллл043Bлллл043Bл() + b043B043B043Bллллл043Bл()) * bллл043Bлллл043Bл() % b043Bл043Bллллл043Bл() != bл043B043Bллллл043Bл()) {}
        switch (1)
        {
        }
      }
    }
    return str;
  }
  
  @Nullable
  public aababa bллллл043Bлл043Bл()
  {
    if (((bллл043Bлллл043Bл() + b043B043B043Bллллл043Bл()) * bллл043Bлллл043Bл() % b043Bл043Bллллл043Bл() != bл043B043Bллллл043Bл()) && ((bллл043Bлллл043Bл() + b043B043B043Bллллл043Bл()) * bллл043Bлллл043Bл() % b043Bл043Bллллл043Bл() != bл043B043Bллллл043Bл())) {}
    try
    {
      aababa localAababa = this.b0429042904290429ЩЩ0429Щ04290429;
      return localAababa;
    }
    catch (Exception localException)
    {
      throw localException;
    }
  }
}
