package kkkkkk;

import android.support.annotation.NonNull;
import java.util.ArrayList;
import java.util.List;

public class txtttt
  implements vvovov, xxddxd
{
  private static final int b042A042A042A042AЪЪЪ042AЪ = 5;
  public static int b042A042AЪ042A042AЪЪ042AЪ = 2;
  public static int b042AЪЪ042A042AЪЪ042AЪ = 0;
  private static txtttt b042AЪЪЪ042AЪЪ042AЪ;
  private static final String bЪ042A042A042AЪЪЪ042AЪ = "\\aQ\\b[hXWm[]hbq-dc";
  public static int bЪ042AЪ042A042AЪЪ042AЪ = 1;
  public static int bЪЪЪ042A042AЪЪ042AЪ = 90;
  private static final String bЪЪЪЪ042AЪЪ042AЪ;
  private List<xtxttt> b042A042A042AЪ042AЪЪ042AЪ = new ArrayList();
  private final xxxttt b042A042AЪЪ042AЪЪ042AЪ = new xxxttt();
  private final txtxtt b042AЪ042AЪ042AЪЪ042AЪ = new txtxtt();
  private final xxtxtt bЪ042A042AЪ042AЪЪ042AЪ = new xxtxtt();
  private final txxttt bЪ042AЪЪ042AЪЪ042AЪ = new txxttt();
  private final txtttt.ttxttt bЪЪ042AЪ042AЪЪ042AЪ = new txtttt.ttxttt(this);
  
  /* Error */
  static
  {
    // Byte code:
    //   0: new 47	java/lang/NullPointerException
    //   3: dup
    //   4: invokespecial 50	java/lang/NullPointerException:<init>	()V
    //   7: athrow
    //   8: astore_0
    //   9: getstatic 52	kkkkkk/txtttt:bЪ042A042A042AЪЪЪ042AЪ	Ljava/lang/String;
    //   12: bipush 76
    //   14: sipush 162
    //   17: iconst_3
    //   18: invokestatic 58	kkkkkk/gguuuu:bк043Aккк043Aкк043A043A	(Ljava/lang/String;CCC)Ljava/lang/String;
    //   21: putstatic 52	kkkkkk/txtttt:bЪ042A042A042AЪЪЪ042AЪ	Ljava/lang/String;
    //   24: ldc 2
    //   26: invokevirtual 64	java/lang/Class:getSimpleName	()Ljava/lang/String;
    //   29: putstatic 66	kkkkkk/txtttt:bЪЪЪЪ042AЪЪ042AЪ	Ljava/lang/String;
    //   32: aconst_null
    //   33: putstatic 68	kkkkkk/txtttt:b042AЪЪЪ042AЪЪ042AЪ	Lkkkkkk/txtttt;
    //   36: return
    //   37: astore_0
    //   38: aload_0
    //   39: athrow
    //   40: astore_0
    //   41: aload_0
    //   42: athrow
    //   43: astore_0
    //   44: aload_0
    //   45: athrow
    // Local variable table:
    //   start	length	slot	name	signature
    //   8	1	0	localException1	Exception
    //   37	2	0	localException2	Exception
    //   40	2	0	localException3	Exception
    //   43	2	0	localException4	Exception
    // Exception table:
    //   from	to	target	type
    //   0	8	8	java/lang/Exception
    //   9	24	37	java/lang/Exception
    //   38	40	40	java/lang/Exception
    //   44	46	40	java/lang/Exception
    //   24	36	43	java/lang/Exception
  }
  
  private txtttt()
  {
    tttxtt localTttxtt = new tttxtt();
    bи043804380438и04380438иии(this.b042AЪ042AЪ042AЪЪ042AЪ);
    bи043804380438и04380438иии(this.b042A042AЪЪ042AЪЪ042AЪ);
    bи043804380438и04380438иии(this.bЪ042AЪЪ042AЪЪ042AЪ);
    bи043804380438и04380438иии(this.bЪ042A042AЪ042AЪЪ042AЪ);
    bи043804380438и04380438иии(localTttxtt);
    this.bЪЪ042AЪ042AЪЪ042AЪ.getWritableDatabase();
  }
  
  public static int b043804380438ии04380438иии()
  {
    return 1;
  }
  
  public static txtttt b04380438и0438и04380438иии()
  {
    if (b042AЪЪЪ042AЪЪ042AЪ == null) {}
    try
    {
      if (b042AЪЪЪ042AЪЪ042AЪ == null)
      {
        break label41;
        b042AЪЪЪ042AЪЪ042AЪ = new txtttt();
      }
      else
      {
        return b042AЪЪЪ042AЪЪ042AЪ;
      }
    }
    finally {}
    label41:
    switch (0)
    {
    }
    for (;;)
    {
      switch (1)
      {
      }
    }
  }
  
  public static int b0438и0438ии04380438иии()
  {
    return 30;
  }
  
  public static int bи04380438ии04380438иии()
  {
    return 2;
  }
  
  public xxtxtt b0438и04380438и04380438иии()
  {
    switch (0)
    {
    case 1: 
    default: 
      for (;;)
      {
        switch (0)
        {
        }
      }
    }
    switch (1)
    {
    case 0: 
    default: 
      for (;;)
      {
        switch (0)
        {
        }
      }
    }
    int i = bЪЪЪ042A042AЪЪ042AЪ;
    int j = bЪ042AЪ042A042AЪЪ042AЪ;
    int k = bЪЪЪ042A042AЪЪ042AЪ;
    if ((bЪЪЪ042A042AЪЪ042AЪ + bЪ042AЪ042A042AЪЪ042AЪ) * bЪЪЪ042A042AЪЪ042AЪ % b042A042AЪ042A042AЪЪ042AЪ != b042AЪЪ042A042AЪЪ042AЪ)
    {
      bЪЪЪ042A042AЪЪ042AЪ = 51;
      b042AЪЪ042A042AЪЪ042AЪ = b0438и0438ии04380438иии();
    }
    if ((i + j) * k % b042A042AЪ042A042AЪЪ042AЪ != b042AЪЪ042A042AЪЪ042AЪ)
    {
      bЪЪЪ042A042AЪЪ042AЪ = b0438и0438ии04380438иии();
      b042AЪЪ042A042AЪЪ042AЪ = b0438и0438ии04380438иии();
    }
    return this.bЪ042A042AЪ042AЪЪ042AЪ;
  }
  
  /* Error */
  public xxxttt b0438ии0438и04380438иии()
  {
    // Byte code:
    //   0: getstatic 119	kkkkkk/txtttt:bЪЪЪ042A042AЪЪ042AЪ	I
    //   3: istore_1
    //   4: invokestatic 128	kkkkkk/txtttt:b043804380438ии04380438иии	()I
    //   7: istore_2
    //   8: getstatic 119	kkkkkk/txtttt:bЪЪЪ042A042AЪЪ042AЪ	I
    //   11: istore_3
    //   12: invokestatic 141	kkkkkk/txtttt:bи04380438ии04380438иии	()I
    //   15: istore 4
    //   17: getstatic 130	kkkkkk/txtttt:b042AЪЪ042A042AЪЪ042AЪ	I
    //   20: istore 5
    //   22: iload_1
    //   23: iload_2
    //   24: iadd
    //   25: iload_3
    //   26: imul
    //   27: iload 4
    //   29: irem
    //   30: iload 5
    //   32: if_icmpeq +44 -> 76
    //   35: getstatic 119	kkkkkk/txtttt:bЪЪЪ042A042AЪЪ042AЪ	I
    //   38: getstatic 121	kkkkkk/txtttt:bЪ042AЪ042A042AЪЪ042AЪ	I
    //   41: iadd
    //   42: getstatic 119	kkkkkk/txtttt:bЪЪЪ042A042AЪЪ042AЪ	I
    //   45: imul
    //   46: getstatic 123	kkkkkk/txtttt:b042A042AЪ042A042AЪЪ042AЪ	I
    //   49: irem
    //   50: getstatic 130	kkkkkk/txtttt:b042AЪЪ042A042AЪЪ042AЪ	I
    //   53: if_icmpeq +14 -> 67
    //   56: invokestatic 126	kkkkkk/txtttt:b0438и0438ии04380438иии	()I
    //   59: putstatic 119	kkkkkk/txtttt:bЪЪЪ042A042AЪЪ042AЪ	I
    //   62: bipush 71
    //   64: putstatic 130	kkkkkk/txtttt:b042AЪЪ042A042AЪЪ042AЪ	I
    //   67: iconst_5
    //   68: putstatic 119	kkkkkk/txtttt:bЪЪЪ042A042AЪЪ042AЪ	I
    //   71: bipush 36
    //   73: putstatic 130	kkkkkk/txtttt:b042AЪЪ042A042AЪЪ042AЪ	I
    //   76: aload_0
    //   77: getfield 90	kkkkkk/txtttt:b042A042AЪЪ042AЪЪ042AЪ	Lkkkkkk/xxxttt;
    //   80: astore 6
    //   82: aload 6
    //   84: areturn
    //   85: astore 6
    //   87: aload 6
    //   89: athrow
    //   90: astore 6
    //   92: aload 6
    //   94: athrow
    //   95: astore 6
    //   97: aload 6
    //   99: athrow
    // Local variable table:
    //   start	length	slot	name	signature
    //   0	100	0	this	txtttt
    //   3	22	1	i	int
    //   7	18	2	j	int
    //   11	16	3	k	int
    //   15	15	4	m	int
    //   20	13	5	n	int
    //   80	3	6	localXxxttt	xxxttt
    //   85	3	6	localException1	Exception
    //   90	3	6	localException2	Exception
    //   95	3	6	localException3	Exception
    // Exception table:
    //   from	to	target	type
    //   76	82	85	java/lang/Exception
    //   0	22	90	java/lang/Exception
    //   87	90	90	java/lang/Exception
    //   67	76	95	java/lang/Exception
  }
  
  /* Error */
  public void b0445044504450445044504450445х04450445()
  {
    // Byte code:
    //   0: getstatic 66	kkkkkk/txtttt:bЪЪЪЪ042AЪЪ042AЪ	Ljava/lang/String;
    //   3: astore 5
    //   5: ldc -112
    //   7: sipush 155
    //   10: iconst_2
    //   11: invokestatic 148	kkkkkk/gguuuu:bккккк043Aкк043A043A	(Ljava/lang/String;CC)Ljava/lang/String;
    //   14: astore 6
    //   16: aload 5
    //   18: aload 6
    //   20: invokestatic 154	kkkkkk/xtxtxt:bии0438и04380438и0438ии	(Ljava/lang/String;Ljava/lang/String;)V
    //   23: getstatic 160	kkkkkk/xxdxxd:instance	Lkkkkkk/xxdxxd;
    //   26: invokevirtual 164	kkkkkk/xxdxxd:bххх044504450445х044504450445	()Landroid/content/Context;
    //   29: ldc -90
    //   31: bipush 49
    //   33: iconst_3
    //   34: invokestatic 148	kkkkkk/gguuuu:bккккк043Aкк043A043A	(Ljava/lang/String;CC)Ljava/lang/String;
    //   37: invokevirtual 172	android/content/Context:deleteDatabase	(Ljava/lang/String;)Z
    //   40: pop
    //   41: aconst_null
    //   42: putstatic 68	kkkkkk/txtttt:b042AЪЪЪ042AЪЪ042AЪ	Lkkkkkk/txtttt;
    //   45: getstatic 119	kkkkkk/txtttt:bЪЪЪ042A042AЪЪ042AЪ	I
    //   48: istore_1
    //   49: getstatic 121	kkkkkk/txtttt:bЪ042AЪ042A042AЪЪ042AЪ	I
    //   52: istore_2
    //   53: getstatic 123	kkkkkk/txtttt:b042A042AЪ042A042AЪЪ042AЪ	I
    //   56: istore_3
    //   57: getstatic 119	kkkkkk/txtttt:bЪЪЪ042A042AЪЪ042AЪ	I
    //   60: istore 4
    //   62: iload 4
    //   64: getstatic 121	kkkkkk/txtttt:bЪ042AЪ042A042AЪЪ042AЪ	I
    //   67: iload 4
    //   69: iadd
    //   70: imul
    //   71: getstatic 123	kkkkkk/txtttt:b042A042AЪ042A042AЪЪ042AЪ	I
    //   74: irem
    //   75: tableswitch	default:+17->92, 0:+26->101
    //   92: iconst_1
    //   93: putstatic 119	kkkkkk/txtttt:bЪЪЪ042A042AЪЪ042AЪ	I
    //   96: bipush 75
    //   98: putstatic 130	kkkkkk/txtttt:b042AЪЪ042A042AЪЪ042AЪ	I
    //   101: iload_1
    //   102: iload_2
    //   103: iload_1
    //   104: iadd
    //   105: imul
    //   106: iload_3
    //   107: irem
    //   108: tableswitch	default:+20->128, 0:+31->139
    //   128: bipush 76
    //   130: putstatic 119	kkkkkk/txtttt:bЪЪЪ042A042AЪЪ042AЪ	I
    //   133: invokestatic 126	kkkkkk/txtttt:b0438и0438ии04380438иии	()I
    //   136: putstatic 130	kkkkkk/txtttt:b042AЪЪ042A042AЪЪ042AЪ	I
    //   139: return
    //   140: astore 5
    //   142: aload 5
    //   144: athrow
    //   145: astore 5
    //   147: aload 5
    //   149: athrow
    // Local variable table:
    //   start	length	slot	name	signature
    //   0	150	0	this	txtttt
    //   48	58	1	i	int
    //   52	53	2	j	int
    //   56	52	3	k	int
    //   60	11	4	m	int
    //   3	14	5	str1	String
    //   140	3	5	localException1	Exception
    //   145	3	5	localException2	Exception
    //   14	5	6	str2	String
    // Exception table:
    //   from	to	target	type
    //   16	41	140	java/lang/Exception
    //   0	16	145	java/lang/Exception
    //   41	57	145	java/lang/Exception
    //   128	139	145	java/lang/Exception
  }
  
  /* Error */
  public void b0445ххх0445хх044504450445()
  {
    // Byte code:
    //   0: new 175	kkkkkk/txtttt$1
    //   3: dup
    //   4: aload_0
    //   5: invokespecial 176	kkkkkk/txtttt$1:<init>	(Lkkkkkk/txtttt;)V
    //   8: astore 4
    //   10: getstatic 119	kkkkkk/txtttt:bЪЪЪ042A042AЪЪ042AЪ	I
    //   13: istore_1
    //   14: iload_1
    //   15: getstatic 121	kkkkkk/txtttt:bЪ042AЪ042A042AЪЪ042AЪ	I
    //   18: iload_1
    //   19: iadd
    //   20: imul
    //   21: getstatic 123	kkkkkk/txtttt:b042A042AЪ042A042AЪЪ042AЪ	I
    //   24: irem
    //   25: tableswitch	default:+19->44, 0:+31->56
    //   44: invokestatic 126	kkkkkk/txtttt:b0438и0438ии04380438иии	()I
    //   47: putstatic 119	kkkkkk/txtttt:bЪЪЪ042A042AЪЪ042AЪ	I
    //   50: invokestatic 126	kkkkkk/txtttt:b0438и0438ии04380438иии	()I
    //   53: putstatic 130	kkkkkk/txtttt:b042AЪЪ042A042AЪЪ042AЪ	I
    //   56: iconst_0
    //   57: tableswitch	default:+23->80, 0:+50->107, 1:+-47->10
    //   80: iconst_1
    //   81: tableswitch	default:+23->104, 0:+-71->10, 1:+26->107
    //   104: goto -24 -> 80
    //   107: getstatic 119	kkkkkk/txtttt:bЪЪЪ042A042AЪЪ042AЪ	I
    //   110: istore_1
    //   111: getstatic 121	kkkkkk/txtttt:bЪ042AЪ042A042AЪЪ042AЪ	I
    //   114: istore_2
    //   115: getstatic 123	kkkkkk/txtttt:b042A042AЪ042A042AЪЪ042AЪ	I
    //   118: istore_3
    //   119: iload_1
    //   120: iload_2
    //   121: iload_1
    //   122: iadd
    //   123: imul
    //   124: iload_3
    //   125: irem
    //   126: tableswitch	default:+18->144, 0:+29->155
    //   144: invokestatic 126	kkkkkk/txtttt:b0438и0438ии04380438иии	()I
    //   147: putstatic 119	kkkkkk/txtttt:bЪЪЪ042A042AЪЪ042AЪ	I
    //   150: bipush 14
    //   152: putstatic 130	kkkkkk/txtttt:b042AЪЪ042A042AЪЪ042AЪ	I
    //   155: aload 4
    //   157: invokestatic 182	kkkkkk/dxxxxx:bи0438и04380438и0438иии	(Lkkkkkk/dddxxd;)V
    //   160: return
    //   161: astore 4
    //   163: aload 4
    //   165: athrow
    //   166: astore 4
    //   168: aload 4
    //   170: athrow
    // Local variable table:
    //   start	length	slot	name	signature
    //   0	171	0	this	txtttt
    //   13	111	1	i	int
    //   114	9	2	j	int
    //   118	8	3	k	int
    //   8	148	4	local1	txtttt.1
    //   161	3	4	localException1	Exception
    //   166	3	4	localException2	Exception
    // Exception table:
    //   from	to	target	type
    //   0	10	161	java/lang/Exception
    //   107	111	161	java/lang/Exception
    //   144	150	161	java/lang/Exception
    //   111	119	166	java/lang/Exception
    //   150	155	166	java/lang/Exception
    //   155	160	166	java/lang/Exception
  }
  
  public void bи043804380438и04380438иии(@NonNull xtxttt paramXtxttt)
  {
    this.b042A042A042AЪ042AЪЪ042AЪ.add(paramXtxttt);
  }
  
  public txtttt.ttxttt bи0438и0438и04380438иии()
  {
    try
    {
      txtttt.ttxttt localTtxttt = this.bЪЪ042AЪ042AЪЪ042AЪ;
      int i = bЪЪЪ042A042AЪЪ042AЪ;
      int j = bЪ042AЪ042A042AЪЪ042AЪ;
      int k = bЪЪЪ042A042AЪЪ042AЪ;
      int m = bЪЪЪ042A042AЪЪ042AЪ;
      switch (m * (bЪ042AЪ042A042AЪЪ042AЪ + m) % b042A042AЪ042A042AЪЪ042AЪ)
      {
      default: 
        bЪЪЪ042A042AЪЪ042AЪ = 12;
        b042AЪЪ042A042AЪЪ042AЪ = 53;
      }
      if ((i + j) * k % b042A042AЪ042A042AЪЪ042AЪ != b042AЪЪ042A042AЪЪ042AЪ)
      {
        bЪЪЪ042A042AЪЪ042AЪ = b0438и0438ии04380438иии();
        b042AЪЪ042A042AЪЪ042AЪ = b0438и0438ии04380438иии();
      }
      return localTtxttt;
    }
    catch (Exception localException)
    {
      throw localException;
    }
  }
  
  public txtxtt bии04380438и04380438иии()
  {
    try
    {
      txtxtt localTxtxtt = this.b042AЪ042AЪ042AЪЪ042AЪ;
      return localTxtxtt;
    }
    catch (Exception localException)
    {
      throw localException;
    }
  }
  
  public txxttt bиии0438и04380438иии()
  {
    switch (0)
    {
    case 1: 
    default: 
      for (;;)
      {
        switch (1)
        {
        }
      }
    }
    int i = bЪЪЪ042A042AЪЪ042AЪ;
    int j = bЪ042AЪ042A042AЪЪ042AЪ;
    int k = bЪЪЪ042A042AЪЪ042AЪ;
    if ((bЪЪЪ042A042AЪЪ042AЪ + bЪ042AЪ042A042AЪЪ042AЪ) * bЪЪЪ042A042AЪЪ042AЪ % b042A042AЪ042A042AЪЪ042AЪ != b042AЪЪ042A042AЪЪ042AЪ)
    {
      bЪЪЪ042A042AЪЪ042AЪ = b0438и0438ии04380438иии();
      b042AЪЪ042A042AЪЪ042AЪ = 60;
    }
    if ((i + j) * k % b042A042AЪ042A042AЪЪ042AЪ != b042AЪЪ042A042AЪЪ042AЪ)
    {
      bЪЪЪ042A042AЪЪ042AЪ = 36;
      b042AЪЪ042A042AЪЪ042AЪ = 25;
    }
    return this.bЪ042AЪЪ042AЪЪ042AЪ;
  }
}
