package kkkkkk;

import android.text.TextUtils;
import java.util.ArrayList;
import java.util.LinkedList;
import java.util.List;
import javax.net.ssl.SSLPeerUnverifiedException;

public class txxtxt
  implements ttxxxt<Exception>
{
  public static final String b042A042A042A042A042A042AЪЪ042A = "X[OQ_LYTiP^b[\\ejWm[mcbrhd";
  private static final int b042A042AЪ042A042A042AЪЪ042A = 100;
  public static int b042A042AЪ042AЪЪ042AЪ042A = 1;
  private static final String b042AЪ042A042A042A042AЪЪ042A = "\n\r\001\003\021}\013\006\033\002\020\006\031\033\007\035\023\030\021\f\023!\" $\022'\032$+";
  public static final String b042AЪЪ042A042A042AЪЪ042A = gguuuu.bк043Aккк043Aкк043A043A(b042AЪЪ042A042A042AЪЪ042A, ';', '#', '\003');
  public static int b042AЪЪ042AЪЪ042AЪ042A = 0;
  public static final String bЪ042A042A042A042A042AЪЪ042A = "MN@@L7B;N3?A87>A,0:7*15";
  private static final String bЪ042AЪ042A042A042AЪЪ042A = "\016\020\022\016#\033$\020\024%\025#\032";
  public static int bЪ042AЪ042AЪЪ042AЪ042A = 2;
  private static final long bЪЪ042A042A042A042AЪЪ042A = 3600000L;
  public static int bЪЪЪ042AЪЪ042AЪ042A = 71;
  public static final String bЪЪЪЪЪЪ042AЪ042A;
  private String b042A042A042AЪЪЪ042AЪ042A;
  private long b042A042AЪЪЪЪ042AЪ042A;
  private LinkedList<tttxxt> b042AЪ042AЪЪЪ042AЪ042A = new LinkedList();
  private List<String> b042AЪЪЪЪЪ042AЪ042A;
  private final Object bЪ042A042AЪЪЪ042AЪ042A = new Object();
  private String bЪ042AЪЪЪЪ042AЪ042A;
  private xxtxxt bЪЪ042AЪЪЪ042AЪ042A = new xttxxt();
  
  /* Error */
  static
  {
    // Byte code:
    //   0: getstatic 61	kkkkkk/txxtxt:b042AЪЪ042A042A042AЪЪ042A	Ljava/lang/String;
    //   3: bipush 59
    //   5: bipush 35
    //   7: iconst_3
    //   8: invokestatic 67	kkkkkk/gguuuu:bк043Aккк043Aкк043A043A	(Ljava/lang/String;CCC)Ljava/lang/String;
    //   11: putstatic 61	kkkkkk/txxtxt:b042AЪЪ042A042A042AЪЪ042A	Ljava/lang/String;
    //   14: getstatic 69	kkkkkk/txxtxt:bЪ042AЪ042A042A042AЪЪ042A	Ljava/lang/String;
    //   17: astore 5
    //   19: getstatic 71	kkkkkk/txxtxt:bЪЪЪ042AЪЪ042AЪ042A	I
    //   22: istore_0
    //   23: invokestatic 75	kkkkkk/txxtxt:b04380438ииии04380438ии	()I
    //   26: istore_1
    //   27: getstatic 71	kkkkkk/txxtxt:bЪЪЪ042AЪЪ042AЪ042A	I
    //   30: istore_2
    //   31: getstatic 77	kkkkkk/txxtxt:bЪ042AЪ042AЪЪ042AЪ042A	I
    //   34: istore_3
    //   35: getstatic 71	kkkkkk/txxtxt:bЪЪЪ042AЪЪ042AЪ042A	I
    //   38: istore 4
    //   40: iload 4
    //   42: getstatic 79	kkkkkk/txxtxt:b042A042AЪ042AЪЪ042AЪ042A	I
    //   45: iload 4
    //   47: iadd
    //   48: imul
    //   49: invokestatic 82	kkkkkk/txxtxt:bии0438иии04380438ии	()I
    //   52: irem
    //   53: tableswitch	default:+19->72, 0:+30->83
    //   72: invokestatic 85	kkkkkk/txxtxt:bи0438ииии04380438ии	()I
    //   75: putstatic 71	kkkkkk/txxtxt:bЪЪЪ042AЪЪ042AЪ042A	I
    //   78: bipush 50
    //   80: putstatic 87	kkkkkk/txxtxt:b042AЪЪ042AЪЪ042AЪ042A	I
    //   83: iload_0
    //   84: iload_1
    //   85: iadd
    //   86: iload_2
    //   87: imul
    //   88: iload_3
    //   89: irem
    //   90: getstatic 87	kkkkkk/txxtxt:b042AЪЪ042AЪЪ042AЪ042A	I
    //   93: if_icmpeq +14 -> 107
    //   96: invokestatic 85	kkkkkk/txxtxt:bи0438ииии04380438ии	()I
    //   99: putstatic 71	kkkkkk/txxtxt:bЪЪЪ042AЪЪ042AЪ042A	I
    //   102: bipush 28
    //   104: putstatic 87	kkkkkk/txxtxt:b042AЪЪ042AЪЪ042AЪ042A	I
    //   107: aload 5
    //   109: sipush 152
    //   112: bipush 16
    //   114: iconst_3
    //   115: invokestatic 67	kkkkkk/gguuuu:bк043Aккк043Aкк043A043A	(Ljava/lang/String;CCC)Ljava/lang/String;
    //   118: putstatic 69	kkkkkk/txxtxt:bЪ042AЪ042A042A042AЪЪ042A	Ljava/lang/String;
    //   121: getstatic 89	kkkkkk/txxtxt:b042AЪ042A042A042A042AЪЪ042A	Ljava/lang/String;
    //   124: astore 5
    //   126: aload 5
    //   128: bipush 25
    //   130: iconst_0
    //   131: invokestatic 93	kkkkkk/gguuuu:bккккк043Aкк043A043A	(Ljava/lang/String;CC)Ljava/lang/String;
    //   134: putstatic 89	kkkkkk/txxtxt:b042AЪ042A042A042A042AЪЪ042A	Ljava/lang/String;
    //   137: getstatic 95	kkkkkk/txxtxt:bЪ042A042A042A042A042AЪЪ042A	Ljava/lang/String;
    //   140: sipush 143
    //   143: sipush 235
    //   146: iconst_0
    //   147: invokestatic 67	kkkkkk/gguuuu:bк043Aккк043Aкк043A043A	(Ljava/lang/String;CCC)Ljava/lang/String;
    //   150: putstatic 95	kkkkkk/txxtxt:bЪ042A042A042A042A042AЪЪ042A	Ljava/lang/String;
    //   153: getstatic 97	kkkkkk/txxtxt:b042A042A042A042A042A042AЪЪ042A	Ljava/lang/String;
    //   156: bipush 15
    //   158: sipush 166
    //   161: iconst_1
    //   162: invokestatic 67	kkkkkk/gguuuu:bк043Aккк043Aкк043A043A	(Ljava/lang/String;CCC)Ljava/lang/String;
    //   165: putstatic 97	kkkkkk/txxtxt:b042A042A042A042A042A042AЪЪ042A	Ljava/lang/String;
    //   168: ldc 2
    //   170: invokevirtual 103	java/lang/Class:getSimpleName	()Ljava/lang/String;
    //   173: putstatic 105	kkkkkk/txxtxt:bЪЪЪЪЪЪ042AЪ042A	Ljava/lang/String;
    //   176: return
    //   177: astore 5
    //   179: aload 5
    //   181: athrow
    //   182: astore 5
    //   184: aload 5
    //   186: athrow
    //   187: astore 5
    //   189: aload 5
    //   191: athrow
    //   192: astore 5
    //   194: aload 5
    //   196: athrow
    // Local variable table:
    //   start	length	slot	name	signature
    //   22	64	0	i	int
    //   26	60	1	j	int
    //   30	58	2	k	int
    //   34	56	3	m	int
    //   38	11	4	n	int
    //   17	110	5	str	String
    //   177	3	5	localException1	Exception
    //   182	3	5	localException2	Exception
    //   187	3	5	localException3	Exception
    //   192	3	5	localException4	Exception
    // Exception table:
    //   from	to	target	type
    //   0	19	177	java/lang/Exception
    //   126	153	177	java/lang/Exception
    //   168	176	177	java/lang/Exception
    //   83	107	182	java/lang/Exception
    //   179	182	182	java/lang/Exception
    //   189	192	182	java/lang/Exception
    //   107	126	187	java/lang/Exception
    //   153	168	187	java/lang/Exception
    //   19	35	192	java/lang/Exception
  }
  
  public txxtxt()
  {
    b04380438ии0438и04380438ии();
  }
  
  /* Error */
  private void b04380438ии0438и04380438ии()
  {
    // Byte code:
    //   0: aload_0
    //   1: getfield 126	kkkkkk/txxtxt:bЪ042AЪЪЪЪ042AЪ042A	Ljava/lang/String;
    //   4: astore 6
    //   6: aload 6
    //   8: ifnonnull +79 -> 87
    //   11: invokestatic 132	kkkkkk/xtxxxt:b0438ии04380438043804380438ии	()Lkkkkkk/xtxxxt;
    //   14: astore 6
    //   16: ldc -122
    //   18: sipush 169
    //   21: sipush 150
    //   24: iconst_1
    //   25: invokestatic 67	kkkkkk/gguuuu:bк043Aккк043Aкк043A043A	(Ljava/lang/String;CCC)Ljava/lang/String;
    //   28: astore 7
    //   30: aload_0
    //   31: aload 6
    //   33: aload 7
    //   35: ldc -120
    //   37: bipush 82
    //   39: bipush 119
    //   41: iconst_1
    //   42: invokestatic 67	kkkkkk/gguuuu:bк043Aккк043Aкк043A043A	(Ljava/lang/String;CCC)Ljava/lang/String;
    //   45: aconst_null
    //   46: invokevirtual 140	kkkkkk/xtxxxt:bи0438043804380438043804380438ии	(Ljava/lang/String;Ljava/lang/String;Ljava/lang/String;)Ljava/lang/String;
    //   49: putfield 126	kkkkkk/txxtxt:bЪ042AЪЪЪЪ042AЪ042A	Ljava/lang/String;
    //   52: getstatic 105	kkkkkk/txxtxt:bЪЪЪЪЪЪ042AЪ042A	Ljava/lang/String;
    //   55: new 142	java/lang/StringBuilder
    //   58: dup
    //   59: invokespecial 143	java/lang/StringBuilder:<init>	()V
    //   62: ldc -111
    //   64: sipush 135
    //   67: iconst_1
    //   68: invokestatic 93	kkkkkk/gguuuu:bккккк043Aкк043A043A	(Ljava/lang/String;CC)Ljava/lang/String;
    //   71: invokevirtual 149	java/lang/StringBuilder:append	(Ljava/lang/String;)Ljava/lang/StringBuilder;
    //   74: aload_0
    //   75: getfield 126	kkkkkk/txxtxt:bЪ042AЪЪЪЪ042AЪ042A	Ljava/lang/String;
    //   78: invokevirtual 149	java/lang/StringBuilder:append	(Ljava/lang/String;)Ljava/lang/StringBuilder;
    //   81: invokevirtual 152	java/lang/StringBuilder:toString	()Ljava/lang/String;
    //   84: invokestatic 158	kkkkkk/xtxtxt:bии0438и04380438и0438ии	(Ljava/lang/String;Ljava/lang/String;)V
    //   87: aload_0
    //   88: getfield 160	kkkkkk/txxtxt:b042A042A042AЪЪЪ042AЪ042A	Ljava/lang/String;
    //   91: ifnonnull +136 -> 227
    //   94: invokestatic 132	kkkkkk/xtxxxt:b0438ии04380438043804380438ии	()Lkkkkkk/xtxxxt;
    //   97: ldc -94
    //   99: bipush 115
    //   101: bipush 77
    //   103: iconst_0
    //   104: invokestatic 67	kkkkkk/gguuuu:bк043Aккк043Aкк043A043A	(Ljava/lang/String;CCC)Ljava/lang/String;
    //   107: ldc -92
    //   109: sipush 141
    //   112: sipush 135
    //   115: iconst_1
    //   116: invokestatic 67	kkkkkk/gguuuu:bк043Aккк043Aкк043A043A	(Ljava/lang/String;CCC)Ljava/lang/String;
    //   119: aconst_null
    //   120: invokevirtual 140	kkkkkk/xtxxxt:bи0438043804380438043804380438ии	(Ljava/lang/String;Ljava/lang/String;Ljava/lang/String;)Ljava/lang/String;
    //   123: astore 6
    //   125: invokestatic 85	kkkkkk/txxtxt:bи0438ииии04380438ии	()I
    //   128: istore_1
    //   129: getstatic 79	kkkkkk/txxtxt:b042A042AЪ042AЪЪ042AЪ042A	I
    //   132: istore_2
    //   133: invokestatic 85	kkkkkk/txxtxt:bи0438ииии04380438ии	()I
    //   136: istore_3
    //   137: invokestatic 82	kkkkkk/txxtxt:bии0438иии04380438ии	()I
    //   140: istore 4
    //   142: invokestatic 167	kkkkkk/txxtxt:b0438и0438иии04380438ии	()I
    //   145: istore 5
    //   147: iload_1
    //   148: iload_2
    //   149: iadd
    //   150: iload_3
    //   151: imul
    //   152: iload 4
    //   154: irem
    //   155: iload 5
    //   157: if_icmpeq +14 -> 171
    //   160: invokestatic 85	kkkkkk/txxtxt:bи0438ииии04380438ии	()I
    //   163: putstatic 71	kkkkkk/txxtxt:bЪЪЪ042AЪЪ042AЪ042A	I
    //   166: bipush 92
    //   168: putstatic 87	kkkkkk/txxtxt:b042AЪЪ042AЪЪ042AЪ042A	I
    //   171: aload_0
    //   172: aload 6
    //   174: putfield 160	kkkkkk/txxtxt:b042A042A042AЪЪЪ042AЪ042A	Ljava/lang/String;
    //   177: getstatic 105	kkkkkk/txxtxt:bЪЪЪЪЪЪ042AЪ042A	Ljava/lang/String;
    //   180: astore 6
    //   182: new 142	java/lang/StringBuilder
    //   185: dup
    //   186: invokespecial 143	java/lang/StringBuilder:<init>	()V
    //   189: astore 7
    //   191: aload 7
    //   193: ldc -87
    //   195: bipush 67
    //   197: iconst_1
    //   198: invokestatic 93	kkkkkk/gguuuu:bккккк043Aкк043A043A	(Ljava/lang/String;CC)Ljava/lang/String;
    //   201: invokevirtual 149	java/lang/StringBuilder:append	(Ljava/lang/String;)Ljava/lang/StringBuilder;
    //   204: aload_0
    //   205: getfield 160	kkkkkk/txxtxt:b042A042A042AЪЪЪ042AЪ042A	Ljava/lang/String;
    //   208: invokevirtual 149	java/lang/StringBuilder:append	(Ljava/lang/String;)Ljava/lang/StringBuilder;
    //   211: astore 7
    //   213: aload 7
    //   215: invokevirtual 152	java/lang/StringBuilder:toString	()Ljava/lang/String;
    //   218: astore 7
    //   220: aload 6
    //   222: aload 7
    //   224: invokestatic 158	kkkkkk/xtxtxt:bии0438и04380438и0438ии	(Ljava/lang/String;Ljava/lang/String;)V
    //   227: return
    //   228: astore 6
    //   230: aload 6
    //   232: athrow
    //   233: astore 6
    //   235: aload 6
    //   237: athrow
    // Local variable table:
    //   start	length	slot	name	signature
    //   0	238	0	this	txxtxt
    //   128	22	1	i	int
    //   132	18	2	j	int
    //   136	16	3	k	int
    //   140	15	4	m	int
    //   145	13	5	n	int
    //   4	217	6	localObject1	Object
    //   228	3	6	localException1	Exception
    //   233	3	6	localException2	Exception
    //   28	195	7	localObject2	Object
    // Exception table:
    //   from	to	target	type
    //   0	6	228	java/lang/Exception
    //   30	87	228	java/lang/Exception
    //   87	147	228	java/lang/Exception
    //   191	213	228	java/lang/Exception
    //   220	227	228	java/lang/Exception
    //   11	16	233	java/lang/Exception
    //   16	30	233	java/lang/Exception
    //   160	171	233	java/lang/Exception
    //   171	191	233	java/lang/Exception
    //   213	220	233	java/lang/Exception
  }
  
  public static int b04380438ииии04380438ии()
  {
    return 1;
  }
  
  public static int b0438и0438иии04380438ии()
  {
    return 0;
  }
  
  private boolean b0438ии0438ии04380438ии()
  {
    try
    {
      boolean bool = xxdddx.b0445хх04450445х0445044504450445();
      if ((bЪЪЪ042AЪЪ042AЪ042A + b042A042AЪ042AЪЪ042AЪ042A) * bЪЪЪ042AЪЪ042AЪ042A % bЪ042AЪ042AЪЪ042AЪ042A != b042AЪЪ042AЪЪ042AЪ042A)
      {
        bЪЪЪ042AЪЪ042AЪ042A = 42;
        b042AЪЪ042AЪЪ042AЪ042A = 89;
        if ((bЪЪЪ042AЪЪ042AЪ042A + b042A042AЪ042AЪЪ042AЪ042A) * bЪЪЪ042AЪЪ042AЪ042A % bЪ042AЪ042AЪЪ042AЪ042A != b042AЪЪ042AЪЪ042AЪ042A)
        {
          bЪЪЪ042AЪЪ042AЪ042A = bи0438ииии04380438ии();
          b042AЪЪ042AЪЪ042AЪ042A = bи0438ииии04380438ии();
        }
      }
      return bool;
    }
    catch (Exception localException)
    {
      throw localException;
    }
  }
  
  private void b0438иииии04380438ии(tttxxt paramTttxxt)
  {
    synchronized (this.bЪ042A042AЪЪЪ042AЪ042A)
    {
      if (this.b042AЪ042AЪЪЪ042AЪ042A.size() >= 100)
      {
        this.b042AЪ042AЪЪЪ042AЪ042A.removeLast();
        break label46;
        this.b042AЪ042AЪЪЪ042AЪ042A.addFirst(paramTttxxt);
        return;
      }
    }
    label46:
    switch (0)
    {
    }
    for (;;)
    {
      switch (0)
      {
      }
    }
  }
  
  private void bи043804380438ии04380438ии()
  {
    if ((b0438ии0438ии04380438ии()) && (bи0438и0438ии04380438ии()))
    {
      Object localObject1 = new ArrayList();
      ??? = bЪЪЪЪЪЪ042AЪ042A;
      StringBuilder localStringBuilder = new StringBuilder().append(gguuuu.bк043Aккк043Aкк043A043A("m`ja?klRwhyj@'[}k}\001G.", 'Å', 'Ë', '\001'));
      long l = System.currentTimeMillis();
      switch (1)
      {
      case 0: 
      default: 
        for (;;)
        {
          switch (0)
          {
          }
        }
      }
      xtxtxt.bии0438и04380438и0438ии((String)???, l);
      synchronized (this.bЪ042A042AЪЪЪ042AЪ042A)
      {
        xtxtxt.bии0438и04380438и0438ии(bЪЪЪЪЪЪ042AЪ042A, gguuuu.bк043Aккк043Aкк043A043A("[LTI%ON2UDSB\026z\035HHPuB9FE274m95>>h)5*d'/'\"2^", 'C', '+', '\000') + this.b042AЪ042AЪЪЪ042AЪ042A.size() + gguuuu.bк043Aккк043Aкк043A043A("k8/<;(-*7", '½', '\n', '\000'));
        ((List)localObject1).addAll(this.b042AЪ042AЪЪЪ042AЪ042A);
        this.b042AЪ042AЪЪЪ042AЪ042A.clear();
        xtxtxt.bии0438и04380438и0438ии(bЪЪЪЪЪЪ042AЪ042A, gguuuu.bккккк043Aкк043A043A("\016~\007{W\002\001d\bv\006tH-_pxmqum%eon!rdnlodnhjp\"\025", 'L', '\002') + ((List)localObject1).size() + gguuuu.bккккк043Aкк043A043A("\026bYfeRWTa", '\005', '\003'));
        this.bЪЪ042AЪЪЪ042AЪ042A.b0438и04380438и043804380438ии(this.bЪ042AЪЪЪЪ042AЪ042A, (List)localObject1, this.b042AЪЪЪЪЪ042AЪ042A);
        this.b042A042AЪЪЪЪ042AЪ042A = System.currentTimeMillis();
        xtxxxt.b0438ии04380438043804380438ии().bи0438ииииии0438и(gguuuu.bккккк043Aкк043A043A("OPBBN9D=P5A5FF0D8;2+0<;79%8)16", '!', '\005'), gguuuu.bккккк043Aкк043A043A("9;=9NFO;?P@NE", 'T', '\000'), this.b042A042AЪЪЪЪ042AЪ042A);
        localObject1 = bЪЪЪЪЪЪ042AЪ042A;
        ??? = new StringBuilder();
        switch (1)
        {
        case 0: 
        default: 
          for (;;)
          {
            switch (1)
            {
            }
          }
        }
        xtxtxt.bии0438и04380438и0438ии((String)localObject1, gguuuu.bккккк043Aкк043A043A("D7A8\026BC)N?PA\027}$NE\034\003", '§', '\004') + System.currentTimeMillis());
        return;
      }
    }
    xtxtxt.bии0438и04380438и0438ии(bЪЪЪЪЪЪ042AЪ042A, gguuuu.bккккк043Aкк043A043A("ZMWN,XY?dUfW-\024C[kohlf\034fq\037npv#e{gptjlwq-}\0020u{w\003<\0137\tz\016\017<\003\r\017\026\t\013C\031\017\024\rH\020\032\036L\034\024(%Q&\031#\032 & gZ&\"-f5a6)3*f5.=>-43B", '"', '\001'));
  }
  
  public static int bи0438ииии04380438ии()
  {
    return 99;
  }
  
  public static int bии0438иии04380438ии()
  {
    return 2;
  }
  
  /* Error */
  public void b0438043804380438ии04380438ии(tttxxt paramTttxxt)
  {
    // Byte code:
    //   0: getstatic 105	kkkkkk/txxtxt:bЪЪЪЪЪЪ042AЪ042A	Ljava/lang/String;
    //   3: ldc -1
    //   5: sipush 135
    //   8: iconst_3
    //   9: iconst_0
    //   10: invokestatic 67	kkkkkk/gguuuu:bк043Aккк043Aкк043A043A	(Ljava/lang/String;CCC)Ljava/lang/String;
    //   13: invokestatic 158	kkkkkk/xtxtxt:bии0438и04380438и0438ии	(Ljava/lang/String;Ljava/lang/String;)V
    //   16: aload_1
    //   17: ifnonnull +135 -> 152
    //   20: getstatic 105	kkkkkk/txxtxt:bЪЪЪЪЪЪ042AЪ042A	Ljava/lang/String;
    //   23: ldc_w 257
    //   26: bipush 21
    //   28: iconst_1
    //   29: invokestatic 93	kkkkkk/gguuuu:bккккк043Aкк043A043A	(Ljava/lang/String;CC)Ljava/lang/String;
    //   32: invokestatic 158	kkkkkk/xtxtxt:bии0438и04380438и0438ии	(Ljava/lang/String;Ljava/lang/String;)V
    //   35: return
    //   36: aload_1
    //   37: invokevirtual 262	kkkkkk/tttxxt:bиии04380438и04380438ии	()Ljava/lang/String;
    //   40: invokestatic 268	android/text/TextUtils:isEmpty	(Ljava/lang/CharSequence;)Z
    //   43: ifeq +12 -> 55
    //   46: aload_1
    //   47: aload_0
    //   48: getfield 160	kkkkkk/txxtxt:b042A042A042AЪЪЪ042AЪ042A	Ljava/lang/String;
    //   51: invokevirtual 272	kkkkkk/tttxxt:b04380438043804380438и04380438ии	(Ljava/lang/String;)Lkkkkkk/tttxxt;
    //   54: pop
    //   55: getstatic 71	kkkkkk/txxtxt:bЪЪЪ042AЪЪ042AЪ042A	I
    //   58: istore_2
    //   59: getstatic 79	kkkkkk/txxtxt:b042A042AЪ042AЪЪ042AЪ042A	I
    //   62: istore_3
    //   63: getstatic 71	kkkkkk/txxtxt:bЪЪЪ042AЪЪ042AЪ042A	I
    //   66: istore 4
    //   68: getstatic 77	kkkkkk/txxtxt:bЪ042AЪ042AЪЪ042AЪ042A	I
    //   71: istore 5
    //   73: invokestatic 167	kkkkkk/txxtxt:b0438и0438иии04380438ии	()I
    //   76: istore 6
    //   78: iload_2
    //   79: iload_3
    //   80: iadd
    //   81: iload 4
    //   83: imul
    //   84: iload 5
    //   86: irem
    //   87: iload 6
    //   89: if_icmpeq +47 -> 136
    //   92: invokestatic 85	kkkkkk/txxtxt:bи0438ииии04380438ии	()I
    //   95: putstatic 71	kkkkkk/txxtxt:bЪЪЪ042AЪЪ042AЪ042A	I
    //   98: invokestatic 85	kkkkkk/txxtxt:bи0438ииии04380438ии	()I
    //   101: putstatic 87	kkkkkk/txxtxt:b042AЪЪ042AЪЪ042AЪ042A	I
    //   104: getstatic 71	kkkkkk/txxtxt:bЪЪЪ042AЪЪ042AЪ042A	I
    //   107: getstatic 79	kkkkkk/txxtxt:b042A042AЪ042AЪЪ042AЪ042A	I
    //   110: iadd
    //   111: getstatic 71	kkkkkk/txxtxt:bЪЪЪ042AЪЪ042AЪ042A	I
    //   114: imul
    //   115: getstatic 77	kkkkkk/txxtxt:bЪ042AЪ042AЪЪ042AЪ042A	I
    //   118: irem
    //   119: getstatic 87	kkkkkk/txxtxt:b042AЪЪ042AЪЪ042AЪ042A	I
    //   122: if_icmpeq +14 -> 136
    //   125: invokestatic 85	kkkkkk/txxtxt:bи0438ииии04380438ии	()I
    //   128: putstatic 71	kkkkkk/txxtxt:bЪЪЪ042AЪЪ042AЪ042A	I
    //   131: bipush 7
    //   133: putstatic 87	kkkkkk/txxtxt:b042AЪЪ042AЪЪ042AЪ042A	I
    //   136: aload_0
    //   137: aload_1
    //   138: invokespecial 274	kkkkkk/txxtxt:b0438иииии04380438ии	(Lkkkkkk/tttxxt;)V
    //   141: aload_0
    //   142: invokespecial 276	kkkkkk/txxtxt:bи043804380438ии04380438ии	()V
    //   145: return
    //   146: astore_1
    //   147: aload_1
    //   148: athrow
    //   149: astore_1
    //   150: aload_1
    //   151: athrow
    //   152: aload_0
    //   153: getfield 126	kkkkkk/txxtxt:bЪ042AЪЪЪЪ042AЪ042A	Ljava/lang/String;
    //   156: ifnull +17 -> 173
    //   159: aload_0
    //   160: getfield 160	kkkkkk/txxtxt:b042A042A042AЪЪЪ042AЪ042A	Ljava/lang/String;
    //   163: ifnull +10 -> 173
    //   166: aload_0
    //   167: invokespecial 192	kkkkkk/txxtxt:b0438ии0438ии04380438ии	()Z
    //   170: ifne -134 -> 36
    //   173: getstatic 105	kkkkkk/txxtxt:bЪЪЪЪЪЪ042AЪ042A	Ljava/lang/String;
    //   176: astore 7
    //   178: aload 7
    //   180: ldc_w 278
    //   183: bipush 51
    //   185: sipush 171
    //   188: iconst_1
    //   189: invokestatic 67	kkkkkk/gguuuu:bк043Aккк043Aкк043A043A	(Ljava/lang/String;CCC)Ljava/lang/String;
    //   192: invokestatic 158	kkkkkk/xtxtxt:bии0438и04380438и0438ии	(Ljava/lang/String;Ljava/lang/String;)V
    //   195: aload_0
    //   196: aload_1
    //   197: invokespecial 274	kkkkkk/txxtxt:b0438иииии04380438ии	(Lkkkkkk/tttxxt;)V
    //   200: return
    //   201: astore_1
    //   202: aload_1
    //   203: athrow
    //   204: astore_1
    //   205: aload_1
    //   206: athrow
    // Local variable table:
    //   start	length	slot	name	signature
    //   0	207	0	this	txxtxt
    //   0	207	1	paramTttxxt	tttxxt
    //   58	23	2	i	int
    //   62	19	3	j	int
    //   66	18	4	k	int
    //   71	16	5	m	int
    //   76	14	6	n	int
    //   176	3	7	str	String
    // Exception table:
    //   from	to	target	type
    //   0	16	146	java/lang/Exception
    //   20	35	146	java/lang/Exception
    //   136	145	146	java/lang/Exception
    //   152	173	146	java/lang/Exception
    //   173	178	146	java/lang/Exception
    //   92	104	149	java/lang/Exception
    //   147	149	149	java/lang/Exception
    //   202	204	149	java/lang/Exception
    //   36	55	201	java/lang/Exception
    //   178	200	201	java/lang/Exception
    //   55	78	204	java/lang/Exception
  }
  
  public String b043804380438иии04380438ии()
  {
    if ((bЪЪЪ042AЪЪ042AЪ042A + b042A042AЪ042AЪЪ042AЪ042A) * bЪЪЪ042AЪЪ042AЪ042A % bЪ042AЪ042AЪЪ042AЪ042A != b042AЪЪ042AЪЪ042AЪ042A)
    {
      bЪЪЪ042AЪЪ042AЪ042A = 35;
      b042AЪЪ042AЪЪ042AЪ042A = bи0438ииии04380438ии();
    }
    switch (0)
    {
    case 1: 
    default: 
      for (;;)
      {
        switch (0)
        {
        case 1: 
        default: 
          for (;;)
          {
            switch (1)
            {
            }
          }
        }
        switch (0)
        {
        }
      }
    }
    int i = bЪЪЪ042AЪЪ042AЪ042A;
    switch (i * (b042A042AЪ042AЪЪ042AЪ042A + i) % bЪ042AЪ042AЪЪ042AЪ042A)
    {
    default: 
      bЪЪЪ042AЪЪ042AЪ042A = bи0438ииии04380438ии();
      b042AЪЪ042AЪЪ042AЪ042A = 19;
    }
    return this.b042A042A042AЪЪЪ042AЪ042A;
  }
  
  public void b04380438и0438ии04380438ии(List<tttxxt> paramList, Exception arg2)
  {
    xtxtxt.bии0438и04380438и0438ии(bЪЪЪЪЪЪ042AЪ042A, gguuuu.bк043Aккк043Aкк043A043A("\032\032q !\037#kRx'(&*X- *!'-'`/(78'.-<wj\r12nD97@s77:CxNJ{QMOPH\003WYGJS\t\022PdPS_dZaa.\025", '.', 'ú', '\003') + ??? + gguuuu.bккккк043Aкк043A043A("h", '¿', '\005'));
    synchronized (this.bЪ042A042AЪЪЪ042AЪ042A)
    {
      this.b042AЪ042AЪЪЪ042AЪ042A.addAll(0, paramList);
      return;
    }
  }
  
  /* Error */
  public void b0438и04380438ии04380438ии()
  {
    // Byte code:
    //   0: getstatic 105	kkkkkk/txxtxt:bЪЪЪЪЪЪ042AЪ042A	Ljava/lang/String;
    //   3: astore_2
    //   4: getstatic 71	kkkkkk/txxtxt:bЪЪЪ042AЪЪ042AЪ042A	I
    //   7: getstatic 79	kkkkkk/txxtxt:b042A042AЪ042AЪЪ042AЪ042A	I
    //   10: iadd
    //   11: getstatic 71	kkkkkk/txxtxt:bЪЪЪ042AЪЪ042AЪ042A	I
    //   14: imul
    //   15: getstatic 77	kkkkkk/txxtxt:bЪ042AЪ042AЪЪ042AЪ042A	I
    //   18: irem
    //   19: getstatic 87	kkkkkk/txxtxt:b042AЪЪ042AЪЪ042AЪ042A	I
    //   22: if_icmpeq +14 -> 36
    //   25: invokestatic 85	kkkkkk/txxtxt:bи0438ииии04380438ии	()I
    //   28: putstatic 71	kkkkkk/txxtxt:bЪЪЪ042AЪЪ042AЪ042A	I
    //   31: bipush 42
    //   33: putstatic 87	kkkkkk/txxtxt:b042AЪЪ042AЪЪ042AЪ042A	I
    //   36: aload_2
    //   37: ldc_w 296
    //   40: bipush 9
    //   42: iconst_0
    //   43: invokestatic 93	kkkkkk/gguuuu:bккккк043Aкк043A043A	(Ljava/lang/String;CC)Ljava/lang/String;
    //   46: invokestatic 158	kkkkkk/xtxtxt:bии0438и04380438и0438ии	(Ljava/lang/String;Ljava/lang/String;)V
    //   49: getstatic 71	kkkkkk/txxtxt:bЪЪЪ042AЪЪ042AЪ042A	I
    //   52: istore_1
    //   53: iload_1
    //   54: getstatic 79	kkkkkk/txxtxt:b042A042AЪ042AЪЪ042AЪ042A	I
    //   57: iload_1
    //   58: iadd
    //   59: imul
    //   60: getstatic 77	kkkkkk/txxtxt:bЪ042AЪ042AЪЪ042AЪ042A	I
    //   63: irem
    //   64: tableswitch	default:+20->84, 0:+32->96
    //   84: invokestatic 85	kkkkkk/txxtxt:bи0438ииии04380438ии	()I
    //   87: putstatic 71	kkkkkk/txxtxt:bЪЪЪ042AЪЪ042AЪ042A	I
    //   90: invokestatic 85	kkkkkk/txxtxt:bи0438ииии04380438ии	()I
    //   93: putstatic 87	kkkkkk/txxtxt:b042AЪЪ042AЪЪ042AЪ042A	I
    //   96: return
    //   97: astore_2
    //   98: aload_2
    //   99: athrow
    //   100: astore_2
    //   101: aload_2
    //   102: athrow
    // Local variable table:
    //   start	length	slot	name	signature
    //   0	103	0	this	txxtxt
    //   52	8	1	i	int
    //   3	34	2	str	String
    //   97	2	2	localException1	Exception
    //   100	2	2	localException2	Exception
    // Exception table:
    //   from	to	target	type
    //   0	4	97	java/lang/Exception
    //   36	49	100	java/lang/Exception
  }
  
  public void b0438иии0438и04380438ии(String paramString)
  {
    this.b042A042A042AЪЪЪ042AЪ042A = paramString;
  }
  
  public String bи04380438иии04380438ии()
  {
    switch (0)
    {
    case 1: 
    default: 
      for (;;)
      {
        switch (1)
        {
        }
      }
    }
    switch (1)
    {
    case 0: 
    default: 
      for (;;)
      {
        switch (1)
        {
        }
      }
    }
    int i = bЪЪЪ042AЪЪ042AЪ042A;
    int j = b042A042AЪ042AЪЪ042AЪ042A;
    int k = bЪЪЪ042AЪЪ042AЪ042A;
    switch (k * (b04380438ииии04380438ии() + k) % bЪ042AЪ042AЪЪ042AЪ042A)
    {
    default: 
      bЪЪЪ042AЪЪ042AЪ042A = bи0438ииии04380438ии();
      b042AЪЪ042AЪЪ042AЪ042A = 97;
    }
    if ((i + j) * bЪЪЪ042AЪЪ042AЪ042A % bЪ042AЪ042AЪЪ042AЪ042A != b042AЪЪ042AЪЪ042AЪ042A)
    {
      bЪЪЪ042AЪЪ042AЪ042A = bи0438ииии04380438ии();
      b042AЪЪ042AЪЪ042AЪ042A = bи0438ииии04380438ии();
    }
    return this.bЪ042AЪЪЪЪ042AЪ042A;
  }
  
  public boolean bи0438и0438ии04380438ии()
  {
    this.b042A042AЪЪЪЪ042AЪ042A = xtxxxt.b0438ии04380438043804380438ии().b04380438и04380438043804380438ии(gguuuu.bккккк043Aкк043A043A("\b\013~\001\017{\t\004\031\016\004\027\031\005\033\021\026\017\n\021\037 \036\"\020%\030\")", 'Ê', '\004'), gguuuu.bк043Aккк043Aкк043A043A("[]_[phq]arbpg", ' ', ')', '\001'), 0L);
    boolean bool;
    if (System.currentTimeMillis() - this.b042A042AЪЪЪЪ042AЪ042A > 3600000L) {
      bool = true;
    }
    for (;;)
    {
      if (!bool)
      {
        String str = bЪЪЪЪЪЪ042AЪ042A;
        switch (1)
        {
        case 0: 
        default: 
          for (;;)
          {
            switch (1)
            {
            }
          }
        }
        switch (1)
        {
        case 0: 
        default: 
          for (;;)
          {
            switch (0)
            {
            }
          }
        }
        xtxtxt.bии0438и04380438и0438ии(str, gguuuu.bк043Aккк043Aкк043A043A("auxo)nyur$octt\037conjl\031aj\026aYfe\021dWO[\f\036 \031\030\027\026\025\004PKMLHQ\013{)IxF<;9sGApC4<1k?9h46-,36", '\021', '\036', '\000'));
      }
      return bool;
      int i = bЪЪЪ042AЪЪ042AЪ042A;
      switch (i * (b042A042AЪ042AЪЪ042AЪ042A + i) % bЪ042AЪ042AЪЪ042AЪ042A)
      {
      default: 
        i = bЪЪЪ042AЪЪ042AЪ042A;
        switch (i * (b042A042AЪ042AЪЪ042AЪ042A + i) % bЪ042AЪ042AЪЪ042AЪ042A)
        {
        default: 
          bЪЪЪ042AЪЪ042AЪ042A = bи0438ииии04380438ии();
          b042AЪЪ042AЪЪ042AЪ042A = bи0438ииии04380438ии();
        }
        bЪЪЪ042AЪЪ042AЪ042A = bи0438ииии04380438ии();
        b042AЪЪ042AЪЪ042AЪ042A = bи0438ииии04380438ии();
        bool = false;
        break;
      case 0: 
        bool = false;
      }
    }
  }
  
  /* Error */
  public void bи0438ии0438и04380438ии()
  {
    // Byte code:
    //   0: getstatic 71	kkkkkk/txxtxt:bЪЪЪ042AЪЪ042AЪ042A	I
    //   3: istore_1
    //   4: getstatic 79	kkkkkk/txxtxt:b042A042AЪ042AЪЪ042AЪ042A	I
    //   7: istore_2
    //   8: getstatic 71	kkkkkk/txxtxt:bЪЪЪ042AЪЪ042AЪ042A	I
    //   11: istore_3
    //   12: getstatic 77	kkkkkk/txxtxt:bЪ042AЪ042AЪЪ042AЪ042A	I
    //   15: istore 4
    //   17: getstatic 87	kkkkkk/txxtxt:b042AЪЪ042AЪЪ042AЪ042A	I
    //   20: istore 5
    //   22: iload_1
    //   23: iload_2
    //   24: iadd
    //   25: iload_3
    //   26: imul
    //   27: iload 4
    //   29: irem
    //   30: iload 5
    //   32: if_icmpeq +47 -> 79
    //   35: getstatic 71	kkkkkk/txxtxt:bЪЪЪ042AЪЪ042AЪ042A	I
    //   38: getstatic 79	kkkkkk/txxtxt:b042A042AЪ042AЪЪ042AЪ042A	I
    //   41: iadd
    //   42: getstatic 71	kkkkkk/txxtxt:bЪЪЪ042AЪЪ042AЪ042A	I
    //   45: imul
    //   46: getstatic 77	kkkkkk/txxtxt:bЪ042AЪ042AЪЪ042AЪ042A	I
    //   49: irem
    //   50: getstatic 87	kkkkkk/txxtxt:b042AЪЪ042AЪЪ042AЪ042A	I
    //   53: if_icmpeq +14 -> 67
    //   56: bipush 20
    //   58: putstatic 71	kkkkkk/txxtxt:bЪЪЪ042AЪЪ042AЪ042A	I
    //   61: invokestatic 85	kkkkkk/txxtxt:bи0438ииии04380438ии	()I
    //   64: putstatic 87	kkkkkk/txxtxt:b042AЪЪ042AЪЪ042AЪ042A	I
    //   67: invokestatic 85	kkkkkk/txxtxt:bи0438ииии04380438ии	()I
    //   70: putstatic 71	kkkkkk/txxtxt:bЪЪЪ042AЪЪ042AЪ042A	I
    //   73: invokestatic 85	kkkkkk/txxtxt:bи0438ииии04380438ии	()I
    //   76: putstatic 87	kkkkkk/txxtxt:b042AЪЪ042AЪЪ042AЪ042A	I
    //   79: aload_0
    //   80: invokespecial 276	kkkkkk/txxtxt:bи043804380438ии04380438ии	()V
    //   83: return
    //   84: astore 6
    //   86: aload 6
    //   88: athrow
    //   89: astore 6
    //   91: aload 6
    //   93: athrow
    // Local variable table:
    //   start	length	slot	name	signature
    //   0	94	0	this	txxtxt
    //   3	22	1	i	int
    //   7	18	2	j	int
    //   11	16	3	k	int
    //   15	15	4	m	int
    //   20	13	5	n	int
    //   84	3	6	localException1	Exception
    //   89	3	6	localException2	Exception
    // Exception table:
    //   from	to	target	type
    //   0	22	84	java/lang/Exception
    //   79	83	84	java/lang/Exception
    //   67	79	89	java/lang/Exception
  }
  
  /* Error */
  public void bиии0438ии04380438ии(String paramString1, String paramString2, List<String> paramList)
  {
    // Byte code:
    //   0: aload_0
    //   1: aload_1
    //   2: putfield 160	kkkkkk/txxtxt:b042A042A042AЪЪЪ042AЪ042A	Ljava/lang/String;
    //   5: aload_0
    //   6: aload_2
    //   7: putfield 126	kkkkkk/txxtxt:bЪ042AЪЪЪЪ042AЪ042A	Ljava/lang/String;
    //   10: aload_0
    //   11: aload_3
    //   12: putfield 232	kkkkkk/txxtxt:b042AЪЪЪЪЪ042AЪ042A	Ljava/util/List;
    //   15: aload_0
    //   16: getfield 114	kkkkkk/txxtxt:bЪЪ042AЪЪЪ042AЪ042A	Lkkkkkk/xxtxxt;
    //   19: new 9	kkkkkk/txxtxt$1
    //   22: dup
    //   23: aload_0
    //   24: invokespecial 319	kkkkkk/txxtxt$1:<init>	(Lkkkkkk/txxtxt;)V
    //   27: invokevirtual 323	kkkkkk/xxtxxt:bииии0438043804380438ии	(Lkkkkkk/ttxxxt;)V
    //   30: getstatic 105	kkkkkk/txxtxt:bЪЪЪЪЪЪ042AЪ042A	Ljava/lang/String;
    //   33: astore_1
    //   34: new 142	java/lang/StringBuilder
    //   37: dup
    //   38: invokespecial 143	java/lang/StringBuilder:<init>	()V
    //   41: ldc_w 325
    //   44: bipush 37
    //   46: bipush 40
    //   48: iconst_0
    //   49: invokestatic 67	kkkkkk/gguuuu:bк043Aккк043Aкк043A043A	(Ljava/lang/String;CCC)Ljava/lang/String;
    //   52: invokevirtual 149	java/lang/StringBuilder:append	(Ljava/lang/String;)Ljava/lang/StringBuilder;
    //   55: aload_0
    //   56: getfield 126	kkkkkk/txxtxt:bЪ042AЪЪЪЪ042AЪ042A	Ljava/lang/String;
    //   59: invokevirtual 149	java/lang/StringBuilder:append	(Ljava/lang/String;)Ljava/lang/StringBuilder;
    //   62: ldc_w 327
    //   65: sipush 210
    //   68: bipush 31
    //   70: iconst_2
    //   71: invokestatic 67	kkkkkk/gguuuu:bк043Aккк043Aкк043A043A	(Ljava/lang/String;CCC)Ljava/lang/String;
    //   74: invokevirtual 149	java/lang/StringBuilder:append	(Ljava/lang/String;)Ljava/lang/StringBuilder;
    //   77: astore_2
    //   78: aload_2
    //   79: aload_0
    //   80: getfield 160	kkkkkk/txxtxt:b042A042A042AЪЪЪ042AЪ042A	Ljava/lang/String;
    //   83: invokevirtual 149	java/lang/StringBuilder:append	(Ljava/lang/String;)Ljava/lang/StringBuilder;
    //   86: astore_2
    //   87: ldc_w 329
    //   90: bipush 76
    //   92: iconst_3
    //   93: invokestatic 93	kkkkkk/gguuuu:bккккк043Aкк043A043A	(Ljava/lang/String;CC)Ljava/lang/String;
    //   96: astore_3
    //   97: aload_1
    //   98: aload_2
    //   99: aload_3
    //   100: invokevirtual 149	java/lang/StringBuilder:append	(Ljava/lang/String;)Ljava/lang/StringBuilder;
    //   103: invokevirtual 152	java/lang/StringBuilder:toString	()Ljava/lang/String;
    //   106: invokestatic 158	kkkkkk/xtxtxt:bии0438и04380438и0438ии	(Ljava/lang/String;Ljava/lang/String;)V
    //   109: invokestatic 132	kkkkkk/xtxxxt:b0438ии04380438043804380438ии	()Lkkkkkk/xtxxxt;
    //   112: astore_1
    //   113: ldc_w 331
    //   116: bipush 89
    //   118: bipush 17
    //   120: iconst_2
    //   121: invokestatic 67	kkkkkk/gguuuu:bк043Aккк043Aкк043A043A	(Ljava/lang/String;CCC)Ljava/lang/String;
    //   124: astore_2
    //   125: getstatic 71	kkkkkk/txxtxt:bЪЪЪ042AЪЪ042AЪ042A	I
    //   128: istore 4
    //   130: iload 4
    //   132: getstatic 79	kkkkkk/txxtxt:b042A042AЪ042AЪЪ042AЪ042A	I
    //   135: iload 4
    //   137: iadd
    //   138: imul
    //   139: getstatic 77	kkkkkk/txxtxt:bЪ042AЪ042AЪЪ042AЪ042A	I
    //   142: irem
    //   143: tableswitch	default:+17->160, 0:+29->172
    //   160: invokestatic 85	kkkkkk/txxtxt:bи0438ииии04380438ии	()I
    //   163: putstatic 71	kkkkkk/txxtxt:bЪЪЪ042AЪЪ042AЪ042A	I
    //   166: invokestatic 85	kkkkkk/txxtxt:bи0438ииии04380438ии	()I
    //   169: putstatic 87	kkkkkk/txxtxt:b042AЪЪ042AЪЪ042AЪ042A	I
    //   172: ldc_w 333
    //   175: sipush 184
    //   178: iconst_2
    //   179: invokestatic 93	kkkkkk/gguuuu:bккккк043Aкк043A043A	(Ljava/lang/String;CC)Ljava/lang/String;
    //   182: astore_3
    //   183: getstatic 71	kkkkkk/txxtxt:bЪЪЪ042AЪЪ042AЪ042A	I
    //   186: istore 4
    //   188: iload 4
    //   190: invokestatic 75	kkkkkk/txxtxt:b04380438ииии04380438ии	()I
    //   193: iload 4
    //   195: iadd
    //   196: imul
    //   197: getstatic 77	kkkkkk/txxtxt:bЪ042AЪ042AЪЪ042AЪ042A	I
    //   200: irem
    //   201: tableswitch	default:+19->220, 0:+30->231
    //   220: invokestatic 85	kkkkkk/txxtxt:bи0438ииии04380438ии	()I
    //   223: putstatic 71	kkkkkk/txxtxt:bЪЪЪ042AЪЪ042AЪ042A	I
    //   226: bipush 91
    //   228: putstatic 87	kkkkkk/txxtxt:b042AЪЪ042AЪЪ042AЪ042A	I
    //   231: aload_1
    //   232: aload_2
    //   233: aload_3
    //   234: aload_0
    //   235: getfield 126	kkkkkk/txxtxt:bЪ042AЪЪЪЪ042AЪ042A	Ljava/lang/String;
    //   238: invokevirtual 337	kkkkkk/xtxxxt:b04380438ииииии0438и	(Ljava/lang/String;Ljava/lang/String;Ljava/lang/String;)V
    //   241: invokestatic 132	kkkkkk/xtxxxt:b0438ии04380438043804380438ии	()Lkkkkkk/xtxxxt;
    //   244: astore_1
    //   245: aload_1
    //   246: ldc_w 339
    //   249: sipush 163
    //   252: iconst_3
    //   253: invokestatic 93	kkkkkk/gguuuu:bккккк043Aкк043A043A	(Ljava/lang/String;CC)Ljava/lang/String;
    //   256: ldc_w 341
    //   259: bipush 28
    //   261: sipush 150
    //   264: iconst_1
    //   265: invokestatic 67	kkkkkk/gguuuu:bк043Aккк043Aкк043A043A	(Ljava/lang/String;CCC)Ljava/lang/String;
    //   268: aload_0
    //   269: getfield 160	kkkkkk/txxtxt:b042A042A042AЪЪЪ042AЪ042A	Ljava/lang/String;
    //   272: invokevirtual 337	kkkkkk/xtxxxt:b04380438ииииии0438и	(Ljava/lang/String;Ljava/lang/String;Ljava/lang/String;)V
    //   275: return
    //   276: astore_1
    //   277: aload_1
    //   278: athrow
    //   279: astore_1
    //   280: aload_1
    //   281: athrow
    // Local variable table:
    //   start	length	slot	name	signature
    //   0	282	0	this	txxtxt
    //   0	282	1	paramString1	String
    //   0	282	2	paramString2	String
    //   0	282	3	paramList	List<String>
    //   128	69	4	i	int
    // Exception table:
    //   from	to	target	type
    //   0	78	276	java/lang/Exception
    //   97	113	276	java/lang/Exception
    //   172	183	276	java/lang/Exception
    //   231	245	276	java/lang/Exception
    //   78	97	279	java/lang/Exception
    //   113	125	279	java/lang/Exception
    //   245	275	279	java/lang/Exception
  }
  
  public void bииии0438и04380438ии(String paramString)
  {
    int i = bЪЪЪ042AЪЪ042AЪ042A;
    switch (i * (b042A042AЪ042AЪЪ042AЪ042A + i) % bЪ042AЪ042AЪЪ042AЪ042A)
    {
    default: 
      bЪЪЪ042AЪЪ042AЪ042A = bи0438ииии04380438ии();
      b042AЪЪ042AЪЪ042AЪ042A = bи0438ииии04380438ии();
    }
    switch (1)
    {
    case 0: 
    default: 
      for (;;)
      {
        switch (1)
        {
        }
      }
    }
    if ((bЪЪЪ042AЪЪ042AЪ042A + b042A042AЪ042AЪЪ042AЪ042A) * bЪЪЪ042AЪЪ042AЪ042A % bЪ042AЪ042AЪЪ042AЪ042A != b042AЪЪ042AЪЪ042AЪ042A)
    {
      bЪЪЪ042AЪЪ042AЪ042A = 24;
      b042AЪЪ042AЪЪ042AЪ042A = bи0438ииии04380438ии();
    }
    this.bЪ042AЪЪЪЪ042AЪ042A = paramString;
  }
  
  public void bииииии04380438ии(tttxxt paramTttxxt)
  {
    if (paramTttxxt == null) {
      if ((bЪЪЪ042AЪЪ042AЪ042A + b042A042AЪ042AЪЪ042AЪ042A) * bЪЪЪ042AЪЪ042AЪ042A % bЪ042AЪ042AЪЪ042AЪ042A != b042AЪЪ042AЪЪ042AЪ042A)
      {
        bЪЪЪ042AЪЪ042AЪ042A = bи0438ииии04380438ии();
        b042AЪЪ042AЪЪ042AЪ042A = 20;
      }
    }
    try
    {
      paramTttxxt = bЪЪЪЪЪЪ042AЪ042A;
      str = gguuuu.bк043Aккк043Aкк043A043A("prqYp}|ink?$oqh lcpo\\a^\030`i\025bh^]\036\0172VP\013XX\\\007YJRG\002UO~*LCBIL", 'È', '\'', '\002');
    }
    catch (Exception paramTttxxt)
    {
      String str;
      throw paramTttxxt;
    }
    xtxtxt.bии0438и04380438и0438ии(paramTttxxt, str);
    return;
    try
    {
      boolean bool = TextUtils.isEmpty(paramTttxxt.bиии04380438и04380438ии());
      if ((bool) && (this.b042A042A042AЪЪЪ042AЪ042A != null)) {
        paramTttxxt.b04380438043804380438и04380438ии(this.b042A042A042AЪЪЪ042AЪ042A);
      }
      int i = bЪЪЪ042AЪЪ042AЪ042A;
      switch (i * (b042A042AЪ042AЪЪ042AЪ042A + i) % bЪ042AЪ042AЪЪ042AЪ042A)
      {
      default: 
        bЪЪЪ042AЪЪ042AЪ042A = 97;
        b042AЪЪ042AЪЪ042AЪ042A = bи0438ииии04380438ии();
      }
      b0438иииии04380438ии(paramTttxxt);
      return;
    }
    catch (Exception paramTttxxt)
    {
      throw paramTttxxt;
    }
    switch (1)
    {
    }
    for (;;)
    {
      switch (1)
      {
      }
    }
  }
}
