package kkkkkk;

public final class uguuuu
{
  public static int b042204220422Т0422ТТ0422Т0422 = 0;
  public static final int b04220422ТТ0422ТТ0422Т0422 = 56320;
  public static final int b0422Т0422Т0422ТТ0422Т0422 = 57344;
  public static int b0422ТТ04220422ТТ0422Т0422 = 2;
  public static int bТ04220422Т0422ТТ0422Т0422 = 7;
  public static final int bТ0422ТТ0422ТТ0422Т0422 = 55296;
  public static final int bТТ0422Т0422ТТ0422Т0422 = 56320;
  public static int bТТТ04220422ТТ0422Т0422 = 1;
  public final String b0422042204220422ТТТ0422Т0422;
  private int b0422ТТТ0422ТТ0422Т0422;
  public final int bТТТТ0422ТТ0422Т0422;
  
  public uguuuu(String paramString)
  {
    this.b0422042204220422ТТТ0422Т0422 = paramString;
    this.bТТТТ0422ТТ0422Т0422 = paramString.length();
  }
  
  public static int b043A043Aк043Aкккк043A043A()
  {
    return 1;
  }
  
  public static int b043Aк043A043Aкккк043A043A()
  {
    return 42;
  }
  
  /* Error */
  public int bк043A043A043Aкккк043A043A()
  {
    // Byte code:
    //   0: iconst_0
    //   1: tableswitch	default:+23->24, 0:+50->51, 1:+-1->0
    //   24: iconst_0
    //   25: tableswitch	default:+23->48, 0:+26->51, 1:+-25->0
    //   48: goto -24 -> 24
    //   51: aload_0
    //   52: getfield 31	kkkkkk/uguuuu:b0422042204220422ТТТ0422Т0422	Ljava/lang/String;
    //   55: aload_0
    //   56: getfield 47	kkkkkk/uguuuu:b0422ТТТ0422ТТ0422Т0422	I
    //   59: invokevirtual 51	java/lang/String:charAt	(I)C
    //   62: istore_1
    //   63: getstatic 53	kkkkkk/uguuuu:bТ04220422Т0422ТТ0422Т0422	I
    //   66: getstatic 55	kkkkkk/uguuuu:bТТТ04220422ТТ0422Т0422	I
    //   69: iadd
    //   70: getstatic 53	kkkkkk/uguuuu:bТ04220422Т0422ТТ0422Т0422	I
    //   73: imul
    //   74: getstatic 57	kkkkkk/uguuuu:b0422ТТ04220422ТТ0422Т0422	I
    //   77: irem
    //   78: getstatic 59	kkkkkk/uguuuu:b042204220422Т0422ТТ0422Т0422	I
    //   81: if_icmpeq +45 -> 126
    //   84: invokestatic 61	kkkkkk/uguuuu:b043Aк043A043Aкккк043A043A	()I
    //   87: putstatic 53	kkkkkk/uguuuu:bТ04220422Т0422ТТ0422Т0422	I
    //   90: bipush 77
    //   92: putstatic 59	kkkkkk/uguuuu:b042204220422Т0422ТТ0422Т0422	I
    //   95: getstatic 53	kkkkkk/uguuuu:bТ04220422Т0422ТТ0422Т0422	I
    //   98: getstatic 55	kkkkkk/uguuuu:bТТТ04220422ТТ0422Т0422	I
    //   101: iadd
    //   102: getstatic 53	kkkkkk/uguuuu:bТ04220422Т0422ТТ0422Т0422	I
    //   105: imul
    //   106: getstatic 57	kkkkkk/uguuuu:b0422ТТ04220422ТТ0422Т0422	I
    //   109: irem
    //   110: getstatic 59	kkkkkk/uguuuu:b042204220422Т0422ТТ0422Т0422	I
    //   113: if_icmpeq +13 -> 126
    //   116: bipush 82
    //   118: putstatic 53	kkkkkk/uguuuu:bТ04220422Т0422ТТ0422Т0422	I
    //   121: bipush 30
    //   123: putstatic 59	kkkkkk/uguuuu:b042204220422Т0422ТТ0422Т0422	I
    //   126: aload_0
    //   127: getfield 47	kkkkkk/uguuuu:b0422ТТТ0422ТТ0422Т0422	I
    //   130: istore_2
    //   131: aload_0
    //   132: iload_2
    //   133: iconst_1
    //   134: iadd
    //   135: putfield 47	kkkkkk/uguuuu:b0422ТТТ0422ТТ0422Т0422	I
    //   138: iload_1
    //   139: ldc 62
    //   141: iand
    //   142: ireturn
    //   143: astore_3
    //   144: aload_3
    //   145: athrow
    //   146: astore_3
    //   147: aload_3
    //   148: athrow
    // Local variable table:
    //   start	length	slot	name	signature
    //   0	149	0	this	uguuuu
    //   62	80	1	i	int
    //   130	5	2	j	int
    //   143	2	3	localException1	Exception
    //   146	2	3	localException2	Exception
    // Exception table:
    //   from	to	target	type
    //   51	63	143	java/lang/Exception
    //   131	138	143	java/lang/Exception
    //   126	131	146	java/lang/Exception
  }
  
  /* Error */
  public boolean bкк043A043Aкккк043A043A()
  {
    // Byte code:
    //   0: iconst_1
    //   1: istore_3
    //   2: invokestatic 61	kkkkkk/uguuuu:b043Aк043A043Aкккк043A043A	()I
    //   5: invokestatic 66	kkkkkk/uguuuu:b043A043Aк043Aкккк043A043A	()I
    //   8: iadd
    //   9: invokestatic 61	kkkkkk/uguuuu:b043Aк043A043Aкккк043A043A	()I
    //   12: imul
    //   13: getstatic 57	kkkkkk/uguuuu:b0422ТТ04220422ТТ0422Т0422	I
    //   16: irem
    //   17: getstatic 59	kkkkkk/uguuuu:b042204220422Т0422ТТ0422Т0422	I
    //   20: if_icmpeq +14 -> 34
    //   23: invokestatic 61	kkkkkk/uguuuu:b043Aк043A043Aкккк043A043A	()I
    //   26: putstatic 53	kkkkkk/uguuuu:bТ04220422Т0422ТТ0422Т0422	I
    //   29: bipush 18
    //   31: putstatic 59	kkkkkk/uguuuu:b042204220422Т0422ТТ0422Т0422	I
    //   34: iconst_1
    //   35: tableswitch	default:+21->56, 0:+-1->34, 1:+48->83
    //   56: iconst_1
    //   57: tableswitch	default:+23->80, 0:+-23->34, 1:+26->83
    //   80: goto -24 -> 56
    //   83: aload_0
    //   84: getfield 47	kkkkkk/uguuuu:b0422ТТТ0422ТТ0422Т0422	I
    //   87: istore_1
    //   88: aload_0
    //   89: getfield 39	kkkkkk/uguuuu:bТТТТ0422ТТ0422Т0422	I
    //   92: istore_2
    //   93: iload_1
    //   94: iload_2
    //   95: if_icmpge +5 -> 100
    //   98: iload_3
    //   99: ireturn
    //   100: iconst_0
    //   101: istore_3
    //   102: getstatic 53	kkkkkk/uguuuu:bТ04220422Т0422ТТ0422Т0422	I
    //   105: invokestatic 66	kkkkkk/uguuuu:b043A043Aк043Aкккк043A043A	()I
    //   108: iadd
    //   109: getstatic 53	kkkkkk/uguuuu:bТ04220422Т0422ТТ0422Т0422	I
    //   112: imul
    //   113: getstatic 57	kkkkkk/uguuuu:b0422ТТ04220422ТТ0422Т0422	I
    //   116: irem
    //   117: getstatic 59	kkkkkk/uguuuu:b042204220422Т0422ТТ0422Т0422	I
    //   120: if_icmpeq -22 -> 98
    //   123: invokestatic 61	kkkkkk/uguuuu:b043Aк043A043Aкккк043A043A	()I
    //   126: putstatic 53	kkkkkk/uguuuu:bТ04220422Т0422ТТ0422Т0422	I
    //   129: bipush 13
    //   131: putstatic 59	kkkkkk/uguuuu:b042204220422Т0422ТТ0422Т0422	I
    //   134: iconst_0
    //   135: ireturn
    //   136: astore 4
    //   138: aload 4
    //   140: athrow
    //   141: astore 4
    //   143: aload 4
    //   145: athrow
    // Local variable table:
    //   start	length	slot	name	signature
    //   0	146	0	this	uguuuu
    //   87	9	1	i	int
    //   92	4	2	j	int
    //   1	101	3	bool	boolean
    //   136	3	4	localException1	Exception
    //   141	3	4	localException2	Exception
    // Exception table:
    //   from	to	target	type
    //   88	93	136	java/lang/Exception
    //   83	88	141	java/lang/Exception
  }
}
