package kkkkkk;

public abstract class uguugu
{
  public static final uguugu b042204220422Т0422Т04220422Т0422;
  public static int b04220422Т04220422Т04220422Т0422 = 1;
  public static int b0422ТТ04220422Т04220422Т0422 = 97;
  public static final uguugu bТ04220422Т0422Т04220422Т0422;
  public static int bТ0422Т04220422Т04220422Т0422 = 10;
  public static int bТТ042204220422Т04220422Т0422 = 2;
  public static final uguugu bТТТ04220422Т04220422Т0422;
  
  /* Error */
  static
  {
    // Byte code:
    //   0: new 23	kkkkkk/guuuuu
    //   3: dup
    //   4: invokespecial 26	kkkkkk/guuuuu:<init>	()V
    //   7: astore_1
    //   8: getstatic 28	kkkkkk/uguugu:b0422ТТ04220422Т04220422Т0422	I
    //   11: istore_0
    //   12: iload_0
    //   13: getstatic 30	kkkkkk/uguugu:b04220422Т04220422Т04220422Т0422	I
    //   16: iload_0
    //   17: iadd
    //   18: imul
    //   19: getstatic 32	kkkkkk/uguugu:bТТ042204220422Т04220422Т0422	I
    //   22: irem
    //   23: tableswitch	default:+17->40, 0:+27->50
    //   40: bipush 97
    //   42: putstatic 28	kkkkkk/uguugu:b0422ТТ04220422Т04220422Т0422	I
    //   45: bipush 10
    //   47: putstatic 34	kkkkkk/uguugu:bТ0422Т04220422Т04220422Т0422	I
    //   50: aload_1
    //   51: putstatic 36	kkkkkk/uguugu:bТ04220422Т0422Т04220422Т0422	Lkkkkkk/uguugu;
    //   54: new 38	kkkkkk/afffff
    //   57: dup
    //   58: invokespecial 39	kkkkkk/afffff:<init>	()V
    //   61: astore_1
    //   62: aload_1
    //   63: putstatic 41	kkkkkk/uguugu:b042204220422Т0422Т04220422Т0422	Lkkkkkk/uguugu;
    //   66: new 43	kkkkkk/guuugu
    //   69: dup
    //   70: invokespecial 44	kkkkkk/guuugu:<init>	()V
    //   73: putstatic 46	kkkkkk/uguugu:bТТТ04220422Т04220422Т0422	Lkkkkkk/uguugu;
    //   76: return
    //   77: astore_1
    //   78: aload_1
    //   79: athrow
    //   80: astore_1
    //   81: aload_1
    //   82: athrow
    // Local variable table:
    //   start	length	slot	name	signature
    //   11	8	0	i	int
    //   7	56	1	localObject	Object
    //   77	2	1	localException1	Exception
    //   80	2	1	localException2	Exception
    // Exception table:
    //   from	to	target	type
    //   0	8	77	java/lang/Exception
    //   50	54	77	java/lang/Exception
    //   62	76	77	java/lang/Exception
    //   54	62	80	java/lang/Exception
  }
  
  public uguugu() {}
  
  public static uguugu b043A043A043A043Aк043Aкк043A043A(int paramInt)
  {
    if (paramInt == 0) {
      return b042204220422Т0422Т04220422Т0422;
    }
    if ((bкккк043A043Aкк043A043A() + b04220422Т04220422Т04220422Т0422) * bкккк043A043Aкк043A043A() % bТТ042204220422Т04220422Т0422 != bТ0422Т04220422Т04220422Т0422)
    {
      b0422ТТ04220422Т04220422Т0422 = bкккк043A043Aкк043A043A();
      bТ0422Т04220422Т04220422Т0422 = bкккк043A043Aкк043A043A();
    }
    switch (0)
    {
    case 1: 
    default: 
      for (;;)
      {
        switch (1)
        {
        }
      }
    }
    if ((0xF800 & paramInt) != 0) {
      return bТТТ04220422Т04220422Т0422;
    }
    switch (1)
    {
    case 0: 
    default: 
      for (;;)
      {
        switch (1)
        {
        }
      }
    }
    if ((b0422ТТ04220422Т04220422Т0422 + b04220422Т04220422Т04220422Т0422) * b0422ТТ04220422Т04220422Т0422 % bТТ042204220422Т04220422Т0422 != bТ0422Т04220422Т04220422Т0422)
    {
      b0422ТТ04220422Т04220422Т0422 = bкккк043A043Aкк043A043A();
      bТ0422Т04220422Т04220422Т0422 = 98;
    }
    if ((paramInt & 0x780) != 0) {
      return b042204220422Т0422Т04220422Т0422;
    }
    return bТ04220422Т0422Т04220422Т0422;
  }
  
  public static int bкккк043A043Aкк043A043A()
  {
    return 83;
  }
  
  public abstract int b043Aк043Aккккк043A043A();
  
  public abstract int b043Aккккккк043A043A(int paramInt);
  
  public abstract int bк043A043Aккккк043A043A(int paramInt);
  
  public abstract boolean bк043Aкккккк043A043A(int paramInt);
}
