package kkkkkk;

public enum ulluuu
{
  /* Error */
  static
  {
    // Byte code:
    //   0: new 2	kkkkkk/ulluuu
    //   3: dup
    //   4: ldc 21
    //   6: bipush 93
    //   8: iconst_2
    //   9: invokestatic 27	kkkkkk/gguuuu:bккккк043Aкк043A043A	(Ljava/lang/String;CC)Ljava/lang/String;
    //   12: iconst_0
    //   13: invokespecial 31	kkkkkk/ulluuu:<init>	(Ljava/lang/String;I)V
    //   16: putstatic 33	kkkkkk/ulluuu:FINGERPRINT_OPT_IN	Lkkkkkk/ulluuu;
    //   19: new 2	kkkkkk/ulluuu
    //   22: dup
    //   23: ldc 35
    //   25: sipush 203
    //   28: bipush 98
    //   30: iconst_1
    //   31: invokestatic 39	kkkkkk/gguuuu:bк043Aккк043Aкк043A043A	(Ljava/lang/String;CCC)Ljava/lang/String;
    //   34: iconst_1
    //   35: invokespecial 31	kkkkkk/ulluuu:<init>	(Ljava/lang/String;I)V
    //   38: astore_1
    //   39: invokestatic 43	kkkkkk/ulluuu:b0412ВВ041204120412В041204120412	()I
    //   42: invokestatic 46	kkkkkk/ulluuu:bВВВ041204120412В041204120412	()I
    //   45: iadd
    //   46: invokestatic 43	kkkkkk/ulluuu:b0412ВВ041204120412В041204120412	()I
    //   49: imul
    //   50: invokestatic 49	kkkkkk/ulluuu:b04120412В041204120412В041204120412	()I
    //   53: irem
    //   54: invokestatic 52	kkkkkk/ulluuu:bВ0412В041204120412В041204120412	()I
    //   57: if_icmpeq +3 -> 60
    //   60: aload_1
    //   61: putstatic 54	kkkkkk/ulluuu:DPN	Lkkkkkk/ulluuu;
    //   64: new 2	kkkkkk/ulluuu
    //   67: dup
    //   68: ldc 56
    //   70: sipush 225
    //   73: bipush 80
    //   75: iconst_1
    //   76: invokestatic 39	kkkkkk/gguuuu:bк043Aккк043Aкк043A043A	(Ljava/lang/String;CCC)Ljava/lang/String;
    //   79: iconst_2
    //   80: invokespecial 31	kkkkkk/ulluuu:<init>	(Ljava/lang/String;I)V
    //   83: putstatic 58	kkkkkk/ulluuu:BIG_PROMPT	Lkkkkkk/ulluuu;
    //   86: new 2	kkkkkk/ulluuu
    //   89: dup
    //   90: ldc 60
    //   92: bipush 9
    //   94: iconst_5
    //   95: invokestatic 27	kkkkkk/gguuuu:bккккк043Aкк043A043A	(Ljava/lang/String;CC)Ljava/lang/String;
    //   98: iconst_3
    //   99: invokespecial 31	kkkkkk/ulluuu:<init>	(Ljava/lang/String;I)V
    //   102: astore_1
    //   103: aload_1
    //   104: putstatic 62	kkkkkk/ulluuu:BIG_PROMPT_TAKEOVER	Lkkkkkk/ulluuu;
    //   107: new 2	kkkkkk/ulluuu
    //   110: dup
    //   111: ldc 64
    //   113: sipush 170
    //   116: iconst_2
    //   117: invokestatic 27	kkkkkk/gguuuu:bккккк043Aкк043A043A	(Ljava/lang/String;CC)Ljava/lang/String;
    //   120: iconst_4
    //   121: invokespecial 31	kkkkkk/ulluuu:<init>	(Ljava/lang/String;I)V
    //   124: putstatic 66	kkkkkk/ulluuu:ANALYTICS_CONSENT	Lkkkkkk/ulluuu;
    //   127: invokestatic 43	kkkkkk/ulluuu:b0412ВВ041204120412В041204120412	()I
    //   130: istore_0
    //   131: iload_0
    //   132: invokestatic 46	kkkkkk/ulluuu:bВВВ041204120412В041204120412	()I
    //   135: iload_0
    //   136: iadd
    //   137: imul
    //   138: invokestatic 49	kkkkkk/ulluuu:b04120412В041204120412В041204120412	()I
    //   141: irem
    //   142: tableswitch	default:+18->160, 0:+18->160
    //   160: new 2	kkkkkk/ulluuu
    //   163: dup
    //   164: ldc 68
    //   166: bipush 38
    //   168: iconst_5
    //   169: invokestatic 27	kkkkkk/gguuuu:bккккк043Aкк043A043A	(Ljava/lang/String;CC)Ljava/lang/String;
    //   172: iconst_5
    //   173: invokespecial 31	kkkkkk/ulluuu:<init>	(Ljava/lang/String;I)V
    //   176: putstatic 70	kkkkkk/ulluuu:KYC	Lkkkkkk/ulluuu;
    //   179: new 2	kkkkkk/ulluuu
    //   182: dup
    //   183: ldc 72
    //   185: sipush 179
    //   188: iconst_5
    //   189: invokestatic 27	kkkkkk/gguuuu:bккккк043Aкк043A043A	(Ljava/lang/String;CC)Ljava/lang/String;
    //   192: bipush 6
    //   194: invokespecial 31	kkkkkk/ulluuu:<init>	(Ljava/lang/String;I)V
    //   197: astore_1
    //   198: aload_1
    //   199: putstatic 74	kkkkkk/ulluuu:NONE	Lkkkkkk/ulluuu;
    //   202: bipush 7
    //   204: anewarray 2	kkkkkk/ulluuu
    //   207: dup
    //   208: iconst_0
    //   209: getstatic 33	kkkkkk/ulluuu:FINGERPRINT_OPT_IN	Lkkkkkk/ulluuu;
    //   212: aastore
    //   213: dup
    //   214: iconst_1
    //   215: getstatic 54	kkkkkk/ulluuu:DPN	Lkkkkkk/ulluuu;
    //   218: aastore
    //   219: dup
    //   220: iconst_2
    //   221: getstatic 58	kkkkkk/ulluuu:BIG_PROMPT	Lkkkkkk/ulluuu;
    //   224: aastore
    //   225: dup
    //   226: iconst_3
    //   227: getstatic 62	kkkkkk/ulluuu:BIG_PROMPT_TAKEOVER	Lkkkkkk/ulluuu;
    //   230: aastore
    //   231: dup
    //   232: iconst_4
    //   233: getstatic 66	kkkkkk/ulluuu:ANALYTICS_CONSENT	Lkkkkkk/ulluuu;
    //   236: aastore
    //   237: dup
    //   238: iconst_5
    //   239: getstatic 70	kkkkkk/ulluuu:KYC	Lkkkkkk/ulluuu;
    //   242: aastore
    //   243: dup
    //   244: bipush 6
    //   246: getstatic 74	kkkkkk/ulluuu:NONE	Lkkkkkk/ulluuu;
    //   249: aastore
    //   250: putstatic 76	kkkkkk/ulluuu:$VALUES	[Lkkkkkk/ulluuu;
    //   253: return
    //   254: astore_1
    //   255: aload_1
    //   256: athrow
    //   257: astore_1
    //   258: aload_1
    //   259: athrow
    // Local variable table:
    //   start	length	slot	name	signature
    //   130	8	0	i	int
    //   38	161	1	localUlluuu	ulluuu
    //   254	2	1	localException1	Exception
    //   257	2	1	localException2	Exception
    // Exception table:
    //   from	to	target	type
    //   0	39	254	java/lang/Exception
    //   103	127	254	java/lang/Exception
    //   198	253	254	java/lang/Exception
    //   60	103	257	java/lang/Exception
    //   160	198	257	java/lang/Exception
  }
  
  private ulluuu() {}
  
  public static int b04120412В041204120412В041204120412()
  {
    return 2;
  }
  
  public static int b0412ВВ041204120412В041204120412()
  {
    return 98;
  }
  
  public static int bВ0412В041204120412В041204120412()
  {
    return 0;
  }
  
  /* Error */
  public static ulluuu bВВ0412041204120412В041204120412(String paramString)
  {
    // Byte code:
    //   0: ldc 2
    //   2: aload_0
    //   3: invokestatic 85	java/lang/Enum:valueOf	(Ljava/lang/Class;Ljava/lang/String;)Ljava/lang/Enum;
    //   6: astore_0
    //   7: invokestatic 43	kkkkkk/ulluuu:b0412ВВ041204120412В041204120412	()I
    //   10: istore_1
    //   11: invokestatic 46	kkkkkk/ulluuu:bВВВ041204120412В041204120412	()I
    //   14: istore_2
    //   15: invokestatic 43	kkkkkk/ulluuu:b0412ВВ041204120412В041204120412	()I
    //   18: istore_3
    //   19: invokestatic 49	kkkkkk/ulluuu:b04120412В041204120412В041204120412	()I
    //   22: istore 4
    //   24: invokestatic 52	kkkkkk/ulluuu:bВ0412В041204120412В041204120412	()I
    //   27: istore 5
    //   29: iload_1
    //   30: iload_2
    //   31: iadd
    //   32: iload_3
    //   33: imul
    //   34: iload 4
    //   36: irem
    //   37: iload 5
    //   39: if_icmpeq +24 -> 63
    //   42: invokestatic 43	kkkkkk/ulluuu:b0412ВВ041204120412В041204120412	()I
    //   45: invokestatic 46	kkkkkk/ulluuu:bВВВ041204120412В041204120412	()I
    //   48: iadd
    //   49: invokestatic 43	kkkkkk/ulluuu:b0412ВВ041204120412В041204120412	()I
    //   52: imul
    //   53: invokestatic 49	kkkkkk/ulluuu:b04120412В041204120412В041204120412	()I
    //   56: irem
    //   57: invokestatic 52	kkkkkk/ulluuu:bВ0412В041204120412В041204120412	()I
    //   60: if_icmpeq +3 -> 63
    //   63: aload_0
    //   64: checkcast 2	kkkkkk/ulluuu
    //   67: astore_0
    //   68: aload_0
    //   69: areturn
    //   70: astore_0
    //   71: aload_0
    //   72: athrow
    //   73: astore_0
    //   74: aload_0
    //   75: athrow
    //   76: astore_0
    //   77: aload_0
    //   78: athrow
    //   79: astore_0
    //   80: aload_0
    //   81: athrow
    // Local variable table:
    //   start	length	slot	name	signature
    //   0	82	0	paramString	String
    //   10	22	1	i	int
    //   14	18	2	j	int
    //   18	16	3	k	int
    //   22	15	4	m	int
    //   27	13	5	n	int
    // Exception table:
    //   from	to	target	type
    //   63	68	70	java/lang/Exception
    //   7	29	73	java/lang/Exception
    //   71	73	73	java/lang/Exception
    //   0	7	76	java/lang/Exception
    //   77	79	79	java/lang/Exception
  }
  
  public static int bВВВ041204120412В041204120412()
  {
    return 1;
  }
}
