package kkkkkk;

public class uuyyyy
{
  public static int b042E042E042EЮЮЮ042E042E042E042E = 1;
  public static int b042EЮ042EЮЮЮ042E042E042E042E = 2;
  public static int bЮ042E042EЮЮЮ042E042E042E042E = 0;
  public static int bЮЮ042EЮЮЮ042E042E042E042E = 29;
  
  private uuyyyy() {}
  
  public static int b044A044Aъъ044Aъ044A044Aъъ()
  {
    return 88;
  }
  
  public static int bъ044Aъъ044Aъ044A044Aъъ()
  {
    return 1;
  }
  
  /* Error */
  public static uyyyyy bъъ044Aъ044Aъ044A044Aъъ(android.app.Application paramApplication, uuuuun paramUuuuun, hhhhha paramHhhhha, @android.support.annotation.Nullable fbffff paramFbffff)
  {
    // Byte code:
    //   0: new 28	kkkkkk/wwbbww
    //   3: dup
    //   4: aload_0
    //   5: invokespecial 31	kkkkkk/wwbbww:<init>	(Landroid/content/Context;)V
    //   8: astore 6
    //   10: getstatic 33	kkkkkk/uuyyyy:bЮЮ042EЮЮЮ042E042E042E042E	I
    //   13: getstatic 35	kkkkkk/uuyyyy:b042E042E042EЮЮЮ042E042E042E042E	I
    //   16: iadd
    //   17: getstatic 33	kkkkkk/uuyyyy:bЮЮ042EЮЮЮ042E042E042E042E	I
    //   20: imul
    //   21: getstatic 37	kkkkkk/uuyyyy:b042EЮ042EЮЮЮ042E042E042E042E	I
    //   24: irem
    //   25: getstatic 39	kkkkkk/uuyyyy:bЮ042E042EЮЮЮ042E042E042E042E	I
    //   28: if_icmpeq +13 -> 41
    //   31: iconst_4
    //   32: putstatic 33	kkkkkk/uuyyyy:bЮЮ042EЮЮЮ042E042E042E042E	I
    //   35: invokestatic 41	kkkkkk/uuyyyy:b044A044Aъъ044Aъ044A044Aъъ	()I
    //   38: putstatic 39	kkkkkk/uuyyyy:bЮ042E042EЮЮЮ042E042E042E042E	I
    //   41: invokestatic 47	kkkkkk/yyuyyy:bъ044Aъ044Aъ044A044A044Aъъ	()Lkkkkkk/uyyyyy$yuyyyy;
    //   44: astore 5
    //   46: new 49	kkkkkk/nnunnn
    //   49: dup
    //   50: aload_0
    //   51: aload_1
    //   52: aload 6
    //   54: aload_3
    //   55: invokespecial 52	kkkkkk/nnunnn:<init>	(Landroid/content/Context;Lkkkkkk/uuuuun;Lkkkkkk/iiiicc;Lkkkkkk/fbffff;)V
    //   58: astore_0
    //   59: getstatic 33	kkkkkk/uuyyyy:bЮЮ042EЮЮЮ042E042E042E042E	I
    //   62: istore 4
    //   64: iload 4
    //   66: invokestatic 54	kkkkkk/uuyyyy:bъ044Aъъ044Aъ044A044Aъъ	()I
    //   69: iload 4
    //   71: iadd
    //   72: imul
    //   73: getstatic 37	kkkkkk/uuyyyy:b042EЮ042EЮЮЮ042E042E042E042E	I
    //   76: irem
    //   77: tableswitch	default:+19->96, 0:+29->106
    //   96: bipush 78
    //   98: putstatic 33	kkkkkk/uuyyyy:bЮЮ042EЮЮЮ042E042E042E042E	I
    //   101: bipush 78
    //   103: putstatic 37	kkkkkk/uuyyyy:b042EЮ042EЮЮЮ042E042E042E042E	I
    //   106: aload 5
    //   108: aload_0
    //   109: invokeinterface 60 2 0
    //   114: aload_2
    //   115: invokeinterface 64 2 0
    //   120: invokeinterface 68 1 0
    //   125: astore_0
    //   126: aload_0
    //   127: areturn
    //   128: astore_0
    //   129: aload_0
    //   130: athrow
    //   131: astore_0
    //   132: aload_0
    //   133: athrow
    // Local variable table:
    //   start	length	slot	name	signature
    //   0	134	0	paramApplication	android.app.Application
    //   0	134	1	paramUuuuun	uuuuun
    //   0	134	2	paramHhhhha	hhhhha
    //   0	134	3	paramFbffff	fbffff
    //   62	11	4	i	int
    //   44	63	5	localYuyyyy	uyyyyy.yuyyyy
    //   8	45	6	localWwbbww	wwbbww
    // Exception table:
    //   from	to	target	type
    //   0	10	128	java/lang/Exception
    //   41	59	128	java/lang/Exception
    //   106	126	131	java/lang/Exception
  }
}
