package kkkkkk;

public class vooovv
  extends ooovov
{
  public static int b044904490449044904490449щщщ = 1;
  public static int b0449щ0449044904490449щщщ = 3;
  public static int bщ04490449044904490449щщщ = 0;
  private static final String bщщ0449044904490449щщщ = "%9EC\022<C9\r8572*8(&\0066$,1";
  public static int bщщщщщщ0449щщ = 2;
  
  static
  {
    String str = bщщ0449044904490449щщщ;
    switch (1)
    {
    case 0: 
    default: 
      for (;;)
      {
        switch (0)
        {
        }
      }
    }
    str = gguuuu.bккккк043Aкк043A043A(str, 'ã', '\002');
    int i = bШ0428Ш042804280428Ш0428ШШ();
    int j = b044904490449044904490449щщщ;
    if ((bШ0428Ш042804280428Ш0428ШШ() + b044904490449044904490449щщщ) * bШ0428Ш042804280428Ш0428ШШ() % bщщщщщщ0449щщ != b04280428Ш042804280428Ш0428ШШ())
    {
      b0449щ0449044904490449щщщ = bШ0428Ш042804280428Ш0428ШШ();
      bщ04490449044904490449щщщ = bШ0428Ш042804280428Ш0428ШШ();
    }
    switch (i * (j + i) % b0428ШШ042804280428Ш0428ШШ())
    {
    default: 
      switch (0)
      {
      case 1: 
      default: 
        for (;;)
        {
          switch (1)
          {
          }
        }
      }
      b0449щ0449044904490449щщщ = 46;
      bщ04490449044904490449щщщ = 29;
    }
    bщщ0449044904490449щщщ = str;
  }
  
  public vooovv()
  {
    super(gguuuu.bк043Aккк043Aкк043A043A("w\f\030\026d\017\026\f_\013\b\n\005|\013zxX\tv~\004", '©', 'Í', '\000'));
  }
  
  public static int b04280428Ш042804280428Ш0428ШШ()
  {
    return 0;
  }
  
  public static int b0428ШШ042804280428Ш0428ШШ()
  {
    return 2;
  }
  
  public static int bШ0428Ш042804280428Ш0428ШШ()
  {
    return 82;
  }
  
  /* Error */
  public void b04280428Ш0428Ш0428Ш0428ШШ(vvovvo paramVvovvo)
  {
    // Byte code:
    //   0: aload_1
    //   1: checkcast 62	kkkkkk/rmmmmm
    //   4: astore_1
    //   5: getstatic 40	kkkkkk/vooovv:b0449щ0449044904490449щщщ	I
    //   8: istore_2
    //   9: getstatic 40	kkkkkk/vooovv:b0449щ0449044904490449щщщ	I
    //   12: istore_3
    //   13: iload_3
    //   14: getstatic 33	kkkkkk/vooovv:b044904490449044904490449щщщ	I
    //   17: iload_3
    //   18: iadd
    //   19: imul
    //   20: invokestatic 45	kkkkkk/vooovv:b0428ШШ042804280428Ш0428ШШ	()I
    //   23: irem
    //   24: tableswitch	default:+20->44, 0:+31->55
    //   44: invokestatic 31	kkkkkk/vooovv:bШ0428Ш042804280428Ш0428ШШ	()I
    //   47: putstatic 40	kkkkkk/vooovv:b0449щ0449044904490449щщщ	I
    //   50: bipush 81
    //   52: putstatic 42	kkkkkk/vooovv:bщ04490449044904490449щщщ	I
    //   55: getstatic 33	kkkkkk/vooovv:b044904490449044904490449щщщ	I
    //   58: istore_3
    //   59: getstatic 40	kkkkkk/vooovv:b0449щ0449044904490449щщщ	I
    //   62: istore 4
    //   64: getstatic 35	kkkkkk/vooovv:bщщщщщщ0449щщ	I
    //   67: istore 5
    //   69: getstatic 42	kkkkkk/vooovv:bщ04490449044904490449щщщ	I
    //   72: istore 6
    //   74: iload_2
    //   75: iload_3
    //   76: iadd
    //   77: iload 4
    //   79: imul
    //   80: iload 5
    //   82: irem
    //   83: iload 6
    //   85: if_icmpeq +14 -> 99
    //   88: bipush 24
    //   90: putstatic 40	kkkkkk/vooovv:b0449щ0449044904490449щщщ	I
    //   93: invokestatic 31	kkkkkk/vooovv:bШ0428Ш042804280428Ш0428ШШ	()I
    //   96: putstatic 42	kkkkkk/vooovv:bщ04490449044904490449щщщ	I
    //   99: aload_1
    //   100: aload_0
    //   101: invokevirtual 66	kkkkkk/rmmmmm:bШ04280428ШШШШ0428ШШ	(Lkkkkkk/vooovv;)V
    //   104: return
    //   105: astore_1
    //   106: aload_1
    //   107: athrow
    //   108: astore_1
    //   109: aload_1
    //   110: athrow
    //   111: astore_1
    //   112: aload_1
    //   113: athrow
    //   114: astore_1
    //   115: aload_1
    //   116: athrow
    // Local variable table:
    //   start	length	slot	name	signature
    //   0	117	0	this	vooovv
    //   0	117	1	paramVvovvo	vvovvo
    //   8	69	2	i	int
    //   12	65	3	j	int
    //   62	18	4	k	int
    //   67	16	5	m	int
    //   72	14	6	n	int
    // Exception table:
    //   from	to	target	type
    //   0	5	105	java/lang/Exception
    //   88	99	108	java/lang/Exception
    //   106	108	108	java/lang/Exception
    //   112	114	108	java/lang/Exception
    //   99	104	111	java/lang/Exception
    //   5	9	114	java/lang/Exception
    //   55	74	114	java/lang/Exception
  }
}
