package kkkkkk;

public class vvoovv
  extends ooovov
{
  private static final String b0449044904490449щ0449щщщ = "OqhotrBr`hm";
  public static int b04490449щщ04490449щщщ = 70;
  public static int b0449щ0449щ04490449щщщ = 2;
  public static int bщ04490449щ04490449щщщ = 0;
  public static int bщщ0449щ04490449щщщ = 1;
  private vvooov b0449щщщ04490449щщщ;
  private boolean bщ0449щщ04490449щщщ;
  private oovovv bщщщщ04490449щщщ = null;
  
  static
  {
    throw new Runtime("d2j fail translate: java.lang.IndexOutOfBoundsException: fromIndex < 0: -1\n\tat java.util.BitSet.nextSetBit(BitSet.java:712)\n\tat com.googlecode.dex2jar.ir.ts.array.FillArrayTransformer.makeSureAllElementAreAssigned(FillArrayTransformer.java:505)\n\tat com.googlecode.dex2jar.ir.ts.array.FillArrayTransformer.transformReportChanged(FillArrayTransformer.java:123)\n\tat com.googlecode.dex2jar.ir.ts.StatedTransformer.transform(StatedTransformer.java:10)\n\tat com.googlecode.d2j.dex.Dex2jar$2.optimize(Dex2jar.java:149)\n\tat com.googlecode.d2j.dex.Dex2Asm.convertCode(Dex2Asm.java:414)\n\tat com.googlecode.d2j.dex.ExDex2Asm.convertCode(ExDex2Asm.java:42)\n\tat com.googlecode.d2j.dex.Dex2jar$2.convertCode(Dex2jar.java:128)\n\tat com.googlecode.d2j.dex.Dex2Asm.convertMethod(Dex2Asm.java:509)\n\tat com.googlecode.d2j.dex.Dex2Asm.convertClass(Dex2Asm.java:406)\n\tat com.googlecode.d2j.dex.Dex2Asm.convertDex(Dex2Asm.java:422)\n\tat com.googlecode.d2j.dex.Dex2jar.doTranslate(Dex2jar.java:172)\n\tat com.googlecode.d2j.dex.Dex2jar.to(Dex2jar.java:272)\n\tat com.googlecode.dex2jar.tools.Dex2jarCmd.doCommandLine(Dex2jarCmd.java:108)\n\tat com.googlecode.dex2jar.tools.BaseCmd.doMain(BaseCmd.java:288)\n\tat com.googlecode.dex2jar.tools.Dex2jarCmd.main(Dex2jarCmd.java:32)\n");
  }
  
  public vvoovv(vvooov paramVvooov)
  {
    super(gguuuu.bк043Aккк043Aкк043A043A("p\023\n\021\026\024c\024\002\n\017", '¾', '', '\002'));
    this.b0449щщщ04490449щщщ = paramVvooov;
  }
  
  public static int b0428042804280428Ш0428Ш0428ШШ()
  {
    return 1;
  }
  
  public static int b0428ШШШ04280428Ш0428ШШ()
  {
    return 0;
  }
  
  public static int bШШШШ04280428Ш0428ШШ()
  {
    return 31;
  }
  
  public void b04280428Ш0428Ш0428Ш0428ШШ(vvovvo paramVvovvo)
  {
    try
    {
      paramVvovvo = (rmmmmm)paramVvovvo;
      if ((b04490449щщ04490449щщщ + bщщ0449щ04490449щщщ) * b04490449щщ04490449щщщ % b0449щ0449щ04490449щщщ != b0428ШШШ04280428Ш0428ШШ())
      {
        b04490449щщ04490449щщщ = 23;
        bщщ0449щ04490449щщщ = bШШШШ04280428Ш0428ШШ();
        if ((b04490449щщ04490449щщщ + bщщ0449щ04490449щщщ) * b04490449щщ04490449щщщ % b0449щ0449щ04490449щщщ != bщ04490449щ04490449щщщ)
        {
          b04490449щщ04490449щщщ = 81;
          bщ04490449щ04490449щщщ = bШШШШ04280428Ш0428ШШ();
        }
      }
      paramVvovvo.bШШ0428ШШШШ0428ШШ(this);
      return;
    }
    catch (Exception paramVvovvo)
    {
      throw paramVvovvo;
    }
  }
  
  public vvooov b04280428ШШ04280428Ш0428ШШ()
  {
    int i = b04490449щщ04490449щщщ;
    switch (i * (b0428042804280428Ш0428Ш0428ШШ() + i) % b0449щ0449щ04490449щщщ)
    {
    default: 
      if ((b04490449щщ04490449щщщ + bщщ0449щ04490449щщщ) * b04490449щщ04490449щщщ % b0449щ0449щ04490449щщщ != bщ04490449щ04490449щщщ)
      {
        b04490449щщ04490449щщщ = 3;
        bщ04490449щ04490449щщщ = bШШШШ04280428Ш0428ШШ();
      }
      b04490449щщ04490449щщщ = 82;
      bщ04490449щ04490449щщщ = 29;
    }
    return this.b0449щщщ04490449щщщ;
  }
  
  /* Error */
  public void b0428Ш0428Ш04280428Ш0428ШШ(boolean paramBoolean)
  {
    // Byte code:
    //   0: getstatic 62	kkkkkk/vvoovv:b04490449щщ04490449щщщ	I
    //   3: istore_2
    //   4: invokestatic 80	kkkkkk/vvoovv:b0428042804280428Ш0428Ш0428ШШ	()I
    //   7: istore_3
    //   8: getstatic 66	kkkkkk/vvoovv:b0449щ0449щ04490449щщщ	I
    //   11: istore 4
    //   13: getstatic 62	kkkkkk/vvoovv:b04490449щщ04490449щщщ	I
    //   16: getstatic 64	kkkkkk/vvoovv:bщщ0449щ04490449щщщ	I
    //   19: iadd
    //   20: getstatic 62	kkkkkk/vvoovv:b04490449щщ04490449щщщ	I
    //   23: imul
    //   24: getstatic 66	kkkkkk/vvoovv:b0449щ0449щ04490449щщщ	I
    //   27: irem
    //   28: getstatic 72	kkkkkk/vvoovv:bщ04490449щ04490449щщщ	I
    //   31: if_icmpeq +15 -> 46
    //   34: invokestatic 70	kkkkkk/vvoovv:bШШШШ04280428Ш0428ШШ	()I
    //   37: putstatic 62	kkkkkk/vvoovv:b04490449щщ04490449щщщ	I
    //   40: invokestatic 70	kkkkkk/vvoovv:bШШШШ04280428Ш0428ШШ	()I
    //   43: putstatic 72	kkkkkk/vvoovv:bщ04490449щ04490449щщщ	I
    //   46: iload_2
    //   47: iload_3
    //   48: iload_2
    //   49: iadd
    //   50: imul
    //   51: iload 4
    //   53: irem
    //   54: tableswitch	default:+18->72, 0:+29->83
    //   72: bipush 55
    //   74: putstatic 62	kkkkkk/vvoovv:b04490449щщ04490449щщщ	I
    //   77: invokestatic 70	kkkkkk/vvoovv:bШШШШ04280428Ш0428ШШ	()I
    //   80: putstatic 72	kkkkkk/vvoovv:bщ04490449щ04490449щщщ	I
    //   83: aload_0
    //   84: iload_1
    //   85: putfield 84	kkkkkk/vvoovv:bщ0449щщ04490449щщщ	Z
    //   88: return
    //   89: astore 5
    //   91: aload 5
    //   93: athrow
    //   94: astore 5
    //   96: aload 5
    //   98: athrow
    //   99: astore 5
    //   101: aload 5
    //   103: athrow
    // Local variable table:
    //   start	length	slot	name	signature
    //   0	104	0	this	vvoovv
    //   0	104	1	paramBoolean	boolean
    //   3	48	2	i	int
    //   7	43	3	j	int
    //   11	43	4	k	int
    //   89	3	5	localException1	Exception
    //   94	3	5	localException2	Exception
    //   99	3	5	localException3	Exception
    // Exception table:
    //   from	to	target	type
    //   83	88	89	java/lang/Exception
    //   0	13	94	java/lang/Exception
    //   91	94	94	java/lang/Exception
    //   72	83	99	java/lang/Exception
  }
  
  public boolean bШ04280428Ш04280428Ш0428ШШ()
  {
    throw new Runtime("d2j fail translate: java.lang.IndexOutOfBoundsException: fromIndex < 0: -1\n\tat java.util.BitSet.nextSetBit(BitSet.java:712)\n\tat com.googlecode.dex2jar.ir.ts.array.FillArrayTransformer.makeSureAllElementAreAssigned(FillArrayTransformer.java:505)\n\tat com.googlecode.dex2jar.ir.ts.array.FillArrayTransformer.transformReportChanged(FillArrayTransformer.java:123)\n\tat com.googlecode.dex2jar.ir.ts.StatedTransformer.transform(StatedTransformer.java:10)\n\tat com.googlecode.d2j.dex.Dex2jar$2.optimize(Dex2jar.java:149)\n\tat com.googlecode.d2j.dex.Dex2Asm.convertCode(Dex2Asm.java:414)\n\tat com.googlecode.d2j.dex.ExDex2Asm.convertCode(ExDex2Asm.java:42)\n\tat com.googlecode.d2j.dex.Dex2jar$2.convertCode(Dex2jar.java:128)\n\tat com.googlecode.d2j.dex.Dex2Asm.convertMethod(Dex2Asm.java:509)\n\tat com.googlecode.d2j.dex.Dex2Asm.convertClass(Dex2Asm.java:406)\n\tat com.googlecode.d2j.dex.Dex2Asm.convertDex(Dex2Asm.java:422)\n\tat com.googlecode.d2j.dex.Dex2jar.doTranslate(Dex2jar.java:172)\n\tat com.googlecode.d2j.dex.Dex2jar.to(Dex2jar.java:272)\n\tat com.googlecode.dex2jar.tools.Dex2jarCmd.doCommandLine(Dex2jarCmd.java:108)\n\tat com.googlecode.dex2jar.tools.BaseCmd.doMain(BaseCmd.java:288)\n\tat com.googlecode.dex2jar.tools.Dex2jarCmd.main(Dex2jarCmd.java:32)\n");
  }
  
  public oovovv bШ0428ШШ04280428Ш0428ШШ()
  {
    int i = b04490449щщ04490449щщщ;
    switch (i * (bщщ0449щ04490449щщщ + i) % b0449щ0449щ04490449щщщ)
    {
    default: 
      i = b04490449щщ04490449щщщ;
      switch (i * (bщщ0449щ04490449щщщ + i) % b0449щ0449щ04490449щщщ)
      {
      default: 
        b04490449щщ04490449щщщ = bШШШШ04280428Ш0428ШШ();
        bщ04490449щ04490449щщщ = bШШШШ04280428Ш0428ШШ();
      }
      b04490449щщ04490449щщщ = bШШШШ04280428Ш0428ШШ();
      bщ04490449щ04490449щщщ = bШШШШ04280428Ш0428ШШ();
    }
    try
    {
      oovovv localOovovv = this.bщщщщ04490449щщщ;
      return localOovovv;
    }
    catch (Exception localException)
    {
      throw localException;
    }
  }
  
  public void bШШ0428Ш04280428Ш0428ШШ(oovovv paramOovovv)
  {
    throw new Runtime("d2j fail translate: java.lang.IndexOutOfBoundsException: fromIndex < 0: -1\n\tat java.util.BitSet.nextSetBit(BitSet.java:712)\n\tat com.googlecode.dex2jar.ir.ts.array.FillArrayTransformer.makeSureAllElementAreAssigned(FillArrayTransformer.java:505)\n\tat com.googlecode.dex2jar.ir.ts.array.FillArrayTransformer.transformReportChanged(FillArrayTransformer.java:123)\n\tat com.googlecode.dex2jar.ir.ts.StatedTransformer.transform(StatedTransformer.java:10)\n\tat com.googlecode.d2j.dex.Dex2jar$2.optimize(Dex2jar.java:149)\n\tat com.googlecode.d2j.dex.Dex2Asm.convertCode(Dex2Asm.java:414)\n\tat com.googlecode.d2j.dex.ExDex2Asm.convertCode(ExDex2Asm.java:42)\n\tat com.googlecode.d2j.dex.Dex2jar$2.convertCode(Dex2jar.java:128)\n\tat com.googlecode.d2j.dex.Dex2Asm.convertMethod(Dex2Asm.java:509)\n\tat com.googlecode.d2j.dex.Dex2Asm.convertClass(Dex2Asm.java:406)\n\tat com.googlecode.d2j.dex.Dex2Asm.convertDex(Dex2Asm.java:422)\n\tat com.googlecode.d2j.dex.Dex2jar.doTranslate(Dex2jar.java:172)\n\tat com.googlecode.d2j.dex.Dex2jar.to(Dex2jar.java:272)\n\tat com.googlecode.dex2jar.tools.Dex2jarCmd.doCommandLine(Dex2jarCmd.java:108)\n\tat com.googlecode.dex2jar.tools.BaseCmd.doMain(BaseCmd.java:288)\n\tat com.googlecode.dex2jar.tools.Dex2jarCmd.main(Dex2jarCmd.java:32)\n");
  }
}
