package kkkkkk;

import android.annotation.SuppressLint;
import android.support.annotation.Nullable;
import android.support.v4.view.ViewCompat;
import android.view.View;
import java.util.regex.Matcher;
import java.util.regex.Pattern;

public class wbbwww
{
  public static int b041A041A041A041AККК041AКК = 2;
  public static int b041AК041A041AККК041AКК = 0;
  public static int bК041A041A041AККК041AКК = 1;
  private static final Pattern bКК041A041AККК041AКК;
  public static int bКККК041AКК041AКК = 6;
  
  static
  {
    String str = gguuuu.bк043Aккк043Aкк043A043A("\002\t\037X\037", '', 'Ã', '\000');
    if ((b0418И0418041804180418И0418И0418() + bК041A041A041AККК041AКК) * b0418И0418041804180418И0418И0418() % b041A041A041A041AККК041AКК != b041AК041A041AККК041AКК) {
      b041AК041A041AККК041AКК = b0418И0418041804180418И0418И0418();
    }
    switch (0)
    {
    case 1: 
    default: 
      for (;;)
      {
        switch (1)
        {
        case 0: 
        default: 
          for (;;)
          {
            switch (0)
            {
            }
          }
        }
        if ((bКККК041AКК041AКК + bК041A041A041AККК041AКК) * bКККК041AКК041AКК % bИИ0418041804180418И0418И0418() != b041AК041A041AККК041AКК)
        {
          bКККК041AКК041AКК = 29;
          b041AК041A041AККК041AКК = 42;
        }
        switch (0)
        {
        }
      }
    }
    bКК041A041AККК041AКК = Pattern.compile(str);
  }
  
  @ooiiio
  private wbbwww()
  {
    throw new AssertionError(gguuuu.bк043Aккк043Aкк043A043A("~!R\035#)+\031'\035 /\\\037+,09((", '{', '4', '\003'));
  }
  
  @SuppressLint({"DefaultLocale"})
  @Nullable
  public static String b041804180418041804180418И0418И0418(@Nullable String paramString)
  {
    if (paramString == null)
    {
      if ((bКККК041AКК041AКК + bК041A041A041AККК041AКК) * bКККК041AКК041AКК % b041A041A041A041AККК041AКК != b041AК041A041AККК041AКК)
      {
        bКККК041AКК041AКК = b0418И0418041804180418И0418И0418();
        b041AК041A041AККК041AКК = 51;
      }
      return paramString;
    }
    if (bКК041A041AККК041AКК.matcher(paramString).matches()) {}
    for (;;)
    {
      String str = gguuuu.bк043Aккк043Aкк043A043A("\017^\032\r\023b\036\021\027f", 'ø', 'o', '\003');
      if ((bКККК041AКК041AКК + bК041A041A041AККК041AКК) * bКККК041AКК041AКК % b041A041A041A041AККК041AКК != b041AК041A041AККК041AКК)
      {
        bКККК041AКК041AКК = b0418И0418041804180418И0418И0418();
        b041AК041A041AККК041AКК = b0418И0418041804180418И0418И0418();
      }
      paramString = String.format(str, new Object[] { paramString.substring(0, 2), paramString.substring(2, 4), paramString.substring(4, 6) });
      switch (1)
      {
      case 0: 
      default: 
        for (;;)
        {
          switch (1)
          {
          }
        }
      }
      return b04180418ИИИИ04180418И0418(paramString);
      paramString = paramString.replaceAll(gguuuu.bккккк043Aкк043A043A("Z", 'Õ', '\004'), "");
    }
  }
  
  /* Error */
  public static String b04180418ИИИИ04180418И0418(String paramString)
  {
    // Byte code:
    //   0: aconst_null
    //   1: astore_2
    //   2: iconst_2
    //   3: istore_1
    //   4: aload_0
    //   5: ifnonnull +52 -> 57
    //   8: aload_2
    //   9: astore_0
    //   10: invokestatic 29	kkkkkk/wbbwww:b0418И0418041804180418И0418И0418	()I
    //   13: istore_1
    //   14: iload_1
    //   15: getstatic 31	kkkkkk/wbbwww:bК041A041A041AККК041AКК	I
    //   18: iload_1
    //   19: iadd
    //   20: imul
    //   21: getstatic 33	kkkkkk/wbbwww:b041A041A041A041AККК041AКК	I
    //   24: irem
    //   25: tableswitch	default:+19->44, 0:+30->55
    //   44: invokestatic 29	kkkkkk/wbbwww:b0418И0418041804180418И0418И0418	()I
    //   47: putstatic 37	kkkkkk/wbbwww:bКККК041AКК041AКК	I
    //   50: bipush 14
    //   52: putstatic 35	kkkkkk/wbbwww:b041AК041A041AККК041AКК	I
    //   55: aload_0
    //   56: areturn
    //   57: ldc 109
    //   59: bipush 108
    //   61: iconst_0
    //   62: invokestatic 98	kkkkkk/gguuuu:bккккк043Aкк043A043A	(Ljava/lang/String;CC)Ljava/lang/String;
    //   65: astore_2
    //   66: aload_0
    //   67: aload_2
    //   68: ldc 111
    //   70: sipush 166
    //   73: iconst_1
    //   74: invokestatic 98	kkkkkk/gguuuu:bккккк043Aкк043A043A	(Ljava/lang/String;CC)Ljava/lang/String;
    //   77: invokevirtual 104	java/lang/String:replaceAll	(Ljava/lang/String;Ljava/lang/String;)Ljava/lang/String;
    //   80: astore_0
    //   81: new 113	java/lang/NullPointerException
    //   84: dup
    //   85: invokespecial 114	java/lang/NullPointerException:<init>	()V
    //   88: athrow
    //   89: astore_2
    //   90: iconst_1
    //   91: tableswitch	default:+21->112, 0:+-1->90, 1:+48->139
    //   112: iconst_1
    //   113: tableswitch	default:+23->136, 0:+-23->90, 1:+26->139
    //   136: goto -24 -> 112
    //   139: invokestatic 29	kkkkkk/wbbwww:b0418И0418041804180418И0418И0418	()I
    //   142: putstatic 37	kkkkkk/wbbwww:bКККК041AКК041AКК	I
    //   145: iload_1
    //   146: iconst_0
    //   147: idiv
    //   148: istore_1
    //   149: goto -4 -> 145
    //   152: astore_0
    //   153: aload_0
    //   154: athrow
    //   155: astore_0
    //   156: aload_0
    //   157: athrow
    //   158: astore_2
    //   159: invokestatic 29	kkkkkk/wbbwww:b0418И0418041804180418И0418И0418	()I
    //   162: putstatic 37	kkkkkk/wbbwww:bКККК041AКК041AКК	I
    //   165: goto -155 -> 10
    // Local variable table:
    //   start	length	slot	name	signature
    //   0	168	0	paramString	String
    //   3	146	1	i	int
    //   1	67	2	str	String
    //   89	1	2	localException1	Exception
    //   158	1	2	localException2	Exception
    // Exception table:
    //   from	to	target	type
    //   81	89	89	java/lang/Exception
    //   66	81	152	java/lang/Exception
    //   57	66	155	java/lang/Exception
    //   145	149	158	java/lang/Exception
  }
  
  public static int b0418И0418041804180418И0418И0418()
  {
    return 91;
  }
  
  public static void b0418ИИИИИ04180418И0418(View paramView)
  {
    switch (1)
    {
    case 0: 
    default: 
      for (;;)
      {
        switch (0)
        {
        }
      }
    }
    if ((bКККК041AКК041AКК + bК041A041A041AККК041AКК) * bКККК041AКК041AКК % b041A041A041A041AККК041AКК != b041AК041A041AККК041AКК)
    {
      switch (1)
      {
      case 0: 
      default: 
        for (;;)
        {
          switch (0)
          {
          }
        }
      }
      bКККК041AКК041AКК = b0418И0418041804180418И0418И0418();
      b041AК041A041AККК041AКК = 6;
      if ((bКККК041AКК041AКК + bК041A041A041AККК041AКК) * bКККК041AКК041AКК % b041A041A041A041AККК041AКК != b041AК041A041AККК041AКК)
      {
        bКККК041AКК041AКК = b0418И0418041804180418И0418И0418();
        b041AК041A041AККК041AКК = 28;
      }
    }
    ViewCompat.setAccessibilityDelegate(paramView, new wbbwww.2());
  }
  
  public static String bИ04180418041804180418И0418И0418(String paramString)
  {
    if ((bКККК041AКК041AКК + bК041A041A041AККК041AКК) * bКККК041AКК041AКК % b041A041A041A041AККК041AКК != b041AК041A041AККК041AКК)
    {
      bКККК041AКК041AКК = b0418И0418041804180418И0418И0418();
      b041AК041A041AККК041AКК = 90;
    }
    if ((bКККК041AКК041AКК + bК041A041A041AККК041AКК) * bКККК041AКК041AКК % b041A041A041A041AККК041AКК != b041AК041A041AККК041AКК)
    {
      bКККК041AКК041AКК = 58;
      b041AК041A041AККК041AКК = b0418И0418041804180418И0418И0418();
    }
    return paramString.replace(gguuuu.bк043Aккк043Aкк043A043A("!", 'n', 'R', '\003'), gguuuu.bккккк043Aкк043A043A("\026", 'z', '\004'));
  }
  
  public static void bИ0418ИИИИ04180418И0418(View paramView)
  {
    wbbwww.1 local1 = new wbbwww.1();
    int i = bКККК041AКК041AКК;
    switch (i * (bК041A041A041AККК041AКК + i) % bИИ0418041804180418И0418И0418())
    {
    default: 
      bКККК041AКК041AКК = 42;
      b041AК041A041AККК041AКК = b0418И0418041804180418И0418И0418();
    }
    ViewCompat.setAccessibilityDelegate(paramView, local1);
    if ((b0418И0418041804180418И0418И0418() + bК041A041A041AККК041AКК) * b0418И0418041804180418И0418И0418() % bИИ0418041804180418И0418И0418() != b041AК041A041AККК041AКК)
    {
      bКККК041AКК041AКК = b0418И0418041804180418И0418И0418();
      b041AК041A041AККК041AКК = 45;
    }
  }
  
  public static int bИИ0418041804180418И0418И0418()
  {
    return 2;
  }
  
  /* Error */
  public static void bИИИИИИ04180418И0418(@android.support.annotation.NonNull View paramView, @android.support.annotation.NonNull String paramString)
  {
    // Byte code:
    //   0: new 113	java/lang/NullPointerException
    //   3: dup
    //   4: invokespecial 114	java/lang/NullPointerException:<init>	()V
    //   7: athrow
    //   8: astore_2
    //   9: invokestatic 29	kkkkkk/wbbwww:b0418И0418041804180418И0418И0418	()I
    //   12: putstatic 37	kkkkkk/wbbwww:bКККК041AКК041AКК	I
    //   15: new 143	kkkkkk/wbbwww$3
    //   18: dup
    //   19: aload_1
    //   20: invokespecial 146	kkkkkk/wbbwww$3:<init>	(Ljava/lang/String;)V
    //   23: astore_1
    //   24: aload_0
    //   25: aload_1
    //   26: invokestatic 125	android/support/v4/view/ViewCompat:setAccessibilityDelegate	(Landroid/view/View;Landroid/support/v4/view/AccessibilityDelegateCompat;)V
    //   29: return
    //   30: astore_0
    //   31: aload_0
    //   32: athrow
    //   33: astore_0
    //   34: aload_0
    //   35: athrow
    //   36: astore_0
    //   37: aload_0
    //   38: athrow
    // Local variable table:
    //   start	length	slot	name	signature
    //   0	39	0	paramView	View
    //   0	39	1	paramString	String
    //   8	1	2	localException	Exception
    // Exception table:
    //   from	to	target	type
    //   0	8	8	java/lang/Exception
    //   24	29	30	java/lang/Exception
    //   9	15	33	java/lang/Exception
    //   31	33	33	java/lang/Exception
    //   37	39	33	java/lang/Exception
    //   15	24	36	java/lang/Exception
  }
}
