package kkkkkk;

import java.lang.annotation.Annotation;
import java.lang.annotation.Retention;
import java.lang.annotation.RetentionPolicy;

public class wbwwww
{
  public static int b041A041A041A041A041AКК041AКК = 1;
  private static final String b041AК041A041A041AКК041AКК = "R";
  public static int b041AКККК041AК041AКК = bИИ0418ИИИ04180418И0418();
  public static int bК041A041A041A041AКК041AКК = bИИ0418ИИИ04180418И0418();
  private static final String bКК041A041A041AКК041AКК = "(";
  public static int bККККК041AК041AКК = 2;
  
  /* Error */
  static
  {
    // Byte code:
    //   0: getstatic 29	kkkkkk/wbwwww:bКК041A041A041AКК041AКК	Ljava/lang/String;
    //   3: astore_3
    //   4: getstatic 31	kkkkkk/wbwwww:b041AКККК041AК041AКК	I
    //   7: getstatic 33	kkkkkk/wbwwww:b041A041A041A041A041AКК041AКК	I
    //   10: iadd
    //   11: getstatic 31	kkkkkk/wbwwww:b041AКККК041AК041AКК	I
    //   14: imul
    //   15: getstatic 35	kkkkkk/wbwwww:bККККК041AК041AКК	I
    //   18: irem
    //   19: getstatic 37	kkkkkk/wbwwww:bК041A041A041A041AКК041AКК	I
    //   22: if_icmpeq +14 -> 36
    //   25: invokestatic 41	kkkkkk/wbwwww:bИИ0418ИИИ04180418И0418	()I
    //   28: putstatic 31	kkkkkk/wbwwww:b041AКККК041AК041AКК	I
    //   31: bipush 41
    //   33: putstatic 37	kkkkkk/wbwwww:bК041A041A041A041AКК041AКК	I
    //   36: aload_3
    //   37: iconst_4
    //   38: iconst_4
    //   39: invokestatic 47	kkkkkk/gguuuu:bккккк043Aкк043A043A	(Ljava/lang/String;CC)Ljava/lang/String;
    //   42: putstatic 29	kkkkkk/wbwwww:bКК041A041A041AКК041AКК	Ljava/lang/String;
    //   45: getstatic 31	kkkkkk/wbwwww:b041AКККК041AК041AКК	I
    //   48: istore_0
    //   49: getstatic 33	kkkkkk/wbwwww:b041A041A041A041A041AКК041AКК	I
    //   52: istore_1
    //   53: getstatic 31	kkkkkk/wbwwww:b041AКККК041AК041AКК	I
    //   56: istore_2
    //   57: iconst_1
    //   58: tableswitch	default:+22->80, 0:+-1->57, 1:+49->107
    //   80: iconst_1
    //   81: tableswitch	default:+23->104, 0:+-24->57, 1:+26->107
    //   104: goto -24 -> 80
    //   107: iload_0
    //   108: iload_1
    //   109: iadd
    //   110: iload_2
    //   111: imul
    //   112: getstatic 35	kkkkkk/wbwwww:bККККК041AК041AКК	I
    //   115: irem
    //   116: getstatic 37	kkkkkk/wbwwww:bК041A041A041A041AКК041AКК	I
    //   119: if_icmpeq +15 -> 134
    //   122: invokestatic 41	kkkkkk/wbwwww:bИИ0418ИИИ04180418И0418	()I
    //   125: putstatic 31	kkkkkk/wbwwww:b041AКККК041AК041AКК	I
    //   128: invokestatic 41	kkkkkk/wbwwww:bИИ0418ИИИ04180418И0418	()I
    //   131: putstatic 37	kkkkkk/wbwwww:bК041A041A041A041AКК041AКК	I
    //   134: getstatic 49	kkkkkk/wbwwww:b041AК041A041A041AКК041AКК	Ljava/lang/String;
    //   137: astore_3
    //   138: aload_3
    //   139: sipush 151
    //   142: iconst_1
    //   143: invokestatic 47	kkkkkk/gguuuu:bккккк043Aкк043A043A	(Ljava/lang/String;CC)Ljava/lang/String;
    //   146: putstatic 49	kkkkkk/wbwwww:b041AК041A041A041AКК041AКК	Ljava/lang/String;
    //   149: return
    //   150: astore_3
    //   151: aload_3
    //   152: athrow
    //   153: astore_3
    //   154: aload_3
    //   155: athrow
    // Local variable table:
    //   start	length	slot	name	signature
    //   48	62	0	i	int
    //   52	58	1	j	int
    //   56	56	2	k	int
    //   3	136	3	str	String
    //   150	2	3	localException1	Exception
    //   153	2	3	localException2	Exception
    // Exception table:
    //   from	to	target	type
    //   0	4	150	java/lang/Exception
    //   36	45	150	java/lang/Exception
    //   134	138	150	java/lang/Exception
    //   138	149	153	java/lang/Exception
  }
  
  private wbwwww() {}
  
  /* Error */
  @android.support.annotation.NonNull
  public static String b041804180418ИИИ04180418И0418(@android.support.annotation.NonNull java.util.List<String> paramList, @android.support.annotation.NonNull String paramString1, String paramString2)
  {
    // Byte code:
    //   0: getstatic 31	kkkkkk/wbwwww:b041AКККК041AК041AКК	I
    //   3: getstatic 33	kkkkkk/wbwwww:b041A041A041A041A041AКК041AКК	I
    //   6: iadd
    //   7: getstatic 31	kkkkkk/wbwwww:b041AКККК041AК041AКК	I
    //   10: imul
    //   11: getstatic 35	kkkkkk/wbwwww:bККККК041AК041AКК	I
    //   14: irem
    //   15: getstatic 37	kkkkkk/wbwwww:bК041A041A041A041AКК041AКК	I
    //   18: if_icmpeq +17 -> 35
    //   21: invokestatic 41	kkkkkk/wbwwww:bИИ0418ИИИ04180418И0418	()I
    //   24: istore_3
    //   25: iload_3
    //   26: putstatic 31	kkkkkk/wbwwww:b041AКККК041AК041AКК	I
    //   29: invokestatic 41	kkkkkk/wbwwww:bИИ0418ИИИ04180418И0418	()I
    //   32: putstatic 37	kkkkkk/wbwwww:bК041A041A041A041AКК041AКК	I
    //   35: aload_0
    //   36: aload_2
    //   37: invokestatic 62	shaded/org/apache/commons/lang3/StringUtils:join	(Ljava/lang/Iterable;Ljava/lang/String;)Ljava/lang/String;
    //   40: invokestatic 66	kkkkkk/wbwwww:bИ04180418ИИИ04180418И0418	(Ljava/lang/String;)Ljava/lang/String;
    //   43: aload_2
    //   44: invokevirtual 71	java/lang/String:concat	(Ljava/lang/String;)Ljava/lang/String;
    //   47: astore_0
    //   48: invokestatic 41	kkkkkk/wbwwww:bИИ0418ИИИ04180418И0418	()I
    //   51: getstatic 33	kkkkkk/wbwwww:b041A041A041A041A041AКК041AКК	I
    //   54: iadd
    //   55: invokestatic 41	kkkkkk/wbwwww:bИИ0418ИИИ04180418И0418	()I
    //   58: imul
    //   59: getstatic 35	kkkkkk/wbwwww:bККККК041AК041AКК	I
    //   62: irem
    //   63: getstatic 37	kkkkkk/wbwwww:bК041A041A041A041AКК041AКК	I
    //   66: if_icmpeq +14 -> 80
    //   69: bipush 39
    //   71: putstatic 31	kkkkkk/wbwwww:b041AКККК041AК041AКК	I
    //   74: invokestatic 41	kkkkkk/wbwwww:bИИ0418ИИИ04180418И0418	()I
    //   77: putstatic 37	kkkkkk/wbwwww:bК041A041A041A041AКК041AКК	I
    //   80: ldc 73
    //   82: bipush 124
    //   84: iconst_1
    //   85: invokestatic 47	kkkkkk/gguuuu:bккккк043Aкк043A043A	(Ljava/lang/String;CC)Ljava/lang/String;
    //   88: astore_2
    //   89: aload_0
    //   90: aload_2
    //   91: ldc 75
    //   93: bipush 109
    //   95: iconst_4
    //   96: invokestatic 47	kkkkkk/gguuuu:bккккк043Aкк043A043A	(Ljava/lang/String;CC)Ljava/lang/String;
    //   99: invokevirtual 79	java/lang/String:replace	(Ljava/lang/CharSequence;Ljava/lang/CharSequence;)Ljava/lang/String;
    //   102: aload_1
    //   103: invokestatic 85	kkkkkk/nmnnmn:b0418И04180418ИИИИ04180418	()Ljava/util/Locale;
    //   106: invokevirtual 89	java/lang/String:toUpperCase	(Ljava/util/Locale;)Ljava/lang/String;
    //   109: invokevirtual 71	java/lang/String:concat	(Ljava/lang/String;)Ljava/lang/String;
    //   112: astore_0
    //   113: aload_0
    //   114: areturn
    //   115: astore_0
    //   116: aload_0
    //   117: athrow
    //   118: astore_0
    //   119: aload_0
    //   120: athrow
    //   121: astore_0
    //   122: aload_0
    //   123: athrow
    //   124: astore_0
    //   125: aload_0
    //   126: athrow
    // Local variable table:
    //   start	length	slot	name	signature
    //   0	127	0	paramList	java.util.List<String>
    //   0	127	1	paramString1	String
    //   0	127	2	paramString2	String
    //   24	2	3	i	int
    // Exception table:
    //   from	to	target	type
    //   35	48	115	java/lang/Exception
    //   89	113	115	java/lang/Exception
    //   0	25	118	java/lang/Exception
    //   116	118	118	java/lang/Exception
    //   122	124	118	java/lang/Exception
    //   80	89	121	java/lang/Exception
    //   25	35	124	java/lang/Exception
  }
  
  public static int b0418И0418ИИИ04180418И0418()
  {
    return 0;
  }
  
  /* Error */
  @android.support.annotation.NonNull
  private static String bИ04180418ИИИ04180418И0418(@android.support.annotation.NonNull String paramString)
  {
    // Byte code:
    //   0: aload_0
    //   1: ldc 96
    //   3: bipush 23
    //   5: bipush 71
    //   7: iconst_2
    //   8: invokestatic 100	kkkkkk/gguuuu:bк043Aккк043Aкк043A043A	(Ljava/lang/String;CCC)Ljava/lang/String;
    //   11: invokevirtual 104	java/lang/String:split	(Ljava/lang/String;)[Ljava/lang/String;
    //   14: astore_0
    //   15: new 106	java/lang/StringBuilder
    //   18: dup
    //   19: invokespecial 107	java/lang/StringBuilder:<init>	()V
    //   22: astore 4
    //   24: aload_0
    //   25: arraylength
    //   26: istore_3
    //   27: iconst_0
    //   28: istore_1
    //   29: iload_1
    //   30: iload_3
    //   31: if_icmpge +108 -> 139
    //   34: aload_0
    //   35: iload_1
    //   36: aaload
    //   37: astore 5
    //   39: getstatic 31	kkkkkk/wbwwww:b041AКККК041AК041AКК	I
    //   42: getstatic 33	kkkkkk/wbwwww:b041A041A041A041A041AКК041AКК	I
    //   45: iadd
    //   46: getstatic 31	kkkkkk/wbwwww:b041AКККК041AК041AКК	I
    //   49: imul
    //   50: getstatic 35	kkkkkk/wbwwww:bККККК041AК041AКК	I
    //   53: irem
    //   54: invokestatic 109	kkkkkk/wbwwww:b0418И0418ИИИ04180418И0418	()I
    //   57: if_icmpeq +14 -> 71
    //   60: invokestatic 41	kkkkkk/wbwwww:bИИ0418ИИИ04180418И0418	()I
    //   63: putstatic 31	kkkkkk/wbwwww:b041AКККК041AК041AКК	I
    //   66: bipush 24
    //   68: putstatic 37	kkkkkk/wbwwww:bК041A041A041A041AКК041AКК	I
    //   71: aload 4
    //   73: ldc 111
    //   75: bipush 30
    //   77: iconst_4
    //   78: invokestatic 47	kkkkkk/gguuuu:bккккк043Aкк043A043A	(Ljava/lang/String;CC)Ljava/lang/String;
    //   81: invokevirtual 115	java/lang/StringBuilder:append	(Ljava/lang/String;)Ljava/lang/StringBuilder;
    //   84: pop
    //   85: aload 4
    //   87: aload 5
    //   89: invokestatic 85	kkkkkk/nmnnmn:b0418И04180418ИИИИ04180418	()Ljava/util/Locale;
    //   92: invokevirtual 118	java/lang/String:toLowerCase	(Ljava/util/Locale;)Ljava/lang/String;
    //   95: invokestatic 121	shaded/org/apache/commons/lang3/StringUtils:capitalize	(Ljava/lang/String;)Ljava/lang/String;
    //   98: invokevirtual 115	java/lang/StringBuilder:append	(Ljava/lang/String;)Ljava/lang/StringBuilder;
    //   101: pop
    //   102: iload_1
    //   103: iconst_1
    //   104: iadd
    //   105: istore_2
    //   106: iload_2
    //   107: istore_1
    //   108: invokestatic 41	kkkkkk/wbwwww:bИИ0418ИИИ04180418И0418	()I
    //   111: getstatic 33	kkkkkk/wbwwww:b041A041A041A041A041AКК041AКК	I
    //   114: iadd
    //   115: invokestatic 41	kkkkkk/wbwwww:bИИ0418ИИИ04180418И0418	()I
    //   118: imul
    //   119: getstatic 35	kkkkkk/wbwwww:bККККК041AК041AКК	I
    //   122: irem
    //   123: getstatic 37	kkkkkk/wbwwww:bК041A041A041A041AКК041AКК	I
    //   126: if_icmpeq -97 -> 29
    //   129: bipush 44
    //   131: putstatic 37	kkkkkk/wbwwww:bК041A041A041A041AКК041AКК	I
    //   134: iload_2
    //   135: istore_1
    //   136: goto -107 -> 29
    //   139: aload 4
    //   141: invokevirtual 125	java/lang/StringBuilder:toString	()Ljava/lang/String;
    //   144: invokevirtual 128	java/lang/String:trim	()Ljava/lang/String;
    //   147: astore_0
    //   148: aload_0
    //   149: areturn
    //   150: astore_0
    //   151: aload_0
    //   152: athrow
    //   153: astore_0
    //   154: aload_0
    //   155: athrow
    // Local variable table:
    //   start	length	slot	name	signature
    //   0	156	0	paramString	String
    //   28	108	1	i	int
    //   105	30	2	j	int
    //   26	6	3	k	int
    //   22	118	4	localStringBuilder	StringBuilder
    //   37	51	5	localObject	Object
    // Exception table:
    //   from	to	target	type
    //   0	27	150	java/lang/Exception
    //   71	102	150	java/lang/Exception
    //   139	148	153	java/lang/Exception
  }
  
  public static int bИИ0418ИИИ04180418И0418()
  {
    return 20;
  }
  
  @Retention(RetentionPolicy.SOURCE)
  public static @interface bwwwww
  {
    public static final int b041A041A041AКК041AК041AКК = 2;
    public static final String b041A041AККК041AК041AКК = "\006\027G";
    public static final int b041AК041AКК041AК041AКК;
    public static final int bК041A041AКК041AК041AКК = 1;
    public static final String bК041AККК041AК041AКК = "0%";
    public static final int bКК041AКК041AК041AКК = 9;
    
    /* Error */
    static
    {
      // Byte code:
      //   0: getstatic 34	kkkkkk/wbwwww$bwwwww:bК041AККК041AК041AКК	Ljava/lang/String;
      //   3: sipush 131
      //   6: iconst_0
      //   7: invokestatic 40	kkkkkk/gguuuu:bккккк043Aкк043A043A	(Ljava/lang/String;CC)Ljava/lang/String;
      //   10: astore_1
      //   11: getstatic 42	kkkkkk/wbwwww$bwwwww:bКК041AКК041AК041AКК	I
      //   14: istore_0
      //   15: getstatic 42	kkkkkk/wbwwww$bwwwww:bКК041AКК041AК041AКК	I
      //   18: getstatic 44	kkkkkk/wbwwww$bwwwww:bК041A041AКК041AК041AКК	I
      //   21: iadd
      //   22: getstatic 42	kkkkkk/wbwwww$bwwwww:bКК041AКК041AК041AКК	I
      //   25: imul
      //   26: getstatic 46	kkkkkk/wbwwww$bwwwww:b041A041A041AКК041AК041AКК	I
      //   29: irem
      //   30: getstatic 48	kkkkkk/wbwwww$bwwwww:b041AК041AКК041AК041AКК	I
      //   33: if_icmpeq +7 -> 40
      //   36: iconst_2
      //   37: putstatic 48	kkkkkk/wbwwww$bwwwww:b041AК041AКК041AК041AКК	I
      //   40: iload_0
      //   41: getstatic 44	kkkkkk/wbwwww$bwwwww:bК041A041AКК041AК041AКК	I
      //   44: iadd
      //   45: getstatic 42	kkkkkk/wbwwww$bwwwww:bКК041AКК041AК041AКК	I
      //   48: imul
      //   49: getstatic 46	kkkkkk/wbwwww$bwwwww:b041A041A041AКК041AК041AКК	I
      //   52: irem
      //   53: getstatic 48	kkkkkk/wbwwww$bwwwww:b041AК041AКК041AК041AКК	I
      //   56: if_icmpeq +8 -> 64
      //   59: bipush 74
      //   61: putstatic 48	kkkkkk/wbwwww$bwwwww:b041AК041AКК041AК041AКК	I
      //   64: aload_1
      //   65: putstatic 34	kkkkkk/wbwwww$bwwwww:bК041AККК041AК041AКК	Ljava/lang/String;
      //   68: getstatic 50	kkkkkk/wbwwww$bwwwww:b041A041AККК041AК041AКК	Ljava/lang/String;
      //   71: sipush 198
      //   74: iconst_2
      //   75: invokestatic 40	kkkkkk/gguuuu:bккккк043Aкк043A043A	(Ljava/lang/String;CC)Ljava/lang/String;
      //   78: astore_1
      //   79: aload_1
      //   80: putstatic 50	kkkkkk/wbwwww$bwwwww:b041A041AККК041AК041AКК	Ljava/lang/String;
      //   83: return
      //   84: astore_1
      //   85: aload_1
      //   86: athrow
      //   87: astore_1
      //   88: aload_1
      //   89: athrow
      //   90: astore_1
      //   91: aload_1
      //   92: athrow
      // Local variable table:
      //   start	length	slot	name	signature
      //   14	31	0	i	int
      //   10	70	1	str	String
      //   84	2	1	localException1	Exception
      //   87	2	1	localException2	Exception
      //   90	2	1	localException3	Exception
      // Exception table:
      //   from	to	target	type
      //   0	11	84	java/lang/Exception
      //   64	79	84	java/lang/Exception
      //   11	15	87	java/lang/Exception
      //   40	64	87	java/lang/Exception
      //   85	87	87	java/lang/Exception
      //   91	93	87	java/lang/Exception
      //   79	83	90	java/lang/Exception
    }
  }
}
