package kkkkkk;

import javax.inject.Inject;

public class wmmwmm
{
  private static final String b042804280428Ш0428ШШШШ = "V\003\002},[kpm";
  public static int b04280428Ш04280428ШШШШ = 2;
  public static int b0428Ш042804280428ШШШШ = 79;
  public static int bШ0428Ш04280428ШШШШ = 0;
  public static int bШШ042804280428ШШШШ = 1;
  private final rgrggg b0428ШШ04280428ШШШШ;
  private final nuuuuu bШШШ04280428ШШШШ;
  
  static
  {
    try
    {
      b042804280428Ш0428ШШШШ = gguuuu.bккккк043Aкк043A043A(b042804280428Ш0428ШШШШ, 'O', '\002');
      int i;
      for (;;) {}
    }
    catch (Exception localException1)
    {
      try
      {
        i = b0428Ш042804280428ШШШШ;
        switch (i * (b04300430а0430а04300430043004300430() + i) % b04280428Ш04280428ШШШШ)
        {
        case 0: 
          b0428Ш042804280428ШШШШ = 34;
          bШ0428Ш04280428ШШШШ = 93;
          return;
        }
      }
      catch (Exception localException2)
      {
        throw localException2;
      }
      localException1 = localException1;
      throw localException1;
    }
  }
  
  @Inject
  public wmmwmm(nuuuuu paramNuuuuu, rgrggg paramRgrggg)
  {
    this.bШШШ04280428ШШШШ = paramNuuuuu;
    this.b0428ШШ04280428ШШШШ = paramRgrggg;
  }
  
  public static int b04300430а0430а04300430043004300430()
  {
    return 1;
  }
  
  public static int bа0430а0430а04300430043004300430()
  {
    return 48;
  }
  
  public static int bаа04300430а04300430043004300430()
  {
    return 2;
  }
  
  public void b0430а04300430а04300430043004300430(String paramString1, String paramString2)
  {
    if ((bа0430а0430а04300430043004300430() + bШШ042804280428ШШШШ) * bа0430а0430а04300430043004300430() % b04280428Ш04280428ШШШШ != bШ0428Ш04280428ШШШШ) {
      bШ0428Ш04280428ШШШШ = 90;
    }
    nnnuuu.nnunuu localNnunuu = nnnuuu.nnunuu.SIX;
    String str = gguuuu.bк043Aккк043Aкк043A043A("O}~|\001/`ryx", ' ', 'i', '\003');
    if ((bа0430а0430а04300430043004300430() + b04300430а0430а04300430043004300430()) * bа0430а0430а04300430043004300430() % b04280428Ш04280428ШШШШ != bШ0428Ш04280428ШШШШ) {
      bШ0428Ш04280428ШШШШ = 24;
    }
    paramString1 = nuuuuu.unuuuu.b043F043F043Fп043F043Fпп043Fп(unuunu.SCREEN_NAME, paramString1);
    nuuuuu.unuuuu localUnuuuu = nuuuuu.unuuuu.b043F043F043Fп043F043Fпп043Fп(unuunu.JOURNEY_ACTION, gguuuu.bккккк043Aкк043A043A("+YZX\\\013<NUT", 'e', '\000'));
    unuunu localUnuunu = unuunu.JOURNEY_ACTION_NARRATIVE;
    switch (1)
    {
    case 0: 
    default: 
      for (;;)
      {
        switch (1)
        {
        }
      }
    }
    bа043004300430а04300430043004300430(localNnunuu, str, new nuuuuu.unuuuu[] { paramString1, localUnuuuu, nuuuuu.unuuuu.b043F043F043Fп043F043Fпп043Fп(localUnuunu, paramString2) });
  }
  
  /* Error */
  public void bа043004300430а04300430043004300430(nnnuuu.nnunuu paramNnunuu, String paramString, nuuuuu.unuuuu... paramVarArgs)
  {
    // Byte code:
    //   0: aload_0
    //   1: getfield 51	kkkkkk/wmmwmm:bШШШ04280428ШШШШ	Lkkkkkk/nuuuuu;
    //   4: astore 5
    //   6: goto +140 -> 146
    //   9: getstatic 104	kkkkkk/uunnuu:SERVICE	Lkkkkkk/uunnuu;
    //   12: astore 6
    //   14: getstatic 110	kkkkkk/nunnuu:ADDRESS	Lkkkkkk/nunnuu;
    //   17: astore 7
    //   19: getstatic 116	kkkkkk/nnnuuu$ununuu:CHANGE_ADDRESS	Lkkkkkk/nnnuuu$ununuu;
    //   22: astore 8
    //   24: getstatic 122	kkkkkk/nuuunu:N3_20	Lkkkkkk/nuuunu;
    //   27: astore 9
    //   29: getstatic 35	kkkkkk/wmmwmm:b0428Ш042804280428ШШШШ	I
    //   32: istore 4
    //   34: iload 4
    //   36: getstatic 62	kkkkkk/wmmwmm:bШШ042804280428ШШШШ	I
    //   39: iload 4
    //   41: iadd
    //   42: imul
    //   43: getstatic 41	kkkkkk/wmmwmm:b04280428Ш04280428ШШШШ	I
    //   46: irem
    //   47: tableswitch	default:+17->64, 0:+76->123
    //   64: bipush 99
    //   66: putstatic 35	kkkkkk/wmmwmm:b0428Ш042804280428ШШШШ	I
    //   69: invokestatic 60	kkkkkk/wmmwmm:bа0430а0430а04300430043004300430	()I
    //   72: putstatic 43	kkkkkk/wmmwmm:bШ0428Ш04280428ШШШШ	I
    //   75: getstatic 35	kkkkkk/wmmwmm:b0428Ш042804280428ШШШШ	I
    //   78: istore 4
    //   80: iload 4
    //   82: getstatic 62	kkkkkk/wmmwmm:bШШ042804280428ШШШШ	I
    //   85: iload 4
    //   87: iadd
    //   88: imul
    //   89: getstatic 41	kkkkkk/wmmwmm:b04280428Ш04280428ШШШШ	I
    //   92: irem
    //   93: tableswitch	default:+19->112, 0:+30->123
    //   112: bipush 17
    //   114: putstatic 35	kkkkkk/wmmwmm:b0428Ш042804280428ШШШШ	I
    //   117: invokestatic 60	kkkkkk/wmmwmm:bа0430а0430а04300430043004300430	()I
    //   120: putstatic 43	kkkkkk/wmmwmm:bШ0428Ш04280428ШШШШ	I
    //   123: aload 5
    //   125: aload 6
    //   127: aload 7
    //   129: aload 8
    //   131: aload 9
    //   133: aload_1
    //   134: aload_2
    //   135: aload_3
    //   136: invokevirtual 128	kkkkkk/nuuuuu:b043Fп043Fппп043Fп043Fп	(Lkkkkkk/uunnuu;Lkkkkkk/nunnuu;Lkkkkkk/nnnuuu$ununuu;Lkkkkkk/nuuunu;Lkkkkkk/nnnuuu$nnunuu;Ljava/lang/String;[Lkkkkkk/nuuuuu$unuuuu;)V
    //   139: return
    //   140: astore_1
    //   141: aload_1
    //   142: athrow
    //   143: astore_1
    //   144: aload_1
    //   145: athrow
    //   146: iconst_0
    //   147: tableswitch	default:+21->168, 0:+-138->9, 1:+-1->146
    //   168: iconst_0
    //   169: tableswitch	default:+23->192, 0:+-160->9, 1:+-23->146
    //   192: goto -24 -> 168
    // Local variable table:
    //   start	length	slot	name	signature
    //   0	195	0	this	wmmwmm
    //   0	195	1	paramNnunuu	nnnuuu.nnunuu
    //   0	195	2	paramString	String
    //   0	195	3	paramVarArgs	nuuuuu.unuuuu[]
    //   32	57	4	i	int
    //   4	120	5	localNuuuuu	nuuuuu
    //   12	114	6	localUunnuu	uunnuu
    //   17	111	7	localNunnuu	nunnuu
    //   22	108	8	localUnunuu	nnnuuu.ununuu
    //   27	105	9	localNuuunu	nuuunu
    // Exception table:
    //   from	to	target	type
    //   0	6	140	java/lang/Exception
    //   9	29	140	java/lang/Exception
    //   123	139	143	java/lang/Exception
  }
}
