package kkkkkk;

import android.support.annotation.NonNull;
import android.support.annotation.Nullable;
import android.support.annotation.VisibleForTesting;
import io.reactivex.Completable;
import io.reactivex.CompletableObserver;
import io.reactivex.Maybe;
import io.reactivex.Single;
import io.reactivex.SingleObserver;
import io.reactivex.disposables.Disposable;
import io.reactivex.functions.Action;
import io.reactivex.functions.Consumer;
import io.reactivex.functions.Function;
import java.lang.annotation.Annotation;
import java.lang.annotation.Retention;
import java.lang.annotation.RetentionPolicy;
import java.util.Iterator;
import java.util.List;
import java.util.concurrent.TimeUnit;
import javax.inject.Inject;

public class wmwmmw
  extends rgrrrg<wmmwwm>
  implements SingleObserver<cccrcc>
{
  public static int b043D043D043Dн043Dнн043D043D = 15;
  private static final int b043Dн043D043Dннн043D043D = 2;
  public static int b043Dнн043D043Dнн043D043D = 1;
  private static final int bн043D043D043Dннн043D043D = 1;
  public static int bн043Dн043D043Dнн043D043D = 2;
  private static final String bнн043D043Dннн043D043D = "\027";
  public static int bннн043D043Dнн043D043D;
  private final mwwmww b043D043D043D043Dннн043D043D;
  private final fbfbfb b043D043Dнн043Dнн043D043D;
  private final wwmwmw b043Dн043Dн043Dнн043D043D;
  private final rrrrrc b043Dннн043Dнн043D043D;
  private final nnmmmn bн043D043Dн043Dнн043D043D;
  private final mmmwmw bн043Dнн043Dнн043D043D;
  private boolean bнн043Dн043Dнн043D043D;
  private final ppppkk bнннн043Dнн043D043D;
  
  static
  {
    String str = bнн043D043Dннн043D043D;
    int i = b043D043D043Dн043Dнн043D043D;
    switch (i * (b043Dнн043D043Dнн043D043D + i) % bн043Dн043D043Dнн043D043D)
    {
    default: 
      b043D043D043Dн043Dнн043D043D = b04300430043004300430аа043004300430();
      bннн043D043Dнн043D043D = 35;
    }
    str = gguuuu.bк043Aккк043Aкк043A043A(str, '!', 'ò', '\002');
    if ((b043D043D043Dн043Dнн043D043D + b043Dнн043D043Dнн043D043D) * b043D043D043Dн043Dнн043D043D % bн043Dн043D043Dнн043D043D != bннн043D043Dнн043D043D)
    {
      b043D043D043Dн043Dнн043D043D = 72;
      bннн043D043Dнн043D043D = b04300430043004300430аа043004300430();
    }
    bнн043D043Dннн043D043D = str;
  }
  
  @Inject
  public wmwmmw(ppppkk paramPpppkk, mmmwmw paramMmmwmw, rrrrrc paramRrrrrc, wwmwmw paramWwmwmw, fbfbfb paramFbfbfb, nnmmmn paramNnmmmn, mwwmww paramMwwmww)
  {
    this.bн043Dнн043Dнн043D043D = paramMmmwmw;
    this.bнннн043Dнн043D043D = paramPpppkk;
    this.b043Dннн043Dнн043D043D = paramRrrrrc;
    this.b043Dн043Dн043Dнн043D043D = paramWwmwmw;
    this.b043D043Dнн043Dнн043D043D = paramFbfbfb;
    this.bн043D043Dн043Dнн043D043D = paramNnmmmn;
    this.b043D043D043D043Dннн043D043D = paramMwwmww;
  }
  
  public static int b04300430043004300430аа043004300430()
  {
    return 7;
  }
  
  /* Error */
  private void b0430043004300430а0430а043004300430(rcrccr paramRcrccr)
  {
    // Byte code:
    //   0: aload_0
    //   1: getfield 115	kkkkkk/wmwmmw:b042804280428ШШ042804280428Ш	Lkkkkkk/gggggr$grrrrg;
    //   4: checkcast 117	kkkkkk/wmmwwm
    //   7: aload_0
    //   8: getfield 94	kkkkkk/wmwmmw:bн043Dнн043Dнн043D043D	Lkkkkkk/mmmwmw;
    //   11: aload_1
    //   12: invokevirtual 123	kkkkkk/mmmwmw:bааа0430043004300430а04300430	(Lkkkkkk/rcrccr;)Ljava/lang/String;
    //   15: invokeinterface 127 2 0
    //   20: aload_0
    //   21: getfield 115	kkkkkk/wmwmmw:b042804280428ШШ042804280428Ш	Lkkkkkk/gggggr$grrrrg;
    //   24: checkcast 117	kkkkkk/wmmwwm
    //   27: astore 5
    //   29: aload_0
    //   30: getfield 94	kkkkkk/wmwmmw:bн043Dнн043Dнн043D043D	Lkkkkkk/mmmwmw;
    //   33: aload_1
    //   34: invokevirtual 130	kkkkkk/mmmwmw:b0430а04300430а04300430а04300430	(Lkkkkkk/rcrccr;)Ljava/lang/String;
    //   37: astore 6
    //   39: getstatic 70	kkkkkk/wmwmmw:b043D043D043Dн043Dнн043D043D	I
    //   42: getstatic 72	kkkkkk/wmwmmw:b043Dнн043D043Dнн043D043D	I
    //   45: iadd
    //   46: getstatic 70	kkkkkk/wmwmmw:b043D043D043Dн043Dнн043D043D	I
    //   49: imul
    //   50: getstatic 74	kkkkkk/wmwmmw:bн043Dн043D043Dнн043D043D	I
    //   53: irem
    //   54: getstatic 80	kkkkkk/wmwmmw:bннн043D043Dнн043D043D	I
    //   57: if_icmpeq +15 -> 72
    //   60: invokestatic 78	kkkkkk/wmwmmw:b04300430043004300430аа043004300430	()I
    //   63: putstatic 70	kkkkkk/wmwmmw:b043D043D043Dн043Dнн043D043D	I
    //   66: invokestatic 78	kkkkkk/wmwmmw:b04300430043004300430аа043004300430	()I
    //   69: putstatic 80	kkkkkk/wmwmmw:bннн043D043Dнн043D043D	I
    //   72: aload 5
    //   74: aload 6
    //   76: aload_0
    //   77: getfield 132	kkkkkk/wmwmmw:bнн043Dн043Dнн043D043D	Z
    //   80: invokeinterface 136 3 0
    //   85: aload_0
    //   86: getfield 115	kkkkkk/wmwmmw:b042804280428ШШ042804280428Ш	Lkkkkkk/gggggr$grrrrg;
    //   89: checkcast 117	kkkkkk/wmmwwm
    //   92: astore 5
    //   94: aload_0
    //   95: getfield 94	kkkkkk/wmwmmw:bн043Dнн043Dнн043D043D	Lkkkkkk/mmmwmw;
    //   98: aload_1
    //   99: invokevirtual 139	kkkkkk/mmmwmw:b0430ааа043004300430а04300430	(Lkkkkkk/rcrccr;)Ljava/lang/String;
    //   102: astore 6
    //   104: aload 5
    //   106: aload 6
    //   108: aload_0
    //   109: getfield 94	kkkkkk/wmwmmw:bн043Dнн043Dнн043D043D	Lkkkkkk/mmmwmw;
    //   112: aload_1
    //   113: invokevirtual 142	kkkkkk/mmmwmw:bа0430аа043004300430а04300430	(Lkkkkkk/rcrccr;)Ljava/lang/String;
    //   116: invokeinterface 146 3 0
    //   121: getstatic 70	kkkkkk/wmwmmw:b043D043D043Dн043Dнн043D043D	I
    //   124: istore_2
    //   125: getstatic 72	kkkkkk/wmwmmw:b043Dнн043D043Dнн043D043D	I
    //   128: istore_3
    //   129: getstatic 74	kkkkkk/wmwmmw:bн043Dн043D043Dнн043D043D	I
    //   132: istore 4
    //   134: iload_2
    //   135: iload_3
    //   136: iload_2
    //   137: iadd
    //   138: imul
    //   139: iload 4
    //   141: irem
    //   142: tableswitch	default:+18->160, 0:+29->171
    //   160: bipush 7
    //   162: putstatic 70	kkkkkk/wmwmmw:b043D043D043Dн043Dнн043D043D	I
    //   165: invokestatic 78	kkkkkk/wmwmmw:b04300430043004300430аа043004300430	()I
    //   168: putstatic 80	kkkkkk/wmwmmw:bннн043D043Dнн043D043D	I
    //   171: aload_0
    //   172: getfield 115	kkkkkk/wmwmmw:b042804280428ШШ042804280428Ш	Lkkkkkk/gggggr$grrrrg;
    //   175: checkcast 117	kkkkkk/wmmwwm
    //   178: aload_0
    //   179: getfield 94	kkkkkk/wmwmmw:bн043Dнн043Dнн043D043D	Lkkkkkk/mmmwmw;
    //   182: aload_1
    //   183: invokevirtual 149	kkkkkk/mmmwmw:b0430а0430а043004300430а04300430	(Lkkkkkk/rcrccr;)Ljava/lang/String;
    //   186: aload_0
    //   187: getfield 94	kkkkkk/wmwmmw:bн043Dнн043Dнн043D043D	Lkkkkkk/mmmwmw;
    //   190: aload_1
    //   191: invokevirtual 152	kkkkkk/mmmwmw:b04300430а0430а04300430а04300430	(Lkkkkkk/rcrccr;)Ljava/lang/String;
    //   194: invokeinterface 155 3 0
    //   199: aload_0
    //   200: getfield 94	kkkkkk/wmwmmw:bн043Dнн043Dнн043D043D	Lkkkkkk/mmmwmw;
    //   203: astore_1
    //   204: aload_1
    //   205: invokevirtual 159	kkkkkk/mmmwmw:b0430аа0430043004300430а04300430	()Z
    //   208: ifne +15 -> 223
    //   211: aload_0
    //   212: getfield 115	kkkkkk/wmwmmw:b042804280428ШШ042804280428Ш	Lkkkkkk/gggggr$grrrrg;
    //   215: checkcast 117	kkkkkk/wmmwwm
    //   218: invokeinterface 162 1 0
    //   223: return
    //   224: astore_1
    //   225: aload_1
    //   226: athrow
    //   227: astore_1
    //   228: aload_1
    //   229: athrow
    // Local variable table:
    //   start	length	slot	name	signature
    //   0	230	0	this	wmwmmw
    //   0	230	1	paramRcrccr	rcrccr
    //   124	15	2	i	int
    //   128	10	3	j	int
    //   132	10	4	k	int
    //   27	78	5	localWmmwwm	wmmwwm
    //   37	70	6	str	String
    // Exception table:
    //   from	to	target	type
    //   0	39	224	java/lang/Exception
    //   72	85	224	java/lang/Exception
    //   104	134	224	java/lang/Exception
    //   171	204	224	java/lang/Exception
    //   85	104	227	java/lang/Exception
    //   160	171	227	java/lang/Exception
    //   204	223	227	java/lang/Exception
  }
  
  private void b04300430а04300430аа043004300430(final rccrcr paramRccrcr, final mmmwwm paramMmmwwm, final fbfffb paramFbfffb)
  {
    if ((b043D043D043Dн043Dнн043D043D + b043Dнн043D043Dнн043D043D) * b043D043D043Dн043Dнн043D043D % bн043Dн043D043Dнн043D043D != bннн043D043Dнн043D043D)
    {
      b043D043D043Dн043Dнн043D043D = b04300430043004300430аа043004300430();
      bннн043D043Dнн043D043D = 62;
    }
    ((wmmwwm)this.b042804280428ШШ042804280428Ш).initialiseSecureCallLoadingDialog();
    ((wmmwwm)this.b042804280428ШШ042804280428Ш).showLoading();
    paramRccrcr = bа0430ааа0430а043004300430(paramMmmwwm).flatMap(new Function()
    {
      public static int b043D043D043D043D043D043Dн043D043D = 2;
      public static int b043Dн043D043D043D043Dн043D043D = 0;
      public static int bн043D043D043D043D043Dн043D043D = 1;
      public static int bнннннн043D043D043D = 47;
      
      public static int b0430а04300430ааа043004300430()
      {
        return 98;
      }
      
      public static int bаа04300430ааа043004300430()
      {
        return 2;
      }
      
      public Maybe<ccrrcr> b04300430а0430ааа043004300430(@NonNull String paramAnonymousString)
        throws Exception
      {
        return wmwmmw.b0430а0430а0430аа043004300430(wmwmmw.this, paramAnonymousString, paramRccrcr, paramFbfffb).toMaybe();
      }
    }).retry(1L);
    paramFbfffb = new Consumer()
    {
      public static int b043D043Dн043Dн043Dн043D043D = 1;
      public static int b043Dн043D043Dн043Dн043D043D = 0;
      public static int bн043Dн043Dн043Dн043D043D = 41;
      public static int bнн043D043Dн043Dн043D043D = 2;
      
      public static int b043004300430аааа043004300430()
      {
        return 78;
      }
      
      public static int b0430а0430аааа043004300430()
      {
        return 2;
      }
      
      public static int bа04300430аааа043004300430()
      {
        return 1;
      }
      
      /* Error */
      public void bаа0430аааа043004300430(@NonNull ccrrcr paramAnonymousCcrrcr)
        throws Exception
      {
        // Byte code:
        //   0: getstatic 44	kkkkkk/wmwmmw$3:bн043Dн043Dн043Dн043D043D	I
        //   3: getstatic 46	kkkkkk/wmwmmw$3:b043D043Dн043Dн043Dн043D043D	I
        //   6: iadd
        //   7: getstatic 44	kkkkkk/wmwmmw$3:bн043Dн043Dн043Dн043D043D	I
        //   10: imul
        //   11: getstatic 48	kkkkkk/wmwmmw$3:bнн043D043Dн043Dн043D043D	I
        //   14: irem
        //   15: getstatic 50	kkkkkk/wmwmmw$3:b043Dн043D043Dн043Dн043D043D	I
        //   18: if_icmpeq +14 -> 32
        //   21: invokestatic 52	kkkkkk/wmwmmw$3:b043004300430аааа043004300430	()I
        //   24: putstatic 44	kkkkkk/wmwmmw$3:bн043Dн043Dн043Dн043D043D	I
        //   27: bipush 30
        //   29: putstatic 50	kkkkkk/wmwmmw$3:b043Dн043D043Dн043Dн043D043D	I
        //   32: aload_0
        //   33: getfield 27	kkkkkk/wmwmmw$3:bннн043Dн043Dн043D043D	Lkkkkkk/wmwmmw;
        //   36: astore_3
        //   37: aload_0
        //   38: getfield 29	kkkkkk/wmwmmw$3:b043Dнн043Dн043Dн043D043D	Lkkkkkk/mmmwwm;
        //   41: astore 4
        //   43: aload_3
        //   44: iconst_1
        //   45: aload 4
        //   47: aload_1
        //   48: invokevirtual 68	kkkkkk/ccrrcr:b043F043F043Fп043Fп043F043Fпп	()Ljava/lang/String;
        //   51: aconst_null
        //   52: invokevirtual 72	kkkkkk/wmwmmw:bаааа04300430а043004300430	(ILkkkkkk/mmmwwm;Ljava/lang/String;Lkkkkkk/rrrccr;)V
        //   55: getstatic 44	kkkkkk/wmwmmw$3:bн043Dн043Dн043Dн043D043D	I
        //   58: istore_2
        //   59: iload_2
        //   60: getstatic 46	kkkkkk/wmwmmw$3:b043D043Dн043Dн043Dн043D043D	I
        //   63: iload_2
        //   64: iadd
        //   65: imul
        //   66: getstatic 48	kkkkkk/wmwmmw$3:bнн043D043Dн043Dн043D043D	I
        //   69: irem
        //   70: tableswitch	default:+42->112, 0:+45->115
        //   88: invokestatic 52	kkkkkk/wmwmmw$3:b043004300430аааа043004300430	()I
        //   91: putstatic 44	kkkkkk/wmwmmw$3:bн043Dн043Dн043Dн043D043D	I
        //   94: bipush 88
        //   96: putstatic 46	kkkkkk/wmwmmw$3:b043D043Dн043Dн043Dн043D043D	I
        //   99: return
        //   100: astore_1
        //   101: aload_1
        //   102: athrow
        //   103: astore_1
        //   104: aload_1
        //   105: athrow
        //   106: astore_1
        //   107: aload_1
        //   108: athrow
        //   109: astore_1
        //   110: aload_1
        //   111: athrow
        //   112: goto -24 -> 88
        //   115: return
        // Local variable table:
        //   start	length	slot	name	signature
        //   0	116	0	this	3
        //   0	116	1	paramAnonymousCcrrcr	ccrrcr
        //   58	8	2	i	int
        //   36	8	3	localWmwmmw	wmwmmw
        //   41	5	4	localMmmwwm	mmmwwm
        // Exception table:
        //   from	to	target	type
        //   32	37	100	java/lang/Exception
        //   43	55	100	java/lang/Exception
        //   55	88	103	java/lang/Exception
        //   88	99	103	java/lang/Exception
        //   101	103	103	java/lang/Exception
        //   37	43	106	java/lang/Exception
        //   107	109	109	java/lang/Exception
      }
    };
    Consumer local4 = new Consumer()
    {
      public static int b043D043Dнн043D043Dн043D043D = 2;
      public static int b043Dннн043D043Dн043D043D = 0;
      public static int bн043Dнн043D043Dн043D043D = 1;
      public static int bнннн043D043Dн043D043D = 48;
      
      public static int b0430аа0430ааа043004300430()
      {
        return 72;
      }
      
      /* Error */
      public void bааа0430ааа043004300430(@NonNull Throwable paramAnonymousThrowable)
        throws Exception
      {
        // Byte code:
        //   0: new 60	java/lang/StringBuilder
        //   3: dup
        //   4: invokespecial 61	java/lang/StringBuilder:<init>	()V
        //   7: ldc 63
        //   9: sipush 146
        //   12: sipush 253
        //   15: iconst_3
        //   16: invokestatic 69	kkkkkk/gguuuu:bк043Aккк043Aкк043A043A	(Ljava/lang/String;CCC)Ljava/lang/String;
        //   19: invokevirtual 73	java/lang/StringBuilder:append	(Ljava/lang/String;)Ljava/lang/StringBuilder;
        //   22: aload_1
        //   23: invokevirtual 77	java/lang/Throwable:getMessage	()Ljava/lang/String;
        //   26: invokevirtual 73	java/lang/StringBuilder:append	(Ljava/lang/String;)Ljava/lang/StringBuilder;
        //   29: ldc 79
        //   31: bipush 26
        //   33: iconst_2
        //   34: invokestatic 83	kkkkkk/gguuuu:bккккк043Aкк043A043A	(Ljava/lang/String;CC)Ljava/lang/String;
        //   37: invokevirtual 73	java/lang/StringBuilder:append	(Ljava/lang/String;)Ljava/lang/StringBuilder;
        //   40: astore_1
        //   41: getstatic 42	kkkkkk/wmwmmw$4:bнннн043D043Dн043D043D	I
        //   44: istore_2
        //   45: getstatic 44	kkkkkk/wmwmmw$4:bн043Dнн043D043Dн043D043D	I
        //   48: istore_3
        //   49: getstatic 42	kkkkkk/wmwmmw$4:bнннн043D043Dн043D043D	I
        //   52: istore 4
        //   54: getstatic 42	kkkkkk/wmwmmw$4:bнннн043D043Dн043D043D	I
        //   57: istore 5
        //   59: iload 5
        //   61: getstatic 44	kkkkkk/wmwmmw$4:bн043Dнн043D043Dн043D043D	I
        //   64: iload 5
        //   66: iadd
        //   67: imul
        //   68: getstatic 46	kkkkkk/wmwmmw$4:b043D043Dнн043D043Dн043D043D	I
        //   71: irem
        //   72: tableswitch	default:+20->92, 0:+32->104
        //   92: invokestatic 50	kkkkkk/wmwmmw$4:b0430аа0430ааа043004300430	()I
        //   95: putstatic 42	kkkkkk/wmwmmw$4:bнннн043D043Dн043D043D	I
        //   98: invokestatic 50	kkkkkk/wmwmmw$4:b0430аа0430ааа043004300430	()I
        //   101: putstatic 48	kkkkkk/wmwmmw$4:b043Dннн043D043Dн043D043D	I
        //   104: iload_2
        //   105: iload_3
        //   106: iadd
        //   107: iload 4
        //   109: imul
        //   110: getstatic 46	kkkkkk/wmwmmw$4:b043D043Dнн043D043Dн043D043D	I
        //   113: irem
        //   114: getstatic 48	kkkkkk/wmwmmw$4:b043Dннн043D043Dн043D043D	I
        //   117: if_icmpeq +13 -> 130
        //   120: bipush 54
        //   122: putstatic 42	kkkkkk/wmwmmw$4:bнннн043D043Dн043D043D	I
        //   125: bipush 91
        //   127: putstatic 48	kkkkkk/wmwmmw$4:b043Dннн043D043Dн043D043D	I
        //   130: aload_1
        //   131: invokevirtual 86	java/lang/StringBuilder:toString	()Ljava/lang/String;
        //   134: iconst_0
        //   135: anewarray 5	java/lang/Object
        //   138: invokestatic 92	kkkkkk/ooooio:bа0430а04300430а0430ааа	(Ljava/lang/String;[Ljava/lang/Object;)V
        //   141: aload_0
        //   142: getfield 27	kkkkkk/wmwmmw$4:bн043D043D043Dн043Dн043D043D	Lkkkkkk/wmwmmw;
        //   145: iconst_2
        //   146: aload_0
        //   147: getfield 29	kkkkkk/wmwmmw$4:b043D043D043D043Dн043Dн043D043D	Lkkkkkk/mmmwwm;
        //   150: aconst_null
        //   151: getstatic 98	kkkkkk/rrrccr:OTHER	Lkkkkkk/rrrccr;
        //   154: invokevirtual 102	kkkkkk/wmwmmw:bаааа04300430а043004300430	(ILkkkkkk/mmmwwm;Ljava/lang/String;Lkkkkkk/rrrccr;)V
        //   157: return
        //   158: astore_1
        //   159: aload_1
        //   160: athrow
        //   161: astore_1
        //   162: aload_1
        //   163: athrow
        //   164: astore_1
        //   165: aload_1
        //   166: athrow
        //   167: astore_1
        //   168: aload_1
        //   169: athrow
        // Local variable table:
        //   start	length	slot	name	signature
        //   0	170	0	this	4
        //   0	170	1	paramAnonymousThrowable	Throwable
        //   44	63	2	i	int
        //   48	59	3	j	int
        //   52	58	4	k	int
        //   57	11	5	m	int
        // Exception table:
        //   from	to	target	type
        //   0	41	158	java/lang/Exception
        //   130	141	158	java/lang/Exception
        //   104	130	161	java/lang/Exception
        //   159	161	161	java/lang/Exception
        //   165	167	161	java/lang/Exception
        //   141	157	164	java/lang/Exception
        //   41	54	167	java/lang/Exception
      }
    };
    paramMmmwwm = new Action()
    {
      public static int b043D043D043Dн043D043Dн043D043D = 1;
      public static int b043Dнн043D043D043Dн043D043D = 2;
      public static int bн043D043Dн043D043Dн043D043D = 0;
      public static int bннн043D043D043Dн043D043D = 2;
      
      public static int bа0430а0430ааа043004300430()
      {
        return 18;
      }
      
      /* Error */
      public void run()
        throws Exception
      {
        // Byte code:
        //   0: getstatic 38	kkkkkk/wmwmmw$5:b043Dнн043D043D043Dн043D043D	I
        //   3: getstatic 40	kkkkkk/wmwmmw$5:b043D043D043Dн043D043Dн043D043D	I
        //   6: iadd
        //   7: getstatic 38	kkkkkk/wmwmmw$5:b043Dнн043D043D043Dн043D043D	I
        //   10: imul
        //   11: getstatic 42	kkkkkk/wmwmmw$5:bннн043D043D043Dн043D043D	I
        //   14: irem
        //   15: getstatic 44	kkkkkk/wmwmmw$5:bн043D043Dн043D043Dн043D043D	I
        //   18: if_icmpeq +15 -> 33
        //   21: invokestatic 46	kkkkkk/wmwmmw$5:bа0430а0430ааа043004300430	()I
        //   24: putstatic 38	kkkkkk/wmwmmw$5:b043Dнн043D043D043Dн043D043D	I
        //   27: invokestatic 46	kkkkkk/wmwmmw$5:bа0430а0430ааа043004300430	()I
        //   30: putstatic 44	kkkkkk/wmwmmw$5:bн043D043Dн043D043Dн043D043D	I
        //   33: invokestatic 46	kkkkkk/wmwmmw$5:bа0430а0430ааа043004300430	()I
        //   36: istore_1
        //   37: getstatic 40	kkkkkk/wmwmmw$5:b043D043D043Dн043D043Dн043D043D	I
        //   40: istore_2
        //   41: invokestatic 46	kkkkkk/wmwmmw$5:bа0430а0430ааа043004300430	()I
        //   44: istore_3
        //   45: getstatic 42	kkkkkk/wmwmmw$5:bннн043D043D043Dн043D043D	I
        //   48: istore 4
        //   50: getstatic 44	kkkkkk/wmwmmw$5:bн043D043Dн043D043Dн043D043D	I
        //   53: istore 5
        //   55: iload_1
        //   56: iload_2
        //   57: iadd
        //   58: iload_3
        //   59: imul
        //   60: iload 4
        //   62: irem
        //   63: iload 5
        //   65: if_icmpeq +59 -> 124
        //   68: invokestatic 46	kkkkkk/wmwmmw$5:bа0430а0430ааа043004300430	()I
        //   71: putstatic 44	kkkkkk/wmwmmw$5:bн043D043Dн043D043Dн043D043D	I
        //   74: goto +50 -> 124
        //   77: ldc 48
        //   79: sipush 144
        //   82: iconst_4
        //   83: invokestatic 54	kkkkkk/gguuuu:bккккк043Aкк043A043A	(Ljava/lang/String;CC)Ljava/lang/String;
        //   86: astore 6
        //   88: aload 6
        //   90: iconst_0
        //   91: anewarray 4	java/lang/Object
        //   94: invokestatic 60	kkkkkk/ooooio:bа0430а04300430а0430ааа	(Ljava/lang/String;[Ljava/lang/Object;)V
        //   97: aload_0
        //   98: getfield 25	kkkkkk/wmwmmw$5:bнн043Dн043D043Dн043D043D	Lkkkkkk/wmwmmw;
        //   101: iconst_2
        //   102: aload_0
        //   103: getfield 27	kkkkkk/wmwmmw$5:b043Dн043Dн043D043Dн043D043D	Lkkkkkk/mmmwwm;
        //   106: aconst_null
        //   107: getstatic 66	kkkkkk/rrrccr:NO_ARRANGEMENT_REFERENCE	Lkkkkkk/rrrccr;
        //   110: invokevirtual 70	kkkkkk/wmwmmw:bаааа04300430а043004300430	(ILkkkkkk/mmmwwm;Ljava/lang/String;Lkkkkkk/rrrccr;)V
        //   113: return
        //   114: astore 6
        //   116: aload 6
        //   118: athrow
        //   119: astore 6
        //   121: aload 6
        //   123: athrow
        //   124: iconst_0
        //   125: tableswitch	default:+23->148, 0:+-48->77, 1:+-1->124
        //   148: iconst_0
        //   149: tableswitch	default:+23->172, 0:+-72->77, 1:+-25->124
        //   172: goto -24 -> 148
        // Local variable table:
        //   start	length	slot	name	signature
        //   0	175	0	this	5
        //   36	22	1	i	int
        //   40	18	2	j	int
        //   44	16	3	k	int
        //   48	15	4	m	int
        //   53	13	5	n	int
        //   86	3	6	str	String
        //   114	3	6	localException1	Exception
        //   119	3	6	localException2	Exception
        // Exception table:
        //   from	to	target	type
        //   33	55	114	java/lang/Exception
        //   88	113	114	java/lang/Exception
        //   68	74	119	java/lang/Exception
        //   77	88	119	java/lang/Exception
      }
    };
    if ((b043D043D043Dн043Dнн043D043D + b043Dнн043D043Dнн043D043D) * b043D043D043Dн043Dнн043D043D % b0430а043004300430аа043004300430() != bннн043D043Dнн043D043D)
    {
      b043D043D043Dн043Dнн043D043D = b04300430043004300430аа043004300430();
      bннн043D043Dнн043D043D = b04300430043004300430аа043004300430();
    }
    switch (0)
    {
    case 1: 
    default: 
      for (;;)
      {
        switch (1)
        {
        }
      }
    }
    b04180418И0418ИИИ0418ИИ(paramRccrcr.subscribe(paramFbfffb, local4, paramMmmwwm));
  }
  
  private void b04300430а0430а0430а043004300430(rcrccr paramRcrccr)
  {
    ((wmmwwm)this.b042804280428ШШ042804280428Ш).showOpeningTimes(this.bн043Dнн043Dнн043D043D.bа043004300430а04300430а04300430(), this.bн043Dнн043Dнн043D043D.bа043004300430а04300430а04300430());
    ((wmmwwm)this.b042804280428ШШ042804280428Ш).showTitle(this.bн043Dнн043Dнн043D043D.bааа0430043004300430а04300430(paramRcrccr));
    wmmwwm localWmmwwm = (wmmwwm)this.b042804280428ШШ042804280428Ш;
    String str1 = this.bн043Dнн043Dнн043D043D.bаа0430а043004300430а04300430(paramRcrccr);
    String str2 = this.bн043Dнн043Dнн043D043D.bа0430а0430а04300430а04300430(paramRcrccr);
    if ((b04300430043004300430аа043004300430() + b043Dнн043D043Dнн043D043D) * b04300430043004300430аа043004300430() % bн043Dн043D043Dнн043D043D != bннн043D043Dнн043D043D)
    {
      b043D043D043Dн043Dнн043D043D = 81;
      bннн043D043Dнн043D043D = 32;
    }
    localWmmwwm.setTextphoneContent(str1, str2);
    localWmmwwm = (wmmwwm)this.b042804280428ШШ042804280428Ш;
    paramRcrccr = this.bн043Dнн043Dнн043D043D.b0430а04300430а04300430а04300430(paramRcrccr);
    switch (0)
    {
    case 1: 
    default: 
      for (;;)
      {
        switch (1)
        {
        }
      }
    }
    switch (1)
    {
    case 0: 
    default: 
      for (;;)
      {
        switch (1)
        {
        }
      }
    }
    localWmmwwm.inflateCallDescriptionText(paramRcrccr, this.bнн043Dн043Dнн043D043D);
    ((wmmwwm)this.b042804280428ШШ042804280428Ш).showCallUsInfo();
    ((wmmwwm)this.b042804280428ШШ042804280428Ш).hideNotAllServicesAvailableMessage();
    int i = b043D043D043Dн043Dнн043D043D;
    switch (i * (b043Dнн043D043Dнн043D043D + i) % bн043Dн043D043Dнн043D043D)
    {
    default: 
      b043D043D043Dн043Dнн043D043D = 73;
      bннн043D043Dнн043D043D = 93;
    }
  }
  
  public static int b0430а043004300430аа043004300430()
  {
    return 2;
  }
  
  /* Error */
  private void b0430а04300430а0430а043004300430(rcrccr paramRcrccr, qqqqqj paramQqqqqj)
  {
    // Byte code:
    //   0: aload_0
    //   1: getfield 115	kkkkkk/wmwmmw:b042804280428ШШ042804280428Ш	Lkkkkkk/gggggr$grrrrg;
    //   4: checkcast 117	kkkkkk/wmmwwm
    //   7: invokeinterface 229 1 0
    //   12: aload_0
    //   13: getfield 115	kkkkkk/wmwmmw:b042804280428ШШ042804280428Ш	Lkkkkkk/gggggr$grrrrg;
    //   16: astore 8
    //   18: aload 8
    //   20: checkcast 117	kkkkkk/wmmwwm
    //   23: aload_2
    //   24: invokeinterface 233 2 0
    //   29: aload_0
    //   30: getfield 115	kkkkkk/wmwmmw:b042804280428ШШ042804280428Ш	Lkkkkkk/gggggr$grrrrg;
    //   33: checkcast 117	kkkkkk/wmmwwm
    //   36: astore_2
    //   37: aload_0
    //   38: getfield 94	kkkkkk/wmwmmw:bн043Dнн043Dнн043D043D	Lkkkkkk/mmmwmw;
    //   41: aload_1
    //   42: invokevirtual 139	kkkkkk/mmmwmw:b0430ааа043004300430а04300430	(Lkkkkkk/rcrccr;)Ljava/lang/String;
    //   45: astore 8
    //   47: aload_0
    //   48: getfield 94	kkkkkk/wmwmmw:bн043Dнн043Dнн043D043D	Lkkkkkk/mmmwmw;
    //   51: astore 9
    //   53: getstatic 70	kkkkkk/wmwmmw:b043D043D043Dн043Dнн043D043D	I
    //   56: istore_3
    //   57: getstatic 72	kkkkkk/wmwmmw:b043Dнн043D043Dнн043D043D	I
    //   60: istore 4
    //   62: getstatic 70	kkkkkk/wmwmmw:b043D043D043Dн043Dнн043D043D	I
    //   65: istore 5
    //   67: getstatic 74	kkkkkk/wmwmmw:bн043Dн043D043Dнн043D043D	I
    //   70: istore 6
    //   72: getstatic 70	kkkkkk/wmwmmw:b043D043D043Dн043Dнн043D043D	I
    //   75: getstatic 72	kkkkkk/wmwmmw:b043Dнн043D043Dнн043D043D	I
    //   78: iadd
    //   79: getstatic 70	kkkkkk/wmwmmw:b043D043D043Dн043Dнн043D043D	I
    //   82: imul
    //   83: getstatic 74	kkkkkk/wmwmmw:bн043Dн043D043Dнн043D043D	I
    //   86: irem
    //   87: invokestatic 236	kkkkkk/wmwmmw:bаа043004300430аа043004300430	()I
    //   90: if_icmpeq +15 -> 105
    //   93: invokestatic 78	kkkkkk/wmwmmw:b04300430043004300430аа043004300430	()I
    //   96: putstatic 70	kkkkkk/wmwmmw:b043D043D043Dн043Dнн043D043D	I
    //   99: invokestatic 78	kkkkkk/wmwmmw:b04300430043004300430аа043004300430	()I
    //   102: putstatic 80	kkkkkk/wmwmmw:bннн043D043Dнн043D043D	I
    //   105: getstatic 80	kkkkkk/wmwmmw:bннн043D043Dнн043D043D	I
    //   108: istore 7
    //   110: iload_3
    //   111: iload 4
    //   113: iadd
    //   114: iload 5
    //   116: imul
    //   117: iload 6
    //   119: irem
    //   120: iload 7
    //   122: if_icmpeq +15 -> 137
    //   125: invokestatic 78	kkkkkk/wmwmmw:b04300430043004300430аа043004300430	()I
    //   128: putstatic 70	kkkkkk/wmwmmw:b043D043D043Dн043Dнн043D043D	I
    //   131: invokestatic 78	kkkkkk/wmwmmw:b04300430043004300430аа043004300430	()I
    //   134: putstatic 80	kkkkkk/wmwmmw:bннн043D043Dнн043D043D	I
    //   137: aload_2
    //   138: aload 8
    //   140: aload 9
    //   142: aload_1
    //   143: invokevirtual 142	kkkkkk/mmmwmw:bа0430аа043004300430а04300430	(Lkkkkkk/rcrccr;)Ljava/lang/String;
    //   146: invokeinterface 146 3 0
    //   151: aload_0
    //   152: getfield 115	kkkkkk/wmwmmw:b042804280428ШШ042804280428Ш	Lkkkkkk/gggggr$grrrrg;
    //   155: checkcast 117	kkkkkk/wmmwwm
    //   158: astore_2
    //   159: aload_0
    //   160: getfield 94	kkkkkk/wmwmmw:bн043Dнн043Dнн043D043D	Lkkkkkk/mmmwmw;
    //   163: astore 8
    //   165: aload_2
    //   166: aload 8
    //   168: aload_1
    //   169: invokevirtual 149	kkkkkk/mmmwmw:b0430а0430а043004300430а04300430	(Lkkkkkk/rcrccr;)Ljava/lang/String;
    //   172: aload_0
    //   173: getfield 94	kkkkkk/wmwmmw:bн043Dнн043Dнн043D043D	Lkkkkkk/mmmwmw;
    //   176: aload_1
    //   177: invokevirtual 152	kkkkkk/mmmwmw:b04300430а0430а04300430а04300430	(Lkkkkkk/rcrccr;)Ljava/lang/String;
    //   180: invokeinterface 155 3 0
    //   185: return
    //   186: astore_1
    //   187: aload_1
    //   188: athrow
    //   189: astore_1
    //   190: aload_1
    //   191: athrow
    //   192: astore_1
    //   193: aload_1
    //   194: athrow
    //   195: astore_1
    //   196: aload_1
    //   197: athrow
    // Local variable table:
    //   start	length	slot	name	signature
    //   0	198	0	this	wmwmmw
    //   0	198	1	paramRcrccr	rcrccr
    //   0	198	2	paramQqqqqj	qqqqqj
    //   56	58	3	i	int
    //   60	54	4	j	int
    //   65	52	5	k	int
    //   70	50	6	m	int
    //   108	15	7	n	int
    //   16	151	8	localObject	Object
    //   51	90	9	localMmmwmw	mmmwmw
    // Exception table:
    //   from	to	target	type
    //   0	18	186	java/lang/Exception
    //   29	53	186	java/lang/Exception
    //   137	165	186	java/lang/Exception
    //   62	72	189	java/lang/Exception
    //   125	137	189	java/lang/Exception
    //   187	189	189	java/lang/Exception
    //   193	195	189	java/lang/Exception
    //   18	29	192	java/lang/Exception
    //   165	185	192	java/lang/Exception
    //   53	62	195	java/lang/Exception
    //   105	110	195	java/lang/Exception
  }
  
  private void b0430а0430аа0430а043004300430(rcrccr paramRcrccr, @NonNull qqqqqj paramQqqqqj)
  {
    int i = b043D043D043Dн043Dнн043D043D;
    switch (i * (b043Dнн043D043Dнн043D043D + i) % bн043Dн043D043Dнн043D043D)
    {
    default: 
      b043D043D043Dн043Dнн043D043D = b04300430043004300430аа043004300430();
      bннн043D043Dнн043D043D = 40;
    }
    if ((paramQqqqqj.bа04300430а0430а043004300430а() == ccrrcc.MORTGAGE_ACCOUNT) || (paramQqqqqj.bа04300430а0430а043004300430а() == ccrrcc.MORTGAGE_UFSS_ACCOUNT))
    {
      b0430а04300430а0430а043004300430(paramRcrccr, paramQqqqqj);
      return;
    }
    bа0430а0430а0430а043004300430(paramRcrccr, paramQqqqqj);
  }
  
  private Single<ccrrcr> b0430аа0430а0430а043004300430(String paramString, rccrcr paramRccrcr, fbfffb paramFbfffb)
  {
    ccrccr localCcrccr = new ccrccr();
    switch (0)
    {
    case 1: 
    default: 
      for (;;)
      {
        switch (1)
        {
        case 0: 
        default: 
          for (;;)
          {
            switch (1)
            {
            }
          }
        }
        switch (1)
        {
        }
      }
    }
    localCcrccr.b043F043F043F043Fп043Fп043Fпп(paramString);
    paramString = paramRccrcr.toString();
    int i = b043D043D043Dн043Dнн043D043D;
    switch (i * (b043Dнн043D043Dнн043D043D + i) % bн043Dн043D043Dнн043D043D)
    {
    default: 
      b043D043D043Dн043Dнн043D043D = b04300430043004300430аа043004300430();
      bннн043D043Dнн043D043D = b04300430043004300430аа043004300430();
    }
    localCcrccr.b043Fппп043F043Fп043Fпп(paramString);
    localCcrccr.bпппп043F043Fп043Fпп(paramFbfffb.bВВВВВ0412В04120412В());
    paramString = this.b043Dннн043Dнн043D043D;
    paramRccrcr = new rrcrcr(localCcrccr);
    if ((b043D043D043Dн043Dнн043D043D + b043Dнн043D043Dнн043D043D) * b043D043D043Dн043Dнн043D043D % bн043Dн043D043Dнн043D043D != bннн043D043Dнн043D043D)
    {
      b043D043D043Dн043Dнн043D043D = b04300430043004300430аа043004300430();
      bннн043D043Dнн043D043D = 97;
    }
    return paramString.bпп043Fпп043Fп043Fпп(paramRccrcr);
  }
  
  @ooiiio
  private void b0430ааа04300430а043004300430(mmmwwm paramMmmwwm, int paramInt, rrrccr paramRrrccr)
  {
    try
    {
      mwwmww localMwwmww = this.b043D043D043D043Dннн043D043D;
      int i = b043D043D043Dн043Dнн043D043D;
      int j = b043Dнн043D043Dнн043D043D;
      try
      {
        int k = bн043Dн043D043Dнн043D043D;
        switch (i * (j + i) % k)
        {
        default: 
          if ((b043D043D043Dн043Dнн043D043D + b043Dнн043D043Dнн043D043D) * b043D043D043Dн043Dнн043D043D % b0430а043004300430аа043004300430() != bннн043D043Dнн043D043D)
          {
            b043D043D043Dн043Dнн043D043D = b04300430043004300430аа043004300430();
            bннн043D043Dнн043D043D = b04300430043004300430аа043004300430();
          }
          b043D043D043Dн043Dнн043D043D = b04300430043004300430аа043004300430();
          bннн043D043Dнн043D043D = 4;
        }
        paramMmmwwm = paramMmmwwm.b0430а0430043004300430а043004300430();
      }
      catch (Exception paramMmmwwm)
      {
        throw paramMmmwwm;
      }
      localMwwmww.bа04300430аа0430аа04300430(paramMmmwwm, paramInt, paramRrrccr);
      return;
    }
    catch (Exception paramMmmwwm)
    {
      throw paramMmmwwm;
    }
    switch (0)
    {
    }
    for (;;)
    {
      switch (1)
      {
      }
    }
  }
  
  public static int bа0430043004300430аа043004300430()
  {
    return 1;
  }
  
  /* Error */
  private void bа043004300430а0430а043004300430(rcrccr paramRcrccr)
  {
    // Byte code:
    //   0: aload_0
    //   1: getfield 115	kkkkkk/wmwmmw:b042804280428ШШ042804280428Ш	Lkkkkkk/gggggr$grrrrg;
    //   4: astore 5
    //   6: aload 5
    //   8: checkcast 117	kkkkkk/wmmwwm
    //   11: astore 5
    //   13: aload_0
    //   14: getfield 94	kkkkkk/wmwmmw:bн043Dнн043Dнн043D043D	Lkkkkkk/mmmwmw;
    //   17: astore 6
    //   19: aload 5
    //   21: aload 6
    //   23: invokevirtual 324	kkkkkk/mmmwmw:bаааа043004300430а04300430	()Ljava/lang/String;
    //   26: invokeinterface 327 2 0
    //   31: aload_0
    //   32: getfield 115	kkkkkk/wmwmmw:b042804280428ШШ042804280428Ш	Lkkkkkk/gggggr$grrrrg;
    //   35: checkcast 117	kkkkkk/wmmwwm
    //   38: astore 5
    //   40: aload 5
    //   42: aload_0
    //   43: getfield 94	kkkkkk/wmwmmw:bн043Dнн043Dнн043D043D	Lkkkkkk/mmmwmw;
    //   46: aload_1
    //   47: invokevirtual 123	kkkkkk/mmmwmw:bааа0430043004300430а04300430	(Lkkkkkk/rcrccr;)Ljava/lang/String;
    //   50: invokeinterface 127 2 0
    //   55: aload_0
    //   56: getfield 115	kkkkkk/wmwmmw:b042804280428ШШ042804280428Ш	Lkkkkkk/gggggr$grrrrg;
    //   59: checkcast 117	kkkkkk/wmmwwm
    //   62: astore 5
    //   64: getstatic 70	kkkkkk/wmwmmw:b043D043D043Dн043Dнн043D043D	I
    //   67: istore_2
    //   68: iload_2
    //   69: invokestatic 329	kkkkkk/wmwmmw:bа0430043004300430аа043004300430	()I
    //   72: iload_2
    //   73: iadd
    //   74: imul
    //   75: getstatic 74	kkkkkk/wmwmmw:bн043Dн043D043Dнн043D043D	I
    //   78: irem
    //   79: tableswitch	default:+17->96, 0:+28->107
    //   96: invokestatic 78	kkkkkk/wmwmmw:b04300430043004300430аа043004300430	()I
    //   99: putstatic 70	kkkkkk/wmwmmw:b043D043D043Dн043Dнн043D043D	I
    //   102: bipush 59
    //   104: putstatic 80	kkkkkk/wmwmmw:bннн043D043Dнн043D043D	I
    //   107: aload 5
    //   109: aload_0
    //   110: getfield 94	kkkkkk/wmwmmw:bн043Dнн043Dнн043D043D	Lkkkkkk/mmmwmw;
    //   113: aload_1
    //   114: invokevirtual 130	kkkkkk/mmmwmw:b0430а04300430а04300430а04300430	(Lkkkkkk/rcrccr;)Ljava/lang/String;
    //   117: aload_0
    //   118: getfield 132	kkkkkk/wmwmmw:bнн043Dн043Dнн043D043D	Z
    //   121: invokeinterface 136 3 0
    //   126: aload_0
    //   127: getfield 115	kkkkkk/wmwmmw:b042804280428ШШ042804280428Ш	Lkkkkkk/gggggr$grrrrg;
    //   130: checkcast 117	kkkkkk/wmmwwm
    //   133: astore_1
    //   134: aload_0
    //   135: getfield 94	kkkkkk/wmwmmw:bн043Dнн043Dнн043D043D	Lkkkkkk/mmmwmw;
    //   138: invokevirtual 332	kkkkkk/mmmwmw:bа04300430а043004300430а04300430	()Ljava/lang/String;
    //   141: astore 5
    //   143: aload_1
    //   144: aload 5
    //   146: aload_0
    //   147: getfield 94	kkkkkk/wmwmmw:bн043Dнн043Dнн043D043D	Lkkkkkk/mmmwmw;
    //   150: invokevirtual 335	kkkkkk/mmmwmw:bаа04300430а04300430а04300430	()Ljava/lang/String;
    //   153: invokeinterface 155 3 0
    //   158: aload_0
    //   159: getfield 115	kkkkkk/wmwmmw:b042804280428ШШ042804280428Ш	Lkkkkkk/gggggr$grrrrg;
    //   162: astore_1
    //   163: getstatic 70	kkkkkk/wmwmmw:b043D043D043Dн043Dнн043D043D	I
    //   166: istore_2
    //   167: getstatic 72	kkkkkk/wmwmmw:b043Dнн043D043Dнн043D043D	I
    //   170: istore_3
    //   171: getstatic 74	kkkkkk/wmwmmw:bн043Dн043D043Dнн043D043D	I
    //   174: istore 4
    //   176: iload_2
    //   177: iload_3
    //   178: iload_2
    //   179: iadd
    //   180: imul
    //   181: iload 4
    //   183: irem
    //   184: tableswitch	default:+20->204, 0:+31->215
    //   204: invokestatic 78	kkkkkk/wmwmmw:b04300430043004300430аа043004300430	()I
    //   207: putstatic 70	kkkkkk/wmwmmw:b043D043D043Dн043Dнн043D043D	I
    //   210: bipush 86
    //   212: putstatic 80	kkkkkk/wmwmmw:bннн043D043Dнн043D043D	I
    //   215: aload_1
    //   216: checkcast 117	kkkkkk/wmmwwm
    //   219: invokeinterface 162 1 0
    //   224: return
    //   225: astore_1
    //   226: aload_1
    //   227: athrow
    //   228: astore_1
    //   229: aload_1
    //   230: athrow
    // Local variable table:
    //   start	length	slot	name	signature
    //   0	231	0	this	wmwmmw
    //   0	231	1	paramRcrccr	rcrccr
    //   67	114	2	i	int
    //   170	10	3	j	int
    //   174	10	4	k	int
    //   4	141	5	localObject	Object
    //   17	5	6	localMmmwmw	mmmwmw
    // Exception table:
    //   from	to	target	type
    //   6	19	225	java/lang/Exception
    //   40	64	225	java/lang/Exception
    //   107	134	225	java/lang/Exception
    //   143	176	225	java/lang/Exception
    //   210	215	225	java/lang/Exception
    //   0	6	228	java/lang/Exception
    //   19	40	228	java/lang/Exception
    //   134	143	228	java/lang/Exception
    //   204	210	228	java/lang/Exception
    //   215	224	228	java/lang/Exception
  }
  
  /* Error */
  private void bа0430а0430а0430а043004300430(rcrccr paramRcrccr, qqqqqj paramQqqqqj)
  {
    // Byte code:
    //   0: aload_0
    //   1: getfield 115	kkkkkk/wmwmmw:b042804280428ШШ042804280428Ш	Lkkkkkk/gggggr$grrrrg;
    //   4: checkcast 117	kkkkkk/wmmwwm
    //   7: aload_0
    //   8: getfield 94	kkkkkk/wmwmmw:bн043Dнн043Dнн043D043D	Lkkkkkk/mmmwmw;
    //   11: invokevirtual 340	kkkkkk/mmmwmw:b0430043004300430а04300430а04300430	()Ljava/lang/String;
    //   14: invokeinterface 327 2 0
    //   19: aload_0
    //   20: getfield 115	kkkkkk/wmwmmw:b042804280428ШШ042804280428Ш	Lkkkkkk/gggggr$grrrrg;
    //   23: checkcast 117	kkkkkk/wmmwwm
    //   26: invokeinterface 229 1 0
    //   31: aload_0
    //   32: getfield 115	kkkkkk/wmwmmw:b042804280428ШШ042804280428Ш	Lkkkkkk/gggggr$grrrrg;
    //   35: checkcast 117	kkkkkk/wmmwwm
    //   38: aload_2
    //   39: invokeinterface 233 2 0
    //   44: aload_0
    //   45: getfield 115	kkkkkk/wmwmmw:b042804280428ШШ042804280428Ш	Lkkkkkk/gggggr$grrrrg;
    //   48: checkcast 117	kkkkkk/wmmwwm
    //   51: astore_2
    //   52: aload_0
    //   53: getfield 94	kkkkkk/wmwmmw:bн043Dнн043Dнн043D043D	Lkkkkkk/mmmwmw;
    //   56: astore 4
    //   58: getstatic 70	kkkkkk/wmwmmw:b043D043D043Dн043Dнн043D043D	I
    //   61: getstatic 72	kkkkkk/wmwmmw:b043Dнн043D043Dнн043D043D	I
    //   64: iadd
    //   65: getstatic 70	kkkkkk/wmwmmw:b043D043D043Dн043Dнн043D043D	I
    //   68: imul
    //   69: getstatic 74	kkkkkk/wmwmmw:bн043Dн043D043Dнн043D043D	I
    //   72: irem
    //   73: getstatic 80	kkkkkk/wmwmmw:bннн043D043Dнн043D043D	I
    //   76: if_icmpeq +58 -> 134
    //   79: invokestatic 78	kkkkkk/wmwmmw:b04300430043004300430аа043004300430	()I
    //   82: putstatic 70	kkkkkk/wmwmmw:b043D043D043Dн043Dнн043D043D	I
    //   85: bipush 76
    //   87: putstatic 80	kkkkkk/wmwmmw:bннн043D043Dнн043D043D	I
    //   90: getstatic 70	kkkkkk/wmwmmw:b043D043D043Dн043Dнн043D043D	I
    //   93: istore_3
    //   94: iload_3
    //   95: invokestatic 329	kkkkkk/wmwmmw:bа0430043004300430аа043004300430	()I
    //   98: iload_3
    //   99: iadd
    //   100: imul
    //   101: getstatic 74	kkkkkk/wmwmmw:bн043Dн043D043Dнн043D043D	I
    //   104: irem
    //   105: tableswitch	default:+19->124, 0:+29->134
    //   124: iconst_0
    //   125: putstatic 70	kkkkkk/wmwmmw:b043D043D043Dн043Dнн043D043D	I
    //   128: invokestatic 78	kkkkkk/wmwmmw:b04300430043004300430аа043004300430	()I
    //   131: putstatic 80	kkkkkk/wmwmmw:bннн043D043Dнн043D043D	I
    //   134: aload 4
    //   136: aload_1
    //   137: invokevirtual 213	kkkkkk/mmmwmw:bаа0430а043004300430а04300430	(Lkkkkkk/rcrccr;)Ljava/lang/String;
    //   140: astore 4
    //   142: aload_2
    //   143: aload 4
    //   145: aload_0
    //   146: getfield 94	kkkkkk/wmwmmw:bн043Dнн043Dнн043D043D	Lkkkkkk/mmmwmw;
    //   149: aload_1
    //   150: invokevirtual 216	kkkkkk/mmmwmw:bа0430а0430а04300430а04300430	(Lkkkkkk/rcrccr;)Ljava/lang/String;
    //   153: invokeinterface 155 3 0
    //   158: return
    //   159: astore_1
    //   160: aload_1
    //   161: athrow
    //   162: astore_1
    //   163: aload_1
    //   164: athrow
    // Local variable table:
    //   start	length	slot	name	signature
    //   0	165	0	this	wmwmmw
    //   0	165	1	paramRcrccr	rcrccr
    //   0	165	2	paramQqqqqj	qqqqqj
    //   93	8	3	i	int
    //   56	88	4	localObject	Object
    // Exception table:
    //   from	to	target	type
    //   52	58	159	java/lang/Exception
    //   142	158	159	java/lang/Exception
    //   0	52	162	java/lang/Exception
    //   134	142	162	java/lang/Exception
  }
  
  /* Error */
  @ooiiio
  private void bа0430аа04300430а043004300430()
  {
    // Byte code:
    //   0: iconst_1
    //   1: tableswitch	default:+23->24, 0:+-1->0, 1:+50->51
    //   24: iconst_1
    //   25: tableswitch	default:+23->48, 0:+-25->0, 1:+26->51
    //   48: goto -24 -> 24
    //   51: aload_0
    //   52: getfield 106	kkkkkk/wmwmmw:b043D043D043D043Dннн043D043D	Lkkkkkk/mwwmww;
    //   55: astore 6
    //   57: getstatic 70	kkkkkk/wmwmmw:b043D043D043Dн043Dнн043D043D	I
    //   60: istore_1
    //   61: iload_1
    //   62: invokestatic 329	kkkkkk/wmwmmw:bа0430043004300430аа043004300430	()I
    //   65: iload_1
    //   66: iadd
    //   67: imul
    //   68: getstatic 74	kkkkkk/wmwmmw:bн043Dн043D043Dнн043D043D	I
    //   71: irem
    //   72: tableswitch	default:+20->92, 0:+31->103
    //   92: invokestatic 78	kkkkkk/wmwmmw:b04300430043004300430аа043004300430	()I
    //   95: putstatic 70	kkkkkk/wmwmmw:b043D043D043Dн043Dнн043D043D	I
    //   98: bipush 46
    //   100: putstatic 80	kkkkkk/wmwmmw:bннн043D043Dнн043D043D	I
    //   103: getstatic 70	kkkkkk/wmwmmw:b043D043D043Dн043Dнн043D043D	I
    //   106: istore_1
    //   107: getstatic 72	kkkkkk/wmwmmw:b043Dнн043D043Dнн043D043D	I
    //   110: istore_2
    //   111: getstatic 70	kkkkkk/wmwmmw:b043D043D043Dн043Dнн043D043D	I
    //   114: istore_3
    //   115: invokestatic 197	kkkkkk/wmwmmw:b0430а043004300430аа043004300430	()I
    //   118: istore 4
    //   120: invokestatic 236	kkkkkk/wmwmmw:bаа043004300430аа043004300430	()I
    //   123: istore 5
    //   125: iload_1
    //   126: iload_2
    //   127: iadd
    //   128: iload_3
    //   129: imul
    //   130: iload 4
    //   132: irem
    //   133: iload 5
    //   135: if_icmpeq +14 -> 149
    //   138: invokestatic 78	kkkkkk/wmwmmw:b04300430043004300430аа043004300430	()I
    //   141: putstatic 70	kkkkkk/wmwmmw:b043D043D043Dн043Dнн043D043D	I
    //   144: bipush 87
    //   146: putstatic 80	kkkkkk/wmwmmw:bннн043D043Dнн043D043D	I
    //   149: aload 6
    //   151: invokevirtual 343	kkkkkk/mwwmww:bаа04300430а0430аа04300430	()V
    //   154: return
    //   155: astore 6
    //   157: aload 6
    //   159: athrow
    //   160: astore 6
    //   162: aload 6
    //   164: athrow
    // Local variable table:
    //   start	length	slot	name	signature
    //   0	165	0	this	wmwmmw
    //   60	68	1	i	int
    //   110	18	2	j	int
    //   114	16	3	k	int
    //   118	15	4	m	int
    //   123	13	5	n	int
    //   55	95	6	localMwwmww	mwwmww
    //   155	3	6	localException1	Exception
    //   160	3	6	localException2	Exception
    // Exception table:
    //   from	to	target	type
    //   51	57	155	java/lang/Exception
    //   103	125	155	java/lang/Exception
    //   149	154	155	java/lang/Exception
    //   138	149	160	java/lang/Exception
  }
  
  private Maybe<String> bа0430ааа0430а043004300430(mmmwwm paramMmmwwm)
  {
    if (paramMmmwwm.b0430а0430043004300430а043004300430() == rcrccr.ARRANGEMENTS) {}
    Maybe localMaybe;
    for (paramMmmwwm = this.b043Dннн043Dнн043D043D.b043F043Fп043F043Fпп043Fпп(paramMmmwwm.bаа0430043004300430а043004300430());; paramMmmwwm = localMaybe)
    {
      switch (0)
      {
      case 1: 
      default: 
        for (;;)
        {
          switch (0)
          {
          }
        }
      }
      return paramMmmwwm;
      localMaybe = this.b043Dннн043Dнн043D043D.b043Fп043F043F043Fпп043Fпп();
      if ((b043D043D043Dн043Dнн043D043D + b043Dнн043D043Dнн043D043D) * b043D043D043Dн043Dнн043D043D % bн043Dн043D043Dнн043D043D != bннн043D043Dнн043D043D)
      {
        b043D043D043Dн043Dнн043D043D = 24;
        bннн043D043Dнн043D043D = 41;
      }
      int i = b04300430043004300430аа043004300430();
      paramMmmwwm = localMaybe;
      switch (i * (b043Dнн043D043Dнн043D043D + i) % bн043Dн043D043Dнн043D043D)
      {
      }
      b043D043D043Dн043Dнн043D043D = 33;
      bннн043D043Dнн043D043D = 16;
    }
  }
  
  public static int bаа043004300430аа043004300430()
  {
    return 0;
  }
  
  private void bаа04300430а0430а043004300430(rcrccr paramRcrccr)
  {
    ((wmmwwm)this.b042804280428ШШ042804280428Ш).showOpenAllHours(this.bн043Dнн043Dнн043D043D.b0430043004300430а04300430а04300430());
    switch (1)
    {
    case 0: 
    default: 
      for (;;)
      {
        switch (1)
        {
        }
      }
    }
    ((wmmwwm)this.b042804280428ШШ042804280428Ш).showTitle(this.bн043Dнн043Dнн043D043D.bааа0430043004300430а04300430(paramRcrccr));
    int i = b043D043D043Dн043Dнн043D043D;
    switch (i * (b043Dнн043D043Dнн043D043D + i) % bн043Dн043D043Dнн043D043D)
    {
    default: 
      b043D043D043Dн043Dнн043D043D = b04300430043004300430аа043004300430();
      bннн043D043Dнн043D043D = 26;
    }
    ((wmmwwm)this.b042804280428ШШ042804280428Ш).setTextphoneContent(this.bн043Dнн043Dнн043D043D.bаа0430а043004300430а04300430(paramRcrccr), this.bн043Dнн043Dнн043D043D.bа0430а0430а04300430а04300430(paramRcrccr));
    ((wmmwwm)this.b042804280428ШШ042804280428Ш).inflateCallDescriptionText(this.bн043Dнн043Dнн043D043D.b0430а04300430а04300430а04300430(paramRcrccr), this.bнн043Dн043Dнн043D043D);
    if ((b043D043D043Dн043Dнн043D043D + b043Dнн043D043Dнн043D043D) * b043D043D043Dн043Dнн043D043D % bн043Dн043D043Dнн043D043D != bннн043D043Dнн043D043D)
    {
      b043D043D043Dн043Dнн043D043D = 58;
      bннн043D043Dнн043D043D = b04300430043004300430аа043004300430();
    }
  }
  
  /* Error */
  @NonNull
  private rccrcr bаа0430аа0430а043004300430(mmmwwm paramMmmwwm)
  {
    // Byte code:
    //   0: aload_1
    //   1: invokevirtual 310	kkkkkk/mmmwwm:b0430а0430043004300430а043004300430	()Lkkkkkk/rcrccr;
    //   4: astore 5
    //   6: aload 5
    //   8: getstatic 353	kkkkkk/rcrccr:ARRANGEMENTS	Lkkkkkk/rcrccr;
    //   11: if_acmpne +11 -> 22
    //   14: aload_1
    //   15: invokevirtual 357	kkkkkk/mmmwwm:bаа0430043004300430а043004300430	()Lkkkkkk/cccrcc;
    //   18: invokestatic 374	kkkkkk/rccrcr:bп043Fп043Fпп043F043Fпп	(Lkkkkkk/cccrcc;)Lkkkkkk/rccrcr;
    //   21: areturn
    //   22: getstatic 377	kkkkkk/rcrccr:CHANGE_OF_ADDRESS	Lkkkkkk/rcrccr;
    //   25: astore_1
    //   26: getstatic 70	kkkkkk/wmwmmw:b043D043D043Dн043Dнн043D043D	I
    //   29: istore_2
    //   30: getstatic 72	kkkkkk/wmwmmw:b043Dнн043D043Dнн043D043D	I
    //   33: istore_3
    //   34: invokestatic 197	kkkkkk/wmwmmw:b0430а043004300430аа043004300430	()I
    //   37: istore 4
    //   39: iload_2
    //   40: iload_3
    //   41: iload_2
    //   42: iadd
    //   43: imul
    //   44: iload 4
    //   46: irem
    //   47: tableswitch	default:+17->64, 0:+59->106
    //   64: getstatic 70	kkkkkk/wmwmmw:b043D043D043Dн043Dнн043D043D	I
    //   67: getstatic 72	kkkkkk/wmwmmw:b043Dнн043D043Dнн043D043D	I
    //   70: iadd
    //   71: getstatic 70	kkkkkk/wmwmmw:b043D043D043Dн043Dнн043D043D	I
    //   74: imul
    //   75: getstatic 74	kkkkkk/wmwmmw:bн043Dн043D043Dнн043D043D	I
    //   78: irem
    //   79: getstatic 80	kkkkkk/wmwmmw:bннн043D043Dнн043D043D	I
    //   82: if_icmpeq +13 -> 95
    //   85: bipush 37
    //   87: putstatic 70	kkkkkk/wmwmmw:b043D043D043Dн043Dнн043D043D	I
    //   90: bipush 20
    //   92: putstatic 80	kkkkkk/wmwmmw:bннн043D043Dнн043D043D	I
    //   95: bipush 48
    //   97: putstatic 70	kkkkkk/wmwmmw:b043D043D043Dн043Dнн043D043D	I
    //   100: invokestatic 78	kkkkkk/wmwmmw:b04300430043004300430аа043004300430	()I
    //   103: putstatic 80	kkkkkk/wmwmmw:bннн043D043Dнн043D043D	I
    //   106: aload 5
    //   108: aload_1
    //   109: if_acmpne +22 -> 131
    //   112: aload_0
    //   113: invokevirtual 380	kkkkkk/wmwmmw:b0430аааа0430а043004300430	()Z
    //   116: ifeq +11 -> 127
    //   119: aload 5
    //   121: invokestatic 384	kkkkkk/rccrcr:b043F043Fп043Fпп043F043Fпп	(Lkkkkkk/rcrccr;)Lkkkkkk/rccrcr;
    //   124: astore_1
    //   125: aload_1
    //   126: areturn
    //   127: getstatic 388	kkkkkk/rccrcr:NO_ROUTING_CODE	Lkkkkkk/rccrcr;
    //   130: areturn
    //   131: aload 5
    //   133: invokestatic 384	kkkkkk/rccrcr:b043F043Fп043Fпп043F043Fпп	(Lkkkkkk/rcrccr;)Lkkkkkk/rccrcr;
    //   136: astore_1
    //   137: aload_1
    //   138: areturn
    //   139: astore_1
    //   140: aload_1
    //   141: athrow
    //   142: astore_1
    //   143: aload_1
    //   144: athrow
    //   145: astore_1
    //   146: aload_1
    //   147: athrow
    //   148: astore_1
    //   149: aload_1
    //   150: athrow
    // Local variable table:
    //   start	length	slot	name	signature
    //   0	151	0	this	wmwmmw
    //   0	151	1	paramMmmwwm	mmmwwm
    //   29	15	2	i	int
    //   33	10	3	j	int
    //   37	10	4	k	int
    //   4	128	5	localRcrccr	rcrccr
    // Exception table:
    //   from	to	target	type
    //   0	22	139	java/lang/Exception
    //   22	26	139	java/lang/Exception
    //   112	125	139	java/lang/Exception
    //   140	142	142	java/lang/Exception
    //   146	148	142	java/lang/Exception
    //   127	131	145	java/lang/Exception
    //   131	137	145	java/lang/Exception
    //   26	39	148	java/lang/Exception
    //   95	106	148	java/lang/Exception
  }
  
  private void bааааа0430а043004300430(final rccrcr paramRccrcr, final mmmwwm paramMmmwwm)
  {
    b04180418И0418ИИИ0418ИИ(this.b043D043Dнн043Dнн043D043D.bВВ041204120412В0412В0412В().subscribe(new Consumer()new rgrrrg.rgrgrg
    {
      public static int b043D043D043D043D043Dнн043D043D = 0;
      public static int b043Dнннн043Dн043D043D = 2;
      public static int bн043D043D043D043Dнн043D043D = 50;
      public static int bннннн043Dн043D043D = 1;
      
      public static int b0430043004300430043004300430а04300430()
      {
        return 74;
      }
      
      public static int bааааааа043004300430()
      {
        return 0;
      }
      
      public void bа043004300430043004300430а04300430(@NonNull fbfffb paramAnonymousFbfffb)
        throws Exception
      {
        label176:
        for (;;)
        {
          try
          {
            if (!wmwmmw.b0430ааа0430аа043004300430(wmwmmw.this).bп043F043F043F043Fпп043Fпп(paramAnonymousFbfffb)) {
              break;
            }
            if ((wmwmmw.b0430ааа0430аа043004300430(wmwmmw.this).bппппп043Fп043Fпп(paramAnonymousFbfffb)) && (paramRccrcr != rccrcr.NO_ROUTING_CODE))
            {
              wmwmmw.bа0430аа0430аа043004300430(wmwmmw.this, paramRccrcr, paramMmmwwm, paramAnonymousFbfffb);
              return;
            }
            Object localObject = wmwmmw.this;
            if ((bн043D043D043D043Dнн043D043D + bннннн043Dн043D043D) * bн043D043D043D043Dнн043D043D % b043Dнннн043Dн043D043D != b043D043D043D043D043Dнн043D043D)
            {
              bн043D043D043D043Dнн043D043D = 34;
              b043D043D043D043D043Dнн043D043D = b0430043004300430043004300430а04300430();
            }
            localObject = wmwmmw.b0430ааа0430аа043004300430((wmwmmw)localObject);
            int i;
            paramAnonymousFbfffb = rrrccr.OTHER;
          }
          catch (Exception paramAnonymousFbfffb)
          {
            try
            {
              if (!((rrrrrc)localObject).b043Fпппп043Fп043Fпп(paramAnonymousFbfffb)) {
                break label176;
              }
              paramAnonymousFbfffb = rrrccr.IN_GRACE_PERIOD;
              localObject = wmwmmw.this;
              i = bн043D043D043D043Dнн043D043D;
              switch (i * (bннннн043Dн043D043D + i) % b043Dнннн043Dн043D043D)
              {
              default: 
                bн043D043D043D043Dнн043D043D = 42;
                b043D043D043D043D043Dнн043D043D = 53;
              }
              ((wmwmmw)localObject).bаааа04300430а043004300430(3, paramMmmwwm, null, paramAnonymousFbfffb);
              return;
            }
            catch (Exception paramAnonymousFbfffb)
            {
              throw paramAnonymousFbfffb;
            }
            paramAnonymousFbfffb = paramAnonymousFbfffb;
            throw paramAnonymousFbfffb;
          }
        }
        wmwmmw.b04300430аа0430аа043004300430(wmwmmw.this);
        ((wmmwwm)wmwmmw.bаа0430а0430аа043004300430(wmwmmw.this)).showNumberNotRegisteredDialog();
      }
    }, new rgrrrg.rgrgrg(paramMmmwwm)
    {
      public static int b043D043D043Dнн043Dн043D043D = 20;
      public static int b043Dн043Dнн043Dн043D043D = 1;
      public static int bн043D043Dнн043Dн043D043D = 2;
      public static int bнн043Dнн043Dн043D043D;
      
      public static int b0430аааааа043004300430()
      {
        return 32;
      }
      
      public static int bа0430ааааа043004300430()
      {
        return 2;
      }
      
      public boolean b04300430ааааа043004300430(@NonNull uuunun paramAnonymousUuunun)
      {
        try
        {
          int i = b0430аааааа043004300430();
          int j = b043Dн043Dнн043Dн043D043D;
          try
          {
            int k = b0430аааааа043004300430();
            int m = bн043D043Dнн043Dн043D043D;
            int n = bнн043Dнн043Dн043D043D;
            if ((i + j) * k % m != n)
            {
              bнн043Dнн043Dн043D043D = 26;
              i = b043D043D043Dнн043Dн043D043D;
              switch (i * (b043Dн043Dнн043Dн043D043D + i) % bа0430ааааа043004300430())
              {
              default: 
                b043D043D043Dнн043Dн043D043D = b0430аааааа043004300430();
                bнн043Dнн043Dн043D043D = b0430аааааа043004300430();
              }
            }
            paramAnonymousUuunun = wmwmmw.this;
            localMmmwwm = paramMmmwwm;
            localRrrccr = rrrccr.GALAXY_ERROR;
          }
          catch (Exception paramAnonymousUuunun)
          {
            mmmwwm localMmmwwm;
            rrrccr localRrrccr;
            throw paramAnonymousUuunun;
          }
          paramAnonymousUuunun.bаааа04300430а043004300430(3, localMmmwwm, null, localRrrccr);
          return true;
        }
        catch (Exception paramAnonymousUuunun)
        {
          throw paramAnonymousUuunun;
        }
        switch (0)
        {
        }
        for (;;)
        {
          switch (1)
          {
          }
        }
      }
    }));
  }
  
  public void b043004300430аа0430а043004300430(String paramString)
  {
    try
    {
      this.bнннн043Dнн043D043D.b04360436ж0436ж0436жжж0436(paramString).subscribe(this);
      return;
    }
    catch (Exception paramString)
    {
      throw paramString;
    }
  }
  
  public void b04300430аа04300430а043004300430(rcrccr paramRcrccr, @Nullable ccrrcc paramCcrrcc)
  {
    switch (8.bннн043Dнн043D043D043D[paramRcrccr.ordinal()])
    {
    default: 
      paramRcrccr = new IllegalArgumentException(gguuuu.bккккк043Aкк043A043A("b\\Z^`ia\024iog]3\032", 'l', '\000') + paramRcrccr);
      if ((b043D043D043Dн043Dнн043D043D + bа0430043004300430аа043004300430()) * b043D043D043Dн043Dнн043D043D % b0430а043004300430аа043004300430() != bннн043D043Dнн043D043D)
      {
        switch (0)
        {
        case 1: 
        default: 
          for (;;)
          {
            switch (0)
            {
            }
          }
        }
        b043D043D043Dн043Dнн043D043D = b04300430043004300430аа043004300430();
        bннн043D043Dнн043D043D = b04300430043004300430аа043004300430();
      }
      throw paramRcrccr;
    case 2: 
    case 3: 
    case 4: 
    case 5: 
    case 6: 
    case 7: 
      for (;;)
      {
        switch (1)
        {
        default: 
          break;
        case 0: 
          switch (0)
          {
          }
          break;
        }
      }
      this.b043D043D043D043Dннн043D043D.b0430аа0430а0430аа04300430(paramRcrccr);
      return;
    case 8: 
    case 9: 
    case 10: 
    case 11: 
    case 12: 
    case 13: 
    case 14: 
    case 15: 
      this.b043D043D043D043Dннн043D043D.b043004300430аа0430аа04300430(paramRcrccr);
      return;
    }
    this.b043D043D043D043Dннн043D043D.bааа0430а0430аа04300430(paramCcrrcc);
    int i = b04300430043004300430аа043004300430();
    switch (i * (b043Dнн043D043Dнн043D043D + i) % bн043Dн043D043Dнн043D043D)
    {
    }
    b043D043D043Dн043Dнн043D043D = 57;
    bннн043D043Dнн043D043D = b04300430043004300430аа043004300430();
  }
  
  /* Error */
  @ooiiio("Trivial")
  public String b04300430ааа0430а043004300430(mmmwwm paramMmmwwm)
  {
    // Byte code:
    //   0: iconst_2
    //   1: istore_2
    //   2: new 463	java/lang/NullPointerException
    //   5: dup
    //   6: invokespecial 464	java/lang/NullPointerException:<init>	()V
    //   9: athrow
    //   10: astore_3
    //   11: invokestatic 78	kkkkkk/wmwmmw:b04300430043004300430аа043004300430	()I
    //   14: putstatic 70	kkkkkk/wmwmmw:b043D043D043Dн043Dнн043D043D	I
    //   17: iload_2
    //   18: iconst_0
    //   19: idiv
    //   20: istore_2
    //   21: goto -4 -> 17
    //   24: astore_3
    //   25: invokestatic 78	kkkkkk/wmwmmw:b04300430043004300430аа043004300430	()I
    //   28: putstatic 70	kkkkkk/wmwmmw:b043D043D043Dн043Dнн043D043D	I
    //   31: aload_0
    //   32: getfield 100	kkkkkk/wmwmmw:b043Dн043Dн043Dнн043D043D	Lkkkkkk/wwmwmw;
    //   35: aload_1
    //   36: invokevirtual 469	kkkkkk/wwmwmw:b0430а043004300430а0430а04300430	(Lkkkkkk/mmmwwm;)Ljava/lang/String;
    //   39: astore_1
    //   40: aload_1
    //   41: areturn
    //   42: astore_1
    //   43: aload_1
    //   44: athrow
    //   45: astore_1
    //   46: aload_1
    //   47: athrow
    //   48: astore_1
    //   49: aload_1
    //   50: athrow
    // Local variable table:
    //   start	length	slot	name	signature
    //   0	51	0	this	wmwmmw
    //   0	51	1	paramMmmwwm	mmmwwm
    //   1	20	2	i	int
    //   10	1	3	localException1	Exception
    //   24	1	3	localException2	Exception
    // Exception table:
    //   from	to	target	type
    //   2	10	10	java/lang/Exception
    //   17	21	24	java/lang/Exception
    //   31	40	42	java/lang/Exception
    //   43	45	45	java/lang/Exception
    //   11	17	48	java/lang/Exception
    //   25	31	48	java/lang/Exception
  }
  
  @VisibleForTesting
  public boolean b0430аааа0430а043004300430()
  {
    Iterator localIterator = this.bнннн043Dнн043D043D.b0436ж04360436ж0436жжж0436().bпп043F043F043Fппппп().iterator();
    for (;;)
    {
      switch (0)
      {
      case 1: 
      default: 
        for (;;)
        {
          switch (1)
          {
          }
        }
      }
      if (!localIterator.hasNext()) {
        break;
      }
      ccrrcc localCcrrcc = ((cccrcc)localIterator.next()).bжж04360436жжжж04360436();
      int[] arrayOfInt = 8.b043D043D043Dннн043D043D043D;
      if ((b043D043D043Dн043Dнн043D043D + b043Dнн043D043Dнн043D043D) * b043D043D043Dн043Dнн043D043D % bн043Dн043D043Dнн043D043D != bннн043D043Dнн043D043D)
      {
        b043D043D043Dн043Dнн043D043D = 60;
        bннн043D043Dнн043D043D = 3;
      }
      switch (arrayOfInt[localCcrrcc.ordinal()])
      {
      }
    }
    if ((b043D043D043Dн043Dнн043D043D + b043Dнн043D043Dнн043D043D) * b043D043D043Dн043Dнн043D043D % bн043Dн043D043Dнн043D043D != bннн043D043Dнн043D043D)
    {
      b043D043D043Dн043Dнн043D043D = b04300430043004300430аа043004300430();
      bннн043D043Dнн043D043D = b04300430043004300430аа043004300430();
      return true;
      return false;
    }
    return true;
  }
  
  public void bа04300430аа0430а043004300430(rcrccr paramRcrccr, boolean paramBoolean)
  {
    switch (0)
    {
    case 1: 
    default: 
      for (;;)
      {
        switch (1)
        {
        }
      }
    }
    this.bнн043Dн043Dнн043D043D = paramBoolean;
    if (paramRcrccr == rcrccr.ARRANGEMENTS) {
      ((wmmwwm)this.b042804280428ШШ042804280428Ш).setCallDescriptionArrangementTile();
    }
    while (this.bнн043Dн043Dнн043D043D)
    {
      ((wmmwwm)this.b042804280428ШШ042804280428Ш).initializeAuthenticatedCallUsButton();
      return;
      ((wmmwwm)this.b042804280428ШШ042804280428Ш).setViewModel(new mmmwwm(paramRcrccr));
      try
      {
        throw new NullPointerException();
      }
      catch (Exception localException)
      {
        b043D043D043Dн043Dнн043D043D = b04300430043004300430аа043004300430();
        bаа0430а04300430а043004300430(paramRcrccr, null);
      }
    }
    switch (0)
    {
    case 1: 
    default: 
      for (;;)
      {
        switch (0)
        {
        }
      }
    }
    ((wmmwwm)this.b042804280428ШШ042804280428Ш).initializeUnauthenticatedCallUsButton();
  }
  
  public void bа0430а04300430аа043004300430(mmmwwm paramMmmwwm)
  {
    try
    {
      localObject = bаа0430аа0430а043004300430(paramMmmwwm);
      boolean bool = this.bнн043Dн043Dнн043D043D;
      if (!bool) {}
    }
    catch (Exception paramMmmwwm)
    {
      Object localObject;
      int i;
      throw paramMmmwwm;
    }
    try
    {
      bааааа0430а043004300430((rccrcr)localObject, paramMmmwwm);
      return;
    }
    catch (Exception paramMmmwwm)
    {
      throw paramMmmwwm;
    }
    i = b04300430043004300430аа043004300430();
    switch (i * (b043Dнн043D043Dнн043D043D + i) % bн043Dн043D043Dнн043D043D)
    {
    }
    for (;;)
    {
      b043D043D043Dн043Dнн043D043D = 50;
      bннн043D043Dнн043D043D = 38;
      if ((b04300430043004300430аа043004300430() + b043Dнн043D043Dнн043D043D) * b04300430043004300430аа043004300430() % bн043Dн043D043Dнн043D043D != bннн043D043Dнн043D043D)
      {
        b043D043D043Dн043Dнн043D043D = b04300430043004300430аа043004300430();
        bннн043D043Dнн043D043D = b04300430043004300430аа043004300430();
      }
      localObject = rrrccr.OTHER;
      bаааа04300430а043004300430(3, paramMmmwwm, null, (rrrccr)localObject);
      return;
    }
  }
  
  public void bаа0430а04300430а043004300430(rcrccr paramRcrccr, @Nullable qqqqqj paramQqqqqj)
  {
    switch (8.bннн043Dнн043D043D043D[paramRcrccr.ordinal()])
    {
    default: 
      bаа04300430а0430а043004300430(paramRcrccr);
      return;
    case 2: 
    case 3: 
    case 4: 
    case 5: 
    case 6: 
    case 7: 
      switch (1)
      {
      case 0: 
      default: 
        for (;;)
        {
          i = b043D043D043Dн043Dнн043D043D;
          switch (i * (bа0430043004300430аа043004300430() + i) % b0430а043004300430аа043004300430())
          {
          default: 
            b043D043D043Dн043Dнн043D043D = 3;
            bннн043D043Dнн043D043D = 59;
          }
          switch (0)
          {
          }
        }
      }
      b0430043004300430а0430а043004300430(paramRcrccr);
      int i = b043D043D043Dн043Dнн043D043D;
      switch (i * (b043Dнн043D043Dнн043D043D + i) % bн043Dн043D043Dнн043D043D)
      {
      }
      b043D043D043Dн043Dнн043D043D = b04300430043004300430аа043004300430();
      bннн043D043Dнн043D043D = 84;
      return;
    case 8: 
      bа043004300430а0430а043004300430(paramRcrccr);
      return;
    case 9: 
      b04300430а0430а0430а043004300430(paramRcrccr);
      return;
    }
    b0430а0430аа0430а043004300430(paramRcrccr, paramQqqqqj);
  }
  
  /* Error */
  public void bааа0430а0430а043004300430(cccrcc paramCccrcc)
  {
    // Byte code:
    //   0: invokestatic 78	kkkkkk/wmwmmw:b04300430043004300430аа043004300430	()I
    //   3: istore_2
    //   4: iload_2
    //   5: getstatic 72	kkkkkk/wmwmmw:b043Dнн043D043Dнн043D043D	I
    //   8: iload_2
    //   9: iadd
    //   10: imul
    //   11: getstatic 74	kkkkkk/wmwmmw:bн043Dн043D043Dнн043D043D	I
    //   14: irem
    //   15: tableswitch	default:+17->32, 0:+27->42
    //   32: invokestatic 78	kkkkkk/wmwmmw:b04300430043004300430аа043004300430	()I
    //   35: putstatic 70	kkkkkk/wmwmmw:b043D043D043Dн043Dнн043D043D	I
    //   38: iconst_2
    //   39: putstatic 80	kkkkkk/wmwmmw:bннн043D043Dнн043D043D	I
    //   42: new 246	kkkkkk/qqqqqj
    //   45: dup
    //   46: aload_1
    //   47: iconst_0
    //   48: new 553	kkkkkk/qqqqqj$qjjjjq
    //   51: dup
    //   52: iconst_0
    //   53: getstatic 558	com/mobile/ui/R$string:accessibility_arrangementsummary_account_name_prefix_for_callus	I
    //   56: iconst_0
    //   57: invokespecial 561	kkkkkk/qqqqqj$qjjjjq:<init>	(ZII)V
    //   60: invokespecial 564	kkkkkk/qqqqqj:<init>	(Lkkkkkk/cccrcc;ZLkkkkkk/qqqqqj$qjjjjq;)V
    //   63: astore 4
    //   65: aload_0
    //   66: getfield 115	kkkkkk/wmwmmw:b042804280428ШШ042804280428Ш	Lkkkkkk/gggggr$grrrrg;
    //   69: astore 5
    //   71: invokestatic 78	kkkkkk/wmwmmw:b04300430043004300430аа043004300430	()I
    //   74: istore_2
    //   75: getstatic 72	kkkkkk/wmwmmw:b043Dнн043D043Dнн043D043D	I
    //   78: istore_3
    //   79: iconst_1
    //   80: tableswitch	default:+24->104, 0:+-1->79, 1:+51->131
    //   104: iconst_1
    //   105: tableswitch	default:+23->128, 0:+-26->79, 1:+26->131
    //   128: goto -24 -> 104
    //   131: iload_2
    //   132: iload_3
    //   133: iload_2
    //   134: iadd
    //   135: imul
    //   136: getstatic 74	kkkkkk/wmwmmw:bн043Dн043D043Dнн043D043D	I
    //   139: irem
    //   140: tableswitch	default:+20->160, 0:+31->171
    //   160: bipush 81
    //   162: putstatic 70	kkkkkk/wmwmmw:b043D043D043Dн043Dнн043D043D	I
    //   165: invokestatic 78	kkkkkk/wmwmmw:b04300430043004300430аа043004300430	()I
    //   168: putstatic 80	kkkkkk/wmwmmw:bннн043D043Dнн043D043D	I
    //   171: aload 5
    //   173: checkcast 117	kkkkkk/wmmwwm
    //   176: astore 5
    //   178: aload 5
    //   180: new 306	kkkkkk/mmmwwm
    //   183: dup
    //   184: aload_1
    //   185: invokespecial 566	kkkkkk/mmmwwm:<init>	(Lkkkkkk/cccrcc;)V
    //   188: invokeinterface 518 2 0
    //   193: aload_0
    //   194: getstatic 353	kkkkkk/rcrccr:ARRANGEMENTS	Lkkkkkk/rcrccr;
    //   197: aload 4
    //   199: invokevirtual 521	kkkkkk/wmwmmw:bаа0430а04300430а043004300430	(Lkkkkkk/rcrccr;Lkkkkkk/qqqqqj;)V
    //   202: return
    //   203: astore_1
    //   204: aload_1
    //   205: athrow
    //   206: astore_1
    //   207: aload_1
    //   208: athrow
    // Local variable table:
    //   start	length	slot	name	signature
    //   0	209	0	this	wmwmmw
    //   0	209	1	paramCccrcc	cccrcc
    //   3	133	2	i	int
    //   78	57	3	j	int
    //   63	135	4	localQqqqqj	qqqqqj
    //   69	110	5	localObject	Object
    // Exception table:
    //   from	to	target	type
    //   65	71	203	java/lang/Exception
    //   178	202	203	java/lang/Exception
    //   42	65	206	java/lang/Exception
    //   171	178	206	java/lang/Exception
  }
  
  public void bаааа04300430а043004300430(int paramInt, final mmmwwm paramMmmwwm, String paramString, rrrccr paramRrrccr)
  {
    for (;;)
    {
      try
      {
        b0430ааа04300430а043004300430(paramMmmwwm, paramInt, paramRrrccr);
        switch (paramInt)
        {
        default: 
          paramInt = b043D043D043Dн043Dнн043D043D;
          switch (paramInt * (bа0430043004300430аа043004300430() + paramInt) % bн043Dн043D043Dнн043D043D)
          {
          default: 
            b043D043D043Dн043Dнн043D043D = 22;
            bннн043D043Dнн043D043D = b04300430043004300430аа043004300430();
          }
          ((wmmwwm)this.b042804280428ШШ042804280428Ш).initialiseInsecureCallLoadingDialog();
        }
      }
      catch (Exception paramMmmwwm)
      {
        int i;
        int j;
        throw paramMmmwwm;
      }
      try
      {
        paramMmmwwm = b04300430ааа0430а043004300430(paramMmmwwm);
        paramInt = b043D043D043Dн043Dнн043D043D;
        i = b043Dнн043D043Dнн043D043D;
        j = bн043Dн043D043Dнн043D043D;
        switch (paramInt * (i + paramInt) % j)
        {
        case 0: 
          b043D043D043Dн043Dнн043D043D = 37;
          bннн043D043Dнн043D043D = b04300430043004300430аа043004300430();
          ((wmmwwm)this.b042804280428ШШ042804280428Ш).showLoading();
          paramString = this.bн043D043Dн043Dнн043D043D;
          paramRrrccr = TimeUnit.SECONDS;
          paramString = paramString.b0418041804180418ИИ0418И04180418(2, paramRrrccr);
          paramMmmwwm = new CompletableObserver()
          {
            public static int b043D043Dнннн043D043D043D = 16;
            public static int b043Dн043Dннн043D043D043D = 1;
            public static int bн043D043Dннн043D043D043D = 2;
            public static int bнн043Dннн043D043D043D;
            
            public static int b0430043004300430ааа043004300430()
            {
              return 75;
            }
            
            public static int bа043004300430ааа043004300430()
            {
              return 2;
            }
            
            public void onComplete()
            {
              ((wmmwwm)wmwmmw.b043004300430а0430аа043004300430(wmwmmw.this)).hideLoading();
              gggggr.grrrrg localGrrrrg = wmwmmw.bааа04300430аа043004300430(wmwmmw.this);
              if ((b043D043Dнннн043D043D043D + b043Dн043Dннн043D043D043D) * b043D043Dнннн043D043D043D % bа043004300430ааа043004300430() != bнн043Dннн043D043D043D)
              {
                b043D043Dнннн043D043D043D = 60;
                bнн043Dннн043D043D043D = 32;
              }
              ((wmmwwm)localGrrrrg).makeCall(paramMmmwwm);
            }
            
            public void onError(Throwable paramAnonymousThrowable)
            {
              ooooio.bаа043004300430а0430ааа(paramAnonymousThrowable);
              paramAnonymousThrowable = wmwmmw.b0430аа04300430аа043004300430(wmwmmw.this);
              if ((b043D043Dнннн043D043D043D + b043Dн043Dннн043D043D043D) * b043D043Dнннн043D043D043D % bн043D043Dннн043D043D043D != bнн043Dннн043D043D043D)
              {
                b043D043Dнннн043D043D043D = b0430043004300430ааа043004300430();
                bнн043Dннн043D043D043D = 76;
              }
              ((wmmwwm)paramAnonymousThrowable).hideLoading();
            }
            
            public void onSubscribe(Disposable paramAnonymousDisposable)
            {
              wmwmmw localWmwmmw = wmwmmw.this;
              if ((b043D043Dнннн043D043D043D + b043Dн043Dннн043D043D043D) * b043D043Dнннн043D043D043D % bн043D043Dннн043D043D043D != bнн043Dннн043D043D043D)
              {
                if ((b043D043Dнннн043D043D043D + b043Dн043Dннн043D043D043D) * b043D043Dнннн043D043D043D % bн043D043Dннн043D043D043D != bнн043Dннн043D043D043D)
                {
                  b043D043Dнннн043D043D043D = b0430043004300430ааа043004300430();
                  bнн043Dннн043D043D043D = 59;
                }
                b043D043Dнннн043D043D043D = 88;
                bнн043Dннн043D043D043D = b0430043004300430ааа043004300430();
              }
              wmwmmw.bа04300430а0430аа043004300430(localWmwmmw, paramAnonymousDisposable);
              switch (1)
              {
              case 0: 
              default: 
                for (;;)
                {
                  switch (0)
                  {
                  }
                }
              }
            }
          };
          paramString.subscribe(paramMmmwwm);
          return;
        }
      }
      catch (Exception paramMmmwwm)
      {
        throw paramMmmwwm;
      }
      paramMmmwwm = this.b043Dн043Dн043Dнн043D043D.b04300430043004300430а0430а04300430() + gguuuu.bккккк043Aкк043A043A("D", 'æ', '\005') + gguuuu.bк043Aккк043Aкк043A043A("\030", '', '', '\000') + paramString;
      continue;
      ((wmmwwm)this.b042804280428ШШ042804280428Ш).hideLoading();
      ((wmmwwm)this.b042804280428ШШ042804280428Ш).initialiseInsecureCallLoadingDialog();
      paramMmmwwm = b04300430ааа0430а043004300430(paramMmmwwm);
      ((wmmwwm)this.b042804280428ШШ042804280428Ш).showLoading();
    }
  }
  
  @ooiiio("Logging")
  public void onError(Throwable paramThrowable)
  {
    ooooio.bаа043004300430а0430ааа(paramThrowable);
    switch (0)
    {
    case 1: 
    default: 
      for (;;)
      {
        switch (0)
        {
        }
      }
    }
    switch (1)
    {
    case 0: 
    default: 
      for (;;)
      {
        switch (1)
        {
        }
      }
    }
    if ((b043D043D043Dн043Dнн043D043D + b043Dнн043D043Dнн043D043D) * b043D043D043Dн043Dнн043D043D % b0430а043004300430аа043004300430() != bннн043D043Dнн043D043D)
    {
      int i = b043D043D043Dн043Dнн043D043D;
      switch (i * (b043Dнн043D043Dнн043D043D + i) % bн043Dн043D043Dнн043D043D)
      {
      default: 
        b043D043D043Dн043Dнн043D043D = b04300430043004300430аа043004300430();
        bннн043D043Dнн043D043D = 53;
      }
      b043D043D043Dн043Dнн043D043D = 92;
      bннн043D043Dнн043D043D = b04300430043004300430аа043004300430();
    }
  }
  
  public void onSubscribe(Disposable paramDisposable)
  {
    if ((b043D043D043Dн043Dнн043D043D + b043Dнн043D043Dнн043D043D) * b043D043D043Dн043Dнн043D043D % bн043Dн043D043Dнн043D043D != bннн043D043Dнн043D043D)
    {
      b043D043D043Dн043Dнн043D043D = 70;
      bннн043D043Dнн043D043D = b04300430043004300430аа043004300430();
    }
    b04180418И0418ИИИ0418ИИ(paramDisposable);
  }
  
  @Retention(RetentionPolicy.SOURCE)
  public static @interface mmwwwm
  {
    public static final int b043D043D043D043Dнн043D043D043D = 3;
    public static final int b043Dн043D043Dнн043D043D043D = 1;
    public static final int bн043D043D043Dнн043D043D043D = 2;
  }
}
