package kkkkkk;

import android.content.Context;
import com.mobile.ui.R.string;
import javax.inject.Inject;

public class wwmwmw
{
  public static int b043D043D043D043Dн043D043Dн043D = 1;
  public static int b043Dннн043D043D043Dн043D = 0;
  public static int bн043D043D043Dн043D043Dн043D = 20;
  public static int bнннн043D043D043Dн043D = 2;
  private final Context b043Dн043D043Dн043D043Dн043D;
  
  @Inject
  public wwmwmw(Context paramContext)
  {
    this.b043Dн043D043Dн043D043Dн043D = paramContext;
  }
  
  private String bа0430043004300430а0430а04300430(ccrrcc paramCcrrcc)
  {
    for (;;)
    {
      try
      {
        localObject = wwmwmw.1.bн043Dнн043D043D043Dн043D;
      }
      catch (Exception paramCcrrcc)
      {
        Object localObject;
        int i;
        int j;
        int k;
        throw paramCcrrcc;
      }
      try
      {
        switch (localObject[paramCcrrcc.ordinal()])
        {
        case 3: 
          paramCcrrcc = this.b043Dн043D043Dн043D043Dн043D.getString(R.string.click_to_call_current_account_non_secure_call_number);
          return paramCcrrcc;
        }
      }
      catch (Exception paramCcrrcc)
      {
        throw paramCcrrcc;
      }
      return this.b043Dн043D043Dн043D043Dн043D.getString(R.string.click_to_call_mortgage_account_non_secure_call_number);
      return this.b043Dн043D043Dн043D043Dн043D.getString(R.string.click_to_call_loan_account_non_secure_call_number);
      return this.b043Dн043D043Dн043D043Dн043D.getString(R.string.click_to_call_term_deposit_account_non_secure_call_number);
      i = bн043D043D043Dн043D043Dн043D;
      j = b043D043D043D043Dн043D043Dн043D;
      k = bнннн043D043D043Dн043D;
      switch (i * (j + i) % k)
      {
      default: 
        bн043D043D043Dн043D043Dн043D = bаа043004300430а0430а04300430();
        b043D043D043D043Dн043D043Dн043D = bаа043004300430а0430а04300430();
      }
      paramCcrrcc = this.b043Dн043D043Dн043D043Dн043D.getString(R.string.click_to_call_savings_account_non_secure_call_number);
      return paramCcrrcc;
      paramCcrrcc = this.b043Dн043D043Dн043D043Dн043D;
      i = R.string.click_to_call_isa_account_non_secure_call_number;
      localObject = paramCcrrcc.getString(i);
      i = bаа043004300430а0430а04300430();
      paramCcrrcc = (ccrrcc)localObject;
      switch (i * (b043D043D043D043Dн043D043Dн043D + i) % bнннн043D043D043Dн043D)
      {
      }
      bн043D043D043Dн043D043Dн043D = bаа043004300430а0430а04300430();
      b043D043D043D043Dн043D043Dн043D = bаа043004300430а0430а04300430();
      return localObject;
      paramCcrrcc = this.b043Dн043D043Dн043D043Dн043D.getString(R.string.click_to_call_credit_account_non_secure_call_number);
      return paramCcrrcc;
    }
  }
  
  public static int bаа043004300430а0430а04300430()
  {
    return 83;
  }
  
  /* Error */
  public String b04300430043004300430а0430а04300430()
  {
    // Byte code:
    //   0: getstatic 63	kkkkkk/wwmwmw:bн043D043D043Dн043D043Dн043D	I
    //   3: istore_1
    //   4: iload_1
    //   5: getstatic 65	kkkkkk/wwmwmw:b043D043D043D043Dн043D043Dн043D	I
    //   8: iload_1
    //   9: iadd
    //   10: imul
    //   11: getstatic 67	kkkkkk/wwmwmw:bнннн043D043D043Dн043D	I
    //   14: irem
    //   15: tableswitch	default:+17->32, 0:+29->44
    //   32: invokestatic 70	kkkkkk/wwmwmw:bаа043004300430а0430а04300430	()I
    //   35: putstatic 63	kkkkkk/wwmwmw:bн043D043D043Dн043D043Dн043D	I
    //   38: invokestatic 70	kkkkkk/wwmwmw:bаа043004300430а0430а04300430	()I
    //   41: putstatic 83	kkkkkk/wwmwmw:b043Dннн043D043D043Dн043D	I
    //   44: aload_0
    //   45: getfield 23	kkkkkk/wwmwmw:b043Dн043D043Dн043D043Dн043D	Landroid/content/Context;
    //   48: astore 6
    //   50: getstatic 63	kkkkkk/wwmwmw:bн043D043D043Dн043D043Dн043D	I
    //   53: istore_1
    //   54: getstatic 65	kkkkkk/wwmwmw:b043D043D043D043Dн043D043Dн043D	I
    //   57: istore_2
    //   58: getstatic 63	kkkkkk/wwmwmw:bн043D043D043Dн043D043Dн043D	I
    //   61: istore_3
    //   62: getstatic 67	kkkkkk/wwmwmw:bнннн043D043D043Dн043D	I
    //   65: istore 4
    //   67: getstatic 83	kkkkkk/wwmwmw:b043Dннн043D043D043Dн043D	I
    //   70: istore 5
    //   72: iload_1
    //   73: iload_2
    //   74: iadd
    //   75: iload_3
    //   76: imul
    //   77: iload 4
    //   79: irem
    //   80: iload 5
    //   82: if_icmpeq +13 -> 95
    //   85: bipush 53
    //   87: putstatic 63	kkkkkk/wwmwmw:bн043D043D043Dн043D043Dн043D	I
    //   90: bipush 58
    //   92: putstatic 83	kkkkkk/wwmwmw:b043Dннн043D043D043Dн043D	I
    //   95: getstatic 86	com/mobile/ui/R$string:click_to_call_secure_call_number	I
    //   98: istore_1
    //   99: aload 6
    //   101: iload_1
    //   102: invokevirtual 52	android/content/Context:getString	(I)Ljava/lang/String;
    //   105: astore 6
    //   107: aload 6
    //   109: areturn
    //   110: astore 6
    //   112: aload 6
    //   114: athrow
    //   115: astore 6
    //   117: aload 6
    //   119: athrow
    //   120: astore 6
    //   122: aload 6
    //   124: athrow
    //   125: astore 6
    //   127: aload 6
    //   129: athrow
    // Local variable table:
    //   start	length	slot	name	signature
    //   0	130	0	this	wwmwmw
    //   3	99	1	i	int
    //   57	18	2	j	int
    //   61	16	3	k	int
    //   65	15	4	m	int
    //   70	13	5	n	int
    //   48	60	6	localObject	Object
    //   110	3	6	localException1	Exception
    //   115	3	6	localException2	Exception
    //   120	3	6	localException3	Exception
    //   125	3	6	localException4	Exception
    // Exception table:
    //   from	to	target	type
    //   44	50	110	java/lang/Exception
    //   95	99	110	java/lang/Exception
    //   67	72	115	java/lang/Exception
    //   112	115	115	java/lang/Exception
    //   122	125	115	java/lang/Exception
    //   99	107	120	java/lang/Exception
    //   50	67	125	java/lang/Exception
    //   85	95	125	java/lang/Exception
  }
  
  public String b0430а043004300430а0430а04300430(mmmwwm paramMmmwwm)
  {
    Object localObject = wwmwmw.1.b043D043Dнн043D043D043Dн043D;
    if ((bн043D043D043Dн043D043Dн043D + b043D043D043D043Dн043D043Dн043D) * bн043D043D043Dн043D043Dн043D % bнннн043D043D043Dн043D != b043Dннн043D043D043Dн043D)
    {
      bн043D043D043Dн043D043Dн043D = bаа043004300430а0430а04300430();
      b043Dннн043D043D043Dн043D = 0;
    }
    switch (localObject[paramMmmwwm.b0430а0430043004300430а043004300430().ordinal()])
    {
    default: 
      paramMmmwwm = this.b043Dн043D043Dн043D043Dн043D.getString(R.string.click_to_call_other_banking_queries_non_secure_call_number);
      return paramMmmwwm;
    case 12: 
      return this.b043Dн043D043Dн043D043Dн043D.getString(R.string.click_to_call_medical_assistance_abroad_non_secure_call_number);
    case 2: 
      return this.b043Dн043D043Dн043D043Dн043D.getString(R.string.click_to_call_current_account_non_secure_call_number);
    case 3: 
      paramMmmwwm = this.b043Dн043D043Dн043D043Dн043D;
      int i = R.string.click_to_call_savings_account_non_secure_call_number;
      if ((bн043D043D043Dн043D043Dн043D + b043D043D043D043Dн043D043Dн043D) * bн043D043D043Dн043D043Dн043D % bнннн043D043D043Dн043D != b043Dннн043D043D043Dн043D)
      {
        bн043D043D043Dн043D043Dн043D = bаа043004300430а0430а04300430();
        b043Dннн043D043D043Dн043D = bаа043004300430а0430а04300430();
      }
      return paramMmmwwm.getString(i);
    case 9: 
      return this.b043Dн043D043Dн043D043Dн043D.getString(R.string.click_to_call_suspected_fraud_non_secure_call_number);
    case 4: 
      return this.b043Dн043D043Dн043D043Dн043D.getString(R.string.click_to_call_new_credit_card_non_secure_call_number);
    case 10: 
      return this.b043Dн043D043Dн043D043Dн043D.getString(R.string.click_to_call_lost_or_stolen_card_non_secure_call_number);
    case 7: 
      return this.b043Dн043D043Dн043D043Dн043D.getString(R.string.click_to_call_new_mortgage_non_secure_call_number);
    case 11: 
      localObject = this.b043Dн043D043Dн043D043Dн043D.getString(R.string.click_to_call_emergency_cash_abroad_non_secure_call_number);
      paramMmmwwm = (mmmwwm)localObject;
      switch (0)
      {
      }
      for (;;)
      {
        paramMmmwwm = (mmmwwm)localObject;
        switch (0)
        {
        }
      }
    case 1: 
      return bа0430043004300430а0430а04300430(paramMmmwwm.bаа0430043004300430а043004300430().bжж04360436жжжж04360436());
    case 5: 
      return this.b043Dн043D043Dн043D043Dн043D.getString(R.string.click_to_call_new_isa_account_non_secure_call_number);
    case 6: 
      return this.b043Dн043D043Dн043D043Dн043D.getString(R.string.click_to_call_new_loan_account_non_secure_call_number);
    }
    return this.b043Dн043D043Dн043D043Dн043D.getString(R.string.click_to_call_internet_banking_non_secure_call_number);
  }
}
