package kkkkkk;

import android.content.Context;
import android.graphics.drawable.Drawable;
import android.support.annotation.Nullable;
import android.support.annotation.StringRes;
import com.mobile.ui.R.string;
import com.mobile.ui.common.view.LoadingDialog;

public class wwwbbb
{
  public static int b04280428Ш0428ШШШ04280428 = 2;
  public static int b0428ШШ0428ШШШ04280428 = 0;
  public static int bШ0428Ш0428ШШШ04280428 = 1;
  public static int bШШШ0428ШШШ04280428 = 93;
  private LoadingDialog b042804280428ШШШШ04280428;
  
  private wwwbbb() {}
  
  public static int b0418ИИИ04180418ИИ0418И()
  {
    return 12;
  }
  
  public static wwwbbb bИИИ041804180418ИИ0418И()
  {
    wwwbbb localWwwbbb = new wwwbbb();
    if ((bШШШ0428ШШШ04280428 + bШ0428Ш0428ШШШ04280428) * bШШШ0428ШШШ04280428 % b04280428Ш0428ШШШ04280428 != b0428ШШ0428ШШШ04280428)
    {
      if ((bШШШ0428ШШШ04280428 + bШ0428Ш0428ШШШ04280428) * bШШШ0428ШШШ04280428 % b04280428Ш0428ШШШ04280428 != b0428ШШ0428ШШШ04280428)
      {
        bШШШ0428ШШШ04280428 = b0418ИИИ04180418ИИ0418И();
        b0428ШШ0428ШШШ04280428 = b0418ИИИ04180418ИИ0418И();
      }
      bШШШ0428ШШШ04280428 = b0418ИИИ04180418ИИ0418И();
      b0428ШШ0428ШШШ04280428 = 57;
    }
    return localWwwbbb;
  }
  
  public static int bИИИИ04180418ИИ0418И()
  {
    return 2;
  }
  
  public boolean b041804180418И04180418ИИ0418И()
  {
    int j = 1;
    int i = j;
    if (this.b042804280428ШШШШ04280428 != null)
    {
      i = j;
      if (this.b042804280428ШШШШ04280428.isShowing()) {
        return true;
      }
    }
    try
    {
      for (;;)
      {
        j = i / 0;
        int k = b0418ИИИ04180418ИИ0418И();
        i = j;
        switch (k * (bШ0428Ш0428ШШШ04280428 + k) % b04280428Ш0428ШШШ04280428)
        {
        }
        bШШШ0428ШШШ04280428 = 62;
        b0428ШШ0428ШШШ04280428 = 40;
        i = j;
      }
      return false;
    }
    catch (Exception localException)
    {
      bШШШ0428ШШШ04280428 = b0418ИИИ04180418ИИ0418И();
    }
  }
  
  public LoadingDialog b04180418ИИ04180418ИИ0418И(Context paramContext, boolean paramBoolean)
  {
    try
    {
      LoadingDialog localLoadingDialog = this.b042804280428ШШШШ04280428;
      if (localLoadingDialog == null) {
        if (!paramBoolean) {
          break label172;
        }
      }
    }
    catch (Exception paramContext)
    {
      int i;
      int j;
      int k;
      throw paramContext;
    }
    try
    {
      bИИ0418И04180418ИИ0418И(paramContext, R.string.default_loading_spinner_title);
      return this.b042804280428ШШШШ04280428;
    }
    catch (Exception paramContext)
    {
      throw paramContext;
    }
    paramContext = this.b042804280428ШШШШ04280428;
    if ((bШШШ0428ШШШ04280428 + bШ0428Ш0428ШШШ04280428) * bШШШ0428ШШШ04280428 % b04280428Ш0428ШШШ04280428 != b0428ШШ0428ШШШ04280428)
    {
      bШШШ0428ШШШ04280428 = 11;
      b0428ШШ0428ШШШ04280428 = b0418ИИИ04180418ИИ0418И();
    }
    switch (1)
    {
    case 0: 
    default: 
      for (;;)
      {
        switch (0)
        {
        }
      }
    }
    i = b0418ИИИ04180418ИИ0418И();
    j = bШ0428Ш0428ШШШ04280428;
    k = b04280428Ш0428ШШШ04280428;
    switch (i * (j + i) % k)
    {
    default: 
      bШШШ0428ШШШ04280428 = 76;
      b0428ШШ0428ШШШ04280428 = b0418ИИИ04180418ИИ0418И();
      return paramContext;
      label172:
      throw new IllegalArgumentException(gguuuu.bккккк043Aкк043A043A("\t)X\004&\027\031\035!\031t\031\020\032\034\023J\023\027\021\033\017\006\020\f\034\006\004", 'b', '\003'));
    }
    return paramContext;
  }
  
  /* Error */
  public void b0418И0418И04180418ИИ0418И(Context paramContext, @StringRes int paramInt1, @StringRes int paramInt2)
  {
    // Byte code:
    //   0: getstatic 27	kkkkkk/wwwbbb:bШШШ0428ШШШ04280428	I
    //   3: getstatic 29	kkkkkk/wwwbbb:bШ0428Ш0428ШШШ04280428	I
    //   6: iadd
    //   7: getstatic 27	kkkkkk/wwwbbb:bШШШ0428ШШШ04280428	I
    //   10: imul
    //   11: getstatic 31	kkkkkk/wwwbbb:b04280428Ш0428ШШШ04280428	I
    //   14: irem
    //   15: getstatic 33	kkkkkk/wwwbbb:b0428ШШ0428ШШШ04280428	I
    //   18: if_icmpeq +15 -> 33
    //   21: invokestatic 35	kkkkkk/wwwbbb:b0418ИИИ04180418ИИ0418И	()I
    //   24: putstatic 27	kkkkkk/wwwbbb:bШШШ0428ШШШ04280428	I
    //   27: invokestatic 35	kkkkkk/wwwbbb:b0418ИИИ04180418ИИ0418И	()I
    //   30: putstatic 33	kkkkkk/wwwbbb:b0428ШШ0428ШШШ04280428	I
    //   33: new 44	com/mobile/ui/common/view/LoadingDialog
    //   36: dup
    //   37: aload_1
    //   38: iload_2
    //   39: iload_3
    //   40: invokespecial 76	com/mobile/ui/common/view/LoadingDialog:<init>	(Landroid/content/Context;II)V
    //   43: astore_1
    //   44: aload_0
    //   45: aload_1
    //   46: putfield 42	kkkkkk/wwwbbb:b042804280428ШШШШ04280428	Lcom/mobile/ui/common/view/LoadingDialog;
    //   49: return
    //   50: astore_1
    //   51: aload_1
    //   52: athrow
    //   53: astore_1
    //   54: aload_1
    //   55: athrow
    // Local variable table:
    //   start	length	slot	name	signature
    //   0	56	0	this	wwwbbb
    //   0	56	1	paramContext	Context
    //   0	56	2	paramInt1	int
    //   0	56	3	paramInt2	int
    // Exception table:
    //   from	to	target	type
    //   44	49	50	java/lang/Exception
    //   33	44	53	java/lang/Exception
  }
  
  public void b0418ИИ041804180418ИИ0418И()
  {
    if ((bШШШ0428ШШШ04280428 + bШ0428Ш0428ШШШ04280428) * bШШШ0428ШШШ04280428 % bИИИИ04180418ИИ0418И() != b0428ШШ0428ШШШ04280428)
    {
      int i = b0418ИИИ04180418ИИ0418И();
      int j = bШШШ0428ШШШ04280428;
      switch (j * (bШ0428Ш0428ШШШ04280428 + j) % bИИИИ04180418ИИ0418И())
      {
      default: 
        bШШШ0428ШШШ04280428 = 31;
        b0428ШШ0428ШШШ04280428 = 74;
      }
      bШШШ0428ШШШ04280428 = i;
      b0428ШШ0428ШШШ04280428 = 74;
    }
    try
    {
      this.b042804280428ШШШШ04280428 = null;
      return;
    }
    catch (Exception localException)
    {
      throw localException;
    }
  }
  
  public void bИ04180418И04180418ИИ0418И(Context paramContext, @StringRes int paramInt1, @StringRes int paramInt2, @Nullable Drawable paramDrawable)
  {
    throw new Runtime("d2j fail translate: java.lang.IndexOutOfBoundsException: fromIndex < 0: -1\n\tat java.util.BitSet.nextSetBit(BitSet.java:712)\n\tat com.googlecode.dex2jar.ir.ts.array.FillArrayTransformer.makeSureAllElementAreAssigned(FillArrayTransformer.java:505)\n\tat com.googlecode.dex2jar.ir.ts.array.FillArrayTransformer.transformReportChanged(FillArrayTransformer.java:123)\n\tat com.googlecode.dex2jar.ir.ts.StatedTransformer.transform(StatedTransformer.java:10)\n\tat com.googlecode.d2j.dex.Dex2jar$2.optimize(Dex2jar.java:149)\n\tat com.googlecode.d2j.dex.Dex2Asm.convertCode(Dex2Asm.java:414)\n\tat com.googlecode.d2j.dex.ExDex2Asm.convertCode(ExDex2Asm.java:42)\n\tat com.googlecode.d2j.dex.Dex2jar$2.convertCode(Dex2jar.java:128)\n\tat com.googlecode.d2j.dex.Dex2Asm.convertMethod(Dex2Asm.java:509)\n\tat com.googlecode.d2j.dex.Dex2Asm.convertClass(Dex2Asm.java:406)\n\tat com.googlecode.d2j.dex.Dex2Asm.convertDex(Dex2Asm.java:422)\n\tat com.googlecode.d2j.dex.Dex2jar.doTranslate(Dex2jar.java:172)\n\tat com.googlecode.d2j.dex.Dex2jar.to(Dex2jar.java:272)\n\tat com.googlecode.dex2jar.tools.Dex2jarCmd.doCommandLine(Dex2jarCmd.java:108)\n\tat com.googlecode.dex2jar.tools.BaseCmd.doMain(BaseCmd.java:288)\n\tat com.googlecode.dex2jar.tools.Dex2jarCmd.main(Dex2jarCmd.java:32)\n");
  }
  
  /* Error */
  public void bИ0418И041804180418ИИ0418И(Context paramContext)
  {
    // Byte code:
    //   0: aload_0
    //   1: aload_1
    //   2: iconst_1
    //   3: invokevirtual 94	kkkkkk/wwwbbb:b04180418ИИ04180418ИИ0418И	(Landroid/content/Context;Z)Lcom/mobile/ui/common/view/LoadingDialog;
    //   6: astore_1
    //   7: getstatic 27	kkkkkk/wwwbbb:bШШШ0428ШШШ04280428	I
    //   10: istore_2
    //   11: getstatic 29	kkkkkk/wwwbbb:bШ0428Ш0428ШШШ04280428	I
    //   14: istore_3
    //   15: getstatic 27	kkkkkk/wwwbbb:bШШШ0428ШШШ04280428	I
    //   18: istore 4
    //   20: getstatic 31	kkkkkk/wwwbbb:b04280428Ш0428ШШШ04280428	I
    //   23: istore 5
    //   25: getstatic 33	kkkkkk/wwwbbb:b0428ШШ0428ШШШ04280428	I
    //   28: istore 6
    //   30: iload_2
    //   31: iload_3
    //   32: iadd
    //   33: iload 4
    //   35: imul
    //   36: iload 5
    //   38: irem
    //   39: iload 6
    //   41: if_icmpeq +56 -> 97
    //   44: getstatic 27	kkkkkk/wwwbbb:bШШШ0428ШШШ04280428	I
    //   47: istore_2
    //   48: iload_2
    //   49: getstatic 29	kkkkkk/wwwbbb:bШ0428Ш0428ШШШ04280428	I
    //   52: iload_2
    //   53: iadd
    //   54: imul
    //   55: getstatic 31	kkkkkk/wwwbbb:b04280428Ш0428ШШШ04280428	I
    //   58: irem
    //   59: tableswitch	default:+17->76, 0:+28->87
    //   76: invokestatic 35	kkkkkk/wwwbbb:b0418ИИИ04180418ИИ0418И	()I
    //   79: putstatic 27	kkkkkk/wwwbbb:bШШШ0428ШШШ04280428	I
    //   82: bipush 39
    //   84: putstatic 33	kkkkkk/wwwbbb:b0428ШШ0428ШШШ04280428	I
    //   87: bipush 67
    //   89: putstatic 27	kkkkkk/wwwbbb:bШШШ0428ШШШ04280428	I
    //   92: bipush 25
    //   94: putstatic 33	kkkkkk/wwwbbb:b0428ШШ0428ШШШ04280428	I
    //   97: aload_1
    //   98: invokevirtual 97	com/mobile/ui/common/view/LoadingDialog:show	()V
    //   101: return
    //   102: astore_1
    //   103: aload_1
    //   104: athrow
    //   105: astore_1
    //   106: aload_1
    //   107: athrow
    //   108: astore_1
    //   109: aload_1
    //   110: athrow
    //   111: astore_1
    //   112: aload_1
    //   113: athrow
    // Local variable table:
    //   start	length	slot	name	signature
    //   0	114	0	this	wwwbbb
    //   0	114	1	paramContext	Context
    //   10	45	2	i	int
    //   14	19	3	j	int
    //   18	18	4	k	int
    //   23	16	5	m	int
    //   28	14	6	n	int
    // Exception table:
    //   from	to	target	type
    //   97	101	102	java/lang/Exception
    //   7	30	105	java/lang/Exception
    //   103	105	105	java/lang/Exception
    //   0	7	108	java/lang/Exception
    //   87	97	111	java/lang/Exception
    //   109	111	111	java/lang/Exception
  }
  
  public void bИ0418ИИ04180418ИИ0418И(Context paramContext)
  {
    boolean bool = b041804180418И04180418ИИ0418И();
    switch (1)
    {
    case 0: 
    default: 
      for (;;)
      {
        switch (1)
        {
        }
      }
    }
    if (bool)
    {
      this.b042804280428ШШШШ04280428.dismiss();
      int i = bШШШ0428ШШШ04280428;
      switch (i * (bШ0428Ш0428ШШШ04280428 + i) % bИИИИ04180418ИИ0418И())
      {
      default: 
        i = bШШШ0428ШШШ04280428;
        switch (i * (bШ0428Ш0428ШШШ04280428 + i) % b04280428Ш0428ШШШ04280428)
        {
        default: 
          bШШШ0428ШШШ04280428 = 79;
          b0428ШШ0428ШШШ04280428 = 74;
        }
        bШШШ0428ШШШ04280428 = 22;
        b0428ШШ0428ШШШ04280428 = b0418ИИИ04180418ИИ0418И();
      }
    }
  }
  
  public void bИИ0418И04180418ИИ0418И(Context paramContext, @StringRes int paramInt)
  {
    paramContext = new LoadingDialog(paramContext, paramInt);
    paramInt = bШШШ0428ШШШ04280428;
    if ((bШШШ0428ШШШ04280428 + bШ0428Ш0428ШШШ04280428) * bШШШ0428ШШШ04280428 % b04280428Ш0428ШШШ04280428 != b0428ШШ0428ШШШ04280428)
    {
      bШШШ0428ШШШ04280428 = b0418ИИИ04180418ИИ0418И();
      b0428ШШ0428ШШШ04280428 = b0418ИИИ04180418ИИ0418И();
    }
    int i = bШ0428Ш0428ШШШ04280428;
    switch (0)
    {
    case 1: 
    default: 
      for (;;)
      {
        switch (0)
        {
        }
      }
    }
    switch (paramInt * (i + paramInt) % bИИИИ04180418ИИ0418И())
    {
    default: 
      bШШШ0428ШШШ04280428 = b0418ИИИ04180418ИИ0418И();
      b0428ШШ0428ШШШ04280428 = 1;
    }
    this.b042804280428ШШШШ04280428 = paramContext;
  }
}
