package kkkkkk;

import javax.inject.Inject;

public class wwwmmm
  extends wmmwmm
{
  public static int b042804280428ШШ0428ШШШ = 0;
  public static int b0428Ш0428ШШ0428ШШШ = 1;
  public static int bШ04280428ШШ0428ШШШ = 2;
  public static int bШШ0428ШШ0428ШШШ = 36;
  
  @Inject
  public wwwmmm(nuuuuu paramNuuuuu, rgrggg paramRgrggg)
  {
    super(paramNuuuuu, paramRgrggg);
  }
  
  public static int b04300430аа043004300430043004300430()
  {
    return 21;
  }
  
  public static int bа0430аа043004300430043004300430()
  {
    return 1;
  }
  
  public static int bаа0430а043004300430043004300430()
  {
    return 2;
  }
  
  /* Error */
  public void b043004300430а043004300430043004300430()
  {
    // Byte code:
    //   0: ldc 30
    //   2: sipush 213
    //   5: sipush 177
    //   8: iconst_1
    //   9: invokestatic 36	kkkkkk/gguuuu:bк043Aккк043Aкк043A043A	(Ljava/lang/String;CCC)Ljava/lang/String;
    //   12: astore 6
    //   14: getstatic 38	kkkkkk/wwwmmm:bШШ0428ШШ0428ШШШ	I
    //   17: istore_1
    //   18: getstatic 40	kkkkkk/wwwmmm:b0428Ш0428ШШ0428ШШШ	I
    //   21: istore_2
    //   22: getstatic 38	kkkkkk/wwwmmm:bШШ0428ШШ0428ШШШ	I
    //   25: istore_3
    //   26: getstatic 42	kkkkkk/wwwmmm:bШ04280428ШШ0428ШШШ	I
    //   29: istore 4
    //   31: getstatic 44	kkkkkk/wwwmmm:b042804280428ШШ0428ШШШ	I
    //   34: istore 5
    //   36: iload_1
    //   37: iload_2
    //   38: iadd
    //   39: iload_3
    //   40: imul
    //   41: iload 4
    //   43: irem
    //   44: iload 5
    //   46: if_icmpeq +58 -> 104
    //   49: getstatic 38	kkkkkk/wwwmmm:bШШ0428ШШ0428ШШШ	I
    //   52: istore_1
    //   53: iload_1
    //   54: invokestatic 46	kkkkkk/wwwmmm:bа0430аа043004300430043004300430	()I
    //   57: iload_1
    //   58: iadd
    //   59: imul
    //   60: getstatic 42	kkkkkk/wwwmmm:bШ04280428ШШ0428ШШШ	I
    //   63: irem
    //   64: tableswitch	default:+20->84, 0:+30->94
    //   84: bipush 24
    //   86: putstatic 38	kkkkkk/wwwmmm:bШШ0428ШШ0428ШШШ	I
    //   89: bipush 86
    //   91: putstatic 44	kkkkkk/wwwmmm:b042804280428ШШ0428ШШШ	I
    //   94: bipush 59
    //   96: putstatic 38	kkkkkk/wwwmmm:bШШ0428ШШ0428ШШШ	I
    //   99: bipush 11
    //   101: putstatic 44	kkkkkk/wwwmmm:b042804280428ШШ0428ШШШ	I
    //   104: aload_0
    //   105: aload 6
    //   107: ldc 48
    //   109: bipush 8
    //   111: sipush 174
    //   114: iconst_1
    //   115: invokestatic 36	kkkkkk/gguuuu:bк043Aккк043Aкк043A043A	(Ljava/lang/String;CCC)Ljava/lang/String;
    //   118: invokevirtual 52	kkkkkk/wwwmmm:b0430а04300430а04300430043004300430	(Ljava/lang/String;Ljava/lang/String;)V
    //   121: return
    //   122: astore 6
    //   124: aload 6
    //   126: athrow
    //   127: astore 6
    //   129: aload 6
    //   131: athrow
    // Local variable table:
    //   start	length	slot	name	signature
    //   0	132	0	this	wwwmmm
    //   17	43	1	i	int
    //   21	18	2	j	int
    //   25	16	3	k	int
    //   29	15	4	m	int
    //   34	13	5	n	int
    //   12	94	6	str	String
    //   122	3	6	localException1	Exception
    //   127	3	6	localException2	Exception
    // Exception table:
    //   from	to	target	type
    //   0	36	122	java/lang/Exception
    //   94	99	122	java/lang/Exception
    //   99	104	127	java/lang/Exception
    //   104	121	127	java/lang/Exception
  }
  
  /* Error */
  public void b04300430а0430043004300430043004300430()
  {
    // Byte code:
    //   0: ldc 55
    //   2: bipush 22
    //   4: sipush 156
    //   7: iconst_2
    //   8: invokestatic 36	kkkkkk/gguuuu:bк043Aккк043Aкк043A043A	(Ljava/lang/String;CCC)Ljava/lang/String;
    //   11: astore 6
    //   13: ldc 57
    //   15: sipush 152
    //   18: bipush 76
    //   20: iconst_3
    //   21: invokestatic 36	kkkkkk/gguuuu:bк043Aккк043Aкк043A043A	(Ljava/lang/String;CCC)Ljava/lang/String;
    //   24: astore 7
    //   26: getstatic 38	kkkkkk/wwwmmm:bШШ0428ШШ0428ШШШ	I
    //   29: istore_1
    //   30: getstatic 40	kkkkkk/wwwmmm:b0428Ш0428ШШ0428ШШШ	I
    //   33: istore_2
    //   34: getstatic 38	kkkkkk/wwwmmm:bШШ0428ШШ0428ШШШ	I
    //   37: istore_3
    //   38: getstatic 42	kkkkkk/wwwmmm:bШ04280428ШШ0428ШШШ	I
    //   41: istore 4
    //   43: getstatic 44	kkkkkk/wwwmmm:b042804280428ШШ0428ШШШ	I
    //   46: istore 5
    //   48: iload_1
    //   49: iload_2
    //   50: iadd
    //   51: iload_3
    //   52: imul
    //   53: iload 4
    //   55: irem
    //   56: iload 5
    //   58: if_icmpeq +61 -> 119
    //   61: getstatic 38	kkkkkk/wwwmmm:bШШ0428ШШ0428ШШШ	I
    //   64: istore_1
    //   65: iload_1
    //   66: getstatic 40	kkkkkk/wwwmmm:b0428Ш0428ШШ0428ШШШ	I
    //   69: iload_1
    //   70: iadd
    //   71: imul
    //   72: getstatic 42	kkkkkk/wwwmmm:bШ04280428ШШ0428ШШШ	I
    //   75: irem
    //   76: tableswitch	default:+20->96, 0:+30->106
    //   96: bipush 76
    //   98: putstatic 38	kkkkkk/wwwmmm:bШШ0428ШШ0428ШШШ	I
    //   101: bipush 16
    //   103: putstatic 44	kkkkkk/wwwmmm:b042804280428ШШ0428ШШШ	I
    //   106: bipush 81
    //   108: putstatic 38	kkkkkk/wwwmmm:bШШ0428ШШ0428ШШШ	I
    //   111: invokestatic 59	kkkkkk/wwwmmm:b04300430аа043004300430043004300430	()I
    //   114: istore_1
    //   115: iload_1
    //   116: putstatic 44	kkkkkk/wwwmmm:b042804280428ШШ0428ШШШ	I
    //   119: aload_0
    //   120: aload 6
    //   122: aload 7
    //   124: invokevirtual 52	kkkkkk/wwwmmm:b0430а04300430а04300430043004300430	(Ljava/lang/String;Ljava/lang/String;)V
    //   127: return
    //   128: astore 6
    //   130: aload 6
    //   132: athrow
    //   133: astore 6
    //   135: aload 6
    //   137: athrow
    //   138: astore 6
    //   140: aload 6
    //   142: athrow
    //   143: astore 6
    //   145: aload 6
    //   147: athrow
    // Local variable table:
    //   start	length	slot	name	signature
    //   0	148	0	this	wwwmmm
    //   29	87	1	i	int
    //   33	18	2	j	int
    //   37	16	3	k	int
    //   41	15	4	m	int
    //   46	13	5	n	int
    //   11	110	6	str1	String
    //   128	3	6	localException1	Exception
    //   133	3	6	localException2	Exception
    //   138	3	6	localException3	Exception
    //   143	3	6	localException4	Exception
    //   24	99	7	str2	String
    // Exception table:
    //   from	to	target	type
    //   0	26	128	java/lang/Exception
    //   26	48	133	java/lang/Exception
    //   111	115	133	java/lang/Exception
    //   130	133	133	java/lang/Exception
    //   119	127	138	java/lang/Exception
    //   106	111	143	java/lang/Exception
    //   115	119	143	java/lang/Exception
    //   140	143	143	java/lang/Exception
  }
  
  /* Error */
  public void b0430а0430а043004300430043004300430()
  {
    // Byte code:
    //   0: ldc 62
    //   2: sipush 176
    //   5: iconst_5
    //   6: invokestatic 66	kkkkkk/gguuuu:bккккк043Aкк043A043A	(Ljava/lang/String;CC)Ljava/lang/String;
    //   9: astore 4
    //   11: aload_0
    //   12: aload 4
    //   14: ldc 68
    //   16: bipush 26
    //   18: bipush 76
    //   20: iconst_2
    //   21: invokestatic 36	kkkkkk/gguuuu:bк043Aккк043Aкк043A043A	(Ljava/lang/String;CCC)Ljava/lang/String;
    //   24: invokevirtual 52	kkkkkk/wwwmmm:b0430а04300430а04300430043004300430	(Ljava/lang/String;Ljava/lang/String;)V
    //   27: getstatic 38	kkkkkk/wwwmmm:bШШ0428ШШ0428ШШШ	I
    //   30: istore_1
    //   31: getstatic 38	kkkkkk/wwwmmm:bШШ0428ШШ0428ШШШ	I
    //   34: invokestatic 46	kkkkkk/wwwmmm:bа0430аа043004300430043004300430	()I
    //   37: iadd
    //   38: getstatic 38	kkkkkk/wwwmmm:bШШ0428ШШ0428ШШШ	I
    //   41: imul
    //   42: invokestatic 70	kkkkkk/wwwmmm:bаа0430а043004300430043004300430	()I
    //   45: irem
    //   46: getstatic 44	kkkkkk/wwwmmm:b042804280428ШШ0428ШШШ	I
    //   49: if_icmpeq +14 -> 63
    //   52: invokestatic 59	kkkkkk/wwwmmm:b04300430аа043004300430043004300430	()I
    //   55: putstatic 38	kkkkkk/wwwmmm:bШШ0428ШШ0428ШШШ	I
    //   58: bipush 33
    //   60: putstatic 44	kkkkkk/wwwmmm:b042804280428ШШ0428ШШШ	I
    //   63: getstatic 40	kkkkkk/wwwmmm:b0428Ш0428ШШ0428ШШШ	I
    //   66: istore_2
    //   67: getstatic 42	kkkkkk/wwwmmm:bШ04280428ШШ0428ШШШ	I
    //   70: istore_3
    //   71: iload_1
    //   72: iload_2
    //   73: iload_1
    //   74: iadd
    //   75: imul
    //   76: iload_3
    //   77: irem
    //   78: tableswitch	default:+18->96, 0:+30->108
    //   96: invokestatic 59	kkkkkk/wwwmmm:b04300430аа043004300430043004300430	()I
    //   99: putstatic 38	kkkkkk/wwwmmm:bШШ0428ШШ0428ШШШ	I
    //   102: invokestatic 59	kkkkkk/wwwmmm:b04300430аа043004300430043004300430	()I
    //   105: putstatic 40	kkkkkk/wwwmmm:b0428Ш0428ШШ0428ШШШ	I
    //   108: return
    //   109: astore 4
    //   111: aload 4
    //   113: athrow
    //   114: astore 4
    //   116: aload 4
    //   118: athrow
    // Local variable table:
    //   start	length	slot	name	signature
    //   0	119	0	this	wwwmmm
    //   30	46	1	i	int
    //   66	9	2	j	int
    //   70	8	3	k	int
    //   9	4	4	str	String
    //   109	3	4	localException1	Exception
    //   114	3	4	localException2	Exception
    // Exception table:
    //   from	to	target	type
    //   0	11	109	java/lang/Exception
    //   63	71	109	java/lang/Exception
    //   11	31	114	java/lang/Exception
    //   96	108	114	java/lang/Exception
  }
  
  /* Error */
  public void b0430аа0430043004300430043004300430()
  {
    // Byte code:
    //   0: ldc 73
    //   2: sipush 164
    //   5: iconst_4
    //   6: invokestatic 66	kkkkkk/gguuuu:bккккк043Aкк043A043A	(Ljava/lang/String;CC)Ljava/lang/String;
    //   9: astore 6
    //   11: getstatic 38	kkkkkk/wwwmmm:bШШ0428ШШ0428ШШШ	I
    //   14: istore_1
    //   15: getstatic 40	kkkkkk/wwwmmm:b0428Ш0428ШШ0428ШШШ	I
    //   18: istore_2
    //   19: getstatic 38	kkkkkk/wwwmmm:bШШ0428ШШ0428ШШШ	I
    //   22: istore_3
    //   23: getstatic 42	kkkkkk/wwwmmm:bШ04280428ШШ0428ШШШ	I
    //   26: istore 4
    //   28: getstatic 44	kkkkkk/wwwmmm:b042804280428ШШ0428ШШШ	I
    //   31: istore 5
    //   33: iload_1
    //   34: iload_2
    //   35: iadd
    //   36: iload_3
    //   37: imul
    //   38: iload 4
    //   40: irem
    //   41: iload 5
    //   43: if_icmpeq +47 -> 90
    //   46: invokestatic 59	kkkkkk/wwwmmm:b04300430аа043004300430043004300430	()I
    //   49: putstatic 38	kkkkkk/wwwmmm:bШШ0428ШШ0428ШШШ	I
    //   52: invokestatic 59	kkkkkk/wwwmmm:b04300430аа043004300430043004300430	()I
    //   55: putstatic 44	kkkkkk/wwwmmm:b042804280428ШШ0428ШШШ	I
    //   58: invokestatic 59	kkkkkk/wwwmmm:b04300430аа043004300430043004300430	()I
    //   61: getstatic 40	kkkkkk/wwwmmm:b0428Ш0428ШШ0428ШШШ	I
    //   64: iadd
    //   65: invokestatic 59	kkkkkk/wwwmmm:b04300430аа043004300430043004300430	()I
    //   68: imul
    //   69: getstatic 42	kkkkkk/wwwmmm:bШ04280428ШШ0428ШШШ	I
    //   72: irem
    //   73: getstatic 44	kkkkkk/wwwmmm:b042804280428ШШ0428ШШШ	I
    //   76: if_icmpeq +14 -> 90
    //   79: bipush 74
    //   81: putstatic 38	kkkkkk/wwwmmm:bШШ0428ШШ0428ШШШ	I
    //   84: invokestatic 59	kkkkkk/wwwmmm:b04300430аа043004300430043004300430	()I
    //   87: putstatic 44	kkkkkk/wwwmmm:b042804280428ШШ0428ШШШ	I
    //   90: aload_0
    //   91: aload 6
    //   93: ldc 75
    //   95: bipush 79
    //   97: iconst_2
    //   98: invokestatic 66	kkkkkk/gguuuu:bккккк043Aкк043A043A	(Ljava/lang/String;CC)Ljava/lang/String;
    //   101: invokevirtual 52	kkkkkk/wwwmmm:b0430а04300430а04300430043004300430	(Ljava/lang/String;Ljava/lang/String;)V
    //   104: return
    //   105: astore 6
    //   107: aload 6
    //   109: athrow
    //   110: astore 6
    //   112: aload 6
    //   114: athrow
    //   115: astore 6
    //   117: aload 6
    //   119: athrow
    //   120: astore 6
    //   122: aload 6
    //   124: athrow
    // Local variable table:
    //   start	length	slot	name	signature
    //   0	125	0	this	wwwmmm
    //   14	22	1	i	int
    //   18	18	2	j	int
    //   22	16	3	k	int
    //   26	15	4	m	int
    //   31	13	5	n	int
    //   9	83	6	str	String
    //   105	3	6	localException1	Exception
    //   110	3	6	localException2	Exception
    //   115	3	6	localException3	Exception
    //   120	3	6	localException4	Exception
    // Exception table:
    //   from	to	target	type
    //   0	11	105	java/lang/Exception
    //   11	33	110	java/lang/Exception
    //   107	110	110	java/lang/Exception
    //   90	104	115	java/lang/Exception
    //   46	58	120	java/lang/Exception
    //   117	120	120	java/lang/Exception
  }
  
  /* Error */
  public void bа04300430а043004300430043004300430()
  {
    // Byte code:
    //   0: getstatic 38	kkkkkk/wwwmmm:bШШ0428ШШ0428ШШШ	I
    //   3: getstatic 40	kkkkkk/wwwmmm:b0428Ш0428ШШ0428ШШШ	I
    //   6: iadd
    //   7: getstatic 38	kkkkkk/wwwmmm:bШШ0428ШШ0428ШШШ	I
    //   10: imul
    //   11: getstatic 42	kkkkkk/wwwmmm:bШ04280428ШШ0428ШШШ	I
    //   14: irem
    //   15: getstatic 44	kkkkkk/wwwmmm:b042804280428ШШ0428ШШШ	I
    //   18: if_icmpeq +15 -> 33
    //   21: invokestatic 59	kkkkkk/wwwmmm:b04300430аа043004300430043004300430	()I
    //   24: putstatic 38	kkkkkk/wwwmmm:bШШ0428ШШ0428ШШШ	I
    //   27: invokestatic 59	kkkkkk/wwwmmm:b04300430аа043004300430043004300430	()I
    //   30: putstatic 44	kkkkkk/wwwmmm:b042804280428ШШ0428ШШШ	I
    //   33: aload_0
    //   34: ldc 78
    //   36: sipush 135
    //   39: bipush 34
    //   41: iconst_1
    //   42: invokestatic 36	kkkkkk/gguuuu:bк043Aккк043Aкк043A043A	(Ljava/lang/String;CCC)Ljava/lang/String;
    //   45: ldc 80
    //   47: sipush 163
    //   50: sipush 183
    //   53: iconst_2
    //   54: invokestatic 36	kkkkkk/gguuuu:bк043Aккк043Aкк043A043A	(Ljava/lang/String;CCC)Ljava/lang/String;
    //   57: invokevirtual 52	kkkkkk/wwwmmm:b0430а04300430а04300430043004300430	(Ljava/lang/String;Ljava/lang/String;)V
    //   60: getstatic 38	kkkkkk/wwwmmm:bШШ0428ШШ0428ШШШ	I
    //   63: istore_1
    //   64: getstatic 40	kkkkkk/wwwmmm:b0428Ш0428ШШ0428ШШШ	I
    //   67: istore_2
    //   68: invokestatic 70	kkkkkk/wwwmmm:bаа0430а043004300430043004300430	()I
    //   71: istore_3
    //   72: iload_1
    //   73: iload_2
    //   74: iload_1
    //   75: iadd
    //   76: imul
    //   77: iload_3
    //   78: irem
    //   79: tableswitch	default:+17->96, 0:+28->107
    //   96: bipush 13
    //   98: putstatic 38	kkkkkk/wwwmmm:bШШ0428ШШ0428ШШШ	I
    //   101: invokestatic 59	kkkkkk/wwwmmm:b04300430аа043004300430043004300430	()I
    //   104: putstatic 44	kkkkkk/wwwmmm:b042804280428ШШ0428ШШШ	I
    //   107: return
    //   108: astore 4
    //   110: aload 4
    //   112: athrow
    //   113: astore 4
    //   115: aload 4
    //   117: athrow
    // Local variable table:
    //   start	length	slot	name	signature
    //   0	118	0	this	wwwmmm
    //   63	14	1	i	int
    //   67	9	2	j	int
    //   71	8	3	k	int
    //   108	3	4	localException1	Exception
    //   113	3	4	localException2	Exception
    // Exception table:
    //   from	to	target	type
    //   33	72	108	java/lang/Exception
    //   96	107	113	java/lang/Exception
  }
  
  /* Error */
  public void bа0430а0430043004300430043004300430()
  {
    // Byte code:
    //   0: aload_0
    //   1: ldc 83
    //   3: bipush 73
    //   5: sipush 202
    //   8: iconst_0
    //   9: invokestatic 36	kkkkkk/gguuuu:bк043Aккк043Aкк043A043A	(Ljava/lang/String;CCC)Ljava/lang/String;
    //   12: ldc 85
    //   14: sipush 154
    //   17: sipush 149
    //   20: iconst_2
    //   21: invokestatic 36	kkkkkk/gguuuu:bк043Aккк043Aкк043A043A	(Ljava/lang/String;CCC)Ljava/lang/String;
    //   24: invokevirtual 52	kkkkkk/wwwmmm:b0430а04300430а04300430043004300430	(Ljava/lang/String;Ljava/lang/String;)V
    //   27: getstatic 38	kkkkkk/wwwmmm:bШШ0428ШШ0428ШШШ	I
    //   30: istore_1
    //   31: getstatic 40	kkkkkk/wwwmmm:b0428Ш0428ШШ0428ШШШ	I
    //   34: istore_2
    //   35: getstatic 38	kkkkkk/wwwmmm:bШШ0428ШШ0428ШШШ	I
    //   38: istore_3
    //   39: getstatic 42	kkkkkk/wwwmmm:bШ04280428ШШ0428ШШШ	I
    //   42: istore 4
    //   44: getstatic 44	kkkkkk/wwwmmm:b042804280428ШШ0428ШШШ	I
    //   47: istore 5
    //   49: iload_1
    //   50: iload_2
    //   51: iadd
    //   52: iload_3
    //   53: imul
    //   54: iload 4
    //   56: irem
    //   57: iload 5
    //   59: if_icmpeq +59 -> 118
    //   62: getstatic 38	kkkkkk/wwwmmm:bШШ0428ШШ0428ШШШ	I
    //   65: istore_1
    //   66: iload_1
    //   67: getstatic 40	kkkkkk/wwwmmm:b0428Ш0428ШШ0428ШШШ	I
    //   70: iload_1
    //   71: iadd
    //   72: imul
    //   73: getstatic 42	kkkkkk/wwwmmm:bШ04280428ШШ0428ШШШ	I
    //   76: irem
    //   77: tableswitch	default:+19->96, 0:+30->107
    //   96: bipush 84
    //   98: putstatic 38	kkkkkk/wwwmmm:bШШ0428ШШ0428ШШШ	I
    //   101: invokestatic 59	kkkkkk/wwwmmm:b04300430аа043004300430043004300430	()I
    //   104: putstatic 44	kkkkkk/wwwmmm:b042804280428ШШ0428ШШШ	I
    //   107: invokestatic 59	kkkkkk/wwwmmm:b04300430аа043004300430043004300430	()I
    //   110: putstatic 38	kkkkkk/wwwmmm:bШШ0428ШШ0428ШШШ	I
    //   113: bipush 78
    //   115: putstatic 44	kkkkkk/wwwmmm:b042804280428ШШ0428ШШШ	I
    //   118: return
    //   119: astore 6
    //   121: aload 6
    //   123: athrow
    //   124: astore 6
    //   126: aload 6
    //   128: athrow
    // Local variable table:
    //   start	length	slot	name	signature
    //   0	129	0	this	wwwmmm
    //   30	43	1	i	int
    //   34	18	2	j	int
    //   38	16	3	k	int
    //   42	15	4	m	int
    //   47	13	5	n	int
    //   119	3	6	localException1	Exception
    //   124	3	6	localException2	Exception
    // Exception table:
    //   from	to	target	type
    //   0	44	119	java/lang/Exception
    //   44	49	124	java/lang/Exception
    //   107	118	124	java/lang/Exception
  }
  
  /* Error */
  public void bааа0430043004300430043004300430()
  {
    // Byte code:
    //   0: getstatic 38	kkkkkk/wwwmmm:bШШ0428ШШ0428ШШШ	I
    //   3: getstatic 40	kkkkkk/wwwmmm:b0428Ш0428ШШ0428ШШШ	I
    //   6: iadd
    //   7: getstatic 38	kkkkkk/wwwmmm:bШШ0428ШШ0428ШШШ	I
    //   10: imul
    //   11: getstatic 42	kkkkkk/wwwmmm:bШ04280428ШШ0428ШШШ	I
    //   14: irem
    //   15: getstatic 44	kkkkkk/wwwmmm:b042804280428ШШ0428ШШШ	I
    //   18: if_icmpeq +14 -> 32
    //   21: bipush 84
    //   23: putstatic 38	kkkkkk/wwwmmm:bШШ0428ШШ0428ШШШ	I
    //   26: invokestatic 59	kkkkkk/wwwmmm:b04300430аа043004300430043004300430	()I
    //   29: putstatic 44	kkkkkk/wwwmmm:b042804280428ШШ0428ШШШ	I
    //   32: ldc 88
    //   34: sipush 228
    //   37: iconst_2
    //   38: invokestatic 66	kkkkkk/gguuuu:bккккк043Aкк043A043A	(Ljava/lang/String;CC)Ljava/lang/String;
    //   41: astore_2
    //   42: ldc 90
    //   44: sipush 243
    //   47: iconst_0
    //   48: invokestatic 66	kkkkkk/gguuuu:bккккк043Aкк043A043A	(Ljava/lang/String;CC)Ljava/lang/String;
    //   51: astore_3
    //   52: getstatic 38	kkkkkk/wwwmmm:bШШ0428ШШ0428ШШШ	I
    //   55: istore_1
    //   56: iload_1
    //   57: invokestatic 46	kkkkkk/wwwmmm:bа0430аа043004300430043004300430	()I
    //   60: iload_1
    //   61: iadd
    //   62: imul
    //   63: getstatic 42	kkkkkk/wwwmmm:bШ04280428ШШ0428ШШШ	I
    //   66: irem
    //   67: tableswitch	default:+17->84, 0:+27->94
    //   84: bipush 40
    //   86: putstatic 38	kkkkkk/wwwmmm:bШШ0428ШШ0428ШШШ	I
    //   89: bipush 18
    //   91: putstatic 44	kkkkkk/wwwmmm:b042804280428ШШ0428ШШШ	I
    //   94: aload_0
    //   95: aload_2
    //   96: aload_3
    //   97: invokevirtual 52	kkkkkk/wwwmmm:b0430а04300430а04300430043004300430	(Ljava/lang/String;Ljava/lang/String;)V
    //   100: return
    //   101: astore_2
    //   102: aload_2
    //   103: athrow
    //   104: astore_2
    //   105: aload_2
    //   106: athrow
    // Local variable table:
    //   start	length	slot	name	signature
    //   0	107	0	this	wwwmmm
    //   55	8	1	i	int
    //   41	55	2	str1	String
    //   101	2	2	localException1	Exception
    //   104	2	2	localException2	Exception
    //   51	46	3	str2	String
    // Exception table:
    //   from	to	target	type
    //   32	52	101	java/lang/Exception
    //   94	100	104	java/lang/Exception
  }
}
