package kkkkkk;

import android.net.Uri;
import android.net.Uri.Builder;
import java.util.Iterator;
import java.util.List;
import org.json.JSONArray;

public class xttxxt
  extends xxtxxt
{
  private static final String b042A042A042AЪЪ042A042AЪ042A = "{\t\n\007\013RHI@\020L\020\nP\017\023\f\r\026\033W\026\032\023[";
  public static int b042A042AЪ042AЪ042A042AЪ042A = 1;
  public static int b042AЪ042A042AЪ042A042AЪ042A = 0;
  public static final String b042AЪЪ042AЪ042A042AЪ042A = xttxxt.class.getSimpleName();
  private static final String bЪ042A042AЪЪ042A042AЪ042A = "CST3GTM";
  public static int bЪ042AЪ042AЪ042A042AЪ042A = 92;
  public static int bЪЪ042A042AЪ042A042AЪ042A = 2;
  private static final String bЪЪЪ042AЪ042A042AЪ042A = "81@A07:@:3(\032\"7\032H?NLGC";
  
  static
  {
    int i = bЪ042AЪ042AЪ042A042AЪ042A;
    switch (i * (b042A042AЪ042AЪ042A042AЪ042A + i) % bЪЪ042A042AЪ042A042AЪ042A)
    {
    default: 
      bЪ042AЪ042AЪ042A042AЪ042A = bии04380438и043804380438ии();
      b042A042AЪ042AЪ042A042AЪ042A = bии04380438и043804380438ии();
      i = bЪ042AЪ042AЪ042A042AЪ042A;
      switch (i * (b04380438и0438и043804380438ии() + i) % bЪЪ042A042AЪ042A042AЪ042A)
      {
      default: 
        bЪ042AЪ042AЪ042A042AЪ042A = 54;
        b042A042AЪ042AЪ042A042AЪ042A = 18;
      }
      break;
    }
    switch (1)
    {
    case 0: 
    default: 
      for (;;)
      {
        switch (1)
        {
        }
      }
    }
    bЪ042A042AЪЪ042A042AЪ042A = gguuuu.bккккк043Aкк043A043A(bЪ042A042AЪЪ042A042AЪ042A, 'p', '\004');
    b042A042A042AЪЪ042A042AЪ042A = gguuuu.bккккк043Aкк043A043A(b042A042A042AЪЪ042A042AЪ042A, 'È', '\004');
    String str = bЪЪЪ042AЪ042A042AЪ042A;
    switch (0)
    {
    case 1: 
    default: 
      for (;;)
      {
        switch (0)
        {
        }
      }
    }
    bЪЪЪ042AЪ042A042AЪ042A = gguuuu.bккккк043Aкк043A043A(str, 'É', '\000');
  }
  
  public xttxxt() {}
  
  public static int b04380438и0438и043804380438ии()
  {
    return 1;
  }
  
  public static int bии04380438и043804380438ии()
  {
    return 33;
  }
  
  public void b0438и04380438и043804380438ии(String paramString, final List<tttxxt> paramList, List<String> paramList1)
  {
    if ((paramString == null) || (paramList == null) || (paramList.isEmpty()))
    {
      xtxtxt.bии0438и04380438и0438ии(b042AЪЪ042AЪ042A042AЪ042A, gguuuu.bк043Aккк043Aкк043A043A("/ (\035y,\" mR\026 \035\020\027\033K\032\034H\025\f\031\030\005\n\007@\t\022=\002\t\013\016\022E6Y}w2\004.\001qyn)tvm", ';', '\t', '\002'));
      return;
    }
    JSONArray localJSONArray = new JSONArray();
    if ((bЪ042AЪ042AЪ042A042AЪ042A + b042A042AЪ042AЪ042A042AЪ042A) * bЪ042AЪ042AЪ042A042AЪ042A % bЪЪ042A042AЪ042A042AЪ042A != b042AЪ042A042AЪ042A042AЪ042A)
    {
      bЪ042AЪ042AЪ042A042AЪ042A = bии04380438и043804380438ии();
      b042AЪ042A042AЪ042A042AЪ042A = 18;
    }
    Iterator localIterator = paramList.iterator();
    while (localIterator.hasNext()) {
      localJSONArray.put(((tttxxt)localIterator.next()).b043804380438ии043804380438ии());
    }
    paramString = new rmrrmr(Uri.parse(String.format(gguuuu.bккккк043Aкк043A043A("\027$%\"&mcd[+g\033+%k*.'(16r15.v", 'd', '\001'), new Object[] { paramString })).buildUpon().appendQueryParameter(gguuuu.bккккк043Aкк043A043A("\035-.\r!.'", '½', '\001'), gguuuu.bк043Aккк043Aкк043A043A("wn{zglmqi`SCI\\=i^kg`Z", 'Ä', 'Î', '\000')).build().toString());
    if ((bЪ042AЪ042AЪ042A042AЪ042A + b042A042AЪ042AЪ042A042AЪ042A) * bЪ042AЪ042AЪ042A042AЪ042A % bЪЪ042A042AЪ042A042AЪ042A != b042AЪ042A042AЪ042A042AЪ042A)
    {
      bЪ042AЪ042AЪ042A042AЪ042A = 41;
      b042AЪ042A042AЪ042A042AЪ042A = bии04380438и043804380438ии();
    }
    paramString.b0438ии04380438ии043804380438(new rrmmrr(localJSONArray));
    paramString.b043804380438и04380438и043804380438(paramList1);
    paramString.bи04380438и04380438и043804380438(new dddxxd()
    {
      public static int b042A042AЪЪ042A042A042AЪ042A = 0;
      public static int b042AЪЪЪ042A042A042AЪ042A = 1;
      public static int bЪ042AЪЪ042A042A042AЪ042A = 2;
      public static int bЪЪЪЪ042A042A042AЪ042A = 86;
      
      public static int b0438ии0438и043804380438ии()
      {
        return 0;
      }
      
      public static int bиии0438и043804380438ии()
      {
        return 95;
      }
      
      public void b0445х0445х0445хх044504450445(Throwable paramAnonymousThrowable)
      {
        String str1 = xttxxt.b042AЪЪ042AЪ042A042AЪ042A;
        StringBuilder localStringBuilder = new StringBuilder();
        String str2 = gguuuu.bк043Aккк043Aкк043A043A("\026'/$\0013)'Z)'|)($&lQ", '|', '@', '\002');
        switch (1)
        {
        case 0: 
        default: 
          for (;;)
          {
            switch (1)
            {
            }
          }
        }
        xtxtxt.bии0438и04380438и0438ии(str1, str2 + paramAnonymousThrowable);
        if (xttxxt.this.bЪЪ042AЪ042A042A042AЪ042A != null)
        {
          switch (1)
          {
          case 0: 
          default: 
            for (;;)
            {
              switch (0)
              {
              }
            }
          }
          int i = bЪЪЪЪ042A042A042AЪ042A;
          int j = b042AЪЪЪ042A042A042AЪ042A;
          int k = bЪЪЪЪ042A042A042AЪ042A;
          if ((bЪЪЪЪ042A042A042AЪ042A + b042AЪЪЪ042A042A042AЪ042A) * bЪЪЪЪ042A042A042AЪ042A % bЪ042AЪЪ042A042A042AЪ042A != b042A042AЪЪ042A042A042AЪ042A)
          {
            bЪЪЪЪ042A042A042AЪ042A = bиии0438и043804380438ии();
            b042A042AЪЪ042A042A042AЪ042A = bиии0438и043804380438ии();
          }
          if ((i + j) * k % bЪ042AЪЪ042A042A042AЪ042A != b0438ии0438и043804380438ии())
          {
            bЪЪЪЪ042A042A042AЪ042A = 50;
            b042AЪЪЪ042A042A042AЪ042A = 89;
          }
          xttxxt.this.bЪЪ042AЪ042A042A042AЪ042A.bии04380438ии04380438ии(paramList, paramAnonymousThrowable);
        }
      }
      
      /* Error */
      public void bи0438и0438и043804380438ии(String paramAnonymousString)
      {
        // Byte code:
        //   0: getstatic 42	kkkkkk/xttxxt:b042AЪЪ042AЪ042A042AЪ042A	Ljava/lang/String;
        //   3: astore 5
        //   5: new 44	java/lang/StringBuilder
        //   8: dup
        //   9: invokespecial 45	java/lang/StringBuilder:<init>	()V
        //   12: astore 6
        //   14: getstatic 76	kkkkkk/xttxxt$1:bЪЪЪЪ042A042A042AЪ042A	I
        //   17: istore_2
        //   18: getstatic 78	kkkkkk/xttxxt$1:b042AЪЪЪ042A042A042AЪ042A	I
        //   21: istore_3
        //   22: getstatic 80	kkkkkk/xttxxt$1:bЪ042AЪЪ042A042A042AЪ042A	I
        //   25: istore 4
        //   27: iload_2
        //   28: iload_3
        //   29: iload_2
        //   30: iadd
        //   31: imul
        //   32: iload 4
        //   34: irem
        //   35: tableswitch	default:+17->52, 0:+28->63
        //   52: invokestatic 84	kkkkkk/xttxxt$1:bиии0438и043804380438ии	()I
        //   55: putstatic 76	kkkkkk/xttxxt$1:bЪЪЪЪ042A042A042AЪ042A	I
        //   58: bipush 12
        //   60: putstatic 82	kkkkkk/xttxxt$1:b042A042AЪЪ042A042A042AЪ042A	I
        //   63: aload 6
        //   65: ldc 98
        //   67: sipush 221
        //   70: sipush 178
        //   73: iconst_2
        //   74: invokestatic 53	kkkkkk/gguuuu:bк043Aккк043Aкк043A043A	(Ljava/lang/String;CCC)Ljava/lang/String;
        //   77: invokevirtual 57	java/lang/StringBuilder:append	(Ljava/lang/String;)Ljava/lang/StringBuilder;
        //   80: astore 6
        //   82: getstatic 76	kkkkkk/xttxxt$1:bЪЪЪЪ042A042A042AЪ042A	I
        //   85: getstatic 78	kkkkkk/xttxxt$1:b042AЪЪЪ042A042A042AЪ042A	I
        //   88: iadd
        //   89: getstatic 76	kkkkkk/xttxxt$1:bЪЪЪЪ042A042A042AЪ042A	I
        //   92: imul
        //   93: getstatic 80	kkkkkk/xttxxt$1:bЪ042AЪЪ042A042A042AЪ042A	I
        //   96: irem
        //   97: getstatic 82	kkkkkk/xttxxt$1:b042A042AЪЪ042A042A042AЪ042A	I
        //   100: if_icmpeq +15 -> 115
        //   103: invokestatic 84	kkkkkk/xttxxt$1:bиии0438и043804380438ии	()I
        //   106: putstatic 76	kkkkkk/xttxxt$1:bЪЪЪЪ042A042A042AЪ042A	I
        //   109: invokestatic 84	kkkkkk/xttxxt$1:bиии0438и043804380438ии	()I
        //   112: putstatic 82	kkkkkk/xttxxt$1:b042A042AЪЪ042A042A042AЪ042A	I
        //   115: aload 5
        //   117: aload 6
        //   119: aload_1
        //   120: invokevirtual 57	java/lang/StringBuilder:append	(Ljava/lang/String;)Ljava/lang/StringBuilder;
        //   123: invokevirtual 64	java/lang/StringBuilder:toString	()Ljava/lang/String;
        //   126: invokestatic 101	kkkkkk/xtxtxt:bиии043804380438и0438ии	(Ljava/lang/String;Ljava/lang/String;)V
        //   129: aload_0
        //   130: getfield 27	kkkkkk/xttxxt$1:bЪ042A042A042AЪ042A042AЪ042A	Lkkkkkk/xttxxt;
        //   133: astore_1
        //   134: aload_1
        //   135: getfield 74	kkkkkk/xttxxt:bЪЪ042AЪ042A042A042AЪ042A	Lkkkkkk/ttxxxt;
        //   138: astore_1
        //   139: aload_1
        //   140: ifnull +15 -> 155
        //   143: aload_0
        //   144: getfield 27	kkkkkk/xttxxt$1:bЪ042A042A042AЪ042A042AЪ042A	Lkkkkkk/xttxxt;
        //   147: getfield 74	kkkkkk/xttxxt:bЪЪ042AЪ042A042A042AЪ042A	Lkkkkkk/ttxxxt;
        //   150: invokeinterface 104 1 0
        //   155: return
        //   156: astore_1
        //   157: aload_1
        //   158: athrow
        //   159: astore_1
        //   160: aload_1
        //   161: athrow
        // Local variable table:
        //   start	length	slot	name	signature
        //   0	162	0	this	1
        //   0	162	1	paramAnonymousString	String
        //   17	15	2	i	int
        //   21	10	3	j	int
        //   25	10	4	k	int
        //   3	113	5	str	String
        //   12	106	6	localStringBuilder	StringBuilder
        // Exception table:
        //   from	to	target	type
        //   0	27	156	java/lang/Exception
        //   63	82	156	java/lang/Exception
        //   115	134	156	java/lang/Exception
        //   143	155	156	java/lang/Exception
        //   52	63	159	java/lang/Exception
        //   134	139	159	java/lang/Exception
      }
    });
    rrmrrr.b04380438иииии043804380438(paramString);
  }
}
