package kkkkkk;

public class xtxtxt
{
  public static final String b042A042A042A042AЪ042AЪЪ042A = "_kjfh";
  public static int b042A042A042AЪ042A042AЪЪ042A = 0;
  public static final String b042A042AЪЪ042A042AЪЪ042A = "5\036.)#'\037";
  public static int b042AЪ042AЪ042A042AЪЪ042A = 53;
  public static final String b042AЪЪЪ042A042AЪЪ042A = "W\004x\006\002ztbrx";
  private static boolean bЪ042A042A042AЪ042AЪЪ042A = false;
  public static int bЪ042A042AЪ042A042AЪЪ042A = 2;
  private static final String bЪ042AЪЪ042A042AЪЪ042A = "\0304@.8,8831";
  private static ttxtxt bЪЪ042AЪ042A042AЪЪ042A;
  public static int bЪЪЪ042A042A042AЪЪ042A = 1;
  public static final String bЪЪЪЪ042A042AЪЪ042A = "\016\022\t\021";
  
  static
  {
    int i = b042AЪ042AЪ042A042AЪЪ042A;
    switch (i * (b0438иии04380438и0438ии() + i) % bЪ042A042AЪ042A042AЪЪ042A)
    {
    default: 
      b042AЪ042AЪ042A042AЪЪ042A = 6;
      bЪ042A042AЪ042A042AЪЪ042A = bи0438ии04380438и0438ии();
    }
    try
    {
      b042A042A042A042AЪ042AЪЪ042A = gguuuu.bк043Aккк043Aкк043A043A(b042A042A042A042AЪ042AЪЪ042A, '¼', '(', '\002');
      Object localObject = bЪЪЪЪ042A042AЪЪ042A;
      try
      {
        bЪЪЪЪ042A042AЪЪ042A = gguuuu.bккккк043Aкк043A043A((String)localObject, 'Ü', '\003');
        localObject = gguuuu.bккккк043Aкк043A043A(b042AЪЪЪ042A042AЪЪ042A, '¢', '\002');
        if ((b042AЪ042AЪ042A042AЪЪ042A + bЪЪЪ042A042A042AЪЪ042A) * b042AЪ042AЪ042A042AЪЪ042A % bЪ042A042AЪ042A042AЪЪ042A != b042A042A042AЪ042A042AЪЪ042A)
        {
          b042AЪ042AЪ042A042AЪЪ042A = 49;
          b042A042A042AЪ042A042AЪЪ042A = 13;
        }
        b042AЪЪЪ042A042AЪЪ042A = (String)localObject;
        bЪ042AЪЪ042A042AЪЪ042A = gguuuu.bк043Aккк043Aкк043A043A(bЪ042AЪЪ042A042AЪЪ042A, '\023', 'Ý', '\000');
        localObject = b042A042AЪЪ042A042AЪЪ042A;
        b042A042AЪЪ042A042AЪЪ042A = gguuuu.bккккк043Aкк043A043A((String)localObject, '', '\003');
        bЪ042A042A042AЪ042AЪЪ042A = true;
        localObject = new xxttxt();
      }
      catch (Exception localException1)
      {
        throw localException1;
      }
      bЪЪ042AЪ042A042AЪЪ042A = (ttxtxt)localObject;
      return;
    }
    catch (Exception localException2)
    {
      throw localException2;
    }
    switch (1)
    {
    }
    for (;;)
    {
      switch (1)
      {
      }
    }
  }
  
  public xtxtxt() {}
  
  /* Error */
  private static void b0438043804380438и0438и0438ии(String paramString1, String paramString2, String paramString3)
  {
    // Byte code:
    //   0: getstatic 39	kkkkkk/xtxtxt:b042AЪ042AЪ042A042AЪЪ042A	I
    //   3: istore_3
    //   4: iload_3
    //   5: getstatic 66	kkkkkk/xtxtxt:bЪЪЪ042A042A042AЪЪ042A	I
    //   8: iload_3
    //   9: iadd
    //   10: imul
    //   11: getstatic 45	kkkkkk/xtxtxt:bЪ042A042AЪ042A042AЪЪ042A	I
    //   14: irem
    //   15: tableswitch	default:+17->32, 0:+28->43
    //   32: bipush 69
    //   34: putstatic 39	kkkkkk/xtxtxt:b042AЪ042AЪ042A042AЪЪ042A	I
    //   37: invokestatic 48	kkkkkk/xtxtxt:bи0438ии04380438и0438ии	()I
    //   40: putstatic 68	kkkkkk/xtxtxt:b042A042A042AЪ042A042AЪЪ042A	I
    //   43: new 87	kkkkkk/tttxxt
    //   46: dup
    //   47: aload_2
    //   48: ldc 89
    //   50: bipush 88
    //   52: iconst_2
    //   53: invokestatic 62	kkkkkk/gguuuu:bккккк043Aкк043A043A	(Ljava/lang/String;CC)Ljava/lang/String;
    //   56: aload_1
    //   57: aload_0
    //   58: invokespecial 92	kkkkkk/tttxxt:<init>	(Ljava/lang/String;Ljava/lang/String;Ljava/lang/String;Ljava/lang/String;)V
    //   61: astore_0
    //   62: getstatic 98	kkkkkk/xxdxxd:instance	Lkkkkkk/xxdxxd;
    //   65: invokevirtual 102	kkkkkk/xxdxxd:b0445х0445044504450445х044504450445	()Lkkkkkk/txxtxt;
    //   68: astore_1
    //   69: getstatic 39	kkkkkk/xtxtxt:b042AЪ042AЪ042A042AЪЪ042A	I
    //   72: getstatic 66	kkkkkk/xtxtxt:bЪЪЪ042A042A042AЪЪ042A	I
    //   75: iadd
    //   76: getstatic 39	kkkkkk/xtxtxt:b042AЪ042AЪ042A042AЪЪ042A	I
    //   79: imul
    //   80: getstatic 45	kkkkkk/xtxtxt:bЪ042A042AЪ042A042AЪЪ042A	I
    //   83: irem
    //   84: getstatic 68	kkkkkk/xtxtxt:b042A042A042AЪ042A042AЪЪ042A	I
    //   87: if_icmpeq +15 -> 102
    //   90: invokestatic 48	kkkkkk/xtxtxt:bи0438ии04380438и0438ии	()I
    //   93: putstatic 39	kkkkkk/xtxtxt:b042AЪ042AЪ042A042AЪЪ042A	I
    //   96: invokestatic 48	kkkkkk/xtxtxt:bи0438ии04380438и0438ии	()I
    //   99: putstatic 68	kkkkkk/xtxtxt:b042A042A042AЪ042A042AЪЪ042A	I
    //   102: aload_1
    //   103: ifnull +8 -> 111
    //   106: aload_1
    //   107: aload_0
    //   108: invokevirtual 108	kkkkkk/txxtxt:bииииии04380438ии	(Lkkkkkk/tttxxt;)V
    //   111: return
    //   112: astore_0
    //   113: iconst_0
    //   114: tableswitch	default:+22->136, 0:+49->163, 1:+-1->113
    //   136: iconst_0
    //   137: tableswitch	default:+23->160, 0:+26->163, 1:+-24->113
    //   160: goto -24 -> 136
    //   163: aload_0
    //   164: athrow
    //   165: astore_0
    //   166: aload_0
    //   167: athrow
    // Local variable table:
    //   start	length	slot	name	signature
    //   0	168	0	paramString1	String
    //   0	168	1	paramString2	String
    //   0	168	2	paramString3	String
    //   3	8	3	i	int
    // Exception table:
    //   from	to	target	type
    //   106	111	112	java/lang/Exception
    //   43	69	165	java/lang/Exception
  }
  
  /* Error */
  private static String b043804380438и04380438и0438ии(Throwable paramThrowable)
  {
    // Byte code:
    //   0: getstatic 39	kkkkkk/xtxtxt:b042AЪ042AЪ042A042AЪЪ042A	I
    //   3: getstatic 66	kkkkkk/xtxtxt:bЪЪЪ042A042A042AЪЪ042A	I
    //   6: iadd
    //   7: getstatic 39	kkkkkk/xtxtxt:b042AЪ042AЪ042A042AЪЪ042A	I
    //   10: imul
    //   11: getstatic 45	kkkkkk/xtxtxt:bЪ042A042AЪ042A042AЪЪ042A	I
    //   14: irem
    //   15: getstatic 68	kkkkkk/xtxtxt:b042A042A042AЪ042A042AЪЪ042A	I
    //   18: if_icmpeq +14 -> 32
    //   21: bipush 76
    //   23: putstatic 39	kkkkkk/xtxtxt:b042AЪ042AЪ042A042AЪЪ042A	I
    //   26: invokestatic 48	kkkkkk/xtxtxt:bи0438ии04380438и0438ии	()I
    //   29: putstatic 68	kkkkkk/xtxtxt:b042A042A042AЪ042A042AЪЪ042A	I
    //   32: iconst_1
    //   33: istore_1
    //   34: new 112	java/io/StringWriter
    //   37: dup
    //   38: invokespecial 113	java/io/StringWriter:<init>	()V
    //   41: astore_2
    //   42: iload_1
    //   43: iconst_0
    //   44: idiv
    //   45: istore_1
    //   46: goto -4 -> 42
    //   49: astore_0
    //   50: aload_0
    //   51: athrow
    //   52: astore_0
    //   53: aload_0
    //   54: athrow
    //   55: astore_3
    //   56: bipush 46
    //   58: putstatic 39	kkkkkk/xtxtxt:b042AЪ042AЪ042A042AЪЪ042A	I
    //   61: aload_0
    //   62: new 115	java/io/PrintWriter
    //   65: dup
    //   66: aload_2
    //   67: invokespecial 118	java/io/PrintWriter:<init>	(Ljava/io/Writer;)V
    //   70: invokevirtual 124	java/lang/Throwable:printStackTrace	(Ljava/io/PrintWriter;)V
    //   73: aload_2
    //   74: invokevirtual 128	java/lang/Object:toString	()Ljava/lang/String;
    //   77: astore_0
    //   78: aload_0
    //   79: areturn
    //   80: astore_0
    //   81: aload_0
    //   82: athrow
    //   83: astore_0
    //   84: aload_0
    //   85: athrow
    // Local variable table:
    //   start	length	slot	name	signature
    //   0	86	0	paramThrowable	Throwable
    //   33	13	1	i	int
    //   41	33	2	localStringWriter	java.io.StringWriter
    //   55	1	3	localException	Exception
    // Exception table:
    //   from	to	target	type
    //   73	78	49	java/lang/Exception
    //   50	52	52	java/lang/Exception
    //   42	46	55	java/lang/Exception
    //   34	42	80	java/lang/Exception
    //   61	73	80	java/lang/Exception
    //   56	61	83	java/lang/Exception
    //   81	83	83	java/lang/Exception
  }
  
  public static void b04380438и043804380438и0438ии(ttxtxt paramTtxtxt)
  {
    if ((b042AЪ042AЪ042A042AЪЪ042A + bЪЪЪ042A042A042AЪЪ042A) * b042AЪ042AЪ042A042AЪЪ042A % b04380438ии04380438и0438ии() != b042A042A042AЪ042A042AЪЪ042A)
    {
      b042AЪ042AЪ042A042AЪЪ042A = 2;
      b042A042A042AЪ042A042AЪЪ042A = bи0438ии04380438и0438ии();
    }
    int i = b042AЪ042AЪ042A042AЪЪ042A;
    switch (1)
    {
    case 0: 
    default: 
      for (;;)
      {
        switch (1)
        {
        }
      }
    }
    switch (i * (bЪЪЪ042A042A042AЪЪ042A + i) % bЪ042A042AЪ042A042AЪЪ042A)
    {
    default: 
      b042AЪ042AЪ042A042AЪЪ042A = bи0438ии04380438и0438ии();
      b042A042A042AЪ042A042AЪЪ042A = bи0438ии04380438и0438ии();
    }
    bЪЪ042AЪ042A042AЪЪ042A = paramTtxtxt;
  }
  
  public static int b04380438ии04380438и0438ии()
  {
    return 2;
  }
  
  /* Error */
  public static void b0438и0438043804380438и0438ии(String paramString, Throwable paramThrowable)
  {
    // Byte code:
    //   0: getstatic 74	kkkkkk/xtxtxt:bЪ042A042A042AЪ042AЪЪ042A	Z
    //   3: ifeq +191 -> 194
    //   6: getstatic 81	kkkkkk/xtxtxt:bЪЪ042AЪ042A042AЪЪ042A	Lkkkkkk/ttxtxt;
    //   9: astore 7
    //   11: new 137	java/lang/StringBuilder
    //   14: dup
    //   15: invokespecial 138	java/lang/StringBuilder:<init>	()V
    //   18: ldc -116
    //   20: sipush 202
    //   23: iconst_0
    //   24: invokestatic 62	kkkkkk/gguuuu:bккккк043Aкк043A043A	(Ljava/lang/String;CC)Ljava/lang/String;
    //   27: invokevirtual 144	java/lang/StringBuilder:append	(Ljava/lang/String;)Ljava/lang/StringBuilder;
    //   30: aload_0
    //   31: invokevirtual 144	java/lang/StringBuilder:append	(Ljava/lang/String;)Ljava/lang/StringBuilder;
    //   34: astore 8
    //   36: getstatic 39	kkkkkk/xtxtxt:b042AЪ042AЪ042A042AЪЪ042A	I
    //   39: istore_2
    //   40: iload_2
    //   41: getstatic 66	kkkkkk/xtxtxt:bЪЪЪ042A042A042AЪЪ042A	I
    //   44: iload_2
    //   45: iadd
    //   46: imul
    //   47: getstatic 45	kkkkkk/xtxtxt:bЪ042A042AЪ042A042AЪЪ042A	I
    //   50: irem
    //   51: tableswitch	default:+17->68, 0:+29->80
    //   68: invokestatic 48	kkkkkk/xtxtxt:bи0438ии04380438и0438ии	()I
    //   71: putstatic 39	kkkkkk/xtxtxt:b042AЪ042AЪ042A042AЪЪ042A	I
    //   74: invokestatic 48	kkkkkk/xtxtxt:bи0438ии04380438и0438ии	()I
    //   77: putstatic 68	kkkkkk/xtxtxt:b042A042A042AЪ042A042AЪЪ042A	I
    //   80: invokestatic 48	kkkkkk/xtxtxt:bи0438ии04380438и0438ии	()I
    //   83: istore_2
    //   84: getstatic 66	kkkkkk/xtxtxt:bЪЪЪ042A042A042AЪЪ042A	I
    //   87: istore_3
    //   88: invokestatic 48	kkkkkk/xtxtxt:bи0438ии04380438и0438ии	()I
    //   91: istore 4
    //   93: getstatic 45	kkkkkk/xtxtxt:bЪ042A042AЪ042A042AЪЪ042A	I
    //   96: istore 5
    //   98: getstatic 68	kkkkkk/xtxtxt:b042A042A042AЪ042A042AЪЪ042A	I
    //   101: istore 6
    //   103: iload_2
    //   104: iload_3
    //   105: iadd
    //   106: iload 4
    //   108: imul
    //   109: iload 5
    //   111: irem
    //   112: iload 6
    //   114: if_icmpeq +14 -> 128
    //   117: invokestatic 48	kkkkkk/xtxtxt:bи0438ии04380438и0438ии	()I
    //   120: putstatic 39	kkkkkk/xtxtxt:b042AЪ042AЪ042A042AЪЪ042A	I
    //   123: bipush 15
    //   125: putstatic 68	kkkkkk/xtxtxt:b042A042A042AЪ042A042AЪЪ042A	I
    //   128: aload 8
    //   130: ldc -110
    //   132: sipush 243
    //   135: bipush 97
    //   137: iconst_3
    //   138: invokestatic 56	kkkkkk/gguuuu:bк043Aккк043Aкк043A043A	(Ljava/lang/String;CCC)Ljava/lang/String;
    //   141: invokevirtual 144	java/lang/StringBuilder:append	(Ljava/lang/String;)Ljava/lang/StringBuilder;
    //   144: invokevirtual 147	java/lang/StringBuilder:toString	()Ljava/lang/String;
    //   147: astore 8
    //   149: new 137	java/lang/StringBuilder
    //   152: dup
    //   153: invokespecial 138	java/lang/StringBuilder:<init>	()V
    //   156: astore 9
    //   158: aload 9
    //   160: ldc -107
    //   162: bipush 50
    //   164: iconst_2
    //   165: invokestatic 62	kkkkkk/gguuuu:bккккк043Aкк043A043A	(Ljava/lang/String;CC)Ljava/lang/String;
    //   168: invokevirtual 144	java/lang/StringBuilder:append	(Ljava/lang/String;)Ljava/lang/StringBuilder;
    //   171: aload_1
    //   172: invokevirtual 152	java/lang/Throwable:getMessage	()Ljava/lang/String;
    //   175: invokevirtual 144	java/lang/StringBuilder:append	(Ljava/lang/String;)Ljava/lang/StringBuilder;
    //   178: astore 9
    //   180: aload 7
    //   182: aload 8
    //   184: aload 9
    //   186: invokevirtual 147	java/lang/StringBuilder:toString	()Ljava/lang/String;
    //   189: invokeinterface 158 3 0
    //   194: aload_0
    //   195: aload_1
    //   196: invokestatic 160	kkkkkk/xtxtxt:b043804380438и04380438и0438ии	(Ljava/lang/Throwable;)Ljava/lang/String;
    //   199: ldc -94
    //   201: bipush 73
    //   203: sipush 184
    //   206: iconst_3
    //   207: invokestatic 56	kkkkkk/gguuuu:bк043Aккк043Aкк043A043A	(Ljava/lang/String;CCC)Ljava/lang/String;
    //   210: invokestatic 164	kkkkkk/xtxtxt:b0438043804380438и0438и0438ии	(Ljava/lang/String;Ljava/lang/String;Ljava/lang/String;)V
    //   213: return
    //   214: astore_0
    //   215: aload_0
    //   216: athrow
    //   217: astore_0
    //   218: aload_0
    //   219: athrow
    // Local variable table:
    //   start	length	slot	name	signature
    //   0	220	0	paramString	String
    //   0	220	1	paramThrowable	Throwable
    //   39	67	2	i	int
    //   87	19	3	j	int
    //   91	18	4	k	int
    //   96	16	5	m	int
    //   101	14	6	n	int
    //   9	172	7	localTtxtxt	ttxtxt
    //   34	149	8	localObject	Object
    //   156	29	9	localStringBuilder	StringBuilder
    // Exception table:
    //   from	to	target	type
    //   0	36	214	java/lang/Exception
    //   80	103	214	java/lang/Exception
    //   128	149	214	java/lang/Exception
    //   158	180	214	java/lang/Exception
    //   194	213	214	java/lang/Exception
    //   117	128	217	java/lang/Exception
    //   149	158	217	java/lang/Exception
    //   180	194	217	java/lang/Exception
  }
  
  /* Error */
  public static void b0438и0438и04380438и0438ии(String paramString1, String paramString2)
  {
    // Byte code:
    //   0: getstatic 74	kkkkkk/xtxtxt:bЪ042A042A042AЪ042AЪЪ042A	Z
    //   3: istore 5
    //   5: goto +183 -> 188
    //   8: iload 5
    //   10: ifeq +157 -> 167
    //   13: getstatic 81	kkkkkk/xtxtxt:bЪЪ042AЪ042A042AЪЪ042A	Lkkkkkk/ttxtxt;
    //   16: astore 6
    //   18: new 137	java/lang/StringBuilder
    //   21: dup
    //   22: invokespecial 138	java/lang/StringBuilder:<init>	()V
    //   25: ldc -89
    //   27: sipush 176
    //   30: iconst_2
    //   31: invokestatic 62	kkkkkk/gguuuu:bккккк043Aкк043A043A	(Ljava/lang/String;CC)Ljava/lang/String;
    //   34: invokevirtual 144	java/lang/StringBuilder:append	(Ljava/lang/String;)Ljava/lang/StringBuilder;
    //   37: aload_0
    //   38: invokevirtual 144	java/lang/StringBuilder:append	(Ljava/lang/String;)Ljava/lang/StringBuilder;
    //   41: astore 7
    //   43: aload 7
    //   45: ldc -87
    //   47: sipush 240
    //   50: iconst_2
    //   51: invokestatic 62	kkkkkk/gguuuu:bккккк043Aкк043A043A	(Ljava/lang/String;CC)Ljava/lang/String;
    //   54: invokevirtual 144	java/lang/StringBuilder:append	(Ljava/lang/String;)Ljava/lang/StringBuilder;
    //   57: invokevirtual 147	java/lang/StringBuilder:toString	()Ljava/lang/String;
    //   60: astore 7
    //   62: aload 6
    //   64: aload 7
    //   66: aload_1
    //   67: invokeinterface 172 3 0
    //   72: getstatic 39	kkkkkk/xtxtxt:b042AЪ042AЪ042A042AЪЪ042A	I
    //   75: istore_2
    //   76: getstatic 66	kkkkkk/xtxtxt:bЪЪЪ042A042A042AЪЪ042A	I
    //   79: istore_3
    //   80: getstatic 45	kkkkkk/xtxtxt:bЪ042A042AЪ042A042AЪЪ042A	I
    //   83: istore 4
    //   85: iload_2
    //   86: iload_3
    //   87: iload_2
    //   88: iadd
    //   89: imul
    //   90: iload 4
    //   92: irem
    //   93: tableswitch	default:+19->112, 0:+74->167
    //   112: bipush 46
    //   114: putstatic 39	kkkkkk/xtxtxt:b042AЪ042AЪ042A042AЪЪ042A	I
    //   117: invokestatic 48	kkkkkk/xtxtxt:bи0438ии04380438и0438ии	()I
    //   120: putstatic 68	kkkkkk/xtxtxt:b042A042A042AЪ042A042AЪЪ042A	I
    //   123: getstatic 39	kkkkkk/xtxtxt:b042AЪ042AЪ042A042AЪЪ042A	I
    //   126: istore_2
    //   127: iload_2
    //   128: invokestatic 43	kkkkkk/xtxtxt:b0438иии04380438и0438ии	()I
    //   131: iload_2
    //   132: iadd
    //   133: imul
    //   134: getstatic 45	kkkkkk/xtxtxt:bЪ042A042AЪ042A042AЪЪ042A	I
    //   137: irem
    //   138: tableswitch	default:+18->156, 0:+29->167
    //   156: bipush 17
    //   158: putstatic 39	kkkkkk/xtxtxt:b042AЪ042AЪ042A042AЪЪ042A	I
    //   161: invokestatic 48	kkkkkk/xtxtxt:bи0438ии04380438и0438ии	()I
    //   164: putstatic 68	kkkkkk/xtxtxt:b042A042A042AЪ042A042AЪЪ042A	I
    //   167: aload_0
    //   168: aload_1
    //   169: ldc -82
    //   171: sipush 185
    //   174: iconst_3
    //   175: invokestatic 62	kkkkkk/gguuuu:bккккк043Aкк043A043A	(Ljava/lang/String;CC)Ljava/lang/String;
    //   178: invokestatic 177	kkkkkk/xtxtxt:b0438ии043804380438и0438ии	(Ljava/lang/String;Ljava/lang/String;Ljava/lang/String;)V
    //   181: return
    //   182: astore_0
    //   183: aload_0
    //   184: athrow
    //   185: astore_0
    //   186: aload_0
    //   187: athrow
    //   188: iconst_0
    //   189: tableswitch	default:+23->212, 0:+-181->8, 1:+-1->188
    //   212: iconst_0
    //   213: tableswitch	default:+23->236, 0:+-205->8, 1:+-25->188
    //   236: goto -24 -> 212
    // Local variable table:
    //   start	length	slot	name	signature
    //   0	239	0	paramString1	String
    //   0	239	1	paramString2	String
    //   75	59	2	i	int
    //   79	10	3	j	int
    //   83	10	4	k	int
    //   3	6	5	bool	boolean
    //   16	47	6	localTtxtxt	ttxtxt
    //   41	24	7	localObject	Object
    // Exception table:
    //   from	to	target	type
    //   0	5	182	java/lang/Exception
    //   13	43	182	java/lang/Exception
    //   62	85	182	java/lang/Exception
    //   167	181	182	java/lang/Exception
    //   43	62	185	java/lang/Exception
    //   112	123	185	java/lang/Exception
  }
  
  /* Error */
  private static void b0438ии043804380438и0438ии(String paramString1, String paramString2, String paramString3)
  {
    // Byte code:
    //   0: new 87	kkkkkk/tttxxt
    //   3: dup
    //   4: aload_2
    //   5: ldc -77
    //   7: sipush 228
    //   10: bipush 73
    //   12: iconst_3
    //   13: invokestatic 56	kkkkkk/gguuuu:bк043Aккк043Aкк043A043A	(Ljava/lang/String;CCC)Ljava/lang/String;
    //   16: aload_1
    //   17: aload_0
    //   18: invokespecial 92	kkkkkk/tttxxt:<init>	(Ljava/lang/String;Ljava/lang/String;Ljava/lang/String;Ljava/lang/String;)V
    //   21: astore_0
    //   22: getstatic 39	kkkkkk/xtxtxt:b042AЪ042AЪ042A042AЪЪ042A	I
    //   25: istore_3
    //   26: iload_3
    //   27: getstatic 66	kkkkkk/xtxtxt:bЪЪЪ042A042A042AЪЪ042A	I
    //   30: iload_3
    //   31: iadd
    //   32: imul
    //   33: invokestatic 133	kkkkkk/xtxtxt:b04380438ии04380438и0438ии	()I
    //   36: irem
    //   37: tableswitch	default:+19->56, 0:+74->111
    //   56: invokestatic 48	kkkkkk/xtxtxt:bи0438ии04380438и0438ии	()I
    //   59: putstatic 39	kkkkkk/xtxtxt:b042AЪ042AЪ042A042AЪЪ042A	I
    //   62: invokestatic 48	kkkkkk/xtxtxt:bи0438ии04380438и0438ии	()I
    //   65: putstatic 68	kkkkkk/xtxtxt:b042A042A042AЪ042A042AЪЪ042A	I
    //   68: invokestatic 48	kkkkkk/xtxtxt:bи0438ии04380438и0438ии	()I
    //   71: istore_3
    //   72: iload_3
    //   73: invokestatic 43	kkkkkk/xtxtxt:b0438иии04380438и0438ии	()I
    //   76: iload_3
    //   77: iadd
    //   78: imul
    //   79: getstatic 45	kkkkkk/xtxtxt:bЪ042A042AЪ042A042AЪЪ042A	I
    //   82: irem
    //   83: tableswitch	default:+17->100, 0:+28->111
    //   100: bipush 74
    //   102: putstatic 39	kkkkkk/xtxtxt:b042AЪ042AЪ042A042AЪЪ042A	I
    //   105: invokestatic 48	kkkkkk/xtxtxt:bи0438ии04380438и0438ии	()I
    //   108: putstatic 68	kkkkkk/xtxtxt:b042A042A042AЪ042A042AЪЪ042A	I
    //   111: getstatic 98	kkkkkk/xxdxxd:instance	Lkkkkkk/xxdxxd;
    //   114: astore_1
    //   115: aload_1
    //   116: invokevirtual 102	kkkkkk/xxdxxd:b0445х0445044504450445х044504450445	()Lkkkkkk/txxtxt;
    //   119: astore_1
    //   120: iconst_1
    //   121: tableswitch	default:+23->144, 0:+-1->120, 1:+50->171
    //   144: iconst_0
    //   145: tableswitch	default:+23->168, 0:+26->171, 1:+-25->120
    //   168: goto -24 -> 144
    //   171: aload_1
    //   172: ifnull +8 -> 180
    //   175: aload_1
    //   176: aload_0
    //   177: invokevirtual 182	kkkkkk/txxtxt:b0438043804380438ии04380438ии	(Lkkkkkk/tttxxt;)V
    //   180: return
    //   181: astore_0
    //   182: aload_0
    //   183: athrow
    //   184: astore_0
    //   185: aload_0
    //   186: athrow
    // Local variable table:
    //   start	length	slot	name	signature
    //   0	187	0	paramString1	String
    //   0	187	1	paramString2	String
    //   0	187	2	paramString3	String
    //   25	54	3	i	int
    // Exception table:
    //   from	to	target	type
    //   111	115	181	java/lang/Exception
    //   175	180	181	java/lang/Exception
    //   0	22	184	java/lang/Exception
    //   115	120	184	java/lang/Exception
  }
  
  public static int b0438иии04380438и0438ии()
  {
    return 1;
  }
  
  public static void bи04380438и04380438и0438ии(String paramString, Throwable paramThrowable)
  {
    try
    {
      bool = bЪ042A042A042AЪ042AЪЪ042A;
    }
    catch (Exception paramString)
    {
      try
      {
        boolean bool;
        ttxtxt localTtxtxt;
        int j;
        int k = b042AЪ042AЪ042A042AЪЪ042A;
        int m = bЪ042A042AЪ042A042AЪЪ042A;
        int n = b042A042A042AЪ042A042AЪЪ042A;
        if ((i + j) * k % m != n)
        {
          b042AЪ042AЪ042A042AЪЪ042A = bи0438ии04380438и0438ии();
          b042A042A042AЪ042A042AЪЪ042A = 61;
        }
        Object localObject = gguuuu.bк043Aккк043Aкк043A043A("10", '', '\'', '\000');
        StringBuilder localStringBuilder = new StringBuilder();
        localStringBuilder = localStringBuilder.append(gguuuu.bккккк043Aкк043A043A("4BCAE\024", 'O', '\001'));
        String str = paramThrowable.getMessage();
        localTtxtxt.bи0438и0438и0438и0438ии((String)localObject, str);
        paramThrowable.printStackTrace();
        int i = bи0438ии04380438и0438ии();
        switch (i * (bЪЪЪ042A042A042AЪЪ042A + i) % b04380438ии04380438и0438ии())
        {
        default: 
          b042AЪ042AЪ042A042AЪЪ042A = bи0438ии04380438и0438ии();
          b042A042A042AЪ042A042AЪЪ042A = bи0438ии04380438и0438ии();
        }
        b0438ии043804380438и0438ии(paramString, b043804380438и04380438и0438ии(paramThrowable), gguuuu.bккккк043Aкк043A043A("\033'&\"$", '', '\003'));
        return;
      }
      catch (Exception paramString)
      {
        throw paramString;
      }
      paramString = paramString;
      throw paramString;
    }
    if (bool)
    {
      localTtxtxt = bЪЪ042AЪ042A042AЪЪ042A;
      localObject = new StringBuilder().append(gguuuu.bккккк043Aкк043A043A("Fbn\\fZffa_\020\031\030", '', '\002')).append(paramString);
      i = b042AЪ042AЪ042A042AЪЪ042A;
      j = bЪЪЪ042A042A042AЪЪ042A;
    }
    switch (1)
    {
    }
    for (;;)
    {
      switch (0)
      {
      }
    }
  }
  
  public static void bи0438и043804380438и0438ии(boolean paramBoolean)
  {
    if ((bи0438ии04380438и0438ии() + bЪЪЪ042A042A042AЪЪ042A) * bи0438ии04380438и0438ии() % bЪ042A042AЪ042A042AЪЪ042A != b042A042A042AЪ042A042AЪЪ042A)
    {
      if ((b042AЪ042AЪ042A042AЪЪ042A + bЪЪЪ042A042A042AЪЪ042A) * b042AЪ042AЪ042A042AЪЪ042A % bЪ042A042AЪ042A042AЪЪ042A != b042A042A042AЪ042A042AЪЪ042A)
      {
        b042AЪ042AЪ042A042AЪЪ042A = bи0438ии04380438и0438ии();
        b042A042A042AЪ042A042AЪЪ042A = 69;
      }
      b042AЪ042AЪ042A042AЪЪ042A = bи0438ии04380438и0438ии();
      b042A042A042AЪ042A042AЪЪ042A = 7;
      switch (0)
      {
      case 1: 
      default: 
        for (;;)
        {
          switch (0)
          {
          }
        }
      }
    }
    try
    {
      bЪ042A042A042AЪ042AЪЪ042A = paramBoolean;
      return;
    }
    catch (Exception localException)
    {
      throw localException;
    }
  }
  
  public static int bи0438ии04380438и0438ии()
  {
    return 32;
  }
  
  /* Error */
  public static void bии0438043804380438и0438ии(String paramString1, String paramString2)
  {
    // Byte code:
    //   0: getstatic 74	kkkkkk/xtxtxt:bЪ042A042A042AЪ042AЪЪ042A	Z
    //   3: ifeq +148 -> 151
    //   6: getstatic 81	kkkkkk/xtxtxt:bЪЪ042AЪ042A042AЪЪ042A	Lkkkkkk/ttxtxt;
    //   9: astore 7
    //   11: getstatic 39	kkkkkk/xtxtxt:b042AЪ042AЪ042A042AЪЪ042A	I
    //   14: istore_2
    //   15: invokestatic 43	kkkkkk/xtxtxt:b0438иии04380438и0438ии	()I
    //   18: istore_3
    //   19: getstatic 39	kkkkkk/xtxtxt:b042AЪ042AЪ042A042AЪЪ042A	I
    //   22: istore 4
    //   24: getstatic 45	kkkkkk/xtxtxt:bЪ042A042AЪ042A042AЪЪ042A	I
    //   27: istore 5
    //   29: getstatic 68	kkkkkk/xtxtxt:b042A042A042AЪ042A042AЪЪ042A	I
    //   32: istore 6
    //   34: iload_2
    //   35: iload_3
    //   36: iadd
    //   37: iload 4
    //   39: imul
    //   40: iload 5
    //   42: irem
    //   43: iload 6
    //   45: if_icmpeq +46 -> 91
    //   48: invokestatic 48	kkkkkk/xtxtxt:bи0438ии04380438и0438ии	()I
    //   51: putstatic 39	kkkkkk/xtxtxt:b042AЪ042AЪ042A042AЪЪ042A	I
    //   54: invokestatic 48	kkkkkk/xtxtxt:bи0438ии04380438и0438ии	()I
    //   57: putstatic 68	kkkkkk/xtxtxt:b042A042A042AЪ042A042AЪЪ042A	I
    //   60: getstatic 39	kkkkkk/xtxtxt:b042AЪ042AЪ042A042AЪЪ042A	I
    //   63: invokestatic 43	kkkkkk/xtxtxt:b0438иии04380438и0438ии	()I
    //   66: iadd
    //   67: getstatic 39	kkkkkk/xtxtxt:b042AЪ042AЪ042A042AЪЪ042A	I
    //   70: imul
    //   71: getstatic 45	kkkkkk/xtxtxt:bЪ042A042AЪ042A042AЪЪ042A	I
    //   74: irem
    //   75: getstatic 68	kkkkkk/xtxtxt:b042A042A042AЪ042A042AЪЪ042A	I
    //   78: if_icmpeq +13 -> 91
    //   81: bipush 28
    //   83: putstatic 39	kkkkkk/xtxtxt:b042AЪ042AЪ042A042AЪЪ042A	I
    //   86: bipush 10
    //   88: putstatic 68	kkkkkk/xtxtxt:b042A042A042AЪ042A042AЪЪ042A	I
    //   91: new 137	java/lang/StringBuilder
    //   94: dup
    //   95: invokespecial 138	java/lang/StringBuilder:<init>	()V
    //   98: astore 8
    //   100: aload 8
    //   102: ldc -58
    //   104: sipush 190
    //   107: iconst_5
    //   108: invokestatic 62	kkkkkk/gguuuu:bккккк043Aкк043A043A	(Ljava/lang/String;CC)Ljava/lang/String;
    //   111: invokevirtual 144	java/lang/StringBuilder:append	(Ljava/lang/String;)Ljava/lang/StringBuilder;
    //   114: astore 8
    //   116: aload 8
    //   118: aload_0
    //   119: invokevirtual 144	java/lang/StringBuilder:append	(Ljava/lang/String;)Ljava/lang/StringBuilder;
    //   122: ldc -56
    //   124: bipush 7
    //   126: sipush 135
    //   129: iconst_0
    //   130: invokestatic 56	kkkkkk/gguuuu:bк043Aккк043Aкк043A043A	(Ljava/lang/String;CCC)Ljava/lang/String;
    //   133: invokevirtual 144	java/lang/StringBuilder:append	(Ljava/lang/String;)Ljava/lang/StringBuilder;
    //   136: invokevirtual 147	java/lang/StringBuilder:toString	()Ljava/lang/String;
    //   139: astore 8
    //   141: aload 7
    //   143: aload 8
    //   145: aload_1
    //   146: invokeinterface 158 3 0
    //   151: aload_0
    //   152: aload_1
    //   153: ldc -54
    //   155: bipush 63
    //   157: bipush 46
    //   159: iconst_1
    //   160: invokestatic 56	kkkkkk/gguuuu:bк043Aккк043Aкк043A043A	(Ljava/lang/String;CCC)Ljava/lang/String;
    //   163: invokestatic 164	kkkkkk/xtxtxt:b0438043804380438и0438и0438ии	(Ljava/lang/String;Ljava/lang/String;Ljava/lang/String;)V
    //   166: return
    //   167: astore_0
    //   168: aload_0
    //   169: athrow
    //   170: astore_0
    //   171: aload_0
    //   172: athrow
    // Local variable table:
    //   start	length	slot	name	signature
    //   0	173	0	paramString1	String
    //   0	173	1	paramString2	String
    //   14	23	2	i	int
    //   18	19	3	j	int
    //   22	18	4	k	int
    //   27	16	5	m	int
    //   32	14	6	n	int
    //   9	133	7	localTtxtxt	ttxtxt
    //   98	46	8	localObject	Object
    // Exception table:
    //   from	to	target	type
    //   15	34	167	java/lang/Exception
    //   100	116	167	java/lang/Exception
    //   141	151	167	java/lang/Exception
    //   151	166	167	java/lang/Exception
    //   0	15	170	java/lang/Exception
    //   48	60	170	java/lang/Exception
    //   91	100	170	java/lang/Exception
    //   116	141	170	java/lang/Exception
  }
  
  public static void bии0438и04380438и0438ии(String paramString1, String paramString2)
  {
    if (bЪ042A042A042AЪ042AЪЪ042A)
    {
      ttxtxt localTtxtxt = bЪЪ042AЪ042A042AЪЪ042A;
      StringBuilder localStringBuilder = new StringBuilder();
      String str = gguuuu.bк043Aккк043Aкк043A043A("Plxfpdppki\032#\"", 'ñ', '\t', '\002');
      int i = b042AЪ042AЪ042A042AЪЪ042A;
      switch (i * (bЪЪЪ042A042A042AЪЪ042A + i) % bЪ042A042AЪ042A042AЪЪ042A)
      {
      default: 
        b042AЪ042AЪ042A042AЪЪ042A = bи0438ии04380438и0438ии();
        b042A042A042AЪ042A042AЪЪ042A = 75;
      }
      localTtxtxt.bиии0438и0438и0438ии(str + paramString1 + gguuuu.bккккк043Aкк043A043A("KJ", 'Ý', '\005'), paramString2);
    }
  }
  
  /* Error */
  public static void bиии043804380438и0438ии(String paramString1, String paramString2)
  {
    // Byte code:
    //   0: getstatic 74	kkkkkk/xtxtxt:bЪ042A042A042AЪ042AЪЪ042A	Z
    //   3: ifeq +139 -> 142
    //   6: getstatic 81	kkkkkk/xtxtxt:bЪЪ042AЪ042A042AЪЪ042A	Lkkkkkk/ttxtxt;
    //   9: astore 7
    //   11: new 137	java/lang/StringBuilder
    //   14: dup
    //   15: invokespecial 138	java/lang/StringBuilder:<init>	()V
    //   18: astore 8
    //   20: getstatic 39	kkkkkk/xtxtxt:b042AЪ042AЪ042A042AЪЪ042A	I
    //   23: istore_2
    //   24: getstatic 66	kkkkkk/xtxtxt:bЪЪЪ042A042A042AЪЪ042A	I
    //   27: istore_3
    //   28: getstatic 39	kkkkkk/xtxtxt:b042AЪ042AЪ042A042AЪЪ042A	I
    //   31: istore 4
    //   33: getstatic 45	kkkkkk/xtxtxt:bЪ042A042AЪ042A042AЪЪ042A	I
    //   36: istore 5
    //   38: getstatic 68	kkkkkk/xtxtxt:b042A042A042AЪ042A042AЪЪ042A	I
    //   41: istore 6
    //   43: iload_2
    //   44: iload_3
    //   45: iadd
    //   46: iload 4
    //   48: imul
    //   49: iload 5
    //   51: irem
    //   52: iload 6
    //   54: if_icmpeq +45 -> 99
    //   57: bipush 99
    //   59: putstatic 39	kkkkkk/xtxtxt:b042AЪ042AЪ042A042AЪЪ042A	I
    //   62: invokestatic 48	kkkkkk/xtxtxt:bи0438ии04380438и0438ии	()I
    //   65: putstatic 68	kkkkkk/xtxtxt:b042A042A042AЪ042A042AЪЪ042A	I
    //   68: getstatic 39	kkkkkk/xtxtxt:b042AЪ042AЪ042A042AЪЪ042A	I
    //   71: getstatic 66	kkkkkk/xtxtxt:bЪЪЪ042A042A042AЪЪ042A	I
    //   74: iadd
    //   75: getstatic 39	kkkkkk/xtxtxt:b042AЪ042AЪ042A042AЪЪ042A	I
    //   78: imul
    //   79: getstatic 45	kkkkkk/xtxtxt:bЪ042A042AЪ042A042AЪЪ042A	I
    //   82: irem
    //   83: invokestatic 214	kkkkkk/xtxtxt:bииии04380438и0438ии	()I
    //   86: if_icmpeq +13 -> 99
    //   89: invokestatic 48	kkkkkk/xtxtxt:bи0438ии04380438и0438ии	()I
    //   92: putstatic 39	kkkkkk/xtxtxt:b042AЪ042AЪ042A042AЪЪ042A	I
    //   95: iconst_0
    //   96: putstatic 68	kkkkkk/xtxtxt:b042A042A042AЪ042A042AЪЪ042A	I
    //   99: aload 8
    //   101: ldc -40
    //   103: bipush 107
    //   105: iconst_5
    //   106: invokestatic 62	kkkkkk/gguuuu:bккккк043Aкк043A043A	(Ljava/lang/String;CC)Ljava/lang/String;
    //   109: invokevirtual 144	java/lang/StringBuilder:append	(Ljava/lang/String;)Ljava/lang/StringBuilder;
    //   112: aload_0
    //   113: invokevirtual 144	java/lang/StringBuilder:append	(Ljava/lang/String;)Ljava/lang/StringBuilder;
    //   116: ldc -38
    //   118: bipush 9
    //   120: iconst_0
    //   121: invokestatic 62	kkkkkk/gguuuu:bккккк043Aкк043A043A	(Ljava/lang/String;CC)Ljava/lang/String;
    //   124: invokevirtual 144	java/lang/StringBuilder:append	(Ljava/lang/String;)Ljava/lang/StringBuilder;
    //   127: astore 8
    //   129: aload 7
    //   131: aload 8
    //   133: invokevirtual 147	java/lang/StringBuilder:toString	()Ljava/lang/String;
    //   136: aload_1
    //   137: invokeinterface 221 3 0
    //   142: aload_0
    //   143: aload_1
    //   144: ldc -33
    //   146: bipush 106
    //   148: iconst_1
    //   149: invokestatic 62	kkkkkk/gguuuu:bккккк043Aкк043A043A	(Ljava/lang/String;CC)Ljava/lang/String;
    //   152: invokestatic 164	kkkkkk/xtxtxt:b0438043804380438и0438и0438ии	(Ljava/lang/String;Ljava/lang/String;Ljava/lang/String;)V
    //   155: return
    //   156: astore_0
    //   157: aload_0
    //   158: athrow
    //   159: astore_0
    //   160: aload_0
    //   161: athrow
    //   162: astore_0
    //   163: aload_0
    //   164: athrow
    //   165: astore_0
    //   166: aload_0
    //   167: athrow
    // Local variable table:
    //   start	length	slot	name	signature
    //   0	168	0	paramString1	String
    //   0	168	1	paramString2	String
    //   23	23	2	i	int
    //   27	19	3	j	int
    //   31	18	4	k	int
    //   36	16	5	m	int
    //   41	14	6	n	int
    //   9	121	7	localTtxtxt	ttxtxt
    //   18	114	8	localStringBuilder	StringBuilder
    // Exception table:
    //   from	to	target	type
    //   0	20	156	java/lang/Exception
    //   99	129	156	java/lang/Exception
    //   28	43	159	java/lang/Exception
    //   157	159	159	java/lang/Exception
    //   163	165	159	java/lang/Exception
    //   129	142	162	java/lang/Exception
    //   142	155	162	java/lang/Exception
    //   20	28	165	java/lang/Exception
    //   57	68	165	java/lang/Exception
  }
  
  public static int bииии04380438и0438ии()
  {
    return 0;
  }
}
