package kkkkkk;

import android.content.Context;
import android.content.SharedPreferences;
import android.content.SharedPreferences.Editor;
import java.util.Set;

public class xtxxxt
{
  private static volatile SharedPreferences b042A042A042A042A042A042A042AЪ042A;
  public static final String b042A042AЪ042A042A042A042AЪ042A = "hegfXkn_iW[QaX^b\\K^RJZPTLCHPBBKCA;KL>><H:B670;4G";
  public static int b042A042AЪЪЪЪЪ042A042A = 98;
  public static final String b042AЪ042A042A042A042A042AЪ042A = "I>H81D5CB6:2=(8/593\"5)!1'+#\032\037'\031\031\"\032\030\022\"#\025\025\023\037\021\031\r\016\007\022\013\036";
  public static final String b042AЪЪ042A042A042A042AЪ042A = gguuuu.bккккк043Aкк043A043A(b042AЪЪ042A042A042A042AЪ042A, 'u', '\002');
  public static int b042AЪЪЪЪЪЪ042A042A = 1;
  private static final String bЪ042A042A042A042A042A042AЪ042A;
  private static volatile xtxxxt bЪ042AЪ042A042A042A042AЪ042A;
  public static int bЪ042AЪЪЪЪЪ042A042A = 2;
  private static final String bЪЪ042A042A042A042A042AЪ042A = "\036#\023(\036\030*\036\036";
  public static int bЪЪЪЪЪЪЪ042A042A;
  
  /* Error */
  static
  {
    // Byte code:
    //   0: getstatic 36	kkkkkk/xtxxxt:b042AЪЪ042A042A042A042AЪ042A	Ljava/lang/String;
    //   3: bipush 117
    //   5: iconst_2
    //   6: invokestatic 42	kkkkkk/gguuuu:bккккк043Aкк043A043A	(Ljava/lang/String;CC)Ljava/lang/String;
    //   9: putstatic 36	kkkkkk/xtxxxt:b042AЪЪ042A042A042A042AЪ042A	Ljava/lang/String;
    //   12: getstatic 44	kkkkkk/xtxxxt:b042A042AЪ042A042A042A042AЪ042A	Ljava/lang/String;
    //   15: sipush 129
    //   18: sipush 255
    //   21: iconst_2
    //   22: invokestatic 48	kkkkkk/gguuuu:bк043Aккк043Aкк043A043A	(Ljava/lang/String;CCC)Ljava/lang/String;
    //   25: putstatic 44	kkkkkk/xtxxxt:b042A042AЪ042A042A042A042AЪ042A	Ljava/lang/String;
    //   28: getstatic 50	kkkkkk/xtxxxt:bЪЪ042A042A042A042A042AЪ042A	Ljava/lang/String;
    //   31: sipush 201
    //   34: sipush 152
    //   37: iconst_1
    //   38: invokestatic 48	kkkkkk/gguuuu:bк043Aккк043Aкк043A043A	(Ljava/lang/String;CCC)Ljava/lang/String;
    //   41: astore 5
    //   43: invokestatic 54	kkkkkk/xtxxxt:b0438иии0438043804380438ии	()I
    //   46: istore_0
    //   47: getstatic 56	kkkkkk/xtxxxt:b042AЪЪЪЪЪЪ042A042A	I
    //   50: istore_1
    //   51: invokestatic 54	kkkkkk/xtxxxt:b0438иии0438043804380438ии	()I
    //   54: istore_2
    //   55: getstatic 58	kkkkkk/xtxxxt:bЪ042AЪЪЪЪЪ042A042A	I
    //   58: istore_3
    //   59: getstatic 60	kkkkkk/xtxxxt:bЪЪЪЪЪЪЪ042A042A	I
    //   62: istore 4
    //   64: iload_0
    //   65: iload_1
    //   66: iadd
    //   67: iload_2
    //   68: imul
    //   69: iload_3
    //   70: irem
    //   71: iload 4
    //   73: if_icmpeq +9 -> 82
    //   76: invokestatic 54	kkkkkk/xtxxxt:b0438иии0438043804380438ии	()I
    //   79: putstatic 60	kkkkkk/xtxxxt:bЪЪЪЪЪЪЪ042A042A	I
    //   82: aload 5
    //   84: putstatic 50	kkkkkk/xtxxxt:bЪЪ042A042A042A042A042AЪ042A	Ljava/lang/String;
    //   87: getstatic 62	kkkkkk/xtxxxt:b042AЪ042A042A042A042A042AЪ042A	Ljava/lang/String;
    //   90: astore 5
    //   92: getstatic 64	kkkkkk/xtxxxt:b042A042AЪЪЪЪЪ042A042A	I
    //   95: invokestatic 67	kkkkkk/xtxxxt:bи0438ии0438043804380438ии	()I
    //   98: iadd
    //   99: getstatic 64	kkkkkk/xtxxxt:b042A042AЪЪЪЪЪ042A042A	I
    //   102: imul
    //   103: getstatic 58	kkkkkk/xtxxxt:bЪ042AЪЪЪЪЪ042A042A	I
    //   106: irem
    //   107: invokestatic 70	kkkkkk/xtxxxt:b0438и0438и0438043804380438ии	()I
    //   110: if_icmpeq +15 -> 125
    //   113: invokestatic 54	kkkkkk/xtxxxt:b0438иии0438043804380438ии	()I
    //   116: putstatic 64	kkkkkk/xtxxxt:b042A042AЪЪЪЪЪ042A042A	I
    //   119: invokestatic 54	kkkkkk/xtxxxt:b0438иии0438043804380438ии	()I
    //   122: putstatic 60	kkkkkk/xtxxxt:bЪЪЪЪЪЪЪ042A042A	I
    //   125: aload 5
    //   127: sipush 229
    //   130: bipush 60
    //   132: iconst_0
    //   133: invokestatic 48	kkkkkk/gguuuu:bк043Aккк043Aкк043A043A	(Ljava/lang/String;CCC)Ljava/lang/String;
    //   136: astore 5
    //   138: aload 5
    //   140: putstatic 62	kkkkkk/xtxxxt:b042AЪ042A042A042A042A042AЪ042A	Ljava/lang/String;
    //   143: ldc 2
    //   145: invokevirtual 76	java/lang/Class:getSimpleName	()Ljava/lang/String;
    //   148: putstatic 78	kkkkkk/xtxxxt:bЪ042A042A042A042A042A042AЪ042A	Ljava/lang/String;
    //   151: aconst_null
    //   152: putstatic 80	kkkkkk/xtxxxt:bЪ042AЪ042A042A042A042AЪ042A	Lkkkkkk/xtxxxt;
    //   155: return
    //   156: astore 5
    //   158: aload 5
    //   160: athrow
    //   161: astore 5
    //   163: aload 5
    //   165: athrow
    //   166: astore 5
    //   168: aload 5
    //   170: athrow
    //   171: astore 5
    //   173: aload 5
    //   175: athrow
    // Local variable table:
    //   start	length	slot	name	signature
    //   46	21	0	i	int
    //   50	17	1	j	int
    //   54	15	2	k	int
    //   58	13	3	m	int
    //   62	12	4	n	int
    //   41	98	5	str	String
    //   156	3	5	localException1	Exception
    //   161	3	5	localException2	Exception
    //   166	3	5	localException3	Exception
    //   171	3	5	localException4	Exception
    // Exception table:
    //   from	to	target	type
    //   82	92	156	java/lang/Exception
    //   138	155	156	java/lang/Exception
    //   76	82	161	java/lang/Exception
    //   158	161	161	java/lang/Exception
    //   168	171	161	java/lang/Exception
    //   0	43	166	java/lang/Exception
    //   125	138	166	java/lang/Exception
    //   43	64	171	java/lang/Exception
  }
  
  private xtxxxt()
  {
    b042A042A042A042A042A042A042AЪ042A = xxdxxd.instance.bххх044504450445х044504450445().getSharedPreferences(gguuuu.bк043Aккк043Aкк043A043A("JM;NB:J<:", 'ó', 'Ñ', '\000'), 0);
  }
  
  private String b04380438ии0438043804380438ии(String paramString1, String paramString2)
  {
    StringBuilder localStringBuilder = new StringBuilder();
    int i = b042A042AЪЪЪЪЪ042A042A;
    switch (i * (b042AЪЪЪЪЪЪ042A042A + i) % bЪ042AЪЪЪЪЪ042A042A)
    {
    default: 
      switch (0)
      {
      case 1: 
      default: 
        for (;;)
        {
          switch (1)
          {
          }
        }
      }
      b042A042AЪЪЪЪЪ042A042A = 72;
      bЪЪЪЪЪЪЪ042A042A = 26;
    }
    paramString1 = localStringBuilder.append(paramString1).append(gguuuu.bк043Aккк043Aкк043A043A("\005\006", '$', 'C', '\001'));
    switch (0)
    {
    case 1: 
    default: 
      for (;;)
      {
        if ((b042A042AЪЪЪЪЪ042A042A + b042AЪЪЪЪЪЪ042A042A) * b042A042AЪЪЪЪЪ042A042A % bии0438и0438043804380438ии() != b0438и0438и0438043804380438ии())
        {
          b042A042AЪЪЪЪЪ042A042A = b0438иии0438043804380438ии();
          bЪЪЪЪЪЪЪ042A042A = 45;
        }
        switch (1)
        {
        }
      }
    }
    return paramString2;
  }
  
  public static int b0438и0438и0438043804380438ии()
  {
    return 0;
  }
  
  public static xtxxxt b0438ии04380438043804380438ии()
  {
    if (bЪ042AЪ042A042A042A042AЪ042A == null) {
      switch (1)
      {
      case 0: 
      default: 
        for (;;)
        {
          switch (1)
          {
          case 0: 
          default: 
            for (;;)
            {
              switch (0)
              {
              }
            }
          }
          switch (1)
          {
          }
        }
      }
    }
    try
    {
      if (bЪ042AЪ042A042A042A042AЪ042A == null) {
        bЪ042AЪ042A042A042A042AЪ042A = new xtxxxt();
      }
      return bЪ042AЪ042A042A042A042AЪ042A;
    }
    finally {}
  }
  
  public static int b0438иии0438043804380438ии()
  {
    return 90;
  }
  
  public static int bи0438ии0438043804380438ии()
  {
    return 1;
  }
  
  public static int bии0438и0438043804380438ии()
  {
    return 2;
  }
  
  public void b04380438043804380438043804380438ии(String paramString1, String paramString2)
  {
    SharedPreferences.Editor localEditor = b042A042A042A042A042A042A042AЪ042A.edit();
    switch (0)
    {
    case 1: 
    default: 
      for (;;)
      {
        switch (0)
        {
        }
      }
    }
    paramString1 = b04380438ии0438043804380438ии(paramString1, paramString2);
    int i = b0438иии0438043804380438ии();
    switch (i * (b042AЪЪЪЪЪЪ042A042A + i) % bЪ042AЪЪЪЪЪ042A042A)
    {
    default: 
      b042A042AЪЪЪЪЪ042A042A = b0438иии0438043804380438ии();
      bЪЪЪЪЪЪЪ042A042A = 96;
    }
    localEditor.remove(paramString1).apply();
  }
  
  public boolean b043804380438и0438043804380438ии(String paramString1, String paramString2)
  {
    try
    {
      SharedPreferences localSharedPreferences = b042A042A042A042A042A042A042AЪ042A;
      int i = b042A042AЪЪЪЪЪ042A042A;
      switch (i * (b042AЪЪЪЪЪЪ042A042A + i) % bЪ042AЪЪЪЪЪ042A042A)
      {
      default: 
        i = b042A042AЪЪЪЪЪ042A042A;
        switch (i * (b042AЪЪЪЪЪЪ042A042A + i) % bЪ042AЪЪЪЪЪ042A042A)
        {
        default: 
          b042A042AЪЪЪЪЪ042A042A = 10;
          bЪЪЪЪЪЪЪ042A042A = 87;
        }
        b042A042AЪЪЪЪЪ042A042A = b0438иии0438043804380438ии();
        bЪЪЪЪЪЪЪ042A042A = 25;
      }
      boolean bool = localSharedPreferences.contains(b04380438ии0438043804380438ии(paramString1, paramString2));
      switch (0)
      {
      case 1: 
      default: 
        for (;;)
        {
          switch (0)
          {
          }
        }
      }
      return bool;
    }
    catch (Exception paramString1)
    {
      throw paramString1;
    }
  }
  
  /* Error */
  public long b04380438и04380438043804380438ии(String paramString1, String paramString2, long paramLong)
  {
    // Byte code:
    //   0: getstatic 104	kkkkkk/xtxxxt:b042A042A042A042A042A042A042AЪ042A	Landroid/content/SharedPreferences;
    //   3: astore 6
    //   5: getstatic 64	kkkkkk/xtxxxt:b042A042AЪЪЪЪЪ042A042A	I
    //   8: getstatic 56	kkkkkk/xtxxxt:b042AЪЪЪЪЪЪ042A042A	I
    //   11: iadd
    //   12: getstatic 64	kkkkkk/xtxxxt:b042A042AЪЪЪЪЪ042A042A	I
    //   15: imul
    //   16: getstatic 58	kkkkkk/xtxxxt:bЪ042AЪЪЪЪЪ042A042A	I
    //   19: irem
    //   20: getstatic 60	kkkkkk/xtxxxt:bЪЪЪЪЪЪЪ042A042A	I
    //   23: if_icmpeq +14 -> 37
    //   26: bipush 52
    //   28: putstatic 64	kkkkkk/xtxxxt:b042A042AЪЪЪЪЪ042A042A	I
    //   31: invokestatic 54	kkkkkk/xtxxxt:b0438иии0438043804380438ии	()I
    //   34: putstatic 60	kkkkkk/xtxxxt:bЪЪЪЪЪЪЪ042A042A	I
    //   37: aload_0
    //   38: aload_1
    //   39: aload_2
    //   40: invokespecial 134	kkkkkk/xtxxxt:b04380438ии0438043804380438ии	(Ljava/lang/String;Ljava/lang/String;)Ljava/lang/String;
    //   43: astore_1
    //   44: getstatic 64	kkkkkk/xtxxxt:b042A042AЪЪЪЪЪ042A042A	I
    //   47: istore 5
    //   49: iload 5
    //   51: getstatic 56	kkkkkk/xtxxxt:b042AЪЪЪЪЪЪ042A042A	I
    //   54: iload 5
    //   56: iadd
    //   57: imul
    //   58: getstatic 58	kkkkkk/xtxxxt:bЪ042AЪЪЪЪЪ042A042A	I
    //   61: irem
    //   62: tableswitch	default:+18->80, 0:+29->91
    //   80: invokestatic 54	kkkkkk/xtxxxt:b0438иии0438043804380438ии	()I
    //   83: putstatic 64	kkkkkk/xtxxxt:b042A042AЪЪЪЪЪ042A042A	I
    //   86: bipush 35
    //   88: putstatic 60	kkkkkk/xtxxxt:bЪЪЪЪЪЪЪ042A042A	I
    //   91: aload 6
    //   93: aload_1
    //   94: lload_3
    //   95: invokeinterface 155 4 0
    //   100: lstore_3
    //   101: lload_3
    //   102: lreturn
    //   103: astore_1
    //   104: iconst_0
    //   105: tableswitch	default:+23->128, 0:+50->155, 1:+-1->104
    //   128: iconst_0
    //   129: tableswitch	default:+23->152, 0:+26->155, 1:+-25->104
    //   152: goto -24 -> 128
    //   155: aload_1
    //   156: athrow
    //   157: astore_1
    //   158: aload_1
    //   159: athrow
    // Local variable table:
    //   start	length	slot	name	signature
    //   0	160	0	this	xtxxxt
    //   0	160	1	paramString1	String
    //   0	160	2	paramString2	String
    //   0	160	3	paramLong	long
    //   47	11	5	i	int
    //   3	89	6	localSharedPreferences	SharedPreferences
    // Exception table:
    //   from	to	target	type
    //   0	5	103	java/lang/Exception
    //   37	44	103	java/lang/Exception
    //   91	101	157	java/lang/Exception
  }
  
  public void b04380438ииииии0438и(String paramString1, String paramString2, String paramString3)
  {
    switch (0)
    {
    case 1: 
    default: 
      for (;;)
      {
        switch (0)
        {
        }
      }
    }
    SharedPreferences.Editor localEditor = b042A042A042A042A042A042A042AЪ042A.edit();
    int i = b042A042AЪЪЪЪЪ042A042A;
    int j = b042A042AЪЪЪЪЪ042A042A;
    switch (j * (b042AЪЪЪЪЪЪ042A042A + j) % bЪ042AЪЪЪЪЪ042A042A)
    {
    default: 
      b042A042AЪЪЪЪЪ042A042A = b0438иии0438043804380438ии();
      bЪЪЪЪЪЪЪ042A042A = b0438иии0438043804380438ии();
    }
    switch (i * (b042AЪЪЪЪЪЪ042A042A + i) % bЪ042AЪЪЪЪЪ042A042A)
    {
    default: 
      b042A042AЪЪЪЪЪ042A042A = 99;
      bЪЪЪЪЪЪЪ042A042A = 88;
    }
    localEditor.putString(b04380438ии0438043804380438ии(paramString1, paramString2), paramString3).apply();
  }
  
  /* Error */
  public Set<String> b0438и043804380438043804380438ии(String paramString1, String paramString2, Set<String> paramSet)
  {
    // Byte code:
    //   0: getstatic 104	kkkkkk/xtxxxt:b042A042A042A042A042A042A042AЪ042A	Landroid/content/SharedPreferences;
    //   3: astore 4
    //   5: getstatic 64	kkkkkk/xtxxxt:b042A042AЪЪЪЪЪ042A042A	I
    //   8: getstatic 56	kkkkkk/xtxxxt:b042AЪЪЪЪЪЪ042A042A	I
    //   11: iadd
    //   12: getstatic 64	kkkkkk/xtxxxt:b042A042AЪЪЪЪЪ042A042A	I
    //   15: imul
    //   16: getstatic 58	kkkkkk/xtxxxt:bЪ042AЪЪЪЪЪ042A042A	I
    //   19: irem
    //   20: getstatic 60	kkkkkk/xtxxxt:bЪЪЪЪЪЪЪ042A042A	I
    //   23: if_icmpeq +14 -> 37
    //   26: invokestatic 54	kkkkkk/xtxxxt:b0438иии0438043804380438ии	()I
    //   29: putstatic 64	kkkkkk/xtxxxt:b042A042AЪЪЪЪЪ042A042A	I
    //   32: bipush 83
    //   34: putstatic 60	kkkkkk/xtxxxt:bЪЪЪЪЪЪЪ042A042A	I
    //   37: getstatic 64	kkkkkk/xtxxxt:b042A042AЪЪЪЪЪ042A042A	I
    //   40: getstatic 56	kkkkkk/xtxxxt:b042AЪЪЪЪЪЪ042A042A	I
    //   43: iadd
    //   44: getstatic 64	kkkkkk/xtxxxt:b042A042AЪЪЪЪЪ042A042A	I
    //   47: imul
    //   48: getstatic 58	kkkkkk/xtxxxt:bЪ042AЪЪЪЪЪ042A042A	I
    //   51: irem
    //   52: getstatic 60	kkkkkk/xtxxxt:bЪЪЪЪЪЪЪ042A042A	I
    //   55: if_icmpeq +63 -> 118
    //   58: iconst_0
    //   59: tableswitch	default:+21->80, 0:+48->107, 1:+-1->58
    //   80: iconst_1
    //   81: tableswitch	default:+23->104, 0:+-23->58, 1:+26->107
    //   104: goto -24 -> 80
    //   107: bipush 85
    //   109: putstatic 64	kkkkkk/xtxxxt:b042A042AЪЪЪЪЪ042A042A	I
    //   112: invokestatic 54	kkkkkk/xtxxxt:b0438иии0438043804380438ии	()I
    //   115: putstatic 60	kkkkkk/xtxxxt:bЪЪЪЪЪЪЪ042A042A	I
    //   118: aload_0
    //   119: aload_1
    //   120: aload_2
    //   121: invokespecial 134	kkkkkk/xtxxxt:b04380438ии0438043804380438ии	(Ljava/lang/String;Ljava/lang/String;)Ljava/lang/String;
    //   124: astore_1
    //   125: aload 4
    //   127: aload_1
    //   128: aload_3
    //   129: invokeinterface 167 3 0
    //   134: astore_1
    //   135: aload_1
    //   136: areturn
    //   137: astore_1
    //   138: aload_1
    //   139: athrow
    //   140: astore_1
    //   141: aload_1
    //   142: athrow
    // Local variable table:
    //   start	length	slot	name	signature
    //   0	143	0	this	xtxxxt
    //   0	143	1	paramString1	String
    //   0	143	2	paramString2	String
    //   0	143	3	paramSet	Set<String>
    //   3	123	4	localSharedPreferences	SharedPreferences
    // Exception table:
    //   from	to	target	type
    //   0	5	137	java/lang/Exception
    //   118	125	137	java/lang/Exception
    //   125	135	140	java/lang/Exception
  }
  
  /* Error */
  public void b0438иииииии0438и(String paramString1, String paramString2, int paramInt)
  {
    // Byte code:
    //   0: new 173	java/lang/NullPointerException
    //   3: dup
    //   4: invokespecial 174	java/lang/NullPointerException:<init>	()V
    //   7: athrow
    //   8: astore 4
    //   10: bipush 38
    //   12: putstatic 64	kkkkkk/xtxxxt:b042A042AЪЪЪЪЪ042A042A	I
    //   15: getstatic 104	kkkkkk/xtxxxt:b042A042A042A042A042A042A042AЪ042A	Landroid/content/SharedPreferences;
    //   18: invokeinterface 132 1 0
    //   23: astore 4
    //   25: getstatic 64	kkkkkk/xtxxxt:b042A042AЪЪЪЪЪ042A042A	I
    //   28: getstatic 56	kkkkkk/xtxxxt:b042AЪЪЪЪЪЪ042A042A	I
    //   31: iadd
    //   32: getstatic 64	kkkkkk/xtxxxt:b042A042AЪЪЪЪЪ042A042A	I
    //   35: imul
    //   36: getstatic 58	kkkkkk/xtxxxt:bЪ042AЪЪЪЪЪ042A042A	I
    //   39: irem
    //   40: getstatic 60	kkkkkk/xtxxxt:bЪЪЪЪЪЪЪ042A042A	I
    //   43: if_icmpeq +14 -> 57
    //   46: bipush 50
    //   48: putstatic 64	kkkkkk/xtxxxt:b042A042AЪЪЪЪЪ042A042A	I
    //   51: invokestatic 54	kkkkkk/xtxxxt:b0438иии0438043804380438ии	()I
    //   54: putstatic 60	kkkkkk/xtxxxt:bЪЪЪЪЪЪЪ042A042A	I
    //   57: aload 4
    //   59: aload_0
    //   60: aload_1
    //   61: aload_2
    //   62: invokespecial 134	kkkkkk/xtxxxt:b04380438ии0438043804380438ии	(Ljava/lang/String;Ljava/lang/String;)Ljava/lang/String;
    //   65: iload_3
    //   66: invokeinterface 178 3 0
    //   71: invokeinterface 143 1 0
    //   76: return
    //   77: astore_1
    //   78: aload_1
    //   79: athrow
    //   80: astore_1
    //   81: aload_1
    //   82: athrow
    //   83: astore_1
    //   84: aload_1
    //   85: athrow
    //   86: astore_1
    //   87: aload_1
    //   88: athrow
    // Local variable table:
    //   start	length	slot	name	signature
    //   0	89	0	this	xtxxxt
    //   0	89	1	paramString1	String
    //   0	89	2	paramString2	String
    //   0	89	3	paramInt	int
    //   8	1	4	localException	Exception
    //   23	35	4	localEditor	SharedPreferences.Editor
    // Exception table:
    //   from	to	target	type
    //   0	8	8	java/lang/Exception
    //   57	76	77	java/lang/Exception
    //   78	80	80	java/lang/Exception
    //   84	86	80	java/lang/Exception
    //   15	25	83	java/lang/Exception
    //   10	15	86	java/lang/Exception
  }
  
  /* Error */
  public String bи0438043804380438043804380438ии(String paramString1, String paramString2, String paramString3)
  {
    // Byte code:
    //   0: getstatic 104	kkkkkk/xtxxxt:b042A042A042A042A042A042A042AЪ042A	Landroid/content/SharedPreferences;
    //   3: astore 8
    //   5: aload_0
    //   6: aload_1
    //   7: aload_2
    //   8: invokespecial 134	kkkkkk/xtxxxt:b04380438ии0438043804380438ии	(Ljava/lang/String;Ljava/lang/String;)Ljava/lang/String;
    //   11: astore_1
    //   12: getstatic 64	kkkkkk/xtxxxt:b042A042AЪЪЪЪЪ042A042A	I
    //   15: istore 4
    //   17: invokestatic 67	kkkkkk/xtxxxt:bи0438ии0438043804380438ии	()I
    //   20: istore 5
    //   22: getstatic 64	kkkkkk/xtxxxt:b042A042AЪЪЪЪЪ042A042A	I
    //   25: istore 6
    //   27: getstatic 58	kkkkkk/xtxxxt:bЪ042AЪЪЪЪЪ042A042A	I
    //   30: istore 7
    //   32: iload 4
    //   34: iload 5
    //   36: iadd
    //   37: iload 6
    //   39: imul
    //   40: iload 7
    //   42: irem
    //   43: getstatic 60	kkkkkk/xtxxxt:bЪЪЪЪЪЪЪ042A042A	I
    //   46: if_icmpeq +46 -> 92
    //   49: invokestatic 54	kkkkkk/xtxxxt:b0438иии0438043804380438ии	()I
    //   52: putstatic 64	kkkkkk/xtxxxt:b042A042AЪЪЪЪЪ042A042A	I
    //   55: bipush 85
    //   57: putstatic 60	kkkkkk/xtxxxt:bЪЪЪЪЪЪЪ042A042A	I
    //   60: getstatic 64	kkkkkk/xtxxxt:b042A042AЪЪЪЪЪ042A042A	I
    //   63: getstatic 56	kkkkkk/xtxxxt:b042AЪЪЪЪЪЪ042A042A	I
    //   66: iadd
    //   67: getstatic 64	kkkkkk/xtxxxt:b042A042AЪЪЪЪЪ042A042A	I
    //   70: imul
    //   71: getstatic 58	kkkkkk/xtxxxt:bЪ042AЪЪЪЪЪ042A042A	I
    //   74: irem
    //   75: getstatic 60	kkkkkk/xtxxxt:bЪЪЪЪЪЪЪ042A042A	I
    //   78: if_icmpeq +14 -> 92
    //   81: invokestatic 54	kkkkkk/xtxxxt:b0438иии0438043804380438ии	()I
    //   84: putstatic 64	kkkkkk/xtxxxt:b042A042AЪЪЪЪЪ042A042A	I
    //   87: bipush 21
    //   89: putstatic 60	kkkkkk/xtxxxt:bЪЪЪЪЪЪЪ042A042A	I
    //   92: aload 8
    //   94: aload_1
    //   95: aload_3
    //   96: invokeinterface 183 3 0
    //   101: astore_1
    //   102: iconst_1
    //   103: tableswitch	default:+21->124, 0:+-1->102, 1:+48->151
    //   124: iconst_1
    //   125: tableswitch	default:+23->148, 0:+-23->102, 1:+26->151
    //   148: goto -24 -> 124
    //   151: aload_1
    //   152: areturn
    //   153: astore_1
    //   154: aload_1
    //   155: athrow
    //   156: astore_1
    //   157: aload_1
    //   158: athrow
    // Local variable table:
    //   start	length	slot	name	signature
    //   0	159	0	this	xtxxxt
    //   0	159	1	paramString1	String
    //   0	159	2	paramString2	String
    //   0	159	3	paramString3	String
    //   15	22	4	i	int
    //   20	17	5	j	int
    //   25	15	6	k	int
    //   30	13	7	m	int
    //   3	90	8	localSharedPreferences	SharedPreferences
    // Exception table:
    //   from	to	target	type
    //   0	5	153	java/lang/Exception
    //   92	102	153	java/lang/Exception
    //   5	32	156	java/lang/Exception
    //   32	60	156	java/lang/Exception
  }
  
  /* Error */
  public boolean bи04380438и0438043804380438ии()
  {
    // Byte code:
    //   0: getstatic 78	kkkkkk/xtxxxt:bЪ042A042A042A042A042A042AЪ042A	Ljava/lang/String;
    //   3: ldc -69
    //   5: sipush 193
    //   8: sipush 152
    //   11: iconst_1
    //   12: invokestatic 48	kkkkkk/gguuuu:bк043Aккк043Aкк043A043A	(Ljava/lang/String;CCC)Ljava/lang/String;
    //   15: invokestatic 192	kkkkkk/xtxtxt:bии0438и04380438и0438ии	(Ljava/lang/String;Ljava/lang/String;)V
    //   18: getstatic 64	kkkkkk/xtxxxt:b042A042AЪЪЪЪЪ042A042A	I
    //   21: istore_1
    //   22: invokestatic 67	kkkkkk/xtxxxt:bи0438ии0438043804380438ии	()I
    //   25: istore_2
    //   26: getstatic 58	kkkkkk/xtxxxt:bЪ042AЪЪЪЪЪ042A042A	I
    //   29: istore_3
    //   30: iload_1
    //   31: iload_2
    //   32: iload_1
    //   33: iadd
    //   34: imul
    //   35: iload_3
    //   36: irem
    //   37: tableswitch	default:+19->56, 0:+31->68
    //   56: invokestatic 54	kkkkkk/xtxxxt:b0438иии0438043804380438ии	()I
    //   59: putstatic 64	kkkkkk/xtxxxt:b042A042AЪЪЪЪЪ042A042A	I
    //   62: invokestatic 54	kkkkkk/xtxxxt:b0438иии0438043804380438ии	()I
    //   65: putstatic 60	kkkkkk/xtxxxt:bЪЪЪЪЪЪЪ042A042A	I
    //   68: iconst_1
    //   69: tableswitch	default:+23->92, 0:+-1->68, 1:+82->151
    //   92: getstatic 64	kkkkkk/xtxxxt:b042A042AЪЪЪЪЪ042A042A	I
    //   95: getstatic 56	kkkkkk/xtxxxt:b042AЪЪЪЪЪЪ042A042A	I
    //   98: iadd
    //   99: getstatic 64	kkkkkk/xtxxxt:b042A042AЪЪЪЪЪ042A042A	I
    //   102: imul
    //   103: getstatic 58	kkkkkk/xtxxxt:bЪ042AЪЪЪЪЪ042A042A	I
    //   106: irem
    //   107: getstatic 60	kkkkkk/xtxxxt:bЪЪЪЪЪЪЪ042A042A	I
    //   110: if_icmpeq +14 -> 124
    //   113: bipush 72
    //   115: putstatic 64	kkkkkk/xtxxxt:b042A042AЪЪЪЪЪ042A042A	I
    //   118: invokestatic 54	kkkkkk/xtxxxt:b0438иии0438043804380438ии	()I
    //   121: putstatic 60	kkkkkk/xtxxxt:bЪЪЪЪЪЪЪ042A042A	I
    //   124: iconst_1
    //   125: tableswitch	default:+23->148, 0:+-57->68, 1:+26->151
    //   148: goto -56 -> 92
    //   151: getstatic 104	kkkkkk/xtxxxt:b042A042A042A042A042A042A042AЪ042A	Landroid/content/SharedPreferences;
    //   154: invokeinterface 132 1 0
    //   159: invokeinterface 195 1 0
    //   164: invokeinterface 198 1 0
    //   169: istore 4
    //   171: iload 4
    //   173: ireturn
    //   174: astore 5
    //   176: aload 5
    //   178: athrow
    //   179: astore 5
    //   181: aload 5
    //   183: athrow
    // Local variable table:
    //   start	length	slot	name	signature
    //   0	184	0	this	xtxxxt
    //   21	14	1	i	int
    //   25	9	2	j	int
    //   29	8	3	k	int
    //   169	3	4	bool	boolean
    //   174	3	5	localException1	Exception
    //   179	3	5	localException2	Exception
    // Exception table:
    //   from	to	target	type
    //   0	30	174	java/lang/Exception
    //   151	171	174	java/lang/Exception
    //   56	68	179	java/lang/Exception
  }
  
  /* Error */
  public int bи0438и04380438043804380438ии(String paramString1, String paramString2, int paramInt)
  {
    // Byte code:
    //   0: getstatic 104	kkkkkk/xtxxxt:b042A042A042A042A042A042A042AЪ042A	Landroid/content/SharedPreferences;
    //   3: astore 7
    //   5: aload_0
    //   6: aload_1
    //   7: aload_2
    //   8: invokespecial 134	kkkkkk/xtxxxt:b04380438ии0438043804380438ии	(Ljava/lang/String;Ljava/lang/String;)Ljava/lang/String;
    //   11: astore_1
    //   12: getstatic 64	kkkkkk/xtxxxt:b042A042AЪЪЪЪЪ042A042A	I
    //   15: istore 4
    //   17: getstatic 56	kkkkkk/xtxxxt:b042AЪЪЪЪЪЪ042A042A	I
    //   20: istore 5
    //   22: getstatic 58	kkkkkk/xtxxxt:bЪ042AЪЪЪЪЪ042A042A	I
    //   25: istore 6
    //   27: iload 4
    //   29: iload 5
    //   31: iload 4
    //   33: iadd
    //   34: imul
    //   35: iload 6
    //   37: irem
    //   38: tableswitch	default:+18->56, 0:+82->120
    //   56: invokestatic 54	kkkkkk/xtxxxt:b0438иии0438043804380438ии	()I
    //   59: putstatic 64	kkkkkk/xtxxxt:b042A042AЪЪЪЪЪ042A042A	I
    //   62: invokestatic 54	kkkkkk/xtxxxt:b0438иии0438043804380438ии	()I
    //   65: istore 4
    //   67: iload 4
    //   69: putstatic 60	kkkkkk/xtxxxt:bЪЪЪЪЪЪЪ042A042A	I
    //   72: getstatic 64	kkkkkk/xtxxxt:b042A042AЪЪЪЪЪ042A042A	I
    //   75: istore 4
    //   77: iload 4
    //   79: invokestatic 67	kkkkkk/xtxxxt:bи0438ии0438043804380438ии	()I
    //   82: iload 4
    //   84: iadd
    //   85: imul
    //   86: getstatic 58	kkkkkk/xtxxxt:bЪ042AЪЪЪЪЪ042A042A	I
    //   89: irem
    //   90: tableswitch	default:+18->108, 0:+30->120
    //   108: invokestatic 54	kkkkkk/xtxxxt:b0438иии0438043804380438ии	()I
    //   111: putstatic 64	kkkkkk/xtxxxt:b042A042AЪЪЪЪЪ042A042A	I
    //   114: invokestatic 54	kkkkkk/xtxxxt:b0438иии0438043804380438ии	()I
    //   117: putstatic 60	kkkkkk/xtxxxt:bЪЪЪЪЪЪЪ042A042A	I
    //   120: aload 7
    //   122: aload_1
    //   123: iload_3
    //   124: invokeinterface 204 3 0
    //   129: istore_3
    //   130: iload_3
    //   131: ireturn
    //   132: astore_1
    //   133: aload_1
    //   134: athrow
    //   135: astore_1
    //   136: aload_1
    //   137: athrow
    // Local variable table:
    //   start	length	slot	name	signature
    //   0	138	0	this	xtxxxt
    //   0	138	1	paramString1	String
    //   0	138	2	paramString2	String
    //   0	138	3	paramInt	int
    //   15	71	4	i	int
    //   20	14	5	j	int
    //   25	13	6	k	int
    //   3	118	7	localSharedPreferences	SharedPreferences
    // Exception table:
    //   from	to	target	type
    //   0	27	132	java/lang/Exception
    //   67	72	132	java/lang/Exception
    //   120	130	132	java/lang/Exception
    //   56	67	135	java/lang/Exception
  }
  
  public void bи0438ииииии0438и(String paramString1, String paramString2, long paramLong)
  {
    try
    {
      b042A042A042A042A042A042A042AЪ042A.edit().putLong(b04380438ии0438043804380438ии(paramString1, paramString2), paramLong).apply();
      if ((b042A042AЪЪЪЪЪ042A042A + b042AЪЪЪЪЪЪ042A042A) * b042A042AЪЪЪЪЪ042A042A % bЪ042AЪЪЪЪЪ042A042A != bЪЪЪЪЪЪЪ042A042A)
      {
        b042A042AЪЪЪЪЪ042A042A = 55;
        bЪЪЪЪЪЪЪ042A042A = 54;
        if ((b042A042AЪЪЪЪЪ042A042A + b042AЪЪЪЪЪЪ042A042A) * b042A042AЪЪЪЪЪ042A042A % bЪ042AЪЪЪЪЪ042A042A != bЪЪЪЪЪЪЪ042A042A)
        {
          b042A042AЪЪЪЪЪ042A042A = b0438иии0438043804380438ии();
          bЪЪЪЪЪЪЪ042A042A = b0438иии0438043804380438ии();
        }
      }
      return;
    }
    catch (Exception paramString1)
    {
      throw paramString1;
    }
  }
  
  /* Error */
  public boolean bии043804380438043804380438ии(String paramString1, String paramString2, boolean paramBoolean)
  {
    // Byte code:
    //   0: getstatic 104	kkkkkk/xtxxxt:b042A042A042A042A042A042A042AЪ042A	Landroid/content/SharedPreferences;
    //   3: astore 9
    //   5: aload_0
    //   6: aload_1
    //   7: aload_2
    //   8: invokespecial 134	kkkkkk/xtxxxt:b04380438ии0438043804380438ии	(Ljava/lang/String;Ljava/lang/String;)Ljava/lang/String;
    //   11: astore_1
    //   12: getstatic 64	kkkkkk/xtxxxt:b042A042AЪЪЪЪЪ042A042A	I
    //   15: istore 4
    //   17: getstatic 56	kkkkkk/xtxxxt:b042AЪЪЪЪЪЪ042A042A	I
    //   20: istore 5
    //   22: getstatic 64	kkkkkk/xtxxxt:b042A042AЪЪЪЪЪ042A042A	I
    //   25: istore 6
    //   27: getstatic 58	kkkkkk/xtxxxt:bЪ042AЪЪЪЪЪ042A042A	I
    //   30: istore 7
    //   32: getstatic 60	kkkkkk/xtxxxt:bЪЪЪЪЪЪЪ042A042A	I
    //   35: istore 8
    //   37: iload 4
    //   39: iload 5
    //   41: iadd
    //   42: iload 6
    //   44: imul
    //   45: iload 7
    //   47: irem
    //   48: iload 8
    //   50: if_icmpeq +62 -> 112
    //   53: bipush 51
    //   55: putstatic 64	kkkkkk/xtxxxt:b042A042AЪЪЪЪЪ042A042A	I
    //   58: bipush 65
    //   60: putstatic 60	kkkkkk/xtxxxt:bЪЪЪЪЪЪЪ042A042A	I
    //   63: getstatic 64	kkkkkk/xtxxxt:b042A042AЪЪЪЪЪ042A042A	I
    //   66: istore 4
    //   68: iload 4
    //   70: getstatic 56	kkkkkk/xtxxxt:b042AЪЪЪЪЪЪ042A042A	I
    //   73: iload 4
    //   75: iadd
    //   76: imul
    //   77: getstatic 58	kkkkkk/xtxxxt:bЪ042AЪЪЪЪЪ042A042A	I
    //   80: irem
    //   81: tableswitch	default:+19->100, 0:+31->112
    //   100: invokestatic 54	kkkkkk/xtxxxt:b0438иии0438043804380438ии	()I
    //   103: putstatic 64	kkkkkk/xtxxxt:b042A042AЪЪЪЪЪ042A042A	I
    //   106: invokestatic 54	kkkkkk/xtxxxt:b0438иии0438043804380438ии	()I
    //   109: putstatic 60	kkkkkk/xtxxxt:bЪЪЪЪЪЪЪ042A042A	I
    //   112: aload 9
    //   114: aload_1
    //   115: iload_3
    //   116: invokeinterface 216 3 0
    //   121: istore_3
    //   122: iload_3
    //   123: ireturn
    //   124: astore_1
    //   125: aload_1
    //   126: athrow
    //   127: astore_1
    //   128: aload_1
    //   129: athrow
    //   130: astore_1
    //   131: aload_1
    //   132: athrow
    //   133: astore_1
    //   134: aload_1
    //   135: athrow
    // Local variable table:
    //   start	length	slot	name	signature
    //   0	136	0	this	xtxxxt
    //   0	136	1	paramString1	String
    //   0	136	2	paramString2	String
    //   0	136	3	paramBoolean	boolean
    //   15	62	4	i	int
    //   20	22	5	j	int
    //   25	20	6	k	int
    //   30	18	7	m	int
    //   35	16	8	n	int
    //   3	110	9	localSharedPreferences	SharedPreferences
    // Exception table:
    //   from	to	target	type
    //   0	12	124	java/lang/Exception
    //   12	37	127	java/lang/Exception
    //   125	127	127	java/lang/Exception
    //   112	122	130	java/lang/Exception
    //   53	63	133	java/lang/Exception
    //   131	133	133	java/lang/Exception
  }
  
  public void bии0438иииии0438и(String paramString1, String paramString2, Set<String> paramSet)
  {
    try
    {
      SharedPreferences.Editor localEditor = b042A042A042A042A042A042A042AЪ042A.edit();
      int i = b042A042AЪЪЪЪЪ042A042A;
      switch (i * (bи0438ии0438043804380438ии() + i) % bЪ042AЪЪЪЪЪ042A042A)
      {
      default: 
        b042A042AЪЪЪЪЪ042A042A = b0438иии0438043804380438ии();
        bЪЪЪЪЪЪЪ042A042A = b0438иии0438043804380438ии();
      }
      localEditor.putStringSet(b04380438ии0438043804380438ии(paramString1, paramString2), paramSet).apply();
      return;
    }
    catch (Exception paramString1)
    {
      throw paramString1;
    }
  }
  
  public boolean bиии04380438043804380438ии(String paramString1, String paramString2, boolean paramBoolean)
  {
    SharedPreferences localSharedPreferences = b042A042A042A042A042A042A042AЪ042A;
    paramString1 = b04380438ии0438043804380438ии(paramString1, paramString2);
    int i = b042A042AЪЪЪЪЪ042A042A;
    switch (i * (b042AЪЪЪЪЪЪ042A042A + i) % bЪ042AЪЪЪЪЪ042A042A)
    {
    default: 
      b042A042AЪЪЪЪЪ042A042A = 91;
      bЪЪЪЪЪЪЪ042A042A = b0438иии0438043804380438ии();
    }
    i = b042A042AЪЪЪЪЪ042A042A;
    int j = b042AЪЪЪЪЪЪ042A042A;
    int k = b042A042AЪЪЪЪЪ042A042A;
    int m = bЪ042AЪЪЪЪЪ042A042A;
    switch (1)
    {
    case 0: 
    default: 
      for (;;)
      {
        switch (0)
        {
        }
      }
    }
    if ((i + j) * k % m != bЪЪЪЪЪЪЪ042A042A)
    {
      b042A042AЪЪЪЪЪ042A042A = b0438иии0438043804380438ии();
      bЪЪЪЪЪЪЪ042A042A = b0438иии0438043804380438ии();
    }
    return localSharedPreferences.getBoolean(paramString1, paramBoolean);
  }
  
  public void bииииииии0438и(String paramString1, String paramString2, boolean paramBoolean)
  {
    SharedPreferences.Editor localEditor = b042A042A042A042A042A042A042AЪ042A.edit();
    switch (1)
    {
    case 0: 
    default: 
      for (;;)
      {
        switch (0)
        {
        }
      }
    }
    paramString1 = b04380438ии0438043804380438ии(paramString1, paramString2);
    int i = b042A042AЪЪЪЪЪ042A042A;
    if ((b042A042AЪЪЪЪЪ042A042A + b042AЪЪЪЪЪЪ042A042A) * b042A042AЪЪЪЪЪ042A042A % bЪ042AЪЪЪЪЪ042A042A != bЪЪЪЪЪЪЪ042A042A)
    {
      b042A042AЪЪЪЪЪ042A042A = b0438иии0438043804380438ии();
      bЪЪЪЪЪЪЪ042A042A = b0438иии0438043804380438ии();
    }
    switch (i * (b042AЪЪЪЪЪЪ042A042A + i) % bЪ042AЪЪЪЪЪ042A042A)
    {
    default: 
      b042A042AЪЪЪЪЪ042A042A = 40;
      bЪЪЪЪЪЪЪ042A042A = b0438иии0438043804380438ии();
    }
    localEditor.putBoolean(paramString1, paramBoolean).apply();
  }
}
