package kkkkkk;

import android.content.BroadcastReceiver;
import android.content.Context;
import android.content.Intent;
import android.content.IntentFilter;
import android.net.ConnectivityManager;
import android.net.NetworkInfo;

public class xxdddx
  implements vvovov
{
  public static int b042A042A042A042A042AЪЪЪЪ = 0;
  public static int b042AЪ042A042A042AЪЪЪЪ = 1;
  public static final String b042AЪЪ042A042AЪЪЪЪ = "MZZ[SRdZaasY_j[hhia`rdd";
  public static int bЪ042A042A042A042AЪЪЪЪ = 2;
  private static final String bЪ042AЪ042A042AЪЪЪЪ;
  public static int bЪЪ042A042A042AЪЪЪЪ = 14;
  public static final String bЪЪЪ042A042AЪЪЪЪ = "<GED:7G;@>N1<:9/,<,*";
  private ConnectionReceiver b042A042AЪ042A042AЪЪЪЪ;
  
  /* Error */
  static
  {
    // Byte code:
    //   0: getstatic 34	kkkkkk/xxdddx:bЪЪЪ042A042AЪЪЪЪ	Ljava/lang/String;
    //   3: astore_3
    //   4: getstatic 36	kkkkkk/xxdddx:bЪЪ042A042A042AЪЪЪЪ	I
    //   7: istore_0
    //   8: getstatic 38	kkkkkk/xxdddx:b042AЪ042A042A042AЪЪЪЪ	I
    //   11: istore_1
    //   12: invokestatic 42	kkkkkk/xxdddx:b044504450445х0445х0445044504450445	()I
    //   15: istore_2
    //   16: iload_2
    //   17: getstatic 38	kkkkkk/xxdddx:b042AЪ042A042A042AЪЪЪЪ	I
    //   20: iload_2
    //   21: iadd
    //   22: imul
    //   23: getstatic 44	kkkkkk/xxdddx:bЪ042A042A042A042AЪЪЪЪ	I
    //   26: irem
    //   27: tableswitch	default:+17->44, 0:+27->54
    //   44: iconst_0
    //   45: putstatic 36	kkkkkk/xxdddx:bЪЪ042A042A042AЪЪЪЪ	I
    //   48: invokestatic 42	kkkkkk/xxdddx:b044504450445х0445х0445044504450445	()I
    //   51: putstatic 38	kkkkkk/xxdddx:b042AЪ042A042A042AЪЪЪЪ	I
    //   54: iload_0
    //   55: iload_1
    //   56: iload_0
    //   57: iadd
    //   58: imul
    //   59: getstatic 44	kkkkkk/xxdddx:bЪ042A042A042A042AЪЪЪЪ	I
    //   62: irem
    //   63: tableswitch	default:+17->80, 0:+27->90
    //   80: bipush 25
    //   82: putstatic 36	kkkkkk/xxdddx:bЪЪ042A042A042AЪЪЪЪ	I
    //   85: bipush 71
    //   87: putstatic 38	kkkkkk/xxdddx:b042AЪ042A042A042AЪЪЪЪ	I
    //   90: aload_3
    //   91: bipush 87
    //   93: iconst_2
    //   94: invokestatic 50	kkkkkk/gguuuu:bккккк043Aкк043A043A	(Ljava/lang/String;CC)Ljava/lang/String;
    //   97: putstatic 34	kkkkkk/xxdddx:bЪЪЪ042A042AЪЪЪЪ	Ljava/lang/String;
    //   100: getstatic 52	kkkkkk/xxdddx:b042AЪЪ042A042AЪЪЪЪ	Ljava/lang/String;
    //   103: sipush 193
    //   106: sipush 183
    //   109: iconst_1
    //   110: invokestatic 56	kkkkkk/gguuuu:bк043Aккк043Aкк043A043A	(Ljava/lang/String;CCC)Ljava/lang/String;
    //   113: putstatic 52	kkkkkk/xxdddx:b042AЪЪ042A042AЪЪЪЪ	Ljava/lang/String;
    //   116: ldc 2
    //   118: invokevirtual 62	java/lang/Class:getSimpleName	()Ljava/lang/String;
    //   121: putstatic 64	kkkkkk/xxdddx:bЪ042AЪ042A042AЪЪЪЪ	Ljava/lang/String;
    //   124: return
    //   125: astore_3
    //   126: aload_3
    //   127: athrow
    //   128: astore_3
    //   129: aload_3
    //   130: athrow
    // Local variable table:
    //   start	length	slot	name	signature
    //   7	52	0	i	int
    //   11	47	1	j	int
    //   15	8	2	k	int
    //   3	88	3	str	String
    //   125	2	3	localException1	Exception
    //   128	2	3	localException2	Exception
    // Exception table:
    //   from	to	target	type
    //   0	4	125	java/lang/Exception
    //   90	116	125	java/lang/Exception
    //   116	124	128	java/lang/Exception
  }
  
  public xxdddx()
  {
    bх0445х04450445х0445044504450445();
  }
  
  public static int b044504450445х0445х0445044504450445()
  {
    return 62;
  }
  
  public static boolean b0445хх04450445х0445044504450445()
  {
    for (;;)
    {
      try
      {
        localObject = xxdxxd.instance.bххх044504450445х044504450445();
        if (localObject != null) {
          str = gguuuu.bк043Aккк043Aкк043A043A("~\f\f\r\005\004\026\f\032\016\032 ", 'Q', 'µ', '\001');
        }
      }
      catch (Exception localException1)
      {
        Object localObject;
        String str;
        int i;
        StringBuilder localStringBuilder;
        throw localException1;
      }
      try
      {
        localObject = ((Context)localObject).getSystemService(str);
        i = bЪЪ042A042A042AЪЪЪЪ;
        switch (i * (b042AЪ042A042A042AЪЪЪЪ + i) % bЪ042A042A042A042AЪЪЪЪ)
        {
        default: 
          bЪЪ042A042A042AЪЪЪЪ = 58;
          b042A042A042A042A042AЪЪЪЪ = 58;
        }
        localObject = ((ConnectivityManager)localObject).getActiveNetworkInfo();
        if ((localObject == null) || (!((NetworkInfo)localObject).isConnectedOrConnecting())) {
          break label279;
        }
        bool = true;
        str = bЪ042AЪ042A042AЪЪЪЪ;
        localStringBuilder = new StringBuilder();
        switch (1)
        {
        case 0: 
        default: 
          switch (1)
          {
          }
          break;
        }
        xtxtxt.bии0438и04380438и0438ии(str, gguuuu.bк043Aккк043Aкк043A043A("\b\023n\007\027\033\024\030\022h\037\013\024\030\016\020\033\025jQ\034'w%%&\036\035/!!]{_", '°', '\023', '\001') + bool);
        str = bЪ042AЪ042A042AЪЪЪЪ;
        if ((bЪЪ042A042A042AЪЪЪЪ + b042AЪ042A042A042AЪЪЪЪ) * bЪЪ042A042A042AЪЪЪЪ % bЪ042A042A042A042AЪЪЪЪ != b042A042A042A042A042AЪЪЪЪ)
        {
          bЪЪ042A042A042AЪЪЪЪ = 64;
          b042A042A042A042A042AЪЪЪЪ = b044504450445х0445х0445044504450445();
        }
        localStringBuilder = new StringBuilder();
        xtxtxt.bии0438и04380438и0438ии(str, gguuuu.bккккк043Aкк043A043A("\027 y\020\036 \027\031\021e\032\004\013\r\001\001\n\002U:\b}\f\016\005\007~[v~.J,", ')', '\003') + localObject);
        return bool;
      }
      catch (Exception localException2)
      {
        throw localException2;
      }
      xtxtxt.bии0438и04380438и0438ии(bЪ042AЪ042A042AЪЪЪЪ, gguuuu.bккккк043Aкк043A043A("<G#;KOHLF\035S?HLBDOI\037\006HXY\nN[[bThe\022\\g\025dlde\033", ')', '\004'));
      return false;
      label279:
      boolean bool = false;
    }
  }
  
  public static int bххх04450445х0445044504450445()
  {
    return 1;
  }
  
  /* Error */
  public void b04450445х04450445х0445044504450445()
  {
    // Byte code:
    //   0: aload_0
    //   1: getfield 137	kkkkkk/xxdddx:b042A042AЪ042A042AЪЪЪЪ	Lkkkkkk/xxdddx$ConnectionReceiver;
    //   4: ifnull +118 -> 122
    //   7: getstatic 64	kkkkkk/xxdddx:bЪ042AЪ042A042AЪЪЪЪ	Ljava/lang/String;
    //   10: ldc -117
    //   12: sipush 250
    //   15: iconst_3
    //   16: invokestatic 50	kkkkkk/gguuuu:bккккк043Aкк043A043A	(Ljava/lang/String;CC)Ljava/lang/String;
    //   19: invokestatic 125	kkkkkk/xtxtxt:bии0438и04380438и0438ии	(Ljava/lang/String;Ljava/lang/String;)V
    //   22: getstatic 79	kkkkkk/xxdxxd:instance	Lkkkkkk/xxdxxd;
    //   25: astore 4
    //   27: aload 4
    //   29: invokevirtual 83	kkkkkk/xxdxxd:bххх044504450445х044504450445	()Landroid/content/Context;
    //   32: aload_0
    //   33: getfield 137	kkkkkk/xxdddx:b042A042AЪ042A042AЪЪЪЪ	Lkkkkkk/xxdddx$ConnectionReceiver;
    //   36: invokevirtual 143	android/content/Context:unregisterReceiver	(Landroid/content/BroadcastReceiver;)V
    //   39: getstatic 36	kkkkkk/xxdddx:bЪЪ042A042A042AЪЪЪЪ	I
    //   42: istore_1
    //   43: getstatic 38	kkkkkk/xxdddx:b042AЪ042A042A042AЪЪЪЪ	I
    //   46: istore_2
    //   47: getstatic 44	kkkkkk/xxdddx:bЪ042A042A042A042AЪЪЪЪ	I
    //   50: istore_3
    //   51: iload_1
    //   52: iload_2
    //   53: iload_1
    //   54: iadd
    //   55: imul
    //   56: iload_3
    //   57: irem
    //   58: tableswitch	default:+18->76, 0:+59->117
    //   76: iconst_4
    //   77: putstatic 36	kkkkkk/xxdddx:bЪЪ042A042A042AЪЪЪЪ	I
    //   80: bipush 66
    //   82: putstatic 93	kkkkkk/xxdddx:b042A042A042A042A042AЪЪЪЪ	I
    //   85: getstatic 36	kkkkkk/xxdddx:bЪЪ042A042A042AЪЪЪЪ	I
    //   88: getstatic 38	kkkkkk/xxdddx:b042AЪ042A042A042AЪЪЪЪ	I
    //   91: iadd
    //   92: getstatic 36	kkkkkk/xxdddx:bЪЪ042A042A042AЪЪЪЪ	I
    //   95: imul
    //   96: getstatic 44	kkkkkk/xxdddx:bЪ042A042A042A042AЪЪЪЪ	I
    //   99: irem
    //   100: getstatic 93	kkkkkk/xxdddx:b042A042A042A042A042AЪЪЪЪ	I
    //   103: if_icmpeq +14 -> 117
    //   106: bipush 33
    //   108: putstatic 36	kkkkkk/xxdddx:bЪЪ042A042A042AЪЪЪЪ	I
    //   111: invokestatic 42	kkkkkk/xxdddx:b044504450445х0445х0445044504450445	()I
    //   114: putstatic 93	kkkkkk/xxdddx:b042A042A042A042A042AЪЪЪЪ	I
    //   117: aload_0
    //   118: aconst_null
    //   119: putfield 137	kkkkkk/xxdddx:b042A042AЪ042A042AЪЪЪЪ	Lkkkkkk/xxdddx$ConnectionReceiver;
    //   122: return
    //   123: astore 4
    //   125: aload 4
    //   127: athrow
    //   128: astore 4
    //   130: aload 4
    //   132: athrow
    //   133: astore 4
    //   135: aload 4
    //   137: athrow
    //   138: astore 4
    //   140: aload 4
    //   142: athrow
    // Local variable table:
    //   start	length	slot	name	signature
    //   0	143	0	this	xxdddx
    //   42	14	1	i	int
    //   46	9	2	j	int
    //   50	8	3	k	int
    //   25	3	4	localXxdxxd	xxdxxd
    //   123	3	4	localException1	Exception
    //   128	3	4	localException2	Exception
    //   133	3	4	localException3	Exception
    //   138	3	4	localException4	Exception
    // Exception table:
    //   from	to	target	type
    //   0	27	123	java/lang/Exception
    //   117	122	123	java/lang/Exception
    //   76	85	128	java/lang/Exception
    //   125	128	128	java/lang/Exception
    //   135	138	128	java/lang/Exception
    //   27	39	133	java/lang/Exception
    //   39	51	138	java/lang/Exception
  }
  
  public void b0445ххх0445хх044504450445()
  {
    throw new Runtime("d2j fail translate: java.lang.IndexOutOfBoundsException: fromIndex < 0: -1\n\tat java.util.BitSet.nextSetBit(BitSet.java:712)\n\tat com.googlecode.dex2jar.ir.ts.array.FillArrayTransformer.makeSureAllElementAreAssigned(FillArrayTransformer.java:505)\n\tat com.googlecode.dex2jar.ir.ts.array.FillArrayTransformer.transformReportChanged(FillArrayTransformer.java:123)\n\tat com.googlecode.dex2jar.ir.ts.StatedTransformer.transform(StatedTransformer.java:10)\n\tat com.googlecode.d2j.dex.Dex2jar$2.optimize(Dex2jar.java:149)\n\tat com.googlecode.d2j.dex.Dex2Asm.convertCode(Dex2Asm.java:414)\n\tat com.googlecode.d2j.dex.ExDex2Asm.convertCode(ExDex2Asm.java:42)\n\tat com.googlecode.d2j.dex.Dex2jar$2.convertCode(Dex2jar.java:128)\n\tat com.googlecode.d2j.dex.Dex2Asm.convertMethod(Dex2Asm.java:509)\n\tat com.googlecode.d2j.dex.Dex2Asm.convertClass(Dex2Asm.java:406)\n\tat com.googlecode.d2j.dex.Dex2Asm.convertDex(Dex2Asm.java:422)\n\tat com.googlecode.d2j.dex.Dex2jar.doTranslate(Dex2jar.java:172)\n\tat com.googlecode.d2j.dex.Dex2jar.to(Dex2jar.java:272)\n\tat com.googlecode.dex2jar.tools.Dex2jarCmd.doCommandLine(Dex2jarCmd.java:108)\n\tat com.googlecode.dex2jar.tools.BaseCmd.doMain(BaseCmd.java:288)\n\tat com.googlecode.dex2jar.tools.Dex2jarCmd.main(Dex2jarCmd.java:32)\n");
  }
  
  public void bх0445х04450445х0445044504450445()
  {
    if (this.b042A042AЪ042A042AЪЪЪЪ == null)
    {
      this.b042A042AЪ042A042AЪЪЪЪ = new ConnectionReceiver();
      switch (0)
      {
      case 1: 
      default: 
        for (;;)
        {
          switch (1)
          {
          case 0: 
          default: 
            for (;;)
            {
              switch (0)
              {
              }
            }
          }
          switch (0)
          {
          }
        }
      }
      int i = b044504450445х0445х0445044504450445();
      switch (i * (b042AЪ042A042A042AЪЪЪЪ + i) % bЪ042A042A042A042AЪЪЪЪ)
      {
      default: 
        bЪЪ042A042A042AЪЪЪЪ = 62;
        b042A042A042A042A042AЪЪЪЪ = b044504450445х0445х0445044504450445();
      }
      String str = bЪ042AЪ042A042AЪЪЪЪ;
      if ((bЪЪ042A042A042AЪЪЪЪ + bххх04450445х0445044504450445()) * bЪЪ042A042A042AЪЪЪЪ % bЪ042A042A042A042AЪЪЪЪ != b042A042A042A042A042AЪЪЪЪ)
      {
        bЪЪ042A042A042AЪЪЪЪ = b044504450445х0445х0445044504450445();
        b042A042A042A042A042AЪЪЪЪ = 66;
      }
      xtxtxt.bии0438и04380438и0438ии(str, gguuuu.bккккк043Aкк043A043A("\004\022\004~\021\005\t\0018\006{\r4\006wtux\005r~", 'J', '\002'));
    }
    this.b042A042AЪ042A042AЪЪЪЪ.register(xxdxxd.instance.bххх044504450445х044504450445());
  }
  
  private class ConnectionReceiver
    extends BroadcastReceiver
  {
    public static int b0437зз0437зз = 93;
    public static int bз04370437ззз = 0;
    public static int bз0437з0437зз = 1;
    public static int bззз0437зз = 2;
    private final IntentFilter intentFilter = new IntentFilter();
    private boolean lastConnectionState;
    
    public ConnectionReceiver()
    {
      this.intentFilter.addAction(gguuuu.bккккк043Aкк043A043A("Vd[jhc_*kcs.dqqr3IVVWON`VdXdjqV\\Vd^]", '¹', '\004'));
    }
    
    public static int b043704370437ззз()
    {
      return 1;
    }
    
    public static int b04370437з0437зз()
    {
      return 0;
    }
    
    public static int b0437з0437ззз()
    {
      return 44;
    }
    
    private void sendUpdateIntent(boolean paramBoolean)
    {
      if (paramBoolean) {}
      for (;;)
      {
        try
        {
          localObject = gguuuu.bккккк043Aкк043A043A("4?=<2/?386F)421'$4$\"", '', '\005');
          hbhbbh.b0428Ш04280428Ш0428042804280428Ш((String)localObject);
          return;
        }
        catch (Exception localException2)
        {
          Object localObject;
          String str;
          int i;
          int j;
          int k;
          int m;
          int n;
          throw localException2;
        }
        str = gguuuu.bк043Aккк043Aкк043A043A("cnlka^nbgeuY]fU`^]SP`PN", '\030', '8', '\000');
        break label131;
        i = b0437з0437ззз();
        j = b043704370437ззз();
        k = b0437з0437ззз();
        m = bззз0437зз;
        n = bз04370437ззз;
        localObject = str;
        if ((i + j) * k % m != n)
        {
          if ((b0437зз0437зз + bз0437з0437зз) * b0437зз0437зз % bззз0437зз != bз04370437ззз)
          {
            b0437зз0437зз = 48;
            bз04370437ззз = 16;
          }
          try
          {
            bз04370437ззз = b0437з0437ззз();
            localObject = str;
          }
          catch (Exception localException1)
          {
            throw localException1;
          }
        }
      }
      label131:
      switch (0)
      {
      }
      for (;;)
      {
        switch (0)
        {
        }
      }
    }
    
    /* Error */
    public void onReceive(Context paramContext, Intent paramIntent)
    {
      // Byte code:
      //   0: aload_1
      //   1: invokestatic 88	kkkkkk/nkkkkk:bЗЗ0417З0417З0417041704170417	(Landroid/content/Context;)V
      //   4: aload_1
      //   5: invokestatic 93	kkkkkk/nnnkkk:bхх0445ххххххх	(Landroid/content/Context;)V
      //   8: aload_1
      //   9: invokestatic 98	kkkkkk/nknnkk:bх0445ххх04450445ххх	(Landroid/content/Context;)V
      //   12: aload_2
      //   13: ifnull +249 -> 262
      //   16: aload_2
      //   17: invokevirtual 104	android/content/Intent:getAction	()Ljava/lang/String;
      //   20: ldc 106
      //   22: bipush 68
      //   24: iconst_4
      //   25: invokestatic 42	kkkkkk/gguuuu:bккккк043Aкк043A043A	(Ljava/lang/String;CC)Ljava/lang/String;
      //   28: invokevirtual 112	java/lang/String:equals	(Ljava/lang/Object;)Z
      //   31: istore_3
      //   32: getstatic 78	kkkkkk/xxdddx$ConnectionReceiver:b0437зз0437зз	I
      //   35: invokestatic 72	kkkkkk/xxdddx$ConnectionReceiver:b043704370437ззз	()I
      //   38: iadd
      //   39: getstatic 78	kkkkkk/xxdddx$ConnectionReceiver:b0437зз0437зз	I
      //   42: imul
      //   43: getstatic 74	kkkkkk/xxdddx$ConnectionReceiver:bззз0437зз	I
      //   46: irem
      //   47: invokestatic 114	kkkkkk/xxdddx$ConnectionReceiver:b04370437з0437зз	()I
      //   50: if_icmpeq +14 -> 64
      //   53: invokestatic 70	kkkkkk/xxdddx$ConnectionReceiver:b0437з0437ззз	()I
      //   56: putstatic 78	kkkkkk/xxdddx$ConnectionReceiver:b0437зз0437зз	I
      //   59: bipush 27
      //   61: putstatic 76	kkkkkk/xxdddx$ConnectionReceiver:bз04370437ззз	I
      //   64: iload_3
      //   65: ifeq +197 -> 262
      //   68: invokestatic 118	kkkkkk/xxdddx:b0445хх04450445х0445044504450445	()Z
      //   71: istore_3
      //   72: invokestatic 121	kkkkkk/xxdddx:bх04450445х0445х0445044504450445	()Ljava/lang/String;
      //   75: astore_1
      //   76: new 123	java/lang/StringBuilder
      //   79: dup
      //   80: invokespecial 124	java/lang/StringBuilder:<init>	()V
      //   83: astore 4
      //   85: aload_1
      //   86: aload 4
      //   88: ldc 126
      //   90: iconst_4
      //   91: iconst_2
      //   92: invokestatic 42	kkkkkk/gguuuu:bккккк043Aкк043A043A	(Ljava/lang/String;CC)Ljava/lang/String;
      //   95: invokevirtual 130	java/lang/StringBuilder:append	(Ljava/lang/String;)Ljava/lang/StringBuilder;
      //   98: iload_3
      //   99: invokevirtual 133	java/lang/StringBuilder:append	(Z)Ljava/lang/StringBuilder;
      //   102: invokevirtual 136	java/lang/StringBuilder:toString	()Ljava/lang/String;
      //   105: invokestatic 142	kkkkkk/xtxtxt:bии0438и04380438и0438ии	(Ljava/lang/String;Ljava/lang/String;)V
      //   108: invokestatic 121	kkkkkk/xxdddx:bх04450445х0445х0445044504450445	()Ljava/lang/String;
      //   111: astore_1
      //   112: new 123	java/lang/StringBuilder
      //   115: dup
      //   116: invokespecial 124	java/lang/StringBuilder:<init>	()V
      //   119: astore 4
      //   121: aload 4
      //   123: ldc -112
      //   125: bipush 121
      //   127: iconst_4
      //   128: invokestatic 42	kkkkkk/gguuuu:bккккк043Aкк043A043A	(Ljava/lang/String;CC)Ljava/lang/String;
      //   131: invokevirtual 130	java/lang/StringBuilder:append	(Ljava/lang/String;)Ljava/lang/StringBuilder;
      //   134: astore 4
      //   136: getstatic 78	kkkkkk/xxdddx$ConnectionReceiver:b0437зз0437зз	I
      //   139: invokestatic 72	kkkkkk/xxdddx$ConnectionReceiver:b043704370437ззз	()I
      //   142: iadd
      //   143: getstatic 78	kkkkkk/xxdddx$ConnectionReceiver:b0437зз0437зз	I
      //   146: imul
      //   147: getstatic 74	kkkkkk/xxdddx$ConnectionReceiver:bззз0437зз	I
      //   150: irem
      //   151: getstatic 76	kkkkkk/xxdddx$ConnectionReceiver:bз04370437ззз	I
      //   154: if_icmpeq +14 -> 168
      //   157: bipush 51
      //   159: putstatic 78	kkkkkk/xxdddx$ConnectionReceiver:b0437зз0437зз	I
      //   162: invokestatic 70	kkkkkk/xxdddx$ConnectionReceiver:b0437з0437ззз	()I
      //   165: putstatic 76	kkkkkk/xxdddx$ConnectionReceiver:bз04370437ззз	I
      //   168: aload_1
      //   169: aload 4
      //   171: aload_0
      //   172: getfield 146	kkkkkk/xxdddx$ConnectionReceiver:lastConnectionState	Z
      //   175: invokevirtual 133	java/lang/StringBuilder:append	(Z)Ljava/lang/StringBuilder;
      //   178: invokevirtual 136	java/lang/StringBuilder:toString	()Ljava/lang/String;
      //   181: invokestatic 142	kkkkkk/xtxtxt:bии0438и04380438и0438ии	(Ljava/lang/String;Ljava/lang/String;)V
      //   184: aload_0
      //   185: getfield 146	kkkkkk/xxdddx$ConnectionReceiver:lastConnectionState	Z
      //   188: iload_3
      //   189: if_icmpeq +73 -> 262
      //   192: aload_0
      //   193: iload_3
      //   194: putfield 146	kkkkkk/xxdddx$ConnectionReceiver:lastConnectionState	Z
      //   197: aload_0
      //   198: iload_3
      //   199: invokespecial 148	kkkkkk/xxdddx$ConnectionReceiver:sendUpdateIntent	(Z)V
      //   202: invokestatic 121	kkkkkk/xxdddx:bх04450445х0445х0445044504450445	()Ljava/lang/String;
      //   205: astore_1
      //   206: new 123	java/lang/StringBuilder
      //   209: dup
      //   210: invokespecial 124	java/lang/StringBuilder:<init>	()V
      //   213: astore 4
      //   215: aload_1
      //   216: aload 4
      //   218: ldc -106
      //   220: bipush 67
      //   222: iconst_1
      //   223: invokestatic 42	kkkkkk/gguuuu:bккккк043Aкк043A043A	(Ljava/lang/String;CC)Ljava/lang/String;
      //   226: invokevirtual 130	java/lang/StringBuilder:append	(Ljava/lang/String;)Ljava/lang/StringBuilder;
      //   229: aload_2
      //   230: invokevirtual 104	android/content/Intent:getAction	()Ljava/lang/String;
      //   233: invokevirtual 130	java/lang/StringBuilder:append	(Ljava/lang/String;)Ljava/lang/StringBuilder;
      //   236: ldc -104
      //   238: bipush 77
      //   240: bipush 60
      //   242: iconst_0
      //   243: invokestatic 68	kkkkkk/gguuuu:bк043Aккк043Aкк043A043A	(Ljava/lang/String;CCC)Ljava/lang/String;
      //   246: invokevirtual 130	java/lang/StringBuilder:append	(Ljava/lang/String;)Ljava/lang/StringBuilder;
      //   249: aload_0
      //   250: getfield 146	kkkkkk/xxdddx$ConnectionReceiver:lastConnectionState	Z
      //   253: invokevirtual 133	java/lang/StringBuilder:append	(Z)Ljava/lang/StringBuilder;
      //   256: invokevirtual 136	java/lang/StringBuilder:toString	()Ljava/lang/String;
      //   259: invokestatic 155	kkkkkk/xtxtxt:bиии043804380438и0438ии	(Ljava/lang/String;Ljava/lang/String;)V
      //   262: return
      //   263: astore_1
      //   264: aload_1
      //   265: athrow
      //   266: astore_1
      //   267: aload_1
      //   268: athrow
      // Local variable table:
      //   start	length	slot	name	signature
      //   0	269	0	this	ConnectionReceiver
      //   0	269	1	paramContext	Context
      //   0	269	2	paramIntent	Intent
      //   31	168	3	bool	boolean
      //   83	134	4	localStringBuilder	StringBuilder
      // Exception table:
      //   from	to	target	type
      //   0	12	263	java/lang/Exception
      //   16	32	263	java/lang/Exception
      //   68	85	263	java/lang/Exception
      //   121	136	263	java/lang/Exception
      //   168	215	263	java/lang/Exception
      //   85	121	266	java/lang/Exception
      //   215	262	266	java/lang/Exception
    }
    
    public void register(Context paramContext)
    {
      Object localObject = paramContext.registerReceiver(this, this.intentFilter);
      this.lastConnectionState = xxdddx.b0445хх04450445х0445044504450445();
      onReceive(paramContext, (Intent)localObject);
      xtxtxt.bии0438и04380438и0438ии(xxdddx.bх04450445х0445х0445044504450445(), gguuuu.bк043Aккк043Aкк043A043A("fxyz\004\004sqo\\nklo{iu.!ctpoainLlXjjg\023/\021", 'Å', '¤', '\002') + localObject);
      paramContext = xxdddx.bх04450445х0445х0445044504450445();
      localObject = new StringBuilder();
      String str = gguuuu.bккккк043Aкк043A043A("\r\037 !**\032&\030\026\003\025\022\023\026\"\020\034TG\023\007\030\030e\021\017\016\004\001\021\005\n\bk\fw\ny3O1", 'b', '\003');
      int i = b0437зз0437зз;
      if ((b0437зз0437зз + bз0437з0437зз) * b0437зз0437зз % bззз0437зз != bз04370437ззз)
      {
        b0437зз0437зз = b0437з0437ззз();
        bз04370437ззз = b0437з0437ззз();
      }
      switch (i * (bз0437з0437зз + i) % bззз0437зз)
      {
      default: 
        b0437зз0437зз = b0437з0437ззз();
        bз04370437ззз = 19;
      }
      xtxtxt.bии0438и04380438и0438ии(paramContext, str + this.lastConnectionState);
    }
  }
}
