package kkkkkk;

import android.content.Context;
import android.os.Handler;
import android.os.Looper;
import android.text.TextUtils;

public enum xxdxxd
  implements xxddxd
{
  public static final String CLEAR_HISTORY_SHOW_CONFIRM_DIALOG = gguuuu.bккккк043Aкк043A043A(CLEAR_HISTORY_SHOW_CONFIRM_DIALOG, '', '\000');
  public static final String CONTEXTUAL_MENU_ON_TOOLBAR = gguuuu.bккккк043Aкк043A043A(CONTEXTUAL_MENU_ON_TOOLBAR, '\005', '\003');
  public static final String DISABLE_TTR_POPUP = gguuuu.bк043Aккк043Aкк043A043A(DISABLE_TTR_POPUP, '\035', '\031', '\003');
  public static final String FEATURES_CONFIGURATION = "NNK_a_SbOTaaZ^]ljZndkk";
  private static final String FILE_PROVIDER_AUTHORITY_PREFIX = "\t\026\025V\026\024\"\022\036\024\"$!!a\036$\035*\032g+.,4($&4p";
  public static final String KEY_AUTH_KEY = "9NNC;HCX";
  public static final String KEY_BRAND_ID = "u\005r~smvp";
  public static final String KEY_READ_ONLY = "7+(,(998F";
  public static final String KEY_TARGET_ID = "gScWTbLUO";
  public static final String KEY_VIEW_PARAMS = "\006yv\nr\005v\tx\006\r";
  public static final String SDK_VERSION = "7)1F>.<>5<<";
  public static final String SHOULD_USE_CONFIGURATION = "h^fme^Zqpc^cppiml{yi}szz";
  public static final String SHOW_AGENT_DETAILS_CSAT = "D:BK47>=GN:@BR@IMUBGXG[";
  public static final String SHOW_CSAT_THANK_YOU = "&\034$-\026\033,\033/\0331& .,!<3:";
  public static final String SHOW_FEEDBACK = "VLT]FNNOONNQZ";
  public static final String SHOW_TIMESTAMP_IN_TTR_NOTIFICATION = "dX^eL`TWN[[GRTBKO?SRO;IIMA=?85G;@>";
  public static final String SHOW_YES_NO_QUESTION = "rhpyb}jyfvxi|\002r\002\004y\001\001";
  private static final String TAG;
  public static final String TTR_MESSAGE_OFF_HOURS_ENABLED = "rqnZg^kjW\\YRaWVNV\\a]]HMUGGPHF";
  private dxxdxx dbEncryptionKeyHelper;
  private Context mAppContext;
  private Handler mAppHandler;
  private xxdddx mConnectionService;
  private String mHostVersion;
  private txxtxt mLoggos;
  private ddddxx mLptagEnvironment;
  public ovvvvv stateMachine = null;
  
  /* Error */
  static
  {
    // Byte code:
    //   0: getstatic 106	kkkkkk/xxdxxd:CLEAR_HISTORY_SHOW_CONFIRM_DIALOG	Ljava/lang/String;
    //   3: sipush 150
    //   6: iconst_0
    //   7: invokestatic 112	kkkkkk/gguuuu:bккккк043Aкк043A043A	(Ljava/lang/String;CC)Ljava/lang/String;
    //   10: putstatic 106	kkkkkk/xxdxxd:CLEAR_HISTORY_SHOW_CONFIRM_DIALOG	Ljava/lang/String;
    //   13: getstatic 114	kkkkkk/xxdxxd:CONTEXTUAL_MENU_ON_TOOLBAR	Ljava/lang/String;
    //   16: iconst_5
    //   17: iconst_3
    //   18: invokestatic 112	kkkkkk/gguuuu:bккккк043Aкк043A043A	(Ljava/lang/String;CC)Ljava/lang/String;
    //   21: putstatic 114	kkkkkk/xxdxxd:CONTEXTUAL_MENU_ON_TOOLBAR	Ljava/lang/String;
    //   24: getstatic 116	kkkkkk/xxdxxd:DISABLE_TTR_POPUP	Ljava/lang/String;
    //   27: bipush 29
    //   29: bipush 25
    //   31: iconst_3
    //   32: invokestatic 120	kkkkkk/gguuuu:bк043Aккк043Aкк043A043A	(Ljava/lang/String;CCC)Ljava/lang/String;
    //   35: putstatic 116	kkkkkk/xxdxxd:DISABLE_TTR_POPUP	Ljava/lang/String;
    //   38: invokestatic 124	kkkkkk/xxdxxd:b044504450445х04450445х044504450445	()I
    //   41: istore_0
    //   42: invokestatic 127	kkkkkk/xxdxxd:b0445х0445х04450445х044504450445	()I
    //   45: istore_1
    //   46: invokestatic 130	kkkkkk/xxdxxd:bх04450445х04450445х044504450445	()I
    //   49: istore_2
    //   50: iload_0
    //   51: iload_1
    //   52: iload_0
    //   53: iadd
    //   54: imul
    //   55: iload_2
    //   56: irem
    //   57: tableswitch	default:+19->76, 0:+19->76
    //   76: getstatic 132	kkkkkk/xxdxxd:FEATURES_CONFIGURATION	Ljava/lang/String;
    //   79: astore_3
    //   80: aload_3
    //   81: sipush 252
    //   84: sipush 149
    //   87: iconst_1
    //   88: invokestatic 120	kkkkkk/gguuuu:bк043Aккк043Aкк043A043A	(Ljava/lang/String;CCC)Ljava/lang/String;
    //   91: putstatic 132	kkkkkk/xxdxxd:FEATURES_CONFIGURATION	Ljava/lang/String;
    //   94: getstatic 134	kkkkkk/xxdxxd:FILE_PROVIDER_AUTHORITY_PREFIX	Ljava/lang/String;
    //   97: bipush 91
    //   99: sipush 200
    //   102: iconst_3
    //   103: invokestatic 120	kkkkkk/gguuuu:bк043Aккк043Aкк043A043A	(Ljava/lang/String;CCC)Ljava/lang/String;
    //   106: putstatic 134	kkkkkk/xxdxxd:FILE_PROVIDER_AUTHORITY_PREFIX	Ljava/lang/String;
    //   109: getstatic 136	kkkkkk/xxdxxd:KEY_AUTH_KEY	Ljava/lang/String;
    //   112: sipush 227
    //   115: bipush 13
    //   117: iconst_1
    //   118: invokestatic 120	kkkkkk/gguuuu:bк043Aккк043Aкк043A043A	(Ljava/lang/String;CCC)Ljava/lang/String;
    //   121: putstatic 136	kkkkkk/xxdxxd:KEY_AUTH_KEY	Ljava/lang/String;
    //   124: getstatic 138	kkkkkk/xxdxxd:KEY_BRAND_ID	Ljava/lang/String;
    //   127: astore_3
    //   128: invokestatic 124	kkkkkk/xxdxxd:b044504450445х04450445х044504450445	()I
    //   131: istore_0
    //   132: iload_0
    //   133: invokestatic 127	kkkkkk/xxdxxd:b0445х0445х04450445х044504450445	()I
    //   136: iload_0
    //   137: iadd
    //   138: imul
    //   139: invokestatic 130	kkkkkk/xxdxxd:bх04450445х04450445х044504450445	()I
    //   142: irem
    //   143: tableswitch	default:+17->160, 0:+17->160
    //   160: aload_3
    //   161: bipush 36
    //   163: iconst_2
    //   164: invokestatic 112	kkkkkk/gguuuu:bккккк043Aкк043A043A	(Ljava/lang/String;CC)Ljava/lang/String;
    //   167: putstatic 138	kkkkkk/xxdxxd:KEY_BRAND_ID	Ljava/lang/String;
    //   170: getstatic 140	kkkkkk/xxdxxd:KEY_READ_ONLY	Ljava/lang/String;
    //   173: sipush 161
    //   176: iconst_4
    //   177: invokestatic 112	kkkkkk/gguuuu:bккккк043Aкк043A043A	(Ljava/lang/String;CC)Ljava/lang/String;
    //   180: putstatic 140	kkkkkk/xxdxxd:KEY_READ_ONLY	Ljava/lang/String;
    //   183: getstatic 142	kkkkkk/xxdxxd:KEY_TARGET_ID	Ljava/lang/String;
    //   186: sipush 140
    //   189: iconst_5
    //   190: invokestatic 112	kkkkkk/gguuuu:bккккк043Aкк043A043A	(Ljava/lang/String;CC)Ljava/lang/String;
    //   193: putstatic 142	kkkkkk/xxdxxd:KEY_TARGET_ID	Ljava/lang/String;
    //   196: getstatic 144	kkkkkk/xxdxxd:KEY_VIEW_PARAMS	Ljava/lang/String;
    //   199: astore_3
    //   200: aload_3
    //   201: bipush 110
    //   203: sipush 222
    //   206: iconst_1
    //   207: invokestatic 120	kkkkkk/gguuuu:bк043Aккк043Aкк043A043A	(Ljava/lang/String;CCC)Ljava/lang/String;
    //   210: putstatic 144	kkkkkk/xxdxxd:KEY_VIEW_PARAMS	Ljava/lang/String;
    //   213: getstatic 146	kkkkkk/xxdxxd:SDK_VERSION	Ljava/lang/String;
    //   216: bipush 33
    //   218: iconst_1
    //   219: invokestatic 112	kkkkkk/gguuuu:bккккк043Aкк043A043A	(Ljava/lang/String;CC)Ljava/lang/String;
    //   222: putstatic 146	kkkkkk/xxdxxd:SDK_VERSION	Ljava/lang/String;
    //   225: getstatic 148	kkkkkk/xxdxxd:SHOULD_USE_CONFIGURATION	Ljava/lang/String;
    //   228: astore_3
    //   229: aload_3
    //   230: sipush 185
    //   233: bipush 69
    //   235: iconst_1
    //   236: invokestatic 120	kkkkkk/gguuuu:bк043Aккк043Aкк043A043A	(Ljava/lang/String;CCC)Ljava/lang/String;
    //   239: putstatic 148	kkkkkk/xxdxxd:SHOULD_USE_CONFIGURATION	Ljava/lang/String;
    //   242: getstatic 150	kkkkkk/xxdxxd:SHOW_AGENT_DETAILS_CSAT	Ljava/lang/String;
    //   245: sipush 167
    //   248: iconst_4
    //   249: invokestatic 112	kkkkkk/gguuuu:bккккк043Aкк043A043A	(Ljava/lang/String;CC)Ljava/lang/String;
    //   252: putstatic 150	kkkkkk/xxdxxd:SHOW_AGENT_DETAILS_CSAT	Ljava/lang/String;
    //   255: getstatic 152	kkkkkk/xxdxxd:SHOW_CSAT_THANK_YOU	Ljava/lang/String;
    //   258: astore_3
    //   259: aload_3
    //   260: bipush 50
    //   262: iconst_0
    //   263: invokestatic 112	kkkkkk/gguuuu:bккккк043Aкк043A043A	(Ljava/lang/String;CC)Ljava/lang/String;
    //   266: astore_3
    //   267: aload_3
    //   268: putstatic 152	kkkkkk/xxdxxd:SHOW_CSAT_THANK_YOU	Ljava/lang/String;
    //   271: getstatic 154	kkkkkk/xxdxxd:SHOW_FEEDBACK	Ljava/lang/String;
    //   274: bipush 87
    //   276: bipush 11
    //   278: iconst_3
    //   279: invokestatic 120	kkkkkk/gguuuu:bк043Aккк043Aкк043A043A	(Ljava/lang/String;CCC)Ljava/lang/String;
    //   282: putstatic 154	kkkkkk/xxdxxd:SHOW_FEEDBACK	Ljava/lang/String;
    //   285: getstatic 156	kkkkkk/xxdxxd:SHOW_TIMESTAMP_IN_TTR_NOTIFICATION	Ljava/lang/String;
    //   288: sipush 132
    //   291: iconst_2
    //   292: invokestatic 112	kkkkkk/gguuuu:bккккк043Aкк043A043A	(Ljava/lang/String;CC)Ljava/lang/String;
    //   295: putstatic 156	kkkkkk/xxdxxd:SHOW_TIMESTAMP_IN_TTR_NOTIFICATION	Ljava/lang/String;
    //   298: getstatic 158	kkkkkk/xxdxxd:SHOW_YES_NO_QUESTION	Ljava/lang/String;
    //   301: sipush 190
    //   304: iconst_4
    //   305: invokestatic 112	kkkkkk/gguuuu:bккккк043Aкк043A043A	(Ljava/lang/String;CC)Ljava/lang/String;
    //   308: putstatic 158	kkkkkk/xxdxxd:SHOW_YES_NO_QUESTION	Ljava/lang/String;
    //   311: getstatic 160	kkkkkk/xxdxxd:TTR_MESSAGE_OFF_HOURS_ENABLED	Ljava/lang/String;
    //   314: astore_3
    //   315: aload_3
    //   316: sipush 128
    //   319: iconst_3
    //   320: invokestatic 112	kkkkkk/gguuuu:bккккк043Aкк043A043A	(Ljava/lang/String;CC)Ljava/lang/String;
    //   323: putstatic 160	kkkkkk/xxdxxd:TTR_MESSAGE_OFF_HOURS_ENABLED	Ljava/lang/String;
    //   326: new 2	kkkkkk/xxdxxd
    //   329: dup
    //   330: ldc -94
    //   332: sipush 186
    //   335: iconst_3
    //   336: invokestatic 112	kkkkkk/gguuuu:bккккк043Aкк043A043A	(Ljava/lang/String;CC)Ljava/lang/String;
    //   339: iconst_0
    //   340: invokespecial 166	kkkkkk/xxdxxd:<init>	(Ljava/lang/String;I)V
    //   343: astore_3
    //   344: aload_3
    //   345: putstatic 168	kkkkkk/xxdxxd:instance	Lkkkkkk/xxdxxd;
    //   348: getstatic 168	kkkkkk/xxdxxd:instance	Lkkkkkk/xxdxxd;
    //   351: astore_3
    //   352: iconst_0
    //   353: tableswitch	default:+23->376, 0:+50->403, 1:+-1->352
    //   376: iconst_1
    //   377: tableswitch	default:+23->400, 0:+-25->352, 1:+26->403
    //   400: goto -24 -> 376
    //   403: iconst_1
    //   404: anewarray 2	kkkkkk/xxdxxd
    //   407: dup
    //   408: iconst_0
    //   409: aload_3
    //   410: aastore
    //   411: putstatic 170	kkkkkk/xxdxxd:$VALUES	[Lkkkkkk/xxdxxd;
    //   414: ldc 2
    //   416: invokevirtual 176	java/lang/Class:getSimpleName	()Ljava/lang/String;
    //   419: putstatic 178	kkkkkk/xxdxxd:TAG	Ljava/lang/String;
    //   422: return
    //   423: astore_3
    //   424: aload_3
    //   425: athrow
    //   426: astore_3
    //   427: aload_3
    //   428: athrow
    // Local variable table:
    //   start	length	slot	name	signature
    //   41	98	0	i	int
    //   45	9	1	j	int
    //   49	8	2	k	int
    //   79	331	3	localObject	Object
    //   423	2	3	localException1	Exception
    //   426	2	3	localException2	Exception
    // Exception table:
    //   from	to	target	type
    //   0	50	423	java/lang/Exception
    //   80	109	423	java/lang/Exception
    //   124	128	423	java/lang/Exception
    //   160	200	423	java/lang/Exception
    //   229	259	423	java/lang/Exception
    //   267	315	423	java/lang/Exception
    //   326	344	423	java/lang/Exception
    //   348	352	423	java/lang/Exception
    //   76	80	426	java/lang/Exception
    //   109	124	426	java/lang/Exception
    //   200	229	426	java/lang/Exception
    //   259	267	426	java/lang/Exception
    //   315	326	426	java/lang/Exception
    //   344	348	426	java/lang/Exception
    //   403	422	426	java/lang/Exception
  }
  
  private xxdxxd()
  {
    b04450445хххх0445044504450445();
  }
  
  /* Error */
  private void b044504450445044504450445х044504450445()
  {
    // Byte code:
    //   0: invokestatic 124	kkkkkk/xxdxxd:b044504450445х04450445х044504450445	()I
    //   3: istore_1
    //   4: invokestatic 127	kkkkkk/xxdxxd:b0445х0445х04450445х044504450445	()I
    //   7: istore_2
    //   8: invokestatic 130	kkkkkk/xxdxxd:bх04450445х04450445х044504450445	()I
    //   11: istore_3
    //   12: iload_1
    //   13: iload_2
    //   14: iload_1
    //   15: iadd
    //   16: imul
    //   17: iload_3
    //   18: irem
    //   19: tableswitch	default:+17->36, 0:+17->36
    //   36: invokestatic 193	kkkkkk/dxxdxd:b04450445х0445ххх044504450445	()Lkkkkkk/dxxdxd;
    //   39: astore 4
    //   41: aload 4
    //   43: invokevirtual 196	kkkkkk/dxxdxd:b0445ххх0445хх044504450445	()V
    //   46: invokestatic 202	kkkkkk/mrmrmm:bШ04280428Ш0428Ш0428ШШШ	()Lkkkkkk/mrmrmm;
    //   49: invokevirtual 203	kkkkkk/mrmrmm:b0445ххх0445хх044504450445	()V
    //   52: invokestatic 208	kkkkkk/bhhhbh:bШШ0428ШШШ0428ШШ0428	()V
    //   55: invokestatic 214	kkkkkk/txtttt:b04380438и0438и04380438иии	()Lkkkkkk/txtttt;
    //   58: astore 4
    //   60: aload 4
    //   62: invokevirtual 215	kkkkkk/txtttt:b0445ххх0445хх044504450445	()V
    //   65: aload_0
    //   66: getfield 217	kkkkkk/xxdxxd:mConnectionService	Lkkkkkk/xxdddx;
    //   69: astore 4
    //   71: invokestatic 124	kkkkkk/xxdxxd:b044504450445х04450445х044504450445	()I
    //   74: istore_1
    //   75: iload_1
    //   76: invokestatic 127	kkkkkk/xxdxxd:b0445х0445х04450445х044504450445	()I
    //   79: iload_1
    //   80: iadd
    //   81: imul
    //   82: invokestatic 130	kkkkkk/xxdxxd:bх04450445х04450445х044504450445	()I
    //   85: irem
    //   86: tableswitch	default:+18->104, 0:+18->104
    //   104: aload 4
    //   106: invokevirtual 220	kkkkkk/xxdddx:b0445ххх0445хх044504450445	()V
    //   109: aload_0
    //   110: getfield 222	kkkkkk/xxdxxd:mAppHandler	Landroid/os/Handler;
    //   113: aconst_null
    //   114: invokevirtual 228	android/os/Handler:removeCallbacksAndMessages	(Ljava/lang/Object;)V
    //   117: aload_0
    //   118: aconst_null
    //   119: putfield 222	kkkkkk/xxdxxd:mAppHandler	Landroid/os/Handler;
    //   122: aload_0
    //   123: aconst_null
    //   124: putfield 230	kkkkkk/xxdxxd:mHostVersion	Ljava/lang/String;
    //   127: return
    //   128: astore 4
    //   130: aload 4
    //   132: athrow
    //   133: astore 4
    //   135: aload 4
    //   137: athrow
    //   138: astore 4
    //   140: aload 4
    //   142: athrow
    //   143: astore 4
    //   145: aload 4
    //   147: athrow
    // Local variable table:
    //   start	length	slot	name	signature
    //   0	148	0	this	xxdxxd
    //   3	79	1	i	int
    //   7	9	2	j	int
    //   11	8	3	k	int
    //   39	66	4	localObject	Object
    //   128	3	4	localException1	Exception
    //   133	3	4	localException2	Exception
    //   138	3	4	localException3	Exception
    //   143	3	4	localException4	Exception
    // Exception table:
    //   from	to	target	type
    //   41	55	128	java/lang/Exception
    //   60	71	128	java/lang/Exception
    //   104	122	128	java/lang/Exception
    //   4	8	133	java/lang/Exception
    //   130	133	133	java/lang/Exception
    //   140	143	133	java/lang/Exception
    //   36	41	138	java/lang/Exception
    //   55	60	138	java/lang/Exception
    //   122	127	138	java/lang/Exception
    //   0	4	143	java/lang/Exception
    //   8	12	143	java/lang/Exception
  }
  
  public static int b044504450445х04450445х044504450445()
  {
    return 95;
  }
  
  public static String b04450445х044504450445х044504450445()
  {
    switch (0)
    {
    case 1: 
    default: 
      for (;;)
      {
        switch (1)
        {
        }
      }
    }
    if (((b044504450445х04450445х044504450445() + b0445х0445х04450445х044504450445()) * b044504450445х04450445х044504450445() % bх04450445х04450445х044504450445() == bхх0445х04450445х044504450445()) || ((b044504450445х04450445х044504450445() + b0445х0445х04450445х044504450445()) * b044504450445х04450445х044504450445() % bх04450445х04450445х044504450445() != bхх0445х04450445х044504450445())) {}
    return gguuuu.bккккк043Aкк043A043A("FSR\024SQ_O[Q_a^^\037[aZgW%hkiqeacq.", 'á', '\000');
  }
  
  public static xxdxxd b04450445х0445хх0445044504450445(String paramString)
  {
    int i = b044504450445х04450445х044504450445();
    switch (i * (b0445х0445х04450445х044504450445() + i) % bх04450445х04450445х044504450445())
    {
    }
    paramString = (xxdxxd)Enum.valueOf(xxdxxd.class, paramString);
    switch (0)
    {
    case 1: 
    default: 
      for (;;)
      {
        i = b044504450445х04450445х044504450445();
        switch (i * (b0445х0445х04450445х044504450445() + i) % bх04450445х04450445х044504450445())
        {
        }
        switch (1)
        {
        }
      }
    }
    return paramString;
  }
  
  private void b04450445хххх0445044504450445()
  {
    int i = 4;
    if (this.stateMachine == null)
    {
      this.stateMachine = new ovvvvv();
      this.stateMachine.b0428ШШ04280428Ш04280428ШШ(new ooooov(this.stateMachine.bШШ0428Ш0428Ш04280428ШШ(), this.stateMachine));
      try
      {
        throw new NullPointerException();
      }
      catch (Exception localException1)
      {
        try
        {
          throw new NullPointerException();
        }
        catch (Exception localException2)
        {
          try
          {
            for (;;)
            {
              i /= 0;
            }
            switch (1)
            {
            case 0: 
            default: 
              for (;;)
              {
                switch (0)
                {
                }
              }
            }
            return;
          }
          catch (Exception localException3) {}
        }
      }
    }
    switch (1)
    {
    }
    for (;;)
    {
      if ((b044504450445х04450445х044504450445() + b0445х0445х04450445х044504450445()) * b044504450445х04450445х044504450445() % bх04450445х04450445х044504450445() != bхх0445х04450445х044504450445()) {}
      switch (1)
      {
      }
    }
  }
  
  public static int b0445х0445х04450445х044504450445()
  {
    return 1;
  }
  
  private void b0445ххххх0445044504450445(Context paramContext, vvvvov paramVvvvov)
  {
    this.mAppContext = paramContext.getApplicationContext();
    paramContext = new Handler(Looper.getMainLooper());
    if ((b044504450445х04450445х044504450445() + b0445х0445х04450445х044504450445()) * b044504450445х04450445х044504450445() % bх04450445х04450445х044504450445() != bхх0445х04450445х044504450445()) {}
    this.mAppHandler = paramContext;
    if (paramVvvvov != null) {}
    for (paramContext = paramVvvvov.b0428ШШШШШ04280428ШШ();; paramContext = null)
    {
      bх0445хххх0445044504450445(paramContext);
      this.mLoggos = new txxtxt();
      this.mLptagEnvironment = new ddddxx();
      switch (0)
      {
      case 1: 
      default: 
        for (;;)
        {
          switch (1)
          {
          }
        }
      }
      int i = b044504450445х04450445х044504450445();
      switch (i * (b0445х0445х04450445х044504450445() + i) % bх04450445х04450445х044504450445())
      {
      }
      if (this.dbEncryptionKeyHelper == null) {
        this.dbEncryptionKeyHelper = new dxxdxx(null);
      }
      this.mConnectionService = new xxdddx();
      return;
    }
  }
  
  public static int bх04450445х04450445х044504450445()
  {
    return 2;
  }
  
  private void bх0445хххх0445044504450445(String paramString)
  {
    if (TextUtils.isEmpty(paramString))
    {
      paramString = xtxxxt.b0438ии04380438043804380438ии();
      String str = gguuuu.bккккк043Aкк043A043A("qy\017\007v\005\007}\005\005", '¸', '\001');
      switch (1)
      {
      case 0: 
      default: 
        for (;;)
        {
          switch (0)
          {
          }
        }
      }
      this.mHostVersion = paramString.bи0438043804380438043804380438ии(str, "", "");
      if (TextUtils.isEmpty(this.mHostVersion)) {
        throw new IllegalStateException(gguuuu.bккккк043Aкк043A043A("~\b\007\t5~x\017~:|<\024\f\026\007B\n\024\030F\033\r\025W\"\022 \"\031  S", '', '\000'));
      }
    }
    else
    {
      this.mHostVersion = paramString;
      xtxxxt.b0438ии04380438043804380438ии().b04380438ииииии0438и(gguuuu.bккккк043Aкк043A043A("\n{\004\031\021\001\017\021\b\017\017", '\033', '\004'), "", this.mHostVersion);
    }
  }
  
  public static int bхх0445х04450445х044504450445()
  {
    return 0;
  }
  
  public void b0445044504450445044504450445х04450445()
  {
    int i = b044504450445х04450445х044504450445();
    switch (i * (b0445х0445х04450445х044504450445() + i) % bх04450445х04450445х044504450445())
    {
    }
    try
    {
      if (this.mAppContext != null)
      {
        xtxxxt.b0438ии04380438043804380438ии().bи04380438и0438043804380438ии();
        txtttt.b04380438и0438и04380438иии().b0445044504450445044504450445х04450445();
        this.dbEncryptionKeyHelper.b0445044504450445044504450445х04450445();
        if ((b044504450445х04450445х044504450445() + b0445х0445х04450445х044504450445()) * b044504450445х04450445х044504450445() % bх04450445х04450445х044504450445() != bхх0445х04450445х044504450445()) {}
        this.dbEncryptionKeyHelper = null;
        this.mAppContext = null;
      }
      return;
    }
    catch (Exception localException)
    {
      throw localException;
    }
  }
  
  public void b044504450445ххх0445044504450445()
  {
    try
    {
      xxdddx localXxdddx = this.mConnectionService;
      if (localXxdddx != null)
      {
        if (((b044504450445х04450445х044504450445() + b0445х0445х04450445х044504450445()) * b044504450445х04450445х044504450445() % bх04450445х04450445х044504450445() != bхх0445х04450445х044504450445()) && ((b044504450445х04450445х044504450445() + b0445х0445х04450445х044504450445()) * b044504450445х04450445х044504450445() % bх04450445х04450445х044504450445() != bхх0445х04450445х044504450445())) {}
        this.mConnectionService.bх0445х04450445х0445044504450445();
      }
      return;
    }
    catch (Exception localException)
    {
      throw localException;
    }
  }
  
  /* Error */
  public txxtxt b0445х0445044504450445х044504450445()
  {
    // Byte code:
    //   0: invokestatic 124	kkkkkk/xxdxxd:b044504450445х04450445х044504450445	()I
    //   3: istore_1
    //   4: invokestatic 127	kkkkkk/xxdxxd:b0445х0445х04450445х044504450445	()I
    //   7: istore_2
    //   8: invokestatic 124	kkkkkk/xxdxxd:b044504450445х04450445х044504450445	()I
    //   11: istore_3
    //   12: invokestatic 130	kkkkkk/xxdxxd:bх04450445х04450445х044504450445	()I
    //   15: istore 4
    //   17: invokestatic 234	kkkkkk/xxdxxd:bхх0445х04450445х044504450445	()I
    //   20: istore 5
    //   22: iload_1
    //   23: iload_2
    //   24: iadd
    //   25: iload_3
    //   26: imul
    //   27: iload 4
    //   29: irem
    //   30: iload 5
    //   32: if_icmpeq +24 -> 56
    //   35: invokestatic 124	kkkkkk/xxdxxd:b044504450445х04450445х044504450445	()I
    //   38: invokestatic 127	kkkkkk/xxdxxd:b0445х0445х04450445х044504450445	()I
    //   41: iadd
    //   42: invokestatic 124	kkkkkk/xxdxxd:b044504450445х04450445х044504450445	()I
    //   45: imul
    //   46: invokestatic 130	kkkkkk/xxdxxd:bх04450445х04450445х044504450445	()I
    //   49: irem
    //   50: invokestatic 234	kkkkkk/xxdxxd:bхх0445х04450445х044504450445	()I
    //   53: if_icmpeq +3 -> 56
    //   56: aload_0
    //   57: getfield 299	kkkkkk/xxdxxd:mLoggos	Lkkkkkk/txxtxt;
    //   60: astore 6
    //   62: aload 6
    //   64: areturn
    //   65: astore 6
    //   67: aload 6
    //   69: athrow
    //   70: astore 6
    //   72: aload 6
    //   74: athrow
    //   75: astore 6
    //   77: aload 6
    //   79: athrow
    // Local variable table:
    //   start	length	slot	name	signature
    //   0	80	0	this	xxdxxd
    //   3	22	1	i	int
    //   7	18	2	j	int
    //   11	16	3	k	int
    //   15	15	4	m	int
    //   20	13	5	n	int
    //   60	3	6	localTxxtxt	txxtxt
    //   65	3	6	localException1	Exception
    //   70	3	6	localException2	Exception
    //   75	3	6	localException3	Exception
    // Exception table:
    //   from	to	target	type
    //   56	62	65	java/lang/Exception
    //   0	8	70	java/lang/Exception
    //   67	70	70	java/lang/Exception
    //   8	22	75	java/lang/Exception
  }
  
  /* Error */
  public void b0445х0445ххх0445044504450445(Context paramContext, vvvvov paramVvvvov, vvooov paramVvooov)
  {
    // Byte code:
    //   0: invokestatic 124	kkkkkk/xxdxxd:b044504450445х04450445х044504450445	()I
    //   3: invokestatic 127	kkkkkk/xxdxxd:b0445х0445х04450445х044504450445	()I
    //   6: iadd
    //   7: invokestatic 124	kkkkkk/xxdxxd:b044504450445х04450445х044504450445	()I
    //   10: imul
    //   11: invokestatic 130	kkkkkk/xxdxxd:bх04450445х04450445х044504450445	()I
    //   14: irem
    //   15: invokestatic 234	kkkkkk/xxdxxd:bхх0445х04450445х044504450445	()I
    //   18: if_icmpeq +24 -> 42
    //   21: invokestatic 124	kkkkkk/xxdxxd:b044504450445х04450445х044504450445	()I
    //   24: invokestatic 127	kkkkkk/xxdxxd:b0445х0445х04450445х044504450445	()I
    //   27: iadd
    //   28: invokestatic 124	kkkkkk/xxdxxd:b044504450445х04450445х044504450445	()I
    //   31: imul
    //   32: invokestatic 130	kkkkkk/xxdxxd:bх04450445х04450445х044504450445	()I
    //   35: irem
    //   36: invokestatic 234	kkkkkk/xxdxxd:bхх0445х04450445х044504450445	()I
    //   39: if_icmpeq +3 -> 42
    //   42: new 18	kkkkkk/xxdxxd$xdxxxd
    //   45: dup
    //   46: aload_0
    //   47: aload_1
    //   48: aload_2
    //   49: aload_3
    //   50: invokespecial 372	kkkkkk/xxdxxd$xdxxxd:<init>	(Lkkkkkk/xxdxxd;Landroid/content/Context;Lkkkkkk/vvvvov;Lkkkkkk/vvooov;)V
    //   53: astore_1
    //   54: aload_0
    //   55: getfield 182	kkkkkk/xxdxxd:stateMachine	Lkkkkkk/ovvvvv;
    //   58: aload_1
    //   59: invokevirtual 376	kkkkkk/ovvvvv:b0428ШШ0428Ш0428Ш0428ШШ	(Lkkkkkk/vvooov;)V
    //   62: return
    //   63: astore_1
    //   64: aload_1
    //   65: athrow
    //   66: astore_1
    //   67: aload_1
    //   68: athrow
    // Local variable table:
    //   start	length	slot	name	signature
    //   0	69	0	this	xxdxxd
    //   0	69	1	paramContext	Context
    //   0	69	2	paramVvvvov	vvvvov
    //   0	69	3	paramVvooov	vvooov
    // Exception table:
    //   from	to	target	type
    //   54	62	63	java/lang/Exception
    //   42	54	66	java/lang/Exception
  }
  
  public Handler b0445хх044504450445х044504450445()
  {
    try
    {
      Handler localHandler = this.mAppHandler;
      if (((b044504450445х04450445х044504450445() + b0445х0445х04450445х044504450445()) * b044504450445х04450445х044504450445() % bх04450445х04450445х044504450445() != bхх0445х04450445х044504450445()) && ((b044504450445х04450445х044504450445() + b0445х0445х04450445х044504450445()) * b044504450445х04450445х044504450445() % bх04450445х04450445х044504450445() != bхх0445х04450445х044504450445())) {}
      return localHandler;
    }
    catch (Exception localException)
    {
      throw localException;
    }
  }
  
  public void b0445хх0445хх0445044504450445(ovooov paramOvooov)
  {
    paramOvooov = new dddddx(paramOvooov);
    ovvvvv localOvvvvv = this.stateMachine;
    switch (1)
    {
    case 0: 
    default: 
      for (;;)
      {
        i = b044504450445х04450445х044504450445();
        switch (i * (b0445х0445х04450445х044504450445() + i) % bх04450445х04450445х044504450445())
        {
        }
        switch (1)
        {
        }
      }
    }
    int i = b044504450445х04450445х044504450445();
    int j = b0445х0445х04450445х044504450445();
    int k = bх04450445х04450445х044504450445();
    switch (0)
    {
    case 1: 
    default: 
      for (;;)
      {
        switch (1)
        {
        }
      }
    }
    switch (i * (j + i) % k)
    {
    }
    localOvvvvv.bШ0428Ш0428Ш0428Ш0428ШШ(paramOvooov);
  }
  
  public ddddxx bх04450445044504450445х044504450445()
  {
    if (((b044504450445х04450445х044504450445() + b0445х0445х04450445х044504450445()) * b044504450445х04450445х044504450445() % bх04450445х04450445х044504450445() != bхх0445х04450445х044504450445()) && ((b044504450445х04450445х044504450445() + b0445х0445х04450445х044504450445()) * b044504450445х04450445х044504450445() % bх04450445х04450445х044504450445() != bхх0445х04450445х044504450445())) {}
    try
    {
      ddddxx localDdddxx = this.mLptagEnvironment;
      return localDdddxx;
    }
    catch (Exception localException)
    {
      throw localException;
    }
  }
  
  public void bх04450445ххх0445044504450445(Runnable paramRunnable)
  {
    if (this.mAppHandler != null)
    {
      Handler localHandler = this.mAppHandler;
      if ((b044504450445х04450445х044504450445() + b0445х0445х04450445х044504450445()) * b044504450445х04450445х044504450445() % bх04450445х04450445х044504450445() != bхх0445х04450445х044504450445()) {}
      localHandler.post(paramRunnable);
    }
    switch (0)
    {
    case 1: 
    default: 
      for (;;)
      {
        switch (1)
        {
        }
      }
    }
  }
  
  public dxxdxx bх0445х044504450445х044504450445()
  {
    if (((b044504450445х04450445х044504450445() + b0445х0445х04450445х044504450445()) * b044504450445х04450445х044504450445() % bх04450445х04450445х044504450445() == bхх0445х04450445х044504450445()) || ((b044504450445х04450445х044504450445() + b0445х0445х04450445х044504450445()) * b044504450445х04450445х044504450445() % bх04450445х04450445х044504450445() != bхх0445х04450445х044504450445())) {
      switch (0)
      {
      case 1: 
      default: 
        for (;;)
        {
          switch (0)
          {
          }
        }
      }
    }
    return this.dbEncryptionKeyHelper;
  }
  
  /* Error */
  public void bх0445х0445хх0445044504450445()
  {
    // Byte code:
    //   0: aload_0
    //   1: getfield 217	kkkkkk/xxdxxd:mConnectionService	Lkkkkkk/xxdddx;
    //   4: ifnull +52 -> 56
    //   7: aload_0
    //   8: getfield 217	kkkkkk/xxdxxd:mConnectionService	Lkkkkkk/xxdddx;
    //   11: astore 4
    //   13: aload 4
    //   15: invokevirtual 400	kkkkkk/xxdddx:b04450445х04450445х0445044504450445	()V
    //   18: invokestatic 124	kkkkkk/xxdxxd:b044504450445х04450445х044504450445	()I
    //   21: istore_1
    //   22: invokestatic 127	kkkkkk/xxdxxd:b0445х0445х04450445х044504450445	()I
    //   25: istore_2
    //   26: invokestatic 130	kkkkkk/xxdxxd:bх04450445х04450445х044504450445	()I
    //   29: istore_3
    //   30: iload_1
    //   31: iload_2
    //   32: iload_1
    //   33: iadd
    //   34: imul
    //   35: iload_3
    //   36: irem
    //   37: tableswitch	default:+19->56, 0:+19->56
    //   56: iconst_1
    //   57: tableswitch	default:+23->80, 0:+-1->56, 1:+70->127
    //   80: invokestatic 124	kkkkkk/xxdxxd:b044504450445х04450445х044504450445	()I
    //   83: invokestatic 127	kkkkkk/xxdxxd:b0445х0445х04450445х044504450445	()I
    //   86: iadd
    //   87: invokestatic 124	kkkkkk/xxdxxd:b044504450445х04450445х044504450445	()I
    //   90: imul
    //   91: invokestatic 130	kkkkkk/xxdxxd:bх04450445х04450445х044504450445	()I
    //   94: irem
    //   95: invokestatic 234	kkkkkk/xxdxxd:bхх0445х04450445х044504450445	()I
    //   98: if_icmpeq +3 -> 101
    //   101: iconst_0
    //   102: tableswitch	default:+22->124, 0:+25->127, 1:+-46->56
    //   124: goto -44 -> 80
    //   127: return
    //   128: astore 4
    //   130: aload 4
    //   132: athrow
    //   133: astore 4
    //   135: aload 4
    //   137: athrow
    // Local variable table:
    //   start	length	slot	name	signature
    //   0	138	0	this	xxdxxd
    //   21	14	1	i	int
    //   25	9	2	j	int
    //   29	8	3	k	int
    //   11	3	4	localXxdddx	xxdddx
    //   128	3	4	localException1	Exception
    //   133	3	4	localException2	Exception
    // Exception table:
    //   from	to	target	type
    //   0	13	128	java/lang/Exception
    //   13	30	133	java/lang/Exception
  }
  
  public String bхх0445044504450445х044504450445()
  {
    try
    {
      str = this.mHostVersion;
    }
    catch (Exception localException)
    {
      String str;
      int i;
      int j;
      int k;
      int m;
      int n;
      throw localException;
    }
    i = b044504450445х04450445х044504450445();
    j = b0445х0445х04450445х044504450445();
    k = b044504450445х04450445х044504450445();
    m = bх04450445х04450445х044504450445();
    n = bхх0445х04450445х044504450445();
    if ((i + j) * k % m != n)
    {
      i = b044504450445х04450445х044504450445();
      switch (i * (b0445х0445х04450445х044504450445() + i) % bх04450445х04450445х044504450445())
      {
      }
    }
    return str;
    switch (1)
    {
    }
    for (;;)
    {
      switch (0)
      {
      }
    }
  }
  
  public boolean bхх0445ххх0445044504450445()
  {
    for (;;)
    {
      try
      {
        if (this.stateMachine != null)
        {
          bool1 = this.stateMachine.bШШШ0428Ш0428Ш0428ШШ();
          if (bool1) {
            bool1 = true;
          }
        }
      }
      catch (Exception localException1)
      {
        try
        {
          boolean bool1;
          int i;
          int j;
          int k;
          boolean bool2;
          throw localException1;
        }
        catch (Exception localException2)
        {
          throw localException2;
        }
      }
      try
      {
        i = b044504450445х04450445х044504450445();
        j = b0445х0445х04450445х044504450445();
        k = bх04450445х04450445х044504450445();
        switch (i * (j + i) % k)
        {
        }
        return bool1;
      }
      catch (Exception localException3)
      {
        throw localException3;
      }
      bool2 = false;
      bool1 = bool2;
      if ((b044504450445х04450445х044504450445() + b0445х0445х04450445х044504450445()) * b044504450445х04450445х044504450445() % bх04450445х04450445х044504450445() != bхх0445х04450445х044504450445()) {
        bool1 = bool2;
      }
    }
  }
  
  public Context bххх044504450445х044504450445()
  {
    switch (0)
    {
    case 1: 
    default: 
      for (;;)
      {
        switch (1)
        {
        }
      }
    }
    if ((b044504450445х04450445х044504450445() + b0445х0445х04450445х044504450445()) * b044504450445х04450445х044504450445() % bх04450445х04450445х044504450445() != bхх0445х04450445х044504450445()) {}
    try
    {
      Context localContext = this.mAppContext;
      int i = b044504450445х04450445х044504450445();
      switch (i * (b0445х0445х04450445х044504450445() + i) % bх04450445х04450445х044504450445())
      {
      }
      return localContext;
    }
    catch (Exception localException)
    {
      throw localException;
    }
  }
  
  public void bххх0445хх0445044504450445()
  {
    if ((b044504450445х04450445х044504450445() + b0445х0445х04450445х044504450445()) * b044504450445х04450445х044504450445() % bх04450445х04450445х044504450445() != bхх0445х04450445х044504450445()) {}
    switch (1)
    {
    case 0: 
    default: 
      for (;;)
      {
        switch (0)
        {
        case 1: 
        default: 
          for (;;)
          {
            switch (0)
            {
            }
          }
        }
        switch (1)
        {
        }
      }
    }
  }
  
  /* Error */
  public void bхххххх0445044504450445(Context paramContext, vvvvov paramVvvvov, vovoov paramVovoov)
  {
    // Byte code:
    //   0: new 15	kkkkkk/xxdxxd$ddxxxd
    //   3: dup
    //   4: aload_0
    //   5: aload_1
    //   6: aload_2
    //   7: aload_3
    //   8: invokespecial 412	kkkkkk/xxdxxd$ddxxxd:<init>	(Lkkkkkk/xxdxxd;Landroid/content/Context;Lkkkkkk/vvvvov;Lkkkkkk/vovoov;)V
    //   11: astore_1
    //   12: invokestatic 124	kkkkkk/xxdxxd:b044504450445х04450445х044504450445	()I
    //   15: istore 4
    //   17: invokestatic 127	kkkkkk/xxdxxd:b0445х0445х04450445х044504450445	()I
    //   20: istore 5
    //   22: invokestatic 130	kkkkkk/xxdxxd:bх04450445х04450445х044504450445	()I
    //   25: istore 6
    //   27: iload 4
    //   29: iload 5
    //   31: iload 4
    //   33: iadd
    //   34: imul
    //   35: iload 6
    //   37: irem
    //   38: tableswitch	default:+18->56, 0:+18->56
    //   56: aload_0
    //   57: getfield 182	kkkkkk/xxdxxd:stateMachine	Lkkkkkk/ovvvvv;
    //   60: astore_2
    //   61: invokestatic 124	kkkkkk/xxdxxd:b044504450445х04450445х044504450445	()I
    //   64: istore 4
    //   66: iload 4
    //   68: invokestatic 127	kkkkkk/xxdxxd:b0445х0445х04450445х044504450445	()I
    //   71: iload 4
    //   73: iadd
    //   74: imul
    //   75: invokestatic 130	kkkkkk/xxdxxd:bх04450445х04450445х044504450445	()I
    //   78: irem
    //   79: tableswitch	default:+17->96, 0:+17->96
    //   96: aload_2
    //   97: aload_1
    //   98: invokevirtual 416	kkkkkk/ovvvvv:b042804280428ШШ0428Ш0428ШШ	(Lkkkkkk/vovoov;)V
    //   101: return
    //   102: astore_1
    //   103: aload_1
    //   104: athrow
    //   105: astore_1
    //   106: aload_1
    //   107: athrow
    //   108: astore_1
    //   109: aload_1
    //   110: athrow
    //   111: astore_1
    //   112: aload_1
    //   113: athrow
    // Local variable table:
    //   start	length	slot	name	signature
    //   0	114	0	this	xxdxxd
    //   0	114	1	paramContext	Context
    //   0	114	2	paramVvvvov	vvvvov
    //   0	114	3	paramVovoov	vovoov
    //   15	60	4	i	int
    //   20	14	5	j	int
    //   25	13	6	k	int
    // Exception table:
    //   from	to	target	type
    //   0	12	102	java/lang/Exception
    //   56	61	102	java/lang/Exception
    //   103	105	105	java/lang/Exception
    //   109	111	105	java/lang/Exception
    //   96	101	108	java/lang/Exception
    //   12	27	111	java/lang/Exception
  }
  
  private class dddddx
    extends ovooov
  {
    private final ovooov b042A042A042AЪЪЪЪЪЪ;
    
    public dddddx(ovooov paramOvooov)
    {
      this.b042A042A042AЪЪЪЪЪЪ = paramOvooov;
    }
    
    /* Error */
    public void bхххх04450445х044504450445(final voovov paramVoovov)
    {
      // Byte code:
      //   0: iconst_1
      //   1: istore_2
      //   2: iload_2
      //   3: iconst_0
      //   4: idiv
      //   5: istore_2
      //   6: goto -4 -> 2
      //   9: astore_3
      //   10: aload_0
      //   11: getfield 23	kkkkkk/xxdxxd$dddddx:b042A042A042AЪЪЪЪЪЪ	Lkkkkkk/ovooov;
      //   14: astore_3
      //   15: new 9	kkkkkk/xxdxxd$dddddx$1
      //   18: dup
      //   19: aload_0
      //   20: aload_1
      //   21: invokespecial 31	kkkkkk/xxdxxd$dddddx$1:<init>	(Lkkkkkk/xxdxxd$dddddx;Lkkkkkk/voovov;)V
      //   24: astore_1
      //   25: aload_3
      //   26: aload_1
      //   27: invokevirtual 33	kkkkkk/ovooov:bхххх04450445х044504450445	(Lkkkkkk/voovov;)V
      //   30: return
      //   31: astore_1
      //   32: aload_1
      //   33: athrow
      //   34: astore_1
      //   35: aload_1
      //   36: athrow
      //   37: new 35	java/lang/NullPointerException
      //   40: dup
      //   41: invokespecial 36	java/lang/NullPointerException:<init>	()V
      //   44: athrow
      //   45: astore_3
      //   46: goto -9 -> 37
      // Local variable table:
      //   start	length	slot	name	signature
      //   0	49	0	this	dddddx
      //   0	49	1	paramVoovov	voovov
      //   1	5	2	i	int
      //   9	1	3	localException1	Exception
      //   14	12	3	localOvooov	ovooov
      //   45	1	3	localException2	Exception
      // Exception table:
      //   from	to	target	type
      //   37	45	9	java/lang/Exception
      //   10	25	31	java/lang/Exception
      //   25	30	34	java/lang/Exception
      //   2	6	45	java/lang/Exception
    }
  }
  
  private class ddxxxd
    extends vovoov
  {
    public static int b044B044B044B044Bы044B044B044B044B = 1;
    public static int b044Bыыы044B044B044B044B044B = 0;
    public static int bы044B044B044Bы044B044B044B044B = 63;
    public static int bыыыы044B044B044B044B044B = 2;
    private final vovoov b044B044Bы044Bы044B044B044B044B;
    private final Context bы044Bы044Bы044B044B044B044B;
    private final vvvvov bыы044B044Bы044B044B044B044B;
    
    public ddxxxd(Context paramContext, vvvvov paramVvvvov, vovoov paramVovoov)
    {
      this.bы044Bы044Bы044B044B044B044B = paramContext;
      this.bыы044B044Bы044B044B044B044B = paramVvvvov;
      this.b044B044Bы044Bы044B044B044B044B = paramVovoov;
    }
    
    public static int b0445хх04450445хх044504450445()
    {
      return 18;
    }
    
    public static int bххх04450445хх044504450445()
    {
      return 1;
    }
    
    /* Error */
    public void b04450445х04450445хх044504450445()
    {
      // Byte code:
      //   0: invokestatic 48	kkkkkk/xxdxxd:b0445ххх04450445х044504450445	()Ljava/lang/String;
      //   3: ldc 50
      //   5: sipush 224
      //   8: iconst_1
      //   9: iconst_0
      //   10: invokestatic 56	kkkkkk/gguuuu:bк043Aккк043Aкк043A043A	(Ljava/lang/String;CCC)Ljava/lang/String;
      //   13: invokestatic 62	kkkkkk/xtxtxt:bии0438и04380438и0438ии	(Ljava/lang/String;Ljava/lang/String;)V
      //   16: aload_0
      //   17: getfield 28	kkkkkk/xxdxxd$ddxxxd:b044Bы044B044Bы044B044B044B044B	Lkkkkkk/xxdxxd;
      //   20: astore 4
      //   22: getstatic 64	kkkkkk/xxdxxd$ddxxxd:bы044B044B044Bы044B044B044B044B	I
      //   25: istore_1
      //   26: getstatic 64	kkkkkk/xxdxxd$ddxxxd:bы044B044B044Bы044B044B044B044B	I
      //   29: getstatic 66	kkkkkk/xxdxxd$ddxxxd:b044B044B044B044Bы044B044B044B044B	I
      //   32: iadd
      //   33: getstatic 64	kkkkkk/xxdxxd$ddxxxd:bы044B044B044Bы044B044B044B044B	I
      //   36: imul
      //   37: getstatic 68	kkkkkk/xxdxxd$ddxxxd:bыыыы044B044B044B044B044B	I
      //   40: irem
      //   41: getstatic 70	kkkkkk/xxdxxd$ddxxxd:b044Bыыы044B044B044B044B044B	I
      //   44: if_icmpeq +13 -> 57
      //   47: bipush 35
      //   49: putstatic 64	kkkkkk/xxdxxd$ddxxxd:bы044B044B044Bы044B044B044B044B	I
      //   52: bipush 81
      //   54: putstatic 70	kkkkkk/xxdxxd$ddxxxd:b044Bыыы044B044B044B044B044B	I
      //   57: getstatic 66	kkkkkk/xxdxxd$ddxxxd:b044B044B044B044Bы044B044B044B044B	I
      //   60: istore_2
      //   61: getstatic 68	kkkkkk/xxdxxd$ddxxxd:bыыыы044B044B044B044B044B	I
      //   64: istore_3
      //   65: iload_1
      //   66: iload_2
      //   67: iload_1
      //   68: iadd
      //   69: imul
      //   70: iload_3
      //   71: irem
      //   72: tableswitch	default:+20->92, 0:+32->104
      //   92: invokestatic 72	kkkkkk/xxdxxd$ddxxxd:b0445хх04450445хх044504450445	()I
      //   95: putstatic 64	kkkkkk/xxdxxd$ddxxxd:bы044B044B044Bы044B044B044B044B	I
      //   98: invokestatic 72	kkkkkk/xxdxxd$ddxxxd:b0445хх04450445хх044504450445	()I
      //   101: putstatic 66	kkkkkk/xxdxxd$ddxxxd:b044B044B044B044Bы044B044B044B044B	I
      //   104: aload_0
      //   105: getfield 33	kkkkkk/xxdxxd$ddxxxd:bы044Bы044Bы044B044B044B044B	Landroid/content/Context;
      //   108: astore 5
      //   110: aload_0
      //   111: getfield 35	kkkkkk/xxdxxd$ddxxxd:bыы044B044Bы044B044B044B044B	Lkkkkkk/vvvvov;
      //   114: astore 6
      //   116: aload 4
      //   118: aload 5
      //   120: aload 6
      //   122: invokestatic 76	kkkkkk/xxdxxd:bх0445хх04450445х044504450445	(Lkkkkkk/xxdxxd;Landroid/content/Context;Lkkkkkk/vvvvov;)V
      //   125: aload_0
      //   126: getfield 37	kkkkkk/xxdxxd$ddxxxd:b044B044Bы044Bы044B044B044B044B	Lkkkkkk/vovoov;
      //   129: astore 4
      //   131: aload 4
      //   133: invokevirtual 78	kkkkkk/vovoov:b04450445х04450445хх044504450445	()V
      //   136: return
      //   137: astore 4
      //   139: aload 4
      //   141: athrow
      //   142: astore 4
      //   144: aload 4
      //   146: athrow
      //   147: astore 4
      //   149: aload 4
      //   151: athrow
      //   152: astore 4
      //   154: aload 4
      //   156: athrow
      // Local variable table:
      //   start	length	slot	name	signature
      //   0	157	0	this	ddxxxd
      //   25	45	1	i	int
      //   60	9	2	j	int
      //   64	8	3	k	int
      //   20	112	4	localObject	Object
      //   137	3	4	localException1	Exception
      //   142	3	4	localException2	Exception
      //   147	3	4	localException3	Exception
      //   152	3	4	localException4	Exception
      //   108	11	5	localContext	Context
      //   114	7	6	localVvvvov	vvvvov
      // Exception table:
      //   from	to	target	type
      //   0	22	137	java/lang/Exception
      //   116	131	137	java/lang/Exception
      //   22	26	142	java/lang/Exception
      //   57	61	142	java/lang/Exception
      //   92	104	142	java/lang/Exception
      //   139	142	142	java/lang/Exception
      //   149	152	142	java/lang/Exception
      //   104	116	147	java/lang/Exception
      //   131	136	147	java/lang/Exception
      //   61	65	152	java/lang/Exception
    }
    
    public xdxxdx bх0445х04450445хх044504450445()
    {
      switch (1)
      {
      case 0: 
      default: 
        for (;;)
        {
          switch (1)
          {
          }
        }
      }
      int i = bы044B044B044Bы044B044B044B044B;
      switch (i * (b044B044B044B044Bы044B044B044B044B + i) % bыыыы044B044B044B044B044B)
      {
      default: 
        i = bы044B044B044Bы044B044B044B044B;
        switch (i * (bххх04450445хх044504450445() + i) % bыыыы044B044B044B044B044B)
        {
        default: 
          bы044B044B044Bы044B044B044B044B = b0445хх04450445хх044504450445();
          b044B044B044B044Bы044B044B044B044B = 84;
        }
        bы044B044B044Bы044B044B044B044B = 64;
        b044B044B044B044Bы044B044B044B044B = 46;
      }
      return this.b044B044Bы044Bы044B044B044B044B.bх0445х04450445хх044504450445();
    }
  }
  
  private class xdxxxd
    extends vvooov
  {
    public static int b044B044B044Bы044B044B044B044B044B = 0;
    public static int b044Bыы044B044B044B044B044B044B = 2;
    public static int bы044B044Bы044B044B044B044B044B = 60;
    public static int bыыы044B044B044B044B044B044B = 1;
    private final vvvvov b044B044Bыы044B044B044B044B044B;
    private final Context bы044Bыы044B044B044B044B044B;
    private final vvooov bыы044Bы044B044B044B044B044B;
    
    public xdxxxd(Context paramContext, vvvvov paramVvvvov, vvooov paramVvooov)
    {
      this.bы044Bыы044B044B044B044B044B = paramContext;
      this.bыы044Bы044B044B044B044B044B = paramVvooov;
      this.b044B044Bыы044B044B044B044B044B = paramVvvvov;
    }
    
    public static int b044504450445хх0445х044504450445()
    {
      return 0;
    }
    
    public static int b0445х0445хх0445х044504450445()
    {
      return 2;
    }
    
    public static int bх04450445хх0445х044504450445()
    {
      return 1;
    }
    
    public static int bххх0445х0445х044504450445()
    {
      return 91;
    }
    
    public void b04450445х0445х0445х044504450445()
    {
      this.bыы044Bы044B044B044B044B044B.b04450445х0445х0445х044504450445();
      if ((bы044B044Bы044B044B044B044B044B + bыыы044B044B044B044B044B044B) * bы044B044Bы044B044B044B044B044B % b044Bыы044B044B044B044B044B044B != b044B044B044Bы044B044B044B044B044B)
      {
        bы044B044Bы044B044B044B044B044B = 19;
        int i = bы044B044Bы044B044B044B044B044B;
        switch (i * (bыыы044B044B044B044B044B044B + i) % b044Bыы044B044B044B044B044B044B)
        {
        default: 
          bы044B044Bы044B044B044B044B044B = 24;
          b044B044B044Bы044B044B044B044B044B = bххх0445х0445х044504450445();
        }
        b044B044B044Bы044B044B044B044B044B = 1;
      }
      xxdxxd.this.b0445044504450445044504450445х04450445();
    }
    
    /* Error */
    public void b0445х04450445х0445х044504450445(final voovov paramVoovov)
    {
      // Byte code:
      //   0: getstatic 54	kkkkkk/xxdxxd$xdxxxd:bы044B044Bы044B044B044B044B044B	I
      //   3: getstatic 56	kkkkkk/xxdxxd$xdxxxd:bыыы044B044B044B044B044B044B	I
      //   6: iadd
      //   7: getstatic 54	kkkkkk/xxdxxd$xdxxxd:bы044B044Bы044B044B044B044B044B	I
      //   10: imul
      //   11: getstatic 58	kkkkkk/xxdxxd$xdxxxd:b044Bыы044B044B044B044B044B044B	I
      //   14: irem
      //   15: getstatic 60	kkkkkk/xxdxxd$xdxxxd:b044B044B044Bы044B044B044B044B044B	I
      //   18: if_icmpeq +14 -> 32
      //   21: bipush 92
      //   23: putstatic 54	kkkkkk/xxdxxd$xdxxxd:bы044B044Bы044B044B044B044B044B	I
      //   26: invokestatic 62	kkkkkk/xxdxxd$xdxxxd:bххх0445х0445х044504450445	()I
      //   29: putstatic 60	kkkkkk/xxdxxd$xdxxxd:b044B044B044Bы044B044B044B044B044B	I
      //   32: aload_0
      //   33: getfield 41	kkkkkk/xxdxxd$xdxxxd:bыы044Bы044B044B044B044B044B	Lkkkkkk/vvooov;
      //   36: astore 6
      //   38: new 12	kkkkkk/xxdxxd$xdxxxd$2
      //   41: dup
      //   42: aload_0
      //   43: aload_1
      //   44: invokespecial 72	kkkkkk/xxdxxd$xdxxxd$2:<init>	(Lkkkkkk/xxdxxd$xdxxxd;Lkkkkkk/voovov;)V
      //   47: astore_1
      //   48: getstatic 54	kkkkkk/xxdxxd$xdxxxd:bы044B044Bы044B044B044B044B044B	I
      //   51: istore_2
      //   52: getstatic 56	kkkkkk/xxdxxd$xdxxxd:bыыы044B044B044B044B044B044B	I
      //   55: istore_3
      //   56: getstatic 54	kkkkkk/xxdxxd$xdxxxd:bы044B044Bы044B044B044B044B044B	I
      //   59: istore 4
      //   61: getstatic 58	kkkkkk/xxdxxd$xdxxxd:b044Bыы044B044B044B044B044B044B	I
      //   64: istore 5
      //   66: iload_2
      //   67: iload_3
      //   68: iadd
      //   69: iload 4
      //   71: imul
      //   72: iload 5
      //   74: irem
      //   75: getstatic 60	kkkkkk/xxdxxd$xdxxxd:b044B044B044Bы044B044B044B044B044B	I
      //   78: if_icmpeq +14 -> 92
      //   81: bipush 53
      //   83: putstatic 54	kkkkkk/xxdxxd$xdxxxd:bы044B044Bы044B044B044B044B044B	I
      //   86: invokestatic 62	kkkkkk/xxdxxd$xdxxxd:bххх0445х0445х044504450445	()I
      //   89: putstatic 60	kkkkkk/xxdxxd$xdxxxd:b044B044B044Bы044B044B044B044B044B	I
      //   92: aload 6
      //   94: aload_1
      //   95: invokevirtual 74	kkkkkk/vvooov:b0445х04450445х0445х044504450445	(Lkkkkkk/voovov;)V
      //   98: return
      //   99: astore_1
      //   100: aload_1
      //   101: athrow
      //   102: astore_1
      //   103: aload_1
      //   104: athrow
      //   105: astore_1
      //   106: aload_1
      //   107: athrow
      //   108: astore_1
      //   109: aload_1
      //   110: athrow
      // Local variable table:
      //   start	length	slot	name	signature
      //   0	111	0	this	xdxxxd
      //   0	111	1	paramVoovov	voovov
      //   51	18	2	i	int
      //   55	14	3	j	int
      //   59	13	4	k	int
      //   64	11	5	m	int
      //   36	57	6	localVvooov	vvooov
      // Exception table:
      //   from	to	target	type
      //   32	38	99	java/lang/Exception
      //   92	98	99	java/lang/Exception
      //   66	92	102	java/lang/Exception
      //   100	102	102	java/lang/Exception
      //   106	108	102	java/lang/Exception
      //   38	48	105	java/lang/Exception
      //   48	66	108	java/lang/Exception
    }
    
    /* Error */
    public dxxxdx b0445хх0445х0445х044504450445()
    {
      // Byte code:
      //   0: getstatic 54	kkkkkk/xxdxxd$xdxxxd:bы044B044Bы044B044B044B044B044B	I
      //   3: getstatic 56	kkkkkk/xxdxxd$xdxxxd:bыыы044B044B044B044B044B044B	I
      //   6: iadd
      //   7: getstatic 54	kkkkkk/xxdxxd$xdxxxd:bы044B044Bы044B044B044B044B044B	I
      //   10: imul
      //   11: getstatic 58	kkkkkk/xxdxxd$xdxxxd:b044Bыы044B044B044B044B044B044B	I
      //   14: irem
      //   15: getstatic 60	kkkkkk/xxdxxd$xdxxxd:b044B044B044Bы044B044B044B044B044B	I
      //   18: if_icmpeq +45 -> 63
      //   21: bipush 16
      //   23: putstatic 54	kkkkkk/xxdxxd$xdxxxd:bы044B044Bы044B044B044B044B044B	I
      //   26: bipush 39
      //   28: putstatic 60	kkkkkk/xxdxxd$xdxxxd:b044B044B044Bы044B044B044B044B044B	I
      //   31: getstatic 54	kkkkkk/xxdxxd$xdxxxd:bы044B044Bы044B044B044B044B044B	I
      //   34: getstatic 56	kkkkkk/xxdxxd$xdxxxd:bыыы044B044B044B044B044B044B	I
      //   37: iadd
      //   38: getstatic 54	kkkkkk/xxdxxd$xdxxxd:bы044B044Bы044B044B044B044B044B	I
      //   41: imul
      //   42: getstatic 58	kkkkkk/xxdxxd$xdxxxd:b044Bыы044B044B044B044B044B044B	I
      //   45: irem
      //   46: getstatic 60	kkkkkk/xxdxxd$xdxxxd:b044B044B044Bы044B044B044B044B044B	I
      //   49: if_icmpeq +14 -> 63
      //   52: bipush 81
      //   54: putstatic 54	kkkkkk/xxdxxd$xdxxxd:bы044B044Bы044B044B044B044B044B	I
      //   57: invokestatic 62	kkkkkk/xxdxxd$xdxxxd:bххх0445х0445х044504450445	()I
      //   60: putstatic 60	kkkkkk/xxdxxd$xdxxxd:b044B044B044Bы044B044B044B044B044B	I
      //   63: aload_0
      //   64: getfield 41	kkkkkk/xxdxxd$xdxxxd:bыы044Bы044B044B044B044B044B	Lkkkkkk/vvooov;
      //   67: astore_1
      //   68: aload_1
      //   69: invokevirtual 78	kkkkkk/vvooov:b0445хх0445х0445х044504450445	()Lkkkkkk/dxxxdx;
      //   72: astore_1
      //   73: aload_1
      //   74: areturn
      //   75: astore_1
      //   76: aload_1
      //   77: athrow
      //   78: astore_1
      //   79: aload_1
      //   80: athrow
      // Local variable table:
      //   start	length	slot	name	signature
      //   0	81	0	this	xdxxxd
      //   67	7	1	localObject	Object
      //   75	2	1	localException1	Exception
      //   78	2	1	localException2	Exception
      // Exception table:
      //   from	to	target	type
      //   68	73	75	java/lang/Exception
      //   63	68	78	java/lang/Exception
    }
    
    /* Error */
    public void bх0445х0445х0445х044504450445()
    {
      // Byte code:
      //   0: iconst_0
      //   1: tableswitch	default:+23->24, 0:+50->51, 1:+-1->0
      //   24: iconst_0
      //   25: tableswitch	default:+23->48, 0:+26->51, 1:+-25->0
      //   48: goto -24 -> 24
      //   51: getstatic 54	kkkkkk/xxdxxd$xdxxxd:bы044B044Bы044B044B044B044B044B	I
      //   54: istore_1
      //   55: invokestatic 81	kkkkkk/xxdxxd$xdxxxd:bх04450445хх0445х044504450445	()I
      //   58: istore_2
      //   59: getstatic 54	kkkkkk/xxdxxd$xdxxxd:bы044B044Bы044B044B044B044B044B	I
      //   62: istore_3
      //   63: getstatic 58	kkkkkk/xxdxxd$xdxxxd:b044Bыы044B044B044B044B044B044B	I
      //   66: istore 4
      //   68: getstatic 54	kkkkkk/xxdxxd$xdxxxd:bы044B044Bы044B044B044B044B044B	I
      //   71: istore 5
      //   73: iload 5
      //   75: getstatic 56	kkkkkk/xxdxxd$xdxxxd:bыыы044B044B044B044B044B044B	I
      //   78: iload 5
      //   80: iadd
      //   81: imul
      //   82: getstatic 58	kkkkkk/xxdxxd$xdxxxd:b044Bыы044B044B044B044B044B044B	I
      //   85: irem
      //   86: tableswitch	default:+18->104, 0:+29->115
      //   104: bipush 47
      //   106: putstatic 54	kkkkkk/xxdxxd$xdxxxd:bы044B044Bы044B044B044B044B044B	I
      //   109: invokestatic 62	kkkkkk/xxdxxd$xdxxxd:bххх0445х0445х044504450445	()I
      //   112: putstatic 60	kkkkkk/xxdxxd$xdxxxd:b044B044B044Bы044B044B044B044B044B	I
      //   115: iload_1
      //   116: iload_2
      //   117: iadd
      //   118: iload_3
      //   119: imul
      //   120: iload 4
      //   122: irem
      //   123: getstatic 60	kkkkkk/xxdxxd$xdxxxd:b044B044B044Bы044B044B044B044B044B	I
      //   126: if_icmpeq +14 -> 140
      //   129: invokestatic 62	kkkkkk/xxdxxd$xdxxxd:bххх0445х0445х044504450445	()I
      //   132: putstatic 54	kkkkkk/xxdxxd$xdxxxd:bы044B044Bы044B044B044B044B044B	I
      //   135: bipush 96
      //   137: putstatic 60	kkkkkk/xxdxxd$xdxxxd:b044B044B044Bы044B044B044B044B044B	I
      //   140: aload_0
      //   141: getfield 34	kkkkkk/xxdxxd$xdxxxd:b044Bы044Bы044B044B044B044B044B	Lkkkkkk/xxdxxd;
      //   144: aload_0
      //   145: getfield 39	kkkkkk/xxdxxd$xdxxxd:bы044Bыы044B044B044B044B044B	Landroid/content/Context;
      //   148: aload_0
      //   149: getfield 43	kkkkkk/xxdxxd$xdxxxd:b044B044Bыы044B044B044B044B044B	Lkkkkkk/vvvvov;
      //   152: invokestatic 85	kkkkkk/xxdxxd:bх0445хх04450445х044504450445	(Lkkkkkk/xxdxxd;Landroid/content/Context;Lkkkkkk/vvvvov;)V
      //   155: aload_0
      //   156: getfield 41	kkkkkk/xxdxxd$xdxxxd:bыы044Bы044B044B044B044B044B	Lkkkkkk/vvooov;
      //   159: invokevirtual 87	kkkkkk/vvooov:bх0445х0445х0445х044504450445	()V
      //   162: return
      //   163: astore 6
      //   165: aload 6
      //   167: athrow
      //   168: astore 6
      //   170: aload 6
      //   172: athrow
      // Local variable table:
      //   start	length	slot	name	signature
      //   0	173	0	this	xdxxxd
      //   54	64	1	i	int
      //   58	60	2	j	int
      //   62	58	3	k	int
      //   66	57	4	m	int
      //   71	11	5	n	int
      //   163	3	6	localException1	Exception
      //   168	3	6	localException2	Exception
      // Exception table:
      //   from	to	target	type
      //   140	155	163	java/lang/Exception
      //   155	162	168	java/lang/Exception
    }
    
    public void bхх04450445х0445х044504450445(final oovvov paramOovvov)
    {
      switch (0)
      {
      case 1: 
      default: 
        for (;;)
        {
          switch (0)
          {
          }
        }
      }
      vvooov localVvooov = this.bыы044Bы044B044B044B044B044B;
      paramOovvov = new oovvov()
      {
        public static int b044Bы044B044B044B044B044B044B044B = 1;
        public static int bы044B044B044B044B044B044B044B044B = 2;
        public static int bыы044B044B044B044B044B044B044B = 64;
        
        public static int bхх044504450445хх044504450445()
        {
          return 90;
        }
        
        public void b0445х044504450445хх044504450445()
        {
          switch (0)
          {
          case 1: 
          default: 
            for (;;)
            {
              switch (0)
              {
              }
            }
          }
          paramOovvov.b0445х044504450445хх044504450445();
          int i = bыы044B044B044B044B044B044B044B;
          int j = b044Bы044B044B044B044B044B044B044B;
          int k = bы044B044B044B044B044B044B044B044B;
          int m = bыы044B044B044B044B044B044B044B;
          switch (m * (b044Bы044B044B044B044B044B044B044B + m) % bы044B044B044B044B044B044B044B044B)
          {
          default: 
            bыы044B044B044B044B044B044B044B = 68;
            b044Bы044B044B044B044B044B044B044B = bхх044504450445хх044504450445();
          }
          switch (i * (j + i) % k)
          {
          default: 
            bыы044B044B044B044B044B044B044B = bхх044504450445хх044504450445();
            b044Bы044B044B044B044B044B044B044B = 43;
          }
        }
        
        public void bх0445044504450445хх044504450445(Exception paramAnonymousException)
        {
          oovvov localOovvov = paramOovvov;
          switch (0)
          {
          case 1: 
          default: 
            for (;;)
            {
              switch (1)
              {
              }
            }
          }
          switch (1)
          {
          case 0: 
          default: 
            for (;;)
            {
              switch (0)
              {
              }
            }
          }
          int i = bыы044B044B044B044B044B044B044B;
          switch (i * (b044Bы044B044B044B044B044B044B044B + i) % bы044B044B044B044B044B044B044B044B)
          {
          default: 
            bыы044B044B044B044B044B044B044B = bхх044504450445хх044504450445();
            b044Bы044B044B044B044B044B044B044B = bхх044504450445хх044504450445();
          }
          localOovvov.bх0445044504450445хх044504450445(paramAnonymousException);
          i = bыы044B044B044B044B044B044B044B;
          switch (i * (b044Bы044B044B044B044B044B044B044B + i) % bы044B044B044B044B044B044B044B044B)
          {
          default: 
            bыы044B044B044B044B044B044B044B = 87;
            b044Bы044B044B044B044B044B044B044B = bхх044504450445хх044504450445();
          }
        }
      };
      if ((bы044B044Bы044B044B044B044B044B + bыыы044B044B044B044B044B044B) * bы044B044Bы044B044B044B044B044B % b0445х0445хх0445х044504450445() != b044B044B044Bы044B044B044B044B044B)
      {
        bы044B044Bы044B044B044B044B044B = 4;
        b044B044B044Bы044B044B044B044B044B = bххх0445х0445х044504450445();
      }
      localVvooov.bхх04450445х0445х044504450445(paramOovvov);
    }
  }
}
