package kkkkkk;

public abstract class xxxdxx
{
  public static int b042A042AЪЪЪ042A042AЪЪ = 0;
  public static int b042AЪ042AЪЪ042A042AЪЪ = 2;
  public static int bЪ042A042AЪЪ042A042AЪЪ = 82;
  public static int bЪЪ042AЪЪ042A042AЪЪ = 1;
  private final dddxxx bЪ042AЪЪЪ042A042AЪЪ = new dddxxx(txtttt.b04380438и0438и04380438иии().bи0438и0438и04380438иии());
  
  public xxxdxx(String paramString)
  {
    this.bЪ042AЪЪЪ042A042AЪЪ.bииии04380438ииии(paramString);
  }
  
  public static int bи0438и0438и0438ииии()
  {
    return 6;
  }
  
  /* Error */
  public dddxxx b04380438и0438и0438ииии()
  {
    // Byte code:
    //   0: getstatic 49	kkkkkk/xxxdxx:bЪ042A042AЪЪ042A042AЪЪ	I
    //   3: istore_1
    //   4: iload_1
    //   5: getstatic 51	kkkkkk/xxxdxx:bЪЪ042AЪЪ042A042AЪЪ	I
    //   8: iload_1
    //   9: iadd
    //   10: imul
    //   11: getstatic 53	kkkkkk/xxxdxx:b042AЪ042AЪЪ042A042AЪЪ	I
    //   14: irem
    //   15: tableswitch	default:+17->32, 0:+29->44
    //   32: invokestatic 55	kkkkkk/xxxdxx:bи0438и0438и0438ииии	()I
    //   35: putstatic 49	kkkkkk/xxxdxx:bЪ042A042AЪЪ042A042AЪЪ	I
    //   38: invokestatic 55	kkkkkk/xxxdxx:bи0438и0438и0438ииии	()I
    //   41: putstatic 57	kkkkkk/xxxdxx:b042A042AЪЪЪ042A042AЪЪ	I
    //   44: aload_0
    //   45: getfield 37	kkkkkk/xxxdxx:bЪ042AЪЪЪ042A042AЪЪ	Lkkkkkk/dddxxx;
    //   48: astore 6
    //   50: invokestatic 55	kkkkkk/xxxdxx:bи0438и0438и0438ииии	()I
    //   53: istore_1
    //   54: getstatic 51	kkkkkk/xxxdxx:bЪЪ042AЪЪ042A042AЪЪ	I
    //   57: istore_2
    //   58: invokestatic 55	kkkkkk/xxxdxx:bи0438и0438и0438ииии	()I
    //   61: istore_3
    //   62: getstatic 53	kkkkkk/xxxdxx:b042AЪ042AЪЪ042A042AЪЪ	I
    //   65: istore 4
    //   67: getstatic 57	kkkkkk/xxxdxx:b042A042AЪЪЪ042A042AЪЪ	I
    //   70: istore 5
    //   72: iload_1
    //   73: iload_2
    //   74: iadd
    //   75: iload_3
    //   76: imul
    //   77: iload 4
    //   79: irem
    //   80: iload 5
    //   82: if_icmpeq +27 -> 109
    //   85: invokestatic 55	kkkkkk/xxxdxx:bи0438и0438и0438ииии	()I
    //   88: putstatic 57	kkkkkk/xxxdxx:b042A042AЪЪЪ042A042AЪЪ	I
    //   91: aload 6
    //   93: areturn
    //   94: astore 6
    //   96: aload 6
    //   98: athrow
    //   99: astore 6
    //   101: aload 6
    //   103: athrow
    //   104: astore 6
    //   106: aload 6
    //   108: athrow
    //   109: aload 6
    //   111: areturn
    // Local variable table:
    //   start	length	slot	name	signature
    //   0	112	0	this	xxxdxx
    //   3	72	1	i	int
    //   57	18	2	j	int
    //   61	16	3	k	int
    //   65	15	4	m	int
    //   70	13	5	n	int
    //   48	44	6	localDddxxx	dddxxx
    //   94	3	6	localException1	Exception
    //   99	3	6	localException2	Exception
    //   104	6	6	localException3	Exception
    // Exception table:
    //   from	to	target	type
    //   44	50	94	java/lang/Exception
    //   85	91	99	java/lang/Exception
    //   96	99	99	java/lang/Exception
    //   50	72	104	java/lang/Exception
  }
}
