package kkkkkk;

public enum xxxxdd
{
  /* Error */
  static
  {
    // Byte code:
    //   0: new 2	kkkkkk/xxxxdd
    //   3: dup
    //   4: ldc 15
    //   6: bipush 116
    //   8: iconst_1
    //   9: invokestatic 21	kkkkkk/gguuuu:bккккк043Aкк043A043A	(Ljava/lang/String;CC)Ljava/lang/String;
    //   12: iconst_0
    //   13: invokespecial 25	kkkkkk/xxxxdd:<init>	(Ljava/lang/String;I)V
    //   16: putstatic 27	kkkkkk/xxxxdd:PHOTO_SHARING	Lkkkkkk/xxxxdd;
    //   19: getstatic 27	kkkkkk/xxxxdd:PHOTO_SHARING	Lkkkkkk/xxxxdd;
    //   22: astore 5
    //   24: iconst_1
    //   25: anewarray 2	kkkkkk/xxxxdd
    //   28: dup
    //   29: iconst_0
    //   30: aload 5
    //   32: aastore
    //   33: putstatic 29	kkkkkk/xxxxdd:$VALUES	[Lkkkkkk/xxxxdd;
    //   36: invokestatic 33	kkkkkk/xxxxdd:b04450445хх044504450445х04450445	()I
    //   39: istore_0
    //   40: invokestatic 36	kkkkkk/xxxxdd:bхх0445х044504450445х04450445	()I
    //   43: istore_1
    //   44: invokestatic 33	kkkkkk/xxxxdd:b04450445хх044504450445х04450445	()I
    //   47: istore_2
    //   48: invokestatic 39	kkkkkk/xxxxdd:b0445х0445х044504450445х04450445	()I
    //   51: istore_3
    //   52: invokestatic 42	kkkkkk/xxxxdd:bх04450445х044504450445х04450445	()I
    //   55: istore 4
    //   57: iload_0
    //   58: iload_1
    //   59: iadd
    //   60: iload_2
    //   61: imul
    //   62: iload_3
    //   63: irem
    //   64: iload 4
    //   66: if_icmpeq +3 -> 69
    //   69: return
    //   70: astore 5
    //   72: aload 5
    //   74: athrow
    //   75: astore 5
    //   77: aload 5
    //   79: athrow
    // Local variable table:
    //   start	length	slot	name	signature
    //   39	21	0	i	int
    //   43	17	1	j	int
    //   47	15	2	k	int
    //   51	13	3	m	int
    //   55	12	4	n	int
    //   22	9	5	localXxxxdd	xxxxdd
    //   70	3	5	localException1	Exception
    //   75	3	5	localException2	Exception
    // Exception table:
    //   from	to	target	type
    //   0	24	70	java/lang/Exception
    //   24	57	75	java/lang/Exception
  }
  
  private xxxxdd() {}
  
  public static xxxxdd b044504450445х044504450445х04450445(String paramString)
  {
    if ((b04450445хх044504450445х04450445() + bхх0445х044504450445х04450445()) * b04450445хх044504450445х04450445() % b0445х0445х044504450445х04450445() != bх04450445х044504450445х04450445()) {}
    try
    {
      paramString = (xxxxdd)Enum.valueOf(xxxxdd.class, paramString);
      int i = b04450445хх044504450445х04450445();
      switch (i * (bхх0445х044504450445х04450445() + i) % b0445х0445х044504450445х04450445())
      {
      }
      return paramString;
    }
    catch (Exception paramString)
    {
      switch (1)
      {
      case 0: 
      default: 
        for (;;)
        {
          switch (0)
          {
          }
        }
      }
      throw paramString;
    }
  }
  
  public static int b04450445хх044504450445х04450445()
  {
    return 41;
  }
  
  public static int b0445х0445х044504450445х04450445()
  {
    return 2;
  }
  
  public static int bх04450445х044504450445х04450445()
  {
    return 0;
  }
  
  public static int bхх0445х044504450445х04450445()
  {
    return 1;
  }
}
