package kkkkkk;

import android.content.Context;
import android.content.Intent;
import android.content.res.Resources;
import android.net.Uri;
import android.os.Bundle;
import android.os.Handler;
import android.os.Looper;
import android.os.Message;
import android.support.annotation.NonNull;
import android.support.v4.util.LongSparseArray;
import android.text.TextUtils;
import android.util.SparseArray;
import com.liveperson.infra.messaging.R.integer;
import com.liveperson.messaging.background.BackgroundActionsService.kyyyky;
import com.liveperson.messaging.background.BackgroundActionsService.ykyyky;
import java.io.File;
import java.util.ArrayList;
import java.util.Iterator;
import java.util.List;
import java.util.concurrent.CopyOnWriteArrayList;

public class ykykyy
  extends hhhbhb
  implements BackgroundActionsService.kyyyky
{
  private static final String b044C044C044C044C044C044C044Cь044C = "VhXbiu`\\";
  public static final String b044C044C044C044Cььь044C044C = "\033\f\030\033\r\006\007\005\027\022\017|y\007}\013\nv{xq\004\007mvp";
  private static final int b044C044C044Cь044Cьь044C044C = 4;
  public static int b044C044C044Cьь044Cь044C044C = 25;
  private static final String b044C044C044Cьььь044C044C = "uiqg{qo[m\002v";
  public static final String b044C044Cь044Cььь044C044C = "UHV[OJMHOc`_ONY^SZYTYXhmcjj";
  private static final String b044C044Cьь044Cьь044C044C = "1\035-!\036,\032";
  private static final String b044C044Cььььь044C044C = "\006\004{_}\t\013";
  private static final String b044Cь044C044C044C044C044Cь044C = "\013\032\b\024\tl\007";
  public static final String b044Cь044C044Cььь044C044C = "TGUZNILGNb_^NMX]RYXSjh`";
  private static final int b044Cь044Cь044Cьь044C044C = 2;
  private static final String b044Cь044Cьььь044C044C = "jlb_`dV`r^`SPZla]ShXHZM";
  private static final int b044Cьь044C044Cьь044C044C = 1;
  public static int b044Cьь044Cь044Cь044C044C = 1;
  public static final String b044Cьь044Cььь044C044C = "\001s\002\007zuxsz\017\f\013zy\001\023\003\r\024\013\007";
  public static final String b044Cььь044Cьь044C044C = "_P\\_QJKDI[VSA>R>NB?M7@:";
  private static final String b044Cьььььь044C044C = "EJ?FE'TRQ(GTM[K";
  private static final String bь044C044C044C044C044C044Cь044C = "\002~\r\020\004\t\007";
  public static final String bь044C044C044Cььь044C044C = "F7CF812+0B=:(%2)65\"'$";
  private static final int bь044C044Cь044Cьь044C044C = 3;
  private static final String bь044C044Cьььь044C044C = "\n\016\006\005\b\016\002\016\"\021\n\031\032\t\020\017* \026\033\024";
  private static int bь044Cь044C044Cьь044C044C = 0;
  public static int bь044Cь044Cь044Cь044C044C = 2;
  public static final String bь044Cь044Cььь044C044C = "NAOTHCFAH\\YXHGOSWQL`^gP[W";
  private static final String bь044Cьь044Cьь044C044C;
  private static final String bь044Cььььь044C044C = "ljb";
  public static final String bьь044C044Cььь044C044C = ")\034*/#\036!\034#743#\"-2'.-(0=;:-21>7E5";
  private static final String bьь044Cь044Cьь044C044C = "%\030$\033\017\032\f\023\025'\023\025\b\005\017!\026\022\b\035\r|\017\002";
  private static final String bьь044Cьььь044C044C = "\003y\007\006rwt`|\004Tn";
  private static final int bььь044C044Cьь044C044C = 5;
  public static int bььь044Cь044Cь044C044C = 0;
  public static final String bььь044Cььь044C044C = "6'36(!\"\033 2-*\030\025\027&\024 \025\017\030\022";
  public static final String bьььь044Cьь044C044C = "\025)&%\025\024%)! #)\035)\035,%45$+*%;16/";
  private static final String bььььььь044C044C = "CGKE3QZ-I";
  private final SparseArray<ykykyy.yjjyyy> b044C044C044C044C044Cьь044C044C = new SparseArray();
  private List<String> b044C044Cь044C044Cьь044C044C;
  private final CopyOnWriteArrayList<jyyjyy> b044C044Cььь044Cь044C044C = new CopyOnWriteArrayList();
  private final kkyykk b044Cь044C044C044Cьь044C044C;
  private String b044Cь044Cьь044Cь044C044C;
  private final int b044Cьььь044Cь044C044C;
  private final LongSparseArray<ykykyy.jyjyyy> bь044C044C044C044Cьь044C044C = new LongSparseArray();
  private final int bь044C044Cьь044Cь044C044C;
  private final CopyOnWriteArrayList<yyyyky> bь044Cььь044Cь044C044C = new CopyOnWriteArrayList();
  private final Context bьь044C044C044Cьь044C044C;
  private uoouoo bьь044Cьь044Cь044C044C = new uoouoo();
  private dddxdx bььььь044Cь044C044C = null;
  
  static
  {
    throw new Runtime("d2j fail translate: java.lang.IndexOutOfBoundsException: fromIndex < 0: -1\n\tat java.util.BitSet.nextSetBit(BitSet.java:712)\n\tat com.googlecode.dex2jar.ir.ts.array.FillArrayTransformer.makeSureAllElementAreAssigned(FillArrayTransformer.java:505)\n\tat com.googlecode.dex2jar.ir.ts.array.FillArrayTransformer.transformReportChanged(FillArrayTransformer.java:123)\n\tat com.googlecode.dex2jar.ir.ts.StatedTransformer.transform(StatedTransformer.java:10)\n\tat com.googlecode.d2j.dex.Dex2jar$2.optimize(Dex2jar.java:149)\n\tat com.googlecode.d2j.dex.Dex2Asm.convertCode(Dex2Asm.java:414)\n\tat com.googlecode.d2j.dex.ExDex2Asm.convertCode(ExDex2Asm.java:42)\n\tat com.googlecode.d2j.dex.Dex2jar$2.convertCode(Dex2jar.java:128)\n\tat com.googlecode.d2j.dex.Dex2Asm.convertMethod(Dex2Asm.java:509)\n\tat com.googlecode.d2j.dex.Dex2Asm.convertClass(Dex2Asm.java:406)\n\tat com.googlecode.d2j.dex.Dex2Asm.convertDex(Dex2Asm.java:422)\n\tat com.googlecode.d2j.dex.Dex2jar.doTranslate(Dex2jar.java:172)\n\tat com.googlecode.d2j.dex.Dex2jar.to(Dex2jar.java:272)\n\tat com.googlecode.dex2jar.tools.Dex2jarCmd.doCommandLine(Dex2jarCmd.java:108)\n\tat com.googlecode.dex2jar.tools.BaseCmd.doMain(BaseCmd.java:288)\n\tat com.googlecode.dex2jar.tools.Dex2jarCmd.main(Dex2jarCmd.java:32)\n");
  }
  
  public ykykyy(kkyykk paramKkyykk, Context paramContext)
  {
    super(bь044Cьь044Cьь044C044C);
    this.bьь044C044C044Cьь044C044C = paramContext;
    this.b044Cь044C044C044Cьь044C044C = paramKkyykk;
    this.bь044C044Cьь044Cь044C044C = xxdxxd.instance.bххх044504450445х044504450445().getResources().getInteger(R.integer.image_upload_timeout_ms);
    this.b044Cьььь044Cь044C044C = xxdxxd.instance.bххх044504450445х044504450445().getResources().getInteger(R.integer.max_number_stored_images);
    bШ042804280428Ш0428Ш04280428Ш(new ykykyy.1(this));
  }
  
  private void b042804280428042804280428Ш042804280428()
  {
    Iterator localIterator = this.b044C044Cььь044Cь044C044C.iterator();
    while (localIterator.hasNext())
    {
      jyyjyy localJyyjyy = (jyyjyy)localIterator.next();
      int i = b044C044C044Cьь044Cь044C044C;
      int j = b044C044C044Cьь044Cь044C044C;
      switch (j * (b044Cьь044Cь044Cь044C044C + j) % bь044Cь044Cь044Cь044C044C)
      {
      default: 
        b044C044C044Cьь044Cь044C044C = 38;
        bььь044Cь044Cь044C044C = b042804280428ШШ0428Ш042804280428();
      }
      if ((i + b044Cьь044Cь044Cь044C044C) * b044C044C044Cьь044Cь044C044C % bь044Cь044Cь044Cь044C044C != bььь044Cь044Cь044C044C)
      {
        b044C044C044Cьь044Cь044C044C = 19;
        bььь044Cь044Cь044C044C = b042804280428ШШ0428Ш042804280428();
      }
      localJyyjyy.bШ0428Ш0428042804280428042804280428();
    }
    localIterator = this.bь044Cььь044Cь044C044C.iterator();
    while (localIterator.hasNext()) {
      ((yyyyky)localIterator.next()).bШ042804280428ШШ0428Ш04280428();
    }
  }
  
  @NonNull
  private jyyjyy b0428042804280428Ш0428Ш042804280428(jyjjyy paramJyjjyy)
    throws fefefe
  {
    if ((b044C044C044Cьь044Cь044C044C + b044Cьь044Cь044Cь044C044C) * b044C044C044Cьь044Cь044C044C % bь044Cь044Cь044Cь044C044C != bььь044Cь044Cь044C044C)
    {
      b044C044C044Cьь044Cь044C044C = 16;
      bььь044Cь044Cь044C044C = b042804280428ШШ0428Ш042804280428();
    }
    return new jyyjyy(paramJyjjyy);
  }
  
  public static int b042804280428ШШ0428Ш042804280428()
  {
    return 66;
  }
  
  private void b04280428Ш042804280428Ш042804280428(Message paramMessage)
  {
    Bundle localBundle = paramMessage.getData();
    if ((b044C044C044Cьь044Cь044C044C + b044Cьь044Cь044Cь044C044C) * b044C044C044Cьь044Cь044C044C % bь044Cь044Cь044Cь044C044C != bььь044Cь044Cь044C044C)
    {
      b044C044C044Cьь044Cь044C044C = 56;
      bььь044Cь044Cь044C044C = b042804280428ШШ0428Ш042804280428();
    }
    String str1 = localBundle.getString(gguuuu.bккккк043Aкк043A043A("t\004q}rVp", 'õ', '\003'));
    Object localObject = localBundle.getString(gguuuu.bккккк043Aкк043A043A("~jznkyMg", 'ô', '\005'));
    Uri localUri = Uri.parse(localBundle.getString(gguuuu.bккккк043Aкк043A043A("ljb", 'v', '\000')));
    String str2 = localBundle.getString(gguuuu.bккккк043Aкк043A043A("\r\n\030\033\017\024\022", 'G', '\002'));
    boolean bool = localBundle.getBoolean(gguuuu.bккккк043Aкк043A043A(" %\032! \002/-,\003\"/(6&", '6', '\000'), false);
    xtxtxt.bии0438и04380438и0438ии(bь044Cьь044Cьь044C044C, gguuuu.bккккк043Aкк043A043A("=K=8J:\"8I&@;=.0\0247*/,\032&7.{`$ 2\036i\"\037-\013+(\036\"\032Yy|otq\013{qPFbD", '', '\003') + localBundle.getString(gguuuu.bккккк043Aкк043A043A("A?7", '\031', '\001')));
    b0428ШШШШШ0428042804280428(str1);
    int i = paramMessage.arg2;
    switch (1)
    {
    case 0: 
    default: 
      for (;;)
      {
        switch (0)
        {
        }
      }
    }
    paramMessage = new jyjjyy();
    paramMessage.b0424ФФ0424ФФФФФФ(this.b044Cь044C044C044Cьь044C044C.b0428Ш04280428Ш04280428ШШ0428(str1, str2)).bФ04240424ФФФФФФФ(str1).bФФ04240424ФФФФФФ((String)localObject).bФФФ0424ФФФФФФ(localUri).b04240424Ф0424ФФФФФФ(this.b044Cь044Cьь044Cь044C044C).bФ0424Ф0424ФФФФФФ(this.bьь044Cьь044Cь044C044C).b042404240424ФФФФФФФ(bool).b042804280428Ш0428Ш0428042804280428(i, this.bьь044C044C044Cьь044C044C);
    xtxtxt.bии0438и04380438и0438ии(bь044Cьь044Cьь044C044C, i + gguuuu.bк043Aккк043Aкк043A043A("|c(8,)=/\0311D#?<@37\035B7>=-;NG\027}4PMQDH.SHON>L_X0d^U^X\024^cX_^Ntlb8\037", '\025', '-', '\003') + paramMessage.bФ0424ФФ0424ФФФФФ() + gguuuu.bккккк043Aкк043A043A("2%i{vfnrglj5\032", 'y', '\005') + paramMessage.bФФ0424Ф0424ФФФФФ());
    bШШ0428042804280428Ш042804280428();
    try
    {
      localObject = b0428042804280428Ш0428Ш042804280428(paramMessage);
      int j = b044C044C044Cьь044Cь044C044C;
      switch (j * (b0428Ш0428ШШ0428Ш042804280428() + j) % bь044Cь044Cь044Cь044C044C)
      {
      default: 
        b044C044C044Cьь044Cь044C044C = 86;
        bььь044Cь044Cь044C044C = b042804280428ШШ0428Ш042804280428();
      }
      b0428Ш04280428Ш0428Ш042804280428((jyyjyy)localObject, str1, i, paramMessage);
      return;
    }
    catch (fefefe paramMessage)
    {
      xtxtxt.bи04380438и04380438и0438ии(bь044Cьь044Cьь044C044C, paramMessage);
      ((ykykyy.yjjyyy)this.b044C044C044C044C044Cьь044C044C.get(i)).bШШШ04280428Ш04280428Ш0428(paramMessage);
      this.b044C044C044C044C044Cьь044C044C.remove(i);
      bШШШ0428Ш0428Ш042804280428();
    }
  }
  
  private void b04280428Ш0428Ш0428Ш042804280428(String paramString1, String paramString2, String paramString3, long paramLong1, long paramLong2, long paramLong3)
  {
    xtxtxt.bии0438и04380438и0438ии(bь044Cьь044Cьь044C044C, gguuuu.bккккк043Aкк043A043A("CQC>P@(>O\033ELB?A24\030;.30\036*;2d6(.\"4(4\"\f\034.!WsU", '', '\005') + paramString3);
    yykkyy localYykkyy = new yykkyy();
    localYykkyy.bШШШ04280428Ш0428Ш04280428(paramString3).b0428Ш0428Ш0428Ш0428Ш04280428(paramString1).b042804280428Ш0428Ш0428Ш04280428(paramLong1).bШ04280428Ш0428Ш0428Ш04280428(paramLong2).b04280428Ш04280428Ш0428Ш04280428(paramString2).bШ0428Ш04280428Ш0428Ш04280428(this.b044Cь044Cьь044Cь044C044C).b0428ШШ04280428Ш0428Ш04280428(this.bьь044Cьь044Cь044C044C).b04280428042804280428Ш0428Ш04280428(paramLong3, this.bьь044C044C044Cьь044C044C);
    paramString2 = bШ0428Ш0428Ш0428Ш042804280428(localYykkyy);
    paramString3 = new ykykyy.5(this, paramString1, paramString2, paramLong3);
    int i = b044C044C044Cьь044Cь044C044C;
    switch (i * (b044Cьь044Cь044Cь044C044C + i) % bь044Cь044Cь044Cь044C044C)
    {
    default: 
      b044C044C044Cьь044Cь044C044C = 40;
      bььь044Cь044Cь044C044C = b042804280428ШШ0428Ш042804280428();
    }
    paramString2.bШ0428ШШ0428Ш0428Ш04280428(paramString3);
    this.bь044Cььь044Cь044C044C.add(paramString2);
    b0428Ш0428ШШШ0428042804280428(paramString1);
  }
  
  /* Error */
  private boolean b04280428ШШ04280428Ш042804280428()
  {
    // Byte code:
    //   0: iconst_0
    //   1: istore_2
    //   2: aload_0
    //   3: getfield 164	kkkkkk/ykykyy:b044C044Cььь044Cь044C044C	Ljava/util/concurrent/CopyOnWriteArrayList;
    //   6: invokevirtual 483	java/util/concurrent/CopyOnWriteArrayList:size	()I
    //   9: istore_1
    //   10: iload_1
    //   11: ifgt +107 -> 118
    //   14: aload_0
    //   15: getfield 166	kkkkkk/ykykyy:bь044Cььь044Cь044C044C	Ljava/util/concurrent/CopyOnWriteArrayList;
    //   18: astore_3
    //   19: invokestatic 240	kkkkkk/ykykyy:b042804280428ШШ0428Ш042804280428	()I
    //   22: istore_1
    //   23: iload_1
    //   24: getstatic 234	kkkkkk/ykykyy:b044Cьь044Cь044Cь044C044C	I
    //   27: iload_1
    //   28: iadd
    //   29: imul
    //   30: getstatic 236	kkkkkk/ykykyy:bь044Cь044Cь044Cь044C044C	I
    //   33: irem
    //   34: tableswitch	default:+18->52, 0:+75->109
    //   52: bipush 87
    //   54: putstatic 232	kkkkkk/ykykyy:b044C044C044Cьь044Cь044C044C	I
    //   57: getstatic 232	kkkkkk/ykykyy:b044C044C044Cьь044Cь044C044C	I
    //   60: istore_1
    //   61: iload_1
    //   62: getstatic 234	kkkkkk/ykykyy:b044Cьь044Cь044Cь044C044C	I
    //   65: iload_1
    //   66: iadd
    //   67: imul
    //   68: getstatic 236	kkkkkk/ykykyy:bь044Cь044Cь044Cь044C044C	I
    //   71: irem
    //   72: tableswitch	default:+20->92, 0:+31->103
    //   92: bipush 78
    //   94: putstatic 232	kkkkkk/ykykyy:b044C044C044Cьь044Cь044C044C	I
    //   97: invokestatic 240	kkkkkk/ykykyy:b042804280428ШШ0428Ш042804280428	()I
    //   100: putstatic 242	kkkkkk/ykykyy:bььь044Cь044Cь044C044C	I
    //   103: invokestatic 240	kkkkkk/ykykyy:b042804280428ШШ0428Ш042804280428	()I
    //   106: putstatic 242	kkkkkk/ykykyy:bььь044Cь044Cь044C044C	I
    //   109: aload_3
    //   110: invokevirtual 483	java/util/concurrent/CopyOnWriteArrayList:size	()I
    //   113: istore_1
    //   114: iload_1
    //   115: ifle +5 -> 120
    //   118: iconst_1
    //   119: istore_2
    //   120: iload_2
    //   121: ireturn
    //   122: astore_3
    //   123: aload_3
    //   124: athrow
    //   125: astore_3
    //   126: iconst_0
    //   127: tableswitch	default:+21->148, 0:+48->175, 1:+-1->126
    //   148: iconst_0
    //   149: tableswitch	default:+23->172, 0:+26->175, 1:+-23->126
    //   172: goto -24 -> 148
    //   175: aload_3
    //   176: athrow
    // Local variable table:
    //   start	length	slot	name	signature
    //   0	177	0	this	ykykyy
    //   9	106	1	i	int
    //   1	120	2	bool	boolean
    //   18	92	3	localCopyOnWriteArrayList	CopyOnWriteArrayList
    //   122	2	3	localException1	Exception
    //   125	51	3	localException2	Exception
    // Exception table:
    //   from	to	target	type
    //   2	10	122	java/lang/Exception
    //   109	114	122	java/lang/Exception
    //   14	19	125	java/lang/Exception
  }
  
  private void b0428Ш0428042804280428Ш042804280428(int paramInt)
  {
    Handler localHandler = new Handler(Looper.getMainLooper());
    ykykyy.11 local11 = new ykykyy.11(this, paramInt);
    if ((b042804280428ШШ0428Ш042804280428() + b044Cьь044Cь044Cь044C044C) * b042804280428ШШ0428Ш042804280428() % bь044Cь044Cь044Cь044C044C != bШШ0428ШШ0428Ш042804280428())
    {
      b044C044C044Cьь044Cь044C044C = 92;
      bььь044Cь044Cь044C044C = b042804280428ШШ0428Ш042804280428();
    }
    switch (1)
    {
    case 0: 
    default: 
      for (;;)
      {
        switch (0)
        {
        }
      }
    }
    if ((b042804280428ШШ0428Ш042804280428() + b044Cьь044Cь044Cь044C044C) * b042804280428ШШ0428Ш042804280428() % bь044Cь044Cь044Cь044C044C != bььь044Cь044Cь044C044C)
    {
      b044C044C044Cьь044Cь044C044C = b042804280428ШШ0428Ш042804280428();
      bььь044Cь044Cь044C044C = b042804280428ШШ0428Ш042804280428();
    }
    localHandler.post(local11);
  }
  
  /* Error */
  private void b0428Ш04280428Ш0428Ш042804280428(jyyjyy paramJyyjyy, String paramString, int paramInt, jyjjyy paramJyjjyy)
  {
    // Byte code:
    //   0: getstatic 140	kkkkkk/ykykyy:bь044Cьь044Cьь044C044C	Ljava/lang/String;
    //   3: astore 6
    //   5: new 308	java/lang/StringBuilder
    //   8: dup
    //   9: invokespecial 309	java/lang/StringBuilder:<init>	()V
    //   12: astore 7
    //   14: ldc_w 520
    //   17: sipush 243
    //   20: iconst_3
    //   21: invokestatic 284	kkkkkk/gguuuu:bккккк043Aкк043A043A	(Ljava/lang/String;CC)Ljava/lang/String;
    //   24: astore 8
    //   26: getstatic 232	kkkkkk/ykykyy:b044C044C044Cьь044Cь044C044C	I
    //   29: getstatic 234	kkkkkk/ykykyy:b044Cьь044Cь044Cь044C044C	I
    //   32: iadd
    //   33: getstatic 232	kkkkkk/ykykyy:b044C044C044Cьь044Cь044C044C	I
    //   36: imul
    //   37: getstatic 236	kkkkkk/ykykyy:bь044Cь044Cь044Cь044C044C	I
    //   40: irem
    //   41: getstatic 242	kkkkkk/ykykyy:bььь044Cь044Cь044C044C	I
    //   44: if_icmpeq +14 -> 58
    //   47: invokestatic 240	kkkkkk/ykykyy:b042804280428ШШ0428Ш042804280428	()I
    //   50: putstatic 232	kkkkkk/ykykyy:b044C044C044Cьь044Cь044C044C	I
    //   53: bipush 29
    //   55: putstatic 242	kkkkkk/ykykyy:bььь044Cь044Cь044C044C	I
    //   58: aload 7
    //   60: aload 8
    //   62: invokevirtual 315	java/lang/StringBuilder:append	(Ljava/lang/String;)Ljava/lang/StringBuilder;
    //   65: astore 7
    //   67: getstatic 232	kkkkkk/ykykyy:b044C044C044Cьь044Cь044C044C	I
    //   70: istore 5
    //   72: iload 5
    //   74: getstatic 234	kkkkkk/ykykyy:b044Cьь044Cь044Cь044C044C	I
    //   77: iload 5
    //   79: iadd
    //   80: imul
    //   81: getstatic 236	kkkkkk/ykykyy:bь044Cь044Cь044Cь044C044C	I
    //   84: irem
    //   85: tableswitch	default:+19->104, 0:+30->115
    //   104: bipush 43
    //   106: putstatic 232	kkkkkk/ykykyy:b044C044C044Cьь044Cь044C044C	I
    //   109: invokestatic 240	kkkkkk/ykykyy:b042804280428ШШ0428Ш042804280428	()I
    //   112: putstatic 242	kkkkkk/ykykyy:bььь044Cь044Cь044C044C	I
    //   115: aload 6
    //   117: aload 7
    //   119: aload 4
    //   121: invokevirtual 523	java/lang/StringBuilder:append	(Ljava/lang/Object;)Ljava/lang/StringBuilder;
    //   124: invokevirtual 321	java/lang/StringBuilder:toString	()Ljava/lang/String;
    //   127: invokestatic 327	kkkkkk/xtxtxt:bии0438и04380438и0438ии	(Ljava/lang/String;Ljava/lang/String;)V
    //   130: new 525	kkkkkk/ykykyy$4
    //   133: dup
    //   134: aload_0
    //   135: aload_2
    //   136: iload_3
    //   137: invokespecial 528	kkkkkk/ykykyy$4:<init>	(Lkkkkkk/ykykyy;Ljava/lang/String;I)V
    //   140: astore_2
    //   141: aload_1
    //   142: aload_2
    //   143: invokevirtual 532	kkkkkk/jyyjyy:b0424ФФФФФФФФФ	(Lkkkkkk/yjjjyy;)V
    //   146: aload_0
    //   147: getfield 164	kkkkkk/ykykyy:b044C044Cььь044Cь044C044C	Ljava/util/concurrent/CopyOnWriteArrayList;
    //   150: aload_1
    //   151: invokevirtual 476	java/util/concurrent/CopyOnWriteArrayList:add	(Ljava/lang/Object;)Z
    //   154: pop
    //   155: aload_1
    //   156: invokevirtual 535	kkkkkk/jyyjyy:bФФ0424ФФФФФФФ	()V
    //   159: return
    //   160: astore_1
    //   161: aload_1
    //   162: athrow
    //   163: astore_1
    //   164: aload_1
    //   165: athrow
    // Local variable table:
    //   start	length	slot	name	signature
    //   0	166	0	this	ykykyy
    //   0	166	1	paramJyyjyy	jyyjyy
    //   0	166	2	paramString	String
    //   0	166	3	paramInt	int
    //   0	166	4	paramJyjjyy	jyjjyy
    //   70	11	5	i	int
    //   3	113	6	str1	String
    //   12	106	7	localStringBuilder	StringBuilder
    //   24	37	8	str2	String
    // Exception table:
    //   from	to	target	type
    //   0	26	160	java/lang/Exception
    //   58	67	160	java/lang/Exception
    //   141	159	160	java/lang/Exception
    //   115	141	163	java/lang/Exception
  }
  
  public static int b0428Ш0428ШШ0428Ш042804280428()
  {
    return 1;
  }
  
  private void b0428Ш0428ШШШ0428042804280428(String paramString)
  {
    do
    {
      try
      {
        Object localObject = bь044Cьь044Cьь044C044C;
        int i;
        int j;
        int k;
        bool = xxdddx.b0445хх04450445х0445044504450445();
      }
      catch (Exception paramString)
      {
        for (;;)
        {
          try
          {
            xtxtxt.bии0438и04380438и0438ии((String)localObject, gguuuu.bк043Aккк043Aкк043A043A("V?FPDH@w=EGs6A?>41A5:8vutsrqponmlkjihgfe", '3', 'm', '\002'));
            bool = ykykky.bШШ0428Ш0428ШШШ04280428().b04280428ШШ0428ШШШ04280428().bььььь044Cь044Cь.b0424Ф0424ФФФФФФ0424(paramString);
            if (!bool) {}
          }
          catch (Exception paramString)
          {
            boolean bool;
            throw paramString;
          }
          try
          {
            i = b044C044C044Cьь044Cь044C044C;
            j = b0428Ш0428ШШ0428Ш042804280428();
            k = bь044Cь044Cь044Cь044C044C;
            switch (i * (j + i) % k)
            {
            }
            try
            {
              b044C044C044Cьь044Cь044C044C = 48;
              bььь044Cь044Cь044C044C = 18;
              bool = ykykky.bШШ0428Ш0428ШШШ04280428().b04280428ШШ0428ШШШ04280428().bььььь044Cь044Cь.bФ04240424ФФФФФФ0424(paramString);
              if ((b044C044C044Cьь044Cь044C044C + b044Cьь044Cь044Cь044C044C) * b044C044C044Cьь044Cь044C044C % bШ04280428ШШ0428Ш042804280428() != bььь044Cь044Cь044C044C)
              {
                b044C044C044Cьь044Cь044C044C = b042804280428ШШ0428Ш042804280428();
                bььь044Cь044Cь044C044C = b042804280428ШШ0428Ш042804280428();
              }
              if (!bool) {
                continue;
              }
              b042804280428042804280428Ш042804280428();
              return;
            }
            catch (Exception paramString)
            {
              throw paramString;
            }
            localObject = this.bььььь044Cь044C044C;
            if (localObject == null)
            {
              localObject = new dddxdx.dxdxdx();
              localObject = ((dddxdx.dxdxdx)localObject).b0445х04450445х04450445044504450445(gguuuu.bк043Aккк043Aкк043A043A("x\b\004tvtq\003\003\rmx}\tkvtsifvjom}rl_[m]vWXh\\a_", '', 'L', '\000')).b0445х04450445х04450445044504450445(gguuuu.bк043Aккк043Aкк043A043A("x\n\bz~~}\021\023\037\f\007\034#\030\025\n\023\016\036*\036\022\017\023)0\023\026(\036%%", 'B', '', '\001'));
              paramString = new ykykyy.7(this, paramString);
              this.bььььь044Cь044C044C = ((dddxdx.dxdxdx)localObject).bхххх044504450445044504450445(paramString);
              return;
            }
          }
          catch (Exception paramString)
          {
            throw paramString;
          }
        }
        paramString = paramString;
        throw paramString;
      }
    } while (bool);
    bШШШШ0428ШШ042804280428();
  }
  
  private void b0428ШШ042804280428Ш042804280428(Message paramMessage)
  {
    try
    {
      Object localObject = paramMessage.getData();
      paramMessage = ((Bundle)localObject).getString(gguuuu.bк043Aккк043Aкк043A043A("^o_mdJf", '\016', '', '\001'));
      try
      {
        int i = b044C044C044Cьь044Cь044C044C;
        int j = b044Cьь044Cь044Cь044C044C;
        int k = b044C044C044Cьь044Cь044C044C;
        int m = bШ04280428ШШ0428Ш042804280428();
        int n = bььь044Cь044Cь044C044C;
        if ((i + j) * k % m != n)
        {
          b044C044C044Cьь044Cь044C044C = 67;
          bььь044Cь044Cь044C044C = b042804280428ШШ0428Ш042804280428();
        }
        str1 = ((Bundle)localObject).getString(gguuuu.bккккк043Aкк043A043A("`L\\PM[/I", '\n', '\003'));
        str2 = gguuuu.bккккк043Aкк043A043A("I=E;OESC/AUJ", '+', '\004');
      }
      catch (Exception paramMessage)
      {
        String str1;
        String str2;
        long l1;
        long l2;
        StringBuilder localStringBuilder;
        throw paramMessage;
      }
      str2 = ((Bundle)localObject).getString(str2);
      l1 = ((Bundle)localObject).getLong(gguuuu.bк043Aккк043Aкк043A043A("OSWQ?]f9U", 'c', 'ù', '\001'));
      l2 = ((Bundle)localObject).getLong(gguuuu.bккккк043Aкк043A043A("LCPO<A>*FM\0368", '!', '\005'));
      localObject = bь044Cьь044Cьь044C044C;
      localStringBuilder = new StringBuilder().append(gguuuu.bккккк043Aкк043A043A("bpb]o_G]n:dka^`QS7ZMRO=IZQ\037\004GCUA\rEBP.NKAE=|&\030\036\022$\030$\022+\033\013\035\020oe\002c", 'U', '\002'));
      if ((b044C044C044Cьь044Cь044C044C + b044Cьь044Cь044Cь044C044C) * b044C044C044Cьь044Cь044C044C % bь044Cь044Cь044Cь044C044C != bььь044Cь044Cь044C044C)
      {
        b044C044C044Cьь044Cь044C044C = b042804280428ШШ0428Ш042804280428();
        bььь044Cь044Cь044C044C = 54;
      }
      localStringBuilder = localStringBuilder.append(str2);
      localStringBuilder = localStringBuilder.append(gguuuu.bккккк043Aкк043A043A("q9=A;)GP#?{\032}", '', '\001')).append(l1).append(gguuuu.bк043Aккк043Aкк043A043A("G\026\017\036\037\016\025\024\002 ){\030TrV", '¥', '\001', '\003')).append(l2);
      xtxtxt.bии0438и04380438и0438ии((String)localObject, localStringBuilder.toString());
      b0428ШШШШШ0428042804280428(paramMessage);
      bШШ0428042804280428Ш042804280428();
      b04280428Ш0428Ш0428Ш042804280428(paramMessage, str1, str2, l2, l1, l1);
      return;
    }
    catch (Exception paramMessage)
    {
      throw paramMessage;
    }
    switch (0)
    {
    }
    for (;;)
    {
      switch (0)
      {
      }
    }
  }
  
  /* Error */
  private void b0428ШШ0428Ш0428Ш042804280428()
  {
    // Byte code:
    //   0: aload_0
    //   1: getfield 164	kkkkkk/ykykyy:b044C044Cььь044Cь044C044C	Ljava/util/concurrent/CopyOnWriteArrayList;
    //   4: invokevirtual 626	java/util/concurrent/CopyOnWriteArrayList:isEmpty	()Z
    //   7: ifeq +109 -> 116
    //   10: getstatic 140	kkkkkk/ykykyy:bь044Cьь044Cьь044C044C	Ljava/lang/String;
    //   13: astore_2
    //   14: ldc_w 628
    //   17: sipush 137
    //   20: bipush 19
    //   22: iconst_0
    //   23: invokestatic 383	kkkkkk/gguuuu:bк043Aккк043Aкк043A043A	(Ljava/lang/String;CCC)Ljava/lang/String;
    //   26: astore_3
    //   27: aload_2
    //   28: aload_3
    //   29: invokestatic 327	kkkkkk/xtxtxt:bии0438и04380438и0438ии	(Ljava/lang/String;Ljava/lang/String;)V
    //   32: aload_0
    //   33: invokespecial 631	kkkkkk/ykykyy:bШШШ042804280428Ш042804280428	()V
    //   36: getstatic 232	kkkkkk/ykykyy:b044C044C044Cьь044Cь044C044C	I
    //   39: istore_1
    //   40: iload_1
    //   41: getstatic 234	kkkkkk/ykykyy:b044Cьь044Cь044Cь044C044C	I
    //   44: iload_1
    //   45: iadd
    //   46: imul
    //   47: getstatic 236	kkkkkk/ykykyy:bь044Cь044Cь044Cь044C044C	I
    //   50: irem
    //   51: tableswitch	default:+17->68, 0:+61->112
    //   68: invokestatic 240	kkkkkk/ykykyy:b042804280428ШШ0428Ш042804280428	()I
    //   71: putstatic 232	kkkkkk/ykykyy:b044C044C044Cьь044Cь044C044C	I
    //   74: invokestatic 240	kkkkkk/ykykyy:b042804280428ШШ0428Ш042804280428	()I
    //   77: putstatic 242	kkkkkk/ykykyy:bььь044Cь044Cь044C044C	I
    //   80: getstatic 232	kkkkkk/ykykyy:b044C044C044Cьь044Cь044C044C	I
    //   83: invokestatic 399	kkkkkk/ykykyy:b0428Ш0428ШШ0428Ш042804280428	()I
    //   86: iadd
    //   87: getstatic 232	kkkkkk/ykykyy:b044C044C044Cьь044Cь044C044C	I
    //   90: imul
    //   91: getstatic 236	kkkkkk/ykykyy:bь044Cь044Cь044Cь044C044C	I
    //   94: irem
    //   95: getstatic 242	kkkkkk/ykykyy:bььь044Cь044Cь044C044C	I
    //   98: if_icmpeq +14 -> 112
    //   101: invokestatic 240	kkkkkk/ykykyy:b042804280428ШШ0428Ш042804280428	()I
    //   104: putstatic 232	kkkkkk/ykykyy:b044C044C044Cьь044Cь044C044C	I
    //   107: bipush 26
    //   109: putstatic 242	kkkkkk/ykykyy:bььь044Cь044Cь044C044C	I
    //   112: aload_0
    //   113: invokespecial 634	kkkkkk/ykykyy:bШ04280428042804280428Ш042804280428	()V
    //   116: return
    //   117: astore_2
    //   118: aload_2
    //   119: athrow
    //   120: astore_2
    //   121: aload_2
    //   122: athrow
    // Local variable table:
    //   start	length	slot	name	signature
    //   0	123	0	this	ykykyy
    //   39	8	1	i	int
    //   13	15	2	str1	String
    //   117	2	2	localException1	Exception
    //   120	2	2	localException2	Exception
    //   26	3	3	str2	String
    // Exception table:
    //   from	to	target	type
    //   0	27	117	java/lang/Exception
    //   112	116	117	java/lang/Exception
    //   27	36	120	java/lang/Exception
  }
  
  /* Error */
  private void b0428ШШШ04280428Ш042804280428(Intent paramIntent, BackgroundActionsService.ykyyky paramYkyyky)
  {
    // Byte code:
    //   0: aload_1
    //   1: ldc_w 638
    //   4: bipush 99
    //   6: iconst_2
    //   7: invokestatic 284	kkkkkk/gguuuu:bккккк043Aкк043A043A	(Ljava/lang/String;CC)Ljava/lang/String;
    //   10: invokevirtual 643	android/content/Intent:getStringExtra	(Ljava/lang/String;)Ljava/lang/String;
    //   13: astore 12
    //   15: aload_1
    //   16: ldc_w 645
    //   19: sipush 223
    //   22: iconst_3
    //   23: invokestatic 284	kkkkkk/gguuuu:bккккк043Aкк043A043A	(Ljava/lang/String;CC)Ljava/lang/String;
    //   26: invokevirtual 643	android/content/Intent:getStringExtra	(Ljava/lang/String;)Ljava/lang/String;
    //   29: astore 13
    //   31: invokestatic 240	kkkkkk/ykykyy:b042804280428ШШ0428Ш042804280428	()I
    //   34: istore_3
    //   35: getstatic 234	kkkkkk/ykykyy:b044Cьь044Cь044Cь044C044C	I
    //   38: istore 4
    //   40: invokestatic 240	kkkkkk/ykykyy:b042804280428ШШ0428Ш042804280428	()I
    //   43: istore 5
    //   45: getstatic 236	kkkkkk/ykykyy:bь044Cь044Cь044Cь044C044C	I
    //   48: istore 6
    //   50: getstatic 242	kkkkkk/ykykyy:bььь044Cь044Cь044C044C	I
    //   53: istore 7
    //   55: iload_3
    //   56: iload 4
    //   58: iadd
    //   59: iload 5
    //   61: imul
    //   62: iload 6
    //   64: irem
    //   65: iload 7
    //   67: if_icmpeq +14 -> 81
    //   70: bipush 59
    //   72: putstatic 232	kkkkkk/ykykyy:b044C044C044Cьь044Cь044C044C	I
    //   75: invokestatic 240	kkkkkk/ykykyy:b042804280428ШШ0428Ш042804280428	()I
    //   78: putstatic 242	kkkkkk/ykykyy:bььь044Cь044Cь044C044C	I
    //   81: aload_1
    //   82: ldc_w 647
    //   85: sipush 136
    //   88: sipush 213
    //   91: iconst_3
    //   92: invokestatic 383	kkkkkk/gguuuu:bк043Aккк043Aкк043A043A	(Ljava/lang/String;CCC)Ljava/lang/String;
    //   95: invokevirtual 643	android/content/Intent:getStringExtra	(Ljava/lang/String;)Ljava/lang/String;
    //   98: astore 14
    //   100: ldc_w 649
    //   103: sipush 239
    //   106: iconst_5
    //   107: invokestatic 284	kkkkkk/gguuuu:bккккк043Aкк043A043A	(Ljava/lang/String;CC)Ljava/lang/String;
    //   110: astore 15
    //   112: aload_1
    //   113: aload 15
    //   115: ldc2_w 650
    //   118: invokevirtual 655	android/content/Intent:getLongExtra	(Ljava/lang/String;J)J
    //   121: lstore 8
    //   123: aload_1
    //   124: ldc_w 657
    //   127: iconst_4
    //   128: iconst_2
    //   129: invokestatic 284	kkkkkk/gguuuu:bккккк043Aкк043A043A	(Ljava/lang/String;CC)Ljava/lang/String;
    //   132: ldc2_w 650
    //   135: invokevirtual 655	android/content/Intent:getLongExtra	(Ljava/lang/String;J)J
    //   138: lstore 10
    //   140: aload 14
    //   142: invokestatic 662	android/text/TextUtils:isEmpty	(Ljava/lang/CharSequence;)Z
    //   145: ifeq +18 -> 163
    //   148: getstatic 140	kkkkkk/ykykyy:bь044Cьь044Cьь044C044C	Ljava/lang/String;
    //   151: ldc_w 664
    //   154: bipush 104
    //   156: iconst_1
    //   157: invokestatic 284	kkkkkk/gguuuu:bккккк043Aкк043A043A	(Ljava/lang/String;CC)Ljava/lang/String;
    //   160: invokestatic 667	kkkkkk/xtxtxt:b0438и0438и04380438и0438ии	(Ljava/lang/String;Ljava/lang/String;)V
    //   163: getstatic 140	kkkkkk/ykykyy:bь044Cьь044Cьь044C044C	Ljava/lang/String;
    //   166: astore_1
    //   167: new 308	java/lang/StringBuilder
    //   170: dup
    //   171: invokespecial 309	java/lang/StringBuilder:<init>	()V
    //   174: ldc_w 669
    //   177: sipush 158
    //   180: iconst_2
    //   181: invokestatic 284	kkkkkk/gguuuu:bккккк043Aкк043A043A	(Ljava/lang/String;CC)Ljava/lang/String;
    //   184: invokevirtual 315	java/lang/StringBuilder:append	(Ljava/lang/String;)Ljava/lang/StringBuilder;
    //   187: astore 15
    //   189: iconst_0
    //   190: tableswitch	default:+22->212, 0:+49->239, 1:+-1->189
    //   212: iconst_0
    //   213: tableswitch	default:+23->236, 0:+26->239, 1:+-24->189
    //   236: goto -24 -> 212
    //   239: invokestatic 240	kkkkkk/ykykyy:b042804280428ШШ0428Ш042804280428	()I
    //   242: istore_3
    //   243: iload_3
    //   244: getstatic 234	kkkkkk/ykykyy:b044Cьь044Cь044Cь044C044C	I
    //   247: iload_3
    //   248: iadd
    //   249: imul
    //   250: getstatic 236	kkkkkk/ykykyy:bь044Cь044Cь044Cь044C044C	I
    //   253: irem
    //   254: tableswitch	default:+18->272, 0:+29->283
    //   272: bipush 67
    //   274: putstatic 232	kkkkkk/ykykyy:b044C044C044Cьь044Cь044C044C	I
    //   277: invokestatic 240	kkkkkk/ykykyy:b042804280428ШШ0428Ш042804280428	()I
    //   280: putstatic 242	kkkkkk/ykykyy:bььь044Cь044Cь044C044C	I
    //   283: aload_1
    //   284: aload 15
    //   286: aload 14
    //   288: invokevirtual 315	java/lang/StringBuilder:append	(Ljava/lang/String;)Ljava/lang/StringBuilder;
    //   291: invokevirtual 321	java/lang/StringBuilder:toString	()Ljava/lang/String;
    //   294: invokestatic 327	kkkkkk/xtxtxt:bии0438и04380438и0438ии	(Ljava/lang/String;Ljava/lang/String;)V
    //   297: aload_0
    //   298: aload 12
    //   300: aload 13
    //   302: aload 14
    //   304: lload 10
    //   306: lload 8
    //   308: new 671	kkkkkk/ykykyy$8
    //   311: dup
    //   312: aload_0
    //   313: aload_2
    //   314: aload 12
    //   316: invokespecial 674	kkkkkk/ykykyy$8:<init>	(Lkkkkkk/ykykyy;Lcom/liveperson/messaging/background/BackgroundActionsService$ykyyky;Ljava/lang/String;)V
    //   319: invokevirtual 678	kkkkkk/ykykyy:bШШШШ04280428Ш042804280428	(Ljava/lang/String;Ljava/lang/String;Ljava/lang/String;JJLkkkkkk/ykykyy$jyjyyy;)V
    //   322: return
    //   323: astore_1
    //   324: aload_1
    //   325: athrow
    //   326: astore_1
    //   327: aload_1
    //   328: athrow
    // Local variable table:
    //   start	length	slot	name	signature
    //   0	329	0	this	ykykyy
    //   0	329	1	paramIntent	Intent
    //   0	329	2	paramYkyyky	BackgroundActionsService.ykyyky
    //   34	216	3	i	int
    //   38	21	4	j	int
    //   43	19	5	k	int
    //   48	17	6	m	int
    //   53	15	7	n	int
    //   121	186	8	l1	long
    //   138	167	10	l2	long
    //   13	302	12	str1	String
    //   29	272	13	str2	String
    //   98	205	14	str3	String
    //   110	175	15	localObject	Object
    // Exception table:
    //   from	to	target	type
    //   0	40	323	java/lang/Exception
    //   70	81	323	java/lang/Exception
    //   112	163	323	java/lang/Exception
    //   163	189	323	java/lang/Exception
    //   40	55	326	java/lang/Exception
    //   81	112	326	java/lang/Exception
    //   283	322	326	java/lang/Exception
  }
  
  private void b0428ШШШШШ0428042804280428(String paramString)
  {
    int i = b044C044C044Cьь044Cь044C044C;
    int j = b044Cьь044Cь044Cь044C044C;
    int k = b044C044C044Cьь044Cь044C044C;
    switch (k * (b044Cьь044Cь044Cь044C044C + k) % bь044Cь044Cь044Cь044C044C)
    {
    default: 
      b044C044C044Cьь044Cь044C044C = b042804280428ШШ0428Ш042804280428();
      bььь044Cь044Cь044C044C = 55;
    }
    switch (i * (j + i) % bь044Cь044Cь044Cь044C044C)
    {
    default: 
      switch (1)
      {
      case 0: 
      default: 
        for (;;)
        {
          switch (0)
          {
          }
        }
      }
      b044C044C044Cьь044Cь044C044C = b042804280428ШШ0428Ш042804280428();
      bььь044Cь044Cь044C044C = b042804280428ШШ0428Ш042804280428();
    }
    bШ0428ШШШШ0428042804280428(paramString);
    bШШШШШШ0428042804280428(paramString);
    switch (1)
    {
    case 0: 
    default: 
      for (;;)
      {
        switch (0)
        {
        }
      }
    }
  }
  
  private void bШ04280428042804280428Ш042804280428()
  {
    if (this.bььььь044Cь044C044C != null)
    {
      this.bььььь044Cь044C044C.bхх04450445044504450445044504450445();
      switch (1)
      {
      case 0: 
      default: 
        for (;;)
        {
          switch (1)
          {
          }
        }
      }
      this.bььььь044Cь044C044C = null;
      int i = b044C044C044Cьь044Cь044C044C;
      switch (i * (b044Cьь044Cь044Cь044C044C + i) % bШ04280428ШШ0428Ш042804280428())
      {
      default: 
        b044C044C044Cьь044Cь044C044C = 22;
        bььь044Cь044Cь044C044C = b042804280428ШШ0428Ш042804280428();
        i = b044C044C044Cьь044Cь044C044C;
        switch (i * (b044Cьь044Cь044Cь044C044C + i) % bь044Cь044Cь044Cь044C044C)
        {
        default: 
          b044C044C044Cьь044Cь044C044C = b042804280428ШШ0428Ш042804280428();
          bььь044Cь044Cь044C044C = 8;
        }
        break;
      }
    }
  }
  
  @NonNull
  private jyyjyy bШ042804280428Ш0428Ш042804280428(yyyjyy paramYyyjyy)
    throws fefefe
  {
    try
    {
      paramYyyjyy = new jjjyyy(paramYyyjyy);
      return paramYyyjyy;
    }
    catch (Exception paramYyyjyy)
    {
      throw paramYyyjyy;
    }
  }
  
  /* Error */
  private void bШ04280428Ш04280428Ш042804280428(Intent paramIntent, BackgroundActionsService.ykyyky paramYkyyky)
  {
    // Byte code:
    //   0: aload_1
    //   1: ldc_w 709
    //   4: sipush 140
    //   7: bipush 43
    //   9: iconst_2
    //   10: invokestatic 383	kkkkkk/gguuuu:bк043Aккк043Aкк043A043A	(Ljava/lang/String;CCC)Ljava/lang/String;
    //   13: invokevirtual 643	android/content/Intent:getStringExtra	(Ljava/lang/String;)Ljava/lang/String;
    //   16: astore 6
    //   18: aload_1
    //   19: ldc_w 711
    //   22: bipush 28
    //   24: iconst_3
    //   25: invokestatic 284	kkkkkk/gguuuu:bккккк043Aкк043A043A	(Ljava/lang/String;CC)Ljava/lang/String;
    //   28: invokevirtual 643	android/content/Intent:getStringExtra	(Ljava/lang/String;)Ljava/lang/String;
    //   31: astore 7
    //   33: aload_1
    //   34: ldc_w 713
    //   37: sipush 194
    //   40: iconst_0
    //   41: invokestatic 284	kkkkkk/gguuuu:bккккк043Aкк043A043A	(Ljava/lang/String;CC)Ljava/lang/String;
    //   44: invokevirtual 643	android/content/Intent:getStringExtra	(Ljava/lang/String;)Ljava/lang/String;
    //   47: astore 8
    //   49: aload_1
    //   50: ldc_w 715
    //   53: sipush 158
    //   56: iconst_5
    //   57: invokestatic 284	kkkkkk/gguuuu:bккккк043Aкк043A043A	(Ljava/lang/String;CC)Ljava/lang/String;
    //   60: invokevirtual 643	android/content/Intent:getStringExtra	(Ljava/lang/String;)Ljava/lang/String;
    //   63: astore 9
    //   65: aload_1
    //   66: ldc_w 717
    //   69: bipush 45
    //   71: bipush 35
    //   73: iconst_1
    //   74: invokestatic 383	kkkkkk/gguuuu:bк043Aккк043Aкк043A043A	(Ljava/lang/String;CCC)Ljava/lang/String;
    //   77: ldc2_w 650
    //   80: invokevirtual 655	android/content/Intent:getLongExtra	(Ljava/lang/String;J)J
    //   83: lstore 4
    //   85: aload_1
    //   86: ldc_w 719
    //   89: bipush 110
    //   91: iconst_4
    //   92: invokestatic 284	kkkkkk/gguuuu:bккккк043Aкк043A043A	(Ljava/lang/String;CC)Ljava/lang/String;
    //   95: ldc2_w 650
    //   98: invokevirtual 655	android/content/Intent:getLongExtra	(Ljava/lang/String;J)J
    //   101: invokestatic 725	java/lang/Long:valueOf	(J)Ljava/lang/Long;
    //   104: astore_1
    //   105: getstatic 140	kkkkkk/ykykyy:bь044Cьь044Cьь044C044C	Ljava/lang/String;
    //   108: astore 10
    //   110: new 308	java/lang/StringBuilder
    //   113: dup
    //   114: invokespecial 309	java/lang/StringBuilder:<init>	()V
    //   117: ldc_w 727
    //   120: sipush 245
    //   123: iconst_2
    //   124: invokestatic 284	kkkkkk/gguuuu:bккккк043Aкк043A043A	(Ljava/lang/String;CC)Ljava/lang/String;
    //   127: invokevirtual 315	java/lang/StringBuilder:append	(Ljava/lang/String;)Ljava/lang/StringBuilder;
    //   130: aload 9
    //   132: invokevirtual 315	java/lang/StringBuilder:append	(Ljava/lang/String;)Ljava/lang/StringBuilder;
    //   135: astore 11
    //   137: getstatic 232	kkkkkk/ykykyy:b044C044C044Cьь044Cь044C044C	I
    //   140: istore_3
    //   141: iload_3
    //   142: getstatic 234	kkkkkk/ykykyy:b044Cьь044Cь044Cь044C044C	I
    //   145: iload_3
    //   146: iadd
    //   147: imul
    //   148: invokestatic 491	kkkkkk/ykykyy:bШ04280428ШШ0428Ш042804280428	()I
    //   151: irem
    //   152: tableswitch	default:+20->172, 0:+30->182
    //   172: bipush 89
    //   174: putstatic 232	kkkkkk/ykykyy:b044C044C044Cьь044Cь044C044C	I
    //   177: bipush 92
    //   179: putstatic 242	kkkkkk/ykykyy:bььь044Cь044Cь044C044C	I
    //   182: ldc_w 729
    //   185: sipush 202
    //   188: bipush 57
    //   190: iconst_2
    //   191: invokestatic 383	kkkkkk/gguuuu:bк043Aккк043Aкк043A043A	(Ljava/lang/String;CCC)Ljava/lang/String;
    //   194: astore 12
    //   196: aload 11
    //   198: aload 12
    //   200: invokevirtual 315	java/lang/StringBuilder:append	(Ljava/lang/String;)Ljava/lang/StringBuilder;
    //   203: aload_1
    //   204: invokevirtual 523	java/lang/StringBuilder:append	(Ljava/lang/Object;)Ljava/lang/StringBuilder;
    //   207: ldc_w 731
    //   210: bipush 118
    //   212: sipush 245
    //   215: iconst_2
    //   216: invokestatic 383	kkkkkk/gguuuu:bк043Aккк043Aкк043A043A	(Ljava/lang/String;CCC)Ljava/lang/String;
    //   219: invokevirtual 315	java/lang/StringBuilder:append	(Ljava/lang/String;)Ljava/lang/StringBuilder;
    //   222: astore 11
    //   224: getstatic 232	kkkkkk/ykykyy:b044C044C044Cьь044Cь044C044C	I
    //   227: getstatic 234	kkkkkk/ykykyy:b044Cьь044Cь044Cь044C044C	I
    //   230: iadd
    //   231: getstatic 232	kkkkkk/ykykyy:b044C044C044Cьь044Cь044C044C	I
    //   234: imul
    //   235: getstatic 236	kkkkkk/ykykyy:bь044Cь044Cь044Cь044C044C	I
    //   238: irem
    //   239: getstatic 242	kkkkkk/ykykyy:bььь044Cь044Cь044C044C	I
    //   242: if_icmpeq +14 -> 256
    //   245: bipush 33
    //   247: putstatic 232	kkkkkk/ykykyy:b044C044C044Cьь044Cь044C044C	I
    //   250: invokestatic 240	kkkkkk/ykykyy:b042804280428ШШ0428Ш042804280428	()I
    //   253: putstatic 242	kkkkkk/ykykyy:bььь044Cь044Cь044C044C	I
    //   256: aload 10
    //   258: aload 11
    //   260: aload 8
    //   262: invokevirtual 315	java/lang/StringBuilder:append	(Ljava/lang/String;)Ljava/lang/StringBuilder;
    //   265: invokevirtual 321	java/lang/StringBuilder:toString	()Ljava/lang/String;
    //   268: invokestatic 327	kkkkkk/xtxtxt:bии0438и04380438и0438ии	(Ljava/lang/String;Ljava/lang/String;)V
    //   271: aload_0
    //   272: aload 6
    //   274: aload 7
    //   276: aload 8
    //   278: aload 9
    //   280: lload 4
    //   282: invokestatic 725	java/lang/Long:valueOf	(J)Ljava/lang/Long;
    //   285: invokevirtual 735	java/lang/Long:longValue	()J
    //   288: aload_1
    //   289: invokevirtual 735	java/lang/Long:longValue	()J
    //   292: new 737	kkkkkk/ykykyy$10
    //   295: dup
    //   296: aload_0
    //   297: aload_2
    //   298: aload 6
    //   300: invokespecial 738	kkkkkk/ykykyy$10:<init>	(Lkkkkkk/ykykyy;Lcom/liveperson/messaging/background/BackgroundActionsService$ykyyky;Ljava/lang/String;)V
    //   303: invokevirtual 742	kkkkkk/ykykyy:b0428Ш0428Ш04280428Ш042804280428	(Ljava/lang/String;Ljava/lang/String;Ljava/lang/String;Ljava/lang/String;JJLkkkkkk/ykykyy$yjjyyy;)V
    //   306: return
    //   307: astore_1
    //   308: aload_1
    //   309: athrow
    //   310: astore_1
    //   311: aload_1
    //   312: athrow
    // Local variable table:
    //   start	length	slot	name	signature
    //   0	313	0	this	ykykyy
    //   0	313	1	paramIntent	Intent
    //   0	313	2	paramYkyyky	BackgroundActionsService.ykyyky
    //   140	8	3	i	int
    //   83	198	4	l	long
    //   16	283	6	str1	String
    //   31	244	7	str2	String
    //   47	230	8	str3	String
    //   63	216	9	str4	String
    //   108	149	10	str5	String
    //   135	124	11	localStringBuilder	StringBuilder
    //   194	5	12	str6	String
    // Exception table:
    //   from	to	target	type
    //   0	137	307	java/lang/Exception
    //   182	196	307	java/lang/Exception
    //   196	224	310	java/lang/Exception
    //   256	306	310	java/lang/Exception
  }
  
  public static int bШ04280428ШШ0428Ш042804280428()
  {
    return 2;
  }
  
  private void bШ0428Ш042804280428Ш042804280428(Message paramMessage)
  {
    Object localObject = paramMessage.getData();
    String str1 = ((Bundle)localObject).getString(gguuuu.bккккк043Aкк043A043A("dvfpw\004nj", 'Î', '\004'));
    int i = paramMessage.arg2;
    paramMessage = this.b044C044Cььь044Cь044C044C.iterator();
    while (paramMessage.hasNext())
    {
      str2 = ((jyyjyy)paramMessage.next()).b0428Ш0428Ш042804280428042804280428();
      xtxtxt.bии0438и04380438и0438ии(bь044Cьь044Cьь044C044C, gguuuu.bк043Aккк043Aкк043A043A("\"2&#7)\023+>\032.\037;8</3\031>3:9)7JC\023y@RBLSJF\035\004", 'z', 'Â', '\003') + str1 + gguuuu.bк043Aккк043Aкк043A043A("\021fTg`;m]gnd`\035;", 't', '{', '\003') + str2);
      if (TextUtils.equals(str2, str1))
      {
        xtxtxt.bии0438и04380438и0438ии(bь044Cьь044Cьь044C044C, gguuuu.bккккк043Aкк043A043A("2B63G9#;N*>/KHL?C)NCJI9GZS#\nPbR\\c\020ZV-\024", '¦', '\004') + str1 + gguuuu.bккккк043Aкк043A043A("-u~*jtykfh|\"jn\037nokbl^kj$\025bb\022_UTR\r`Z\n[MZKSH\021", 'r', '\005'));
        return;
      }
    }
    paramMessage = gguuuu.bк043Aккк043Aкк043A043A("CTDRI/K", 'ç', '', '\001');
    int j = b044C044C044Cьь044Cь044C044C;
    switch (j * (b044Cьь044Cь044Cь044C044C + j) % bь044Cь044Cь044Cь044C044C)
    {
    default: 
      b044C044C044Cьь044Cь044C044C = 42;
      bььь044Cь044Cь044C044C = b042804280428ШШ0428Ш042804280428();
    }
    paramMessage = ((Bundle)localObject).getString(paramMessage);
    String str2 = ((Bundle)localObject).getString(gguuuu.bк043Aккк043Aкк043A043A("\tv\t~}\016c", '·', '£', '\001'));
    j = b042804280428ШШ0428Ш042804280428();
    switch (j * (b044Cьь044Cь044Cь044C044C + j) % bь044Cь044Cь044Cь044C044C)
    {
    default: 
      b044C044C044Cьь044Cь044C044C = b042804280428ШШ0428Ш042804280428();
      bььь044Cь044Cь044C044C = 81;
    }
    String str3 = ((Bundle)localObject).getString(gguuuu.bккккк043Aкк043A043A("xw\b\r\003\n\n", '', '\000'));
    String str4 = ((Bundle)localObject).getString(gguuuu.bк043Aккк043Aкк043A043A("\005\t\001\003\t|\t\035\013\017\004\003\017#\032\030\020'\031\013\037\024", 'E', '\020', '\001'));
    String str5 = ((Bundle)localObject).getString(gguuuu.bккккк043Aкк043A043A(":-90$/!(*<(*\035\032$6+'\0352\"\022$\027", '\032', '\005'));
    long l1 = ((Bundle)localObject).getLong(gguuuu.bккккк043Aкк043A043A("\024\030\020\017\022\030\f\030,\033\024#$\023\032\0314* %\036", 'D', '\000'));
    long l2 = ((Bundle)localObject).getLong(gguuuu.bккккк043Aкк043A043A("?CGA/MV)E", 'ñ', '\001'));
    boolean bool = ((Bundle)localObject).getBoolean(gguuuu.bккккк043Aкк043A043A("pujqpR}|Srx\007v", 'Â', '\004'), false);
    xtxtxt.bии0438и04380438и0438ии(bь044Cьь044Cьь044C044C, gguuuu.bккккк043Aкк043A043A("2B63G9#;N*>/KHL?C)NCJI9GZS#\n_Tb[Q^R[_@dYXdNldL^rg >\"", 'N', '\000') + str5);
    b0428ШШШШШ0428042804280428(paramMessage);
    localObject = new yyyjyy();
    ((yyyjyy)localObject).bШШШШ0428Ш0428042804280428(l2).b0428ШШШ0428Ш0428042804280428(str4).b04280428ШШ0428Ш0428042804280428(str5).b0428042804280428ШШ0428042804280428(str1).bШ0428ШШ0428Ш0428042804280428(l1).bФ04240424ФФФФФФФ(paramMessage).bФФ04240424ФФФФФФ(str2).bФФФ0424ФФФФФФ(Uri.parse(str4)).b04240424Ф0424ФФФФФФ(this.b044Cь044Cьь044Cь044C044C).bФ0424Ф0424ФФФФФФ(this.bьь044Cьь044Cь044C044C).b0424ФФ0424ФФФФФФ(this.b044Cь044C044C044Cьь044C044C.b0428Ш04280428Ш04280428ШШ0428(paramMessage, str3)).b042404240424ФФФФФФФ(bool).b042804280428Ш0428Ш0428042804280428(i, this.bьь044C044C044Cьь044C044C);
    xtxtxt.bии0438и04380438и0438ии(bь044Cьь044Cьь044C044C, i + gguuuu.bккккк043Aкк043A043A("B'iwidvfNduRlgiZ\\@cV[XFRcZ(\rA[VXIK/REJG5ARI\037QI>E=v?B5:7%I?3\007k", '{', '\003') + ((yyyjyy)localObject).bФ0424ФФ0424ФФФФФ() + gguuuu.bк043Aккк043Aкк043A043A("\023\bNb_Q[aX__,\023", 'Z', '', '\003') + ((yyyjyy)localObject).bФФ0424Ф0424ФФФФФ());
    bШШ0428042804280428Ш042804280428();
    try
    {
      b0428Ш04280428Ш0428Ш042804280428(bШ042804280428Ш0428Ш042804280428((yyyjyy)localObject), paramMessage, i, (jyjjyy)localObject);
      return;
    }
    catch (fefefe paramMessage)
    {
      xtxtxt.bи04380438и04380438и0438ии(bь044Cьь044Cьь044C044C, paramMessage);
      ((ykykyy.yjjyyy)this.b044C044C044C044C044Cьь044C044C.get(i)).bШШШ04280428Ш04280428Ш0428(paramMessage);
      this.b044C044C044C044C044Cьь044C044C.remove(i);
      bШШШ0428Ш0428Ш042804280428();
    }
  }
  
  @NonNull
  private yyyyky bШ0428Ш0428Ш0428Ш042804280428(yykkyy paramYykkyy)
  {
    if ((b044C044C044Cьь044Cь044C044C + b044Cьь044Cь044Cь044C044C) * b044C044C044Cьь044Cь044C044C % bь044Cь044Cь044Cь044C044C != bШШ0428ШШ0428Ш042804280428())
    {
      b044C044C044Cьь044Cь044C044C = b042804280428ШШ0428Ш042804280428();
      if ((b044C044C044Cьь044Cь044C044C + b044Cьь044Cь044Cь044C044C) * b044C044C044Cьь044Cь044C044C % bь044Cь044Cь044Cь044C044C != bььь044Cь044Cь044C044C)
      {
        b044C044C044Cьь044Cь044C044C = 89;
        bььь044Cь044Cь044C044C = 43;
      }
      bььь044Cь044Cь044C044C = 41;
    }
    return new yyyyky(paramYykkyy);
  }
  
  /* Error */
  private void bШ0428ШШШШ0428042804280428(String paramString)
  {
    // Byte code:
    //   0: aload_0
    //   1: getfield 359	kkkkkk/ykykyy:b044Cь044Cьь044Cь044C044C	Ljava/lang/String;
    //   4: invokestatic 662	android/text/TextUtils:isEmpty	(Ljava/lang/CharSequence;)Z
    //   7: ifeq +156 -> 163
    //   10: aload_0
    //   11: aload_0
    //   12: getfield 170	kkkkkk/ykykyy:b044Cь044C044C044Cьь044C044C	Lkkkkkk/kkyykk;
    //   15: getfield 824	kkkkkk/kkyykk:bь044C044C044C044Cьь044Cь	Lkkkkkk/cmmmcc;
    //   18: aload_1
    //   19: ldc_w 826
    //   22: bipush 80
    //   24: iconst_2
    //   25: invokestatic 284	kkkkkk/gguuuu:bккккк043Aкк043A043A	(Ljava/lang/String;CC)Ljava/lang/String;
    //   28: invokevirtual 832	kkkkkk/cmmmcc:b0424Ф0424042404240424Ф04240424Ф	(Ljava/lang/String;Ljava/lang/String;)Ljava/lang/String;
    //   31: putfield 359	kkkkkk/ykykyy:b044Cь044Cьь044Cь044C044C	Ljava/lang/String;
    //   34: aload_0
    //   35: getfield 359	kkkkkk/ykykyy:b044Cь044Cьь044Cь044C044C	Ljava/lang/String;
    //   38: astore_1
    //   39: getstatic 232	kkkkkk/ykykyy:b044C044C044Cьь044Cь044C044C	I
    //   42: istore_2
    //   43: getstatic 234	kkkkkk/ykykyy:b044Cьь044Cь044Cь044C044C	I
    //   46: istore_3
    //   47: getstatic 236	kkkkkk/ykykyy:bь044Cь044Cь044Cь044C044C	I
    //   50: istore 4
    //   52: iload_2
    //   53: iload_3
    //   54: iload_2
    //   55: iadd
    //   56: imul
    //   57: iload 4
    //   59: irem
    //   60: tableswitch	default:+20->80, 0:+31->91
    //   80: invokestatic 240	kkkkkk/ykykyy:b042804280428ШШ0428Ш042804280428	()I
    //   83: putstatic 232	kkkkkk/ykykyy:b044C044C044Cьь044Cь044C044C	I
    //   86: bipush 58
    //   88: putstatic 242	kkkkkk/ykykyy:bььь044Cь044Cь044C044C	I
    //   91: aload_1
    //   92: invokestatic 662	android/text/TextUtils:isEmpty	(Ljava/lang/CharSequence;)Z
    //   95: ifeq +68 -> 163
    //   98: getstatic 140	kkkkkk/ykykyy:bь044Cьь044Cьь044C044C	Ljava/lang/String;
    //   101: astore_1
    //   102: aload_1
    //   103: ldc_w 834
    //   106: bipush 45
    //   108: iconst_4
    //   109: invokestatic 284	kkkkkk/gguuuu:bккккк043Aкк043A043A	(Ljava/lang/String;CC)Ljava/lang/String;
    //   112: invokestatic 837	kkkkkk/xtxtxt:bии0438043804380438и0438ии	(Ljava/lang/String;Ljava/lang/String;)V
    //   115: aload_0
    //   116: invokespecial 518	kkkkkk/ykykyy:bШШШШ0428ШШ042804280428	()V
    //   119: getstatic 232	kkkkkk/ykykyy:b044C044C044Cьь044Cь044C044C	I
    //   122: istore_2
    //   123: iload_2
    //   124: getstatic 234	kkkkkk/ykykyy:b044Cьь044Cь044Cь044C044C	I
    //   127: iload_2
    //   128: iadd
    //   129: imul
    //   130: getstatic 236	kkkkkk/ykykyy:bь044Cь044Cь044Cь044C044C	I
    //   133: irem
    //   134: tableswitch	default:+18->152, 0:+29->163
    //   152: invokestatic 240	kkkkkk/ykykyy:b042804280428ШШ0428Ш042804280428	()I
    //   155: putstatic 232	kkkkkk/ykykyy:b044C044C044Cьь044Cь044C044C	I
    //   158: bipush 65
    //   160: putstatic 242	kkkkkk/ykykyy:bььь044Cь044Cь044C044C	I
    //   163: return
    //   164: astore_1
    //   165: aload_1
    //   166: athrow
    //   167: astore_1
    //   168: aload_1
    //   169: athrow
    //   170: astore_1
    //   171: aload_1
    //   172: athrow
    //   173: astore_1
    //   174: aload_1
    //   175: athrow
    // Local variable table:
    //   start	length	slot	name	signature
    //   0	176	0	this	ykykyy
    //   0	176	1	paramString	String
    //   42	88	2	i	int
    //   46	10	3	j	int
    //   50	10	4	k	int
    // Exception table:
    //   from	to	target	type
    //   0	39	164	java/lang/Exception
    //   102	115	164	java/lang/Exception
    //   80	91	167	java/lang/Exception
    //   165	167	167	java/lang/Exception
    //   171	173	167	java/lang/Exception
    //   91	102	170	java/lang/Exception
    //   115	119	170	java/lang/Exception
    //   39	52	173	java/lang/Exception
  }
  
  private void bШШ0428042804280428Ш042804280428()
  {
    bШШШ042804280428Ш042804280428();
    Message localMessage = new Message();
    int i = b042804280428ШШ0428Ш042804280428();
    int j = b044Cьь044Cь044Cь044C044C;
    int k = bШ04280428ШШ0428Ш042804280428();
    if ((b044C044C044Cьь044Cь044C044C + b044Cьь044Cь044Cь044C044C) * b044C044C044Cьь044Cь044C044C % bь044Cь044Cь044Cь044C044C != bШШ0428ШШ0428Ш042804280428())
    {
      b044C044C044Cьь044Cь044C044C = 45;
      bььь044Cь044Cь044C044C = 68;
    }
    switch (i * (j + i) % k)
    {
    default: 
      b044C044C044Cьь044Cь044C044C = 60;
      bььь044Cь044Cь044C044C = 23;
    }
    localMessage.what = 3;
    b0428Ш04280428Ш0428Ш04280428Ш(localMessage, this.bь044C044Cьь044Cь044C044C);
  }
  
  private void bШШ04280428Ш0428Ш042804280428(String paramString, ArrayList<String> paramArrayList)
  {
    for (;;)
    {
      try
      {
        Iterator localIterator = paramArrayList.iterator();
        if (!localIterator.hasNext()) {
          break;
        }
        str1 = (String)localIterator.next();
        localObject = new File(str1);
        if (((File)localObject).isFile())
        {
          xtxtxt.bии0438и04380438и0438ии(bь044Cьь044Cьь044C044C, gguuuu.bк043Aккк043Aкк043A043A("ZhZUgW?Uf@RYZ`N7SJ.QDIF&HJB0<MD\022v::@8F:>6m357/\003g", 'î', 'å', '\000') + paramArrayList);
          boolean bool = ((File)localObject).delete();
          if (!bool) {
            break label312;
          }
          i = b044C044C044Cьь044Cь044C044C;
          switch (i * (b044Cьь044Cь044Cь044C044C + i) % bь044Cь044Cь044Cь044C044C)
          {
          default: 
            b044C044C044Cьь044Cь044C044C = 13;
            bььь044Cь044Cь044C044C = 88;
          }
          xtxtxt.bии0438и04380438и0438ии(bь044Cьь044Cьь044C044C, gguuuu.bк043Aккк043Aкк043A043A("\020\036\020\013\035\rt\013\034u\b\017\020\026\004l\tc\007y~{[}weq\003yG,qsum'xjqrxfd\037qr_^_lk]ka`l", '', ':', '\000'));
          ykykky.bШШ0428Ш0428ШШШ04280428().b04280428ШШ0428ШШШ04280428().bь044Cь044C044Cьь044Cь.bэ044Dэ044Dээ044Dэээ(paramString, str1).b04380438и0438ии0438иии(new ykykyy.6(this, paramArrayList)).b0438ии0438ии0438иии();
          i = b044C044C044Cьь044Cь044C044C;
          j = b0428Ш0428ШШ0428Ш042804280428();
        }
      }
      catch (Exception paramString)
      {
        try
        {
          int i;
          int j;
          int k = bь044Cь044Cь044Cь044C044C;
          switch (i * (j + i) % k)
          {
          }
          b044C044C044Cьь044Cь044C044C = 83;
          bььь044Cь044Cь044C044C = b042804280428ШШ0428Ш042804280428();
        }
        catch (Exception paramString)
        {
          throw paramString;
        }
        paramString = paramString;
        throw paramString;
      }
      String str1 = bь044Cьь044Cьь044C044C;
      Object localObject = new StringBuilder();
      localObject = ((StringBuilder)localObject).append(gguuuu.bк043Aккк043Aкк043A043A("\r\033\r\b\032\nq\b\031r\005\f\r\023\001i\006|`\004v{xXz|tbnvD)Nprj$wq!rdklr`\032bk\027ddh\023S\021VXZR\f\023", '@', '', '\002')).append(paramArrayList);
      xtxtxt.bии0438043804380438и0438ии(str1, gguuuu.bк043Aккк043Aкк043A043A("v", 'µ', '\004', '\000'));
      continue;
      label312:
      str1 = bь044Cьь044Cьь044C044C;
      localObject = new StringBuilder().append(gguuuu.bккккк043Aкк043A043A("@N@;M=%;L&8?@F4\03590\0247*/,\f.0(\026\"3*w\\\"$&\036W.\027(S!!%O!\023\032\033!\017\rGN", 'Ð', '\003')).append(paramArrayList);
      String str2 = gguuuu.bккккк043Aкк043A043A("6", 'F', '\004');
      xtxtxt.bии0438043804380438и0438ии(str1, str2);
    }
  }
  
  private boolean bШШ0428Ш04280428Ш042804280428(String paramString)
  {
    cmmmcc localCmmmcc = this.b044Cь044C044C044Cьь044C044C.bь044C044C044C044Cьь044Cь;
    if ((b044C044C044Cьь044Cь044C044C + b044Cьь044Cь044Cь044C044C) * b044C044C044Cьь044Cь044C044C % bь044Cь044Cь044Cь044C044C != bШШ0428ШШ0428Ш042804280428())
    {
      b044C044C044Cьь044Cь044C044C = b042804280428ШШ0428Ш042804280428();
      bььь044Cь044Cь044C044C = 61;
    }
    paramString = localCmmmcc.b0424ФФ042404240424Ф04240424Ф(paramString);
    paramString = mrmrmm.bШ04280428Ш0428Ш0428ШШШ().bШШШ04280428Ш0428ШШШ(paramString);
    xtxtxt.bиии043804380438и0438ии(bь044Cьь044Cьь044C044C, gguuuu.bк043Aккк043Aкк043A043A("\017B@A5?FrGD9B=MyNP>RD\032\001", '\b', '<', '\001') + paramString);
    switch (ykykyy.12.b044Cь044C044C044C044Cь044C044C[paramString.ordinal()])
    {
    default: 
      return true;
    }
    return false;
  }
  
  public static int bШШ0428ШШ0428Ш042804280428()
  {
    return 0;
  }
  
  private void bШШ0428ШШШ0428042804280428(Intent paramIntent, BackgroundActionsService.ykyyky paramYkyyky)
  {
    String str1 = paramIntent.getStringExtra(gguuuu.bккккк043Aкк043A043A("]NZ]OHIBGYTQ?<>M;G<6?9", '\013', '\003'));
    String str2 = paramIntent.getStringExtra(gguuuu.bккккк043Aкк043A043A("~q\005xsvqx\r\n\txw\016{\016\004\003\023~\n\006", '', '\000'));
    String str3 = paramIntent.getStringExtra(gguuuu.bккккк043Aкк043A043A("2#/2$\035\036\027\034.)&\024\021\032\035\020\025\022\013 \034\022", 'À', '\005'));
    String str4 = paramIntent.getStringExtra(gguuuu.bккккк043Aкк043A043A("\025\006\022\025\007\001y~\021\f\tvs|rwtmpm{~rwu", '^', '\005'));
    int i = b044C044C044Cьь044Cь044C044C;
    switch (i * (b044Cьь044Cь044Cь044C044C + i) % bь044Cь044Cь044Cь044C044C)
    {
    default: 
      b044C044C044Cьь044Cь044C044C = 13;
      bььь044Cь044Cь044C044C = b042804280428ШШ0428Ш042804280428();
    }
    boolean bool = paramIntent.getBooleanExtra(gguuuu.bккккк043Aкк043A043A("\013}\f\021\005\003}\005\031\026\025\005\004\017\024\t\020\017\n\022\037\035\034\017\024\023 \031'\027", 'Ê', '\004'), false);
    if (TextUtils.isEmpty(str3)) {
      xtxtxt.b0438и0438и04380438и0438ии(bь044Cьь044Cьь044C044C, gguuuu.bккккк043Aкк043A043A("/)$&\027\031| \023\030\025hMq\036\035\031\033G\016\013\031\030\f\020\b?\016\f\002;\n8\f~z4\006w\003\006x\001rp+zjzhsx$iqs tnik\\^bf^\026Vb\023[^QVS", '¢', '\003'));
    }
    xtxtxt.bии0438и04380438и0438ии(bь044Cьь044Cьь044C044C, gguuuu.bккккк043Aкк043A043A("NHCE68\034?274\bl??+;<04,c$a5(1#\036 Z +'$U)\034\030Q$\025!$\026\017\020WH|\027\022\024\005\007Ap\001\021~\n\017T9\002\005w|yh\005zM", '', '\002') + str3);
    paramIntent = new ykykyy.9(this, paramYkyyky, str1);
    i = b044C044C044Cьь044Cь044C044C;
    switch (i * (b044Cьь044Cь044Cь044C044C + i) % bь044Cь044Cь044Cь044C044C)
    {
    default: 
      b044C044C044Cьь044Cь044C044C = 3;
      bььь044Cь044Cь044C044C = 21;
    }
    b04280428ШШШШ0428042804280428(str1, str2, str3, str4, bool, paramIntent);
  }
  
  private void bШШШ042804280428Ш042804280428()
  {
    throw new Runtime("d2j fail translate: java.lang.IndexOutOfBoundsException: fromIndex < 0: -1\n\tat java.util.BitSet.nextSetBit(BitSet.java:712)\n\tat com.googlecode.dex2jar.ir.ts.array.FillArrayTransformer.makeSureAllElementAreAssigned(FillArrayTransformer.java:505)\n\tat com.googlecode.dex2jar.ir.ts.array.FillArrayTransformer.transformReportChanged(FillArrayTransformer.java:123)\n\tat com.googlecode.dex2jar.ir.ts.StatedTransformer.transform(StatedTransformer.java:10)\n\tat com.googlecode.d2j.dex.Dex2jar$2.optimize(Dex2jar.java:149)\n\tat com.googlecode.d2j.dex.Dex2Asm.convertCode(Dex2Asm.java:414)\n\tat com.googlecode.d2j.dex.ExDex2Asm.convertCode(ExDex2Asm.java:42)\n\tat com.googlecode.d2j.dex.Dex2jar$2.convertCode(Dex2jar.java:128)\n\tat com.googlecode.d2j.dex.Dex2Asm.convertMethod(Dex2Asm.java:509)\n\tat com.googlecode.d2j.dex.Dex2Asm.convertClass(Dex2Asm.java:406)\n\tat com.googlecode.d2j.dex.Dex2Asm.convertDex(Dex2Asm.java:422)\n\tat com.googlecode.d2j.dex.Dex2jar.doTranslate(Dex2jar.java:172)\n\tat com.googlecode.d2j.dex.Dex2jar.to(Dex2jar.java:272)\n\tat com.googlecode.dex2jar.tools.Dex2jarCmd.doCommandLine(Dex2jarCmd.java:108)\n\tat com.googlecode.dex2jar.tools.BaseCmd.doMain(BaseCmd.java:288)\n\tat com.googlecode.dex2jar.tools.Dex2jarCmd.main(Dex2jarCmd.java:32)\n");
  }
  
  private void bШШШ0428Ш0428Ш042804280428()
  {
    if (this.bь044Cььь044Cь044C044C.isEmpty())
    {
      String str1 = bь044Cьь044Cьь044C044C;
      if ((b044C044C044Cьь044Cь044C044C + b0428Ш0428ШШ0428Ш042804280428()) * b044C044C044Cьь044Cь044C044C % bь044Cь044Cь044Cь044C044C != bььь044Cь044Cь044C044C)
      {
        b044C044C044Cьь044Cь044C044C = 17;
        bььь044Cь044Cь044C044C = 73;
      }
      String str2 = gguuuu.bк043Aккк043Aкк043A043A("-OSMVJFD~F>J?FBF>u6@?qE84m:1>=*/,9", '³', '\033', '\000');
      switch (0)
      {
      case 1: 
      default: 
        for (;;)
        {
          int i = b044C044C044Cьь044Cь044C044C;
          switch (i * (b044Cьь044Cь044Cь044C044C + i) % bь044Cь044Cь044Cь044C044C)
          {
          default: 
            b044C044C044Cьь044Cь044C044C = b042804280428ШШ0428Ш042804280428();
            bььь044Cь044Cь044C044C = b042804280428ШШ0428Ш042804280428();
          }
          switch (1)
          {
          }
        }
      }
      xtxtxt.bии0438и04380438и0438ии(str1, str2);
      bШШШ042804280428Ш042804280428();
      bШ04280428042804280428Ш042804280428();
    }
  }
  
  /* Error */
  private void bШШШШ0428ШШ042804280428()
  {
    // Byte code:
    //   0: getstatic 140	kkkkkk/ykykyy:bь044Cьь044Cьь044C044C	Ljava/lang/String;
    //   3: ldc_w 959
    //   6: sipush 170
    //   9: bipush 63
    //   11: iconst_0
    //   12: invokestatic 383	kkkkkk/gguuuu:bк043Aккк043Aкк043A043A	(Ljava/lang/String;CCC)Ljava/lang/String;
    //   15: invokestatic 327	kkkkkk/xtxtxt:bии0438и04380438и0438ии	(Ljava/lang/String;Ljava/lang/String;)V
    //   18: aload_0
    //   19: invokespecial 634	kkkkkk/ykykyy:bШ04280428042804280428Ш042804280428	()V
    //   22: aload_0
    //   23: getfield 164	kkkkkk/ykykyy:b044C044Cььь044Cь044C044C	Ljava/util/concurrent/CopyOnWriteArrayList;
    //   26: invokevirtual 218	java/util/concurrent/CopyOnWriteArrayList:iterator	()Ljava/util/Iterator;
    //   29: astore 7
    //   31: getstatic 232	kkkkkk/ykykyy:b044C044C044Cьь044Cь044C044C	I
    //   34: istore_1
    //   35: getstatic 234	kkkkkk/ykykyy:b044Cьь044Cь044Cь044C044C	I
    //   38: istore_2
    //   39: getstatic 232	kkkkkk/ykykyy:b044C044C044Cьь044Cь044C044C	I
    //   42: istore_3
    //   43: getstatic 236	kkkkkk/ykykyy:bь044Cь044Cь044Cь044C044C	I
    //   46: istore 4
    //   48: getstatic 242	kkkkkk/ykykyy:bььь044Cь044Cь044C044C	I
    //   51: istore 5
    //   53: iload_1
    //   54: iload_2
    //   55: iadd
    //   56: iload_3
    //   57: imul
    //   58: iload 4
    //   60: irem
    //   61: iload 5
    //   63: if_icmpeq +14 -> 77
    //   66: invokestatic 240	kkkkkk/ykykyy:b042804280428ШШ0428Ш042804280428	()I
    //   69: putstatic 232	kkkkkk/ykykyy:b044C044C044Cьь044Cь044C044C	I
    //   72: bipush 64
    //   74: putstatic 242	kkkkkk/ykykyy:bььь044Cь044Cь044C044C	I
    //   77: aload 7
    //   79: invokeinterface 224 1 0
    //   84: istore 6
    //   86: iload 6
    //   88: ifeq +95 -> 183
    //   91: aload 7
    //   93: invokeinterface 228 1 0
    //   98: checkcast 230	kkkkkk/jyyjyy
    //   101: invokevirtual 962	kkkkkk/jyyjyy:b04280428Ш0428042804280428042804280428	()V
    //   104: goto -27 -> 77
    //   107: astore 7
    //   109: aload 7
    //   111: athrow
    //   112: aload 7
    //   114: invokeinterface 224 1 0
    //   119: ifeq +81 -> 200
    //   122: aload 7
    //   124: invokeinterface 228 1 0
    //   129: checkcast 247	kkkkkk/yyyyky
    //   132: invokevirtual 965	kkkkkk/yyyyky:b0428042804280428ШШ0428Ш04280428	()V
    //   135: getstatic 232	kkkkkk/ykykyy:b044C044C044Cьь044Cь044C044C	I
    //   138: istore_1
    //   139: iload_1
    //   140: invokestatic 399	kkkkkk/ykykyy:b0428Ш0428ШШ0428Ш042804280428	()I
    //   143: iload_1
    //   144: iadd
    //   145: imul
    //   146: getstatic 236	kkkkkk/ykykyy:bь044Cь044Cь044Cь044C044C	I
    //   149: irem
    //   150: tableswitch	default:+18->168, 0:+-38->112
    //   168: invokestatic 240	kkkkkk/ykykyy:b042804280428ШШ0428Ш042804280428	()I
    //   171: putstatic 232	kkkkkk/ykykyy:b044C044C044Cьь044Cь044C044C	I
    //   174: invokestatic 240	kkkkkk/ykykyy:b042804280428ШШ0428Ш042804280428	()I
    //   177: putstatic 242	kkkkkk/ykykyy:bььь044Cь044Cь044C044C	I
    //   180: goto -68 -> 112
    //   183: aload_0
    //   184: getfield 166	kkkkkk/ykykyy:bь044Cььь044Cь044C044C	Ljava/util/concurrent/CopyOnWriteArrayList;
    //   187: invokevirtual 218	java/util/concurrent/CopyOnWriteArrayList:iterator	()Ljava/util/Iterator;
    //   190: astore 7
    //   192: goto -80 -> 112
    //   195: astore 7
    //   197: aload 7
    //   199: athrow
    //   200: return
    // Local variable table:
    //   start	length	slot	name	signature
    //   0	201	0	this	ykykyy
    //   34	112	1	i	int
    //   38	18	2	j	int
    //   42	16	3	k	int
    //   46	15	4	m	int
    //   51	13	5	n	int
    //   84	3	6	bool	boolean
    //   29	63	7	localIterator1	Iterator
    //   107	16	7	localException1	Exception
    //   190	1	7	localIterator2	Iterator
    //   195	3	7	localException2	Exception
    // Exception table:
    //   from	to	target	type
    //   0	53	107	java/lang/Exception
    //   91	104	107	java/lang/Exception
    //   112	135	107	java/lang/Exception
    //   66	77	195	java/lang/Exception
    //   77	86	195	java/lang/Exception
    //   183	192	195	java/lang/Exception
  }
  
  private void bШШШШШШ0428042804280428(String paramString)
  {
    try
    {
      if (!this.bьь044Cьь044Cь044C044C.bэ044D044Dэ044Dэ044D044Dэ044D()) {
        break label176;
      }
      this.bьь044Cьь044Cь044C044C.b044D044D044Dэ044Dэ044D044Dэ044D(paramString, this.b044Cь044C044C044Cьь044C044C.bь044C044C044C044Cьь044Cь.b0424Ф0424042404240424Ф04240424Ф(paramString, gguuuu.bк043Aккк043Aкк043A043A("\033.5+!\f%45$+.4.\r7>", 'V', '', '\001')), this.b044Cь044C044C044Cьь044C044C.bь044C044C044C044Cьь044Cь.bФ04240424042404240424Ф04240424Ф(paramString), this.b044Cь044C044C044Cьь044C044C.bь044C044C044C044Cьь044Cь.bФ04240424Ф04240424Ф04240424Ф(paramString));
    }
    catch (Exception paramString)
    {
      try
      {
        if (paramString.bэ044D044Dэ044Dэ044D044Dэ044D())
        {
          paramString = bь044Cьь044Cьь044C044C;
          if ((b044C044C044Cьь044Cь044C044C + b044Cьь044Cь044Cь044C044C) * b044C044C044Cьь044Cь044C044C % bШ04280428ШШ0428Ш042804280428() != bььь044Cь044Cь044C044C)
          {
            b044C044C044Cьь044Cь044C044C = 86;
            bььь044Cь044Cь044C044C = 97;
          }
          i = b044C044C044Cьь044Cь044C044C;
          j = b044Cьь044Cь044Cь044C044C;
          k = bь044Cь044Cь044Cь044C044C;
        }
        switch (i * (j + i) % k)
        {
        case 0: 
          b044C044C044Cьь044Cь044C044C = 14;
          bььь044Cь044Cь044C044C = b042804280428ШШ0428Ш042804280428();
          xtxtxt.bии0438043804380438и0438ии(paramString, gguuuu.bккккк043Aкк043A043A("Cc\023Sdi]Q:Q^]JOPTL)QV\001UQJ|BMIFw:I9Gsq41=\tAk@:57(*d-0#(%l", '\013', '\005'));
          label176:
          return;
        }
      }
      catch (Exception paramString)
      {
        throw paramString;
      }
      paramString = paramString;
      throw paramString;
    }
    paramString = this.bьь044Cьь044Cь044C044C;
    for (;;)
    {
      int i;
      int j;
      int k;
      switch (1)
      {
      }
      for (;;)
      {
        switch (0)
        {
        }
      }
    }
  }
  
  public void b042804280428Ш04280428Ш042804280428(String paramString)
  {
    Object localObject = bь044Cьь044Cьь044C044C;
    StringBuilder localStringBuilder = new StringBuilder().append(gguuuu.bк043Aккк043Aкк043A043A("4(14<,\025>6?5=:4\037=68F\036C8?>M\025{OCLOWKQK\005USLN\\\013UZOVUd\022\\Z\025]i]Zn`n\035rgao<#", 'ê', '©', '\001'));
    int i = this.b044Cьььь044Cь044C044C;
    int j = b044C044C044Cьь044Cь044C044C;
    switch (j * (b044Cьь044Cь044Cь044C044C + j) % bь044Cь044Cь044Cь044C044C)
    {
    default: 
      b044C044C044Cьь044Cь044C044C = 26;
      bььь044Cь044Cь044C044C = 44;
    }
    localStringBuilder = localStringBuilder.append(i);
    i = b042804280428ШШ0428Ш042804280428();
    switch (i * (b0428Ш0428ШШ0428Ш042804280428() + i) % bь044Cь044Cь044Cь044C044C)
    {
    default: 
      b044C044C044Cьь044Cь044C044C = b042804280428ШШ0428Ш042804280428();
      bььь044Cь044Cь044C044C = 84;
    }
    xtxtxt.bии0438и04380438и0438ии((String)localObject, localStringBuilder.toString());
    localObject = ykykky.bШШ0428Ш0428ШШШ04280428();
    switch (0)
    {
    case 1: 
    default: 
      for (;;)
      {
        switch (0)
        {
        }
      }
    }
    ((ykykky)localObject).b04280428ШШ0428ШШШ04280428().bь044Cь044C044Cьь044Cь.b044Dээ044Dээ044Dэээ(paramString).b04380438и0438ии0438иии(new ykykyy.3(this, paramString)).b0438ии0438ии0438иии();
  }
  
  public void b04280428ШШШШ0428042804280428(String paramString1, String paramString2, String paramString3, String paramString4, boolean paramBoolean, ykykyy.yjjyyy paramYjjyyy)
  {
    try
    {
      localMessage = Message.obtain();
      localBundle = new Bundle();
      localMessage.arg1 = 1;
      if ((b044C044C044Cьь044Cь044C044C + b044Cьь044Cь044Cь044C044C) * b044C044C044Cьь044Cь044C044C % bь044Cь044Cь044Cь044C044C != bььь044Cь044Cь044C044C)
      {
        b044C044C044Cьь044Cь044C044C = 44;
        bььь044Cь044Cь044C044C = 41;
      }
    }
    catch (Exception paramString1)
    {
      Message localMessage;
      Bundle localBundle;
      String str;
      int i;
      int j;
      int k;
      int m;
      int n;
      throw paramString1;
    }
    try
    {
      str = gguuuu.bккккк043Aкк043A043A("#2 ,!\005\037", '¾', '\005');
      localBundle.putString(str, paramString1);
      localBundle.putString(gguuuu.bккккк043Aкк043A043A(">*:.+9\r'", '', '\003'), paramString2);
      localBundle.putString(gguuuu.bккккк043Aкк043A043A("PLB", '¤', '\005'), paramString3);
      localBundle.putString(gguuuu.bк043Aккк043Aкк043A043A("khvymrp", 'O', 'Ö', '\000'), paramString4);
      localBundle.putBoolean(gguuuu.bккккк043Aкк043A043A("BE8=:\032EA>\0230;2>,", 'S', '\003'), paramBoolean);
      localMessage.setData(localBundle);
      i = bь044Cь044C044Cьь044C044C;
      bь044Cь044C044Cьь044C044C = i + 1;
      localMessage.arg2 = i;
      paramString1 = this.b044C044C044C044C044Cьь044C044C;
    }
    catch (Exception paramString1)
    {
      throw paramString1;
    }
    paramString1.put(i, paramYjjyyy);
    bШШ04280428Ш0428Ш04280428Ш(localMessage);
    i = b044C044C044Cьь044Cь044C044C;
    j = b044Cьь044Cь044Cь044C044C;
    k = b044C044C044Cьь044Cь044C044C;
    m = bь044Cь044Cь044Cь044C044C;
    n = bььь044Cь044Cь044C044C;
    if ((i + j) * k % m != n)
    {
      b044C044C044Cьь044Cь044C044C = 1;
      bььь044Cь044Cь044C044C = 51;
    }
    return;
    switch (1)
    {
    }
    for (;;)
    {
      switch (1)
      {
      }
    }
  }
  
  public void b0428Ш0428Ш04280428Ш042804280428(String paramString1, String paramString2, String paramString3, String paramString4, long paramLong1, long paramLong2, ykykyy.yjjyyy paramYjjyyy)
  {
    xddxxx localXddxxx = this.b044Cь044C044C044Cьь044C044C.bь044Cь044C044Cьь044Cь.bээ044Dэээ044Dэээ(paramLong2);
    paramString1 = new ykykyy.2(this, paramString1, paramString2, paramString4, paramLong1, paramLong2, paramString3, paramYjjyyy);
    switch (0)
    {
    case 1: 
    default: 
      for (;;)
      {
        switch (0)
        {
        }
      }
    }
    paramString1 = localXddxxx.b04380438и0438ии0438иии(paramString1);
    int i = b044C044C044Cьь044Cь044C044C;
    switch (i * (b0428Ш0428ШШ0428Ш042804280428() + i) % bь044Cь044Cь044Cь044C044C)
    {
    default: 
      b044C044C044Cьь044Cь044C044C = b042804280428ШШ0428Ш042804280428();
      bььь044Cь044Cь044C044C = 63;
    }
    paramString1.b0438ии0438ии0438иии();
    if ((b044C044C044Cьь044Cь044C044C + b044Cьь044Cь044Cь044C044C) * b044C044C044Cьь044Cь044C044C % bь044Cь044Cь044Cь044C044C != bььь044Cь044Cь044C044C)
    {
      switch (0)
      {
      case 1: 
      default: 
        for (;;)
        {
          switch (0)
          {
          }
        }
      }
      b044C044C044Cьь044Cь044C044C = 6;
      bььь044Cь044Cь044C044C = b042804280428ШШ0428Ш042804280428();
    }
  }
  
  public void b0428ШШШ04280428ШШ04280428(Intent paramIntent, BackgroundActionsService.ykyyky paramYkyyky)
  {
    int i = 5;
    try
    {
      for (;;)
      {
        int j = i / 0;
        int k = b044C044C044Cьь044Cь044C044C;
        i = j;
        switch (k * (b0428Ш0428ШШ0428Ш042804280428() + k) % bь044Cь044Cь044Cь044C044C)
        {
        }
        b044C044C044Cьь044Cь044C044C = 72;
        bььь044Cь044Cь044C044C = b042804280428ШШ0428Ш042804280428();
        i = j;
      }
      String str;
      StringBuilder localStringBuilder;
      bШШ0428ШШШ0428042804280428(paramIntent, paramYkyyky);
    }
    catch (Exception localException)
    {
      b044C044C044Cьь044Cь044C044C = b042804280428ШШ0428Ш042804280428();
      i = paramIntent.getIntExtra(gguuuu.bккккк043Aкк043A043A("k}xuc`txnb", '}', '\002'), -1);
      str = bь044Cьь044Cьь044C044C;
      localStringBuilder = new StringBuilder();
      switch (0)
      {
      case 1: 
      default: 
        for (;;)
        {
          switch (0)
          {
          }
        }
      }
      xtxtxt.bии0438и04380438и0438ии(str, gguuuu.bк043Aккк043Aкк043A043A("`cukrrKxvu\\o}\003vqtJ1\001x\f5wz\r\003\n\n<\004\016\022@\025\b\026\033\017\n\rVI~%\035\023NlP", '6', 'Ç', '\003') + i);
      if (i == -1)
      {
        xtxtxt.b0438и0438и04380438и0438ии(bь044Cьь044Cьь044C044C, gguuuu.bккккк043Aкк043A043A("\016\021#\031  x&$#\n\035+0$\037\"w^2&%(-;++g=C;1lz}p\0254BCEKwILJ?BCCXKWL\005GJ\\RYY", '9', '\001'));
        paramYkyyky.b0428042804280428Ш0428ШШ04280428(paramIntent.getStringExtra(gguuuu.bк043Aккк043Aкк043A043A("@3AF:583:NKJ:9=N>LC?JF", ' ', 'ª', '\003')));
        return;
        b0428ШШШ04280428Ш042804280428(paramIntent, paramYkyyky);
        return;
        switch (1)
        {
        case 0: 
        default: 
          for (;;)
          {
            switch (0)
            {
            }
          }
        }
        bШ04280428Ш04280428Ш042804280428(paramIntent, paramYkyyky);
        return;
      }
      switch (i)
      {
      case 2: 
      case 3: 
      default: 
        
      }
    }
  }
  
  public String bШ0428ШШ04280428Ш042804280428()
  {
    try
    {
      localStringBuilder = new StringBuilder();
      localIterator = this.b044C044Cььь044Cь044C044C.iterator();
      boolean bool = localIterator.hasNext();
      if (bool)
      {
        if ((b044C044C044Cьь044Cь044C044C + b044Cьь044Cь044Cь044C044C) * b044C044C044Cьь044Cь044C044C % bь044Cь044Cь044Cь044C044C != bььь044Cь044Cь044C044C)
        {
          b044C044C044Cьь044Cь044C044C = b042804280428ШШ0428Ш042804280428();
          bььь044Cь044Cь044C044C = b042804280428ШШ0428Ш042804280428();
        }
        i = b044C044C044Cьь044Cь044C044C;
        switch (i * (b044Cьь044Cь044Cь044C044C + i) % bШ04280428ШШ0428Ш042804280428())
        {
        default: 
          b044C044C044Cьь044Cь044C044C = 38;
          bььь044Cь044Cь044C044C = b042804280428ШШ0428Ш042804280428();
        }
        switch (1)
        {
        case 0: 
        default: 
          for (;;)
          {
            switch (0)
            {
            }
          }
        }
      }
    }
    catch (Exception localException1)
    {
      try
      {
        StringBuilder localStringBuilder;
        Iterator localIterator;
        jyyjyy localJyyjyy = (jyyjyy)localIterator.next();
        localStringBuilder.append(localJyyjyy.bШ04280428Ш042804280428042804280428());
        localStringBuilder.append(gguuuu.bккккк043Aкк043A043A("\023", 'å', '\000'));
      }
      catch (Exception localException2)
      {
        int i;
        String str;
        throw localException2;
      }
      localException1 = localException1;
      throw localException1;
    }
    i = localException1.length();
    if (i > 0)
    {
      str = localException1.substring(0, localException1.length() - 1);
      return str;
    }
    return "";
  }
  
  /* Error */
  public boolean bШ0428ШШ04280428ШШ04280428()
  {
    // Byte code:
    //   0: getstatic 232	kkkkkk/ykykyy:b044C044C044Cьь044Cь044C044C	I
    //   3: getstatic 234	kkkkkk/ykykyy:b044Cьь044Cь044Cь044C044C	I
    //   6: iadd
    //   7: getstatic 232	kkkkkk/ykykyy:b044C044C044Cьь044Cь044C044C	I
    //   10: imul
    //   11: getstatic 236	kkkkkk/ykykyy:bь044Cь044Cь044Cь044C044C	I
    //   14: irem
    //   15: getstatic 242	kkkkkk/ykykyy:bььь044Cь044Cь044C044C	I
    //   18: if_icmpeq +14 -> 32
    //   21: invokestatic 240	kkkkkk/ykykyy:b042804280428ШШ0428Ш042804280428	()I
    //   24: putstatic 232	kkkkkk/ykykyy:b044C044C044Cьь044Cь044C044C	I
    //   27: bipush 33
    //   29: putstatic 242	kkkkkk/ykykyy:bььь044Cь044Cь044C044C	I
    //   32: aload_0
    //   33: invokespecial 1083	kkkkkk/ykykyy:b04280428ШШ04280428Ш042804280428	()Z
    //   36: istore 6
    //   38: getstatic 232	kkkkkk/ykykyy:b044C044C044Cьь044Cь044C044C	I
    //   41: istore_1
    //   42: getstatic 234	kkkkkk/ykykyy:b044Cьь044Cь044Cь044C044C	I
    //   45: istore_2
    //   46: getstatic 232	kkkkkk/ykykyy:b044C044C044Cьь044Cь044C044C	I
    //   49: istore_3
    //   50: getstatic 236	kkkkkk/ykykyy:bь044Cь044Cь044Cь044C044C	I
    //   53: istore 4
    //   55: getstatic 242	kkkkkk/ykykyy:bььь044Cь044Cь044C044C	I
    //   58: istore 5
    //   60: iload_1
    //   61: iload_2
    //   62: iadd
    //   63: iload_3
    //   64: imul
    //   65: iload 4
    //   67: irem
    //   68: iload 5
    //   70: if_icmpeq +32 -> 102
    //   73: bipush 94
    //   75: putstatic 232	kkkkkk/ykykyy:b044C044C044Cьь044Cь044C044C	I
    //   78: invokestatic 240	kkkkkk/ykykyy:b042804280428ШШ0428Ш042804280428	()I
    //   81: putstatic 242	kkkkkk/ykykyy:bььь044Cь044Cь044C044C	I
    //   84: iload 6
    //   86: ireturn
    //   87: astore 7
    //   89: aload 7
    //   91: athrow
    //   92: astore 7
    //   94: aload 7
    //   96: athrow
    //   97: astore 7
    //   99: aload 7
    //   101: athrow
    //   102: iload 6
    //   104: ireturn
    // Local variable table:
    //   start	length	slot	name	signature
    //   0	105	0	this	ykykyy
    //   41	22	1	i	int
    //   45	18	2	j	int
    //   49	16	3	k	int
    //   53	15	4	m	int
    //   58	13	5	n	int
    //   36	67	6	bool	boolean
    //   87	3	7	localException1	Exception
    //   92	3	7	localException2	Exception
    //   97	3	7	localException3	Exception
    // Exception table:
    //   from	to	target	type
    //   32	38	87	java/lang/Exception
    //   73	84	92	java/lang/Exception
    //   89	92	92	java/lang/Exception
    //   38	60	97	java/lang/Exception
  }
  
  /* Error */
  public void bШШШШ04280428Ш042804280428(String paramString1, String paramString2, String paramString3, long paramLong1, long paramLong2, ykykyy.jyjyyy paramJyjyyy)
  {
    // Byte code:
    //   0: new 272	android/os/Message
    //   3: dup
    //   4: invokespecial 838	android/os/Message:<init>	()V
    //   7: astore 9
    //   9: new 286	android/os/Bundle
    //   12: dup
    //   13: invokespecial 1001	android/os/Bundle:<init>	()V
    //   16: astore 10
    //   18: aload 9
    //   20: iconst_2
    //   21: putfield 1004	android/os/Message:arg1	I
    //   24: aload 10
    //   26: ldc_w 1085
    //   29: sipush 202
    //   32: iconst_1
    //   33: invokestatic 284	kkkkkk/gguuuu:bккккк043Aкк043A043A	(Ljava/lang/String;CC)Ljava/lang/String;
    //   36: aload_1
    //   37: invokevirtual 1009	android/os/Bundle:putString	(Ljava/lang/String;Ljava/lang/String;)V
    //   40: aload 10
    //   42: ldc_w 1087
    //   45: sipush 226
    //   48: sipush 211
    //   51: iconst_2
    //   52: invokestatic 383	kkkkkk/gguuuu:bк043Aккк043Aкк043A043A	(Ljava/lang/String;CCC)Ljava/lang/String;
    //   55: aload_2
    //   56: invokevirtual 1009	android/os/Bundle:putString	(Ljava/lang/String;Ljava/lang/String;)V
    //   59: aload 10
    //   61: ldc_w 1089
    //   64: sipush 151
    //   67: sipush 162
    //   70: iconst_2
    //   71: invokestatic 383	kkkkkk/gguuuu:bк043Aккк043Aкк043A043A	(Ljava/lang/String;CCC)Ljava/lang/String;
    //   74: aload_3
    //   75: invokevirtual 1009	android/os/Bundle:putString	(Ljava/lang/String;Ljava/lang/String;)V
    //   78: aload 10
    //   80: ldc_w 1091
    //   83: sipush 236
    //   86: bipush 14
    //   88: iconst_1
    //   89: invokestatic 383	kkkkkk/gguuuu:bк043Aккк043Aкк043A043A	(Ljava/lang/String;CCC)Ljava/lang/String;
    //   92: lload 6
    //   94: invokevirtual 1095	android/os/Bundle:putLong	(Ljava/lang/String;J)V
    //   97: aload 10
    //   99: ldc_w 1097
    //   102: sipush 208
    //   105: iconst_3
    //   106: invokestatic 284	kkkkkk/gguuuu:bккккк043Aкк043A043A	(Ljava/lang/String;CC)Ljava/lang/String;
    //   109: lload 4
    //   111: invokevirtual 1095	android/os/Bundle:putLong	(Ljava/lang/String;J)V
    //   114: aload 9
    //   116: aload 10
    //   118: invokevirtual 1025	android/os/Message:setData	(Landroid/os/Bundle;)V
    //   121: aload_0
    //   122: getfield 154	kkkkkk/ykykyy:bь044C044C044C044Cьь044C044C	Landroid/support/v4/util/LongSparseArray;
    //   125: lload 6
    //   127: invokevirtual 1100	android/support/v4/util/LongSparseArray:get	(J)Ljava/lang/Object;
    //   130: ifnonnull +153 -> 283
    //   133: getstatic 140	kkkkkk/ykykyy:bь044Cьь044Cьь044C044C	Ljava/lang/String;
    //   136: astore_1
    //   137: getstatic 232	kkkkkk/ykykyy:b044C044C044Cьь044Cь044C044C	I
    //   140: getstatic 234	kkkkkk/ykykyy:b044Cьь044Cь044Cь044C044C	I
    //   143: iadd
    //   144: getstatic 232	kkkkkk/ykykyy:b044C044C044Cьь044Cь044C044C	I
    //   147: imul
    //   148: getstatic 236	kkkkkk/ykykyy:bь044Cь044Cь044Cь044C044C	I
    //   151: irem
    //   152: getstatic 242	kkkkkk/ykykyy:bььь044Cь044Cь044C044C	I
    //   155: if_icmpeq +14 -> 169
    //   158: invokestatic 240	kkkkkk/ykykyy:b042804280428ШШ0428Ш042804280428	()I
    //   161: putstatic 232	kkkkkk/ykykyy:b044C044C044Cьь044Cь044C044C	I
    //   164: bipush 29
    //   166: putstatic 242	kkkkkk/ykykyy:bььь044Cь044Cь044C044C	I
    //   169: aload_1
    //   170: ldc_w 1102
    //   173: bipush 122
    //   175: bipush 45
    //   177: iconst_3
    //   178: invokestatic 383	kkkkkk/gguuuu:bк043Aккк043Aкк043A043A	(Ljava/lang/String;CCC)Ljava/lang/String;
    //   181: invokestatic 327	kkkkkk/xtxtxt:bии0438и04380438и0438ии	(Ljava/lang/String;Ljava/lang/String;)V
    //   184: aload_0
    //   185: getfield 154	kkkkkk/ykykyy:bь044C044C044C044Cьь044C044C	Landroid/support/v4/util/LongSparseArray;
    //   188: lload 6
    //   190: aload 8
    //   192: invokevirtual 1105	android/support/v4/util/LongSparseArray:put	(JLjava/lang/Object;)V
    //   195: aload_0
    //   196: aload 9
    //   198: invokevirtual 1032	kkkkkk/ykykyy:bШШ04280428Ш0428Ш04280428Ш	(Landroid/os/Message;)V
    //   201: iconst_1
    //   202: tableswitch	default:+22->224, 0:+-1->201, 1:+49->251
    //   224: iconst_0
    //   225: tableswitch	default:+23->248, 0:+26->251, 1:+-24->201
    //   248: goto -24 -> 224
    //   251: getstatic 232	kkkkkk/ykykyy:b044C044C044Cьь044Cь044C044C	I
    //   254: getstatic 234	kkkkkk/ykykyy:b044Cьь044Cь044Cь044C044C	I
    //   257: iadd
    //   258: getstatic 232	kkkkkk/ykykyy:b044C044C044Cьь044Cь044C044C	I
    //   261: imul
    //   262: getstatic 236	kkkkkk/ykykyy:bь044Cь044Cь044Cь044C044C	I
    //   265: irem
    //   266: invokestatic 488	kkkkkk/ykykyy:bШШ0428ШШ0428Ш042804280428	()I
    //   269: if_icmpeq +13 -> 282
    //   272: bipush 94
    //   274: putstatic 232	kkkkkk/ykykyy:b044C044C044Cьь044Cь044C044C	I
    //   277: bipush 29
    //   279: putstatic 242	kkkkkk/ykykyy:bььь044Cь044Cь044C044C	I
    //   282: return
    //   283: getstatic 140	kkkkkk/ykykyy:bь044Cьь044Cьь044C044C	Ljava/lang/String;
    //   286: ldc_w 1107
    //   289: sipush 209
    //   292: iconst_1
    //   293: invokestatic 284	kkkkkk/gguuuu:bккккк043Aкк043A043A	(Ljava/lang/String;CC)Ljava/lang/String;
    //   296: invokestatic 327	kkkkkk/xtxtxt:bии0438и04380438и0438ии	(Ljava/lang/String;Ljava/lang/String;)V
    //   299: aload_0
    //   300: getfield 154	kkkkkk/ykykyy:bь044C044C044C044Cьь044C044C	Landroid/support/v4/util/LongSparseArray;
    //   303: lload 6
    //   305: aload 8
    //   307: invokevirtual 1105	android/support/v4/util/LongSparseArray:put	(JLjava/lang/Object;)V
    //   310: return
    //   311: astore_1
    //   312: aload_1
    //   313: athrow
    //   314: astore_1
    //   315: aload_1
    //   316: athrow
    // Local variable table:
    //   start	length	slot	name	signature
    //   0	317	0	this	ykykyy
    //   0	317	1	paramString1	String
    //   0	317	2	paramString2	String
    //   0	317	3	paramString3	String
    //   0	317	4	paramLong1	long
    //   0	317	6	paramLong2	long
    //   0	317	8	paramJyjyyy	ykykyy.jyjyyy
    //   7	190	9	localMessage	Message
    //   16	101	10	localBundle	Bundle
    // Exception table:
    //   from	to	target	type
    //   59	78	311	java/lang/Exception
    //   283	310	311	java/lang/Exception
    //   0	59	314	java/lang/Exception
    //   78	137	314	java/lang/Exception
    //   169	201	314	java/lang/Exception
  }
}
