package kkkkkk;

import android.content.Context;

public class ykykky
{
  public static ykykky b044C044C044C044C044C044Cьь044C;
  public static int b044C044Cьььь044Cь044C = 2;
  public static int b044Cььььь044Cь044C = 41;
  public static int bь044Cьььь044Cь044C = 1;
  public static int bьь044Cььь044Cь044C;
  public kkyykk bьььььь044Cь044C;
  
  public ykykky() {}
  
  public static int b0428042804280428ШШШШ04280428()
  {
    return 0;
  }
  
  public static int b0428ШШШ0428ШШШ04280428()
  {
    return 75;
  }
  
  /* Error */
  private void bШ04280428Ш0428ШШШ04280428()
  {
    // Byte code:
    //   0: aload_0
    //   1: getfield 29	kkkkkk/ykykky:bьььььь044Cь044C	Lkkkkkk/kkyykk;
    //   4: astore_2
    //   5: aload_2
    //   6: ifnonnull +104 -> 110
    //   9: new 31	kkkkkk/kkyykk
    //   12: dup
    //   13: invokespecial 32	kkkkkk/kkyykk:<init>	()V
    //   16: astore_2
    //   17: getstatic 34	kkkkkk/ykykky:b044Cььььь044Cь044C	I
    //   20: istore_1
    //   21: iload_1
    //   22: getstatic 36	kkkkkk/ykykky:bь044Cьььь044Cь044C	I
    //   25: iload_1
    //   26: iadd
    //   27: imul
    //   28: getstatic 38	kkkkkk/ykykky:b044C044Cьььь044Cь044C	I
    //   31: irem
    //   32: tableswitch	default:+91->123, 0:+31->63
    //   52: bipush 19
    //   54: putstatic 34	kkkkkk/ykykky:b044Cььььь044Cь044C	I
    //   57: invokestatic 40	kkkkkk/ykykky:b0428ШШШ0428ШШШ04280428	()I
    //   60: putstatic 36	kkkkkk/ykykky:bь044Cьььь044Cь044C	I
    //   63: aload_0
    //   64: aload_2
    //   65: putfield 29	kkkkkk/ykykky:bьььььь044Cь044C	Lkkkkkk/kkyykk;
    //   68: getstatic 34	kkkkkk/ykykky:b044Cььььь044Cь044C	I
    //   71: istore_1
    //   72: iload_1
    //   73: getstatic 36	kkkkkk/ykykky:bь044Cьььь044Cь044C	I
    //   76: iload_1
    //   77: iadd
    //   78: imul
    //   79: getstatic 38	kkkkkk/ykykky:b044C044Cьььь044Cь044C	I
    //   82: irem
    //   83: tableswitch	default:+17->100, 0:+27->110
    //   100: bipush 80
    //   102: putstatic 34	kkkkkk/ykykky:b044Cььььь044Cь044C	I
    //   105: bipush 78
    //   107: putstatic 36	kkkkkk/ykykky:bь044Cьььь044Cь044C	I
    //   110: return
    //   111: astore_2
    //   112: aload_2
    //   113: athrow
    //   114: astore_2
    //   115: aload_2
    //   116: athrow
    //   117: astore_2
    //   118: aload_2
    //   119: athrow
    //   120: astore_2
    //   121: aload_2
    //   122: athrow
    //   123: goto -71 -> 52
    // Local variable table:
    //   start	length	slot	name	signature
    //   0	126	0	this	ykykky
    //   20	59	1	i	int
    //   4	61	2	localKkyykk	kkyykk
    //   111	2	2	localException1	Exception
    //   114	2	2	localException2	Exception
    //   117	2	2	localException3	Exception
    //   120	2	2	localException4	Exception
    // Exception table:
    //   from	to	target	type
    //   0	5	111	java/lang/Exception
    //   63	68	111	java/lang/Exception
    //   112	114	114	java/lang/Exception
    //   118	120	114	java/lang/Exception
    //   9	17	117	java/lang/Exception
    //   17	52	120	java/lang/Exception
    //   52	63	120	java/lang/Exception
  }
  
  public static int bШ0428ШШ0428ШШШ04280428()
  {
    return 1;
  }
  
  public static ykykky bШШ0428Ш0428ШШШ04280428()
  {
    if (b044C044C044C044C044C044Cьь044C == null) {}
    try
    {
      if (b044C044C044C044C044C044Cьь044C == null) {
        b044C044C044C044C044C044Cьь044C = new ykykky();
      }
      ykykky localYkykky = b044C044C044C044C044C044Cьь044C;
      switch (0)
      {
      case 1: 
      default: 
        for (;;)
        {
          switch (1)
          {
          }
        }
      }
      return localYkykky;
    }
    finally {}
  }
  
  /* Error */
  public boolean b042804280428Ш0428ШШШ04280428()
  {
    // Byte code:
    //   0: getstatic 34	kkkkkk/ykykky:b044Cььььь044Cь044C	I
    //   3: istore_1
    //   4: invokestatic 50	kkkkkk/ykykky:bШ0428ШШ0428ШШШ04280428	()I
    //   7: istore_2
    //   8: getstatic 38	kkkkkk/ykykky:b044C044Cьььь044Cь044C	I
    //   11: istore_3
    //   12: iload_1
    //   13: iload_2
    //   14: iload_1
    //   15: iadd
    //   16: imul
    //   17: iload_3
    //   18: irem
    //   19: tableswitch	default:+17->36, 0:+29->48
    //   36: invokestatic 40	kkkkkk/ykykky:b0428ШШШ0428ШШШ04280428	()I
    //   39: putstatic 34	kkkkkk/ykykky:b044Cььььь044Cь044C	I
    //   42: invokestatic 40	kkkkkk/ykykky:b0428ШШШ0428ШШШ04280428	()I
    //   45: putstatic 52	kkkkkk/ykykky:bьь044Cььь044Cь044C	I
    //   48: aload_0
    //   49: getfield 29	kkkkkk/ykykky:bьььььь044Cь044C	Lkkkkkk/kkyykk;
    //   52: astore 5
    //   54: aload 5
    //   56: invokevirtual 55	kkkkkk/kkyykk:b0428ШШШ042804280428ШШ0428	()Z
    //   59: istore 4
    //   61: getstatic 34	kkkkkk/ykykky:b044Cььььь044Cь044C	I
    //   64: getstatic 36	kkkkkk/ykykky:bь044Cьььь044Cь044C	I
    //   67: iadd
    //   68: getstatic 34	kkkkkk/ykykky:b044Cььььь044Cь044C	I
    //   71: imul
    //   72: getstatic 38	kkkkkk/ykykky:b044C044Cьььь044Cь044C	I
    //   75: irem
    //   76: getstatic 52	kkkkkk/ykykky:bьь044Cььь044Cь044C	I
    //   79: if_icmpeq +14 -> 93
    //   82: bipush 13
    //   84: putstatic 34	kkkkkk/ykykky:b044Cььььь044Cь044C	I
    //   87: invokestatic 40	kkkkkk/ykykky:b0428ШШШ0428ШШШ04280428	()I
    //   90: putstatic 52	kkkkkk/ykykky:bьь044Cььь044Cь044C	I
    //   93: iload 4
    //   95: ireturn
    //   96: astore 5
    //   98: aload 5
    //   100: athrow
    //   101: astore 5
    //   103: aload 5
    //   105: athrow
    //   106: astore 5
    //   108: aload 5
    //   110: athrow
    //   111: astore 5
    //   113: aload 5
    //   115: athrow
    // Local variable table:
    //   start	length	slot	name	signature
    //   0	116	0	this	ykykky
    //   3	14	1	i	int
    //   7	9	2	j	int
    //   11	8	3	k	int
    //   59	35	4	bool	boolean
    //   52	3	5	localKkyykk	kkyykk
    //   96	3	5	localException1	Exception
    //   101	3	5	localException2	Exception
    //   106	3	5	localException3	Exception
    //   111	3	5	localException4	Exception
    // Exception table:
    //   from	to	target	type
    //   48	54	96	java/lang/Exception
    //   36	48	101	java/lang/Exception
    //   98	101	101	java/lang/Exception
    //   108	111	101	java/lang/Exception
    //   54	61	106	java/lang/Exception
    //   0	12	111	java/lang/Exception
  }
  
  public kkyykk b04280428ШШ0428ШШШ04280428()
  {
    switch (0)
    {
    case 1: 
    default: 
      for (;;)
      {
        switch (1)
        {
        }
      }
    }
    int i = b044Cььььь044Cь044C;
    switch (i * (bь044Cьььь044Cь044C + i) % b044C044Cьььь044Cь044C)
    {
    default: 
      b044Cььььь044Cь044C = b0428ШШШ0428ШШШ04280428();
      bьь044Cььь044Cь044C = b0428ШШШ0428ШШШ04280428();
    }
    return this.bьььььь044Cь044C;
  }
  
  public void b0428Ш0428Ш0428ШШШ04280428(Context paramContext, kyykky paramKyykky, vovoov paramVovoov)
  {
    switch (0)
    {
    case 1: 
    default: 
      for (;;)
      {
        switch (0)
        {
        }
      }
    }
    try
    {
      bШ04280428Ш0428ШШШ04280428();
      this.bьььььь044Cь044C.bШШШШ042804280428ШШ0428(paramContext, paramKyykky, paramVovoov);
      switch (0)
      {
      case 1: 
      default: 
        for (;;)
        {
          switch (1)
          {
          }
        }
      }
      return;
    }
    finally
    {
      paramContext = finally;
      throw paramContext;
    }
  }
  
  /* Error */
  public void b0428ШШ04280428ШШШ04280428(ovooov paramOvooov)
  {
    // Byte code:
    //   0: getstatic 34	kkkkkk/ykykky:b044Cььььь044Cь044C	I
    //   3: istore_2
    //   4: getstatic 36	kkkkkk/ykykky:bь044Cьььь044Cь044C	I
    //   7: istore_3
    //   8: getstatic 34	kkkkkk/ykykky:b044Cььььь044Cь044C	I
    //   11: istore 4
    //   13: getstatic 38	kkkkkk/ykykky:b044C044Cьььь044Cь044C	I
    //   16: istore 5
    //   18: invokestatic 68	kkkkkk/ykykky:b0428042804280428ШШШШ04280428	()I
    //   21: istore 6
    //   23: iload_2
    //   24: iload_3
    //   25: iadd
    //   26: iload 4
    //   28: imul
    //   29: iload 5
    //   31: irem
    //   32: iload 6
    //   34: if_icmpeq +14 -> 48
    //   37: bipush 78
    //   39: putstatic 34	kkkkkk/ykykky:b044Cььььь044Cь044C	I
    //   42: invokestatic 40	kkkkkk/ykykky:b0428ШШШ0428ШШШ04280428	()I
    //   45: putstatic 52	kkkkkk/ykykky:bьь044Cььь044Cь044C	I
    //   48: getstatic 34	kkkkkk/ykykky:b044Cььььь044Cь044C	I
    //   51: istore_2
    //   52: iload_2
    //   53: getstatic 36	kkkkkk/ykykky:bь044Cьььь044Cь044C	I
    //   56: iload_2
    //   57: iadd
    //   58: imul
    //   59: getstatic 38	kkkkkk/ykykky:b044C044Cьььь044Cь044C	I
    //   62: irem
    //   63: tableswitch	default:+17->80, 0:+29->92
    //   80: invokestatic 40	kkkkkk/ykykky:b0428ШШШ0428ШШШ04280428	()I
    //   83: putstatic 34	kkkkkk/ykykky:b044Cььььь044Cь044C	I
    //   86: invokestatic 40	kkkkkk/ykykky:b0428ШШШ0428ШШШ04280428	()I
    //   89: putstatic 52	kkkkkk/ykykky:bьь044Cььь044Cь044C	I
    //   92: aload_0
    //   93: getfield 29	kkkkkk/ykykky:bьььььь044Cь044C	Lkkkkkk/kkyykk;
    //   96: astore 7
    //   98: aload 7
    //   100: aload_1
    //   101: invokevirtual 71	kkkkkk/kkyykk:b0428ШШ0428ШШШ0428Ш0428	(Lkkkkkk/ovooov;)V
    //   104: return
    //   105: astore_1
    //   106: aload_1
    //   107: athrow
    //   108: astore_1
    //   109: aload_1
    //   110: athrow
    //   111: astore_1
    //   112: aload_1
    //   113: athrow
    //   114: astore_1
    //   115: aload_1
    //   116: athrow
    // Local variable table:
    //   start	length	slot	name	signature
    //   0	117	0	this	ykykky
    //   0	117	1	paramOvooov	ovooov
    //   3	56	2	i	int
    //   7	19	3	j	int
    //   11	18	4	k	int
    //   16	16	5	m	int
    //   21	14	6	n	int
    //   96	3	7	localKkyykk	kkyykk
    // Exception table:
    //   from	to	target	type
    //   92	98	105	java/lang/Exception
    //   0	8	108	java/lang/Exception
    //   37	48	108	java/lang/Exception
    //   106	108	108	java/lang/Exception
    //   112	114	108	java/lang/Exception
    //   98	104	111	java/lang/Exception
    //   8	23	114	java/lang/Exception
  }
  
  public void bШШШ04280428ШШШ04280428(Context paramContext, kyykky paramKyykky, vvooov paramVvooov)
  {
    bШ04280428Ш0428ШШШ04280428();
    kkyykk localKkyykk = this.bьььььь044Cь044C;
    int i = b044Cььььь044Cь044C;
    switch (i * (bь044Cьььь044Cь044C + i) % b044C044Cьььь044Cь044C)
    {
    default: 
      switch (0)
      {
      case 1: 
      default: 
        for (;;)
        {
          switch (0)
          {
          }
        }
      }
      b044Cььььь044Cь044C = b0428ШШШ0428ШШШ04280428();
      bьь044Cььь044Cь044C = b0428ШШШ0428ШШШ04280428();
    }
    localKkyykk.bШШ0428Ш042804280428ШШ0428(paramContext, paramKyykky, paramVvooov);
  }
  
  public void bШШШШ0428ШШШ04280428()
  {
    if ((b044Cььььь044Cь044C + bь044Cьььь044Cь044C) * b044Cььььь044Cь044C % b044C044Cьььь044Cь044C != bьь044Cььь044Cь044C)
    {
      b044Cььььь044Cь044C = b0428ШШШ0428ШШШ04280428();
      bьь044Cььь044Cь044C = 85;
    }
    switch (0)
    {
    case 1: 
    default: 
      for (;;)
      {
        switch (0)
        {
        }
      }
    }
    this.bьььььь044Cь044C.b04280428ШШ0428042804280428Ш0428();
  }
}
