package kkkkkk;

import android.support.annotation.Nullable;
import java.io.Serializable;

public class yytyyt
  implements Serializable
{
  private static final long serialVersionUID = 2922504802431258764L;
  @Nullable
  private String b04290429042904290429ЩЩ042904290429;
  @Nullable
  private String b042904290429Щ0429ЩЩ042904290429;
  @Nullable
  private String b04290429Щ04290429ЩЩ042904290429;
  private yyyhyh b04290429ЩЩЩ0429Щ042904290429 = yyyhyh.UNHANDLED;
  @Nullable
  private String b0429Щ042904290429ЩЩ042904290429;
  @Nullable
  private String b0429ЩЩ04290429ЩЩ042904290429;
  @Nullable
  private String b0429ЩЩЩЩ0429Щ042904290429;
  private jjjjee bЩ0429042904290429ЩЩ042904290429;
  @Nullable
  private String bЩ0429Щ04290429ЩЩ042904290429;
  @Nullable
  private String bЩ0429ЩЩЩ0429Щ042904290429;
  private boolean bЩЩ042904290429ЩЩ042904290429;
  @Nullable
  private baabaa bЩЩЩ04290429ЩЩ042904290429;
  @Nullable
  private abbaba bЩЩЩЩЩ0429Щ042904290429;
  
  private yytyyt() {}
  
  public static int b043B043B043B043B043Bлл043B043Bл()
  {
    return 98;
  }
  
  public static int b043Bлллл043Bл043B043Bл()
  {
    return 2;
  }
  
  public static int bл043Bллл043Bл043B043Bл()
  {
    return 0;
  }
  
  public static int bллллл043Bл043B043Bл()
  {
    return 1;
  }
  
  public yyyhyh b043B043B043B043Bл043Bл043B043Bл()
  {
    switch (1)
    {
    case 0: 
    default: 
      for (;;)
      {
        if ((b043B043B043B043B043Bлл043B043Bл() + bллллл043Bл043B043Bл()) * b043B043B043B043B043Bлл043B043Bл() % b043Bлллл043Bл043B043Bл() != bл043Bллл043Bл043B043Bл()) {}
        switch (1)
        {
        }
      }
    }
    if ((b043B043B043B043B043Bлл043B043Bл() + bллллл043Bл043B043Bл()) * b043B043B043B043B043Bлл043B043Bл() % b043Bлллл043Bл043B043Bл() != bл043Bллл043Bл043B043Bл()) {
      switch (0)
      {
      case 1: 
      default: 
        for (;;)
        {
          switch (1)
          {
          }
        }
      }
    }
    return this.b04290429ЩЩЩ0429Щ042904290429;
  }
  
  @Nullable
  public String b043B043B043Bлл043Bл043B043Bл()
  {
    if ((b043B043B043B043B043Bлл043B043Bл() + bллллл043Bл043B043Bл()) * b043B043B043B043B043Bлл043B043Bл() % b043Bлллл043Bл043B043Bл() != bл043Bллл043Bл043B043Bл()) {}
    switch (1)
    {
    case 0: 
    default: 
      for (;;)
      {
        switch (1)
        {
        }
      }
    }
    return this.b04290429Щ04290429ЩЩ042904290429;
  }
  
  @Nullable
  public String b043B043Bл043Bл043Bл043B043Bл()
  {
    int i = b043B043B043B043B043Bлл043B043Bл();
    switch (i * (bллллл043Bл043B043Bл() + i) % b043Bлллл043Bл043B043Bл())
    {
    }
    try
    {
      String str = this.b04290429042904290429ЩЩ042904290429;
      i = b043B043B043B043B043Bлл043B043Bл();
      int j = bллллл043Bл043B043Bл();
      switch (1)
      {
      case 0: 
      default: 
        for (;;)
        {
          switch (0)
          {
          }
        }
      }
      switch (i * (j + i) % b043Bлллл043Bл043B043Bл())
      {
      }
      return str;
    }
    catch (Exception localException)
    {
      throw localException;
    }
  }
  
  @Nullable
  public String b043B043Bллл043Bл043B043Bл()
  {
    int i = b043B043B043B043B043Bлл043B043Bл();
    switch (i * (bллллл043Bл043B043Bл() + i) % b043Bлллл043Bл043B043Bл())
    {
    }
    try
    {
      String str = this.b042904290429Щ0429ЩЩ042904290429;
      return str;
    }
    catch (Exception localException)
    {
      switch (1)
      {
      case 0: 
      default: 
        for (;;)
        {
          switch (0)
          {
          }
        }
      }
      throw localException;
    }
  }
  
  @Nullable
  public String b043Bл043B043Bл043Bл043B043Bл()
  {
    String str = this.b0429ЩЩЩЩ0429Щ042904290429;
    if ((b043B043B043B043B043Bлл043B043Bл() + bллллл043Bл043B043Bл()) * b043B043B043B043B043Bлл043B043Bл() % b043Bлллл043Bл043B043Bл() != bл043Bллл043Bл043B043Bл()) {}
    return str;
  }
  
  @Nullable
  public String b043Bл043Bлл043Bл043B043Bл()
  {
    try
    {
      String str = this.b0429ЩЩ04290429ЩЩ042904290429;
      if ((b043B043B043B043B043Bлл043B043Bл() + bллллл043Bл043B043Bл()) * b043B043B043B043B043Bлл043B043Bл() % b043Bлллл043Bл043B043Bл() != bл043Bллл043Bл043B043Bл())
      {
        int i = b043B043B043B043B043Bлл043B043Bл();
        switch (i * (bллллл043Bл043B043Bл() + i) % b043Bлллл043Bл043B043Bл())
        {
        }
      }
      return str;
    }
    catch (Exception localException)
    {
      throw localException;
    }
  }
  
  /* Error */
  @Nullable
  public String b043Bлл043Bл043Bл043B043Bл()
  {
    // Byte code:
    //   0: invokestatic 53	kkkkkk/yytyyt:b043B043B043B043B043Bлл043B043Bл	()I
    //   3: istore_1
    //   4: iload_1
    //   5: invokestatic 56	kkkkkk/yytyyt:bллллл043Bл043B043Bл	()I
    //   8: iload_1
    //   9: iadd
    //   10: imul
    //   11: invokestatic 59	kkkkkk/yytyyt:b043Bлллл043Bл043B043Bл	()I
    //   14: irem
    //   15: tableswitch	default:+17->32, 0:+17->32
    //   32: invokestatic 53	kkkkkk/yytyyt:b043B043B043B043B043Bлл043B043Bл	()I
    //   35: istore_1
    //   36: invokestatic 56	kkkkkk/yytyyt:bллллл043Bл043B043Bл	()I
    //   39: istore_2
    //   40: invokestatic 59	kkkkkk/yytyyt:b043Bлллл043Bл043B043Bл	()I
    //   43: istore_3
    //   44: iload_1
    //   45: iload_2
    //   46: iload_1
    //   47: iadd
    //   48: imul
    //   49: iload_3
    //   50: irem
    //   51: tableswitch	default:+17->68, 0:+17->68
    //   68: aload_0
    //   69: getfield 81	kkkkkk/yytyyt:b0429Щ042904290429ЩЩ042904290429	Ljava/lang/String;
    //   72: astore 4
    //   74: aload 4
    //   76: areturn
    //   77: astore 4
    //   79: aload 4
    //   81: athrow
    //   82: astore 4
    //   84: aload 4
    //   86: athrow
    //   87: astore 4
    //   89: aload 4
    //   91: athrow
    // Local variable table:
    //   start	length	slot	name	signature
    //   0	92	0	this	yytyyt
    //   3	46	1	i	int
    //   39	9	2	j	int
    //   43	8	3	k	int
    //   72	3	4	str	String
    //   77	3	4	localException1	Exception
    //   82	3	4	localException2	Exception
    //   87	3	4	localException3	Exception
    // Exception table:
    //   from	to	target	type
    //   68	74	77	java/lang/Exception
    //   79	82	82	java/lang/Exception
    //   32	44	87	java/lang/Exception
  }
  
  @Nullable
  public String bл043B043B043Bл043Bл043B043Bл()
  {
    return this.bЩ0429ЩЩЩ0429Щ042904290429;
  }
  
  @Nullable
  public String bл043B043Bлл043Bл043B043Bл()
  {
    try
    {
      String str = this.bЩ0429Щ04290429ЩЩ042904290429;
      return str;
    }
    catch (Exception localException)
    {
      throw localException;
    }
  }
  
  @Nullable
  public jjjjee bл043Bл043Bл043Bл043B043Bл()
  {
    switch (0)
    {
    case 1: 
    default: 
      for (;;)
      {
        switch (1)
        {
        }
      }
    }
    switch (1)
    {
    case 0: 
    default: 
      for (;;)
      {
        switch (1)
        {
        }
      }
    }
    jjjjee localJjjjee = this.bЩ0429042904290429ЩЩ042904290429;
    if (((b043B043B043B043B043Bлл043B043Bл() + bллллл043Bл043B043Bл()) * b043B043B043B043B043Bлл043B043Bл() % b043Bлллл043Bл043B043Bл() != bл043Bллл043Bл043B043Bл()) && ((b043B043B043B043B043Bлл043B043Bл() + bллллл043Bл043B043Bл()) * b043B043B043B043B043Bлл043B043Bл() % b043Bлллл043Bл043B043Bл() != bл043Bллл043Bл043B043Bл())) {}
    return localJjjjee;
  }
  
  @Nullable
  public abbaba bлл043B043Bл043Bл043B043Bл()
  {
    return this.bЩЩЩЩЩ0429Щ042904290429;
  }
  
  @Nullable
  public baabaa bлл043Bлл043Bл043B043Bл()
  {
    baabaa localBaabaa = this.bЩЩЩ04290429ЩЩ042904290429;
    int i = b043B043B043B043B043Bлл043B043Bл();
    switch (i * (bллллл043Bл043B043Bл() + i) % b043Bлллл043Bл043B043Bл())
    {
    default: 
      switch (0)
      {
      case 1: 
      default: 
        for (;;)
        {
          switch (1)
          {
          }
        }
      }
      if ((b043B043B043B043B043Bлл043B043Bл() + bллллл043Bл043B043Bл()) * b043B043B043B043B043Bлл043B043Bл() % b043Bлллл043Bл043B043Bл() == bл043Bллл043Bл043B043Bл()) {
        break;
      }
    }
    switch (0)
    {
    case 1: 
    default: 
      for (;;)
      {
        switch (1)
        {
        }
      }
    }
    return localBaabaa;
  }
  
  public boolean bллл043Bл043Bл043B043Bл()
  {
    if ((b043B043B043B043B043Bлл043B043Bл() + bллллл043Bл043B043Bл()) * b043B043B043B043B043Bлл043B043Bл() % b043Bлллл043Bл043B043Bл() != bл043Bллл043Bл043B043Bл()) {}
    boolean bool = this.bЩЩ042904290429ЩЩ042904290429;
    if ((b043B043B043B043B043Bлл043B043Bл() + bллллл043Bл043B043Bл()) * b043B043B043B043B043Bлл043B043Bл() % b043Bлллл043Bл043B043Bл() != bл043Bллл043Bл043B043Bл()) {}
    return bool;
  }
  
  public static class ytyyyt
  {
    public static int b042904290429ЩЩ0429Щ042904290429 = 2;
    public static int b0429Щ0429ЩЩ0429Щ042904290429 = 85;
    public static int bЩ04290429ЩЩ0429Щ042904290429 = 1;
    public static int bЩЩЩ0429Щ0429Щ042904290429;
    private final yytyyt bЩЩ0429ЩЩ0429Щ042904290429 = new yytyyt(null);
    
    public ytyyyt() {}
    
    public ytyyyt(ttyytt paramTtyytt)
    {
      yytyyt.b043B043Bлл043Bлл043B043Bл(this.bЩЩ0429ЩЩ0429Щ042904290429, paramTtyytt.b043B043B043B043B043Bллл043Bл());
      yytyyt.b043B043B043Bл043Bлл043B043Bл(this.bЩЩ0429ЩЩ0429Щ042904290429, paramTtyytt.bлллл043Bллл043Bл());
      yytyyt.bллл043B043Bлл043B043Bл(this.bЩЩ0429ЩЩ0429Щ042904290429, paramTtyytt.bл043B043B043B043Bллл043Bл());
      yytyyt.b043Bлл043B043Bлл043B043Bл(this.bЩЩ0429ЩЩ0429Щ042904290429, paramTtyytt.bлл043Bл043Bллл043Bл());
      yytyyt.bл043Bл043B043Bлл043B043Bл(this.bЩЩ0429ЩЩ0429Щ042904290429, paramTtyytt.bл043Bл043B043Bллл043Bл());
      yytyyt.b043B043Bл043B043Bлл043B043Bл(this.bЩЩ0429ЩЩ0429Щ042904290429, paramTtyytt.b043B043Bл043Bлллл043Bл());
      yytyyt.bлл043B043B043Bлл043B043Bл(this.bЩЩ0429ЩЩ0429Щ042904290429, paramTtyytt.b043Bл043B043Bлллл043Bл());
      yytyyt.b043Bл043B043B043Bлл043B043Bл(this.bЩЩ0429ЩЩ0429Щ042904290429, paramTtyytt.bллл043B043Bллл043Bл());
      yytyyt.bл043B043B043B043Bлл043B043Bл(this.bЩЩ0429ЩЩ0429Щ042904290429, paramTtyytt.bл043B043B043Bлллл043Bл());
      yytyyt.bл043Bлл043Bлл043B043Bл(this.bЩЩ0429ЩЩ0429Щ042904290429, paramTtyytt.b043Bллл043Bллл043Bл());
    }
    
    public ytyyyt(yytyyt paramYytyyt)
    {
      yytyyt.b043B043Bлл043Bлл043B043Bл(this.bЩЩ0429ЩЩ0429Щ042904290429, paramYytyyt.b043B043B043B043Bл043Bл043B043Bл());
      yytyyt.b043B043B043Bл043Bлл043B043Bл(this.bЩЩ0429ЩЩ0429Щ042904290429, paramYytyyt.b043B043B043Bлл043Bл043B043Bл());
      yytyyt.bллл043B043Bлл043B043Bл(this.bЩЩ0429ЩЩ0429Щ042904290429, paramYytyyt.bл043B043B043Bл043Bл043B043Bл());
      yytyyt.b043Bлл043B043Bлл043B043Bл(this.bЩЩ0429ЩЩ0429Щ042904290429, paramYytyyt.b043Bлл043Bл043Bл043B043Bл());
      yytyyt.bл043Bл043B043Bлл043B043Bл(this.bЩЩ0429ЩЩ0429Щ042904290429, paramYytyyt.bлл043B043Bл043Bл043B043Bл());
      yytyyt.b043B043Bл043B043Bлл043B043Bл(this.bЩЩ0429ЩЩ0429Щ042904290429, paramYytyyt.bлл043Bлл043Bл043B043Bл());
      yytyyt.bлл043B043B043Bлл043B043Bл(this.bЩЩ0429ЩЩ0429Щ042904290429, paramYytyyt.b043Bл043Bлл043Bл043B043Bл());
      yytyyt.b043Bл043B043B043Bлл043B043Bл(this.bЩЩ0429ЩЩ0429Щ042904290429, paramYytyyt.b043B043Bл043Bл043Bл043B043Bл());
      yytyyt.bл043B043B043B043Bлл043B043Bл(this.bЩЩ0429ЩЩ0429Щ042904290429, paramYytyyt.bл043B043Bлл043Bл043B043Bл());
      yytyyt.bл043Bлл043Bлл043B043Bл(this.bЩЩ0429ЩЩ0429Щ042904290429, paramYytyyt.bллл043Bл043Bл043B043Bл());
      yytyyt.bлл043Bл043Bлл043B043Bл(this.bЩЩ0429ЩЩ0429Щ042904290429, paramYytyyt.bл043Bл043Bл043Bл043B043Bл());
    }
    
    public static int b043B043Bллллл043B043Bл()
    {
      return 0;
    }
    
    public static int b043Bлллллл043B043Bл()
    {
      return 44;
    }
    
    public static int bлл043Bлллл043B043Bл()
    {
      return 2;
    }
    
    public static int bллллллл043B043Bл()
    {
      return 1;
    }
    
    /* Error */
    public ytyyyt b043B043B043B043Bллл043B043Bл(String paramString)
    {
      // Byte code:
      //   0: getstatic 150	kkkkkk/yytyyt$ytyyyt:b0429Щ0429ЩЩ0429Щ042904290429	I
      //   3: getstatic 152	kkkkkk/yytyyt$ytyyyt:bЩ04290429ЩЩ0429Щ042904290429	I
      //   6: iadd
      //   7: getstatic 150	kkkkkk/yytyyt$ytyyyt:b0429Щ0429ЩЩ0429Щ042904290429	I
      //   10: imul
      //   11: getstatic 154	kkkkkk/yytyyt$ytyyyt:b042904290429ЩЩ0429Щ042904290429	I
      //   14: irem
      //   15: invokestatic 156	kkkkkk/yytyyt$ytyyyt:b043B043Bллллл043B043Bл	()I
      //   18: if_icmpeq +14 -> 32
      //   21: invokestatic 158	kkkkkk/yytyyt$ytyyyt:b043Bлллллл043B043Bл	()I
      //   24: putstatic 150	kkkkkk/yytyyt$ytyyyt:b0429Щ0429ЩЩ0429Щ042904290429	I
      //   27: bipush 77
      //   29: putstatic 160	kkkkkk/yytyyt$ytyyyt:bЩЩЩ0429Щ0429Щ042904290429	I
      //   32: aload_0
      //   33: getfield 26	kkkkkk/yytyyt$ytyyyt:bЩЩ0429ЩЩ0429Щ042904290429	Lkkkkkk/yytyyt;
      //   36: astore 5
      //   38: invokestatic 158	kkkkkk/yytyyt$ytyyyt:b043Bлллллл043B043Bл	()I
      //   41: istore_2
      //   42: getstatic 152	kkkkkk/yytyyt$ytyyyt:bЩ04290429ЩЩ0429Щ042904290429	I
      //   45: istore_3
      //   46: getstatic 154	kkkkkk/yytyyt$ytyyyt:b042904290429ЩЩ0429Щ042904290429	I
      //   49: istore 4
      //   51: iload_2
      //   52: iload_3
      //   53: iload_2
      //   54: iadd
      //   55: imul
      //   56: iload 4
      //   58: irem
      //   59: tableswitch	default:+17->76, 0:+27->86
      //   76: bipush 82
      //   78: putstatic 150	kkkkkk/yytyyt$ytyyyt:b0429Щ0429ЩЩ0429Щ042904290429	I
      //   81: bipush 16
      //   83: putstatic 160	kkkkkk/yytyyt$ytyyyt:bЩЩЩ0429Щ0429Щ042904290429	I
      //   86: aload 5
      //   88: aload_1
      //   89: invokestatic 163	kkkkkk/yytyyt:bл043B043Bл043Bлл043B043Bл	(Lkkkkkk/yytyyt;Ljava/lang/String;)Ljava/lang/String;
      //   92: pop
      //   93: aload_0
      //   94: areturn
      //   95: astore_1
      //   96: aload_1
      //   97: athrow
      //   98: astore_1
      //   99: aload_1
      //   100: athrow
      // Local variable table:
      //   start	length	slot	name	signature
      //   0	101	0	this	ytyyyt
      //   0	101	1	paramString	String
      //   41	15	2	i	int
      //   45	10	3	j	int
      //   49	10	4	k	int
      //   36	51	5	localYytyyt	yytyyt
      // Exception table:
      //   from	to	target	type
      //   32	51	95	java/lang/Exception
      //   76	86	98	java/lang/Exception
      //   86	93	98	java/lang/Exception
    }
    
    /* Error */
    public ytyyyt b043B043B043Bлллл043B043Bл(String paramString)
    {
      // Byte code:
      //   0: aload_0
      //   1: getfield 26	kkkkkk/yytyyt$ytyyyt:bЩЩ0429ЩЩ0429Щ042904290429	Lkkkkkk/yytyyt;
      //   4: aload_1
      //   5: invokestatic 80	kkkkkk/yytyyt:bлл043B043B043Bлл043B043Bл	(Lkkkkkk/yytyyt;Ljava/lang/String;)Ljava/lang/String;
      //   8: pop
      //   9: getstatic 150	kkkkkk/yytyyt$ytyyyt:b0429Щ0429ЩЩ0429Щ042904290429	I
      //   12: istore_2
      //   13: getstatic 152	kkkkkk/yytyyt$ytyyyt:bЩ04290429ЩЩ0429Щ042904290429	I
      //   16: istore_3
      //   17: getstatic 150	kkkkkk/yytyyt$ytyyyt:b0429Щ0429ЩЩ0429Щ042904290429	I
      //   20: istore 4
      //   22: getstatic 154	kkkkkk/yytyyt$ytyyyt:b042904290429ЩЩ0429Щ042904290429	I
      //   25: istore 5
      //   27: getstatic 160	kkkkkk/yytyyt$ytyyyt:bЩЩЩ0429Щ0429Щ042904290429	I
      //   30: istore 6
      //   32: iload_2
      //   33: iload_3
      //   34: iadd
      //   35: iload 4
      //   37: imul
      //   38: iload 5
      //   40: irem
      //   41: iload 6
      //   43: if_icmpeq +60 -> 103
      //   46: getstatic 150	kkkkkk/yytyyt$ytyyyt:b0429Щ0429ЩЩ0429Щ042904290429	I
      //   49: istore_2
      //   50: iload_2
      //   51: getstatic 152	kkkkkk/yytyyt$ytyyyt:bЩ04290429ЩЩ0429Щ042904290429	I
      //   54: iload_2
      //   55: iadd
      //   56: imul
      //   57: getstatic 154	kkkkkk/yytyyt$ytyyyt:b042904290429ЩЩ0429Щ042904290429	I
      //   60: irem
      //   61: tableswitch	default:+19->80, 0:+30->91
      //   80: bipush 62
      //   82: putstatic 150	kkkkkk/yytyyt$ytyyyt:b0429Щ0429ЩЩ0429Щ042904290429	I
      //   85: invokestatic 158	kkkkkk/yytyyt$ytyyyt:b043Bлллллл043B043Bл	()I
      //   88: putstatic 160	kkkkkk/yytyyt$ytyyyt:bЩЩЩ0429Щ0429Щ042904290429	I
      //   91: invokestatic 158	kkkkkk/yytyyt$ytyyyt:b043Bлллллл043B043Bл	()I
      //   94: putstatic 150	kkkkkk/yytyyt$ytyyyt:b0429Щ0429ЩЩ0429Щ042904290429	I
      //   97: invokestatic 158	kkkkkk/yytyyt$ytyyyt:b043Bлллллл043B043Bл	()I
      //   100: putstatic 160	kkkkkk/yytyyt$ytyyyt:bЩЩЩ0429Щ0429Щ042904290429	I
      //   103: aload_0
      //   104: areturn
      //   105: astore_1
      //   106: aload_1
      //   107: athrow
      //   108: astore_1
      //   109: aload_1
      //   110: athrow
      //   111: astore_1
      //   112: aload_1
      //   113: athrow
      // Local variable table:
      //   start	length	slot	name	signature
      //   0	114	0	this	ytyyyt
      //   0	114	1	paramString	String
      //   12	45	2	i	int
      //   16	19	3	j	int
      //   20	18	4	k	int
      //   25	16	5	m	int
      //   30	14	6	n	int
      // Exception table:
      //   from	to	target	type
      //   0	9	105	java/lang/Exception
      //   27	32	108	java/lang/Exception
      //   106	108	108	java/lang/Exception
      //   9	27	111	java/lang/Exception
      //   91	103	111	java/lang/Exception
    }
    
    public ytyyyt b043B043Bл043Bллл043B043Bл(String paramString)
    {
      yytyyt localYytyyt = this.bЩЩ0429ЩЩ0429Щ042904290429;
      switch (1)
      {
      case 0: 
      default: 
        for (;;)
        {
          switch (1)
          {
          }
        }
      }
      int i = b0429Щ0429ЩЩ0429Щ042904290429;
      int j = bЩ04290429ЩЩ0429Щ042904290429;
      int k = b0429Щ0429ЩЩ0429Щ042904290429;
      int m = b0429Щ0429ЩЩ0429Щ042904290429;
      switch (m * (bЩ04290429ЩЩ0429Щ042904290429 + m) % b042904290429ЩЩ0429Щ042904290429)
      {
      default: 
        b0429Щ0429ЩЩ0429Щ042904290429 = b043Bлллллл043B043Bл();
        bЩЩЩ0429Щ0429Щ042904290429 = 89;
      }
      if ((i + j) * k % b042904290429ЩЩ0429Щ042904290429 != bЩЩЩ0429Щ0429Щ042904290429)
      {
        b0429Щ0429ЩЩ0429Щ042904290429 = 61;
        bЩЩЩ0429Щ0429Щ042904290429 = 96;
      }
      yytyyt.b043Bлл043B043Bлл043B043Bл(localYytyyt, paramString);
      return this;
    }
    
    public ytyyyt b043Bл043B043Bллл043B043Bл(String paramString)
    {
      if ((b0429Щ0429ЩЩ0429Щ042904290429 + bллллллл043B043Bл()) * b0429Щ0429ЩЩ0429Щ042904290429 % b042904290429ЩЩ0429Щ042904290429 != bЩЩЩ0429Щ0429Щ042904290429)
      {
        if ((b0429Щ0429ЩЩ0429Щ042904290429 + bЩ04290429ЩЩ0429Щ042904290429) * b0429Щ0429ЩЩ0429Щ042904290429 % b042904290429ЩЩ0429Щ042904290429 != bЩЩЩ0429Щ0429Щ042904290429)
        {
          b0429Щ0429ЩЩ0429Щ042904290429 = b043Bлллллл043B043Bл();
          bЩЩЩ0429Щ0429Щ042904290429 = 79;
        }
        b0429Щ0429ЩЩ0429Щ042904290429 = 73;
        bЩЩЩ0429Щ0429Щ042904290429 = 31;
      }
      yytyyt.b043Bл043B043B043Bлл043B043Bл(this.bЩЩ0429ЩЩ0429Щ042904290429, paramString);
      switch (0)
      {
      case 1: 
      default: 
        for (;;)
        {
          switch (0)
          {
          }
        }
      }
      return this;
    }
    
    public ytyyyt b043Bл043Bлллл043B043Bл(String paramString)
    {
      if ((b0429Щ0429ЩЩ0429Щ042904290429 + bЩ04290429ЩЩ0429Щ042904290429) * b0429Щ0429ЩЩ0429Щ042904290429 % b042904290429ЩЩ0429Щ042904290429 != bЩЩЩ0429Щ0429Щ042904290429)
      {
        b0429Щ0429ЩЩ0429Щ042904290429 = b043Bлллллл043B043Bл();
        bЩЩЩ0429Щ0429Щ042904290429 = 81;
        if ((b0429Щ0429ЩЩ0429Щ042904290429 + bллллллл043B043Bл()) * b0429Щ0429ЩЩ0429Щ042904290429 % bлл043Bлллл043B043Bл() != b043B043Bллллл043B043Bл())
        {
          b0429Щ0429ЩЩ0429Щ042904290429 = 30;
          bЩЩЩ0429Щ0429Щ042904290429 = 38;
        }
      }
      switch (1)
      {
      case 0: 
      default: 
        for (;;)
        {
          switch (1)
          {
          case 0: 
          default: 
            for (;;)
            {
              switch (0)
              {
              }
            }
          }
          switch (0)
          {
          }
        }
      }
      yytyyt.b043Bл043Bл043Bлл043B043Bл(this.bЩЩ0429ЩЩ0429Щ042904290429, paramString);
      return this;
    }
    
    public ytyyyt b043Bлл043Bллл043B043Bл(String paramString)
    {
      if ((b0429Щ0429ЩЩ0429Щ042904290429 + bллллллл043B043Bл()) * b0429Щ0429ЩЩ0429Щ042904290429 % b042904290429ЩЩ0429Щ042904290429 != bЩЩЩ0429Щ0429Щ042904290429)
      {
        switch (1)
        {
        case 0: 
        default: 
          for (;;)
          {
            switch (0)
            {
            }
          }
        }
        b0429Щ0429ЩЩ0429Щ042904290429 = 98;
        bЩЩЩ0429Щ0429Щ042904290429 = b043Bлллллл043B043Bл();
      }
      yytyyt.b043B043B043Bл043Bлл043B043Bл(this.bЩЩ0429ЩЩ0429Щ042904290429, paramString);
      switch (0)
      {
      case 1: 
      default: 
        for (;;)
        {
          int i = b0429Щ0429ЩЩ0429Щ042904290429;
          switch (i * (bЩ04290429ЩЩ0429Щ042904290429 + i) % b042904290429ЩЩ0429Щ042904290429)
          {
          default: 
            b0429Щ0429ЩЩ0429Щ042904290429 = b043Bлллллл043B043Bл();
            bЩЩЩ0429Щ0429Щ042904290429 = b043Bлллллл043B043Bл();
          }
          switch (1)
          {
          }
        }
      }
      return this;
    }
    
    public ytyyyt b043Bллл043Bлл043B043Bл(yyyhyh paramYyyhyh)
    {
      try
      {
        yytyyt.b043B043Bлл043Bлл043B043Bл(this.bЩЩ0429ЩЩ0429Щ042904290429, paramYyyhyh);
        return this;
      }
      catch (Exception paramYyyhyh)
      {
        throw paramYyyhyh;
      }
    }
    
    public ytyyyt bл043B043B043Bллл043B043Bл(abbaba paramAbbaba)
    {
      yytyyt localYytyyt = this.bЩЩ0429ЩЩ0429Щ042904290429;
      if ((b0429Щ0429ЩЩ0429Щ042904290429 + bЩ04290429ЩЩ0429Щ042904290429) * b0429Щ0429ЩЩ0429Щ042904290429 % b042904290429ЩЩ0429Щ042904290429 != bЩЩЩ0429Щ0429Щ042904290429)
      {
        b0429Щ0429ЩЩ0429Щ042904290429 = b043Bлллллл043B043Bл();
        bЩЩЩ0429Щ0429Щ042904290429 = 44;
      }
      yytyyt.bл043Bл043B043Bлл043B043Bл(localYytyyt, paramAbbaba);
      return this;
    }
    
    public ytyyyt bл043B043Bлллл043B043Bл(baabaa paramBaabaa)
    {
      try
      {
        yytyyt localYytyyt = this.bЩЩ0429ЩЩ0429Щ042904290429;
        if ((b0429Щ0429ЩЩ0429Щ042904290429 + bЩ04290429ЩЩ0429Щ042904290429) * b0429Щ0429ЩЩ0429Щ042904290429 % b042904290429ЩЩ0429Щ042904290429 != bЩЩЩ0429Щ0429Щ042904290429)
        {
          b0429Щ0429ЩЩ0429Щ042904290429 = 93;
          bЩЩЩ0429Щ0429Щ042904290429 = 69;
        }
        try
        {
          yytyyt.b043B043Bл043B043Bлл043B043Bл(localYytyyt, paramBaabaa);
        }
        catch (Exception paramBaabaa)
        {
          int i;
          int j;
          throw paramBaabaa;
        }
        i = b0429Щ0429ЩЩ0429Щ042904290429;
        j = bЩ04290429ЩЩ0429Щ042904290429;
        if ((i + j) * b0429Щ0429ЩЩ0429Щ042904290429 % b042904290429ЩЩ0429Щ042904290429 != bЩЩЩ0429Щ0429Щ042904290429)
        {
          b0429Щ0429ЩЩ0429Щ042904290429 = b043Bлллллл043B043Bл();
          bЩЩЩ0429Щ0429Щ042904290429 = b043Bлллллл043B043Bл();
        }
        return this;
      }
      catch (Exception paramBaabaa)
      {
        throw paramBaabaa;
      }
      switch (0)
      {
      }
      for (;;)
      {
        switch (0)
        {
        }
      }
    }
    
    public ytyyyt bл043Bл043Bллл043B043Bл(boolean paramBoolean)
    {
      int i = b0429Щ0429ЩЩ0429Щ042904290429;
      int j = bЩ04290429ЩЩ0429Щ042904290429;
      int k = bлл043Bлллл043B043Bл();
      if ((b0429Щ0429ЩЩ0429Щ042904290429 + bЩ04290429ЩЩ0429Щ042904290429) * b0429Щ0429ЩЩ0429Щ042904290429 % b042904290429ЩЩ0429Щ042904290429 != bЩЩЩ0429Щ0429Щ042904290429)
      {
        b0429Щ0429ЩЩ0429Щ042904290429 = 79;
        bЩЩЩ0429Щ0429Щ042904290429 = b043Bлллллл043B043Bл();
      }
      switch (0)
      {
      case 1: 
      default: 
        for (;;)
        {
          switch (0)
          {
          }
        }
      }
      switch (i * (j + i) % k)
      {
      default: 
        b0429Щ0429ЩЩ0429Щ042904290429 = b043Bлллллл043B043Bл();
        bЩЩЩ0429Щ0429Щ042904290429 = 64;
      }
      try
      {
        yytyyt.bл043Bлл043Bлл043B043Bл(this.bЩЩ0429ЩЩ0429Щ042904290429, paramBoolean);
        return this;
      }
      catch (Exception localException)
      {
        throw localException;
      }
    }
    
    public yytyyt bл043Bллллл043B043Bл()
    {
      int i = b0429Щ0429ЩЩ0429Щ042904290429;
      switch (i * (bЩ04290429ЩЩ0429Щ042904290429 + i) % b042904290429ЩЩ0429Щ042904290429)
      {
      default: 
        b0429Щ0429ЩЩ0429Щ042904290429 = 61;
        bЩ04290429ЩЩ0429Щ042904290429 = 54;
        if ((b0429Щ0429ЩЩ0429Щ042904290429 + bЩ04290429ЩЩ0429Щ042904290429) * b0429Щ0429ЩЩ0429Щ042904290429 % b042904290429ЩЩ0429Щ042904290429 != bЩЩЩ0429Щ0429Щ042904290429)
        {
          b0429Щ0429ЩЩ0429Щ042904290429 = b043Bлллллл043B043Bл();
          bЩЩЩ0429Щ0429Щ042904290429 = b043Bлллллл043B043Bл();
        }
        break;
      }
      switch (1)
      {
      case 0: 
      default: 
        for (;;)
        {
          switch (1)
          {
          }
        }
      }
      return this.bЩЩ0429ЩЩ0429Щ042904290429;
    }
    
    public ytyyyt bлл043B043Bллл043B043Bл(jjjjee paramJjjjee)
    {
      try
      {
        yytyyt localYytyyt = this.bЩЩ0429ЩЩ0429Щ042904290429;
        int i;
        for (;;) {}
      }
      catch (Exception paramJjjjee)
      {
        try
        {
          yytyyt.bлл043Bл043Bлл043B043Bл(localYytyyt, paramJjjjee);
          i = b0429Щ0429ЩЩ0429Щ042904290429;
          switch (i * (bЩ04290429ЩЩ0429Щ042904290429 + i) % bлл043Bлллл043B043Bл())
          {
          case 0: 
            b0429Щ0429ЩЩ0429Щ042904290429 = 66;
            bЩЩЩ0429Щ0429Щ042904290429 = 10;
            return this;
          }
        }
        catch (Exception paramJjjjee)
        {
          throw paramJjjjee;
        }
        paramJjjjee = paramJjjjee;
        throw paramJjjjee;
      }
    }
    
    /* Error */
    public ytyyyt bллл043Bллл043B043Bл(String paramString)
    {
      // Byte code:
      //   0: aload_0
      //   1: getfield 26	kkkkkk/yytyyt$ytyyyt:bЩЩ0429ЩЩ0429Щ042904290429	Lkkkkkk/yytyyt;
      //   4: astore 6
      //   6: aload 6
      //   8: aload_1
      //   9: invokestatic 92	kkkkkk/yytyyt:bл043B043B043B043Bлл043B043Bл	(Lkkkkkk/yytyyt;Ljava/lang/String;)Ljava/lang/String;
      //   12: pop
      //   13: getstatic 150	kkkkkk/yytyyt$ytyyyt:b0429Щ0429ЩЩ0429Щ042904290429	I
      //   16: istore_2
      //   17: getstatic 152	kkkkkk/yytyyt$ytyyyt:bЩ04290429ЩЩ0429Щ042904290429	I
      //   20: istore_3
      //   21: getstatic 150	kkkkkk/yytyyt$ytyyyt:b0429Щ0429ЩЩ0429Щ042904290429	I
      //   24: istore 4
      //   26: getstatic 154	kkkkkk/yytyyt$ytyyyt:b042904290429ЩЩ0429Щ042904290429	I
      //   29: istore 5
      //   31: iconst_0
      //   32: tableswitch	default:+24->56, 0:+51->83, 1:+-1->31
      //   56: iconst_1
      //   57: tableswitch	default:+23->80, 0:+-26->31, 1:+26->83
      //   80: goto -24 -> 56
      //   83: iload_2
      //   84: iload_3
      //   85: iadd
      //   86: iload 4
      //   88: imul
      //   89: iload 5
      //   91: irem
      //   92: getstatic 160	kkkkkk/yytyyt$ytyyyt:bЩЩЩ0429Щ0429Щ042904290429	I
      //   95: if_icmpeq +48 -> 143
      //   98: getstatic 150	kkkkkk/yytyyt$ytyyyt:b0429Щ0429ЩЩ0429Щ042904290429	I
      //   101: getstatic 152	kkkkkk/yytyyt$ytyyyt:bЩ04290429ЩЩ0429Щ042904290429	I
      //   104: iadd
      //   105: getstatic 150	kkkkkk/yytyyt$ytyyyt:b0429Щ0429ЩЩ0429Щ042904290429	I
      //   108: imul
      //   109: getstatic 154	kkkkkk/yytyyt$ytyyyt:b042904290429ЩЩ0429Щ042904290429	I
      //   112: irem
      //   113: getstatic 160	kkkkkk/yytyyt$ytyyyt:bЩЩЩ0429Щ0429Щ042904290429	I
      //   116: if_icmpeq +15 -> 131
      //   119: invokestatic 158	kkkkkk/yytyyt$ytyyyt:b043Bлллллл043B043Bл	()I
      //   122: putstatic 150	kkkkkk/yytyyt$ytyyyt:b0429Щ0429ЩЩ0429Щ042904290429	I
      //   125: invokestatic 158	kkkkkk/yytyyt$ytyyyt:b043Bлллллл043B043Bл	()I
      //   128: putstatic 160	kkkkkk/yytyyt$ytyyyt:bЩЩЩ0429Щ0429Щ042904290429	I
      //   131: invokestatic 158	kkkkkk/yytyyt$ytyyyt:b043Bлллллл043B043Bл	()I
      //   134: putstatic 150	kkkkkk/yytyyt$ytyyyt:b0429Щ0429ЩЩ0429Щ042904290429	I
      //   137: invokestatic 158	kkkkkk/yytyyt$ytyyyt:b043Bлллллл043B043Bл	()I
      //   140: putstatic 160	kkkkkk/yytyyt$ytyyyt:bЩЩЩ0429Щ0429Щ042904290429	I
      //   143: aload_0
      //   144: areturn
      //   145: astore_1
      //   146: aload_1
      //   147: athrow
      //   148: astore_1
      //   149: aload_1
      //   150: athrow
      // Local variable table:
      //   start	length	slot	name	signature
      //   0	151	0	this	ytyyyt
      //   0	151	1	paramString	String
      //   16	70	2	i	int
      //   20	66	3	j	int
      //   24	65	4	k	int
      //   29	63	5	m	int
      //   4	3	6	localYytyyt	yytyyt
      // Exception table:
      //   from	to	target	type
      //   0	6	145	java/lang/Exception
      //   6	13	148	java/lang/Exception
    }
    
    public ytyyyt bлллл043Bлл043B043Bл(String paramString)
    {
      int i = b0429Щ0429ЩЩ0429Щ042904290429;
      switch (i * (bЩ04290429ЩЩ0429Щ042904290429 + i) % b042904290429ЩЩ0429Щ042904290429)
      {
      default: 
        b0429Щ0429ЩЩ0429Щ042904290429 = b043Bлллллл043B043Bл();
        bЩЩЩ0429Щ0429Щ042904290429 = 18;
      }
      yytyyt localYytyyt = this.bЩЩ0429ЩЩ0429Щ042904290429;
      switch (0)
      {
      case 1: 
      default: 
        for (;;)
        {
          i = b043Bлллллл043B043Bл();
          switch (i * (bЩ04290429ЩЩ0429Щ042904290429 + i) % b042904290429ЩЩ0429Щ042904290429)
          {
          default: 
            b0429Щ0429ЩЩ0429Щ042904290429 = b043Bлллллл043B043Bл();
            bЩЩЩ0429Щ0429Щ042904290429 = 82;
          }
          switch (1)
          {
          }
        }
      }
      yytyyt.bллл043B043Bлл043B043Bл(localYytyyt, paramString);
      switch (1)
      {
      case 0: 
      default: 
        for (;;)
        {
          switch (0)
          {
          }
        }
      }
      return this;
    }
  }
}
