package kkkkkk;

public enum yyyhyh
{
  static
  {
    if ((bе04350435е043504350435ее0435() + b043504350435е043504350435ее0435()) * bе04350435е043504350435ее0435() % bеее0435043504350435ее0435() != b0435ее0435043504350435ее0435()) {}
    yyyhyh localYyyhyh1 = new yyyhyh(gguuuu.bк043Aккк043Aкк043A043A(",)\027#'\031\027#", '\037', '', '\002'), 0);
    int i = bе04350435е043504350435ее0435();
    switch (i * (b043504350435е043504350435ее0435() + i) % bеее0435043504350435ее0435())
    {
    }
    TRANSFER = localYyyhyh1;
    PAYMENT = new yyyhyh(gguuuu.bк043Aккк043Aкк043A043A("\004u\017\004|\007\016", '&', 'ñ', '\001'), 1);
    PAYM = new yyyhyh(gguuuu.bк043Aккк043Aкк043A043A("\002s\r\002", '²', 'ü', '\003'), 2);
    CREDIT_CARD_PAYMENT = new yyyhyh(gguuuu.bккккк043Aкк043A043A("kykimw\002daqb|l\\sf]ej", 'Ö', '\005'), 3);
    STANDING_ORDER = new yyyhyh(gguuuu.bккккк043Aкк043A043A("\032\032\006\022\007\013\017\007\036\r\017\f", '', '\002'), 4);
    UNHANDLED = new yyyhyh(gguuuu.bккккк043Aкк043A043A("}wrlzqztt", 'á', '\001'), 5);
    localYyyhyh1 = TRANSFER;
    yyyhyh localYyyhyh2 = PAYMENT;
    yyyhyh localYyyhyh3 = PAYM;
    yyyhyh localYyyhyh4 = CREDIT_CARD_PAYMENT;
    switch (0)
    {
    case 1: 
    default: 
      for (;;)
      {
        switch (1)
        {
        }
      }
    }
    $VALUES = new yyyhyh[] { localYyyhyh1, localYyyhyh2, localYyyhyh3, localYyyhyh4, STANDING_ORDER, UNHANDLED };
  }
  
  private yyyhyh() {}
  
  public static int b043504350435е043504350435ее0435()
  {
    return 1;
  }
  
  public static int b0435ее0435043504350435ее0435()
  {
    return 0;
  }
  
  public static int bе04350435е043504350435ее0435()
  {
    return 53;
  }
  
  /* Error */
  public static yyyhyh bе0435е0435043504350435ее0435(String paramString)
  {
    // Byte code:
    //   0: invokestatic 20	kkkkkk/yyyhyh:bе04350435е043504350435ее0435	()I
    //   3: istore_1
    //   4: invokestatic 23	kkkkkk/yyyhyh:b043504350435е043504350435ее0435	()I
    //   7: istore_2
    //   8: invokestatic 20	kkkkkk/yyyhyh:bе04350435е043504350435ее0435	()I
    //   11: istore_3
    //   12: iload_3
    //   13: invokestatic 23	kkkkkk/yyyhyh:b043504350435е043504350435ее0435	()I
    //   16: iload_3
    //   17: iadd
    //   18: imul
    //   19: invokestatic 26	kkkkkk/yyyhyh:bеее0435043504350435ее0435	()I
    //   22: irem
    //   23: tableswitch	default:+17->40, 0:+17->40
    //   40: invokestatic 20	kkkkkk/yyyhyh:bе04350435е043504350435ее0435	()I
    //   43: istore_3
    //   44: invokestatic 26	kkkkkk/yyyhyh:bеее0435043504350435ее0435	()I
    //   47: istore 4
    //   49: invokestatic 29	kkkkkk/yyyhyh:b0435ее0435043504350435ее0435	()I
    //   52: istore 5
    //   54: iload_1
    //   55: iload_2
    //   56: iadd
    //   57: iload_3
    //   58: imul
    //   59: iload 4
    //   61: irem
    //   62: iload 5
    //   64: if_icmpeq +3 -> 67
    //   67: ldc 2
    //   69: aload_0
    //   70: invokestatic 80	java/lang/Enum:valueOf	(Ljava/lang/Class;Ljava/lang/String;)Ljava/lang/Enum;
    //   73: astore_0
    //   74: aload_0
    //   75: checkcast 2	kkkkkk/yyyhyh
    //   78: astore_0
    //   79: aload_0
    //   80: areturn
    //   81: astore_0
    //   82: aload_0
    //   83: athrow
    //   84: astore_0
    //   85: aload_0
    //   86: athrow
    //   87: astore_0
    //   88: aload_0
    //   89: athrow
    //   90: astore_0
    //   91: aload_0
    //   92: athrow
    // Local variable table:
    //   start	length	slot	name	signature
    //   0	93	0	paramString	String
    //   3	54	1	i	int
    //   7	50	2	j	int
    //   11	48	3	k	int
    //   47	15	4	m	int
    //   52	13	5	n	int
    // Exception table:
    //   from	to	target	type
    //   67	74	81	java/lang/Exception
    //   0	8	84	java/lang/Exception
    //   44	54	84	java/lang/Exception
    //   82	84	84	java/lang/Exception
    //   74	79	87	java/lang/Exception
    //   40	44	90	java/lang/Exception
    //   88	90	90	java/lang/Exception
  }
  
  public static int bеее0435043504350435ее0435()
  {
    return 2;
  }
}
