package kkkkkk;

import android.support.annotation.NonNull;
import android.support.annotation.Nullable;
import java.io.Serializable;

public class yyytty
  implements Serializable
{
  @NonNull
  private String b04290429Щ04290429Щ0429042904290429;
  @Nullable
  private String b0429Щ042904290429Щ0429042904290429;
  @NonNull
  private String bЩ0429042904290429Щ0429042904290429;
  @NonNull
  private String bЩЩ042904290429Щ0429042904290429;
  
  public yyytty() {}
  
  public yyytty(@NonNull String paramString1, @NonNull String paramString2, @NonNull String paramString3, @Nullable String paramString4)
  {
    this.bЩ0429042904290429Щ0429042904290429 = paramString1;
    this.b04290429Щ04290429Щ0429042904290429 = paramString2;
    this.bЩЩ042904290429Щ0429042904290429 = paramString3;
    this.b0429Щ042904290429Щ0429042904290429 = paramString4;
  }
  
  public static int b043B043Bл043Bл043B043B043B043Bл()
  {
    return 63;
  }
  
  public static int b043Bл043B043Bл043B043B043B043Bл()
  {
    return 0;
  }
  
  public static int bл043Bл043Bл043B043B043B043Bл()
  {
    return 2;
  }
  
  public static int bлл043B043Bл043B043B043B043Bл()
  {
    return 1;
  }
  
  @Nullable
  public String b043B043B043B043Bл043B043B043B043Bл()
  {
    if ((b043B043Bл043Bл043B043B043B043Bл() + bлл043B043Bл043B043B043B043Bл()) * b043B043Bл043Bл043B043B043B043Bл() % bл043Bл043Bл043B043B043B043Bл() != b043Bл043B043Bл043B043B043B043Bл()) {}
    String str = this.bЩЩ042904290429Щ0429042904290429;
    int i = b043B043Bл043Bл043B043B043B043Bл();
    int j = bлл043B043Bл043B043B043B043Bл();
    switch (1)
    {
    case 0: 
    default: 
      for (;;)
      {
        switch (0)
        {
        }
      }
    }
    if ((i + j) * b043B043Bл043Bл043B043B043B043Bл() % bл043Bл043Bл043B043B043B043Bл() != b043Bл043B043Bл043B043B043B043Bл()) {}
    return str;
  }
  
  /* Error */
  public void b043B043Bлл043B043B043B043B043Bл(@Nullable String paramString)
  {
    // Byte code:
    //   0: invokestatic 37	kkkkkk/yyytty:b043B043Bл043Bл043B043B043B043Bл	()I
    //   3: istore_2
    //   4: invokestatic 39	kkkkkk/yyytty:bлл043B043Bл043B043B043B043Bл	()I
    //   7: istore_3
    //   8: invokestatic 41	kkkkkk/yyytty:bл043Bл043Bл043B043B043B043Bл	()I
    //   11: istore 4
    //   13: iload_2
    //   14: iload_3
    //   15: iload_2
    //   16: iadd
    //   17: imul
    //   18: iload 4
    //   20: irem
    //   21: tableswitch	default:+19->40, 0:+19->40
    //   40: aload_0
    //   41: aload_1
    //   42: putfield 25	kkkkkk/yyytty:bЩЩ042904290429Щ0429042904290429	Ljava/lang/String;
    //   45: invokestatic 37	kkkkkk/yyytty:b043B043Bл043Bл043B043B043B043Bл	()I
    //   48: invokestatic 39	kkkkkk/yyytty:bлл043B043Bл043B043B043B043Bл	()I
    //   51: iadd
    //   52: invokestatic 37	kkkkkk/yyytty:b043B043Bл043Bл043B043B043B043Bл	()I
    //   55: imul
    //   56: invokestatic 41	kkkkkk/yyytty:bл043Bл043Bл043B043B043B043Bл	()I
    //   59: irem
    //   60: invokestatic 43	kkkkkk/yyytty:b043Bл043B043Bл043B043B043B043Bл	()I
    //   63: if_icmpeq +3 -> 66
    //   66: return
    //   67: astore_1
    //   68: aload_1
    //   69: athrow
    //   70: astore_1
    //   71: aload_1
    //   72: athrow
    //   73: astore_1
    //   74: aload_1
    //   75: athrow
    // Local variable table:
    //   start	length	slot	name	signature
    //   0	76	0	this	yyytty
    //   0	76	1	paramString	String
    //   3	15	2	i	int
    //   7	10	3	j	int
    //   11	10	4	k	int
    // Exception table:
    //   from	to	target	type
    //   40	45	67	java/lang/Exception
    //   68	70	70	java/lang/Exception
    //   0	13	73	java/lang/Exception
  }
  
  public void b043Bл043Bл043B043B043B043B043Bл(@Nullable String paramString)
  {
    if ((b043B043Bл043Bл043B043B043B043Bл() + bлл043B043Bл043B043B043B043Bл()) * b043B043Bл043Bл043B043B043B043Bл() % bл043Bл043Bл043B043B043B043Bл() != b043Bл043B043Bл043B043B043B043Bл())
    {
      switch (0)
      {
      case 1: 
      default: 
        for (;;)
        {
          switch (1)
          {
          }
        }
      }
      int i = b043B043Bл043Bл043B043B043B043Bл();
      switch (i * (bлл043B043Bл043B043B043B043Bл() + i) % bл043Bл043Bл043B043B043B043Bл())
      {
      }
    }
    this.bЩ0429042904290429Щ0429042904290429 = paramString;
  }
  
  @Nullable
  public String b043Bллл043B043B043B043B043Bл()
  {
    try
    {
      String str = this.bЩ0429042904290429Щ0429042904290429;
      int i = b043B043Bл043Bл043B043B043B043Bл();
      int j = bлл043B043Bл043B043B043B043Bл();
      int k = b043B043Bл043Bл043B043B043B043Bл();
      int m = bл043Bл043Bл043B043B043B043Bл();
      int n = b043Bл043B043Bл043B043B043B043Bл();
      if (((i + j) * k % m != n) && ((b043B043Bл043Bл043B043B043B043Bл() + bлл043B043Bл043B043B043B043Bл()) * b043B043Bл043Bл043B043B043B043Bл() % bл043Bл043Bл043B043B043B043Bл() != b043Bл043B043Bл043B043B043B043Bл())) {}
      switch (1)
      {
      case 0: 
      default: 
        for (;;)
        {
          switch (1)
          {
          }
        }
      }
      return str;
    }
    catch (Exception localException)
    {
      throw localException;
    }
  }
  
  @Nullable
  public String bл043B043B043Bл043B043B043B043Bл()
  {
    int i = b043B043Bл043Bл043B043B043B043Bл();
    switch (i * (bлл043B043Bл043B043B043B043Bл() + i) % bл043Bл043Bл043B043B043B043Bл())
    {
    default: 
      switch (1)
      {
      case 0: 
      default: 
        for (;;)
        {
          switch (1)
          {
          }
        }
      }
      i = b043B043Bл043Bл043B043B043B043Bл();
      switch (i * (bлл043B043Bл043B043B043B043Bл() + i) % bл043Bл043Bл043B043B043B043Bл())
      {
      }
      break;
    }
    try
    {
      String str = this.b04290429Щ04290429Щ0429042904290429;
      return str;
    }
    catch (Exception localException)
    {
      throw localException;
    }
  }
  
  public void bл043Bлл043B043B043B043B043Bл(@Nullable String paramString)
  {
    switch (1)
    {
    case 0: 
    default: 
      for (;;)
      {
        switch (0)
        {
        case 1: 
        default: 
          for (;;)
          {
            switch (1)
            {
            }
          }
        }
        switch (0)
        {
        }
      }
    }
    int i = b043B043Bл043Bл043B043B043B043Bл();
    switch (i * (bлл043B043Bл043B043B043B043Bл() + i) % bл043Bл043Bл043B043B043B043Bл())
    {
    default: 
      i = b043B043Bл043Bл043B043B043B043Bл();
      switch (i * (bлл043B043Bл043B043B043B043Bл() + i) % bл043Bл043Bл043B043B043B043Bл())
      {
      }
      break;
    }
    this.b04290429Щ04290429Щ0429042904290429 = paramString;
  }
  
  /* Error */
  public void bлл043Bл043B043B043B043B043Bл(@Nullable String paramString)
  {
    // Byte code:
    //   0: aload_0
    //   1: aload_1
    //   2: putfield 27	kkkkkk/yyytty:b0429Щ042904290429Щ0429042904290429	Ljava/lang/String;
    //   5: invokestatic 37	kkkkkk/yyytty:b043B043Bл043Bл043B043B043B043Bл	()I
    //   8: invokestatic 39	kkkkkk/yyytty:bлл043B043Bл043B043B043B043Bл	()I
    //   11: iadd
    //   12: invokestatic 37	kkkkkk/yyytty:b043B043Bл043Bл043B043B043B043Bл	()I
    //   15: imul
    //   16: invokestatic 41	kkkkkk/yyytty:bл043Bл043Bл043B043B043B043Bл	()I
    //   19: irem
    //   20: invokestatic 43	kkkkkk/yyytty:b043Bл043B043Bл043B043B043B043Bл	()I
    //   23: if_icmpeq +3 -> 26
    //   26: new 55	java/lang/NullPointerException
    //   29: dup
    //   30: invokespecial 56	java/lang/NullPointerException:<init>	()V
    //   33: athrow
    //   34: astore_1
    //   35: return
    //   36: astore_1
    //   37: aload_1
    //   38: athrow
    // Local variable table:
    //   start	length	slot	name	signature
    //   0	39	0	this	yyytty
    //   0	39	1	paramString	String
    // Exception table:
    //   from	to	target	type
    //   26	34	34	java/lang/Exception
    //   0	5	36	java/lang/Exception
  }
  
  /* Error */
  @Nullable
  public String bлллл043B043B043B043B043Bл()
  {
    // Byte code:
    //   0: new 55	java/lang/NullPointerException
    //   3: dup
    //   4: invokespecial 56	java/lang/NullPointerException:<init>	()V
    //   7: athrow
    //   8: astore_2
    //   9: new 55	java/lang/NullPointerException
    //   12: dup
    //   13: invokespecial 56	java/lang/NullPointerException:<init>	()V
    //   16: athrow
    //   17: astore_2
    //   18: iconst_0
    //   19: istore_1
    //   20: iload_1
    //   21: iconst_0
    //   22: idiv
    //   23: istore_1
    //   24: goto -4 -> 20
    //   27: astore_2
    //   28: iconst_0
    //   29: tableswitch	default:+23->52, 0:+50->79, 1:+-1->28
    //   52: iconst_1
    //   53: tableswitch	default:+23->76, 0:+-25->28, 1:+26->79
    //   76: goto -24 -> 52
    //   79: aload_0
    //   80: getfield 27	kkkkkk/yyytty:b0429Щ042904290429Щ0429042904290429	Ljava/lang/String;
    //   83: astore_2
    //   84: aload_2
    //   85: areturn
    //   86: astore_2
    //   87: aload_2
    //   88: athrow
    // Local variable table:
    //   start	length	slot	name	signature
    //   0	89	0	this	yyytty
    //   19	5	1	i	int
    //   8	1	2	localException1	Exception
    //   17	1	2	localException2	Exception
    //   27	1	2	localException3	Exception
    //   83	2	2	str	String
    //   86	2	2	localException4	Exception
    // Exception table:
    //   from	to	target	type
    //   0	8	8	java/lang/Exception
    //   9	17	17	java/lang/Exception
    //   20	24	27	java/lang/Exception
    //   79	84	86	java/lang/Exception
  }
}
