package kkkkkk;

import android.support.annotation.NonNull;
import android.support.annotation.Nullable;
import java.io.Serializable;

public class yyyytt
  implements Serializable
{
  private static final long serialVersionUID = -2814500487317809623L;
  @Nullable
  private final cccrcc b042904290429Щ0429Щ0429Щ04290429;
  @Nullable
  private final bbabba b0429Щ0429Щ0429Щ0429Щ04290429;
  @NonNull
  private final cccrcc bЩ04290429Щ0429Щ0429Щ04290429;
  
  public yyyytt(@NonNull cccrcc paramCccrcc, @NonNull bbabba paramBbabba)
  {
    this.bЩ04290429Щ0429Щ0429Щ04290429 = paramCccrcc;
    this.b042904290429Щ0429Щ0429Щ04290429 = null;
    this.b0429Щ0429Щ0429Щ0429Щ04290429 = paramBbabba;
  }
  
  public yyyytt(@NonNull cccrcc paramCccrcc1, @NonNull cccrcc paramCccrcc2)
  {
    this.bЩ04290429Щ0429Щ0429Щ04290429 = paramCccrcc1;
    this.b042904290429Щ0429Щ0429Щ04290429 = paramCccrcc2;
    this.b0429Щ0429Щ0429Щ0429Щ04290429 = null;
  }
  
  public static int b043B043Bллл043Bлл043Bл()
  {
    return 0;
  }
  
  public static int b043Bл043Bлл043Bлл043Bл()
  {
    return 35;
  }
  
  public static int bл043B043Bлл043Bлл043Bл()
  {
    return 1;
  }
  
  public static int bлл043Bлл043Bлл043Bл()
  {
    return 2;
  }
  
  /* Error */
  @Nullable
  public bbabba b043B043B043Bлл043Bлл043Bл()
  {
    // Byte code:
    //   0: iconst_1
    //   1: tableswitch	default:+23->24, 0:+-1->0, 1:+50->51
    //   24: iconst_0
    //   25: tableswitch	default:+23->48, 0:+26->51, 1:+-25->0
    //   48: goto -24 -> 24
    //   51: aload_0
    //   52: getfield 28	kkkkkk/yyyytt:b0429Щ0429Щ0429Щ0429Щ04290429	Lkkkkkk/bbabba;
    //   55: astore 6
    //   57: invokestatic 42	kkkkkk/yyyytt:b043Bл043Bлл043Bлл043Bл	()I
    //   60: istore_1
    //   61: invokestatic 44	kkkkkk/yyyytt:bл043B043Bлл043Bлл043Bл	()I
    //   64: istore_2
    //   65: invokestatic 42	kkkkkk/yyyytt:b043Bл043Bлл043Bлл043Bл	()I
    //   68: istore_3
    //   69: invokestatic 46	kkkkkk/yyyytt:bлл043Bлл043Bлл043Bл	()I
    //   72: istore 4
    //   74: invokestatic 48	kkkkkk/yyyytt:b043B043Bллл043Bлл043Bл	()I
    //   77: istore 5
    //   79: iload_1
    //   80: iload_2
    //   81: iadd
    //   82: iload_3
    //   83: imul
    //   84: iload 4
    //   86: irem
    //   87: iload 5
    //   89: if_icmpeq +24 -> 113
    //   92: invokestatic 42	kkkkkk/yyyytt:b043Bл043Bлл043Bлл043Bл	()I
    //   95: invokestatic 44	kkkkkk/yyyytt:bл043B043Bлл043Bлл043Bл	()I
    //   98: iadd
    //   99: invokestatic 42	kkkkkk/yyyytt:b043Bл043Bлл043Bлл043Bл	()I
    //   102: imul
    //   103: invokestatic 46	kkkkkk/yyyytt:bлл043Bлл043Bлл043Bл	()I
    //   106: irem
    //   107: invokestatic 48	kkkkkk/yyyytt:b043B043Bллл043Bлл043Bл	()I
    //   110: if_icmpeq +3 -> 113
    //   113: aload 6
    //   115: areturn
    //   116: astore 6
    //   118: aload 6
    //   120: athrow
    //   121: astore 6
    //   123: aload 6
    //   125: athrow
    // Local variable table:
    //   start	length	slot	name	signature
    //   0	126	0	this	yyyytt
    //   60	22	1	i	int
    //   64	18	2	j	int
    //   68	16	3	k	int
    //   72	15	4	m	int
    //   77	13	5	n	int
    //   55	59	6	localBbabba	bbabba
    //   116	3	6	localException1	Exception
    //   121	3	6	localException2	Exception
    // Exception table:
    //   from	to	target	type
    //   69	79	116	java/lang/Exception
    //   51	69	121	java/lang/Exception
  }
  
  @Nullable
  public cccrcc b043Bлл043Bл043Bлл043Bл()
  {
    if (((b043Bл043Bлл043Bлл043Bл() + bл043B043Bлл043Bлл043Bл()) * b043Bл043Bлл043Bлл043Bл() % bлл043Bлл043Bлл043Bл() != b043B043Bллл043Bлл043Bл()) && ((b043Bл043Bлл043Bлл043Bл() + bл043B043Bлл043Bлл043Bл()) * b043Bл043Bлл043Bлл043Bл() % bлл043Bлл043Bлл043Bл() != b043B043Bллл043Bлл043Bл())) {}
    switch (0)
    {
    case 1: 
    default: 
      for (;;)
      {
        switch (0)
        {
        case 1: 
        default: 
          for (;;)
          {
            switch (1)
            {
            }
          }
        }
        switch (1)
        {
        }
      }
    }
    return this.b042904290429Щ0429Щ0429Щ04290429;
  }
  
  @NonNull
  public cccrcc bллл043Bл043Bлл043Bл()
  {
    if ((b043Bл043Bлл043Bлл043Bл() + bл043B043Bлл043Bлл043Bл()) * b043Bл043Bлл043Bлл043Bл() % bлл043Bлл043Bлл043Bл() != b043B043Bллл043Bлл043Bл()) {}
    switch (1)
    {
    case 0: 
    default: 
      for (;;)
      {
        switch (0)
        {
        }
      }
    }
    cccrcc localCccrcc = this.bЩ04290429Щ0429Щ0429Щ04290429;
    int i = b043Bл043Bлл043Bлл043Bл();
    switch (i * (bл043B043Bлл043Bлл043Bл() + i) % bлл043Bлл043Bлл043Bл())
    {
    }
    return localCccrcc;
  }
}
