package com.mobile.ui.registration.cms;

import android.os.Bundle;
import android.support.annotation.NonNull;
import android.support.annotation.Nullable;
import com.mobile.ui.App;
import com.mobile.ui.cms.CmsMessageFragment;
import javax.inject.Inject;
import kkkkkk.gguuuu;
import kkkkkk.iiisis.siisis;
import kkkkkk.isisis;
import kkkkkk.isisss.iissss;
import kkkkkk.uyyyyy;

public class RegistrationCmsMessageFragment
  extends CmsMessageFragment
  implements iiisis.siisis
{
  private static final String ARG_BACK_TO_LOGIN = "BTJcGGJSh^ZkY]VY_";
  private static final String ARG_SCREEN_EVENT = "\002\022\006\035\020~\r~}\006\026z\013x\001\006";
  public static int b04100410АА0410041004100410А = 0;
  public static int b0410А0410А0410041004100410А = 2;
  public static int bА0410АА0410041004100410А = 67;
  public static int bАА0410А0410041004100410А = 1;
  @Inject
  public isisis mActivationAnalytics;
  
  static
  {
    try
    {
      str = ARG_BACK_TO_LOGIN;
    }
    catch (Exception localException1)
    {
      try
      {
        int j;
        int k;
        int m;
        int n;
        bА0410АА0410041004100410А = 37;
        int i = bА0410АА0410041004100410А;
        switch (i * (bАА0410А0410041004100410А + i) % b0410А0410А0410041004100410А)
        {
        default: 
          bА0410АА0410041004100410А = bА04100410А0410041004100410А();
          b04100410АА0410041004100410А = 52;
        }
        b04100410АА0410041004100410А = 23;
        ARG_BACK_TO_LOGIN = gguuuu.bк043Aккк043Aкк043A043A(str, 'ÿ', 'þ', '\003');
        String str = ARG_SCREEN_EVENT;
        ARG_SCREEN_EVENT = gguuuu.bккккк043Aкк043A043A(str, 'Þ', '\003');
        return;
      }
      catch (Exception localException2)
      {
        throw localException2;
      }
      localException1 = localException1;
      throw localException1;
    }
    i = bА0410АА0410041004100410А;
    j = bАА0410А0410041004100410А;
    k = bА0410АА0410041004100410А;
    m = b0410А0410А0410041004100410А;
    n = b04100410АА0410041004100410А;
    if ((i + j) * k % m != n) {}
    switch (0)
    {
    }
    for (;;)
    {
      switch (1)
      {
      }
    }
  }
  
  public RegistrationCmsMessageFragment() {}
  
  public static int b041004100410А0410041004100410А()
  {
    return 2;
  }
  
  public static int bА04100410А0410041004100410А()
  {
    return 67;
  }
  
  public static int bААА04100410041004100410А()
  {
    return 1;
  }
  
  /* Error */
  public static RegistrationCmsMessageFragment newInstance(@NonNull String paramString1, @NonNull String paramString2, isisss.iissss paramIissss, String... paramVarArgs)
  {
    // Byte code:
    //   0: new 2	com/mobile/ui/registration/cms/RegistrationCmsMessageFragment
    //   3: dup
    //   4: invokespecial 65	com/mobile/ui/registration/cms/RegistrationCmsMessageFragment:<init>	()V
    //   7: astore 9
    //   9: getstatic 33	com/mobile/ui/registration/cms/RegistrationCmsMessageFragment:bА0410АА0410041004100410А	I
    //   12: istore 4
    //   14: getstatic 35	com/mobile/ui/registration/cms/RegistrationCmsMessageFragment:bАА0410А0410041004100410А	I
    //   17: istore 5
    //   19: getstatic 33	com/mobile/ui/registration/cms/RegistrationCmsMessageFragment:bА0410АА0410041004100410А	I
    //   22: istore 6
    //   24: getstatic 37	com/mobile/ui/registration/cms/RegistrationCmsMessageFragment:b0410А0410А0410041004100410А	I
    //   27: istore 7
    //   29: getstatic 39	com/mobile/ui/registration/cms/RegistrationCmsMessageFragment:b04100410АА0410041004100410А	I
    //   32: istore 8
    //   34: iload 4
    //   36: iload 5
    //   38: iadd
    //   39: iload 6
    //   41: imul
    //   42: iload 7
    //   44: irem
    //   45: iload 8
    //   47: if_icmpeq +19 -> 66
    //   50: invokestatic 43	com/mobile/ui/registration/cms/RegistrationCmsMessageFragment:bА04100410А0410041004100410А	()I
    //   53: putstatic 33	com/mobile/ui/registration/cms/RegistrationCmsMessageFragment:bА0410АА0410041004100410А	I
    //   56: invokestatic 43	com/mobile/ui/registration/cms/RegistrationCmsMessageFragment:bА04100410А0410041004100410А	()I
    //   59: istore 4
    //   61: iload 4
    //   63: putstatic 39	com/mobile/ui/registration/cms/RegistrationCmsMessageFragment:b04100410АА0410041004100410А	I
    //   66: aload_0
    //   67: aload_1
    //   68: aload_3
    //   69: invokestatic 69	com/mobile/ui/registration/cms/RegistrationCmsMessageFragment:createArguments	(Ljava/lang/String;Ljava/lang/String;[Ljava/lang/String;)Landroid/os/Bundle;
    //   72: astore_0
    //   73: ldc 71
    //   75: sipush 241
    //   78: sipush 219
    //   81: iconst_3
    //   82: invokestatic 49	kkkkkk/gguuuu:bк043Aккк043Aкк043A043A	(Ljava/lang/String;CCC)Ljava/lang/String;
    //   85: astore_1
    //   86: aload_2
    //   87: invokevirtual 76	kkkkkk/isisss$iissss:ordinal	()I
    //   90: istore 4
    //   92: getstatic 33	com/mobile/ui/registration/cms/RegistrationCmsMessageFragment:bА0410АА0410041004100410А	I
    //   95: istore 5
    //   97: iload 5
    //   99: getstatic 35	com/mobile/ui/registration/cms/RegistrationCmsMessageFragment:bАА0410А0410041004100410А	I
    //   102: iload 5
    //   104: iadd
    //   105: imul
    //   106: getstatic 37	com/mobile/ui/registration/cms/RegistrationCmsMessageFragment:b0410А0410А0410041004100410А	I
    //   109: irem
    //   110: tableswitch	default:+18->128, 0:+29->139
    //   128: invokestatic 43	com/mobile/ui/registration/cms/RegistrationCmsMessageFragment:bА04100410А0410041004100410А	()I
    //   131: putstatic 33	com/mobile/ui/registration/cms/RegistrationCmsMessageFragment:bА0410АА0410041004100410А	I
    //   134: bipush 28
    //   136: putstatic 39	com/mobile/ui/registration/cms/RegistrationCmsMessageFragment:b04100410АА0410041004100410А	I
    //   139: aload_0
    //   140: aload_1
    //   141: iload 4
    //   143: invokevirtual 82	android/os/Bundle:putInt	(Ljava/lang/String;I)V
    //   146: aload 9
    //   148: aload_0
    //   149: invokevirtual 86	com/mobile/ui/registration/cms/RegistrationCmsMessageFragment:setArguments	(Landroid/os/Bundle;)V
    //   152: aload 9
    //   154: areturn
    //   155: astore_0
    //   156: aload_0
    //   157: athrow
    //   158: astore_0
    //   159: aload_0
    //   160: athrow
    //   161: astore_0
    //   162: aload_0
    //   163: athrow
    //   164: astore_0
    //   165: aload_0
    //   166: athrow
    // Local variable table:
    //   start	length	slot	name	signature
    //   0	167	0	paramString1	String
    //   0	167	1	paramString2	String
    //   0	167	2	paramIissss	isisss.iissss
    //   0	167	3	paramVarArgs	String[]
    //   12	130	4	i	int
    //   17	89	5	j	int
    //   22	20	6	k	int
    //   27	18	7	m	int
    //   32	16	8	n	int
    //   7	146	9	localRegistrationCmsMessageFragment	RegistrationCmsMessageFragment
    // Exception table:
    //   from	to	target	type
    //   0	9	155	java/lang/Exception
    //   66	86	155	java/lang/Exception
    //   50	61	158	java/lang/Exception
    //   156	158	158	java/lang/Exception
    //   162	164	158	java/lang/Exception
    //   86	92	161	java/lang/Exception
    //   139	152	161	java/lang/Exception
    //   9	34	164	java/lang/Exception
    //   61	66	164	java/lang/Exception
  }
  
  /* Error */
  public static RegistrationCmsMessageFragment newInstance(@NonNull String paramString1, @NonNull String paramString2, String... paramVarArgs)
  {
    // Byte code:
    //   0: aload_0
    //   1: aload_1
    //   2: getstatic 92	kkkkkk/isisss$iissss:NONE	Lkkkkkk/isisss$iissss;
    //   5: aload_2
    //   6: invokestatic 94	com/mobile/ui/registration/cms/RegistrationCmsMessageFragment:newInstance	(Ljava/lang/String;Ljava/lang/String;Lkkkkkk/isisss$iissss;[Ljava/lang/String;)Lcom/mobile/ui/registration/cms/RegistrationCmsMessageFragment;
    //   9: astore_0
    //   10: getstatic 33	com/mobile/ui/registration/cms/RegistrationCmsMessageFragment:bА0410АА0410041004100410А	I
    //   13: istore_3
    //   14: getstatic 35	com/mobile/ui/registration/cms/RegistrationCmsMessageFragment:bАА0410А0410041004100410А	I
    //   17: istore 4
    //   19: iload_3
    //   20: iload 4
    //   22: iload_3
    //   23: iadd
    //   24: imul
    //   25: invokestatic 96	com/mobile/ui/registration/cms/RegistrationCmsMessageFragment:b041004100410А0410041004100410А	()I
    //   28: irem
    //   29: tableswitch	default:+38->67, 0:+30->59
    //   48: bipush 12
    //   50: putstatic 33	com/mobile/ui/registration/cms/RegistrationCmsMessageFragment:bА0410АА0410041004100410А	I
    //   53: invokestatic 43	com/mobile/ui/registration/cms/RegistrationCmsMessageFragment:bА04100410А0410041004100410А	()I
    //   56: putstatic 39	com/mobile/ui/registration/cms/RegistrationCmsMessageFragment:b04100410АА0410041004100410А	I
    //   59: aload_0
    //   60: areturn
    //   61: astore_0
    //   62: aload_0
    //   63: athrow
    //   64: astore_0
    //   65: aload_0
    //   66: athrow
    //   67: goto -19 -> 48
    // Local variable table:
    //   start	length	slot	name	signature
    //   0	70	0	paramString1	String
    //   0	70	1	paramString2	String
    //   0	70	2	paramVarArgs	String[]
    //   13	12	3	i	int
    //   17	7	4	j	int
    // Exception table:
    //   from	to	target	type
    //   0	19	61	java/lang/Exception
    //   19	48	64	java/lang/Exception
    //   48	59	64	java/lang/Exception
  }
  
  public static RegistrationCmsMessageFragment newInstanceForUnrecoverableError(@NonNull String paramString1, @NonNull String paramString2, isisss.iissss paramIissss, String... paramVarArgs)
  {
    switch (1)
    {
    case 0: 
    default: 
      for (;;)
      {
        switch (0)
        {
        }
      }
    }
    paramString1 = newInstance(paramString1, paramString2, paramIissss, paramVarArgs);
    paramString1.getArguments().putBoolean(gguuuu.bккккк043Aкк043A043A("9I=T645<OC=L8:126", '-', '\002'), true);
    int i = bА0410АА0410041004100410А;
    int j = bААА04100410041004100410А();
    int k = bА0410АА0410041004100410А;
    int m = b041004100410А0410041004100410А();
    int n = b04100410АА0410041004100410А;
    if ((bА0410АА0410041004100410А + bАА0410А0410041004100410А) * bА0410АА0410041004100410А % b0410А0410А0410041004100410А != b04100410АА0410041004100410А)
    {
      bА0410АА0410041004100410А = bА04100410А0410041004100410А();
      b04100410АА0410041004100410А = bА04100410А0410041004100410А();
    }
    if ((i + j) * k % m != n)
    {
      bА0410АА0410041004100410А = bА04100410А0410041004100410А();
      b04100410АА0410041004100410А = bА04100410А0410041004100410А();
    }
    return paramString1;
  }
  
  /* Error */
  public boolean onBackPressed()
  {
    // Byte code:
    //   0: iconst_2
    //   1: istore_1
    //   2: iconst_0
    //   3: istore_3
    //   4: aload_0
    //   5: invokevirtual 101	com/mobile/ui/registration/cms/RegistrationCmsMessageFragment:getArguments	()Landroid/os/Bundle;
    //   8: astore 5
    //   10: aload 5
    //   12: ldc 113
    //   14: bipush 52
    //   16: sipush 147
    //   19: iconst_2
    //   20: invokestatic 49	kkkkkk/gguuuu:bк043Aккк043Aкк043A043A	(Ljava/lang/String;CCC)Ljava/lang/String;
    //   23: invokevirtual 117	android/os/Bundle:getBoolean	(Ljava/lang/String;)Z
    //   26: istore 4
    //   28: getstatic 33	com/mobile/ui/registration/cms/RegistrationCmsMessageFragment:bА0410АА0410041004100410А	I
    //   31: istore_2
    //   32: iload_2
    //   33: getstatic 35	com/mobile/ui/registration/cms/RegistrationCmsMessageFragment:bАА0410А0410041004100410А	I
    //   36: iload_2
    //   37: iadd
    //   38: imul
    //   39: getstatic 37	com/mobile/ui/registration/cms/RegistrationCmsMessageFragment:b0410А0410А0410041004100410А	I
    //   42: irem
    //   43: tableswitch	default:+17->60, 0:+29->72
    //   60: invokestatic 43	com/mobile/ui/registration/cms/RegistrationCmsMessageFragment:bА04100410А0410041004100410А	()I
    //   63: putstatic 33	com/mobile/ui/registration/cms/RegistrationCmsMessageFragment:bА0410АА0410041004100410А	I
    //   66: invokestatic 43	com/mobile/ui/registration/cms/RegistrationCmsMessageFragment:bА04100410А0410041004100410А	()I
    //   69: putstatic 39	com/mobile/ui/registration/cms/RegistrationCmsMessageFragment:b04100410АА0410041004100410А	I
    //   72: iload 4
    //   74: ifeq +83 -> 157
    //   77: iload_1
    //   78: iconst_0
    //   79: idiv
    //   80: istore_1
    //   81: goto -4 -> 77
    //   84: astore 5
    //   86: invokestatic 43	com/mobile/ui/registration/cms/RegistrationCmsMessageFragment:bА04100410А0410041004100410А	()I
    //   89: putstatic 33	com/mobile/ui/registration/cms/RegistrationCmsMessageFragment:bА0410АА0410041004100410А	I
    //   92: iconst_0
    //   93: tableswitch	default:+23->116, 0:+50->143, 1:+-1->92
    //   116: iconst_1
    //   117: tableswitch	default:+23->140, 0:+-25->92, 1:+26->143
    //   140: goto -24 -> 116
    //   143: aload_0
    //   144: invokevirtual 121	com/mobile/ui/registration/cms/RegistrationCmsMessageFragment:getActivity	()Landroid/support/v4/app/FragmentActivity;
    //   147: checkcast 123	kkkkkk/iiisis
    //   150: invokeinterface 126 1 0
    //   155: iconst_1
    //   156: istore_3
    //   157: iload_3
    //   158: ireturn
    //   159: astore 5
    //   161: aload 5
    //   163: athrow
    //   164: astore 5
    //   166: aload 5
    //   168: athrow
    // Local variable table:
    //   start	length	slot	name	signature
    //   0	169	0	this	RegistrationCmsMessageFragment
    //   1	80	1	i	int
    //   31	8	2	j	int
    //   3	155	3	bool1	boolean
    //   26	47	4	bool2	boolean
    //   8	3	5	localBundle	Bundle
    //   84	1	5	localException1	Exception
    //   159	3	5	localException2	Exception
    //   164	3	5	localException3	Exception
    // Exception table:
    //   from	to	target	type
    //   77	81	84	java/lang/Exception
    //   4	10	159	java/lang/Exception
    //   143	155	159	java/lang/Exception
    //   10	28	164	java/lang/Exception
  }
  
  public void onCreate(@Nullable Bundle paramBundle)
  {
    int i = bА0410АА0410041004100410А;
    int j = bАА0410А0410041004100410А;
    int k = bА0410АА0410041004100410А;
    switch (k * (bАА0410А0410041004100410А + k) % b0410А0410А0410041004100410А)
    {
    default: 
      bА0410АА0410041004100410А = 31;
      b04100410АА0410041004100410А = bА04100410А0410041004100410А();
    }
    switch (i * (j + i) % b0410А0410А0410041004100410А)
    {
    default: 
      bА0410АА0410041004100410А = bА04100410А0410041004100410А();
      b04100410АА0410041004100410А = 19;
    }
    switch (0)
    {
    case 1: 
    default: 
      for (;;)
      {
        switch (0)
        {
        }
      }
    }
    super.onCreate(paramBundle);
    App.get().getAppComponent().b0418И0418ИИИИИИ0418(this);
  }
  
  /* Error */
  public void trackScreenView()
  {
    // Byte code:
    //   0: invokestatic 151	kkkkkk/isisss$iissss:values	()[Lkkkkkk/isisss$iissss;
    //   3: astore 5
    //   5: aload_0
    //   6: invokevirtual 101	com/mobile/ui/registration/cms/RegistrationCmsMessageFragment:getArguments	()Landroid/os/Bundle;
    //   9: astore 6
    //   11: aload 5
    //   13: aload 6
    //   15: ldc -103
    //   17: sipush 175
    //   20: iconst_1
    //   21: invokestatic 55	kkkkkk/gguuuu:bккккк043Aкк043A043A	(Ljava/lang/String;CC)Ljava/lang/String;
    //   24: iconst_0
    //   25: invokevirtual 157	android/os/Bundle:getInt	(Ljava/lang/String;I)I
    //   28: aaload
    //   29: astore 5
    //   31: getstatic 33	com/mobile/ui/registration/cms/RegistrationCmsMessageFragment:bА0410АА0410041004100410А	I
    //   34: istore_1
    //   35: getstatic 35	com/mobile/ui/registration/cms/RegistrationCmsMessageFragment:bАА0410А0410041004100410А	I
    //   38: istore_2
    //   39: getstatic 33	com/mobile/ui/registration/cms/RegistrationCmsMessageFragment:bА0410АА0410041004100410А	I
    //   42: istore_3
    //   43: getstatic 33	com/mobile/ui/registration/cms/RegistrationCmsMessageFragment:bА0410АА0410041004100410А	I
    //   46: istore 4
    //   48: iload 4
    //   50: getstatic 35	com/mobile/ui/registration/cms/RegistrationCmsMessageFragment:bАА0410А0410041004100410А	I
    //   53: iload 4
    //   55: iadd
    //   56: imul
    //   57: invokestatic 96	com/mobile/ui/registration/cms/RegistrationCmsMessageFragment:b041004100410А0410041004100410А	()I
    //   60: irem
    //   61: tableswitch	default:+19->80, 0:+31->92
    //   80: invokestatic 43	com/mobile/ui/registration/cms/RegistrationCmsMessageFragment:bА04100410А0410041004100410А	()I
    //   83: putstatic 33	com/mobile/ui/registration/cms/RegistrationCmsMessageFragment:bА0410АА0410041004100410А	I
    //   86: invokestatic 43	com/mobile/ui/registration/cms/RegistrationCmsMessageFragment:bА04100410А0410041004100410А	()I
    //   89: putstatic 39	com/mobile/ui/registration/cms/RegistrationCmsMessageFragment:b04100410АА0410041004100410А	I
    //   92: iconst_0
    //   93: tableswitch	default:+23->116, 0:+50->143, 1:+-1->92
    //   116: iconst_1
    //   117: tableswitch	default:+23->140, 0:+-25->92, 1:+26->143
    //   140: goto -24 -> 116
    //   143: iload_1
    //   144: iload_2
    //   145: iadd
    //   146: iload_3
    //   147: imul
    //   148: getstatic 37	com/mobile/ui/registration/cms/RegistrationCmsMessageFragment:b0410А0410А0410041004100410А	I
    //   151: irem
    //   152: getstatic 39	com/mobile/ui/registration/cms/RegistrationCmsMessageFragment:b04100410АА0410041004100410А	I
    //   155: if_icmpeq +14 -> 169
    //   158: bipush 31
    //   160: putstatic 33	com/mobile/ui/registration/cms/RegistrationCmsMessageFragment:bА0410АА0410041004100410А	I
    //   163: invokestatic 43	com/mobile/ui/registration/cms/RegistrationCmsMessageFragment:bА04100410А0410041004100410А	()I
    //   166: putstatic 39	com/mobile/ui/registration/cms/RegistrationCmsMessageFragment:b04100410АА0410041004100410А	I
    //   169: aload 5
    //   171: invokevirtual 160	kkkkkk/isisss$iissss:b043B043B043B043B043Bллл043B043B	()Z
    //   174: ifeq +12 -> 186
    //   177: aload_0
    //   178: getfield 162	com/mobile/ui/registration/cms/RegistrationCmsMessageFragment:mActivationAnalytics	Lkkkkkk/isisis;
    //   181: aload 5
    //   183: invokevirtual 168	kkkkkk/isisis:bл043B043Bл043Bл043B043Bл043B	(Lkkkkkk/isisss$iissss;)V
    //   186: return
    //   187: astore 5
    //   189: aload 5
    //   191: athrow
    //   192: astore 5
    //   194: aload 5
    //   196: athrow
    // Local variable table:
    //   start	length	slot	name	signature
    //   0	197	0	this	RegistrationCmsMessageFragment
    //   34	112	1	i	int
    //   38	108	2	j	int
    //   42	106	3	k	int
    //   46	11	4	m	int
    //   3	179	5	localObject	Object
    //   187	3	5	localException1	Exception
    //   192	3	5	localException2	Exception
    //   9	5	6	localBundle	Bundle
    // Exception table:
    //   from	to	target	type
    //   0	11	187	java/lang/Exception
    //   169	186	187	java/lang/Exception
    //   11	31	192	java/lang/Exception
  }
}
