package com.mobile.ui.common.fragment;

import android.content.Context;
import android.support.annotation.Nullable;
import android.support.v4.app.Fragment;
import butterknife.Unbinder;
import com.mobile.ui.common.activity.BaseActivity;
import com.mobile.ui.interstitial.activity.InterstitialActivity;
import com.mobile.ui.toolbar.view.NavigationToolbar;
import javax.inject.Inject;
import kkkkkk.mmmmnn;
import kkkkkk.ulluuu;

public abstract class BaseFragment
  extends Fragment
{
  private static final String IS_BACK_BUTTON_VISIBLE = ":ER669BW;OOPLL^VJULFQK";
  public static int b04360436ж0436жжжж = 1;
  public static int b0436жж0436жжжж = 61;
  public static int bж0436ж0436жжжж = 0;
  public static int bжж04360436жжжж = 2;
  @Inject
  public mmmmnn mKeyboardUtils;
  @Nullable
  private Unbinder mViewUnbinder;
  
  /* Error */
  static
  {
    // Byte code:
    //   0: getstatic 29	com/mobile/ui/common/fragment/BaseFragment:IS_BACK_BUTTON_VISIBLE	Ljava/lang/String;
    //   3: astore_0
    //   4: aload_0
    //   5: bipush 90
    //   7: sipush 232
    //   10: iconst_1
    //   11: invokestatic 35	kkkkkk/gguuuu:bк043Aккк043Aкк043A043A	(Ljava/lang/String;CCC)Ljava/lang/String;
    //   14: putstatic 29	com/mobile/ui/common/fragment/BaseFragment:IS_BACK_BUTTON_VISIBLE	Ljava/lang/String;
    //   17: return
    //   18: astore_0
    //   19: aload_0
    //   20: athrow
    //   21: astore_0
    //   22: aload_0
    //   23: athrow
    // Local variable table:
    //   start	length	slot	name	signature
    //   3	2	0	str	String
    //   18	2	0	localException1	Exception
    //   21	2	0	localException2	Exception
    // Exception table:
    //   from	to	target	type
    //   4	17	18	java/lang/Exception
    //   0	4	21	java/lang/Exception
  }
  
  public BaseFragment() {}
  
  public static int b0436043604360436жжжж()
  {
    return 2;
  }
  
  public static int b0436ж04360436жжжж()
  {
    return 91;
  }
  
  public static int bж043604360436жжжж()
  {
    return 1;
  }
  
  public static int bжжжж0436жжж()
  {
    return 0;
  }
  
  @Nullable
  public String getAccessibilityScreenTitle()
  {
    switch (0)
    {
    case 1: 
    default: 
      for (;;)
      {
        switch (0)
        {
        }
      }
    }
    int i = b0436жж0436жжжж;
    int j = b04360436ж0436жжжж;
    int k = b0436жж0436жжжж;
    int m = bжж04360436жжжж;
    int n = bж0436ж0436жжжж;
    switch (1)
    {
    case 0: 
    default: 
      for (;;)
      {
        switch (0)
        {
        }
      }
    }
    if ((i + j) * k % m != n)
    {
      i = b0436жж0436жжжж;
      switch (i * (b04360436ж0436жжжж + i) % bжж04360436жжжж)
      {
      default: 
        b0436жж0436жжжж = b0436ж04360436жжжж();
        bж0436ж0436жжжж = b0436ж04360436жжжж();
      }
      b0436жж0436жжжж = b0436ж04360436жжжж();
      bж0436ж0436жжжж = 84;
    }
    return null;
  }
  
  public NavigationToolbar getNavigationToolbar()
  {
    try
    {
      localObject = (BaseActivity)getActivity();
    }
    catch (Exception localException1)
    {
      try
      {
        Object localObject;
        int i = b0436жж0436жжжж;
        int j = b04360436ж0436жжжж;
        int k = b0436жж0436жжжж;
        int m = bжж04360436жжжж;
        int n = bж0436ж0436жжжж;
        if ((b0436жж0436жжжж + b04360436ж0436жжжж) * b0436жж0436жжжж % bжж04360436жжжж != bж0436ж0436жжжж)
        {
          b0436жж0436жжжж = b0436ж04360436жжжж();
          bж0436ж0436жжжж = 89;
        }
        if ((i + j) * k % m != n)
        {
          b0436жж0436жжжж = b0436ж04360436жжжж();
          bж0436ж0436жжжж = 64;
        }
        return localObject;
      }
      catch (Exception localException2)
      {
        throw localException2;
      }
      localException1 = localException1;
      throw localException1;
    }
    localObject = ((BaseActivity)localObject).getNavigationToolbar();
    switch (1)
    {
    }
    for (;;)
    {
      switch (0)
      {
      }
    }
  }
  
  public void onDestroyView()
  {
    if ((b0436жж0436жжжж + b04360436ж0436жжжж) * b0436жж0436жжжж % bжж04360436жжжж != bж0436ж0436жжжж)
    {
      b0436жж0436жжжж = b0436ж04360436жжжж();
      bж0436ж0436жжжж = 55;
    }
    super.onDestroyView();
    mmmmnn localMmmmnn = this.mKeyboardUtils;
    switch (1)
    {
    case 0: 
    default: 
      for (;;)
      {
        switch (0)
        {
        }
      }
    }
    if (localMmmmnn != null) {
      this.mKeyboardUtils.bИИ0418ИИИИИ04180418(getActivity());
    }
    if (this.mViewUnbinder != null)
    {
      this.mViewUnbinder.unbind();
      if ((b0436ж04360436жжжж() + b04360436ж0436жжжж) * b0436ж04360436жжжж() % bжж04360436жжжж != bж0436ж0436жжжж)
      {
        b0436жж0436жжжж = b0436ж04360436жжжж();
        bж0436ж0436жжжж = b0436ж04360436жжжж();
      }
    }
  }
  
  /* Error */
  public void onSaveInstanceState(android.os.Bundle paramBundle)
  {
    // Byte code:
    //   0: iconst_1
    //   1: tableswitch	default:+23->24, 0:+-1->0, 1:+50->51
    //   24: iconst_0
    //   25: tableswitch	default:+23->48, 0:+26->51, 1:+-25->0
    //   48: goto -24 -> 24
    //   51: ldc 89
    //   53: sipush 254
    //   56: iconst_4
    //   57: invokestatic 93	kkkkkk/gguuuu:bккккк043Aкк043A043A	(Ljava/lang/String;CC)Ljava/lang/String;
    //   60: astore 6
    //   62: aload_0
    //   63: invokevirtual 94	com/mobile/ui/common/fragment/BaseFragment:getNavigationToolbar	()Lcom/mobile/ui/toolbar/view/NavigationToolbar;
    //   66: invokevirtual 100	com/mobile/ui/toolbar/view/NavigationToolbar:getIsBackNavigationVisible	()Z
    //   69: istore 5
    //   71: getstatic 48	com/mobile/ui/common/fragment/BaseFragment:b0436жж0436жжжж	I
    //   74: istore_2
    //   75: invokestatic 102	com/mobile/ui/common/fragment/BaseFragment:bж043604360436жжжж	()I
    //   78: istore_3
    //   79: getstatic 52	com/mobile/ui/common/fragment/BaseFragment:bжж04360436жжжж	I
    //   82: istore 4
    //   84: iload_2
    //   85: iload_3
    //   86: iload_2
    //   87: iadd
    //   88: imul
    //   89: iload 4
    //   91: irem
    //   92: tableswitch	default:+20->112, 0:+73->165
    //   112: invokestatic 56	com/mobile/ui/common/fragment/BaseFragment:b0436ж04360436жжжж	()I
    //   115: putstatic 48	com/mobile/ui/common/fragment/BaseFragment:b0436жж0436жжжж	I
    //   118: bipush 66
    //   120: putstatic 54	com/mobile/ui/common/fragment/BaseFragment:bж0436ж0436жжжж	I
    //   123: getstatic 48	com/mobile/ui/common/fragment/BaseFragment:b0436жж0436жжжж	I
    //   126: istore_2
    //   127: iload_2
    //   128: getstatic 50	com/mobile/ui/common/fragment/BaseFragment:b04360436ж0436жжжж	I
    //   131: iload_2
    //   132: iadd
    //   133: imul
    //   134: getstatic 52	com/mobile/ui/common/fragment/BaseFragment:bжж04360436жжжж	I
    //   137: irem
    //   138: tableswitch	default:+18->156, 0:+27->165
    //   156: iconst_4
    //   157: putstatic 48	com/mobile/ui/common/fragment/BaseFragment:b0436жж0436жжжж	I
    //   160: bipush 77
    //   162: putstatic 54	com/mobile/ui/common/fragment/BaseFragment:bж0436ж0436жжжж	I
    //   165: aload_1
    //   166: aload 6
    //   168: iload 5
    //   170: invokevirtual 108	android/os/Bundle:putBoolean	(Ljava/lang/String;Z)V
    //   173: return
    //   174: astore_1
    //   175: aload_1
    //   176: athrow
    //   177: astore_1
    //   178: aload_1
    //   179: athrow
    // Local variable table:
    //   start	length	slot	name	signature
    //   0	180	0	this	BaseFragment
    //   0	180	1	paramBundle	android.os.Bundle
    //   74	60	2	i	int
    //   78	10	3	j	int
    //   82	10	4	k	int
    //   69	100	5	bool	boolean
    //   60	107	6	str	String
    // Exception table:
    //   from	to	target	type
    //   62	84	174	java/lang/Exception
    //   165	173	174	java/lang/Exception
    //   51	62	177	java/lang/Exception
    //   112	123	177	java/lang/Exception
  }
  
  /* Error */
  public void onStart()
  {
    // Byte code:
    //   0: invokestatic 56	com/mobile/ui/common/fragment/BaseFragment:b0436ж04360436жжжж	()I
    //   3: istore_1
    //   4: iload_1
    //   5: getstatic 50	com/mobile/ui/common/fragment/BaseFragment:b04360436ж0436жжжж	I
    //   8: iload_1
    //   9: iadd
    //   10: imul
    //   11: getstatic 52	com/mobile/ui/common/fragment/BaseFragment:bжж04360436жжжж	I
    //   14: irem
    //   15: tableswitch	default:+17->32, 0:+27->42
    //   32: bipush 88
    //   34: putstatic 48	com/mobile/ui/common/fragment/BaseFragment:b0436жж0436жжжж	I
    //   37: bipush 94
    //   39: putstatic 54	com/mobile/ui/common/fragment/BaseFragment:bж0436ж0436жжжж	I
    //   42: aload_0
    //   43: invokespecial 111	android/support/v4/app/Fragment:onStart	()V
    //   46: aload_0
    //   47: invokevirtual 114	com/mobile/ui/common/fragment/BaseFragment:trackScreenView	()V
    //   50: aload_0
    //   51: invokevirtual 116	com/mobile/ui/common/fragment/BaseFragment:getAccessibilityScreenTitle	()Ljava/lang/String;
    //   54: astore_2
    //   55: getstatic 48	com/mobile/ui/common/fragment/BaseFragment:b0436жж0436жжжж	I
    //   58: istore_1
    //   59: iload_1
    //   60: invokestatic 102	com/mobile/ui/common/fragment/BaseFragment:bж043604360436жжжж	()I
    //   63: iload_1
    //   64: iadd
    //   65: imul
    //   66: getstatic 52	com/mobile/ui/common/fragment/BaseFragment:bжж04360436жжжж	I
    //   69: irem
    //   70: tableswitch	default:+18->88, 0:+29->99
    //   88: invokestatic 56	com/mobile/ui/common/fragment/BaseFragment:b0436ж04360436жжжж	()I
    //   91: putstatic 48	com/mobile/ui/common/fragment/BaseFragment:b0436жж0436жжжж	I
    //   94: bipush 55
    //   96: putstatic 54	com/mobile/ui/common/fragment/BaseFragment:bж0436ж0436жжжж	I
    //   99: aload_2
    //   100: ifnull +26 -> 126
    //   103: aload_0
    //   104: invokevirtual 63	com/mobile/ui/common/fragment/BaseFragment:getActivity	()Landroid/support/v4/app/FragmentActivity;
    //   107: aload_2
    //   108: invokevirtual 122	android/support/v4/app/FragmentActivity:setTitle	(Ljava/lang/CharSequence;)V
    //   111: aload_0
    //   112: invokevirtual 63	com/mobile/ui/common/fragment/BaseFragment:getActivity	()Landroid/support/v4/app/FragmentActivity;
    //   115: invokevirtual 126	android/support/v4/app/FragmentActivity:getWindow	()Landroid/view/Window;
    //   118: invokevirtual 132	android/view/Window:getDecorView	()Landroid/view/View;
    //   121: bipush 32
    //   123: invokevirtual 138	android/view/View:sendAccessibilityEvent	(I)V
    //   126: return
    //   127: astore_2
    //   128: aload_2
    //   129: athrow
    //   130: astore_2
    //   131: aload_2
    //   132: athrow
    // Local variable table:
    //   start	length	slot	name	signature
    //   0	133	0	this	BaseFragment
    //   3	63	1	i	int
    //   54	54	2	str	String
    //   127	2	2	localException1	Exception
    //   130	2	2	localException2	Exception
    // Exception table:
    //   from	to	target	type
    //   42	55	127	java/lang/Exception
    //   103	111	127	java/lang/Exception
    //   111	126	130	java/lang/Exception
  }
  
  /* Error */
  public void onViewCreated(android.view.View paramView, @Nullable android.os.Bundle paramBundle)
  {
    // Byte code:
    //   0: getstatic 48	com/mobile/ui/common/fragment/BaseFragment:b0436жж0436жжжж	I
    //   3: istore_3
    //   4: iload_3
    //   5: getstatic 50	com/mobile/ui/common/fragment/BaseFragment:b04360436ж0436жжжж	I
    //   8: iload_3
    //   9: iadd
    //   10: imul
    //   11: invokestatic 142	com/mobile/ui/common/fragment/BaseFragment:b0436043604360436жжжж	()I
    //   14: irem
    //   15: tableswitch	default:+17->32, 0:+27->42
    //   32: bipush 86
    //   34: putstatic 48	com/mobile/ui/common/fragment/BaseFragment:b0436жж0436жжжж	I
    //   37: bipush 82
    //   39: putstatic 54	com/mobile/ui/common/fragment/BaseFragment:bж0436ж0436жжжж	I
    //   42: aload_0
    //   43: aload_1
    //   44: aload_2
    //   45: invokespecial 144	android/support/v4/app/Fragment:onViewCreated	(Landroid/view/View;Landroid/os/Bundle;)V
    //   48: aload_0
    //   49: aload_0
    //   50: aload_1
    //   51: invokestatic 150	butterknife/ButterKnife:bind	(Ljava/lang/Object;Landroid/view/View;)Lbutterknife/Unbinder;
    //   54: putfield 80	com/mobile/ui/common/fragment/BaseFragment:mViewUnbinder	Lbutterknife/Unbinder;
    //   57: aload_2
    //   58: ifnull +110 -> 168
    //   61: iconst_1
    //   62: tableswitch	default:+22->84, 0:+-1->61, 1:+49->111
    //   84: iconst_0
    //   85: tableswitch	default:+23->108, 0:+26->111, 1:+-24->61
    //   108: goto -24 -> 84
    //   111: aload_2
    //   112: ldc -104
    //   114: bipush 69
    //   116: iconst_0
    //   117: invokestatic 93	kkkkkk/gguuuu:bккккк043Aкк043A043A	(Ljava/lang/String;CC)Ljava/lang/String;
    //   120: invokevirtual 156	android/os/Bundle:getBoolean	(Ljava/lang/String;)Z
    //   123: istore 4
    //   125: getstatic 48	com/mobile/ui/common/fragment/BaseFragment:b0436жж0436жжжж	I
    //   128: getstatic 50	com/mobile/ui/common/fragment/BaseFragment:b04360436ж0436жжжж	I
    //   131: iadd
    //   132: getstatic 48	com/mobile/ui/common/fragment/BaseFragment:b0436жж0436жжжж	I
    //   135: imul
    //   136: getstatic 52	com/mobile/ui/common/fragment/BaseFragment:bжж04360436жжжж	I
    //   139: irem
    //   140: invokestatic 158	com/mobile/ui/common/fragment/BaseFragment:bжжжж0436жжж	()I
    //   143: if_icmpeq +15 -> 158
    //   146: invokestatic 56	com/mobile/ui/common/fragment/BaseFragment:b0436ж04360436жжжж	()I
    //   149: putstatic 48	com/mobile/ui/common/fragment/BaseFragment:b0436жж0436жжжж	I
    //   152: invokestatic 56	com/mobile/ui/common/fragment/BaseFragment:b0436ж04360436жжжж	()I
    //   155: putstatic 54	com/mobile/ui/common/fragment/BaseFragment:bж0436ж0436жжжж	I
    //   158: iload 4
    //   160: ifeq +8 -> 168
    //   163: aload_0
    //   164: iconst_1
    //   165: invokevirtual 162	com/mobile/ui/common/fragment/BaseFragment:setBackNavigationEnabled	(Z)V
    //   168: return
    //   169: astore_1
    //   170: aload_1
    //   171: athrow
    //   172: astore_1
    //   173: aload_1
    //   174: athrow
    // Local variable table:
    //   start	length	slot	name	signature
    //   0	175	0	this	BaseFragment
    //   0	175	1	paramView	android.view.View
    //   0	175	2	paramBundle	android.os.Bundle
    //   3	8	3	i	int
    //   123	36	4	bool	boolean
    // Exception table:
    //   from	to	target	type
    //   42	57	169	java/lang/Exception
    //   163	168	169	java/lang/Exception
    //   111	125	172	java/lang/Exception
  }
  
  public void setBackNavigationEnabled(boolean paramBoolean)
  {
    if ((b0436жж0436жжжж + b04360436ж0436жжжж) * b0436жж0436жжжж % bжж04360436жжжж != bж0436ж0436жжжж)
    {
      b0436жж0436жжжж = 1;
      bж0436ж0436жжжж = 86;
    }
    try
    {
      NavigationToolbar localNavigationToolbar = getNavigationToolbar();
      if ((b0436жж0436жжжж + b04360436ж0436жжжж) * b0436жж0436жжжж % bжж04360436жжжж != bж0436ж0436жжжж)
      {
        b0436жж0436жжжж = 27;
        bж0436ж0436жжжж = 18;
      }
      localNavigationToolbar.setBackNavigationEnabled(paramBoolean);
      return;
    }
    catch (Exception localException)
    {
      throw localException;
    }
  }
  
  /* Error */
  public void showHomeScreen()
  {
    // Byte code:
    //   0: getstatic 48	com/mobile/ui/common/fragment/BaseFragment:b0436жж0436жжжж	I
    //   3: istore_1
    //   4: iload_1
    //   5: getstatic 50	com/mobile/ui/common/fragment/BaseFragment:b04360436ж0436жжжж	I
    //   8: iload_1
    //   9: iadd
    //   10: imul
    //   11: getstatic 52	com/mobile/ui/common/fragment/BaseFragment:bжж04360436жжжж	I
    //   14: irem
    //   15: tableswitch	default:+17->32, 0:+28->43
    //   32: bipush 63
    //   34: putstatic 48	com/mobile/ui/common/fragment/BaseFragment:b0436жж0436жжжж	I
    //   37: invokestatic 56	com/mobile/ui/common/fragment/BaseFragment:b0436ж04360436жжжж	()I
    //   40: putstatic 54	com/mobile/ui/common/fragment/BaseFragment:bж0436ж0436жжжж	I
    //   43: iconst_1
    //   44: tableswitch	default:+24->68, 0:+-44->0, 1:+51->95
    //   68: iconst_1
    //   69: tableswitch	default:+23->92, 0:+-69->0, 1:+26->95
    //   92: goto -24 -> 68
    //   95: aload_0
    //   96: aload_0
    //   97: invokevirtual 169	com/mobile/ui/common/fragment/BaseFragment:getContext	()Landroid/content/Context;
    //   100: invokestatic 175	com/mobile/ui/home/activity/HomeActivity:getIntent	(Landroid/content/Context;)Landroid/content/Intent;
    //   103: invokevirtual 179	com/mobile/ui/common/fragment/BaseFragment:startActivity	(Landroid/content/Intent;)V
    //   106: getstatic 48	com/mobile/ui/common/fragment/BaseFragment:b0436жж0436жжжж	I
    //   109: istore_1
    //   110: getstatic 50	com/mobile/ui/common/fragment/BaseFragment:b04360436ж0436жжжж	I
    //   113: istore_2
    //   114: getstatic 52	com/mobile/ui/common/fragment/BaseFragment:bжж04360436жжжж	I
    //   117: istore_3
    //   118: iload_1
    //   119: iload_2
    //   120: iload_1
    //   121: iadd
    //   122: imul
    //   123: iload_3
    //   124: irem
    //   125: tableswitch	default:+19->144, 0:+31->156
    //   144: invokestatic 56	com/mobile/ui/common/fragment/BaseFragment:b0436ж04360436жжжж	()I
    //   147: putstatic 48	com/mobile/ui/common/fragment/BaseFragment:b0436жж0436жжжж	I
    //   150: invokestatic 56	com/mobile/ui/common/fragment/BaseFragment:b0436ж04360436жжжж	()I
    //   153: putstatic 54	com/mobile/ui/common/fragment/BaseFragment:bж0436ж0436жжжж	I
    //   156: return
    //   157: astore 4
    //   159: aload 4
    //   161: athrow
    //   162: astore 4
    //   164: aload 4
    //   166: athrow
    // Local variable table:
    //   start	length	slot	name	signature
    //   0	167	0	this	BaseFragment
    //   3	120	1	i	int
    //   113	9	2	j	int
    //   117	8	3	k	int
    //   157	3	4	localException1	Exception
    //   162	3	4	localException2	Exception
    // Exception table:
    //   from	to	target	type
    //   95	118	157	java/lang/Exception
    //   144	156	162	java/lang/Exception
  }
  
  public void showInterstitialPage(ulluuu paramUlluuu)
  {
    int i = b0436ж04360436жжжж();
    switch (i * (b04360436ж0436жжжж + i) % bжж04360436жжжж)
    {
    default: 
      b0436жж0436жжжж = b0436ж04360436жжжж();
      bж0436ж0436жжжж = 8;
    }
    Context localContext = getContext();
    switch (0)
    {
    case 1: 
    default: 
      for (;;)
      {
        switch (0)
        {
        case 1: 
        default: 
          for (;;)
          {
            switch (1)
            {
            }
          }
        }
        switch (0)
        {
        }
      }
    }
    if ((b0436жж0436жжжж + b04360436ж0436жжжж) * b0436жж0436жжжж % bжж04360436жжжж != bж0436ж0436жжжж)
    {
      b0436жж0436жжжж = b0436ж04360436жжжж();
      bж0436ж0436жжжж = b0436ж04360436жжжж();
    }
    startActivity(InterstitialActivity.getIntent(localContext, paramUlluuu));
  }
  
  public void showPushNotificationConflictScreen()
  {
    throw new Runtime("d2j fail translate: java.lang.IndexOutOfBoundsException: fromIndex < 0: -1\n\tat java.util.BitSet.nextSetBit(BitSet.java:712)\n\tat com.googlecode.dex2jar.ir.ts.array.FillArrayTransformer.makeSureAllElementAreAssigned(FillArrayTransformer.java:505)\n\tat com.googlecode.dex2jar.ir.ts.array.FillArrayTransformer.transformReportChanged(FillArrayTransformer.java:123)\n\tat com.googlecode.dex2jar.ir.ts.StatedTransformer.transform(StatedTransformer.java:10)\n\tat com.googlecode.d2j.dex.Dex2jar$2.optimize(Dex2jar.java:149)\n\tat com.googlecode.d2j.dex.Dex2Asm.convertCode(Dex2Asm.java:414)\n\tat com.googlecode.d2j.dex.ExDex2Asm.convertCode(ExDex2Asm.java:42)\n\tat com.googlecode.d2j.dex.Dex2jar$2.convertCode(Dex2jar.java:128)\n\tat com.googlecode.d2j.dex.Dex2Asm.convertMethod(Dex2Asm.java:509)\n\tat com.googlecode.d2j.dex.Dex2Asm.convertClass(Dex2Asm.java:406)\n\tat com.googlecode.d2j.dex.Dex2Asm.convertDex(Dex2Asm.java:422)\n\tat com.googlecode.d2j.dex.Dex2jar.doTranslate(Dex2jar.java:172)\n\tat com.googlecode.d2j.dex.Dex2jar.to(Dex2jar.java:272)\n\tat com.googlecode.dex2jar.tools.Dex2jarCmd.doCommandLine(Dex2jarCmd.java:108)\n\tat com.googlecode.dex2jar.tools.BaseCmd.doMain(BaseCmd.java:288)\n\tat com.googlecode.dex2jar.tools.Dex2jarCmd.main(Dex2jarCmd.java:32)\n");
  }
  
  public abstract void trackScreenView();
}
