package com.mobile.ui.common.fragment;

import kkkkkk.rgrrrg;
import kkkkkk.rgrrrg.ggrgrg;

public abstract class BasePreHomeScreenFragment<V extends rgrrrg.ggrgrg, P extends rgrrrg<V>>
  extends BaseRequestFragment<V, P>
{
  public static int b043604360436жж0436жж = 2;
  public static int b0436ж0436жж0436жж = 0;
  public static int bж04360436жж0436жж = 1;
  public static int bжжж0436ж0436жж = 64;
  
  public BasePreHomeScreenFragment() {}
  
  public static int bжж0436жж0436жж()
  {
    return 88;
  }
  
  /* Error */
  public void showHomeScreen()
  {
    // Byte code:
    //   0: aload_0
    //   1: aload_0
    //   2: invokevirtual 28	com/mobile/ui/common/fragment/BasePreHomeScreenFragment:getContext	()Landroid/content/Context;
    //   5: invokestatic 34	com/mobile/ui/home/activity/HomeActivity:getIntentWithoutFlags	(Landroid/content/Context;)Landroid/content/Intent;
    //   8: invokevirtual 38	com/mobile/ui/common/fragment/BasePreHomeScreenFragment:startActivity	(Landroid/content/Intent;)V
    //   11: aload_0
    //   12: invokevirtual 42	com/mobile/ui/common/fragment/BasePreHomeScreenFragment:getActivity	()Landroid/support/v4/app/FragmentActivity;
    //   15: astore_1
    //   16: invokestatic 44	com/mobile/ui/common/fragment/BasePreHomeScreenFragment:bжж0436жж0436жж	()I
    //   19: getstatic 46	com/mobile/ui/common/fragment/BasePreHomeScreenFragment:bж04360436жж0436жж	I
    //   22: iadd
    //   23: invokestatic 44	com/mobile/ui/common/fragment/BasePreHomeScreenFragment:bжж0436жж0436жж	()I
    //   26: imul
    //   27: getstatic 48	com/mobile/ui/common/fragment/BasePreHomeScreenFragment:b043604360436жж0436жж	I
    //   30: irem
    //   31: getstatic 50	com/mobile/ui/common/fragment/BasePreHomeScreenFragment:b0436ж0436жж0436жж	I
    //   34: if_icmpeq +40 -> 74
    //   37: getstatic 52	com/mobile/ui/common/fragment/BasePreHomeScreenFragment:bжжж0436ж0436жж	I
    //   40: getstatic 46	com/mobile/ui/common/fragment/BasePreHomeScreenFragment:bж04360436жж0436жж	I
    //   43: iadd
    //   44: getstatic 52	com/mobile/ui/common/fragment/BasePreHomeScreenFragment:bжжж0436ж0436жж	I
    //   47: imul
    //   48: getstatic 48	com/mobile/ui/common/fragment/BasePreHomeScreenFragment:b043604360436жж0436жж	I
    //   51: irem
    //   52: getstatic 50	com/mobile/ui/common/fragment/BasePreHomeScreenFragment:b0436ж0436жж0436жж	I
    //   55: if_icmpeq +13 -> 68
    //   58: bipush 97
    //   60: putstatic 52	com/mobile/ui/common/fragment/BasePreHomeScreenFragment:bжжж0436ж0436жж	I
    //   63: bipush 30
    //   65: putstatic 50	com/mobile/ui/common/fragment/BasePreHomeScreenFragment:b0436ж0436жж0436жж	I
    //   68: invokestatic 44	com/mobile/ui/common/fragment/BasePreHomeScreenFragment:bжж0436жж0436жж	()I
    //   71: putstatic 50	com/mobile/ui/common/fragment/BasePreHomeScreenFragment:b0436ж0436жж0436жж	I
    //   74: aload_1
    //   75: invokevirtual 57	android/support/v4/app/FragmentActivity:finishAffinity	()V
    //   78: return
    //   79: astore_1
    //   80: aload_1
    //   81: athrow
    //   82: astore_1
    //   83: aload_1
    //   84: athrow
    // Local variable table:
    //   start	length	slot	name	signature
    //   0	85	0	this	BasePreHomeScreenFragment
    //   15	60	1	localFragmentActivity	android.support.v4.app.FragmentActivity
    //   79	2	1	localException1	Exception
    //   82	2	1	localException2	Exception
    // Exception table:
    //   from	to	target	type
    //   0	16	79	java/lang/Exception
    //   74	78	82	java/lang/Exception
  }
}
