package com.mobile.ui.paymenthub.fragment;

import android.content.Context;
import android.os.Bundle;
import android.support.annotation.Nullable;
import android.view.LayoutInflater;
import android.view.View;
import android.view.ViewGroup;
import android.widget.TextView;
import butterknife.BindView;
import butterknife.OnClick;
import com.mobile.ui.R.drawable;
import com.mobile.ui.R.layout;
import com.mobile.ui.R.string;
import com.mobile.ui.common.fragment.BaseRequestFragment;
import javax.inject.Inject;
import kkkkkk.atttaa;
import kkkkkk.gguuuu;
import kkkkkk.mnmnnn;
import kkkkkk.yyyyty;

public class PaymentHubReactivateIsaDeclarationFragment
  extends BaseRequestFragment<yyyyty, atttaa>
  implements yyyyty
{
  public static final String ARG_ARRANGEMENT_ID = ")9-D%54\".&#*!).8!\033";
  public static int b04450445хх04450445х0445 = 2;
  public static int b0445х0445х04450445х0445 = 0;
  public static int b0445ххх04450445х0445 = 58;
  public static int bх0445хх04450445х0445 = 1;
  @BindView(2131492909)
  public View mAccountPlaceHolder;
  @BindView(2131493001)
  public TextView mArrangementAccountNumber;
  @BindView(2131493011)
  public TextView mArrangementSortCode;
  @BindView(2131493018)
  public TextView mArrangementTitle;
  @Inject
  public mnmnnn mCompoundDrawable;
  @BindView(2131494238)
  public TextView mHeader;
  
  static
  {
    for (;;)
    {
      try
      {
        String str = gguuuu.bк043Aккк043Aкк043A043A(ARG_ARRANGEMENT_ID, 'z', '', '\002');
        int i = b0445ххх04450445х0445;
        switch (i * (bх0445хх04450445х0445 + i) % bх04450445х04450445х0445())
        {
        case 0: 
          b0445ххх04450445х0445 = bхх0445х04450445х0445();
          b0445х0445х04450445х0445 = 39;
          ARG_ARRANGEMENT_ID = str;
          return;
        }
      }
      catch (Exception localException)
      {
        throw localException;
      }
    }
  }
  
  public PaymentHubReactivateIsaDeclarationFragment() {}
  
  public static int b044504450445х04450445х0445()
  {
    return 1;
  }
  
  public static int bх04450445х04450445х0445()
  {
    return 2;
  }
  
  public static int bх0445х044504450445х0445()
  {
    return 0;
  }
  
  public static int bхх0445х04450445х0445()
  {
    return 23;
  }
  
  public static PaymentHubReactivateIsaDeclarationFragment newInstance(@Nullable String paramString)
  {
    PaymentHubReactivateIsaDeclarationFragment localPaymentHubReactivateIsaDeclarationFragment = new PaymentHubReactivateIsaDeclarationFragment();
    if ((b0445ххх04450445х0445 + bх0445хх04450445х0445) * b0445ххх04450445х0445 % bх04450445х04450445х0445() != b0445х0445х04450445х0445)
    {
      b0445ххх04450445х0445 = bхх0445х04450445х0445();
      b0445х0445х04450445х0445 = 23;
    }
    Bundle localBundle = new Bundle();
    localBundle.putString(gguuuu.bк043Aккк043Aкк043A043A("Vh^wZlm]kedmfpw\004nj", '\002', '', '\003'), paramString);
    localPaymentHubReactivateIsaDeclarationFragment.setArguments(localBundle);
    return localPaymentHubReactivateIsaDeclarationFragment;
  }
  
  private void setHeadingIcon()
  {
    mnmnnn localMnmnnn = this.mCompoundDrawable;
    if ((b0445ххх04450445х0445 + bх0445хх04450445х0445) * b0445ххх04450445х0445 % b04450445хх04450445х0445 != b0445х0445х04450445х0445)
    {
      int i = bхх0445х04450445х0445();
      switch (i * (bх0445хх04450445х0445 + i) % b04450445хх04450445х0445)
      {
      default: 
        b0445ххх04450445х0445 = 5;
        b0445х0445х04450445х0445 = 80;
      }
      switch (1)
      {
      case 0: 
      default: 
        for (;;)
        {
          switch (1)
          {
          }
        }
      }
      b0445ххх04450445х0445 = 59;
      b0445х0445х04450445х0445 = 94;
    }
    Context localContext = getContext();
    switch (1)
    {
    case 0: 
    default: 
      for (;;)
      {
        switch (0)
        {
        }
      }
    }
    localMnmnnn.bИИ041804180418И04180418И0418(localContext, this.mHeader, R.drawable.reactivate_isa_alert_icon);
  }
  
  @Nullable
  public String getAccessibilityScreenTitle()
  {
    if ((b0445ххх04450445х0445 + b044504450445х04450445х0445()) * b0445ххх04450445х0445 % b04450445хх04450445х0445 != b0445х0445х04450445х0445)
    {
      b0445ххх04450445х0445 = bхх0445х04450445х0445();
      int i = b0445ххх04450445х0445;
      switch (i * (bх0445хх04450445х0445 + i) % b04450445хх04450445х0445)
      {
      default: 
        b0445ххх04450445х0445 = 86;
        b0445х0445х04450445х0445 = bхх0445х04450445х0445();
      }
      b0445х0445х04450445х0445 = bхх0445х04450445х0445();
    }
    try
    {
      String str = getString(R.string.accessibility_reactivate_isa_page_title);
      return str;
    }
    catch (Exception localException)
    {
      throw localException;
    }
  }
  
  /* Error */
  public void onAttach(Context paramContext)
  {
    // Byte code:
    //   0: iconst_0
    //   1: istore_2
    //   2: aload_0
    //   3: aload_1
    //   4: invokespecial 129	com/mobile/ui/common/fragment/BaseRequestFragment:onAttach	(Landroid/content/Context;)V
    //   7: aload_1
    //   8: instanceof 9
    //   11: istore 5
    //   13: iload 5
    //   15: ifne +116 -> 131
    //   18: iload_2
    //   19: iconst_0
    //   20: idiv
    //   21: istore_3
    //   22: getstatic 54	com/mobile/ui/paymenthub/fragment/PaymentHubReactivateIsaDeclarationFragment:b0445ххх04450445х0445	I
    //   25: istore 4
    //   27: iload_3
    //   28: istore_2
    //   29: iload 4
    //   31: getstatic 56	com/mobile/ui/paymenthub/fragment/PaymentHubReactivateIsaDeclarationFragment:bх0445хх04450445х0445	I
    //   34: iload 4
    //   36: iadd
    //   37: imul
    //   38: getstatic 94	com/mobile/ui/paymenthub/fragment/PaymentHubReactivateIsaDeclarationFragment:b04450445хх04450445х0445	I
    //   41: irem
    //   42: tableswitch	default:+18->60, 0:+-24->18
    //   60: bipush 12
    //   62: putstatic 54	com/mobile/ui/paymenthub/fragment/PaymentHubReactivateIsaDeclarationFragment:b0445ххх04450445х0445	I
    //   65: bipush 48
    //   67: putstatic 65	com/mobile/ui/paymenthub/fragment/PaymentHubReactivateIsaDeclarationFragment:b0445х0445х04450445х0445	I
    //   70: iload_3
    //   71: istore_2
    //   72: goto -54 -> 18
    //   75: astore 6
    //   77: invokestatic 63	com/mobile/ui/paymenthub/fragment/PaymentHubReactivateIsaDeclarationFragment:bхх0445х04450445х0445	()I
    //   80: putstatic 54	com/mobile/ui/paymenthub/fragment/PaymentHubReactivateIsaDeclarationFragment:b0445ххх04450445х0445	I
    //   83: new 131	java/lang/ClassCastException
    //   86: dup
    //   87: new 133	java/lang/StringBuilder
    //   90: dup
    //   91: invokespecial 134	java/lang/StringBuilder:<init>	()V
    //   94: aload_1
    //   95: invokevirtual 139	java/lang/Object:toString	()Ljava/lang/String;
    //   98: invokevirtual 143	java/lang/StringBuilder:append	(Ljava/lang/String;)Ljava/lang/StringBuilder;
    //   101: ldc -111
    //   103: sipush 185
    //   106: sipush 169
    //   109: iconst_3
    //   110: invokestatic 52	kkkkkk/gguuuu:bк043Aккк043Aкк043A043A	(Ljava/lang/String;CCC)Ljava/lang/String;
    //   113: invokevirtual 143	java/lang/StringBuilder:append	(Ljava/lang/String;)Ljava/lang/StringBuilder;
    //   116: invokevirtual 146	java/lang/StringBuilder:toString	()Ljava/lang/String;
    //   119: invokespecial 149	java/lang/ClassCastException:<init>	(Ljava/lang/String;)V
    //   122: astore_1
    //   123: aload_1
    //   124: athrow
    //   125: astore_1
    //   126: aload_1
    //   127: athrow
    //   128: astore_1
    //   129: aload_1
    //   130: athrow
    //   131: return
    // Local variable table:
    //   start	length	slot	name	signature
    //   0	132	0	this	PaymentHubReactivateIsaDeclarationFragment
    //   0	132	1	paramContext	Context
    //   1	71	2	i	int
    //   21	50	3	j	int
    //   25	13	4	k	int
    //   11	3	5	bool	boolean
    //   75	1	6	localException	Exception
    // Exception table:
    //   from	to	target	type
    //   18	22	75	java/lang/Exception
    //   7	13	125	java/lang/Exception
    //   123	125	125	java/lang/Exception
    //   2	7	128	java/lang/Exception
  }
  
  /* Error */
  public void onCreate(@Nullable Bundle paramBundle)
  {
    // Byte code:
    //   0: getstatic 54	com/mobile/ui/paymenthub/fragment/PaymentHubReactivateIsaDeclarationFragment:b0445ххх04450445х0445	I
    //   3: getstatic 56	com/mobile/ui/paymenthub/fragment/PaymentHubReactivateIsaDeclarationFragment:bх0445хх04450445х0445	I
    //   6: iadd
    //   7: getstatic 54	com/mobile/ui/paymenthub/fragment/PaymentHubReactivateIsaDeclarationFragment:b0445ххх04450445х0445	I
    //   10: imul
    //   11: getstatic 94	com/mobile/ui/paymenthub/fragment/PaymentHubReactivateIsaDeclarationFragment:b04450445хх04450445х0445	I
    //   14: irem
    //   15: invokestatic 152	com/mobile/ui/paymenthub/fragment/PaymentHubReactivateIsaDeclarationFragment:bх0445х044504450445х0445	()I
    //   18: if_icmpeq +48 -> 66
    //   21: invokestatic 63	com/mobile/ui/paymenthub/fragment/PaymentHubReactivateIsaDeclarationFragment:bхх0445х04450445х0445	()I
    //   24: putstatic 54	com/mobile/ui/paymenthub/fragment/PaymentHubReactivateIsaDeclarationFragment:b0445ххх04450445х0445	I
    //   27: invokestatic 63	com/mobile/ui/paymenthub/fragment/PaymentHubReactivateIsaDeclarationFragment:bхх0445х04450445х0445	()I
    //   30: putstatic 65	com/mobile/ui/paymenthub/fragment/PaymentHubReactivateIsaDeclarationFragment:b0445х0445х04450445х0445	I
    //   33: getstatic 54	com/mobile/ui/paymenthub/fragment/PaymentHubReactivateIsaDeclarationFragment:b0445ххх04450445х0445	I
    //   36: getstatic 56	com/mobile/ui/paymenthub/fragment/PaymentHubReactivateIsaDeclarationFragment:bх0445хх04450445х0445	I
    //   39: iadd
    //   40: getstatic 54	com/mobile/ui/paymenthub/fragment/PaymentHubReactivateIsaDeclarationFragment:b0445ххх04450445х0445	I
    //   43: imul
    //   44: invokestatic 60	com/mobile/ui/paymenthub/fragment/PaymentHubReactivateIsaDeclarationFragment:bх04450445х04450445х0445	()I
    //   47: irem
    //   48: getstatic 65	com/mobile/ui/paymenthub/fragment/PaymentHubReactivateIsaDeclarationFragment:b0445х0445х04450445х0445	I
    //   51: if_icmpeq +15 -> 66
    //   54: invokestatic 63	com/mobile/ui/paymenthub/fragment/PaymentHubReactivateIsaDeclarationFragment:bхх0445х04450445х0445	()I
    //   57: putstatic 54	com/mobile/ui/paymenthub/fragment/PaymentHubReactivateIsaDeclarationFragment:b0445ххх04450445х0445	I
    //   60: invokestatic 63	com/mobile/ui/paymenthub/fragment/PaymentHubReactivateIsaDeclarationFragment:bхх0445х04450445х0445	()I
    //   63: putstatic 65	com/mobile/ui/paymenthub/fragment/PaymentHubReactivateIsaDeclarationFragment:b0445х0445х04450445х0445	I
    //   66: aload_0
    //   67: aload_1
    //   68: invokespecial 154	com/mobile/ui/common/fragment/BaseRequestFragment:onCreate	(Landroid/os/Bundle;)V
    //   71: invokestatic 160	com/mobile/ui/App:get	()Lcom/mobile/ui/App;
    //   74: invokevirtual 164	com/mobile/ui/App:getAppComponent	()Lkkkkkk/uyyyyy;
    //   77: astore_1
    //   78: iconst_0
    //   79: tableswitch	default:+21->100, 0:+48->127, 1:+-1->78
    //   100: iconst_1
    //   101: tableswitch	default:+23->124, 0:+-23->78, 1:+26->127
    //   124: goto -24 -> 100
    //   127: aload_1
    //   128: aload_0
    //   129: invokeinterface 170 2 0
    //   134: return
    //   135: astore_1
    //   136: aload_1
    //   137: athrow
    //   138: astore_1
    //   139: aload_1
    //   140: athrow
    // Local variable table:
    //   start	length	slot	name	signature
    //   0	141	0	this	PaymentHubReactivateIsaDeclarationFragment
    //   0	141	1	paramBundle	Bundle
    // Exception table:
    //   from	to	target	type
    //   66	78	135	java/lang/Exception
    //   127	134	138	java/lang/Exception
  }
  
  public View onCreateView(LayoutInflater paramLayoutInflater, ViewGroup paramViewGroup, Bundle paramBundle)
  {
    try
    {
      i = R.layout.fragment_reactivate_isa_declaration;
    }
    catch (Exception paramLayoutInflater)
    {
      try
      {
        int i;
        int j;
        int k;
        int m = b04450445хх04450445х0445;
        int n = b0445х0445х04450445х0445;
        if ((i + j) * k % m != n)
        {
          if ((b0445ххх04450445х0445 + bх0445хх04450445х0445) * b0445ххх04450445х0445 % bх04450445х04450445х0445() != b0445х0445х04450445х0445)
          {
            b0445ххх04450445х0445 = 29;
            b0445х0445х04450445х0445 = 38;
          }
          b0445ххх04450445х0445 = 19;
          b0445х0445х04450445х0445 = bхх0445х04450445х0445();
        }
        return paramLayoutInflater;
      }
      catch (Exception paramLayoutInflater)
      {
        throw paramLayoutInflater;
      }
      paramLayoutInflater = paramLayoutInflater;
      throw paramLayoutInflater;
    }
    paramLayoutInflater = paramLayoutInflater.inflate(i, paramViewGroup, false);
    i = b0445ххх04450445х0445;
    j = bх0445хх04450445х0445;
    k = b0445ххх04450445х0445;
    switch (0)
    {
    }
    for (;;)
    {
      switch (1)
      {
      }
    }
  }
  
  @OnClick({2131494235})
  public void onReactivateIsaDeclarationButtonClick()
  {
    int i = b0445ххх04450445х0445;
    if ((b0445ххх04450445х0445 + bх0445хх04450445х0445) * b0445ххх04450445х0445 % b04450445хх04450445х0445 != b0445х0445х04450445х0445)
    {
      b0445ххх04450445х0445 = 40;
      b0445х0445х04450445х0445 = 98;
    }
    switch (i * (bх0445хх04450445х0445 + i) % b04450445хх04450445х0445)
    {
    default: 
      b0445ххх04450445х0445 = 17;
      b0445х0445х04450445х0445 = 53;
    }
    try
    {
      ((yhyyhh)getActivity()).onReactivateButtonClicked();
      return;
    }
    catch (Exception localException)
    {
      switch (0)
      {
      case 1: 
      default: 
        for (;;)
        {
          switch (1)
          {
          }
        }
      }
      throw localException;
    }
  }
  
  public void onViewCreated(View paramView, @Nullable Bundle paramBundle)
  {
    super.onViewCreated(paramView, paramBundle);
    setHeadingIcon();
    paramView = (atttaa)this.mPresenter;
    int i = b0445ххх04450445х0445;
    switch (i * (bх0445хх04450445х0445 + i) % b04450445хх04450445х0445)
    {
    default: 
      b0445ххх04450445х0445 = 50;
      b0445х0445х04450445х0445 = 31;
    }
    paramView.b043B043B043B043Bлллллл(getArguments().getString(gguuuu.bккккк043Aкк043A043A("q\002u\rm}|jvnkriqv\001ic", 'O', '\005')));
  }
  
  /* Error */
  public void setViews(kkkkkk.yyytyt paramYyytyt)
  {
    // Byte code:
    //   0: aload_0
    //   1: getfield 225	com/mobile/ui/paymenthub/fragment/PaymentHubReactivateIsaDeclarationFragment:mArrangementTitle	Landroid/widget/TextView;
    //   4: aload_1
    //   5: invokevirtual 230	kkkkkk/yyytyt:bлл043B043Bл043B043Bл043Bл	()Ljava/lang/String;
    //   8: invokevirtual 236	android/widget/TextView:setText	(Ljava/lang/CharSequence;)V
    //   11: getstatic 54	com/mobile/ui/paymenthub/fragment/PaymentHubReactivateIsaDeclarationFragment:b0445ххх04450445х0445	I
    //   14: istore_2
    //   15: iload_2
    //   16: getstatic 56	com/mobile/ui/paymenthub/fragment/PaymentHubReactivateIsaDeclarationFragment:bх0445хх04450445х0445	I
    //   19: iload_2
    //   20: iadd
    //   21: imul
    //   22: getstatic 94	com/mobile/ui/paymenthub/fragment/PaymentHubReactivateIsaDeclarationFragment:b04450445хх04450445х0445	I
    //   25: irem
    //   26: tableswitch	default:+18->44, 0:+29->55
    //   44: invokestatic 63	com/mobile/ui/paymenthub/fragment/PaymentHubReactivateIsaDeclarationFragment:bхх0445х04450445х0445	()I
    //   47: putstatic 54	com/mobile/ui/paymenthub/fragment/PaymentHubReactivateIsaDeclarationFragment:b0445ххх04450445х0445	I
    //   50: bipush 82
    //   52: putstatic 65	com/mobile/ui/paymenthub/fragment/PaymentHubReactivateIsaDeclarationFragment:b0445х0445х04450445х0445	I
    //   55: aload_0
    //   56: getfield 238	com/mobile/ui/paymenthub/fragment/PaymentHubReactivateIsaDeclarationFragment:mArrangementSortCode	Landroid/widget/TextView;
    //   59: astore 8
    //   61: aload_1
    //   62: invokevirtual 241	kkkkkk/yyytyt:bл043B043B043Bл043B043Bл043Bл	()Ljava/lang/String;
    //   65: astore 9
    //   67: aload 8
    //   69: aload 9
    //   71: invokestatic 246	kkkkkk/mnmnmn:b0418И0418И04180418ИИ04180418	(Ljava/lang/String;)Ljava/lang/String;
    //   74: invokevirtual 236	android/widget/TextView:setText	(Ljava/lang/CharSequence;)V
    //   77: aload_0
    //   78: getfield 248	com/mobile/ui/paymenthub/fragment/PaymentHubReactivateIsaDeclarationFragment:mArrangementAccountNumber	Landroid/widget/TextView;
    //   81: aload_1
    //   82: invokevirtual 251	kkkkkk/yyytyt:b043Bл043B043Bл043B043Bл043Bл	()Ljava/lang/String;
    //   85: invokevirtual 236	android/widget/TextView:setText	(Ljava/lang/CharSequence;)V
    //   88: aload_0
    //   89: getfield 253	com/mobile/ui/paymenthub/fragment/PaymentHubReactivateIsaDeclarationFragment:mAccountPlaceHolder	Landroid/view/View;
    //   92: astore 8
    //   94: getstatic 256	com/mobile/ui/R$string:accessibility_reactivate_isa_account_detail	I
    //   97: istore_2
    //   98: aload_1
    //   99: invokevirtual 230	kkkkkk/yyytyt:bлл043B043Bл043B043Bл043Bл	()Ljava/lang/String;
    //   102: astore 9
    //   104: getstatic 54	com/mobile/ui/paymenthub/fragment/PaymentHubReactivateIsaDeclarationFragment:b0445ххх04450445х0445	I
    //   107: istore_3
    //   108: getstatic 56	com/mobile/ui/paymenthub/fragment/PaymentHubReactivateIsaDeclarationFragment:bх0445хх04450445х0445	I
    //   111: istore 4
    //   113: getstatic 54	com/mobile/ui/paymenthub/fragment/PaymentHubReactivateIsaDeclarationFragment:b0445ххх04450445х0445	I
    //   116: istore 5
    //   118: invokestatic 60	com/mobile/ui/paymenthub/fragment/PaymentHubReactivateIsaDeclarationFragment:bх04450445х04450445х0445	()I
    //   121: istore 6
    //   123: getstatic 65	com/mobile/ui/paymenthub/fragment/PaymentHubReactivateIsaDeclarationFragment:b0445х0445х04450445х0445	I
    //   126: istore 7
    //   128: iload_3
    //   129: iload 4
    //   131: iadd
    //   132: iload 5
    //   134: imul
    //   135: iload 6
    //   137: irem
    //   138: iload 7
    //   140: if_icmpeq +15 -> 155
    //   143: invokestatic 63	com/mobile/ui/paymenthub/fragment/PaymentHubReactivateIsaDeclarationFragment:bхх0445х04450445х0445	()I
    //   146: putstatic 54	com/mobile/ui/paymenthub/fragment/PaymentHubReactivateIsaDeclarationFragment:b0445ххх04450445х0445	I
    //   149: invokestatic 63	com/mobile/ui/paymenthub/fragment/PaymentHubReactivateIsaDeclarationFragment:bхх0445х04450445х0445	()I
    //   152: putstatic 65	com/mobile/ui/paymenthub/fragment/PaymentHubReactivateIsaDeclarationFragment:b0445х0445х04450445х0445	I
    //   155: aload_1
    //   156: invokevirtual 241	kkkkkk/yyytyt:bл043B043B043Bл043B043Bл043Bл	()Ljava/lang/String;
    //   159: invokestatic 261	kkkkkk/wbbwww:b041804180418041804180418И0418И0418	(Ljava/lang/String;)Ljava/lang/String;
    //   162: astore 10
    //   164: aload_1
    //   165: invokevirtual 251	kkkkkk/yyytyt:b043Bл043B043Bл043B043Bл043Bл	()Ljava/lang/String;
    //   168: astore_1
    //   169: aload_0
    //   170: iload_2
    //   171: iconst_3
    //   172: anewarray 136	java/lang/Object
    //   175: dup
    //   176: iconst_0
    //   177: aload 9
    //   179: aastore
    //   180: dup
    //   181: iconst_1
    //   182: aload 10
    //   184: aastore
    //   185: dup
    //   186: iconst_2
    //   187: aload_1
    //   188: invokestatic 264	kkkkkk/wbbwww:b04180418ИИИИ04180418И0418	(Ljava/lang/String;)Ljava/lang/String;
    //   191: aastore
    //   192: invokevirtual 267	com/mobile/ui/paymenthub/fragment/PaymentHubReactivateIsaDeclarationFragment:getString	(I[Ljava/lang/Object;)Ljava/lang/String;
    //   195: astore_1
    //   196: aload 8
    //   198: aload_1
    //   199: invokevirtual 272	android/view/View:setContentDescription	(Ljava/lang/CharSequence;)V
    //   202: return
    //   203: astore_1
    //   204: aload_1
    //   205: athrow
    //   206: astore_1
    //   207: aload_1
    //   208: athrow
    //   209: astore_1
    //   210: aload_1
    //   211: athrow
    //   212: astore_1
    //   213: aload_1
    //   214: athrow
    // Local variable table:
    //   start	length	slot	name	signature
    //   0	215	0	this	PaymentHubReactivateIsaDeclarationFragment
    //   0	215	1	paramYyytyt	kkkkkk.yyytyt
    //   14	157	2	i	int
    //   107	25	3	j	int
    //   111	21	4	k	int
    //   116	19	5	m	int
    //   121	17	6	n	int
    //   126	15	7	i1	int
    //   59	138	8	localObject	Object
    //   65	113	9	str1	String
    //   162	21	10	str2	String
    // Exception table:
    //   from	to	target	type
    //   67	77	203	java/lang/Exception
    //   98	104	203	java/lang/Exception
    //   164	169	203	java/lang/Exception
    //   196	202	203	java/lang/Exception
    //   104	118	206	java/lang/Exception
    //   143	155	206	java/lang/Exception
    //   204	206	206	java/lang/Exception
    //   210	212	206	java/lang/Exception
    //   0	11	209	java/lang/Exception
    //   55	67	209	java/lang/Exception
    //   77	98	209	java/lang/Exception
    //   155	164	209	java/lang/Exception
    //   169	196	209	java/lang/Exception
    //   118	128	212	java/lang/Exception
  }
  
  public void trackScreenView()
  {
    if ((b0445ххх04450445х0445 + bх0445хх04450445х0445) * b0445ххх04450445х0445 % b04450445хх04450445х0445 != b0445х0445х04450445х0445)
    {
      b0445ххх04450445х0445 = 18;
      b0445х0445х04450445х0445 = bхх0445х04450445х0445();
    }
    switch (0)
    {
    case 1: 
    default: 
      for (;;)
      {
        switch (1)
        {
        case 0: 
        default: 
          for (;;)
          {
            switch (0)
            {
            }
          }
        }
        switch (1)
        {
        }
      }
    }
  }
  
  public static abstract interface yhyyhh
  {
    public abstract void onReactivateButtonClicked();
  }
}
