package com.mobile.ui.paymenthub.fragment;

import android.content.Context;
import android.os.Bundle;
import android.support.annotation.NonNull;
import android.support.annotation.Nullable;
import android.view.View;
import android.widget.TextView;
import butterknife.BindView;
import com.mobile.ui.R.string;
import com.mobile.ui.arrangementsummary.fragment.ArrangementSummaryFragment;
import javax.inject.Inject;
import kkkkkk.aallaa;
import kkkkkk.attaaa;
import kkkkkk.ccrrcc;
import kkkkkk.gguuuu;
import kkkkkk.jjqqqj.qjqqqj;
import kkkkkk.ooooio;

public class PaymentHubRemittingAccountsFragment
  extends ArrangementSummaryFragment
{
  private static final String ARG_FROM_FRAGMENT_TAG = "FXNgO\\ZYlTaQX_XbiukY`";
  public static int b043Fп043F043F043Fппп = 1;
  public static int bпп043F043F043Fппп = 0;
  public static int bпп043Fп043Fппп = b043Fпп043F043Fппп();
  public static int bппп043F043Fппп = 2;
  @BindView(2131493012)
  public View mArrangementSummaryDivider;
  @BindView(2131493014)
  public TextView mArrangementSummaryTitle;
  private aallaa mPaymentHubNavigationHandler;
  @Inject
  public attaaa mPaymentHubRemittingAccountsPresenter;
  
  /* Error */
  static
  {
    // Byte code:
    //   0: getstatic 36	com/mobile/ui/paymenthub/fragment/PaymentHubRemittingAccountsFragment:ARG_FROM_FRAGMENT_TAG	Ljava/lang/String;
    //   3: iconst_5
    //   4: iconst_0
    //   5: invokestatic 42	kkkkkk/gguuuu:bккккк043Aкк043A043A	(Ljava/lang/String;CC)Ljava/lang/String;
    //   8: astore_0
    //   9: getstatic 44	com/mobile/ui/paymenthub/fragment/PaymentHubRemittingAccountsFragment:bпп043Fп043Fппп	I
    //   12: getstatic 46	com/mobile/ui/paymenthub/fragment/PaymentHubRemittingAccountsFragment:b043Fп043F043F043Fппп	I
    //   15: iadd
    //   16: getstatic 44	com/mobile/ui/paymenthub/fragment/PaymentHubRemittingAccountsFragment:bпп043Fп043Fппп	I
    //   19: imul
    //   20: getstatic 48	com/mobile/ui/paymenthub/fragment/PaymentHubRemittingAccountsFragment:bппп043F043Fппп	I
    //   23: irem
    //   24: getstatic 50	com/mobile/ui/paymenthub/fragment/PaymentHubRemittingAccountsFragment:bпп043F043F043Fппп	I
    //   27: if_icmpeq +14 -> 41
    //   30: invokestatic 54	com/mobile/ui/paymenthub/fragment/PaymentHubRemittingAccountsFragment:b043Fпп043F043Fппп	()I
    //   33: putstatic 44	com/mobile/ui/paymenthub/fragment/PaymentHubRemittingAccountsFragment:bпп043Fп043Fппп	I
    //   36: bipush 47
    //   38: putstatic 50	com/mobile/ui/paymenthub/fragment/PaymentHubRemittingAccountsFragment:bпп043F043F043Fппп	I
    //   41: aload_0
    //   42: putstatic 36	com/mobile/ui/paymenthub/fragment/PaymentHubRemittingAccountsFragment:ARG_FROM_FRAGMENT_TAG	Ljava/lang/String;
    //   45: getstatic 44	com/mobile/ui/paymenthub/fragment/PaymentHubRemittingAccountsFragment:bпп043Fп043Fппп	I
    //   48: getstatic 46	com/mobile/ui/paymenthub/fragment/PaymentHubRemittingAccountsFragment:b043Fп043F043F043Fппп	I
    //   51: iadd
    //   52: getstatic 44	com/mobile/ui/paymenthub/fragment/PaymentHubRemittingAccountsFragment:bпп043Fп043Fппп	I
    //   55: imul
    //   56: getstatic 48	com/mobile/ui/paymenthub/fragment/PaymentHubRemittingAccountsFragment:bппп043F043Fппп	I
    //   59: irem
    //   60: getstatic 50	com/mobile/ui/paymenthub/fragment/PaymentHubRemittingAccountsFragment:bпп043F043F043Fппп	I
    //   63: if_icmpeq +14 -> 77
    //   66: bipush 60
    //   68: putstatic 44	com/mobile/ui/paymenthub/fragment/PaymentHubRemittingAccountsFragment:bпп043Fп043Fппп	I
    //   71: invokestatic 54	com/mobile/ui/paymenthub/fragment/PaymentHubRemittingAccountsFragment:b043Fпп043F043Fппп	()I
    //   74: putstatic 50	com/mobile/ui/paymenthub/fragment/PaymentHubRemittingAccountsFragment:bпп043F043F043Fппп	I
    //   77: return
    //   78: astore_0
    //   79: aload_0
    //   80: athrow
    //   81: astore_0
    //   82: aload_0
    //   83: athrow
    // Local variable table:
    //   start	length	slot	name	signature
    //   8	34	0	str	String
    //   78	2	0	localException1	Exception
    //   81	2	0	localException2	Exception
    // Exception table:
    //   from	to	target	type
    //   0	9	78	java/lang/Exception
    //   41	45	81	java/lang/Exception
  }
  
  public PaymentHubRemittingAccountsFragment() {}
  
  public static int b043F043F043Fп043Fппп()
  {
    return 2;
  }
  
  public static int b043Fп043Fп043Fппп()
  {
    return 0;
  }
  
  public static int b043Fпп043F043Fппп()
  {
    return 43;
  }
  
  public static int bп043F043Fп043Fппп()
  {
    return 1;
  }
  
  public static PaymentHubRemittingAccountsFragment newInstance(@NonNull jjqqqj.qjqqqj paramQjqqqj, @NonNull String paramString)
  {
    PaymentHubRemittingAccountsFragment localPaymentHubRemittingAccountsFragment = new PaymentHubRemittingAccountsFragment();
    switch (1)
    {
    case 0: 
    default: 
      for (;;)
      {
        switch (0)
        {
        }
      }
    }
    paramQjqqqj = getArgumentsFor(R.string.accessibility_payment_hub_remitting_accounts_title, paramQjqqqj, new ccrrcc[0]);
    paramQjqqqj.putString(gguuuu.bк043Aккк043Aкк043A043A(" 0$;!,(%6\034'\025\032\037\026\036#-!\r\022", '', '\025', '\002'), paramString);
    if ((bпп043Fп043Fппп + bп043F043Fп043Fппп()) * bпп043Fп043Fппп % b043F043F043Fп043Fппп() != b043Fп043Fп043Fппп())
    {
      switch (1)
      {
      case 0: 
      default: 
        for (;;)
        {
          switch (0)
          {
          }
        }
      }
      bпп043Fп043Fппп = 19;
      int i = bпп043Fп043Fппп;
      switch (i * (bп043F043Fп043Fппп() + i) % bппп043F043Fппп)
      {
      default: 
        bпп043Fп043Fппп = b043Fпп043F043Fппп();
        bппп043F043Fппп = b043Fпп043F043Fппп();
      }
    }
    localPaymentHubRemittingAccountsFragment.setArguments(paramQjqqqj);
    return localPaymentHubRemittingAccountsFragment;
  }
  
  public void notifyParentOfArrangementSelected(int paramInt)
  {
    throw new Runtime("d2j fail translate: java.lang.IndexOutOfBoundsException: fromIndex < 0: -1\n\tat java.util.BitSet.nextSetBit(BitSet.java:712)\n\tat com.googlecode.dex2jar.ir.ts.array.FillArrayTransformer.makeSureAllElementAreAssigned(FillArrayTransformer.java:505)\n\tat com.googlecode.dex2jar.ir.ts.array.FillArrayTransformer.transformReportChanged(FillArrayTransformer.java:123)\n\tat com.googlecode.dex2jar.ir.ts.StatedTransformer.transform(StatedTransformer.java:10)\n\tat com.googlecode.d2j.dex.Dex2jar$2.optimize(Dex2jar.java:149)\n\tat com.googlecode.d2j.dex.Dex2Asm.convertCode(Dex2Asm.java:414)\n\tat com.googlecode.d2j.dex.ExDex2Asm.convertCode(ExDex2Asm.java:42)\n\tat com.googlecode.d2j.dex.Dex2jar$2.convertCode(Dex2jar.java:128)\n\tat com.googlecode.d2j.dex.Dex2Asm.convertMethod(Dex2Asm.java:509)\n\tat com.googlecode.d2j.dex.Dex2Asm.convertClass(Dex2Asm.java:406)\n\tat com.googlecode.d2j.dex.Dex2Asm.convertDex(Dex2Asm.java:422)\n\tat com.googlecode.d2j.dex.Dex2jar.doTranslate(Dex2jar.java:172)\n\tat com.googlecode.d2j.dex.Dex2jar.to(Dex2jar.java:272)\n\tat com.googlecode.dex2jar.tools.Dex2jarCmd.doCommandLine(Dex2jarCmd.java:108)\n\tat com.googlecode.dex2jar.tools.BaseCmd.doMain(BaseCmd.java:288)\n\tat com.googlecode.dex2jar.tools.Dex2jarCmd.main(Dex2jarCmd.java:32)\n");
  }
  
  public void onAttach(Context paramContext)
  {
    try
    {
      super.onAttach(paramContext);
      if ((bпп043Fп043Fппп + b043Fп043F043F043Fппп) * bпп043Fп043Fппп % bппп043F043Fппп != bпп043F043F043Fппп)
      {
        int i = bпп043Fп043Fппп;
        switch (i * (b043Fп043F043F043Fппп + i) % bппп043F043Fппп)
        {
        default: 
          bпп043Fп043Fппп = b043Fпп043F043Fппп();
          bпп043F043F043Fппп = 71;
        }
        bпп043Fп043Fппп = b043Fпп043F043Fппп();
        bпп043F043F043Fппп = b043Fпп043F043Fппп();
      }
    }
    catch (Exception paramContext)
    {
      throw paramContext;
    }
    try
    {
      this.mPaymentHubNavigationHandler = ((aallaa)paramContext);
      return;
    }
    catch (ClassCastException localClassCastException)
    {
      ooooio.bаа043004300430а0430ааа(localClassCastException);
      paramContext = new ClassCastException(paramContext + gguuuu.bккккк043Aкк043A043A("H\027 \037!M\030\035!\036\030!\032$+W\t\0334)\",3\b6$\021%;/.)=3::\025/=4=7E", '', '\004'));
      switch (1)
      {
      }
      for (;;)
      {
        switch (1)
        {
        }
      }
    }
    catch (Exception paramContext)
    {
      throw paramContext;
    }
    throw paramContext;
  }
  
  /* Error */
  public void onCreate(@Nullable Bundle paramBundle)
  {
    // Byte code:
    //   0: aload_0
    //   1: aload_1
    //   2: invokespecial 147	com/mobile/ui/arrangementsummary/fragment/ArrangementSummaryFragment:onCreate	(Landroid/os/Bundle;)V
    //   5: invokestatic 153	com/mobile/ui/App:get	()Lcom/mobile/ui/App;
    //   8: astore_1
    //   9: getstatic 44	com/mobile/ui/paymenthub/fragment/PaymentHubRemittingAccountsFragment:bпп043Fп043Fппп	I
    //   12: istore_2
    //   13: iload_2
    //   14: getstatic 46	com/mobile/ui/paymenthub/fragment/PaymentHubRemittingAccountsFragment:b043Fп043F043F043Fппп	I
    //   17: iload_2
    //   18: iadd
    //   19: imul
    //   20: invokestatic 92	com/mobile/ui/paymenthub/fragment/PaymentHubRemittingAccountsFragment:b043F043F043Fп043Fппп	()I
    //   23: irem
    //   24: tableswitch	default:+20->44, 0:+31->55
    //   44: bipush 97
    //   46: putstatic 44	com/mobile/ui/paymenthub/fragment/PaymentHubRemittingAccountsFragment:bпп043Fп043Fппп	I
    //   49: invokestatic 54	com/mobile/ui/paymenthub/fragment/PaymentHubRemittingAccountsFragment:b043Fпп043F043Fппп	()I
    //   52: putstatic 50	com/mobile/ui/paymenthub/fragment/PaymentHubRemittingAccountsFragment:bпп043F043F043Fппп	I
    //   55: aload_1
    //   56: invokevirtual 157	com/mobile/ui/App:getAppComponent	()Lkkkkkk/uyyyyy;
    //   59: aload_0
    //   60: invokeinterface 163 2 0
    //   65: getstatic 44	com/mobile/ui/paymenthub/fragment/PaymentHubRemittingAccountsFragment:bпп043Fп043Fппп	I
    //   68: getstatic 46	com/mobile/ui/paymenthub/fragment/PaymentHubRemittingAccountsFragment:b043Fп043F043F043Fппп	I
    //   71: iadd
    //   72: getstatic 44	com/mobile/ui/paymenthub/fragment/PaymentHubRemittingAccountsFragment:bпп043Fп043Fппп	I
    //   75: imul
    //   76: getstatic 48	com/mobile/ui/paymenthub/fragment/PaymentHubRemittingAccountsFragment:bппп043F043Fппп	I
    //   79: irem
    //   80: getstatic 50	com/mobile/ui/paymenthub/fragment/PaymentHubRemittingAccountsFragment:bпп043F043F043Fппп	I
    //   83: if_icmpeq +14 -> 97
    //   86: bipush 15
    //   88: putstatic 44	com/mobile/ui/paymenthub/fragment/PaymentHubRemittingAccountsFragment:bпп043Fп043Fппп	I
    //   91: invokestatic 54	com/mobile/ui/paymenthub/fragment/PaymentHubRemittingAccountsFragment:b043Fпп043F043Fппп	()I
    //   94: putstatic 50	com/mobile/ui/paymenthub/fragment/PaymentHubRemittingAccountsFragment:bпп043F043F043Fппп	I
    //   97: return
    //   98: astore_1
    //   99: aload_1
    //   100: athrow
    //   101: astore_1
    //   102: aload_1
    //   103: athrow
    // Local variable table:
    //   start	length	slot	name	signature
    //   0	104	0	this	PaymentHubRemittingAccountsFragment
    //   0	104	1	paramBundle	Bundle
    //   12	8	2	i	int
    // Exception table:
    //   from	to	target	type
    //   0	9	98	java/lang/Exception
    //   55	91	98	java/lang/Exception
    //   91	97	101	java/lang/Exception
  }
  
  public void onViewCreated(View paramView, @Nullable Bundle paramBundle)
  {
    try
    {
      super.onViewCreated(paramView, paramBundle);
      this.mArrangementSummaryTitle.setVisibility(8);
      this.mArrangementSummaryDivider.setVisibility(8);
      if ((bпп043Fп043Fппп + b043Fп043F043F043Fппп) * bпп043Fп043Fппп % bппп043F043Fппп != bпп043F043F043Fппп)
      {
        bпп043Fп043Fппп = b043Fпп043F043Fппп();
        bпп043F043F043Fппп = b043Fпп043F043Fппп();
      }
      return;
    }
    catch (Exception paramView)
    {
      throw paramView;
    }
  }
  
  /* Error */
  public void trackScreenView()
  {
    // Byte code:
    //   0: aload_0
    //   1: getfield 182	com/mobile/ui/paymenthub/fragment/PaymentHubRemittingAccountsFragment:mPaymentHubRemittingAccountsPresenter	Lkkkkkk/attaaa;
    //   4: astore_3
    //   5: getstatic 44	com/mobile/ui/paymenthub/fragment/PaymentHubRemittingAccountsFragment:bпп043Fп043Fппп	I
    //   8: istore_1
    //   9: getstatic 46	com/mobile/ui/paymenthub/fragment/PaymentHubRemittingAccountsFragment:b043Fп043F043F043Fппп	I
    //   12: istore_2
    //   13: getstatic 44	com/mobile/ui/paymenthub/fragment/PaymentHubRemittingAccountsFragment:bпп043Fп043Fппп	I
    //   16: getstatic 46	com/mobile/ui/paymenthub/fragment/PaymentHubRemittingAccountsFragment:b043Fп043F043F043Fппп	I
    //   19: iadd
    //   20: getstatic 44	com/mobile/ui/paymenthub/fragment/PaymentHubRemittingAccountsFragment:bпп043Fп043Fппп	I
    //   23: imul
    //   24: getstatic 48	com/mobile/ui/paymenthub/fragment/PaymentHubRemittingAccountsFragment:bппп043F043Fппп	I
    //   27: irem
    //   28: getstatic 50	com/mobile/ui/paymenthub/fragment/PaymentHubRemittingAccountsFragment:bпп043F043F043Fппп	I
    //   31: if_icmpeq +14 -> 45
    //   34: bipush 29
    //   36: putstatic 44	com/mobile/ui/paymenthub/fragment/PaymentHubRemittingAccountsFragment:bпп043Fп043Fппп	I
    //   39: invokestatic 54	com/mobile/ui/paymenthub/fragment/PaymentHubRemittingAccountsFragment:b043Fпп043F043Fппп	()I
    //   42: putstatic 50	com/mobile/ui/paymenthub/fragment/PaymentHubRemittingAccountsFragment:bпп043F043F043Fппп	I
    //   45: iload_1
    //   46: iload_2
    //   47: iadd
    //   48: getstatic 44	com/mobile/ui/paymenthub/fragment/PaymentHubRemittingAccountsFragment:bпп043Fп043Fппп	I
    //   51: imul
    //   52: getstatic 48	com/mobile/ui/paymenthub/fragment/PaymentHubRemittingAccountsFragment:bппп043F043Fппп	I
    //   55: irem
    //   56: getstatic 50	com/mobile/ui/paymenthub/fragment/PaymentHubRemittingAccountsFragment:bпп043F043F043Fппп	I
    //   59: if_icmpeq +12 -> 71
    //   62: bipush 17
    //   64: putstatic 44	com/mobile/ui/paymenthub/fragment/PaymentHubRemittingAccountsFragment:bпп043Fп043Fппп	I
    //   67: iconst_3
    //   68: putstatic 50	com/mobile/ui/paymenthub/fragment/PaymentHubRemittingAccountsFragment:bпп043F043F043Fппп	I
    //   71: aload_3
    //   72: invokevirtual 187	kkkkkk/attaaa:b043Bлл043Bлл043Bллл	()V
    //   75: return
    //   76: astore_3
    //   77: aload_3
    //   78: athrow
    //   79: astore_3
    //   80: aload_3
    //   81: athrow
    //   82: astore_3
    //   83: aload_3
    //   84: athrow
    //   85: astore_3
    //   86: aload_3
    //   87: athrow
    // Local variable table:
    //   start	length	slot	name	signature
    //   0	88	0	this	PaymentHubRemittingAccountsFragment
    //   8	40	1	i	int
    //   12	36	2	j	int
    //   4	68	3	localAttaaa	attaaa
    //   76	2	3	localException1	Exception
    //   79	2	3	localException2	Exception
    //   82	2	3	localException3	Exception
    //   85	2	3	localException4	Exception
    // Exception table:
    //   from	to	target	type
    //   0	5	76	java/lang/Exception
    //   77	79	79	java/lang/Exception
    //   83	85	79	java/lang/Exception
    //   71	75	82	java/lang/Exception
    //   5	13	85	java/lang/Exception
    //   45	71	85	java/lang/Exception
  }
}
