package com.nielsen.app.sdk;

import java.util.HashMap;
import java.util.Map;
import java.util.concurrent.locks.Lock;
import java.util.concurrent.locks.ReentrantLock;

class AppTaskPendingUploader
  extends AppScheduler.AppTask
{
  public static final String a = "AppPendingUpload";
  public static final int b = 1000;
  private Lock c = new ReentrantLock();
  private a d = null;
  private j e = null;
  private f g = null;
  private Map<String, AppTaskPendingUploader.AppPendingUploadRequest> h = null;
  
  public AppTaskPendingUploader(AppScheduler paramAppScheduler, long paramLong, a paramA)
  {
    super(paramAppScheduler, "AppPendingUpload", 0L, paramLong);
    this.d = paramA;
    this.e = paramA.n();
    this.g = paramA.m();
    this.h = new HashMap();
  }
  
  /* Error */
  public boolean execute()
  {
    // Byte code:
    //   0: aload_0
    //   1: getfield 44	com/nielsen/app/sdk/AppTaskPendingUploader:d	Lcom/nielsen/app/sdk/a;
    //   4: invokevirtual 74	com/nielsen/app/sdk/a:p	()Lcom/nielsen/app/sdk/b;
    //   7: astore 17
    //   9: aload_0
    //   10: getfield 44	com/nielsen/app/sdk/AppTaskPendingUploader:d	Lcom/nielsen/app/sdk/a;
    //   13: invokevirtual 78	com/nielsen/app/sdk/a:o	()Lcom/nielsen/app/sdk/AppConfig;
    //   16: astore 20
    //   18: aload_0
    //   19: getfield 44	com/nielsen/app/sdk/AppTaskPendingUploader:d	Lcom/nielsen/app/sdk/a;
    //   22: invokevirtual 82	com/nielsen/app/sdk/a:s	()Lcom/nielsen/app/sdk/AppRequestManager;
    //   25: astore 19
    //   27: aload_0
    //   28: getfield 44	com/nielsen/app/sdk/AppTaskPendingUploader:d	Lcom/nielsen/app/sdk/a;
    //   31: invokevirtual 86	com/nielsen/app/sdk/a:r	()Lcom/nielsen/app/sdk/g;
    //   34: astore 13
    //   36: aload 17
    //   38: ifnull +949 -> 987
    //   41: aload 20
    //   43: ifnull +944 -> 987
    //   46: aload 19
    //   48: ifnull +939 -> 987
    //   51: aload 13
    //   53: ifnull +934 -> 987
    //   56: aload_0
    //   57: getfield 42	com/nielsen/app/sdk/AppTaskPendingUploader:c	Ljava/util/concurrent/locks/Lock;
    //   60: invokeinterface 91 1 0
    //   65: aload 17
    //   67: invokevirtual 97	com/nielsen/app/sdk/b:f	()J
    //   70: lstore_3
    //   71: lload_3
    //   72: lconst_0
    //   73: lcmp
    //   74: ifgt +48 -> 122
    //   77: aload_0
    //   78: getfield 48	com/nielsen/app/sdk/AppTaskPendingUploader:g	Lcom/nielsen/app/sdk/f;
    //   81: ifnull +18 -> 99
    //   84: aload_0
    //   85: getfield 48	com/nielsen/app/sdk/AppTaskPendingUploader:g	Lcom/nielsen/app/sdk/f;
    //   88: bipush 73
    //   90: ldc 99
    //   92: iconst_0
    //   93: anewarray 26	java/lang/Object
    //   96: invokevirtual 104	com/nielsen/app/sdk/f:a	(CLjava/lang/String;[Ljava/lang/Object;)V
    //   99: aload_0
    //   100: getfield 42	com/nielsen/app/sdk/AppTaskPendingUploader:c	Ljava/util/concurrent/locks/Lock;
    //   103: ifnull +12 -> 115
    //   106: aload_0
    //   107: getfield 42	com/nielsen/app/sdk/AppTaskPendingUploader:c	Ljava/util/concurrent/locks/Lock;
    //   110: invokeinterface 107 1 0
    //   115: iconst_0
    //   116: ireturn
    //   117: astore 11
    //   119: goto +807 -> 926
    //   122: aload_0
    //   123: getfield 46	com/nielsen/app/sdk/AppTaskPendingUploader:e	Lcom/nielsen/app/sdk/j;
    //   126: invokevirtual 112	com/nielsen/app/sdk/j:w	()Z
    //   129: istore 9
    //   131: iload 9
    //   133: ifne +21 -> 154
    //   136: aload_0
    //   137: getfield 42	com/nielsen/app/sdk/AppTaskPendingUploader:c	Ljava/util/concurrent/locks/Lock;
    //   140: ifnull +12 -> 152
    //   143: aload_0
    //   144: getfield 42	com/nielsen/app/sdk/AppTaskPendingUploader:c	Ljava/util/concurrent/locks/Lock;
    //   147: invokeinterface 107 1 0
    //   152: iconst_1
    //   153: ireturn
    //   154: aload 20
    //   156: invokevirtual 117	com/nielsen/app/sdk/AppConfig:i	()Z
    //   159: istore 9
    //   161: iload 9
    //   163: ifne +21 -> 184
    //   166: aload_0
    //   167: getfield 42	com/nielsen/app/sdk/AppTaskPendingUploader:c	Ljava/util/concurrent/locks/Lock;
    //   170: ifnull +12 -> 182
    //   173: aload_0
    //   174: getfield 42	com/nielsen/app/sdk/AppTaskPendingUploader:c	Ljava/util/concurrent/locks/Lock;
    //   177: invokeinterface 107 1 0
    //   182: iconst_1
    //   183: ireturn
    //   184: aload_0
    //   185: getfield 46	com/nielsen/app/sdk/AppTaskPendingUploader:e	Lcom/nielsen/app/sdk/j;
    //   188: invokevirtual 119	com/nielsen/app/sdk/j:h	()Z
    //   191: istore 9
    //   193: aload_0
    //   194: getfield 46	com/nielsen/app/sdk/AppTaskPendingUploader:e	Lcom/nielsen/app/sdk/j;
    //   197: invokevirtual 122	com/nielsen/app/sdk/j:j	()Z
    //   200: istore 10
    //   202: iload 9
    //   204: ifne +697 -> 901
    //   207: iload 10
    //   209: ifeq +6 -> 215
    //   212: goto +689 -> 901
    //   215: aload 17
    //   217: iconst_2
    //   218: iconst_0
    //   219: iconst_1
    //   220: invokevirtual 125	com/nielsen/app/sdk/b:a	(IIZ)Lcom/nielsen/app/sdk/b$a;
    //   223: astore 18
    //   225: ldc 127
    //   227: astore 11
    //   229: aload 18
    //   231: ifnull +806 -> 1037
    //   234: aload 11
    //   236: astore 12
    //   238: aload 13
    //   240: aload 18
    //   242: invokevirtual 132	com/nielsen/app/sdk/b$a:b	()I
    //   245: invokevirtual 137	com/nielsen/app/sdk/g:a	(I)Lcom/nielsen/app/sdk/AppProcessor;
    //   248: astore 13
    //   250: aload 13
    //   252: ifnull +29 -> 281
    //   255: aload 11
    //   257: astore 12
    //   259: aload 13
    //   261: invokevirtual 142	com/nielsen/app/sdk/AppProcessor:c	()Ljava/lang/String;
    //   264: astore 11
    //   266: aload 13
    //   268: invokevirtual 145	com/nielsen/app/sdk/AppProcessor:e	()Lcom/nielsen/app/sdk/d;
    //   271: astore 13
    //   273: goto +11 -> 284
    //   276: astore 12
    //   278: goto +544 -> 822
    //   281: aconst_null
    //   282: astore 13
    //   284: aload 18
    //   286: invokevirtual 147	com/nielsen/app/sdk/b$a:e	()Ljava/lang/String;
    //   289: astore 15
    //   291: aload 18
    //   293: invokevirtual 149	com/nielsen/app/sdk/b$a:c	()I
    //   296: istore_1
    //   297: iload_1
    //   298: bipush 8
    //   300: if_icmpne +718 -> 1018
    //   303: aload 13
    //   305: ifnull +209 -> 514
    //   308: aload 11
    //   310: ifnull +204 -> 514
    //   313: aload 11
    //   315: astore 12
    //   317: aload 11
    //   319: invokevirtual 154	java/lang/String:isEmpty	()Z
    //   322: ifne +192 -> 514
    //   325: aload 15
    //   327: ifnull +34 -> 361
    //   330: aload 11
    //   332: astore 12
    //   334: aload 15
    //   336: invokevirtual 154	java/lang/String:isEmpty	()Z
    //   339: ifne +22 -> 361
    //   342: aload 11
    //   344: astore 12
    //   346: aload 13
    //   348: new 156	org/json/JSONObject
    //   351: dup
    //   352: aload 15
    //   354: invokespecial 159	org/json/JSONObject:<init>	(Ljava/lang/String;)V
    //   357: invokevirtual 164	com/nielsen/app/sdk/d:b	(Lorg/json/JSONObject;)Ljava/util/Map;
    //   360: pop
    //   361: aload 11
    //   363: astore 12
    //   365: aload 13
    //   367: aload 11
    //   369: invokevirtual 167	com/nielsen/app/sdk/d:h	(Ljava/lang/String;)Ljava/lang/String;
    //   372: astore 16
    //   374: aload 16
    //   376: ifnull +97 -> 473
    //   379: aload 11
    //   381: astore 12
    //   383: aload 16
    //   385: invokevirtual 154	java/lang/String:isEmpty	()Z
    //   388: ifne +85 -> 473
    //   391: aload 11
    //   393: astore 12
    //   395: new 169	java/lang/StringBuilder
    //   398: dup
    //   399: invokespecial 170	java/lang/StringBuilder:<init>	()V
    //   402: astore 14
    //   404: aload 11
    //   406: astore 12
    //   408: aload 14
    //   410: aload 16
    //   412: invokevirtual 174	java/lang/StringBuilder:append	(Ljava/lang/String;)Ljava/lang/StringBuilder;
    //   415: pop
    //   416: aload 11
    //   418: astore 12
    //   420: aload 14
    //   422: invokestatic 177	com/nielsen/app/sdk/j:y	()Ljava/lang/String;
    //   425: invokevirtual 174	java/lang/StringBuilder:append	(Ljava/lang/String;)Ljava/lang/StringBuilder;
    //   428: pop
    //   429: aload 11
    //   431: astore 12
    //   433: aload 14
    //   435: invokevirtual 180	java/lang/StringBuilder:toString	()Ljava/lang/String;
    //   438: astore 14
    //   440: aload 11
    //   442: astore 12
    //   444: aload_0
    //   445: getfield 48	com/nielsen/app/sdk/AppTaskPendingUploader:g	Lcom/nielsen/app/sdk/f;
    //   448: ifnull +565 -> 1013
    //   451: aload 11
    //   453: astore 12
    //   455: aload_0
    //   456: getfield 48	com/nielsen/app/sdk/AppTaskPendingUploader:g	Lcom/nielsen/app/sdk/f;
    //   459: bipush 73
    //   461: ldc -74
    //   463: iconst_0
    //   464: anewarray 26	java/lang/Object
    //   467: invokevirtual 104	com/nielsen/app/sdk/f:a	(CLjava/lang/String;[Ljava/lang/Object;)V
    //   470: goto +543 -> 1013
    //   473: aload 11
    //   475: astore 12
    //   477: aload 16
    //   479: astore 14
    //   481: aload_0
    //   482: getfield 48	com/nielsen/app/sdk/AppTaskPendingUploader:g	Lcom/nielsen/app/sdk/f;
    //   485: ifnull +537 -> 1022
    //   488: aload 11
    //   490: astore 12
    //   492: aload_0
    //   493: getfield 48	com/nielsen/app/sdk/AppTaskPendingUploader:g	Lcom/nielsen/app/sdk/f;
    //   496: bipush 73
    //   498: ldc -72
    //   500: iconst_0
    //   501: anewarray 26	java/lang/Object
    //   504: invokevirtual 104	com/nielsen/app/sdk/f:a	(CLjava/lang/String;[Ljava/lang/Object;)V
    //   507: aload 16
    //   509: astore 14
    //   511: goto +511 -> 1022
    //   514: aload 11
    //   516: astore 12
    //   518: aload_0
    //   519: getfield 48	com/nielsen/app/sdk/AppTaskPendingUploader:g	Lcom/nielsen/app/sdk/f;
    //   522: ifnull +496 -> 1018
    //   525: aload 11
    //   527: astore 12
    //   529: aload_0
    //   530: getfield 48	com/nielsen/app/sdk/AppTaskPendingUploader:g	Lcom/nielsen/app/sdk/f;
    //   533: bipush 73
    //   535: ldc -70
    //   537: iconst_0
    //   538: anewarray 26	java/lang/Object
    //   541: invokevirtual 104	com/nielsen/app/sdk/f:a	(CLjava/lang/String;[Ljava/lang/Object;)V
    //   544: goto +474 -> 1018
    //   547: iload_1
    //   548: bipush 8
    //   550: if_icmpeq +310 -> 860
    //   553: aload 13
    //   555: ifnull +470 -> 1025
    //   558: aload 11
    //   560: astore 12
    //   562: aload 13
    //   564: ldc -68
    //   566: ldc2_w 189
    //   569: invokevirtual 193	com/nielsen/app/sdk/d:a	(Ljava/lang/String;J)J
    //   572: lstore_3
    //   573: lload_3
    //   574: lconst_0
    //   575: lcmp
    //   576: ifeq +449 -> 1025
    //   579: ldc2_w 194
    //   582: lload_3
    //   583: lmul
    //   584: ldc2_w 196
    //   587: ladd
    //   588: lstore_3
    //   589: goto +3 -> 592
    //   592: aload 15
    //   594: astore 13
    //   596: aload 14
    //   598: ifnull +30 -> 628
    //   601: aload 11
    //   603: astore 12
    //   605: aload 14
    //   607: invokevirtual 154	java/lang/String:isEmpty	()Z
    //   610: istore 9
    //   612: iload 9
    //   614: ifeq +10 -> 624
    //   617: aload 15
    //   619: astore 13
    //   621: goto +7 -> 628
    //   624: aload 14
    //   626: astore 13
    //   628: aload 13
    //   630: ifnull +230 -> 860
    //   633: aload 13
    //   635: invokevirtual 154	java/lang/String:isEmpty	()Z
    //   638: ifne +222 -> 860
    //   641: aload 20
    //   643: invokestatic 199	com/nielsen/app/sdk/j:m	()J
    //   646: invokevirtual 202	com/nielsen/app/sdk/AppConfig:a	(J)Landroid/util/Pair;
    //   649: astore 14
    //   651: aload 18
    //   653: invokevirtual 204	com/nielsen/app/sdk/b$a:d	()J
    //   656: lstore 5
    //   658: aload 14
    //   660: ifnull +110 -> 770
    //   663: aload 11
    //   665: astore 12
    //   667: aload 14
    //   669: getfield 210	android/util/Pair:first	Ljava/lang/Object;
    //   672: checkcast 212	java/lang/Long
    //   675: invokevirtual 215	java/lang/Long:longValue	()J
    //   678: lload 5
    //   680: lsub
    //   681: lstore 7
    //   683: lload 7
    //   685: lconst_0
    //   686: lcmp
    //   687: ifle +83 -> 770
    //   690: lload_3
    //   691: lconst_0
    //   692: lcmp
    //   693: ifle +77 -> 770
    //   696: lload 7
    //   698: lload_3
    //   699: lcmp
    //   700: ifle +70 -> 770
    //   703: aload 11
    //   705: astore 12
    //   707: new 169	java/lang/StringBuilder
    //   710: dup
    //   711: invokespecial 170	java/lang/StringBuilder:<init>	()V
    //   714: astore 14
    //   716: aload 11
    //   718: astore 12
    //   720: aload 14
    //   722: aload 13
    //   724: invokevirtual 174	java/lang/StringBuilder:append	(Ljava/lang/String;)Ljava/lang/StringBuilder;
    //   727: pop
    //   728: aload 11
    //   730: astore 12
    //   732: aload 14
    //   734: ldc -39
    //   736: invokevirtual 174	java/lang/StringBuilder:append	(Ljava/lang/String;)Ljava/lang/StringBuilder;
    //   739: pop
    //   740: aload 11
    //   742: astore 12
    //   744: aload 14
    //   746: lload 7
    //   748: invokevirtual 220	java/lang/StringBuilder:append	(J)Ljava/lang/StringBuilder;
    //   751: pop
    //   752: aload 11
    //   754: astore 12
    //   756: aload 14
    //   758: invokevirtual 180	java/lang/StringBuilder:toString	()Ljava/lang/String;
    //   761: astore 13
    //   763: aload 13
    //   765: astore 12
    //   767: goto +7 -> 774
    //   770: aload 13
    //   772: astore 12
    //   774: aload 18
    //   776: invokevirtual 132	com/nielsen/app/sdk/b$a:b	()I
    //   779: istore_2
    //   780: new 222	com/nielsen/app/sdk/AppTaskPendingUploader$AppPendingUploadRequest
    //   783: dup
    //   784: aload_0
    //   785: aload 19
    //   787: aload 12
    //   789: iload_1
    //   790: iload_2
    //   791: lload 5
    //   793: invokespecial 225	com/nielsen/app/sdk/AppTaskPendingUploader$AppPendingUploadRequest:<init>	(Lcom/nielsen/app/sdk/AppTaskPendingUploader;Lcom/nielsen/app/sdk/AppRequestManager;Ljava/lang/String;IIJ)V
    //   796: invokevirtual 228	com/nielsen/app/sdk/AppTaskPendingUploader$AppPendingUploadRequest:startRequest	()V
    //   799: goto +61 -> 860
    //   802: astore 12
    //   804: goto +18 -> 822
    //   807: astore 12
    //   809: goto +13 -> 822
    //   812: astore 13
    //   814: aload 12
    //   816: astore 11
    //   818: aload 13
    //   820: astore 12
    //   822: aload_0
    //   823: getfield 48	com/nielsen/app/sdk/AppTaskPendingUploader:g	Lcom/nielsen/app/sdk/f;
    //   826: ifnull +34 -> 860
    //   829: aload_0
    //   830: getfield 48	com/nielsen/app/sdk/AppTaskPendingUploader:g	Lcom/nielsen/app/sdk/f;
    //   833: astore 13
    //   835: aload 13
    //   837: aload 12
    //   839: bipush 10
    //   841: bipush 69
    //   843: ldc -26
    //   845: iconst_1
    //   846: anewarray 26	java/lang/Object
    //   849: dup
    //   850: iconst_0
    //   851: aload 11
    //   853: aastore
    //   854: invokevirtual 233	com/nielsen/app/sdk/f:a	(Ljava/lang/Throwable;ICLjava/lang/String;[Ljava/lang/Object;)V
    //   857: goto +3 -> 860
    //   860: aload 18
    //   862: invokevirtual 234	com/nielsen/app/sdk/b$a:f	()J
    //   865: lstore_3
    //   866: goto +3 -> 869
    //   869: aload 17
    //   871: iconst_2
    //   872: lload_3
    //   873: invokevirtual 237	com/nielsen/app/sdk/b:a	(IJ)J
    //   876: pop2
    //   877: aload_0
    //   878: getfield 42	com/nielsen/app/sdk/AppTaskPendingUploader:c	Ljava/util/concurrent/locks/Lock;
    //   881: ifnull +12 -> 893
    //   884: aload_0
    //   885: getfield 42	com/nielsen/app/sdk/AppTaskPendingUploader:c	Ljava/util/concurrent/locks/Lock;
    //   888: invokeinterface 107 1 0
    //   893: goto +73 -> 966
    //   896: astore 11
    //   898: goto +28 -> 926
    //   901: aload_0
    //   902: getfield 42	com/nielsen/app/sdk/AppTaskPendingUploader:c	Ljava/util/concurrent/locks/Lock;
    //   905: ifnull +12 -> 917
    //   908: aload_0
    //   909: getfield 42	com/nielsen/app/sdk/AppTaskPendingUploader:c	Ljava/util/concurrent/locks/Lock;
    //   912: invokeinterface 107 1 0
    //   917: iconst_1
    //   918: ireturn
    //   919: astore 11
    //   921: goto +47 -> 968
    //   924: astore 11
    //   926: aload_0
    //   927: getfield 48	com/nielsen/app/sdk/AppTaskPendingUploader:g	Lcom/nielsen/app/sdk/f;
    //   930: ifnull +20 -> 950
    //   933: aload_0
    //   934: getfield 48	com/nielsen/app/sdk/AppTaskPendingUploader:g	Lcom/nielsen/app/sdk/f;
    //   937: aload 11
    //   939: bipush 69
    //   941: ldc -17
    //   943: iconst_0
    //   944: anewarray 26	java/lang/Object
    //   947: invokevirtual 242	com/nielsen/app/sdk/f:a	(Ljava/lang/Throwable;CLjava/lang/String;[Ljava/lang/Object;)V
    //   950: aload_0
    //   951: getfield 42	com/nielsen/app/sdk/AppTaskPendingUploader:c	Ljava/util/concurrent/locks/Lock;
    //   954: ifnull +12 -> 966
    //   957: aload_0
    //   958: getfield 42	com/nielsen/app/sdk/AppTaskPendingUploader:c	Ljava/util/concurrent/locks/Lock;
    //   961: invokeinterface 107 1 0
    //   966: iconst_1
    //   967: ireturn
    //   968: aload_0
    //   969: getfield 42	com/nielsen/app/sdk/AppTaskPendingUploader:c	Ljava/util/concurrent/locks/Lock;
    //   972: ifnull +12 -> 984
    //   975: aload_0
    //   976: getfield 42	com/nielsen/app/sdk/AppTaskPendingUploader:c	Ljava/util/concurrent/locks/Lock;
    //   979: invokeinterface 107 1 0
    //   984: aload 11
    //   986: athrow
    //   987: aload_0
    //   988: getfield 48	com/nielsen/app/sdk/AppTaskPendingUploader:g	Lcom/nielsen/app/sdk/f;
    //   991: ifnull +20 -> 1011
    //   994: aload_0
    //   995: getfield 48	com/nielsen/app/sdk/AppTaskPendingUploader:g	Lcom/nielsen/app/sdk/f;
    //   998: bipush 10
    //   1000: bipush 69
    //   1002: ldc -12
    //   1004: iconst_0
    //   1005: anewarray 26	java/lang/Object
    //   1008: invokevirtual 247	com/nielsen/app/sdk/f:a	(ICLjava/lang/String;[Ljava/lang/Object;)V
    //   1011: iconst_0
    //   1012: ireturn
    //   1013: iconst_3
    //   1014: istore_1
    //   1015: goto -468 -> 547
    //   1018: ldc 127
    //   1020: astore 14
    //   1022: goto -475 -> 547
    //   1025: ldc2_w 248
    //   1028: lstore_3
    //   1029: goto -437 -> 592
    //   1032: astore 11
    //   1034: goto -108 -> 926
    //   1037: ldc2_w 250
    //   1040: lstore_3
    //   1041: goto -172 -> 869
    // Exception table:
    //   from	to	target	type
    //   77	99	117	java/lang/Exception
    //   215	225	117	java/lang/Exception
    //   266	273	276	java/lang/Exception
    //   780	799	802	java/lang/Exception
    //   284	297	807	java/lang/Exception
    //   633	658	807	java/lang/Exception
    //   774	780	807	java/lang/Exception
    //   238	250	812	java/lang/Exception
    //   259	266	812	java/lang/Exception
    //   317	325	812	java/lang/Exception
    //   334	342	812	java/lang/Exception
    //   346	361	812	java/lang/Exception
    //   365	374	812	java/lang/Exception
    //   383	391	812	java/lang/Exception
    //   395	404	812	java/lang/Exception
    //   408	416	812	java/lang/Exception
    //   420	429	812	java/lang/Exception
    //   433	440	812	java/lang/Exception
    //   444	451	812	java/lang/Exception
    //   455	470	812	java/lang/Exception
    //   481	488	812	java/lang/Exception
    //   492	507	812	java/lang/Exception
    //   518	525	812	java/lang/Exception
    //   529	544	812	java/lang/Exception
    //   562	573	812	java/lang/Exception
    //   605	612	812	java/lang/Exception
    //   667	683	812	java/lang/Exception
    //   707	716	812	java/lang/Exception
    //   720	728	812	java/lang/Exception
    //   732	740	812	java/lang/Exception
    //   744	752	812	java/lang/Exception
    //   756	763	812	java/lang/Exception
    //   822	835	896	java/lang/Exception
    //   835	857	896	java/lang/Exception
    //   860	866	896	java/lang/Exception
    //   869	877	896	java/lang/Exception
    //   56	71	919	finally
    //   77	99	919	finally
    //   122	131	919	finally
    //   154	161	919	finally
    //   184	202	919	finally
    //   215	225	919	finally
    //   238	250	919	finally
    //   259	266	919	finally
    //   266	273	919	finally
    //   284	297	919	finally
    //   317	325	919	finally
    //   334	342	919	finally
    //   346	361	919	finally
    //   365	374	919	finally
    //   383	391	919	finally
    //   395	404	919	finally
    //   408	416	919	finally
    //   420	429	919	finally
    //   433	440	919	finally
    //   444	451	919	finally
    //   455	470	919	finally
    //   481	488	919	finally
    //   492	507	919	finally
    //   518	525	919	finally
    //   529	544	919	finally
    //   562	573	919	finally
    //   605	612	919	finally
    //   633	658	919	finally
    //   667	683	919	finally
    //   707	716	919	finally
    //   720	728	919	finally
    //   732	740	919	finally
    //   744	752	919	finally
    //   756	763	919	finally
    //   774	780	919	finally
    //   780	799	919	finally
    //   822	835	919	finally
    //   835	857	919	finally
    //   860	866	919	finally
    //   869	877	919	finally
    //   926	950	919	finally
    //   56	71	924	java/lang/Exception
    //   122	131	924	java/lang/Exception
    //   154	161	924	java/lang/Exception
    //   184	202	924	java/lang/Exception
  }
}
