package com.google.android.gms.internal;

import android.os.Binder;
import android.os.IBinder;
import android.os.IInterface;
import android.os.Parcel;
import android.os.Parcelable.Creator;
import android.os.RemoteException;
import com.google.android.gms.fitness.request.DailyTotalRequest;
import com.google.android.gms.fitness.request.DataDeleteRequest;
import com.google.android.gms.fitness.request.DataInsertRequest;
import com.google.android.gms.fitness.request.DataReadRequest;
import com.google.android.gms.fitness.request.GetSyncInfoRequest;
import com.google.android.gms.fitness.request.ReadRawRequest;
import com.google.android.gms.fitness.request.ReadStatsRequest;

public abstract interface zzmk
  extends IInterface
{
  public abstract void zza(DailyTotalRequest paramDailyTotalRequest)
    throws RemoteException;
  
  public abstract void zza(DataDeleteRequest paramDataDeleteRequest)
    throws RemoteException;
  
  public abstract void zza(DataInsertRequest paramDataInsertRequest)
    throws RemoteException;
  
  public abstract void zza(DataReadRequest paramDataReadRequest)
    throws RemoteException;
  
  public abstract void zza(GetSyncInfoRequest paramGetSyncInfoRequest)
    throws RemoteException;
  
  public abstract void zza(ReadRawRequest paramReadRawRequest)
    throws RemoteException;
  
  public abstract void zza(ReadStatsRequest paramReadStatsRequest)
    throws RemoteException;
  
  public static abstract class zza
    extends Binder
    implements zzmk
  {
    public static zzmk zzbv(IBinder paramIBinder)
    {
      if (paramIBinder == null) {
        return null;
      }
      IInterface localIInterface = paramIBinder.queryLocalInterface("com.google.android.gms.fitness.internal.IGoogleFitHistoryApi");
      if ((localIInterface != null) && ((localIInterface instanceof zzmk))) {
        return (zzmk)localIInterface;
      }
      return new zza(paramIBinder);
    }
    
    public boolean onTransact(int paramInt1, Parcel paramParcel1, Parcel paramParcel2, int paramInt2)
      throws RemoteException
    {
      Object localObject2 = null;
      Object localObject3 = null;
      Object localObject4 = null;
      Object localObject5 = null;
      Object localObject6 = null;
      Object localObject7 = null;
      Object localObject1 = null;
      switch (paramInt1)
      {
      default: 
        return super.onTransact(paramInt1, paramParcel1, paramParcel2, paramInt2);
      case 1598968902: 
        paramParcel2.writeString("com.google.android.gms.fitness.internal.IGoogleFitHistoryApi");
        return true;
      case 1: 
        paramParcel1.enforceInterface("com.google.android.gms.fitness.internal.IGoogleFitHistoryApi");
        paramParcel2 = localObject1;
        if (paramParcel1.readInt() != 0) {
          paramParcel2 = (DataReadRequest)DataReadRequest.CREATOR.createFromParcel(paramParcel1);
        }
        zza(paramParcel2);
        return true;
      case 2: 
        paramParcel1.enforceInterface("com.google.android.gms.fitness.internal.IGoogleFitHistoryApi");
        paramParcel2 = localObject2;
        if (paramParcel1.readInt() != 0) {
          paramParcel2 = (DataInsertRequest)DataInsertRequest.CREATOR.createFromParcel(paramParcel1);
        }
        zza(paramParcel2);
        return true;
      case 3: 
        paramParcel1.enforceInterface("com.google.android.gms.fitness.internal.IGoogleFitHistoryApi");
        paramParcel2 = localObject3;
        if (paramParcel1.readInt() != 0) {
          paramParcel2 = (DataDeleteRequest)DataDeleteRequest.CREATOR.createFromParcel(paramParcel1);
        }
        zza(paramParcel2);
        return true;
      case 4: 
        paramParcel1.enforceInterface("com.google.android.gms.fitness.internal.IGoogleFitHistoryApi");
        paramParcel2 = localObject4;
        if (paramParcel1.readInt() != 0) {
          paramParcel2 = (GetSyncInfoRequest)GetSyncInfoRequest.CREATOR.createFromParcel(paramParcel1);
        }
        zza(paramParcel2);
        return true;
      case 5: 
        paramParcel1.enforceInterface("com.google.android.gms.fitness.internal.IGoogleFitHistoryApi");
        paramParcel2 = localObject5;
        if (paramParcel1.readInt() != 0) {
          paramParcel2 = (ReadStatsRequest)ReadStatsRequest.CREATOR.createFromParcel(paramParcel1);
        }
        zza(paramParcel2);
        return true;
      case 6: 
        paramParcel1.enforceInterface("com.google.android.gms.fitness.internal.IGoogleFitHistoryApi");
        paramParcel2 = localObject6;
        if (paramParcel1.readInt() != 0) {
          paramParcel2 = (ReadRawRequest)ReadRawRequest.CREATOR.createFromParcel(paramParcel1);
        }
        zza(paramParcel2);
        return true;
      }
      paramParcel1.enforceInterface("com.google.android.gms.fitness.internal.IGoogleFitHistoryApi");
      paramParcel2 = localObject7;
      if (paramParcel1.readInt() != 0) {
        paramParcel2 = (DailyTotalRequest)DailyTotalRequest.CREATOR.createFromParcel(paramParcel1);
      }
      zza(paramParcel2);
      return true;
    }
    
    private static class zza
      implements zzmk
    {
      private IBinder zznF;
      
      zza(IBinder paramIBinder)
      {
        this.zznF = paramIBinder;
      }
      
      public IBinder asBinder()
      {
        return this.zznF;
      }
      
      /* Error */
      public void zza(DailyTotalRequest paramDailyTotalRequest)
        throws RemoteException
      {
        // Byte code:
        //   0: invokestatic 30	android/os/Parcel:obtain	()Landroid/os/Parcel;
        //   3: astore_2
        //   4: aload_2
        //   5: ldc 32
        //   7: invokevirtual 36	android/os/Parcel:writeInterfaceToken	(Ljava/lang/String;)V
        //   10: aload_1
        //   11: ifnull +34 -> 45
        //   14: aload_2
        //   15: iconst_1
        //   16: invokevirtual 40	android/os/Parcel:writeInt	(I)V
        //   19: aload_1
        //   20: aload_2
        //   21: iconst_0
        //   22: invokevirtual 46	com/google/android/gms/fitness/request/DailyTotalRequest:writeToParcel	(Landroid/os/Parcel;I)V
        //   25: aload_0
        //   26: getfield 18	com/google/android/gms/internal/zzmk$zza$zza:zznF	Landroid/os/IBinder;
        //   29: bipush 7
        //   31: aload_2
        //   32: aconst_null
        //   33: iconst_1
        //   34: invokeinterface 52 5 0
        //   39: pop
        //   40: aload_2
        //   41: invokevirtual 55	android/os/Parcel:recycle	()V
        //   44: return
        //   45: aload_2
        //   46: iconst_0
        //   47: invokevirtual 40	android/os/Parcel:writeInt	(I)V
        //   50: goto -25 -> 25
        //   53: astore_1
        //   54: aload_2
        //   55: invokevirtual 55	android/os/Parcel:recycle	()V
        //   58: aload_1
        //   59: athrow
        // Local variable table:
        //   start	length	slot	name	signature
        //   0	60	0	this	zza
        //   0	60	1	paramDailyTotalRequest	DailyTotalRequest
        //   3	52	2	localParcel	Parcel
        // Exception table:
        //   from	to	target	type
        //   4	10	53	finally
        //   14	25	53	finally
        //   25	40	53	finally
        //   45	50	53	finally
      }
      
      /* Error */
      public void zza(DataDeleteRequest paramDataDeleteRequest)
        throws RemoteException
      {
        // Byte code:
        //   0: invokestatic 30	android/os/Parcel:obtain	()Landroid/os/Parcel;
        //   3: astore_2
        //   4: aload_2
        //   5: ldc 32
        //   7: invokevirtual 36	android/os/Parcel:writeInterfaceToken	(Ljava/lang/String;)V
        //   10: aload_1
        //   11: ifnull +33 -> 44
        //   14: aload_2
        //   15: iconst_1
        //   16: invokevirtual 40	android/os/Parcel:writeInt	(I)V
        //   19: aload_1
        //   20: aload_2
        //   21: iconst_0
        //   22: invokevirtual 60	com/google/android/gms/fitness/request/DataDeleteRequest:writeToParcel	(Landroid/os/Parcel;I)V
        //   25: aload_0
        //   26: getfield 18	com/google/android/gms/internal/zzmk$zza$zza:zznF	Landroid/os/IBinder;
        //   29: iconst_3
        //   30: aload_2
        //   31: aconst_null
        //   32: iconst_1
        //   33: invokeinterface 52 5 0
        //   38: pop
        //   39: aload_2
        //   40: invokevirtual 55	android/os/Parcel:recycle	()V
        //   43: return
        //   44: aload_2
        //   45: iconst_0
        //   46: invokevirtual 40	android/os/Parcel:writeInt	(I)V
        //   49: goto -24 -> 25
        //   52: astore_1
        //   53: aload_2
        //   54: invokevirtual 55	android/os/Parcel:recycle	()V
        //   57: aload_1
        //   58: athrow
        // Local variable table:
        //   start	length	slot	name	signature
        //   0	59	0	this	zza
        //   0	59	1	paramDataDeleteRequest	DataDeleteRequest
        //   3	51	2	localParcel	Parcel
        // Exception table:
        //   from	to	target	type
        //   4	10	52	finally
        //   14	25	52	finally
        //   25	39	52	finally
        //   44	49	52	finally
      }
      
      /* Error */
      public void zza(DataInsertRequest paramDataInsertRequest)
        throws RemoteException
      {
        // Byte code:
        //   0: invokestatic 30	android/os/Parcel:obtain	()Landroid/os/Parcel;
        //   3: astore_2
        //   4: aload_2
        //   5: ldc 32
        //   7: invokevirtual 36	android/os/Parcel:writeInterfaceToken	(Ljava/lang/String;)V
        //   10: aload_1
        //   11: ifnull +33 -> 44
        //   14: aload_2
        //   15: iconst_1
        //   16: invokevirtual 40	android/os/Parcel:writeInt	(I)V
        //   19: aload_1
        //   20: aload_2
        //   21: iconst_0
        //   22: invokevirtual 64	com/google/android/gms/fitness/request/DataInsertRequest:writeToParcel	(Landroid/os/Parcel;I)V
        //   25: aload_0
        //   26: getfield 18	com/google/android/gms/internal/zzmk$zza$zza:zznF	Landroid/os/IBinder;
        //   29: iconst_2
        //   30: aload_2
        //   31: aconst_null
        //   32: iconst_1
        //   33: invokeinterface 52 5 0
        //   38: pop
        //   39: aload_2
        //   40: invokevirtual 55	android/os/Parcel:recycle	()V
        //   43: return
        //   44: aload_2
        //   45: iconst_0
        //   46: invokevirtual 40	android/os/Parcel:writeInt	(I)V
        //   49: goto -24 -> 25
        //   52: astore_1
        //   53: aload_2
        //   54: invokevirtual 55	android/os/Parcel:recycle	()V
        //   57: aload_1
        //   58: athrow
        // Local variable table:
        //   start	length	slot	name	signature
        //   0	59	0	this	zza
        //   0	59	1	paramDataInsertRequest	DataInsertRequest
        //   3	51	2	localParcel	Parcel
        // Exception table:
        //   from	to	target	type
        //   4	10	52	finally
        //   14	25	52	finally
        //   25	39	52	finally
        //   44	49	52	finally
      }
      
      /* Error */
      public void zza(DataReadRequest paramDataReadRequest)
        throws RemoteException
      {
        // Byte code:
        //   0: invokestatic 30	android/os/Parcel:obtain	()Landroid/os/Parcel;
        //   3: astore_2
        //   4: aload_2
        //   5: ldc 32
        //   7: invokevirtual 36	android/os/Parcel:writeInterfaceToken	(Ljava/lang/String;)V
        //   10: aload_1
        //   11: ifnull +33 -> 44
        //   14: aload_2
        //   15: iconst_1
        //   16: invokevirtual 40	android/os/Parcel:writeInt	(I)V
        //   19: aload_1
        //   20: aload_2
        //   21: iconst_0
        //   22: invokevirtual 68	com/google/android/gms/fitness/request/DataReadRequest:writeToParcel	(Landroid/os/Parcel;I)V
        //   25: aload_0
        //   26: getfield 18	com/google/android/gms/internal/zzmk$zza$zza:zznF	Landroid/os/IBinder;
        //   29: iconst_1
        //   30: aload_2
        //   31: aconst_null
        //   32: iconst_1
        //   33: invokeinterface 52 5 0
        //   38: pop
        //   39: aload_2
        //   40: invokevirtual 55	android/os/Parcel:recycle	()V
        //   43: return
        //   44: aload_2
        //   45: iconst_0
        //   46: invokevirtual 40	android/os/Parcel:writeInt	(I)V
        //   49: goto -24 -> 25
        //   52: astore_1
        //   53: aload_2
        //   54: invokevirtual 55	android/os/Parcel:recycle	()V
        //   57: aload_1
        //   58: athrow
        // Local variable table:
        //   start	length	slot	name	signature
        //   0	59	0	this	zza
        //   0	59	1	paramDataReadRequest	DataReadRequest
        //   3	51	2	localParcel	Parcel
        // Exception table:
        //   from	to	target	type
        //   4	10	52	finally
        //   14	25	52	finally
        //   25	39	52	finally
        //   44	49	52	finally
      }
      
      /* Error */
      public void zza(GetSyncInfoRequest paramGetSyncInfoRequest)
        throws RemoteException
      {
        // Byte code:
        //   0: invokestatic 30	android/os/Parcel:obtain	()Landroid/os/Parcel;
        //   3: astore_2
        //   4: aload_2
        //   5: ldc 32
        //   7: invokevirtual 36	android/os/Parcel:writeInterfaceToken	(Ljava/lang/String;)V
        //   10: aload_1
        //   11: ifnull +33 -> 44
        //   14: aload_2
        //   15: iconst_1
        //   16: invokevirtual 40	android/os/Parcel:writeInt	(I)V
        //   19: aload_1
        //   20: aload_2
        //   21: iconst_0
        //   22: invokevirtual 72	com/google/android/gms/fitness/request/GetSyncInfoRequest:writeToParcel	(Landroid/os/Parcel;I)V
        //   25: aload_0
        //   26: getfield 18	com/google/android/gms/internal/zzmk$zza$zza:zznF	Landroid/os/IBinder;
        //   29: iconst_4
        //   30: aload_2
        //   31: aconst_null
        //   32: iconst_1
        //   33: invokeinterface 52 5 0
        //   38: pop
        //   39: aload_2
        //   40: invokevirtual 55	android/os/Parcel:recycle	()V
        //   43: return
        //   44: aload_2
        //   45: iconst_0
        //   46: invokevirtual 40	android/os/Parcel:writeInt	(I)V
        //   49: goto -24 -> 25
        //   52: astore_1
        //   53: aload_2
        //   54: invokevirtual 55	android/os/Parcel:recycle	()V
        //   57: aload_1
        //   58: athrow
        // Local variable table:
        //   start	length	slot	name	signature
        //   0	59	0	this	zza
        //   0	59	1	paramGetSyncInfoRequest	GetSyncInfoRequest
        //   3	51	2	localParcel	Parcel
        // Exception table:
        //   from	to	target	type
        //   4	10	52	finally
        //   14	25	52	finally
        //   25	39	52	finally
        //   44	49	52	finally
      }
      
      /* Error */
      public void zza(ReadRawRequest paramReadRawRequest)
        throws RemoteException
      {
        // Byte code:
        //   0: invokestatic 30	android/os/Parcel:obtain	()Landroid/os/Parcel;
        //   3: astore_2
        //   4: aload_2
        //   5: ldc 32
        //   7: invokevirtual 36	android/os/Parcel:writeInterfaceToken	(Ljava/lang/String;)V
        //   10: aload_1
        //   11: ifnull +34 -> 45
        //   14: aload_2
        //   15: iconst_1
        //   16: invokevirtual 40	android/os/Parcel:writeInt	(I)V
        //   19: aload_1
        //   20: aload_2
        //   21: iconst_0
        //   22: invokevirtual 76	com/google/android/gms/fitness/request/ReadRawRequest:writeToParcel	(Landroid/os/Parcel;I)V
        //   25: aload_0
        //   26: getfield 18	com/google/android/gms/internal/zzmk$zza$zza:zznF	Landroid/os/IBinder;
        //   29: bipush 6
        //   31: aload_2
        //   32: aconst_null
        //   33: iconst_1
        //   34: invokeinterface 52 5 0
        //   39: pop
        //   40: aload_2
        //   41: invokevirtual 55	android/os/Parcel:recycle	()V
        //   44: return
        //   45: aload_2
        //   46: iconst_0
        //   47: invokevirtual 40	android/os/Parcel:writeInt	(I)V
        //   50: goto -25 -> 25
        //   53: astore_1
        //   54: aload_2
        //   55: invokevirtual 55	android/os/Parcel:recycle	()V
        //   58: aload_1
        //   59: athrow
        // Local variable table:
        //   start	length	slot	name	signature
        //   0	60	0	this	zza
        //   0	60	1	paramReadRawRequest	ReadRawRequest
        //   3	52	2	localParcel	Parcel
        // Exception table:
        //   from	to	target	type
        //   4	10	53	finally
        //   14	25	53	finally
        //   25	40	53	finally
        //   45	50	53	finally
      }
      
      /* Error */
      public void zza(ReadStatsRequest paramReadStatsRequest)
        throws RemoteException
      {
        // Byte code:
        //   0: invokestatic 30	android/os/Parcel:obtain	()Landroid/os/Parcel;
        //   3: astore_2
        //   4: aload_2
        //   5: ldc 32
        //   7: invokevirtual 36	android/os/Parcel:writeInterfaceToken	(Ljava/lang/String;)V
        //   10: aload_1
        //   11: ifnull +33 -> 44
        //   14: aload_2
        //   15: iconst_1
        //   16: invokevirtual 40	android/os/Parcel:writeInt	(I)V
        //   19: aload_1
        //   20: aload_2
        //   21: iconst_0
        //   22: invokevirtual 80	com/google/android/gms/fitness/request/ReadStatsRequest:writeToParcel	(Landroid/os/Parcel;I)V
        //   25: aload_0
        //   26: getfield 18	com/google/android/gms/internal/zzmk$zza$zza:zznF	Landroid/os/IBinder;
        //   29: iconst_5
        //   30: aload_2
        //   31: aconst_null
        //   32: iconst_1
        //   33: invokeinterface 52 5 0
        //   38: pop
        //   39: aload_2
        //   40: invokevirtual 55	android/os/Parcel:recycle	()V
        //   43: return
        //   44: aload_2
        //   45: iconst_0
        //   46: invokevirtual 40	android/os/Parcel:writeInt	(I)V
        //   49: goto -24 -> 25
        //   52: astore_1
        //   53: aload_2
        //   54: invokevirtual 55	android/os/Parcel:recycle	()V
        //   57: aload_1
        //   58: athrow
        // Local variable table:
        //   start	length	slot	name	signature
        //   0	59	0	this	zza
        //   0	59	1	paramReadStatsRequest	ReadStatsRequest
        //   3	51	2	localParcel	Parcel
        // Exception table:
        //   from	to	target	type
        //   4	10	52	finally
        //   14	25	52	finally
        //   25	39	52	finally
        //   44	49	52	finally
      }
    }
  }
}
