package com.google.android.gms.internal;

import android.os.Binder;
import android.os.IBinder;
import android.os.IInterface;
import android.os.Parcel;
import android.os.RemoteException;
import com.google.android.gms.nearby.bootstrap.request.ConnectRequest;
import com.google.android.gms.nearby.bootstrap.request.ContinueConnectRequest;
import com.google.android.gms.nearby.bootstrap.request.DisableTargetRequest;
import com.google.android.gms.nearby.bootstrap.request.DisconnectRequest;
import com.google.android.gms.nearby.bootstrap.request.EnableTargetRequest;
import com.google.android.gms.nearby.bootstrap.request.SendDataRequest;
import com.google.android.gms.nearby.bootstrap.request.StartScanRequest;
import com.google.android.gms.nearby.bootstrap.request.StopScanRequest;
import com.google.android.gms.nearby.bootstrap.request.zza;
import com.google.android.gms.nearby.bootstrap.request.zzb;
import com.google.android.gms.nearby.bootstrap.request.zzc;
import com.google.android.gms.nearby.bootstrap.request.zzd;
import com.google.android.gms.nearby.bootstrap.request.zze;
import com.google.android.gms.nearby.bootstrap.request.zzf;
import com.google.android.gms.nearby.bootstrap.request.zzg;
import com.google.android.gms.nearby.bootstrap.request.zzh;

public abstract interface zzom
  extends IInterface
{
  public abstract String getToken()
    throws RemoteException;
  
  public abstract void zza(ConnectRequest paramConnectRequest)
    throws RemoteException;
  
  public abstract void zza(ContinueConnectRequest paramContinueConnectRequest)
    throws RemoteException;
  
  public abstract void zza(DisableTargetRequest paramDisableTargetRequest)
    throws RemoteException;
  
  public abstract void zza(DisconnectRequest paramDisconnectRequest)
    throws RemoteException;
  
  public abstract void zza(EnableTargetRequest paramEnableTargetRequest)
    throws RemoteException;
  
  public abstract void zza(SendDataRequest paramSendDataRequest)
    throws RemoteException;
  
  public abstract void zza(StartScanRequest paramStartScanRequest)
    throws RemoteException;
  
  public abstract void zza(StopScanRequest paramStopScanRequest)
    throws RemoteException;
  
  public static abstract class zza
    extends Binder
    implements zzom
  {
    public static zzom zzcY(IBinder paramIBinder)
    {
      if (paramIBinder == null) {
        return null;
      }
      IInterface localIInterface = paramIBinder.queryLocalInterface("com.google.android.gms.nearby.bootstrap.internal.INearbyBootstrapService");
      if ((localIInterface != null) && ((localIInterface instanceof zzom))) {
        return (zzom)localIInterface;
      }
      return new zza(paramIBinder);
    }
    
    public boolean onTransact(int paramInt1, Parcel paramParcel1, Parcel paramParcel2, int paramInt2)
      throws RemoteException
    {
      Object localObject2 = null;
      Object localObject3 = null;
      Object localObject4 = null;
      Object localObject5 = null;
      Object localObject6 = null;
      Object localObject7 = null;
      Object localObject8 = null;
      Object localObject1 = null;
      switch (paramInt1)
      {
      default: 
        return super.onTransact(paramInt1, paramParcel1, paramParcel2, paramInt2);
      case 1598968902: 
        paramParcel2.writeString("com.google.android.gms.nearby.bootstrap.internal.INearbyBootstrapService");
        return true;
      case 1: 
        paramParcel1.enforceInterface("com.google.android.gms.nearby.bootstrap.internal.INearbyBootstrapService");
        paramParcel2 = localObject1;
        if (paramParcel1.readInt() != 0) {
          paramParcel2 = StartScanRequest.CREATOR.zzfl(paramParcel1);
        }
        zza(paramParcel2);
        return true;
      case 2: 
        paramParcel1.enforceInterface("com.google.android.gms.nearby.bootstrap.internal.INearbyBootstrapService");
        paramParcel2 = localObject2;
        if (paramParcel1.readInt() != 0) {
          paramParcel2 = StopScanRequest.CREATOR.zzfm(paramParcel1);
        }
        zza(paramParcel2);
        return true;
      case 3: 
        paramParcel1.enforceInterface("com.google.android.gms.nearby.bootstrap.internal.INearbyBootstrapService");
        paramParcel2 = localObject3;
        if (paramParcel1.readInt() != 0) {
          paramParcel2 = EnableTargetRequest.CREATOR.zzfj(paramParcel1);
        }
        zza(paramParcel2);
        return true;
      case 4: 
        paramParcel1.enforceInterface("com.google.android.gms.nearby.bootstrap.internal.INearbyBootstrapService");
        paramParcel2 = localObject4;
        if (paramParcel1.readInt() != 0) {
          paramParcel2 = DisableTargetRequest.CREATOR.zzfh(paramParcel1);
        }
        zza(paramParcel2);
        return true;
      case 5: 
        paramParcel1.enforceInterface("com.google.android.gms.nearby.bootstrap.internal.INearbyBootstrapService");
        paramParcel2 = localObject5;
        if (paramParcel1.readInt() != 0) {
          paramParcel2 = ConnectRequest.CREATOR.zzff(paramParcel1);
        }
        zza(paramParcel2);
        return true;
      case 6: 
        paramParcel1.enforceInterface("com.google.android.gms.nearby.bootstrap.internal.INearbyBootstrapService");
        paramParcel2 = localObject6;
        if (paramParcel1.readInt() != 0) {
          paramParcel2 = DisconnectRequest.CREATOR.zzfi(paramParcel1);
        }
        zza(paramParcel2);
        return true;
      case 7: 
        paramParcel1.enforceInterface("com.google.android.gms.nearby.bootstrap.internal.INearbyBootstrapService");
        paramParcel2 = localObject7;
        if (paramParcel1.readInt() != 0) {
          paramParcel2 = SendDataRequest.CREATOR.zzfk(paramParcel1);
        }
        zza(paramParcel2);
        return true;
      case 8: 
        paramParcel1.enforceInterface("com.google.android.gms.nearby.bootstrap.internal.INearbyBootstrapService");
        paramParcel2 = localObject8;
        if (paramParcel1.readInt() != 0) {
          paramParcel2 = ContinueConnectRequest.CREATOR.zzfg(paramParcel1);
        }
        zza(paramParcel2);
        return true;
      }
      paramParcel1.enforceInterface("com.google.android.gms.nearby.bootstrap.internal.INearbyBootstrapService");
      paramParcel1 = getToken();
      paramParcel2.writeNoException();
      paramParcel2.writeString(paramParcel1);
      return true;
    }
    
    private static class zza
      implements zzom
    {
      private IBinder zznF;
      
      zza(IBinder paramIBinder)
      {
        this.zznF = paramIBinder;
      }
      
      public IBinder asBinder()
      {
        return this.zznF;
      }
      
      public String getToken()
        throws RemoteException
      {
        Parcel localParcel1 = Parcel.obtain();
        Parcel localParcel2 = Parcel.obtain();
        try
        {
          localParcel1.writeInterfaceToken("com.google.android.gms.nearby.bootstrap.internal.INearbyBootstrapService");
          this.zznF.transact(9, localParcel1, localParcel2, 0);
          localParcel2.readException();
          String str = localParcel2.readString();
          return str;
        }
        finally
        {
          localParcel2.recycle();
          localParcel1.recycle();
        }
      }
      
      /* Error */
      public void zza(ConnectRequest paramConnectRequest)
        throws RemoteException
      {
        // Byte code:
        //   0: invokestatic 31	android/os/Parcel:obtain	()Landroid/os/Parcel;
        //   3: astore_2
        //   4: aload_2
        //   5: ldc 33
        //   7: invokevirtual 37	android/os/Parcel:writeInterfaceToken	(Ljava/lang/String;)V
        //   10: aload_1
        //   11: ifnull +33 -> 44
        //   14: aload_2
        //   15: iconst_1
        //   16: invokevirtual 58	android/os/Parcel:writeInt	(I)V
        //   19: aload_1
        //   20: aload_2
        //   21: iconst_0
        //   22: invokevirtual 64	com/google/android/gms/nearby/bootstrap/request/ConnectRequest:writeToParcel	(Landroid/os/Parcel;I)V
        //   25: aload_0
        //   26: getfield 18	com/google/android/gms/internal/zzom$zza$zza:zznF	Landroid/os/IBinder;
        //   29: iconst_5
        //   30: aload_2
        //   31: aconst_null
        //   32: iconst_1
        //   33: invokeinterface 43 5 0
        //   38: pop
        //   39: aload_2
        //   40: invokevirtual 52	android/os/Parcel:recycle	()V
        //   43: return
        //   44: aload_2
        //   45: iconst_0
        //   46: invokevirtual 58	android/os/Parcel:writeInt	(I)V
        //   49: goto -24 -> 25
        //   52: astore_1
        //   53: aload_2
        //   54: invokevirtual 52	android/os/Parcel:recycle	()V
        //   57: aload_1
        //   58: athrow
        // Local variable table:
        //   start	length	slot	name	signature
        //   0	59	0	this	zza
        //   0	59	1	paramConnectRequest	ConnectRequest
        //   3	51	2	localParcel	Parcel
        // Exception table:
        //   from	to	target	type
        //   4	10	52	finally
        //   14	25	52	finally
        //   25	39	52	finally
        //   44	49	52	finally
      }
      
      /* Error */
      public void zza(ContinueConnectRequest paramContinueConnectRequest)
        throws RemoteException
      {
        // Byte code:
        //   0: invokestatic 31	android/os/Parcel:obtain	()Landroid/os/Parcel;
        //   3: astore_2
        //   4: aload_2
        //   5: ldc 33
        //   7: invokevirtual 37	android/os/Parcel:writeInterfaceToken	(Ljava/lang/String;)V
        //   10: aload_1
        //   11: ifnull +34 -> 45
        //   14: aload_2
        //   15: iconst_1
        //   16: invokevirtual 58	android/os/Parcel:writeInt	(I)V
        //   19: aload_1
        //   20: aload_2
        //   21: iconst_0
        //   22: invokevirtual 68	com/google/android/gms/nearby/bootstrap/request/ContinueConnectRequest:writeToParcel	(Landroid/os/Parcel;I)V
        //   25: aload_0
        //   26: getfield 18	com/google/android/gms/internal/zzom$zza$zza:zznF	Landroid/os/IBinder;
        //   29: bipush 8
        //   31: aload_2
        //   32: aconst_null
        //   33: iconst_1
        //   34: invokeinterface 43 5 0
        //   39: pop
        //   40: aload_2
        //   41: invokevirtual 52	android/os/Parcel:recycle	()V
        //   44: return
        //   45: aload_2
        //   46: iconst_0
        //   47: invokevirtual 58	android/os/Parcel:writeInt	(I)V
        //   50: goto -25 -> 25
        //   53: astore_1
        //   54: aload_2
        //   55: invokevirtual 52	android/os/Parcel:recycle	()V
        //   58: aload_1
        //   59: athrow
        // Local variable table:
        //   start	length	slot	name	signature
        //   0	60	0	this	zza
        //   0	60	1	paramContinueConnectRequest	ContinueConnectRequest
        //   3	52	2	localParcel	Parcel
        // Exception table:
        //   from	to	target	type
        //   4	10	53	finally
        //   14	25	53	finally
        //   25	40	53	finally
        //   45	50	53	finally
      }
      
      /* Error */
      public void zza(DisableTargetRequest paramDisableTargetRequest)
        throws RemoteException
      {
        // Byte code:
        //   0: invokestatic 31	android/os/Parcel:obtain	()Landroid/os/Parcel;
        //   3: astore_2
        //   4: aload_2
        //   5: ldc 33
        //   7: invokevirtual 37	android/os/Parcel:writeInterfaceToken	(Ljava/lang/String;)V
        //   10: aload_1
        //   11: ifnull +33 -> 44
        //   14: aload_2
        //   15: iconst_1
        //   16: invokevirtual 58	android/os/Parcel:writeInt	(I)V
        //   19: aload_1
        //   20: aload_2
        //   21: iconst_0
        //   22: invokevirtual 72	com/google/android/gms/nearby/bootstrap/request/DisableTargetRequest:writeToParcel	(Landroid/os/Parcel;I)V
        //   25: aload_0
        //   26: getfield 18	com/google/android/gms/internal/zzom$zza$zza:zznF	Landroid/os/IBinder;
        //   29: iconst_4
        //   30: aload_2
        //   31: aconst_null
        //   32: iconst_1
        //   33: invokeinterface 43 5 0
        //   38: pop
        //   39: aload_2
        //   40: invokevirtual 52	android/os/Parcel:recycle	()V
        //   43: return
        //   44: aload_2
        //   45: iconst_0
        //   46: invokevirtual 58	android/os/Parcel:writeInt	(I)V
        //   49: goto -24 -> 25
        //   52: astore_1
        //   53: aload_2
        //   54: invokevirtual 52	android/os/Parcel:recycle	()V
        //   57: aload_1
        //   58: athrow
        // Local variable table:
        //   start	length	slot	name	signature
        //   0	59	0	this	zza
        //   0	59	1	paramDisableTargetRequest	DisableTargetRequest
        //   3	51	2	localParcel	Parcel
        // Exception table:
        //   from	to	target	type
        //   4	10	52	finally
        //   14	25	52	finally
        //   25	39	52	finally
        //   44	49	52	finally
      }
      
      /* Error */
      public void zza(DisconnectRequest paramDisconnectRequest)
        throws RemoteException
      {
        // Byte code:
        //   0: invokestatic 31	android/os/Parcel:obtain	()Landroid/os/Parcel;
        //   3: astore_2
        //   4: aload_2
        //   5: ldc 33
        //   7: invokevirtual 37	android/os/Parcel:writeInterfaceToken	(Ljava/lang/String;)V
        //   10: aload_1
        //   11: ifnull +34 -> 45
        //   14: aload_2
        //   15: iconst_1
        //   16: invokevirtual 58	android/os/Parcel:writeInt	(I)V
        //   19: aload_1
        //   20: aload_2
        //   21: iconst_0
        //   22: invokevirtual 76	com/google/android/gms/nearby/bootstrap/request/DisconnectRequest:writeToParcel	(Landroid/os/Parcel;I)V
        //   25: aload_0
        //   26: getfield 18	com/google/android/gms/internal/zzom$zza$zza:zznF	Landroid/os/IBinder;
        //   29: bipush 6
        //   31: aload_2
        //   32: aconst_null
        //   33: iconst_1
        //   34: invokeinterface 43 5 0
        //   39: pop
        //   40: aload_2
        //   41: invokevirtual 52	android/os/Parcel:recycle	()V
        //   44: return
        //   45: aload_2
        //   46: iconst_0
        //   47: invokevirtual 58	android/os/Parcel:writeInt	(I)V
        //   50: goto -25 -> 25
        //   53: astore_1
        //   54: aload_2
        //   55: invokevirtual 52	android/os/Parcel:recycle	()V
        //   58: aload_1
        //   59: athrow
        // Local variable table:
        //   start	length	slot	name	signature
        //   0	60	0	this	zza
        //   0	60	1	paramDisconnectRequest	DisconnectRequest
        //   3	52	2	localParcel	Parcel
        // Exception table:
        //   from	to	target	type
        //   4	10	53	finally
        //   14	25	53	finally
        //   25	40	53	finally
        //   45	50	53	finally
      }
      
      /* Error */
      public void zza(EnableTargetRequest paramEnableTargetRequest)
        throws RemoteException
      {
        // Byte code:
        //   0: invokestatic 31	android/os/Parcel:obtain	()Landroid/os/Parcel;
        //   3: astore_2
        //   4: aload_2
        //   5: ldc 33
        //   7: invokevirtual 37	android/os/Parcel:writeInterfaceToken	(Ljava/lang/String;)V
        //   10: aload_1
        //   11: ifnull +33 -> 44
        //   14: aload_2
        //   15: iconst_1
        //   16: invokevirtual 58	android/os/Parcel:writeInt	(I)V
        //   19: aload_1
        //   20: aload_2
        //   21: iconst_0
        //   22: invokevirtual 80	com/google/android/gms/nearby/bootstrap/request/EnableTargetRequest:writeToParcel	(Landroid/os/Parcel;I)V
        //   25: aload_0
        //   26: getfield 18	com/google/android/gms/internal/zzom$zza$zza:zznF	Landroid/os/IBinder;
        //   29: iconst_3
        //   30: aload_2
        //   31: aconst_null
        //   32: iconst_1
        //   33: invokeinterface 43 5 0
        //   38: pop
        //   39: aload_2
        //   40: invokevirtual 52	android/os/Parcel:recycle	()V
        //   43: return
        //   44: aload_2
        //   45: iconst_0
        //   46: invokevirtual 58	android/os/Parcel:writeInt	(I)V
        //   49: goto -24 -> 25
        //   52: astore_1
        //   53: aload_2
        //   54: invokevirtual 52	android/os/Parcel:recycle	()V
        //   57: aload_1
        //   58: athrow
        // Local variable table:
        //   start	length	slot	name	signature
        //   0	59	0	this	zza
        //   0	59	1	paramEnableTargetRequest	EnableTargetRequest
        //   3	51	2	localParcel	Parcel
        // Exception table:
        //   from	to	target	type
        //   4	10	52	finally
        //   14	25	52	finally
        //   25	39	52	finally
        //   44	49	52	finally
      }
      
      /* Error */
      public void zza(SendDataRequest paramSendDataRequest)
        throws RemoteException
      {
        // Byte code:
        //   0: invokestatic 31	android/os/Parcel:obtain	()Landroid/os/Parcel;
        //   3: astore_2
        //   4: aload_2
        //   5: ldc 33
        //   7: invokevirtual 37	android/os/Parcel:writeInterfaceToken	(Ljava/lang/String;)V
        //   10: aload_1
        //   11: ifnull +34 -> 45
        //   14: aload_2
        //   15: iconst_1
        //   16: invokevirtual 58	android/os/Parcel:writeInt	(I)V
        //   19: aload_1
        //   20: aload_2
        //   21: iconst_0
        //   22: invokevirtual 84	com/google/android/gms/nearby/bootstrap/request/SendDataRequest:writeToParcel	(Landroid/os/Parcel;I)V
        //   25: aload_0
        //   26: getfield 18	com/google/android/gms/internal/zzom$zza$zza:zznF	Landroid/os/IBinder;
        //   29: bipush 7
        //   31: aload_2
        //   32: aconst_null
        //   33: iconst_1
        //   34: invokeinterface 43 5 0
        //   39: pop
        //   40: aload_2
        //   41: invokevirtual 52	android/os/Parcel:recycle	()V
        //   44: return
        //   45: aload_2
        //   46: iconst_0
        //   47: invokevirtual 58	android/os/Parcel:writeInt	(I)V
        //   50: goto -25 -> 25
        //   53: astore_1
        //   54: aload_2
        //   55: invokevirtual 52	android/os/Parcel:recycle	()V
        //   58: aload_1
        //   59: athrow
        // Local variable table:
        //   start	length	slot	name	signature
        //   0	60	0	this	zza
        //   0	60	1	paramSendDataRequest	SendDataRequest
        //   3	52	2	localParcel	Parcel
        // Exception table:
        //   from	to	target	type
        //   4	10	53	finally
        //   14	25	53	finally
        //   25	40	53	finally
        //   45	50	53	finally
      }
      
      /* Error */
      public void zza(StartScanRequest paramStartScanRequest)
        throws RemoteException
      {
        // Byte code:
        //   0: invokestatic 31	android/os/Parcel:obtain	()Landroid/os/Parcel;
        //   3: astore_2
        //   4: aload_2
        //   5: ldc 33
        //   7: invokevirtual 37	android/os/Parcel:writeInterfaceToken	(Ljava/lang/String;)V
        //   10: aload_1
        //   11: ifnull +33 -> 44
        //   14: aload_2
        //   15: iconst_1
        //   16: invokevirtual 58	android/os/Parcel:writeInt	(I)V
        //   19: aload_1
        //   20: aload_2
        //   21: iconst_0
        //   22: invokevirtual 88	com/google/android/gms/nearby/bootstrap/request/StartScanRequest:writeToParcel	(Landroid/os/Parcel;I)V
        //   25: aload_0
        //   26: getfield 18	com/google/android/gms/internal/zzom$zza$zza:zznF	Landroid/os/IBinder;
        //   29: iconst_1
        //   30: aload_2
        //   31: aconst_null
        //   32: iconst_1
        //   33: invokeinterface 43 5 0
        //   38: pop
        //   39: aload_2
        //   40: invokevirtual 52	android/os/Parcel:recycle	()V
        //   43: return
        //   44: aload_2
        //   45: iconst_0
        //   46: invokevirtual 58	android/os/Parcel:writeInt	(I)V
        //   49: goto -24 -> 25
        //   52: astore_1
        //   53: aload_2
        //   54: invokevirtual 52	android/os/Parcel:recycle	()V
        //   57: aload_1
        //   58: athrow
        // Local variable table:
        //   start	length	slot	name	signature
        //   0	59	0	this	zza
        //   0	59	1	paramStartScanRequest	StartScanRequest
        //   3	51	2	localParcel	Parcel
        // Exception table:
        //   from	to	target	type
        //   4	10	52	finally
        //   14	25	52	finally
        //   25	39	52	finally
        //   44	49	52	finally
      }
      
      /* Error */
      public void zza(StopScanRequest paramStopScanRequest)
        throws RemoteException
      {
        // Byte code:
        //   0: invokestatic 31	android/os/Parcel:obtain	()Landroid/os/Parcel;
        //   3: astore_2
        //   4: aload_2
        //   5: ldc 33
        //   7: invokevirtual 37	android/os/Parcel:writeInterfaceToken	(Ljava/lang/String;)V
        //   10: aload_1
        //   11: ifnull +33 -> 44
        //   14: aload_2
        //   15: iconst_1
        //   16: invokevirtual 58	android/os/Parcel:writeInt	(I)V
        //   19: aload_1
        //   20: aload_2
        //   21: iconst_0
        //   22: invokevirtual 92	com/google/android/gms/nearby/bootstrap/request/StopScanRequest:writeToParcel	(Landroid/os/Parcel;I)V
        //   25: aload_0
        //   26: getfield 18	com/google/android/gms/internal/zzom$zza$zza:zznF	Landroid/os/IBinder;
        //   29: iconst_2
        //   30: aload_2
        //   31: aconst_null
        //   32: iconst_1
        //   33: invokeinterface 43 5 0
        //   38: pop
        //   39: aload_2
        //   40: invokevirtual 52	android/os/Parcel:recycle	()V
        //   43: return
        //   44: aload_2
        //   45: iconst_0
        //   46: invokevirtual 58	android/os/Parcel:writeInt	(I)V
        //   49: goto -24 -> 25
        //   52: astore_1
        //   53: aload_2
        //   54: invokevirtual 52	android/os/Parcel:recycle	()V
        //   57: aload_1
        //   58: athrow
        // Local variable table:
        //   start	length	slot	name	signature
        //   0	59	0	this	zza
        //   0	59	1	paramStopScanRequest	StopScanRequest
        //   3	51	2	localParcel	Parcel
        // Exception table:
        //   from	to	target	type
        //   4	10	52	finally
        //   14	25	52	finally
        //   25	39	52	finally
        //   44	49	52	finally
      }
    }
  }
}
