package com.google.android.gms.maps;

import android.graphics.Bitmap;
import android.location.Location;
import android.os.RemoteException;
import android.view.View;
import com.google.android.gms.dynamic.b;
import com.google.android.gms.dynamic.c;
import com.google.android.gms.internal.s;
import com.google.android.gms.maps.internal.IGoogleMapDelegate;
import com.google.android.gms.maps.internal.ILocationSourceDelegate.a;
import com.google.android.gms.maps.internal.b.a;
import com.google.android.gms.maps.internal.d.a;
import com.google.android.gms.maps.internal.e.a;
import com.google.android.gms.maps.internal.f.a;
import com.google.android.gms.maps.internal.g;
import com.google.android.gms.maps.internal.h.a;
import com.google.android.gms.maps.internal.i.a;
import com.google.android.gms.maps.internal.j.a;
import com.google.android.gms.maps.internal.k.a;
import com.google.android.gms.maps.internal.l.a;
import com.google.android.gms.maps.internal.m.a;
import com.google.android.gms.maps.internal.n.a;
import com.google.android.gms.maps.model.CameraPosition;
import com.google.android.gms.maps.model.Circle;
import com.google.android.gms.maps.model.CircleOptions;
import com.google.android.gms.maps.model.GroundOverlay;
import com.google.android.gms.maps.model.GroundOverlayOptions;
import com.google.android.gms.maps.model.LatLng;
import com.google.android.gms.maps.model.Marker;
import com.google.android.gms.maps.model.MarkerOptions;
import com.google.android.gms.maps.model.Polygon;
import com.google.android.gms.maps.model.PolygonOptions;
import com.google.android.gms.maps.model.Polyline;
import com.google.android.gms.maps.model.PolylineOptions;
import com.google.android.gms.maps.model.RuntimeRemoteException;
import com.google.android.gms.maps.model.TileOverlay;
import com.google.android.gms.maps.model.TileOverlayOptions;
import com.google.android.gms.maps.model.internal.d;

public final class GoogleMap
{
  public static final int MAP_TYPE_HYBRID = 4;
  public static final int MAP_TYPE_NONE = 0;
  public static final int MAP_TYPE_NORMAL = 1;
  public static final int MAP_TYPE_SATELLITE = 2;
  public static final int MAP_TYPE_TERRAIN = 3;
  private final IGoogleMapDelegate fX;
  private UiSettings fY;
  
  protected GoogleMap(IGoogleMapDelegate paramIGoogleMapDelegate)
  {
    this.fX = ((IGoogleMapDelegate)s.d(paramIGoogleMapDelegate));
  }
  
  IGoogleMapDelegate aY()
  {
    return this.fX;
  }
  
  public final Circle addCircle(CircleOptions paramCircleOptions)
  {
    try
    {
      paramCircleOptions = new Circle(this.fX.addCircle(paramCircleOptions));
      return paramCircleOptions;
    }
    catch (RemoteException paramCircleOptions)
    {
      throw new RuntimeRemoteException(paramCircleOptions);
    }
  }
  
  public final GroundOverlay addGroundOverlay(GroundOverlayOptions paramGroundOverlayOptions)
  {
    try
    {
      paramGroundOverlayOptions = this.fX.addGroundOverlay(paramGroundOverlayOptions);
      if (paramGroundOverlayOptions != null)
      {
        paramGroundOverlayOptions = new GroundOverlay(paramGroundOverlayOptions);
        return paramGroundOverlayOptions;
      }
      return null;
    }
    catch (RemoteException paramGroundOverlayOptions)
    {
      throw new RuntimeRemoteException(paramGroundOverlayOptions);
    }
  }
  
  public final Marker addMarker(MarkerOptions paramMarkerOptions)
  {
    try
    {
      paramMarkerOptions = this.fX.addMarker(paramMarkerOptions);
      if (paramMarkerOptions != null)
      {
        paramMarkerOptions = new Marker(paramMarkerOptions);
        return paramMarkerOptions;
      }
      return null;
    }
    catch (RemoteException paramMarkerOptions)
    {
      throw new RuntimeRemoteException(paramMarkerOptions);
    }
  }
  
  public final Polygon addPolygon(PolygonOptions paramPolygonOptions)
  {
    try
    {
      paramPolygonOptions = new Polygon(this.fX.addPolygon(paramPolygonOptions));
      return paramPolygonOptions;
    }
    catch (RemoteException paramPolygonOptions)
    {
      throw new RuntimeRemoteException(paramPolygonOptions);
    }
  }
  
  public final Polyline addPolyline(PolylineOptions paramPolylineOptions)
  {
    try
    {
      paramPolylineOptions = new Polyline(this.fX.addPolyline(paramPolylineOptions));
      return paramPolylineOptions;
    }
    catch (RemoteException paramPolylineOptions)
    {
      throw new RuntimeRemoteException(paramPolylineOptions);
    }
  }
  
  public final TileOverlay addTileOverlay(TileOverlayOptions paramTileOverlayOptions)
  {
    try
    {
      paramTileOverlayOptions = this.fX.addTileOverlay(paramTileOverlayOptions);
      if (paramTileOverlayOptions != null)
      {
        paramTileOverlayOptions = new TileOverlay(paramTileOverlayOptions);
        return paramTileOverlayOptions;
      }
      return null;
    }
    catch (RemoteException paramTileOverlayOptions)
    {
      throw new RuntimeRemoteException(paramTileOverlayOptions);
    }
  }
  
  public final void animateCamera(CameraUpdate paramCameraUpdate)
  {
    try
    {
      this.fX.animateCamera(paramCameraUpdate.aW());
      return;
    }
    catch (RemoteException paramCameraUpdate)
    {
      throw new RuntimeRemoteException(paramCameraUpdate);
    }
  }
  
  /* Error */
  public final void animateCamera(CameraUpdate paramCameraUpdate, int paramInt, CancelableCallback paramCancelableCallback)
  {
    // Byte code:
    //   0: aload_0
    //   1: getfield 94	com/google/android/gms/maps/GoogleMap:fX	Lcom/google/android/gms/maps/internal/IGoogleMapDelegate;
    //   4: astore 4
    //   6: aload_1
    //   7: invokevirtual 172	com/google/android/gms/maps/CameraUpdate:aW	()Lcom/google/android/gms/dynamic/b;
    //   10: astore 5
    //   12: aload_3
    //   13: ifnonnull +17 -> 30
    //   16: aconst_null
    //   17: astore_1
    //   18: aload 4
    //   20: aload 5
    //   22: iload_2
    //   23: aload_1
    //   24: invokeinterface 180 4 0
    //   29: return
    //   30: new 63	com/google/android/gms/maps/GoogleMap$a
    //   33: dup
    //   34: aload_3
    //   35: invokespecial 183	com/google/android/gms/maps/GoogleMap$a:<init>	(Lcom/google/android/gms/maps/GoogleMap$CancelableCallback;)V
    //   38: astore_1
    //   39: goto -21 -> 18
    //   42: astore_1
    //   43: new 111	com/google/android/gms/maps/model/RuntimeRemoteException
    //   46: dup
    //   47: aload_1
    //   48: invokespecial 114	com/google/android/gms/maps/model/RuntimeRemoteException:<init>	(Landroid/os/RemoteException;)V
    //   51: athrow
    // Local variable table:
    //   start	length	slot	name	signature
    //   0	52	0	this	GoogleMap
    //   0	52	1	paramCameraUpdate	CameraUpdate
    //   0	52	2	paramInt	int
    //   0	52	3	paramCancelableCallback	CancelableCallback
    //   4	15	4	localIGoogleMapDelegate	IGoogleMapDelegate
    //   10	11	5	localB	b
    // Exception table:
    //   from	to	target	type
    //   0	12	42	android/os/RemoteException
    //   18	29	42	android/os/RemoteException
    //   30	39	42	android/os/RemoteException
  }
  
  /* Error */
  public final void animateCamera(CameraUpdate paramCameraUpdate, CancelableCallback paramCancelableCallback)
  {
    // Byte code:
    //   0: aload_0
    //   1: getfield 94	com/google/android/gms/maps/GoogleMap:fX	Lcom/google/android/gms/maps/internal/IGoogleMapDelegate;
    //   4: astore_3
    //   5: aload_1
    //   6: invokevirtual 172	com/google/android/gms/maps/CameraUpdate:aW	()Lcom/google/android/gms/dynamic/b;
    //   9: astore 4
    //   11: aload_2
    //   12: ifnonnull +15 -> 27
    //   15: aconst_null
    //   16: astore_1
    //   17: aload_3
    //   18: aload 4
    //   20: aload_1
    //   21: invokeinterface 188 3 0
    //   26: return
    //   27: new 63	com/google/android/gms/maps/GoogleMap$a
    //   30: dup
    //   31: aload_2
    //   32: invokespecial 183	com/google/android/gms/maps/GoogleMap$a:<init>	(Lcom/google/android/gms/maps/GoogleMap$CancelableCallback;)V
    //   35: astore_1
    //   36: goto -19 -> 17
    //   39: astore_1
    //   40: new 111	com/google/android/gms/maps/model/RuntimeRemoteException
    //   43: dup
    //   44: aload_1
    //   45: invokespecial 114	com/google/android/gms/maps/model/RuntimeRemoteException:<init>	(Landroid/os/RemoteException;)V
    //   48: athrow
    // Local variable table:
    //   start	length	slot	name	signature
    //   0	49	0	this	GoogleMap
    //   0	49	1	paramCameraUpdate	CameraUpdate
    //   0	49	2	paramCancelableCallback	CancelableCallback
    //   4	14	3	localIGoogleMapDelegate	IGoogleMapDelegate
    //   9	10	4	localB	b
    // Exception table:
    //   from	to	target	type
    //   0	11	39	android/os/RemoteException
    //   17	26	39	android/os/RemoteException
    //   27	36	39	android/os/RemoteException
  }
  
  public final void clear()
  {
    try
    {
      this.fX.clear();
      return;
    }
    catch (RemoteException localRemoteException)
    {
      throw new RuntimeRemoteException(localRemoteException);
    }
  }
  
  public final CameraPosition getCameraPosition()
  {
    try
    {
      CameraPosition localCameraPosition = this.fX.getCameraPosition();
      return localCameraPosition;
    }
    catch (RemoteException localRemoteException)
    {
      throw new RuntimeRemoteException(localRemoteException);
    }
  }
  
  public final int getMapType()
  {
    try
    {
      int i = this.fX.getMapType();
      return i;
    }
    catch (RemoteException localRemoteException)
    {
      throw new RuntimeRemoteException(localRemoteException);
    }
  }
  
  public final float getMaxZoomLevel()
  {
    try
    {
      float f = this.fX.getMaxZoomLevel();
      return f;
    }
    catch (RemoteException localRemoteException)
    {
      throw new RuntimeRemoteException(localRemoteException);
    }
  }
  
  public final float getMinZoomLevel()
  {
    try
    {
      float f = this.fX.getMinZoomLevel();
      return f;
    }
    catch (RemoteException localRemoteException)
    {
      throw new RuntimeRemoteException(localRemoteException);
    }
  }
  
  @Deprecated
  public final Location getMyLocation()
  {
    try
    {
      Location localLocation = this.fX.getMyLocation();
      return localLocation;
    }
    catch (RemoteException localRemoteException)
    {
      throw new RuntimeRemoteException(localRemoteException);
    }
  }
  
  public final Projection getProjection()
  {
    try
    {
      Projection localProjection = new Projection(this.fX.getProjection());
      return localProjection;
    }
    catch (RemoteException localRemoteException)
    {
      throw new RuntimeRemoteException(localRemoteException);
    }
  }
  
  public final UiSettings getUiSettings()
  {
    try
    {
      if (this.fY == null) {
        this.fY = new UiSettings(this.fX.getUiSettings());
      }
      UiSettings localUiSettings = this.fY;
      return localUiSettings;
    }
    catch (RemoteException localRemoteException)
    {
      throw new RuntimeRemoteException(localRemoteException);
    }
  }
  
  public final boolean isIndoorEnabled()
  {
    try
    {
      boolean bool = this.fX.isIndoorEnabled();
      return bool;
    }
    catch (RemoteException localRemoteException)
    {
      throw new RuntimeRemoteException(localRemoteException);
    }
  }
  
  public final boolean isMyLocationEnabled()
  {
    try
    {
      boolean bool = this.fX.isMyLocationEnabled();
      return bool;
    }
    catch (RemoteException localRemoteException)
    {
      throw new RuntimeRemoteException(localRemoteException);
    }
  }
  
  public final boolean isTrafficEnabled()
  {
    try
    {
      boolean bool = this.fX.isTrafficEnabled();
      return bool;
    }
    catch (RemoteException localRemoteException)
    {
      throw new RuntimeRemoteException(localRemoteException);
    }
  }
  
  public final void moveCamera(CameraUpdate paramCameraUpdate)
  {
    try
    {
      this.fX.moveCamera(paramCameraUpdate.aW());
      return;
    }
    catch (RemoteException paramCameraUpdate)
    {
      throw new RuntimeRemoteException(paramCameraUpdate);
    }
  }
  
  public final boolean setIndoorEnabled(boolean paramBoolean)
  {
    try
    {
      paramBoolean = this.fX.setIndoorEnabled(paramBoolean);
      return paramBoolean;
    }
    catch (RemoteException localRemoteException)
    {
      throw new RuntimeRemoteException(localRemoteException);
    }
  }
  
  public final void setInfoWindowAdapter(final InfoWindowAdapter paramInfoWindowAdapter)
  {
    if (paramInfoWindowAdapter == null) {}
    try
    {
      this.fX.setInfoWindowAdapter(null);
      return;
    }
    catch (RemoteException paramInfoWindowAdapter)
    {
      throw new RuntimeRemoteException(paramInfoWindowAdapter);
    }
    this.fX.setInfoWindowAdapter(new d.a()
    {
      public b f(d paramAnonymousD)
      {
        return c.f(paramInfoWindowAdapter.getInfoWindow(new Marker(paramAnonymousD)));
      }
      
      public b g(d paramAnonymousD)
      {
        return c.f(paramInfoWindowAdapter.getInfoContents(new Marker(paramAnonymousD)));
      }
    });
  }
  
  public final void setLocationSource(final LocationSource paramLocationSource)
  {
    if (paramLocationSource == null) {}
    try
    {
      this.fX.setLocationSource(null);
      return;
    }
    catch (RemoteException paramLocationSource)
    {
      throw new RuntimeRemoteException(paramLocationSource);
    }
    this.fX.setLocationSource(new ILocationSourceDelegate.a()
    {
      public void activate(final g paramAnonymousG)
      {
        paramLocationSource.activate(new LocationSource.OnLocationChangedListener()
        {
          public void onLocationChanged(Location paramAnonymous2Location)
          {
            try
            {
              paramAnonymousG.e(c.f(paramAnonymous2Location));
              return;
            }
            catch (RemoteException paramAnonymous2Location)
            {
              throw new RuntimeRemoteException(paramAnonymous2Location);
            }
          }
        });
      }
      
      public void deactivate()
      {
        paramLocationSource.deactivate();
      }
    });
  }
  
  public final void setMapType(int paramInt)
  {
    try
    {
      this.fX.setMapType(paramInt);
      return;
    }
    catch (RemoteException localRemoteException)
    {
      throw new RuntimeRemoteException(localRemoteException);
    }
  }
  
  public final void setMyLocationEnabled(boolean paramBoolean)
  {
    try
    {
      this.fX.setMyLocationEnabled(paramBoolean);
      return;
    }
    catch (RemoteException localRemoteException)
    {
      throw new RuntimeRemoteException(localRemoteException);
    }
  }
  
  public final void setOnCameraChangeListener(final OnCameraChangeListener paramOnCameraChangeListener)
  {
    if (paramOnCameraChangeListener == null) {}
    try
    {
      this.fX.setOnCameraChangeListener(null);
      return;
    }
    catch (RemoteException paramOnCameraChangeListener)
    {
      throw new RuntimeRemoteException(paramOnCameraChangeListener);
    }
    this.fX.setOnCameraChangeListener(new e.a()
    {
      public void onCameraChange(CameraPosition paramAnonymousCameraPosition)
      {
        paramOnCameraChangeListener.onCameraChange(paramAnonymousCameraPosition);
      }
    });
  }
  
  public final void setOnInfoWindowClickListener(final OnInfoWindowClickListener paramOnInfoWindowClickListener)
  {
    if (paramOnInfoWindowClickListener == null) {}
    try
    {
      this.fX.setOnInfoWindowClickListener(null);
      return;
    }
    catch (RemoteException paramOnInfoWindowClickListener)
    {
      throw new RuntimeRemoteException(paramOnInfoWindowClickListener);
    }
    this.fX.setOnInfoWindowClickListener(new f.a()
    {
      public void e(d paramAnonymousD)
      {
        paramOnInfoWindowClickListener.onInfoWindowClick(new Marker(paramAnonymousD));
      }
    });
  }
  
  public final void setOnMapClickListener(final OnMapClickListener paramOnMapClickListener)
  {
    if (paramOnMapClickListener == null) {}
    try
    {
      this.fX.setOnMapClickListener(null);
      return;
    }
    catch (RemoteException paramOnMapClickListener)
    {
      throw new RuntimeRemoteException(paramOnMapClickListener);
    }
    this.fX.setOnMapClickListener(new h.a()
    {
      public void onMapClick(LatLng paramAnonymousLatLng)
      {
        paramOnMapClickListener.onMapClick(paramAnonymousLatLng);
      }
    });
  }
  
  public final void setOnMapLongClickListener(final OnMapLongClickListener paramOnMapLongClickListener)
  {
    if (paramOnMapLongClickListener == null) {}
    try
    {
      this.fX.setOnMapLongClickListener(null);
      return;
    }
    catch (RemoteException paramOnMapLongClickListener)
    {
      throw new RuntimeRemoteException(paramOnMapLongClickListener);
    }
    this.fX.setOnMapLongClickListener(new i.a()
    {
      public void onMapLongClick(LatLng paramAnonymousLatLng)
      {
        paramOnMapLongClickListener.onMapLongClick(paramAnonymousLatLng);
      }
    });
  }
  
  public final void setOnMarkerClickListener(final OnMarkerClickListener paramOnMarkerClickListener)
  {
    if (paramOnMarkerClickListener == null) {}
    try
    {
      this.fX.setOnMarkerClickListener(null);
      return;
    }
    catch (RemoteException paramOnMarkerClickListener)
    {
      throw new RuntimeRemoteException(paramOnMarkerClickListener);
    }
    this.fX.setOnMarkerClickListener(new j.a()
    {
      public boolean a(d paramAnonymousD)
      {
        return paramOnMarkerClickListener.onMarkerClick(new Marker(paramAnonymousD));
      }
    });
  }
  
  public final void setOnMarkerDragListener(final OnMarkerDragListener paramOnMarkerDragListener)
  {
    if (paramOnMarkerDragListener == null) {}
    try
    {
      this.fX.setOnMarkerDragListener(null);
      return;
    }
    catch (RemoteException paramOnMarkerDragListener)
    {
      throw new RuntimeRemoteException(paramOnMarkerDragListener);
    }
    this.fX.setOnMarkerDragListener(new k.a()
    {
      public void b(d paramAnonymousD)
      {
        paramOnMarkerDragListener.onMarkerDragStart(new Marker(paramAnonymousD));
      }
      
      public void c(d paramAnonymousD)
      {
        paramOnMarkerDragListener.onMarkerDragEnd(new Marker(paramAnonymousD));
      }
      
      public void d(d paramAnonymousD)
      {
        paramOnMarkerDragListener.onMarkerDrag(new Marker(paramAnonymousD));
      }
    });
  }
  
  public final void setOnMyLocationButtonClickListener(final OnMyLocationButtonClickListener paramOnMyLocationButtonClickListener)
  {
    if (paramOnMyLocationButtonClickListener == null) {}
    try
    {
      this.fX.setOnMyLocationButtonClickListener(null);
      return;
    }
    catch (RemoteException paramOnMyLocationButtonClickListener)
    {
      throw new RuntimeRemoteException(paramOnMyLocationButtonClickListener);
    }
    this.fX.setOnMyLocationButtonClickListener(new l.a()
    {
      public boolean onMyLocationButtonClick()
        throws RemoteException
      {
        return paramOnMyLocationButtonClickListener.onMyLocationButtonClick();
      }
    });
  }
  
  @Deprecated
  public final void setOnMyLocationChangeListener(final OnMyLocationChangeListener paramOnMyLocationChangeListener)
  {
    if (paramOnMyLocationChangeListener == null) {}
    try
    {
      this.fX.setOnMyLocationChangeListener(null);
      return;
    }
    catch (RemoteException paramOnMyLocationChangeListener)
    {
      throw new RuntimeRemoteException(paramOnMyLocationChangeListener);
    }
    this.fX.setOnMyLocationChangeListener(new m.a()
    {
      public void b(b paramAnonymousB)
      {
        paramOnMyLocationChangeListener.onMyLocationChange((Location)c.a(paramAnonymousB));
      }
    });
  }
  
  public final void setPadding(int paramInt1, int paramInt2, int paramInt3, int paramInt4)
  {
    try
    {
      this.fX.setPadding(paramInt1, paramInt2, paramInt3, paramInt4);
      return;
    }
    catch (RemoteException localRemoteException)
    {
      throw new RuntimeRemoteException(localRemoteException);
    }
  }
  
  public final void setTrafficEnabled(boolean paramBoolean)
  {
    try
    {
      this.fX.setTrafficEnabled(paramBoolean);
      return;
    }
    catch (RemoteException localRemoteException)
    {
      throw new RuntimeRemoteException(localRemoteException);
    }
  }
  
  public final void snapshot(SnapshotReadyCallback paramSnapshotReadyCallback)
  {
    snapshot(paramSnapshotReadyCallback, null);
  }
  
  public final void snapshot(final SnapshotReadyCallback paramSnapshotReadyCallback, Bitmap paramBitmap)
  {
    if (paramBitmap != null) {}
    for (paramBitmap = c.f(paramBitmap);; paramBitmap = null)
    {
      paramBitmap = (c)paramBitmap;
      try
      {
        this.fX.snapshot(new n.a()
        {
          public void onSnapshotReady(Bitmap paramAnonymousBitmap)
            throws RemoteException
          {
            paramSnapshotReadyCallback.onSnapshotReady(paramAnonymousBitmap);
          }
        }, paramBitmap);
        return;
      }
      catch (RemoteException paramSnapshotReadyCallback)
      {
        throw new RuntimeRemoteException(paramSnapshotReadyCallback);
      }
    }
  }
  
  public final void stopAnimation()
  {
    try
    {
      this.fX.stopAnimation();
      return;
    }
    catch (RemoteException localRemoteException)
    {
      throw new RuntimeRemoteException(localRemoteException);
    }
  }
  
  public static abstract interface CancelableCallback
  {
    public abstract void onCancel();
    
    public abstract void onFinish();
  }
  
  public static abstract interface InfoWindowAdapter
  {
    public abstract View getInfoContents(Marker paramMarker);
    
    public abstract View getInfoWindow(Marker paramMarker);
  }
  
  public static abstract interface OnCameraChangeListener
  {
    public abstract void onCameraChange(CameraPosition paramCameraPosition);
  }
  
  public static abstract interface OnInfoWindowClickListener
  {
    public abstract void onInfoWindowClick(Marker paramMarker);
  }
  
  public static abstract interface OnMapClickListener
  {
    public abstract void onMapClick(LatLng paramLatLng);
  }
  
  public static abstract interface OnMapLongClickListener
  {
    public abstract void onMapLongClick(LatLng paramLatLng);
  }
  
  public static abstract interface OnMarkerClickListener
  {
    public abstract boolean onMarkerClick(Marker paramMarker);
  }
  
  public static abstract interface OnMarkerDragListener
  {
    public abstract void onMarkerDrag(Marker paramMarker);
    
    public abstract void onMarkerDragEnd(Marker paramMarker);
    
    public abstract void onMarkerDragStart(Marker paramMarker);
  }
  
  public static abstract interface OnMyLocationButtonClickListener
  {
    public abstract boolean onMyLocationButtonClick();
  }
  
  @Deprecated
  public static abstract interface OnMyLocationChangeListener
  {
    public abstract void onMyLocationChange(Location paramLocation);
  }
  
  public static abstract interface SnapshotReadyCallback
  {
    public abstract void onSnapshotReady(Bitmap paramBitmap);
  }
  
  private static final class a
    extends b.a
  {
    private final GoogleMap.CancelableCallback gn;
    
    a(GoogleMap.CancelableCallback paramCancelableCallback)
    {
      this.gn = paramCancelableCallback;
    }
    
    public void onCancel()
    {
      this.gn.onCancel();
    }
    
    public void onFinish()
    {
      this.gn.onFinish();
    }
  }
}
