package com.db.pwcc.dbmobile.data.utils.network;

import android.content.BroadcastReceiver;
import android.content.Context;
import android.support.annotation.NonNull;
import uuuuuu.hhhhyh;

public class NetworkChangeReceiver
  extends BroadcastReceiver
{
  private static final String TAG;
  public static int b00710071q00710071q0071 = 2;
  public static int b0071q007100710071q0071 = 1;
  public static int bq0071007100710071q0071 = 2;
  public static int bqq007100710071q0071;
  private yhhhyh callback;
  
  static
  {
    if ((b00710071q00710071q0071 + b0071q007100710071q0071) * b00710071q00710071q0071 % bq0071007100710071q0071 != bqq007100710071q0071)
    {
      b00710071q00710071q0071 = 78;
      bqq007100710071q0071 = b00710071007100710071q0071();
    }
    TAG = NetworkChangeReceiver.class.getSimpleName();
    if ((b00710071q00710071q0071 + b0071q007100710071q0071) * b00710071q00710071q0071 % bq0071007100710071q0071 != bqq007100710071q0071)
    {
      b00710071q00710071q0071 = b00710071007100710071q0071();
      bqq007100710071q0071 = 87;
    }
  }
  
  public NetworkChangeReceiver(@NonNull yhhhyh paramYhhhyh)
  {
    this.callback = paramYhhhyh;
  }
  
  public static int b00710071007100710071q0071()
  {
    return 82;
  }
  
  public static int b0071qqqq00710071()
  {
    return 0;
  }
  
  public static int bqqqqq00710071()
  {
    return 1;
  }
  
  /* Error */
  public void onReceive(Context paramContext, android.content.Intent paramIntent)
  {
    // Byte code:
    //   0: ldc 57
    //   2: ldc 59
    //   4: sipush 156
    //   7: iconst_4
    //   8: invokestatic 65	xxxxxx/uxxxxx:bb00620062bb0062b0062b0062	(Ljava/lang/String;CC)Ljava/lang/String;
    //   11: iconst_1
    //   12: anewarray 34	java/lang/Class
    //   15: dup
    //   16: iconst_0
    //   17: ldc 67
    //   19: aastore
    //   20: invokevirtual 71	java/lang/Class:getMethod	(Ljava/lang/String;[Ljava/lang/Class;)Ljava/lang/reflect/Method;
    //   23: astore 4
    //   25: aload 4
    //   27: aconst_null
    //   28: iconst_1
    //   29: anewarray 73	java/lang/Object
    //   32: dup
    //   33: iconst_0
    //   34: aload_1
    //   35: aastore
    //   36: invokevirtual 79	java/lang/reflect/Method:invoke	(Ljava/lang/Object;[Ljava/lang/Object;)Ljava/lang/Object;
    //   39: pop
    //   40: ldc 81
    //   42: ldc 83
    //   44: bipush 55
    //   46: sipush 231
    //   49: iconst_2
    //   50: invokestatic 87	xxxxxx/uxxxxx:bbbb0062b0062b0062b0062	(Ljava/lang/String;CCC)Ljava/lang/String;
    //   53: iconst_1
    //   54: anewarray 34	java/lang/Class
    //   57: dup
    //   58: iconst_0
    //   59: ldc 67
    //   61: aastore
    //   62: invokevirtual 71	java/lang/Class:getMethod	(Ljava/lang/String;[Ljava/lang/Class;)Ljava/lang/reflect/Method;
    //   65: astore 4
    //   67: aload 4
    //   69: aconst_null
    //   70: iconst_1
    //   71: anewarray 73	java/lang/Object
    //   74: dup
    //   75: iconst_0
    //   76: aload_1
    //   77: aastore
    //   78: invokevirtual 79	java/lang/reflect/Method:invoke	(Ljava/lang/Object;[Ljava/lang/Object;)Ljava/lang/Object;
    //   81: pop
    //   82: aload_1
    //   83: invokestatic 93	uuuuuu/uppupu:b0072r0072r00720072rr0072	(Landroid/content/Context;)V
    //   86: ldc 95
    //   88: ldc 97
    //   90: sipush 148
    //   93: iconst_1
    //   94: invokestatic 65	xxxxxx/uxxxxx:bb00620062bb0062b0062b0062	(Ljava/lang/String;CC)Ljava/lang/String;
    //   97: iconst_3
    //   98: anewarray 34	java/lang/Class
    //   101: dup
    //   102: iconst_0
    //   103: ldc 99
    //   105: aastore
    //   106: dup
    //   107: iconst_1
    //   108: getstatic 105	java/lang/Character:TYPE	Ljava/lang/Class;
    //   111: aastore
    //   112: dup
    //   113: iconst_2
    //   114: getstatic 105	java/lang/Character:TYPE	Ljava/lang/Class;
    //   117: aastore
    //   118: invokevirtual 71	java/lang/Class:getMethod	(Ljava/lang/String;[Ljava/lang/Class;)Ljava/lang/reflect/Method;
    //   121: astore 4
    //   123: aload 4
    //   125: aconst_null
    //   126: iconst_3
    //   127: anewarray 73	java/lang/Object
    //   130: dup
    //   131: iconst_0
    //   132: ldc 107
    //   134: aastore
    //   135: dup
    //   136: iconst_1
    //   137: sipush 172
    //   140: invokestatic 111	java/lang/Character:valueOf	(C)Ljava/lang/Character;
    //   143: aastore
    //   144: dup
    //   145: iconst_2
    //   146: iconst_4
    //   147: invokestatic 111	java/lang/Character:valueOf	(C)Ljava/lang/Character;
    //   150: aastore
    //   151: invokevirtual 79	java/lang/reflect/Method:invoke	(Ljava/lang/Object;[Ljava/lang/Object;)Ljava/lang/Object;
    //   154: astore 4
    //   156: aload 4
    //   158: checkcast 99	java/lang/String
    //   161: aload_2
    //   162: invokevirtual 116	android/content/Intent:getAction	()Ljava/lang/String;
    //   165: invokevirtual 120	java/lang/String:equals	(Ljava/lang/Object;)Z
    //   168: ifeq +142 -> 310
    //   171: aload_1
    //   172: invokestatic 126	uuuuuu/hyhhyh:b006Fooooooooo	(Landroid/content/Context;)Z
    //   175: ifne +136 -> 311
    //   178: getstatic 40	com/db/pwcc/dbmobile/data/utils/network/NetworkChangeReceiver:TAG	Ljava/lang/String;
    //   181: astore_1
    //   182: getstatic 22	com/db/pwcc/dbmobile/data/utils/network/NetworkChangeReceiver:b00710071q00710071q0071	I
    //   185: istore_3
    //   186: iload_3
    //   187: getstatic 24	com/db/pwcc/dbmobile/data/utils/network/NetworkChangeReceiver:b0071q007100710071q0071	I
    //   190: iload_3
    //   191: iadd
    //   192: imul
    //   193: getstatic 26	com/db/pwcc/dbmobile/data/utils/network/NetworkChangeReceiver:bq0071007100710071q0071	I
    //   196: irem
    //   197: tableswitch	default:+19->216, 0:+31->228
    //   216: invokestatic 32	com/db/pwcc/dbmobile/data/utils/network/NetworkChangeReceiver:b00710071007100710071q0071	()I
    //   219: putstatic 22	com/db/pwcc/dbmobile/data/utils/network/NetworkChangeReceiver:b00710071q00710071q0071	I
    //   222: invokestatic 32	com/db/pwcc/dbmobile/data/utils/network/NetworkChangeReceiver:b00710071007100710071q0071	()I
    //   225: putstatic 28	com/db/pwcc/dbmobile/data/utils/network/NetworkChangeReceiver:bqq007100710071q0071	I
    //   228: ldc 95
    //   230: ldc -128
    //   232: bipush 111
    //   234: iconst_2
    //   235: invokestatic 65	xxxxxx/uxxxxx:bb00620062bb0062b0062b0062	(Ljava/lang/String;CC)Ljava/lang/String;
    //   238: iconst_3
    //   239: anewarray 34	java/lang/Class
    //   242: dup
    //   243: iconst_0
    //   244: ldc 99
    //   246: aastore
    //   247: dup
    //   248: iconst_1
    //   249: getstatic 105	java/lang/Character:TYPE	Ljava/lang/Class;
    //   252: aastore
    //   253: dup
    //   254: iconst_2
    //   255: getstatic 105	java/lang/Character:TYPE	Ljava/lang/Class;
    //   258: aastore
    //   259: invokevirtual 71	java/lang/Class:getMethod	(Ljava/lang/String;[Ljava/lang/Class;)Ljava/lang/reflect/Method;
    //   262: astore_2
    //   263: aload_2
    //   264: aconst_null
    //   265: iconst_3
    //   266: anewarray 73	java/lang/Object
    //   269: dup
    //   270: iconst_0
    //   271: ldc -126
    //   273: aastore
    //   274: dup
    //   275: iconst_1
    //   276: bipush 34
    //   278: invokestatic 111	java/lang/Character:valueOf	(C)Ljava/lang/Character;
    //   281: aastore
    //   282: dup
    //   283: iconst_2
    //   284: iconst_4
    //   285: invokestatic 111	java/lang/Character:valueOf	(C)Ljava/lang/Character;
    //   288: aastore
    //   289: invokevirtual 79	java/lang/reflect/Method:invoke	(Ljava/lang/Object;[Ljava/lang/Object;)Ljava/lang/Object;
    //   292: astore_2
    //   293: aload_1
    //   294: aload_2
    //   295: checkcast 99	java/lang/String
    //   298: invokestatic 136	uuuuuu/rvvvrv:bqqqq00710071q0071q0071	(Ljava/lang/String;Ljava/lang/String;)V
    //   301: aload_0
    //   302: getfield 48	com/db/pwcc/dbmobile/data/utils/network/NetworkChangeReceiver:callback	Lcom/db/pwcc/dbmobile/data/utils/network/NetworkChangeReceiver$yhhhyh;
    //   305: invokeinterface 139 1 0
    //   310: return
    //   311: aload_1
    //   312: invokestatic 142	uuuuuu/hyhhyh:bo006Foooooooo	(Landroid/content/Context;)Z
    //   315: ifeq +137 -> 452
    //   318: getstatic 40	com/db/pwcc/dbmobile/data/utils/network/NetworkChangeReceiver:TAG	Ljava/lang/String;
    //   321: astore_1
    //   322: new 144	java/lang/StringBuilder
    //   325: dup
    //   326: invokespecial 145	java/lang/StringBuilder:<init>	()V
    //   329: astore_2
    //   330: ldc 95
    //   332: ldc -109
    //   334: bipush 92
    //   336: sipush 174
    //   339: iconst_1
    //   340: invokestatic 87	xxxxxx/uxxxxx:bbbb0062b0062b0062b0062	(Ljava/lang/String;CCC)Ljava/lang/String;
    //   343: iconst_3
    //   344: anewarray 34	java/lang/Class
    //   347: dup
    //   348: iconst_0
    //   349: ldc 99
    //   351: aastore
    //   352: dup
    //   353: iconst_1
    //   354: getstatic 105	java/lang/Character:TYPE	Ljava/lang/Class;
    //   357: aastore
    //   358: dup
    //   359: iconst_2
    //   360: getstatic 105	java/lang/Character:TYPE	Ljava/lang/Class;
    //   363: aastore
    //   364: invokevirtual 71	java/lang/Class:getMethod	(Ljava/lang/String;[Ljava/lang/Class;)Ljava/lang/reflect/Method;
    //   367: astore 4
    //   369: aload 4
    //   371: aconst_null
    //   372: iconst_3
    //   373: anewarray 73	java/lang/Object
    //   376: dup
    //   377: iconst_0
    //   378: ldc -107
    //   380: aastore
    //   381: dup
    //   382: iconst_1
    //   383: sipush 195
    //   386: invokestatic 111	java/lang/Character:valueOf	(C)Ljava/lang/Character;
    //   389: aastore
    //   390: dup
    //   391: iconst_2
    //   392: iconst_3
    //   393: invokestatic 111	java/lang/Character:valueOf	(C)Ljava/lang/Character;
    //   396: aastore
    //   397: invokevirtual 79	java/lang/reflect/Method:invoke	(Ljava/lang/Object;[Ljava/lang/Object;)Ljava/lang/Object;
    //   400: astore 4
    //   402: aload_1
    //   403: aload_2
    //   404: aload 4
    //   406: checkcast 99	java/lang/String
    //   409: invokevirtual 153	java/lang/StringBuilder:append	(Ljava/lang/String;)Ljava/lang/StringBuilder;
    //   412: getstatic 159	uuuuuu/hhhhyh:b00700070p007000700070ppp	Luuuuuu/hhhhyh;
    //   415: invokevirtual 162	uuuuuu/hhhhyh:name	()Ljava/lang/String;
    //   418: invokevirtual 153	java/lang/StringBuilder:append	(Ljava/lang/String;)Ljava/lang/StringBuilder;
    //   421: invokevirtual 165	java/lang/StringBuilder:toString	()Ljava/lang/String;
    //   424: invokestatic 136	uuuuuu/rvvvrv:bqqqq00710071q0071q0071	(Ljava/lang/String;Ljava/lang/String;)V
    //   427: aload_0
    //   428: getfield 48	com/db/pwcc/dbmobile/data/utils/network/NetworkChangeReceiver:callback	Lcom/db/pwcc/dbmobile/data/utils/network/NetworkChangeReceiver$yhhhyh;
    //   431: getstatic 159	uuuuuu/hhhhyh:b00700070p007000700070ppp	Luuuuuu/hhhhyh;
    //   434: invokeinterface 169 2 0
    //   439: return
    //   440: astore_1
    //   441: aload_1
    //   442: invokevirtual 173	java/lang/reflect/InvocationTargetException:getCause	()Ljava/lang/Throwable;
    //   445: athrow
    //   446: astore_1
    //   447: aload_1
    //   448: invokevirtual 173	java/lang/reflect/InvocationTargetException:getCause	()Ljava/lang/Throwable;
    //   451: athrow
    //   452: aload_1
    //   453: invokestatic 177	uuuuuu/hyhhyh:b00700070p0070007000700070007000700070	(Landroid/content/Context;)Luuuuuu/hhhhyh;
    //   456: astore_1
    //   457: aload_0
    //   458: getfield 48	com/db/pwcc/dbmobile/data/utils/network/NetworkChangeReceiver:callback	Lcom/db/pwcc/dbmobile/data/utils/network/NetworkChangeReceiver$yhhhyh;
    //   461: aload_1
    //   462: invokeinterface 169 2 0
    //   467: getstatic 40	com/db/pwcc/dbmobile/data/utils/network/NetworkChangeReceiver:TAG	Ljava/lang/String;
    //   470: astore_2
    //   471: new 144	java/lang/StringBuilder
    //   474: dup
    //   475: invokespecial 145	java/lang/StringBuilder:<init>	()V
    //   478: astore 4
    //   480: getstatic 22	com/db/pwcc/dbmobile/data/utils/network/NetworkChangeReceiver:b00710071q00710071q0071	I
    //   483: invokestatic 179	com/db/pwcc/dbmobile/data/utils/network/NetworkChangeReceiver:bqqqqq00710071	()I
    //   486: iadd
    //   487: getstatic 22	com/db/pwcc/dbmobile/data/utils/network/NetworkChangeReceiver:b00710071q00710071q0071	I
    //   490: imul
    //   491: getstatic 26	com/db/pwcc/dbmobile/data/utils/network/NetworkChangeReceiver:bq0071007100710071q0071	I
    //   494: irem
    //   495: getstatic 28	com/db/pwcc/dbmobile/data/utils/network/NetworkChangeReceiver:bqq007100710071q0071	I
    //   498: if_icmpeq +15 -> 513
    //   501: invokestatic 32	com/db/pwcc/dbmobile/data/utils/network/NetworkChangeReceiver:b00710071007100710071q0071	()I
    //   504: putstatic 22	com/db/pwcc/dbmobile/data/utils/network/NetworkChangeReceiver:b00710071q00710071q0071	I
    //   507: invokestatic 32	com/db/pwcc/dbmobile/data/utils/network/NetworkChangeReceiver:b00710071007100710071q0071	()I
    //   510: putstatic 28	com/db/pwcc/dbmobile/data/utils/network/NetworkChangeReceiver:bqq007100710071q0071	I
    //   513: ldc 95
    //   515: ldc -75
    //   517: sipush 252
    //   520: bipush 117
    //   522: iconst_1
    //   523: invokestatic 87	xxxxxx/uxxxxx:bbbb0062b0062b0062b0062	(Ljava/lang/String;CCC)Ljava/lang/String;
    //   526: iconst_4
    //   527: anewarray 34	java/lang/Class
    //   530: dup
    //   531: iconst_0
    //   532: ldc 99
    //   534: aastore
    //   535: dup
    //   536: iconst_1
    //   537: getstatic 105	java/lang/Character:TYPE	Ljava/lang/Class;
    //   540: aastore
    //   541: dup
    //   542: iconst_2
    //   543: getstatic 105	java/lang/Character:TYPE	Ljava/lang/Class;
    //   546: aastore
    //   547: dup
    //   548: iconst_3
    //   549: getstatic 105	java/lang/Character:TYPE	Ljava/lang/Class;
    //   552: aastore
    //   553: invokevirtual 71	java/lang/Class:getMethod	(Ljava/lang/String;[Ljava/lang/Class;)Ljava/lang/reflect/Method;
    //   556: astore 5
    //   558: aload 5
    //   560: aconst_null
    //   561: iconst_4
    //   562: anewarray 73	java/lang/Object
    //   565: dup
    //   566: iconst_0
    //   567: ldc -73
    //   569: aastore
    //   570: dup
    //   571: iconst_1
    //   572: bipush 8
    //   574: invokestatic 111	java/lang/Character:valueOf	(C)Ljava/lang/Character;
    //   577: aastore
    //   578: dup
    //   579: iconst_2
    //   580: sipush 132
    //   583: invokestatic 111	java/lang/Character:valueOf	(C)Ljava/lang/Character;
    //   586: aastore
    //   587: dup
    //   588: iconst_3
    //   589: iconst_3
    //   590: invokestatic 111	java/lang/Character:valueOf	(C)Ljava/lang/Character;
    //   593: aastore
    //   594: invokevirtual 79	java/lang/reflect/Method:invoke	(Ljava/lang/Object;[Ljava/lang/Object;)Ljava/lang/Object;
    //   597: astore 5
    //   599: aload_2
    //   600: aload 4
    //   602: aload 5
    //   604: checkcast 99	java/lang/String
    //   607: invokevirtual 153	java/lang/StringBuilder:append	(Ljava/lang/String;)Ljava/lang/StringBuilder;
    //   610: aload_1
    //   611: invokevirtual 162	uuuuuu/hhhhyh:name	()Ljava/lang/String;
    //   614: invokevirtual 153	java/lang/StringBuilder:append	(Ljava/lang/String;)Ljava/lang/StringBuilder;
    //   617: invokevirtual 165	java/lang/StringBuilder:toString	()Ljava/lang/String;
    //   620: invokestatic 136	uuuuuu/rvvvrv:bqqqq00710071q0071q0071	(Ljava/lang/String;Ljava/lang/String;)V
    //   623: return
    //   624: astore_1
    //   625: aload_1
    //   626: invokevirtual 173	java/lang/reflect/InvocationTargetException:getCause	()Ljava/lang/Throwable;
    //   629: athrow
    //   630: astore_1
    //   631: aload_1
    //   632: invokevirtual 173	java/lang/reflect/InvocationTargetException:getCause	()Ljava/lang/Throwable;
    //   635: athrow
    //   636: astore_1
    //   637: aload_1
    //   638: invokevirtual 173	java/lang/reflect/InvocationTargetException:getCause	()Ljava/lang/Throwable;
    //   641: athrow
    //   642: astore_1
    //   643: aload_1
    //   644: invokevirtual 173	java/lang/reflect/InvocationTargetException:getCause	()Ljava/lang/Throwable;
    //   647: athrow
    // Local variable table:
    //   start	length	slot	name	signature
    //   0	648	0	this	NetworkChangeReceiver
    //   0	648	1	paramContext	Context
    //   0	648	2	paramIntent	android.content.Intent
    //   185	8	3	i	int
    //   23	578	4	localObject1	Object
    //   556	47	5	localObject2	Object
    // Exception table:
    //   from	to	target	type
    //   369	402	440	java/lang/reflect/InvocationTargetException
    //   263	293	446	java/lang/reflect/InvocationTargetException
    //   67	82	624	java/lang/reflect/InvocationTargetException
    //   123	156	630	java/lang/reflect/InvocationTargetException
    //   558	599	636	java/lang/reflect/InvocationTargetException
    //   25	40	642	java/lang/reflect/InvocationTargetException
  }
  
  /* Error */
  public void registerReceiver(Context paramContext)
  {
    // Byte code:
    //   0: getstatic 22	com/db/pwcc/dbmobile/data/utils/network/NetworkChangeReceiver:b00710071q00710071q0071	I
    //   3: istore_2
    //   4: iload_2
    //   5: getstatic 24	com/db/pwcc/dbmobile/data/utils/network/NetworkChangeReceiver:b0071q007100710071q0071	I
    //   8: iload_2
    //   9: iadd
    //   10: imul
    //   11: getstatic 26	com/db/pwcc/dbmobile/data/utils/network/NetworkChangeReceiver:bq0071007100710071q0071	I
    //   14: irem
    //   15: tableswitch	default:+17->32, 0:+28->43
    //   32: bipush 27
    //   34: putstatic 22	com/db/pwcc/dbmobile/data/utils/network/NetworkChangeReceiver:b00710071q00710071q0071	I
    //   37: invokestatic 32	com/db/pwcc/dbmobile/data/utils/network/NetworkChangeReceiver:b00710071007100710071q0071	()I
    //   40: putstatic 28	com/db/pwcc/dbmobile/data/utils/network/NetworkChangeReceiver:bqq007100710071q0071	I
    //   43: ldc 95
    //   45: ldc -70
    //   47: bipush 68
    //   49: sipush 129
    //   52: iconst_3
    //   53: invokestatic 87	xxxxxx/uxxxxx:bbbb0062b0062b0062b0062	(Ljava/lang/String;CCC)Ljava/lang/String;
    //   56: iconst_3
    //   57: anewarray 34	java/lang/Class
    //   60: dup
    //   61: iconst_0
    //   62: ldc 99
    //   64: aastore
    //   65: dup
    //   66: iconst_1
    //   67: getstatic 105	java/lang/Character:TYPE	Ljava/lang/Class;
    //   70: aastore
    //   71: dup
    //   72: iconst_2
    //   73: getstatic 105	java/lang/Character:TYPE	Ljava/lang/Class;
    //   76: aastore
    //   77: invokevirtual 71	java/lang/Class:getMethod	(Ljava/lang/String;[Ljava/lang/Class;)Ljava/lang/reflect/Method;
    //   80: astore_3
    //   81: aload_3
    //   82: aconst_null
    //   83: iconst_3
    //   84: anewarray 73	java/lang/Object
    //   87: dup
    //   88: iconst_0
    //   89: ldc -68
    //   91: aastore
    //   92: dup
    //   93: iconst_1
    //   94: bipush 76
    //   96: invokestatic 111	java/lang/Character:valueOf	(C)Ljava/lang/Character;
    //   99: aastore
    //   100: dup
    //   101: iconst_2
    //   102: iconst_2
    //   103: invokestatic 111	java/lang/Character:valueOf	(C)Ljava/lang/Character;
    //   106: aastore
    //   107: invokevirtual 79	java/lang/reflect/Method:invoke	(Ljava/lang/Object;[Ljava/lang/Object;)Ljava/lang/Object;
    //   110: astore_3
    //   111: new 190	android/content/IntentFilter
    //   114: dup
    //   115: aload_3
    //   116: checkcast 99	java/lang/String
    //   119: invokespecial 193	android/content/IntentFilter:<init>	(Ljava/lang/String;)V
    //   122: astore_3
    //   123: ldc 95
    //   125: ldc -61
    //   127: bipush 35
    //   129: iconst_5
    //   130: invokestatic 65	xxxxxx/uxxxxx:bb00620062bb0062b0062b0062	(Ljava/lang/String;CC)Ljava/lang/String;
    //   133: iconst_4
    //   134: anewarray 34	java/lang/Class
    //   137: dup
    //   138: iconst_0
    //   139: ldc 99
    //   141: aastore
    //   142: dup
    //   143: iconst_1
    //   144: getstatic 105	java/lang/Character:TYPE	Ljava/lang/Class;
    //   147: aastore
    //   148: dup
    //   149: iconst_2
    //   150: getstatic 105	java/lang/Character:TYPE	Ljava/lang/Class;
    //   153: aastore
    //   154: dup
    //   155: iconst_3
    //   156: getstatic 105	java/lang/Character:TYPE	Ljava/lang/Class;
    //   159: aastore
    //   160: invokevirtual 71	java/lang/Class:getMethod	(Ljava/lang/String;[Ljava/lang/Class;)Ljava/lang/reflect/Method;
    //   163: astore 4
    //   165: aload 4
    //   167: aconst_null
    //   168: iconst_4
    //   169: anewarray 73	java/lang/Object
    //   172: dup
    //   173: iconst_0
    //   174: ldc -59
    //   176: aastore
    //   177: dup
    //   178: iconst_1
    //   179: sipush 137
    //   182: invokestatic 111	java/lang/Character:valueOf	(C)Ljava/lang/Character;
    //   185: aastore
    //   186: dup
    //   187: iconst_2
    //   188: sipush 240
    //   191: invokestatic 111	java/lang/Character:valueOf	(C)Ljava/lang/Character;
    //   194: aastore
    //   195: dup
    //   196: iconst_3
    //   197: iconst_1
    //   198: invokestatic 111	java/lang/Character:valueOf	(C)Ljava/lang/Character;
    //   201: aastore
    //   202: invokevirtual 79	java/lang/reflect/Method:invoke	(Ljava/lang/Object;[Ljava/lang/Object;)Ljava/lang/Object;
    //   205: astore 4
    //   207: aload_3
    //   208: aload 4
    //   210: checkcast 99	java/lang/String
    //   213: invokevirtual 200	android/content/IntentFilter:addAction	(Ljava/lang/String;)V
    //   216: aload_1
    //   217: aload_0
    //   218: aload_3
    //   219: invokevirtual 203	android/content/Context:registerReceiver	(Landroid/content/BroadcastReceiver;Landroid/content/IntentFilter;)Landroid/content/Intent;
    //   222: pop
    //   223: getstatic 22	com/db/pwcc/dbmobile/data/utils/network/NetworkChangeReceiver:b00710071q00710071q0071	I
    //   226: getstatic 24	com/db/pwcc/dbmobile/data/utils/network/NetworkChangeReceiver:b0071q007100710071q0071	I
    //   229: iadd
    //   230: getstatic 22	com/db/pwcc/dbmobile/data/utils/network/NetworkChangeReceiver:b00710071q00710071q0071	I
    //   233: imul
    //   234: getstatic 26	com/db/pwcc/dbmobile/data/utils/network/NetworkChangeReceiver:bq0071007100710071q0071	I
    //   237: irem
    //   238: invokestatic 205	com/db/pwcc/dbmobile/data/utils/network/NetworkChangeReceiver:b0071qqqq00710071	()I
    //   241: if_icmpeq +14 -> 255
    //   244: bipush 75
    //   246: putstatic 22	com/db/pwcc/dbmobile/data/utils/network/NetworkChangeReceiver:b00710071q00710071q0071	I
    //   249: invokestatic 32	com/db/pwcc/dbmobile/data/utils/network/NetworkChangeReceiver:b00710071007100710071q0071	()I
    //   252: putstatic 28	com/db/pwcc/dbmobile/data/utils/network/NetworkChangeReceiver:bqq007100710071q0071	I
    //   255: return
    //   256: astore_1
    //   257: aload_1
    //   258: invokevirtual 173	java/lang/reflect/InvocationTargetException:getCause	()Ljava/lang/Throwable;
    //   261: athrow
    //   262: astore_1
    //   263: aload_1
    //   264: invokevirtual 173	java/lang/reflect/InvocationTargetException:getCause	()Ljava/lang/Throwable;
    //   267: athrow
    // Local variable table:
    //   start	length	slot	name	signature
    //   0	268	0	this	NetworkChangeReceiver
    //   0	268	1	paramContext	Context
    //   3	8	2	i	int
    //   80	139	3	localObject1	Object
    //   163	46	4	localObject2	Object
    // Exception table:
    //   from	to	target	type
    //   81	111	256	java/lang/reflect/InvocationTargetException
    //   165	207	262	java/lang/reflect/InvocationTargetException
  }
  
  public void unregisterReceiver(Context paramContext)
  {
    paramContext.unregisterReceiver(this);
    if ((b00710071q00710071q0071 + b0071q007100710071q0071) * b00710071q00710071q0071 % bq0071007100710071q0071 != b0071qqqq00710071())
    {
      int i = b00710071q00710071q0071;
      switch (i * (b0071q007100710071q0071 + i) % bq0071007100710071q0071)
      {
      default: 
        b00710071q00710071q0071 = b00710071007100710071q0071();
        bqq007100710071q0071 = 45;
      }
      b00710071q00710071q0071 = 83;
      bqq007100710071q0071 = 15;
    }
  }
  
  public static abstract interface yhhhyh
  {
    public abstract void b00610061aa0061aaa0061a(hhhhyh paramHhhhyh);
    
    public abstract void baa0061a0061aaa0061a();
  }
}
