package com.db.pwcc.dbmobile.transfer.standingorder.confirm;

import android.content.Context;
import android.content.Intent;
import android.os.Bundle;
import android.widget.TextView;
import com.db.pwcc.dbmobile.model.error.DbError;
import com.db.pwcc.dbmobile.model.tan.Authorization;
import com.db.pwcc.dbmobile.model.tan.AuthorizationStatus;
import com.db.pwcc.dbmobile.model.tan.ChallengeResponse;
import com.db.pwcc.dbmobile.tan.ui.TanModule;
import com.db.pwcc.dbmobile.transfer.R.id;
import com.db.pwcc.dbmobile.transfer.R.layout;
import com.db.pwcc.dbmobile.transfer.R.string;
import com.db.pwcc.dbmobile.transfer.inputscreen.activities.ConfirmationActivity;
import com.db.pwcc.dbmobile.transfer.inputscreen.activities.StandingOrderDetailsActivity;
import com.db.pwcc.dbmobile.transfer.inputscreen.activities.StandingOrdersActivity;
import com.db.pwcc.dbmobile.transfer.standingorder.model.StandingOrderRequestResponse;
import com.db.pwcc.dbmobile.transfer.standingorder.model.StandingOrderTemplate;
import com.db.pwcc.dbmobile.transfer.standingorder.model.StandingOrderTransaction;
import java.lang.reflect.InvocationTargetException;
import java.lang.reflect.Method;
import java.text.ParseException;
import java.text.SimpleDateFormat;
import java.util.Calendar;
import java.util.Date;
import java.util.Locale;
import uuuuuu.kkkklk;
import uuuuuu.llvvll.lvvvll;
import uuuuuu.llvvll.vlvvll;
import uuuuuu.ppphhp;
import uuuuuu.pqpppq;
import uuuuuu.vvrvrv;
import uuuuuu.xxsxsx;
import xxxxxx.uxxxxx;

public class StandingOrderConfirmationActivity
  extends ConfirmationActivity
  implements llvvll.lvvvll
{
  public static final String EXTRA_BIC = "N\003~nPxs";
  public static final String EXTRA_FROM_TRANSACTIONS_LIST = "ITPM3P>JN;<L@ECG\037;DD";
  public static final String EXTRA_FROM_TRANSACTION_DETAILS = "\004\021\017\016u\025\005\023\031\b\013\035\023\032\032p\023#\021\032\036&";
  public static final String EXTRA_STANDING_ORDER_REQUEST_RESPONSE = "g\nw\006|\003\t\003k\020\003\005\023s\b\025\032\013\032\034z\017\036\034\034\034\"\025";
  public static final String EXTRA_TAN_CHALLENGE = "\"VSRB6DR(NHTUOYSR";
  public static final String EXTRA_TEMPLATE = "\t\033\026\023\001r\003\n\f\007z\r|";
  public static int b006D006D006D006Dm006Dmm006D = 1;
  public static int b006Dmm006Dm006Dmm006D = 6;
  public static int bm006Dm006Dm006Dmm006D = 0;
  public static int bmm006D006Dm006Dmm006D = 2;
  private ChallengeResponse challengeResponse = null;
  private llvvll.vlvvll presenter = null;
  private StandingOrderRequestResponse standingOrderRequestResponse = null;
  private StandingOrderTemplate standingOrderTemplate = null;
  
  public StandingOrderConfirmationActivity() {}
  
  public static int b006D006Dm006Dm006Dmm006D()
  {
    return 1;
  }
  
  public static int b006Dm006D006Dm006Dmm006D()
  {
    return 60;
  }
  
  public static int bm006D006D006Dm006Dmm006D()
  {
    return 0;
  }
  
  public static int bmmmm006D006Dmm006D()
  {
    return 2;
  }
  
  private boolean isDeleteMode()
  {
    Object localObject1 = this.standingOrderRequestResponse.getTransaction();
    if ((b006Dmm006Dm006Dmm006D + b006D006D006D006Dm006Dmm006D) * b006Dmm006Dm006Dmm006D % bmm006D006Dm006Dmm006D != bm006D006D006Dm006Dmm006D())
    {
      if ((b006Dmm006Dm006Dmm006D + b006D006D006D006Dm006Dmm006D) * b006Dmm006Dm006Dmm006D % bmm006D006Dm006Dmm006D != bm006Dm006Dm006Dmm006D)
      {
        b006Dmm006Dm006Dmm006D = 50;
        bm006Dm006Dm006Dmm006D = 35;
      }
      b006Dmm006Dm006Dmm006D = 21;
      bm006Dm006Dm006Dmm006D = 99;
    }
    localObject1 = ((StandingOrderTransaction)localObject1).getType();
    if ((b006Dmm006Dm006Dmm006D + b006D006Dm006Dm006Dmm006D()) * b006Dmm006Dm006Dmm006D % bmm006D006Dm006Dmm006D != bm006Dm006Dm006Dmm006D)
    {
      b006Dmm006Dm006Dmm006D = 62;
      int i = b006Dm006D006Dm006Dmm006D();
      int j = b006Dm006D006Dm006Dmm006D();
      switch (j * (b006D006D006D006Dm006Dmm006D + j) % bmm006D006Dm006Dmm006D)
      {
      default: 
        b006Dmm006Dm006Dmm006D = 67;
        bm006Dm006Dm006Dmm006D = b006Dm006D006Dm006Dmm006D();
      }
      bm006Dm006Dm006Dmm006D = i;
    }
    Object localObject2 = ppphhp.class.getMethod(uxxxxx.bb00620062bb0062b0062b0062("\013!\"#$]^fgabjk-fgopjkst6", '(', '\002'), new Class[] { String.class, Character.TYPE, Character.TYPE });
    try
    {
      localObject2 = ((Method)localObject2).invoke(null, new Object[] { "MOWQaSnceSaX^d^whl_ao", Character.valueOf('D'), Character.valueOf('\001') });
      return ((String)localObject1).equals((String)localObject2);
    }
    catch (InvocationTargetException localInvocationTargetException)
    {
      throw localInvocationTargetException.getCause();
    }
  }
  
  private boolean isUpdateMode()
  {
    int i = b006Dmm006Dm006Dmm006D;
    switch (i * (b006D006D006D006Dm006Dmm006D + i) % bmm006D006Dm006Dmm006D)
    {
    default: 
      b006Dmm006Dm006Dmm006D = b006Dm006D006Dm006Dmm006D();
      bm006Dm006Dm006Dmm006D = b006Dm006D006Dm006Dmm006D();
      i = b006Dmm006Dm006Dmm006D;
      switch (i * (b006D006D006D006Dm006Dmm006D + i) % bmm006D006Dm006Dmm006D)
      {
      default: 
        b006Dmm006Dm006Dmm006D = b006Dm006D006Dm006Dmm006D();
        bm006Dm006Dm006Dmm006D = b006Dm006D006Dm006Dmm006D();
      }
      break;
    }
    String str = this.standingOrderRequestResponse.getTransaction().getType();
    Object localObject = ppphhp.class.getMethod(uxxxxx.bb00620062bb0062b0062b0062("\005\033\034\035\036WX`a[\\de'`aijdemn0", '\021', '\001'), new Class[] { String.class, Character.TYPE, Character.TYPE });
    try
    {
      localObject = ((Method)localObject).invoke(null, new Object[] { "A=20D6QFH6D;AGAZKOBDR", Character.valueOf('N'), Character.valueOf('\000') });
      localObject = (String)localObject;
      if ((b006Dmm006Dm006Dmm006D + b006D006D006D006Dm006Dmm006D) * b006Dmm006Dm006Dmm006D % bmm006D006Dm006Dmm006D != bm006Dm006Dm006Dmm006D)
      {
        b006Dmm006Dm006Dmm006D = 83;
        bm006Dm006Dm006Dmm006D = b006Dm006D006Dm006Dmm006D();
        i = b006Dmm006Dm006Dmm006D;
        switch (i * (b006D006D006D006Dm006Dmm006D + i) % bmm006D006Dm006Dmm006D)
        {
        default: 
          b006Dmm006Dm006Dmm006D = b006Dm006D006Dm006Dmm006D();
          bm006Dm006Dm006Dmm006D = 6;
        }
      }
      return str.equals(localObject);
    }
    catch (InvocationTargetException localInvocationTargetException)
    {
      throw localInvocationTargetException.getCause();
    }
  }
  
  public static Intent makeIntent(Context paramContext, StandingOrderRequestResponse paramStandingOrderRequestResponse, ChallengeResponse paramChallengeResponse, Authorization paramAuthorization, AuthorizationStatus paramAuthorizationStatus, String paramString)
  {
    paramContext = makeIntent(paramContext, paramStandingOrderRequestResponse, paramChallengeResponse, paramAuthorization, paramAuthorizationStatus, paramString, null, null, null);
    if ((b006Dmm006Dm006Dmm006D + b006D006D006D006Dm006Dmm006D) * b006Dmm006Dm006Dmm006D % bmm006D006Dm006Dmm006D != bm006Dm006Dm006Dmm006D)
    {
      int i = b006Dmm006Dm006Dmm006D;
      switch (i * (b006D006D006D006Dm006Dmm006D + i) % bmm006D006Dm006Dmm006D)
      {
      default: 
        b006Dmm006Dm006Dmm006D = 43;
        bm006Dm006Dm006Dmm006D = 52;
        if ((b006Dmm006Dm006Dmm006D + b006D006D006D006Dm006Dmm006D) * b006Dmm006Dm006Dmm006D % bmm006D006Dm006Dmm006D != bm006Dm006Dm006Dmm006D)
        {
          b006Dmm006Dm006Dmm006D = 85;
          bm006Dm006Dm006Dmm006D = 60;
        }
        break;
      }
      b006Dmm006Dm006Dmm006D = 48;
      bm006Dm006Dm006Dmm006D = 50;
      i = b006Dmm006Dm006Dmm006D;
      switch (i * (b006D006D006D006Dm006Dmm006D + i) % bmm006D006Dm006Dmm006D)
      {
      default: 
        b006Dmm006Dm006Dmm006D = b006Dm006D006Dm006Dmm006D();
        bm006Dm006Dm006Dmm006D = 37;
      }
    }
    return paramContext;
  }
  
  public static Intent makeIntent(Context paramContext, StandingOrderRequestResponse paramStandingOrderRequestResponse, ChallengeResponse paramChallengeResponse, Authorization paramAuthorization, AuthorizationStatus paramAuthorizationStatus, String paramString1, String paramString2)
  {
    if ((b006Dmm006Dm006Dmm006D + b006D006D006D006Dm006Dmm006D) * b006Dmm006Dm006Dmm006D % bmmmm006D006Dmm006D() != bm006D006D006Dm006Dmm006D())
    {
      b006Dmm006Dm006Dmm006D = b006Dm006D006Dm006Dmm006D();
      bm006Dm006Dm006Dmm006D = b006Dm006D006Dm006Dmm006D();
    }
    if ((b006Dm006D006Dm006Dmm006D() + b006D006D006D006Dm006Dmm006D) * b006Dm006D006Dm006Dmm006D() % bmm006D006Dm006Dmm006D != bm006Dm006Dm006Dmm006D)
    {
      if ((b006Dmm006Dm006Dmm006D + b006D006D006D006Dm006Dmm006D) * b006Dmm006Dm006Dmm006D % bmm006D006Dm006Dmm006D != bm006Dm006Dm006Dmm006D)
      {
        if ((b006Dmm006Dm006Dmm006D + b006D006Dm006Dm006Dmm006D()) * b006Dmm006Dm006Dmm006D % bmm006D006Dm006Dmm006D != bm006Dm006Dm006Dmm006D)
        {
          b006Dmm006Dm006Dmm006D = b006Dm006D006Dm006Dmm006D();
          bm006Dm006Dm006Dmm006D = 25;
        }
        b006Dmm006Dm006Dmm006D = b006Dm006D006Dm006Dmm006D();
        bm006Dm006Dm006Dmm006D = b006Dm006D006Dm006Dmm006D();
      }
      b006Dmm006Dm006Dmm006D = 32;
      bm006Dm006Dm006Dmm006D = b006Dm006D006Dm006Dmm006D();
    }
    return makeIntent(paramContext, paramStandingOrderRequestResponse, paramChallengeResponse, paramAuthorization, paramAuthorizationStatus, paramString1, paramString2, null, null);
  }
  
  public static Intent makeIntent(Context paramContext, StandingOrderRequestResponse paramStandingOrderRequestResponse, ChallengeResponse paramChallengeResponse, Authorization paramAuthorization, AuthorizationStatus paramAuthorizationStatus, String paramString1, String paramString2, StandingOrderTemplate paramStandingOrderTemplate)
  {
    int i = b006Dmm006Dm006Dmm006D;
    switch (i * (b006D006D006D006Dm006Dmm006D + i) % bmm006D006Dm006Dmm006D)
    {
    default: 
      b006Dmm006Dm006Dmm006D = b006Dm006D006Dm006Dmm006D();
      bm006Dm006Dm006Dmm006D = b006Dm006D006Dm006Dmm006D();
    }
    i = b006Dm006D006Dm006Dmm006D();
    int j = b006D006D006D006Dm006Dmm006D;
    int k = b006Dm006D006Dm006Dmm006D();
    int m = b006Dmm006Dm006Dmm006D;
    switch (m * (b006D006D006D006Dm006Dmm006D + m) % bmm006D006Dm006Dmm006D)
    {
    default: 
      b006Dmm006Dm006Dmm006D = b006Dm006D006Dm006Dmm006D();
      bm006Dm006Dm006Dmm006D = b006Dm006D006Dm006Dmm006D();
      if ((b006Dmm006Dm006Dmm006D + b006D006D006D006Dm006Dmm006D) * b006Dmm006Dm006Dmm006D % bmm006D006Dm006Dmm006D != bm006Dm006Dm006Dmm006D)
      {
        b006Dmm006Dm006Dmm006D = 22;
        bm006Dm006Dm006Dmm006D = 96;
      }
      break;
    }
    if ((i + j) * k % bmm006D006Dm006Dmm006D != bm006Dm006Dm006Dmm006D)
    {
      b006Dmm006Dm006Dmm006D = 86;
      bm006Dm006Dm006Dmm006D = 13;
    }
    return makeIntent(paramContext, paramStandingOrderRequestResponse, paramChallengeResponse, paramAuthorization, paramAuthorizationStatus, paramString1, paramString2, paramStandingOrderTemplate, null);
  }
  
  /* Error */
  public static Intent makeIntent(Context paramContext, StandingOrderRequestResponse paramStandingOrderRequestResponse, ChallengeResponse paramChallengeResponse, Authorization paramAuthorization, AuthorizationStatus paramAuthorizationStatus, String paramString1, String paramString2, StandingOrderTemplate paramStandingOrderTemplate, String paramString3)
  {
    // Byte code:
    //   0: new 152	android/content/Intent
    //   3: dup
    //   4: aload_0
    //   5: ldc 2
    //   7: invokespecial 155	android/content/Intent:<init>	(Landroid/content/Context;Ljava/lang/Class;)V
    //   10: astore_0
    //   11: ldc 92
    //   13: ldc -99
    //   15: bipush 76
    //   17: iconst_1
    //   18: invokestatic 100	xxxxxx/uxxxxx:bb00620062bb0062b0062b0062	(Ljava/lang/String;CC)Ljava/lang/String;
    //   21: iconst_3
    //   22: anewarray 102	java/lang/Class
    //   25: dup
    //   26: iconst_0
    //   27: ldc 104
    //   29: aastore
    //   30: dup
    //   31: iconst_1
    //   32: getstatic 110	java/lang/Character:TYPE	Ljava/lang/Class;
    //   35: aastore
    //   36: dup
    //   37: iconst_2
    //   38: getstatic 110	java/lang/Character:TYPE	Ljava/lang/Class;
    //   41: aastore
    //   42: invokevirtual 114	java/lang/Class:getMethod	(Ljava/lang/String;[Ljava/lang/Class;)Ljava/lang/reflect/Method;
    //   45: astore 10
    //   47: aload 10
    //   49: aconst_null
    //   50: iconst_3
    //   51: anewarray 116	java/lang/Object
    //   54: dup
    //   55: iconst_0
    //   56: ldc -97
    //   58: aastore
    //   59: dup
    //   60: iconst_1
    //   61: sipush 131
    //   64: invokestatic 122	java/lang/Character:valueOf	(C)Ljava/lang/Character;
    //   67: aastore
    //   68: dup
    //   69: iconst_2
    //   70: iconst_2
    //   71: invokestatic 122	java/lang/Character:valueOf	(C)Ljava/lang/Character;
    //   74: aastore
    //   75: invokevirtual 128	java/lang/reflect/Method:invoke	(Ljava/lang/Object;[Ljava/lang/Object;)Ljava/lang/Object;
    //   78: astore 10
    //   80: aload_0
    //   81: aload 10
    //   83: checkcast 104	java/lang/String
    //   86: aload_1
    //   87: invokevirtual 163	android/content/Intent:putExtra	(Ljava/lang/String;Ljava/io/Serializable;)Landroid/content/Intent;
    //   90: pop
    //   91: getstatic 72	com/db/pwcc/dbmobile/transfer/standingorder/confirm/StandingOrderConfirmationActivity:b006Dmm006Dm006Dmm006D	I
    //   94: istore 9
    //   96: iload 9
    //   98: getstatic 74	com/db/pwcc/dbmobile/transfer/standingorder/confirm/StandingOrderConfirmationActivity:b006D006D006D006Dm006Dmm006D	I
    //   101: iload 9
    //   103: iadd
    //   104: imul
    //   105: getstatic 76	com/db/pwcc/dbmobile/transfer/standingorder/confirm/StandingOrderConfirmationActivity:bmm006D006Dm006Dmm006D	I
    //   108: irem
    //   109: tableswitch	default:+19->128, 0:+29->138
    //   128: bipush 13
    //   130: putstatic 72	com/db/pwcc/dbmobile/transfer/standingorder/confirm/StandingOrderConfirmationActivity:b006Dmm006Dm006Dmm006D	I
    //   133: bipush 25
    //   135: putstatic 80	com/db/pwcc/dbmobile/transfer/standingorder/confirm/StandingOrderConfirmationActivity:bm006Dm006Dm006Dmm006D	I
    //   138: ldc 92
    //   140: ldc -91
    //   142: sipush 137
    //   145: iconst_1
    //   146: invokestatic 100	xxxxxx/uxxxxx:bb00620062bb0062b0062b0062	(Ljava/lang/String;CC)Ljava/lang/String;
    //   149: iconst_3
    //   150: anewarray 102	java/lang/Class
    //   153: dup
    //   154: iconst_0
    //   155: ldc 104
    //   157: aastore
    //   158: dup
    //   159: iconst_1
    //   160: getstatic 110	java/lang/Character:TYPE	Ljava/lang/Class;
    //   163: aastore
    //   164: dup
    //   165: iconst_2
    //   166: getstatic 110	java/lang/Character:TYPE	Ljava/lang/Class;
    //   169: aastore
    //   170: invokevirtual 114	java/lang/Class:getMethod	(Ljava/lang/String;[Ljava/lang/Class;)Ljava/lang/reflect/Method;
    //   173: astore_1
    //   174: aload_1
    //   175: aconst_null
    //   176: iconst_3
    //   177: anewarray 116	java/lang/Object
    //   180: dup
    //   181: iconst_0
    //   182: ldc -89
    //   184: aastore
    //   185: dup
    //   186: iconst_1
    //   187: sipush 137
    //   190: invokestatic 122	java/lang/Character:valueOf	(C)Ljava/lang/Character;
    //   193: aastore
    //   194: dup
    //   195: iconst_2
    //   196: iconst_1
    //   197: invokestatic 122	java/lang/Character:valueOf	(C)Ljava/lang/Character;
    //   200: aastore
    //   201: invokevirtual 128	java/lang/reflect/Method:invoke	(Ljava/lang/Object;[Ljava/lang/Object;)Ljava/lang/Object;
    //   204: astore_1
    //   205: aload_0
    //   206: aload_1
    //   207: checkcast 104	java/lang/String
    //   210: aload_2
    //   211: invokevirtual 170	android/content/Intent:putExtra	(Ljava/lang/String;Landroid/os/Parcelable;)Landroid/content/Intent;
    //   214: pop
    //   215: ldc 92
    //   217: ldc -84
    //   219: bipush 115
    //   221: iconst_0
    //   222: invokestatic 100	xxxxxx/uxxxxx:bb00620062bb0062b0062b0062	(Ljava/lang/String;CC)Ljava/lang/String;
    //   225: iconst_3
    //   226: anewarray 102	java/lang/Class
    //   229: dup
    //   230: iconst_0
    //   231: ldc 104
    //   233: aastore
    //   234: dup
    //   235: iconst_1
    //   236: getstatic 110	java/lang/Character:TYPE	Ljava/lang/Class;
    //   239: aastore
    //   240: dup
    //   241: iconst_2
    //   242: getstatic 110	java/lang/Character:TYPE	Ljava/lang/Class;
    //   245: aastore
    //   246: invokevirtual 114	java/lang/Class:getMethod	(Ljava/lang/String;[Ljava/lang/Class;)Ljava/lang/reflect/Method;
    //   249: astore_1
    //   250: aload_1
    //   251: aconst_null
    //   252: iconst_3
    //   253: anewarray 116	java/lang/Object
    //   256: dup
    //   257: iconst_0
    //   258: ldc -82
    //   260: aastore
    //   261: dup
    //   262: iconst_1
    //   263: bipush 49
    //   265: invokestatic 122	java/lang/Character:valueOf	(C)Ljava/lang/Character;
    //   268: aastore
    //   269: dup
    //   270: iconst_2
    //   271: iconst_4
    //   272: invokestatic 122	java/lang/Character:valueOf	(C)Ljava/lang/Character;
    //   275: aastore
    //   276: invokevirtual 128	java/lang/reflect/Method:invoke	(Ljava/lang/Object;[Ljava/lang/Object;)Ljava/lang/Object;
    //   279: astore_1
    //   280: aload_0
    //   281: aload_1
    //   282: checkcast 104	java/lang/String
    //   285: aload 5
    //   287: invokevirtual 177	android/content/Intent:putExtra	(Ljava/lang/String;Ljava/lang/String;)Landroid/content/Intent;
    //   290: pop
    //   291: ldc 92
    //   293: ldc -77
    //   295: bipush 28
    //   297: iconst_5
    //   298: invokestatic 100	xxxxxx/uxxxxx:bb00620062bb0062b0062b0062	(Ljava/lang/String;CC)Ljava/lang/String;
    //   301: iconst_3
    //   302: anewarray 102	java/lang/Class
    //   305: dup
    //   306: iconst_0
    //   307: ldc 104
    //   309: aastore
    //   310: dup
    //   311: iconst_1
    //   312: getstatic 110	java/lang/Character:TYPE	Ljava/lang/Class;
    //   315: aastore
    //   316: dup
    //   317: iconst_2
    //   318: getstatic 110	java/lang/Character:TYPE	Ljava/lang/Class;
    //   321: aastore
    //   322: invokevirtual 114	java/lang/Class:getMethod	(Ljava/lang/String;[Ljava/lang/Class;)Ljava/lang/reflect/Method;
    //   325: astore_1
    //   326: aload_1
    //   327: aconst_null
    //   328: iconst_3
    //   329: anewarray 116	java/lang/Object
    //   332: dup
    //   333: iconst_0
    //   334: ldc -75
    //   336: aastore
    //   337: dup
    //   338: iconst_1
    //   339: sipush 172
    //   342: invokestatic 122	java/lang/Character:valueOf	(C)Ljava/lang/Character;
    //   345: aastore
    //   346: dup
    //   347: iconst_2
    //   348: iconst_2
    //   349: invokestatic 122	java/lang/Character:valueOf	(C)Ljava/lang/Character;
    //   352: aastore
    //   353: invokevirtual 128	java/lang/reflect/Method:invoke	(Ljava/lang/Object;[Ljava/lang/Object;)Ljava/lang/Object;
    //   356: astore_1
    //   357: aload_0
    //   358: aload_1
    //   359: checkcast 104	java/lang/String
    //   362: aload_3
    //   363: invokevirtual 163	android/content/Intent:putExtra	(Ljava/lang/String;Ljava/io/Serializable;)Landroid/content/Intent;
    //   366: pop
    //   367: ldc 92
    //   369: ldc -73
    //   371: sipush 172
    //   374: bipush 39
    //   376: iconst_1
    //   377: invokestatic 187	xxxxxx/uxxxxx:bbbb0062b0062b0062b0062	(Ljava/lang/String;CCC)Ljava/lang/String;
    //   380: iconst_3
    //   381: anewarray 102	java/lang/Class
    //   384: dup
    //   385: iconst_0
    //   386: ldc 104
    //   388: aastore
    //   389: dup
    //   390: iconst_1
    //   391: getstatic 110	java/lang/Character:TYPE	Ljava/lang/Class;
    //   394: aastore
    //   395: dup
    //   396: iconst_2
    //   397: getstatic 110	java/lang/Character:TYPE	Ljava/lang/Class;
    //   400: aastore
    //   401: invokevirtual 114	java/lang/Class:getMethod	(Ljava/lang/String;[Ljava/lang/Class;)Ljava/lang/reflect/Method;
    //   404: astore_1
    //   405: aload_1
    //   406: aconst_null
    //   407: iconst_3
    //   408: anewarray 116	java/lang/Object
    //   411: dup
    //   412: iconst_0
    //   413: ldc -67
    //   415: aastore
    //   416: dup
    //   417: iconst_1
    //   418: sipush 163
    //   421: invokestatic 122	java/lang/Character:valueOf	(C)Ljava/lang/Character;
    //   424: aastore
    //   425: dup
    //   426: iconst_2
    //   427: iconst_2
    //   428: invokestatic 122	java/lang/Character:valueOf	(C)Ljava/lang/Character;
    //   431: aastore
    //   432: invokevirtual 128	java/lang/reflect/Method:invoke	(Ljava/lang/Object;[Ljava/lang/Object;)Ljava/lang/Object;
    //   435: astore_1
    //   436: aload_0
    //   437: aload_1
    //   438: checkcast 104	java/lang/String
    //   441: aload 4
    //   443: invokevirtual 163	android/content/Intent:putExtra	(Ljava/lang/String;Ljava/io/Serializable;)Landroid/content/Intent;
    //   446: pop
    //   447: getstatic 72	com/db/pwcc/dbmobile/transfer/standingorder/confirm/StandingOrderConfirmationActivity:b006Dmm006Dm006Dmm006D	I
    //   450: istore 9
    //   452: iload 9
    //   454: getstatic 74	com/db/pwcc/dbmobile/transfer/standingorder/confirm/StandingOrderConfirmationActivity:b006D006D006D006Dm006Dmm006D	I
    //   457: iload 9
    //   459: iadd
    //   460: imul
    //   461: getstatic 76	com/db/pwcc/dbmobile/transfer/standingorder/confirm/StandingOrderConfirmationActivity:bmm006D006Dm006Dmm006D	I
    //   464: irem
    //   465: tableswitch	default:+19->484, 0:+75->540
    //   484: getstatic 72	com/db/pwcc/dbmobile/transfer/standingorder/confirm/StandingOrderConfirmationActivity:b006Dmm006Dm006Dmm006D	I
    //   487: istore 9
    //   489: iload 9
    //   491: invokestatic 88	com/db/pwcc/dbmobile/transfer/standingorder/confirm/StandingOrderConfirmationActivity:b006D006Dm006Dm006Dmm006D	()I
    //   494: iload 9
    //   496: iadd
    //   497: imul
    //   498: getstatic 76	com/db/pwcc/dbmobile/transfer/standingorder/confirm/StandingOrderConfirmationActivity:bmm006D006Dm006Dmm006D	I
    //   501: irem
    //   502: tableswitch	default:+18->520, 0:+28->530
    //   520: bipush 99
    //   522: putstatic 72	com/db/pwcc/dbmobile/transfer/standingorder/confirm/StandingOrderConfirmationActivity:b006Dmm006Dm006Dmm006D	I
    //   525: bipush 99
    //   527: putstatic 80	com/db/pwcc/dbmobile/transfer/standingorder/confirm/StandingOrderConfirmationActivity:bm006Dm006Dm006Dmm006D	I
    //   530: bipush 51
    //   532: putstatic 72	com/db/pwcc/dbmobile/transfer/standingorder/confirm/StandingOrderConfirmationActivity:b006Dmm006Dm006Dmm006D	I
    //   535: bipush 79
    //   537: putstatic 80	com/db/pwcc/dbmobile/transfer/standingorder/confirm/StandingOrderConfirmationActivity:bm006Dm006Dm006Dmm006D	I
    //   540: aload 6
    //   542: ifnull +98 -> 640
    //   545: ldc 92
    //   547: ldc -65
    //   549: bipush 87
    //   551: sipush 148
    //   554: iconst_2
    //   555: invokestatic 187	xxxxxx/uxxxxx:bbbb0062b0062b0062b0062	(Ljava/lang/String;CCC)Ljava/lang/String;
    //   558: iconst_4
    //   559: anewarray 102	java/lang/Class
    //   562: dup
    //   563: iconst_0
    //   564: ldc 104
    //   566: aastore
    //   567: dup
    //   568: iconst_1
    //   569: getstatic 110	java/lang/Character:TYPE	Ljava/lang/Class;
    //   572: aastore
    //   573: dup
    //   574: iconst_2
    //   575: getstatic 110	java/lang/Character:TYPE	Ljava/lang/Class;
    //   578: aastore
    //   579: dup
    //   580: iconst_3
    //   581: getstatic 110	java/lang/Character:TYPE	Ljava/lang/Class;
    //   584: aastore
    //   585: invokevirtual 114	java/lang/Class:getMethod	(Ljava/lang/String;[Ljava/lang/Class;)Ljava/lang/reflect/Method;
    //   588: astore_1
    //   589: aload_1
    //   590: aconst_null
    //   591: iconst_4
    //   592: anewarray 116	java/lang/Object
    //   595: dup
    //   596: iconst_0
    //   597: ldc -63
    //   599: aastore
    //   600: dup
    //   601: iconst_1
    //   602: sipush 128
    //   605: invokestatic 122	java/lang/Character:valueOf	(C)Ljava/lang/Character;
    //   608: aastore
    //   609: dup
    //   610: iconst_2
    //   611: sipush 210
    //   614: invokestatic 122	java/lang/Character:valueOf	(C)Ljava/lang/Character;
    //   617: aastore
    //   618: dup
    //   619: iconst_3
    //   620: iconst_1
    //   621: invokestatic 122	java/lang/Character:valueOf	(C)Ljava/lang/Character;
    //   624: aastore
    //   625: invokevirtual 128	java/lang/reflect/Method:invoke	(Ljava/lang/Object;[Ljava/lang/Object;)Ljava/lang/Object;
    //   628: astore_1
    //   629: aload_0
    //   630: aload_1
    //   631: checkcast 104	java/lang/String
    //   634: aload 6
    //   636: invokevirtual 177	android/content/Intent:putExtra	(Ljava/lang/String;Ljava/lang/String;)Landroid/content/Intent;
    //   639: pop
    //   640: aload 7
    //   642: ifnull +145 -> 787
    //   645: ldc 92
    //   647: ldc -61
    //   649: bipush 38
    //   651: sipush 172
    //   654: iconst_1
    //   655: invokestatic 187	xxxxxx/uxxxxx:bbbb0062b0062b0062b0062	(Ljava/lang/String;CCC)Ljava/lang/String;
    //   658: iconst_4
    //   659: anewarray 102	java/lang/Class
    //   662: dup
    //   663: iconst_0
    //   664: ldc 104
    //   666: aastore
    //   667: dup
    //   668: iconst_1
    //   669: getstatic 110	java/lang/Character:TYPE	Ljava/lang/Class;
    //   672: aastore
    //   673: dup
    //   674: iconst_2
    //   675: getstatic 110	java/lang/Character:TYPE	Ljava/lang/Class;
    //   678: aastore
    //   679: dup
    //   680: iconst_3
    //   681: getstatic 110	java/lang/Character:TYPE	Ljava/lang/Class;
    //   684: aastore
    //   685: invokevirtual 114	java/lang/Class:getMethod	(Ljava/lang/String;[Ljava/lang/Class;)Ljava/lang/reflect/Method;
    //   688: astore_1
    //   689: aload_1
    //   690: aconst_null
    //   691: iconst_4
    //   692: anewarray 116	java/lang/Object
    //   695: dup
    //   696: iconst_0
    //   697: ldc -59
    //   699: aastore
    //   700: dup
    //   701: iconst_1
    //   702: bipush 83
    //   704: invokestatic 122	java/lang/Character:valueOf	(C)Ljava/lang/Character;
    //   707: aastore
    //   708: dup
    //   709: iconst_2
    //   710: sipush 251
    //   713: invokestatic 122	java/lang/Character:valueOf	(C)Ljava/lang/Character;
    //   716: aastore
    //   717: dup
    //   718: iconst_3
    //   719: iconst_0
    //   720: invokestatic 122	java/lang/Character:valueOf	(C)Ljava/lang/Character;
    //   723: aastore
    //   724: invokevirtual 128	java/lang/reflect/Method:invoke	(Ljava/lang/Object;[Ljava/lang/Object;)Ljava/lang/Object;
    //   727: astore_1
    //   728: aload_1
    //   729: checkcast 104	java/lang/String
    //   732: astore_1
    //   733: getstatic 72	com/db/pwcc/dbmobile/transfer/standingorder/confirm/StandingOrderConfirmationActivity:b006Dmm006Dm006Dmm006D	I
    //   736: istore 9
    //   738: iload 9
    //   740: getstatic 74	com/db/pwcc/dbmobile/transfer/standingorder/confirm/StandingOrderConfirmationActivity:b006D006D006D006Dm006Dmm006D	I
    //   743: iload 9
    //   745: iadd
    //   746: imul
    //   747: getstatic 76	com/db/pwcc/dbmobile/transfer/standingorder/confirm/StandingOrderConfirmationActivity:bmm006D006Dm006Dmm006D	I
    //   750: irem
    //   751: tableswitch	default:+17->768, 0:+28->779
    //   768: bipush 12
    //   770: putstatic 72	com/db/pwcc/dbmobile/transfer/standingorder/confirm/StandingOrderConfirmationActivity:b006Dmm006Dm006Dmm006D	I
    //   773: invokestatic 90	com/db/pwcc/dbmobile/transfer/standingorder/confirm/StandingOrderConfirmationActivity:b006Dm006D006Dm006Dmm006D	()I
    //   776: putstatic 80	com/db/pwcc/dbmobile/transfer/standingorder/confirm/StandingOrderConfirmationActivity:bm006Dm006Dm006Dmm006D	I
    //   779: aload_0
    //   780: aload_1
    //   781: aload 7
    //   783: invokevirtual 170	android/content/Intent:putExtra	(Ljava/lang/String;Landroid/os/Parcelable;)Landroid/content/Intent;
    //   786: pop
    //   787: ldc 92
    //   789: ldc -57
    //   791: sipush 215
    //   794: iconst_1
    //   795: invokestatic 100	xxxxxx/uxxxxx:bb00620062bb0062b0062b0062	(Ljava/lang/String;CC)Ljava/lang/String;
    //   798: iconst_3
    //   799: anewarray 102	java/lang/Class
    //   802: dup
    //   803: iconst_0
    //   804: ldc 104
    //   806: aastore
    //   807: dup
    //   808: iconst_1
    //   809: getstatic 110	java/lang/Character:TYPE	Ljava/lang/Class;
    //   812: aastore
    //   813: dup
    //   814: iconst_2
    //   815: getstatic 110	java/lang/Character:TYPE	Ljava/lang/Class;
    //   818: aastore
    //   819: invokevirtual 114	java/lang/Class:getMethod	(Ljava/lang/String;[Ljava/lang/Class;)Ljava/lang/reflect/Method;
    //   822: astore_1
    //   823: aload_1
    //   824: aconst_null
    //   825: iconst_3
    //   826: anewarray 116	java/lang/Object
    //   829: dup
    //   830: iconst_0
    //   831: ldc -55
    //   833: aastore
    //   834: dup
    //   835: iconst_1
    //   836: sipush 166
    //   839: invokestatic 122	java/lang/Character:valueOf	(C)Ljava/lang/Character;
    //   842: aastore
    //   843: dup
    //   844: iconst_2
    //   845: iconst_2
    //   846: invokestatic 122	java/lang/Character:valueOf	(C)Ljava/lang/Character;
    //   849: aastore
    //   850: invokevirtual 128	java/lang/reflect/Method:invoke	(Ljava/lang/Object;[Ljava/lang/Object;)Ljava/lang/Object;
    //   853: astore_1
    //   854: aload_0
    //   855: aload_1
    //   856: checkcast 104	java/lang/String
    //   859: aload 8
    //   861: invokevirtual 177	android/content/Intent:putExtra	(Ljava/lang/String;Ljava/lang/String;)Landroid/content/Intent;
    //   864: pop
    //   865: aload_0
    //   866: areturn
    //   867: astore_0
    //   868: aload_0
    //   869: invokevirtual 136	java/lang/reflect/InvocationTargetException:getCause	()Ljava/lang/Throwable;
    //   872: athrow
    //   873: astore_0
    //   874: aload_0
    //   875: invokevirtual 136	java/lang/reflect/InvocationTargetException:getCause	()Ljava/lang/Throwable;
    //   878: athrow
    //   879: astore_0
    //   880: aload_0
    //   881: invokevirtual 136	java/lang/reflect/InvocationTargetException:getCause	()Ljava/lang/Throwable;
    //   884: athrow
    //   885: astore_0
    //   886: aload_0
    //   887: invokevirtual 136	java/lang/reflect/InvocationTargetException:getCause	()Ljava/lang/Throwable;
    //   890: athrow
    //   891: astore_0
    //   892: aload_0
    //   893: invokevirtual 136	java/lang/reflect/InvocationTargetException:getCause	()Ljava/lang/Throwable;
    //   896: athrow
    //   897: astore_0
    //   898: aload_0
    //   899: invokevirtual 136	java/lang/reflect/InvocationTargetException:getCause	()Ljava/lang/Throwable;
    //   902: athrow
    //   903: astore_0
    //   904: aload_0
    //   905: invokevirtual 136	java/lang/reflect/InvocationTargetException:getCause	()Ljava/lang/Throwable;
    //   908: athrow
    //   909: astore_0
    //   910: aload_0
    //   911: invokevirtual 136	java/lang/reflect/InvocationTargetException:getCause	()Ljava/lang/Throwable;
    //   914: athrow
    // Local variable table:
    //   start	length	slot	name	signature
    //   0	915	0	paramContext	Context
    //   0	915	1	paramStandingOrderRequestResponse	StandingOrderRequestResponse
    //   0	915	2	paramChallengeResponse	ChallengeResponse
    //   0	915	3	paramAuthorization	Authorization
    //   0	915	4	paramAuthorizationStatus	AuthorizationStatus
    //   0	915	5	paramString1	String
    //   0	915	6	paramString2	String
    //   0	915	7	paramStandingOrderTemplate	StandingOrderTemplate
    //   0	915	8	paramString3	String
    //   94	653	9	i	int
    //   45	37	10	localObject	Object
    // Exception table:
    //   from	to	target	type
    //   47	80	867	java/lang/reflect/InvocationTargetException
    //   250	280	873	java/lang/reflect/InvocationTargetException
    //   823	854	879	java/lang/reflect/InvocationTargetException
    //   405	436	885	java/lang/reflect/InvocationTargetException
    //   589	629	891	java/lang/reflect/InvocationTargetException
    //   689	728	897	java/lang/reflect/InvocationTargetException
    //   326	357	903	java/lang/reflect/InvocationTargetException
    //   174	205	909	java/lang/reflect/InvocationTargetException
  }
  
  private void navigateToActivity(Class<?> paramClass)
  {
    if ((b006Dmm006Dm006Dmm006D + b006D006D006D006Dm006Dmm006D) * b006Dmm006Dm006Dmm006D % bmm006D006Dm006Dmm006D != bm006Dm006Dm006Dmm006D)
    {
      i = b006Dm006D006Dm006Dmm006D();
      int j = b006D006D006D006Dm006Dmm006D;
      int k = b006Dm006D006Dm006Dmm006D();
      int m = b006Dmm006Dm006Dmm006D;
      switch (m * (b006D006D006D006Dm006Dmm006D + m) % bmm006D006Dm006Dmm006D)
      {
      default: 
        b006Dmm006Dm006Dmm006D = b006Dm006D006Dm006Dmm006D();
        bm006Dm006Dm006Dmm006D = 35;
      }
      if ((i + j) * k % bmm006D006Dm006Dmm006D != bm006Dm006Dm006Dmm006D)
      {
        b006Dmm006Dm006Dmm006D = b006Dm006D006Dm006Dmm006D();
        bm006Dm006Dm006Dmm006D = b006Dm006D006Dm006Dmm006D();
      }
      b006Dmm006Dm006Dmm006D = b006Dm006D006Dm006Dmm006D();
      bm006Dm006Dm006Dmm006D = b006Dm006D006Dm006Dmm006D();
    }
    paramClass = new Intent(this, paramClass);
    paramClass.addFlags(872415232);
    int i = b006Dmm006Dm006Dmm006D;
    switch (i * (b006D006Dm006Dm006Dmm006D() + i) % bmm006D006Dm006Dmm006D)
    {
    default: 
      b006Dmm006Dm006Dmm006D = 24;
      bm006Dm006Dm006Dmm006D = b006Dm006D006Dm006Dmm006D();
    }
    startActivity(paramClass);
    finish();
  }
  
  /* Error */
  private Date parseTemplateDateString(String paramString)
  {
    // Byte code:
    //   0: ldc 92
    //   2: ldc -33
    //   4: sipush 171
    //   7: iconst_0
    //   8: invokestatic 100	xxxxxx/uxxxxx:bb00620062bb0062b0062b0062	(Ljava/lang/String;CC)Ljava/lang/String;
    //   11: iconst_3
    //   12: anewarray 102	java/lang/Class
    //   15: dup
    //   16: iconst_0
    //   17: ldc 104
    //   19: aastore
    //   20: dup
    //   21: iconst_1
    //   22: getstatic 110	java/lang/Character:TYPE	Ljava/lang/Class;
    //   25: aastore
    //   26: dup
    //   27: iconst_2
    //   28: getstatic 110	java/lang/Character:TYPE	Ljava/lang/Class;
    //   31: aastore
    //   32: invokevirtual 114	java/lang/Class:getMethod	(Ljava/lang/String;[Ljava/lang/Class;)Ljava/lang/reflect/Method;
    //   35: astore_3
    //   36: aload_3
    //   37: aconst_null
    //   38: iconst_3
    //   39: anewarray 116	java/lang/Object
    //   42: dup
    //   43: iconst_0
    //   44: ldc -31
    //   46: aastore
    //   47: dup
    //   48: iconst_1
    //   49: bipush 115
    //   51: invokestatic 122	java/lang/Character:valueOf	(C)Ljava/lang/Character;
    //   54: aastore
    //   55: dup
    //   56: iconst_2
    //   57: iconst_2
    //   58: invokestatic 122	java/lang/Character:valueOf	(C)Ljava/lang/Character;
    //   61: aastore
    //   62: invokevirtual 128	java/lang/reflect/Method:invoke	(Ljava/lang/Object;[Ljava/lang/Object;)Ljava/lang/Object;
    //   65: astore_3
    //   66: new 227	java/text/SimpleDateFormat
    //   69: dup
    //   70: aload_3
    //   71: checkcast 104	java/lang/String
    //   74: invokestatic 233	java/util/Locale:getDefault	()Ljava/util/Locale;
    //   77: invokespecial 236	java/text/SimpleDateFormat:<init>	(Ljava/lang/String;Ljava/util/Locale;)V
    //   80: astore_3
    //   81: aload_3
    //   82: aload_1
    //   83: invokevirtual 239	java/text/SimpleDateFormat:parse	(Ljava/lang/String;)Ljava/util/Date;
    //   86: astore_1
    //   87: getstatic 72	com/db/pwcc/dbmobile/transfer/standingorder/confirm/StandingOrderConfirmationActivity:b006Dmm006Dm006Dmm006D	I
    //   90: istore_2
    //   91: getstatic 72	com/db/pwcc/dbmobile/transfer/standingorder/confirm/StandingOrderConfirmationActivity:b006Dmm006Dm006Dmm006D	I
    //   94: getstatic 74	com/db/pwcc/dbmobile/transfer/standingorder/confirm/StandingOrderConfirmationActivity:b006D006D006D006Dm006Dmm006D	I
    //   97: iadd
    //   98: getstatic 72	com/db/pwcc/dbmobile/transfer/standingorder/confirm/StandingOrderConfirmationActivity:b006Dmm006Dm006Dmm006D	I
    //   101: imul
    //   102: getstatic 76	com/db/pwcc/dbmobile/transfer/standingorder/confirm/StandingOrderConfirmationActivity:bmm006D006Dm006Dmm006D	I
    //   105: irem
    //   106: invokestatic 78	com/db/pwcc/dbmobile/transfer/standingorder/confirm/StandingOrderConfirmationActivity:bm006D006D006Dm006Dmm006D	()I
    //   109: if_icmpeq +13 -> 122
    //   112: bipush 88
    //   114: putstatic 72	com/db/pwcc/dbmobile/transfer/standingorder/confirm/StandingOrderConfirmationActivity:b006Dmm006Dm006Dmm006D	I
    //   117: bipush 98
    //   119: putstatic 80	com/db/pwcc/dbmobile/transfer/standingorder/confirm/StandingOrderConfirmationActivity:bm006Dm006Dm006Dmm006D	I
    //   122: iload_2
    //   123: getstatic 74	com/db/pwcc/dbmobile/transfer/standingorder/confirm/StandingOrderConfirmationActivity:b006D006D006D006Dm006Dmm006D	I
    //   126: iload_2
    //   127: iadd
    //   128: imul
    //   129: getstatic 76	com/db/pwcc/dbmobile/transfer/standingorder/confirm/StandingOrderConfirmationActivity:bmm006D006Dm006Dmm006D	I
    //   132: irem
    //   133: tableswitch	default:+19->152, 0:+106->239
    //   152: invokestatic 90	com/db/pwcc/dbmobile/transfer/standingorder/confirm/StandingOrderConfirmationActivity:b006Dm006D006Dm006Dmm006D	()I
    //   155: putstatic 72	com/db/pwcc/dbmobile/transfer/standingorder/confirm/StandingOrderConfirmationActivity:b006Dmm006Dm006Dmm006D	I
    //   158: getstatic 72	com/db/pwcc/dbmobile/transfer/standingorder/confirm/StandingOrderConfirmationActivity:b006Dmm006Dm006Dmm006D	I
    //   161: invokestatic 88	com/db/pwcc/dbmobile/transfer/standingorder/confirm/StandingOrderConfirmationActivity:b006D006Dm006Dm006Dmm006D	()I
    //   164: iadd
    //   165: getstatic 72	com/db/pwcc/dbmobile/transfer/standingorder/confirm/StandingOrderConfirmationActivity:b006Dmm006Dm006Dmm006D	I
    //   168: imul
    //   169: getstatic 76	com/db/pwcc/dbmobile/transfer/standingorder/confirm/StandingOrderConfirmationActivity:bmm006D006Dm006Dmm006D	I
    //   172: irem
    //   173: getstatic 80	com/db/pwcc/dbmobile/transfer/standingorder/confirm/StandingOrderConfirmationActivity:bm006Dm006Dm006Dmm006D	I
    //   176: if_icmpeq +15 -> 191
    //   179: invokestatic 90	com/db/pwcc/dbmobile/transfer/standingorder/confirm/StandingOrderConfirmationActivity:b006Dm006D006Dm006Dmm006D	()I
    //   182: putstatic 72	com/db/pwcc/dbmobile/transfer/standingorder/confirm/StandingOrderConfirmationActivity:b006Dmm006Dm006Dmm006D	I
    //   185: invokestatic 90	com/db/pwcc/dbmobile/transfer/standingorder/confirm/StandingOrderConfirmationActivity:b006Dm006D006Dm006Dmm006D	()I
    //   188: putstatic 80	com/db/pwcc/dbmobile/transfer/standingorder/confirm/StandingOrderConfirmationActivity:bm006Dm006Dm006Dmm006D	I
    //   191: bipush 46
    //   193: putstatic 80	com/db/pwcc/dbmobile/transfer/standingorder/confirm/StandingOrderConfirmationActivity:bm006Dm006Dm006Dmm006D	I
    //   196: getstatic 72	com/db/pwcc/dbmobile/transfer/standingorder/confirm/StandingOrderConfirmationActivity:b006Dmm006Dm006Dmm006D	I
    //   199: istore_2
    //   200: iload_2
    //   201: getstatic 74	com/db/pwcc/dbmobile/transfer/standingorder/confirm/StandingOrderConfirmationActivity:b006D006D006D006Dm006Dmm006D	I
    //   204: iload_2
    //   205: iadd
    //   206: imul
    //   207: getstatic 76	com/db/pwcc/dbmobile/transfer/standingorder/confirm/StandingOrderConfirmationActivity:bmm006D006Dm006Dmm006D	I
    //   210: irem
    //   211: tableswitch	default:+17->228, 0:+28->239
    //   228: bipush 18
    //   230: putstatic 72	com/db/pwcc/dbmobile/transfer/standingorder/confirm/StandingOrderConfirmationActivity:b006Dmm006Dm006Dmm006D	I
    //   233: invokestatic 90	com/db/pwcc/dbmobile/transfer/standingorder/confirm/StandingOrderConfirmationActivity:b006Dm006D006Dm006Dmm006D	()I
    //   236: putstatic 80	com/db/pwcc/dbmobile/transfer/standingorder/confirm/StandingOrderConfirmationActivity:bm006Dm006Dm006Dmm006D	I
    //   239: aload_1
    //   240: areturn
    //   241: astore_1
    //   242: aconst_null
    //   243: astore_1
    //   244: goto -157 -> 87
    //   247: astore_1
    //   248: aload_1
    //   249: invokevirtual 136	java/lang/reflect/InvocationTargetException:getCause	()Ljava/lang/Throwable;
    //   252: athrow
    // Local variable table:
    //   start	length	slot	name	signature
    //   0	253	0	this	StandingOrderConfirmationActivity
    //   0	253	1	paramString	String
    //   90	117	2	i	int
    //   35	47	3	localObject	Object
    // Exception table:
    //   from	to	target	type
    //   81	87	241	java/text/ParseException
    //   36	66	247	java/lang/reflect/InvocationTargetException
  }
  
  /* Error */
  private void setFormattedFrequencyText(TextView paramTextView, int paramInt, String paramString)
  {
    // Byte code:
    //   0: aload_3
    //   1: invokevirtual 244	java/lang/String:hashCode	()I
    //   4: lookupswitch	default:+84->88, -1738378111:+730->734, -445144898:+1185->1189, 64808441:+229->233, 398230326:+330->334, 1297843654:+936->940, 1720567065:+141->145, 1935336927:+1041->1045, 1954618349:+618->622, 2003304760:+825->829
    //   88: iconst_m1
    //   89: istore 4
    //   91: iload 4
    //   93: tableswitch	default:+51->144, 0:+839->932, 1:+377->470, 2:+1088->1181, 3:+938->1031, 4:+938->1031, 5:+435->528, 6:+1208->1301, 7:+1216->1309, 8:+1236->1329
    //   144: return
    //   145: ldc 92
    //   147: ldc -10
    //   149: bipush 26
    //   151: iconst_5
    //   152: invokestatic 100	xxxxxx/uxxxxx:bb00620062bb0062b0062b0062	(Ljava/lang/String;CC)Ljava/lang/String;
    //   155: iconst_3
    //   156: anewarray 102	java/lang/Class
    //   159: dup
    //   160: iconst_0
    //   161: ldc 104
    //   163: aastore
    //   164: dup
    //   165: iconst_1
    //   166: getstatic 110	java/lang/Character:TYPE	Ljava/lang/Class;
    //   169: aastore
    //   170: dup
    //   171: iconst_2
    //   172: getstatic 110	java/lang/Character:TYPE	Ljava/lang/Class;
    //   175: aastore
    //   176: invokevirtual 114	java/lang/Class:getMethod	(Ljava/lang/String;[Ljava/lang/Class;)Ljava/lang/reflect/Method;
    //   179: astore 5
    //   181: aload 5
    //   183: aconst_null
    //   184: iconst_3
    //   185: anewarray 116	java/lang/Object
    //   188: dup
    //   189: iconst_0
    //   190: ldc -8
    //   192: aastore
    //   193: dup
    //   194: iconst_1
    //   195: sipush 205
    //   198: invokestatic 122	java/lang/Character:valueOf	(C)Ljava/lang/Character;
    //   201: aastore
    //   202: dup
    //   203: iconst_2
    //   204: iconst_3
    //   205: invokestatic 122	java/lang/Character:valueOf	(C)Ljava/lang/Character;
    //   208: aastore
    //   209: invokevirtual 128	java/lang/reflect/Method:invoke	(Ljava/lang/Object;[Ljava/lang/Object;)Ljava/lang/Object;
    //   212: astore 5
    //   214: aload_3
    //   215: aload 5
    //   217: checkcast 104	java/lang/String
    //   220: invokevirtual 132	java/lang/String:equals	(Ljava/lang/Object;)Z
    //   223: ifeq -135 -> 88
    //   226: bipush 6
    //   228: istore 4
    //   230: goto -139 -> 91
    //   233: ldc 92
    //   235: ldc -6
    //   237: bipush 23
    //   239: iconst_4
    //   240: invokestatic 100	xxxxxx/uxxxxx:bb00620062bb0062b0062b0062	(Ljava/lang/String;CC)Ljava/lang/String;
    //   243: iconst_4
    //   244: anewarray 102	java/lang/Class
    //   247: dup
    //   248: iconst_0
    //   249: ldc 104
    //   251: aastore
    //   252: dup
    //   253: iconst_1
    //   254: getstatic 110	java/lang/Character:TYPE	Ljava/lang/Class;
    //   257: aastore
    //   258: dup
    //   259: iconst_2
    //   260: getstatic 110	java/lang/Character:TYPE	Ljava/lang/Class;
    //   263: aastore
    //   264: dup
    //   265: iconst_3
    //   266: getstatic 110	java/lang/Character:TYPE	Ljava/lang/Class;
    //   269: aastore
    //   270: invokevirtual 114	java/lang/Class:getMethod	(Ljava/lang/String;[Ljava/lang/Class;)Ljava/lang/reflect/Method;
    //   273: astore 5
    //   275: aload 5
    //   277: aconst_null
    //   278: iconst_4
    //   279: anewarray 116	java/lang/Object
    //   282: dup
    //   283: iconst_0
    //   284: ldc -4
    //   286: aastore
    //   287: dup
    //   288: iconst_1
    //   289: bipush 114
    //   291: invokestatic 122	java/lang/Character:valueOf	(C)Ljava/lang/Character;
    //   294: aastore
    //   295: dup
    //   296: iconst_2
    //   297: sipush 200
    //   300: invokestatic 122	java/lang/Character:valueOf	(C)Ljava/lang/Character;
    //   303: aastore
    //   304: dup
    //   305: iconst_3
    //   306: iconst_0
    //   307: invokestatic 122	java/lang/Character:valueOf	(C)Ljava/lang/Character;
    //   310: aastore
    //   311: invokevirtual 128	java/lang/reflect/Method:invoke	(Ljava/lang/Object;[Ljava/lang/Object;)Ljava/lang/Object;
    //   314: astore 5
    //   316: aload_3
    //   317: aload 5
    //   319: checkcast 104	java/lang/String
    //   322: invokevirtual 132	java/lang/String:equals	(Ljava/lang/Object;)Z
    //   325: ifeq -237 -> 88
    //   328: iconst_0
    //   329: istore 4
    //   331: goto -240 -> 91
    //   334: getstatic 72	com/db/pwcc/dbmobile/transfer/standingorder/confirm/StandingOrderConfirmationActivity:b006Dmm006Dm006Dmm006D	I
    //   337: istore 4
    //   339: iload 4
    //   341: getstatic 74	com/db/pwcc/dbmobile/transfer/standingorder/confirm/StandingOrderConfirmationActivity:b006D006D006D006Dm006Dmm006D	I
    //   344: iload 4
    //   346: iadd
    //   347: imul
    //   348: getstatic 76	com/db/pwcc/dbmobile/transfer/standingorder/confirm/StandingOrderConfirmationActivity:bmm006D006Dm006Dmm006D	I
    //   351: irem
    //   352: tableswitch	default:+20->372, 0:+31->383
    //   372: bipush 82
    //   374: putstatic 72	com/db/pwcc/dbmobile/transfer/standingorder/confirm/StandingOrderConfirmationActivity:b006Dmm006Dm006Dmm006D	I
    //   377: invokestatic 90	com/db/pwcc/dbmobile/transfer/standingorder/confirm/StandingOrderConfirmationActivity:b006Dm006D006Dm006Dmm006D	()I
    //   380: putstatic 80	com/db/pwcc/dbmobile/transfer/standingorder/confirm/StandingOrderConfirmationActivity:bm006Dm006Dm006Dmm006D	I
    //   383: ldc 92
    //   385: ldc -2
    //   387: bipush 50
    //   389: iconst_3
    //   390: invokestatic 100	xxxxxx/uxxxxx:bb00620062bb0062b0062b0062	(Ljava/lang/String;CC)Ljava/lang/String;
    //   393: iconst_3
    //   394: anewarray 102	java/lang/Class
    //   397: dup
    //   398: iconst_0
    //   399: ldc 104
    //   401: aastore
    //   402: dup
    //   403: iconst_1
    //   404: getstatic 110	java/lang/Character:TYPE	Ljava/lang/Class;
    //   407: aastore
    //   408: dup
    //   409: iconst_2
    //   410: getstatic 110	java/lang/Character:TYPE	Ljava/lang/Class;
    //   413: aastore
    //   414: invokevirtual 114	java/lang/Class:getMethod	(Ljava/lang/String;[Ljava/lang/Class;)Ljava/lang/reflect/Method;
    //   417: astore 5
    //   419: aload 5
    //   421: aconst_null
    //   422: iconst_3
    //   423: anewarray 116	java/lang/Object
    //   426: dup
    //   427: iconst_0
    //   428: ldc_w 256
    //   431: aastore
    //   432: dup
    //   433: iconst_1
    //   434: bipush 88
    //   436: invokestatic 122	java/lang/Character:valueOf	(C)Ljava/lang/Character;
    //   439: aastore
    //   440: dup
    //   441: iconst_2
    //   442: iconst_1
    //   443: invokestatic 122	java/lang/Character:valueOf	(C)Ljava/lang/Character;
    //   446: aastore
    //   447: invokevirtual 128	java/lang/reflect/Method:invoke	(Ljava/lang/Object;[Ljava/lang/Object;)Ljava/lang/Object;
    //   450: astore 5
    //   452: aload_3
    //   453: aload 5
    //   455: checkcast 104	java/lang/String
    //   458: invokevirtual 132	java/lang/String:equals	(Ljava/lang/Object;)Z
    //   461: ifeq -373 -> 88
    //   464: iconst_3
    //   465: istore 4
    //   467: goto -376 -> 91
    //   470: aload_1
    //   471: aload_0
    //   472: getstatic 261	com/db/pwcc/dbmobile/transfer/R$string:standing_order_frequency_weekly	I
    //   475: invokevirtual 265	com/db/pwcc/dbmobile/transfer/standingorder/confirm/StandingOrderConfirmationActivity:getString	(I)Ljava/lang/String;
    //   478: invokevirtual 271	android/widget/TextView:setText	(Ljava/lang/CharSequence;)V
    //   481: getstatic 72	com/db/pwcc/dbmobile/transfer/standingorder/confirm/StandingOrderConfirmationActivity:b006Dmm006Dm006Dmm006D	I
    //   484: istore_2
    //   485: iload_2
    //   486: getstatic 74	com/db/pwcc/dbmobile/transfer/standingorder/confirm/StandingOrderConfirmationActivity:b006D006D006D006Dm006Dmm006D	I
    //   489: iload_2
    //   490: iadd
    //   491: imul
    //   492: getstatic 76	com/db/pwcc/dbmobile/transfer/standingorder/confirm/StandingOrderConfirmationActivity:bmm006D006Dm006Dmm006D	I
    //   495: irem
    //   496: tableswitch	default:+20->516, 0:+-352->144
    //   516: invokestatic 90	com/db/pwcc/dbmobile/transfer/standingorder/confirm/StandingOrderConfirmationActivity:b006Dm006D006Dm006Dmm006D	()I
    //   519: putstatic 72	com/db/pwcc/dbmobile/transfer/standingorder/confirm/StandingOrderConfirmationActivity:b006Dmm006Dm006Dmm006D	I
    //   522: bipush 58
    //   524: putstatic 80	com/db/pwcc/dbmobile/transfer/standingorder/confirm/StandingOrderConfirmationActivity:bm006Dm006Dm006Dmm006D	I
    //   527: return
    //   528: getstatic 274	com/db/pwcc/dbmobile/transfer/R$string:standing_order_frequency_bimonthly_formatted	I
    //   531: istore 4
    //   533: new 276	java/lang/StringBuilder
    //   536: dup
    //   537: invokespecial 277	java/lang/StringBuilder:<init>	()V
    //   540: aload_0
    //   541: iload 4
    //   543: invokevirtual 265	com/db/pwcc/dbmobile/transfer/standingorder/confirm/StandingOrderConfirmationActivity:getString	(I)Ljava/lang/String;
    //   546: iconst_1
    //   547: anewarray 116	java/lang/Object
    //   550: dup
    //   551: iconst_0
    //   552: iload_2
    //   553: invokestatic 282	java/lang/Integer:valueOf	(I)Ljava/lang/Integer;
    //   556: aastore
    //   557: invokestatic 286	java/lang/String:format	(Ljava/lang/String;[Ljava/lang/Object;)Ljava/lang/String;
    //   560: invokevirtual 290	java/lang/StringBuilder:append	(Ljava/lang/String;)Ljava/lang/StringBuilder;
    //   563: astore_3
    //   564: invokestatic 233	java/util/Locale:getDefault	()Ljava/util/Locale;
    //   567: iload_2
    //   568: invokestatic 296	uuuuuu/pqpppq:bkk006Bk006B006Bkkkk	(Ljava/util/Locale;I)Ljava/lang/String;
    //   571: astore 5
    //   573: getstatic 72	com/db/pwcc/dbmobile/transfer/standingorder/confirm/StandingOrderConfirmationActivity:b006Dmm006Dm006Dmm006D	I
    //   576: getstatic 74	com/db/pwcc/dbmobile/transfer/standingorder/confirm/StandingOrderConfirmationActivity:b006D006D006D006Dm006Dmm006D	I
    //   579: iadd
    //   580: getstatic 72	com/db/pwcc/dbmobile/transfer/standingorder/confirm/StandingOrderConfirmationActivity:b006Dmm006Dm006Dmm006D	I
    //   583: imul
    //   584: getstatic 76	com/db/pwcc/dbmobile/transfer/standingorder/confirm/StandingOrderConfirmationActivity:bmm006D006Dm006Dmm006D	I
    //   587: irem
    //   588: invokestatic 78	com/db/pwcc/dbmobile/transfer/standingorder/confirm/StandingOrderConfirmationActivity:bm006D006D006Dm006Dmm006D	()I
    //   591: if_icmpeq +14 -> 605
    //   594: bipush 21
    //   596: putstatic 72	com/db/pwcc/dbmobile/transfer/standingorder/confirm/StandingOrderConfirmationActivity:b006Dmm006Dm006Dmm006D	I
    //   599: invokestatic 90	com/db/pwcc/dbmobile/transfer/standingorder/confirm/StandingOrderConfirmationActivity:b006Dm006D006Dm006Dmm006D	()I
    //   602: putstatic 80	com/db/pwcc/dbmobile/transfer/standingorder/confirm/StandingOrderConfirmationActivity:bm006Dm006Dm006Dmm006D	I
    //   605: aload_1
    //   606: aload_3
    //   607: aload 5
    //   609: invokevirtual 290	java/lang/StringBuilder:append	(Ljava/lang/String;)Ljava/lang/StringBuilder;
    //   612: invokevirtual 299	java/lang/StringBuilder:toString	()Ljava/lang/String;
    //   615: invokestatic 305	android/text/Html:fromHtml	(Ljava/lang/String;)Landroid/text/Spanned;
    //   618: invokevirtual 271	android/widget/TextView:setText	(Ljava/lang/CharSequence;)V
    //   621: return
    //   622: ldc 92
    //   624: ldc_w 307
    //   627: sipush 192
    //   630: sipush 141
    //   633: iconst_2
    //   634: invokestatic 187	xxxxxx/uxxxxx:bbbb0062b0062b0062b0062	(Ljava/lang/String;CCC)Ljava/lang/String;
    //   637: iconst_4
    //   638: anewarray 102	java/lang/Class
    //   641: dup
    //   642: iconst_0
    //   643: ldc 104
    //   645: aastore
    //   646: dup
    //   647: iconst_1
    //   648: getstatic 110	java/lang/Character:TYPE	Ljava/lang/Class;
    //   651: aastore
    //   652: dup
    //   653: iconst_2
    //   654: getstatic 110	java/lang/Character:TYPE	Ljava/lang/Class;
    //   657: aastore
    //   658: dup
    //   659: iconst_3
    //   660: getstatic 110	java/lang/Character:TYPE	Ljava/lang/Class;
    //   663: aastore
    //   664: invokevirtual 114	java/lang/Class:getMethod	(Ljava/lang/String;[Ljava/lang/Class;)Ljava/lang/reflect/Method;
    //   667: astore 5
    //   669: aload 5
    //   671: aconst_null
    //   672: iconst_4
    //   673: anewarray 116	java/lang/Object
    //   676: dup
    //   677: iconst_0
    //   678: ldc_w 309
    //   681: aastore
    //   682: dup
    //   683: iconst_1
    //   684: bipush 112
    //   686: invokestatic 122	java/lang/Character:valueOf	(C)Ljava/lang/Character;
    //   689: aastore
    //   690: dup
    //   691: iconst_2
    //   692: bipush 82
    //   694: invokestatic 122	java/lang/Character:valueOf	(C)Ljava/lang/Character;
    //   697: aastore
    //   698: dup
    //   699: iconst_3
    //   700: iconst_2
    //   701: invokestatic 122	java/lang/Character:valueOf	(C)Ljava/lang/Character;
    //   704: aastore
    //   705: invokevirtual 128	java/lang/reflect/Method:invoke	(Ljava/lang/Object;[Ljava/lang/Object;)Ljava/lang/Object;
    //   708: astore 5
    //   710: aload_3
    //   711: aload 5
    //   713: checkcast 104	java/lang/String
    //   716: invokevirtual 132	java/lang/String:equals	(Ljava/lang/Object;)Z
    //   719: ifeq -631 -> 88
    //   722: iconst_2
    //   723: istore 4
    //   725: goto -634 -> 91
    //   728: astore_1
    //   729: aload_1
    //   730: invokevirtual 136	java/lang/reflect/InvocationTargetException:getCause	()Ljava/lang/Throwable;
    //   733: athrow
    //   734: ldc 92
    //   736: ldc_w 311
    //   739: sipush 208
    //   742: iconst_0
    //   743: invokestatic 100	xxxxxx/uxxxxx:bb00620062bb0062b0062b0062	(Ljava/lang/String;CC)Ljava/lang/String;
    //   746: iconst_3
    //   747: anewarray 102	java/lang/Class
    //   750: dup
    //   751: iconst_0
    //   752: ldc 104
    //   754: aastore
    //   755: dup
    //   756: iconst_1
    //   757: getstatic 110	java/lang/Character:TYPE	Ljava/lang/Class;
    //   760: aastore
    //   761: dup
    //   762: iconst_2
    //   763: getstatic 110	java/lang/Character:TYPE	Ljava/lang/Class;
    //   766: aastore
    //   767: invokevirtual 114	java/lang/Class:getMethod	(Ljava/lang/String;[Ljava/lang/Class;)Ljava/lang/reflect/Method;
    //   770: astore 5
    //   772: aload 5
    //   774: aconst_null
    //   775: iconst_3
    //   776: anewarray 116	java/lang/Object
    //   779: dup
    //   780: iconst_0
    //   781: ldc_w 313
    //   784: aastore
    //   785: dup
    //   786: iconst_1
    //   787: bipush 38
    //   789: invokestatic 122	java/lang/Character:valueOf	(C)Ljava/lang/Character;
    //   792: aastore
    //   793: dup
    //   794: iconst_2
    //   795: iconst_1
    //   796: invokestatic 122	java/lang/Character:valueOf	(C)Ljava/lang/Character;
    //   799: aastore
    //   800: invokevirtual 128	java/lang/reflect/Method:invoke	(Ljava/lang/Object;[Ljava/lang/Object;)Ljava/lang/Object;
    //   803: astore 5
    //   805: aload_3
    //   806: aload 5
    //   808: checkcast 104	java/lang/String
    //   811: invokevirtual 132	java/lang/String:equals	(Ljava/lang/Object;)Z
    //   814: ifeq -726 -> 88
    //   817: iconst_1
    //   818: istore 4
    //   820: goto -729 -> 91
    //   823: astore_1
    //   824: aload_1
    //   825: invokevirtual 136	java/lang/reflect/InvocationTargetException:getCause	()Ljava/lang/Throwable;
    //   828: athrow
    //   829: ldc 92
    //   831: ldc_w 315
    //   834: bipush 35
    //   836: iconst_4
    //   837: invokestatic 100	xxxxxx/uxxxxx:bb00620062bb0062b0062b0062	(Ljava/lang/String;CC)Ljava/lang/String;
    //   840: iconst_4
    //   841: anewarray 102	java/lang/Class
    //   844: dup
    //   845: iconst_0
    //   846: ldc 104
    //   848: aastore
    //   849: dup
    //   850: iconst_1
    //   851: getstatic 110	java/lang/Character:TYPE	Ljava/lang/Class;
    //   854: aastore
    //   855: dup
    //   856: iconst_2
    //   857: getstatic 110	java/lang/Character:TYPE	Ljava/lang/Class;
    //   860: aastore
    //   861: dup
    //   862: iconst_3
    //   863: getstatic 110	java/lang/Character:TYPE	Ljava/lang/Class;
    //   866: aastore
    //   867: invokevirtual 114	java/lang/Class:getMethod	(Ljava/lang/String;[Ljava/lang/Class;)Ljava/lang/reflect/Method;
    //   870: astore 5
    //   872: aload 5
    //   874: aconst_null
    //   875: iconst_4
    //   876: anewarray 116	java/lang/Object
    //   879: dup
    //   880: iconst_0
    //   881: ldc_w 317
    //   884: aastore
    //   885: dup
    //   886: iconst_1
    //   887: bipush 94
    //   889: invokestatic 122	java/lang/Character:valueOf	(C)Ljava/lang/Character;
    //   892: aastore
    //   893: dup
    //   894: iconst_2
    //   895: bipush 27
    //   897: invokestatic 122	java/lang/Character:valueOf	(C)Ljava/lang/Character;
    //   900: aastore
    //   901: dup
    //   902: iconst_3
    //   903: iconst_2
    //   904: invokestatic 122	java/lang/Character:valueOf	(C)Ljava/lang/Character;
    //   907: aastore
    //   908: invokevirtual 128	java/lang/reflect/Method:invoke	(Ljava/lang/Object;[Ljava/lang/Object;)Ljava/lang/Object;
    //   911: astore 5
    //   913: aload_3
    //   914: aload 5
    //   916: checkcast 104	java/lang/String
    //   919: invokevirtual 132	java/lang/String:equals	(Ljava/lang/Object;)Z
    //   922: ifeq -834 -> 88
    //   925: bipush 7
    //   927: istore 4
    //   929: goto -838 -> 91
    //   932: aload_1
    //   933: getstatic 320	com/db/pwcc/dbmobile/transfer/R$string:standing_order_frequency_daily	I
    //   936: invokevirtual 323	android/widget/TextView:setText	(I)V
    //   939: return
    //   940: ldc 92
    //   942: ldc_w 325
    //   945: bipush 110
    //   947: bipush 22
    //   949: iconst_0
    //   950: invokestatic 187	xxxxxx/uxxxxx:bbbb0062b0062b0062b0062	(Ljava/lang/String;CCC)Ljava/lang/String;
    //   953: iconst_3
    //   954: anewarray 102	java/lang/Class
    //   957: dup
    //   958: iconst_0
    //   959: ldc 104
    //   961: aastore
    //   962: dup
    //   963: iconst_1
    //   964: getstatic 110	java/lang/Character:TYPE	Ljava/lang/Class;
    //   967: aastore
    //   968: dup
    //   969: iconst_2
    //   970: getstatic 110	java/lang/Character:TYPE	Ljava/lang/Class;
    //   973: aastore
    //   974: invokevirtual 114	java/lang/Class:getMethod	(Ljava/lang/String;[Ljava/lang/Class;)Ljava/lang/reflect/Method;
    //   977: astore 5
    //   979: aload 5
    //   981: aconst_null
    //   982: iconst_3
    //   983: anewarray 116	java/lang/Object
    //   986: dup
    //   987: iconst_0
    //   988: ldc_w 327
    //   991: aastore
    //   992: dup
    //   993: iconst_1
    //   994: sipush 172
    //   997: invokestatic 122	java/lang/Character:valueOf	(C)Ljava/lang/Character;
    //   1000: aastore
    //   1001: dup
    //   1002: iconst_2
    //   1003: iconst_3
    //   1004: invokestatic 122	java/lang/Character:valueOf	(C)Ljava/lang/Character;
    //   1007: aastore
    //   1008: invokevirtual 128	java/lang/reflect/Method:invoke	(Ljava/lang/Object;[Ljava/lang/Object;)Ljava/lang/Object;
    //   1011: astore 5
    //   1013: aload_3
    //   1014: aload 5
    //   1016: checkcast 104	java/lang/String
    //   1019: invokevirtual 132	java/lang/String:equals	(Ljava/lang/Object;)Z
    //   1022: ifeq -934 -> 88
    //   1025: iconst_5
    //   1026: istore 4
    //   1028: goto -937 -> 91
    //   1031: getstatic 330	com/db/pwcc/dbmobile/transfer/R$string:standing_order_frequency_monthly_without_jan_jul_formatted	I
    //   1034: istore 4
    //   1036: goto -503 -> 533
    //   1039: astore_1
    //   1040: aload_1
    //   1041: invokevirtual 136	java/lang/reflect/InvocationTargetException:getCause	()Ljava/lang/Throwable;
    //   1044: athrow
    //   1045: getstatic 72	com/db/pwcc/dbmobile/transfer/standingorder/confirm/StandingOrderConfirmationActivity:b006Dmm006Dm006Dmm006D	I
    //   1048: getstatic 74	com/db/pwcc/dbmobile/transfer/standingorder/confirm/StandingOrderConfirmationActivity:b006D006D006D006Dm006Dmm006D	I
    //   1051: iadd
    //   1052: getstatic 72	com/db/pwcc/dbmobile/transfer/standingorder/confirm/StandingOrderConfirmationActivity:b006Dmm006Dm006Dmm006D	I
    //   1055: imul
    //   1056: getstatic 76	com/db/pwcc/dbmobile/transfer/standingorder/confirm/StandingOrderConfirmationActivity:bmm006D006Dm006Dmm006D	I
    //   1059: irem
    //   1060: invokestatic 78	com/db/pwcc/dbmobile/transfer/standingorder/confirm/StandingOrderConfirmationActivity:bm006D006D006Dm006Dmm006D	()I
    //   1063: if_icmpeq +13 -> 1076
    //   1066: bipush 77
    //   1068: putstatic 72	com/db/pwcc/dbmobile/transfer/standingorder/confirm/StandingOrderConfirmationActivity:b006Dmm006Dm006Dmm006D	I
    //   1071: bipush 94
    //   1073: putstatic 80	com/db/pwcc/dbmobile/transfer/standingorder/confirm/StandingOrderConfirmationActivity:bm006Dm006Dm006Dmm006D	I
    //   1076: ldc 92
    //   1078: ldc_w 332
    //   1081: sipush 129
    //   1084: iconst_0
    //   1085: invokestatic 100	xxxxxx/uxxxxx:bb00620062bb0062b0062b0062	(Ljava/lang/String;CC)Ljava/lang/String;
    //   1088: iconst_4
    //   1089: anewarray 102	java/lang/Class
    //   1092: dup
    //   1093: iconst_0
    //   1094: ldc 104
    //   1096: aastore
    //   1097: dup
    //   1098: iconst_1
    //   1099: getstatic 110	java/lang/Character:TYPE	Ljava/lang/Class;
    //   1102: aastore
    //   1103: dup
    //   1104: iconst_2
    //   1105: getstatic 110	java/lang/Character:TYPE	Ljava/lang/Class;
    //   1108: aastore
    //   1109: dup
    //   1110: iconst_3
    //   1111: getstatic 110	java/lang/Character:TYPE	Ljava/lang/Class;
    //   1114: aastore
    //   1115: invokevirtual 114	java/lang/Class:getMethod	(Ljava/lang/String;[Ljava/lang/Class;)Ljava/lang/reflect/Method;
    //   1118: astore 5
    //   1120: aload 5
    //   1122: aconst_null
    //   1123: iconst_4
    //   1124: anewarray 116	java/lang/Object
    //   1127: dup
    //   1128: iconst_0
    //   1129: ldc_w 334
    //   1132: aastore
    //   1133: dup
    //   1134: iconst_1
    //   1135: bipush 27
    //   1137: invokestatic 122	java/lang/Character:valueOf	(C)Ljava/lang/Character;
    //   1140: aastore
    //   1141: dup
    //   1142: iconst_2
    //   1143: sipush 184
    //   1146: invokestatic 122	java/lang/Character:valueOf	(C)Ljava/lang/Character;
    //   1149: aastore
    //   1150: dup
    //   1151: iconst_3
    //   1152: iconst_2
    //   1153: invokestatic 122	java/lang/Character:valueOf	(C)Ljava/lang/Character;
    //   1156: aastore
    //   1157: invokevirtual 128	java/lang/reflect/Method:invoke	(Ljava/lang/Object;[Ljava/lang/Object;)Ljava/lang/Object;
    //   1160: astore 5
    //   1162: aload_3
    //   1163: aload 5
    //   1165: checkcast 104	java/lang/String
    //   1168: invokevirtual 132	java/lang/String:equals	(Ljava/lang/Object;)Z
    //   1171: ifeq -1083 -> 88
    //   1174: bipush 8
    //   1176: istore 4
    //   1178: goto -1087 -> 91
    //   1181: getstatic 337	com/db/pwcc/dbmobile/transfer/R$string:standing_order_frequency_monthly_formatted	I
    //   1184: istore 4
    //   1186: goto -653 -> 533
    //   1189: ldc 92
    //   1191: ldc_w 339
    //   1194: bipush 104
    //   1196: iconst_2
    //   1197: invokestatic 100	xxxxxx/uxxxxx:bb00620062bb0062b0062b0062	(Ljava/lang/String;CC)Ljava/lang/String;
    //   1200: iconst_3
    //   1201: anewarray 102	java/lang/Class
    //   1204: dup
    //   1205: iconst_0
    //   1206: ldc 104
    //   1208: aastore
    //   1209: dup
    //   1210: iconst_1
    //   1211: getstatic 110	java/lang/Character:TYPE	Ljava/lang/Class;
    //   1214: aastore
    //   1215: dup
    //   1216: iconst_2
    //   1217: getstatic 110	java/lang/Character:TYPE	Ljava/lang/Class;
    //   1220: aastore
    //   1221: invokevirtual 114	java/lang/Class:getMethod	(Ljava/lang/String;[Ljava/lang/Class;)Ljava/lang/reflect/Method;
    //   1224: astore 5
    //   1226: aload 5
    //   1228: aconst_null
    //   1229: iconst_3
    //   1230: anewarray 116	java/lang/Object
    //   1233: dup
    //   1234: iconst_0
    //   1235: ldc_w 341
    //   1238: aastore
    //   1239: dup
    //   1240: iconst_1
    //   1241: bipush 85
    //   1243: invokestatic 122	java/lang/Character:valueOf	(C)Ljava/lang/Character;
    //   1246: aastore
    //   1247: dup
    //   1248: iconst_2
    //   1249: iconst_1
    //   1250: invokestatic 122	java/lang/Character:valueOf	(C)Ljava/lang/Character;
    //   1253: aastore
    //   1254: invokevirtual 128	java/lang/reflect/Method:invoke	(Ljava/lang/Object;[Ljava/lang/Object;)Ljava/lang/Object;
    //   1257: astore 5
    //   1259: aload_3
    //   1260: aload 5
    //   1262: checkcast 104	java/lang/String
    //   1265: invokevirtual 132	java/lang/String:equals	(Ljava/lang/Object;)Z
    //   1268: ifeq -1180 -> 88
    //   1271: iconst_4
    //   1272: istore 4
    //   1274: goto -1183 -> 91
    //   1277: astore_1
    //   1278: aload_1
    //   1279: invokevirtual 136	java/lang/reflect/InvocationTargetException:getCause	()Ljava/lang/Throwable;
    //   1282: athrow
    //   1283: astore_1
    //   1284: aload_1
    //   1285: invokevirtual 136	java/lang/reflect/InvocationTargetException:getCause	()Ljava/lang/Throwable;
    //   1288: athrow
    //   1289: astore_1
    //   1290: aload_1
    //   1291: invokevirtual 136	java/lang/reflect/InvocationTargetException:getCause	()Ljava/lang/Throwable;
    //   1294: athrow
    //   1295: astore_1
    //   1296: aload_1
    //   1297: invokevirtual 136	java/lang/reflect/InvocationTargetException:getCause	()Ljava/lang/Throwable;
    //   1300: athrow
    //   1301: getstatic 344	com/db/pwcc/dbmobile/transfer/R$string:standing_order_frequency_quarterly_formatted	I
    //   1304: istore 4
    //   1306: goto -773 -> 533
    //   1309: getstatic 347	com/db/pwcc/dbmobile/transfer/R$string:standing_order_frequency_half_year_formatted	I
    //   1312: istore 4
    //   1314: goto -781 -> 533
    //   1317: astore_1
    //   1318: aload_1
    //   1319: invokevirtual 136	java/lang/reflect/InvocationTargetException:getCause	()Ljava/lang/Throwable;
    //   1322: athrow
    //   1323: astore_1
    //   1324: aload_1
    //   1325: invokevirtual 136	java/lang/reflect/InvocationTargetException:getCause	()Ljava/lang/Throwable;
    //   1328: athrow
    //   1329: getstatic 350	com/db/pwcc/dbmobile/transfer/R$string:standing_order_frequency_yearly_formatted	I
    //   1332: istore 4
    //   1334: goto -801 -> 533
    // Local variable table:
    //   start	length	slot	name	signature
    //   0	1337	0	this	StandingOrderConfirmationActivity
    //   0	1337	1	paramTextView	TextView
    //   0	1337	2	paramInt	int
    //   0	1337	3	paramString	String
    //   89	1244	4	i	int
    //   179	1082	5	localObject	Object
    // Exception table:
    //   from	to	target	type
    //   669	710	728	java/lang/reflect/InvocationTargetException
    //   772	805	823	java/lang/reflect/InvocationTargetException
    //   979	1013	1039	java/lang/reflect/InvocationTargetException
    //   181	214	1277	java/lang/reflect/InvocationTargetException
    //   419	452	1283	java/lang/reflect/InvocationTargetException
    //   1120	1162	1289	java/lang/reflect/InvocationTargetException
    //   1226	1259	1295	java/lang/reflect/InvocationTargetException
    //   872	913	1317	java/lang/reflect/InvocationTargetException
    //   275	316	1323	java/lang/reflect/InvocationTargetException
  }
  
  private void setFormattedFrequencyText(TextView paramTextView, StandingOrderTemplate paramStandingOrderTemplate)
  {
    String str = paramStandingOrderTemplate.getExecutionOn();
    Object localObject = ppphhp.class.getMethod(uxxxxx.bbbb0062b0062b0062b0062("\001\027\030\031\032ST\\]WX`a#\\]ef`aij,", 'p', 'R', '\002'), new Class[] { String.class, Character.TYPE, Character.TYPE });
    try
    {
      localObject = ((Method)localObject).invoke(null, new Object[] { "`", Character.valueOf('@'), Character.valueOf('\001') });
      str = str.replace((String)localObject, "").trim();
      int i = b006Dmm006Dm006Dmm006D;
      int j = b006D006D006D006Dm006Dmm006D;
      int k = b006Dmm006Dm006Dmm006D;
      int m = bmmmm006D006Dmm006D();
      int n = bm006Dm006Dm006Dmm006D;
      int i1 = b006Dmm006Dm006Dmm006D;
      switch (i1 * (b006D006D006D006Dm006Dmm006D + i1) % bmm006D006Dm006Dmm006D)
      {
      default: 
        b006Dmm006Dm006Dmm006D = 46;
        bm006Dm006Dm006Dmm006D = b006Dm006D006Dm006Dmm006D();
      }
      if ((i + j) * k % m != n)
      {
        b006Dmm006Dm006Dmm006D = 41;
        bm006Dm006Dm006Dmm006D = 56;
        if ((b006Dmm006Dm006Dmm006D + b006D006D006D006Dm006Dmm006D) * b006Dmm006Dm006Dmm006D % bmm006D006Dm006Dmm006D != bm006Dm006Dm006Dmm006D)
        {
          i = b006Dmm006Dm006Dmm006D;
          switch (i * (b006D006D006D006Dm006Dmm006D + i) % bmm006D006Dm006Dmm006D)
          {
          default: 
            b006Dmm006Dm006Dmm006D = 40;
            bm006Dm006Dm006Dmm006D = 8;
          }
          b006Dmm006Dm006Dmm006D = b006Dm006D006Dm006Dmm006D();
          bm006Dm006Dm006Dmm006D = 8;
        }
      }
      setFormattedFrequencyText(paramTextView, Integer.parseInt(str), paramStandingOrderTemplate.getFrequency());
      return;
    }
    catch (InvocationTargetException paramTextView)
    {
      throw paramTextView.getCause();
    }
  }
  
  private void setFormattedFrequencyText(TextView paramTextView, StandingOrderTransaction paramStandingOrderTransaction)
  {
    int i = b006Dmm006Dm006Dmm006D;
    switch (i * (b006D006D006D006Dm006Dmm006D + i) % bmm006D006Dm006Dmm006D)
    {
    default: 
      b006Dmm006Dm006Dmm006D = 51;
      bm006Dm006Dm006Dmm006D = b006Dm006D006Dm006Dmm006D();
      i = b006Dmm006Dm006Dmm006D;
      switch (i * (b006D006D006D006Dm006Dmm006D + i) % bmm006D006Dm006Dmm006D)
      {
      default: 
        b006Dmm006Dm006Dmm006D = b006Dm006D006Dm006Dmm006D();
        bm006Dm006Dm006Dmm006D = b006Dm006D006Dm006Dmm006D();
      }
      break;
    }
    String str = paramStandingOrderTransaction.getExecutionOn();
    Object localObject = ppphhp.class.getMethod(uxxxxx.bb00620062bb0062b0062b0062("\024(_^dc#\"YX^]UTZY\031POUTLKQP\020", '', '\003'), new Class[] { String.class, Character.TYPE, Character.TYPE, Character.TYPE });
    try
    {
      localObject = ((Method)localObject).invoke(null, new Object[] { "U", Character.valueOf(''), Character.valueOf('F'), Character.valueOf('\002') });
      localObject = (String)localObject;
      if ((b006Dmm006Dm006Dmm006D + b006D006D006D006Dm006Dmm006D) * b006Dmm006Dm006Dmm006D % bmm006D006Dm006Dmm006D != bm006Dm006Dm006Dmm006D)
      {
        b006Dmm006Dm006Dmm006D = 77;
        bm006Dm006Dm006Dmm006D = b006Dm006D006Dm006Dmm006D();
      }
      i = Integer.parseInt(str.replace((CharSequence)localObject, "").trim());
      paramStandingOrderTransaction = paramStandingOrderTransaction.getFrequency();
      if ((b006Dmm006Dm006Dmm006D + b006D006Dm006Dm006Dmm006D()) * b006Dmm006Dm006Dmm006D % bmmmm006D006Dmm006D() != bm006Dm006Dm006Dmm006D)
      {
        b006Dmm006Dm006Dmm006D = b006Dm006D006Dm006Dmm006D();
        bm006Dm006Dm006Dmm006D = b006Dm006D006Dm006Dmm006D();
      }
      setFormattedFrequencyText(paramTextView, i, paramStandingOrderTransaction);
      return;
    }
    catch (InvocationTargetException paramTextView)
    {
      throw paramTextView.getCause();
    }
  }
  
  private void setValidUntilText(TextView paramTextView, StandingOrderTemplate paramStandingOrderTemplate)
  {
    paramStandingOrderTemplate = paramStandingOrderTemplate.getValidUntil();
    int i = b006Dmm006Dm006Dmm006D;
    int j = b006D006D006D006Dm006Dmm006D;
    int k = bmm006D006Dm006Dmm006D;
    if ((b006Dmm006Dm006Dmm006D + b006D006D006D006Dm006Dmm006D) * b006Dmm006Dm006Dmm006D % bmm006D006Dm006Dmm006D != bm006Dm006Dm006Dmm006D)
    {
      b006Dmm006Dm006Dmm006D = 24;
      bm006Dm006Dm006Dmm006D = b006Dm006D006Dm006Dmm006D();
    }
    switch (i * (j + i) % k)
    {
    default: 
      b006Dmm006Dm006Dmm006D = b006Dm006D006Dm006Dmm006D();
      bm006Dm006Dm006Dmm006D = b006Dm006D006Dm006Dmm006D();
    }
    Object localObject = ppphhp.class.getMethod(uxxxxx.bb00620062bb0062b0062b0062("9MLKJ\002\001\007\006}|\003\002Axw}|tsyx8", 'T', '\004'), new Class[] { String.class, Character.TYPE, Character.TYPE });
    try
    {
      localObject = ((Method)localObject).invoke(null, new Object[] { "\006\007\b\t=^_", Character.valueOf('\004'), Character.valueOf('\000') });
      localObject = (String)localObject;
      Locale localLocale = Locale.getDefault();
      if ((b006Dmm006Dm006Dmm006D + b006D006D006D006Dm006Dmm006D) * b006Dmm006Dm006Dmm006D % bmm006D006Dm006Dmm006D != bm006Dm006Dm006Dmm006D)
      {
        b006Dmm006Dm006Dmm006D = b006Dm006D006Dm006Dmm006D();
        bm006Dm006Dm006Dmm006D = b006Dm006D006Dm006Dmm006D();
      }
      paramStandingOrderTemplate = new SimpleDateFormat((String)localObject, localLocale).parse(paramStandingOrderTemplate);
      localObject = Calendar.getInstance();
      ((Calendar)localObject).set(1, 9000);
      if (paramStandingOrderTemplate.after(((Calendar)localObject).getTime()))
      {
        paramTextView.setText(R.string.standing_order_valid_unlimited);
        return;
      }
      if ((b006Dmm006Dm006Dmm006D + b006D006D006D006Dm006Dmm006D) * b006Dmm006Dm006Dmm006D % bmm006D006Dm006Dmm006D != bm006Dm006Dm006Dmm006D)
      {
        b006Dmm006Dm006Dmm006D = 17;
        bm006Dm006Dm006Dmm006D = b006Dm006D006Dm006Dmm006D();
      }
      paramTextView.setText(pqpppq.b006Bkkk006B006Bkkkk(Locale.getDefault(), paramStandingOrderTemplate));
      return;
    }
    catch (InvocationTargetException paramTextView)
    {
      throw paramTextView.getCause();
    }
    catch (ParseException paramTextView) {}
  }
  
  public void closeActivity()
  {
    throw new Runtime("d2j fail translate: java.lang.IndexOutOfBoundsException: fromIndex < 0: -1\n\tat java.util.BitSet.nextSetBit(BitSet.java:712)\n\tat com.googlecode.dex2jar.ir.ts.array.FillArrayTransformer.makeSureAllElementAreAssigned(FillArrayTransformer.java:505)\n\tat com.googlecode.dex2jar.ir.ts.array.FillArrayTransformer.transformReportChanged(FillArrayTransformer.java:123)\n\tat com.googlecode.dex2jar.ir.ts.StatedTransformer.transform(StatedTransformer.java:10)\n\tat com.googlecode.d2j.dex.Dex2jar$2.optimize(Dex2jar.java:149)\n\tat com.googlecode.d2j.dex.Dex2Asm.convertCode(Dex2Asm.java:414)\n\tat com.googlecode.d2j.dex.ExDex2Asm.convertCode(ExDex2Asm.java:42)\n\tat com.googlecode.d2j.dex.Dex2jar$2.convertCode(Dex2jar.java:128)\n\tat com.googlecode.d2j.dex.Dex2Asm.convertMethod(Dex2Asm.java:509)\n\tat com.googlecode.d2j.dex.Dex2Asm.convertClass(Dex2Asm.java:406)\n\tat com.googlecode.d2j.dex.Dex2Asm.convertDex(Dex2Asm.java:422)\n\tat com.googlecode.d2j.dex.Dex2jar.doTranslate(Dex2jar.java:172)\n\tat com.googlecode.d2j.dex.Dex2jar.to(Dex2jar.java:272)\n\tat com.googlecode.dex2jar.tools.Dex2jarCmd.doCommandLine(Dex2jarCmd.java:108)\n\tat com.googlecode.dex2jar.tools.BaseCmd.doMain(BaseCmd.java:288)\n\tat com.googlecode.dex2jar.tools.Dex2jarCmd.main(Dex2jarCmd.java:32)\n");
  }
  
  public int getLayout()
  {
    int i = R.layout.activity_standing_order_confirmation;
    if ((b006Dmm006Dm006Dmm006D + b006D006D006D006Dm006Dmm006D) * b006Dmm006Dm006Dmm006D % bmm006D006Dm006Dmm006D != bm006Dm006Dm006Dmm006D)
    {
      if ((b006Dmm006Dm006Dmm006D + b006D006D006D006Dm006Dmm006D) * b006Dmm006Dm006Dmm006D % bmm006D006Dm006Dmm006D != bm006Dm006Dm006Dmm006D)
      {
        j = b006Dm006D006Dm006Dmm006D();
        if ((b006Dmm006Dm006Dmm006D + b006D006D006D006Dm006Dmm006D) * b006Dmm006Dm006Dmm006D % bmm006D006Dm006Dmm006D != bm006Dm006Dm006Dmm006D)
        {
          b006Dmm006Dm006Dmm006D = 31;
          bm006Dm006Dm006Dmm006D = b006Dm006D006Dm006Dmm006D();
        }
        b006Dmm006Dm006Dmm006D = j;
        bm006Dm006Dm006Dmm006D = 48;
      }
      b006Dmm006Dm006Dmm006D = 79;
      int j = b006Dmm006Dm006Dmm006D;
      switch (j * (b006D006D006D006Dm006Dmm006D + j) % bmm006D006Dm006Dmm006D)
      {
      default: 
        b006Dmm006Dm006Dmm006D = 73;
        bm006Dm006Dm006Dmm006D = b006Dm006D006Dm006Dmm006D();
      }
      bm006Dm006Dm006Dmm006D = 48;
    }
    return i;
  }
  
  public vvrvrv getResultSharedMetric()
  {
    if ((b006Dmm006Dm006Dmm006D + b006D006D006D006Dm006Dmm006D) * b006Dmm006Dm006Dmm006D % bmmmm006D006Dmm006D() != bm006D006D006Dm006Dmm006D())
    {
      b006Dmm006Dm006Dmm006D = b006Dm006D006Dm006Dmm006D();
      bm006Dm006Dm006Dmm006D = b006Dm006D006Dm006Dmm006D();
    }
    int i = b006Dmm006Dm006Dmm006D;
    int j = b006D006D006D006Dm006Dmm006D;
    int k = b006Dmm006Dm006Dmm006D;
    int m = bmm006D006Dm006Dmm006D;
    int n = bm006Dm006Dm006Dmm006D;
    if ((b006Dmm006Dm006Dmm006D + b006D006D006D006Dm006Dmm006D) * b006Dmm006Dm006Dmm006D % bmmmm006D006Dmm006D() != bm006Dm006Dm006Dmm006D)
    {
      b006Dmm006Dm006Dmm006D = 35;
      bm006Dm006Dm006Dmm006D = b006Dm006D006Dm006Dmm006D();
    }
    if ((i + j) * k % m != n)
    {
      if ((b006Dmm006Dm006Dmm006D + b006D006D006D006Dm006Dmm006D) * b006Dmm006Dm006Dmm006D % bmm006D006Dm006Dmm006D != bm006Dm006Dm006Dmm006D)
      {
        b006Dmm006Dm006Dmm006D = 15;
        bm006Dm006Dm006Dmm006D = b006Dm006D006Dm006Dmm006D();
      }
      b006Dmm006Dm006Dmm006D = b006Dm006D006Dm006Dmm006D();
      bm006Dm006Dm006Dmm006D = b006Dm006D006Dm006Dmm006D();
    }
    return null;
  }
  
  /* Error */
  public void initDbToolbar()
  {
    // Byte code:
    //   0: aload_0
    //   1: invokespecial 441	com/db/pwcc/dbmobile/transfer/inputscreen/activities/ConfirmationActivity:initDbToolbar	()V
    //   4: aload_0
    //   5: getfield 50	com/db/pwcc/dbmobile/transfer/standingorder/confirm/StandingOrderConfirmationActivity:standingOrderRequestResponse	Lcom/db/pwcc/dbmobile/transfer/standingorder/model/StandingOrderRequestResponse;
    //   8: invokevirtual 70	com/db/pwcc/dbmobile/transfer/standingorder/model/StandingOrderRequestResponse:getTransaction	()Lcom/db/pwcc/dbmobile/transfer/standingorder/model/StandingOrderTransaction;
    //   11: invokevirtual 86	com/db/pwcc/dbmobile/transfer/standingorder/model/StandingOrderTransaction:getType	()Ljava/lang/String;
    //   14: astore 5
    //   16: aload 5
    //   18: invokevirtual 244	java/lang/String:hashCode	()I
    //   21: lookupswitch	default:+35->56, -1410683983:+479->500, 1634254479:+238->259, 1712813854:+342->363
    //   56: iconst_m1
    //   57: istore_1
    //   58: iload_1
    //   59: tableswitch	default:+25->84, 0:+40->99, 1:+134->193, 2:+550->609
    //   84: ldc_w 362
    //   87: astore 5
    //   89: aload_0
    //   90: invokevirtual 445	com/db/pwcc/dbmobile/transfer/standingorder/confirm/StandingOrderConfirmationActivity:getActionToolbar	()Lcom/db/pwcc/dbmobile/foundation/views/toolbar/DbToolbar;
    //   93: aload 5
    //   95: invokevirtual 450	com/db/pwcc/dbmobile/foundation/views/toolbar/DbToolbar:setTitle	(Ljava/lang/String;)V
    //   98: return
    //   99: aload_0
    //   100: getstatic 453	com/db/pwcc/dbmobile/transfer/R$string:standing_order_add_title	I
    //   103: invokevirtual 265	com/db/pwcc/dbmobile/transfer/standingorder/confirm/StandingOrderConfirmationActivity:getString	(I)Ljava/lang/String;
    //   106: astore 6
    //   108: invokestatic 90	com/db/pwcc/dbmobile/transfer/standingorder/confirm/StandingOrderConfirmationActivity:b006Dm006D006Dm006Dmm006D	()I
    //   111: istore_1
    //   112: getstatic 74	com/db/pwcc/dbmobile/transfer/standingorder/confirm/StandingOrderConfirmationActivity:b006D006D006D006Dm006Dmm006D	I
    //   115: istore_2
    //   116: invokestatic 90	com/db/pwcc/dbmobile/transfer/standingorder/confirm/StandingOrderConfirmationActivity:b006Dm006D006Dm006Dmm006D	()I
    //   119: istore_3
    //   120: invokestatic 149	com/db/pwcc/dbmobile/transfer/standingorder/confirm/StandingOrderConfirmationActivity:bmmmm006D006Dmm006D	()I
    //   123: istore 4
    //   125: getstatic 72	com/db/pwcc/dbmobile/transfer/standingorder/confirm/StandingOrderConfirmationActivity:b006Dmm006Dm006Dmm006D	I
    //   128: getstatic 74	com/db/pwcc/dbmobile/transfer/standingorder/confirm/StandingOrderConfirmationActivity:b006D006D006D006Dm006Dmm006D	I
    //   131: iadd
    //   132: getstatic 72	com/db/pwcc/dbmobile/transfer/standingorder/confirm/StandingOrderConfirmationActivity:b006Dmm006Dm006Dmm006D	I
    //   135: imul
    //   136: getstatic 76	com/db/pwcc/dbmobile/transfer/standingorder/confirm/StandingOrderConfirmationActivity:bmm006D006Dm006Dmm006D	I
    //   139: irem
    //   140: getstatic 80	com/db/pwcc/dbmobile/transfer/standingorder/confirm/StandingOrderConfirmationActivity:bm006Dm006Dm006Dmm006D	I
    //   143: if_icmpeq +15 -> 158
    //   146: invokestatic 90	com/db/pwcc/dbmobile/transfer/standingorder/confirm/StandingOrderConfirmationActivity:b006Dm006D006Dm006Dmm006D	()I
    //   149: putstatic 72	com/db/pwcc/dbmobile/transfer/standingorder/confirm/StandingOrderConfirmationActivity:b006Dmm006Dm006Dmm006D	I
    //   152: invokestatic 90	com/db/pwcc/dbmobile/transfer/standingorder/confirm/StandingOrderConfirmationActivity:b006Dm006D006Dm006Dmm006D	()I
    //   155: putstatic 80	com/db/pwcc/dbmobile/transfer/standingorder/confirm/StandingOrderConfirmationActivity:bm006Dm006Dm006Dmm006D	I
    //   158: aload 6
    //   160: astore 5
    //   162: iload_1
    //   163: iload_2
    //   164: iadd
    //   165: iload_3
    //   166: imul
    //   167: iload 4
    //   169: irem
    //   170: getstatic 80	com/db/pwcc/dbmobile/transfer/standingorder/confirm/StandingOrderConfirmationActivity:bm006Dm006Dm006Dmm006D	I
    //   173: if_icmpeq -84 -> 89
    //   176: invokestatic 90	com/db/pwcc/dbmobile/transfer/standingorder/confirm/StandingOrderConfirmationActivity:b006Dm006D006Dm006Dmm006D	()I
    //   179: putstatic 72	com/db/pwcc/dbmobile/transfer/standingorder/confirm/StandingOrderConfirmationActivity:b006Dmm006Dm006Dmm006D	I
    //   182: iconst_1
    //   183: putstatic 80	com/db/pwcc/dbmobile/transfer/standingorder/confirm/StandingOrderConfirmationActivity:bm006Dm006Dm006Dmm006D	I
    //   186: aload 6
    //   188: astore 5
    //   190: goto -101 -> 89
    //   193: aload_0
    //   194: getstatic 456	com/db/pwcc/dbmobile/transfer/R$string:edit_standing_order_title	I
    //   197: invokevirtual 265	com/db/pwcc/dbmobile/transfer/standingorder/confirm/StandingOrderConfirmationActivity:getString	(I)Ljava/lang/String;
    //   200: astore 6
    //   202: getstatic 72	com/db/pwcc/dbmobile/transfer/standingorder/confirm/StandingOrderConfirmationActivity:b006Dmm006Dm006Dmm006D	I
    //   205: istore_1
    //   206: aload 6
    //   208: astore 5
    //   210: iload_1
    //   211: getstatic 74	com/db/pwcc/dbmobile/transfer/standingorder/confirm/StandingOrderConfirmationActivity:b006D006D006D006Dm006Dmm006D	I
    //   214: iload_1
    //   215: iadd
    //   216: imul
    //   217: getstatic 76	com/db/pwcc/dbmobile/transfer/standingorder/confirm/StandingOrderConfirmationActivity:bmm006D006Dm006Dmm006D	I
    //   220: irem
    //   221: tableswitch	default:+19->240, 0:+-132->89
    //   240: invokestatic 90	com/db/pwcc/dbmobile/transfer/standingorder/confirm/StandingOrderConfirmationActivity:b006Dm006D006Dm006Dmm006D	()I
    //   243: putstatic 72	com/db/pwcc/dbmobile/transfer/standingorder/confirm/StandingOrderConfirmationActivity:b006Dmm006Dm006Dmm006D	I
    //   246: invokestatic 90	com/db/pwcc/dbmobile/transfer/standingorder/confirm/StandingOrderConfirmationActivity:b006Dm006D006Dm006Dmm006D	()I
    //   249: putstatic 80	com/db/pwcc/dbmobile/transfer/standingorder/confirm/StandingOrderConfirmationActivity:bm006Dm006Dm006Dmm006D	I
    //   252: aload 6
    //   254: astore 5
    //   256: goto -167 -> 89
    //   259: ldc 92
    //   261: ldc_w 458
    //   264: bipush 102
    //   266: iconst_5
    //   267: invokestatic 100	xxxxxx/uxxxxx:bb00620062bb0062b0062b0062	(Ljava/lang/String;CC)Ljava/lang/String;
    //   270: iconst_4
    //   271: anewarray 102	java/lang/Class
    //   274: dup
    //   275: iconst_0
    //   276: ldc 104
    //   278: aastore
    //   279: dup
    //   280: iconst_1
    //   281: getstatic 110	java/lang/Character:TYPE	Ljava/lang/Class;
    //   284: aastore
    //   285: dup
    //   286: iconst_2
    //   287: getstatic 110	java/lang/Character:TYPE	Ljava/lang/Class;
    //   290: aastore
    //   291: dup
    //   292: iconst_3
    //   293: getstatic 110	java/lang/Character:TYPE	Ljava/lang/Class;
    //   296: aastore
    //   297: invokevirtual 114	java/lang/Class:getMethod	(Ljava/lang/String;[Ljava/lang/Class;)Ljava/lang/reflect/Method;
    //   300: astore 6
    //   302: aload 6
    //   304: aconst_null
    //   305: iconst_4
    //   306: anewarray 116	java/lang/Object
    //   309: dup
    //   310: iconst_0
    //   311: ldc_w 460
    //   314: aastore
    //   315: dup
    //   316: iconst_1
    //   317: sipush 134
    //   320: invokestatic 122	java/lang/Character:valueOf	(C)Ljava/lang/Character;
    //   323: aastore
    //   324: dup
    //   325: iconst_2
    //   326: sipush 220
    //   329: invokestatic 122	java/lang/Character:valueOf	(C)Ljava/lang/Character;
    //   332: aastore
    //   333: dup
    //   334: iconst_3
    //   335: iconst_3
    //   336: invokestatic 122	java/lang/Character:valueOf	(C)Ljava/lang/Character;
    //   339: aastore
    //   340: invokevirtual 128	java/lang/reflect/Method:invoke	(Ljava/lang/Object;[Ljava/lang/Object;)Ljava/lang/Object;
    //   343: astore 6
    //   345: aload 5
    //   347: aload 6
    //   349: checkcast 104	java/lang/String
    //   352: invokevirtual 132	java/lang/String:equals	(Ljava/lang/Object;)Z
    //   355: ifeq -299 -> 56
    //   358: iconst_2
    //   359: istore_1
    //   360: goto -302 -> 58
    //   363: getstatic 72	com/db/pwcc/dbmobile/transfer/standingorder/confirm/StandingOrderConfirmationActivity:b006Dmm006Dm006Dmm006D	I
    //   366: getstatic 74	com/db/pwcc/dbmobile/transfer/standingorder/confirm/StandingOrderConfirmationActivity:b006D006D006D006Dm006Dmm006D	I
    //   369: iadd
    //   370: getstatic 72	com/db/pwcc/dbmobile/transfer/standingorder/confirm/StandingOrderConfirmationActivity:b006Dmm006Dm006Dmm006D	I
    //   373: imul
    //   374: getstatic 76	com/db/pwcc/dbmobile/transfer/standingorder/confirm/StandingOrderConfirmationActivity:bmm006D006Dm006Dmm006D	I
    //   377: irem
    //   378: getstatic 80	com/db/pwcc/dbmobile/transfer/standingorder/confirm/StandingOrderConfirmationActivity:bm006Dm006Dm006Dmm006D	I
    //   381: if_icmpeq +14 -> 395
    //   384: bipush 63
    //   386: putstatic 72	com/db/pwcc/dbmobile/transfer/standingorder/confirm/StandingOrderConfirmationActivity:b006Dmm006Dm006Dmm006D	I
    //   389: invokestatic 90	com/db/pwcc/dbmobile/transfer/standingorder/confirm/StandingOrderConfirmationActivity:b006Dm006D006Dm006Dmm006D	()I
    //   392: putstatic 80	com/db/pwcc/dbmobile/transfer/standingorder/confirm/StandingOrderConfirmationActivity:bm006Dm006Dm006Dmm006D	I
    //   395: ldc 92
    //   397: ldc_w 462
    //   400: sipush 145
    //   403: iconst_1
    //   404: invokestatic 100	xxxxxx/uxxxxx:bb00620062bb0062b0062b0062	(Ljava/lang/String;CC)Ljava/lang/String;
    //   407: iconst_4
    //   408: anewarray 102	java/lang/Class
    //   411: dup
    //   412: iconst_0
    //   413: ldc 104
    //   415: aastore
    //   416: dup
    //   417: iconst_1
    //   418: getstatic 110	java/lang/Character:TYPE	Ljava/lang/Class;
    //   421: aastore
    //   422: dup
    //   423: iconst_2
    //   424: getstatic 110	java/lang/Character:TYPE	Ljava/lang/Class;
    //   427: aastore
    //   428: dup
    //   429: iconst_3
    //   430: getstatic 110	java/lang/Character:TYPE	Ljava/lang/Class;
    //   433: aastore
    //   434: invokevirtual 114	java/lang/Class:getMethod	(Ljava/lang/String;[Ljava/lang/Class;)Ljava/lang/reflect/Method;
    //   437: astore 6
    //   439: aload 6
    //   441: aconst_null
    //   442: iconst_4
    //   443: anewarray 116	java/lang/Object
    //   446: dup
    //   447: iconst_0
    //   448: ldc_w 464
    //   451: aastore
    //   452: dup
    //   453: iconst_1
    //   454: sipush 175
    //   457: invokestatic 122	java/lang/Character:valueOf	(C)Ljava/lang/Character;
    //   460: aastore
    //   461: dup
    //   462: iconst_2
    //   463: sipush 236
    //   466: invokestatic 122	java/lang/Character:valueOf	(C)Ljava/lang/Character;
    //   469: aastore
    //   470: dup
    //   471: iconst_3
    //   472: iconst_3
    //   473: invokestatic 122	java/lang/Character:valueOf	(C)Ljava/lang/Character;
    //   476: aastore
    //   477: invokevirtual 128	java/lang/reflect/Method:invoke	(Ljava/lang/Object;[Ljava/lang/Object;)Ljava/lang/Object;
    //   480: astore 6
    //   482: aload 5
    //   484: aload 6
    //   486: checkcast 104	java/lang/String
    //   489: invokevirtual 132	java/lang/String:equals	(Ljava/lang/Object;)Z
    //   492: ifeq -436 -> 56
    //   495: iconst_0
    //   496: istore_1
    //   497: goto -439 -> 58
    //   500: ldc 92
    //   502: ldc_w 466
    //   505: sipush 200
    //   508: sipush 157
    //   511: iconst_2
    //   512: invokestatic 187	xxxxxx/uxxxxx:bbbb0062b0062b0062b0062	(Ljava/lang/String;CCC)Ljava/lang/String;
    //   515: iconst_3
    //   516: anewarray 102	java/lang/Class
    //   519: dup
    //   520: iconst_0
    //   521: ldc 104
    //   523: aastore
    //   524: dup
    //   525: iconst_1
    //   526: getstatic 110	java/lang/Character:TYPE	Ljava/lang/Class;
    //   529: aastore
    //   530: dup
    //   531: iconst_2
    //   532: getstatic 110	java/lang/Character:TYPE	Ljava/lang/Class;
    //   535: aastore
    //   536: invokevirtual 114	java/lang/Class:getMethod	(Ljava/lang/String;[Ljava/lang/Class;)Ljava/lang/reflect/Method;
    //   539: astore 6
    //   541: aload 6
    //   543: aconst_null
    //   544: iconst_3
    //   545: anewarray 116	java/lang/Object
    //   548: dup
    //   549: iconst_0
    //   550: ldc_w 468
    //   553: aastore
    //   554: dup
    //   555: iconst_1
    //   556: sipush 250
    //   559: invokestatic 122	java/lang/Character:valueOf	(C)Ljava/lang/Character;
    //   562: aastore
    //   563: dup
    //   564: iconst_2
    //   565: iconst_4
    //   566: invokestatic 122	java/lang/Character:valueOf	(C)Ljava/lang/Character;
    //   569: aastore
    //   570: invokevirtual 128	java/lang/reflect/Method:invoke	(Ljava/lang/Object;[Ljava/lang/Object;)Ljava/lang/Object;
    //   573: astore 6
    //   575: aload 5
    //   577: aload 6
    //   579: checkcast 104	java/lang/String
    //   582: invokevirtual 132	java/lang/String:equals	(Ljava/lang/Object;)Z
    //   585: ifeq -529 -> 56
    //   588: iconst_1
    //   589: istore_1
    //   590: goto -532 -> 58
    //   593: astore 5
    //   595: aload 5
    //   597: invokevirtual 136	java/lang/reflect/InvocationTargetException:getCause	()Ljava/lang/Throwable;
    //   600: athrow
    //   601: astore 5
    //   603: aload 5
    //   605: invokevirtual 136	java/lang/reflect/InvocationTargetException:getCause	()Ljava/lang/Throwable;
    //   608: athrow
    //   609: aload_0
    //   610: getstatic 471	com/db/pwcc/dbmobile/transfer/R$string:delete_standing_order_title	I
    //   613: invokevirtual 265	com/db/pwcc/dbmobile/transfer/standingorder/confirm/StandingOrderConfirmationActivity:getString	(I)Ljava/lang/String;
    //   616: astore 5
    //   618: goto -529 -> 89
    //   621: astore 5
    //   623: aload 5
    //   625: invokevirtual 136	java/lang/reflect/InvocationTargetException:getCause	()Ljava/lang/Throwable;
    //   628: athrow
    // Local variable table:
    //   start	length	slot	name	signature
    //   0	629	0	this	StandingOrderConfirmationActivity
    //   57	533	1	i	int
    //   115	50	2	j	int
    //   119	48	3	k	int
    //   123	47	4	m	int
    //   14	562	5	localObject1	Object
    //   593	3	5	localInvocationTargetException1	InvocationTargetException
    //   601	3	5	localInvocationTargetException2	InvocationTargetException
    //   616	1	5	str	String
    //   621	3	5	localInvocationTargetException3	InvocationTargetException
    //   106	472	6	localObject2	Object
    // Exception table:
    //   from	to	target	type
    //   302	345	593	java/lang/reflect/InvocationTargetException
    //   439	482	601	java/lang/reflect/InvocationTargetException
    //   541	575	621	java/lang/reflect/InvocationTargetException
  }
  
  public void initView()
  {
    throw new Runtime("d2j fail translate: java.lang.IndexOutOfBoundsException: fromIndex < 0: -1\n\tat java.util.BitSet.nextSetBit(BitSet.java:712)\n\tat com.googlecode.dex2jar.ir.ts.array.FillArrayTransformer.makeSureAllElementAreAssigned(FillArrayTransformer.java:505)\n\tat com.googlecode.dex2jar.ir.ts.array.FillArrayTransformer.transformReportChanged(FillArrayTransformer.java:123)\n\tat com.googlecode.dex2jar.ir.ts.StatedTransformer.transform(StatedTransformer.java:10)\n\tat com.googlecode.d2j.dex.Dex2jar$2.optimize(Dex2jar.java:149)\n\tat com.googlecode.d2j.dex.Dex2Asm.convertCode(Dex2Asm.java:414)\n\tat com.googlecode.d2j.dex.ExDex2Asm.convertCode(ExDex2Asm.java:42)\n\tat com.googlecode.d2j.dex.Dex2jar$2.convertCode(Dex2jar.java:128)\n\tat com.googlecode.d2j.dex.Dex2Asm.convertMethod(Dex2Asm.java:509)\n\tat com.googlecode.d2j.dex.Dex2Asm.convertClass(Dex2Asm.java:406)\n\tat com.googlecode.d2j.dex.Dex2Asm.convertDex(Dex2Asm.java:422)\n\tat com.googlecode.d2j.dex.Dex2jar.doTranslate(Dex2jar.java:172)\n\tat com.googlecode.d2j.dex.Dex2jar.to(Dex2jar.java:272)\n\tat com.googlecode.dex2jar.tools.Dex2jarCmd.doCommandLine(Dex2jarCmd.java:108)\n\tat com.googlecode.dex2jar.tools.BaseCmd.doMain(BaseCmd.java:288)\n\tat com.googlecode.dex2jar.tools.Dex2jarCmd.main(Dex2jarCmd.java:32)\n");
  }
  
  public void navigateToStandingOrderDetailsActivity()
  {
    if ((b006Dmm006Dm006Dmm006D + b006D006D006D006Dm006Dmm006D) * b006Dmm006Dm006Dmm006D % bmm006D006Dm006Dmm006D != bm006D006D006Dm006Dmm006D())
    {
      b006Dmm006Dm006Dmm006D = 27;
      bm006Dm006Dm006Dmm006D = b006Dm006D006Dm006Dmm006D();
    }
    if ((b006Dmm006Dm006Dmm006D + b006D006D006D006Dm006Dmm006D) * b006Dmm006Dm006Dmm006D % bmm006D006Dm006Dmm006D != bm006Dm006Dm006Dmm006D)
    {
      b006Dmm006Dm006Dmm006D = 75;
      bm006Dm006Dm006Dmm006D = 88;
      int i = b006Dm006D006Dm006Dmm006D();
      switch (i * (b006D006D006D006Dm006Dmm006D + i) % bmmmm006D006Dmm006D())
      {
      default: 
        if ((b006Dmm006Dm006Dmm006D + b006D006D006D006Dm006Dmm006D) * b006Dmm006Dm006Dmm006D % bmmmm006D006Dmm006D() != bm006Dm006Dm006Dmm006D)
        {
          b006Dmm006Dm006Dmm006D = 20;
          bm006Dm006Dm006Dmm006D = b006Dm006D006Dm006Dmm006D();
        }
        b006Dmm006Dm006Dmm006D = b006Dm006D006Dm006Dmm006D();
        bm006Dm006Dm006Dmm006D = b006Dm006D006Dm006Dmm006D();
      }
    }
    navigateToActivity(StandingOrderDetailsActivity.class);
  }
  
  public void navigateToStandingOrdersActivity()
  {
    int i = b006Dmm006Dm006Dmm006D;
    switch (i * (b006D006D006D006Dm006Dmm006D + i) % bmm006D006Dm006Dmm006D)
    {
    default: 
      b006Dmm006Dm006Dmm006D = b006Dm006D006Dm006Dmm006D();
      bm006Dm006Dm006Dmm006D = b006Dm006D006Dm006Dmm006D();
      if ((b006Dmm006Dm006Dmm006D + b006D006D006D006Dm006Dmm006D) * b006Dmm006Dm006Dmm006D % bmm006D006Dm006Dmm006D != bm006D006D006Dm006Dmm006D())
      {
        b006Dmm006Dm006Dmm006D = b006Dm006D006Dm006Dmm006D();
        bm006Dm006Dm006Dmm006D = 36;
      }
      if ((b006Dmm006Dm006Dmm006D + b006D006D006D006Dm006Dmm006D) * b006Dmm006Dm006Dmm006D % bmm006D006Dm006Dmm006D != bm006Dm006Dm006Dmm006D)
      {
        b006Dmm006Dm006Dmm006D = 77;
        bm006Dm006Dm006Dmm006D = b006Dm006D006Dm006Dmm006D();
      }
      break;
    }
    navigateToActivity(StandingOrdersActivity.class);
    try
    {
      throw new NullPointerException();
    }
    catch (Exception localException)
    {
      b006Dmm006Dm006Dmm006D = b006Dm006D006Dm006Dmm006D();
    }
  }
  
  public void onBackPressed()
  {
    if ((b006Dmm006Dm006Dmm006D + b006D006D006D006Dm006Dmm006D) * b006Dmm006Dm006Dmm006D % bmm006D006Dm006Dmm006D != bm006Dm006Dm006Dmm006D)
    {
      b006Dmm006Dm006Dmm006D = 64;
      bm006Dm006Dm006Dmm006D = b006Dm006D006Dm006Dmm006D();
    }
    Object localObject;
    Method localMethod;
    if (!this.isUiDisabled)
    {
      super.onBackPressed();
      localObject = this.presenter;
      localMethod = llvvll.vlvvll.class.getMethod(uxxxxx.bb00620062bb0062b0062b0062("|\005\006MNUY\013RSZ^\020\021\022YZae]^ei", '\r', '\001'), new Class[0]);
    }
    try
    {
      localObject = localMethod.invoke(localObject, new Object[0]);
      if (((Boolean)localObject).booleanValue()) {
        closeActivity();
      }
      localObject = this.tanModule;
      int i = b006Dmm006Dm006Dmm006D;
      switch (i * (b006D006D006D006Dm006Dmm006D + i) % bmm006D006Dm006Dmm006D)
      {
      default: 
        b006Dmm006Dm006Dmm006D = 76;
        bm006Dm006Dm006Dmm006D = b006Dm006D006Dm006Dmm006D();
        if ((b006Dmm006Dm006Dmm006D + b006D006D006D006Dm006Dmm006D) * b006Dmm006Dm006Dmm006D % bmm006D006Dm006Dmm006D != bm006Dm006Dm006Dmm006D)
        {
          b006Dmm006Dm006Dmm006D = 74;
          bm006Dm006Dm006Dmm006D = 28;
        }
        break;
      }
      if (((TanModule)localObject).isAnyTanMethodAvailable())
      {
        finish();
        return;
      }
      if ((b006Dmm006Dm006Dmm006D + b006D006Dm006Dm006Dmm006D()) * b006Dmm006Dm006Dmm006D % bmm006D006Dm006Dmm006D != bm006Dm006Dm006Dmm006D)
      {
        b006Dmm006Dm006Dmm006D = b006Dm006D006Dm006Dmm006D();
        bm006Dm006Dm006Dmm006D = b006Dm006D006Dm006Dmm006D();
      }
      closeActivity();
      return;
    }
    catch (InvocationTargetException localInvocationTargetException)
    {
      throw localInvocationTargetException.getCause();
    }
  }
  
  /* Error */
  public void onCreate(Bundle paramBundle)
  {
    // Byte code:
    //   0: aload_0
    //   1: invokevirtual 518	com/db/pwcc/dbmobile/transfer/standingorder/confirm/StandingOrderConfirmationActivity:getApplicationContext	()Landroid/content/Context;
    //   4: astore 6
    //   6: ldc_w 520
    //   9: ldc_w 522
    //   12: sipush 223
    //   15: sipush 212
    //   18: iconst_0
    //   19: invokestatic 187	xxxxxx/uxxxxx:bbbb0062b0062b0062b0062	(Ljava/lang/String;CCC)Ljava/lang/String;
    //   22: iconst_1
    //   23: anewarray 102	java/lang/Class
    //   26: dup
    //   27: iconst_0
    //   28: ldc_w 524
    //   31: aastore
    //   32: invokevirtual 114	java/lang/Class:getMethod	(Ljava/lang/String;[Ljava/lang/Class;)Ljava/lang/reflect/Method;
    //   35: astore 7
    //   37: aload 7
    //   39: aconst_null
    //   40: iconst_1
    //   41: anewarray 116	java/lang/Object
    //   44: dup
    //   45: iconst_0
    //   46: aload 6
    //   48: aastore
    //   49: invokevirtual 128	java/lang/reflect/Method:invoke	(Ljava/lang/Object;[Ljava/lang/Object;)Ljava/lang/Object;
    //   52: pop
    //   53: aload_0
    //   54: invokevirtual 518	com/db/pwcc/dbmobile/transfer/standingorder/confirm/StandingOrderConfirmationActivity:getApplicationContext	()Landroid/content/Context;
    //   57: astore 6
    //   59: ldc_w 526
    //   62: ldc_w 528
    //   65: bipush 15
    //   67: sipush 201
    //   70: iconst_2
    //   71: invokestatic 187	xxxxxx/uxxxxx:bbbb0062b0062b0062b0062	(Ljava/lang/String;CCC)Ljava/lang/String;
    //   74: iconst_1
    //   75: anewarray 102	java/lang/Class
    //   78: dup
    //   79: iconst_0
    //   80: ldc_w 524
    //   83: aastore
    //   84: invokevirtual 114	java/lang/Class:getMethod	(Ljava/lang/String;[Ljava/lang/Class;)Ljava/lang/reflect/Method;
    //   87: astore 7
    //   89: aload 7
    //   91: aconst_null
    //   92: iconst_1
    //   93: anewarray 116	java/lang/Object
    //   96: dup
    //   97: iconst_0
    //   98: aload 6
    //   100: aastore
    //   101: invokevirtual 128	java/lang/reflect/Method:invoke	(Ljava/lang/Object;[Ljava/lang/Object;)Ljava/lang/Object;
    //   104: pop
    //   105: aload_0
    //   106: invokevirtual 518	com/db/pwcc/dbmobile/transfer/standingorder/confirm/StandingOrderConfirmationActivity:getApplicationContext	()Landroid/content/Context;
    //   109: invokestatic 534	uuuuuu/uppupu:b0072r0072r00720072rr0072	(Landroid/content/Context;)V
    //   112: getstatic 72	com/db/pwcc/dbmobile/transfer/standingorder/confirm/StandingOrderConfirmationActivity:b006Dmm006Dm006Dmm006D	I
    //   115: getstatic 74	com/db/pwcc/dbmobile/transfer/standingorder/confirm/StandingOrderConfirmationActivity:b006D006D006D006Dm006Dmm006D	I
    //   118: iadd
    //   119: getstatic 72	com/db/pwcc/dbmobile/transfer/standingorder/confirm/StandingOrderConfirmationActivity:b006Dmm006Dm006Dmm006D	I
    //   122: imul
    //   123: invokestatic 149	com/db/pwcc/dbmobile/transfer/standingorder/confirm/StandingOrderConfirmationActivity:bmmmm006D006Dmm006D	()I
    //   126: irem
    //   127: getstatic 80	com/db/pwcc/dbmobile/transfer/standingorder/confirm/StandingOrderConfirmationActivity:bm006Dm006Dm006Dmm006D	I
    //   130: if_icmpeq +14 -> 144
    //   133: invokestatic 90	com/db/pwcc/dbmobile/transfer/standingorder/confirm/StandingOrderConfirmationActivity:b006Dm006D006Dm006Dmm006D	()I
    //   136: putstatic 72	com/db/pwcc/dbmobile/transfer/standingorder/confirm/StandingOrderConfirmationActivity:b006Dmm006Dm006Dmm006D	I
    //   139: bipush 58
    //   141: putstatic 80	com/db/pwcc/dbmobile/transfer/standingorder/confirm/StandingOrderConfirmationActivity:bm006Dm006Dm006Dmm006D	I
    //   144: aload_0
    //   145: aload_1
    //   146: invokespecial 536	com/db/pwcc/dbmobile/transfer/inputscreen/activities/ConfirmationActivity:onCreate	(Landroid/os/Bundle;)V
    //   149: aload_0
    //   150: invokestatic 542	uuuuuu/lklkkk:bi0069i0069iii00690069i	(Landroid/content/Context;)Luuuuuu/kklkkk;
    //   153: aload_0
    //   154: invokeinterface 548 2 0
    //   159: aload_0
    //   160: invokevirtual 552	com/db/pwcc/dbmobile/transfer/standingorder/confirm/StandingOrderConfirmationActivity:getIntent	()Landroid/content/Intent;
    //   163: astore_1
    //   164: ldc 92
    //   166: ldc_w 554
    //   169: sipush 165
    //   172: bipush 58
    //   174: iconst_3
    //   175: invokestatic 187	xxxxxx/uxxxxx:bbbb0062b0062b0062b0062	(Ljava/lang/String;CCC)Ljava/lang/String;
    //   178: iconst_3
    //   179: anewarray 102	java/lang/Class
    //   182: dup
    //   183: iconst_0
    //   184: ldc 104
    //   186: aastore
    //   187: dup
    //   188: iconst_1
    //   189: getstatic 110	java/lang/Character:TYPE	Ljava/lang/Class;
    //   192: aastore
    //   193: dup
    //   194: iconst_2
    //   195: getstatic 110	java/lang/Character:TYPE	Ljava/lang/Class;
    //   198: aastore
    //   199: invokevirtual 114	java/lang/Class:getMethod	(Ljava/lang/String;[Ljava/lang/Class;)Ljava/lang/reflect/Method;
    //   202: astore 6
    //   204: aload 6
    //   206: aconst_null
    //   207: iconst_3
    //   208: anewarray 116	java/lang/Object
    //   211: dup
    //   212: iconst_0
    //   213: ldc_w 556
    //   216: aastore
    //   217: dup
    //   218: iconst_1
    //   219: bipush 87
    //   221: invokestatic 122	java/lang/Character:valueOf	(C)Ljava/lang/Character;
    //   224: aastore
    //   225: dup
    //   226: iconst_2
    //   227: iconst_5
    //   228: invokestatic 122	java/lang/Character:valueOf	(C)Ljava/lang/Character;
    //   231: aastore
    //   232: invokevirtual 128	java/lang/reflect/Method:invoke	(Ljava/lang/Object;[Ljava/lang/Object;)Ljava/lang/Object;
    //   235: astore 6
    //   237: aload_0
    //   238: aload_1
    //   239: aload 6
    //   241: checkcast 104	java/lang/String
    //   244: invokevirtual 560	android/content/Intent:getSerializableExtra	(Ljava/lang/String;)Ljava/io/Serializable;
    //   247: checkcast 66	com/db/pwcc/dbmobile/transfer/standingorder/model/StandingOrderRequestResponse
    //   250: putfield 50	com/db/pwcc/dbmobile/transfer/standingorder/confirm/StandingOrderConfirmationActivity:standingOrderRequestResponse	Lcom/db/pwcc/dbmobile/transfer/standingorder/model/StandingOrderRequestResponse;
    //   253: aload_0
    //   254: invokevirtual 552	com/db/pwcc/dbmobile/transfer/standingorder/confirm/StandingOrderConfirmationActivity:getIntent	()Landroid/content/Intent;
    //   257: astore_1
    //   258: ldc 92
    //   260: ldc_w 562
    //   263: sipush 166
    //   266: iconst_1
    //   267: invokestatic 100	xxxxxx/uxxxxx:bb00620062bb0062b0062b0062	(Ljava/lang/String;CC)Ljava/lang/String;
    //   270: iconst_3
    //   271: anewarray 102	java/lang/Class
    //   274: dup
    //   275: iconst_0
    //   276: ldc 104
    //   278: aastore
    //   279: dup
    //   280: iconst_1
    //   281: getstatic 110	java/lang/Character:TYPE	Ljava/lang/Class;
    //   284: aastore
    //   285: dup
    //   286: iconst_2
    //   287: getstatic 110	java/lang/Character:TYPE	Ljava/lang/Class;
    //   290: aastore
    //   291: invokevirtual 114	java/lang/Class:getMethod	(Ljava/lang/String;[Ljava/lang/Class;)Ljava/lang/reflect/Method;
    //   294: astore 6
    //   296: aload 6
    //   298: aconst_null
    //   299: iconst_3
    //   300: anewarray 116	java/lang/Object
    //   303: dup
    //   304: iconst_0
    //   305: ldc_w 564
    //   308: aastore
    //   309: dup
    //   310: iconst_1
    //   311: bipush 87
    //   313: invokestatic 122	java/lang/Character:valueOf	(C)Ljava/lang/Character;
    //   316: aastore
    //   317: dup
    //   318: iconst_2
    //   319: iconst_5
    //   320: invokestatic 122	java/lang/Character:valueOf	(C)Ljava/lang/Character;
    //   323: aastore
    //   324: invokevirtual 128	java/lang/reflect/Method:invoke	(Ljava/lang/Object;[Ljava/lang/Object;)Ljava/lang/Object;
    //   327: astore 6
    //   329: aload_0
    //   330: aload_1
    //   331: aload 6
    //   333: checkcast 104	java/lang/String
    //   336: invokevirtual 568	android/content/Intent:getParcelableExtra	(Ljava/lang/String;)Landroid/os/Parcelable;
    //   339: checkcast 570	com/db/pwcc/dbmobile/model/tan/ChallengeResponse
    //   342: putfield 52	com/db/pwcc/dbmobile/transfer/standingorder/confirm/StandingOrderConfirmationActivity:challengeResponse	Lcom/db/pwcc/dbmobile/model/tan/ChallengeResponse;
    //   345: aload_0
    //   346: invokevirtual 552	com/db/pwcc/dbmobile/transfer/standingorder/confirm/StandingOrderConfirmationActivity:getIntent	()Landroid/content/Intent;
    //   349: astore_1
    //   350: getstatic 72	com/db/pwcc/dbmobile/transfer/standingorder/confirm/StandingOrderConfirmationActivity:b006Dmm006Dm006Dmm006D	I
    //   353: istore_2
    //   354: getstatic 72	com/db/pwcc/dbmobile/transfer/standingorder/confirm/StandingOrderConfirmationActivity:b006Dmm006Dm006Dmm006D	I
    //   357: getstatic 74	com/db/pwcc/dbmobile/transfer/standingorder/confirm/StandingOrderConfirmationActivity:b006D006D006D006Dm006Dmm006D	I
    //   360: iadd
    //   361: getstatic 72	com/db/pwcc/dbmobile/transfer/standingorder/confirm/StandingOrderConfirmationActivity:b006Dmm006Dm006Dmm006D	I
    //   364: imul
    //   365: getstatic 76	com/db/pwcc/dbmobile/transfer/standingorder/confirm/StandingOrderConfirmationActivity:bmm006D006Dm006Dmm006D	I
    //   368: irem
    //   369: getstatic 80	com/db/pwcc/dbmobile/transfer/standingorder/confirm/StandingOrderConfirmationActivity:bm006Dm006Dm006Dmm006D	I
    //   372: if_icmpeq +15 -> 387
    //   375: invokestatic 90	com/db/pwcc/dbmobile/transfer/standingorder/confirm/StandingOrderConfirmationActivity:b006Dm006D006Dm006Dmm006D	()I
    //   378: putstatic 72	com/db/pwcc/dbmobile/transfer/standingorder/confirm/StandingOrderConfirmationActivity:b006Dmm006Dm006Dmm006D	I
    //   381: invokestatic 90	com/db/pwcc/dbmobile/transfer/standingorder/confirm/StandingOrderConfirmationActivity:b006Dm006D006Dm006Dmm006D	()I
    //   384: putstatic 80	com/db/pwcc/dbmobile/transfer/standingorder/confirm/StandingOrderConfirmationActivity:bm006Dm006Dm006Dmm006D	I
    //   387: getstatic 74	com/db/pwcc/dbmobile/transfer/standingorder/confirm/StandingOrderConfirmationActivity:b006D006D006D006Dm006Dmm006D	I
    //   390: istore_3
    //   391: getstatic 72	com/db/pwcc/dbmobile/transfer/standingorder/confirm/StandingOrderConfirmationActivity:b006Dmm006Dm006Dmm006D	I
    //   394: istore 4
    //   396: getstatic 72	com/db/pwcc/dbmobile/transfer/standingorder/confirm/StandingOrderConfirmationActivity:b006Dmm006Dm006Dmm006D	I
    //   399: istore 5
    //   401: iload 5
    //   403: getstatic 74	com/db/pwcc/dbmobile/transfer/standingorder/confirm/StandingOrderConfirmationActivity:b006D006D006D006Dm006Dmm006D	I
    //   406: iload 5
    //   408: iadd
    //   409: imul
    //   410: invokestatic 149	com/db/pwcc/dbmobile/transfer/standingorder/confirm/StandingOrderConfirmationActivity:bmmmm006D006Dmm006D	()I
    //   413: irem
    //   414: tableswitch	default:+18->432, 0:+29->443
    //   432: invokestatic 90	com/db/pwcc/dbmobile/transfer/standingorder/confirm/StandingOrderConfirmationActivity:b006Dm006D006Dm006Dmm006D	()I
    //   435: putstatic 72	com/db/pwcc/dbmobile/transfer/standingorder/confirm/StandingOrderConfirmationActivity:b006Dmm006Dm006Dmm006D	I
    //   438: bipush 83
    //   440: putstatic 80	com/db/pwcc/dbmobile/transfer/standingorder/confirm/StandingOrderConfirmationActivity:bm006Dm006Dm006Dmm006D	I
    //   443: iload_2
    //   444: iload_3
    //   445: iadd
    //   446: iload 4
    //   448: imul
    //   449: getstatic 76	com/db/pwcc/dbmobile/transfer/standingorder/confirm/StandingOrderConfirmationActivity:bmm006D006Dm006Dmm006D	I
    //   452: irem
    //   453: getstatic 80	com/db/pwcc/dbmobile/transfer/standingorder/confirm/StandingOrderConfirmationActivity:bm006Dm006Dm006Dmm006D	I
    //   456: if_icmpeq +14 -> 470
    //   459: invokestatic 90	com/db/pwcc/dbmobile/transfer/standingorder/confirm/StandingOrderConfirmationActivity:b006Dm006D006Dm006Dmm006D	()I
    //   462: putstatic 72	com/db/pwcc/dbmobile/transfer/standingorder/confirm/StandingOrderConfirmationActivity:b006Dmm006Dm006Dmm006D	I
    //   465: bipush 25
    //   467: putstatic 80	com/db/pwcc/dbmobile/transfer/standingorder/confirm/StandingOrderConfirmationActivity:bm006Dm006Dm006Dmm006D	I
    //   470: ldc 92
    //   472: ldc_w 572
    //   475: bipush 13
    //   477: iconst_1
    //   478: invokestatic 100	xxxxxx/uxxxxx:bb00620062bb0062b0062b0062	(Ljava/lang/String;CC)Ljava/lang/String;
    //   481: iconst_3
    //   482: anewarray 102	java/lang/Class
    //   485: dup
    //   486: iconst_0
    //   487: ldc 104
    //   489: aastore
    //   490: dup
    //   491: iconst_1
    //   492: getstatic 110	java/lang/Character:TYPE	Ljava/lang/Class;
    //   495: aastore
    //   496: dup
    //   497: iconst_2
    //   498: getstatic 110	java/lang/Character:TYPE	Ljava/lang/Class;
    //   501: aastore
    //   502: invokevirtual 114	java/lang/Class:getMethod	(Ljava/lang/String;[Ljava/lang/Class;)Ljava/lang/reflect/Method;
    //   505: astore 6
    //   507: aload 6
    //   509: aconst_null
    //   510: iconst_3
    //   511: anewarray 116	java/lang/Object
    //   514: dup
    //   515: iconst_0
    //   516: ldc_w 574
    //   519: aastore
    //   520: dup
    //   521: iconst_1
    //   522: bipush 46
    //   524: invokestatic 122	java/lang/Character:valueOf	(C)Ljava/lang/Character;
    //   527: aastore
    //   528: dup
    //   529: iconst_2
    //   530: iconst_5
    //   531: invokestatic 122	java/lang/Character:valueOf	(C)Ljava/lang/Character;
    //   534: aastore
    //   535: invokevirtual 128	java/lang/reflect/Method:invoke	(Ljava/lang/Object;[Ljava/lang/Object;)Ljava/lang/Object;
    //   538: astore 6
    //   540: aload_0
    //   541: aload_1
    //   542: aload 6
    //   544: checkcast 104	java/lang/String
    //   547: invokevirtual 568	android/content/Intent:getParcelableExtra	(Ljava/lang/String;)Landroid/os/Parcelable;
    //   550: checkcast 353	com/db/pwcc/dbmobile/transfer/standingorder/model/StandingOrderTemplate
    //   553: putfield 54	com/db/pwcc/dbmobile/transfer/standingorder/confirm/StandingOrderConfirmationActivity:standingOrderTemplate	Lcom/db/pwcc/dbmobile/transfer/standingorder/model/StandingOrderTemplate;
    //   556: aload_0
    //   557: new 576	uuuuuu/vvvvll
    //   560: dup
    //   561: invokespecial 577	uuuuuu/vvvvll:<init>	()V
    //   564: putfield 48	com/db/pwcc/dbmobile/transfer/standingorder/confirm/StandingOrderConfirmationActivity:presenter	Luuuuuu/llvvll$vlvvll;
    //   567: aload_0
    //   568: getfield 48	com/db/pwcc/dbmobile/transfer/standingorder/confirm/StandingOrderConfirmationActivity:presenter	Luuuuuu/llvvll$vlvvll;
    //   571: astore_1
    //   572: ldc_w 494
    //   575: ldc_w 579
    //   578: sipush 167
    //   581: bipush 118
    //   583: iconst_2
    //   584: invokestatic 187	xxxxxx/uxxxxx:bbbb0062b0062b0062b0062	(Ljava/lang/String;CCC)Ljava/lang/String;
    //   587: iconst_1
    //   588: anewarray 102	java/lang/Class
    //   591: dup
    //   592: iconst_0
    //   593: ldc 6
    //   595: aastore
    //   596: invokevirtual 114	java/lang/Class:getMethod	(Ljava/lang/String;[Ljava/lang/Class;)Ljava/lang/reflect/Method;
    //   599: astore 6
    //   601: aload 6
    //   603: aload_1
    //   604: iconst_1
    //   605: anewarray 116	java/lang/Object
    //   608: dup
    //   609: iconst_0
    //   610: aload_0
    //   611: aastore
    //   612: invokevirtual 128	java/lang/reflect/Method:invoke	(Ljava/lang/Object;[Ljava/lang/Object;)Ljava/lang/Object;
    //   615: pop
    //   616: aload_0
    //   617: invokevirtual 581	com/db/pwcc/dbmobile/transfer/standingorder/confirm/StandingOrderConfirmationActivity:initView	()V
    //   620: aload_0
    //   621: invokevirtual 582	com/db/pwcc/dbmobile/transfer/standingorder/confirm/StandingOrderConfirmationActivity:initDbToolbar	()V
    //   624: return
    //   625: astore_1
    //   626: aload_1
    //   627: invokevirtual 136	java/lang/reflect/InvocationTargetException:getCause	()Ljava/lang/Throwable;
    //   630: athrow
    //   631: astore_1
    //   632: aload_1
    //   633: invokevirtual 136	java/lang/reflect/InvocationTargetException:getCause	()Ljava/lang/Throwable;
    //   636: athrow
    //   637: astore_1
    //   638: aload_1
    //   639: invokevirtual 136	java/lang/reflect/InvocationTargetException:getCause	()Ljava/lang/Throwable;
    //   642: athrow
    //   643: astore_1
    //   644: aload_1
    //   645: invokevirtual 136	java/lang/reflect/InvocationTargetException:getCause	()Ljava/lang/Throwable;
    //   648: athrow
    //   649: astore_1
    //   650: aload_1
    //   651: invokevirtual 136	java/lang/reflect/InvocationTargetException:getCause	()Ljava/lang/Throwable;
    //   654: athrow
    //   655: astore_1
    //   656: aload_1
    //   657: invokevirtual 136	java/lang/reflect/InvocationTargetException:getCause	()Ljava/lang/Throwable;
    //   660: athrow
    // Local variable table:
    //   start	length	slot	name	signature
    //   0	661	0	this	StandingOrderConfirmationActivity
    //   0	661	1	paramBundle	Bundle
    //   353	93	2	i	int
    //   390	56	3	j	int
    //   394	55	4	k	int
    //   399	11	5	m	int
    //   4	598	6	localObject	Object
    //   35	55	7	localMethod	Method
    // Exception table:
    //   from	to	target	type
    //   37	53	625	java/lang/reflect/InvocationTargetException
    //   89	105	631	java/lang/reflect/InvocationTargetException
    //   296	329	637	java/lang/reflect/InvocationTargetException
    //   204	237	643	java/lang/reflect/InvocationTargetException
    //   507	540	649	java/lang/reflect/InvocationTargetException
    //   601	616	655	java/lang/reflect/InvocationTargetException
  }
  
  public void onRestoreInstanceState(Bundle paramBundle)
  {
    super.onRestoreInstanceState(paramBundle);
    Object localObject = ppphhp.class.getMethod(uxxxxx.bbbb0062b0062b0062b0062("\0364567pqyztu}~@yz\003\004}~\007\bI", ',', '', '\003'), new Class[] { String.class, Character.TYPE, Character.TYPE });
    try
    {
      localObject = ((Method)localObject).invoke(null, new Object[] { "\035*)j\"!m19&'r*)58,482{CB2@F::H\005,\032(:),\"4,&A'-863)B=J>2AD<E", Character.valueOf('\023'), Character.valueOf('\000') });
      if (paramBundle.getBoolean((String)localObject)) {
        localObject = ppphhp.class.getMethod(uxxxxx.bb00620062bb0062b0062b0062(" 6opxy;<uv~yz\003\004E~\b\t\003\004\f\rN", '', '\002'), new Class[] { String.class, Character.TYPE, Character.TYPE, Character.TYPE });
      }
      paramBundle = xxsxsx.b006B006B006B006Bk006Bk006B006B006B(paramBundle);
    }
    catch (InvocationTargetException paramBundle)
    {
      try
      {
        localObject = ((Method)localObject).invoke(null, new Object[] { "`ml.ed1t|ij6mlx{ow{u?\007\006u\004\n}}\fHo]k}loewoi\005jp{yvl\006\001\016t\003\004\002\006", Character.valueOf('Q'), Character.valueOf(''), Character.valueOf('\003') });
        paramBundle = (DbError)paramBundle.getSerializable((String)localObject);
        if (paramBundle != null) {
          break label376;
        }
        this.tanModule.showSuccessLayoutView();
        i = b006Dm006D006Dm006Dmm006D();
        switch (i * (b006D006Dm006Dm006Dmm006D() + i) % bmm006D006Dm006Dmm006D)
        {
        default: 
          b006Dmm006Dm006Dmm006D = 69;
          bm006Dm006Dm006Dmm006D = 68;
        }
        showShareableToolbar();
        return;
      }
      catch (InvocationTargetException paramBundle)
      {
        int i;
        throw paramBundle.getCause();
      }
      paramBundle = paramBundle;
      throw paramBundle.getCause();
    }
    label376:
    do
    {
      if ((b006Dmm006Dm006Dmm006D + b006D006D006D006Dm006Dmm006D) * b006Dmm006Dm006Dmm006D % bmm006D006Dm006Dmm006D != bm006Dm006Dm006Dmm006D)
      {
        b006Dmm006Dm006Dmm006D = b006Dm006D006Dm006Dmm006D();
        bm006Dm006Dm006Dmm006D = 90;
      }
      this.tanModule.showErrorLayoutView(paramBundle);
      i = b006Dmm006Dm006Dmm006D;
      switch (i * (b006D006D006D006Dm006Dmm006D + i) % bmmmm006D006Dmm006D())
      {
      }
      b006Dmm006Dm006Dmm006D = b006Dm006D006Dm006Dmm006D();
      bm006Dm006Dm006Dmm006D = b006Dm006D006Dm006Dmm006D();
      if ((b006Dmm006Dm006Dmm006D + b006D006D006D006Dm006Dmm006D) * b006Dmm006Dm006Dmm006D % bmm006D006Dm006Dmm006D == bm006Dm006Dm006Dmm006D) {
        break;
      }
      b006Dmm006Dm006Dmm006D = b006Dm006D006Dm006Dmm006D();
      bm006Dm006Dm006Dmm006D = b006Dm006D006Dm006Dmm006D();
      return;
    } while (!xxsxsx.bkk006Bk006B006Bk006B006B006B(paramBundle));
    ((kkkklk)this.presenter).onTransactionAuthenticationFailure(R.string.check_internet_connection);
  }
  
  /* Error */
  public void onSaveInstanceState(Bundle paramBundle)
  {
    // Byte code:
    //   0: getstatic 72	com/db/pwcc/dbmobile/transfer/standingorder/confirm/StandingOrderConfirmationActivity:b006Dmm006Dm006Dmm006D	I
    //   3: getstatic 74	com/db/pwcc/dbmobile/transfer/standingorder/confirm/StandingOrderConfirmationActivity:b006D006D006D006Dm006Dmm006D	I
    //   6: iadd
    //   7: getstatic 72	com/db/pwcc/dbmobile/transfer/standingorder/confirm/StandingOrderConfirmationActivity:b006Dmm006Dm006Dmm006D	I
    //   10: imul
    //   11: getstatic 76	com/db/pwcc/dbmobile/transfer/standingorder/confirm/StandingOrderConfirmationActivity:bmm006D006Dm006Dmm006D	I
    //   14: irem
    //   15: getstatic 80	com/db/pwcc/dbmobile/transfer/standingorder/confirm/StandingOrderConfirmationActivity:bm006Dm006Dm006Dmm006D	I
    //   18: if_icmpeq +91 -> 109
    //   21: getstatic 72	com/db/pwcc/dbmobile/transfer/standingorder/confirm/StandingOrderConfirmationActivity:b006Dmm006Dm006Dmm006D	I
    //   24: istore_2
    //   25: iload_2
    //   26: getstatic 74	com/db/pwcc/dbmobile/transfer/standingorder/confirm/StandingOrderConfirmationActivity:b006D006D006D006Dm006Dmm006D	I
    //   29: iload_2
    //   30: iadd
    //   31: imul
    //   32: getstatic 76	com/db/pwcc/dbmobile/transfer/standingorder/confirm/StandingOrderConfirmationActivity:bmm006D006Dm006Dmm006D	I
    //   35: irem
    //   36: tableswitch	default:+20->56, 0:+30->66
    //   56: bipush 14
    //   58: putstatic 72	com/db/pwcc/dbmobile/transfer/standingorder/confirm/StandingOrderConfirmationActivity:b006Dmm006Dm006Dmm006D	I
    //   61: bipush 67
    //   63: putstatic 80	com/db/pwcc/dbmobile/transfer/standingorder/confirm/StandingOrderConfirmationActivity:bm006Dm006Dm006Dmm006D	I
    //   66: bipush 35
    //   68: putstatic 72	com/db/pwcc/dbmobile/transfer/standingorder/confirm/StandingOrderConfirmationActivity:b006Dmm006Dm006Dmm006D	I
    //   71: invokestatic 90	com/db/pwcc/dbmobile/transfer/standingorder/confirm/StandingOrderConfirmationActivity:b006Dm006D006Dm006Dmm006D	()I
    //   74: putstatic 80	com/db/pwcc/dbmobile/transfer/standingorder/confirm/StandingOrderConfirmationActivity:bm006Dm006Dm006Dmm006D	I
    //   77: invokestatic 90	com/db/pwcc/dbmobile/transfer/standingorder/confirm/StandingOrderConfirmationActivity:b006Dm006D006Dm006Dmm006D	()I
    //   80: getstatic 74	com/db/pwcc/dbmobile/transfer/standingorder/confirm/StandingOrderConfirmationActivity:b006D006D006D006Dm006Dmm006D	I
    //   83: iadd
    //   84: invokestatic 90	com/db/pwcc/dbmobile/transfer/standingorder/confirm/StandingOrderConfirmationActivity:b006Dm006D006Dm006Dmm006D	()I
    //   87: imul
    //   88: getstatic 76	com/db/pwcc/dbmobile/transfer/standingorder/confirm/StandingOrderConfirmationActivity:bmm006D006Dm006Dmm006D	I
    //   91: irem
    //   92: getstatic 80	com/db/pwcc/dbmobile/transfer/standingorder/confirm/StandingOrderConfirmationActivity:bm006Dm006Dm006Dmm006D	I
    //   95: if_icmpeq +14 -> 109
    //   98: bipush 31
    //   100: putstatic 72	com/db/pwcc/dbmobile/transfer/standingorder/confirm/StandingOrderConfirmationActivity:b006Dmm006Dm006Dmm006D	I
    //   103: invokestatic 90	com/db/pwcc/dbmobile/transfer/standingorder/confirm/StandingOrderConfirmationActivity:b006Dm006D006Dm006Dmm006D	()I
    //   106: putstatic 80	com/db/pwcc/dbmobile/transfer/standingorder/confirm/StandingOrderConfirmationActivity:bm006Dm006Dm006Dmm006D	I
    //   109: ldc 92
    //   111: ldc_w 635
    //   114: sipush 160
    //   117: bipush 120
    //   119: iconst_2
    //   120: invokestatic 187	xxxxxx/uxxxxx:bbbb0062b0062b0062b0062	(Ljava/lang/String;CCC)Ljava/lang/String;
    //   123: iconst_4
    //   124: anewarray 102	java/lang/Class
    //   127: dup
    //   128: iconst_0
    //   129: ldc 104
    //   131: aastore
    //   132: dup
    //   133: iconst_1
    //   134: getstatic 110	java/lang/Character:TYPE	Ljava/lang/Class;
    //   137: aastore
    //   138: dup
    //   139: iconst_2
    //   140: getstatic 110	java/lang/Character:TYPE	Ljava/lang/Class;
    //   143: aastore
    //   144: dup
    //   145: iconst_3
    //   146: getstatic 110	java/lang/Character:TYPE	Ljava/lang/Class;
    //   149: aastore
    //   150: invokevirtual 114	java/lang/Class:getMethod	(Ljava/lang/String;[Ljava/lang/Class;)Ljava/lang/reflect/Method;
    //   153: astore_3
    //   154: aload_3
    //   155: aconst_null
    //   156: iconst_4
    //   157: anewarray 116	java/lang/Object
    //   160: dup
    //   161: iconst_0
    //   162: ldc_w 589
    //   165: aastore
    //   166: dup
    //   167: iconst_1
    //   168: bipush 56
    //   170: invokestatic 122	java/lang/Character:valueOf	(C)Ljava/lang/Character;
    //   173: aastore
    //   174: dup
    //   175: iconst_2
    //   176: sipush 128
    //   179: invokestatic 122	java/lang/Character:valueOf	(C)Ljava/lang/Character;
    //   182: aastore
    //   183: dup
    //   184: iconst_3
    //   185: iconst_3
    //   186: invokestatic 122	java/lang/Character:valueOf	(C)Ljava/lang/Character;
    //   189: aastore
    //   190: invokevirtual 128	java/lang/reflect/Method:invoke	(Ljava/lang/Object;[Ljava/lang/Object;)Ljava/lang/Object;
    //   193: astore_3
    //   194: aload_3
    //   195: checkcast 104	java/lang/String
    //   198: astore_3
    //   199: invokestatic 90	com/db/pwcc/dbmobile/transfer/standingorder/confirm/StandingOrderConfirmationActivity:b006Dm006D006Dm006Dmm006D	()I
    //   202: getstatic 74	com/db/pwcc/dbmobile/transfer/standingorder/confirm/StandingOrderConfirmationActivity:b006D006D006D006Dm006Dmm006D	I
    //   205: iadd
    //   206: invokestatic 90	com/db/pwcc/dbmobile/transfer/standingorder/confirm/StandingOrderConfirmationActivity:b006Dm006D006Dm006Dmm006D	()I
    //   209: imul
    //   210: invokestatic 149	com/db/pwcc/dbmobile/transfer/standingorder/confirm/StandingOrderConfirmationActivity:bmmmm006D006Dmm006D	()I
    //   213: irem
    //   214: getstatic 80	com/db/pwcc/dbmobile/transfer/standingorder/confirm/StandingOrderConfirmationActivity:bm006Dm006Dm006Dmm006D	I
    //   217: if_icmpeq +14 -> 231
    //   220: bipush 72
    //   222: putstatic 72	com/db/pwcc/dbmobile/transfer/standingorder/confirm/StandingOrderConfirmationActivity:b006Dmm006Dm006Dmm006D	I
    //   225: invokestatic 90	com/db/pwcc/dbmobile/transfer/standingorder/confirm/StandingOrderConfirmationActivity:b006Dm006D006Dm006Dmm006D	()I
    //   228: putstatic 80	com/db/pwcc/dbmobile/transfer/standingorder/confirm/StandingOrderConfirmationActivity:bm006Dm006Dm006Dmm006D	I
    //   231: aload_0
    //   232: getfield 48	com/db/pwcc/dbmobile/transfer/standingorder/confirm/StandingOrderConfirmationActivity:presenter	Luuuuuu/llvvll$vlvvll;
    //   235: astore 4
    //   237: ldc_w 494
    //   240: ldc_w 637
    //   243: bipush 56
    //   245: sipush 148
    //   248: iconst_3
    //   249: invokestatic 187	xxxxxx/uxxxxx:bbbb0062b0062b0062b0062	(Ljava/lang/String;CCC)Ljava/lang/String;
    //   252: iconst_0
    //   253: anewarray 102	java/lang/Class
    //   256: invokevirtual 114	java/lang/Class:getMethod	(Ljava/lang/String;[Ljava/lang/Class;)Ljava/lang/reflect/Method;
    //   259: astore 5
    //   261: aload 5
    //   263: aload 4
    //   265: iconst_0
    //   266: anewarray 116	java/lang/Object
    //   269: invokevirtual 128	java/lang/reflect/Method:invoke	(Ljava/lang/Object;[Ljava/lang/Object;)Ljava/lang/Object;
    //   272: astore 4
    //   274: aload_1
    //   275: aload_3
    //   276: aload 4
    //   278: checkcast 498	java/lang/Boolean
    //   281: invokevirtual 501	java/lang/Boolean:booleanValue	()Z
    //   284: invokevirtual 641	android/os/Bundle:putBoolean	(Ljava/lang/String;Z)V
    //   287: ldc 92
    //   289: ldc_w 643
    //   292: sipush 180
    //   295: iconst_1
    //   296: invokestatic 100	xxxxxx/uxxxxx:bb00620062bb0062b0062b0062	(Ljava/lang/String;CC)Ljava/lang/String;
    //   299: iconst_3
    //   300: anewarray 102	java/lang/Class
    //   303: dup
    //   304: iconst_0
    //   305: ldc 104
    //   307: aastore
    //   308: dup
    //   309: iconst_1
    //   310: getstatic 110	java/lang/Character:TYPE	Ljava/lang/Class;
    //   313: aastore
    //   314: dup
    //   315: iconst_2
    //   316: getstatic 110	java/lang/Character:TYPE	Ljava/lang/Class;
    //   319: aastore
    //   320: invokevirtual 114	java/lang/Class:getMethod	(Ljava/lang/String;[Ljava/lang/Class;)Ljava/lang/reflect/Method;
    //   323: astore_3
    //   324: aload_3
    //   325: aconst_null
    //   326: iconst_3
    //   327: anewarray 116	java/lang/Object
    //   330: dup
    //   331: iconst_0
    //   332: ldc_w 645
    //   335: aastore
    //   336: dup
    //   337: iconst_1
    //   338: sipush 247
    //   341: invokestatic 122	java/lang/Character:valueOf	(C)Ljava/lang/Character;
    //   344: aastore
    //   345: dup
    //   346: iconst_2
    //   347: iconst_2
    //   348: invokestatic 122	java/lang/Character:valueOf	(C)Ljava/lang/Character;
    //   351: aastore
    //   352: invokevirtual 128	java/lang/reflect/Method:invoke	(Ljava/lang/Object;[Ljava/lang/Object;)Ljava/lang/Object;
    //   355: astore_3
    //   356: aload_1
    //   357: aload_3
    //   358: checkcast 104	java/lang/String
    //   361: aload_0
    //   362: getfield 48	com/db/pwcc/dbmobile/transfer/standingorder/confirm/StandingOrderConfirmationActivity:presenter	Luuuuuu/llvvll$vlvvll;
    //   365: invokeinterface 649 1 0
    //   370: invokevirtual 653	android/os/Bundle:putSerializable	(Ljava/lang/String;Ljava/io/Serializable;)V
    //   373: aload_0
    //   374: aload_1
    //   375: invokespecial 655	com/db/pwcc/dbmobile/transfer/inputscreen/activities/ConfirmationActivity:onSaveInstanceState	(Landroid/os/Bundle;)V
    //   378: return
    //   379: astore_1
    //   380: aload_1
    //   381: invokevirtual 136	java/lang/reflect/InvocationTargetException:getCause	()Ljava/lang/Throwable;
    //   384: athrow
    //   385: astore_1
    //   386: aload_1
    //   387: invokevirtual 136	java/lang/reflect/InvocationTargetException:getCause	()Ljava/lang/Throwable;
    //   390: athrow
    //   391: astore_1
    //   392: aload_1
    //   393: invokevirtual 136	java/lang/reflect/InvocationTargetException:getCause	()Ljava/lang/Throwable;
    //   396: athrow
    // Local variable table:
    //   start	length	slot	name	signature
    //   0	397	0	this	StandingOrderConfirmationActivity
    //   0	397	1	paramBundle	Bundle
    //   24	8	2	i	int
    //   153	205	3	localObject1	Object
    //   235	42	4	localObject2	Object
    //   259	3	5	localMethod	Method
    // Exception table:
    //   from	to	target	type
    //   154	194	379	java/lang/reflect/InvocationTargetException
    //   324	356	385	java/lang/reflect/InvocationTargetException
    //   261	274	391	java/lang/reflect/InvocationTargetException
  }
  
  public void retrievePrincipalAccountDetails(String paramString)
  {
    if ((b006Dmm006Dm006Dmm006D + b006D006Dm006Dm006Dmm006D()) * b006Dmm006Dm006Dmm006D % bmm006D006Dm006Dmm006D != bm006D006D006Dm006Dmm006D())
    {
      if ((b006Dmm006Dm006Dmm006D + b006D006Dm006Dm006Dmm006D()) * b006Dmm006Dm006Dmm006D % bmm006D006Dm006Dmm006D != bm006Dm006Dm006Dmm006D)
      {
        b006Dmm006Dm006Dmm006D = 7;
        bm006Dm006Dm006Dmm006D = b006Dm006D006Dm006Dmm006D();
      }
      if ((b006Dmm006Dm006Dmm006D + b006D006D006D006Dm006Dmm006D) * b006Dmm006Dm006Dmm006D % bmm006D006Dm006Dmm006D != bm006Dm006Dm006Dmm006D)
      {
        b006Dmm006Dm006Dmm006D = 47;
        bm006Dm006Dm006Dmm006D = 1;
      }
      b006Dmm006Dm006Dmm006D = b006Dm006D006Dm006Dmm006D();
      bm006Dm006Dm006Dmm006D = b006Dm006D006Dm006Dmm006D();
    }
    int i = b006Dmm006Dm006Dmm006D;
    switch (i * (b006D006D006D006Dm006Dmm006D + i) % bmm006D006Dm006Dmm006D)
    {
    default: 
      b006Dmm006Dm006Dmm006D = b006Dm006D006Dm006Dmm006D();
      bm006Dm006Dm006Dmm006D = b006Dm006D006Dm006Dmm006D();
    }
    llvvll.vlvvll localVlvvll = this.presenter;
    Method localMethod = llvvll.vlvvll.class.getMethod(uxxxxx.bbbb0062b0062b0062b0062("6\003\002\007\t8}|\002\0043xw|~.-,qpuwmlqs", '\002', 'U', '\001'), new Class[] { String.class });
    try
    {
      localMethod.invoke(localVlvvll, new Object[] { paramString });
      return;
    }
    catch (InvocationTargetException paramString)
    {
      throw paramString.getCause();
    }
  }
  
  public void setAccountName(String paramString)
  {
    int j = 5;
    int i = j;
    if ((b006Dmm006Dm006Dmm006D + b006D006Dm006Dm006Dmm006D()) * b006Dmm006Dm006Dmm006D % bmmmm006D006Dmm006D() != bm006D006D006Dm006Dmm006D())
    {
      b006Dmm006Dm006Dmm006D = 14;
      bm006Dm006Dm006Dmm006D = b006Dm006D006Dm006Dmm006D();
      i = j;
    }
    try
    {
      for (;;)
      {
        j = i / 0;
        i = j;
        if ((b006Dmm006Dm006Dmm006D + b006D006D006D006Dm006Dmm006D) * b006Dmm006Dm006Dmm006D % bmm006D006Dm006Dmm006D != bm006D006D006Dm006Dmm006D())
        {
          b006Dmm006Dm006Dmm006D = b006Dm006D006Dm006Dmm006D();
          bm006Dm006Dm006Dmm006D = b006Dm006D006Dm006Dmm006D();
          int k = b006Dmm006Dm006Dmm006D;
          i = j;
          switch (k * (b006D006D006D006Dm006Dmm006D + k) % bmm006D006Dm006Dmm006D)
          {
          }
          b006Dmm006Dm006Dmm006D = b006Dm006D006Dm006Dmm006D();
          bm006Dm006Dm006Dmm006D = b006Dm006D006Dm006Dmm006D();
          i = j;
        }
      }
      return;
    }
    catch (Exception localException)
    {
      b006Dmm006Dm006Dmm006D = b006Dm006D006Dm006Dmm006D();
      ((TextView)findViewById(R.id.confirmation_principalCurrentBalance)).setText(paramString);
    }
  }
  
  public void setPrincipalName(String paramString1, String paramString2)
  {
    int i = b006Dm006D006Dm006Dmm006D();
    int j = b006D006Dm006Dm006Dmm006D();
    int k = bmm006D006Dm006Dmm006D;
    if ((b006Dmm006Dm006Dmm006D + b006D006D006D006Dm006Dmm006D) * b006Dmm006Dm006Dmm006D % bmm006D006Dm006Dmm006D != bm006Dm006Dm006Dmm006D)
    {
      b006Dmm006Dm006Dmm006D = b006Dm006D006Dm006Dmm006D();
      bm006Dm006Dm006Dmm006D = b006Dm006D006Dm006Dmm006D();
      int m = b006Dmm006Dm006Dmm006D;
      switch (m * (b006D006D006D006Dm006Dmm006D + m) % bmm006D006Dm006Dmm006D)
      {
      default: 
        b006Dmm006Dm006Dmm006D = 6;
        bm006Dm006Dm006Dmm006D = 87;
      }
    }
    switch (i * (j + i) % k)
    {
    default: 
      i = b006Dmm006Dm006Dmm006D;
      switch (i * (b006D006Dm006Dm006Dmm006D() + i) % bmm006D006Dm006Dmm006D)
      {
      default: 
        b006Dmm006Dm006Dmm006D = 95;
        bm006Dm006Dm006Dmm006D = b006Dm006D006Dm006Dmm006D();
      }
      b006Dmm006Dm006Dmm006D = b006Dm006D006Dm006Dmm006D();
      bm006Dm006Dm006Dmm006D = 88;
    }
    TextView localTextView = (TextView)findViewById(R.id.confirmation_principalInitials);
    ((TextView)findViewById(R.id.confirmation_principalName)).setText(paramString1);
    localTextView.setText(paramString2);
  }
  
  /* Error */
  public void setTransactionData(StandingOrderRequestResponse paramStandingOrderRequestResponse)
  {
    // Byte code:
    //   0: aload_0
    //   1: getstatic 681	com/db/pwcc/dbmobile/transfer/R$id:confirmation_beneficiaryName	I
    //   4: invokevirtual 668	com/db/pwcc/dbmobile/transfer/standingorder/confirm/StandingOrderConfirmationActivity:findViewById	(I)Landroid/view/View;
    //   7: checkcast 267	android/widget/TextView
    //   10: astore 14
    //   12: aload_0
    //   13: getstatic 684	com/db/pwcc/dbmobile/transfer/R$id:confirmation_beneficiaryIban	I
    //   16: invokevirtual 668	com/db/pwcc/dbmobile/transfer/standingorder/confirm/StandingOrderConfirmationActivity:findViewById	(I)Landroid/view/View;
    //   19: checkcast 267	android/widget/TextView
    //   22: astore 8
    //   24: aload_0
    //   25: getstatic 687	com/db/pwcc/dbmobile/transfer/R$id:bic	I
    //   28: invokevirtual 668	com/db/pwcc/dbmobile/transfer/standingorder/confirm/StandingOrderConfirmationActivity:findViewById	(I)Landroid/view/View;
    //   31: checkcast 267	android/widget/TextView
    //   34: astore 9
    //   36: aload_0
    //   37: getstatic 690	com/db/pwcc/dbmobile/transfer/R$id:description	I
    //   40: invokevirtual 668	com/db/pwcc/dbmobile/transfer/standingorder/confirm/StandingOrderConfirmationActivity:findViewById	(I)Landroid/view/View;
    //   43: checkcast 267	android/widget/TextView
    //   46: astore 10
    //   48: aload_0
    //   49: getstatic 693	com/db/pwcc/dbmobile/transfer/R$id:confirmation_reference	I
    //   52: invokevirtual 668	com/db/pwcc/dbmobile/transfer/standingorder/confirm/StandingOrderConfirmationActivity:findViewById	(I)Landroid/view/View;
    //   55: checkcast 267	android/widget/TextView
    //   58: astore 11
    //   60: aload_0
    //   61: getstatic 696	com/db/pwcc/dbmobile/transfer/R$id:amountValue	I
    //   64: invokevirtual 668	com/db/pwcc/dbmobile/transfer/standingorder/confirm/StandingOrderConfirmationActivity:findViewById	(I)Landroid/view/View;
    //   67: checkcast 267	android/widget/TextView
    //   70: astore 6
    //   72: aload_0
    //   73: getstatic 699	com/db/pwcc/dbmobile/transfer/R$id:confirmation_principalIban	I
    //   76: invokevirtual 668	com/db/pwcc/dbmobile/transfer/standingorder/confirm/StandingOrderConfirmationActivity:findViewById	(I)Landroid/view/View;
    //   79: checkcast 267	android/widget/TextView
    //   82: astore 7
    //   84: getstatic 72	com/db/pwcc/dbmobile/transfer/standingorder/confirm/StandingOrderConfirmationActivity:b006Dmm006Dm006Dmm006D	I
    //   87: istore_2
    //   88: iload_2
    //   89: getstatic 74	com/db/pwcc/dbmobile/transfer/standingorder/confirm/StandingOrderConfirmationActivity:b006D006D006D006Dm006Dmm006D	I
    //   92: iload_2
    //   93: iadd
    //   94: imul
    //   95: getstatic 76	com/db/pwcc/dbmobile/transfer/standingorder/confirm/StandingOrderConfirmationActivity:bmm006D006Dm006Dmm006D	I
    //   98: irem
    //   99: tableswitch	default:+17->116, 0:+28->127
    //   116: bipush 20
    //   118: putstatic 72	com/db/pwcc/dbmobile/transfer/standingorder/confirm/StandingOrderConfirmationActivity:b006Dmm006Dm006Dmm006D	I
    //   121: invokestatic 90	com/db/pwcc/dbmobile/transfer/standingorder/confirm/StandingOrderConfirmationActivity:b006Dm006D006Dm006Dmm006D	()I
    //   124: putstatic 80	com/db/pwcc/dbmobile/transfer/standingorder/confirm/StandingOrderConfirmationActivity:bm006Dm006Dm006Dmm006D	I
    //   127: aload_0
    //   128: getstatic 702	com/db/pwcc/dbmobile/transfer/R$id:confirmation_executionDate	I
    //   131: invokevirtual 668	com/db/pwcc/dbmobile/transfer/standingorder/confirm/StandingOrderConfirmationActivity:findViewById	(I)Landroid/view/View;
    //   134: checkcast 267	android/widget/TextView
    //   137: astore_3
    //   138: aload_0
    //   139: getstatic 705	com/db/pwcc/dbmobile/transfer/R$id:confirmation_frequency	I
    //   142: invokevirtual 668	com/db/pwcc/dbmobile/transfer/standingorder/confirm/StandingOrderConfirmationActivity:findViewById	(I)Landroid/view/View;
    //   145: checkcast 267	android/widget/TextView
    //   148: astore 4
    //   150: aload_0
    //   151: getstatic 708	com/db/pwcc/dbmobile/transfer/R$id:confirmation_validUntil	I
    //   154: invokevirtual 668	com/db/pwcc/dbmobile/transfer/standingorder/confirm/StandingOrderConfirmationActivity:findViewById	(I)Landroid/view/View;
    //   157: checkcast 267	android/widget/TextView
    //   160: astore 5
    //   162: aload_3
    //   163: invokestatic 714	uuuuuu/xsxxxs:bkk006Bkk006B006Bk006B006B	(Landroid/view/View;)V
    //   166: aload 5
    //   168: invokestatic 714	uuuuuu/xsxxxs:bkk006Bkk006B006Bk006B006B	(Landroid/view/View;)V
    //   171: aload_1
    //   172: ifnull +597 -> 769
    //   175: aload_1
    //   176: invokevirtual 70	com/db/pwcc/dbmobile/transfer/standingorder/model/StandingOrderRequestResponse:getTransaction	()Lcom/db/pwcc/dbmobile/transfer/standingorder/model/StandingOrderTransaction;
    //   179: ifnull +590 -> 769
    //   182: aload_1
    //   183: invokevirtual 70	com/db/pwcc/dbmobile/transfer/standingorder/model/StandingOrderRequestResponse:getTransaction	()Lcom/db/pwcc/dbmobile/transfer/standingorder/model/StandingOrderTransaction;
    //   186: astore_1
    //   187: aload_1
    //   188: invokevirtual 717	com/db/pwcc/dbmobile/transfer/standingorder/model/StandingOrderTransaction:getPurpose	()Ljava/lang/String;
    //   191: astore 12
    //   193: aload_1
    //   194: invokevirtual 720	com/db/pwcc/dbmobile/transfer/standingorder/model/StandingOrderTransaction:getReference	()Ljava/lang/String;
    //   197: astore 13
    //   199: aload_1
    //   200: invokevirtual 723	com/db/pwcc/dbmobile/transfer/standingorder/model/StandingOrderTransaction:getBeneficiary	()Ljava/lang/String;
    //   203: astore 15
    //   205: getstatic 72	com/db/pwcc/dbmobile/transfer/standingorder/confirm/StandingOrderConfirmationActivity:b006Dmm006Dm006Dmm006D	I
    //   208: getstatic 74	com/db/pwcc/dbmobile/transfer/standingorder/confirm/StandingOrderConfirmationActivity:b006D006D006D006Dm006Dmm006D	I
    //   211: iadd
    //   212: getstatic 72	com/db/pwcc/dbmobile/transfer/standingorder/confirm/StandingOrderConfirmationActivity:b006Dmm006Dm006Dmm006D	I
    //   215: imul
    //   216: getstatic 76	com/db/pwcc/dbmobile/transfer/standingorder/confirm/StandingOrderConfirmationActivity:bmm006D006Dm006Dmm006D	I
    //   219: irem
    //   220: getstatic 80	com/db/pwcc/dbmobile/transfer/standingorder/confirm/StandingOrderConfirmationActivity:bm006Dm006Dm006Dmm006D	I
    //   223: if_icmpeq +13 -> 236
    //   226: iconst_2
    //   227: putstatic 72	com/db/pwcc/dbmobile/transfer/standingorder/confirm/StandingOrderConfirmationActivity:b006Dmm006Dm006Dmm006D	I
    //   230: invokestatic 90	com/db/pwcc/dbmobile/transfer/standingorder/confirm/StandingOrderConfirmationActivity:b006Dm006D006Dm006Dmm006D	()I
    //   233: putstatic 80	com/db/pwcc/dbmobile/transfer/standingorder/confirm/StandingOrderConfirmationActivity:bm006Dm006Dm006Dmm006D	I
    //   236: aload 15
    //   238: invokestatic 729	uuuuuu/oononn:b006Bk006B006Bk006Bk006Bk006B	(Ljava/lang/String;)Ljava/lang/String;
    //   241: astore 16
    //   243: aload 14
    //   245: aload 15
    //   247: invokevirtual 271	android/widget/TextView:setText	(Ljava/lang/CharSequence;)V
    //   250: aload_0
    //   251: getfield 733	com/db/pwcc/dbmobile/transfer/standingorder/confirm/StandingOrderConfirmationActivity:beneficiaryAvatar	Lcom/db/pwcc/dbmobile/foundation/widgets/UserAvatar;
    //   254: aload 16
    //   256: invokevirtual 736	com/db/pwcc/dbmobile/foundation/widgets/UserAvatar:setText	(Ljava/lang/CharSequence;)V
    //   259: aload_0
    //   260: invokevirtual 552	com/db/pwcc/dbmobile/transfer/standingorder/confirm/StandingOrderConfirmationActivity:getIntent	()Landroid/content/Intent;
    //   263: astore 14
    //   265: ldc 92
    //   267: ldc_w 738
    //   270: bipush 12
    //   272: iconst_2
    //   273: iconst_0
    //   274: invokestatic 187	xxxxxx/uxxxxx:bbbb0062b0062b0062b0062	(Ljava/lang/String;CCC)Ljava/lang/String;
    //   277: iconst_4
    //   278: anewarray 102	java/lang/Class
    //   281: dup
    //   282: iconst_0
    //   283: ldc 104
    //   285: aastore
    //   286: dup
    //   287: iconst_1
    //   288: getstatic 110	java/lang/Character:TYPE	Ljava/lang/Class;
    //   291: aastore
    //   292: dup
    //   293: iconst_2
    //   294: getstatic 110	java/lang/Character:TYPE	Ljava/lang/Class;
    //   297: aastore
    //   298: dup
    //   299: iconst_3
    //   300: getstatic 110	java/lang/Character:TYPE	Ljava/lang/Class;
    //   303: aastore
    //   304: invokevirtual 114	java/lang/Class:getMethod	(Ljava/lang/String;[Ljava/lang/Class;)Ljava/lang/reflect/Method;
    //   307: astore 15
    //   309: aload 15
    //   311: aconst_null
    //   312: iconst_4
    //   313: anewarray 116	java/lang/Object
    //   316: dup
    //   317: iconst_0
    //   318: ldc_w 740
    //   321: aastore
    //   322: dup
    //   323: iconst_1
    //   324: bipush 32
    //   326: invokestatic 122	java/lang/Character:valueOf	(C)Ljava/lang/Character;
    //   329: aastore
    //   330: dup
    //   331: iconst_2
    //   332: sipush 166
    //   335: invokestatic 122	java/lang/Character:valueOf	(C)Ljava/lang/Character;
    //   338: aastore
    //   339: dup
    //   340: iconst_3
    //   341: iconst_3
    //   342: invokestatic 122	java/lang/Character:valueOf	(C)Ljava/lang/Character;
    //   345: aastore
    //   346: invokevirtual 128	java/lang/reflect/Method:invoke	(Ljava/lang/Object;[Ljava/lang/Object;)Ljava/lang/Object;
    //   349: astore 15
    //   351: aload 14
    //   353: aload 15
    //   355: checkcast 104	java/lang/String
    //   358: invokevirtual 743	android/content/Intent:hasExtra	(Ljava/lang/String;)Z
    //   361: ifeq +445 -> 806
    //   364: aload_0
    //   365: invokevirtual 552	com/db/pwcc/dbmobile/transfer/standingorder/confirm/StandingOrderConfirmationActivity:getIntent	()Landroid/content/Intent;
    //   368: astore 14
    //   370: ldc 92
    //   372: ldc_w 745
    //   375: sipush 137
    //   378: iconst_3
    //   379: invokestatic 100	xxxxxx/uxxxxx:bb00620062bb0062b0062b0062	(Ljava/lang/String;CC)Ljava/lang/String;
    //   382: iconst_4
    //   383: anewarray 102	java/lang/Class
    //   386: dup
    //   387: iconst_0
    //   388: ldc 104
    //   390: aastore
    //   391: dup
    //   392: iconst_1
    //   393: getstatic 110	java/lang/Character:TYPE	Ljava/lang/Class;
    //   396: aastore
    //   397: dup
    //   398: iconst_2
    //   399: getstatic 110	java/lang/Character:TYPE	Ljava/lang/Class;
    //   402: aastore
    //   403: dup
    //   404: iconst_3
    //   405: getstatic 110	java/lang/Character:TYPE	Ljava/lang/Class;
    //   408: aastore
    //   409: invokevirtual 114	java/lang/Class:getMethod	(Ljava/lang/String;[Ljava/lang/Class;)Ljava/lang/reflect/Method;
    //   412: astore 15
    //   414: aload 15
    //   416: aconst_null
    //   417: iconst_4
    //   418: anewarray 116	java/lang/Object
    //   421: dup
    //   422: iconst_0
    //   423: ldc_w 747
    //   426: aastore
    //   427: dup
    //   428: iconst_1
    //   429: sipush 147
    //   432: invokestatic 122	java/lang/Character:valueOf	(C)Ljava/lang/Character;
    //   435: aastore
    //   436: dup
    //   437: iconst_2
    //   438: sipush 172
    //   441: invokestatic 122	java/lang/Character:valueOf	(C)Ljava/lang/Character;
    //   444: aastore
    //   445: dup
    //   446: iconst_3
    //   447: iconst_3
    //   448: invokestatic 122	java/lang/Character:valueOf	(C)Ljava/lang/Character;
    //   451: aastore
    //   452: invokevirtual 128	java/lang/reflect/Method:invoke	(Ljava/lang/Object;[Ljava/lang/Object;)Ljava/lang/Object;
    //   455: astore 15
    //   457: aload 9
    //   459: aload 14
    //   461: aload 15
    //   463: checkcast 104	java/lang/String
    //   466: invokevirtual 750	android/content/Intent:getStringExtra	(Ljava/lang/String;)Ljava/lang/String;
    //   469: invokevirtual 271	android/widget/TextView:setText	(Ljava/lang/CharSequence;)V
    //   472: aload 12
    //   474: ifnull +423 -> 897
    //   477: aload 12
    //   479: invokevirtual 369	java/lang/String:trim	()Ljava/lang/String;
    //   482: ldc_w 362
    //   485: invokevirtual 132	java/lang/String:equals	(Ljava/lang/Object;)Z
    //   488: ifne +409 -> 897
    //   491: aload 10
    //   493: aload 12
    //   495: invokevirtual 271	android/widget/TextView:setText	(Ljava/lang/CharSequence;)V
    //   498: aload 13
    //   500: ifnull +316 -> 816
    //   503: aload 13
    //   505: invokevirtual 369	java/lang/String:trim	()Ljava/lang/String;
    //   508: ldc_w 362
    //   511: invokevirtual 132	java/lang/String:equals	(Ljava/lang/Object;)Z
    //   514: ifne +302 -> 816
    //   517: aload 11
    //   519: aload 13
    //   521: invokevirtual 271	android/widget/TextView:setText	(Ljava/lang/CharSequence;)V
    //   524: aload 8
    //   526: aload_1
    //   527: invokevirtual 753	com/db/pwcc/dbmobile/transfer/standingorder/model/StandingOrderTransaction:getTargetAccount	()Ljava/lang/String;
    //   530: invokevirtual 271	android/widget/TextView:setText	(Ljava/lang/CharSequence;)V
    //   533: invokestatic 233	java/util/Locale:getDefault	()Ljava/util/Locale;
    //   536: astore 8
    //   538: aload 6
    //   540: new 755	java/math/BigDecimal
    //   543: dup
    //   544: aload_1
    //   545: invokevirtual 758	com/db/pwcc/dbmobile/transfer/standingorder/model/StandingOrderTransaction:getAmount	()Ljava/lang/String;
    //   548: invokespecial 759	java/math/BigDecimal:<init>	(Ljava/lang/String;)V
    //   551: getstatic 765	uuuuuu/hhhpph:by0079y007900790079yy0079	Ljava/util/Currency;
    //   554: invokevirtual 770	java/util/Currency:getCurrencyCode	()Ljava/lang/String;
    //   557: aload 8
    //   559: invokestatic 774	uuuuuu/hhhpph:bw0077wwwwww0077w	(Ljava/math/BigDecimal;Ljava/lang/String;Ljava/util/Locale;)Ljava/lang/String;
    //   562: invokevirtual 271	android/widget/TextView:setText	(Ljava/lang/CharSequence;)V
    //   565: aload 7
    //   567: aload_1
    //   568: invokevirtual 777	com/db/pwcc/dbmobile/transfer/standingorder/model/StandingOrderTransaction:getSourceAccount	()Ljava/lang/String;
    //   571: invokevirtual 271	android/widget/TextView:setText	(Ljava/lang/CharSequence;)V
    //   574: ldc 92
    //   576: ldc_w 779
    //   579: bipush 50
    //   581: sipush 193
    //   584: iconst_3
    //   585: invokestatic 187	xxxxxx/uxxxxx:bbbb0062b0062b0062b0062	(Ljava/lang/String;CCC)Ljava/lang/String;
    //   588: iconst_4
    //   589: anewarray 102	java/lang/Class
    //   592: dup
    //   593: iconst_0
    //   594: ldc 104
    //   596: aastore
    //   597: dup
    //   598: iconst_1
    //   599: getstatic 110	java/lang/Character:TYPE	Ljava/lang/Class;
    //   602: aastore
    //   603: dup
    //   604: iconst_2
    //   605: getstatic 110	java/lang/Character:TYPE	Ljava/lang/Class;
    //   608: aastore
    //   609: dup
    //   610: iconst_3
    //   611: getstatic 110	java/lang/Character:TYPE	Ljava/lang/Class;
    //   614: aastore
    //   615: invokevirtual 114	java/lang/Class:getMethod	(Ljava/lang/String;[Ljava/lang/Class;)Ljava/lang/reflect/Method;
    //   618: astore 6
    //   620: aload 6
    //   622: aconst_null
    //   623: iconst_4
    //   624: anewarray 116	java/lang/Object
    //   627: dup
    //   628: iconst_0
    //   629: ldc_w 781
    //   632: aastore
    //   633: dup
    //   634: iconst_1
    //   635: sipush 138
    //   638: invokestatic 122	java/lang/Character:valueOf	(C)Ljava/lang/Character;
    //   641: aastore
    //   642: dup
    //   643: iconst_2
    //   644: sipush 186
    //   647: invokestatic 122	java/lang/Character:valueOf	(C)Ljava/lang/Character;
    //   650: aastore
    //   651: dup
    //   652: iconst_3
    //   653: iconst_0
    //   654: invokestatic 122	java/lang/Character:valueOf	(C)Ljava/lang/Character;
    //   657: aastore
    //   658: invokevirtual 128	java/lang/reflect/Method:invoke	(Ljava/lang/Object;[Ljava/lang/Object;)Ljava/lang/Object;
    //   661: astore 6
    //   663: aload 6
    //   665: checkcast 104	java/lang/String
    //   668: astore 6
    //   670: aload_1
    //   671: invokevirtual 86	com/db/pwcc/dbmobile/transfer/standingorder/model/StandingOrderTransaction:getType	()Ljava/lang/String;
    //   674: astore 7
    //   676: getstatic 72	com/db/pwcc/dbmobile/transfer/standingorder/confirm/StandingOrderConfirmationActivity:b006Dmm006Dm006Dmm006D	I
    //   679: istore_2
    //   680: iload_2
    //   681: getstatic 74	com/db/pwcc/dbmobile/transfer/standingorder/confirm/StandingOrderConfirmationActivity:b006D006D006D006Dm006Dmm006D	I
    //   684: iload_2
    //   685: iadd
    //   686: imul
    //   687: getstatic 76	com/db/pwcc/dbmobile/transfer/standingorder/confirm/StandingOrderConfirmationActivity:bmm006D006Dm006Dmm006D	I
    //   690: irem
    //   691: tableswitch	default:+17->708, 0:+28->719
    //   708: bipush 43
    //   710: putstatic 72	com/db/pwcc/dbmobile/transfer/standingorder/confirm/StandingOrderConfirmationActivity:b006Dmm006Dm006Dmm006D	I
    //   713: invokestatic 90	com/db/pwcc/dbmobile/transfer/standingorder/confirm/StandingOrderConfirmationActivity:b006Dm006D006Dm006Dmm006D	()I
    //   716: putstatic 80	com/db/pwcc/dbmobile/transfer/standingorder/confirm/StandingOrderConfirmationActivity:bm006Dm006Dm006Dmm006D	I
    //   719: aload 6
    //   721: aload 7
    //   723: invokevirtual 132	java/lang/String:equals	(Ljava/lang/Object;)Z
    //   726: ifeq +44 -> 770
    //   729: aload_3
    //   730: aload 8
    //   732: aload_0
    //   733: aload_0
    //   734: getfield 54	com/db/pwcc/dbmobile/transfer/standingorder/confirm/StandingOrderConfirmationActivity:standingOrderTemplate	Lcom/db/pwcc/dbmobile/transfer/standingorder/model/StandingOrderTemplate;
    //   737: invokevirtual 784	com/db/pwcc/dbmobile/transfer/standingorder/model/StandingOrderTemplate:getValidFrom	()Ljava/lang/String;
    //   740: invokespecial 786	com/db/pwcc/dbmobile/transfer/standingorder/confirm/StandingOrderConfirmationActivity:parseTemplateDateString	(Ljava/lang/String;)Ljava/util/Date;
    //   743: invokestatic 420	uuuuuu/pqpppq:b006Bkkk006B006Bkkkk	(Ljava/util/Locale;Ljava/util/Date;)Ljava/lang/String;
    //   746: invokevirtual 271	android/widget/TextView:setText	(Ljava/lang/CharSequence;)V
    //   749: aload_0
    //   750: aload 4
    //   752: aload_0
    //   753: getfield 54	com/db/pwcc/dbmobile/transfer/standingorder/confirm/StandingOrderConfirmationActivity:standingOrderTemplate	Lcom/db/pwcc/dbmobile/transfer/standingorder/model/StandingOrderTemplate;
    //   756: invokespecial 788	com/db/pwcc/dbmobile/transfer/standingorder/confirm/StandingOrderConfirmationActivity:setFormattedFrequencyText	(Landroid/widget/TextView;Lcom/db/pwcc/dbmobile/transfer/standingorder/model/StandingOrderTemplate;)V
    //   759: aload_0
    //   760: aload 5
    //   762: aload_0
    //   763: getfield 54	com/db/pwcc/dbmobile/transfer/standingorder/confirm/StandingOrderConfirmationActivity:standingOrderTemplate	Lcom/db/pwcc/dbmobile/transfer/standingorder/model/StandingOrderTemplate;
    //   766: invokespecial 790	com/db/pwcc/dbmobile/transfer/standingorder/confirm/StandingOrderConfirmationActivity:setValidUntilText	(Landroid/widget/TextView;Lcom/db/pwcc/dbmobile/transfer/standingorder/model/StandingOrderTemplate;)V
    //   769: return
    //   770: aload_3
    //   771: aload 8
    //   773: aload_1
    //   774: invokevirtual 792	com/db/pwcc/dbmobile/transfer/standingorder/model/StandingOrderTransaction:getValidFrom	()Ljava/util/Date;
    //   777: invokestatic 420	uuuuuu/pqpppq:b006Bkkk006B006Bkkkk	(Ljava/util/Locale;Ljava/util/Date;)Ljava/lang/String;
    //   780: invokevirtual 271	android/widget/TextView:setText	(Ljava/lang/CharSequence;)V
    //   783: aload_0
    //   784: aload 4
    //   786: aload_1
    //   787: invokespecial 794	com/db/pwcc/dbmobile/transfer/standingorder/confirm/StandingOrderConfirmationActivity:setFormattedFrequencyText	(Landroid/widget/TextView;Lcom/db/pwcc/dbmobile/transfer/standingorder/model/StandingOrderTransaction;)V
    //   790: aload_1
    //   791: invokevirtual 796	com/db/pwcc/dbmobile/transfer/standingorder/model/StandingOrderTransaction:getValidUntil	()Ljava/util/Date;
    //   794: ifnonnull +38 -> 832
    //   797: aload 5
    //   799: getstatic 416	com/db/pwcc/dbmobile/transfer/R$string:standing_order_valid_unlimited	I
    //   802: invokevirtual 323	android/widget/TextView:setText	(I)V
    //   805: return
    //   806: aload 9
    //   808: bipush 8
    //   810: invokevirtual 799	android/widget/TextView:setVisibility	(I)V
    //   813: goto -341 -> 472
    //   816: aload 11
    //   818: bipush 8
    //   820: invokevirtual 799	android/widget/TextView:setVisibility	(I)V
    //   823: goto -299 -> 524
    //   826: astore_1
    //   827: aload_1
    //   828: invokevirtual 136	java/lang/reflect/InvocationTargetException:getCause	()Ljava/lang/Throwable;
    //   831: athrow
    //   832: aload 5
    //   834: aload 8
    //   836: aload_1
    //   837: invokevirtual 796	com/db/pwcc/dbmobile/transfer/standingorder/model/StandingOrderTransaction:getValidUntil	()Ljava/util/Date;
    //   840: invokestatic 420	uuuuuu/pqpppq:b006Bkkk006B006Bkkkk	(Ljava/util/Locale;Ljava/util/Date;)Ljava/lang/String;
    //   843: invokevirtual 271	android/widget/TextView:setText	(Ljava/lang/CharSequence;)V
    //   846: invokestatic 90	com/db/pwcc/dbmobile/transfer/standingorder/confirm/StandingOrderConfirmationActivity:b006Dm006D006Dm006Dmm006D	()I
    //   849: istore_2
    //   850: iload_2
    //   851: getstatic 74	com/db/pwcc/dbmobile/transfer/standingorder/confirm/StandingOrderConfirmationActivity:b006D006D006D006Dm006Dmm006D	I
    //   854: iload_2
    //   855: iadd
    //   856: imul
    //   857: invokestatic 149	com/db/pwcc/dbmobile/transfer/standingorder/confirm/StandingOrderConfirmationActivity:bmmmm006D006Dmm006D	()I
    //   860: irem
    //   861: tableswitch	default:+19->880, 0:+-92->769
    //   880: bipush 28
    //   882: putstatic 72	com/db/pwcc/dbmobile/transfer/standingorder/confirm/StandingOrderConfirmationActivity:b006Dmm006Dm006Dmm006D	I
    //   885: bipush 74
    //   887: putstatic 80	com/db/pwcc/dbmobile/transfer/standingorder/confirm/StandingOrderConfirmationActivity:bm006Dm006Dm006Dmm006D	I
    //   890: return
    //   891: astore_1
    //   892: aload_1
    //   893: invokevirtual 136	java/lang/reflect/InvocationTargetException:getCause	()Ljava/lang/Throwable;
    //   896: athrow
    //   897: aload 10
    //   899: bipush 8
    //   901: invokevirtual 799	android/widget/TextView:setVisibility	(I)V
    //   904: goto -406 -> 498
    //   907: astore_1
    //   908: aload_1
    //   909: invokevirtual 136	java/lang/reflect/InvocationTargetException:getCause	()Ljava/lang/Throwable;
    //   912: athrow
    // Local variable table:
    //   start	length	slot	name	signature
    //   0	913	0	this	StandingOrderConfirmationActivity
    //   0	913	1	paramStandingOrderRequestResponse	StandingOrderRequestResponse
    //   87	770	2	i	int
    //   137	634	3	localTextView1	TextView
    //   148	637	4	localTextView2	TextView
    //   160	673	5	localTextView3	TextView
    //   70	650	6	localObject1	Object
    //   82	640	7	localObject2	Object
    //   22	813	8	localObject3	Object
    //   34	773	9	localTextView4	TextView
    //   46	852	10	localTextView5	TextView
    //   58	759	11	localTextView6	TextView
    //   191	303	12	str1	String
    //   197	323	13	str2	String
    //   10	450	14	localObject4	Object
    //   203	259	15	localObject5	Object
    //   241	14	16	str3	String
    // Exception table:
    //   from	to	target	type
    //   414	457	826	java/lang/reflect/InvocationTargetException
    //   309	351	891	java/lang/reflect/InvocationTargetException
    //   620	663	907	java/lang/reflect/InvocationTargetException
  }
  
  public void showTanError(int paramInt)
  {
    TanModule localTanModule = this.tanModule;
    int i = b006Dmm006Dm006Dmm006D;
    int j = b006D006D006D006Dm006Dmm006D;
    int k = b006Dmm006Dm006Dmm006D;
    switch (k * (b006D006D006D006Dm006Dmm006D + k) % bmm006D006Dm006Dmm006D)
    {
    default: 
      b006Dmm006Dm006Dmm006D = 42;
      bm006Dm006Dm006Dmm006D = b006Dm006D006Dm006Dmm006D();
      k = b006Dmm006Dm006Dmm006D;
      switch (k * (b006D006Dm006Dm006Dmm006D() + k) % bmm006D006Dm006Dmm006D)
      {
      default: 
        b006Dmm006Dm006Dmm006D = 7;
        bm006Dm006Dm006Dmm006D = 0;
      }
      break;
    }
    switch (i * (j + i) % bmm006D006Dm006Dmm006D)
    {
    default: 
      i = b006Dm006D006Dm006Dmm006D();
      if ((b006Dm006D006Dm006Dmm006D() + b006D006D006D006Dm006Dmm006D) * b006Dm006D006Dm006Dmm006D() % bmm006D006Dm006Dmm006D != bm006Dm006Dm006Dmm006D)
      {
        b006Dmm006Dm006Dmm006D = 90;
        bm006Dm006Dm006Dmm006D = 30;
      }
      b006Dmm006Dm006Dmm006D = i;
      bm006Dm006Dm006Dmm006D = 55;
    }
    localTanModule.showErrorLayoutView(paramInt);
  }
  
  public void showTanError(AuthorizationStatus paramAuthorizationStatus)
  {
    this.tanModule.showErrorLayoutView(paramAuthorizationStatus);
    if ((b006Dmm006Dm006Dmm006D + b006D006D006D006Dm006Dmm006D) * b006Dmm006Dm006Dmm006D % bmm006D006Dm006Dmm006D != bm006D006D006Dm006Dmm006D())
    {
      int i = b006Dm006D006Dm006Dmm006D();
      switch (i * (b006D006D006D006Dm006Dmm006D + i) % bmm006D006Dm006Dmm006D)
      {
      default: 
        b006Dmm006Dm006Dmm006D = b006Dm006D006Dm006Dmm006D();
        bm006Dm006Dm006Dmm006D = 10;
      }
      if ((b006Dmm006Dm006Dmm006D + b006D006Dm006Dm006Dmm006D()) * b006Dmm006Dm006Dmm006D % bmmmm006D006Dmm006D() != bm006Dm006Dm006Dmm006D)
      {
        b006Dmm006Dm006Dmm006D = 78;
        bm006Dm006Dm006Dmm006D = 90;
        if ((b006Dmm006Dm006Dmm006D + b006D006Dm006Dm006Dmm006D()) * b006Dmm006Dm006Dmm006D % bmm006D006Dm006Dmm006D != bm006Dm006Dm006Dmm006D)
        {
          b006Dmm006Dm006Dmm006D = b006Dm006D006Dm006Dmm006D();
          bm006Dm006Dm006Dmm006D = 40;
        }
      }
      b006Dmm006Dm006Dmm006D = 98;
      bm006Dm006Dm006Dmm006D = 52;
    }
  }
  
  public void showTanSuccess(Date paramDate)
  {
    int i = 0;
    TanModule localTanModule = this.tanModule;
    if ((b006Dmm006Dm006Dmm006D + b006D006Dm006Dm006Dmm006D()) * b006Dmm006Dm006Dmm006D % bmm006D006Dm006Dmm006D != bm006Dm006Dm006Dmm006D)
    {
      if ((b006Dmm006Dm006Dmm006D + b006D006D006D006Dm006Dmm006D) * b006Dmm006Dm006Dmm006D % bmm006D006Dm006Dmm006D != bm006Dm006Dm006Dmm006D)
      {
        b006Dmm006Dm006Dmm006D = b006Dm006D006Dm006Dmm006D();
        bm006Dm006Dm006Dmm006D = b006Dm006D006Dm006Dmm006D();
      }
      b006Dmm006Dm006Dmm006D = 43;
      bm006Dm006Dm006Dmm006D = b006Dm006D006Dm006Dmm006D();
    }
    localTanModule.showSuccessLayoutView(paramDate);
    try
    {
      for (;;)
      {
        i /= 0;
      }
      return;
    }
    catch (Exception paramDate)
    {
      b006Dmm006Dm006Dmm006D = 2;
      i = b006Dmm006Dm006Dmm006D;
      switch (i * (b006D006D006D006Dm006Dmm006D + i) % bmm006D006Dm006Dmm006D)
      {
      default: 
        b006Dmm006Dm006Dmm006D = b006Dm006D006Dm006Dmm006D();
        bm006Dm006Dm006Dmm006D = 61;
      }
    }
  }
}
