package com.google.zxing.a;

import com.google.zxing.l;

public final class b
  implements l
{
  public b() {}
  
  /* Error */
  public final com.google.zxing.m a(com.google.zxing.c paramC, java.util.Map<com.google.zxing.d, ?> paramMap)
    throws com.google.zxing.NotFoundException, com.google.zxing.FormatException
  {
    // Byte code:
    //   0: aconst_null
    //   1: astore 7
    //   3: new 19	com/google/zxing/a/b/a
    //   6: dup
    //   7: aload_1
    //   8: invokevirtual 24	com/google/zxing/c:a	()Lcom/google/zxing/common/b;
    //   11: invokespecial 27	com/google/zxing/a/b/a:<init>	(Lcom/google/zxing/common/b;)V
    //   14: astore 9
    //   16: aload 9
    //   18: iconst_0
    //   19: invokevirtual 30	com/google/zxing/a/b/a:a	(Z)Lcom/google/zxing/a/a;
    //   22: astore_1
    //   23: aload_1
    //   24: getfield 36	com/google/zxing/common/g:e	[Lcom/google/zxing/o;
    //   27: astore 5
    //   29: new 38	com/google/zxing/a/a/a
    //   32: dup
    //   33: invokespecial 39	com/google/zxing/a/a/a:<init>	()V
    //   36: aload_1
    //   37: invokevirtual 42	com/google/zxing/a/a/a:a	(Lcom/google/zxing/a/a;)Lcom/google/zxing/common/e;
    //   40: astore_1
    //   41: aconst_null
    //   42: astore 6
    //   44: aload_1
    //   45: ifnonnull +216 -> 261
    //   48: aload 9
    //   50: iconst_1
    //   51: invokevirtual 30	com/google/zxing/a/b/a:a	(Z)Lcom/google/zxing/a/a;
    //   54: astore_1
    //   55: aload_1
    //   56: getfield 36	com/google/zxing/common/g:e	[Lcom/google/zxing/o;
    //   59: astore 5
    //   61: new 38	com/google/zxing/a/a/a
    //   64: dup
    //   65: invokespecial 39	com/google/zxing/a/a/a:<init>	()V
    //   68: aload_1
    //   69: invokevirtual 42	com/google/zxing/a/a/a:a	(Lcom/google/zxing/a/a;)Lcom/google/zxing/common/e;
    //   72: astore_1
    //   73: aload_2
    //   74: ifnull +119 -> 193
    //   77: aload_2
    //   78: getstatic 48	com/google/zxing/d:j	Lcom/google/zxing/d;
    //   81: invokeinterface 54 2 0
    //   86: checkcast 56	com/google/zxing/p
    //   89: astore_2
    //   90: aload_2
    //   91: ifnull +102 -> 193
    //   94: aload 5
    //   96: arraylength
    //   97: istore 4
    //   99: iconst_0
    //   100: istore_3
    //   101: iload_3
    //   102: iload 4
    //   104: if_icmpge +89 -> 193
    //   107: aload_2
    //   108: aload 5
    //   110: iload_3
    //   111: aaload
    //   112: invokeinterface 59 2 0
    //   117: iload_3
    //   118: iconst_1
    //   119: iadd
    //   120: istore_3
    //   121: goto -20 -> 101
    //   124: astore_1
    //   125: aconst_null
    //   126: astore 5
    //   128: aload_1
    //   129: astore 6
    //   131: aconst_null
    //   132: astore_1
    //   133: goto -89 -> 44
    //   136: astore_1
    //   137: aconst_null
    //   138: astore 5
    //   140: aconst_null
    //   141: astore 6
    //   143: aconst_null
    //   144: astore 8
    //   146: aload_1
    //   147: astore 7
    //   149: aload 8
    //   151: astore_1
    //   152: goto -108 -> 44
    //   155: astore_1
    //   156: aload 6
    //   158: ifnull +6 -> 164
    //   161: aload 6
    //   163: athrow
    //   164: aload 7
    //   166: ifnull +6 -> 172
    //   169: aload 7
    //   171: athrow
    //   172: aload_1
    //   173: athrow
    //   174: astore_1
    //   175: aload 6
    //   177: ifnull +6 -> 183
    //   180: aload 6
    //   182: athrow
    //   183: aload 7
    //   185: ifnull +6 -> 191
    //   188: aload 7
    //   190: athrow
    //   191: aload_1
    //   192: athrow
    //   193: new 61	com/google/zxing/m
    //   196: dup
    //   197: aload_1
    //   198: getfield 67	com/google/zxing/common/e:b	Ljava/lang/String;
    //   201: aload_1
    //   202: getfield 70	com/google/zxing/common/e:a	[B
    //   205: aload 5
    //   207: getstatic 75	com/google/zxing/a:a	Lcom/google/zxing/a;
    //   210: invokespecial 78	com/google/zxing/m:<init>	(Ljava/lang/String;[B[Lcom/google/zxing/o;Lcom/google/zxing/a;)V
    //   213: astore_2
    //   214: aload_1
    //   215: getfield 82	com/google/zxing/common/e:c	Ljava/util/List;
    //   218: astore 5
    //   220: aload 5
    //   222: ifnull +12 -> 234
    //   225: aload_2
    //   226: getstatic 87	com/google/zxing/n:c	Lcom/google/zxing/n;
    //   229: aload 5
    //   231: invokevirtual 90	com/google/zxing/m:a	(Lcom/google/zxing/n;Ljava/lang/Object;)V
    //   234: aload_1
    //   235: getfield 93	com/google/zxing/common/e:d	Ljava/lang/String;
    //   238: astore_1
    //   239: aload_1
    //   240: ifnull +11 -> 251
    //   243: aload_2
    //   244: getstatic 95	com/google/zxing/n:d	Lcom/google/zxing/n;
    //   247: aload_1
    //   248: invokevirtual 90	com/google/zxing/m:a	(Lcom/google/zxing/n;Ljava/lang/Object;)V
    //   251: aload_2
    //   252: areturn
    //   253: astore_1
    //   254: goto -114 -> 140
    //   257: astore_1
    //   258: goto -130 -> 128
    //   261: goto -188 -> 73
    // Local variable table:
    //   start	length	slot	name	signature
    //   0	264	0	this	b
    //   0	264	1	paramC	com.google.zxing.c
    //   0	264	2	paramMap	java.util.Map<com.google.zxing.d, ?>
    //   100	21	3	i	int
    //   97	8	4	j	int
    //   27	203	5	localObject1	Object
    //   42	139	6	localC1	com.google.zxing.c
    //   1	188	7	localC2	com.google.zxing.c
    //   144	6	8	localObject2	Object
    //   14	35	9	localA	com.google.zxing.a.b.a
    // Exception table:
    //   from	to	target	type
    //   16	29	124	com/google/zxing/NotFoundException
    //   16	29	136	com/google/zxing/FormatException
    //   48	73	155	com/google/zxing/NotFoundException
    //   48	73	174	com/google/zxing/FormatException
    //   29	41	253	com/google/zxing/FormatException
    //   29	41	257	com/google/zxing/NotFoundException
  }
  
  public final void a() {}
}
