package com.mobile.business.ics.model;

import android.os.Parcel;
import android.os.Parcelable;
import android.os.Parcelable.Creator;
import com.mobile.business.statements.model.AmountDomainModel;
import kkkkkk.ooiiio;
import kkkkkk.pppppd;
import kkkkkk.uluulu;
import org.threeten.bp.ZonedDateTime;

public class IcsDepositChequeDomainModel
  implements Parcelable
{
  public static final Parcelable.Creator<IcsDepositChequeDomainModel> CREATOR = new Parcelable.Creator()
  {
    public static int b04350435е0435ееее0435 = 1;
    public static int b0435ее0435ееее0435 = 2;
    public static int bе0435е0435ееее0435 = 0;
    public static int bеее0435ееее0435 = 49;
    
    public static int b04120412В0412041204120412В04120412()
    {
      return 1;
    }
    
    public static int b0412ВВ0412041204120412В04120412()
    {
      return 0;
    }
    
    public static int bВ0412В0412041204120412В04120412()
    {
      return 18;
    }
    
    /* Error */
    @ooiiio
    public IcsDepositChequeDomainModel[] b0412В04120412041204120412В04120412(int paramAnonymousInt)
    {
      // Byte code:
      //   0: iload_1
      //   1: anewarray 9	com/mobile/business/ics/model/IcsDepositChequeDomainModel
      //   4: astore 6
      //   6: getstatic 34	com/mobile/business/ics/model/IcsDepositChequeDomainModel$1:bеее0435ееее0435	I
      //   9: istore_1
      //   10: getstatic 36	com/mobile/business/ics/model/IcsDepositChequeDomainModel$1:b04350435е0435ееее0435	I
      //   13: istore_2
      //   14: getstatic 34	com/mobile/business/ics/model/IcsDepositChequeDomainModel$1:bеее0435ееее0435	I
      //   17: istore_3
      //   18: getstatic 38	com/mobile/business/ics/model/IcsDepositChequeDomainModel$1:b0435ее0435ееее0435	I
      //   21: istore 4
      //   23: getstatic 40	com/mobile/business/ics/model/IcsDepositChequeDomainModel$1:bе0435е0435ееее0435	I
      //   26: istore 5
      //   28: iload_1
      //   29: iload_2
      //   30: iadd
      //   31: iload_3
      //   32: imul
      //   33: iload 4
      //   35: irem
      //   36: iload 5
      //   38: if_icmpeq +48 -> 86
      //   41: getstatic 34	com/mobile/business/ics/model/IcsDepositChequeDomainModel$1:bеее0435ееее0435	I
      //   44: getstatic 36	com/mobile/business/ics/model/IcsDepositChequeDomainModel$1:b04350435е0435ееее0435	I
      //   47: iadd
      //   48: getstatic 34	com/mobile/business/ics/model/IcsDepositChequeDomainModel$1:bеее0435ееее0435	I
      //   51: imul
      //   52: getstatic 38	com/mobile/business/ics/model/IcsDepositChequeDomainModel$1:b0435ее0435ееее0435	I
      //   55: irem
      //   56: invokestatic 42	com/mobile/business/ics/model/IcsDepositChequeDomainModel$1:b0412ВВ0412041204120412В04120412	()I
      //   59: if_icmpeq +13 -> 72
      //   62: bipush 24
      //   64: putstatic 34	com/mobile/business/ics/model/IcsDepositChequeDomainModel$1:bеее0435ееее0435	I
      //   67: bipush 75
      //   69: putstatic 40	com/mobile/business/ics/model/IcsDepositChequeDomainModel$1:bе0435е0435ееее0435	I
      //   72: invokestatic 44	com/mobile/business/ics/model/IcsDepositChequeDomainModel$1:bВ0412В0412041204120412В04120412	()I
      //   75: putstatic 34	com/mobile/business/ics/model/IcsDepositChequeDomainModel$1:bеее0435ееее0435	I
      //   78: invokestatic 44	com/mobile/business/ics/model/IcsDepositChequeDomainModel$1:bВ0412В0412041204120412В04120412	()I
      //   81: istore_1
      //   82: iload_1
      //   83: putstatic 40	com/mobile/business/ics/model/IcsDepositChequeDomainModel$1:bе0435е0435ееее0435	I
      //   86: aload 6
      //   88: areturn
      //   89: astore 6
      //   91: aload 6
      //   93: athrow
      //   94: astore 6
      //   96: aload 6
      //   98: athrow
      //   99: astore 6
      //   101: aload 6
      //   103: athrow
      // Local variable table:
      //   start	length	slot	name	signature
      //   0	104	0	this	1
      //   0	104	1	paramAnonymousInt	int
      //   13	18	2	i	int
      //   17	16	3	j	int
      //   21	15	4	k	int
      //   26	13	5	m	int
      //   4	83	6	arrayOfIcsDepositChequeDomainModel	IcsDepositChequeDomainModel[]
      //   89	3	6	localException1	Exception
      //   94	3	6	localException2	Exception
      //   99	3	6	localException3	Exception
      // Exception table:
      //   from	to	target	type
      //   0	6	89	java/lang/Exception
      //   6	28	94	java/lang/Exception
      //   78	82	94	java/lang/Exception
      //   91	94	94	java/lang/Exception
      //   72	78	99	java/lang/Exception
      //   82	86	99	java/lang/Exception
    }
    
    @ooiiio
    public IcsDepositChequeDomainModel bВВ04120412041204120412В04120412(Parcel paramAnonymousParcel)
    {
      if ((bеее0435ееее0435 + b04120412В0412041204120412В04120412()) * bеее0435ееее0435 % b0435ее0435ееее0435 != b0412ВВ0412041204120412В04120412())
      {
        bеее0435ееее0435 = bВ0412В0412041204120412В04120412();
        b0435ее0435ееее0435 = bВ0412В0412041204120412В04120412();
      }
      try
      {
        paramAnonymousParcel = new IcsDepositChequeDomainModel(paramAnonymousParcel);
        return paramAnonymousParcel;
      }
      catch (Exception paramAnonymousParcel)
      {
        throw paramAnonymousParcel;
      }
    }
  };
  public static int b04100410А0410А04100410А = 2;
  public static int b0410А04100410А04100410А = 0;
  public static int b0410АА0410А04100410А = 79;
  public static int bА0410А0410А04100410А = 1;
  private AmountDomainModel mAvailableBalance;
  private String mChequeStatus;
  private ZonedDateTime mClearingDate;
  private String[] mErrorMessages;
  private ZonedDateTime mProcessingDate;
  private String mTransactionId;
  
  static
  {
    int i = b0410АА0410А04100410А;
    switch (0)
    {
    case 1: 
    default: 
      for (;;)
      {
        switch (1)
        {
        }
      }
    }
    int j = bА0410А0410А04100410А;
    if ((b0410АА0410А04100410А + bА0410А0410А04100410А) * b0410АА0410А04100410А % bА041004100410А04100410А() != b0410А04100410А04100410А)
    {
      b0410АА0410А04100410А = bАА04100410А04100410А();
      b0410А04100410А04100410А = 34;
    }
    switch (i * (j + i) % b04100410А0410А04100410А)
    {
    default: 
      b0410АА0410А04100410А = bАА04100410А04100410А();
      bА0410А0410А04100410А = 22;
    }
  }
  
  public IcsDepositChequeDomainModel() {}
  
  @ooiiio
  public IcsDepositChequeDomainModel(Parcel paramParcel)
  {
    this.mAvailableBalance = ((AmountDomainModel)paramParcel.readParcelable(AmountDomainModel.class.getClassLoader()));
    this.mChequeStatus = paramParcel.readString();
    this.mTransactionId = paramParcel.readString();
    this.mErrorMessages = new String[paramParcel.readInt()];
    paramParcel.readStringArray(this.mErrorMessages);
    this.mProcessingDate = ZonedDateTime.parse(paramParcel.readString());
    this.mClearingDate = ZonedDateTime.parse(paramParcel.readString());
  }
  
  public static int b0410ААА041004100410А()
  {
    return 1;
  }
  
  public static int bА041004100410А04100410А()
  {
    return 2;
  }
  
  public static int bАА04100410А04100410А()
  {
    return 26;
  }
  
  @ooiiio
  public static IcsDepositChequeDomainModel fromIcsDepositCheque(uluulu paramUluulu)
  {
    IcsDepositChequeDomainModel localIcsDepositChequeDomainModel = new IcsDepositChequeDomainModel();
    localIcsDepositChequeDomainModel.setAvailableBalance(AmountDomainModel.fromBalance(paramUluulu.b0412041204120412ВВ0412В04120412()));
    switch (0)
    {
    case 1: 
    default: 
      for (;;)
      {
        switch (1)
        {
        }
      }
    }
    if ((b0410АА0410А04100410А + bА0410А0410А04100410А) * b0410АА0410А04100410А % bА041004100410А04100410А() != b0410А04100410А04100410А)
    {
      b0410АА0410А04100410А = bАА04100410А04100410А();
      b0410А04100410А04100410А = bАА04100410А04100410А();
      if ((b0410АА0410А04100410А + bА0410А0410А04100410А) * b0410АА0410А04100410А % b04100410А0410А04100410А != b0410А04100410А04100410А)
      {
        b0410АА0410А04100410А = bАА04100410А04100410А();
        b0410А04100410А04100410А = 7;
      }
    }
    localIcsDepositChequeDomainModel.setChequeStatus(paramUluulu.bВВВВ0412В0412В04120412());
    localIcsDepositChequeDomainModel.setClearingDate(paramUluulu.b0412ВВВ0412В0412В04120412());
    localIcsDepositChequeDomainModel.setErrorMessages(paramUluulu.bВ0412ВВ0412В0412В04120412());
    localIcsDepositChequeDomainModel.setProcessingDate(paramUluulu.b04120412ВВ0412В0412В04120412());
    localIcsDepositChequeDomainModel.setTransactionId(paramUluulu.bВВ0412В0412В0412В04120412());
    return localIcsDepositChequeDomainModel;
  }
  
  @ooiiio
  public int describeContents()
  {
    return 0;
  }
  
  public AmountDomainModel getAvailableBalance()
  {
    AmountDomainModel localAmountDomainModel = this.mAvailableBalance;
    if ((b0410АА0410А04100410А + bА0410А0410А04100410А) * b0410АА0410А04100410А % bА041004100410А04100410А() != b0410А04100410А04100410А)
    {
      b0410АА0410А04100410А = 15;
      b0410А04100410А04100410А = 45;
    }
    return localAmountDomainModel;
  }
  
  public String getChequeStatus()
  {
    switch (0)
    {
    case 1: 
    default: 
      for (;;)
      {
        switch (0)
        {
        }
      }
    }
    String str = this.mChequeStatus;
    if ((b0410АА0410А04100410А + bА0410А0410А04100410А) * b0410АА0410А04100410А % b04100410А0410А04100410А != b0410А04100410А04100410А)
    {
      int i = b0410АА0410А04100410А;
      switch (i * (bА0410А0410А04100410А + i) % b04100410А0410А04100410А)
      {
      default: 
        b0410АА0410А04100410А = 26;
        b0410А04100410А04100410А = bАА04100410А04100410А();
      }
      b0410АА0410А04100410А = 33;
      b0410А04100410А04100410А = 16;
    }
    return str;
  }
  
  public ZonedDateTime getClearingDate()
  {
    try
    {
      ZonedDateTime localZonedDateTime = this.mClearingDate;
      int i = b0410АА0410А04100410А;
      switch (i * (bА0410А0410А04100410А + i) % b04100410А0410А04100410А)
      {
      default: 
        b0410АА0410А04100410А = bАА04100410А04100410А();
        b0410А04100410А04100410А = bАА04100410А04100410А();
      }
      return localZonedDateTime;
    }
    catch (Exception localException1)
    {
      try
      {
        throw localException1;
      }
      catch (Exception localException2)
      {
        throw localException2;
      }
    }
  }
  
  @ooiiio
  public String[] getErrorMessages()
  {
    if ((b0410АА0410А04100410А + bА0410А0410А04100410А) * b0410АА0410А04100410А % b04100410А0410А04100410А != b0410А04100410А04100410А)
    {
      b0410АА0410А04100410А = bАА04100410А04100410А();
      if ((b0410АА0410А04100410А + bА0410А0410А04100410А) * b0410АА0410А04100410А % b04100410А0410А04100410А != b0410А04100410А04100410А)
      {
        b0410АА0410А04100410А = bАА04100410А04100410А();
        b0410А04100410А04100410А = 28;
      }
      b0410А04100410А04100410А = 96;
    }
    String[] arrayOfString = this.mErrorMessages;
    switch (1)
    {
    case 0: 
    default: 
      for (;;)
      {
        switch (1)
        {
        }
      }
    }
    return (String[])pppppd.b043004300430ааааа0430а(arrayOfString);
  }
  
  /* Error */
  public ZonedDateTime getProcessingDate()
  {
    // Byte code:
    //   0: iconst_3
    //   1: istore_1
    //   2: iload_1
    //   3: iconst_0
    //   4: idiv
    //   5: istore_2
    //   6: iload_2
    //   7: istore_1
    //   8: getstatic 39	com/mobile/business/ics/model/IcsDepositChequeDomainModel:b0410АА0410А04100410А	I
    //   11: invokestatic 172	com/mobile/business/ics/model/IcsDepositChequeDomainModel:b0410ААА041004100410А	()I
    //   14: iadd
    //   15: getstatic 39	com/mobile/business/ics/model/IcsDepositChequeDomainModel:b0410АА0410А04100410А	I
    //   18: imul
    //   19: invokestatic 45	com/mobile/business/ics/model/IcsDepositChequeDomainModel:bА041004100410А04100410А	()I
    //   22: irem
    //   23: getstatic 47	com/mobile/business/ics/model/IcsDepositChequeDomainModel:b0410А04100410А04100410А	I
    //   26: if_icmpeq -24 -> 2
    //   29: iconst_0
    //   30: putstatic 39	com/mobile/business/ics/model/IcsDepositChequeDomainModel:b0410АА0410А04100410А	I
    //   33: invokestatic 50	com/mobile/business/ics/model/IcsDepositChequeDomainModel:bАА04100410А04100410А	()I
    //   36: putstatic 47	com/mobile/business/ics/model/IcsDepositChequeDomainModel:b0410А04100410А04100410А	I
    //   39: iload_2
    //   40: istore_1
    //   41: goto -39 -> 2
    //   44: astore_3
    //   45: invokestatic 50	com/mobile/business/ics/model/IcsDepositChequeDomainModel:bАА04100410А04100410А	()I
    //   48: istore_2
    //   49: iload_2
    //   50: putstatic 39	com/mobile/business/ics/model/IcsDepositChequeDomainModel:b0410АА0410А04100410А	I
    //   53: iload_1
    //   54: iconst_0
    //   55: idiv
    //   56: istore_1
    //   57: goto -4 -> 53
    //   60: astore_3
    //   61: bipush 47
    //   63: putstatic 39	com/mobile/business/ics/model/IcsDepositChequeDomainModel:b0410АА0410А04100410А	I
    //   66: aload_0
    //   67: getfield 99	com/mobile/business/ics/model/IcsDepositChequeDomainModel:mProcessingDate	Lorg/threeten/bp/ZonedDateTime;
    //   70: astore_3
    //   71: aload_3
    //   72: areturn
    //   73: astore_3
    //   74: aload_3
    //   75: athrow
    //   76: astore_3
    //   77: aload_3
    //   78: athrow
    //   79: astore_3
    //   80: aload_3
    //   81: athrow
    // Local variable table:
    //   start	length	slot	name	signature
    //   0	82	0	this	IcsDepositChequeDomainModel
    //   1	56	1	i	int
    //   5	45	2	j	int
    //   44	1	3	localException1	Exception
    //   60	1	3	localException2	Exception
    //   70	2	3	localZonedDateTime	ZonedDateTime
    //   73	2	3	localException3	Exception
    //   76	2	3	localException4	Exception
    //   79	2	3	localException5	Exception
    // Exception table:
    //   from	to	target	type
    //   2	6	44	java/lang/Exception
    //   53	57	60	java/lang/Exception
    //   66	71	73	java/lang/Exception
    //   49	53	76	java/lang/Exception
    //   74	76	76	java/lang/Exception
    //   45	49	79	java/lang/Exception
    //   61	66	79	java/lang/Exception
  }
  
  /* Error */
  public String getTransactionId()
  {
    // Byte code:
    //   0: aload_0
    //   1: getfield 80	com/mobile/business/ics/model/IcsDepositChequeDomainModel:mTransactionId	Ljava/lang/String;
    //   4: astore 4
    //   6: getstatic 39	com/mobile/business/ics/model/IcsDepositChequeDomainModel:b0410АА0410А04100410А	I
    //   9: istore_1
    //   10: getstatic 41	com/mobile/business/ics/model/IcsDepositChequeDomainModel:bА0410А0410А04100410А	I
    //   13: istore_2
    //   14: invokestatic 45	com/mobile/business/ics/model/IcsDepositChequeDomainModel:bА041004100410А04100410А	()I
    //   17: istore_3
    //   18: iload_1
    //   19: iload_2
    //   20: iload_1
    //   21: iadd
    //   22: imul
    //   23: iload_3
    //   24: irem
    //   25: tableswitch	default:+19->44, 0:+63->88
    //   44: getstatic 39	com/mobile/business/ics/model/IcsDepositChequeDomainModel:b0410АА0410А04100410А	I
    //   47: getstatic 41	com/mobile/business/ics/model/IcsDepositChequeDomainModel:bА0410А0410А04100410А	I
    //   50: iadd
    //   51: getstatic 39	com/mobile/business/ics/model/IcsDepositChequeDomainModel:b0410АА0410А04100410А	I
    //   54: imul
    //   55: getstatic 52	com/mobile/business/ics/model/IcsDepositChequeDomainModel:b04100410А0410А04100410А	I
    //   58: irem
    //   59: getstatic 47	com/mobile/business/ics/model/IcsDepositChequeDomainModel:b0410А04100410А04100410А	I
    //   62: if_icmpeq +15 -> 77
    //   65: invokestatic 50	com/mobile/business/ics/model/IcsDepositChequeDomainModel:bАА04100410А04100410А	()I
    //   68: putstatic 39	com/mobile/business/ics/model/IcsDepositChequeDomainModel:b0410АА0410А04100410А	I
    //   71: invokestatic 50	com/mobile/business/ics/model/IcsDepositChequeDomainModel:bАА04100410А04100410А	()I
    //   74: putstatic 47	com/mobile/business/ics/model/IcsDepositChequeDomainModel:b0410А04100410А04100410А	I
    //   77: bipush 95
    //   79: putstatic 39	com/mobile/business/ics/model/IcsDepositChequeDomainModel:b0410АА0410А04100410А	I
    //   82: invokestatic 50	com/mobile/business/ics/model/IcsDepositChequeDomainModel:bАА04100410А04100410А	()I
    //   85: putstatic 47	com/mobile/business/ics/model/IcsDepositChequeDomainModel:b0410А04100410А04100410А	I
    //   88: aload 4
    //   90: areturn
    //   91: astore 4
    //   93: aload 4
    //   95: athrow
    //   96: astore 4
    //   98: aload 4
    //   100: athrow
    //   101: astore 4
    //   103: aload 4
    //   105: athrow
    // Local variable table:
    //   start	length	slot	name	signature
    //   0	106	0	this	IcsDepositChequeDomainModel
    //   9	14	1	i	int
    //   13	9	2	j	int
    //   17	8	3	k	int
    //   4	85	4	str	String
    //   91	3	4	localException1	Exception
    //   96	3	4	localException2	Exception
    //   101	3	4	localException3	Exception
    // Exception table:
    //   from	to	target	type
    //   0	6	91	java/lang/Exception
    //   93	96	96	java/lang/Exception
    //   6	18	101	java/lang/Exception
    //   77	88	101	java/lang/Exception
  }
  
  public void setAvailableBalance(AmountDomainModel paramAmountDomainModel)
  {
    throw new Runtime("d2j fail translate: java.lang.IndexOutOfBoundsException: fromIndex < 0: -1\n\tat java.util.BitSet.nextSetBit(BitSet.java:712)\n\tat com.googlecode.dex2jar.ir.ts.array.FillArrayTransformer.makeSureAllElementAreAssigned(FillArrayTransformer.java:505)\n\tat com.googlecode.dex2jar.ir.ts.array.FillArrayTransformer.transformReportChanged(FillArrayTransformer.java:123)\n\tat com.googlecode.dex2jar.ir.ts.StatedTransformer.transform(StatedTransformer.java:10)\n\tat com.googlecode.d2j.dex.Dex2jar$2.optimize(Dex2jar.java:149)\n\tat com.googlecode.d2j.dex.Dex2Asm.convertCode(Dex2Asm.java:414)\n\tat com.googlecode.d2j.dex.ExDex2Asm.convertCode(ExDex2Asm.java:42)\n\tat com.googlecode.d2j.dex.Dex2jar$2.convertCode(Dex2jar.java:128)\n\tat com.googlecode.d2j.dex.Dex2Asm.convertMethod(Dex2Asm.java:509)\n\tat com.googlecode.d2j.dex.Dex2Asm.convertClass(Dex2Asm.java:406)\n\tat com.googlecode.d2j.dex.Dex2Asm.convertDex(Dex2Asm.java:422)\n\tat com.googlecode.d2j.dex.Dex2jar.doTranslate(Dex2jar.java:172)\n\tat com.googlecode.d2j.dex.Dex2jar.to(Dex2jar.java:272)\n\tat com.googlecode.dex2jar.tools.Dex2jarCmd.doCommandLine(Dex2jarCmd.java:108)\n\tat com.googlecode.dex2jar.tools.BaseCmd.doMain(BaseCmd.java:288)\n\tat com.googlecode.dex2jar.tools.Dex2jarCmd.main(Dex2jarCmd.java:32)\n");
  }
  
  /* Error */
  public void setChequeStatus(String paramString)
  {
    // Byte code:
    //   0: iconst_0
    //   1: tableswitch	default:+23->24, 0:+50->51, 1:+-1->0
    //   24: iconst_0
    //   25: tableswitch	default:+23->48, 0:+26->51, 1:+-25->0
    //   48: goto -24 -> 24
    //   51: getstatic 39	com/mobile/business/ics/model/IcsDepositChequeDomainModel:b0410АА0410А04100410А	I
    //   54: istore_2
    //   55: getstatic 41	com/mobile/business/ics/model/IcsDepositChequeDomainModel:bА0410А0410А04100410А	I
    //   58: istore_3
    //   59: getstatic 39	com/mobile/business/ics/model/IcsDepositChequeDomainModel:b0410АА0410А04100410А	I
    //   62: istore 4
    //   64: getstatic 52	com/mobile/business/ics/model/IcsDepositChequeDomainModel:b04100410А0410А04100410А	I
    //   67: istore 5
    //   69: getstatic 47	com/mobile/business/ics/model/IcsDepositChequeDomainModel:b0410А04100410А04100410А	I
    //   72: istore 6
    //   74: iload_2
    //   75: iload_3
    //   76: iadd
    //   77: iload 4
    //   79: imul
    //   80: iload 5
    //   82: irem
    //   83: iload 6
    //   85: if_icmpeq +62 -> 147
    //   88: invokestatic 50	com/mobile/business/ics/model/IcsDepositChequeDomainModel:bАА04100410А04100410А	()I
    //   91: istore_2
    //   92: iload_2
    //   93: putstatic 39	com/mobile/business/ics/model/IcsDepositChequeDomainModel:b0410АА0410А04100410А	I
    //   96: invokestatic 50	com/mobile/business/ics/model/IcsDepositChequeDomainModel:bАА04100410А04100410А	()I
    //   99: putstatic 47	com/mobile/business/ics/model/IcsDepositChequeDomainModel:b0410А04100410А04100410А	I
    //   102: getstatic 39	com/mobile/business/ics/model/IcsDepositChequeDomainModel:b0410АА0410А04100410А	I
    //   105: istore_2
    //   106: iload_2
    //   107: getstatic 41	com/mobile/business/ics/model/IcsDepositChequeDomainModel:bА0410А0410А04100410А	I
    //   110: iload_2
    //   111: iadd
    //   112: imul
    //   113: getstatic 52	com/mobile/business/ics/model/IcsDepositChequeDomainModel:b04100410А0410А04100410А	I
    //   116: irem
    //   117: tableswitch	default:+19->136, 0:+30->147
    //   136: bipush 67
    //   138: putstatic 39	com/mobile/business/ics/model/IcsDepositChequeDomainModel:b0410АА0410А04100410А	I
    //   141: invokestatic 50	com/mobile/business/ics/model/IcsDepositChequeDomainModel:bАА04100410А04100410А	()I
    //   144: putstatic 47	com/mobile/business/ics/model/IcsDepositChequeDomainModel:b0410А04100410А04100410А	I
    //   147: aload_0
    //   148: aload_1
    //   149: putfield 78	com/mobile/business/ics/model/IcsDepositChequeDomainModel:mChequeStatus	Ljava/lang/String;
    //   152: return
    //   153: astore_1
    //   154: aload_1
    //   155: athrow
    //   156: astore_1
    //   157: aload_1
    //   158: athrow
    // Local variable table:
    //   start	length	slot	name	signature
    //   0	159	0	this	IcsDepositChequeDomainModel
    //   0	159	1	paramString	String
    //   54	59	2	i	int
    //   58	19	3	j	int
    //   62	18	4	k	int
    //   67	16	5	m	int
    //   72	14	6	n	int
    // Exception table:
    //   from	to	target	type
    //   51	74	153	java/lang/Exception
    //   92	102	153	java/lang/Exception
    //   147	152	153	java/lang/Exception
    //   88	92	156	java/lang/Exception
  }
  
  /* Error */
  public void setClearingDate(ZonedDateTime paramZonedDateTime)
  {
    // Byte code:
    //   0: getstatic 39	com/mobile/business/ics/model/IcsDepositChequeDomainModel:b0410АА0410А04100410А	I
    //   3: istore_2
    //   4: iload_2
    //   5: getstatic 41	com/mobile/business/ics/model/IcsDepositChequeDomainModel:bА0410А0410А04100410А	I
    //   8: iload_2
    //   9: iadd
    //   10: imul
    //   11: getstatic 52	com/mobile/business/ics/model/IcsDepositChequeDomainModel:b04100410А0410А04100410А	I
    //   14: irem
    //   15: tableswitch	default:+17->32, 0:+29->44
    //   32: invokestatic 50	com/mobile/business/ics/model/IcsDepositChequeDomainModel:bАА04100410А04100410А	()I
    //   35: putstatic 39	com/mobile/business/ics/model/IcsDepositChequeDomainModel:b0410АА0410А04100410А	I
    //   38: invokestatic 50	com/mobile/business/ics/model/IcsDepositChequeDomainModel:bАА04100410А04100410А	()I
    //   41: putstatic 47	com/mobile/business/ics/model/IcsDepositChequeDomainModel:b0410А04100410А04100410А	I
    //   44: getstatic 39	com/mobile/business/ics/model/IcsDepositChequeDomainModel:b0410АА0410А04100410А	I
    //   47: istore_2
    //   48: getstatic 41	com/mobile/business/ics/model/IcsDepositChequeDomainModel:bА0410А0410А04100410А	I
    //   51: istore_3
    //   52: getstatic 52	com/mobile/business/ics/model/IcsDepositChequeDomainModel:b04100410А0410А04100410А	I
    //   55: istore 4
    //   57: iload_2
    //   58: iload_3
    //   59: iload_2
    //   60: iadd
    //   61: imul
    //   62: iload 4
    //   64: irem
    //   65: tableswitch	default:+19->84, 0:+29->94
    //   84: bipush 32
    //   86: putstatic 39	com/mobile/business/ics/model/IcsDepositChequeDomainModel:b0410АА0410А04100410А	I
    //   89: bipush 45
    //   91: putstatic 47	com/mobile/business/ics/model/IcsDepositChequeDomainModel:b0410А04100410А04100410А	I
    //   94: aload_0
    //   95: aload_1
    //   96: putfield 101	com/mobile/business/ics/model/IcsDepositChequeDomainModel:mClearingDate	Lorg/threeten/bp/ZonedDateTime;
    //   99: return
    //   100: astore_1
    //   101: aload_1
    //   102: athrow
    //   103: astore_1
    //   104: aload_1
    //   105: athrow
    //   106: astore_1
    //   107: aload_1
    //   108: athrow
    // Local variable table:
    //   start	length	slot	name	signature
    //   0	109	0	this	IcsDepositChequeDomainModel
    //   0	109	1	paramZonedDateTime	ZonedDateTime
    //   3	59	2	i	int
    //   51	10	3	j	int
    //   55	10	4	k	int
    // Exception table:
    //   from	to	target	type
    //   94	99	100	java/lang/Exception
    //   48	57	103	java/lang/Exception
    //   101	103	103	java/lang/Exception
    //   44	48	106	java/lang/Exception
    //   84	94	106	java/lang/Exception
  }
  
  @ooiiio
  public void setErrorMessages(String[] paramArrayOfString)
  {
    int i = 4;
    try
    {
      throw new NullPointerException();
    }
    catch (Exception localException1)
    {
      b0410АА0410А04100410А = 6;
      try
      {
        for (;;)
        {
          int j = i / 0;
          int k = b0410АА0410А04100410А;
          i = j;
          switch (k * (bА0410А0410А04100410А + k) % b04100410А0410А04100410А)
          {
          }
          b0410АА0410А04100410А = 64;
          b0410А04100410А04100410А = 2;
          i = j;
        }
        return;
      }
      catch (Exception localException2)
      {
        b0410АА0410А04100410А = bАА04100410А04100410А();
        switch (0)
        {
        case 1: 
        default: 
          for (;;)
          {
            switch (0)
            {
            }
          }
        }
        this.mErrorMessages = ((String[])pppppd.b043004300430ааааа0430а(paramArrayOfString));
      }
    }
  }
  
  public void setProcessingDate(ZonedDateTime paramZonedDateTime)
  {
    int i = b0410АА0410А04100410А;
    int j = bА0410А0410А04100410А;
    if ((b0410АА0410А04100410А + bА0410А0410А04100410А) * b0410АА0410А04100410А % b04100410А0410А04100410А != b0410А04100410А04100410А)
    {
      b0410АА0410А04100410А = 83;
      b0410А04100410А04100410А = 9;
    }
    switch (0)
    {
    case 1: 
    default: 
      for (;;)
      {
        switch (1)
        {
        }
      }
    }
    switch (i * (j + i) % b04100410А0410А04100410А)
    {
    default: 
      b0410АА0410А04100410А = 1;
      b0410А04100410А04100410А = bАА04100410А04100410А();
    }
    try
    {
      this.mProcessingDate = paramZonedDateTime;
      return;
    }
    catch (Exception paramZonedDateTime)
    {
      throw paramZonedDateTime;
    }
  }
  
  public void setTransactionId(String paramString)
  {
    throw new Runtime("d2j fail translate: java.lang.IndexOutOfBoundsException: fromIndex < 0: -1\n\tat java.util.BitSet.nextSetBit(BitSet.java:712)\n\tat com.googlecode.dex2jar.ir.ts.array.FillArrayTransformer.makeSureAllElementAreAssigned(FillArrayTransformer.java:505)\n\tat com.googlecode.dex2jar.ir.ts.array.FillArrayTransformer.transformReportChanged(FillArrayTransformer.java:123)\n\tat com.googlecode.dex2jar.ir.ts.StatedTransformer.transform(StatedTransformer.java:10)\n\tat com.googlecode.d2j.dex.Dex2jar$2.optimize(Dex2jar.java:149)\n\tat com.googlecode.d2j.dex.Dex2Asm.convertCode(Dex2Asm.java:414)\n\tat com.googlecode.d2j.dex.ExDex2Asm.convertCode(ExDex2Asm.java:42)\n\tat com.googlecode.d2j.dex.Dex2jar$2.convertCode(Dex2jar.java:128)\n\tat com.googlecode.d2j.dex.Dex2Asm.convertMethod(Dex2Asm.java:509)\n\tat com.googlecode.d2j.dex.Dex2Asm.convertClass(Dex2Asm.java:406)\n\tat com.googlecode.d2j.dex.Dex2Asm.convertDex(Dex2Asm.java:422)\n\tat com.googlecode.d2j.dex.Dex2jar.doTranslate(Dex2jar.java:172)\n\tat com.googlecode.d2j.dex.Dex2jar.to(Dex2jar.java:272)\n\tat com.googlecode.dex2jar.tools.Dex2jarCmd.doCommandLine(Dex2jarCmd.java:108)\n\tat com.googlecode.dex2jar.tools.BaseCmd.doMain(BaseCmd.java:288)\n\tat com.googlecode.dex2jar.tools.Dex2jarCmd.main(Dex2jarCmd.java:32)\n");
  }
  
  @ooiiio
  public void writeToParcel(Parcel paramParcel, int paramInt)
  {
    paramParcel.writeParcelable(this.mAvailableBalance, paramInt);
    paramParcel.writeString(this.mChequeStatus);
    paramParcel.writeString(this.mTransactionId);
    Object localObject = this.mErrorMessages;
    if ((b0410АА0410А04100410А + b0410ААА041004100410А()) * b0410АА0410А04100410А % b04100410А0410А04100410А != b0410А04100410А04100410А)
    {
      b0410АА0410А04100410А = 43;
      b0410А04100410А04100410А = bАА04100410А04100410А();
    }
    paramParcel.writeInt(localObject.length);
    paramParcel.writeStringArray(this.mErrorMessages);
    paramParcel.writeString(this.mProcessingDate.toString());
    localObject = this.mClearingDate;
    paramInt = b0410АА0410А04100410А;
    switch (paramInt * (bА0410А0410А04100410А + paramInt) % b04100410А0410А04100410А)
    {
    default: 
      b0410АА0410А04100410А = bАА04100410А04100410А();
      b0410А04100410А04100410А = bАА04100410А04100410А();
    }
    localObject = ((ZonedDateTime)localObject).toString();
    switch (1)
    {
    case 0: 
    default: 
      for (;;)
      {
        switch (0)
        {
        }
      }
    }
    switch (1)
    {
    case 0: 
    default: 
      for (;;)
      {
        switch (1)
        {
        }
      }
    }
    paramParcel.writeString((String)localObject);
  }
}
