package com.appdynamics.repacked.gson.stream;

import java.io.Closeable;
import java.io.EOFException;
import java.io.IOException;
import java.io.Reader;
import kkkkkk.gguuuu;

public final class a
  implements Closeable
{
  private static final char[] a;
  public static int b041E041EО041EОО = b041E041E041E041EОО();
  public static int bО041E041E041EОО = 2;
  public static int bОО041E041EОО = 97;
  public static int bОООО041EО = 1;
  private final Reader b;
  private boolean c = false;
  private final char[] d = new char['Ѐ'];
  private int e = 0;
  private int f = 0;
  private int g = 0;
  private int h = 0;
  private int i = 0;
  private long j;
  private int k;
  private String l;
  private int[] m = new int[32];
  private int n = 0;
  private String[] o;
  private int[] p;
  
  /* Error */
  static
  {
    // Byte code:
    //   0: ldc 46
    //   2: sipush 135
    //   5: iconst_0
    //   6: invokestatic 52	kkkkkk/gguuuu:bккккк043Aкк043A043A	(Ljava/lang/String;CC)Ljava/lang/String;
    //   9: invokevirtual 58	java/lang/String:toCharArray	()[C
    //   12: astore 4
    //   14: getstatic 60	com/appdynamics/repacked/gson/stream/a:b041E041EО041EОО	I
    //   17: istore_0
    //   18: invokestatic 64	com/appdynamics/repacked/gson/stream/a:b041EО041E041EОО	()I
    //   21: istore_1
    //   22: getstatic 60	com/appdynamics/repacked/gson/stream/a:b041E041EО041EОО	I
    //   25: istore_2
    //   26: getstatic 60	com/appdynamics/repacked/gson/stream/a:b041E041EО041EОО	I
    //   29: istore_3
    //   30: iload_3
    //   31: invokestatic 64	com/appdynamics/repacked/gson/stream/a:b041EО041E041EОО	()I
    //   34: iload_3
    //   35: iadd
    //   36: imul
    //   37: getstatic 66	com/appdynamics/repacked/gson/stream/a:bО041E041E041EОО	I
    //   40: irem
    //   41: tableswitch	default:+19->60, 0:+30->71
    //   60: bipush 86
    //   62: putstatic 60	com/appdynamics/repacked/gson/stream/a:b041E041EО041EОО	I
    //   65: invokestatic 69	com/appdynamics/repacked/gson/stream/a:b041E041E041E041EОО	()I
    //   68: putstatic 71	com/appdynamics/repacked/gson/stream/a:bОО041E041EОО	I
    //   71: iload_0
    //   72: iload_1
    //   73: iadd
    //   74: iload_2
    //   75: imul
    //   76: getstatic 66	com/appdynamics/repacked/gson/stream/a:bО041E041E041EОО	I
    //   79: irem
    //   80: getstatic 71	com/appdynamics/repacked/gson/stream/a:bОО041E041EОО	I
    //   83: if_icmpeq +14 -> 97
    //   86: invokestatic 69	com/appdynamics/repacked/gson/stream/a:b041E041E041E041EОО	()I
    //   89: putstatic 60	com/appdynamics/repacked/gson/stream/a:b041E041EО041EОО	I
    //   92: bipush 97
    //   94: putstatic 71	com/appdynamics/repacked/gson/stream/a:bОО041E041EОО	I
    //   97: aload 4
    //   99: putstatic 73	com/appdynamics/repacked/gson/stream/a:a	[C
    //   102: new 8	com/appdynamics/repacked/gson/stream/a$1
    //   105: dup
    //   106: invokespecial 76	com/appdynamics/repacked/gson/stream/a$1:<init>	()V
    //   109: pop
    //   110: return
    //   111: astore 4
    //   113: aload 4
    //   115: athrow
    //   116: astore 4
    //   118: aload 4
    //   120: athrow
    // Local variable table:
    //   start	length	slot	name	signature
    //   17	57	0	i1	int
    //   21	53	1	i2	int
    //   25	51	2	i3	int
    //   29	8	3	i4	int
    //   12	86	4	arrayOfChar	char[]
    //   111	3	4	localException1	Exception
    //   116	3	4	localException2	Exception
    // Exception table:
    //   from	to	target	type
    //   0	14	111	java/lang/Exception
    //   97	102	111	java/lang/Exception
    //   102	110	116	java/lang/Exception
  }
  
  public a(Reader paramReader)
  {
    int[] arrayOfInt = this.m;
    int i1 = this.n;
    this.n = (i1 + 1);
    arrayOfInt[i1] = 6;
    this.o = new String[32];
    this.p = new int[32];
    this.b = paramReader;
  }
  
  private int a(boolean paramBoolean)
  {
    for (;;)
    {
      int i1;
      int i2;
      try
      {
        char[] arrayOfChar = this.d;
        i1 = this.e;
        i3 = this.f;
        int i4 = i1;
        i2 = i3;
        if (i1 == i3)
        {
          this.e = i1;
          if (b(1))
          {
            i4 = this.e;
            i2 = this.f;
          }
        }
        else
        {
          i1 = i4 + 1;
          i3 = arrayOfChar[i4];
          if (i3 == 10)
          {
            this.g += 1;
            this.h = i1;
            i3 = i2;
            continue;
          }
          if ((i3 == 32) || (i3 == 13) || (i3 == 9)) {
            break label404;
          }
          if (i3 != 47) {
            break label350;
          }
          this.e = i1;
          if (i1 != i2) {
            break label380;
          }
          if ((b041E041EО041EОО + bОООО041EО) * b041E041EО041EОО % b041EООО041EО() != bОО041E041EОО)
          {
            b041E041EО041EОО = b041E041E041E041EОО();
            bОО041E041EОО = b041E041E041E041EОО();
          }
          i1 = this.e;
        }
      }
      catch (Exception localException1)
      {
        throw localException1;
      }
      try
      {
        this.e = (i1 - 1);
        paramBoolean = b(2);
        this.e += 1;
        if ((b041E041EО041EОО + bОООО041EО) * b041E041EО041EОО % bО041E041E041EОО != bОО041E041EОО)
        {
          switch (0)
          {
          case 1: 
          default: 
            switch (1)
            {
            }
            break;
          }
          b041E041EО041EОО = b041E041E041E041EОО();
          bОО041E041EОО = b041E041E041E041EОО();
        }
        if (paramBoolean) {
          break label380;
        }
        return i3;
      }
      catch (Exception localException2)
      {
        label350:
        throw localException2;
      }
      if (paramBoolean)
      {
        throw new EOFException(gguuuu.bк043Aккк043Aкк043A043A("\r5*d3)a*./31[\034.X$ $\032S", '5', 'û', '\000') + (this.g + 1) + gguuuu.bк043Aккк043Aкк043A043A("u8C?G>>n", '¹', 'o', '\002') + m());
        if (i3 == 35)
        {
          this.e = i1;
          throw a(gguuuu.bккккк043Aкк043A043A("Kj]\031DnkkPdaegu2xk{Tnxtq{\0037\005\004\bx=5\013\0078z}~\002\016\023?\016\003\017\n\024\030\024\r\rIt~{{", 'z', '\004'));
          label380:
          throw a(gguuuu.bккккк043Aкк043A043A("g\007y5`\013\b\bl\001}\002\004\022N\025\b\030p\013\025\021\016\030\037S! $\025YQ'#T\027\032\033\036*/[*\037+&040))e\021\033\030\030", '', '\000'));
        }
        this.e = i1;
        return i3;
      }
      return -1;
      label404:
      int i3 = i2;
    }
  }
  
  private IOException a(String paramString)
  {
    switch (0)
    {
    case 1: 
    default: 
      for (;;)
      {
        switch (1)
        {
        }
      }
    }
    if ((b041E041EО041EОО + bОООО041EО) * b041E041EО041EОО % bО041E041E041EОО != bОО041E041EОО)
    {
      b041E041EО041EОО = 33;
      bОО041E041EОО = b041E041E041E041EОО();
    }
    paramString = new d(paramString + gguuuu.bккккк043Aкк043A043A("\006FX\003NJND}", '\032', '\005') + (this.g + 1) + gguuuu.bк043Aккк043Aкк043A043A("\bJUQYPP\001", '9', '^', '\002') + m() + gguuuu.bк043Aккк043Aкк043A043A("\013ZJ\\O\006", '=', 'W', '\002') + n());
    if ((b041E041EО041EОО + bОООО041EО) * b041E041EО041EОО % bО041E041E041EОО != bОО041E041EОО)
    {
      b041E041EО041EОО = b041E041E041E041EОО();
      bОО041E041EОО = b041E041E041E041EОО();
    }
    try
    {
      throw paramString;
    }
    catch (Exception paramString)
    {
      throw paramString;
    }
  }
  
  /* Error */
  private void a(int paramInt)
  {
    // Byte code:
    //   0: aload_0
    //   1: getfield 97	com/appdynamics/repacked/gson/stream/a:n	I
    //   4: istore_2
    //   5: iload_2
    //   6: aload_0
    //   7: getfield 95	com/appdynamics/repacked/gson/stream/a:m	[I
    //   10: arraylength
    //   11: if_icmpne +180 -> 191
    //   14: aload_0
    //   15: getfield 97	com/appdynamics/repacked/gson/stream/a:n	I
    //   18: istore_2
    //   19: iload_2
    //   20: iconst_1
    //   21: ishl
    //   22: newarray int
    //   24: astore_3
    //   25: aload_0
    //   26: getfield 97	com/appdynamics/repacked/gson/stream/a:n	I
    //   29: iconst_1
    //   30: ishl
    //   31: newarray int
    //   33: astore 4
    //   35: aload_0
    //   36: getfield 97	com/appdynamics/repacked/gson/stream/a:n	I
    //   39: iconst_1
    //   40: ishl
    //   41: anewarray 54	java/lang/String
    //   44: astore 5
    //   46: getstatic 60	com/appdynamics/repacked/gson/stream/a:b041E041EО041EОО	I
    //   49: getstatic 109	com/appdynamics/repacked/gson/stream/a:bОООО041EО	I
    //   52: iadd
    //   53: getstatic 60	com/appdynamics/repacked/gson/stream/a:b041E041EО041EОО	I
    //   56: imul
    //   57: getstatic 66	com/appdynamics/repacked/gson/stream/a:bО041E041E041EОО	I
    //   60: irem
    //   61: invokestatic 164	com/appdynamics/repacked/gson/stream/a:bО041EОО041EО	()I
    //   64: if_icmpeq +17 -> 81
    //   67: invokestatic 69	com/appdynamics/repacked/gson/stream/a:b041E041E041E041EОО	()I
    //   70: putstatic 60	com/appdynamics/repacked/gson/stream/a:b041E041EО041EОО	I
    //   73: invokestatic 69	com/appdynamics/repacked/gson/stream/a:b041E041E041E041EОО	()I
    //   76: istore_2
    //   77: iload_2
    //   78: putstatic 71	com/appdynamics/repacked/gson/stream/a:bОО041E041EОО	I
    //   81: aload_0
    //   82: getfield 95	com/appdynamics/repacked/gson/stream/a:m	[I
    //   85: iconst_0
    //   86: aload_3
    //   87: iconst_0
    //   88: aload_0
    //   89: getfield 97	com/appdynamics/repacked/gson/stream/a:n	I
    //   92: invokestatic 170	java/lang/System:arraycopy	(Ljava/lang/Object;ILjava/lang/Object;II)V
    //   95: aload_0
    //   96: getfield 101	com/appdynamics/repacked/gson/stream/a:p	[I
    //   99: iconst_0
    //   100: aload 4
    //   102: iconst_0
    //   103: aload_0
    //   104: getfield 97	com/appdynamics/repacked/gson/stream/a:n	I
    //   107: invokestatic 170	java/lang/System:arraycopy	(Ljava/lang/Object;ILjava/lang/Object;II)V
    //   110: getstatic 60	com/appdynamics/repacked/gson/stream/a:b041E041EО041EОО	I
    //   113: istore_2
    //   114: iload_2
    //   115: getstatic 109	com/appdynamics/repacked/gson/stream/a:bОООО041EО	I
    //   118: iload_2
    //   119: iadd
    //   120: imul
    //   121: getstatic 66	com/appdynamics/repacked/gson/stream/a:bО041E041E041EОО	I
    //   124: irem
    //   125: tableswitch	default:+19->144, 0:+30->155
    //   144: bipush 77
    //   146: putstatic 60	com/appdynamics/repacked/gson/stream/a:b041E041EО041EОО	I
    //   149: invokestatic 69	com/appdynamics/repacked/gson/stream/a:b041E041E041E041EОО	()I
    //   152: putstatic 71	com/appdynamics/repacked/gson/stream/a:bОО041E041EОО	I
    //   155: aload_0
    //   156: getfield 99	com/appdynamics/repacked/gson/stream/a:o	[Ljava/lang/String;
    //   159: astore 6
    //   161: aload 6
    //   163: iconst_0
    //   164: aload 5
    //   166: iconst_0
    //   167: aload_0
    //   168: getfield 97	com/appdynamics/repacked/gson/stream/a:n	I
    //   171: invokestatic 170	java/lang/System:arraycopy	(Ljava/lang/Object;ILjava/lang/Object;II)V
    //   174: aload_0
    //   175: aload_3
    //   176: putfield 95	com/appdynamics/repacked/gson/stream/a:m	[I
    //   179: aload_0
    //   180: aload 4
    //   182: putfield 101	com/appdynamics/repacked/gson/stream/a:p	[I
    //   185: aload_0
    //   186: aload 5
    //   188: putfield 99	com/appdynamics/repacked/gson/stream/a:o	[Ljava/lang/String;
    //   191: aload_0
    //   192: getfield 95	com/appdynamics/repacked/gson/stream/a:m	[I
    //   195: astore_3
    //   196: aload_0
    //   197: getfield 97	com/appdynamics/repacked/gson/stream/a:n	I
    //   200: istore_2
    //   201: aload_0
    //   202: iload_2
    //   203: iconst_1
    //   204: iadd
    //   205: putfield 97	com/appdynamics/repacked/gson/stream/a:n	I
    //   208: aload_3
    //   209: iload_2
    //   210: iload_1
    //   211: iastore
    //   212: return
    //   213: astore_3
    //   214: aload_3
    //   215: athrow
    //   216: astore_3
    //   217: aload_3
    //   218: athrow
    // Local variable table:
    //   start	length	slot	name	signature
    //   0	219	0	this	a
    //   0	219	1	paramInt	int
    //   4	206	2	i1	int
    //   24	185	3	arrayOfInt1	int[]
    //   213	2	3	localException1	Exception
    //   216	2	3	localException2	Exception
    //   33	148	4	arrayOfInt2	int[]
    //   44	143	5	arrayOfString1	String[]
    //   159	3	6	arrayOfString2	String[]
    // Exception table:
    //   from	to	target	type
    //   0	5	213	java/lang/Exception
    //   19	77	213	java/lang/Exception
    //   81	110	213	java/lang/Exception
    //   161	185	213	java/lang/Exception
    //   5	19	216	java/lang/Exception
    //   77	81	216	java/lang/Exception
    //   155	161	216	java/lang/Exception
    //   185	191	216	java/lang/Exception
    //   191	208	216	java/lang/Exception
  }
  
  private boolean a(char paramChar)
  {
    boolean bool2 = false;
    boolean bool1;
    switch (paramChar)
    {
    default: 
      bool1 = true;
    case '#': 
    case '/': 
    case ';': 
    case '=': 
    case '\\': 
      for (;;)
      {
        return bool1;
        try
        {
          IOException localIOException = a(gguuuu.bккккк043Aкк043A043A("6UH\004/YVV;OLPR`\035cVf?Yc_\\fm\"onrc( uq#ehilx}*xmyt~\003~ww4_iff", 'ß', '\000'));
          try
          {
            throw localIOException;
          }
          catch (Exception localException1)
          {
            try
            {
              throw localException1;
            }
            catch (Exception localException2)
            {
              throw localException2;
            }
          }
          try
          {
            paramChar = b041E041EО041EОО;
            bool1 = bool2;
            switch (paramChar * (bОООО041EО + paramChar) % bО041E041E041EОО)
            {
            case 0: 
              b041E041EО041EОО = b041E041E041E041EОО();
              bОО041E041EОО = 67;
              bool1 = bool2;
              if ((b041E041EО041EОО + bОООО041EО) * b041E041EО041EОО % bО041E041E041EОО != bОО041E041EОО)
              {
                b041E041EО041EОО = 7;
                bОО041E041EОО = 77;
                return false;
              }
              break;
            }
          }
          catch (Exception localException4)
          {
            throw localException4;
          }
        }
        catch (Exception localException3)
        {
          throw localException3;
        }
      }
    }
    for (;;) {}
  }
  
  /* Error */
  private String b(char paramChar)
  {
    // Byte code:
    //   0: iconst_1
    //   1: istore_2
    //   2: iload_2
    //   3: iconst_0
    //   4: idiv
    //   5: istore_2
    //   6: goto -4 -> 2
    //   9: iload_2
    //   10: iconst_1
    //   11: iadd
    //   12: istore 5
    //   14: aload 7
    //   16: iload_2
    //   17: caload
    //   18: istore_2
    //   19: iload_2
    //   20: iload_1
    //   21: if_icmpne +32 -> 53
    //   24: aload_0
    //   25: iload 5
    //   27: putfield 85	com/appdynamics/repacked/gson/stream/a:e	I
    //   30: aload 6
    //   32: aload 7
    //   34: iload 4
    //   36: iload 5
    //   38: iload 4
    //   40: isub
    //   41: iconst_1
    //   42: isub
    //   43: invokevirtual 177	java/lang/StringBuilder:append	([CII)Ljava/lang/StringBuilder;
    //   46: pop
    //   47: aload 6
    //   49: invokevirtual 140	java/lang/StringBuilder:toString	()Ljava/lang/String;
    //   52: areturn
    //   53: iload_2
    //   54: bipush 92
    //   56: if_icmpne +135 -> 191
    //   59: aload_0
    //   60: iload 5
    //   62: putfield 85	com/appdynamics/repacked/gson/stream/a:e	I
    //   65: aload 6
    //   67: aload 7
    //   69: iload 4
    //   71: iload 5
    //   73: iload 4
    //   75: isub
    //   76: iconst_1
    //   77: isub
    //   78: invokevirtual 177	java/lang/StringBuilder:append	([CII)Ljava/lang/StringBuilder;
    //   81: pop
    //   82: aload 6
    //   84: aload_0
    //   85: invokespecial 180	com/appdynamics/repacked/gson/stream/a:o	()C
    //   88: invokevirtual 183	java/lang/StringBuilder:append	(C)Ljava/lang/StringBuilder;
    //   91: pop
    //   92: aload_0
    //   93: getfield 85	com/appdynamics/repacked/gson/stream/a:e	I
    //   96: istore_2
    //   97: aload_0
    //   98: getfield 87	com/appdynamics/repacked/gson/stream/a:f	I
    //   101: istore_3
    //   102: getstatic 60	com/appdynamics/repacked/gson/stream/a:b041E041EО041EОО	I
    //   105: getstatic 109	com/appdynamics/repacked/gson/stream/a:bОООО041EО	I
    //   108: iadd
    //   109: getstatic 60	com/appdynamics/repacked/gson/stream/a:b041E041EО041EОО	I
    //   112: imul
    //   113: getstatic 66	com/appdynamics/repacked/gson/stream/a:bО041E041E041EОО	I
    //   116: irem
    //   117: getstatic 71	com/appdynamics/repacked/gson/stream/a:bОО041E041EОО	I
    //   120: if_icmpeq +14 -> 134
    //   123: invokestatic 69	com/appdynamics/repacked/gson/stream/a:b041E041E041E041EОО	()I
    //   126: putstatic 60	com/appdynamics/repacked/gson/stream/a:b041E041EО041EОО	I
    //   129: bipush 24
    //   131: putstatic 71	com/appdynamics/repacked/gson/stream/a:bОО041E041EОО	I
    //   134: iload_2
    //   135: istore 4
    //   137: iload_2
    //   138: iload_3
    //   139: if_icmpge +80 -> 219
    //   142: iconst_0
    //   143: tableswitch	default:+21->164, 0:+-134->9, 1:+-1->142
    //   164: iconst_0
    //   165: tableswitch	default:+23->188, 0:+-156->9, 1:+-23->142
    //   188: goto -24 -> 164
    //   191: iload_2
    //   192: bipush 10
    //   194: if_icmpne +19 -> 213
    //   197: aload_0
    //   198: aload_0
    //   199: getfield 89	com/appdynamics/repacked/gson/stream/a:g	I
    //   202: iconst_1
    //   203: iadd
    //   204: putfield 89	com/appdynamics/repacked/gson/stream/a:g	I
    //   207: aload_0
    //   208: iload 5
    //   210: putfield 91	com/appdynamics/repacked/gson/stream/a:h	I
    //   213: iload 5
    //   215: istore_2
    //   216: goto -79 -> 137
    //   219: aload 6
    //   221: aload 7
    //   223: iload 4
    //   225: iload_2
    //   226: iload 4
    //   228: isub
    //   229: invokevirtual 177	java/lang/StringBuilder:append	([CII)Ljava/lang/StringBuilder;
    //   232: pop
    //   233: aload_0
    //   234: iload_2
    //   235: putfield 85	com/appdynamics/repacked/gson/stream/a:e	I
    //   238: aload_0
    //   239: iconst_1
    //   240: invokespecial 107	com/appdynamics/repacked/gson/stream/a:b	(I)Z
    //   243: ifne +47 -> 290
    //   246: aload_0
    //   247: ldc -71
    //   249: bipush 109
    //   251: sipush 220
    //   254: iconst_0
    //   255: invokestatic 122	kkkkkk/gguuuu:bк043Aккк043Aкк043A043A	(Ljava/lang/String;CCC)Ljava/lang/String;
    //   258: invokespecial 146	com/appdynamics/repacked/gson/stream/a:a	(Ljava/lang/String;)Ljava/io/IOException;
    //   261: athrow
    //   262: astore 6
    //   264: aload 6
    //   266: athrow
    //   267: astore 6
    //   269: invokestatic 69	com/appdynamics/repacked/gson/stream/a:b041E041E041E041EОО	()I
    //   272: putstatic 60	com/appdynamics/repacked/gson/stream/a:b041E041EО041EОО	I
    //   275: aload_0
    //   276: getfield 83	com/appdynamics/repacked/gson/stream/a:d	[C
    //   279: astore 7
    //   281: new 116	java/lang/StringBuilder
    //   284: dup
    //   285: invokespecial 151	java/lang/StringBuilder:<init>	()V
    //   288: astore 6
    //   290: aload_0
    //   291: getfield 85	com/appdynamics/repacked/gson/stream/a:e	I
    //   294: istore_2
    //   295: aload_0
    //   296: getfield 87	com/appdynamics/repacked/gson/stream/a:f	I
    //   299: istore_3
    //   300: iload_2
    //   301: istore 4
    //   303: goto -166 -> 137
    //   306: astore 6
    //   308: aload 6
    //   310: athrow
    //   311: astore 6
    //   313: bipush 15
    //   315: putstatic 60	com/appdynamics/repacked/gson/stream/a:b041E041EО041EОО	I
    //   318: new 187	java/lang/NullPointerException
    //   321: dup
    //   322: invokespecial 188	java/lang/NullPointerException:<init>	()V
    //   325: athrow
    // Local variable table:
    //   start	length	slot	name	signature
    //   0	326	0	this	a
    //   0	326	1	paramChar	char
    //   1	300	2	c1	char
    //   101	199	3	c2	char
    //   34	268	4	c3	char
    //   12	202	5	c4	char
    //   30	190	6	localObject	Object
    //   262	3	6	localException1	Exception
    //   267	1	6	localException2	Exception
    //   288	1	6	localStringBuilder	StringBuilder
    //   306	3	6	localException3	Exception
    //   311	1	6	localException4	Exception
    //   14	266	7	arrayOfChar	char[]
    // Exception table:
    //   from	to	target	type
    //   92	102	262	java/lang/Exception
    //   219	262	262	java/lang/Exception
    //   318	326	267	java/lang/Exception
    //   24	53	306	java/lang/Exception
    //   59	92	306	java/lang/Exception
    //   197	213	306	java/lang/Exception
    //   275	290	306	java/lang/Exception
    //   290	300	306	java/lang/Exception
    //   2	6	311	java/lang/Exception
  }
  
  private boolean b(int paramInt)
  {
    try
    {
      char[] arrayOfChar = this.d;
      this.h -= this.e;
      int i1;
      if (this.f != this.e) {
        i1 = this.f;
      }
      for (;;)
      {
        try
        {
          this.f = (i1 - this.e);
          System.arraycopy(arrayOfChar, this.e, arrayOfChar, 0, this.f);
          this.e = 0;
          Reader localReader = this.b;
          i1 = this.f;
          i1 = localReader.read(arrayOfChar, i1, 1024 - this.f);
          if (i1 == -1) {
            break;
          }
          this.f = (i1 + this.f);
          i1 = paramInt;
          if (this.g == 0)
          {
            i1 = paramInt;
            if (this.h == 0)
            {
              int i2 = this.f;
              i1 = paramInt;
              if (i2 > 0)
              {
                i1 = paramInt;
                if (arrayOfChar[0] == 65279)
                {
                  i1 = this.e;
                  if ((b041E041EО041EОО + bОООО041EО) * b041E041EО041EОО % bО041E041E041EОО != bО041EОО041EО())
                  {
                    b041E041EО041EОО = 25;
                    bОО041E041EОО = b041E041E041E041EОО();
                  }
                  this.e = (i1 + 1);
                  this.h += 1;
                  i1 = paramInt + 1;
                }
              }
            }
          }
          paramInt = i1;
          if (this.f < i1) {
            continue;
          }
          return true;
        }
        catch (Exception localException1)
        {
          throw localException1;
        }
        this.f = 0;
      }
      return false;
    }
    catch (Exception localException2)
    {
      throw localException2;
    }
  }
  
  public static int b041E041E041E041EОО()
  {
    return 83;
  }
  
  public static int b041EО041E041EОО()
  {
    return 1;
  }
  
  public static int b041EООО041EО()
  {
    return 2;
  }
  
  public static int bО041EОО041EО()
  {
    return 0;
  }
  
  private void c(char paramChar)
  {
    try
    {
      char[] arrayOfChar = this.d;
      for (;;)
      {
        char c3;
        try
        {
          c1 = this.e;
          char c2 = this.f;
          c3 = b041E041EО041EОО;
          int i1 = bОООО041EО;
          int i2 = b041E041EО041EОО;
          int i3 = bО041E041E041EОО;
          int i4 = bОО041E041EОО;
          if ((c3 + i1) * i2 % i3 != i4)
          {
            b041E041EО041EОО = b041E041E041E041EОО();
            bОО041E041EОО = 80;
          }
          if (c1 >= c2) {
            break;
          }
          c3 = c1 + '\001';
          c1 = arrayOfChar[c1];
          if (c1 == paramChar)
          {
            this.e = c3;
            return;
          }
          if (c1 == '\\')
          {
            this.e = c3;
            o();
            c1 = this.e;
            c2 = this.f;
            continue;
            this.e = c1;
            boolean bool = b(1);
            c1 = b041E041EО041EОО;
            switch (c1 * (bОООО041EО + c1) % bО041E041E041EОО)
            {
            default: 
              b041E041EО041EОО = 78;
              bОО041E041EОО = b041E041E041E041EОО();
            }
            if (bool) {
              continue;
            }
            throw a(gguuuu.bк043Aккк043Aкк043A043A("-EJ:F@;?1C31k>>;15-", '¬', 'ù', '\002'));
          }
        }
        catch (Exception localException1)
        {
          throw localException1;
        }
        if (c1 == '\n')
        {
          this.g += 1;
          this.h = c3;
        }
        char c1 = c3;
      }
      switch (1)
      {
      }
    }
    catch (Exception localException2)
    {
      throw localException2;
    }
    for (;;)
    {
      switch (0)
      {
      }
    }
  }
  
  private b h()
  {
    int i2 = 4;
    int i3 = this.i;
    int i1 = i3;
    if (i3 == 0)
    {
      switch (1)
      {
      case 0: 
      default: 
        for (;;)
        {
          switch (1)
          {
          }
        }
      }
      i1 = i();
    }
    Object localObject;
    switch (i1)
    {
    default: 
      throw new AssertionError();
    case 8: 
    case 9: 
    case 10: 
    case 11: 
      localObject = b.f;
      return localObject;
    case 17: 
      return b.j;
    case 15: 
    case 16: 
      b localB = b.g;
      i1 = b041E041EО041EОО;
      localObject = localB;
      switch (i1 * (bОООО041EО + i1) % bО041E041E041EОО)
      {
      }
      b041E041EО041EОО = b041E041E041E041EОО();
      bОО041E041EОО = b041E041E041E041EОО();
      return localB;
    case 4: 
      localObject = b.b;
      i1 = i2;
    }
    try
    {
      for (;;)
      {
        i1 /= 0;
      }
      return b.c;
    }
    catch (Exception localException1)
    {
      b041E041EО041EОО = 55;
      try
      {
        throw new NullPointerException();
      }
      catch (Exception localException2)
      {
        b041E041EО041EОО = b041E041E041E041EОО();
      }
    }
    return b.d;
    return b.a;
    return b.e;
    return b.h;
    return b.i;
    return localObject;
  }
  
  private int i()
  {
    int i1;
    try
    {
      i1 = this.m[(this.n - 1)];
      if ((b041E041EО041EОО + bОООО041EО) * b041E041EО041EОО % bО041E041E041EОО != bОО041E041EОО)
      {
        b041E041EО041EОО = 12;
        bОО041E041EОО = 21;
      }
      if (i1 != 1) {
        break label415;
      }
      this.m[(this.n - 1)] = 2;
      switch (a(true))
      {
      case 34: 
        this.e -= 1;
        if (this.n != 1) {
          break label480;
        }
        throw a(gguuuu.bк043Aккк043Aкк043A043A("\"?0i\023;64\027)$&&2l1\"0\007\037'!\034$)['$&\025WM!\033J\013\f\013\f\026\031C\020\003\r\006\016\020\n\001~9bjec", '<', 'õ', '\002'));
      }
    }
    catch (Exception localException1)
    {
      throw localException1;
    }
    throw a(gguuuu.bк043Aккк043Aкк043A043A("[zm)T~{{`tquw\006B\t{\fd~\t\005\002\f\023G\025\024\030\tME\033\027H\013\016\017\022\036#O\036\023\037\032$($\035\035Y\005\017\f\f", 'q', 'k', '\001'));
    Object localObject = gguuuu.bккккк043Aкк043A043A("\0243&a\r744\031-*.0>zA4D\0357A=:DKMLPA\006}SO\001CFGJV[\bVKWR\\`\\UU\022=GDD", '\037', '\004');
    if ((b041E041EО041EОО + b041EО041E041EОО()) * b041E041EО041EОО % bО041E041E041EОО != bОО041E041EОО)
    {
      b041E041EО041EОО = b041E041E041E041EОО();
      bОО041E041EОО = b041E041E041E041EОО();
    }
    throw a((String)localObject);
    label232:
    localObject = this.m;
    int i2 = this.n;
    localObject[(i2 - 1)] = 4;
    if (i1 == 5)
    {
      i2 = b041E041E041E041EОО();
      switch (i2 * (bОООО041EО + i2) % b041EООО041EО())
      {
      default: 
        b041E041EО041EОО = 81;
        bОО041E041EОО = 39;
      }
      label336:
      label415:
      label460:
      label480:
      label547:
      do
      {
        try
        {
          switch (a(true))
          {
          case 125: 
            throw a(gguuuu.bккккк043Aкк043A043A("\0357>0>:7=1E77sD8A=<N", 'Á', '\001'));
          }
        }
        catch (Exception localException2)
        {
          throw localException2;
        }
        throw a(gguuuu.bк043Aккк043Aкк043A043A("\0210#^\n411\026*'+-;w>1A\0324>:7AH|JIM>\003zPL}@CDGSX\005SHTOY]YRR\017:DAA", 'ö', 'C', '\003'));
        do
        {
          if (i1 != 8) {
            break;
          }
          throw new IllegalStateException(gguuuu.bккккк043Aкк043A043A("c\016\013\013o\004\001\005\007\025C\016\031F\013\025\031\036\021\021", ']', '\001'));
          if (this.n != 1) {
            break label730;
          }
          throw a(gguuuu.bк043Aккк043Aкк043A043A("8UF)QLJ-?:<<H\003G8F\0355=72:?q=:<+mc71`!\"!\",/Y&\031#\034$& \027\025Ox\001{y", ':', '', '\000'));
          if (i1 != 2) {
            break label872;
          }
          switch (a(true))
          {
          case 44: 
          case 59: 
            throw a(gguuuu.bккккк043Aкк043A043A("Zrwgsmhl^p`^\031YihVm", 'z', '\005'));
          case 93: 
            this.i = 4;
            return 4;
            i2 = j();
            i1 = i2;
            if (i2 != 0) {
              break label891;
            }
            i2 = k();
            i1 = i2;
            if (i2 != 0) {
              break label891;
            }
            if (!a(this.d[this.e])) {
              throw a(gguuuu.bккккк043Aкк043A043A("Ewnb_o_]\030mWaiX", '', '\005'));
            }
            throw a(gguuuu.bккккк043Aкк043A043A("\f+\036Y\005/,,\021%\"&(6r9,<\025/952<CwEDH9}uKGx;>?BNSNCOJTXTMM\n5?<<", 'µ', '\000'));
          }
        } while (i1 != 7);
        i1 = a(false);
      } while (i1 != -1);
      this.i = 17;
      return 17;
    }
    label660:
    label730:
    label739:
    do
    {
      if (i1 != 6) {
        break label547;
      }
      int[] arrayOfInt = this.m;
      arrayOfInt[(this.n - 1)] = 7;
      break;
      this.i = 2;
      return 2;
      throw a(gguuuu.bккккк043Aкк043A043A("DaR\f5]XV9KFHHT\017SDR)AIC>FK}IFH7yoC=l-.-.8;e2%/(02,#![\005\r\b\006", 'Ç', '\003'));
      switch (a(true))
      {
      case 34: 
        throw a(gguuuu.bккккк043Aкк043A043A("\0210#^\n411\026*'+-;w>1A\0324>:7AH|JIM>\003zPL}@CDGSX\005SHTOY]YRR\017:DAA", '½', '\001'));
      case 39: 
      case 125: 
        do
        {
          throw a(gguuuu.bккккк043Aкк043A043A("j\037\030\016\r\037\021\021M\035\021\036\027", '%', '\000'));
          this.i = 13;
          return 13;
          throw a(gguuuu.bккккк043Aкк043A043A("\017.!\\\b2//\024(%)+9u</?\0302<85?FzHGK<\001xNJ{>ABEQV\003QFRMW[WPP\r8B??", '9', '\000'));
          this.i = 1;
          return 1;
        } while (i1 == 5);
        this.i = 2;
        return 2;
        this.i = 9;
        return 9;
      }
    } while (i1 != 4);
    this.m[(this.n - 1)] = 5;
    switch (a(true))
    {
    case 58: 
    case 61: 
    case 59: 
    case 60: 
      label792:
      throw a(gguuuu.bккккк043Aкк043A043A("%WNB?O?=w}\020{", '´', '\002'));
      label807:
      throw a(gguuuu.bк043Aккк043Aкк043A043A("Xrj~wml~pp-\005p|\007w", '\\', 'Y', '\001'));
      this.i = 3;
      return 3;
      if (i1 == 1)
      {
        this.i = 4;
        return 4;
      }
      break;
    }
    for (;;)
    {
      throw a(gguuuu.bккккк043Aкк043A043A("6UH\004/YVV;OLPR`\035cVf?Yc_\\fm\"onrc( uq#ehilx}*xmyt~\003~ww4_iff", '', '\001'));
      throw a(gguuuu.bккккк043Aкк043A043A("Vuh$Oyvv[olpr\001=\004v\007_y\004|\007\016B\020\017\023\004H@\026\022C\006\t\n\r\031\036J\031\016\032\025\037#\037\030\030T\n\007\007", '\001', '\000'));
      break;
      label872:
      if (i1 == 3) {
        break label232;
      }
      if (i1 != 5) {
        break label739;
      }
      break label232;
      break label336;
      break label460;
      label891:
      return i1;
      break label660;
      break label792;
      if (i1 != 1) {
        if (i1 != 2) {
          break label807;
        }
      }
    }
  }
  
  private int j()
  {
    int i2 = 1;
    int i1 = this.d[this.e];
    String str2;
    String str1;
    int i3;
    if ((i1 == 116) || (i1 == 84))
    {
      str2 = gguuuu.bккккк043Aкк043A043A("-,0!", '\034', '\004');
      str1 = gguuuu.bккккк043Aкк043A043A("\t\b\f|", 'f', '\001');
      i1 = 5;
      i3 = str2.length();
    }
    for (;;)
    {
      if (i2 < i3) {
        if ((this.e + i2 < this.f) || (b(i2 + 1))) {}
      }
      label294:
      while (this.e + i3 < this.f)
      {
        while (a(this.d[(this.e + i3)]))
        {
          do
          {
            do
            {
              return 0;
              if ((b041E041EО041EОО + bОООО041EО) * b041E041EО041EОО % bО041E041E041EОО != bОО041E041EОО)
              {
                b041E041EО041EОО = 38;
                bОО041E041EОО = 26;
              }
              if ((i1 == 102) || (i1 == 70))
              {
                str2 = gguuuu.bккккк043Aкк043A043A("\r\t\025\035\020", '¶', '\001');
                str1 = gguuuu.bккккк043Aкк043A043A("E?IO@", 'ÿ', '\005');
                i1 = 6;
                break;
              }
            } while ((i1 != 110) && (i1 != 78));
            str2 = gguuuu.bк043Aккк043Aкк043A043A("LRHG", 'æ', 'Ä', '\000');
            str1 = gguuuu.bккккк043Aкк043A043A("QWML", '~', '\002');
            i1 = 7;
            break;
            int i4 = this.d[(this.e + i2)];
            if ((i4 == str2.charAt(i2)) || (i4 == str1.charAt(i2))) {
              break label383;
            }
          } while ((b041E041EО041EОО + bОООО041EО) * b041E041EО041EОО % bО041E041E041EОО == bОО041E041EОО);
          b041E041EО041EОО = b041E041E041E041EОО();
          bОО041E041EОО = b041E041E041E041EОО();
          return 0;
          if (!bool) {
            break label294;
          }
        }
        this.e += i3;
        this.i = i1;
        return i1;
      }
      boolean bool = b(i3 + 1);
      switch (0)
      {
      }
      for (;;)
      {
        switch (0)
        {
        }
      }
      label383:
      i2 += 1;
    }
  }
  
  private int k()
  {
    throw new Runtime("d2j fail translate: java.lang.IndexOutOfBoundsException: fromIndex < 0: -1\n\tat java.util.BitSet.nextSetBit(BitSet.java:712)\n\tat com.googlecode.dex2jar.ir.ts.array.FillArrayTransformer.makeSureAllElementAreAssigned(FillArrayTransformer.java:505)\n\tat com.googlecode.dex2jar.ir.ts.array.FillArrayTransformer.transformReportChanged(FillArrayTransformer.java:123)\n\tat com.googlecode.dex2jar.ir.ts.StatedTransformer.transform(StatedTransformer.java:10)\n\tat com.googlecode.d2j.dex.Dex2jar$2.optimize(Dex2jar.java:149)\n\tat com.googlecode.d2j.dex.Dex2Asm.convertCode(Dex2Asm.java:414)\n\tat com.googlecode.d2j.dex.ExDex2Asm.convertCode(ExDex2Asm.java:42)\n\tat com.googlecode.d2j.dex.Dex2jar$2.convertCode(Dex2jar.java:128)\n\tat com.googlecode.d2j.dex.Dex2Asm.convertMethod(Dex2Asm.java:509)\n\tat com.googlecode.d2j.dex.Dex2Asm.convertClass(Dex2Asm.java:406)\n\tat com.googlecode.d2j.dex.Dex2Asm.convertDex(Dex2Asm.java:422)\n\tat com.googlecode.d2j.dex.Dex2jar.doTranslate(Dex2jar.java:172)\n\tat com.googlecode.d2j.dex.Dex2jar.to(Dex2jar.java:272)\n\tat com.googlecode.dex2jar.tools.Dex2jarCmd.doCommandLine(Dex2jarCmd.java:108)\n\tat com.googlecode.dex2jar.tools.BaseCmd.doMain(BaseCmd.java:288)\n\tat com.googlecode.dex2jar.tools.Dex2jarCmd.main(Dex2jarCmd.java:32)\n");
  }
  
  private String l()
  {
    int i2 = 0;
    Object localObject2 = null;
    int i1 = 0;
    do
    {
      for (;;)
      {
        int i3 = this.e;
        if ((b041E041EО041EОО + bОООО041EО) * b041E041EО041EОО % bО041E041E041EОО != bОО041E041EОО)
        {
          b041E041EО041EОО = b041E041E041E041EОО();
          bОО041E041EОО = b041E041E041E041EОО();
        }
        if (i3 + i1 >= this.f) {
          break;
        }
        switch (this.d[(this.e + i1)])
        {
        default: 
          i1 += 1;
        }
      }
      if (i1 >= 1024) {
        break;
      }
    } while (b(i1 + 1));
    for (;;)
    {
      label228:
      if (localObject2 == null) {}
      for (Object localObject1 = new String(this.d, this.e, i1);; localObject1 = localObject2.toString())
      {
        this.e = (i1 + this.e);
        return localObject1;
        localObject1 = localObject2;
        if (localObject2 == null) {
          localObject1 = new StringBuilder();
        }
        ((StringBuilder)localObject1).append(this.d, this.e, i1);
        this.e = (i1 + this.e);
        i1 = i2;
        localObject2 = localObject1;
        if (!b(1)) {
          break label228;
        }
        i1 = 0;
        localObject2 = localObject1;
        break;
        throw a(gguuuu.bк043Aккк043Aкк043A043A("<YJ\004-UPN1C>@@L\007K<J!9A;6>CuA>@/qg;5d%&%&03]*\035' (*$\033\031S|\005}", '\032', 'ÿ', '\000'));
        localObject1 = this.d;
        i2 = b041E041EО041EОО;
        switch (i2 * (b041EО041E041EОО() + i2) % bО041E041E041EОО)
        {
        default: 
          b041E041EО041EОО = b041E041E041E041EОО();
          bОО041E041EОО = 67;
        }
        localObject2.append((char[])localObject1, this.e, i1);
      }
    }
  }
  
  private int m()
  {
    try
    {
      int i1 = this.e;
      int i2 = this.h;
      int i3 = b041E041EО041EОО;
      switch (i3 * (bОООО041EО + i3) % bО041E041E041EОО)
      {
      default: 
        if ((b041E041EО041EОО + bОООО041EО) * b041E041EО041EОО % bО041E041E041EОО != bО041EОО041EО())
        {
          b041E041EО041EОО = b041E041E041E041EОО();
          bОО041E041EОО = b041E041E041E041EОО();
        }
        switch (0)
        {
        case 1: 
        default: 
          for (;;)
          {
            switch (0)
            {
            }
          }
        }
        b041E041EО041EОО = 78;
        bОО041E041EОО = 66;
      }
      return i1 - i2 + 1;
    }
    catch (Exception localException)
    {
      throw localException;
    }
  }
  
  private String n()
  {
    throw new Runtime("d2j fail translate: java.lang.IndexOutOfBoundsException: fromIndex < 0: -1\n\tat java.util.BitSet.nextSetBit(BitSet.java:712)\n\tat com.googlecode.dex2jar.ir.ts.array.FillArrayTransformer.makeSureAllElementAreAssigned(FillArrayTransformer.java:505)\n\tat com.googlecode.dex2jar.ir.ts.array.FillArrayTransformer.transformReportChanged(FillArrayTransformer.java:123)\n\tat com.googlecode.dex2jar.ir.ts.StatedTransformer.transform(StatedTransformer.java:10)\n\tat com.googlecode.d2j.dex.Dex2jar$2.optimize(Dex2jar.java:149)\n\tat com.googlecode.d2j.dex.Dex2Asm.convertCode(Dex2Asm.java:414)\n\tat com.googlecode.d2j.dex.ExDex2Asm.convertCode(ExDex2Asm.java:42)\n\tat com.googlecode.d2j.dex.Dex2jar$2.convertCode(Dex2jar.java:128)\n\tat com.googlecode.d2j.dex.Dex2Asm.convertMethod(Dex2Asm.java:509)\n\tat com.googlecode.d2j.dex.Dex2Asm.convertClass(Dex2Asm.java:406)\n\tat com.googlecode.d2j.dex.Dex2Asm.convertDex(Dex2Asm.java:422)\n\tat com.googlecode.d2j.dex.Dex2jar.doTranslate(Dex2jar.java:172)\n\tat com.googlecode.d2j.dex.Dex2jar.to(Dex2jar.java:272)\n\tat com.googlecode.dex2jar.tools.Dex2jarCmd.doCommandLine(Dex2jarCmd.java:108)\n\tat com.googlecode.dex2jar.tools.BaseCmd.doMain(BaseCmd.java:288)\n\tat com.googlecode.dex2jar.tools.Dex2jarCmd.main(Dex2jarCmd.java:32)\n");
  }
  
  private char o()
  {
    label377:
    label454:
    label486:
    for (;;)
    {
      char c1;
      int i4;
      int i3;
      try
      {
        if (this.e == this.f)
        {
          boolean bool = b(1);
          if (!bool)
          {
            try
            {
              throw a(gguuuu.bк043Aккк043Aкк043A043A("\t#*\034*&#)\0351##_&5&%5+f;.;@1;14", 'Õ', '#', '\001'));
            }
            catch (Exception localException1)
            {
              throw localException1;
            }
            int i2 = this.e;
            c1 = '\000';
            i1 = i2;
            if (i1 >= i2 + 4) {
              break label454;
            }
            i4 = this.d[i1];
            i3 = (char)(c1 << '\004');
            if (i4 < 48) {
              continue;
            }
            try
            {
              throw new NullPointerException();
            }
            catch (Exception localException2)
            {
              b041E041EО041EОО = 56;
              if (i4 > 57) {
                continue;
              }
            }
            c1 = (char)(i3 + (i4 - 48));
            i1 += 1;
            if ((b041E041EО041EОО + bОООО041EО) * b041E041EО041EОО % bО041E041E041EОО == bОО041E041EОО) {
              break label486;
            }
            b041E041EО041EОО = b041E041E041E041EОО();
            bОО041E041EОО = b041E041E041E041EОО();
            continue;
          }
        }
        char[] arrayOfChar = this.d;
        int i1 = this.e;
        this.e = (i1 + 1);
        c1 = arrayOfChar[i1];
        switch (0)
        {
        case 1: 
        default: 
          switch (1)
          {
          }
          break;
        }
        switch (c1)
        {
        default: 
          return c1;
          if ((i4 < 97) || (i4 > 102)) {
            break label377;
          }
          c1 = (char)(i3 + (i4 - 97 + 10));
          break;
        case 'u': 
          i1 = this.e;
          if ((i1 + 4 <= this.f) || (b(4))) {
            continue;
          }
          throw a(gguuuu.bккккк043Aкк043A043A("s\f\021\001\r\007\002\006w\nyw2v\004ro}q+}ny|ksgh", 'ô', '\002'));
        }
      }
      catch (Exception localException3)
      {
        throw localException3;
      }
      return '\r';
      return '\f';
      if ((i4 >= 65) && (i4 <= 70))
      {
        c1 = (char)(i3 + (i4 - 65 + 10));
      }
      else
      {
        throw new NumberFormatException(gguuuu.bккккк043Aкк043A043A("Kc", 'Ç', '\003') + new String(this.d, this.e, 4));
        this.e += 4;
        return c1;
        this.g += 1;
        this.h = this.e;
        return c1;
      }
    }
    return '\t';
    return '\b';
    return '\n';
  }
  
  public final void a()
  {
    try
    {
      int i2 = this.i;
      if ((b041E041EО041EОО + bОООО041EО) * b041E041EО041EОО % b041EООО041EО() != bО041EОО041EО())
      {
        if ((b041E041EО041EОО + b041EО041E041EОО()) * b041E041EО041EОО % bО041E041E041EОО != bОО041E041EОО)
        {
          b041E041EО041EОО = b041E041E041E041EОО();
          bОО041E041EОО = 20;
        }
        b041E041EО041EОО = b041E041E041E041EОО();
        bОО041E041EОО = 10;
      }
      int i1 = i2;
      if (i2 == 0) {}
      try
      {
        i1 = i();
        if (i1 == 1)
        {
          a(3);
          break label205;
          this.i = 0;
        }
        else
        {
          IllegalStateException localIllegalStateException = new IllegalStateException(gguuuu.bккккк043Aкк043A043A("P\005}sr\005vv3VZ]`fxi]fbas@\004\030\030D\035\b\033H", '\013', '\000') + h() + gguuuu.bккккк043Aкк043A043A("\tI[\006QMQG\001", '\027', '\005') + (this.g + 1) + gguuuu.bк043Aккк043Aкк043A043A("c(53=68j", '', '¹', '\003') + m() + gguuuu.bккккк043Aкк043A043A("R\"\022$\027M", 'Ã', '\002') + n());
          throw localIllegalStateException;
        }
      }
      catch (Exception localException1)
      {
        throw localException1;
      }
      switch (1)
      {
      }
    }
    catch (Exception localException2)
    {
      throw localException2;
    }
    for (;;)
    {
      label205:
      switch (1)
      {
      }
    }
  }
  
  public final void b()
  {
    try
    {
      i2 = this.i;
      i1 = i2;
      if (i2 == 0) {
        i1 = i();
      }
      if (i1 == 2)
      {
        this.n -= 1;
        this.o[this.n] = null;
      }
    }
    catch (Exception localException1)
    {
      int i2;
      int i1;
      Object localObject;
      throw localException1;
    }
    try
    {
      if ((b041E041EО041EОО + bОООО041EО) * b041E041EО041EОО % bО041E041E041EОО != bОО041E041EОО)
      {
        b041E041EО041EОО = b041E041E041E041EОО();
        bОО041E041EОО = 23;
      }
      localObject = this.p;
      i1 = this.n - 1;
      i2 = localObject[i1];
      localObject[i1] = (i2 + 1);
      this.i = 0;
      return;
    }
    catch (Exception localException2)
    {
      throw localException2;
    }
    localObject = new IllegalStateException(gguuuu.bккккк043Aкк043A043A("]\020\007zw\bwu0T\\QkZLSMJZ%fxv!w`q\035", 'ö', '\002') + h() + gguuuu.bк043Aккк043Aкк043A043A("|=OyEAE;t", 'å', '<', '\002') + (this.g + 1) + gguuuu.bк043Aккк043Aкк043A043A("\036`kgoff\027", '\021', '\017', '\000') + m() + gguuuu.bккккк043Aкк043A043A("\"seyn'", '', '\000') + n());
    i1 = b041E041EО041EОО;
    switch (i1 * (bОООО041EО + i1) % bО041E041E041EОО)
    {
    default: 
      b041E041EО041EОО = b041E041E041E041EОО();
      bОО041E041EОО = b041E041E041E041EОО();
    }
    switch (0)
    {
    case 1: 
    default: 
      for (;;)
      {
        switch (1)
        {
        }
      }
    }
    throw ((Throwable)localObject);
  }
  
  public final boolean c()
  {
    int i2 = this.i;
    int i1 = i2;
    if (i2 == 0)
    {
      i2 = i();
      int i3 = b041E041EО041EОО;
      i1 = i2;
      switch (i3 * (bОООО041EО + i3) % b041EООО041EО())
      {
      default: 
        b041E041EО041EОО = 27;
        bОО041E041EОО = 34;
        i1 = i2;
      }
    }
    if ((i1 != 2) && (i1 != 4))
    {
      if ((b041E041EО041EОО + bОООО041EО) * b041E041EО041EОО % bО041E041E041EОО != bОО041E041EОО)
      {
        b041E041EО041EОО = b041E041E041E041EОО();
        bОО041E041EОО = 78;
      }
      return true;
    }
    return false;
  }
  
  /* Error */
  public final void close()
  {
    // Byte code:
    //   0: aload_0
    //   1: iconst_0
    //   2: putfield 93	com/appdynamics/repacked/gson/stream/a:i	I
    //   5: aload_0
    //   6: getfield 95	com/appdynamics/repacked/gson/stream/a:m	[I
    //   9: iconst_0
    //   10: bipush 8
    //   12: iastore
    //   13: getstatic 60	com/appdynamics/repacked/gson/stream/a:b041E041EО041EОО	I
    //   16: istore_1
    //   17: iload_1
    //   18: getstatic 109	com/appdynamics/repacked/gson/stream/a:bОООО041EО	I
    //   21: iload_1
    //   22: iadd
    //   23: imul
    //   24: invokestatic 112	com/appdynamics/repacked/gson/stream/a:b041EООО041EО	()I
    //   27: irem
    //   28: tableswitch	default:+20->48, 0:+30->58
    //   48: bipush 22
    //   50: putstatic 60	com/appdynamics/repacked/gson/stream/a:b041E041EО041EОО	I
    //   53: bipush 42
    //   55: putstatic 71	com/appdynamics/repacked/gson/stream/a:bОО041E041EОО	I
    //   58: getstatic 60	com/appdynamics/repacked/gson/stream/a:b041E041EО041EОО	I
    //   61: istore_1
    //   62: getstatic 109	com/appdynamics/repacked/gson/stream/a:bОООО041EО	I
    //   65: istore_2
    //   66: getstatic 66	com/appdynamics/repacked/gson/stream/a:bО041E041E041EОО	I
    //   69: istore_3
    //   70: iload_1
    //   71: iload_2
    //   72: iload_1
    //   73: iadd
    //   74: imul
    //   75: iload_3
    //   76: irem
    //   77: tableswitch	default:+19->96, 0:+31->108
    //   96: invokestatic 69	com/appdynamics/repacked/gson/stream/a:b041E041E041E041EОО	()I
    //   99: putstatic 60	com/appdynamics/repacked/gson/stream/a:b041E041EО041EОО	I
    //   102: invokestatic 69	com/appdynamics/repacked/gson/stream/a:b041E041E041E041EОО	()I
    //   105: putstatic 71	com/appdynamics/repacked/gson/stream/a:bОО041E041EОО	I
    //   108: aload_0
    //   109: iconst_1
    //   110: putfield 97	com/appdynamics/repacked/gson/stream/a:n	I
    //   113: aload_0
    //   114: getfield 103	com/appdynamics/repacked/gson/stream/a:b	Ljava/io/Reader;
    //   117: invokevirtual 337	java/io/Reader:close	()V
    //   120: return
    //   121: astore 4
    //   123: aload 4
    //   125: athrow
    //   126: astore 4
    //   128: aload 4
    //   130: athrow
    // Local variable table:
    //   start	length	slot	name	signature
    //   0	131	0	this	a
    //   16	59	1	i1	int
    //   65	9	2	i2	int
    //   69	8	3	i3	int
    //   121	3	4	localException1	Exception
    //   126	3	4	localException2	Exception
    // Exception table:
    //   from	to	target	type
    //   0	5	121	java/lang/Exception
    //   58	70	121	java/lang/Exception
    //   108	120	121	java/lang/Exception
    //   5	13	126	java/lang/Exception
    //   96	108	126	java/lang/Exception
  }
  
  public final String d()
  {
    try
    {
      int i2 = this.i;
      int i1 = i2;
      if (i2 == 0) {
        i1 = i();
      }
      if (i1 == 14) {
        localObject = l();
      }
      for (;;)
      {
        this.i = 0;
        try
        {
          this.o[(this.n - 1)] = localObject;
          return localObject;
        }
        catch (Exception localException1)
        {
          int i3;
          throw localException1;
        }
        if (i1 == 12)
        {
          localObject = b('\'');
        }
        else
        {
          if (i1 != 13) {
            break;
          }
          localObject = b('"');
        }
      }
      Object localObject = new IllegalStateException(gguuuu.bккккк043Aкк043A043A("a\026\017\005\004\026\b\bD\007F\026\n\027\020K\017##O(\023&S", '\016', '\004') + h() + gguuuu.bк043Aккк043Aкк043A043A("5u\b2}y}s-", '', '´', '\000') + (this.g + 1) + gguuuu.bккккк043Aкк043A043A("N\023 \036(!#U", 'ã', '\001') + m() + gguuuu.bк043Aккк043Aкк043A043A("{M?SH\001", 'ó', 'å', '\003') + n());
      i1 = b041E041EО041EОО;
      i2 = b041EО041E041EОО();
      i3 = b041E041EО041EОО;
      if ((i1 + i2) * i3 % bО041E041E041EОО != bОО041E041EОО)
      {
        b041E041EО041EОО = 26;
        bОО041E041EОО = 90;
        i1 = b041E041EО041EОО;
        switch (i1 * (b041EО041E041EОО() + i1) % bО041E041E041EОО)
        {
        default: 
          b041E041EО041EОО = 8;
          bОО041E041EОО = 81;
        }
      }
      switch (1)
      {
      case 0: 
      default: 
        for (;;)
        {
          switch (1)
          {
          }
        }
      }
      throw ((Throwable)localObject);
    }
    catch (Exception localException2)
    {
      throw localException2;
    }
  }
  
  public final String e()
  {
    int i2 = this.i;
    int i1 = i2;
    if (i2 == 0) {
      i1 = i();
    }
    switch (0)
    {
    case 1: 
    default: 
      for (;;)
      {
        switch (0)
        {
        }
      }
    }
    Object localObject1;
    if (i1 == 10) {
      localObject1 = l();
    }
    for (;;)
    {
      this.i = 0;
      Object localObject2 = this.p;
      i1 = this.n;
      i2 = b041E041EО041EОО;
      int i3 = bОООО041EО;
      int i4 = b041E041EО041EОО;
      int i5 = bО041E041E041EОО;
      switch (0)
      {
      case 1: 
      default: 
        for (;;)
        {
          switch (1)
          {
          }
        }
      }
      if ((i2 + i3) * i4 % i5 != bОО041E041EОО)
      {
        b041E041EО041EОО = b041E041E041E041EОО();
        bОО041E041EОО = b041E041E041E041EОО();
      }
      i1 -= 1;
      localObject2[i1] += 1;
      label380:
      do
      {
        return localObject1;
        while (i1 != 16)
        {
          throw new IllegalStateException(gguuuu.bккккк043Aкк043A043A("&XOC@P@>x9vIIF<@8o1CAkB+<g", '_', '\002') + h() + gguuuu.bккккк043Aкк043A043A("=\024@\016\f\022\nE", '4', '\001') + (this.g + 1) + gguuuu.bккккк043Aкк043A043A("/s\001~\t\002\0046", '', '\001') + m() + gguuuu.bк043Aккк043Aкк043A043A("\032k]qf\037", ')', '/', '\001') + n());
          if (i1 == 8)
          {
            localObject1 = b('\'');
            break;
          }
          if (i1 != 9) {
            break label380;
          }
          localObject1 = b('"');
          break;
        }
        localObject1 = new String(this.d, this.e, this.k);
        this.e += this.k;
        break;
        if (i1 == 11)
        {
          localObject1 = this.l;
          this.l = null;
          break;
        }
      } while (i1 != 15);
      localObject2 = Long.toString(this.j);
      i1 = b041E041EО041EОО;
      localObject1 = localObject2;
      switch (i1 * (bОООО041EО + i1) % bО041E041E041EОО)
      {
      }
      b041E041EО041EОО = 27;
      bОО041E041EОО = b041E041E041E041EОО();
      localObject1 = localObject2;
    }
  }
  
  public final long f()
  {
    int i2 = this.i;
    int i1 = i2;
    if (i2 == 0) {
      i1 = i();
    }
    int[] arrayOfInt;
    if (i1 == 15)
    {
      this.i = 0;
      arrayOfInt = this.p;
      i1 = this.n - 1;
      arrayOfInt[i1] += 1;
      return this.j;
      this.l = null;
      this.i = 0;
      arrayOfInt = this.p;
      i1 = this.n - 1;
      arrayOfInt[i1] += 1;
      Object localObject;
      return localObject;
    }
    if (i1 == 16)
    {
      this.l = new String(this.d, this.e, this.k);
      this.e += this.k;
    }
    for (;;)
    {
      i1 = b041E041EО041EОО;
      switch (i1 * (bОООО041EО + i1) % bО041E041E041EОО)
      {
      default: 
        b041E041EО041EОО = b041E041E041E041EОО();
        bОО041E041EОО = b041E041E041E041EОО();
      }
      this.i = 11;
      double d1 = Double.parseDouble(this.l);
      long l1 = d1;
      i1 = b041E041EО041EОО;
      switch (i1 * (bОООО041EО + i1) % b041EООО041EО())
      {
      default: 
        b041E041EО041EОО = 77;
        bОО041E041EОО = 91;
      }
      if (l1 == d1) {
        break;
      }
      throw new NumberFormatException(gguuuu.bк043Aккк043Aкк043A043A("w*!\025\022\"\022\020J\013H\024\026\024\fC\005\027\025?\026~\020;", '°', '', '\002') + this.l + gguuuu.bк043Aккк043Aкк043A043A("N\021%Q\037\035#\033V", 'õ', 'Ç', '\001') + (this.g + 1) + gguuuu.bккккк043Aкк043A043A("\034^iemdd\025", '', '\005') + m() + gguuuu.bккккк043Aкк043A043A(".}mr)", '÷', '\003') + n());
      throw new IllegalStateException(gguuuu.bк043Aккк043Aкк043A043A("2f_UTfXX\025W\027dhhb\034_ss xcv$", 'Þ', 'ñ', '\001') + h() + gguuuu.bккккк043Aкк043A043A("l-?i515+d", 'Y', '\003') + (this.g + 1) + gguuuu.bк043Aккк043Aкк043A043A("\006HSOWNN~", '\036', '', '\000') + m() + gguuuu.bккккк043Aкк043A043A("]-\035/\"X", 'Á', '\005') + n());
      if (i1 == 8) {}
      for (char c1 = '\'';; c1 = '"')
      {
        this.l = b(c1);
        try
        {
          l1 = Long.parseLong(this.l);
          this.i = 0;
          arrayOfInt = this.p;
          i1 = this.n;
          i1 -= 1;
          arrayOfInt[i1] += 1;
          return l1;
        }
        catch (NumberFormatException localNumberFormatException) {}
        if ((i1 != 8) && (i1 != 9)) {
          break;
        }
        switch (1)
        {
        }
        for (;;)
        {
          switch (1)
          {
          }
        }
      }
    }
  }
  
  /* Error */
  public final void g()
  {
    // Byte code:
    //   0: iconst_2
    //   1: istore_2
    //   2: iconst_0
    //   3: istore_1
    //   4: aload_0
    //   5: getfield 93	com/appdynamics/repacked/gson/stream/a:i	I
    //   8: istore 4
    //   10: iload 4
    //   12: istore_3
    //   13: iload 4
    //   15: ifne +8 -> 23
    //   18: aload_0
    //   19: invokespecial 201	com/appdynamics/repacked/gson/stream/a:i	()I
    //   22: istore_3
    //   23: iload_3
    //   24: iconst_3
    //   25: if_icmpne +319 -> 344
    //   28: aload_0
    //   29: iconst_1
    //   30: invokespecial 312	com/appdynamics/repacked/gson/stream/a:a	(I)V
    //   33: iload_1
    //   34: iconst_1
    //   35: iadd
    //   36: istore_1
    //   37: aload_0
    //   38: iconst_0
    //   39: putfield 93	com/appdynamics/repacked/gson/stream/a:i	I
    //   42: iload_1
    //   43: ifne +461 -> 504
    //   46: aload_0
    //   47: getfield 101	com/appdynamics/repacked/gson/stream/a:p	[I
    //   50: astore 6
    //   52: aload_0
    //   53: getfield 97	com/appdynamics/repacked/gson/stream/a:n	I
    //   56: iconst_1
    //   57: isub
    //   58: istore_1
    //   59: aload 6
    //   61: iload_1
    //   62: aload 6
    //   64: iload_1
    //   65: iaload
    //   66: iconst_1
    //   67: iadd
    //   68: iastore
    //   69: aload_0
    //   70: getfield 99	com/appdynamics/repacked/gson/stream/a:o	[Ljava/lang/String;
    //   73: astore 6
    //   75: aload_0
    //   76: getfield 97	com/appdynamics/repacked/gson/stream/a:n	I
    //   79: istore_1
    //   80: aload 6
    //   82: iload_1
    //   83: iconst_1
    //   84: isub
    //   85: ldc_w 397
    //   88: bipush 45
    //   90: iconst_1
    //   91: invokestatic 52	kkkkkk/gguuuu:bккккк043Aкк043A043A	(Ljava/lang/String;CC)Ljava/lang/String;
    //   94: aastore
    //   95: return
    //   96: iload_3
    //   97: bipush 9
    //   99: if_icmpeq +9 -> 108
    //   102: iload_3
    //   103: bipush 13
    //   105: if_icmpne +12 -> 117
    //   108: aload_0
    //   109: bipush 34
    //   111: invokespecial 399	com/appdynamics/repacked/gson/stream/a:c	(C)V
    //   114: goto +393 -> 507
    //   117: iload_3
    //   118: bipush 16
    //   120: if_icmpne +381 -> 501
    //   123: aload_0
    //   124: getfield 85	com/appdynamics/repacked/gson/stream/a:e	I
    //   127: istore_3
    //   128: aload_0
    //   129: iload_3
    //   130: aload_0
    //   131: getfield 359	com/appdynamics/repacked/gson/stream/a:k	I
    //   134: iadd
    //   135: putfield 85	com/appdynamics/repacked/gson/stream/a:e	I
    //   138: goto -101 -> 37
    //   141: aload_0
    //   142: getfield 85	com/appdynamics/repacked/gson/stream/a:e	I
    //   145: iload_3
    //   146: iadd
    //   147: aload_0
    //   148: getfield 87	com/appdynamics/repacked/gson/stream/a:f	I
    //   151: if_icmpge +168 -> 319
    //   154: aload_0
    //   155: getfield 83	com/appdynamics/repacked/gson/stream/a:d	[C
    //   158: aload_0
    //   159: getfield 85	com/appdynamics/repacked/gson/stream/a:e	I
    //   162: iload_3
    //   163: iadd
    //   164: caload
    //   165: lookupswitch	default:+414->579, 9:+275->440, 10:+275->440, 12:+275->440, 13:+275->440, 32:+275->440, 35:+309->474, 44:+275->440, 47:+309->474, 58:+275->440, 59:+309->474, 61:+309->474, 91:+275->440, 92:+309->474, 93:+275->440, 123:+275->440, 125:+275->440
    //   304: astore 6
    //   306: invokestatic 69	com/appdynamics/repacked/gson/stream/a:b041E041E041E041EОО	()I
    //   309: putstatic 60	com/appdynamics/repacked/gson/stream/a:b041E041EО041EОО	I
    //   312: iload_1
    //   313: iconst_1
    //   314: isub
    //   315: istore_1
    //   316: goto -279 -> 37
    //   319: aload_0
    //   320: iload_3
    //   321: aload_0
    //   322: getfield 85	com/appdynamics/repacked/gson/stream/a:e	I
    //   325: iadd
    //   326: putfield 85	com/appdynamics/repacked/gson/stream/a:e	I
    //   329: aload_0
    //   330: iconst_1
    //   331: invokespecial 107	com/appdynamics/repacked/gson/stream/a:b	(I)Z
    //   334: istore 5
    //   336: iload 5
    //   338: ifne +236 -> 574
    //   341: goto -304 -> 37
    //   344: iload_3
    //   345: iconst_1
    //   346: if_icmpne +15 -> 361
    //   349: aload_0
    //   350: iconst_3
    //   351: invokespecial 312	com/appdynamics/repacked/gson/stream/a:a	(I)V
    //   354: iload_1
    //   355: iconst_1
    //   356: iadd
    //   357: istore_1
    //   358: goto -321 -> 37
    //   361: iload_3
    //   362: iconst_4
    //   363: if_icmpne +55 -> 418
    //   366: aload_0
    //   367: aload_0
    //   368: getfield 97	com/appdynamics/repacked/gson/stream/a:n	I
    //   371: iconst_1
    //   372: isub
    //   373: putfield 97	com/appdynamics/repacked/gson/stream/a:n	I
    //   376: iload_2
    //   377: iconst_0
    //   378: idiv
    //   379: istore_3
    //   380: iload_3
    //   381: istore_2
    //   382: getstatic 60	com/appdynamics/repacked/gson/stream/a:b041E041EО041EОО	I
    //   385: getstatic 109	com/appdynamics/repacked/gson/stream/a:bОООО041EО	I
    //   388: iadd
    //   389: getstatic 60	com/appdynamics/repacked/gson/stream/a:b041E041EО041EОО	I
    //   392: imul
    //   393: getstatic 66	com/appdynamics/repacked/gson/stream/a:bО041E041E041EОО	I
    //   396: irem
    //   397: getstatic 71	com/appdynamics/repacked/gson/stream/a:bОО041E041EОО	I
    //   400: if_icmpeq -24 -> 376
    //   403: bipush 41
    //   405: putstatic 60	com/appdynamics/repacked/gson/stream/a:b041E041EО041EОО	I
    //   408: bipush 68
    //   410: putstatic 71	com/appdynamics/repacked/gson/stream/a:bОО041E041EОО	I
    //   413: iload_3
    //   414: istore_2
    //   415: goto -39 -> 376
    //   418: iload_3
    //   419: iconst_2
    //   420: if_icmpne +142 -> 562
    //   423: aload_0
    //   424: aload_0
    //   425: getfield 97	com/appdynamics/repacked/gson/stream/a:n	I
    //   428: iconst_1
    //   429: isub
    //   430: putfield 97	com/appdynamics/repacked/gson/stream/a:n	I
    //   433: iload_1
    //   434: iconst_1
    //   435: isub
    //   436: istore_1
    //   437: goto -400 -> 37
    //   440: aload_0
    //   441: iload_3
    //   442: aload_0
    //   443: getfield 85	com/appdynamics/repacked/gson/stream/a:e	I
    //   446: iadd
    //   447: putfield 85	com/appdynamics/repacked/gson/stream/a:e	I
    //   450: goto -413 -> 37
    //   453: iload_3
    //   454: bipush 8
    //   456: if_icmpeq +9 -> 465
    //   459: iload_3
    //   460: bipush 12
    //   462: if_icmpne -366 -> 96
    //   465: aload_0
    //   466: bipush 39
    //   468: invokespecial 399	com/appdynamics/repacked/gson/stream/a:c	(C)V
    //   471: goto -434 -> 37
    //   474: aload_0
    //   475: ldc_w 401
    //   478: sipush 174
    //   481: bipush 28
    //   483: iconst_0
    //   484: invokestatic 122	kkkkkk/gguuuu:bк043Aккк043Aкк043A043A	(Ljava/lang/String;CCC)Ljava/lang/String;
    //   487: invokespecial 146	com/appdynamics/repacked/gson/stream/a:a	(Ljava/lang/String;)Ljava/io/IOException;
    //   490: athrow
    //   491: astore 6
    //   493: aload 6
    //   495: athrow
    //   496: astore 6
    //   498: aload 6
    //   500: athrow
    //   501: goto -464 -> 37
    //   504: goto -500 -> 4
    //   507: iconst_1
    //   508: tableswitch	default:+24->532, 0:+-1->507, 1:+51->559
    //   532: iconst_0
    //   533: tableswitch	default:+23->556, 0:+26->559, 1:+-26->507
    //   556: goto -24 -> 532
    //   559: goto -522 -> 37
    //   562: iload_3
    //   563: bipush 14
    //   565: if_icmpeq +9 -> 574
    //   568: iload_3
    //   569: bipush 10
    //   571: if_icmpne -118 -> 453
    //   574: iconst_0
    //   575: istore_3
    //   576: goto -435 -> 141
    //   579: iload_3
    //   580: iconst_1
    //   581: iadd
    //   582: istore_3
    //   583: goto -442 -> 141
    // Local variable table:
    //   start	length	slot	name	signature
    //   0	586	0	this	a
    //   3	434	1	i1	int
    //   1	414	2	i2	int
    //   12	571	3	i3	int
    //   8	6	4	i4	int
    //   334	3	5	bool	boolean
    //   50	31	6	localObject	Object
    //   304	1	6	localException1	Exception
    //   491	3	6	localException2	Exception
    //   496	3	6	localException3	Exception
    // Exception table:
    //   from	to	target	type
    //   376	380	304	java/lang/Exception
    //   18	23	491	java/lang/Exception
    //   108	114	491	java/lang/Exception
    //   123	128	491	java/lang/Exception
    //   329	336	491	java/lang/Exception
    //   465	471	491	java/lang/Exception
    //   474	491	491	java/lang/Exception
    //   4	10	496	java/lang/Exception
    //   28	33	496	java/lang/Exception
    //   37	42	496	java/lang/Exception
    //   46	59	496	java/lang/Exception
    //   69	80	496	java/lang/Exception
    //   80	95	496	java/lang/Exception
    //   128	138	496	java/lang/Exception
    //   141	304	496	java/lang/Exception
    //   306	312	496	java/lang/Exception
    //   319	329	496	java/lang/Exception
    //   349	354	496	java/lang/Exception
    //   366	376	496	java/lang/Exception
    //   423	433	496	java/lang/Exception
    //   440	450	496	java/lang/Exception
  }
  
  public final String toString()
  {
    StringBuilder localStringBuilder = new StringBuilder();
    switch (1)
    {
    case 0: 
    default: 
      for (;;)
      {
        switch (0)
        {
        }
      }
    }
    localStringBuilder = localStringBuilder.append(getClass().getSimpleName()).append(gguuuu.bк043Aккк043Aкк043A043A("\023Se\020[W[Q\013", 'x', 'k', '\000'));
    int i1 = this.g;
    if ((b041E041EО041EОО + bОООО041EО) * b041E041EО041EОО % bО041E041E041EОО != bО041EОО041EО())
    {
      switch (1)
      {
      case 0: 
      default: 
        for (;;)
        {
          switch (1)
          {
          }
        }
      }
      b041E041EО041EОО = 46;
      if ((b041E041EО041EОО + bОООО041EО) * b041E041EО041EОО % bО041E041E041EОО != bОО041E041EОО)
      {
        b041E041EО041EОО = 9;
        bОО041E041EОО = 6;
      }
      bОО041E041EОО = 95;
    }
    return i1 + 1 + gguuuu.bккккк043Aкк043A043A("B\007\024\022\034\025\027I", 'ß', '\001') + m();
  }
}
