package com.appdynamics.repacked.gson.stream;

import kkkkkk.gguuuu;

public enum b
{
  /* Error */
  static
  {
    // Byte code:
    //   0: new 2	com/appdynamics/repacked/gson/stream/b
    //   3: dup
    //   4: ldc 21
    //   6: bipush 97
    //   8: bipush 55
    //   10: iconst_3
    //   11: invokestatic 27	kkkkkk/gguuuu:bк043Aккк043Aкк043A043A	(Ljava/lang/String;CCC)Ljava/lang/String;
    //   14: iconst_0
    //   15: invokespecial 31	com/appdynamics/repacked/gson/stream/b:<init>	(Ljava/lang/String;I)V
    //   18: putstatic 33	com/appdynamics/repacked/gson/stream/b:a	Lcom/appdynamics/repacked/gson/stream/b;
    //   21: new 2	com/appdynamics/repacked/gson/stream/b
    //   24: dup
    //   25: ldc 35
    //   27: bipush 48
    //   29: iconst_1
    //   30: invokestatic 39	kkkkkk/gguuuu:bккккк043Aкк043A043A	(Ljava/lang/String;CC)Ljava/lang/String;
    //   33: iconst_1
    //   34: invokespecial 31	com/appdynamics/repacked/gson/stream/b:<init>	(Ljava/lang/String;I)V
    //   37: astore 5
    //   39: invokestatic 43	com/appdynamics/repacked/gson/stream/b:b041E041EООО041E	()I
    //   42: invokestatic 46	com/appdynamics/repacked/gson/stream/b:b041EО041EОО041E	()I
    //   45: iadd
    //   46: invokestatic 43	com/appdynamics/repacked/gson/stream/b:b041E041EООО041E	()I
    //   49: imul
    //   50: invokestatic 49	com/appdynamics/repacked/gson/stream/b:bО041E041EОО041E	()I
    //   53: irem
    //   54: invokestatic 52	com/appdynamics/repacked/gson/stream/b:bОО041EОО041E	()I
    //   57: if_icmpeq +3 -> 60
    //   60: aload 5
    //   62: putstatic 54	com/appdynamics/repacked/gson/stream/b:b	Lcom/appdynamics/repacked/gson/stream/b;
    //   65: new 2	com/appdynamics/repacked/gson/stream/b
    //   68: dup
    //   69: ldc 56
    //   71: bipush 111
    //   73: iconst_4
    //   74: invokestatic 39	kkkkkk/gguuuu:bккккк043Aкк043A043A	(Ljava/lang/String;CC)Ljava/lang/String;
    //   77: iconst_2
    //   78: invokespecial 31	com/appdynamics/repacked/gson/stream/b:<init>	(Ljava/lang/String;I)V
    //   81: putstatic 58	com/appdynamics/repacked/gson/stream/b:c	Lcom/appdynamics/repacked/gson/stream/b;
    //   84: new 2	com/appdynamics/repacked/gson/stream/b
    //   87: dup
    //   88: ldc 60
    //   90: bipush 39
    //   92: iconst_5
    //   93: invokestatic 39	kkkkkk/gguuuu:bккккк043Aкк043A043A	(Ljava/lang/String;CC)Ljava/lang/String;
    //   96: iconst_3
    //   97: invokespecial 31	com/appdynamics/repacked/gson/stream/b:<init>	(Ljava/lang/String;I)V
    //   100: astore 5
    //   102: aload 5
    //   104: putstatic 62	com/appdynamics/repacked/gson/stream/b:d	Lcom/appdynamics/repacked/gson/stream/b;
    //   107: new 2	com/appdynamics/repacked/gson/stream/b
    //   110: dup
    //   111: ldc 64
    //   113: sipush 185
    //   116: iconst_2
    //   117: invokestatic 39	kkkkkk/gguuuu:bккккк043Aкк043A043A	(Ljava/lang/String;CC)Ljava/lang/String;
    //   120: iconst_4
    //   121: invokespecial 31	com/appdynamics/repacked/gson/stream/b:<init>	(Ljava/lang/String;I)V
    //   124: putstatic 66	com/appdynamics/repacked/gson/stream/b:e	Lcom/appdynamics/repacked/gson/stream/b;
    //   127: new 2	com/appdynamics/repacked/gson/stream/b
    //   130: dup
    //   131: ldc 68
    //   133: bipush 42
    //   135: iconst_5
    //   136: invokestatic 39	kkkkkk/gguuuu:bккккк043Aкк043A043A	(Ljava/lang/String;CC)Ljava/lang/String;
    //   139: iconst_5
    //   140: invokespecial 31	com/appdynamics/repacked/gson/stream/b:<init>	(Ljava/lang/String;I)V
    //   143: putstatic 70	com/appdynamics/repacked/gson/stream/b:f	Lcom/appdynamics/repacked/gson/stream/b;
    //   146: new 2	com/appdynamics/repacked/gson/stream/b
    //   149: dup
    //   150: ldc 72
    //   152: sipush 212
    //   155: sipush 157
    //   158: iconst_0
    //   159: invokestatic 27	kkkkkk/gguuuu:bк043Aккк043Aкк043A043A	(Ljava/lang/String;CCC)Ljava/lang/String;
    //   162: bipush 6
    //   164: invokespecial 31	com/appdynamics/repacked/gson/stream/b:<init>	(Ljava/lang/String;I)V
    //   167: putstatic 74	com/appdynamics/repacked/gson/stream/b:g	Lcom/appdynamics/repacked/gson/stream/b;
    //   170: new 2	com/appdynamics/repacked/gson/stream/b
    //   173: dup
    //   174: ldc 76
    //   176: bipush 39
    //   178: iconst_1
    //   179: invokestatic 39	kkkkkk/gguuuu:bккккк043Aкк043A043A	(Ljava/lang/String;CC)Ljava/lang/String;
    //   182: bipush 7
    //   184: invokespecial 31	com/appdynamics/repacked/gson/stream/b:<init>	(Ljava/lang/String;I)V
    //   187: astore 5
    //   189: invokestatic 43	com/appdynamics/repacked/gson/stream/b:b041E041EООО041E	()I
    //   192: istore_0
    //   193: invokestatic 46	com/appdynamics/repacked/gson/stream/b:b041EО041EОО041E	()I
    //   196: istore_1
    //   197: invokestatic 43	com/appdynamics/repacked/gson/stream/b:b041E041EООО041E	()I
    //   200: istore_2
    //   201: invokestatic 49	com/appdynamics/repacked/gson/stream/b:bО041E041EОО041E	()I
    //   204: istore_3
    //   205: invokestatic 52	com/appdynamics/repacked/gson/stream/b:bОО041EОО041E	()I
    //   208: istore 4
    //   210: iload_0
    //   211: iload_1
    //   212: iadd
    //   213: iload_2
    //   214: imul
    //   215: iload_3
    //   216: irem
    //   217: iload 4
    //   219: if_icmpeq +3 -> 222
    //   222: aload 5
    //   224: putstatic 78	com/appdynamics/repacked/gson/stream/b:h	Lcom/appdynamics/repacked/gson/stream/b;
    //   227: new 2	com/appdynamics/repacked/gson/stream/b
    //   230: dup
    //   231: ldc 80
    //   233: bipush 50
    //   235: iconst_1
    //   236: invokestatic 39	kkkkkk/gguuuu:bккккк043Aкк043A043A	(Ljava/lang/String;CC)Ljava/lang/String;
    //   239: bipush 8
    //   241: invokespecial 31	com/appdynamics/repacked/gson/stream/b:<init>	(Ljava/lang/String;I)V
    //   244: astore 5
    //   246: aload 5
    //   248: putstatic 82	com/appdynamics/repacked/gson/stream/b:i	Lcom/appdynamics/repacked/gson/stream/b;
    //   251: new 2	com/appdynamics/repacked/gson/stream/b
    //   254: dup
    //   255: ldc 84
    //   257: bipush 127
    //   259: iconst_1
    //   260: invokestatic 39	kkkkkk/gguuuu:bккккк043Aкк043A043A	(Ljava/lang/String;CC)Ljava/lang/String;
    //   263: bipush 9
    //   265: invokespecial 31	com/appdynamics/repacked/gson/stream/b:<init>	(Ljava/lang/String;I)V
    //   268: putstatic 86	com/appdynamics/repacked/gson/stream/b:j	Lcom/appdynamics/repacked/gson/stream/b;
    //   271: getstatic 33	com/appdynamics/repacked/gson/stream/b:a	Lcom/appdynamics/repacked/gson/stream/b;
    //   274: astore 5
    //   276: getstatic 54	com/appdynamics/repacked/gson/stream/b:b	Lcom/appdynamics/repacked/gson/stream/b;
    //   279: astore 5
    //   281: getstatic 58	com/appdynamics/repacked/gson/stream/b:c	Lcom/appdynamics/repacked/gson/stream/b;
    //   284: astore 5
    //   286: getstatic 62	com/appdynamics/repacked/gson/stream/b:d	Lcom/appdynamics/repacked/gson/stream/b;
    //   289: astore 5
    //   291: getstatic 66	com/appdynamics/repacked/gson/stream/b:e	Lcom/appdynamics/repacked/gson/stream/b;
    //   294: astore 5
    //   296: getstatic 70	com/appdynamics/repacked/gson/stream/b:f	Lcom/appdynamics/repacked/gson/stream/b;
    //   299: astore 5
    //   301: getstatic 74	com/appdynamics/repacked/gson/stream/b:g	Lcom/appdynamics/repacked/gson/stream/b;
    //   304: astore 5
    //   306: getstatic 78	com/appdynamics/repacked/gson/stream/b:h	Lcom/appdynamics/repacked/gson/stream/b;
    //   309: astore 5
    //   311: getstatic 82	com/appdynamics/repacked/gson/stream/b:i	Lcom/appdynamics/repacked/gson/stream/b;
    //   314: astore 5
    //   316: getstatic 86	com/appdynamics/repacked/gson/stream/b:j	Lcom/appdynamics/repacked/gson/stream/b;
    //   319: astore 5
    //   321: return
    //   322: astore 5
    //   324: aload 5
    //   326: athrow
    //   327: astore 5
    //   329: aload 5
    //   331: athrow
    //   332: astore 5
    //   334: aload 5
    //   336: athrow
    //   337: astore 5
    //   339: aload 5
    //   341: athrow
    // Local variable table:
    //   start	length	slot	name	signature
    //   192	21	0	k	int
    //   196	17	1	m	int
    //   200	15	2	n	int
    //   204	13	3	i1	int
    //   208	12	4	i2	int
    //   37	283	5	localB	b
    //   322	3	5	localException1	Exception
    //   327	3	5	localException2	Exception
    //   332	3	5	localException3	Exception
    //   337	3	5	localException4	Exception
    // Exception table:
    //   from	to	target	type
    //   0	39	322	java/lang/Exception
    //   60	84	322	java/lang/Exception
    //   102	170	322	java/lang/Exception
    //   222	246	322	java/lang/Exception
    //   316	321	322	java/lang/Exception
    //   324	327	327	java/lang/Exception
    //   334	337	327	java/lang/Exception
    //   84	102	332	java/lang/Exception
    //   170	189	332	java/lang/Exception
    //   246	316	332	java/lang/Exception
    //   189	210	337	java/lang/Exception
  }
  
  public static int b041E041EООО041E()
  {
    return 22;
  }
  
  public static int b041EО041EОО041E()
  {
    return 1;
  }
  
  public static int bО041E041EОО041E()
  {
    return 2;
  }
  
  public static int bОО041EОО041E()
  {
    return 0;
  }
}
