package com.mobile.ui.marketinghub.fragment;

import android.os.Bundle;
import android.support.annotation.Nullable;
import android.view.LayoutInflater;
import android.view.View;
import android.view.ViewGroup;
import com.mobile.ui.App;
import com.mobile.ui.R.layout;
import com.mobile.ui.common.fragment.BasePresentationFragment;
import com.mobile.ui.marketinghub.activity.MarketingHubActivity;
import com.mobile.ui.settings.activity.PersonalDetailsSettingsActivity;
import kkkkkk.laaala;
import kkkkkk.llaala;
import kkkkkk.uyyyyy;

public class MarketingHubUpdateSuccessFragment
  extends BasePresentationFragment<laaala, llaala>
  implements laaala
{
  public static int b041704170417З0417ЗЗ0417 = 96;
  public static int b0417ЗЗ04170417ЗЗ0417 = 1;
  public static int bЗ0417З04170417ЗЗ0417 = 2;
  public static int bЗЗЗ04170417ЗЗ0417;
  private MarketingHubActivity mMarketingHubActivity;
  
  public MarketingHubUpdateSuccessFragment() {}
  
  public static int b04170417З04170417ЗЗ0417()
  {
    return 67;
  }
  
  public static int b0417З041704170417ЗЗ0417()
  {
    return 2;
  }
  
  public static int bЗ0417041704170417ЗЗ0417()
  {
    return 1;
  }
  
  public static int bЗЗ041704170417ЗЗ0417()
  {
    return 0;
  }
  
  public static MarketingHubUpdateSuccessFragment newInstance()
  {
    int i = b04170417З04170417ЗЗ0417();
    switch (i * (b0417ЗЗ04170417ЗЗ0417 + i) % bЗ0417З04170417ЗЗ0417)
    {
    default: 
      b041704170417З0417ЗЗ0417 = b04170417З04170417ЗЗ0417();
      bЗЗЗ04170417ЗЗ0417 = b04170417З04170417ЗЗ0417();
    }
    try
    {
      MarketingHubUpdateSuccessFragment localMarketingHubUpdateSuccessFragment = new MarketingHubUpdateSuccessFragment();
      return localMarketingHubUpdateSuccessFragment;
    }
    catch (Exception localException)
    {
      throw localException;
    }
  }
  
  public void disableUpButton()
  {
    switch (0)
    {
    case 1: 
    default: 
      for (;;)
      {
        switch (1)
        {
        }
      }
    }
    MarketingHubActivity localMarketingHubActivity = this.mMarketingHubActivity;
    int i = b041704170417З0417ЗЗ0417;
    switch (i * (b0417ЗЗ04170417ЗЗ0417 + i) % bЗ0417З04170417ЗЗ0417)
    {
    default: 
      b041704170417З0417ЗЗ0417 = 58;
      bЗЗЗ04170417ЗЗ0417 = b04170417З04170417ЗЗ0417();
      if ((b04170417З04170417ЗЗ0417() + b0417ЗЗ04170417ЗЗ0417) * b04170417З04170417ЗЗ0417() % b0417З041704170417ЗЗ0417() != bЗЗЗ04170417ЗЗ0417)
      {
        b041704170417З0417ЗЗ0417 = b04170417З04170417ЗЗ0417();
        bЗЗЗ04170417ЗЗ0417 = 78;
      }
      break;
    }
    localMarketingHubActivity.enableBackNavigation(false);
  }
  
  /* Error */
  @Nullable
  public String getAccessibilityScreenTitle()
  {
    // Byte code:
    //   0: getstatic 26	com/mobile/ui/marketinghub/fragment/MarketingHubUpdateSuccessFragment:b041704170417З0417ЗЗ0417	I
    //   3: istore_1
    //   4: getstatic 28	com/mobile/ui/marketinghub/fragment/MarketingHubUpdateSuccessFragment:b0417ЗЗ04170417ЗЗ0417	I
    //   7: istore_2
    //   8: getstatic 30	com/mobile/ui/marketinghub/fragment/MarketingHubUpdateSuccessFragment:bЗ0417З04170417ЗЗ0417	I
    //   11: istore_3
    //   12: iload_1
    //   13: iload_2
    //   14: iload_1
    //   15: iadd
    //   16: imul
    //   17: iload_3
    //   18: irem
    //   19: tableswitch	default:+17->36, 0:+62->81
    //   36: invokestatic 36	com/mobile/ui/marketinghub/fragment/MarketingHubUpdateSuccessFragment:b04170417З04170417ЗЗ0417	()I
    //   39: putstatic 26	com/mobile/ui/marketinghub/fragment/MarketingHubUpdateSuccessFragment:b041704170417З0417ЗЗ0417	I
    //   42: invokestatic 36	com/mobile/ui/marketinghub/fragment/MarketingHubUpdateSuccessFragment:b04170417З04170417ЗЗ0417	()I
    //   45: putstatic 32	com/mobile/ui/marketinghub/fragment/MarketingHubUpdateSuccessFragment:bЗЗЗ04170417ЗЗ0417	I
    //   48: getstatic 26	com/mobile/ui/marketinghub/fragment/MarketingHubUpdateSuccessFragment:b041704170417З0417ЗЗ0417	I
    //   51: getstatic 28	com/mobile/ui/marketinghub/fragment/MarketingHubUpdateSuccessFragment:b0417ЗЗ04170417ЗЗ0417	I
    //   54: iadd
    //   55: getstatic 26	com/mobile/ui/marketinghub/fragment/MarketingHubUpdateSuccessFragment:b041704170417З0417ЗЗ0417	I
    //   58: imul
    //   59: getstatic 30	com/mobile/ui/marketinghub/fragment/MarketingHubUpdateSuccessFragment:bЗ0417З04170417ЗЗ0417	I
    //   62: irem
    //   63: getstatic 32	com/mobile/ui/marketinghub/fragment/MarketingHubUpdateSuccessFragment:bЗЗЗ04170417ЗЗ0417	I
    //   66: if_icmpeq +15 -> 81
    //   69: invokestatic 36	com/mobile/ui/marketinghub/fragment/MarketingHubUpdateSuccessFragment:b04170417З04170417ЗЗ0417	()I
    //   72: putstatic 26	com/mobile/ui/marketinghub/fragment/MarketingHubUpdateSuccessFragment:b041704170417З0417ЗЗ0417	I
    //   75: invokestatic 36	com/mobile/ui/marketinghub/fragment/MarketingHubUpdateSuccessFragment:b04170417З04170417ЗЗ0417	()I
    //   78: putstatic 32	com/mobile/ui/marketinghub/fragment/MarketingHubUpdateSuccessFragment:bЗЗЗ04170417ЗЗ0417	I
    //   81: getstatic 65	com/mobile/ui/R$string:accessibility_marketing_hub_success_page_header	I
    //   84: istore_1
    //   85: aload_0
    //   86: iload_1
    //   87: invokevirtual 69	com/mobile/ui/marketinghub/fragment/MarketingHubUpdateSuccessFragment:getString	(I)Ljava/lang/String;
    //   90: astore 4
    //   92: aload 4
    //   94: areturn
    //   95: astore 4
    //   97: aload 4
    //   99: athrow
    //   100: astore 4
    //   102: aload 4
    //   104: athrow
    //   105: astore 4
    //   107: aload 4
    //   109: athrow
    //   110: astore 4
    //   112: aload 4
    //   114: athrow
    // Local variable table:
    //   start	length	slot	name	signature
    //   0	115	0	this	MarketingHubUpdateSuccessFragment
    //   3	84	1	i	int
    //   7	9	2	j	int
    //   11	8	3	k	int
    //   90	3	4	str	String
    //   95	3	4	localException1	Exception
    //   100	3	4	localException2	Exception
    //   105	3	4	localException3	Exception
    //   110	3	4	localException4	Exception
    // Exception table:
    //   from	to	target	type
    //   81	85	95	java/lang/Exception
    //   0	12	100	java/lang/Exception
    //   97	100	100	java/lang/Exception
    //   107	110	100	java/lang/Exception
    //   85	92	105	java/lang/Exception
    //   36	48	110	java/lang/Exception
  }
  
  public void handleBackButtonEvent()
  {
    Object localObject = this.mPresenter;
    switch (1)
    {
    case 0: 
    default: 
      for (;;)
      {
        switch (1)
        {
        }
      }
    }
    localObject = (llaala)localObject;
    if ((b041704170417З0417ЗЗ0417 + bЗ0417041704170417ЗЗ0417()) * b041704170417З0417ЗЗ0417 % bЗ0417З04170417ЗЗ0417 != bЗЗЗ04170417ЗЗ0417)
    {
      int i = b04170417З04170417ЗЗ0417();
      if ((b041704170417З0417ЗЗ0417 + bЗ0417041704170417ЗЗ0417()) * b041704170417З0417ЗЗ0417 % bЗ0417З04170417ЗЗ0417 != bЗЗЗ04170417ЗЗ0417)
      {
        b041704170417З0417ЗЗ0417 = 78;
        bЗЗЗ04170417ЗЗ0417 = 76;
      }
      b041704170417З0417ЗЗ0417 = i;
      bЗЗЗ04170417ЗЗ0417 = 11;
    }
    ((llaala)localObject).bе0435ееее0435е0435е();
  }
  
  /* Error */
  @butterknife.OnClick({2131493239})
  public void onAccountButtonClicked()
  {
    // Byte code:
    //   0: getstatic 26	com/mobile/ui/marketinghub/fragment/MarketingHubUpdateSuccessFragment:b041704170417З0417ЗЗ0417	I
    //   3: istore_1
    //   4: getstatic 28	com/mobile/ui/marketinghub/fragment/MarketingHubUpdateSuccessFragment:b0417ЗЗ04170417ЗЗ0417	I
    //   7: istore_2
    //   8: getstatic 26	com/mobile/ui/marketinghub/fragment/MarketingHubUpdateSuccessFragment:b041704170417З0417ЗЗ0417	I
    //   11: istore_3
    //   12: getstatic 30	com/mobile/ui/marketinghub/fragment/MarketingHubUpdateSuccessFragment:bЗ0417З04170417ЗЗ0417	I
    //   15: istore 4
    //   17: getstatic 32	com/mobile/ui/marketinghub/fragment/MarketingHubUpdateSuccessFragment:bЗЗЗ04170417ЗЗ0417	I
    //   20: istore 5
    //   22: iload_1
    //   23: iload_2
    //   24: iadd
    //   25: iload_3
    //   26: imul
    //   27: iload 4
    //   29: irem
    //   30: iload 5
    //   32: if_icmpeq +58 -> 90
    //   35: getstatic 26	com/mobile/ui/marketinghub/fragment/MarketingHubUpdateSuccessFragment:b041704170417З0417ЗЗ0417	I
    //   38: istore_1
    //   39: iload_1
    //   40: getstatic 28	com/mobile/ui/marketinghub/fragment/MarketingHubUpdateSuccessFragment:b0417ЗЗ04170417ЗЗ0417	I
    //   43: iload_1
    //   44: iadd
    //   45: imul
    //   46: getstatic 30	com/mobile/ui/marketinghub/fragment/MarketingHubUpdateSuccessFragment:bЗ0417З04170417ЗЗ0417	I
    //   49: irem
    //   50: tableswitch	default:+18->68, 0:+29->79
    //   68: invokestatic 36	com/mobile/ui/marketinghub/fragment/MarketingHubUpdateSuccessFragment:b04170417З04170417ЗЗ0417	()I
    //   71: putstatic 26	com/mobile/ui/marketinghub/fragment/MarketingHubUpdateSuccessFragment:b041704170417З0417ЗЗ0417	I
    //   74: bipush 78
    //   76: putstatic 32	com/mobile/ui/marketinghub/fragment/MarketingHubUpdateSuccessFragment:bЗЗЗ04170417ЗЗ0417	I
    //   79: invokestatic 36	com/mobile/ui/marketinghub/fragment/MarketingHubUpdateSuccessFragment:b04170417З04170417ЗЗ0417	()I
    //   82: putstatic 26	com/mobile/ui/marketinghub/fragment/MarketingHubUpdateSuccessFragment:b041704170417З0417ЗЗ0417	I
    //   85: bipush 57
    //   87: putstatic 32	com/mobile/ui/marketinghub/fragment/MarketingHubUpdateSuccessFragment:bЗЗЗ04170417ЗЗ0417	I
    //   90: aload_0
    //   91: getfield 75	com/mobile/ui/marketinghub/fragment/MarketingHubUpdateSuccessFragment:mPresenter	Lkkkkkk/gggggr;
    //   94: astore 6
    //   96: aload 6
    //   98: checkcast 77	kkkkkk/llaala
    //   101: invokevirtual 89	kkkkkk/llaala:b04350435ееее0435е0435е	()V
    //   104: return
    //   105: astore 6
    //   107: aload 6
    //   109: athrow
    //   110: astore 6
    //   112: aload 6
    //   114: athrow
    //   115: astore 6
    //   117: aload 6
    //   119: athrow
    //   120: astore 6
    //   122: aload 6
    //   124: athrow
    // Local variable table:
    //   start	length	slot	name	signature
    //   0	125	0	this	MarketingHubUpdateSuccessFragment
    //   3	43	1	i	int
    //   7	18	2	j	int
    //   11	16	3	k	int
    //   15	15	4	m	int
    //   20	13	5	n	int
    //   94	3	6	localGggggr	kkkkkk.gggggr
    //   105	3	6	localException1	Exception
    //   110	3	6	localException2	Exception
    //   115	3	6	localException3	Exception
    //   120	3	6	localException4	Exception
    // Exception table:
    //   from	to	target	type
    //   90	96	105	java/lang/Exception
    //   8	22	110	java/lang/Exception
    //   79	85	110	java/lang/Exception
    //   107	110	110	java/lang/Exception
    //   96	104	115	java/lang/Exception
    //   0	8	120	java/lang/Exception
    //   85	90	120	java/lang/Exception
    //   117	120	120	java/lang/Exception
  }
  
  /* Error */
  public void onActivityCreated(@Nullable Bundle paramBundle)
  {
    // Byte code:
    //   0: aload_0
    //   1: aload_1
    //   2: invokespecial 93	com/mobile/ui/common/fragment/BasePresentationFragment:onActivityCreated	(Landroid/os/Bundle;)V
    //   5: aload_0
    //   6: getfield 38	com/mobile/ui/marketinghub/fragment/MarketingHubUpdateSuccessFragment:mMarketingHubActivity	Lcom/mobile/ui/marketinghub/activity/MarketingHubActivity;
    //   9: astore_1
    //   10: getstatic 26	com/mobile/ui/marketinghub/fragment/MarketingHubUpdateSuccessFragment:b041704170417З0417ЗЗ0417	I
    //   13: invokestatic 79	com/mobile/ui/marketinghub/fragment/MarketingHubUpdateSuccessFragment:bЗ0417041704170417ЗЗ0417	()I
    //   16: iadd
    //   17: getstatic 26	com/mobile/ui/marketinghub/fragment/MarketingHubUpdateSuccessFragment:b041704170417З0417ЗЗ0417	I
    //   20: imul
    //   21: getstatic 30	com/mobile/ui/marketinghub/fragment/MarketingHubUpdateSuccessFragment:bЗ0417З04170417ЗЗ0417	I
    //   24: irem
    //   25: getstatic 32	com/mobile/ui/marketinghub/fragment/MarketingHubUpdateSuccessFragment:bЗЗЗ04170417ЗЗ0417	I
    //   28: if_icmpeq +15 -> 43
    //   31: invokestatic 36	com/mobile/ui/marketinghub/fragment/MarketingHubUpdateSuccessFragment:b04170417З04170417ЗЗ0417	()I
    //   34: putstatic 26	com/mobile/ui/marketinghub/fragment/MarketingHubUpdateSuccessFragment:b041704170417З0417ЗЗ0417	I
    //   37: invokestatic 36	com/mobile/ui/marketinghub/fragment/MarketingHubUpdateSuccessFragment:b04170417З04170417ЗЗ0417	()I
    //   40: putstatic 32	com/mobile/ui/marketinghub/fragment/MarketingHubUpdateSuccessFragment:bЗЗЗ04170417ЗЗ0417	I
    //   43: aload_1
    //   44: new 95	com/mobile/ui/marketinghub/fragment/MarketingHubUpdateSuccessFragment$1
    //   47: dup
    //   48: aload_0
    //   49: invokespecial 98	com/mobile/ui/marketinghub/fragment/MarketingHubUpdateSuccessFragment$1:<init>	(Lcom/mobile/ui/marketinghub/fragment/MarketingHubUpdateSuccessFragment;)V
    //   52: invokevirtual 102	com/mobile/ui/marketinghub/activity/MarketingHubActivity:addNavigationInterceptToMenu	(Lcom/mobile/ui/globalmenu/adapter/BaseGlobalMenuAdapter$eeeeue;)V
    //   55: getstatic 26	com/mobile/ui/marketinghub/fragment/MarketingHubUpdateSuccessFragment:b041704170417З0417ЗЗ0417	I
    //   58: istore_2
    //   59: iload_2
    //   60: getstatic 28	com/mobile/ui/marketinghub/fragment/MarketingHubUpdateSuccessFragment:b0417ЗЗ04170417ЗЗ0417	I
    //   63: iload_2
    //   64: iadd
    //   65: imul
    //   66: getstatic 30	com/mobile/ui/marketinghub/fragment/MarketingHubUpdateSuccessFragment:bЗ0417З04170417ЗЗ0417	I
    //   69: irem
    //   70: tableswitch	default:+18->88, 0:+29->99
    //   88: invokestatic 36	com/mobile/ui/marketinghub/fragment/MarketingHubUpdateSuccessFragment:b04170417З04170417ЗЗ0417	()I
    //   91: putstatic 26	com/mobile/ui/marketinghub/fragment/MarketingHubUpdateSuccessFragment:b041704170417З0417ЗЗ0417	I
    //   94: bipush 99
    //   96: putstatic 32	com/mobile/ui/marketinghub/fragment/MarketingHubUpdateSuccessFragment:bЗЗЗ04170417ЗЗ0417	I
    //   99: return
    //   100: astore_1
    //   101: aload_1
    //   102: athrow
    //   103: astore_1
    //   104: aload_1
    //   105: athrow
    // Local variable table:
    //   start	length	slot	name	signature
    //   0	106	0	this	MarketingHubUpdateSuccessFragment
    //   0	106	1	paramBundle	Bundle
    //   58	8	2	i	int
    // Exception table:
    //   from	to	target	type
    //   0	5	100	java/lang/Exception
    //   43	55	100	java/lang/Exception
    //   5	10	103	java/lang/Exception
  }
  
  /* Error */
  public void onAttach(android.content.Context paramContext)
  {
    // Byte code:
    //   0: aload_0
    //   1: aload_1
    //   2: invokespecial 107	com/mobile/ui/common/fragment/BasePresentationFragment:onAttach	(Landroid/content/Context;)V
    //   5: iconst_0
    //   6: tableswitch	default:+22->28, 0:+49->55, 1:+-1->5
    //   28: iconst_0
    //   29: tableswitch	default:+23->52, 0:+26->55, 1:+-24->5
    //   52: goto -24 -> 28
    //   55: getstatic 26	com/mobile/ui/marketinghub/fragment/MarketingHubUpdateSuccessFragment:b041704170417З0417ЗЗ0417	I
    //   58: istore_2
    //   59: getstatic 28	com/mobile/ui/marketinghub/fragment/MarketingHubUpdateSuccessFragment:b0417ЗЗ04170417ЗЗ0417	I
    //   62: istore_3
    //   63: getstatic 30	com/mobile/ui/marketinghub/fragment/MarketingHubUpdateSuccessFragment:bЗ0417З04170417ЗЗ0417	I
    //   66: istore 4
    //   68: iload_2
    //   69: iload_3
    //   70: iload_2
    //   71: iadd
    //   72: imul
    //   73: iload 4
    //   75: irem
    //   76: tableswitch	default:+20->96, 0:+62->138
    //   96: getstatic 26	com/mobile/ui/marketinghub/fragment/MarketingHubUpdateSuccessFragment:b041704170417З0417ЗЗ0417	I
    //   99: getstatic 28	com/mobile/ui/marketinghub/fragment/MarketingHubUpdateSuccessFragment:b0417ЗЗ04170417ЗЗ0417	I
    //   102: iadd
    //   103: getstatic 26	com/mobile/ui/marketinghub/fragment/MarketingHubUpdateSuccessFragment:b041704170417З0417ЗЗ0417	I
    //   106: imul
    //   107: getstatic 30	com/mobile/ui/marketinghub/fragment/MarketingHubUpdateSuccessFragment:bЗ0417З04170417ЗЗ0417	I
    //   110: irem
    //   111: getstatic 32	com/mobile/ui/marketinghub/fragment/MarketingHubUpdateSuccessFragment:bЗЗЗ04170417ЗЗ0417	I
    //   114: if_icmpeq +13 -> 127
    //   117: bipush 24
    //   119: putstatic 26	com/mobile/ui/marketinghub/fragment/MarketingHubUpdateSuccessFragment:b041704170417З0417ЗЗ0417	I
    //   122: bipush 38
    //   124: putstatic 32	com/mobile/ui/marketinghub/fragment/MarketingHubUpdateSuccessFragment:bЗЗЗ04170417ЗЗ0417	I
    //   127: invokestatic 36	com/mobile/ui/marketinghub/fragment/MarketingHubUpdateSuccessFragment:b04170417З04170417ЗЗ0417	()I
    //   130: putstatic 26	com/mobile/ui/marketinghub/fragment/MarketingHubUpdateSuccessFragment:b041704170417З0417ЗЗ0417	I
    //   133: bipush 12
    //   135: putstatic 32	com/mobile/ui/marketinghub/fragment/MarketingHubUpdateSuccessFragment:bЗЗЗ04170417ЗЗ0417	I
    //   138: aload_1
    //   139: checkcast 53	com/mobile/ui/marketinghub/activity/MarketingHubActivity
    //   142: astore_1
    //   143: aload_0
    //   144: aload_1
    //   145: putfield 38	com/mobile/ui/marketinghub/fragment/MarketingHubUpdateSuccessFragment:mMarketingHubActivity	Lcom/mobile/ui/marketinghub/activity/MarketingHubActivity;
    //   148: return
    //   149: astore_1
    //   150: aload_1
    //   151: athrow
    //   152: astore_1
    //   153: aload_1
    //   154: athrow
    // Local variable table:
    //   start	length	slot	name	signature
    //   0	155	0	this	MarketingHubUpdateSuccessFragment
    //   0	155	1	paramContext	android.content.Context
    //   58	15	2	i	int
    //   62	10	3	j	int
    //   66	10	4	k	int
    // Exception table:
    //   from	to	target	type
    //   55	68	149	java/lang/Exception
    //   138	143	149	java/lang/Exception
    //   0	5	152	java/lang/Exception
    //   127	138	152	java/lang/Exception
    //   143	148	152	java/lang/Exception
  }
  
  /* Error */
  @butterknife.OnClick({2131493240})
  public void onContactDetailsButtonClicked()
  {
    // Byte code:
    //   0: getstatic 26	com/mobile/ui/marketinghub/fragment/MarketingHubUpdateSuccessFragment:b041704170417З0417ЗЗ0417	I
    //   3: getstatic 28	com/mobile/ui/marketinghub/fragment/MarketingHubUpdateSuccessFragment:b0417ЗЗ04170417ЗЗ0417	I
    //   6: iadd
    //   7: getstatic 26	com/mobile/ui/marketinghub/fragment/MarketingHubUpdateSuccessFragment:b041704170417З0417ЗЗ0417	I
    //   10: imul
    //   11: getstatic 30	com/mobile/ui/marketinghub/fragment/MarketingHubUpdateSuccessFragment:bЗ0417З04170417ЗЗ0417	I
    //   14: irem
    //   15: getstatic 32	com/mobile/ui/marketinghub/fragment/MarketingHubUpdateSuccessFragment:bЗЗЗ04170417ЗЗ0417	I
    //   18: if_icmpeq +109 -> 127
    //   21: invokestatic 36	com/mobile/ui/marketinghub/fragment/MarketingHubUpdateSuccessFragment:b04170417З04170417ЗЗ0417	()I
    //   24: istore_1
    //   25: iload_1
    //   26: getstatic 28	com/mobile/ui/marketinghub/fragment/MarketingHubUpdateSuccessFragment:b0417ЗЗ04170417ЗЗ0417	I
    //   29: iload_1
    //   30: iadd
    //   31: imul
    //   32: getstatic 30	com/mobile/ui/marketinghub/fragment/MarketingHubUpdateSuccessFragment:bЗ0417З04170417ЗЗ0417	I
    //   35: irem
    //   36: tableswitch	default:+20->56, 0:+31->67
    //   56: invokestatic 36	com/mobile/ui/marketinghub/fragment/MarketingHubUpdateSuccessFragment:b04170417З04170417ЗЗ0417	()I
    //   59: putstatic 26	com/mobile/ui/marketinghub/fragment/MarketingHubUpdateSuccessFragment:b041704170417З0417ЗЗ0417	I
    //   62: bipush 10
    //   64: putstatic 32	com/mobile/ui/marketinghub/fragment/MarketingHubUpdateSuccessFragment:bЗЗЗ04170417ЗЗ0417	I
    //   67: bipush 9
    //   69: putstatic 26	com/mobile/ui/marketinghub/fragment/MarketingHubUpdateSuccessFragment:b041704170417З0417ЗЗ0417	I
    //   72: invokestatic 36	com/mobile/ui/marketinghub/fragment/MarketingHubUpdateSuccessFragment:b04170417З04170417ЗЗ0417	()I
    //   75: putstatic 32	com/mobile/ui/marketinghub/fragment/MarketingHubUpdateSuccessFragment:bЗЗЗ04170417ЗЗ0417	I
    //   78: iconst_0
    //   79: tableswitch	default:+21->100, 0:+48->127, 1:+-1->78
    //   100: iconst_0
    //   101: tableswitch	default:+23->124, 0:+26->127, 1:+-23->78
    //   124: goto -24 -> 100
    //   127: aload_0
    //   128: getfield 75	com/mobile/ui/marketinghub/fragment/MarketingHubUpdateSuccessFragment:mPresenter	Lkkkkkk/gggggr;
    //   131: astore_2
    //   132: aload_2
    //   133: checkcast 77	kkkkkk/llaala
    //   136: astore_2
    //   137: aload_2
    //   138: invokevirtual 112	kkkkkk/llaala:bее0435еее0435е0435е	()V
    //   141: return
    //   142: astore_2
    //   143: aload_2
    //   144: athrow
    //   145: astore_2
    //   146: aload_2
    //   147: athrow
    // Local variable table:
    //   start	length	slot	name	signature
    //   0	148	0	this	MarketingHubUpdateSuccessFragment
    //   24	8	1	i	int
    //   131	7	2	localObject	Object
    //   142	2	2	localException1	Exception
    //   145	2	2	localException2	Exception
    // Exception table:
    //   from	to	target	type
    //   127	132	142	java/lang/Exception
    //   137	141	142	java/lang/Exception
    //   132	137	145	java/lang/Exception
  }
  
  public void onCreate(@Nullable Bundle paramBundle)
  {
    super.onCreate(paramBundle);
    paramBundle = App.get();
    if ((b04170417З04170417ЗЗ0417() + b0417ЗЗ04170417ЗЗ0417) * b04170417З04170417ЗЗ0417() % bЗ0417З04170417ЗЗ0417 != bЗЗЗ04170417ЗЗ0417)
    {
      b041704170417З0417ЗЗ0417 = b04170417З04170417ЗЗ0417();
      bЗЗЗ04170417ЗЗ0417 = 47;
    }
    paramBundle = paramBundle.getAppComponent();
    if ((b041704170417З0417ЗЗ0417 + b0417ЗЗ04170417ЗЗ0417) * b041704170417З0417ЗЗ0417 % bЗ0417З04170417ЗЗ0417 != bЗЗЗ04170417ЗЗ0417)
    {
      b041704170417З0417ЗЗ0417 = b04170417З04170417ЗЗ0417();
      bЗЗЗ04170417ЗЗ0417 = 15;
    }
    paramBundle.bИ041804180418И0418041804180418И(this);
  }
  
  public View onCreateView(LayoutInflater paramLayoutInflater, @Nullable ViewGroup paramViewGroup, @Nullable Bundle paramBundle)
  {
    int i = R.layout.fragment_marketing_hub_update_success;
    switch (0)
    {
    case 1: 
    default: 
      for (;;)
      {
        switch (1)
        {
        }
      }
    }
    paramLayoutInflater = paramLayoutInflater.inflate(i, paramViewGroup, false);
    i = b041704170417З0417ЗЗ0417;
    switch (i * (b0417ЗЗ04170417ЗЗ0417 + i) % bЗ0417З04170417ЗЗ0417)
    {
    default: 
      b041704170417З0417ЗЗ0417 = b04170417З04170417ЗЗ0417();
      bЗЗЗ04170417ЗЗ0417 = b04170417З04170417ЗЗ0417();
    }
    return paramLayoutInflater;
  }
  
  /* Error */
  public void onViewCreated(View paramView, @Nullable Bundle paramBundle)
  {
    // Byte code:
    //   0: getstatic 26	com/mobile/ui/marketinghub/fragment/MarketingHubUpdateSuccessFragment:b041704170417З0417ЗЗ0417	I
    //   3: istore_3
    //   4: getstatic 28	com/mobile/ui/marketinghub/fragment/MarketingHubUpdateSuccessFragment:b0417ЗЗ04170417ЗЗ0417	I
    //   7: istore 4
    //   9: getstatic 26	com/mobile/ui/marketinghub/fragment/MarketingHubUpdateSuccessFragment:b041704170417З0417ЗЗ0417	I
    //   12: istore 5
    //   14: getstatic 30	com/mobile/ui/marketinghub/fragment/MarketingHubUpdateSuccessFragment:bЗ0417З04170417ЗЗ0417	I
    //   17: istore 6
    //   19: getstatic 32	com/mobile/ui/marketinghub/fragment/MarketingHubUpdateSuccessFragment:bЗЗЗ04170417ЗЗ0417	I
    //   22: istore 7
    //   24: iload_3
    //   25: iload 4
    //   27: iadd
    //   28: iload 5
    //   30: imul
    //   31: iload 6
    //   33: irem
    //   34: iload 7
    //   36: if_icmpeq +14 -> 50
    //   39: bipush 87
    //   41: putstatic 26	com/mobile/ui/marketinghub/fragment/MarketingHubUpdateSuccessFragment:b041704170417З0417ЗЗ0417	I
    //   44: invokestatic 36	com/mobile/ui/marketinghub/fragment/MarketingHubUpdateSuccessFragment:b04170417З04170417ЗЗ0417	()I
    //   47: putstatic 32	com/mobile/ui/marketinghub/fragment/MarketingHubUpdateSuccessFragment:bЗЗЗ04170417ЗЗ0417	I
    //   50: aload_0
    //   51: aload_1
    //   52: aload_2
    //   53: invokespecial 147	com/mobile/ui/common/fragment/BasePresentationFragment:onViewCreated	(Landroid/view/View;Landroid/os/Bundle;)V
    //   56: aload_0
    //   57: getfield 75	com/mobile/ui/marketinghub/fragment/MarketingHubUpdateSuccessFragment:mPresenter	Lkkkkkk/gggggr;
    //   60: astore_1
    //   61: iconst_1
    //   62: tableswitch	default:+22->84, 0:+-1->61, 1:+49->111
    //   84: iconst_0
    //   85: tableswitch	default:+23->108, 0:+26->111, 1:+-24->61
    //   108: goto -24 -> 84
    //   111: getstatic 26	com/mobile/ui/marketinghub/fragment/MarketingHubUpdateSuccessFragment:b041704170417З0417ЗЗ0417	I
    //   114: istore_3
    //   115: iload_3
    //   116: invokestatic 79	com/mobile/ui/marketinghub/fragment/MarketingHubUpdateSuccessFragment:bЗ0417041704170417ЗЗ0417	()I
    //   119: iload_3
    //   120: iadd
    //   121: imul
    //   122: getstatic 30	com/mobile/ui/marketinghub/fragment/MarketingHubUpdateSuccessFragment:bЗ0417З04170417ЗЗ0417	I
    //   125: irem
    //   126: tableswitch	default:+18->144, 0:+30->156
    //   144: invokestatic 36	com/mobile/ui/marketinghub/fragment/MarketingHubUpdateSuccessFragment:b04170417З04170417ЗЗ0417	()I
    //   147: putstatic 26	com/mobile/ui/marketinghub/fragment/MarketingHubUpdateSuccessFragment:b041704170417З0417ЗЗ0417	I
    //   150: invokestatic 36	com/mobile/ui/marketinghub/fragment/MarketingHubUpdateSuccessFragment:b04170417З04170417ЗЗ0417	()I
    //   153: putstatic 32	com/mobile/ui/marketinghub/fragment/MarketingHubUpdateSuccessFragment:bЗЗЗ04170417ЗЗ0417	I
    //   156: aload_1
    //   157: checkcast 77	kkkkkk/llaala
    //   160: invokevirtual 150	kkkkkk/llaala:b0435е0435еее0435е0435е	()V
    //   163: return
    //   164: astore_1
    //   165: aload_1
    //   166: athrow
    //   167: astore_1
    //   168: aload_1
    //   169: athrow
    // Local variable table:
    //   start	length	slot	name	signature
    //   0	170	0	this	MarketingHubUpdateSuccessFragment
    //   0	170	1	paramView	View
    //   0	170	2	paramBundle	Bundle
    //   3	119	3	i	int
    //   7	21	4	j	int
    //   12	19	5	k	int
    //   17	17	6	m	int
    //   22	15	7	n	int
    // Exception table:
    //   from	to	target	type
    //   0	24	164	java/lang/Exception
    //   50	61	164	java/lang/Exception
    //   156	163	164	java/lang/Exception
    //   39	50	167	java/lang/Exception
  }
  
  /* Error */
  public boolean originatedFromLead()
  {
    // Byte code:
    //   0: getstatic 26	com/mobile/ui/marketinghub/fragment/MarketingHubUpdateSuccessFragment:b041704170417З0417ЗЗ0417	I
    //   3: invokestatic 79	com/mobile/ui/marketinghub/fragment/MarketingHubUpdateSuccessFragment:bЗ0417041704170417ЗЗ0417	()I
    //   6: iadd
    //   7: getstatic 26	com/mobile/ui/marketinghub/fragment/MarketingHubUpdateSuccessFragment:b041704170417З0417ЗЗ0417	I
    //   10: imul
    //   11: getstatic 30	com/mobile/ui/marketinghub/fragment/MarketingHubUpdateSuccessFragment:bЗ0417З04170417ЗЗ0417	I
    //   14: irem
    //   15: getstatic 32	com/mobile/ui/marketinghub/fragment/MarketingHubUpdateSuccessFragment:bЗЗЗ04170417ЗЗ0417	I
    //   18: if_icmpeq +14 -> 32
    //   21: invokestatic 36	com/mobile/ui/marketinghub/fragment/MarketingHubUpdateSuccessFragment:b04170417З04170417ЗЗ0417	()I
    //   24: putstatic 26	com/mobile/ui/marketinghub/fragment/MarketingHubUpdateSuccessFragment:b041704170417З0417ЗЗ0417	I
    //   27: bipush 20
    //   29: putstatic 32	com/mobile/ui/marketinghub/fragment/MarketingHubUpdateSuccessFragment:bЗЗЗ04170417ЗЗ0417	I
    //   32: aload_0
    //   33: getfield 38	com/mobile/ui/marketinghub/fragment/MarketingHubUpdateSuccessFragment:mMarketingHubActivity	Lcom/mobile/ui/marketinghub/activity/MarketingHubActivity;
    //   36: astore_3
    //   37: getstatic 26	com/mobile/ui/marketinghub/fragment/MarketingHubUpdateSuccessFragment:b041704170417З0417ЗЗ0417	I
    //   40: istore_1
    //   41: iload_1
    //   42: getstatic 28	com/mobile/ui/marketinghub/fragment/MarketingHubUpdateSuccessFragment:b0417ЗЗ04170417ЗЗ0417	I
    //   45: iload_1
    //   46: iadd
    //   47: imul
    //   48: getstatic 30	com/mobile/ui/marketinghub/fragment/MarketingHubUpdateSuccessFragment:bЗ0417З04170417ЗЗ0417	I
    //   51: irem
    //   52: tableswitch	default:+20->72, 0:+31->83
    //   72: bipush 54
    //   74: putstatic 26	com/mobile/ui/marketinghub/fragment/MarketingHubUpdateSuccessFragment:b041704170417З0417ЗЗ0417	I
    //   77: invokestatic 36	com/mobile/ui/marketinghub/fragment/MarketingHubUpdateSuccessFragment:b04170417З04170417ЗЗ0417	()I
    //   80: putstatic 32	com/mobile/ui/marketinghub/fragment/MarketingHubUpdateSuccessFragment:bЗЗЗ04170417ЗЗ0417	I
    //   83: aload_3
    //   84: invokevirtual 155	com/mobile/ui/marketinghub/activity/MarketingHubActivity:originatedFromALead	()Z
    //   87: istore_2
    //   88: iload_2
    //   89: ireturn
    //   90: astore_3
    //   91: aload_3
    //   92: athrow
    //   93: astore_3
    //   94: aload_3
    //   95: athrow
    // Local variable table:
    //   start	length	slot	name	signature
    //   0	96	0	this	MarketingHubUpdateSuccessFragment
    //   40	8	1	i	int
    //   87	2	2	bool	boolean
    //   36	48	3	localMarketingHubActivity	MarketingHubActivity
    //   90	2	3	localException1	Exception
    //   93	2	3	localException2	Exception
    // Exception table:
    //   from	to	target	type
    //   83	88	90	java/lang/Exception
    //   32	37	93	java/lang/Exception
  }
  
  public void showProfileScreen()
  {
    startActivity(PersonalDetailsSettingsActivity.getIntent(getContext()));
    int i = b041704170417З0417ЗЗ0417;
    if ((b04170417З04170417ЗЗ0417() + b0417ЗЗ04170417ЗЗ0417) * b04170417З04170417ЗЗ0417() % bЗ0417З04170417ЗЗ0417 != bЗЗЗ04170417ЗЗ0417)
    {
      b041704170417З0417ЗЗ0417 = 71;
      bЗЗЗ04170417ЗЗ0417 = 29;
    }
    switch (i * (b0417ЗЗ04170417ЗЗ0417 + i) % bЗ0417З04170417ЗЗ0417)
    {
    default: 
      b041704170417З0417ЗЗ0417 = b04170417З04170417ЗЗ0417();
      bЗЗЗ04170417ЗЗ0417 = b04170417З04170417ЗЗ0417();
    }
    this.mMarketingHubActivity.finish();
    switch (0)
    {
    case 1: 
    default: 
      for (;;)
      {
        switch (1)
        {
        }
      }
    }
  }
  
  /* Error */
  public void trackScreenView()
  {
    // Byte code:
    //   0: aload_0
    //   1: getfield 75	com/mobile/ui/marketinghub/fragment/MarketingHubUpdateSuccessFragment:mPresenter	Lkkkkkk/gggggr;
    //   4: checkcast 77	kkkkkk/llaala
    //   7: astore_1
    //   8: getstatic 26	com/mobile/ui/marketinghub/fragment/MarketingHubUpdateSuccessFragment:b041704170417З0417ЗЗ0417	I
    //   11: getstatic 28	com/mobile/ui/marketinghub/fragment/MarketingHubUpdateSuccessFragment:b0417ЗЗ04170417ЗЗ0417	I
    //   14: iadd
    //   15: getstatic 26	com/mobile/ui/marketinghub/fragment/MarketingHubUpdateSuccessFragment:b041704170417З0417ЗЗ0417	I
    //   18: imul
    //   19: getstatic 30	com/mobile/ui/marketinghub/fragment/MarketingHubUpdateSuccessFragment:bЗ0417З04170417ЗЗ0417	I
    //   22: irem
    //   23: getstatic 32	com/mobile/ui/marketinghub/fragment/MarketingHubUpdateSuccessFragment:bЗЗЗ04170417ЗЗ0417	I
    //   26: if_icmpeq +14 -> 40
    //   29: invokestatic 36	com/mobile/ui/marketinghub/fragment/MarketingHubUpdateSuccessFragment:b04170417З04170417ЗЗ0417	()I
    //   32: putstatic 26	com/mobile/ui/marketinghub/fragment/MarketingHubUpdateSuccessFragment:b041704170417З0417ЗЗ0417	I
    //   35: bipush 8
    //   37: putstatic 32	com/mobile/ui/marketinghub/fragment/MarketingHubUpdateSuccessFragment:bЗЗЗ04170417ЗЗ0417	I
    //   40: aload_1
    //   41: invokevirtual 177	kkkkkk/llaala:bе04350435еее0435е0435е	()V
    //   44: return
    //   45: astore_1
    //   46: aload_1
    //   47: athrow
    //   48: astore_1
    //   49: aload_1
    //   50: athrow
    // Local variable table:
    //   start	length	slot	name	signature
    //   0	51	0	this	MarketingHubUpdateSuccessFragment
    //   7	34	1	localLlaala	llaala
    //   45	2	1	localException1	Exception
    //   48	2	1	localException2	Exception
    // Exception table:
    //   from	to	target	type
    //   40	44	45	java/lang/Exception
    //   0	8	48	java/lang/Exception
  }
}
