package com.appdynamics.eumagent.runtime;

import android.content.Context;
import android.content.SharedPreferences;
import android.content.SharedPreferences.Editor;
import java.util.UUID;
import java.util.concurrent.atomic.AtomicLong;
import kkkkkk.gguuuu;

public final class c
{
  public static int b043E043E043E043Eо043E = 0;
  public static int b043E043Eо043Eо043E = 19;
  public static int b043Eо043E043Eо043E = 2;
  public static int bоооо043E043E = 1;
  private final a a;
  private final String b;
  private final AtomicLong c = new AtomicLong();
  
  public c(Context paramContext, String paramString)
  {
    this(new a(paramContext), paramString);
    this.c.set(this.a.b(gguuuu.bккккк043Aкк043A043A(");+5<(-:A;B4B", 'C', '\000'), 0L));
    this.c.addAndGet(100L);
    this.c.incrementAndGet();
    this.a.a(gguuuu.bккккк043Aкк043A043A("iygot^alqin^j", '¨', '\002'), this.c.get());
  }
  
  private c(a paramA, String paramString)
  {
    this.a = paramA;
    this.b = paramString;
  }
  
  public static int b043Eооо043E043E()
  {
    return 2;
  }
  
  public static int bо043E043E043Eо043E()
  {
    return 68;
  }
  
  public static int bо043Eоо043E043E()
  {
    return 0;
  }
  
  public static int bоо043E043Eо043E()
  {
    return 1;
  }
  
  public final void a(long paramLong)
  {
    try
    {
      this.a.a(gguuuu.bккккк043Aкк043A043A("z~\btt}unotqy~h|prq", '#', '\002'), paramLong);
      int i = b043E043Eо043Eо043E;
      switch (i * (bоо043E043Eо043E() + i) % b043Eо043E043Eо043E)
      {
      default: 
        b043E043Eо043Eо043E = 18;
        i = bо043E043E043Eо043E();
        if ((b043E043Eо043Eо043E + bоооо043E043E) * b043E043Eо043Eо043E % b043Eо043E043Eо043E != b043E043E043E043Eо043E)
        {
          b043E043Eо043Eо043E = 76;
          b043E043E043E043Eо043E = 43;
        }
        b043Eо043E043Eо043E = i;
      }
      return;
    }
    catch (Exception localException)
    {
      throw localException;
    }
  }
  
  public final void a(String paramString)
  {
    a localA = this.a;
    switch (0)
    {
    case 1: 
    default: 
      for (;;)
      {
        switch (1)
        {
        }
      }
    }
    if ((b043E043Eо043Eо043E + bоооо043E043E) * b043E043Eо043Eо043E % b043Eо043E043Eо043E != b043E043E043E043Eо043E)
    {
      b043E043Eо043Eо043E = bо043E043E043Eо043E();
      b043E043E043E043Eо043E = 96;
    }
    switch (1)
    {
    case 0: 
    default: 
      for (;;)
      {
        switch (1)
        {
        }
      }
    }
    int i = b043E043Eо043Eо043E;
    switch (i * (bоооо043E043E + i) % b043Eо043E043Eо043E)
    {
    default: 
      b043E043Eо043Eо043E = bо043E043E043Eо043E();
      b043E043E043E043Eо043E = bо043E043E043Eо043E();
    }
    localA.a(gguuuu.bк043Aккк043Aкк043A043A("IJ<BD<\027<9AF%?:3;", 'Y', '5', '\000'), paramString);
  }
  
  public final void a(boolean paramBoolean)
  {
    if ((b043E043Eо043Eо043E + bоооо043E043E) * b043E043Eо043Eо043E % b043Eооо043E043E() != b043E043E043E043Eо043E)
    {
      b043E043Eо043Eо043E = 77;
      b043E043E043E043Eо043E = 39;
    }
    try
    {
      this.a.a(gguuuu.bккккк043Aкк043A043A("170:\034<7=D$399IO\035D:A", 'â', '\004'), paramBoolean);
      int i = b043E043Eо043Eо043E;
      switch (i * (bоооо043E043E + i) % b043Eооо043E043E())
      {
      default: 
        b043E043Eо043Eо043E = 87;
        b043E043E043E043Eо043E = 82;
      }
      return;
    }
    catch (Exception localException)
    {
      throw localException;
    }
  }
  
  /* Error */
  public final boolean a()
  {
    // Byte code:
    //   0: iconst_0
    //   1: istore_1
    //   2: getstatic 86	com/appdynamics/eumagent/runtime/c:b043E043Eо043Eо043E	I
    //   5: getstatic 94	com/appdynamics/eumagent/runtime/c:bоооо043E043E	I
    //   8: iadd
    //   9: getstatic 86	com/appdynamics/eumagent/runtime/c:b043E043Eо043Eо043E	I
    //   12: imul
    //   13: getstatic 90	com/appdynamics/eumagent/runtime/c:b043Eо043E043Eо043E	I
    //   16: irem
    //   17: invokestatic 117	com/appdynamics/eumagent/runtime/c:bо043Eоо043E043E	()I
    //   20: if_icmpeq +13 -> 33
    //   23: invokestatic 92	com/appdynamics/eumagent/runtime/c:bо043E043E043Eо043E	()I
    //   26: putstatic 86	com/appdynamics/eumagent/runtime/c:b043E043Eо043Eо043E	I
    //   29: iconst_0
    //   30: putstatic 96	com/appdynamics/eumagent/runtime/c:b043E043E043E043Eо043E	I
    //   33: aload_0
    //   34: invokevirtual 119	com/appdynamics/eumagent/runtime/c:b	()J
    //   37: lstore_2
    //   38: invokestatic 124	java/lang/System:currentTimeMillis	()J
    //   41: lstore 4
    //   43: lload_2
    //   44: lload 4
    //   46: lcmp
    //   47: ifle +7 -> 54
    //   50: iconst_1
    //   51: istore_1
    //   52: iload_1
    //   53: ireturn
    //   54: getstatic 86	com/appdynamics/eumagent/runtime/c:b043E043Eо043Eо043E	I
    //   57: getstatic 94	com/appdynamics/eumagent/runtime/c:bоооо043E043E	I
    //   60: iadd
    //   61: getstatic 86	com/appdynamics/eumagent/runtime/c:b043E043Eо043Eо043E	I
    //   64: imul
    //   65: getstatic 90	com/appdynamics/eumagent/runtime/c:b043Eо043E043Eо043E	I
    //   68: irem
    //   69: getstatic 96	com/appdynamics/eumagent/runtime/c:b043E043E043E043Eо043E	I
    //   72: if_icmpeq -20 -> 52
    //   75: invokestatic 92	com/appdynamics/eumagent/runtime/c:bо043E043E043Eо043E	()I
    //   78: putstatic 86	com/appdynamics/eumagent/runtime/c:b043E043Eо043Eо043E	I
    //   81: invokestatic 92	com/appdynamics/eumagent/runtime/c:bо043E043E043Eо043E	()I
    //   84: putstatic 96	com/appdynamics/eumagent/runtime/c:b043E043E043E043Eо043E	I
    //   87: iconst_0
    //   88: ireturn
    //   89: astore 6
    //   91: aload 6
    //   93: athrow
    //   94: astore 6
    //   96: aload 6
    //   98: athrow
    //   99: astore 6
    //   101: aload 6
    //   103: athrow
    // Local variable table:
    //   start	length	slot	name	signature
    //   0	104	0	this	c
    //   1	52	1	bool	boolean
    //   37	7	2	l1	long
    //   41	4	4	l2	long
    //   89	3	6	localException1	Exception
    //   94	3	6	localException2	Exception
    //   99	3	6	localException3	Exception
    // Exception table:
    //   from	to	target	type
    //   33	43	89	java/lang/Exception
    //   91	94	94	java/lang/Exception
    //   2	33	99	java/lang/Exception
  }
  
  /* Error */
  public final long b()
  {
    // Byte code:
    //   0: getstatic 86	com/appdynamics/eumagent/runtime/c:b043E043Eо043Eо043E	I
    //   3: getstatic 94	com/appdynamics/eumagent/runtime/c:bоооо043E043E	I
    //   6: iadd
    //   7: getstatic 86	com/appdynamics/eumagent/runtime/c:b043E043Eо043Eо043E	I
    //   10: imul
    //   11: getstatic 90	com/appdynamics/eumagent/runtime/c:b043Eо043E043Eо043E	I
    //   14: irem
    //   15: getstatic 96	com/appdynamics/eumagent/runtime/c:b043E043E043E043Eо043E	I
    //   18: if_icmpeq +14 -> 32
    //   21: bipush 50
    //   23: putstatic 86	com/appdynamics/eumagent/runtime/c:b043E043Eо043Eо043E	I
    //   26: invokestatic 92	com/appdynamics/eumagent/runtime/c:bо043E043E043Eо043E	()I
    //   29: putstatic 96	com/appdynamics/eumagent/runtime/c:b043E043E043E043Eо043E	I
    //   32: aload_0
    //   33: getfield 33	com/appdynamics/eumagent/runtime/c:a	Lcom/appdynamics/eumagent/runtime/c$a;
    //   36: astore_3
    //   37: ldc 126
    //   39: bipush 100
    //   41: iconst_1
    //   42: invokestatic 41	kkkkkk/gguuuu:bккккк043Aкк043A043A	(Ljava/lang/String;CC)Ljava/lang/String;
    //   45: astore 4
    //   47: invokestatic 92	com/appdynamics/eumagent/runtime/c:bо043E043E043Eо043E	()I
    //   50: getstatic 94	com/appdynamics/eumagent/runtime/c:bоооо043E043E	I
    //   53: iadd
    //   54: invokestatic 92	com/appdynamics/eumagent/runtime/c:bо043E043E043Eо043E	()I
    //   57: imul
    //   58: getstatic 90	com/appdynamics/eumagent/runtime/c:b043Eо043E043Eо043E	I
    //   61: irem
    //   62: getstatic 96	com/appdynamics/eumagent/runtime/c:b043E043E043E043Eо043E	I
    //   65: if_icmpeq +13 -> 78
    //   68: bipush 51
    //   70: putstatic 86	com/appdynamics/eumagent/runtime/c:b043E043Eо043Eо043E	I
    //   73: bipush 18
    //   75: putstatic 96	com/appdynamics/eumagent/runtime/c:b043E043E043E043Eо043E	I
    //   78: aload_3
    //   79: aload 4
    //   81: ldc2_w 127
    //   84: invokevirtual 44	com/appdynamics/eumagent/runtime/c$a:b	(Ljava/lang/String;J)J
    //   87: lstore_1
    //   88: lload_1
    //   89: lreturn
    //   90: astore_3
    //   91: aload_3
    //   92: athrow
    //   93: astore_3
    //   94: aload_3
    //   95: athrow
    // Local variable table:
    //   start	length	slot	name	signature
    //   0	96	0	this	c
    //   87	2	1	l	long
    //   36	43	3	localA	a
    //   90	2	3	localException1	Exception
    //   93	2	3	localException2	Exception
    //   45	35	4	str	String
    // Exception table:
    //   from	to	target	type
    //   32	47	90	java/lang/Exception
    //   78	88	93	java/lang/Exception
  }
  
  public final void b(long paramLong)
  {
    if (this.b != null) {
      this.a.a(gguuuu.bк043Aккк043Aкк043A043A("4F9;2\0260", 'Ü', '®', '\000'), this.b);
    }
    this.a.a(gguuuu.bккккк043Aкк043A043A("fleo`rrmszf~n|~u||", 'ý', '\001'), paramLong);
    this.a.a(gguuuu.bккккк043Aкк043A043A("QWPZK]]X^eQiYgi`ggY^krlses", 'w', '\001'), 0L);
  }
  
  public final String c()
  {
    a localA = this.a;
    if ((b043E043Eо043Eо043E + bоо043E043Eо043E()) * b043E043Eо043Eо043E % b043Eо043E043Eо043E != bо043Eоо043E043E())
    {
      b043E043Eо043Eо043E = bо043E043E043Eо043E();
      b043E043E043E043Eо043E = bо043E043E043Eо043E();
    }
    return localA.b(gguuuu.bк043Aккк043Aкк043A043A("&)\035%)#'&07\03041,6", 'ï', '·', '\001'), gguuuu.bккккк043Aкк043A043A("BG", 'É', '\004'));
  }
  
  public final String d()
  {
    String str = this.a.b(gguuuu.bк043Aккк043Aкк043A043A("T[ZdkA]_ipfdhes", 'J', 'Ö', '\001'), null);
    int i = b043E043Eо043Eо043E;
    switch (i * (bоооо043E043E + i) % b043Eо043E043Eо043E)
    {
    default: 
      b043E043Eо043Eо043E = 77;
      b043E043E043E043Eо043E = 9;
    }
    Object localObject = str;
    if (str == null)
    {
      localObject = UUID.randomUUID();
      switch (0)
      {
      case 1: 
      default: 
        for (;;)
        {
          switch (0)
          {
          }
        }
      }
      localObject = ((UUID)localObject).toString();
      this.a.a(gguuuu.bк043Aккк043Aкк043A043A("UZW_d8RRZ_SOQLX", '\f', 'þ', '\000'), (String)localObject);
    }
    return localObject;
  }
  
  public final boolean e()
  {
    switch (1)
    {
    case 0: 
    default: 
      for (;;)
      {
        if ((b043E043Eо043Eо043E + bоооо043E043E) * b043E043Eо043Eо043E % b043Eо043E043Eо043E != b043E043E043E043Eо043E)
        {
          b043E043Eо043Eо043E = 67;
          b043E043E043E043Eо043E = 95;
        }
        switch (1)
        {
        }
      }
    }
    if (g() != -1L) {
      return true;
    }
    if ((b043E043Eо043Eо043E + bоо043E043Eо043E()) * b043E043Eо043Eо043E % b043Eооо043E043E() != b043E043E043E043Eо043E)
    {
      switch (1)
      {
      case 0: 
      default: 
        for (;;)
        {
          switch (0)
          {
          }
        }
      }
      b043E043Eо043Eо043E = 12;
      b043E043E043E043Eо043E = 34;
      return false;
    }
    return false;
  }
  
  public final long f()
  {
    long l = this.a.b(gguuuu.bккккк043Aкк043A043A("EI@H7GE>BG1G5AA6;9),7<49)5", '\f', '\002'), 0L);
    int i = b043E043Eо043Eо043E;
    switch (i * (bоооо043E043E + i) % b043Eо043E043Eо043E)
    {
    default: 
      b043E043Eо043Eо043E = 95;
      b043E043E043E043Eо043E = 41;
    }
    a localA = this.a;
    l += 1L;
    localA.a(gguuuu.bккккк043Aкк043A043A("cibl]oojpwc{ky{ryykp}\005~\006w\006", 'ø', '\000'), l);
    return l;
  }
  
  /* Error */
  public final long g()
  {
    // Byte code:
    //   0: ldc2_w 127
    //   3: lstore 6
    //   5: iconst_1
    //   6: istore_1
    //   7: aload_0
    //   8: getfield 75	com/appdynamics/eumagent/runtime/c:b	Ljava/lang/String;
    //   11: ifnull +83 -> 94
    //   14: aload_0
    //   15: getfield 75	com/appdynamics/eumagent/runtime/c:b	Ljava/lang/String;
    //   18: astore 8
    //   20: aload_0
    //   21: getfield 33	com/appdynamics/eumagent/runtime/c:a	Lcom/appdynamics/eumagent/runtime/c$a;
    //   24: astore 9
    //   26: ldc -89
    //   28: bipush 32
    //   30: sipush 240
    //   33: iconst_1
    //   34: invokestatic 103	kkkkkk/gguuuu:bк043Aккк043Aкк043A043A	(Ljava/lang/String;CCC)Ljava/lang/String;
    //   37: astore 10
    //   39: aload 8
    //   41: aload 9
    //   43: aload 10
    //   45: ldc -87
    //   47: invokevirtual 142	com/appdynamics/eumagent/runtime/c$a:b	(Ljava/lang/String;Ljava/lang/String;)Ljava/lang/String;
    //   50: invokevirtual 175	java/lang/String:equals	(Ljava/lang/Object;)Z
    //   53: ifeq +41 -> 94
    //   56: iload_1
    //   57: ifeq +34 -> 91
    //   60: aload_0
    //   61: getfield 33	com/appdynamics/eumagent/runtime/c:a	Lcom/appdynamics/eumagent/runtime/c$a;
    //   64: astore 8
    //   66: ldc -79
    //   68: bipush 21
    //   70: sipush 233
    //   73: iconst_1
    //   74: invokestatic 103	kkkkkk/gguuuu:bк043Aккк043Aкк043A043A	(Ljava/lang/String;CCC)Ljava/lang/String;
    //   77: astore 9
    //   79: aload 8
    //   81: aload 9
    //   83: ldc2_w 127
    //   86: invokevirtual 44	com/appdynamics/eumagent/runtime/c$a:b	(Ljava/lang/String;J)J
    //   89: lstore 6
    //   91: lload 6
    //   93: lreturn
    //   94: iconst_0
    //   95: istore_2
    //   96: getstatic 86	com/appdynamics/eumagent/runtime/c:b043E043Eо043Eо043E	I
    //   99: getstatic 94	com/appdynamics/eumagent/runtime/c:bоооо043E043E	I
    //   102: iadd
    //   103: getstatic 86	com/appdynamics/eumagent/runtime/c:b043E043Eо043Eо043E	I
    //   106: imul
    //   107: getstatic 90	com/appdynamics/eumagent/runtime/c:b043Eо043E043Eо043E	I
    //   110: irem
    //   111: getstatic 96	com/appdynamics/eumagent/runtime/c:b043E043E043E043Eо043E	I
    //   114: if_icmpeq +14 -> 128
    //   117: invokestatic 92	com/appdynamics/eumagent/runtime/c:bо043E043E043Eо043E	()I
    //   120: putstatic 86	com/appdynamics/eumagent/runtime/c:b043E043Eо043Eо043E	I
    //   123: bipush 38
    //   125: putstatic 96	com/appdynamics/eumagent/runtime/c:b043E043E043E043Eо043E	I
    //   128: getstatic 86	com/appdynamics/eumagent/runtime/c:b043E043Eо043Eо043E	I
    //   131: istore_3
    //   132: getstatic 94	com/appdynamics/eumagent/runtime/c:bоооо043E043E	I
    //   135: istore 4
    //   137: getstatic 86	com/appdynamics/eumagent/runtime/c:b043E043Eо043Eо043E	I
    //   140: istore 5
    //   142: iload_2
    //   143: istore_1
    //   144: iload_3
    //   145: iload 4
    //   147: iadd
    //   148: iload 5
    //   150: imul
    //   151: invokestatic 109	com/appdynamics/eumagent/runtime/c:b043Eооо043E043E	()I
    //   154: irem
    //   155: getstatic 96	com/appdynamics/eumagent/runtime/c:b043E043E043E043Eо043E	I
    //   158: if_icmpeq -102 -> 56
    //   161: invokestatic 92	com/appdynamics/eumagent/runtime/c:bо043E043E043Eо043E	()I
    //   164: putstatic 86	com/appdynamics/eumagent/runtime/c:b043E043Eо043Eо043E	I
    //   167: bipush 94
    //   169: putstatic 96	com/appdynamics/eumagent/runtime/c:b043E043E043E043Eо043E	I
    //   172: iload_2
    //   173: istore_1
    //   174: goto -118 -> 56
    //   177: astore 8
    //   179: aload 8
    //   181: athrow
    //   182: astore 8
    //   184: aload 8
    //   186: athrow
    // Local variable table:
    //   start	length	slot	name	signature
    //   0	187	0	this	c
    //   6	168	1	i	int
    //   95	78	2	j	int
    //   131	17	3	k	int
    //   135	13	4	m	int
    //   140	11	5	n	int
    //   3	89	6	l	long
    //   18	62	8	localObject1	Object
    //   177	3	8	localException1	Exception
    //   182	3	8	localException2	Exception
    //   24	58	9	localObject2	Object
    //   37	7	10	str	String
    // Exception table:
    //   from	to	target	type
    //   39	56	177	java/lang/Exception
    //   60	79	177	java/lang/Exception
    //   144	172	177	java/lang/Exception
    //   7	39	182	java/lang/Exception
    //   79	91	182	java/lang/Exception
    //   128	142	182	java/lang/Exception
  }
  
  final long h()
  {
    long l = this.c.getAndIncrement();
    if (l % 100L == 0L)
    {
      int i = b043E043Eо043Eо043E;
      int j = bоооо043E043E;
      switch (1)
      {
      case 0: 
      default: 
        for (;;)
        {
          switch (0)
          {
          }
        }
      }
      switch (i * (j + i) % b043Eо043E043Eо043E)
      {
      default: 
        b043E043Eо043Eо043E = bо043E043E043Eо043E();
        b043E043E043E043Eо043E = bо043E043E043Eо043E();
      }
      this.a.a(gguuuu.bккккк043Aкк043A043A("|\rz\003\bqt\005|\002q}", 'ç', '\005'), l);
      switch (0)
      {
      case 1: 
      default: 
        for (;;)
        {
          switch (1)
          {
          }
        }
      }
    }
    if ((b043E043Eо043Eо043E + bоооо043E043E) * b043E043Eо043Eо043E % b043Eо043E043Eо043E != b043E043E043E043Eо043E)
    {
      b043E043Eо043Eо043E = 62;
      b043E043E043E043Eо043E = 23;
    }
    return l;
  }
  
  /* Error */
  final long i()
  {
    // Byte code:
    //   0: aload_0
    //   1: getfield 31	com/appdynamics/eumagent/runtime/c:c	Ljava/util/concurrent/atomic/AtomicLong;
    //   4: invokevirtual 181	java/util/concurrent/atomic/AtomicLong:getAndIncrement	()J
    //   7: lstore_3
    //   8: invokestatic 92	com/appdynamics/eumagent/runtime/c:bо043E043E043Eо043E	()I
    //   11: istore_1
    //   12: getstatic 94	com/appdynamics/eumagent/runtime/c:bоооо043E043E	I
    //   15: istore_2
    //   16: iload_1
    //   17: iload_2
    //   18: iadd
    //   19: invokestatic 92	com/appdynamics/eumagent/runtime/c:bо043E043E043Eо043E	()I
    //   22: imul
    //   23: getstatic 90	com/appdynamics/eumagent/runtime/c:b043Eо043E043Eо043E	I
    //   26: irem
    //   27: invokestatic 117	com/appdynamics/eumagent/runtime/c:bо043Eоо043E043E	()I
    //   30: if_icmpeq +15 -> 45
    //   33: invokestatic 92	com/appdynamics/eumagent/runtime/c:bо043E043E043Eо043E	()I
    //   36: putstatic 86	com/appdynamics/eumagent/runtime/c:b043E043Eо043Eо043E	I
    //   39: invokestatic 92	com/appdynamics/eumagent/runtime/c:bо043E043E043Eо043E	()I
    //   42: putstatic 96	com/appdynamics/eumagent/runtime/c:b043E043E043E043Eо043E	I
    //   45: lload_3
    //   46: lreturn
    //   47: astore 5
    //   49: aload 5
    //   51: athrow
    //   52: astore 5
    //   54: aload 5
    //   56: athrow
    // Local variable table:
    //   start	length	slot	name	signature
    //   0	57	0	this	c
    //   11	8	1	i	int
    //   15	4	2	j	int
    //   7	39	3	l	long
    //   47	3	5	localException1	Exception
    //   52	3	5	localException2	Exception
    // Exception table:
    //   from	to	target	type
    //   0	16	47	java/lang/Exception
    //   16	45	52	java/lang/Exception
  }
  
  public final boolean j()
  {
    try
    {
      boolean bool = this.a.b(gguuuu.bк043Aккк043Aкк043A043A("7=6@\"B=CJ*9??OU#J@G", '\032', '3', '\003'), false);
      return bool;
    }
    catch (Exception localException)
    {
      throw localException;
    }
  }
  
  static class a
  {
    public static int b043E043Eо043E043E043E = 1;
    public static int b043Eоо043E043E043E = 75;
    public static int bо043Eо043E043E043E = 0;
    public static int bоо043E043E043E043E = 2;
    private final SharedPreferences a;
    
    a(Context paramContext)
    {
      if (paramContext == null) {
        throw new IllegalArgumentException(gguuuu.bк043Aккк043Aкк043A043A("\023><A1C>h+(4337a#%^,2('Z", 'Q', 'Ý', '\002'));
      }
      this.a = paramContext.getApplicationContext().getSharedPreferences(gguuuu.bккккк043Aкк043A043A("ivu7k{|q\b}q~{v\bC{\r\006z\002\001\013\022L\022\026\020\027\r\022\013T\t\020\017\031 \"\020$\026", '\006', '\000'), 0);
    }
    
    public static int b0431ббббб()
    {
      return 1;
    }
    
    public static int b043Eо043E043E043E043E()
    {
      return 70;
    }
    
    public static int bб0431бббб()
    {
      return 2;
    }
    
    public static int bо043E043E043E043E043E()
    {
      return 0;
    }
    
    public void a(String paramString, long paramLong)
    {
      throw new Runtime("d2j fail translate: java.lang.IndexOutOfBoundsException: fromIndex < 0: -1\n\tat java.util.BitSet.nextSetBit(BitSet.java:712)\n\tat com.googlecode.dex2jar.ir.ts.array.FillArrayTransformer.makeSureAllElementAreAssigned(FillArrayTransformer.java:505)\n\tat com.googlecode.dex2jar.ir.ts.array.FillArrayTransformer.transformReportChanged(FillArrayTransformer.java:123)\n\tat com.googlecode.dex2jar.ir.ts.StatedTransformer.transform(StatedTransformer.java:10)\n\tat com.googlecode.d2j.dex.Dex2jar$2.optimize(Dex2jar.java:149)\n\tat com.googlecode.d2j.dex.Dex2Asm.convertCode(Dex2Asm.java:414)\n\tat com.googlecode.d2j.dex.ExDex2Asm.convertCode(ExDex2Asm.java:42)\n\tat com.googlecode.d2j.dex.Dex2jar$2.convertCode(Dex2jar.java:128)\n\tat com.googlecode.d2j.dex.Dex2Asm.convertMethod(Dex2Asm.java:509)\n\tat com.googlecode.d2j.dex.Dex2Asm.convertClass(Dex2Asm.java:406)\n\tat com.googlecode.d2j.dex.Dex2Asm.convertDex(Dex2Asm.java:422)\n\tat com.googlecode.d2j.dex.Dex2jar.doTranslate(Dex2jar.java:172)\n\tat com.googlecode.d2j.dex.Dex2jar.to(Dex2jar.java:272)\n\tat com.googlecode.dex2jar.tools.Dex2jarCmd.doCommandLine(Dex2jarCmd.java:108)\n\tat com.googlecode.dex2jar.tools.BaseCmd.doMain(BaseCmd.java:288)\n\tat com.googlecode.dex2jar.tools.Dex2jarCmd.main(Dex2jarCmd.java:32)\n");
    }
    
    public void a(String paramString1, String paramString2)
    {
      this.a.edit().putString(paramString1, paramString2).commit();
      if ((b043Eоо043E043E043E + b0431ббббб()) * b043Eоо043E043E043E % bб0431бббб() != bо043E043E043E043E043E())
      {
        b043Eоо043E043E043E = 40;
        bо043Eо043E043E043E = b043Eо043E043E043E043E();
      }
    }
    
    /* Error */
    public void a(String paramString, boolean paramBoolean)
    {
      // Byte code:
      //   0: aload_0
      //   1: getfield 53	com/appdynamics/eumagent/runtime/c$a:a	Landroid/content/SharedPreferences;
      //   4: invokeinterface 74 1 0
      //   9: astore 8
      //   11: getstatic 86	com/appdynamics/eumagent/runtime/c$a:b043Eоо043E043E043E	I
      //   14: getstatic 101	com/appdynamics/eumagent/runtime/c$a:b043E043Eо043E043E043E	I
      //   17: iadd
      //   18: getstatic 86	com/appdynamics/eumagent/runtime/c$a:b043Eоо043E043E043E	I
      //   21: imul
      //   22: getstatic 103	com/appdynamics/eumagent/runtime/c$a:bоо043E043E043E043E	I
      //   25: irem
      //   26: getstatic 96	com/appdynamics/eumagent/runtime/c$a:bо043Eо043E043E043E	I
      //   29: if_icmpeq +15 -> 44
      //   32: invokestatic 94	com/appdynamics/eumagent/runtime/c$a:b043Eо043E043E043E043E	()I
      //   35: putstatic 86	com/appdynamics/eumagent/runtime/c$a:b043Eоо043E043E043E	I
      //   38: invokestatic 94	com/appdynamics/eumagent/runtime/c$a:b043Eо043E043E043E043E	()I
      //   41: putstatic 96	com/appdynamics/eumagent/runtime/c$a:bо043Eо043E043E043E	I
      //   44: getstatic 86	com/appdynamics/eumagent/runtime/c$a:b043Eоо043E043E043E	I
      //   47: istore_3
      //   48: getstatic 101	com/appdynamics/eumagent/runtime/c$a:b043E043Eо043E043E043E	I
      //   51: istore 4
      //   53: getstatic 86	com/appdynamics/eumagent/runtime/c$a:b043Eоо043E043E043E	I
      //   56: istore 5
      //   58: getstatic 103	com/appdynamics/eumagent/runtime/c$a:bоо043E043E043E043E	I
      //   61: istore 6
      //   63: getstatic 96	com/appdynamics/eumagent/runtime/c$a:bо043Eо043E043E043E	I
      //   66: istore 7
      //   68: iload_3
      //   69: iload 4
      //   71: iadd
      //   72: iload 5
      //   74: imul
      //   75: iload 6
      //   77: irem
      //   78: iload 7
      //   80: if_icmpeq +13 -> 93
      //   83: bipush 10
      //   85: putstatic 86	com/appdynamics/eumagent/runtime/c$a:b043Eоо043E043E043E	I
      //   88: bipush 78
      //   90: putstatic 96	com/appdynamics/eumagent/runtime/c$a:bо043Eо043E043E043E	I
      //   93: aload 8
      //   95: aload_1
      //   96: iload_2
      //   97: invokeinterface 107 3 0
      //   102: invokeinterface 84 1 0
      //   107: pop
      //   108: return
      //   109: astore_1
      //   110: aload_1
      //   111: athrow
      //   112: astore_1
      //   113: aload_1
      //   114: athrow
      // Local variable table:
      //   start	length	slot	name	signature
      //   0	115	0	this	a
      //   0	115	1	paramString	String
      //   0	115	2	paramBoolean	boolean
      //   47	25	3	i	int
      //   51	21	4	j	int
      //   56	19	5	k	int
      //   61	17	6	m	int
      //   66	15	7	n	int
      //   9	85	8	localEditor	SharedPreferences.Editor
      // Exception table:
      //   from	to	target	type
      //   0	11	109	java/lang/Exception
      //   63	68	109	java/lang/Exception
      //   93	108	109	java/lang/Exception
      //   44	63	112	java/lang/Exception
      //   83	93	112	java/lang/Exception
    }
    
    /* Error */
    public long b(String paramString, long paramLong)
    {
      // Byte code:
      //   0: getstatic 86	com/appdynamics/eumagent/runtime/c$a:b043Eоо043E043E043E	I
      //   3: getstatic 101	com/appdynamics/eumagent/runtime/c$a:b043E043Eо043E043E043E	I
      //   6: iadd
      //   7: getstatic 86	com/appdynamics/eumagent/runtime/c$a:b043Eоо043E043E043E	I
      //   10: imul
      //   11: invokestatic 90	com/appdynamics/eumagent/runtime/c$a:bб0431бббб	()I
      //   14: irem
      //   15: getstatic 96	com/appdynamics/eumagent/runtime/c$a:bо043Eо043E043E043E	I
      //   18: if_icmpeq +14 -> 32
      //   21: invokestatic 94	com/appdynamics/eumagent/runtime/c$a:b043Eо043E043E043E043E	()I
      //   24: putstatic 86	com/appdynamics/eumagent/runtime/c$a:b043Eоо043E043E043E	I
      //   27: bipush 68
      //   29: putstatic 96	com/appdynamics/eumagent/runtime/c$a:bо043Eо043E043E043E	I
      //   32: iconst_1
      //   33: tableswitch	default:+23->56, 0:+-33->0, 1:+50->83
      //   56: iconst_1
      //   57: tableswitch	default:+23->80, 0:+-57->0, 1:+26->83
      //   80: goto -24 -> 56
      //   83: invokestatic 94	com/appdynamics/eumagent/runtime/c$a:b043Eо043E043E043E043E	()I
      //   86: istore 4
      //   88: getstatic 101	com/appdynamics/eumagent/runtime/c$a:b043E043Eо043E043E043E	I
      //   91: istore 5
      //   93: iload 4
      //   95: iload 5
      //   97: iadd
      //   98: invokestatic 94	com/appdynamics/eumagent/runtime/c$a:b043Eо043E043E043E043E	()I
      //   101: imul
      //   102: getstatic 103	com/appdynamics/eumagent/runtime/c$a:bоо043E043E043E043E	I
      //   105: irem
      //   106: getstatic 96	com/appdynamics/eumagent/runtime/c$a:bо043Eо043E043E043E	I
      //   109: if_icmpeq +15 -> 124
      //   112: invokestatic 94	com/appdynamics/eumagent/runtime/c$a:b043Eо043E043E043E043E	()I
      //   115: putstatic 86	com/appdynamics/eumagent/runtime/c$a:b043Eоо043E043E043E	I
      //   118: invokestatic 94	com/appdynamics/eumagent/runtime/c$a:b043Eо043E043E043E043E	()I
      //   121: putstatic 96	com/appdynamics/eumagent/runtime/c$a:bо043Eо043E043E043E	I
      //   124: aload_0
      //   125: getfield 53	com/appdynamics/eumagent/runtime/c$a:a	Landroid/content/SharedPreferences;
      //   128: aload_1
      //   129: lload_2
      //   130: invokeinterface 112 4 0
      //   135: lstore_2
      //   136: lload_2
      //   137: lreturn
      //   138: astore_1
      //   139: aload_1
      //   140: athrow
      //   141: astore_1
      //   142: aload_1
      //   143: athrow
      // Local variable table:
      //   start	length	slot	name	signature
      //   0	144	0	this	a
      //   0	144	1	paramString	String
      //   0	144	2	paramLong	long
      //   86	12	4	i	int
      //   91	7	5	j	int
      // Exception table:
      //   from	to	target	type
      //   88	93	138	java/lang/Exception
      //   124	136	138	java/lang/Exception
      //   83	88	141	java/lang/Exception
      //   93	124	141	java/lang/Exception
    }
    
    public String b(String paramString1, String paramString2)
    {
      try
      {
        SharedPreferences localSharedPreferences = this.a;
        if ((b043Eоо043E043E043E + b043E043Eо043E043E043E) * b043Eоо043E043E043E % bоо043E043E043E043E != bо043Eо043E043E043E)
        {
          b043Eоо043E043E043E = b043Eо043E043E043E043E();
          bо043Eо043E043E043E = b043Eо043E043E043E043E();
          if ((b043Eо043E043E043E043E() + b043E043Eо043E043E043E) * b043Eо043E043E043E043E() % bоо043E043E043E043E != bо043Eо043E043E043E)
          {
            b043Eоо043E043E043E = b043Eо043E043E043E043E();
            bо043Eо043E043E043E = b043Eо043E043E043E043E();
          }
        }
        paramString1 = localSharedPreferences.getString(paramString1, paramString2);
        return paramString1;
      }
      catch (Exception paramString1)
      {
        throw paramString1;
      }
    }
    
    public boolean b(String paramString, boolean paramBoolean)
    {
      switch (0)
      {
      case 1: 
      default: 
        for (;;)
        {
          switch (0)
          {
          }
        }
      }
      SharedPreferences localSharedPreferences = this.a;
      int i = b043Eоо043E043E043E;
      switch (i * (b043E043Eо043E043E043E + i) % bоо043E043E043E043E)
      {
      default: 
        b043Eоо043E043E043E = 53;
        bо043Eо043E043E043E = b043Eо043E043E043E043E();
      }
      return localSharedPreferences.getBoolean(paramString, false);
    }
  }
}
