package com.appdynamics.eumagent.runtime;

public abstract interface d
{
  public static final int a;
  public static final int b04310431043104310431б;
  public static final int b0431б043104310431б = 1;
  public static final int bб0431043104310431б = 2;
  public static final int bбб043104310431б = 20;
  
  /* Error */
  static
  {
    // Byte code:
    //   0: new 19	java/util/HashSet
    //   3: dup
    //   4: iconst_5
    //   5: anewarray 21	java/lang/String
    //   8: dup
    //   9: iconst_0
    //   10: ldc 23
    //   12: sipush 171
    //   15: sipush 154
    //   18: iconst_1
    //   19: invokestatic 29	kkkkkk/gguuuu:bк043Aккк043Aкк043A043A	(Ljava/lang/String;CCC)Ljava/lang/String;
    //   22: aastore
    //   23: dup
    //   24: iconst_1
    //   25: ldc 31
    //   27: sipush 196
    //   30: iconst_5
    //   31: invokestatic 35	kkkkkk/gguuuu:bккккк043Aкк043A043A	(Ljava/lang/String;CC)Ljava/lang/String;
    //   34: aastore
    //   35: dup
    //   36: iconst_2
    //   37: ldc 37
    //   39: bipush 50
    //   41: iconst_5
    //   42: invokestatic 35	kkkkkk/gguuuu:bккккк043Aкк043A043A	(Ljava/lang/String;CC)Ljava/lang/String;
    //   45: aastore
    //   46: dup
    //   47: iconst_3
    //   48: ldc 39
    //   50: sipush 209
    //   53: sipush 245
    //   56: iconst_2
    //   57: invokestatic 29	kkkkkk/gguuuu:bк043Aккк043Aкк043A043A	(Ljava/lang/String;CCC)Ljava/lang/String;
    //   60: aastore
    //   61: dup
    //   62: iconst_4
    //   63: ldc 41
    //   65: bipush 19
    //   67: iconst_4
    //   68: invokestatic 35	kkkkkk/gguuuu:bккккк043Aкк043A043A	(Ljava/lang/String;CC)Ljava/lang/String;
    //   71: aastore
    //   72: invokestatic 47	java/util/Arrays:asList	([Ljava/lang/Object;)Ljava/util/List;
    //   75: invokespecial 51	java/util/HashSet:<init>	(Ljava/util/Collection;)V
    //   78: astore_1
    //   79: aload_1
    //   80: invokestatic 57	java/util/Collections:unmodifiableSet	(Ljava/util/Set;)Ljava/util/Set;
    //   83: pop
    //   84: getstatic 59	com/appdynamics/eumagent/runtime/d:bбб043104310431б	I
    //   87: istore_0
    //   88: iload_0
    //   89: getstatic 61	com/appdynamics/eumagent/runtime/d:b0431б043104310431б	I
    //   92: iload_0
    //   93: iadd
    //   94: imul
    //   95: getstatic 63	com/appdynamics/eumagent/runtime/d:bб0431043104310431б	I
    //   98: irem
    //   99: tableswitch	default:+17->116, 0:+22->121
    //   116: bipush 17
    //   118: putstatic 61	com/appdynamics/eumagent/runtime/d:b0431б043104310431б	I
    //   121: getstatic 69	java/util/concurrent/TimeUnit:MILLISECONDS	Ljava/util/concurrent/TimeUnit;
    //   124: ldc2_w 70
    //   127: getstatic 74	java/util/concurrent/TimeUnit:MINUTES	Ljava/util/concurrent/TimeUnit;
    //   130: invokevirtual 78	java/util/concurrent/TimeUnit:convert	(JLjava/util/concurrent/TimeUnit;)J
    //   133: l2i
    //   134: putstatic 80	com/appdynamics/eumagent/runtime/d:a	I
    //   137: getstatic 69	java/util/concurrent/TimeUnit:MILLISECONDS	Ljava/util/concurrent/TimeUnit;
    //   140: astore_1
    //   141: getstatic 83	java/util/concurrent/TimeUnit:HOURS	Ljava/util/concurrent/TimeUnit;
    //   144: astore_2
    //   145: getstatic 59	com/appdynamics/eumagent/runtime/d:bбб043104310431б	I
    //   148: getstatic 61	com/appdynamics/eumagent/runtime/d:b0431б043104310431б	I
    //   151: iadd
    //   152: getstatic 59	com/appdynamics/eumagent/runtime/d:bбб043104310431б	I
    //   155: imul
    //   156: getstatic 63	com/appdynamics/eumagent/runtime/d:bб0431043104310431б	I
    //   159: irem
    //   160: getstatic 85	com/appdynamics/eumagent/runtime/d:b04310431043104310431б	I
    //   163: if_icmpeq +8 -> 171
    //   166: bipush 86
    //   168: putstatic 85	com/appdynamics/eumagent/runtime/d:b04310431043104310431б	I
    //   171: aload_1
    //   172: lconst_1
    //   173: aload_2
    //   174: invokevirtual 78	java/util/concurrent/TimeUnit:convert	(JLjava/util/concurrent/TimeUnit;)J
    //   177: pop2
    //   178: return
    //   179: astore_1
    //   180: aload_1
    //   181: athrow
    //   182: astore_1
    //   183: aload_1
    //   184: athrow
    // Local variable table:
    //   start	length	slot	name	signature
    //   87	8	0	i	int
    //   78	94	1	localObject	Object
    //   179	2	1	localException1	Exception
    //   182	2	1	localException2	Exception
    //   144	30	2	localTimeUnit	java.util.concurrent.TimeUnit
    // Exception table:
    //   from	to	target	type
    //   79	84	179	java/lang/Exception
    //   121	145	179	java/lang/Exception
    //   171	178	179	java/lang/Exception
    //   0	79	182	java/lang/Exception
  }
}
