package com.appdynamics.eumagent.runtime;

import android.content.BroadcastReceiver;
import android.content.Context;
import android.content.IntentFilter;
import android.content.pm.PackageInfo;
import android.content.pm.PackageManager;
import android.os.Build;
import android.os.Build.VERSION;
import android.os.Environment;
import android.os.StatFs;
import android.telephony.TelephonyManager;
import android.util.Log;
import com.appdynamics.eumagent.runtime.events.l;
import com.appdynamics.eumagent.runtime.events.l.b;
import com.appdynamics.eumagent.runtime.events.r;
import com.appdynamics.eumagent.runtime.events.s;
import java.io.File;
import java.io.FileFilter;
import java.util.Map;
import java.util.regex.Pattern;
import kkkkkk.gguuuu;

class e
  implements l.b
{
  private static final String a;
  public static int b04310431б043104310431 = 0;
  public static int b0431б0431б04310431 = 1;
  public static int b0431бб043104310431 = 2;
  public static int bбб0431б04310431 = 44;
  private static final Map k;
  private final Context b;
  private final l c;
  private final b d;
  private final String e;
  private final String f;
  private volatile String g;
  private String h;
  private boolean i;
  private com.appdynamics.eumagent.runtime.events.e j = null;
  
  /* Error */
  static
  {
    // Byte code:
    //   0: ldc 2
    //   2: invokevirtual 49	java/lang/Class:getSimpleName	()Ljava/lang/String;
    //   5: astore_3
    //   6: getstatic 51	com/appdynamics/eumagent/runtime/e:bбб0431б04310431	I
    //   9: istore_0
    //   10: getstatic 53	com/appdynamics/eumagent/runtime/e:b0431б0431б04310431	I
    //   13: istore_1
    //   14: invokestatic 57	com/appdynamics/eumagent/runtime/e:bб04310431б04310431	()I
    //   17: istore_2
    //   18: iload_0
    //   19: iload_1
    //   20: iload_0
    //   21: iadd
    //   22: imul
    //   23: iload_2
    //   24: irem
    //   25: tableswitch	default:+19->44, 0:+31->56
    //   44: invokestatic 60	com/appdynamics/eumagent/runtime/e:b043104310431б04310431	()I
    //   47: putstatic 51	com/appdynamics/eumagent/runtime/e:bбб0431б04310431	I
    //   50: invokestatic 60	com/appdynamics/eumagent/runtime/e:b043104310431б04310431	()I
    //   53: putstatic 53	com/appdynamics/eumagent/runtime/e:b0431б0431б04310431	I
    //   56: aload_3
    //   57: putstatic 62	com/appdynamics/eumagent/runtime/e:a	Ljava/lang/String;
    //   60: new 64	java/util/HashMap
    //   63: dup
    //   64: invokespecial 67	java/util/HashMap:<init>	()V
    //   67: astore_3
    //   68: aload_3
    //   69: putstatic 69	com/appdynamics/eumagent/runtime/e:k	Ljava/util/Map;
    //   72: aload_3
    //   73: bipush 7
    //   75: invokestatic 75	java/lang/Integer:valueOf	(I)Ljava/lang/Integer;
    //   78: ldc 77
    //   80: bipush 64
    //   82: bipush 69
    //   84: iconst_0
    //   85: invokestatic 83	kkkkkk/gguuuu:bк043Aккк043Aкк043A043A	(Ljava/lang/String;CCC)Ljava/lang/String;
    //   88: invokeinterface 89 3 0
    //   93: pop
    //   94: getstatic 69	com/appdynamics/eumagent/runtime/e:k	Ljava/util/Map;
    //   97: astore_3
    //   98: ldc 91
    //   100: bipush 44
    //   102: iconst_3
    //   103: invokestatic 95	kkkkkk/gguuuu:bккккк043Aкк043A043A	(Ljava/lang/String;CC)Ljava/lang/String;
    //   106: astore 4
    //   108: getstatic 51	com/appdynamics/eumagent/runtime/e:bбб0431б04310431	I
    //   111: getstatic 53	com/appdynamics/eumagent/runtime/e:b0431б0431б04310431	I
    //   114: iadd
    //   115: getstatic 51	com/appdynamics/eumagent/runtime/e:bбб0431б04310431	I
    //   118: imul
    //   119: getstatic 97	com/appdynamics/eumagent/runtime/e:b0431бб043104310431	I
    //   122: irem
    //   123: invokestatic 100	com/appdynamics/eumagent/runtime/e:bббб043104310431	()I
    //   126: if_icmpeq +14 -> 140
    //   129: bipush 55
    //   131: putstatic 51	com/appdynamics/eumagent/runtime/e:bбб0431б04310431	I
    //   134: invokestatic 60	com/appdynamics/eumagent/runtime/e:b043104310431б04310431	()I
    //   137: putstatic 53	com/appdynamics/eumagent/runtime/e:b0431б0431б04310431	I
    //   140: aload_3
    //   141: iconst_4
    //   142: invokestatic 75	java/lang/Integer:valueOf	(I)Ljava/lang/Integer;
    //   145: aload 4
    //   147: invokeinterface 89 3 0
    //   152: pop
    //   153: getstatic 69	com/appdynamics/eumagent/runtime/e:k	Ljava/util/Map;
    //   156: iconst_2
    //   157: invokestatic 75	java/lang/Integer:valueOf	(I)Ljava/lang/Integer;
    //   160: ldc 102
    //   162: sipush 147
    //   165: sipush 194
    //   168: iconst_2
    //   169: invokestatic 83	kkkkkk/gguuuu:bк043Aккк043Aкк043A043A	(Ljava/lang/String;CCC)Ljava/lang/String;
    //   172: invokeinterface 89 3 0
    //   177: pop
    //   178: getstatic 69	com/appdynamics/eumagent/runtime/e:k	Ljava/util/Map;
    //   181: astore_3
    //   182: aload_3
    //   183: iconst_1
    //   184: invokestatic 75	java/lang/Integer:valueOf	(I)Ljava/lang/Integer;
    //   187: ldc 104
    //   189: sipush 174
    //   192: iconst_3
    //   193: invokestatic 95	kkkkkk/gguuuu:bккккк043Aкк043A043A	(Ljava/lang/String;CC)Ljava/lang/String;
    //   196: invokeinterface 89 3 0
    //   201: pop
    //   202: getstatic 69	com/appdynamics/eumagent/runtime/e:k	Ljava/util/Map;
    //   205: bipush 11
    //   207: invokestatic 75	java/lang/Integer:valueOf	(I)Ljava/lang/Integer;
    //   210: ldc 106
    //   212: sipush 207
    //   215: sipush 140
    //   218: iconst_1
    //   219: invokestatic 83	kkkkkk/gguuuu:bк043Aккк043Aкк043A043A	(Ljava/lang/String;CCC)Ljava/lang/String;
    //   222: invokeinterface 89 3 0
    //   227: pop
    //   228: getstatic 69	com/appdynamics/eumagent/runtime/e:k	Ljava/util/Map;
    //   231: iconst_5
    //   232: invokestatic 75	java/lang/Integer:valueOf	(I)Ljava/lang/Integer;
    //   235: ldc 108
    //   237: sipush 184
    //   240: bipush 23
    //   242: iconst_1
    //   243: invokestatic 83	kkkkkk/gguuuu:bк043Aккк043Aкк043A043A	(Ljava/lang/String;CCC)Ljava/lang/String;
    //   246: invokeinterface 89 3 0
    //   251: pop
    //   252: getstatic 69	com/appdynamics/eumagent/runtime/e:k	Ljava/util/Map;
    //   255: astore_3
    //   256: aload_3
    //   257: bipush 6
    //   259: invokestatic 75	java/lang/Integer:valueOf	(I)Ljava/lang/Integer;
    //   262: ldc 110
    //   264: bipush 28
    //   266: bipush 22
    //   268: iconst_0
    //   269: invokestatic 83	kkkkkk/gguuuu:bк043Aккк043Aкк043A043A	(Ljava/lang/String;CCC)Ljava/lang/String;
    //   272: invokeinterface 89 3 0
    //   277: pop
    //   278: getstatic 69	com/appdynamics/eumagent/runtime/e:k	Ljava/util/Map;
    //   281: astore_3
    //   282: ldc 112
    //   284: sipush 235
    //   287: iconst_3
    //   288: invokestatic 95	kkkkkk/gguuuu:bккккк043Aкк043A043A	(Ljava/lang/String;CC)Ljava/lang/String;
    //   291: astore 4
    //   293: aload_3
    //   294: bipush 10
    //   296: invokestatic 75	java/lang/Integer:valueOf	(I)Ljava/lang/Integer;
    //   299: aload 4
    //   301: invokeinterface 89 3 0
    //   306: pop
    //   307: getstatic 69	com/appdynamics/eumagent/runtime/e:k	Ljava/util/Map;
    //   310: astore_3
    //   311: aload_3
    //   312: bipush 9
    //   314: invokestatic 75	java/lang/Integer:valueOf	(I)Ljava/lang/Integer;
    //   317: ldc 114
    //   319: bipush 63
    //   321: iconst_5
    //   322: invokestatic 95	kkkkkk/gguuuu:bккккк043Aкк043A043A	(Ljava/lang/String;CC)Ljava/lang/String;
    //   325: invokeinterface 89 3 0
    //   330: pop
    //   331: getstatic 69	com/appdynamics/eumagent/runtime/e:k	Ljava/util/Map;
    //   334: iconst_3
    //   335: invokestatic 75	java/lang/Integer:valueOf	(I)Ljava/lang/Integer;
    //   338: ldc 116
    //   340: sipush 202
    //   343: bipush 29
    //   345: iconst_2
    //   346: invokestatic 83	kkkkkk/gguuuu:bк043Aккк043Aкк043A043A	(Ljava/lang/String;CCC)Ljava/lang/String;
    //   349: invokeinterface 89 3 0
    //   354: pop
    //   355: getstatic 69	com/appdynamics/eumagent/runtime/e:k	Ljava/util/Map;
    //   358: astore_3
    //   359: aload_3
    //   360: bipush 14
    //   362: invokestatic 75	java/lang/Integer:valueOf	(I)Ljava/lang/Integer;
    //   365: ldc 118
    //   367: sipush 174
    //   370: bipush 98
    //   372: iconst_3
    //   373: invokestatic 83	kkkkkk/gguuuu:bк043Aккк043Aкк043A043A	(Ljava/lang/String;CCC)Ljava/lang/String;
    //   376: invokeinterface 89 3 0
    //   381: pop
    //   382: getstatic 69	com/appdynamics/eumagent/runtime/e:k	Ljava/util/Map;
    //   385: bipush 12
    //   387: invokestatic 75	java/lang/Integer:valueOf	(I)Ljava/lang/Integer;
    //   390: ldc 120
    //   392: bipush 108
    //   394: iconst_5
    //   395: invokestatic 95	kkkkkk/gguuuu:bккккк043Aкк043A043A	(Ljava/lang/String;CC)Ljava/lang/String;
    //   398: invokeinterface 89 3 0
    //   403: pop
    //   404: getstatic 69	com/appdynamics/eumagent/runtime/e:k	Ljava/util/Map;
    //   407: bipush 15
    //   409: invokestatic 75	java/lang/Integer:valueOf	(I)Ljava/lang/Integer;
    //   412: ldc 122
    //   414: sipush 152
    //   417: sipush 145
    //   420: iconst_1
    //   421: invokestatic 83	kkkkkk/gguuuu:bк043Aккк043Aкк043A043A	(Ljava/lang/String;CCC)Ljava/lang/String;
    //   424: invokeinterface 89 3 0
    //   429: pop
    //   430: getstatic 69	com/appdynamics/eumagent/runtime/e:k	Ljava/util/Map;
    //   433: bipush 8
    //   435: invokestatic 75	java/lang/Integer:valueOf	(I)Ljava/lang/Integer;
    //   438: ldc 124
    //   440: bipush 124
    //   442: sipush 169
    //   445: iconst_1
    //   446: invokestatic 83	kkkkkk/gguuuu:bк043Aккк043Aкк043A043A	(Ljava/lang/String;CCC)Ljava/lang/String;
    //   449: invokeinterface 89 3 0
    //   454: pop
    //   455: getstatic 69	com/appdynamics/eumagent/runtime/e:k	Ljava/util/Map;
    //   458: bipush 13
    //   460: invokestatic 75	java/lang/Integer:valueOf	(I)Ljava/lang/Integer;
    //   463: ldc 126
    //   465: bipush 103
    //   467: iconst_1
    //   468: invokestatic 95	kkkkkk/gguuuu:bккккк043Aкк043A043A	(Ljava/lang/String;CC)Ljava/lang/String;
    //   471: invokeinterface 89 3 0
    //   476: pop
    //   477: return
    //   478: astore_3
    //   479: aload_3
    //   480: athrow
    //   481: astore_3
    //   482: aload_3
    //   483: athrow
    //   484: astore_3
    //   485: aload_3
    //   486: athrow
    //   487: astore_3
    //   488: aload_3
    //   489: athrow
    // Local variable table:
    //   start	length	slot	name	signature
    //   9	14	0	m	int
    //   13	9	1	n	int
    //   17	8	2	i1	int
    //   5	355	3	localObject	Object
    //   478	2	3	localException1	Exception
    //   481	2	3	localException2	Exception
    //   484	2	3	localException3	Exception
    //   487	2	3	localException4	Exception
    //   106	194	4	str	String
    // Exception table:
    //   from	to	target	type
    //   0	6	478	java/lang/Exception
    //   56	108	478	java/lang/Exception
    //   140	182	478	java/lang/Exception
    //   182	256	478	java/lang/Exception
    //   282	293	478	java/lang/Exception
    //   311	355	478	java/lang/Exception
    //   359	404	478	java/lang/Exception
    //   14	18	481	java/lang/Exception
    //   44	56	481	java/lang/Exception
    //   479	481	481	java/lang/Exception
    //   485	487	481	java/lang/Exception
    //   256	282	484	java/lang/Exception
    //   293	311	484	java/lang/Exception
    //   355	359	484	java/lang/Exception
    //   404	477	484	java/lang/Exception
    //   6	14	487	java/lang/Exception
  }
  
  e(Context paramContext, String paramString1, String paramString2, l paramL, u paramU)
  {
    this.b = paramContext;
    this.c = paramL;
    this.d = new b((byte)0);
    this.f = paramString1;
    this.e = a(paramContext);
    paramString1 = this.e;
    int m = b(paramContext);
    String str1 = this.f;
    String str2 = Build.MANUFACTURER;
    String str3 = Build.MODEL;
    StatFs localStatFs = new StatFs(Environment.getDataDirectory().getAbsolutePath());
    long l = localStatFs.getBlockCount();
    this.j = new com.appdynamics.eumagent.runtime.events.e(paramString1, m, str1, gguuuu.bккккк043Aкк043A043A("\016\t\016\013\017\r\020", 'l', '\004'), gguuuu.bккккк043Aкк043A043A("[0^\\_2ac0:dg7g=9A>ml?A?rsADDxMIPPzNTN\001P", 'ú', '\004'), str2, str3, Long.valueOf(localStatFs.getBlockSize() * l / 1048576L), e(), f(), Integer.valueOf(g()), Build.VERSION.RELEASE, gguuuu.bккккк043Aкк043A043A("1+)-/80", 'Ü', '\004'), gguuuu.bккккк043Aкк043A043A("'!\037#%.&", 'e', '\001'), paramU.a());
    this.i = false;
    this.g = paramString2;
    this.h = paramContext.getPackageName();
    paramL.a(s.class, this);
    paramL.a(r.class, this);
  }
  
  /* Error */
  private static String a(Context paramContext)
  {
    // Byte code:
    //   0: getstatic 51	com/appdynamics/eumagent/runtime/e:bбб0431б04310431	I
    //   3: getstatic 53	com/appdynamics/eumagent/runtime/e:b0431б0431б04310431	I
    //   6: iadd
    //   7: getstatic 51	com/appdynamics/eumagent/runtime/e:bбб0431б04310431	I
    //   10: imul
    //   11: getstatic 97	com/appdynamics/eumagent/runtime/e:b0431бб043104310431	I
    //   14: irem
    //   15: getstatic 242	com/appdynamics/eumagent/runtime/e:b04310431б043104310431	I
    //   18: if_icmpeq +14 -> 32
    //   21: invokestatic 60	com/appdynamics/eumagent/runtime/e:b043104310431б04310431	()I
    //   24: putstatic 51	com/appdynamics/eumagent/runtime/e:bбб0431б04310431	I
    //   27: bipush 90
    //   29: putstatic 242	com/appdynamics/eumagent/runtime/e:b04310431б043104310431	I
    //   32: ldc -10
    //   34: bipush 66
    //   36: iconst_3
    //   37: invokestatic 95	kkkkkk/gguuuu:bккккк043Aкк043A043A	(Ljava/lang/String;CC)Ljava/lang/String;
    //   40: astore 4
    //   42: aload_0
    //   43: invokevirtual 250	android/content/Context:getPackageManager	()Landroid/content/pm/PackageManager;
    //   46: aload_0
    //   47: invokevirtual 225	android/content/Context:getPackageName	()Ljava/lang/String;
    //   50: iconst_0
    //   51: invokevirtual 256	android/content/pm/PackageManager:getPackageInfo	(Ljava/lang/String;I)Landroid/content/pm/PackageInfo;
    //   54: getfield 261	android/content/pm/PackageInfo:versionName	Ljava/lang/String;
    //   57: astore_0
    //   58: aload_0
    //   59: areturn
    //   60: astore_0
    //   61: iconst_1
    //   62: tableswitch	default:+22->84, 0:+-1->61, 1:+49->111
    //   84: iconst_0
    //   85: tableswitch	default:+23->108, 0:+26->111, 1:+-24->61
    //   108: goto -24 -> 84
    //   111: getstatic 51	com/appdynamics/eumagent/runtime/e:bбб0431б04310431	I
    //   114: istore_1
    //   115: getstatic 53	com/appdynamics/eumagent/runtime/e:b0431б0431б04310431	I
    //   118: istore_2
    //   119: getstatic 97	com/appdynamics/eumagent/runtime/e:b0431бб043104310431	I
    //   122: istore_3
    //   123: aload 4
    //   125: astore_0
    //   126: iload_1
    //   127: iload_2
    //   128: iload_1
    //   129: iadd
    //   130: imul
    //   131: iload_3
    //   132: irem
    //   133: tableswitch	default:+19->152, 0:+-75->58
    //   152: bipush 66
    //   154: putstatic 51	com/appdynamics/eumagent/runtime/e:bбб0431б04310431	I
    //   157: invokestatic 60	com/appdynamics/eumagent/runtime/e:b043104310431б04310431	()I
    //   160: putstatic 242	com/appdynamics/eumagent/runtime/e:b04310431б043104310431	I
    //   163: aload 4
    //   165: areturn
    //   166: astore_0
    //   167: aload_0
    //   168: athrow
    //   169: astore_0
    //   170: aload_0
    //   171: athrow
    // Local variable table:
    //   start	length	slot	name	signature
    //   0	172	0	paramContext	Context
    //   114	17	1	m	int
    //   118	12	2	n	int
    //   122	11	3	i1	int
    //   40	124	4	str	String
    // Exception table:
    //   from	to	target	type
    //   42	58	60	android/content/pm/PackageManager$NameNotFoundException
    //   152	163	166	java/lang/Exception
    //   32	42	169	java/lang/Exception
    //   42	58	169	java/lang/Exception
    //   111	123	169	java/lang/Exception
  }
  
  private static int b(Context paramContext)
  {
    try
    {
      int m = paramContext.getPackageManager().getPackageInfo(paramContext.getPackageName(), 0).versionCode;
      return m;
    }
    catch (Throwable paramContext)
    {
      Log.e(a, gguuuu.bккккк043Aкк043A043A("v#\"\036 L\036\020\036\033\021\f\034\016\022\nA\002\020\017\n\006~{\016\002\007\0055\013x\005\005y~|", '\'', '\003'), paramContext);
    }
    return -1;
  }
  
  public static int b043104310431б04310431()
  {
    return 22;
  }
  
  public static int bб04310431б04310431()
  {
    return 2;
  }
  
  public static int bб0431б043104310431()
  {
    return 1;
  }
  
  public static int bббб043104310431()
  {
    return 0;
  }
  
  private static String c(Context paramContext)
  {
    switch (0)
    {
    case 1: 
    default: 
      for (;;)
      {
        switch (0)
        {
        }
      }
    }
    for (;;)
    {
      try
      {
        paramContext = ((TelephonyManager)paramContext.getSystemService(gguuuu.bк043Aккк043Aкк043A043A("\n\001\007\005z", 'Ø', 'r', '\000'))).getNetworkOperatorName();
        if (paramContext != null)
        {
          localObject = paramContext;
          if (!paramContext.isEmpty()) {}
        }
        else
        {
          localObject = gguuuu.bккккк043Aкк043A043A("g_[]]dZ", '', '\003');
        }
        return localObject;
      }
      catch (Throwable paramContext)
      {
        Object localObject;
        switch (0)
        {
        }
      }
      InstrumentationCallbacks.safeLog(gguuuu.bккккк043Aкк043A043A("f\025\026\024\030F\f\016\036\020\036\032\027\035\031\037\031R\027\026()!\036,Z*\036+$", '', '\001'), paramContext);
      localObject = gguuuu.bк043Aккк043Aкк043A043A("& \036\"$-%", 'ù', '5', '\003');
      paramContext = (Context)localObject;
      if ((b043104310431б04310431() + b0431б0431б04310431) * b043104310431б04310431() % bб04310431б04310431() != b04310431б043104310431)
      {
        if ((bбб0431б04310431 + bб0431б043104310431()) * bбб0431б04310431 % b0431бб043104310431 != b04310431б043104310431)
        {
          bбб0431б04310431 = 43;
          b04310431б043104310431 = 11;
        }
        bбб0431б04310431 = 80;
        b04310431б043104310431 = 66;
        paramContext = (Context)localObject;
      }
    }
    for (;;)
    {
      switch (0)
      {
      }
    }
  }
  
  /* Error */
  private void d()
  {
    // Byte code:
    //   0: aload_0
    //   1: invokespecial 307	com/appdynamics/eumagent/runtime/e:h	()Ljava/lang/String;
    //   4: astore 7
    //   6: aload_0
    //   7: getfield 133	com/appdynamics/eumagent/runtime/e:b	Landroid/content/Context;
    //   10: astore 8
    //   12: aload 8
    //   14: invokestatic 309	com/appdynamics/eumagent/runtime/e:c	(Landroid/content/Context;)Ljava/lang/String;
    //   17: astore 8
    //   19: aload 7
    //   21: aload_0
    //   22: getfield 131	com/appdynamics/eumagent/runtime/e:j	Lcom/appdynamics/eumagent/runtime/events/e;
    //   25: getfield 312	com/appdynamics/eumagent/runtime/events/e:n	Ljava/lang/String;
    //   28: invokevirtual 316	java/lang/String:equals	(Ljava/lang/Object;)Z
    //   31: ifeq +22 -> 53
    //   34: aload 8
    //   36: aload_0
    //   37: getfield 131	com/appdynamics/eumagent/runtime/e:j	Lcom/appdynamics/eumagent/runtime/events/e;
    //   40: getfield 319	com/appdynamics/eumagent/runtime/events/e:m	Ljava/lang/String;
    //   43: invokevirtual 316	java/lang/String:equals	(Ljava/lang/Object;)Z
    //   46: istore 6
    //   48: iload 6
    //   50: ifne +90 -> 140
    //   53: aload_0
    //   54: getfield 131	com/appdynamics/eumagent/runtime/e:j	Lcom/appdynamics/eumagent/runtime/events/e;
    //   57: astore 9
    //   59: getstatic 51	com/appdynamics/eumagent/runtime/e:bбб0431б04310431	I
    //   62: istore_1
    //   63: getstatic 53	com/appdynamics/eumagent/runtime/e:b0431б0431б04310431	I
    //   66: istore_2
    //   67: getstatic 51	com/appdynamics/eumagent/runtime/e:bбб0431б04310431	I
    //   70: istore_3
    //   71: getstatic 97	com/appdynamics/eumagent/runtime/e:b0431бб043104310431	I
    //   74: istore 4
    //   76: getstatic 242	com/appdynamics/eumagent/runtime/e:b04310431б043104310431	I
    //   79: istore 5
    //   81: iload_1
    //   82: iload_2
    //   83: iadd
    //   84: iload_3
    //   85: imul
    //   86: iload 4
    //   88: irem
    //   89: iload 5
    //   91: if_icmpeq +13 -> 104
    //   94: bipush 32
    //   96: putstatic 51	com/appdynamics/eumagent/runtime/e:bбб0431б04310431	I
    //   99: bipush 88
    //   101: putstatic 242	com/appdynamics/eumagent/runtime/e:b04310431б043104310431	I
    //   104: aload_0
    //   105: aload 9
    //   107: aload 8
    //   109: aload 7
    //   111: aload 9
    //   113: getfield 322	com/appdynamics/eumagent/runtime/events/e:o	Ljava/util/Map;
    //   116: invokevirtual 325	com/appdynamics/eumagent/runtime/events/e:a	(Ljava/lang/String;Ljava/lang/String;Ljava/util/Map;)Lcom/appdynamics/eumagent/runtime/events/e;
    //   119: putfield 131	com/appdynamics/eumagent/runtime/e:j	Lcom/appdynamics/eumagent/runtime/events/e;
    //   122: iconst_1
    //   123: ldc_w 327
    //   126: sipush 205
    //   129: iconst_3
    //   130: invokestatic 95	kkkkkk/gguuuu:bккккк043Aкк043A043A	(Ljava/lang/String;CC)Ljava/lang/String;
    //   133: aload 7
    //   135: aload 8
    //   137: invokestatic 332	com/appdynamics/eumagent/runtime/util/c:a	(ILjava/lang/String;Ljava/lang/Object;Ljava/lang/Object;)V
    //   140: return
    //   141: astore 7
    //   143: aload 7
    //   145: athrow
    //   146: astore 7
    //   148: aload 7
    //   150: athrow
    // Local variable table:
    //   start	length	slot	name	signature
    //   0	151	0	this	e
    //   62	22	1	m	int
    //   66	18	2	n	int
    //   70	16	3	i1	int
    //   74	15	4	i2	int
    //   79	13	5	i3	int
    //   46	3	6	bool	boolean
    //   4	130	7	str	String
    //   141	3	7	localException1	Exception
    //   146	3	7	localException2	Exception
    //   10	126	8	localObject	Object
    //   57	55	9	localE	com.appdynamics.eumagent.runtime.events.e
    // Exception table:
    //   from	to	target	type
    //   0	6	141	java/lang/Exception
    //   12	48	141	java/lang/Exception
    //   59	81	141	java/lang/Exception
    //   104	140	141	java/lang/Exception
    //   6	12	146	java/lang/Exception
    //   53	59	146	java/lang/Exception
    //   94	104	146	java/lang/Exception
  }
  
  /* Error */
  private static String e()
  {
    // Byte code:
    //   0: aconst_null
    //   1: astore 7
    //   3: getstatic 51	com/appdynamics/eumagent/runtime/e:bбб0431б04310431	I
    //   6: istore_0
    //   7: getstatic 53	com/appdynamics/eumagent/runtime/e:b0431б0431б04310431	I
    //   10: istore_1
    //   11: getstatic 51	com/appdynamics/eumagent/runtime/e:bбб0431б04310431	I
    //   14: istore_2
    //   15: getstatic 97	com/appdynamics/eumagent/runtime/e:b0431бб043104310431	I
    //   18: istore_3
    //   19: invokestatic 100	com/appdynamics/eumagent/runtime/e:bббб043104310431	()I
    //   22: istore 4
    //   24: iload_0
    //   25: iload_1
    //   26: iadd
    //   27: iload_2
    //   28: imul
    //   29: iload_3
    //   30: irem
    //   31: iload 4
    //   33: if_icmpeq +15 -> 48
    //   36: invokestatic 60	com/appdynamics/eumagent/runtime/e:b043104310431б04310431	()I
    //   39: putstatic 51	com/appdynamics/eumagent/runtime/e:bбб0431б04310431	I
    //   42: invokestatic 60	com/appdynamics/eumagent/runtime/e:b043104310431б04310431	()I
    //   45: putstatic 242	com/appdynamics/eumagent/runtime/e:b04310431б043104310431	I
    //   48: ldc_w 334
    //   51: sipush 133
    //   54: bipush 15
    //   56: iconst_0
    //   57: invokestatic 83	kkkkkk/gguuuu:bк043Aккк043Aкк043A043A	(Ljava/lang/String;CCC)Ljava/lang/String;
    //   60: astore 5
    //   62: new 336	java/io/RandomAccessFile
    //   65: dup
    //   66: ldc_w 338
    //   69: sipush 165
    //   72: iconst_5
    //   73: invokestatic 95	kkkkkk/gguuuu:bккккк043Aкк043A043A	(Ljava/lang/String;CC)Ljava/lang/String;
    //   76: ldc_w 340
    //   79: bipush 115
    //   81: iconst_3
    //   82: invokestatic 95	kkkkkk/gguuuu:bккккк043Aкк043A043A	(Ljava/lang/String;CC)Ljava/lang/String;
    //   85: invokespecial 343	java/io/RandomAccessFile:<init>	(Ljava/lang/String;Ljava/lang/String;)V
    //   88: astore 6
    //   90: aload 6
    //   92: invokevirtual 346	java/io/RandomAccessFile:readLine	()Ljava/lang/String;
    //   95: astore 7
    //   97: aload 7
    //   99: astore 5
    //   101: new 348	java/lang/StringBuilder
    //   104: dup
    //   105: invokespecial 349	java/lang/StringBuilder:<init>	()V
    //   108: astore 8
    //   110: iconst_0
    //   111: istore_0
    //   112: aload 7
    //   114: astore 5
    //   116: iload_0
    //   117: aload 7
    //   119: invokevirtual 352	java/lang/String:length	()I
    //   122: if_icmpge +96 -> 218
    //   125: aload 7
    //   127: astore 5
    //   129: aload 7
    //   131: iload_0
    //   132: invokevirtual 356	java/lang/String:charAt	(I)C
    //   135: invokestatic 361	java/lang/Character:valueOf	(C)Ljava/lang/Character;
    //   138: astore 9
    //   140: aload 7
    //   142: astore 5
    //   144: aload 9
    //   146: invokevirtual 365	java/lang/Character:charValue	()C
    //   149: invokestatic 369	java/lang/Character:isDigit	(C)Z
    //   152: ifeq +59 -> 211
    //   155: aload 7
    //   157: astore 5
    //   159: aload 8
    //   161: aload 9
    //   163: invokevirtual 373	java/lang/StringBuilder:append	(Ljava/lang/Object;)Ljava/lang/StringBuilder;
    //   166: pop
    //   167: getstatic 51	com/appdynamics/eumagent/runtime/e:bбб0431б04310431	I
    //   170: istore_1
    //   171: iload_1
    //   172: getstatic 53	com/appdynamics/eumagent/runtime/e:b0431б0431б04310431	I
    //   175: iload_1
    //   176: iadd
    //   177: imul
    //   178: getstatic 97	com/appdynamics/eumagent/runtime/e:b0431бб043104310431	I
    //   181: irem
    //   182: tableswitch	default:+18->200, 0:+29->211
    //   200: bipush 90
    //   202: putstatic 51	com/appdynamics/eumagent/runtime/e:bбб0431б04310431	I
    //   205: invokestatic 60	com/appdynamics/eumagent/runtime/e:b043104310431б04310431	()I
    //   208: putstatic 242	com/appdynamics/eumagent/runtime/e:b04310431б043104310431	I
    //   211: iload_0
    //   212: iconst_1
    //   213: iadd
    //   214: istore_0
    //   215: goto -103 -> 112
    //   218: aload 7
    //   220: astore 5
    //   222: aload 8
    //   224: invokevirtual 376	java/lang/StringBuilder:toString	()Ljava/lang/String;
    //   227: invokestatic 380	java/lang/Long:parseLong	(Ljava/lang/String;)J
    //   230: invokestatic 193	java/lang/Long:valueOf	(J)Ljava/lang/Long;
    //   233: invokevirtual 384	java/lang/Long:longValue	()J
    //   236: ldc2_w 385
    //   239: ldiv
    //   240: invokestatic 389	java/lang/Long:toString	(J)Ljava/lang/String;
    //   243: astore 7
    //   245: aload 6
    //   247: invokevirtual 392	java/io/RandomAccessFile:close	()V
    //   250: aload 7
    //   252: areturn
    //   253: astore 6
    //   255: aload 7
    //   257: astore 6
    //   259: aload 5
    //   261: astore 7
    //   263: aload 6
    //   265: ifnull -15 -> 250
    //   268: iconst_0
    //   269: tableswitch	default:+23->292, 0:+50->319, 1:+-1->268
    //   292: iconst_1
    //   293: tableswitch	default:+23->316, 0:+-25->268, 1:+26->319
    //   316: goto -24 -> 292
    //   319: aload 6
    //   321: invokevirtual 392	java/io/RandomAccessFile:close	()V
    //   324: aload 5
    //   326: areturn
    //   327: astore 6
    //   329: aload 5
    //   331: areturn
    //   332: astore 5
    //   334: aconst_null
    //   335: astore 6
    //   337: aload 6
    //   339: ifnull +8 -> 347
    //   342: aload 6
    //   344: invokevirtual 392	java/io/RandomAccessFile:close	()V
    //   347: aload 5
    //   349: athrow
    //   350: astore 5
    //   352: aload 5
    //   354: athrow
    //   355: astore 7
    //   357: goto -98 -> 259
    //   360: astore 5
    //   362: aload 7
    //   364: areturn
    //   365: astore 5
    //   367: aload 5
    //   369: athrow
    //   370: astore 6
    //   372: goto -25 -> 347
    //   375: astore 5
    //   377: goto -40 -> 337
    // Local variable table:
    //   start	length	slot	name	signature
    //   6	209	0	m	int
    //   10	168	1	n	int
    //   14	15	2	i1	int
    //   18	13	3	i2	int
    //   22	12	4	i3	int
    //   60	270	5	localObject1	Object
    //   332	16	5	localObject2	Object
    //   350	3	5	localException1	Exception
    //   360	1	5	localThrowable1	Throwable
    //   365	3	5	localException2	Exception
    //   375	1	5	localObject3	Object
    //   88	158	6	localRandomAccessFile	java.io.RandomAccessFile
    //   253	1	6	localThrowable2	Throwable
    //   257	63	6	localObject4	Object
    //   327	1	6	localThrowable3	Throwable
    //   335	8	6	localObject5	Object
    //   370	1	6	localThrowable4	Throwable
    //   1	261	7	localObject6	Object
    //   355	8	7	localThrowable5	Throwable
    //   108	115	8	localStringBuilder	StringBuilder
    //   138	24	9	localCharacter	Character
    // Exception table:
    //   from	to	target	type
    //   62	90	253	java/lang/Throwable
    //   319	324	327	java/lang/Throwable
    //   62	90	332	finally
    //   3	24	350	java/lang/Exception
    //   48	62	350	java/lang/Exception
    //   245	250	350	java/lang/Exception
    //   342	347	350	java/lang/Exception
    //   347	350	350	java/lang/Exception
    //   90	97	355	java/lang/Throwable
    //   101	110	355	java/lang/Throwable
    //   116	125	355	java/lang/Throwable
    //   129	140	355	java/lang/Throwable
    //   144	155	355	java/lang/Throwable
    //   159	167	355	java/lang/Throwable
    //   222	245	355	java/lang/Throwable
    //   245	250	360	java/lang/Throwable
    //   36	48	365	java/lang/Exception
    //   319	324	365	java/lang/Exception
    //   342	347	370	java/lang/Throwable
    //   90	97	375	finally
    //   101	110	375	finally
    //   116	125	375	finally
    //   129	140	375	finally
    //   144	155	375	finally
    //   159	167	375	finally
    //   222	245	375	finally
  }
  
  /* Error */
  private static String f()
  {
    // Byte code:
    //   0: ldc_w 394
    //   3: sipush 137
    //   6: bipush 124
    //   8: iconst_0
    //   9: invokestatic 83	kkkkkk/gguuuu:bк043Aккк043Aкк043A043A	(Ljava/lang/String;CCC)Ljava/lang/String;
    //   12: astore_3
    //   13: new 336	java/io/RandomAccessFile
    //   16: dup
    //   17: ldc_w 396
    //   20: sipush 177
    //   23: sipush 242
    //   26: iconst_2
    //   27: invokestatic 83	kkkkkk/gguuuu:bк043Aккк043Aкк043A043A	(Ljava/lang/String;CCC)Ljava/lang/String;
    //   30: ldc_w 398
    //   33: sipush 130
    //   36: iconst_4
    //   37: invokestatic 95	kkkkkk/gguuuu:bккккк043Aкк043A043A	(Ljava/lang/String;CC)Ljava/lang/String;
    //   40: invokespecial 343	java/io/RandomAccessFile:<init>	(Ljava/lang/String;Ljava/lang/String;)V
    //   43: astore_1
    //   44: aload_1
    //   45: invokevirtual 346	java/io/RandomAccessFile:readLine	()Ljava/lang/String;
    //   48: astore_2
    //   49: aload_1
    //   50: invokevirtual 392	java/io/RandomAccessFile:close	()V
    //   53: aload_2
    //   54: areturn
    //   55: astore_1
    //   56: aconst_null
    //   57: astore_1
    //   58: aload_3
    //   59: astore_2
    //   60: aload_1
    //   61: ifnull -8 -> 53
    //   64: aload_1
    //   65: invokevirtual 392	java/io/RandomAccessFile:close	()V
    //   68: aload_3
    //   69: areturn
    //   70: astore_1
    //   71: aload_3
    //   72: areturn
    //   73: aload_1
    //   74: ifnull +53 -> 127
    //   77: invokestatic 60	com/appdynamics/eumagent/runtime/e:b043104310431б04310431	()I
    //   80: istore_0
    //   81: iload_0
    //   82: getstatic 53	com/appdynamics/eumagent/runtime/e:b0431б0431б04310431	I
    //   85: iload_0
    //   86: iadd
    //   87: imul
    //   88: invokestatic 57	com/appdynamics/eumagent/runtime/e:bб04310431б04310431	()I
    //   91: irem
    //   92: tableswitch	default:+20->112, 0:+31->123
    //   112: invokestatic 60	com/appdynamics/eumagent/runtime/e:b043104310431б04310431	()I
    //   115: putstatic 51	com/appdynamics/eumagent/runtime/e:bбб0431б04310431	I
    //   118: bipush 32
    //   120: putstatic 242	com/appdynamics/eumagent/runtime/e:b04310431б043104310431	I
    //   123: aload_1
    //   124: invokevirtual 392	java/io/RandomAccessFile:close	()V
    //   127: aload_2
    //   128: athrow
    //   129: astore_2
    //   130: getstatic 51	com/appdynamics/eumagent/runtime/e:bбб0431б04310431	I
    //   133: istore_0
    //   134: iload_0
    //   135: getstatic 53	com/appdynamics/eumagent/runtime/e:b0431б0431б04310431	I
    //   138: iload_0
    //   139: iadd
    //   140: imul
    //   141: getstatic 97	com/appdynamics/eumagent/runtime/e:b0431бб043104310431	I
    //   144: irem
    //   145: tableswitch	default:+19->164, 0:+97->242
    //   164: bipush 71
    //   166: putstatic 51	com/appdynamics/eumagent/runtime/e:bбб0431б04310431	I
    //   169: invokestatic 60	com/appdynamics/eumagent/runtime/e:b043104310431б04310431	()I
    //   172: putstatic 242	com/appdynamics/eumagent/runtime/e:b04310431б043104310431	I
    //   175: aconst_null
    //   176: astore_1
    //   177: iconst_1
    //   178: tableswitch	default:+22->200, 0:+-1->177, 1:+-105->73
    //   200: iconst_0
    //   201: tableswitch	default:+23->224, 0:+-128->73, 1:+-24->177
    //   224: goto -24 -> 200
    //   227: astore_2
    //   228: goto -170 -> 58
    //   231: astore_2
    //   232: goto -55 -> 177
    //   235: astore_1
    //   236: aload_2
    //   237: areturn
    //   238: astore_1
    //   239: goto -112 -> 127
    //   242: aconst_null
    //   243: astore_1
    //   244: goto -67 -> 177
    // Local variable table:
    //   start	length	slot	name	signature
    //   80	61	0	m	int
    //   43	7	1	localRandomAccessFile	java.io.RandomAccessFile
    //   55	1	1	localThrowable1	Throwable
    //   57	8	1	localObject1	Object
    //   70	54	1	localThrowable2	Throwable
    //   176	1	1	localObject2	Object
    //   235	1	1	localThrowable3	Throwable
    //   238	1	1	localThrowable4	Throwable
    //   243	1	1	localObject3	Object
    //   48	80	2	str1	String
    //   129	1	2	localObject4	Object
    //   227	1	2	localThrowable5	Throwable
    //   231	6	2	str2	String
    //   12	60	3	str3	String
    // Exception table:
    //   from	to	target	type
    //   13	44	55	java/lang/Throwable
    //   64	68	70	java/lang/Throwable
    //   13	44	129	finally
    //   44	49	227	java/lang/Throwable
    //   44	49	231	finally
    //   49	53	235	java/lang/Throwable
    //   123	127	238	java/lang/Throwable
  }
  
  private int g()
  {
    switch (1)
    {
    case 0: 
    default: 
      for (;;)
      {
        switch (1)
        {
        }
      }
    }
    try
    {
      File localFile = new File(gguuuu.bккккк043Aкк043A043A("I\r\022\013Eyy\n{tu\003=\001\006~~nu6iuy2", 'ñ', '\003'));
      a localA;
      int m;
      int n;
      for (;;) {}
    }
    catch (Throwable localThrowable)
    {
      for (;;)
      {
        try
        {
          localA = new a();
          m = bбб0431б04310431;
          switch (m * (b0431б0431б04310431 + m) % b0431бб043104310431)
          {
          default: 
            bбб0431б04310431 = b043104310431б04310431();
            b04310431б043104310431 = b043104310431б04310431();
          }
          m = localFile.listFiles(localA).length;
          n = bбб0431б04310431;
          switch (n * (b0431б0431б04310431 + n) % b0431бб043104310431)
          {
          case 0: 
            bбб0431б04310431 = 87;
            b04310431б043104310431 = b043104310431б04310431();
            return m;
          }
        }
        catch (Exception localException2)
        {
          throw localException2;
        }
        localThrowable = localThrowable;
        m = -1;
      }
    }
    catch (Exception localException1)
    {
      throw localException1;
    }
  }
  
  /* Error */
  private String h()
  {
    // Byte code:
    //   0: aload_0
    //   1: getfield 218	com/appdynamics/eumagent/runtime/e:i	Z
    //   4: ifeq +160 -> 164
    //   7: ldc_w 411
    //   10: bipush 83
    //   12: iconst_1
    //   13: invokestatic 95	kkkkkk/gguuuu:bккккк043Aкк043A043A	(Ljava/lang/String;CC)Ljava/lang/String;
    //   16: astore 4
    //   18: getstatic 51	com/appdynamics/eumagent/runtime/e:bбб0431б04310431	I
    //   21: istore_1
    //   22: iload_1
    //   23: invokestatic 240	com/appdynamics/eumagent/runtime/e:bб0431б043104310431	()I
    //   26: iload_1
    //   27: iadd
    //   28: imul
    //   29: getstatic 97	com/appdynamics/eumagent/runtime/e:b0431бб043104310431	I
    //   32: irem
    //   33: tableswitch	default:+19->52, 0:+29->62
    //   52: bipush 73
    //   54: putstatic 51	com/appdynamics/eumagent/runtime/e:bбб0431б04310431	I
    //   57: bipush 20
    //   59: putstatic 242	com/appdynamics/eumagent/runtime/e:b04310431б043104310431	I
    //   62: aload 4
    //   64: areturn
    //   65: aload 4
    //   67: invokevirtual 416	android/net/NetworkInfo:getType	()I
    //   70: ifne +173 -> 243
    //   73: aload 4
    //   75: invokevirtual 419	android/net/NetworkInfo:getSubtype	()I
    //   78: istore_1
    //   79: getstatic 69	com/appdynamics/eumagent/runtime/e:k	Ljava/util/Map;
    //   82: iload_1
    //   83: invokestatic 75	java/lang/Integer:valueOf	(I)Ljava/lang/Integer;
    //   86: invokeinterface 422 2 0
    //   91: ifeq +152 -> 243
    //   94: getstatic 69	com/appdynamics/eumagent/runtime/e:k	Ljava/util/Map;
    //   97: iload_1
    //   98: invokestatic 75	java/lang/Integer:valueOf	(I)Ljava/lang/Integer;
    //   101: invokeinterface 426 2 0
    //   106: checkcast 289	java/lang/String
    //   109: astore 5
    //   111: getstatic 51	com/appdynamics/eumagent/runtime/e:bбб0431б04310431	I
    //   114: istore_1
    //   115: getstatic 53	com/appdynamics/eumagent/runtime/e:b0431б0431б04310431	I
    //   118: istore_2
    //   119: getstatic 51	com/appdynamics/eumagent/runtime/e:bбб0431б04310431	I
    //   122: istore_3
    //   123: aload 5
    //   125: astore 4
    //   127: iload_1
    //   128: iload_2
    //   129: iadd
    //   130: iload_3
    //   131: imul
    //   132: getstatic 97	com/appdynamics/eumagent/runtime/e:b0431бб043104310431	I
    //   135: irem
    //   136: getstatic 242	com/appdynamics/eumagent/runtime/e:b04310431б043104310431	I
    //   139: if_icmpeq -121 -> 18
    //   142: invokestatic 60	com/appdynamics/eumagent/runtime/e:b043104310431б04310431	()I
    //   145: putstatic 51	com/appdynamics/eumagent/runtime/e:bбб0431б04310431	I
    //   148: iconst_4
    //   149: putstatic 242	com/appdynamics/eumagent/runtime/e:b04310431б043104310431	I
    //   152: aload 5
    //   154: astore 4
    //   156: goto -138 -> 18
    //   159: astore 4
    //   161: aload 4
    //   163: athrow
    //   164: aload_0
    //   165: getfield 133	com/appdynamics/eumagent/runtime/e:b	Landroid/content/Context;
    //   168: ldc_w 428
    //   171: sipush 171
    //   174: iconst_5
    //   175: invokestatic 95	kkkkkk/gguuuu:bккккк043Aкк043A043A	(Ljava/lang/String;CC)Ljava/lang/String;
    //   178: invokevirtual 282	android/content/Context:getSystemService	(Ljava/lang/String;)Ljava/lang/Object;
    //   181: checkcast 430	android/net/ConnectivityManager
    //   184: invokevirtual 434	android/net/ConnectivityManager:getActiveNetworkInfo	()Landroid/net/NetworkInfo;
    //   187: astore 4
    //   189: aload 4
    //   191: ifnull +67 -> 258
    //   194: aload 4
    //   196: invokevirtual 437	android/net/NetworkInfo:isConnected	()Z
    //   199: ifeq +59 -> 258
    //   202: aload 4
    //   204: invokevirtual 416	android/net/NetworkInfo:getType	()I
    //   207: istore_1
    //   208: iload_1
    //   209: iconst_1
    //   210: if_icmpne -145 -> 65
    //   213: ldc_w 439
    //   216: bipush 85
    //   218: iconst_5
    //   219: invokestatic 95	kkkkkk/gguuuu:bккккк043Aкк043A043A	(Ljava/lang/String;CC)Ljava/lang/String;
    //   222: astore 4
    //   224: goto -206 -> 18
    //   227: astore 4
    //   229: ldc_w 441
    //   232: bipush 33
    //   234: iconst_0
    //   235: invokestatic 95	kkkkkk/gguuuu:bккккк043Aкк043A043A	(Ljava/lang/String;CC)Ljava/lang/String;
    //   238: aload 4
    //   240: invokestatic 303	com/appdynamics/eumagent/runtime/InstrumentationCallbacks:safeLog	(Ljava/lang/String;Ljava/lang/Throwable;)V
    //   243: ldc_w 443
    //   246: sipush 187
    //   249: iconst_4
    //   250: invokestatic 95	kkkkkk/gguuuu:bккккк043Aкк043A043A	(Ljava/lang/String;CC)Ljava/lang/String;
    //   253: astore 4
    //   255: goto -237 -> 18
    //   258: ldc_w 445
    //   261: bipush 121
    //   263: iconst_5
    //   264: invokestatic 95	kkkkkk/gguuuu:bккккк043Aкк043A043A	(Ljava/lang/String;CC)Ljava/lang/String;
    //   267: astore 4
    //   269: goto -251 -> 18
    //   272: astore 4
    //   274: aload_0
    //   275: iconst_1
    //   276: putfield 218	com/appdynamics/eumagent/runtime/e:i	Z
    //   279: goto -279 -> 0
    //   282: astore 4
    //   284: aload 4
    //   286: athrow
    //   287: astore 4
    //   289: aload 4
    //   291: athrow
    //   292: astore 4
    //   294: aload 4
    //   296: athrow
    // Local variable table:
    //   start	length	slot	name	signature
    //   0	297	0	this	e
    //   21	190	1	m	int
    //   118	12	2	n	int
    //   122	10	3	i1	int
    //   16	139	4	localObject1	Object
    //   159	3	4	localException1	Exception
    //   187	36	4	localObject2	Object
    //   227	12	4	localThrowable	Throwable
    //   253	15	4	str1	String
    //   272	1	4	localSecurityException	SecurityException
    //   282	3	4	localException2	Exception
    //   287	3	4	localException3	Exception
    //   292	3	4	localException4	Exception
    //   109	44	5	str2	String
    // Exception table:
    //   from	to	target	type
    //   127	152	159	java/lang/Exception
    //   284	287	159	java/lang/Exception
    //   289	292	159	java/lang/Exception
    //   65	111	227	java/lang/Throwable
    //   164	189	227	java/lang/Throwable
    //   194	208	227	java/lang/Throwable
    //   65	111	272	java/lang/SecurityException
    //   164	189	272	java/lang/SecurityException
    //   194	208	272	java/lang/SecurityException
    //   229	243	282	java/lang/Exception
    //   243	255	282	java/lang/Exception
    //   258	269	282	java/lang/Exception
    //   274	279	282	java/lang/Exception
    //   0	18	287	java/lang/Exception
    //   65	111	287	java/lang/Exception
    //   164	189	287	java/lang/Exception
    //   194	208	287	java/lang/Exception
    //   213	224	287	java/lang/Exception
    //   111	123	292	java/lang/Exception
  }
  
  /* Error */
  final com.appdynamics.eumagent.runtime.events.e a()
  {
    // Byte code:
    //   0: aload_0
    //   1: getfield 140	com/appdynamics/eumagent/runtime/e:d	Lcom/appdynamics/eumagent/runtime/e$b;
    //   4: getfield 448	com/appdynamics/eumagent/runtime/e$b:a	Z
    //   7: istore_2
    //   8: iload_2
    //   9: ifne +7 -> 16
    //   12: aload_0
    //   13: invokespecial 276	com/appdynamics/eumagent/runtime/e:d	()V
    //   16: getstatic 51	com/appdynamics/eumagent/runtime/e:bбб0431б04310431	I
    //   19: getstatic 53	com/appdynamics/eumagent/runtime/e:b0431б0431б04310431	I
    //   22: iadd
    //   23: getstatic 51	com/appdynamics/eumagent/runtime/e:bбб0431б04310431	I
    //   26: imul
    //   27: getstatic 97	com/appdynamics/eumagent/runtime/e:b0431бб043104310431	I
    //   30: irem
    //   31: getstatic 242	com/appdynamics/eumagent/runtime/e:b04310431б043104310431	I
    //   34: if_icmpeq +61 -> 95
    //   37: bipush 47
    //   39: putstatic 51	com/appdynamics/eumagent/runtime/e:bбб0431б04310431	I
    //   42: invokestatic 60	com/appdynamics/eumagent/runtime/e:b043104310431б04310431	()I
    //   45: istore_1
    //   46: iload_1
    //   47: putstatic 242	com/appdynamics/eumagent/runtime/e:b04310431б043104310431	I
    //   50: getstatic 51	com/appdynamics/eumagent/runtime/e:bбб0431б04310431	I
    //   53: istore_1
    //   54: iload_1
    //   55: getstatic 53	com/appdynamics/eumagent/runtime/e:b0431б0431б04310431	I
    //   58: iload_1
    //   59: iadd
    //   60: imul
    //   61: getstatic 97	com/appdynamics/eumagent/runtime/e:b0431бб043104310431	I
    //   64: irem
    //   65: tableswitch	default:+19->84, 0:+30->95
    //   84: invokestatic 60	com/appdynamics/eumagent/runtime/e:b043104310431б04310431	()I
    //   87: putstatic 51	com/appdynamics/eumagent/runtime/e:bбб0431б04310431	I
    //   90: bipush 56
    //   92: putstatic 242	com/appdynamics/eumagent/runtime/e:b04310431б043104310431	I
    //   95: aload_0
    //   96: getfield 131	com/appdynamics/eumagent/runtime/e:j	Lcom/appdynamics/eumagent/runtime/events/e;
    //   99: astore_3
    //   100: aload_3
    //   101: areturn
    //   102: astore_3
    //   103: ldc_w 450
    //   106: bipush 49
    //   108: bipush 20
    //   110: iconst_3
    //   111: invokestatic 83	kkkkkk/gguuuu:bк043Aккк043Aкк043A043A	(Ljava/lang/String;CCC)Ljava/lang/String;
    //   114: astore 4
    //   116: aload 4
    //   118: aload_3
    //   119: invokestatic 452	com/appdynamics/eumagent/runtime/util/c:a	(Ljava/lang/String;Ljava/lang/Throwable;)V
    //   122: goto -106 -> 16
    //   125: astore_3
    //   126: aload_3
    //   127: athrow
    //   128: astore_3
    //   129: aload_3
    //   130: athrow
    // Local variable table:
    //   start	length	slot	name	signature
    //   0	131	0	this	e
    //   45	16	1	m	int
    //   7	2	2	bool	boolean
    //   99	2	3	localE	com.appdynamics.eumagent.runtime.events.e
    //   102	17	3	localThrowable	Throwable
    //   125	2	3	localException1	Exception
    //   128	2	3	localException2	Exception
    //   114	3	4	str	String
    // Exception table:
    //   from	to	target	type
    //   12	16	102	java/lang/Throwable
    //   46	50	125	java/lang/Exception
    //   95	100	125	java/lang/Exception
    //   116	122	125	java/lang/Exception
    //   0	8	128	java/lang/Exception
    //   12	16	128	java/lang/Exception
    //   16	46	128	java/lang/Exception
    //   103	116	128	java/lang/Exception
  }
  
  final void a(CollectorChannel paramCollectorChannel)
  {
    paramCollectorChannel.addRequestProperty(gguuuu.bккккк043Aкк043A043A("'4", 'D', '\005'), this.g);
    paramCollectorChannel.addRequestProperty(gguuuu.bккккк043Aкк043A043A("\001\r", '`', '\005'), this.h);
    paramCollectorChannel.addRequestProperty(gguuuu.bк043Aккк043Aкк043A043A("chd", 'J', 'V', '\001'), gguuuu.bк043Aккк043Aкк043A043A("Esjywrn", '', '', '\003'));
    paramCollectorChannel.addRequestProperty(gguuuu.bккккк043Aкк043A043A("tzt", 'õ', '\003'), this.f);
    if ((bбб0431б04310431 + b0431б0431б04310431) * bбб0431б04310431 % b0431бб043104310431 != b04310431б043104310431)
    {
      bбб0431б04310431 = b043104310431б04310431();
      b04310431б043104310431 = b043104310431б04310431();
    }
    int m = bбб0431б04310431;
    switch (m * (b0431б0431б04310431 + m) % b0431бб043104310431)
    {
    default: 
      bбб0431б04310431 = b043104310431б04310431();
      b04310431б043104310431 = b043104310431б04310431();
    }
    paramCollectorChannel.addRequestProperty(gguuuu.bккккк043Aкк043A043A("KJZ", 'ò', '\004'), gguuuu.bккккк043Aкк043A043A("h0(", 'ó', '\000'));
  }
  
  public final void a(Object paramObject)
  {
    if ((paramObject instanceof s))
    {
      Object localObject = (s)paramObject;
      paramObject = this.j;
      localObject = ((s)localObject).a;
      paramObject = paramObject.a(paramObject.m, paramObject.n, (Map)localObject);
      switch (1)
      {
      case 0: 
      default: 
        for (;;)
        {
          switch (0)
          {
          }
        }
      }
      this.j = paramObject;
    }
    do
    {
      do
      {
        return;
      } while (!(paramObject instanceof r));
      paramObject = (r)paramObject;
      if (gguuuu.bк043Aккк043Aкк043A043A("Fts\"Tt`pq", '¦', 'Ò', '\002').equals(paramObject.g))
      {
        paramObject = this.d;
        if ((bбб0431б04310431 + b0431б0431б04310431) * bбб0431б04310431 % b0431бб043104310431 != bббб043104310431())
        {
          bбб0431б04310431 = 44;
          b04310431б043104310431 = 57;
        }
        try
        {
          paramObject.b.b.registerReceiver(paramObject, new IntentFilter(gguuuu.bккккк043Aкк043A043A("\005\023\n\031\027\022\016X\032\022\"\\\023  !aw\005\005\006}|\017\005\023\007\023\031 \005\013\005\023\r\f", 'µ', '\001')));
          int m = bбб0431б04310431;
          switch (m * (b0431б0431б04310431 + m) % b0431бб043104310431)
          {
          default: 
            bбб0431б04310431 = 6;
            b04310431б043104310431 = b043104310431б04310431();
          }
          paramObject.a = true;
          return;
        }
        catch (Throwable paramObject)
        {
          InstrumentationCallbacks.safeLog(gguuuu.bк043Aккк043Aкк043A043A("M{|z~-\001twz\006\by\b\0069]\013\013\f\004\003\025\013\022\022p\017\032\034\016\030\020\036", '*', '¡', '\001'), paramObject);
          return;
        }
      }
    } while (!gguuuu.bккккк043Aкк043A043A("w()Y\0160,.", '6', '\000').equals(paramObject.g));
    paramObject = this.d;
    paramObject.b.b.unregisterReceiver(paramObject);
    paramObject.a = false;
  }
  
  /* Error */
  public final void a(String paramString)
  {
    // Byte code:
    //   0: invokestatic 60	com/appdynamics/eumagent/runtime/e:b043104310431б04310431	()I
    //   3: getstatic 53	com/appdynamics/eumagent/runtime/e:b0431б0431б04310431	I
    //   6: iadd
    //   7: invokestatic 60	com/appdynamics/eumagent/runtime/e:b043104310431б04310431	()I
    //   10: imul
    //   11: getstatic 97	com/appdynamics/eumagent/runtime/e:b0431бб043104310431	I
    //   14: irem
    //   15: getstatic 242	com/appdynamics/eumagent/runtime/e:b04310431б043104310431	I
    //   18: if_icmpeq +13 -> 31
    //   21: bipush 18
    //   23: putstatic 51	com/appdynamics/eumagent/runtime/e:bбб0431б04310431	I
    //   26: bipush 49
    //   28: putstatic 242	com/appdynamics/eumagent/runtime/e:b04310431б043104310431	I
    //   31: iconst_1
    //   32: tableswitch	default:+24->56, 0:+-32->0, 1:+51->83
    //   56: iconst_0
    //   57: tableswitch	default:+23->80, 0:+26->83, 1:+-57->0
    //   80: goto -24 -> 56
    //   83: getstatic 51	com/appdynamics/eumagent/runtime/e:bбб0431б04310431	I
    //   86: istore_2
    //   87: getstatic 53	com/appdynamics/eumagent/runtime/e:b0431б0431б04310431	I
    //   90: istore_3
    //   91: getstatic 51	com/appdynamics/eumagent/runtime/e:bбб0431б04310431	I
    //   94: istore 4
    //   96: getstatic 97	com/appdynamics/eumagent/runtime/e:b0431бб043104310431	I
    //   99: istore 5
    //   101: invokestatic 100	com/appdynamics/eumagent/runtime/e:bббб043104310431	()I
    //   104: istore 6
    //   106: iload_2
    //   107: iload_3
    //   108: iadd
    //   109: iload 4
    //   111: imul
    //   112: iload 5
    //   114: irem
    //   115: iload 6
    //   117: if_icmpeq +14 -> 131
    //   120: bipush 66
    //   122: putstatic 51	com/appdynamics/eumagent/runtime/e:bбб0431б04310431	I
    //   125: invokestatic 60	com/appdynamics/eumagent/runtime/e:b043104310431б04310431	()I
    //   128: putstatic 242	com/appdynamics/eumagent/runtime/e:b04310431б043104310431	I
    //   131: aload_0
    //   132: aload_1
    //   133: putfield 220	com/appdynamics/eumagent/runtime/e:g	Ljava/lang/String;
    //   136: return
    //   137: astore_1
    //   138: aload_1
    //   139: athrow
    //   140: astore_1
    //   141: aload_1
    //   142: athrow
    // Local variable table:
    //   start	length	slot	name	signature
    //   0	143	0	this	e
    //   0	143	1	paramString	String
    //   86	23	2	m	int
    //   90	19	3	n	int
    //   94	18	4	i1	int
    //   99	16	5	i2	int
    //   104	14	6	i3	int
    // Exception table:
    //   from	to	target	type
    //   96	106	137	java/lang/Exception
    //   131	136	137	java/lang/Exception
    //   83	96	140	java/lang/Exception
    //   120	131	140	java/lang/Exception
  }
  
  /* Error */
  final String b()
  {
    // Byte code:
    //   0: getstatic 51	com/appdynamics/eumagent/runtime/e:bбб0431б04310431	I
    //   3: istore_1
    //   4: invokestatic 240	com/appdynamics/eumagent/runtime/e:bб0431б043104310431	()I
    //   7: istore_2
    //   8: getstatic 51	com/appdynamics/eumagent/runtime/e:bбб0431б04310431	I
    //   11: istore_3
    //   12: getstatic 97	com/appdynamics/eumagent/runtime/e:b0431бб043104310431	I
    //   15: istore 4
    //   17: iload_1
    //   18: iload_2
    //   19: iadd
    //   20: iload_3
    //   21: imul
    //   22: iload 4
    //   24: irem
    //   25: getstatic 242	com/appdynamics/eumagent/runtime/e:b04310431б043104310431	I
    //   28: if_icmpeq +55 -> 83
    //   31: bipush 13
    //   33: putstatic 51	com/appdynamics/eumagent/runtime/e:bбб0431б04310431	I
    //   36: iconst_3
    //   37: putstatic 242	com/appdynamics/eumagent/runtime/e:b04310431б043104310431	I
    //   40: getstatic 51	com/appdynamics/eumagent/runtime/e:bбб0431б04310431	I
    //   43: istore_1
    //   44: iload_1
    //   45: getstatic 53	com/appdynamics/eumagent/runtime/e:b0431б0431б04310431	I
    //   48: iload_1
    //   49: iadd
    //   50: imul
    //   51: getstatic 97	com/appdynamics/eumagent/runtime/e:b0431бб043104310431	I
    //   54: irem
    //   55: tableswitch	default:+17->72, 0:+28->83
    //   72: bipush 42
    //   74: putstatic 51	com/appdynamics/eumagent/runtime/e:bбб0431б04310431	I
    //   77: invokestatic 60	com/appdynamics/eumagent/runtime/e:b043104310431б04310431	()I
    //   80: putstatic 242	com/appdynamics/eumagent/runtime/e:b04310431б043104310431	I
    //   83: aload_0
    //   84: getfield 147	com/appdynamics/eumagent/runtime/e:e	Ljava/lang/String;
    //   87: astore 5
    //   89: aload 5
    //   91: areturn
    //   92: astore 5
    //   94: aload 5
    //   96: athrow
    //   97: astore 5
    //   99: aload 5
    //   101: athrow
    //   102: astore 5
    //   104: aload 5
    //   106: athrow
    // Local variable table:
    //   start	length	slot	name	signature
    //   0	107	0	this	e
    //   3	48	1	m	int
    //   7	13	2	n	int
    //   11	11	3	i1	int
    //   15	10	4	i2	int
    //   87	3	5	str	String
    //   92	3	5	localException1	Exception
    //   97	3	5	localException2	Exception
    //   102	3	5	localException3	Exception
    // Exception table:
    //   from	to	target	type
    //   83	89	92	java/lang/Exception
    //   0	17	97	java/lang/Exception
    //   94	97	97	java/lang/Exception
    //   17	40	102	java/lang/Exception
  }
  
  /* Error */
  public final void b(String paramString)
  {
    // Byte code:
    //   0: aload_1
    //   1: invokestatic 501	com/appdynamics/eumagent/runtime/util/c:c	(Ljava/lang/String;)Z
    //   4: ifeq +163 -> 167
    //   7: new 503	java/lang/IllegalArgumentException
    //   10: dup
    //   11: ldc_w 505
    //   14: sipush 184
    //   17: iconst_1
    //   18: invokestatic 95	kkkkkk/gguuuu:bккккк043Aкк043A043A	(Ljava/lang/String;CC)Ljava/lang/String;
    //   21: invokespecial 506	java/lang/IllegalArgumentException:<init>	(Ljava/lang/String;)V
    //   24: athrow
    //   25: astore_1
    //   26: aload_1
    //   27: athrow
    //   28: astore_1
    //   29: aload_1
    //   30: athrow
    //   31: iload_2
    //   32: getstatic 53	com/appdynamics/eumagent/runtime/e:b0431б0431б04310431	I
    //   35: iadd
    //   36: getstatic 51	com/appdynamics/eumagent/runtime/e:bбб0431б04310431	I
    //   39: imul
    //   40: getstatic 97	com/appdynamics/eumagent/runtime/e:b0431бб043104310431	I
    //   43: irem
    //   44: getstatic 242	com/appdynamics/eumagent/runtime/e:b04310431б043104310431	I
    //   47: if_icmpeq +60 -> 107
    //   50: invokestatic 60	com/appdynamics/eumagent/runtime/e:b043104310431б04310431	()I
    //   53: istore_2
    //   54: iload_2
    //   55: invokestatic 240	com/appdynamics/eumagent/runtime/e:bб0431б043104310431	()I
    //   58: iload_2
    //   59: iadd
    //   60: imul
    //   61: getstatic 97	com/appdynamics/eumagent/runtime/e:b0431бб043104310431	I
    //   64: irem
    //   65: tableswitch	default:+19->84, 0:+31->96
    //   84: invokestatic 60	com/appdynamics/eumagent/runtime/e:b043104310431б04310431	()I
    //   87: putstatic 51	com/appdynamics/eumagent/runtime/e:bбб0431б04310431	I
    //   90: invokestatic 60	com/appdynamics/eumagent/runtime/e:b043104310431б04310431	()I
    //   93: putstatic 242	com/appdynamics/eumagent/runtime/e:b04310431б043104310431	I
    //   96: invokestatic 60	com/appdynamics/eumagent/runtime/e:b043104310431б04310431	()I
    //   99: putstatic 51	com/appdynamics/eumagent/runtime/e:bбб0431б04310431	I
    //   102: bipush 71
    //   104: putstatic 242	com/appdynamics/eumagent/runtime/e:b04310431б043104310431	I
    //   107: aload_0
    //   108: aload_1
    //   109: putfield 227	com/appdynamics/eumagent/runtime/e:h	Ljava/lang/String;
    //   112: return
    //   113: getstatic 51	com/appdynamics/eumagent/runtime/e:bбб0431б04310431	I
    //   116: istore_2
    //   117: iconst_0
    //   118: tableswitch	default:+22->140, 0:+-87->31, 1:+-1->117
    //   140: iconst_0
    //   141: tableswitch	default:+23->164, 0:+-110->31, 1:+-24->117
    //   164: goto -24 -> 140
    //   167: aload_1
    //   168: invokestatic 508	com/appdynamics/eumagent/runtime/util/c:d	(Ljava/lang/String;)Z
    //   171: istore_3
    //   172: iload_3
    //   173: ifne -60 -> 113
    //   176: new 503	java/lang/IllegalArgumentException
    //   179: dup
    //   180: ldc_w 510
    //   183: sipush 228
    //   186: sipush 245
    //   189: iconst_1
    //   190: invokestatic 83	kkkkkk/gguuuu:bк043Aккк043Aкк043A043A	(Ljava/lang/String;CCC)Ljava/lang/String;
    //   193: invokespecial 506	java/lang/IllegalArgumentException:<init>	(Ljava/lang/String;)V
    //   196: athrow
    // Local variable table:
    //   start	length	slot	name	signature
    //   0	197	0	this	e
    //   0	197	1	paramString	String
    //   31	86	2	m	int
    //   171	2	3	bool	boolean
    // Exception table:
    //   from	to	target	type
    //   0	25	25	java/lang/Exception
    //   167	172	25	java/lang/Exception
    //   107	112	28	java/lang/Exception
    //   176	197	28	java/lang/Exception
  }
  
  public final String c()
  {
    return this.g;
  }
  
  final class a
    implements FileFilter
  {
    public static int b043A043Aкккк = 0;
    public static int b043Aккккк = 2;
    public static int bб04310431043104310431 = 1;
    public static int bбб0431043104310431 = 24;
    
    a() {}
    
    public static int b0431б0431043104310431()
    {
      return 0;
    }
    
    public static int bк043Aкккк()
    {
      return 21;
    }
    
    public final boolean accept(File paramFile)
    {
      String str = gguuuu.bккккк043Aкк043A043A("\025#)\020ecp\026d", '1', '\000');
      if ((bбб0431043104310431 + bб04310431043104310431) * bбб0431043104310431 % b043Aккккк != b0431б0431043104310431())
      {
        bбб0431043104310431 = 88;
        bб04310431043104310431 = bк043Aкккк();
      }
      if ((bбб0431043104310431 + bб04310431043104310431) * bбб0431043104310431 % b043Aккккк != b043A043Aкккк)
      {
        bбб0431043104310431 = 96;
        b043A043Aкккк = 29;
      }
      switch (0)
      {
      case 1: 
      default: 
        for (;;)
        {
          switch (1)
          {
          case 0: 
          default: 
            for (;;)
            {
              switch (0)
              {
              }
            }
          }
          switch (0)
          {
          }
        }
      }
      return Pattern.matches(str, paramFile.getName());
    }
  }
  
  final class b
    extends BroadcastReceiver
  {
    public static int b043Aк043Aккк = 1;
    public static int b043Aкк043Aкк = 2;
    public static int bкк043Aккк = 61;
    public static int bккк043Aкк;
    boolean a = false;
    
    private b() {}
    
    public static int b043A043A043Aккк()
    {
      return 50;
    }
    
    public static int bк043A043Aккк()
    {
      return 2;
    }
    
    /* Error */
    public final void onReceive(Context paramContext, android.content.Intent paramIntent)
    {
      // Byte code:
      //   0: aload_1
      //   1: invokestatic 48	kkkkkk/nkkkkk:bЗЗ0417З0417З0417041704170417	(Landroid/content/Context;)V
      //   4: aload_1
      //   5: invokestatic 53	kkkkkk/nnnkkk:bхх0445ххххххх	(Landroid/content/Context;)V
      //   8: aload_1
      //   9: invokestatic 58	kkkkkk/nknnkk:bх0445ххх04450445ххх	(Landroid/content/Context;)V
      //   12: aload_0
      //   13: getfield 24	com/appdynamics/eumagent/runtime/e$b:b	Lcom/appdynamics/eumagent/runtime/e;
      //   16: invokestatic 61	com/appdynamics/eumagent/runtime/e:a	(Lcom/appdynamics/eumagent/runtime/e;)Lcom/appdynamics/eumagent/runtime/events/l;
      //   19: astore_1
      //   20: getstatic 63	com/appdynamics/eumagent/runtime/e$b:bкк043Aккк	I
      //   23: istore_3
      //   24: iload_3
      //   25: getstatic 65	com/appdynamics/eumagent/runtime/e$b:b043Aк043Aккк	I
      //   28: iload_3
      //   29: iadd
      //   30: imul
      //   31: invokestatic 67	com/appdynamics/eumagent/runtime/e$b:bк043A043Aккк	()I
      //   34: irem
      //   35: tableswitch	default:+17->52, 0:+28->63
      //   52: bipush 64
      //   54: putstatic 63	com/appdynamics/eumagent/runtime/e$b:bкк043Aккк	I
      //   57: invokestatic 69	com/appdynamics/eumagent/runtime/e$b:b043A043A043Aккк	()I
      //   60: putstatic 65	com/appdynamics/eumagent/runtime/e$b:b043Aк043Aккк	I
      //   63: aload_1
      //   64: new 9	com/appdynamics/eumagent/runtime/e$b$a
      //   67: dup
      //   68: aload_0
      //   69: iconst_0
      //   70: invokespecial 72	com/appdynamics/eumagent/runtime/e$b$a:<init>	(Lcom/appdynamics/eumagent/runtime/e$b;B)V
      //   73: ldc2_w 73
      //   76: invokevirtual 79	com/appdynamics/eumagent/runtime/events/l:a	(Ljava/lang/Runnable;J)V
      //   79: return
      //   80: astore_1
      //   81: ldc 81
      //   83: sipush 225
      //   86: iconst_5
      //   87: invokestatic 87	kkkkkk/gguuuu:bккккк043Aкк043A043A	(Ljava/lang/String;CC)Ljava/lang/String;
      //   90: aload_1
      //   91: invokestatic 93	com/appdynamics/eumagent/runtime/InstrumentationCallbacks:safeLog	(Ljava/lang/String;Ljava/lang/Throwable;)V
      //   94: return
      //   95: astore_1
      //   96: aload_1
      //   97: athrow
      //   98: astore_1
      //   99: aload_1
      //   100: athrow
      // Local variable table:
      //   start	length	slot	name	signature
      //   0	101	0	this	b
      //   0	101	1	paramContext	Context
      //   0	101	2	paramIntent	android.content.Intent
      //   23	8	3	i	int
      // Exception table:
      //   from	to	target	type
      //   12	20	80	java/lang/Throwable
      //   63	79	80	java/lang/Throwable
      //   81	94	95	java/lang/Exception
      //   0	12	98	java/lang/Exception
      //   12	20	98	java/lang/Exception
      //   63	79	98	java/lang/Exception
    }
    
    final class a
      implements Runnable
    {
      public static int b043Aк043A043Aкк = 1;
      public static int bк043Aк043Aкк = 52;
      public static int bкк043A043Aкк = 2;
      
      private a() {}
      
      public static int b043A043Aк043Aкк()
      {
        return 1;
      }
      
      public static int bк043A043A043Aкк()
      {
        return 87;
      }
      
      public final void run()
      {
        try
        {
          e.b(e.this);
          int i = bк043Aк043Aкк;
          switch (i * (b043A043Aк043Aкк() + i) % bкк043A043Aкк)
          {
          default: 
            bк043Aк043Aкк = 29;
            switch (1)
            {
            case 0: 
            default: 
              for (;;)
              {
                switch (1)
                {
                }
              }
            }
            bкк043A043Aкк = 28;
            i = bк043Aк043Aкк;
            switch (i * (b043Aк043A043Aкк + i) % bкк043A043Aкк)
            {
            default: 
              bк043Aк043Aкк = bк043A043A043Aкк();
              b043Aк043A043Aкк = bк043A043A043Aкк();
            }
            break;
          }
          return;
        }
        catch (Exception localException)
        {
          throw localException;
        }
      }
    }
  }
}
