package uuuuuu;

import android.content.Context;
import android.graphics.Bitmap;
import android.support.annotation.NonNull;
import android.support.annotation.Nullable;
import android.util.SparseArray;
import android.util.SparseBooleanArray;
import com.bumptech.glide.BitmapRequestBuilder;
import com.bumptech.glide.BitmapTypeRequest;
import com.bumptech.glide.DrawableTypeRequest;
import com.bumptech.glide.Glide;
import com.bumptech.glide.RequestManager;
import com.bumptech.glide.load.engine.DiskCacheStrategy;
import com.db.pwcc.dbmobile.foundation.utils.LocaleChangeReceiver;
import com.db.pwcc.dbmobile.model.error.DbError;
import com.db.pwcc.dbmobile.secure.preferences.SharedPreferencesHelper;
import com.db.pwcc.dbmobile.treatments.model.Treatment;
import com.db.pwcc.dbmobile.treatments.model.TreatmentCache;
import com.db.pwcc.dbmobile.treatments.model.TreatmentCategory;
import java.io.File;
import java.lang.reflect.InvocationTargetException;
import java.lang.reflect.Method;
import java.util.Locale;
import javax.inject.Inject;
import rx.Observable;
import rx.android.schedulers.AndroidSchedulers;
import rx.schedulers.Schedulers;
import xxxxxx.uxxxxx;

public class gaaaga
  implements gaagaa.aaagaa
{
  public static int b00790079y0079y0079y0079y = 2;
  private static final long b0079y007900790079yy0079y = 900000L;
  public static int b0079yy0079y0079y0079y = 15;
  private static final long by0079007900790079yy0079y = 86400000L;
  public static int by0079y0079y0079y0079y = 1;
  public static int byy00790079y0079y0079y;
  @Inject
  public ggyggy b00790079007900790079yy0079y;
  public SparseArray<Long> b007900790079yy0079y0079y;
  private final gaagaa b00790079yyy0079y0079y;
  public LocaleChangeReceiver b0079y0079yy0079y0079y;
  private final Context b0079yyyy0079y0079y;
  @Inject
  public SharedPreferencesHelper by00790079yy0079y0079y;
  public SparseBooleanArray by0079yyy0079y0079y;
  public SparseBooleanArray byy0079yy0079y0079y;
  public SparseArray<aaggaa> byyy0079y0079y0079y;
  public ggaaga byyyyy0079y0079y;
  
  public gaaaga(@NonNull Context paramContext)
  {
    this.b0079yyyy0079y0079y = paramContext;
    gaagga.b007700770077www0077www(paramContext).bpp00700070p0070pppp(this);
    this.b0079y0079yy0079y0079y = new LocaleChangeReceiver(new gaaaga.4(this));
    this.b0079y0079yy0079y0079y.registerReceiver(paramContext);
    this.b00790079yyy0079y0079y = new gggaaa();
    this.byyyyy0079y0079y = new agaaga(paramContext);
    this.b007900790079yy0079y0079y = new SparseArray();
    this.byy0079yy0079y0079y = new SparseBooleanArray();
    this.byyy0079y0079y0079y = new SparseArray();
    this.by0079yyy0079y0079y = new SparseBooleanArray();
  }
  
  private boolean b0077007700770077www0077ww()
  {
    int i = b0079yy0079y0079y0079y;
    switch (i * (i + by0079y0079y0079y0079y) % b00790079y0079y0079y0079y)
    {
    default: 
      b0079yy0079y0079y0079y = b00770077w0077007700770077www();
      byy00790079y0079y0079y = 58;
    }
    TreatmentCategory localTreatmentCategory = b0077w0077wwww0077ww(1).getCategory();
    if ((b0079yy0079y0079y0079y + b0077ww0077007700770077www()) * b0079yy0079y0079y0079y % bwww0077007700770077www() != byy00790079y0079y0079y)
    {
      b0079yy0079y0079y0079y = b00770077w0077007700770077www();
      byy00790079y0079y0079y = b00770077w0077007700770077www();
    }
    return localTreatmentCategory == TreatmentCategory.INFORMATION;
  }
  
  private String b007700770077wwww0077ww()
  {
    if ((b00770077w0077007700770077www() + by0079y0079y0079y0079y) * b00770077w0077007700770077www() % b00790079y0079y0079y0079y != byy00790079y0079y0079y)
    {
      b0079yy0079y0079y0079y = 86;
      byy00790079y0079y0079y = b00770077w0077007700770077www();
    }
    String str = Locale.getDefault().getLanguage();
    if ((b0079yy0079y0079y0079y + by0079y0079y0079y0079y) * b0079yy0079y0079y0079y % b00790079y0079y0079y0079y != byy00790079y0079y0079y)
    {
      b0079yy0079y0079y0079y = b00770077w0077007700770077www();
      byy00790079y0079y0079y = b00770077w0077007700770077www();
    }
    if (!str.equals(Locale.GERMAN.getLanguage())) {
      str = Locale.ENGLISH.getLanguage();
    }
    return str;
  }
  
  public static int b00770077w0077007700770077www()
  {
    return 80;
  }
  
  private void b00770077w00770077ww0077ww(int paramInt)
  {
    SharedPreferencesHelper localSharedPreferencesHelper2;
    Method localMethod2;
    Object[] arrayOfObject2;
    if (paramInt == 1)
    {
      localSharedPreferencesHelper2 = this.by00790079yy0079y0079y;
      long l2 = System.currentTimeMillis();
      String str2 = uxxxxx.bb00620062bb0062b0062b0062("\035\020 r#\033\034$\025%\031\032$\013*\036\033/)\",3\f\"57\007-+*3\035381", '8', '\000');
      Class[] arrayOfClass2 = new Class[1];
      arrayOfClass2[0] = Long.TYPE;
      localMethod2 = SharedPreferencesHelper.class.getMethod(str2, arrayOfClass2);
      arrayOfObject2 = new Object[1];
      arrayOfObject2[0] = Long.valueOf(l2);
    }
    for (;;)
    {
      try
      {
        localMethod2.invoke(localSharedPreferencesHelper2, arrayOfObject2);
        this.by0079yyy0079y0079y.put(paramInt, false);
        int i = b0079yy0079y0079y0079y;
        switch (i * (i + b0077ww0077007700770077www()) % b00790079y0079y0079y0079y)
        {
        default: 
          int j = b0079yy0079y0079y0079y;
          switch (j * (j + by0079y0079y0079y0079y) % b00790079y0079y0079y0079y)
          {
          default: 
            b0079yy0079y0079y0079y = 41;
            byy00790079y0079y0079y = 99;
          }
          b0079yy0079y0079y0079y = 78;
          byy00790079y0079y0079y = b00770077w0077007700770077www();
        }
        return;
      }
      catch (InvocationTargetException localInvocationTargetException2)
      {
        throw localInvocationTargetException2.getCause();
      }
      SharedPreferencesHelper localSharedPreferencesHelper1 = this.by00790079yy0079y0079y;
      long l1 = System.currentTimeMillis();
      String str1 = uxxxxx.bbbb0062b0062b0062b0062("eXhI_c]E_qaiRqebvpiszzTj}Ousr{e{\001y", 'F', 'Ó', '\002');
      Class[] arrayOfClass1 = new Class[2];
      arrayOfClass1[0] = Integer.TYPE;
      arrayOfClass1[1] = Long.TYPE;
      Method localMethod1 = SharedPreferencesHelper.class.getMethod(str1, arrayOfClass1);
      Object[] arrayOfObject1 = new Object[2];
      arrayOfObject1[0] = Integer.valueOf(paramInt);
      arrayOfObject1[1] = Long.valueOf(l1);
      try
      {
        localMethod1.invoke(localSharedPreferencesHelper1, arrayOfObject1);
      }
      catch (InvocationTargetException localInvocationTargetException1)
      {
        throw localInvocationTargetException1.getCause();
      }
    }
  }
  
  private boolean b00770077w0077www0077ww(int paramInt)
  {
    if ((b0077w0077wwww0077ww(paramInt).getCategory() == TreatmentCategory.INFORMATION) && (!this.byyyyy0079y0079y.bww007700770077w0077www(paramInt))) {}
    for (boolean bool = true;; bool = false)
    {
      if ((b0079yy0079y0079y0079y + by0079y0079y0079y0079y) * b0079yy0079y0079y0079y % b00790079y0079y0079y0079y != bw0077w0077007700770077www())
      {
        b0079yy0079y0079y0079y = b00770077w0077007700770077www();
        byy00790079y0079y0079y = 76;
        int i = b0079yy0079y0079y0079y;
        switch (i * (i + by0079y0079y0079y0079y) % b00790079y0079y0079y0079y)
        {
        default: 
          b0079yy0079y0079y0079y = 73;
          byy00790079y0079y0079y = 70;
        }
      }
      return bool;
    }
  }
  
  private void b0077w00770077007700770077www(int paramInt, @Nullable String paramString)
  {
    if (paramString == null) {
      return;
    }
    BitmapRequestBuilder localBitmapRequestBuilder = Glide.with(this.b0079yyyy0079y0079y).load(paramString).asBitmap().skipMemoryCache(true).diskCacheStrategy(DiskCacheStrategy.NONE);
    if ((b0079yy0079y0079y0079y + by0079y0079y0079y0079y) * b0079yy0079y0079y0079y % b00790079y0079y0079y0079y != byy00790079y0079y0079y)
    {
      b0079yy0079y0079y0079y = b00770077w0077007700770077www();
      byy00790079y0079y0079y = b00770077w0077007700770077www();
    }
    gaaaga.1 local1 = new gaaaga.1(this, paramInt);
    int i = b0079yy0079y0079y0079y;
    switch (i * (i + by0079y0079y0079y0079y) % b00790079y0079y0079y0079y)
    {
    default: 
      b0079yy0079y0079y0079y = b00770077w0077007700770077www();
      byy00790079y0079y0079y = b00770077w0077007700770077www();
    }
    localBitmapRequestBuilder.into(local1);
  }
  
  private void b0077w0077w0077ww0077ww(int paramInt, Bitmap paramBitmap)
  {
    int i = b0079yy0079y0079y0079y;
    switch (i * (i + by0079y0079y0079y0079y) % bwww0077007700770077www())
    {
    default: 
      b0079yy0079y0079y0079y = b00770077w0077007700770077www();
      byy00790079y0079y0079y = b00770077w0077007700770077www();
      if ((b0079yy0079y0079y0079y + by0079y0079y0079y0079y) * b0079yy0079y0079y0079y % bwww0077007700770077www() != byy00790079y0079y0079y)
      {
        b0079yy0079y0079y0079y = 83;
        byy00790079y0079y0079y = 41;
      }
      break;
    }
    Observable.fromCallable(new gaaaga.3(this, paramBitmap, paramInt)).observeOn(Schedulers.io()).subscribeOn(AndroidSchedulers.mainThread()).subscribe(new gaaaga.2(this, paramInt));
  }
  
  public static int b0077ww0077007700770077www()
  {
    return 1;
  }
  
  public static int bw0077w0077007700770077www()
  {
    return 0;
  }
  
  private TreatmentCache bww00770077007700770077www(int paramInt, @NonNull Treatment paramTreatment)
  {
    TreatmentCache localTreatmentCache = new TreatmentCache();
    int i = b00770077w0077007700770077www() + by0079y0079y0079y0079y;
    int j = b0079yy0079y0079y0079y;
    switch (j * (j + by0079y0079y0079y0079y) % b00790079y0079y0079y0079y)
    {
    default: 
      b0079yy0079y0079y0079y = 86;
      byy00790079y0079y0079y = b00770077w0077007700770077www();
    }
    if (i * b00770077w0077007700770077www() % b00790079y0079y0079y0079y != byy00790079y0079y0079y)
    {
      b0079yy0079y0079y0079y = b00770077w0077007700770077www();
      byy00790079y0079y0079y = b00770077w0077007700770077www();
    }
    localTreatmentCache.setCategory(paramTreatment.getCategory());
    localTreatmentCache.setHeadline(paramTreatment.getHeadline());
    localTreatmentCache.setText(paramTreatment.getText());
    localTreatmentCache.setLink(paramTreatment.getLink());
    localTreatmentCache.setPosition(paramInt);
    return localTreatmentCache;
  }
  
  public static int bwww0077007700770077www()
  {
    return 2;
  }
  
  private void bwwww0077ww0077ww(int paramInt)
  {
    if ((b0079yy0079y0079y0079y + by0079y0079y0079y0079y) * b0079yy0079y0079y0079y % b00790079y0079y0079y0079y != bw0077w0077007700770077www())
    {
      b0079yy0079y0079y0079y = b00770077w0077007700770077www();
      byy00790079y0079y0079y = 19;
    }
    aaggaa localAaggaa = (aaggaa)this.byyy0079y0079y0079y.get(paramInt);
    if (localAaggaa != null)
    {
      long l = System.currentTimeMillis();
      SparseArray localSparseArray = this.b007900790079yy0079y0079y;
      Long localLong = Long.valueOf(0L);
      if ((b0079yy0079y0079y0079y + b0077ww0077007700770077www()) * b0079yy0079y0079y0079y % bwww0077007700770077www() != byy00790079y0079y0079y)
      {
        b0079yy0079y0079y0079y = 51;
        byy00790079y0079y0079y = 10;
      }
      localAaggaa.baa006100610061006100610061aa(paramInt, l - ((Long)localSparseArray.get(paramInt, localLong)).longValue());
      this.byyy0079y0079y0079y.delete(paramInt);
    }
  }
  
  private void bwwwwwww0077ww(int paramInt)
  {
    this.by0079yyy0079y0079y.put(paramInt, true);
    this.b007900790079yy0079y0079y.put(paramInt, Long.valueOf(System.currentTimeMillis()));
    String str1 = b007700770077wwww0077ww();
    gaagaa localGaagaa = this.b00790079yyy0079y0079y;
    if ((b0079yy0079y0079y0079y + by0079y0079y0079y0079y) * b0079yy0079y0079y0079y % b00790079y0079y0079y0079y != byy00790079y0079y0079y)
    {
      int i = b00770077w0077007700770077www();
      switch (i * (i + b0077ww0077007700770077www()) % b00790079y0079y0079y0079y)
      {
      default: 
        b0079yy0079y0079y0079y = 44;
        byy00790079y0079y0079y = 98;
      }
      b0079yy0079y0079y0079y = 60;
      byy00790079y0079y0079y = 25;
    }
    String str2 = uxxxxx.bbbb0062b0062b0062b0062("$:st|}?@yz\003\004}~\007\bI\003\004\f\r\007\b\020\021R", '', '¦', '\003');
    Class[] arrayOfClass = new Class[4];
    arrayOfClass[0] = String.class;
    arrayOfClass[1] = Character.TYPE;
    arrayOfClass[2] = Character.TYPE;
    arrayOfClass[3] = Character.TYPE;
    Method localMethod = ppphhp.class.getMethod(str2, arrayOfClass);
    Object[] arrayOfObject = new Object[4];
    arrayOfObject[0] = "\b\007";
    arrayOfObject[1] = Character.valueOf('¢');
    arrayOfObject[2] = Character.valueOf('þ');
    arrayOfObject[3] = Character.valueOf('\002');
    try
    {
      Object localObject = localMethod.invoke(null, arrayOfObject);
      localGaagaa.bww0077ww0077w0077ww(this, paramInt, (String)localObject, str1, hphhhh.b007700770077007700770077w0077ww(onoonn.bk006B006B006B006Bkk006Bk006B(this.b0079yyyy0079y0079y)), this.byyyyy0079y0079y.bw0077w00770077w0077www(paramInt));
      return;
    }
    catch (InvocationTargetException localInvocationTargetException)
    {
      throw localInvocationTargetException.getCause();
    }
  }
  
  public void b0077007700770077007700770077www(int paramInt)
  {
    int i = b0079yy0079y0079y0079y;
    switch (i * (i + b0077ww0077007700770077www()) % b00790079y0079y0079y0079y)
    {
    default: 
      b0079yy0079y0079y0079y = b00770077w0077007700770077www();
      byy00790079y0079y0079y = b00770077w0077007700770077www();
    }
    int j = b0079yy0079y0079y0079y;
    switch (j * (j + by0079y0079y0079y0079y) % b00790079y0079y0079y0079y)
    {
    default: 
      b0079yy0079y0079y0079y = 72;
      byy00790079y0079y0079y = 7;
    }
    bwwwwwww0077ww(paramInt);
  }
  
  public void b007700770077w0077ww0077ww()
  {
    bw0077w00770077ww0077ww(1);
    if (b0077007700770077www0077ww())
    {
      vvrvrv localVvrvrv = vvrvrv.b0078007800780078xxxxx;
      int i = b0079yy0079y0079y0079y + by0079y0079y0079y0079y;
      int j = b0079yy0079y0079y0079y;
      switch (j * (j + by0079y0079y0079y0079y) % bwww0077007700770077www())
      {
      default: 
        b0079yy0079y0079y0079y = 24;
        byy00790079y0079y0079y = 33;
      }
      if (i * b0079yy0079y0079y0079y % bwww0077007700770077www() != byy00790079y0079y0079y)
      {
        b0079yy0079y0079y0079y = 20;
        byy00790079y0079y0079y = b00770077w0077007700770077www();
      }
      rrvvrv.b0071q0071qq0071q0071q0071(localVvrvrv);
      return;
    }
    rrvvrv.b0071q0071qq0071q0071q0071(vvrvrv.bxx0078x0078xxxx);
  }
  
  /* Error */
  public void b00770077ww0077ww0077ww()
  {
    // Byte code:
    //   0: aload_0
    //   1: getfield 169	uuuuuu/gaaaga:by00790079yy0079y0079y	Lcom/db/pwcc/dbmobile/secure/preferences/SharedPreferencesHelper;
    //   4: astore_1
    //   5: getstatic 105	uuuuuu/gaaaga:b0079yy0079y0079y0079y	I
    //   8: getstatic 107	uuuuuu/gaaaga:by0079y0079y0079y0079y	I
    //   11: iadd
    //   12: getstatic 105	uuuuuu/gaaaga:b0079yy0079y0079y0079y	I
    //   15: imul
    //   16: invokestatic 131	uuuuuu/gaaaga:bwww0077007700770077www	()I
    //   19: irem
    //   20: getstatic 115	uuuuuu/gaaaga:byy00790079y0079y0079y	I
    //   23: if_icmpeq +15 -> 38
    //   26: invokestatic 113	uuuuuu/gaaaga:b00770077w0077007700770077www	()I
    //   29: putstatic 105	uuuuuu/gaaaga:b0079yy0079y0079y0079y	I
    //   32: invokestatic 113	uuuuuu/gaaaga:b00770077w0077007700770077www	()I
    //   35: putstatic 115	uuuuuu/gaaaga:byy00790079y0079y0079y	I
    //   38: getstatic 105	uuuuuu/gaaaga:b0079yy0079y0079y0079y	I
    //   41: istore_2
    //   42: iload_2
    //   43: iload_2
    //   44: invokestatic 128	uuuuuu/gaaaga:b0077ww0077007700770077www	()I
    //   47: iadd
    //   48: imul
    //   49: getstatic 109	uuuuuu/gaaaga:b00790079y0079y0079y0079y	I
    //   52: irem
    //   53: tableswitch	default:+19->72, 0:+31->84
    //   72: invokestatic 113	uuuuuu/gaaaga:b00770077w0077007700770077www	()I
    //   75: putstatic 105	uuuuuu/gaaaga:b0079yy0079y0079y0079y	I
    //   78: invokestatic 113	uuuuuu/gaaaga:b00770077w0077007700770077www	()I
    //   81: putstatic 115	uuuuuu/gaaaga:byy00790079y0079y0079y	I
    //   84: ldc_w 452
    //   87: bipush 55
    //   89: iconst_2
    //   90: invokestatic 183	xxxxxx/uxxxxx:bb00620062bb0062b0062b0062	(Ljava/lang/String;CC)Ljava/lang/String;
    //   93: astore_3
    //   94: iconst_1
    //   95: anewarray 185	java/lang/Class
    //   98: astore 4
    //   100: aload 4
    //   102: iconst_0
    //   103: getstatic 191	java/lang/Long:TYPE	Ljava/lang/Class;
    //   106: aastore
    //   107: ldc -63
    //   109: aload_3
    //   110: aload 4
    //   112: invokevirtual 197	java/lang/Class:getMethod	(Ljava/lang/String;[Ljava/lang/Class;)Ljava/lang/reflect/Method;
    //   115: astore 5
    //   117: iconst_1
    //   118: anewarray 4	java/lang/Object
    //   121: astore 6
    //   123: aload 6
    //   125: iconst_0
    //   126: lconst_0
    //   127: invokestatic 201	java/lang/Long:valueOf	(J)Ljava/lang/Long;
    //   130: aastore
    //   131: aload 5
    //   133: aload_1
    //   134: aload 6
    //   136: invokevirtual 207	java/lang/reflect/Method:invoke	(Ljava/lang/Object;[Ljava/lang/Object;)Ljava/lang/Object;
    //   139: pop
    //   140: aload_0
    //   141: getfield 169	uuuuuu/gaaaga:by00790079yy0079y0079y	Lcom/db/pwcc/dbmobile/secure/preferences/SharedPreferencesHelper;
    //   144: astore 9
    //   146: ldc_w 454
    //   149: bipush 75
    //   151: iconst_2
    //   152: invokestatic 183	xxxxxx/uxxxxx:bb00620062bb0062b0062b0062	(Ljava/lang/String;CC)Ljava/lang/String;
    //   155: astore 10
    //   157: iconst_2
    //   158: anewarray 185	java/lang/Class
    //   161: astore 11
    //   163: aload 11
    //   165: iconst_0
    //   166: getstatic 224	java/lang/Integer:TYPE	Ljava/lang/Class;
    //   169: aastore
    //   170: aload 11
    //   172: iconst_1
    //   173: getstatic 191	java/lang/Long:TYPE	Ljava/lang/Class;
    //   176: aastore
    //   177: ldc -63
    //   179: aload 10
    //   181: aload 11
    //   183: invokevirtual 197	java/lang/Class:getMethod	(Ljava/lang/String;[Ljava/lang/Class;)Ljava/lang/reflect/Method;
    //   186: astore 12
    //   188: iconst_2
    //   189: anewarray 4	java/lang/Object
    //   192: astore 13
    //   194: aload 13
    //   196: iconst_0
    //   197: iconst_2
    //   198: invokestatic 227	java/lang/Integer:valueOf	(I)Ljava/lang/Integer;
    //   201: aastore
    //   202: aload 13
    //   204: iconst_1
    //   205: lconst_0
    //   206: invokestatic 201	java/lang/Long:valueOf	(J)Ljava/lang/Long;
    //   209: aastore
    //   210: aload 12
    //   212: aload 9
    //   214: aload 13
    //   216: invokevirtual 207	java/lang/reflect/Method:invoke	(Ljava/lang/Object;[Ljava/lang/Object;)Ljava/lang/Object;
    //   219: pop
    //   220: aload_0
    //   221: getfield 169	uuuuuu/gaaaga:by00790079yy0079y0079y	Lcom/db/pwcc/dbmobile/secure/preferences/SharedPreferencesHelper;
    //   224: astore 16
    //   226: ldc_w 456
    //   229: sipush 134
    //   232: iconst_0
    //   233: invokestatic 183	xxxxxx/uxxxxx:bb00620062bb0062b0062b0062	(Ljava/lang/String;CC)Ljava/lang/String;
    //   236: astore 17
    //   238: iconst_2
    //   239: anewarray 185	java/lang/Class
    //   242: astore 18
    //   244: aload 18
    //   246: iconst_0
    //   247: getstatic 224	java/lang/Integer:TYPE	Ljava/lang/Class;
    //   250: aastore
    //   251: aload 18
    //   253: iconst_1
    //   254: getstatic 191	java/lang/Long:TYPE	Ljava/lang/Class;
    //   257: aastore
    //   258: ldc -63
    //   260: aload 17
    //   262: aload 18
    //   264: invokevirtual 197	java/lang/Class:getMethod	(Ljava/lang/String;[Ljava/lang/Class;)Ljava/lang/reflect/Method;
    //   267: astore 19
    //   269: iconst_2
    //   270: anewarray 4	java/lang/Object
    //   273: astore 20
    //   275: aload 20
    //   277: iconst_0
    //   278: iconst_3
    //   279: invokestatic 227	java/lang/Integer:valueOf	(I)Ljava/lang/Integer;
    //   282: aastore
    //   283: aload 20
    //   285: iconst_1
    //   286: lconst_0
    //   287: invokestatic 201	java/lang/Long:valueOf	(J)Ljava/lang/Long;
    //   290: aastore
    //   291: aload 19
    //   293: aload 16
    //   295: aload 20
    //   297: invokevirtual 207	java/lang/reflect/Method:invoke	(Ljava/lang/Object;[Ljava/lang/Object;)Ljava/lang/Object;
    //   300: pop
    //   301: return
    //   302: astore 7
    //   304: aload 7
    //   306: invokevirtual 215	java/lang/reflect/InvocationTargetException:getCause	()Ljava/lang/Throwable;
    //   309: athrow
    //   310: astore 14
    //   312: aload 14
    //   314: invokevirtual 215	java/lang/reflect/InvocationTargetException:getCause	()Ljava/lang/Throwable;
    //   317: athrow
    //   318: astore 21
    //   320: aload 21
    //   322: invokevirtual 215	java/lang/reflect/InvocationTargetException:getCause	()Ljava/lang/Throwable;
    //   325: athrow
    // Local variable table:
    //   start	length	slot	name	signature
    //   0	326	0	this	gaaaga
    //   4	130	1	localSharedPreferencesHelper1	SharedPreferencesHelper
    //   41	8	2	i	int
    //   93	17	3	str1	String
    //   98	13	4	arrayOfClass1	Class[]
    //   115	17	5	localMethod1	Method
    //   121	14	6	arrayOfObject1	Object[]
    //   302	3	7	localInvocationTargetException1	InvocationTargetException
    //   144	69	9	localSharedPreferencesHelper2	SharedPreferencesHelper
    //   155	25	10	str2	String
    //   161	21	11	arrayOfClass2	Class[]
    //   186	25	12	localMethod2	Method
    //   192	23	13	arrayOfObject2	Object[]
    //   310	3	14	localInvocationTargetException2	InvocationTargetException
    //   224	70	16	localSharedPreferencesHelper3	SharedPreferencesHelper
    //   236	25	17	str3	String
    //   242	21	18	arrayOfClass3	Class[]
    //   267	25	19	localMethod3	Method
    //   273	23	20	arrayOfObject3	Object[]
    //   318	3	21	localInvocationTargetException3	InvocationTargetException
    // Exception table:
    //   from	to	target	type
    //   131	140	302	java/lang/reflect/InvocationTargetException
    //   210	220	310	java/lang/reflect/InvocationTargetException
    //   291	301	318	java/lang/reflect/InvocationTargetException
  }
  
  public String b00770077wwwww0077ww(int paramInt)
  {
    Method localMethod3;
    Object[] arrayOfObject3;
    switch (paramInt)
    {
    default: 
      String str4 = uxxxxx.bb00620062bb0062b0062b0062("2F}|\003\002A@wv|{srxw7nmsrjion.", '\020', '\005');
      Class[] arrayOfClass3 = new Class[4];
      arrayOfClass3[0] = String.class;
      arrayOfClass3[1] = Character.TYPE;
      arrayOfClass3[2] = Character.TYPE;
      arrayOfClass3[3] = Character.TYPE;
      localMethod3 = ppphhp.class.getMethod(str4, arrayOfClass3);
      arrayOfObject3 = new Object[4];
      arrayOfObject3[0] = "('\033\030,&\037)0\034..3*6,33%66.)49.54};B:";
      arrayOfObject3[1] = Character.valueOf('v');
      arrayOfObject3[2] = Character.valueOf('»');
      arrayOfObject3[3] = Character.valueOf('\003');
    }
    try
    {
      Object localObject3 = localMethod3.invoke(null, arrayOfObject3);
      str2 = (String)localObject3;
      return str2;
    }
    catch (InvocationTargetException localInvocationTargetException3)
    {
      String str2;
      String str3;
      Class[] arrayOfClass2;
      Method localMethod2;
      Object[] arrayOfObject2;
      String str1;
      Class[] arrayOfClass1;
      Method localMethod1;
      Object[] arrayOfObject1;
      throw localInvocationTargetException3.getCause();
    }
    str3 = uxxxxx.bb00620062bb0062b0062b0062("fzyxw/.43+*0/n&%+*\"!'&e", '¨', '\005');
    arrayOfClass2 = new Class[3];
    arrayOfClass2[0] = String.class;
    arrayOfClass2[1] = Character.TYPE;
    arrayOfClass2[2] = Character.TYPE;
    localMethod2 = ppphhp.class.getMethod(str3, arrayOfClass2);
    arrayOfObject2 = new Object[3];
    arrayOfObject2[0] = "0/# 4.'18$66;2>4;;-CG@1<A6=<\006CJB";
    arrayOfObject2[1] = Character.valueOf('º');
    arrayOfObject2[2] = Character.valueOf('\002');
    try
    {
      Object localObject2 = localMethod2.invoke(null, arrayOfObject2);
      return (String)localObject2;
    }
    catch (InvocationTargetException localInvocationTargetException2)
    {
      throw localInvocationTargetException2.getCause();
    }
    str1 = uxxxxx.bbbb0062b0062b0062b0062("3G~}\004\003BAxw}|tsyx8ontskjpo/", 'T', 'Ù', '\000');
    arrayOfClass1 = new Class[4];
    arrayOfClass1[0] = String.class;
    arrayOfClass1[1] = Character.TYPE;
    arrayOfClass1[2] = Character.TYPE;
    arrayOfClass1[3] = Character.TYPE;
    localMethod1 = ppphhp.class.getMethod(str1, arrayOfClass1);
    arrayOfObject1 = new Object[4];
    arrayOfObject1[0] = "&%\031\026*$\035'.\032,,1(4*11#9.9-.)49.54};B:";
    arrayOfObject1[1] = Character.valueOf('X');
    arrayOfObject1[2] = Character.valueOf('¦');
    arrayOfObject1[3] = Character.valueOf('\002');
    try
    {
      Object localObject1 = localMethod1.invoke(null, arrayOfObject1);
      str2 = (String)localObject1;
      int i = b0079yy0079y0079y0079y;
      switch (i * (i + by0079y0079y0079y0079y) % b00790079y0079y0079y0079y)
      {
      default: 
        b0079yy0079y0079y0079y = 37;
        byy00790079y0079y0079y = b00770077w0077007700770077www();
      }
      int j = b00770077w0077007700770077www();
      switch (j * (j + b0077ww0077007700770077www()) % bwww0077007700770077www())
      {
      }
      b0079yy0079y0079y0079y = 27;
      byy00790079y0079y0079y = b00770077w0077007700770077www();
      return str2;
    }
    catch (InvocationTargetException localInvocationTargetException1)
    {
      throw localInvocationTargetException1.getCause();
    }
  }
  
  public boolean b0077w00770077www0077ww(int paramInt)
  {
    long l = System.currentTimeMillis();
    SharedPreferencesHelper localSharedPreferencesHelper = this.by00790079yy0079y0079y;
    String str = uxxxxx.bb00620062bb0062b0062b0062("\t\006\024r\007\t\001f~\017|\003i\007xs\006}t|\002Wk||JnjgnVjmd", '^', '\003');
    Class[] arrayOfClass = new Class[1];
    arrayOfClass[0] = Integer.TYPE;
    Method localMethod = SharedPreferencesHelper.class.getMethod(str, arrayOfClass);
    Object[] arrayOfObject = new Object[1];
    arrayOfObject[0] = Integer.valueOf(paramInt);
    try
    {
      Object localObject = localMethod.invoke(localSharedPreferencesHelper, arrayOfObject);
      if (l - ((Long)localObject).longValue() > 86400000L) {
        return true;
      }
      int i = (b0079yy0079y0079y0079y + by0079y0079y0079y0079y) * b0079yy0079y0079y0079y % b00790079y0079y0079y0079y;
      int j = byy00790079y0079y0079y;
      int k = b0079yy0079y0079y0079y;
      switch (k * (k + by0079y0079y0079y0079y) % b00790079y0079y0079y0079y)
      {
      default: 
        b0079yy0079y0079y0079y = 62;
        byy00790079y0079y0079y = 27;
      }
      if (i != j)
      {
        b0079yy0079y0079y0079y = 37;
        byy00790079y0079y0079y = 39;
        return false;
      }
    }
    catch (InvocationTargetException localInvocationTargetException)
    {
      throw localInvocationTargetException.getCause();
    }
    return false;
  }
  
  public TreatmentCache b0077w0077wwww0077ww(int paramInt)
  {
    if ((b0079yy0079y0079y0079y + by0079y0079y0079y0079y) * b0079yy0079y0079y0079y % b00790079y0079y0079y0079y != byy00790079y0079y0079y)
    {
      if ((b0079yy0079y0079y0079y + by0079y0079y0079y0079y) * b0079yy0079y0079y0079y % b00790079y0079y0079y0079y != byy00790079y0079y0079y)
      {
        b0079yy0079y0079y0079y = 94;
        byy00790079y0079y0079y = b00770077w0077007700770077www();
      }
      b0079yy0079y0079y0079y = 27;
      byy00790079y0079y0079y = 65;
    }
    return this.byyyyy0079y0079y.b00770077w00770077w0077www(paramInt);
  }
  
  public void b0077ww00770077ww0077ww(int paramInt)
  {
    if (!this.byy0079yy0079y0079y.get(paramInt)) {
      bw0077w00770077ww0077ww(paramInt);
    }
    if (paramInt == 2) {
      rrvvrv.b0071q0071qq0071q0071q0071(vvrvrv.bx0078007800780078xxxx);
    }
    do
    {
      do
      {
        return;
        int i = b0079yy0079y0079y0079y;
        switch (i * (i + by0079y0079y0079y0079y) % b00790079y0079y0079y0079y)
        {
        default: 
          b0079yy0079y0079y0079y = b00770077w0077007700770077www();
          byy00790079y0079y0079y = 13;
        }
      } while (paramInt != 3);
      rrvvrv.b0071q0071qq0071q0071q0071(vvrvrv.b0078xx00780078xxxx);
    } while ((b0079yy0079y0079y0079y + b0077ww0077007700770077www()) * b0079yy0079y0079y0079y % bwww0077007700770077www() == bw0077w0077007700770077www());
    b0079yy0079y0079y0079y = b00770077w0077007700770077www();
    byy00790079y0079y0079y = 86;
  }
  
  public boolean b0077ww0077www0077ww(int paramInt)
  {
    boolean bool;
    if ((!this.b00790079007900790079yy0079y.bpppp0070p00700070pp()) && (b0077w0077wwww0077ww(paramInt).getCategory() == TreatmentCategory.ADVERTISEMENT) && (bw00770077wwww0077ww(paramInt) != null) && (!this.byyyyy0079y0079y.bww007700770077w0077www(paramInt))) {
      bool = true;
    }
    for (;;)
    {
      if ((b0079yy0079y0079y0079y + by0079y0079y0079y0079y) * b0079yy0079y0079y0079y % b00790079y0079y0079y0079y != byy00790079y0079y0079y)
      {
        b0079yy0079y0079y0079y = 96;
        byy00790079y0079y0079y = b00770077w0077007700770077www();
      }
      return bool;
      int i = (b0079yy0079y0079y0079y + by0079y0079y0079y0079y) * b0079yy0079y0079y0079y % bwww0077007700770077www();
      int j = byy00790079y0079y0079y;
      bool = false;
      if (i != j)
      {
        b0079yy0079y0079y0079y = 22;
        byy00790079y0079y0079y = b00770077w0077007700770077www();
        bool = false;
      }
    }
  }
  
  public void b0077www0077ww0077ww(DbError paramDbError, int paramInt)
  {
    switch (paramDbError.getStatusCode())
    {
    default: 
      switch (paramInt)
      {
      default: 
        rrvvrv.b0071q0071qq0071q0071q0071(vvrvrv.b007800780078x0078xxxx);
      }
      break;
    }
    for (;;)
    {
      this.byyy0079y0079y0079y.delete(paramInt);
      b00770077w00770077ww0077ww(paramInt);
      return;
      this.byyyyy0079y0079y.bwww00770077w0077www(paramInt);
      this.b0079yyyy0079y0079y.deleteFile(b00770077wwwww0077ww(paramInt));
      continue;
      bwwww0077ww0077ww(paramInt);
      if (paramInt != 1)
      {
        this.byy0079yy0079y0079y.put(paramInt, false);
        if ((b0079yy0079y0079y0079y + b0077ww0077007700770077www()) * b0079yy0079y0079y0079y % b00790079y0079y0079y0079y != byy00790079y0079y0079y)
        {
          b0079yy0079y0079y0079y = 77;
          byy00790079y0079y0079y = b00770077w0077007700770077www();
          if ((b00770077w0077007700770077www() + by0079y0079y0079y0079y) * b00770077w0077007700770077www() % bwww0077007700770077www() != byy00790079y0079y0079y)
          {
            b0079yy0079y0079y0079y = b00770077w0077007700770077www();
            byy00790079y0079y0079y = b00770077w0077007700770077www();
          }
        }
      }
    }
    rrvvrv.b0071q0071qq0071q0071q0071(vvrvrv.bx0078xx0078xxxx);
    return;
    rrvvrv.b0071q0071qq0071q0071q0071(vvrvrv.bxx007800780078xxxx);
  }
  
  public Bitmap b0077wwwwww0077ww()
  {
    int i = b0079yy0079y0079y0079y;
    switch (i * (i + by0079y0079y0079y0079y) % b00790079y0079y0079y0079y)
    {
    default: 
      b0079yy0079y0079y0079y = b00770077w0077007700770077www();
      byy00790079y0079y0079y = 74;
    }
    Bitmap localBitmap = bw00770077wwww0077ww(1);
    if ((b0079yy0079y0079y0079y + by0079y0079y0079y0079y) * b0079yy0079y0079y0079y % b00790079y0079y0079y0079y != byy00790079y0079y0079y)
    {
      b0079yy0079y0079y0079y = 65;
      byy00790079y0079y0079y = b00770077w0077007700770077www();
    }
    return localBitmap;
  }
  
  public void bw007700770077007700770077www(@Nullable aaggaa paramAaggaa)
  {
    this.byyy0079y0079y0079y.put(1, paramAaggaa);
    SparseBooleanArray localSparseBooleanArray = this.by0079yyy0079y0079y;
    if ((b0079yy0079y0079y0079y + by0079y0079y0079y0079y) * b0079yy0079y0079y0079y % b00790079y0079y0079y0079y != byy00790079y0079y0079y)
    {
      b0079yy0079y0079y0079y = b00770077w0077007700770077www();
      byy00790079y0079y0079y = b00770077w0077007700770077www();
    }
    if (localSparseBooleanArray.get(1, false)) {}
    do
    {
      return;
      bwwwwwww0077ww(1);
    } while ((b0079yy0079y0079y0079y + by0079y0079y0079y0079y) * b0079yy0079y0079y0079y % b00790079y0079y0079y0079y == byy00790079y0079y0079y);
    b0079yy0079y0079y0079y = 98;
    byy00790079y0079y0079y = b00770077w0077007700770077www();
  }
  
  public boolean bw007700770077www0077ww()
  {
    if ((b0079yy0079y0079y0079y + by0079y0079y0079y0079y) * b0079yy0079y0079y0079y % b00790079y0079y0079y0079y != byy00790079y0079y0079y)
    {
      b0079yy0079y0079y0079y = b00770077w0077007700770077www();
      int i = b00770077w0077007700770077www();
      if ((b0079yy0079y0079y0079y + b0077ww0077007700770077www()) * b0079yy0079y0079y0079y % b00790079y0079y0079y0079y != byy00790079y0079y0079y)
      {
        b0079yy0079y0079y0079y = 58;
        byy00790079y0079y0079y = 48;
      }
      byy00790079y0079y0079y = i;
    }
    return this.byyyyy0079y0079y.b0077w007700770077w0077www();
  }
  
  public void bw00770077w0077ww0077ww(boolean paramBoolean)
  {
    ggaaga localGgaaga = this.byyyyy0079y0079y;
    if ((b0079yy0079y0079y0079y + by0079y0079y0079y0079y) * b0079yy0079y0079y0079y % bwww0077007700770077www() != byy00790079y0079y0079y)
    {
      int i = b0079yy0079y0079y0079y;
      switch (i * (i + b0077ww0077007700770077www()) % b00790079y0079y0079y0079y)
      {
      default: 
        b0079yy0079y0079y0079y = 45;
        byy00790079y0079y0079y = b00770077w0077007700770077www();
      }
      b0079yy0079y0079y0079y = b00770077w0077007700770077www();
      byy00790079y0079y0079y = 67;
    }
    localGgaaga.bw0077007700770077w0077www(paramBoolean);
  }
  
  public Bitmap bw00770077wwww0077ww(int paramInt)
  {
    int i = b0079yy0079y0079y0079y;
    int j = i * (i + by0079y0079y0079y0079y) % b00790079y0079y0079y0079y;
    if ((b0079yy0079y0079y0079y + by0079y0079y0079y0079y) * b0079yy0079y0079y0079y % b00790079y0079y0079y0079y != byy00790079y0079y0079y)
    {
      b0079yy0079y0079y0079y = b00770077w0077007700770077www();
      byy00790079y0079y0079y = 74;
    }
    switch (j)
    {
    default: 
      b0079yy0079y0079y0079y = b00770077w0077007700770077www();
      byy00790079y0079y0079y = 48;
    }
    return ssxxxs.b006Bkk006B006Bk006Bk006B006B(this.b0079yyyy0079y0079y, b00770077wwwww0077ww(paramInt));
  }
  
  public void bw0077w00770077ww0077ww(int paramInt)
  {
    this.byyyyy0079y0079y.bwwwww00770077www(paramInt, true);
    String str = b00770077wwwww0077ww(paramInt);
    if ((b0079yy0079y0079y0079y + by0079y0079y0079y0079y) * b0079yy0079y0079y0079y % bwww0077007700770077www() != byy00790079y0079y0079y)
    {
      b0079yy0079y0079y0079y = 12;
      byy00790079y0079y0079y = b00770077w0077007700770077www();
    }
    if (this.b0079yyyy0079y0079y.getFileStreamPath(str).exists())
    {
      int i = b0079yy0079y0079y0079y;
      switch (i * (i + by0079y0079y0079y0079y) % b00790079y0079y0079y0079y)
      {
      default: 
        b0079yy0079y0079y0079y = b00770077w0077007700770077www();
        byy00790079y0079y0079y = 99;
      }
      this.b0079yyyy0079y0079y.deleteFile(str);
    }
  }
  
  public boolean bw0077w0077www0077ww()
  {
    if (!this.b00790079007900790079yy0079y.bpppp0070p00700070pp())
    {
      if (!b00770077w0077www0077ww(1))
      {
        if (!b0077ww0077www0077ww(1)) {
          break label105;
        }
        if ((b0079yy0079y0079y0079y + by0079y0079y0079y0079y) * b0079yy0079y0079y0079y % b00790079y0079y0079y0079y != byy00790079y0079y0079y)
        {
          int i = b0079yy0079y0079y0079y;
          switch (i * (i + by0079y0079y0079y0079y) % b00790079y0079y0079y0079y)
          {
          default: 
            b0079yy0079y0079y0079y = b00770077w0077007700770077www();
            byy00790079y0079y0079y = b00770077w0077007700770077www();
          }
          b0079yy0079y0079y0079y = b00770077w0077007700770077www();
          byy00790079y0079y0079y = 18;
        }
      }
      return true;
    }
    label105:
    return false;
  }
  
  public void bw0077ww0077ww0077ww(Treatment paramTreatment, int paramInt, String paramString)
  {
    this.byyyyy0079y0079y.b00770077007700770077w0077www(paramInt, paramString);
    String str = b00770077wwwww0077ww(paramInt);
    if (paramTreatment != null)
    {
      this.byyyyy0079y0079y.bwwwww00770077www(paramInt, false);
      this.byyyyy0079y0079y.b0077wwww00770077www(paramInt, bww00770077007700770077www(paramInt, paramTreatment));
      if (paramTreatment.getCategory() == TreatmentCategory.INFORMATION)
      {
        b00770077w00770077ww0077ww(paramInt);
        bwwww0077ww0077ww(paramInt);
        if (this.b0079yyyy0079y0079y.getFileStreamPath(str).exists())
        {
          this.b0079yyyy0079y0079y.deleteFile(str);
          if ((b0079yy0079y0079y0079y + by0079y0079y0079y0079y) * b0079yy0079y0079y0079y % b00790079y0079y0079y0079y != byy00790079y0079y0079y)
          {
            b0079yy0079y0079y0079y = b00770077w0077007700770077www();
            byy00790079y0079y0079y = b00770077w0077007700770077www();
          }
        }
        return;
      }
      int i = b0079yy0079y0079y0079y;
      switch (i * (i + b0077ww0077007700770077www()) % b00790079y0079y0079y0079y)
      {
      default: 
        b0079yy0079y0079y0079y = 88;
        byy00790079y0079y0079y = b00770077w0077007700770077www();
      }
      b0077w00770077007700770077www(paramInt, paramTreatment.getSource());
      return;
    }
    this.byyy0079y0079y0079y.delete(paramInt);
    b00770077w00770077ww0077ww(paramInt);
  }
  
  public String bw0077wwwww0077ww()
  {
    int i = b0079yy0079y0079y0079y;
    switch (i * (i + by0079y0079y0079y0079y) % b00790079y0079y0079y0079y)
    {
    default: 
      int j = b0079yy0079y0079y0079y;
      switch (j * (j + by0079y0079y0079y0079y) % b00790079y0079y0079y0079y)
      {
      default: 
        b0079yy0079y0079y0079y = 37;
        byy00790079y0079y0079y = b00770077w0077007700770077www();
      }
      b0079yy0079y0079y0079y = b00770077w0077007700770077www();
      byy00790079y0079y0079y = b00770077w0077007700770077www();
    }
    return bww0077wwww0077ww(1);
  }
  
  public boolean bww007700770077ww0077ww()
  {
    if ((b0079yy0079y0079y0079y + by0079y0079y0079y0079y) * b0079yy0079y0079y0079y % b00790079y0079y0079y0079y != byy00790079y0079y0079y)
    {
      b0079yy0079y0079y0079y = 12;
      byy00790079y0079y0079y = 16;
    }
    ggaaga localGgaaga = this.byyyyy0079y0079y;
    if ((b0079yy0079y0079y0079y + by0079y0079y0079y0079y) * b0079yy0079y0079y0079y % b00790079y0079y0079y0079y != byy00790079y0079y0079y)
    {
      b0079yy0079y0079y0079y = b00770077w0077007700770077www();
      byy00790079y0079y0079y = b00770077w0077007700770077www();
    }
    return localGgaaga.bww007700770077w0077www(1);
  }
  
  public boolean bww00770077www0077ww()
  {
    long l = System.currentTimeMillis();
    SharedPreferencesHelper localSharedPreferencesHelper = this.by00790079yy0079y0079y;
    Method localMethod = SharedPreferencesHelper.class.getMethod(uxxxxx.bb00620062bb0062b0062b0062("MJX)WMLRAOA@H-J<7IA8@E\0340AA\0173/,3\033/2)", '\032', '\003'), new Class[0]);
    Object[] arrayOfObject = new Object[0];
    for (;;)
    {
      boolean bool;
      try
      {
        Object localObject = localMethod.invoke(localSharedPreferencesHelper, arrayOfObject);
        if (l - ((Long)localObject).longValue() > 900000L)
        {
          bool = true;
          if ((b0079yy0079y0079y0079y + by0079y0079y0079y0079y) * b0079yy0079y0079y0079y % b00790079y0079y0079y0079y != byy00790079y0079y0079y)
          {
            b0079yy0079y0079y0079y = b00770077w0077007700770077www();
            byy00790079y0079y0079y = 41;
          }
          return bool;
        }
      }
      catch (InvocationTargetException localInvocationTargetException)
      {
        throw localInvocationTargetException.getCause();
      }
      int i = b00770077w0077007700770077www();
      switch (i * (i + by0079y0079y0079y0079y) % bwww0077007700770077www())
      {
      default: 
        b0079yy0079y0079y0079y = b00770077w0077007700770077www();
        byy00790079y0079y0079y = 86;
        bool = false;
        break;
      case 0: 
        bool = false;
      }
    }
  }
  
  public void bww0077w0077ww0077ww()
  {
    b00770077w00770077ww0077ww(1);
    if ((b0079yy0079y0079y0079y + by0079y0079y0079y0079y) * b0079yy0079y0079y0079y % b00790079y0079y0079y0079y != byy00790079y0079y0079y)
    {
      b0079yy0079y0079y0079y = b00770077w0077007700770077www();
      byy00790079y0079y0079y = 87;
      int i = b0079yy0079y0079y0079y;
      switch (i * (i + by0079y0079y0079y0079y) % b00790079y0079y0079y0079y)
      {
      default: 
        b0079yy0079y0079y0079y = b00770077w0077007700770077www();
        byy00790079y0079y0079y = b00770077w0077007700770077www();
      }
    }
  }
  
  public String bww0077wwww0077ww(int paramInt)
  {
    String str = this.byyyyy0079y0079y.b00770077w00770077w0077www(paramInt).getLink();
    if ((b0079yy0079y0079y0079y + by0079y0079y0079y0079y) * b0079yy0079y0079y0079y % b00790079y0079y0079y0079y != byy00790079y0079y0079y)
    {
      if ((b0079yy0079y0079y0079y + by0079y0079y0079y0079y) * b0079yy0079y0079y0079y % b00790079y0079y0079y0079y != byy00790079y0079y0079y)
      {
        b0079yy0079y0079y0079y = b00770077w0077007700770077www();
        byy00790079y0079y0079y = b00770077w0077007700770077www();
      }
      b0079yy0079y0079y0079y = b00770077w0077007700770077www();
      byy00790079y0079y0079y = b00770077w0077007700770077www();
    }
    return str;
  }
  
  public void bwww00770077ww0077ww()
  {
    bw0077w00770077ww0077ww(1);
    if (b0077007700770077www0077ww()) {
      rrvvrv.b0071q0071qq0071q0071q0071(vvrvrv.bxxxx0078xxxx);
    }
    do
    {
      return;
      rrvvrv.b0071q0071qq0071q0071q0071(vvrvrv.bxx0078x0078xxxx);
    } while ((b0079yy0079y0079y0079y + by0079y0079y0079y0079y) * b0079yy0079y0079y0079y % b00790079y0079y0079y0079y == byy00790079y0079y0079y);
    if ((b0079yy0079y0079y0079y + b0077ww0077007700770077www()) * b0079yy0079y0079y0079y % b00790079y0079y0079y0079y != byy00790079y0079y0079y)
    {
      b0079yy0079y0079y0079y = b00770077w0077007700770077www();
      byy00790079y0079y0079y = b00770077w0077007700770077www();
    }
    b0079yy0079y0079y0079y = 19;
    byy00790079y0079y0079y = b00770077w0077007700770077www();
  }
  
  public void bwww0077www0077ww(int paramInt)
  {
    if ((paramInt != 1) && (this.by0079yyy0079y0079y.get(paramInt)))
    {
      if ((b0079yy0079y0079y0079y + by0079y0079y0079y0079y) * b0079yy0079y0079y0079y % b00790079y0079y0079y0079y != byy00790079y0079y0079y)
      {
        b0079yy0079y0079y0079y = 39;
        byy00790079y0079y0079y = b00770077w0077007700770077www();
        if ((b0079yy0079y0079y0079y + by0079y0079y0079y0079y) * b0079yy0079y0079y0079y % bwww0077007700770077www() != byy00790079y0079y0079y)
        {
          b0079yy0079y0079y0079y = 86;
          byy00790079y0079y0079y = 7;
        }
      }
      this.byy0079yy0079y0079y.put(paramInt, true);
    }
  }
  
  public static abstract interface aaggaa
  {
    public abstract void baa006100610061006100610061aa(int paramInt, long paramLong);
  }
}
