package uuuuuu;

import com.db.pwcc.dbmobile.data.model.banking.BalanceHistory;
import com.db.pwcc.dbmobile.model.error.DbError;
import rx.Observable;
import rx.Subscription;

public class llllql
  extends qqqqll
  implements vvpvpv.ppvvpv, vvvpvp.pppvvp
{
  public static int b00700070p0070pp0070p0070 = 63;
  public static int b0070p00700070pp0070p0070 = 1;
  public static int bp007000700070pp0070p0070 = 2;
  public static int bpp00700070pp0070p0070;
  private Subscription b007000700070ppp0070p0070;
  private String b00700070pppp0070p0070;
  private fmmffm b0070p0070ppp0070p0070 = new fmmffm();
  private boolean b0070pp0070pp0070p0070 = false;
  private Observable<BalanceHistory> b0070ppppp0070p0070;
  private vvpvpv bp00700070ppp0070p0070 = new tssttt(new fmfmff());
  private DbError bp0070p0070pp0070p0070 = null;
  private String bp0070pppp0070p0070;
  private DbError bpp0070ppp0070p0070 = null;
  private boolean bppp0070pp0070p0070 = false;
  
  public llllql(String paramString)
  {
    super(paramString);
    onooon localOnooon = new onooon(onooon.nnooon.bn006En006E006E006E006E006E006E);
    this.bp0070pppp0070p0070 = localOnooon.bkkk006B006Bk006Bkk006B();
    this.b00700070pppp0070p0070 = localOnooon.b006Bkk006B006Bk006Bkk006B();
  }
  
  public static int b006F006F006Fo006F006Fo006Foo()
  {
    return 2;
  }
  
  public static int b006Fo006Fo006F006Fo006Foo()
  {
    return 1;
  }
  
  public static int bo006F006Fo006F006Fo006Foo()
  {
    return 0;
  }
  
  public static int booo006F006F006Fo006Foo()
  {
    return 71;
  }
  
  /* Error */
  public void b006F006Fo006F006F006Fo006Foo()
  {
    // Byte code:
    //   0: aload_0
    //   1: getfield 44	uuuuuu/llllql:bppp0070pp0070p0070	Z
    //   4: ifeq +651 -> 655
    //   7: aload_0
    //   8: getfield 46	uuuuuu/llllql:b0070pp0070pp0070p0070	Z
    //   11: ifeq +644 -> 655
    //   14: ldc 2
    //   16: ldc 97
    //   18: bipush 79
    //   20: iconst_1
    //   21: invokestatic 103	xxxxxx/uxxxxx:bb00620062bb0062b0062b0062	(Ljava/lang/String;CC)Ljava/lang/String;
    //   24: iconst_0
    //   25: anewarray 105	java/lang/Class
    //   28: invokevirtual 109	java/lang/Class:getMethod	(Ljava/lang/String;[Ljava/lang/Class;)Ljava/lang/reflect/Method;
    //   31: astore_1
    //   32: iconst_0
    //   33: anewarray 111	java/lang/Object
    //   36: astore_2
    //   37: aload_1
    //   38: aload_0
    //   39: aload_2
    //   40: invokevirtual 117	java/lang/reflect/Method:invoke	(Ljava/lang/Object;[Ljava/lang/Object;)Ljava/lang/Object;
    //   43: pop
    //   44: aconst_null
    //   45: invokevirtual 122	java/lang/String:length	()I
    //   48: pop
    //   49: goto -5 -> 44
    //   52: astore 5
    //   54: bipush 49
    //   56: putstatic 124	uuuuuu/llllql:b00700070p0070pp0070p0070	I
    //   59: aconst_null
    //   60: invokevirtual 122	java/lang/String:length	()I
    //   63: pop
    //   64: goto -5 -> 59
    //   67: astore 6
    //   69: bipush 85
    //   71: putstatic 124	uuuuuu/llllql:b00700070p0070pp0070p0070	I
    //   74: iconst_5
    //   75: istore 7
    //   77: iload 7
    //   79: iconst_0
    //   80: idiv
    //   81: istore 7
    //   83: goto -6 -> 77
    //   86: astore 8
    //   88: ldc 2
    //   90: ldc 126
    //   92: sipush 203
    //   95: iconst_5
    //   96: invokestatic 103	xxxxxx/uxxxxx:bb00620062bb0062b0062b0062	(Ljava/lang/String;CC)Ljava/lang/String;
    //   99: iconst_0
    //   100: anewarray 105	java/lang/Class
    //   103: invokevirtual 109	java/lang/Class:getMethod	(Ljava/lang/String;[Ljava/lang/Class;)Ljava/lang/reflect/Method;
    //   106: astore 9
    //   108: iconst_0
    //   109: anewarray 111	java/lang/Object
    //   112: astore 10
    //   114: aload 9
    //   116: aconst_null
    //   117: aload 10
    //   119: invokevirtual 117	java/lang/reflect/Method:invoke	(Ljava/lang/Object;[Ljava/lang/Object;)Ljava/lang/Object;
    //   122: astore 12
    //   124: aload 12
    //   126: checkcast 128	java/lang/Integer
    //   129: invokevirtual 131	java/lang/Integer:intValue	()I
    //   132: putstatic 124	uuuuuu/llllql:b00700070p0070pp0070p0070	I
    //   135: getstatic 124	uuuuuu/llllql:b00700070p0070pp0070p0070	I
    //   138: istore 13
    //   140: ldc 2
    //   142: ldc -123
    //   144: sipush 249
    //   147: iconst_5
    //   148: invokestatic 103	xxxxxx/uxxxxx:bb00620062bb0062b0062b0062	(Ljava/lang/String;CC)Ljava/lang/String;
    //   151: iconst_0
    //   152: anewarray 105	java/lang/Class
    //   155: invokevirtual 109	java/lang/Class:getMethod	(Ljava/lang/String;[Ljava/lang/Class;)Ljava/lang/reflect/Method;
    //   158: astore 14
    //   160: iconst_0
    //   161: anewarray 111	java/lang/Object
    //   164: astore 15
    //   166: aload 14
    //   168: aconst_null
    //   169: aload 15
    //   171: invokevirtual 117	java/lang/reflect/Method:invoke	(Ljava/lang/Object;[Ljava/lang/Object;)Ljava/lang/Object;
    //   174: astore 17
    //   176: aload 17
    //   178: checkcast 128	java/lang/Integer
    //   181: invokevirtual 131	java/lang/Integer:intValue	()I
    //   184: istore 18
    //   186: ldc 2
    //   188: ldc -121
    //   190: sipush 248
    //   193: iconst_4
    //   194: invokestatic 103	xxxxxx/uxxxxx:bb00620062bb0062b0062b0062	(Ljava/lang/String;CC)Ljava/lang/String;
    //   197: iconst_0
    //   198: anewarray 105	java/lang/Class
    //   201: invokevirtual 109	java/lang/Class:getMethod	(Ljava/lang/String;[Ljava/lang/Class;)Ljava/lang/reflect/Method;
    //   204: astore 19
    //   206: iconst_0
    //   207: anewarray 111	java/lang/Object
    //   210: astore 20
    //   212: aload 19
    //   214: aconst_null
    //   215: aload 20
    //   217: invokevirtual 117	java/lang/reflect/Method:invoke	(Ljava/lang/Object;[Ljava/lang/Object;)Ljava/lang/Object;
    //   220: astore 22
    //   222: iload 18
    //   224: iload 18
    //   226: aload 22
    //   228: checkcast 128	java/lang/Integer
    //   231: invokevirtual 131	java/lang/Integer:intValue	()I
    //   234: iadd
    //   235: imul
    //   236: getstatic 137	uuuuuu/llllql:bp007000700070pp0070p0070	I
    //   239: irem
    //   240: tableswitch	default:+20->260, 0:+119->359
    //   260: ldc 2
    //   262: ldc -117
    //   264: bipush 22
    //   266: sipush 141
    //   269: iconst_0
    //   270: invokestatic 143	xxxxxx/uxxxxx:bbbb0062b0062b0062b0062	(Ljava/lang/String;CCC)Ljava/lang/String;
    //   273: iconst_0
    //   274: anewarray 105	java/lang/Class
    //   277: invokevirtual 109	java/lang/Class:getMethod	(Ljava/lang/String;[Ljava/lang/Class;)Ljava/lang/reflect/Method;
    //   280: astore 44
    //   282: iconst_0
    //   283: anewarray 111	java/lang/Object
    //   286: astore 45
    //   288: aload 44
    //   290: aconst_null
    //   291: aload 45
    //   293: invokevirtual 117	java/lang/reflect/Method:invoke	(Ljava/lang/Object;[Ljava/lang/Object;)Ljava/lang/Object;
    //   296: astore 47
    //   298: aload 47
    //   300: checkcast 128	java/lang/Integer
    //   303: invokevirtual 131	java/lang/Integer:intValue	()I
    //   306: putstatic 124	uuuuuu/llllql:b00700070p0070pp0070p0070	I
    //   309: ldc 2
    //   311: ldc -111
    //   313: sipush 203
    //   316: sipush 153
    //   319: iconst_3
    //   320: invokestatic 143	xxxxxx/uxxxxx:bbbb0062b0062b0062b0062	(Ljava/lang/String;CCC)Ljava/lang/String;
    //   323: iconst_0
    //   324: anewarray 105	java/lang/Class
    //   327: invokevirtual 109	java/lang/Class:getMethod	(Ljava/lang/String;[Ljava/lang/Class;)Ljava/lang/reflect/Method;
    //   330: astore 48
    //   332: iconst_0
    //   333: anewarray 111	java/lang/Object
    //   336: astore 49
    //   338: aload 48
    //   340: aconst_null
    //   341: aload 49
    //   343: invokevirtual 117	java/lang/reflect/Method:invoke	(Ljava/lang/Object;[Ljava/lang/Object;)Ljava/lang/Object;
    //   346: astore 51
    //   348: aload 51
    //   350: checkcast 128	java/lang/Integer
    //   353: invokevirtual 131	java/lang/Integer:intValue	()I
    //   356: putstatic 147	uuuuuu/llllql:bpp00700070pp0070p0070	I
    //   359: ldc 2
    //   361: ldc -107
    //   363: bipush 107
    //   365: iconst_4
    //   366: invokestatic 103	xxxxxx/uxxxxx:bb00620062bb0062b0062b0062	(Ljava/lang/String;CC)Ljava/lang/String;
    //   369: iconst_0
    //   370: anewarray 105	java/lang/Class
    //   373: invokevirtual 109	java/lang/Class:getMethod	(Ljava/lang/String;[Ljava/lang/Class;)Ljava/lang/reflect/Method;
    //   376: astore 23
    //   378: iconst_0
    //   379: anewarray 111	java/lang/Object
    //   382: astore 24
    //   384: aload 23
    //   386: aconst_null
    //   387: aload 24
    //   389: invokevirtual 117	java/lang/reflect/Method:invoke	(Ljava/lang/Object;[Ljava/lang/Object;)Ljava/lang/Object;
    //   392: astore 26
    //   394: iload 13
    //   396: iload 13
    //   398: aload 26
    //   400: checkcast 128	java/lang/Integer
    //   403: invokevirtual 131	java/lang/Integer:intValue	()I
    //   406: iadd
    //   407: imul
    //   408: getstatic 137	uuuuuu/llllql:bp007000700070pp0070p0070	I
    //   411: irem
    //   412: tableswitch	default:+20->432, 0:+243->655
    //   432: ldc 2
    //   434: ldc -105
    //   436: bipush 105
    //   438: iconst_1
    //   439: invokestatic 103	xxxxxx/uxxxxx:bb00620062bb0062b0062b0062	(Ljava/lang/String;CC)Ljava/lang/String;
    //   442: iconst_0
    //   443: anewarray 105	java/lang/Class
    //   446: invokevirtual 109	java/lang/Class:getMethod	(Ljava/lang/String;[Ljava/lang/Class;)Ljava/lang/reflect/Method;
    //   449: astore 27
    //   451: iconst_0
    //   452: anewarray 111	java/lang/Object
    //   455: astore 28
    //   457: aload 27
    //   459: aconst_null
    //   460: aload 28
    //   462: invokevirtual 117	java/lang/reflect/Method:invoke	(Ljava/lang/Object;[Ljava/lang/Object;)Ljava/lang/Object;
    //   465: astore 30
    //   467: aload 30
    //   469: checkcast 128	java/lang/Integer
    //   472: invokevirtual 131	java/lang/Integer:intValue	()I
    //   475: putstatic 124	uuuuuu/llllql:b00700070p0070pp0070p0070	I
    //   478: ldc 2
    //   480: ldc -103
    //   482: sipush 247
    //   485: iconst_2
    //   486: invokestatic 103	xxxxxx/uxxxxx:bb00620062bb0062b0062b0062	(Ljava/lang/String;CC)Ljava/lang/String;
    //   489: iconst_0
    //   490: anewarray 105	java/lang/Class
    //   493: invokevirtual 109	java/lang/Class:getMethod	(Ljava/lang/String;[Ljava/lang/Class;)Ljava/lang/reflect/Method;
    //   496: astore 31
    //   498: iconst_0
    //   499: anewarray 111	java/lang/Object
    //   502: astore 32
    //   504: aload 31
    //   506: aconst_null
    //   507: aload 32
    //   509: invokevirtual 117	java/lang/reflect/Method:invoke	(Ljava/lang/Object;[Ljava/lang/Object;)Ljava/lang/Object;
    //   512: astore 34
    //   514: aload 34
    //   516: checkcast 128	java/lang/Integer
    //   519: invokevirtual 131	java/lang/Integer:intValue	()I
    //   522: putstatic 147	uuuuuu/llllql:bpp00700070pp0070p0070	I
    //   525: ldc 2
    //   527: ldc -101
    //   529: sipush 161
    //   532: iconst_4
    //   533: invokestatic 103	xxxxxx/uxxxxx:bb00620062bb0062b0062b0062	(Ljava/lang/String;CC)Ljava/lang/String;
    //   536: iconst_0
    //   537: anewarray 105	java/lang/Class
    //   540: invokevirtual 109	java/lang/Class:getMethod	(Ljava/lang/String;[Ljava/lang/Class;)Ljava/lang/reflect/Method;
    //   543: astore 35
    //   545: iconst_0
    //   546: anewarray 111	java/lang/Object
    //   549: astore 36
    //   551: aload 35
    //   553: aconst_null
    //   554: aload 36
    //   556: invokevirtual 117	java/lang/reflect/Method:invoke	(Ljava/lang/Object;[Ljava/lang/Object;)Ljava/lang/Object;
    //   559: astore 38
    //   561: aload 38
    //   563: checkcast 128	java/lang/Integer
    //   566: invokevirtual 131	java/lang/Integer:intValue	()I
    //   569: istore 39
    //   571: iload 39
    //   573: iload 39
    //   575: getstatic 157	uuuuuu/llllql:b0070p00700070pp0070p0070	I
    //   578: iadd
    //   579: imul
    //   580: getstatic 137	uuuuuu/llllql:bp007000700070pp0070p0070	I
    //   583: irem
    //   584: tableswitch	default:+20->604, 0:+71->655
    //   604: bipush 59
    //   606: putstatic 124	uuuuuu/llllql:b00700070p0070pp0070p0070	I
    //   609: ldc 2
    //   611: ldc -97
    //   613: bipush 103
    //   615: iconst_4
    //   616: invokestatic 103	xxxxxx/uxxxxx:bb00620062bb0062b0062b0062	(Ljava/lang/String;CC)Ljava/lang/String;
    //   619: iconst_0
    //   620: anewarray 105	java/lang/Class
    //   623: invokevirtual 109	java/lang/Class:getMethod	(Ljava/lang/String;[Ljava/lang/Class;)Ljava/lang/reflect/Method;
    //   626: astore 40
    //   628: iconst_0
    //   629: anewarray 111	java/lang/Object
    //   632: astore 41
    //   634: aload 40
    //   636: aconst_null
    //   637: aload 41
    //   639: invokevirtual 117	java/lang/reflect/Method:invoke	(Ljava/lang/Object;[Ljava/lang/Object;)Ljava/lang/Object;
    //   642: astore 43
    //   644: aload 43
    //   646: checkcast 128	java/lang/Integer
    //   649: invokevirtual 131	java/lang/Integer:intValue	()I
    //   652: putstatic 147	uuuuuu/llllql:bpp00700070pp0070p0070	I
    //   655: return
    //   656: astore 16
    //   658: aload 16
    //   660: invokevirtual 163	java/lang/reflect/InvocationTargetException:getCause	()Ljava/lang/Throwable;
    //   663: athrow
    //   664: astore 21
    //   666: aload 21
    //   668: invokevirtual 163	java/lang/reflect/InvocationTargetException:getCause	()Ljava/lang/Throwable;
    //   671: athrow
    //   672: astore_3
    //   673: aload_3
    //   674: invokevirtual 163	java/lang/reflect/InvocationTargetException:getCause	()Ljava/lang/Throwable;
    //   677: athrow
    //   678: astore 29
    //   680: aload 29
    //   682: invokevirtual 163	java/lang/reflect/InvocationTargetException:getCause	()Ljava/lang/Throwable;
    //   685: athrow
    //   686: astore 33
    //   688: aload 33
    //   690: invokevirtual 163	java/lang/reflect/InvocationTargetException:getCause	()Ljava/lang/Throwable;
    //   693: athrow
    //   694: astore 37
    //   696: aload 37
    //   698: invokevirtual 163	java/lang/reflect/InvocationTargetException:getCause	()Ljava/lang/Throwable;
    //   701: athrow
    //   702: astore 25
    //   704: aload 25
    //   706: invokevirtual 163	java/lang/reflect/InvocationTargetException:getCause	()Ljava/lang/Throwable;
    //   709: athrow
    //   710: astore 11
    //   712: aload 11
    //   714: invokevirtual 163	java/lang/reflect/InvocationTargetException:getCause	()Ljava/lang/Throwable;
    //   717: athrow
    //   718: astore 46
    //   720: aload 46
    //   722: invokevirtual 163	java/lang/reflect/InvocationTargetException:getCause	()Ljava/lang/Throwable;
    //   725: athrow
    //   726: astore 50
    //   728: aload 50
    //   730: invokevirtual 163	java/lang/reflect/InvocationTargetException:getCause	()Ljava/lang/Throwable;
    //   733: athrow
    //   734: astore 42
    //   736: aload 42
    //   738: invokevirtual 163	java/lang/reflect/InvocationTargetException:getCause	()Ljava/lang/Throwable;
    //   741: athrow
    // Local variable table:
    //   start	length	slot	name	signature
    //   0	742	0	this	llllql
    //   31	7	1	localMethod1	java.lang.reflect.Method
    //   36	4	2	arrayOfObject1	Object[]
    //   672	2	3	localInvocationTargetException1	java.lang.reflect.InvocationTargetException
    //   52	1	5	localException1	Exception
    //   67	1	6	localException2	Exception
    //   75	7	7	i	int
    //   86	1	8	localException3	Exception
    //   106	9	9	localMethod2	java.lang.reflect.Method
    //   112	6	10	arrayOfObject2	Object[]
    //   710	3	11	localInvocationTargetException2	java.lang.reflect.InvocationTargetException
    //   122	3	12	localObject1	Object
    //   138	270	13	j	int
    //   158	9	14	localMethod3	java.lang.reflect.Method
    //   164	6	15	arrayOfObject3	Object[]
    //   656	3	16	localInvocationTargetException3	java.lang.reflect.InvocationTargetException
    //   174	3	17	localObject2	Object
    //   184	52	18	k	int
    //   204	9	19	localMethod4	java.lang.reflect.Method
    //   210	6	20	arrayOfObject4	Object[]
    //   664	3	21	localInvocationTargetException4	java.lang.reflect.InvocationTargetException
    //   220	7	22	localObject3	Object
    //   376	9	23	localMethod5	java.lang.reflect.Method
    //   382	6	24	arrayOfObject5	Object[]
    //   702	3	25	localInvocationTargetException5	java.lang.reflect.InvocationTargetException
    //   392	7	26	localObject4	Object
    //   449	9	27	localMethod6	java.lang.reflect.Method
    //   455	6	28	arrayOfObject6	Object[]
    //   678	3	29	localInvocationTargetException6	java.lang.reflect.InvocationTargetException
    //   465	3	30	localObject5	Object
    //   496	9	31	localMethod7	java.lang.reflect.Method
    //   502	6	32	arrayOfObject7	Object[]
    //   686	3	33	localInvocationTargetException7	java.lang.reflect.InvocationTargetException
    //   512	3	34	localObject6	Object
    //   543	9	35	localMethod8	java.lang.reflect.Method
    //   549	6	36	arrayOfObject8	Object[]
    //   694	3	37	localInvocationTargetException8	java.lang.reflect.InvocationTargetException
    //   559	3	38	localObject7	Object
    //   569	11	39	m	int
    //   626	9	40	localMethod9	java.lang.reflect.Method
    //   632	6	41	arrayOfObject9	Object[]
    //   734	3	42	localInvocationTargetException9	java.lang.reflect.InvocationTargetException
    //   642	3	43	localObject8	Object
    //   280	9	44	localMethod10	java.lang.reflect.Method
    //   286	6	45	arrayOfObject10	Object[]
    //   718	3	46	localInvocationTargetException10	java.lang.reflect.InvocationTargetException
    //   296	3	47	localObject9	Object
    //   330	9	48	localMethod11	java.lang.reflect.Method
    //   336	6	49	arrayOfObject11	Object[]
    //   726	3	50	localInvocationTargetException11	java.lang.reflect.InvocationTargetException
    //   346	3	51	localObject10	Object
    // Exception table:
    //   from	to	target	type
    //   44	49	52	java/lang/Exception
    //   59	64	67	java/lang/Exception
    //   77	83	86	java/lang/Exception
    //   166	176	656	java/lang/reflect/InvocationTargetException
    //   212	222	664	java/lang/reflect/InvocationTargetException
    //   37	44	672	java/lang/reflect/InvocationTargetException
    //   457	467	678	java/lang/reflect/InvocationTargetException
    //   504	514	686	java/lang/reflect/InvocationTargetException
    //   551	561	694	java/lang/reflect/InvocationTargetException
    //   384	394	702	java/lang/reflect/InvocationTargetException
    //   114	124	710	java/lang/reflect/InvocationTargetException
    //   288	298	718	java/lang/reflect/InvocationTargetException
    //   338	348	726	java/lang/reflect/InvocationTargetException
    //   634	644	734	java/lang/reflect/InvocationTargetException
  }
  
  /* Error */
  public void b006Fo006F006Fo006Fo006Foo()
  {
    // Byte code:
    //   0: aload_0
    //   1: iconst_0
    //   2: putfield 44	uuuuuu/llllql:bppp0070pp0070p0070	Z
    //   5: ldc 2
    //   7: ldc -90
    //   9: sipush 234
    //   12: iconst_1
    //   13: invokestatic 103	xxxxxx/uxxxxx:bb00620062bb0062b0062b0062	(Ljava/lang/String;CC)Ljava/lang/String;
    //   16: iconst_0
    //   17: anewarray 105	java/lang/Class
    //   20: invokevirtual 109	java/lang/Class:getMethod	(Ljava/lang/String;[Ljava/lang/Class;)Ljava/lang/reflect/Method;
    //   23: astore_1
    //   24: iconst_0
    //   25: anewarray 111	java/lang/Object
    //   28: astore_2
    //   29: aload_1
    //   30: aconst_null
    //   31: aload_2
    //   32: invokevirtual 117	java/lang/reflect/Method:invoke	(Ljava/lang/Object;[Ljava/lang/Object;)Ljava/lang/Object;
    //   35: astore 4
    //   37: aload 4
    //   39: checkcast 128	java/lang/Integer
    //   42: invokevirtual 131	java/lang/Integer:intValue	()I
    //   45: istore 5
    //   47: iload 5
    //   49: iload 5
    //   51: getstatic 157	uuuuuu/llllql:b0070p00700070pp0070p0070	I
    //   54: iadd
    //   55: imul
    //   56: getstatic 137	uuuuuu/llllql:bp007000700070pp0070p0070	I
    //   59: irem
    //   60: tableswitch	default:+20->80, 0:+112->172
    //   80: ldc 2
    //   82: ldc -88
    //   84: bipush 117
    //   86: iconst_1
    //   87: invokestatic 103	xxxxxx/uxxxxx:bb00620062bb0062b0062b0062	(Ljava/lang/String;CC)Ljava/lang/String;
    //   90: iconst_0
    //   91: anewarray 105	java/lang/Class
    //   94: invokevirtual 109	java/lang/Class:getMethod	(Ljava/lang/String;[Ljava/lang/Class;)Ljava/lang/reflect/Method;
    //   97: astore 22
    //   99: iconst_0
    //   100: anewarray 111	java/lang/Object
    //   103: astore 23
    //   105: aload 22
    //   107: aconst_null
    //   108: aload 23
    //   110: invokevirtual 117	java/lang/reflect/Method:invoke	(Ljava/lang/Object;[Ljava/lang/Object;)Ljava/lang/Object;
    //   113: astore 25
    //   115: aload 25
    //   117: checkcast 128	java/lang/Integer
    //   120: invokevirtual 131	java/lang/Integer:intValue	()I
    //   123: putstatic 124	uuuuuu/llllql:b00700070p0070pp0070p0070	I
    //   126: ldc 2
    //   128: ldc -86
    //   130: bipush 73
    //   132: iconst_4
    //   133: invokestatic 103	xxxxxx/uxxxxx:bb00620062bb0062b0062b0062	(Ljava/lang/String;CC)Ljava/lang/String;
    //   136: iconst_0
    //   137: anewarray 105	java/lang/Class
    //   140: invokevirtual 109	java/lang/Class:getMethod	(Ljava/lang/String;[Ljava/lang/Class;)Ljava/lang/reflect/Method;
    //   143: astore 26
    //   145: iconst_0
    //   146: anewarray 111	java/lang/Object
    //   149: astore 27
    //   151: aload 26
    //   153: aconst_null
    //   154: aload 27
    //   156: invokevirtual 117	java/lang/reflect/Method:invoke	(Ljava/lang/Object;[Ljava/lang/Object;)Ljava/lang/Object;
    //   159: astore 29
    //   161: aload 29
    //   163: checkcast 128	java/lang/Integer
    //   166: invokevirtual 131	java/lang/Integer:intValue	()I
    //   169: putstatic 147	uuuuuu/llllql:bpp00700070pp0070p0070	I
    //   172: aload_0
    //   173: iconst_0
    //   174: putfield 46	uuuuuu/llllql:b0070pp0070pp0070p0070	Z
    //   177: aload_0
    //   178: getfield 58	uuuuuu/llllql:bp00700070ppp0070p0070	Luuuuuu/vvpvpv;
    //   181: aload_0
    //   182: aload_0
    //   183: getfield 173	uuuuuu/llllql:bp0070p007000700070pp0070	Ljava/lang/String;
    //   186: aload_0
    //   187: getfield 80	uuuuuu/llllql:bp0070pppp0070p0070	Ljava/lang/String;
    //   190: aload_0
    //   191: getfield 85	uuuuuu/llllql:b00700070pppp0070p0070	Ljava/lang/String;
    //   194: invokeinterface 179 5 0
    //   199: aload_0
    //   200: getfield 63	uuuuuu/llllql:b0070p0070ppp0070p0070	Luuuuuu/fmmffm;
    //   203: astore 6
    //   205: getstatic 124	uuuuuu/llllql:b00700070p0070pp0070p0070	I
    //   208: getstatic 157	uuuuuu/llllql:b0070p00700070pp0070p0070	I
    //   211: iadd
    //   212: getstatic 124	uuuuuu/llllql:b00700070p0070pp0070p0070	I
    //   215: imul
    //   216: getstatic 137	uuuuuu/llllql:bp007000700070pp0070p0070	I
    //   219: irem
    //   220: getstatic 147	uuuuuu/llllql:bpp00700070pp0070p0070	I
    //   223: if_icmpeq +147 -> 370
    //   226: getstatic 124	uuuuuu/llllql:b00700070p0070pp0070p0070	I
    //   229: istore 13
    //   231: iload 13
    //   233: iload 13
    //   235: getstatic 157	uuuuuu/llllql:b0070p00700070pp0070p0070	I
    //   238: iadd
    //   239: imul
    //   240: getstatic 137	uuuuuu/llllql:bp007000700070pp0070p0070	I
    //   243: irem
    //   244: tableswitch	default:+20->264, 0:+75->319
    //   264: bipush 86
    //   266: putstatic 124	uuuuuu/llllql:b00700070p0070pp0070p0070	I
    //   269: ldc 2
    //   271: ldc -75
    //   273: sipush 177
    //   276: sipush 189
    //   279: iconst_2
    //   280: invokestatic 143	xxxxxx/uxxxxx:bbbb0062b0062b0062b0062	(Ljava/lang/String;CCC)Ljava/lang/String;
    //   283: iconst_0
    //   284: anewarray 105	java/lang/Class
    //   287: invokevirtual 109	java/lang/Class:getMethod	(Ljava/lang/String;[Ljava/lang/Class;)Ljava/lang/reflect/Method;
    //   290: astore 18
    //   292: iconst_0
    //   293: anewarray 111	java/lang/Object
    //   296: astore 19
    //   298: aload 18
    //   300: aconst_null
    //   301: aload 19
    //   303: invokevirtual 117	java/lang/reflect/Method:invoke	(Ljava/lang/Object;[Ljava/lang/Object;)Ljava/lang/Object;
    //   306: astore 21
    //   308: aload 21
    //   310: checkcast 128	java/lang/Integer
    //   313: invokevirtual 131	java/lang/Integer:intValue	()I
    //   316: putstatic 147	uuuuuu/llllql:bpp00700070pp0070p0070	I
    //   319: bipush 32
    //   321: putstatic 124	uuuuuu/llllql:b00700070p0070pp0070p0070	I
    //   324: ldc 2
    //   326: ldc -73
    //   328: bipush 42
    //   330: iconst_2
    //   331: invokestatic 103	xxxxxx/uxxxxx:bb00620062bb0062b0062b0062	(Ljava/lang/String;CC)Ljava/lang/String;
    //   334: iconst_0
    //   335: anewarray 105	java/lang/Class
    //   338: invokevirtual 109	java/lang/Class:getMethod	(Ljava/lang/String;[Ljava/lang/Class;)Ljava/lang/reflect/Method;
    //   341: astore 14
    //   343: iconst_0
    //   344: anewarray 111	java/lang/Object
    //   347: astore 15
    //   349: aload 14
    //   351: aconst_null
    //   352: aload 15
    //   354: invokevirtual 117	java/lang/reflect/Method:invoke	(Ljava/lang/Object;[Ljava/lang/Object;)Ljava/lang/Object;
    //   357: astore 17
    //   359: aload 17
    //   361: checkcast 128	java/lang/Integer
    //   364: invokevirtual 131	java/lang/Integer:intValue	()I
    //   367: putstatic 147	uuuuuu/llllql:bpp00700070pp0070p0070	I
    //   370: aload_0
    //   371: getfield 187	uuuuuu/llllql:b006E006E006E006E006En006E006En	Luuuuuu/hyhyhh;
    //   374: invokevirtual 192	uuuuuu/hyhyhh:b0070pp007000700070p007000700070	()Ljava/lang/String;
    //   377: astore 7
    //   379: aload_0
    //   380: getfield 173	uuuuuu/llllql:bp0070p007000700070pp0070	Ljava/lang/String;
    //   383: astore 8
    //   385: getstatic 124	uuuuuu/llllql:b00700070p0070pp0070p0070	I
    //   388: getstatic 157	uuuuuu/llllql:b0070p00700070pp0070p0070	I
    //   391: iadd
    //   392: getstatic 124	uuuuuu/llllql:b00700070p0070pp0070p0070	I
    //   395: imul
    //   396: getstatic 137	uuuuuu/llllql:bp007000700070pp0070p0070	I
    //   399: irem
    //   400: getstatic 147	uuuuuu/llllql:bpp00700070pp0070p0070	I
    //   403: if_icmpeq +54 -> 457
    //   406: bipush 86
    //   408: putstatic 124	uuuuuu/llllql:b00700070p0070pp0070p0070	I
    //   411: ldc 2
    //   413: ldc -62
    //   415: bipush 15
    //   417: iconst_3
    //   418: invokestatic 103	xxxxxx/uxxxxx:bb00620062bb0062b0062b0062	(Ljava/lang/String;CC)Ljava/lang/String;
    //   421: iconst_0
    //   422: anewarray 105	java/lang/Class
    //   425: invokevirtual 109	java/lang/Class:getMethod	(Ljava/lang/String;[Ljava/lang/Class;)Ljava/lang/reflect/Method;
    //   428: astore 9
    //   430: iconst_0
    //   431: anewarray 111	java/lang/Object
    //   434: astore 10
    //   436: aload 9
    //   438: aconst_null
    //   439: aload 10
    //   441: invokevirtual 117	java/lang/reflect/Method:invoke	(Ljava/lang/Object;[Ljava/lang/Object;)Ljava/lang/Object;
    //   444: astore 12
    //   446: aload 12
    //   448: checkcast 128	java/lang/Integer
    //   451: invokevirtual 131	java/lang/Integer:intValue	()I
    //   454: putstatic 147	uuuuuu/llllql:bpp00700070pp0070p0070	I
    //   457: aload 6
    //   459: aload_0
    //   460: aload 7
    //   462: aload 8
    //   464: invokevirtual 198	uuuuuu/fmmffm:bppppp0070p00700070p	(Luuuuuu/vvvpvp$pppvvp;Ljava/lang/String;Ljava/lang/String;)V
    //   467: return
    //   468: astore 16
    //   470: aload 16
    //   472: invokevirtual 163	java/lang/reflect/InvocationTargetException:getCause	()Ljava/lang/Throwable;
    //   475: athrow
    //   476: astore 24
    //   478: aload 24
    //   480: invokevirtual 163	java/lang/reflect/InvocationTargetException:getCause	()Ljava/lang/Throwable;
    //   483: athrow
    //   484: astore 28
    //   486: aload 28
    //   488: invokevirtual 163	java/lang/reflect/InvocationTargetException:getCause	()Ljava/lang/Throwable;
    //   491: athrow
    //   492: astore 11
    //   494: aload 11
    //   496: invokevirtual 163	java/lang/reflect/InvocationTargetException:getCause	()Ljava/lang/Throwable;
    //   499: athrow
    //   500: astore_3
    //   501: aload_3
    //   502: invokevirtual 163	java/lang/reflect/InvocationTargetException:getCause	()Ljava/lang/Throwable;
    //   505: athrow
    //   506: astore 20
    //   508: aload 20
    //   510: invokevirtual 163	java/lang/reflect/InvocationTargetException:getCause	()Ljava/lang/Throwable;
    //   513: athrow
    // Local variable table:
    //   start	length	slot	name	signature
    //   0	514	0	this	llllql
    //   23	7	1	localMethod1	java.lang.reflect.Method
    //   28	4	2	arrayOfObject1	Object[]
    //   500	2	3	localInvocationTargetException1	java.lang.reflect.InvocationTargetException
    //   35	3	4	localObject1	Object
    //   45	11	5	i	int
    //   203	255	6	localFmmffm	fmmffm
    //   377	84	7	str1	String
    //   383	80	8	str2	String
    //   428	9	9	localMethod2	java.lang.reflect.Method
    //   434	6	10	arrayOfObject2	Object[]
    //   492	3	11	localInvocationTargetException2	java.lang.reflect.InvocationTargetException
    //   444	3	12	localObject2	Object
    //   229	11	13	j	int
    //   341	9	14	localMethod3	java.lang.reflect.Method
    //   347	6	15	arrayOfObject3	Object[]
    //   468	3	16	localInvocationTargetException3	java.lang.reflect.InvocationTargetException
    //   357	3	17	localObject3	Object
    //   290	9	18	localMethod4	java.lang.reflect.Method
    //   296	6	19	arrayOfObject4	Object[]
    //   506	3	20	localInvocationTargetException4	java.lang.reflect.InvocationTargetException
    //   306	3	21	localObject4	Object
    //   97	9	22	localMethod5	java.lang.reflect.Method
    //   103	6	23	arrayOfObject5	Object[]
    //   476	3	24	localInvocationTargetException5	java.lang.reflect.InvocationTargetException
    //   113	3	25	localObject5	Object
    //   143	9	26	localMethod6	java.lang.reflect.Method
    //   149	6	27	arrayOfObject6	Object[]
    //   484	3	28	localInvocationTargetException6	java.lang.reflect.InvocationTargetException
    //   159	3	29	localObject6	Object
    // Exception table:
    //   from	to	target	type
    //   349	359	468	java/lang/reflect/InvocationTargetException
    //   105	115	476	java/lang/reflect/InvocationTargetException
    //   151	161	484	java/lang/reflect/InvocationTargetException
    //   436	446	492	java/lang/reflect/InvocationTargetException
    //   29	37	500	java/lang/reflect/InvocationTargetException
    //   298	308	506	java/lang/reflect/InvocationTargetException
  }
  
  /* Error */
  public boolean b006Fo006Foo006Fo006Foo()
  {
    // Byte code:
    //   0: aload_0
    //   1: getfield 204	uuuuuu/llllql:bpp0070007000700070pp0070	Luuuuuu/heeeeh;
    //   4: ifnull +611 -> 615
    //   7: aload_0
    //   8: getfield 204	uuuuuu/llllql:bpp0070007000700070pp0070	Luuuuuu/heeeeh;
    //   11: invokevirtual 210	uuuuuu/heeeeh:bo006Fooooooo006F	()Lcom/db/pwcc/dbmobile/data/model/banking/BalanceHistory;
    //   14: ifnull +601 -> 615
    //   17: aload_0
    //   18: getfield 204	uuuuuu/llllql:bpp0070007000700070pp0070	Luuuuuu/heeeeh;
    //   21: invokevirtual 210	uuuuuu/heeeeh:bo006Fooooooo006F	()Lcom/db/pwcc/dbmobile/data/model/banking/BalanceHistory;
    //   24: invokevirtual 216	com/db/pwcc/dbmobile/data/model/banking/BalanceHistory:getBalanceHistoryGraphData	()Lcom/db/pwcc/dbmobile/data/model/banking/BalanceHistoryData;
    //   27: ifnull +588 -> 615
    //   30: aload_0
    //   31: getfield 204	uuuuuu/llllql:bpp0070007000700070pp0070	Luuuuuu/heeeeh;
    //   34: invokevirtual 210	uuuuuu/heeeeh:bo006Fooooooo006F	()Lcom/db/pwcc/dbmobile/data/model/banking/BalanceHistory;
    //   37: invokevirtual 216	com/db/pwcc/dbmobile/data/model/banking/BalanceHistory:getBalanceHistoryGraphData	()Lcom/db/pwcc/dbmobile/data/model/banking/BalanceHistoryData;
    //   40: invokevirtual 222	com/db/pwcc/dbmobile/data/model/banking/BalanceHistoryData:getData	()Ljava/util/Map;
    //   43: invokeinterface 227 1 0
    //   48: ifne +567 -> 615
    //   51: ldc 2
    //   53: ldc -75
    //   55: sipush 242
    //   58: iconst_2
    //   59: invokestatic 103	xxxxxx/uxxxxx:bb00620062bb0062b0062b0062	(Ljava/lang/String;CC)Ljava/lang/String;
    //   62: iconst_0
    //   63: anewarray 105	java/lang/Class
    //   66: invokevirtual 109	java/lang/Class:getMethod	(Ljava/lang/String;[Ljava/lang/Class;)Ljava/lang/reflect/Method;
    //   69: astore_1
    //   70: iconst_0
    //   71: anewarray 111	java/lang/Object
    //   74: astore_2
    //   75: aload_1
    //   76: aconst_null
    //   77: aload_2
    //   78: invokevirtual 117	java/lang/reflect/Method:invoke	(Ljava/lang/Object;[Ljava/lang/Object;)Ljava/lang/Object;
    //   81: astore 4
    //   83: aload 4
    //   85: checkcast 128	java/lang/Integer
    //   88: invokevirtual 131	java/lang/Integer:intValue	()I
    //   91: getstatic 157	uuuuuu/llllql:b0070p00700070pp0070p0070	I
    //   94: iadd
    //   95: istore 5
    //   97: ldc 2
    //   99: ldc -27
    //   101: bipush 81
    //   103: iconst_4
    //   104: invokestatic 103	xxxxxx/uxxxxx:bb00620062bb0062b0062b0062	(Ljava/lang/String;CC)Ljava/lang/String;
    //   107: iconst_0
    //   108: anewarray 105	java/lang/Class
    //   111: invokevirtual 109	java/lang/Class:getMethod	(Ljava/lang/String;[Ljava/lang/Class;)Ljava/lang/reflect/Method;
    //   114: astore 6
    //   116: iconst_0
    //   117: anewarray 111	java/lang/Object
    //   120: astore 7
    //   122: aload 6
    //   124: aconst_null
    //   125: aload 7
    //   127: invokevirtual 117	java/lang/reflect/Method:invoke	(Ljava/lang/Object;[Ljava/lang/Object;)Ljava/lang/Object;
    //   130: astore 9
    //   132: iload 5
    //   134: aload 9
    //   136: checkcast 128	java/lang/Integer
    //   139: invokevirtual 131	java/lang/Integer:intValue	()I
    //   142: imul
    //   143: istore 10
    //   145: ldc 2
    //   147: ldc -25
    //   149: sipush 132
    //   152: iconst_5
    //   153: invokestatic 103	xxxxxx/uxxxxx:bb00620062bb0062b0062b0062	(Ljava/lang/String;CC)Ljava/lang/String;
    //   156: iconst_0
    //   157: anewarray 105	java/lang/Class
    //   160: invokevirtual 109	java/lang/Class:getMethod	(Ljava/lang/String;[Ljava/lang/Class;)Ljava/lang/reflect/Method;
    //   163: astore 11
    //   165: iconst_0
    //   166: anewarray 111	java/lang/Object
    //   169: astore 12
    //   171: aload 11
    //   173: aconst_null
    //   174: aload 12
    //   176: invokevirtual 117	java/lang/reflect/Method:invoke	(Ljava/lang/Object;[Ljava/lang/Object;)Ljava/lang/Object;
    //   179: astore 14
    //   181: iload 10
    //   183: aload 14
    //   185: checkcast 128	java/lang/Integer
    //   188: invokevirtual 131	java/lang/Integer:intValue	()I
    //   191: irem
    //   192: getstatic 147	uuuuuu/llllql:bpp00700070pp0070p0070	I
    //   195: if_icmpeq +460 -> 655
    //   198: getstatic 124	uuuuuu/llllql:b00700070p0070pp0070p0070	I
    //   201: getstatic 157	uuuuuu/llllql:b0070p00700070pp0070p0070	I
    //   204: iadd
    //   205: getstatic 124	uuuuuu/llllql:b00700070p0070pp0070p0070	I
    //   208: imul
    //   209: getstatic 137	uuuuuu/llllql:bp007000700070pp0070p0070	I
    //   212: irem
    //   213: getstatic 147	uuuuuu/llllql:bpp00700070pp0070p0070	I
    //   216: if_icmpeq +95 -> 311
    //   219: ldc 2
    //   221: ldc -23
    //   223: bipush 124
    //   225: iconst_2
    //   226: invokestatic 103	xxxxxx/uxxxxx:bb00620062bb0062b0062b0062	(Ljava/lang/String;CC)Ljava/lang/String;
    //   229: iconst_0
    //   230: anewarray 105	java/lang/Class
    //   233: invokevirtual 109	java/lang/Class:getMethod	(Ljava/lang/String;[Ljava/lang/Class;)Ljava/lang/reflect/Method;
    //   236: astore 34
    //   238: iconst_0
    //   239: anewarray 111	java/lang/Object
    //   242: astore 35
    //   244: aload 34
    //   246: aconst_null
    //   247: aload 35
    //   249: invokevirtual 117	java/lang/reflect/Method:invoke	(Ljava/lang/Object;[Ljava/lang/Object;)Ljava/lang/Object;
    //   252: astore 37
    //   254: aload 37
    //   256: checkcast 128	java/lang/Integer
    //   259: invokevirtual 131	java/lang/Integer:intValue	()I
    //   262: putstatic 124	uuuuuu/llllql:b00700070p0070pp0070p0070	I
    //   265: ldc 2
    //   267: ldc -21
    //   269: bipush 99
    //   271: iconst_1
    //   272: invokestatic 103	xxxxxx/uxxxxx:bb00620062bb0062b0062b0062	(Ljava/lang/String;CC)Ljava/lang/String;
    //   275: iconst_0
    //   276: anewarray 105	java/lang/Class
    //   279: invokevirtual 109	java/lang/Class:getMethod	(Ljava/lang/String;[Ljava/lang/Class;)Ljava/lang/reflect/Method;
    //   282: astore 38
    //   284: iconst_0
    //   285: anewarray 111	java/lang/Object
    //   288: astore 39
    //   290: aload 38
    //   292: aconst_null
    //   293: aload 39
    //   295: invokevirtual 117	java/lang/reflect/Method:invoke	(Ljava/lang/Object;[Ljava/lang/Object;)Ljava/lang/Object;
    //   298: astore 41
    //   300: aload 41
    //   302: checkcast 128	java/lang/Integer
    //   305: invokevirtual 131	java/lang/Integer:intValue	()I
    //   308: putstatic 147	uuuuuu/llllql:bpp00700070pp0070p0070	I
    //   311: bipush 83
    //   313: putstatic 124	uuuuuu/llllql:b00700070p0070pp0070p0070	I
    //   316: ldc 2
    //   318: ldc -19
    //   320: bipush 18
    //   322: iconst_3
    //   323: invokestatic 103	xxxxxx/uxxxxx:bb00620062bb0062b0062b0062	(Ljava/lang/String;CC)Ljava/lang/String;
    //   326: iconst_0
    //   327: anewarray 105	java/lang/Class
    //   330: invokevirtual 109	java/lang/Class:getMethod	(Ljava/lang/String;[Ljava/lang/Class;)Ljava/lang/reflect/Method;
    //   333: astore 15
    //   335: iconst_0
    //   336: anewarray 111	java/lang/Object
    //   339: astore 16
    //   341: aload 15
    //   343: aconst_null
    //   344: aload 16
    //   346: invokevirtual 117	java/lang/reflect/Method:invoke	(Ljava/lang/Object;[Ljava/lang/Object;)Ljava/lang/Object;
    //   349: astore 18
    //   351: aload 18
    //   353: checkcast 128	java/lang/Integer
    //   356: invokevirtual 131	java/lang/Integer:intValue	()I
    //   359: putstatic 147	uuuuuu/llllql:bpp00700070pp0070p0070	I
    //   362: getstatic 124	uuuuuu/llllql:b00700070p0070pp0070p0070	I
    //   365: istore 19
    //   367: ldc 2
    //   369: ldc -17
    //   371: sipush 231
    //   374: iconst_1
    //   375: invokestatic 103	xxxxxx/uxxxxx:bb00620062bb0062b0062b0062	(Ljava/lang/String;CC)Ljava/lang/String;
    //   378: iconst_0
    //   379: anewarray 105	java/lang/Class
    //   382: invokevirtual 109	java/lang/Class:getMethod	(Ljava/lang/String;[Ljava/lang/Class;)Ljava/lang/reflect/Method;
    //   385: astore 20
    //   387: iconst_0
    //   388: anewarray 111	java/lang/Object
    //   391: astore 21
    //   393: aload 20
    //   395: aconst_null
    //   396: aload 21
    //   398: invokevirtual 117	java/lang/reflect/Method:invoke	(Ljava/lang/Object;[Ljava/lang/Object;)Ljava/lang/Object;
    //   401: astore 23
    //   403: iload 19
    //   405: iload 19
    //   407: aload 23
    //   409: checkcast 128	java/lang/Integer
    //   412: invokevirtual 131	java/lang/Integer:intValue	()I
    //   415: iadd
    //   416: imul
    //   417: getstatic 137	uuuuuu/llllql:bp007000700070pp0070p0070	I
    //   420: irem
    //   421: tableswitch	default:+19->440, 0:+234->655
    //   440: ldc 2
    //   442: ldc -15
    //   444: sipush 209
    //   447: iconst_1
    //   448: invokestatic 103	xxxxxx/uxxxxx:bb00620062bb0062b0062b0062	(Ljava/lang/String;CC)Ljava/lang/String;
    //   451: iconst_0
    //   452: anewarray 105	java/lang/Class
    //   455: invokevirtual 109	java/lang/Class:getMethod	(Ljava/lang/String;[Ljava/lang/Class;)Ljava/lang/reflect/Method;
    //   458: astore 24
    //   460: iconst_0
    //   461: anewarray 111	java/lang/Object
    //   464: astore 25
    //   466: aload 24
    //   468: aconst_null
    //   469: aload 25
    //   471: invokevirtual 117	java/lang/reflect/Method:invoke	(Ljava/lang/Object;[Ljava/lang/Object;)Ljava/lang/Object;
    //   474: astore 27
    //   476: aload 27
    //   478: checkcast 128	java/lang/Integer
    //   481: invokevirtual 131	java/lang/Integer:intValue	()I
    //   484: putstatic 124	uuuuuu/llllql:b00700070p0070pp0070p0070	I
    //   487: bipush 40
    //   489: putstatic 147	uuuuuu/llllql:bpp00700070pp0070p0070	I
    //   492: getstatic 124	uuuuuu/llllql:b00700070p0070pp0070p0070	I
    //   495: istore 28
    //   497: iload 28
    //   499: iload 28
    //   501: getstatic 157	uuuuuu/llllql:b0070p00700070pp0070p0070	I
    //   504: iadd
    //   505: imul
    //   506: istore 29
    //   508: ldc 2
    //   510: ldc -13
    //   512: bipush 90
    //   514: iconst_4
    //   515: invokestatic 103	xxxxxx/uxxxxx:bb00620062bb0062b0062b0062	(Ljava/lang/String;CC)Ljava/lang/String;
    //   518: iconst_0
    //   519: anewarray 105	java/lang/Class
    //   522: invokevirtual 109	java/lang/Class:getMethod	(Ljava/lang/String;[Ljava/lang/Class;)Ljava/lang/reflect/Method;
    //   525: astore 30
    //   527: iconst_0
    //   528: anewarray 111	java/lang/Object
    //   531: astore 31
    //   533: aload 30
    //   535: aconst_null
    //   536: aload 31
    //   538: invokevirtual 117	java/lang/reflect/Method:invoke	(Ljava/lang/Object;[Ljava/lang/Object;)Ljava/lang/Object;
    //   541: astore 33
    //   543: iload 29
    //   545: aload 33
    //   547: checkcast 128	java/lang/Integer
    //   550: invokevirtual 131	java/lang/Integer:intValue	()I
    //   553: irem
    //   554: tableswitch	default:+18->572, 0:+101->655
    //   572: iconst_3
    //   573: putstatic 124	uuuuuu/llllql:b00700070p0070pp0070p0070	I
    //   576: bipush 69
    //   578: putstatic 147	uuuuuu/llllql:bpp00700070pp0070p0070	I
    //   581: iconst_1
    //   582: ireturn
    //   583: astore 17
    //   585: aload 17
    //   587: invokevirtual 163	java/lang/reflect/InvocationTargetException:getCause	()Ljava/lang/Throwable;
    //   590: athrow
    //   591: astore 26
    //   593: aload 26
    //   595: invokevirtual 163	java/lang/reflect/InvocationTargetException:getCause	()Ljava/lang/Throwable;
    //   598: athrow
    //   599: astore 32
    //   601: aload 32
    //   603: invokevirtual 163	java/lang/reflect/InvocationTargetException:getCause	()Ljava/lang/Throwable;
    //   606: athrow
    //   607: astore 22
    //   609: aload 22
    //   611: invokevirtual 163	java/lang/reflect/InvocationTargetException:getCause	()Ljava/lang/Throwable;
    //   614: athrow
    //   615: iconst_0
    //   616: ireturn
    //   617: astore_3
    //   618: aload_3
    //   619: invokevirtual 163	java/lang/reflect/InvocationTargetException:getCause	()Ljava/lang/Throwable;
    //   622: athrow
    //   623: astore 8
    //   625: aload 8
    //   627: invokevirtual 163	java/lang/reflect/InvocationTargetException:getCause	()Ljava/lang/Throwable;
    //   630: athrow
    //   631: astore 13
    //   633: aload 13
    //   635: invokevirtual 163	java/lang/reflect/InvocationTargetException:getCause	()Ljava/lang/Throwable;
    //   638: athrow
    //   639: astore 36
    //   641: aload 36
    //   643: invokevirtual 163	java/lang/reflect/InvocationTargetException:getCause	()Ljava/lang/Throwable;
    //   646: athrow
    //   647: astore 40
    //   649: aload 40
    //   651: invokevirtual 163	java/lang/reflect/InvocationTargetException:getCause	()Ljava/lang/Throwable;
    //   654: athrow
    //   655: iconst_1
    //   656: ireturn
    // Local variable table:
    //   start	length	slot	name	signature
    //   0	657	0	this	llllql
    //   69	7	1	localMethod1	java.lang.reflect.Method
    //   74	4	2	arrayOfObject1	Object[]
    //   617	2	3	localInvocationTargetException1	java.lang.reflect.InvocationTargetException
    //   81	3	4	localObject1	Object
    //   95	48	5	i	int
    //   114	9	6	localMethod2	java.lang.reflect.Method
    //   120	6	7	arrayOfObject2	Object[]
    //   623	3	8	localInvocationTargetException2	java.lang.reflect.InvocationTargetException
    //   130	5	9	localObject2	Object
    //   143	49	10	j	int
    //   163	9	11	localMethod3	java.lang.reflect.Method
    //   169	6	12	arrayOfObject3	Object[]
    //   631	3	13	localInvocationTargetException3	java.lang.reflect.InvocationTargetException
    //   179	5	14	localObject3	Object
    //   333	9	15	localMethod4	java.lang.reflect.Method
    //   339	6	16	arrayOfObject4	Object[]
    //   583	3	17	localInvocationTargetException4	java.lang.reflect.InvocationTargetException
    //   349	3	18	localObject4	Object
    //   365	52	19	k	int
    //   385	9	20	localMethod5	java.lang.reflect.Method
    //   391	6	21	arrayOfObject5	Object[]
    //   607	3	22	localInvocationTargetException5	java.lang.reflect.InvocationTargetException
    //   401	7	23	localObject5	Object
    //   458	9	24	localMethod6	java.lang.reflect.Method
    //   464	6	25	arrayOfObject6	Object[]
    //   591	3	26	localInvocationTargetException6	java.lang.reflect.InvocationTargetException
    //   474	3	27	localObject6	Object
    //   495	11	28	m	int
    //   506	48	29	n	int
    //   525	9	30	localMethod7	java.lang.reflect.Method
    //   531	6	31	arrayOfObject7	Object[]
    //   599	3	32	localInvocationTargetException7	java.lang.reflect.InvocationTargetException
    //   541	5	33	localObject7	Object
    //   236	9	34	localMethod8	java.lang.reflect.Method
    //   242	6	35	arrayOfObject8	Object[]
    //   639	3	36	localInvocationTargetException8	java.lang.reflect.InvocationTargetException
    //   252	3	37	localObject8	Object
    //   282	9	38	localMethod9	java.lang.reflect.Method
    //   288	6	39	arrayOfObject9	Object[]
    //   647	3	40	localInvocationTargetException9	java.lang.reflect.InvocationTargetException
    //   298	3	41	localObject9	Object
    // Exception table:
    //   from	to	target	type
    //   341	351	583	java/lang/reflect/InvocationTargetException
    //   466	476	591	java/lang/reflect/InvocationTargetException
    //   533	543	599	java/lang/reflect/InvocationTargetException
    //   393	403	607	java/lang/reflect/InvocationTargetException
    //   75	83	617	java/lang/reflect/InvocationTargetException
    //   122	132	623	java/lang/reflect/InvocationTargetException
    //   171	181	631	java/lang/reflect/InvocationTargetException
    //   244	254	639	java/lang/reflect/InvocationTargetException
    //   290	300	647	java/lang/reflect/InvocationTargetException
  }
  
  /* Error */
  public void b006Foo006F006F006Fo006Foo()
  {
    // Byte code:
    //   0: aload_0
    //   1: invokevirtual 247	uuuuuu/llllql:bkk006Bk006Bk006Bk006Bk	()Z
    //   4: ifne +124 -> 128
    //   7: getstatic 124	uuuuuu/llllql:b00700070p0070pp0070p0070	I
    //   10: getstatic 157	uuuuuu/llllql:b0070p00700070pp0070p0070	I
    //   13: iadd
    //   14: getstatic 124	uuuuuu/llllql:b00700070p0070pp0070p0070	I
    //   17: imul
    //   18: getstatic 137	uuuuuu/llllql:bp007000700070pp0070p0070	I
    //   21: irem
    //   22: getstatic 147	uuuuuu/llllql:bpp00700070pp0070p0070	I
    //   25: if_icmpeq +102 -> 127
    //   28: ldc 2
    //   30: ldc -7
    //   32: sipush 193
    //   35: sipush 146
    //   38: iconst_0
    //   39: invokestatic 143	xxxxxx/uxxxxx:bbbb0062b0062b0062b0062	(Ljava/lang/String;CCC)Ljava/lang/String;
    //   42: iconst_0
    //   43: anewarray 105	java/lang/Class
    //   46: invokevirtual 109	java/lang/Class:getMethod	(Ljava/lang/String;[Ljava/lang/Class;)Ljava/lang/reflect/Method;
    //   49: astore 34
    //   51: iconst_0
    //   52: anewarray 111	java/lang/Object
    //   55: astore 35
    //   57: aload 34
    //   59: aconst_null
    //   60: aload 35
    //   62: invokevirtual 117	java/lang/reflect/Method:invoke	(Ljava/lang/Object;[Ljava/lang/Object;)Ljava/lang/Object;
    //   65: astore 37
    //   67: aload 37
    //   69: checkcast 128	java/lang/Integer
    //   72: invokevirtual 131	java/lang/Integer:intValue	()I
    //   75: putstatic 124	uuuuuu/llllql:b00700070p0070pp0070p0070	I
    //   78: ldc 2
    //   80: ldc -5
    //   82: sipush 138
    //   85: bipush 23
    //   87: iconst_0
    //   88: invokestatic 143	xxxxxx/uxxxxx:bbbb0062b0062b0062b0062	(Ljava/lang/String;CCC)Ljava/lang/String;
    //   91: iconst_0
    //   92: anewarray 105	java/lang/Class
    //   95: invokevirtual 109	java/lang/Class:getMethod	(Ljava/lang/String;[Ljava/lang/Class;)Ljava/lang/reflect/Method;
    //   98: astore 38
    //   100: iconst_0
    //   101: anewarray 111	java/lang/Object
    //   104: astore 39
    //   106: aload 38
    //   108: aconst_null
    //   109: aload 39
    //   111: invokevirtual 117	java/lang/reflect/Method:invoke	(Ljava/lang/Object;[Ljava/lang/Object;)Ljava/lang/Object;
    //   114: astore 41
    //   116: aload 41
    //   118: checkcast 128	java/lang/Integer
    //   121: invokevirtual 131	java/lang/Integer:intValue	()I
    //   124: putstatic 147	uuuuuu/llllql:bpp00700070pp0070p0070	I
    //   127: return
    //   128: aload_0
    //   129: getfield 40	uuuuuu/llllql:bp0070p0070pp0070p0070	Lcom/db/pwcc/dbmobile/model/error/DbError;
    //   132: ifnull +20 -> 152
    //   135: aload_0
    //   136: getfield 255	uuuuuu/llllql:bnnnnn006E006E006En	Luuuuuu/ttssst$tsssst;
    //   139: checkcast 257	uuuuuu/llqqll$lqqqll
    //   142: aload_0
    //   143: getfield 40	uuuuuu/llllql:bp0070p0070pp0070p0070	Lcom/db/pwcc/dbmobile/model/error/DbError;
    //   146: invokeinterface 261 2 0
    //   151: return
    //   152: aload_0
    //   153: getfield 255	uuuuuu/llllql:bnnnnn006E006E006En	Luuuuuu/ttssst$tsssst;
    //   156: checkcast 257	uuuuuu/llqqll$lqqqll
    //   159: aload_0
    //   160: getfield 204	uuuuuu/llllql:bpp0070007000700070pp0070	Luuuuuu/heeeeh;
    //   163: invokevirtual 265	uuuuuu/heeeeh:b006F006Fooooooo006F	()Lcom/db/pwcc/dbmobile/model/banking/FinancialOverviewData;
    //   166: aload_0
    //   167: getfield 173	uuuuuu/llllql:bp0070p007000700070pp0070	Ljava/lang/String;
    //   170: invokevirtual 271	com/db/pwcc/dbmobile/model/banking/FinancialOverviewData:getAccountByID	(Ljava/lang/String;)Lcom/db/pwcc/dbmobile/model/banking/Account;
    //   173: invokeinterface 275 2 0
    //   178: getstatic 124	uuuuuu/llllql:b00700070p0070pp0070p0070	I
    //   181: istore_1
    //   182: iload_1
    //   183: iload_1
    //   184: getstatic 157	uuuuuu/llllql:b0070p00700070pp0070p0070	I
    //   187: iadd
    //   188: imul
    //   189: getstatic 137	uuuuuu/llllql:bp007000700070pp0070p0070	I
    //   192: irem
    //   193: tableswitch	default:+19->212, 0:+29->222
    //   212: bipush 75
    //   214: putstatic 124	uuuuuu/llllql:b00700070p0070pp0070p0070	I
    //   217: bipush 19
    //   219: putstatic 147	uuuuuu/llllql:bpp00700070pp0070p0070	I
    //   222: aload_0
    //   223: getfield 255	uuuuuu/llllql:bnnnnn006E006E006En	Luuuuuu/ttssst$tsssst;
    //   226: checkcast 257	uuuuuu/llqqll$lqqqll
    //   229: invokeinterface 278 1 0
    //   234: aload_0
    //   235: invokevirtual 281	uuuuuu/llllql:bo006F006F006Fo006Fo006Foo	()Z
    //   238: ifne -111 -> 127
    //   241: aload_0
    //   242: getfield 255	uuuuuu/llllql:bnnnnn006E006E006En	Luuuuuu/ttssst$tsssst;
    //   245: checkcast 257	uuuuuu/llqqll$lqqqll
    //   248: astore_2
    //   249: ldc 2
    //   251: ldc_w 283
    //   254: sipush 227
    //   257: iconst_1
    //   258: invokestatic 103	xxxxxx/uxxxxx:bb00620062bb0062b0062b0062	(Ljava/lang/String;CC)Ljava/lang/String;
    //   261: iconst_0
    //   262: anewarray 105	java/lang/Class
    //   265: invokevirtual 109	java/lang/Class:getMethod	(Ljava/lang/String;[Ljava/lang/Class;)Ljava/lang/reflect/Method;
    //   268: astore_3
    //   269: iconst_0
    //   270: anewarray 111	java/lang/Object
    //   273: astore 4
    //   275: aload_3
    //   276: aconst_null
    //   277: aload 4
    //   279: invokevirtual 117	java/lang/reflect/Method:invoke	(Ljava/lang/Object;[Ljava/lang/Object;)Ljava/lang/Object;
    //   282: astore 6
    //   284: aload 6
    //   286: checkcast 128	java/lang/Integer
    //   289: invokevirtual 131	java/lang/Integer:intValue	()I
    //   292: getstatic 157	uuuuuu/llllql:b0070p00700070pp0070p0070	I
    //   295: iadd
    //   296: istore 7
    //   298: ldc 2
    //   300: ldc_w 285
    //   303: bipush 118
    //   305: iconst_3
    //   306: invokestatic 103	xxxxxx/uxxxxx:bb00620062bb0062b0062b0062	(Ljava/lang/String;CC)Ljava/lang/String;
    //   309: iconst_0
    //   310: anewarray 105	java/lang/Class
    //   313: invokevirtual 109	java/lang/Class:getMethod	(Ljava/lang/String;[Ljava/lang/Class;)Ljava/lang/reflect/Method;
    //   316: astore 8
    //   318: iconst_0
    //   319: anewarray 111	java/lang/Object
    //   322: astore 9
    //   324: aload 8
    //   326: aconst_null
    //   327: aload 9
    //   329: invokevirtual 117	java/lang/reflect/Method:invoke	(Ljava/lang/Object;[Ljava/lang/Object;)Ljava/lang/Object;
    //   332: astore 11
    //   334: iload 7
    //   336: aload 11
    //   338: checkcast 128	java/lang/Integer
    //   341: invokevirtual 131	java/lang/Integer:intValue	()I
    //   344: imul
    //   345: getstatic 137	uuuuuu/llllql:bp007000700070pp0070p0070	I
    //   348: irem
    //   349: getstatic 147	uuuuuu/llllql:bpp00700070pp0070p0070	I
    //   352: if_icmpeq +55 -> 407
    //   355: ldc 2
    //   357: ldc_w 287
    //   360: bipush 82
    //   362: iconst_2
    //   363: invokestatic 103	xxxxxx/uxxxxx:bb00620062bb0062b0062b0062	(Ljava/lang/String;CC)Ljava/lang/String;
    //   366: iconst_0
    //   367: anewarray 105	java/lang/Class
    //   370: invokevirtual 109	java/lang/Class:getMethod	(Ljava/lang/String;[Ljava/lang/Class;)Ljava/lang/reflect/Method;
    //   373: astore 30
    //   375: iconst_0
    //   376: anewarray 111	java/lang/Object
    //   379: astore 31
    //   381: aload 30
    //   383: aconst_null
    //   384: aload 31
    //   386: invokevirtual 117	java/lang/reflect/Method:invoke	(Ljava/lang/Object;[Ljava/lang/Object;)Ljava/lang/Object;
    //   389: astore 33
    //   391: aload 33
    //   393: checkcast 128	java/lang/Integer
    //   396: invokevirtual 131	java/lang/Integer:intValue	()I
    //   399: putstatic 124	uuuuuu/llllql:b00700070p0070pp0070p0070	I
    //   402: bipush 23
    //   404: putstatic 147	uuuuuu/llllql:bpp00700070pp0070p0070	I
    //   407: aload_0
    //   408: getfield 204	uuuuuu/llllql:bpp0070007000700070pp0070	Luuuuuu/heeeeh;
    //   411: invokevirtual 291	uuuuuu/heeeeh:boo006Foooooo006F	()Lcom/db/pwcc/dbmobile/model/banking/TransactionsData;
    //   414: astore 12
    //   416: aload_0
    //   417: getfield 204	uuuuuu/llllql:bpp0070007000700070pp0070	Luuuuuu/heeeeh;
    //   420: invokevirtual 265	uuuuuu/heeeeh:b006F006Fooooooo006F	()Lcom/db/pwcc/dbmobile/model/banking/FinancialOverviewData;
    //   423: aload_0
    //   424: getfield 173	uuuuuu/llllql:bp0070p007000700070pp0070	Ljava/lang/String;
    //   427: invokevirtual 271	com/db/pwcc/dbmobile/model/banking/FinancialOverviewData:getAccountByID	(Ljava/lang/String;)Lcom/db/pwcc/dbmobile/model/banking/Account;
    //   430: astore 13
    //   432: aload_0
    //   433: getfield 42	uuuuuu/llllql:bpp0070ppp0070p0070	Lcom/db/pwcc/dbmobile/model/error/DbError;
    //   436: astore 14
    //   438: ldc 2
    //   440: ldc_w 293
    //   443: sipush 212
    //   446: iconst_4
    //   447: invokestatic 103	xxxxxx/uxxxxx:bb00620062bb0062b0062b0062	(Ljava/lang/String;CC)Ljava/lang/String;
    //   450: iconst_0
    //   451: anewarray 105	java/lang/Class
    //   454: invokevirtual 109	java/lang/Class:getMethod	(Ljava/lang/String;[Ljava/lang/Class;)Ljava/lang/reflect/Method;
    //   457: astore 15
    //   459: iconst_0
    //   460: anewarray 111	java/lang/Object
    //   463: astore 16
    //   465: aload 15
    //   467: aconst_null
    //   468: aload 16
    //   470: invokevirtual 117	java/lang/reflect/Method:invoke	(Ljava/lang/Object;[Ljava/lang/Object;)Ljava/lang/Object;
    //   473: astore 18
    //   475: aload 18
    //   477: checkcast 128	java/lang/Integer
    //   480: invokevirtual 131	java/lang/Integer:intValue	()I
    //   483: getstatic 157	uuuuuu/llllql:b0070p00700070pp0070p0070	I
    //   486: iadd
    //   487: istore 19
    //   489: ldc 2
    //   491: ldc_w 295
    //   494: bipush 120
    //   496: sipush 190
    //   499: iconst_0
    //   500: invokestatic 143	xxxxxx/uxxxxx:bbbb0062b0062b0062b0062	(Ljava/lang/String;CCC)Ljava/lang/String;
    //   503: iconst_0
    //   504: anewarray 105	java/lang/Class
    //   507: invokevirtual 109	java/lang/Class:getMethod	(Ljava/lang/String;[Ljava/lang/Class;)Ljava/lang/reflect/Method;
    //   510: astore 20
    //   512: iconst_0
    //   513: anewarray 111	java/lang/Object
    //   516: astore 21
    //   518: aload 20
    //   520: aconst_null
    //   521: aload 21
    //   523: invokevirtual 117	java/lang/reflect/Method:invoke	(Ljava/lang/Object;[Ljava/lang/Object;)Ljava/lang/Object;
    //   526: astore 23
    //   528: iload 19
    //   530: aload 23
    //   532: checkcast 128	java/lang/Integer
    //   535: invokevirtual 131	java/lang/Integer:intValue	()I
    //   538: imul
    //   539: getstatic 137	uuuuuu/llllql:bp007000700070pp0070p0070	I
    //   542: irem
    //   543: istore 24
    //   545: ldc 2
    //   547: ldc_w 297
    //   550: iconst_5
    //   551: iconst_2
    //   552: invokestatic 103	xxxxxx/uxxxxx:bb00620062bb0062b0062b0062	(Ljava/lang/String;CC)Ljava/lang/String;
    //   555: iconst_0
    //   556: anewarray 105	java/lang/Class
    //   559: invokevirtual 109	java/lang/Class:getMethod	(Ljava/lang/String;[Ljava/lang/Class;)Ljava/lang/reflect/Method;
    //   562: astore 25
    //   564: iconst_0
    //   565: anewarray 111	java/lang/Object
    //   568: astore 26
    //   570: aload 25
    //   572: aconst_null
    //   573: aload 26
    //   575: invokevirtual 117	java/lang/reflect/Method:invoke	(Ljava/lang/Object;[Ljava/lang/Object;)Ljava/lang/Object;
    //   578: astore 28
    //   580: iload 24
    //   582: aload 28
    //   584: checkcast 128	java/lang/Integer
    //   587: invokevirtual 131	java/lang/Integer:intValue	()I
    //   590: if_icmpeq +13 -> 603
    //   593: bipush 70
    //   595: putstatic 124	uuuuuu/llllql:b00700070p0070pp0070p0070	I
    //   598: bipush 70
    //   600: putstatic 147	uuuuuu/llllql:bpp00700070pp0070p0070	I
    //   603: aload 14
    //   605: ifnull +43 -> 648
    //   608: iconst_1
    //   609: istore 29
    //   611: aload_2
    //   612: aload 12
    //   614: aload 13
    //   616: iload 29
    //   618: invokeinterface 301 4 0
    //   623: return
    //   624: astore 22
    //   626: aload 22
    //   628: invokevirtual 163	java/lang/reflect/InvocationTargetException:getCause	()Ljava/lang/Throwable;
    //   631: athrow
    //   632: astore 27
    //   634: aload 27
    //   636: invokevirtual 163	java/lang/reflect/InvocationTargetException:getCause	()Ljava/lang/Throwable;
    //   639: athrow
    //   640: astore 17
    //   642: aload 17
    //   644: invokevirtual 163	java/lang/reflect/InvocationTargetException:getCause	()Ljava/lang/Throwable;
    //   647: athrow
    //   648: iconst_0
    //   649: istore 29
    //   651: goto -40 -> 611
    //   654: astore 5
    //   656: aload 5
    //   658: invokevirtual 163	java/lang/reflect/InvocationTargetException:getCause	()Ljava/lang/Throwable;
    //   661: athrow
    //   662: astore 10
    //   664: aload 10
    //   666: invokevirtual 163	java/lang/reflect/InvocationTargetException:getCause	()Ljava/lang/Throwable;
    //   669: athrow
    //   670: astore 36
    //   672: aload 36
    //   674: invokevirtual 163	java/lang/reflect/InvocationTargetException:getCause	()Ljava/lang/Throwable;
    //   677: athrow
    //   678: astore 40
    //   680: aload 40
    //   682: invokevirtual 163	java/lang/reflect/InvocationTargetException:getCause	()Ljava/lang/Throwable;
    //   685: athrow
    //   686: astore 32
    //   688: aload 32
    //   690: invokevirtual 163	java/lang/reflect/InvocationTargetException:getCause	()Ljava/lang/Throwable;
    //   693: athrow
    // Local variable table:
    //   start	length	slot	name	signature
    //   0	694	0	this	llllql
    //   181	8	1	i	int
    //   248	364	2	localLqqqll	llqqll.lqqqll
    //   268	8	3	localMethod1	java.lang.reflect.Method
    //   273	5	4	arrayOfObject1	Object[]
    //   654	3	5	localInvocationTargetException1	java.lang.reflect.InvocationTargetException
    //   282	3	6	localObject1	Object
    //   296	49	7	j	int
    //   316	9	8	localMethod2	java.lang.reflect.Method
    //   322	6	9	arrayOfObject2	Object[]
    //   662	3	10	localInvocationTargetException2	java.lang.reflect.InvocationTargetException
    //   332	5	11	localObject2	Object
    //   414	199	12	localTransactionsData	com.db.pwcc.dbmobile.model.banking.TransactionsData
    //   430	185	13	localAccount	com.db.pwcc.dbmobile.model.banking.Account
    //   436	168	14	localDbError	DbError
    //   457	9	15	localMethod3	java.lang.reflect.Method
    //   463	6	16	arrayOfObject3	Object[]
    //   640	3	17	localInvocationTargetException3	java.lang.reflect.InvocationTargetException
    //   473	3	18	localObject3	Object
    //   487	52	19	k	int
    //   510	9	20	localMethod4	java.lang.reflect.Method
    //   516	6	21	arrayOfObject4	Object[]
    //   624	3	22	localInvocationTargetException4	java.lang.reflect.InvocationTargetException
    //   526	5	23	localObject4	Object
    //   543	48	24	m	int
    //   562	9	25	localMethod5	java.lang.reflect.Method
    //   568	6	26	arrayOfObject5	Object[]
    //   632	3	27	localInvocationTargetException5	java.lang.reflect.InvocationTargetException
    //   578	5	28	localObject5	Object
    //   609	41	29	bool	boolean
    //   373	9	30	localMethod6	java.lang.reflect.Method
    //   379	6	31	arrayOfObject6	Object[]
    //   686	3	32	localInvocationTargetException6	java.lang.reflect.InvocationTargetException
    //   389	3	33	localObject6	Object
    //   49	9	34	localMethod7	java.lang.reflect.Method
    //   55	6	35	arrayOfObject7	Object[]
    //   670	3	36	localInvocationTargetException7	java.lang.reflect.InvocationTargetException
    //   65	3	37	localObject7	Object
    //   98	9	38	localMethod8	java.lang.reflect.Method
    //   104	6	39	arrayOfObject8	Object[]
    //   678	3	40	localInvocationTargetException8	java.lang.reflect.InvocationTargetException
    //   114	3	41	localObject8	Object
    // Exception table:
    //   from	to	target	type
    //   518	528	624	java/lang/reflect/InvocationTargetException
    //   570	580	632	java/lang/reflect/InvocationTargetException
    //   465	475	640	java/lang/reflect/InvocationTargetException
    //   275	284	654	java/lang/reflect/InvocationTargetException
    //   324	334	662	java/lang/reflect/InvocationTargetException
    //   57	67	670	java/lang/reflect/InvocationTargetException
    //   106	116	678	java/lang/reflect/InvocationTargetException
    //   381	391	686	java/lang/reflect/InvocationTargetException
  }
  
  /* Error */
  public void b00700070007000700070pp00700070p(com.db.pwcc.dbmobile.model.future_transfers.FutureDateTransfersResponse paramFutureDateTransfersResponse)
  {
    // Byte code:
    //   0: aload_0
    //   1: aconst_null
    //   2: putfield 42	uuuuuu/llllql:bpp0070ppp0070p0070	Lcom/db/pwcc/dbmobile/model/error/DbError;
    //   5: aload_1
    //   6: invokevirtual 309	com/db/pwcc/dbmobile/model/future_transfers/FutureDateTransfersResponse:getFutureDateTransfers	()Ljava/util/List;
    //   9: astore_2
    //   10: getstatic 124	uuuuuu/llllql:b00700070p0070pp0070p0070	I
    //   13: getstatic 157	uuuuuu/llllql:b0070p00700070pp0070p0070	I
    //   16: iadd
    //   17: getstatic 124	uuuuuu/llllql:b00700070p0070pp0070p0070	I
    //   20: imul
    //   21: istore_3
    //   22: ldc 2
    //   24: ldc_w 311
    //   27: iconst_1
    //   28: iconst_3
    //   29: invokestatic 103	xxxxxx/uxxxxx:bb00620062bb0062b0062b0062	(Ljava/lang/String;CC)Ljava/lang/String;
    //   32: iconst_0
    //   33: anewarray 105	java/lang/Class
    //   36: invokevirtual 109	java/lang/Class:getMethod	(Ljava/lang/String;[Ljava/lang/Class;)Ljava/lang/reflect/Method;
    //   39: astore 4
    //   41: iconst_0
    //   42: anewarray 111	java/lang/Object
    //   45: astore 5
    //   47: aload 4
    //   49: aconst_null
    //   50: aload 5
    //   52: invokevirtual 117	java/lang/reflect/Method:invoke	(Ljava/lang/Object;[Ljava/lang/Object;)Ljava/lang/Object;
    //   55: astore 7
    //   57: iload_3
    //   58: aload 7
    //   60: checkcast 128	java/lang/Integer
    //   63: invokevirtual 131	java/lang/Integer:intValue	()I
    //   66: irem
    //   67: getstatic 147	uuuuuu/llllql:bpp00700070pp0070p0070	I
    //   70: if_icmpeq +56 -> 126
    //   73: ldc 2
    //   75: ldc_w 313
    //   78: bipush 77
    //   80: bipush 23
    //   82: iconst_0
    //   83: invokestatic 143	xxxxxx/uxxxxx:bbbb0062b0062b0062b0062	(Ljava/lang/String;CCC)Ljava/lang/String;
    //   86: iconst_0
    //   87: anewarray 105	java/lang/Class
    //   90: invokevirtual 109	java/lang/Class:getMethod	(Ljava/lang/String;[Ljava/lang/Class;)Ljava/lang/reflect/Method;
    //   93: astore 46
    //   95: iconst_0
    //   96: anewarray 111	java/lang/Object
    //   99: astore 47
    //   101: aload 46
    //   103: aconst_null
    //   104: aload 47
    //   106: invokevirtual 117	java/lang/reflect/Method:invoke	(Ljava/lang/Object;[Ljava/lang/Object;)Ljava/lang/Object;
    //   109: astore 49
    //   111: aload 49
    //   113: checkcast 128	java/lang/Integer
    //   116: invokevirtual 131	java/lang/Integer:intValue	()I
    //   119: putstatic 124	uuuuuu/llllql:b00700070p0070pp0070p0070	I
    //   122: iconst_0
    //   123: putstatic 147	uuuuuu/llllql:bpp00700070pp0070p0070	I
    //   126: aload_2
    //   127: invokestatic 319	uuuuuu/eheeeh:boo006F006Fooooo006F	(Ljava/util/List;)Ljava/util/List;
    //   130: astore 8
    //   132: aload_0
    //   133: getfield 204	uuuuuu/llllql:bpp0070007000700070pp0070	Luuuuuu/heeeeh;
    //   136: invokevirtual 291	uuuuuu/heeeeh:boo006Foooooo006F	()Lcom/db/pwcc/dbmobile/model/banking/TransactionsData;
    //   139: ifnonnull +17 -> 156
    //   142: aload_0
    //   143: getfield 204	uuuuuu/llllql:bpp0070007000700070pp0070	Luuuuuu/heeeeh;
    //   146: new 321	com/db/pwcc/dbmobile/model/banking/TransactionsData
    //   149: dup
    //   150: invokespecial 322	com/db/pwcc/dbmobile/model/banking/TransactionsData:<init>	()V
    //   153: invokevirtual 326	uuuuuu/heeeeh:b006F006F006Foooooo006F	(Lcom/db/pwcc/dbmobile/model/banking/TransactionsData;)V
    //   156: aload_0
    //   157: getfield 204	uuuuuu/llllql:bpp0070007000700070pp0070	Luuuuuu/heeeeh;
    //   160: invokevirtual 291	uuuuuu/heeeeh:boo006Foooooo006F	()Lcom/db/pwcc/dbmobile/model/banking/TransactionsData;
    //   163: astore 9
    //   165: getstatic 124	uuuuuu/llllql:b00700070p0070pp0070p0070	I
    //   168: istore 10
    //   170: ldc 2
    //   172: ldc_w 328
    //   175: bipush 76
    //   177: iconst_3
    //   178: invokestatic 103	xxxxxx/uxxxxx:bb00620062bb0062b0062b0062	(Ljava/lang/String;CC)Ljava/lang/String;
    //   181: iconst_0
    //   182: anewarray 105	java/lang/Class
    //   185: invokevirtual 109	java/lang/Class:getMethod	(Ljava/lang/String;[Ljava/lang/Class;)Ljava/lang/reflect/Method;
    //   188: astore 11
    //   190: iconst_0
    //   191: anewarray 111	java/lang/Object
    //   194: astore 12
    //   196: aload 11
    //   198: aconst_null
    //   199: aload 12
    //   201: invokevirtual 117	java/lang/reflect/Method:invoke	(Ljava/lang/Object;[Ljava/lang/Object;)Ljava/lang/Object;
    //   204: astore 14
    //   206: iload 10
    //   208: aload 14
    //   210: checkcast 128	java/lang/Integer
    //   213: invokevirtual 131	java/lang/Integer:intValue	()I
    //   216: iadd
    //   217: getstatic 124	uuuuuu/llllql:b00700070p0070pp0070p0070	I
    //   220: imul
    //   221: getstatic 137	uuuuuu/llllql:bp007000700070pp0070p0070	I
    //   224: irem
    //   225: istore 15
    //   227: ldc 2
    //   229: ldc_w 330
    //   232: bipush 93
    //   234: bipush 74
    //   236: iconst_2
    //   237: invokestatic 143	xxxxxx/uxxxxx:bbbb0062b0062b0062b0062	(Ljava/lang/String;CCC)Ljava/lang/String;
    //   240: iconst_0
    //   241: anewarray 105	java/lang/Class
    //   244: invokevirtual 109	java/lang/Class:getMethod	(Ljava/lang/String;[Ljava/lang/Class;)Ljava/lang/reflect/Method;
    //   247: astore 16
    //   249: iconst_0
    //   250: anewarray 111	java/lang/Object
    //   253: astore 17
    //   255: aload 16
    //   257: aconst_null
    //   258: aload 17
    //   260: invokevirtual 117	java/lang/reflect/Method:invoke	(Ljava/lang/Object;[Ljava/lang/Object;)Ljava/lang/Object;
    //   263: astore 19
    //   265: iload 15
    //   267: aload 19
    //   269: checkcast 128	java/lang/Integer
    //   272: invokevirtual 131	java/lang/Integer:intValue	()I
    //   275: if_icmpeq +103 -> 378
    //   278: ldc 2
    //   280: ldc 126
    //   282: bipush 83
    //   284: sipush 145
    //   287: iconst_0
    //   288: invokestatic 143	xxxxxx/uxxxxx:bbbb0062b0062b0062b0062	(Ljava/lang/String;CCC)Ljava/lang/String;
    //   291: iconst_0
    //   292: anewarray 105	java/lang/Class
    //   295: invokevirtual 109	java/lang/Class:getMethod	(Ljava/lang/String;[Ljava/lang/Class;)Ljava/lang/reflect/Method;
    //   298: astore 38
    //   300: iconst_0
    //   301: anewarray 111	java/lang/Object
    //   304: astore 39
    //   306: aload 38
    //   308: aconst_null
    //   309: aload 39
    //   311: invokevirtual 117	java/lang/reflect/Method:invoke	(Ljava/lang/Object;[Ljava/lang/Object;)Ljava/lang/Object;
    //   314: astore 41
    //   316: aload 41
    //   318: checkcast 128	java/lang/Integer
    //   321: invokevirtual 131	java/lang/Integer:intValue	()I
    //   324: putstatic 124	uuuuuu/llllql:b00700070p0070pp0070p0070	I
    //   327: ldc 2
    //   329: ldc_w 332
    //   332: sipush 234
    //   335: sipush 128
    //   338: iconst_0
    //   339: invokestatic 143	xxxxxx/uxxxxx:bbbb0062b0062b0062b0062	(Ljava/lang/String;CCC)Ljava/lang/String;
    //   342: iconst_0
    //   343: anewarray 105	java/lang/Class
    //   346: invokevirtual 109	java/lang/Class:getMethod	(Ljava/lang/String;[Ljava/lang/Class;)Ljava/lang/reflect/Method;
    //   349: astore 42
    //   351: iconst_0
    //   352: anewarray 111	java/lang/Object
    //   355: astore 43
    //   357: aload 42
    //   359: aconst_null
    //   360: aload 43
    //   362: invokevirtual 117	java/lang/reflect/Method:invoke	(Ljava/lang/Object;[Ljava/lang/Object;)Ljava/lang/Object;
    //   365: astore 45
    //   367: aload 45
    //   369: checkcast 128	java/lang/Integer
    //   372: invokevirtual 131	java/lang/Integer:intValue	()I
    //   375: putstatic 147	uuuuuu/llllql:bpp00700070pp0070p0070	I
    //   378: aload 9
    //   380: aload 8
    //   382: invokevirtual 336	com/db/pwcc/dbmobile/model/banking/TransactionsData:setFutureTransactions	(Ljava/util/List;)V
    //   385: aload_0
    //   386: iconst_1
    //   387: putfield 44	uuuuuu/llllql:bppp0070pp0070p0070	Z
    //   390: ldc 2
    //   392: ldc_w 338
    //   395: sipush 172
    //   398: iconst_5
    //   399: invokestatic 103	xxxxxx/uxxxxx:bb00620062bb0062b0062b0062	(Ljava/lang/String;CC)Ljava/lang/String;
    //   402: iconst_0
    //   403: anewarray 105	java/lang/Class
    //   406: invokevirtual 109	java/lang/Class:getMethod	(Ljava/lang/String;[Ljava/lang/Class;)Ljava/lang/reflect/Method;
    //   409: astore 20
    //   411: iconst_0
    //   412: anewarray 111	java/lang/Object
    //   415: astore 21
    //   417: aload 20
    //   419: aload_0
    //   420: aload 21
    //   422: invokevirtual 117	java/lang/reflect/Method:invoke	(Ljava/lang/Object;[Ljava/lang/Object;)Ljava/lang/Object;
    //   425: pop
    //   426: getstatic 124	uuuuuu/llllql:b00700070p0070pp0070p0070	I
    //   429: getstatic 157	uuuuuu/llllql:b0070p00700070pp0070p0070	I
    //   432: iadd
    //   433: getstatic 124	uuuuuu/llllql:b00700070p0070pp0070p0070	I
    //   436: imul
    //   437: istore 24
    //   439: ldc 2
    //   441: ldc_w 340
    //   444: sipush 182
    //   447: iconst_0
    //   448: invokestatic 103	xxxxxx/uxxxxx:bb00620062bb0062b0062b0062	(Ljava/lang/String;CC)Ljava/lang/String;
    //   451: iconst_0
    //   452: anewarray 105	java/lang/Class
    //   455: invokevirtual 109	java/lang/Class:getMethod	(Ljava/lang/String;[Ljava/lang/Class;)Ljava/lang/reflect/Method;
    //   458: astore 25
    //   460: iconst_0
    //   461: anewarray 111	java/lang/Object
    //   464: astore 26
    //   466: aload 25
    //   468: aconst_null
    //   469: aload 26
    //   471: invokevirtual 117	java/lang/reflect/Method:invoke	(Ljava/lang/Object;[Ljava/lang/Object;)Ljava/lang/Object;
    //   474: astore 28
    //   476: aload 28
    //   478: checkcast 128	java/lang/Integer
    //   481: invokevirtual 131	java/lang/Integer:intValue	()I
    //   484: istore 29
    //   486: getstatic 124	uuuuuu/llllql:b00700070p0070pp0070p0070	I
    //   489: getstatic 157	uuuuuu/llllql:b0070p00700070pp0070p0070	I
    //   492: iadd
    //   493: getstatic 124	uuuuuu/llllql:b00700070p0070pp0070p0070	I
    //   496: imul
    //   497: getstatic 137	uuuuuu/llllql:bp007000700070pp0070p0070	I
    //   500: irem
    //   501: getstatic 147	uuuuuu/llllql:bpp00700070pp0070p0070	I
    //   504: if_icmpeq +56 -> 560
    //   507: ldc 2
    //   509: ldc_w 342
    //   512: sipush 136
    //   515: iconst_3
    //   516: invokestatic 103	xxxxxx/uxxxxx:bb00620062bb0062b0062b0062	(Ljava/lang/String;CC)Ljava/lang/String;
    //   519: iconst_0
    //   520: anewarray 105	java/lang/Class
    //   523: invokevirtual 109	java/lang/Class:getMethod	(Ljava/lang/String;[Ljava/lang/Class;)Ljava/lang/reflect/Method;
    //   526: astore 34
    //   528: iconst_0
    //   529: anewarray 111	java/lang/Object
    //   532: astore 35
    //   534: aload 34
    //   536: aconst_null
    //   537: aload 35
    //   539: invokevirtual 117	java/lang/reflect/Method:invoke	(Ljava/lang/Object;[Ljava/lang/Object;)Ljava/lang/Object;
    //   542: astore 37
    //   544: aload 37
    //   546: checkcast 128	java/lang/Integer
    //   549: invokevirtual 131	java/lang/Integer:intValue	()I
    //   552: putstatic 124	uuuuuu/llllql:b00700070p0070pp0070p0070	I
    //   555: bipush 32
    //   557: putstatic 147	uuuuuu/llllql:bpp00700070pp0070p0070	I
    //   560: iload 24
    //   562: iload 29
    //   564: irem
    //   565: getstatic 147	uuuuuu/llllql:bpp00700070pp0070p0070	I
    //   568: if_icmpeq +55 -> 623
    //   571: bipush 78
    //   573: putstatic 124	uuuuuu/llllql:b00700070p0070pp0070p0070	I
    //   576: ldc 2
    //   578: ldc_w 344
    //   581: bipush 11
    //   583: iconst_4
    //   584: invokestatic 103	xxxxxx/uxxxxx:bb00620062bb0062b0062b0062	(Ljava/lang/String;CC)Ljava/lang/String;
    //   587: iconst_0
    //   588: anewarray 105	java/lang/Class
    //   591: invokevirtual 109	java/lang/Class:getMethod	(Ljava/lang/String;[Ljava/lang/Class;)Ljava/lang/reflect/Method;
    //   594: astore 30
    //   596: iconst_0
    //   597: anewarray 111	java/lang/Object
    //   600: astore 31
    //   602: aload 30
    //   604: aconst_null
    //   605: aload 31
    //   607: invokevirtual 117	java/lang/reflect/Method:invoke	(Ljava/lang/Object;[Ljava/lang/Object;)Ljava/lang/Object;
    //   610: astore 33
    //   612: aload 33
    //   614: checkcast 128	java/lang/Integer
    //   617: invokevirtual 131	java/lang/Integer:intValue	()I
    //   620: putstatic 147	uuuuuu/llllql:bpp00700070pp0070p0070	I
    //   623: return
    //   624: astore 22
    //   626: aload 22
    //   628: invokevirtual 163	java/lang/reflect/InvocationTargetException:getCause	()Ljava/lang/Throwable;
    //   631: athrow
    //   632: astore 27
    //   634: aload 27
    //   636: invokevirtual 163	java/lang/reflect/InvocationTargetException:getCause	()Ljava/lang/Throwable;
    //   639: athrow
    //   640: astore 6
    //   642: aload 6
    //   644: invokevirtual 163	java/lang/reflect/InvocationTargetException:getCause	()Ljava/lang/Throwable;
    //   647: athrow
    //   648: astore 13
    //   650: aload 13
    //   652: invokevirtual 163	java/lang/reflect/InvocationTargetException:getCause	()Ljava/lang/Throwable;
    //   655: athrow
    //   656: astore 18
    //   658: aload 18
    //   660: invokevirtual 163	java/lang/reflect/InvocationTargetException:getCause	()Ljava/lang/Throwable;
    //   663: athrow
    //   664: astore 32
    //   666: aload 32
    //   668: invokevirtual 163	java/lang/reflect/InvocationTargetException:getCause	()Ljava/lang/Throwable;
    //   671: athrow
    //   672: astore 40
    //   674: aload 40
    //   676: invokevirtual 163	java/lang/reflect/InvocationTargetException:getCause	()Ljava/lang/Throwable;
    //   679: athrow
    //   680: astore 44
    //   682: aload 44
    //   684: invokevirtual 163	java/lang/reflect/InvocationTargetException:getCause	()Ljava/lang/Throwable;
    //   687: athrow
    //   688: astore 36
    //   690: aload 36
    //   692: invokevirtual 163	java/lang/reflect/InvocationTargetException:getCause	()Ljava/lang/Throwable;
    //   695: athrow
    //   696: astore 48
    //   698: aload 48
    //   700: invokevirtual 163	java/lang/reflect/InvocationTargetException:getCause	()Ljava/lang/Throwable;
    //   703: athrow
    // Local variable table:
    //   start	length	slot	name	signature
    //   0	704	0	this	llllql
    //   0	704	1	paramFutureDateTransfersResponse	com.db.pwcc.dbmobile.model.future_transfers.FutureDateTransfersResponse
    //   9	118	2	localList1	java.util.List
    //   21	46	3	i	int
    //   39	9	4	localMethod1	java.lang.reflect.Method
    //   45	6	5	arrayOfObject1	Object[]
    //   640	3	6	localInvocationTargetException1	java.lang.reflect.InvocationTargetException
    //   55	4	7	localObject1	Object
    //   130	251	8	localList2	java.util.List
    //   163	216	9	localTransactionsData	com.db.pwcc.dbmobile.model.banking.TransactionsData
    //   168	49	10	j	int
    //   188	9	11	localMethod2	java.lang.reflect.Method
    //   194	6	12	arrayOfObject2	Object[]
    //   648	3	13	localInvocationTargetException2	java.lang.reflect.InvocationTargetException
    //   204	5	14	localObject2	Object
    //   225	51	15	k	int
    //   247	9	16	localMethod3	java.lang.reflect.Method
    //   253	6	17	arrayOfObject3	Object[]
    //   656	3	18	localInvocationTargetException3	java.lang.reflect.InvocationTargetException
    //   263	5	19	localObject3	Object
    //   409	9	20	localMethod4	java.lang.reflect.Method
    //   415	6	21	arrayOfObject4	Object[]
    //   624	3	22	localInvocationTargetException4	java.lang.reflect.InvocationTargetException
    //   437	128	24	m	int
    //   458	9	25	localMethod5	java.lang.reflect.Method
    //   464	6	26	arrayOfObject5	Object[]
    //   632	3	27	localInvocationTargetException5	java.lang.reflect.InvocationTargetException
    //   474	3	28	localObject4	Object
    //   484	81	29	n	int
    //   594	9	30	localMethod6	java.lang.reflect.Method
    //   600	6	31	arrayOfObject6	Object[]
    //   664	3	32	localInvocationTargetException6	java.lang.reflect.InvocationTargetException
    //   610	3	33	localObject5	Object
    //   526	9	34	localMethod7	java.lang.reflect.Method
    //   532	6	35	arrayOfObject7	Object[]
    //   688	3	36	localInvocationTargetException7	java.lang.reflect.InvocationTargetException
    //   542	3	37	localObject6	Object
    //   298	9	38	localMethod8	java.lang.reflect.Method
    //   304	6	39	arrayOfObject8	Object[]
    //   672	3	40	localInvocationTargetException8	java.lang.reflect.InvocationTargetException
    //   314	3	41	localObject7	Object
    //   349	9	42	localMethod9	java.lang.reflect.Method
    //   355	6	43	arrayOfObject9	Object[]
    //   680	3	44	localInvocationTargetException9	java.lang.reflect.InvocationTargetException
    //   365	3	45	localObject8	Object
    //   93	9	46	localMethod10	java.lang.reflect.Method
    //   99	6	47	arrayOfObject10	Object[]
    //   696	3	48	localInvocationTargetException10	java.lang.reflect.InvocationTargetException
    //   109	3	49	localObject9	Object
    // Exception table:
    //   from	to	target	type
    //   417	426	624	java/lang/reflect/InvocationTargetException
    //   466	476	632	java/lang/reflect/InvocationTargetException
    //   47	57	640	java/lang/reflect/InvocationTargetException
    //   196	206	648	java/lang/reflect/InvocationTargetException
    //   255	265	656	java/lang/reflect/InvocationTargetException
    //   602	612	664	java/lang/reflect/InvocationTargetException
    //   306	316	672	java/lang/reflect/InvocationTargetException
    //   357	367	680	java/lang/reflect/InvocationTargetException
    //   534	544	688	java/lang/reflect/InvocationTargetException
    //   101	111	696	java/lang/reflect/InvocationTargetException
  }
  
  /* Error */
  public void b00700070p007000700070p00700070p(com.db.pwcc.dbmobile.model.banking.TransactionsData paramTransactionsData)
  {
    // Byte code:
    //   0: aload_1
    //   1: ifnonnull +561 -> 562
    //   4: aconst_null
    //   5: getstatic 351	com/db/pwcc/dbmobile/model/error/DbErrorCode:SERVER_ERROR	Lcom/db/pwcc/dbmobile/model/error/DbErrorCode;
    //   8: invokestatic 357	com/db/pwcc/dbmobile/model/error/DbError:createError	(Ljava/lang/String;Lcom/db/pwcc/dbmobile/model/error/DbErrorCode;)Lcom/db/pwcc/dbmobile/model/error/DbError;
    //   11: astore 44
    //   13: ldc 2
    //   15: ldc_w 359
    //   18: sipush 174
    //   21: iconst_2
    //   22: invokestatic 103	xxxxxx/uxxxxx:bb00620062bb0062b0062b0062	(Ljava/lang/String;CC)Ljava/lang/String;
    //   25: iconst_1
    //   26: anewarray 105	java/lang/Class
    //   29: dup
    //   30: iconst_0
    //   31: ldc_w 353
    //   34: aastore
    //   35: invokevirtual 109	java/lang/Class:getMethod	(Ljava/lang/String;[Ljava/lang/Class;)Ljava/lang/reflect/Method;
    //   38: astore 45
    //   40: iconst_1
    //   41: anewarray 111	java/lang/Object
    //   44: dup
    //   45: iconst_0
    //   46: aload 44
    //   48: aastore
    //   49: astore 46
    //   51: aload 45
    //   53: aload_0
    //   54: aload 46
    //   56: invokevirtual 117	java/lang/reflect/Method:invoke	(Ljava/lang/Object;[Ljava/lang/Object;)Ljava/lang/Object;
    //   59: pop
    //   60: return
    //   61: aload_0
    //   62: getfield 204	uuuuuu/llllql:bpp0070007000700070pp0070	Luuuuuu/heeeeh;
    //   65: invokevirtual 291	uuuuuu/heeeeh:boo006Foooooo006F	()Lcom/db/pwcc/dbmobile/model/banking/TransactionsData;
    //   68: invokevirtual 362	com/db/pwcc/dbmobile/model/banking/TransactionsData:getFutureTransactions	()Ljava/util/List;
    //   71: astore 34
    //   73: getstatic 124	uuuuuu/llllql:b00700070p0070pp0070p0070	I
    //   76: istore 35
    //   78: iload 35
    //   80: iload 35
    //   82: getstatic 157	uuuuuu/llllql:b0070p00700070pp0070p0070	I
    //   85: iadd
    //   86: imul
    //   87: getstatic 137	uuuuuu/llllql:bp007000700070pp0070p0070	I
    //   90: irem
    //   91: tableswitch	default:+17->108, 0:+70->161
    //   108: bipush 56
    //   110: putstatic 124	uuuuuu/llllql:b00700070p0070pp0070p0070	I
    //   113: ldc 2
    //   115: ldc_w 364
    //   118: sipush 148
    //   121: iconst_2
    //   122: invokestatic 103	xxxxxx/uxxxxx:bb00620062bb0062b0062b0062	(Ljava/lang/String;CC)Ljava/lang/String;
    //   125: iconst_0
    //   126: anewarray 105	java/lang/Class
    //   129: invokevirtual 109	java/lang/Class:getMethod	(Ljava/lang/String;[Ljava/lang/Class;)Ljava/lang/reflect/Method;
    //   132: astore 36
    //   134: iconst_0
    //   135: anewarray 111	java/lang/Object
    //   138: astore 37
    //   140: aload 36
    //   142: aconst_null
    //   143: aload 37
    //   145: invokevirtual 117	java/lang/reflect/Method:invoke	(Ljava/lang/Object;[Ljava/lang/Object;)Ljava/lang/Object;
    //   148: astore 39
    //   150: aload 39
    //   152: checkcast 128	java/lang/Integer
    //   155: invokevirtual 131	java/lang/Integer:intValue	()I
    //   158: putstatic 147	uuuuuu/llllql:bpp00700070pp0070p0070	I
    //   161: aload_0
    //   162: getfield 204	uuuuuu/llllql:bpp0070007000700070pp0070	Luuuuuu/heeeeh;
    //   165: aload_1
    //   166: invokevirtual 326	uuuuuu/heeeeh:b006F006F006Foooooo006F	(Lcom/db/pwcc/dbmobile/model/banking/TransactionsData;)V
    //   169: aload_0
    //   170: getfield 204	uuuuuu/llllql:bpp0070007000700070pp0070	Luuuuuu/heeeeh;
    //   173: invokevirtual 291	uuuuuu/heeeeh:boo006Foooooo006F	()Lcom/db/pwcc/dbmobile/model/banking/TransactionsData;
    //   176: aload 34
    //   178: invokevirtual 336	com/db/pwcc/dbmobile/model/banking/TransactionsData:setFutureTransactions	(Ljava/util/List;)V
    //   181: aload_0
    //   182: getfield 204	uuuuuu/llllql:bpp0070007000700070pp0070	Luuuuuu/heeeeh;
    //   185: invokevirtual 291	uuuuuu/heeeeh:boo006Foooooo006F	()Lcom/db/pwcc/dbmobile/model/banking/TransactionsData;
    //   188: astore 12
    //   190: getstatic 124	uuuuuu/llllql:b00700070p0070pp0070p0070	I
    //   193: getstatic 157	uuuuuu/llllql:b0070p00700070pp0070p0070	I
    //   196: iadd
    //   197: getstatic 124	uuuuuu/llllql:b00700070p0070pp0070p0070	I
    //   200: imul
    //   201: getstatic 137	uuuuuu/llllql:bp007000700070pp0070p0070	I
    //   204: irem
    //   205: getstatic 147	uuuuuu/llllql:bpp00700070pp0070p0070	I
    //   208: if_icmpeq +55 -> 263
    //   211: ldc 2
    //   213: ldc_w 366
    //   216: bipush 109
    //   218: iconst_2
    //   219: invokestatic 103	xxxxxx/uxxxxx:bb00620062bb0062b0062b0062	(Ljava/lang/String;CC)Ljava/lang/String;
    //   222: iconst_0
    //   223: anewarray 105	java/lang/Class
    //   226: invokevirtual 109	java/lang/Class:getMethod	(Ljava/lang/String;[Ljava/lang/Class;)Ljava/lang/reflect/Method;
    //   229: astore 30
    //   231: iconst_0
    //   232: anewarray 111	java/lang/Object
    //   235: astore 31
    //   237: aload 30
    //   239: aconst_null
    //   240: aload 31
    //   242: invokevirtual 117	java/lang/reflect/Method:invoke	(Ljava/lang/Object;[Ljava/lang/Object;)Ljava/lang/Object;
    //   245: astore 33
    //   247: aload 33
    //   249: checkcast 128	java/lang/Integer
    //   252: invokevirtual 131	java/lang/Integer:intValue	()I
    //   255: putstatic 124	uuuuuu/llllql:b00700070p0070pp0070p0070	I
    //   258: bipush 94
    //   260: putstatic 147	uuuuuu/llllql:bpp00700070pp0070p0070	I
    //   263: aload 12
    //   265: invokevirtual 370	com/db/pwcc/dbmobile/model/banking/TransactionsData:getAccount	()Lcom/db/pwcc/dbmobile/model/banking/Account;
    //   268: invokevirtual 375	com/db/pwcc/dbmobile/model/banking/Account:getBaseCurrency	()Ljava/lang/String;
    //   271: ifnonnull +26 -> 297
    //   274: aload_0
    //   275: getfield 204	uuuuuu/llllql:bpp0070007000700070pp0070	Luuuuuu/heeeeh;
    //   278: invokevirtual 291	uuuuuu/heeeeh:boo006Foooooo006F	()Lcom/db/pwcc/dbmobile/model/banking/TransactionsData;
    //   281: invokevirtual 370	com/db/pwcc/dbmobile/model/banking/TransactionsData:getAccount	()Lcom/db/pwcc/dbmobile/model/banking/Account;
    //   284: aload_0
    //   285: getfield 204	uuuuuu/llllql:bpp0070007000700070pp0070	Luuuuuu/heeeeh;
    //   288: invokevirtual 291	uuuuuu/heeeeh:boo006Foooooo006F	()Lcom/db/pwcc/dbmobile/model/banking/TransactionsData;
    //   291: invokevirtual 376	com/db/pwcc/dbmobile/model/banking/TransactionsData:getBaseCurrency	()Ljava/lang/String;
    //   294: invokevirtual 379	com/db/pwcc/dbmobile/model/banking/Account:setBaseCurrency	(Ljava/lang/String;)V
    //   297: aload_0
    //   298: iconst_1
    //   299: putfield 46	uuuuuu/llllql:b0070pp0070pp0070p0070	Z
    //   302: ldc 2
    //   304: ldc_w 381
    //   307: bipush 43
    //   309: iconst_3
    //   310: invokestatic 103	xxxxxx/uxxxxx:bb00620062bb0062b0062b0062	(Ljava/lang/String;CC)Ljava/lang/String;
    //   313: iconst_0
    //   314: anewarray 105	java/lang/Class
    //   317: invokevirtual 109	java/lang/Class:getMethod	(Ljava/lang/String;[Ljava/lang/Class;)Ljava/lang/reflect/Method;
    //   320: astore 13
    //   322: iconst_0
    //   323: anewarray 111	java/lang/Object
    //   326: astore 14
    //   328: aload 13
    //   330: aload_0
    //   331: aload 14
    //   333: invokevirtual 117	java/lang/reflect/Method:invoke	(Ljava/lang/Object;[Ljava/lang/Object;)Ljava/lang/Object;
    //   336: pop
    //   337: ldc 2
    //   339: ldc_w 383
    //   342: sipush 236
    //   345: iconst_4
    //   346: invokestatic 103	xxxxxx/uxxxxx:bb00620062bb0062b0062b0062	(Ljava/lang/String;CC)Ljava/lang/String;
    //   349: iconst_0
    //   350: anewarray 105	java/lang/Class
    //   353: invokevirtual 109	java/lang/Class:getMethod	(Ljava/lang/String;[Ljava/lang/Class;)Ljava/lang/reflect/Method;
    //   356: astore 17
    //   358: iconst_0
    //   359: anewarray 111	java/lang/Object
    //   362: astore 18
    //   364: aload 17
    //   366: aconst_null
    //   367: aload 18
    //   369: invokevirtual 117	java/lang/reflect/Method:invoke	(Ljava/lang/Object;[Ljava/lang/Object;)Ljava/lang/Object;
    //   372: astore 20
    //   374: aload 20
    //   376: checkcast 128	java/lang/Integer
    //   379: invokevirtual 131	java/lang/Integer:intValue	()I
    //   382: getstatic 157	uuuuuu/llllql:b0070p00700070pp0070p0070	I
    //   385: iadd
    //   386: istore 21
    //   388: ldc 2
    //   390: ldc_w 385
    //   393: sipush 143
    //   396: iconst_2
    //   397: invokestatic 103	xxxxxx/uxxxxx:bb00620062bb0062b0062b0062	(Ljava/lang/String;CC)Ljava/lang/String;
    //   400: iconst_0
    //   401: anewarray 105	java/lang/Class
    //   404: invokevirtual 109	java/lang/Class:getMethod	(Ljava/lang/String;[Ljava/lang/Class;)Ljava/lang/reflect/Method;
    //   407: astore 22
    //   409: iconst_0
    //   410: anewarray 111	java/lang/Object
    //   413: astore 23
    //   415: aload 22
    //   417: aconst_null
    //   418: aload 23
    //   420: invokevirtual 117	java/lang/reflect/Method:invoke	(Ljava/lang/Object;[Ljava/lang/Object;)Ljava/lang/Object;
    //   423: astore 25
    //   425: iload 21
    //   427: aload 25
    //   429: checkcast 128	java/lang/Integer
    //   432: invokevirtual 131	java/lang/Integer:intValue	()I
    //   435: imul
    //   436: getstatic 137	uuuuuu/llllql:bp007000700070pp0070p0070	I
    //   439: irem
    //   440: getstatic 147	uuuuuu/llllql:bpp00700070pp0070p0070	I
    //   443: if_icmpeq +56 -> 499
    //   446: ldc 2
    //   448: ldc_w 387
    //   451: bipush 66
    //   453: bipush 94
    //   455: iconst_3
    //   456: invokestatic 143	xxxxxx/uxxxxx:bbbb0062b0062b0062b0062	(Ljava/lang/String;CCC)Ljava/lang/String;
    //   459: iconst_0
    //   460: anewarray 105	java/lang/Class
    //   463: invokevirtual 109	java/lang/Class:getMethod	(Ljava/lang/String;[Ljava/lang/Class;)Ljava/lang/reflect/Method;
    //   466: astore 26
    //   468: iconst_0
    //   469: anewarray 111	java/lang/Object
    //   472: astore 27
    //   474: aload 26
    //   476: aconst_null
    //   477: aload 27
    //   479: invokevirtual 117	java/lang/reflect/Method:invoke	(Ljava/lang/Object;[Ljava/lang/Object;)Ljava/lang/Object;
    //   482: astore 29
    //   484: aload 29
    //   486: checkcast 128	java/lang/Integer
    //   489: invokevirtual 131	java/lang/Integer:intValue	()I
    //   492: putstatic 124	uuuuuu/llllql:b00700070p0070pp0070p0070	I
    //   495: iconst_5
    //   496: putstatic 147	uuuuuu/llllql:bpp00700070pp0070p0070	I
    //   499: aload_0
    //   500: new 389	uuuuuu/hhhhhe
    //   503: dup
    //   504: aload_1
    //   505: invokespecial 391	uuuuuu/hhhhhe:<init>	(Lcom/db/pwcc/dbmobile/model/banking/TransactionsData;)V
    //   508: invokevirtual 395	uuuuuu/hhhhhe:boo006F006F006F006F006F006F006Fo	()Lrx/Observable;
    //   511: putfield 397	uuuuuu/llllql:b0070ppppp0070p0070	Lrx/Observable;
    //   514: aload_0
    //   515: aload_0
    //   516: getfield 397	uuuuuu/llllql:b0070ppppp0070p0070	Lrx/Observable;
    //   519: invokestatic 403	rx/schedulers/Schedulers:computation	()Lrx/Scheduler;
    //   522: invokevirtual 409	rx/Observable:subscribeOn	(Lrx/Scheduler;)Lrx/Observable;
    //   525: invokestatic 414	rx/android/schedulers/AndroidSchedulers:mainThread	()Lrx/Scheduler;
    //   528: invokevirtual 417	rx/Observable:observeOn	(Lrx/Scheduler;)Lrx/Observable;
    //   531: new 419	uuuuuu/llllql$1
    //   534: dup
    //   535: aload_0
    //   536: invokespecial 422	uuuuuu/llllql$1:<init>	(Luuuuuu/llllql;)V
    //   539: new 424	uuuuuu/llllql$2
    //   542: dup
    //   543: aload_0
    //   544: invokespecial 425	uuuuuu/llllql$2:<init>	(Luuuuuu/llllql;)V
    //   547: invokevirtual 429	rx/Observable:subscribe	(Lrx/functions/Action1;Lrx/functions/Action1;)Lrx/Subscription;
    //   550: putfield 431	uuuuuu/llllql:b007000700070ppp0070p0070	Lrx/Subscription;
    //   553: return
    //   554: astore 47
    //   556: aload 47
    //   558: invokevirtual 163	java/lang/reflect/InvocationTargetException:getCause	()Ljava/lang/Throwable;
    //   561: athrow
    //   562: getstatic 124	uuuuuu/llllql:b00700070p0070pp0070p0070	I
    //   565: istore_2
    //   566: ldc 2
    //   568: ldc_w 433
    //   571: bipush 61
    //   573: iconst_2
    //   574: invokestatic 103	xxxxxx/uxxxxx:bb00620062bb0062b0062b0062	(Ljava/lang/String;CC)Ljava/lang/String;
    //   577: iconst_0
    //   578: anewarray 105	java/lang/Class
    //   581: invokevirtual 109	java/lang/Class:getMethod	(Ljava/lang/String;[Ljava/lang/Class;)Ljava/lang/reflect/Method;
    //   584: astore_3
    //   585: iconst_0
    //   586: anewarray 111	java/lang/Object
    //   589: astore 4
    //   591: aload_3
    //   592: aconst_null
    //   593: aload 4
    //   595: invokevirtual 117	java/lang/reflect/Method:invoke	(Ljava/lang/Object;[Ljava/lang/Object;)Ljava/lang/Object;
    //   598: astore 6
    //   600: iload_2
    //   601: iload_2
    //   602: aload 6
    //   604: checkcast 128	java/lang/Integer
    //   607: invokevirtual 131	java/lang/Integer:intValue	()I
    //   610: iadd
    //   611: imul
    //   612: istore 7
    //   614: ldc 2
    //   616: ldc_w 435
    //   619: bipush 101
    //   621: iconst_0
    //   622: invokestatic 103	xxxxxx/uxxxxx:bb00620062bb0062b0062b0062	(Ljava/lang/String;CC)Ljava/lang/String;
    //   625: iconst_0
    //   626: anewarray 105	java/lang/Class
    //   629: invokevirtual 109	java/lang/Class:getMethod	(Ljava/lang/String;[Ljava/lang/Class;)Ljava/lang/reflect/Method;
    //   632: astore 8
    //   634: iconst_0
    //   635: anewarray 111	java/lang/Object
    //   638: astore 9
    //   640: aload 8
    //   642: aconst_null
    //   643: aload 9
    //   645: invokevirtual 117	java/lang/reflect/Method:invoke	(Ljava/lang/Object;[Ljava/lang/Object;)Ljava/lang/Object;
    //   648: astore 11
    //   650: iload 7
    //   652: aload 11
    //   654: checkcast 128	java/lang/Integer
    //   657: invokevirtual 131	java/lang/Integer:intValue	()I
    //   660: irem
    //   661: tableswitch	default:+19->680, 0:+72->733
    //   680: ldc 2
    //   682: ldc_w 437
    //   685: sipush 150
    //   688: iconst_5
    //   689: invokestatic 103	xxxxxx/uxxxxx:bb00620062bb0062b0062b0062	(Ljava/lang/String;CC)Ljava/lang/String;
    //   692: iconst_0
    //   693: anewarray 105	java/lang/Class
    //   696: invokevirtual 109	java/lang/Class:getMethod	(Ljava/lang/String;[Ljava/lang/Class;)Ljava/lang/reflect/Method;
    //   699: astore 40
    //   701: iconst_0
    //   702: anewarray 111	java/lang/Object
    //   705: astore 41
    //   707: aload 40
    //   709: aconst_null
    //   710: aload 41
    //   712: invokevirtual 117	java/lang/reflect/Method:invoke	(Ljava/lang/Object;[Ljava/lang/Object;)Ljava/lang/Object;
    //   715: astore 43
    //   717: aload 43
    //   719: checkcast 128	java/lang/Integer
    //   722: invokevirtual 131	java/lang/Integer:intValue	()I
    //   725: putstatic 124	uuuuuu/llllql:b00700070p0070pp0070p0070	I
    //   728: bipush 95
    //   730: putstatic 147	uuuuuu/llllql:bpp00700070pp0070p0070	I
    //   733: aload_0
    //   734: aconst_null
    //   735: putfield 40	uuuuuu/llllql:bp0070p0070pp0070p0070	Lcom/db/pwcc/dbmobile/model/error/DbError;
    //   738: aload_0
    //   739: getfield 204	uuuuuu/llllql:bpp0070007000700070pp0070	Luuuuuu/heeeeh;
    //   742: invokevirtual 291	uuuuuu/heeeeh:boo006Foooooo006F	()Lcom/db/pwcc/dbmobile/model/banking/TransactionsData;
    //   745: ifnonnull -684 -> 61
    //   748: aload_0
    //   749: getfield 204	uuuuuu/llllql:bpp0070007000700070pp0070	Luuuuuu/heeeeh;
    //   752: aload_1
    //   753: invokevirtual 326	uuuuuu/heeeeh:b006F006F006Foooooo006F	(Lcom/db/pwcc/dbmobile/model/banking/TransactionsData;)V
    //   756: goto -575 -> 181
    //   759: astore 19
    //   761: aload 19
    //   763: invokevirtual 163	java/lang/reflect/InvocationTargetException:getCause	()Ljava/lang/Throwable;
    //   766: athrow
    //   767: astore 24
    //   769: aload 24
    //   771: invokevirtual 163	java/lang/reflect/InvocationTargetException:getCause	()Ljava/lang/Throwable;
    //   774: athrow
    //   775: astore 5
    //   777: aload 5
    //   779: invokevirtual 163	java/lang/reflect/InvocationTargetException:getCause	()Ljava/lang/Throwable;
    //   782: athrow
    //   783: astore 10
    //   785: aload 10
    //   787: invokevirtual 163	java/lang/reflect/InvocationTargetException:getCause	()Ljava/lang/Throwable;
    //   790: athrow
    //   791: astore 15
    //   793: aload 15
    //   795: invokevirtual 163	java/lang/reflect/InvocationTargetException:getCause	()Ljava/lang/Throwable;
    //   798: athrow
    //   799: astore 28
    //   801: aload 28
    //   803: invokevirtual 163	java/lang/reflect/InvocationTargetException:getCause	()Ljava/lang/Throwable;
    //   806: athrow
    //   807: astore 38
    //   809: aload 38
    //   811: invokevirtual 163	java/lang/reflect/InvocationTargetException:getCause	()Ljava/lang/Throwable;
    //   814: athrow
    //   815: astore 32
    //   817: aload 32
    //   819: invokevirtual 163	java/lang/reflect/InvocationTargetException:getCause	()Ljava/lang/Throwable;
    //   822: athrow
    //   823: astore 42
    //   825: aload 42
    //   827: invokevirtual 163	java/lang/reflect/InvocationTargetException:getCause	()Ljava/lang/Throwable;
    //   830: athrow
    // Local variable table:
    //   start	length	slot	name	signature
    //   0	831	0	this	llllql
    //   0	831	1	paramTransactionsData	com.db.pwcc.dbmobile.model.banking.TransactionsData
    //   565	47	2	i	int
    //   584	8	3	localMethod1	java.lang.reflect.Method
    //   589	5	4	arrayOfObject1	Object[]
    //   775	3	5	localInvocationTargetException1	java.lang.reflect.InvocationTargetException
    //   598	5	6	localObject1	Object
    //   612	49	7	j	int
    //   632	9	8	localMethod2	java.lang.reflect.Method
    //   638	6	9	arrayOfObject2	Object[]
    //   783	3	10	localInvocationTargetException2	java.lang.reflect.InvocationTargetException
    //   648	5	11	localObject2	Object
    //   188	76	12	localTransactionsData	com.db.pwcc.dbmobile.model.banking.TransactionsData
    //   320	9	13	localMethod3	java.lang.reflect.Method
    //   326	6	14	arrayOfObject3	Object[]
    //   791	3	15	localInvocationTargetException3	java.lang.reflect.InvocationTargetException
    //   356	9	17	localMethod4	java.lang.reflect.Method
    //   362	6	18	arrayOfObject4	Object[]
    //   759	3	19	localInvocationTargetException4	java.lang.reflect.InvocationTargetException
    //   372	3	20	localObject3	Object
    //   386	50	21	k	int
    //   407	9	22	localMethod5	java.lang.reflect.Method
    //   413	6	23	arrayOfObject5	Object[]
    //   767	3	24	localInvocationTargetException5	java.lang.reflect.InvocationTargetException
    //   423	5	25	localObject4	Object
    //   466	9	26	localMethod6	java.lang.reflect.Method
    //   472	6	27	arrayOfObject6	Object[]
    //   799	3	28	localInvocationTargetException6	java.lang.reflect.InvocationTargetException
    //   482	3	29	localObject5	Object
    //   229	9	30	localMethod7	java.lang.reflect.Method
    //   235	6	31	arrayOfObject7	Object[]
    //   815	3	32	localInvocationTargetException7	java.lang.reflect.InvocationTargetException
    //   245	3	33	localObject6	Object
    //   71	106	34	localList	java.util.List
    //   76	11	35	m	int
    //   132	9	36	localMethod8	java.lang.reflect.Method
    //   138	6	37	arrayOfObject8	Object[]
    //   807	3	38	localInvocationTargetException8	java.lang.reflect.InvocationTargetException
    //   148	3	39	localObject7	Object
    //   699	9	40	localMethod9	java.lang.reflect.Method
    //   705	6	41	arrayOfObject9	Object[]
    //   823	3	42	localInvocationTargetException9	java.lang.reflect.InvocationTargetException
    //   715	3	43	localObject8	Object
    //   11	36	44	localDbError	DbError
    //   38	14	45	localMethod10	java.lang.reflect.Method
    //   49	6	46	arrayOfObject10	Object[]
    //   554	3	47	localInvocationTargetException10	java.lang.reflect.InvocationTargetException
    // Exception table:
    //   from	to	target	type
    //   51	60	554	java/lang/reflect/InvocationTargetException
    //   364	374	759	java/lang/reflect/InvocationTargetException
    //   415	425	767	java/lang/reflect/InvocationTargetException
    //   591	600	775	java/lang/reflect/InvocationTargetException
    //   640	650	783	java/lang/reflect/InvocationTargetException
    //   328	337	791	java/lang/reflect/InvocationTargetException
    //   474	484	799	java/lang/reflect/InvocationTargetException
    //   140	150	807	java/lang/reflect/InvocationTargetException
    //   237	247	815	java/lang/reflect/InvocationTargetException
    //   707	717	823	java/lang/reflect/InvocationTargetException
  }
  
  /* Error */
  public void ba006100610061a0061aa0061a()
  {
    // Byte code:
    //   0: aload_0
    //   1: getfield 431	uuuuuu/llllql:b007000700070ppp0070p0070	Lrx/Subscription;
    //   4: ifnull +535 -> 539
    //   7: getstatic 124	uuuuuu/llllql:b00700070p0070pp0070p0070	I
    //   10: getstatic 157	uuuuuu/llllql:b0070p00700070pp0070p0070	I
    //   13: iadd
    //   14: getstatic 124	uuuuuu/llllql:b00700070p0070pp0070p0070	I
    //   17: imul
    //   18: istore_1
    //   19: ldc 2
    //   21: ldc_w 440
    //   24: sipush 177
    //   27: bipush 75
    //   29: iconst_2
    //   30: invokestatic 143	xxxxxx/uxxxxx:bbbb0062b0062b0062b0062	(Ljava/lang/String;CCC)Ljava/lang/String;
    //   33: iconst_0
    //   34: anewarray 105	java/lang/Class
    //   37: invokevirtual 109	java/lang/Class:getMethod	(Ljava/lang/String;[Ljava/lang/Class;)Ljava/lang/reflect/Method;
    //   40: astore_2
    //   41: iconst_0
    //   42: anewarray 111	java/lang/Object
    //   45: astore_3
    //   46: aload_2
    //   47: aconst_null
    //   48: aload_3
    //   49: invokevirtual 117	java/lang/reflect/Method:invoke	(Ljava/lang/Object;[Ljava/lang/Object;)Ljava/lang/Object;
    //   52: astore 5
    //   54: iload_1
    //   55: aload 5
    //   57: checkcast 128	java/lang/Integer
    //   60: invokevirtual 131	java/lang/Integer:intValue	()I
    //   63: irem
    //   64: getstatic 147	uuuuuu/llllql:bpp00700070pp0070p0070	I
    //   67: if_icmpeq +98 -> 165
    //   70: ldc 2
    //   72: ldc_w 442
    //   75: bipush 89
    //   77: iconst_1
    //   78: invokestatic 103	xxxxxx/uxxxxx:bb00620062bb0062b0062b0062	(Ljava/lang/String;CC)Ljava/lang/String;
    //   81: iconst_0
    //   82: anewarray 105	java/lang/Class
    //   85: invokevirtual 109	java/lang/Class:getMethod	(Ljava/lang/String;[Ljava/lang/Class;)Ljava/lang/reflect/Method;
    //   88: astore 29
    //   90: iconst_0
    //   91: anewarray 111	java/lang/Object
    //   94: astore 30
    //   96: aload 29
    //   98: aconst_null
    //   99: aload 30
    //   101: invokevirtual 117	java/lang/reflect/Method:invoke	(Ljava/lang/Object;[Ljava/lang/Object;)Ljava/lang/Object;
    //   104: astore 32
    //   106: aload 32
    //   108: checkcast 128	java/lang/Integer
    //   111: invokevirtual 131	java/lang/Integer:intValue	()I
    //   114: putstatic 124	uuuuuu/llllql:b00700070p0070pp0070p0070	I
    //   117: ldc 2
    //   119: ldc_w 444
    //   122: sipush 240
    //   125: iconst_1
    //   126: invokestatic 103	xxxxxx/uxxxxx:bb00620062bb0062b0062b0062	(Ljava/lang/String;CC)Ljava/lang/String;
    //   129: iconst_0
    //   130: anewarray 105	java/lang/Class
    //   133: invokevirtual 109	java/lang/Class:getMethod	(Ljava/lang/String;[Ljava/lang/Class;)Ljava/lang/reflect/Method;
    //   136: astore 33
    //   138: iconst_0
    //   139: anewarray 111	java/lang/Object
    //   142: astore 34
    //   144: aload 33
    //   146: aconst_null
    //   147: aload 34
    //   149: invokevirtual 117	java/lang/reflect/Method:invoke	(Ljava/lang/Object;[Ljava/lang/Object;)Ljava/lang/Object;
    //   152: astore 36
    //   154: aload 36
    //   156: checkcast 128	java/lang/Integer
    //   159: invokevirtual 131	java/lang/Integer:intValue	()I
    //   162: putstatic 147	uuuuuu/llllql:bpp00700070pp0070p0070	I
    //   165: ldc 2
    //   167: ldc_w 446
    //   170: bipush 56
    //   172: bipush 60
    //   174: iconst_2
    //   175: invokestatic 143	xxxxxx/uxxxxx:bbbb0062b0062b0062b0062	(Ljava/lang/String;CCC)Ljava/lang/String;
    //   178: iconst_0
    //   179: anewarray 105	java/lang/Class
    //   182: invokevirtual 109	java/lang/Class:getMethod	(Ljava/lang/String;[Ljava/lang/Class;)Ljava/lang/reflect/Method;
    //   185: astore 6
    //   187: iconst_0
    //   188: anewarray 111	java/lang/Object
    //   191: astore 7
    //   193: aload 6
    //   195: aconst_null
    //   196: aload 7
    //   198: invokevirtual 117	java/lang/reflect/Method:invoke	(Ljava/lang/Object;[Ljava/lang/Object;)Ljava/lang/Object;
    //   201: astore 9
    //   203: aload 9
    //   205: checkcast 128	java/lang/Integer
    //   208: invokevirtual 131	java/lang/Integer:intValue	()I
    //   211: istore 10
    //   213: iload 10
    //   215: iload 10
    //   217: getstatic 157	uuuuuu/llllql:b0070p00700070pp0070p0070	I
    //   220: iadd
    //   221: imul
    //   222: getstatic 137	uuuuuu/llllql:bp007000700070pp0070p0070	I
    //   225: irem
    //   226: tableswitch	default:+18->244, 0:+292->518
    //   244: getstatic 124	uuuuuu/llllql:b00700070p0070pp0070p0070	I
    //   247: istore 11
    //   249: iload 11
    //   251: iload 11
    //   253: getstatic 157	uuuuuu/llllql:b0070p00700070pp0070p0070	I
    //   256: iadd
    //   257: imul
    //   258: getstatic 137	uuuuuu/llllql:bp007000700070pp0070p0070	I
    //   261: irem
    //   262: tableswitch	default:+18->280, 0:+70->332
    //   280: ldc 2
    //   282: ldc -103
    //   284: sipush 187
    //   287: iconst_1
    //   288: invokestatic 103	xxxxxx/uxxxxx:bb00620062bb0062b0062b0062	(Ljava/lang/String;CC)Ljava/lang/String;
    //   291: iconst_0
    //   292: anewarray 105	java/lang/Class
    //   295: invokevirtual 109	java/lang/Class:getMethod	(Ljava/lang/String;[Ljava/lang/Class;)Ljava/lang/reflect/Method;
    //   298: astore 25
    //   300: iconst_0
    //   301: anewarray 111	java/lang/Object
    //   304: astore 26
    //   306: aload 25
    //   308: aconst_null
    //   309: aload 26
    //   311: invokevirtual 117	java/lang/reflect/Method:invoke	(Ljava/lang/Object;[Ljava/lang/Object;)Ljava/lang/Object;
    //   314: astore 28
    //   316: aload 28
    //   318: checkcast 128	java/lang/Integer
    //   321: invokevirtual 131	java/lang/Integer:intValue	()I
    //   324: putstatic 124	uuuuuu/llllql:b00700070p0070pp0070p0070	I
    //   327: bipush 64
    //   329: putstatic 147	uuuuuu/llllql:bpp00700070pp0070p0070	I
    //   332: bipush 7
    //   334: putstatic 124	uuuuuu/llllql:b00700070p0070pp0070p0070	I
    //   337: getstatic 124	uuuuuu/llllql:b00700070p0070pp0070p0070	I
    //   340: istore 12
    //   342: iload 12
    //   344: iload 12
    //   346: getstatic 157	uuuuuu/llllql:b0070p00700070pp0070p0070	I
    //   349: iadd
    //   350: imul
    //   351: getstatic 137	uuuuuu/llllql:bp007000700070pp0070p0070	I
    //   354: irem
    //   355: tableswitch	default:+17->372, 0:+115->470
    //   372: ldc 2
    //   374: ldc_w 448
    //   377: bipush 38
    //   379: iconst_4
    //   380: invokestatic 103	xxxxxx/uxxxxx:bb00620062bb0062b0062b0062	(Ljava/lang/String;CC)Ljava/lang/String;
    //   383: iconst_0
    //   384: anewarray 105	java/lang/Class
    //   387: invokevirtual 109	java/lang/Class:getMethod	(Ljava/lang/String;[Ljava/lang/Class;)Ljava/lang/reflect/Method;
    //   390: astore 17
    //   392: iconst_0
    //   393: anewarray 111	java/lang/Object
    //   396: astore 18
    //   398: aload 17
    //   400: aconst_null
    //   401: aload 18
    //   403: invokevirtual 117	java/lang/reflect/Method:invoke	(Ljava/lang/Object;[Ljava/lang/Object;)Ljava/lang/Object;
    //   406: astore 20
    //   408: aload 20
    //   410: checkcast 128	java/lang/Integer
    //   413: invokevirtual 131	java/lang/Integer:intValue	()I
    //   416: putstatic 124	uuuuuu/llllql:b00700070p0070pp0070p0070	I
    //   419: ldc 2
    //   421: ldc_w 450
    //   424: sipush 183
    //   427: sipush 157
    //   430: iconst_1
    //   431: invokestatic 143	xxxxxx/uxxxxx:bbbb0062b0062b0062b0062	(Ljava/lang/String;CCC)Ljava/lang/String;
    //   434: iconst_0
    //   435: anewarray 105	java/lang/Class
    //   438: invokevirtual 109	java/lang/Class:getMethod	(Ljava/lang/String;[Ljava/lang/Class;)Ljava/lang/reflect/Method;
    //   441: astore 21
    //   443: iconst_0
    //   444: anewarray 111	java/lang/Object
    //   447: astore 22
    //   449: aload 21
    //   451: aconst_null
    //   452: aload 22
    //   454: invokevirtual 117	java/lang/reflect/Method:invoke	(Ljava/lang/Object;[Ljava/lang/Object;)Ljava/lang/Object;
    //   457: astore 24
    //   459: aload 24
    //   461: checkcast 128	java/lang/Integer
    //   464: invokevirtual 131	java/lang/Integer:intValue	()I
    //   467: putstatic 147	uuuuuu/llllql:bpp00700070pp0070p0070	I
    //   470: ldc 2
    //   472: ldc_w 452
    //   475: sipush 138
    //   478: iconst_1
    //   479: invokestatic 103	xxxxxx/uxxxxx:bb00620062bb0062b0062b0062	(Ljava/lang/String;CC)Ljava/lang/String;
    //   482: iconst_0
    //   483: anewarray 105	java/lang/Class
    //   486: invokevirtual 109	java/lang/Class:getMethod	(Ljava/lang/String;[Ljava/lang/Class;)Ljava/lang/reflect/Method;
    //   489: astore 13
    //   491: iconst_0
    //   492: anewarray 111	java/lang/Object
    //   495: astore 14
    //   497: aload 13
    //   499: aconst_null
    //   500: aload 14
    //   502: invokevirtual 117	java/lang/reflect/Method:invoke	(Ljava/lang/Object;[Ljava/lang/Object;)Ljava/lang/Object;
    //   505: astore 16
    //   507: aload 16
    //   509: checkcast 128	java/lang/Integer
    //   512: invokevirtual 131	java/lang/Integer:intValue	()I
    //   515: putstatic 147	uuuuuu/llllql:bpp00700070pp0070p0070	I
    //   518: aload_0
    //   519: getfield 431	uuuuuu/llllql:b007000700070ppp0070p0070	Lrx/Subscription;
    //   522: invokeinterface 457 1 0
    //   527: ifne +12 -> 539
    //   530: aload_0
    //   531: getfield 431	uuuuuu/llllql:b007000700070ppp0070p0070	Lrx/Subscription;
    //   534: invokeinterface 460 1 0
    //   539: aload_0
    //   540: invokespecial 462	uuuuuu/qqqqll:ba006100610061a0061aa0061a	()V
    //   543: return
    //   544: astore 27
    //   546: aload 27
    //   548: invokevirtual 163	java/lang/reflect/InvocationTargetException:getCause	()Ljava/lang/Throwable;
    //   551: athrow
    //   552: astore 4
    //   554: aload 4
    //   556: invokevirtual 163	java/lang/reflect/InvocationTargetException:getCause	()Ljava/lang/Throwable;
    //   559: athrow
    //   560: astore 15
    //   562: aload 15
    //   564: invokevirtual 163	java/lang/reflect/InvocationTargetException:getCause	()Ljava/lang/Throwable;
    //   567: athrow
    //   568: astore 8
    //   570: aload 8
    //   572: invokevirtual 163	java/lang/reflect/InvocationTargetException:getCause	()Ljava/lang/Throwable;
    //   575: athrow
    //   576: astore 31
    //   578: aload 31
    //   580: invokevirtual 163	java/lang/reflect/InvocationTargetException:getCause	()Ljava/lang/Throwable;
    //   583: athrow
    //   584: astore 35
    //   586: aload 35
    //   588: invokevirtual 163	java/lang/reflect/InvocationTargetException:getCause	()Ljava/lang/Throwable;
    //   591: athrow
    //   592: astore 19
    //   594: aload 19
    //   596: invokevirtual 163	java/lang/reflect/InvocationTargetException:getCause	()Ljava/lang/Throwable;
    //   599: athrow
    //   600: astore 23
    //   602: aload 23
    //   604: invokevirtual 163	java/lang/reflect/InvocationTargetException:getCause	()Ljava/lang/Throwable;
    //   607: athrow
    // Local variable table:
    //   start	length	slot	name	signature
    //   0	608	0	this	llllql
    //   18	46	1	i	int
    //   40	7	2	localMethod1	java.lang.reflect.Method
    //   45	4	3	arrayOfObject1	Object[]
    //   552	3	4	localInvocationTargetException1	java.lang.reflect.InvocationTargetException
    //   52	4	5	localObject1	Object
    //   185	9	6	localMethod2	java.lang.reflect.Method
    //   191	6	7	arrayOfObject2	Object[]
    //   568	3	8	localInvocationTargetException2	java.lang.reflect.InvocationTargetException
    //   201	3	9	localObject2	Object
    //   211	11	10	j	int
    //   247	11	11	k	int
    //   340	11	12	m	int
    //   489	9	13	localMethod3	java.lang.reflect.Method
    //   495	6	14	arrayOfObject3	Object[]
    //   560	3	15	localInvocationTargetException3	java.lang.reflect.InvocationTargetException
    //   505	3	16	localObject3	Object
    //   390	9	17	localMethod4	java.lang.reflect.Method
    //   396	6	18	arrayOfObject4	Object[]
    //   592	3	19	localInvocationTargetException4	java.lang.reflect.InvocationTargetException
    //   406	3	20	localObject4	Object
    //   441	9	21	localMethod5	java.lang.reflect.Method
    //   447	6	22	arrayOfObject5	Object[]
    //   600	3	23	localInvocationTargetException5	java.lang.reflect.InvocationTargetException
    //   457	3	24	localObject5	Object
    //   298	9	25	localMethod6	java.lang.reflect.Method
    //   304	6	26	arrayOfObject6	Object[]
    //   544	3	27	localInvocationTargetException6	java.lang.reflect.InvocationTargetException
    //   314	3	28	localObject6	Object
    //   88	9	29	localMethod7	java.lang.reflect.Method
    //   94	6	30	arrayOfObject7	Object[]
    //   576	3	31	localInvocationTargetException7	java.lang.reflect.InvocationTargetException
    //   104	3	32	localObject7	Object
    //   136	9	33	localMethod8	java.lang.reflect.Method
    //   142	6	34	arrayOfObject8	Object[]
    //   584	3	35	localInvocationTargetException8	java.lang.reflect.InvocationTargetException
    //   152	3	36	localObject8	Object
    // Exception table:
    //   from	to	target	type
    //   306	316	544	java/lang/reflect/InvocationTargetException
    //   46	54	552	java/lang/reflect/InvocationTargetException
    //   497	507	560	java/lang/reflect/InvocationTargetException
    //   193	203	568	java/lang/reflect/InvocationTargetException
    //   96	106	576	java/lang/reflect/InvocationTargetException
    //   144	154	584	java/lang/reflect/InvocationTargetException
    //   398	408	592	java/lang/reflect/InvocationTargetException
    //   449	459	600	java/lang/reflect/InvocationTargetException
  }
  
  /* Error */
  public void bo006Fo006F006F006Fo006Foo(BalanceHistory paramBalanceHistory)
  {
    // Byte code:
    //   0: aload_0
    //   1: invokevirtual 247	uuuuuu/llllql:bkk006Bk006Bk006Bk006Bk	()Z
    //   4: ifne +4 -> 8
    //   7: return
    //   8: ldc 2
    //   10: ldc_w 466
    //   13: bipush 76
    //   15: bipush 68
    //   17: iconst_2
    //   18: invokestatic 143	xxxxxx/uxxxxx:bbbb0062b0062b0062b0062	(Ljava/lang/String;CCC)Ljava/lang/String;
    //   21: iconst_0
    //   22: anewarray 105	java/lang/Class
    //   25: invokevirtual 109	java/lang/Class:getMethod	(Ljava/lang/String;[Ljava/lang/Class;)Ljava/lang/reflect/Method;
    //   28: astore_2
    //   29: iconst_0
    //   30: anewarray 111	java/lang/Object
    //   33: astore_3
    //   34: aload_2
    //   35: aconst_null
    //   36: aload_3
    //   37: invokevirtual 117	java/lang/reflect/Method:invoke	(Ljava/lang/Object;[Ljava/lang/Object;)Ljava/lang/Object;
    //   40: astore 5
    //   42: aload 5
    //   44: checkcast 128	java/lang/Integer
    //   47: invokevirtual 131	java/lang/Integer:intValue	()I
    //   50: istore 6
    //   52: iload 6
    //   54: iload 6
    //   56: getstatic 157	uuuuuu/llllql:b0070p00700070pp0070p0070	I
    //   59: iadd
    //   60: imul
    //   61: getstatic 137	uuuuuu/llllql:bp007000700070pp0070p0070	I
    //   64: irem
    //   65: tableswitch	default:+19->84, 0:+73->138
    //   84: bipush 84
    //   86: putstatic 124	uuuuuu/llllql:b00700070p0070pp0070p0070	I
    //   89: ldc 2
    //   91: ldc -73
    //   93: sipush 149
    //   96: bipush 20
    //   98: iconst_3
    //   99: invokestatic 143	xxxxxx/uxxxxx:bbbb0062b0062b0062b0062	(Ljava/lang/String;CCC)Ljava/lang/String;
    //   102: iconst_0
    //   103: anewarray 105	java/lang/Class
    //   106: invokevirtual 109	java/lang/Class:getMethod	(Ljava/lang/String;[Ljava/lang/Class;)Ljava/lang/reflect/Method;
    //   109: astore 33
    //   111: iconst_0
    //   112: anewarray 111	java/lang/Object
    //   115: astore 34
    //   117: aload 33
    //   119: aconst_null
    //   120: aload 34
    //   122: invokevirtual 117	java/lang/reflect/Method:invoke	(Ljava/lang/Object;[Ljava/lang/Object;)Ljava/lang/Object;
    //   125: astore 36
    //   127: aload 36
    //   129: checkcast 128	java/lang/Integer
    //   132: invokevirtual 131	java/lang/Integer:intValue	()I
    //   135: putstatic 147	uuuuuu/llllql:bpp00700070pp0070p0070	I
    //   138: aload_0
    //   139: getfield 255	uuuuuu/llllql:bnnnnn006E006E006En	Luuuuuu/ttssst$tsssst;
    //   142: checkcast 257	uuuuuu/llqqll$lqqqll
    //   145: invokeinterface 278 1 0
    //   150: aload_0
    //   151: getfield 204	uuuuuu/llllql:bpp0070007000700070pp0070	Luuuuuu/heeeeh;
    //   154: astore 7
    //   156: getstatic 124	uuuuuu/llllql:b00700070p0070pp0070p0070	I
    //   159: getstatic 157	uuuuuu/llllql:b0070p00700070pp0070p0070	I
    //   162: iadd
    //   163: getstatic 124	uuuuuu/llllql:b00700070p0070pp0070p0070	I
    //   166: imul
    //   167: istore 8
    //   169: ldc 2
    //   171: ldc_w 468
    //   174: sipush 252
    //   177: iconst_5
    //   178: invokestatic 103	xxxxxx/uxxxxx:bb00620062bb0062b0062b0062	(Ljava/lang/String;CC)Ljava/lang/String;
    //   181: iconst_0
    //   182: anewarray 105	java/lang/Class
    //   185: invokevirtual 109	java/lang/Class:getMethod	(Ljava/lang/String;[Ljava/lang/Class;)Ljava/lang/reflect/Method;
    //   188: astore 9
    //   190: iconst_0
    //   191: anewarray 111	java/lang/Object
    //   194: astore 10
    //   196: aload 9
    //   198: aconst_null
    //   199: aload 10
    //   201: invokevirtual 117	java/lang/reflect/Method:invoke	(Ljava/lang/Object;[Ljava/lang/Object;)Ljava/lang/Object;
    //   204: astore 12
    //   206: iload 8
    //   208: aload 12
    //   210: checkcast 128	java/lang/Integer
    //   213: invokevirtual 131	java/lang/Integer:intValue	()I
    //   216: irem
    //   217: getstatic 147	uuuuuu/llllql:bpp00700070pp0070p0070	I
    //   220: if_icmpeq +55 -> 275
    //   223: bipush 69
    //   225: putstatic 124	uuuuuu/llllql:b00700070p0070pp0070p0070	I
    //   228: ldc 2
    //   230: ldc_w 470
    //   233: bipush 29
    //   235: iconst_1
    //   236: invokestatic 103	xxxxxx/uxxxxx:bb00620062bb0062b0062b0062	(Ljava/lang/String;CC)Ljava/lang/String;
    //   239: iconst_0
    //   240: anewarray 105	java/lang/Class
    //   243: invokevirtual 109	java/lang/Class:getMethod	(Ljava/lang/String;[Ljava/lang/Class;)Ljava/lang/reflect/Method;
    //   246: astore 29
    //   248: iconst_0
    //   249: anewarray 111	java/lang/Object
    //   252: astore 30
    //   254: aload 29
    //   256: aconst_null
    //   257: aload 30
    //   259: invokevirtual 117	java/lang/reflect/Method:invoke	(Ljava/lang/Object;[Ljava/lang/Object;)Ljava/lang/Object;
    //   262: astore 32
    //   264: aload 32
    //   266: checkcast 128	java/lang/Integer
    //   269: invokevirtual 131	java/lang/Integer:intValue	()I
    //   272: putstatic 147	uuuuuu/llllql:bpp00700070pp0070p0070	I
    //   275: getstatic 124	uuuuuu/llllql:b00700070p0070pp0070p0070	I
    //   278: getstatic 157	uuuuuu/llllql:b0070p00700070pp0070p0070	I
    //   281: iadd
    //   282: getstatic 124	uuuuuu/llllql:b00700070p0070pp0070p0070	I
    //   285: imul
    //   286: getstatic 137	uuuuuu/llllql:bp007000700070pp0070p0070	I
    //   289: irem
    //   290: getstatic 147	uuuuuu/llllql:bpp00700070pp0070p0070	I
    //   293: if_icmpeq +13 -> 306
    //   296: bipush 81
    //   298: putstatic 124	uuuuuu/llllql:b00700070p0070pp0070p0070	I
    //   301: bipush 31
    //   303: putstatic 147	uuuuuu/llllql:bpp00700070pp0070p0070	I
    //   306: aload 7
    //   308: aload_1
    //   309: invokevirtual 473	uuuuuu/heeeeh:b006Fo006Foooooo006F	(Lcom/db/pwcc/dbmobile/data/model/banking/BalanceHistory;)V
    //   312: aload_0
    //   313: getfield 204	uuuuuu/llllql:bpp0070007000700070pp0070	Luuuuuu/heeeeh;
    //   316: invokevirtual 210	uuuuuu/heeeeh:bo006Fooooooo006F	()Lcom/db/pwcc/dbmobile/data/model/banking/BalanceHistory;
    //   319: invokevirtual 476	com/db/pwcc/dbmobile/data/model/banking/BalanceHistory:transformBalanceHistoryGraphData	()V
    //   322: aload_0
    //   323: getfield 255	uuuuuu/llllql:bnnnnn006E006E006En	Luuuuuu/ttssst$tsssst;
    //   326: astore 13
    //   328: getstatic 124	uuuuuu/llllql:b00700070p0070pp0070p0070	I
    //   331: istore 14
    //   333: iload 14
    //   335: iload 14
    //   337: getstatic 157	uuuuuu/llllql:b0070p00700070pp0070p0070	I
    //   340: iadd
    //   341: imul
    //   342: istore 15
    //   344: ldc 2
    //   346: ldc_w 478
    //   349: sipush 217
    //   352: sipush 151
    //   355: iconst_1
    //   356: invokestatic 143	xxxxxx/uxxxxx:bbbb0062b0062b0062b0062	(Ljava/lang/String;CCC)Ljava/lang/String;
    //   359: iconst_0
    //   360: anewarray 105	java/lang/Class
    //   363: invokevirtual 109	java/lang/Class:getMethod	(Ljava/lang/String;[Ljava/lang/Class;)Ljava/lang/reflect/Method;
    //   366: astore 16
    //   368: iconst_0
    //   369: anewarray 111	java/lang/Object
    //   372: astore 17
    //   374: aload 16
    //   376: aconst_null
    //   377: aload 17
    //   379: invokevirtual 117	java/lang/reflect/Method:invoke	(Ljava/lang/Object;[Ljava/lang/Object;)Ljava/lang/Object;
    //   382: astore 19
    //   384: iload 15
    //   386: aload 19
    //   388: checkcast 128	java/lang/Integer
    //   391: invokevirtual 131	java/lang/Integer:intValue	()I
    //   394: irem
    //   395: tableswitch	default:+17->412, 0:+69->464
    //   412: bipush 90
    //   414: putstatic 124	uuuuuu/llllql:b00700070p0070pp0070p0070	I
    //   417: ldc 2
    //   419: ldc_w 480
    //   422: bipush 25
    //   424: iconst_3
    //   425: invokestatic 103	xxxxxx/uxxxxx:bb00620062bb0062b0062b0062	(Ljava/lang/String;CC)Ljava/lang/String;
    //   428: iconst_0
    //   429: anewarray 105	java/lang/Class
    //   432: invokevirtual 109	java/lang/Class:getMethod	(Ljava/lang/String;[Ljava/lang/Class;)Ljava/lang/reflect/Method;
    //   435: astore 25
    //   437: iconst_0
    //   438: anewarray 111	java/lang/Object
    //   441: astore 26
    //   443: aload 25
    //   445: aconst_null
    //   446: aload 26
    //   448: invokevirtual 117	java/lang/reflect/Method:invoke	(Ljava/lang/Object;[Ljava/lang/Object;)Ljava/lang/Object;
    //   451: astore 28
    //   453: aload 28
    //   455: checkcast 128	java/lang/Integer
    //   458: invokevirtual 131	java/lang/Integer:intValue	()I
    //   461: putstatic 147	uuuuuu/llllql:bpp00700070pp0070p0070	I
    //   464: aload 13
    //   466: checkcast 257	uuuuuu/llqqll$lqqqll
    //   469: astore 20
    //   471: ldc 2
    //   473: ldc_w 482
    //   476: sipush 151
    //   479: iconst_5
    //   480: invokestatic 103	xxxxxx/uxxxxx:bb00620062bb0062b0062b0062	(Ljava/lang/String;CC)Ljava/lang/String;
    //   483: iconst_0
    //   484: anewarray 105	java/lang/Class
    //   487: invokevirtual 109	java/lang/Class:getMethod	(Ljava/lang/String;[Ljava/lang/Class;)Ljava/lang/reflect/Method;
    //   490: astore 21
    //   492: iconst_0
    //   493: anewarray 111	java/lang/Object
    //   496: astore 22
    //   498: aload 21
    //   500: aload_0
    //   501: aload 22
    //   503: invokevirtual 117	java/lang/reflect/Method:invoke	(Ljava/lang/Object;[Ljava/lang/Object;)Ljava/lang/Object;
    //   506: astore 24
    //   508: aload 20
    //   510: aload 24
    //   512: checkcast 484	java/lang/Boolean
    //   515: invokevirtual 487	java/lang/Boolean:booleanValue	()Z
    //   518: aload_1
    //   519: invokeinterface 491 3 0
    //   524: return
    //   525: astore 23
    //   527: aload 23
    //   529: invokevirtual 163	java/lang/reflect/InvocationTargetException:getCause	()Ljava/lang/Throwable;
    //   532: athrow
    //   533: astore 11
    //   535: aload 11
    //   537: invokevirtual 163	java/lang/reflect/InvocationTargetException:getCause	()Ljava/lang/Throwable;
    //   540: athrow
    //   541: astore 18
    //   543: aload 18
    //   545: invokevirtual 163	java/lang/reflect/InvocationTargetException:getCause	()Ljava/lang/Throwable;
    //   548: athrow
    //   549: astore 4
    //   551: aload 4
    //   553: invokevirtual 163	java/lang/reflect/InvocationTargetException:getCause	()Ljava/lang/Throwable;
    //   556: athrow
    //   557: astore 35
    //   559: aload 35
    //   561: invokevirtual 163	java/lang/reflect/InvocationTargetException:getCause	()Ljava/lang/Throwable;
    //   564: athrow
    //   565: astore 27
    //   567: aload 27
    //   569: invokevirtual 163	java/lang/reflect/InvocationTargetException:getCause	()Ljava/lang/Throwable;
    //   572: athrow
    //   573: astore 31
    //   575: aload 31
    //   577: invokevirtual 163	java/lang/reflect/InvocationTargetException:getCause	()Ljava/lang/Throwable;
    //   580: athrow
    // Local variable table:
    //   start	length	slot	name	signature
    //   0	581	0	this	llllql
    //   0	581	1	paramBalanceHistory	BalanceHistory
    //   28	7	2	localMethod1	java.lang.reflect.Method
    //   33	4	3	arrayOfObject1	Object[]
    //   549	3	4	localInvocationTargetException1	java.lang.reflect.InvocationTargetException
    //   40	3	5	localObject1	Object
    //   50	11	6	i	int
    //   154	153	7	localHeeeeh	heeeeh
    //   167	50	8	j	int
    //   188	9	9	localMethod2	java.lang.reflect.Method
    //   194	6	10	arrayOfObject2	Object[]
    //   533	3	11	localInvocationTargetException2	java.lang.reflect.InvocationTargetException
    //   204	5	12	localObject2	Object
    //   326	139	13	localTsssst	ttssst.tsssst
    //   331	11	14	k	int
    //   342	53	15	m	int
    //   366	9	16	localMethod3	java.lang.reflect.Method
    //   372	6	17	arrayOfObject3	Object[]
    //   541	3	18	localInvocationTargetException3	java.lang.reflect.InvocationTargetException
    //   382	5	19	localObject3	Object
    //   469	40	20	localLqqqll	llqqll.lqqqll
    //   490	9	21	localMethod4	java.lang.reflect.Method
    //   496	6	22	arrayOfObject4	Object[]
    //   525	3	23	localInvocationTargetException4	java.lang.reflect.InvocationTargetException
    //   506	5	24	localObject4	Object
    //   435	9	25	localMethod5	java.lang.reflect.Method
    //   441	6	26	arrayOfObject5	Object[]
    //   565	3	27	localInvocationTargetException5	java.lang.reflect.InvocationTargetException
    //   451	3	28	localObject5	Object
    //   246	9	29	localMethod6	java.lang.reflect.Method
    //   252	6	30	arrayOfObject6	Object[]
    //   573	3	31	localInvocationTargetException6	java.lang.reflect.InvocationTargetException
    //   262	3	32	localObject6	Object
    //   109	9	33	localMethod7	java.lang.reflect.Method
    //   115	6	34	arrayOfObject7	Object[]
    //   557	3	35	localInvocationTargetException7	java.lang.reflect.InvocationTargetException
    //   125	3	36	localObject7	Object
    // Exception table:
    //   from	to	target	type
    //   498	508	525	java/lang/reflect/InvocationTargetException
    //   196	206	533	java/lang/reflect/InvocationTargetException
    //   374	384	541	java/lang/reflect/InvocationTargetException
    //   34	42	549	java/lang/reflect/InvocationTargetException
    //   117	127	557	java/lang/reflect/InvocationTargetException
    //   443	453	565	java/lang/reflect/InvocationTargetException
    //   254	264	573	java/lang/reflect/InvocationTargetException
  }
  
  /* Error */
  public void bp0070007000700070pp00700070p(DbError paramDbError)
  {
    // Byte code:
    //   0: getstatic 124	uuuuuu/llllql:b00700070p0070pp0070p0070	I
    //   3: getstatic 157	uuuuuu/llllql:b0070p00700070pp0070p0070	I
    //   6: iadd
    //   7: getstatic 124	uuuuuu/llllql:b00700070p0070pp0070p0070	I
    //   10: imul
    //   11: getstatic 137	uuuuuu/llllql:bp007000700070pp0070p0070	I
    //   14: irem
    //   15: getstatic 147	uuuuuu/llllql:bpp00700070pp0070p0070	I
    //   18: if_icmpeq +98 -> 116
    //   21: ldc 2
    //   23: ldc_w 494
    //   26: bipush 59
    //   28: iconst_3
    //   29: invokestatic 103	xxxxxx/uxxxxx:bb00620062bb0062b0062b0062	(Ljava/lang/String;CC)Ljava/lang/String;
    //   32: iconst_0
    //   33: anewarray 105	java/lang/Class
    //   36: invokevirtual 109	java/lang/Class:getMethod	(Ljava/lang/String;[Ljava/lang/Class;)Ljava/lang/reflect/Method;
    //   39: astore 36
    //   41: iconst_0
    //   42: anewarray 111	java/lang/Object
    //   45: astore 37
    //   47: aload 36
    //   49: aconst_null
    //   50: aload 37
    //   52: invokevirtual 117	java/lang/reflect/Method:invoke	(Ljava/lang/Object;[Ljava/lang/Object;)Ljava/lang/Object;
    //   55: astore 39
    //   57: aload 39
    //   59: checkcast 128	java/lang/Integer
    //   62: invokevirtual 131	java/lang/Integer:intValue	()I
    //   65: putstatic 124	uuuuuu/llllql:b00700070p0070pp0070p0070	I
    //   68: ldc 2
    //   70: ldc_w 496
    //   73: sipush 210
    //   76: iconst_5
    //   77: invokestatic 103	xxxxxx/uxxxxx:bb00620062bb0062b0062b0062	(Ljava/lang/String;CC)Ljava/lang/String;
    //   80: iconst_0
    //   81: anewarray 105	java/lang/Class
    //   84: invokevirtual 109	java/lang/Class:getMethod	(Ljava/lang/String;[Ljava/lang/Class;)Ljava/lang/reflect/Method;
    //   87: astore 40
    //   89: iconst_0
    //   90: anewarray 111	java/lang/Object
    //   93: astore 41
    //   95: aload 40
    //   97: aconst_null
    //   98: aload 41
    //   100: invokevirtual 117	java/lang/reflect/Method:invoke	(Ljava/lang/Object;[Ljava/lang/Object;)Ljava/lang/Object;
    //   103: astore 43
    //   105: aload 43
    //   107: checkcast 128	java/lang/Integer
    //   110: invokevirtual 131	java/lang/Integer:intValue	()I
    //   113: putstatic 147	uuuuuu/llllql:bpp00700070pp0070p0070	I
    //   116: aload_0
    //   117: aload_1
    //   118: putfield 42	uuuuuu/llllql:bpp0070ppp0070p0070	Lcom/db/pwcc/dbmobile/model/error/DbError;
    //   121: getstatic 499	com/db/pwcc/dbmobile/model/error/DbErrorCode:NO_INTERNET_ERROR	Lcom/db/pwcc/dbmobile/model/error/DbErrorCode;
    //   124: aload_1
    //   125: invokevirtual 503	com/db/pwcc/dbmobile/model/error/DbError:getDbCode	()Lcom/db/pwcc/dbmobile/model/error/DbErrorCode;
    //   128: if_acmpeq +187 -> 315
    //   131: getstatic 506	com/db/pwcc/dbmobile/model/error/DbErrorCode:INSECURE_CONNECTION_ERROR	Lcom/db/pwcc/dbmobile/model/error/DbErrorCode;
    //   134: astore 21
    //   136: aload_1
    //   137: invokevirtual 503	com/db/pwcc/dbmobile/model/error/DbError:getDbCode	()Lcom/db/pwcc/dbmobile/model/error/DbErrorCode;
    //   140: astore 22
    //   142: ldc 2
    //   144: ldc_w 508
    //   147: bipush 110
    //   149: iconst_4
    //   150: invokestatic 103	xxxxxx/uxxxxx:bb00620062bb0062b0062b0062	(Ljava/lang/String;CC)Ljava/lang/String;
    //   153: iconst_0
    //   154: anewarray 105	java/lang/Class
    //   157: invokevirtual 109	java/lang/Class:getMethod	(Ljava/lang/String;[Ljava/lang/Class;)Ljava/lang/reflect/Method;
    //   160: astore 23
    //   162: iconst_0
    //   163: anewarray 111	java/lang/Object
    //   166: astore 24
    //   168: aload 23
    //   170: aconst_null
    //   171: aload 24
    //   173: invokevirtual 117	java/lang/reflect/Method:invoke	(Ljava/lang/Object;[Ljava/lang/Object;)Ljava/lang/Object;
    //   176: astore 26
    //   178: aload 26
    //   180: checkcast 128	java/lang/Integer
    //   183: invokevirtual 131	java/lang/Integer:intValue	()I
    //   186: getstatic 157	uuuuuu/llllql:b0070p00700070pp0070p0070	I
    //   189: iadd
    //   190: istore 27
    //   192: ldc 2
    //   194: ldc_w 510
    //   197: sipush 205
    //   200: iconst_4
    //   201: invokestatic 103	xxxxxx/uxxxxx:bb00620062bb0062b0062b0062	(Ljava/lang/String;CC)Ljava/lang/String;
    //   204: iconst_0
    //   205: anewarray 105	java/lang/Class
    //   208: invokevirtual 109	java/lang/Class:getMethod	(Ljava/lang/String;[Ljava/lang/Class;)Ljava/lang/reflect/Method;
    //   211: astore 28
    //   213: iconst_0
    //   214: anewarray 111	java/lang/Object
    //   217: astore 29
    //   219: aload 28
    //   221: aconst_null
    //   222: aload 29
    //   224: invokevirtual 117	java/lang/reflect/Method:invoke	(Ljava/lang/Object;[Ljava/lang/Object;)Ljava/lang/Object;
    //   227: astore 31
    //   229: iload 27
    //   231: aload 31
    //   233: checkcast 128	java/lang/Integer
    //   236: invokevirtual 131	java/lang/Integer:intValue	()I
    //   239: imul
    //   240: getstatic 137	uuuuuu/llllql:bp007000700070pp0070p0070	I
    //   243: irem
    //   244: getstatic 147	uuuuuu/llllql:bpp00700070pp0070p0070	I
    //   247: if_icmpeq +55 -> 302
    //   250: ldc 2
    //   252: ldc_w 512
    //   255: bipush 68
    //   257: iconst_0
    //   258: invokestatic 103	xxxxxx/uxxxxx:bb00620062bb0062b0062b0062	(Ljava/lang/String;CC)Ljava/lang/String;
    //   261: iconst_0
    //   262: anewarray 105	java/lang/Class
    //   265: invokevirtual 109	java/lang/Class:getMethod	(Ljava/lang/String;[Ljava/lang/Class;)Ljava/lang/reflect/Method;
    //   268: astore 32
    //   270: iconst_0
    //   271: anewarray 111	java/lang/Object
    //   274: astore 33
    //   276: aload 32
    //   278: aconst_null
    //   279: aload 33
    //   281: invokevirtual 117	java/lang/reflect/Method:invoke	(Ljava/lang/Object;[Ljava/lang/Object;)Ljava/lang/Object;
    //   284: astore 35
    //   286: aload 35
    //   288: checkcast 128	java/lang/Integer
    //   291: invokevirtual 131	java/lang/Integer:intValue	()I
    //   294: putstatic 124	uuuuuu/llllql:b00700070p0070pp0070p0070	I
    //   297: bipush 18
    //   299: putstatic 147	uuuuuu/llllql:bpp00700070pp0070p0070	I
    //   302: aload 21
    //   304: aload 22
    //   306: if_acmpeq +9 -> 315
    //   309: getstatic 518	uuuuuu/vvrvrv:b0068hh0068006800680068h0068	Luuuuuu/vvrvrv;
    //   312: invokestatic 524	uuuuuu/rrvvrv:b0071q0071qq0071q0071q0071	(Luuuuuu/vvrvrv;)V
    //   315: aload_0
    //   316: iconst_1
    //   317: putfield 44	uuuuuu/llllql:bppp0070pp0070p0070	Z
    //   320: getstatic 124	uuuuuu/llllql:b00700070p0070pp0070p0070	I
    //   323: istore_2
    //   324: ldc 2
    //   326: ldc_w 526
    //   329: sipush 130
    //   332: bipush 15
    //   334: iconst_2
    //   335: invokestatic 143	xxxxxx/uxxxxx:bbbb0062b0062b0062b0062	(Ljava/lang/String;CCC)Ljava/lang/String;
    //   338: iconst_0
    //   339: anewarray 105	java/lang/Class
    //   342: invokevirtual 109	java/lang/Class:getMethod	(Ljava/lang/String;[Ljava/lang/Class;)Ljava/lang/reflect/Method;
    //   345: astore_3
    //   346: iconst_0
    //   347: anewarray 111	java/lang/Object
    //   350: astore 4
    //   352: aload_3
    //   353: aconst_null
    //   354: aload 4
    //   356: invokevirtual 117	java/lang/reflect/Method:invoke	(Ljava/lang/Object;[Ljava/lang/Object;)Ljava/lang/Object;
    //   359: astore 6
    //   361: iload_2
    //   362: aload 6
    //   364: checkcast 128	java/lang/Integer
    //   367: invokevirtual 131	java/lang/Integer:intValue	()I
    //   370: iadd
    //   371: getstatic 124	uuuuuu/llllql:b00700070p0070pp0070p0070	I
    //   374: imul
    //   375: getstatic 137	uuuuuu/llllql:bp007000700070pp0070p0070	I
    //   378: irem
    //   379: getstatic 147	uuuuuu/llllql:bpp00700070pp0070p0070	I
    //   382: if_icmpeq +58 -> 440
    //   385: ldc 2
    //   387: ldc_w 528
    //   390: bipush 92
    //   392: sipush 220
    //   395: iconst_0
    //   396: invokestatic 143	xxxxxx/uxxxxx:bbbb0062b0062b0062b0062	(Ljava/lang/String;CCC)Ljava/lang/String;
    //   399: iconst_0
    //   400: anewarray 105	java/lang/Class
    //   403: invokevirtual 109	java/lang/Class:getMethod	(Ljava/lang/String;[Ljava/lang/Class;)Ljava/lang/reflect/Method;
    //   406: astore 17
    //   408: iconst_0
    //   409: anewarray 111	java/lang/Object
    //   412: astore 18
    //   414: aload 17
    //   416: aconst_null
    //   417: aload 18
    //   419: invokevirtual 117	java/lang/reflect/Method:invoke	(Ljava/lang/Object;[Ljava/lang/Object;)Ljava/lang/Object;
    //   422: astore 20
    //   424: aload 20
    //   426: checkcast 128	java/lang/Integer
    //   429: invokevirtual 131	java/lang/Integer:intValue	()I
    //   432: putstatic 124	uuuuuu/llllql:b00700070p0070pp0070p0070	I
    //   435: bipush 24
    //   437: putstatic 147	uuuuuu/llllql:bpp00700070pp0070p0070	I
    //   440: ldc 2
    //   442: ldc_w 530
    //   445: sipush 179
    //   448: bipush 113
    //   450: iconst_3
    //   451: invokestatic 143	xxxxxx/uxxxxx:bbbb0062b0062b0062b0062	(Ljava/lang/String;CCC)Ljava/lang/String;
    //   454: iconst_0
    //   455: anewarray 105	java/lang/Class
    //   458: invokevirtual 109	java/lang/Class:getMethod	(Ljava/lang/String;[Ljava/lang/Class;)Ljava/lang/reflect/Method;
    //   461: astore 7
    //   463: iconst_0
    //   464: anewarray 111	java/lang/Object
    //   467: astore 8
    //   469: aload 7
    //   471: aload_0
    //   472: aload 8
    //   474: invokevirtual 117	java/lang/reflect/Method:invoke	(Ljava/lang/Object;[Ljava/lang/Object;)Ljava/lang/Object;
    //   477: pop
    //   478: iconst_3
    //   479: istore 11
    //   481: iload 11
    //   483: iconst_0
    //   484: idiv
    //   485: istore 11
    //   487: goto -6 -> 481
    //   490: astore 12
    //   492: ldc 2
    //   494: ldc_w 532
    //   497: sipush 189
    //   500: iconst_3
    //   501: invokestatic 103	xxxxxx/uxxxxx:bb00620062bb0062b0062b0062	(Ljava/lang/String;CC)Ljava/lang/String;
    //   504: iconst_0
    //   505: anewarray 105	java/lang/Class
    //   508: invokevirtual 109	java/lang/Class:getMethod	(Ljava/lang/String;[Ljava/lang/Class;)Ljava/lang/reflect/Method;
    //   511: astore 13
    //   513: iconst_0
    //   514: anewarray 111	java/lang/Object
    //   517: astore 14
    //   519: aload 13
    //   521: aconst_null
    //   522: aload 14
    //   524: invokevirtual 117	java/lang/reflect/Method:invoke	(Ljava/lang/Object;[Ljava/lang/Object;)Ljava/lang/Object;
    //   527: astore 16
    //   529: aload 16
    //   531: checkcast 128	java/lang/Integer
    //   534: invokevirtual 131	java/lang/Integer:intValue	()I
    //   537: putstatic 124	uuuuuu/llllql:b00700070p0070pp0070p0070	I
    //   540: return
    //   541: astore 15
    //   543: aload 15
    //   545: invokevirtual 163	java/lang/reflect/InvocationTargetException:getCause	()Ljava/lang/Throwable;
    //   548: athrow
    //   549: astore 5
    //   551: aload 5
    //   553: invokevirtual 163	java/lang/reflect/InvocationTargetException:getCause	()Ljava/lang/Throwable;
    //   556: athrow
    //   557: astore 25
    //   559: aload 25
    //   561: invokevirtual 163	java/lang/reflect/InvocationTargetException:getCause	()Ljava/lang/Throwable;
    //   564: athrow
    //   565: astore 30
    //   567: aload 30
    //   569: invokevirtual 163	java/lang/reflect/InvocationTargetException:getCause	()Ljava/lang/Throwable;
    //   572: athrow
    //   573: astore 9
    //   575: aload 9
    //   577: invokevirtual 163	java/lang/reflect/InvocationTargetException:getCause	()Ljava/lang/Throwable;
    //   580: athrow
    //   581: astore 34
    //   583: aload 34
    //   585: invokevirtual 163	java/lang/reflect/InvocationTargetException:getCause	()Ljava/lang/Throwable;
    //   588: athrow
    //   589: astore 19
    //   591: aload 19
    //   593: invokevirtual 163	java/lang/reflect/InvocationTargetException:getCause	()Ljava/lang/Throwable;
    //   596: athrow
    //   597: astore 38
    //   599: aload 38
    //   601: invokevirtual 163	java/lang/reflect/InvocationTargetException:getCause	()Ljava/lang/Throwable;
    //   604: athrow
    //   605: astore 42
    //   607: aload 42
    //   609: invokevirtual 163	java/lang/reflect/InvocationTargetException:getCause	()Ljava/lang/Throwable;
    //   612: athrow
    // Local variable table:
    //   start	length	slot	name	signature
    //   0	613	0	this	llllql
    //   0	613	1	paramDbError	DbError
    //   323	48	2	i	int
    //   345	8	3	localMethod1	java.lang.reflect.Method
    //   350	5	4	arrayOfObject1	Object[]
    //   549	3	5	localInvocationTargetException1	java.lang.reflect.InvocationTargetException
    //   359	4	6	localObject1	Object
    //   461	9	7	localMethod2	java.lang.reflect.Method
    //   467	6	8	arrayOfObject2	Object[]
    //   573	3	9	localInvocationTargetException2	java.lang.reflect.InvocationTargetException
    //   479	7	11	j	int
    //   490	1	12	localException	Exception
    //   511	9	13	localMethod3	java.lang.reflect.Method
    //   517	6	14	arrayOfObject3	Object[]
    //   541	3	15	localInvocationTargetException3	java.lang.reflect.InvocationTargetException
    //   527	3	16	localObject2	Object
    //   406	9	17	localMethod4	java.lang.reflect.Method
    //   412	6	18	arrayOfObject4	Object[]
    //   589	3	19	localInvocationTargetException4	java.lang.reflect.InvocationTargetException
    //   422	3	20	localObject3	Object
    //   134	169	21	localDbErrorCode1	com.db.pwcc.dbmobile.model.error.DbErrorCode
    //   140	165	22	localDbErrorCode2	com.db.pwcc.dbmobile.model.error.DbErrorCode
    //   160	9	23	localMethod5	java.lang.reflect.Method
    //   166	6	24	arrayOfObject5	Object[]
    //   557	3	25	localInvocationTargetException5	java.lang.reflect.InvocationTargetException
    //   176	3	26	localObject4	Object
    //   190	50	27	k	int
    //   211	9	28	localMethod6	java.lang.reflect.Method
    //   217	6	29	arrayOfObject6	Object[]
    //   565	3	30	localInvocationTargetException6	java.lang.reflect.InvocationTargetException
    //   227	5	31	localObject5	Object
    //   268	9	32	localMethod7	java.lang.reflect.Method
    //   274	6	33	arrayOfObject7	Object[]
    //   581	3	34	localInvocationTargetException7	java.lang.reflect.InvocationTargetException
    //   284	3	35	localObject6	Object
    //   39	9	36	localMethod8	java.lang.reflect.Method
    //   45	6	37	arrayOfObject8	Object[]
    //   597	3	38	localInvocationTargetException8	java.lang.reflect.InvocationTargetException
    //   55	3	39	localObject7	Object
    //   87	9	40	localMethod9	java.lang.reflect.Method
    //   93	6	41	arrayOfObject9	Object[]
    //   605	3	42	localInvocationTargetException9	java.lang.reflect.InvocationTargetException
    //   103	3	43	localObject8	Object
    // Exception table:
    //   from	to	target	type
    //   481	487	490	java/lang/Exception
    //   519	529	541	java/lang/reflect/InvocationTargetException
    //   352	361	549	java/lang/reflect/InvocationTargetException
    //   168	178	557	java/lang/reflect/InvocationTargetException
    //   219	229	565	java/lang/reflect/InvocationTargetException
    //   469	478	573	java/lang/reflect/InvocationTargetException
    //   276	286	581	java/lang/reflect/InvocationTargetException
    //   414	424	589	java/lang/reflect/InvocationTargetException
    //   47	57	597	java/lang/reflect/InvocationTargetException
    //   95	105	605	java/lang/reflect/InvocationTargetException
  }
  
  /* Error */
  public void bp0070p007000700070p00700070p(DbError paramDbError)
  {
    // Byte code:
    //   0: aload_0
    //   1: aload_1
    //   2: putfield 40	uuuuuu/llllql:bp0070p0070pp0070p0070	Lcom/db/pwcc/dbmobile/model/error/DbError;
    //   5: getstatic 124	uuuuuu/llllql:b00700070p0070pp0070p0070	I
    //   8: getstatic 157	uuuuuu/llllql:b0070p00700070pp0070p0070	I
    //   11: iadd
    //   12: getstatic 124	uuuuuu/llllql:b00700070p0070pp0070p0070	I
    //   15: imul
    //   16: getstatic 137	uuuuuu/llllql:bp007000700070pp0070p0070	I
    //   19: irem
    //   20: getstatic 147	uuuuuu/llllql:bpp00700070pp0070p0070	I
    //   23: if_icmpeq +99 -> 122
    //   26: ldc 2
    //   28: ldc_w 535
    //   31: bipush 46
    //   33: iconst_4
    //   34: invokestatic 103	xxxxxx/uxxxxx:bb00620062bb0062b0062b0062	(Ljava/lang/String;CC)Ljava/lang/String;
    //   37: iconst_0
    //   38: anewarray 105	java/lang/Class
    //   41: invokevirtual 109	java/lang/Class:getMethod	(Ljava/lang/String;[Ljava/lang/Class;)Ljava/lang/reflect/Method;
    //   44: astore 33
    //   46: iconst_0
    //   47: anewarray 111	java/lang/Object
    //   50: astore 34
    //   52: aload 33
    //   54: aconst_null
    //   55: aload 34
    //   57: invokevirtual 117	java/lang/reflect/Method:invoke	(Ljava/lang/Object;[Ljava/lang/Object;)Ljava/lang/Object;
    //   60: astore 36
    //   62: aload 36
    //   64: checkcast 128	java/lang/Integer
    //   67: invokevirtual 131	java/lang/Integer:intValue	()I
    //   70: putstatic 124	uuuuuu/llllql:b00700070p0070pp0070p0070	I
    //   73: ldc 2
    //   75: ldc_w 537
    //   78: bipush 108
    //   80: bipush 33
    //   82: iconst_2
    //   83: invokestatic 143	xxxxxx/uxxxxx:bbbb0062b0062b0062b0062	(Ljava/lang/String;CCC)Ljava/lang/String;
    //   86: iconst_0
    //   87: anewarray 105	java/lang/Class
    //   90: invokevirtual 109	java/lang/Class:getMethod	(Ljava/lang/String;[Ljava/lang/Class;)Ljava/lang/reflect/Method;
    //   93: astore 37
    //   95: iconst_0
    //   96: anewarray 111	java/lang/Object
    //   99: astore 38
    //   101: aload 37
    //   103: aconst_null
    //   104: aload 38
    //   106: invokevirtual 117	java/lang/reflect/Method:invoke	(Ljava/lang/Object;[Ljava/lang/Object;)Ljava/lang/Object;
    //   109: astore 40
    //   111: aload 40
    //   113: checkcast 128	java/lang/Integer
    //   116: invokevirtual 131	java/lang/Integer:intValue	()I
    //   119: putstatic 147	uuuuuu/llllql:bpp00700070pp0070p0070	I
    //   122: aload_0
    //   123: iconst_1
    //   124: putfield 46	uuuuuu/llllql:b0070pp0070pp0070p0070	Z
    //   127: getstatic 124	uuuuuu/llllql:b00700070p0070pp0070p0070	I
    //   130: istore_2
    //   131: ldc 2
    //   133: ldc_w 539
    //   136: sipush 135
    //   139: iconst_3
    //   140: invokestatic 103	xxxxxx/uxxxxx:bb00620062bb0062b0062b0062	(Ljava/lang/String;CC)Ljava/lang/String;
    //   143: iconst_0
    //   144: anewarray 105	java/lang/Class
    //   147: invokevirtual 109	java/lang/Class:getMethod	(Ljava/lang/String;[Ljava/lang/Class;)Ljava/lang/reflect/Method;
    //   150: astore_3
    //   151: iconst_0
    //   152: anewarray 111	java/lang/Object
    //   155: astore 4
    //   157: aload_3
    //   158: aconst_null
    //   159: aload 4
    //   161: invokevirtual 117	java/lang/reflect/Method:invoke	(Ljava/lang/Object;[Ljava/lang/Object;)Ljava/lang/Object;
    //   164: astore 6
    //   166: iload_2
    //   167: aload 6
    //   169: checkcast 128	java/lang/Integer
    //   172: invokevirtual 131	java/lang/Integer:intValue	()I
    //   175: iadd
    //   176: getstatic 124	uuuuuu/llllql:b00700070p0070pp0070p0070	I
    //   179: imul
    //   180: getstatic 137	uuuuuu/llllql:bp007000700070pp0070p0070	I
    //   183: irem
    //   184: getstatic 147	uuuuuu/llllql:bpp00700070pp0070p0070	I
    //   187: if_icmpeq +316 -> 503
    //   190: ldc 2
    //   192: ldc_w 541
    //   195: bipush 82
    //   197: iconst_5
    //   198: invokestatic 103	xxxxxx/uxxxxx:bb00620062bb0062b0062b0062	(Ljava/lang/String;CC)Ljava/lang/String;
    //   201: iconst_0
    //   202: anewarray 105	java/lang/Class
    //   205: invokevirtual 109	java/lang/Class:getMethod	(Ljava/lang/String;[Ljava/lang/Class;)Ljava/lang/reflect/Method;
    //   208: astore 11
    //   210: iconst_0
    //   211: anewarray 111	java/lang/Object
    //   214: astore 12
    //   216: aload 11
    //   218: aconst_null
    //   219: aload 12
    //   221: invokevirtual 117	java/lang/reflect/Method:invoke	(Ljava/lang/Object;[Ljava/lang/Object;)Ljava/lang/Object;
    //   224: astore 14
    //   226: aload 14
    //   228: checkcast 128	java/lang/Integer
    //   231: invokevirtual 131	java/lang/Integer:intValue	()I
    //   234: putstatic 124	uuuuuu/llllql:b00700070p0070pp0070p0070	I
    //   237: bipush 91
    //   239: putstatic 147	uuuuuu/llllql:bpp00700070pp0070p0070	I
    //   242: getstatic 124	uuuuuu/llllql:b00700070p0070pp0070p0070	I
    //   245: istore 15
    //   247: iload 15
    //   249: iload 15
    //   251: getstatic 157	uuuuuu/llllql:b0070p00700070pp0070p0070	I
    //   254: iadd
    //   255: imul
    //   256: getstatic 137	uuuuuu/llllql:bp007000700070pp0070p0070	I
    //   259: irem
    //   260: tableswitch	default:+20->280, 0:+243->503
    //   280: ldc 2
    //   282: ldc_w 543
    //   285: bipush 75
    //   287: iconst_5
    //   288: invokestatic 103	xxxxxx/uxxxxx:bb00620062bb0062b0062b0062	(Ljava/lang/String;CC)Ljava/lang/String;
    //   291: iconst_0
    //   292: anewarray 105	java/lang/Class
    //   295: invokevirtual 109	java/lang/Class:getMethod	(Ljava/lang/String;[Ljava/lang/Class;)Ljava/lang/reflect/Method;
    //   298: astore 16
    //   300: iconst_0
    //   301: anewarray 111	java/lang/Object
    //   304: astore 17
    //   306: aload 16
    //   308: aconst_null
    //   309: aload 17
    //   311: invokevirtual 117	java/lang/reflect/Method:invoke	(Ljava/lang/Object;[Ljava/lang/Object;)Ljava/lang/Object;
    //   314: astore 19
    //   316: aload 19
    //   318: checkcast 128	java/lang/Integer
    //   321: invokevirtual 131	java/lang/Integer:intValue	()I
    //   324: putstatic 124	uuuuuu/llllql:b00700070p0070pp0070p0070	I
    //   327: ldc 2
    //   329: ldc_w 545
    //   332: bipush 96
    //   334: iconst_3
    //   335: invokestatic 103	xxxxxx/uxxxxx:bb00620062bb0062b0062b0062	(Ljava/lang/String;CC)Ljava/lang/String;
    //   338: iconst_0
    //   339: anewarray 105	java/lang/Class
    //   342: invokevirtual 109	java/lang/Class:getMethod	(Ljava/lang/String;[Ljava/lang/Class;)Ljava/lang/reflect/Method;
    //   345: astore 20
    //   347: iconst_0
    //   348: anewarray 111	java/lang/Object
    //   351: astore 21
    //   353: aload 20
    //   355: aconst_null
    //   356: aload 21
    //   358: invokevirtual 117	java/lang/reflect/Method:invoke	(Ljava/lang/Object;[Ljava/lang/Object;)Ljava/lang/Object;
    //   361: astore 23
    //   363: aload 23
    //   365: checkcast 128	java/lang/Integer
    //   368: invokevirtual 131	java/lang/Integer:intValue	()I
    //   371: putstatic 147	uuuuuu/llllql:bpp00700070pp0070p0070	I
    //   374: getstatic 124	uuuuuu/llllql:b00700070p0070pp0070p0070	I
    //   377: istore 24
    //   379: ldc 2
    //   381: ldc_w 547
    //   384: bipush 94
    //   386: iconst_4
    //   387: invokestatic 103	xxxxxx/uxxxxx:bb00620062bb0062b0062b0062	(Ljava/lang/String;CC)Ljava/lang/String;
    //   390: iconst_0
    //   391: anewarray 105	java/lang/Class
    //   394: invokevirtual 109	java/lang/Class:getMethod	(Ljava/lang/String;[Ljava/lang/Class;)Ljava/lang/reflect/Method;
    //   397: astore 25
    //   399: iconst_0
    //   400: anewarray 111	java/lang/Object
    //   403: astore 26
    //   405: aload 25
    //   407: aconst_null
    //   408: aload 26
    //   410: invokevirtual 117	java/lang/reflect/Method:invoke	(Ljava/lang/Object;[Ljava/lang/Object;)Ljava/lang/Object;
    //   413: astore 28
    //   415: iload 24
    //   417: iload 24
    //   419: aload 28
    //   421: checkcast 128	java/lang/Integer
    //   424: invokevirtual 131	java/lang/Integer:intValue	()I
    //   427: iadd
    //   428: imul
    //   429: getstatic 137	uuuuuu/llllql:bp007000700070pp0070p0070	I
    //   432: irem
    //   433: tableswitch	default:+19->452, 0:+70->503
    //   452: ldc 2
    //   454: ldc -86
    //   456: bipush 91
    //   458: iconst_5
    //   459: invokestatic 103	xxxxxx/uxxxxx:bb00620062bb0062b0062b0062	(Ljava/lang/String;CC)Ljava/lang/String;
    //   462: iconst_0
    //   463: anewarray 105	java/lang/Class
    //   466: invokevirtual 109	java/lang/Class:getMethod	(Ljava/lang/String;[Ljava/lang/Class;)Ljava/lang/reflect/Method;
    //   469: astore 29
    //   471: iconst_0
    //   472: anewarray 111	java/lang/Object
    //   475: astore 30
    //   477: aload 29
    //   479: aconst_null
    //   480: aload 30
    //   482: invokevirtual 117	java/lang/reflect/Method:invoke	(Ljava/lang/Object;[Ljava/lang/Object;)Ljava/lang/Object;
    //   485: astore 32
    //   487: aload 32
    //   489: checkcast 128	java/lang/Integer
    //   492: invokevirtual 131	java/lang/Integer:intValue	()I
    //   495: putstatic 124	uuuuuu/llllql:b00700070p0070pp0070p0070	I
    //   498: bipush 39
    //   500: putstatic 147	uuuuuu/llllql:bpp00700070pp0070p0070	I
    //   503: ldc 2
    //   505: ldc_w 549
    //   508: bipush 83
    //   510: iconst_1
    //   511: invokestatic 103	xxxxxx/uxxxxx:bb00620062bb0062b0062b0062	(Ljava/lang/String;CC)Ljava/lang/String;
    //   514: iconst_0
    //   515: anewarray 105	java/lang/Class
    //   518: invokevirtual 109	java/lang/Class:getMethod	(Ljava/lang/String;[Ljava/lang/Class;)Ljava/lang/reflect/Method;
    //   521: astore 7
    //   523: iconst_0
    //   524: anewarray 111	java/lang/Object
    //   527: astore 8
    //   529: aload 7
    //   531: aload_0
    //   532: aload 8
    //   534: invokevirtual 117	java/lang/reflect/Method:invoke	(Ljava/lang/Object;[Ljava/lang/Object;)Ljava/lang/Object;
    //   537: pop
    //   538: return
    //   539: astore 39
    //   541: aload 39
    //   543: invokevirtual 163	java/lang/reflect/InvocationTargetException:getCause	()Ljava/lang/Throwable;
    //   546: athrow
    //   547: astore 35
    //   549: aload 35
    //   551: invokevirtual 163	java/lang/reflect/InvocationTargetException:getCause	()Ljava/lang/Throwable;
    //   554: athrow
    //   555: astore 18
    //   557: aload 18
    //   559: invokevirtual 163	java/lang/reflect/InvocationTargetException:getCause	()Ljava/lang/Throwable;
    //   562: athrow
    //   563: astore 22
    //   565: aload 22
    //   567: invokevirtual 163	java/lang/reflect/InvocationTargetException:getCause	()Ljava/lang/Throwable;
    //   570: athrow
    //   571: astore 27
    //   573: aload 27
    //   575: invokevirtual 163	java/lang/reflect/InvocationTargetException:getCause	()Ljava/lang/Throwable;
    //   578: athrow
    //   579: astore 5
    //   581: aload 5
    //   583: invokevirtual 163	java/lang/reflect/InvocationTargetException:getCause	()Ljava/lang/Throwable;
    //   586: athrow
    //   587: astore 9
    //   589: aload 9
    //   591: invokevirtual 163	java/lang/reflect/InvocationTargetException:getCause	()Ljava/lang/Throwable;
    //   594: athrow
    //   595: astore 13
    //   597: aload 13
    //   599: invokevirtual 163	java/lang/reflect/InvocationTargetException:getCause	()Ljava/lang/Throwable;
    //   602: athrow
    //   603: astore 31
    //   605: aload 31
    //   607: invokevirtual 163	java/lang/reflect/InvocationTargetException:getCause	()Ljava/lang/Throwable;
    //   610: athrow
    // Local variable table:
    //   start	length	slot	name	signature
    //   0	611	0	this	llllql
    //   0	611	1	paramDbError	DbError
    //   130	46	2	i	int
    //   150	8	3	localMethod1	java.lang.reflect.Method
    //   155	5	4	arrayOfObject1	Object[]
    //   579	3	5	localInvocationTargetException1	java.lang.reflect.InvocationTargetException
    //   164	4	6	localObject1	Object
    //   521	9	7	localMethod2	java.lang.reflect.Method
    //   527	6	8	arrayOfObject2	Object[]
    //   587	3	9	localInvocationTargetException2	java.lang.reflect.InvocationTargetException
    //   208	9	11	localMethod3	java.lang.reflect.Method
    //   214	6	12	arrayOfObject3	Object[]
    //   595	3	13	localInvocationTargetException3	java.lang.reflect.InvocationTargetException
    //   224	3	14	localObject2	Object
    //   245	11	15	j	int
    //   298	9	16	localMethod4	java.lang.reflect.Method
    //   304	6	17	arrayOfObject4	Object[]
    //   555	3	18	localInvocationTargetException4	java.lang.reflect.InvocationTargetException
    //   314	3	19	localObject3	Object
    //   345	9	20	localMethod5	java.lang.reflect.Method
    //   351	6	21	arrayOfObject5	Object[]
    //   563	3	22	localInvocationTargetException5	java.lang.reflect.InvocationTargetException
    //   361	3	23	localObject4	Object
    //   377	52	24	k	int
    //   397	9	25	localMethod6	java.lang.reflect.Method
    //   403	6	26	arrayOfObject6	Object[]
    //   571	3	27	localInvocationTargetException6	java.lang.reflect.InvocationTargetException
    //   413	7	28	localObject5	Object
    //   469	9	29	localMethod7	java.lang.reflect.Method
    //   475	6	30	arrayOfObject7	Object[]
    //   603	3	31	localInvocationTargetException7	java.lang.reflect.InvocationTargetException
    //   485	3	32	localObject6	Object
    //   44	9	33	localMethod8	java.lang.reflect.Method
    //   50	6	34	arrayOfObject8	Object[]
    //   547	3	35	localInvocationTargetException8	java.lang.reflect.InvocationTargetException
    //   60	3	36	localObject7	Object
    //   93	9	37	localMethod9	java.lang.reflect.Method
    //   99	6	38	arrayOfObject9	Object[]
    //   539	3	39	localInvocationTargetException9	java.lang.reflect.InvocationTargetException
    //   109	3	40	localObject8	Object
    // Exception table:
    //   from	to	target	type
    //   101	111	539	java/lang/reflect/InvocationTargetException
    //   52	62	547	java/lang/reflect/InvocationTargetException
    //   306	316	555	java/lang/reflect/InvocationTargetException
    //   353	363	563	java/lang/reflect/InvocationTargetException
    //   405	415	571	java/lang/reflect/InvocationTargetException
    //   157	166	579	java/lang/reflect/InvocationTargetException
    //   529	538	587	java/lang/reflect/InvocationTargetException
    //   216	226	595	java/lang/reflect/InvocationTargetException
    //   477	487	603	java/lang/reflect/InvocationTargetException
  }
}
