package uuuuuu;

import com.db.pwcc.dbmobile.model.banking.Account;
import javax.inject.Inject;

public class lqlllq
  extends qppppp<lllqql.lqlqql>
  implements lllqql.qllqql, vxvxvv.xvvxvv
{
  public static int b0070007000700070p0070p00700070 = 0;
  public static int b0070p00700070p0070p00700070 = 1;
  public static int bp007000700070p0070p00700070 = 2;
  private static final String bpp007000700070pp00700070;
  public static int bpp00700070p0070p00700070 = 49;
  @Inject
  public sssttt b00700070007000700070pp00700070;
  public sxxxsx b007000700070pp0070p00700070 = new sxxxsx();
  public sxxxsx.xsxsxx b00700070p0070p0070p00700070 = new sxxxsx.xsxsxx()
  {
    public static int b007000700070p00700070p00700070 = 0;
    public static int b0070pp007000700070p00700070 = 2;
    public static int bp00700070p00700070p00700070 = 16;
    public static int bppp007000700070p00700070 = 1;
    
    public static int b006F006F006Foo006F006F006Foo()
    {
      return 0;
    }
    
    public static int b006Fo006Foo006F006F006Foo()
    {
      return 92;
    }
    
    public static int bo006F006Foo006F006F006Foo()
    {
      return 1;
    }
    
    public void b006Fooo006Foo006Foo(int paramAnonymousInt) {}
    
    /* Error */
    public void bo006Foo006Foo006Foo(int paramAnonymousInt, com.db.pwcc.dbmobile.model.error.DbError paramAnonymousDbError)
    {
      // Byte code:
      //   0: ldc 36
      //   2: ldc 38
      //   4: bipush 118
      //   6: iconst_4
      //   7: invokestatic 44	xxxxxx/uxxxxx:bb00620062bb0062b0062b0062	(Ljava/lang/String;CC)Ljava/lang/String;
      //   10: iconst_0
      //   11: anewarray 46	java/lang/Class
      //   14: invokevirtual 50	java/lang/Class:getMethod	(Ljava/lang/String;[Ljava/lang/Class;)Ljava/lang/reflect/Method;
      //   17: astore_3
      //   18: iconst_0
      //   19: anewarray 4	java/lang/Object
      //   22: astore 4
      //   24: aload_3
      //   25: aconst_null
      //   26: aload 4
      //   28: invokevirtual 56	java/lang/reflect/Method:invoke	(Ljava/lang/Object;[Ljava/lang/Object;)Ljava/lang/Object;
      //   31: astore 6
      //   33: aload 6
      //   35: checkcast 58	java/lang/String
      //   38: astore 7
      //   40: getstatic 60	uuuuuu/lqlllq$2:bp00700070p00700070p00700070	I
      //   43: istore 8
      //   45: iload 8
      //   47: iload 8
      //   49: getstatic 62	uuuuuu/lqlllq$2:bppp007000700070p00700070	I
      //   52: iadd
      //   53: imul
      //   54: getstatic 64	uuuuuu/lqlllq$2:b0070pp007000700070p00700070	I
      //   57: irem
      //   58: tableswitch	default:+18->76, 0:+30->88
      //   76: invokestatic 66	uuuuuu/lqlllq$2:b006Fo006Foo006F006F006Foo	()I
      //   79: putstatic 60	uuuuuu/lqlllq$2:bp00700070p00700070p00700070	I
      //   82: invokestatic 66	uuuuuu/lqlllq$2:b006Fo006Foo006F006F006Foo	()I
      //   85: putstatic 68	uuuuuu/lqlllq$2:b007000700070p00700070p00700070	I
      //   88: ldc 70
      //   90: sipush 184
      //   93: iconst_0
      //   94: invokestatic 44	xxxxxx/uxxxxx:bb00620062bb0062b0062b0062	(Ljava/lang/String;CC)Ljava/lang/String;
      //   97: astore 9
      //   99: iconst_3
      //   100: anewarray 46	java/lang/Class
      //   103: astore 10
      //   105: aload 10
      //   107: iconst_0
      //   108: ldc 58
      //   110: aastore
      //   111: aload 10
      //   113: iconst_1
      //   114: getstatic 76	java/lang/Character:TYPE	Ljava/lang/Class;
      //   117: aastore
      //   118: aload 10
      //   120: iconst_2
      //   121: getstatic 76	java/lang/Character:TYPE	Ljava/lang/Class;
      //   124: aastore
      //   125: ldc 78
      //   127: aload 9
      //   129: aload 10
      //   131: invokevirtual 50	java/lang/Class:getMethod	(Ljava/lang/String;[Ljava/lang/Class;)Ljava/lang/reflect/Method;
      //   134: astore 11
      //   136: iconst_3
      //   137: anewarray 4	java/lang/Object
      //   140: astore 12
      //   142: aload 12
      //   144: iconst_0
      //   145: ldc 80
      //   147: aastore
      //   148: aload 12
      //   150: iconst_1
      //   151: sipush 167
      //   154: invokestatic 84	java/lang/Character:valueOf	(C)Ljava/lang/Character;
      //   157: aastore
      //   158: aload 12
      //   160: iconst_2
      //   161: iconst_4
      //   162: invokestatic 84	java/lang/Character:valueOf	(C)Ljava/lang/Character;
      //   165: aastore
      //   166: aload 11
      //   168: aconst_null
      //   169: aload 12
      //   171: invokevirtual 56	java/lang/reflect/Method:invoke	(Ljava/lang/Object;[Ljava/lang/Object;)Ljava/lang/Object;
      //   174: astore 14
      //   176: aload 7
      //   178: aload 14
      //   180: checkcast 58	java/lang/String
      //   183: aload_2
      //   184: invokestatic 90	uuuuuu/rvvvrv:b00710071qq00710071q0071q0071	(Ljava/lang/String;Ljava/lang/String;Ljava/lang/Throwable;)V
      //   187: getstatic 60	uuuuuu/lqlllq$2:bp00700070p00700070p00700070	I
      //   190: invokestatic 92	uuuuuu/lqlllq$2:bo006F006Foo006F006F006Foo	()I
      //   193: iadd
      //   194: getstatic 60	uuuuuu/lqlllq$2:bp00700070p00700070p00700070	I
      //   197: imul
      //   198: getstatic 64	uuuuuu/lqlllq$2:b0070pp007000700070p00700070	I
      //   201: irem
      //   202: invokestatic 94	uuuuuu/lqlllq$2:b006F006F006Foo006F006F006Foo	()I
      //   205: if_icmpeq +14 -> 219
      //   208: bipush 23
      //   210: putstatic 60	uuuuuu/lqlllq$2:bp00700070p00700070p00700070	I
      //   213: invokestatic 66	uuuuuu/lqlllq$2:b006Fo006Foo006F006F006Foo	()I
      //   216: putstatic 68	uuuuuu/lqlllq$2:b007000700070p00700070p00700070	I
      //   219: return
      //   220: astore 5
      //   222: aload 5
      //   224: invokevirtual 98	java/lang/reflect/InvocationTargetException:getCause	()Ljava/lang/Throwable;
      //   227: athrow
      //   228: astore 13
      //   230: aload 13
      //   232: invokevirtual 98	java/lang/reflect/InvocationTargetException:getCause	()Ljava/lang/Throwable;
      //   235: athrow
      // Local variable table:
      //   start	length	slot	name	signature
      //   0	236	0	this	2
      //   0	236	1	paramAnonymousInt	int
      //   0	236	2	paramAnonymousDbError	com.db.pwcc.dbmobile.model.error.DbError
      //   17	8	3	localMethod1	java.lang.reflect.Method
      //   22	5	4	arrayOfObject1	Object[]
      //   220	3	5	localInvocationTargetException1	java.lang.reflect.InvocationTargetException
      //   31	3	6	localObject1	Object
      //   38	139	7	str1	String
      //   43	11	8	i	int
      //   97	31	9	str2	String
      //   103	27	10	arrayOfClass	Class[]
      //   134	33	11	localMethod2	java.lang.reflect.Method
      //   140	30	12	arrayOfObject2	Object[]
      //   228	3	13	localInvocationTargetException2	java.lang.reflect.InvocationTargetException
      //   174	5	14	localObject2	Object
      // Exception table:
      //   from	to	target	type
      //   24	33	220	java/lang/reflect/InvocationTargetException
      //   166	176	228	java/lang/reflect/InvocationTargetException
    }
    
    /* Error */
    public void boooo006Foo006Foo()
    {
      // Byte code:
      //   0: aload_0
      //   1: getfield 21	uuuuuu/lqlllq$2:b0070p0070p00700070p00700070	Luuuuuu/lqlllq;
      //   4: astore_1
      //   5: ldc 36
      //   7: ldc 101
      //   9: bipush 67
      //   11: iconst_1
      //   12: invokestatic 44	xxxxxx/uxxxxx:bb00620062bb0062b0062b0062	(Ljava/lang/String;CC)Ljava/lang/String;
      //   15: iconst_1
      //   16: anewarray 46	java/lang/Class
      //   19: dup
      //   20: iconst_0
      //   21: ldc 36
      //   23: aastore
      //   24: invokevirtual 50	java/lang/Class:getMethod	(Ljava/lang/String;[Ljava/lang/Class;)Ljava/lang/reflect/Method;
      //   27: astore_2
      //   28: iconst_1
      //   29: anewarray 4	java/lang/Object
      //   32: dup
      //   33: iconst_0
      //   34: aload_1
      //   35: aastore
      //   36: astore_3
      //   37: aload_2
      //   38: aconst_null
      //   39: aload_3
      //   40: invokevirtual 56	java/lang/reflect/Method:invoke	(Ljava/lang/Object;[Ljava/lang/Object;)Ljava/lang/Object;
      //   43: astore 5
      //   45: aload 5
      //   47: checkcast 103	uuuuuu/ttssst$tsssst
      //   50: ifnull +162 -> 212
      //   53: aload_0
      //   54: getfield 21	uuuuuu/lqlllq$2:b0070p0070p00700070p00700070	Luuuuuu/lqlllq;
      //   57: astore 6
      //   59: ldc 36
      //   61: ldc 105
      //   63: sipush 171
      //   66: bipush 114
      //   68: iconst_1
      //   69: invokestatic 109	xxxxxx/uxxxxx:bbbb0062b0062b0062b0062	(Ljava/lang/String;CCC)Ljava/lang/String;
      //   72: iconst_1
      //   73: anewarray 46	java/lang/Class
      //   76: dup
      //   77: iconst_0
      //   78: ldc 36
      //   80: aastore
      //   81: invokevirtual 50	java/lang/Class:getMethod	(Ljava/lang/String;[Ljava/lang/Class;)Ljava/lang/reflect/Method;
      //   84: astore 7
      //   86: iconst_1
      //   87: anewarray 4	java/lang/Object
      //   90: dup
      //   91: iconst_0
      //   92: aload 6
      //   94: aastore
      //   95: astore 8
      //   97: aload 7
      //   99: aconst_null
      //   100: aload 8
      //   102: invokevirtual 56	java/lang/reflect/Method:invoke	(Ljava/lang/Object;[Ljava/lang/Object;)Ljava/lang/Object;
      //   105: astore 10
      //   107: aload 10
      //   109: checkcast 103	uuuuuu/ttssst$tsssst
      //   112: astore 11
      //   114: getstatic 60	uuuuuu/lqlllq$2:bp00700070p00700070p00700070	I
      //   117: getstatic 62	uuuuuu/lqlllq$2:bppp007000700070p00700070	I
      //   120: iadd
      //   121: getstatic 60	uuuuuu/lqlllq$2:bp00700070p00700070p00700070	I
      //   124: imul
      //   125: getstatic 64	uuuuuu/lqlllq$2:b0070pp007000700070p00700070	I
      //   128: irem
      //   129: getstatic 68	uuuuuu/lqlllq$2:b007000700070p00700070p00700070	I
      //   132: if_icmpeq +13 -> 145
      //   135: bipush 86
      //   137: putstatic 60	uuuuuu/lqlllq$2:bp00700070p00700070p00700070	I
      //   140: bipush 33
      //   142: putstatic 68	uuuuuu/lqlllq$2:b007000700070p00700070p00700070	I
      //   145: aload 11
      //   147: checkcast 111	uuuuuu/lllqql$lqlqql
      //   150: astore 12
      //   152: getstatic 116	com/db/pwcc/dbmobile/financial_overview/R$id:menu_item_transfer_subaccount	I
      //   155: istore 13
      //   157: getstatic 60	uuuuuu/lqlllq$2:bp00700070p00700070p00700070	I
      //   160: istore 14
      //   162: iload 14
      //   164: iload 14
      //   166: invokestatic 92	uuuuuu/lqlllq$2:bo006F006Foo006F006F006Foo	()I
      //   169: iadd
      //   170: imul
      //   171: getstatic 64	uuuuuu/lqlllq$2:b0070pp007000700070p00700070	I
      //   174: irem
      //   175: tableswitch	default:+17->192, 0:+28->203
      //   192: invokestatic 66	uuuuuu/lqlllq$2:b006Fo006Foo006F006F006Foo	()I
      //   195: putstatic 60	uuuuuu/lqlllq$2:bp00700070p00700070p00700070	I
      //   198: bipush 19
      //   200: putstatic 68	uuuuuu/lqlllq$2:b007000700070p00700070p00700070	I
      //   203: aload 12
      //   205: iload 13
      //   207: invokeinterface 119 2 0
      //   212: return
      //   213: astore 4
      //   215: aload 4
      //   217: invokevirtual 98	java/lang/reflect/InvocationTargetException:getCause	()Ljava/lang/Throwable;
      //   220: athrow
      //   221: astore 9
      //   223: aload 9
      //   225: invokevirtual 98	java/lang/reflect/InvocationTargetException:getCause	()Ljava/lang/Throwable;
      //   228: athrow
      // Local variable table:
      //   start	length	slot	name	signature
      //   0	229	0	this	2
      //   4	31	1	localLqlllq1	lqlllq
      //   27	11	2	localMethod1	java.lang.reflect.Method
      //   36	4	3	arrayOfObject1	Object[]
      //   213	3	4	localInvocationTargetException1	java.lang.reflect.InvocationTargetException
      //   43	3	5	localObject1	Object
      //   57	36	6	localLqlllq2	lqlllq
      //   84	14	7	localMethod2	java.lang.reflect.Method
      //   95	6	8	arrayOfObject2	Object[]
      //   221	3	9	localInvocationTargetException2	java.lang.reflect.InvocationTargetException
      //   105	3	10	localObject2	Object
      //   112	34	11	localTsssst	ttssst.tsssst
      //   150	54	12	localLqlqql	lllqql.lqlqql
      //   155	51	13	i	int
      //   160	11	14	j	int
      // Exception table:
      //   from	to	target	type
      //   37	45	213	java/lang/reflect/InvocationTargetException
      //   97	107	221	java/lang/reflect/InvocationTargetException
    }
  };
  public sxxxsx.xsxsxx b00700070ppp0070p00700070 = new sxxxsx.xsxsxx()
  {
    public static int b007000700070ppp007000700070 = 1;
    public static int b0070p0070ppp007000700070 = 57;
    public static int bp00700070ppp007000700070 = 0;
    public static int bppp0070pp007000700070 = 2;
    
    public static int b006F006Fo006Fo006F006F006Foo()
    {
      return 43;
    }
    
    public void b006Fooo006Foo006Foo(int paramAnonymousInt) {}
    
    /* Error */
    public void bo006Foo006Foo006Foo(int paramAnonymousInt, com.db.pwcc.dbmobile.model.error.DbError paramAnonymousDbError)
    {
      // Byte code:
      //   0: ldc 34
      //   2: ldc 36
      //   4: bipush 83
      //   6: iconst_4
      //   7: invokestatic 42	xxxxxx/uxxxxx:bb00620062bb0062b0062b0062	(Ljava/lang/String;CC)Ljava/lang/String;
      //   10: iconst_0
      //   11: anewarray 44	java/lang/Class
      //   14: invokevirtual 48	java/lang/Class:getMethod	(Ljava/lang/String;[Ljava/lang/Class;)Ljava/lang/reflect/Method;
      //   17: astore_3
      //   18: iconst_0
      //   19: anewarray 4	java/lang/Object
      //   22: astore 4
      //   24: aload_3
      //   25: aconst_null
      //   26: aload 4
      //   28: invokevirtual 54	java/lang/reflect/Method:invoke	(Ljava/lang/Object;[Ljava/lang/Object;)Ljava/lang/Object;
      //   31: astore 6
      //   33: aload 6
      //   35: checkcast 56	java/lang/String
      //   38: astore 7
      //   40: getstatic 58	uuuuuu/lqlllq$5:b0070p0070ppp007000700070	I
      //   43: getstatic 60	uuuuuu/lqlllq$5:b007000700070ppp007000700070	I
      //   46: iadd
      //   47: getstatic 58	uuuuuu/lqlllq$5:b0070p0070ppp007000700070	I
      //   50: imul
      //   51: getstatic 62	uuuuuu/lqlllq$5:bppp0070pp007000700070	I
      //   54: irem
      //   55: getstatic 64	uuuuuu/lqlllq$5:bp00700070ppp007000700070	I
      //   58: if_icmpeq +46 -> 104
      //   61: invokestatic 66	uuuuuu/lqlllq$5:b006F006Fo006Fo006F006F006Foo	()I
      //   64: putstatic 58	uuuuuu/lqlllq$5:b0070p0070ppp007000700070	I
      //   67: bipush 69
      //   69: putstatic 64	uuuuuu/lqlllq$5:bp00700070ppp007000700070	I
      //   72: invokestatic 66	uuuuuu/lqlllq$5:b006F006Fo006Fo006F006F006Foo	()I
      //   75: getstatic 60	uuuuuu/lqlllq$5:b007000700070ppp007000700070	I
      //   78: iadd
      //   79: invokestatic 66	uuuuuu/lqlllq$5:b006F006Fo006Fo006F006F006Foo	()I
      //   82: imul
      //   83: getstatic 62	uuuuuu/lqlllq$5:bppp0070pp007000700070	I
      //   86: irem
      //   87: getstatic 64	uuuuuu/lqlllq$5:bp00700070ppp007000700070	I
      //   90: if_icmpeq +14 -> 104
      //   93: invokestatic 66	uuuuuu/lqlllq$5:b006F006Fo006Fo006F006F006Foo	()I
      //   96: putstatic 58	uuuuuu/lqlllq$5:b0070p0070ppp007000700070	I
      //   99: bipush 94
      //   101: putstatic 64	uuuuuu/lqlllq$5:bp00700070ppp007000700070	I
      //   104: ldc 68
      //   106: sipush 250
      //   109: iconst_0
      //   110: invokestatic 42	xxxxxx/uxxxxx:bb00620062bb0062b0062b0062	(Ljava/lang/String;CC)Ljava/lang/String;
      //   113: astore 8
      //   115: iconst_4
      //   116: anewarray 44	java/lang/Class
      //   119: astore 9
      //   121: aload 9
      //   123: iconst_0
      //   124: ldc 56
      //   126: aastore
      //   127: aload 9
      //   129: iconst_1
      //   130: getstatic 74	java/lang/Character:TYPE	Ljava/lang/Class;
      //   133: aastore
      //   134: aload 9
      //   136: iconst_2
      //   137: getstatic 74	java/lang/Character:TYPE	Ljava/lang/Class;
      //   140: aastore
      //   141: aload 9
      //   143: iconst_3
      //   144: getstatic 74	java/lang/Character:TYPE	Ljava/lang/Class;
      //   147: aastore
      //   148: ldc 76
      //   150: aload 8
      //   152: aload 9
      //   154: invokevirtual 48	java/lang/Class:getMethod	(Ljava/lang/String;[Ljava/lang/Class;)Ljava/lang/reflect/Method;
      //   157: astore 10
      //   159: iconst_4
      //   160: anewarray 4	java/lang/Object
      //   163: astore 11
      //   165: aload 11
      //   167: iconst_0
      //   168: ldc 78
      //   170: aastore
      //   171: aload 11
      //   173: iconst_1
      //   174: bipush 80
      //   176: invokestatic 82	java/lang/Character:valueOf	(C)Ljava/lang/Character;
      //   179: aastore
      //   180: aload 11
      //   182: iconst_2
      //   183: sipush 239
      //   186: invokestatic 82	java/lang/Character:valueOf	(C)Ljava/lang/Character;
      //   189: aastore
      //   190: aload 11
      //   192: iconst_3
      //   193: iconst_3
      //   194: invokestatic 82	java/lang/Character:valueOf	(C)Ljava/lang/Character;
      //   197: aastore
      //   198: aload 10
      //   200: aconst_null
      //   201: aload 11
      //   203: invokevirtual 54	java/lang/reflect/Method:invoke	(Ljava/lang/Object;[Ljava/lang/Object;)Ljava/lang/Object;
      //   206: astore 13
      //   208: aload 7
      //   210: aload 13
      //   212: checkcast 56	java/lang/String
      //   215: aload_2
      //   216: invokestatic 88	uuuuuu/rvvvrv:b00710071qq00710071q0071q0071	(Ljava/lang/String;Ljava/lang/String;Ljava/lang/Throwable;)V
      //   219: return
      //   220: astore 5
      //   222: aload 5
      //   224: invokevirtual 92	java/lang/reflect/InvocationTargetException:getCause	()Ljava/lang/Throwable;
      //   227: athrow
      //   228: astore 12
      //   230: aload 12
      //   232: invokevirtual 92	java/lang/reflect/InvocationTargetException:getCause	()Ljava/lang/Throwable;
      //   235: athrow
      // Local variable table:
      //   start	length	slot	name	signature
      //   0	236	0	this	5
      //   0	236	1	paramAnonymousInt	int
      //   0	236	2	paramAnonymousDbError	com.db.pwcc.dbmobile.model.error.DbError
      //   17	8	3	localMethod1	java.lang.reflect.Method
      //   22	5	4	arrayOfObject1	Object[]
      //   220	3	5	localInvocationTargetException1	java.lang.reflect.InvocationTargetException
      //   31	3	6	localObject1	Object
      //   38	171	7	str1	String
      //   113	38	8	str2	String
      //   119	34	9	arrayOfClass	Class[]
      //   157	42	10	localMethod2	java.lang.reflect.Method
      //   163	39	11	arrayOfObject2	Object[]
      //   228	3	12	localInvocationTargetException2	java.lang.reflect.InvocationTargetException
      //   206	5	13	localObject2	Object
      // Exception table:
      //   from	to	target	type
      //   24	33	220	java/lang/reflect/InvocationTargetException
      //   198	208	228	java/lang/reflect/InvocationTargetException
    }
    
    public void boooo006Foo006Foo()
    {
      vppvvp localVppvvp = lqlllq.this.bppppp0070p00700070;
      lqlllq localLqlllq = lqlllq.this;
      if ((b0070p0070ppp007000700070 + b007000700070ppp007000700070) * b0070p0070ppp007000700070 % bppp0070pp007000700070 != bp00700070ppp007000700070)
      {
        b0070p0070ppp007000700070 = 67;
        bp00700070ppp007000700070 = b006F006Fo006Fo006F006F006Foo();
        if ((b0070p0070ppp007000700070 + b007000700070ppp007000700070) * b0070p0070ppp007000700070 % bppp0070pp007000700070 != bp00700070ppp007000700070)
        {
          b0070p0070ppp007000700070 = 89;
          bp00700070ppp007000700070 = b006F006Fo006Fo006F006F006Foo();
        }
      }
      localVppvvp.b00700070ppp0070p00700070p(localLqlllq.b0070pppp0070p00700070);
    }
  };
  private Account b0070p007000700070pp00700070;
  @Inject
  public pqqqqq b0070p0070pp0070p00700070;
  public sxxxsx b0070pp0070p0070p00700070 = new sxxxsx();
  public vppvvp.pvpvvp b0070pppp0070p00700070 = new vppvvp.pvpvvp()
  {
    public static int b00700070pppp007000700070 = 1;
    public static int b0070ppppp007000700070 = 0;
    public static int bp0070pppp007000700070 = 2;
    public static int bpppppp007000700070 = 38;
    
    public static int b006Foo006Fo006F006F006Foo()
    {
      return 27;
    }
    
    public static int bo006Fo006Fo006F006F006Foo()
    {
      return 1;
    }
    
    /* Error */
    public void b0070pppp0070p00700070p(com.db.pwcc.dbmobile.model.error.DbError paramAnonymousDbError)
    {
      // Byte code:
      //   0: ldc 33
      //   2: ldc 35
      //   4: sipush 238
      //   7: sipush 244
      //   10: iconst_3
      //   11: invokestatic 41	xxxxxx/uxxxxx:bbbb0062b0062b0062b0062	(Ljava/lang/String;CCC)Ljava/lang/String;
      //   14: iconst_0
      //   15: anewarray 43	java/lang/Class
      //   18: invokevirtual 47	java/lang/Class:getMethod	(Ljava/lang/String;[Ljava/lang/Class;)Ljava/lang/reflect/Method;
      //   21: astore_2
      //   22: iconst_0
      //   23: anewarray 4	java/lang/Object
      //   26: astore_3
      //   27: aload_2
      //   28: aconst_null
      //   29: aload_3
      //   30: invokevirtual 53	java/lang/reflect/Method:invoke	(Ljava/lang/Object;[Ljava/lang/Object;)Ljava/lang/Object;
      //   33: astore 5
      //   35: aload 5
      //   37: checkcast 55	java/lang/String
      //   40: astore 6
      //   42: ldc 57
      //   44: bipush 73
      //   46: iconst_4
      //   47: invokestatic 61	xxxxxx/uxxxxx:bb00620062bb0062b0062b0062	(Ljava/lang/String;CC)Ljava/lang/String;
      //   50: astore 7
      //   52: iconst_3
      //   53: anewarray 43	java/lang/Class
      //   56: astore 8
      //   58: aload 8
      //   60: iconst_0
      //   61: ldc 55
      //   63: aastore
      //   64: aload 8
      //   66: iconst_1
      //   67: getstatic 67	java/lang/Character:TYPE	Ljava/lang/Class;
      //   70: aastore
      //   71: aload 8
      //   73: iconst_2
      //   74: getstatic 67	java/lang/Character:TYPE	Ljava/lang/Class;
      //   77: aastore
      //   78: ldc 69
      //   80: aload 7
      //   82: aload 8
      //   84: invokevirtual 47	java/lang/Class:getMethod	(Ljava/lang/String;[Ljava/lang/Class;)Ljava/lang/reflect/Method;
      //   87: astore 9
      //   89: iconst_3
      //   90: anewarray 4	java/lang/Object
      //   93: astore 10
      //   95: aload 10
      //   97: iconst_0
      //   98: ldc 71
      //   100: aastore
      //   101: aload 10
      //   103: iconst_1
      //   104: bipush 17
      //   106: invokestatic 75	java/lang/Character:valueOf	(C)Ljava/lang/Character;
      //   109: aastore
      //   110: aload 10
      //   112: iconst_2
      //   113: iconst_4
      //   114: invokestatic 75	java/lang/Character:valueOf	(C)Ljava/lang/Character;
      //   117: aastore
      //   118: aload 9
      //   120: aconst_null
      //   121: aload 10
      //   123: invokevirtual 53	java/lang/reflect/Method:invoke	(Ljava/lang/Object;[Ljava/lang/Object;)Ljava/lang/Object;
      //   126: astore 12
      //   128: aload 12
      //   130: checkcast 55	java/lang/String
      //   133: astore 13
      //   135: getstatic 77	uuuuuu/lqlllq$4:bpppppp007000700070	I
      //   138: invokestatic 79	uuuuuu/lqlllq$4:bo006Fo006Fo006F006F006Foo	()I
      //   141: iadd
      //   142: getstatic 77	uuuuuu/lqlllq$4:bpppppp007000700070	I
      //   145: imul
      //   146: getstatic 81	uuuuuu/lqlllq$4:bp0070pppp007000700070	I
      //   149: irem
      //   150: getstatic 83	uuuuuu/lqlllq$4:b0070ppppp007000700070	I
      //   153: if_icmpeq +62 -> 215
      //   156: bipush 11
      //   158: putstatic 77	uuuuuu/lqlllq$4:bpppppp007000700070	I
      //   161: invokestatic 85	uuuuuu/lqlllq$4:b006Foo006Fo006F006F006Foo	()I
      //   164: putstatic 83	uuuuuu/lqlllq$4:b0070ppppp007000700070	I
      //   167: getstatic 77	uuuuuu/lqlllq$4:bpppppp007000700070	I
      //   170: istore 14
      //   172: iload 14
      //   174: iload 14
      //   176: getstatic 87	uuuuuu/lqlllq$4:b00700070pppp007000700070	I
      //   179: iadd
      //   180: imul
      //   181: getstatic 81	uuuuuu/lqlllq$4:bp0070pppp007000700070	I
      //   184: irem
      //   185: tableswitch	default:+19->204, 0:+30->215
      //   204: bipush 29
      //   206: putstatic 77	uuuuuu/lqlllq$4:bpppppp007000700070	I
      //   209: invokestatic 85	uuuuuu/lqlllq$4:b006Foo006Fo006F006F006Foo	()I
      //   212: putstatic 83	uuuuuu/lqlllq$4:b0070ppppp007000700070	I
      //   215: aload 6
      //   217: aload 13
      //   219: aload_1
      //   220: invokestatic 93	uuuuuu/rvvvrv:b00710071qq00710071q0071q0071	(Ljava/lang/String;Ljava/lang/String;Ljava/lang/Throwable;)V
      //   223: return
      //   224: astore 4
      //   226: aload 4
      //   228: invokevirtual 97	java/lang/reflect/InvocationTargetException:getCause	()Ljava/lang/Throwable;
      //   231: athrow
      //   232: astore 11
      //   234: aload 11
      //   236: invokevirtual 97	java/lang/reflect/InvocationTargetException:getCause	()Ljava/lang/Throwable;
      //   239: athrow
      // Local variable table:
      //   start	length	slot	name	signature
      //   0	240	0	this	4
      //   0	240	1	paramAnonymousDbError	com.db.pwcc.dbmobile.model.error.DbError
      //   21	7	2	localMethod1	java.lang.reflect.Method
      //   26	4	3	arrayOfObject1	Object[]
      //   224	3	4	localInvocationTargetException1	java.lang.reflect.InvocationTargetException
      //   33	3	5	localObject1	Object
      //   40	176	6	str1	String
      //   50	31	7	str2	String
      //   56	27	8	arrayOfClass	Class[]
      //   87	32	9	localMethod2	java.lang.reflect.Method
      //   93	29	10	arrayOfObject2	Object[]
      //   232	3	11	localInvocationTargetException2	java.lang.reflect.InvocationTargetException
      //   126	3	12	localObject2	Object
      //   133	85	13	str3	String
      //   170	11	14	i	int
      // Exception table:
      //   from	to	target	type
      //   27	35	224	java/lang/reflect/InvocationTargetException
      //   118	128	232	java/lang/reflect/InvocationTargetException
    }
    
    /* Error */
    public void bp0070ppp0070p00700070p(com.db.pwcc.dbmobile.model.gini.GiniCredentials paramAnonymousGiniCredentials)
    {
      // Byte code:
      //   0: aload_0
      //   1: getfield 21	uuuuuu/lqlllq$4:b007000700070007000700070p00700070	Luuuuuu/lqlllq;
      //   4: getfield 103	uuuuuu/lqlllq:bp0070ppp0070p00700070	Luuuuuu/kvvkkk;
      //   7: aload_1
      //   8: invokevirtual 109	com/db/pwcc/dbmobile/model/gini/GiniCredentials:getUserId	()Ljava/lang/String;
      //   11: invokevirtual 115	uuuuuu/kvvkkk:b0071qq007100710071q0071qq	(Ljava/lang/String;)V
      //   14: aload_0
      //   15: getfield 21	uuuuuu/lqlllq$4:b007000700070007000700070p00700070	Luuuuuu/lqlllq;
      //   18: getfield 103	uuuuuu/lqlllq:bp0070ppp0070p00700070	Luuuuuu/kvvkkk;
      //   21: aload_1
      //   22: invokevirtual 118	com/db/pwcc/dbmobile/model/gini/GiniCredentials:getLicenseKey	()Ljava/lang/String;
      //   25: invokevirtual 121	uuuuuu/kvvkkk:bqqq007100710071q0071qq	(Ljava/lang/String;)V
      //   28: getstatic 77	uuuuuu/lqlllq$4:bpppppp007000700070	I
      //   31: getstatic 87	uuuuuu/lqlllq$4:b00700070pppp007000700070	I
      //   34: iadd
      //   35: getstatic 77	uuuuuu/lqlllq$4:bpppppp007000700070	I
      //   38: imul
      //   39: getstatic 81	uuuuuu/lqlllq$4:bp0070pppp007000700070	I
      //   42: irem
      //   43: getstatic 83	uuuuuu/lqlllq$4:b0070ppppp007000700070	I
      //   46: if_icmpeq +14 -> 60
      //   49: invokestatic 85	uuuuuu/lqlllq$4:b006Foo006Fo006F006F006Foo	()I
      //   52: putstatic 77	uuuuuu/lqlllq$4:bpppppp007000700070	I
      //   55: bipush 50
      //   57: putstatic 83	uuuuuu/lqlllq$4:b0070ppppp007000700070	I
      //   60: aload_0
      //   61: getfield 21	uuuuuu/lqlllq$4:b007000700070007000700070p00700070	Luuuuuu/lqlllq;
      //   64: astore_2
      //   65: ldc 33
      //   67: ldc 123
      //   69: bipush 126
      //   71: iconst_2
      //   72: invokestatic 61	xxxxxx/uxxxxx:bb00620062bb0062b0062b0062	(Ljava/lang/String;CC)Ljava/lang/String;
      //   75: iconst_1
      //   76: anewarray 43	java/lang/Class
      //   79: dup
      //   80: iconst_0
      //   81: ldc 33
      //   83: aastore
      //   84: invokevirtual 47	java/lang/Class:getMethod	(Ljava/lang/String;[Ljava/lang/Class;)Ljava/lang/reflect/Method;
      //   87: astore_3
      //   88: iconst_1
      //   89: anewarray 4	java/lang/Object
      //   92: dup
      //   93: iconst_0
      //   94: aload_2
      //   95: aastore
      //   96: astore 4
      //   98: aload_3
      //   99: aconst_null
      //   100: aload 4
      //   102: invokevirtual 53	java/lang/reflect/Method:invoke	(Ljava/lang/Object;[Ljava/lang/Object;)Ljava/lang/Object;
      //   105: astore 6
      //   107: aload 6
      //   109: checkcast 125	uuuuuu/ttssst$tsssst
      //   112: ifnull +118 -> 230
      //   115: aload_0
      //   116: getfield 21	uuuuuu/lqlllq$4:b007000700070007000700070p00700070	Luuuuuu/lqlllq;
      //   119: astore 7
      //   121: ldc 33
      //   123: ldc 127
      //   125: bipush 60
      //   127: bipush 53
      //   129: iconst_1
      //   130: invokestatic 41	xxxxxx/uxxxxx:bbbb0062b0062b0062b0062	(Ljava/lang/String;CCC)Ljava/lang/String;
      //   133: iconst_1
      //   134: anewarray 43	java/lang/Class
      //   137: dup
      //   138: iconst_0
      //   139: ldc 33
      //   141: aastore
      //   142: invokevirtual 47	java/lang/Class:getMethod	(Ljava/lang/String;[Ljava/lang/Class;)Ljava/lang/reflect/Method;
      //   145: astore 8
      //   147: iconst_1
      //   148: anewarray 4	java/lang/Object
      //   151: dup
      //   152: iconst_0
      //   153: aload 7
      //   155: aastore
      //   156: astore 9
      //   158: aload 8
      //   160: aconst_null
      //   161: aload 9
      //   163: invokevirtual 53	java/lang/reflect/Method:invoke	(Ljava/lang/Object;[Ljava/lang/Object;)Ljava/lang/Object;
      //   166: astore 11
      //   168: aload 11
      //   170: checkcast 125	uuuuuu/ttssst$tsssst
      //   173: checkcast 129	uuuuuu/lllqql$lqlqql
      //   176: getstatic 134	com/db/pwcc/dbmobile/financial_overview/R$id:menu_item_photo_transfer	I
      //   179: invokeinterface 138 2 0
      //   184: getstatic 77	uuuuuu/lqlllq$4:bpppppp007000700070	I
      //   187: istore 12
      //   189: iload 12
      //   191: iload 12
      //   193: getstatic 87	uuuuuu/lqlllq$4:b00700070pppp007000700070	I
      //   196: iadd
      //   197: imul
      //   198: getstatic 81	uuuuuu/lqlllq$4:bp0070pppp007000700070	I
      //   201: irem
      //   202: tableswitch	default:+18->220, 0:+28->230
      //   220: bipush 53
      //   222: putstatic 77	uuuuuu/lqlllq$4:bpppppp007000700070	I
      //   225: bipush 87
      //   227: putstatic 83	uuuuuu/lqlllq$4:b0070ppppp007000700070	I
      //   230: return
      //   231: astore 5
      //   233: aload 5
      //   235: invokevirtual 97	java/lang/reflect/InvocationTargetException:getCause	()Ljava/lang/Throwable;
      //   238: athrow
      //   239: astore 10
      //   241: aload 10
      //   243: invokevirtual 97	java/lang/reflect/InvocationTargetException:getCause	()Ljava/lang/Throwable;
      //   246: athrow
      // Local variable table:
      //   start	length	slot	name	signature
      //   0	247	0	this	4
      //   0	247	1	paramAnonymousGiniCredentials	com.db.pwcc.dbmobile.model.gini.GiniCredentials
      //   64	31	2	localLqlllq1	lqlllq
      //   87	12	3	localMethod1	java.lang.reflect.Method
      //   96	5	4	arrayOfObject1	Object[]
      //   231	3	5	localInvocationTargetException1	java.lang.reflect.InvocationTargetException
      //   105	3	6	localObject1	Object
      //   119	35	7	localLqlllq2	lqlllq
      //   145	14	8	localMethod2	java.lang.reflect.Method
      //   156	6	9	arrayOfObject2	Object[]
      //   239	3	10	localInvocationTargetException2	java.lang.reflect.InvocationTargetException
      //   166	3	11	localObject2	Object
      //   187	11	12	i	int
      // Exception table:
      //   from	to	target	type
      //   98	107	231	java/lang/reflect/InvocationTargetException
      //   158	168	239	java/lang/reflect/InvocationTargetException
    }
  };
  private String bp0070007000700070pp00700070;
  public sxxxsx.xsxsxx bp00700070pp0070p00700070 = new sxxxsx.xsxsxx()
  {
    public static int b00700070pp00700070p00700070 = 2;
    public static int b0070ppp00700070p00700070 = 0;
    public static int bp0070pp00700070p00700070 = 1;
    public static int bpp0070p00700070p00700070 = 69;
    
    public static int b006F006Fooo006F006F006Foo()
    {
      return 25;
    }
    
    public static int b006Foooo006F006F006Foo()
    {
      return 2;
    }
    
    public static int bo006Fooo006F006F006Foo()
    {
      return 1;
    }
    
    public static int boo006Foo006F006F006Foo()
    {
      return 0;
    }
    
    public void b006Fooo006Foo006Foo(int paramAnonymousInt) {}
    
    /* Error */
    public void bo006Foo006Foo006Foo(int paramAnonymousInt, com.db.pwcc.dbmobile.model.error.DbError paramAnonymousDbError)
    {
      // Byte code:
      //   0: ldc 37
      //   2: ldc 39
      //   4: sipush 169
      //   7: sipush 132
      //   10: iconst_3
      //   11: invokestatic 45	xxxxxx/uxxxxx:bbbb0062b0062b0062b0062	(Ljava/lang/String;CCC)Ljava/lang/String;
      //   14: iconst_0
      //   15: anewarray 47	java/lang/Class
      //   18: invokevirtual 51	java/lang/Class:getMethod	(Ljava/lang/String;[Ljava/lang/Class;)Ljava/lang/reflect/Method;
      //   21: astore_3
      //   22: iconst_0
      //   23: anewarray 4	java/lang/Object
      //   26: astore 4
      //   28: aload_3
      //   29: aconst_null
      //   30: aload 4
      //   32: invokevirtual 57	java/lang/reflect/Method:invoke	(Ljava/lang/Object;[Ljava/lang/Object;)Ljava/lang/Object;
      //   35: astore 6
      //   37: aload 6
      //   39: checkcast 59	java/lang/String
      //   42: astore 7
      //   44: ldc 61
      //   46: bipush 125
      //   48: sipush 211
      //   51: iconst_2
      //   52: invokestatic 45	xxxxxx/uxxxxx:bbbb0062b0062b0062b0062	(Ljava/lang/String;CCC)Ljava/lang/String;
      //   55: astore 8
      //   57: iconst_4
      //   58: anewarray 47	java/lang/Class
      //   61: astore 9
      //   63: aload 9
      //   65: iconst_0
      //   66: ldc 59
      //   68: aastore
      //   69: aload 9
      //   71: iconst_1
      //   72: getstatic 67	java/lang/Character:TYPE	Ljava/lang/Class;
      //   75: aastore
      //   76: aload 9
      //   78: iconst_2
      //   79: getstatic 67	java/lang/Character:TYPE	Ljava/lang/Class;
      //   82: aastore
      //   83: aload 9
      //   85: iconst_3
      //   86: getstatic 67	java/lang/Character:TYPE	Ljava/lang/Class;
      //   89: aastore
      //   90: ldc 69
      //   92: aload 8
      //   94: aload 9
      //   96: invokevirtual 51	java/lang/Class:getMethod	(Ljava/lang/String;[Ljava/lang/Class;)Ljava/lang/reflect/Method;
      //   99: astore 10
      //   101: iconst_4
      //   102: anewarray 4	java/lang/Object
      //   105: astore 11
      //   107: aload 11
      //   109: iconst_0
      //   110: ldc 71
      //   112: aastore
      //   113: aload 11
      //   115: iconst_1
      //   116: sipush 205
      //   119: invokestatic 75	java/lang/Character:valueOf	(C)Ljava/lang/Character;
      //   122: aastore
      //   123: aload 11
      //   125: iconst_2
      //   126: bipush 13
      //   128: invokestatic 75	java/lang/Character:valueOf	(C)Ljava/lang/Character;
      //   131: aastore
      //   132: aload 11
      //   134: iconst_3
      //   135: iconst_1
      //   136: invokestatic 75	java/lang/Character:valueOf	(C)Ljava/lang/Character;
      //   139: aastore
      //   140: aload 10
      //   142: aconst_null
      //   143: aload 11
      //   145: invokevirtual 57	java/lang/reflect/Method:invoke	(Ljava/lang/Object;[Ljava/lang/Object;)Ljava/lang/Object;
      //   148: astore 13
      //   150: aload 7
      //   152: aload 13
      //   154: checkcast 59	java/lang/String
      //   157: aload_2
      //   158: invokestatic 81	uuuuuu/rvvvrv:b00710071qq00710071q0071q0071	(Ljava/lang/String;Ljava/lang/String;Ljava/lang/Throwable;)V
      //   161: getstatic 83	uuuuuu/lqlllq$1:bpp0070p00700070p00700070	I
      //   164: invokestatic 85	uuuuuu/lqlllq$1:bo006Fooo006F006F006Foo	()I
      //   167: iadd
      //   168: getstatic 83	uuuuuu/lqlllq$1:bpp0070p00700070p00700070	I
      //   171: imul
      //   172: getstatic 87	uuuuuu/lqlllq$1:b00700070pp00700070p00700070	I
      //   175: irem
      //   176: invokestatic 89	uuuuuu/lqlllq$1:boo006Foo006F006F006Foo	()I
      //   179: if_icmpeq +47 -> 226
      //   182: getstatic 83	uuuuuu/lqlllq$1:bpp0070p00700070p00700070	I
      //   185: getstatic 91	uuuuuu/lqlllq$1:bp0070pp00700070p00700070	I
      //   188: iadd
      //   189: getstatic 83	uuuuuu/lqlllq$1:bpp0070p00700070p00700070	I
      //   192: imul
      //   193: invokestatic 93	uuuuuu/lqlllq$1:b006Foooo006F006F006Foo	()I
      //   196: irem
      //   197: getstatic 95	uuuuuu/lqlllq$1:b0070ppp00700070p00700070	I
      //   200: if_icmpeq +15 -> 215
      //   203: invokestatic 97	uuuuuu/lqlllq$1:b006F006Fooo006F006F006Foo	()I
      //   206: putstatic 83	uuuuuu/lqlllq$1:bpp0070p00700070p00700070	I
      //   209: invokestatic 97	uuuuuu/lqlllq$1:b006F006Fooo006F006F006Foo	()I
      //   212: putstatic 95	uuuuuu/lqlllq$1:b0070ppp00700070p00700070	I
      //   215: invokestatic 97	uuuuuu/lqlllq$1:b006F006Fooo006F006F006Foo	()I
      //   218: putstatic 83	uuuuuu/lqlllq$1:bpp0070p00700070p00700070	I
      //   221: bipush 10
      //   223: putstatic 95	uuuuuu/lqlllq$1:b0070ppp00700070p00700070	I
      //   226: return
      //   227: astore 5
      //   229: aload 5
      //   231: invokevirtual 101	java/lang/reflect/InvocationTargetException:getCause	()Ljava/lang/Throwable;
      //   234: athrow
      //   235: astore 12
      //   237: aload 12
      //   239: invokevirtual 101	java/lang/reflect/InvocationTargetException:getCause	()Ljava/lang/Throwable;
      //   242: athrow
      // Local variable table:
      //   start	length	slot	name	signature
      //   0	243	0	this	1
      //   0	243	1	paramAnonymousInt	int
      //   0	243	2	paramAnonymousDbError	com.db.pwcc.dbmobile.model.error.DbError
      //   21	8	3	localMethod1	java.lang.reflect.Method
      //   26	5	4	arrayOfObject1	Object[]
      //   227	3	5	localInvocationTargetException1	java.lang.reflect.InvocationTargetException
      //   35	3	6	localObject1	Object
      //   42	109	7	str1	String
      //   55	38	8	str2	String
      //   61	34	9	arrayOfClass	Class[]
      //   99	42	10	localMethod2	java.lang.reflect.Method
      //   105	39	11	arrayOfObject2	Object[]
      //   235	3	12	localInvocationTargetException2	java.lang.reflect.InvocationTargetException
      //   148	5	13	localObject2	Object
      // Exception table:
      //   from	to	target	type
      //   28	37	227	java/lang/reflect/InvocationTargetException
      //   140	150	235	java/lang/reflect/InvocationTargetException
    }
    
    /* Error */
    public void boooo006Foo006Foo()
    {
      // Byte code:
      //   0: aload_0
      //   1: getfield 21	uuuuuu/lqlllq$1:bpppp00700070p00700070	Luuuuuu/lqlllq;
      //   4: astore_1
      //   5: getstatic 83	uuuuuu/lqlllq$1:bpp0070p00700070p00700070	I
      //   8: istore_2
      //   9: iload_2
      //   10: iload_2
      //   11: getstatic 91	uuuuuu/lqlllq$1:bp0070pp00700070p00700070	I
      //   14: iadd
      //   15: imul
      //   16: invokestatic 93	uuuuuu/lqlllq$1:b006Foooo006F006F006Foo	()I
      //   19: irem
      //   20: tableswitch	default:+20->40, 0:+31->51
      //   40: bipush 26
      //   42: putstatic 83	uuuuuu/lqlllq$1:bpp0070p00700070p00700070	I
      //   45: invokestatic 97	uuuuuu/lqlllq$1:b006F006Fooo006F006F006Foo	()I
      //   48: putstatic 95	uuuuuu/lqlllq$1:b0070ppp00700070p00700070	I
      //   51: ldc 37
      //   53: ldc 104
      //   55: sipush 162
      //   58: iconst_5
      //   59: invokestatic 108	xxxxxx/uxxxxx:bb00620062bb0062b0062b0062	(Ljava/lang/String;CC)Ljava/lang/String;
      //   62: iconst_1
      //   63: anewarray 47	java/lang/Class
      //   66: dup
      //   67: iconst_0
      //   68: ldc 37
      //   70: aastore
      //   71: invokevirtual 51	java/lang/Class:getMethod	(Ljava/lang/String;[Ljava/lang/Class;)Ljava/lang/reflect/Method;
      //   74: astore_3
      //   75: iconst_1
      //   76: anewarray 4	java/lang/Object
      //   79: dup
      //   80: iconst_0
      //   81: aload_1
      //   82: aastore
      //   83: astore 4
      //   85: aload_3
      //   86: aconst_null
      //   87: aload 4
      //   89: invokevirtual 57	java/lang/reflect/Method:invoke	(Ljava/lang/Object;[Ljava/lang/Object;)Ljava/lang/Object;
      //   92: astore 6
      //   94: aload 6
      //   96: checkcast 110	uuuuuu/ttssst$tsssst
      //   99: ifnull +191 -> 290
      //   102: aload_0
      //   103: getfield 21	uuuuuu/lqlllq$1:bpppp00700070p00700070	Luuuuuu/lqlllq;
      //   106: astore 7
      //   108: ldc 37
      //   110: ldc 112
      //   112: sipush 200
      //   115: sipush 226
      //   118: iconst_3
      //   119: invokestatic 45	xxxxxx/uxxxxx:bbbb0062b0062b0062b0062	(Ljava/lang/String;CCC)Ljava/lang/String;
      //   122: iconst_1
      //   123: anewarray 47	java/lang/Class
      //   126: dup
      //   127: iconst_0
      //   128: ldc 37
      //   130: aastore
      //   131: invokevirtual 51	java/lang/Class:getMethod	(Ljava/lang/String;[Ljava/lang/Class;)Ljava/lang/reflect/Method;
      //   134: astore 8
      //   136: iconst_1
      //   137: anewarray 4	java/lang/Object
      //   140: dup
      //   141: iconst_0
      //   142: aload 7
      //   144: aastore
      //   145: astore 9
      //   147: aload 8
      //   149: aconst_null
      //   150: aload 9
      //   152: invokevirtual 57	java/lang/reflect/Method:invoke	(Ljava/lang/Object;[Ljava/lang/Object;)Ljava/lang/Object;
      //   155: astore 11
      //   157: aload 11
      //   159: checkcast 110	uuuuuu/ttssst$tsssst
      //   162: checkcast 114	uuuuuu/lllqql$lqlqql
      //   165: getstatic 119	com/db/pwcc/dbmobile/financial_overview/R$id:menu_item_new_transaction	I
      //   168: invokeinterface 122 2 0
      //   173: aload_0
      //   174: getfield 21	uuuuuu/lqlllq$1:bpppp00700070p00700070	Luuuuuu/lqlllq;
      //   177: getfield 126	uuuuuu/lqlllq:b00700070007000700070pp00700070	Luuuuuu/sssttt;
      //   180: getstatic 132	com/db/pwcc/dbmobile/foundation/features/Feature:SEPAFLOW	Lcom/db/pwcc/dbmobile/foundation/features/Feature;
      //   183: invokevirtual 138	uuuuuu/sssttt:bk006Bkkk006B006B006Bkk	(Lcom/db/pwcc/dbmobile/foundation/features/Feature;)Luuuuuu/sststt;
      //   186: astore 12
      //   188: invokestatic 97	uuuuuu/lqlllq$1:b006F006Fooo006F006F006Foo	()I
      //   191: getstatic 91	uuuuuu/lqlllq$1:bp0070pp00700070p00700070	I
      //   194: iadd
      //   195: invokestatic 97	uuuuuu/lqlllq$1:b006F006Fooo006F006F006Foo	()I
      //   198: imul
      //   199: getstatic 87	uuuuuu/lqlllq$1:b00700070pp00700070p00700070	I
      //   202: irem
      //   203: getstatic 95	uuuuuu/lqlllq$1:b0070ppp00700070p00700070	I
      //   206: if_icmpeq +9 -> 215
      //   209: invokestatic 97	uuuuuu/lqlllq$1:b006F006Fooo006F006F006Foo	()I
      //   212: putstatic 95	uuuuuu/lqlllq$1:b0070ppp00700070p00700070	I
      //   215: aload 12
      //   217: getstatic 144	uuuuuu/sststt:b006En006En006Enn006En	Luuuuuu/sststt;
      //   220: if_acmpne +70 -> 290
      //   223: aload_0
      //   224: getfield 21	uuuuuu/lqlllq$1:bpppp00700070p00700070	Luuuuuu/lqlllq;
      //   227: astore 13
      //   229: ldc 37
      //   231: ldc -110
      //   233: bipush 91
      //   235: iconst_0
      //   236: invokestatic 108	xxxxxx/uxxxxx:bb00620062bb0062b0062b0062	(Ljava/lang/String;CC)Ljava/lang/String;
      //   239: iconst_1
      //   240: anewarray 47	java/lang/Class
      //   243: dup
      //   244: iconst_0
      //   245: ldc 37
      //   247: aastore
      //   248: invokevirtual 51	java/lang/Class:getMethod	(Ljava/lang/String;[Ljava/lang/Class;)Ljava/lang/reflect/Method;
      //   251: astore 14
      //   253: iconst_1
      //   254: anewarray 4	java/lang/Object
      //   257: dup
      //   258: iconst_0
      //   259: aload 13
      //   261: aastore
      //   262: astore 15
      //   264: aload 14
      //   266: aconst_null
      //   267: aload 15
      //   269: invokevirtual 57	java/lang/reflect/Method:invoke	(Ljava/lang/Object;[Ljava/lang/Object;)Ljava/lang/Object;
      //   272: astore 17
      //   274: aload 17
      //   276: checkcast 110	uuuuuu/ttssst$tsssst
      //   279: checkcast 114	uuuuuu/lllqql$lqlqql
      //   282: getstatic 149	com/db/pwcc/dbmobile/financial_overview/R$id:menu_item_new_transfer_sepa_flow	I
      //   285: invokeinterface 122 2 0
      //   290: return
      //   291: astore 16
      //   293: aload 16
      //   295: invokevirtual 101	java/lang/reflect/InvocationTargetException:getCause	()Ljava/lang/Throwable;
      //   298: athrow
      //   299: astore 5
      //   301: aload 5
      //   303: invokevirtual 101	java/lang/reflect/InvocationTargetException:getCause	()Ljava/lang/Throwable;
      //   306: athrow
      //   307: astore 10
      //   309: aload 10
      //   311: invokevirtual 101	java/lang/reflect/InvocationTargetException:getCause	()Ljava/lang/Throwable;
      //   314: athrow
      // Local variable table:
      //   start	length	slot	name	signature
      //   0	315	0	this	1
      //   4	78	1	localLqlllq1	lqlllq
      //   8	8	2	i	int
      //   74	12	3	localMethod1	java.lang.reflect.Method
      //   83	5	4	arrayOfObject1	Object[]
      //   299	3	5	localInvocationTargetException1	java.lang.reflect.InvocationTargetException
      //   92	3	6	localObject1	Object
      //   106	37	7	localLqlllq2	lqlllq
      //   134	14	8	localMethod2	java.lang.reflect.Method
      //   145	6	9	arrayOfObject2	Object[]
      //   307	3	10	localInvocationTargetException2	java.lang.reflect.InvocationTargetException
      //   155	3	11	localObject2	Object
      //   186	30	12	localSststt	sststt
      //   227	33	13	localLqlllq3	lqlllq
      //   251	14	14	localMethod3	java.lang.reflect.Method
      //   262	6	15	arrayOfObject3	Object[]
      //   291	3	16	localInvocationTargetException3	java.lang.reflect.InvocationTargetException
      //   272	3	17	localObject3	Object
      // Exception table:
      //   from	to	target	type
      //   264	274	291	java/lang/reflect/InvocationTargetException
      //   85	94	299	java/lang/reflect/InvocationTargetException
      //   147	157	307	java/lang/reflect/InvocationTargetException
    }
  };
  public sxxxsx bp0070p0070p0070p00700070 = new sxxxsx();
  @Inject
  public kvvkkk bp0070ppp0070p00700070;
  public sxxxsx bpp0070pp0070p00700070 = new sxxxsx();
  public sxxxsx.xsxsxx bppp0070p0070p00700070 = new sxxxsx.xsxsxx()
  {
    public static int b00700070p007000700070p00700070 = 28;
    public static int b0070p0070007000700070p00700070 = 1;
    public static int bp00700070007000700070p00700070 = 2;
    public static int bpp0070007000700070p00700070;
    
    public static int booo006Fo006F006F006Foo()
    {
      return 64;
    }
    
    public void b006Fooo006Foo006Foo(int paramAnonymousInt) {}
    
    /* Error */
    public void bo006Foo006Foo006Foo(int paramAnonymousInt, com.db.pwcc.dbmobile.model.error.DbError paramAnonymousDbError)
    {
      // Byte code:
      //   0: ldc 33
      //   2: ldc 35
      //   4: sipush 132
      //   7: bipush 126
      //   9: iconst_2
      //   10: invokestatic 41	xxxxxx/uxxxxx:bbbb0062b0062b0062b0062	(Ljava/lang/String;CCC)Ljava/lang/String;
      //   13: iconst_0
      //   14: anewarray 43	java/lang/Class
      //   17: invokevirtual 47	java/lang/Class:getMethod	(Ljava/lang/String;[Ljava/lang/Class;)Ljava/lang/reflect/Method;
      //   20: astore_3
      //   21: iconst_0
      //   22: anewarray 4	java/lang/Object
      //   25: astore 4
      //   27: aload_3
      //   28: aconst_null
      //   29: aload 4
      //   31: invokevirtual 53	java/lang/reflect/Method:invoke	(Ljava/lang/Object;[Ljava/lang/Object;)Ljava/lang/Object;
      //   34: astore 6
      //   36: aload 6
      //   38: checkcast 55	java/lang/String
      //   41: astore 7
      //   43: getstatic 57	uuuuuu/lqlllq$3:b00700070p007000700070p00700070	I
      //   46: getstatic 59	uuuuuu/lqlllq$3:b0070p0070007000700070p00700070	I
      //   49: iadd
      //   50: getstatic 57	uuuuuu/lqlllq$3:b00700070p007000700070p00700070	I
      //   53: imul
      //   54: getstatic 61	uuuuuu/lqlllq$3:bp00700070007000700070p00700070	I
      //   57: irem
      //   58: getstatic 63	uuuuuu/lqlllq$3:bpp0070007000700070p00700070	I
      //   61: if_icmpeq +15 -> 76
      //   64: invokestatic 65	uuuuuu/lqlllq$3:booo006Fo006F006F006Foo	()I
      //   67: putstatic 57	uuuuuu/lqlllq$3:b00700070p007000700070p00700070	I
      //   70: invokestatic 65	uuuuuu/lqlllq$3:booo006Fo006F006F006Foo	()I
      //   73: putstatic 63	uuuuuu/lqlllq$3:bpp0070007000700070p00700070	I
      //   76: ldc 67
      //   78: sipush 174
      //   81: bipush 57
      //   83: iconst_1
      //   84: invokestatic 41	xxxxxx/uxxxxx:bbbb0062b0062b0062b0062	(Ljava/lang/String;CCC)Ljava/lang/String;
      //   87: astore 8
      //   89: iconst_4
      //   90: anewarray 43	java/lang/Class
      //   93: astore 9
      //   95: aload 9
      //   97: iconst_0
      //   98: ldc 55
      //   100: aastore
      //   101: aload 9
      //   103: iconst_1
      //   104: getstatic 73	java/lang/Character:TYPE	Ljava/lang/Class;
      //   107: aastore
      //   108: aload 9
      //   110: iconst_2
      //   111: getstatic 73	java/lang/Character:TYPE	Ljava/lang/Class;
      //   114: aastore
      //   115: aload 9
      //   117: iconst_3
      //   118: getstatic 73	java/lang/Character:TYPE	Ljava/lang/Class;
      //   121: aastore
      //   122: ldc 75
      //   124: aload 8
      //   126: aload 9
      //   128: invokevirtual 47	java/lang/Class:getMethod	(Ljava/lang/String;[Ljava/lang/Class;)Ljava/lang/reflect/Method;
      //   131: astore 10
      //   133: iconst_4
      //   134: anewarray 4	java/lang/Object
      //   137: astore 11
      //   139: aload 11
      //   141: iconst_0
      //   142: ldc 77
      //   144: aastore
      //   145: aload 11
      //   147: iconst_1
      //   148: bipush 126
      //   150: invokestatic 81	java/lang/Character:valueOf	(C)Ljava/lang/Character;
      //   153: aastore
      //   154: aload 11
      //   156: iconst_2
      //   157: sipush 180
      //   160: invokestatic 81	java/lang/Character:valueOf	(C)Ljava/lang/Character;
      //   163: aastore
      //   164: aload 11
      //   166: iconst_3
      //   167: iconst_1
      //   168: invokestatic 81	java/lang/Character:valueOf	(C)Ljava/lang/Character;
      //   171: aastore
      //   172: aload 10
      //   174: aconst_null
      //   175: aload 11
      //   177: invokevirtual 53	java/lang/reflect/Method:invoke	(Ljava/lang/Object;[Ljava/lang/Object;)Ljava/lang/Object;
      //   180: astore 13
      //   182: aload 13
      //   184: checkcast 55	java/lang/String
      //   187: astore 14
      //   189: getstatic 57	uuuuuu/lqlllq$3:b00700070p007000700070p00700070	I
      //   192: getstatic 59	uuuuuu/lqlllq$3:b0070p0070007000700070p00700070	I
      //   195: iadd
      //   196: getstatic 57	uuuuuu/lqlllq$3:b00700070p007000700070p00700070	I
      //   199: imul
      //   200: getstatic 61	uuuuuu/lqlllq$3:bp00700070007000700070p00700070	I
      //   203: irem
      //   204: getstatic 63	uuuuuu/lqlllq$3:bpp0070007000700070p00700070	I
      //   207: if_icmpeq +13 -> 220
      //   210: bipush 57
      //   212: putstatic 57	uuuuuu/lqlllq$3:b00700070p007000700070p00700070	I
      //   215: bipush 38
      //   217: putstatic 63	uuuuuu/lqlllq$3:bpp0070007000700070p00700070	I
      //   220: aload 7
      //   222: aload 14
      //   224: aload_2
      //   225: invokestatic 87	uuuuuu/rvvvrv:b00710071qq00710071q0071q0071	(Ljava/lang/String;Ljava/lang/String;Ljava/lang/Throwable;)V
      //   228: return
      //   229: astore 12
      //   231: aload 12
      //   233: invokevirtual 91	java/lang/reflect/InvocationTargetException:getCause	()Ljava/lang/Throwable;
      //   236: athrow
      //   237: astore 5
      //   239: aload 5
      //   241: invokevirtual 91	java/lang/reflect/InvocationTargetException:getCause	()Ljava/lang/Throwable;
      //   244: athrow
      // Local variable table:
      //   start	length	slot	name	signature
      //   0	245	0	this	3
      //   0	245	1	paramAnonymousInt	int
      //   0	245	2	paramAnonymousDbError	com.db.pwcc.dbmobile.model.error.DbError
      //   20	8	3	localMethod1	java.lang.reflect.Method
      //   25	5	4	arrayOfObject1	Object[]
      //   237	3	5	localInvocationTargetException1	java.lang.reflect.InvocationTargetException
      //   34	3	6	localObject1	Object
      //   41	180	7	str1	String
      //   87	38	8	str2	String
      //   93	34	9	arrayOfClass	Class[]
      //   131	42	10	localMethod2	java.lang.reflect.Method
      //   137	39	11	arrayOfObject2	Object[]
      //   229	3	12	localInvocationTargetException2	java.lang.reflect.InvocationTargetException
      //   180	3	13	localObject2	Object
      //   187	36	14	str3	String
      // Exception table:
      //   from	to	target	type
      //   172	182	229	java/lang/reflect/InvocationTargetException
      //   27	36	237	java/lang/reflect/InvocationTargetException
    }
    
    /* Error */
    public void boooo006Foo006Foo()
    {
      // Byte code:
      //   0: aload_0
      //   1: getfield 20	uuuuuu/lqlllq$3:bp0070p007000700070p00700070	Luuuuuu/lqlllq;
      //   4: astore_1
      //   5: ldc 33
      //   7: ldc 94
      //   9: sipush 185
      //   12: iconst_4
      //   13: invokestatic 98	xxxxxx/uxxxxx:bb00620062bb0062b0062b0062	(Ljava/lang/String;CC)Ljava/lang/String;
      //   16: iconst_1
      //   17: anewarray 43	java/lang/Class
      //   20: dup
      //   21: iconst_0
      //   22: ldc 33
      //   24: aastore
      //   25: invokevirtual 47	java/lang/Class:getMethod	(Ljava/lang/String;[Ljava/lang/Class;)Ljava/lang/reflect/Method;
      //   28: astore_2
      //   29: iconst_1
      //   30: anewarray 4	java/lang/Object
      //   33: dup
      //   34: iconst_0
      //   35: aload_1
      //   36: aastore
      //   37: astore_3
      //   38: aload_2
      //   39: aconst_null
      //   40: aload_3
      //   41: invokevirtual 53	java/lang/reflect/Method:invoke	(Ljava/lang/Object;[Ljava/lang/Object;)Ljava/lang/Object;
      //   44: astore 5
      //   46: aload 5
      //   48: checkcast 100	uuuuuu/ttssst$tsssst
      //   51: ifnull +150 -> 201
      //   54: aload_0
      //   55: getfield 20	uuuuuu/lqlllq$3:bp0070p007000700070p00700070	Luuuuuu/lqlllq;
      //   58: astore 6
      //   60: ldc 33
      //   62: ldc 102
      //   64: bipush 90
      //   66: iconst_3
      //   67: invokestatic 98	xxxxxx/uxxxxx:bb00620062bb0062b0062b0062	(Ljava/lang/String;CC)Ljava/lang/String;
      //   70: iconst_1
      //   71: anewarray 43	java/lang/Class
      //   74: dup
      //   75: iconst_0
      //   76: ldc 33
      //   78: aastore
      //   79: invokevirtual 47	java/lang/Class:getMethod	(Ljava/lang/String;[Ljava/lang/Class;)Ljava/lang/reflect/Method;
      //   82: astore 7
      //   84: iconst_1
      //   85: anewarray 4	java/lang/Object
      //   88: dup
      //   89: iconst_0
      //   90: aload 6
      //   92: aastore
      //   93: astore 8
      //   95: aload 7
      //   97: aconst_null
      //   98: aload 8
      //   100: invokevirtual 53	java/lang/reflect/Method:invoke	(Ljava/lang/Object;[Ljava/lang/Object;)Ljava/lang/Object;
      //   103: astore 10
      //   105: aload 10
      //   107: checkcast 100	uuuuuu/ttssst$tsssst
      //   110: checkcast 104	uuuuuu/lllqql$lqlqql
      //   113: getstatic 109	com/db/pwcc/dbmobile/financial_overview/R$id:menu_item_new_standing_order	I
      //   116: invokeinterface 112 2 0
      //   121: getstatic 57	uuuuuu/lqlllq$3:b00700070p007000700070p00700070	I
      //   124: getstatic 59	uuuuuu/lqlllq$3:b0070p0070007000700070p00700070	I
      //   127: iadd
      //   128: getstatic 57	uuuuuu/lqlllq$3:b00700070p007000700070p00700070	I
      //   131: imul
      //   132: getstatic 61	uuuuuu/lqlllq$3:bp00700070007000700070p00700070	I
      //   135: irem
      //   136: getstatic 63	uuuuuu/lqlllq$3:bpp0070007000700070p00700070	I
      //   139: if_icmpeq +62 -> 201
      //   142: invokestatic 65	uuuuuu/lqlllq$3:booo006Fo006F006F006Foo	()I
      //   145: istore 11
      //   147: iload 11
      //   149: iload 11
      //   151: getstatic 59	uuuuuu/lqlllq$3:b0070p0070007000700070p00700070	I
      //   154: iadd
      //   155: imul
      //   156: getstatic 61	uuuuuu/lqlllq$3:bp00700070007000700070p00700070	I
      //   159: irem
      //   160: tableswitch	default:+20->180, 0:+31->191
      //   180: invokestatic 65	uuuuuu/lqlllq$3:booo006Fo006F006F006Foo	()I
      //   183: putstatic 57	uuuuuu/lqlllq$3:b00700070p007000700070p00700070	I
      //   186: bipush 32
      //   188: putstatic 63	uuuuuu/lqlllq$3:bpp0070007000700070p00700070	I
      //   191: bipush 36
      //   193: putstatic 57	uuuuuu/lqlllq$3:b00700070p007000700070p00700070	I
      //   196: bipush 57
      //   198: putstatic 63	uuuuuu/lqlllq$3:bpp0070007000700070p00700070	I
      //   201: return
      //   202: astore 4
      //   204: aload 4
      //   206: invokevirtual 91	java/lang/reflect/InvocationTargetException:getCause	()Ljava/lang/Throwable;
      //   209: athrow
      //   210: astore 9
      //   212: aload 9
      //   214: invokevirtual 91	java/lang/reflect/InvocationTargetException:getCause	()Ljava/lang/Throwable;
      //   217: athrow
      // Local variable table:
      //   start	length	slot	name	signature
      //   0	218	0	this	3
      //   4	32	1	localLqlllq1	lqlllq
      //   28	11	2	localMethod1	java.lang.reflect.Method
      //   37	4	3	arrayOfObject1	Object[]
      //   202	3	4	localInvocationTargetException1	java.lang.reflect.InvocationTargetException
      //   44	3	5	localObject1	Object
      //   58	33	6	localLqlllq2	lqlllq
      //   82	14	7	localMethod2	java.lang.reflect.Method
      //   93	6	8	arrayOfObject2	Object[]
      //   210	3	9	localInvocationTargetException2	java.lang.reflect.InvocationTargetException
      //   103	3	10	localObject2	Object
      //   145	11	11	i	int
      // Exception table:
      //   from	to	target	type
      //   38	46	202	java/lang/reflect/InvocationTargetException
      //   95	105	210	java/lang/reflect/InvocationTargetException
    }
  };
  public vppvvp bppppp0070p00700070 = new mmfffm();
  
  /* Error */
  static
  {
    // Byte code:
    //   0: getstatic 50	uuuuuu/lqlllq:bpp00700070p0070p00700070	I
    //   3: istore_0
    //   4: iload_0
    //   5: getstatic 52	uuuuuu/lqlllq:b0070p00700070p0070p00700070	I
    //   8: iadd
    //   9: istore_1
    //   10: getstatic 50	uuuuuu/lqlllq:bpp00700070p0070p00700070	I
    //   13: getstatic 52	uuuuuu/lqlllq:b0070p00700070p0070p00700070	I
    //   16: iadd
    //   17: getstatic 50	uuuuuu/lqlllq:bpp00700070p0070p00700070	I
    //   20: imul
    //   21: istore_2
    //   22: ldc 2
    //   24: ldc 54
    //   26: bipush 36
    //   28: iconst_4
    //   29: invokestatic 60	xxxxxx/uxxxxx:bb00620062bb0062b0062b0062	(Ljava/lang/String;CC)Ljava/lang/String;
    //   32: iconst_0
    //   33: anewarray 62	java/lang/Class
    //   36: invokevirtual 66	java/lang/Class:getMethod	(Ljava/lang/String;[Ljava/lang/Class;)Ljava/lang/reflect/Method;
    //   39: astore_3
    //   40: iconst_0
    //   41: anewarray 68	java/lang/Object
    //   44: astore 4
    //   46: aload_3
    //   47: aconst_null
    //   48: aload 4
    //   50: invokevirtual 74	java/lang/reflect/Method:invoke	(Ljava/lang/Object;[Ljava/lang/Object;)Ljava/lang/Object;
    //   53: astore 6
    //   55: iload_2
    //   56: aload 6
    //   58: checkcast 76	java/lang/Integer
    //   61: invokevirtual 80	java/lang/Integer:intValue	()I
    //   64: irem
    //   65: istore 7
    //   67: ldc 2
    //   69: ldc 82
    //   71: bipush 36
    //   73: sipush 163
    //   76: iconst_3
    //   77: invokestatic 86	xxxxxx/uxxxxx:bbbb0062b0062b0062b0062	(Ljava/lang/String;CCC)Ljava/lang/String;
    //   80: iconst_0
    //   81: anewarray 62	java/lang/Class
    //   84: invokevirtual 66	java/lang/Class:getMethod	(Ljava/lang/String;[Ljava/lang/Class;)Ljava/lang/reflect/Method;
    //   87: astore 8
    //   89: iconst_0
    //   90: anewarray 68	java/lang/Object
    //   93: astore 9
    //   95: aload 8
    //   97: aconst_null
    //   98: aload 9
    //   100: invokevirtual 74	java/lang/reflect/Method:invoke	(Ljava/lang/Object;[Ljava/lang/Object;)Ljava/lang/Object;
    //   103: astore 11
    //   105: iload 7
    //   107: aload 11
    //   109: checkcast 76	java/lang/Integer
    //   112: invokevirtual 80	java/lang/Integer:intValue	()I
    //   115: if_icmpeq +12 -> 127
    //   118: iconst_5
    //   119: putstatic 50	uuuuuu/lqlllq:bpp00700070p0070p00700070	I
    //   122: bipush 33
    //   124: putstatic 88	uuuuuu/lqlllq:b0070007000700070p0070p00700070	I
    //   127: iload_0
    //   128: iload_1
    //   129: imul
    //   130: getstatic 90	uuuuuu/lqlllq:bp007000700070p0070p00700070	I
    //   133: irem
    //   134: tableswitch	default:+18->152, 0:+70->204
    //   152: bipush 79
    //   154: putstatic 50	uuuuuu/lqlllq:bpp00700070p0070p00700070	I
    //   157: ldc 2
    //   159: ldc 92
    //   161: sipush 252
    //   164: iconst_2
    //   165: invokestatic 60	xxxxxx/uxxxxx:bb00620062bb0062b0062b0062	(Ljava/lang/String;CC)Ljava/lang/String;
    //   168: iconst_0
    //   169: anewarray 62	java/lang/Class
    //   172: invokevirtual 66	java/lang/Class:getMethod	(Ljava/lang/String;[Ljava/lang/Class;)Ljava/lang/reflect/Method;
    //   175: astore 14
    //   177: iconst_0
    //   178: anewarray 68	java/lang/Object
    //   181: astore 15
    //   183: aload 14
    //   185: aconst_null
    //   186: aload 15
    //   188: invokevirtual 74	java/lang/reflect/Method:invoke	(Ljava/lang/Object;[Ljava/lang/Object;)Ljava/lang/Object;
    //   191: astore 17
    //   193: aload 17
    //   195: checkcast 76	java/lang/Integer
    //   198: invokevirtual 80	java/lang/Integer:intValue	()I
    //   201: putstatic 52	uuuuuu/lqlllq:b0070p00700070p0070p00700070	I
    //   204: getstatic 50	uuuuuu/lqlllq:bpp00700070p0070p00700070	I
    //   207: getstatic 52	uuuuuu/lqlllq:b0070p00700070p0070p00700070	I
    //   210: iadd
    //   211: getstatic 50	uuuuuu/lqlllq:bpp00700070p0070p00700070	I
    //   214: imul
    //   215: getstatic 90	uuuuuu/lqlllq:bp007000700070p0070p00700070	I
    //   218: irem
    //   219: getstatic 88	uuuuuu/lqlllq:b0070007000700070p0070p00700070	I
    //   222: if_icmpeq +13 -> 235
    //   225: bipush 19
    //   227: putstatic 50	uuuuuu/lqlllq:bpp00700070p0070p00700070	I
    //   230: bipush 36
    //   232: putstatic 88	uuuuuu/lqlllq:b0070007000700070p0070p00700070	I
    //   235: ldc 2
    //   237: invokevirtual 96	java/lang/Class:getSimpleName	()Ljava/lang/String;
    //   240: astore 12
    //   242: getstatic 50	uuuuuu/lqlllq:bpp00700070p0070p00700070	I
    //   245: istore 13
    //   247: iload 13
    //   249: iload 13
    //   251: getstatic 52	uuuuuu/lqlllq:b0070p00700070p0070p00700070	I
    //   254: iadd
    //   255: imul
    //   256: getstatic 90	uuuuuu/lqlllq:bp007000700070p0070p00700070	I
    //   259: irem
    //   260: tableswitch	default:+20->280, 0:+30->290
    //   280: bipush 92
    //   282: putstatic 50	uuuuuu/lqlllq:bpp00700070p0070p00700070	I
    //   285: bipush 90
    //   287: putstatic 88	uuuuuu/lqlllq:b0070007000700070p0070p00700070	I
    //   290: aload 12
    //   292: putstatic 98	uuuuuu/lqlllq:bpp007000700070pp00700070	Ljava/lang/String;
    //   295: return
    //   296: astore 5
    //   298: aload 5
    //   300: invokevirtual 102	java/lang/reflect/InvocationTargetException:getCause	()Ljava/lang/Throwable;
    //   303: athrow
    //   304: astore 10
    //   306: aload 10
    //   308: invokevirtual 102	java/lang/reflect/InvocationTargetException:getCause	()Ljava/lang/Throwable;
    //   311: athrow
    //   312: astore 16
    //   314: aload 16
    //   316: invokevirtual 102	java/lang/reflect/InvocationTargetException:getCause	()Ljava/lang/Throwable;
    //   319: athrow
    // Local variable table:
    //   start	length	slot	name	signature
    //   3	127	0	i	int
    //   9	121	1	j	int
    //   21	44	2	k	int
    //   39	8	3	localMethod1	java.lang.reflect.Method
    //   44	5	4	arrayOfObject1	Object[]
    //   296	3	5	localInvocationTargetException1	java.lang.reflect.InvocationTargetException
    //   53	4	6	localObject1	Object
    //   65	51	7	m	int
    //   87	9	8	localMethod2	java.lang.reflect.Method
    //   93	6	9	arrayOfObject2	Object[]
    //   304	3	10	localInvocationTargetException2	java.lang.reflect.InvocationTargetException
    //   103	5	11	localObject2	Object
    //   240	51	12	str	String
    //   245	11	13	n	int
    //   175	9	14	localMethod3	java.lang.reflect.Method
    //   181	6	15	arrayOfObject3	Object[]
    //   312	3	16	localInvocationTargetException3	java.lang.reflect.InvocationTargetException
    //   191	3	17	localObject3	Object
    // Exception table:
    //   from	to	target	type
    //   46	55	296	java/lang/reflect/InvocationTargetException
    //   95	105	304	java/lang/reflect/InvocationTargetException
    //   183	193	312	java/lang/reflect/InvocationTargetException
  }
  
  public lqlllq() {}
  
  public static int b006F006F006Fo006F006F006F006Foo()
  {
    return 1;
  }
  
  /* Error */
  private void b006F006Fo006F006F006F006F006Foo()
  {
    // Byte code:
    //   0: new 176	com/db/pwcc/dbmobile/model/sepa/TransferTemplate
    //   3: dup
    //   4: invokespecial 177	com/db/pwcc/dbmobile/model/sepa/TransferTemplate:<init>	()V
    //   7: astore_1
    //   8: aload_1
    //   9: aload_0
    //   10: getfield 179	uuuuuu/lqlllq:b0070p007000700070pp00700070	Lcom/db/pwcc/dbmobile/model/banking/Account;
    //   13: invokevirtual 184	com/db/pwcc/dbmobile/model/banking/Account:getIban	()Ljava/lang/String;
    //   16: invokevirtual 188	com/db/pwcc/dbmobile/model/sepa/TransferTemplate:setSourceAccount	(Ljava/lang/String;)V
    //   19: aconst_null
    //   20: invokevirtual 172	java/lang/String:length	()I
    //   23: pop
    //   24: goto -5 -> 19
    //   27: astore_2
    //   28: bipush 68
    //   30: putstatic 50	uuuuuu/lqlllq:bpp00700070p0070p00700070	I
    //   33: getstatic 50	uuuuuu/lqlllq:bpp00700070p0070p00700070	I
    //   36: istore_3
    //   37: ldc 2
    //   39: ldc -66
    //   41: sipush 198
    //   44: iconst_0
    //   45: invokestatic 60	xxxxxx/uxxxxx:bb00620062bb0062b0062b0062	(Ljava/lang/String;CC)Ljava/lang/String;
    //   48: iconst_0
    //   49: anewarray 62	java/lang/Class
    //   52: invokevirtual 66	java/lang/Class:getMethod	(Ljava/lang/String;[Ljava/lang/Class;)Ljava/lang/reflect/Method;
    //   55: astore 4
    //   57: iconst_0
    //   58: anewarray 68	java/lang/Object
    //   61: astore 5
    //   63: aload 4
    //   65: aconst_null
    //   66: aload 5
    //   68: invokevirtual 74	java/lang/reflect/Method:invoke	(Ljava/lang/Object;[Ljava/lang/Object;)Ljava/lang/Object;
    //   71: astore 7
    //   73: iload_3
    //   74: iload_3
    //   75: aload 7
    //   77: checkcast 76	java/lang/Integer
    //   80: invokevirtual 80	java/lang/Integer:intValue	()I
    //   83: iadd
    //   84: imul
    //   85: getstatic 90	uuuuuu/lqlllq:bp007000700070p0070p00700070	I
    //   88: irem
    //   89: tableswitch	default:+19->108, 0:+160->249
    //   108: getstatic 50	uuuuuu/lqlllq:bpp00700070p0070p00700070	I
    //   111: istore 21
    //   113: iload 21
    //   115: iload 21
    //   117: getstatic 52	uuuuuu/lqlllq:b0070p00700070p0070p00700070	I
    //   120: iadd
    //   121: imul
    //   122: getstatic 90	uuuuuu/lqlllq:bp007000700070p0070p00700070	I
    //   125: irem
    //   126: tableswitch	default:+18->144, 0:+72->198
    //   144: iconst_3
    //   145: putstatic 50	uuuuuu/lqlllq:bpp00700070p0070p00700070	I
    //   148: ldc 2
    //   150: ldc -64
    //   152: sipush 138
    //   155: sipush 141
    //   158: iconst_0
    //   159: invokestatic 86	xxxxxx/uxxxxx:bbbb0062b0062b0062b0062	(Ljava/lang/String;CCC)Ljava/lang/String;
    //   162: iconst_0
    //   163: anewarray 62	java/lang/Class
    //   166: invokevirtual 66	java/lang/Class:getMethod	(Ljava/lang/String;[Ljava/lang/Class;)Ljava/lang/reflect/Method;
    //   169: astore 26
    //   171: iconst_0
    //   172: anewarray 68	java/lang/Object
    //   175: astore 27
    //   177: aload 26
    //   179: aconst_null
    //   180: aload 27
    //   182: invokevirtual 74	java/lang/reflect/Method:invoke	(Ljava/lang/Object;[Ljava/lang/Object;)Ljava/lang/Object;
    //   185: astore 29
    //   187: aload 29
    //   189: checkcast 76	java/lang/Integer
    //   192: invokevirtual 80	java/lang/Integer:intValue	()I
    //   195: putstatic 88	uuuuuu/lqlllq:b0070007000700070p0070p00700070	I
    //   198: bipush 86
    //   200: putstatic 50	uuuuuu/lqlllq:bpp00700070p0070p00700070	I
    //   203: ldc 2
    //   205: ldc -62
    //   207: bipush 48
    //   209: iconst_2
    //   210: invokestatic 60	xxxxxx/uxxxxx:bb00620062bb0062b0062b0062	(Ljava/lang/String;CC)Ljava/lang/String;
    //   213: iconst_0
    //   214: anewarray 62	java/lang/Class
    //   217: invokevirtual 66	java/lang/Class:getMethod	(Ljava/lang/String;[Ljava/lang/Class;)Ljava/lang/reflect/Method;
    //   220: astore 22
    //   222: iconst_0
    //   223: anewarray 68	java/lang/Object
    //   226: astore 23
    //   228: aload 22
    //   230: aconst_null
    //   231: aload 23
    //   233: invokevirtual 74	java/lang/reflect/Method:invoke	(Ljava/lang/Object;[Ljava/lang/Object;)Ljava/lang/Object;
    //   236: astore 25
    //   238: aload 25
    //   240: checkcast 76	java/lang/Integer
    //   243: invokevirtual 80	java/lang/Integer:intValue	()I
    //   246: putstatic 88	uuuuuu/lqlllq:b0070007000700070p0070p00700070	I
    //   249: iconst_m1
    //   250: newarray int
    //   252: pop
    //   253: goto -4 -> 249
    //   256: astore 10
    //   258: bipush 78
    //   260: putstatic 50	uuuuuu/lqlllq:bpp00700070p0070p00700070	I
    //   263: aload_0
    //   264: getfield 198	uuuuuu/lqlllq:bnnnnn006E006E006En	Luuuuuu/ttssst$tsssst;
    //   267: checkcast 200	uuuuuu/lllqql$lqlqql
    //   270: aload_1
    //   271: invokeinterface 204 2 0
    //   276: getstatic 50	uuuuuu/lqlllq:bpp00700070p0070p00700070	I
    //   279: istore 11
    //   281: ldc 2
    //   283: ldc -50
    //   285: bipush 85
    //   287: bipush 77
    //   289: iconst_0
    //   290: invokestatic 86	xxxxxx/uxxxxx:bbbb0062b0062b0062b0062	(Ljava/lang/String;CCC)Ljava/lang/String;
    //   293: iconst_0
    //   294: anewarray 62	java/lang/Class
    //   297: invokevirtual 66	java/lang/Class:getMethod	(Ljava/lang/String;[Ljava/lang/Class;)Ljava/lang/reflect/Method;
    //   300: astore 12
    //   302: iconst_0
    //   303: anewarray 68	java/lang/Object
    //   306: astore 13
    //   308: aload 12
    //   310: aconst_null
    //   311: aload 13
    //   313: invokevirtual 74	java/lang/reflect/Method:invoke	(Ljava/lang/Object;[Ljava/lang/Object;)Ljava/lang/Object;
    //   316: astore 15
    //   318: iload 11
    //   320: aload 15
    //   322: checkcast 76	java/lang/Integer
    //   325: invokevirtual 80	java/lang/Integer:intValue	()I
    //   328: iadd
    //   329: getstatic 50	uuuuuu/lqlllq:bpp00700070p0070p00700070	I
    //   332: imul
    //   333: getstatic 90	uuuuuu/lqlllq:bp007000700070p0070p00700070	I
    //   336: irem
    //   337: getstatic 88	uuuuuu/lqlllq:b0070007000700070p0070p00700070	I
    //   340: if_icmpeq +54 -> 394
    //   343: bipush 32
    //   345: putstatic 50	uuuuuu/lqlllq:bpp00700070p0070p00700070	I
    //   348: ldc 2
    //   350: ldc -48
    //   352: bipush 105
    //   354: iconst_0
    //   355: invokestatic 60	xxxxxx/uxxxxx:bb00620062bb0062b0062b0062	(Ljava/lang/String;CC)Ljava/lang/String;
    //   358: iconst_0
    //   359: anewarray 62	java/lang/Class
    //   362: invokevirtual 66	java/lang/Class:getMethod	(Ljava/lang/String;[Ljava/lang/Class;)Ljava/lang/reflect/Method;
    //   365: astore 16
    //   367: iconst_0
    //   368: anewarray 68	java/lang/Object
    //   371: astore 17
    //   373: aload 16
    //   375: aconst_null
    //   376: aload 17
    //   378: invokevirtual 74	java/lang/reflect/Method:invoke	(Ljava/lang/Object;[Ljava/lang/Object;)Ljava/lang/Object;
    //   381: astore 19
    //   383: aload 19
    //   385: checkcast 76	java/lang/Integer
    //   388: invokevirtual 80	java/lang/Integer:intValue	()I
    //   391: putstatic 88	uuuuuu/lqlllq:b0070007000700070p0070p00700070	I
    //   394: return
    //   395: astore 14
    //   397: aload 14
    //   399: invokevirtual 102	java/lang/reflect/InvocationTargetException:getCause	()Ljava/lang/Throwable;
    //   402: athrow
    //   403: astore 18
    //   405: aload 18
    //   407: invokevirtual 102	java/lang/reflect/InvocationTargetException:getCause	()Ljava/lang/Throwable;
    //   410: athrow
    //   411: astore 6
    //   413: aload 6
    //   415: invokevirtual 102	java/lang/reflect/InvocationTargetException:getCause	()Ljava/lang/Throwable;
    //   418: athrow
    //   419: astore 8
    //   421: bipush 67
    //   423: putstatic 50	uuuuuu/lqlllq:bpp00700070p0070p00700070	I
    //   426: iconst_2
    //   427: istore 9
    //   429: iload 9
    //   431: iconst_0
    //   432: idiv
    //   433: istore 9
    //   435: goto -6 -> 429
    //   438: astore 24
    //   440: aload 24
    //   442: invokevirtual 102	java/lang/reflect/InvocationTargetException:getCause	()Ljava/lang/Throwable;
    //   445: athrow
    //   446: astore 28
    //   448: aload 28
    //   450: invokevirtual 102	java/lang/reflect/InvocationTargetException:getCause	()Ljava/lang/Throwable;
    //   453: athrow
    // Local variable table:
    //   start	length	slot	name	signature
    //   0	454	0	this	lqlllq
    //   7	264	1	localTransferTemplate	com.db.pwcc.dbmobile.model.sepa.TransferTemplate
    //   27	1	2	localException1	Exception
    //   36	49	3	i	int
    //   55	9	4	localMethod1	java.lang.reflect.Method
    //   61	6	5	arrayOfObject1	Object[]
    //   411	3	6	localInvocationTargetException1	java.lang.reflect.InvocationTargetException
    //   71	5	7	localObject1	Object
    //   419	1	8	localException2	Exception
    //   427	7	9	j	int
    //   256	1	10	localException3	Exception
    //   279	50	11	k	int
    //   300	9	12	localMethod2	java.lang.reflect.Method
    //   306	6	13	arrayOfObject2	Object[]
    //   395	3	14	localInvocationTargetException2	java.lang.reflect.InvocationTargetException
    //   316	5	15	localObject2	Object
    //   365	9	16	localMethod3	java.lang.reflect.Method
    //   371	6	17	arrayOfObject3	Object[]
    //   403	3	18	localInvocationTargetException3	java.lang.reflect.InvocationTargetException
    //   381	3	19	localObject3	Object
    //   111	11	21	m	int
    //   220	9	22	localMethod4	java.lang.reflect.Method
    //   226	6	23	arrayOfObject4	Object[]
    //   438	3	24	localInvocationTargetException4	java.lang.reflect.InvocationTargetException
    //   236	3	25	localObject4	Object
    //   169	9	26	localMethod5	java.lang.reflect.Method
    //   175	6	27	arrayOfObject5	Object[]
    //   446	3	28	localInvocationTargetException5	java.lang.reflect.InvocationTargetException
    //   185	3	29	localObject5	Object
    // Exception table:
    //   from	to	target	type
    //   19	24	27	java/lang/Exception
    //   429	435	256	java/lang/Exception
    //   308	318	395	java/lang/reflect/InvocationTargetException
    //   373	383	403	java/lang/reflect/InvocationTargetException
    //   63	73	411	java/lang/reflect/InvocationTargetException
    //   249	253	419	java/lang/Exception
    //   228	238	438	java/lang/reflect/InvocationTargetException
    //   177	187	446	java/lang/reflect/InvocationTargetException
  }
  
  /* Error */
  private void b006Fo006F006F006F006F006F006Foo()
  {
    // Byte code:
    //   0: getstatic 50	uuuuuu/lqlllq:bpp00700070p0070p00700070	I
    //   3: getstatic 52	uuuuuu/lqlllq:b0070p00700070p0070p00700070	I
    //   6: iadd
    //   7: getstatic 50	uuuuuu/lqlllq:bpp00700070p0070p00700070	I
    //   10: imul
    //   11: getstatic 90	uuuuuu/lqlllq:bp007000700070p0070p00700070	I
    //   14: irem
    //   15: getstatic 88	uuuuuu/lqlllq:b0070007000700070p0070p00700070	I
    //   18: if_icmpeq +364 -> 382
    //   21: ldc 2
    //   23: ldc -99
    //   25: bipush 66
    //   27: sipush 230
    //   30: iconst_0
    //   31: invokestatic 86	xxxxxx/uxxxxx:bbbb0062b0062b0062b0062	(Ljava/lang/String;CCC)Ljava/lang/String;
    //   34: iconst_0
    //   35: anewarray 62	java/lang/Class
    //   38: invokevirtual 66	java/lang/Class:getMethod	(Ljava/lang/String;[Ljava/lang/Class;)Ljava/lang/reflect/Method;
    //   41: astore_1
    //   42: iconst_0
    //   43: anewarray 68	java/lang/Object
    //   46: astore_2
    //   47: aload_1
    //   48: aconst_null
    //   49: aload_2
    //   50: invokevirtual 74	java/lang/reflect/Method:invoke	(Ljava/lang/Object;[Ljava/lang/Object;)Ljava/lang/Object;
    //   53: astore 4
    //   55: aload 4
    //   57: checkcast 76	java/lang/Integer
    //   60: invokevirtual 80	java/lang/Integer:intValue	()I
    //   63: putstatic 50	uuuuuu/lqlllq:bpp00700070p0070p00700070	I
    //   66: ldc 2
    //   68: ldc -31
    //   70: sipush 172
    //   73: iconst_1
    //   74: invokestatic 60	xxxxxx/uxxxxx:bb00620062bb0062b0062b0062	(Ljava/lang/String;CC)Ljava/lang/String;
    //   77: iconst_0
    //   78: anewarray 62	java/lang/Class
    //   81: invokevirtual 66	java/lang/Class:getMethod	(Ljava/lang/String;[Ljava/lang/Class;)Ljava/lang/reflect/Method;
    //   84: astore 5
    //   86: iconst_0
    //   87: anewarray 68	java/lang/Object
    //   90: astore 6
    //   92: aload 5
    //   94: aconst_null
    //   95: aload 6
    //   97: invokevirtual 74	java/lang/reflect/Method:invoke	(Ljava/lang/Object;[Ljava/lang/Object;)Ljava/lang/Object;
    //   100: astore 8
    //   102: aload 8
    //   104: checkcast 76	java/lang/Integer
    //   107: invokevirtual 80	java/lang/Integer:intValue	()I
    //   110: istore 9
    //   112: getstatic 50	uuuuuu/lqlllq:bpp00700070p0070p00700070	I
    //   115: istore 10
    //   117: iload 10
    //   119: iload 10
    //   121: getstatic 52	uuuuuu/lqlllq:b0070p00700070p0070p00700070	I
    //   124: iadd
    //   125: imul
    //   126: getstatic 90	uuuuuu/lqlllq:bp007000700070p0070p00700070	I
    //   129: irem
    //   130: tableswitch	default:+18->148, 0:+202->332
    //   148: bipush 26
    //   150: putstatic 50	uuuuuu/lqlllq:bpp00700070p0070p00700070	I
    //   153: ldc 2
    //   155: ldc -29
    //   157: sipush 161
    //   160: iconst_3
    //   161: invokestatic 60	xxxxxx/uxxxxx:bb00620062bb0062b0062b0062	(Ljava/lang/String;CC)Ljava/lang/String;
    //   164: iconst_0
    //   165: anewarray 62	java/lang/Class
    //   168: invokevirtual 66	java/lang/Class:getMethod	(Ljava/lang/String;[Ljava/lang/Class;)Ljava/lang/reflect/Method;
    //   171: astore 12
    //   173: iconst_0
    //   174: anewarray 68	java/lang/Object
    //   177: astore 13
    //   179: aload 12
    //   181: aconst_null
    //   182: aload 13
    //   184: invokevirtual 74	java/lang/reflect/Method:invoke	(Ljava/lang/Object;[Ljava/lang/Object;)Ljava/lang/Object;
    //   187: astore 15
    //   189: aload 15
    //   191: checkcast 76	java/lang/Integer
    //   194: invokevirtual 80	java/lang/Integer:intValue	()I
    //   197: putstatic 88	uuuuuu/lqlllq:b0070007000700070p0070p00700070	I
    //   200: getstatic 50	uuuuuu/lqlllq:bpp00700070p0070p00700070	I
    //   203: istore 16
    //   205: iload 16
    //   207: iload 16
    //   209: getstatic 52	uuuuuu/lqlllq:b0070p00700070p0070p00700070	I
    //   212: iadd
    //   213: imul
    //   214: getstatic 90	uuuuuu/lqlllq:bp007000700070p0070p00700070	I
    //   217: irem
    //   218: tableswitch	default:+18->236, 0:+114->332
    //   236: ldc 2
    //   238: ldc -27
    //   240: bipush 40
    //   242: iconst_1
    //   243: invokestatic 60	xxxxxx/uxxxxx:bb00620062bb0062b0062b0062	(Ljava/lang/String;CC)Ljava/lang/String;
    //   246: iconst_0
    //   247: anewarray 62	java/lang/Class
    //   250: invokevirtual 66	java/lang/Class:getMethod	(Ljava/lang/String;[Ljava/lang/Class;)Ljava/lang/reflect/Method;
    //   253: astore 17
    //   255: iconst_0
    //   256: anewarray 68	java/lang/Object
    //   259: astore 18
    //   261: aload 17
    //   263: aconst_null
    //   264: aload 18
    //   266: invokevirtual 74	java/lang/reflect/Method:invoke	(Ljava/lang/Object;[Ljava/lang/Object;)Ljava/lang/Object;
    //   269: astore 20
    //   271: aload 20
    //   273: checkcast 76	java/lang/Integer
    //   276: invokevirtual 80	java/lang/Integer:intValue	()I
    //   279: putstatic 50	uuuuuu/lqlllq:bpp00700070p0070p00700070	I
    //   282: ldc 2
    //   284: ldc -25
    //   286: sipush 236
    //   289: sipush 135
    //   292: iconst_0
    //   293: invokestatic 86	xxxxxx/uxxxxx:bbbb0062b0062b0062b0062	(Ljava/lang/String;CCC)Ljava/lang/String;
    //   296: iconst_0
    //   297: anewarray 62	java/lang/Class
    //   300: invokevirtual 66	java/lang/Class:getMethod	(Ljava/lang/String;[Ljava/lang/Class;)Ljava/lang/reflect/Method;
    //   303: astore 21
    //   305: iconst_0
    //   306: anewarray 68	java/lang/Object
    //   309: astore 22
    //   311: aload 21
    //   313: aconst_null
    //   314: aload 22
    //   316: invokevirtual 74	java/lang/reflect/Method:invoke	(Ljava/lang/Object;[Ljava/lang/Object;)Ljava/lang/Object;
    //   319: astore 24
    //   321: aload 24
    //   323: checkcast 76	java/lang/Integer
    //   326: invokevirtual 80	java/lang/Integer:intValue	()I
    //   329: putstatic 88	uuuuuu/lqlllq:b0070007000700070p0070p00700070	I
    //   332: iload 9
    //   334: putstatic 88	uuuuuu/lqlllq:b0070007000700070p0070p00700070	I
    //   337: getstatic 50	uuuuuu/lqlllq:bpp00700070p0070p00700070	I
    //   340: istore 11
    //   342: iload 11
    //   344: iload 11
    //   346: getstatic 52	uuuuuu/lqlllq:b0070p00700070p0070p00700070	I
    //   349: iadd
    //   350: imul
    //   351: getstatic 90	uuuuuu/lqlllq:bp007000700070p0070p00700070	I
    //   354: irem
    //   355: tableswitch	default:+17->372, 0:+27->382
    //   372: bipush 79
    //   374: putstatic 50	uuuuuu/lqlllq:bpp00700070p0070p00700070	I
    //   377: bipush 27
    //   379: putstatic 88	uuuuuu/lqlllq:b0070007000700070p0070p00700070	I
    //   382: aload_0
    //   383: getfield 198	uuuuuu/lqlllq:bnnnnn006E006E006En	Luuuuuu/ttssst$tsssst;
    //   386: checkcast 200	uuuuuu/lllqql$lqlqql
    //   389: aload_0
    //   390: getfield 233	uuuuuu/lqlllq:bp0070007000700070pp00700070	Ljava/lang/String;
    //   393: invokeinterface 236 2 0
    //   398: return
    //   399: astore_3
    //   400: aload_3
    //   401: invokevirtual 102	java/lang/reflect/InvocationTargetException:getCause	()Ljava/lang/Throwable;
    //   404: athrow
    //   405: astore 7
    //   407: aload 7
    //   409: invokevirtual 102	java/lang/reflect/InvocationTargetException:getCause	()Ljava/lang/Throwable;
    //   412: athrow
    //   413: astore 14
    //   415: aload 14
    //   417: invokevirtual 102	java/lang/reflect/InvocationTargetException:getCause	()Ljava/lang/Throwable;
    //   420: athrow
    //   421: astore 19
    //   423: aload 19
    //   425: invokevirtual 102	java/lang/reflect/InvocationTargetException:getCause	()Ljava/lang/Throwable;
    //   428: athrow
    //   429: astore 23
    //   431: aload 23
    //   433: invokevirtual 102	java/lang/reflect/InvocationTargetException:getCause	()Ljava/lang/Throwable;
    //   436: athrow
    // Local variable table:
    //   start	length	slot	name	signature
    //   0	437	0	this	lqlllq
    //   41	7	1	localMethod1	java.lang.reflect.Method
    //   46	4	2	arrayOfObject1	Object[]
    //   399	2	3	localInvocationTargetException1	java.lang.reflect.InvocationTargetException
    //   53	3	4	localObject1	Object
    //   84	9	5	localMethod2	java.lang.reflect.Method
    //   90	6	6	arrayOfObject2	Object[]
    //   405	3	7	localInvocationTargetException2	java.lang.reflect.InvocationTargetException
    //   100	3	8	localObject2	Object
    //   110	223	9	i	int
    //   115	11	10	j	int
    //   340	11	11	k	int
    //   171	9	12	localMethod3	java.lang.reflect.Method
    //   177	6	13	arrayOfObject3	Object[]
    //   413	3	14	localInvocationTargetException3	java.lang.reflect.InvocationTargetException
    //   187	3	15	localObject3	Object
    //   203	11	16	m	int
    //   253	9	17	localMethod4	java.lang.reflect.Method
    //   259	6	18	arrayOfObject4	Object[]
    //   421	3	19	localInvocationTargetException4	java.lang.reflect.InvocationTargetException
    //   269	3	20	localObject4	Object
    //   303	9	21	localMethod5	java.lang.reflect.Method
    //   309	6	22	arrayOfObject5	Object[]
    //   429	3	23	localInvocationTargetException5	java.lang.reflect.InvocationTargetException
    //   319	3	24	localObject5	Object
    // Exception table:
    //   from	to	target	type
    //   47	55	399	java/lang/reflect/InvocationTargetException
    //   92	102	405	java/lang/reflect/InvocationTargetException
    //   179	189	413	java/lang/reflect/InvocationTargetException
    //   261	271	421	java/lang/reflect/InvocationTargetException
    //   311	321	429	java/lang/reflect/InvocationTargetException
  }
  
  public static int b006Foo006F006F006F006F006Foo()
  {
    return 2;
  }
  
  /* Error */
  private boolean bo006F006F006F006F006F006F006Foo()
  {
    // Byte code:
    //   0: aload_0
    //   1: getfield 198	uuuuuu/lqlllq:bnnnnn006E006E006En	Luuuuuu/ttssst$tsssst;
    //   4: ifnull +76 -> 80
    //   7: aload_0
    //   8: getfield 284	uuuuuu/lqlllq:b006En006E006E006En006E006En	Luuuuuu/ggyggy;
    //   11: invokevirtual 289	uuuuuu/ggyggy:bpppp0070p00700070pp	()Z
    //   14: ifeq +66 -> 80
    //   17: aload_0
    //   18: getfield 198	uuuuuu/lqlllq:bnnnnn006E006E006En	Luuuuuu/ttssst$tsssst;
    //   21: checkcast 200	uuuuuu/lllqql$lqlqql
    //   24: astore 19
    //   26: getstatic 294	com/db/pwcc/dbmobile/financial_overview/R$string:demo_mode_alert_title	I
    //   29: istore 20
    //   31: getstatic 297	com/db/pwcc/dbmobile/financial_overview/R$string:demo_mode_alert_message	I
    //   34: istore 21
    //   36: getstatic 50	uuuuuu/lqlllq:bpp00700070p0070p00700070	I
    //   39: getstatic 52	uuuuuu/lqlllq:b0070p00700070p0070p00700070	I
    //   42: iadd
    //   43: getstatic 50	uuuuuu/lqlllq:bpp00700070p0070p00700070	I
    //   46: imul
    //   47: getstatic 90	uuuuuu/lqlllq:bp007000700070p0070p00700070	I
    //   50: irem
    //   51: getstatic 88	uuuuuu/lqlllq:b0070007000700070p0070p00700070	I
    //   54: if_icmpeq +13 -> 67
    //   57: bipush 55
    //   59: putstatic 50	uuuuuu/lqlllq:bpp00700070p0070p00700070	I
    //   62: bipush 45
    //   64: putstatic 88	uuuuuu/lqlllq:b0070007000700070p0070p00700070	I
    //   67: aload 19
    //   69: iload 20
    //   71: iload 21
    //   73: invokeinterface 301 3 0
    //   78: iconst_1
    //   79: ireturn
    //   80: getstatic 50	uuuuuu/lqlllq:bpp00700070p0070p00700070	I
    //   83: istore_1
    //   84: ldc 2
    //   86: ldc_w 303
    //   89: bipush 69
    //   91: iconst_3
    //   92: invokestatic 60	xxxxxx/uxxxxx:bb00620062bb0062b0062b0062	(Ljava/lang/String;CC)Ljava/lang/String;
    //   95: iconst_0
    //   96: anewarray 62	java/lang/Class
    //   99: invokevirtual 66	java/lang/Class:getMethod	(Ljava/lang/String;[Ljava/lang/Class;)Ljava/lang/reflect/Method;
    //   102: astore_2
    //   103: iconst_0
    //   104: anewarray 68	java/lang/Object
    //   107: astore_3
    //   108: aload_2
    //   109: aconst_null
    //   110: aload_3
    //   111: invokevirtual 74	java/lang/reflect/Method:invoke	(Ljava/lang/Object;[Ljava/lang/Object;)Ljava/lang/Object;
    //   114: astore 5
    //   116: iload_1
    //   117: iload_1
    //   118: aload 5
    //   120: checkcast 76	java/lang/Integer
    //   123: invokevirtual 80	java/lang/Integer:intValue	()I
    //   126: iadd
    //   127: imul
    //   128: getstatic 90	uuuuuu/lqlllq:bp007000700070p0070p00700070	I
    //   131: irem
    //   132: tableswitch	default:+20->152, 0:+145->277
    //   152: ldc 2
    //   154: ldc -103
    //   156: sipush 249
    //   159: iconst_3
    //   160: invokestatic 60	xxxxxx/uxxxxx:bb00620062bb0062b0062b0062	(Ljava/lang/String;CC)Ljava/lang/String;
    //   163: iconst_0
    //   164: anewarray 62	java/lang/Class
    //   167: invokevirtual 66	java/lang/Class:getMethod	(Ljava/lang/String;[Ljava/lang/Class;)Ljava/lang/reflect/Method;
    //   170: astore 11
    //   172: iconst_0
    //   173: anewarray 68	java/lang/Object
    //   176: astore 12
    //   178: aload 11
    //   180: aconst_null
    //   181: aload 12
    //   183: invokevirtual 74	java/lang/reflect/Method:invoke	(Ljava/lang/Object;[Ljava/lang/Object;)Ljava/lang/Object;
    //   186: astore 14
    //   188: aload 14
    //   190: checkcast 76	java/lang/Integer
    //   193: invokevirtual 80	java/lang/Integer:intValue	()I
    //   196: putstatic 50	uuuuuu/lqlllq:bpp00700070p0070p00700070	I
    //   199: ldc 2
    //   201: ldc_w 305
    //   204: iconst_4
    //   205: bipush 108
    //   207: iconst_0
    //   208: invokestatic 86	xxxxxx/uxxxxx:bbbb0062b0062b0062b0062	(Ljava/lang/String;CCC)Ljava/lang/String;
    //   211: iconst_0
    //   212: anewarray 62	java/lang/Class
    //   215: invokevirtual 66	java/lang/Class:getMethod	(Ljava/lang/String;[Ljava/lang/Class;)Ljava/lang/reflect/Method;
    //   218: astore 15
    //   220: iconst_0
    //   221: anewarray 68	java/lang/Object
    //   224: astore 16
    //   226: aload 15
    //   228: aconst_null
    //   229: aload 16
    //   231: invokevirtual 74	java/lang/reflect/Method:invoke	(Ljava/lang/Object;[Ljava/lang/Object;)Ljava/lang/Object;
    //   234: astore 18
    //   236: aload 18
    //   238: checkcast 76	java/lang/Integer
    //   241: invokevirtual 80	java/lang/Integer:intValue	()I
    //   244: putstatic 88	uuuuuu/lqlllq:b0070007000700070p0070p00700070	I
    //   247: getstatic 50	uuuuuu/lqlllq:bpp00700070p0070p00700070	I
    //   250: getstatic 52	uuuuuu/lqlllq:b0070p00700070p0070p00700070	I
    //   253: iadd
    //   254: getstatic 50	uuuuuu/lqlllq:bpp00700070p0070p00700070	I
    //   257: imul
    //   258: getstatic 90	uuuuuu/lqlllq:bp007000700070p0070p00700070	I
    //   261: irem
    //   262: getstatic 88	uuuuuu/lqlllq:b0070007000700070p0070p00700070	I
    //   265: if_icmpeq +12 -> 277
    //   268: bipush 30
    //   270: putstatic 50	uuuuuu/lqlllq:bpp00700070p0070p00700070	I
    //   273: iconst_0
    //   274: putstatic 88	uuuuuu/lqlllq:b0070007000700070p0070p00700070	I
    //   277: getstatic 50	uuuuuu/lqlllq:bpp00700070p0070p00700070	I
    //   280: istore 6
    //   282: iload 6
    //   284: iload 6
    //   286: getstatic 52	uuuuuu/lqlllq:b0070p00700070p0070p00700070	I
    //   289: iadd
    //   290: imul
    //   291: getstatic 90	uuuuuu/lqlllq:bp007000700070p0070p00700070	I
    //   294: irem
    //   295: tableswitch	default:+17->312, 0:+104->399
    //   312: bipush 10
    //   314: putstatic 50	uuuuuu/lqlllq:bpp00700070p0070p00700070	I
    //   317: ldc 2
    //   319: ldc_w 307
    //   322: sipush 228
    //   325: iconst_4
    //   326: invokestatic 60	xxxxxx/uxxxxx:bb00620062bb0062b0062b0062	(Ljava/lang/String;CC)Ljava/lang/String;
    //   329: iconst_0
    //   330: anewarray 62	java/lang/Class
    //   333: invokevirtual 66	java/lang/Class:getMethod	(Ljava/lang/String;[Ljava/lang/Class;)Ljava/lang/reflect/Method;
    //   336: astore 7
    //   338: iconst_0
    //   339: anewarray 68	java/lang/Object
    //   342: astore 8
    //   344: aload 7
    //   346: aconst_null
    //   347: aload 8
    //   349: invokevirtual 74	java/lang/reflect/Method:invoke	(Ljava/lang/Object;[Ljava/lang/Object;)Ljava/lang/Object;
    //   352: astore 10
    //   354: aload 10
    //   356: checkcast 76	java/lang/Integer
    //   359: invokevirtual 80	java/lang/Integer:intValue	()I
    //   362: putstatic 88	uuuuuu/lqlllq:b0070007000700070p0070p00700070	I
    //   365: iconst_0
    //   366: ireturn
    //   367: astore 4
    //   369: aload 4
    //   371: invokevirtual 102	java/lang/reflect/InvocationTargetException:getCause	()Ljava/lang/Throwable;
    //   374: athrow
    //   375: astore 9
    //   377: aload 9
    //   379: invokevirtual 102	java/lang/reflect/InvocationTargetException:getCause	()Ljava/lang/Throwable;
    //   382: athrow
    //   383: astore 13
    //   385: aload 13
    //   387: invokevirtual 102	java/lang/reflect/InvocationTargetException:getCause	()Ljava/lang/Throwable;
    //   390: athrow
    //   391: astore 17
    //   393: aload 17
    //   395: invokevirtual 102	java/lang/reflect/InvocationTargetException:getCause	()Ljava/lang/Throwable;
    //   398: athrow
    //   399: iconst_0
    //   400: ireturn
    // Local variable table:
    //   start	length	slot	name	signature
    //   0	401	0	this	lqlllq
    //   83	45	1	i	int
    //   102	7	2	localMethod1	java.lang.reflect.Method
    //   107	4	3	arrayOfObject1	Object[]
    //   367	3	4	localInvocationTargetException1	java.lang.reflect.InvocationTargetException
    //   114	5	5	localObject1	Object
    //   280	11	6	j	int
    //   336	9	7	localMethod2	java.lang.reflect.Method
    //   342	6	8	arrayOfObject2	Object[]
    //   375	3	9	localInvocationTargetException2	java.lang.reflect.InvocationTargetException
    //   352	3	10	localObject2	Object
    //   170	9	11	localMethod3	java.lang.reflect.Method
    //   176	6	12	arrayOfObject3	Object[]
    //   383	3	13	localInvocationTargetException3	java.lang.reflect.InvocationTargetException
    //   186	3	14	localObject3	Object
    //   218	9	15	localMethod4	java.lang.reflect.Method
    //   224	6	16	arrayOfObject4	Object[]
    //   391	3	17	localInvocationTargetException4	java.lang.reflect.InvocationTargetException
    //   234	3	18	localObject4	Object
    //   24	44	19	localLqlqql	lllqql.lqlqql
    //   29	41	20	k	int
    //   34	38	21	m	int
    // Exception table:
    //   from	to	target	type
    //   108	116	367	java/lang/reflect/InvocationTargetException
    //   344	354	375	java/lang/reflect/InvocationTargetException
    //   178	188	383	java/lang/reflect/InvocationTargetException
    //   226	236	391	java/lang/reflect/InvocationTargetException
  }
  
  public static int bo006F006Fo006F006F006F006Foo()
  {
    return 19;
  }
  
  /* Error */
  private void bo006Fo006F006F006F006F006Foo()
  {
    // Byte code:
    //   0: getstatic 50	uuuuuu/lqlllq:bpp00700070p0070p00700070	I
    //   3: istore_1
    //   4: iload_1
    //   5: iload_1
    //   6: getstatic 52	uuuuuu/lqlllq:b0070p00700070p0070p00700070	I
    //   9: iadd
    //   10: imul
    //   11: getstatic 90	uuuuuu/lqlllq:bp007000700070p0070p00700070	I
    //   14: irem
    //   15: tableswitch	default:+17->32, 0:+72->87
    //   32: ldc 2
    //   34: ldc_w 324
    //   37: sipush 151
    //   40: bipush 115
    //   42: iconst_3
    //   43: invokestatic 86	xxxxxx/uxxxxx:bbbb0062b0062b0062b0062	(Ljava/lang/String;CCC)Ljava/lang/String;
    //   46: iconst_0
    //   47: anewarray 62	java/lang/Class
    //   50: invokevirtual 66	java/lang/Class:getMethod	(Ljava/lang/String;[Ljava/lang/Class;)Ljava/lang/reflect/Method;
    //   53: astore 21
    //   55: iconst_0
    //   56: anewarray 68	java/lang/Object
    //   59: astore 22
    //   61: aload 21
    //   63: aconst_null
    //   64: aload 22
    //   66: invokevirtual 74	java/lang/reflect/Method:invoke	(Ljava/lang/Object;[Ljava/lang/Object;)Ljava/lang/Object;
    //   69: astore 24
    //   71: aload 24
    //   73: checkcast 76	java/lang/Integer
    //   76: invokevirtual 80	java/lang/Integer:intValue	()I
    //   79: putstatic 50	uuuuuu/lqlllq:bpp00700070p0070p00700070	I
    //   82: bipush 33
    //   84: putstatic 88	uuuuuu/lqlllq:b0070007000700070p0070p00700070	I
    //   87: aload_0
    //   88: getfield 198	uuuuuu/lqlllq:bnnnnn006E006E006En	Luuuuuu/ttssst$tsssst;
    //   91: checkcast 200	uuuuuu/lllqql$lqlqql
    //   94: astore_2
    //   95: getstatic 50	uuuuuu/lqlllq:bpp00700070p0070p00700070	I
    //   98: getstatic 52	uuuuuu/lqlllq:b0070p00700070p0070p00700070	I
    //   101: iadd
    //   102: getstatic 50	uuuuuu/lqlllq:bpp00700070p0070p00700070	I
    //   105: imul
    //   106: getstatic 90	uuuuuu/lqlllq:bp007000700070p0070p00700070	I
    //   109: irem
    //   110: getstatic 88	uuuuuu/lqlllq:b0070007000700070p0070p00700070	I
    //   113: if_icmpeq +219 -> 332
    //   116: bipush 43
    //   118: putstatic 50	uuuuuu/lqlllq:bpp00700070p0070p00700070	I
    //   121: bipush 59
    //   123: putstatic 88	uuuuuu/lqlllq:b0070007000700070p0070p00700070	I
    //   126: ldc 2
    //   128: ldc_w 326
    //   131: sipush 150
    //   134: sipush 214
    //   137: iconst_1
    //   138: invokestatic 86	xxxxxx/uxxxxx:bbbb0062b0062b0062b0062	(Ljava/lang/String;CCC)Ljava/lang/String;
    //   141: iconst_0
    //   142: anewarray 62	java/lang/Class
    //   145: invokevirtual 66	java/lang/Class:getMethod	(Ljava/lang/String;[Ljava/lang/Class;)Ljava/lang/reflect/Method;
    //   148: astore 4
    //   150: iconst_0
    //   151: anewarray 68	java/lang/Object
    //   154: astore 5
    //   156: aload 4
    //   158: aconst_null
    //   159: aload 5
    //   161: invokevirtual 74	java/lang/reflect/Method:invoke	(Ljava/lang/Object;[Ljava/lang/Object;)Ljava/lang/Object;
    //   164: astore 7
    //   166: aload 7
    //   168: checkcast 76	java/lang/Integer
    //   171: invokevirtual 80	java/lang/Integer:intValue	()I
    //   174: getstatic 52	uuuuuu/lqlllq:b0070p00700070p0070p00700070	I
    //   177: iadd
    //   178: istore 8
    //   180: ldc 2
    //   182: ldc_w 328
    //   185: sipush 150
    //   188: iconst_2
    //   189: invokestatic 60	xxxxxx/uxxxxx:bb00620062bb0062b0062b0062	(Ljava/lang/String;CC)Ljava/lang/String;
    //   192: iconst_0
    //   193: anewarray 62	java/lang/Class
    //   196: invokevirtual 66	java/lang/Class:getMethod	(Ljava/lang/String;[Ljava/lang/Class;)Ljava/lang/reflect/Method;
    //   199: astore 9
    //   201: iconst_0
    //   202: anewarray 68	java/lang/Object
    //   205: astore 10
    //   207: aload 9
    //   209: aconst_null
    //   210: aload 10
    //   212: invokevirtual 74	java/lang/reflect/Method:invoke	(Ljava/lang/Object;[Ljava/lang/Object;)Ljava/lang/Object;
    //   215: astore 12
    //   217: iload 8
    //   219: aload 12
    //   221: checkcast 76	java/lang/Integer
    //   224: invokevirtual 80	java/lang/Integer:intValue	()I
    //   227: imul
    //   228: getstatic 90	uuuuuu/lqlllq:bp007000700070p0070p00700070	I
    //   231: irem
    //   232: getstatic 88	uuuuuu/lqlllq:b0070007000700070p0070p00700070	I
    //   235: if_icmpeq +97 -> 332
    //   238: ldc 2
    //   240: ldc -11
    //   242: bipush 93
    //   244: iconst_3
    //   245: invokestatic 60	xxxxxx/uxxxxx:bb00620062bb0062b0062b0062	(Ljava/lang/String;CC)Ljava/lang/String;
    //   248: iconst_0
    //   249: anewarray 62	java/lang/Class
    //   252: invokevirtual 66	java/lang/Class:getMethod	(Ljava/lang/String;[Ljava/lang/Class;)Ljava/lang/reflect/Method;
    //   255: astore 13
    //   257: iconst_0
    //   258: anewarray 68	java/lang/Object
    //   261: astore 14
    //   263: aload 13
    //   265: aconst_null
    //   266: aload 14
    //   268: invokevirtual 74	java/lang/reflect/Method:invoke	(Ljava/lang/Object;[Ljava/lang/Object;)Ljava/lang/Object;
    //   271: astore 16
    //   273: aload 16
    //   275: checkcast 76	java/lang/Integer
    //   278: invokevirtual 80	java/lang/Integer:intValue	()I
    //   281: putstatic 50	uuuuuu/lqlllq:bpp00700070p0070p00700070	I
    //   284: ldc 2
    //   286: ldc_w 330
    //   289: sipush 239
    //   292: iconst_1
    //   293: invokestatic 60	xxxxxx/uxxxxx:bb00620062bb0062b0062b0062	(Ljava/lang/String;CC)Ljava/lang/String;
    //   296: iconst_0
    //   297: anewarray 62	java/lang/Class
    //   300: invokevirtual 66	java/lang/Class:getMethod	(Ljava/lang/String;[Ljava/lang/Class;)Ljava/lang/reflect/Method;
    //   303: astore 17
    //   305: iconst_0
    //   306: anewarray 68	java/lang/Object
    //   309: astore 18
    //   311: aload 17
    //   313: aconst_null
    //   314: aload 18
    //   316: invokevirtual 74	java/lang/reflect/Method:invoke	(Ljava/lang/Object;[Ljava/lang/Object;)Ljava/lang/Object;
    //   319: astore 20
    //   321: aload 20
    //   323: checkcast 76	java/lang/Integer
    //   326: invokevirtual 80	java/lang/Integer:intValue	()I
    //   329: putstatic 88	uuuuuu/lqlllq:b0070007000700070p0070p00700070	I
    //   332: getstatic 50	uuuuuu/lqlllq:bpp00700070p0070p00700070	I
    //   335: istore_3
    //   336: iload_3
    //   337: iload_3
    //   338: getstatic 52	uuuuuu/lqlllq:b0070p00700070p0070p00700070	I
    //   341: iadd
    //   342: imul
    //   343: getstatic 90	uuuuuu/lqlllq:bp007000700070p0070p00700070	I
    //   346: irem
    //   347: tableswitch	default:+17->364, 0:+27->374
    //   364: bipush 86
    //   366: putstatic 50	uuuuuu/lqlllq:bpp00700070p0070p00700070	I
    //   369: bipush 71
    //   371: putstatic 88	uuuuuu/lqlllq:b0070007000700070p0070p00700070	I
    //   374: aload_2
    //   375: aload_0
    //   376: getfield 179	uuuuuu/lqlllq:b0070p007000700070pp00700070	Lcom/db/pwcc/dbmobile/model/banking/Account;
    //   379: invokevirtual 184	com/db/pwcc/dbmobile/model/banking/Account:getIban	()Ljava/lang/String;
    //   382: invokeinterface 333 2 0
    //   387: return
    //   388: astore 23
    //   390: aload 23
    //   392: invokevirtual 102	java/lang/reflect/InvocationTargetException:getCause	()Ljava/lang/Throwable;
    //   395: athrow
    //   396: astore 6
    //   398: aload 6
    //   400: invokevirtual 102	java/lang/reflect/InvocationTargetException:getCause	()Ljava/lang/Throwable;
    //   403: athrow
    //   404: astore 11
    //   406: aload 11
    //   408: invokevirtual 102	java/lang/reflect/InvocationTargetException:getCause	()Ljava/lang/Throwable;
    //   411: athrow
    //   412: astore 15
    //   414: aload 15
    //   416: invokevirtual 102	java/lang/reflect/InvocationTargetException:getCause	()Ljava/lang/Throwable;
    //   419: athrow
    //   420: astore 19
    //   422: aload 19
    //   424: invokevirtual 102	java/lang/reflect/InvocationTargetException:getCause	()Ljava/lang/Throwable;
    //   427: athrow
    // Local variable table:
    //   start	length	slot	name	signature
    //   0	428	0	this	lqlllq
    //   3	8	1	i	int
    //   94	281	2	localLqlqql	lllqql.lqlqql
    //   335	8	3	j	int
    //   148	9	4	localMethod1	java.lang.reflect.Method
    //   154	6	5	arrayOfObject1	Object[]
    //   396	3	6	localInvocationTargetException1	java.lang.reflect.InvocationTargetException
    //   164	3	7	localObject1	Object
    //   178	50	8	k	int
    //   199	9	9	localMethod2	java.lang.reflect.Method
    //   205	6	10	arrayOfObject2	Object[]
    //   404	3	11	localInvocationTargetException2	java.lang.reflect.InvocationTargetException
    //   215	5	12	localObject2	Object
    //   255	9	13	localMethod3	java.lang.reflect.Method
    //   261	6	14	arrayOfObject3	Object[]
    //   412	3	15	localInvocationTargetException3	java.lang.reflect.InvocationTargetException
    //   271	3	16	localObject3	Object
    //   303	9	17	localMethod4	java.lang.reflect.Method
    //   309	6	18	arrayOfObject4	Object[]
    //   420	3	19	localInvocationTargetException4	java.lang.reflect.InvocationTargetException
    //   319	3	20	localObject4	Object
    //   53	9	21	localMethod5	java.lang.reflect.Method
    //   59	6	22	arrayOfObject5	Object[]
    //   388	3	23	localInvocationTargetException5	java.lang.reflect.InvocationTargetException
    //   69	3	24	localObject5	Object
    // Exception table:
    //   from	to	target	type
    //   61	71	388	java/lang/reflect/InvocationTargetException
    //   156	166	396	java/lang/reflect/InvocationTargetException
    //   207	217	404	java/lang/reflect/InvocationTargetException
    //   263	273	412	java/lang/reflect/InvocationTargetException
    //   311	321	420	java/lang/reflect/InvocationTargetException
  }
  
  /* Error */
  private void boo006F006F006F006F006F006Foo()
  {
    // Byte code:
    //   0: getstatic 50	uuuuuu/lqlllq:bpp00700070p0070p00700070	I
    //   3: istore_1
    //   4: iload_1
    //   5: iload_1
    //   6: getstatic 52	uuuuuu/lqlllq:b0070p00700070p0070p00700070	I
    //   9: iadd
    //   10: imul
    //   11: getstatic 90	uuuuuu/lqlllq:bp007000700070p0070p00700070	I
    //   14: irem
    //   15: tableswitch	default:+17->32, 0:+71->86
    //   32: bipush 73
    //   34: putstatic 50	uuuuuu/lqlllq:bpp00700070p0070p00700070	I
    //   37: ldc 2
    //   39: ldc_w 270
    //   42: bipush 91
    //   44: bipush 126
    //   46: iconst_0
    //   47: invokestatic 86	xxxxxx/uxxxxx:bbbb0062b0062b0062b0062	(Ljava/lang/String;CCC)Ljava/lang/String;
    //   50: iconst_0
    //   51: anewarray 62	java/lang/Class
    //   54: invokevirtual 66	java/lang/Class:getMethod	(Ljava/lang/String;[Ljava/lang/Class;)Ljava/lang/reflect/Method;
    //   57: astore 22
    //   59: iconst_0
    //   60: anewarray 68	java/lang/Object
    //   63: astore 23
    //   65: aload 22
    //   67: aconst_null
    //   68: aload 23
    //   70: invokevirtual 74	java/lang/reflect/Method:invoke	(Ljava/lang/Object;[Ljava/lang/Object;)Ljava/lang/Object;
    //   73: astore 25
    //   75: aload 25
    //   77: checkcast 76	java/lang/Integer
    //   80: invokevirtual 80	java/lang/Integer:intValue	()I
    //   83: putstatic 88	uuuuuu/lqlllq:b0070007000700070p0070p00700070	I
    //   86: new 176	com/db/pwcc/dbmobile/model/sepa/TransferTemplate
    //   89: dup
    //   90: invokespecial 177	com/db/pwcc/dbmobile/model/sepa/TransferTemplate:<init>	()V
    //   93: astore_2
    //   94: aload_2
    //   95: aload_0
    //   96: getfield 179	uuuuuu/lqlllq:b0070p007000700070pp00700070	Lcom/db/pwcc/dbmobile/model/banking/Account;
    //   99: invokevirtual 184	com/db/pwcc/dbmobile/model/banking/Account:getIban	()Ljava/lang/String;
    //   102: invokevirtual 188	com/db/pwcc/dbmobile/model/sepa/TransferTemplate:setSourceAccount	(Ljava/lang/String;)V
    //   105: getstatic 50	uuuuuu/lqlllq:bpp00700070p0070p00700070	I
    //   108: istore_3
    //   109: iload_3
    //   110: iload_3
    //   111: getstatic 52	uuuuuu/lqlllq:b0070p00700070p0070p00700070	I
    //   114: iadd
    //   115: imul
    //   116: getstatic 90	uuuuuu/lqlllq:bp007000700070p0070p00700070	I
    //   119: irem
    //   120: tableswitch	default:+20->140, 0:+75->195
    //   140: bipush 13
    //   142: putstatic 50	uuuuuu/lqlllq:bpp00700070p0070p00700070	I
    //   145: ldc 2
    //   147: ldc_w 344
    //   150: bipush 120
    //   152: sipush 255
    //   155: iconst_3
    //   156: invokestatic 86	xxxxxx/uxxxxx:bbbb0062b0062b0062b0062	(Ljava/lang/String;CCC)Ljava/lang/String;
    //   159: iconst_0
    //   160: anewarray 62	java/lang/Class
    //   163: invokevirtual 66	java/lang/Class:getMethod	(Ljava/lang/String;[Ljava/lang/Class;)Ljava/lang/reflect/Method;
    //   166: astore 18
    //   168: iconst_0
    //   169: anewarray 68	java/lang/Object
    //   172: astore 19
    //   174: aload 18
    //   176: aconst_null
    //   177: aload 19
    //   179: invokevirtual 74	java/lang/reflect/Method:invoke	(Ljava/lang/Object;[Ljava/lang/Object;)Ljava/lang/Object;
    //   182: astore 21
    //   184: aload 21
    //   186: checkcast 76	java/lang/Integer
    //   189: invokevirtual 80	java/lang/Integer:intValue	()I
    //   192: putstatic 88	uuuuuu/lqlllq:b0070007000700070p0070p00700070	I
    //   195: aload_0
    //   196: getfield 198	uuuuuu/lqlllq:bnnnnn006E006E006En	Luuuuuu/ttssst$tsssst;
    //   199: checkcast 200	uuuuuu/lllqql$lqlqql
    //   202: astore 4
    //   204: ldc 2
    //   206: ldc_w 353
    //   209: bipush 48
    //   211: bipush 19
    //   213: iconst_3
    //   214: invokestatic 86	xxxxxx/uxxxxx:bbbb0062b0062b0062b0062	(Ljava/lang/String;CCC)Ljava/lang/String;
    //   217: iconst_0
    //   218: anewarray 62	java/lang/Class
    //   221: invokevirtual 66	java/lang/Class:getMethod	(Ljava/lang/String;[Ljava/lang/Class;)Ljava/lang/reflect/Method;
    //   224: astore 5
    //   226: iconst_0
    //   227: anewarray 68	java/lang/Object
    //   230: astore 6
    //   232: aload 5
    //   234: aconst_null
    //   235: aload 6
    //   237: invokevirtual 74	java/lang/reflect/Method:invoke	(Ljava/lang/Object;[Ljava/lang/Object;)Ljava/lang/Object;
    //   240: astore 8
    //   242: aload 8
    //   244: checkcast 76	java/lang/Integer
    //   247: invokevirtual 80	java/lang/Integer:intValue	()I
    //   250: getstatic 52	uuuuuu/lqlllq:b0070p00700070p0070p00700070	I
    //   253: iadd
    //   254: istore 9
    //   256: ldc 2
    //   258: ldc_w 355
    //   261: sipush 172
    //   264: bipush 111
    //   266: iconst_1
    //   267: invokestatic 86	xxxxxx/uxxxxx:bbbb0062b0062b0062b0062	(Ljava/lang/String;CCC)Ljava/lang/String;
    //   270: iconst_0
    //   271: anewarray 62	java/lang/Class
    //   274: invokevirtual 66	java/lang/Class:getMethod	(Ljava/lang/String;[Ljava/lang/Class;)Ljava/lang/reflect/Method;
    //   277: astore 10
    //   279: iconst_0
    //   280: anewarray 68	java/lang/Object
    //   283: astore 11
    //   285: aload 10
    //   287: aconst_null
    //   288: aload 11
    //   290: invokevirtual 74	java/lang/reflect/Method:invoke	(Ljava/lang/Object;[Ljava/lang/Object;)Ljava/lang/Object;
    //   293: astore 13
    //   295: iload 9
    //   297: aload 13
    //   299: checkcast 76	java/lang/Integer
    //   302: invokevirtual 80	java/lang/Integer:intValue	()I
    //   305: imul
    //   306: getstatic 90	uuuuuu/lqlllq:bp007000700070p0070p00700070	I
    //   309: irem
    //   310: getstatic 88	uuuuuu/lqlllq:b0070007000700070p0070p00700070	I
    //   313: if_icmpeq +87 -> 400
    //   316: bipush 54
    //   318: putstatic 50	uuuuuu/lqlllq:bpp00700070p0070p00700070	I
    //   321: getstatic 50	uuuuuu/lqlllq:bpp00700070p0070p00700070	I
    //   324: getstatic 52	uuuuuu/lqlllq:b0070p00700070p0070p00700070	I
    //   327: iadd
    //   328: getstatic 50	uuuuuu/lqlllq:bpp00700070p0070p00700070	I
    //   331: imul
    //   332: getstatic 90	uuuuuu/lqlllq:bp007000700070p0070p00700070	I
    //   335: irem
    //   336: getstatic 88	uuuuuu/lqlllq:b0070007000700070p0070p00700070	I
    //   339: if_icmpeq +56 -> 395
    //   342: bipush 47
    //   344: putstatic 50	uuuuuu/lqlllq:bpp00700070p0070p00700070	I
    //   347: ldc 2
    //   349: ldc_w 357
    //   352: sipush 136
    //   355: iconst_5
    //   356: invokestatic 60	xxxxxx/uxxxxx:bb00620062bb0062b0062b0062	(Ljava/lang/String;CC)Ljava/lang/String;
    //   359: iconst_0
    //   360: anewarray 62	java/lang/Class
    //   363: invokevirtual 66	java/lang/Class:getMethod	(Ljava/lang/String;[Ljava/lang/Class;)Ljava/lang/reflect/Method;
    //   366: astore 14
    //   368: iconst_0
    //   369: anewarray 68	java/lang/Object
    //   372: astore 15
    //   374: aload 14
    //   376: aconst_null
    //   377: aload 15
    //   379: invokevirtual 74	java/lang/reflect/Method:invoke	(Ljava/lang/Object;[Ljava/lang/Object;)Ljava/lang/Object;
    //   382: astore 17
    //   384: aload 17
    //   386: checkcast 76	java/lang/Integer
    //   389: invokevirtual 80	java/lang/Integer:intValue	()I
    //   392: putstatic 88	uuuuuu/lqlllq:b0070007000700070p0070p00700070	I
    //   395: bipush 69
    //   397: putstatic 88	uuuuuu/lqlllq:b0070007000700070p0070p00700070	I
    //   400: aload 4
    //   402: aload_2
    //   403: invokeinterface 360 2 0
    //   408: return
    //   409: astore 7
    //   411: aload 7
    //   413: invokevirtual 102	java/lang/reflect/InvocationTargetException:getCause	()Ljava/lang/Throwable;
    //   416: athrow
    //   417: astore 12
    //   419: aload 12
    //   421: invokevirtual 102	java/lang/reflect/InvocationTargetException:getCause	()Ljava/lang/Throwable;
    //   424: athrow
    //   425: astore 24
    //   427: aload 24
    //   429: invokevirtual 102	java/lang/reflect/InvocationTargetException:getCause	()Ljava/lang/Throwable;
    //   432: athrow
    //   433: astore 20
    //   435: aload 20
    //   437: invokevirtual 102	java/lang/reflect/InvocationTargetException:getCause	()Ljava/lang/Throwable;
    //   440: athrow
    //   441: astore 16
    //   443: aload 16
    //   445: invokevirtual 102	java/lang/reflect/InvocationTargetException:getCause	()Ljava/lang/Throwable;
    //   448: athrow
    // Local variable table:
    //   start	length	slot	name	signature
    //   0	449	0	this	lqlllq
    //   3	8	1	i	int
    //   93	310	2	localTransferTemplate	com.db.pwcc.dbmobile.model.sepa.TransferTemplate
    //   108	8	3	j	int
    //   202	199	4	localLqlqql	lllqql.lqlqql
    //   224	9	5	localMethod1	java.lang.reflect.Method
    //   230	6	6	arrayOfObject1	Object[]
    //   409	3	7	localInvocationTargetException1	java.lang.reflect.InvocationTargetException
    //   240	3	8	localObject1	Object
    //   254	52	9	k	int
    //   277	9	10	localMethod2	java.lang.reflect.Method
    //   283	6	11	arrayOfObject2	Object[]
    //   417	3	12	localInvocationTargetException2	java.lang.reflect.InvocationTargetException
    //   293	5	13	localObject2	Object
    //   366	9	14	localMethod3	java.lang.reflect.Method
    //   372	6	15	arrayOfObject3	Object[]
    //   441	3	16	localInvocationTargetException3	java.lang.reflect.InvocationTargetException
    //   382	3	17	localObject3	Object
    //   166	9	18	localMethod4	java.lang.reflect.Method
    //   172	6	19	arrayOfObject4	Object[]
    //   433	3	20	localInvocationTargetException4	java.lang.reflect.InvocationTargetException
    //   182	3	21	localObject4	Object
    //   57	9	22	localMethod5	java.lang.reflect.Method
    //   63	6	23	arrayOfObject5	Object[]
    //   425	3	24	localInvocationTargetException5	java.lang.reflect.InvocationTargetException
    //   73	3	25	localObject5	Object
    // Exception table:
    //   from	to	target	type
    //   232	242	409	java/lang/reflect/InvocationTargetException
    //   285	295	417	java/lang/reflect/InvocationTargetException
    //   65	75	425	java/lang/reflect/InvocationTargetException
    //   174	184	433	java/lang/reflect/InvocationTargetException
    //   374	384	441	java/lang/reflect/InvocationTargetException
  }
  
  public static int booo006F006F006F006F006Foo()
  {
    return 0;
  }
  
  /* Error */
  public void b006F006Fo006Foo006F006Foo()
  {
    // Byte code:
    //   0: aload_0
    //   1: getfield 198	uuuuuu/lqlllq:bnnnnn006E006E006En	Luuuuuu/ttssst$tsssst;
    //   4: checkcast 200	uuuuuu/lllqql$lqlqql
    //   7: invokeinterface 388 1 0
    //   12: new 390	uuuuuu/aaalla
    //   15: dup
    //   16: invokespecial 391	uuuuuu/aaalla:<init>	()V
    //   19: astore_1
    //   20: aload_0
    //   21: getfield 395	uuuuuu/lqlllq:b006E006E006E006E006En006E006En	Luuuuuu/hyhyhh;
    //   24: astore_2
    //   25: getstatic 50	uuuuuu/lqlllq:bpp00700070p0070p00700070	I
    //   28: istore_3
    //   29: getstatic 52	uuuuuu/lqlllq:b0070p00700070p0070p00700070	I
    //   32: istore 4
    //   34: getstatic 50	uuuuuu/lqlllq:bpp00700070p0070p00700070	I
    //   37: getstatic 52	uuuuuu/lqlllq:b0070p00700070p0070p00700070	I
    //   40: iadd
    //   41: getstatic 50	uuuuuu/lqlllq:bpp00700070p0070p00700070	I
    //   44: imul
    //   45: getstatic 90	uuuuuu/lqlllq:bp007000700070p0070p00700070	I
    //   48: irem
    //   49: getstatic 88	uuuuuu/lqlllq:b0070007000700070p0070p00700070	I
    //   52: if_icmpeq +55 -> 107
    //   55: bipush 28
    //   57: putstatic 50	uuuuuu/lqlllq:bpp00700070p0070p00700070	I
    //   60: ldc 2
    //   62: ldc_w 397
    //   65: bipush 12
    //   67: iconst_5
    //   68: invokestatic 60	xxxxxx/uxxxxx:bb00620062bb0062b0062b0062	(Ljava/lang/String;CC)Ljava/lang/String;
    //   71: iconst_0
    //   72: anewarray 62	java/lang/Class
    //   75: invokevirtual 66	java/lang/Class:getMethod	(Ljava/lang/String;[Ljava/lang/Class;)Ljava/lang/reflect/Method;
    //   78: astore 19
    //   80: iconst_0
    //   81: anewarray 68	java/lang/Object
    //   84: astore 20
    //   86: aload 19
    //   88: aconst_null
    //   89: aload 20
    //   91: invokevirtual 74	java/lang/reflect/Method:invoke	(Ljava/lang/Object;[Ljava/lang/Object;)Ljava/lang/Object;
    //   94: astore 22
    //   96: aload 22
    //   98: checkcast 76	java/lang/Integer
    //   101: invokevirtual 80	java/lang/Integer:intValue	()I
    //   104: putstatic 88	uuuuuu/lqlllq:b0070007000700070p0070p00700070	I
    //   107: iload_3
    //   108: iload_3
    //   109: iload 4
    //   111: iadd
    //   112: imul
    //   113: getstatic 90	uuuuuu/lqlllq:bp007000700070p0070p00700070	I
    //   116: irem
    //   117: tableswitch	default:+19->136, 0:+162->279
    //   136: getstatic 50	uuuuuu/lqlllq:bpp00700070p0070p00700070	I
    //   139: istore 10
    //   141: ldc 2
    //   143: ldc_w 399
    //   146: sipush 228
    //   149: iconst_3
    //   150: invokestatic 60	xxxxxx/uxxxxx:bb00620062bb0062b0062b0062	(Ljava/lang/String;CC)Ljava/lang/String;
    //   153: iconst_0
    //   154: anewarray 62	java/lang/Class
    //   157: invokevirtual 66	java/lang/Class:getMethod	(Ljava/lang/String;[Ljava/lang/Class;)Ljava/lang/reflect/Method;
    //   160: astore 11
    //   162: iconst_0
    //   163: anewarray 68	java/lang/Object
    //   166: astore 12
    //   168: aload 11
    //   170: aconst_null
    //   171: aload 12
    //   173: invokevirtual 74	java/lang/reflect/Method:invoke	(Ljava/lang/Object;[Ljava/lang/Object;)Ljava/lang/Object;
    //   176: astore 14
    //   178: iload 10
    //   180: iload 10
    //   182: aload 14
    //   184: checkcast 76	java/lang/Integer
    //   187: invokevirtual 80	java/lang/Integer:intValue	()I
    //   190: iadd
    //   191: imul
    //   192: getstatic 90	uuuuuu/lqlllq:bp007000700070p0070p00700070	I
    //   195: irem
    //   196: tableswitch	default:+20->216, 0:+73->269
    //   216: bipush 14
    //   218: putstatic 50	uuuuuu/lqlllq:bpp00700070p0070p00700070	I
    //   221: ldc 2
    //   223: ldc_w 401
    //   226: sipush 217
    //   229: iconst_0
    //   230: invokestatic 60	xxxxxx/uxxxxx:bb00620062bb0062b0062b0062	(Ljava/lang/String;CC)Ljava/lang/String;
    //   233: iconst_0
    //   234: anewarray 62	java/lang/Class
    //   237: invokevirtual 66	java/lang/Class:getMethod	(Ljava/lang/String;[Ljava/lang/Class;)Ljava/lang/reflect/Method;
    //   240: astore 15
    //   242: iconst_0
    //   243: anewarray 68	java/lang/Object
    //   246: astore 16
    //   248: aload 15
    //   250: aconst_null
    //   251: aload 16
    //   253: invokevirtual 74	java/lang/reflect/Method:invoke	(Ljava/lang/Object;[Ljava/lang/Object;)Ljava/lang/Object;
    //   256: astore 18
    //   258: aload 18
    //   260: checkcast 76	java/lang/Integer
    //   263: invokevirtual 80	java/lang/Integer:intValue	()I
    //   266: putstatic 88	uuuuuu/lqlllq:b0070007000700070p0070p00700070	I
    //   269: bipush 35
    //   271: putstatic 50	uuuuuu/lqlllq:bpp00700070p0070p00700070	I
    //   274: bipush 72
    //   276: putstatic 88	uuuuuu/lqlllq:b0070007000700070p0070p00700070	I
    //   279: aload_2
    //   280: invokevirtual 406	uuuuuu/hyhyhh:b0070pp007000700070p007000700070	()Ljava/lang/String;
    //   283: astore 5
    //   285: getstatic 50	uuuuuu/lqlllq:bpp00700070p0070p00700070	I
    //   288: getstatic 52	uuuuuu/lqlllq:b0070p00700070p0070p00700070	I
    //   291: iadd
    //   292: getstatic 50	uuuuuu/lqlllq:bpp00700070p0070p00700070	I
    //   295: imul
    //   296: getstatic 90	uuuuuu/lqlllq:bp007000700070p0070p00700070	I
    //   299: irem
    //   300: getstatic 88	uuuuuu/lqlllq:b0070007000700070p0070p00700070	I
    //   303: if_icmpeq +55 -> 358
    //   306: iconst_3
    //   307: putstatic 50	uuuuuu/lqlllq:bpp00700070p0070p00700070	I
    //   310: ldc 2
    //   312: ldc_w 408
    //   315: sipush 175
    //   318: iconst_4
    //   319: invokestatic 60	xxxxxx/uxxxxx:bb00620062bb0062b0062b0062	(Ljava/lang/String;CC)Ljava/lang/String;
    //   322: iconst_0
    //   323: anewarray 62	java/lang/Class
    //   326: invokevirtual 66	java/lang/Class:getMethod	(Ljava/lang/String;[Ljava/lang/Class;)Ljava/lang/reflect/Method;
    //   329: astore 6
    //   331: iconst_0
    //   332: anewarray 68	java/lang/Object
    //   335: astore 7
    //   337: aload 6
    //   339: aconst_null
    //   340: aload 7
    //   342: invokevirtual 74	java/lang/reflect/Method:invoke	(Ljava/lang/Object;[Ljava/lang/Object;)Ljava/lang/Object;
    //   345: astore 9
    //   347: aload 9
    //   349: checkcast 76	java/lang/Integer
    //   352: invokevirtual 80	java/lang/Integer:intValue	()I
    //   355: putstatic 88	uuuuuu/lqlllq:b0070007000700070p0070p00700070	I
    //   358: aload_1
    //   359: aload_0
    //   360: aload 5
    //   362: aload_0
    //   363: getfield 233	uuuuuu/lqlllq:bp0070007000700070pp00700070	Ljava/lang/String;
    //   366: invokevirtual 412	uuuuuu/aaalla:bu0075007500750075u0075007500750075	(Luuuuuu/vxvxvv$xvvxvv;Ljava/lang/String;Ljava/lang/String;)V
    //   369: return
    //   370: astore 21
    //   372: aload 21
    //   374: invokevirtual 102	java/lang/reflect/InvocationTargetException:getCause	()Ljava/lang/Throwable;
    //   377: athrow
    //   378: astore 13
    //   380: aload 13
    //   382: invokevirtual 102	java/lang/reflect/InvocationTargetException:getCause	()Ljava/lang/Throwable;
    //   385: athrow
    //   386: astore 8
    //   388: aload 8
    //   390: invokevirtual 102	java/lang/reflect/InvocationTargetException:getCause	()Ljava/lang/Throwable;
    //   393: athrow
    //   394: astore 17
    //   396: aload 17
    //   398: invokevirtual 102	java/lang/reflect/InvocationTargetException:getCause	()Ljava/lang/Throwable;
    //   401: athrow
    // Local variable table:
    //   start	length	slot	name	signature
    //   0	402	0	this	lqlllq
    //   19	340	1	localAaalla	aaalla
    //   24	256	2	localHyhyhh	hyhyhh
    //   28	85	3	i	int
    //   32	80	4	j	int
    //   283	78	5	str	String
    //   329	9	6	localMethod1	java.lang.reflect.Method
    //   335	6	7	arrayOfObject1	Object[]
    //   386	3	8	localInvocationTargetException1	java.lang.reflect.InvocationTargetException
    //   345	3	9	localObject1	Object
    //   139	53	10	k	int
    //   160	9	11	localMethod2	java.lang.reflect.Method
    //   166	6	12	arrayOfObject2	Object[]
    //   378	3	13	localInvocationTargetException2	java.lang.reflect.InvocationTargetException
    //   176	7	14	localObject2	Object
    //   240	9	15	localMethod3	java.lang.reflect.Method
    //   246	6	16	arrayOfObject3	Object[]
    //   394	3	17	localInvocationTargetException3	java.lang.reflect.InvocationTargetException
    //   256	3	18	localObject3	Object
    //   78	9	19	localMethod4	java.lang.reflect.Method
    //   84	6	20	arrayOfObject4	Object[]
    //   370	3	21	localInvocationTargetException4	java.lang.reflect.InvocationTargetException
    //   94	3	22	localObject4	Object
    // Exception table:
    //   from	to	target	type
    //   86	96	370	java/lang/reflect/InvocationTargetException
    //   168	178	378	java/lang/reflect/InvocationTargetException
    //   337	347	386	java/lang/reflect/InvocationTargetException
    //   248	258	394	java/lang/reflect/InvocationTargetException
  }
  
  /* Error */
  public void b006Fo006F006Foo006F006Foo()
  {
    // Byte code:
    //   0: aload_0
    //   1: getfield 198	uuuuuu/lqlllq:bnnnnn006E006E006En	Luuuuuu/ttssst$tsssst;
    //   4: checkcast 200	uuuuuu/lllqql$lqlqql
    //   7: getstatic 418	com/db/pwcc/dbmobile/financial_overview/R$id:menu_item_new_transfer_sepa_flow	I
    //   10: invokeinterface 422 2 0
    //   15: aload_0
    //   16: getfield 198	uuuuuu/lqlllq:bnnnnn006E006E006En	Luuuuuu/ttssst$tsssst;
    //   19: checkcast 200	uuuuuu/lllqql$lqlqql
    //   22: getstatic 425	com/db/pwcc/dbmobile/financial_overview/R$id:menu_item_new_transaction	I
    //   25: invokeinterface 422 2 0
    //   30: aload_0
    //   31: getfield 198	uuuuuu/lqlllq:bnnnnn006E006E006En	Luuuuuu/ttssst$tsssst;
    //   34: checkcast 200	uuuuuu/lllqql$lqlqql
    //   37: getstatic 428	com/db/pwcc/dbmobile/financial_overview/R$id:menu_item_transfer_subaccount	I
    //   40: invokeinterface 422 2 0
    //   45: aload_0
    //   46: getfield 198	uuuuuu/lqlllq:bnnnnn006E006E006En	Luuuuuu/ttssst$tsssst;
    //   49: checkcast 200	uuuuuu/lllqql$lqlqql
    //   52: getstatic 431	com/db/pwcc/dbmobile/financial_overview/R$id:menu_item_new_standing_order	I
    //   55: invokeinterface 422 2 0
    //   60: aload_0
    //   61: getfield 198	uuuuuu/lqlllq:bnnnnn006E006E006En	Luuuuuu/ttssst$tsssst;
    //   64: checkcast 200	uuuuuu/lllqql$lqlqql
    //   67: astore_1
    //   68: getstatic 50	uuuuuu/lqlllq:bpp00700070p0070p00700070	I
    //   71: istore_2
    //   72: iload_2
    //   73: iload_2
    //   74: getstatic 52	uuuuuu/lqlllq:b0070p00700070p0070p00700070	I
    //   77: iadd
    //   78: imul
    //   79: getstatic 90	uuuuuu/lqlllq:bp007000700070p0070p00700070	I
    //   82: irem
    //   83: tableswitch	default:+17->100, 0:+72->155
    //   100: bipush 75
    //   102: putstatic 50	uuuuuu/lqlllq:bpp00700070p0070p00700070	I
    //   105: ldc 2
    //   107: ldc_w 433
    //   110: bipush 102
    //   112: sipush 166
    //   115: iconst_3
    //   116: invokestatic 86	xxxxxx/uxxxxx:bbbb0062b0062b0062b0062	(Ljava/lang/String;CCC)Ljava/lang/String;
    //   119: iconst_0
    //   120: anewarray 62	java/lang/Class
    //   123: invokevirtual 66	java/lang/Class:getMethod	(Ljava/lang/String;[Ljava/lang/Class;)Ljava/lang/reflect/Method;
    //   126: astore 29
    //   128: iconst_0
    //   129: anewarray 68	java/lang/Object
    //   132: astore 30
    //   134: aload 29
    //   136: aconst_null
    //   137: aload 30
    //   139: invokevirtual 74	java/lang/reflect/Method:invoke	(Ljava/lang/Object;[Ljava/lang/Object;)Ljava/lang/Object;
    //   142: astore 32
    //   144: aload 32
    //   146: checkcast 76	java/lang/Integer
    //   149: invokevirtual 80	java/lang/Integer:intValue	()I
    //   152: putstatic 88	uuuuuu/lqlllq:b0070007000700070p0070p00700070	I
    //   155: aload_1
    //   156: getstatic 436	com/db/pwcc/dbmobile/financial_overview/R$id:menu_item_photo_transfer	I
    //   159: invokeinterface 422 2 0
    //   164: getstatic 442	com/db/pwcc/dbmobile/model/banking/Account$ProductType:CURRENT_ACCOUNT	Lcom/db/pwcc/dbmobile/model/banking/Account$ProductType;
    //   167: aload_0
    //   168: getfield 179	uuuuuu/lqlllq:b0070p007000700070pp00700070	Lcom/db/pwcc/dbmobile/model/banking/Account;
    //   171: invokevirtual 446	com/db/pwcc/dbmobile/model/banking/Account:getProductType	()Lcom/db/pwcc/dbmobile/model/banking/Account$ProductType;
    //   174: if_acmpeq +4 -> 178
    //   177: return
    //   178: aload_0
    //   179: getfield 137	uuuuuu/lqlllq:b007000700070pp0070p00700070	Luuuuuu/sxxxsx;
    //   182: aload_0
    //   183: getfield 112	uuuuuu/lqlllq:bp00700070pp0070p00700070	Luuuuuu/sxxxsx$xsxsxx;
    //   186: iconst_2
    //   187: newarray int
    //   189: dup
    //   190: iconst_0
    //   191: iconst_1
    //   192: iastore
    //   193: dup
    //   194: iconst_1
    //   195: iconst_0
    //   196: iastore
    //   197: invokevirtual 450	uuuuuu/sxxxsx:bk006B006B006B006Bk006B006B006B006B	(Luuuuuu/sxxxsx$xsxsxx;[I)V
    //   200: aload_0
    //   201: getfield 139	uuuuuu/lqlllq:bp0070p0070p0070p00700070	Luuuuuu/sxxxsx;
    //   204: astore_3
    //   205: getstatic 50	uuuuuu/lqlllq:bpp00700070p0070p00700070	I
    //   208: getstatic 52	uuuuuu/lqlllq:b0070p00700070p0070p00700070	I
    //   211: iadd
    //   212: getstatic 50	uuuuuu/lqlllq:bpp00700070p0070p00700070	I
    //   215: imul
    //   216: getstatic 90	uuuuuu/lqlllq:bp007000700070p0070p00700070	I
    //   219: irem
    //   220: getstatic 88	uuuuuu/lqlllq:b0070007000700070p0070p00700070	I
    //   223: if_icmpeq +13 -> 236
    //   226: bipush 86
    //   228: putstatic 50	uuuuuu/lqlllq:bpp00700070p0070p00700070	I
    //   231: bipush 6
    //   233: putstatic 88	uuuuuu/lqlllq:b0070007000700070p0070p00700070	I
    //   236: aload_3
    //   237: aload_0
    //   238: getfield 117	uuuuuu/lqlllq:b00700070p0070p0070p00700070	Luuuuuu/sxxxsx$xsxsxx;
    //   241: iconst_2
    //   242: newarray int
    //   244: dup
    //   245: iconst_0
    //   246: iconst_1
    //   247: iastore
    //   248: dup
    //   249: iconst_1
    //   250: iconst_3
    //   251: iastore
    //   252: invokevirtual 450	uuuuuu/sxxxsx:bk006B006B006B006Bk006B006B006B006B	(Luuuuuu/sxxxsx$xsxsxx;[I)V
    //   255: aload_0
    //   256: getfield 141	uuuuuu/lqlllq:b0070pp0070p0070p00700070	Luuuuuu/sxxxsx;
    //   259: aload_0
    //   260: getfield 122	uuuuuu/lqlllq:bppp0070p0070p00700070	Luuuuuu/sxxxsx$xsxsxx;
    //   263: iconst_2
    //   264: newarray int
    //   266: dup
    //   267: iconst_0
    //   268: iconst_4
    //   269: iastore
    //   270: dup
    //   271: iconst_1
    //   272: iconst_0
    //   273: iastore
    //   274: invokevirtual 450	uuuuuu/sxxxsx:bk006B006B006B006Bk006B006B006B006B	(Luuuuuu/sxxxsx$xsxsxx;[I)V
    //   277: aload_0
    //   278: getfield 452	uuuuuu/lqlllq:b00700070007000700070pp00700070	Luuuuuu/sssttt;
    //   281: astore 4
    //   283: ldc 2
    //   285: ldc_w 454
    //   288: bipush 61
    //   290: sipush 238
    //   293: iconst_1
    //   294: invokestatic 86	xxxxxx/uxxxxx:bbbb0062b0062b0062b0062	(Ljava/lang/String;CCC)Ljava/lang/String;
    //   297: iconst_0
    //   298: anewarray 62	java/lang/Class
    //   301: invokevirtual 66	java/lang/Class:getMethod	(Ljava/lang/String;[Ljava/lang/Class;)Ljava/lang/reflect/Method;
    //   304: astore 5
    //   306: iconst_0
    //   307: anewarray 68	java/lang/Object
    //   310: astore 6
    //   312: aload 5
    //   314: aconst_null
    //   315: aload 6
    //   317: invokevirtual 74	java/lang/reflect/Method:invoke	(Ljava/lang/Object;[Ljava/lang/Object;)Ljava/lang/Object;
    //   320: astore 8
    //   322: aload 8
    //   324: checkcast 76	java/lang/Integer
    //   327: invokevirtual 80	java/lang/Integer:intValue	()I
    //   330: getstatic 52	uuuuuu/lqlllq:b0070p00700070p0070p00700070	I
    //   333: iadd
    //   334: istore 9
    //   336: ldc 2
    //   338: ldc_w 314
    //   341: sipush 248
    //   344: sipush 204
    //   347: iconst_2
    //   348: invokestatic 86	xxxxxx/uxxxxx:bbbb0062b0062b0062b0062	(Ljava/lang/String;CCC)Ljava/lang/String;
    //   351: iconst_0
    //   352: anewarray 62	java/lang/Class
    //   355: invokevirtual 66	java/lang/Class:getMethod	(Ljava/lang/String;[Ljava/lang/Class;)Ljava/lang/reflect/Method;
    //   358: astore 10
    //   360: iconst_0
    //   361: anewarray 68	java/lang/Object
    //   364: astore 11
    //   366: aload 10
    //   368: aconst_null
    //   369: aload 11
    //   371: invokevirtual 74	java/lang/reflect/Method:invoke	(Ljava/lang/Object;[Ljava/lang/Object;)Ljava/lang/Object;
    //   374: astore 13
    //   376: iload 9
    //   378: aload 13
    //   380: checkcast 76	java/lang/Integer
    //   383: invokevirtual 80	java/lang/Integer:intValue	()I
    //   386: imul
    //   387: getstatic 90	uuuuuu/lqlllq:bp007000700070p0070p00700070	I
    //   390: irem
    //   391: getstatic 88	uuuuuu/lqlllq:b0070007000700070p0070p00700070	I
    //   394: if_icmpeq +59 -> 453
    //   397: ldc 2
    //   399: ldc_w 456
    //   402: sipush 249
    //   405: sipush 182
    //   408: iconst_0
    //   409: invokestatic 86	xxxxxx/uxxxxx:bbbb0062b0062b0062b0062	(Ljava/lang/String;CCC)Ljava/lang/String;
    //   412: iconst_0
    //   413: anewarray 62	java/lang/Class
    //   416: invokevirtual 66	java/lang/Class:getMethod	(Ljava/lang/String;[Ljava/lang/Class;)Ljava/lang/reflect/Method;
    //   419: astore 25
    //   421: iconst_0
    //   422: anewarray 68	java/lang/Object
    //   425: astore 26
    //   427: aload 25
    //   429: aconst_null
    //   430: aload 26
    //   432: invokevirtual 74	java/lang/reflect/Method:invoke	(Ljava/lang/Object;[Ljava/lang/Object;)Ljava/lang/Object;
    //   435: astore 28
    //   437: aload 28
    //   439: checkcast 76	java/lang/Integer
    //   442: invokevirtual 80	java/lang/Integer:intValue	()I
    //   445: putstatic 50	uuuuuu/lqlllq:bpp00700070p0070p00700070	I
    //   448: bipush 33
    //   450: putstatic 88	uuuuuu/lqlllq:b0070007000700070p0070p00700070	I
    //   453: aload 4
    //   455: getstatic 462	com/db/pwcc/dbmobile/foundation/features/Feature:GINI	Lcom/db/pwcc/dbmobile/foundation/features/Feature;
    //   458: invokevirtual 468	uuuuuu/sssttt:bk006Bkkk006B006B006Bkk	(Lcom/db/pwcc/dbmobile/foundation/features/Feature;)Luuuuuu/sststt;
    //   461: getstatic 474	uuuuuu/sststt:b006En006En006Enn006En	Luuuuuu/sststt;
    //   464: if_acmpne -287 -> 177
    //   467: aload_0
    //   468: getfield 143	uuuuuu/lqlllq:bpp0070pp0070p00700070	Luuuuuu/sxxxsx;
    //   471: astore 14
    //   473: aload_0
    //   474: getfield 132	uuuuuu/lqlllq:b00700070ppp0070p00700070	Luuuuuu/sxxxsx$xsxsxx;
    //   477: astore 15
    //   479: iconst_2
    //   480: newarray int
    //   482: astore 16
    //   484: getstatic 50	uuuuuu/lqlllq:bpp00700070p0070p00700070	I
    //   487: getstatic 52	uuuuuu/lqlllq:b0070p00700070p0070p00700070	I
    //   490: iadd
    //   491: getstatic 50	uuuuuu/lqlllq:bpp00700070p0070p00700070	I
    //   494: imul
    //   495: getstatic 90	uuuuuu/lqlllq:bp007000700070p0070p00700070	I
    //   498: irem
    //   499: getstatic 88	uuuuuu/lqlllq:b0070007000700070p0070p00700070	I
    //   502: if_icmpeq +99 -> 601
    //   505: ldc 2
    //   507: ldc_w 476
    //   510: sipush 197
    //   513: sipush 226
    //   516: iconst_2
    //   517: invokestatic 86	xxxxxx/uxxxxx:bbbb0062b0062b0062b0062	(Ljava/lang/String;CCC)Ljava/lang/String;
    //   520: iconst_0
    //   521: anewarray 62	java/lang/Class
    //   524: invokevirtual 66	java/lang/Class:getMethod	(Ljava/lang/String;[Ljava/lang/Class;)Ljava/lang/reflect/Method;
    //   527: astore 17
    //   529: iconst_0
    //   530: anewarray 68	java/lang/Object
    //   533: astore 18
    //   535: aload 17
    //   537: aconst_null
    //   538: aload 18
    //   540: invokevirtual 74	java/lang/reflect/Method:invoke	(Ljava/lang/Object;[Ljava/lang/Object;)Ljava/lang/Object;
    //   543: astore 20
    //   545: aload 20
    //   547: checkcast 76	java/lang/Integer
    //   550: invokevirtual 80	java/lang/Integer:intValue	()I
    //   553: putstatic 50	uuuuuu/lqlllq:bpp00700070p0070p00700070	I
    //   556: ldc 2
    //   558: ldc -34
    //   560: iconst_2
    //   561: iconst_2
    //   562: invokestatic 60	xxxxxx/uxxxxx:bb00620062bb0062b0062b0062	(Ljava/lang/String;CC)Ljava/lang/String;
    //   565: iconst_0
    //   566: anewarray 62	java/lang/Class
    //   569: invokevirtual 66	java/lang/Class:getMethod	(Ljava/lang/String;[Ljava/lang/Class;)Ljava/lang/reflect/Method;
    //   572: astore 21
    //   574: iconst_0
    //   575: anewarray 68	java/lang/Object
    //   578: astore 22
    //   580: aload 21
    //   582: aconst_null
    //   583: aload 22
    //   585: invokevirtual 74	java/lang/reflect/Method:invoke	(Ljava/lang/Object;[Ljava/lang/Object;)Ljava/lang/Object;
    //   588: astore 24
    //   590: aload 24
    //   592: checkcast 76	java/lang/Integer
    //   595: invokevirtual 80	java/lang/Integer:intValue	()I
    //   598: putstatic 88	uuuuuu/lqlllq:b0070007000700070p0070p00700070	I
    //   601: aload 16
    //   603: iconst_0
    //   604: iconst_1
    //   605: iastore
    //   606: aload 16
    //   608: iconst_1
    //   609: iconst_0
    //   610: iastore
    //   611: aload 14
    //   613: aload 15
    //   615: aload 16
    //   617: invokevirtual 450	uuuuuu/sxxxsx:bk006B006B006B006Bk006B006B006B006B	(Luuuuuu/sxxxsx$xsxsxx;[I)V
    //   620: return
    //   621: astore 19
    //   623: aload 19
    //   625: invokevirtual 102	java/lang/reflect/InvocationTargetException:getCause	()Ljava/lang/Throwable;
    //   628: athrow
    //   629: astore 7
    //   631: aload 7
    //   633: invokevirtual 102	java/lang/reflect/InvocationTargetException:getCause	()Ljava/lang/Throwable;
    //   636: athrow
    //   637: astore 12
    //   639: aload 12
    //   641: invokevirtual 102	java/lang/reflect/InvocationTargetException:getCause	()Ljava/lang/Throwable;
    //   644: athrow
    //   645: astore 23
    //   647: aload 23
    //   649: invokevirtual 102	java/lang/reflect/InvocationTargetException:getCause	()Ljava/lang/Throwable;
    //   652: athrow
    //   653: astore 27
    //   655: aload 27
    //   657: invokevirtual 102	java/lang/reflect/InvocationTargetException:getCause	()Ljava/lang/Throwable;
    //   660: athrow
    //   661: astore 31
    //   663: aload 31
    //   665: invokevirtual 102	java/lang/reflect/InvocationTargetException:getCause	()Ljava/lang/Throwable;
    //   668: athrow
    // Local variable table:
    //   start	length	slot	name	signature
    //   0	669	0	this	lqlllq
    //   67	89	1	localLqlqql	lllqql.lqlqql
    //   71	8	2	i	int
    //   204	33	3	localSxxxsx1	sxxxsx
    //   281	173	4	localSssttt	sssttt
    //   304	9	5	localMethod1	java.lang.reflect.Method
    //   310	6	6	arrayOfObject1	Object[]
    //   629	3	7	localInvocationTargetException1	java.lang.reflect.InvocationTargetException
    //   320	3	8	localObject1	Object
    //   334	53	9	j	int
    //   358	9	10	localMethod2	java.lang.reflect.Method
    //   364	6	11	arrayOfObject2	Object[]
    //   637	3	12	localInvocationTargetException2	java.lang.reflect.InvocationTargetException
    //   374	5	13	localObject2	Object
    //   471	141	14	localSxxxsx2	sxxxsx
    //   477	137	15	localXsxsxx	sxxxsx.xsxsxx
    //   482	134	16	arrayOfInt	int[]
    //   527	9	17	localMethod3	java.lang.reflect.Method
    //   533	6	18	arrayOfObject3	Object[]
    //   621	3	19	localInvocationTargetException3	java.lang.reflect.InvocationTargetException
    //   543	3	20	localObject3	Object
    //   572	9	21	localMethod4	java.lang.reflect.Method
    //   578	6	22	arrayOfObject4	Object[]
    //   645	3	23	localInvocationTargetException4	java.lang.reflect.InvocationTargetException
    //   588	3	24	localObject4	Object
    //   419	9	25	localMethod5	java.lang.reflect.Method
    //   425	6	26	arrayOfObject5	Object[]
    //   653	3	27	localInvocationTargetException5	java.lang.reflect.InvocationTargetException
    //   435	3	28	localObject5	Object
    //   126	9	29	localMethod6	java.lang.reflect.Method
    //   132	6	30	arrayOfObject6	Object[]
    //   661	3	31	localInvocationTargetException6	java.lang.reflect.InvocationTargetException
    //   142	3	32	localObject6	Object
    // Exception table:
    //   from	to	target	type
    //   535	545	621	java/lang/reflect/InvocationTargetException
    //   312	322	629	java/lang/reflect/InvocationTargetException
    //   366	376	637	java/lang/reflect/InvocationTargetException
    //   580	590	645	java/lang/reflect/InvocationTargetException
    //   427	437	653	java/lang/reflect/InvocationTargetException
    //   134	144	661	java/lang/reflect/InvocationTargetException
  }
  
  /* Error */
  public void b006Fooooo006Fooo(com.db.pwcc.dbmobile.model.error.DbError paramDbError)
  {
    // Byte code:
    //   0: aload_0
    //   1: invokevirtual 481	uuuuuu/lqlllq:bkk006Bk006Bk006Bk006Bk	()Z
    //   4: istore_2
    //   5: getstatic 50	uuuuuu/lqlllq:bpp00700070p0070p00700070	I
    //   8: istore_3
    //   9: iload_3
    //   10: iload_3
    //   11: getstatic 52	uuuuuu/lqlllq:b0070p00700070p0070p00700070	I
    //   14: iadd
    //   15: imul
    //   16: getstatic 90	uuuuuu/lqlllq:bp007000700070p0070p00700070	I
    //   19: irem
    //   20: tableswitch	default:+20->40, 0:+30->50
    //   40: bipush 89
    //   42: putstatic 50	uuuuuu/lqlllq:bpp00700070p0070p00700070	I
    //   45: bipush 32
    //   47: putstatic 88	uuuuuu/lqlllq:b0070007000700070p0070p00700070	I
    //   50: iload_2
    //   51: ifne +127 -> 178
    //   54: ldc 2
    //   56: ldc_w 483
    //   59: bipush 16
    //   61: sipush 165
    //   64: iconst_2
    //   65: invokestatic 86	xxxxxx/uxxxxx:bbbb0062b0062b0062b0062	(Ljava/lang/String;CCC)Ljava/lang/String;
    //   68: iconst_0
    //   69: anewarray 62	java/lang/Class
    //   72: invokevirtual 66	java/lang/Class:getMethod	(Ljava/lang/String;[Ljava/lang/Class;)Ljava/lang/reflect/Method;
    //   75: astore 27
    //   77: iconst_0
    //   78: anewarray 68	java/lang/Object
    //   81: astore 28
    //   83: aload 27
    //   85: aconst_null
    //   86: aload 28
    //   88: invokevirtual 74	java/lang/reflect/Method:invoke	(Ljava/lang/Object;[Ljava/lang/Object;)Ljava/lang/Object;
    //   91: astore 30
    //   93: aload 30
    //   95: checkcast 76	java/lang/Integer
    //   98: invokevirtual 80	java/lang/Integer:intValue	()I
    //   101: getstatic 52	uuuuuu/lqlllq:b0070p00700070p0070p00700070	I
    //   104: iadd
    //   105: istore 31
    //   107: ldc 2
    //   109: ldc_w 485
    //   112: sipush 252
    //   115: bipush 40
    //   117: iconst_2
    //   118: invokestatic 86	xxxxxx/uxxxxx:bbbb0062b0062b0062b0062	(Ljava/lang/String;CCC)Ljava/lang/String;
    //   121: iconst_0
    //   122: anewarray 62	java/lang/Class
    //   125: invokevirtual 66	java/lang/Class:getMethod	(Ljava/lang/String;[Ljava/lang/Class;)Ljava/lang/reflect/Method;
    //   128: astore 32
    //   130: iconst_0
    //   131: anewarray 68	java/lang/Object
    //   134: astore 33
    //   136: aload 32
    //   138: aconst_null
    //   139: aload 33
    //   141: invokevirtual 74	java/lang/reflect/Method:invoke	(Ljava/lang/Object;[Ljava/lang/Object;)Ljava/lang/Object;
    //   144: astore 35
    //   146: iload 31
    //   148: aload 35
    //   150: checkcast 76	java/lang/Integer
    //   153: invokevirtual 80	java/lang/Integer:intValue	()I
    //   156: imul
    //   157: getstatic 90	uuuuuu/lqlllq:bp007000700070p0070p00700070	I
    //   160: irem
    //   161: getstatic 88	uuuuuu/lqlllq:b0070007000700070p0070p00700070	I
    //   164: if_icmpeq +13 -> 177
    //   167: bipush 91
    //   169: putstatic 50	uuuuuu/lqlllq:bpp00700070p0070p00700070	I
    //   172: bipush 67
    //   174: putstatic 88	uuuuuu/lqlllq:b0070007000700070p0070p00700070	I
    //   177: return
    //   178: aload_0
    //   179: getfield 198	uuuuuu/lqlllq:bnnnnn006E006E006En	Luuuuuu/ttssst$tsssst;
    //   182: checkcast 200	uuuuuu/lllqql$lqlqql
    //   185: invokeinterface 488 1 0
    //   190: getstatic 98	uuuuuu/lqlllq:bpp007000700070pp00700070	Ljava/lang/String;
    //   193: astore 4
    //   195: ldc_w 490
    //   198: sipush 183
    //   201: iconst_1
    //   202: invokestatic 60	xxxxxx/uxxxxx:bb00620062bb0062b0062b0062	(Ljava/lang/String;CC)Ljava/lang/String;
    //   205: astore 5
    //   207: iconst_3
    //   208: anewarray 62	java/lang/Class
    //   211: astore 6
    //   213: aload 6
    //   215: iconst_0
    //   216: ldc -87
    //   218: aastore
    //   219: aload 6
    //   221: iconst_1
    //   222: getstatic 496	java/lang/Character:TYPE	Ljava/lang/Class;
    //   225: aastore
    //   226: aload 6
    //   228: iconst_2
    //   229: getstatic 496	java/lang/Character:TYPE	Ljava/lang/Class;
    //   232: aastore
    //   233: ldc_w 498
    //   236: aload 5
    //   238: aload 6
    //   240: invokevirtual 66	java/lang/Class:getMethod	(Ljava/lang/String;[Ljava/lang/Class;)Ljava/lang/reflect/Method;
    //   243: astore 7
    //   245: iconst_3
    //   246: anewarray 68	java/lang/Object
    //   249: astore 8
    //   251: aload 8
    //   253: iconst_0
    //   254: ldc_w 500
    //   257: aastore
    //   258: aload 8
    //   260: iconst_1
    //   261: sipush 145
    //   264: invokestatic 504	java/lang/Character:valueOf	(C)Ljava/lang/Character;
    //   267: aastore
    //   268: aload 8
    //   270: iconst_2
    //   271: iconst_4
    //   272: invokestatic 504	java/lang/Character:valueOf	(C)Ljava/lang/Character;
    //   275: aastore
    //   276: aload 7
    //   278: aconst_null
    //   279: aload 8
    //   281: invokevirtual 74	java/lang/reflect/Method:invoke	(Ljava/lang/Object;[Ljava/lang/Object;)Ljava/lang/Object;
    //   284: astore 10
    //   286: aload 4
    //   288: aload 10
    //   290: checkcast 169	java/lang/String
    //   293: aload_1
    //   294: invokestatic 510	uuuuuu/rvvvrv:b00710071qq00710071q0071q0071	(Ljava/lang/String;Ljava/lang/String;Ljava/lang/Throwable;)V
    //   297: aload_0
    //   298: aload_1
    //   299: invokevirtual 514	uuuuuu/lqlllq:boo006F006F006F006Fo006F006F006F	(Lcom/db/pwcc/dbmobile/model/error/DbError;)Z
    //   302: ifeq +223 -> 525
    //   305: ldc 2
    //   307: ldc_w 305
    //   310: sipush 219
    //   313: sipush 234
    //   316: iconst_1
    //   317: invokestatic 86	xxxxxx/uxxxxx:bbbb0062b0062b0062b0062	(Ljava/lang/String;CCC)Ljava/lang/String;
    //   320: iconst_0
    //   321: anewarray 62	java/lang/Class
    //   324: invokevirtual 66	java/lang/Class:getMethod	(Ljava/lang/String;[Ljava/lang/Class;)Ljava/lang/reflect/Method;
    //   327: astore 12
    //   329: iconst_0
    //   330: anewarray 68	java/lang/Object
    //   333: astore 13
    //   335: aload 12
    //   337: aconst_null
    //   338: aload 13
    //   340: invokevirtual 74	java/lang/reflect/Method:invoke	(Ljava/lang/Object;[Ljava/lang/Object;)Ljava/lang/Object;
    //   343: astore 15
    //   345: aload 15
    //   347: checkcast 76	java/lang/Integer
    //   350: invokevirtual 80	java/lang/Integer:intValue	()I
    //   353: getstatic 52	uuuuuu/lqlllq:b0070p00700070p0070p00700070	I
    //   356: iadd
    //   357: istore 16
    //   359: ldc 2
    //   361: ldc_w 516
    //   364: bipush 88
    //   366: bipush 48
    //   368: iconst_0
    //   369: invokestatic 86	xxxxxx/uxxxxx:bbbb0062b0062b0062b0062	(Ljava/lang/String;CCC)Ljava/lang/String;
    //   372: iconst_0
    //   373: anewarray 62	java/lang/Class
    //   376: invokevirtual 66	java/lang/Class:getMethod	(Ljava/lang/String;[Ljava/lang/Class;)Ljava/lang/reflect/Method;
    //   379: astore 17
    //   381: iconst_0
    //   382: anewarray 68	java/lang/Object
    //   385: astore 18
    //   387: aload 17
    //   389: aconst_null
    //   390: aload 18
    //   392: invokevirtual 74	java/lang/reflect/Method:invoke	(Ljava/lang/Object;[Ljava/lang/Object;)Ljava/lang/Object;
    //   395: astore 20
    //   397: iload 16
    //   399: aload 20
    //   401: checkcast 76	java/lang/Integer
    //   404: invokevirtual 80	java/lang/Integer:intValue	()I
    //   407: imul
    //   408: getstatic 90	uuuuuu/lqlllq:bp007000700070p0070p00700070	I
    //   411: irem
    //   412: getstatic 88	uuuuuu/lqlllq:b0070007000700070p0070p00700070	I
    //   415: if_icmpeq +58 -> 473
    //   418: bipush 12
    //   420: putstatic 50	uuuuuu/lqlllq:bpp00700070p0070p00700070	I
    //   423: ldc 2
    //   425: ldc_w 518
    //   428: bipush 90
    //   430: sipush 174
    //   433: iconst_2
    //   434: invokestatic 86	xxxxxx/uxxxxx:bbbb0062b0062b0062b0062	(Ljava/lang/String;CCC)Ljava/lang/String;
    //   437: iconst_0
    //   438: anewarray 62	java/lang/Class
    //   441: invokevirtual 66	java/lang/Class:getMethod	(Ljava/lang/String;[Ljava/lang/Class;)Ljava/lang/reflect/Method;
    //   444: astore 23
    //   446: iconst_0
    //   447: anewarray 68	java/lang/Object
    //   450: astore 24
    //   452: aload 23
    //   454: aconst_null
    //   455: aload 24
    //   457: invokevirtual 74	java/lang/reflect/Method:invoke	(Ljava/lang/Object;[Ljava/lang/Object;)Ljava/lang/Object;
    //   460: astore 26
    //   462: aload 26
    //   464: checkcast 76	java/lang/Integer
    //   467: invokevirtual 80	java/lang/Integer:intValue	()I
    //   470: putstatic 88	uuuuuu/lqlllq:b0070007000700070p0070p00700070	I
    //   473: aload_0
    //   474: aload_1
    //   475: invokevirtual 524	com/db/pwcc/dbmobile/model/error/DbError:getDbCode	()Lcom/db/pwcc/dbmobile/model/error/DbErrorCode;
    //   478: invokevirtual 528	uuuuuu/lqlllq:bo006Fo006F006F006Fo006F006F006F	(Lcom/db/pwcc/dbmobile/model/error/DbErrorCode;)V
    //   481: iconst_4
    //   482: istore 21
    //   484: iload 21
    //   486: iconst_0
    //   487: idiv
    //   488: istore 21
    //   490: goto -6 -> 484
    //   493: astore 9
    //   495: aload 9
    //   497: invokevirtual 102	java/lang/reflect/InvocationTargetException:getCause	()Ljava/lang/Throwable;
    //   500: athrow
    //   501: astore 22
    //   503: bipush 67
    //   505: putstatic 50	uuuuuu/lqlllq:bpp00700070p0070p00700070	I
    //   508: return
    //   509: astore 14
    //   511: aload 14
    //   513: invokevirtual 102	java/lang/reflect/InvocationTargetException:getCause	()Ljava/lang/Throwable;
    //   516: athrow
    //   517: astore 19
    //   519: aload 19
    //   521: invokevirtual 102	java/lang/reflect/InvocationTargetException:getCause	()Ljava/lang/Throwable;
    //   524: athrow
    //   525: aload_1
    //   526: iconst_0
    //   527: invokestatic 534	uuuuuu/ooooso:b0069iii006900690069iii	(Lcom/db/pwcc/dbmobile/model/error/DbError;Z)Lcom/db/pwcc/dbmobile/multi_bank_aggregator/model/MbaErrorCode;
    //   530: astore 11
    //   532: aload_0
    //   533: getfield 198	uuuuuu/lqlllq:bnnnnn006E006E006En	Luuuuuu/ttssst$tsssst;
    //   536: checkcast 200	uuuuuu/lllqql$lqlqql
    //   539: aload 11
    //   541: invokeinterface 537 2 0
    //   546: return
    //   547: astore 29
    //   549: aload 29
    //   551: invokevirtual 102	java/lang/reflect/InvocationTargetException:getCause	()Ljava/lang/Throwable;
    //   554: athrow
    //   555: astore 34
    //   557: aload 34
    //   559: invokevirtual 102	java/lang/reflect/InvocationTargetException:getCause	()Ljava/lang/Throwable;
    //   562: athrow
    //   563: astore 25
    //   565: aload 25
    //   567: invokevirtual 102	java/lang/reflect/InvocationTargetException:getCause	()Ljava/lang/Throwable;
    //   570: athrow
    // Local variable table:
    //   start	length	slot	name	signature
    //   0	571	0	this	lqlllq
    //   0	571	1	paramDbError	com.db.pwcc.dbmobile.model.error.DbError
    //   4	47	2	bool	boolean
    //   8	8	3	i	int
    //   193	94	4	str1	String
    //   205	32	5	str2	String
    //   211	28	6	arrayOfClass	Class[]
    //   243	34	7	localMethod1	java.lang.reflect.Method
    //   249	31	8	arrayOfObject1	Object[]
    //   493	3	9	localInvocationTargetException1	java.lang.reflect.InvocationTargetException
    //   284	5	10	localObject1	Object
    //   530	10	11	localMbaErrorCode	com.db.pwcc.dbmobile.multi_bank_aggregator.model.MbaErrorCode
    //   327	9	12	localMethod2	java.lang.reflect.Method
    //   333	6	13	arrayOfObject2	Object[]
    //   509	3	14	localInvocationTargetException2	java.lang.reflect.InvocationTargetException
    //   343	3	15	localObject2	Object
    //   357	51	16	j	int
    //   379	9	17	localMethod3	java.lang.reflect.Method
    //   385	6	18	arrayOfObject3	Object[]
    //   517	3	19	localInvocationTargetException3	java.lang.reflect.InvocationTargetException
    //   395	5	20	localObject3	Object
    //   482	7	21	k	int
    //   501	1	22	localException	Exception
    //   444	9	23	localMethod4	java.lang.reflect.Method
    //   450	6	24	arrayOfObject4	Object[]
    //   563	3	25	localInvocationTargetException4	java.lang.reflect.InvocationTargetException
    //   460	3	26	localObject4	Object
    //   75	9	27	localMethod5	java.lang.reflect.Method
    //   81	6	28	arrayOfObject5	Object[]
    //   547	3	29	localInvocationTargetException5	java.lang.reflect.InvocationTargetException
    //   91	3	30	localObject5	Object
    //   105	52	31	m	int
    //   128	9	32	localMethod6	java.lang.reflect.Method
    //   134	6	33	arrayOfObject6	Object[]
    //   555	3	34	localInvocationTargetException6	java.lang.reflect.InvocationTargetException
    //   144	5	35	localObject6	Object
    // Exception table:
    //   from	to	target	type
    //   276	286	493	java/lang/reflect/InvocationTargetException
    //   484	490	501	java/lang/Exception
    //   335	345	509	java/lang/reflect/InvocationTargetException
    //   387	397	517	java/lang/reflect/InvocationTargetException
    //   83	93	547	java/lang/reflect/InvocationTargetException
    //   136	146	555	java/lang/reflect/InvocationTargetException
    //   452	462	563	java/lang/reflect/InvocationTargetException
  }
  
  /* Error */
  public void bo006F006F006Foo006F006Foo(int paramInt)
  {
    // Byte code:
    //   0: getstatic 425	com/db/pwcc/dbmobile/financial_overview/R$id:menu_item_new_transaction	I
    //   3: istore_2
    //   4: getstatic 50	uuuuuu/lqlllq:bpp00700070p0070p00700070	I
    //   7: getstatic 52	uuuuuu/lqlllq:b0070p00700070p0070p00700070	I
    //   10: iadd
    //   11: getstatic 50	uuuuuu/lqlllq:bpp00700070p0070p00700070	I
    //   14: imul
    //   15: getstatic 90	uuuuuu/lqlllq:bp007000700070p0070p00700070	I
    //   18: irem
    //   19: getstatic 88	uuuuuu/lqlllq:b0070007000700070p0070p00700070	I
    //   22: if_icmpeq +220 -> 242
    //   25: ldc 2
    //   27: ldc_w 540
    //   30: sipush 193
    //   33: bipush 40
    //   35: iconst_3
    //   36: invokestatic 86	xxxxxx/uxxxxx:bbbb0062b0062b0062b0062	(Ljava/lang/String;CCC)Ljava/lang/String;
    //   39: iconst_0
    //   40: anewarray 62	java/lang/Class
    //   43: invokevirtual 66	java/lang/Class:getMethod	(Ljava/lang/String;[Ljava/lang/Class;)Ljava/lang/reflect/Method;
    //   46: astore 61
    //   48: iconst_0
    //   49: anewarray 68	java/lang/Object
    //   52: astore 62
    //   54: aload 61
    //   56: aconst_null
    //   57: aload 62
    //   59: invokevirtual 74	java/lang/reflect/Method:invoke	(Ljava/lang/Object;[Ljava/lang/Object;)Ljava/lang/Object;
    //   62: astore 64
    //   64: aload 64
    //   66: checkcast 76	java/lang/Integer
    //   69: invokevirtual 80	java/lang/Integer:intValue	()I
    //   72: getstatic 52	uuuuuu/lqlllq:b0070p00700070p0070p00700070	I
    //   75: iadd
    //   76: istore 65
    //   78: ldc 2
    //   80: ldc_w 257
    //   83: sipush 249
    //   86: iconst_0
    //   87: invokestatic 60	xxxxxx/uxxxxx:bb00620062bb0062b0062b0062	(Ljava/lang/String;CC)Ljava/lang/String;
    //   90: iconst_0
    //   91: anewarray 62	java/lang/Class
    //   94: invokevirtual 66	java/lang/Class:getMethod	(Ljava/lang/String;[Ljava/lang/Class;)Ljava/lang/reflect/Method;
    //   97: astore 66
    //   99: iconst_0
    //   100: anewarray 68	java/lang/Object
    //   103: astore 67
    //   105: aload 66
    //   107: aconst_null
    //   108: aload 67
    //   110: invokevirtual 74	java/lang/reflect/Method:invoke	(Ljava/lang/Object;[Ljava/lang/Object;)Ljava/lang/Object;
    //   113: astore 69
    //   115: iload 65
    //   117: aload 69
    //   119: checkcast 76	java/lang/Integer
    //   122: invokevirtual 80	java/lang/Integer:intValue	()I
    //   125: imul
    //   126: getstatic 90	uuuuuu/lqlllq:bp007000700070p0070p00700070	I
    //   129: irem
    //   130: getstatic 88	uuuuuu/lqlllq:b0070007000700070p0070p00700070	I
    //   133: if_icmpeq +56 -> 189
    //   136: ldc 2
    //   138: ldc_w 542
    //   141: sipush 241
    //   144: iconst_3
    //   145: invokestatic 60	xxxxxx/uxxxxx:bb00620062bb0062b0062b0062	(Ljava/lang/String;CC)Ljava/lang/String;
    //   148: iconst_0
    //   149: anewarray 62	java/lang/Class
    //   152: invokevirtual 66	java/lang/Class:getMethod	(Ljava/lang/String;[Ljava/lang/Class;)Ljava/lang/reflect/Method;
    //   155: astore 74
    //   157: iconst_0
    //   158: anewarray 68	java/lang/Object
    //   161: astore 75
    //   163: aload 74
    //   165: aconst_null
    //   166: aload 75
    //   168: invokevirtual 74	java/lang/reflect/Method:invoke	(Ljava/lang/Object;[Ljava/lang/Object;)Ljava/lang/Object;
    //   171: astore 77
    //   173: aload 77
    //   175: checkcast 76	java/lang/Integer
    //   178: invokevirtual 80	java/lang/Integer:intValue	()I
    //   181: putstatic 50	uuuuuu/lqlllq:bpp00700070p0070p00700070	I
    //   184: bipush 53
    //   186: putstatic 88	uuuuuu/lqlllq:b0070007000700070p0070p00700070	I
    //   189: ldc 2
    //   191: ldc_w 544
    //   194: sipush 160
    //   197: iconst_1
    //   198: invokestatic 60	xxxxxx/uxxxxx:bb00620062bb0062b0062b0062	(Ljava/lang/String;CC)Ljava/lang/String;
    //   201: iconst_0
    //   202: anewarray 62	java/lang/Class
    //   205: invokevirtual 66	java/lang/Class:getMethod	(Ljava/lang/String;[Ljava/lang/Class;)Ljava/lang/reflect/Method;
    //   208: astore 70
    //   210: iconst_0
    //   211: anewarray 68	java/lang/Object
    //   214: astore 71
    //   216: aload 70
    //   218: aconst_null
    //   219: aload 71
    //   221: invokevirtual 74	java/lang/reflect/Method:invoke	(Ljava/lang/Object;[Ljava/lang/Object;)Ljava/lang/Object;
    //   224: astore 73
    //   226: aload 73
    //   228: checkcast 76	java/lang/Integer
    //   231: invokevirtual 80	java/lang/Integer:intValue	()I
    //   234: putstatic 50	uuuuuu/lqlllq:bpp00700070p0070p00700070	I
    //   237: bipush 51
    //   239: putstatic 88	uuuuuu/lqlllq:b0070007000700070p0070p00700070	I
    //   242: getstatic 50	uuuuuu/lqlllq:bpp00700070p0070p00700070	I
    //   245: getstatic 52	uuuuuu/lqlllq:b0070p00700070p0070p00700070	I
    //   248: iadd
    //   249: getstatic 50	uuuuuu/lqlllq:bpp00700070p0070p00700070	I
    //   252: imul
    //   253: istore_3
    //   254: ldc 2
    //   256: ldc_w 546
    //   259: sipush 191
    //   262: iconst_1
    //   263: invokestatic 60	xxxxxx/uxxxxx:bb00620062bb0062b0062b0062	(Ljava/lang/String;CC)Ljava/lang/String;
    //   266: iconst_0
    //   267: anewarray 62	java/lang/Class
    //   270: invokevirtual 66	java/lang/Class:getMethod	(Ljava/lang/String;[Ljava/lang/Class;)Ljava/lang/reflect/Method;
    //   273: astore 4
    //   275: iconst_0
    //   276: anewarray 68	java/lang/Object
    //   279: astore 5
    //   281: aload 4
    //   283: aconst_null
    //   284: aload 5
    //   286: invokevirtual 74	java/lang/reflect/Method:invoke	(Ljava/lang/Object;[Ljava/lang/Object;)Ljava/lang/Object;
    //   289: astore 7
    //   291: iload_3
    //   292: aload 7
    //   294: checkcast 76	java/lang/Integer
    //   297: invokevirtual 80	java/lang/Integer:intValue	()I
    //   300: irem
    //   301: getstatic 88	uuuuuu/lqlllq:b0070007000700070p0070p00700070	I
    //   304: if_icmpeq +13 -> 317
    //   307: bipush 73
    //   309: putstatic 50	uuuuuu/lqlllq:bpp00700070p0070p00700070	I
    //   312: bipush 26
    //   314: putstatic 88	uuuuuu/lqlllq:b0070007000700070p0070p00700070	I
    //   317: iload_2
    //   318: iload_1
    //   319: if_icmpne +606 -> 925
    //   322: ldc 2
    //   324: ldc_w 548
    //   327: bipush 34
    //   329: sipush 229
    //   332: iconst_1
    //   333: invokestatic 86	xxxxxx/uxxxxx:bbbb0062b0062b0062b0062	(Ljava/lang/String;CCC)Ljava/lang/String;
    //   336: iconst_0
    //   337: anewarray 62	java/lang/Class
    //   340: invokevirtual 551	java/lang/Class:getDeclaredMethod	(Ljava/lang/String;[Ljava/lang/Class;)Ljava/lang/reflect/Method;
    //   343: astore 53
    //   345: iconst_0
    //   346: anewarray 68	java/lang/Object
    //   349: astore 54
    //   351: aload 53
    //   353: aload_0
    //   354: aload 54
    //   356: invokevirtual 74	java/lang/reflect/Method:invoke	(Ljava/lang/Object;[Ljava/lang/Object;)Ljava/lang/Object;
    //   359: astore 56
    //   361: aload 56
    //   363: checkcast 553	java/lang/Boolean
    //   366: invokevirtual 556	java/lang/Boolean:booleanValue	()Z
    //   369: ifne +556 -> 925
    //   372: ldc 2
    //   374: ldc_w 558
    //   377: sipush 136
    //   380: sipush 181
    //   383: iconst_0
    //   384: invokestatic 86	xxxxxx/uxxxxx:bbbb0062b0062b0062b0062	(Ljava/lang/String;CCC)Ljava/lang/String;
    //   387: iconst_0
    //   388: anewarray 62	java/lang/Class
    //   391: invokevirtual 551	java/lang/Class:getDeclaredMethod	(Ljava/lang/String;[Ljava/lang/Class;)Ljava/lang/reflect/Method;
    //   394: astore 57
    //   396: iconst_0
    //   397: anewarray 68	java/lang/Object
    //   400: astore 58
    //   402: aload 57
    //   404: aload_0
    //   405: aload 58
    //   407: invokevirtual 74	java/lang/reflect/Method:invoke	(Ljava/lang/Object;[Ljava/lang/Object;)Ljava/lang/Object;
    //   410: pop
    //   411: getstatic 564	uuuuuu/vvrvrv:bx007800780078xxxxx	Luuuuuu/vvrvrv;
    //   414: invokestatic 570	uuuuuu/rrvvrv:b0071q0071qq0071q0071q0071	(Luuuuuu/vvrvrv;)V
    //   417: return
    //   418: getstatic 431	com/db/pwcc/dbmobile/financial_overview/R$id:menu_item_new_standing_order	I
    //   421: iload_1
    //   422: if_icmpne +403 -> 825
    //   425: ldc 2
    //   427: ldc_w 572
    //   430: sipush 165
    //   433: iconst_3
    //   434: invokestatic 60	xxxxxx/uxxxxx:bb00620062bb0062b0062b0062	(Ljava/lang/String;CC)Ljava/lang/String;
    //   437: iconst_0
    //   438: anewarray 62	java/lang/Class
    //   441: invokevirtual 551	java/lang/Class:getDeclaredMethod	(Ljava/lang/String;[Ljava/lang/Class;)Ljava/lang/reflect/Method;
    //   444: astore 45
    //   446: iconst_0
    //   447: anewarray 68	java/lang/Object
    //   450: astore 46
    //   452: aload 45
    //   454: aload_0
    //   455: aload 46
    //   457: invokevirtual 74	java/lang/reflect/Method:invoke	(Ljava/lang/Object;[Ljava/lang/Object;)Ljava/lang/Object;
    //   460: astore 48
    //   462: aload 48
    //   464: checkcast 553	java/lang/Boolean
    //   467: invokevirtual 556	java/lang/Boolean:booleanValue	()Z
    //   470: ifne +355 -> 825
    //   473: ldc 2
    //   475: ldc_w 574
    //   478: bipush 119
    //   480: iconst_1
    //   481: invokestatic 60	xxxxxx/uxxxxx:bb00620062bb0062b0062b0062	(Ljava/lang/String;CC)Ljava/lang/String;
    //   484: iconst_0
    //   485: anewarray 62	java/lang/Class
    //   488: invokevirtual 551	java/lang/Class:getDeclaredMethod	(Ljava/lang/String;[Ljava/lang/Class;)Ljava/lang/reflect/Method;
    //   491: astore 49
    //   493: iconst_0
    //   494: anewarray 68	java/lang/Object
    //   497: astore 50
    //   499: aload 49
    //   501: aload_0
    //   502: aload 50
    //   504: invokevirtual 74	java/lang/reflect/Method:invoke	(Ljava/lang/Object;[Ljava/lang/Object;)Ljava/lang/Object;
    //   507: pop
    //   508: getstatic 577	uuuuuu/vvrvrv:b00780078xxxxxxx	Luuuuuu/vvrvrv;
    //   511: invokestatic 570	uuuuuu/rrvvrv:b0071q0071qq0071q0071q0071	(Luuuuuu/vvrvrv;)V
    //   514: return
    //   515: astore 47
    //   517: aload 47
    //   519: invokevirtual 102	java/lang/reflect/InvocationTargetException:getCause	()Ljava/lang/Throwable;
    //   522: athrow
    //   523: astore 6
    //   525: aload 6
    //   527: invokevirtual 102	java/lang/reflect/InvocationTargetException:getCause	()Ljava/lang/Throwable;
    //   530: athrow
    //   531: getstatic 418	com/db/pwcc/dbmobile/financial_overview/R$id:menu_item_new_transfer_sepa_flow	I
    //   534: iload_1
    //   535: if_icmpne -118 -> 417
    //   538: ldc 2
    //   540: ldc_w 579
    //   543: bipush 122
    //   545: iconst_3
    //   546: invokestatic 60	xxxxxx/uxxxxx:bb00620062bb0062b0062b0062	(Ljava/lang/String;CC)Ljava/lang/String;
    //   549: iconst_0
    //   550: anewarray 62	java/lang/Class
    //   553: invokevirtual 551	java/lang/Class:getDeclaredMethod	(Ljava/lang/String;[Ljava/lang/Class;)Ljava/lang/reflect/Method;
    //   556: astore 24
    //   558: iconst_0
    //   559: anewarray 68	java/lang/Object
    //   562: astore 25
    //   564: aload 24
    //   566: aload_0
    //   567: aload 25
    //   569: invokevirtual 74	java/lang/reflect/Method:invoke	(Ljava/lang/Object;[Ljava/lang/Object;)Ljava/lang/Object;
    //   572: astore 27
    //   574: aload 27
    //   576: checkcast 553	java/lang/Boolean
    //   579: invokevirtual 556	java/lang/Boolean:booleanValue	()Z
    //   582: ifne -165 -> 417
    //   585: getstatic 98	uuuuuu/lqlllq:bpp007000700070pp00700070	Ljava/lang/String;
    //   588: astore 28
    //   590: ldc_w 581
    //   593: sipush 240
    //   596: iconst_4
    //   597: invokestatic 60	xxxxxx/uxxxxx:bb00620062bb0062b0062b0062	(Ljava/lang/String;CC)Ljava/lang/String;
    //   600: astore 29
    //   602: iconst_3
    //   603: anewarray 62	java/lang/Class
    //   606: astore 30
    //   608: aload 30
    //   610: iconst_0
    //   611: ldc -87
    //   613: aastore
    //   614: aload 30
    //   616: iconst_1
    //   617: getstatic 496	java/lang/Character:TYPE	Ljava/lang/Class;
    //   620: aastore
    //   621: aload 30
    //   623: iconst_2
    //   624: getstatic 496	java/lang/Character:TYPE	Ljava/lang/Class;
    //   627: aastore
    //   628: ldc_w 498
    //   631: aload 29
    //   633: aload 30
    //   635: invokevirtual 66	java/lang/Class:getMethod	(Ljava/lang/String;[Ljava/lang/Class;)Ljava/lang/reflect/Method;
    //   638: astore 31
    //   640: iconst_3
    //   641: anewarray 68	java/lang/Object
    //   644: astore 32
    //   646: aload 32
    //   648: iconst_0
    //   649: ldc_w 583
    //   652: aastore
    //   653: aload 32
    //   655: iconst_1
    //   656: sipush 140
    //   659: invokestatic 504	java/lang/Character:valueOf	(C)Ljava/lang/Character;
    //   662: aastore
    //   663: aload 32
    //   665: iconst_2
    //   666: iconst_1
    //   667: invokestatic 504	java/lang/Character:valueOf	(C)Ljava/lang/Character;
    //   670: aastore
    //   671: aload 31
    //   673: aconst_null
    //   674: aload 32
    //   676: invokevirtual 74	java/lang/reflect/Method:invoke	(Ljava/lang/Object;[Ljava/lang/Object;)Ljava/lang/Object;
    //   679: astore 34
    //   681: aload 34
    //   683: checkcast 169	java/lang/String
    //   686: astore 35
    //   688: getstatic 50	uuuuuu/lqlllq:bpp00700070p0070p00700070	I
    //   691: getstatic 52	uuuuuu/lqlllq:b0070p00700070p0070p00700070	I
    //   694: iadd
    //   695: getstatic 50	uuuuuu/lqlllq:bpp00700070p0070p00700070	I
    //   698: imul
    //   699: getstatic 90	uuuuuu/lqlllq:bp007000700070p0070p00700070	I
    //   702: irem
    //   703: istore 36
    //   705: ldc 2
    //   707: ldc_w 585
    //   710: bipush 73
    //   712: sipush 165
    //   715: iconst_3
    //   716: invokestatic 86	xxxxxx/uxxxxx:bbbb0062b0062b0062b0062	(Ljava/lang/String;CCC)Ljava/lang/String;
    //   719: iconst_0
    //   720: anewarray 62	java/lang/Class
    //   723: invokevirtual 66	java/lang/Class:getMethod	(Ljava/lang/String;[Ljava/lang/Class;)Ljava/lang/reflect/Method;
    //   726: astore 37
    //   728: iconst_0
    //   729: anewarray 68	java/lang/Object
    //   732: astore 38
    //   734: aload 37
    //   736: aconst_null
    //   737: aload 38
    //   739: invokevirtual 74	java/lang/reflect/Method:invoke	(Ljava/lang/Object;[Ljava/lang/Object;)Ljava/lang/Object;
    //   742: astore 40
    //   744: iload 36
    //   746: aload 40
    //   748: checkcast 76	java/lang/Integer
    //   751: invokevirtual 80	java/lang/Integer:intValue	()I
    //   754: if_icmpeq +55 -> 809
    //   757: bipush 36
    //   759: putstatic 50	uuuuuu/lqlllq:bpp00700070p0070p00700070	I
    //   762: ldc 2
    //   764: ldc_w 587
    //   767: bipush 118
    //   769: iconst_0
    //   770: invokestatic 60	xxxxxx/uxxxxx:bb00620062bb0062b0062b0062	(Ljava/lang/String;CC)Ljava/lang/String;
    //   773: iconst_0
    //   774: anewarray 62	java/lang/Class
    //   777: invokevirtual 66	java/lang/Class:getMethod	(Ljava/lang/String;[Ljava/lang/Class;)Ljava/lang/reflect/Method;
    //   780: astore 41
    //   782: iconst_0
    //   783: anewarray 68	java/lang/Object
    //   786: astore 42
    //   788: aload 41
    //   790: aconst_null
    //   791: aload 42
    //   793: invokevirtual 74	java/lang/reflect/Method:invoke	(Ljava/lang/Object;[Ljava/lang/Object;)Ljava/lang/Object;
    //   796: astore 44
    //   798: aload 44
    //   800: checkcast 76	java/lang/Integer
    //   803: invokevirtual 80	java/lang/Integer:intValue	()I
    //   806: putstatic 88	uuuuuu/lqlllq:b0070007000700070p0070p00700070	I
    //   809: aload 28
    //   811: aload 35
    //   813: invokestatic 591	uuuuuu/rvvvrv:bqqqq00710071q0071q0071	(Ljava/lang/String;Ljava/lang/String;)V
    //   816: return
    //   817: astore 55
    //   819: aload 55
    //   821: invokevirtual 102	java/lang/reflect/InvocationTargetException:getCause	()Ljava/lang/Throwable;
    //   824: athrow
    //   825: getstatic 436	com/db/pwcc/dbmobile/financial_overview/R$id:menu_item_photo_transfer	I
    //   828: iload_1
    //   829: if_icmpne -298 -> 531
    //   832: ldc 2
    //   834: ldc_w 593
    //   837: sipush 209
    //   840: sipush 164
    //   843: iconst_2
    //   844: invokestatic 86	xxxxxx/uxxxxx:bbbb0062b0062b0062b0062	(Ljava/lang/String;CCC)Ljava/lang/String;
    //   847: iconst_0
    //   848: anewarray 62	java/lang/Class
    //   851: invokevirtual 551	java/lang/Class:getDeclaredMethod	(Ljava/lang/String;[Ljava/lang/Class;)Ljava/lang/reflect/Method;
    //   854: astore 16
    //   856: iconst_0
    //   857: anewarray 68	java/lang/Object
    //   860: astore 17
    //   862: aload 16
    //   864: aload_0
    //   865: aload 17
    //   867: invokevirtual 74	java/lang/reflect/Method:invoke	(Ljava/lang/Object;[Ljava/lang/Object;)Ljava/lang/Object;
    //   870: astore 19
    //   872: aload 19
    //   874: checkcast 553	java/lang/Boolean
    //   877: invokevirtual 556	java/lang/Boolean:booleanValue	()Z
    //   880: ifne -349 -> 531
    //   883: ldc 2
    //   885: ldc_w 595
    //   888: bipush 61
    //   890: iconst_2
    //   891: invokestatic 60	xxxxxx/uxxxxx:bb00620062bb0062b0062b0062	(Ljava/lang/String;CC)Ljava/lang/String;
    //   894: iconst_0
    //   895: anewarray 62	java/lang/Class
    //   898: invokevirtual 551	java/lang/Class:getDeclaredMethod	(Ljava/lang/String;[Ljava/lang/Class;)Ljava/lang/reflect/Method;
    //   901: astore 20
    //   903: iconst_0
    //   904: anewarray 68	java/lang/Object
    //   907: astore 21
    //   909: aload 20
    //   911: aload_0
    //   912: aload 21
    //   914: invokevirtual 74	java/lang/reflect/Method:invoke	(Ljava/lang/Object;[Ljava/lang/Object;)Ljava/lang/Object;
    //   917: pop
    //   918: getstatic 598	uuuuuu/vvrvrv:b0068hhh0068h006800680068	Luuuuuu/vvrvrv;
    //   921: invokestatic 570	uuuuuu/rrvvrv:b0071q0071qq0071q0071q0071	(Luuuuuu/vvrvrv;)V
    //   924: return
    //   925: getstatic 428	com/db/pwcc/dbmobile/financial_overview/R$id:menu_item_transfer_subaccount	I
    //   928: iload_1
    //   929: if_icmpne -511 -> 418
    //   932: ldc 2
    //   934: ldc_w 600
    //   937: sipush 239
    //   940: iconst_5
    //   941: invokestatic 60	xxxxxx/uxxxxx:bb00620062bb0062b0062b0062	(Ljava/lang/String;CC)Ljava/lang/String;
    //   944: iconst_0
    //   945: anewarray 62	java/lang/Class
    //   948: invokevirtual 551	java/lang/Class:getDeclaredMethod	(Ljava/lang/String;[Ljava/lang/Class;)Ljava/lang/reflect/Method;
    //   951: astore 8
    //   953: iconst_0
    //   954: anewarray 68	java/lang/Object
    //   957: astore 9
    //   959: aload 8
    //   961: aload_0
    //   962: aload 9
    //   964: invokevirtual 74	java/lang/reflect/Method:invoke	(Ljava/lang/Object;[Ljava/lang/Object;)Ljava/lang/Object;
    //   967: astore 11
    //   969: aload 11
    //   971: checkcast 553	java/lang/Boolean
    //   974: invokevirtual 556	java/lang/Boolean:booleanValue	()Z
    //   977: ifne -559 -> 418
    //   980: ldc 2
    //   982: ldc_w 602
    //   985: bipush 114
    //   987: iconst_5
    //   988: invokestatic 60	xxxxxx/uxxxxx:bb00620062bb0062b0062b0062	(Ljava/lang/String;CC)Ljava/lang/String;
    //   991: iconst_0
    //   992: anewarray 62	java/lang/Class
    //   995: invokevirtual 551	java/lang/Class:getDeclaredMethod	(Ljava/lang/String;[Ljava/lang/Class;)Ljava/lang/reflect/Method;
    //   998: astore 12
    //   1000: iconst_0
    //   1001: anewarray 68	java/lang/Object
    //   1004: astore 13
    //   1006: aload 12
    //   1008: aload_0
    //   1009: aload 13
    //   1011: invokevirtual 74	java/lang/reflect/Method:invoke	(Ljava/lang/Object;[Ljava/lang/Object;)Ljava/lang/Object;
    //   1014: pop
    //   1015: getstatic 605	uuuuuu/vvrvrv:b0078x00780078xxxxx	Luuuuuu/vvrvrv;
    //   1018: invokestatic 570	uuuuuu/rrvvrv:b0071q0071qq0071q0071q0071	(Luuuuuu/vvrvrv;)V
    //   1021: return
    //   1022: astore 10
    //   1024: aload 10
    //   1026: invokevirtual 102	java/lang/reflect/InvocationTargetException:getCause	()Ljava/lang/Throwable;
    //   1029: athrow
    //   1030: astore 63
    //   1032: aload 63
    //   1034: invokevirtual 102	java/lang/reflect/InvocationTargetException:getCause	()Ljava/lang/Throwable;
    //   1037: athrow
    //   1038: astore 68
    //   1040: aload 68
    //   1042: invokevirtual 102	java/lang/reflect/InvocationTargetException:getCause	()Ljava/lang/Throwable;
    //   1045: athrow
    //   1046: astore 18
    //   1048: aload 18
    //   1050: invokevirtual 102	java/lang/reflect/InvocationTargetException:getCause	()Ljava/lang/Throwable;
    //   1053: athrow
    //   1054: astore 22
    //   1056: aload 22
    //   1058: invokevirtual 102	java/lang/reflect/InvocationTargetException:getCause	()Ljava/lang/Throwable;
    //   1061: athrow
    //   1062: astore 51
    //   1064: aload 51
    //   1066: invokevirtual 102	java/lang/reflect/InvocationTargetException:getCause	()Ljava/lang/Throwable;
    //   1069: athrow
    //   1070: astore 26
    //   1072: aload 26
    //   1074: invokevirtual 102	java/lang/reflect/InvocationTargetException:getCause	()Ljava/lang/Throwable;
    //   1077: athrow
    //   1078: astore 43
    //   1080: aload 43
    //   1082: invokevirtual 102	java/lang/reflect/InvocationTargetException:getCause	()Ljava/lang/Throwable;
    //   1085: athrow
    //   1086: astore 14
    //   1088: aload 14
    //   1090: invokevirtual 102	java/lang/reflect/InvocationTargetException:getCause	()Ljava/lang/Throwable;
    //   1093: athrow
    //   1094: astore 59
    //   1096: aload 59
    //   1098: invokevirtual 102	java/lang/reflect/InvocationTargetException:getCause	()Ljava/lang/Throwable;
    //   1101: athrow
    //   1102: astore 39
    //   1104: aload 39
    //   1106: invokevirtual 102	java/lang/reflect/InvocationTargetException:getCause	()Ljava/lang/Throwable;
    //   1109: athrow
    //   1110: astore 33
    //   1112: aload 33
    //   1114: invokevirtual 102	java/lang/reflect/InvocationTargetException:getCause	()Ljava/lang/Throwable;
    //   1117: athrow
    //   1118: astore 72
    //   1120: aload 72
    //   1122: invokevirtual 102	java/lang/reflect/InvocationTargetException:getCause	()Ljava/lang/Throwable;
    //   1125: athrow
    //   1126: astore 76
    //   1128: aload 76
    //   1130: invokevirtual 102	java/lang/reflect/InvocationTargetException:getCause	()Ljava/lang/Throwable;
    //   1133: athrow
    // Local variable table:
    //   start	length	slot	name	signature
    //   0	1134	0	this	lqlllq
    //   0	1134	1	paramInt	int
    //   3	317	2	i	int
    //   253	48	3	j	int
    //   273	9	4	localMethod1	java.lang.reflect.Method
    //   279	6	5	arrayOfObject1	Object[]
    //   523	3	6	localInvocationTargetException1	java.lang.reflect.InvocationTargetException
    //   289	4	7	localObject1	Object
    //   951	9	8	localMethod2	java.lang.reflect.Method
    //   957	6	9	arrayOfObject2	Object[]
    //   1022	3	10	localInvocationTargetException2	java.lang.reflect.InvocationTargetException
    //   967	3	11	localObject2	Object
    //   998	9	12	localMethod3	java.lang.reflect.Method
    //   1004	6	13	arrayOfObject3	Object[]
    //   1086	3	14	localInvocationTargetException3	java.lang.reflect.InvocationTargetException
    //   854	9	16	localMethod4	java.lang.reflect.Method
    //   860	6	17	arrayOfObject4	Object[]
    //   1046	3	18	localInvocationTargetException4	java.lang.reflect.InvocationTargetException
    //   870	3	19	localObject3	Object
    //   901	9	20	localMethod5	java.lang.reflect.Method
    //   907	6	21	arrayOfObject5	Object[]
    //   1054	3	22	localInvocationTargetException5	java.lang.reflect.InvocationTargetException
    //   556	9	24	localMethod6	java.lang.reflect.Method
    //   562	6	25	arrayOfObject6	Object[]
    //   1070	3	26	localInvocationTargetException6	java.lang.reflect.InvocationTargetException
    //   572	3	27	localObject4	Object
    //   588	222	28	str1	String
    //   600	32	29	str2	String
    //   606	28	30	arrayOfClass	Class[]
    //   638	34	31	localMethod7	java.lang.reflect.Method
    //   644	31	32	arrayOfObject7	Object[]
    //   1110	3	33	localInvocationTargetException7	java.lang.reflect.InvocationTargetException
    //   679	3	34	localObject5	Object
    //   686	126	35	str3	String
    //   703	52	36	k	int
    //   726	9	37	localMethod8	java.lang.reflect.Method
    //   732	6	38	arrayOfObject8	Object[]
    //   1102	3	39	localInvocationTargetException8	java.lang.reflect.InvocationTargetException
    //   742	5	40	localObject6	Object
    //   780	9	41	localMethod9	java.lang.reflect.Method
    //   786	6	42	arrayOfObject9	Object[]
    //   1078	3	43	localInvocationTargetException9	java.lang.reflect.InvocationTargetException
    //   796	3	44	localObject7	Object
    //   444	9	45	localMethod10	java.lang.reflect.Method
    //   450	6	46	arrayOfObject10	Object[]
    //   515	3	47	localInvocationTargetException10	java.lang.reflect.InvocationTargetException
    //   460	3	48	localObject8	Object
    //   491	9	49	localMethod11	java.lang.reflect.Method
    //   497	6	50	arrayOfObject11	Object[]
    //   1062	3	51	localInvocationTargetException11	java.lang.reflect.InvocationTargetException
    //   343	9	53	localMethod12	java.lang.reflect.Method
    //   349	6	54	arrayOfObject12	Object[]
    //   817	3	55	localInvocationTargetException12	java.lang.reflect.InvocationTargetException
    //   359	3	56	localObject9	Object
    //   394	9	57	localMethod13	java.lang.reflect.Method
    //   400	6	58	arrayOfObject13	Object[]
    //   1094	3	59	localInvocationTargetException13	java.lang.reflect.InvocationTargetException
    //   46	9	61	localMethod14	java.lang.reflect.Method
    //   52	6	62	arrayOfObject14	Object[]
    //   1030	3	63	localInvocationTargetException14	java.lang.reflect.InvocationTargetException
    //   62	3	64	localObject10	Object
    //   76	50	65	m	int
    //   97	9	66	localMethod15	java.lang.reflect.Method
    //   103	6	67	arrayOfObject15	Object[]
    //   1038	3	68	localInvocationTargetException15	java.lang.reflect.InvocationTargetException
    //   113	5	69	localObject11	Object
    //   208	9	70	localMethod16	java.lang.reflect.Method
    //   214	6	71	arrayOfObject16	Object[]
    //   1118	3	72	localInvocationTargetException16	java.lang.reflect.InvocationTargetException
    //   224	3	73	localObject12	Object
    //   155	9	74	localMethod17	java.lang.reflect.Method
    //   161	6	75	arrayOfObject17	Object[]
    //   1126	3	76	localInvocationTargetException17	java.lang.reflect.InvocationTargetException
    //   171	3	77	localObject13	Object
    // Exception table:
    //   from	to	target	type
    //   452	462	515	java/lang/reflect/InvocationTargetException
    //   281	291	523	java/lang/reflect/InvocationTargetException
    //   351	361	817	java/lang/reflect/InvocationTargetException
    //   959	969	1022	java/lang/reflect/InvocationTargetException
    //   54	64	1030	java/lang/reflect/InvocationTargetException
    //   105	115	1038	java/lang/reflect/InvocationTargetException
    //   862	872	1046	java/lang/reflect/InvocationTargetException
    //   909	918	1054	java/lang/reflect/InvocationTargetException
    //   499	508	1062	java/lang/reflect/InvocationTargetException
    //   564	574	1070	java/lang/reflect/InvocationTargetException
    //   788	798	1078	java/lang/reflect/InvocationTargetException
    //   1006	1015	1086	java/lang/reflect/InvocationTargetException
    //   402	411	1094	java/lang/reflect/InvocationTargetException
    //   734	744	1102	java/lang/reflect/InvocationTargetException
    //   671	681	1110	java/lang/reflect/InvocationTargetException
    //   216	226	1118	java/lang/reflect/InvocationTargetException
    //   163	173	1126	java/lang/reflect/InvocationTargetException
  }
  
  /* Error */
  public void bo006Fo006Foo006F006Foo(lllqql.lqlqql paramLqlqql, android.content.Context paramContext)
  {
    // Byte code:
    //   0: getstatic 50	uuuuuu/lqlllq:bpp00700070p0070p00700070	I
    //   3: istore_3
    //   4: iload_3
    //   5: iload_3
    //   6: getstatic 52	uuuuuu/lqlllq:b0070p00700070p0070p00700070	I
    //   9: iadd
    //   10: imul
    //   11: getstatic 90	uuuuuu/lqlllq:bp007000700070p0070p00700070	I
    //   14: irem
    //   15: tableswitch	default:+17->32, 0:+27->42
    //   32: bipush 74
    //   34: putstatic 50	uuuuuu/lqlllq:bpp00700070p0070p00700070	I
    //   37: bipush 69
    //   39: putstatic 88	uuuuuu/lqlllq:b0070007000700070p0070p00700070	I
    //   42: getstatic 50	uuuuuu/lqlllq:bpp00700070p0070p00700070	I
    //   45: istore 4
    //   47: iload 4
    //   49: iload 4
    //   51: getstatic 52	uuuuuu/lqlllq:b0070p00700070p0070p00700070	I
    //   54: iadd
    //   55: imul
    //   56: istore 5
    //   58: getstatic 90	uuuuuu/lqlllq:bp007000700070p0070p00700070	I
    //   61: istore 6
    //   63: getstatic 50	uuuuuu/lqlllq:bpp00700070p0070p00700070	I
    //   66: getstatic 52	uuuuuu/lqlllq:b0070p00700070p0070p00700070	I
    //   69: iadd
    //   70: getstatic 50	uuuuuu/lqlllq:bpp00700070p0070p00700070	I
    //   73: imul
    //   74: getstatic 90	uuuuuu/lqlllq:bp007000700070p0070p00700070	I
    //   77: irem
    //   78: istore 7
    //   80: ldc 2
    //   82: ldc_w 609
    //   85: sipush 135
    //   88: iconst_0
    //   89: invokestatic 60	xxxxxx/uxxxxx:bb00620062bb0062b0062b0062	(Ljava/lang/String;CC)Ljava/lang/String;
    //   92: iconst_0
    //   93: anewarray 62	java/lang/Class
    //   96: invokevirtual 66	java/lang/Class:getMethod	(Ljava/lang/String;[Ljava/lang/Class;)Ljava/lang/reflect/Method;
    //   99: astore 8
    //   101: iconst_0
    //   102: anewarray 68	java/lang/Object
    //   105: astore 9
    //   107: aload 8
    //   109: aconst_null
    //   110: aload 9
    //   112: invokevirtual 74	java/lang/reflect/Method:invoke	(Ljava/lang/Object;[Ljava/lang/Object;)Ljava/lang/Object;
    //   115: astore 11
    //   117: iload 7
    //   119: aload 11
    //   121: checkcast 76	java/lang/Integer
    //   124: invokevirtual 80	java/lang/Integer:intValue	()I
    //   127: if_icmpeq +97 -> 224
    //   130: ldc 2
    //   132: ldc_w 518
    //   135: bipush 43
    //   137: iconst_2
    //   138: invokestatic 60	xxxxxx/uxxxxx:bb00620062bb0062b0062b0062	(Ljava/lang/String;CC)Ljava/lang/String;
    //   141: iconst_0
    //   142: anewarray 62	java/lang/Class
    //   145: invokevirtual 66	java/lang/Class:getMethod	(Ljava/lang/String;[Ljava/lang/Class;)Ljava/lang/reflect/Method;
    //   148: astore 21
    //   150: iconst_0
    //   151: anewarray 68	java/lang/Object
    //   154: astore 22
    //   156: aload 21
    //   158: aconst_null
    //   159: aload 22
    //   161: invokevirtual 74	java/lang/reflect/Method:invoke	(Ljava/lang/Object;[Ljava/lang/Object;)Ljava/lang/Object;
    //   164: astore 24
    //   166: aload 24
    //   168: checkcast 76	java/lang/Integer
    //   171: invokevirtual 80	java/lang/Integer:intValue	()I
    //   174: putstatic 50	uuuuuu/lqlllq:bpp00700070p0070p00700070	I
    //   177: ldc 2
    //   179: ldc_w 611
    //   182: bipush 53
    //   184: iconst_5
    //   185: invokestatic 60	xxxxxx/uxxxxx:bb00620062bb0062b0062b0062	(Ljava/lang/String;CC)Ljava/lang/String;
    //   188: iconst_0
    //   189: anewarray 62	java/lang/Class
    //   192: invokevirtual 66	java/lang/Class:getMethod	(Ljava/lang/String;[Ljava/lang/Class;)Ljava/lang/reflect/Method;
    //   195: astore 25
    //   197: iconst_0
    //   198: anewarray 68	java/lang/Object
    //   201: astore 26
    //   203: aload 25
    //   205: aconst_null
    //   206: aload 26
    //   208: invokevirtual 74	java/lang/reflect/Method:invoke	(Ljava/lang/Object;[Ljava/lang/Object;)Ljava/lang/Object;
    //   211: astore 28
    //   213: aload 28
    //   215: checkcast 76	java/lang/Integer
    //   218: invokevirtual 80	java/lang/Integer:intValue	()I
    //   221: putstatic 88	uuuuuu/lqlllq:b0070007000700070p0070p00700070	I
    //   224: iload 5
    //   226: iload 6
    //   228: irem
    //   229: tableswitch	default:+19->248, 0:+71->300
    //   248: ldc 2
    //   250: ldc_w 613
    //   253: bipush 40
    //   255: iconst_3
    //   256: invokestatic 60	xxxxxx/uxxxxx:bb00620062bb0062b0062b0062	(Ljava/lang/String;CC)Ljava/lang/String;
    //   259: iconst_0
    //   260: anewarray 62	java/lang/Class
    //   263: invokevirtual 66	java/lang/Class:getMethod	(Ljava/lang/String;[Ljava/lang/Class;)Ljava/lang/reflect/Method;
    //   266: astore 17
    //   268: iconst_0
    //   269: anewarray 68	java/lang/Object
    //   272: astore 18
    //   274: aload 17
    //   276: aconst_null
    //   277: aload 18
    //   279: invokevirtual 74	java/lang/reflect/Method:invoke	(Ljava/lang/Object;[Ljava/lang/Object;)Ljava/lang/Object;
    //   282: astore 20
    //   284: aload 20
    //   286: checkcast 76	java/lang/Integer
    //   289: invokevirtual 80	java/lang/Integer:intValue	()I
    //   292: putstatic 50	uuuuuu/lqlllq:bpp00700070p0070p00700070	I
    //   295: bipush 26
    //   297: putstatic 88	uuuuuu/lqlllq:b0070007000700070p0070p00700070	I
    //   300: aload_0
    //   301: aload_1
    //   302: invokespecial 617	uuuuuu/qppppp:ba0061a0061a0061a0061aa	(Luuuuuu/ttssst$tsssst;)V
    //   305: getstatic 50	uuuuuu/lqlllq:bpp00700070p0070p00700070	I
    //   308: istore 12
    //   310: iload 12
    //   312: iload 12
    //   314: getstatic 52	uuuuuu/lqlllq:b0070p00700070p0070p00700070	I
    //   317: iadd
    //   318: imul
    //   319: getstatic 90	uuuuuu/lqlllq:bp007000700070p0070p00700070	I
    //   322: irem
    //   323: tableswitch	default:+17->340, 0:+69->392
    //   340: ldc 2
    //   342: ldc_w 619
    //   345: bipush 11
    //   347: iconst_1
    //   348: invokestatic 60	xxxxxx/uxxxxx:bb00620062bb0062b0062b0062	(Ljava/lang/String;CC)Ljava/lang/String;
    //   351: iconst_0
    //   352: anewarray 62	java/lang/Class
    //   355: invokevirtual 66	java/lang/Class:getMethod	(Ljava/lang/String;[Ljava/lang/Class;)Ljava/lang/reflect/Method;
    //   358: astore 13
    //   360: iconst_0
    //   361: anewarray 68	java/lang/Object
    //   364: astore 14
    //   366: aload 13
    //   368: aconst_null
    //   369: aload 14
    //   371: invokevirtual 74	java/lang/reflect/Method:invoke	(Ljava/lang/Object;[Ljava/lang/Object;)Ljava/lang/Object;
    //   374: astore 16
    //   376: aload 16
    //   378: checkcast 76	java/lang/Integer
    //   381: invokevirtual 80	java/lang/Integer:intValue	()I
    //   384: putstatic 50	uuuuuu/lqlllq:bpp00700070p0070p00700070	I
    //   387: bipush 45
    //   389: putstatic 88	uuuuuu/lqlllq:b0070007000700070p0070p00700070	I
    //   392: aload_2
    //   393: invokestatic 625	uuuuuu/heehhe:b006F006F006Foo006F006F006F006Fo	(Landroid/content/Context;)Luuuuuu/ehehhe;
    //   396: aload_0
    //   397: invokeinterface 630 2 0
    //   402: return
    //   403: astore 19
    //   405: aload 19
    //   407: invokevirtual 102	java/lang/reflect/InvocationTargetException:getCause	()Ljava/lang/Throwable;
    //   410: athrow
    //   411: astore 23
    //   413: aload 23
    //   415: invokevirtual 102	java/lang/reflect/InvocationTargetException:getCause	()Ljava/lang/Throwable;
    //   418: athrow
    //   419: astore 27
    //   421: aload 27
    //   423: invokevirtual 102	java/lang/reflect/InvocationTargetException:getCause	()Ljava/lang/Throwable;
    //   426: athrow
    //   427: astore 10
    //   429: aload 10
    //   431: invokevirtual 102	java/lang/reflect/InvocationTargetException:getCause	()Ljava/lang/Throwable;
    //   434: athrow
    //   435: astore 15
    //   437: aload 15
    //   439: invokevirtual 102	java/lang/reflect/InvocationTargetException:getCause	()Ljava/lang/Throwable;
    //   442: athrow
    // Local variable table:
    //   start	length	slot	name	signature
    //   0	443	0	this	lqlllq
    //   0	443	1	paramLqlqql	lllqql.lqlqql
    //   0	443	2	paramContext	android.content.Context
    //   3	8	3	i	int
    //   45	11	4	j	int
    //   56	173	5	k	int
    //   61	168	6	m	int
    //   78	50	7	n	int
    //   99	9	8	localMethod1	java.lang.reflect.Method
    //   105	6	9	arrayOfObject1	Object[]
    //   427	3	10	localInvocationTargetException1	java.lang.reflect.InvocationTargetException
    //   115	5	11	localObject1	Object
    //   308	11	12	i1	int
    //   358	9	13	localMethod2	java.lang.reflect.Method
    //   364	6	14	arrayOfObject2	Object[]
    //   435	3	15	localInvocationTargetException2	java.lang.reflect.InvocationTargetException
    //   374	3	16	localObject2	Object
    //   266	9	17	localMethod3	java.lang.reflect.Method
    //   272	6	18	arrayOfObject3	Object[]
    //   403	3	19	localInvocationTargetException3	java.lang.reflect.InvocationTargetException
    //   282	3	20	localObject3	Object
    //   148	9	21	localMethod4	java.lang.reflect.Method
    //   154	6	22	arrayOfObject4	Object[]
    //   411	3	23	localInvocationTargetException4	java.lang.reflect.InvocationTargetException
    //   164	3	24	localObject4	Object
    //   195	9	25	localMethod5	java.lang.reflect.Method
    //   201	6	26	arrayOfObject5	Object[]
    //   419	3	27	localInvocationTargetException5	java.lang.reflect.InvocationTargetException
    //   211	3	28	localObject5	Object
    // Exception table:
    //   from	to	target	type
    //   274	284	403	java/lang/reflect/InvocationTargetException
    //   156	166	411	java/lang/reflect/InvocationTargetException
    //   203	213	419	java/lang/reflect/InvocationTargetException
    //   107	117	427	java/lang/reflect/InvocationTargetException
    //   366	376	435	java/lang/reflect/InvocationTargetException
  }
  
  /* Error */
  public void bo006Foooo006Fooo()
  {
    // Byte code:
    //   0: aload_0
    //   1: getfield 633	uuuuuu/lqlllq:b0070p0070pp0070p00700070	Luuuuuu/pqqqqq;
    //   4: astore_1
    //   5: getstatic 50	uuuuuu/lqlllq:bpp00700070p0070p00700070	I
    //   8: istore_2
    //   9: ldc 2
    //   11: ldc_w 635
    //   14: sipush 229
    //   17: iconst_4
    //   18: invokestatic 60	xxxxxx/uxxxxx:bb00620062bb0062b0062b0062	(Ljava/lang/String;CC)Ljava/lang/String;
    //   21: iconst_0
    //   22: anewarray 62	java/lang/Class
    //   25: invokevirtual 66	java/lang/Class:getMethod	(Ljava/lang/String;[Ljava/lang/Class;)Ljava/lang/reflect/Method;
    //   28: astore_3
    //   29: iconst_0
    //   30: anewarray 68	java/lang/Object
    //   33: astore 4
    //   35: aload_3
    //   36: aconst_null
    //   37: aload 4
    //   39: invokevirtual 74	java/lang/reflect/Method:invoke	(Ljava/lang/Object;[Ljava/lang/Object;)Ljava/lang/Object;
    //   42: astore 6
    //   44: iload_2
    //   45: iload_2
    //   46: aload 6
    //   48: checkcast 76	java/lang/Integer
    //   51: invokevirtual 80	java/lang/Integer:intValue	()I
    //   54: iadd
    //   55: imul
    //   56: getstatic 90	uuuuuu/lqlllq:bp007000700070p0070p00700070	I
    //   59: irem
    //   60: tableswitch	default:+20->80, 0:+75->135
    //   80: bipush 21
    //   82: putstatic 50	uuuuuu/lqlllq:bpp00700070p0070p00700070	I
    //   85: ldc 2
    //   87: ldc_w 637
    //   90: sipush 194
    //   93: bipush 101
    //   95: iconst_3
    //   96: invokestatic 86	xxxxxx/uxxxxx:bbbb0062b0062b0062b0062	(Ljava/lang/String;CCC)Ljava/lang/String;
    //   99: iconst_0
    //   100: anewarray 62	java/lang/Class
    //   103: invokevirtual 66	java/lang/Class:getMethod	(Ljava/lang/String;[Ljava/lang/Class;)Ljava/lang/reflect/Method;
    //   106: astore 22
    //   108: iconst_0
    //   109: anewarray 68	java/lang/Object
    //   112: astore 23
    //   114: aload 22
    //   116: aconst_null
    //   117: aload 23
    //   119: invokevirtual 74	java/lang/reflect/Method:invoke	(Ljava/lang/Object;[Ljava/lang/Object;)Ljava/lang/Object;
    //   122: astore 25
    //   124: aload 25
    //   126: checkcast 76	java/lang/Integer
    //   129: invokevirtual 80	java/lang/Integer:intValue	()I
    //   132: putstatic 88	uuuuuu/lqlllq:b0070007000700070p0070p00700070	I
    //   135: getstatic 50	uuuuuu/lqlllq:bpp00700070p0070p00700070	I
    //   138: getstatic 52	uuuuuu/lqlllq:b0070p00700070p0070p00700070	I
    //   141: iadd
    //   142: getstatic 50	uuuuuu/lqlllq:bpp00700070p0070p00700070	I
    //   145: imul
    //   146: getstatic 90	uuuuuu/lqlllq:bp007000700070p0070p00700070	I
    //   149: irem
    //   150: getstatic 88	uuuuuu/lqlllq:b0070007000700070p0070p00700070	I
    //   153: if_icmpeq +55 -> 208
    //   156: ldc 2
    //   158: ldc_w 357
    //   161: bipush 27
    //   163: iconst_3
    //   164: invokestatic 60	xxxxxx/uxxxxx:bb00620062bb0062b0062b0062	(Ljava/lang/String;CC)Ljava/lang/String;
    //   167: iconst_0
    //   168: anewarray 62	java/lang/Class
    //   171: invokevirtual 66	java/lang/Class:getMethod	(Ljava/lang/String;[Ljava/lang/Class;)Ljava/lang/reflect/Method;
    //   174: astore 18
    //   176: iconst_0
    //   177: anewarray 68	java/lang/Object
    //   180: astore 19
    //   182: aload 18
    //   184: aconst_null
    //   185: aload 19
    //   187: invokevirtual 74	java/lang/reflect/Method:invoke	(Ljava/lang/Object;[Ljava/lang/Object;)Ljava/lang/Object;
    //   190: astore 21
    //   192: aload 21
    //   194: checkcast 76	java/lang/Integer
    //   197: invokevirtual 80	java/lang/Integer:intValue	()I
    //   200: putstatic 50	uuuuuu/lqlllq:bpp00700070p0070p00700070	I
    //   203: bipush 31
    //   205: putstatic 88	uuuuuu/lqlllq:b0070007000700070p0070p00700070	I
    //   208: aload_0
    //   209: getfield 233	uuuuuu/lqlllq:bp0070007000700070pp00700070	Ljava/lang/String;
    //   212: astore 7
    //   214: getstatic 50	uuuuuu/lqlllq:bpp00700070p0070p00700070	I
    //   217: istore 8
    //   219: iload 8
    //   221: iload 8
    //   223: getstatic 52	uuuuuu/lqlllq:b0070p00700070p0070p00700070	I
    //   226: iadd
    //   227: imul
    //   228: getstatic 90	uuuuuu/lqlllq:bp007000700070p0070p00700070	I
    //   231: irem
    //   232: tableswitch	default:+20->252, 0:+161->393
    //   252: ldc 2
    //   254: ldc_w 639
    //   257: sipush 179
    //   260: iconst_1
    //   261: invokestatic 60	xxxxxx/uxxxxx:bb00620062bb0062b0062b0062	(Ljava/lang/String;CC)Ljava/lang/String;
    //   264: iconst_0
    //   265: anewarray 62	java/lang/Class
    //   268: invokevirtual 66	java/lang/Class:getMethod	(Ljava/lang/String;[Ljava/lang/Class;)Ljava/lang/reflect/Method;
    //   271: astore 9
    //   273: iconst_0
    //   274: anewarray 68	java/lang/Object
    //   277: astore 10
    //   279: aload 9
    //   281: aconst_null
    //   282: aload 10
    //   284: invokevirtual 74	java/lang/reflect/Method:invoke	(Ljava/lang/Object;[Ljava/lang/Object;)Ljava/lang/Object;
    //   287: astore 12
    //   289: aload 12
    //   291: checkcast 76	java/lang/Integer
    //   294: invokevirtual 80	java/lang/Integer:intValue	()I
    //   297: putstatic 50	uuuuuu/lqlllq:bpp00700070p0070p00700070	I
    //   300: getstatic 50	uuuuuu/lqlllq:bpp00700070p0070p00700070	I
    //   303: istore 13
    //   305: iload 13
    //   307: iload 13
    //   309: getstatic 52	uuuuuu/lqlllq:b0070p00700070p0070p00700070	I
    //   312: iadd
    //   313: imul
    //   314: getstatic 90	uuuuuu/lqlllq:bp007000700070p0070p00700070	I
    //   317: irem
    //   318: tableswitch	default:+18->336, 0:+70->388
    //   336: ldc 2
    //   338: ldc_w 641
    //   341: sipush 219
    //   344: iconst_2
    //   345: invokestatic 60	xxxxxx/uxxxxx:bb00620062bb0062b0062b0062	(Ljava/lang/String;CC)Ljava/lang/String;
    //   348: iconst_0
    //   349: anewarray 62	java/lang/Class
    //   352: invokevirtual 66	java/lang/Class:getMethod	(Ljava/lang/String;[Ljava/lang/Class;)Ljava/lang/reflect/Method;
    //   355: astore 14
    //   357: iconst_0
    //   358: anewarray 68	java/lang/Object
    //   361: astore 15
    //   363: aload 14
    //   365: aconst_null
    //   366: aload 15
    //   368: invokevirtual 74	java/lang/reflect/Method:invoke	(Ljava/lang/Object;[Ljava/lang/Object;)Ljava/lang/Object;
    //   371: astore 17
    //   373: aload 17
    //   375: checkcast 76	java/lang/Integer
    //   378: invokevirtual 80	java/lang/Integer:intValue	()I
    //   381: putstatic 50	uuuuuu/lqlllq:bpp00700070p0070p00700070	I
    //   384: iconst_3
    //   385: putstatic 88	uuuuuu/lqlllq:b0070007000700070p0070p00700070	I
    //   388: bipush 15
    //   390: putstatic 88	uuuuuu/lqlllq:b0070007000700070p0070p00700070	I
    //   393: aload_1
    //   394: aload 7
    //   396: invokeinterface 646 2 0
    //   401: return
    //   402: astore 5
    //   404: aload 5
    //   406: invokevirtual 102	java/lang/reflect/InvocationTargetException:getCause	()Ljava/lang/Throwable;
    //   409: athrow
    //   410: astore 20
    //   412: aload 20
    //   414: invokevirtual 102	java/lang/reflect/InvocationTargetException:getCause	()Ljava/lang/Throwable;
    //   417: athrow
    //   418: astore 11
    //   420: aload 11
    //   422: invokevirtual 102	java/lang/reflect/InvocationTargetException:getCause	()Ljava/lang/Throwable;
    //   425: athrow
    //   426: astore 24
    //   428: aload 24
    //   430: invokevirtual 102	java/lang/reflect/InvocationTargetException:getCause	()Ljava/lang/Throwable;
    //   433: athrow
    //   434: astore 16
    //   436: aload 16
    //   438: invokevirtual 102	java/lang/reflect/InvocationTargetException:getCause	()Ljava/lang/Throwable;
    //   441: athrow
    // Local variable table:
    //   start	length	slot	name	signature
    //   0	442	0	this	lqlllq
    //   4	390	1	localPqqqqq	pqqqqq
    //   8	48	2	i	int
    //   28	8	3	localMethod1	java.lang.reflect.Method
    //   33	5	4	arrayOfObject1	Object[]
    //   402	3	5	localInvocationTargetException1	java.lang.reflect.InvocationTargetException
    //   42	5	6	localObject1	Object
    //   212	183	7	str	String
    //   217	11	8	j	int
    //   271	9	9	localMethod2	java.lang.reflect.Method
    //   277	6	10	arrayOfObject2	Object[]
    //   418	3	11	localInvocationTargetException2	java.lang.reflect.InvocationTargetException
    //   287	3	12	localObject2	Object
    //   303	11	13	k	int
    //   355	9	14	localMethod3	java.lang.reflect.Method
    //   361	6	15	arrayOfObject3	Object[]
    //   434	3	16	localInvocationTargetException3	java.lang.reflect.InvocationTargetException
    //   371	3	17	localObject3	Object
    //   174	9	18	localMethod4	java.lang.reflect.Method
    //   180	6	19	arrayOfObject4	Object[]
    //   410	3	20	localInvocationTargetException4	java.lang.reflect.InvocationTargetException
    //   190	3	21	localObject4	Object
    //   106	9	22	localMethod5	java.lang.reflect.Method
    //   112	6	23	arrayOfObject5	Object[]
    //   426	3	24	localInvocationTargetException5	java.lang.reflect.InvocationTargetException
    //   122	3	25	localObject5	Object
    // Exception table:
    //   from	to	target	type
    //   35	44	402	java/lang/reflect/InvocationTargetException
    //   182	192	410	java/lang/reflect/InvocationTargetException
    //   279	289	418	java/lang/reflect/InvocationTargetException
    //   114	124	426	java/lang/reflect/InvocationTargetException
    //   363	373	434	java/lang/reflect/InvocationTargetException
  }
  
  /* Error */
  public void boo006F006Foo006F006Foo(String paramString, Account paramAccount)
  {
    // Byte code:
    //   0: getstatic 50	uuuuuu/lqlllq:bpp00700070p0070p00700070	I
    //   3: getstatic 52	uuuuuu/lqlllq:b0070p00700070p0070p00700070	I
    //   6: iadd
    //   7: getstatic 50	uuuuuu/lqlllq:bpp00700070p0070p00700070	I
    //   10: imul
    //   11: istore_3
    //   12: ldc 2
    //   14: ldc_w 650
    //   17: bipush 43
    //   19: bipush 99
    //   21: iconst_3
    //   22: invokestatic 86	xxxxxx/uxxxxx:bbbb0062b0062b0062b0062	(Ljava/lang/String;CCC)Ljava/lang/String;
    //   25: iconst_0
    //   26: anewarray 62	java/lang/Class
    //   29: invokevirtual 66	java/lang/Class:getMethod	(Ljava/lang/String;[Ljava/lang/Class;)Ljava/lang/reflect/Method;
    //   32: astore 4
    //   34: iconst_0
    //   35: anewarray 68	java/lang/Object
    //   38: astore 5
    //   40: aload 4
    //   42: aconst_null
    //   43: aload 5
    //   45: invokevirtual 74	java/lang/reflect/Method:invoke	(Ljava/lang/Object;[Ljava/lang/Object;)Ljava/lang/Object;
    //   48: astore 7
    //   50: aload 7
    //   52: checkcast 76	java/lang/Integer
    //   55: invokevirtual 80	java/lang/Integer:intValue	()I
    //   58: istore 8
    //   60: getstatic 50	uuuuuu/lqlllq:bpp00700070p0070p00700070	I
    //   63: istore 9
    //   65: getstatic 50	uuuuuu/lqlllq:bpp00700070p0070p00700070	I
    //   68: getstatic 52	uuuuuu/lqlllq:b0070p00700070p0070p00700070	I
    //   71: iadd
    //   72: getstatic 50	uuuuuu/lqlllq:bpp00700070p0070p00700070	I
    //   75: imul
    //   76: istore 10
    //   78: ldc 2
    //   80: ldc_w 652
    //   83: sipush 180
    //   86: iconst_0
    //   87: invokestatic 60	xxxxxx/uxxxxx:bb00620062bb0062b0062b0062	(Ljava/lang/String;CC)Ljava/lang/String;
    //   90: iconst_0
    //   91: anewarray 62	java/lang/Class
    //   94: invokevirtual 66	java/lang/Class:getMethod	(Ljava/lang/String;[Ljava/lang/Class;)Ljava/lang/reflect/Method;
    //   97: astore 11
    //   99: iconst_0
    //   100: anewarray 68	java/lang/Object
    //   103: astore 12
    //   105: aload 11
    //   107: aconst_null
    //   108: aload 12
    //   110: invokevirtual 74	java/lang/reflect/Method:invoke	(Ljava/lang/Object;[Ljava/lang/Object;)Ljava/lang/Object;
    //   113: astore 14
    //   115: iload 10
    //   117: aload 14
    //   119: checkcast 76	java/lang/Integer
    //   122: invokevirtual 80	java/lang/Integer:intValue	()I
    //   125: irem
    //   126: getstatic 88	uuuuuu/lqlllq:b0070007000700070p0070p00700070	I
    //   129: if_icmpeq +13 -> 142
    //   132: bipush 84
    //   134: putstatic 50	uuuuuu/lqlllq:bpp00700070p0070p00700070	I
    //   137: bipush 88
    //   139: putstatic 88	uuuuuu/lqlllq:b0070007000700070p0070p00700070	I
    //   142: iload 9
    //   144: iload 9
    //   146: getstatic 52	uuuuuu/lqlllq:b0070p00700070p0070p00700070	I
    //   149: iadd
    //   150: imul
    //   151: getstatic 90	uuuuuu/lqlllq:bp007000700070p0070p00700070	I
    //   154: irem
    //   155: tableswitch	default:+17->172, 0:+69->224
    //   172: ldc 2
    //   174: ldc_w 456
    //   177: bipush 59
    //   179: iconst_5
    //   180: invokestatic 60	xxxxxx/uxxxxx:bb00620062bb0062b0062b0062	(Ljava/lang/String;CC)Ljava/lang/String;
    //   183: iconst_0
    //   184: anewarray 62	java/lang/Class
    //   187: invokevirtual 66	java/lang/Class:getMethod	(Ljava/lang/String;[Ljava/lang/Class;)Ljava/lang/reflect/Method;
    //   190: astore 24
    //   192: iconst_0
    //   193: anewarray 68	java/lang/Object
    //   196: astore 25
    //   198: aload 24
    //   200: aconst_null
    //   201: aload 25
    //   203: invokevirtual 74	java/lang/reflect/Method:invoke	(Ljava/lang/Object;[Ljava/lang/Object;)Ljava/lang/Object;
    //   206: astore 27
    //   208: aload 27
    //   210: checkcast 76	java/lang/Integer
    //   213: invokevirtual 80	java/lang/Integer:intValue	()I
    //   216: putstatic 50	uuuuuu/lqlllq:bpp00700070p0070p00700070	I
    //   219: bipush 60
    //   221: putstatic 88	uuuuuu/lqlllq:b0070007000700070p0070p00700070	I
    //   224: iload_3
    //   225: iload 8
    //   227: irem
    //   228: getstatic 88	uuuuuu/lqlllq:b0070007000700070p0070p00700070	I
    //   231: if_icmpeq +146 -> 377
    //   234: getstatic 50	uuuuuu/lqlllq:bpp00700070p0070p00700070	I
    //   237: istore 15
    //   239: ldc 2
    //   241: ldc_w 654
    //   244: sipush 146
    //   247: iconst_5
    //   248: invokestatic 60	xxxxxx/uxxxxx:bb00620062bb0062b0062b0062	(Ljava/lang/String;CC)Ljava/lang/String;
    //   251: iconst_0
    //   252: anewarray 62	java/lang/Class
    //   255: invokevirtual 66	java/lang/Class:getMethod	(Ljava/lang/String;[Ljava/lang/Class;)Ljava/lang/reflect/Method;
    //   258: astore 16
    //   260: iconst_0
    //   261: anewarray 68	java/lang/Object
    //   264: astore 17
    //   266: aload 16
    //   268: aconst_null
    //   269: aload 17
    //   271: invokevirtual 74	java/lang/reflect/Method:invoke	(Ljava/lang/Object;[Ljava/lang/Object;)Ljava/lang/Object;
    //   274: astore 19
    //   276: iload 15
    //   278: iload 15
    //   280: aload 19
    //   282: checkcast 76	java/lang/Integer
    //   285: invokevirtual 80	java/lang/Integer:intValue	()I
    //   288: iadd
    //   289: imul
    //   290: getstatic 90	uuuuuu/lqlllq:bp007000700070p0070p00700070	I
    //   293: irem
    //   294: tableswitch	default:+18->312, 0:+28->322
    //   312: bipush 35
    //   314: putstatic 50	uuuuuu/lqlllq:bpp00700070p0070p00700070	I
    //   317: bipush 15
    //   319: putstatic 88	uuuuuu/lqlllq:b0070007000700070p0070p00700070	I
    //   322: bipush 61
    //   324: putstatic 50	uuuuuu/lqlllq:bpp00700070p0070p00700070	I
    //   327: ldc 2
    //   329: ldc_w 656
    //   332: sipush 144
    //   335: bipush 120
    //   337: iconst_1
    //   338: invokestatic 86	xxxxxx/uxxxxx:bbbb0062b0062b0062b0062	(Ljava/lang/String;CCC)Ljava/lang/String;
    //   341: iconst_0
    //   342: anewarray 62	java/lang/Class
    //   345: invokevirtual 66	java/lang/Class:getMethod	(Ljava/lang/String;[Ljava/lang/Class;)Ljava/lang/reflect/Method;
    //   348: astore 20
    //   350: iconst_0
    //   351: anewarray 68	java/lang/Object
    //   354: astore 21
    //   356: aload 20
    //   358: aconst_null
    //   359: aload 21
    //   361: invokevirtual 74	java/lang/reflect/Method:invoke	(Ljava/lang/Object;[Ljava/lang/Object;)Ljava/lang/Object;
    //   364: astore 23
    //   366: aload 23
    //   368: checkcast 76	java/lang/Integer
    //   371: invokevirtual 80	java/lang/Integer:intValue	()I
    //   374: putstatic 88	uuuuuu/lqlllq:b0070007000700070p0070p00700070	I
    //   377: aload_0
    //   378: aload_1
    //   379: putfield 233	uuuuuu/lqlllq:bp0070007000700070pp00700070	Ljava/lang/String;
    //   382: aload_0
    //   383: aload_2
    //   384: putfield 179	uuuuuu/lqlllq:b0070p007000700070pp00700070	Lcom/db/pwcc/dbmobile/model/banking/Account;
    //   387: return
    //   388: astore 26
    //   390: aload 26
    //   392: invokevirtual 102	java/lang/reflect/InvocationTargetException:getCause	()Ljava/lang/Throwable;
    //   395: athrow
    //   396: astore 22
    //   398: aload 22
    //   400: invokevirtual 102	java/lang/reflect/InvocationTargetException:getCause	()Ljava/lang/Throwable;
    //   403: athrow
    //   404: astore 6
    //   406: aload 6
    //   408: invokevirtual 102	java/lang/reflect/InvocationTargetException:getCause	()Ljava/lang/Throwable;
    //   411: athrow
    //   412: astore 13
    //   414: aload 13
    //   416: invokevirtual 102	java/lang/reflect/InvocationTargetException:getCause	()Ljava/lang/Throwable;
    //   419: athrow
    //   420: astore 18
    //   422: aload 18
    //   424: invokevirtual 102	java/lang/reflect/InvocationTargetException:getCause	()Ljava/lang/Throwable;
    //   427: athrow
    // Local variable table:
    //   start	length	slot	name	signature
    //   0	428	0	this	lqlllq
    //   0	428	1	paramString	String
    //   0	428	2	paramAccount	Account
    //   11	217	3	i	int
    //   32	9	4	localMethod1	java.lang.reflect.Method
    //   38	6	5	arrayOfObject1	Object[]
    //   404	3	6	localInvocationTargetException1	java.lang.reflect.InvocationTargetException
    //   48	3	7	localObject1	Object
    //   58	170	8	j	int
    //   63	88	9	k	int
    //   76	50	10	m	int
    //   97	9	11	localMethod2	java.lang.reflect.Method
    //   103	6	12	arrayOfObject2	Object[]
    //   412	3	13	localInvocationTargetException2	java.lang.reflect.InvocationTargetException
    //   113	5	14	localObject2	Object
    //   237	53	15	n	int
    //   258	9	16	localMethod3	java.lang.reflect.Method
    //   264	6	17	arrayOfObject3	Object[]
    //   420	3	18	localInvocationTargetException3	java.lang.reflect.InvocationTargetException
    //   274	7	19	localObject3	Object
    //   348	9	20	localMethod4	java.lang.reflect.Method
    //   354	6	21	arrayOfObject4	Object[]
    //   396	3	22	localInvocationTargetException4	java.lang.reflect.InvocationTargetException
    //   364	3	23	localObject4	Object
    //   190	9	24	localMethod5	java.lang.reflect.Method
    //   196	6	25	arrayOfObject5	Object[]
    //   388	3	26	localInvocationTargetException5	java.lang.reflect.InvocationTargetException
    //   206	3	27	localObject5	Object
    // Exception table:
    //   from	to	target	type
    //   198	208	388	java/lang/reflect/InvocationTargetException
    //   356	366	396	java/lang/reflect/InvocationTargetException
    //   40	50	404	java/lang/reflect/InvocationTargetException
    //   105	115	412	java/lang/reflect/InvocationTargetException
    //   266	276	420	java/lang/reflect/InvocationTargetException
  }
}
