package uuuuuu;

import android.os.Bundle;
import com.db.pwcc.dbmobile.foundation.data.manager.broadcasting.InputActionRequiredBroadcastReceiver;
import com.db.pwcc.dbmobile.foundation.data.manager.broadcasting.ModelUpdatedBroadcastReceiver;
import com.db.pwcc.dbmobile.model.error.DbError;
import java.lang.reflect.InvocationTargetException;
import java.lang.reflect.Method;
import java.security.interfaces.RSAPublicKey;
import javax.inject.Inject;
import xxxxxx.uxxxxx;

public class qmqqmm
  extends qppppp<mmmmqm.mqqqmm>
  implements mmmmqm.qqqqmm, alaall.laaall, vvxxvv.xxvxvv
{
  public static int b00760076vv0076v00760076v = 1;
  public static int b0076vvv0076v00760076v = 46;
  public static int bv0076vv0076v00760076v = 0;
  public static int bvv0076v0076v00760076v = 2;
  private RSAPublicKey b0076007600760076vv00760076v;
  private final String b00760076v0076vv00760076v;
  @Inject
  public vxvvvx b0076v00760076vv00760076v;
  private ModelUpdatedBroadcastReceiver bv007600760076vv00760076v;
  private InputActionRequiredBroadcastReceiver bvv00760076vv00760076v;
  public boolean bvvvv0076v00760076v = false;
  
  public qmqqmm(String paramString)
  {
    this.b00760076v0076vv00760076v = paramString;
    xvvvxx.b0075uu00750075007500750075u0075().bpp007000700070ppppp(this);
  }
  
  /* Error */
  private boolean b0075007500750075007500750075uu0075(Bundle paramBundle)
  {
    // Byte code:
    //   0: aload_1
    //   1: ifnull +394 -> 395
    //   4: aload_0
    //   5: getfield 42	uuuuuu/qmqqmm:b00760076v0076vv00760076v	Ljava/lang/String;
    //   8: astore 7
    //   10: ldc 60
    //   12: bipush 26
    //   14: iconst_2
    //   15: invokestatic 66	xxxxxx/uxxxxx:bb00620062bb0062b0062b0062	(Ljava/lang/String;CC)Ljava/lang/String;
    //   18: astore 8
    //   20: iconst_3
    //   21: anewarray 68	java/lang/Class
    //   24: astore 9
    //   26: aload 9
    //   28: iconst_0
    //   29: ldc 70
    //   31: aastore
    //   32: aload 9
    //   34: iconst_1
    //   35: getstatic 76	java/lang/Character:TYPE	Ljava/lang/Class;
    //   38: aastore
    //   39: aload 9
    //   41: iconst_2
    //   42: getstatic 76	java/lang/Character:TYPE	Ljava/lang/Class;
    //   45: aastore
    //   46: ldc 78
    //   48: aload 8
    //   50: aload 9
    //   52: invokevirtual 82	java/lang/Class:getMethod	(Ljava/lang/String;[Ljava/lang/Class;)Ljava/lang/reflect/Method;
    //   55: astore 10
    //   57: iconst_3
    //   58: anewarray 84	java/lang/Object
    //   61: astore 11
    //   63: aload 11
    //   65: iconst_0
    //   66: ldc 86
    //   68: aastore
    //   69: aload 11
    //   71: iconst_1
    //   72: bipush 96
    //   74: invokestatic 90	java/lang/Character:valueOf	(C)Ljava/lang/Character;
    //   77: aastore
    //   78: aload 11
    //   80: iconst_2
    //   81: iconst_5
    //   82: invokestatic 90	java/lang/Character:valueOf	(C)Ljava/lang/Character;
    //   85: aastore
    //   86: aload 10
    //   88: aconst_null
    //   89: aload 11
    //   91: invokevirtual 96	java/lang/reflect/Method:invoke	(Ljava/lang/Object;[Ljava/lang/Object;)Ljava/lang/Object;
    //   94: astore 13
    //   96: aload 7
    //   98: aload_1
    //   99: aload 13
    //   101: checkcast 70	java/lang/String
    //   104: invokevirtual 102	android/os/Bundle:getString	(Ljava/lang/String;)Ljava/lang/String;
    //   107: invokevirtual 106	java/lang/String:equals	(Ljava/lang/Object;)Z
    //   110: ifeq +285 -> 395
    //   113: getstatic 108	uuuuuu/qmqqmm:b0076vvv0076v00760076v	I
    //   116: getstatic 110	uuuuuu/qmqqmm:b00760076vv0076v00760076v	I
    //   119: iadd
    //   120: getstatic 108	uuuuuu/qmqqmm:b0076vvv0076v00760076v	I
    //   123: imul
    //   124: istore 14
    //   126: ldc 2
    //   128: ldc 112
    //   130: sipush 187
    //   133: iconst_1
    //   134: invokestatic 66	xxxxxx/uxxxxx:bb00620062bb0062b0062b0062	(Ljava/lang/String;CC)Ljava/lang/String;
    //   137: iconst_0
    //   138: anewarray 68	java/lang/Class
    //   141: invokevirtual 82	java/lang/Class:getMethod	(Ljava/lang/String;[Ljava/lang/Class;)Ljava/lang/reflect/Method;
    //   144: astore 15
    //   146: iconst_0
    //   147: anewarray 84	java/lang/Object
    //   150: astore 16
    //   152: aload 15
    //   154: aconst_null
    //   155: aload 16
    //   157: invokevirtual 96	java/lang/reflect/Method:invoke	(Ljava/lang/Object;[Ljava/lang/Object;)Ljava/lang/Object;
    //   160: astore 18
    //   162: iload 14
    //   164: aload 18
    //   166: checkcast 114	java/lang/Integer
    //   169: invokevirtual 118	java/lang/Integer:intValue	()I
    //   172: irem
    //   173: getstatic 120	uuuuuu/qmqqmm:bv0076vv0076v00760076v	I
    //   176: if_icmpeq +351 -> 527
    //   179: getstatic 108	uuuuuu/qmqqmm:b0076vvv0076v00760076v	I
    //   182: istore 19
    //   184: iload 19
    //   186: iload 19
    //   188: getstatic 110	uuuuuu/qmqqmm:b00760076vv0076v00760076v	I
    //   191: iadd
    //   192: imul
    //   193: getstatic 122	uuuuuu/qmqqmm:bvv0076v0076v00760076v	I
    //   196: irem
    //   197: tableswitch	default:+19->216, 0:+70->267
    //   216: ldc 2
    //   218: ldc 124
    //   220: bipush 76
    //   222: iconst_3
    //   223: invokestatic 66	xxxxxx/uxxxxx:bb00620062bb0062b0062b0062	(Ljava/lang/String;CC)Ljava/lang/String;
    //   226: iconst_0
    //   227: anewarray 68	java/lang/Class
    //   230: invokevirtual 82	java/lang/Class:getMethod	(Ljava/lang/String;[Ljava/lang/Class;)Ljava/lang/reflect/Method;
    //   233: astore 28
    //   235: iconst_0
    //   236: anewarray 84	java/lang/Object
    //   239: astore 29
    //   241: aload 28
    //   243: aconst_null
    //   244: aload 29
    //   246: invokevirtual 96	java/lang/reflect/Method:invoke	(Ljava/lang/Object;[Ljava/lang/Object;)Ljava/lang/Object;
    //   249: astore 31
    //   251: aload 31
    //   253: checkcast 114	java/lang/Integer
    //   256: invokevirtual 118	java/lang/Integer:intValue	()I
    //   259: putstatic 108	uuuuuu/qmqqmm:b0076vvv0076v00760076v	I
    //   262: bipush 50
    //   264: putstatic 120	uuuuuu/qmqqmm:bv0076vv0076v00760076v	I
    //   267: getstatic 108	uuuuuu/qmqqmm:b0076vvv0076v00760076v	I
    //   270: getstatic 110	uuuuuu/qmqqmm:b00760076vv0076v00760076v	I
    //   273: iadd
    //   274: getstatic 108	uuuuuu/qmqqmm:b0076vvv0076v00760076v	I
    //   277: imul
    //   278: getstatic 122	uuuuuu/qmqqmm:bvv0076v0076v00760076v	I
    //   281: irem
    //   282: getstatic 120	uuuuuu/qmqqmm:bv0076vv0076v00760076v	I
    //   285: if_icmpeq +54 -> 339
    //   288: bipush 11
    //   290: putstatic 108	uuuuuu/qmqqmm:b0076vvv0076v00760076v	I
    //   293: ldc 2
    //   295: ldc 126
    //   297: bipush 51
    //   299: iconst_3
    //   300: invokestatic 66	xxxxxx/uxxxxx:bb00620062bb0062b0062b0062	(Ljava/lang/String;CC)Ljava/lang/String;
    //   303: iconst_0
    //   304: anewarray 68	java/lang/Class
    //   307: invokevirtual 82	java/lang/Class:getMethod	(Ljava/lang/String;[Ljava/lang/Class;)Ljava/lang/reflect/Method;
    //   310: astore 24
    //   312: iconst_0
    //   313: anewarray 84	java/lang/Object
    //   316: astore 25
    //   318: aload 24
    //   320: aconst_null
    //   321: aload 25
    //   323: invokevirtual 96	java/lang/reflect/Method:invoke	(Ljava/lang/Object;[Ljava/lang/Object;)Ljava/lang/Object;
    //   326: astore 27
    //   328: aload 27
    //   330: checkcast 114	java/lang/Integer
    //   333: invokevirtual 118	java/lang/Integer:intValue	()I
    //   336: putstatic 120	uuuuuu/qmqqmm:bv0076vv0076v00760076v	I
    //   339: ldc 2
    //   341: ldc -128
    //   343: bipush 8
    //   345: sipush 214
    //   348: iconst_0
    //   349: invokestatic 132	xxxxxx/uxxxxx:bbbb0062b0062b0062b0062	(Ljava/lang/String;CCC)Ljava/lang/String;
    //   352: iconst_0
    //   353: anewarray 68	java/lang/Class
    //   356: invokevirtual 82	java/lang/Class:getMethod	(Ljava/lang/String;[Ljava/lang/Class;)Ljava/lang/reflect/Method;
    //   359: astore 20
    //   361: iconst_0
    //   362: anewarray 84	java/lang/Object
    //   365: astore 21
    //   367: aload 20
    //   369: aconst_null
    //   370: aload 21
    //   372: invokevirtual 96	java/lang/reflect/Method:invoke	(Ljava/lang/Object;[Ljava/lang/Object;)Ljava/lang/Object;
    //   375: astore 23
    //   377: aload 23
    //   379: checkcast 114	java/lang/Integer
    //   382: invokevirtual 118	java/lang/Integer:intValue	()I
    //   385: putstatic 108	uuuuuu/qmqqmm:b0076vvv0076v00760076v	I
    //   388: bipush 8
    //   390: putstatic 120	uuuuuu/qmqqmm:bv0076vv0076v00760076v	I
    //   393: iconst_1
    //   394: ireturn
    //   395: getstatic 108	uuuuuu/qmqqmm:b0076vvv0076v00760076v	I
    //   398: istore_2
    //   399: iload_2
    //   400: iload_2
    //   401: getstatic 110	uuuuuu/qmqqmm:b00760076vv0076v00760076v	I
    //   404: iadd
    //   405: imul
    //   406: getstatic 122	uuuuuu/qmqqmm:bvv0076v0076v00760076v	I
    //   409: irem
    //   410: tableswitch	default:+18->428, 0:+119->529
    //   428: ldc 2
    //   430: ldc -122
    //   432: bipush 36
    //   434: iconst_3
    //   435: invokestatic 66	xxxxxx/uxxxxx:bb00620062bb0062b0062b0062	(Ljava/lang/String;CC)Ljava/lang/String;
    //   438: iconst_0
    //   439: anewarray 68	java/lang/Class
    //   442: invokevirtual 82	java/lang/Class:getMethod	(Ljava/lang/String;[Ljava/lang/Class;)Ljava/lang/reflect/Method;
    //   445: astore_3
    //   446: iconst_0
    //   447: anewarray 84	java/lang/Object
    //   450: astore 4
    //   452: aload_3
    //   453: aconst_null
    //   454: aload 4
    //   456: invokevirtual 96	java/lang/reflect/Method:invoke	(Ljava/lang/Object;[Ljava/lang/Object;)Ljava/lang/Object;
    //   459: astore 6
    //   461: aload 6
    //   463: checkcast 114	java/lang/Integer
    //   466: invokevirtual 118	java/lang/Integer:intValue	()I
    //   469: putstatic 108	uuuuuu/qmqqmm:b0076vvv0076v00760076v	I
    //   472: bipush 98
    //   474: putstatic 120	uuuuuu/qmqqmm:bv0076vv0076v00760076v	I
    //   477: iconst_0
    //   478: ireturn
    //   479: astore 12
    //   481: aload 12
    //   483: invokevirtual 138	java/lang/reflect/InvocationTargetException:getCause	()Ljava/lang/Throwable;
    //   486: athrow
    //   487: astore 17
    //   489: aload 17
    //   491: invokevirtual 138	java/lang/reflect/InvocationTargetException:getCause	()Ljava/lang/Throwable;
    //   494: athrow
    //   495: astore 22
    //   497: aload 22
    //   499: invokevirtual 138	java/lang/reflect/InvocationTargetException:getCause	()Ljava/lang/Throwable;
    //   502: athrow
    //   503: astore 30
    //   505: aload 30
    //   507: invokevirtual 138	java/lang/reflect/InvocationTargetException:getCause	()Ljava/lang/Throwable;
    //   510: athrow
    //   511: astore 5
    //   513: aload 5
    //   515: invokevirtual 138	java/lang/reflect/InvocationTargetException:getCause	()Ljava/lang/Throwable;
    //   518: athrow
    //   519: astore 26
    //   521: aload 26
    //   523: invokevirtual 138	java/lang/reflect/InvocationTargetException:getCause	()Ljava/lang/Throwable;
    //   526: athrow
    //   527: iconst_1
    //   528: ireturn
    //   529: iconst_0
    //   530: ireturn
    // Local variable table:
    //   start	length	slot	name	signature
    //   0	531	0	this	qmqqmm
    //   0	531	1	paramBundle	Bundle
    //   398	8	2	i	int
    //   445	8	3	localMethod1	Method
    //   450	5	4	arrayOfObject1	Object[]
    //   511	3	5	localInvocationTargetException1	InvocationTargetException
    //   459	3	6	localObject1	Object
    //   8	89	7	str1	String
    //   18	31	8	str2	String
    //   24	27	9	arrayOfClass	Class[]
    //   55	32	10	localMethod2	Method
    //   61	29	11	arrayOfObject2	Object[]
    //   479	3	12	localInvocationTargetException2	InvocationTargetException
    //   94	6	13	localObject2	Object
    //   124	49	14	j	int
    //   144	9	15	localMethod3	Method
    //   150	6	16	arrayOfObject3	Object[]
    //   487	3	17	localInvocationTargetException3	InvocationTargetException
    //   160	5	18	localObject3	Object
    //   182	11	19	k	int
    //   359	9	20	localMethod4	Method
    //   365	6	21	arrayOfObject4	Object[]
    //   495	3	22	localInvocationTargetException4	InvocationTargetException
    //   375	3	23	localObject4	Object
    //   310	9	24	localMethod5	Method
    //   316	6	25	arrayOfObject5	Object[]
    //   519	3	26	localInvocationTargetException5	InvocationTargetException
    //   326	3	27	localObject5	Object
    //   233	9	28	localMethod6	Method
    //   239	6	29	arrayOfObject6	Object[]
    //   503	3	30	localInvocationTargetException6	InvocationTargetException
    //   249	3	31	localObject6	Object
    // Exception table:
    //   from	to	target	type
    //   86	96	479	java/lang/reflect/InvocationTargetException
    //   152	162	487	java/lang/reflect/InvocationTargetException
    //   367	377	495	java/lang/reflect/InvocationTargetException
    //   241	251	503	java/lang/reflect/InvocationTargetException
    //   452	461	511	java/lang/reflect/InvocationTargetException
    //   318	328	519	java/lang/reflect/InvocationTargetException
  }
  
  /* Error */
  private void b007500750075uuuu0075u0075(android.content.Context paramContext, android.content.BroadcastReceiver paramBroadcastReceiver)
  {
    // Byte code:
    //   0: aload_2
    //   1: ifnull +425 -> 426
    //   4: getstatic 108	uuuuuu/qmqqmm:b0076vvv0076v00760076v	I
    //   7: istore_3
    //   8: iload_3
    //   9: iload_3
    //   10: getstatic 110	uuuuuu/qmqqmm:b00760076vv0076v00760076v	I
    //   13: iadd
    //   14: imul
    //   15: getstatic 122	uuuuuu/qmqqmm:bvv0076v0076v00760076v	I
    //   18: irem
    //   19: tableswitch	default:+17->36, 0:+68->87
    //   36: ldc 2
    //   38: ldc -90
    //   40: bipush 34
    //   42: iconst_1
    //   43: invokestatic 66	xxxxxx/uxxxxx:bb00620062bb0062b0062b0062	(Ljava/lang/String;CC)Ljava/lang/String;
    //   46: iconst_0
    //   47: anewarray 68	java/lang/Class
    //   50: invokevirtual 82	java/lang/Class:getMethod	(Ljava/lang/String;[Ljava/lang/Class;)Ljava/lang/reflect/Method;
    //   53: astore 27
    //   55: iconst_0
    //   56: anewarray 84	java/lang/Object
    //   59: astore 28
    //   61: aload 27
    //   63: aconst_null
    //   64: aload 28
    //   66: invokevirtual 96	java/lang/reflect/Method:invoke	(Ljava/lang/Object;[Ljava/lang/Object;)Ljava/lang/Object;
    //   69: astore 30
    //   71: aload 30
    //   73: checkcast 114	java/lang/Integer
    //   76: invokevirtual 118	java/lang/Integer:intValue	()I
    //   79: putstatic 108	uuuuuu/qmqqmm:b0076vvv0076v00760076v	I
    //   82: bipush 17
    //   84: putstatic 120	uuuuuu/qmqqmm:bv0076vv0076v00760076v	I
    //   87: aload_1
    //   88: invokestatic 172	android/support/v4/content/LocalBroadcastManager:getInstance	(Landroid/content/Context;)Landroid/support/v4/content/LocalBroadcastManager;
    //   91: astore 4
    //   93: getstatic 108	uuuuuu/qmqqmm:b0076vvv0076v00760076v	I
    //   96: getstatic 110	uuuuuu/qmqqmm:b00760076vv0076v00760076v	I
    //   99: iadd
    //   100: getstatic 108	uuuuuu/qmqqmm:b0076vvv0076v00760076v	I
    //   103: imul
    //   104: getstatic 122	uuuuuu/qmqqmm:bvv0076v0076v00760076v	I
    //   107: irem
    //   108: getstatic 120	uuuuuu/qmqqmm:bv0076vv0076v00760076v	I
    //   111: if_icmpeq +147 -> 258
    //   114: getstatic 108	uuuuuu/qmqqmm:b0076vvv0076v00760076v	I
    //   117: istore 18
    //   119: iload 18
    //   121: iload 18
    //   123: getstatic 110	uuuuuu/qmqqmm:b00760076vv0076v00760076v	I
    //   126: iadd
    //   127: imul
    //   128: getstatic 122	uuuuuu/qmqqmm:bvv0076v0076v00760076v	I
    //   131: irem
    //   132: tableswitch	default:+20->152, 0:+72->204
    //   152: bipush 32
    //   154: putstatic 108	uuuuuu/qmqqmm:b0076vvv0076v00760076v	I
    //   157: ldc 2
    //   159: ldc -82
    //   161: sipush 192
    //   164: iconst_2
    //   165: invokestatic 66	xxxxxx/uxxxxx:bb00620062bb0062b0062b0062	(Ljava/lang/String;CC)Ljava/lang/String;
    //   168: iconst_0
    //   169: anewarray 68	java/lang/Class
    //   172: invokevirtual 82	java/lang/Class:getMethod	(Ljava/lang/String;[Ljava/lang/Class;)Ljava/lang/reflect/Method;
    //   175: astore 23
    //   177: iconst_0
    //   178: anewarray 84	java/lang/Object
    //   181: astore 24
    //   183: aload 23
    //   185: aconst_null
    //   186: aload 24
    //   188: invokevirtual 96	java/lang/reflect/Method:invoke	(Ljava/lang/Object;[Ljava/lang/Object;)Ljava/lang/Object;
    //   191: astore 26
    //   193: aload 26
    //   195: checkcast 114	java/lang/Integer
    //   198: invokevirtual 118	java/lang/Integer:intValue	()I
    //   201: putstatic 120	uuuuuu/qmqqmm:bv0076vv0076v00760076v	I
    //   204: ldc 2
    //   206: ldc -80
    //   208: bipush 127
    //   210: sipush 170
    //   213: iconst_1
    //   214: invokestatic 132	xxxxxx/uxxxxx:bbbb0062b0062b0062b0062	(Ljava/lang/String;CCC)Ljava/lang/String;
    //   217: iconst_0
    //   218: anewarray 68	java/lang/Class
    //   221: invokevirtual 82	java/lang/Class:getMethod	(Ljava/lang/String;[Ljava/lang/Class;)Ljava/lang/reflect/Method;
    //   224: astore 19
    //   226: iconst_0
    //   227: anewarray 84	java/lang/Object
    //   230: astore 20
    //   232: aload 19
    //   234: aconst_null
    //   235: aload 20
    //   237: invokevirtual 96	java/lang/reflect/Method:invoke	(Ljava/lang/Object;[Ljava/lang/Object;)Ljava/lang/Object;
    //   240: astore 22
    //   242: aload 22
    //   244: checkcast 114	java/lang/Integer
    //   247: invokevirtual 118	java/lang/Integer:intValue	()I
    //   250: putstatic 108	uuuuuu/qmqqmm:b0076vvv0076v00760076v	I
    //   253: bipush 84
    //   255: putstatic 120	uuuuuu/qmqqmm:bv0076vv0076v00760076v	I
    //   258: aload 4
    //   260: aload_2
    //   261: invokevirtual 180	android/support/v4/content/LocalBroadcastManager:unregisterReceiver	(Landroid/content/BroadcastReceiver;)V
    //   264: getstatic 108	uuuuuu/qmqqmm:b0076vvv0076v00760076v	I
    //   267: getstatic 110	uuuuuu/qmqqmm:b00760076vv0076v00760076v	I
    //   270: iadd
    //   271: getstatic 108	uuuuuu/qmqqmm:b0076vvv0076v00760076v	I
    //   274: imul
    //   275: istore 5
    //   277: ldc 2
    //   279: ldc -74
    //   281: bipush 104
    //   283: iconst_1
    //   284: invokestatic 66	xxxxxx/uxxxxx:bb00620062bb0062b0062b0062	(Ljava/lang/String;CC)Ljava/lang/String;
    //   287: iconst_0
    //   288: anewarray 68	java/lang/Class
    //   291: invokevirtual 82	java/lang/Class:getMethod	(Ljava/lang/String;[Ljava/lang/Class;)Ljava/lang/reflect/Method;
    //   294: astore 6
    //   296: iconst_0
    //   297: anewarray 84	java/lang/Object
    //   300: astore 7
    //   302: aload 6
    //   304: aconst_null
    //   305: aload 7
    //   307: invokevirtual 96	java/lang/reflect/Method:invoke	(Ljava/lang/Object;[Ljava/lang/Object;)Ljava/lang/Object;
    //   310: astore 9
    //   312: iload 5
    //   314: aload 9
    //   316: checkcast 114	java/lang/Integer
    //   319: invokevirtual 118	java/lang/Integer:intValue	()I
    //   322: irem
    //   323: getstatic 120	uuuuuu/qmqqmm:bv0076vv0076v00760076v	I
    //   326: if_icmpeq +100 -> 426
    //   329: ldc 2
    //   331: ldc -72
    //   333: sipush 159
    //   336: iconst_0
    //   337: invokestatic 66	xxxxxx/uxxxxx:bb00620062bb0062b0062b0062	(Ljava/lang/String;CC)Ljava/lang/String;
    //   340: iconst_0
    //   341: anewarray 68	java/lang/Class
    //   344: invokevirtual 82	java/lang/Class:getMethod	(Ljava/lang/String;[Ljava/lang/Class;)Ljava/lang/reflect/Method;
    //   347: astore 10
    //   349: iconst_0
    //   350: anewarray 84	java/lang/Object
    //   353: astore 11
    //   355: aload 10
    //   357: aconst_null
    //   358: aload 11
    //   360: invokevirtual 96	java/lang/reflect/Method:invoke	(Ljava/lang/Object;[Ljava/lang/Object;)Ljava/lang/Object;
    //   363: astore 13
    //   365: aload 13
    //   367: checkcast 114	java/lang/Integer
    //   370: invokevirtual 118	java/lang/Integer:intValue	()I
    //   373: putstatic 108	uuuuuu/qmqqmm:b0076vvv0076v00760076v	I
    //   376: ldc 2
    //   378: ldc -70
    //   380: sipush 231
    //   383: sipush 167
    //   386: iconst_3
    //   387: invokestatic 132	xxxxxx/uxxxxx:bbbb0062b0062b0062b0062	(Ljava/lang/String;CCC)Ljava/lang/String;
    //   390: iconst_0
    //   391: anewarray 68	java/lang/Class
    //   394: invokevirtual 82	java/lang/Class:getMethod	(Ljava/lang/String;[Ljava/lang/Class;)Ljava/lang/reflect/Method;
    //   397: astore 14
    //   399: iconst_0
    //   400: anewarray 84	java/lang/Object
    //   403: astore 15
    //   405: aload 14
    //   407: aconst_null
    //   408: aload 15
    //   410: invokevirtual 96	java/lang/reflect/Method:invoke	(Ljava/lang/Object;[Ljava/lang/Object;)Ljava/lang/Object;
    //   413: astore 17
    //   415: aload 17
    //   417: checkcast 114	java/lang/Integer
    //   420: invokevirtual 118	java/lang/Integer:intValue	()I
    //   423: putstatic 120	uuuuuu/qmqqmm:bv0076vv0076v00760076v	I
    //   426: return
    //   427: astore 8
    //   429: aload 8
    //   431: invokevirtual 138	java/lang/reflect/InvocationTargetException:getCause	()Ljava/lang/Throwable;
    //   434: athrow
    //   435: astore 21
    //   437: aload 21
    //   439: invokevirtual 138	java/lang/reflect/InvocationTargetException:getCause	()Ljava/lang/Throwable;
    //   442: athrow
    //   443: astore 25
    //   445: aload 25
    //   447: invokevirtual 138	java/lang/reflect/InvocationTargetException:getCause	()Ljava/lang/Throwable;
    //   450: athrow
    //   451: astore 12
    //   453: aload 12
    //   455: invokevirtual 138	java/lang/reflect/InvocationTargetException:getCause	()Ljava/lang/Throwable;
    //   458: athrow
    //   459: astore 16
    //   461: aload 16
    //   463: invokevirtual 138	java/lang/reflect/InvocationTargetException:getCause	()Ljava/lang/Throwable;
    //   466: athrow
    //   467: astore 29
    //   469: aload 29
    //   471: invokevirtual 138	java/lang/reflect/InvocationTargetException:getCause	()Ljava/lang/Throwable;
    //   474: athrow
    // Local variable table:
    //   start	length	slot	name	signature
    //   0	475	0	this	qmqqmm
    //   0	475	1	paramContext	android.content.Context
    //   0	475	2	paramBroadcastReceiver	android.content.BroadcastReceiver
    //   7	8	3	i	int
    //   91	168	4	localLocalBroadcastManager	android.support.v4.content.LocalBroadcastManager
    //   275	48	5	j	int
    //   294	9	6	localMethod1	Method
    //   300	6	7	arrayOfObject1	Object[]
    //   427	3	8	localInvocationTargetException1	InvocationTargetException
    //   310	5	9	localObject1	Object
    //   347	9	10	localMethod2	Method
    //   353	6	11	arrayOfObject2	Object[]
    //   451	3	12	localInvocationTargetException2	InvocationTargetException
    //   363	3	13	localObject2	Object
    //   397	9	14	localMethod3	Method
    //   403	6	15	arrayOfObject3	Object[]
    //   459	3	16	localInvocationTargetException3	InvocationTargetException
    //   413	3	17	localObject3	Object
    //   117	11	18	k	int
    //   224	9	19	localMethod4	Method
    //   230	6	20	arrayOfObject4	Object[]
    //   435	3	21	localInvocationTargetException4	InvocationTargetException
    //   240	3	22	localObject4	Object
    //   175	9	23	localMethod5	Method
    //   181	6	24	arrayOfObject5	Object[]
    //   443	3	25	localInvocationTargetException5	InvocationTargetException
    //   191	3	26	localObject5	Object
    //   53	9	27	localMethod6	Method
    //   59	6	28	arrayOfObject6	Object[]
    //   467	3	29	localInvocationTargetException6	InvocationTargetException
    //   69	3	30	localObject6	Object
    // Exception table:
    //   from	to	target	type
    //   302	312	427	java/lang/reflect/InvocationTargetException
    //   232	242	435	java/lang/reflect/InvocationTargetException
    //   183	193	443	java/lang/reflect/InvocationTargetException
    //   355	365	451	java/lang/reflect/InvocationTargetException
    //   405	415	459	java/lang/reflect/InvocationTargetException
    //   61	71	467	java/lang/reflect/InvocationTargetException
  }
  
  public static int b00750075u0075007500750075uu0075()
  {
    return 0;
  }
  
  public static int b0075u00750075007500750075uu0075()
  {
    return 1;
  }
  
  /* Error */
  private void b0075u0075uuuu0075u0075(DbError paramDbError, Bundle paramBundle)
  {
    // Byte code:
    //   0: ldc -64
    //   2: bipush 93
    //   4: sipush 158
    //   7: iconst_3
    //   8: invokestatic 132	xxxxxx/uxxxxx:bbbb0062b0062b0062b0062	(Ljava/lang/String;CCC)Ljava/lang/String;
    //   11: astore_3
    //   12: iconst_4
    //   13: anewarray 68	java/lang/Class
    //   16: astore 4
    //   18: aload 4
    //   20: iconst_0
    //   21: ldc 70
    //   23: aastore
    //   24: aload 4
    //   26: iconst_1
    //   27: getstatic 76	java/lang/Character:TYPE	Ljava/lang/Class;
    //   30: aastore
    //   31: aload 4
    //   33: iconst_2
    //   34: getstatic 76	java/lang/Character:TYPE	Ljava/lang/Class;
    //   37: aastore
    //   38: aload 4
    //   40: iconst_3
    //   41: getstatic 76	java/lang/Character:TYPE	Ljava/lang/Class;
    //   44: aastore
    //   45: ldc 78
    //   47: aload_3
    //   48: aload 4
    //   50: invokevirtual 82	java/lang/Class:getMethod	(Ljava/lang/String;[Ljava/lang/Class;)Ljava/lang/reflect/Method;
    //   53: astore 5
    //   55: iconst_4
    //   56: anewarray 84	java/lang/Object
    //   59: astore 6
    //   61: aload 6
    //   63: iconst_0
    //   64: ldc -62
    //   66: aastore
    //   67: aload 6
    //   69: iconst_1
    //   70: sipush 137
    //   73: invokestatic 90	java/lang/Character:valueOf	(C)Ljava/lang/Character;
    //   76: aastore
    //   77: aload 6
    //   79: iconst_2
    //   80: bipush 114
    //   82: invokestatic 90	java/lang/Character:valueOf	(C)Ljava/lang/Character;
    //   85: aastore
    //   86: aload 6
    //   88: iconst_3
    //   89: iconst_1
    //   90: invokestatic 90	java/lang/Character:valueOf	(C)Ljava/lang/Character;
    //   93: aastore
    //   94: aload 5
    //   96: aconst_null
    //   97: aload 6
    //   99: invokevirtual 96	java/lang/reflect/Method:invoke	(Ljava/lang/Object;[Ljava/lang/Object;)Ljava/lang/Object;
    //   102: astore 8
    //   104: aload_2
    //   105: aload 8
    //   107: checkcast 70	java/lang/String
    //   110: invokevirtual 102	android/os/Bundle:getString	(Ljava/lang/String;)Ljava/lang/String;
    //   113: astore 9
    //   115: aload_0
    //   116: getfield 42	uuuuuu/qmqqmm:b00760076v0076vv00760076v	Ljava/lang/String;
    //   119: aload 9
    //   121: invokevirtual 106	java/lang/String:equals	(Ljava/lang/Object;)Z
    //   124: ifne +4 -> 128
    //   127: return
    //   128: aload_0
    //   129: getfield 196	uuuuuu/qmqqmm:b0076v00760076vv00760076v	Luuuuuu/vxvvvx;
    //   132: aload_0
    //   133: getfield 42	uuuuuu/qmqqmm:b00760076v0076vv00760076v	Ljava/lang/String;
    //   136: invokevirtual 201	uuuuuu/vxvvvx:buuuuu00750075u00750075	(Ljava/lang/String;)V
    //   139: aload_0
    //   140: invokevirtual 205	uuuuuu/qmqqmm:bkk006Bk006Bk006Bk006Bk	()Z
    //   143: istore 10
    //   145: getstatic 108	uuuuuu/qmqqmm:b0076vvv0076v00760076v	I
    //   148: istore 11
    //   150: ldc 2
    //   152: ldc -49
    //   154: bipush 116
    //   156: iconst_5
    //   157: invokestatic 66	xxxxxx/uxxxxx:bb00620062bb0062b0062b0062	(Ljava/lang/String;CC)Ljava/lang/String;
    //   160: iconst_0
    //   161: anewarray 68	java/lang/Class
    //   164: invokevirtual 82	java/lang/Class:getMethod	(Ljava/lang/String;[Ljava/lang/Class;)Ljava/lang/reflect/Method;
    //   167: astore 12
    //   169: iconst_0
    //   170: anewarray 84	java/lang/Object
    //   173: astore 13
    //   175: aload 12
    //   177: aconst_null
    //   178: aload 13
    //   180: invokevirtual 96	java/lang/reflect/Method:invoke	(Ljava/lang/Object;[Ljava/lang/Object;)Ljava/lang/Object;
    //   183: astore 15
    //   185: iload 11
    //   187: aload 15
    //   189: checkcast 114	java/lang/Integer
    //   192: invokevirtual 118	java/lang/Integer:intValue	()I
    //   195: iadd
    //   196: getstatic 108	uuuuuu/qmqqmm:b0076vvv0076v00760076v	I
    //   199: imul
    //   200: getstatic 122	uuuuuu/qmqqmm:bvv0076v0076v00760076v	I
    //   203: irem
    //   204: getstatic 120	uuuuuu/qmqqmm:bv0076vv0076v00760076v	I
    //   207: if_icmpeq +55 -> 262
    //   210: ldc 2
    //   212: ldc -47
    //   214: sipush 182
    //   217: iconst_3
    //   218: invokestatic 66	xxxxxx/uxxxxx:bb00620062bb0062b0062b0062	(Ljava/lang/String;CC)Ljava/lang/String;
    //   221: iconst_0
    //   222: anewarray 68	java/lang/Class
    //   225: invokevirtual 82	java/lang/Class:getMethod	(Ljava/lang/String;[Ljava/lang/Class;)Ljava/lang/reflect/Method;
    //   228: astore 34
    //   230: iconst_0
    //   231: anewarray 84	java/lang/Object
    //   234: astore 35
    //   236: aload 34
    //   238: aconst_null
    //   239: aload 35
    //   241: invokevirtual 96	java/lang/reflect/Method:invoke	(Ljava/lang/Object;[Ljava/lang/Object;)Ljava/lang/Object;
    //   244: astore 37
    //   246: aload 37
    //   248: checkcast 114	java/lang/Integer
    //   251: invokevirtual 118	java/lang/Integer:intValue	()I
    //   254: putstatic 108	uuuuuu/qmqqmm:b0076vvv0076v00760076v	I
    //   257: bipush 67
    //   259: putstatic 120	uuuuuu/qmqqmm:bv0076vv0076v00760076v	I
    //   262: iload 10
    //   264: ifeq -137 -> 127
    //   267: aload_0
    //   268: getfield 152	uuuuuu/qmqqmm:bnnnnn006E006E006En	Luuuuuu/ttssst$tsssst;
    //   271: astore 16
    //   273: getstatic 108	uuuuuu/qmqqmm:b0076vvv0076v00760076v	I
    //   276: istore 17
    //   278: iload 17
    //   280: iload 17
    //   282: getstatic 110	uuuuuu/qmqqmm:b00760076vv0076v00760076v	I
    //   285: iadd
    //   286: imul
    //   287: getstatic 122	uuuuuu/qmqqmm:bvv0076v0076v00760076v	I
    //   290: irem
    //   291: tableswitch	default:+17->308, 0:+110->401
    //   308: ldc 2
    //   310: ldc -45
    //   312: bipush 25
    //   314: iconst_0
    //   315: invokestatic 66	xxxxxx/uxxxxx:bb00620062bb0062b0062b0062	(Ljava/lang/String;CC)Ljava/lang/String;
    //   318: iconst_0
    //   319: anewarray 68	java/lang/Class
    //   322: invokevirtual 82	java/lang/Class:getMethod	(Ljava/lang/String;[Ljava/lang/Class;)Ljava/lang/reflect/Method;
    //   325: astore 26
    //   327: iconst_0
    //   328: anewarray 84	java/lang/Object
    //   331: astore 27
    //   333: aload 26
    //   335: aconst_null
    //   336: aload 27
    //   338: invokevirtual 96	java/lang/reflect/Method:invoke	(Ljava/lang/Object;[Ljava/lang/Object;)Ljava/lang/Object;
    //   341: astore 29
    //   343: aload 29
    //   345: checkcast 114	java/lang/Integer
    //   348: invokevirtual 118	java/lang/Integer:intValue	()I
    //   351: putstatic 108	uuuuuu/qmqqmm:b0076vvv0076v00760076v	I
    //   354: ldc 2
    //   356: ldc -43
    //   358: sipush 176
    //   361: iconst_1
    //   362: invokestatic 66	xxxxxx/uxxxxx:bb00620062bb0062b0062b0062	(Ljava/lang/String;CC)Ljava/lang/String;
    //   365: iconst_0
    //   366: anewarray 68	java/lang/Class
    //   369: invokevirtual 82	java/lang/Class:getMethod	(Ljava/lang/String;[Ljava/lang/Class;)Ljava/lang/reflect/Method;
    //   372: astore 30
    //   374: iconst_0
    //   375: anewarray 84	java/lang/Object
    //   378: astore 31
    //   380: aload 30
    //   382: aconst_null
    //   383: aload 31
    //   385: invokevirtual 96	java/lang/reflect/Method:invoke	(Ljava/lang/Object;[Ljava/lang/Object;)Ljava/lang/Object;
    //   388: astore 33
    //   390: aload 33
    //   392: checkcast 114	java/lang/Integer
    //   395: invokevirtual 118	java/lang/Integer:intValue	()I
    //   398: putstatic 120	uuuuuu/qmqqmm:bv0076vv0076v00760076v	I
    //   401: aload 16
    //   403: checkcast 215	uuuuuu/mmmmqm$mqqqmm
    //   406: invokeinterface 218 1 0
    //   411: aload_0
    //   412: aload_1
    //   413: invokevirtual 222	uuuuuu/qmqqmm:boo006F006F006F006Fo006F006F006F	(Lcom/db/pwcc/dbmobile/model/error/DbError;)Z
    //   416: istore 18
    //   418: getstatic 108	uuuuuu/qmqqmm:b0076vvv0076v00760076v	I
    //   421: getstatic 110	uuuuuu/qmqqmm:b00760076vv0076v00760076v	I
    //   424: iadd
    //   425: getstatic 108	uuuuuu/qmqqmm:b0076vvv0076v00760076v	I
    //   428: imul
    //   429: getstatic 122	uuuuuu/qmqqmm:bvv0076v0076v00760076v	I
    //   432: irem
    //   433: getstatic 120	uuuuuu/qmqqmm:bv0076vv0076v00760076v	I
    //   436: if_icmpeq +87 -> 523
    //   439: getstatic 108	uuuuuu/qmqqmm:b0076vvv0076v00760076v	I
    //   442: getstatic 110	uuuuuu/qmqqmm:b00760076vv0076v00760076v	I
    //   445: iadd
    //   446: getstatic 108	uuuuuu/qmqqmm:b0076vvv0076v00760076v	I
    //   449: imul
    //   450: getstatic 122	uuuuuu/qmqqmm:bvv0076v0076v00760076v	I
    //   453: irem
    //   454: getstatic 120	uuuuuu/qmqqmm:bv0076vv0076v00760076v	I
    //   457: if_icmpeq +13 -> 470
    //   460: bipush 43
    //   462: putstatic 108	uuuuuu/qmqqmm:b0076vvv0076v00760076v	I
    //   465: bipush 60
    //   467: putstatic 120	uuuuuu/qmqqmm:bv0076vv0076v00760076v	I
    //   470: bipush 13
    //   472: putstatic 108	uuuuuu/qmqqmm:b0076vvv0076v00760076v	I
    //   475: ldc 2
    //   477: ldc -32
    //   479: bipush 14
    //   481: bipush 42
    //   483: iconst_2
    //   484: invokestatic 132	xxxxxx/uxxxxx:bbbb0062b0062b0062b0062	(Ljava/lang/String;CCC)Ljava/lang/String;
    //   487: iconst_0
    //   488: anewarray 68	java/lang/Class
    //   491: invokevirtual 82	java/lang/Class:getMethod	(Ljava/lang/String;[Ljava/lang/Class;)Ljava/lang/reflect/Method;
    //   494: astore 22
    //   496: iconst_0
    //   497: anewarray 84	java/lang/Object
    //   500: astore 23
    //   502: aload 22
    //   504: aconst_null
    //   505: aload 23
    //   507: invokevirtual 96	java/lang/reflect/Method:invoke	(Ljava/lang/Object;[Ljava/lang/Object;)Ljava/lang/Object;
    //   510: astore 25
    //   512: aload 25
    //   514: checkcast 114	java/lang/Integer
    //   517: invokevirtual 118	java/lang/Integer:intValue	()I
    //   520: putstatic 120	uuuuuu/qmqqmm:bv0076vv0076v00760076v	I
    //   523: iload 18
    //   525: ifeq +69 -> 594
    //   528: aload_0
    //   529: aload_1
    //   530: invokevirtual 230	com/db/pwcc/dbmobile/model/error/DbError:getDbCode	()Lcom/db/pwcc/dbmobile/model/error/DbErrorCode;
    //   533: invokevirtual 234	uuuuuu/qmqqmm:bo006Fo006F006F006Fo006F006F006F	(Lcom/db/pwcc/dbmobile/model/error/DbErrorCode;)V
    //   536: aload_0
    //   537: getfield 152	uuuuuu/qmqqmm:bnnnnn006E006E006En	Luuuuuu/ttssst$tsssst;
    //   540: checkcast 215	uuuuuu/mmmmqm$mqqqmm
    //   543: astore 19
    //   545: aload_0
    //   546: getfield 42	uuuuuu/qmqqmm:b00760076v0076vv00760076v	Ljava/lang/String;
    //   549: astore 20
    //   551: aload_1
    //   552: ifnonnull +75 -> 627
    //   555: iconst_1
    //   556: istore 21
    //   558: aload 19
    //   560: aload 20
    //   562: iload 21
    //   564: invokeinterface 238 3 0
    //   569: return
    //   570: astore 24
    //   572: aload 24
    //   574: invokevirtual 138	java/lang/reflect/InvocationTargetException:getCause	()Ljava/lang/Throwable;
    //   577: athrow
    //   578: astore 28
    //   580: aload 28
    //   582: invokevirtual 138	java/lang/reflect/InvocationTargetException:getCause	()Ljava/lang/Throwable;
    //   585: athrow
    //   586: astore 32
    //   588: aload 32
    //   590: invokevirtual 138	java/lang/reflect/InvocationTargetException:getCause	()Ljava/lang/Throwable;
    //   593: athrow
    //   594: aload_1
    //   595: ifnull -59 -> 536
    //   598: aload_0
    //   599: getfield 152	uuuuuu/qmqqmm:bnnnnn006E006E006En	Luuuuuu/ttssst$tsssst;
    //   602: checkcast 215	uuuuuu/mmmmqm$mqqqmm
    //   605: getstatic 243	com/db/pwcc/dbmobile/multi_bank_aggregator/R$string:mba_delete_institute_error_title	I
    //   608: getstatic 246	com/db/pwcc/dbmobile/multi_bank_aggregator/R$string:mba_delete_institute_error_message	I
    //   611: invokeinterface 250 3 0
    //   616: goto -80 -> 536
    //   619: astore 36
    //   621: aload 36
    //   623: invokevirtual 138	java/lang/reflect/InvocationTargetException:getCause	()Ljava/lang/Throwable;
    //   626: athrow
    //   627: iconst_0
    //   628: istore 21
    //   630: goto -72 -> 558
    //   633: astore 14
    //   635: aload 14
    //   637: invokevirtual 138	java/lang/reflect/InvocationTargetException:getCause	()Ljava/lang/Throwable;
    //   640: athrow
    //   641: astore 7
    //   643: aload 7
    //   645: invokevirtual 138	java/lang/reflect/InvocationTargetException:getCause	()Ljava/lang/Throwable;
    //   648: athrow
    // Local variable table:
    //   start	length	slot	name	signature
    //   0	649	0	this	qmqqmm
    //   0	649	1	paramDbError	DbError
    //   0	649	2	paramBundle	Bundle
    //   11	37	3	str1	String
    //   16	33	4	arrayOfClass	Class[]
    //   53	42	5	localMethod1	Method
    //   59	39	6	arrayOfObject1	Object[]
    //   641	3	7	localInvocationTargetException1	InvocationTargetException
    //   102	4	8	localObject1	Object
    //   113	7	9	str2	String
    //   143	120	10	bool1	boolean
    //   148	48	11	i	int
    //   167	9	12	localMethod2	Method
    //   173	6	13	arrayOfObject2	Object[]
    //   633	3	14	localInvocationTargetException2	InvocationTargetException
    //   183	5	15	localObject2	Object
    //   271	131	16	localTsssst	ttssst.tsssst
    //   276	11	17	j	int
    //   416	108	18	bool2	boolean
    //   543	16	19	localMqqqmm	mmmmqm.mqqqmm
    //   549	12	20	str3	String
    //   556	73	21	bool3	boolean
    //   494	9	22	localMethod3	Method
    //   500	6	23	arrayOfObject3	Object[]
    //   570	3	24	localInvocationTargetException3	InvocationTargetException
    //   510	3	25	localObject3	Object
    //   325	9	26	localMethod4	Method
    //   331	6	27	arrayOfObject4	Object[]
    //   578	3	28	localInvocationTargetException4	InvocationTargetException
    //   341	3	29	localObject4	Object
    //   372	9	30	localMethod5	Method
    //   378	6	31	arrayOfObject5	Object[]
    //   586	3	32	localInvocationTargetException5	InvocationTargetException
    //   388	3	33	localObject5	Object
    //   228	9	34	localMethod6	Method
    //   234	6	35	arrayOfObject6	Object[]
    //   619	3	36	localInvocationTargetException6	InvocationTargetException
    //   244	3	37	localObject6	Object
    // Exception table:
    //   from	to	target	type
    //   502	512	570	java/lang/reflect/InvocationTargetException
    //   333	343	578	java/lang/reflect/InvocationTargetException
    //   380	390	586	java/lang/reflect/InvocationTargetException
    //   236	246	619	java/lang/reflect/InvocationTargetException
    //   175	185	633	java/lang/reflect/InvocationTargetException
    //   94	104	641	java/lang/reflect/InvocationTargetException
  }
  
  public static int bu007500750075007500750075uu0075()
  {
    return 93;
  }
  
  /* Error */
  private void bu00750075uuuu0075u0075()
  {
    // Byte code:
    //   0: getstatic 313	uuuuuu/vvrvrv:b00680068hh0068hh00680068	Luuuuuu/vvrvrv;
    //   3: astore_1
    //   4: getstatic 108	uuuuuu/qmqqmm:b0076vvv0076v00760076v	I
    //   7: istore_2
    //   8: iload_2
    //   9: iload_2
    //   10: getstatic 110	uuuuuu/qmqqmm:b00760076vv0076v00760076v	I
    //   13: iadd
    //   14: imul
    //   15: getstatic 122	uuuuuu/qmqqmm:bvv0076v0076v00760076v	I
    //   18: irem
    //   19: tableswitch	default:+17->36, 0:+73->92
    //   36: ldc 2
    //   38: ldc_w 315
    //   41: sipush 234
    //   44: sipush 228
    //   47: iconst_2
    //   48: invokestatic 132	xxxxxx/uxxxxx:bbbb0062b0062b0062b0062	(Ljava/lang/String;CCC)Ljava/lang/String;
    //   51: iconst_0
    //   52: anewarray 68	java/lang/Class
    //   55: invokevirtual 82	java/lang/Class:getMethod	(Ljava/lang/String;[Ljava/lang/Class;)Ljava/lang/reflect/Method;
    //   58: astore 22
    //   60: iconst_0
    //   61: anewarray 84	java/lang/Object
    //   64: astore 23
    //   66: aload 22
    //   68: aconst_null
    //   69: aload 23
    //   71: invokevirtual 96	java/lang/reflect/Method:invoke	(Ljava/lang/Object;[Ljava/lang/Object;)Ljava/lang/Object;
    //   74: astore 25
    //   76: aload 25
    //   78: checkcast 114	java/lang/Integer
    //   81: invokevirtual 118	java/lang/Integer:intValue	()I
    //   84: putstatic 108	uuuuuu/qmqqmm:b0076vvv0076v00760076v	I
    //   87: bipush 13
    //   89: putstatic 120	uuuuuu/qmqqmm:bv0076vv0076v00760076v	I
    //   92: getstatic 108	uuuuuu/qmqqmm:b0076vvv0076v00760076v	I
    //   95: istore_3
    //   96: iload_3
    //   97: iload_3
    //   98: getstatic 110	uuuuuu/qmqqmm:b00760076vv0076v00760076v	I
    //   101: iadd
    //   102: imul
    //   103: getstatic 122	uuuuuu/qmqqmm:bvv0076v0076v00760076v	I
    //   106: irem
    //   107: tableswitch	default:+17->124, 0:+188->295
    //   124: getstatic 108	uuuuuu/qmqqmm:b0076vvv0076v00760076v	I
    //   127: getstatic 110	uuuuuu/qmqqmm:b00760076vv0076v00760076v	I
    //   130: iadd
    //   131: getstatic 108	uuuuuu/qmqqmm:b0076vvv0076v00760076v	I
    //   134: imul
    //   135: getstatic 122	uuuuuu/qmqqmm:bvv0076v0076v00760076v	I
    //   138: irem
    //   139: getstatic 120	uuuuuu/qmqqmm:bv0076vv0076v00760076v	I
    //   142: if_icmpeq +58 -> 200
    //   145: ldc 2
    //   147: ldc_w 317
    //   150: sipush 161
    //   153: bipush 69
    //   155: iconst_2
    //   156: invokestatic 132	xxxxxx/uxxxxx:bbbb0062b0062b0062b0062	(Ljava/lang/String;CCC)Ljava/lang/String;
    //   159: iconst_0
    //   160: anewarray 68	java/lang/Class
    //   163: invokevirtual 82	java/lang/Class:getMethod	(Ljava/lang/String;[Ljava/lang/Class;)Ljava/lang/reflect/Method;
    //   166: astore 18
    //   168: iconst_0
    //   169: anewarray 84	java/lang/Object
    //   172: astore 19
    //   174: aload 18
    //   176: aconst_null
    //   177: aload 19
    //   179: invokevirtual 96	java/lang/reflect/Method:invoke	(Ljava/lang/Object;[Ljava/lang/Object;)Ljava/lang/Object;
    //   182: astore 21
    //   184: aload 21
    //   186: checkcast 114	java/lang/Integer
    //   189: invokevirtual 118	java/lang/Integer:intValue	()I
    //   192: putstatic 108	uuuuuu/qmqqmm:b0076vvv0076v00760076v	I
    //   195: bipush 66
    //   197: putstatic 120	uuuuuu/qmqqmm:bv0076vv0076v00760076v	I
    //   200: ldc 2
    //   202: ldc_w 319
    //   205: bipush 78
    //   207: iconst_1
    //   208: invokestatic 66	xxxxxx/uxxxxx:bb00620062bb0062b0062b0062	(Ljava/lang/String;CC)Ljava/lang/String;
    //   211: iconst_0
    //   212: anewarray 68	java/lang/Class
    //   215: invokevirtual 82	java/lang/Class:getMethod	(Ljava/lang/String;[Ljava/lang/Class;)Ljava/lang/reflect/Method;
    //   218: astore 10
    //   220: iconst_0
    //   221: anewarray 84	java/lang/Object
    //   224: astore 11
    //   226: aload 10
    //   228: aconst_null
    //   229: aload 11
    //   231: invokevirtual 96	java/lang/reflect/Method:invoke	(Ljava/lang/Object;[Ljava/lang/Object;)Ljava/lang/Object;
    //   234: astore 13
    //   236: aload 13
    //   238: checkcast 114	java/lang/Integer
    //   241: invokevirtual 118	java/lang/Integer:intValue	()I
    //   244: putstatic 108	uuuuuu/qmqqmm:b0076vvv0076v00760076v	I
    //   247: ldc 2
    //   249: ldc_w 321
    //   252: sipush 199
    //   255: iconst_4
    //   256: invokestatic 66	xxxxxx/uxxxxx:bb00620062bb0062b0062b0062	(Ljava/lang/String;CC)Ljava/lang/String;
    //   259: iconst_0
    //   260: anewarray 68	java/lang/Class
    //   263: invokevirtual 82	java/lang/Class:getMethod	(Ljava/lang/String;[Ljava/lang/Class;)Ljava/lang/reflect/Method;
    //   266: astore 14
    //   268: iconst_0
    //   269: anewarray 84	java/lang/Object
    //   272: astore 15
    //   274: aload 14
    //   276: aconst_null
    //   277: aload 15
    //   279: invokevirtual 96	java/lang/reflect/Method:invoke	(Ljava/lang/Object;[Ljava/lang/Object;)Ljava/lang/Object;
    //   282: astore 17
    //   284: aload 17
    //   286: checkcast 114	java/lang/Integer
    //   289: invokevirtual 118	java/lang/Integer:intValue	()I
    //   292: putstatic 120	uuuuuu/qmqqmm:bv0076vv0076v00760076v	I
    //   295: aload_1
    //   296: invokestatic 327	uuuuuu/rrvvrv:b0071q0071qq0071q0071q0071	(Luuuuuu/vvrvrv;)V
    //   299: getstatic 330	uuuuuu/vvrvrv:bhh0068h0068hh00680068	Luuuuuu/vvrvrv;
    //   302: astore 4
    //   304: getstatic 108	uuuuuu/qmqqmm:b0076vvv0076v00760076v	I
    //   307: istore 5
    //   309: iload 5
    //   311: iload 5
    //   313: getstatic 110	uuuuuu/qmqqmm:b00760076vv0076v00760076v	I
    //   316: iadd
    //   317: imul
    //   318: getstatic 122	uuuuuu/qmqqmm:bvv0076v0076v00760076v	I
    //   321: irem
    //   322: tableswitch	default:+18->340, 0:+72->394
    //   340: iconst_5
    //   341: putstatic 108	uuuuuu/qmqqmm:b0076vvv0076v00760076v	I
    //   344: ldc 2
    //   346: ldc_w 332
    //   349: bipush 7
    //   351: sipush 197
    //   354: iconst_2
    //   355: invokestatic 132	xxxxxx/uxxxxx:bbbb0062b0062b0062b0062	(Ljava/lang/String;CCC)Ljava/lang/String;
    //   358: iconst_0
    //   359: anewarray 68	java/lang/Class
    //   362: invokevirtual 82	java/lang/Class:getMethod	(Ljava/lang/String;[Ljava/lang/Class;)Ljava/lang/reflect/Method;
    //   365: astore 6
    //   367: iconst_0
    //   368: anewarray 84	java/lang/Object
    //   371: astore 7
    //   373: aload 6
    //   375: aconst_null
    //   376: aload 7
    //   378: invokevirtual 96	java/lang/reflect/Method:invoke	(Ljava/lang/Object;[Ljava/lang/Object;)Ljava/lang/Object;
    //   381: astore 9
    //   383: aload 9
    //   385: checkcast 114	java/lang/Integer
    //   388: invokevirtual 118	java/lang/Integer:intValue	()I
    //   391: putstatic 120	uuuuuu/qmqqmm:bv0076vv0076v00760076v	I
    //   394: aload 4
    //   396: invokestatic 327	uuuuuu/rrvvrv:b0071q0071qq0071q0071q0071	(Luuuuuu/vvrvrv;)V
    //   399: return
    //   400: astore 16
    //   402: aload 16
    //   404: invokevirtual 138	java/lang/reflect/InvocationTargetException:getCause	()Ljava/lang/Throwable;
    //   407: athrow
    //   408: astore 12
    //   410: aload 12
    //   412: invokevirtual 138	java/lang/reflect/InvocationTargetException:getCause	()Ljava/lang/Throwable;
    //   415: athrow
    //   416: astore 20
    //   418: aload 20
    //   420: invokevirtual 138	java/lang/reflect/InvocationTargetException:getCause	()Ljava/lang/Throwable;
    //   423: athrow
    //   424: astore 8
    //   426: aload 8
    //   428: invokevirtual 138	java/lang/reflect/InvocationTargetException:getCause	()Ljava/lang/Throwable;
    //   431: athrow
    //   432: astore 24
    //   434: aload 24
    //   436: invokevirtual 138	java/lang/reflect/InvocationTargetException:getCause	()Ljava/lang/Throwable;
    //   439: athrow
    // Local variable table:
    //   start	length	slot	name	signature
    //   0	440	0	this	qmqqmm
    //   3	293	1	localVvrvrv1	vvrvrv
    //   7	8	2	i	int
    //   95	8	3	j	int
    //   302	93	4	localVvrvrv2	vvrvrv
    //   307	11	5	k	int
    //   365	9	6	localMethod1	Method
    //   371	6	7	arrayOfObject1	Object[]
    //   424	3	8	localInvocationTargetException1	InvocationTargetException
    //   381	3	9	localObject1	Object
    //   218	9	10	localMethod2	Method
    //   224	6	11	arrayOfObject2	Object[]
    //   408	3	12	localInvocationTargetException2	InvocationTargetException
    //   234	3	13	localObject2	Object
    //   266	9	14	localMethod3	Method
    //   272	6	15	arrayOfObject3	Object[]
    //   400	3	16	localInvocationTargetException3	InvocationTargetException
    //   282	3	17	localObject3	Object
    //   166	9	18	localMethod4	Method
    //   172	6	19	arrayOfObject4	Object[]
    //   416	3	20	localInvocationTargetException4	InvocationTargetException
    //   182	3	21	localObject4	Object
    //   58	9	22	localMethod5	Method
    //   64	6	23	arrayOfObject5	Object[]
    //   432	3	24	localInvocationTargetException5	InvocationTargetException
    //   74	3	25	localObject5	Object
    // Exception table:
    //   from	to	target	type
    //   274	284	400	java/lang/reflect/InvocationTargetException
    //   226	236	408	java/lang/reflect/InvocationTargetException
    //   174	184	416	java/lang/reflect/InvocationTargetException
    //   373	383	424	java/lang/reflect/InvocationTargetException
    //   66	76	432	java/lang/reflect/InvocationTargetException
  }
  
  public static int buu00750075007500750075uu0075()
  {
    return 2;
  }
  
  /* Error */
  public void b0075007500750075u00750075uu0075(int paramInt)
  {
    // Byte code:
    //   0: getstatic 108	uuuuuu/qmqqmm:b0076vvv0076v00760076v	I
    //   3: getstatic 110	uuuuuu/qmqqmm:b00760076vv0076v00760076v	I
    //   6: iadd
    //   7: getstatic 108	uuuuuu/qmqqmm:b0076vvv0076v00760076v	I
    //   10: imul
    //   11: getstatic 122	uuuuuu/qmqqmm:bvv0076v0076v00760076v	I
    //   14: irem
    //   15: getstatic 120	uuuuuu/qmqqmm:bv0076vv0076v00760076v	I
    //   18: if_icmpeq +101 -> 119
    //   21: ldc 2
    //   23: ldc_w 362
    //   26: sipush 255
    //   29: iconst_0
    //   30: invokestatic 66	xxxxxx/uxxxxx:bb00620062bb0062b0062b0062	(Ljava/lang/String;CC)Ljava/lang/String;
    //   33: iconst_0
    //   34: anewarray 68	java/lang/Class
    //   37: invokevirtual 82	java/lang/Class:getMethod	(Ljava/lang/String;[Ljava/lang/Class;)Ljava/lang/reflect/Method;
    //   40: astore 21
    //   42: iconst_0
    //   43: anewarray 84	java/lang/Object
    //   46: astore 22
    //   48: aload 21
    //   50: aconst_null
    //   51: aload 22
    //   53: invokevirtual 96	java/lang/reflect/Method:invoke	(Ljava/lang/Object;[Ljava/lang/Object;)Ljava/lang/Object;
    //   56: astore 24
    //   58: aload 24
    //   60: checkcast 114	java/lang/Integer
    //   63: invokevirtual 118	java/lang/Integer:intValue	()I
    //   66: putstatic 108	uuuuuu/qmqqmm:b0076vvv0076v00760076v	I
    //   69: ldc 2
    //   71: ldc_w 364
    //   74: bipush 76
    //   76: sipush 180
    //   79: iconst_3
    //   80: invokestatic 132	xxxxxx/uxxxxx:bbbb0062b0062b0062b0062	(Ljava/lang/String;CCC)Ljava/lang/String;
    //   83: iconst_0
    //   84: anewarray 68	java/lang/Class
    //   87: invokevirtual 82	java/lang/Class:getMethod	(Ljava/lang/String;[Ljava/lang/Class;)Ljava/lang/reflect/Method;
    //   90: astore 25
    //   92: iconst_0
    //   93: anewarray 84	java/lang/Object
    //   96: astore 26
    //   98: aload 25
    //   100: aconst_null
    //   101: aload 26
    //   103: invokevirtual 96	java/lang/reflect/Method:invoke	(Ljava/lang/Object;[Ljava/lang/Object;)Ljava/lang/Object;
    //   106: astore 28
    //   108: aload 28
    //   110: checkcast 114	java/lang/Integer
    //   113: invokevirtual 118	java/lang/Integer:intValue	()I
    //   116: putstatic 120	uuuuuu/qmqqmm:bv0076vv0076v00760076v	I
    //   119: iload_1
    //   120: bipush 35
    //   122: if_icmpeq +99 -> 221
    //   125: iload_1
    //   126: bipush 37
    //   128: if_icmpeq +93 -> 221
    //   131: getstatic 108	uuuuuu/qmqqmm:b0076vvv0076v00760076v	I
    //   134: istore 16
    //   136: iload 16
    //   138: iload 16
    //   140: getstatic 110	uuuuuu/qmqqmm:b00760076vv0076v00760076v	I
    //   143: iadd
    //   144: imul
    //   145: getstatic 122	uuuuuu/qmqqmm:bvv0076v0076v00760076v	I
    //   148: irem
    //   149: tableswitch	default:+19->168, 0:+71->220
    //   168: bipush 87
    //   170: putstatic 108	uuuuuu/qmqqmm:b0076vvv0076v00760076v	I
    //   173: ldc 2
    //   175: ldc_w 366
    //   178: bipush 35
    //   180: iconst_2
    //   181: invokestatic 66	xxxxxx/uxxxxx:bb00620062bb0062b0062b0062	(Ljava/lang/String;CC)Ljava/lang/String;
    //   184: iconst_0
    //   185: anewarray 68	java/lang/Class
    //   188: invokevirtual 82	java/lang/Class:getMethod	(Ljava/lang/String;[Ljava/lang/Class;)Ljava/lang/reflect/Method;
    //   191: astore 17
    //   193: iconst_0
    //   194: anewarray 84	java/lang/Object
    //   197: astore 18
    //   199: aload 17
    //   201: aconst_null
    //   202: aload 18
    //   204: invokevirtual 96	java/lang/reflect/Method:invoke	(Ljava/lang/Object;[Ljava/lang/Object;)Ljava/lang/Object;
    //   207: astore 20
    //   209: aload 20
    //   211: checkcast 114	java/lang/Integer
    //   214: invokevirtual 118	java/lang/Integer:intValue	()I
    //   217: putstatic 120	uuuuuu/qmqqmm:bv0076vv0076v00760076v	I
    //   220: return
    //   221: aload_0
    //   222: getfield 196	uuuuuu/qmqqmm:b0076v00760076vv00760076v	Luuuuuu/vxvvvx;
    //   225: invokevirtual 370	uuuuuu/vxvvvx:buuuu007500750075u00750075	()Luuuuuu/xxxvvx;
    //   228: astore_2
    //   229: aload_2
    //   230: invokevirtual 376	uuuuuu/xxxvvx:buu00750075u0075uu00750075	()Ljava/util/Set;
    //   233: astore_3
    //   234: getstatic 108	uuuuuu/qmqqmm:b0076vvv0076v00760076v	I
    //   237: getstatic 110	uuuuuu/qmqqmm:b00760076vv0076v00760076v	I
    //   240: iadd
    //   241: getstatic 108	uuuuuu/qmqqmm:b0076vvv0076v00760076v	I
    //   244: imul
    //   245: getstatic 122	uuuuuu/qmqqmm:bvv0076v0076v00760076v	I
    //   248: irem
    //   249: getstatic 120	uuuuuu/qmqqmm:bv0076vv0076v00760076v	I
    //   252: if_icmpeq +13 -> 265
    //   255: bipush 91
    //   257: putstatic 108	uuuuuu/qmqqmm:b0076vvv0076v00760076v	I
    //   260: bipush 19
    //   262: putstatic 120	uuuuuu/qmqqmm:bv0076vv0076v00760076v	I
    //   265: aload_3
    //   266: aload_0
    //   267: getfield 42	uuuuuu/qmqqmm:b00760076v0076vv00760076v	Ljava/lang/String;
    //   270: invokeinterface 381 2 0
    //   275: ifne +19 -> 294
    //   278: aload_2
    //   279: invokevirtual 384	uuuuuu/xxxvvx:bu0075u0075u0075uu00750075	()Ljava/util/Set;
    //   282: aload_0
    //   283: getfield 42	uuuuuu/qmqqmm:b00760076v0076vv00760076v	Ljava/lang/String;
    //   286: invokeinterface 381 2 0
    //   291: ifeq -71 -> 220
    //   294: ldc 2
    //   296: ldc_w 386
    //   299: bipush 17
    //   301: sipush 173
    //   304: iconst_2
    //   305: invokestatic 132	xxxxxx/uxxxxx:bbbb0062b0062b0062b0062	(Ljava/lang/String;CCC)Ljava/lang/String;
    //   308: iconst_0
    //   309: anewarray 68	java/lang/Class
    //   312: invokevirtual 82	java/lang/Class:getMethod	(Ljava/lang/String;[Ljava/lang/Class;)Ljava/lang/reflect/Method;
    //   315: astore 4
    //   317: iconst_0
    //   318: anewarray 84	java/lang/Object
    //   321: astore 5
    //   323: aload 4
    //   325: aload_0
    //   326: aload 5
    //   328: invokevirtual 96	java/lang/reflect/Method:invoke	(Ljava/lang/Object;[Ljava/lang/Object;)Ljava/lang/Object;
    //   331: pop
    //   332: getstatic 108	uuuuuu/qmqqmm:b0076vvv0076v00760076v	I
    //   335: getstatic 110	uuuuuu/qmqqmm:b00760076vv0076v00760076v	I
    //   338: iadd
    //   339: getstatic 108	uuuuuu/qmqqmm:b0076vvv0076v00760076v	I
    //   342: imul
    //   343: getstatic 122	uuuuuu/qmqqmm:bvv0076v0076v00760076v	I
    //   346: irem
    //   347: getstatic 120	uuuuuu/qmqqmm:bv0076vv0076v00760076v	I
    //   350: if_icmpeq -130 -> 220
    //   353: ldc 2
    //   355: ldc_w 388
    //   358: sipush 182
    //   361: iconst_4
    //   362: invokestatic 66	xxxxxx/uxxxxx:bb00620062bb0062b0062b0062	(Ljava/lang/String;CC)Ljava/lang/String;
    //   365: iconst_0
    //   366: anewarray 68	java/lang/Class
    //   369: invokevirtual 82	java/lang/Class:getMethod	(Ljava/lang/String;[Ljava/lang/Class;)Ljava/lang/reflect/Method;
    //   372: astore 8
    //   374: iconst_0
    //   375: anewarray 84	java/lang/Object
    //   378: astore 9
    //   380: aload 8
    //   382: aconst_null
    //   383: aload 9
    //   385: invokevirtual 96	java/lang/reflect/Method:invoke	(Ljava/lang/Object;[Ljava/lang/Object;)Ljava/lang/Object;
    //   388: astore 11
    //   390: aload 11
    //   392: checkcast 114	java/lang/Integer
    //   395: invokevirtual 118	java/lang/Integer:intValue	()I
    //   398: putstatic 108	uuuuuu/qmqqmm:b0076vvv0076v00760076v	I
    //   401: ldc 2
    //   403: ldc_w 390
    //   406: bipush 68
    //   408: bipush 127
    //   410: iconst_1
    //   411: invokestatic 132	xxxxxx/uxxxxx:bbbb0062b0062b0062b0062	(Ljava/lang/String;CCC)Ljava/lang/String;
    //   414: iconst_0
    //   415: anewarray 68	java/lang/Class
    //   418: invokevirtual 82	java/lang/Class:getMethod	(Ljava/lang/String;[Ljava/lang/Class;)Ljava/lang/reflect/Method;
    //   421: astore 12
    //   423: iconst_0
    //   424: anewarray 84	java/lang/Object
    //   427: astore 13
    //   429: aload 12
    //   431: aconst_null
    //   432: aload 13
    //   434: invokevirtual 96	java/lang/reflect/Method:invoke	(Ljava/lang/Object;[Ljava/lang/Object;)Ljava/lang/Object;
    //   437: astore 15
    //   439: aload 15
    //   441: checkcast 114	java/lang/Integer
    //   444: invokevirtual 118	java/lang/Integer:intValue	()I
    //   447: putstatic 120	uuuuuu/qmqqmm:bv0076vv0076v00760076v	I
    //   450: return
    //   451: astore 14
    //   453: aload 14
    //   455: invokevirtual 138	java/lang/reflect/InvocationTargetException:getCause	()Ljava/lang/Throwable;
    //   458: athrow
    //   459: astore 10
    //   461: aload 10
    //   463: invokevirtual 138	java/lang/reflect/InvocationTargetException:getCause	()Ljava/lang/Throwable;
    //   466: athrow
    //   467: astore 6
    //   469: aload 6
    //   471: invokevirtual 138	java/lang/reflect/InvocationTargetException:getCause	()Ljava/lang/Throwable;
    //   474: athrow
    //   475: astore 19
    //   477: aload 19
    //   479: invokevirtual 138	java/lang/reflect/InvocationTargetException:getCause	()Ljava/lang/Throwable;
    //   482: athrow
    //   483: astore 23
    //   485: aload 23
    //   487: invokevirtual 138	java/lang/reflect/InvocationTargetException:getCause	()Ljava/lang/Throwable;
    //   490: athrow
    //   491: astore 27
    //   493: aload 27
    //   495: invokevirtual 138	java/lang/reflect/InvocationTargetException:getCause	()Ljava/lang/Throwable;
    //   498: athrow
    // Local variable table:
    //   start	length	slot	name	signature
    //   0	499	0	this	qmqqmm
    //   0	499	1	paramInt	int
    //   228	51	2	localXxxvvx	xxxvvx
    //   233	33	3	localSet	java.util.Set
    //   315	9	4	localMethod1	Method
    //   321	6	5	arrayOfObject1	Object[]
    //   467	3	6	localInvocationTargetException1	InvocationTargetException
    //   372	9	8	localMethod2	Method
    //   378	6	9	arrayOfObject2	Object[]
    //   459	3	10	localInvocationTargetException2	InvocationTargetException
    //   388	3	11	localObject1	Object
    //   421	9	12	localMethod3	Method
    //   427	6	13	arrayOfObject3	Object[]
    //   451	3	14	localInvocationTargetException3	InvocationTargetException
    //   437	3	15	localObject2	Object
    //   134	11	16	i	int
    //   191	9	17	localMethod4	Method
    //   197	6	18	arrayOfObject4	Object[]
    //   475	3	19	localInvocationTargetException4	InvocationTargetException
    //   207	3	20	localObject3	Object
    //   40	9	21	localMethod5	Method
    //   46	6	22	arrayOfObject5	Object[]
    //   483	3	23	localInvocationTargetException5	InvocationTargetException
    //   56	3	24	localObject4	Object
    //   90	9	25	localMethod6	Method
    //   96	6	26	arrayOfObject6	Object[]
    //   491	3	27	localInvocationTargetException6	InvocationTargetException
    //   106	3	28	localObject5	Object
    // Exception table:
    //   from	to	target	type
    //   429	439	451	java/lang/reflect/InvocationTargetException
    //   380	390	459	java/lang/reflect/InvocationTargetException
    //   323	332	467	java/lang/reflect/InvocationTargetException
    //   199	209	475	java/lang/reflect/InvocationTargetException
    //   48	58	483	java/lang/reflect/InvocationTargetException
    //   98	108	491	java/lang/reflect/InvocationTargetException
  }
  
  /* Error */
  public void b00750075u0075u00750075uu0075()
  {
    // Byte code:
    //   0: getstatic 108	uuuuuu/qmqqmm:b0076vvv0076v00760076v	I
    //   3: getstatic 110	uuuuuu/qmqqmm:b00760076vv0076v00760076v	I
    //   6: iadd
    //   7: getstatic 108	uuuuuu/qmqqmm:b0076vvv0076v00760076v	I
    //   10: imul
    //   11: istore_1
    //   12: ldc 2
    //   14: ldc_w 393
    //   17: sipush 168
    //   20: iconst_5
    //   21: invokestatic 66	xxxxxx/uxxxxx:bb00620062bb0062b0062b0062	(Ljava/lang/String;CC)Ljava/lang/String;
    //   24: iconst_0
    //   25: anewarray 68	java/lang/Class
    //   28: invokevirtual 82	java/lang/Class:getMethod	(Ljava/lang/String;[Ljava/lang/Class;)Ljava/lang/reflect/Method;
    //   31: astore_2
    //   32: iconst_0
    //   33: anewarray 84	java/lang/Object
    //   36: astore_3
    //   37: aload_2
    //   38: aconst_null
    //   39: aload_3
    //   40: invokevirtual 96	java/lang/reflect/Method:invoke	(Ljava/lang/Object;[Ljava/lang/Object;)Ljava/lang/Object;
    //   43: astore 5
    //   45: iload_1
    //   46: aload 5
    //   48: checkcast 114	java/lang/Integer
    //   51: invokevirtual 118	java/lang/Integer:intValue	()I
    //   54: irem
    //   55: getstatic 120	uuuuuu/qmqqmm:bv0076vv0076v00760076v	I
    //   58: if_icmpeq +58 -> 116
    //   61: ldc 2
    //   63: ldc_w 395
    //   66: bipush 92
    //   68: sipush 226
    //   71: iconst_1
    //   72: invokestatic 132	xxxxxx/uxxxxx:bbbb0062b0062b0062b0062	(Ljava/lang/String;CCC)Ljava/lang/String;
    //   75: iconst_0
    //   76: anewarray 68	java/lang/Class
    //   79: invokevirtual 82	java/lang/Class:getMethod	(Ljava/lang/String;[Ljava/lang/Class;)Ljava/lang/reflect/Method;
    //   82: astore 36
    //   84: iconst_0
    //   85: anewarray 84	java/lang/Object
    //   88: astore 37
    //   90: aload 36
    //   92: aconst_null
    //   93: aload 37
    //   95: invokevirtual 96	java/lang/reflect/Method:invoke	(Ljava/lang/Object;[Ljava/lang/Object;)Ljava/lang/Object;
    //   98: astore 39
    //   100: aload 39
    //   102: checkcast 114	java/lang/Integer
    //   105: invokevirtual 118	java/lang/Integer:intValue	()I
    //   108: putstatic 108	uuuuuu/qmqqmm:b0076vvv0076v00760076v	I
    //   111: bipush 63
    //   113: putstatic 120	uuuuuu/qmqqmm:bv0076vv0076v00760076v	I
    //   116: aload_0
    //   117: getfield 196	uuuuuu/qmqqmm:b0076v00760076vv00760076v	Luuuuuu/vxvvvx;
    //   120: invokevirtual 398	uuuuuu/vxvvvx:bu0075u0075007500750075u00750075	()Z
    //   123: ifeq +23 -> 146
    //   126: aload_0
    //   127: invokevirtual 205	uuuuuu/qmqqmm:bkk006Bk006Bk006Bk006Bk	()Z
    //   130: ifeq +15 -> 145
    //   133: aload_0
    //   134: getfield 152	uuuuuu/qmqqmm:bnnnnn006E006E006En	Luuuuuu/ttssst$tsssst;
    //   137: checkcast 215	uuuuuu/mmmmqm$mqqqmm
    //   140: invokeinterface 401 1 0
    //   145: return
    //   146: getstatic 108	uuuuuu/qmqqmm:b0076vvv0076v00760076v	I
    //   149: istore 6
    //   151: ldc 2
    //   153: ldc_w 403
    //   156: sipush 138
    //   159: bipush 14
    //   161: iconst_1
    //   162: invokestatic 132	xxxxxx/uxxxxx:bbbb0062b0062b0062b0062	(Ljava/lang/String;CCC)Ljava/lang/String;
    //   165: iconst_0
    //   166: anewarray 68	java/lang/Class
    //   169: invokevirtual 82	java/lang/Class:getMethod	(Ljava/lang/String;[Ljava/lang/Class;)Ljava/lang/reflect/Method;
    //   172: astore 7
    //   174: iconst_0
    //   175: anewarray 84	java/lang/Object
    //   178: astore 8
    //   180: aload 7
    //   182: aconst_null
    //   183: aload 8
    //   185: invokevirtual 96	java/lang/reflect/Method:invoke	(Ljava/lang/Object;[Ljava/lang/Object;)Ljava/lang/Object;
    //   188: astore 10
    //   190: iload 6
    //   192: iload 6
    //   194: aload 10
    //   196: checkcast 114	java/lang/Integer
    //   199: invokevirtual 118	java/lang/Integer:intValue	()I
    //   202: iadd
    //   203: imul
    //   204: getstatic 122	uuuuuu/qmqqmm:bvv0076v0076v00760076v	I
    //   207: irem
    //   208: tableswitch	default:+20->228, 0:+114->322
    //   228: ldc 2
    //   230: ldc 124
    //   232: sipush 165
    //   235: iconst_4
    //   236: invokestatic 66	xxxxxx/uxxxxx:bb00620062bb0062b0062b0062	(Ljava/lang/String;CC)Ljava/lang/String;
    //   239: iconst_0
    //   240: anewarray 68	java/lang/Class
    //   243: invokevirtual 82	java/lang/Class:getMethod	(Ljava/lang/String;[Ljava/lang/Class;)Ljava/lang/reflect/Method;
    //   246: astore 28
    //   248: iconst_0
    //   249: anewarray 84	java/lang/Object
    //   252: astore 29
    //   254: aload 28
    //   256: aconst_null
    //   257: aload 29
    //   259: invokevirtual 96	java/lang/reflect/Method:invoke	(Ljava/lang/Object;[Ljava/lang/Object;)Ljava/lang/Object;
    //   262: astore 31
    //   264: aload 31
    //   266: checkcast 114	java/lang/Integer
    //   269: invokevirtual 118	java/lang/Integer:intValue	()I
    //   272: putstatic 108	uuuuuu/qmqqmm:b0076vvv0076v00760076v	I
    //   275: ldc 2
    //   277: ldc_w 405
    //   280: bipush 19
    //   282: iconst_0
    //   283: invokestatic 66	xxxxxx/uxxxxx:bb00620062bb0062b0062b0062	(Ljava/lang/String;CC)Ljava/lang/String;
    //   286: iconst_0
    //   287: anewarray 68	java/lang/Class
    //   290: invokevirtual 82	java/lang/Class:getMethod	(Ljava/lang/String;[Ljava/lang/Class;)Ljava/lang/reflect/Method;
    //   293: astore 32
    //   295: iconst_0
    //   296: anewarray 84	java/lang/Object
    //   299: astore 33
    //   301: aload 32
    //   303: aconst_null
    //   304: aload 33
    //   306: invokevirtual 96	java/lang/reflect/Method:invoke	(Ljava/lang/Object;[Ljava/lang/Object;)Ljava/lang/Object;
    //   309: astore 35
    //   311: aload 35
    //   313: checkcast 114	java/lang/Integer
    //   316: invokevirtual 118	java/lang/Integer:intValue	()I
    //   319: putstatic 120	uuuuuu/qmqqmm:bv0076vv0076v00760076v	I
    //   322: aload_0
    //   323: getfield 196	uuuuuu/qmqqmm:b0076v00760076vv00760076v	Luuuuuu/vxvvvx;
    //   326: aload_0
    //   327: getfield 42	uuuuuu/qmqqmm:b00760076v0076vv00760076v	Ljava/lang/String;
    //   330: invokevirtual 409	uuuuuu/vxvvvx:b0075u00750075u00750075u00750075	(Ljava/lang/String;)Lcom/db/pwcc/dbmobile/multi_bank_aggregator/data/MbaFinancialOverviewData;
    //   333: astore 11
    //   335: aload 11
    //   337: ifnull +28 -> 365
    //   340: aload_0
    //   341: invokevirtual 205	uuuuuu/qmqqmm:bkk006Bk006Bk006Bk006Bk	()Z
    //   344: ifeq +21 -> 365
    //   347: aload_0
    //   348: getfield 152	uuuuuu/qmqqmm:bnnnnn006E006E006En	Luuuuuu/ttssst$tsssst;
    //   351: checkcast 215	uuuuuu/mmmmqm$mqqqmm
    //   354: getstatic 243	com/db/pwcc/dbmobile/multi_bank_aggregator/R$string:mba_delete_institute_error_title	I
    //   357: getstatic 246	com/db/pwcc/dbmobile/multi_bank_aggregator/R$string:mba_delete_institute_error_message	I
    //   360: invokeinterface 250 3 0
    //   365: aload_0
    //   366: getfield 196	uuuuuu/qmqqmm:b0076v00760076vv00760076v	Luuuuuu/vxvvvx;
    //   369: aload_0
    //   370: getfield 42	uuuuuu/qmqqmm:b00760076v0076vv00760076v	Ljava/lang/String;
    //   373: invokevirtual 201	uuuuuu/vxvvvx:buuuuu00750075u00750075	(Ljava/lang/String;)V
    //   376: aload_0
    //   377: invokevirtual 205	uuuuuu/qmqqmm:bkk006Bk006Bk006Bk006Bk	()Z
    //   380: ifeq -235 -> 145
    //   383: aload_0
    //   384: getfield 152	uuuuuu/qmqqmm:bnnnnn006E006E006En	Luuuuuu/ttssst$tsssst;
    //   387: checkcast 215	uuuuuu/mmmmqm$mqqqmm
    //   390: astore 12
    //   392: aload_0
    //   393: getfield 42	uuuuuu/qmqqmm:b00760076v0076vv00760076v	Ljava/lang/String;
    //   396: astore 13
    //   398: getstatic 108	uuuuuu/qmqqmm:b0076vvv0076v00760076v	I
    //   401: istore 14
    //   403: ldc 2
    //   405: ldc_w 411
    //   408: sipush 237
    //   411: iconst_3
    //   412: invokestatic 66	xxxxxx/uxxxxx:bb00620062bb0062b0062b0062	(Ljava/lang/String;CC)Ljava/lang/String;
    //   415: iconst_0
    //   416: anewarray 68	java/lang/Class
    //   419: invokevirtual 82	java/lang/Class:getMethod	(Ljava/lang/String;[Ljava/lang/Class;)Ljava/lang/reflect/Method;
    //   422: astore 15
    //   424: iconst_0
    //   425: anewarray 84	java/lang/Object
    //   428: astore 16
    //   430: aload 15
    //   432: aconst_null
    //   433: aload 16
    //   435: invokevirtual 96	java/lang/reflect/Method:invoke	(Ljava/lang/Object;[Ljava/lang/Object;)Ljava/lang/Object;
    //   438: astore 18
    //   440: iload 14
    //   442: iload 14
    //   444: aload 18
    //   446: checkcast 114	java/lang/Integer
    //   449: invokevirtual 118	java/lang/Integer:intValue	()I
    //   452: iadd
    //   453: imul
    //   454: getstatic 122	uuuuuu/qmqqmm:bvv0076v0076v00760076v	I
    //   457: irem
    //   458: tableswitch	default:+18->476, 0:+70->528
    //   476: ldc 2
    //   478: ldc_w 390
    //   481: bipush 65
    //   483: iconst_5
    //   484: invokestatic 66	xxxxxx/uxxxxx:bb00620062bb0062b0062b0062	(Ljava/lang/String;CC)Ljava/lang/String;
    //   487: iconst_0
    //   488: anewarray 68	java/lang/Class
    //   491: invokevirtual 82	java/lang/Class:getMethod	(Ljava/lang/String;[Ljava/lang/Class;)Ljava/lang/reflect/Method;
    //   494: astore 24
    //   496: iconst_0
    //   497: anewarray 84	java/lang/Object
    //   500: astore 25
    //   502: aload 24
    //   504: aconst_null
    //   505: aload 25
    //   507: invokevirtual 96	java/lang/reflect/Method:invoke	(Ljava/lang/Object;[Ljava/lang/Object;)Ljava/lang/Object;
    //   510: astore 27
    //   512: aload 27
    //   514: checkcast 114	java/lang/Integer
    //   517: invokevirtual 118	java/lang/Integer:intValue	()I
    //   520: putstatic 108	uuuuuu/qmqqmm:b0076vvv0076v00760076v	I
    //   523: bipush 61
    //   525: putstatic 120	uuuuuu/qmqqmm:bv0076vv0076v00760076v	I
    //   528: aload 11
    //   530: ifnonnull +18 -> 548
    //   533: iconst_1
    //   534: istore 19
    //   536: aload 12
    //   538: aload 13
    //   540: iload 19
    //   542: invokeinterface 238 3 0
    //   547: return
    //   548: getstatic 108	uuuuuu/qmqqmm:b0076vvv0076v00760076v	I
    //   551: getstatic 110	uuuuuu/qmqqmm:b00760076vv0076v00760076v	I
    //   554: iadd
    //   555: getstatic 108	uuuuuu/qmqqmm:b0076vvv0076v00760076v	I
    //   558: imul
    //   559: getstatic 122	uuuuuu/qmqqmm:bvv0076v0076v00760076v	I
    //   562: irem
    //   563: getstatic 120	uuuuuu/qmqqmm:bv0076vv0076v00760076v	I
    //   566: if_icmpeq +127 -> 693
    //   569: bipush 62
    //   571: putstatic 108	uuuuuu/qmqqmm:b0076vvv0076v00760076v	I
    //   574: ldc 2
    //   576: ldc_w 413
    //   579: bipush 33
    //   581: bipush 41
    //   583: iconst_1
    //   584: invokestatic 132	xxxxxx/uxxxxx:bbbb0062b0062b0062b0062	(Ljava/lang/String;CCC)Ljava/lang/String;
    //   587: iconst_0
    //   588: anewarray 68	java/lang/Class
    //   591: invokevirtual 82	java/lang/Class:getMethod	(Ljava/lang/String;[Ljava/lang/Class;)Ljava/lang/reflect/Method;
    //   594: astore 20
    //   596: iconst_0
    //   597: anewarray 84	java/lang/Object
    //   600: astore 21
    //   602: aload 20
    //   604: aconst_null
    //   605: aload 21
    //   607: invokevirtual 96	java/lang/reflect/Method:invoke	(Ljava/lang/Object;[Ljava/lang/Object;)Ljava/lang/Object;
    //   610: astore 23
    //   612: aload 23
    //   614: checkcast 114	java/lang/Integer
    //   617: invokevirtual 118	java/lang/Integer:intValue	()I
    //   620: putstatic 120	uuuuuu/qmqqmm:bv0076vv0076v00760076v	I
    //   623: iconst_0
    //   624: istore 19
    //   626: goto -90 -> 536
    //   629: astore 4
    //   631: aload 4
    //   633: invokevirtual 138	java/lang/reflect/InvocationTargetException:getCause	()Ljava/lang/Throwable;
    //   636: athrow
    //   637: astore 9
    //   639: aload 9
    //   641: invokevirtual 138	java/lang/reflect/InvocationTargetException:getCause	()Ljava/lang/Throwable;
    //   644: athrow
    //   645: astore 17
    //   647: aload 17
    //   649: invokevirtual 138	java/lang/reflect/InvocationTargetException:getCause	()Ljava/lang/Throwable;
    //   652: athrow
    //   653: astore 26
    //   655: aload 26
    //   657: invokevirtual 138	java/lang/reflect/InvocationTargetException:getCause	()Ljava/lang/Throwable;
    //   660: athrow
    //   661: astore 22
    //   663: aload 22
    //   665: invokevirtual 138	java/lang/reflect/InvocationTargetException:getCause	()Ljava/lang/Throwable;
    //   668: athrow
    //   669: astore 38
    //   671: aload 38
    //   673: invokevirtual 138	java/lang/reflect/InvocationTargetException:getCause	()Ljava/lang/Throwable;
    //   676: athrow
    //   677: astore 30
    //   679: aload 30
    //   681: invokevirtual 138	java/lang/reflect/InvocationTargetException:getCause	()Ljava/lang/Throwable;
    //   684: athrow
    //   685: astore 34
    //   687: aload 34
    //   689: invokevirtual 138	java/lang/reflect/InvocationTargetException:getCause	()Ljava/lang/Throwable;
    //   692: athrow
    //   693: iconst_0
    //   694: istore 19
    //   696: goto -160 -> 536
    // Local variable table:
    //   start	length	slot	name	signature
    //   0	699	0	this	qmqqmm
    //   11	44	1	i	int
    //   31	7	2	localMethod1	Method
    //   36	4	3	arrayOfObject1	Object[]
    //   629	3	4	localInvocationTargetException1	InvocationTargetException
    //   43	4	5	localObject1	Object
    //   149	55	6	j	int
    //   172	9	7	localMethod2	Method
    //   178	6	8	arrayOfObject2	Object[]
    //   637	3	9	localInvocationTargetException2	InvocationTargetException
    //   188	7	10	localObject2	Object
    //   333	196	11	localMbaFinancialOverviewData	com.db.pwcc.dbmobile.multi_bank_aggregator.data.MbaFinancialOverviewData
    //   390	147	12	localMqqqmm	mmmmqm.mqqqmm
    //   396	143	13	str	String
    //   401	53	14	k	int
    //   422	9	15	localMethod3	Method
    //   428	6	16	arrayOfObject3	Object[]
    //   645	3	17	localInvocationTargetException3	InvocationTargetException
    //   438	7	18	localObject3	Object
    //   534	161	19	bool	boolean
    //   594	9	20	localMethod4	Method
    //   600	6	21	arrayOfObject4	Object[]
    //   661	3	22	localInvocationTargetException4	InvocationTargetException
    //   610	3	23	localObject4	Object
    //   494	9	24	localMethod5	Method
    //   500	6	25	arrayOfObject5	Object[]
    //   653	3	26	localInvocationTargetException5	InvocationTargetException
    //   510	3	27	localObject5	Object
    //   246	9	28	localMethod6	Method
    //   252	6	29	arrayOfObject6	Object[]
    //   677	3	30	localInvocationTargetException6	InvocationTargetException
    //   262	3	31	localObject6	Object
    //   293	9	32	localMethod7	Method
    //   299	6	33	arrayOfObject7	Object[]
    //   685	3	34	localInvocationTargetException7	InvocationTargetException
    //   309	3	35	localObject7	Object
    //   82	9	36	localMethod8	Method
    //   88	6	37	arrayOfObject8	Object[]
    //   669	3	38	localInvocationTargetException8	InvocationTargetException
    //   98	3	39	localObject8	Object
    // Exception table:
    //   from	to	target	type
    //   37	45	629	java/lang/reflect/InvocationTargetException
    //   180	190	637	java/lang/reflect/InvocationTargetException
    //   430	440	645	java/lang/reflect/InvocationTargetException
    //   502	512	653	java/lang/reflect/InvocationTargetException
    //   602	612	661	java/lang/reflect/InvocationTargetException
    //   90	100	669	java/lang/reflect/InvocationTargetException
    //   254	264	677	java/lang/reflect/InvocationTargetException
    //   301	311	685	java/lang/reflect/InvocationTargetException
  }
  
  /* Error */
  public void b00750075uu007500750075uu0075(@android.support.annotation.NonNull com.db.pwcc.dbmobile.multi_bank_aggregator.data.MbaFinancialOverviewData paramMbaFinancialOverviewData, @android.support.annotation.NonNull RSAPublicKey paramRSAPublicKey, @android.support.annotation.NonNull String paramString)
  {
    // Byte code:
    //   0: new 418	java/lang/StringBuilder
    //   3: dup
    //   4: invokespecial 419	java/lang/StringBuilder:<init>	()V
    //   7: astore 4
    //   9: ldc_w 421
    //   12: sipush 253
    //   15: iconst_4
    //   16: invokestatic 66	xxxxxx/uxxxxx:bb00620062bb0062b0062b0062	(Ljava/lang/String;CC)Ljava/lang/String;
    //   19: astore 5
    //   21: iconst_3
    //   22: anewarray 68	java/lang/Class
    //   25: astore 6
    //   27: aload 6
    //   29: iconst_0
    //   30: ldc 70
    //   32: aastore
    //   33: aload 6
    //   35: iconst_1
    //   36: getstatic 76	java/lang/Character:TYPE	Ljava/lang/Class;
    //   39: aastore
    //   40: aload 6
    //   42: iconst_2
    //   43: getstatic 76	java/lang/Character:TYPE	Ljava/lang/Class;
    //   46: aastore
    //   47: ldc 78
    //   49: aload 5
    //   51: aload 6
    //   53: invokevirtual 82	java/lang/Class:getMethod	(Ljava/lang/String;[Ljava/lang/Class;)Ljava/lang/reflect/Method;
    //   56: astore 7
    //   58: iconst_3
    //   59: anewarray 84	java/lang/Object
    //   62: astore 8
    //   64: aload 8
    //   66: iconst_0
    //   67: ldc_w 423
    //   70: aastore
    //   71: aload 8
    //   73: iconst_1
    //   74: bipush 104
    //   76: invokestatic 90	java/lang/Character:valueOf	(C)Ljava/lang/Character;
    //   79: aastore
    //   80: aload 8
    //   82: iconst_2
    //   83: iconst_5
    //   84: invokestatic 90	java/lang/Character:valueOf	(C)Ljava/lang/Character;
    //   87: aastore
    //   88: aload 7
    //   90: aconst_null
    //   91: aload 8
    //   93: invokevirtual 96	java/lang/reflect/Method:invoke	(Ljava/lang/Object;[Ljava/lang/Object;)Ljava/lang/Object;
    //   96: astore 10
    //   98: aload 4
    //   100: aload 10
    //   102: checkcast 70	java/lang/String
    //   105: invokevirtual 427	java/lang/StringBuilder:append	(Ljava/lang/String;)Ljava/lang/StringBuilder;
    //   108: aload_3
    //   109: invokevirtual 427	java/lang/StringBuilder:append	(Ljava/lang/String;)Ljava/lang/StringBuilder;
    //   112: astore 11
    //   114: getstatic 108	uuuuuu/qmqqmm:b0076vvv0076v00760076v	I
    //   117: istore 12
    //   119: iload 12
    //   121: iload 12
    //   123: getstatic 110	uuuuuu/qmqqmm:b00760076vv0076v00760076v	I
    //   126: iadd
    //   127: imul
    //   128: getstatic 122	uuuuuu/qmqqmm:bvv0076v0076v00760076v	I
    //   131: irem
    //   132: tableswitch	default:+20->152, 0:+72->204
    //   152: ldc 2
    //   154: ldc_w 429
    //   157: bipush 113
    //   159: iconst_0
    //   160: invokestatic 66	xxxxxx/uxxxxx:bb00620062bb0062b0062b0062	(Ljava/lang/String;CC)Ljava/lang/String;
    //   163: iconst_0
    //   164: anewarray 68	java/lang/Class
    //   167: invokevirtual 82	java/lang/Class:getMethod	(Ljava/lang/String;[Ljava/lang/Class;)Ljava/lang/reflect/Method;
    //   170: astore 46
    //   172: iconst_0
    //   173: anewarray 84	java/lang/Object
    //   176: astore 47
    //   178: aload 46
    //   180: aconst_null
    //   181: aload 47
    //   183: invokevirtual 96	java/lang/reflect/Method:invoke	(Ljava/lang/Object;[Ljava/lang/Object;)Ljava/lang/Object;
    //   186: astore 49
    //   188: aload 49
    //   190: checkcast 114	java/lang/Integer
    //   193: invokevirtual 118	java/lang/Integer:intValue	()I
    //   196: putstatic 108	uuuuuu/qmqqmm:b0076vvv0076v00760076v	I
    //   199: bipush 46
    //   201: putstatic 120	uuuuuu/qmqqmm:bv0076vv0076v00760076v	I
    //   204: ldc_w 431
    //   207: sipush 162
    //   210: iconst_0
    //   211: invokestatic 66	xxxxxx/uxxxxx:bb00620062bb0062b0062b0062	(Ljava/lang/String;CC)Ljava/lang/String;
    //   214: astore 13
    //   216: iconst_3
    //   217: anewarray 68	java/lang/Class
    //   220: astore 14
    //   222: aload 14
    //   224: iconst_0
    //   225: ldc 70
    //   227: aastore
    //   228: aload 14
    //   230: iconst_1
    //   231: getstatic 76	java/lang/Character:TYPE	Ljava/lang/Class;
    //   234: aastore
    //   235: aload 14
    //   237: iconst_2
    //   238: getstatic 76	java/lang/Character:TYPE	Ljava/lang/Class;
    //   241: aastore
    //   242: ldc 78
    //   244: aload 13
    //   246: aload 14
    //   248: invokevirtual 82	java/lang/Class:getMethod	(Ljava/lang/String;[Ljava/lang/Class;)Ljava/lang/reflect/Method;
    //   251: astore 15
    //   253: iconst_3
    //   254: anewarray 84	java/lang/Object
    //   257: astore 16
    //   259: aload 16
    //   261: iconst_0
    //   262: ldc_w 433
    //   265: aastore
    //   266: aload 16
    //   268: iconst_1
    //   269: bipush 105
    //   271: invokestatic 90	java/lang/Character:valueOf	(C)Ljava/lang/Character;
    //   274: aastore
    //   275: aload 16
    //   277: iconst_2
    //   278: iconst_0
    //   279: invokestatic 90	java/lang/Character:valueOf	(C)Ljava/lang/Character;
    //   282: aastore
    //   283: aload 15
    //   285: aconst_null
    //   286: aload 16
    //   288: invokevirtual 96	java/lang/reflect/Method:invoke	(Ljava/lang/Object;[Ljava/lang/Object;)Ljava/lang/Object;
    //   291: astore 18
    //   293: aload 11
    //   295: aload 18
    //   297: checkcast 70	java/lang/String
    //   300: invokevirtual 427	java/lang/StringBuilder:append	(Ljava/lang/String;)Ljava/lang/StringBuilder;
    //   303: invokevirtual 437	java/lang/StringBuilder:toString	()Ljava/lang/String;
    //   306: astore 19
    //   308: ldc_w 439
    //   311: ldc_w 441
    //   314: bipush 58
    //   316: sipush 141
    //   319: iconst_1
    //   320: invokestatic 132	xxxxxx/uxxxxx:bbbb0062b0062b0062b0062	(Ljava/lang/String;CCC)Ljava/lang/String;
    //   323: iconst_2
    //   324: anewarray 68	java/lang/Class
    //   327: dup
    //   328: iconst_0
    //   329: ldc 70
    //   331: aastore
    //   332: dup
    //   333: iconst_1
    //   334: ldc_w 443
    //   337: aastore
    //   338: invokevirtual 82	java/lang/Class:getMethod	(Ljava/lang/String;[Ljava/lang/Class;)Ljava/lang/reflect/Method;
    //   341: astore 20
    //   343: iconst_2
    //   344: anewarray 84	java/lang/Object
    //   347: dup
    //   348: iconst_0
    //   349: aload 19
    //   351: aastore
    //   352: dup
    //   353: iconst_1
    //   354: aload_2
    //   355: aastore
    //   356: astore 21
    //   358: aload 20
    //   360: aconst_null
    //   361: aload 21
    //   363: invokevirtual 96	java/lang/reflect/Method:invoke	(Ljava/lang/Object;[Ljava/lang/Object;)Ljava/lang/Object;
    //   366: astore 23
    //   368: aload 23
    //   370: checkcast 70	java/lang/String
    //   373: astore 24
    //   375: aload 24
    //   377: ifnonnull +39 -> 416
    //   380: aload_0
    //   381: invokevirtual 205	uuuuuu/qmqqmm:bkk006Bk006Bk006Bk006Bk	()Z
    //   384: ifeq +31 -> 415
    //   387: aload_0
    //   388: getfield 152	uuuuuu/qmqqmm:bnnnnn006E006E006En	Luuuuuu/ttssst$tsssst;
    //   391: checkcast 215	uuuuuu/mmmmqm$mqqqmm
    //   394: getstatic 446	com/db/pwcc/dbmobile/multi_bank_aggregator/R$string:technical_error_retry	I
    //   397: invokeinterface 448 2 0
    //   402: aload_0
    //   403: getfield 152	uuuuuu/qmqqmm:bnnnnn006E006E006En	Luuuuuu/ttssst$tsssst;
    //   406: checkcast 215	uuuuuu/mmmmqm$mqqqmm
    //   409: iconst_0
    //   410: invokeinterface 452 2 0
    //   415: return
    //   416: aload_0
    //   417: iconst_0
    //   418: putfield 40	uuuuuu/qmqqmm:bvvvv0076v00760076v	Z
    //   421: aload_0
    //   422: getfield 196	uuuuuu/qmqqmm:b0076v00760076vv00760076v	Luuuuuu/vxvvvx;
    //   425: aload_1
    //   426: invokevirtual 457	com/db/pwcc/dbmobile/multi_bank_aggregator/data/MbaFinancialOverviewData:getBankLoginId	()Ljava/lang/String;
    //   429: aload 24
    //   431: iconst_1
    //   432: invokevirtual 461	uuuuuu/vxvvvx:b006Bk006Bkkk006B006Bkk	(Ljava/lang/String;Ljava/lang/String;Z)V
    //   435: aload_0
    //   436: getfield 196	uuuuuu/qmqqmm:b0076v00760076vv00760076v	Luuuuuu/vxvvvx;
    //   439: astore 25
    //   441: getstatic 108	uuuuuu/qmqqmm:b0076vvv0076v00760076v	I
    //   444: getstatic 110	uuuuuu/qmqqmm:b00760076vv0076v00760076v	I
    //   447: iadd
    //   448: getstatic 108	uuuuuu/qmqqmm:b0076vvv0076v00760076v	I
    //   451: imul
    //   452: istore 26
    //   454: getstatic 108	uuuuuu/qmqqmm:b0076vvv0076v00760076v	I
    //   457: istore 27
    //   459: ldc 2
    //   461: ldc_w 463
    //   464: bipush 31
    //   466: bipush 111
    //   468: iconst_0
    //   469: invokestatic 132	xxxxxx/uxxxxx:bbbb0062b0062b0062b0062	(Ljava/lang/String;CCC)Ljava/lang/String;
    //   472: iconst_0
    //   473: anewarray 68	java/lang/Class
    //   476: invokevirtual 82	java/lang/Class:getMethod	(Ljava/lang/String;[Ljava/lang/Class;)Ljava/lang/reflect/Method;
    //   479: astore 28
    //   481: iconst_0
    //   482: anewarray 84	java/lang/Object
    //   485: astore 29
    //   487: aload 28
    //   489: aconst_null
    //   490: aload 29
    //   492: invokevirtual 96	java/lang/reflect/Method:invoke	(Ljava/lang/Object;[Ljava/lang/Object;)Ljava/lang/Object;
    //   495: astore 31
    //   497: iload 27
    //   499: iload 27
    //   501: aload 31
    //   503: checkcast 114	java/lang/Integer
    //   506: invokevirtual 118	java/lang/Integer:intValue	()I
    //   509: iadd
    //   510: imul
    //   511: getstatic 122	uuuuuu/qmqqmm:bvv0076v0076v00760076v	I
    //   514: irem
    //   515: tableswitch	default:+17->532, 0:+27->542
    //   532: bipush 12
    //   534: putstatic 108	uuuuuu/qmqqmm:b0076vvv0076v00760076v	I
    //   537: bipush 66
    //   539: putstatic 120	uuuuuu/qmqqmm:bv0076vv0076v00760076v	I
    //   542: getstatic 122	uuuuuu/qmqqmm:bvv0076v0076v00760076v	I
    //   545: istore 32
    //   547: getstatic 108	uuuuuu/qmqqmm:b0076vvv0076v00760076v	I
    //   550: istore 33
    //   552: iload 33
    //   554: iload 33
    //   556: getstatic 110	uuuuuu/qmqqmm:b00760076vv0076v00760076v	I
    //   559: iadd
    //   560: imul
    //   561: getstatic 122	uuuuuu/qmqqmm:bvv0076v0076v00760076v	I
    //   564: irem
    //   565: tableswitch	default:+19->584, 0:+73->638
    //   584: ldc 2
    //   586: ldc_w 465
    //   589: bipush 126
    //   591: bipush 116
    //   593: iconst_2
    //   594: invokestatic 132	xxxxxx/uxxxxx:bbbb0062b0062b0062b0062	(Ljava/lang/String;CCC)Ljava/lang/String;
    //   597: iconst_0
    //   598: anewarray 68	java/lang/Class
    //   601: invokevirtual 82	java/lang/Class:getMethod	(Ljava/lang/String;[Ljava/lang/Class;)Ljava/lang/reflect/Method;
    //   604: astore 42
    //   606: iconst_0
    //   607: anewarray 84	java/lang/Object
    //   610: astore 43
    //   612: aload 42
    //   614: aconst_null
    //   615: aload 43
    //   617: invokevirtual 96	java/lang/reflect/Method:invoke	(Ljava/lang/Object;[Ljava/lang/Object;)Ljava/lang/Object;
    //   620: astore 45
    //   622: aload 45
    //   624: checkcast 114	java/lang/Integer
    //   627: invokevirtual 118	java/lang/Integer:intValue	()I
    //   630: putstatic 108	uuuuuu/qmqqmm:b0076vvv0076v00760076v	I
    //   633: bipush 96
    //   635: putstatic 120	uuuuuu/qmqqmm:bv0076vv0076v00760076v	I
    //   638: iload 26
    //   640: iload 32
    //   642: irem
    //   643: getstatic 120	uuuuuu/qmqqmm:bv0076vv0076v00760076v	I
    //   646: if_icmpeq +56 -> 702
    //   649: bipush 66
    //   651: putstatic 108	uuuuuu/qmqqmm:b0076vvv0076v00760076v	I
    //   654: ldc 2
    //   656: ldc_w 405
    //   659: sipush 184
    //   662: iconst_2
    //   663: invokestatic 66	xxxxxx/uxxxxx:bb00620062bb0062b0062b0062	(Ljava/lang/String;CC)Ljava/lang/String;
    //   666: iconst_0
    //   667: anewarray 68	java/lang/Class
    //   670: invokevirtual 82	java/lang/Class:getMethod	(Ljava/lang/String;[Ljava/lang/Class;)Ljava/lang/reflect/Method;
    //   673: astore 38
    //   675: iconst_0
    //   676: anewarray 84	java/lang/Object
    //   679: astore 39
    //   681: aload 38
    //   683: aconst_null
    //   684: aload 39
    //   686: invokevirtual 96	java/lang/reflect/Method:invoke	(Ljava/lang/Object;[Ljava/lang/Object;)Ljava/lang/Object;
    //   689: astore 41
    //   691: aload 41
    //   693: checkcast 114	java/lang/Integer
    //   696: invokevirtual 118	java/lang/Integer:intValue	()I
    //   699: putstatic 120	uuuuuu/qmqqmm:bv0076vv0076v00760076v	I
    //   702: aload 25
    //   704: aload_0
    //   705: getfield 42	uuuuuu/qmqqmm:b00760076v0076vv00760076v	Ljava/lang/String;
    //   708: invokevirtual 468	uuuuuu/vxvvvx:b00750075uuu00750075u00750075	(Ljava/lang/String;)V
    //   711: ldc 2
    //   713: ldc_w 470
    //   716: sipush 213
    //   719: bipush 30
    //   721: iconst_3
    //   722: invokestatic 132	xxxxxx/uxxxxx:bbbb0062b0062b0062b0062	(Ljava/lang/String;CCC)Ljava/lang/String;
    //   725: iconst_0
    //   726: anewarray 68	java/lang/Class
    //   729: invokevirtual 287	java/lang/Class:getDeclaredMethod	(Ljava/lang/String;[Ljava/lang/Class;)Ljava/lang/reflect/Method;
    //   732: astore 34
    //   734: iconst_0
    //   735: anewarray 84	java/lang/Object
    //   738: astore 35
    //   740: aload 34
    //   742: aload_0
    //   743: aload 35
    //   745: invokevirtual 96	java/lang/reflect/Method:invoke	(Ljava/lang/Object;[Ljava/lang/Object;)Ljava/lang/Object;
    //   748: pop
    //   749: return
    //   750: astore 36
    //   752: aload 36
    //   754: invokevirtual 138	java/lang/reflect/InvocationTargetException:getCause	()Ljava/lang/Throwable;
    //   757: athrow
    //   758: astore 9
    //   760: aload 9
    //   762: invokevirtual 138	java/lang/reflect/InvocationTargetException:getCause	()Ljava/lang/Throwable;
    //   765: athrow
    //   766: astore 40
    //   768: aload 40
    //   770: invokevirtual 138	java/lang/reflect/InvocationTargetException:getCause	()Ljava/lang/Throwable;
    //   773: athrow
    //   774: astore 30
    //   776: aload 30
    //   778: invokevirtual 138	java/lang/reflect/InvocationTargetException:getCause	()Ljava/lang/Throwable;
    //   781: athrow
    //   782: astore 44
    //   784: aload 44
    //   786: invokevirtual 138	java/lang/reflect/InvocationTargetException:getCause	()Ljava/lang/Throwable;
    //   789: athrow
    //   790: astore 17
    //   792: aload 17
    //   794: invokevirtual 138	java/lang/reflect/InvocationTargetException:getCause	()Ljava/lang/Throwable;
    //   797: athrow
    //   798: astore 22
    //   800: aload 22
    //   802: invokevirtual 138	java/lang/reflect/InvocationTargetException:getCause	()Ljava/lang/Throwable;
    //   805: athrow
    //   806: astore 48
    //   808: aload 48
    //   810: invokevirtual 138	java/lang/reflect/InvocationTargetException:getCause	()Ljava/lang/Throwable;
    //   813: athrow
    // Local variable table:
    //   start	length	slot	name	signature
    //   0	814	0	this	qmqqmm
    //   0	814	1	paramMbaFinancialOverviewData	com.db.pwcc.dbmobile.multi_bank_aggregator.data.MbaFinancialOverviewData
    //   0	814	2	paramRSAPublicKey	RSAPublicKey
    //   0	814	3	paramString	String
    //   7	92	4	localStringBuilder1	StringBuilder
    //   19	31	5	str1	String
    //   25	27	6	arrayOfClass1	Class[]
    //   56	33	7	localMethod1	Method
    //   62	30	8	arrayOfObject1	Object[]
    //   758	3	9	localInvocationTargetException1	InvocationTargetException
    //   96	5	10	localObject1	Object
    //   112	182	11	localStringBuilder2	StringBuilder
    //   117	11	12	i	int
    //   214	31	13	str2	String
    //   220	27	14	arrayOfClass2	Class[]
    //   251	33	15	localMethod2	Method
    //   257	30	16	arrayOfObject2	Object[]
    //   790	3	17	localInvocationTargetException2	InvocationTargetException
    //   291	5	18	localObject2	Object
    //   306	44	19	str3	String
    //   341	18	20	localMethod3	Method
    //   356	6	21	arrayOfObject3	Object[]
    //   798	3	22	localInvocationTargetException3	InvocationTargetException
    //   366	3	23	localObject3	Object
    //   373	57	24	str4	String
    //   439	264	25	localVxvvvx	vxvvvx
    //   452	191	26	j	int
    //   457	54	27	k	int
    //   479	9	28	localMethod4	Method
    //   485	6	29	arrayOfObject4	Object[]
    //   774	3	30	localInvocationTargetException4	InvocationTargetException
    //   495	7	31	localObject4	Object
    //   545	98	32	m	int
    //   550	11	33	n	int
    //   732	9	34	localMethod5	Method
    //   738	6	35	arrayOfObject5	Object[]
    //   750	3	36	localInvocationTargetException5	InvocationTargetException
    //   673	9	38	localMethod6	Method
    //   679	6	39	arrayOfObject6	Object[]
    //   766	3	40	localInvocationTargetException6	InvocationTargetException
    //   689	3	41	localObject5	Object
    //   604	9	42	localMethod7	Method
    //   610	6	43	arrayOfObject7	Object[]
    //   782	3	44	localInvocationTargetException7	InvocationTargetException
    //   620	3	45	localObject6	Object
    //   170	9	46	localMethod8	Method
    //   176	6	47	arrayOfObject8	Object[]
    //   806	3	48	localInvocationTargetException8	InvocationTargetException
    //   186	3	49	localObject7	Object
    // Exception table:
    //   from	to	target	type
    //   740	749	750	java/lang/reflect/InvocationTargetException
    //   88	98	758	java/lang/reflect/InvocationTargetException
    //   681	691	766	java/lang/reflect/InvocationTargetException
    //   487	497	774	java/lang/reflect/InvocationTargetException
    //   612	622	782	java/lang/reflect/InvocationTargetException
    //   283	293	790	java/lang/reflect/InvocationTargetException
    //   358	368	798	java/lang/reflect/InvocationTargetException
    //   178	188	806	java/lang/reflect/InvocationTargetException
  }
  
  public void b00750075uuuuu0075u0075(DbError paramDbError)
  {
    int i = b0076vvv0076v00760076v;
    switch (i * (i + b00760076vv0076v00760076v) % bvv0076v0076v00760076v)
    {
    default: 
      b0076vvv0076v00760076v = 13;
      bv0076vv0076v00760076v = 92;
    }
    mmmmqm.mqqqmm localMqqqmm;
    int j;
    int m;
    int n;
    Method localMethod;
    Object[] arrayOfObject;
    if (bkk006Bk006Bk006Bk006Bk())
    {
      localMqqqmm = (mmmmqm.mqqqmm)this.bnnnnn006E006E006En;
      j = b0076vvv0076v00760076v;
      int k = b0076vvv0076v00760076v;
      m = k * (k + b00760076vv0076v00760076v) % bvv0076v0076v00760076v;
      n = b0076vvv0076v00760076v;
      localMethod = qmqqmm.class.getMethod(uxxxxx.bb00620062bb0062b0062b0062("k:;CB\004?@HGCDLKGHPOKLTSOPXW\031\032UV^]", '', '\000'), new Class[0]);
      arrayOfObject = new Object[0];
    }
    try
    {
      Object localObject = localMethod.invoke(null, arrayOfObject);
      if ((n + ((Integer)localObject).intValue()) * b0076vvv0076v00760076v % bvv0076v0076v00760076v != bv0076vv0076v00760076v)
      {
        b0076vvv0076v00760076v = 66;
        bv0076vv0076v00760076v = 6;
      }
      switch (m)
      {
      default: 
        b0076vvv0076v00760076v = 76;
        bv0076vv0076v00760076v = 15;
      }
      if ((j + b00760076vv0076v00760076v) * b0076vvv0076v00760076v % bvv0076v0076v00760076v != bv0076vv0076v00760076v)
      {
        b0076vvv0076v00760076v = 43;
        bv0076vv0076v00760076v = 81;
      }
      localMqqqmm.onPublicKeyError(paramDbError);
      return;
    }
    catch (InvocationTargetException localInvocationTargetException)
    {
      throw localInvocationTargetException.getCause();
    }
  }
  
  /* Error */
  public com.db.pwcc.dbmobile.multi_bank_aggregator.data.MbaFinancialOverviewData b0075u00750075u00750075uu0075()
  {
    // Byte code:
    //   0: aload_0
    //   1: getfield 196	uuuuuu/qmqqmm:b0076v00760076vv00760076v	Luuuuuu/vxvvvx;
    //   4: astore_1
    //   5: getstatic 108	uuuuuu/qmqqmm:b0076vvv0076v00760076v	I
    //   8: getstatic 110	uuuuuu/qmqqmm:b00760076vv0076v00760076v	I
    //   11: iadd
    //   12: getstatic 108	uuuuuu/qmqqmm:b0076vvv0076v00760076v	I
    //   15: imul
    //   16: istore_2
    //   17: getstatic 108	uuuuuu/qmqqmm:b0076vvv0076v00760076v	I
    //   20: getstatic 110	uuuuuu/qmqqmm:b00760076vv0076v00760076v	I
    //   23: iadd
    //   24: getstatic 108	uuuuuu/qmqqmm:b0076vvv0076v00760076v	I
    //   27: imul
    //   28: istore_3
    //   29: ldc 2
    //   31: ldc_w 481
    //   34: sipush 202
    //   37: sipush 240
    //   40: iconst_2
    //   41: invokestatic 132	xxxxxx/uxxxxx:bbbb0062b0062b0062b0062	(Ljava/lang/String;CCC)Ljava/lang/String;
    //   44: iconst_0
    //   45: anewarray 68	java/lang/Class
    //   48: invokevirtual 82	java/lang/Class:getMethod	(Ljava/lang/String;[Ljava/lang/Class;)Ljava/lang/reflect/Method;
    //   51: astore 4
    //   53: iconst_0
    //   54: anewarray 84	java/lang/Object
    //   57: astore 5
    //   59: aload 4
    //   61: aconst_null
    //   62: aload 5
    //   64: invokevirtual 96	java/lang/reflect/Method:invoke	(Ljava/lang/Object;[Ljava/lang/Object;)Ljava/lang/Object;
    //   67: astore 7
    //   69: iload_3
    //   70: aload 7
    //   72: checkcast 114	java/lang/Integer
    //   75: invokevirtual 118	java/lang/Integer:intValue	()I
    //   78: irem
    //   79: getstatic 120	uuuuuu/qmqqmm:bv0076vv0076v00760076v	I
    //   82: if_icmpeq +13 -> 95
    //   85: bipush 85
    //   87: putstatic 108	uuuuuu/qmqqmm:b0076vvv0076v00760076v	I
    //   90: bipush 37
    //   92: putstatic 120	uuuuuu/qmqqmm:bv0076vv0076v00760076v	I
    //   95: iload_2
    //   96: getstatic 122	uuuuuu/qmqqmm:bvv0076v0076v00760076v	I
    //   99: irem
    //   100: getstatic 120	uuuuuu/qmqqmm:bv0076vv0076v00760076v	I
    //   103: if_icmpeq +327 -> 430
    //   106: getstatic 108	uuuuuu/qmqqmm:b0076vvv0076v00760076v	I
    //   109: istore 8
    //   111: iload 8
    //   113: iload 8
    //   115: getstatic 110	uuuuuu/qmqqmm:b00760076vv0076v00760076v	I
    //   118: iadd
    //   119: imul
    //   120: getstatic 122	uuuuuu/qmqqmm:bvv0076v0076v00760076v	I
    //   123: irem
    //   124: tableswitch	default:+20->144, 0:+73->197
    //   144: bipush 51
    //   146: putstatic 108	uuuuuu/qmqqmm:b0076vvv0076v00760076v	I
    //   149: ldc 2
    //   151: ldc_w 483
    //   154: sipush 226
    //   157: iconst_5
    //   158: invokestatic 66	xxxxxx/uxxxxx:bb00620062bb0062b0062b0062	(Ljava/lang/String;CC)Ljava/lang/String;
    //   161: iconst_0
    //   162: anewarray 68	java/lang/Class
    //   165: invokevirtual 82	java/lang/Class:getMethod	(Ljava/lang/String;[Ljava/lang/Class;)Ljava/lang/reflect/Method;
    //   168: astore 27
    //   170: iconst_0
    //   171: anewarray 84	java/lang/Object
    //   174: astore 28
    //   176: aload 27
    //   178: aconst_null
    //   179: aload 28
    //   181: invokevirtual 96	java/lang/reflect/Method:invoke	(Ljava/lang/Object;[Ljava/lang/Object;)Ljava/lang/Object;
    //   184: astore 30
    //   186: aload 30
    //   188: checkcast 114	java/lang/Integer
    //   191: invokevirtual 118	java/lang/Integer:intValue	()I
    //   194: putstatic 120	uuuuuu/qmqqmm:bv0076vv0076v00760076v	I
    //   197: ldc 2
    //   199: ldc_w 485
    //   202: bipush 93
    //   204: iconst_2
    //   205: invokestatic 66	xxxxxx/uxxxxx:bb00620062bb0062b0062b0062	(Ljava/lang/String;CC)Ljava/lang/String;
    //   208: iconst_0
    //   209: anewarray 68	java/lang/Class
    //   212: invokevirtual 82	java/lang/Class:getMethod	(Ljava/lang/String;[Ljava/lang/Class;)Ljava/lang/reflect/Method;
    //   215: astore 9
    //   217: iconst_0
    //   218: anewarray 84	java/lang/Object
    //   221: astore 10
    //   223: aload 9
    //   225: aconst_null
    //   226: aload 10
    //   228: invokevirtual 96	java/lang/reflect/Method:invoke	(Ljava/lang/Object;[Ljava/lang/Object;)Ljava/lang/Object;
    //   231: astore 12
    //   233: aload 12
    //   235: checkcast 114	java/lang/Integer
    //   238: invokevirtual 118	java/lang/Integer:intValue	()I
    //   241: putstatic 108	uuuuuu/qmqqmm:b0076vvv0076v00760076v	I
    //   244: ldc 2
    //   246: ldc_w 487
    //   249: bipush 31
    //   251: iconst_5
    //   252: invokestatic 66	xxxxxx/uxxxxx:bb00620062bb0062b0062b0062	(Ljava/lang/String;CC)Ljava/lang/String;
    //   255: iconst_0
    //   256: anewarray 68	java/lang/Class
    //   259: invokevirtual 82	java/lang/Class:getMethod	(Ljava/lang/String;[Ljava/lang/Class;)Ljava/lang/reflect/Method;
    //   262: astore 13
    //   264: iconst_0
    //   265: anewarray 84	java/lang/Object
    //   268: astore 14
    //   270: aload 13
    //   272: aconst_null
    //   273: aload 14
    //   275: invokevirtual 96	java/lang/reflect/Method:invoke	(Ljava/lang/Object;[Ljava/lang/Object;)Ljava/lang/Object;
    //   278: astore 16
    //   280: aload 16
    //   282: checkcast 114	java/lang/Integer
    //   285: invokevirtual 118	java/lang/Integer:intValue	()I
    //   288: putstatic 120	uuuuuu/qmqqmm:bv0076vv0076v00760076v	I
    //   291: getstatic 108	uuuuuu/qmqqmm:b0076vvv0076v00760076v	I
    //   294: istore 17
    //   296: iload 17
    //   298: iload 17
    //   300: getstatic 110	uuuuuu/qmqqmm:b00760076vv0076v00760076v	I
    //   303: iadd
    //   304: imul
    //   305: istore 18
    //   307: ldc 2
    //   309: ldc_w 489
    //   312: bipush 86
    //   314: sipush 206
    //   317: iconst_1
    //   318: invokestatic 132	xxxxxx/uxxxxx:bbbb0062b0062b0062b0062	(Ljava/lang/String;CCC)Ljava/lang/String;
    //   321: iconst_0
    //   322: anewarray 68	java/lang/Class
    //   325: invokevirtual 82	java/lang/Class:getMethod	(Ljava/lang/String;[Ljava/lang/Class;)Ljava/lang/reflect/Method;
    //   328: astore 19
    //   330: iconst_0
    //   331: anewarray 84	java/lang/Object
    //   334: astore 20
    //   336: aload 19
    //   338: aconst_null
    //   339: aload 20
    //   341: invokevirtual 96	java/lang/reflect/Method:invoke	(Ljava/lang/Object;[Ljava/lang/Object;)Ljava/lang/Object;
    //   344: astore 22
    //   346: iload 18
    //   348: aload 22
    //   350: checkcast 114	java/lang/Integer
    //   353: invokevirtual 118	java/lang/Integer:intValue	()I
    //   356: irem
    //   357: tableswitch	default:+19->376, 0:+73->430
    //   376: ldc 2
    //   378: ldc_w 491
    //   381: bipush 106
    //   383: bipush 103
    //   385: iconst_1
    //   386: invokestatic 132	xxxxxx/uxxxxx:bbbb0062b0062b0062b0062	(Ljava/lang/String;CCC)Ljava/lang/String;
    //   389: iconst_0
    //   390: anewarray 68	java/lang/Class
    //   393: invokevirtual 82	java/lang/Class:getMethod	(Ljava/lang/String;[Ljava/lang/Class;)Ljava/lang/reflect/Method;
    //   396: astore 23
    //   398: iconst_0
    //   399: anewarray 84	java/lang/Object
    //   402: astore 24
    //   404: aload 23
    //   406: aconst_null
    //   407: aload 24
    //   409: invokevirtual 96	java/lang/reflect/Method:invoke	(Ljava/lang/Object;[Ljava/lang/Object;)Ljava/lang/Object;
    //   412: astore 26
    //   414: aload 26
    //   416: checkcast 114	java/lang/Integer
    //   419: invokevirtual 118	java/lang/Integer:intValue	()I
    //   422: putstatic 108	uuuuuu/qmqqmm:b0076vvv0076v00760076v	I
    //   425: bipush 87
    //   427: putstatic 120	uuuuuu/qmqqmm:bv0076vv0076v00760076v	I
    //   430: aload_1
    //   431: aload_0
    //   432: getfield 42	uuuuuu/qmqqmm:b00760076v0076vv00760076v	Ljava/lang/String;
    //   435: invokevirtual 409	uuuuuu/vxvvvx:b0075u00750075u00750075u00750075	(Ljava/lang/String;)Lcom/db/pwcc/dbmobile/multi_bank_aggregator/data/MbaFinancialOverviewData;
    //   438: areturn
    //   439: astore 15
    //   441: aload 15
    //   443: invokevirtual 138	java/lang/reflect/InvocationTargetException:getCause	()Ljava/lang/Throwable;
    //   446: athrow
    //   447: astore 21
    //   449: aload 21
    //   451: invokevirtual 138	java/lang/reflect/InvocationTargetException:getCause	()Ljava/lang/Throwable;
    //   454: athrow
    //   455: astore 11
    //   457: aload 11
    //   459: invokevirtual 138	java/lang/reflect/InvocationTargetException:getCause	()Ljava/lang/Throwable;
    //   462: athrow
    //   463: astore 6
    //   465: aload 6
    //   467: invokevirtual 138	java/lang/reflect/InvocationTargetException:getCause	()Ljava/lang/Throwable;
    //   470: athrow
    //   471: astore 25
    //   473: aload 25
    //   475: invokevirtual 138	java/lang/reflect/InvocationTargetException:getCause	()Ljava/lang/Throwable;
    //   478: athrow
    //   479: astore 29
    //   481: aload 29
    //   483: invokevirtual 138	java/lang/reflect/InvocationTargetException:getCause	()Ljava/lang/Throwable;
    //   486: athrow
    // Local variable table:
    //   start	length	slot	name	signature
    //   0	487	0	this	qmqqmm
    //   4	427	1	localVxvvvx	vxvvvx
    //   16	84	2	i	int
    //   28	51	3	j	int
    //   51	9	4	localMethod1	Method
    //   57	6	5	arrayOfObject1	Object[]
    //   463	3	6	localInvocationTargetException1	InvocationTargetException
    //   67	4	7	localObject1	Object
    //   109	11	8	k	int
    //   215	9	9	localMethod2	Method
    //   221	6	10	arrayOfObject2	Object[]
    //   455	3	11	localInvocationTargetException2	InvocationTargetException
    //   231	3	12	localObject2	Object
    //   262	9	13	localMethod3	Method
    //   268	6	14	arrayOfObject3	Object[]
    //   439	3	15	localInvocationTargetException3	InvocationTargetException
    //   278	3	16	localObject3	Object
    //   294	11	17	m	int
    //   305	52	18	n	int
    //   328	9	19	localMethod4	Method
    //   334	6	20	arrayOfObject4	Object[]
    //   447	3	21	localInvocationTargetException4	InvocationTargetException
    //   344	5	22	localObject4	Object
    //   396	9	23	localMethod5	Method
    //   402	6	24	arrayOfObject5	Object[]
    //   471	3	25	localInvocationTargetException5	InvocationTargetException
    //   412	3	26	localObject5	Object
    //   168	9	27	localMethod6	Method
    //   174	6	28	arrayOfObject6	Object[]
    //   479	3	29	localInvocationTargetException6	InvocationTargetException
    //   184	3	30	localObject6	Object
    // Exception table:
    //   from	to	target	type
    //   270	280	439	java/lang/reflect/InvocationTargetException
    //   336	346	447	java/lang/reflect/InvocationTargetException
    //   223	233	455	java/lang/reflect/InvocationTargetException
    //   59	69	463	java/lang/reflect/InvocationTargetException
    //   404	414	471	java/lang/reflect/InvocationTargetException
    //   176	186	479	java/lang/reflect/InvocationTargetException
  }
  
  /* Error */
  public void b0075u0075u007500750075uu0075()
  {
    // Byte code:
    //   0: ldc 2
    //   2: ldc_w 496
    //   5: sipush 187
    //   8: iconst_4
    //   9: invokestatic 66	xxxxxx/uxxxxx:bb00620062bb0062b0062b0062	(Ljava/lang/String;CC)Ljava/lang/String;
    //   12: iconst_0
    //   13: anewarray 68	java/lang/Class
    //   16: invokevirtual 82	java/lang/Class:getMethod	(Ljava/lang/String;[Ljava/lang/Class;)Ljava/lang/reflect/Method;
    //   19: astore_1
    //   20: iconst_0
    //   21: anewarray 84	java/lang/Object
    //   24: astore_2
    //   25: aload_1
    //   26: aload_0
    //   27: aload_2
    //   28: invokevirtual 96	java/lang/reflect/Method:invoke	(Ljava/lang/Object;[Ljava/lang/Object;)Ljava/lang/Object;
    //   31: astore 4
    //   33: aload 4
    //   35: checkcast 454	com/db/pwcc/dbmobile/multi_bank_aggregator/data/MbaFinancialOverviewData
    //   38: ifnonnull +46 -> 84
    //   41: aload_0
    //   42: getfield 196	uuuuuu/qmqqmm:b0076v00760076vv00760076v	Luuuuuu/vxvvvx;
    //   45: aload_0
    //   46: getfield 42	uuuuuu/qmqqmm:b00760076v0076vv00760076v	Ljava/lang/String;
    //   49: invokevirtual 201	uuuuuu/vxvvvx:buuuuu00750075u00750075	(Ljava/lang/String;)V
    //   52: aload_0
    //   53: invokevirtual 205	uuuuuu/qmqqmm:bkk006Bk006Bk006Bk006Bk	()Z
    //   56: ifeq +20 -> 76
    //   59: aload_0
    //   60: getfield 152	uuuuuu/qmqqmm:bnnnnn006E006E006En	Luuuuuu/ttssst$tsssst;
    //   63: checkcast 215	uuuuuu/mmmmqm$mqqqmm
    //   66: aload_0
    //   67: getfield 42	uuuuuu/qmqqmm:b00760076v0076vv00760076v	Ljava/lang/String;
    //   70: iconst_1
    //   71: invokeinterface 238 3 0
    //   76: return
    //   77: astore 12
    //   79: iconst_2
    //   80: putstatic 108	uuuuuu/qmqqmm:b0076vvv0076v00760076v	I
    //   83: return
    //   84: aload_0
    //   85: invokevirtual 205	uuuuuu/qmqqmm:bkk006Bk006Bk006Bk006Bk	()Z
    //   88: ifeq -12 -> 76
    //   91: getstatic 108	uuuuuu/qmqqmm:b0076vvv0076v00760076v	I
    //   94: getstatic 110	uuuuuu/qmqqmm:b00760076vv0076v00760076v	I
    //   97: iadd
    //   98: getstatic 108	uuuuuu/qmqqmm:b0076vvv0076v00760076v	I
    //   101: imul
    //   102: getstatic 122	uuuuuu/qmqqmm:bvv0076v0076v00760076v	I
    //   105: irem
    //   106: istore 5
    //   108: ldc 2
    //   110: ldc_w 498
    //   113: sipush 173
    //   116: iconst_0
    //   117: invokestatic 66	xxxxxx/uxxxxx:bb00620062bb0062b0062b0062	(Ljava/lang/String;CC)Ljava/lang/String;
    //   120: iconst_0
    //   121: anewarray 68	java/lang/Class
    //   124: invokevirtual 82	java/lang/Class:getMethod	(Ljava/lang/String;[Ljava/lang/Class;)Ljava/lang/reflect/Method;
    //   127: astore 6
    //   129: iconst_0
    //   130: anewarray 84	java/lang/Object
    //   133: astore 7
    //   135: aload 6
    //   137: aconst_null
    //   138: aload 7
    //   140: invokevirtual 96	java/lang/reflect/Method:invoke	(Ljava/lang/Object;[Ljava/lang/Object;)Ljava/lang/Object;
    //   143: astore 9
    //   145: iload 5
    //   147: aload 9
    //   149: checkcast 114	java/lang/Integer
    //   152: invokevirtual 118	java/lang/Integer:intValue	()I
    //   155: if_icmpeq +85 -> 240
    //   158: bipush 46
    //   160: putstatic 108	uuuuuu/qmqqmm:b0076vvv0076v00760076v	I
    //   163: bipush 63
    //   165: putstatic 120	uuuuuu/qmqqmm:bv0076vv0076v00760076v	I
    //   168: getstatic 108	uuuuuu/qmqqmm:b0076vvv0076v00760076v	I
    //   171: getstatic 110	uuuuuu/qmqqmm:b00760076vv0076v00760076v	I
    //   174: iadd
    //   175: getstatic 108	uuuuuu/qmqqmm:b0076vvv0076v00760076v	I
    //   178: imul
    //   179: getstatic 122	uuuuuu/qmqqmm:bvv0076v0076v00760076v	I
    //   182: irem
    //   183: getstatic 120	uuuuuu/qmqqmm:bv0076vv0076v00760076v	I
    //   186: if_icmpeq +54 -> 240
    //   189: ldc 2
    //   191: ldc_w 500
    //   194: iconst_5
    //   195: iconst_3
    //   196: invokestatic 66	xxxxxx/uxxxxx:bb00620062bb0062b0062b0062	(Ljava/lang/String;CC)Ljava/lang/String;
    //   199: iconst_0
    //   200: anewarray 68	java/lang/Class
    //   203: invokevirtual 82	java/lang/Class:getMethod	(Ljava/lang/String;[Ljava/lang/Class;)Ljava/lang/reflect/Method;
    //   206: astore 19
    //   208: iconst_0
    //   209: anewarray 84	java/lang/Object
    //   212: astore 20
    //   214: aload 19
    //   216: aconst_null
    //   217: aload 20
    //   219: invokevirtual 96	java/lang/reflect/Method:invoke	(Ljava/lang/Object;[Ljava/lang/Object;)Ljava/lang/Object;
    //   222: astore 22
    //   224: aload 22
    //   226: checkcast 114	java/lang/Integer
    //   229: invokevirtual 118	java/lang/Integer:intValue	()I
    //   232: putstatic 108	uuuuuu/qmqqmm:b0076vvv0076v00760076v	I
    //   235: bipush 91
    //   237: putstatic 120	uuuuuu/qmqqmm:bv0076vv0076v00760076v	I
    //   240: aload_0
    //   241: getfield 152	uuuuuu/qmqqmm:bnnnnn006E006E006En	Luuuuuu/ttssst$tsssst;
    //   244: checkcast 215	uuuuuu/mmmmqm$mqqqmm
    //   247: invokeinterface 503 1 0
    //   252: aconst_null
    //   253: invokevirtual 506	java/lang/String:length	()I
    //   256: pop
    //   257: getstatic 108	uuuuuu/qmqqmm:b0076vvv0076v00760076v	I
    //   260: istore 14
    //   262: iload 14
    //   264: iload 14
    //   266: getstatic 110	uuuuuu/qmqqmm:b00760076vv0076v00760076v	I
    //   269: iadd
    //   270: imul
    //   271: getstatic 122	uuuuuu/qmqqmm:bvv0076v0076v00760076v	I
    //   274: irem
    //   275: tableswitch	default:+17->292, 0:+-23->252
    //   292: ldc 2
    //   294: ldc_w 508
    //   297: sipush 166
    //   300: sipush 226
    //   303: iconst_1
    //   304: invokestatic 132	xxxxxx/uxxxxx:bbbb0062b0062b0062b0062	(Ljava/lang/String;CCC)Ljava/lang/String;
    //   307: iconst_0
    //   308: anewarray 68	java/lang/Class
    //   311: invokevirtual 82	java/lang/Class:getMethod	(Ljava/lang/String;[Ljava/lang/Class;)Ljava/lang/reflect/Method;
    //   314: astore 15
    //   316: iconst_0
    //   317: anewarray 84	java/lang/Object
    //   320: astore 16
    //   322: aload 15
    //   324: aconst_null
    //   325: aload 16
    //   327: invokevirtual 96	java/lang/reflect/Method:invoke	(Ljava/lang/Object;[Ljava/lang/Object;)Ljava/lang/Object;
    //   330: astore 18
    //   332: aload 18
    //   334: checkcast 114	java/lang/Integer
    //   337: invokevirtual 118	java/lang/Integer:intValue	()I
    //   340: putstatic 108	uuuuuu/qmqqmm:b0076vvv0076v00760076v	I
    //   343: bipush 23
    //   345: putstatic 120	uuuuuu/qmqqmm:bv0076vv0076v00760076v	I
    //   348: goto -96 -> 252
    //   351: astore 10
    //   353: bipush 93
    //   355: putstatic 108	uuuuuu/qmqqmm:b0076vvv0076v00760076v	I
    //   358: iconst_3
    //   359: istore 11
    //   361: iload 11
    //   363: iconst_0
    //   364: idiv
    //   365: istore 11
    //   367: goto -6 -> 361
    //   370: astore 8
    //   372: aload 8
    //   374: invokevirtual 138	java/lang/reflect/InvocationTargetException:getCause	()Ljava/lang/Throwable;
    //   377: athrow
    //   378: astore_3
    //   379: aload_3
    //   380: invokevirtual 138	java/lang/reflect/InvocationTargetException:getCause	()Ljava/lang/Throwable;
    //   383: athrow
    //   384: astore 17
    //   386: aload 17
    //   388: invokevirtual 138	java/lang/reflect/InvocationTargetException:getCause	()Ljava/lang/Throwable;
    //   391: athrow
    //   392: astore 21
    //   394: aload 21
    //   396: invokevirtual 138	java/lang/reflect/InvocationTargetException:getCause	()Ljava/lang/Throwable;
    //   399: athrow
    // Local variable table:
    //   start	length	slot	name	signature
    //   0	400	0	this	qmqqmm
    //   19	7	1	localMethod1	Method
    //   24	4	2	arrayOfObject1	Object[]
    //   378	2	3	localInvocationTargetException1	InvocationTargetException
    //   31	3	4	localObject1	Object
    //   106	50	5	i	int
    //   127	9	6	localMethod2	Method
    //   133	6	7	arrayOfObject2	Object[]
    //   370	3	8	localInvocationTargetException2	InvocationTargetException
    //   143	5	9	localObject2	Object
    //   351	1	10	localException1	Exception
    //   359	7	11	j	int
    //   77	1	12	localException2	Exception
    //   260	11	14	k	int
    //   314	9	15	localMethod3	Method
    //   320	6	16	arrayOfObject3	Object[]
    //   384	3	17	localInvocationTargetException3	InvocationTargetException
    //   330	3	18	localObject3	Object
    //   206	9	19	localMethod4	Method
    //   212	6	20	arrayOfObject4	Object[]
    //   392	3	21	localInvocationTargetException4	InvocationTargetException
    //   222	3	22	localObject4	Object
    // Exception table:
    //   from	to	target	type
    //   361	367	77	java/lang/Exception
    //   252	257	351	java/lang/Exception
    //   135	145	370	java/lang/reflect/InvocationTargetException
    //   25	33	378	java/lang/reflect/InvocationTargetException
    //   322	332	384	java/lang/reflect/InvocationTargetException
    //   214	224	392	java/lang/reflect/InvocationTargetException
  }
  
  /* Error */
  public void b0075uuu007500750075uu0075()
  {
    // Byte code:
    //   0: aload_0
    //   1: getfield 196	uuuuuu/qmqqmm:b0076v00760076vv00760076v	Luuuuuu/vxvvvx;
    //   4: astore_1
    //   5: getstatic 108	uuuuuu/qmqqmm:b0076vvv0076v00760076v	I
    //   8: istore_2
    //   9: iload_2
    //   10: iload_2
    //   11: getstatic 110	uuuuuu/qmqqmm:b00760076vv0076v00760076v	I
    //   14: iadd
    //   15: imul
    //   16: getstatic 122	uuuuuu/qmqqmm:bvv0076v0076v00760076v	I
    //   19: irem
    //   20: tableswitch	default:+20->40, 0:+280->300
    //   40: getstatic 108	uuuuuu/qmqqmm:b0076vvv0076v00760076v	I
    //   43: istore 17
    //   45: ldc 2
    //   47: ldc_w 511
    //   50: sipush 193
    //   53: bipush 61
    //   55: iconst_2
    //   56: invokestatic 132	xxxxxx/uxxxxx:bbbb0062b0062b0062b0062	(Ljava/lang/String;CCC)Ljava/lang/String;
    //   59: iconst_0
    //   60: anewarray 68	java/lang/Class
    //   63: invokevirtual 82	java/lang/Class:getMethod	(Ljava/lang/String;[Ljava/lang/Class;)Ljava/lang/reflect/Method;
    //   66: astore 18
    //   68: iconst_0
    //   69: anewarray 84	java/lang/Object
    //   72: astore 19
    //   74: aload 18
    //   76: aconst_null
    //   77: aload 19
    //   79: invokevirtual 96	java/lang/reflect/Method:invoke	(Ljava/lang/Object;[Ljava/lang/Object;)Ljava/lang/Object;
    //   82: astore 21
    //   84: iload 17
    //   86: iload 17
    //   88: aload 21
    //   90: checkcast 114	java/lang/Integer
    //   93: invokevirtual 118	java/lang/Integer:intValue	()I
    //   96: iadd
    //   97: imul
    //   98: getstatic 122	uuuuuu/qmqqmm:bvv0076v0076v00760076v	I
    //   101: irem
    //   102: tableswitch	default:+18->120, 0:+28->130
    //   120: bipush 23
    //   122: putstatic 108	uuuuuu/qmqqmm:b0076vvv0076v00760076v	I
    //   125: bipush 33
    //   127: putstatic 120	uuuuuu/qmqqmm:bv0076vv0076v00760076v	I
    //   130: ldc 2
    //   132: ldc_w 513
    //   135: bipush 38
    //   137: iconst_1
    //   138: invokestatic 66	xxxxxx/uxxxxx:bb00620062bb0062b0062b0062	(Ljava/lang/String;CC)Ljava/lang/String;
    //   141: iconst_0
    //   142: anewarray 68	java/lang/Class
    //   145: invokevirtual 82	java/lang/Class:getMethod	(Ljava/lang/String;[Ljava/lang/Class;)Ljava/lang/reflect/Method;
    //   148: astore 22
    //   150: iconst_0
    //   151: anewarray 84	java/lang/Object
    //   154: astore 23
    //   156: aload 22
    //   158: aconst_null
    //   159: aload 23
    //   161: invokevirtual 96	java/lang/reflect/Method:invoke	(Ljava/lang/Object;[Ljava/lang/Object;)Ljava/lang/Object;
    //   164: astore 25
    //   166: aload 25
    //   168: checkcast 114	java/lang/Integer
    //   171: invokevirtual 118	java/lang/Integer:intValue	()I
    //   174: getstatic 110	uuuuuu/qmqqmm:b00760076vv0076v00760076v	I
    //   177: iadd
    //   178: istore 26
    //   180: ldc 2
    //   182: ldc_w 508
    //   185: bipush 97
    //   187: iconst_4
    //   188: invokestatic 66	xxxxxx/uxxxxx:bb00620062bb0062b0062b0062	(Ljava/lang/String;CC)Ljava/lang/String;
    //   191: iconst_0
    //   192: anewarray 68	java/lang/Class
    //   195: invokevirtual 82	java/lang/Class:getMethod	(Ljava/lang/String;[Ljava/lang/Class;)Ljava/lang/reflect/Method;
    //   198: astore 27
    //   200: iconst_0
    //   201: anewarray 84	java/lang/Object
    //   204: astore 28
    //   206: aload 27
    //   208: aconst_null
    //   209: aload 28
    //   211: invokevirtual 96	java/lang/reflect/Method:invoke	(Ljava/lang/Object;[Ljava/lang/Object;)Ljava/lang/Object;
    //   214: astore 30
    //   216: iload 26
    //   218: aload 30
    //   220: checkcast 114	java/lang/Integer
    //   223: invokevirtual 118	java/lang/Integer:intValue	()I
    //   226: imul
    //   227: getstatic 122	uuuuuu/qmqqmm:bvv0076v0076v00760076v	I
    //   230: irem
    //   231: getstatic 120	uuuuuu/qmqqmm:bv0076vv0076v00760076v	I
    //   234: if_icmpeq +13 -> 247
    //   237: bipush 85
    //   239: putstatic 108	uuuuuu/qmqqmm:b0076vvv0076v00760076v	I
    //   242: bipush 71
    //   244: putstatic 120	uuuuuu/qmqqmm:bv0076vv0076v00760076v	I
    //   247: ldc 2
    //   249: ldc_w 508
    //   252: sipush 194
    //   255: iconst_3
    //   256: invokestatic 66	xxxxxx/uxxxxx:bb00620062bb0062b0062b0062	(Ljava/lang/String;CC)Ljava/lang/String;
    //   259: iconst_0
    //   260: anewarray 68	java/lang/Class
    //   263: invokevirtual 82	java/lang/Class:getMethod	(Ljava/lang/String;[Ljava/lang/Class;)Ljava/lang/reflect/Method;
    //   266: astore 31
    //   268: iconst_0
    //   269: anewarray 84	java/lang/Object
    //   272: astore 32
    //   274: aload 31
    //   276: aconst_null
    //   277: aload 32
    //   279: invokevirtual 96	java/lang/reflect/Method:invoke	(Ljava/lang/Object;[Ljava/lang/Object;)Ljava/lang/Object;
    //   282: astore 34
    //   284: aload 34
    //   286: checkcast 114	java/lang/Integer
    //   289: invokevirtual 118	java/lang/Integer:intValue	()I
    //   292: putstatic 108	uuuuuu/qmqqmm:b0076vvv0076v00760076v	I
    //   295: bipush 61
    //   297: putstatic 120	uuuuuu/qmqqmm:bv0076vv0076v00760076v	I
    //   300: aload_0
    //   301: getfield 42	uuuuuu/qmqqmm:b00760076v0076vv00760076v	Ljava/lang/String;
    //   304: astore_3
    //   305: ldc 2
    //   307: ldc_w 515
    //   310: bipush 108
    //   312: iconst_2
    //   313: invokestatic 66	xxxxxx/uxxxxx:bb00620062bb0062b0062b0062	(Ljava/lang/String;CC)Ljava/lang/String;
    //   316: iconst_0
    //   317: anewarray 68	java/lang/Class
    //   320: invokevirtual 82	java/lang/Class:getMethod	(Ljava/lang/String;[Ljava/lang/Class;)Ljava/lang/reflect/Method;
    //   323: astore 4
    //   325: iconst_0
    //   326: anewarray 84	java/lang/Object
    //   329: astore 5
    //   331: aload 4
    //   333: aconst_null
    //   334: aload 5
    //   336: invokevirtual 96	java/lang/reflect/Method:invoke	(Ljava/lang/Object;[Ljava/lang/Object;)Ljava/lang/Object;
    //   339: astore 7
    //   341: aload 7
    //   343: checkcast 114	java/lang/Integer
    //   346: invokevirtual 118	java/lang/Integer:intValue	()I
    //   349: getstatic 110	uuuuuu/qmqqmm:b00760076vv0076v00760076v	I
    //   352: iadd
    //   353: istore 8
    //   355: ldc 2
    //   357: ldc_w 517
    //   360: bipush 98
    //   362: iconst_1
    //   363: invokestatic 66	xxxxxx/uxxxxx:bb00620062bb0062b0062b0062	(Ljava/lang/String;CC)Ljava/lang/String;
    //   366: iconst_0
    //   367: anewarray 68	java/lang/Class
    //   370: invokevirtual 82	java/lang/Class:getMethod	(Ljava/lang/String;[Ljava/lang/Class;)Ljava/lang/reflect/Method;
    //   373: astore 9
    //   375: iconst_0
    //   376: anewarray 84	java/lang/Object
    //   379: astore 10
    //   381: aload 9
    //   383: aconst_null
    //   384: aload 10
    //   386: invokevirtual 96	java/lang/reflect/Method:invoke	(Ljava/lang/Object;[Ljava/lang/Object;)Ljava/lang/Object;
    //   389: astore 12
    //   391: iload 8
    //   393: aload 12
    //   395: checkcast 114	java/lang/Integer
    //   398: invokevirtual 118	java/lang/Integer:intValue	()I
    //   401: imul
    //   402: getstatic 122	uuuuuu/qmqqmm:bvv0076v0076v00760076v	I
    //   405: irem
    //   406: getstatic 120	uuuuuu/qmqqmm:bv0076vv0076v00760076v	I
    //   409: if_icmpeq +56 -> 465
    //   412: bipush 63
    //   414: putstatic 108	uuuuuu/qmqqmm:b0076vvv0076v00760076v	I
    //   417: ldc 2
    //   419: ldc_w 519
    //   422: sipush 179
    //   425: iconst_1
    //   426: invokestatic 66	xxxxxx/uxxxxx:bb00620062bb0062b0062b0062	(Ljava/lang/String;CC)Ljava/lang/String;
    //   429: iconst_0
    //   430: anewarray 68	java/lang/Class
    //   433: invokevirtual 82	java/lang/Class:getMethod	(Ljava/lang/String;[Ljava/lang/Class;)Ljava/lang/reflect/Method;
    //   436: astore 13
    //   438: iconst_0
    //   439: anewarray 84	java/lang/Object
    //   442: astore 14
    //   444: aload 13
    //   446: aconst_null
    //   447: aload 14
    //   449: invokevirtual 96	java/lang/reflect/Method:invoke	(Ljava/lang/Object;[Ljava/lang/Object;)Ljava/lang/Object;
    //   452: astore 16
    //   454: aload 16
    //   456: checkcast 114	java/lang/Integer
    //   459: invokevirtual 118	java/lang/Integer:intValue	()I
    //   462: putstatic 120	uuuuuu/qmqqmm:bv0076vv0076v00760076v	I
    //   465: aload_1
    //   466: aload_3
    //   467: invokevirtual 522	uuuuuu/vxvvvx:bu00750075uuuu007500750075	(Ljava/lang/String;)V
    //   470: aload_0
    //   471: invokevirtual 205	uuuuuu/qmqqmm:bkk006Bk006Bk006Bk006Bk	()Z
    //   474: ifeq +15 -> 489
    //   477: aload_0
    //   478: getfield 152	uuuuuu/qmqqmm:bnnnnn006E006E006En	Luuuuuu/ttssst$tsssst;
    //   481: checkcast 215	uuuuuu/mmmmqm$mqqqmm
    //   484: invokeinterface 401 1 0
    //   489: return
    //   490: astore 20
    //   492: aload 20
    //   494: invokevirtual 138	java/lang/reflect/InvocationTargetException:getCause	()Ljava/lang/Throwable;
    //   497: athrow
    //   498: astore 6
    //   500: aload 6
    //   502: invokevirtual 138	java/lang/reflect/InvocationTargetException:getCause	()Ljava/lang/Throwable;
    //   505: athrow
    //   506: astore 11
    //   508: aload 11
    //   510: invokevirtual 138	java/lang/reflect/InvocationTargetException:getCause	()Ljava/lang/Throwable;
    //   513: athrow
    //   514: astore 33
    //   516: aload 33
    //   518: invokevirtual 138	java/lang/reflect/InvocationTargetException:getCause	()Ljava/lang/Throwable;
    //   521: athrow
    //   522: astore 24
    //   524: aload 24
    //   526: invokevirtual 138	java/lang/reflect/InvocationTargetException:getCause	()Ljava/lang/Throwable;
    //   529: athrow
    //   530: astore 29
    //   532: aload 29
    //   534: invokevirtual 138	java/lang/reflect/InvocationTargetException:getCause	()Ljava/lang/Throwable;
    //   537: athrow
    //   538: astore 15
    //   540: aload 15
    //   542: invokevirtual 138	java/lang/reflect/InvocationTargetException:getCause	()Ljava/lang/Throwable;
    //   545: athrow
    // Local variable table:
    //   start	length	slot	name	signature
    //   0	546	0	this	qmqqmm
    //   4	462	1	localVxvvvx	vxvvvx
    //   8	8	2	i	int
    //   304	163	3	str	String
    //   323	9	4	localMethod1	Method
    //   329	6	5	arrayOfObject1	Object[]
    //   498	3	6	localInvocationTargetException1	InvocationTargetException
    //   339	3	7	localObject1	Object
    //   353	49	8	j	int
    //   373	9	9	localMethod2	Method
    //   379	6	10	arrayOfObject2	Object[]
    //   506	3	11	localInvocationTargetException2	InvocationTargetException
    //   389	5	12	localObject2	Object
    //   436	9	13	localMethod3	Method
    //   442	6	14	arrayOfObject3	Object[]
    //   538	3	15	localInvocationTargetException3	InvocationTargetException
    //   452	3	16	localObject3	Object
    //   43	55	17	k	int
    //   66	9	18	localMethod4	Method
    //   72	6	19	arrayOfObject4	Object[]
    //   490	3	20	localInvocationTargetException4	InvocationTargetException
    //   82	7	21	localObject4	Object
    //   148	9	22	localMethod5	Method
    //   154	6	23	arrayOfObject5	Object[]
    //   522	3	24	localInvocationTargetException5	InvocationTargetException
    //   164	3	25	localObject5	Object
    //   178	49	26	m	int
    //   198	9	27	localMethod6	Method
    //   204	6	28	arrayOfObject6	Object[]
    //   530	3	29	localInvocationTargetException6	InvocationTargetException
    //   214	5	30	localObject6	Object
    //   266	9	31	localMethod7	Method
    //   272	6	32	arrayOfObject7	Object[]
    //   514	3	33	localInvocationTargetException7	InvocationTargetException
    //   282	3	34	localObject7	Object
    // Exception table:
    //   from	to	target	type
    //   74	84	490	java/lang/reflect/InvocationTargetException
    //   331	341	498	java/lang/reflect/InvocationTargetException
    //   381	391	506	java/lang/reflect/InvocationTargetException
    //   274	284	514	java/lang/reflect/InvocationTargetException
    //   156	166	522	java/lang/reflect/InvocationTargetException
    //   206	216	530	java/lang/reflect/InvocationTargetException
    //   444	454	538	java/lang/reflect/InvocationTargetException
  }
  
  /* Error */
  public void b0075uuuuuu0075u0075(DbError paramDbError)
  {
    // Byte code:
    //   0: aload_0
    //   1: invokevirtual 205	uuuuuu/qmqqmm:bkk006Bk006Bk006Bk006Bk	()Z
    //   4: istore_2
    //   5: getstatic 108	uuuuuu/qmqqmm:b0076vvv0076v00760076v	I
    //   8: getstatic 110	uuuuuu/qmqqmm:b00760076vv0076v00760076v	I
    //   11: iadd
    //   12: getstatic 108	uuuuuu/qmqqmm:b0076vvv0076v00760076v	I
    //   15: imul
    //   16: getstatic 122	uuuuuu/qmqqmm:bvv0076v0076v00760076v	I
    //   19: irem
    //   20: istore_3
    //   21: getstatic 108	uuuuuu/qmqqmm:b0076vvv0076v00760076v	I
    //   24: getstatic 110	uuuuuu/qmqqmm:b00760076vv0076v00760076v	I
    //   27: iadd
    //   28: getstatic 108	uuuuuu/qmqqmm:b0076vvv0076v00760076v	I
    //   31: imul
    //   32: getstatic 122	uuuuuu/qmqqmm:bvv0076v0076v00760076v	I
    //   35: irem
    //   36: istore 4
    //   38: ldc 2
    //   40: ldc_w 525
    //   43: bipush 30
    //   45: iconst_2
    //   46: invokestatic 66	xxxxxx/uxxxxx:bb00620062bb0062b0062b0062	(Ljava/lang/String;CC)Ljava/lang/String;
    //   49: iconst_0
    //   50: anewarray 68	java/lang/Class
    //   53: invokevirtual 82	java/lang/Class:getMethod	(Ljava/lang/String;[Ljava/lang/Class;)Ljava/lang/reflect/Method;
    //   56: astore 5
    //   58: iconst_0
    //   59: anewarray 84	java/lang/Object
    //   62: astore 6
    //   64: aload 5
    //   66: aconst_null
    //   67: aload 6
    //   69: invokevirtual 96	java/lang/reflect/Method:invoke	(Ljava/lang/Object;[Ljava/lang/Object;)Ljava/lang/Object;
    //   72: astore 8
    //   74: iload 4
    //   76: aload 8
    //   78: checkcast 114	java/lang/Integer
    //   81: invokevirtual 118	java/lang/Integer:intValue	()I
    //   84: if_icmpeq +55 -> 139
    //   87: ldc 2
    //   89: ldc_w 527
    //   92: bipush 20
    //   94: iconst_4
    //   95: invokestatic 66	xxxxxx/uxxxxx:bb00620062bb0062b0062b0062	(Ljava/lang/String;CC)Ljava/lang/String;
    //   98: iconst_0
    //   99: anewarray 68	java/lang/Class
    //   102: invokevirtual 82	java/lang/Class:getMethod	(Ljava/lang/String;[Ljava/lang/Class;)Ljava/lang/reflect/Method;
    //   105: astore 36
    //   107: iconst_0
    //   108: anewarray 84	java/lang/Object
    //   111: astore 37
    //   113: aload 36
    //   115: aconst_null
    //   116: aload 37
    //   118: invokevirtual 96	java/lang/reflect/Method:invoke	(Ljava/lang/Object;[Ljava/lang/Object;)Ljava/lang/Object;
    //   121: astore 39
    //   123: aload 39
    //   125: checkcast 114	java/lang/Integer
    //   128: invokevirtual 118	java/lang/Integer:intValue	()I
    //   131: putstatic 108	uuuuuu/qmqqmm:b0076vvv0076v00760076v	I
    //   134: bipush 43
    //   136: putstatic 120	uuuuuu/qmqqmm:bv0076vv0076v00760076v	I
    //   139: iload_3
    //   140: getstatic 120	uuuuuu/qmqqmm:bv0076vv0076v00760076v	I
    //   143: if_icmpeq +173 -> 316
    //   146: ldc 2
    //   148: ldc_w 259
    //   151: sipush 131
    //   154: iconst_0
    //   155: invokestatic 66	xxxxxx/uxxxxx:bb00620062bb0062b0062b0062	(Ljava/lang/String;CC)Ljava/lang/String;
    //   158: iconst_0
    //   159: anewarray 68	java/lang/Class
    //   162: invokevirtual 82	java/lang/Class:getMethod	(Ljava/lang/String;[Ljava/lang/Class;)Ljava/lang/reflect/Method;
    //   165: astore 24
    //   167: iconst_0
    //   168: anewarray 84	java/lang/Object
    //   171: astore 25
    //   173: aload 24
    //   175: aconst_null
    //   176: aload 25
    //   178: invokevirtual 96	java/lang/reflect/Method:invoke	(Ljava/lang/Object;[Ljava/lang/Object;)Ljava/lang/Object;
    //   181: astore 27
    //   183: aload 27
    //   185: checkcast 114	java/lang/Integer
    //   188: invokevirtual 118	java/lang/Integer:intValue	()I
    //   191: putstatic 108	uuuuuu/qmqqmm:b0076vvv0076v00760076v	I
    //   194: iconst_1
    //   195: putstatic 120	uuuuuu/qmqqmm:bv0076vv0076v00760076v	I
    //   198: getstatic 108	uuuuuu/qmqqmm:b0076vvv0076v00760076v	I
    //   201: getstatic 110	uuuuuu/qmqqmm:b00760076vv0076v00760076v	I
    //   204: iadd
    //   205: getstatic 108	uuuuuu/qmqqmm:b0076vvv0076v00760076v	I
    //   208: imul
    //   209: getstatic 122	uuuuuu/qmqqmm:bvv0076v0076v00760076v	I
    //   212: irem
    //   213: getstatic 120	uuuuuu/qmqqmm:bv0076vv0076v00760076v	I
    //   216: if_icmpeq +100 -> 316
    //   219: ldc 2
    //   221: ldc_w 529
    //   224: bipush 69
    //   226: sipush 145
    //   229: iconst_0
    //   230: invokestatic 132	xxxxxx/uxxxxx:bbbb0062b0062b0062b0062	(Ljava/lang/String;CCC)Ljava/lang/String;
    //   233: iconst_0
    //   234: anewarray 68	java/lang/Class
    //   237: invokevirtual 82	java/lang/Class:getMethod	(Ljava/lang/String;[Ljava/lang/Class;)Ljava/lang/reflect/Method;
    //   240: astore 28
    //   242: iconst_0
    //   243: anewarray 84	java/lang/Object
    //   246: astore 29
    //   248: aload 28
    //   250: aconst_null
    //   251: aload 29
    //   253: invokevirtual 96	java/lang/reflect/Method:invoke	(Ljava/lang/Object;[Ljava/lang/Object;)Ljava/lang/Object;
    //   256: astore 31
    //   258: aload 31
    //   260: checkcast 114	java/lang/Integer
    //   263: invokevirtual 118	java/lang/Integer:intValue	()I
    //   266: putstatic 108	uuuuuu/qmqqmm:b0076vvv0076v00760076v	I
    //   269: ldc 2
    //   271: ldc_w 302
    //   274: bipush 83
    //   276: iconst_2
    //   277: invokestatic 66	xxxxxx/uxxxxx:bb00620062bb0062b0062b0062	(Ljava/lang/String;CC)Ljava/lang/String;
    //   280: iconst_0
    //   281: anewarray 68	java/lang/Class
    //   284: invokevirtual 82	java/lang/Class:getMethod	(Ljava/lang/String;[Ljava/lang/Class;)Ljava/lang/reflect/Method;
    //   287: astore 32
    //   289: iconst_0
    //   290: anewarray 84	java/lang/Object
    //   293: astore 33
    //   295: aload 32
    //   297: aconst_null
    //   298: aload 33
    //   300: invokevirtual 96	java/lang/reflect/Method:invoke	(Ljava/lang/Object;[Ljava/lang/Object;)Ljava/lang/Object;
    //   303: astore 35
    //   305: aload 35
    //   307: checkcast 114	java/lang/Integer
    //   310: invokevirtual 118	java/lang/Integer:intValue	()I
    //   313: putstatic 120	uuuuuu/qmqqmm:bv0076vv0076v00760076v	I
    //   316: iload_2
    //   317: ifeq +197 -> 514
    //   320: aload_0
    //   321: getfield 152	uuuuuu/qmqqmm:bnnnnn006E006E006En	Luuuuuu/ttssst$tsssst;
    //   324: checkcast 215	uuuuuu/mmmmqm$mqqqmm
    //   327: astore 9
    //   329: ldc 2
    //   331: ldc_w 531
    //   334: sipush 246
    //   337: iconst_1
    //   338: invokestatic 66	xxxxxx/uxxxxx:bb00620062bb0062b0062b0062	(Ljava/lang/String;CC)Ljava/lang/String;
    //   341: iconst_0
    //   342: anewarray 68	java/lang/Class
    //   345: invokevirtual 82	java/lang/Class:getMethod	(Ljava/lang/String;[Ljava/lang/Class;)Ljava/lang/reflect/Method;
    //   348: astore 10
    //   350: iconst_0
    //   351: anewarray 84	java/lang/Object
    //   354: astore 11
    //   356: aload 10
    //   358: aconst_null
    //   359: aload 11
    //   361: invokevirtual 96	java/lang/reflect/Method:invoke	(Ljava/lang/Object;[Ljava/lang/Object;)Ljava/lang/Object;
    //   364: astore 13
    //   366: aload 13
    //   368: checkcast 114	java/lang/Integer
    //   371: invokevirtual 118	java/lang/Integer:intValue	()I
    //   374: istore 14
    //   376: iload 14
    //   378: iload 14
    //   380: getstatic 110	uuuuuu/qmqqmm:b00760076vv0076v00760076v	I
    //   383: iadd
    //   384: imul
    //   385: istore 15
    //   387: ldc 2
    //   389: ldc_w 533
    //   392: bipush 93
    //   394: iconst_2
    //   395: invokestatic 66	xxxxxx/uxxxxx:bb00620062bb0062b0062b0062	(Ljava/lang/String;CC)Ljava/lang/String;
    //   398: iconst_0
    //   399: anewarray 68	java/lang/Class
    //   402: invokevirtual 82	java/lang/Class:getMethod	(Ljava/lang/String;[Ljava/lang/Class;)Ljava/lang/reflect/Method;
    //   405: astore 16
    //   407: iconst_0
    //   408: anewarray 84	java/lang/Object
    //   411: astore 17
    //   413: aload 16
    //   415: aconst_null
    //   416: aload 17
    //   418: invokevirtual 96	java/lang/reflect/Method:invoke	(Ljava/lang/Object;[Ljava/lang/Object;)Ljava/lang/Object;
    //   421: astore 19
    //   423: iload 15
    //   425: aload 19
    //   427: checkcast 114	java/lang/Integer
    //   430: invokevirtual 118	java/lang/Integer:intValue	()I
    //   433: irem
    //   434: tableswitch	default:+18->452, 0:+72->506
    //   452: bipush 55
    //   454: putstatic 108	uuuuuu/qmqqmm:b0076vvv0076v00760076v	I
    //   457: ldc 2
    //   459: ldc_w 535
    //   462: bipush 82
    //   464: bipush 60
    //   466: iconst_2
    //   467: invokestatic 132	xxxxxx/uxxxxx:bbbb0062b0062b0062b0062	(Ljava/lang/String;CCC)Ljava/lang/String;
    //   470: iconst_0
    //   471: anewarray 68	java/lang/Class
    //   474: invokevirtual 82	java/lang/Class:getMethod	(Ljava/lang/String;[Ljava/lang/Class;)Ljava/lang/reflect/Method;
    //   477: astore 20
    //   479: iconst_0
    //   480: anewarray 84	java/lang/Object
    //   483: astore 21
    //   485: aload 20
    //   487: aconst_null
    //   488: aload 21
    //   490: invokevirtual 96	java/lang/reflect/Method:invoke	(Ljava/lang/Object;[Ljava/lang/Object;)Ljava/lang/Object;
    //   493: astore 23
    //   495: aload 23
    //   497: checkcast 114	java/lang/Integer
    //   500: invokevirtual 118	java/lang/Integer:intValue	()I
    //   503: putstatic 120	uuuuuu/qmqqmm:bv0076vv0076v00760076v	I
    //   506: aload 9
    //   508: aload_1
    //   509: invokeinterface 538 2 0
    //   514: return
    //   515: astore 22
    //   517: aload 22
    //   519: invokevirtual 138	java/lang/reflect/InvocationTargetException:getCause	()Ljava/lang/Throwable;
    //   522: athrow
    //   523: astore 18
    //   525: aload 18
    //   527: invokevirtual 138	java/lang/reflect/InvocationTargetException:getCause	()Ljava/lang/Throwable;
    //   530: athrow
    //   531: astore 26
    //   533: aload 26
    //   535: invokevirtual 138	java/lang/reflect/InvocationTargetException:getCause	()Ljava/lang/Throwable;
    //   538: athrow
    //   539: astore 7
    //   541: aload 7
    //   543: invokevirtual 138	java/lang/reflect/InvocationTargetException:getCause	()Ljava/lang/Throwable;
    //   546: athrow
    //   547: astore 12
    //   549: aload 12
    //   551: invokevirtual 138	java/lang/reflect/InvocationTargetException:getCause	()Ljava/lang/Throwable;
    //   554: athrow
    //   555: astore 38
    //   557: aload 38
    //   559: invokevirtual 138	java/lang/reflect/InvocationTargetException:getCause	()Ljava/lang/Throwable;
    //   562: athrow
    //   563: astore 30
    //   565: aload 30
    //   567: invokevirtual 138	java/lang/reflect/InvocationTargetException:getCause	()Ljava/lang/Throwable;
    //   570: athrow
    //   571: astore 34
    //   573: aload 34
    //   575: invokevirtual 138	java/lang/reflect/InvocationTargetException:getCause	()Ljava/lang/Throwable;
    //   578: athrow
    // Local variable table:
    //   start	length	slot	name	signature
    //   0	579	0	this	qmqqmm
    //   0	579	1	paramDbError	DbError
    //   4	313	2	bool	boolean
    //   20	124	3	i	int
    //   36	49	4	j	int
    //   56	9	5	localMethod1	Method
    //   62	6	6	arrayOfObject1	Object[]
    //   539	3	7	localInvocationTargetException1	InvocationTargetException
    //   72	5	8	localObject1	Object
    //   327	180	9	localMqqqmm	mmmmqm.mqqqmm
    //   348	9	10	localMethod2	Method
    //   354	6	11	arrayOfObject2	Object[]
    //   547	3	12	localInvocationTargetException2	InvocationTargetException
    //   364	3	13	localObject2	Object
    //   374	11	14	k	int
    //   385	49	15	m	int
    //   405	9	16	localMethod3	Method
    //   411	6	17	arrayOfObject3	Object[]
    //   523	3	18	localInvocationTargetException3	InvocationTargetException
    //   421	5	19	localObject3	Object
    //   477	9	20	localMethod4	Method
    //   483	6	21	arrayOfObject4	Object[]
    //   515	3	22	localInvocationTargetException4	InvocationTargetException
    //   493	3	23	localObject4	Object
    //   165	9	24	localMethod5	Method
    //   171	6	25	arrayOfObject5	Object[]
    //   531	3	26	localInvocationTargetException5	InvocationTargetException
    //   181	3	27	localObject5	Object
    //   240	9	28	localMethod6	Method
    //   246	6	29	arrayOfObject6	Object[]
    //   563	3	30	localInvocationTargetException6	InvocationTargetException
    //   256	3	31	localObject6	Object
    //   287	9	32	localMethod7	Method
    //   293	6	33	arrayOfObject7	Object[]
    //   571	3	34	localInvocationTargetException7	InvocationTargetException
    //   303	3	35	localObject7	Object
    //   105	9	36	localMethod8	Method
    //   111	6	37	arrayOfObject8	Object[]
    //   555	3	38	localInvocationTargetException8	InvocationTargetException
    //   121	3	39	localObject8	Object
    // Exception table:
    //   from	to	target	type
    //   485	495	515	java/lang/reflect/InvocationTargetException
    //   413	423	523	java/lang/reflect/InvocationTargetException
    //   173	183	531	java/lang/reflect/InvocationTargetException
    //   64	74	539	java/lang/reflect/InvocationTargetException
    //   356	366	547	java/lang/reflect/InvocationTargetException
    //   113	123	555	java/lang/reflect/InvocationTargetException
    //   248	258	563	java/lang/reflect/InvocationTargetException
    //   295	305	571	java/lang/reflect/InvocationTargetException
  }
  
  /* Error */
  public RSAPublicKey bu007500750075u00750075uu0075()
  {
    // Byte code:
    //   0: getstatic 108	uuuuuu/qmqqmm:b0076vvv0076v00760076v	I
    //   3: istore_1
    //   4: iload_1
    //   5: iload_1
    //   6: getstatic 110	uuuuuu/qmqqmm:b00760076vv0076v00760076v	I
    //   9: iadd
    //   10: imul
    //   11: getstatic 122	uuuuuu/qmqqmm:bvv0076v0076v00760076v	I
    //   14: irem
    //   15: tableswitch	default:+17->32, 0:+443->458
    //   32: ldc 2
    //   34: ldc_w 261
    //   37: sipush 185
    //   40: iconst_5
    //   41: invokestatic 66	xxxxxx/uxxxxx:bb00620062bb0062b0062b0062	(Ljava/lang/String;CC)Ljava/lang/String;
    //   44: iconst_0
    //   45: anewarray 68	java/lang/Class
    //   48: invokevirtual 82	java/lang/Class:getMethod	(Ljava/lang/String;[Ljava/lang/Class;)Ljava/lang/reflect/Method;
    //   51: astore_2
    //   52: iconst_0
    //   53: anewarray 84	java/lang/Object
    //   56: astore_3
    //   57: aload_2
    //   58: aconst_null
    //   59: aload_3
    //   60: invokevirtual 96	java/lang/reflect/Method:invoke	(Ljava/lang/Object;[Ljava/lang/Object;)Ljava/lang/Object;
    //   63: astore 5
    //   65: aload 5
    //   67: checkcast 114	java/lang/Integer
    //   70: invokevirtual 118	java/lang/Integer:intValue	()I
    //   73: putstatic 108	uuuuuu/qmqqmm:b0076vvv0076v00760076v	I
    //   76: getstatic 108	uuuuuu/qmqqmm:b0076vvv0076v00760076v	I
    //   79: getstatic 110	uuuuuu/qmqqmm:b00760076vv0076v00760076v	I
    //   82: iadd
    //   83: getstatic 108	uuuuuu/qmqqmm:b0076vvv0076v00760076v	I
    //   86: imul
    //   87: getstatic 122	uuuuuu/qmqqmm:bvv0076v0076v00760076v	I
    //   90: irem
    //   91: getstatic 120	uuuuuu/qmqqmm:bv0076vv0076v00760076v	I
    //   94: if_icmpeq +56 -> 150
    //   97: ldc 2
    //   99: ldc_w 542
    //   102: sipush 141
    //   105: iconst_3
    //   106: invokestatic 66	xxxxxx/uxxxxx:bb00620062bb0062b0062b0062	(Ljava/lang/String;CC)Ljava/lang/String;
    //   109: iconst_0
    //   110: anewarray 68	java/lang/Class
    //   113: invokevirtual 82	java/lang/Class:getMethod	(Ljava/lang/String;[Ljava/lang/Class;)Ljava/lang/reflect/Method;
    //   116: astore 29
    //   118: iconst_0
    //   119: anewarray 84	java/lang/Object
    //   122: astore 30
    //   124: aload 29
    //   126: aconst_null
    //   127: aload 30
    //   129: invokevirtual 96	java/lang/reflect/Method:invoke	(Ljava/lang/Object;[Ljava/lang/Object;)Ljava/lang/Object;
    //   132: astore 32
    //   134: aload 32
    //   136: checkcast 114	java/lang/Integer
    //   139: invokevirtual 118	java/lang/Integer:intValue	()I
    //   142: putstatic 108	uuuuuu/qmqqmm:b0076vvv0076v00760076v	I
    //   145: bipush 43
    //   147: putstatic 120	uuuuuu/qmqqmm:bv0076vv0076v00760076v	I
    //   150: bipush 66
    //   152: putstatic 120	uuuuuu/qmqqmm:bv0076vv0076v00760076v	I
    //   155: ldc 2
    //   157: ldc_w 298
    //   160: bipush 124
    //   162: iconst_4
    //   163: invokestatic 66	xxxxxx/uxxxxx:bb00620062bb0062b0062b0062	(Ljava/lang/String;CC)Ljava/lang/String;
    //   166: iconst_0
    //   167: anewarray 68	java/lang/Class
    //   170: invokevirtual 82	java/lang/Class:getMethod	(Ljava/lang/String;[Ljava/lang/Class;)Ljava/lang/reflect/Method;
    //   173: astore 6
    //   175: iconst_0
    //   176: anewarray 84	java/lang/Object
    //   179: astore 7
    //   181: aload 6
    //   183: aconst_null
    //   184: aload 7
    //   186: invokevirtual 96	java/lang/reflect/Method:invoke	(Ljava/lang/Object;[Ljava/lang/Object;)Ljava/lang/Object;
    //   189: astore 9
    //   191: aload 9
    //   193: checkcast 114	java/lang/Integer
    //   196: invokevirtual 118	java/lang/Integer:intValue	()I
    //   199: getstatic 110	uuuuuu/qmqqmm:b00760076vv0076v00760076v	I
    //   202: iadd
    //   203: istore 10
    //   205: ldc 2
    //   207: ldc_w 544
    //   210: sipush 246
    //   213: sipush 193
    //   216: iconst_1
    //   217: invokestatic 132	xxxxxx/uxxxxx:bbbb0062b0062b0062b0062	(Ljava/lang/String;CCC)Ljava/lang/String;
    //   220: iconst_0
    //   221: anewarray 68	java/lang/Class
    //   224: invokevirtual 82	java/lang/Class:getMethod	(Ljava/lang/String;[Ljava/lang/Class;)Ljava/lang/reflect/Method;
    //   227: astore 11
    //   229: iconst_0
    //   230: anewarray 84	java/lang/Object
    //   233: astore 12
    //   235: aload 11
    //   237: aconst_null
    //   238: aload 12
    //   240: invokevirtual 96	java/lang/reflect/Method:invoke	(Ljava/lang/Object;[Ljava/lang/Object;)Ljava/lang/Object;
    //   243: astore 14
    //   245: iload 10
    //   247: aload 14
    //   249: checkcast 114	java/lang/Integer
    //   252: invokevirtual 118	java/lang/Integer:intValue	()I
    //   255: imul
    //   256: getstatic 122	uuuuuu/qmqqmm:bvv0076v0076v00760076v	I
    //   259: irem
    //   260: getstatic 120	uuuuuu/qmqqmm:bv0076vv0076v00760076v	I
    //   263: if_icmpeq +195 -> 458
    //   266: bipush 33
    //   268: putstatic 108	uuuuuu/qmqqmm:b0076vvv0076v00760076v	I
    //   271: ldc 2
    //   273: ldc_w 546
    //   276: bipush 12
    //   278: sipush 207
    //   281: iconst_2
    //   282: invokestatic 132	xxxxxx/uxxxxx:bbbb0062b0062b0062b0062	(Ljava/lang/String;CCC)Ljava/lang/String;
    //   285: iconst_0
    //   286: anewarray 68	java/lang/Class
    //   289: invokevirtual 82	java/lang/Class:getMethod	(Ljava/lang/String;[Ljava/lang/Class;)Ljava/lang/reflect/Method;
    //   292: astore 15
    //   294: iconst_0
    //   295: anewarray 84	java/lang/Object
    //   298: astore 16
    //   300: aload 15
    //   302: aconst_null
    //   303: aload 16
    //   305: invokevirtual 96	java/lang/reflect/Method:invoke	(Ljava/lang/Object;[Ljava/lang/Object;)Ljava/lang/Object;
    //   308: astore 18
    //   310: aload 18
    //   312: checkcast 114	java/lang/Integer
    //   315: invokevirtual 118	java/lang/Integer:intValue	()I
    //   318: putstatic 120	uuuuuu/qmqqmm:bv0076vv0076v00760076v	I
    //   321: getstatic 108	uuuuuu/qmqqmm:b0076vvv0076v00760076v	I
    //   324: istore 19
    //   326: ldc 2
    //   328: ldc_w 271
    //   331: bipush 63
    //   333: sipush 145
    //   336: iconst_3
    //   337: invokestatic 132	xxxxxx/uxxxxx:bbbb0062b0062b0062b0062	(Ljava/lang/String;CCC)Ljava/lang/String;
    //   340: iconst_0
    //   341: anewarray 68	java/lang/Class
    //   344: invokevirtual 82	java/lang/Class:getMethod	(Ljava/lang/String;[Ljava/lang/Class;)Ljava/lang/reflect/Method;
    //   347: astore 20
    //   349: iconst_0
    //   350: anewarray 84	java/lang/Object
    //   353: astore 21
    //   355: aload 20
    //   357: aconst_null
    //   358: aload 21
    //   360: invokevirtual 96	java/lang/reflect/Method:invoke	(Ljava/lang/Object;[Ljava/lang/Object;)Ljava/lang/Object;
    //   363: astore 23
    //   365: iload 19
    //   367: iload 19
    //   369: aload 23
    //   371: checkcast 114	java/lang/Integer
    //   374: invokevirtual 118	java/lang/Integer:intValue	()I
    //   377: iadd
    //   378: imul
    //   379: istore 24
    //   381: ldc 2
    //   383: ldc_w 548
    //   386: bipush 36
    //   388: iconst_2
    //   389: invokestatic 66	xxxxxx/uxxxxx:bb00620062bb0062b0062b0062	(Ljava/lang/String;CC)Ljava/lang/String;
    //   392: iconst_0
    //   393: anewarray 68	java/lang/Class
    //   396: invokevirtual 82	java/lang/Class:getMethod	(Ljava/lang/String;[Ljava/lang/Class;)Ljava/lang/reflect/Method;
    //   399: astore 25
    //   401: iconst_0
    //   402: anewarray 84	java/lang/Object
    //   405: astore 26
    //   407: aload 25
    //   409: aconst_null
    //   410: aload 26
    //   412: invokevirtual 96	java/lang/reflect/Method:invoke	(Ljava/lang/Object;[Ljava/lang/Object;)Ljava/lang/Object;
    //   415: astore 28
    //   417: iload 24
    //   419: aload 28
    //   421: checkcast 114	java/lang/Integer
    //   424: invokevirtual 118	java/lang/Integer:intValue	()I
    //   427: irem
    //   428: tableswitch	default:+20->448, 0:+30->458
    //   448: bipush 36
    //   450: putstatic 108	uuuuuu/qmqqmm:b0076vvv0076v00760076v	I
    //   453: bipush 22
    //   455: putstatic 120	uuuuuu/qmqqmm:bv0076vv0076v00760076v	I
    //   458: aload_0
    //   459: getfield 550	uuuuuu/qmqqmm:b0076007600760076vv00760076v	Ljava/security/interfaces/RSAPublicKey;
    //   462: areturn
    //   463: astore 8
    //   465: aload 8
    //   467: invokevirtual 138	java/lang/reflect/InvocationTargetException:getCause	()Ljava/lang/Throwable;
    //   470: athrow
    //   471: astore 4
    //   473: aload 4
    //   475: invokevirtual 138	java/lang/reflect/InvocationTargetException:getCause	()Ljava/lang/Throwable;
    //   478: athrow
    //   479: astore 22
    //   481: aload 22
    //   483: invokevirtual 138	java/lang/reflect/InvocationTargetException:getCause	()Ljava/lang/Throwable;
    //   486: athrow
    //   487: astore 27
    //   489: aload 27
    //   491: invokevirtual 138	java/lang/reflect/InvocationTargetException:getCause	()Ljava/lang/Throwable;
    //   494: athrow
    //   495: astore 13
    //   497: aload 13
    //   499: invokevirtual 138	java/lang/reflect/InvocationTargetException:getCause	()Ljava/lang/Throwable;
    //   502: athrow
    //   503: astore 17
    //   505: aload 17
    //   507: invokevirtual 138	java/lang/reflect/InvocationTargetException:getCause	()Ljava/lang/Throwable;
    //   510: athrow
    //   511: astore 31
    //   513: aload 31
    //   515: invokevirtual 138	java/lang/reflect/InvocationTargetException:getCause	()Ljava/lang/Throwable;
    //   518: athrow
    // Local variable table:
    //   start	length	slot	name	signature
    //   0	519	0	this	qmqqmm
    //   3	8	1	i	int
    //   51	7	2	localMethod1	Method
    //   56	4	3	arrayOfObject1	Object[]
    //   471	3	4	localInvocationTargetException1	InvocationTargetException
    //   63	3	5	localObject1	Object
    //   173	9	6	localMethod2	Method
    //   179	6	7	arrayOfObject2	Object[]
    //   463	3	8	localInvocationTargetException2	InvocationTargetException
    //   189	3	9	localObject2	Object
    //   203	53	10	j	int
    //   227	9	11	localMethod3	Method
    //   233	6	12	arrayOfObject3	Object[]
    //   495	3	13	localInvocationTargetException3	InvocationTargetException
    //   243	5	14	localObject3	Object
    //   292	9	15	localMethod4	Method
    //   298	6	16	arrayOfObject4	Object[]
    //   503	3	17	localInvocationTargetException4	InvocationTargetException
    //   308	3	18	localObject4	Object
    //   324	55	19	k	int
    //   347	9	20	localMethod5	Method
    //   353	6	21	arrayOfObject5	Object[]
    //   479	3	22	localInvocationTargetException5	InvocationTargetException
    //   363	7	23	localObject5	Object
    //   379	49	24	m	int
    //   399	9	25	localMethod6	Method
    //   405	6	26	arrayOfObject6	Object[]
    //   487	3	27	localInvocationTargetException6	InvocationTargetException
    //   415	5	28	localObject6	Object
    //   116	9	29	localMethod7	Method
    //   122	6	30	arrayOfObject7	Object[]
    //   511	3	31	localInvocationTargetException7	InvocationTargetException
    //   132	3	32	localObject7	Object
    // Exception table:
    //   from	to	target	type
    //   181	191	463	java/lang/reflect/InvocationTargetException
    //   57	65	471	java/lang/reflect/InvocationTargetException
    //   355	365	479	java/lang/reflect/InvocationTargetException
    //   407	417	487	java/lang/reflect/InvocationTargetException
    //   235	245	495	java/lang/reflect/InvocationTargetException
    //   300	310	503	java/lang/reflect/InvocationTargetException
    //   124	134	511	java/lang/reflect/InvocationTargetException
  }
  
  /* Error */
  public void bu0075u0075u00750075uu0075(com.db.pwcc.dbmobile.model.banking.Account paramAccount)
  {
    // Byte code:
    //   0: invokestatic 558	java/util/Locale:getDefault	()Ljava/util/Locale;
    //   3: astore_2
    //   4: getstatic 108	uuuuuu/qmqqmm:b0076vvv0076v00760076v	I
    //   7: getstatic 110	uuuuuu/qmqqmm:b00760076vv0076v00760076v	I
    //   10: iadd
    //   11: getstatic 108	uuuuuu/qmqqmm:b0076vvv0076v00760076v	I
    //   14: imul
    //   15: getstatic 122	uuuuuu/qmqqmm:bvv0076v0076v00760076v	I
    //   18: irem
    //   19: getstatic 120	uuuuuu/qmqqmm:bv0076vv0076v00760076v	I
    //   22: if_icmpeq +101 -> 123
    //   25: ldc 2
    //   27: ldc_w 560
    //   30: bipush 79
    //   32: sipush 180
    //   35: iconst_1
    //   36: invokestatic 132	xxxxxx/uxxxxx:bbbb0062b0062b0062b0062	(Ljava/lang/String;CCC)Ljava/lang/String;
    //   39: iconst_0
    //   40: anewarray 68	java/lang/Class
    //   43: invokevirtual 82	java/lang/Class:getMethod	(Ljava/lang/String;[Ljava/lang/Class;)Ljava/lang/reflect/Method;
    //   46: astore 39
    //   48: iconst_0
    //   49: anewarray 84	java/lang/Object
    //   52: astore 40
    //   54: aload 39
    //   56: aconst_null
    //   57: aload 40
    //   59: invokevirtual 96	java/lang/reflect/Method:invoke	(Ljava/lang/Object;[Ljava/lang/Object;)Ljava/lang/Object;
    //   62: astore 42
    //   64: aload 42
    //   66: checkcast 114	java/lang/Integer
    //   69: invokevirtual 118	java/lang/Integer:intValue	()I
    //   72: putstatic 108	uuuuuu/qmqqmm:b0076vvv0076v00760076v	I
    //   75: ldc 2
    //   77: ldc_w 562
    //   80: sipush 240
    //   83: iconst_4
    //   84: invokestatic 66	xxxxxx/uxxxxx:bb00620062bb0062b0062b0062	(Ljava/lang/String;CC)Ljava/lang/String;
    //   87: iconst_0
    //   88: anewarray 68	java/lang/Class
    //   91: invokevirtual 82	java/lang/Class:getMethod	(Ljava/lang/String;[Ljava/lang/Class;)Ljava/lang/reflect/Method;
    //   94: astore 43
    //   96: iconst_0
    //   97: anewarray 84	java/lang/Object
    //   100: astore 44
    //   102: aload 43
    //   104: aconst_null
    //   105: aload 44
    //   107: invokevirtual 96	java/lang/reflect/Method:invoke	(Ljava/lang/Object;[Ljava/lang/Object;)Ljava/lang/Object;
    //   110: astore 46
    //   112: aload 46
    //   114: checkcast 114	java/lang/Integer
    //   117: invokevirtual 118	java/lang/Integer:intValue	()I
    //   120: putstatic 120	uuuuuu/qmqqmm:bv0076vv0076v00760076v	I
    //   123: aload_1
    //   124: aload_2
    //   125: invokevirtual 568	com/db/pwcc/dbmobile/model/banking/Account:getBookedBalanceInBaseCurrencyLocalized	(Ljava/util/Locale;)Ljava/lang/String;
    //   128: astore_3
    //   129: aload_1
    //   130: invokevirtual 571	com/db/pwcc/dbmobile/model/banking/Account:shouldDisplayOverallBalanceIncludingPrebookedTransactions	()Z
    //   133: istore 4
    //   135: aconst_null
    //   136: astore 5
    //   138: iload 4
    //   140: ifeq +218 -> 358
    //   143: getstatic 108	uuuuuu/qmqqmm:b0076vvv0076v00760076v	I
    //   146: istore 21
    //   148: ldc 2
    //   150: ldc_w 573
    //   153: bipush 87
    //   155: bipush 104
    //   157: iconst_2
    //   158: invokestatic 132	xxxxxx/uxxxxx:bbbb0062b0062b0062b0062	(Ljava/lang/String;CCC)Ljava/lang/String;
    //   161: iconst_0
    //   162: anewarray 68	java/lang/Class
    //   165: invokevirtual 82	java/lang/Class:getMethod	(Ljava/lang/String;[Ljava/lang/Class;)Ljava/lang/reflect/Method;
    //   168: astore 22
    //   170: iconst_0
    //   171: anewarray 84	java/lang/Object
    //   174: astore 23
    //   176: aload 22
    //   178: aconst_null
    //   179: aload 23
    //   181: invokevirtual 96	java/lang/reflect/Method:invoke	(Ljava/lang/Object;[Ljava/lang/Object;)Ljava/lang/Object;
    //   184: astore 25
    //   186: iload 21
    //   188: aload 25
    //   190: checkcast 114	java/lang/Integer
    //   193: invokevirtual 118	java/lang/Integer:intValue	()I
    //   196: iadd
    //   197: getstatic 108	uuuuuu/qmqqmm:b0076vvv0076v00760076v	I
    //   200: imul
    //   201: istore 26
    //   203: ldc 2
    //   205: ldc_w 575
    //   208: bipush 85
    //   210: iconst_1
    //   211: invokestatic 66	xxxxxx/uxxxxx:bb00620062bb0062b0062b0062	(Ljava/lang/String;CC)Ljava/lang/String;
    //   214: iconst_0
    //   215: anewarray 68	java/lang/Class
    //   218: invokevirtual 82	java/lang/Class:getMethod	(Ljava/lang/String;[Ljava/lang/Class;)Ljava/lang/reflect/Method;
    //   221: astore 27
    //   223: iconst_0
    //   224: anewarray 84	java/lang/Object
    //   227: astore 28
    //   229: aload 27
    //   231: aconst_null
    //   232: aload 28
    //   234: invokevirtual 96	java/lang/reflect/Method:invoke	(Ljava/lang/Object;[Ljava/lang/Object;)Ljava/lang/Object;
    //   237: astore 30
    //   239: iload 26
    //   241: aload 30
    //   243: checkcast 114	java/lang/Integer
    //   246: invokevirtual 118	java/lang/Integer:intValue	()I
    //   249: irem
    //   250: getstatic 120	uuuuuu/qmqqmm:bv0076vv0076v00760076v	I
    //   253: if_icmpeq +98 -> 351
    //   256: ldc 2
    //   258: ldc_w 577
    //   261: bipush 45
    //   263: iconst_1
    //   264: invokestatic 66	xxxxxx/uxxxxx:bb00620062bb0062b0062b0062	(Ljava/lang/String;CC)Ljava/lang/String;
    //   267: iconst_0
    //   268: anewarray 68	java/lang/Class
    //   271: invokevirtual 82	java/lang/Class:getMethod	(Ljava/lang/String;[Ljava/lang/Class;)Ljava/lang/reflect/Method;
    //   274: astore 31
    //   276: iconst_0
    //   277: anewarray 84	java/lang/Object
    //   280: astore 32
    //   282: aload 31
    //   284: aconst_null
    //   285: aload 32
    //   287: invokevirtual 96	java/lang/reflect/Method:invoke	(Ljava/lang/Object;[Ljava/lang/Object;)Ljava/lang/Object;
    //   290: astore 34
    //   292: aload 34
    //   294: checkcast 114	java/lang/Integer
    //   297: invokevirtual 118	java/lang/Integer:intValue	()I
    //   300: putstatic 108	uuuuuu/qmqqmm:b0076vvv0076v00760076v	I
    //   303: ldc 2
    //   305: ldc_w 579
    //   308: sipush 187
    //   311: iconst_0
    //   312: invokestatic 66	xxxxxx/uxxxxx:bb00620062bb0062b0062b0062	(Ljava/lang/String;CC)Ljava/lang/String;
    //   315: iconst_0
    //   316: anewarray 68	java/lang/Class
    //   319: invokevirtual 82	java/lang/Class:getMethod	(Ljava/lang/String;[Ljava/lang/Class;)Ljava/lang/reflect/Method;
    //   322: astore 35
    //   324: iconst_0
    //   325: anewarray 84	java/lang/Object
    //   328: astore 36
    //   330: aload 35
    //   332: aconst_null
    //   333: aload 36
    //   335: invokevirtual 96	java/lang/reflect/Method:invoke	(Ljava/lang/Object;[Ljava/lang/Object;)Ljava/lang/Object;
    //   338: astore 38
    //   340: aload 38
    //   342: checkcast 114	java/lang/Integer
    //   345: invokevirtual 118	java/lang/Integer:intValue	()I
    //   348: putstatic 120	uuuuuu/qmqqmm:bv0076vv0076v00760076v	I
    //   351: aload_1
    //   352: aload_2
    //   353: invokevirtual 582	com/db/pwcc/dbmobile/model/banking/Account:getOnlineBalanceInCurrencyLocalized	(Ljava/util/Locale;)Ljava/lang/String;
    //   356: astore 5
    //   358: aload_1
    //   359: invokevirtual 585	com/db/pwcc/dbmobile/model/banking/Account:isForeignCurrencyAccount	()Z
    //   362: ifeq +59 -> 421
    //   365: aload_1
    //   366: aload_2
    //   367: invokevirtual 588	com/db/pwcc/dbmobile/model/banking/Account:getBookedBalanceInAccountCurrencyLocalized	(Ljava/util/Locale;)Ljava/lang/String;
    //   370: astore 19
    //   372: getstatic 108	uuuuuu/qmqqmm:b0076vvv0076v00760076v	I
    //   375: istore 20
    //   377: iload 20
    //   379: iload 20
    //   381: getstatic 110	uuuuuu/qmqqmm:b00760076vv0076v00760076v	I
    //   384: iadd
    //   385: imul
    //   386: getstatic 122	uuuuuu/qmqqmm:bvv0076v0076v00760076v	I
    //   389: irem
    //   390: tableswitch	default:+18->408, 0:+315->705
    //   408: bipush 83
    //   410: putstatic 108	uuuuuu/qmqqmm:b0076vvv0076v00760076v	I
    //   413: bipush 18
    //   415: putstatic 120	uuuuuu/qmqqmm:bv0076vv0076v00760076v	I
    //   418: aload 19
    //   420: astore_3
    //   421: aload_0
    //   422: invokevirtual 205	uuuuuu/qmqqmm:bkk006Bk006Bk006Bk006Bk	()Z
    //   425: ifne +4 -> 429
    //   428: return
    //   429: aload_1
    //   430: invokevirtual 592	com/db/pwcc/dbmobile/model/banking/Account:getProductType	()Lcom/db/pwcc/dbmobile/model/banking/Account$ProductType;
    //   433: getstatic 598	com/db/pwcc/dbmobile/model/banking/Account$ProductType:SECURITIES_ACCOUNT	Lcom/db/pwcc/dbmobile/model/banking/Account$ProductType;
    //   436: if_acmpne +180 -> 616
    //   439: getstatic 108	uuuuuu/qmqqmm:b0076vvv0076v00760076v	I
    //   442: getstatic 110	uuuuuu/qmqqmm:b00760076vv0076v00760076v	I
    //   445: iadd
    //   446: getstatic 108	uuuuuu/qmqqmm:b0076vvv0076v00760076v	I
    //   449: imul
    //   450: getstatic 122	uuuuuu/qmqqmm:bvv0076v0076v00760076v	I
    //   453: irem
    //   454: istore 6
    //   456: ldc 2
    //   458: ldc_w 600
    //   461: bipush 113
    //   463: iconst_5
    //   464: invokestatic 66	xxxxxx/uxxxxx:bb00620062bb0062b0062b0062	(Ljava/lang/String;CC)Ljava/lang/String;
    //   467: iconst_0
    //   468: anewarray 68	java/lang/Class
    //   471: invokevirtual 82	java/lang/Class:getMethod	(Ljava/lang/String;[Ljava/lang/Class;)Ljava/lang/reflect/Method;
    //   474: astore 7
    //   476: iconst_0
    //   477: anewarray 84	java/lang/Object
    //   480: astore 8
    //   482: aload 7
    //   484: aconst_null
    //   485: aload 8
    //   487: invokevirtual 96	java/lang/reflect/Method:invoke	(Ljava/lang/Object;[Ljava/lang/Object;)Ljava/lang/Object;
    //   490: astore 10
    //   492: iload 6
    //   494: aload 10
    //   496: checkcast 114	java/lang/Integer
    //   499: invokevirtual 118	java/lang/Integer:intValue	()I
    //   502: if_icmpeq +99 -> 601
    //   505: ldc 2
    //   507: ldc_w 602
    //   510: sipush 216
    //   513: iconst_2
    //   514: invokestatic 66	xxxxxx/uxxxxx:bb00620062bb0062b0062b0062	(Ljava/lang/String;CC)Ljava/lang/String;
    //   517: iconst_0
    //   518: anewarray 68	java/lang/Class
    //   521: invokevirtual 82	java/lang/Class:getMethod	(Ljava/lang/String;[Ljava/lang/Class;)Ljava/lang/reflect/Method;
    //   524: astore 11
    //   526: iconst_0
    //   527: anewarray 84	java/lang/Object
    //   530: astore 12
    //   532: aload 11
    //   534: aconst_null
    //   535: aload 12
    //   537: invokevirtual 96	java/lang/reflect/Method:invoke	(Ljava/lang/Object;[Ljava/lang/Object;)Ljava/lang/Object;
    //   540: astore 14
    //   542: aload 14
    //   544: checkcast 114	java/lang/Integer
    //   547: invokevirtual 118	java/lang/Integer:intValue	()I
    //   550: putstatic 108	uuuuuu/qmqqmm:b0076vvv0076v00760076v	I
    //   553: ldc 2
    //   555: ldc_w 604
    //   558: sipush 168
    //   561: iconst_3
    //   562: invokestatic 66	xxxxxx/uxxxxx:bb00620062bb0062b0062b0062	(Ljava/lang/String;CC)Ljava/lang/String;
    //   565: iconst_0
    //   566: anewarray 68	java/lang/Class
    //   569: invokevirtual 82	java/lang/Class:getMethod	(Ljava/lang/String;[Ljava/lang/Class;)Ljava/lang/reflect/Method;
    //   572: astore 15
    //   574: iconst_0
    //   575: anewarray 84	java/lang/Object
    //   578: astore 16
    //   580: aload 15
    //   582: aconst_null
    //   583: aload 16
    //   585: invokevirtual 96	java/lang/reflect/Method:invoke	(Ljava/lang/Object;[Ljava/lang/Object;)Ljava/lang/Object;
    //   588: astore 18
    //   590: aload 18
    //   592: checkcast 114	java/lang/Integer
    //   595: invokevirtual 118	java/lang/Integer:intValue	()I
    //   598: putstatic 120	uuuuuu/qmqqmm:bv0076vv0076v00760076v	I
    //   601: aload_0
    //   602: getfield 152	uuuuuu/qmqqmm:bnnnnn006E006E006En	Luuuuuu/ttssst$tsssst;
    //   605: checkcast 215	uuuuuu/mmmmqm$mqqqmm
    //   608: aload_1
    //   609: aload_3
    //   610: invokeinterface 608 3 0
    //   615: return
    //   616: aload_0
    //   617: getfield 152	uuuuuu/qmqqmm:bnnnnn006E006E006En	Luuuuuu/ttssst$tsssst;
    //   620: checkcast 215	uuuuuu/mmmmqm$mqqqmm
    //   623: aload_1
    //   624: aload_3
    //   625: aload 5
    //   627: invokeinterface 612 4 0
    //   632: return
    //   633: astore 41
    //   635: aload 41
    //   637: invokevirtual 138	java/lang/reflect/InvocationTargetException:getCause	()Ljava/lang/Throwable;
    //   640: athrow
    //   641: astore 45
    //   643: aload 45
    //   645: invokevirtual 138	java/lang/reflect/InvocationTargetException:getCause	()Ljava/lang/Throwable;
    //   648: athrow
    //   649: astore 9
    //   651: aload 9
    //   653: invokevirtual 138	java/lang/reflect/InvocationTargetException:getCause	()Ljava/lang/Throwable;
    //   656: athrow
    //   657: astore 24
    //   659: aload 24
    //   661: invokevirtual 138	java/lang/reflect/InvocationTargetException:getCause	()Ljava/lang/Throwable;
    //   664: athrow
    //   665: astore 29
    //   667: aload 29
    //   669: invokevirtual 138	java/lang/reflect/InvocationTargetException:getCause	()Ljava/lang/Throwable;
    //   672: athrow
    //   673: astore 13
    //   675: aload 13
    //   677: invokevirtual 138	java/lang/reflect/InvocationTargetException:getCause	()Ljava/lang/Throwable;
    //   680: athrow
    //   681: astore 17
    //   683: aload 17
    //   685: invokevirtual 138	java/lang/reflect/InvocationTargetException:getCause	()Ljava/lang/Throwable;
    //   688: athrow
    //   689: astore 33
    //   691: aload 33
    //   693: invokevirtual 138	java/lang/reflect/InvocationTargetException:getCause	()Ljava/lang/Throwable;
    //   696: athrow
    //   697: astore 37
    //   699: aload 37
    //   701: invokevirtual 138	java/lang/reflect/InvocationTargetException:getCause	()Ljava/lang/Throwable;
    //   704: athrow
    //   705: aload 19
    //   707: astore_3
    //   708: goto -287 -> 421
    // Local variable table:
    //   start	length	slot	name	signature
    //   0	711	0	this	qmqqmm
    //   0	711	1	paramAccount	com.db.pwcc.dbmobile.model.banking.Account
    //   3	364	2	localLocale	java.util.Locale
    //   128	580	3	localObject1	Object
    //   133	6	4	bool	boolean
    //   136	490	5	str1	String
    //   454	49	6	i	int
    //   474	9	7	localMethod1	Method
    //   480	6	8	arrayOfObject1	Object[]
    //   649	3	9	localInvocationTargetException1	InvocationTargetException
    //   490	5	10	localObject2	Object
    //   524	9	11	localMethod2	Method
    //   530	6	12	arrayOfObject2	Object[]
    //   673	3	13	localInvocationTargetException2	InvocationTargetException
    //   540	3	14	localObject3	Object
    //   572	9	15	localMethod3	Method
    //   578	6	16	arrayOfObject3	Object[]
    //   681	3	17	localInvocationTargetException3	InvocationTargetException
    //   588	3	18	localObject4	Object
    //   370	336	19	str2	String
    //   375	11	20	j	int
    //   146	51	21	k	int
    //   168	9	22	localMethod4	Method
    //   174	6	23	arrayOfObject4	Object[]
    //   657	3	24	localInvocationTargetException4	InvocationTargetException
    //   184	5	25	localObject5	Object
    //   201	49	26	m	int
    //   221	9	27	localMethod5	Method
    //   227	6	28	arrayOfObject5	Object[]
    //   665	3	29	localInvocationTargetException5	InvocationTargetException
    //   237	5	30	localObject6	Object
    //   274	9	31	localMethod6	Method
    //   280	6	32	arrayOfObject6	Object[]
    //   689	3	33	localInvocationTargetException6	InvocationTargetException
    //   290	3	34	localObject7	Object
    //   322	9	35	localMethod7	Method
    //   328	6	36	arrayOfObject7	Object[]
    //   697	3	37	localInvocationTargetException7	InvocationTargetException
    //   338	3	38	localObject8	Object
    //   46	9	39	localMethod8	Method
    //   52	6	40	arrayOfObject8	Object[]
    //   633	3	41	localInvocationTargetException8	InvocationTargetException
    //   62	3	42	localObject9	Object
    //   94	9	43	localMethod9	Method
    //   100	6	44	arrayOfObject9	Object[]
    //   641	3	45	localInvocationTargetException9	InvocationTargetException
    //   110	3	46	localObject10	Object
    // Exception table:
    //   from	to	target	type
    //   54	64	633	java/lang/reflect/InvocationTargetException
    //   102	112	641	java/lang/reflect/InvocationTargetException
    //   482	492	649	java/lang/reflect/InvocationTargetException
    //   176	186	657	java/lang/reflect/InvocationTargetException
    //   229	239	665	java/lang/reflect/InvocationTargetException
    //   532	542	673	java/lang/reflect/InvocationTargetException
    //   580	590	681	java/lang/reflect/InvocationTargetException
    //   282	292	689	java/lang/reflect/InvocationTargetException
    //   330	340	697	java/lang/reflect/InvocationTargetException
  }
  
  /* Error */
  public void bu0075uu007500750075uu0075()
  {
    // Byte code:
    //   0: getstatic 108	uuuuuu/qmqqmm:b0076vvv0076v00760076v	I
    //   3: getstatic 110	uuuuuu/qmqqmm:b00760076vv0076v00760076v	I
    //   6: iadd
    //   7: getstatic 108	uuuuuu/qmqqmm:b0076vvv0076v00760076v	I
    //   10: imul
    //   11: getstatic 122	uuuuuu/qmqqmm:bvv0076v0076v00760076v	I
    //   14: irem
    //   15: getstatic 120	uuuuuu/qmqqmm:bv0076vv0076v00760076v	I
    //   18: if_icmpeq +44 -> 62
    //   21: bipush 59
    //   23: putstatic 108	uuuuuu/qmqqmm:b0076vvv0076v00760076v	I
    //   26: bipush 98
    //   28: putstatic 120	uuuuuu/qmqqmm:bv0076vv0076v00760076v	I
    //   31: getstatic 108	uuuuuu/qmqqmm:b0076vvv0076v00760076v	I
    //   34: getstatic 110	uuuuuu/qmqqmm:b00760076vv0076v00760076v	I
    //   37: iadd
    //   38: getstatic 108	uuuuuu/qmqqmm:b0076vvv0076v00760076v	I
    //   41: imul
    //   42: getstatic 122	uuuuuu/qmqqmm:bvv0076v0076v00760076v	I
    //   45: irem
    //   46: getstatic 120	uuuuuu/qmqqmm:bv0076vv0076v00760076v	I
    //   49: if_icmpeq +13 -> 62
    //   52: bipush 26
    //   54: putstatic 108	uuuuuu/qmqqmm:b0076vvv0076v00760076v	I
    //   57: bipush 19
    //   59: putstatic 120	uuuuuu/qmqqmm:bv0076vv0076v00760076v	I
    //   62: iconst_m1
    //   63: newarray int
    //   65: pop
    //   66: goto -4 -> 62
    //   69: astore 13
    //   71: bipush 89
    //   73: putstatic 108	uuuuuu/qmqqmm:b0076vvv0076v00760076v	I
    //   76: new 615	uuuuuu/osoooo
    //   79: dup
    //   80: invokespecial 616	uuuuuu/osoooo:<init>	()V
    //   83: aload_0
    //   84: aload_0
    //   85: getfield 620	uuuuuu/qmqqmm:b006E006E006E006E006En006E006En	Luuuuuu/hyhyhh;
    //   88: invokevirtual 625	uuuuuu/hyhyhh:b0070pp007000700070p007000700070	()Ljava/lang/String;
    //   91: invokevirtual 629	uuuuuu/osoooo:bu0075u0075u00750075007500750075	(Luuuuuu/alaall$laaall;Ljava/lang/String;)V
    //   94: return
    //   95: astore_1
    //   96: bipush 77
    //   98: putstatic 108	uuuuuu/qmqqmm:b0076vvv0076v00760076v	I
    //   101: getstatic 108	uuuuuu/qmqqmm:b0076vvv0076v00760076v	I
    //   104: getstatic 110	uuuuuu/qmqqmm:b00760076vv0076v00760076v	I
    //   107: iadd
    //   108: getstatic 108	uuuuuu/qmqqmm:b0076vvv0076v00760076v	I
    //   111: imul
    //   112: getstatic 122	uuuuuu/qmqqmm:bvv0076v0076v00760076v	I
    //   115: irem
    //   116: istore_2
    //   117: ldc 2
    //   119: ldc_w 631
    //   122: bipush 117
    //   124: sipush 176
    //   127: iconst_3
    //   128: invokestatic 132	xxxxxx/uxxxxx:bbbb0062b0062b0062b0062	(Ljava/lang/String;CCC)Ljava/lang/String;
    //   131: iconst_0
    //   132: anewarray 68	java/lang/Class
    //   135: invokevirtual 82	java/lang/Class:getMethod	(Ljava/lang/String;[Ljava/lang/Class;)Ljava/lang/reflect/Method;
    //   138: astore_3
    //   139: iconst_0
    //   140: anewarray 84	java/lang/Object
    //   143: astore 4
    //   145: aload_3
    //   146: aconst_null
    //   147: aload 4
    //   149: invokevirtual 96	java/lang/reflect/Method:invoke	(Ljava/lang/Object;[Ljava/lang/Object;)Ljava/lang/Object;
    //   152: astore 6
    //   154: iload_2
    //   155: aload 6
    //   157: checkcast 114	java/lang/Integer
    //   160: invokevirtual 118	java/lang/Integer:intValue	()I
    //   163: if_icmpeq +13 -> 176
    //   166: bipush 41
    //   168: putstatic 108	uuuuuu/qmqqmm:b0076vvv0076v00760076v	I
    //   171: bipush 84
    //   173: putstatic 120	uuuuuu/qmqqmm:bv0076vv0076v00760076v	I
    //   176: aconst_null
    //   177: invokevirtual 506	java/lang/String:length	()I
    //   180: pop
    //   181: goto -5 -> 176
    //   184: astore 7
    //   186: ldc 2
    //   188: ldc_w 633
    //   191: bipush 50
    //   193: iconst_5
    //   194: invokestatic 66	xxxxxx/uxxxxx:bb00620062bb0062b0062b0062	(Ljava/lang/String;CC)Ljava/lang/String;
    //   197: iconst_0
    //   198: anewarray 68	java/lang/Class
    //   201: invokevirtual 82	java/lang/Class:getMethod	(Ljava/lang/String;[Ljava/lang/Class;)Ljava/lang/reflect/Method;
    //   204: astore 8
    //   206: iconst_0
    //   207: anewarray 84	java/lang/Object
    //   210: astore 9
    //   212: aload 8
    //   214: aconst_null
    //   215: aload 9
    //   217: invokevirtual 96	java/lang/reflect/Method:invoke	(Ljava/lang/Object;[Ljava/lang/Object;)Ljava/lang/Object;
    //   220: astore 11
    //   222: aload 11
    //   224: checkcast 114	java/lang/Integer
    //   227: invokevirtual 118	java/lang/Integer:intValue	()I
    //   230: putstatic 108	uuuuuu/qmqqmm:b0076vvv0076v00760076v	I
    //   233: iconst_m1
    //   234: newarray int
    //   236: pop
    //   237: goto -4 -> 233
    //   240: astore 5
    //   242: aload 5
    //   244: invokevirtual 138	java/lang/reflect/InvocationTargetException:getCause	()Ljava/lang/Throwable;
    //   247: athrow
    //   248: astore 10
    //   250: aload 10
    //   252: invokevirtual 138	java/lang/reflect/InvocationTargetException:getCause	()Ljava/lang/Throwable;
    //   255: athrow
    // Local variable table:
    //   start	length	slot	name	signature
    //   0	256	0	this	qmqqmm
    //   95	1	1	localException1	Exception
    //   116	48	2	i	int
    //   138	8	3	localMethod1	Method
    //   143	5	4	arrayOfObject1	Object[]
    //   240	3	5	localInvocationTargetException1	InvocationTargetException
    //   152	4	6	localObject1	Object
    //   184	1	7	localException2	Exception
    //   204	9	8	localMethod2	Method
    //   210	6	9	arrayOfObject2	Object[]
    //   248	3	10	localInvocationTargetException2	InvocationTargetException
    //   220	3	11	localObject2	Object
    //   69	1	13	localException3	Exception
    // Exception table:
    //   from	to	target	type
    //   233	237	69	java/lang/Exception
    //   62	66	95	java/lang/Exception
    //   176	181	184	java/lang/Exception
    //   145	154	240	java/lang/reflect/InvocationTargetException
    //   212	222	248	java/lang/reflect/InvocationTargetException
  }
  
  /* Error */
  public void bu0075uuuuu0075u0075()
  {
    // Byte code:
    //   0: aload_0
    //   1: getfield 196	uuuuuu/qmqqmm:b0076v00760076vv00760076v	Luuuuuu/vxvvvx;
    //   4: astore_1
    //   5: getstatic 108	uuuuuu/qmqqmm:b0076vvv0076v00760076v	I
    //   8: getstatic 110	uuuuuu/qmqqmm:b00760076vv0076v00760076v	I
    //   11: iadd
    //   12: getstatic 108	uuuuuu/qmqqmm:b0076vvv0076v00760076v	I
    //   15: imul
    //   16: getstatic 122	uuuuuu/qmqqmm:bvv0076v0076v00760076v	I
    //   19: irem
    //   20: istore_2
    //   21: getstatic 120	uuuuuu/qmqqmm:bv0076vv0076v00760076v	I
    //   24: istore_3
    //   25: ldc 2
    //   27: ldc_w 636
    //   30: bipush 20
    //   32: iconst_3
    //   33: invokestatic 66	xxxxxx/uxxxxx:bb00620062bb0062b0062b0062	(Ljava/lang/String;CC)Ljava/lang/String;
    //   36: iconst_0
    //   37: anewarray 68	java/lang/Class
    //   40: invokevirtual 82	java/lang/Class:getMethod	(Ljava/lang/String;[Ljava/lang/Class;)Ljava/lang/reflect/Method;
    //   43: astore 4
    //   45: iconst_0
    //   46: anewarray 84	java/lang/Object
    //   49: astore 5
    //   51: aload 4
    //   53: aconst_null
    //   54: aload 5
    //   56: invokevirtual 96	java/lang/reflect/Method:invoke	(Ljava/lang/Object;[Ljava/lang/Object;)Ljava/lang/Object;
    //   59: astore 7
    //   61: aload 7
    //   63: checkcast 114	java/lang/Integer
    //   66: invokevirtual 118	java/lang/Integer:intValue	()I
    //   69: istore 8
    //   71: iload 8
    //   73: iload 8
    //   75: getstatic 110	uuuuuu/qmqqmm:b00760076vv0076v00760076v	I
    //   78: iadd
    //   79: imul
    //   80: getstatic 122	uuuuuu/qmqqmm:bvv0076v0076v00760076v	I
    //   83: irem
    //   84: tableswitch	default:+20->104, 0:+164->248
    //   104: getstatic 108	uuuuuu/qmqqmm:b0076vvv0076v00760076v	I
    //   107: istore 14
    //   109: iload 14
    //   111: iload 14
    //   113: getstatic 110	uuuuuu/qmqqmm:b00760076vv0076v00760076v	I
    //   116: iadd
    //   117: imul
    //   118: getstatic 122	uuuuuu/qmqqmm:bvv0076v0076v00760076v	I
    //   121: irem
    //   122: tableswitch	default:+18->140, 0:+74->196
    //   140: bipush 46
    //   142: putstatic 108	uuuuuu/qmqqmm:b0076vvv0076v00760076v	I
    //   145: ldc 2
    //   147: ldc_w 638
    //   150: sipush 134
    //   153: sipush 200
    //   156: iconst_3
    //   157: invokestatic 132	xxxxxx/uxxxxx:bbbb0062b0062b0062b0062	(Ljava/lang/String;CCC)Ljava/lang/String;
    //   160: iconst_0
    //   161: anewarray 68	java/lang/Class
    //   164: invokevirtual 82	java/lang/Class:getMethod	(Ljava/lang/String;[Ljava/lang/Class;)Ljava/lang/reflect/Method;
    //   167: astore 19
    //   169: iconst_0
    //   170: anewarray 84	java/lang/Object
    //   173: astore 20
    //   175: aload 19
    //   177: aconst_null
    //   178: aload 20
    //   180: invokevirtual 96	java/lang/reflect/Method:invoke	(Ljava/lang/Object;[Ljava/lang/Object;)Ljava/lang/Object;
    //   183: astore 22
    //   185: aload 22
    //   187: checkcast 114	java/lang/Integer
    //   190: invokevirtual 118	java/lang/Integer:intValue	()I
    //   193: putstatic 120	uuuuuu/qmqqmm:bv0076vv0076v00760076v	I
    //   196: bipush 10
    //   198: putstatic 108	uuuuuu/qmqqmm:b0076vvv0076v00760076v	I
    //   201: ldc 2
    //   203: ldc_w 577
    //   206: bipush 90
    //   208: iconst_2
    //   209: invokestatic 66	xxxxxx/uxxxxx:bb00620062bb0062b0062b0062	(Ljava/lang/String;CC)Ljava/lang/String;
    //   212: iconst_0
    //   213: anewarray 68	java/lang/Class
    //   216: invokevirtual 82	java/lang/Class:getMethod	(Ljava/lang/String;[Ljava/lang/Class;)Ljava/lang/reflect/Method;
    //   219: astore 15
    //   221: iconst_0
    //   222: anewarray 84	java/lang/Object
    //   225: astore 16
    //   227: aload 15
    //   229: aconst_null
    //   230: aload 16
    //   232: invokevirtual 96	java/lang/reflect/Method:invoke	(Ljava/lang/Object;[Ljava/lang/Object;)Ljava/lang/Object;
    //   235: astore 18
    //   237: aload 18
    //   239: checkcast 114	java/lang/Integer
    //   242: invokevirtual 118	java/lang/Integer:intValue	()I
    //   245: putstatic 120	uuuuuu/qmqqmm:bv0076vv0076v00760076v	I
    //   248: iload_2
    //   249: iload_3
    //   250: if_icmpeq +12 -> 262
    //   253: bipush 16
    //   255: putstatic 108	uuuuuu/qmqqmm:b0076vvv0076v00760076v	I
    //   258: iconst_5
    //   259: putstatic 120	uuuuuu/qmqqmm:bv0076vv0076v00760076v	I
    //   262: aload_0
    //   263: getfield 42	uuuuuu/qmqqmm:b00760076v0076vv00760076v	Ljava/lang/String;
    //   266: astore 9
    //   268: getstatic 108	uuuuuu/qmqqmm:b0076vvv0076v00760076v	I
    //   271: getstatic 110	uuuuuu/qmqqmm:b00760076vv0076v00760076v	I
    //   274: iadd
    //   275: getstatic 108	uuuuuu/qmqqmm:b0076vvv0076v00760076v	I
    //   278: imul
    //   279: getstatic 122	uuuuuu/qmqqmm:bvv0076v0076v00760076v	I
    //   282: irem
    //   283: getstatic 120	uuuuuu/qmqqmm:bv0076vv0076v00760076v	I
    //   286: if_icmpeq +58 -> 344
    //   289: bipush 8
    //   291: putstatic 108	uuuuuu/qmqqmm:b0076vvv0076v00760076v	I
    //   294: ldc 2
    //   296: ldc_w 640
    //   299: bipush 55
    //   301: sipush 233
    //   304: iconst_0
    //   305: invokestatic 132	xxxxxx/uxxxxx:bbbb0062b0062b0062b0062	(Ljava/lang/String;CCC)Ljava/lang/String;
    //   308: iconst_0
    //   309: anewarray 68	java/lang/Class
    //   312: invokevirtual 82	java/lang/Class:getMethod	(Ljava/lang/String;[Ljava/lang/Class;)Ljava/lang/reflect/Method;
    //   315: astore 10
    //   317: iconst_0
    //   318: anewarray 84	java/lang/Object
    //   321: astore 11
    //   323: aload 10
    //   325: aconst_null
    //   326: aload 11
    //   328: invokevirtual 96	java/lang/reflect/Method:invoke	(Ljava/lang/Object;[Ljava/lang/Object;)Ljava/lang/Object;
    //   331: astore 13
    //   333: aload 13
    //   335: checkcast 114	java/lang/Integer
    //   338: invokevirtual 118	java/lang/Integer:intValue	()I
    //   341: putstatic 120	uuuuuu/qmqqmm:bv0076vv0076v00760076v	I
    //   344: aload_1
    //   345: aload 9
    //   347: invokevirtual 643	uuuuuu/vxvvvx:b006Bkkkkk006B006Bkk	(Ljava/lang/String;)V
    //   350: return
    //   351: astore 6
    //   353: aload 6
    //   355: invokevirtual 138	java/lang/reflect/InvocationTargetException:getCause	()Ljava/lang/Throwable;
    //   358: athrow
    //   359: astore 17
    //   361: aload 17
    //   363: invokevirtual 138	java/lang/reflect/InvocationTargetException:getCause	()Ljava/lang/Throwable;
    //   366: athrow
    //   367: astore 12
    //   369: aload 12
    //   371: invokevirtual 138	java/lang/reflect/InvocationTargetException:getCause	()Ljava/lang/Throwable;
    //   374: athrow
    //   375: astore 21
    //   377: aload 21
    //   379: invokevirtual 138	java/lang/reflect/InvocationTargetException:getCause	()Ljava/lang/Throwable;
    //   382: athrow
    // Local variable table:
    //   start	length	slot	name	signature
    //   0	383	0	this	qmqqmm
    //   4	341	1	localVxvvvx	vxvvvx
    //   20	231	2	i	int
    //   24	227	3	j	int
    //   43	9	4	localMethod1	Method
    //   49	6	5	arrayOfObject1	Object[]
    //   351	3	6	localInvocationTargetException1	InvocationTargetException
    //   59	3	7	localObject1	Object
    //   69	11	8	k	int
    //   266	80	9	str	String
    //   315	9	10	localMethod2	Method
    //   321	6	11	arrayOfObject2	Object[]
    //   367	3	12	localInvocationTargetException2	InvocationTargetException
    //   331	3	13	localObject2	Object
    //   107	11	14	m	int
    //   219	9	15	localMethod3	Method
    //   225	6	16	arrayOfObject3	Object[]
    //   359	3	17	localInvocationTargetException3	InvocationTargetException
    //   235	3	18	localObject3	Object
    //   167	9	19	localMethod4	Method
    //   173	6	20	arrayOfObject4	Object[]
    //   375	3	21	localInvocationTargetException4	InvocationTargetException
    //   183	3	22	localObject4	Object
    // Exception table:
    //   from	to	target	type
    //   51	61	351	java/lang/reflect/InvocationTargetException
    //   227	237	359	java/lang/reflect/InvocationTargetException
    //   323	333	367	java/lang/reflect/InvocationTargetException
    //   175	185	375	java/lang/reflect/InvocationTargetException
  }
  
  /* Error */
  public void buu00750075u00750075uu0075(String paramString)
  {
    // Byte code:
    //   0: getstatic 108	uuuuuu/qmqqmm:b0076vvv0076v00760076v	I
    //   3: getstatic 110	uuuuuu/qmqqmm:b00760076vv0076v00760076v	I
    //   6: iadd
    //   7: getstatic 108	uuuuuu/qmqqmm:b0076vvv0076v00760076v	I
    //   10: imul
    //   11: istore_2
    //   12: getstatic 108	uuuuuu/qmqqmm:b0076vvv0076v00760076v	I
    //   15: istore_3
    //   16: iload_3
    //   17: iload_3
    //   18: getstatic 110	uuuuuu/qmqqmm:b00760076vv0076v00760076v	I
    //   21: iadd
    //   22: imul
    //   23: istore 4
    //   25: ldc 2
    //   27: ldc_w 646
    //   30: bipush 37
    //   32: iconst_0
    //   33: invokestatic 66	xxxxxx/uxxxxx:bb00620062bb0062b0062b0062	(Ljava/lang/String;CC)Ljava/lang/String;
    //   36: iconst_0
    //   37: anewarray 68	java/lang/Class
    //   40: invokevirtual 82	java/lang/Class:getMethod	(Ljava/lang/String;[Ljava/lang/Class;)Ljava/lang/reflect/Method;
    //   43: astore 5
    //   45: iconst_0
    //   46: anewarray 84	java/lang/Object
    //   49: astore 6
    //   51: aload 5
    //   53: aconst_null
    //   54: aload 6
    //   56: invokevirtual 96	java/lang/reflect/Method:invoke	(Ljava/lang/Object;[Ljava/lang/Object;)Ljava/lang/Object;
    //   59: astore 8
    //   61: iload 4
    //   63: aload 8
    //   65: checkcast 114	java/lang/Integer
    //   68: invokevirtual 118	java/lang/Integer:intValue	()I
    //   71: irem
    //   72: tableswitch	default:+20->92, 0:+73->145
    //   92: ldc 2
    //   94: ldc_w 648
    //   97: sipush 203
    //   100: iconst_4
    //   101: invokestatic 66	xxxxxx/uxxxxx:bb00620062bb0062b0062b0062	(Ljava/lang/String;CC)Ljava/lang/String;
    //   104: iconst_0
    //   105: anewarray 68	java/lang/Class
    //   108: invokevirtual 82	java/lang/Class:getMethod	(Ljava/lang/String;[Ljava/lang/Class;)Ljava/lang/reflect/Method;
    //   111: astore 33
    //   113: iconst_0
    //   114: anewarray 84	java/lang/Object
    //   117: astore 34
    //   119: aload 33
    //   121: aconst_null
    //   122: aload 34
    //   124: invokevirtual 96	java/lang/reflect/Method:invoke	(Ljava/lang/Object;[Ljava/lang/Object;)Ljava/lang/Object;
    //   127: astore 36
    //   129: aload 36
    //   131: checkcast 114	java/lang/Integer
    //   134: invokevirtual 118	java/lang/Integer:intValue	()I
    //   137: putstatic 108	uuuuuu/qmqqmm:b0076vvv0076v00760076v	I
    //   140: bipush 51
    //   142: putstatic 120	uuuuuu/qmqqmm:bv0076vv0076v00760076v	I
    //   145: iload_2
    //   146: getstatic 122	uuuuuu/qmqqmm:bvv0076v0076v00760076v	I
    //   149: irem
    //   150: istore 9
    //   152: ldc 2
    //   154: ldc_w 650
    //   157: sipush 218
    //   160: iconst_1
    //   161: invokestatic 66	xxxxxx/uxxxxx:bb00620062bb0062b0062b0062	(Ljava/lang/String;CC)Ljava/lang/String;
    //   164: iconst_0
    //   165: anewarray 68	java/lang/Class
    //   168: invokevirtual 82	java/lang/Class:getMethod	(Ljava/lang/String;[Ljava/lang/Class;)Ljava/lang/reflect/Method;
    //   171: astore 10
    //   173: iconst_0
    //   174: anewarray 84	java/lang/Object
    //   177: astore 11
    //   179: aload 10
    //   181: aconst_null
    //   182: aload 11
    //   184: invokevirtual 96	java/lang/reflect/Method:invoke	(Ljava/lang/Object;[Ljava/lang/Object;)Ljava/lang/Object;
    //   187: astore 13
    //   189: iload 9
    //   191: aload 13
    //   193: checkcast 114	java/lang/Integer
    //   196: invokevirtual 118	java/lang/Integer:intValue	()I
    //   199: if_icmpeq +97 -> 296
    //   202: ldc 2
    //   204: ldc_w 652
    //   207: bipush 27
    //   209: iconst_0
    //   210: invokestatic 66	xxxxxx/uxxxxx:bb00620062bb0062b0062b0062	(Ljava/lang/String;CC)Ljava/lang/String;
    //   213: iconst_0
    //   214: anewarray 68	java/lang/Class
    //   217: invokevirtual 82	java/lang/Class:getMethod	(Ljava/lang/String;[Ljava/lang/Class;)Ljava/lang/reflect/Method;
    //   220: astore 25
    //   222: iconst_0
    //   223: anewarray 84	java/lang/Object
    //   226: astore 26
    //   228: aload 25
    //   230: aconst_null
    //   231: aload 26
    //   233: invokevirtual 96	java/lang/reflect/Method:invoke	(Ljava/lang/Object;[Ljava/lang/Object;)Ljava/lang/Object;
    //   236: astore 28
    //   238: aload 28
    //   240: checkcast 114	java/lang/Integer
    //   243: invokevirtual 118	java/lang/Integer:intValue	()I
    //   246: putstatic 108	uuuuuu/qmqqmm:b0076vvv0076v00760076v	I
    //   249: ldc 2
    //   251: ldc_w 654
    //   254: bipush 123
    //   256: iconst_0
    //   257: invokestatic 66	xxxxxx/uxxxxx:bb00620062bb0062b0062b0062	(Ljava/lang/String;CC)Ljava/lang/String;
    //   260: iconst_0
    //   261: anewarray 68	java/lang/Class
    //   264: invokevirtual 82	java/lang/Class:getMethod	(Ljava/lang/String;[Ljava/lang/Class;)Ljava/lang/reflect/Method;
    //   267: astore 29
    //   269: iconst_0
    //   270: anewarray 84	java/lang/Object
    //   273: astore 30
    //   275: aload 29
    //   277: aconst_null
    //   278: aload 30
    //   280: invokevirtual 96	java/lang/reflect/Method:invoke	(Ljava/lang/Object;[Ljava/lang/Object;)Ljava/lang/Object;
    //   283: astore 32
    //   285: aload 32
    //   287: checkcast 114	java/lang/Integer
    //   290: invokevirtual 118	java/lang/Integer:intValue	()I
    //   293: putstatic 120	uuuuuu/qmqqmm:bv0076vv0076v00760076v	I
    //   296: new 656	uuuuuu/alalla
    //   299: dup
    //   300: invokespecial 657	uuuuuu/alalla:<init>	()V
    //   303: astore 14
    //   305: aload_0
    //   306: getfield 620	uuuuuu/qmqqmm:b006E006E006E006E006En006E006En	Luuuuuu/hyhyhh;
    //   309: invokevirtual 625	uuuuuu/hyhyhh:b0070pp007000700070p007000700070	()Ljava/lang/String;
    //   312: astore 15
    //   314: getstatic 108	uuuuuu/qmqqmm:b0076vvv0076v00760076v	I
    //   317: getstatic 110	uuuuuu/qmqqmm:b00760076vv0076v00760076v	I
    //   320: iadd
    //   321: getstatic 108	uuuuuu/qmqqmm:b0076vvv0076v00760076v	I
    //   324: imul
    //   325: getstatic 122	uuuuuu/qmqqmm:bvv0076v0076v00760076v	I
    //   328: irem
    //   329: getstatic 120	uuuuuu/qmqqmm:bv0076vv0076v00760076v	I
    //   332: if_icmpeq +13 -> 345
    //   335: bipush 54
    //   337: putstatic 108	uuuuuu/qmqqmm:b0076vvv0076v00760076v	I
    //   340: bipush 37
    //   342: putstatic 120	uuuuuu/qmqqmm:bv0076vv0076v00760076v	I
    //   345: getstatic 108	uuuuuu/qmqqmm:b0076vvv0076v00760076v	I
    //   348: istore 16
    //   350: iload 16
    //   352: iload 16
    //   354: getstatic 110	uuuuuu/qmqqmm:b00760076vv0076v00760076v	I
    //   357: iadd
    //   358: imul
    //   359: getstatic 122	uuuuuu/qmqqmm:bvv0076v0076v00760076v	I
    //   362: irem
    //   363: tableswitch	default:+17->380, 0:+111->474
    //   380: ldc 2
    //   382: ldc_w 659
    //   385: bipush 21
    //   387: iconst_3
    //   388: invokestatic 66	xxxxxx/uxxxxx:bb00620062bb0062b0062b0062	(Ljava/lang/String;CC)Ljava/lang/String;
    //   391: iconst_0
    //   392: anewarray 68	java/lang/Class
    //   395: invokevirtual 82	java/lang/Class:getMethod	(Ljava/lang/String;[Ljava/lang/Class;)Ljava/lang/reflect/Method;
    //   398: astore 17
    //   400: iconst_0
    //   401: anewarray 84	java/lang/Object
    //   404: astore 18
    //   406: aload 17
    //   408: aconst_null
    //   409: aload 18
    //   411: invokevirtual 96	java/lang/reflect/Method:invoke	(Ljava/lang/Object;[Ljava/lang/Object;)Ljava/lang/Object;
    //   414: astore 20
    //   416: aload 20
    //   418: checkcast 114	java/lang/Integer
    //   421: invokevirtual 118	java/lang/Integer:intValue	()I
    //   424: putstatic 108	uuuuuu/qmqqmm:b0076vvv0076v00760076v	I
    //   427: ldc 2
    //   429: ldc_w 661
    //   432: bipush 69
    //   434: iconst_4
    //   435: invokestatic 66	xxxxxx/uxxxxx:bb00620062bb0062b0062b0062	(Ljava/lang/String;CC)Ljava/lang/String;
    //   438: iconst_0
    //   439: anewarray 68	java/lang/Class
    //   442: invokevirtual 82	java/lang/Class:getMethod	(Ljava/lang/String;[Ljava/lang/Class;)Ljava/lang/reflect/Method;
    //   445: astore 21
    //   447: iconst_0
    //   448: anewarray 84	java/lang/Object
    //   451: astore 22
    //   453: aload 21
    //   455: aconst_null
    //   456: aload 22
    //   458: invokevirtual 96	java/lang/reflect/Method:invoke	(Ljava/lang/Object;[Ljava/lang/Object;)Ljava/lang/Object;
    //   461: astore 24
    //   463: aload 24
    //   465: checkcast 114	java/lang/Integer
    //   468: invokevirtual 118	java/lang/Integer:intValue	()I
    //   471: putstatic 120	uuuuuu/qmqqmm:bv0076vv0076v00760076v	I
    //   474: aload 14
    //   476: aload_0
    //   477: aload 15
    //   479: aload_1
    //   480: invokevirtual 665	uuuuuu/alalla:b0075u007500750075u0075007500750075	(Luuuuuu/vvxxvv$xxvxvv;Ljava/lang/String;Ljava/lang/String;)V
    //   483: return
    //   484: astore 31
    //   486: aload 31
    //   488: invokevirtual 138	java/lang/reflect/InvocationTargetException:getCause	()Ljava/lang/Throwable;
    //   491: athrow
    //   492: astore 27
    //   494: aload 27
    //   496: invokevirtual 138	java/lang/reflect/InvocationTargetException:getCause	()Ljava/lang/Throwable;
    //   499: athrow
    //   500: astore 12
    //   502: aload 12
    //   504: invokevirtual 138	java/lang/reflect/InvocationTargetException:getCause	()Ljava/lang/Throwable;
    //   507: athrow
    //   508: astore 7
    //   510: aload 7
    //   512: invokevirtual 138	java/lang/reflect/InvocationTargetException:getCause	()Ljava/lang/Throwable;
    //   515: athrow
    //   516: astore 35
    //   518: aload 35
    //   520: invokevirtual 138	java/lang/reflect/InvocationTargetException:getCause	()Ljava/lang/Throwable;
    //   523: athrow
    //   524: astore 19
    //   526: aload 19
    //   528: invokevirtual 138	java/lang/reflect/InvocationTargetException:getCause	()Ljava/lang/Throwable;
    //   531: athrow
    //   532: astore 23
    //   534: aload 23
    //   536: invokevirtual 138	java/lang/reflect/InvocationTargetException:getCause	()Ljava/lang/Throwable;
    //   539: athrow
    // Local variable table:
    //   start	length	slot	name	signature
    //   0	540	0	this	qmqqmm
    //   0	540	1	paramString	String
    //   11	139	2	i	int
    //   15	8	3	j	int
    //   23	49	4	k	int
    //   43	9	5	localMethod1	Method
    //   49	6	6	arrayOfObject1	Object[]
    //   508	3	7	localInvocationTargetException1	InvocationTargetException
    //   59	5	8	localObject1	Object
    //   150	50	9	m	int
    //   171	9	10	localMethod2	Method
    //   177	6	11	arrayOfObject2	Object[]
    //   500	3	12	localInvocationTargetException2	InvocationTargetException
    //   187	5	13	localObject2	Object
    //   303	172	14	localAlalla	alalla
    //   312	166	15	str	String
    //   348	11	16	n	int
    //   398	9	17	localMethod3	Method
    //   404	6	18	arrayOfObject3	Object[]
    //   524	3	19	localInvocationTargetException3	InvocationTargetException
    //   414	3	20	localObject3	Object
    //   445	9	21	localMethod4	Method
    //   451	6	22	arrayOfObject4	Object[]
    //   532	3	23	localInvocationTargetException4	InvocationTargetException
    //   461	3	24	localObject4	Object
    //   220	9	25	localMethod5	Method
    //   226	6	26	arrayOfObject5	Object[]
    //   492	3	27	localInvocationTargetException5	InvocationTargetException
    //   236	3	28	localObject5	Object
    //   267	9	29	localMethod6	Method
    //   273	6	30	arrayOfObject6	Object[]
    //   484	3	31	localInvocationTargetException6	InvocationTargetException
    //   283	3	32	localObject6	Object
    //   111	9	33	localMethod7	Method
    //   117	6	34	arrayOfObject7	Object[]
    //   516	3	35	localInvocationTargetException7	InvocationTargetException
    //   127	3	36	localObject7	Object
    // Exception table:
    //   from	to	target	type
    //   275	285	484	java/lang/reflect/InvocationTargetException
    //   228	238	492	java/lang/reflect/InvocationTargetException
    //   179	189	500	java/lang/reflect/InvocationTargetException
    //   51	61	508	java/lang/reflect/InvocationTargetException
    //   119	129	516	java/lang/reflect/InvocationTargetException
    //   406	416	524	java/lang/reflect/InvocationTargetException
    //   453	463	532	java/lang/reflect/InvocationTargetException
  }
  
  /* Error */
  public void buu0075u007500750075uu0075(@android.support.annotation.NonNull android.content.Context paramContext)
  {
    // Byte code:
    //   0: aload_0
    //   1: getfield 669	uuuuuu/qmqqmm:bv007600760076vv00760076v	Lcom/db/pwcc/dbmobile/foundation/data/manager/broadcasting/ModelUpdatedBroadcastReceiver;
    //   4: astore_2
    //   5: ldc 2
    //   7: ldc_w 671
    //   10: sipush 204
    //   13: bipush 29
    //   15: iconst_0
    //   16: invokestatic 132	xxxxxx/uxxxxx:bbbb0062b0062b0062b0062	(Ljava/lang/String;CCC)Ljava/lang/String;
    //   19: iconst_2
    //   20: anewarray 68	java/lang/Class
    //   23: dup
    //   24: iconst_0
    //   25: ldc_w 673
    //   28: aastore
    //   29: dup
    //   30: iconst_1
    //   31: ldc_w 675
    //   34: aastore
    //   35: invokevirtual 287	java/lang/Class:getDeclaredMethod	(Ljava/lang/String;[Ljava/lang/Class;)Ljava/lang/reflect/Method;
    //   38: astore_3
    //   39: iconst_2
    //   40: anewarray 84	java/lang/Object
    //   43: dup
    //   44: iconst_0
    //   45: aload_1
    //   46: aastore
    //   47: dup
    //   48: iconst_1
    //   49: aload_2
    //   50: aastore
    //   51: astore 4
    //   53: aload_3
    //   54: aload_0
    //   55: aload 4
    //   57: invokevirtual 96	java/lang/reflect/Method:invoke	(Ljava/lang/Object;[Ljava/lang/Object;)Ljava/lang/Object;
    //   60: pop
    //   61: getstatic 108	uuuuuu/qmqqmm:b0076vvv0076v00760076v	I
    //   64: getstatic 110	uuuuuu/qmqqmm:b00760076vv0076v00760076v	I
    //   67: iadd
    //   68: getstatic 108	uuuuuu/qmqqmm:b0076vvv0076v00760076v	I
    //   71: imul
    //   72: getstatic 122	uuuuuu/qmqqmm:bvv0076v0076v00760076v	I
    //   75: irem
    //   76: istore 7
    //   78: getstatic 120	uuuuuu/qmqqmm:bv0076vv0076v00760076v	I
    //   81: istore 8
    //   83: getstatic 108	uuuuuu/qmqqmm:b0076vvv0076v00760076v	I
    //   86: getstatic 110	uuuuuu/qmqqmm:b00760076vv0076v00760076v	I
    //   89: iadd
    //   90: getstatic 108	uuuuuu/qmqqmm:b0076vvv0076v00760076v	I
    //   93: imul
    //   94: getstatic 122	uuuuuu/qmqqmm:bvv0076v0076v00760076v	I
    //   97: irem
    //   98: getstatic 120	uuuuuu/qmqqmm:bv0076vv0076v00760076v	I
    //   101: if_icmpeq +217 -> 318
    //   104: ldc 2
    //   106: ldc_w 677
    //   109: sipush 204
    //   112: iconst_2
    //   113: invokestatic 66	xxxxxx/uxxxxx:bb00620062bb0062b0062b0062	(Ljava/lang/String;CC)Ljava/lang/String;
    //   116: iconst_0
    //   117: anewarray 68	java/lang/Class
    //   120: invokevirtual 82	java/lang/Class:getMethod	(Ljava/lang/String;[Ljava/lang/Class;)Ljava/lang/reflect/Method;
    //   123: astore 19
    //   125: iconst_0
    //   126: anewarray 84	java/lang/Object
    //   129: astore 20
    //   131: aload 19
    //   133: aconst_null
    //   134: aload 20
    //   136: invokevirtual 96	java/lang/reflect/Method:invoke	(Ljava/lang/Object;[Ljava/lang/Object;)Ljava/lang/Object;
    //   139: astore 22
    //   141: aload 22
    //   143: checkcast 114	java/lang/Integer
    //   146: invokevirtual 118	java/lang/Integer:intValue	()I
    //   149: getstatic 110	uuuuuu/qmqqmm:b00760076vv0076v00760076v	I
    //   152: iadd
    //   153: istore 23
    //   155: ldc 2
    //   157: ldc_w 679
    //   160: bipush 58
    //   162: iconst_4
    //   163: invokestatic 66	xxxxxx/uxxxxx:bb00620062bb0062b0062b0062	(Ljava/lang/String;CC)Ljava/lang/String;
    //   166: iconst_0
    //   167: anewarray 68	java/lang/Class
    //   170: invokevirtual 82	java/lang/Class:getMethod	(Ljava/lang/String;[Ljava/lang/Class;)Ljava/lang/reflect/Method;
    //   173: astore 24
    //   175: iconst_0
    //   176: anewarray 84	java/lang/Object
    //   179: astore 25
    //   181: aload 24
    //   183: aconst_null
    //   184: aload 25
    //   186: invokevirtual 96	java/lang/reflect/Method:invoke	(Ljava/lang/Object;[Ljava/lang/Object;)Ljava/lang/Object;
    //   189: astore 27
    //   191: iload 23
    //   193: aload 27
    //   195: checkcast 114	java/lang/Integer
    //   198: invokevirtual 118	java/lang/Integer:intValue	()I
    //   201: imul
    //   202: getstatic 122	uuuuuu/qmqqmm:bvv0076v0076v00760076v	I
    //   205: irem
    //   206: getstatic 120	uuuuuu/qmqqmm:bv0076vv0076v00760076v	I
    //   209: if_icmpeq +56 -> 265
    //   212: ldc 2
    //   214: ldc_w 633
    //   217: sipush 202
    //   220: iconst_4
    //   221: invokestatic 66	xxxxxx/uxxxxx:bb00620062bb0062b0062b0062	(Ljava/lang/String;CC)Ljava/lang/String;
    //   224: iconst_0
    //   225: anewarray 68	java/lang/Class
    //   228: invokevirtual 82	java/lang/Class:getMethod	(Ljava/lang/String;[Ljava/lang/Class;)Ljava/lang/reflect/Method;
    //   231: astore 32
    //   233: iconst_0
    //   234: anewarray 84	java/lang/Object
    //   237: astore 33
    //   239: aload 32
    //   241: aconst_null
    //   242: aload 33
    //   244: invokevirtual 96	java/lang/reflect/Method:invoke	(Ljava/lang/Object;[Ljava/lang/Object;)Ljava/lang/Object;
    //   247: astore 35
    //   249: aload 35
    //   251: checkcast 114	java/lang/Integer
    //   254: invokevirtual 118	java/lang/Integer:intValue	()I
    //   257: putstatic 108	uuuuuu/qmqqmm:b0076vvv0076v00760076v	I
    //   260: bipush 50
    //   262: putstatic 120	uuuuuu/qmqqmm:bv0076vv0076v00760076v	I
    //   265: bipush 50
    //   267: putstatic 108	uuuuuu/qmqqmm:b0076vvv0076v00760076v	I
    //   270: ldc 2
    //   272: ldc_w 681
    //   275: sipush 173
    //   278: iconst_0
    //   279: invokestatic 66	xxxxxx/uxxxxx:bb00620062bb0062b0062b0062	(Ljava/lang/String;CC)Ljava/lang/String;
    //   282: iconst_0
    //   283: anewarray 68	java/lang/Class
    //   286: invokevirtual 82	java/lang/Class:getMethod	(Ljava/lang/String;[Ljava/lang/Class;)Ljava/lang/reflect/Method;
    //   289: astore 28
    //   291: iconst_0
    //   292: anewarray 84	java/lang/Object
    //   295: astore 29
    //   297: aload 28
    //   299: aconst_null
    //   300: aload 29
    //   302: invokevirtual 96	java/lang/reflect/Method:invoke	(Ljava/lang/Object;[Ljava/lang/Object;)Ljava/lang/Object;
    //   305: astore 31
    //   307: aload 31
    //   309: checkcast 114	java/lang/Integer
    //   312: invokevirtual 118	java/lang/Integer:intValue	()I
    //   315: putstatic 120	uuuuuu/qmqqmm:bv0076vv0076v00760076v	I
    //   318: iload 7
    //   320: iload 8
    //   322: if_icmpeq +105 -> 427
    //   325: bipush 66
    //   327: putstatic 108	uuuuuu/qmqqmm:b0076vvv0076v00760076v	I
    //   330: bipush 89
    //   332: putstatic 120	uuuuuu/qmqqmm:bv0076vv0076v00760076v	I
    //   335: getstatic 108	uuuuuu/qmqqmm:b0076vvv0076v00760076v	I
    //   338: istore 14
    //   340: iload 14
    //   342: iload 14
    //   344: getstatic 110	uuuuuu/qmqqmm:b00760076vv0076v00760076v	I
    //   347: iadd
    //   348: imul
    //   349: getstatic 122	uuuuuu/qmqqmm:bvv0076v0076v00760076v	I
    //   352: irem
    //   353: tableswitch	default:+19->372, 0:+74->427
    //   372: bipush 8
    //   374: putstatic 108	uuuuuu/qmqqmm:b0076vvv0076v00760076v	I
    //   377: ldc 2
    //   379: ldc_w 683
    //   382: bipush 108
    //   384: sipush 198
    //   387: iconst_1
    //   388: invokestatic 132	xxxxxx/uxxxxx:bbbb0062b0062b0062b0062	(Ljava/lang/String;CCC)Ljava/lang/String;
    //   391: iconst_0
    //   392: anewarray 68	java/lang/Class
    //   395: invokevirtual 82	java/lang/Class:getMethod	(Ljava/lang/String;[Ljava/lang/Class;)Ljava/lang/reflect/Method;
    //   398: astore 15
    //   400: iconst_0
    //   401: anewarray 84	java/lang/Object
    //   404: astore 16
    //   406: aload 15
    //   408: aconst_null
    //   409: aload 16
    //   411: invokevirtual 96	java/lang/reflect/Method:invoke	(Ljava/lang/Object;[Ljava/lang/Object;)Ljava/lang/Object;
    //   414: astore 18
    //   416: aload 18
    //   418: checkcast 114	java/lang/Integer
    //   421: invokevirtual 118	java/lang/Integer:intValue	()I
    //   424: putstatic 120	uuuuuu/qmqqmm:bv0076vv0076v00760076v	I
    //   427: aload_0
    //   428: getfield 685	uuuuuu/qmqqmm:bvv00760076vv00760076v	Lcom/db/pwcc/dbmobile/foundation/data/manager/broadcasting/InputActionRequiredBroadcastReceiver;
    //   431: astore 9
    //   433: ldc 2
    //   435: ldc_w 687
    //   438: bipush 125
    //   440: iconst_2
    //   441: invokestatic 66	xxxxxx/uxxxxx:bb00620062bb0062b0062b0062	(Ljava/lang/String;CC)Ljava/lang/String;
    //   444: iconst_2
    //   445: anewarray 68	java/lang/Class
    //   448: dup
    //   449: iconst_0
    //   450: ldc_w 673
    //   453: aastore
    //   454: dup
    //   455: iconst_1
    //   456: ldc_w 675
    //   459: aastore
    //   460: invokevirtual 287	java/lang/Class:getDeclaredMethod	(Ljava/lang/String;[Ljava/lang/Class;)Ljava/lang/reflect/Method;
    //   463: astore 10
    //   465: iconst_2
    //   466: anewarray 84	java/lang/Object
    //   469: dup
    //   470: iconst_0
    //   471: aload_1
    //   472: aastore
    //   473: dup
    //   474: iconst_1
    //   475: aload 9
    //   477: aastore
    //   478: astore 11
    //   480: aload 10
    //   482: aload_0
    //   483: aload 11
    //   485: invokevirtual 96	java/lang/reflect/Method:invoke	(Ljava/lang/Object;[Ljava/lang/Object;)Ljava/lang/Object;
    //   488: pop
    //   489: aload_0
    //   490: aconst_null
    //   491: putfield 669	uuuuuu/qmqqmm:bv007600760076vv00760076v	Lcom/db/pwcc/dbmobile/foundation/data/manager/broadcasting/ModelUpdatedBroadcastReceiver;
    //   494: aload_0
    //   495: aconst_null
    //   496: putfield 685	uuuuuu/qmqqmm:bvv00760076vv00760076v	Lcom/db/pwcc/dbmobile/foundation/data/manager/broadcasting/InputActionRequiredBroadcastReceiver;
    //   499: return
    //   500: astore 12
    //   502: aload 12
    //   504: invokevirtual 138	java/lang/reflect/InvocationTargetException:getCause	()Ljava/lang/Throwable;
    //   507: athrow
    //   508: astore 21
    //   510: aload 21
    //   512: invokevirtual 138	java/lang/reflect/InvocationTargetException:getCause	()Ljava/lang/Throwable;
    //   515: athrow
    //   516: astore 26
    //   518: aload 26
    //   520: invokevirtual 138	java/lang/reflect/InvocationTargetException:getCause	()Ljava/lang/Throwable;
    //   523: athrow
    //   524: astore 30
    //   526: aload 30
    //   528: invokevirtual 138	java/lang/reflect/InvocationTargetException:getCause	()Ljava/lang/Throwable;
    //   531: athrow
    //   532: astore 17
    //   534: aload 17
    //   536: invokevirtual 138	java/lang/reflect/InvocationTargetException:getCause	()Ljava/lang/Throwable;
    //   539: athrow
    //   540: astore 5
    //   542: aload 5
    //   544: invokevirtual 138	java/lang/reflect/InvocationTargetException:getCause	()Ljava/lang/Throwable;
    //   547: athrow
    //   548: astore 34
    //   550: aload 34
    //   552: invokevirtual 138	java/lang/reflect/InvocationTargetException:getCause	()Ljava/lang/Throwable;
    //   555: athrow
    // Local variable table:
    //   start	length	slot	name	signature
    //   0	556	0	this	qmqqmm
    //   0	556	1	paramContext	android.content.Context
    //   4	46	2	localModelUpdatedBroadcastReceiver	ModelUpdatedBroadcastReceiver
    //   38	16	3	localMethod1	Method
    //   51	5	4	arrayOfObject1	Object[]
    //   540	3	5	localInvocationTargetException1	InvocationTargetException
    //   76	247	7	i	int
    //   81	242	8	j	int
    //   431	45	9	localInputActionRequiredBroadcastReceiver	InputActionRequiredBroadcastReceiver
    //   463	18	10	localMethod2	Method
    //   478	6	11	arrayOfObject2	Object[]
    //   500	3	12	localInvocationTargetException2	InvocationTargetException
    //   338	11	14	k	int
    //   398	9	15	localMethod3	Method
    //   404	6	16	arrayOfObject3	Object[]
    //   532	3	17	localInvocationTargetException3	InvocationTargetException
    //   414	3	18	localObject1	Object
    //   123	9	19	localMethod4	Method
    //   129	6	20	arrayOfObject4	Object[]
    //   508	3	21	localInvocationTargetException4	InvocationTargetException
    //   139	3	22	localObject2	Object
    //   153	49	23	m	int
    //   173	9	24	localMethod5	Method
    //   179	6	25	arrayOfObject5	Object[]
    //   516	3	26	localInvocationTargetException5	InvocationTargetException
    //   189	5	27	localObject3	Object
    //   289	9	28	localMethod6	Method
    //   295	6	29	arrayOfObject6	Object[]
    //   524	3	30	localInvocationTargetException6	InvocationTargetException
    //   305	3	31	localObject4	Object
    //   231	9	32	localMethod7	Method
    //   237	6	33	arrayOfObject7	Object[]
    //   548	3	34	localInvocationTargetException7	InvocationTargetException
    //   247	3	35	localObject5	Object
    // Exception table:
    //   from	to	target	type
    //   480	489	500	java/lang/reflect/InvocationTargetException
    //   131	141	508	java/lang/reflect/InvocationTargetException
    //   181	191	516	java/lang/reflect/InvocationTargetException
    //   297	307	524	java/lang/reflect/InvocationTargetException
    //   406	416	532	java/lang/reflect/InvocationTargetException
    //   53	61	540	java/lang/reflect/InvocationTargetException
    //   239	249	548	java/lang/reflect/InvocationTargetException
  }
  
  /* Error */
  public void buu0075uuuu0075u0075(com.db.pwcc.dbmobile.multi_bank_aggregator.model.MbaPublicKey paramMbaPublicKey)
  {
    // Byte code:
    //   0: getstatic 108	uuuuuu/qmqqmm:b0076vvv0076v00760076v	I
    //   3: istore_2
    //   4: iload_2
    //   5: iload_2
    //   6: getstatic 110	uuuuuu/qmqqmm:b00760076vv0076v00760076v	I
    //   9: iadd
    //   10: imul
    //   11: getstatic 122	uuuuuu/qmqqmm:bvv0076v0076v00760076v	I
    //   14: irem
    //   15: tableswitch	default:+17->32, 0:+68->83
    //   32: ldc 2
    //   34: ldc_w 691
    //   37: iconst_2
    //   38: iconst_4
    //   39: invokestatic 66	xxxxxx/uxxxxx:bb00620062bb0062b0062b0062	(Ljava/lang/String;CC)Ljava/lang/String;
    //   42: iconst_0
    //   43: anewarray 68	java/lang/Class
    //   46: invokevirtual 82	java/lang/Class:getMethod	(Ljava/lang/String;[Ljava/lang/Class;)Ljava/lang/reflect/Method;
    //   49: astore 27
    //   51: iconst_0
    //   52: anewarray 84	java/lang/Object
    //   55: astore 28
    //   57: aload 27
    //   59: aconst_null
    //   60: aload 28
    //   62: invokevirtual 96	java/lang/reflect/Method:invoke	(Ljava/lang/Object;[Ljava/lang/Object;)Ljava/lang/Object;
    //   65: astore 30
    //   67: aload 30
    //   69: checkcast 114	java/lang/Integer
    //   72: invokevirtual 118	java/lang/Integer:intValue	()I
    //   75: putstatic 108	uuuuuu/qmqqmm:b0076vvv0076v00760076v	I
    //   78: bipush 66
    //   80: putstatic 120	uuuuuu/qmqqmm:bv0076vv0076v00760076v	I
    //   83: aload_1
    //   84: invokevirtual 696	com/db/pwcc/dbmobile/multi_bank_aggregator/model/MbaPublicKey:getModulus	()Ljava/lang/String;
    //   87: astore_3
    //   88: aload_1
    //   89: invokevirtual 700	com/db/pwcc/dbmobile/multi_bank_aggregator/model/MbaPublicKey:getExponent	()Ljava/lang/Integer;
    //   92: astore 4
    //   94: ldc_w 439
    //   97: ldc_w 702
    //   100: sipush 221
    //   103: bipush 8
    //   105: iconst_2
    //   106: invokestatic 132	xxxxxx/uxxxxx:bbbb0062b0062b0062b0062	(Ljava/lang/String;CCC)Ljava/lang/String;
    //   109: iconst_2
    //   110: anewarray 68	java/lang/Class
    //   113: dup
    //   114: iconst_0
    //   115: ldc 70
    //   117: aastore
    //   118: dup
    //   119: iconst_1
    //   120: ldc 114
    //   122: aastore
    //   123: invokevirtual 82	java/lang/Class:getMethod	(Ljava/lang/String;[Ljava/lang/Class;)Ljava/lang/reflect/Method;
    //   126: astore 5
    //   128: iconst_2
    //   129: anewarray 84	java/lang/Object
    //   132: dup
    //   133: iconst_0
    //   134: aload_3
    //   135: aastore
    //   136: dup
    //   137: iconst_1
    //   138: aload 4
    //   140: aastore
    //   141: astore 6
    //   143: aload 5
    //   145: aconst_null
    //   146: aload 6
    //   148: invokevirtual 96	java/lang/reflect/Method:invoke	(Ljava/lang/Object;[Ljava/lang/Object;)Ljava/lang/Object;
    //   151: astore 8
    //   153: aload_0
    //   154: aload 8
    //   156: checkcast 443	java/security/interfaces/RSAPublicKey
    //   159: putfield 550	uuuuuu/qmqqmm:b0076007600760076vv00760076v	Ljava/security/interfaces/RSAPublicKey;
    //   162: aload_0
    //   163: invokevirtual 205	uuuuuu/qmqqmm:bkk006Bk006Bk006Bk006Bk	()Z
    //   166: ifeq +308 -> 474
    //   169: getstatic 108	uuuuuu/qmqqmm:b0076vvv0076v00760076v	I
    //   172: getstatic 110	uuuuuu/qmqqmm:b00760076vv0076v00760076v	I
    //   175: iadd
    //   176: getstatic 108	uuuuuu/qmqqmm:b0076vvv0076v00760076v	I
    //   179: imul
    //   180: getstatic 122	uuuuuu/qmqqmm:bvv0076v0076v00760076v	I
    //   183: irem
    //   184: getstatic 120	uuuuuu/qmqqmm:bv0076vv0076v00760076v	I
    //   187: if_icmpeq +98 -> 285
    //   190: ldc 2
    //   192: ldc_w 704
    //   195: sipush 227
    //   198: iconst_5
    //   199: invokestatic 66	xxxxxx/uxxxxx:bb00620062bb0062b0062b0062	(Ljava/lang/String;CC)Ljava/lang/String;
    //   202: iconst_0
    //   203: anewarray 68	java/lang/Class
    //   206: invokevirtual 82	java/lang/Class:getMethod	(Ljava/lang/String;[Ljava/lang/Class;)Ljava/lang/reflect/Method;
    //   209: astore 19
    //   211: iconst_0
    //   212: anewarray 84	java/lang/Object
    //   215: astore 20
    //   217: aload 19
    //   219: aconst_null
    //   220: aload 20
    //   222: invokevirtual 96	java/lang/reflect/Method:invoke	(Ljava/lang/Object;[Ljava/lang/Object;)Ljava/lang/Object;
    //   225: astore 22
    //   227: aload 22
    //   229: checkcast 114	java/lang/Integer
    //   232: invokevirtual 118	java/lang/Integer:intValue	()I
    //   235: putstatic 108	uuuuuu/qmqqmm:b0076vvv0076v00760076v	I
    //   238: ldc 2
    //   240: ldc_w 706
    //   243: bipush 11
    //   245: iconst_4
    //   246: invokestatic 66	xxxxxx/uxxxxx:bb00620062bb0062b0062b0062	(Ljava/lang/String;CC)Ljava/lang/String;
    //   249: iconst_0
    //   250: anewarray 68	java/lang/Class
    //   253: invokevirtual 82	java/lang/Class:getMethod	(Ljava/lang/String;[Ljava/lang/Class;)Ljava/lang/reflect/Method;
    //   256: astore 23
    //   258: iconst_0
    //   259: anewarray 84	java/lang/Object
    //   262: astore 24
    //   264: aload 23
    //   266: aconst_null
    //   267: aload 24
    //   269: invokevirtual 96	java/lang/reflect/Method:invoke	(Ljava/lang/Object;[Ljava/lang/Object;)Ljava/lang/Object;
    //   272: astore 26
    //   274: aload 26
    //   276: checkcast 114	java/lang/Integer
    //   279: invokevirtual 118	java/lang/Integer:intValue	()I
    //   282: putstatic 120	uuuuuu/qmqqmm:bv0076vv0076v00760076v	I
    //   285: aload_0
    //   286: getfield 152	uuuuuu/qmqqmm:bnnnnn006E006E006En	Luuuuuu/ttssst$tsssst;
    //   289: checkcast 215	uuuuuu/mmmmqm$mqqqmm
    //   292: invokeinterface 709 1 0
    //   297: getstatic 108	uuuuuu/qmqqmm:b0076vvv0076v00760076v	I
    //   300: istore 9
    //   302: getstatic 108	uuuuuu/qmqqmm:b0076vvv0076v00760076v	I
    //   305: istore 10
    //   307: iload 10
    //   309: iload 10
    //   311: getstatic 110	uuuuuu/qmqqmm:b00760076vv0076v00760076v	I
    //   314: iadd
    //   315: imul
    //   316: getstatic 122	uuuuuu/qmqqmm:bvv0076v0076v00760076v	I
    //   319: irem
    //   320: tableswitch	default:+20->340, 0:+73->393
    //   340: bipush 38
    //   342: putstatic 108	uuuuuu/qmqqmm:b0076vvv0076v00760076v	I
    //   345: ldc 2
    //   347: ldc_w 711
    //   350: sipush 236
    //   353: iconst_1
    //   354: invokestatic 66	xxxxxx/uxxxxx:bb00620062bb0062b0062b0062	(Ljava/lang/String;CC)Ljava/lang/String;
    //   357: iconst_0
    //   358: anewarray 68	java/lang/Class
    //   361: invokevirtual 82	java/lang/Class:getMethod	(Ljava/lang/String;[Ljava/lang/Class;)Ljava/lang/reflect/Method;
    //   364: astore 15
    //   366: iconst_0
    //   367: anewarray 84	java/lang/Object
    //   370: astore 16
    //   372: aload 15
    //   374: aconst_null
    //   375: aload 16
    //   377: invokevirtual 96	java/lang/reflect/Method:invoke	(Ljava/lang/Object;[Ljava/lang/Object;)Ljava/lang/Object;
    //   380: astore 18
    //   382: aload 18
    //   384: checkcast 114	java/lang/Integer
    //   387: invokevirtual 118	java/lang/Integer:intValue	()I
    //   390: putstatic 120	uuuuuu/qmqqmm:bv0076vv0076v00760076v	I
    //   393: iload 9
    //   395: iload 9
    //   397: getstatic 110	uuuuuu/qmqqmm:b00760076vv0076v00760076v	I
    //   400: iadd
    //   401: imul
    //   402: getstatic 122	uuuuuu/qmqqmm:bvv0076v0076v00760076v	I
    //   405: irem
    //   406: tableswitch	default:+18->424, 0:+68->474
    //   424: ldc 2
    //   426: ldc -90
    //   428: bipush 34
    //   430: iconst_1
    //   431: invokestatic 66	xxxxxx/uxxxxx:bb00620062bb0062b0062b0062	(Ljava/lang/String;CC)Ljava/lang/String;
    //   434: iconst_0
    //   435: anewarray 68	java/lang/Class
    //   438: invokevirtual 82	java/lang/Class:getMethod	(Ljava/lang/String;[Ljava/lang/Class;)Ljava/lang/reflect/Method;
    //   441: astore 11
    //   443: iconst_0
    //   444: anewarray 84	java/lang/Object
    //   447: astore 12
    //   449: aload 11
    //   451: aconst_null
    //   452: aload 12
    //   454: invokevirtual 96	java/lang/reflect/Method:invoke	(Ljava/lang/Object;[Ljava/lang/Object;)Ljava/lang/Object;
    //   457: astore 14
    //   459: aload 14
    //   461: checkcast 114	java/lang/Integer
    //   464: invokevirtual 118	java/lang/Integer:intValue	()I
    //   467: putstatic 108	uuuuuu/qmqqmm:b0076vvv0076v00760076v	I
    //   470: iconst_4
    //   471: putstatic 120	uuuuuu/qmqqmm:bv0076vv0076v00760076v	I
    //   474: return
    //   475: astore 7
    //   477: aload 7
    //   479: invokevirtual 138	java/lang/reflect/InvocationTargetException:getCause	()Ljava/lang/Throwable;
    //   482: athrow
    //   483: astore 13
    //   485: aload 13
    //   487: invokevirtual 138	java/lang/reflect/InvocationTargetException:getCause	()Ljava/lang/Throwable;
    //   490: athrow
    //   491: astore 21
    //   493: aload 21
    //   495: invokevirtual 138	java/lang/reflect/InvocationTargetException:getCause	()Ljava/lang/Throwable;
    //   498: athrow
    //   499: astore 25
    //   501: aload 25
    //   503: invokevirtual 138	java/lang/reflect/InvocationTargetException:getCause	()Ljava/lang/Throwable;
    //   506: athrow
    //   507: astore 17
    //   509: aload 17
    //   511: invokevirtual 138	java/lang/reflect/InvocationTargetException:getCause	()Ljava/lang/Throwable;
    //   514: athrow
    //   515: astore 29
    //   517: aload 29
    //   519: invokevirtual 138	java/lang/reflect/InvocationTargetException:getCause	()Ljava/lang/Throwable;
    //   522: athrow
    // Local variable table:
    //   start	length	slot	name	signature
    //   0	523	0	this	qmqqmm
    //   0	523	1	paramMbaPublicKey	com.db.pwcc.dbmobile.multi_bank_aggregator.model.MbaPublicKey
    //   3	8	2	i	int
    //   87	48	3	str	String
    //   92	47	4	localInteger	Integer
    //   126	18	5	localMethod1	Method
    //   141	6	6	arrayOfObject1	Object[]
    //   475	3	7	localInvocationTargetException1	InvocationTargetException
    //   151	4	8	localObject1	Object
    //   300	102	9	j	int
    //   305	11	10	k	int
    //   441	9	11	localMethod2	Method
    //   447	6	12	arrayOfObject2	Object[]
    //   483	3	13	localInvocationTargetException2	InvocationTargetException
    //   457	3	14	localObject2	Object
    //   364	9	15	localMethod3	Method
    //   370	6	16	arrayOfObject3	Object[]
    //   507	3	17	localInvocationTargetException3	InvocationTargetException
    //   380	3	18	localObject3	Object
    //   209	9	19	localMethod4	Method
    //   215	6	20	arrayOfObject4	Object[]
    //   491	3	21	localInvocationTargetException4	InvocationTargetException
    //   225	3	22	localObject4	Object
    //   256	9	23	localMethod5	Method
    //   262	6	24	arrayOfObject5	Object[]
    //   499	3	25	localInvocationTargetException5	InvocationTargetException
    //   272	3	26	localObject5	Object
    //   49	9	27	localMethod6	Method
    //   55	6	28	arrayOfObject6	Object[]
    //   515	3	29	localInvocationTargetException6	InvocationTargetException
    //   65	3	30	localObject6	Object
    // Exception table:
    //   from	to	target	type
    //   143	153	475	java/lang/reflect/InvocationTargetException
    //   449	459	483	java/lang/reflect/InvocationTargetException
    //   217	227	491	java/lang/reflect/InvocationTargetException
    //   264	274	499	java/lang/reflect/InvocationTargetException
    //   372	382	507	java/lang/reflect/InvocationTargetException
    //   57	67	515	java/lang/reflect/InvocationTargetException
  }
  
  /* Error */
  public void buuuu007500750075uu0075(@android.support.annotation.NonNull android.content.Context paramContext)
  {
    // Byte code:
    //   0: aload_0
    //   1: getfield 669	uuuuuu/qmqqmm:bv007600760076vv00760076v	Lcom/db/pwcc/dbmobile/foundation/data/manager/broadcasting/ModelUpdatedBroadcastReceiver;
    //   4: ifnonnull +337 -> 341
    //   7: aconst_null
    //   8: invokevirtual 506	java/lang/String:length	()I
    //   11: pop
    //   12: goto -5 -> 7
    //   15: astore 8
    //   17: ldc 2
    //   19: ldc_w 350
    //   22: sipush 130
    //   25: iconst_5
    //   26: invokestatic 66	xxxxxx/uxxxxx:bb00620062bb0062b0062b0062	(Ljava/lang/String;CC)Ljava/lang/String;
    //   29: iconst_0
    //   30: anewarray 68	java/lang/Class
    //   33: invokevirtual 82	java/lang/Class:getMethod	(Ljava/lang/String;[Ljava/lang/Class;)Ljava/lang/reflect/Method;
    //   36: astore 9
    //   38: iconst_0
    //   39: anewarray 84	java/lang/Object
    //   42: astore 10
    //   44: aload 9
    //   46: aconst_null
    //   47: aload 10
    //   49: invokevirtual 96	java/lang/reflect/Method:invoke	(Ljava/lang/Object;[Ljava/lang/Object;)Ljava/lang/Object;
    //   52: astore 12
    //   54: aload 12
    //   56: checkcast 114	java/lang/Integer
    //   59: invokevirtual 118	java/lang/Integer:intValue	()I
    //   62: putstatic 108	uuuuuu/qmqqmm:b0076vvv0076v00760076v	I
    //   65: iconst_3
    //   66: istore 13
    //   68: iload 13
    //   70: iconst_0
    //   71: idiv
    //   72: istore 26
    //   74: getstatic 108	uuuuuu/qmqqmm:b0076vvv0076v00760076v	I
    //   77: istore 27
    //   79: ldc 2
    //   81: ldc_w 714
    //   84: bipush 63
    //   86: sipush 201
    //   89: iconst_2
    //   90: invokestatic 132	xxxxxx/uxxxxx:bbbb0062b0062b0062b0062	(Ljava/lang/String;CCC)Ljava/lang/String;
    //   93: iconst_0
    //   94: anewarray 68	java/lang/Class
    //   97: invokevirtual 82	java/lang/Class:getMethod	(Ljava/lang/String;[Ljava/lang/Class;)Ljava/lang/reflect/Method;
    //   100: astore 28
    //   102: iconst_0
    //   103: anewarray 84	java/lang/Object
    //   106: astore 29
    //   108: aload 28
    //   110: aconst_null
    //   111: aload 29
    //   113: invokevirtual 96	java/lang/reflect/Method:invoke	(Ljava/lang/Object;[Ljava/lang/Object;)Ljava/lang/Object;
    //   116: astore 31
    //   118: iload 27
    //   120: iload 27
    //   122: aload 31
    //   124: checkcast 114	java/lang/Integer
    //   127: invokevirtual 118	java/lang/Integer:intValue	()I
    //   130: iadd
    //   131: imul
    //   132: getstatic 122	uuuuuu/qmqqmm:bvv0076v0076v00760076v	I
    //   135: irem
    //   136: tableswitch	default:+20->156, 0:+373->509
    //   156: bipush 59
    //   158: putstatic 108	uuuuuu/qmqqmm:b0076vvv0076v00760076v	I
    //   161: bipush 62
    //   163: putstatic 120	uuuuuu/qmqqmm:bv0076vv0076v00760076v	I
    //   166: iload 26
    //   168: istore 13
    //   170: goto -102 -> 68
    //   173: astore 15
    //   175: ldc 2
    //   177: ldc_w 716
    //   180: sipush 180
    //   183: sipush 164
    //   186: iconst_0
    //   187: invokestatic 132	xxxxxx/uxxxxx:bbbb0062b0062b0062b0062	(Ljava/lang/String;CCC)Ljava/lang/String;
    //   190: iconst_0
    //   191: anewarray 68	java/lang/Class
    //   194: invokevirtual 82	java/lang/Class:getMethod	(Ljava/lang/String;[Ljava/lang/Class;)Ljava/lang/reflect/Method;
    //   197: astore 16
    //   199: iconst_0
    //   200: anewarray 84	java/lang/Object
    //   203: astore 17
    //   205: aload 16
    //   207: aconst_null
    //   208: aload 17
    //   210: invokevirtual 96	java/lang/reflect/Method:invoke	(Ljava/lang/Object;[Ljava/lang/Object;)Ljava/lang/Object;
    //   213: astore 19
    //   215: aload 19
    //   217: checkcast 114	java/lang/Integer
    //   220: invokevirtual 118	java/lang/Integer:intValue	()I
    //   223: putstatic 108	uuuuuu/qmqqmm:b0076vvv0076v00760076v	I
    //   226: aload_0
    //   227: new 718	uuuuuu/qmqqmm$1
    //   230: dup
    //   231: aload_0
    //   232: invokespecial 720	uuuuuu/qmqqmm$1:<init>	(Luuuuuu/qmqqmm;)V
    //   235: putfield 669	uuuuuu/qmqqmm:bv007600760076vv00760076v	Lcom/db/pwcc/dbmobile/foundation/data/manager/broadcasting/ModelUpdatedBroadcastReceiver;
    //   238: aload_1
    //   239: invokestatic 172	android/support/v4/content/LocalBroadcastManager:getInstance	(Landroid/content/Context;)Landroid/support/v4/content/LocalBroadcastManager;
    //   242: aload_0
    //   243: getfield 669	uuuuuu/qmqqmm:bv007600760076vv00760076v	Lcom/db/pwcc/dbmobile/foundation/data/manager/broadcasting/ModelUpdatedBroadcastReceiver;
    //   246: invokestatic 726	com/db/pwcc/dbmobile/foundation/data/manager/broadcasting/ModelUpdatedBroadcastReceiver:makeModelUpdatedIntentFilter	()Landroid/content/IntentFilter;
    //   249: invokevirtual 730	android/support/v4/content/LocalBroadcastManager:registerReceiver	(Landroid/content/BroadcastReceiver;Landroid/content/IntentFilter;)V
    //   252: getstatic 108	uuuuuu/qmqqmm:b0076vvv0076v00760076v	I
    //   255: istore 20
    //   257: iload 20
    //   259: iload 20
    //   261: getstatic 110	uuuuuu/qmqqmm:b00760076vv0076v00760076v	I
    //   264: iadd
    //   265: imul
    //   266: istore 21
    //   268: ldc 2
    //   270: ldc_w 732
    //   273: bipush 11
    //   275: iconst_5
    //   276: invokestatic 66	xxxxxx/uxxxxx:bb00620062bb0062b0062b0062	(Ljava/lang/String;CC)Ljava/lang/String;
    //   279: iconst_0
    //   280: anewarray 68	java/lang/Class
    //   283: invokevirtual 82	java/lang/Class:getMethod	(Ljava/lang/String;[Ljava/lang/Class;)Ljava/lang/reflect/Method;
    //   286: astore 22
    //   288: iconst_0
    //   289: anewarray 84	java/lang/Object
    //   292: astore 23
    //   294: aload 22
    //   296: aconst_null
    //   297: aload 23
    //   299: invokevirtual 96	java/lang/reflect/Method:invoke	(Ljava/lang/Object;[Ljava/lang/Object;)Ljava/lang/Object;
    //   302: astore 25
    //   304: iload 21
    //   306: aload 25
    //   308: checkcast 114	java/lang/Integer
    //   311: invokevirtual 118	java/lang/Integer:intValue	()I
    //   314: irem
    //   315: tableswitch	default:+17->332, 0:+26->341
    //   332: iconst_3
    //   333: putstatic 108	uuuuuu/qmqqmm:b0076vvv0076v00760076v	I
    //   336: bipush 10
    //   338: putstatic 120	uuuuuu/qmqqmm:bv0076vv0076v00760076v	I
    //   341: aload_0
    //   342: getfield 685	uuuuuu/qmqqmm:bvv00760076vv00760076v	Lcom/db/pwcc/dbmobile/foundation/data/manager/broadcasting/InputActionRequiredBroadcastReceiver;
    //   345: ifnonnull +107 -> 452
    //   348: aload_0
    //   349: new 734	uuuuuu/qmqqmm$2
    //   352: dup
    //   353: aload_0
    //   354: invokespecial 735	uuuuuu/qmqqmm$2:<init>	(Luuuuuu/qmqqmm;)V
    //   357: putfield 685	uuuuuu/qmqqmm:bvv00760076vv00760076v	Lcom/db/pwcc/dbmobile/foundation/data/manager/broadcasting/InputActionRequiredBroadcastReceiver;
    //   360: aload_1
    //   361: invokestatic 172	android/support/v4/content/LocalBroadcastManager:getInstance	(Landroid/content/Context;)Landroid/support/v4/content/LocalBroadcastManager;
    //   364: astore_2
    //   365: aload_0
    //   366: getfield 685	uuuuuu/qmqqmm:bvv00760076vv00760076v	Lcom/db/pwcc/dbmobile/foundation/data/manager/broadcasting/InputActionRequiredBroadcastReceiver;
    //   369: astore_3
    //   370: getstatic 108	uuuuuu/qmqqmm:b0076vvv0076v00760076v	I
    //   373: getstatic 110	uuuuuu/qmqqmm:b00760076vv0076v00760076v	I
    //   376: iadd
    //   377: getstatic 108	uuuuuu/qmqqmm:b0076vvv0076v00760076v	I
    //   380: imul
    //   381: getstatic 122	uuuuuu/qmqqmm:bvv0076v0076v00760076v	I
    //   384: irem
    //   385: getstatic 120	uuuuuu/qmqqmm:bv0076vv0076v00760076v	I
    //   388: if_icmpeq +56 -> 444
    //   391: bipush 6
    //   393: putstatic 108	uuuuuu/qmqqmm:b0076vvv0076v00760076v	I
    //   396: ldc 2
    //   398: ldc_w 737
    //   401: sipush 236
    //   404: iconst_5
    //   405: invokestatic 66	xxxxxx/uxxxxx:bb00620062bb0062b0062b0062	(Ljava/lang/String;CC)Ljava/lang/String;
    //   408: iconst_0
    //   409: anewarray 68	java/lang/Class
    //   412: invokevirtual 82	java/lang/Class:getMethod	(Ljava/lang/String;[Ljava/lang/Class;)Ljava/lang/reflect/Method;
    //   415: astore 4
    //   417: iconst_0
    //   418: anewarray 84	java/lang/Object
    //   421: astore 5
    //   423: aload 4
    //   425: aconst_null
    //   426: aload 5
    //   428: invokevirtual 96	java/lang/reflect/Method:invoke	(Ljava/lang/Object;[Ljava/lang/Object;)Ljava/lang/Object;
    //   431: astore 7
    //   433: aload 7
    //   435: checkcast 114	java/lang/Integer
    //   438: invokevirtual 118	java/lang/Integer:intValue	()I
    //   441: putstatic 120	uuuuuu/qmqqmm:bv0076vv0076v00760076v	I
    //   444: aload_2
    //   445: aload_3
    //   446: invokestatic 742	com/db/pwcc/dbmobile/foundation/data/manager/broadcasting/InputActionRequiredBroadcastReceiver:makeInputActionRequiredIntentFilter	()Landroid/content/IntentFilter;
    //   449: invokevirtual 730	android/support/v4/content/LocalBroadcastManager:registerReceiver	(Landroid/content/BroadcastReceiver;Landroid/content/IntentFilter;)V
    //   452: return
    //   453: astore 11
    //   455: aload 11
    //   457: invokevirtual 138	java/lang/reflect/InvocationTargetException:getCause	()Ljava/lang/Throwable;
    //   460: athrow
    //   461: astore 14
    //   463: bipush 42
    //   465: putstatic 108	uuuuuu/qmqqmm:b0076vvv0076v00760076v	I
    //   468: iload 13
    //   470: iconst_0
    //   471: idiv
    //   472: istore 13
    //   474: goto -6 -> 468
    //   477: astore 30
    //   479: aload 30
    //   481: invokevirtual 138	java/lang/reflect/InvocationTargetException:getCause	()Ljava/lang/Throwable;
    //   484: athrow
    //   485: astore 18
    //   487: aload 18
    //   489: invokevirtual 138	java/lang/reflect/InvocationTargetException:getCause	()Ljava/lang/Throwable;
    //   492: athrow
    //   493: astore 24
    //   495: aload 24
    //   497: invokevirtual 138	java/lang/reflect/InvocationTargetException:getCause	()Ljava/lang/Throwable;
    //   500: athrow
    //   501: astore 6
    //   503: aload 6
    //   505: invokevirtual 138	java/lang/reflect/InvocationTargetException:getCause	()Ljava/lang/Throwable;
    //   508: athrow
    //   509: iload 26
    //   511: istore 13
    //   513: goto -445 -> 68
    // Local variable table:
    //   start	length	slot	name	signature
    //   0	516	0	this	qmqqmm
    //   0	516	1	paramContext	android.content.Context
    //   364	81	2	localLocalBroadcastManager	android.support.v4.content.LocalBroadcastManager
    //   369	77	3	localInputActionRequiredBroadcastReceiver	InputActionRequiredBroadcastReceiver
    //   415	9	4	localMethod1	Method
    //   421	6	5	arrayOfObject1	Object[]
    //   501	3	6	localInvocationTargetException1	InvocationTargetException
    //   431	3	7	localObject1	Object
    //   15	1	8	localException1	Exception
    //   36	9	9	localMethod2	Method
    //   42	6	10	arrayOfObject2	Object[]
    //   453	3	11	localInvocationTargetException2	InvocationTargetException
    //   52	3	12	localObject2	Object
    //   66	446	13	i	int
    //   461	1	14	localException2	Exception
    //   173	1	15	localException3	Exception
    //   197	9	16	localMethod3	Method
    //   203	6	17	arrayOfObject3	Object[]
    //   485	3	18	localInvocationTargetException3	InvocationTargetException
    //   213	3	19	localObject3	Object
    //   255	11	20	j	int
    //   266	49	21	k	int
    //   286	9	22	localMethod4	Method
    //   292	6	23	arrayOfObject4	Object[]
    //   493	3	24	localInvocationTargetException4	InvocationTargetException
    //   302	5	25	localObject4	Object
    //   72	438	26	m	int
    //   77	55	27	n	int
    //   100	9	28	localMethod5	Method
    //   106	6	29	arrayOfObject5	Object[]
    //   477	3	30	localInvocationTargetException5	InvocationTargetException
    //   116	7	31	localObject5	Object
    // Exception table:
    //   from	to	target	type
    //   7	12	15	java/lang/Exception
    //   468	474	173	java/lang/Exception
    //   44	54	453	java/lang/reflect/InvocationTargetException
    //   68	74	461	java/lang/Exception
    //   108	118	477	java/lang/reflect/InvocationTargetException
    //   205	215	485	java/lang/reflect/InvocationTargetException
    //   294	304	493	java/lang/reflect/InvocationTargetException
    //   423	433	501	java/lang/reflect/InvocationTargetException
  }
  
  /* Error */
  public void buuuuuuu0075u0075()
  {
    // Byte code:
    //   0: aload_0
    //   1: invokevirtual 205	uuuuuu/qmqqmm:bkk006Bk006Bk006Bk006Bk	()Z
    //   4: ifne +137 -> 141
    //   7: getstatic 108	uuuuuu/qmqqmm:b0076vvv0076v00760076v	I
    //   10: istore 18
    //   12: iload 18
    //   14: iload 18
    //   16: getstatic 110	uuuuuu/qmqqmm:b00760076vv0076v00760076v	I
    //   19: iadd
    //   20: imul
    //   21: istore 19
    //   23: ldc 2
    //   25: ldc_w 745
    //   28: sipush 239
    //   31: iconst_3
    //   32: invokestatic 66	xxxxxx/uxxxxx:bb00620062bb0062b0062b0062	(Ljava/lang/String;CC)Ljava/lang/String;
    //   35: iconst_0
    //   36: anewarray 68	java/lang/Class
    //   39: invokevirtual 82	java/lang/Class:getMethod	(Ljava/lang/String;[Ljava/lang/Class;)Ljava/lang/reflect/Method;
    //   42: astore 20
    //   44: iconst_0
    //   45: anewarray 84	java/lang/Object
    //   48: astore 21
    //   50: aload 20
    //   52: aconst_null
    //   53: aload 21
    //   55: invokevirtual 96	java/lang/reflect/Method:invoke	(Ljava/lang/Object;[Ljava/lang/Object;)Ljava/lang/Object;
    //   58: astore 23
    //   60: iload 19
    //   62: aload 23
    //   64: checkcast 114	java/lang/Integer
    //   67: invokevirtual 118	java/lang/Integer:intValue	()I
    //   70: irem
    //   71: tableswitch	default:+17->88, 0:+69->140
    //   88: ldc 2
    //   90: ldc_w 269
    //   93: bipush 111
    //   95: iconst_5
    //   96: invokestatic 66	xxxxxx/uxxxxx:bb00620062bb0062b0062b0062	(Ljava/lang/String;CC)Ljava/lang/String;
    //   99: iconst_0
    //   100: anewarray 68	java/lang/Class
    //   103: invokevirtual 82	java/lang/Class:getMethod	(Ljava/lang/String;[Ljava/lang/Class;)Ljava/lang/reflect/Method;
    //   106: astore 24
    //   108: iconst_0
    //   109: anewarray 84	java/lang/Object
    //   112: astore 25
    //   114: aload 24
    //   116: aconst_null
    //   117: aload 25
    //   119: invokevirtual 96	java/lang/reflect/Method:invoke	(Ljava/lang/Object;[Ljava/lang/Object;)Ljava/lang/Object;
    //   122: astore 27
    //   124: aload 27
    //   126: checkcast 114	java/lang/Integer
    //   129: invokevirtual 118	java/lang/Integer:intValue	()I
    //   132: putstatic 108	uuuuuu/qmqqmm:b0076vvv0076v00760076v	I
    //   135: bipush 33
    //   137: putstatic 120	uuuuuu/qmqqmm:bv0076vv0076v00760076v	I
    //   140: return
    //   141: aload_0
    //   142: getfield 196	uuuuuu/qmqqmm:b0076v00760076vv00760076v	Luuuuuu/vxvvvx;
    //   145: aload_0
    //   146: getfield 42	uuuuuu/qmqqmm:b00760076v0076vv00760076v	Ljava/lang/String;
    //   149: invokevirtual 409	uuuuuu/vxvvvx:b0075u00750075u00750075u00750075	(Ljava/lang/String;)Lcom/db/pwcc/dbmobile/multi_bank_aggregator/data/MbaFinancialOverviewData;
    //   152: astore_1
    //   153: aload_0
    //   154: getfield 40	uuuuuu/qmqqmm:bvvvv0076v00760076v	Z
    //   157: ifeq +70 -> 227
    //   160: aload_0
    //   161: getfield 152	uuuuuu/qmqqmm:bnnnnn006E006E006En	Luuuuuu/ttssst$tsssst;
    //   164: checkcast 215	uuuuuu/mmmmqm$mqqqmm
    //   167: astore 16
    //   169: getstatic 108	uuuuuu/qmqqmm:b0076vvv0076v00760076v	I
    //   172: getstatic 110	uuuuuu/qmqqmm:b00760076vv0076v00760076v	I
    //   175: iadd
    //   176: getstatic 108	uuuuuu/qmqqmm:b0076vvv0076v00760076v	I
    //   179: imul
    //   180: getstatic 122	uuuuuu/qmqqmm:bvv0076v0076v00760076v	I
    //   183: irem
    //   184: getstatic 120	uuuuuu/qmqqmm:bv0076vv0076v00760076v	I
    //   187: if_icmpeq +13 -> 200
    //   190: bipush 97
    //   192: putstatic 108	uuuuuu/qmqqmm:b0076vvv0076v00760076v	I
    //   195: bipush 99
    //   197: putstatic 120	uuuuuu/qmqqmm:bv0076vv0076v00760076v	I
    //   200: aload_1
    //   201: ifnull +306 -> 507
    //   204: aload_1
    //   205: invokevirtual 749	com/db/pwcc/dbmobile/multi_bank_aggregator/data/MbaFinancialOverviewData:getPinSaved	()Ljava/lang/Boolean;
    //   208: invokevirtual 292	java/lang/Boolean:booleanValue	()Z
    //   211: ifeq +296 -> 507
    //   214: iconst_1
    //   215: istore 17
    //   217: aload 16
    //   219: iload 17
    //   221: invokeinterface 452 2 0
    //   226: return
    //   227: aload_1
    //   228: ifnull -88 -> 140
    //   231: aload_1
    //   232: invokevirtual 752	com/db/pwcc/dbmobile/multi_bank_aggregator/data/MbaFinancialOverviewData:getSynchronizationErrorMessage	()Ljava/lang/String;
    //   235: ifnull -95 -> 140
    //   238: aload_0
    //   239: getfield 152	uuuuuu/qmqqmm:bnnnnn006E006E006En	Luuuuuu/ttssst$tsssst;
    //   242: checkcast 215	uuuuuu/mmmmqm$mqqqmm
    //   245: astore_2
    //   246: getstatic 108	uuuuuu/qmqqmm:b0076vvv0076v00760076v	I
    //   249: getstatic 110	uuuuuu/qmqqmm:b00760076vv0076v00760076v	I
    //   252: iadd
    //   253: getstatic 108	uuuuuu/qmqqmm:b0076vvv0076v00760076v	I
    //   256: imul
    //   257: getstatic 122	uuuuuu/qmqqmm:bvv0076v0076v00760076v	I
    //   260: irem
    //   261: getstatic 120	uuuuuu/qmqqmm:bv0076vv0076v00760076v	I
    //   264: if_icmpeq +58 -> 322
    //   267: bipush 51
    //   269: putstatic 108	uuuuuu/qmqqmm:b0076vvv0076v00760076v	I
    //   272: ldc 2
    //   274: ldc_w 529
    //   277: bipush 100
    //   279: sipush 140
    //   282: iconst_1
    //   283: invokestatic 132	xxxxxx/uxxxxx:bbbb0062b0062b0062b0062	(Ljava/lang/String;CCC)Ljava/lang/String;
    //   286: iconst_0
    //   287: anewarray 68	java/lang/Class
    //   290: invokevirtual 82	java/lang/Class:getMethod	(Ljava/lang/String;[Ljava/lang/Class;)Ljava/lang/reflect/Method;
    //   293: astore 12
    //   295: iconst_0
    //   296: anewarray 84	java/lang/Object
    //   299: astore 13
    //   301: aload 12
    //   303: aconst_null
    //   304: aload 13
    //   306: invokevirtual 96	java/lang/reflect/Method:invoke	(Ljava/lang/Object;[Ljava/lang/Object;)Ljava/lang/Object;
    //   309: astore 15
    //   311: aload 15
    //   313: checkcast 114	java/lang/Integer
    //   316: invokevirtual 118	java/lang/Integer:intValue	()I
    //   319: putstatic 120	uuuuuu/qmqqmm:bv0076vv0076v00760076v	I
    //   322: aload_2
    //   323: iconst_0
    //   324: invokeinterface 452 2 0
    //   329: aload_0
    //   330: getfield 152	uuuuuu/qmqqmm:bnnnnn006E006E006En	Luuuuuu/ttssst$tsssst;
    //   333: checkcast 215	uuuuuu/mmmmqm$mqqqmm
    //   336: aload_1
    //   337: invokevirtual 755	com/db/pwcc/dbmobile/multi_bank_aggregator/data/MbaFinancialOverviewData:getBankName	()Ljava/lang/String;
    //   340: aload_1
    //   341: invokevirtual 752	com/db/pwcc/dbmobile/multi_bank_aggregator/data/MbaFinancialOverviewData:getSynchronizationErrorMessage	()Ljava/lang/String;
    //   344: invokeinterface 758 3 0
    //   349: getstatic 108	uuuuuu/qmqqmm:b0076vvv0076v00760076v	I
    //   352: getstatic 110	uuuuuu/qmqqmm:b00760076vv0076v00760076v	I
    //   355: iadd
    //   356: getstatic 108	uuuuuu/qmqqmm:b0076vvv0076v00760076v	I
    //   359: imul
    //   360: getstatic 122	uuuuuu/qmqqmm:bvv0076v0076v00760076v	I
    //   363: irem
    //   364: istore_3
    //   365: ldc 2
    //   367: ldc_w 760
    //   370: bipush 6
    //   372: iconst_0
    //   373: invokestatic 66	xxxxxx/uxxxxx:bb00620062bb0062b0062b0062	(Ljava/lang/String;CC)Ljava/lang/String;
    //   376: iconst_0
    //   377: anewarray 68	java/lang/Class
    //   380: invokevirtual 82	java/lang/Class:getMethod	(Ljava/lang/String;[Ljava/lang/Class;)Ljava/lang/reflect/Method;
    //   383: astore 4
    //   385: iconst_0
    //   386: anewarray 84	java/lang/Object
    //   389: astore 5
    //   391: aload 4
    //   393: aconst_null
    //   394: aload 5
    //   396: invokevirtual 96	java/lang/reflect/Method:invoke	(Ljava/lang/Object;[Ljava/lang/Object;)Ljava/lang/Object;
    //   399: astore 7
    //   401: iload_3
    //   402: aload 7
    //   404: checkcast 114	java/lang/Integer
    //   407: invokevirtual 118	java/lang/Integer:intValue	()I
    //   410: if_icmpeq -270 -> 140
    //   413: ldc 2
    //   415: ldc_w 259
    //   418: sipush 133
    //   421: iconst_1
    //   422: invokestatic 66	xxxxxx/uxxxxx:bb00620062bb0062b0062b0062	(Ljava/lang/String;CC)Ljava/lang/String;
    //   425: iconst_0
    //   426: anewarray 68	java/lang/Class
    //   429: invokevirtual 82	java/lang/Class:getMethod	(Ljava/lang/String;[Ljava/lang/Class;)Ljava/lang/reflect/Method;
    //   432: astore 8
    //   434: iconst_0
    //   435: anewarray 84	java/lang/Object
    //   438: astore 9
    //   440: aload 8
    //   442: aconst_null
    //   443: aload 9
    //   445: invokevirtual 96	java/lang/reflect/Method:invoke	(Ljava/lang/Object;[Ljava/lang/Object;)Ljava/lang/Object;
    //   448: astore 11
    //   450: aload 11
    //   452: checkcast 114	java/lang/Integer
    //   455: invokevirtual 118	java/lang/Integer:intValue	()I
    //   458: putstatic 108	uuuuuu/qmqqmm:b0076vvv0076v00760076v	I
    //   461: bipush 21
    //   463: putstatic 120	uuuuuu/qmqqmm:bv0076vv0076v00760076v	I
    //   466: return
    //   467: astore 22
    //   469: aload 22
    //   471: invokevirtual 138	java/lang/reflect/InvocationTargetException:getCause	()Ljava/lang/Throwable;
    //   474: athrow
    //   475: astore 10
    //   477: aload 10
    //   479: invokevirtual 138	java/lang/reflect/InvocationTargetException:getCause	()Ljava/lang/Throwable;
    //   482: athrow
    //   483: astore 6
    //   485: aload 6
    //   487: invokevirtual 138	java/lang/reflect/InvocationTargetException:getCause	()Ljava/lang/Throwable;
    //   490: athrow
    //   491: astore 26
    //   493: aload 26
    //   495: invokevirtual 138	java/lang/reflect/InvocationTargetException:getCause	()Ljava/lang/Throwable;
    //   498: athrow
    //   499: astore 14
    //   501: aload 14
    //   503: invokevirtual 138	java/lang/reflect/InvocationTargetException:getCause	()Ljava/lang/Throwable;
    //   506: athrow
    //   507: iconst_0
    //   508: istore 17
    //   510: goto -293 -> 217
    // Local variable table:
    //   start	length	slot	name	signature
    //   0	513	0	this	qmqqmm
    //   152	189	1	localMbaFinancialOverviewData	com.db.pwcc.dbmobile.multi_bank_aggregator.data.MbaFinancialOverviewData
    //   245	78	2	localMqqqmm1	mmmmqm.mqqqmm
    //   364	47	3	i	int
    //   383	9	4	localMethod1	Method
    //   389	6	5	arrayOfObject1	Object[]
    //   483	3	6	localInvocationTargetException1	InvocationTargetException
    //   399	4	7	localObject1	Object
    //   432	9	8	localMethod2	Method
    //   438	6	9	arrayOfObject2	Object[]
    //   475	3	10	localInvocationTargetException2	InvocationTargetException
    //   448	3	11	localObject2	Object
    //   293	9	12	localMethod3	Method
    //   299	6	13	arrayOfObject3	Object[]
    //   499	3	14	localInvocationTargetException3	InvocationTargetException
    //   309	3	15	localObject3	Object
    //   167	51	16	localMqqqmm2	mmmmqm.mqqqmm
    //   215	294	17	bool	boolean
    //   10	11	18	j	int
    //   21	50	19	k	int
    //   42	9	20	localMethod4	Method
    //   48	6	21	arrayOfObject4	Object[]
    //   467	3	22	localInvocationTargetException4	InvocationTargetException
    //   58	5	23	localObject4	Object
    //   106	9	24	localMethod5	Method
    //   112	6	25	arrayOfObject5	Object[]
    //   491	3	26	localInvocationTargetException5	InvocationTargetException
    //   122	3	27	localObject5	Object
    // Exception table:
    //   from	to	target	type
    //   50	60	467	java/lang/reflect/InvocationTargetException
    //   440	450	475	java/lang/reflect/InvocationTargetException
    //   391	401	483	java/lang/reflect/InvocationTargetException
    //   114	124	491	java/lang/reflect/InvocationTargetException
    //   301	311	499	java/lang/reflect/InvocationTargetException
  }
}
