package uuuuuu;

import com.db.pwcc.dbmobile.foundation.R.string;
import com.db.pwcc.dbmobile.model.error.DbError;
import com.db.pwcc.dbmobile.secure.preferences.SharedPreferencesHelper;
import java.lang.reflect.InvocationTargetException;
import java.lang.reflect.Method;
import javax.inject.Inject;
import xxxxxx.uxxxxx;

public class ttttst
  extends sttsst<stsstt.sssstt>
  implements stsstt.tssstt<stsstt.sssstt>, vvpvvp.ppvvvp
{
  public static int b006E006E006E006E006Enn006En = 2;
  public static int b006Ennnn006En006En = 74;
  public static int bn006E006E006E006Enn006En = 1;
  public static int bnnnnn006En006En;
  @Inject
  public xxsxxs b006E006En006E006Enn006En;
  public mffffm b006En006E006E006Enn006En = new mffffm();
  @Inject
  public yygggy bn006En006E006Enn006En;
  @Inject
  public sssttt bnn006E006E006Enn006En;
  
  public ttttst()
  {
    this.b006Enn006Enn006E006En = true;
  }
  
  public static int b006B006B006Bkkkkk006Bk()
  {
    return 2;
  }
  
  public static int b006Bk006Bkkkkk006Bk()
  {
    return 3;
  }
  
  public static int bk006B006Bkkkkk006Bk()
  {
    return 0;
  }
  
  public static int bkkk006Bkkkk006Bk()
  {
    return 1;
  }
  
  /* Error */
  public void b0061aa00610061aaa0061a(com.db.pwcc.dbmobile.model.profile.Profile paramProfile)
  {
    // Byte code:
    //   0: aload_0
    //   1: getfield 52	uuuuuu/ttttst:bnnnnn006E006E006En	Luuuuuu/ttssst$tsssst;
    //   4: checkcast 54	uuuuuu/stsstt$sssstt
    //   7: astore_2
    //   8: aload_1
    //   9: invokevirtual 60	com/db/pwcc/dbmobile/model/profile/Profile:getAccountHolder	()Ljava/lang/String;
    //   12: invokestatic 66	uuuuuu/oononn:b006Bk006B006Bk006Bk006Bk006B	(Ljava/lang/String;)Ljava/lang/String;
    //   15: astore_3
    //   16: aload_1
    //   17: invokevirtual 60	com/db/pwcc/dbmobile/model/profile/Profile:getAccountHolder	()Ljava/lang/String;
    //   20: astore 4
    //   22: ldc 2
    //   24: ldc 68
    //   26: bipush 89
    //   28: iconst_5
    //   29: invokestatic 74	xxxxxx/uxxxxx:bb00620062bb0062b0062b0062	(Ljava/lang/String;CC)Ljava/lang/String;
    //   32: iconst_0
    //   33: anewarray 76	java/lang/Class
    //   36: invokevirtual 80	java/lang/Class:getMethod	(Ljava/lang/String;[Ljava/lang/Class;)Ljava/lang/reflect/Method;
    //   39: astore 5
    //   41: iconst_0
    //   42: anewarray 82	java/lang/Object
    //   45: astore 6
    //   47: aload 5
    //   49: aconst_null
    //   50: aload 6
    //   52: invokevirtual 88	java/lang/reflect/Method:invoke	(Ljava/lang/Object;[Ljava/lang/Object;)Ljava/lang/Object;
    //   55: astore 8
    //   57: aload 8
    //   59: checkcast 90	java/lang/Integer
    //   62: invokevirtual 93	java/lang/Integer:intValue	()I
    //   65: getstatic 95	uuuuuu/ttttst:bn006E006E006E006Enn006En	I
    //   68: iadd
    //   69: istore 9
    //   71: ldc 2
    //   73: ldc 97
    //   75: iconst_3
    //   76: sipush 134
    //   79: iconst_0
    //   80: invokestatic 101	xxxxxx/uxxxxx:bbbb0062b0062b0062b0062	(Ljava/lang/String;CCC)Ljava/lang/String;
    //   83: iconst_0
    //   84: anewarray 76	java/lang/Class
    //   87: invokevirtual 80	java/lang/Class:getMethod	(Ljava/lang/String;[Ljava/lang/Class;)Ljava/lang/reflect/Method;
    //   90: astore 10
    //   92: iconst_0
    //   93: anewarray 82	java/lang/Object
    //   96: astore 11
    //   98: aload 10
    //   100: aconst_null
    //   101: aload 11
    //   103: invokevirtual 88	java/lang/reflect/Method:invoke	(Ljava/lang/Object;[Ljava/lang/Object;)Ljava/lang/Object;
    //   106: astore 13
    //   108: iload 9
    //   110: aload 13
    //   112: checkcast 90	java/lang/Integer
    //   115: invokevirtual 93	java/lang/Integer:intValue	()I
    //   118: imul
    //   119: getstatic 103	uuuuuu/ttttst:b006E006E006E006E006Enn006En	I
    //   122: irem
    //   123: getstatic 105	uuuuuu/ttttst:bnnnnn006En006En	I
    //   126: if_icmpeq +290 -> 416
    //   129: getstatic 107	uuuuuu/ttttst:b006Ennnn006En006En	I
    //   132: getstatic 95	uuuuuu/ttttst:bn006E006E006E006Enn006En	I
    //   135: iadd
    //   136: getstatic 107	uuuuuu/ttttst:b006Ennnn006En006En	I
    //   139: imul
    //   140: getstatic 103	uuuuuu/ttttst:b006E006E006E006E006Enn006En	I
    //   143: irem
    //   144: getstatic 105	uuuuuu/ttttst:bnnnnn006En006En	I
    //   147: if_icmpeq +13 -> 160
    //   150: bipush 33
    //   152: putstatic 107	uuuuuu/ttttst:b006Ennnn006En006En	I
    //   155: bipush 89
    //   157: putstatic 105	uuuuuu/ttttst:bnnnnn006En006En	I
    //   160: iconst_0
    //   161: putstatic 107	uuuuuu/ttttst:b006Ennnn006En006En	I
    //   164: ldc 2
    //   166: ldc 109
    //   168: sipush 194
    //   171: iconst_4
    //   172: invokestatic 74	xxxxxx/uxxxxx:bb00620062bb0062b0062b0062	(Ljava/lang/String;CC)Ljava/lang/String;
    //   175: iconst_0
    //   176: anewarray 76	java/lang/Class
    //   179: invokevirtual 80	java/lang/Class:getMethod	(Ljava/lang/String;[Ljava/lang/Class;)Ljava/lang/reflect/Method;
    //   182: astore 29
    //   184: iconst_0
    //   185: anewarray 82	java/lang/Object
    //   188: astore 30
    //   190: aload 29
    //   192: aconst_null
    //   193: aload 30
    //   195: invokevirtual 88	java/lang/reflect/Method:invoke	(Ljava/lang/Object;[Ljava/lang/Object;)Ljava/lang/Object;
    //   198: astore 32
    //   200: aload 32
    //   202: checkcast 90	java/lang/Integer
    //   205: invokevirtual 93	java/lang/Integer:intValue	()I
    //   208: putstatic 105	uuuuuu/ttttst:bnnnnn006En006En	I
    //   211: ldc 2
    //   213: ldc 111
    //   215: bipush 33
    //   217: iconst_4
    //   218: invokestatic 74	xxxxxx/uxxxxx:bb00620062bb0062b0062b0062	(Ljava/lang/String;CC)Ljava/lang/String;
    //   221: iconst_0
    //   222: anewarray 76	java/lang/Class
    //   225: invokevirtual 80	java/lang/Class:getMethod	(Ljava/lang/String;[Ljava/lang/Class;)Ljava/lang/reflect/Method;
    //   228: astore 33
    //   230: iconst_0
    //   231: anewarray 82	java/lang/Object
    //   234: astore 34
    //   236: aload 33
    //   238: aconst_null
    //   239: aload 34
    //   241: invokevirtual 88	java/lang/reflect/Method:invoke	(Ljava/lang/Object;[Ljava/lang/Object;)Ljava/lang/Object;
    //   244: astore 36
    //   246: aload 36
    //   248: checkcast 90	java/lang/Integer
    //   251: invokevirtual 93	java/lang/Integer:intValue	()I
    //   254: getstatic 95	uuuuuu/ttttst:bn006E006E006E006Enn006En	I
    //   257: iadd
    //   258: istore 37
    //   260: ldc 2
    //   262: ldc 113
    //   264: sipush 206
    //   267: bipush 59
    //   269: iconst_2
    //   270: invokestatic 101	xxxxxx/uxxxxx:bbbb0062b0062b0062b0062	(Ljava/lang/String;CCC)Ljava/lang/String;
    //   273: iconst_0
    //   274: anewarray 76	java/lang/Class
    //   277: invokevirtual 80	java/lang/Class:getMethod	(Ljava/lang/String;[Ljava/lang/Class;)Ljava/lang/reflect/Method;
    //   280: astore 38
    //   282: iconst_0
    //   283: anewarray 82	java/lang/Object
    //   286: astore 39
    //   288: aload 38
    //   290: aconst_null
    //   291: aload 39
    //   293: invokevirtual 88	java/lang/reflect/Method:invoke	(Ljava/lang/Object;[Ljava/lang/Object;)Ljava/lang/Object;
    //   296: astore 41
    //   298: iload 37
    //   300: aload 41
    //   302: checkcast 90	java/lang/Integer
    //   305: invokevirtual 93	java/lang/Integer:intValue	()I
    //   308: imul
    //   309: getstatic 103	uuuuuu/ttttst:b006E006E006E006E006Enn006En	I
    //   312: irem
    //   313: getstatic 105	uuuuuu/ttttst:bnnnnn006En006En	I
    //   316: if_icmpeq +100 -> 416
    //   319: ldc 2
    //   321: ldc 115
    //   323: sipush 180
    //   326: iconst_2
    //   327: iconst_0
    //   328: invokestatic 101	xxxxxx/uxxxxx:bbbb0062b0062b0062b0062	(Ljava/lang/String;CCC)Ljava/lang/String;
    //   331: iconst_0
    //   332: anewarray 76	java/lang/Class
    //   335: invokevirtual 80	java/lang/Class:getMethod	(Ljava/lang/String;[Ljava/lang/Class;)Ljava/lang/reflect/Method;
    //   338: astore 42
    //   340: iconst_0
    //   341: anewarray 82	java/lang/Object
    //   344: astore 43
    //   346: aload 42
    //   348: aconst_null
    //   349: aload 43
    //   351: invokevirtual 88	java/lang/reflect/Method:invoke	(Ljava/lang/Object;[Ljava/lang/Object;)Ljava/lang/Object;
    //   354: astore 45
    //   356: aload 45
    //   358: checkcast 90	java/lang/Integer
    //   361: invokevirtual 93	java/lang/Integer:intValue	()I
    //   364: putstatic 107	uuuuuu/ttttst:b006Ennnn006En006En	I
    //   367: ldc 2
    //   369: ldc 117
    //   371: sipush 156
    //   374: bipush 121
    //   376: iconst_1
    //   377: invokestatic 101	xxxxxx/uxxxxx:bbbb0062b0062b0062b0062	(Ljava/lang/String;CCC)Ljava/lang/String;
    //   380: iconst_0
    //   381: anewarray 76	java/lang/Class
    //   384: invokevirtual 80	java/lang/Class:getMethod	(Ljava/lang/String;[Ljava/lang/Class;)Ljava/lang/reflect/Method;
    //   387: astore 46
    //   389: iconst_0
    //   390: anewarray 82	java/lang/Object
    //   393: astore 47
    //   395: aload 46
    //   397: aconst_null
    //   398: aload 47
    //   400: invokevirtual 88	java/lang/reflect/Method:invoke	(Ljava/lang/Object;[Ljava/lang/Object;)Ljava/lang/Object;
    //   403: astore 49
    //   405: aload 49
    //   407: checkcast 90	java/lang/Integer
    //   410: invokevirtual 93	java/lang/Integer:intValue	()I
    //   413: putstatic 105	uuuuuu/ttttst:bnnnnn006En006En	I
    //   416: aload_1
    //   417: invokevirtual 120	com/db/pwcc/dbmobile/model/profile/Profile:getFkn	()Ljava/lang/String;
    //   420: astore 14
    //   422: ldc 2
    //   424: ldc 122
    //   426: bipush 71
    //   428: bipush 108
    //   430: iconst_3
    //   431: invokestatic 101	xxxxxx/uxxxxx:bbbb0062b0062b0062b0062	(Ljava/lang/String;CCC)Ljava/lang/String;
    //   434: iconst_1
    //   435: anewarray 76	java/lang/Class
    //   438: dup
    //   439: iconst_0
    //   440: ldc 124
    //   442: aastore
    //   443: invokevirtual 80	java/lang/Class:getMethod	(Ljava/lang/String;[Ljava/lang/Class;)Ljava/lang/reflect/Method;
    //   446: astore 15
    //   448: iconst_1
    //   449: anewarray 82	java/lang/Object
    //   452: dup
    //   453: iconst_0
    //   454: aload 14
    //   456: aastore
    //   457: astore 16
    //   459: aload 15
    //   461: aload_0
    //   462: aload 16
    //   464: invokevirtual 88	java/lang/reflect/Method:invoke	(Ljava/lang/Object;[Ljava/lang/Object;)Ljava/lang/Object;
    //   467: astore 18
    //   469: aload 18
    //   471: checkcast 124	java/lang/String
    //   474: astore 19
    //   476: ldc 2
    //   478: ldc 126
    //   480: bipush 111
    //   482: iconst_0
    //   483: invokestatic 74	xxxxxx/uxxxxx:bb00620062bb0062b0062b0062	(Ljava/lang/String;CC)Ljava/lang/String;
    //   486: iconst_0
    //   487: anewarray 76	java/lang/Class
    //   490: invokevirtual 80	java/lang/Class:getMethod	(Ljava/lang/String;[Ljava/lang/Class;)Ljava/lang/reflect/Method;
    //   493: astore 20
    //   495: iconst_0
    //   496: anewarray 82	java/lang/Object
    //   499: astore 21
    //   501: aload 20
    //   503: aconst_null
    //   504: aload 21
    //   506: invokevirtual 88	java/lang/reflect/Method:invoke	(Ljava/lang/Object;[Ljava/lang/Object;)Ljava/lang/Object;
    //   509: astore 23
    //   511: aload 23
    //   513: checkcast 90	java/lang/Integer
    //   516: invokevirtual 93	java/lang/Integer:intValue	()I
    //   519: istore 24
    //   521: iload 24
    //   523: iload 24
    //   525: getstatic 95	uuuuuu/ttttst:bn006E006E006E006Enn006En	I
    //   528: iadd
    //   529: imul
    //   530: getstatic 103	uuuuuu/ttttst:b006E006E006E006E006Enn006En	I
    //   533: irem
    //   534: tableswitch	default:+18->552, 0:+72->606
    //   552: bipush 38
    //   554: putstatic 107	uuuuuu/ttttst:b006Ennnn006En006En	I
    //   557: ldc 2
    //   559: ldc -128
    //   561: sipush 242
    //   564: bipush 119
    //   566: iconst_2
    //   567: invokestatic 101	xxxxxx/uxxxxx:bbbb0062b0062b0062b0062	(Ljava/lang/String;CCC)Ljava/lang/String;
    //   570: iconst_0
    //   571: anewarray 76	java/lang/Class
    //   574: invokevirtual 80	java/lang/Class:getMethod	(Ljava/lang/String;[Ljava/lang/Class;)Ljava/lang/reflect/Method;
    //   577: astore 25
    //   579: iconst_0
    //   580: anewarray 82	java/lang/Object
    //   583: astore 26
    //   585: aload 25
    //   587: aconst_null
    //   588: aload 26
    //   590: invokevirtual 88	java/lang/reflect/Method:invoke	(Ljava/lang/Object;[Ljava/lang/Object;)Ljava/lang/Object;
    //   593: astore 28
    //   595: aload 28
    //   597: checkcast 90	java/lang/Integer
    //   600: invokevirtual 93	java/lang/Integer:intValue	()I
    //   603: putstatic 105	uuuuuu/ttttst:bnnnnn006En006En	I
    //   606: aload_2
    //   607: aload_3
    //   608: aload 4
    //   610: aload 19
    //   612: getstatic 133	com/db/pwcc/dbmobile/foundation/R$string:menu_item_logout	I
    //   615: invokeinterface 137 5 0
    //   620: return
    //   621: astore 31
    //   623: aload 31
    //   625: invokevirtual 141	java/lang/reflect/InvocationTargetException:getCause	()Ljava/lang/Throwable;
    //   628: athrow
    //   629: astore 35
    //   631: aload 35
    //   633: invokevirtual 141	java/lang/reflect/InvocationTargetException:getCause	()Ljava/lang/Throwable;
    //   636: athrow
    //   637: astore 40
    //   639: aload 40
    //   641: invokevirtual 141	java/lang/reflect/InvocationTargetException:getCause	()Ljava/lang/Throwable;
    //   644: athrow
    //   645: astore 17
    //   647: aload 17
    //   649: invokevirtual 141	java/lang/reflect/InvocationTargetException:getCause	()Ljava/lang/Throwable;
    //   652: athrow
    //   653: astore 27
    //   655: aload 27
    //   657: invokevirtual 141	java/lang/reflect/InvocationTargetException:getCause	()Ljava/lang/Throwable;
    //   660: athrow
    //   661: astore 22
    //   663: aload 22
    //   665: invokevirtual 141	java/lang/reflect/InvocationTargetException:getCause	()Ljava/lang/Throwable;
    //   668: athrow
    //   669: astore 7
    //   671: aload 7
    //   673: invokevirtual 141	java/lang/reflect/InvocationTargetException:getCause	()Ljava/lang/Throwable;
    //   676: athrow
    //   677: astore 12
    //   679: aload 12
    //   681: invokevirtual 141	java/lang/reflect/InvocationTargetException:getCause	()Ljava/lang/Throwable;
    //   684: athrow
    //   685: astore 44
    //   687: aload 44
    //   689: invokevirtual 141	java/lang/reflect/InvocationTargetException:getCause	()Ljava/lang/Throwable;
    //   692: athrow
    //   693: astore 48
    //   695: aload 48
    //   697: invokevirtual 141	java/lang/reflect/InvocationTargetException:getCause	()Ljava/lang/Throwable;
    //   700: athrow
    // Local variable table:
    //   start	length	slot	name	signature
    //   0	701	0	this	ttttst
    //   0	701	1	paramProfile	com.db.pwcc.dbmobile.model.profile.Profile
    //   7	600	2	localSssstt	stsstt.sssstt
    //   15	593	3	str1	String
    //   20	589	4	str2	String
    //   39	9	5	localMethod1	Method
    //   45	6	6	arrayOfObject1	Object[]
    //   669	3	7	localInvocationTargetException1	InvocationTargetException
    //   55	3	8	localObject1	Object
    //   69	50	9	i	int
    //   90	9	10	localMethod2	Method
    //   96	6	11	arrayOfObject2	Object[]
    //   677	3	12	localInvocationTargetException2	InvocationTargetException
    //   106	5	13	localObject2	Object
    //   420	35	14	str3	String
    //   446	14	15	localMethod3	Method
    //   457	6	16	arrayOfObject3	Object[]
    //   645	3	17	localInvocationTargetException3	InvocationTargetException
    //   467	3	18	localObject3	Object
    //   474	137	19	str4	String
    //   493	9	20	localMethod4	Method
    //   499	6	21	arrayOfObject4	Object[]
    //   661	3	22	localInvocationTargetException4	InvocationTargetException
    //   509	3	23	localObject4	Object
    //   519	11	24	j	int
    //   577	9	25	localMethod5	Method
    //   583	6	26	arrayOfObject5	Object[]
    //   653	3	27	localInvocationTargetException5	InvocationTargetException
    //   593	3	28	localObject5	Object
    //   182	9	29	localMethod6	Method
    //   188	6	30	arrayOfObject6	Object[]
    //   621	3	31	localInvocationTargetException6	InvocationTargetException
    //   198	3	32	localObject6	Object
    //   228	9	33	localMethod7	Method
    //   234	6	34	arrayOfObject7	Object[]
    //   629	3	35	localInvocationTargetException7	InvocationTargetException
    //   244	3	36	localObject7	Object
    //   258	51	37	k	int
    //   280	9	38	localMethod8	Method
    //   286	6	39	arrayOfObject8	Object[]
    //   637	3	40	localInvocationTargetException8	InvocationTargetException
    //   296	5	41	localObject8	Object
    //   338	9	42	localMethod9	Method
    //   344	6	43	arrayOfObject9	Object[]
    //   685	3	44	localInvocationTargetException9	InvocationTargetException
    //   354	3	45	localObject9	Object
    //   387	9	46	localMethod10	Method
    //   393	6	47	arrayOfObject10	Object[]
    //   693	3	48	localInvocationTargetException10	InvocationTargetException
    //   403	3	49	localObject10	Object
    // Exception table:
    //   from	to	target	type
    //   190	200	621	java/lang/reflect/InvocationTargetException
    //   236	246	629	java/lang/reflect/InvocationTargetException
    //   288	298	637	java/lang/reflect/InvocationTargetException
    //   459	469	645	java/lang/reflect/InvocationTargetException
    //   585	595	653	java/lang/reflect/InvocationTargetException
    //   501	511	661	java/lang/reflect/InvocationTargetException
    //   47	57	669	java/lang/reflect/InvocationTargetException
    //   98	108	677	java/lang/reflect/InvocationTargetException
    //   346	356	685	java/lang/reflect/InvocationTargetException
    //   395	405	693	java/lang/reflect/InvocationTargetException
  }
  
  /* Error */
  public void b006B006B006B006B006B006B006B006Bkk(stsstt.sssstt paramSssstt)
  {
    // Byte code:
    //   0: aload_0
    //   1: aload_1
    //   2: invokespecial 147	uuuuuu/sttsst:b006Bkk006Bkkkk006Bk	(Luuuuuu/tsstst$tttsst;)V
    //   5: invokestatic 153	uuuuuu/pqqppq:b006B006B006Bkkk006Bkkk	()Luuuuuu/pppqpq;
    //   8: aload_0
    //   9: invokeinterface 159 2 0
    //   14: aload_0
    //   15: getfield 163	uuuuuu/ttttst:b006E006En006Enn006E006En	Lcom/db/pwcc/dbmobile/secure/preferences/SharedPreferencesHelper;
    //   18: astore_2
    //   19: ldc -91
    //   21: ldc -89
    //   23: sipush 189
    //   26: iconst_0
    //   27: invokestatic 74	xxxxxx/uxxxxx:bb00620062bb0062b0062b0062	(Ljava/lang/String;CC)Ljava/lang/String;
    //   30: iconst_0
    //   31: anewarray 76	java/lang/Class
    //   34: invokevirtual 80	java/lang/Class:getMethod	(Ljava/lang/String;[Ljava/lang/Class;)Ljava/lang/reflect/Method;
    //   37: astore_3
    //   38: iconst_0
    //   39: anewarray 82	java/lang/Object
    //   42: astore 4
    //   44: aload_3
    //   45: aload_2
    //   46: aload 4
    //   48: invokevirtual 88	java/lang/reflect/Method:invoke	(Ljava/lang/Object;[Ljava/lang/Object;)Ljava/lang/Object;
    //   51: astore 6
    //   53: aload_1
    //   54: aload 6
    //   56: checkcast 124	java/lang/String
    //   59: invokeinterface 171 2 0
    //   64: ldc 2
    //   66: ldc -83
    //   68: sipush 169
    //   71: iconst_4
    //   72: invokestatic 74	xxxxxx/uxxxxx:bb00620062bb0062b0062b0062	(Ljava/lang/String;CC)Ljava/lang/String;
    //   75: iconst_0
    //   76: anewarray 76	java/lang/Class
    //   79: invokevirtual 80	java/lang/Class:getMethod	(Ljava/lang/String;[Ljava/lang/Class;)Ljava/lang/reflect/Method;
    //   82: astore 7
    //   84: iconst_0
    //   85: anewarray 82	java/lang/Object
    //   88: astore 8
    //   90: aload 7
    //   92: aload_0
    //   93: aload 8
    //   95: invokevirtual 88	java/lang/reflect/Method:invoke	(Ljava/lang/Object;[Ljava/lang/Object;)Ljava/lang/Object;
    //   98: pop
    //   99: getstatic 107	uuuuuu/ttttst:b006Ennnn006En006En	I
    //   102: istore 11
    //   104: iload 11
    //   106: iload 11
    //   108: getstatic 95	uuuuuu/ttttst:bn006E006E006E006Enn006En	I
    //   111: iadd
    //   112: imul
    //   113: getstatic 103	uuuuuu/ttttst:b006E006E006E006E006Enn006En	I
    //   116: irem
    //   117: tableswitch	default:+19->136, 0:+72->189
    //   136: ldc 2
    //   138: ldc -81
    //   140: bipush 103
    //   142: bipush 117
    //   144: iconst_1
    //   145: invokestatic 101	xxxxxx/uxxxxx:bbbb0062b0062b0062b0062	(Ljava/lang/String;CCC)Ljava/lang/String;
    //   148: iconst_0
    //   149: anewarray 76	java/lang/Class
    //   152: invokevirtual 80	java/lang/Class:getMethod	(Ljava/lang/String;[Ljava/lang/Class;)Ljava/lang/reflect/Method;
    //   155: astore 43
    //   157: iconst_0
    //   158: anewarray 82	java/lang/Object
    //   161: astore 44
    //   163: aload 43
    //   165: aconst_null
    //   166: aload 44
    //   168: invokevirtual 88	java/lang/reflect/Method:invoke	(Ljava/lang/Object;[Ljava/lang/Object;)Ljava/lang/Object;
    //   171: astore 46
    //   173: aload 46
    //   175: checkcast 90	java/lang/Integer
    //   178: invokevirtual 93	java/lang/Integer:intValue	()I
    //   181: putstatic 107	uuuuuu/ttttst:b006Ennnn006En006En	I
    //   184: bipush 39
    //   186: putstatic 105	uuuuuu/ttttst:bnnnnn006En006En	I
    //   189: ldc 2
    //   191: ldc -79
    //   193: iconst_1
    //   194: iconst_1
    //   195: invokestatic 74	xxxxxx/uxxxxx:bb00620062bb0062b0062b0062	(Ljava/lang/String;CC)Ljava/lang/String;
    //   198: iconst_0
    //   199: anewarray 76	java/lang/Class
    //   202: invokevirtual 80	java/lang/Class:getMethod	(Ljava/lang/String;[Ljava/lang/Class;)Ljava/lang/reflect/Method;
    //   205: astore 12
    //   207: iconst_0
    //   208: anewarray 82	java/lang/Object
    //   211: astore 13
    //   213: aload 12
    //   215: aload_0
    //   216: aload 13
    //   218: invokevirtual 88	java/lang/reflect/Method:invoke	(Ljava/lang/Object;[Ljava/lang/Object;)Ljava/lang/Object;
    //   221: astore 15
    //   223: aload 15
    //   225: checkcast 179	java/lang/Boolean
    //   228: invokevirtual 183	java/lang/Boolean:booleanValue	()Z
    //   231: ifeq +333 -> 564
    //   234: ldc 2
    //   236: ldc -71
    //   238: sipush 224
    //   241: bipush 79
    //   243: iconst_1
    //   244: invokestatic 101	xxxxxx/uxxxxx:bbbb0062b0062b0062b0062	(Ljava/lang/String;CCC)Ljava/lang/String;
    //   247: iconst_0
    //   248: anewarray 76	java/lang/Class
    //   251: invokevirtual 80	java/lang/Class:getMethod	(Ljava/lang/String;[Ljava/lang/Class;)Ljava/lang/reflect/Method;
    //   254: astore 29
    //   256: iconst_0
    //   257: anewarray 82	java/lang/Object
    //   260: astore 30
    //   262: aload 29
    //   264: aload_0
    //   265: aload 30
    //   267: invokevirtual 88	java/lang/reflect/Method:invoke	(Ljava/lang/Object;[Ljava/lang/Object;)Ljava/lang/Object;
    //   270: pop
    //   271: ldc 2
    //   273: ldc -69
    //   275: bipush 14
    //   277: iconst_4
    //   278: invokestatic 74	xxxxxx/uxxxxx:bb00620062bb0062b0062b0062	(Ljava/lang/String;CC)Ljava/lang/String;
    //   281: iconst_0
    //   282: anewarray 76	java/lang/Class
    //   285: invokevirtual 80	java/lang/Class:getMethod	(Ljava/lang/String;[Ljava/lang/Class;)Ljava/lang/reflect/Method;
    //   288: astore 33
    //   290: iconst_0
    //   291: anewarray 82	java/lang/Object
    //   294: astore 34
    //   296: aload 33
    //   298: aload_0
    //   299: aload 34
    //   301: invokevirtual 88	java/lang/reflect/Method:invoke	(Ljava/lang/Object;[Ljava/lang/Object;)Ljava/lang/Object;
    //   304: pop
    //   305: getstatic 107	uuuuuu/ttttst:b006Ennnn006En006En	I
    //   308: istore 37
    //   310: iload 37
    //   312: iload 37
    //   314: getstatic 95	uuuuuu/ttttst:bn006E006E006E006Enn006En	I
    //   317: iadd
    //   318: imul
    //   319: getstatic 103	uuuuuu/ttttst:b006E006E006E006E006Enn006En	I
    //   322: irem
    //   323: tableswitch	default:+17->340, 0:+70->393
    //   340: bipush 91
    //   342: putstatic 107	uuuuuu/ttttst:b006Ennnn006En006En	I
    //   345: ldc 2
    //   347: ldc -67
    //   349: bipush 40
    //   351: bipush 17
    //   353: iconst_2
    //   354: invokestatic 101	xxxxxx/uxxxxx:bbbb0062b0062b0062b0062	(Ljava/lang/String;CCC)Ljava/lang/String;
    //   357: iconst_0
    //   358: anewarray 76	java/lang/Class
    //   361: invokevirtual 80	java/lang/Class:getMethod	(Ljava/lang/String;[Ljava/lang/Class;)Ljava/lang/reflect/Method;
    //   364: astore 39
    //   366: iconst_0
    //   367: anewarray 82	java/lang/Object
    //   370: astore 40
    //   372: aload 39
    //   374: aconst_null
    //   375: aload 40
    //   377: invokevirtual 88	java/lang/reflect/Method:invoke	(Ljava/lang/Object;[Ljava/lang/Object;)Ljava/lang/Object;
    //   380: astore 42
    //   382: aload 42
    //   384: checkcast 90	java/lang/Integer
    //   387: invokevirtual 93	java/lang/Integer:intValue	()I
    //   390: putstatic 105	uuuuuu/ttttst:bnnnnn006En006En	I
    //   393: aload_1
    //   394: iconst_1
    //   395: invokeinterface 193 2 0
    //   400: aload_0
    //   401: invokevirtual 196	uuuuuu/ttttst:b006Bk006B006Bkk006Bk006Bk	()Z
    //   404: ifeq +141 -> 545
    //   407: getstatic 107	uuuuuu/ttttst:b006Ennnn006En006En	I
    //   410: istore 38
    //   412: iload 38
    //   414: iload 38
    //   416: getstatic 95	uuuuuu/ttttst:bn006E006E006E006Enn006En	I
    //   419: iadd
    //   420: imul
    //   421: getstatic 103	uuuuuu/ttttst:b006E006E006E006E006Enn006En	I
    //   424: irem
    //   425: tableswitch	default:+19->444, 0:+29->454
    //   444: bipush 63
    //   446: putstatic 107	uuuuuu/ttttst:b006Ennnn006En006En	I
    //   449: bipush 97
    //   451: putstatic 105	uuuuuu/ttttst:bnnnnn006En006En	I
    //   454: aload_1
    //   455: getstatic 199	com/db/pwcc/dbmobile/foundation/R$string:navigation_header_demo_initials	I
    //   458: getstatic 202	com/db/pwcc/dbmobile/foundation/R$string:navigation_header_demo_name	I
    //   461: getstatic 205	com/db/pwcc/dbmobile/foundation/R$string:navigation_header_demo_fkn	I
    //   464: getstatic 208	com/db/pwcc/dbmobile/foundation/R$string:menu_item_exit_demo	I
    //   467: invokeinterface 211 5 0
    //   472: ldc 2
    //   474: ldc -43
    //   476: sipush 232
    //   479: iconst_4
    //   480: iconst_3
    //   481: invokestatic 101	xxxxxx/uxxxxx:bbbb0062b0062b0062b0062	(Ljava/lang/String;CCC)Ljava/lang/String;
    //   484: iconst_0
    //   485: anewarray 76	java/lang/Class
    //   488: invokevirtual 80	java/lang/Class:getMethod	(Ljava/lang/String;[Ljava/lang/Class;)Ljava/lang/reflect/Method;
    //   491: astore 16
    //   493: iconst_0
    //   494: anewarray 82	java/lang/Object
    //   497: astore 17
    //   499: aload 16
    //   501: aload_0
    //   502: aload 17
    //   504: invokevirtual 88	java/lang/reflect/Method:invoke	(Ljava/lang/Object;[Ljava/lang/Object;)Ljava/lang/Object;
    //   507: astore 19
    //   509: aload 19
    //   511: checkcast 179	java/lang/Boolean
    //   514: invokevirtual 183	java/lang/Boolean:booleanValue	()Z
    //   517: ifeq +22 -> 539
    //   520: aload_0
    //   521: invokevirtual 196	uuuuuu/ttttst:b006Bk006B006Bkk006Bk006Bk	()Z
    //   524: ifne +15 -> 539
    //   527: iconst_1
    //   528: istore 20
    //   530: aload_1
    //   531: iload 20
    //   533: invokeinterface 216 2 0
    //   538: return
    //   539: iconst_0
    //   540: istore 20
    //   542: goto -12 -> 530
    //   545: aload_0
    //   546: getfield 35	uuuuuu/ttttst:b006En006E006E006Enn006En	Luuuuuu/mffffm;
    //   549: aload_0
    //   550: invokevirtual 220	uuuuuu/mffffm:bpp0070pp0070p00700070p	(Luuuuuu/vvpvvp$ppvvvp;)V
    //   553: goto -81 -> 472
    //   556: astore 18
    //   558: aload 18
    //   560: invokevirtual 141	java/lang/reflect/InvocationTargetException:getCause	()Ljava/lang/Throwable;
    //   563: athrow
    //   564: getstatic 107	uuuuuu/ttttst:b006Ennnn006En006En	I
    //   567: getstatic 95	uuuuuu/ttttst:bn006E006E006E006Enn006En	I
    //   570: iadd
    //   571: getstatic 107	uuuuuu/ttttst:b006Ennnn006En006En	I
    //   574: imul
    //   575: getstatic 103	uuuuuu/ttttst:b006E006E006E006E006Enn006En	I
    //   578: irem
    //   579: getstatic 105	uuuuuu/ttttst:bnnnnn006En006En	I
    //   582: if_icmpeq +97 -> 679
    //   585: ldc 2
    //   587: ldc -34
    //   589: bipush 77
    //   591: iconst_2
    //   592: invokestatic 74	xxxxxx/uxxxxx:bb00620062bb0062b0062b0062	(Ljava/lang/String;CC)Ljava/lang/String;
    //   595: iconst_0
    //   596: anewarray 76	java/lang/Class
    //   599: invokevirtual 80	java/lang/Class:getMethod	(Ljava/lang/String;[Ljava/lang/Class;)Ljava/lang/reflect/Method;
    //   602: astore 21
    //   604: iconst_0
    //   605: anewarray 82	java/lang/Object
    //   608: astore 22
    //   610: aload 21
    //   612: aconst_null
    //   613: aload 22
    //   615: invokevirtual 88	java/lang/reflect/Method:invoke	(Ljava/lang/Object;[Ljava/lang/Object;)Ljava/lang/Object;
    //   618: astore 24
    //   620: aload 24
    //   622: checkcast 90	java/lang/Integer
    //   625: invokevirtual 93	java/lang/Integer:intValue	()I
    //   628: putstatic 107	uuuuuu/ttttst:b006Ennnn006En006En	I
    //   631: ldc 2
    //   633: ldc -32
    //   635: bipush 53
    //   637: bipush 63
    //   639: iconst_1
    //   640: invokestatic 101	xxxxxx/uxxxxx:bbbb0062b0062b0062b0062	(Ljava/lang/String;CCC)Ljava/lang/String;
    //   643: iconst_0
    //   644: anewarray 76	java/lang/Class
    //   647: invokevirtual 80	java/lang/Class:getMethod	(Ljava/lang/String;[Ljava/lang/Class;)Ljava/lang/reflect/Method;
    //   650: astore 25
    //   652: iconst_0
    //   653: anewarray 82	java/lang/Object
    //   656: astore 26
    //   658: aload 25
    //   660: aconst_null
    //   661: aload 26
    //   663: invokevirtual 88	java/lang/reflect/Method:invoke	(Ljava/lang/Object;[Ljava/lang/Object;)Ljava/lang/Object;
    //   666: astore 28
    //   668: aload 28
    //   670: checkcast 90	java/lang/Integer
    //   673: invokevirtual 93	java/lang/Integer:intValue	()I
    //   676: putstatic 105	uuuuuu/ttttst:bnnnnn006En006En	I
    //   679: aload_1
    //   680: iconst_0
    //   681: invokeinterface 193 2 0
    //   686: goto -214 -> 472
    //   689: astore 14
    //   691: aload 14
    //   693: invokevirtual 141	java/lang/reflect/InvocationTargetException:getCause	()Ljava/lang/Throwable;
    //   696: athrow
    //   697: astore 5
    //   699: aload 5
    //   701: invokevirtual 141	java/lang/reflect/InvocationTargetException:getCause	()Ljava/lang/Throwable;
    //   704: athrow
    //   705: astore 9
    //   707: aload 9
    //   709: invokevirtual 141	java/lang/reflect/InvocationTargetException:getCause	()Ljava/lang/Throwable;
    //   712: athrow
    //   713: astore 31
    //   715: aload 31
    //   717: invokevirtual 141	java/lang/reflect/InvocationTargetException:getCause	()Ljava/lang/Throwable;
    //   720: athrow
    //   721: astore 35
    //   723: aload 35
    //   725: invokevirtual 141	java/lang/reflect/InvocationTargetException:getCause	()Ljava/lang/Throwable;
    //   728: athrow
    //   729: astore 45
    //   731: aload 45
    //   733: invokevirtual 141	java/lang/reflect/InvocationTargetException:getCause	()Ljava/lang/Throwable;
    //   736: athrow
    //   737: astore 41
    //   739: aload 41
    //   741: invokevirtual 141	java/lang/reflect/InvocationTargetException:getCause	()Ljava/lang/Throwable;
    //   744: athrow
    //   745: astore 23
    //   747: aload 23
    //   749: invokevirtual 141	java/lang/reflect/InvocationTargetException:getCause	()Ljava/lang/Throwable;
    //   752: athrow
    //   753: astore 27
    //   755: aload 27
    //   757: invokevirtual 141	java/lang/reflect/InvocationTargetException:getCause	()Ljava/lang/Throwable;
    //   760: athrow
    // Local variable table:
    //   start	length	slot	name	signature
    //   0	761	0	this	ttttst
    //   0	761	1	paramSssstt	stsstt.sssstt
    //   18	28	2	localSharedPreferencesHelper	SharedPreferencesHelper
    //   37	8	3	localMethod1	Method
    //   42	5	4	arrayOfObject1	Object[]
    //   697	3	5	localInvocationTargetException1	InvocationTargetException
    //   51	4	6	localObject1	Object
    //   82	9	7	localMethod2	Method
    //   88	6	8	arrayOfObject2	Object[]
    //   705	3	9	localInvocationTargetException2	InvocationTargetException
    //   102	11	11	i	int
    //   205	9	12	localMethod3	Method
    //   211	6	13	arrayOfObject3	Object[]
    //   689	3	14	localInvocationTargetException3	InvocationTargetException
    //   221	3	15	localObject2	Object
    //   491	9	16	localMethod4	Method
    //   497	6	17	arrayOfObject4	Object[]
    //   556	3	18	localInvocationTargetException4	InvocationTargetException
    //   507	3	19	localObject3	Object
    //   528	13	20	bool	boolean
    //   602	9	21	localMethod5	Method
    //   608	6	22	arrayOfObject5	Object[]
    //   745	3	23	localInvocationTargetException5	InvocationTargetException
    //   618	3	24	localObject4	Object
    //   650	9	25	localMethod6	Method
    //   656	6	26	arrayOfObject6	Object[]
    //   753	3	27	localInvocationTargetException6	InvocationTargetException
    //   666	3	28	localObject5	Object
    //   254	9	29	localMethod7	Method
    //   260	6	30	arrayOfObject7	Object[]
    //   713	3	31	localInvocationTargetException7	InvocationTargetException
    //   288	9	33	localMethod8	Method
    //   294	6	34	arrayOfObject8	Object[]
    //   721	3	35	localInvocationTargetException8	InvocationTargetException
    //   308	11	37	j	int
    //   410	11	38	k	int
    //   364	9	39	localMethod9	Method
    //   370	6	40	arrayOfObject9	Object[]
    //   737	3	41	localInvocationTargetException9	InvocationTargetException
    //   380	3	42	localObject6	Object
    //   155	9	43	localMethod10	Method
    //   161	6	44	arrayOfObject10	Object[]
    //   729	3	45	localInvocationTargetException10	InvocationTargetException
    //   171	3	46	localObject7	Object
    // Exception table:
    //   from	to	target	type
    //   499	509	556	java/lang/reflect/InvocationTargetException
    //   213	223	689	java/lang/reflect/InvocationTargetException
    //   44	53	697	java/lang/reflect/InvocationTargetException
    //   90	99	705	java/lang/reflect/InvocationTargetException
    //   262	271	713	java/lang/reflect/InvocationTargetException
    //   296	305	721	java/lang/reflect/InvocationTargetException
    //   163	173	729	java/lang/reflect/InvocationTargetException
    //   372	382	737	java/lang/reflect/InvocationTargetException
    //   610	620	745	java/lang/reflect/InvocationTargetException
    //   658	668	753	java/lang/reflect/InvocationTargetException
  }
  
  /* Error */
  public void b006B006Bk006Bkkkk006Bk()
  {
    // Byte code:
    //   0: aload_0
    //   1: getfield 229	uuuuuu/ttttst:b006E006E006E006E006En006E006En	Luuuuuu/hyhyhh;
    //   4: ifnull +503 -> 507
    //   7: aload_0
    //   8: getfield 229	uuuuuu/ttttst:b006E006E006E006E006En006E006En	Luuuuuu/hyhyhh;
    //   11: invokevirtual 234	uuuuuu/hyhyhh:bp0070pppp0070007000700070	()Z
    //   14: ifeq +493 -> 507
    //   17: aload_0
    //   18: getfield 236	uuuuuu/ttttst:bnn006E006E006Enn006En	Luuuuuu/sssttt;
    //   21: getstatic 242	com/db/pwcc/dbmobile/foundation/features/Feature:CLICK4CREDIT	Lcom/db/pwcc/dbmobile/foundation/features/Feature;
    //   24: invokevirtual 248	uuuuuu/sssttt:bk006Bkkk006B006B006Bkk	(Lcom/db/pwcc/dbmobile/foundation/features/Feature;)Luuuuuu/sststt;
    //   27: getstatic 254	uuuuuu/sststt:b006En006En006Enn006En	Luuuuuu/sststt;
    //   30: if_acmpne +477 -> 507
    //   33: aload_0
    //   34: invokevirtual 196	uuuuuu/ttttst:b006Bk006B006Bkk006Bk006Bk	()Z
    //   37: ifne +470 -> 507
    //   40: getstatic 107	uuuuuu/ttttst:b006Ennnn006En006En	I
    //   43: istore_1
    //   44: ldc 2
    //   46: ldc_w 256
    //   49: bipush 9
    //   51: bipush 70
    //   53: iconst_2
    //   54: invokestatic 101	xxxxxx/uxxxxx:bbbb0062b0062b0062b0062	(Ljava/lang/String;CCC)Ljava/lang/String;
    //   57: iconst_0
    //   58: anewarray 76	java/lang/Class
    //   61: invokevirtual 80	java/lang/Class:getMethod	(Ljava/lang/String;[Ljava/lang/Class;)Ljava/lang/reflect/Method;
    //   64: astore_2
    //   65: iconst_0
    //   66: anewarray 82	java/lang/Object
    //   69: astore_3
    //   70: aload_2
    //   71: aconst_null
    //   72: aload_3
    //   73: invokevirtual 88	java/lang/reflect/Method:invoke	(Ljava/lang/Object;[Ljava/lang/Object;)Ljava/lang/Object;
    //   76: astore 5
    //   78: iload_1
    //   79: iload_1
    //   80: aload 5
    //   82: checkcast 90	java/lang/Integer
    //   85: invokevirtual 93	java/lang/Integer:intValue	()I
    //   88: iadd
    //   89: imul
    //   90: istore 6
    //   92: getstatic 103	uuuuuu/ttttst:b006E006E006E006E006Enn006En	I
    //   95: istore 7
    //   97: ldc 2
    //   99: ldc_w 258
    //   102: bipush 68
    //   104: sipush 242
    //   107: iconst_3
    //   108: invokestatic 101	xxxxxx/uxxxxx:bbbb0062b0062b0062b0062	(Ljava/lang/String;CCC)Ljava/lang/String;
    //   111: iconst_0
    //   112: anewarray 76	java/lang/Class
    //   115: invokevirtual 80	java/lang/Class:getMethod	(Ljava/lang/String;[Ljava/lang/Class;)Ljava/lang/reflect/Method;
    //   118: astore 8
    //   120: iconst_0
    //   121: anewarray 82	java/lang/Object
    //   124: astore 9
    //   126: aload 8
    //   128: aconst_null
    //   129: aload 9
    //   131: invokevirtual 88	java/lang/reflect/Method:invoke	(Ljava/lang/Object;[Ljava/lang/Object;)Ljava/lang/Object;
    //   134: astore 11
    //   136: aload 11
    //   138: checkcast 90	java/lang/Integer
    //   141: invokevirtual 93	java/lang/Integer:intValue	()I
    //   144: getstatic 95	uuuuuu/ttttst:bn006E006E006E006Enn006En	I
    //   147: iadd
    //   148: istore 12
    //   150: ldc 2
    //   152: ldc_w 260
    //   155: bipush 88
    //   157: bipush 91
    //   159: iconst_0
    //   160: invokestatic 101	xxxxxx/uxxxxx:bbbb0062b0062b0062b0062	(Ljava/lang/String;CCC)Ljava/lang/String;
    //   163: iconst_0
    //   164: anewarray 76	java/lang/Class
    //   167: invokevirtual 80	java/lang/Class:getMethod	(Ljava/lang/String;[Ljava/lang/Class;)Ljava/lang/reflect/Method;
    //   170: astore 13
    //   172: iconst_0
    //   173: anewarray 82	java/lang/Object
    //   176: astore 14
    //   178: aload 13
    //   180: aconst_null
    //   181: aload 14
    //   183: invokevirtual 88	java/lang/reflect/Method:invoke	(Ljava/lang/Object;[Ljava/lang/Object;)Ljava/lang/Object;
    //   186: astore 16
    //   188: iload 12
    //   190: aload 16
    //   192: checkcast 90	java/lang/Integer
    //   195: invokevirtual 93	java/lang/Integer:intValue	()I
    //   198: imul
    //   199: getstatic 103	uuuuuu/ttttst:b006E006E006E006E006Enn006En	I
    //   202: irem
    //   203: getstatic 105	uuuuuu/ttttst:bnnnnn006En006En	I
    //   206: if_icmpeq +58 -> 264
    //   209: bipush 35
    //   211: putstatic 107	uuuuuu/ttttst:b006Ennnn006En006En	I
    //   214: ldc 2
    //   216: ldc_w 262
    //   219: bipush 82
    //   221: sipush 193
    //   224: iconst_1
    //   225: invokestatic 101	xxxxxx/uxxxxx:bbbb0062b0062b0062b0062	(Ljava/lang/String;CCC)Ljava/lang/String;
    //   228: iconst_0
    //   229: anewarray 76	java/lang/Class
    //   232: invokevirtual 80	java/lang/Class:getMethod	(Ljava/lang/String;[Ljava/lang/Class;)Ljava/lang/reflect/Method;
    //   235: astore 30
    //   237: iconst_0
    //   238: anewarray 82	java/lang/Object
    //   241: astore 31
    //   243: aload 30
    //   245: aconst_null
    //   246: aload 31
    //   248: invokevirtual 88	java/lang/reflect/Method:invoke	(Ljava/lang/Object;[Ljava/lang/Object;)Ljava/lang/Object;
    //   251: astore 33
    //   253: aload 33
    //   255: checkcast 90	java/lang/Integer
    //   258: invokevirtual 93	java/lang/Integer:intValue	()I
    //   261: putstatic 105	uuuuuu/ttttst:bnnnnn006En006En	I
    //   264: iload 6
    //   266: iload 7
    //   268: irem
    //   269: tableswitch	default:+19->288, 0:+116->385
    //   288: ldc 2
    //   290: ldc_w 264
    //   293: sipush 133
    //   296: iconst_4
    //   297: invokestatic 74	xxxxxx/uxxxxx:bb00620062bb0062b0062b0062	(Ljava/lang/String;CC)Ljava/lang/String;
    //   300: iconst_0
    //   301: anewarray 76	java/lang/Class
    //   304: invokevirtual 80	java/lang/Class:getMethod	(Ljava/lang/String;[Ljava/lang/Class;)Ljava/lang/reflect/Method;
    //   307: astore 22
    //   309: iconst_0
    //   310: anewarray 82	java/lang/Object
    //   313: astore 23
    //   315: aload 22
    //   317: aconst_null
    //   318: aload 23
    //   320: invokevirtual 88	java/lang/reflect/Method:invoke	(Ljava/lang/Object;[Ljava/lang/Object;)Ljava/lang/Object;
    //   323: astore 25
    //   325: aload 25
    //   327: checkcast 90	java/lang/Integer
    //   330: invokevirtual 93	java/lang/Integer:intValue	()I
    //   333: putstatic 107	uuuuuu/ttttst:b006Ennnn006En006En	I
    //   336: ldc 2
    //   338: ldc_w 266
    //   341: bipush 74
    //   343: bipush 21
    //   345: iconst_1
    //   346: invokestatic 101	xxxxxx/uxxxxx:bbbb0062b0062b0062b0062	(Ljava/lang/String;CCC)Ljava/lang/String;
    //   349: iconst_0
    //   350: anewarray 76	java/lang/Class
    //   353: invokevirtual 80	java/lang/Class:getMethod	(Ljava/lang/String;[Ljava/lang/Class;)Ljava/lang/reflect/Method;
    //   356: astore 26
    //   358: iconst_0
    //   359: anewarray 82	java/lang/Object
    //   362: astore 27
    //   364: aload 26
    //   366: aconst_null
    //   367: aload 27
    //   369: invokevirtual 88	java/lang/reflect/Method:invoke	(Ljava/lang/Object;[Ljava/lang/Object;)Ljava/lang/Object;
    //   372: astore 29
    //   374: aload 29
    //   376: checkcast 90	java/lang/Integer
    //   379: invokevirtual 93	java/lang/Integer:intValue	()I
    //   382: putstatic 105	uuuuuu/ttttst:bnnnnn006En006En	I
    //   385: getstatic 107	uuuuuu/ttttst:b006Ennnn006En006En	I
    //   388: getstatic 95	uuuuuu/ttttst:bn006E006E006E006Enn006En	I
    //   391: iadd
    //   392: getstatic 107	uuuuuu/ttttst:b006Ennnn006En006En	I
    //   395: imul
    //   396: getstatic 103	uuuuuu/ttttst:b006E006E006E006E006Enn006En	I
    //   399: irem
    //   400: getstatic 105	uuuuuu/ttttst:bnnnnn006En006En	I
    //   403: if_icmpeq +92 -> 495
    //   406: bipush 67
    //   408: putstatic 107	uuuuuu/ttttst:b006Ennnn006En006En	I
    //   411: bipush 46
    //   413: putstatic 105	uuuuuu/ttttst:bnnnnn006En006En	I
    //   416: getstatic 107	uuuuuu/ttttst:b006Ennnn006En006En	I
    //   419: getstatic 95	uuuuuu/ttttst:bn006E006E006E006Enn006En	I
    //   422: iadd
    //   423: getstatic 107	uuuuuu/ttttst:b006Ennnn006En006En	I
    //   426: imul
    //   427: getstatic 103	uuuuuu/ttttst:b006E006E006E006E006Enn006En	I
    //   430: irem
    //   431: istore 17
    //   433: ldc 2
    //   435: ldc_w 268
    //   438: sipush 146
    //   441: bipush 121
    //   443: iconst_1
    //   444: invokestatic 101	xxxxxx/uxxxxx:bbbb0062b0062b0062b0062	(Ljava/lang/String;CCC)Ljava/lang/String;
    //   447: iconst_0
    //   448: anewarray 76	java/lang/Class
    //   451: invokevirtual 80	java/lang/Class:getMethod	(Ljava/lang/String;[Ljava/lang/Class;)Ljava/lang/reflect/Method;
    //   454: astore 18
    //   456: iconst_0
    //   457: anewarray 82	java/lang/Object
    //   460: astore 19
    //   462: aload 18
    //   464: aconst_null
    //   465: aload 19
    //   467: invokevirtual 88	java/lang/reflect/Method:invoke	(Ljava/lang/Object;[Ljava/lang/Object;)Ljava/lang/Object;
    //   470: astore 21
    //   472: iload 17
    //   474: aload 21
    //   476: checkcast 90	java/lang/Integer
    //   479: invokevirtual 93	java/lang/Integer:intValue	()I
    //   482: if_icmpeq +13 -> 495
    //   485: bipush 66
    //   487: putstatic 107	uuuuuu/ttttst:b006Ennnn006En006En	I
    //   490: bipush 53
    //   492: putstatic 105	uuuuuu/ttttst:bnnnnn006En006En	I
    //   495: aload_0
    //   496: getfield 52	uuuuuu/ttttst:bnnnnn006E006E006En	Luuuuuu/ttssst$tsssst;
    //   499: checkcast 54	uuuuuu/stsstt$sssstt
    //   502: invokeinterface 271 1 0
    //   507: return
    //   508: astore 20
    //   510: aload 20
    //   512: invokevirtual 141	java/lang/reflect/InvocationTargetException:getCause	()Ljava/lang/Throwable;
    //   515: athrow
    //   516: astore 4
    //   518: aload 4
    //   520: invokevirtual 141	java/lang/reflect/InvocationTargetException:getCause	()Ljava/lang/Throwable;
    //   523: athrow
    //   524: astore 10
    //   526: aload 10
    //   528: invokevirtual 141	java/lang/reflect/InvocationTargetException:getCause	()Ljava/lang/Throwable;
    //   531: athrow
    //   532: astore 15
    //   534: aload 15
    //   536: invokevirtual 141	java/lang/reflect/InvocationTargetException:getCause	()Ljava/lang/Throwable;
    //   539: athrow
    //   540: astore 24
    //   542: aload 24
    //   544: invokevirtual 141	java/lang/reflect/InvocationTargetException:getCause	()Ljava/lang/Throwable;
    //   547: athrow
    //   548: astore 28
    //   550: aload 28
    //   552: invokevirtual 141	java/lang/reflect/InvocationTargetException:getCause	()Ljava/lang/Throwable;
    //   555: athrow
    //   556: astore 32
    //   558: aload 32
    //   560: invokevirtual 141	java/lang/reflect/InvocationTargetException:getCause	()Ljava/lang/Throwable;
    //   563: athrow
    // Local variable table:
    //   start	length	slot	name	signature
    //   0	564	0	this	ttttst
    //   43	47	1	i	int
    //   64	7	2	localMethod1	Method
    //   69	4	3	arrayOfObject1	Object[]
    //   516	3	4	localInvocationTargetException1	InvocationTargetException
    //   76	5	5	localObject1	Object
    //   90	179	6	j	int
    //   95	174	7	k	int
    //   118	9	8	localMethod2	Method
    //   124	6	9	arrayOfObject2	Object[]
    //   524	3	10	localInvocationTargetException2	InvocationTargetException
    //   134	3	11	localObject2	Object
    //   148	51	12	m	int
    //   170	9	13	localMethod3	Method
    //   176	6	14	arrayOfObject3	Object[]
    //   532	3	15	localInvocationTargetException3	InvocationTargetException
    //   186	5	16	localObject3	Object
    //   431	52	17	n	int
    //   454	9	18	localMethod4	Method
    //   460	6	19	arrayOfObject4	Object[]
    //   508	3	20	localInvocationTargetException4	InvocationTargetException
    //   470	5	21	localObject4	Object
    //   307	9	22	localMethod5	Method
    //   313	6	23	arrayOfObject5	Object[]
    //   540	3	24	localInvocationTargetException5	InvocationTargetException
    //   323	3	25	localObject5	Object
    //   356	9	26	localMethod6	Method
    //   362	6	27	arrayOfObject6	Object[]
    //   548	3	28	localInvocationTargetException6	InvocationTargetException
    //   372	3	29	localObject6	Object
    //   235	9	30	localMethod7	Method
    //   241	6	31	arrayOfObject7	Object[]
    //   556	3	32	localInvocationTargetException7	InvocationTargetException
    //   251	3	33	localObject7	Object
    // Exception table:
    //   from	to	target	type
    //   462	472	508	java/lang/reflect/InvocationTargetException
    //   70	78	516	java/lang/reflect/InvocationTargetException
    //   126	136	524	java/lang/reflect/InvocationTargetException
    //   178	188	532	java/lang/reflect/InvocationTargetException
    //   315	325	540	java/lang/reflect/InvocationTargetException
    //   364	374	548	java/lang/reflect/InvocationTargetException
    //   243	253	556	java/lang/reflect/InvocationTargetException
  }
  
  /* Error */
  public void b006B006Bkkkkkk006Bk()
  {
    // Byte code:
    //   0: ldc 2
    //   2: ldc_w 274
    //   5: bipush 88
    //   7: iconst_1
    //   8: invokestatic 74	xxxxxx/uxxxxx:bb00620062bb0062b0062b0062	(Ljava/lang/String;CC)Ljava/lang/String;
    //   11: iconst_0
    //   12: anewarray 76	java/lang/Class
    //   15: invokevirtual 80	java/lang/Class:getMethod	(Ljava/lang/String;[Ljava/lang/Class;)Ljava/lang/reflect/Method;
    //   18: astore_1
    //   19: iconst_0
    //   20: anewarray 82	java/lang/Object
    //   23: astore_2
    //   24: aload_1
    //   25: aload_0
    //   26: aload_2
    //   27: invokevirtual 88	java/lang/reflect/Method:invoke	(Ljava/lang/Object;[Ljava/lang/Object;)Ljava/lang/Object;
    //   30: astore 4
    //   32: aload 4
    //   34: checkcast 179	java/lang/Boolean
    //   37: invokevirtual 183	java/lang/Boolean:booleanValue	()Z
    //   40: ifeq +10 -> 50
    //   43: aload_0
    //   44: invokevirtual 196	uuuuuu/ttttst:b006Bk006B006Bkk006Bk006Bk	()Z
    //   47: ifeq +4 -> 51
    //   50: return
    //   51: ldc 2
    //   53: ldc_w 276
    //   56: bipush 112
    //   58: bipush 82
    //   60: iconst_2
    //   61: invokestatic 101	xxxxxx/uxxxxx:bbbb0062b0062b0062b0062	(Ljava/lang/String;CCC)Ljava/lang/String;
    //   64: iconst_0
    //   65: anewarray 76	java/lang/Class
    //   68: invokevirtual 80	java/lang/Class:getMethod	(Ljava/lang/String;[Ljava/lang/Class;)Ljava/lang/reflect/Method;
    //   71: astore 5
    //   73: iconst_0
    //   74: anewarray 82	java/lang/Object
    //   77: astore 6
    //   79: aload 5
    //   81: aload_0
    //   82: aload 6
    //   84: invokevirtual 88	java/lang/reflect/Method:invoke	(Ljava/lang/Object;[Ljava/lang/Object;)Ljava/lang/Object;
    //   87: astore 8
    //   89: aload 8
    //   91: checkcast 124	java/lang/String
    //   94: astore 9
    //   96: aload 9
    //   98: invokevirtual 279	java/lang/String:isEmpty	()Z
    //   101: ifne -51 -> 50
    //   104: aload_0
    //   105: getfield 52	uuuuuu/ttttst:bnnnnn006E006E006En	Luuuuuu/ttssst$tsssst;
    //   108: checkcast 54	uuuuuu/stsstt$sssstt
    //   111: astore 10
    //   113: getstatic 107	uuuuuu/ttttst:b006Ennnn006En006En	I
    //   116: istore 11
    //   118: iload 11
    //   120: iload 11
    //   122: getstatic 95	uuuuuu/ttttst:bn006E006E006E006Enn006En	I
    //   125: iadd
    //   126: imul
    //   127: getstatic 103	uuuuuu/ttttst:b006E006E006E006E006Enn006En	I
    //   130: irem
    //   131: tableswitch	default:+17->148, 0:+69->200
    //   148: ldc 2
    //   150: ldc_w 281
    //   153: bipush 85
    //   155: iconst_1
    //   156: invokestatic 74	xxxxxx/uxxxxx:bb00620062bb0062b0062b0062	(Ljava/lang/String;CC)Ljava/lang/String;
    //   159: iconst_0
    //   160: anewarray 76	java/lang/Class
    //   163: invokevirtual 80	java/lang/Class:getMethod	(Ljava/lang/String;[Ljava/lang/Class;)Ljava/lang/reflect/Method;
    //   166: astore 26
    //   168: iconst_0
    //   169: anewarray 82	java/lang/Object
    //   172: astore 27
    //   174: aload 26
    //   176: aconst_null
    //   177: aload 27
    //   179: invokevirtual 88	java/lang/reflect/Method:invoke	(Ljava/lang/Object;[Ljava/lang/Object;)Ljava/lang/Object;
    //   182: astore 29
    //   184: aload 29
    //   186: checkcast 90	java/lang/Integer
    //   189: invokevirtual 93	java/lang/Integer:intValue	()I
    //   192: putstatic 107	uuuuuu/ttttst:b006Ennnn006En006En	I
    //   195: bipush 84
    //   197: putstatic 105	uuuuuu/ttttst:bnnnnn006En006En	I
    //   200: aload 10
    //   202: aload 9
    //   204: invokeinterface 284 2 0
    //   209: getstatic 107	uuuuuu/ttttst:b006Ennnn006En006En	I
    //   212: getstatic 95	uuuuuu/ttttst:bn006E006E006E006Enn006En	I
    //   215: iadd
    //   216: getstatic 107	uuuuuu/ttttst:b006Ennnn006En006En	I
    //   219: imul
    //   220: getstatic 103	uuuuuu/ttttst:b006E006E006E006E006Enn006En	I
    //   223: irem
    //   224: getstatic 105	uuuuuu/ttttst:bnnnnn006En006En	I
    //   227: if_icmpeq -177 -> 50
    //   230: getstatic 107	uuuuuu/ttttst:b006Ennnn006En006En	I
    //   233: istore 12
    //   235: iload 12
    //   237: iload 12
    //   239: getstatic 95	uuuuuu/ttttst:bn006E006E006E006Enn006En	I
    //   242: iadd
    //   243: imul
    //   244: getstatic 103	uuuuuu/ttttst:b006E006E006E006E006Enn006En	I
    //   247: irem
    //   248: tableswitch	default:+20->268, 0:+162->410
    //   268: getstatic 107	uuuuuu/ttttst:b006Ennnn006En006En	I
    //   271: istore 17
    //   273: iload 17
    //   275: iload 17
    //   277: getstatic 95	uuuuuu/ttttst:bn006E006E006E006Enn006En	I
    //   280: iadd
    //   281: imul
    //   282: getstatic 103	uuuuuu/ttttst:b006E006E006E006E006Enn006En	I
    //   285: irem
    //   286: tableswitch	default:+18->304, 0:+71->357
    //   304: ldc 2
    //   306: ldc_w 286
    //   309: sipush 205
    //   312: iconst_3
    //   313: invokestatic 74	xxxxxx/uxxxxx:bb00620062bb0062b0062b0062	(Ljava/lang/String;CC)Ljava/lang/String;
    //   316: iconst_0
    //   317: anewarray 76	java/lang/Class
    //   320: invokevirtual 80	java/lang/Class:getMethod	(Ljava/lang/String;[Ljava/lang/Class;)Ljava/lang/reflect/Method;
    //   323: astore 22
    //   325: iconst_0
    //   326: anewarray 82	java/lang/Object
    //   329: astore 23
    //   331: aload 22
    //   333: aconst_null
    //   334: aload 23
    //   336: invokevirtual 88	java/lang/reflect/Method:invoke	(Ljava/lang/Object;[Ljava/lang/Object;)Ljava/lang/Object;
    //   339: astore 25
    //   341: aload 25
    //   343: checkcast 90	java/lang/Integer
    //   346: invokevirtual 93	java/lang/Integer:intValue	()I
    //   349: putstatic 107	uuuuuu/ttttst:b006Ennnn006En006En	I
    //   352: bipush 22
    //   354: putstatic 105	uuuuuu/ttttst:bnnnnn006En006En	I
    //   357: ldc 2
    //   359: ldc_w 288
    //   362: sipush 172
    //   365: iconst_3
    //   366: invokestatic 74	xxxxxx/uxxxxx:bb00620062bb0062b0062b0062	(Ljava/lang/String;CC)Ljava/lang/String;
    //   369: iconst_0
    //   370: anewarray 76	java/lang/Class
    //   373: invokevirtual 80	java/lang/Class:getMethod	(Ljava/lang/String;[Ljava/lang/Class;)Ljava/lang/reflect/Method;
    //   376: astore 18
    //   378: iconst_0
    //   379: anewarray 82	java/lang/Object
    //   382: astore 19
    //   384: aload 18
    //   386: aconst_null
    //   387: aload 19
    //   389: invokevirtual 88	java/lang/reflect/Method:invoke	(Ljava/lang/Object;[Ljava/lang/Object;)Ljava/lang/Object;
    //   392: astore 21
    //   394: aload 21
    //   396: checkcast 90	java/lang/Integer
    //   399: invokevirtual 93	java/lang/Integer:intValue	()I
    //   402: putstatic 107	uuuuuu/ttttst:b006Ennnn006En006En	I
    //   405: bipush 88
    //   407: putstatic 105	uuuuuu/ttttst:bnnnnn006En006En	I
    //   410: ldc 2
    //   412: ldc_w 290
    //   415: bipush 38
    //   417: iconst_1
    //   418: invokestatic 74	xxxxxx/uxxxxx:bb00620062bb0062b0062b0062	(Ljava/lang/String;CC)Ljava/lang/String;
    //   421: iconst_0
    //   422: anewarray 76	java/lang/Class
    //   425: invokevirtual 80	java/lang/Class:getMethod	(Ljava/lang/String;[Ljava/lang/Class;)Ljava/lang/reflect/Method;
    //   428: astore 13
    //   430: iconst_0
    //   431: anewarray 82	java/lang/Object
    //   434: astore 14
    //   436: aload 13
    //   438: aconst_null
    //   439: aload 14
    //   441: invokevirtual 88	java/lang/reflect/Method:invoke	(Ljava/lang/Object;[Ljava/lang/Object;)Ljava/lang/Object;
    //   444: astore 16
    //   446: aload 16
    //   448: checkcast 90	java/lang/Integer
    //   451: invokevirtual 93	java/lang/Integer:intValue	()I
    //   454: putstatic 107	uuuuuu/ttttst:b006Ennnn006En006En	I
    //   457: bipush 13
    //   459: putstatic 105	uuuuuu/ttttst:bnnnnn006En006En	I
    //   462: return
    //   463: astore 15
    //   465: aload 15
    //   467: invokevirtual 141	java/lang/reflect/InvocationTargetException:getCause	()Ljava/lang/Throwable;
    //   470: athrow
    //   471: astore 7
    //   473: aload 7
    //   475: invokevirtual 141	java/lang/reflect/InvocationTargetException:getCause	()Ljava/lang/Throwable;
    //   478: athrow
    //   479: astore_3
    //   480: aload_3
    //   481: invokevirtual 141	java/lang/reflect/InvocationTargetException:getCause	()Ljava/lang/Throwable;
    //   484: athrow
    //   485: astore 28
    //   487: aload 28
    //   489: invokevirtual 141	java/lang/reflect/InvocationTargetException:getCause	()Ljava/lang/Throwable;
    //   492: athrow
    //   493: astore 20
    //   495: aload 20
    //   497: invokevirtual 141	java/lang/reflect/InvocationTargetException:getCause	()Ljava/lang/Throwable;
    //   500: athrow
    //   501: astore 24
    //   503: aload 24
    //   505: invokevirtual 141	java/lang/reflect/InvocationTargetException:getCause	()Ljava/lang/Throwable;
    //   508: athrow
    // Local variable table:
    //   start	length	slot	name	signature
    //   0	509	0	this	ttttst
    //   18	7	1	localMethod1	Method
    //   23	4	2	arrayOfObject1	Object[]
    //   479	2	3	localInvocationTargetException1	InvocationTargetException
    //   30	3	4	localObject1	Object
    //   71	9	5	localMethod2	Method
    //   77	6	6	arrayOfObject2	Object[]
    //   471	3	7	localInvocationTargetException2	InvocationTargetException
    //   87	3	8	localObject2	Object
    //   94	109	9	str	String
    //   111	90	10	localSssstt	stsstt.sssstt
    //   116	11	11	i	int
    //   233	11	12	j	int
    //   428	9	13	localMethod3	Method
    //   434	6	14	arrayOfObject3	Object[]
    //   463	3	15	localInvocationTargetException3	InvocationTargetException
    //   444	3	16	localObject3	Object
    //   271	11	17	k	int
    //   376	9	18	localMethod4	Method
    //   382	6	19	arrayOfObject4	Object[]
    //   493	3	20	localInvocationTargetException4	InvocationTargetException
    //   392	3	21	localObject4	Object
    //   323	9	22	localMethod5	Method
    //   329	6	23	arrayOfObject5	Object[]
    //   501	3	24	localInvocationTargetException5	InvocationTargetException
    //   339	3	25	localObject5	Object
    //   166	9	26	localMethod6	Method
    //   172	6	27	arrayOfObject6	Object[]
    //   485	3	28	localInvocationTargetException6	InvocationTargetException
    //   182	3	29	localObject6	Object
    // Exception table:
    //   from	to	target	type
    //   436	446	463	java/lang/reflect/InvocationTargetException
    //   79	89	471	java/lang/reflect/InvocationTargetException
    //   24	32	479	java/lang/reflect/InvocationTargetException
    //   174	184	485	java/lang/reflect/InvocationTargetException
    //   384	394	493	java/lang/reflect/InvocationTargetException
    //   331	341	501	java/lang/reflect/InvocationTargetException
  }
  
  public String b006Bk006B006Bkkkk006Bk()
  {
    if ((b006Ennnn006En006En + bn006E006E006E006Enn006En) * b006Ennnn006En006En % b006E006E006E006E006Enn006En != bnnnnn006En006En)
    {
      b006Ennnn006En006En = 45;
      bnnnnn006En006En = 40;
    }
    SharedPreferencesHelper localSharedPreferencesHelper1 = this.b006E006En006Enn006E006En;
    Method localMethod1 = SharedPreferencesHelper.class.getMethod(uxxxxx.bb00620062bb0062b0062b0062("\013\b\026t\005\002\006\013\005}z\005`z", '.', '\004'), new Class[0]);
    Object[] arrayOfObject1 = new Object[0];
    for (;;)
    {
      try
      {
        Object localObject1 = localMethod1.invoke(localSharedPreferencesHelper1, arrayOfObject1);
        str = (String)localObject1;
        if (!str.isEmpty())
        {
          localSharedPreferencesHelper2 = this.b006E006En006Enn006E006En;
          localMethod2 = SharedPreferencesHelper.class.getMethod(uxxxxx.bb00620062bb0062b0062b0062("qn|Rk~Grwot", '', '\005'), new Class[0]);
          arrayOfObject2 = new Object[0];
        }
      }
      catch (InvocationTargetException localInvocationTargetException1)
      {
        String str;
        SharedPreferencesHelper localSharedPreferencesHelper2;
        Method localMethod2;
        Object[] arrayOfObject2;
        Object localObject2;
        int i;
        Method localMethod3;
        Object[] arrayOfObject3;
        Object localObject3;
        int j;
        Method localMethod4;
        Object[] arrayOfObject4;
        Object localObject4;
        Method localMethod8;
        Object[] arrayOfObject9;
        throw localInvocationTargetException1.getCause();
      }
      try
      {
        localObject2 = localMethod2.invoke(localSharedPreferencesHelper2, arrayOfObject2);
        i = ((Integer)localObject2).intValue();
        if (i > -1)
        {
          localMethod3 = ttttst.class.getMethod(uxxxxx.bb00620062bb0062b0062b0062("5\004\005\f\031C\t\n\021\036HIJKL\022\023\032'Q", 'p', '\000'), new Class[0]);
          arrayOfObject3 = new Object[0];
        }
      }
      catch (InvocationTargetException localInvocationTargetException2)
      {
        throw localInvocationTargetException2.getCause();
      }
      try
      {
        localObject3 = localMethod3.invoke(null, arrayOfObject3);
        j = ((Integer)localObject3).intValue() + bn006E006E006E006Enn006En;
        localMethod4 = ttttst.class.getMethod(uxxxxx.bbbb0062b0062b0062b0062("M\032\031\036)Q\025\024\031$LKJIH\f\013\020\033C", 'p', '[', '\001'), new Class[0]);
        arrayOfObject4 = new Object[0];
      }
      catch (InvocationTargetException localInvocationTargetException3)
      {
        throw localInvocationTargetException3.getCause();
      }
      try
      {
        localObject4 = localMethod4.invoke(null, arrayOfObject4);
        if (j * ((Integer)localObject4).intValue() % b006E006E006E006E006Enn006En != bnnnnn006En006En)
        {
          localMethod8 = ttttst.class.getMethod(uxxxxx.bb00620062bb0062b0062b0062("a.-2=e)(-8`_^]\\ \037$/W", '\001', '\003'), new Class[0]);
          arrayOfObject9 = new Object[0];
        }
        try
        {
          Object localObject8 = localMethod8.invoke(null, arrayOfObject9);
          b006Ennnn006En006En = ((Integer)localObject8).intValue();
          bnnnnn006En006En = 99;
          localSssstt = (stsstt.sssstt)this.bnnnnn006E006E006En;
          int k = b006Ennnn006En006En;
          switch (k * (k + bn006E006E006E006Enn006En) % b006E006E006E006E006Enn006En)
          {
          default: 
            b006Ennnn006En006En = 34;
            bnnnnn006En006En = 49;
            localMethod5 = ttttst.class.getMethod(uxxxxx.bbbb0062b0062b0062b0062("\003ONS^\007JINY\002\001~}A@EPx", '', '', '\001'), new Class[0]);
            arrayOfObject6 = new Object[0];
          }
        }
        catch (InvocationTargetException localInvocationTargetException8)
        {
          stsstt.sssstt localSssstt;
          Method localMethod5;
          Object[] arrayOfObject6;
          Object localObject5;
          int n;
          Method localMethod6;
          Object[] arrayOfObject7;
          Object localObject6;
          Method localMethod7;
          Object[] arrayOfObject8;
          Object localObject7;
          int m;
          Object[] arrayOfObject5;
          throw localInvocationTargetException8.getCause();
        }
      }
      catch (InvocationTargetException localInvocationTargetException4)
      {
        throw localInvocationTargetException4.getCause();
      }
    }
    try
    {
      localObject5 = localMethod5.invoke(null, arrayOfObject6);
      n = ((Integer)localObject5).intValue();
      switch (n * (n + bn006E006E006E006Enn006En) % b006E006E006E006E006Enn006En)
      {
      default: 
        localMethod6 = ttttst.class.getMethod(uxxxxx.bb00620062bb0062b0062b0062("\037kjoz#feju\036\035\034\033\032]\\al\025", '', '\003'), new Class[0]);
        arrayOfObject7 = new Object[0];
      }
    }
    catch (InvocationTargetException localInvocationTargetException5)
    {
      throw localInvocationTargetException5.getCause();
    }
    try
    {
      localObject6 = localMethod6.invoke(null, arrayOfObject7);
      b006Ennnn006En006En = ((Integer)localObject6).intValue();
      localMethod7 = ttttst.class.getMethod(uxxxxx.bb00620062bb0062b0062b0062("\031edit\035`_do\030\027\026\025\024WV[f\017", 'd', '\004'), new Class[0]);
      arrayOfObject8 = new Object[0];
    }
    catch (InvocationTargetException localInvocationTargetException6)
    {
      throw localInvocationTargetException6.getCause();
    }
    try
    {
      localObject7 = localMethod7.invoke(null, arrayOfObject8);
      bnnnnn006En006En = ((Integer)localObject7).intValue();
      m = R.string.menu_item_client_id_with_tokens_count;
      arrayOfObject5 = new Object[2];
      arrayOfObject5[0] = str;
      arrayOfObject5[1] = Integer.valueOf(i);
      return localSssstt.getStringResource(m, arrayOfObject5);
    }
    catch (InvocationTargetException localInvocationTargetException7)
    {
      throw localInvocationTargetException7.getCause();
    }
    return "";
    return ((stsstt.sssstt)this.bnnnnn006E006E006En).getStringResource(R.string.mopay_technical_id, new Object[] { str });
  }
  
  /* Error */
  public void b006Bkkkkkkk006Bk(@android.support.annotation.IdRes int paramInt)
  {
    // Byte code:
    //   0: getstatic 107	uuuuuu/ttttst:b006Ennnn006En006En	I
    //   3: getstatic 95	uuuuuu/ttttst:bn006E006E006E006Enn006En	I
    //   6: iadd
    //   7: getstatic 107	uuuuuu/ttttst:b006Ennnn006En006En	I
    //   10: imul
    //   11: getstatic 103	uuuuuu/ttttst:b006E006E006E006E006Enn006En	I
    //   14: irem
    //   15: getstatic 105	uuuuuu/ttttst:bnnnnn006En006En	I
    //   18: if_icmpeq +55 -> 73
    //   21: ldc 2
    //   23: ldc_w 342
    //   26: bipush 78
    //   28: iconst_0
    //   29: invokestatic 74	xxxxxx/uxxxxx:bb00620062bb0062b0062b0062	(Ljava/lang/String;CC)Ljava/lang/String;
    //   32: iconst_0
    //   33: anewarray 76	java/lang/Class
    //   36: invokevirtual 80	java/lang/Class:getMethod	(Ljava/lang/String;[Ljava/lang/Class;)Ljava/lang/reflect/Method;
    //   39: astore 33
    //   41: iconst_0
    //   42: anewarray 82	java/lang/Object
    //   45: astore 34
    //   47: aload 33
    //   49: aconst_null
    //   50: aload 34
    //   52: invokevirtual 88	java/lang/reflect/Method:invoke	(Ljava/lang/Object;[Ljava/lang/Object;)Ljava/lang/Object;
    //   55: astore 36
    //   57: aload 36
    //   59: checkcast 90	java/lang/Integer
    //   62: invokevirtual 93	java/lang/Integer:intValue	()I
    //   65: putstatic 107	uuuuuu/ttttst:b006Ennnn006En006En	I
    //   68: bipush 85
    //   70: putstatic 105	uuuuuu/ttttst:bnnnnn006En006En	I
    //   73: aload_0
    //   74: invokevirtual 345	uuuuuu/ttttst:bkk006Bk006Bk006Bk006Bk	()Z
    //   77: ifne +655 -> 732
    //   80: return
    //   81: iload_1
    //   82: getstatic 350	com/db/pwcc/dbmobile/foundation/R$id:settings_item	I
    //   85: if_icmpne +452 -> 537
    //   88: getstatic 356	uuuuuu/vvrvrv:bxx00780078xxxxx	Luuuuuu/vvrvrv;
    //   91: invokestatic 362	uuuuuu/rrvvrv:b0071q0071qq0071q0071q0071	(Luuuuuu/vvrvrv;)V
    //   94: aload_0
    //   95: getfield 52	uuuuuu/ttttst:bnnnnn006E006E006En	Luuuuuu/ttssst$tsssst;
    //   98: checkcast 54	uuuuuu/stsstt$sssstt
    //   101: invokeinterface 365 1 0
    //   106: getstatic 107	uuuuuu/ttttst:b006Ennnn006En006En	I
    //   109: istore 7
    //   111: ldc 2
    //   113: ldc_w 367
    //   116: bipush 68
    //   118: iconst_1
    //   119: invokestatic 74	xxxxxx/uxxxxx:bb00620062bb0062b0062b0062	(Ljava/lang/String;CC)Ljava/lang/String;
    //   122: iconst_0
    //   123: anewarray 76	java/lang/Class
    //   126: invokevirtual 80	java/lang/Class:getMethod	(Ljava/lang/String;[Ljava/lang/Class;)Ljava/lang/reflect/Method;
    //   129: astore 8
    //   131: iconst_0
    //   132: anewarray 82	java/lang/Object
    //   135: astore 9
    //   137: aload 8
    //   139: aconst_null
    //   140: aload 9
    //   142: invokevirtual 88	java/lang/reflect/Method:invoke	(Ljava/lang/Object;[Ljava/lang/Object;)Ljava/lang/Object;
    //   145: astore 11
    //   147: iload 7
    //   149: aload 11
    //   151: checkcast 90	java/lang/Integer
    //   154: invokevirtual 93	java/lang/Integer:intValue	()I
    //   157: iadd
    //   158: getstatic 107	uuuuuu/ttttst:b006Ennnn006En006En	I
    //   161: imul
    //   162: getstatic 103	uuuuuu/ttttst:b006E006E006E006E006Enn006En	I
    //   165: irem
    //   166: getstatic 105	uuuuuu/ttttst:bnnnnn006En006En	I
    //   169: if_icmpeq -89 -> 80
    //   172: bipush 15
    //   174: putstatic 107	uuuuuu/ttttst:b006Ennnn006En006En	I
    //   177: ldc 2
    //   179: ldc_w 369
    //   182: bipush 49
    //   184: bipush 68
    //   186: iconst_1
    //   187: invokestatic 101	xxxxxx/uxxxxx:bbbb0062b0062b0062b0062	(Ljava/lang/String;CCC)Ljava/lang/String;
    //   190: iconst_0
    //   191: anewarray 76	java/lang/Class
    //   194: invokevirtual 80	java/lang/Class:getMethod	(Ljava/lang/String;[Ljava/lang/Class;)Ljava/lang/reflect/Method;
    //   197: astore 12
    //   199: iconst_0
    //   200: anewarray 82	java/lang/Object
    //   203: astore 13
    //   205: aload 12
    //   207: aconst_null
    //   208: aload 13
    //   210: invokevirtual 88	java/lang/reflect/Method:invoke	(Ljava/lang/Object;[Ljava/lang/Object;)Ljava/lang/Object;
    //   213: astore 15
    //   215: aload 15
    //   217: checkcast 90	java/lang/Integer
    //   220: invokevirtual 93	java/lang/Integer:intValue	()I
    //   223: putstatic 105	uuuuuu/ttttst:bnnnnn006En006En	I
    //   226: return
    //   227: iload_1
    //   228: getstatic 372	com/db/pwcc/dbmobile/foundation/R$id:feedback_item	I
    //   231: if_icmpne +22 -> 253
    //   234: getstatic 375	uuuuuu/vvrvrv:b006800680068hh0068006800680068	Luuuuuu/vvrvrv;
    //   237: invokestatic 362	uuuuuu/rrvvrv:b0071q0071qq0071q0071q0071	(Luuuuuu/vvrvrv;)V
    //   240: aload_0
    //   241: getfield 52	uuuuuu/ttttst:bnnnnn006E006E006En	Luuuuuu/ttssst$tsssst;
    //   244: checkcast 54	uuuuuu/stsstt$sssstt
    //   247: invokeinterface 378 1 0
    //   252: return
    //   253: iload_1
    //   254: getstatic 381	com/db/pwcc/dbmobile/foundation/R$id:imprint_item	I
    //   257: if_icmpne +399 -> 656
    //   260: getstatic 384	uuuuuu/vvrvrv:bhhh0068h0068006800680068	Luuuuuu/vvrvrv;
    //   263: invokestatic 362	uuuuuu/rrvvrv:b0071q0071qq0071q0071q0071	(Luuuuuu/vvrvrv;)V
    //   266: aload_0
    //   267: getfield 52	uuuuuu/ttttst:bnnnnn006E006E006En	Luuuuuu/ttssst$tsssst;
    //   270: checkcast 54	uuuuuu/stsstt$sssstt
    //   273: invokeinterface 387 1 0
    //   278: return
    //   279: iload_1
    //   280: getstatic 390	com/db/pwcc/dbmobile/foundation/R$id:ibanbic_item	I
    //   283: if_icmpne +228 -> 511
    //   286: getstatic 393	uuuuuu/vvrvrv:bh0068h0068hhh00680068	Luuuuuu/vvrvrv;
    //   289: invokestatic 362	uuuuuu/rrvvrv:b0071q0071qq0071q0071q0071	(Luuuuuu/vvrvrv;)V
    //   292: ldc 2
    //   294: ldc_w 395
    //   297: sipush 219
    //   300: bipush 64
    //   302: iconst_3
    //   303: invokestatic 101	xxxxxx/uxxxxx:bbbb0062b0062b0062b0062	(Ljava/lang/String;CCC)Ljava/lang/String;
    //   306: iconst_0
    //   307: anewarray 76	java/lang/Class
    //   310: invokevirtual 80	java/lang/Class:getMethod	(Ljava/lang/String;[Ljava/lang/Class;)Ljava/lang/reflect/Method;
    //   313: astore 16
    //   315: iconst_0
    //   316: anewarray 82	java/lang/Object
    //   319: astore 17
    //   321: aload 16
    //   323: aconst_null
    //   324: aload 17
    //   326: invokevirtual 88	java/lang/reflect/Method:invoke	(Ljava/lang/Object;[Ljava/lang/Object;)Ljava/lang/Object;
    //   329: astore 19
    //   331: aload 19
    //   333: checkcast 90	java/lang/Integer
    //   336: invokevirtual 93	java/lang/Integer:intValue	()I
    //   339: getstatic 95	uuuuuu/ttttst:bn006E006E006E006Enn006En	I
    //   342: iadd
    //   343: istore 20
    //   345: ldc 2
    //   347: ldc_w 397
    //   350: bipush 73
    //   352: bipush 60
    //   354: iconst_2
    //   355: invokestatic 101	xxxxxx/uxxxxx:bbbb0062b0062b0062b0062	(Ljava/lang/String;CCC)Ljava/lang/String;
    //   358: iconst_0
    //   359: anewarray 76	java/lang/Class
    //   362: invokevirtual 80	java/lang/Class:getMethod	(Ljava/lang/String;[Ljava/lang/Class;)Ljava/lang/reflect/Method;
    //   365: astore 21
    //   367: iconst_0
    //   368: anewarray 82	java/lang/Object
    //   371: astore 22
    //   373: aload 21
    //   375: aconst_null
    //   376: aload 22
    //   378: invokevirtual 88	java/lang/reflect/Method:invoke	(Ljava/lang/Object;[Ljava/lang/Object;)Ljava/lang/Object;
    //   381: astore 24
    //   383: iload 20
    //   385: aload 24
    //   387: checkcast 90	java/lang/Integer
    //   390: invokevirtual 93	java/lang/Integer:intValue	()I
    //   393: imul
    //   394: getstatic 103	uuuuuu/ttttst:b006E006E006E006E006Enn006En	I
    //   397: irem
    //   398: getstatic 105	uuuuuu/ttttst:bnnnnn006En006En	I
    //   401: if_icmpeq +97 -> 498
    //   404: ldc 2
    //   406: ldc 113
    //   408: sipush 137
    //   411: iconst_1
    //   412: invokestatic 74	xxxxxx/uxxxxx:bb00620062bb0062b0062b0062	(Ljava/lang/String;CC)Ljava/lang/String;
    //   415: iconst_0
    //   416: anewarray 76	java/lang/Class
    //   419: invokevirtual 80	java/lang/Class:getMethod	(Ljava/lang/String;[Ljava/lang/Class;)Ljava/lang/reflect/Method;
    //   422: astore 25
    //   424: iconst_0
    //   425: anewarray 82	java/lang/Object
    //   428: astore 26
    //   430: aload 25
    //   432: aconst_null
    //   433: aload 26
    //   435: invokevirtual 88	java/lang/reflect/Method:invoke	(Ljava/lang/Object;[Ljava/lang/Object;)Ljava/lang/Object;
    //   438: astore 28
    //   440: aload 28
    //   442: checkcast 90	java/lang/Integer
    //   445: invokevirtual 93	java/lang/Integer:intValue	()I
    //   448: putstatic 107	uuuuuu/ttttst:b006Ennnn006En006En	I
    //   451: ldc 2
    //   453: ldc_w 399
    //   456: bipush 49
    //   458: iconst_4
    //   459: invokestatic 74	xxxxxx/uxxxxx:bb00620062bb0062b0062b0062	(Ljava/lang/String;CC)Ljava/lang/String;
    //   462: iconst_0
    //   463: anewarray 76	java/lang/Class
    //   466: invokevirtual 80	java/lang/Class:getMethod	(Ljava/lang/String;[Ljava/lang/Class;)Ljava/lang/reflect/Method;
    //   469: astore 29
    //   471: iconst_0
    //   472: anewarray 82	java/lang/Object
    //   475: astore 30
    //   477: aload 29
    //   479: aconst_null
    //   480: aload 30
    //   482: invokevirtual 88	java/lang/reflect/Method:invoke	(Ljava/lang/Object;[Ljava/lang/Object;)Ljava/lang/Object;
    //   485: astore 32
    //   487: aload 32
    //   489: checkcast 90	java/lang/Integer
    //   492: invokevirtual 93	java/lang/Integer:intValue	()I
    //   495: putstatic 105	uuuuuu/ttttst:bnnnnn006En006En	I
    //   498: aload_0
    //   499: getfield 52	uuuuuu/ttttst:bnnnnn006E006E006En	Luuuuuu/ttssst$tsssst;
    //   502: checkcast 54	uuuuuu/stsstt$sssstt
    //   505: invokeinterface 402 1 0
    //   510: return
    //   511: iload_1
    //   512: getstatic 405	com/db/pwcc/dbmobile/foundation/R$id:overdraft_item	I
    //   515: if_icmpne +237 -> 752
    //   518: getstatic 408	uuuuuu/vvrvrv:b00680068hh0068h0068h0068	Luuuuuu/vvrvrv;
    //   521: invokestatic 362	uuuuuu/rrvvrv:b0071q0071qq0071q0071q0071	(Luuuuuu/vvrvrv;)V
    //   524: aload_0
    //   525: getfield 52	uuuuuu/ttttst:bnnnnn006E006E006En	Luuuuuu/ttssst$tsssst;
    //   528: checkcast 54	uuuuuu/stsstt$sssstt
    //   531: invokeinterface 411 1 0
    //   536: return
    //   537: iload_1
    //   538: getstatic 414	com/db/pwcc/dbmobile/foundation/R$id:whatsnew_item	I
    //   541: if_icmpne -314 -> 227
    //   544: getstatic 417	uuuuuu/vvrvrv:b0068h00680068h0068006800680068	Luuuuuu/vvrvrv;
    //   547: invokestatic 362	uuuuuu/rrvvrv:b0071q0071qq0071q0071q0071	(Luuuuuu/vvrvrv;)V
    //   550: aload_0
    //   551: getfield 52	uuuuuu/ttttst:bnnnnn006E006E006En	Luuuuuu/ttssst$tsssst;
    //   554: checkcast 54	uuuuuu/stsstt$sssstt
    //   557: invokeinterface 420 1 0
    //   562: getstatic 107	uuuuuu/ttttst:b006Ennnn006En006En	I
    //   565: istore_2
    //   566: iload_2
    //   567: iload_2
    //   568: getstatic 95	uuuuuu/ttttst:bn006E006E006E006Enn006En	I
    //   571: iadd
    //   572: imul
    //   573: getstatic 103	uuuuuu/ttttst:b006E006E006E006E006Enn006En	I
    //   576: irem
    //   577: tableswitch	default:+19->596, 0:+-497->80
    //   596: ldc 2
    //   598: ldc_w 422
    //   601: sipush 131
    //   604: iconst_2
    //   605: invokestatic 74	xxxxxx/uxxxxx:bb00620062bb0062b0062b0062	(Ljava/lang/String;CC)Ljava/lang/String;
    //   608: iconst_0
    //   609: anewarray 76	java/lang/Class
    //   612: invokevirtual 80	java/lang/Class:getMethod	(Ljava/lang/String;[Ljava/lang/Class;)Ljava/lang/reflect/Method;
    //   615: astore_3
    //   616: iconst_0
    //   617: anewarray 82	java/lang/Object
    //   620: astore 4
    //   622: aload_3
    //   623: aconst_null
    //   624: aload 4
    //   626: invokevirtual 88	java/lang/reflect/Method:invoke	(Ljava/lang/Object;[Ljava/lang/Object;)Ljava/lang/Object;
    //   629: astore 6
    //   631: aload 6
    //   633: checkcast 90	java/lang/Integer
    //   636: invokevirtual 93	java/lang/Integer:intValue	()I
    //   639: putstatic 107	uuuuuu/ttttst:b006Ennnn006En006En	I
    //   642: bipush 9
    //   644: putstatic 105	uuuuuu/ttttst:bnnnnn006En006En	I
    //   647: return
    //   648: astore 14
    //   650: aload 14
    //   652: invokevirtual 141	java/lang/reflect/InvocationTargetException:getCause	()Ljava/lang/Throwable;
    //   655: athrow
    //   656: iload_1
    //   657: getstatic 425	com/db/pwcc/dbmobile/foundation/R$id:logout_button	I
    //   660: if_icmpne -580 -> 80
    //   663: getstatic 428	uuuuuu/vvrvrv:b0068hh0068h0068006800680068	Luuuuuu/vvrvrv;
    //   666: invokestatic 362	uuuuuu/rrvvrv:b0071q0071qq0071q0071q0071	(Luuuuuu/vvrvrv;)V
    //   669: aload_0
    //   670: getfield 52	uuuuuu/ttttst:bnnnnn006E006E006En	Luuuuuu/ttssst$tsssst;
    //   673: checkcast 54	uuuuuu/stsstt$sssstt
    //   676: invokeinterface 431 1 0
    //   681: return
    //   682: iload_1
    //   683: getstatic 434	com/db/pwcc/dbmobile/foundation/R$id:postbox_item	I
    //   686: if_icmpne -407 -> 279
    //   689: getstatic 437	uuuuuu/vvrvrv:bh0068hh0068h006800680068	Luuuuuu/vvrvrv;
    //   692: invokestatic 362	uuuuuu/rrvvrv:b0071q0071qq0071q0071q0071	(Luuuuuu/vvrvrv;)V
    //   695: aload_0
    //   696: getfield 52	uuuuuu/ttttst:bnnnnn006E006E006En	Luuuuuu/ttssst$tsssst;
    //   699: checkcast 54	uuuuuu/stsstt$sssstt
    //   702: aload_0
    //   703: getfield 163	uuuuuu/ttttst:b006E006En006Enn006E006En	Lcom/db/pwcc/dbmobile/secure/preferences/SharedPreferencesHelper;
    //   706: aload_0
    //   707: getfield 441	uuuuuu/ttttst:b006En006E006E006En006E006En	Luuuuuu/ggyggy;
    //   710: invokeinterface 445 3 0
    //   715: return
    //   716: astore 18
    //   718: aload 18
    //   720: invokevirtual 141	java/lang/reflect/InvocationTargetException:getCause	()Ljava/lang/Throwable;
    //   723: athrow
    //   724: astore 23
    //   726: aload 23
    //   728: invokevirtual 141	java/lang/reflect/InvocationTargetException:getCause	()Ljava/lang/Throwable;
    //   731: athrow
    //   732: iload_1
    //   733: getstatic 448	com/db/pwcc/dbmobile/foundation/R$id:multibanking_item	I
    //   736: if_icmpne -54 -> 682
    //   739: aload_0
    //   740: getfield 52	uuuuuu/ttttst:bnnnnn006E006E006En	Luuuuuu/ttssst$tsssst;
    //   743: checkcast 54	uuuuuu/stsstt$sssstt
    //   746: invokeinterface 451 1 0
    //   751: return
    //   752: iload_1
    //   753: getstatic 454	com/db/pwcc/dbmobile/foundation/R$id:branchfinder_item	I
    //   756: if_icmpne -675 -> 81
    //   759: getstatic 457	uuuuuu/vvrvrv:bhhhhhh0068h0068	Luuuuuu/vvrvrv;
    //   762: invokestatic 362	uuuuuu/rrvvrv:b0071q0071qq0071q0071q0071	(Luuuuuu/vvrvrv;)V
    //   765: aload_0
    //   766: getfield 52	uuuuuu/ttttst:bnnnnn006E006E006En	Luuuuuu/ttssst$tsssst;
    //   769: checkcast 54	uuuuuu/stsstt$sssstt
    //   772: invokeinterface 460 1 0
    //   777: return
    //   778: astore 10
    //   780: aload 10
    //   782: invokevirtual 141	java/lang/reflect/InvocationTargetException:getCause	()Ljava/lang/Throwable;
    //   785: athrow
    //   786: astore 35
    //   788: aload 35
    //   790: invokevirtual 141	java/lang/reflect/InvocationTargetException:getCause	()Ljava/lang/Throwable;
    //   793: athrow
    //   794: astore 5
    //   796: aload 5
    //   798: invokevirtual 141	java/lang/reflect/InvocationTargetException:getCause	()Ljava/lang/Throwable;
    //   801: athrow
    //   802: astore 27
    //   804: aload 27
    //   806: invokevirtual 141	java/lang/reflect/InvocationTargetException:getCause	()Ljava/lang/Throwable;
    //   809: athrow
    //   810: astore 31
    //   812: aload 31
    //   814: invokevirtual 141	java/lang/reflect/InvocationTargetException:getCause	()Ljava/lang/Throwable;
    //   817: athrow
    // Local variable table:
    //   start	length	slot	name	signature
    //   0	818	0	this	ttttst
    //   0	818	1	paramInt	int
    //   565	8	2	i	int
    //   615	8	3	localMethod1	Method
    //   620	5	4	arrayOfObject1	Object[]
    //   794	3	5	localInvocationTargetException1	InvocationTargetException
    //   629	3	6	localObject1	Object
    //   109	49	7	j	int
    //   129	9	8	localMethod2	Method
    //   135	6	9	arrayOfObject2	Object[]
    //   778	3	10	localInvocationTargetException2	InvocationTargetException
    //   145	5	11	localObject2	Object
    //   197	9	12	localMethod3	Method
    //   203	6	13	arrayOfObject3	Object[]
    //   648	3	14	localInvocationTargetException3	InvocationTargetException
    //   213	3	15	localObject3	Object
    //   313	9	16	localMethod4	Method
    //   319	6	17	arrayOfObject4	Object[]
    //   716	3	18	localInvocationTargetException4	InvocationTargetException
    //   329	3	19	localObject4	Object
    //   343	51	20	k	int
    //   365	9	21	localMethod5	Method
    //   371	6	22	arrayOfObject5	Object[]
    //   724	3	23	localInvocationTargetException5	InvocationTargetException
    //   381	5	24	localObject5	Object
    //   422	9	25	localMethod6	Method
    //   428	6	26	arrayOfObject6	Object[]
    //   802	3	27	localInvocationTargetException6	InvocationTargetException
    //   438	3	28	localObject6	Object
    //   469	9	29	localMethod7	Method
    //   475	6	30	arrayOfObject7	Object[]
    //   810	3	31	localInvocationTargetException7	InvocationTargetException
    //   485	3	32	localObject7	Object
    //   39	9	33	localMethod8	Method
    //   45	6	34	arrayOfObject8	Object[]
    //   786	3	35	localInvocationTargetException8	InvocationTargetException
    //   55	3	36	localObject8	Object
    // Exception table:
    //   from	to	target	type
    //   205	215	648	java/lang/reflect/InvocationTargetException
    //   321	331	716	java/lang/reflect/InvocationTargetException
    //   373	383	724	java/lang/reflect/InvocationTargetException
    //   137	147	778	java/lang/reflect/InvocationTargetException
    //   47	57	786	java/lang/reflect/InvocationTargetException
    //   622	631	794	java/lang/reflect/InvocationTargetException
    //   430	440	802	java/lang/reflect/InvocationTargetException
    //   477	487	810	java/lang/reflect/InvocationTargetException
  }
  
  public void baaa00610061aaa0061a(DbError paramDbError) {}
  
  /* Error */
  public boolean bk006B006B006Bkkkk006Bk()
  {
    // Byte code:
    //   0: getstatic 107	uuuuuu/ttttst:b006Ennnn006En006En	I
    //   3: istore_1
    //   4: iload_1
    //   5: iload_1
    //   6: getstatic 95	uuuuuu/ttttst:bn006E006E006E006Enn006En	I
    //   9: iadd
    //   10: imul
    //   11: getstatic 103	uuuuuu/ttttst:b006E006E006E006E006Enn006En	I
    //   14: irem
    //   15: tableswitch	default:+17->32, 0:+72->87
    //   32: ldc 2
    //   34: ldc_w 422
    //   37: bipush 39
    //   39: sipush 219
    //   42: iconst_3
    //   43: invokestatic 101	xxxxxx/uxxxxx:bbbb0062b0062b0062b0062	(Ljava/lang/String;CCC)Ljava/lang/String;
    //   46: iconst_0
    //   47: anewarray 76	java/lang/Class
    //   50: invokevirtual 80	java/lang/Class:getMethod	(Ljava/lang/String;[Ljava/lang/Class;)Ljava/lang/reflect/Method;
    //   53: astore 45
    //   55: iconst_0
    //   56: anewarray 82	java/lang/Object
    //   59: astore 46
    //   61: aload 45
    //   63: aconst_null
    //   64: aload 46
    //   66: invokevirtual 88	java/lang/reflect/Method:invoke	(Ljava/lang/Object;[Ljava/lang/Object;)Ljava/lang/Object;
    //   69: astore 48
    //   71: aload 48
    //   73: checkcast 90	java/lang/Integer
    //   76: invokevirtual 93	java/lang/Integer:intValue	()I
    //   79: putstatic 107	uuuuuu/ttttst:b006Ennnn006En006En	I
    //   82: bipush 92
    //   84: putstatic 105	uuuuuu/ttttst:bnnnnn006En006En	I
    //   87: aload_0
    //   88: getfield 229	uuuuuu/ttttst:b006E006E006E006E006En006E006En	Luuuuuu/hyhyhh;
    //   91: astore_2
    //   92: ldc 2
    //   94: ldc_w 483
    //   97: bipush 98
    //   99: sipush 129
    //   102: iconst_2
    //   103: invokestatic 101	xxxxxx/uxxxxx:bbbb0062b0062b0062b0062	(Ljava/lang/String;CCC)Ljava/lang/String;
    //   106: iconst_0
    //   107: anewarray 76	java/lang/Class
    //   110: invokevirtual 80	java/lang/Class:getMethod	(Ljava/lang/String;[Ljava/lang/Class;)Ljava/lang/reflect/Method;
    //   113: astore_3
    //   114: iconst_0
    //   115: anewarray 82	java/lang/Object
    //   118: astore 4
    //   120: aload_3
    //   121: aconst_null
    //   122: aload 4
    //   124: invokevirtual 88	java/lang/reflect/Method:invoke	(Ljava/lang/Object;[Ljava/lang/Object;)Ljava/lang/Object;
    //   127: astore 6
    //   129: aload 6
    //   131: checkcast 90	java/lang/Integer
    //   134: invokevirtual 93	java/lang/Integer:intValue	()I
    //   137: getstatic 95	uuuuuu/ttttst:bn006E006E006E006Enn006En	I
    //   140: iadd
    //   141: istore 7
    //   143: ldc 2
    //   145: ldc_w 485
    //   148: sipush 232
    //   151: iconst_5
    //   152: invokestatic 74	xxxxxx/uxxxxx:bb00620062bb0062b0062b0062	(Ljava/lang/String;CC)Ljava/lang/String;
    //   155: iconst_0
    //   156: anewarray 76	java/lang/Class
    //   159: invokevirtual 80	java/lang/Class:getMethod	(Ljava/lang/String;[Ljava/lang/Class;)Ljava/lang/reflect/Method;
    //   162: astore 8
    //   164: iconst_0
    //   165: anewarray 82	java/lang/Object
    //   168: astore 9
    //   170: aload 8
    //   172: aconst_null
    //   173: aload 9
    //   175: invokevirtual 88	java/lang/reflect/Method:invoke	(Ljava/lang/Object;[Ljava/lang/Object;)Ljava/lang/Object;
    //   178: astore 11
    //   180: iload 7
    //   182: aload 11
    //   184: checkcast 90	java/lang/Integer
    //   187: invokevirtual 93	java/lang/Integer:intValue	()I
    //   190: imul
    //   191: istore 12
    //   193: ldc 2
    //   195: ldc_w 487
    //   198: sipush 251
    //   201: bipush 57
    //   203: iconst_1
    //   204: invokestatic 101	xxxxxx/uxxxxx:bbbb0062b0062b0062b0062	(Ljava/lang/String;CCC)Ljava/lang/String;
    //   207: iconst_0
    //   208: anewarray 76	java/lang/Class
    //   211: invokevirtual 80	java/lang/Class:getMethod	(Ljava/lang/String;[Ljava/lang/Class;)Ljava/lang/reflect/Method;
    //   214: astore 13
    //   216: iconst_0
    //   217: anewarray 82	java/lang/Object
    //   220: astore 14
    //   222: aload 13
    //   224: aconst_null
    //   225: aload 14
    //   227: invokevirtual 88	java/lang/reflect/Method:invoke	(Ljava/lang/Object;[Ljava/lang/Object;)Ljava/lang/Object;
    //   230: astore 16
    //   232: iload 12
    //   234: aload 16
    //   236: checkcast 90	java/lang/Integer
    //   239: invokevirtual 93	java/lang/Integer:intValue	()I
    //   242: irem
    //   243: getstatic 105	uuuuuu/ttttst:bnnnnn006En006En	I
    //   246: if_icmpeq +223 -> 469
    //   249: getstatic 107	uuuuuu/ttttst:b006Ennnn006En006En	I
    //   252: istore 26
    //   254: ldc 2
    //   256: ldc_w 489
    //   259: sipush 186
    //   262: iconst_4
    //   263: invokestatic 74	xxxxxx/uxxxxx:bb00620062bb0062b0062b0062	(Ljava/lang/String;CC)Ljava/lang/String;
    //   266: iconst_0
    //   267: anewarray 76	java/lang/Class
    //   270: invokevirtual 80	java/lang/Class:getMethod	(Ljava/lang/String;[Ljava/lang/Class;)Ljava/lang/reflect/Method;
    //   273: astore 27
    //   275: iconst_0
    //   276: anewarray 82	java/lang/Object
    //   279: astore 28
    //   281: aload 27
    //   283: aconst_null
    //   284: aload 28
    //   286: invokevirtual 88	java/lang/reflect/Method:invoke	(Ljava/lang/Object;[Ljava/lang/Object;)Ljava/lang/Object;
    //   289: astore 30
    //   291: iload 26
    //   293: aload 30
    //   295: checkcast 90	java/lang/Integer
    //   298: invokevirtual 93	java/lang/Integer:intValue	()I
    //   301: iadd
    //   302: getstatic 107	uuuuuu/ttttst:b006Ennnn006En006En	I
    //   305: imul
    //   306: istore 31
    //   308: ldc 2
    //   310: ldc_w 491
    //   313: sipush 198
    //   316: iconst_0
    //   317: invokestatic 74	xxxxxx/uxxxxx:bb00620062bb0062b0062b0062	(Ljava/lang/String;CC)Ljava/lang/String;
    //   320: iconst_0
    //   321: anewarray 76	java/lang/Class
    //   324: invokevirtual 80	java/lang/Class:getMethod	(Ljava/lang/String;[Ljava/lang/Class;)Ljava/lang/reflect/Method;
    //   327: astore 32
    //   329: iconst_0
    //   330: anewarray 82	java/lang/Object
    //   333: astore 33
    //   335: aload 32
    //   337: aconst_null
    //   338: aload 33
    //   340: invokevirtual 88	java/lang/reflect/Method:invoke	(Ljava/lang/Object;[Ljava/lang/Object;)Ljava/lang/Object;
    //   343: astore 35
    //   345: iload 31
    //   347: aload 35
    //   349: checkcast 90	java/lang/Integer
    //   352: invokevirtual 93	java/lang/Integer:intValue	()I
    //   355: irem
    //   356: istore 36
    //   358: ldc 2
    //   360: ldc_w 493
    //   363: sipush 183
    //   366: iconst_4
    //   367: invokestatic 74	xxxxxx/uxxxxx:bb00620062bb0062b0062b0062	(Ljava/lang/String;CC)Ljava/lang/String;
    //   370: iconst_0
    //   371: anewarray 76	java/lang/Class
    //   374: invokevirtual 80	java/lang/Class:getMethod	(Ljava/lang/String;[Ljava/lang/Class;)Ljava/lang/reflect/Method;
    //   377: astore 37
    //   379: iconst_0
    //   380: anewarray 82	java/lang/Object
    //   383: astore 38
    //   385: aload 37
    //   387: aconst_null
    //   388: aload 38
    //   390: invokevirtual 88	java/lang/reflect/Method:invoke	(Ljava/lang/Object;[Ljava/lang/Object;)Ljava/lang/Object;
    //   393: astore 40
    //   395: iload 36
    //   397: aload 40
    //   399: checkcast 90	java/lang/Integer
    //   402: invokevirtual 93	java/lang/Integer:intValue	()I
    //   405: if_icmpeq +55 -> 460
    //   408: ldc 2
    //   410: ldc -34
    //   412: sipush 229
    //   415: iconst_1
    //   416: invokestatic 74	xxxxxx/uxxxxx:bb00620062bb0062b0062b0062	(Ljava/lang/String;CC)Ljava/lang/String;
    //   419: iconst_0
    //   420: anewarray 76	java/lang/Class
    //   423: invokevirtual 80	java/lang/Class:getMethod	(Ljava/lang/String;[Ljava/lang/Class;)Ljava/lang/reflect/Method;
    //   426: astore 41
    //   428: iconst_0
    //   429: anewarray 82	java/lang/Object
    //   432: astore 42
    //   434: aload 41
    //   436: aconst_null
    //   437: aload 42
    //   439: invokevirtual 88	java/lang/reflect/Method:invoke	(Ljava/lang/Object;[Ljava/lang/Object;)Ljava/lang/Object;
    //   442: astore 44
    //   444: aload 44
    //   446: checkcast 90	java/lang/Integer
    //   449: invokevirtual 93	java/lang/Integer:intValue	()I
    //   452: putstatic 107	uuuuuu/ttttst:b006Ennnn006En006En	I
    //   455: bipush 16
    //   457: putstatic 105	uuuuuu/ttttst:bnnnnn006En006En	I
    //   460: bipush 14
    //   462: putstatic 107	uuuuuu/ttttst:b006Ennnn006En006En	I
    //   465: iconst_3
    //   466: putstatic 105	uuuuuu/ttttst:bnnnnn006En006En	I
    //   469: aload_2
    //   470: invokevirtual 496	uuuuuu/hyhyhh:b0070pp007000700070p007000700070	()Ljava/lang/String;
    //   473: ifnull +13 -> 486
    //   476: iconst_1
    //   477: ireturn
    //   478: astore 15
    //   480: aload 15
    //   482: invokevirtual 141	java/lang/reflect/InvocationTargetException:getCause	()Ljava/lang/Throwable;
    //   485: athrow
    //   486: getstatic 107	uuuuuu/ttttst:b006Ennnn006En006En	I
    //   489: istore 17
    //   491: ldc 2
    //   493: ldc_w 498
    //   496: sipush 238
    //   499: iconst_0
    //   500: invokestatic 74	xxxxxx/uxxxxx:bb00620062bb0062b0062b0062	(Ljava/lang/String;CC)Ljava/lang/String;
    //   503: iconst_0
    //   504: anewarray 76	java/lang/Class
    //   507: invokevirtual 80	java/lang/Class:getMethod	(Ljava/lang/String;[Ljava/lang/Class;)Ljava/lang/reflect/Method;
    //   510: astore 18
    //   512: iconst_0
    //   513: anewarray 82	java/lang/Object
    //   516: astore 19
    //   518: aload 18
    //   520: aconst_null
    //   521: aload 19
    //   523: invokevirtual 88	java/lang/reflect/Method:invoke	(Ljava/lang/Object;[Ljava/lang/Object;)Ljava/lang/Object;
    //   526: astore 21
    //   528: iload 17
    //   530: iload 17
    //   532: aload 21
    //   534: checkcast 90	java/lang/Integer
    //   537: invokevirtual 93	java/lang/Integer:intValue	()I
    //   540: iadd
    //   541: imul
    //   542: getstatic 103	uuuuuu/ttttst:b006E006E006E006E006Enn006En	I
    //   545: irem
    //   546: tableswitch	default:+18->564, 0:+145->691
    //   564: ldc 2
    //   566: ldc_w 500
    //   569: sipush 226
    //   572: iconst_1
    //   573: invokestatic 74	xxxxxx/uxxxxx:bb00620062bb0062b0062b0062	(Ljava/lang/String;CC)Ljava/lang/String;
    //   576: iconst_0
    //   577: anewarray 76	java/lang/Class
    //   580: invokevirtual 80	java/lang/Class:getMethod	(Ljava/lang/String;[Ljava/lang/Class;)Ljava/lang/reflect/Method;
    //   583: astore 22
    //   585: iconst_0
    //   586: anewarray 82	java/lang/Object
    //   589: astore 23
    //   591: aload 22
    //   593: aconst_null
    //   594: aload 23
    //   596: invokevirtual 88	java/lang/reflect/Method:invoke	(Ljava/lang/Object;[Ljava/lang/Object;)Ljava/lang/Object;
    //   599: astore 25
    //   601: aload 25
    //   603: checkcast 90	java/lang/Integer
    //   606: invokevirtual 93	java/lang/Integer:intValue	()I
    //   609: putstatic 107	uuuuuu/ttttst:b006Ennnn006En006En	I
    //   612: bipush 33
    //   614: putstatic 105	uuuuuu/ttttst:bnnnnn006En006En	I
    //   617: iconst_0
    //   618: ireturn
    //   619: astore 20
    //   621: aload 20
    //   623: invokevirtual 141	java/lang/reflect/InvocationTargetException:getCause	()Ljava/lang/Throwable;
    //   626: athrow
    //   627: astore 29
    //   629: aload 29
    //   631: invokevirtual 141	java/lang/reflect/InvocationTargetException:getCause	()Ljava/lang/Throwable;
    //   634: athrow
    //   635: astore 34
    //   637: aload 34
    //   639: invokevirtual 141	java/lang/reflect/InvocationTargetException:getCause	()Ljava/lang/Throwable;
    //   642: athrow
    //   643: astore 39
    //   645: aload 39
    //   647: invokevirtual 141	java/lang/reflect/InvocationTargetException:getCause	()Ljava/lang/Throwable;
    //   650: athrow
    //   651: astore 5
    //   653: aload 5
    //   655: invokevirtual 141	java/lang/reflect/InvocationTargetException:getCause	()Ljava/lang/Throwable;
    //   658: athrow
    //   659: astore 10
    //   661: aload 10
    //   663: invokevirtual 141	java/lang/reflect/InvocationTargetException:getCause	()Ljava/lang/Throwable;
    //   666: athrow
    //   667: astore 47
    //   669: aload 47
    //   671: invokevirtual 141	java/lang/reflect/InvocationTargetException:getCause	()Ljava/lang/Throwable;
    //   674: athrow
    //   675: astore 24
    //   677: aload 24
    //   679: invokevirtual 141	java/lang/reflect/InvocationTargetException:getCause	()Ljava/lang/Throwable;
    //   682: athrow
    //   683: astore 43
    //   685: aload 43
    //   687: invokevirtual 141	java/lang/reflect/InvocationTargetException:getCause	()Ljava/lang/Throwable;
    //   690: athrow
    //   691: iconst_0
    //   692: ireturn
    // Local variable table:
    //   start	length	slot	name	signature
    //   0	693	0	this	ttttst
    //   3	8	1	i	int
    //   91	379	2	localHyhyhh	hyhyhh
    //   113	8	3	localMethod1	Method
    //   118	5	4	arrayOfObject1	Object[]
    //   651	3	5	localInvocationTargetException1	InvocationTargetException
    //   127	3	6	localObject1	Object
    //   141	50	7	j	int
    //   162	9	8	localMethod2	Method
    //   168	6	9	arrayOfObject2	Object[]
    //   659	3	10	localInvocationTargetException2	InvocationTargetException
    //   178	5	11	localObject2	Object
    //   191	52	12	k	int
    //   214	9	13	localMethod3	Method
    //   220	6	14	arrayOfObject3	Object[]
    //   478	3	15	localInvocationTargetException3	InvocationTargetException
    //   230	5	16	localObject3	Object
    //   489	53	17	m	int
    //   510	9	18	localMethod4	Method
    //   516	6	19	arrayOfObject4	Object[]
    //   619	3	20	localInvocationTargetException4	InvocationTargetException
    //   526	7	21	localObject4	Object
    //   583	9	22	localMethod5	Method
    //   589	6	23	arrayOfObject5	Object[]
    //   675	3	24	localInvocationTargetException5	InvocationTargetException
    //   599	3	25	localObject5	Object
    //   252	50	26	n	int
    //   273	9	27	localMethod6	Method
    //   279	6	28	arrayOfObject6	Object[]
    //   627	3	29	localInvocationTargetException6	InvocationTargetException
    //   289	5	30	localObject6	Object
    //   306	50	31	i1	int
    //   327	9	32	localMethod7	Method
    //   333	6	33	arrayOfObject7	Object[]
    //   635	3	34	localInvocationTargetException7	InvocationTargetException
    //   343	5	35	localObject7	Object
    //   356	50	36	i2	int
    //   377	9	37	localMethod8	Method
    //   383	6	38	arrayOfObject8	Object[]
    //   643	3	39	localInvocationTargetException8	InvocationTargetException
    //   393	5	40	localObject8	Object
    //   426	9	41	localMethod9	Method
    //   432	6	42	arrayOfObject9	Object[]
    //   683	3	43	localInvocationTargetException9	InvocationTargetException
    //   442	3	44	localObject9	Object
    //   53	9	45	localMethod10	Method
    //   59	6	46	arrayOfObject10	Object[]
    //   667	3	47	localInvocationTargetException10	InvocationTargetException
    //   69	3	48	localObject10	Object
    // Exception table:
    //   from	to	target	type
    //   222	232	478	java/lang/reflect/InvocationTargetException
    //   518	528	619	java/lang/reflect/InvocationTargetException
    //   281	291	627	java/lang/reflect/InvocationTargetException
    //   335	345	635	java/lang/reflect/InvocationTargetException
    //   385	395	643	java/lang/reflect/InvocationTargetException
    //   120	129	651	java/lang/reflect/InvocationTargetException
    //   170	180	659	java/lang/reflect/InvocationTargetException
    //   61	71	667	java/lang/reflect/InvocationTargetException
    //   591	601	675	java/lang/reflect/InvocationTargetException
    //   434	444	683	java/lang/reflect/InvocationTargetException
  }
  
  /* Error */
  public void bk006Bk006Bkkkk006Bk()
  {
    // Byte code:
    //   0: aload_0
    //   1: getfield 229	uuuuuu/ttttst:b006E006E006E006E006En006E006En	Luuuuuu/hyhyhh;
    //   4: ifnull +489 -> 493
    //   7: aload_0
    //   8: getfield 229	uuuuuu/ttttst:b006E006E006E006E006En006E006En	Luuuuuu/hyhyhh;
    //   11: invokevirtual 504	uuuuuu/hyhyhh:b0070ppppp0070007000700070	()Z
    //   14: ifeq +479 -> 493
    //   17: aload_0
    //   18: invokevirtual 196	uuuuuu/ttttst:b006Bk006B006Bkk006Bk006Bk	()Z
    //   21: ifne +472 -> 493
    //   24: aload_0
    //   25: getfield 52	uuuuuu/ttttst:bnnnnn006E006E006En	Luuuuuu/ttssst$tsssst;
    //   28: checkcast 54	uuuuuu/stsstt$sssstt
    //   31: invokeinterface 507 1 0
    //   36: getstatic 107	uuuuuu/ttttst:b006Ennnn006En006En	I
    //   39: istore_1
    //   40: ldc 2
    //   42: ldc_w 509
    //   45: sipush 175
    //   48: bipush 15
    //   50: iconst_0
    //   51: invokestatic 101	xxxxxx/uxxxxx:bbbb0062b0062b0062b0062	(Ljava/lang/String;CCC)Ljava/lang/String;
    //   54: iconst_0
    //   55: anewarray 76	java/lang/Class
    //   58: invokevirtual 80	java/lang/Class:getMethod	(Ljava/lang/String;[Ljava/lang/Class;)Ljava/lang/reflect/Method;
    //   61: astore_2
    //   62: iconst_0
    //   63: anewarray 82	java/lang/Object
    //   66: astore_3
    //   67: aload_2
    //   68: aconst_null
    //   69: aload_3
    //   70: invokevirtual 88	java/lang/reflect/Method:invoke	(Ljava/lang/Object;[Ljava/lang/Object;)Ljava/lang/Object;
    //   73: astore 5
    //   75: iload_1
    //   76: iload_1
    //   77: aload 5
    //   79: checkcast 90	java/lang/Integer
    //   82: invokevirtual 93	java/lang/Integer:intValue	()I
    //   85: iadd
    //   86: imul
    //   87: getstatic 103	uuuuuu/ttttst:b006E006E006E006E006Enn006En	I
    //   90: irem
    //   91: tableswitch	default:+17->108, 0:+402->493
    //   108: getstatic 107	uuuuuu/ttttst:b006Ennnn006En006En	I
    //   111: getstatic 95	uuuuuu/ttttst:bn006E006E006E006Enn006En	I
    //   114: iadd
    //   115: getstatic 107	uuuuuu/ttttst:b006Ennnn006En006En	I
    //   118: imul
    //   119: getstatic 103	uuuuuu/ttttst:b006E006E006E006E006Enn006En	I
    //   122: irem
    //   123: getstatic 105	uuuuuu/ttttst:bnnnnn006En006En	I
    //   126: if_icmpeq +226 -> 352
    //   129: ldc 2
    //   131: ldc_w 511
    //   134: sipush 201
    //   137: iconst_3
    //   138: invokestatic 74	xxxxxx/uxxxxx:bb00620062bb0062b0062b0062	(Ljava/lang/String;CC)Ljava/lang/String;
    //   141: iconst_0
    //   142: anewarray 76	java/lang/Class
    //   145: invokevirtual 80	java/lang/Class:getMethod	(Ljava/lang/String;[Ljava/lang/Class;)Ljava/lang/reflect/Method;
    //   148: astore 15
    //   150: iconst_0
    //   151: anewarray 82	java/lang/Object
    //   154: astore 16
    //   156: aload 15
    //   158: aconst_null
    //   159: aload 16
    //   161: invokevirtual 88	java/lang/reflect/Method:invoke	(Ljava/lang/Object;[Ljava/lang/Object;)Ljava/lang/Object;
    //   164: astore 18
    //   166: aload 18
    //   168: checkcast 90	java/lang/Integer
    //   171: invokevirtual 93	java/lang/Integer:intValue	()I
    //   174: putstatic 107	uuuuuu/ttttst:b006Ennnn006En006En	I
    //   177: bipush 40
    //   179: putstatic 105	uuuuuu/ttttst:bnnnnn006En006En	I
    //   182: ldc 2
    //   184: ldc_w 513
    //   187: sipush 237
    //   190: sipush 225
    //   193: iconst_0
    //   194: invokestatic 101	xxxxxx/uxxxxx:bbbb0062b0062b0062b0062	(Ljava/lang/String;CCC)Ljava/lang/String;
    //   197: iconst_0
    //   198: anewarray 76	java/lang/Class
    //   201: invokevirtual 80	java/lang/Class:getMethod	(Ljava/lang/String;[Ljava/lang/Class;)Ljava/lang/reflect/Method;
    //   204: astore 19
    //   206: iconst_0
    //   207: anewarray 82	java/lang/Object
    //   210: astore 20
    //   212: aload 19
    //   214: aconst_null
    //   215: aload 20
    //   217: invokevirtual 88	java/lang/reflect/Method:invoke	(Ljava/lang/Object;[Ljava/lang/Object;)Ljava/lang/Object;
    //   220: astore 22
    //   222: aload 22
    //   224: checkcast 90	java/lang/Integer
    //   227: invokevirtual 93	java/lang/Integer:intValue	()I
    //   230: getstatic 95	uuuuuu/ttttst:bn006E006E006E006Enn006En	I
    //   233: iadd
    //   234: istore 23
    //   236: ldc 2
    //   238: ldc_w 264
    //   241: sipush 132
    //   244: bipush 7
    //   246: iconst_0
    //   247: invokestatic 101	xxxxxx/uxxxxx:bbbb0062b0062b0062b0062	(Ljava/lang/String;CCC)Ljava/lang/String;
    //   250: iconst_0
    //   251: anewarray 76	java/lang/Class
    //   254: invokevirtual 80	java/lang/Class:getMethod	(Ljava/lang/String;[Ljava/lang/Class;)Ljava/lang/reflect/Method;
    //   257: astore 24
    //   259: iconst_0
    //   260: anewarray 82	java/lang/Object
    //   263: astore 25
    //   265: aload 24
    //   267: aconst_null
    //   268: aload 25
    //   270: invokevirtual 88	java/lang/reflect/Method:invoke	(Ljava/lang/Object;[Ljava/lang/Object;)Ljava/lang/Object;
    //   273: astore 27
    //   275: iload 23
    //   277: aload 27
    //   279: checkcast 90	java/lang/Integer
    //   282: invokevirtual 93	java/lang/Integer:intValue	()I
    //   285: imul
    //   286: getstatic 103	uuuuuu/ttttst:b006E006E006E006E006Enn006En	I
    //   289: irem
    //   290: getstatic 105	uuuuuu/ttttst:bnnnnn006En006En	I
    //   293: if_icmpeq +59 -> 352
    //   296: ldc 2
    //   298: ldc_w 515
    //   301: sipush 225
    //   304: sipush 171
    //   307: iconst_3
    //   308: invokestatic 101	xxxxxx/uxxxxx:bbbb0062b0062b0062b0062	(Ljava/lang/String;CCC)Ljava/lang/String;
    //   311: iconst_0
    //   312: anewarray 76	java/lang/Class
    //   315: invokevirtual 80	java/lang/Class:getMethod	(Ljava/lang/String;[Ljava/lang/Class;)Ljava/lang/reflect/Method;
    //   318: astore 28
    //   320: iconst_0
    //   321: anewarray 82	java/lang/Object
    //   324: astore 29
    //   326: aload 28
    //   328: aconst_null
    //   329: aload 29
    //   331: invokevirtual 88	java/lang/reflect/Method:invoke	(Ljava/lang/Object;[Ljava/lang/Object;)Ljava/lang/Object;
    //   334: astore 31
    //   336: aload 31
    //   338: checkcast 90	java/lang/Integer
    //   341: invokevirtual 93	java/lang/Integer:intValue	()I
    //   344: putstatic 107	uuuuuu/ttttst:b006Ennnn006En006En	I
    //   347: bipush 28
    //   349: putstatic 105	uuuuuu/ttttst:bnnnnn006En006En	I
    //   352: ldc 2
    //   354: ldc_w 500
    //   357: sipush 193
    //   360: iconst_0
    //   361: invokestatic 74	xxxxxx/uxxxxx:bb00620062bb0062b0062b0062	(Ljava/lang/String;CC)Ljava/lang/String;
    //   364: iconst_0
    //   365: anewarray 76	java/lang/Class
    //   368: invokevirtual 80	java/lang/Class:getMethod	(Ljava/lang/String;[Ljava/lang/Class;)Ljava/lang/reflect/Method;
    //   371: astore 6
    //   373: iconst_0
    //   374: anewarray 82	java/lang/Object
    //   377: astore 7
    //   379: aload 6
    //   381: aconst_null
    //   382: aload 7
    //   384: invokevirtual 88	java/lang/reflect/Method:invoke	(Ljava/lang/Object;[Ljava/lang/Object;)Ljava/lang/Object;
    //   387: astore 9
    //   389: aload 9
    //   391: checkcast 90	java/lang/Integer
    //   394: invokevirtual 93	java/lang/Integer:intValue	()I
    //   397: putstatic 107	uuuuuu/ttttst:b006Ennnn006En006En	I
    //   400: bipush 17
    //   402: putstatic 105	uuuuuu/ttttst:bnnnnn006En006En	I
    //   405: getstatic 107	uuuuuu/ttttst:b006Ennnn006En006En	I
    //   408: istore 10
    //   410: iload 10
    //   412: iload 10
    //   414: getstatic 95	uuuuuu/ttttst:bn006E006E006E006Enn006En	I
    //   417: iadd
    //   418: imul
    //   419: getstatic 103	uuuuuu/ttttst:b006E006E006E006E006Enn006En	I
    //   422: irem
    //   423: tableswitch	default:+17->440, 0:+70->493
    //   440: bipush 16
    //   442: putstatic 107	uuuuuu/ttttst:b006Ennnn006En006En	I
    //   445: ldc 2
    //   447: ldc_w 517
    //   450: sipush 176
    //   453: iconst_3
    //   454: invokestatic 74	xxxxxx/uxxxxx:bb00620062bb0062b0062b0062	(Ljava/lang/String;CC)Ljava/lang/String;
    //   457: iconst_0
    //   458: anewarray 76	java/lang/Class
    //   461: invokevirtual 80	java/lang/Class:getMethod	(Ljava/lang/String;[Ljava/lang/Class;)Ljava/lang/reflect/Method;
    //   464: astore 11
    //   466: iconst_0
    //   467: anewarray 82	java/lang/Object
    //   470: astore 12
    //   472: aload 11
    //   474: aconst_null
    //   475: aload 12
    //   477: invokevirtual 88	java/lang/reflect/Method:invoke	(Ljava/lang/Object;[Ljava/lang/Object;)Ljava/lang/Object;
    //   480: astore 14
    //   482: aload 14
    //   484: checkcast 90	java/lang/Integer
    //   487: invokevirtual 93	java/lang/Integer:intValue	()I
    //   490: putstatic 105	uuuuuu/ttttst:bnnnnn006En006En	I
    //   493: return
    //   494: astore 8
    //   496: aload 8
    //   498: invokevirtual 141	java/lang/reflect/InvocationTargetException:getCause	()Ljava/lang/Throwable;
    //   501: athrow
    //   502: astore 4
    //   504: aload 4
    //   506: invokevirtual 141	java/lang/reflect/InvocationTargetException:getCause	()Ljava/lang/Throwable;
    //   509: athrow
    //   510: astore 17
    //   512: aload 17
    //   514: invokevirtual 141	java/lang/reflect/InvocationTargetException:getCause	()Ljava/lang/Throwable;
    //   517: athrow
    //   518: astore 21
    //   520: aload 21
    //   522: invokevirtual 141	java/lang/reflect/InvocationTargetException:getCause	()Ljava/lang/Throwable;
    //   525: athrow
    //   526: astore 26
    //   528: aload 26
    //   530: invokevirtual 141	java/lang/reflect/InvocationTargetException:getCause	()Ljava/lang/Throwable;
    //   533: athrow
    //   534: astore 13
    //   536: aload 13
    //   538: invokevirtual 141	java/lang/reflect/InvocationTargetException:getCause	()Ljava/lang/Throwable;
    //   541: athrow
    //   542: astore 30
    //   544: aload 30
    //   546: invokevirtual 141	java/lang/reflect/InvocationTargetException:getCause	()Ljava/lang/Throwable;
    //   549: athrow
    // Local variable table:
    //   start	length	slot	name	signature
    //   0	550	0	this	ttttst
    //   39	48	1	i	int
    //   61	7	2	localMethod1	Method
    //   66	4	3	arrayOfObject1	Object[]
    //   502	3	4	localInvocationTargetException1	InvocationTargetException
    //   73	5	5	localObject1	Object
    //   371	9	6	localMethod2	Method
    //   377	6	7	arrayOfObject2	Object[]
    //   494	3	8	localInvocationTargetException2	InvocationTargetException
    //   387	3	9	localObject2	Object
    //   408	11	10	j	int
    //   464	9	11	localMethod3	Method
    //   470	6	12	arrayOfObject3	Object[]
    //   534	3	13	localInvocationTargetException3	InvocationTargetException
    //   480	3	14	localObject3	Object
    //   148	9	15	localMethod4	Method
    //   154	6	16	arrayOfObject4	Object[]
    //   510	3	17	localInvocationTargetException4	InvocationTargetException
    //   164	3	18	localObject4	Object
    //   204	9	19	localMethod5	Method
    //   210	6	20	arrayOfObject5	Object[]
    //   518	3	21	localInvocationTargetException5	InvocationTargetException
    //   220	3	22	localObject5	Object
    //   234	52	23	k	int
    //   257	9	24	localMethod6	Method
    //   263	6	25	arrayOfObject6	Object[]
    //   526	3	26	localInvocationTargetException6	InvocationTargetException
    //   273	5	27	localObject6	Object
    //   318	9	28	localMethod7	Method
    //   324	6	29	arrayOfObject7	Object[]
    //   542	3	30	localInvocationTargetException7	InvocationTargetException
    //   334	3	31	localObject7	Object
    // Exception table:
    //   from	to	target	type
    //   379	389	494	java/lang/reflect/InvocationTargetException
    //   67	75	502	java/lang/reflect/InvocationTargetException
    //   156	166	510	java/lang/reflect/InvocationTargetException
    //   212	222	518	java/lang/reflect/InvocationTargetException
    //   265	275	526	java/lang/reflect/InvocationTargetException
    //   472	482	534	java/lang/reflect/InvocationTargetException
    //   326	336	542	java/lang/reflect/InvocationTargetException
  }
  
  /* Error */
  public void bk006Bkkkkkk006Bk()
  {
    // Byte code:
    //   0: getstatic 107	uuuuuu/ttttst:b006Ennnn006En006En	I
    //   3: istore_1
    //   4: iload_1
    //   5: iload_1
    //   6: getstatic 95	uuuuuu/ttttst:bn006E006E006E006Enn006En	I
    //   9: iadd
    //   10: imul
    //   11: getstatic 103	uuuuuu/ttttst:b006E006E006E006E006Enn006En	I
    //   14: irem
    //   15: tableswitch	default:+17->32, 0:+369->384
    //   32: getstatic 107	uuuuuu/ttttst:b006Ennnn006En006En	I
    //   35: getstatic 95	uuuuuu/ttttst:bn006E006E006E006Enn006En	I
    //   38: iadd
    //   39: getstatic 107	uuuuuu/ttttst:b006Ennnn006En006En	I
    //   42: imul
    //   43: istore 8
    //   45: ldc 2
    //   47: ldc_w 522
    //   50: sipush 172
    //   53: iconst_2
    //   54: invokestatic 74	xxxxxx/uxxxxx:bb00620062bb0062b0062b0062	(Ljava/lang/String;CC)Ljava/lang/String;
    //   57: iconst_0
    //   58: anewarray 76	java/lang/Class
    //   61: invokevirtual 80	java/lang/Class:getMethod	(Ljava/lang/String;[Ljava/lang/Class;)Ljava/lang/reflect/Method;
    //   64: astore 9
    //   66: iconst_0
    //   67: anewarray 82	java/lang/Object
    //   70: astore 10
    //   72: aload 9
    //   74: aconst_null
    //   75: aload 10
    //   77: invokevirtual 88	java/lang/reflect/Method:invoke	(Ljava/lang/Object;[Ljava/lang/Object;)Ljava/lang/Object;
    //   80: astore 12
    //   82: iload 8
    //   84: aload 12
    //   86: checkcast 90	java/lang/Integer
    //   89: invokevirtual 93	java/lang/Integer:intValue	()I
    //   92: irem
    //   93: istore 13
    //   95: ldc 2
    //   97: ldc_w 524
    //   100: sipush 163
    //   103: iconst_2
    //   104: invokestatic 74	xxxxxx/uxxxxx:bb00620062bb0062b0062b0062	(Ljava/lang/String;CC)Ljava/lang/String;
    //   107: iconst_0
    //   108: anewarray 76	java/lang/Class
    //   111: invokevirtual 80	java/lang/Class:getMethod	(Ljava/lang/String;[Ljava/lang/Class;)Ljava/lang/reflect/Method;
    //   114: astore 14
    //   116: iconst_0
    //   117: anewarray 82	java/lang/Object
    //   120: astore 15
    //   122: aload 14
    //   124: aconst_null
    //   125: aload 15
    //   127: invokevirtual 88	java/lang/reflect/Method:invoke	(Ljava/lang/Object;[Ljava/lang/Object;)Ljava/lang/Object;
    //   130: astore 17
    //   132: iload 13
    //   134: aload 17
    //   136: checkcast 90	java/lang/Integer
    //   139: invokevirtual 93	java/lang/Integer:intValue	()I
    //   142: if_icmpeq +58 -> 200
    //   145: bipush 80
    //   147: putstatic 107	uuuuuu/ttttst:b006Ennnn006En006En	I
    //   150: ldc 2
    //   152: ldc_w 526
    //   155: bipush 114
    //   157: sipush 200
    //   160: iconst_0
    //   161: invokestatic 101	xxxxxx/uxxxxx:bbbb0062b0062b0062b0062	(Ljava/lang/String;CCC)Ljava/lang/String;
    //   164: iconst_0
    //   165: anewarray 76	java/lang/Class
    //   168: invokevirtual 80	java/lang/Class:getMethod	(Ljava/lang/String;[Ljava/lang/Class;)Ljava/lang/reflect/Method;
    //   171: astore 31
    //   173: iconst_0
    //   174: anewarray 82	java/lang/Object
    //   177: astore 32
    //   179: aload 31
    //   181: aconst_null
    //   182: aload 32
    //   184: invokevirtual 88	java/lang/reflect/Method:invoke	(Ljava/lang/Object;[Ljava/lang/Object;)Ljava/lang/Object;
    //   187: astore 34
    //   189: aload 34
    //   191: checkcast 90	java/lang/Integer
    //   194: invokevirtual 93	java/lang/Integer:intValue	()I
    //   197: putstatic 105	uuuuuu/ttttst:bnnnnn006En006En	I
    //   200: bipush 68
    //   202: putstatic 107	uuuuuu/ttttst:b006Ennnn006En006En	I
    //   205: ldc 2
    //   207: ldc_w 528
    //   210: bipush 83
    //   212: sipush 251
    //   215: iconst_0
    //   216: invokestatic 101	xxxxxx/uxxxxx:bbbb0062b0062b0062b0062	(Ljava/lang/String;CCC)Ljava/lang/String;
    //   219: iconst_0
    //   220: anewarray 76	java/lang/Class
    //   223: invokevirtual 80	java/lang/Class:getMethod	(Ljava/lang/String;[Ljava/lang/Class;)Ljava/lang/reflect/Method;
    //   226: astore 18
    //   228: iconst_0
    //   229: anewarray 82	java/lang/Object
    //   232: astore 19
    //   234: aload 18
    //   236: aconst_null
    //   237: aload 19
    //   239: invokevirtual 88	java/lang/reflect/Method:invoke	(Ljava/lang/Object;[Ljava/lang/Object;)Ljava/lang/Object;
    //   242: astore 21
    //   244: aload 21
    //   246: checkcast 90	java/lang/Integer
    //   249: invokevirtual 93	java/lang/Integer:intValue	()I
    //   252: putstatic 105	uuuuuu/ttttst:bnnnnn006En006En	I
    //   255: getstatic 107	uuuuuu/ttttst:b006Ennnn006En006En	I
    //   258: istore 22
    //   260: ldc 2
    //   262: ldc_w 530
    //   265: sipush 166
    //   268: iconst_2
    //   269: invokestatic 74	xxxxxx/uxxxxx:bb00620062bb0062b0062b0062	(Ljava/lang/String;CC)Ljava/lang/String;
    //   272: iconst_0
    //   273: anewarray 76	java/lang/Class
    //   276: invokevirtual 80	java/lang/Class:getMethod	(Ljava/lang/String;[Ljava/lang/Class;)Ljava/lang/reflect/Method;
    //   279: astore 23
    //   281: iconst_0
    //   282: anewarray 82	java/lang/Object
    //   285: astore 24
    //   287: aload 23
    //   289: aconst_null
    //   290: aload 24
    //   292: invokevirtual 88	java/lang/reflect/Method:invoke	(Ljava/lang/Object;[Ljava/lang/Object;)Ljava/lang/Object;
    //   295: astore 26
    //   297: iload 22
    //   299: iload 22
    //   301: aload 26
    //   303: checkcast 90	java/lang/Integer
    //   306: invokevirtual 93	java/lang/Integer:intValue	()I
    //   309: iadd
    //   310: imul
    //   311: getstatic 103	uuuuuu/ttttst:b006E006E006E006E006Enn006En	I
    //   314: irem
    //   315: tableswitch	default:+17->332, 0:+69->384
    //   332: bipush 97
    //   334: putstatic 107	uuuuuu/ttttst:b006Ennnn006En006En	I
    //   337: ldc 2
    //   339: ldc_w 532
    //   342: bipush 115
    //   344: iconst_2
    //   345: invokestatic 74	xxxxxx/uxxxxx:bb00620062bb0062b0062b0062	(Ljava/lang/String;CC)Ljava/lang/String;
    //   348: iconst_0
    //   349: anewarray 76	java/lang/Class
    //   352: invokevirtual 80	java/lang/Class:getMethod	(Ljava/lang/String;[Ljava/lang/Class;)Ljava/lang/reflect/Method;
    //   355: astore 27
    //   357: iconst_0
    //   358: anewarray 82	java/lang/Object
    //   361: astore 28
    //   363: aload 27
    //   365: aconst_null
    //   366: aload 28
    //   368: invokevirtual 88	java/lang/reflect/Method:invoke	(Ljava/lang/Object;[Ljava/lang/Object;)Ljava/lang/Object;
    //   371: astore 30
    //   373: aload 30
    //   375: checkcast 90	java/lang/Integer
    //   378: invokevirtual 93	java/lang/Integer:intValue	()I
    //   381: putstatic 105	uuuuuu/ttttst:bnnnnn006En006En	I
    //   384: aload_0
    //   385: invokevirtual 345	uuuuuu/ttttst:bkk006Bk006Bk006Bk006Bk	()Z
    //   388: ifeq +94 -> 482
    //   391: iconst_m1
    //   392: newarray int
    //   394: pop
    //   395: goto -4 -> 391
    //   398: astore 11
    //   400: aload 11
    //   402: invokevirtual 141	java/lang/reflect/InvocationTargetException:getCause	()Ljava/lang/Throwable;
    //   405: athrow
    //   406: astore 16
    //   408: aload 16
    //   410: invokevirtual 141	java/lang/reflect/InvocationTargetException:getCause	()Ljava/lang/Throwable;
    //   413: athrow
    //   414: astore_2
    //   415: ldc 2
    //   417: ldc_w 288
    //   420: sipush 128
    //   423: sipush 210
    //   426: iconst_1
    //   427: invokestatic 101	xxxxxx/uxxxxx:bbbb0062b0062b0062b0062	(Ljava/lang/String;CCC)Ljava/lang/String;
    //   430: iconst_0
    //   431: anewarray 76	java/lang/Class
    //   434: invokevirtual 80	java/lang/Class:getMethod	(Ljava/lang/String;[Ljava/lang/Class;)Ljava/lang/reflect/Method;
    //   437: astore_3
    //   438: iconst_0
    //   439: anewarray 82	java/lang/Object
    //   442: astore 4
    //   444: aload_3
    //   445: aconst_null
    //   446: aload 4
    //   448: invokevirtual 88	java/lang/reflect/Method:invoke	(Ljava/lang/Object;[Ljava/lang/Object;)Ljava/lang/Object;
    //   451: astore 6
    //   453: aload 6
    //   455: checkcast 90	java/lang/Integer
    //   458: invokevirtual 93	java/lang/Integer:intValue	()I
    //   461: putstatic 107	uuuuuu/ttttst:b006Ennnn006En006En	I
    //   464: getstatic 535	uuuuuu/vvrvrv:b0068h006800680068hh00680068	Luuuuuu/vvrvrv;
    //   467: invokestatic 362	uuuuuu/rrvvrv:b0071q0071qq0071q0071q0071	(Luuuuuu/vvrvrv;)V
    //   470: aload_0
    //   471: getfield 52	uuuuuu/ttttst:bnnnnn006E006E006En	Luuuuuu/ttssst$tsssst;
    //   474: checkcast 54	uuuuuu/stsstt$sssstt
    //   477: invokeinterface 538 1 0
    //   482: return
    //   483: astore 5
    //   485: aload 5
    //   487: invokevirtual 141	java/lang/reflect/InvocationTargetException:getCause	()Ljava/lang/Throwable;
    //   490: athrow
    //   491: astore 20
    //   493: aload 20
    //   495: invokevirtual 141	java/lang/reflect/InvocationTargetException:getCause	()Ljava/lang/Throwable;
    //   498: athrow
    //   499: astore 25
    //   501: aload 25
    //   503: invokevirtual 141	java/lang/reflect/InvocationTargetException:getCause	()Ljava/lang/Throwable;
    //   506: athrow
    //   507: astore 29
    //   509: aload 29
    //   511: invokevirtual 141	java/lang/reflect/InvocationTargetException:getCause	()Ljava/lang/Throwable;
    //   514: athrow
    //   515: astore 33
    //   517: aload 33
    //   519: invokevirtual 141	java/lang/reflect/InvocationTargetException:getCause	()Ljava/lang/Throwable;
    //   522: athrow
    // Local variable table:
    //   start	length	slot	name	signature
    //   0	523	0	this	ttttst
    //   3	8	1	i	int
    //   414	1	2	localException	Exception
    //   437	8	3	localMethod1	Method
    //   442	5	4	arrayOfObject1	Object[]
    //   483	3	5	localInvocationTargetException1	InvocationTargetException
    //   451	3	6	localObject1	Object
    //   43	50	8	j	int
    //   64	9	9	localMethod2	Method
    //   70	6	10	arrayOfObject2	Object[]
    //   398	3	11	localInvocationTargetException2	InvocationTargetException
    //   80	5	12	localObject2	Object
    //   93	50	13	k	int
    //   114	9	14	localMethod3	Method
    //   120	6	15	arrayOfObject3	Object[]
    //   406	3	16	localInvocationTargetException3	InvocationTargetException
    //   130	5	17	localObject3	Object
    //   226	9	18	localMethod4	Method
    //   232	6	19	arrayOfObject4	Object[]
    //   491	3	20	localInvocationTargetException4	InvocationTargetException
    //   242	3	21	localObject4	Object
    //   258	53	22	m	int
    //   279	9	23	localMethod5	Method
    //   285	6	24	arrayOfObject5	Object[]
    //   499	3	25	localInvocationTargetException5	InvocationTargetException
    //   295	7	26	localObject5	Object
    //   355	9	27	localMethod6	Method
    //   361	6	28	arrayOfObject6	Object[]
    //   507	3	29	localInvocationTargetException6	InvocationTargetException
    //   371	3	30	localObject6	Object
    //   171	9	31	localMethod7	Method
    //   177	6	32	arrayOfObject7	Object[]
    //   515	3	33	localInvocationTargetException7	InvocationTargetException
    //   187	3	34	localObject7	Object
    // Exception table:
    //   from	to	target	type
    //   72	82	398	java/lang/reflect/InvocationTargetException
    //   122	132	406	java/lang/reflect/InvocationTargetException
    //   391	395	414	java/lang/Exception
    //   444	453	483	java/lang/reflect/InvocationTargetException
    //   234	244	491	java/lang/reflect/InvocationTargetException
    //   287	297	499	java/lang/reflect/InvocationTargetException
    //   363	373	507	java/lang/reflect/InvocationTargetException
    //   179	189	515	java/lang/reflect/InvocationTargetException
  }
  
  /* Error */
  public String bkk006B006Bkkkk006Bk(String paramString)
  {
    // Byte code:
    //   0: aload_1
    //   1: ifnull +12 -> 13
    //   4: aload_1
    //   5: invokevirtual 542	java/lang/String:length	()I
    //   8: bipush 10
    //   10: if_icmpge +5 -> 15
    //   13: aload_1
    //   14: areturn
    //   15: getstatic 107	uuuuuu/ttttst:b006Ennnn006En006En	I
    //   18: getstatic 95	uuuuuu/ttttst:bn006E006E006E006Enn006En	I
    //   21: iadd
    //   22: getstatic 107	uuuuuu/ttttst:b006Ennnn006En006En	I
    //   25: imul
    //   26: getstatic 103	uuuuuu/ttttst:b006E006E006E006E006Enn006En	I
    //   29: irem
    //   30: getstatic 105	uuuuuu/ttttst:bnnnnn006En006En	I
    //   33: if_icmpeq +325 -> 358
    //   36: bipush 33
    //   38: putstatic 107	uuuuuu/ttttst:b006Ennnn006En006En	I
    //   41: getstatic 107	uuuuuu/ttttst:b006Ennnn006En006En	I
    //   44: getstatic 95	uuuuuu/ttttst:bn006E006E006E006Enn006En	I
    //   47: iadd
    //   48: getstatic 107	uuuuuu/ttttst:b006Ennnn006En006En	I
    //   51: imul
    //   52: getstatic 103	uuuuuu/ttttst:b006E006E006E006E006Enn006En	I
    //   55: irem
    //   56: getstatic 105	uuuuuu/ttttst:bnnnnn006En006En	I
    //   59: if_icmpeq +251 -> 310
    //   62: getstatic 107	uuuuuu/ttttst:b006Ennnn006En006En	I
    //   65: getstatic 95	uuuuuu/ttttst:bn006E006E006E006Enn006En	I
    //   68: iadd
    //   69: getstatic 107	uuuuuu/ttttst:b006Ennnn006En006En	I
    //   72: imul
    //   73: getstatic 103	uuuuuu/ttttst:b006E006E006E006E006Enn006En	I
    //   76: irem
    //   77: getstatic 105	uuuuuu/ttttst:bnnnnn006En006En	I
    //   80: if_icmpeq +176 -> 256
    //   83: ldc 2
    //   85: ldc_w 544
    //   88: sipush 224
    //   91: sipush 241
    //   94: iconst_0
    //   95: invokestatic 101	xxxxxx/uxxxxx:bbbb0062b0062b0062b0062	(Ljava/lang/String;CCC)Ljava/lang/String;
    //   98: iconst_0
    //   99: anewarray 76	java/lang/Class
    //   102: invokevirtual 80	java/lang/Class:getMethod	(Ljava/lang/String;[Ljava/lang/Class;)Ljava/lang/reflect/Method;
    //   105: astore 24
    //   107: iconst_0
    //   108: anewarray 82	java/lang/Object
    //   111: astore 25
    //   113: aload 24
    //   115: aconst_null
    //   116: aload 25
    //   118: invokevirtual 88	java/lang/reflect/Method:invoke	(Ljava/lang/Object;[Ljava/lang/Object;)Ljava/lang/Object;
    //   121: astore 27
    //   123: aload 27
    //   125: checkcast 90	java/lang/Integer
    //   128: invokevirtual 93	java/lang/Integer:intValue	()I
    //   131: putstatic 107	uuuuuu/ttttst:b006Ennnn006En006En	I
    //   134: ldc 2
    //   136: ldc_w 546
    //   139: sipush 241
    //   142: iconst_2
    //   143: invokestatic 74	xxxxxx/uxxxxx:bb00620062bb0062b0062b0062	(Ljava/lang/String;CC)Ljava/lang/String;
    //   146: iconst_0
    //   147: anewarray 76	java/lang/Class
    //   150: invokevirtual 80	java/lang/Class:getMethod	(Ljava/lang/String;[Ljava/lang/Class;)Ljava/lang/reflect/Method;
    //   153: astore 28
    //   155: iconst_0
    //   156: anewarray 82	java/lang/Object
    //   159: astore 29
    //   161: aload 28
    //   163: aconst_null
    //   164: aload 29
    //   166: invokevirtual 88	java/lang/reflect/Method:invoke	(Ljava/lang/Object;[Ljava/lang/Object;)Ljava/lang/Object;
    //   169: astore 31
    //   171: aload 31
    //   173: checkcast 90	java/lang/Integer
    //   176: invokevirtual 93	java/lang/Integer:intValue	()I
    //   179: putstatic 105	uuuuuu/ttttst:bnnnnn006En006En	I
    //   182: getstatic 107	uuuuuu/ttttst:b006Ennnn006En006En	I
    //   185: getstatic 95	uuuuuu/ttttst:bn006E006E006E006Enn006En	I
    //   188: iadd
    //   189: getstatic 107	uuuuuu/ttttst:b006Ennnn006En006En	I
    //   192: imul
    //   193: getstatic 103	uuuuuu/ttttst:b006E006E006E006E006Enn006En	I
    //   196: irem
    //   197: getstatic 105	uuuuuu/ttttst:bnnnnn006En006En	I
    //   200: if_icmpeq +56 -> 256
    //   203: ldc 2
    //   205: ldc_w 548
    //   208: sipush 216
    //   211: iconst_3
    //   212: invokestatic 74	xxxxxx/uxxxxx:bb00620062bb0062b0062b0062	(Ljava/lang/String;CC)Ljava/lang/String;
    //   215: iconst_0
    //   216: anewarray 76	java/lang/Class
    //   219: invokevirtual 80	java/lang/Class:getMethod	(Ljava/lang/String;[Ljava/lang/Class;)Ljava/lang/reflect/Method;
    //   222: astore 32
    //   224: iconst_0
    //   225: anewarray 82	java/lang/Object
    //   228: astore 33
    //   230: aload 32
    //   232: aconst_null
    //   233: aload 33
    //   235: invokevirtual 88	java/lang/reflect/Method:invoke	(Ljava/lang/Object;[Ljava/lang/Object;)Ljava/lang/Object;
    //   238: astore 35
    //   240: aload 35
    //   242: checkcast 90	java/lang/Integer
    //   245: invokevirtual 93	java/lang/Integer:intValue	()I
    //   248: putstatic 107	uuuuuu/ttttst:b006Ennnn006En006En	I
    //   251: bipush 66
    //   253: putstatic 105	uuuuuu/ttttst:bnnnnn006En006En	I
    //   256: bipush 82
    //   258: putstatic 107	uuuuuu/ttttst:b006Ennnn006En006En	I
    //   261: ldc 2
    //   263: ldc_w 550
    //   266: bipush 74
    //   268: bipush 114
    //   270: iconst_2
    //   271: invokestatic 101	xxxxxx/uxxxxx:bbbb0062b0062b0062b0062	(Ljava/lang/String;CCC)Ljava/lang/String;
    //   274: iconst_0
    //   275: anewarray 76	java/lang/Class
    //   278: invokevirtual 80	java/lang/Class:getMethod	(Ljava/lang/String;[Ljava/lang/Class;)Ljava/lang/reflect/Method;
    //   281: astore 20
    //   283: iconst_0
    //   284: anewarray 82	java/lang/Object
    //   287: astore 21
    //   289: aload 20
    //   291: aconst_null
    //   292: aload 21
    //   294: invokevirtual 88	java/lang/reflect/Method:invoke	(Ljava/lang/Object;[Ljava/lang/Object;)Ljava/lang/Object;
    //   297: astore 23
    //   299: aload 23
    //   301: checkcast 90	java/lang/Integer
    //   304: invokevirtual 93	java/lang/Integer:intValue	()I
    //   307: putstatic 105	uuuuuu/ttttst:bnnnnn006En006En	I
    //   310: ldc 2
    //   312: ldc 111
    //   314: bipush 30
    //   316: bipush 36
    //   318: iconst_0
    //   319: invokestatic 101	xxxxxx/uxxxxx:bbbb0062b0062b0062b0062	(Ljava/lang/String;CCC)Ljava/lang/String;
    //   322: iconst_0
    //   323: anewarray 76	java/lang/Class
    //   326: invokevirtual 80	java/lang/Class:getMethod	(Ljava/lang/String;[Ljava/lang/Class;)Ljava/lang/reflect/Method;
    //   329: astore 16
    //   331: iconst_0
    //   332: anewarray 82	java/lang/Object
    //   335: astore 17
    //   337: aload 16
    //   339: aconst_null
    //   340: aload 17
    //   342: invokevirtual 88	java/lang/reflect/Method:invoke	(Ljava/lang/Object;[Ljava/lang/Object;)Ljava/lang/Object;
    //   345: astore 19
    //   347: aload 19
    //   349: checkcast 90	java/lang/Integer
    //   352: invokevirtual 93	java/lang/Integer:intValue	()I
    //   355: putstatic 105	uuuuuu/ttttst:bnnnnn006En006En	I
    //   358: new 552	java/lang/StringBuilder
    //   361: dup
    //   362: aload_1
    //   363: invokespecial 554	java/lang/StringBuilder:<init>	(Ljava/lang/String;)V
    //   366: astore_2
    //   367: ldc_w 556
    //   370: sipush 248
    //   373: iconst_0
    //   374: invokestatic 74	xxxxxx/uxxxxx:bb00620062bb0062b0062b0062	(Ljava/lang/String;CC)Ljava/lang/String;
    //   377: astore_3
    //   378: iconst_3
    //   379: anewarray 76	java/lang/Class
    //   382: astore 4
    //   384: aload 4
    //   386: iconst_0
    //   387: ldc 124
    //   389: aastore
    //   390: aload 4
    //   392: iconst_1
    //   393: getstatic 562	java/lang/Character:TYPE	Ljava/lang/Class;
    //   396: aastore
    //   397: aload 4
    //   399: iconst_2
    //   400: getstatic 562	java/lang/Character:TYPE	Ljava/lang/Class;
    //   403: aastore
    //   404: ldc_w 564
    //   407: aload_3
    //   408: aload 4
    //   410: invokevirtual 80	java/lang/Class:getMethod	(Ljava/lang/String;[Ljava/lang/Class;)Ljava/lang/reflect/Method;
    //   413: astore 5
    //   415: iconst_3
    //   416: anewarray 82	java/lang/Object
    //   419: astore 6
    //   421: aload 6
    //   423: iconst_0
    //   424: ldc_w 566
    //   427: aastore
    //   428: aload 6
    //   430: iconst_1
    //   431: bipush 123
    //   433: invokestatic 569	java/lang/Character:valueOf	(C)Ljava/lang/Character;
    //   436: aastore
    //   437: aload 6
    //   439: iconst_2
    //   440: iconst_5
    //   441: invokestatic 569	java/lang/Character:valueOf	(C)Ljava/lang/Character;
    //   444: aastore
    //   445: aload 5
    //   447: aconst_null
    //   448: aload 6
    //   450: invokevirtual 88	java/lang/reflect/Method:invoke	(Ljava/lang/Object;[Ljava/lang/Object;)Ljava/lang/Object;
    //   453: astore 8
    //   455: aload_2
    //   456: iconst_3
    //   457: aload 8
    //   459: checkcast 124	java/lang/String
    //   462: invokevirtual 573	java/lang/StringBuilder:insert	(ILjava/lang/String;)Ljava/lang/StringBuilder;
    //   465: astore 9
    //   467: ldc_w 575
    //   470: sipush 222
    //   473: iconst_0
    //   474: invokestatic 74	xxxxxx/uxxxxx:bb00620062bb0062b0062b0062	(Ljava/lang/String;CC)Ljava/lang/String;
    //   477: astore 10
    //   479: iconst_4
    //   480: anewarray 76	java/lang/Class
    //   483: astore 11
    //   485: aload 11
    //   487: iconst_0
    //   488: ldc 124
    //   490: aastore
    //   491: aload 11
    //   493: iconst_1
    //   494: getstatic 562	java/lang/Character:TYPE	Ljava/lang/Class;
    //   497: aastore
    //   498: aload 11
    //   500: iconst_2
    //   501: getstatic 562	java/lang/Character:TYPE	Ljava/lang/Class;
    //   504: aastore
    //   505: aload 11
    //   507: iconst_3
    //   508: getstatic 562	java/lang/Character:TYPE	Ljava/lang/Class;
    //   511: aastore
    //   512: ldc_w 564
    //   515: aload 10
    //   517: aload 11
    //   519: invokevirtual 80	java/lang/Class:getMethod	(Ljava/lang/String;[Ljava/lang/Class;)Ljava/lang/reflect/Method;
    //   522: astore 12
    //   524: iconst_4
    //   525: anewarray 82	java/lang/Object
    //   528: astore 13
    //   530: aload 13
    //   532: iconst_0
    //   533: ldc_w 577
    //   536: aastore
    //   537: aload 13
    //   539: iconst_1
    //   540: bipush 46
    //   542: invokestatic 569	java/lang/Character:valueOf	(C)Ljava/lang/Character;
    //   545: aastore
    //   546: aload 13
    //   548: iconst_2
    //   549: sipush 222
    //   552: invokestatic 569	java/lang/Character:valueOf	(C)Ljava/lang/Character;
    //   555: aastore
    //   556: aload 13
    //   558: iconst_3
    //   559: iconst_2
    //   560: invokestatic 569	java/lang/Character:valueOf	(C)Ljava/lang/Character;
    //   563: aastore
    //   564: aload 12
    //   566: aconst_null
    //   567: aload 13
    //   569: invokevirtual 88	java/lang/reflect/Method:invoke	(Ljava/lang/Object;[Ljava/lang/Object;)Ljava/lang/Object;
    //   572: astore 15
    //   574: aload 9
    //   576: bipush 11
    //   578: aload 15
    //   580: checkcast 124	java/lang/String
    //   583: invokevirtual 573	java/lang/StringBuilder:insert	(ILjava/lang/String;)Ljava/lang/StringBuilder;
    //   586: invokevirtual 580	java/lang/StringBuilder:toString	()Ljava/lang/String;
    //   589: areturn
    //   590: astore 18
    //   592: aload 18
    //   594: invokevirtual 141	java/lang/reflect/InvocationTargetException:getCause	()Ljava/lang/Throwable;
    //   597: athrow
    //   598: astore 22
    //   600: aload 22
    //   602: invokevirtual 141	java/lang/reflect/InvocationTargetException:getCause	()Ljava/lang/Throwable;
    //   605: athrow
    //   606: astore 14
    //   608: aload 14
    //   610: invokevirtual 141	java/lang/reflect/InvocationTargetException:getCause	()Ljava/lang/Throwable;
    //   613: athrow
    //   614: astore 7
    //   616: aload 7
    //   618: invokevirtual 141	java/lang/reflect/InvocationTargetException:getCause	()Ljava/lang/Throwable;
    //   621: athrow
    //   622: astore 26
    //   624: aload 26
    //   626: invokevirtual 141	java/lang/reflect/InvocationTargetException:getCause	()Ljava/lang/Throwable;
    //   629: athrow
    //   630: astore 30
    //   632: aload 30
    //   634: invokevirtual 141	java/lang/reflect/InvocationTargetException:getCause	()Ljava/lang/Throwable;
    //   637: athrow
    //   638: astore 34
    //   640: aload 34
    //   642: invokevirtual 141	java/lang/reflect/InvocationTargetException:getCause	()Ljava/lang/Throwable;
    //   645: athrow
    // Local variable table:
    //   start	length	slot	name	signature
    //   0	646	0	this	ttttst
    //   0	646	1	paramString	String
    //   366	90	2	localStringBuilder1	StringBuilder
    //   377	31	3	str1	String
    //   382	27	4	arrayOfClass1	Class[]
    //   413	33	5	localMethod1	Method
    //   419	30	6	arrayOfObject1	Object[]
    //   614	3	7	localInvocationTargetException1	InvocationTargetException
    //   453	5	8	localObject1	Object
    //   465	110	9	localStringBuilder2	StringBuilder
    //   477	39	10	str2	String
    //   483	35	11	arrayOfClass2	Class[]
    //   522	43	12	localMethod2	Method
    //   528	40	13	arrayOfObject2	Object[]
    //   606	3	14	localInvocationTargetException2	InvocationTargetException
    //   572	7	15	localObject2	Object
    //   329	9	16	localMethod3	Method
    //   335	6	17	arrayOfObject3	Object[]
    //   590	3	18	localInvocationTargetException3	InvocationTargetException
    //   345	3	19	localObject3	Object
    //   281	9	20	localMethod4	Method
    //   287	6	21	arrayOfObject4	Object[]
    //   598	3	22	localInvocationTargetException4	InvocationTargetException
    //   297	3	23	localObject4	Object
    //   105	9	24	localMethod5	Method
    //   111	6	25	arrayOfObject5	Object[]
    //   622	3	26	localInvocationTargetException5	InvocationTargetException
    //   121	3	27	localObject5	Object
    //   153	9	28	localMethod6	Method
    //   159	6	29	arrayOfObject6	Object[]
    //   630	3	30	localInvocationTargetException6	InvocationTargetException
    //   169	3	31	localObject6	Object
    //   222	9	32	localMethod7	Method
    //   228	6	33	arrayOfObject7	Object[]
    //   638	3	34	localInvocationTargetException7	InvocationTargetException
    //   238	3	35	localObject7	Object
    // Exception table:
    //   from	to	target	type
    //   337	347	590	java/lang/reflect/InvocationTargetException
    //   289	299	598	java/lang/reflect/InvocationTargetException
    //   564	574	606	java/lang/reflect/InvocationTargetException
    //   445	455	614	java/lang/reflect/InvocationTargetException
    //   113	123	622	java/lang/reflect/InvocationTargetException
    //   161	171	630	java/lang/reflect/InvocationTargetException
    //   230	240	638	java/lang/reflect/InvocationTargetException
  }
  
  /* Error */
  public void bkk006Bkkkkk006Bk()
  {
    // Byte code:
    //   0: aload_0
    //   1: getfield 583	uuuuuu/ttttst:bn006En006E006Enn006En	Luuuuuu/yygggy;
    //   4: invokeinterface 588 1 0
    //   9: ifeq +787 -> 796
    //   12: new 552	java/lang/StringBuilder
    //   15: dup
    //   16: invokespecial 589	java/lang/StringBuilder:<init>	()V
    //   19: astore_1
    //   20: aload_0
    //   21: getfield 52	uuuuuu/ttttst:bnnnnn006E006E006En	Luuuuuu/ttssst$tsssst;
    //   24: checkcast 54	uuuuuu/stsstt$sssstt
    //   27: astore_2
    //   28: getstatic 592	com/db/pwcc/dbmobile/foundation/R$string:menu_item_environment_prefix	I
    //   31: istore_3
    //   32: iconst_1
    //   33: anewarray 82	java/lang/Object
    //   36: astore 4
    //   38: aload_0
    //   39: getfield 163	uuuuuu/ttttst:b006E006En006Enn006E006En	Lcom/db/pwcc/dbmobile/secure/preferences/SharedPreferencesHelper;
    //   42: astore 5
    //   44: ldc -91
    //   46: ldc_w 594
    //   49: bipush 40
    //   51: sipush 198
    //   54: iconst_1
    //   55: invokestatic 101	xxxxxx/uxxxxx:bbbb0062b0062b0062b0062	(Ljava/lang/String;CCC)Ljava/lang/String;
    //   58: iconst_0
    //   59: anewarray 76	java/lang/Class
    //   62: invokevirtual 80	java/lang/Class:getMethod	(Ljava/lang/String;[Ljava/lang/Class;)Ljava/lang/reflect/Method;
    //   65: astore 6
    //   67: iconst_0
    //   68: anewarray 82	java/lang/Object
    //   71: astore 7
    //   73: aload 6
    //   75: aload 5
    //   77: aload 7
    //   79: invokevirtual 88	java/lang/reflect/Method:invoke	(Ljava/lang/Object;[Ljava/lang/Object;)Ljava/lang/Object;
    //   82: astore 9
    //   84: aload 4
    //   86: iconst_0
    //   87: aload 9
    //   89: checkcast 124	java/lang/String
    //   92: aastore
    //   93: aload_1
    //   94: aload_2
    //   95: iload_3
    //   96: aload 4
    //   98: invokeinterface 318 3 0
    //   103: invokevirtual 598	java/lang/StringBuilder:append	(Ljava/lang/String;)Ljava/lang/StringBuilder;
    //   106: pop
    //   107: aload_1
    //   108: bipush 10
    //   110: invokevirtual 601	java/lang/StringBuilder:append	(C)Ljava/lang/StringBuilder;
    //   113: pop
    //   114: ldc 2
    //   116: ldc_w 603
    //   119: sipush 154
    //   122: iconst_4
    //   123: invokestatic 74	xxxxxx/uxxxxx:bb00620062bb0062b0062b0062	(Ljava/lang/String;CC)Ljava/lang/String;
    //   126: iconst_0
    //   127: anewarray 76	java/lang/Class
    //   130: invokevirtual 80	java/lang/Class:getMethod	(Ljava/lang/String;[Ljava/lang/Class;)Ljava/lang/reflect/Method;
    //   133: astore 12
    //   135: iconst_0
    //   136: anewarray 82	java/lang/Object
    //   139: astore 13
    //   141: aload 12
    //   143: aconst_null
    //   144: aload 13
    //   146: invokevirtual 88	java/lang/reflect/Method:invoke	(Ljava/lang/Object;[Ljava/lang/Object;)Ljava/lang/Object;
    //   149: astore 15
    //   151: aload 15
    //   153: checkcast 90	java/lang/Integer
    //   156: invokevirtual 93	java/lang/Integer:intValue	()I
    //   159: istore 16
    //   161: iload 16
    //   163: iload 16
    //   165: getstatic 95	uuuuuu/ttttst:bn006E006E006E006Enn006En	I
    //   168: iadd
    //   169: imul
    //   170: getstatic 103	uuuuuu/ttttst:b006E006E006E006E006Enn006En	I
    //   173: irem
    //   174: tableswitch	default:+18->192, 0:+65->239
    //   192: ldc 2
    //   194: ldc_w 605
    //   197: bipush 38
    //   199: iconst_3
    //   200: invokestatic 74	xxxxxx/uxxxxx:bb00620062bb0062b0062b0062	(Ljava/lang/String;CC)Ljava/lang/String;
    //   203: iconst_0
    //   204: anewarray 76	java/lang/Class
    //   207: invokevirtual 80	java/lang/Class:getMethod	(Ljava/lang/String;[Ljava/lang/Class;)Ljava/lang/reflect/Method;
    //   210: astore 62
    //   212: iconst_0
    //   213: anewarray 82	java/lang/Object
    //   216: astore 63
    //   218: aload 62
    //   220: aconst_null
    //   221: aload 63
    //   223: invokevirtual 88	java/lang/reflect/Method:invoke	(Ljava/lang/Object;[Ljava/lang/Object;)Ljava/lang/Object;
    //   226: astore 65
    //   228: aload 65
    //   230: checkcast 90	java/lang/Integer
    //   233: invokevirtual 93	java/lang/Integer:intValue	()I
    //   236: putstatic 95	uuuuuu/ttttst:bn006E006E006E006Enn006En	I
    //   239: aload_0
    //   240: getfield 52	uuuuuu/ttttst:bnnnnn006E006E006En	Luuuuuu/ttssst$tsssst;
    //   243: checkcast 54	uuuuuu/stsstt$sssstt
    //   246: astore 17
    //   248: getstatic 608	com/db/pwcc/dbmobile/foundation/R$string:menu_item_server_url_prefix	I
    //   251: istore 18
    //   253: iconst_1
    //   254: anewarray 82	java/lang/Object
    //   257: astore 19
    //   259: aload 19
    //   261: iconst_0
    //   262: aload_0
    //   263: getfield 441	uuuuuu/ttttst:b006En006E006E006En006E006En	Luuuuuu/ggyggy;
    //   266: getstatic 614	uuuuuu/gyyygy$yyyygy:bkkk006Bk006Bk006Bk	Luuuuuu/gyyygy$yyyygy;
    //   269: invokevirtual 620	uuuuuu/ggyggy:b0070007000700070pp00700070pp	(Luuuuuu/gyyygy$yyyygy;)Luuuuuu/yyyggy;
    //   272: invokeinterface 626 1 0
    //   277: invokevirtual 631	uuuuuu/ygyygy:b00700070pp0070ppp0070p	()Ljava/lang/String;
    //   280: aastore
    //   281: aload_1
    //   282: aload 17
    //   284: iload 18
    //   286: aload 19
    //   288: invokeinterface 318 3 0
    //   293: invokevirtual 598	java/lang/StringBuilder:append	(Ljava/lang/String;)Ljava/lang/StringBuilder;
    //   296: pop
    //   297: aload_1
    //   298: bipush 10
    //   300: invokevirtual 601	java/lang/StringBuilder:append	(C)Ljava/lang/StringBuilder;
    //   303: pop
    //   304: aload_0
    //   305: getfield 52	uuuuuu/ttttst:bnnnnn006E006E006En	Luuuuuu/ttssst$tsssst;
    //   308: astore 22
    //   310: ldc 2
    //   312: ldc_w 633
    //   315: bipush 116
    //   317: iconst_1
    //   318: invokestatic 74	xxxxxx/uxxxxx:bb00620062bb0062b0062b0062	(Ljava/lang/String;CC)Ljava/lang/String;
    //   321: iconst_0
    //   322: anewarray 76	java/lang/Class
    //   325: invokevirtual 80	java/lang/Class:getMethod	(Ljava/lang/String;[Ljava/lang/Class;)Ljava/lang/reflect/Method;
    //   328: astore 23
    //   330: iconst_0
    //   331: anewarray 82	java/lang/Object
    //   334: astore 24
    //   336: aload 23
    //   338: aconst_null
    //   339: aload 24
    //   341: invokevirtual 88	java/lang/reflect/Method:invoke	(Ljava/lang/Object;[Ljava/lang/Object;)Ljava/lang/Object;
    //   344: astore 26
    //   346: aload 26
    //   348: checkcast 90	java/lang/Integer
    //   351: invokevirtual 93	java/lang/Integer:intValue	()I
    //   354: getstatic 95	uuuuuu/ttttst:bn006E006E006E006Enn006En	I
    //   357: iadd
    //   358: istore 27
    //   360: ldc 2
    //   362: ldc_w 303
    //   365: sipush 201
    //   368: iconst_5
    //   369: invokestatic 74	xxxxxx/uxxxxx:bb00620062bb0062b0062b0062	(Ljava/lang/String;CC)Ljava/lang/String;
    //   372: iconst_0
    //   373: anewarray 76	java/lang/Class
    //   376: invokevirtual 80	java/lang/Class:getMethod	(Ljava/lang/String;[Ljava/lang/Class;)Ljava/lang/reflect/Method;
    //   379: astore 28
    //   381: iconst_0
    //   382: anewarray 82	java/lang/Object
    //   385: astore 29
    //   387: aload 28
    //   389: aconst_null
    //   390: aload 29
    //   392: invokevirtual 88	java/lang/reflect/Method:invoke	(Ljava/lang/Object;[Ljava/lang/Object;)Ljava/lang/Object;
    //   395: astore 31
    //   397: iload 27
    //   399: aload 31
    //   401: checkcast 90	java/lang/Integer
    //   404: invokevirtual 93	java/lang/Integer:intValue	()I
    //   407: imul
    //   408: getstatic 103	uuuuuu/ttttst:b006E006E006E006E006Enn006En	I
    //   411: irem
    //   412: getstatic 105	uuuuuu/ttttst:bnnnnn006En006En	I
    //   415: if_icmpeq +8 -> 423
    //   418: bipush 52
    //   420: putstatic 105	uuuuuu/ttttst:bnnnnn006En006En	I
    //   423: aload 22
    //   425: checkcast 54	uuuuuu/stsstt$sssstt
    //   428: astore 32
    //   430: getstatic 636	com/db/pwcc/dbmobile/foundation/R$string:menu_item_builtat_prefix	I
    //   433: istore 33
    //   435: iconst_1
    //   436: anewarray 82	java/lang/Object
    //   439: astore 34
    //   441: aload_0
    //   442: getfield 163	uuuuuu/ttttst:b006E006En006Enn006E006En	Lcom/db/pwcc/dbmobile/secure/preferences/SharedPreferencesHelper;
    //   445: astore 35
    //   447: ldc -91
    //   449: ldc_w 638
    //   452: sipush 155
    //   455: iconst_4
    //   456: invokestatic 74	xxxxxx/uxxxxx:bb00620062bb0062b0062b0062	(Ljava/lang/String;CC)Ljava/lang/String;
    //   459: iconst_0
    //   460: anewarray 76	java/lang/Class
    //   463: invokevirtual 80	java/lang/Class:getMethod	(Ljava/lang/String;[Ljava/lang/Class;)Ljava/lang/reflect/Method;
    //   466: astore 36
    //   468: iconst_0
    //   469: anewarray 82	java/lang/Object
    //   472: astore 37
    //   474: aload 36
    //   476: aload 35
    //   478: aload 37
    //   480: invokevirtual 88	java/lang/reflect/Method:invoke	(Ljava/lang/Object;[Ljava/lang/Object;)Ljava/lang/Object;
    //   483: astore 39
    //   485: aload 34
    //   487: iconst_0
    //   488: aload 39
    //   490: checkcast 124	java/lang/String
    //   493: aastore
    //   494: aload_1
    //   495: aload 32
    //   497: iload 33
    //   499: aload 34
    //   501: invokeinterface 318 3 0
    //   506: invokevirtual 598	java/lang/StringBuilder:append	(Ljava/lang/String;)Ljava/lang/StringBuilder;
    //   509: pop
    //   510: getstatic 107	uuuuuu/ttttst:b006Ennnn006En006En	I
    //   513: istore 41
    //   515: iload 41
    //   517: iload 41
    //   519: getstatic 95	uuuuuu/ttttst:bn006E006E006E006Enn006En	I
    //   522: iadd
    //   523: imul
    //   524: getstatic 103	uuuuuu/ttttst:b006E006E006E006E006Enn006En	I
    //   527: irem
    //   528: tableswitch	default:+20->548, 0:+72->600
    //   548: ldc 2
    //   550: ldc_w 640
    //   553: bipush 63
    //   555: iconst_4
    //   556: invokestatic 74	xxxxxx/uxxxxx:bb00620062bb0062b0062b0062	(Ljava/lang/String;CC)Ljava/lang/String;
    //   559: iconst_0
    //   560: anewarray 76	java/lang/Class
    //   563: invokevirtual 80	java/lang/Class:getMethod	(Ljava/lang/String;[Ljava/lang/Class;)Ljava/lang/reflect/Method;
    //   566: astore 58
    //   568: iconst_0
    //   569: anewarray 82	java/lang/Object
    //   572: astore 59
    //   574: aload 58
    //   576: aconst_null
    //   577: aload 59
    //   579: invokevirtual 88	java/lang/reflect/Method:invoke	(Ljava/lang/Object;[Ljava/lang/Object;)Ljava/lang/Object;
    //   582: astore 61
    //   584: aload 61
    //   586: checkcast 90	java/lang/Integer
    //   589: invokevirtual 93	java/lang/Integer:intValue	()I
    //   592: putstatic 107	uuuuuu/ttttst:b006Ennnn006En006En	I
    //   595: bipush 19
    //   597: putstatic 105	uuuuuu/ttttst:bnnnnn006En006En	I
    //   600: aload_1
    //   601: bipush 10
    //   603: invokevirtual 601	java/lang/StringBuilder:append	(C)Ljava/lang/StringBuilder;
    //   606: pop
    //   607: aload_0
    //   608: getfield 52	uuuuuu/ttttst:bnnnnn006E006E006En	Luuuuuu/ttssst$tsssst;
    //   611: checkcast 54	uuuuuu/stsstt$sssstt
    //   614: astore 43
    //   616: getstatic 643	com/db/pwcc/dbmobile/foundation/R$string:menu_item_buildconfig_prefix	I
    //   619: istore 44
    //   621: iconst_1
    //   622: anewarray 82	java/lang/Object
    //   625: astore 45
    //   627: aload_0
    //   628: getfield 163	uuuuuu/ttttst:b006E006En006Enn006E006En	Lcom/db/pwcc/dbmobile/secure/preferences/SharedPreferencesHelper;
    //   631: astore 46
    //   633: ldc -91
    //   635: ldc_w 645
    //   638: bipush 82
    //   640: iconst_2
    //   641: invokestatic 74	xxxxxx/uxxxxx:bb00620062bb0062b0062b0062	(Ljava/lang/String;CC)Ljava/lang/String;
    //   644: iconst_0
    //   645: anewarray 76	java/lang/Class
    //   648: invokevirtual 80	java/lang/Class:getMethod	(Ljava/lang/String;[Ljava/lang/Class;)Ljava/lang/reflect/Method;
    //   651: astore 47
    //   653: iconst_0
    //   654: anewarray 82	java/lang/Object
    //   657: astore 48
    //   659: aload 47
    //   661: aload 46
    //   663: aload 48
    //   665: invokevirtual 88	java/lang/reflect/Method:invoke	(Ljava/lang/Object;[Ljava/lang/Object;)Ljava/lang/Object;
    //   668: astore 50
    //   670: aload 45
    //   672: iconst_0
    //   673: aload 50
    //   675: checkcast 124	java/lang/String
    //   678: aastore
    //   679: aload_1
    //   680: aload 43
    //   682: iload 44
    //   684: aload 45
    //   686: invokeinterface 318 3 0
    //   691: invokevirtual 598	java/lang/StringBuilder:append	(Ljava/lang/String;)Ljava/lang/StringBuilder;
    //   694: pop
    //   695: aload_0
    //   696: getfield 52	uuuuuu/ttttst:bnnnnn006E006E006En	Luuuuuu/ttssst$tsssst;
    //   699: checkcast 54	uuuuuu/stsstt$sssstt
    //   702: astore 52
    //   704: aload_1
    //   705: invokevirtual 580	java/lang/StringBuilder:toString	()Ljava/lang/String;
    //   708: astore 53
    //   710: getstatic 107	uuuuuu/ttttst:b006Ennnn006En006En	I
    //   713: getstatic 95	uuuuuu/ttttst:bn006E006E006E006Enn006En	I
    //   716: iadd
    //   717: getstatic 107	uuuuuu/ttttst:b006Ennnn006En006En	I
    //   720: imul
    //   721: getstatic 103	uuuuuu/ttttst:b006E006E006E006E006Enn006En	I
    //   724: irem
    //   725: getstatic 105	uuuuuu/ttttst:bnnnnn006En006En	I
    //   728: if_icmpeq +59 -> 787
    //   731: ldc 2
    //   733: ldc_w 647
    //   736: sipush 207
    //   739: sipush 190
    //   742: iconst_1
    //   743: invokestatic 101	xxxxxx/uxxxxx:bbbb0062b0062b0062b0062	(Ljava/lang/String;CCC)Ljava/lang/String;
    //   746: iconst_0
    //   747: anewarray 76	java/lang/Class
    //   750: invokevirtual 80	java/lang/Class:getMethod	(Ljava/lang/String;[Ljava/lang/Class;)Ljava/lang/reflect/Method;
    //   753: astore 54
    //   755: iconst_0
    //   756: anewarray 82	java/lang/Object
    //   759: astore 55
    //   761: aload 54
    //   763: aconst_null
    //   764: aload 55
    //   766: invokevirtual 88	java/lang/reflect/Method:invoke	(Ljava/lang/Object;[Ljava/lang/Object;)Ljava/lang/Object;
    //   769: astore 57
    //   771: aload 57
    //   773: checkcast 90	java/lang/Integer
    //   776: invokevirtual 93	java/lang/Integer:intValue	()I
    //   779: putstatic 107	uuuuuu/ttttst:b006Ennnn006En006En	I
    //   782: bipush 10
    //   784: putstatic 105	uuuuuu/ttttst:bnnnnn006En006En	I
    //   787: aload 52
    //   789: aload 53
    //   791: invokeinterface 650 2 0
    //   796: return
    //   797: astore 25
    //   799: aload 25
    //   801: invokevirtual 141	java/lang/reflect/InvocationTargetException:getCause	()Ljava/lang/Throwable;
    //   804: athrow
    //   805: astore 30
    //   807: aload 30
    //   809: invokevirtual 141	java/lang/reflect/InvocationTargetException:getCause	()Ljava/lang/Throwable;
    //   812: athrow
    //   813: astore 49
    //   815: aload 49
    //   817: invokevirtual 141	java/lang/reflect/InvocationTargetException:getCause	()Ljava/lang/Throwable;
    //   820: athrow
    //   821: astore 38
    //   823: aload 38
    //   825: invokevirtual 141	java/lang/reflect/InvocationTargetException:getCause	()Ljava/lang/Throwable;
    //   828: athrow
    //   829: astore 8
    //   831: aload 8
    //   833: invokevirtual 141	java/lang/reflect/InvocationTargetException:getCause	()Ljava/lang/Throwable;
    //   836: athrow
    //   837: astore 64
    //   839: aload 64
    //   841: invokevirtual 141	java/lang/reflect/InvocationTargetException:getCause	()Ljava/lang/Throwable;
    //   844: athrow
    //   845: astore 14
    //   847: aload 14
    //   849: invokevirtual 141	java/lang/reflect/InvocationTargetException:getCause	()Ljava/lang/Throwable;
    //   852: athrow
    //   853: astore 60
    //   855: aload 60
    //   857: invokevirtual 141	java/lang/reflect/InvocationTargetException:getCause	()Ljava/lang/Throwable;
    //   860: athrow
    //   861: astore 56
    //   863: aload 56
    //   865: invokevirtual 141	java/lang/reflect/InvocationTargetException:getCause	()Ljava/lang/Throwable;
    //   868: athrow
    // Local variable table:
    //   start	length	slot	name	signature
    //   0	869	0	this	ttttst
    //   19	686	1	localStringBuilder	StringBuilder
    //   27	68	2	localSssstt1	stsstt.sssstt
    //   31	65	3	i	int
    //   36	61	4	arrayOfObject1	Object[]
    //   42	34	5	localSharedPreferencesHelper1	SharedPreferencesHelper
    //   65	9	6	localMethod1	Method
    //   71	7	7	arrayOfObject2	Object[]
    //   829	3	8	localInvocationTargetException1	InvocationTargetException
    //   82	6	9	localObject1	Object
    //   133	9	12	localMethod2	Method
    //   139	6	13	arrayOfObject3	Object[]
    //   845	3	14	localInvocationTargetException2	InvocationTargetException
    //   149	3	15	localObject2	Object
    //   159	11	16	j	int
    //   246	37	17	localSssstt2	stsstt.sssstt
    //   251	34	18	k	int
    //   257	30	19	arrayOfObject4	Object[]
    //   308	116	22	localTsssst	ttssst.tsssst
    //   328	9	23	localMethod3	Method
    //   334	6	24	arrayOfObject5	Object[]
    //   797	3	25	localInvocationTargetException3	InvocationTargetException
    //   344	3	26	localObject3	Object
    //   358	50	27	m	int
    //   379	9	28	localMethod4	Method
    //   385	6	29	arrayOfObject6	Object[]
    //   805	3	30	localInvocationTargetException4	InvocationTargetException
    //   395	5	31	localObject4	Object
    //   428	68	32	localSssstt3	stsstt.sssstt
    //   433	65	33	n	int
    //   439	61	34	arrayOfObject7	Object[]
    //   445	32	35	localSharedPreferencesHelper2	SharedPreferencesHelper
    //   466	9	36	localMethod5	Method
    //   472	7	37	arrayOfObject8	Object[]
    //   821	3	38	localInvocationTargetException5	InvocationTargetException
    //   483	6	39	localObject5	Object
    //   513	11	41	i1	int
    //   614	67	43	localSssstt4	stsstt.sssstt
    //   619	64	44	i2	int
    //   625	60	45	arrayOfObject9	Object[]
    //   631	31	46	localSharedPreferencesHelper3	SharedPreferencesHelper
    //   651	9	47	localMethod6	Method
    //   657	7	48	arrayOfObject10	Object[]
    //   813	3	49	localInvocationTargetException6	InvocationTargetException
    //   668	6	50	localObject6	Object
    //   702	86	52	localSssstt5	stsstt.sssstt
    //   708	82	53	str	String
    //   753	9	54	localMethod7	Method
    //   759	6	55	arrayOfObject11	Object[]
    //   861	3	56	localInvocationTargetException7	InvocationTargetException
    //   769	3	57	localObject7	Object
    //   566	9	58	localMethod8	Method
    //   572	6	59	arrayOfObject12	Object[]
    //   853	3	60	localInvocationTargetException8	InvocationTargetException
    //   582	3	61	localObject8	Object
    //   210	9	62	localMethod9	Method
    //   216	6	63	arrayOfObject13	Object[]
    //   837	3	64	localInvocationTargetException9	InvocationTargetException
    //   226	3	65	localObject9	Object
    // Exception table:
    //   from	to	target	type
    //   336	346	797	java/lang/reflect/InvocationTargetException
    //   387	397	805	java/lang/reflect/InvocationTargetException
    //   659	670	813	java/lang/reflect/InvocationTargetException
    //   474	485	821	java/lang/reflect/InvocationTargetException
    //   73	84	829	java/lang/reflect/InvocationTargetException
    //   218	228	837	java/lang/reflect/InvocationTargetException
    //   141	151	845	java/lang/reflect/InvocationTargetException
    //   574	584	853	java/lang/reflect/InvocationTargetException
    //   761	771	861	java/lang/reflect/InvocationTargetException
  }
  
  /* Error */
  public void bkkkkkkkk006Bk()
  {
    // Byte code:
    //   0: getstatic 654	uuuuuu/vvrvrv:bh0068006800680068hh00680068	Luuuuuu/vvrvrv;
    //   3: astore_1
    //   4: getstatic 107	uuuuuu/ttttst:b006Ennnn006En006En	I
    //   7: istore_2
    //   8: iload_2
    //   9: iload_2
    //   10: getstatic 95	uuuuuu/ttttst:bn006E006E006E006Enn006En	I
    //   13: iadd
    //   14: imul
    //   15: getstatic 103	uuuuuu/ttttst:b006E006E006E006E006Enn006En	I
    //   18: irem
    //   19: tableswitch	default:+17->36, 0:+158->177
    //   36: ldc 2
    //   38: ldc_w 656
    //   41: bipush 37
    //   43: iconst_2
    //   44: invokestatic 74	xxxxxx/uxxxxx:bb00620062bb0062b0062b0062	(Ljava/lang/String;CC)Ljava/lang/String;
    //   47: iconst_0
    //   48: anewarray 76	java/lang/Class
    //   51: invokevirtual 80	java/lang/Class:getMethod	(Ljava/lang/String;[Ljava/lang/Class;)Ljava/lang/reflect/Method;
    //   54: astore 13
    //   56: iconst_0
    //   57: anewarray 82	java/lang/Object
    //   60: astore 14
    //   62: aload 13
    //   64: aconst_null
    //   65: aload 14
    //   67: invokevirtual 88	java/lang/reflect/Method:invoke	(Ljava/lang/Object;[Ljava/lang/Object;)Ljava/lang/Object;
    //   70: astore 16
    //   72: aload 16
    //   74: checkcast 90	java/lang/Integer
    //   77: invokevirtual 93	java/lang/Integer:intValue	()I
    //   80: putstatic 107	uuuuuu/ttttst:b006Ennnn006En006En	I
    //   83: bipush 23
    //   85: putstatic 105	uuuuuu/ttttst:bnnnnn006En006En	I
    //   88: getstatic 107	uuuuuu/ttttst:b006Ennnn006En006En	I
    //   91: istore 17
    //   93: iload 17
    //   95: iload 17
    //   97: getstatic 95	uuuuuu/ttttst:bn006E006E006E006Enn006En	I
    //   100: iadd
    //   101: imul
    //   102: getstatic 103	uuuuuu/ttttst:b006E006E006E006E006Enn006En	I
    //   105: irem
    //   106: tableswitch	default:+18->124, 0:+71->177
    //   124: ldc 2
    //   126: ldc_w 342
    //   129: sipush 205
    //   132: iconst_0
    //   133: invokestatic 74	xxxxxx/uxxxxx:bb00620062bb0062b0062b0062	(Ljava/lang/String;CC)Ljava/lang/String;
    //   136: iconst_0
    //   137: anewarray 76	java/lang/Class
    //   140: invokevirtual 80	java/lang/Class:getMethod	(Ljava/lang/String;[Ljava/lang/Class;)Ljava/lang/reflect/Method;
    //   143: astore 18
    //   145: iconst_0
    //   146: anewarray 82	java/lang/Object
    //   149: astore 19
    //   151: aload 18
    //   153: aconst_null
    //   154: aload 19
    //   156: invokevirtual 88	java/lang/reflect/Method:invoke	(Ljava/lang/Object;[Ljava/lang/Object;)Ljava/lang/Object;
    //   159: astore 21
    //   161: aload 21
    //   163: checkcast 90	java/lang/Integer
    //   166: invokevirtual 93	java/lang/Integer:intValue	()I
    //   169: putstatic 107	uuuuuu/ttttst:b006Ennnn006En006En	I
    //   172: bipush 73
    //   174: putstatic 105	uuuuuu/ttttst:bnnnnn006En006En	I
    //   177: aload_1
    //   178: invokestatic 362	uuuuuu/rrvvrv:b0071q0071qq0071q0071q0071	(Luuuuuu/vvrvrv;)V
    //   181: getstatic 107	uuuuuu/ttttst:b006Ennnn006En006En	I
    //   184: istore_3
    //   185: iload_3
    //   186: iload_3
    //   187: getstatic 95	uuuuuu/ttttst:bn006E006E006E006Enn006En	I
    //   190: iadd
    //   191: imul
    //   192: getstatic 103	uuuuuu/ttttst:b006E006E006E006E006Enn006En	I
    //   195: irem
    //   196: tableswitch	default:+20->216, 0:+161->357
    //   216: getstatic 107	uuuuuu/ttttst:b006Ennnn006En006En	I
    //   219: istore 4
    //   221: iload 4
    //   223: iload 4
    //   225: getstatic 95	uuuuuu/ttttst:bn006E006E006E006Enn006En	I
    //   228: iadd
    //   229: imul
    //   230: getstatic 103	uuuuuu/ttttst:b006E006E006E006E006Enn006En	I
    //   233: irem
    //   234: tableswitch	default:+18->252, 0:+113->347
    //   252: ldc 2
    //   254: ldc_w 658
    //   257: iconst_2
    //   258: iconst_3
    //   259: invokestatic 74	xxxxxx/uxxxxx:bb00620062bb0062b0062b0062	(Ljava/lang/String;CC)Ljava/lang/String;
    //   262: iconst_0
    //   263: anewarray 76	java/lang/Class
    //   266: invokevirtual 80	java/lang/Class:getMethod	(Ljava/lang/String;[Ljava/lang/Class;)Ljava/lang/reflect/Method;
    //   269: astore 5
    //   271: iconst_0
    //   272: anewarray 82	java/lang/Object
    //   275: astore 6
    //   277: aload 5
    //   279: aconst_null
    //   280: aload 6
    //   282: invokevirtual 88	java/lang/reflect/Method:invoke	(Ljava/lang/Object;[Ljava/lang/Object;)Ljava/lang/Object;
    //   285: astore 8
    //   287: aload 8
    //   289: checkcast 90	java/lang/Integer
    //   292: invokevirtual 93	java/lang/Integer:intValue	()I
    //   295: putstatic 107	uuuuuu/ttttst:b006Ennnn006En006En	I
    //   298: ldc 2
    //   300: ldc_w 660
    //   303: bipush 112
    //   305: bipush 103
    //   307: iconst_3
    //   308: invokestatic 101	xxxxxx/uxxxxx:bbbb0062b0062b0062b0062	(Ljava/lang/String;CCC)Ljava/lang/String;
    //   311: iconst_0
    //   312: anewarray 76	java/lang/Class
    //   315: invokevirtual 80	java/lang/Class:getMethod	(Ljava/lang/String;[Ljava/lang/Class;)Ljava/lang/reflect/Method;
    //   318: astore 9
    //   320: iconst_0
    //   321: anewarray 82	java/lang/Object
    //   324: astore 10
    //   326: aload 9
    //   328: aconst_null
    //   329: aload 10
    //   331: invokevirtual 88	java/lang/reflect/Method:invoke	(Ljava/lang/Object;[Ljava/lang/Object;)Ljava/lang/Object;
    //   334: astore 12
    //   336: aload 12
    //   338: checkcast 90	java/lang/Integer
    //   341: invokevirtual 93	java/lang/Integer:intValue	()I
    //   344: putstatic 105	uuuuuu/ttttst:bnnnnn006En006En	I
    //   347: bipush 27
    //   349: putstatic 107	uuuuuu/ttttst:b006Ennnn006En006En	I
    //   352: bipush 45
    //   354: putstatic 105	uuuuuu/ttttst:bnnnnn006En006En	I
    //   357: return
    //   358: astore 15
    //   360: aload 15
    //   362: invokevirtual 141	java/lang/reflect/InvocationTargetException:getCause	()Ljava/lang/Throwable;
    //   365: athrow
    //   366: astore 7
    //   368: aload 7
    //   370: invokevirtual 141	java/lang/reflect/InvocationTargetException:getCause	()Ljava/lang/Throwable;
    //   373: athrow
    //   374: astore 11
    //   376: aload 11
    //   378: invokevirtual 141	java/lang/reflect/InvocationTargetException:getCause	()Ljava/lang/Throwable;
    //   381: athrow
    //   382: astore 20
    //   384: aload 20
    //   386: invokevirtual 141	java/lang/reflect/InvocationTargetException:getCause	()Ljava/lang/Throwable;
    //   389: athrow
    // Local variable table:
    //   start	length	slot	name	signature
    //   0	390	0	this	ttttst
    //   3	175	1	localVvrvrv	vvrvrv
    //   7	8	2	i	int
    //   184	8	3	j	int
    //   219	11	4	k	int
    //   269	9	5	localMethod1	Method
    //   275	6	6	arrayOfObject1	Object[]
    //   366	3	7	localInvocationTargetException1	InvocationTargetException
    //   285	3	8	localObject1	Object
    //   318	9	9	localMethod2	Method
    //   324	6	10	arrayOfObject2	Object[]
    //   374	3	11	localInvocationTargetException2	InvocationTargetException
    //   334	3	12	localObject2	Object
    //   54	9	13	localMethod3	Method
    //   60	6	14	arrayOfObject3	Object[]
    //   358	3	15	localInvocationTargetException3	InvocationTargetException
    //   70	3	16	localObject3	Object
    //   91	11	17	m	int
    //   143	9	18	localMethod4	Method
    //   149	6	19	arrayOfObject4	Object[]
    //   382	3	20	localInvocationTargetException4	InvocationTargetException
    //   159	3	21	localObject4	Object
    // Exception table:
    //   from	to	target	type
    //   62	72	358	java/lang/reflect/InvocationTargetException
    //   277	287	366	java/lang/reflect/InvocationTargetException
    //   326	336	374	java/lang/reflect/InvocationTargetException
    //   151	161	382	java/lang/reflect/InvocationTargetException
  }
}
