package uuuuuu;

import android.content.Context;
import java.util.List;

public class vllllv
  extends vlllvl<String>
{
  public static int b006F006F006F006Foo006Fo006F = 0;
  public static int b006Fo006F006Foo006Fo006F = 1;
  public static int bo006F006F006Foo006Fo006F = 2;
  public static int boo006F006Foo006Fo006F = 14;
  
  public vllllv(Context paramContext, List<String> paramList)
  {
    super(paramContext, paramList);
  }
  
  public static int b00690069i00690069i0069i00690069()
  {
    return 2;
  }
  
  public static int b0069ii00690069i0069i00690069()
  {
    return 2;
  }
  
  public static int bi0069i00690069i0069i00690069()
  {
    return 1;
  }
  
  /* Error */
  private int bii006900690069i0069i00690069(String paramString)
  {
    // Byte code:
    //   0: aload_1
    //   1: invokevirtual 31	java/lang/String:hashCode	()I
    //   4: lookupswitch	default:+84->88, -1738378111:+918->922, -445144898:+569->573, 64808441:+1152->1156, 398230326:+674->678, 1297843654:+327->331, 1720567065:+1033->1037, 1935336927:+146->150, 1954618349:+803->807, 2003304760:+1323->1327
    //   88: iconst_m1
    //   89: istore 8
    //   91: iload 8
    //   93: tableswitch	default:+51->144, 0:+230->323, 1:+234->327, 2:+427->520, 3:+706->799, 4:+710->803, 5:+710->803, 6:+1059->1152, 7:+936->1029, 8:+940->1033
    //   144: iconst_m1
    //   145: istore 9
    //   147: iload 9
    //   149: ireturn
    //   150: ldc 33
    //   152: bipush 74
    //   154: bipush 60
    //   156: iconst_3
    //   157: invokestatic 39	xxxxxx/uxxxxx:bbbb0062b0062b0062b0062	(Ljava/lang/String;CCC)Ljava/lang/String;
    //   160: astore 55
    //   162: iconst_4
    //   163: anewarray 41	java/lang/Class
    //   166: astore 56
    //   168: aload 56
    //   170: iconst_0
    //   171: ldc 28
    //   173: aastore
    //   174: aload 56
    //   176: iconst_1
    //   177: getstatic 47	java/lang/Character:TYPE	Ljava/lang/Class;
    //   180: aastore
    //   181: aload 56
    //   183: iconst_2
    //   184: getstatic 47	java/lang/Character:TYPE	Ljava/lang/Class;
    //   187: aastore
    //   188: aload 56
    //   190: iconst_3
    //   191: getstatic 47	java/lang/Character:TYPE	Ljava/lang/Class;
    //   194: aastore
    //   195: ldc 49
    //   197: aload 55
    //   199: aload 56
    //   201: invokevirtual 53	java/lang/Class:getMethod	(Ljava/lang/String;[Ljava/lang/Class;)Ljava/lang/reflect/Method;
    //   204: astore 57
    //   206: iconst_4
    //   207: anewarray 55	java/lang/Object
    //   210: astore 58
    //   212: aload 58
    //   214: iconst_0
    //   215: ldc 57
    //   217: aastore
    //   218: aload 58
    //   220: iconst_1
    //   221: bipush 118
    //   223: invokestatic 61	java/lang/Character:valueOf	(C)Ljava/lang/Character;
    //   226: aastore
    //   227: aload 58
    //   229: iconst_2
    //   230: sipush 210
    //   233: invokestatic 61	java/lang/Character:valueOf	(C)Ljava/lang/Character;
    //   236: aastore
    //   237: aload 58
    //   239: iconst_3
    //   240: iconst_1
    //   241: invokestatic 61	java/lang/Character:valueOf	(C)Ljava/lang/Character;
    //   244: aastore
    //   245: aload 57
    //   247: aconst_null
    //   248: aload 58
    //   250: invokevirtual 67	java/lang/reflect/Method:invoke	(Ljava/lang/Object;[Ljava/lang/Object;)Ljava/lang/Object;
    //   253: astore 60
    //   255: aload_1
    //   256: aload 60
    //   258: checkcast 28	java/lang/String
    //   261: invokevirtual 71	java/lang/String:equals	(Ljava/lang/Object;)Z
    //   264: ifeq -176 -> 88
    //   267: bipush 8
    //   269: istore 8
    //   271: getstatic 73	uuuuuu/vllllv:boo006F006Foo006Fo006F	I
    //   274: istore 61
    //   276: iload 61
    //   278: iload 61
    //   280: getstatic 75	uuuuuu/vllllv:b006Fo006F006Foo006Fo006F	I
    //   283: iadd
    //   284: imul
    //   285: getstatic 77	uuuuuu/vllllv:bo006F006F006Foo006Fo006F	I
    //   288: irem
    //   289: tableswitch	default:+19->308, 0:+-198->91
    //   308: invokestatic 79	uuuuuu/vllllv:b00690069i00690069i0069i00690069	()I
    //   311: putstatic 73	uuuuuu/vllllv:boo006F006Foo006Fo006F	I
    //   314: invokestatic 79	uuuuuu/vllllv:b00690069i00690069i0069i00690069	()I
    //   317: putstatic 75	uuuuuu/vllllv:b006Fo006F006Foo006Fo006F	I
    //   320: goto -229 -> 91
    //   323: getstatic 84	com/db/pwcc/dbmobile/transfer/R$string:standing_order_frequency_daily	I
    //   326: ireturn
    //   327: getstatic 87	com/db/pwcc/dbmobile/transfer/R$string:standing_order_frequency_weekly	I
    //   330: ireturn
    //   331: getstatic 73	uuuuuu/vllllv:boo006F006Foo006Fo006F	I
    //   334: istore 47
    //   336: iload 47
    //   338: iload 47
    //   340: getstatic 75	uuuuuu/vllllv:b006Fo006F006Foo006Fo006F	I
    //   343: iadd
    //   344: imul
    //   345: invokestatic 89	uuuuuu/vllllv:b0069ii00690069i0069i00690069	()I
    //   348: irem
    //   349: tableswitch	default:+19->368, 0:+31->380
    //   368: invokestatic 79	uuuuuu/vllllv:b00690069i00690069i0069i00690069	()I
    //   371: putstatic 73	uuuuuu/vllllv:boo006F006Foo006Fo006F	I
    //   374: invokestatic 79	uuuuuu/vllllv:b00690069i00690069i0069i00690069	()I
    //   377: putstatic 75	uuuuuu/vllllv:b006Fo006F006Foo006Fo006F	I
    //   380: ldc 91
    //   382: bipush 104
    //   384: iconst_3
    //   385: invokestatic 95	xxxxxx/uxxxxx:bb00620062bb0062b0062b0062	(Ljava/lang/String;CC)Ljava/lang/String;
    //   388: astore 48
    //   390: iconst_3
    //   391: anewarray 41	java/lang/Class
    //   394: astore 49
    //   396: aload 49
    //   398: iconst_0
    //   399: ldc 28
    //   401: aastore
    //   402: aload 49
    //   404: iconst_1
    //   405: getstatic 47	java/lang/Character:TYPE	Ljava/lang/Class;
    //   408: aastore
    //   409: aload 49
    //   411: iconst_2
    //   412: getstatic 47	java/lang/Character:TYPE	Ljava/lang/Class;
    //   415: aastore
    //   416: ldc 49
    //   418: aload 48
    //   420: aload 49
    //   422: invokevirtual 53	java/lang/Class:getMethod	(Ljava/lang/String;[Ljava/lang/Class;)Ljava/lang/reflect/Method;
    //   425: astore 50
    //   427: iconst_3
    //   428: anewarray 55	java/lang/Object
    //   431: astore 51
    //   433: aload 51
    //   435: iconst_0
    //   436: ldc 97
    //   438: aastore
    //   439: aload 51
    //   441: iconst_1
    //   442: bipush 84
    //   444: invokestatic 61	java/lang/Character:valueOf	(C)Ljava/lang/Character;
    //   447: aastore
    //   448: aload 51
    //   450: iconst_2
    //   451: iconst_4
    //   452: invokestatic 61	java/lang/Character:valueOf	(C)Ljava/lang/Character;
    //   455: aastore
    //   456: aload 50
    //   458: aconst_null
    //   459: aload 51
    //   461: invokevirtual 67	java/lang/reflect/Method:invoke	(Ljava/lang/Object;[Ljava/lang/Object;)Ljava/lang/Object;
    //   464: astore 53
    //   466: aload_1
    //   467: aload 53
    //   469: checkcast 28	java/lang/String
    //   472: invokevirtual 71	java/lang/String:equals	(Ljava/lang/Object;)Z
    //   475: istore 54
    //   477: getstatic 73	uuuuuu/vllllv:boo006F006Foo006Fo006F	I
    //   480: getstatic 75	uuuuuu/vllllv:b006Fo006F006Foo006Fo006F	I
    //   483: iadd
    //   484: getstatic 73	uuuuuu/vllllv:boo006F006Foo006Fo006F	I
    //   487: imul
    //   488: getstatic 77	uuuuuu/vllllv:bo006F006F006Foo006Fo006F	I
    //   491: irem
    //   492: getstatic 99	uuuuuu/vllllv:b006F006F006F006Foo006Fo006F	I
    //   495: if_icmpeq +13 -> 508
    //   498: bipush 8
    //   500: putstatic 73	uuuuuu/vllllv:boo006F006Foo006Fo006F	I
    //   503: bipush 99
    //   505: putstatic 99	uuuuuu/vllllv:b006F006F006F006Foo006Fo006F	I
    //   508: iload 54
    //   510: ifeq -422 -> 88
    //   513: bipush 6
    //   515: istore 8
    //   517: goto -426 -> 91
    //   520: getstatic 102	com/db/pwcc/dbmobile/transfer/R$string:standing_order_frequency_monthly	I
    //   523: istore 9
    //   525: getstatic 73	uuuuuu/vllllv:boo006F006Foo006Fo006F	I
    //   528: istore 10
    //   530: iload 10
    //   532: iload 10
    //   534: getstatic 75	uuuuuu/vllllv:b006Fo006F006Foo006Fo006F	I
    //   537: iadd
    //   538: imul
    //   539: getstatic 77	uuuuuu/vllllv:bo006F006F006Foo006Fo006F	I
    //   542: irem
    //   543: tableswitch	default:+17->560, 0:+-396->147
    //   560: iconst_5
    //   561: putstatic 73	uuuuuu/vllllv:boo006F006Foo006Fo006F	I
    //   564: invokestatic 79	uuuuuu/vllllv:b00690069i00690069i0069i00690069	()I
    //   567: putstatic 75	uuuuuu/vllllv:b006Fo006F006Foo006Fo006F	I
    //   570: iload 9
    //   572: ireturn
    //   573: ldc 104
    //   575: bipush 54
    //   577: iconst_1
    //   578: invokestatic 95	xxxxxx/uxxxxx:bb00620062bb0062b0062b0062	(Ljava/lang/String;CC)Ljava/lang/String;
    //   581: astore 41
    //   583: iconst_3
    //   584: anewarray 41	java/lang/Class
    //   587: astore 42
    //   589: aload 42
    //   591: iconst_0
    //   592: ldc 28
    //   594: aastore
    //   595: aload 42
    //   597: iconst_1
    //   598: getstatic 47	java/lang/Character:TYPE	Ljava/lang/Class;
    //   601: aastore
    //   602: aload 42
    //   604: iconst_2
    //   605: getstatic 47	java/lang/Character:TYPE	Ljava/lang/Class;
    //   608: aastore
    //   609: ldc 49
    //   611: aload 41
    //   613: aload 42
    //   615: invokevirtual 53	java/lang/Class:getMethod	(Ljava/lang/String;[Ljava/lang/Class;)Ljava/lang/reflect/Method;
    //   618: astore 43
    //   620: iconst_3
    //   621: anewarray 55	java/lang/Object
    //   624: astore 44
    //   626: aload 44
    //   628: iconst_0
    //   629: ldc 106
    //   631: aastore
    //   632: aload 44
    //   634: iconst_1
    //   635: sipush 185
    //   638: invokestatic 61	java/lang/Character:valueOf	(C)Ljava/lang/Character;
    //   641: aastore
    //   642: aload 44
    //   644: iconst_2
    //   645: iconst_3
    //   646: invokestatic 61	java/lang/Character:valueOf	(C)Ljava/lang/Character;
    //   649: aastore
    //   650: aload 43
    //   652: aconst_null
    //   653: aload 44
    //   655: invokevirtual 67	java/lang/reflect/Method:invoke	(Ljava/lang/Object;[Ljava/lang/Object;)Ljava/lang/Object;
    //   658: astore 46
    //   660: aload_1
    //   661: aload 46
    //   663: checkcast 28	java/lang/String
    //   666: invokevirtual 71	java/lang/String:equals	(Ljava/lang/Object;)Z
    //   669: ifeq -581 -> 88
    //   672: iconst_5
    //   673: istore 8
    //   675: goto -584 -> 91
    //   678: ldc 108
    //   680: sipush 175
    //   683: iconst_4
    //   684: invokestatic 95	xxxxxx/uxxxxx:bb00620062bb0062b0062b0062	(Ljava/lang/String;CC)Ljava/lang/String;
    //   687: astore 35
    //   689: iconst_4
    //   690: anewarray 41	java/lang/Class
    //   693: astore 36
    //   695: aload 36
    //   697: iconst_0
    //   698: ldc 28
    //   700: aastore
    //   701: aload 36
    //   703: iconst_1
    //   704: getstatic 47	java/lang/Character:TYPE	Ljava/lang/Class;
    //   707: aastore
    //   708: aload 36
    //   710: iconst_2
    //   711: getstatic 47	java/lang/Character:TYPE	Ljava/lang/Class;
    //   714: aastore
    //   715: aload 36
    //   717: iconst_3
    //   718: getstatic 47	java/lang/Character:TYPE	Ljava/lang/Class;
    //   721: aastore
    //   722: ldc 49
    //   724: aload 35
    //   726: aload 36
    //   728: invokevirtual 53	java/lang/Class:getMethod	(Ljava/lang/String;[Ljava/lang/Class;)Ljava/lang/reflect/Method;
    //   731: astore 37
    //   733: iconst_4
    //   734: anewarray 55	java/lang/Object
    //   737: astore 38
    //   739: aload 38
    //   741: iconst_0
    //   742: ldc 110
    //   744: aastore
    //   745: aload 38
    //   747: iconst_1
    //   748: bipush 80
    //   750: invokestatic 61	java/lang/Character:valueOf	(C)Ljava/lang/Character;
    //   753: aastore
    //   754: aload 38
    //   756: iconst_2
    //   757: bipush 94
    //   759: invokestatic 61	java/lang/Character:valueOf	(C)Ljava/lang/Character;
    //   762: aastore
    //   763: aload 38
    //   765: iconst_3
    //   766: iconst_3
    //   767: invokestatic 61	java/lang/Character:valueOf	(C)Ljava/lang/Character;
    //   770: aastore
    //   771: aload 37
    //   773: aconst_null
    //   774: aload 38
    //   776: invokevirtual 67	java/lang/reflect/Method:invoke	(Ljava/lang/Object;[Ljava/lang/Object;)Ljava/lang/Object;
    //   779: astore 40
    //   781: aload_1
    //   782: aload 40
    //   784: checkcast 28	java/lang/String
    //   787: invokevirtual 71	java/lang/String:equals	(Ljava/lang/Object;)Z
    //   790: ifeq -702 -> 88
    //   793: iconst_4
    //   794: istore 8
    //   796: goto -705 -> 91
    //   799: getstatic 113	com/db/pwcc/dbmobile/transfer/R$string:standing_order_frequency_quarterly	I
    //   802: ireturn
    //   803: getstatic 116	com/db/pwcc/dbmobile/transfer/R$string:standing_order_frequency_monthly_without_jan_jul	I
    //   806: ireturn
    //   807: ldc 118
    //   809: bipush 123
    //   811: bipush 52
    //   813: iconst_1
    //   814: invokestatic 39	xxxxxx/uxxxxx:bbbb0062b0062b0062b0062	(Ljava/lang/String;CCC)Ljava/lang/String;
    //   817: astore 29
    //   819: iconst_3
    //   820: anewarray 41	java/lang/Class
    //   823: astore 30
    //   825: aload 30
    //   827: iconst_0
    //   828: ldc 28
    //   830: aastore
    //   831: aload 30
    //   833: iconst_1
    //   834: getstatic 47	java/lang/Character:TYPE	Ljava/lang/Class;
    //   837: aastore
    //   838: aload 30
    //   840: iconst_2
    //   841: getstatic 47	java/lang/Character:TYPE	Ljava/lang/Class;
    //   844: aastore
    //   845: ldc 49
    //   847: aload 29
    //   849: aload 30
    //   851: invokevirtual 53	java/lang/Class:getMethod	(Ljava/lang/String;[Ljava/lang/Class;)Ljava/lang/reflect/Method;
    //   854: astore 31
    //   856: iconst_3
    //   857: anewarray 55	java/lang/Object
    //   860: astore 32
    //   862: aload 32
    //   864: iconst_0
    //   865: ldc 120
    //   867: aastore
    //   868: aload 32
    //   870: iconst_1
    //   871: sipush 194
    //   874: invokestatic 61	java/lang/Character:valueOf	(C)Ljava/lang/Character;
    //   877: aastore
    //   878: aload 32
    //   880: iconst_2
    //   881: iconst_2
    //   882: invokestatic 61	java/lang/Character:valueOf	(C)Ljava/lang/Character;
    //   885: aastore
    //   886: aload 31
    //   888: aconst_null
    //   889: aload 32
    //   891: invokevirtual 67	java/lang/reflect/Method:invoke	(Ljava/lang/Object;[Ljava/lang/Object;)Ljava/lang/Object;
    //   894: astore 34
    //   896: aload_1
    //   897: aload 34
    //   899: checkcast 28	java/lang/String
    //   902: invokevirtual 71	java/lang/String:equals	(Ljava/lang/Object;)Z
    //   905: ifeq -817 -> 88
    //   908: iconst_2
    //   909: istore 8
    //   911: goto -820 -> 91
    //   914: astore 33
    //   916: aload 33
    //   918: invokevirtual 124	java/lang/reflect/InvocationTargetException:getCause	()Ljava/lang/Throwable;
    //   921: athrow
    //   922: ldc 126
    //   924: bipush 122
    //   926: sipush 217
    //   929: iconst_1
    //   930: invokestatic 39	xxxxxx/uxxxxx:bbbb0062b0062b0062b0062	(Ljava/lang/String;CCC)Ljava/lang/String;
    //   933: astore 23
    //   935: iconst_3
    //   936: anewarray 41	java/lang/Class
    //   939: astore 24
    //   941: aload 24
    //   943: iconst_0
    //   944: ldc 28
    //   946: aastore
    //   947: aload 24
    //   949: iconst_1
    //   950: getstatic 47	java/lang/Character:TYPE	Ljava/lang/Class;
    //   953: aastore
    //   954: aload 24
    //   956: iconst_2
    //   957: getstatic 47	java/lang/Character:TYPE	Ljava/lang/Class;
    //   960: aastore
    //   961: ldc 49
    //   963: aload 23
    //   965: aload 24
    //   967: invokevirtual 53	java/lang/Class:getMethod	(Ljava/lang/String;[Ljava/lang/Class;)Ljava/lang/reflect/Method;
    //   970: astore 25
    //   972: iconst_3
    //   973: anewarray 55	java/lang/Object
    //   976: astore 26
    //   978: aload 26
    //   980: iconst_0
    //   981: ldc -128
    //   983: aastore
    //   984: aload 26
    //   986: iconst_1
    //   987: bipush 85
    //   989: invokestatic 61	java/lang/Character:valueOf	(C)Ljava/lang/Character;
    //   992: aastore
    //   993: aload 26
    //   995: iconst_2
    //   996: iconst_1
    //   997: invokestatic 61	java/lang/Character:valueOf	(C)Ljava/lang/Character;
    //   1000: aastore
    //   1001: aload 25
    //   1003: aconst_null
    //   1004: aload 26
    //   1006: invokevirtual 67	java/lang/reflect/Method:invoke	(Ljava/lang/Object;[Ljava/lang/Object;)Ljava/lang/Object;
    //   1009: astore 28
    //   1011: aload_1
    //   1012: aload 28
    //   1014: checkcast 28	java/lang/String
    //   1017: invokevirtual 71	java/lang/String:equals	(Ljava/lang/Object;)Z
    //   1020: ifeq -932 -> 88
    //   1023: iconst_1
    //   1024: istore 8
    //   1026: goto -935 -> 91
    //   1029: getstatic 131	com/db/pwcc/dbmobile/transfer/R$string:standing_order_frequency_half_year	I
    //   1032: ireturn
    //   1033: getstatic 134	com/db/pwcc/dbmobile/transfer/R$string:standing_order_frequency_yearly	I
    //   1036: ireturn
    //   1037: ldc -120
    //   1039: bipush 8
    //   1041: bipush 72
    //   1043: iconst_3
    //   1044: invokestatic 39	xxxxxx/uxxxxx:bbbb0062b0062b0062b0062	(Ljava/lang/String;CCC)Ljava/lang/String;
    //   1047: astore 17
    //   1049: iconst_3
    //   1050: anewarray 41	java/lang/Class
    //   1053: astore 18
    //   1055: aload 18
    //   1057: iconst_0
    //   1058: ldc 28
    //   1060: aastore
    //   1061: aload 18
    //   1063: iconst_1
    //   1064: getstatic 47	java/lang/Character:TYPE	Ljava/lang/Class;
    //   1067: aastore
    //   1068: aload 18
    //   1070: iconst_2
    //   1071: getstatic 47	java/lang/Character:TYPE	Ljava/lang/Class;
    //   1074: aastore
    //   1075: ldc 49
    //   1077: aload 17
    //   1079: aload 18
    //   1081: invokevirtual 53	java/lang/Class:getMethod	(Ljava/lang/String;[Ljava/lang/Class;)Ljava/lang/reflect/Method;
    //   1084: astore 19
    //   1086: iconst_3
    //   1087: anewarray 55	java/lang/Object
    //   1090: astore 20
    //   1092: aload 20
    //   1094: iconst_0
    //   1095: ldc -118
    //   1097: aastore
    //   1098: aload 20
    //   1100: iconst_1
    //   1101: sipush 233
    //   1104: invokestatic 61	java/lang/Character:valueOf	(C)Ljava/lang/Character;
    //   1107: aastore
    //   1108: aload 20
    //   1110: iconst_2
    //   1111: iconst_5
    //   1112: invokestatic 61	java/lang/Character:valueOf	(C)Ljava/lang/Character;
    //   1115: aastore
    //   1116: aload 19
    //   1118: aconst_null
    //   1119: aload 20
    //   1121: invokevirtual 67	java/lang/reflect/Method:invoke	(Ljava/lang/Object;[Ljava/lang/Object;)Ljava/lang/Object;
    //   1124: astore 22
    //   1126: aload_1
    //   1127: aload 22
    //   1129: checkcast 28	java/lang/String
    //   1132: invokevirtual 71	java/lang/String:equals	(Ljava/lang/Object;)Z
    //   1135: ifeq -1047 -> 88
    //   1138: iconst_3
    //   1139: istore 8
    //   1141: goto -1050 -> 91
    //   1144: astore 21
    //   1146: aload 21
    //   1148: invokevirtual 124	java/lang/reflect/InvocationTargetException:getCause	()Ljava/lang/Throwable;
    //   1151: athrow
    //   1152: getstatic 141	com/db/pwcc/dbmobile/transfer/R$string:standing_order_frequency_bimonthly	I
    //   1155: ireturn
    //   1156: ldc -113
    //   1158: bipush 51
    //   1160: sipush 155
    //   1163: iconst_1
    //   1164: invokestatic 39	xxxxxx/uxxxxx:bbbb0062b0062b0062b0062	(Ljava/lang/String;CCC)Ljava/lang/String;
    //   1167: astore 11
    //   1169: iconst_4
    //   1170: anewarray 41	java/lang/Class
    //   1173: astore 12
    //   1175: aload 12
    //   1177: iconst_0
    //   1178: ldc 28
    //   1180: aastore
    //   1181: aload 12
    //   1183: iconst_1
    //   1184: getstatic 47	java/lang/Character:TYPE	Ljava/lang/Class;
    //   1187: aastore
    //   1188: aload 12
    //   1190: iconst_2
    //   1191: getstatic 47	java/lang/Character:TYPE	Ljava/lang/Class;
    //   1194: aastore
    //   1195: aload 12
    //   1197: iconst_3
    //   1198: getstatic 47	java/lang/Character:TYPE	Ljava/lang/Class;
    //   1201: aastore
    //   1202: ldc 49
    //   1204: aload 11
    //   1206: aload 12
    //   1208: invokevirtual 53	java/lang/Class:getMethod	(Ljava/lang/String;[Ljava/lang/Class;)Ljava/lang/reflect/Method;
    //   1211: astore 13
    //   1213: iconst_4
    //   1214: anewarray 55	java/lang/Object
    //   1217: astore 14
    //   1219: aload 14
    //   1221: iconst_0
    //   1222: ldc -111
    //   1224: aastore
    //   1225: aload 14
    //   1227: iconst_1
    //   1228: bipush 23
    //   1230: invokestatic 61	java/lang/Character:valueOf	(C)Ljava/lang/Character;
    //   1233: aastore
    //   1234: aload 14
    //   1236: iconst_2
    //   1237: bipush 88
    //   1239: invokestatic 61	java/lang/Character:valueOf	(C)Ljava/lang/Character;
    //   1242: aastore
    //   1243: aload 14
    //   1245: iconst_3
    //   1246: iconst_0
    //   1247: invokestatic 61	java/lang/Character:valueOf	(C)Ljava/lang/Character;
    //   1250: aastore
    //   1251: aload 13
    //   1253: aconst_null
    //   1254: aload 14
    //   1256: invokevirtual 67	java/lang/reflect/Method:invoke	(Ljava/lang/Object;[Ljava/lang/Object;)Ljava/lang/Object;
    //   1259: astore 16
    //   1261: aload_1
    //   1262: aload 16
    //   1264: checkcast 28	java/lang/String
    //   1267: invokevirtual 71	java/lang/String:equals	(Ljava/lang/Object;)Z
    //   1270: ifeq -1182 -> 88
    //   1273: iconst_0
    //   1274: istore 8
    //   1276: goto -1185 -> 91
    //   1279: astore 39
    //   1281: aload 39
    //   1283: invokevirtual 124	java/lang/reflect/InvocationTargetException:getCause	()Ljava/lang/Throwable;
    //   1286: athrow
    //   1287: astore 59
    //   1289: aload 59
    //   1291: invokevirtual 124	java/lang/reflect/InvocationTargetException:getCause	()Ljava/lang/Throwable;
    //   1294: athrow
    //   1295: astore 52
    //   1297: aload 52
    //   1299: invokevirtual 124	java/lang/reflect/InvocationTargetException:getCause	()Ljava/lang/Throwable;
    //   1302: athrow
    //   1303: astore 27
    //   1305: aload 27
    //   1307: invokevirtual 124	java/lang/reflect/InvocationTargetException:getCause	()Ljava/lang/Throwable;
    //   1310: athrow
    //   1311: astore 15
    //   1313: aload 15
    //   1315: invokevirtual 124	java/lang/reflect/InvocationTargetException:getCause	()Ljava/lang/Throwable;
    //   1318: athrow
    //   1319: astore 45
    //   1321: aload 45
    //   1323: invokevirtual 124	java/lang/reflect/InvocationTargetException:getCause	()Ljava/lang/Throwable;
    //   1326: athrow
    //   1327: ldc -109
    //   1329: sipush 161
    //   1332: iconst_5
    //   1333: invokestatic 95	xxxxxx/uxxxxx:bb00620062bb0062b0062b0062	(Ljava/lang/String;CC)Ljava/lang/String;
    //   1336: astore_2
    //   1337: iconst_3
    //   1338: anewarray 41	java/lang/Class
    //   1341: astore_3
    //   1342: aload_3
    //   1343: iconst_0
    //   1344: ldc 28
    //   1346: aastore
    //   1347: aload_3
    //   1348: iconst_1
    //   1349: getstatic 47	java/lang/Character:TYPE	Ljava/lang/Class;
    //   1352: aastore
    //   1353: aload_3
    //   1354: iconst_2
    //   1355: getstatic 47	java/lang/Character:TYPE	Ljava/lang/Class;
    //   1358: aastore
    //   1359: ldc 49
    //   1361: aload_2
    //   1362: aload_3
    //   1363: invokevirtual 53	java/lang/Class:getMethod	(Ljava/lang/String;[Ljava/lang/Class;)Ljava/lang/reflect/Method;
    //   1366: astore 4
    //   1368: iconst_3
    //   1369: anewarray 55	java/lang/Object
    //   1372: astore 5
    //   1374: aload 5
    //   1376: iconst_0
    //   1377: ldc -107
    //   1379: aastore
    //   1380: aload 5
    //   1382: iconst_1
    //   1383: sipush 150
    //   1386: invokestatic 61	java/lang/Character:valueOf	(C)Ljava/lang/Character;
    //   1389: aastore
    //   1390: aload 5
    //   1392: iconst_2
    //   1393: iconst_1
    //   1394: invokestatic 61	java/lang/Character:valueOf	(C)Ljava/lang/Character;
    //   1397: aastore
    //   1398: aload 4
    //   1400: aconst_null
    //   1401: aload 5
    //   1403: invokevirtual 67	java/lang/reflect/Method:invoke	(Ljava/lang/Object;[Ljava/lang/Object;)Ljava/lang/Object;
    //   1406: astore 7
    //   1408: aload_1
    //   1409: aload 7
    //   1411: checkcast 28	java/lang/String
    //   1414: invokevirtual 71	java/lang/String:equals	(Ljava/lang/Object;)Z
    //   1417: ifeq -1329 -> 88
    //   1420: bipush 7
    //   1422: istore 8
    //   1424: goto -1333 -> 91
    //   1427: astore 6
    //   1429: aload 6
    //   1431: invokevirtual 124	java/lang/reflect/InvocationTargetException:getCause	()Ljava/lang/Throwable;
    //   1434: athrow
    // Local variable table:
    //   start	length	slot	name	signature
    //   0	1435	0	this	vllllv
    //   0	1435	1	paramString	String
    //   1336	26	2	str1	String
    //   1341	22	3	arrayOfClass1	Class[]
    //   1366	33	4	localMethod1	java.lang.reflect.Method
    //   1372	30	5	arrayOfObject1	Object[]
    //   1427	3	6	localInvocationTargetException1	java.lang.reflect.InvocationTargetException
    //   1406	4	7	localObject1	Object
    //   89	1334	8	i	int
    //   145	426	9	j	int
    //   528	11	10	k	int
    //   1167	38	11	str2	String
    //   1173	34	12	arrayOfClass2	Class[]
    //   1211	41	13	localMethod2	java.lang.reflect.Method
    //   1217	38	14	arrayOfObject2	Object[]
    //   1311	3	15	localInvocationTargetException2	java.lang.reflect.InvocationTargetException
    //   1259	4	16	localObject2	Object
    //   1047	31	17	str3	String
    //   1053	27	18	arrayOfClass3	Class[]
    //   1084	33	19	localMethod3	java.lang.reflect.Method
    //   1090	30	20	arrayOfObject3	Object[]
    //   1144	3	21	localInvocationTargetException3	java.lang.reflect.InvocationTargetException
    //   1124	4	22	localObject3	Object
    //   933	31	23	str4	String
    //   939	27	24	arrayOfClass4	Class[]
    //   970	32	25	localMethod4	java.lang.reflect.Method
    //   976	29	26	arrayOfObject4	Object[]
    //   1303	3	27	localInvocationTargetException4	java.lang.reflect.InvocationTargetException
    //   1009	4	28	localObject4	Object
    //   817	31	29	str5	String
    //   823	27	30	arrayOfClass5	Class[]
    //   854	33	31	localMethod5	java.lang.reflect.Method
    //   860	30	32	arrayOfObject5	Object[]
    //   914	3	33	localInvocationTargetException5	java.lang.reflect.InvocationTargetException
    //   894	4	34	localObject5	Object
    //   687	38	35	str6	String
    //   693	34	36	arrayOfClass6	Class[]
    //   731	41	37	localMethod6	java.lang.reflect.Method
    //   737	38	38	arrayOfObject6	Object[]
    //   1279	3	39	localInvocationTargetException6	java.lang.reflect.InvocationTargetException
    //   779	4	40	localObject6	Object
    //   581	31	41	str7	String
    //   587	27	42	arrayOfClass7	Class[]
    //   618	33	43	localMethod7	java.lang.reflect.Method
    //   624	30	44	arrayOfObject7	Object[]
    //   1319	3	45	localInvocationTargetException7	java.lang.reflect.InvocationTargetException
    //   658	4	46	localObject7	Object
    //   334	11	47	m	int
    //   388	31	48	str8	String
    //   394	27	49	arrayOfClass8	Class[]
    //   425	32	50	localMethod8	java.lang.reflect.Method
    //   431	29	51	arrayOfObject8	Object[]
    //   1295	3	52	localInvocationTargetException8	java.lang.reflect.InvocationTargetException
    //   464	4	53	localObject8	Object
    //   475	34	54	bool	boolean
    //   160	38	55	str9	String
    //   166	34	56	arrayOfClass9	Class[]
    //   204	42	57	localMethod9	java.lang.reflect.Method
    //   210	39	58	arrayOfObject9	Object[]
    //   1287	3	59	localInvocationTargetException9	java.lang.reflect.InvocationTargetException
    //   253	4	60	localObject9	Object
    //   274	11	61	n	int
    // Exception table:
    //   from	to	target	type
    //   886	896	914	java/lang/reflect/InvocationTargetException
    //   1116	1126	1144	java/lang/reflect/InvocationTargetException
    //   771	781	1279	java/lang/reflect/InvocationTargetException
    //   245	255	1287	java/lang/reflect/InvocationTargetException
    //   456	466	1295	java/lang/reflect/InvocationTargetException
    //   1001	1011	1303	java/lang/reflect/InvocationTargetException
    //   1251	1261	1311	java/lang/reflect/InvocationTargetException
    //   650	660	1319	java/lang/reflect/InvocationTargetException
    //   1398	1408	1427	java/lang/reflect/InvocationTargetException
  }
  
  public String b0071q00710071qq0071qqq(int paramInt)
  {
    if ((boo006F006Foo006Fo006F + b006Fo006F006Foo006Fo006F) * boo006F006Foo006Fo006F % bo006F006F006Foo006Fo006F != b006F006F006F006Foo006Fo006F)
    {
      int m = boo006F006Foo006Fo006F;
      switch (m * (m + b006Fo006F006Foo006Fo006F) % bo006F006F006Foo006Fo006F)
      {
      default: 
        boo006F006Foo006Fo006F = 20;
        b006F006F006F006Foo006Fo006F = b00690069i00690069i0069i00690069();
      }
      boo006F006Foo006Fo006F = 63;
      b006F006F006F006Foo006Fo006F = 6;
    }
    if (paramInt < getCount())
    {
      String str = (String)getItem(paramInt);
      if (str != null)
      {
        int i = bii006900690069i0069i00690069(str);
        int j = boo006F006Foo006Fo006F;
        switch (j * (j + b006Fo006F006Foo006Fo006F) % bo006F006F006Foo006Fo006F)
        {
        default: 
          boo006F006Foo006Fo006F = b00690069i00690069i0069i00690069();
          b006F006F006F006Foo006Fo006F = b00690069i00690069i0069i00690069();
        }
        if (i != -1)
        {
          Context localContext = getContext();
          int k = boo006F006Foo006Fo006F;
          switch (k * (k + bi0069i00690069i0069i00690069()) % bo006F006F006Foo006Fo006F)
          {
          default: 
            boo006F006Foo006Fo006F = b00690069i00690069i0069i00690069();
            b006F006F006F006Foo006Fo006F = b00690069i00690069i0069i00690069();
          }
          return localContext.getString(i);
        }
      }
    }
    return "";
  }
}
