package uuuuuu;

public class vlvlll
  extends qppppp<tntttn.ttnttn>
  implements tntttn.nntttn, vpvvpv.pvvvpv
{
  public static int b006F006F006Fo006Fo006F006Fo = 26;
  private static final String b006Fo006Fo006Fo006F006Fo;
  public static int b006Foo006F006Fo006F006Fo = 1;
  public static int bo006Fo006F006Fo006F006Fo = 2;
  public static int booo006F006Fo006F006Fo;
  private final vpvvpv bo006F006Fo006Fo006F006Fo = new fmmfff();
  
  /* Error */
  static
  {
    // Byte code:
    //   0: getstatic 29	uuuuuu/vlvlll:b006F006F006Fo006Fo006F006Fo	I
    //   3: getstatic 31	uuuuuu/vlvlll:b006Foo006F006Fo006F006Fo	I
    //   6: iadd
    //   7: getstatic 29	uuuuuu/vlvlll:b006F006F006Fo006Fo006F006Fo	I
    //   10: imul
    //   11: getstatic 33	uuuuuu/vlvlll:bo006Fo006F006Fo006F006Fo	I
    //   14: irem
    //   15: getstatic 35	uuuuuu/vlvlll:booo006F006Fo006F006Fo	I
    //   18: if_icmpeq +286 -> 304
    //   21: getstatic 29	uuuuuu/vlvlll:b006F006F006Fo006Fo006F006Fo	I
    //   24: istore_2
    //   25: ldc 2
    //   27: ldc 37
    //   29: sipush 203
    //   32: iconst_1
    //   33: invokestatic 43	xxxxxx/uxxxxx:bb00620062bb0062b0062b0062	(Ljava/lang/String;CC)Ljava/lang/String;
    //   36: iconst_0
    //   37: anewarray 45	java/lang/Class
    //   40: invokevirtual 49	java/lang/Class:getMethod	(Ljava/lang/String;[Ljava/lang/Class;)Ljava/lang/reflect/Method;
    //   43: astore_3
    //   44: iconst_0
    //   45: anewarray 51	java/lang/Object
    //   48: astore 4
    //   50: aload_3
    //   51: aconst_null
    //   52: aload 4
    //   54: invokevirtual 57	java/lang/reflect/Method:invoke	(Ljava/lang/Object;[Ljava/lang/Object;)Ljava/lang/Object;
    //   57: astore 6
    //   59: iload_2
    //   60: aload 6
    //   62: checkcast 59	java/lang/Integer
    //   65: invokevirtual 63	java/lang/Integer:intValue	()I
    //   68: iadd
    //   69: getstatic 29	uuuuuu/vlvlll:b006F006F006Fo006Fo006F006Fo	I
    //   72: imul
    //   73: getstatic 33	uuuuuu/vlvlll:bo006Fo006F006Fo006F006Fo	I
    //   76: irem
    //   77: getstatic 35	uuuuuu/vlvlll:booo006F006Fo006F006Fo	I
    //   80: if_icmpeq +214 -> 294
    //   83: getstatic 29	uuuuuu/vlvlll:b006F006F006Fo006Fo006F006Fo	I
    //   86: istore 7
    //   88: ldc 2
    //   90: ldc 65
    //   92: bipush 40
    //   94: bipush 60
    //   96: iconst_2
    //   97: invokestatic 69	xxxxxx/uxxxxx:bbbb0062b0062b0062b0062	(Ljava/lang/String;CCC)Ljava/lang/String;
    //   100: iconst_0
    //   101: anewarray 45	java/lang/Class
    //   104: invokevirtual 49	java/lang/Class:getMethod	(Ljava/lang/String;[Ljava/lang/Class;)Ljava/lang/reflect/Method;
    //   107: astore 8
    //   109: iconst_0
    //   110: anewarray 51	java/lang/Object
    //   113: astore 9
    //   115: aload 8
    //   117: aconst_null
    //   118: aload 9
    //   120: invokevirtual 57	java/lang/reflect/Method:invoke	(Ljava/lang/Object;[Ljava/lang/Object;)Ljava/lang/Object;
    //   123: astore 11
    //   125: iload 7
    //   127: aload 11
    //   129: checkcast 59	java/lang/Integer
    //   132: invokevirtual 63	java/lang/Integer:intValue	()I
    //   135: iadd
    //   136: getstatic 29	uuuuuu/vlvlll:b006F006F006Fo006Fo006F006Fo	I
    //   139: imul
    //   140: getstatic 33	uuuuuu/vlvlll:bo006Fo006F006Fo006F006Fo	I
    //   143: irem
    //   144: getstatic 35	uuuuuu/vlvlll:booo006F006Fo006F006Fo	I
    //   147: if_icmpeq +55 -> 202
    //   150: ldc 2
    //   152: ldc 71
    //   154: sipush 129
    //   157: iconst_1
    //   158: invokestatic 43	xxxxxx/uxxxxx:bb00620062bb0062b0062b0062	(Ljava/lang/String;CC)Ljava/lang/String;
    //   161: iconst_0
    //   162: anewarray 45	java/lang/Class
    //   165: invokevirtual 49	java/lang/Class:getMethod	(Ljava/lang/String;[Ljava/lang/Class;)Ljava/lang/reflect/Method;
    //   168: astore 20
    //   170: iconst_0
    //   171: anewarray 51	java/lang/Object
    //   174: astore 21
    //   176: aload 20
    //   178: aconst_null
    //   179: aload 21
    //   181: invokevirtual 57	java/lang/reflect/Method:invoke	(Ljava/lang/Object;[Ljava/lang/Object;)Ljava/lang/Object;
    //   184: astore 23
    //   186: aload 23
    //   188: checkcast 59	java/lang/Integer
    //   191: invokevirtual 63	java/lang/Integer:intValue	()I
    //   194: putstatic 29	uuuuuu/vlvlll:b006F006F006Fo006Fo006F006Fo	I
    //   197: bipush 64
    //   199: putstatic 35	uuuuuu/vlvlll:booo006F006Fo006F006Fo	I
    //   202: ldc 2
    //   204: ldc 73
    //   206: bipush 40
    //   208: iconst_4
    //   209: invokestatic 43	xxxxxx/uxxxxx:bb00620062bb0062b0062b0062	(Ljava/lang/String;CC)Ljava/lang/String;
    //   212: iconst_0
    //   213: anewarray 45	java/lang/Class
    //   216: invokevirtual 49	java/lang/Class:getMethod	(Ljava/lang/String;[Ljava/lang/Class;)Ljava/lang/reflect/Method;
    //   219: astore 12
    //   221: iconst_0
    //   222: anewarray 51	java/lang/Object
    //   225: astore 13
    //   227: aload 12
    //   229: aconst_null
    //   230: aload 13
    //   232: invokevirtual 57	java/lang/reflect/Method:invoke	(Ljava/lang/Object;[Ljava/lang/Object;)Ljava/lang/Object;
    //   235: astore 15
    //   237: aload 15
    //   239: checkcast 59	java/lang/Integer
    //   242: invokevirtual 63	java/lang/Integer:intValue	()I
    //   245: putstatic 29	uuuuuu/vlvlll:b006F006F006Fo006Fo006F006Fo	I
    //   248: ldc 2
    //   250: ldc 75
    //   252: bipush 11
    //   254: iconst_5
    //   255: invokestatic 43	xxxxxx/uxxxxx:bb00620062bb0062b0062b0062	(Ljava/lang/String;CC)Ljava/lang/String;
    //   258: iconst_0
    //   259: anewarray 45	java/lang/Class
    //   262: invokevirtual 49	java/lang/Class:getMethod	(Ljava/lang/String;[Ljava/lang/Class;)Ljava/lang/reflect/Method;
    //   265: astore 16
    //   267: iconst_0
    //   268: anewarray 51	java/lang/Object
    //   271: astore 17
    //   273: aload 16
    //   275: aconst_null
    //   276: aload 17
    //   278: invokevirtual 57	java/lang/reflect/Method:invoke	(Ljava/lang/Object;[Ljava/lang/Object;)Ljava/lang/Object;
    //   281: astore 19
    //   283: aload 19
    //   285: checkcast 59	java/lang/Integer
    //   288: invokevirtual 63	java/lang/Integer:intValue	()I
    //   291: putstatic 35	uuuuuu/vlvlll:booo006F006Fo006F006Fo	I
    //   294: bipush 57
    //   296: putstatic 29	uuuuuu/vlvlll:b006F006F006Fo006Fo006F006Fo	I
    //   299: bipush 33
    //   301: putstatic 35	uuuuuu/vlvlll:booo006F006Fo006F006Fo	I
    //   304: ldc 2
    //   306: invokevirtual 79	java/lang/Class:getSimpleName	()Ljava/lang/String;
    //   309: putstatic 81	uuuuuu/vlvlll:b006Fo006Fo006Fo006F006Fo	Ljava/lang/String;
    //   312: iconst_m1
    //   313: newarray int
    //   315: pop
    //   316: goto -4 -> 312
    //   319: astore 5
    //   321: aload 5
    //   323: invokevirtual 85	java/lang/reflect/InvocationTargetException:getCause	()Ljava/lang/Throwable;
    //   326: athrow
    //   327: astore 10
    //   329: aload 10
    //   331: invokevirtual 85	java/lang/reflect/InvocationTargetException:getCause	()Ljava/lang/Throwable;
    //   334: athrow
    //   335: astore 14
    //   337: aload 14
    //   339: invokevirtual 85	java/lang/reflect/InvocationTargetException:getCause	()Ljava/lang/Throwable;
    //   342: athrow
    //   343: astore 18
    //   345: aload 18
    //   347: invokevirtual 85	java/lang/reflect/InvocationTargetException:getCause	()Ljava/lang/Throwable;
    //   350: athrow
    //   351: astore 22
    //   353: aload 22
    //   355: invokevirtual 85	java/lang/reflect/InvocationTargetException:getCause	()Ljava/lang/Throwable;
    //   358: athrow
    //   359: astore_0
    //   360: return
    // Local variable table:
    //   start	length	slot	name	signature
    //   359	1	0	localException	Exception
    //   24	45	2	i	int
    //   43	8	3	localMethod1	java.lang.reflect.Method
    //   48	5	4	arrayOfObject1	Object[]
    //   319	3	5	localInvocationTargetException1	java.lang.reflect.InvocationTargetException
    //   57	4	6	localObject1	Object
    //   86	50	7	j	int
    //   107	9	8	localMethod2	java.lang.reflect.Method
    //   113	6	9	arrayOfObject2	Object[]
    //   327	3	10	localInvocationTargetException2	java.lang.reflect.InvocationTargetException
    //   123	5	11	localObject2	Object
    //   219	9	12	localMethod3	java.lang.reflect.Method
    //   225	6	13	arrayOfObject3	Object[]
    //   335	3	14	localInvocationTargetException3	java.lang.reflect.InvocationTargetException
    //   235	3	15	localObject3	Object
    //   265	9	16	localMethod4	java.lang.reflect.Method
    //   271	6	17	arrayOfObject4	Object[]
    //   343	3	18	localInvocationTargetException4	java.lang.reflect.InvocationTargetException
    //   281	3	19	localObject4	Object
    //   168	9	20	localMethod5	java.lang.reflect.Method
    //   174	6	21	arrayOfObject5	Object[]
    //   351	3	22	localInvocationTargetException5	java.lang.reflect.InvocationTargetException
    //   184	3	23	localObject5	Object
    // Exception table:
    //   from	to	target	type
    //   50	59	319	java/lang/reflect/InvocationTargetException
    //   115	125	327	java/lang/reflect/InvocationTargetException
    //   227	237	335	java/lang/reflect/InvocationTargetException
    //   273	283	343	java/lang/reflect/InvocationTargetException
    //   176	186	351	java/lang/reflect/InvocationTargetException
    //   312	316	359	java/lang/Exception
  }
  
  public vlvlll() {}
  
  public static int b006900690069iiiii00690069()
  {
    return 1;
  }
  
  public static int bi00690069iiiii00690069()
  {
    return 2;
  }
  
  public static int biii0069iiii00690069()
  {
    return 92;
  }
  
  /* Error */
  public void b00690069006900690069i0069ii0069()
  {
    // Byte code:
    //   0: aload_0
    //   1: getfield 101	uuuuuu/vlvlll:bnnnnn006E006E006En	Luuuuuu/ttssst$tsssst;
    //   4: checkcast 103	uuuuuu/tntttn$ttnttn
    //   7: invokeinterface 106 1 0
    //   12: aload_0
    //   13: getfield 93	uuuuuu/vlvlll:bo006F006Fo006Fo006F006Fo	Luuuuuu/vpvvpv;
    //   16: astore_1
    //   17: getstatic 29	uuuuuu/vlvlll:b006F006F006Fo006Fo006F006Fo	I
    //   20: istore_2
    //   21: iload_2
    //   22: iload_2
    //   23: getstatic 31	uuuuuu/vlvlll:b006Foo006F006Fo006F006Fo	I
    //   26: iadd
    //   27: imul
    //   28: getstatic 33	uuuuuu/vlvlll:bo006Fo006F006Fo006F006Fo	I
    //   31: irem
    //   32: tableswitch	default:+20->52, 0:+72->104
    //   52: bipush 11
    //   54: putstatic 29	uuuuuu/vlvlll:b006F006F006Fo006Fo006F006Fo	I
    //   57: ldc 2
    //   59: ldc 108
    //   61: sipush 250
    //   64: iconst_1
    //   65: invokestatic 43	xxxxxx/uxxxxx:bb00620062bb0062b0062b0062	(Ljava/lang/String;CC)Ljava/lang/String;
    //   68: iconst_0
    //   69: anewarray 45	java/lang/Class
    //   72: invokevirtual 49	java/lang/Class:getMethod	(Ljava/lang/String;[Ljava/lang/Class;)Ljava/lang/reflect/Method;
    //   75: astore 26
    //   77: iconst_0
    //   78: anewarray 51	java/lang/Object
    //   81: astore 27
    //   83: aload 26
    //   85: aconst_null
    //   86: aload 27
    //   88: invokevirtual 57	java/lang/reflect/Method:invoke	(Ljava/lang/Object;[Ljava/lang/Object;)Ljava/lang/Object;
    //   91: astore 29
    //   93: aload 29
    //   95: checkcast 59	java/lang/Integer
    //   98: invokevirtual 63	java/lang/Integer:intValue	()I
    //   101: putstatic 35	uuuuuu/vlvlll:booo006F006Fo006F006Fo	I
    //   104: getstatic 29	uuuuuu/vlvlll:b006F006F006Fo006Fo006F006Fo	I
    //   107: getstatic 31	uuuuuu/vlvlll:b006Foo006F006Fo006F006Fo	I
    //   110: iadd
    //   111: getstatic 29	uuuuuu/vlvlll:b006F006F006Fo006Fo006F006Fo	I
    //   114: imul
    //   115: getstatic 33	uuuuuu/vlvlll:bo006Fo006F006Fo006F006Fo	I
    //   118: irem
    //   119: getstatic 35	uuuuuu/vlvlll:booo006F006Fo006F006Fo	I
    //   122: if_icmpeq +55 -> 177
    //   125: bipush 50
    //   127: putstatic 29	uuuuuu/vlvlll:b006F006F006Fo006Fo006F006Fo	I
    //   130: ldc 2
    //   132: ldc 110
    //   134: sipush 177
    //   137: iconst_2
    //   138: invokestatic 43	xxxxxx/uxxxxx:bb00620062bb0062b0062b0062	(Ljava/lang/String;CC)Ljava/lang/String;
    //   141: iconst_0
    //   142: anewarray 45	java/lang/Class
    //   145: invokevirtual 49	java/lang/Class:getMethod	(Ljava/lang/String;[Ljava/lang/Class;)Ljava/lang/reflect/Method;
    //   148: astore 22
    //   150: iconst_0
    //   151: anewarray 51	java/lang/Object
    //   154: astore 23
    //   156: aload 22
    //   158: aconst_null
    //   159: aload 23
    //   161: invokevirtual 57	java/lang/reflect/Method:invoke	(Ljava/lang/Object;[Ljava/lang/Object;)Ljava/lang/Object;
    //   164: astore 25
    //   166: aload 25
    //   168: checkcast 59	java/lang/Integer
    //   171: invokevirtual 63	java/lang/Integer:intValue	()I
    //   174: putstatic 35	uuuuuu/vlvlll:booo006F006Fo006F006Fo	I
    //   177: ldc 2
    //   179: ldc 112
    //   181: sipush 247
    //   184: iconst_0
    //   185: invokestatic 43	xxxxxx/uxxxxx:bb00620062bb0062b0062b0062	(Ljava/lang/String;CC)Ljava/lang/String;
    //   188: iconst_0
    //   189: anewarray 45	java/lang/Class
    //   192: invokevirtual 49	java/lang/Class:getMethod	(Ljava/lang/String;[Ljava/lang/Class;)Ljava/lang/reflect/Method;
    //   195: astore_3
    //   196: iconst_0
    //   197: anewarray 51	java/lang/Object
    //   200: astore 4
    //   202: aload_3
    //   203: aconst_null
    //   204: aload 4
    //   206: invokevirtual 57	java/lang/reflect/Method:invoke	(Ljava/lang/Object;[Ljava/lang/Object;)Ljava/lang/Object;
    //   209: astore 6
    //   211: aload 6
    //   213: checkcast 59	java/lang/Integer
    //   216: invokevirtual 63	java/lang/Integer:intValue	()I
    //   219: getstatic 31	uuuuuu/vlvlll:b006Foo006F006Fo006F006Fo	I
    //   222: iadd
    //   223: istore 7
    //   225: ldc 2
    //   227: ldc 114
    //   229: sipush 146
    //   232: sipush 243
    //   235: iconst_0
    //   236: invokestatic 69	xxxxxx/uxxxxx:bbbb0062b0062b0062b0062	(Ljava/lang/String;CCC)Ljava/lang/String;
    //   239: iconst_0
    //   240: anewarray 45	java/lang/Class
    //   243: invokevirtual 49	java/lang/Class:getMethod	(Ljava/lang/String;[Ljava/lang/Class;)Ljava/lang/reflect/Method;
    //   246: astore 8
    //   248: iconst_0
    //   249: anewarray 51	java/lang/Object
    //   252: astore 9
    //   254: aload 8
    //   256: aconst_null
    //   257: aload 9
    //   259: invokevirtual 57	java/lang/reflect/Method:invoke	(Ljava/lang/Object;[Ljava/lang/Object;)Ljava/lang/Object;
    //   262: astore 11
    //   264: iload 7
    //   266: aload 11
    //   268: checkcast 59	java/lang/Integer
    //   271: invokevirtual 63	java/lang/Integer:intValue	()I
    //   274: imul
    //   275: getstatic 33	uuuuuu/vlvlll:bo006Fo006F006Fo006F006Fo	I
    //   278: irem
    //   279: getstatic 35	uuuuuu/vlvlll:booo006F006Fo006F006Fo	I
    //   282: if_icmpeq +54 -> 336
    //   285: bipush 80
    //   287: putstatic 29	uuuuuu/vlvlll:b006F006F006Fo006Fo006F006Fo	I
    //   290: ldc 2
    //   292: ldc 116
    //   294: bipush 42
    //   296: iconst_0
    //   297: invokestatic 43	xxxxxx/uxxxxx:bb00620062bb0062b0062b0062	(Ljava/lang/String;CC)Ljava/lang/String;
    //   300: iconst_0
    //   301: anewarray 45	java/lang/Class
    //   304: invokevirtual 49	java/lang/Class:getMethod	(Ljava/lang/String;[Ljava/lang/Class;)Ljava/lang/reflect/Method;
    //   307: astore 18
    //   309: iconst_0
    //   310: anewarray 51	java/lang/Object
    //   313: astore 19
    //   315: aload 18
    //   317: aconst_null
    //   318: aload 19
    //   320: invokevirtual 57	java/lang/reflect/Method:invoke	(Ljava/lang/Object;[Ljava/lang/Object;)Ljava/lang/Object;
    //   323: astore 21
    //   325: aload 21
    //   327: checkcast 59	java/lang/Integer
    //   330: invokevirtual 63	java/lang/Integer:intValue	()I
    //   333: putstatic 35	uuuuuu/vlvlll:booo006F006Fo006F006Fo	I
    //   336: aload_0
    //   337: getfield 120	uuuuuu/vlvlll:b006E006E006E006E006En006E006En	Luuuuuu/hyhyhh;
    //   340: astore 12
    //   342: getstatic 29	uuuuuu/vlvlll:b006F006F006Fo006Fo006F006Fo	I
    //   345: istore 13
    //   347: iload 13
    //   349: iload 13
    //   351: getstatic 31	uuuuuu/vlvlll:b006Foo006F006Fo006F006Fo	I
    //   354: iadd
    //   355: imul
    //   356: getstatic 33	uuuuuu/vlvlll:bo006Fo006F006Fo006F006Fo	I
    //   359: irem
    //   360: tableswitch	default:+20->380, 0:+72->432
    //   380: ldc 2
    //   382: ldc 122
    //   384: sipush 162
    //   387: iconst_0
    //   388: invokestatic 43	xxxxxx/uxxxxx:bb00620062bb0062b0062b0062	(Ljava/lang/String;CC)Ljava/lang/String;
    //   391: iconst_0
    //   392: anewarray 45	java/lang/Class
    //   395: invokevirtual 49	java/lang/Class:getMethod	(Ljava/lang/String;[Ljava/lang/Class;)Ljava/lang/reflect/Method;
    //   398: astore 14
    //   400: iconst_0
    //   401: anewarray 51	java/lang/Object
    //   404: astore 15
    //   406: aload 14
    //   408: aconst_null
    //   409: aload 15
    //   411: invokevirtual 57	java/lang/reflect/Method:invoke	(Ljava/lang/Object;[Ljava/lang/Object;)Ljava/lang/Object;
    //   414: astore 17
    //   416: aload 17
    //   418: checkcast 59	java/lang/Integer
    //   421: invokevirtual 63	java/lang/Integer:intValue	()I
    //   424: putstatic 29	uuuuuu/vlvlll:b006F006F006Fo006Fo006F006Fo	I
    //   427: bipush 68
    //   429: putstatic 35	uuuuuu/vlvlll:booo006F006Fo006F006Fo	I
    //   432: aload_1
    //   433: aload_0
    //   434: aload 12
    //   436: invokevirtual 127	uuuuuu/hyhyhh:b0070pp007000700070p007000700070	()Ljava/lang/String;
    //   439: invokeinterface 133 3 0
    //   444: return
    //   445: astore 28
    //   447: aload 28
    //   449: invokevirtual 85	java/lang/reflect/InvocationTargetException:getCause	()Ljava/lang/Throwable;
    //   452: athrow
    //   453: astore 5
    //   455: aload 5
    //   457: invokevirtual 85	java/lang/reflect/InvocationTargetException:getCause	()Ljava/lang/Throwable;
    //   460: athrow
    //   461: astore 10
    //   463: aload 10
    //   465: invokevirtual 85	java/lang/reflect/InvocationTargetException:getCause	()Ljava/lang/Throwable;
    //   468: athrow
    //   469: astore 20
    //   471: aload 20
    //   473: invokevirtual 85	java/lang/reflect/InvocationTargetException:getCause	()Ljava/lang/Throwable;
    //   476: athrow
    //   477: astore 16
    //   479: aload 16
    //   481: invokevirtual 85	java/lang/reflect/InvocationTargetException:getCause	()Ljava/lang/Throwable;
    //   484: athrow
    //   485: astore 24
    //   487: aload 24
    //   489: invokevirtual 85	java/lang/reflect/InvocationTargetException:getCause	()Ljava/lang/Throwable;
    //   492: athrow
    // Local variable table:
    //   start	length	slot	name	signature
    //   0	493	0	this	vlvlll
    //   16	417	1	localVpvvpv	vpvvpv
    //   20	8	2	i	int
    //   195	8	3	localMethod1	java.lang.reflect.Method
    //   200	5	4	arrayOfObject1	Object[]
    //   453	3	5	localInvocationTargetException1	java.lang.reflect.InvocationTargetException
    //   209	3	6	localObject1	Object
    //   223	52	7	j	int
    //   246	9	8	localMethod2	java.lang.reflect.Method
    //   252	6	9	arrayOfObject2	Object[]
    //   461	3	10	localInvocationTargetException2	java.lang.reflect.InvocationTargetException
    //   262	5	11	localObject2	Object
    //   340	95	12	localHyhyhh	hyhyhh
    //   345	11	13	k	int
    //   398	9	14	localMethod3	java.lang.reflect.Method
    //   404	6	15	arrayOfObject3	Object[]
    //   477	3	16	localInvocationTargetException3	java.lang.reflect.InvocationTargetException
    //   414	3	17	localObject3	Object
    //   307	9	18	localMethod4	java.lang.reflect.Method
    //   313	6	19	arrayOfObject4	Object[]
    //   469	3	20	localInvocationTargetException4	java.lang.reflect.InvocationTargetException
    //   323	3	21	localObject4	Object
    //   148	9	22	localMethod5	java.lang.reflect.Method
    //   154	6	23	arrayOfObject5	Object[]
    //   485	3	24	localInvocationTargetException5	java.lang.reflect.InvocationTargetException
    //   164	3	25	localObject5	Object
    //   75	9	26	localMethod6	java.lang.reflect.Method
    //   81	6	27	arrayOfObject6	Object[]
    //   445	3	28	localInvocationTargetException6	java.lang.reflect.InvocationTargetException
    //   91	3	29	localObject6	Object
    // Exception table:
    //   from	to	target	type
    //   83	93	445	java/lang/reflect/InvocationTargetException
    //   202	211	453	java/lang/reflect/InvocationTargetException
    //   254	264	461	java/lang/reflect/InvocationTargetException
    //   315	325	469	java/lang/reflect/InvocationTargetException
    //   406	416	477	java/lang/reflect/InvocationTargetException
    //   156	166	485	java/lang/reflect/InvocationTargetException
  }
  
  /* Error */
  public void b007000700070007000700070p00700070p(com.db.pwcc.dbmobile.model.error.DbError paramDbError)
  {
    // Byte code:
    //   0: getstatic 81	uuuuuu/vlvlll:b006Fo006Fo006Fo006F006Fo	Ljava/lang/String;
    //   3: astore_2
    //   4: new 137	java/lang/StringBuilder
    //   7: dup
    //   8: invokespecial 138	java/lang/StringBuilder:<init>	()V
    //   11: astore_3
    //   12: ldc -116
    //   14: bipush 58
    //   16: iconst_2
    //   17: invokestatic 43	xxxxxx/uxxxxx:bb00620062bb0062b0062b0062	(Ljava/lang/String;CC)Ljava/lang/String;
    //   20: astore 4
    //   22: iconst_3
    //   23: anewarray 45	java/lang/Class
    //   26: astore 5
    //   28: aload 5
    //   30: iconst_0
    //   31: ldc -114
    //   33: aastore
    //   34: aload 5
    //   36: iconst_1
    //   37: getstatic 148	java/lang/Character:TYPE	Ljava/lang/Class;
    //   40: aastore
    //   41: aload 5
    //   43: iconst_2
    //   44: getstatic 148	java/lang/Character:TYPE	Ljava/lang/Class;
    //   47: aastore
    //   48: ldc -106
    //   50: aload 4
    //   52: aload 5
    //   54: invokevirtual 49	java/lang/Class:getMethod	(Ljava/lang/String;[Ljava/lang/Class;)Ljava/lang/reflect/Method;
    //   57: astore 6
    //   59: iconst_3
    //   60: anewarray 51	java/lang/Object
    //   63: astore 7
    //   65: aload 7
    //   67: iconst_0
    //   68: ldc -104
    //   70: aastore
    //   71: aload 7
    //   73: iconst_1
    //   74: bipush 89
    //   76: invokestatic 156	java/lang/Character:valueOf	(C)Ljava/lang/Character;
    //   79: aastore
    //   80: aload 7
    //   82: iconst_2
    //   83: iconst_5
    //   84: invokestatic 156	java/lang/Character:valueOf	(C)Ljava/lang/Character;
    //   87: aastore
    //   88: aload 6
    //   90: aconst_null
    //   91: aload 7
    //   93: invokevirtual 57	java/lang/reflect/Method:invoke	(Ljava/lang/Object;[Ljava/lang/Object;)Ljava/lang/Object;
    //   96: astore 9
    //   98: aload_2
    //   99: aload_3
    //   100: aload 9
    //   102: checkcast 142	java/lang/String
    //   105: invokevirtual 160	java/lang/StringBuilder:append	(Ljava/lang/String;)Ljava/lang/StringBuilder;
    //   108: aload_1
    //   109: invokevirtual 165	com/db/pwcc/dbmobile/model/error/DbError:getMessage	()Ljava/lang/String;
    //   112: invokevirtual 160	java/lang/StringBuilder:append	(Ljava/lang/String;)Ljava/lang/StringBuilder;
    //   115: invokevirtual 168	java/lang/StringBuilder:toString	()Ljava/lang/String;
    //   118: invokestatic 174	uuuuuu/rvvvrv:bq0071qq00710071q0071q0071	(Ljava/lang/String;Ljava/lang/String;)V
    //   121: aload_0
    //   122: invokevirtual 178	uuuuuu/vlvlll:bkk006Bk006Bk006Bk006Bk	()Z
    //   125: ifne +166 -> 291
    //   128: getstatic 29	uuuuuu/vlvlll:b006F006F006Fo006Fo006F006Fo	I
    //   131: istore 26
    //   133: getstatic 29	uuuuuu/vlvlll:b006F006F006Fo006Fo006F006Fo	I
    //   136: istore 27
    //   138: ldc 2
    //   140: ldc -76
    //   142: bipush 115
    //   144: iconst_1
    //   145: invokestatic 43	xxxxxx/uxxxxx:bb00620062bb0062b0062b0062	(Ljava/lang/String;CC)Ljava/lang/String;
    //   148: iconst_0
    //   149: anewarray 45	java/lang/Class
    //   152: invokevirtual 49	java/lang/Class:getMethod	(Ljava/lang/String;[Ljava/lang/Class;)Ljava/lang/reflect/Method;
    //   155: astore 28
    //   157: iconst_0
    //   158: anewarray 51	java/lang/Object
    //   161: astore 29
    //   163: aload 28
    //   165: aconst_null
    //   166: aload 29
    //   168: invokevirtual 57	java/lang/reflect/Method:invoke	(Ljava/lang/Object;[Ljava/lang/Object;)Ljava/lang/Object;
    //   171: astore 31
    //   173: iload 27
    //   175: aload 31
    //   177: checkcast 59	java/lang/Integer
    //   180: invokevirtual 63	java/lang/Integer:intValue	()I
    //   183: iadd
    //   184: getstatic 29	uuuuuu/vlvlll:b006F006F006Fo006Fo006F006Fo	I
    //   187: imul
    //   188: getstatic 33	uuuuuu/vlvlll:bo006Fo006F006Fo006F006Fo	I
    //   191: irem
    //   192: getstatic 35	uuuuuu/vlvlll:booo006F006Fo006F006Fo	I
    //   195: if_icmpeq +13 -> 208
    //   198: bipush 65
    //   200: putstatic 29	uuuuuu/vlvlll:b006F006F006Fo006Fo006F006Fo	I
    //   203: bipush 58
    //   205: putstatic 35	uuuuuu/vlvlll:booo006F006Fo006F006Fo	I
    //   208: ldc 2
    //   210: ldc -74
    //   212: bipush 30
    //   214: iconst_1
    //   215: invokestatic 43	xxxxxx/uxxxxx:bb00620062bb0062b0062b0062	(Ljava/lang/String;CC)Ljava/lang/String;
    //   218: iconst_0
    //   219: anewarray 45	java/lang/Class
    //   222: invokevirtual 49	java/lang/Class:getMethod	(Ljava/lang/String;[Ljava/lang/Class;)Ljava/lang/reflect/Method;
    //   225: astore 32
    //   227: iconst_0
    //   228: anewarray 51	java/lang/Object
    //   231: astore 33
    //   233: aload 32
    //   235: aconst_null
    //   236: aload 33
    //   238: invokevirtual 57	java/lang/reflect/Method:invoke	(Ljava/lang/Object;[Ljava/lang/Object;)Ljava/lang/Object;
    //   241: astore 35
    //   243: iload 26
    //   245: iload 26
    //   247: aload 35
    //   249: checkcast 59	java/lang/Integer
    //   252: invokevirtual 63	java/lang/Integer:intValue	()I
    //   255: iadd
    //   256: imul
    //   257: getstatic 33	uuuuuu/vlvlll:bo006Fo006F006Fo006F006Fo	I
    //   260: irem
    //   261: tableswitch	default:+19->280, 0:+29->290
    //   280: bipush 88
    //   282: putstatic 29	uuuuuu/vlvlll:b006F006F006Fo006Fo006F006Fo	I
    //   285: bipush 30
    //   287: putstatic 35	uuuuuu/vlvlll:booo006F006Fo006F006Fo	I
    //   290: return
    //   291: aload_0
    //   292: aload_1
    //   293: invokevirtual 186	uuuuuu/vlvlll:boo006F006F006F006Fo006F006F006F	(Lcom/db/pwcc/dbmobile/model/error/DbError;)Z
    //   296: ifeq +12 -> 308
    //   299: aload_0
    //   300: aload_1
    //   301: invokevirtual 190	com/db/pwcc/dbmobile/model/error/DbError:getDbCode	()Lcom/db/pwcc/dbmobile/model/error/DbErrorCode;
    //   304: invokevirtual 194	uuuuuu/vlvlll:bo006Fo006F006F006Fo006F006F006F	(Lcom/db/pwcc/dbmobile/model/error/DbErrorCode;)V
    //   307: return
    //   308: aload_0
    //   309: getfield 101	uuuuuu/vlvlll:bnnnnn006E006E006En	Luuuuuu/ttssst$tsssst;
    //   312: checkcast 103	uuuuuu/tntttn$ttnttn
    //   315: astore 10
    //   317: ldc 2
    //   319: ldc -60
    //   321: sipush 239
    //   324: iconst_5
    //   325: invokestatic 43	xxxxxx/uxxxxx:bb00620062bb0062b0062b0062	(Ljava/lang/String;CC)Ljava/lang/String;
    //   328: iconst_0
    //   329: anewarray 45	java/lang/Class
    //   332: invokevirtual 49	java/lang/Class:getMethod	(Ljava/lang/String;[Ljava/lang/Class;)Ljava/lang/reflect/Method;
    //   335: astore 11
    //   337: iconst_0
    //   338: anewarray 51	java/lang/Object
    //   341: astore 12
    //   343: aload 11
    //   345: aconst_null
    //   346: aload 12
    //   348: invokevirtual 57	java/lang/reflect/Method:invoke	(Ljava/lang/Object;[Ljava/lang/Object;)Ljava/lang/Object;
    //   351: astore 14
    //   353: aload 14
    //   355: checkcast 59	java/lang/Integer
    //   358: invokevirtual 63	java/lang/Integer:intValue	()I
    //   361: istore 15
    //   363: ldc 2
    //   365: ldc -58
    //   367: sipush 140
    //   370: iconst_2
    //   371: invokestatic 43	xxxxxx/uxxxxx:bb00620062bb0062b0062b0062	(Ljava/lang/String;CC)Ljava/lang/String;
    //   374: iconst_0
    //   375: anewarray 45	java/lang/Class
    //   378: invokevirtual 49	java/lang/Class:getMethod	(Ljava/lang/String;[Ljava/lang/Class;)Ljava/lang/reflect/Method;
    //   381: astore 16
    //   383: iconst_0
    //   384: anewarray 51	java/lang/Object
    //   387: astore 17
    //   389: aload 16
    //   391: aconst_null
    //   392: aload 17
    //   394: invokevirtual 57	java/lang/reflect/Method:invoke	(Ljava/lang/Object;[Ljava/lang/Object;)Ljava/lang/Object;
    //   397: astore 19
    //   399: iload 15
    //   401: aload 19
    //   403: checkcast 59	java/lang/Integer
    //   406: invokevirtual 63	java/lang/Integer:intValue	()I
    //   409: iadd
    //   410: istore 20
    //   412: ldc 2
    //   414: ldc -56
    //   416: bipush 73
    //   418: iconst_1
    //   419: invokestatic 43	xxxxxx/uxxxxx:bb00620062bb0062b0062b0062	(Ljava/lang/String;CC)Ljava/lang/String;
    //   422: iconst_0
    //   423: anewarray 45	java/lang/Class
    //   426: invokevirtual 49	java/lang/Class:getMethod	(Ljava/lang/String;[Ljava/lang/Class;)Ljava/lang/reflect/Method;
    //   429: astore 21
    //   431: iconst_0
    //   432: anewarray 51	java/lang/Object
    //   435: astore 22
    //   437: aload 21
    //   439: aconst_null
    //   440: aload 22
    //   442: invokevirtual 57	java/lang/reflect/Method:invoke	(Ljava/lang/Object;[Ljava/lang/Object;)Ljava/lang/Object;
    //   445: astore 24
    //   447: iload 20
    //   449: aload 24
    //   451: checkcast 59	java/lang/Integer
    //   454: invokevirtual 63	java/lang/Integer:intValue	()I
    //   457: imul
    //   458: getstatic 33	uuuuuu/vlvlll:bo006Fo006F006Fo006F006Fo	I
    //   461: irem
    //   462: getstatic 35	uuuuuu/vlvlll:booo006F006Fo006F006Fo	I
    //   465: if_icmpeq +61 -> 526
    //   468: bipush 97
    //   470: putstatic 29	uuuuuu/vlvlll:b006F006F006Fo006Fo006F006Fo	I
    //   473: bipush 61
    //   475: putstatic 35	uuuuuu/vlvlll:booo006F006Fo006F006Fo	I
    //   478: getstatic 29	uuuuuu/vlvlll:b006F006F006Fo006Fo006F006Fo	I
    //   481: istore 25
    //   483: iload 25
    //   485: iload 25
    //   487: getstatic 31	uuuuuu/vlvlll:b006Foo006F006Fo006F006Fo	I
    //   490: iadd
    //   491: imul
    //   492: getstatic 33	uuuuuu/vlvlll:bo006Fo006F006Fo006F006Fo	I
    //   495: irem
    //   496: tableswitch	default:+20->516, 0:+30->526
    //   516: bipush 51
    //   518: putstatic 29	uuuuuu/vlvlll:b006F006F006Fo006Fo006F006Fo	I
    //   521: bipush 71
    //   523: putstatic 35	uuuuuu/vlvlll:booo006F006Fo006F006Fo	I
    //   526: aload 10
    //   528: getstatic 205	com/db/pwcc/dbmobile/foundation/R$string:technical_error_retry	I
    //   531: invokeinterface 209 2 0
    //   536: return
    //   537: astore 8
    //   539: aload 8
    //   541: invokevirtual 85	java/lang/reflect/InvocationTargetException:getCause	()Ljava/lang/Throwable;
    //   544: athrow
    //   545: astore 34
    //   547: aload 34
    //   549: invokevirtual 85	java/lang/reflect/InvocationTargetException:getCause	()Ljava/lang/Throwable;
    //   552: athrow
    //   553: astore 13
    //   555: aload 13
    //   557: invokevirtual 85	java/lang/reflect/InvocationTargetException:getCause	()Ljava/lang/Throwable;
    //   560: athrow
    //   561: astore 18
    //   563: aload 18
    //   565: invokevirtual 85	java/lang/reflect/InvocationTargetException:getCause	()Ljava/lang/Throwable;
    //   568: athrow
    //   569: astore 23
    //   571: aload 23
    //   573: invokevirtual 85	java/lang/reflect/InvocationTargetException:getCause	()Ljava/lang/Throwable;
    //   576: athrow
    //   577: astore 30
    //   579: aload 30
    //   581: invokevirtual 85	java/lang/reflect/InvocationTargetException:getCause	()Ljava/lang/Throwable;
    //   584: athrow
    // Local variable table:
    //   start	length	slot	name	signature
    //   0	585	0	this	vlvlll
    //   0	585	1	paramDbError	com.db.pwcc.dbmobile.model.error.DbError
    //   3	96	2	str1	String
    //   11	89	3	localStringBuilder	StringBuilder
    //   20	31	4	str2	String
    //   26	27	5	arrayOfClass	Class[]
    //   57	32	6	localMethod1	java.lang.reflect.Method
    //   63	29	7	arrayOfObject1	Object[]
    //   537	3	8	localInvocationTargetException1	java.lang.reflect.InvocationTargetException
    //   96	5	9	localObject1	Object
    //   315	212	10	localTtnttn	tntttn.ttnttn
    //   335	9	11	localMethod2	java.lang.reflect.Method
    //   341	6	12	arrayOfObject2	Object[]
    //   553	3	13	localInvocationTargetException2	java.lang.reflect.InvocationTargetException
    //   351	3	14	localObject2	Object
    //   361	49	15	i	int
    //   381	9	16	localMethod3	java.lang.reflect.Method
    //   387	6	17	arrayOfObject3	Object[]
    //   561	3	18	localInvocationTargetException3	java.lang.reflect.InvocationTargetException
    //   397	5	19	localObject3	Object
    //   410	48	20	j	int
    //   429	9	21	localMethod4	java.lang.reflect.Method
    //   435	6	22	arrayOfObject4	Object[]
    //   569	3	23	localInvocationTargetException4	java.lang.reflect.InvocationTargetException
    //   445	5	24	localObject4	Object
    //   481	11	25	k	int
    //   131	126	26	m	int
    //   136	48	27	n	int
    //   155	9	28	localMethod5	java.lang.reflect.Method
    //   161	6	29	arrayOfObject5	Object[]
    //   577	3	30	localInvocationTargetException5	java.lang.reflect.InvocationTargetException
    //   171	5	31	localObject5	Object
    //   225	9	32	localMethod6	java.lang.reflect.Method
    //   231	6	33	arrayOfObject6	Object[]
    //   545	3	34	localInvocationTargetException6	java.lang.reflect.InvocationTargetException
    //   241	7	35	localObject6	Object
    // Exception table:
    //   from	to	target	type
    //   88	98	537	java/lang/reflect/InvocationTargetException
    //   233	243	545	java/lang/reflect/InvocationTargetException
    //   343	353	553	java/lang/reflect/InvocationTargetException
    //   389	399	561	java/lang/reflect/InvocationTargetException
    //   437	447	569	java/lang/reflect/InvocationTargetException
    //   163	173	577	java/lang/reflect/InvocationTargetException
  }
  
  /* Error */
  public void bpppppp007000700070p(com.db.pwcc.dbmobile.model.sepa.TransferTemplatesResponse paramTransferTemplatesResponse)
  {
    // Byte code:
    //   0: aload_0
    //   1: invokevirtual 178	uuuuuu/vlvlll:bkk006Bk006Bk006Bk006Bk	()Z
    //   4: ifne +26 -> 30
    //   7: return
    //   8: aload_0
    //   9: getfield 101	uuuuuu/vlvlll:bnnnnn006E006E006En	Luuuuuu/ttssst$tsssst;
    //   12: checkcast 103	uuuuuu/tntttn$ttnttn
    //   15: aload_1
    //   16: invokeinterface 214 2 0
    //   21: iconst_5
    //   22: istore_2
    //   23: iload_2
    //   24: iconst_0
    //   25: idiv
    //   26: istore_2
    //   27: goto -4 -> 23
    //   30: aload_1
    //   31: invokevirtual 219	com/db/pwcc/dbmobile/model/sepa/TransferTemplatesResponse:getTotalNumberOfTemplates	()I
    //   34: ifne -26 -> 8
    //   37: aload_0
    //   38: getfield 101	uuuuuu/vlvlll:bnnnnn006E006E006En	Luuuuuu/ttssst$tsssst;
    //   41: checkcast 103	uuuuuu/tntttn$ttnttn
    //   44: invokeinterface 222 1 0
    //   49: return
    //   50: astore 5
    //   52: bipush 81
    //   54: putstatic 29	uuuuuu/vlvlll:b006F006F006Fo006Fo006F006Fo	I
    //   57: bipush 97
    //   59: putstatic 29	uuuuuu/vlvlll:b006F006F006Fo006Fo006F006Fo	I
    //   62: return
    //   63: astore_3
    //   64: iconst_m1
    //   65: newarray int
    //   67: pop
    //   68: goto -4 -> 64
    // Local variable table:
    //   start	length	slot	name	signature
    //   0	71	0	this	vlvlll
    //   0	71	1	paramTransferTemplatesResponse	com.db.pwcc.dbmobile.model.sepa.TransferTemplatesResponse
    //   22	5	2	i	int
    //   63	1	3	localException1	Exception
    //   50	1	5	localException2	Exception
    // Exception table:
    //   from	to	target	type
    //   64	68	50	java/lang/Exception
    //   23	27	63	java/lang/Exception
  }
}
