package uuuuuu;

import com.db.pwcc.dbmobile.model.banking.FinancialOverviewData;
import com.db.pwcc.dbmobile.model.sepa.StandingOrdersResponse;
import java.lang.reflect.InvocationTargetException;
import java.lang.reflect.Method;
import java.util.Collections;
import java.util.List;
import xxxxxx.uxxxxx;

public class vvllll
  extends ssssst<nnnnnt.nttttn>
  implements nnnnnt.tttttn, vpvpvp.pvvpvp
{
  public static int b006F006F006F006Foo006F006Fo = 2;
  private static final String b006F006F006Fooo006F006Fo;
  public static int b006Fo006F006Foo006F006Fo = 0;
  public static int bo006F006F006Foo006F006Fo = 1;
  public static int boo006F006Foo006F006Fo = 44;
  private int b006F006Fo006Foo006F006Fo = 0;
  public vppppv b006Foo006Foo006F006Fo = new ffmfmf();
  private boolean bo006Fo006Foo006F006Fo;
  public vpvpvp booo006Foo006F006Fo = new fmfmfm();
  
  /* Error */
  static
  {
    // Byte code:
    //   0: getstatic 33	uuuuuu/vvllll:boo006F006Foo006F006Fo	I
    //   3: istore_0
    //   4: iload_0
    //   5: iload_0
    //   6: getstatic 35	uuuuuu/vvllll:bo006F006F006Foo006F006Fo	I
    //   9: iadd
    //   10: imul
    //   11: getstatic 37	uuuuuu/vvllll:b006F006F006F006Foo006F006Fo	I
    //   14: irem
    //   15: tableswitch	default:+17->32, 0:+67->82
    //   32: iconst_0
    //   33: putstatic 33	uuuuuu/vvllll:boo006F006Foo006F006Fo	I
    //   36: ldc 2
    //   38: ldc 39
    //   40: bipush 36
    //   42: iconst_5
    //   43: invokestatic 45	xxxxxx/uxxxxx:bb00620062bb0062b0062b0062	(Ljava/lang/String;CC)Ljava/lang/String;
    //   46: iconst_0
    //   47: anewarray 47	java/lang/Class
    //   50: invokevirtual 51	java/lang/Class:getMethod	(Ljava/lang/String;[Ljava/lang/Class;)Ljava/lang/reflect/Method;
    //   53: astore 28
    //   55: iconst_0
    //   56: anewarray 53	java/lang/Object
    //   59: astore 29
    //   61: aload 28
    //   63: aconst_null
    //   64: aload 29
    //   66: invokevirtual 59	java/lang/reflect/Method:invoke	(Ljava/lang/Object;[Ljava/lang/Object;)Ljava/lang/Object;
    //   69: astore 31
    //   71: aload 31
    //   73: checkcast 61	java/lang/Integer
    //   76: invokevirtual 65	java/lang/Integer:intValue	()I
    //   79: putstatic 67	uuuuuu/vvllll:b006Fo006F006Foo006F006Fo	I
    //   82: getstatic 33	uuuuuu/vvllll:boo006F006Foo006F006Fo	I
    //   85: getstatic 35	uuuuuu/vvllll:bo006F006F006Foo006F006Fo	I
    //   88: iadd
    //   89: getstatic 33	uuuuuu/vvllll:boo006F006Foo006F006Fo	I
    //   92: imul
    //   93: getstatic 37	uuuuuu/vvllll:b006F006F006F006Foo006F006Fo	I
    //   96: irem
    //   97: getstatic 67	uuuuuu/vvllll:b006Fo006F006Foo006F006Fo	I
    //   100: if_icmpeq +95 -> 195
    //   103: ldc 2
    //   105: ldc 69
    //   107: bipush 99
    //   109: iconst_0
    //   110: invokestatic 45	xxxxxx/uxxxxx:bb00620062bb0062b0062b0062	(Ljava/lang/String;CC)Ljava/lang/String;
    //   113: iconst_0
    //   114: anewarray 47	java/lang/Class
    //   117: invokevirtual 51	java/lang/Class:getMethod	(Ljava/lang/String;[Ljava/lang/Class;)Ljava/lang/reflect/Method;
    //   120: astore 20
    //   122: iconst_0
    //   123: anewarray 53	java/lang/Object
    //   126: astore 21
    //   128: aload 20
    //   130: aconst_null
    //   131: aload 21
    //   133: invokevirtual 59	java/lang/reflect/Method:invoke	(Ljava/lang/Object;[Ljava/lang/Object;)Ljava/lang/Object;
    //   136: astore 23
    //   138: aload 23
    //   140: checkcast 61	java/lang/Integer
    //   143: invokevirtual 65	java/lang/Integer:intValue	()I
    //   146: putstatic 33	uuuuuu/vvllll:boo006F006Foo006F006Fo	I
    //   149: ldc 2
    //   151: ldc 71
    //   153: bipush 84
    //   155: iconst_3
    //   156: invokestatic 45	xxxxxx/uxxxxx:bb00620062bb0062b0062b0062	(Ljava/lang/String;CC)Ljava/lang/String;
    //   159: iconst_0
    //   160: anewarray 47	java/lang/Class
    //   163: invokevirtual 51	java/lang/Class:getMethod	(Ljava/lang/String;[Ljava/lang/Class;)Ljava/lang/reflect/Method;
    //   166: astore 24
    //   168: iconst_0
    //   169: anewarray 53	java/lang/Object
    //   172: astore 25
    //   174: aload 24
    //   176: aconst_null
    //   177: aload 25
    //   179: invokevirtual 59	java/lang/reflect/Method:invoke	(Ljava/lang/Object;[Ljava/lang/Object;)Ljava/lang/Object;
    //   182: astore 27
    //   184: aload 27
    //   186: checkcast 61	java/lang/Integer
    //   189: invokevirtual 65	java/lang/Integer:intValue	()I
    //   192: putstatic 67	uuuuuu/vvllll:b006Fo006F006Foo006F006Fo	I
    //   195: ldc 2
    //   197: invokevirtual 75	java/lang/Class:getSimpleName	()Ljava/lang/String;
    //   200: astore_1
    //   201: getstatic 33	uuuuuu/vvllll:boo006F006Foo006F006Fo	I
    //   204: getstatic 35	uuuuuu/vvllll:bo006F006F006Foo006F006Fo	I
    //   207: iadd
    //   208: getstatic 33	uuuuuu/vvllll:boo006F006Foo006F006Fo	I
    //   211: imul
    //   212: istore_2
    //   213: ldc 2
    //   215: ldc 77
    //   217: bipush 103
    //   219: iconst_5
    //   220: invokestatic 45	xxxxxx/uxxxxx:bb00620062bb0062b0062b0062	(Ljava/lang/String;CC)Ljava/lang/String;
    //   223: iconst_0
    //   224: anewarray 47	java/lang/Class
    //   227: invokevirtual 51	java/lang/Class:getMethod	(Ljava/lang/String;[Ljava/lang/Class;)Ljava/lang/reflect/Method;
    //   230: astore_3
    //   231: iconst_0
    //   232: anewarray 53	java/lang/Object
    //   235: astore 4
    //   237: aload_3
    //   238: aconst_null
    //   239: aload 4
    //   241: invokevirtual 59	java/lang/reflect/Method:invoke	(Ljava/lang/Object;[Ljava/lang/Object;)Ljava/lang/Object;
    //   244: astore 6
    //   246: iload_2
    //   247: aload 6
    //   249: checkcast 61	java/lang/Integer
    //   252: invokevirtual 65	java/lang/Integer:intValue	()I
    //   255: irem
    //   256: getstatic 67	uuuuuu/vvllll:b006Fo006F006Foo006F006Fo	I
    //   259: if_icmpeq +187 -> 446
    //   262: getstatic 33	uuuuuu/vvllll:boo006F006Foo006F006Fo	I
    //   265: istore 7
    //   267: ldc 2
    //   269: ldc 79
    //   271: bipush 96
    //   273: iconst_3
    //   274: invokestatic 45	xxxxxx/uxxxxx:bb00620062bb0062b0062b0062	(Ljava/lang/String;CC)Ljava/lang/String;
    //   277: iconst_0
    //   278: anewarray 47	java/lang/Class
    //   281: invokevirtual 51	java/lang/Class:getMethod	(Ljava/lang/String;[Ljava/lang/Class;)Ljava/lang/reflect/Method;
    //   284: astore 8
    //   286: iconst_0
    //   287: anewarray 53	java/lang/Object
    //   290: astore 9
    //   292: aload 8
    //   294: aconst_null
    //   295: aload 9
    //   297: invokevirtual 59	java/lang/reflect/Method:invoke	(Ljava/lang/Object;[Ljava/lang/Object;)Ljava/lang/Object;
    //   300: astore 11
    //   302: iload 7
    //   304: iload 7
    //   306: aload 11
    //   308: checkcast 61	java/lang/Integer
    //   311: invokevirtual 65	java/lang/Integer:intValue	()I
    //   314: iadd
    //   315: imul
    //   316: getstatic 37	uuuuuu/vvllll:b006F006F006F006Foo006F006Fo	I
    //   319: irem
    //   320: tableswitch	default:+20->340, 0:+116->436
    //   340: ldc 2
    //   342: ldc 81
    //   344: sipush 230
    //   347: iconst_4
    //   348: invokestatic 45	xxxxxx/uxxxxx:bb00620062bb0062b0062b0062	(Ljava/lang/String;CC)Ljava/lang/String;
    //   351: iconst_0
    //   352: anewarray 47	java/lang/Class
    //   355: invokevirtual 51	java/lang/Class:getMethod	(Ljava/lang/String;[Ljava/lang/Class;)Ljava/lang/reflect/Method;
    //   358: astore 12
    //   360: iconst_0
    //   361: anewarray 53	java/lang/Object
    //   364: astore 13
    //   366: aload 12
    //   368: aconst_null
    //   369: aload 13
    //   371: invokevirtual 59	java/lang/reflect/Method:invoke	(Ljava/lang/Object;[Ljava/lang/Object;)Ljava/lang/Object;
    //   374: astore 15
    //   376: aload 15
    //   378: checkcast 61	java/lang/Integer
    //   381: invokevirtual 65	java/lang/Integer:intValue	()I
    //   384: putstatic 33	uuuuuu/vvllll:boo006F006Foo006F006Fo	I
    //   387: ldc 2
    //   389: ldc 83
    //   391: sipush 227
    //   394: bipush 7
    //   396: iconst_2
    //   397: invokestatic 87	xxxxxx/uxxxxx:bbbb0062b0062b0062b0062	(Ljava/lang/String;CCC)Ljava/lang/String;
    //   400: iconst_0
    //   401: anewarray 47	java/lang/Class
    //   404: invokevirtual 51	java/lang/Class:getMethod	(Ljava/lang/String;[Ljava/lang/Class;)Ljava/lang/reflect/Method;
    //   407: astore 16
    //   409: iconst_0
    //   410: anewarray 53	java/lang/Object
    //   413: astore 17
    //   415: aload 16
    //   417: aconst_null
    //   418: aload 17
    //   420: invokevirtual 59	java/lang/reflect/Method:invoke	(Ljava/lang/Object;[Ljava/lang/Object;)Ljava/lang/Object;
    //   423: astore 19
    //   425: aload 19
    //   427: checkcast 61	java/lang/Integer
    //   430: invokevirtual 65	java/lang/Integer:intValue	()I
    //   433: putstatic 67	uuuuuu/vvllll:b006Fo006F006Foo006F006Fo	I
    //   436: bipush 47
    //   438: putstatic 33	uuuuuu/vvllll:boo006F006Foo006F006Fo	I
    //   441: bipush 93
    //   443: putstatic 67	uuuuuu/vvllll:b006Fo006F006Foo006F006Fo	I
    //   446: aload_1
    //   447: putstatic 89	uuuuuu/vvllll:b006F006F006Fooo006F006Fo	Ljava/lang/String;
    //   450: return
    //   451: astore 5
    //   453: aload 5
    //   455: invokevirtual 93	java/lang/reflect/InvocationTargetException:getCause	()Ljava/lang/Throwable;
    //   458: athrow
    //   459: astore 22
    //   461: aload 22
    //   463: invokevirtual 93	java/lang/reflect/InvocationTargetException:getCause	()Ljava/lang/Throwable;
    //   466: athrow
    //   467: astore 10
    //   469: aload 10
    //   471: invokevirtual 93	java/lang/reflect/InvocationTargetException:getCause	()Ljava/lang/Throwable;
    //   474: athrow
    //   475: astore 26
    //   477: aload 26
    //   479: invokevirtual 93	java/lang/reflect/InvocationTargetException:getCause	()Ljava/lang/Throwable;
    //   482: athrow
    //   483: astore 14
    //   485: aload 14
    //   487: invokevirtual 93	java/lang/reflect/InvocationTargetException:getCause	()Ljava/lang/Throwable;
    //   490: athrow
    //   491: astore 18
    //   493: aload 18
    //   495: invokevirtual 93	java/lang/reflect/InvocationTargetException:getCause	()Ljava/lang/Throwable;
    //   498: athrow
    //   499: astore 30
    //   501: aload 30
    //   503: invokevirtual 93	java/lang/reflect/InvocationTargetException:getCause	()Ljava/lang/Throwable;
    //   506: athrow
    // Local variable table:
    //   start	length	slot	name	signature
    //   3	8	0	i	int
    //   200	247	1	str	String
    //   212	44	2	j	int
    //   230	8	3	localMethod1	Method
    //   235	5	4	arrayOfObject1	Object[]
    //   451	3	5	localInvocationTargetException1	InvocationTargetException
    //   244	4	6	localObject1	Object
    //   265	51	7	k	int
    //   284	9	8	localMethod2	Method
    //   290	6	9	arrayOfObject2	Object[]
    //   467	3	10	localInvocationTargetException2	InvocationTargetException
    //   300	7	11	localObject2	Object
    //   358	9	12	localMethod3	Method
    //   364	6	13	arrayOfObject3	Object[]
    //   483	3	14	localInvocationTargetException3	InvocationTargetException
    //   374	3	15	localObject3	Object
    //   407	9	16	localMethod4	Method
    //   413	6	17	arrayOfObject4	Object[]
    //   491	3	18	localInvocationTargetException4	InvocationTargetException
    //   423	3	19	localObject4	Object
    //   120	9	20	localMethod5	Method
    //   126	6	21	arrayOfObject5	Object[]
    //   459	3	22	localInvocationTargetException5	InvocationTargetException
    //   136	3	23	localObject5	Object
    //   166	9	24	localMethod6	Method
    //   172	6	25	arrayOfObject6	Object[]
    //   475	3	26	localInvocationTargetException6	InvocationTargetException
    //   182	3	27	localObject6	Object
    //   53	9	28	localMethod7	Method
    //   59	6	29	arrayOfObject7	Object[]
    //   499	3	30	localInvocationTargetException7	InvocationTargetException
    //   69	3	31	localObject7	Object
    // Exception table:
    //   from	to	target	type
    //   237	246	451	java/lang/reflect/InvocationTargetException
    //   128	138	459	java/lang/reflect/InvocationTargetException
    //   292	302	467	java/lang/reflect/InvocationTargetException
    //   174	184	475	java/lang/reflect/InvocationTargetException
    //   366	376	483	java/lang/reflect/InvocationTargetException
    //   415	425	491	java/lang/reflect/InvocationTargetException
    //   61	71	499	java/lang/reflect/InvocationTargetException
  }
  
  public vvllll() {}
  
  public static int b00690069iiiiii00690069()
  {
    return 18;
  }
  
  public static int b0069iiiiiii00690069()
  {
    return 0;
  }
  
  public static int bi0069iiiiii00690069()
  {
    return 2;
  }
  
  public static int biiiiiiii00690069()
  {
    return 1;
  }
  
  /* Error */
  public void b00690069i00690069i0069ii0069(boolean paramBoolean)
  {
    // Byte code:
    //   0: aload_0
    //   1: iload_1
    //   2: putfield 187	uuuuuu/vvllll:bo006Fo006Foo006F006Fo	Z
    //   5: getstatic 33	uuuuuu/vvllll:boo006F006Foo006F006Fo	I
    //   8: getstatic 35	uuuuuu/vvllll:bo006F006F006Foo006F006Fo	I
    //   11: iadd
    //   12: getstatic 33	uuuuuu/vvllll:boo006F006Foo006F006Fo	I
    //   15: imul
    //   16: getstatic 37	uuuuuu/vvllll:b006F006F006F006Foo006F006Fo	I
    //   19: irem
    //   20: istore_2
    //   21: ldc 2
    //   23: ldc -67
    //   25: bipush 36
    //   27: iconst_2
    //   28: invokestatic 45	xxxxxx/uxxxxx:bb00620062bb0062b0062b0062	(Ljava/lang/String;CC)Ljava/lang/String;
    //   31: iconst_0
    //   32: anewarray 47	java/lang/Class
    //   35: invokevirtual 51	java/lang/Class:getMethod	(Ljava/lang/String;[Ljava/lang/Class;)Ljava/lang/reflect/Method;
    //   38: astore_3
    //   39: iconst_0
    //   40: anewarray 53	java/lang/Object
    //   43: astore 4
    //   45: aload_3
    //   46: aconst_null
    //   47: aload 4
    //   49: invokevirtual 59	java/lang/reflect/Method:invoke	(Ljava/lang/Object;[Ljava/lang/Object;)Ljava/lang/Object;
    //   52: astore 6
    //   54: iload_2
    //   55: aload 6
    //   57: checkcast 61	java/lang/Integer
    //   60: invokevirtual 65	java/lang/Integer:intValue	()I
    //   63: if_icmpeq +310 -> 373
    //   66: getstatic 33	uuuuuu/vvllll:boo006F006Foo006F006Fo	I
    //   69: istore 7
    //   71: iload 7
    //   73: iload 7
    //   75: getstatic 35	uuuuuu/vvllll:bo006F006F006Foo006F006Fo	I
    //   78: iadd
    //   79: imul
    //   80: getstatic 37	uuuuuu/vvllll:b006F006F006F006Foo006F006Fo	I
    //   83: irem
    //   84: tableswitch	default:+20->104, 0:+145->229
    //   104: bipush 83
    //   106: putstatic 33	uuuuuu/vvllll:boo006F006Foo006F006Fo	I
    //   109: ldc 2
    //   111: ldc -65
    //   113: bipush 73
    //   115: iconst_1
    //   116: invokestatic 45	xxxxxx/uxxxxx:bb00620062bb0062b0062b0062	(Ljava/lang/String;CC)Ljava/lang/String;
    //   119: iconst_0
    //   120: anewarray 47	java/lang/Class
    //   123: invokevirtual 51	java/lang/Class:getMethod	(Ljava/lang/String;[Ljava/lang/Class;)Ljava/lang/reflect/Method;
    //   126: astore 18
    //   128: iconst_0
    //   129: anewarray 53	java/lang/Object
    //   132: astore 19
    //   134: aload 18
    //   136: aconst_null
    //   137: aload 19
    //   139: invokevirtual 59	java/lang/reflect/Method:invoke	(Ljava/lang/Object;[Ljava/lang/Object;)Ljava/lang/Object;
    //   142: astore 21
    //   144: aload 21
    //   146: checkcast 61	java/lang/Integer
    //   149: invokevirtual 65	java/lang/Integer:intValue	()I
    //   152: putstatic 67	uuuuuu/vvllll:b006Fo006F006Foo006F006Fo	I
    //   155: getstatic 33	uuuuuu/vvllll:boo006F006Foo006F006Fo	I
    //   158: getstatic 35	uuuuuu/vvllll:bo006F006F006Foo006F006Fo	I
    //   161: iadd
    //   162: getstatic 33	uuuuuu/vvllll:boo006F006Foo006F006Fo	I
    //   165: imul
    //   166: getstatic 37	uuuuuu/vvllll:b006F006F006F006Foo006F006Fo	I
    //   169: irem
    //   170: getstatic 67	uuuuuu/vvllll:b006Fo006F006Foo006F006Fo	I
    //   173: if_icmpeq +56 -> 229
    //   176: ldc 2
    //   178: ldc -63
    //   180: bipush 64
    //   182: bipush 18
    //   184: iconst_3
    //   185: invokestatic 87	xxxxxx/uxxxxx:bbbb0062b0062b0062b0062	(Ljava/lang/String;CCC)Ljava/lang/String;
    //   188: iconst_0
    //   189: anewarray 47	java/lang/Class
    //   192: invokevirtual 51	java/lang/Class:getMethod	(Ljava/lang/String;[Ljava/lang/Class;)Ljava/lang/reflect/Method;
    //   195: astore 22
    //   197: iconst_0
    //   198: anewarray 53	java/lang/Object
    //   201: astore 23
    //   203: aload 22
    //   205: aconst_null
    //   206: aload 23
    //   208: invokevirtual 59	java/lang/reflect/Method:invoke	(Ljava/lang/Object;[Ljava/lang/Object;)Ljava/lang/Object;
    //   211: astore 25
    //   213: aload 25
    //   215: checkcast 61	java/lang/Integer
    //   218: invokevirtual 65	java/lang/Integer:intValue	()I
    //   221: putstatic 33	uuuuuu/vvllll:boo006F006Foo006F006Fo	I
    //   224: bipush 73
    //   226: putstatic 67	uuuuuu/vvllll:b006Fo006F006Foo006F006Fo	I
    //   229: ldc 2
    //   231: ldc -61
    //   233: sipush 236
    //   236: bipush 18
    //   238: iconst_2
    //   239: invokestatic 87	xxxxxx/uxxxxx:bbbb0062b0062b0062b0062	(Ljava/lang/String;CCC)Ljava/lang/String;
    //   242: iconst_0
    //   243: anewarray 47	java/lang/Class
    //   246: invokevirtual 51	java/lang/Class:getMethod	(Ljava/lang/String;[Ljava/lang/Class;)Ljava/lang/reflect/Method;
    //   249: astore 8
    //   251: iconst_0
    //   252: anewarray 53	java/lang/Object
    //   255: astore 9
    //   257: aload 8
    //   259: aconst_null
    //   260: aload 9
    //   262: invokevirtual 59	java/lang/reflect/Method:invoke	(Ljava/lang/Object;[Ljava/lang/Object;)Ljava/lang/Object;
    //   265: astore 11
    //   267: aload 11
    //   269: checkcast 61	java/lang/Integer
    //   272: invokevirtual 65	java/lang/Integer:intValue	()I
    //   275: istore 12
    //   277: getstatic 33	uuuuuu/vvllll:boo006F006Foo006F006Fo	I
    //   280: istore 13
    //   282: iload 13
    //   284: iload 13
    //   286: getstatic 35	uuuuuu/vvllll:bo006F006F006Foo006F006Fo	I
    //   289: iadd
    //   290: imul
    //   291: getstatic 37	uuuuuu/vvllll:b006F006F006F006Foo006F006Fo	I
    //   294: irem
    //   295: tableswitch	default:+17->312, 0:+68->363
    //   312: bipush 96
    //   314: putstatic 33	uuuuuu/vvllll:boo006F006Foo006F006Fo	I
    //   317: ldc 2
    //   319: ldc -59
    //   321: bipush 23
    //   323: iconst_1
    //   324: invokestatic 45	xxxxxx/uxxxxx:bb00620062bb0062b0062b0062	(Ljava/lang/String;CC)Ljava/lang/String;
    //   327: iconst_0
    //   328: anewarray 47	java/lang/Class
    //   331: invokevirtual 51	java/lang/Class:getMethod	(Ljava/lang/String;[Ljava/lang/Class;)Ljava/lang/reflect/Method;
    //   334: astore 14
    //   336: iconst_0
    //   337: anewarray 53	java/lang/Object
    //   340: astore 15
    //   342: aload 14
    //   344: aconst_null
    //   345: aload 15
    //   347: invokevirtual 59	java/lang/reflect/Method:invoke	(Ljava/lang/Object;[Ljava/lang/Object;)Ljava/lang/Object;
    //   350: astore 17
    //   352: aload 17
    //   354: checkcast 61	java/lang/Integer
    //   357: invokevirtual 65	java/lang/Integer:intValue	()I
    //   360: putstatic 67	uuuuuu/vvllll:b006Fo006F006Foo006F006Fo	I
    //   363: iload 12
    //   365: putstatic 33	uuuuuu/vvllll:boo006F006Foo006F006Fo	I
    //   368: bipush 6
    //   370: putstatic 67	uuuuuu/vvllll:b006Fo006F006Foo006F006Fo	I
    //   373: return
    //   374: astore 10
    //   376: aload 10
    //   378: invokevirtual 93	java/lang/reflect/InvocationTargetException:getCause	()Ljava/lang/Throwable;
    //   381: athrow
    //   382: astore 16
    //   384: aload 16
    //   386: invokevirtual 93	java/lang/reflect/InvocationTargetException:getCause	()Ljava/lang/Throwable;
    //   389: athrow
    //   390: astore 20
    //   392: aload 20
    //   394: invokevirtual 93	java/lang/reflect/InvocationTargetException:getCause	()Ljava/lang/Throwable;
    //   397: athrow
    //   398: astore 5
    //   400: aload 5
    //   402: invokevirtual 93	java/lang/reflect/InvocationTargetException:getCause	()Ljava/lang/Throwable;
    //   405: athrow
    //   406: astore 24
    //   408: aload 24
    //   410: invokevirtual 93	java/lang/reflect/InvocationTargetException:getCause	()Ljava/lang/Throwable;
    //   413: athrow
    // Local variable table:
    //   start	length	slot	name	signature
    //   0	414	0	this	vvllll
    //   0	414	1	paramBoolean	boolean
    //   20	44	2	i	int
    //   38	8	3	localMethod1	Method
    //   43	5	4	arrayOfObject1	Object[]
    //   398	3	5	localInvocationTargetException1	InvocationTargetException
    //   52	4	6	localObject1	Object
    //   69	11	7	j	int
    //   249	9	8	localMethod2	Method
    //   255	6	9	arrayOfObject2	Object[]
    //   374	3	10	localInvocationTargetException2	InvocationTargetException
    //   265	3	11	localObject2	Object
    //   275	89	12	k	int
    //   280	11	13	m	int
    //   334	9	14	localMethod3	Method
    //   340	6	15	arrayOfObject3	Object[]
    //   382	3	16	localInvocationTargetException3	InvocationTargetException
    //   350	3	17	localObject3	Object
    //   126	9	18	localMethod4	Method
    //   132	6	19	arrayOfObject4	Object[]
    //   390	3	20	localInvocationTargetException4	InvocationTargetException
    //   142	3	21	localObject4	Object
    //   195	9	22	localMethod5	Method
    //   201	6	23	arrayOfObject5	Object[]
    //   406	3	24	localInvocationTargetException5	InvocationTargetException
    //   211	3	25	localObject5	Object
    // Exception table:
    //   from	to	target	type
    //   257	267	374	java/lang/reflect/InvocationTargetException
    //   342	352	382	java/lang/reflect/InvocationTargetException
    //   134	144	390	java/lang/reflect/InvocationTargetException
    //   45	54	398	java/lang/reflect/InvocationTargetException
    //   203	213	406	java/lang/reflect/InvocationTargetException
  }
  
  /* Error */
  public void b0069i006900690069i0069ii0069()
  {
    // Byte code:
    //   0: getstatic 204	uuuuuu/vvrvrv:bx0078x0078xxxxx	Luuuuuu/vvrvrv;
    //   3: astore_1
    //   4: getstatic 33	uuuuuu/vvllll:boo006F006Foo006F006Fo	I
    //   7: istore_2
    //   8: iload_2
    //   9: iload_2
    //   10: getstatic 35	uuuuuu/vvllll:bo006F006F006Foo006F006Fo	I
    //   13: iadd
    //   14: imul
    //   15: getstatic 37	uuuuuu/vvllll:b006F006F006F006Foo006F006Fo	I
    //   18: irem
    //   19: tableswitch	default:+17->36, 0:+68->87
    //   36: bipush 24
    //   38: putstatic 33	uuuuuu/vvllll:boo006F006Foo006F006Fo	I
    //   41: ldc 2
    //   43: ldc -50
    //   45: bipush 56
    //   47: iconst_3
    //   48: invokestatic 45	xxxxxx/uxxxxx:bb00620062bb0062b0062b0062	(Ljava/lang/String;CC)Ljava/lang/String;
    //   51: iconst_0
    //   52: anewarray 47	java/lang/Class
    //   55: invokevirtual 51	java/lang/Class:getMethod	(Ljava/lang/String;[Ljava/lang/Class;)Ljava/lang/reflect/Method;
    //   58: astore 33
    //   60: iconst_0
    //   61: anewarray 53	java/lang/Object
    //   64: astore 34
    //   66: aload 33
    //   68: aconst_null
    //   69: aload 34
    //   71: invokevirtual 59	java/lang/reflect/Method:invoke	(Ljava/lang/Object;[Ljava/lang/Object;)Ljava/lang/Object;
    //   74: astore 36
    //   76: aload 36
    //   78: checkcast 61	java/lang/Integer
    //   81: invokevirtual 65	java/lang/Integer:intValue	()I
    //   84: putstatic 67	uuuuuu/vvllll:b006Fo006F006Foo006F006Fo	I
    //   87: aload_1
    //   88: invokestatic 212	uuuuuu/rrvvrv:b0071q0071qq0071q0071q0071	(Luuuuuu/vvrvrv;)V
    //   91: getstatic 33	uuuuuu/vvllll:boo006F006Foo006F006Fo	I
    //   94: getstatic 35	uuuuuu/vvllll:bo006F006F006Foo006F006Fo	I
    //   97: iadd
    //   98: getstatic 33	uuuuuu/vvllll:boo006F006Foo006F006Fo	I
    //   101: imul
    //   102: getstatic 37	uuuuuu/vvllll:b006F006F006F006Foo006F006Fo	I
    //   105: irem
    //   106: getstatic 67	uuuuuu/vvllll:b006Fo006F006Foo006F006Fo	I
    //   109: if_icmpeq +370 -> 479
    //   112: ldc 2
    //   114: ldc -42
    //   116: bipush 57
    //   118: iconst_3
    //   119: invokestatic 45	xxxxxx/uxxxxx:bb00620062bb0062b0062b0062	(Ljava/lang/String;CC)Ljava/lang/String;
    //   122: iconst_0
    //   123: anewarray 47	java/lang/Class
    //   126: invokevirtual 51	java/lang/Class:getMethod	(Ljava/lang/String;[Ljava/lang/Class;)Ljava/lang/reflect/Method;
    //   129: astore_3
    //   130: iconst_0
    //   131: anewarray 53	java/lang/Object
    //   134: astore 4
    //   136: aload_3
    //   137: aconst_null
    //   138: aload 4
    //   140: invokevirtual 59	java/lang/reflect/Method:invoke	(Ljava/lang/Object;[Ljava/lang/Object;)Ljava/lang/Object;
    //   143: astore 6
    //   145: aload 6
    //   147: checkcast 61	java/lang/Integer
    //   150: invokevirtual 65	java/lang/Integer:intValue	()I
    //   153: getstatic 35	uuuuuu/vvllll:bo006F006F006Foo006F006Fo	I
    //   156: iadd
    //   157: istore 7
    //   159: ldc 2
    //   161: ldc -40
    //   163: sipush 243
    //   166: iconst_5
    //   167: invokestatic 45	xxxxxx/uxxxxx:bb00620062bb0062b0062b0062	(Ljava/lang/String;CC)Ljava/lang/String;
    //   170: iconst_0
    //   171: anewarray 47	java/lang/Class
    //   174: invokevirtual 51	java/lang/Class:getMethod	(Ljava/lang/String;[Ljava/lang/Class;)Ljava/lang/reflect/Method;
    //   177: astore 8
    //   179: iconst_0
    //   180: anewarray 53	java/lang/Object
    //   183: astore 9
    //   185: aload 8
    //   187: aconst_null
    //   188: aload 9
    //   190: invokevirtual 59	java/lang/reflect/Method:invoke	(Ljava/lang/Object;[Ljava/lang/Object;)Ljava/lang/Object;
    //   193: astore 11
    //   195: iload 7
    //   197: aload 11
    //   199: checkcast 61	java/lang/Integer
    //   202: invokevirtual 65	java/lang/Integer:intValue	()I
    //   205: imul
    //   206: getstatic 37	uuuuuu/vvllll:b006F006F006F006Foo006F006Fo	I
    //   209: irem
    //   210: getstatic 67	uuuuuu/vvllll:b006Fo006F006Foo006F006Fo	I
    //   213: if_icmpeq +97 -> 310
    //   216: ldc 2
    //   218: ldc -38
    //   220: sipush 201
    //   223: iconst_0
    //   224: invokestatic 45	xxxxxx/uxxxxx:bb00620062bb0062b0062b0062	(Ljava/lang/String;CC)Ljava/lang/String;
    //   227: iconst_0
    //   228: anewarray 47	java/lang/Class
    //   231: invokevirtual 51	java/lang/Class:getMethod	(Ljava/lang/String;[Ljava/lang/Class;)Ljava/lang/reflect/Method;
    //   234: astore 25
    //   236: iconst_0
    //   237: anewarray 53	java/lang/Object
    //   240: astore 26
    //   242: aload 25
    //   244: aconst_null
    //   245: aload 26
    //   247: invokevirtual 59	java/lang/reflect/Method:invoke	(Ljava/lang/Object;[Ljava/lang/Object;)Ljava/lang/Object;
    //   250: astore 28
    //   252: aload 28
    //   254: checkcast 61	java/lang/Integer
    //   257: invokevirtual 65	java/lang/Integer:intValue	()I
    //   260: putstatic 33	uuuuuu/vvllll:boo006F006Foo006F006Fo	I
    //   263: ldc 2
    //   265: ldc -36
    //   267: sipush 154
    //   270: iconst_2
    //   271: invokestatic 45	xxxxxx/uxxxxx:bb00620062bb0062b0062b0062	(Ljava/lang/String;CC)Ljava/lang/String;
    //   274: iconst_0
    //   275: anewarray 47	java/lang/Class
    //   278: invokevirtual 51	java/lang/Class:getMethod	(Ljava/lang/String;[Ljava/lang/Class;)Ljava/lang/reflect/Method;
    //   281: astore 29
    //   283: iconst_0
    //   284: anewarray 53	java/lang/Object
    //   287: astore 30
    //   289: aload 29
    //   291: aconst_null
    //   292: aload 30
    //   294: invokevirtual 59	java/lang/reflect/Method:invoke	(Ljava/lang/Object;[Ljava/lang/Object;)Ljava/lang/Object;
    //   297: astore 32
    //   299: aload 32
    //   301: checkcast 61	java/lang/Integer
    //   304: invokevirtual 65	java/lang/Integer:intValue	()I
    //   307: putstatic 67	uuuuuu/vvllll:b006Fo006F006Foo006F006Fo	I
    //   310: ldc 2
    //   312: ldc -34
    //   314: sipush 197
    //   317: iconst_4
    //   318: invokestatic 45	xxxxxx/uxxxxx:bb00620062bb0062b0062b0062	(Ljava/lang/String;CC)Ljava/lang/String;
    //   321: iconst_0
    //   322: anewarray 47	java/lang/Class
    //   325: invokevirtual 51	java/lang/Class:getMethod	(Ljava/lang/String;[Ljava/lang/Class;)Ljava/lang/reflect/Method;
    //   328: astore 12
    //   330: iconst_0
    //   331: anewarray 53	java/lang/Object
    //   334: astore 13
    //   336: aload 12
    //   338: aconst_null
    //   339: aload 13
    //   341: invokevirtual 59	java/lang/reflect/Method:invoke	(Ljava/lang/Object;[Ljava/lang/Object;)Ljava/lang/Object;
    //   344: astore 15
    //   346: aload 15
    //   348: checkcast 61	java/lang/Integer
    //   351: invokevirtual 65	java/lang/Integer:intValue	()I
    //   354: putstatic 33	uuuuuu/vvllll:boo006F006Foo006F006Fo	I
    //   357: bipush 80
    //   359: putstatic 67	uuuuuu/vvllll:b006Fo006F006Foo006F006Fo	I
    //   362: getstatic 33	uuuuuu/vvllll:boo006F006Foo006F006Fo	I
    //   365: getstatic 35	uuuuuu/vvllll:bo006F006F006Foo006F006Fo	I
    //   368: iadd
    //   369: getstatic 33	uuuuuu/vvllll:boo006F006Foo006F006Fo	I
    //   372: imul
    //   373: istore 16
    //   375: ldc 2
    //   377: ldc -32
    //   379: bipush 72
    //   381: iconst_5
    //   382: invokestatic 45	xxxxxx/uxxxxx:bb00620062bb0062b0062b0062	(Ljava/lang/String;CC)Ljava/lang/String;
    //   385: iconst_0
    //   386: anewarray 47	java/lang/Class
    //   389: invokevirtual 51	java/lang/Class:getMethod	(Ljava/lang/String;[Ljava/lang/Class;)Ljava/lang/reflect/Method;
    //   392: astore 17
    //   394: iconst_0
    //   395: anewarray 53	java/lang/Object
    //   398: astore 18
    //   400: aload 17
    //   402: aconst_null
    //   403: aload 18
    //   405: invokevirtual 59	java/lang/reflect/Method:invoke	(Ljava/lang/Object;[Ljava/lang/Object;)Ljava/lang/Object;
    //   408: astore 20
    //   410: iload 16
    //   412: aload 20
    //   414: checkcast 61	java/lang/Integer
    //   417: invokevirtual 65	java/lang/Integer:intValue	()I
    //   420: irem
    //   421: getstatic 67	uuuuuu/vvllll:b006Fo006F006Foo006F006Fo	I
    //   424: if_icmpeq +55 -> 479
    //   427: ldc 2
    //   429: ldc -78
    //   431: sipush 128
    //   434: iconst_5
    //   435: invokestatic 45	xxxxxx/uxxxxx:bb00620062bb0062b0062b0062	(Ljava/lang/String;CC)Ljava/lang/String;
    //   438: iconst_0
    //   439: anewarray 47	java/lang/Class
    //   442: invokevirtual 51	java/lang/Class:getMethod	(Ljava/lang/String;[Ljava/lang/Class;)Ljava/lang/reflect/Method;
    //   445: astore 21
    //   447: iconst_0
    //   448: anewarray 53	java/lang/Object
    //   451: astore 22
    //   453: aload 21
    //   455: aconst_null
    //   456: aload 22
    //   458: invokevirtual 59	java/lang/reflect/Method:invoke	(Ljava/lang/Object;[Ljava/lang/Object;)Ljava/lang/Object;
    //   461: astore 24
    //   463: aload 24
    //   465: checkcast 61	java/lang/Integer
    //   468: invokevirtual 65	java/lang/Integer:intValue	()I
    //   471: putstatic 33	uuuuuu/vvllll:boo006F006Foo006F006Fo	I
    //   474: bipush 98
    //   476: putstatic 67	uuuuuu/vvllll:b006Fo006F006Foo006F006Fo	I
    //   479: return
    //   480: astore 14
    //   482: aload 14
    //   484: invokevirtual 93	java/lang/reflect/InvocationTargetException:getCause	()Ljava/lang/Throwable;
    //   487: athrow
    //   488: astore 19
    //   490: aload 19
    //   492: invokevirtual 93	java/lang/reflect/InvocationTargetException:getCause	()Ljava/lang/Throwable;
    //   495: athrow
    //   496: astore 23
    //   498: aload 23
    //   500: invokevirtual 93	java/lang/reflect/InvocationTargetException:getCause	()Ljava/lang/Throwable;
    //   503: athrow
    //   504: astore 5
    //   506: aload 5
    //   508: invokevirtual 93	java/lang/reflect/InvocationTargetException:getCause	()Ljava/lang/Throwable;
    //   511: athrow
    //   512: astore 10
    //   514: aload 10
    //   516: invokevirtual 93	java/lang/reflect/InvocationTargetException:getCause	()Ljava/lang/Throwable;
    //   519: athrow
    //   520: astore 35
    //   522: aload 35
    //   524: invokevirtual 93	java/lang/reflect/InvocationTargetException:getCause	()Ljava/lang/Throwable;
    //   527: athrow
    //   528: astore 27
    //   530: aload 27
    //   532: invokevirtual 93	java/lang/reflect/InvocationTargetException:getCause	()Ljava/lang/Throwable;
    //   535: athrow
    //   536: astore 31
    //   538: aload 31
    //   540: invokevirtual 93	java/lang/reflect/InvocationTargetException:getCause	()Ljava/lang/Throwable;
    //   543: athrow
    // Local variable table:
    //   start	length	slot	name	signature
    //   0	544	0	this	vvllll
    //   3	85	1	localVvrvrv	vvrvrv
    //   7	8	2	i	int
    //   129	8	3	localMethod1	Method
    //   134	5	4	arrayOfObject1	Object[]
    //   504	3	5	localInvocationTargetException1	InvocationTargetException
    //   143	3	6	localObject1	Object
    //   157	49	7	j	int
    //   177	9	8	localMethod2	Method
    //   183	6	9	arrayOfObject2	Object[]
    //   512	3	10	localInvocationTargetException2	InvocationTargetException
    //   193	5	11	localObject2	Object
    //   328	9	12	localMethod3	Method
    //   334	6	13	arrayOfObject3	Object[]
    //   480	3	14	localInvocationTargetException3	InvocationTargetException
    //   344	3	15	localObject3	Object
    //   373	48	16	k	int
    //   392	9	17	localMethod4	Method
    //   398	6	18	arrayOfObject4	Object[]
    //   488	3	19	localInvocationTargetException4	InvocationTargetException
    //   408	5	20	localObject4	Object
    //   445	9	21	localMethod5	Method
    //   451	6	22	arrayOfObject5	Object[]
    //   496	3	23	localInvocationTargetException5	InvocationTargetException
    //   461	3	24	localObject5	Object
    //   234	9	25	localMethod6	Method
    //   240	6	26	arrayOfObject6	Object[]
    //   528	3	27	localInvocationTargetException6	InvocationTargetException
    //   250	3	28	localObject6	Object
    //   281	9	29	localMethod7	Method
    //   287	6	30	arrayOfObject7	Object[]
    //   536	3	31	localInvocationTargetException7	InvocationTargetException
    //   297	3	32	localObject7	Object
    //   58	9	33	localMethod8	Method
    //   64	6	34	arrayOfObject8	Object[]
    //   520	3	35	localInvocationTargetException8	InvocationTargetException
    //   74	3	36	localObject8	Object
    // Exception table:
    //   from	to	target	type
    //   336	346	480	java/lang/reflect/InvocationTargetException
    //   400	410	488	java/lang/reflect/InvocationTargetException
    //   453	463	496	java/lang/reflect/InvocationTargetException
    //   136	145	504	java/lang/reflect/InvocationTargetException
    //   185	195	512	java/lang/reflect/InvocationTargetException
    //   66	76	520	java/lang/reflect/InvocationTargetException
    //   242	252	528	java/lang/reflect/InvocationTargetException
    //   289	299	536	java/lang/reflect/InvocationTargetException
  }
  
  public void b0069i0069iiiii00690069(FinancialOverviewData paramFinancialOverviewData) {}
  
  /* Error */
  public void b0069ii00690069i0069ii0069()
  {
    // Byte code:
    //   0: aload_0
    //   1: invokevirtual 231	uuuuuu/vvllll:bkk006Bk006Bk006Bk006Bk	()Z
    //   4: ifne +4 -> 8
    //   7: return
    //   8: getstatic 33	uuuuuu/vvllll:boo006F006Foo006F006Fo	I
    //   11: istore_1
    //   12: ldc 2
    //   14: ldc -23
    //   16: bipush 17
    //   18: iconst_2
    //   19: invokestatic 45	xxxxxx/uxxxxx:bb00620062bb0062b0062b0062	(Ljava/lang/String;CC)Ljava/lang/String;
    //   22: iconst_0
    //   23: anewarray 47	java/lang/Class
    //   26: invokevirtual 51	java/lang/Class:getMethod	(Ljava/lang/String;[Ljava/lang/Class;)Ljava/lang/reflect/Method;
    //   29: astore_2
    //   30: iconst_0
    //   31: anewarray 53	java/lang/Object
    //   34: astore_3
    //   35: aload_2
    //   36: aconst_null
    //   37: aload_3
    //   38: invokevirtual 59	java/lang/reflect/Method:invoke	(Ljava/lang/Object;[Ljava/lang/Object;)Ljava/lang/Object;
    //   41: astore 5
    //   43: iload_1
    //   44: iload_1
    //   45: aload 5
    //   47: checkcast 61	java/lang/Integer
    //   50: invokevirtual 65	java/lang/Integer:intValue	()I
    //   53: iadd
    //   54: imul
    //   55: getstatic 37	uuuuuu/vvllll:b006F006F006F006Foo006F006Fo	I
    //   58: irem
    //   59: tableswitch	default:+17->76, 0:+203->262
    //   76: ldc 2
    //   78: ldc -21
    //   80: sipush 137
    //   83: iconst_4
    //   84: invokestatic 45	xxxxxx/uxxxxx:bb00620062bb0062b0062b0062	(Ljava/lang/String;CC)Ljava/lang/String;
    //   87: iconst_0
    //   88: anewarray 47	java/lang/Class
    //   91: invokevirtual 51	java/lang/Class:getMethod	(Ljava/lang/String;[Ljava/lang/Class;)Ljava/lang/reflect/Method;
    //   94: astore 14
    //   96: iconst_0
    //   97: anewarray 53	java/lang/Object
    //   100: astore 15
    //   102: aload 14
    //   104: aconst_null
    //   105: aload 15
    //   107: invokevirtual 59	java/lang/reflect/Method:invoke	(Ljava/lang/Object;[Ljava/lang/Object;)Ljava/lang/Object;
    //   110: astore 17
    //   112: aload 17
    //   114: checkcast 61	java/lang/Integer
    //   117: invokevirtual 65	java/lang/Integer:intValue	()I
    //   120: putstatic 33	uuuuuu/vvllll:boo006F006Foo006F006Fo	I
    //   123: getstatic 33	uuuuuu/vvllll:boo006F006Foo006F006Fo	I
    //   126: istore 18
    //   128: iload 18
    //   130: iload 18
    //   132: getstatic 35	uuuuuu/vvllll:bo006F006F006Foo006F006Fo	I
    //   135: iadd
    //   136: imul
    //   137: getstatic 37	uuuuuu/vvllll:b006F006F006F006Foo006F006Fo	I
    //   140: irem
    //   141: tableswitch	default:+19->160, 0:+116->257
    //   160: ldc 2
    //   162: ldc -128
    //   164: bipush 111
    //   166: bipush 55
    //   168: iconst_3
    //   169: invokestatic 87	xxxxxx/uxxxxx:bbbb0062b0062b0062b0062	(Ljava/lang/String;CCC)Ljava/lang/String;
    //   172: iconst_0
    //   173: anewarray 47	java/lang/Class
    //   176: invokevirtual 51	java/lang/Class:getMethod	(Ljava/lang/String;[Ljava/lang/Class;)Ljava/lang/reflect/Method;
    //   179: astore 19
    //   181: iconst_0
    //   182: anewarray 53	java/lang/Object
    //   185: astore 20
    //   187: aload 19
    //   189: aconst_null
    //   190: aload 20
    //   192: invokevirtual 59	java/lang/reflect/Method:invoke	(Ljava/lang/Object;[Ljava/lang/Object;)Ljava/lang/Object;
    //   195: astore 22
    //   197: aload 22
    //   199: checkcast 61	java/lang/Integer
    //   202: invokevirtual 65	java/lang/Integer:intValue	()I
    //   205: putstatic 33	uuuuuu/vvllll:boo006F006Foo006F006Fo	I
    //   208: ldc 2
    //   210: ldc -19
    //   212: sipush 212
    //   215: bipush 90
    //   217: iconst_1
    //   218: invokestatic 87	xxxxxx/uxxxxx:bbbb0062b0062b0062b0062	(Ljava/lang/String;CCC)Ljava/lang/String;
    //   221: iconst_0
    //   222: anewarray 47	java/lang/Class
    //   225: invokevirtual 51	java/lang/Class:getMethod	(Ljava/lang/String;[Ljava/lang/Class;)Ljava/lang/reflect/Method;
    //   228: astore 23
    //   230: iconst_0
    //   231: anewarray 53	java/lang/Object
    //   234: astore 24
    //   236: aload 23
    //   238: aconst_null
    //   239: aload 24
    //   241: invokevirtual 59	java/lang/reflect/Method:invoke	(Ljava/lang/Object;[Ljava/lang/Object;)Ljava/lang/Object;
    //   244: astore 26
    //   246: aload 26
    //   248: checkcast 61	java/lang/Integer
    //   251: invokevirtual 65	java/lang/Integer:intValue	()I
    //   254: putstatic 67	uuuuuu/vvllll:b006Fo006F006Foo006F006Fo	I
    //   257: bipush 16
    //   259: putstatic 67	uuuuuu/vvllll:b006Fo006F006Foo006F006Fo	I
    //   262: aload_0
    //   263: getfield 114	uuuuuu/vvllll:bnnnnn006E006E006En	Luuuuuu/ttssst$tsssst;
    //   266: checkcast 239	uuuuuu/nnnnnt$nttttn
    //   269: invokeinterface 242 1 0
    //   274: aload_0
    //   275: getfield 101	uuuuuu/vvllll:booo006Foo006F006Fo	Luuuuuu/vpvpvp;
    //   278: aload_0
    //   279: aload_0
    //   280: getfield 246	uuuuuu/vvllll:b006E006E006E006E006En006E006En	Luuuuuu/hyhyhh;
    //   283: invokevirtual 251	uuuuuu/hyhyhh:b0070pp007000700070p007000700070	()Ljava/lang/String;
    //   286: invokeinterface 257 3 0
    //   291: getstatic 33	uuuuuu/vvllll:boo006F006Foo006F006Fo	I
    //   294: getstatic 35	uuuuuu/vvllll:bo006F006F006Foo006F006Fo	I
    //   297: iadd
    //   298: getstatic 33	uuuuuu/vvllll:boo006F006Foo006F006Fo	I
    //   301: imul
    //   302: istore 6
    //   304: ldc 2
    //   306: ldc_w 259
    //   309: bipush 95
    //   311: sipush 238
    //   314: iconst_3
    //   315: invokestatic 87	xxxxxx/uxxxxx:bbbb0062b0062b0062b0062	(Ljava/lang/String;CCC)Ljava/lang/String;
    //   318: iconst_0
    //   319: anewarray 47	java/lang/Class
    //   322: invokevirtual 51	java/lang/Class:getMethod	(Ljava/lang/String;[Ljava/lang/Class;)Ljava/lang/reflect/Method;
    //   325: astore 7
    //   327: iconst_0
    //   328: anewarray 53	java/lang/Object
    //   331: astore 8
    //   333: aload 7
    //   335: aconst_null
    //   336: aload 8
    //   338: invokevirtual 59	java/lang/reflect/Method:invoke	(Ljava/lang/Object;[Ljava/lang/Object;)Ljava/lang/Object;
    //   341: astore 10
    //   343: iload 6
    //   345: aload 10
    //   347: checkcast 61	java/lang/Integer
    //   350: invokevirtual 65	java/lang/Integer:intValue	()I
    //   353: irem
    //   354: istore 11
    //   356: getstatic 67	uuuuuu/vvllll:b006Fo006F006Foo006F006Fo	I
    //   359: istore 12
    //   361: getstatic 33	uuuuuu/vvllll:boo006F006Foo006F006Fo	I
    //   364: istore 13
    //   366: iload 13
    //   368: iload 13
    //   370: getstatic 35	uuuuuu/vvllll:bo006F006F006Foo006F006Fo	I
    //   373: iadd
    //   374: imul
    //   375: getstatic 37	uuuuuu/vvllll:b006F006F006F006Foo006F006Fo	I
    //   378: irem
    //   379: tableswitch	default:+17->396, 0:+27->406
    //   396: bipush 48
    //   398: putstatic 33	uuuuuu/vvllll:boo006F006Foo006F006Fo	I
    //   401: bipush 50
    //   403: putstatic 67	uuuuuu/vvllll:b006Fo006F006Foo006F006Fo	I
    //   406: iload 11
    //   408: iload 12
    //   410: if_icmpeq -403 -> 7
    //   413: bipush 80
    //   415: putstatic 33	uuuuuu/vvllll:boo006F006Foo006F006Fo	I
    //   418: bipush 79
    //   420: putstatic 67	uuuuuu/vvllll:b006Fo006F006Foo006F006Fo	I
    //   423: return
    //   424: astore 4
    //   426: aload 4
    //   428: invokevirtual 93	java/lang/reflect/InvocationTargetException:getCause	()Ljava/lang/Throwable;
    //   431: athrow
    //   432: astore 16
    //   434: aload 16
    //   436: invokevirtual 93	java/lang/reflect/InvocationTargetException:getCause	()Ljava/lang/Throwable;
    //   439: athrow
    //   440: astore 9
    //   442: aload 9
    //   444: invokevirtual 93	java/lang/reflect/InvocationTargetException:getCause	()Ljava/lang/Throwable;
    //   447: athrow
    //   448: astore 21
    //   450: aload 21
    //   452: invokevirtual 93	java/lang/reflect/InvocationTargetException:getCause	()Ljava/lang/Throwable;
    //   455: athrow
    //   456: astore 25
    //   458: aload 25
    //   460: invokevirtual 93	java/lang/reflect/InvocationTargetException:getCause	()Ljava/lang/Throwable;
    //   463: athrow
    // Local variable table:
    //   start	length	slot	name	signature
    //   0	464	0	this	vvllll
    //   11	44	1	i	int
    //   29	7	2	localMethod1	Method
    //   34	4	3	arrayOfObject1	Object[]
    //   424	3	4	localInvocationTargetException1	InvocationTargetException
    //   41	5	5	localObject1	Object
    //   302	52	6	j	int
    //   325	9	7	localMethod2	Method
    //   331	6	8	arrayOfObject2	Object[]
    //   440	3	9	localInvocationTargetException2	InvocationTargetException
    //   341	5	10	localObject2	Object
    //   354	57	11	k	int
    //   359	52	12	m	int
    //   364	11	13	n	int
    //   94	9	14	localMethod3	Method
    //   100	6	15	arrayOfObject3	Object[]
    //   432	3	16	localInvocationTargetException3	InvocationTargetException
    //   110	3	17	localObject3	Object
    //   126	11	18	i1	int
    //   179	9	19	localMethod4	Method
    //   185	6	20	arrayOfObject4	Object[]
    //   448	3	21	localInvocationTargetException4	InvocationTargetException
    //   195	3	22	localObject4	Object
    //   228	9	23	localMethod5	Method
    //   234	6	24	arrayOfObject5	Object[]
    //   456	3	25	localInvocationTargetException5	InvocationTargetException
    //   244	3	26	localObject5	Object
    // Exception table:
    //   from	to	target	type
    //   35	43	424	java/lang/reflect/InvocationTargetException
    //   102	112	432	java/lang/reflect/InvocationTargetException
    //   333	343	440	java/lang/reflect/InvocationTargetException
    //   187	197	448	java/lang/reflect/InvocationTargetException
    //   236	246	456	java/lang/reflect/InvocationTargetException
  }
  
  /* Error */
  public void bi0069006900690069i0069ii0069(int paramInt)
  {
    // Byte code:
    //   0: getstatic 33	uuuuuu/vvllll:boo006F006Foo006F006Fo	I
    //   3: getstatic 35	uuuuuu/vvllll:bo006F006F006Foo006F006Fo	I
    //   6: iadd
    //   7: getstatic 33	uuuuuu/vvllll:boo006F006Foo006F006Fo	I
    //   10: imul
    //   11: getstatic 37	uuuuuu/vvllll:b006F006F006F006Foo006F006Fo	I
    //   14: irem
    //   15: istore_2
    //   16: ldc 2
    //   18: ldc_w 281
    //   21: bipush 6
    //   23: bipush 87
    //   25: iconst_1
    //   26: invokestatic 87	xxxxxx/uxxxxx:bbbb0062b0062b0062b0062	(Ljava/lang/String;CCC)Ljava/lang/String;
    //   29: iconst_0
    //   30: anewarray 47	java/lang/Class
    //   33: invokevirtual 51	java/lang/Class:getMethod	(Ljava/lang/String;[Ljava/lang/Class;)Ljava/lang/reflect/Method;
    //   36: astore_3
    //   37: iconst_0
    //   38: anewarray 53	java/lang/Object
    //   41: astore 4
    //   43: aload_3
    //   44: aconst_null
    //   45: aload 4
    //   47: invokevirtual 59	java/lang/reflect/Method:invoke	(Ljava/lang/Object;[Ljava/lang/Object;)Ljava/lang/Object;
    //   50: astore 6
    //   52: iload_2
    //   53: aload 6
    //   55: checkcast 61	java/lang/Integer
    //   58: invokevirtual 65	java/lang/Integer:intValue	()I
    //   61: if_icmpeq +57 -> 118
    //   64: ldc 2
    //   66: ldc_w 283
    //   69: sipush 214
    //   72: iconst_4
    //   73: iconst_0
    //   74: invokestatic 87	xxxxxx/uxxxxx:bbbb0062b0062b0062b0062	(Ljava/lang/String;CCC)Ljava/lang/String;
    //   77: iconst_0
    //   78: anewarray 47	java/lang/Class
    //   81: invokevirtual 51	java/lang/Class:getMethod	(Ljava/lang/String;[Ljava/lang/Class;)Ljava/lang/reflect/Method;
    //   84: astore 16
    //   86: iconst_0
    //   87: anewarray 53	java/lang/Object
    //   90: astore 17
    //   92: aload 16
    //   94: aconst_null
    //   95: aload 17
    //   97: invokevirtual 59	java/lang/reflect/Method:invoke	(Ljava/lang/Object;[Ljava/lang/Object;)Ljava/lang/Object;
    //   100: astore 19
    //   102: aload 19
    //   104: checkcast 61	java/lang/Integer
    //   107: invokevirtual 65	java/lang/Integer:intValue	()I
    //   110: putstatic 33	uuuuuu/vvllll:boo006F006Foo006F006Fo	I
    //   113: bipush 83
    //   115: putstatic 67	uuuuuu/vvllll:b006Fo006F006Foo006F006Fo	I
    //   118: aload_0
    //   119: iload_1
    //   120: putfield 108	uuuuuu/vvllll:b006F006Fo006Foo006F006Fo	I
    //   123: iconst_4
    //   124: istore 7
    //   126: iload 7
    //   128: iconst_0
    //   129: idiv
    //   130: istore 7
    //   132: goto -6 -> 126
    //   135: astore 5
    //   137: aload 5
    //   139: invokevirtual 93	java/lang/reflect/InvocationTargetException:getCause	()Ljava/lang/Throwable;
    //   142: athrow
    //   143: astore 15
    //   145: iconst_1
    //   146: putstatic 33	uuuuuu/vvllll:boo006F006Foo006F006Fo	I
    //   149: return
    //   150: astore 8
    //   152: bipush 40
    //   154: putstatic 33	uuuuuu/vvllll:boo006F006Foo006F006Fo	I
    //   157: iconst_m1
    //   158: newarray int
    //   160: pop
    //   161: getstatic 33	uuuuuu/vvllll:boo006F006Foo006F006Fo	I
    //   164: istore 10
    //   166: iload 10
    //   168: iload 10
    //   170: getstatic 35	uuuuuu/vvllll:bo006F006F006Foo006F006Fo	I
    //   173: iadd
    //   174: imul
    //   175: getstatic 37	uuuuuu/vvllll:b006F006F006F006Foo006F006Fo	I
    //   178: irem
    //   179: tableswitch	default:+17->196, 0:+-22->157
    //   196: ldc 2
    //   198: ldc -118
    //   200: sipush 129
    //   203: bipush 90
    //   205: iconst_1
    //   206: invokestatic 87	xxxxxx/uxxxxx:bbbb0062b0062b0062b0062	(Ljava/lang/String;CCC)Ljava/lang/String;
    //   209: iconst_0
    //   210: anewarray 47	java/lang/Class
    //   213: invokevirtual 51	java/lang/Class:getMethod	(Ljava/lang/String;[Ljava/lang/Class;)Ljava/lang/reflect/Method;
    //   216: astore 11
    //   218: iconst_0
    //   219: anewarray 53	java/lang/Object
    //   222: astore 12
    //   224: aload 11
    //   226: aconst_null
    //   227: aload 12
    //   229: invokevirtual 59	java/lang/reflect/Method:invoke	(Ljava/lang/Object;[Ljava/lang/Object;)Ljava/lang/Object;
    //   232: astore 14
    //   234: aload 14
    //   236: checkcast 61	java/lang/Integer
    //   239: invokevirtual 65	java/lang/Integer:intValue	()I
    //   242: putstatic 33	uuuuuu/vvllll:boo006F006Foo006F006Fo	I
    //   245: bipush 34
    //   247: putstatic 67	uuuuuu/vvllll:b006Fo006F006Foo006F006Fo	I
    //   250: goto -93 -> 157
    //   253: astore 13
    //   255: aload 13
    //   257: invokevirtual 93	java/lang/reflect/InvocationTargetException:getCause	()Ljava/lang/Throwable;
    //   260: athrow
    //   261: astore 18
    //   263: aload 18
    //   265: invokevirtual 93	java/lang/reflect/InvocationTargetException:getCause	()Ljava/lang/Throwable;
    //   268: athrow
    // Local variable table:
    //   start	length	slot	name	signature
    //   0	269	0	this	vvllll
    //   0	269	1	paramInt	int
    //   15	47	2	i	int
    //   36	8	3	localMethod1	Method
    //   41	5	4	arrayOfObject1	Object[]
    //   135	3	5	localInvocationTargetException1	InvocationTargetException
    //   50	4	6	localObject1	Object
    //   124	7	7	j	int
    //   150	1	8	localException1	Exception
    //   164	11	10	k	int
    //   216	9	11	localMethod2	Method
    //   222	6	12	arrayOfObject2	Object[]
    //   253	3	13	localInvocationTargetException2	InvocationTargetException
    //   232	3	14	localObject2	Object
    //   143	1	15	localException2	Exception
    //   84	9	16	localMethod3	Method
    //   90	6	17	arrayOfObject3	Object[]
    //   261	3	18	localInvocationTargetException3	InvocationTargetException
    //   100	3	19	localObject3	Object
    // Exception table:
    //   from	to	target	type
    //   43	52	135	java/lang/reflect/InvocationTargetException
    //   157	161	143	java/lang/Exception
    //   126	132	150	java/lang/Exception
    //   224	234	253	java/lang/reflect/InvocationTargetException
    //   92	102	261	java/lang/reflect/InvocationTargetException
  }
  
  /* Error */
  public void bi0069i00690069i0069ii0069(int paramInt, String paramString)
  {
    // Byte code:
    //   0: aload_0
    //   1: iload_1
    //   2: putfield 108	uuuuuu/vvllll:b006F006Fo006Foo006F006Fo	I
    //   5: ldc 2
    //   7: ldc 83
    //   9: sipush 237
    //   12: iconst_1
    //   13: invokestatic 45	xxxxxx/uxxxxx:bb00620062bb0062b0062b0062	(Ljava/lang/String;CC)Ljava/lang/String;
    //   16: iconst_0
    //   17: anewarray 47	java/lang/Class
    //   20: invokevirtual 51	java/lang/Class:getMethod	(Ljava/lang/String;[Ljava/lang/Class;)Ljava/lang/reflect/Method;
    //   23: astore_3
    //   24: iconst_0
    //   25: anewarray 53	java/lang/Object
    //   28: astore 4
    //   30: aload_3
    //   31: aconst_null
    //   32: aload 4
    //   34: invokevirtual 59	java/lang/reflect/Method:invoke	(Ljava/lang/Object;[Ljava/lang/Object;)Ljava/lang/Object;
    //   37: astore 6
    //   39: aload 6
    //   41: checkcast 61	java/lang/Integer
    //   44: invokevirtual 65	java/lang/Integer:intValue	()I
    //   47: istore 7
    //   49: iload 7
    //   51: iload 7
    //   53: getstatic 35	uuuuuu/vvllll:bo006F006F006Foo006F006Fo	I
    //   56: iadd
    //   57: imul
    //   58: istore 8
    //   60: getstatic 33	uuuuuu/vvllll:boo006F006Foo006F006Fo	I
    //   63: istore 9
    //   65: iload 9
    //   67: iload 9
    //   69: getstatic 35	uuuuuu/vvllll:bo006F006F006Foo006F006Fo	I
    //   72: iadd
    //   73: imul
    //   74: getstatic 37	uuuuuu/vvllll:b006F006F006F006Foo006F006Fo	I
    //   77: irem
    //   78: tableswitch	default:+18->96, 0:+73->151
    //   96: ldc 2
    //   98: ldc -74
    //   100: sipush 227
    //   103: sipush 186
    //   106: iconst_3
    //   107: invokestatic 87	xxxxxx/uxxxxx:bbbb0062b0062b0062b0062	(Ljava/lang/String;CCC)Ljava/lang/String;
    //   110: iconst_0
    //   111: anewarray 47	java/lang/Class
    //   114: invokevirtual 51	java/lang/Class:getMethod	(Ljava/lang/String;[Ljava/lang/Class;)Ljava/lang/reflect/Method;
    //   117: astore 32
    //   119: iconst_0
    //   120: anewarray 53	java/lang/Object
    //   123: astore 33
    //   125: aload 32
    //   127: aconst_null
    //   128: aload 33
    //   130: invokevirtual 59	java/lang/reflect/Method:invoke	(Ljava/lang/Object;[Ljava/lang/Object;)Ljava/lang/Object;
    //   133: astore 35
    //   135: aload 35
    //   137: checkcast 61	java/lang/Integer
    //   140: invokevirtual 65	java/lang/Integer:intValue	()I
    //   143: putstatic 33	uuuuuu/vvllll:boo006F006Foo006F006Fo	I
    //   146: bipush 26
    //   148: putstatic 67	uuuuuu/vvllll:b006Fo006F006Foo006F006Fo	I
    //   151: iload 8
    //   153: getstatic 37	uuuuuu/vvllll:b006F006F006F006Foo006F006Fo	I
    //   156: irem
    //   157: tableswitch	default:+19->176, 0:+74->231
    //   176: bipush 60
    //   178: putstatic 33	uuuuuu/vvllll:boo006F006Foo006F006Fo	I
    //   181: ldc 2
    //   183: ldc_w 287
    //   186: bipush 28
    //   188: sipush 141
    //   191: iconst_0
    //   192: invokestatic 87	xxxxxx/uxxxxx:bbbb0062b0062b0062b0062	(Ljava/lang/String;CCC)Ljava/lang/String;
    //   195: iconst_0
    //   196: anewarray 47	java/lang/Class
    //   199: invokevirtual 51	java/lang/Class:getMethod	(Ljava/lang/String;[Ljava/lang/Class;)Ljava/lang/reflect/Method;
    //   202: astore 28
    //   204: iconst_0
    //   205: anewarray 53	java/lang/Object
    //   208: astore 29
    //   210: aload 28
    //   212: aconst_null
    //   213: aload 29
    //   215: invokevirtual 59	java/lang/reflect/Method:invoke	(Ljava/lang/Object;[Ljava/lang/Object;)Ljava/lang/Object;
    //   218: astore 31
    //   220: aload 31
    //   222: checkcast 61	java/lang/Integer
    //   225: invokevirtual 65	java/lang/Integer:intValue	()I
    //   228: putstatic 67	uuuuuu/vvllll:b006Fo006F006Foo006F006Fo	I
    //   231: ldc 2
    //   233: ldc_w 289
    //   236: sipush 207
    //   239: iconst_4
    //   240: invokestatic 45	xxxxxx/uxxxxx:bb00620062bb0062b0062b0062	(Ljava/lang/String;CC)Ljava/lang/String;
    //   243: iconst_0
    //   244: anewarray 47	java/lang/Class
    //   247: invokevirtual 51	java/lang/Class:getMethod	(Ljava/lang/String;[Ljava/lang/Class;)Ljava/lang/reflect/Method;
    //   250: astore 10
    //   252: iconst_0
    //   253: anewarray 53	java/lang/Object
    //   256: astore 11
    //   258: aload 10
    //   260: aconst_null
    //   261: aload 11
    //   263: invokevirtual 59	java/lang/reflect/Method:invoke	(Ljava/lang/Object;[Ljava/lang/Object;)Ljava/lang/Object;
    //   266: astore 13
    //   268: aload 13
    //   270: checkcast 61	java/lang/Integer
    //   273: invokevirtual 65	java/lang/Integer:intValue	()I
    //   276: getstatic 35	uuuuuu/vvllll:bo006F006F006Foo006F006Fo	I
    //   279: iadd
    //   280: istore 14
    //   282: ldc 2
    //   284: ldc_w 291
    //   287: sipush 176
    //   290: iconst_4
    //   291: invokestatic 45	xxxxxx/uxxxxx:bb00620062bb0062b0062b0062	(Ljava/lang/String;CC)Ljava/lang/String;
    //   294: iconst_0
    //   295: anewarray 47	java/lang/Class
    //   298: invokevirtual 51	java/lang/Class:getMethod	(Ljava/lang/String;[Ljava/lang/Class;)Ljava/lang/reflect/Method;
    //   301: astore 15
    //   303: iconst_0
    //   304: anewarray 53	java/lang/Object
    //   307: astore 16
    //   309: aload 15
    //   311: aconst_null
    //   312: aload 16
    //   314: invokevirtual 59	java/lang/reflect/Method:invoke	(Ljava/lang/Object;[Ljava/lang/Object;)Ljava/lang/Object;
    //   317: astore 18
    //   319: iload 14
    //   321: aload 18
    //   323: checkcast 61	java/lang/Integer
    //   326: invokevirtual 65	java/lang/Integer:intValue	()I
    //   329: imul
    //   330: getstatic 37	uuuuuu/vvllll:b006F006F006F006Foo006F006Fo	I
    //   333: irem
    //   334: getstatic 67	uuuuuu/vvllll:b006Fo006F006Foo006F006Fo	I
    //   337: if_icmpeq +148 -> 485
    //   340: bipush 64
    //   342: putstatic 33	uuuuuu/vvllll:boo006F006Foo006F006Fo	I
    //   345: ldc 2
    //   347: ldc -100
    //   349: sipush 141
    //   352: bipush 125
    //   354: iconst_1
    //   355: invokestatic 87	xxxxxx/uxxxxx:bbbb0062b0062b0062b0062	(Ljava/lang/String;CCC)Ljava/lang/String;
    //   358: iconst_0
    //   359: anewarray 47	java/lang/Class
    //   362: invokevirtual 51	java/lang/Class:getMethod	(Ljava/lang/String;[Ljava/lang/Class;)Ljava/lang/reflect/Method;
    //   365: astore 19
    //   367: iconst_0
    //   368: anewarray 53	java/lang/Object
    //   371: astore 20
    //   373: aload 19
    //   375: aconst_null
    //   376: aload 20
    //   378: invokevirtual 59	java/lang/reflect/Method:invoke	(Ljava/lang/Object;[Ljava/lang/Object;)Ljava/lang/Object;
    //   381: astore 22
    //   383: aload 22
    //   385: checkcast 61	java/lang/Integer
    //   388: invokevirtual 65	java/lang/Integer:intValue	()I
    //   391: putstatic 67	uuuuuu/vvllll:b006Fo006F006Foo006F006Fo	I
    //   394: getstatic 33	uuuuuu/vvllll:boo006F006Foo006F006Fo	I
    //   397: istore 23
    //   399: iload 23
    //   401: iload 23
    //   403: getstatic 35	uuuuuu/vvllll:bo006F006F006Foo006F006Fo	I
    //   406: iadd
    //   407: imul
    //   408: getstatic 37	uuuuuu/vvllll:b006F006F006F006Foo006F006Fo	I
    //   411: irem
    //   412: tableswitch	default:+20->432, 0:+73->485
    //   432: ldc 2
    //   434: ldc_w 293
    //   437: sipush 234
    //   440: iconst_2
    //   441: invokestatic 45	xxxxxx/uxxxxx:bb00620062bb0062b0062b0062	(Ljava/lang/String;CC)Ljava/lang/String;
    //   444: iconst_0
    //   445: anewarray 47	java/lang/Class
    //   448: invokevirtual 51	java/lang/Class:getMethod	(Ljava/lang/String;[Ljava/lang/Class;)Ljava/lang/reflect/Method;
    //   451: astore 24
    //   453: iconst_0
    //   454: anewarray 53	java/lang/Object
    //   457: astore 25
    //   459: aload 24
    //   461: aconst_null
    //   462: aload 25
    //   464: invokevirtual 59	java/lang/reflect/Method:invoke	(Ljava/lang/Object;[Ljava/lang/Object;)Ljava/lang/Object;
    //   467: astore 27
    //   469: aload 27
    //   471: checkcast 61	java/lang/Integer
    //   474: invokevirtual 65	java/lang/Integer:intValue	()I
    //   477: putstatic 33	uuuuuu/vvllll:boo006F006Foo006F006Fo	I
    //   480: bipush 96
    //   482: putstatic 67	uuuuuu/vvllll:b006Fo006F006Foo006F006Fo	I
    //   485: aload_0
    //   486: getfield 114	uuuuuu/vvllll:bnnnnn006E006E006En	Luuuuuu/ttssst$tsssst;
    //   489: checkcast 239	uuuuuu/nnnnnt$nttttn
    //   492: invokeinterface 242 1 0
    //   497: aload_0
    //   498: getfield 106	uuuuuu/vvllll:b006Foo006Foo006F006Fo	Luuuuuu/vppppv;
    //   501: new 295	uuuuuu/vvllll$1
    //   504: dup
    //   505: aload_0
    //   506: invokespecial 298	uuuuuu/vvllll$1:<init>	(Luuuuuu/vvllll;)V
    //   509: aload_2
    //   510: invokeinterface 304 3 0
    //   515: return
    //   516: astore 17
    //   518: aload 17
    //   520: invokevirtual 93	java/lang/reflect/InvocationTargetException:getCause	()Ljava/lang/Throwable;
    //   523: athrow
    //   524: astore 21
    //   526: aload 21
    //   528: invokevirtual 93	java/lang/reflect/InvocationTargetException:getCause	()Ljava/lang/Throwable;
    //   531: athrow
    //   532: astore 12
    //   534: aload 12
    //   536: invokevirtual 93	java/lang/reflect/InvocationTargetException:getCause	()Ljava/lang/Throwable;
    //   539: athrow
    //   540: astore 5
    //   542: aload 5
    //   544: invokevirtual 93	java/lang/reflect/InvocationTargetException:getCause	()Ljava/lang/Throwable;
    //   547: athrow
    //   548: astore 30
    //   550: aload 30
    //   552: invokevirtual 93	java/lang/reflect/InvocationTargetException:getCause	()Ljava/lang/Throwable;
    //   555: athrow
    //   556: astore 26
    //   558: aload 26
    //   560: invokevirtual 93	java/lang/reflect/InvocationTargetException:getCause	()Ljava/lang/Throwable;
    //   563: athrow
    //   564: astore 34
    //   566: aload 34
    //   568: invokevirtual 93	java/lang/reflect/InvocationTargetException:getCause	()Ljava/lang/Throwable;
    //   571: athrow
    // Local variable table:
    //   start	length	slot	name	signature
    //   0	572	0	this	vvllll
    //   0	572	1	paramInt	int
    //   0	572	2	paramString	String
    //   23	8	3	localMethod1	Method
    //   28	5	4	arrayOfObject1	Object[]
    //   540	3	5	localInvocationTargetException1	InvocationTargetException
    //   37	3	6	localObject1	Object
    //   47	11	7	i	int
    //   58	99	8	j	int
    //   63	11	9	k	int
    //   250	9	10	localMethod2	Method
    //   256	6	11	arrayOfObject2	Object[]
    //   532	3	12	localInvocationTargetException2	InvocationTargetException
    //   266	3	13	localObject2	Object
    //   280	50	14	m	int
    //   301	9	15	localMethod3	Method
    //   307	6	16	arrayOfObject3	Object[]
    //   516	3	17	localInvocationTargetException3	InvocationTargetException
    //   317	5	18	localObject3	Object
    //   365	9	19	localMethod4	Method
    //   371	6	20	arrayOfObject4	Object[]
    //   524	3	21	localInvocationTargetException4	InvocationTargetException
    //   381	3	22	localObject4	Object
    //   397	11	23	n	int
    //   451	9	24	localMethod5	Method
    //   457	6	25	arrayOfObject5	Object[]
    //   556	3	26	localInvocationTargetException5	InvocationTargetException
    //   467	3	27	localObject5	Object
    //   202	9	28	localMethod6	Method
    //   208	6	29	arrayOfObject6	Object[]
    //   548	3	30	localInvocationTargetException6	InvocationTargetException
    //   218	3	31	localObject6	Object
    //   117	9	32	localMethod7	Method
    //   123	6	33	arrayOfObject7	Object[]
    //   564	3	34	localInvocationTargetException7	InvocationTargetException
    //   133	3	35	localObject7	Object
    // Exception table:
    //   from	to	target	type
    //   309	319	516	java/lang/reflect/InvocationTargetException
    //   373	383	524	java/lang/reflect/InvocationTargetException
    //   258	268	532	java/lang/reflect/InvocationTargetException
    //   30	39	540	java/lang/reflect/InvocationTargetException
    //   210	220	548	java/lang/reflect/InvocationTargetException
    //   459	469	556	java/lang/reflect/InvocationTargetException
    //   125	135	564	java/lang/reflect/InvocationTargetException
  }
  
  /* Error */
  public void bii006900690069i0069ii0069()
  {
    // Byte code:
    //   0: ldc 2
    //   2: ldc_w 307
    //   5: bipush 50
    //   7: sipush 165
    //   10: iconst_3
    //   11: invokestatic 87	xxxxxx/uxxxxx:bbbb0062b0062b0062b0062	(Ljava/lang/String;CCC)Ljava/lang/String;
    //   14: iconst_0
    //   15: anewarray 47	java/lang/Class
    //   18: invokevirtual 51	java/lang/Class:getMethod	(Ljava/lang/String;[Ljava/lang/Class;)Ljava/lang/reflect/Method;
    //   21: astore_1
    //   22: iconst_0
    //   23: anewarray 53	java/lang/Object
    //   26: astore_2
    //   27: aload_1
    //   28: aconst_null
    //   29: aload_2
    //   30: invokevirtual 59	java/lang/reflect/Method:invoke	(Ljava/lang/Object;[Ljava/lang/Object;)Ljava/lang/Object;
    //   33: astore 4
    //   35: aload 4
    //   37: checkcast 61	java/lang/Integer
    //   40: invokevirtual 65	java/lang/Integer:intValue	()I
    //   43: istore 5
    //   45: getstatic 33	uuuuuu/vvllll:boo006F006Foo006F006Fo	I
    //   48: istore 6
    //   50: iload 6
    //   52: iload 6
    //   54: getstatic 35	uuuuuu/vvllll:bo006F006F006Foo006F006Fo	I
    //   57: iadd
    //   58: imul
    //   59: getstatic 37	uuuuuu/vvllll:b006F006F006F006Foo006F006Fo	I
    //   62: irem
    //   63: tableswitch	default:+17->80, 0:+272->335
    //   80: ldc 2
    //   82: ldc_w 309
    //   85: sipush 171
    //   88: iconst_3
    //   89: invokestatic 45	xxxxxx/uxxxxx:bb00620062bb0062b0062b0062	(Ljava/lang/String;CC)Ljava/lang/String;
    //   92: iconst_0
    //   93: anewarray 47	java/lang/Class
    //   96: invokevirtual 51	java/lang/Class:getMethod	(Ljava/lang/String;[Ljava/lang/Class;)Ljava/lang/reflect/Method;
    //   99: astore 11
    //   101: iconst_0
    //   102: anewarray 53	java/lang/Object
    //   105: astore 12
    //   107: aload 11
    //   109: aconst_null
    //   110: aload 12
    //   112: invokevirtual 59	java/lang/reflect/Method:invoke	(Ljava/lang/Object;[Ljava/lang/Object;)Ljava/lang/Object;
    //   115: astore 14
    //   117: aload 14
    //   119: checkcast 61	java/lang/Integer
    //   122: invokevirtual 65	java/lang/Integer:intValue	()I
    //   125: putstatic 33	uuuuuu/vvllll:boo006F006Foo006F006Fo	I
    //   128: bipush 6
    //   130: putstatic 67	uuuuuu/vvllll:b006Fo006F006Foo006F006Fo	I
    //   133: getstatic 33	uuuuuu/vvllll:boo006F006Foo006F006Fo	I
    //   136: getstatic 35	uuuuuu/vvllll:bo006F006F006Foo006F006Fo	I
    //   139: iadd
    //   140: getstatic 33	uuuuuu/vvllll:boo006F006Foo006F006Fo	I
    //   143: imul
    //   144: istore 15
    //   146: getstatic 37	uuuuuu/vvllll:b006F006F006F006Foo006F006Fo	I
    //   149: istore 16
    //   151: getstatic 33	uuuuuu/vvllll:boo006F006Foo006F006Fo	I
    //   154: getstatic 35	uuuuuu/vvllll:bo006F006F006Foo006F006Fo	I
    //   157: iadd
    //   158: getstatic 33	uuuuuu/vvllll:boo006F006Foo006F006Fo	I
    //   161: imul
    //   162: getstatic 37	uuuuuu/vvllll:b006F006F006F006Foo006F006Fo	I
    //   165: irem
    //   166: getstatic 67	uuuuuu/vvllll:b006Fo006F006Foo006F006Fo	I
    //   169: if_icmpeq +56 -> 225
    //   172: ldc 2
    //   174: ldc_w 311
    //   177: sipush 214
    //   180: iconst_0
    //   181: invokestatic 45	xxxxxx/uxxxxx:bb00620062bb0062b0062b0062	(Ljava/lang/String;CC)Ljava/lang/String;
    //   184: iconst_0
    //   185: anewarray 47	java/lang/Class
    //   188: invokevirtual 51	java/lang/Class:getMethod	(Ljava/lang/String;[Ljava/lang/Class;)Ljava/lang/reflect/Method;
    //   191: astore 26
    //   193: iconst_0
    //   194: anewarray 53	java/lang/Object
    //   197: astore 27
    //   199: aload 26
    //   201: aconst_null
    //   202: aload 27
    //   204: invokevirtual 59	java/lang/reflect/Method:invoke	(Ljava/lang/Object;[Ljava/lang/Object;)Ljava/lang/Object;
    //   207: astore 29
    //   209: aload 29
    //   211: checkcast 61	java/lang/Integer
    //   214: invokevirtual 65	java/lang/Integer:intValue	()I
    //   217: putstatic 33	uuuuuu/vvllll:boo006F006Foo006F006Fo	I
    //   220: bipush 10
    //   222: putstatic 67	uuuuuu/vvllll:b006Fo006F006Foo006F006Fo	I
    //   225: iload 15
    //   227: iload 16
    //   229: irem
    //   230: istore 17
    //   232: ldc 2
    //   234: ldc_w 313
    //   237: bipush 43
    //   239: bipush 116
    //   241: iconst_2
    //   242: invokestatic 87	xxxxxx/uxxxxx:bbbb0062b0062b0062b0062	(Ljava/lang/String;CCC)Ljava/lang/String;
    //   245: iconst_0
    //   246: anewarray 47	java/lang/Class
    //   249: invokevirtual 51	java/lang/Class:getMethod	(Ljava/lang/String;[Ljava/lang/Class;)Ljava/lang/reflect/Method;
    //   252: astore 18
    //   254: iconst_0
    //   255: anewarray 53	java/lang/Object
    //   258: astore 19
    //   260: aload 18
    //   262: aconst_null
    //   263: aload 19
    //   265: invokevirtual 59	java/lang/reflect/Method:invoke	(Ljava/lang/Object;[Ljava/lang/Object;)Ljava/lang/Object;
    //   268: astore 21
    //   270: iload 17
    //   272: aload 21
    //   274: checkcast 61	java/lang/Integer
    //   277: invokevirtual 65	java/lang/Integer:intValue	()I
    //   280: if_icmpeq +55 -> 335
    //   283: bipush 77
    //   285: putstatic 33	uuuuuu/vvllll:boo006F006Foo006F006Fo	I
    //   288: ldc 2
    //   290: ldc_w 315
    //   293: bipush 79
    //   295: iconst_5
    //   296: invokestatic 45	xxxxxx/uxxxxx:bb00620062bb0062b0062b0062	(Ljava/lang/String;CC)Ljava/lang/String;
    //   299: iconst_0
    //   300: anewarray 47	java/lang/Class
    //   303: invokevirtual 51	java/lang/Class:getMethod	(Ljava/lang/String;[Ljava/lang/Class;)Ljava/lang/reflect/Method;
    //   306: astore 22
    //   308: iconst_0
    //   309: anewarray 53	java/lang/Object
    //   312: astore 23
    //   314: aload 22
    //   316: aconst_null
    //   317: aload 23
    //   319: invokevirtual 59	java/lang/reflect/Method:invoke	(Ljava/lang/Object;[Ljava/lang/Object;)Ljava/lang/Object;
    //   322: astore 25
    //   324: aload 25
    //   326: checkcast 61	java/lang/Integer
    //   329: invokevirtual 65	java/lang/Integer:intValue	()I
    //   332: putstatic 67	uuuuuu/vvllll:b006Fo006F006Foo006F006Fo	I
    //   335: iload 5
    //   337: iload 5
    //   339: getstatic 35	uuuuuu/vvllll:bo006F006F006Foo006F006Fo	I
    //   342: iadd
    //   343: imul
    //   344: getstatic 37	uuuuuu/vvllll:b006F006F006F006Foo006F006Fo	I
    //   347: irem
    //   348: tableswitch	default:+20->368, 0:+72->420
    //   368: bipush 63
    //   370: putstatic 33	uuuuuu/vvllll:boo006F006Foo006F006Fo	I
    //   373: ldc 2
    //   375: ldc_w 317
    //   378: bipush 101
    //   380: iconst_5
    //   381: invokestatic 45	xxxxxx/uxxxxx:bb00620062bb0062b0062b0062	(Ljava/lang/String;CC)Ljava/lang/String;
    //   384: iconst_0
    //   385: anewarray 47	java/lang/Class
    //   388: invokevirtual 51	java/lang/Class:getMethod	(Ljava/lang/String;[Ljava/lang/Class;)Ljava/lang/reflect/Method;
    //   391: astore 7
    //   393: iconst_0
    //   394: anewarray 53	java/lang/Object
    //   397: astore 8
    //   399: aload 7
    //   401: aconst_null
    //   402: aload 8
    //   404: invokevirtual 59	java/lang/reflect/Method:invoke	(Ljava/lang/Object;[Ljava/lang/Object;)Ljava/lang/Object;
    //   407: astore 10
    //   409: aload 10
    //   411: checkcast 61	java/lang/Integer
    //   414: invokevirtual 65	java/lang/Integer:intValue	()I
    //   417: putstatic 67	uuuuuu/vvllll:b006Fo006F006Foo006F006Fo	I
    //   420: getstatic 320	uuuuuu/vvrvrv:bx0078xxxxxxx	Luuuuuu/vvrvrv;
    //   423: invokestatic 212	uuuuuu/rrvvrv:b0071q0071qq0071q0071q0071	(Luuuuuu/vvrvrv;)V
    //   426: return
    //   427: astore_3
    //   428: aload_3
    //   429: invokevirtual 93	java/lang/reflect/InvocationTargetException:getCause	()Ljava/lang/Throwable;
    //   432: athrow
    //   433: astore 9
    //   435: aload 9
    //   437: invokevirtual 93	java/lang/reflect/InvocationTargetException:getCause	()Ljava/lang/Throwable;
    //   440: athrow
    //   441: astore 20
    //   443: aload 20
    //   445: invokevirtual 93	java/lang/reflect/InvocationTargetException:getCause	()Ljava/lang/Throwable;
    //   448: athrow
    //   449: astore 13
    //   451: aload 13
    //   453: invokevirtual 93	java/lang/reflect/InvocationTargetException:getCause	()Ljava/lang/Throwable;
    //   456: athrow
    //   457: astore 24
    //   459: aload 24
    //   461: invokevirtual 93	java/lang/reflect/InvocationTargetException:getCause	()Ljava/lang/Throwable;
    //   464: athrow
    //   465: astore 28
    //   467: aload 28
    //   469: invokevirtual 93	java/lang/reflect/InvocationTargetException:getCause	()Ljava/lang/Throwable;
    //   472: athrow
    // Local variable table:
    //   start	length	slot	name	signature
    //   0	473	0	this	vvllll
    //   21	7	1	localMethod1	Method
    //   26	4	2	arrayOfObject1	Object[]
    //   427	2	3	localInvocationTargetException1	InvocationTargetException
    //   33	3	4	localObject1	Object
    //   43	301	5	i	int
    //   48	11	6	j	int
    //   391	9	7	localMethod2	Method
    //   397	6	8	arrayOfObject2	Object[]
    //   433	3	9	localInvocationTargetException2	InvocationTargetException
    //   407	3	10	localObject2	Object
    //   99	9	11	localMethod3	Method
    //   105	6	12	arrayOfObject3	Object[]
    //   449	3	13	localInvocationTargetException3	InvocationTargetException
    //   115	3	14	localObject3	Object
    //   144	86	15	k	int
    //   149	81	16	m	int
    //   230	51	17	n	int
    //   252	9	18	localMethod4	Method
    //   258	6	19	arrayOfObject4	Object[]
    //   441	3	20	localInvocationTargetException4	InvocationTargetException
    //   268	5	21	localObject4	Object
    //   306	9	22	localMethod5	Method
    //   312	6	23	arrayOfObject5	Object[]
    //   457	3	24	localInvocationTargetException5	InvocationTargetException
    //   322	3	25	localObject5	Object
    //   191	9	26	localMethod6	Method
    //   197	6	27	arrayOfObject6	Object[]
    //   465	3	28	localInvocationTargetException6	InvocationTargetException
    //   207	3	29	localObject6	Object
    // Exception table:
    //   from	to	target	type
    //   27	35	427	java/lang/reflect/InvocationTargetException
    //   399	409	433	java/lang/reflect/InvocationTargetException
    //   260	270	441	java/lang/reflect/InvocationTargetException
    //   107	117	449	java/lang/reflect/InvocationTargetException
    //   314	324	457	java/lang/reflect/InvocationTargetException
    //   199	209	465	java/lang/reflect/InvocationTargetException
  }
  
  /* Error */
  @android.support.annotation.StringRes
  public int bii0069iiiii00690069(com.db.pwcc.dbmobile.model.error.DbError paramDbError)
  {
    // Byte code:
    //   0: getstatic 329	com/db/pwcc/dbmobile/model/error/DbErrorCode:NO_INTERNET_ERROR	Lcom/db/pwcc/dbmobile/model/error/DbErrorCode;
    //   3: astore_2
    //   4: aload_1
    //   5: invokevirtual 335	com/db/pwcc/dbmobile/model/error/DbError:getDbCode	()Lcom/db/pwcc/dbmobile/model/error/DbErrorCode;
    //   8: astore_3
    //   9: getstatic 33	uuuuuu/vvllll:boo006F006Foo006F006Fo	I
    //   12: getstatic 35	uuuuuu/vvllll:bo006F006F006Foo006F006Fo	I
    //   15: iadd
    //   16: istore 4
    //   18: getstatic 33	uuuuuu/vvllll:boo006F006Foo006F006Fo	I
    //   21: istore 5
    //   23: getstatic 33	uuuuuu/vvllll:boo006F006Foo006F006Fo	I
    //   26: istore 6
    //   28: iload 6
    //   30: iload 6
    //   32: getstatic 35	uuuuuu/vvllll:bo006F006F006Foo006F006Fo	I
    //   35: iadd
    //   36: imul
    //   37: istore 7
    //   39: ldc 2
    //   41: ldc_w 337
    //   44: bipush 36
    //   46: bipush 127
    //   48: iconst_3
    //   49: invokestatic 87	xxxxxx/uxxxxx:bbbb0062b0062b0062b0062	(Ljava/lang/String;CCC)Ljava/lang/String;
    //   52: iconst_0
    //   53: anewarray 47	java/lang/Class
    //   56: invokevirtual 51	java/lang/Class:getMethod	(Ljava/lang/String;[Ljava/lang/Class;)Ljava/lang/reflect/Method;
    //   59: astore 8
    //   61: iconst_0
    //   62: anewarray 53	java/lang/Object
    //   65: astore 9
    //   67: aload 8
    //   69: aconst_null
    //   70: aload 9
    //   72: invokevirtual 59	java/lang/reflect/Method:invoke	(Ljava/lang/Object;[Ljava/lang/Object;)Ljava/lang/Object;
    //   75: astore 11
    //   77: iload 7
    //   79: aload 11
    //   81: checkcast 61	java/lang/Integer
    //   84: invokevirtual 65	java/lang/Integer:intValue	()I
    //   87: irem
    //   88: tableswitch	default:+20->108, 0:+121->209
    //   108: ldc 2
    //   110: ldc_w 339
    //   113: bipush 18
    //   115: sipush 212
    //   118: iconst_1
    //   119: invokestatic 87	xxxxxx/uxxxxx:bbbb0062b0062b0062b0062	(Ljava/lang/String;CCC)Ljava/lang/String;
    //   122: iconst_0
    //   123: anewarray 47	java/lang/Class
    //   126: invokevirtual 51	java/lang/Class:getMethod	(Ljava/lang/String;[Ljava/lang/Class;)Ljava/lang/reflect/Method;
    //   129: astore 26
    //   131: iconst_0
    //   132: anewarray 53	java/lang/Object
    //   135: astore 27
    //   137: aload 26
    //   139: aconst_null
    //   140: aload 27
    //   142: invokevirtual 59	java/lang/reflect/Method:invoke	(Ljava/lang/Object;[Ljava/lang/Object;)Ljava/lang/Object;
    //   145: astore 29
    //   147: aload 29
    //   149: checkcast 61	java/lang/Integer
    //   152: invokevirtual 65	java/lang/Integer:intValue	()I
    //   155: putstatic 33	uuuuuu/vvllll:boo006F006Foo006F006Fo	I
    //   158: bipush 42
    //   160: putstatic 67	uuuuuu/vvllll:b006Fo006F006Foo006F006Fo	I
    //   163: getstatic 33	uuuuuu/vvllll:boo006F006Foo006F006Fo	I
    //   166: istore 30
    //   168: iload 30
    //   170: iload 30
    //   172: getstatic 35	uuuuuu/vvllll:bo006F006F006Foo006F006Fo	I
    //   175: iadd
    //   176: imul
    //   177: getstatic 37	uuuuuu/vvllll:b006F006F006F006Foo006F006Fo	I
    //   180: irem
    //   181: tableswitch	default:+19->200, 0:+28->209
    //   200: iconst_3
    //   201: putstatic 33	uuuuuu/vvllll:boo006F006Foo006F006Fo	I
    //   204: bipush 25
    //   206: putstatic 67	uuuuuu/vvllll:b006Fo006F006Foo006F006Fo	I
    //   209: iload 4
    //   211: iload 5
    //   213: imul
    //   214: getstatic 37	uuuuuu/vvllll:b006F006F006F006Foo006F006Fo	I
    //   217: irem
    //   218: istore 12
    //   220: getstatic 33	uuuuuu/vvllll:boo006F006Foo006F006Fo	I
    //   223: istore 13
    //   225: iload 13
    //   227: iload 13
    //   229: getstatic 35	uuuuuu/vvllll:bo006F006F006Foo006F006Fo	I
    //   232: iadd
    //   233: imul
    //   234: getstatic 37	uuuuuu/vvllll:b006F006F006F006Foo006F006Fo	I
    //   237: irem
    //   238: tableswitch	default:+18->256, 0:+72->310
    //   256: bipush 9
    //   258: putstatic 33	uuuuuu/vvllll:boo006F006Foo006F006Fo	I
    //   261: ldc 2
    //   263: ldc_w 341
    //   266: bipush 116
    //   268: bipush 109
    //   270: iconst_1
    //   271: invokestatic 87	xxxxxx/uxxxxx:bbbb0062b0062b0062b0062	(Ljava/lang/String;CCC)Ljava/lang/String;
    //   274: iconst_0
    //   275: anewarray 47	java/lang/Class
    //   278: invokevirtual 51	java/lang/Class:getMethod	(Ljava/lang/String;[Ljava/lang/Class;)Ljava/lang/reflect/Method;
    //   281: astore 22
    //   283: iconst_0
    //   284: anewarray 53	java/lang/Object
    //   287: astore 23
    //   289: aload 22
    //   291: aconst_null
    //   292: aload 23
    //   294: invokevirtual 59	java/lang/reflect/Method:invoke	(Ljava/lang/Object;[Ljava/lang/Object;)Ljava/lang/Object;
    //   297: astore 25
    //   299: aload 25
    //   301: checkcast 61	java/lang/Integer
    //   304: invokevirtual 65	java/lang/Integer:intValue	()I
    //   307: putstatic 67	uuuuuu/vvllll:b006Fo006F006Foo006F006Fo	I
    //   310: iload 12
    //   312: getstatic 67	uuuuuu/vvllll:b006Fo006F006Foo006F006Fo	I
    //   315: if_icmpeq +101 -> 416
    //   318: ldc 2
    //   320: ldc_w 343
    //   323: bipush 8
    //   325: sipush 131
    //   328: iconst_0
    //   329: invokestatic 87	xxxxxx/uxxxxx:bbbb0062b0062b0062b0062	(Ljava/lang/String;CCC)Ljava/lang/String;
    //   332: iconst_0
    //   333: anewarray 47	java/lang/Class
    //   336: invokevirtual 51	java/lang/Class:getMethod	(Ljava/lang/String;[Ljava/lang/Class;)Ljava/lang/reflect/Method;
    //   339: astore 14
    //   341: iconst_0
    //   342: anewarray 53	java/lang/Object
    //   345: astore 15
    //   347: aload 14
    //   349: aconst_null
    //   350: aload 15
    //   352: invokevirtual 59	java/lang/reflect/Method:invoke	(Ljava/lang/Object;[Ljava/lang/Object;)Ljava/lang/Object;
    //   355: astore 17
    //   357: aload 17
    //   359: checkcast 61	java/lang/Integer
    //   362: invokevirtual 65	java/lang/Integer:intValue	()I
    //   365: putstatic 33	uuuuuu/vvllll:boo006F006Foo006F006Fo	I
    //   368: ldc 2
    //   370: ldc_w 345
    //   373: sipush 247
    //   376: iconst_3
    //   377: invokestatic 45	xxxxxx/uxxxxx:bb00620062bb0062b0062b0062	(Ljava/lang/String;CC)Ljava/lang/String;
    //   380: iconst_0
    //   381: anewarray 47	java/lang/Class
    //   384: invokevirtual 51	java/lang/Class:getMethod	(Ljava/lang/String;[Ljava/lang/Class;)Ljava/lang/reflect/Method;
    //   387: astore 18
    //   389: iconst_0
    //   390: anewarray 53	java/lang/Object
    //   393: astore 19
    //   395: aload 18
    //   397: aconst_null
    //   398: aload 19
    //   400: invokevirtual 59	java/lang/reflect/Method:invoke	(Ljava/lang/Object;[Ljava/lang/Object;)Ljava/lang/Object;
    //   403: astore 21
    //   405: aload 21
    //   407: checkcast 61	java/lang/Integer
    //   410: invokevirtual 65	java/lang/Integer:intValue	()I
    //   413: putstatic 67	uuuuuu/vvllll:b006Fo006F006Foo006F006Fo	I
    //   416: aload_2
    //   417: aload_3
    //   418: if_acmpne +39 -> 457
    //   421: getstatic 350	com/db/pwcc/dbmobile/transfer/R$string:check_internet_connection	I
    //   424: ireturn
    //   425: astore 16
    //   427: aload 16
    //   429: invokevirtual 93	java/lang/reflect/InvocationTargetException:getCause	()Ljava/lang/Throwable;
    //   432: athrow
    //   433: astore 28
    //   435: aload 28
    //   437: invokevirtual 93	java/lang/reflect/InvocationTargetException:getCause	()Ljava/lang/Throwable;
    //   440: athrow
    //   441: astore 20
    //   443: aload 20
    //   445: invokevirtual 93	java/lang/reflect/InvocationTargetException:getCause	()Ljava/lang/Throwable;
    //   448: athrow
    //   449: astore 10
    //   451: aload 10
    //   453: invokevirtual 93	java/lang/reflect/InvocationTargetException:getCause	()Ljava/lang/Throwable;
    //   456: athrow
    //   457: getstatic 353	com/db/pwcc/dbmobile/transfer/R$string:technical_error_retry	I
    //   460: ireturn
    //   461: astore 24
    //   463: aload 24
    //   465: invokevirtual 93	java/lang/reflect/InvocationTargetException:getCause	()Ljava/lang/Throwable;
    //   468: athrow
    // Local variable table:
    //   start	length	slot	name	signature
    //   0	469	0	this	vvllll
    //   0	469	1	paramDbError	com.db.pwcc.dbmobile.model.error.DbError
    //   3	414	2	localDbErrorCode1	com.db.pwcc.dbmobile.model.error.DbErrorCode
    //   8	410	3	localDbErrorCode2	com.db.pwcc.dbmobile.model.error.DbErrorCode
    //   16	198	4	i	int
    //   21	193	5	j	int
    //   26	11	6	k	int
    //   37	51	7	m	int
    //   59	9	8	localMethod1	Method
    //   65	6	9	arrayOfObject1	Object[]
    //   449	3	10	localInvocationTargetException1	InvocationTargetException
    //   75	5	11	localObject1	Object
    //   218	98	12	n	int
    //   223	11	13	i1	int
    //   339	9	14	localMethod2	Method
    //   345	6	15	arrayOfObject2	Object[]
    //   425	3	16	localInvocationTargetException2	InvocationTargetException
    //   355	3	17	localObject2	Object
    //   387	9	18	localMethod3	Method
    //   393	6	19	arrayOfObject3	Object[]
    //   441	3	20	localInvocationTargetException3	InvocationTargetException
    //   403	3	21	localObject3	Object
    //   281	9	22	localMethod4	Method
    //   287	6	23	arrayOfObject4	Object[]
    //   461	3	24	localInvocationTargetException4	InvocationTargetException
    //   297	3	25	localObject4	Object
    //   129	9	26	localMethod5	Method
    //   135	6	27	arrayOfObject5	Object[]
    //   433	3	28	localInvocationTargetException5	InvocationTargetException
    //   145	3	29	localObject5	Object
    //   166	11	30	i2	int
    // Exception table:
    //   from	to	target	type
    //   347	357	425	java/lang/reflect/InvocationTargetException
    //   137	147	433	java/lang/reflect/InvocationTargetException
    //   395	405	441	java/lang/reflect/InvocationTargetException
    //   67	77	449	java/lang/reflect/InvocationTargetException
    //   289	299	461	java/lang/reflect/InvocationTargetException
  }
  
  /* Error */
  public void biii00690069i0069ii0069(nnnnnt.nttttn paramNttttn)
  {
    // Byte code:
    //   0: aload_0
    //   1: aload_1
    //   2: invokespecial 357	uuuuuu/ssssst:ba0061a0061a0061a0061aa	(Luuuuuu/ttssst$tsssst;)V
    //   5: iconst_m1
    //   6: newarray int
    //   8: pop
    //   9: goto -4 -> 5
    //   12: astore_2
    //   13: bipush 96
    //   15: putstatic 33	uuuuuu/vvllll:boo006F006Foo006F006Fo	I
    //   18: aload_0
    //   19: getfield 187	uuuuuu/vvllll:bo006Fo006Foo006F006Fo	Z
    //   22: ifeq +217 -> 239
    //   25: getstatic 33	uuuuuu/vvllll:boo006F006Foo006F006Fo	I
    //   28: istore_3
    //   29: ldc 2
    //   31: ldc_w 359
    //   34: sipush 249
    //   37: iconst_5
    //   38: invokestatic 45	xxxxxx/uxxxxx:bb00620062bb0062b0062b0062	(Ljava/lang/String;CC)Ljava/lang/String;
    //   41: iconst_0
    //   42: anewarray 47	java/lang/Class
    //   45: invokevirtual 51	java/lang/Class:getMethod	(Ljava/lang/String;[Ljava/lang/Class;)Ljava/lang/reflect/Method;
    //   48: astore 4
    //   50: iconst_0
    //   51: anewarray 53	java/lang/Object
    //   54: astore 5
    //   56: aload 4
    //   58: aconst_null
    //   59: aload 5
    //   61: invokevirtual 59	java/lang/reflect/Method:invoke	(Ljava/lang/Object;[Ljava/lang/Object;)Ljava/lang/Object;
    //   64: astore 7
    //   66: iload_3
    //   67: iload_3
    //   68: aload 7
    //   70: checkcast 61	java/lang/Integer
    //   73: invokevirtual 65	java/lang/Integer:intValue	()I
    //   76: iadd
    //   77: imul
    //   78: getstatic 37	uuuuuu/vvllll:b006F006F006F006Foo006F006Fo	I
    //   81: irem
    //   82: tableswitch	default:+18->100, 0:+115->197
    //   100: ldc 2
    //   102: ldc -114
    //   104: bipush 27
    //   106: iconst_4
    //   107: invokestatic 45	xxxxxx/uxxxxx:bb00620062bb0062b0062b0062	(Ljava/lang/String;CC)Ljava/lang/String;
    //   110: iconst_0
    //   111: anewarray 47	java/lang/Class
    //   114: invokevirtual 51	java/lang/Class:getMethod	(Ljava/lang/String;[Ljava/lang/Class;)Ljava/lang/reflect/Method;
    //   117: astore 12
    //   119: iconst_0
    //   120: anewarray 53	java/lang/Object
    //   123: astore 13
    //   125: aload 12
    //   127: aconst_null
    //   128: aload 13
    //   130: invokevirtual 59	java/lang/reflect/Method:invoke	(Ljava/lang/Object;[Ljava/lang/Object;)Ljava/lang/Object;
    //   133: astore 15
    //   135: aload 15
    //   137: checkcast 61	java/lang/Integer
    //   140: invokevirtual 65	java/lang/Integer:intValue	()I
    //   143: putstatic 33	uuuuuu/vvllll:boo006F006Foo006F006Fo	I
    //   146: ldc 2
    //   148: ldc_w 361
    //   151: sipush 172
    //   154: sipush 228
    //   157: iconst_2
    //   158: invokestatic 87	xxxxxx/uxxxxx:bbbb0062b0062b0062b0062	(Ljava/lang/String;CCC)Ljava/lang/String;
    //   161: iconst_0
    //   162: anewarray 47	java/lang/Class
    //   165: invokevirtual 51	java/lang/Class:getMethod	(Ljava/lang/String;[Ljava/lang/Class;)Ljava/lang/reflect/Method;
    //   168: astore 16
    //   170: iconst_0
    //   171: anewarray 53	java/lang/Object
    //   174: astore 17
    //   176: aload 16
    //   178: aconst_null
    //   179: aload 17
    //   181: invokevirtual 59	java/lang/reflect/Method:invoke	(Ljava/lang/Object;[Ljava/lang/Object;)Ljava/lang/Object;
    //   184: astore 19
    //   186: aload 19
    //   188: checkcast 61	java/lang/Integer
    //   191: invokevirtual 65	java/lang/Integer:intValue	()I
    //   194: putstatic 67	uuuuuu/vvllll:b006Fo006F006Foo006F006Fo	I
    //   197: ldc 2
    //   199: ldc_w 363
    //   202: bipush 16
    //   204: bipush 102
    //   206: iconst_2
    //   207: invokestatic 87	xxxxxx/uxxxxx:bbbb0062b0062b0062b0062	(Ljava/lang/String;CCC)Ljava/lang/String;
    //   210: iconst_0
    //   211: anewarray 47	java/lang/Class
    //   214: invokevirtual 51	java/lang/Class:getMethod	(Ljava/lang/String;[Ljava/lang/Class;)Ljava/lang/reflect/Method;
    //   217: astore 8
    //   219: iconst_0
    //   220: anewarray 53	java/lang/Object
    //   223: astore 9
    //   225: aload 8
    //   227: aload_0
    //   228: aload 9
    //   230: invokevirtual 59	java/lang/reflect/Method:invoke	(Ljava/lang/Object;[Ljava/lang/Object;)Ljava/lang/Object;
    //   233: pop
    //   234: aload_0
    //   235: iconst_0
    //   236: putfield 187	uuuuuu/vvllll:bo006Fo006Foo006F006Fo	Z
    //   239: return
    //   240: astore 10
    //   242: aload 10
    //   244: invokevirtual 93	java/lang/reflect/InvocationTargetException:getCause	()Ljava/lang/Throwable;
    //   247: athrow
    //   248: astore 6
    //   250: aload 6
    //   252: invokevirtual 93	java/lang/reflect/InvocationTargetException:getCause	()Ljava/lang/Throwable;
    //   255: athrow
    //   256: astore 14
    //   258: aload 14
    //   260: invokevirtual 93	java/lang/reflect/InvocationTargetException:getCause	()Ljava/lang/Throwable;
    //   263: athrow
    //   264: astore 18
    //   266: aload 18
    //   268: invokevirtual 93	java/lang/reflect/InvocationTargetException:getCause	()Ljava/lang/Throwable;
    //   271: athrow
    // Local variable table:
    //   start	length	slot	name	signature
    //   0	272	0	this	vvllll
    //   0	272	1	paramNttttn	nnnnnt.nttttn
    //   12	1	2	localException	Exception
    //   28	50	3	i	int
    //   48	9	4	localMethod1	Method
    //   54	6	5	arrayOfObject1	Object[]
    //   248	3	6	localInvocationTargetException1	InvocationTargetException
    //   64	5	7	localObject1	Object
    //   217	9	8	localMethod2	Method
    //   223	6	9	arrayOfObject2	Object[]
    //   240	3	10	localInvocationTargetException2	InvocationTargetException
    //   117	9	12	localMethod3	Method
    //   123	6	13	arrayOfObject3	Object[]
    //   256	3	14	localInvocationTargetException3	InvocationTargetException
    //   133	3	15	localObject2	Object
    //   168	9	16	localMethod4	Method
    //   174	6	17	arrayOfObject4	Object[]
    //   264	3	18	localInvocationTargetException4	InvocationTargetException
    //   184	3	19	localObject3	Object
    // Exception table:
    //   from	to	target	type
    //   5	9	12	java/lang/Exception
    //   225	234	240	java/lang/reflect/InvocationTargetException
    //   56	66	248	java/lang/reflect/InvocationTargetException
    //   125	135	256	java/lang/reflect/InvocationTargetException
    //   176	186	264	java/lang/reflect/InvocationTargetException
  }
  
  /* Error */
  public void onGetFinancialOverviewError(com.db.pwcc.dbmobile.model.error.DbError paramDbError)
  {
    // Byte code:
    //   0: getstatic 89	uuuuuu/vvllll:b006F006F006Fooo006F006Fo	Ljava/lang/String;
    //   3: astore_2
    //   4: getstatic 33	uuuuuu/vvllll:boo006F006Foo006F006Fo	I
    //   7: istore_3
    //   8: getstatic 33	uuuuuu/vvllll:boo006F006Foo006F006Fo	I
    //   11: istore 4
    //   13: iload 4
    //   15: iload 4
    //   17: getstatic 35	uuuuuu/vvllll:bo006F006F006Foo006F006Fo	I
    //   20: iadd
    //   21: imul
    //   22: getstatic 37	uuuuuu/vvllll:b006F006F006F006Foo006F006Fo	I
    //   25: irem
    //   26: tableswitch	default:+18->44, 0:+28->54
    //   44: bipush 33
    //   46: putstatic 33	uuuuuu/vvllll:boo006F006Foo006F006Fo	I
    //   49: bipush 96
    //   51: putstatic 67	uuuuuu/vvllll:b006Fo006F006Foo006F006Fo	I
    //   54: iload_3
    //   55: iload_3
    //   56: getstatic 35	uuuuuu/vvllll:bo006F006F006Foo006F006Fo	I
    //   59: iadd
    //   60: imul
    //   61: getstatic 37	uuuuuu/vvllll:b006F006F006F006Foo006F006Fo	I
    //   64: irem
    //   65: tableswitch	default:+19->84, 0:+309->374
    //   84: ldc 2
    //   86: ldc_w 367
    //   89: bipush 90
    //   91: bipush 44
    //   93: iconst_1
    //   94: invokestatic 87	xxxxxx/uxxxxx:bbbb0062b0062b0062b0062	(Ljava/lang/String;CCC)Ljava/lang/String;
    //   97: iconst_0
    //   98: anewarray 47	java/lang/Class
    //   101: invokevirtual 51	java/lang/Class:getMethod	(Ljava/lang/String;[Ljava/lang/Class;)Ljava/lang/reflect/Method;
    //   104: astore 10
    //   106: iconst_0
    //   107: anewarray 53	java/lang/Object
    //   110: astore 11
    //   112: aload 10
    //   114: aconst_null
    //   115: aload 11
    //   117: invokevirtual 59	java/lang/reflect/Method:invoke	(Ljava/lang/Object;[Ljava/lang/Object;)Ljava/lang/Object;
    //   120: astore 13
    //   122: aload 13
    //   124: checkcast 61	java/lang/Integer
    //   127: invokevirtual 65	java/lang/Integer:intValue	()I
    //   130: putstatic 33	uuuuuu/vvllll:boo006F006Foo006F006Fo	I
    //   133: bipush 42
    //   135: putstatic 67	uuuuuu/vvllll:b006Fo006F006Foo006F006Fo	I
    //   138: getstatic 33	uuuuuu/vvllll:boo006F006Foo006F006Fo	I
    //   141: getstatic 35	uuuuuu/vvllll:bo006F006F006Foo006F006Fo	I
    //   144: iadd
    //   145: getstatic 33	uuuuuu/vvllll:boo006F006Foo006F006Fo	I
    //   148: imul
    //   149: getstatic 37	uuuuuu/vvllll:b006F006F006F006Foo006F006Fo	I
    //   152: irem
    //   153: getstatic 67	uuuuuu/vvllll:b006Fo006F006Foo006F006Fo	I
    //   156: if_icmpeq +55 -> 211
    //   159: bipush 85
    //   161: putstatic 33	uuuuuu/vvllll:boo006F006Foo006F006Fo	I
    //   164: ldc 2
    //   166: ldc -65
    //   168: sipush 218
    //   171: iconst_0
    //   172: invokestatic 45	xxxxxx/uxxxxx:bb00620062bb0062b0062b0062	(Ljava/lang/String;CC)Ljava/lang/String;
    //   175: iconst_0
    //   176: anewarray 47	java/lang/Class
    //   179: invokevirtual 51	java/lang/Class:getMethod	(Ljava/lang/String;[Ljava/lang/Class;)Ljava/lang/reflect/Method;
    //   182: astore 27
    //   184: iconst_0
    //   185: anewarray 53	java/lang/Object
    //   188: astore 28
    //   190: aload 27
    //   192: aconst_null
    //   193: aload 28
    //   195: invokevirtual 59	java/lang/reflect/Method:invoke	(Ljava/lang/Object;[Ljava/lang/Object;)Ljava/lang/Object;
    //   198: astore 30
    //   200: aload 30
    //   202: checkcast 61	java/lang/Integer
    //   205: invokevirtual 65	java/lang/Integer:intValue	()I
    //   208: putstatic 67	uuuuuu/vvllll:b006Fo006F006Foo006F006Fo	I
    //   211: getstatic 33	uuuuuu/vvllll:boo006F006Foo006F006Fo	I
    //   214: getstatic 35	uuuuuu/vvllll:bo006F006F006Foo006F006Fo	I
    //   217: iadd
    //   218: getstatic 33	uuuuuu/vvllll:boo006F006Foo006F006Fo	I
    //   221: imul
    //   222: istore 14
    //   224: ldc 2
    //   226: ldc_w 369
    //   229: sipush 185
    //   232: iconst_0
    //   233: invokestatic 45	xxxxxx/uxxxxx:bb00620062bb0062b0062b0062	(Ljava/lang/String;CC)Ljava/lang/String;
    //   236: iconst_0
    //   237: anewarray 47	java/lang/Class
    //   240: invokevirtual 51	java/lang/Class:getMethod	(Ljava/lang/String;[Ljava/lang/Class;)Ljava/lang/reflect/Method;
    //   243: astore 15
    //   245: iconst_0
    //   246: anewarray 53	java/lang/Object
    //   249: astore 16
    //   251: aload 15
    //   253: aconst_null
    //   254: aload 16
    //   256: invokevirtual 59	java/lang/reflect/Method:invoke	(Ljava/lang/Object;[Ljava/lang/Object;)Ljava/lang/Object;
    //   259: astore 18
    //   261: iload 14
    //   263: aload 18
    //   265: checkcast 61	java/lang/Integer
    //   268: invokevirtual 65	java/lang/Integer:intValue	()I
    //   271: irem
    //   272: getstatic 67	uuuuuu/vvllll:b006Fo006F006Foo006F006Fo	I
    //   275: if_icmpeq +99 -> 374
    //   278: ldc 2
    //   280: ldc -19
    //   282: sipush 166
    //   285: bipush 83
    //   287: iconst_0
    //   288: invokestatic 87	xxxxxx/uxxxxx:bbbb0062b0062b0062b0062	(Ljava/lang/String;CCC)Ljava/lang/String;
    //   291: iconst_0
    //   292: anewarray 47	java/lang/Class
    //   295: invokevirtual 51	java/lang/Class:getMethod	(Ljava/lang/String;[Ljava/lang/Class;)Ljava/lang/reflect/Method;
    //   298: astore 19
    //   300: iconst_0
    //   301: anewarray 53	java/lang/Object
    //   304: astore 20
    //   306: aload 19
    //   308: aconst_null
    //   309: aload 20
    //   311: invokevirtual 59	java/lang/reflect/Method:invoke	(Ljava/lang/Object;[Ljava/lang/Object;)Ljava/lang/Object;
    //   314: astore 22
    //   316: aload 22
    //   318: checkcast 61	java/lang/Integer
    //   321: invokevirtual 65	java/lang/Integer:intValue	()I
    //   324: putstatic 33	uuuuuu/vvllll:boo006F006Foo006F006Fo	I
    //   327: ldc 2
    //   329: ldc_w 371
    //   332: bipush 106
    //   334: iconst_0
    //   335: invokestatic 45	xxxxxx/uxxxxx:bb00620062bb0062b0062b0062	(Ljava/lang/String;CC)Ljava/lang/String;
    //   338: iconst_0
    //   339: anewarray 47	java/lang/Class
    //   342: invokevirtual 51	java/lang/Class:getMethod	(Ljava/lang/String;[Ljava/lang/Class;)Ljava/lang/reflect/Method;
    //   345: astore 23
    //   347: iconst_0
    //   348: anewarray 53	java/lang/Object
    //   351: astore 24
    //   353: aload 23
    //   355: aconst_null
    //   356: aload 24
    //   358: invokevirtual 59	java/lang/reflect/Method:invoke	(Ljava/lang/Object;[Ljava/lang/Object;)Ljava/lang/Object;
    //   361: astore 26
    //   363: aload 26
    //   365: checkcast 61	java/lang/Integer
    //   368: invokevirtual 65	java/lang/Integer:intValue	()I
    //   371: putstatic 67	uuuuuu/vvllll:b006Fo006F006Foo006F006Fo	I
    //   374: aload_2
    //   375: ldc_w 373
    //   378: aload_1
    //   379: invokestatic 379	uuuuuu/rvvvrv:b00710071qq00710071q0071q0071	(Ljava/lang/String;Ljava/lang/String;Ljava/lang/Throwable;)V
    //   382: aload_0
    //   383: invokevirtual 231	uuuuuu/vvllll:bkk006Bk006Bk006Bk006Bk	()Z
    //   386: ifeq +77 -> 463
    //   389: aload_0
    //   390: getfield 114	uuuuuu/vvllll:bnnnnn006E006E006En	Luuuuuu/ttssst$tsssst;
    //   393: checkcast 239	uuuuuu/nnnnnt$nttttn
    //   396: astore 5
    //   398: ldc 2
    //   400: ldc_w 381
    //   403: sipush 209
    //   406: sipush 179
    //   409: iconst_0
    //   410: invokestatic 87	xxxxxx/uxxxxx:bbbb0062b0062b0062b0062	(Ljava/lang/String;CCC)Ljava/lang/String;
    //   413: iconst_1
    //   414: anewarray 47	java/lang/Class
    //   417: dup
    //   418: iconst_0
    //   419: ldc_w 331
    //   422: aastore
    //   423: invokevirtual 51	java/lang/Class:getMethod	(Ljava/lang/String;[Ljava/lang/Class;)Ljava/lang/reflect/Method;
    //   426: astore 6
    //   428: iconst_1
    //   429: anewarray 53	java/lang/Object
    //   432: dup
    //   433: iconst_0
    //   434: aload_1
    //   435: aastore
    //   436: astore 7
    //   438: aload 6
    //   440: aload_0
    //   441: aload 7
    //   443: invokevirtual 59	java/lang/reflect/Method:invoke	(Ljava/lang/Object;[Ljava/lang/Object;)Ljava/lang/Object;
    //   446: astore 9
    //   448: aload 5
    //   450: aload 9
    //   452: checkcast 61	java/lang/Integer
    //   455: invokevirtual 65	java/lang/Integer:intValue	()I
    //   458: invokeinterface 384 2 0
    //   463: return
    //   464: astore 29
    //   466: aload 29
    //   468: invokevirtual 93	java/lang/reflect/InvocationTargetException:getCause	()Ljava/lang/Throwable;
    //   471: athrow
    //   472: astore 17
    //   474: aload 17
    //   476: invokevirtual 93	java/lang/reflect/InvocationTargetException:getCause	()Ljava/lang/Throwable;
    //   479: athrow
    //   480: astore 12
    //   482: aload 12
    //   484: invokevirtual 93	java/lang/reflect/InvocationTargetException:getCause	()Ljava/lang/Throwable;
    //   487: athrow
    //   488: astore 8
    //   490: aload 8
    //   492: invokevirtual 93	java/lang/reflect/InvocationTargetException:getCause	()Ljava/lang/Throwable;
    //   495: athrow
    //   496: astore 21
    //   498: aload 21
    //   500: invokevirtual 93	java/lang/reflect/InvocationTargetException:getCause	()Ljava/lang/Throwable;
    //   503: athrow
    //   504: astore 25
    //   506: aload 25
    //   508: invokevirtual 93	java/lang/reflect/InvocationTargetException:getCause	()Ljava/lang/Throwable;
    //   511: athrow
    // Local variable table:
    //   start	length	slot	name	signature
    //   0	512	0	this	vvllll
    //   0	512	1	paramDbError	com.db.pwcc.dbmobile.model.error.DbError
    //   3	372	2	str	String
    //   7	54	3	i	int
    //   11	11	4	j	int
    //   396	53	5	localNttttn	nnnnnt.nttttn
    //   426	13	6	localMethod1	Method
    //   436	6	7	arrayOfObject1	Object[]
    //   488	3	8	localInvocationTargetException1	InvocationTargetException
    //   446	5	9	localObject1	Object
    //   104	9	10	localMethod2	Method
    //   110	6	11	arrayOfObject2	Object[]
    //   480	3	12	localInvocationTargetException2	InvocationTargetException
    //   120	3	13	localObject2	Object
    //   222	50	14	k	int
    //   243	9	15	localMethod3	Method
    //   249	6	16	arrayOfObject3	Object[]
    //   472	3	17	localInvocationTargetException3	InvocationTargetException
    //   259	5	18	localObject3	Object
    //   298	9	19	localMethod4	Method
    //   304	6	20	arrayOfObject4	Object[]
    //   496	3	21	localInvocationTargetException4	InvocationTargetException
    //   314	3	22	localObject4	Object
    //   345	9	23	localMethod5	Method
    //   351	6	24	arrayOfObject5	Object[]
    //   504	3	25	localInvocationTargetException5	InvocationTargetException
    //   361	3	26	localObject5	Object
    //   182	9	27	localMethod6	Method
    //   188	6	28	arrayOfObject6	Object[]
    //   464	3	29	localInvocationTargetException6	InvocationTargetException
    //   198	3	30	localObject6	Object
    // Exception table:
    //   from	to	target	type
    //   190	200	464	java/lang/reflect/InvocationTargetException
    //   251	261	472	java/lang/reflect/InvocationTargetException
    //   112	122	480	java/lang/reflect/InvocationTargetException
    //   438	448	488	java/lang/reflect/InvocationTargetException
    //   306	316	496	java/lang/reflect/InvocationTargetException
    //   353	363	504	java/lang/reflect/InvocationTargetException
  }
  
  /* Error */
  public void onGetFinancialOverviewSuccess(FinancialOverviewData paramFinancialOverviewData)
  {
    // Byte code:
    //   0: aload_1
    //   1: invokevirtual 391	com/db/pwcc/dbmobile/model/banking/FinancialOverviewData:getStandingOrderCapableAccounts	()Ljava/util/List;
    //   4: astore_2
    //   5: aload_2
    //   6: invokeinterface 396 1 0
    //   11: ifne +453 -> 464
    //   14: aload_0
    //   15: getfield 108	uuuuuu/vvllll:b006F006Fo006Foo006F006Fo	I
    //   18: iflt +16 -> 34
    //   21: aload_0
    //   22: getfield 108	uuuuuu/vvllll:b006F006Fo006Foo006F006Fo	I
    //   25: aload_2
    //   26: invokeinterface 399 1 0
    //   31: if_icmplt +8 -> 39
    //   34: aload_0
    //   35: iconst_0
    //   36: putfield 108	uuuuuu/vvllll:b006F006Fo006Foo006F006Fo	I
    //   39: getstatic 33	uuuuuu/vvllll:boo006F006Foo006F006Fo	I
    //   42: getstatic 35	uuuuuu/vvllll:bo006F006F006Foo006F006Fo	I
    //   45: iadd
    //   46: getstatic 33	uuuuuu/vvllll:boo006F006Foo006F006Fo	I
    //   49: imul
    //   50: getstatic 37	uuuuuu/vvllll:b006F006F006F006Foo006F006Fo	I
    //   53: irem
    //   54: getstatic 67	uuuuuu/vvllll:b006Fo006F006Foo006F006Fo	I
    //   57: if_icmpeq +100 -> 157
    //   60: ldc 2
    //   62: ldc_w 289
    //   65: sipush 160
    //   68: iconst_3
    //   69: invokestatic 45	xxxxxx/uxxxxx:bb00620062bb0062b0062b0062	(Ljava/lang/String;CC)Ljava/lang/String;
    //   72: iconst_0
    //   73: anewarray 47	java/lang/Class
    //   76: invokevirtual 51	java/lang/Class:getMethod	(Ljava/lang/String;[Ljava/lang/Class;)Ljava/lang/reflect/Method;
    //   79: astore 23
    //   81: iconst_0
    //   82: anewarray 53	java/lang/Object
    //   85: astore 24
    //   87: aload 23
    //   89: aconst_null
    //   90: aload 24
    //   92: invokevirtual 59	java/lang/reflect/Method:invoke	(Ljava/lang/Object;[Ljava/lang/Object;)Ljava/lang/Object;
    //   95: astore 26
    //   97: aload 26
    //   99: checkcast 61	java/lang/Integer
    //   102: invokevirtual 65	java/lang/Integer:intValue	()I
    //   105: putstatic 33	uuuuuu/vvllll:boo006F006Foo006F006Fo	I
    //   108: ldc 2
    //   110: ldc_w 401
    //   113: iconst_1
    //   114: sipush 174
    //   117: iconst_1
    //   118: invokestatic 87	xxxxxx/uxxxxx:bbbb0062b0062b0062b0062	(Ljava/lang/String;CCC)Ljava/lang/String;
    //   121: iconst_0
    //   122: anewarray 47	java/lang/Class
    //   125: invokevirtual 51	java/lang/Class:getMethod	(Ljava/lang/String;[Ljava/lang/Class;)Ljava/lang/reflect/Method;
    //   128: astore 27
    //   130: iconst_0
    //   131: anewarray 53	java/lang/Object
    //   134: astore 28
    //   136: aload 27
    //   138: aconst_null
    //   139: aload 28
    //   141: invokevirtual 59	java/lang/reflect/Method:invoke	(Ljava/lang/Object;[Ljava/lang/Object;)Ljava/lang/Object;
    //   144: astore 30
    //   146: aload 30
    //   148: checkcast 61	java/lang/Integer
    //   151: invokevirtual 65	java/lang/Integer:intValue	()I
    //   154: putstatic 67	uuuuuu/vvllll:b006Fo006F006Foo006F006Fo	I
    //   157: aload_0
    //   158: invokevirtual 231	uuuuuu/vvllll:bkk006Bk006Bk006Bk006Bk	()Z
    //   161: ifeq +32 -> 193
    //   164: aload_0
    //   165: getfield 114	uuuuuu/vvllll:bnnnnn006E006E006En	Luuuuuu/ttssst$tsssst;
    //   168: checkcast 239	uuuuuu/nnnnnt$nttttn
    //   171: aload_2
    //   172: invokeinterface 405 2 0
    //   177: aload_0
    //   178: getfield 114	uuuuuu/vvllll:bnnnnn006E006E006En	Luuuuuu/ttssst$tsssst;
    //   181: checkcast 239	uuuuuu/nnnnnt$nttttn
    //   184: aload_0
    //   185: getfield 108	uuuuuu/vvllll:b006F006Fo006Foo006F006Fo	I
    //   188: invokeinterface 408 2 0
    //   193: aload_2
    //   194: aload_0
    //   195: getfield 108	uuuuuu/vvllll:b006F006Fo006Foo006F006Fo	I
    //   198: invokeinterface 412 2 0
    //   203: checkcast 414	com/db/pwcc/dbmobile/model/banking/Account
    //   206: invokevirtual 417	com/db/pwcc/dbmobile/model/banking/Account:getId	()Ljava/lang/String;
    //   209: astore 11
    //   211: aload 11
    //   213: ifnull +158 -> 371
    //   216: aload_0
    //   217: getfield 108	uuuuuu/vvllll:b006F006Fo006Foo006F006Fo	I
    //   220: istore 12
    //   222: getstatic 33	uuuuuu/vvllll:boo006F006Foo006F006Fo	I
    //   225: getstatic 35	uuuuuu/vvllll:bo006F006F006Foo006F006Fo	I
    //   228: iadd
    //   229: getstatic 33	uuuuuu/vvllll:boo006F006Foo006F006Fo	I
    //   232: imul
    //   233: getstatic 37	uuuuuu/vvllll:b006F006F006F006Foo006F006Fo	I
    //   236: irem
    //   237: getstatic 67	uuuuuu/vvllll:b006Fo006F006Foo006F006Fo	I
    //   240: if_icmpeq +58 -> 298
    //   243: ldc 2
    //   245: ldc_w 287
    //   248: sipush 193
    //   251: bipush 103
    //   253: iconst_0
    //   254: invokestatic 87	xxxxxx/uxxxxx:bbbb0062b0062b0062b0062	(Ljava/lang/String;CCC)Ljava/lang/String;
    //   257: iconst_0
    //   258: anewarray 47	java/lang/Class
    //   261: invokevirtual 51	java/lang/Class:getMethod	(Ljava/lang/String;[Ljava/lang/Class;)Ljava/lang/reflect/Method;
    //   264: astore 19
    //   266: iconst_0
    //   267: anewarray 53	java/lang/Object
    //   270: astore 20
    //   272: aload 19
    //   274: aconst_null
    //   275: aload 20
    //   277: invokevirtual 59	java/lang/reflect/Method:invoke	(Ljava/lang/Object;[Ljava/lang/Object;)Ljava/lang/Object;
    //   280: astore 22
    //   282: aload 22
    //   284: checkcast 61	java/lang/Integer
    //   287: invokevirtual 65	java/lang/Integer:intValue	()I
    //   290: putstatic 33	uuuuuu/vvllll:boo006F006Foo006F006Fo	I
    //   293: bipush 35
    //   295: putstatic 67	uuuuuu/vvllll:b006Fo006F006Foo006F006Fo	I
    //   298: ldc_w 419
    //   301: sipush 206
    //   304: iconst_4
    //   305: invokestatic 45	xxxxxx/uxxxxx:bb00620062bb0062b0062b0062	(Ljava/lang/String;CC)Ljava/lang/String;
    //   308: astore 13
    //   310: iconst_2
    //   311: anewarray 47	java/lang/Class
    //   314: astore 14
    //   316: aload 14
    //   318: iconst_0
    //   319: getstatic 423	java/lang/Integer:TYPE	Ljava/lang/Class;
    //   322: aastore
    //   323: aload 14
    //   325: iconst_1
    //   326: ldc_w 425
    //   329: aastore
    //   330: ldc 2
    //   332: aload 13
    //   334: aload 14
    //   336: invokevirtual 51	java/lang/Class:getMethod	(Ljava/lang/String;[Ljava/lang/Class;)Ljava/lang/reflect/Method;
    //   339: astore 15
    //   341: iconst_2
    //   342: anewarray 53	java/lang/Object
    //   345: astore 16
    //   347: aload 16
    //   349: iconst_0
    //   350: iload 12
    //   352: invokestatic 429	java/lang/Integer:valueOf	(I)Ljava/lang/Integer;
    //   355: aastore
    //   356: aload 16
    //   358: iconst_1
    //   359: aload 11
    //   361: aastore
    //   362: aload 15
    //   364: aload_0
    //   365: aload 16
    //   367: invokevirtual 59	java/lang/reflect/Method:invoke	(Ljava/lang/Object;[Ljava/lang/Object;)Ljava/lang/Object;
    //   370: pop
    //   371: return
    //   372: aconst_null
    //   373: invokevirtual 432	java/lang/String:length	()I
    //   376: pop
    //   377: goto -5 -> 372
    //   380: astore 5
    //   382: ldc 2
    //   384: ldc_w 434
    //   387: sipush 153
    //   390: sipush 152
    //   393: iconst_3
    //   394: invokestatic 87	xxxxxx/uxxxxx:bbbb0062b0062b0062b0062	(Ljava/lang/String;CCC)Ljava/lang/String;
    //   397: iconst_0
    //   398: anewarray 47	java/lang/Class
    //   401: invokevirtual 51	java/lang/Class:getMethod	(Ljava/lang/String;[Ljava/lang/Class;)Ljava/lang/reflect/Method;
    //   404: astore 6
    //   406: iconst_0
    //   407: anewarray 53	java/lang/Object
    //   410: astore 7
    //   412: aload 6
    //   414: aconst_null
    //   415: aload 7
    //   417: invokevirtual 59	java/lang/reflect/Method:invoke	(Ljava/lang/Object;[Ljava/lang/Object;)Ljava/lang/Object;
    //   420: astore 9
    //   422: aload 9
    //   424: checkcast 61	java/lang/Integer
    //   427: invokevirtual 65	java/lang/Integer:intValue	()I
    //   430: putstatic 33	uuuuuu/vvllll:boo006F006Foo006F006Fo	I
    //   433: return
    //   434: astore 8
    //   436: aload 8
    //   438: invokevirtual 93	java/lang/reflect/InvocationTargetException:getCause	()Ljava/lang/Throwable;
    //   441: athrow
    //   442: astore 4
    //   444: bipush 30
    //   446: putstatic 33	uuuuuu/vvllll:boo006F006Foo006F006Fo	I
    //   449: aload_0
    //   450: getfield 114	uuuuuu/vvllll:bnnnnn006E006E006En	Luuuuuu/ttssst$tsssst;
    //   453: checkcast 239	uuuuuu/nnnnnt$nttttn
    //   456: invokeinterface 437 1 0
    //   461: goto -89 -> 372
    //   464: aload_0
    //   465: invokevirtual 231	uuuuuu/vvllll:bkk006Bk006Bk006Bk006Bk	()Z
    //   468: ifeq -97 -> 371
    //   471: aconst_null
    //   472: invokevirtual 432	java/lang/String:length	()I
    //   475: pop
    //   476: goto -5 -> 471
    //   479: astore 17
    //   481: aload 17
    //   483: invokevirtual 93	java/lang/reflect/InvocationTargetException:getCause	()Ljava/lang/Throwable;
    //   486: athrow
    //   487: astore 21
    //   489: aload 21
    //   491: invokevirtual 93	java/lang/reflect/InvocationTargetException:getCause	()Ljava/lang/Throwable;
    //   494: athrow
    //   495: astore 25
    //   497: aload 25
    //   499: invokevirtual 93	java/lang/reflect/InvocationTargetException:getCause	()Ljava/lang/Throwable;
    //   502: athrow
    //   503: astore 29
    //   505: aload 29
    //   507: invokevirtual 93	java/lang/reflect/InvocationTargetException:getCause	()Ljava/lang/Throwable;
    //   510: athrow
    // Local variable table:
    //   start	length	slot	name	signature
    //   0	511	0	this	vvllll
    //   0	511	1	paramFinancialOverviewData	FinancialOverviewData
    //   4	190	2	localList	List
    //   442	1	4	localException1	Exception
    //   380	1	5	localException2	Exception
    //   404	9	6	localMethod1	Method
    //   410	6	7	arrayOfObject1	Object[]
    //   434	3	8	localInvocationTargetException1	InvocationTargetException
    //   420	3	9	localObject1	Object
    //   209	151	11	str1	String
    //   220	131	12	i	int
    //   308	25	13	str2	String
    //   314	21	14	arrayOfClass	Class[]
    //   339	24	15	localMethod2	Method
    //   345	21	16	arrayOfObject2	Object[]
    //   479	3	17	localInvocationTargetException2	InvocationTargetException
    //   264	9	19	localMethod3	Method
    //   270	6	20	arrayOfObject3	Object[]
    //   487	3	21	localInvocationTargetException3	InvocationTargetException
    //   280	3	22	localObject2	Object
    //   79	9	23	localMethod4	Method
    //   85	6	24	arrayOfObject4	Object[]
    //   495	3	25	localInvocationTargetException4	InvocationTargetException
    //   95	3	26	localObject3	Object
    //   128	9	27	localMethod5	Method
    //   134	6	28	arrayOfObject5	Object[]
    //   503	3	29	localInvocationTargetException5	InvocationTargetException
    //   144	3	30	localObject4	Object
    // Exception table:
    //   from	to	target	type
    //   372	377	380	java/lang/Exception
    //   412	422	434	java/lang/reflect/InvocationTargetException
    //   471	476	442	java/lang/Exception
    //   362	371	479	java/lang/reflect/InvocationTargetException
    //   272	282	487	java/lang/reflect/InvocationTargetException
    //   87	97	495	java/lang/reflect/InvocationTargetException
    //   136	146	503	java/lang/reflect/InvocationTargetException
  }
}
