package uuuuuu;

import com.db.pwcc.dbmobile.foundation.data.manager.broadcasting.ModelUpdatedBroadcastReceiver;
import com.db.pwcc.dbmobile.model.error.DbError;
import java.lang.reflect.InvocationTargetException;
import java.lang.reflect.Method;
import javax.inject.Inject;
import xxxxxx.uxxxxx;

public class xvxxxx
  extends ssssst<mqmmmm.vxxxxx>
  implements mqmmmm.qmmmmm, vvpvvp.ppvvvp, aaalal.lllaal
{
  public static int b00760076v00760076007600760076v = 2;
  public static int b0076v007600760076007600760076v = 0;
  private static final String bv00760076v0076007600760076v = xvxxxx.class.getSimpleName();
  public static int bv0076v00760076007600760076v = 1;
  public static int bvv007600760076007600760076v = 20;
  private final aaalal b007600760076v0076007600760076v = new alaaal();
  public ModelUpdatedBroadcastReceiver b0076vv00760076007600760076v;
  @Inject
  public vxvvvx bvvv00760076007600760076v;
  
  /* Error */
  static
  {
    // Byte code:
    //   0: ldc 2
    //   2: invokevirtual 39	java/lang/Class:getSimpleName	()Ljava/lang/String;
    //   5: putstatic 41	uuuuuu/xvxxxx:bv00760076v0076007600760076v	Ljava/lang/String;
    //   8: ldc 2
    //   10: ldc 43
    //   12: bipush 24
    //   14: iconst_5
    //   15: invokestatic 49	xxxxxx/uxxxxx:bb00620062bb0062b0062b0062	(Ljava/lang/String;CC)Ljava/lang/String;
    //   18: iconst_0
    //   19: anewarray 35	java/lang/Class
    //   22: invokevirtual 53	java/lang/Class:getMethod	(Ljava/lang/String;[Ljava/lang/Class;)Ljava/lang/reflect/Method;
    //   25: astore_0
    //   26: iconst_0
    //   27: anewarray 55	java/lang/Object
    //   30: astore_1
    //   31: aload_0
    //   32: aconst_null
    //   33: aload_1
    //   34: invokevirtual 61	java/lang/reflect/Method:invoke	(Ljava/lang/Object;[Ljava/lang/Object;)Ljava/lang/Object;
    //   37: astore_3
    //   38: aload_3
    //   39: checkcast 63	java/lang/Integer
    //   42: invokevirtual 67	java/lang/Integer:intValue	()I
    //   45: istore 4
    //   47: iload 4
    //   49: getstatic 69	uuuuuu/xvxxxx:bv0076v00760076007600760076v	I
    //   52: iadd
    //   53: istore 5
    //   55: getstatic 71	uuuuuu/xvxxxx:bvv007600760076007600760076v	I
    //   58: getstatic 69	uuuuuu/xvxxxx:bv0076v00760076007600760076v	I
    //   61: iadd
    //   62: istore 6
    //   64: getstatic 71	uuuuuu/xvxxxx:bvv007600760076007600760076v	I
    //   67: getstatic 69	uuuuuu/xvxxxx:bv0076v00760076007600760076v	I
    //   70: iadd
    //   71: getstatic 71	uuuuuu/xvxxxx:bvv007600760076007600760076v	I
    //   74: imul
    //   75: getstatic 73	uuuuuu/xvxxxx:b00760076v00760076007600760076v	I
    //   78: irem
    //   79: getstatic 75	uuuuuu/xvxxxx:b0076v007600760076007600760076v	I
    //   82: if_icmpeq +55 -> 137
    //   85: ldc 2
    //   87: ldc 77
    //   89: sipush 150
    //   92: iconst_4
    //   93: invokestatic 49	xxxxxx/uxxxxx:bb00620062bb0062b0062b0062	(Ljava/lang/String;CC)Ljava/lang/String;
    //   96: iconst_0
    //   97: anewarray 35	java/lang/Class
    //   100: invokevirtual 53	java/lang/Class:getMethod	(Ljava/lang/String;[Ljava/lang/Class;)Ljava/lang/reflect/Method;
    //   103: astore 18
    //   105: iconst_0
    //   106: anewarray 55	java/lang/Object
    //   109: astore 19
    //   111: aload 18
    //   113: aconst_null
    //   114: aload 19
    //   116: invokevirtual 61	java/lang/reflect/Method:invoke	(Ljava/lang/Object;[Ljava/lang/Object;)Ljava/lang/Object;
    //   119: astore 21
    //   121: aload 21
    //   123: checkcast 63	java/lang/Integer
    //   126: invokevirtual 67	java/lang/Integer:intValue	()I
    //   129: putstatic 71	uuuuuu/xvxxxx:bvv007600760076007600760076v	I
    //   132: bipush 79
    //   134: putstatic 75	uuuuuu/xvxxxx:b0076v007600760076007600760076v	I
    //   137: iload 6
    //   139: getstatic 71	uuuuuu/xvxxxx:bvv007600760076007600760076v	I
    //   142: imul
    //   143: istore 7
    //   145: ldc 2
    //   147: ldc 79
    //   149: sipush 170
    //   152: sipush 128
    //   155: iconst_2
    //   156: invokestatic 83	xxxxxx/uxxxxx:bbbb0062b0062b0062b0062	(Ljava/lang/String;CCC)Ljava/lang/String;
    //   159: iconst_0
    //   160: anewarray 35	java/lang/Class
    //   163: invokevirtual 53	java/lang/Class:getMethod	(Ljava/lang/String;[Ljava/lang/Class;)Ljava/lang/reflect/Method;
    //   166: astore 8
    //   168: iconst_0
    //   169: anewarray 55	java/lang/Object
    //   172: astore 9
    //   174: aload 8
    //   176: aconst_null
    //   177: aload 9
    //   179: invokevirtual 61	java/lang/reflect/Method:invoke	(Ljava/lang/Object;[Ljava/lang/Object;)Ljava/lang/Object;
    //   182: astore 11
    //   184: iload 7
    //   186: aload 11
    //   188: checkcast 63	java/lang/Integer
    //   191: invokevirtual 67	java/lang/Integer:intValue	()I
    //   194: irem
    //   195: istore 12
    //   197: ldc 2
    //   199: ldc 85
    //   201: bipush 17
    //   203: bipush 28
    //   205: iconst_1
    //   206: invokestatic 83	xxxxxx/uxxxxx:bbbb0062b0062b0062b0062	(Ljava/lang/String;CCC)Ljava/lang/String;
    //   209: iconst_0
    //   210: anewarray 35	java/lang/Class
    //   213: invokevirtual 53	java/lang/Class:getMethod	(Ljava/lang/String;[Ljava/lang/Class;)Ljava/lang/reflect/Method;
    //   216: astore 13
    //   218: iconst_0
    //   219: anewarray 55	java/lang/Object
    //   222: astore 14
    //   224: aload 13
    //   226: aconst_null
    //   227: aload 14
    //   229: invokevirtual 61	java/lang/reflect/Method:invoke	(Ljava/lang/Object;[Ljava/lang/Object;)Ljava/lang/Object;
    //   232: astore 16
    //   234: aload 16
    //   236: checkcast 63	java/lang/Integer
    //   239: invokevirtual 67	java/lang/Integer:intValue	()I
    //   242: istore 17
    //   244: getstatic 71	uuuuuu/xvxxxx:bvv007600760076007600760076v	I
    //   247: getstatic 69	uuuuuu/xvxxxx:bv0076v00760076007600760076v	I
    //   250: iadd
    //   251: getstatic 71	uuuuuu/xvxxxx:bvv007600760076007600760076v	I
    //   254: imul
    //   255: getstatic 73	uuuuuu/xvxxxx:b00760076v00760076007600760076v	I
    //   258: irem
    //   259: getstatic 75	uuuuuu/xvxxxx:b0076v007600760076007600760076v	I
    //   262: if_icmpeq +13 -> 275
    //   265: bipush 92
    //   267: putstatic 71	uuuuuu/xvxxxx:bvv007600760076007600760076v	I
    //   270: bipush 98
    //   272: putstatic 75	uuuuuu/xvxxxx:b0076v007600760076007600760076v	I
    //   275: iload 12
    //   277: iload 17
    //   279: if_icmpeq +13 -> 292
    //   282: bipush 39
    //   284: putstatic 71	uuuuuu/xvxxxx:bvv007600760076007600760076v	I
    //   287: bipush 44
    //   289: putstatic 69	uuuuuu/xvxxxx:bv0076v00760076007600760076v	I
    //   292: iload 4
    //   294: iload 5
    //   296: imul
    //   297: getstatic 73	uuuuuu/xvxxxx:b00760076v00760076007600760076v	I
    //   300: irem
    //   301: tableswitch	default:+19->320, 0:+24->325
    //   320: bipush 84
    //   322: putstatic 69	uuuuuu/xvxxxx:bv0076v00760076007600760076v	I
    //   325: return
    //   326: astore 15
    //   328: aload 15
    //   330: invokevirtual 89	java/lang/reflect/InvocationTargetException:getCause	()Ljava/lang/Throwable;
    //   333: athrow
    //   334: astore_2
    //   335: aload_2
    //   336: invokevirtual 89	java/lang/reflect/InvocationTargetException:getCause	()Ljava/lang/Throwable;
    //   339: athrow
    //   340: astore 10
    //   342: aload 10
    //   344: invokevirtual 89	java/lang/reflect/InvocationTargetException:getCause	()Ljava/lang/Throwable;
    //   347: athrow
    //   348: astore 20
    //   350: aload 20
    //   352: invokevirtual 89	java/lang/reflect/InvocationTargetException:getCause	()Ljava/lang/Throwable;
    //   355: athrow
    // Local variable table:
    //   start	length	slot	name	signature
    //   25	7	0	localMethod1	Method
    //   30	4	1	arrayOfObject1	Object[]
    //   334	2	2	localInvocationTargetException1	InvocationTargetException
    //   37	2	3	localObject1	Object
    //   45	252	4	i	int
    //   53	244	5	j	int
    //   62	81	6	k	int
    //   143	52	7	m	int
    //   166	9	8	localMethod2	Method
    //   172	6	9	arrayOfObject2	Object[]
    //   340	3	10	localInvocationTargetException2	InvocationTargetException
    //   182	5	11	localObject2	Object
    //   195	85	12	n	int
    //   216	9	13	localMethod3	Method
    //   222	6	14	arrayOfObject3	Object[]
    //   326	3	15	localInvocationTargetException3	InvocationTargetException
    //   232	3	16	localObject3	Object
    //   242	38	17	i1	int
    //   103	9	18	localMethod4	Method
    //   109	6	19	arrayOfObject4	Object[]
    //   348	3	20	localInvocationTargetException4	InvocationTargetException
    //   119	3	21	localObject4	Object
    // Exception table:
    //   from	to	target	type
    //   224	234	326	java/lang/reflect/InvocationTargetException
    //   31	38	334	java/lang/reflect/InvocationTargetException
    //   174	184	340	java/lang/reflect/InvocationTargetException
    //   111	121	348	java/lang/reflect/InvocationTargetException
  }
  
  public xvxxxx()
  {
    xvvvxx.b0075uu00750075007500750075u0075().b0070p007000700070ppppp(this);
  }
  
  public static int b0075007500750075u0075u0075u0075()
  {
    return 0;
  }
  
  public static int b00750075uu00750075u0075u0075()
  {
    return 2;
  }
  
  public static int bu0075uu00750075u0075u0075()
  {
    return 1;
  }
  
  public static int buuuu00750075u0075u0075()
  {
    return 28;
  }
  
  /* Error */
  public void b0061aa00610061aaa0061a(com.db.pwcc.dbmobile.model.profile.Profile paramProfile)
  {
    // Byte code:
    //   0: aload_1
    //   1: ifnull +217 -> 218
    //   4: aload_0
    //   5: invokevirtual 159	uuuuuu/xvxxxx:bkk006Bk006Bk006Bk006Bk	()Z
    //   8: ifne +211 -> 219
    //   11: getstatic 71	uuuuuu/xvxxxx:bvv007600760076007600760076v	I
    //   14: getstatic 69	uuuuuu/xvxxxx:bv0076v00760076007600760076v	I
    //   17: iadd
    //   18: getstatic 71	uuuuuu/xvxxxx:bvv007600760076007600760076v	I
    //   21: imul
    //   22: getstatic 73	uuuuuu/xvxxxx:b00760076v00760076007600760076v	I
    //   25: irem
    //   26: istore 25
    //   28: ldc 2
    //   30: ldc -95
    //   32: bipush 116
    //   34: iconst_5
    //   35: invokestatic 49	xxxxxx/uxxxxx:bb00620062bb0062b0062b0062	(Ljava/lang/String;CC)Ljava/lang/String;
    //   38: iconst_0
    //   39: anewarray 35	java/lang/Class
    //   42: invokevirtual 53	java/lang/Class:getMethod	(Ljava/lang/String;[Ljava/lang/Class;)Ljava/lang/reflect/Method;
    //   45: astore 26
    //   47: iconst_0
    //   48: anewarray 55	java/lang/Object
    //   51: astore 27
    //   53: aload 26
    //   55: aconst_null
    //   56: aload 27
    //   58: invokevirtual 61	java/lang/reflect/Method:invoke	(Ljava/lang/Object;[Ljava/lang/Object;)Ljava/lang/Object;
    //   61: astore 29
    //   63: iload 25
    //   65: aload 29
    //   67: checkcast 63	java/lang/Integer
    //   70: invokevirtual 67	java/lang/Integer:intValue	()I
    //   73: if_icmpeq +145 -> 218
    //   76: getstatic 71	uuuuuu/xvxxxx:bvv007600760076007600760076v	I
    //   79: istore 30
    //   81: iload 30
    //   83: iload 30
    //   85: getstatic 69	uuuuuu/xvxxxx:bv0076v00760076007600760076v	I
    //   88: iadd
    //   89: imul
    //   90: getstatic 73	uuuuuu/xvxxxx:b00760076v00760076007600760076v	I
    //   93: irem
    //   94: tableswitch	default:+18->112, 0:+72->166
    //   112: bipush 51
    //   114: putstatic 71	uuuuuu/xvxxxx:bvv007600760076007600760076v	I
    //   117: ldc 2
    //   119: ldc -93
    //   121: sipush 205
    //   124: bipush 73
    //   126: iconst_2
    //   127: invokestatic 83	xxxxxx/uxxxxx:bbbb0062b0062b0062b0062	(Ljava/lang/String;CCC)Ljava/lang/String;
    //   130: iconst_0
    //   131: anewarray 35	java/lang/Class
    //   134: invokevirtual 53	java/lang/Class:getMethod	(Ljava/lang/String;[Ljava/lang/Class;)Ljava/lang/reflect/Method;
    //   137: astore 35
    //   139: iconst_0
    //   140: anewarray 55	java/lang/Object
    //   143: astore 36
    //   145: aload 35
    //   147: aconst_null
    //   148: aload 36
    //   150: invokevirtual 61	java/lang/reflect/Method:invoke	(Ljava/lang/Object;[Ljava/lang/Object;)Ljava/lang/Object;
    //   153: astore 38
    //   155: aload 38
    //   157: checkcast 63	java/lang/Integer
    //   160: invokevirtual 67	java/lang/Integer:intValue	()I
    //   163: putstatic 75	uuuuuu/xvxxxx:b0076v007600760076007600760076v	I
    //   166: bipush 71
    //   168: putstatic 71	uuuuuu/xvxxxx:bvv007600760076007600760076v	I
    //   171: ldc 2
    //   173: ldc -91
    //   175: sipush 230
    //   178: iconst_2
    //   179: invokestatic 49	xxxxxx/uxxxxx:bb00620062bb0062b0062b0062	(Ljava/lang/String;CC)Ljava/lang/String;
    //   182: iconst_0
    //   183: anewarray 35	java/lang/Class
    //   186: invokevirtual 53	java/lang/Class:getMethod	(Ljava/lang/String;[Ljava/lang/Class;)Ljava/lang/reflect/Method;
    //   189: astore 31
    //   191: iconst_0
    //   192: anewarray 55	java/lang/Object
    //   195: astore 32
    //   197: aload 31
    //   199: aconst_null
    //   200: aload 32
    //   202: invokevirtual 61	java/lang/reflect/Method:invoke	(Ljava/lang/Object;[Ljava/lang/Object;)Ljava/lang/Object;
    //   205: astore 34
    //   207: aload 34
    //   209: checkcast 63	java/lang/Integer
    //   212: invokevirtual 67	java/lang/Integer:intValue	()I
    //   215: putstatic 75	uuuuuu/xvxxxx:b0076v007600760076007600760076v	I
    //   218: return
    //   219: aload_0
    //   220: getfield 119	uuuuuu/xvxxxx:bnnnnn006E006E006En	Luuuuuu/ttssst$tsssst;
    //   223: checkcast 167	uuuuuu/mqmmmm$vxxxxx
    //   226: astore_2
    //   227: aload_1
    //   228: invokevirtual 172	com/db/pwcc/dbmobile/model/profile/Profile:getMandatorId	()Ljava/lang/String;
    //   231: astore_3
    //   232: getstatic 71	uuuuuu/xvxxxx:bvv007600760076007600760076v	I
    //   235: istore 4
    //   237: iload 4
    //   239: iload 4
    //   241: getstatic 69	uuuuuu/xvxxxx:bv0076v00760076007600760076v	I
    //   244: iadd
    //   245: imul
    //   246: getstatic 73	uuuuuu/xvxxxx:b00760076v00760076007600760076v	I
    //   249: irem
    //   250: tableswitch	default:+18->268, 0:+197->447
    //   268: ldc 2
    //   270: ldc -82
    //   272: sipush 185
    //   275: iconst_5
    //   276: invokestatic 49	xxxxxx/uxxxxx:bb00620062bb0062b0062b0062	(Ljava/lang/String;CC)Ljava/lang/String;
    //   279: iconst_0
    //   280: anewarray 35	java/lang/Class
    //   283: invokevirtual 53	java/lang/Class:getMethod	(Ljava/lang/String;[Ljava/lang/Class;)Ljava/lang/reflect/Method;
    //   286: astore 12
    //   288: iconst_0
    //   289: anewarray 55	java/lang/Object
    //   292: astore 13
    //   294: aload 12
    //   296: aconst_null
    //   297: aload 13
    //   299: invokevirtual 61	java/lang/reflect/Method:invoke	(Ljava/lang/Object;[Ljava/lang/Object;)Ljava/lang/Object;
    //   302: astore 15
    //   304: aload 15
    //   306: checkcast 63	java/lang/Integer
    //   309: invokevirtual 67	java/lang/Integer:intValue	()I
    //   312: putstatic 71	uuuuuu/xvxxxx:bvv007600760076007600760076v	I
    //   315: ldc 2
    //   317: ldc -80
    //   319: iconst_4
    //   320: iconst_2
    //   321: invokestatic 49	xxxxxx/uxxxxx:bb00620062bb0062b0062b0062	(Ljava/lang/String;CC)Ljava/lang/String;
    //   324: iconst_0
    //   325: anewarray 35	java/lang/Class
    //   328: invokevirtual 53	java/lang/Class:getMethod	(Ljava/lang/String;[Ljava/lang/Class;)Ljava/lang/reflect/Method;
    //   331: astore 16
    //   333: iconst_0
    //   334: anewarray 55	java/lang/Object
    //   337: astore 17
    //   339: aload 16
    //   341: aconst_null
    //   342: aload 17
    //   344: invokevirtual 61	java/lang/reflect/Method:invoke	(Ljava/lang/Object;[Ljava/lang/Object;)Ljava/lang/Object;
    //   347: astore 19
    //   349: aload 19
    //   351: checkcast 63	java/lang/Integer
    //   354: invokevirtual 67	java/lang/Integer:intValue	()I
    //   357: putstatic 75	uuuuuu/xvxxxx:b0076v007600760076007600760076v	I
    //   360: getstatic 71	uuuuuu/xvxxxx:bvv007600760076007600760076v	I
    //   363: istore 20
    //   365: iload 20
    //   367: iload 20
    //   369: getstatic 69	uuuuuu/xvxxxx:bv0076v00760076007600760076v	I
    //   372: iadd
    //   373: imul
    //   374: getstatic 73	uuuuuu/xvxxxx:b00760076v00760076007600760076v	I
    //   377: irem
    //   378: tableswitch	default:+18->396, 0:+69->447
    //   396: ldc 2
    //   398: ldc -78
    //   400: bipush 32
    //   402: iconst_0
    //   403: invokestatic 49	xxxxxx/uxxxxx:bb00620062bb0062b0062b0062	(Ljava/lang/String;CC)Ljava/lang/String;
    //   406: iconst_0
    //   407: anewarray 35	java/lang/Class
    //   410: invokevirtual 53	java/lang/Class:getMethod	(Ljava/lang/String;[Ljava/lang/Class;)Ljava/lang/reflect/Method;
    //   413: astore 21
    //   415: iconst_0
    //   416: anewarray 55	java/lang/Object
    //   419: astore 22
    //   421: aload 21
    //   423: aconst_null
    //   424: aload 22
    //   426: invokevirtual 61	java/lang/reflect/Method:invoke	(Ljava/lang/Object;[Ljava/lang/Object;)Ljava/lang/Object;
    //   429: astore 24
    //   431: aload 24
    //   433: checkcast 63	java/lang/Integer
    //   436: invokevirtual 67	java/lang/Integer:intValue	()I
    //   439: putstatic 71	uuuuuu/xvxxxx:bvv007600760076007600760076v	I
    //   442: bipush 30
    //   444: putstatic 75	uuuuuu/xvxxxx:b0076v007600760076007600760076v	I
    //   447: aload_3
    //   448: invokevirtual 183	java/lang/String:toLowerCase	()Ljava/lang/String;
    //   451: astore 5
    //   453: ldc -71
    //   455: bipush 11
    //   457: iconst_1
    //   458: invokestatic 49	xxxxxx/uxxxxx:bb00620062bb0062b0062b0062	(Ljava/lang/String;CC)Ljava/lang/String;
    //   461: astore 6
    //   463: iconst_3
    //   464: anewarray 35	java/lang/Class
    //   467: astore 7
    //   469: aload 7
    //   471: iconst_0
    //   472: ldc -76
    //   474: aastore
    //   475: aload 7
    //   477: iconst_1
    //   478: getstatic 191	java/lang/Character:TYPE	Ljava/lang/Class;
    //   481: aastore
    //   482: aload 7
    //   484: iconst_2
    //   485: getstatic 191	java/lang/Character:TYPE	Ljava/lang/Class;
    //   488: aastore
    //   489: ldc -63
    //   491: aload 6
    //   493: aload 7
    //   495: invokevirtual 53	java/lang/Class:getMethod	(Ljava/lang/String;[Ljava/lang/Class;)Ljava/lang/reflect/Method;
    //   498: astore 8
    //   500: iconst_3
    //   501: anewarray 55	java/lang/Object
    //   504: astore 9
    //   506: aload 9
    //   508: iconst_0
    //   509: ldc -61
    //   511: aastore
    //   512: aload 9
    //   514: iconst_1
    //   515: sipush 233
    //   518: invokestatic 199	java/lang/Character:valueOf	(C)Ljava/lang/Character;
    //   521: aastore
    //   522: aload 9
    //   524: iconst_2
    //   525: iconst_2
    //   526: invokestatic 199	java/lang/Character:valueOf	(C)Ljava/lang/Character;
    //   529: aastore
    //   530: aload 8
    //   532: aconst_null
    //   533: aload 9
    //   535: invokevirtual 61	java/lang/reflect/Method:invoke	(Ljava/lang/Object;[Ljava/lang/Object;)Ljava/lang/Object;
    //   538: astore 11
    //   540: aload_2
    //   541: aload 5
    //   543: aload 11
    //   545: checkcast 180	java/lang/String
    //   548: invokevirtual 203	java/lang/String:contains	(Ljava/lang/CharSequence;)Z
    //   551: invokeinterface 207 2 0
    //   556: return
    //   557: astore 18
    //   559: aload 18
    //   561: invokevirtual 89	java/lang/reflect/InvocationTargetException:getCause	()Ljava/lang/Throwable;
    //   564: athrow
    //   565: astore 33
    //   567: aload 33
    //   569: invokevirtual 89	java/lang/reflect/InvocationTargetException:getCause	()Ljava/lang/Throwable;
    //   572: athrow
    //   573: astore 28
    //   575: aload 28
    //   577: invokevirtual 89	java/lang/reflect/InvocationTargetException:getCause	()Ljava/lang/Throwable;
    //   580: athrow
    //   581: astore 10
    //   583: aload 10
    //   585: invokevirtual 89	java/lang/reflect/InvocationTargetException:getCause	()Ljava/lang/Throwable;
    //   588: athrow
    //   589: astore 14
    //   591: aload 14
    //   593: invokevirtual 89	java/lang/reflect/InvocationTargetException:getCause	()Ljava/lang/Throwable;
    //   596: athrow
    //   597: astore 37
    //   599: aload 37
    //   601: invokevirtual 89	java/lang/reflect/InvocationTargetException:getCause	()Ljava/lang/Throwable;
    //   604: athrow
    //   605: astore 23
    //   607: aload 23
    //   609: invokevirtual 89	java/lang/reflect/InvocationTargetException:getCause	()Ljava/lang/Throwable;
    //   612: athrow
    // Local variable table:
    //   start	length	slot	name	signature
    //   0	613	0	this	xvxxxx
    //   0	613	1	paramProfile	com.db.pwcc.dbmobile.model.profile.Profile
    //   226	315	2	localVxxxxx	mqmmmm.vxxxxx
    //   231	217	3	str1	String
    //   235	11	4	i	int
    //   451	91	5	str2	String
    //   461	31	6	str3	String
    //   467	27	7	arrayOfClass	Class[]
    //   498	33	8	localMethod1	Method
    //   504	30	9	arrayOfObject1	Object[]
    //   581	3	10	localInvocationTargetException1	InvocationTargetException
    //   538	6	11	localObject1	Object
    //   286	9	12	localMethod2	Method
    //   292	6	13	arrayOfObject2	Object[]
    //   589	3	14	localInvocationTargetException2	InvocationTargetException
    //   302	3	15	localObject2	Object
    //   331	9	16	localMethod3	Method
    //   337	6	17	arrayOfObject3	Object[]
    //   557	3	18	localInvocationTargetException3	InvocationTargetException
    //   347	3	19	localObject3	Object
    //   363	11	20	j	int
    //   413	9	21	localMethod4	Method
    //   419	6	22	arrayOfObject4	Object[]
    //   605	3	23	localInvocationTargetException4	InvocationTargetException
    //   429	3	24	localObject4	Object
    //   26	48	25	k	int
    //   45	9	26	localMethod5	Method
    //   51	6	27	arrayOfObject5	Object[]
    //   573	3	28	localInvocationTargetException5	InvocationTargetException
    //   61	5	29	localObject5	Object
    //   79	11	30	m	int
    //   189	9	31	localMethod6	Method
    //   195	6	32	arrayOfObject6	Object[]
    //   565	3	33	localInvocationTargetException6	InvocationTargetException
    //   205	3	34	localObject6	Object
    //   137	9	35	localMethod7	Method
    //   143	6	36	arrayOfObject7	Object[]
    //   597	3	37	localInvocationTargetException7	InvocationTargetException
    //   153	3	38	localObject7	Object
    // Exception table:
    //   from	to	target	type
    //   339	349	557	java/lang/reflect/InvocationTargetException
    //   197	207	565	java/lang/reflect/InvocationTargetException
    //   53	63	573	java/lang/reflect/InvocationTargetException
    //   530	540	581	java/lang/reflect/InvocationTargetException
    //   294	304	589	java/lang/reflect/InvocationTargetException
    //   145	155	597	java/lang/reflect/InvocationTargetException
    //   421	431	605	java/lang/reflect/InvocationTargetException
  }
  
  /* Error */
  public void b007500750075u00750075u0075u0075()
  {
    // Byte code:
    //   0: getstatic 71	uuuuuu/xvxxxx:bvv007600760076007600760076v	I
    //   3: getstatic 69	uuuuuu/xvxxxx:bv0076v00760076007600760076v	I
    //   6: iadd
    //   7: getstatic 71	uuuuuu/xvxxxx:bvv007600760076007600760076v	I
    //   10: imul
    //   11: istore_1
    //   12: ldc 2
    //   14: ldc -46
    //   16: bipush 43
    //   18: iconst_2
    //   19: invokestatic 49	xxxxxx/uxxxxx:bb00620062bb0062b0062b0062	(Ljava/lang/String;CC)Ljava/lang/String;
    //   22: iconst_0
    //   23: anewarray 35	java/lang/Class
    //   26: invokevirtual 53	java/lang/Class:getMethod	(Ljava/lang/String;[Ljava/lang/Class;)Ljava/lang/reflect/Method;
    //   29: astore_2
    //   30: iconst_0
    //   31: anewarray 55	java/lang/Object
    //   34: astore_3
    //   35: aload_2
    //   36: aconst_null
    //   37: aload_3
    //   38: invokevirtual 61	java/lang/reflect/Method:invoke	(Ljava/lang/Object;[Ljava/lang/Object;)Ljava/lang/Object;
    //   41: astore 5
    //   43: iload_1
    //   44: aload 5
    //   46: checkcast 63	java/lang/Integer
    //   49: invokevirtual 67	java/lang/Integer:intValue	()I
    //   52: irem
    //   53: getstatic 75	uuuuuu/xvxxxx:b0076v007600760076007600760076v	I
    //   56: if_icmpeq +56 -> 112
    //   59: bipush 27
    //   61: putstatic 71	uuuuuu/xvxxxx:bvv007600760076007600760076v	I
    //   64: ldc 2
    //   66: ldc -44
    //   68: bipush 76
    //   70: bipush 77
    //   72: iconst_2
    //   73: invokestatic 83	xxxxxx/uxxxxx:bbbb0062b0062b0062b0062	(Ljava/lang/String;CCC)Ljava/lang/String;
    //   76: iconst_0
    //   77: anewarray 35	java/lang/Class
    //   80: invokevirtual 53	java/lang/Class:getMethod	(Ljava/lang/String;[Ljava/lang/Class;)Ljava/lang/reflect/Method;
    //   83: astore 31
    //   85: iconst_0
    //   86: anewarray 55	java/lang/Object
    //   89: astore 32
    //   91: aload 31
    //   93: aconst_null
    //   94: aload 32
    //   96: invokevirtual 61	java/lang/reflect/Method:invoke	(Ljava/lang/Object;[Ljava/lang/Object;)Ljava/lang/Object;
    //   99: astore 34
    //   101: aload 34
    //   103: checkcast 63	java/lang/Integer
    //   106: invokevirtual 67	java/lang/Integer:intValue	()I
    //   109: putstatic 75	uuuuuu/xvxxxx:b0076v007600760076007600760076v	I
    //   112: aload_0
    //   113: getfield 216	uuuuuu/xvxxxx:b006E006E006E006E006En006E006En	Luuuuuu/hyhyhh;
    //   116: invokevirtual 222	uuuuuu/hyhyhh:bp0070p007000700070p007000700070	()Luuuuuu/yhhyhh;
    //   119: invokevirtual 227	uuuuuu/yhhyhh:bp0070p0070p0070p007000700070	()Z
    //   122: istore 6
    //   124: getstatic 71	uuuuuu/xvxxxx:bvv007600760076007600760076v	I
    //   127: istore 7
    //   129: getstatic 69	uuuuuu/xvxxxx:bv0076v00760076007600760076v	I
    //   132: istore 8
    //   134: getstatic 71	uuuuuu/xvxxxx:bvv007600760076007600760076v	I
    //   137: istore 9
    //   139: iload 9
    //   141: iload 9
    //   143: getstatic 69	uuuuuu/xvxxxx:bv0076v00760076007600760076v	I
    //   146: iadd
    //   147: imul
    //   148: getstatic 73	uuuuuu/xvxxxx:b00760076v00760076007600760076v	I
    //   151: irem
    //   152: tableswitch	default:+20->172, 0:+73->225
    //   172: ldc 2
    //   174: ldc -27
    //   176: bipush 16
    //   178: bipush 39
    //   180: iconst_3
    //   181: invokestatic 83	xxxxxx/uxxxxx:bbbb0062b0062b0062b0062	(Ljava/lang/String;CCC)Ljava/lang/String;
    //   184: iconst_0
    //   185: anewarray 35	java/lang/Class
    //   188: invokevirtual 53	java/lang/Class:getMethod	(Ljava/lang/String;[Ljava/lang/Class;)Ljava/lang/reflect/Method;
    //   191: astore 27
    //   193: iconst_0
    //   194: anewarray 55	java/lang/Object
    //   197: astore 28
    //   199: aload 27
    //   201: aconst_null
    //   202: aload 28
    //   204: invokevirtual 61	java/lang/reflect/Method:invoke	(Ljava/lang/Object;[Ljava/lang/Object;)Ljava/lang/Object;
    //   207: astore 30
    //   209: aload 30
    //   211: checkcast 63	java/lang/Integer
    //   214: invokevirtual 67	java/lang/Integer:intValue	()I
    //   217: putstatic 71	uuuuuu/xvxxxx:bvv007600760076007600760076v	I
    //   220: bipush 11
    //   222: putstatic 75	uuuuuu/xvxxxx:b0076v007600760076007600760076v	I
    //   225: iload 7
    //   227: iload 7
    //   229: iload 8
    //   231: iadd
    //   232: imul
    //   233: getstatic 73	uuuuuu/xvxxxx:b00760076v00760076007600760076v	I
    //   236: irem
    //   237: tableswitch	default:+19->256, 0:+157->394
    //   256: bipush 21
    //   258: putstatic 71	uuuuuu/xvxxxx:bvv007600760076007600760076v	I
    //   261: iconst_1
    //   262: putstatic 75	uuuuuu/xvxxxx:b0076v007600760076007600760076v	I
    //   265: getstatic 71	uuuuuu/xvxxxx:bvv007600760076007600760076v	I
    //   268: istore 18
    //   270: iload 18
    //   272: iload 18
    //   274: getstatic 69	uuuuuu/xvxxxx:bv0076v00760076007600760076v	I
    //   277: iadd
    //   278: imul
    //   279: getstatic 73	uuuuuu/xvxxxx:b00760076v00760076007600760076v	I
    //   282: irem
    //   283: tableswitch	default:+17->300, 0:+111->394
    //   300: ldc 2
    //   302: ldc -25
    //   304: bipush 118
    //   306: iconst_1
    //   307: invokestatic 49	xxxxxx/uxxxxx:bb00620062bb0062b0062b0062	(Ljava/lang/String;CC)Ljava/lang/String;
    //   310: iconst_0
    //   311: anewarray 35	java/lang/Class
    //   314: invokevirtual 53	java/lang/Class:getMethod	(Ljava/lang/String;[Ljava/lang/Class;)Ljava/lang/reflect/Method;
    //   317: astore 19
    //   319: iconst_0
    //   320: anewarray 55	java/lang/Object
    //   323: astore 20
    //   325: aload 19
    //   327: aconst_null
    //   328: aload 20
    //   330: invokevirtual 61	java/lang/reflect/Method:invoke	(Ljava/lang/Object;[Ljava/lang/Object;)Ljava/lang/Object;
    //   333: astore 22
    //   335: aload 22
    //   337: checkcast 63	java/lang/Integer
    //   340: invokevirtual 67	java/lang/Integer:intValue	()I
    //   343: putstatic 71	uuuuuu/xvxxxx:bvv007600760076007600760076v	I
    //   346: ldc 2
    //   348: ldc -23
    //   350: bipush 12
    //   352: bipush 17
    //   354: iconst_0
    //   355: invokestatic 83	xxxxxx/uxxxxx:bbbb0062b0062b0062b0062	(Ljava/lang/String;CCC)Ljava/lang/String;
    //   358: iconst_0
    //   359: anewarray 35	java/lang/Class
    //   362: invokevirtual 53	java/lang/Class:getMethod	(Ljava/lang/String;[Ljava/lang/Class;)Ljava/lang/reflect/Method;
    //   365: astore 23
    //   367: iconst_0
    //   368: anewarray 55	java/lang/Object
    //   371: astore 24
    //   373: aload 23
    //   375: aconst_null
    //   376: aload 24
    //   378: invokevirtual 61	java/lang/reflect/Method:invoke	(Ljava/lang/Object;[Ljava/lang/Object;)Ljava/lang/Object;
    //   381: astore 26
    //   383: aload 26
    //   385: checkcast 63	java/lang/Integer
    //   388: invokevirtual 67	java/lang/Integer:intValue	()I
    //   391: putstatic 75	uuuuuu/xvxxxx:b0076v007600760076007600760076v	I
    //   394: iload 6
    //   396: ifeq +62 -> 458
    //   399: ldc 2
    //   401: ldc -21
    //   403: bipush 22
    //   405: iconst_3
    //   406: invokestatic 49	xxxxxx/uxxxxx:bb00620062bb0062b0062b0062	(Ljava/lang/String;CC)Ljava/lang/String;
    //   409: iconst_0
    //   410: anewarray 35	java/lang/Class
    //   413: invokevirtual 53	java/lang/Class:getMethod	(Ljava/lang/String;[Ljava/lang/Class;)Ljava/lang/reflect/Method;
    //   416: astore 14
    //   418: iconst_0
    //   419: anewarray 55	java/lang/Object
    //   422: astore 15
    //   424: aload 14
    //   426: aload_0
    //   427: aload 15
    //   429: invokevirtual 61	java/lang/reflect/Method:invoke	(Ljava/lang/Object;[Ljava/lang/Object;)Ljava/lang/Object;
    //   432: pop
    //   433: return
    //   434: astore 4
    //   436: aload 4
    //   438: invokevirtual 89	java/lang/reflect/InvocationTargetException:getCause	()Ljava/lang/Throwable;
    //   441: athrow
    //   442: astore 29
    //   444: aload 29
    //   446: invokevirtual 89	java/lang/reflect/InvocationTargetException:getCause	()Ljava/lang/Throwable;
    //   449: athrow
    //   450: astore 16
    //   452: aload 16
    //   454: invokevirtual 89	java/lang/reflect/InvocationTargetException:getCause	()Ljava/lang/Throwable;
    //   457: athrow
    //   458: ldc 2
    //   460: ldc -19
    //   462: bipush 95
    //   464: bipush 77
    //   466: iconst_3
    //   467: invokestatic 83	xxxxxx/uxxxxx:bbbb0062b0062b0062b0062	(Ljava/lang/String;CCC)Ljava/lang/String;
    //   470: iconst_0
    //   471: anewarray 35	java/lang/Class
    //   474: invokevirtual 53	java/lang/Class:getMethod	(Ljava/lang/String;[Ljava/lang/Class;)Ljava/lang/reflect/Method;
    //   477: astore 10
    //   479: iconst_0
    //   480: anewarray 55	java/lang/Object
    //   483: astore 11
    //   485: aload 10
    //   487: aload_0
    //   488: aload 11
    //   490: invokevirtual 61	java/lang/reflect/Method:invoke	(Ljava/lang/Object;[Ljava/lang/Object;)Ljava/lang/Object;
    //   493: pop
    //   494: return
    //   495: astore 12
    //   497: aload 12
    //   499: invokevirtual 89	java/lang/reflect/InvocationTargetException:getCause	()Ljava/lang/Throwable;
    //   502: athrow
    //   503: astore 33
    //   505: aload 33
    //   507: invokevirtual 89	java/lang/reflect/InvocationTargetException:getCause	()Ljava/lang/Throwable;
    //   510: athrow
    //   511: astore 21
    //   513: aload 21
    //   515: invokevirtual 89	java/lang/reflect/InvocationTargetException:getCause	()Ljava/lang/Throwable;
    //   518: athrow
    //   519: astore 25
    //   521: aload 25
    //   523: invokevirtual 89	java/lang/reflect/InvocationTargetException:getCause	()Ljava/lang/Throwable;
    //   526: athrow
    // Local variable table:
    //   start	length	slot	name	signature
    //   0	527	0	this	xvxxxx
    //   11	42	1	i	int
    //   29	7	2	localMethod1	Method
    //   34	4	3	arrayOfObject1	Object[]
    //   434	3	4	localInvocationTargetException1	InvocationTargetException
    //   41	4	5	localObject1	Object
    //   122	273	6	bool	boolean
    //   127	106	7	j	int
    //   132	100	8	k	int
    //   137	11	9	m	int
    //   477	9	10	localMethod2	Method
    //   483	6	11	arrayOfObject2	Object[]
    //   495	3	12	localInvocationTargetException2	InvocationTargetException
    //   416	9	14	localMethod3	Method
    //   422	6	15	arrayOfObject3	Object[]
    //   450	3	16	localInvocationTargetException3	InvocationTargetException
    //   268	11	18	n	int
    //   317	9	19	localMethod4	Method
    //   323	6	20	arrayOfObject4	Object[]
    //   511	3	21	localInvocationTargetException4	InvocationTargetException
    //   333	3	22	localObject2	Object
    //   365	9	23	localMethod5	Method
    //   371	6	24	arrayOfObject5	Object[]
    //   519	3	25	localInvocationTargetException5	InvocationTargetException
    //   381	3	26	localObject3	Object
    //   191	9	27	localMethod6	Method
    //   197	6	28	arrayOfObject6	Object[]
    //   442	3	29	localInvocationTargetException6	InvocationTargetException
    //   207	3	30	localObject4	Object
    //   83	9	31	localMethod7	Method
    //   89	6	32	arrayOfObject7	Object[]
    //   503	3	33	localInvocationTargetException7	InvocationTargetException
    //   99	3	34	localObject5	Object
    // Exception table:
    //   from	to	target	type
    //   35	43	434	java/lang/reflect/InvocationTargetException
    //   199	209	442	java/lang/reflect/InvocationTargetException
    //   424	433	450	java/lang/reflect/InvocationTargetException
    //   485	494	495	java/lang/reflect/InvocationTargetException
    //   91	101	503	java/lang/reflect/InvocationTargetException
    //   325	335	511	java/lang/reflect/InvocationTargetException
    //   373	383	519	java/lang/reflect/InvocationTargetException
  }
  
  /* Error */
  public void b007500750075uu0075u0075u0075()
  {
    // Byte code:
    //   0: aload_0
    //   1: getfield 119	uuuuuu/xvxxxx:bnnnnn006E006E006En	Luuuuuu/ttssst$tsssst;
    //   4: checkcast 167	uuuuuu/mqmmmm$vxxxxx
    //   7: astore_1
    //   8: aload_0
    //   9: getfield 240	uuuuuu/xvxxxx:bvvv00760076007600760076v	Luuuuuu/vxvvvx;
    //   12: astore_2
    //   13: getstatic 71	uuuuuu/xvxxxx:bvv007600760076007600760076v	I
    //   16: getstatic 69	uuuuuu/xvxxxx:bv0076v00760076007600760076v	I
    //   19: iadd
    //   20: getstatic 71	uuuuuu/xvxxxx:bvv007600760076007600760076v	I
    //   23: imul
    //   24: getstatic 73	uuuuuu/xvxxxx:b00760076v00760076007600760076v	I
    //   27: irem
    //   28: getstatic 75	uuuuuu/xvxxxx:b0076v007600760076007600760076v	I
    //   31: if_icmpeq +450 -> 481
    //   34: bipush 53
    //   36: putstatic 71	uuuuuu/xvxxxx:bvv007600760076007600760076v	I
    //   39: ldc 2
    //   41: ldc -14
    //   43: sipush 186
    //   46: sipush 232
    //   49: iconst_3
    //   50: invokestatic 83	xxxxxx/uxxxxx:bbbb0062b0062b0062b0062	(Ljava/lang/String;CCC)Ljava/lang/String;
    //   53: iconst_0
    //   54: anewarray 35	java/lang/Class
    //   57: invokevirtual 53	java/lang/Class:getMethod	(Ljava/lang/String;[Ljava/lang/Class;)Ljava/lang/reflect/Method;
    //   60: astore_3
    //   61: iconst_0
    //   62: anewarray 55	java/lang/Object
    //   65: astore 4
    //   67: aload_3
    //   68: aconst_null
    //   69: aload 4
    //   71: invokevirtual 61	java/lang/reflect/Method:invoke	(Ljava/lang/Object;[Ljava/lang/Object;)Ljava/lang/Object;
    //   74: astore 6
    //   76: aload 6
    //   78: checkcast 63	java/lang/Integer
    //   81: invokevirtual 67	java/lang/Integer:intValue	()I
    //   84: putstatic 75	uuuuuu/xvxxxx:b0076v007600760076007600760076v	I
    //   87: getstatic 71	uuuuuu/xvxxxx:bvv007600760076007600760076v	I
    //   90: istore 7
    //   92: iload 7
    //   94: iload 7
    //   96: getstatic 69	uuuuuu/xvxxxx:bv0076v00760076007600760076v	I
    //   99: iadd
    //   100: imul
    //   101: getstatic 73	uuuuuu/xvxxxx:b00760076v00760076007600760076v	I
    //   104: irem
    //   105: tableswitch	default:+19->124, 0:+376->481
    //   124: getstatic 71	uuuuuu/xvxxxx:bvv007600760076007600760076v	I
    //   127: istore 8
    //   129: iload 8
    //   131: iload 8
    //   133: getstatic 69	uuuuuu/xvxxxx:bv0076v00760076007600760076v	I
    //   136: iadd
    //   137: imul
    //   138: getstatic 73	uuuuuu/xvxxxx:b00760076v00760076007600760076v	I
    //   141: irem
    //   142: tableswitch	default:+18->160, 0:+115->257
    //   160: ldc 2
    //   162: ldc -12
    //   164: sipush 239
    //   167: sipush 142
    //   170: iconst_3
    //   171: invokestatic 83	xxxxxx/uxxxxx:bbbb0062b0062b0062b0062	(Ljava/lang/String;CCC)Ljava/lang/String;
    //   174: iconst_0
    //   175: anewarray 35	java/lang/Class
    //   178: invokevirtual 53	java/lang/Class:getMethod	(Ljava/lang/String;[Ljava/lang/Class;)Ljava/lang/reflect/Method;
    //   181: astore 26
    //   183: iconst_0
    //   184: anewarray 55	java/lang/Object
    //   187: astore 27
    //   189: aload 26
    //   191: aconst_null
    //   192: aload 27
    //   194: invokevirtual 61	java/lang/reflect/Method:invoke	(Ljava/lang/Object;[Ljava/lang/Object;)Ljava/lang/Object;
    //   197: astore 29
    //   199: aload 29
    //   201: checkcast 63	java/lang/Integer
    //   204: invokevirtual 67	java/lang/Integer:intValue	()I
    //   207: putstatic 71	uuuuuu/xvxxxx:bvv007600760076007600760076v	I
    //   210: ldc 2
    //   212: ldc -10
    //   214: sipush 203
    //   217: iconst_4
    //   218: invokestatic 49	xxxxxx/uxxxxx:bb00620062bb0062b0062b0062	(Ljava/lang/String;CC)Ljava/lang/String;
    //   221: iconst_0
    //   222: anewarray 35	java/lang/Class
    //   225: invokevirtual 53	java/lang/Class:getMethod	(Ljava/lang/String;[Ljava/lang/Class;)Ljava/lang/reflect/Method;
    //   228: astore 30
    //   230: iconst_0
    //   231: anewarray 55	java/lang/Object
    //   234: astore 31
    //   236: aload 30
    //   238: aconst_null
    //   239: aload 31
    //   241: invokevirtual 61	java/lang/reflect/Method:invoke	(Ljava/lang/Object;[Ljava/lang/Object;)Ljava/lang/Object;
    //   244: astore 33
    //   246: aload 33
    //   248: checkcast 63	java/lang/Integer
    //   251: invokevirtual 67	java/lang/Integer:intValue	()I
    //   254: putstatic 75	uuuuuu/xvxxxx:b0076v007600760076007600760076v	I
    //   257: ldc 2
    //   259: ldc -8
    //   261: sipush 225
    //   264: iconst_4
    //   265: invokestatic 49	xxxxxx/uxxxxx:bb00620062bb0062b0062b0062	(Ljava/lang/String;CC)Ljava/lang/String;
    //   268: iconst_0
    //   269: anewarray 35	java/lang/Class
    //   272: invokevirtual 53	java/lang/Class:getMethod	(Ljava/lang/String;[Ljava/lang/Class;)Ljava/lang/reflect/Method;
    //   275: astore 9
    //   277: iconst_0
    //   278: anewarray 55	java/lang/Object
    //   281: astore 10
    //   283: aload 9
    //   285: aconst_null
    //   286: aload 10
    //   288: invokevirtual 61	java/lang/reflect/Method:invoke	(Ljava/lang/Object;[Ljava/lang/Object;)Ljava/lang/Object;
    //   291: astore 12
    //   293: aload 12
    //   295: checkcast 63	java/lang/Integer
    //   298: invokevirtual 67	java/lang/Integer:intValue	()I
    //   301: putstatic 71	uuuuuu/xvxxxx:bvv007600760076007600760076v	I
    //   304: ldc 2
    //   306: ldc -6
    //   308: bipush 70
    //   310: sipush 200
    //   313: iconst_1
    //   314: invokestatic 83	xxxxxx/uxxxxx:bbbb0062b0062b0062b0062	(Ljava/lang/String;CCC)Ljava/lang/String;
    //   317: iconst_0
    //   318: anewarray 35	java/lang/Class
    //   321: invokevirtual 53	java/lang/Class:getMethod	(Ljava/lang/String;[Ljava/lang/Class;)Ljava/lang/reflect/Method;
    //   324: astore 13
    //   326: iconst_0
    //   327: anewarray 55	java/lang/Object
    //   330: astore 14
    //   332: aload 13
    //   334: aconst_null
    //   335: aload 14
    //   337: invokevirtual 61	java/lang/reflect/Method:invoke	(Ljava/lang/Object;[Ljava/lang/Object;)Ljava/lang/Object;
    //   340: astore 16
    //   342: aload 16
    //   344: checkcast 63	java/lang/Integer
    //   347: invokevirtual 67	java/lang/Integer:intValue	()I
    //   350: putstatic 75	uuuuuu/xvxxxx:b0076v007600760076007600760076v	I
    //   353: getstatic 71	uuuuuu/xvxxxx:bvv007600760076007600760076v	I
    //   356: istore 17
    //   358: iload 17
    //   360: iload 17
    //   362: getstatic 69	uuuuuu/xvxxxx:bv0076v00760076007600760076v	I
    //   365: iadd
    //   366: imul
    //   367: getstatic 73	uuuuuu/xvxxxx:b00760076v00760076007600760076v	I
    //   370: irem
    //   371: tableswitch	default:+17->388, 0:+110->481
    //   388: ldc 2
    //   390: ldc -91
    //   392: sipush 246
    //   395: iconst_0
    //   396: invokestatic 49	xxxxxx/uxxxxx:bb00620062bb0062b0062b0062	(Ljava/lang/String;CC)Ljava/lang/String;
    //   399: iconst_0
    //   400: anewarray 35	java/lang/Class
    //   403: invokevirtual 53	java/lang/Class:getMethod	(Ljava/lang/String;[Ljava/lang/Class;)Ljava/lang/reflect/Method;
    //   406: astore 18
    //   408: iconst_0
    //   409: anewarray 55	java/lang/Object
    //   412: astore 19
    //   414: aload 18
    //   416: aconst_null
    //   417: aload 19
    //   419: invokevirtual 61	java/lang/reflect/Method:invoke	(Ljava/lang/Object;[Ljava/lang/Object;)Ljava/lang/Object;
    //   422: astore 21
    //   424: aload 21
    //   426: checkcast 63	java/lang/Integer
    //   429: invokevirtual 67	java/lang/Integer:intValue	()I
    //   432: putstatic 71	uuuuuu/xvxxxx:bvv007600760076007600760076v	I
    //   435: ldc 2
    //   437: ldc -4
    //   439: bipush 67
    //   441: iconst_3
    //   442: invokestatic 49	xxxxxx/uxxxxx:bb00620062bb0062b0062b0062	(Ljava/lang/String;CC)Ljava/lang/String;
    //   445: iconst_0
    //   446: anewarray 35	java/lang/Class
    //   449: invokevirtual 53	java/lang/Class:getMethod	(Ljava/lang/String;[Ljava/lang/Class;)Ljava/lang/reflect/Method;
    //   452: astore 22
    //   454: iconst_0
    //   455: anewarray 55	java/lang/Object
    //   458: astore 23
    //   460: aload 22
    //   462: aconst_null
    //   463: aload 23
    //   465: invokevirtual 61	java/lang/reflect/Method:invoke	(Ljava/lang/Object;[Ljava/lang/Object;)Ljava/lang/Object;
    //   468: astore 25
    //   470: aload 25
    //   472: checkcast 63	java/lang/Integer
    //   475: invokevirtual 67	java/lang/Integer:intValue	()I
    //   478: putstatic 75	uuuuuu/xvxxxx:b0076v007600760076007600760076v	I
    //   481: aload_1
    //   482: aload_2
    //   483: invokevirtual 258	uuuuuu/vxvvvx:bu007500750075u00750075u00750075	()Ljava/util/List;
    //   486: invokeinterface 262 2 0
    //   491: return
    //   492: astore 28
    //   494: aload 28
    //   496: invokevirtual 89	java/lang/reflect/InvocationTargetException:getCause	()Ljava/lang/Throwable;
    //   499: athrow
    //   500: astore 32
    //   502: aload 32
    //   504: invokevirtual 89	java/lang/reflect/InvocationTargetException:getCause	()Ljava/lang/Throwable;
    //   507: athrow
    //   508: astore 5
    //   510: aload 5
    //   512: invokevirtual 89	java/lang/reflect/InvocationTargetException:getCause	()Ljava/lang/Throwable;
    //   515: athrow
    //   516: astore 11
    //   518: aload 11
    //   520: invokevirtual 89	java/lang/reflect/InvocationTargetException:getCause	()Ljava/lang/Throwable;
    //   523: athrow
    //   524: astore 15
    //   526: aload 15
    //   528: invokevirtual 89	java/lang/reflect/InvocationTargetException:getCause	()Ljava/lang/Throwable;
    //   531: athrow
    //   532: astore 20
    //   534: aload 20
    //   536: invokevirtual 89	java/lang/reflect/InvocationTargetException:getCause	()Ljava/lang/Throwable;
    //   539: athrow
    //   540: astore 24
    //   542: aload 24
    //   544: invokevirtual 89	java/lang/reflect/InvocationTargetException:getCause	()Ljava/lang/Throwable;
    //   547: athrow
    // Local variable table:
    //   start	length	slot	name	signature
    //   0	548	0	this	xvxxxx
    //   7	475	1	localVxxxxx	mqmmmm.vxxxxx
    //   12	471	2	localVxvvvx	vxvvvx
    //   60	8	3	localMethod1	Method
    //   65	5	4	arrayOfObject1	Object[]
    //   508	3	5	localInvocationTargetException1	InvocationTargetException
    //   74	3	6	localObject1	Object
    //   90	11	7	i	int
    //   127	11	8	j	int
    //   275	9	9	localMethod2	Method
    //   281	6	10	arrayOfObject2	Object[]
    //   516	3	11	localInvocationTargetException2	InvocationTargetException
    //   291	3	12	localObject2	Object
    //   324	9	13	localMethod3	Method
    //   330	6	14	arrayOfObject3	Object[]
    //   524	3	15	localInvocationTargetException3	InvocationTargetException
    //   340	3	16	localObject3	Object
    //   356	11	17	k	int
    //   406	9	18	localMethod4	Method
    //   412	6	19	arrayOfObject4	Object[]
    //   532	3	20	localInvocationTargetException4	InvocationTargetException
    //   422	3	21	localObject4	Object
    //   452	9	22	localMethod5	Method
    //   458	6	23	arrayOfObject5	Object[]
    //   540	3	24	localInvocationTargetException5	InvocationTargetException
    //   468	3	25	localObject5	Object
    //   181	9	26	localMethod6	Method
    //   187	6	27	arrayOfObject6	Object[]
    //   492	3	28	localInvocationTargetException6	InvocationTargetException
    //   197	3	29	localObject6	Object
    //   228	9	30	localMethod7	Method
    //   234	6	31	arrayOfObject7	Object[]
    //   500	3	32	localInvocationTargetException7	InvocationTargetException
    //   244	3	33	localObject7	Object
    // Exception table:
    //   from	to	target	type
    //   189	199	492	java/lang/reflect/InvocationTargetException
    //   236	246	500	java/lang/reflect/InvocationTargetException
    //   67	76	508	java/lang/reflect/InvocationTargetException
    //   283	293	516	java/lang/reflect/InvocationTargetException
    //   332	342	524	java/lang/reflect/InvocationTargetException
    //   414	424	532	java/lang/reflect/InvocationTargetException
    //   460	470	540	java/lang/reflect/InvocationTargetException
  }
  
  /* Error */
  public void b0075u007500750075uu0075u0075(com.db.pwcc.dbmobile.multi_bank_aggregator.model.consents.ConsentsResponse paramConsentsResponse)
  {
    // Byte code:
    //   0: aload_1
    //   1: invokevirtual 269	com/db/pwcc/dbmobile/multi_bank_aggregator/model/consents/ConsentsResponse:getConsents	()Ljava/util/List;
    //   4: ifnull +15 -> 19
    //   7: aload_1
    //   8: invokevirtual 269	com/db/pwcc/dbmobile/multi_bank_aggregator/model/consents/ConsentsResponse:getConsents	()Ljava/util/List;
    //   11: invokeinterface 274 1 0
    //   16: ifeq +450 -> 466
    //   19: iconst_1
    //   20: istore_2
    //   21: iload_2
    //   22: ifeq +152 -> 174
    //   25: aload_0
    //   26: getfield 216	uuuuuu/xvxxxx:b006E006E006E006E006En006E006En	Luuuuuu/hyhyhh;
    //   29: invokevirtual 222	uuuuuu/hyhyhh:bp0070p007000700070p007000700070	()Luuuuuu/yhhyhh;
    //   32: invokevirtual 277	uuuuuu/yhhyhh:bp007000700070p0070p007000700070	()V
    //   35: getstatic 71	uuuuuu/xvxxxx:bvv007600760076007600760076v	I
    //   38: istore 24
    //   40: iload 24
    //   42: iload 24
    //   44: getstatic 69	uuuuuu/xvxxxx:bv0076v00760076007600760076v	I
    //   47: iadd
    //   48: imul
    //   49: getstatic 73	uuuuuu/xvxxxx:b00760076v00760076007600760076v	I
    //   52: irem
    //   53: tableswitch	default:+19->72, 0:+29->82
    //   72: bipush 90
    //   74: putstatic 71	uuuuuu/xvxxxx:bvv007600760076007600760076v	I
    //   77: bipush 86
    //   79: putstatic 75	uuuuuu/xvxxxx:b0076v007600760076007600760076v	I
    //   82: aload_0
    //   83: getfield 216	uuuuuu/xvxxxx:b006E006E006E006E006En006E006En	Luuuuuu/hyhyhh;
    //   86: invokevirtual 222	uuuuuu/hyhyhh:bp0070p007000700070p007000700070	()Luuuuuu/yhhyhh;
    //   89: iconst_1
    //   90: invokevirtual 280	uuuuuu/yhhyhh:bpppp00700070p007000700070	(Z)V
    //   93: aload_0
    //   94: invokevirtual 159	uuuuuu/xvxxxx:bkk006Bk006Bk006Bk006Bk	()Z
    //   97: ifeq +76 -> 173
    //   100: aload_0
    //   101: getfield 119	uuuuuu/xvxxxx:bnnnnn006E006E006En	Luuuuuu/ttssst$tsssst;
    //   104: checkcast 167	uuuuuu/mqmmmm$vxxxxx
    //   107: iconst_0
    //   108: invokeinterface 283 2 0
    //   113: aload_0
    //   114: getfield 119	uuuuuu/xvxxxx:bnnnnn006E006E006En	Luuuuuu/ttssst$tsssst;
    //   117: checkcast 167	uuuuuu/mqmmmm$vxxxxx
    //   120: astore 10
    //   122: iconst_0
    //   123: istore 11
    //   125: iload_2
    //   126: ifne +6 -> 132
    //   129: iconst_1
    //   130: istore 11
    //   132: getstatic 71	uuuuuu/xvxxxx:bvv007600760076007600760076v	I
    //   135: getstatic 69	uuuuuu/xvxxxx:bv0076v00760076007600760076v	I
    //   138: iadd
    //   139: getstatic 71	uuuuuu/xvxxxx:bvv007600760076007600760076v	I
    //   142: imul
    //   143: getstatic 73	uuuuuu/xvxxxx:b00760076v00760076007600760076v	I
    //   146: irem
    //   147: getstatic 75	uuuuuu/xvxxxx:b0076v007600760076007600760076v	I
    //   150: if_icmpeq +13 -> 163
    //   153: bipush 53
    //   155: putstatic 71	uuuuuu/xvxxxx:bvv007600760076007600760076v	I
    //   158: bipush 91
    //   160: putstatic 75	uuuuuu/xvxxxx:b0076v007600760076007600760076v	I
    //   163: aload 10
    //   165: iconst_1
    //   166: iload 11
    //   168: invokeinterface 287 3 0
    //   173: return
    //   174: aload_0
    //   175: getfield 216	uuuuuu/xvxxxx:b006E006E006E006E006En006E006En	Luuuuuu/hyhyhh;
    //   178: astore_3
    //   179: ldc 2
    //   181: ldc_w 289
    //   184: bipush 77
    //   186: iconst_1
    //   187: invokestatic 49	xxxxxx/uxxxxx:bb00620062bb0062b0062b0062	(Ljava/lang/String;CC)Ljava/lang/String;
    //   190: iconst_0
    //   191: anewarray 35	java/lang/Class
    //   194: invokevirtual 53	java/lang/Class:getMethod	(Ljava/lang/String;[Ljava/lang/Class;)Ljava/lang/reflect/Method;
    //   197: astore 4
    //   199: iconst_0
    //   200: anewarray 55	java/lang/Object
    //   203: astore 5
    //   205: aload 4
    //   207: aconst_null
    //   208: aload 5
    //   210: invokevirtual 61	java/lang/reflect/Method:invoke	(Ljava/lang/Object;[Ljava/lang/Object;)Ljava/lang/Object;
    //   213: astore 7
    //   215: aload 7
    //   217: checkcast 63	java/lang/Integer
    //   220: invokevirtual 67	java/lang/Integer:intValue	()I
    //   223: istore 8
    //   225: iload 8
    //   227: iload 8
    //   229: getstatic 69	uuuuuu/xvxxxx:bv0076v00760076007600760076v	I
    //   232: iadd
    //   233: imul
    //   234: getstatic 73	uuuuuu/xvxxxx:b00760076v00760076007600760076v	I
    //   237: irem
    //   238: tableswitch	default:+18->256, 0:+113->351
    //   256: ldc 2
    //   258: ldc_w 291
    //   261: sipush 197
    //   264: iconst_1
    //   265: invokestatic 49	xxxxxx/uxxxxx:bb00620062bb0062b0062b0062	(Ljava/lang/String;CC)Ljava/lang/String;
    //   268: iconst_0
    //   269: anewarray 35	java/lang/Class
    //   272: invokevirtual 53	java/lang/Class:getMethod	(Ljava/lang/String;[Ljava/lang/Class;)Ljava/lang/reflect/Method;
    //   275: astore 16
    //   277: iconst_0
    //   278: anewarray 55	java/lang/Object
    //   281: astore 17
    //   283: aload 16
    //   285: aconst_null
    //   286: aload 17
    //   288: invokevirtual 61	java/lang/reflect/Method:invoke	(Ljava/lang/Object;[Ljava/lang/Object;)Ljava/lang/Object;
    //   291: astore 19
    //   293: aload 19
    //   295: checkcast 63	java/lang/Integer
    //   298: invokevirtual 67	java/lang/Integer:intValue	()I
    //   301: putstatic 71	uuuuuu/xvxxxx:bvv007600760076007600760076v	I
    //   304: ldc 2
    //   306: ldc_w 293
    //   309: bipush 24
    //   311: iconst_2
    //   312: invokestatic 49	xxxxxx/uxxxxx:bb00620062bb0062b0062b0062	(Ljava/lang/String;CC)Ljava/lang/String;
    //   315: iconst_0
    //   316: anewarray 35	java/lang/Class
    //   319: invokevirtual 53	java/lang/Class:getMethod	(Ljava/lang/String;[Ljava/lang/Class;)Ljava/lang/reflect/Method;
    //   322: astore 20
    //   324: iconst_0
    //   325: anewarray 55	java/lang/Object
    //   328: astore 21
    //   330: aload 20
    //   332: aconst_null
    //   333: aload 21
    //   335: invokevirtual 61	java/lang/reflect/Method:invoke	(Ljava/lang/Object;[Ljava/lang/Object;)Ljava/lang/Object;
    //   338: astore 23
    //   340: aload 23
    //   342: checkcast 63	java/lang/Integer
    //   345: invokevirtual 67	java/lang/Integer:intValue	()I
    //   348: putstatic 75	uuuuuu/xvxxxx:b0076v007600760076007600760076v	I
    //   351: aload_3
    //   352: invokevirtual 222	uuuuuu/hyhyhh:bp0070p007000700070p007000700070	()Luuuuuu/yhhyhh;
    //   355: astore 9
    //   357: getstatic 71	uuuuuu/xvxxxx:bvv007600760076007600760076v	I
    //   360: getstatic 69	uuuuuu/xvxxxx:bv0076v00760076007600760076v	I
    //   363: iadd
    //   364: getstatic 71	uuuuuu/xvxxxx:bvv007600760076007600760076v	I
    //   367: imul
    //   368: getstatic 73	uuuuuu/xvxxxx:b00760076v00760076007600760076v	I
    //   371: irem
    //   372: getstatic 75	uuuuuu/xvxxxx:b0076v007600760076007600760076v	I
    //   375: if_icmpeq +59 -> 434
    //   378: ldc 2
    //   380: ldc_w 295
    //   383: sipush 224
    //   386: sipush 214
    //   389: iconst_1
    //   390: invokestatic 83	xxxxxx/uxxxxx:bbbb0062b0062b0062b0062	(Ljava/lang/String;CCC)Ljava/lang/String;
    //   393: iconst_0
    //   394: anewarray 35	java/lang/Class
    //   397: invokevirtual 53	java/lang/Class:getMethod	(Ljava/lang/String;[Ljava/lang/Class;)Ljava/lang/reflect/Method;
    //   400: astore 12
    //   402: iconst_0
    //   403: anewarray 55	java/lang/Object
    //   406: astore 13
    //   408: aload 12
    //   410: aconst_null
    //   411: aload 13
    //   413: invokevirtual 61	java/lang/reflect/Method:invoke	(Ljava/lang/Object;[Ljava/lang/Object;)Ljava/lang/Object;
    //   416: astore 15
    //   418: aload 15
    //   420: checkcast 63	java/lang/Integer
    //   423: invokevirtual 67	java/lang/Integer:intValue	()I
    //   426: putstatic 71	uuuuuu/xvxxxx:bvv007600760076007600760076v	I
    //   429: bipush 46
    //   431: putstatic 75	uuuuuu/xvxxxx:b0076v007600760076007600760076v	I
    //   434: aload 9
    //   436: aload_1
    //   437: invokevirtual 269	com/db/pwcc/dbmobile/multi_bank_aggregator/model/consents/ConsentsResponse:getConsents	()Ljava/util/List;
    //   440: iconst_0
    //   441: invokeinterface 299 2 0
    //   446: checkcast 301	com/db/pwcc/dbmobile/multi_bank_aggregator/model/consents/Consent
    //   449: invokevirtual 304	com/db/pwcc/dbmobile/multi_bank_aggregator/model/consents/Consent:getId	()I
    //   452: invokevirtual 308	uuuuuu/yhhyhh:b0070007000700070p0070p007000700070	(I)V
    //   455: goto -373 -> 82
    //   458: astore 6
    //   460: aload 6
    //   462: invokevirtual 89	java/lang/reflect/InvocationTargetException:getCause	()Ljava/lang/Throwable;
    //   465: athrow
    //   466: iconst_0
    //   467: istore_2
    //   468: goto -447 -> 21
    //   471: astore 14
    //   473: aload 14
    //   475: invokevirtual 89	java/lang/reflect/InvocationTargetException:getCause	()Ljava/lang/Throwable;
    //   478: athrow
    //   479: astore 18
    //   481: aload 18
    //   483: invokevirtual 89	java/lang/reflect/InvocationTargetException:getCause	()Ljava/lang/Throwable;
    //   486: athrow
    //   487: astore 22
    //   489: aload 22
    //   491: invokevirtual 89	java/lang/reflect/InvocationTargetException:getCause	()Ljava/lang/Throwable;
    //   494: athrow
    // Local variable table:
    //   start	length	slot	name	signature
    //   0	495	0	this	xvxxxx
    //   0	495	1	paramConsentsResponse	com.db.pwcc.dbmobile.multi_bank_aggregator.model.consents.ConsentsResponse
    //   20	448	2	i	int
    //   178	174	3	localHyhyhh	hyhyhh
    //   197	9	4	localMethod1	Method
    //   203	6	5	arrayOfObject1	Object[]
    //   458	3	6	localInvocationTargetException1	InvocationTargetException
    //   213	3	7	localObject1	Object
    //   223	11	8	j	int
    //   355	80	9	localYhhyhh	yhhyhh
    //   120	44	10	localVxxxxx	mqmmmm.vxxxxx
    //   123	44	11	bool	boolean
    //   400	9	12	localMethod2	Method
    //   406	6	13	arrayOfObject2	Object[]
    //   471	3	14	localInvocationTargetException2	InvocationTargetException
    //   416	3	15	localObject2	Object
    //   275	9	16	localMethod3	Method
    //   281	6	17	arrayOfObject3	Object[]
    //   479	3	18	localInvocationTargetException3	InvocationTargetException
    //   291	3	19	localObject3	Object
    //   322	9	20	localMethod4	Method
    //   328	6	21	arrayOfObject4	Object[]
    //   487	3	22	localInvocationTargetException4	InvocationTargetException
    //   338	3	23	localObject4	Object
    //   38	11	24	k	int
    // Exception table:
    //   from	to	target	type
    //   205	215	458	java/lang/reflect/InvocationTargetException
    //   408	418	471	java/lang/reflect/InvocationTargetException
    //   283	293	479	java/lang/reflect/InvocationTargetException
    //   330	340	487	java/lang/reflect/InvocationTargetException
  }
  
  /* Error */
  public boolean b0075u0075u00750075u0075u0075()
  {
    // Byte code:
    //   0: getstatic 71	uuuuuu/xvxxxx:bvv007600760076007600760076v	I
    //   3: getstatic 69	uuuuuu/xvxxxx:bv0076v00760076007600760076v	I
    //   6: iadd
    //   7: istore_1
    //   8: getstatic 71	uuuuuu/xvxxxx:bvv007600760076007600760076v	I
    //   11: istore_2
    //   12: getstatic 71	uuuuuu/xvxxxx:bvv007600760076007600760076v	I
    //   15: istore_3
    //   16: iload_3
    //   17: iload_3
    //   18: getstatic 69	uuuuuu/xvxxxx:bv0076v00760076007600760076v	I
    //   21: iadd
    //   22: imul
    //   23: getstatic 73	uuuuuu/xvxxxx:b00760076v00760076007600760076v	I
    //   26: irem
    //   27: tableswitch	default:+17->44, 0:+27->54
    //   44: bipush 65
    //   46: putstatic 71	uuuuuu/xvxxxx:bvv007600760076007600760076v	I
    //   49: bipush 53
    //   51: putstatic 75	uuuuuu/xvxxxx:b0076v007600760076007600760076v	I
    //   54: iload_1
    //   55: iload_2
    //   56: imul
    //   57: getstatic 73	uuuuuu/xvxxxx:b00760076v00760076007600760076v	I
    //   60: irem
    //   61: getstatic 75	uuuuuu/xvxxxx:b0076v007600760076007600760076v	I
    //   64: if_icmpeq +44 -> 108
    //   67: bipush 32
    //   69: putstatic 71	uuuuuu/xvxxxx:bvv007600760076007600760076v	I
    //   72: bipush 35
    //   74: putstatic 75	uuuuuu/xvxxxx:b0076v007600760076007600760076v	I
    //   77: getstatic 71	uuuuuu/xvxxxx:bvv007600760076007600760076v	I
    //   80: getstatic 69	uuuuuu/xvxxxx:bv0076v00760076007600760076v	I
    //   83: iadd
    //   84: getstatic 71	uuuuuu/xvxxxx:bvv007600760076007600760076v	I
    //   87: imul
    //   88: getstatic 73	uuuuuu/xvxxxx:b00760076v00760076007600760076v	I
    //   91: irem
    //   92: getstatic 75	uuuuuu/xvxxxx:b0076v007600760076007600760076v	I
    //   95: if_icmpeq +13 -> 108
    //   98: bipush 88
    //   100: putstatic 71	uuuuuu/xvxxxx:bvv007600760076007600760076v	I
    //   103: bipush 70
    //   105: putstatic 75	uuuuuu/xvxxxx:b0076v007600760076007600760076v	I
    //   108: ldc_w 311
    //   111: bipush 18
    //   113: iconst_2
    //   114: invokestatic 49	xxxxxx/uxxxxx:bb00620062bb0062b0062b0062	(Ljava/lang/String;CC)Ljava/lang/String;
    //   117: astore 4
    //   119: iconst_4
    //   120: anewarray 35	java/lang/Class
    //   123: astore 5
    //   125: aload 5
    //   127: iconst_0
    //   128: ldc -76
    //   130: aastore
    //   131: aload 5
    //   133: iconst_1
    //   134: getstatic 191	java/lang/Character:TYPE	Ljava/lang/Class;
    //   137: aastore
    //   138: aload 5
    //   140: iconst_2
    //   141: getstatic 191	java/lang/Character:TYPE	Ljava/lang/Class;
    //   144: aastore
    //   145: aload 5
    //   147: iconst_3
    //   148: getstatic 191	java/lang/Character:TYPE	Ljava/lang/Class;
    //   151: aastore
    //   152: ldc -63
    //   154: aload 4
    //   156: aload 5
    //   158: invokevirtual 53	java/lang/Class:getMethod	(Ljava/lang/String;[Ljava/lang/Class;)Ljava/lang/reflect/Method;
    //   161: astore 6
    //   163: iconst_4
    //   164: anewarray 55	java/lang/Object
    //   167: astore 7
    //   169: aload 7
    //   171: iconst_0
    //   172: ldc_w 313
    //   175: aastore
    //   176: aload 7
    //   178: iconst_1
    //   179: sipush 143
    //   182: invokestatic 199	java/lang/Character:valueOf	(C)Ljava/lang/Character;
    //   185: aastore
    //   186: aload 7
    //   188: iconst_2
    //   189: bipush 14
    //   191: invokestatic 199	java/lang/Character:valueOf	(C)Ljava/lang/Character;
    //   194: aastore
    //   195: aload 7
    //   197: iconst_3
    //   198: iconst_3
    //   199: invokestatic 199	java/lang/Character:valueOf	(C)Ljava/lang/Character;
    //   202: aastore
    //   203: aload 6
    //   205: aconst_null
    //   206: aload 7
    //   208: invokevirtual 61	java/lang/reflect/Method:invoke	(Ljava/lang/Object;[Ljava/lang/Object;)Ljava/lang/Object;
    //   211: astore 9
    //   213: aload 9
    //   215: checkcast 180	java/lang/String
    //   218: astore 10
    //   220: ldc_w 315
    //   223: ldc_w 317
    //   226: bipush 68
    //   228: sipush 245
    //   231: iconst_0
    //   232: invokestatic 83	xxxxxx/uxxxxx:bbbb0062b0062b0062b0062	(Ljava/lang/String;CCC)Ljava/lang/String;
    //   235: iconst_0
    //   236: anewarray 35	java/lang/Class
    //   239: invokevirtual 53	java/lang/Class:getMethod	(Ljava/lang/String;[Ljava/lang/Class;)Ljava/lang/reflect/Method;
    //   242: astore 11
    //   244: iconst_0
    //   245: anewarray 55	java/lang/Object
    //   248: astore 12
    //   250: aload 11
    //   252: aconst_null
    //   253: aload 12
    //   255: invokevirtual 61	java/lang/reflect/Method:invoke	(Ljava/lang/Object;[Ljava/lang/Object;)Ljava/lang/Object;
    //   258: astore 14
    //   260: aload 14
    //   262: checkcast 315	com/db/pwcc/dbmobile/secure/preferences/SharedPreferencesHelper
    //   265: astore 15
    //   267: getstatic 71	uuuuuu/xvxxxx:bvv007600760076007600760076v	I
    //   270: istore 16
    //   272: iload 16
    //   274: iload 16
    //   276: getstatic 69	uuuuuu/xvxxxx:bv0076v00760076007600760076v	I
    //   279: iadd
    //   280: imul
    //   281: getstatic 73	uuuuuu/xvxxxx:b00760076v00760076007600760076v	I
    //   284: irem
    //   285: tableswitch	default:+19->304, 0:+71->356
    //   304: ldc 2
    //   306: ldc -4
    //   308: sipush 224
    //   311: iconst_4
    //   312: invokestatic 49	xxxxxx/uxxxxx:bb00620062bb0062b0062b0062	(Ljava/lang/String;CC)Ljava/lang/String;
    //   315: iconst_0
    //   316: anewarray 35	java/lang/Class
    //   319: invokevirtual 53	java/lang/Class:getMethod	(Ljava/lang/String;[Ljava/lang/Class;)Ljava/lang/reflect/Method;
    //   322: astore 28
    //   324: iconst_0
    //   325: anewarray 55	java/lang/Object
    //   328: astore 29
    //   330: aload 28
    //   332: aconst_null
    //   333: aload 29
    //   335: invokevirtual 61	java/lang/reflect/Method:invoke	(Ljava/lang/Object;[Ljava/lang/Object;)Ljava/lang/Object;
    //   338: astore 31
    //   340: aload 31
    //   342: checkcast 63	java/lang/Integer
    //   345: invokevirtual 67	java/lang/Integer:intValue	()I
    //   348: putstatic 71	uuuuuu/xvxxxx:bvv007600760076007600760076v	I
    //   351: bipush 98
    //   353: putstatic 75	uuuuuu/xvxxxx:b0076v007600760076007600760076v	I
    //   356: ldc_w 319
    //   359: sipush 178
    //   362: sipush 226
    //   365: iconst_3
    //   366: invokestatic 83	xxxxxx/uxxxxx:bbbb0062b0062b0062b0062	(Ljava/lang/String;CCC)Ljava/lang/String;
    //   369: astore 17
    //   371: iconst_4
    //   372: anewarray 35	java/lang/Class
    //   375: astore 18
    //   377: aload 18
    //   379: iconst_0
    //   380: ldc -76
    //   382: aastore
    //   383: aload 18
    //   385: iconst_1
    //   386: getstatic 191	java/lang/Character:TYPE	Ljava/lang/Class;
    //   389: aastore
    //   390: aload 18
    //   392: iconst_2
    //   393: getstatic 191	java/lang/Character:TYPE	Ljava/lang/Class;
    //   396: aastore
    //   397: aload 18
    //   399: iconst_3
    //   400: getstatic 191	java/lang/Character:TYPE	Ljava/lang/Class;
    //   403: aastore
    //   404: ldc -63
    //   406: aload 17
    //   408: aload 18
    //   410: invokevirtual 53	java/lang/Class:getMethod	(Ljava/lang/String;[Ljava/lang/Class;)Ljava/lang/reflect/Method;
    //   413: astore 19
    //   415: iconst_4
    //   416: anewarray 55	java/lang/Object
    //   419: astore 20
    //   421: aload 20
    //   423: iconst_0
    //   424: ldc_w 321
    //   427: aastore
    //   428: aload 20
    //   430: iconst_1
    //   431: bipush 82
    //   433: invokestatic 199	java/lang/Character:valueOf	(C)Ljava/lang/Character;
    //   436: aastore
    //   437: aload 20
    //   439: iconst_2
    //   440: bipush 109
    //   442: invokestatic 199	java/lang/Character:valueOf	(C)Ljava/lang/Character;
    //   445: aastore
    //   446: aload 20
    //   448: iconst_3
    //   449: iconst_3
    //   450: invokestatic 199	java/lang/Character:valueOf	(C)Ljava/lang/Character;
    //   453: aastore
    //   454: aload 19
    //   456: aconst_null
    //   457: aload 20
    //   459: invokevirtual 61	java/lang/reflect/Method:invoke	(Ljava/lang/Object;[Ljava/lang/Object;)Ljava/lang/Object;
    //   462: astore 22
    //   464: aload 22
    //   466: checkcast 180	java/lang/String
    //   469: astore 23
    //   471: ldc_w 315
    //   474: ldc_w 323
    //   477: sipush 249
    //   480: iconst_3
    //   481: invokestatic 49	xxxxxx/uxxxxx:bb00620062bb0062b0062b0062	(Ljava/lang/String;CC)Ljava/lang/String;
    //   484: iconst_1
    //   485: anewarray 35	java/lang/Class
    //   488: dup
    //   489: iconst_0
    //   490: ldc -76
    //   492: aastore
    //   493: invokevirtual 53	java/lang/Class:getMethod	(Ljava/lang/String;[Ljava/lang/Class;)Ljava/lang/reflect/Method;
    //   496: astore 24
    //   498: iconst_1
    //   499: anewarray 55	java/lang/Object
    //   502: dup
    //   503: iconst_0
    //   504: aload 23
    //   506: aastore
    //   507: astore 25
    //   509: aload 24
    //   511: aload 15
    //   513: aload 25
    //   515: invokevirtual 61	java/lang/reflect/Method:invoke	(Ljava/lang/Object;[Ljava/lang/Object;)Ljava/lang/Object;
    //   518: astore 27
    //   520: aload 10
    //   522: aload 27
    //   524: checkcast 180	java/lang/String
    //   527: invokevirtual 327	java/lang/String:equals	(Ljava/lang/Object;)Z
    //   530: ireturn
    //   531: astore 21
    //   533: aload 21
    //   535: invokevirtual 89	java/lang/reflect/InvocationTargetException:getCause	()Ljava/lang/Throwable;
    //   538: athrow
    //   539: astore 26
    //   541: aload 26
    //   543: invokevirtual 89	java/lang/reflect/InvocationTargetException:getCause	()Ljava/lang/Throwable;
    //   546: athrow
    //   547: astore 30
    //   549: aload 30
    //   551: invokevirtual 89	java/lang/reflect/InvocationTargetException:getCause	()Ljava/lang/Throwable;
    //   554: athrow
    //   555: astore 8
    //   557: aload 8
    //   559: invokevirtual 89	java/lang/reflect/InvocationTargetException:getCause	()Ljava/lang/Throwable;
    //   562: athrow
    //   563: astore 13
    //   565: aload 13
    //   567: invokevirtual 89	java/lang/reflect/InvocationTargetException:getCause	()Ljava/lang/Throwable;
    //   570: athrow
    // Local variable table:
    //   start	length	slot	name	signature
    //   0	571	0	this	xvxxxx
    //   7	50	1	i	int
    //   11	46	2	j	int
    //   15	8	3	k	int
    //   117	38	4	str1	String
    //   123	34	5	arrayOfClass1	Class[]
    //   161	43	6	localMethod1	Method
    //   167	40	7	arrayOfObject1	Object[]
    //   555	3	8	localInvocationTargetException1	InvocationTargetException
    //   211	3	9	localObject1	Object
    //   218	303	10	str2	String
    //   242	9	11	localMethod2	Method
    //   248	6	12	arrayOfObject2	Object[]
    //   563	3	13	localInvocationTargetException2	InvocationTargetException
    //   258	3	14	localObject2	Object
    //   265	247	15	localSharedPreferencesHelper	com.db.pwcc.dbmobile.secure.preferences.SharedPreferencesHelper
    //   270	11	16	m	int
    //   369	38	17	str3	String
    //   375	34	18	arrayOfClass2	Class[]
    //   413	42	19	localMethod3	Method
    //   419	39	20	arrayOfObject3	Object[]
    //   531	3	21	localInvocationTargetException3	InvocationTargetException
    //   462	3	22	localObject3	Object
    //   469	36	23	str4	String
    //   496	14	24	localMethod4	Method
    //   507	7	25	arrayOfObject4	Object[]
    //   539	3	26	localInvocationTargetException4	InvocationTargetException
    //   518	5	27	localObject4	Object
    //   322	9	28	localMethod5	Method
    //   328	6	29	arrayOfObject5	Object[]
    //   547	3	30	localInvocationTargetException5	InvocationTargetException
    //   338	3	31	localObject5	Object
    // Exception table:
    //   from	to	target	type
    //   454	464	531	java/lang/reflect/InvocationTargetException
    //   509	520	539	java/lang/reflect/InvocationTargetException
    //   330	340	547	java/lang/reflect/InvocationTargetException
    //   203	213	555	java/lang/reflect/InvocationTargetException
    //   250	260	563	java/lang/reflect/InvocationTargetException
  }
  
  /* Error */
  public void b0075u0075uu0075u0075u0075()
  {
    // Byte code:
    //   0: aload_0
    //   1: getfield 119	uuuuuu/xvxxxx:bnnnnn006E006E006En	Luuuuuu/ttssst$tsssst;
    //   4: checkcast 167	uuuuuu/mqmmmm$vxxxxx
    //   7: getstatic 333	com/db/pwcc/dbmobile/multi_bank_aggregator/R$string:deactivate_function	I
    //   10: invokeinterface 336 2 0
    //   15: getstatic 71	uuuuuu/xvxxxx:bvv007600760076007600760076v	I
    //   18: getstatic 69	uuuuuu/xvxxxx:bv0076v00760076007600760076v	I
    //   21: iadd
    //   22: getstatic 71	uuuuuu/xvxxxx:bvv007600760076007600760076v	I
    //   25: imul
    //   26: getstatic 73	uuuuuu/xvxxxx:b00760076v00760076007600760076v	I
    //   29: irem
    //   30: getstatic 75	uuuuuu/xvxxxx:b0076v007600760076007600760076v	I
    //   33: if_icmpeq +455 -> 488
    //   36: getstatic 71	uuuuuu/xvxxxx:bvv007600760076007600760076v	I
    //   39: istore 10
    //   41: iload 10
    //   43: getstatic 69	uuuuuu/xvxxxx:bv0076v00760076007600760076v	I
    //   46: iadd
    //   47: istore 11
    //   49: ldc 2
    //   51: ldc_w 338
    //   54: sipush 216
    //   57: sipush 185
    //   60: iconst_3
    //   61: invokestatic 83	xxxxxx/uxxxxx:bbbb0062b0062b0062b0062	(Ljava/lang/String;CCC)Ljava/lang/String;
    //   64: iconst_0
    //   65: anewarray 35	java/lang/Class
    //   68: invokevirtual 53	java/lang/Class:getMethod	(Ljava/lang/String;[Ljava/lang/Class;)Ljava/lang/reflect/Method;
    //   71: astore 12
    //   73: iconst_0
    //   74: anewarray 55	java/lang/Object
    //   77: astore 13
    //   79: aload 12
    //   81: aconst_null
    //   82: aload 13
    //   84: invokevirtual 61	java/lang/reflect/Method:invoke	(Ljava/lang/Object;[Ljava/lang/Object;)Ljava/lang/Object;
    //   87: astore 15
    //   89: aload 15
    //   91: checkcast 63	java/lang/Integer
    //   94: invokevirtual 67	java/lang/Integer:intValue	()I
    //   97: istore 16
    //   99: ldc 2
    //   101: ldc_w 340
    //   104: bipush 30
    //   106: bipush 84
    //   108: iconst_0
    //   109: invokestatic 83	xxxxxx/uxxxxx:bbbb0062b0062b0062b0062	(Ljava/lang/String;CCC)Ljava/lang/String;
    //   112: iconst_0
    //   113: anewarray 35	java/lang/Class
    //   116: invokevirtual 53	java/lang/Class:getMethod	(Ljava/lang/String;[Ljava/lang/Class;)Ljava/lang/reflect/Method;
    //   119: astore 17
    //   121: iconst_0
    //   122: anewarray 55	java/lang/Object
    //   125: astore 18
    //   127: aload 17
    //   129: aconst_null
    //   130: aload 18
    //   132: invokevirtual 61	java/lang/reflect/Method:invoke	(Ljava/lang/Object;[Ljava/lang/Object;)Ljava/lang/Object;
    //   135: astore 20
    //   137: iload 16
    //   139: aload 20
    //   141: checkcast 63	java/lang/Integer
    //   144: invokevirtual 67	java/lang/Integer:intValue	()I
    //   147: iadd
    //   148: istore 21
    //   150: ldc 2
    //   152: ldc -104
    //   154: bipush 32
    //   156: bipush 13
    //   158: iconst_1
    //   159: invokestatic 83	xxxxxx/uxxxxx:bbbb0062b0062b0062b0062	(Ljava/lang/String;CCC)Ljava/lang/String;
    //   162: iconst_0
    //   163: anewarray 35	java/lang/Class
    //   166: invokevirtual 53	java/lang/Class:getMethod	(Ljava/lang/String;[Ljava/lang/Class;)Ljava/lang/reflect/Method;
    //   169: astore 22
    //   171: iconst_0
    //   172: anewarray 55	java/lang/Object
    //   175: astore 23
    //   177: aload 22
    //   179: aconst_null
    //   180: aload 23
    //   182: invokevirtual 61	java/lang/reflect/Method:invoke	(Ljava/lang/Object;[Ljava/lang/Object;)Ljava/lang/Object;
    //   185: astore 25
    //   187: iload 21
    //   189: aload 25
    //   191: checkcast 63	java/lang/Integer
    //   194: invokevirtual 67	java/lang/Integer:intValue	()I
    //   197: imul
    //   198: getstatic 73	uuuuuu/xvxxxx:b00760076v00760076007600760076v	I
    //   201: irem
    //   202: istore 26
    //   204: ldc 2
    //   206: ldc_w 342
    //   209: bipush 89
    //   211: iconst_5
    //   212: invokestatic 49	xxxxxx/uxxxxx:bb00620062bb0062b0062b0062	(Ljava/lang/String;CC)Ljava/lang/String;
    //   215: iconst_0
    //   216: anewarray 35	java/lang/Class
    //   219: invokevirtual 53	java/lang/Class:getMethod	(Ljava/lang/String;[Ljava/lang/Class;)Ljava/lang/reflect/Method;
    //   222: astore 27
    //   224: iconst_0
    //   225: anewarray 55	java/lang/Object
    //   228: astore 28
    //   230: aload 27
    //   232: aconst_null
    //   233: aload 28
    //   235: invokevirtual 61	java/lang/reflect/Method:invoke	(Ljava/lang/Object;[Ljava/lang/Object;)Ljava/lang/Object;
    //   238: astore 30
    //   240: iload 26
    //   242: aload 30
    //   244: checkcast 63	java/lang/Integer
    //   247: invokevirtual 67	java/lang/Integer:intValue	()I
    //   250: if_icmpeq +57 -> 307
    //   253: ldc 2
    //   255: ldc_w 344
    //   258: sipush 212
    //   261: bipush 122
    //   263: iconst_0
    //   264: invokestatic 83	xxxxxx/uxxxxx:bbbb0062b0062b0062b0062	(Ljava/lang/String;CCC)Ljava/lang/String;
    //   267: iconst_0
    //   268: anewarray 35	java/lang/Class
    //   271: invokevirtual 53	java/lang/Class:getMethod	(Ljava/lang/String;[Ljava/lang/Class;)Ljava/lang/reflect/Method;
    //   274: astore 44
    //   276: iconst_0
    //   277: anewarray 55	java/lang/Object
    //   280: astore 45
    //   282: aload 44
    //   284: aconst_null
    //   285: aload 45
    //   287: invokevirtual 61	java/lang/reflect/Method:invoke	(Ljava/lang/Object;[Ljava/lang/Object;)Ljava/lang/Object;
    //   290: astore 47
    //   292: aload 47
    //   294: checkcast 63	java/lang/Integer
    //   297: invokevirtual 67	java/lang/Integer:intValue	()I
    //   300: putstatic 71	uuuuuu/xvxxxx:bvv007600760076007600760076v	I
    //   303: iconst_1
    //   304: putstatic 75	uuuuuu/xvxxxx:b0076v007600760076007600760076v	I
    //   307: iload 10
    //   309: iload 11
    //   311: imul
    //   312: istore 31
    //   314: ldc 2
    //   316: ldc_w 346
    //   319: sipush 237
    //   322: iconst_1
    //   323: invokestatic 49	xxxxxx/uxxxxx:bb00620062bb0062b0062b0062	(Ljava/lang/String;CC)Ljava/lang/String;
    //   326: iconst_0
    //   327: anewarray 35	java/lang/Class
    //   330: invokevirtual 53	java/lang/Class:getMethod	(Ljava/lang/String;[Ljava/lang/Class;)Ljava/lang/reflect/Method;
    //   333: astore 32
    //   335: iconst_0
    //   336: anewarray 55	java/lang/Object
    //   339: astore 33
    //   341: aload 32
    //   343: aconst_null
    //   344: aload 33
    //   346: invokevirtual 61	java/lang/reflect/Method:invoke	(Ljava/lang/Object;[Ljava/lang/Object;)Ljava/lang/Object;
    //   349: astore 35
    //   351: iload 31
    //   353: aload 35
    //   355: checkcast 63	java/lang/Integer
    //   358: invokevirtual 67	java/lang/Integer:intValue	()I
    //   361: irem
    //   362: tableswitch	default:+18->380, 0:+116->478
    //   380: ldc 2
    //   382: ldc_w 348
    //   385: bipush 62
    //   387: iconst_2
    //   388: invokestatic 49	xxxxxx/uxxxxx:bb00620062bb0062b0062b0062	(Ljava/lang/String;CC)Ljava/lang/String;
    //   391: iconst_0
    //   392: anewarray 35	java/lang/Class
    //   395: invokevirtual 53	java/lang/Class:getMethod	(Ljava/lang/String;[Ljava/lang/Class;)Ljava/lang/reflect/Method;
    //   398: astore 36
    //   400: iconst_0
    //   401: anewarray 55	java/lang/Object
    //   404: astore 37
    //   406: aload 36
    //   408: aconst_null
    //   409: aload 37
    //   411: invokevirtual 61	java/lang/reflect/Method:invoke	(Ljava/lang/Object;[Ljava/lang/Object;)Ljava/lang/Object;
    //   414: astore 39
    //   416: aload 39
    //   418: checkcast 63	java/lang/Integer
    //   421: invokevirtual 67	java/lang/Integer:intValue	()I
    //   424: putstatic 71	uuuuuu/xvxxxx:bvv007600760076007600760076v	I
    //   427: ldc 2
    //   429: ldc_w 350
    //   432: sipush 140
    //   435: sipush 186
    //   438: iconst_2
    //   439: invokestatic 83	xxxxxx/uxxxxx:bbbb0062b0062b0062b0062	(Ljava/lang/String;CCC)Ljava/lang/String;
    //   442: iconst_0
    //   443: anewarray 35	java/lang/Class
    //   446: invokevirtual 53	java/lang/Class:getMethod	(Ljava/lang/String;[Ljava/lang/Class;)Ljava/lang/reflect/Method;
    //   449: astore 40
    //   451: iconst_0
    //   452: anewarray 55	java/lang/Object
    //   455: astore 41
    //   457: aload 40
    //   459: aconst_null
    //   460: aload 41
    //   462: invokevirtual 61	java/lang/reflect/Method:invoke	(Ljava/lang/Object;[Ljava/lang/Object;)Ljava/lang/Object;
    //   465: astore 43
    //   467: aload 43
    //   469: checkcast 63	java/lang/Integer
    //   472: invokevirtual 67	java/lang/Integer:intValue	()I
    //   475: putstatic 75	uuuuuu/xvxxxx:b0076v007600760076007600760076v	I
    //   478: bipush 63
    //   480: putstatic 71	uuuuuu/xvxxxx:bvv007600760076007600760076v	I
    //   483: bipush 98
    //   485: putstatic 75	uuuuuu/xvxxxx:b0076v007600760076007600760076v	I
    //   488: getstatic 71	uuuuuu/xvxxxx:bvv007600760076007600760076v	I
    //   491: getstatic 69	uuuuuu/xvxxxx:bv0076v00760076007600760076v	I
    //   494: iadd
    //   495: getstatic 71	uuuuuu/xvxxxx:bvv007600760076007600760076v	I
    //   498: imul
    //   499: istore_1
    //   500: ldc 2
    //   502: ldc_w 352
    //   505: sipush 157
    //   508: iconst_2
    //   509: invokestatic 49	xxxxxx/uxxxxx:bb00620062bb0062b0062b0062	(Ljava/lang/String;CC)Ljava/lang/String;
    //   512: iconst_0
    //   513: anewarray 35	java/lang/Class
    //   516: invokevirtual 53	java/lang/Class:getMethod	(Ljava/lang/String;[Ljava/lang/Class;)Ljava/lang/reflect/Method;
    //   519: astore_2
    //   520: iconst_0
    //   521: anewarray 55	java/lang/Object
    //   524: astore_3
    //   525: aload_2
    //   526: aconst_null
    //   527: aload_3
    //   528: invokevirtual 61	java/lang/reflect/Method:invoke	(Ljava/lang/Object;[Ljava/lang/Object;)Ljava/lang/Object;
    //   531: astore 5
    //   533: iload_1
    //   534: aload 5
    //   536: checkcast 63	java/lang/Integer
    //   539: invokevirtual 67	java/lang/Integer:intValue	()I
    //   542: irem
    //   543: getstatic 75	uuuuuu/xvxxxx:b0076v007600760076007600760076v	I
    //   546: if_icmpeq +56 -> 602
    //   549: bipush 95
    //   551: putstatic 71	uuuuuu/xvxxxx:bvv007600760076007600760076v	I
    //   554: ldc 2
    //   556: ldc_w 354
    //   559: sipush 253
    //   562: iconst_1
    //   563: invokestatic 49	xxxxxx/uxxxxx:bb00620062bb0062b0062b0062	(Ljava/lang/String;CC)Ljava/lang/String;
    //   566: iconst_0
    //   567: anewarray 35	java/lang/Class
    //   570: invokevirtual 53	java/lang/Class:getMethod	(Ljava/lang/String;[Ljava/lang/Class;)Ljava/lang/reflect/Method;
    //   573: astore 6
    //   575: iconst_0
    //   576: anewarray 55	java/lang/Object
    //   579: astore 7
    //   581: aload 6
    //   583: aconst_null
    //   584: aload 7
    //   586: invokevirtual 61	java/lang/reflect/Method:invoke	(Ljava/lang/Object;[Ljava/lang/Object;)Ljava/lang/Object;
    //   589: astore 9
    //   591: aload 9
    //   593: checkcast 63	java/lang/Integer
    //   596: invokevirtual 67	java/lang/Integer:intValue	()I
    //   599: putstatic 75	uuuuuu/xvxxxx:b0076v007600760076007600760076v	I
    //   602: aload_0
    //   603: getfield 240	uuuuuu/xvxxxx:bvvv00760076007600760076v	Luuuuuu/vxvvvx;
    //   606: invokevirtual 357	uuuuuu/vxvvvx:bkk006B006B006B006Bk006Bkk	()V
    //   609: return
    //   610: astore 4
    //   612: aload 4
    //   614: invokevirtual 89	java/lang/reflect/InvocationTargetException:getCause	()Ljava/lang/Throwable;
    //   617: athrow
    //   618: astore 8
    //   620: aload 8
    //   622: invokevirtual 89	java/lang/reflect/InvocationTargetException:getCause	()Ljava/lang/Throwable;
    //   625: athrow
    //   626: astore 34
    //   628: aload 34
    //   630: invokevirtual 89	java/lang/reflect/InvocationTargetException:getCause	()Ljava/lang/Throwable;
    //   633: athrow
    //   634: astore 14
    //   636: aload 14
    //   638: invokevirtual 89	java/lang/reflect/InvocationTargetException:getCause	()Ljava/lang/Throwable;
    //   641: athrow
    //   642: astore 19
    //   644: aload 19
    //   646: invokevirtual 89	java/lang/reflect/InvocationTargetException:getCause	()Ljava/lang/Throwable;
    //   649: athrow
    //   650: astore 24
    //   652: aload 24
    //   654: invokevirtual 89	java/lang/reflect/InvocationTargetException:getCause	()Ljava/lang/Throwable;
    //   657: athrow
    //   658: astore 29
    //   660: aload 29
    //   662: invokevirtual 89	java/lang/reflect/InvocationTargetException:getCause	()Ljava/lang/Throwable;
    //   665: athrow
    //   666: astore 38
    //   668: aload 38
    //   670: invokevirtual 89	java/lang/reflect/InvocationTargetException:getCause	()Ljava/lang/Throwable;
    //   673: athrow
    //   674: astore 42
    //   676: aload 42
    //   678: invokevirtual 89	java/lang/reflect/InvocationTargetException:getCause	()Ljava/lang/Throwable;
    //   681: athrow
    //   682: astore 46
    //   684: aload 46
    //   686: invokevirtual 89	java/lang/reflect/InvocationTargetException:getCause	()Ljava/lang/Throwable;
    //   689: athrow
    // Local variable table:
    //   start	length	slot	name	signature
    //   0	690	0	this	xvxxxx
    //   499	44	1	i	int
    //   519	7	2	localMethod1	Method
    //   524	4	3	arrayOfObject1	Object[]
    //   610	3	4	localInvocationTargetException1	InvocationTargetException
    //   531	4	5	localObject1	Object
    //   573	9	6	localMethod2	Method
    //   579	6	7	arrayOfObject2	Object[]
    //   618	3	8	localInvocationTargetException2	InvocationTargetException
    //   589	3	9	localObject2	Object
    //   39	273	10	j	int
    //   47	265	11	k	int
    //   71	9	12	localMethod3	Method
    //   77	6	13	arrayOfObject3	Object[]
    //   634	3	14	localInvocationTargetException3	InvocationTargetException
    //   87	3	15	localObject3	Object
    //   97	51	16	m	int
    //   119	9	17	localMethod4	Method
    //   125	6	18	arrayOfObject4	Object[]
    //   642	3	19	localInvocationTargetException4	InvocationTargetException
    //   135	5	20	localObject4	Object
    //   148	50	21	n	int
    //   169	9	22	localMethod5	Method
    //   175	6	23	arrayOfObject5	Object[]
    //   650	3	24	localInvocationTargetException5	InvocationTargetException
    //   185	5	25	localObject5	Object
    //   202	49	26	i1	int
    //   222	9	27	localMethod6	Method
    //   228	6	28	arrayOfObject6	Object[]
    //   658	3	29	localInvocationTargetException6	InvocationTargetException
    //   238	5	30	localObject6	Object
    //   312	50	31	i2	int
    //   333	9	32	localMethod7	Method
    //   339	6	33	arrayOfObject7	Object[]
    //   626	3	34	localInvocationTargetException7	InvocationTargetException
    //   349	5	35	localObject7	Object
    //   398	9	36	localMethod8	Method
    //   404	6	37	arrayOfObject8	Object[]
    //   666	3	38	localInvocationTargetException8	InvocationTargetException
    //   414	3	39	localObject8	Object
    //   449	9	40	localMethod9	Method
    //   455	6	41	arrayOfObject9	Object[]
    //   674	3	42	localInvocationTargetException9	InvocationTargetException
    //   465	3	43	localObject9	Object
    //   274	9	44	localMethod10	Method
    //   280	6	45	arrayOfObject10	Object[]
    //   682	3	46	localInvocationTargetException10	InvocationTargetException
    //   290	3	47	localObject10	Object
    // Exception table:
    //   from	to	target	type
    //   525	533	610	java/lang/reflect/InvocationTargetException
    //   581	591	618	java/lang/reflect/InvocationTargetException
    //   341	351	626	java/lang/reflect/InvocationTargetException
    //   79	89	634	java/lang/reflect/InvocationTargetException
    //   127	137	642	java/lang/reflect/InvocationTargetException
    //   177	187	650	java/lang/reflect/InvocationTargetException
    //   230	240	658	java/lang/reflect/InvocationTargetException
    //   406	416	666	java/lang/reflect/InvocationTargetException
    //   457	467	674	java/lang/reflect/InvocationTargetException
    //   282	292	682	java/lang/reflect/InvocationTargetException
  }
  
  /* Error */
  public void b0075uu007500750075u0075u0075()
  {
    // Byte code:
    //   0: getstatic 71	uuuuuu/xvxxxx:bvv007600760076007600760076v	I
    //   3: getstatic 69	uuuuuu/xvxxxx:bv0076v00760076007600760076v	I
    //   6: iadd
    //   7: getstatic 71	uuuuuu/xvxxxx:bvv007600760076007600760076v	I
    //   10: imul
    //   11: getstatic 73	uuuuuu/xvxxxx:b00760076v00760076007600760076v	I
    //   14: irem
    //   15: getstatic 75	uuuuuu/xvxxxx:b0076v007600760076007600760076v	I
    //   18: if_icmpeq +268 -> 286
    //   21: getstatic 71	uuuuuu/xvxxxx:bvv007600760076007600760076v	I
    //   24: istore 11
    //   26: getstatic 71	uuuuuu/xvxxxx:bvv007600760076007600760076v	I
    //   29: getstatic 69	uuuuuu/xvxxxx:bv0076v00760076007600760076v	I
    //   32: iadd
    //   33: getstatic 71	uuuuuu/xvxxxx:bvv007600760076007600760076v	I
    //   36: imul
    //   37: getstatic 73	uuuuuu/xvxxxx:b00760076v00760076007600760076v	I
    //   40: irem
    //   41: getstatic 75	uuuuuu/xvxxxx:b0076v007600760076007600760076v	I
    //   44: if_icmpeq +101 -> 145
    //   47: ldc 2
    //   49: ldc_w 360
    //   52: sipush 134
    //   55: bipush 110
    //   57: iconst_1
    //   58: invokestatic 83	xxxxxx/uxxxxx:bbbb0062b0062b0062b0062	(Ljava/lang/String;CCC)Ljava/lang/String;
    //   61: iconst_0
    //   62: anewarray 35	java/lang/Class
    //   65: invokevirtual 53	java/lang/Class:getMethod	(Ljava/lang/String;[Ljava/lang/Class;)Ljava/lang/reflect/Method;
    //   68: astore 21
    //   70: iconst_0
    //   71: anewarray 55	java/lang/Object
    //   74: astore 22
    //   76: aload 21
    //   78: aconst_null
    //   79: aload 22
    //   81: invokevirtual 61	java/lang/reflect/Method:invoke	(Ljava/lang/Object;[Ljava/lang/Object;)Ljava/lang/Object;
    //   84: astore 24
    //   86: aload 24
    //   88: checkcast 63	java/lang/Integer
    //   91: invokevirtual 67	java/lang/Integer:intValue	()I
    //   94: putstatic 71	uuuuuu/xvxxxx:bvv007600760076007600760076v	I
    //   97: ldc 2
    //   99: ldc_w 362
    //   102: sipush 207
    //   105: iconst_5
    //   106: invokestatic 49	xxxxxx/uxxxxx:bb00620062bb0062b0062b0062	(Ljava/lang/String;CC)Ljava/lang/String;
    //   109: iconst_0
    //   110: anewarray 35	java/lang/Class
    //   113: invokevirtual 53	java/lang/Class:getMethod	(Ljava/lang/String;[Ljava/lang/Class;)Ljava/lang/reflect/Method;
    //   116: astore 25
    //   118: iconst_0
    //   119: anewarray 55	java/lang/Object
    //   122: astore 26
    //   124: aload 25
    //   126: aconst_null
    //   127: aload 26
    //   129: invokevirtual 61	java/lang/reflect/Method:invoke	(Ljava/lang/Object;[Ljava/lang/Object;)Ljava/lang/Object;
    //   132: astore 28
    //   134: aload 28
    //   136: checkcast 63	java/lang/Integer
    //   139: invokevirtual 67	java/lang/Integer:intValue	()I
    //   142: putstatic 75	uuuuuu/xvxxxx:b0076v007600760076007600760076v	I
    //   145: iload 11
    //   147: iload 11
    //   149: getstatic 69	uuuuuu/xvxxxx:bv0076v00760076007600760076v	I
    //   152: iadd
    //   153: imul
    //   154: istore 12
    //   156: ldc 2
    //   158: ldc_w 364
    //   161: bipush 13
    //   163: bipush 70
    //   165: iconst_0
    //   166: invokestatic 83	xxxxxx/uxxxxx:bbbb0062b0062b0062b0062	(Ljava/lang/String;CCC)Ljava/lang/String;
    //   169: iconst_0
    //   170: anewarray 35	java/lang/Class
    //   173: invokevirtual 53	java/lang/Class:getMethod	(Ljava/lang/String;[Ljava/lang/Class;)Ljava/lang/reflect/Method;
    //   176: astore 13
    //   178: iconst_0
    //   179: anewarray 55	java/lang/Object
    //   182: astore 14
    //   184: aload 13
    //   186: aconst_null
    //   187: aload 14
    //   189: invokevirtual 61	java/lang/reflect/Method:invoke	(Ljava/lang/Object;[Ljava/lang/Object;)Ljava/lang/Object;
    //   192: astore 16
    //   194: iload 12
    //   196: aload 16
    //   198: checkcast 63	java/lang/Integer
    //   201: invokevirtual 67	java/lang/Integer:intValue	()I
    //   204: irem
    //   205: tableswitch	default:+19->224, 0:+71->276
    //   224: bipush 78
    //   226: putstatic 71	uuuuuu/xvxxxx:bvv007600760076007600760076v	I
    //   229: ldc 2
    //   231: ldc 121
    //   233: sipush 219
    //   236: iconst_3
    //   237: invokestatic 49	xxxxxx/uxxxxx:bb00620062bb0062b0062b0062	(Ljava/lang/String;CC)Ljava/lang/String;
    //   240: iconst_0
    //   241: anewarray 35	java/lang/Class
    //   244: invokevirtual 53	java/lang/Class:getMethod	(Ljava/lang/String;[Ljava/lang/Class;)Ljava/lang/reflect/Method;
    //   247: astore 17
    //   249: iconst_0
    //   250: anewarray 55	java/lang/Object
    //   253: astore 18
    //   255: aload 17
    //   257: aconst_null
    //   258: aload 18
    //   260: invokevirtual 61	java/lang/reflect/Method:invoke	(Ljava/lang/Object;[Ljava/lang/Object;)Ljava/lang/Object;
    //   263: astore 20
    //   265: aload 20
    //   267: checkcast 63	java/lang/Integer
    //   270: invokevirtual 67	java/lang/Integer:intValue	()I
    //   273: putstatic 75	uuuuuu/xvxxxx:b0076v007600760076007600760076v	I
    //   276: bipush 65
    //   278: putstatic 71	uuuuuu/xvxxxx:bvv007600760076007600760076v	I
    //   281: bipush 27
    //   283: putstatic 75	uuuuuu/xvxxxx:b0076v007600760076007600760076v	I
    //   286: aload_0
    //   287: getfield 366	uuuuuu/xvxxxx:b0076vv00760076007600760076v	Lcom/db/pwcc/dbmobile/foundation/data/manager/broadcasting/ModelUpdatedBroadcastReceiver;
    //   290: ifnull +140 -> 430
    //   293: aload_0
    //   294: getfield 119	uuuuuu/xvxxxx:bnnnnn006E006E006En	Luuuuuu/ttssst$tsssst;
    //   297: checkcast 167	uuuuuu/mqmmmm$vxxxxx
    //   300: astore_1
    //   301: getstatic 71	uuuuuu/xvxxxx:bvv007600760076007600760076v	I
    //   304: istore_2
    //   305: ldc 2
    //   307: ldc_w 368
    //   310: sipush 222
    //   313: iconst_2
    //   314: invokestatic 49	xxxxxx/uxxxxx:bb00620062bb0062b0062b0062	(Ljava/lang/String;CC)Ljava/lang/String;
    //   317: iconst_0
    //   318: anewarray 35	java/lang/Class
    //   321: invokevirtual 53	java/lang/Class:getMethod	(Ljava/lang/String;[Ljava/lang/Class;)Ljava/lang/reflect/Method;
    //   324: astore_3
    //   325: iconst_0
    //   326: anewarray 55	java/lang/Object
    //   329: astore 4
    //   331: aload_3
    //   332: aconst_null
    //   333: aload 4
    //   335: invokevirtual 61	java/lang/reflect/Method:invoke	(Ljava/lang/Object;[Ljava/lang/Object;)Ljava/lang/Object;
    //   338: astore 6
    //   340: iload_2
    //   341: aload 6
    //   343: checkcast 63	java/lang/Integer
    //   346: invokevirtual 67	java/lang/Integer:intValue	()I
    //   349: iadd
    //   350: getstatic 71	uuuuuu/xvxxxx:bvv007600760076007600760076v	I
    //   353: imul
    //   354: getstatic 73	uuuuuu/xvxxxx:b00760076v00760076007600760076v	I
    //   357: irem
    //   358: getstatic 75	uuuuuu/xvxxxx:b0076v007600760076007600760076v	I
    //   361: if_icmpeq +54 -> 415
    //   364: ldc 2
    //   366: ldc_w 293
    //   369: bipush 8
    //   371: iconst_0
    //   372: invokestatic 49	xxxxxx/uxxxxx:bb00620062bb0062b0062b0062	(Ljava/lang/String;CC)Ljava/lang/String;
    //   375: iconst_0
    //   376: anewarray 35	java/lang/Class
    //   379: invokevirtual 53	java/lang/Class:getMethod	(Ljava/lang/String;[Ljava/lang/Class;)Ljava/lang/reflect/Method;
    //   382: astore 7
    //   384: iconst_0
    //   385: anewarray 55	java/lang/Object
    //   388: astore 8
    //   390: aload 7
    //   392: aconst_null
    //   393: aload 8
    //   395: invokevirtual 61	java/lang/reflect/Method:invoke	(Ljava/lang/Object;[Ljava/lang/Object;)Ljava/lang/Object;
    //   398: astore 10
    //   400: aload 10
    //   402: checkcast 63	java/lang/Integer
    //   405: invokevirtual 67	java/lang/Integer:intValue	()I
    //   408: putstatic 71	uuuuuu/xvxxxx:bvv007600760076007600760076v	I
    //   411: iconst_4
    //   412: putstatic 75	uuuuuu/xvxxxx:b0076v007600760076007600760076v	I
    //   415: aload_1
    //   416: aload_0
    //   417: getfield 366	uuuuuu/xvxxxx:b0076vv00760076007600760076v	Lcom/db/pwcc/dbmobile/foundation/data/manager/broadcasting/ModelUpdatedBroadcastReceiver;
    //   420: invokeinterface 372 2 0
    //   425: aload_0
    //   426: aconst_null
    //   427: putfield 366	uuuuuu/xvxxxx:b0076vv00760076007600760076v	Lcom/db/pwcc/dbmobile/foundation/data/manager/broadcasting/ModelUpdatedBroadcastReceiver;
    //   430: return
    //   431: astore 15
    //   433: aload 15
    //   435: invokevirtual 89	java/lang/reflect/InvocationTargetException:getCause	()Ljava/lang/Throwable;
    //   438: athrow
    //   439: astore 5
    //   441: aload 5
    //   443: invokevirtual 89	java/lang/reflect/InvocationTargetException:getCause	()Ljava/lang/Throwable;
    //   446: athrow
    //   447: astore 9
    //   449: aload 9
    //   451: invokevirtual 89	java/lang/reflect/InvocationTargetException:getCause	()Ljava/lang/Throwable;
    //   454: athrow
    //   455: astore 19
    //   457: aload 19
    //   459: invokevirtual 89	java/lang/reflect/InvocationTargetException:getCause	()Ljava/lang/Throwable;
    //   462: athrow
    //   463: astore 23
    //   465: aload 23
    //   467: invokevirtual 89	java/lang/reflect/InvocationTargetException:getCause	()Ljava/lang/Throwable;
    //   470: athrow
    //   471: astore 27
    //   473: aload 27
    //   475: invokevirtual 89	java/lang/reflect/InvocationTargetException:getCause	()Ljava/lang/Throwable;
    //   478: athrow
    // Local variable table:
    //   start	length	slot	name	signature
    //   0	479	0	this	xvxxxx
    //   300	116	1	localVxxxxx	mqmmmm.vxxxxx
    //   304	46	2	i	int
    //   324	8	3	localMethod1	Method
    //   329	5	4	arrayOfObject1	Object[]
    //   439	3	5	localInvocationTargetException1	InvocationTargetException
    //   338	4	6	localObject1	Object
    //   382	9	7	localMethod2	Method
    //   388	6	8	arrayOfObject2	Object[]
    //   447	3	9	localInvocationTargetException2	InvocationTargetException
    //   398	3	10	localObject2	Object
    //   24	130	11	j	int
    //   154	51	12	k	int
    //   176	9	13	localMethod3	Method
    //   182	6	14	arrayOfObject3	Object[]
    //   431	3	15	localInvocationTargetException3	InvocationTargetException
    //   192	5	16	localObject3	Object
    //   247	9	17	localMethod4	Method
    //   253	6	18	arrayOfObject4	Object[]
    //   455	3	19	localInvocationTargetException4	InvocationTargetException
    //   263	3	20	localObject4	Object
    //   68	9	21	localMethod5	Method
    //   74	6	22	arrayOfObject5	Object[]
    //   463	3	23	localInvocationTargetException5	InvocationTargetException
    //   84	3	24	localObject5	Object
    //   116	9	25	localMethod6	Method
    //   122	6	26	arrayOfObject6	Object[]
    //   471	3	27	localInvocationTargetException6	InvocationTargetException
    //   132	3	28	localObject6	Object
    // Exception table:
    //   from	to	target	type
    //   184	194	431	java/lang/reflect/InvocationTargetException
    //   331	340	439	java/lang/reflect/InvocationTargetException
    //   390	400	447	java/lang/reflect/InvocationTargetException
    //   255	265	455	java/lang/reflect/InvocationTargetException
    //   76	86	463	java/lang/reflect/InvocationTargetException
    //   124	134	471	java/lang/reflect/InvocationTargetException
  }
  
  /* Error */
  public void b0075uu0075u0075u0075u0075()
  {
    // Byte code:
    //   0: getstatic 71	uuuuuu/xvxxxx:bvv007600760076007600760076v	I
    //   3: getstatic 69	uuuuuu/xvxxxx:bv0076v00760076007600760076v	I
    //   6: iadd
    //   7: getstatic 71	uuuuuu/xvxxxx:bvv007600760076007600760076v	I
    //   10: imul
    //   11: getstatic 73	uuuuuu/xvxxxx:b00760076v00760076007600760076v	I
    //   14: irem
    //   15: getstatic 75	uuuuuu/xvxxxx:b0076v007600760076007600760076v	I
    //   18: if_icmpeq +44 -> 62
    //   21: getstatic 71	uuuuuu/xvxxxx:bvv007600760076007600760076v	I
    //   24: getstatic 69	uuuuuu/xvxxxx:bv0076v00760076007600760076v	I
    //   27: iadd
    //   28: getstatic 71	uuuuuu/xvxxxx:bvv007600760076007600760076v	I
    //   31: imul
    //   32: getstatic 73	uuuuuu/xvxxxx:b00760076v00760076007600760076v	I
    //   35: irem
    //   36: getstatic 75	uuuuuu/xvxxxx:b0076v007600760076007600760076v	I
    //   39: if_icmpeq +13 -> 52
    //   42: bipush 15
    //   44: putstatic 71	uuuuuu/xvxxxx:bvv007600760076007600760076v	I
    //   47: bipush 22
    //   49: putstatic 75	uuuuuu/xvxxxx:b0076v007600760076007600760076v	I
    //   52: bipush 89
    //   54: putstatic 71	uuuuuu/xvxxxx:bvv007600760076007600760076v	I
    //   57: bipush 92
    //   59: putstatic 75	uuuuuu/xvxxxx:b0076v007600760076007600760076v	I
    //   62: aload_0
    //   63: getfield 240	uuuuuu/xvxxxx:bvvv00760076007600760076v	Luuuuuu/vxvvvx;
    //   66: astore_1
    //   67: getstatic 71	uuuuuu/xvxxxx:bvv007600760076007600760076v	I
    //   70: istore_2
    //   71: iload_2
    //   72: iload_2
    //   73: getstatic 69	uuuuuu/xvxxxx:bv0076v00760076007600760076v	I
    //   76: iadd
    //   77: imul
    //   78: getstatic 73	uuuuuu/xvxxxx:b00760076v00760076007600760076v	I
    //   81: irem
    //   82: tableswitch	default:+18->100, 0:+28->110
    //   100: bipush 24
    //   102: putstatic 71	uuuuuu/xvxxxx:bvv007600760076007600760076v	I
    //   105: bipush 37
    //   107: putstatic 75	uuuuuu/xvxxxx:b0076v007600760076007600760076v	I
    //   110: aload_1
    //   111: invokevirtual 376	uuuuuu/vxvvvx:bu00750075u007500750075u00750075	()Z
    //   114: ifeq +23 -> 137
    //   117: aload_0
    //   118: getfield 119	uuuuuu/xvxxxx:bnnnnn006E006E006En	Luuuuuu/ttssst$tsssst;
    //   121: checkcast 167	uuuuuu/mqmmmm$vxxxxx
    //   124: aload_0
    //   125: getfield 240	uuuuuu/xvxxxx:bvvv00760076007600760076v	Luuuuuu/vxvvvx;
    //   128: invokevirtual 258	uuuuuu/vxvvvx:bu007500750075u00750075u00750075	()Ljava/util/List;
    //   131: invokeinterface 262 2 0
    //   136: return
    //   137: ldc 2
    //   139: ldc_w 378
    //   142: sipush 243
    //   145: iconst_3
    //   146: invokestatic 49	xxxxxx/uxxxxx:bb00620062bb0062b0062b0062	(Ljava/lang/String;CC)Ljava/lang/String;
    //   149: iconst_0
    //   150: anewarray 35	java/lang/Class
    //   153: invokevirtual 53	java/lang/Class:getMethod	(Ljava/lang/String;[Ljava/lang/Class;)Ljava/lang/reflect/Method;
    //   156: astore_3
    //   157: iconst_0
    //   158: anewarray 55	java/lang/Object
    //   161: astore 4
    //   163: aload_3
    //   164: aload_0
    //   165: aload 4
    //   167: invokevirtual 61	java/lang/reflect/Method:invoke	(Ljava/lang/Object;[Ljava/lang/Object;)Ljava/lang/Object;
    //   170: pop
    //   171: aload_0
    //   172: getfield 240	uuuuuu/xvxxxx:bvvv00760076007600760076v	Luuuuuu/vxvvvx;
    //   175: invokevirtual 381	uuuuuu/vxvvvx:bkkkkkk006B006Bkk	()V
    //   178: getstatic 71	uuuuuu/xvxxxx:bvv007600760076007600760076v	I
    //   181: istore 7
    //   183: iload 7
    //   185: iload 7
    //   187: getstatic 69	uuuuuu/xvxxxx:bv0076v00760076007600760076v	I
    //   190: iadd
    //   191: imul
    //   192: istore 8
    //   194: ldc 2
    //   196: ldc_w 383
    //   199: sipush 159
    //   202: iconst_2
    //   203: invokestatic 49	xxxxxx/uxxxxx:bb00620062bb0062b0062b0062	(Ljava/lang/String;CC)Ljava/lang/String;
    //   206: iconst_0
    //   207: anewarray 35	java/lang/Class
    //   210: invokevirtual 53	java/lang/Class:getMethod	(Ljava/lang/String;[Ljava/lang/Class;)Ljava/lang/reflect/Method;
    //   213: astore 9
    //   215: iconst_0
    //   216: anewarray 55	java/lang/Object
    //   219: astore 10
    //   221: aload 9
    //   223: aconst_null
    //   224: aload 10
    //   226: invokevirtual 61	java/lang/reflect/Method:invoke	(Ljava/lang/Object;[Ljava/lang/Object;)Ljava/lang/Object;
    //   229: astore 12
    //   231: iload 8
    //   233: aload 12
    //   235: checkcast 63	java/lang/Integer
    //   238: invokevirtual 67	java/lang/Integer:intValue	()I
    //   241: irem
    //   242: tableswitch	default:+18->260, 0:+-106->136
    //   260: ldc 2
    //   262: ldc_w 385
    //   265: sipush 172
    //   268: sipush 143
    //   271: iconst_0
    //   272: invokestatic 83	xxxxxx/uxxxxx:bbbb0062b0062b0062b0062	(Ljava/lang/String;CCC)Ljava/lang/String;
    //   275: iconst_0
    //   276: anewarray 35	java/lang/Class
    //   279: invokevirtual 53	java/lang/Class:getMethod	(Ljava/lang/String;[Ljava/lang/Class;)Ljava/lang/reflect/Method;
    //   282: astore 13
    //   284: iconst_0
    //   285: anewarray 55	java/lang/Object
    //   288: astore 14
    //   290: aload 13
    //   292: aconst_null
    //   293: aload 14
    //   295: invokevirtual 61	java/lang/reflect/Method:invoke	(Ljava/lang/Object;[Ljava/lang/Object;)Ljava/lang/Object;
    //   298: astore 16
    //   300: aload 16
    //   302: checkcast 63	java/lang/Integer
    //   305: invokevirtual 67	java/lang/Integer:intValue	()I
    //   308: putstatic 71	uuuuuu/xvxxxx:bvv007600760076007600760076v	I
    //   311: bipush 39
    //   313: putstatic 75	uuuuuu/xvxxxx:b0076v007600760076007600760076v	I
    //   316: return
    //   317: astore 11
    //   319: aload 11
    //   321: invokevirtual 89	java/lang/reflect/InvocationTargetException:getCause	()Ljava/lang/Throwable;
    //   324: athrow
    //   325: astore 15
    //   327: aload 15
    //   329: invokevirtual 89	java/lang/reflect/InvocationTargetException:getCause	()Ljava/lang/Throwable;
    //   332: athrow
    //   333: astore 5
    //   335: aload 5
    //   337: invokevirtual 89	java/lang/reflect/InvocationTargetException:getCause	()Ljava/lang/Throwable;
    //   340: athrow
    // Local variable table:
    //   start	length	slot	name	signature
    //   0	341	0	this	xvxxxx
    //   66	45	1	localVxvvvx	vxvvvx
    //   70	8	2	i	int
    //   156	8	3	localMethod1	Method
    //   161	5	4	arrayOfObject1	Object[]
    //   333	3	5	localInvocationTargetException1	InvocationTargetException
    //   181	11	7	j	int
    //   192	50	8	k	int
    //   213	9	9	localMethod2	Method
    //   219	6	10	arrayOfObject2	Object[]
    //   317	3	11	localInvocationTargetException2	InvocationTargetException
    //   229	5	12	localObject1	Object
    //   282	9	13	localMethod3	Method
    //   288	6	14	arrayOfObject3	Object[]
    //   325	3	15	localInvocationTargetException3	InvocationTargetException
    //   298	3	16	localObject2	Object
    // Exception table:
    //   from	to	target	type
    //   221	231	317	java/lang/reflect/InvocationTargetException
    //   290	300	325	java/lang/reflect/InvocationTargetException
    //   163	171	333	java/lang/reflect/InvocationTargetException
  }
  
  /* Error */
  public void b0075uuu00750075u0075u0075(mqmmmm.vxxxxx paramVxxxxx)
  {
    // Byte code:
    //   0: aload_0
    //   1: aload_1
    //   2: invokespecial 391	uuuuuu/ssssst:ba0061a0061a0061a0061aa	(Luuuuuu/ttssst$tsssst;)V
    //   5: getstatic 71	uuuuuu/xvxxxx:bvv007600760076007600760076v	I
    //   8: getstatic 69	uuuuuu/xvxxxx:bv0076v00760076007600760076v	I
    //   11: iadd
    //   12: getstatic 71	uuuuuu/xvxxxx:bvv007600760076007600760076v	I
    //   15: imul
    //   16: getstatic 73	uuuuuu/xvxxxx:b00760076v00760076007600760076v	I
    //   19: irem
    //   20: istore_2
    //   21: ldc 2
    //   23: ldc_w 393
    //   26: bipush 15
    //   28: iconst_5
    //   29: invokestatic 49	xxxxxx/uxxxxx:bb00620062bb0062b0062b0062	(Ljava/lang/String;CC)Ljava/lang/String;
    //   32: iconst_0
    //   33: anewarray 35	java/lang/Class
    //   36: invokevirtual 53	java/lang/Class:getMethod	(Ljava/lang/String;[Ljava/lang/Class;)Ljava/lang/reflect/Method;
    //   39: astore_3
    //   40: iconst_0
    //   41: anewarray 55	java/lang/Object
    //   44: astore 4
    //   46: aload_3
    //   47: aconst_null
    //   48: aload 4
    //   50: invokevirtual 61	java/lang/reflect/Method:invoke	(Ljava/lang/Object;[Ljava/lang/Object;)Ljava/lang/Object;
    //   53: astore 6
    //   55: iload_2
    //   56: aload 6
    //   58: checkcast 63	java/lang/Integer
    //   61: invokevirtual 67	java/lang/Integer:intValue	()I
    //   64: if_icmpeq +267 -> 331
    //   67: getstatic 71	uuuuuu/xvxxxx:bvv007600760076007600760076v	I
    //   70: getstatic 69	uuuuuu/xvxxxx:bv0076v00760076007600760076v	I
    //   73: iadd
    //   74: getstatic 71	uuuuuu/xvxxxx:bvv007600760076007600760076v	I
    //   77: imul
    //   78: getstatic 73	uuuuuu/xvxxxx:b00760076v00760076007600760076v	I
    //   81: irem
    //   82: istore 19
    //   84: ldc 2
    //   86: ldc_w 395
    //   89: bipush 121
    //   91: iconst_2
    //   92: invokestatic 49	xxxxxx/uxxxxx:bb00620062bb0062b0062b0062	(Ljava/lang/String;CC)Ljava/lang/String;
    //   95: iconst_0
    //   96: anewarray 35	java/lang/Class
    //   99: invokevirtual 53	java/lang/Class:getMethod	(Ljava/lang/String;[Ljava/lang/Class;)Ljava/lang/reflect/Method;
    //   102: astore 20
    //   104: iconst_0
    //   105: anewarray 55	java/lang/Object
    //   108: astore 21
    //   110: aload 20
    //   112: aconst_null
    //   113: aload 21
    //   115: invokevirtual 61	java/lang/reflect/Method:invoke	(Ljava/lang/Object;[Ljava/lang/Object;)Ljava/lang/Object;
    //   118: astore 23
    //   120: iload 19
    //   122: aload 23
    //   124: checkcast 63	java/lang/Integer
    //   127: invokevirtual 67	java/lang/Integer:intValue	()I
    //   130: if_icmpeq +191 -> 321
    //   133: bipush 64
    //   135: putstatic 71	uuuuuu/xvxxxx:bvv007600760076007600760076v	I
    //   138: ldc 2
    //   140: ldc 121
    //   142: sipush 138
    //   145: bipush 46
    //   147: iconst_1
    //   148: invokestatic 83	xxxxxx/uxxxxx:bbbb0062b0062b0062b0062	(Ljava/lang/String;CCC)Ljava/lang/String;
    //   151: iconst_0
    //   152: anewarray 35	java/lang/Class
    //   155: invokevirtual 53	java/lang/Class:getMethod	(Ljava/lang/String;[Ljava/lang/Class;)Ljava/lang/reflect/Method;
    //   158: astore 24
    //   160: iconst_0
    //   161: anewarray 55	java/lang/Object
    //   164: astore 25
    //   166: aload 24
    //   168: aconst_null
    //   169: aload 25
    //   171: invokevirtual 61	java/lang/reflect/Method:invoke	(Ljava/lang/Object;[Ljava/lang/Object;)Ljava/lang/Object;
    //   174: astore 27
    //   176: aload 27
    //   178: checkcast 63	java/lang/Integer
    //   181: invokevirtual 67	java/lang/Integer:intValue	()I
    //   184: putstatic 75	uuuuuu/xvxxxx:b0076v007600760076007600760076v	I
    //   187: getstatic 71	uuuuuu/xvxxxx:bvv007600760076007600760076v	I
    //   190: istore 28
    //   192: iload 28
    //   194: iload 28
    //   196: getstatic 69	uuuuuu/xvxxxx:bv0076v00760076007600760076v	I
    //   199: iadd
    //   200: imul
    //   201: getstatic 73	uuuuuu/xvxxxx:b00760076v00760076007600760076v	I
    //   204: irem
    //   205: tableswitch	default:+19->224, 0:+116->321
    //   224: ldc 2
    //   226: ldc_w 397
    //   229: bipush 53
    //   231: iconst_4
    //   232: invokestatic 49	xxxxxx/uxxxxx:bb00620062bb0062b0062b0062	(Ljava/lang/String;CC)Ljava/lang/String;
    //   235: iconst_0
    //   236: anewarray 35	java/lang/Class
    //   239: invokevirtual 53	java/lang/Class:getMethod	(Ljava/lang/String;[Ljava/lang/Class;)Ljava/lang/reflect/Method;
    //   242: astore 29
    //   244: iconst_0
    //   245: anewarray 55	java/lang/Object
    //   248: astore 30
    //   250: aload 29
    //   252: aconst_null
    //   253: aload 30
    //   255: invokevirtual 61	java/lang/reflect/Method:invoke	(Ljava/lang/Object;[Ljava/lang/Object;)Ljava/lang/Object;
    //   258: astore 32
    //   260: aload 32
    //   262: checkcast 63	java/lang/Integer
    //   265: invokevirtual 67	java/lang/Integer:intValue	()I
    //   268: putstatic 71	uuuuuu/xvxxxx:bvv007600760076007600760076v	I
    //   271: ldc 2
    //   273: ldc_w 291
    //   276: bipush 108
    //   278: sipush 222
    //   281: iconst_2
    //   282: invokestatic 83	xxxxxx/uxxxxx:bbbb0062b0062b0062b0062	(Ljava/lang/String;CCC)Ljava/lang/String;
    //   285: iconst_0
    //   286: anewarray 35	java/lang/Class
    //   289: invokevirtual 53	java/lang/Class:getMethod	(Ljava/lang/String;[Ljava/lang/Class;)Ljava/lang/reflect/Method;
    //   292: astore 33
    //   294: iconst_0
    //   295: anewarray 55	java/lang/Object
    //   298: astore 34
    //   300: aload 33
    //   302: aconst_null
    //   303: aload 34
    //   305: invokevirtual 61	java/lang/reflect/Method:invoke	(Ljava/lang/Object;[Ljava/lang/Object;)Ljava/lang/Object;
    //   308: astore 36
    //   310: aload 36
    //   312: checkcast 63	java/lang/Integer
    //   315: invokevirtual 67	java/lang/Integer:intValue	()I
    //   318: putstatic 75	uuuuuu/xvxxxx:b0076v007600760076007600760076v	I
    //   321: bipush 9
    //   323: putstatic 71	uuuuuu/xvxxxx:bvv007600760076007600760076v	I
    //   326: bipush 58
    //   328: putstatic 75	uuuuuu/xvxxxx:b0076v007600760076007600760076v	I
    //   331: ldc 2
    //   333: ldc_w 399
    //   336: sipush 199
    //   339: iconst_4
    //   340: invokestatic 49	xxxxxx/uxxxxx:bb00620062bb0062b0062b0062	(Ljava/lang/String;CC)Ljava/lang/String;
    //   343: iconst_0
    //   344: anewarray 35	java/lang/Class
    //   347: invokevirtual 53	java/lang/Class:getMethod	(Ljava/lang/String;[Ljava/lang/Class;)Ljava/lang/reflect/Method;
    //   350: astore 7
    //   352: iconst_0
    //   353: anewarray 55	java/lang/Object
    //   356: astore 8
    //   358: aload 7
    //   360: aload_0
    //   361: aload 8
    //   363: invokevirtual 61	java/lang/reflect/Method:invoke	(Ljava/lang/Object;[Ljava/lang/Object;)Ljava/lang/Object;
    //   366: pop
    //   367: getstatic 71	uuuuuu/xvxxxx:bvv007600760076007600760076v	I
    //   370: getstatic 69	uuuuuu/xvxxxx:bv0076v00760076007600760076v	I
    //   373: iadd
    //   374: getstatic 71	uuuuuu/xvxxxx:bvv007600760076007600760076v	I
    //   377: imul
    //   378: getstatic 73	uuuuuu/xvxxxx:b00760076v00760076007600760076v	I
    //   381: irem
    //   382: getstatic 75	uuuuuu/xvxxxx:b0076v007600760076007600760076v	I
    //   385: if_icmpeq +95 -> 480
    //   388: ldc 2
    //   390: ldc_w 401
    //   393: iconst_3
    //   394: iconst_5
    //   395: invokestatic 49	xxxxxx/uxxxxx:bb00620062bb0062b0062b0062	(Ljava/lang/String;CC)Ljava/lang/String;
    //   398: iconst_0
    //   399: anewarray 35	java/lang/Class
    //   402: invokevirtual 53	java/lang/Class:getMethod	(Ljava/lang/String;[Ljava/lang/Class;)Ljava/lang/reflect/Method;
    //   405: astore 11
    //   407: iconst_0
    //   408: anewarray 55	java/lang/Object
    //   411: astore 12
    //   413: aload 11
    //   415: aconst_null
    //   416: aload 12
    //   418: invokevirtual 61	java/lang/reflect/Method:invoke	(Ljava/lang/Object;[Ljava/lang/Object;)Ljava/lang/Object;
    //   421: astore 14
    //   423: aload 14
    //   425: checkcast 63	java/lang/Integer
    //   428: invokevirtual 67	java/lang/Integer:intValue	()I
    //   431: putstatic 71	uuuuuu/xvxxxx:bvv007600760076007600760076v	I
    //   434: ldc 2
    //   436: ldc 43
    //   438: bipush 36
    //   440: iconst_4
    //   441: invokestatic 49	xxxxxx/uxxxxx:bb00620062bb0062b0062b0062	(Ljava/lang/String;CC)Ljava/lang/String;
    //   444: iconst_0
    //   445: anewarray 35	java/lang/Class
    //   448: invokevirtual 53	java/lang/Class:getMethod	(Ljava/lang/String;[Ljava/lang/Class;)Ljava/lang/reflect/Method;
    //   451: astore 15
    //   453: iconst_0
    //   454: anewarray 55	java/lang/Object
    //   457: astore 16
    //   459: aload 15
    //   461: aconst_null
    //   462: aload 16
    //   464: invokevirtual 61	java/lang/reflect/Method:invoke	(Ljava/lang/Object;[Ljava/lang/Object;)Ljava/lang/Object;
    //   467: astore 18
    //   469: aload 18
    //   471: checkcast 63	java/lang/Integer
    //   474: invokevirtual 67	java/lang/Integer:intValue	()I
    //   477: putstatic 75	uuuuuu/xvxxxx:b0076v007600760076007600760076v	I
    //   480: return
    //   481: astore 5
    //   483: aload 5
    //   485: invokevirtual 89	java/lang/reflect/InvocationTargetException:getCause	()Ljava/lang/Throwable;
    //   488: athrow
    //   489: astore 22
    //   491: aload 22
    //   493: invokevirtual 89	java/lang/reflect/InvocationTargetException:getCause	()Ljava/lang/Throwable;
    //   496: athrow
    //   497: astore 9
    //   499: aload 9
    //   501: invokevirtual 89	java/lang/reflect/InvocationTargetException:getCause	()Ljava/lang/Throwable;
    //   504: athrow
    //   505: astore 26
    //   507: aload 26
    //   509: invokevirtual 89	java/lang/reflect/InvocationTargetException:getCause	()Ljava/lang/Throwable;
    //   512: athrow
    //   513: astore 31
    //   515: aload 31
    //   517: invokevirtual 89	java/lang/reflect/InvocationTargetException:getCause	()Ljava/lang/Throwable;
    //   520: athrow
    //   521: astore 35
    //   523: aload 35
    //   525: invokevirtual 89	java/lang/reflect/InvocationTargetException:getCause	()Ljava/lang/Throwable;
    //   528: athrow
    //   529: astore 13
    //   531: aload 13
    //   533: invokevirtual 89	java/lang/reflect/InvocationTargetException:getCause	()Ljava/lang/Throwable;
    //   536: athrow
    //   537: astore 17
    //   539: aload 17
    //   541: invokevirtual 89	java/lang/reflect/InvocationTargetException:getCause	()Ljava/lang/Throwable;
    //   544: athrow
    // Local variable table:
    //   start	length	slot	name	signature
    //   0	545	0	this	xvxxxx
    //   0	545	1	paramVxxxxx	mqmmmm.vxxxxx
    //   20	45	2	i	int
    //   39	8	3	localMethod1	Method
    //   44	5	4	arrayOfObject1	Object[]
    //   481	3	5	localInvocationTargetException1	InvocationTargetException
    //   53	4	6	localObject1	Object
    //   350	9	7	localMethod2	Method
    //   356	6	8	arrayOfObject2	Object[]
    //   497	3	9	localInvocationTargetException2	InvocationTargetException
    //   405	9	11	localMethod3	Method
    //   411	6	12	arrayOfObject3	Object[]
    //   529	3	13	localInvocationTargetException3	InvocationTargetException
    //   421	3	14	localObject2	Object
    //   451	9	15	localMethod4	Method
    //   457	6	16	arrayOfObject4	Object[]
    //   537	3	17	localInvocationTargetException4	InvocationTargetException
    //   467	3	18	localObject3	Object
    //   82	49	19	j	int
    //   102	9	20	localMethod5	Method
    //   108	6	21	arrayOfObject5	Object[]
    //   489	3	22	localInvocationTargetException5	InvocationTargetException
    //   118	5	23	localObject4	Object
    //   158	9	24	localMethod6	Method
    //   164	6	25	arrayOfObject6	Object[]
    //   505	3	26	localInvocationTargetException6	InvocationTargetException
    //   174	3	27	localObject5	Object
    //   190	11	28	k	int
    //   242	9	29	localMethod7	Method
    //   248	6	30	arrayOfObject7	Object[]
    //   513	3	31	localInvocationTargetException7	InvocationTargetException
    //   258	3	32	localObject6	Object
    //   292	9	33	localMethod8	Method
    //   298	6	34	arrayOfObject8	Object[]
    //   521	3	35	localInvocationTargetException8	InvocationTargetException
    //   308	3	36	localObject7	Object
    // Exception table:
    //   from	to	target	type
    //   46	55	481	java/lang/reflect/InvocationTargetException
    //   110	120	489	java/lang/reflect/InvocationTargetException
    //   358	367	497	java/lang/reflect/InvocationTargetException
    //   166	176	505	java/lang/reflect/InvocationTargetException
    //   250	260	513	java/lang/reflect/InvocationTargetException
    //   300	310	521	java/lang/reflect/InvocationTargetException
    //   413	423	529	java/lang/reflect/InvocationTargetException
    //   459	469	537	java/lang/reflect/InvocationTargetException
  }
  
  /* Error */
  public void ba006100610061a0061aa0061a()
  {
    // Byte code:
    //   0: getstatic 71	uuuuuu/xvxxxx:bvv007600760076007600760076v	I
    //   3: getstatic 69	uuuuuu/xvxxxx:bv0076v00760076007600760076v	I
    //   6: iadd
    //   7: getstatic 71	uuuuuu/xvxxxx:bvv007600760076007600760076v	I
    //   10: imul
    //   11: getstatic 73	uuuuuu/xvxxxx:b00760076v00760076007600760076v	I
    //   14: irem
    //   15: getstatic 75	uuuuuu/xvxxxx:b0076v007600760076007600760076v	I
    //   18: if_icmpeq +55 -> 73
    //   21: bipush 99
    //   23: putstatic 71	uuuuuu/xvxxxx:bvv007600760076007600760076v	I
    //   26: ldc 2
    //   28: ldc_w 404
    //   31: bipush 38
    //   33: iconst_3
    //   34: invokestatic 49	xxxxxx/uxxxxx:bb00620062bb0062b0062b0062	(Ljava/lang/String;CC)Ljava/lang/String;
    //   37: iconst_0
    //   38: anewarray 35	java/lang/Class
    //   41: invokevirtual 53	java/lang/Class:getMethod	(Ljava/lang/String;[Ljava/lang/Class;)Ljava/lang/reflect/Method;
    //   44: astore 24
    //   46: iconst_0
    //   47: anewarray 55	java/lang/Object
    //   50: astore 25
    //   52: aload 24
    //   54: aconst_null
    //   55: aload 25
    //   57: invokevirtual 61	java/lang/reflect/Method:invoke	(Ljava/lang/Object;[Ljava/lang/Object;)Ljava/lang/Object;
    //   60: astore 27
    //   62: aload 27
    //   64: checkcast 63	java/lang/Integer
    //   67: invokevirtual 67	java/lang/Integer:intValue	()I
    //   70: putstatic 75	uuuuuu/xvxxxx:b0076v007600760076007600760076v	I
    //   73: getstatic 71	uuuuuu/xvxxxx:bvv007600760076007600760076v	I
    //   76: getstatic 69	uuuuuu/xvxxxx:bv0076v00760076007600760076v	I
    //   79: iadd
    //   80: getstatic 71	uuuuuu/xvxxxx:bvv007600760076007600760076v	I
    //   83: imul
    //   84: getstatic 73	uuuuuu/xvxxxx:b00760076v00760076007600760076v	I
    //   87: irem
    //   88: istore_1
    //   89: getstatic 71	uuuuuu/xvxxxx:bvv007600760076007600760076v	I
    //   92: getstatic 69	uuuuuu/xvxxxx:bv0076v00760076007600760076v	I
    //   95: iadd
    //   96: getstatic 71	uuuuuu/xvxxxx:bvv007600760076007600760076v	I
    //   99: imul
    //   100: getstatic 73	uuuuuu/xvxxxx:b00760076v00760076007600760076v	I
    //   103: irem
    //   104: getstatic 75	uuuuuu/xvxxxx:b0076v007600760076007600760076v	I
    //   107: if_icmpeq +98 -> 205
    //   110: ldc 2
    //   112: ldc_w 406
    //   115: bipush 86
    //   117: iconst_2
    //   118: invokestatic 49	xxxxxx/uxxxxx:bb00620062bb0062b0062b0062	(Ljava/lang/String;CC)Ljava/lang/String;
    //   121: iconst_0
    //   122: anewarray 35	java/lang/Class
    //   125: invokevirtual 53	java/lang/Class:getMethod	(Ljava/lang/String;[Ljava/lang/Class;)Ljava/lang/reflect/Method;
    //   128: astore 16
    //   130: iconst_0
    //   131: anewarray 55	java/lang/Object
    //   134: astore 17
    //   136: aload 16
    //   138: aconst_null
    //   139: aload 17
    //   141: invokevirtual 61	java/lang/reflect/Method:invoke	(Ljava/lang/Object;[Ljava/lang/Object;)Ljava/lang/Object;
    //   144: astore 19
    //   146: aload 19
    //   148: checkcast 63	java/lang/Integer
    //   151: invokevirtual 67	java/lang/Integer:intValue	()I
    //   154: putstatic 71	uuuuuu/xvxxxx:bvv007600760076007600760076v	I
    //   157: ldc 2
    //   159: ldc -27
    //   161: sipush 178
    //   164: iconst_4
    //   165: iconst_3
    //   166: invokestatic 83	xxxxxx/uxxxxx:bbbb0062b0062b0062b0062	(Ljava/lang/String;CCC)Ljava/lang/String;
    //   169: iconst_0
    //   170: anewarray 35	java/lang/Class
    //   173: invokevirtual 53	java/lang/Class:getMethod	(Ljava/lang/String;[Ljava/lang/Class;)Ljava/lang/reflect/Method;
    //   176: astore 20
    //   178: iconst_0
    //   179: anewarray 55	java/lang/Object
    //   182: astore 21
    //   184: aload 20
    //   186: aconst_null
    //   187: aload 21
    //   189: invokevirtual 61	java/lang/reflect/Method:invoke	(Ljava/lang/Object;[Ljava/lang/Object;)Ljava/lang/Object;
    //   192: astore 23
    //   194: aload 23
    //   196: checkcast 63	java/lang/Integer
    //   199: invokevirtual 67	java/lang/Integer:intValue	()I
    //   202: putstatic 75	uuuuuu/xvxxxx:b0076v007600760076007600760076v	I
    //   205: getstatic 75	uuuuuu/xvxxxx:b0076v007600760076007600760076v	I
    //   208: istore_2
    //   209: getstatic 71	uuuuuu/xvxxxx:bvv007600760076007600760076v	I
    //   212: istore_3
    //   213: iload_3
    //   214: iload_3
    //   215: getstatic 69	uuuuuu/xvxxxx:bv0076v00760076007600760076v	I
    //   218: iadd
    //   219: imul
    //   220: getstatic 73	uuuuuu/xvxxxx:b00760076v00760076007600760076v	I
    //   223: irem
    //   224: tableswitch	default:+20->244, 0:+30->254
    //   244: bipush 41
    //   246: putstatic 71	uuuuuu/xvxxxx:bvv007600760076007600760076v	I
    //   249: bipush 96
    //   251: putstatic 75	uuuuuu/xvxxxx:b0076v007600760076007600760076v	I
    //   254: iload_1
    //   255: iload_2
    //   256: if_icmpeq +97 -> 353
    //   259: ldc 2
    //   261: ldc_w 408
    //   264: bipush 43
    //   266: iconst_4
    //   267: invokestatic 49	xxxxxx/uxxxxx:bb00620062bb0062b0062b0062	(Ljava/lang/String;CC)Ljava/lang/String;
    //   270: iconst_0
    //   271: anewarray 35	java/lang/Class
    //   274: invokevirtual 53	java/lang/Class:getMethod	(Ljava/lang/String;[Ljava/lang/Class;)Ljava/lang/reflect/Method;
    //   277: astore 8
    //   279: iconst_0
    //   280: anewarray 55	java/lang/Object
    //   283: astore 9
    //   285: aload 8
    //   287: aconst_null
    //   288: aload 9
    //   290: invokevirtual 61	java/lang/reflect/Method:invoke	(Ljava/lang/Object;[Ljava/lang/Object;)Ljava/lang/Object;
    //   293: astore 11
    //   295: aload 11
    //   297: checkcast 63	java/lang/Integer
    //   300: invokevirtual 67	java/lang/Integer:intValue	()I
    //   303: putstatic 71	uuuuuu/xvxxxx:bvv007600760076007600760076v	I
    //   306: ldc 2
    //   308: ldc_w 410
    //   311: bipush 30
    //   313: iconst_4
    //   314: invokestatic 49	xxxxxx/uxxxxx:bb00620062bb0062b0062b0062	(Ljava/lang/String;CC)Ljava/lang/String;
    //   317: iconst_0
    //   318: anewarray 35	java/lang/Class
    //   321: invokevirtual 53	java/lang/Class:getMethod	(Ljava/lang/String;[Ljava/lang/Class;)Ljava/lang/reflect/Method;
    //   324: astore 12
    //   326: iconst_0
    //   327: anewarray 55	java/lang/Object
    //   330: astore 13
    //   332: aload 12
    //   334: aconst_null
    //   335: aload 13
    //   337: invokevirtual 61	java/lang/reflect/Method:invoke	(Ljava/lang/Object;[Ljava/lang/Object;)Ljava/lang/Object;
    //   340: astore 15
    //   342: aload 15
    //   344: checkcast 63	java/lang/Integer
    //   347: invokevirtual 67	java/lang/Integer:intValue	()I
    //   350: putstatic 75	uuuuuu/xvxxxx:b0076v007600760076007600760076v	I
    //   353: ldc 2
    //   355: ldc_w 412
    //   358: bipush 95
    //   360: bipush 6
    //   362: iconst_1
    //   363: invokestatic 83	xxxxxx/uxxxxx:bbbb0062b0062b0062b0062	(Ljava/lang/String;CCC)Ljava/lang/String;
    //   366: iconst_0
    //   367: anewarray 35	java/lang/Class
    //   370: invokevirtual 53	java/lang/Class:getMethod	(Ljava/lang/String;[Ljava/lang/Class;)Ljava/lang/reflect/Method;
    //   373: astore 4
    //   375: iconst_0
    //   376: anewarray 55	java/lang/Object
    //   379: astore 5
    //   381: aload 4
    //   383: aload_0
    //   384: aload 5
    //   386: invokevirtual 61	java/lang/reflect/Method:invoke	(Ljava/lang/Object;[Ljava/lang/Object;)Ljava/lang/Object;
    //   389: pop
    //   390: aload_0
    //   391: invokespecial 414	uuuuuu/ssssst:ba006100610061a0061aa0061a	()V
    //   394: return
    //   395: astore 6
    //   397: aload 6
    //   399: invokevirtual 89	java/lang/reflect/InvocationTargetException:getCause	()Ljava/lang/Throwable;
    //   402: athrow
    //   403: astore 14
    //   405: aload 14
    //   407: invokevirtual 89	java/lang/reflect/InvocationTargetException:getCause	()Ljava/lang/Throwable;
    //   410: athrow
    //   411: astore 26
    //   413: aload 26
    //   415: invokevirtual 89	java/lang/reflect/InvocationTargetException:getCause	()Ljava/lang/Throwable;
    //   418: athrow
    //   419: astore 10
    //   421: aload 10
    //   423: invokevirtual 89	java/lang/reflect/InvocationTargetException:getCause	()Ljava/lang/Throwable;
    //   426: athrow
    //   427: astore 18
    //   429: aload 18
    //   431: invokevirtual 89	java/lang/reflect/InvocationTargetException:getCause	()Ljava/lang/Throwable;
    //   434: athrow
    //   435: astore 22
    //   437: aload 22
    //   439: invokevirtual 89	java/lang/reflect/InvocationTargetException:getCause	()Ljava/lang/Throwable;
    //   442: athrow
    // Local variable table:
    //   start	length	slot	name	signature
    //   0	443	0	this	xvxxxx
    //   88	169	1	i	int
    //   208	49	2	j	int
    //   212	8	3	k	int
    //   373	9	4	localMethod1	Method
    //   379	6	5	arrayOfObject1	Object[]
    //   395	3	6	localInvocationTargetException1	InvocationTargetException
    //   277	9	8	localMethod2	Method
    //   283	6	9	arrayOfObject2	Object[]
    //   419	3	10	localInvocationTargetException2	InvocationTargetException
    //   293	3	11	localObject1	Object
    //   324	9	12	localMethod3	Method
    //   330	6	13	arrayOfObject3	Object[]
    //   403	3	14	localInvocationTargetException3	InvocationTargetException
    //   340	3	15	localObject2	Object
    //   128	9	16	localMethod4	Method
    //   134	6	17	arrayOfObject4	Object[]
    //   427	3	18	localInvocationTargetException4	InvocationTargetException
    //   144	3	19	localObject3	Object
    //   176	9	20	localMethod5	Method
    //   182	6	21	arrayOfObject5	Object[]
    //   435	3	22	localInvocationTargetException5	InvocationTargetException
    //   192	3	23	localObject4	Object
    //   44	9	24	localMethod6	Method
    //   50	6	25	arrayOfObject6	Object[]
    //   411	3	26	localInvocationTargetException6	InvocationTargetException
    //   60	3	27	localObject5	Object
    // Exception table:
    //   from	to	target	type
    //   381	390	395	java/lang/reflect/InvocationTargetException
    //   332	342	403	java/lang/reflect/InvocationTargetException
    //   52	62	411	java/lang/reflect/InvocationTargetException
    //   285	295	419	java/lang/reflect/InvocationTargetException
    //   136	146	427	java/lang/reflect/InvocationTargetException
    //   184	194	435	java/lang/reflect/InvocationTargetException
  }
  
  /* Error */
  public void baaa00610061aaa0061a(DbError paramDbError)
  {
    // Byte code:
    //   0: getstatic 41	uuuuuu/xvxxxx:bv00760076v0076007600760076v	Ljava/lang/String;
    //   3: astore_2
    //   4: ldc_w 430
    //   7: sipush 199
    //   10: iconst_1
    //   11: iconst_3
    //   12: invokestatic 83	xxxxxx/uxxxxx:bbbb0062b0062b0062b0062	(Ljava/lang/String;CCC)Ljava/lang/String;
    //   15: astore_3
    //   16: iconst_3
    //   17: anewarray 35	java/lang/Class
    //   20: astore 4
    //   22: aload 4
    //   24: iconst_0
    //   25: ldc -76
    //   27: aastore
    //   28: aload 4
    //   30: iconst_1
    //   31: getstatic 191	java/lang/Character:TYPE	Ljava/lang/Class;
    //   34: aastore
    //   35: aload 4
    //   37: iconst_2
    //   38: getstatic 191	java/lang/Character:TYPE	Ljava/lang/Class;
    //   41: aastore
    //   42: ldc -63
    //   44: aload_3
    //   45: aload 4
    //   47: invokevirtual 53	java/lang/Class:getMethod	(Ljava/lang/String;[Ljava/lang/Class;)Ljava/lang/reflect/Method;
    //   50: astore 5
    //   52: iconst_3
    //   53: anewarray 55	java/lang/Object
    //   56: astore 6
    //   58: aload 6
    //   60: iconst_0
    //   61: ldc_w 432
    //   64: aastore
    //   65: aload 6
    //   67: iconst_1
    //   68: sipush 235
    //   71: invokestatic 199	java/lang/Character:valueOf	(C)Ljava/lang/Character;
    //   74: aastore
    //   75: aload 6
    //   77: iconst_2
    //   78: iconst_2
    //   79: invokestatic 199	java/lang/Character:valueOf	(C)Ljava/lang/Character;
    //   82: aastore
    //   83: aload 5
    //   85: aconst_null
    //   86: aload 6
    //   88: invokevirtual 61	java/lang/reflect/Method:invoke	(Ljava/lang/Object;[Ljava/lang/Object;)Ljava/lang/Object;
    //   91: astore 8
    //   93: aload 8
    //   95: checkcast 180	java/lang/String
    //   98: astore 9
    //   100: getstatic 71	uuuuuu/xvxxxx:bvv007600760076007600760076v	I
    //   103: istore 10
    //   105: getstatic 71	uuuuuu/xvxxxx:bvv007600760076007600760076v	I
    //   108: istore 11
    //   110: iload 11
    //   112: iload 11
    //   114: getstatic 69	uuuuuu/xvxxxx:bv0076v00760076007600760076v	I
    //   117: iadd
    //   118: imul
    //   119: getstatic 73	uuuuuu/xvxxxx:b00760076v00760076007600760076v	I
    //   122: irem
    //   123: tableswitch	default:+17->140, 0:+112->235
    //   140: ldc 2
    //   142: ldc_w 434
    //   145: bipush 99
    //   147: iconst_4
    //   148: invokestatic 49	xxxxxx/uxxxxx:bb00620062bb0062b0062b0062	(Ljava/lang/String;CC)Ljava/lang/String;
    //   151: iconst_0
    //   152: anewarray 35	java/lang/Class
    //   155: invokevirtual 53	java/lang/Class:getMethod	(Ljava/lang/String;[Ljava/lang/Class;)Ljava/lang/reflect/Method;
    //   158: astore 17
    //   160: iconst_0
    //   161: anewarray 55	java/lang/Object
    //   164: astore 18
    //   166: aload 17
    //   168: aconst_null
    //   169: aload 18
    //   171: invokevirtual 61	java/lang/reflect/Method:invoke	(Ljava/lang/Object;[Ljava/lang/Object;)Ljava/lang/Object;
    //   174: astore 20
    //   176: aload 20
    //   178: checkcast 63	java/lang/Integer
    //   181: invokevirtual 67	java/lang/Integer:intValue	()I
    //   184: putstatic 71	uuuuuu/xvxxxx:bvv007600760076007600760076v	I
    //   187: ldc 2
    //   189: ldc_w 436
    //   192: sipush 206
    //   195: iconst_5
    //   196: invokestatic 49	xxxxxx/uxxxxx:bb00620062bb0062b0062b0062	(Ljava/lang/String;CC)Ljava/lang/String;
    //   199: iconst_0
    //   200: anewarray 35	java/lang/Class
    //   203: invokevirtual 53	java/lang/Class:getMethod	(Ljava/lang/String;[Ljava/lang/Class;)Ljava/lang/reflect/Method;
    //   206: astore 21
    //   208: iconst_0
    //   209: anewarray 55	java/lang/Object
    //   212: astore 22
    //   214: aload 21
    //   216: aconst_null
    //   217: aload 22
    //   219: invokevirtual 61	java/lang/reflect/Method:invoke	(Ljava/lang/Object;[Ljava/lang/Object;)Ljava/lang/Object;
    //   222: astore 24
    //   224: aload 24
    //   226: checkcast 63	java/lang/Integer
    //   229: invokevirtual 67	java/lang/Integer:intValue	()I
    //   232: putstatic 75	uuuuuu/xvxxxx:b0076v007600760076007600760076v	I
    //   235: iload 10
    //   237: getstatic 69	uuuuuu/xvxxxx:bv0076v00760076007600760076v	I
    //   240: iadd
    //   241: getstatic 71	uuuuuu/xvxxxx:bvv007600760076007600760076v	I
    //   244: imul
    //   245: getstatic 73	uuuuuu/xvxxxx:b00760076v00760076007600760076v	I
    //   248: irem
    //   249: getstatic 75	uuuuuu/xvxxxx:b0076v007600760076007600760076v	I
    //   252: if_icmpeq +134 -> 386
    //   255: getstatic 71	uuuuuu/xvxxxx:bvv007600760076007600760076v	I
    //   258: getstatic 69	uuuuuu/xvxxxx:bv0076v00760076007600760076v	I
    //   261: iadd
    //   262: getstatic 71	uuuuuu/xvxxxx:bvv007600760076007600760076v	I
    //   265: imul
    //   266: getstatic 73	uuuuuu/xvxxxx:b00760076v00760076007600760076v	I
    //   269: irem
    //   270: getstatic 75	uuuuuu/xvxxxx:b0076v007600760076007600760076v	I
    //   273: if_icmpeq +56 -> 329
    //   276: ldc 2
    //   278: ldc_w 438
    //   281: bipush 21
    //   283: bipush 78
    //   285: iconst_2
    //   286: invokestatic 83	xxxxxx/uxxxxx:bbbb0062b0062b0062b0062	(Ljava/lang/String;CCC)Ljava/lang/String;
    //   289: iconst_0
    //   290: anewarray 35	java/lang/Class
    //   293: invokevirtual 53	java/lang/Class:getMethod	(Ljava/lang/String;[Ljava/lang/Class;)Ljava/lang/reflect/Method;
    //   296: astore 13
    //   298: iconst_0
    //   299: anewarray 55	java/lang/Object
    //   302: astore 14
    //   304: aload 13
    //   306: aconst_null
    //   307: aload 14
    //   309: invokevirtual 61	java/lang/reflect/Method:invoke	(Ljava/lang/Object;[Ljava/lang/Object;)Ljava/lang/Object;
    //   312: astore 16
    //   314: aload 16
    //   316: checkcast 63	java/lang/Integer
    //   319: invokevirtual 67	java/lang/Integer:intValue	()I
    //   322: putstatic 71	uuuuuu/xvxxxx:bvv007600760076007600760076v	I
    //   325: iconst_2
    //   326: putstatic 75	uuuuuu/xvxxxx:b0076v007600760076007600760076v	I
    //   329: bipush 76
    //   331: putstatic 71	uuuuuu/xvxxxx:bvv007600760076007600760076v	I
    //   334: bipush 18
    //   336: putstatic 75	uuuuuu/xvxxxx:b0076v007600760076007600760076v	I
    //   339: getstatic 71	uuuuuu/xvxxxx:bvv007600760076007600760076v	I
    //   342: istore 12
    //   344: iload 12
    //   346: iload 12
    //   348: getstatic 69	uuuuuu/xvxxxx:bv0076v00760076007600760076v	I
    //   351: iadd
    //   352: imul
    //   353: getstatic 73	uuuuuu/xvxxxx:b00760076v00760076007600760076v	I
    //   356: irem
    //   357: tableswitch	default:+19->376, 0:+29->386
    //   376: bipush 49
    //   378: putstatic 71	uuuuuu/xvxxxx:bvv007600760076007600760076v	I
    //   381: bipush 55
    //   383: putstatic 75	uuuuuu/xvxxxx:b0076v007600760076007600760076v	I
    //   386: aload_2
    //   387: aload 9
    //   389: aload_1
    //   390: invokestatic 444	uuuuuu/rvvvrv:b00710071qq00710071q0071q0071	(Ljava/lang/String;Ljava/lang/String;Ljava/lang/Throwable;)V
    //   393: return
    //   394: astore 19
    //   396: aload 19
    //   398: invokevirtual 89	java/lang/reflect/InvocationTargetException:getCause	()Ljava/lang/Throwable;
    //   401: athrow
    //   402: astore 23
    //   404: aload 23
    //   406: invokevirtual 89	java/lang/reflect/InvocationTargetException:getCause	()Ljava/lang/Throwable;
    //   409: athrow
    //   410: astore 7
    //   412: aload 7
    //   414: invokevirtual 89	java/lang/reflect/InvocationTargetException:getCause	()Ljava/lang/Throwable;
    //   417: athrow
    //   418: astore 15
    //   420: aload 15
    //   422: invokevirtual 89	java/lang/reflect/InvocationTargetException:getCause	()Ljava/lang/Throwable;
    //   425: athrow
    // Local variable table:
    //   start	length	slot	name	signature
    //   0	426	0	this	xvxxxx
    //   0	426	1	paramDbError	DbError
    //   3	384	2	str1	String
    //   15	30	3	str2	String
    //   20	26	4	arrayOfClass	Class[]
    //   50	34	5	localMethod1	Method
    //   56	31	6	arrayOfObject1	Object[]
    //   410	3	7	localInvocationTargetException1	InvocationTargetException
    //   91	3	8	localObject1	Object
    //   98	290	9	str3	String
    //   103	138	10	i	int
    //   108	11	11	j	int
    //   342	11	12	k	int
    //   296	9	13	localMethod2	Method
    //   302	6	14	arrayOfObject2	Object[]
    //   418	3	15	localInvocationTargetException2	InvocationTargetException
    //   312	3	16	localObject2	Object
    //   158	9	17	localMethod3	Method
    //   164	6	18	arrayOfObject3	Object[]
    //   394	3	19	localInvocationTargetException3	InvocationTargetException
    //   174	3	20	localObject3	Object
    //   206	9	21	localMethod4	Method
    //   212	6	22	arrayOfObject4	Object[]
    //   402	3	23	localInvocationTargetException4	InvocationTargetException
    //   222	3	24	localObject4	Object
    // Exception table:
    //   from	to	target	type
    //   166	176	394	java/lang/reflect/InvocationTargetException
    //   214	224	402	java/lang/reflect/InvocationTargetException
    //   83	93	410	java/lang/reflect/InvocationTargetException
    //   304	314	418	java/lang/reflect/InvocationTargetException
  }
  
  /* Error */
  public void bu00750075u00750075u0075u0075()
  {
    // Byte code:
    //   0: aload_0
    //   1: invokevirtual 159	uuuuuu/xvxxxx:bkk006Bk006Bk006Bk006Bk	()Z
    //   4: ifne +4 -> 8
    //   7: return
    //   8: aload_0
    //   9: getfield 119	uuuuuu/xvxxxx:bnnnnn006E006E006En	Luuuuuu/ttssst$tsssst;
    //   12: checkcast 167	uuuuuu/mqmmmm$vxxxxx
    //   15: invokeinterface 448 1 0
    //   20: getstatic 71	uuuuuu/xvxxxx:bvv007600760076007600760076v	I
    //   23: istore_1
    //   24: iload_1
    //   25: iload_1
    //   26: getstatic 69	uuuuuu/xvxxxx:bv0076v00760076007600760076v	I
    //   29: iadd
    //   30: imul
    //   31: getstatic 73	uuuuuu/xvxxxx:b00760076v00760076007600760076v	I
    //   34: irem
    //   35: tableswitch	default:+17->52, 0:+382->417
    //   52: ldc 2
    //   54: ldc_w 450
    //   57: bipush 71
    //   59: sipush 220
    //   62: iconst_0
    //   63: invokestatic 83	xxxxxx/uxxxxx:bbbb0062b0062b0062b0062	(Ljava/lang/String;CCC)Ljava/lang/String;
    //   66: iconst_0
    //   67: anewarray 35	java/lang/Class
    //   70: invokevirtual 53	java/lang/Class:getMethod	(Ljava/lang/String;[Ljava/lang/Class;)Ljava/lang/reflect/Method;
    //   73: astore_2
    //   74: iconst_0
    //   75: anewarray 55	java/lang/Object
    //   78: astore_3
    //   79: aload_2
    //   80: aconst_null
    //   81: aload_3
    //   82: invokevirtual 61	java/lang/reflect/Method:invoke	(Ljava/lang/Object;[Ljava/lang/Object;)Ljava/lang/Object;
    //   85: astore 5
    //   87: aload 5
    //   89: checkcast 63	java/lang/Integer
    //   92: invokevirtual 67	java/lang/Integer:intValue	()I
    //   95: putstatic 71	uuuuuu/xvxxxx:bvv007600760076007600760076v	I
    //   98: ldc 2
    //   100: ldc -122
    //   102: iconst_4
    //   103: iconst_4
    //   104: invokestatic 49	xxxxxx/uxxxxx:bb00620062bb0062b0062b0062	(Ljava/lang/String;CC)Ljava/lang/String;
    //   107: iconst_0
    //   108: anewarray 35	java/lang/Class
    //   111: invokevirtual 53	java/lang/Class:getMethod	(Ljava/lang/String;[Ljava/lang/Class;)Ljava/lang/reflect/Method;
    //   114: astore 6
    //   116: iconst_0
    //   117: anewarray 55	java/lang/Object
    //   120: astore 7
    //   122: aload 6
    //   124: aconst_null
    //   125: aload 7
    //   127: invokevirtual 61	java/lang/reflect/Method:invoke	(Ljava/lang/Object;[Ljava/lang/Object;)Ljava/lang/Object;
    //   130: astore 9
    //   132: aload 9
    //   134: checkcast 63	java/lang/Integer
    //   137: invokevirtual 67	java/lang/Integer:intValue	()I
    //   140: putstatic 75	uuuuuu/xvxxxx:b0076v007600760076007600760076v	I
    //   143: getstatic 71	uuuuuu/xvxxxx:bvv007600760076007600760076v	I
    //   146: getstatic 69	uuuuuu/xvxxxx:bv0076v00760076007600760076v	I
    //   149: iadd
    //   150: getstatic 71	uuuuuu/xvxxxx:bvv007600760076007600760076v	I
    //   153: imul
    //   154: getstatic 73	uuuuuu/xvxxxx:b00760076v00760076007600760076v	I
    //   157: irem
    //   158: getstatic 75	uuuuuu/xvxxxx:b0076v007600760076007600760076v	I
    //   161: if_icmpeq +256 -> 417
    //   164: ldc 2
    //   166: ldc_w 452
    //   169: bipush 92
    //   171: iconst_5
    //   172: invokestatic 49	xxxxxx/uxxxxx:bb00620062bb0062b0062b0062	(Ljava/lang/String;CC)Ljava/lang/String;
    //   175: iconst_0
    //   176: anewarray 35	java/lang/Class
    //   179: invokevirtual 53	java/lang/Class:getMethod	(Ljava/lang/String;[Ljava/lang/Class;)Ljava/lang/reflect/Method;
    //   182: astore 10
    //   184: iconst_0
    //   185: anewarray 55	java/lang/Object
    //   188: astore 11
    //   190: aload 10
    //   192: aconst_null
    //   193: aload 11
    //   195: invokevirtual 61	java/lang/reflect/Method:invoke	(Ljava/lang/Object;[Ljava/lang/Object;)Ljava/lang/Object;
    //   198: astore 13
    //   200: aload 13
    //   202: checkcast 63	java/lang/Integer
    //   205: invokevirtual 67	java/lang/Integer:intValue	()I
    //   208: istore 14
    //   210: iload 14
    //   212: iload 14
    //   214: getstatic 69	uuuuuu/xvxxxx:bv0076v00760076007600760076v	I
    //   217: iadd
    //   218: imul
    //   219: getstatic 73	uuuuuu/xvxxxx:b00760076v00760076007600760076v	I
    //   222: irem
    //   223: tableswitch	default:+17->240, 0:+69->292
    //   240: ldc 2
    //   242: ldc_w 454
    //   245: bipush 121
    //   247: iconst_4
    //   248: invokestatic 49	xxxxxx/uxxxxx:bb00620062bb0062b0062b0062	(Ljava/lang/String;CC)Ljava/lang/String;
    //   251: iconst_0
    //   252: anewarray 35	java/lang/Class
    //   255: invokevirtual 53	java/lang/Class:getMethod	(Ljava/lang/String;[Ljava/lang/Class;)Ljava/lang/reflect/Method;
    //   258: astore 23
    //   260: iconst_0
    //   261: anewarray 55	java/lang/Object
    //   264: astore 24
    //   266: aload 23
    //   268: aconst_null
    //   269: aload 24
    //   271: invokevirtual 61	java/lang/reflect/Method:invoke	(Ljava/lang/Object;[Ljava/lang/Object;)Ljava/lang/Object;
    //   274: astore 26
    //   276: aload 26
    //   278: checkcast 63	java/lang/Integer
    //   281: invokevirtual 67	java/lang/Integer:intValue	()I
    //   284: putstatic 71	uuuuuu/xvxxxx:bvv007600760076007600760076v	I
    //   287: bipush 87
    //   289: putstatic 75	uuuuuu/xvxxxx:b0076v007600760076007600760076v	I
    //   292: getstatic 71	uuuuuu/xvxxxx:bvv007600760076007600760076v	I
    //   295: getstatic 69	uuuuuu/xvxxxx:bv0076v00760076007600760076v	I
    //   298: iadd
    //   299: getstatic 71	uuuuuu/xvxxxx:bvv007600760076007600760076v	I
    //   302: imul
    //   303: getstatic 73	uuuuuu/xvxxxx:b00760076v00760076007600760076v	I
    //   306: irem
    //   307: getstatic 75	uuuuuu/xvxxxx:b0076v007600760076007600760076v	I
    //   310: if_icmpeq +97 -> 407
    //   313: ldc 2
    //   315: ldc_w 348
    //   318: bipush 31
    //   320: iconst_1
    //   321: invokestatic 49	xxxxxx/uxxxxx:bb00620062bb0062b0062b0062	(Ljava/lang/String;CC)Ljava/lang/String;
    //   324: iconst_0
    //   325: anewarray 35	java/lang/Class
    //   328: invokevirtual 53	java/lang/Class:getMethod	(Ljava/lang/String;[Ljava/lang/Class;)Ljava/lang/reflect/Method;
    //   331: astore 15
    //   333: iconst_0
    //   334: anewarray 55	java/lang/Object
    //   337: astore 16
    //   339: aload 15
    //   341: aconst_null
    //   342: aload 16
    //   344: invokevirtual 61	java/lang/reflect/Method:invoke	(Ljava/lang/Object;[Ljava/lang/Object;)Ljava/lang/Object;
    //   347: astore 18
    //   349: aload 18
    //   351: checkcast 63	java/lang/Integer
    //   354: invokevirtual 67	java/lang/Integer:intValue	()I
    //   357: putstatic 71	uuuuuu/xvxxxx:bvv007600760076007600760076v	I
    //   360: ldc 2
    //   362: ldc_w 456
    //   365: bipush 47
    //   367: iconst_0
    //   368: invokestatic 49	xxxxxx/uxxxxx:bb00620062bb0062b0062b0062	(Ljava/lang/String;CC)Ljava/lang/String;
    //   371: iconst_0
    //   372: anewarray 35	java/lang/Class
    //   375: invokevirtual 53	java/lang/Class:getMethod	(Ljava/lang/String;[Ljava/lang/Class;)Ljava/lang/reflect/Method;
    //   378: astore 19
    //   380: iconst_0
    //   381: anewarray 55	java/lang/Object
    //   384: astore 20
    //   386: aload 19
    //   388: aconst_null
    //   389: aload 20
    //   391: invokevirtual 61	java/lang/reflect/Method:invoke	(Ljava/lang/Object;[Ljava/lang/Object;)Ljava/lang/Object;
    //   394: astore 22
    //   396: aload 22
    //   398: checkcast 63	java/lang/Integer
    //   401: invokevirtual 67	java/lang/Integer:intValue	()I
    //   404: putstatic 75	uuuuuu/xvxxxx:b0076v007600760076007600760076v	I
    //   407: bipush 42
    //   409: putstatic 71	uuuuuu/xvxxxx:bvv007600760076007600760076v	I
    //   412: bipush 98
    //   414: putstatic 75	uuuuuu/xvxxxx:b0076v007600760076007600760076v	I
    //   417: aload_0
    //   418: getfield 119	uuuuuu/xvxxxx:bnnnnn006E006E006En	Luuuuuu/ttssst$tsssst;
    //   421: checkcast 167	uuuuuu/mqmmmm$vxxxxx
    //   424: iconst_1
    //   425: invokeinterface 459 2 0
    //   430: return
    //   431: astore 4
    //   433: aload 4
    //   435: invokevirtual 89	java/lang/reflect/InvocationTargetException:getCause	()Ljava/lang/Throwable;
    //   438: athrow
    //   439: astore 8
    //   441: aload 8
    //   443: invokevirtual 89	java/lang/reflect/InvocationTargetException:getCause	()Ljava/lang/Throwable;
    //   446: athrow
    //   447: astore 12
    //   449: aload 12
    //   451: invokevirtual 89	java/lang/reflect/InvocationTargetException:getCause	()Ljava/lang/Throwable;
    //   454: athrow
    //   455: astore 25
    //   457: aload 25
    //   459: invokevirtual 89	java/lang/reflect/InvocationTargetException:getCause	()Ljava/lang/Throwable;
    //   462: athrow
    //   463: astore 17
    //   465: aload 17
    //   467: invokevirtual 89	java/lang/reflect/InvocationTargetException:getCause	()Ljava/lang/Throwable;
    //   470: athrow
    //   471: astore 21
    //   473: aload 21
    //   475: invokevirtual 89	java/lang/reflect/InvocationTargetException:getCause	()Ljava/lang/Throwable;
    //   478: athrow
    // Local variable table:
    //   start	length	slot	name	signature
    //   0	479	0	this	xvxxxx
    //   23	8	1	i	int
    //   73	7	2	localMethod1	Method
    //   78	4	3	arrayOfObject1	Object[]
    //   431	3	4	localInvocationTargetException1	InvocationTargetException
    //   85	3	5	localObject1	Object
    //   114	9	6	localMethod2	Method
    //   120	6	7	arrayOfObject2	Object[]
    //   439	3	8	localInvocationTargetException2	InvocationTargetException
    //   130	3	9	localObject2	Object
    //   182	9	10	localMethod3	Method
    //   188	6	11	arrayOfObject3	Object[]
    //   447	3	12	localInvocationTargetException3	InvocationTargetException
    //   198	3	13	localObject3	Object
    //   208	11	14	j	int
    //   331	9	15	localMethod4	Method
    //   337	6	16	arrayOfObject4	Object[]
    //   463	3	17	localInvocationTargetException4	InvocationTargetException
    //   347	3	18	localObject4	Object
    //   378	9	19	localMethod5	Method
    //   384	6	20	arrayOfObject5	Object[]
    //   471	3	21	localInvocationTargetException5	InvocationTargetException
    //   394	3	22	localObject5	Object
    //   258	9	23	localMethod6	Method
    //   264	6	24	arrayOfObject6	Object[]
    //   455	3	25	localInvocationTargetException6	InvocationTargetException
    //   274	3	26	localObject6	Object
    // Exception table:
    //   from	to	target	type
    //   79	87	431	java/lang/reflect/InvocationTargetException
    //   122	132	439	java/lang/reflect/InvocationTargetException
    //   190	200	447	java/lang/reflect/InvocationTargetException
    //   266	276	455	java/lang/reflect/InvocationTargetException
    //   339	349	463	java/lang/reflect/InvocationTargetException
    //   386	396	471	java/lang/reflect/InvocationTargetException
  }
  
  /* Error */
  public void bu00750075uu0075u0075u0075()
  {
    // Byte code:
    //   0: aload_0
    //   1: getfield 119	uuuuuu/xvxxxx:bnnnnn006E006E006En	Luuuuuu/ttssst$tsssst;
    //   4: astore_1
    //   5: getstatic 71	uuuuuu/xvxxxx:bvv007600760076007600760076v	I
    //   8: istore_2
    //   9: iload_2
    //   10: iload_2
    //   11: getstatic 69	uuuuuu/xvxxxx:bv0076v00760076007600760076v	I
    //   14: iadd
    //   15: imul
    //   16: getstatic 73	uuuuuu/xvxxxx:b00760076v00760076007600760076v	I
    //   19: irem
    //   20: tableswitch	default:+20->40, 0:+246->266
    //   40: ldc 2
    //   42: ldc_w 462
    //   45: sipush 169
    //   48: iconst_4
    //   49: invokestatic 49	xxxxxx/uxxxxx:bb00620062bb0062b0062b0062	(Ljava/lang/String;CC)Ljava/lang/String;
    //   52: iconst_0
    //   53: anewarray 35	java/lang/Class
    //   56: invokevirtual 53	java/lang/Class:getMethod	(Ljava/lang/String;[Ljava/lang/Class;)Ljava/lang/reflect/Method;
    //   59: astore 23
    //   61: iconst_0
    //   62: anewarray 55	java/lang/Object
    //   65: astore 24
    //   67: aload 23
    //   69: aconst_null
    //   70: aload 24
    //   72: invokevirtual 61	java/lang/reflect/Method:invoke	(Ljava/lang/Object;[Ljava/lang/Object;)Ljava/lang/Object;
    //   75: astore 26
    //   77: aload 26
    //   79: checkcast 63	java/lang/Integer
    //   82: invokevirtual 67	java/lang/Integer:intValue	()I
    //   85: putstatic 71	uuuuuu/xvxxxx:bvv007600760076007600760076v	I
    //   88: ldc 2
    //   90: ldc_w 464
    //   93: sipush 195
    //   96: iconst_2
    //   97: invokestatic 49	xxxxxx/uxxxxx:bb00620062bb0062b0062b0062	(Ljava/lang/String;CC)Ljava/lang/String;
    //   100: iconst_0
    //   101: anewarray 35	java/lang/Class
    //   104: invokevirtual 53	java/lang/Class:getMethod	(Ljava/lang/String;[Ljava/lang/Class;)Ljava/lang/reflect/Method;
    //   107: astore 27
    //   109: iconst_0
    //   110: anewarray 55	java/lang/Object
    //   113: astore 28
    //   115: aload 27
    //   117: aconst_null
    //   118: aload 28
    //   120: invokevirtual 61	java/lang/reflect/Method:invoke	(Ljava/lang/Object;[Ljava/lang/Object;)Ljava/lang/Object;
    //   123: astore 30
    //   125: aload 30
    //   127: checkcast 63	java/lang/Integer
    //   130: invokevirtual 67	java/lang/Integer:intValue	()I
    //   133: putstatic 75	uuuuuu/xvxxxx:b0076v007600760076007600760076v	I
    //   136: getstatic 71	uuuuuu/xvxxxx:bvv007600760076007600760076v	I
    //   139: istore 31
    //   141: iload 31
    //   143: iload 31
    //   145: getstatic 69	uuuuuu/xvxxxx:bv0076v00760076007600760076v	I
    //   148: iadd
    //   149: imul
    //   150: getstatic 73	uuuuuu/xvxxxx:b00760076v00760076007600760076v	I
    //   153: irem
    //   154: tableswitch	default:+18->172, 0:+112->266
    //   172: ldc 2
    //   174: ldc_w 466
    //   177: bipush 51
    //   179: iconst_3
    //   180: invokestatic 49	xxxxxx/uxxxxx:bb00620062bb0062b0062b0062	(Ljava/lang/String;CC)Ljava/lang/String;
    //   183: iconst_0
    //   184: anewarray 35	java/lang/Class
    //   187: invokevirtual 53	java/lang/Class:getMethod	(Ljava/lang/String;[Ljava/lang/Class;)Ljava/lang/reflect/Method;
    //   190: astore 32
    //   192: iconst_0
    //   193: anewarray 55	java/lang/Object
    //   196: astore 33
    //   198: aload 32
    //   200: aconst_null
    //   201: aload 33
    //   203: invokevirtual 61	java/lang/reflect/Method:invoke	(Ljava/lang/Object;[Ljava/lang/Object;)Ljava/lang/Object;
    //   206: astore 35
    //   208: aload 35
    //   210: checkcast 63	java/lang/Integer
    //   213: invokevirtual 67	java/lang/Integer:intValue	()I
    //   216: putstatic 71	uuuuuu/xvxxxx:bvv007600760076007600760076v	I
    //   219: ldc 2
    //   221: ldc_w 468
    //   224: bipush 70
    //   226: iconst_3
    //   227: invokestatic 49	xxxxxx/uxxxxx:bb00620062bb0062b0062b0062	(Ljava/lang/String;CC)Ljava/lang/String;
    //   230: iconst_0
    //   231: anewarray 35	java/lang/Class
    //   234: invokevirtual 53	java/lang/Class:getMethod	(Ljava/lang/String;[Ljava/lang/Class;)Ljava/lang/reflect/Method;
    //   237: astore 36
    //   239: iconst_0
    //   240: anewarray 55	java/lang/Object
    //   243: astore 37
    //   245: aload 36
    //   247: aconst_null
    //   248: aload 37
    //   250: invokevirtual 61	java/lang/reflect/Method:invoke	(Ljava/lang/Object;[Ljava/lang/Object;)Ljava/lang/Object;
    //   253: astore 39
    //   255: aload 39
    //   257: checkcast 63	java/lang/Integer
    //   260: invokevirtual 67	java/lang/Integer:intValue	()I
    //   263: putstatic 75	uuuuuu/xvxxxx:b0076v007600760076007600760076v	I
    //   266: aload_1
    //   267: checkcast 167	uuuuuu/mqmmmm$vxxxxx
    //   270: astore_3
    //   271: aload_0
    //   272: getfield 216	uuuuuu/xvxxxx:b006E006E006E006E006En006E006En	Luuuuuu/hyhyhh;
    //   275: invokevirtual 222	uuuuuu/hyhyhh:bp0070p007000700070p007000700070	()Luuuuuu/yhhyhh;
    //   278: invokevirtual 227	uuuuuu/yhhyhh:bp0070p0070p0070p007000700070	()Z
    //   281: istore 4
    //   283: aload_0
    //   284: getfield 216	uuuuuu/xvxxxx:b006E006E006E006E006En006E006En	Luuuuuu/hyhyhh;
    //   287: invokevirtual 222	uuuuuu/hyhyhh:bp0070p007000700070p007000700070	()Luuuuuu/yhhyhh;
    //   290: astore 5
    //   292: getstatic 71	uuuuuu/xvxxxx:bvv007600760076007600760076v	I
    //   295: getstatic 69	uuuuuu/xvxxxx:bv0076v00760076007600760076v	I
    //   298: iadd
    //   299: getstatic 71	uuuuuu/xvxxxx:bvv007600760076007600760076v	I
    //   302: imul
    //   303: getstatic 73	uuuuuu/xvxxxx:b00760076v00760076007600760076v	I
    //   306: irem
    //   307: getstatic 75	uuuuuu/xvxxxx:b0076v007600760076007600760076v	I
    //   310: if_icmpeq +230 -> 540
    //   313: ldc 2
    //   315: ldc_w 470
    //   318: bipush 66
    //   320: bipush 123
    //   322: iconst_0
    //   323: invokestatic 83	xxxxxx/uxxxxx:bbbb0062b0062b0062b0062	(Ljava/lang/String;CCC)Ljava/lang/String;
    //   326: iconst_0
    //   327: anewarray 35	java/lang/Class
    //   330: invokevirtual 53	java/lang/Class:getMethod	(Ljava/lang/String;[Ljava/lang/Class;)Ljava/lang/reflect/Method;
    //   333: astore 6
    //   335: iconst_0
    //   336: anewarray 55	java/lang/Object
    //   339: astore 7
    //   341: aload 6
    //   343: aconst_null
    //   344: aload 7
    //   346: invokevirtual 61	java/lang/reflect/Method:invoke	(Ljava/lang/Object;[Ljava/lang/Object;)Ljava/lang/Object;
    //   349: astore 9
    //   351: aload 9
    //   353: checkcast 63	java/lang/Integer
    //   356: invokevirtual 67	java/lang/Integer:intValue	()I
    //   359: istore 10
    //   361: iload 10
    //   363: iload 10
    //   365: getstatic 69	uuuuuu/xvxxxx:bv0076v00760076007600760076v	I
    //   368: iadd
    //   369: imul
    //   370: getstatic 73	uuuuuu/xvxxxx:b00760076v00760076007600760076v	I
    //   373: irem
    //   374: tableswitch	default:+18->392, 0:+70->444
    //   392: bipush 57
    //   394: putstatic 71	uuuuuu/xvxxxx:bvv007600760076007600760076v	I
    //   397: ldc 2
    //   399: ldc_w 472
    //   402: bipush 34
    //   404: iconst_3
    //   405: invokestatic 49	xxxxxx/uxxxxx:bb00620062bb0062b0062b0062	(Ljava/lang/String;CC)Ljava/lang/String;
    //   408: iconst_0
    //   409: anewarray 35	java/lang/Class
    //   412: invokevirtual 53	java/lang/Class:getMethod	(Ljava/lang/String;[Ljava/lang/Class;)Ljava/lang/reflect/Method;
    //   415: astore 19
    //   417: iconst_0
    //   418: anewarray 55	java/lang/Object
    //   421: astore 20
    //   423: aload 19
    //   425: aconst_null
    //   426: aload 20
    //   428: invokevirtual 61	java/lang/reflect/Method:invoke	(Ljava/lang/Object;[Ljava/lang/Object;)Ljava/lang/Object;
    //   431: astore 22
    //   433: aload 22
    //   435: checkcast 63	java/lang/Integer
    //   438: invokevirtual 67	java/lang/Integer:intValue	()I
    //   441: putstatic 75	uuuuuu/xvxxxx:b0076v007600760076007600760076v	I
    //   444: ldc 2
    //   446: ldc_w 474
    //   449: sipush 223
    //   452: iconst_3
    //   453: invokestatic 49	xxxxxx/uxxxxx:bb00620062bb0062b0062b0062	(Ljava/lang/String;CC)Ljava/lang/String;
    //   456: iconst_0
    //   457: anewarray 35	java/lang/Class
    //   460: invokevirtual 53	java/lang/Class:getMethod	(Ljava/lang/String;[Ljava/lang/Class;)Ljava/lang/reflect/Method;
    //   463: astore 11
    //   465: iconst_0
    //   466: anewarray 55	java/lang/Object
    //   469: astore 12
    //   471: aload 11
    //   473: aconst_null
    //   474: aload 12
    //   476: invokevirtual 61	java/lang/reflect/Method:invoke	(Ljava/lang/Object;[Ljava/lang/Object;)Ljava/lang/Object;
    //   479: astore 14
    //   481: aload 14
    //   483: checkcast 63	java/lang/Integer
    //   486: invokevirtual 67	java/lang/Integer:intValue	()I
    //   489: putstatic 71	uuuuuu/xvxxxx:bvv007600760076007600760076v	I
    //   492: ldc 2
    //   494: ldc_w 476
    //   497: sipush 199
    //   500: iconst_0
    //   501: invokestatic 49	xxxxxx/uxxxxx:bb00620062bb0062b0062b0062	(Ljava/lang/String;CC)Ljava/lang/String;
    //   504: iconst_0
    //   505: anewarray 35	java/lang/Class
    //   508: invokevirtual 53	java/lang/Class:getMethod	(Ljava/lang/String;[Ljava/lang/Class;)Ljava/lang/reflect/Method;
    //   511: astore 15
    //   513: iconst_0
    //   514: anewarray 55	java/lang/Object
    //   517: astore 16
    //   519: aload 15
    //   521: aconst_null
    //   522: aload 16
    //   524: invokevirtual 61	java/lang/reflect/Method:invoke	(Ljava/lang/Object;[Ljava/lang/Object;)Ljava/lang/Object;
    //   527: astore 18
    //   529: aload 18
    //   531: checkcast 63	java/lang/Integer
    //   534: invokevirtual 67	java/lang/Integer:intValue	()I
    //   537: putstatic 75	uuuuuu/xvxxxx:b0076v007600760076007600760076v	I
    //   540: aload_3
    //   541: iload 4
    //   543: aload 5
    //   545: invokevirtual 479	uuuuuu/yhhyhh:b0070pp0070p0070p007000700070	()I
    //   548: invokeinterface 483 3 0
    //   553: return
    //   554: astore 13
    //   556: aload 13
    //   558: invokevirtual 89	java/lang/reflect/InvocationTargetException:getCause	()Ljava/lang/Throwable;
    //   561: athrow
    //   562: astore 17
    //   564: aload 17
    //   566: invokevirtual 89	java/lang/reflect/InvocationTargetException:getCause	()Ljava/lang/Throwable;
    //   569: athrow
    //   570: astore 29
    //   572: aload 29
    //   574: invokevirtual 89	java/lang/reflect/InvocationTargetException:getCause	()Ljava/lang/Throwable;
    //   577: athrow
    //   578: astore 8
    //   580: aload 8
    //   582: invokevirtual 89	java/lang/reflect/InvocationTargetException:getCause	()Ljava/lang/Throwable;
    //   585: athrow
    //   586: astore 34
    //   588: aload 34
    //   590: invokevirtual 89	java/lang/reflect/InvocationTargetException:getCause	()Ljava/lang/Throwable;
    //   593: athrow
    //   594: astore 25
    //   596: aload 25
    //   598: invokevirtual 89	java/lang/reflect/InvocationTargetException:getCause	()Ljava/lang/Throwable;
    //   601: athrow
    //   602: astore 38
    //   604: aload 38
    //   606: invokevirtual 89	java/lang/reflect/InvocationTargetException:getCause	()Ljava/lang/Throwable;
    //   609: athrow
    //   610: astore 21
    //   612: aload 21
    //   614: invokevirtual 89	java/lang/reflect/InvocationTargetException:getCause	()Ljava/lang/Throwable;
    //   617: athrow
    // Local variable table:
    //   start	length	slot	name	signature
    //   0	618	0	this	xvxxxx
    //   4	263	1	localTsssst	ttssst.tsssst
    //   8	8	2	i	int
    //   270	271	3	localVxxxxx	mqmmmm.vxxxxx
    //   281	261	4	bool	boolean
    //   290	254	5	localYhhyhh	yhhyhh
    //   333	9	6	localMethod1	Method
    //   339	6	7	arrayOfObject1	Object[]
    //   578	3	8	localInvocationTargetException1	InvocationTargetException
    //   349	3	9	localObject1	Object
    //   359	11	10	j	int
    //   463	9	11	localMethod2	Method
    //   469	6	12	arrayOfObject2	Object[]
    //   554	3	13	localInvocationTargetException2	InvocationTargetException
    //   479	3	14	localObject2	Object
    //   511	9	15	localMethod3	Method
    //   517	6	16	arrayOfObject3	Object[]
    //   562	3	17	localInvocationTargetException3	InvocationTargetException
    //   527	3	18	localObject3	Object
    //   415	9	19	localMethod4	Method
    //   421	6	20	arrayOfObject4	Object[]
    //   610	3	21	localInvocationTargetException4	InvocationTargetException
    //   431	3	22	localObject4	Object
    //   59	9	23	localMethod5	Method
    //   65	6	24	arrayOfObject5	Object[]
    //   594	3	25	localInvocationTargetException5	InvocationTargetException
    //   75	3	26	localObject5	Object
    //   107	9	27	localMethod6	Method
    //   113	6	28	arrayOfObject6	Object[]
    //   570	3	29	localInvocationTargetException6	InvocationTargetException
    //   123	3	30	localObject6	Object
    //   139	11	31	k	int
    //   190	9	32	localMethod7	Method
    //   196	6	33	arrayOfObject7	Object[]
    //   586	3	34	localInvocationTargetException7	InvocationTargetException
    //   206	3	35	localObject7	Object
    //   237	9	36	localMethod8	Method
    //   243	6	37	arrayOfObject8	Object[]
    //   602	3	38	localInvocationTargetException8	InvocationTargetException
    //   253	3	39	localObject8	Object
    // Exception table:
    //   from	to	target	type
    //   471	481	554	java/lang/reflect/InvocationTargetException
    //   519	529	562	java/lang/reflect/InvocationTargetException
    //   115	125	570	java/lang/reflect/InvocationTargetException
    //   341	351	578	java/lang/reflect/InvocationTargetException
    //   198	208	586	java/lang/reflect/InvocationTargetException
    //   67	77	594	java/lang/reflect/InvocationTargetException
    //   245	255	602	java/lang/reflect/InvocationTargetException
    //   423	433	610	java/lang/reflect/InvocationTargetException
  }
  
  /* Error */
  public void bu0075u0075u0075u0075u0075()
  {
    // Byte code:
    //   0: new 486	uuuuuu/mffffm
    //   3: dup
    //   4: invokespecial 487	uuuuuu/mffffm:<init>	()V
    //   7: astore_1
    //   8: getstatic 71	uuuuuu/xvxxxx:bvv007600760076007600760076v	I
    //   11: istore_2
    //   12: iload_2
    //   13: iload_2
    //   14: getstatic 69	uuuuuu/xvxxxx:bv0076v00760076007600760076v	I
    //   17: iadd
    //   18: imul
    //   19: getstatic 73	uuuuuu/xvxxxx:b00760076v00760076007600760076v	I
    //   22: irem
    //   23: tableswitch	default:+17->40, 0:+69->92
    //   40: bipush 52
    //   42: putstatic 71	uuuuuu/xvxxxx:bvv007600760076007600760076v	I
    //   45: ldc 2
    //   47: ldc_w 489
    //   50: bipush 96
    //   52: iconst_1
    //   53: invokestatic 49	xxxxxx/uxxxxx:bb00620062bb0062b0062b0062	(Ljava/lang/String;CC)Ljava/lang/String;
    //   56: iconst_0
    //   57: anewarray 35	java/lang/Class
    //   60: invokevirtual 53	java/lang/Class:getMethod	(Ljava/lang/String;[Ljava/lang/Class;)Ljava/lang/reflect/Method;
    //   63: astore 23
    //   65: iconst_0
    //   66: anewarray 55	java/lang/Object
    //   69: astore 24
    //   71: aload 23
    //   73: aconst_null
    //   74: aload 24
    //   76: invokevirtual 61	java/lang/reflect/Method:invoke	(Ljava/lang/Object;[Ljava/lang/Object;)Ljava/lang/Object;
    //   79: astore 26
    //   81: aload 26
    //   83: checkcast 63	java/lang/Integer
    //   86: invokevirtual 67	java/lang/Integer:intValue	()I
    //   89: putstatic 75	uuuuuu/xvxxxx:b0076v007600760076007600760076v	I
    //   92: aload_1
    //   93: aload_0
    //   94: invokevirtual 493	uuuuuu/mffffm:bpp0070pp0070p00700070p	(Luuuuuu/vvpvvp$ppvvvp;)V
    //   97: getstatic 71	uuuuuu/xvxxxx:bvv007600760076007600760076v	I
    //   100: istore_3
    //   101: iload_3
    //   102: iload_3
    //   103: getstatic 69	uuuuuu/xvxxxx:bv0076v00760076007600760076v	I
    //   106: iadd
    //   107: imul
    //   108: getstatic 73	uuuuuu/xvxxxx:b00760076v00760076007600760076v	I
    //   111: irem
    //   112: tableswitch	default:+20->132, 0:+289->401
    //   132: ldc 2
    //   134: ldc_w 474
    //   137: sipush 154
    //   140: sipush 185
    //   143: iconst_1
    //   144: invokestatic 83	xxxxxx/uxxxxx:bbbb0062b0062b0062b0062	(Ljava/lang/String;CCC)Ljava/lang/String;
    //   147: iconst_0
    //   148: anewarray 35	java/lang/Class
    //   151: invokevirtual 53	java/lang/Class:getMethod	(Ljava/lang/String;[Ljava/lang/Class;)Ljava/lang/reflect/Method;
    //   154: astore 4
    //   156: iconst_0
    //   157: anewarray 55	java/lang/Object
    //   160: astore 5
    //   162: aload 4
    //   164: aconst_null
    //   165: aload 5
    //   167: invokevirtual 61	java/lang/reflect/Method:invoke	(Ljava/lang/Object;[Ljava/lang/Object;)Ljava/lang/Object;
    //   170: astore 7
    //   172: aload 7
    //   174: checkcast 63	java/lang/Integer
    //   177: invokevirtual 67	java/lang/Integer:intValue	()I
    //   180: istore 8
    //   182: getstatic 71	uuuuuu/xvxxxx:bvv007600760076007600760076v	I
    //   185: istore 9
    //   187: iload 9
    //   189: iload 9
    //   191: getstatic 69	uuuuuu/xvxxxx:bv0076v00760076007600760076v	I
    //   194: iadd
    //   195: imul
    //   196: getstatic 73	uuuuuu/xvxxxx:b00760076v00760076007600760076v	I
    //   199: irem
    //   200: tableswitch	default:+20->220, 0:+72->272
    //   220: bipush 44
    //   222: putstatic 71	uuuuuu/xvxxxx:bvv007600760076007600760076v	I
    //   225: ldc 2
    //   227: ldc -8
    //   229: sipush 150
    //   232: iconst_5
    //   233: invokestatic 49	xxxxxx/uxxxxx:bb00620062bb0062b0062b0062	(Ljava/lang/String;CC)Ljava/lang/String;
    //   236: iconst_0
    //   237: anewarray 35	java/lang/Class
    //   240: invokevirtual 53	java/lang/Class:getMethod	(Ljava/lang/String;[Ljava/lang/Class;)Ljava/lang/reflect/Method;
    //   243: astore 19
    //   245: iconst_0
    //   246: anewarray 55	java/lang/Object
    //   249: astore 20
    //   251: aload 19
    //   253: aconst_null
    //   254: aload 20
    //   256: invokevirtual 61	java/lang/reflect/Method:invoke	(Ljava/lang/Object;[Ljava/lang/Object;)Ljava/lang/Object;
    //   259: astore 22
    //   261: aload 22
    //   263: checkcast 63	java/lang/Integer
    //   266: invokevirtual 67	java/lang/Integer:intValue	()I
    //   269: putstatic 75	uuuuuu/xvxxxx:b0076v007600760076007600760076v	I
    //   272: iload 8
    //   274: putstatic 71	uuuuuu/xvxxxx:bvv007600760076007600760076v	I
    //   277: bipush 14
    //   279: putstatic 75	uuuuuu/xvxxxx:b0076v007600760076007600760076v	I
    //   282: getstatic 71	uuuuuu/xvxxxx:bvv007600760076007600760076v	I
    //   285: getstatic 69	uuuuuu/xvxxxx:bv0076v00760076007600760076v	I
    //   288: iadd
    //   289: getstatic 71	uuuuuu/xvxxxx:bvv007600760076007600760076v	I
    //   292: imul
    //   293: getstatic 73	uuuuuu/xvxxxx:b00760076v00760076007600760076v	I
    //   296: irem
    //   297: istore 10
    //   299: ldc 2
    //   301: ldc_w 495
    //   304: bipush 62
    //   306: iconst_3
    //   307: invokestatic 49	xxxxxx/uxxxxx:bb00620062bb0062b0062b0062	(Ljava/lang/String;CC)Ljava/lang/String;
    //   310: iconst_0
    //   311: anewarray 35	java/lang/Class
    //   314: invokevirtual 53	java/lang/Class:getMethod	(Ljava/lang/String;[Ljava/lang/Class;)Ljava/lang/reflect/Method;
    //   317: astore 11
    //   319: iconst_0
    //   320: anewarray 55	java/lang/Object
    //   323: astore 12
    //   325: aload 11
    //   327: aconst_null
    //   328: aload 12
    //   330: invokevirtual 61	java/lang/reflect/Method:invoke	(Ljava/lang/Object;[Ljava/lang/Object;)Ljava/lang/Object;
    //   333: astore 14
    //   335: iload 10
    //   337: aload 14
    //   339: checkcast 63	java/lang/Integer
    //   342: invokevirtual 67	java/lang/Integer:intValue	()I
    //   345: if_icmpeq +56 -> 401
    //   348: bipush 45
    //   350: putstatic 71	uuuuuu/xvxxxx:bvv007600760076007600760076v	I
    //   353: ldc 2
    //   355: ldc_w 497
    //   358: sipush 186
    //   361: iconst_1
    //   362: invokestatic 49	xxxxxx/uxxxxx:bb00620062bb0062b0062b0062	(Ljava/lang/String;CC)Ljava/lang/String;
    //   365: iconst_0
    //   366: anewarray 35	java/lang/Class
    //   369: invokevirtual 53	java/lang/Class:getMethod	(Ljava/lang/String;[Ljava/lang/Class;)Ljava/lang/reflect/Method;
    //   372: astore 15
    //   374: iconst_0
    //   375: anewarray 55	java/lang/Object
    //   378: astore 16
    //   380: aload 15
    //   382: aconst_null
    //   383: aload 16
    //   385: invokevirtual 61	java/lang/reflect/Method:invoke	(Ljava/lang/Object;[Ljava/lang/Object;)Ljava/lang/Object;
    //   388: astore 18
    //   390: aload 18
    //   392: checkcast 63	java/lang/Integer
    //   395: invokevirtual 67	java/lang/Integer:intValue	()I
    //   398: putstatic 75	uuuuuu/xvxxxx:b0076v007600760076007600760076v	I
    //   401: return
    //   402: astore 25
    //   404: aload 25
    //   406: invokevirtual 89	java/lang/reflect/InvocationTargetException:getCause	()Ljava/lang/Throwable;
    //   409: athrow
    //   410: astore 13
    //   412: aload 13
    //   414: invokevirtual 89	java/lang/reflect/InvocationTargetException:getCause	()Ljava/lang/Throwable;
    //   417: athrow
    //   418: astore 17
    //   420: aload 17
    //   422: invokevirtual 89	java/lang/reflect/InvocationTargetException:getCause	()Ljava/lang/Throwable;
    //   425: athrow
    //   426: astore 6
    //   428: aload 6
    //   430: invokevirtual 89	java/lang/reflect/InvocationTargetException:getCause	()Ljava/lang/Throwable;
    //   433: athrow
    //   434: astore 21
    //   436: aload 21
    //   438: invokevirtual 89	java/lang/reflect/InvocationTargetException:getCause	()Ljava/lang/Throwable;
    //   441: athrow
    // Local variable table:
    //   start	length	slot	name	signature
    //   0	442	0	this	xvxxxx
    //   7	86	1	localMffffm	mffffm
    //   11	8	2	i	int
    //   100	8	3	j	int
    //   154	9	4	localMethod1	Method
    //   160	6	5	arrayOfObject1	Object[]
    //   426	3	6	localInvocationTargetException1	InvocationTargetException
    //   170	3	7	localObject1	Object
    //   180	93	8	k	int
    //   185	11	9	m	int
    //   297	49	10	n	int
    //   317	9	11	localMethod2	Method
    //   323	6	12	arrayOfObject2	Object[]
    //   410	3	13	localInvocationTargetException2	InvocationTargetException
    //   333	5	14	localObject2	Object
    //   372	9	15	localMethod3	Method
    //   378	6	16	arrayOfObject3	Object[]
    //   418	3	17	localInvocationTargetException3	InvocationTargetException
    //   388	3	18	localObject3	Object
    //   243	9	19	localMethod4	Method
    //   249	6	20	arrayOfObject4	Object[]
    //   434	3	21	localInvocationTargetException4	InvocationTargetException
    //   259	3	22	localObject4	Object
    //   63	9	23	localMethod5	Method
    //   69	6	24	arrayOfObject5	Object[]
    //   402	3	25	localInvocationTargetException5	InvocationTargetException
    //   79	3	26	localObject5	Object
    // Exception table:
    //   from	to	target	type
    //   71	81	402	java/lang/reflect/InvocationTargetException
    //   325	335	410	java/lang/reflect/InvocationTargetException
    //   380	390	418	java/lang/reflect/InvocationTargetException
    //   162	172	426	java/lang/reflect/InvocationTargetException
    //   251	261	434	java/lang/reflect/InvocationTargetException
  }
  
  /* Error */
  public void buu007500750075uu0075u0075(int paramInt, DbError paramDbError)
  {
    // Byte code:
    //   0: iload_1
    //   1: sipush 403
    //   4: if_icmpne +85 -> 89
    //   7: aload_0
    //   8: getfield 216	uuuuuu/xvxxxx:b006E006E006E006E006En006E006En	Luuuuuu/hyhyhh;
    //   11: invokevirtual 222	uuuuuu/hyhyhh:bp0070p007000700070p007000700070	()Luuuuuu/yhhyhh;
    //   14: iconst_1
    //   15: invokevirtual 280	uuuuuu/yhhyhh:bpppp00700070p007000700070	(Z)V
    //   18: iconst_0
    //   19: istore 9
    //   21: iload 9
    //   23: iconst_0
    //   24: idiv
    //   25: istore 9
    //   27: goto -6 -> 21
    //   30: astore 30
    //   32: ldc 2
    //   34: ldc_w 501
    //   37: bipush 14
    //   39: iconst_5
    //   40: invokestatic 49	xxxxxx/uxxxxx:bb00620062bb0062b0062b0062	(Ljava/lang/String;CC)Ljava/lang/String;
    //   43: iconst_0
    //   44: anewarray 35	java/lang/Class
    //   47: invokevirtual 53	java/lang/Class:getMethod	(Ljava/lang/String;[Ljava/lang/Class;)Ljava/lang/reflect/Method;
    //   50: astore 31
    //   52: iconst_0
    //   53: anewarray 55	java/lang/Object
    //   56: astore 32
    //   58: aload 31
    //   60: aconst_null
    //   61: aload 32
    //   63: invokevirtual 61	java/lang/reflect/Method:invoke	(Ljava/lang/Object;[Ljava/lang/Object;)Ljava/lang/Object;
    //   66: astore 34
    //   68: aload 34
    //   70: checkcast 63	java/lang/Integer
    //   73: invokevirtual 67	java/lang/Integer:intValue	()I
    //   76: putstatic 71	uuuuuu/xvxxxx:bvv007600760076007600760076v	I
    //   79: aload_0
    //   80: getfield 216	uuuuuu/xvxxxx:b006E006E006E006E006En006E006En	Luuuuuu/hyhyhh;
    //   83: invokevirtual 222	uuuuuu/hyhyhh:bp0070p007000700070p007000700070	()Luuuuuu/yhhyhh;
    //   86: invokevirtual 504	uuuuuu/yhhyhh:b0070p00700070p0070p007000700070	()V
    //   89: getstatic 41	uuuuuu/xvxxxx:bv00760076v0076007600760076v	Ljava/lang/String;
    //   92: aload_2
    //   93: invokevirtual 509	com/db/pwcc/dbmobile/model/error/DbError:getLocalizedMessage	()Ljava/lang/String;
    //   96: invokestatic 513	uuuuuu/rvvvrv:bq0071qq00710071q0071q0071	(Ljava/lang/String;Ljava/lang/String;)V
    //   99: aload_0
    //   100: getfield 216	uuuuuu/xvxxxx:b006E006E006E006E006En006E006En	Luuuuuu/hyhyhh;
    //   103: invokevirtual 222	uuuuuu/hyhyhh:bp0070p007000700070p007000700070	()Luuuuuu/yhhyhh;
    //   106: invokevirtual 277	uuuuuu/yhhyhh:bp007000700070p0070p007000700070	()V
    //   109: aload_0
    //   110: invokevirtual 159	uuuuuu/xvxxxx:bkk006Bk006Bk006Bk006Bk	()Z
    //   113: ifeq +97 -> 210
    //   116: aload_0
    //   117: getfield 119	uuuuuu/xvxxxx:bnnnnn006E006E006En	Luuuuuu/ttssst$tsssst;
    //   120: astore_3
    //   121: getstatic 71	uuuuuu/xvxxxx:bvv007600760076007600760076v	I
    //   124: getstatic 69	uuuuuu/xvxxxx:bv0076v00760076007600760076v	I
    //   127: iadd
    //   128: getstatic 71	uuuuuu/xvxxxx:bvv007600760076007600760076v	I
    //   131: imul
    //   132: istore 4
    //   134: ldc 2
    //   136: ldc_w 515
    //   139: bipush 122
    //   141: sipush 130
    //   144: iconst_0
    //   145: invokestatic 83	xxxxxx/uxxxxx:bbbb0062b0062b0062b0062	(Ljava/lang/String;CCC)Ljava/lang/String;
    //   148: iconst_0
    //   149: anewarray 35	java/lang/Class
    //   152: invokevirtual 53	java/lang/Class:getMethod	(Ljava/lang/String;[Ljava/lang/Class;)Ljava/lang/reflect/Method;
    //   155: astore 5
    //   157: iconst_0
    //   158: anewarray 55	java/lang/Object
    //   161: astore 6
    //   163: aload 5
    //   165: aconst_null
    //   166: aload 6
    //   168: invokevirtual 61	java/lang/reflect/Method:invoke	(Ljava/lang/Object;[Ljava/lang/Object;)Ljava/lang/Object;
    //   171: astore 8
    //   173: iload 4
    //   175: aload 8
    //   177: checkcast 63	java/lang/Integer
    //   180: invokevirtual 67	java/lang/Integer:intValue	()I
    //   183: irem
    //   184: getstatic 75	uuuuuu/xvxxxx:b0076v007600760076007600760076v	I
    //   187: if_icmpeq +13 -> 200
    //   190: bipush 60
    //   192: putstatic 71	uuuuuu/xvxxxx:bvv007600760076007600760076v	I
    //   195: bipush 8
    //   197: putstatic 75	uuuuuu/xvxxxx:b0076v007600760076007600760076v	I
    //   200: aload_3
    //   201: checkcast 167	uuuuuu/mqmmmm$vxxxxx
    //   204: iconst_0
    //   205: invokeinterface 283 2 0
    //   210: return
    //   211: astore 10
    //   213: ldc 2
    //   215: ldc_w 418
    //   218: bipush 65
    //   220: bipush 69
    //   222: iconst_1
    //   223: invokestatic 83	xxxxxx/uxxxxx:bbbb0062b0062b0062b0062	(Ljava/lang/String;CCC)Ljava/lang/String;
    //   226: iconst_0
    //   227: anewarray 35	java/lang/Class
    //   230: invokevirtual 53	java/lang/Class:getMethod	(Ljava/lang/String;[Ljava/lang/Class;)Ljava/lang/reflect/Method;
    //   233: astore 11
    //   235: iconst_0
    //   236: anewarray 55	java/lang/Object
    //   239: astore 12
    //   241: aload 11
    //   243: aconst_null
    //   244: aload 12
    //   246: invokevirtual 61	java/lang/reflect/Method:invoke	(Ljava/lang/Object;[Ljava/lang/Object;)Ljava/lang/Object;
    //   249: astore 14
    //   251: aload 14
    //   253: checkcast 63	java/lang/Integer
    //   256: invokevirtual 67	java/lang/Integer:intValue	()I
    //   259: putstatic 71	uuuuuu/xvxxxx:bvv007600760076007600760076v	I
    //   262: aconst_null
    //   263: invokevirtual 518	java/lang/String:length	()I
    //   266: pop
    //   267: getstatic 71	uuuuuu/xvxxxx:bvv007600760076007600760076v	I
    //   270: istore 16
    //   272: iload 16
    //   274: iload 16
    //   276: getstatic 69	uuuuuu/xvxxxx:bv0076v00760076007600760076v	I
    //   279: iadd
    //   280: imul
    //   281: getstatic 73	uuuuuu/xvxxxx:b00760076v00760076007600760076v	I
    //   284: irem
    //   285: tableswitch	default:+19->304, 0:+-23->262
    //   304: ldc 2
    //   306: ldc_w 295
    //   309: sipush 137
    //   312: iconst_3
    //   313: invokestatic 49	xxxxxx/uxxxxx:bb00620062bb0062b0062b0062	(Ljava/lang/String;CC)Ljava/lang/String;
    //   316: iconst_0
    //   317: anewarray 35	java/lang/Class
    //   320: invokevirtual 53	java/lang/Class:getMethod	(Ljava/lang/String;[Ljava/lang/Class;)Ljava/lang/reflect/Method;
    //   323: astore 17
    //   325: iconst_0
    //   326: anewarray 55	java/lang/Object
    //   329: astore 18
    //   331: aload 17
    //   333: aconst_null
    //   334: aload 18
    //   336: invokevirtual 61	java/lang/reflect/Method:invoke	(Ljava/lang/Object;[Ljava/lang/Object;)Ljava/lang/Object;
    //   339: astore 20
    //   341: aload 20
    //   343: checkcast 63	java/lang/Integer
    //   346: invokevirtual 67	java/lang/Integer:intValue	()I
    //   349: putstatic 71	uuuuuu/xvxxxx:bvv007600760076007600760076v	I
    //   352: bipush 35
    //   354: putstatic 75	uuuuuu/xvxxxx:b0076v007600760076007600760076v	I
    //   357: getstatic 71	uuuuuu/xvxxxx:bvv007600760076007600760076v	I
    //   360: istore 21
    //   362: iload 21
    //   364: iload 21
    //   366: getstatic 69	uuuuuu/xvxxxx:bv0076v00760076007600760076v	I
    //   369: iadd
    //   370: imul
    //   371: getstatic 73	uuuuuu/xvxxxx:b00760076v00760076007600760076v	I
    //   374: irem
    //   375: tableswitch	default:+17->392, 0:+-113->262
    //   392: ldc 2
    //   394: ldc_w 520
    //   397: sipush 175
    //   400: bipush 100
    //   402: iconst_3
    //   403: invokestatic 83	xxxxxx/uxxxxx:bbbb0062b0062b0062b0062	(Ljava/lang/String;CCC)Ljava/lang/String;
    //   406: iconst_0
    //   407: anewarray 35	java/lang/Class
    //   410: invokevirtual 53	java/lang/Class:getMethod	(Ljava/lang/String;[Ljava/lang/Class;)Ljava/lang/reflect/Method;
    //   413: astore 22
    //   415: iconst_0
    //   416: anewarray 55	java/lang/Object
    //   419: astore 23
    //   421: aload 22
    //   423: aconst_null
    //   424: aload 23
    //   426: invokevirtual 61	java/lang/reflect/Method:invoke	(Ljava/lang/Object;[Ljava/lang/Object;)Ljava/lang/Object;
    //   429: astore 25
    //   431: aload 25
    //   433: checkcast 63	java/lang/Integer
    //   436: invokevirtual 67	java/lang/Integer:intValue	()I
    //   439: putstatic 71	uuuuuu/xvxxxx:bvv007600760076007600760076v	I
    //   442: ldc 2
    //   444: ldc_w 501
    //   447: sipush 130
    //   450: sipush 166
    //   453: iconst_0
    //   454: invokestatic 83	xxxxxx/uxxxxx:bbbb0062b0062b0062b0062	(Ljava/lang/String;CCC)Ljava/lang/String;
    //   457: iconst_0
    //   458: anewarray 35	java/lang/Class
    //   461: invokevirtual 53	java/lang/Class:getMethod	(Ljava/lang/String;[Ljava/lang/Class;)Ljava/lang/reflect/Method;
    //   464: astore 26
    //   466: iconst_0
    //   467: anewarray 55	java/lang/Object
    //   470: astore 27
    //   472: aload 26
    //   474: aconst_null
    //   475: aload 27
    //   477: invokevirtual 61	java/lang/reflect/Method:invoke	(Ljava/lang/Object;[Ljava/lang/Object;)Ljava/lang/Object;
    //   480: astore 29
    //   482: aload 29
    //   484: checkcast 63	java/lang/Integer
    //   487: invokevirtual 67	java/lang/Integer:intValue	()I
    //   490: putstatic 75	uuuuuu/xvxxxx:b0076v007600760076007600760076v	I
    //   493: goto -231 -> 262
    //   496: astore 13
    //   498: aload 13
    //   500: invokevirtual 89	java/lang/reflect/InvocationTargetException:getCause	()Ljava/lang/Throwable;
    //   503: athrow
    //   504: astore 19
    //   506: aload 19
    //   508: invokevirtual 89	java/lang/reflect/InvocationTargetException:getCause	()Ljava/lang/Throwable;
    //   511: athrow
    //   512: astore 7
    //   514: aload 7
    //   516: invokevirtual 89	java/lang/reflect/InvocationTargetException:getCause	()Ljava/lang/Throwable;
    //   519: athrow
    //   520: astore 33
    //   522: aload 33
    //   524: invokevirtual 89	java/lang/reflect/InvocationTargetException:getCause	()Ljava/lang/Throwable;
    //   527: athrow
    //   528: astore 24
    //   530: aload 24
    //   532: invokevirtual 89	java/lang/reflect/InvocationTargetException:getCause	()Ljava/lang/Throwable;
    //   535: athrow
    //   536: astore 28
    //   538: aload 28
    //   540: invokevirtual 89	java/lang/reflect/InvocationTargetException:getCause	()Ljava/lang/Throwable;
    //   543: athrow
    // Local variable table:
    //   start	length	slot	name	signature
    //   0	544	0	this	xvxxxx
    //   0	544	1	paramInt	int
    //   0	544	2	paramDbError	DbError
    //   120	81	3	localTsssst	ttssst.tsssst
    //   132	52	4	i	int
    //   155	9	5	localMethod1	Method
    //   161	6	6	arrayOfObject1	Object[]
    //   512	3	7	localInvocationTargetException1	InvocationTargetException
    //   171	5	8	localObject1	Object
    //   19	7	9	j	int
    //   211	1	10	localException1	Exception
    //   233	9	11	localMethod2	Method
    //   239	6	12	arrayOfObject2	Object[]
    //   496	3	13	localInvocationTargetException2	InvocationTargetException
    //   249	3	14	localObject2	Object
    //   270	11	16	k	int
    //   323	9	17	localMethod3	Method
    //   329	6	18	arrayOfObject3	Object[]
    //   504	3	19	localInvocationTargetException3	InvocationTargetException
    //   339	3	20	localObject3	Object
    //   360	11	21	m	int
    //   413	9	22	localMethod4	Method
    //   419	6	23	arrayOfObject4	Object[]
    //   528	3	24	localInvocationTargetException4	InvocationTargetException
    //   429	3	25	localObject4	Object
    //   464	9	26	localMethod5	Method
    //   470	6	27	arrayOfObject5	Object[]
    //   536	3	28	localInvocationTargetException5	InvocationTargetException
    //   480	3	29	localObject5	Object
    //   30	1	30	localException2	Exception
    //   50	9	31	localMethod6	Method
    //   56	6	32	arrayOfObject6	Object[]
    //   520	3	33	localInvocationTargetException6	InvocationTargetException
    //   66	3	34	localObject6	Object
    // Exception table:
    //   from	to	target	type
    //   262	267	30	java/lang/Exception
    //   21	27	211	java/lang/Exception
    //   241	251	496	java/lang/reflect/InvocationTargetException
    //   331	341	504	java/lang/reflect/InvocationTargetException
    //   163	173	512	java/lang/reflect/InvocationTargetException
    //   58	68	520	java/lang/reflect/InvocationTargetException
    //   421	431	528	java/lang/reflect/InvocationTargetException
    //   472	482	536	java/lang/reflect/InvocationTargetException
  }
  
  /* Error */
  public void buu0075u00750075u0075u0075()
  {
    // Byte code:
    //   0: getstatic 71	uuuuuu/xvxxxx:bvv007600760076007600760076v	I
    //   3: getstatic 69	uuuuuu/xvxxxx:bv0076v00760076007600760076v	I
    //   6: iadd
    //   7: getstatic 71	uuuuuu/xvxxxx:bvv007600760076007600760076v	I
    //   10: imul
    //   11: getstatic 73	uuuuuu/xvxxxx:b00760076v00760076007600760076v	I
    //   14: irem
    //   15: getstatic 75	uuuuuu/xvxxxx:b0076v007600760076007600760076v	I
    //   18: if_icmpeq +13 -> 31
    //   21: bipush 64
    //   23: putstatic 71	uuuuuu/xvxxxx:bvv007600760076007600760076v	I
    //   26: bipush 95
    //   28: putstatic 75	uuuuuu/xvxxxx:b0076v007600760076007600760076v	I
    //   31: new 523	uuuuuu/aaaaal
    //   34: dup
    //   35: invokespecial 524	uuuuuu/aaaaal:<init>	()V
    //   38: astore_1
    //   39: getstatic 71	uuuuuu/xvxxxx:bvv007600760076007600760076v	I
    //   42: istore_2
    //   43: iload_2
    //   44: iload_2
    //   45: getstatic 69	uuuuuu/xvxxxx:bv0076v00760076007600760076v	I
    //   48: iadd
    //   49: imul
    //   50: getstatic 73	uuuuuu/xvxxxx:b00760076v00760076007600760076v	I
    //   53: irem
    //   54: tableswitch	default:+18->72, 0:+246->300
    //   72: ldc 2
    //   74: ldc -108
    //   76: sipush 213
    //   79: iconst_1
    //   80: invokestatic 49	xxxxxx/uxxxxx:bb00620062bb0062b0062b0062	(Ljava/lang/String;CC)Ljava/lang/String;
    //   83: iconst_0
    //   84: anewarray 35	java/lang/Class
    //   87: invokevirtual 53	java/lang/Class:getMethod	(Ljava/lang/String;[Ljava/lang/Class;)Ljava/lang/reflect/Method;
    //   90: astore 18
    //   92: iconst_0
    //   93: anewarray 55	java/lang/Object
    //   96: astore 19
    //   98: aload 18
    //   100: aconst_null
    //   101: aload 19
    //   103: invokevirtual 61	java/lang/reflect/Method:invoke	(Ljava/lang/Object;[Ljava/lang/Object;)Ljava/lang/Object;
    //   106: astore 21
    //   108: aload 21
    //   110: checkcast 63	java/lang/Integer
    //   113: invokevirtual 67	java/lang/Integer:intValue	()I
    //   116: putstatic 71	uuuuuu/xvxxxx:bvv007600760076007600760076v	I
    //   119: ldc 2
    //   121: ldc_w 526
    //   124: sipush 158
    //   127: sipush 151
    //   130: iconst_1
    //   131: invokestatic 83	xxxxxx/uxxxxx:bbbb0062b0062b0062b0062	(Ljava/lang/String;CCC)Ljava/lang/String;
    //   134: iconst_0
    //   135: anewarray 35	java/lang/Class
    //   138: invokevirtual 53	java/lang/Class:getMethod	(Ljava/lang/String;[Ljava/lang/Class;)Ljava/lang/reflect/Method;
    //   141: astore 22
    //   143: iconst_0
    //   144: anewarray 55	java/lang/Object
    //   147: astore 23
    //   149: aload 22
    //   151: aconst_null
    //   152: aload 23
    //   154: invokevirtual 61	java/lang/reflect/Method:invoke	(Ljava/lang/Object;[Ljava/lang/Object;)Ljava/lang/Object;
    //   157: astore 25
    //   159: aload 25
    //   161: checkcast 63	java/lang/Integer
    //   164: invokevirtual 67	java/lang/Integer:intValue	()I
    //   167: putstatic 75	uuuuuu/xvxxxx:b0076v007600760076007600760076v	I
    //   170: ldc 2
    //   172: ldc_w 528
    //   175: bipush 38
    //   177: iconst_2
    //   178: invokestatic 49	xxxxxx/uxxxxx:bb00620062bb0062b0062b0062	(Ljava/lang/String;CC)Ljava/lang/String;
    //   181: iconst_0
    //   182: anewarray 35	java/lang/Class
    //   185: invokevirtual 53	java/lang/Class:getMethod	(Ljava/lang/String;[Ljava/lang/Class;)Ljava/lang/reflect/Method;
    //   188: astore 26
    //   190: iconst_0
    //   191: anewarray 55	java/lang/Object
    //   194: astore 27
    //   196: aload 26
    //   198: aconst_null
    //   199: aload 27
    //   201: invokevirtual 61	java/lang/reflect/Method:invoke	(Ljava/lang/Object;[Ljava/lang/Object;)Ljava/lang/Object;
    //   204: astore 29
    //   206: aload 29
    //   208: checkcast 63	java/lang/Integer
    //   211: invokevirtual 67	java/lang/Integer:intValue	()I
    //   214: istore 30
    //   216: iload 30
    //   218: iload 30
    //   220: getstatic 69	uuuuuu/xvxxxx:bv0076v00760076007600760076v	I
    //   223: iadd
    //   224: imul
    //   225: getstatic 73	uuuuuu/xvxxxx:b00760076v00760076007600760076v	I
    //   228: irem
    //   229: tableswitch	default:+19->248, 0:+71->300
    //   248: ldc 2
    //   250: ldc -8
    //   252: sipush 225
    //   255: iconst_4
    //   256: invokestatic 49	xxxxxx/uxxxxx:bb00620062bb0062b0062b0062	(Ljava/lang/String;CC)Ljava/lang/String;
    //   259: iconst_0
    //   260: anewarray 35	java/lang/Class
    //   263: invokevirtual 53	java/lang/Class:getMethod	(Ljava/lang/String;[Ljava/lang/Class;)Ljava/lang/reflect/Method;
    //   266: astore 31
    //   268: iconst_0
    //   269: anewarray 55	java/lang/Object
    //   272: astore 32
    //   274: aload 31
    //   276: aconst_null
    //   277: aload 32
    //   279: invokevirtual 61	java/lang/reflect/Method:invoke	(Ljava/lang/Object;[Ljava/lang/Object;)Ljava/lang/Object;
    //   282: astore 34
    //   284: aload 34
    //   286: checkcast 63	java/lang/Integer
    //   289: invokevirtual 67	java/lang/Integer:intValue	()I
    //   292: putstatic 71	uuuuuu/xvxxxx:bvv007600760076007600760076v	I
    //   295: bipush 16
    //   297: putstatic 75	uuuuuu/xvxxxx:b0076v007600760076007600760076v	I
    //   300: new 530	uuuuuu/xvxxxx$2
    //   303: dup
    //   304: aload_0
    //   305: invokespecial 532	uuuuuu/xvxxxx$2:<init>	(Luuuuuu/xvxxxx;)V
    //   308: astore_3
    //   309: aload_0
    //   310: getfield 216	uuuuuu/xvxxxx:b006E006E006E006E006En006E006En	Luuuuuu/hyhyhh;
    //   313: invokevirtual 535	uuuuuu/hyhyhh:bpp0070007000700070p007000700070	()Ljava/lang/String;
    //   316: astore 4
    //   318: getstatic 71	uuuuuu/xvxxxx:bvv007600760076007600760076v	I
    //   321: getstatic 69	uuuuuu/xvxxxx:bv0076v00760076007600760076v	I
    //   324: iadd
    //   325: getstatic 71	uuuuuu/xvxxxx:bvv007600760076007600760076v	I
    //   328: imul
    //   329: getstatic 73	uuuuuu/xvxxxx:b00760076v00760076007600760076v	I
    //   332: irem
    //   333: istore 5
    //   335: ldc 2
    //   337: ldc_w 537
    //   340: bipush 88
    //   342: iconst_3
    //   343: invokestatic 49	xxxxxx/uxxxxx:bb00620062bb0062b0062b0062	(Ljava/lang/String;CC)Ljava/lang/String;
    //   346: iconst_0
    //   347: anewarray 35	java/lang/Class
    //   350: invokevirtual 53	java/lang/Class:getMethod	(Ljava/lang/String;[Ljava/lang/Class;)Ljava/lang/reflect/Method;
    //   353: astore 6
    //   355: iconst_0
    //   356: anewarray 55	java/lang/Object
    //   359: astore 7
    //   361: aload 6
    //   363: aconst_null
    //   364: aload 7
    //   366: invokevirtual 61	java/lang/reflect/Method:invoke	(Ljava/lang/Object;[Ljava/lang/Object;)Ljava/lang/Object;
    //   369: astore 9
    //   371: iload 5
    //   373: aload 9
    //   375: checkcast 63	java/lang/Integer
    //   378: invokevirtual 67	java/lang/Integer:intValue	()I
    //   381: if_icmpeq +99 -> 480
    //   384: ldc 2
    //   386: ldc_w 539
    //   389: sipush 236
    //   392: iconst_5
    //   393: invokestatic 49	xxxxxx/uxxxxx:bb00620062bb0062b0062b0062	(Ljava/lang/String;CC)Ljava/lang/String;
    //   396: iconst_0
    //   397: anewarray 35	java/lang/Class
    //   400: invokevirtual 53	java/lang/Class:getMethod	(Ljava/lang/String;[Ljava/lang/Class;)Ljava/lang/reflect/Method;
    //   403: astore 10
    //   405: iconst_0
    //   406: anewarray 55	java/lang/Object
    //   409: astore 11
    //   411: aload 10
    //   413: aconst_null
    //   414: aload 11
    //   416: invokevirtual 61	java/lang/reflect/Method:invoke	(Ljava/lang/Object;[Ljava/lang/Object;)Ljava/lang/Object;
    //   419: astore 13
    //   421: aload 13
    //   423: checkcast 63	java/lang/Integer
    //   426: invokevirtual 67	java/lang/Integer:intValue	()I
    //   429: putstatic 71	uuuuuu/xvxxxx:bvv007600760076007600760076v	I
    //   432: ldc 2
    //   434: ldc_w 541
    //   437: sipush 173
    //   440: iconst_5
    //   441: invokestatic 49	xxxxxx/uxxxxx:bb00620062bb0062b0062b0062	(Ljava/lang/String;CC)Ljava/lang/String;
    //   444: iconst_0
    //   445: anewarray 35	java/lang/Class
    //   448: invokevirtual 53	java/lang/Class:getMethod	(Ljava/lang/String;[Ljava/lang/Class;)Ljava/lang/reflect/Method;
    //   451: astore 14
    //   453: iconst_0
    //   454: anewarray 55	java/lang/Object
    //   457: astore 15
    //   459: aload 14
    //   461: aconst_null
    //   462: aload 15
    //   464: invokevirtual 61	java/lang/reflect/Method:invoke	(Ljava/lang/Object;[Ljava/lang/Object;)Ljava/lang/Object;
    //   467: astore 17
    //   469: aload 17
    //   471: checkcast 63	java/lang/Integer
    //   474: invokevirtual 67	java/lang/Integer:intValue	()I
    //   477: putstatic 75	uuuuuu/xvxxxx:b0076v007600760076007600760076v	I
    //   480: aload_1
    //   481: aload_3
    //   482: aload 4
    //   484: aload_0
    //   485: getfield 216	uuuuuu/xvxxxx:b006E006E006E006E006En006E006En	Luuuuuu/hyhyhh;
    //   488: invokevirtual 222	uuuuuu/hyhyhh:bp0070p007000700070p007000700070	()Luuuuuu/yhhyhh;
    //   491: invokevirtual 479	uuuuuu/yhhyhh:b0070pp0070p0070p007000700070	()I
    //   494: invokestatic 544	java/lang/String:valueOf	(I)Ljava/lang/String;
    //   497: getstatic 550	com/db/pwcc/dbmobile/multi_bank_aggregator/model/consents/Status:INACTIVE	Lcom/db/pwcc/dbmobile/multi_bank_aggregator/model/consents/Status;
    //   500: invokevirtual 554	uuuuuu/aaaaal:buuuu007500750075007500750075	(Luuuuuu/allaal$lalaal;Ljava/lang/String;Ljava/lang/String;Lcom/db/pwcc/dbmobile/multi_bank_aggregator/model/consents/Status;)V
    //   503: return
    //   504: astore 8
    //   506: aload 8
    //   508: invokevirtual 89	java/lang/reflect/InvocationTargetException:getCause	()Ljava/lang/Throwable;
    //   511: athrow
    //   512: astore 20
    //   514: aload 20
    //   516: invokevirtual 89	java/lang/reflect/InvocationTargetException:getCause	()Ljava/lang/Throwable;
    //   519: athrow
    //   520: astore 12
    //   522: aload 12
    //   524: invokevirtual 89	java/lang/reflect/InvocationTargetException:getCause	()Ljava/lang/Throwable;
    //   527: athrow
    //   528: astore 24
    //   530: aload 24
    //   532: invokevirtual 89	java/lang/reflect/InvocationTargetException:getCause	()Ljava/lang/Throwable;
    //   535: athrow
    //   536: astore 28
    //   538: aload 28
    //   540: invokevirtual 89	java/lang/reflect/InvocationTargetException:getCause	()Ljava/lang/Throwable;
    //   543: athrow
    //   544: astore 33
    //   546: aload 33
    //   548: invokevirtual 89	java/lang/reflect/InvocationTargetException:getCause	()Ljava/lang/Throwable;
    //   551: athrow
    //   552: astore 16
    //   554: aload 16
    //   556: invokevirtual 89	java/lang/reflect/InvocationTargetException:getCause	()Ljava/lang/Throwable;
    //   559: athrow
    // Local variable table:
    //   start	length	slot	name	signature
    //   0	560	0	this	xvxxxx
    //   38	443	1	localAaaaal	aaaaal
    //   42	8	2	i	int
    //   308	174	3	local2	2
    //   316	167	4	str	String
    //   333	49	5	j	int
    //   353	9	6	localMethod1	Method
    //   359	6	7	arrayOfObject1	Object[]
    //   504	3	8	localInvocationTargetException1	InvocationTargetException
    //   369	5	9	localObject1	Object
    //   403	9	10	localMethod2	Method
    //   409	6	11	arrayOfObject2	Object[]
    //   520	3	12	localInvocationTargetException2	InvocationTargetException
    //   419	3	13	localObject2	Object
    //   451	9	14	localMethod3	Method
    //   457	6	15	arrayOfObject3	Object[]
    //   552	3	16	localInvocationTargetException3	InvocationTargetException
    //   467	3	17	localObject3	Object
    //   90	9	18	localMethod4	Method
    //   96	6	19	arrayOfObject4	Object[]
    //   512	3	20	localInvocationTargetException4	InvocationTargetException
    //   106	3	21	localObject4	Object
    //   141	9	22	localMethod5	Method
    //   147	6	23	arrayOfObject5	Object[]
    //   528	3	24	localInvocationTargetException5	InvocationTargetException
    //   157	3	25	localObject5	Object
    //   188	9	26	localMethod6	Method
    //   194	6	27	arrayOfObject6	Object[]
    //   536	3	28	localInvocationTargetException6	InvocationTargetException
    //   204	3	29	localObject6	Object
    //   214	11	30	k	int
    //   266	9	31	localMethod7	Method
    //   272	6	32	arrayOfObject7	Object[]
    //   544	3	33	localInvocationTargetException7	InvocationTargetException
    //   282	3	34	localObject7	Object
    // Exception table:
    //   from	to	target	type
    //   361	371	504	java/lang/reflect/InvocationTargetException
    //   98	108	512	java/lang/reflect/InvocationTargetException
    //   411	421	520	java/lang/reflect/InvocationTargetException
    //   149	159	528	java/lang/reflect/InvocationTargetException
    //   196	206	536	java/lang/reflect/InvocationTargetException
    //   274	284	544	java/lang/reflect/InvocationTargetException
    //   459	469	552	java/lang/reflect/InvocationTargetException
  }
  
  /* Error */
  public void buuu007500750075u0075u0075()
  {
    // Byte code:
    //   0: ldc 2
    //   2: ldc_w 557
    //   5: sipush 150
    //   8: bipush 110
    //   10: iconst_3
    //   11: invokestatic 83	xxxxxx/uxxxxx:bbbb0062b0062b0062b0062	(Ljava/lang/String;CCC)Ljava/lang/String;
    //   14: iconst_0
    //   15: anewarray 35	java/lang/Class
    //   18: invokevirtual 53	java/lang/Class:getMethod	(Ljava/lang/String;[Ljava/lang/Class;)Ljava/lang/reflect/Method;
    //   21: astore_1
    //   22: iconst_0
    //   23: anewarray 55	java/lang/Object
    //   26: astore_2
    //   27: aload_1
    //   28: aconst_null
    //   29: aload_2
    //   30: invokevirtual 61	java/lang/reflect/Method:invoke	(Ljava/lang/Object;[Ljava/lang/Object;)Ljava/lang/Object;
    //   33: astore 4
    //   35: aload 4
    //   37: checkcast 63	java/lang/Integer
    //   40: invokevirtual 67	java/lang/Integer:intValue	()I
    //   43: istore 5
    //   45: iload 5
    //   47: iload 5
    //   49: getstatic 69	uuuuuu/xvxxxx:bv0076v00760076007600760076v	I
    //   52: iadd
    //   53: imul
    //   54: getstatic 73	uuuuuu/xvxxxx:b00760076v00760076007600760076v	I
    //   57: irem
    //   58: tableswitch	default:+18->76, 0:+285->343
    //   76: ldc 2
    //   78: ldc_w 501
    //   81: sipush 208
    //   84: bipush 39
    //   86: iconst_1
    //   87: invokestatic 83	xxxxxx/uxxxxx:bbbb0062b0062b0062b0062	(Ljava/lang/String;CCC)Ljava/lang/String;
    //   90: iconst_0
    //   91: anewarray 35	java/lang/Class
    //   94: invokevirtual 53	java/lang/Class:getMethod	(Ljava/lang/String;[Ljava/lang/Class;)Ljava/lang/reflect/Method;
    //   97: astore 16
    //   99: iconst_0
    //   100: anewarray 55	java/lang/Object
    //   103: astore 17
    //   105: aload 16
    //   107: aconst_null
    //   108: aload 17
    //   110: invokevirtual 61	java/lang/reflect/Method:invoke	(Ljava/lang/Object;[Ljava/lang/Object;)Ljava/lang/Object;
    //   113: astore 19
    //   115: aload 19
    //   117: checkcast 63	java/lang/Integer
    //   120: invokevirtual 67	java/lang/Integer:intValue	()I
    //   123: istore 20
    //   125: ldc 2
    //   127: ldc_w 559
    //   130: sipush 242
    //   133: iconst_2
    //   134: invokestatic 49	xxxxxx/uxxxxx:bb00620062bb0062b0062b0062	(Ljava/lang/String;CC)Ljava/lang/String;
    //   137: iconst_0
    //   138: anewarray 35	java/lang/Class
    //   141: invokevirtual 53	java/lang/Class:getMethod	(Ljava/lang/String;[Ljava/lang/Class;)Ljava/lang/reflect/Method;
    //   144: astore 21
    //   146: iconst_0
    //   147: anewarray 55	java/lang/Object
    //   150: astore 22
    //   152: aload 21
    //   154: aconst_null
    //   155: aload 22
    //   157: invokevirtual 61	java/lang/reflect/Method:invoke	(Ljava/lang/Object;[Ljava/lang/Object;)Ljava/lang/Object;
    //   160: astore 24
    //   162: iload 20
    //   164: aload 24
    //   166: checkcast 63	java/lang/Integer
    //   169: invokevirtual 67	java/lang/Integer:intValue	()I
    //   172: iadd
    //   173: istore 25
    //   175: ldc 2
    //   177: ldc 121
    //   179: sipush 200
    //   182: iconst_5
    //   183: invokestatic 49	xxxxxx/uxxxxx:bb00620062bb0062b0062b0062	(Ljava/lang/String;CC)Ljava/lang/String;
    //   186: iconst_0
    //   187: anewarray 35	java/lang/Class
    //   190: invokevirtual 53	java/lang/Class:getMethod	(Ljava/lang/String;[Ljava/lang/Class;)Ljava/lang/reflect/Method;
    //   193: astore 26
    //   195: iconst_0
    //   196: anewarray 55	java/lang/Object
    //   199: astore 27
    //   201: aload 26
    //   203: aconst_null
    //   204: aload 27
    //   206: invokevirtual 61	java/lang/reflect/Method:invoke	(Ljava/lang/Object;[Ljava/lang/Object;)Ljava/lang/Object;
    //   209: astore 29
    //   211: iload 25
    //   213: aload 29
    //   215: checkcast 63	java/lang/Integer
    //   218: invokevirtual 67	java/lang/Integer:intValue	()I
    //   221: imul
    //   222: istore 30
    //   224: ldc 2
    //   226: ldc_w 561
    //   229: bipush 127
    //   231: sipush 132
    //   234: iconst_1
    //   235: invokestatic 83	xxxxxx/uxxxxx:bbbb0062b0062b0062b0062	(Ljava/lang/String;CCC)Ljava/lang/String;
    //   238: iconst_0
    //   239: anewarray 35	java/lang/Class
    //   242: invokevirtual 53	java/lang/Class:getMethod	(Ljava/lang/String;[Ljava/lang/Class;)Ljava/lang/reflect/Method;
    //   245: astore 31
    //   247: iconst_0
    //   248: anewarray 55	java/lang/Object
    //   251: astore 32
    //   253: aload 31
    //   255: aconst_null
    //   256: aload 32
    //   258: invokevirtual 61	java/lang/reflect/Method:invoke	(Ljava/lang/Object;[Ljava/lang/Object;)Ljava/lang/Object;
    //   261: astore 34
    //   263: iload 30
    //   265: aload 34
    //   267: checkcast 63	java/lang/Integer
    //   270: invokevirtual 67	java/lang/Integer:intValue	()I
    //   273: irem
    //   274: getstatic 75	uuuuuu/xvxxxx:b0076v007600760076007600760076v	I
    //   277: if_icmpeq +56 -> 333
    //   280: bipush 14
    //   282: putstatic 71	uuuuuu/xvxxxx:bvv007600760076007600760076v	I
    //   285: ldc 2
    //   287: ldc_w 474
    //   290: sipush 175
    //   293: iconst_4
    //   294: invokestatic 49	xxxxxx/uxxxxx:bb00620062bb0062b0062b0062	(Ljava/lang/String;CC)Ljava/lang/String;
    //   297: iconst_0
    //   298: anewarray 35	java/lang/Class
    //   301: invokevirtual 53	java/lang/Class:getMethod	(Ljava/lang/String;[Ljava/lang/Class;)Ljava/lang/reflect/Method;
    //   304: astore 35
    //   306: iconst_0
    //   307: anewarray 55	java/lang/Object
    //   310: astore 36
    //   312: aload 35
    //   314: aconst_null
    //   315: aload 36
    //   317: invokevirtual 61	java/lang/reflect/Method:invoke	(Ljava/lang/Object;[Ljava/lang/Object;)Ljava/lang/Object;
    //   320: astore 38
    //   322: aload 38
    //   324: checkcast 63	java/lang/Integer
    //   327: invokevirtual 67	java/lang/Integer:intValue	()I
    //   330: putstatic 75	uuuuuu/xvxxxx:b0076v007600760076007600760076v	I
    //   333: bipush 35
    //   335: putstatic 71	uuuuuu/xvxxxx:bvv007600760076007600760076v	I
    //   338: bipush 86
    //   340: putstatic 75	uuuuuu/xvxxxx:b0076v007600760076007600760076v	I
    //   343: aload_0
    //   344: getfield 366	uuuuuu/xvxxxx:b0076vv00760076007600760076v	Lcom/db/pwcc/dbmobile/foundation/data/manager/broadcasting/ModelUpdatedBroadcastReceiver;
    //   347: astore 6
    //   349: getstatic 71	uuuuuu/xvxxxx:bvv007600760076007600760076v	I
    //   352: getstatic 69	uuuuuu/xvxxxx:bv0076v00760076007600760076v	I
    //   355: iadd
    //   356: getstatic 71	uuuuuu/xvxxxx:bvv007600760076007600760076v	I
    //   359: imul
    //   360: getstatic 73	uuuuuu/xvxxxx:b00760076v00760076007600760076v	I
    //   363: irem
    //   364: getstatic 75	uuuuuu/xvxxxx:b0076v007600760076007600760076v	I
    //   367: if_icmpeq +56 -> 423
    //   370: bipush 52
    //   372: putstatic 71	uuuuuu/xvxxxx:bvv007600760076007600760076v	I
    //   375: ldc 2
    //   377: ldc_w 563
    //   380: sipush 228
    //   383: iconst_5
    //   384: invokestatic 49	xxxxxx/uxxxxx:bb00620062bb0062b0062b0062	(Ljava/lang/String;CC)Ljava/lang/String;
    //   387: iconst_0
    //   388: anewarray 35	java/lang/Class
    //   391: invokevirtual 53	java/lang/Class:getMethod	(Ljava/lang/String;[Ljava/lang/Class;)Ljava/lang/reflect/Method;
    //   394: astore 12
    //   396: iconst_0
    //   397: anewarray 55	java/lang/Object
    //   400: astore 13
    //   402: aload 12
    //   404: aconst_null
    //   405: aload 13
    //   407: invokevirtual 61	java/lang/reflect/Method:invoke	(Ljava/lang/Object;[Ljava/lang/Object;)Ljava/lang/Object;
    //   410: astore 15
    //   412: aload 15
    //   414: checkcast 63	java/lang/Integer
    //   417: invokevirtual 67	java/lang/Integer:intValue	()I
    //   420: putstatic 75	uuuuuu/xvxxxx:b0076v007600760076007600760076v	I
    //   423: getstatic 71	uuuuuu/xvxxxx:bvv007600760076007600760076v	I
    //   426: istore 7
    //   428: iload 7
    //   430: iload 7
    //   432: getstatic 69	uuuuuu/xvxxxx:bv0076v00760076007600760076v	I
    //   435: iadd
    //   436: imul
    //   437: getstatic 73	uuuuuu/xvxxxx:b00760076v00760076007600760076v	I
    //   440: irem
    //   441: tableswitch	default:+19->460, 0:+72->513
    //   460: ldc 2
    //   462: ldc_w 348
    //   465: sipush 158
    //   468: iconst_1
    //   469: invokestatic 49	xxxxxx/uxxxxx:bb00620062bb0062b0062b0062	(Ljava/lang/String;CC)Ljava/lang/String;
    //   472: iconst_0
    //   473: anewarray 35	java/lang/Class
    //   476: invokevirtual 53	java/lang/Class:getMethod	(Ljava/lang/String;[Ljava/lang/Class;)Ljava/lang/reflect/Method;
    //   479: astore 8
    //   481: iconst_0
    //   482: anewarray 55	java/lang/Object
    //   485: astore 9
    //   487: aload 8
    //   489: aconst_null
    //   490: aload 9
    //   492: invokevirtual 61	java/lang/reflect/Method:invoke	(Ljava/lang/Object;[Ljava/lang/Object;)Ljava/lang/Object;
    //   495: astore 11
    //   497: aload 11
    //   499: checkcast 63	java/lang/Integer
    //   502: invokevirtual 67	java/lang/Integer:intValue	()I
    //   505: putstatic 71	uuuuuu/xvxxxx:bvv007600760076007600760076v	I
    //   508: bipush 81
    //   510: putstatic 75	uuuuuu/xvxxxx:b0076v007600760076007600760076v	I
    //   513: aload 6
    //   515: ifnonnull +34 -> 549
    //   518: aload_0
    //   519: new 565	uuuuuu/xvxxxx$1
    //   522: dup
    //   523: aload_0
    //   524: invokespecial 566	uuuuuu/xvxxxx$1:<init>	(Luuuuuu/xvxxxx;)V
    //   527: putfield 366	uuuuuu/xvxxxx:b0076vv00760076007600760076v	Lcom/db/pwcc/dbmobile/foundation/data/manager/broadcasting/ModelUpdatedBroadcastReceiver;
    //   530: aload_0
    //   531: getfield 119	uuuuuu/xvxxxx:bnnnnn006E006E006En	Luuuuuu/ttssst$tsssst;
    //   534: checkcast 167	uuuuuu/mqmmmm$vxxxxx
    //   537: aload_0
    //   538: getfield 366	uuuuuu/xvxxxx:b0076vv00760076007600760076v	Lcom/db/pwcc/dbmobile/foundation/data/manager/broadcasting/ModelUpdatedBroadcastReceiver;
    //   541: invokestatic 572	com/db/pwcc/dbmobile/foundation/data/manager/broadcasting/ModelUpdatedBroadcastReceiver:makeModelUpdatedIntentFilter	()Landroid/content/IntentFilter;
    //   544: invokeinterface 576 3 0
    //   549: return
    //   550: astore 18
    //   552: aload 18
    //   554: invokevirtual 89	java/lang/reflect/InvocationTargetException:getCause	()Ljava/lang/Throwable;
    //   557: athrow
    //   558: astore 23
    //   560: aload 23
    //   562: invokevirtual 89	java/lang/reflect/InvocationTargetException:getCause	()Ljava/lang/Throwable;
    //   565: athrow
    //   566: astore_3
    //   567: aload_3
    //   568: invokevirtual 89	java/lang/reflect/InvocationTargetException:getCause	()Ljava/lang/Throwable;
    //   571: athrow
    //   572: astore 28
    //   574: aload 28
    //   576: invokevirtual 89	java/lang/reflect/InvocationTargetException:getCause	()Ljava/lang/Throwable;
    //   579: athrow
    //   580: astore 33
    //   582: aload 33
    //   584: invokevirtual 89	java/lang/reflect/InvocationTargetException:getCause	()Ljava/lang/Throwable;
    //   587: athrow
    //   588: astore 37
    //   590: aload 37
    //   592: invokevirtual 89	java/lang/reflect/InvocationTargetException:getCause	()Ljava/lang/Throwable;
    //   595: athrow
    //   596: astore 10
    //   598: aload 10
    //   600: invokevirtual 89	java/lang/reflect/InvocationTargetException:getCause	()Ljava/lang/Throwable;
    //   603: athrow
    //   604: astore 14
    //   606: aload 14
    //   608: invokevirtual 89	java/lang/reflect/InvocationTargetException:getCause	()Ljava/lang/Throwable;
    //   611: athrow
    // Local variable table:
    //   start	length	slot	name	signature
    //   0	612	0	this	xvxxxx
    //   21	7	1	localMethod1	Method
    //   26	4	2	arrayOfObject1	Object[]
    //   566	2	3	localInvocationTargetException1	InvocationTargetException
    //   33	3	4	localObject1	Object
    //   43	11	5	i	int
    //   347	167	6	localModelUpdatedBroadcastReceiver	ModelUpdatedBroadcastReceiver
    //   426	11	7	j	int
    //   479	9	8	localMethod2	Method
    //   485	6	9	arrayOfObject2	Object[]
    //   596	3	10	localInvocationTargetException2	InvocationTargetException
    //   495	3	11	localObject2	Object
    //   394	9	12	localMethod3	Method
    //   400	6	13	arrayOfObject3	Object[]
    //   604	3	14	localInvocationTargetException3	InvocationTargetException
    //   410	3	15	localObject3	Object
    //   97	9	16	localMethod4	Method
    //   103	6	17	arrayOfObject4	Object[]
    //   550	3	18	localInvocationTargetException4	InvocationTargetException
    //   113	3	19	localObject4	Object
    //   123	50	20	k	int
    //   144	9	21	localMethod5	Method
    //   150	6	22	arrayOfObject5	Object[]
    //   558	3	23	localInvocationTargetException5	InvocationTargetException
    //   160	5	24	localObject5	Object
    //   173	49	25	m	int
    //   193	9	26	localMethod6	Method
    //   199	6	27	arrayOfObject6	Object[]
    //   572	3	28	localInvocationTargetException6	InvocationTargetException
    //   209	5	29	localObject6	Object
    //   222	52	30	n	int
    //   245	9	31	localMethod7	Method
    //   251	6	32	arrayOfObject7	Object[]
    //   580	3	33	localInvocationTargetException7	InvocationTargetException
    //   261	5	34	localObject7	Object
    //   304	9	35	localMethod8	Method
    //   310	6	36	arrayOfObject8	Object[]
    //   588	3	37	localInvocationTargetException8	InvocationTargetException
    //   320	3	38	localObject8	Object
    // Exception table:
    //   from	to	target	type
    //   105	115	550	java/lang/reflect/InvocationTargetException
    //   152	162	558	java/lang/reflect/InvocationTargetException
    //   27	35	566	java/lang/reflect/InvocationTargetException
    //   201	211	572	java/lang/reflect/InvocationTargetException
    //   253	263	580	java/lang/reflect/InvocationTargetException
    //   312	322	588	java/lang/reflect/InvocationTargetException
    //   487	497	596	java/lang/reflect/InvocationTargetException
    //   402	412	604	java/lang/reflect/InvocationTargetException
  }
  
  public void buuu0075u0075u0075u0075()
  {
    ((mqmmmm.vxxxxx)this.bnnnnn006E006E006En).updateConsentFieldProperties(false, false);
    Method localMethod1 = xvxxxx.class.getMethod(uxxxxx.bbbb0062b0062b0062b0062("`/087x45=<}9:BA=>FE\007BCKJ\fGHPO", '{', '}', '\002'), new Class[0]);
    Object[] arrayOfObject1 = new Object[0];
    for (;;)
    {
      try
      {
        Object localObject1 = localMethod1.invoke(this, arrayOfObject1);
        boolean bool = ((Boolean)localObject1).booleanValue();
        ((mqmmmm.vxxxxx)this.bnnnnn006E006E006En).setMbaSwitchState(bool);
        if (bool) {
          if ((bvv007600760076007600760076v + bv0076v00760076007600760076v) * bvv007600760076007600760076v % b00760076v00760076007600760076v != b0076v007600760076007600760076v)
          {
            localMethod6 = xvxxxx.class.getMethod(uxxxxx.bbbb0062b0062b0062b0062("H\\]^_\033\034$#\037 ('h$%-,m)*21", '\033', '5', '\002'), new Class[0]);
            arrayOfObject6 = new Object[0];
          }
        }
      }
      catch (InvocationTargetException localInvocationTargetException1)
      {
        try
        {
          Method localMethod6;
          Object[] arrayOfObject6;
          Object localObject6;
          int j;
          Method localMethod4;
          Object[] arrayOfObject4;
          localObject3 = localMethod3.invoke(null, arrayOfObject3);
          b0076v007600760076007600760076v = ((Integer)localObject3).intValue();
          localHyhyhh = this.b006E006E006E006E006En006E006En;
          if ((bvv007600760076007600760076v + bv0076v00760076007600760076v) * bvv007600760076007600760076v % b00760076v00760076007600760076v != b0076v007600760076007600760076v)
          {
            bvv007600760076007600760076v = 63;
            localMethod2 = xvxxxx.class.getMethod(uxxxxx.bbbb0062b0062b0062b0062("\030*)('`_eb\\[a^\036WV\\Y\031RQWT", 's', '', '\001'), new Class[0]);
            arrayOfObject2 = new Object[0];
          }
          try
          {
            localObject2 = localMethod2.invoke(null, arrayOfObject2);
            b0076v007600760076007600760076v = ((Integer)localObject2).intValue();
            localVxxxxx.updateConsentFieldProperties(true, localHyhyhh.bp0070p007000700070p007000700070().bp0070p0070p0070p007000700070());
            return;
          }
          catch (InvocationTargetException localInvocationTargetException2)
          {
            throw localInvocationTargetException2.getCause();
          }
          ((mqmmmm.vxxxxx)this.bnnnnn006E006E006En).showLoadingIndicator(true);
          this.b007600760076v0076007600760076v.b0075007500750075u00750075007500750075(this, this.b006E006E006E006E006En006E006En.bpp0070007000700070p007000700070());
          return;
        }
        catch (InvocationTargetException localInvocationTargetException3)
        {
          throw localInvocationTargetException3.getCause();
        }
        localInvocationTargetException1 = localInvocationTargetException1;
        throw localInvocationTargetException1.getCause();
      }
      try
      {
        localObject6 = localMethod6.invoke(null, arrayOfObject6);
        bvv007600760076007600760076v = ((Integer)localObject6).intValue();
        b0076v007600760076007600760076v = 82;
        if (this.b006E006E006E006E006En006E006En.bp0070p007000700070p007000700070().b00700070p0070p0070p007000700070())
        {
          j = (bvv007600760076007600760076v + bv0076v00760076007600760076v) * bvv007600760076007600760076v;
          localMethod4 = xvxxxx.class.getMethod(uxxxxx.bb00620062bb0062b0062b0062("tCDLKGHPO\021\022MNVUQRZY\033VW_^ [\\dc", '\006', '\000'), new Class[0]);
          arrayOfObject4 = new Object[0];
        }
        try
        {
          Object localObject4 = localMethod4.invoke(null, arrayOfObject4);
          if (j % ((Integer)localObject4).intValue() != b0076v007600760076007600760076v)
          {
            localMethod5 = xvxxxx.class.getMethod(uxxxxx.bb00620062bb0062b0062b0062("GYXWV\020\017\025\022\f\013\021\016M\007\006\f\tH\002\001\007\004", '', '\005'), new Class[0]);
            arrayOfObject5 = new Object[0];
          }
        }
        catch (InvocationTargetException localInvocationTargetException4)
        {
          Method localMethod5;
          Object[] arrayOfObject5;
          Object localObject5;
          mqmmmm.vxxxxx localVxxxxx;
          int i;
          Method localMethod3;
          Object[] arrayOfObject3;
          Object localObject3;
          hyhyhh localHyhyhh;
          Method localMethod2;
          Object[] arrayOfObject2;
          Object localObject2;
          throw localInvocationTargetException4.getCause();
        }
      }
      catch (InvocationTargetException localInvocationTargetException6)
      {
        throw localInvocationTargetException6.getCause();
      }
    }
    try
    {
      localObject5 = localMethod5.invoke(null, arrayOfObject5);
      bvv007600760076007600760076v = ((Integer)localObject5).intValue();
      b0076v007600760076007600760076v = 96;
      return;
    }
    catch (InvocationTargetException localInvocationTargetException5)
    {
      throw localInvocationTargetException5.getCause();
    }
    if (this.b006E006E006E006E006En006E006En.bp0070p007000700070p007000700070().bpp00700070p0070p007000700070())
    {
      localVxxxxx = (mqmmmm.vxxxxx)this.bnnnnn006E006E006En;
      i = bvv007600760076007600760076v;
      switch (i * (i + bv0076v00760076007600760076v) % b00760076v00760076007600760076v)
      {
      default: 
        bvv007600760076007600760076v = 4;
        localMethod3 = xvxxxx.class.getMethod(uxxxxx.bbbb0062b0062b0062b0062("l\001\002\003\004?@HGCDLK\rHIQP\022MNVU", '-', '\\', '\003'), new Class[0]);
        arrayOfObject3 = new Object[0];
      }
    }
  }
}
