package uuuuuu;

import com.db.pwcc.dbmobile.model.securities.SecurityPosition;

public class yhyyyy
  extends ssssst<yhhyyy.hhyyyy>
  implements yhhyyy.yyhyyy
{
  public static int b00700070pp0070007000700070p = 1;
  public static int b0070p0070p0070007000700070p = 22;
  public static int bp00700070p0070007000700070p = 0;
  public static int bpp0070p0070007000700070p = 2;
  private String b0070ppp0070007000700070p;
  private SecurityPosition bp0070pp0070007000700070p;
  
  public yhyyyy(SecurityPosition paramSecurityPosition, String paramString)
  {
    this.bp0070pp0070007000700070p = paramSecurityPosition;
    this.b0070ppp0070007000700070p = paramString;
  }
  
  public static int b006F006Fo006F006F006F006Fooo()
  {
    return 92;
  }
  
  public static int b006Fo006F006F006F006F006Fooo()
  {
    return 0;
  }
  
  public static int bo006F006F006F006F006F006Fooo()
  {
    return 1;
  }
  
  public static int bo006Fo006F006F006F006Fooo()
  {
    return 2;
  }
  
  /* Error */
  public boolean b006F006F006Fo006F006F006Fooo(String paramString)
  {
    // Byte code:
    //   0: aload_1
    //   1: ifnull +535 -> 536
    //   4: aload_1
    //   5: invokevirtual 43	java/lang/String:length	()I
    //   8: istore_2
    //   9: getstatic 45	uuuuuu/yhyyyy:b0070p0070p0070007000700070p	I
    //   12: istore_3
    //   13: ldc 2
    //   15: ldc 47
    //   17: bipush 127
    //   19: iconst_5
    //   20: invokestatic 53	xxxxxx/uxxxxx:bb00620062bb0062b0062b0062	(Ljava/lang/String;CC)Ljava/lang/String;
    //   23: iconst_0
    //   24: anewarray 55	java/lang/Class
    //   27: invokevirtual 59	java/lang/Class:getMethod	(Ljava/lang/String;[Ljava/lang/Class;)Ljava/lang/reflect/Method;
    //   30: astore 4
    //   32: iconst_0
    //   33: anewarray 61	java/lang/Object
    //   36: astore 5
    //   38: aload 4
    //   40: aconst_null
    //   41: aload 5
    //   43: invokevirtual 67	java/lang/reflect/Method:invoke	(Ljava/lang/Object;[Ljava/lang/Object;)Ljava/lang/Object;
    //   46: astore 7
    //   48: iload_3
    //   49: iload_3
    //   50: aload 7
    //   52: checkcast 69	java/lang/Integer
    //   55: invokevirtual 72	java/lang/Integer:intValue	()I
    //   58: iadd
    //   59: imul
    //   60: istore 8
    //   62: getstatic 74	uuuuuu/yhyyyy:bpp0070p0070007000700070p	I
    //   65: istore 9
    //   67: ldc 2
    //   69: ldc 76
    //   71: bipush 80
    //   73: iconst_2
    //   74: invokestatic 53	xxxxxx/uxxxxx:bb00620062bb0062b0062b0062	(Ljava/lang/String;CC)Ljava/lang/String;
    //   77: iconst_0
    //   78: anewarray 55	java/lang/Class
    //   81: invokevirtual 59	java/lang/Class:getMethod	(Ljava/lang/String;[Ljava/lang/Class;)Ljava/lang/reflect/Method;
    //   84: astore 10
    //   86: iconst_0
    //   87: anewarray 61	java/lang/Object
    //   90: astore 11
    //   92: aload 10
    //   94: aconst_null
    //   95: aload 11
    //   97: invokevirtual 67	java/lang/reflect/Method:invoke	(Ljava/lang/Object;[Ljava/lang/Object;)Ljava/lang/Object;
    //   100: astore 13
    //   102: aload 13
    //   104: checkcast 69	java/lang/Integer
    //   107: invokevirtual 72	java/lang/Integer:intValue	()I
    //   110: getstatic 78	uuuuuu/yhyyyy:b00700070pp0070007000700070p	I
    //   113: iadd
    //   114: istore 14
    //   116: ldc 2
    //   118: ldc 80
    //   120: bipush 13
    //   122: sipush 180
    //   125: iconst_3
    //   126: invokestatic 84	xxxxxx/uxxxxx:bbbb0062b0062b0062b0062	(Ljava/lang/String;CCC)Ljava/lang/String;
    //   129: iconst_0
    //   130: anewarray 55	java/lang/Class
    //   133: invokevirtual 59	java/lang/Class:getMethod	(Ljava/lang/String;[Ljava/lang/Class;)Ljava/lang/reflect/Method;
    //   136: astore 15
    //   138: iconst_0
    //   139: anewarray 61	java/lang/Object
    //   142: astore 16
    //   144: aload 15
    //   146: aconst_null
    //   147: aload 16
    //   149: invokevirtual 67	java/lang/reflect/Method:invoke	(Ljava/lang/Object;[Ljava/lang/Object;)Ljava/lang/Object;
    //   152: astore 18
    //   154: iload 14
    //   156: aload 18
    //   158: checkcast 69	java/lang/Integer
    //   161: invokevirtual 72	java/lang/Integer:intValue	()I
    //   164: imul
    //   165: getstatic 74	uuuuuu/yhyyyy:bpp0070p0070007000700070p	I
    //   168: irem
    //   169: getstatic 86	uuuuuu/yhyyyy:bp00700070p0070007000700070p	I
    //   172: if_icmpeq +55 -> 227
    //   175: bipush 78
    //   177: putstatic 45	uuuuuu/yhyyyy:b0070p0070p0070007000700070p	I
    //   180: ldc 2
    //   182: ldc 88
    //   184: sipush 240
    //   187: iconst_0
    //   188: invokestatic 53	xxxxxx/uxxxxx:bb00620062bb0062b0062b0062	(Ljava/lang/String;CC)Ljava/lang/String;
    //   191: iconst_0
    //   192: anewarray 55	java/lang/Class
    //   195: invokevirtual 59	java/lang/Class:getMethod	(Ljava/lang/String;[Ljava/lang/Class;)Ljava/lang/reflect/Method;
    //   198: astore 37
    //   200: iconst_0
    //   201: anewarray 61	java/lang/Object
    //   204: astore 38
    //   206: aload 37
    //   208: aconst_null
    //   209: aload 38
    //   211: invokevirtual 67	java/lang/reflect/Method:invoke	(Ljava/lang/Object;[Ljava/lang/Object;)Ljava/lang/Object;
    //   214: astore 40
    //   216: aload 40
    //   218: checkcast 69	java/lang/Integer
    //   221: invokevirtual 72	java/lang/Integer:intValue	()I
    //   224: putstatic 86	uuuuuu/yhyyyy:bp00700070p0070007000700070p	I
    //   227: iload 8
    //   229: iload 9
    //   231: irem
    //   232: tableswitch	default:+20->252, 0:+162->394
    //   252: getstatic 45	uuuuuu/yhyyyy:b0070p0070p0070007000700070p	I
    //   255: istore 28
    //   257: iload 28
    //   259: iload 28
    //   261: getstatic 78	uuuuuu/yhyyyy:b00700070pp0070007000700070p	I
    //   264: iadd
    //   265: imul
    //   266: getstatic 74	uuuuuu/yhyyyy:bpp0070p0070007000700070p	I
    //   269: irem
    //   270: tableswitch	default:+18->288, 0:+28->298
    //   288: bipush 87
    //   290: putstatic 45	uuuuuu/yhyyyy:b0070p0070p0070007000700070p	I
    //   293: bipush 30
    //   295: putstatic 86	uuuuuu/yhyyyy:bp00700070p0070007000700070p	I
    //   298: ldc 2
    //   300: ldc 90
    //   302: sipush 202
    //   305: bipush 29
    //   307: iconst_1
    //   308: invokestatic 84	xxxxxx/uxxxxx:bbbb0062b0062b0062b0062	(Ljava/lang/String;CCC)Ljava/lang/String;
    //   311: iconst_0
    //   312: anewarray 55	java/lang/Class
    //   315: invokevirtual 59	java/lang/Class:getMethod	(Ljava/lang/String;[Ljava/lang/Class;)Ljava/lang/reflect/Method;
    //   318: astore 29
    //   320: iconst_0
    //   321: anewarray 61	java/lang/Object
    //   324: astore 30
    //   326: aload 29
    //   328: aconst_null
    //   329: aload 30
    //   331: invokevirtual 67	java/lang/reflect/Method:invoke	(Ljava/lang/Object;[Ljava/lang/Object;)Ljava/lang/Object;
    //   334: astore 32
    //   336: aload 32
    //   338: checkcast 69	java/lang/Integer
    //   341: invokevirtual 72	java/lang/Integer:intValue	()I
    //   344: putstatic 45	uuuuuu/yhyyyy:b0070p0070p0070007000700070p	I
    //   347: ldc 2
    //   349: ldc 92
    //   351: sipush 139
    //   354: iconst_4
    //   355: invokestatic 53	xxxxxx/uxxxxx:bb00620062bb0062b0062b0062	(Ljava/lang/String;CC)Ljava/lang/String;
    //   358: iconst_0
    //   359: anewarray 55	java/lang/Class
    //   362: invokevirtual 59	java/lang/Class:getMethod	(Ljava/lang/String;[Ljava/lang/Class;)Ljava/lang/reflect/Method;
    //   365: astore 33
    //   367: iconst_0
    //   368: anewarray 61	java/lang/Object
    //   371: astore 34
    //   373: aload 33
    //   375: aconst_null
    //   376: aload 34
    //   378: invokevirtual 67	java/lang/reflect/Method:invoke	(Ljava/lang/Object;[Ljava/lang/Object;)Ljava/lang/Object;
    //   381: astore 36
    //   383: aload 36
    //   385: checkcast 69	java/lang/Integer
    //   388: invokevirtual 72	java/lang/Integer:intValue	()I
    //   391: putstatic 78	uuuuuu/yhyyyy:b00700070pp0070007000700070p	I
    //   394: iload_2
    //   395: ifle +141 -> 536
    //   398: getstatic 45	uuuuuu/yhyyyy:b0070p0070p0070007000700070p	I
    //   401: istore 19
    //   403: iload 19
    //   405: iload 19
    //   407: getstatic 78	uuuuuu/yhyyyy:b00700070pp0070007000700070p	I
    //   410: iadd
    //   411: imul
    //   412: getstatic 74	uuuuuu/yhyyyy:bpp0070p0070007000700070p	I
    //   415: irem
    //   416: tableswitch	default:+20->436, 0:+186->602
    //   436: ldc 2
    //   438: ldc 94
    //   440: bipush 59
    //   442: bipush 109
    //   444: iconst_2
    //   445: invokestatic 84	xxxxxx/uxxxxx:bbbb0062b0062b0062b0062	(Ljava/lang/String;CCC)Ljava/lang/String;
    //   448: iconst_0
    //   449: anewarray 55	java/lang/Class
    //   452: invokevirtual 59	java/lang/Class:getMethod	(Ljava/lang/String;[Ljava/lang/Class;)Ljava/lang/reflect/Method;
    //   455: astore 20
    //   457: iconst_0
    //   458: anewarray 61	java/lang/Object
    //   461: astore 21
    //   463: aload 20
    //   465: aconst_null
    //   466: aload 21
    //   468: invokevirtual 67	java/lang/reflect/Method:invoke	(Ljava/lang/Object;[Ljava/lang/Object;)Ljava/lang/Object;
    //   471: astore 23
    //   473: aload 23
    //   475: checkcast 69	java/lang/Integer
    //   478: invokevirtual 72	java/lang/Integer:intValue	()I
    //   481: putstatic 45	uuuuuu/yhyyyy:b0070p0070p0070007000700070p	I
    //   484: ldc 2
    //   486: ldc 96
    //   488: sipush 229
    //   491: sipush 131
    //   494: iconst_0
    //   495: invokestatic 84	xxxxxx/uxxxxx:bbbb0062b0062b0062b0062	(Ljava/lang/String;CCC)Ljava/lang/String;
    //   498: iconst_0
    //   499: anewarray 55	java/lang/Class
    //   502: invokevirtual 59	java/lang/Class:getMethod	(Ljava/lang/String;[Ljava/lang/Class;)Ljava/lang/reflect/Method;
    //   505: astore 24
    //   507: iconst_0
    //   508: anewarray 61	java/lang/Object
    //   511: astore 25
    //   513: aload 24
    //   515: aconst_null
    //   516: aload 25
    //   518: invokevirtual 67	java/lang/reflect/Method:invoke	(Ljava/lang/Object;[Ljava/lang/Object;)Ljava/lang/Object;
    //   521: astore 27
    //   523: aload 27
    //   525: checkcast 69	java/lang/Integer
    //   528: invokevirtual 72	java/lang/Integer:intValue	()I
    //   531: putstatic 78	uuuuuu/yhyyyy:b00700070pp0070007000700070p	I
    //   534: iconst_1
    //   535: ireturn
    //   536: iconst_0
    //   537: ireturn
    //   538: astore 22
    //   540: aload 22
    //   542: invokevirtual 100	java/lang/reflect/InvocationTargetException:getCause	()Ljava/lang/Throwable;
    //   545: athrow
    //   546: astore 26
    //   548: aload 26
    //   550: invokevirtual 100	java/lang/reflect/InvocationTargetException:getCause	()Ljava/lang/Throwable;
    //   553: athrow
    //   554: astore 31
    //   556: aload 31
    //   558: invokevirtual 100	java/lang/reflect/InvocationTargetException:getCause	()Ljava/lang/Throwable;
    //   561: athrow
    //   562: astore 35
    //   564: aload 35
    //   566: invokevirtual 100	java/lang/reflect/InvocationTargetException:getCause	()Ljava/lang/Throwable;
    //   569: athrow
    //   570: astore 6
    //   572: aload 6
    //   574: invokevirtual 100	java/lang/reflect/InvocationTargetException:getCause	()Ljava/lang/Throwable;
    //   577: athrow
    //   578: astore 12
    //   580: aload 12
    //   582: invokevirtual 100	java/lang/reflect/InvocationTargetException:getCause	()Ljava/lang/Throwable;
    //   585: athrow
    //   586: astore 17
    //   588: aload 17
    //   590: invokevirtual 100	java/lang/reflect/InvocationTargetException:getCause	()Ljava/lang/Throwable;
    //   593: athrow
    //   594: astore 39
    //   596: aload 39
    //   598: invokevirtual 100	java/lang/reflect/InvocationTargetException:getCause	()Ljava/lang/Throwable;
    //   601: athrow
    //   602: iconst_1
    //   603: ireturn
    // Local variable table:
    //   start	length	slot	name	signature
    //   0	604	0	this	yhyyyy
    //   0	604	1	paramString	String
    //   8	387	2	i	int
    //   12	48	3	j	int
    //   30	9	4	localMethod1	java.lang.reflect.Method
    //   36	6	5	arrayOfObject1	Object[]
    //   570	3	6	localInvocationTargetException1	java.lang.reflect.InvocationTargetException
    //   46	5	7	localObject1	Object
    //   60	172	8	k	int
    //   65	167	9	m	int
    //   84	9	10	localMethod2	java.lang.reflect.Method
    //   90	6	11	arrayOfObject2	Object[]
    //   578	3	12	localInvocationTargetException2	java.lang.reflect.InvocationTargetException
    //   100	3	13	localObject2	Object
    //   114	51	14	n	int
    //   136	9	15	localMethod3	java.lang.reflect.Method
    //   142	6	16	arrayOfObject3	Object[]
    //   586	3	17	localInvocationTargetException3	java.lang.reflect.InvocationTargetException
    //   152	5	18	localObject3	Object
    //   401	11	19	i1	int
    //   455	9	20	localMethod4	java.lang.reflect.Method
    //   461	6	21	arrayOfObject4	Object[]
    //   538	3	22	localInvocationTargetException4	java.lang.reflect.InvocationTargetException
    //   471	3	23	localObject4	Object
    //   505	9	24	localMethod5	java.lang.reflect.Method
    //   511	6	25	arrayOfObject5	Object[]
    //   546	3	26	localInvocationTargetException5	java.lang.reflect.InvocationTargetException
    //   521	3	27	localObject5	Object
    //   255	11	28	i2	int
    //   318	9	29	localMethod6	java.lang.reflect.Method
    //   324	6	30	arrayOfObject6	Object[]
    //   554	3	31	localInvocationTargetException6	java.lang.reflect.InvocationTargetException
    //   334	3	32	localObject6	Object
    //   365	9	33	localMethod7	java.lang.reflect.Method
    //   371	6	34	arrayOfObject7	Object[]
    //   562	3	35	localInvocationTargetException7	java.lang.reflect.InvocationTargetException
    //   381	3	36	localObject7	Object
    //   198	9	37	localMethod8	java.lang.reflect.Method
    //   204	6	38	arrayOfObject8	Object[]
    //   594	3	39	localInvocationTargetException8	java.lang.reflect.InvocationTargetException
    //   214	3	40	localObject8	Object
    // Exception table:
    //   from	to	target	type
    //   463	473	538	java/lang/reflect/InvocationTargetException
    //   513	523	546	java/lang/reflect/InvocationTargetException
    //   326	336	554	java/lang/reflect/InvocationTargetException
    //   373	383	562	java/lang/reflect/InvocationTargetException
    //   38	48	570	java/lang/reflect/InvocationTargetException
    //   92	102	578	java/lang/reflect/InvocationTargetException
    //   144	154	586	java/lang/reflect/InvocationTargetException
    //   206	216	594	java/lang/reflect/InvocationTargetException
  }
  
  /* Error */
  public boolean b006Foo006F006F006F006Fooo(String paramString1, String paramString2)
  {
    // Byte code:
    //   0: aload_1
    //   1: ifnull +242 -> 243
    //   4: getstatic 45	uuuuuu/yhyyyy:b0070p0070p0070007000700070p	I
    //   7: getstatic 78	uuuuuu/yhyyyy:b00700070pp0070007000700070p	I
    //   10: iadd
    //   11: getstatic 45	uuuuuu/yhyyyy:b0070p0070p0070007000700070p	I
    //   14: imul
    //   15: getstatic 74	uuuuuu/yhyyyy:bpp0070p0070007000700070p	I
    //   18: irem
    //   19: getstatic 86	uuuuuu/yhyyyy:bp00700070p0070007000700070p	I
    //   22: if_icmpeq +55 -> 77
    //   25: bipush 61
    //   27: putstatic 45	uuuuuu/yhyyyy:b0070p0070p0070007000700070p	I
    //   30: ldc 2
    //   32: ldc 106
    //   34: sipush 235
    //   37: iconst_5
    //   38: invokestatic 53	xxxxxx/uxxxxx:bb00620062bb0062b0062b0062	(Ljava/lang/String;CC)Ljava/lang/String;
    //   41: iconst_0
    //   42: anewarray 55	java/lang/Class
    //   45: invokevirtual 59	java/lang/Class:getMethod	(Ljava/lang/String;[Ljava/lang/Class;)Ljava/lang/reflect/Method;
    //   48: astore 19
    //   50: iconst_0
    //   51: anewarray 61	java/lang/Object
    //   54: astore 20
    //   56: aload 19
    //   58: aconst_null
    //   59: aload 20
    //   61: invokevirtual 67	java/lang/reflect/Method:invoke	(Ljava/lang/Object;[Ljava/lang/Object;)Ljava/lang/Object;
    //   64: astore 22
    //   66: aload 22
    //   68: checkcast 69	java/lang/Integer
    //   71: invokevirtual 72	java/lang/Integer:intValue	()I
    //   74: putstatic 86	uuuuuu/yhyyyy:bp00700070p0070007000700070p	I
    //   77: aload_1
    //   78: aload_2
    //   79: invokevirtual 110	java/lang/String:equals	(Ljava/lang/Object;)Z
    //   82: ifne +161 -> 243
    //   85: getstatic 45	uuuuuu/yhyyyy:b0070p0070p0070007000700070p	I
    //   88: getstatic 78	uuuuuu/yhyyyy:b00700070pp0070007000700070p	I
    //   91: iadd
    //   92: istore 9
    //   94: getstatic 45	uuuuuu/yhyyyy:b0070p0070p0070007000700070p	I
    //   97: istore 10
    //   99: ldc 2
    //   101: ldc 112
    //   103: sipush 219
    //   106: iconst_5
    //   107: invokestatic 53	xxxxxx/uxxxxx:bb00620062bb0062b0062b0062	(Ljava/lang/String;CC)Ljava/lang/String;
    //   110: iconst_0
    //   111: anewarray 55	java/lang/Class
    //   114: invokevirtual 59	java/lang/Class:getMethod	(Ljava/lang/String;[Ljava/lang/Class;)Ljava/lang/reflect/Method;
    //   117: astore 11
    //   119: iconst_0
    //   120: anewarray 61	java/lang/Object
    //   123: astore 12
    //   125: aload 11
    //   127: aconst_null
    //   128: aload 12
    //   130: invokevirtual 67	java/lang/reflect/Method:invoke	(Ljava/lang/Object;[Ljava/lang/Object;)Ljava/lang/Object;
    //   133: astore 14
    //   135: iload 10
    //   137: aload 14
    //   139: checkcast 69	java/lang/Integer
    //   142: invokevirtual 72	java/lang/Integer:intValue	()I
    //   145: iadd
    //   146: getstatic 45	uuuuuu/yhyyyy:b0070p0070p0070007000700070p	I
    //   149: imul
    //   150: getstatic 74	uuuuuu/yhyyyy:bpp0070p0070007000700070p	I
    //   153: irem
    //   154: getstatic 86	uuuuuu/yhyyyy:bp00700070p0070007000700070p	I
    //   157: if_icmpeq +13 -> 170
    //   160: bipush 58
    //   162: putstatic 45	uuuuuu/yhyyyy:b0070p0070p0070007000700070p	I
    //   165: bipush 67
    //   167: putstatic 86	uuuuuu/yhyyyy:bp00700070p0070007000700070p	I
    //   170: iload 9
    //   172: getstatic 45	uuuuuu/yhyyyy:b0070p0070p0070007000700070p	I
    //   175: imul
    //   176: getstatic 74	uuuuuu/yhyyyy:bpp0070p0070007000700070p	I
    //   179: irem
    //   180: getstatic 86	uuuuuu/yhyyyy:bp00700070p0070007000700070p	I
    //   183: if_icmpeq +58 -> 241
    //   186: bipush 33
    //   188: putstatic 45	uuuuuu/yhyyyy:b0070p0070p0070007000700070p	I
    //   191: ldc 2
    //   193: ldc 114
    //   195: sipush 236
    //   198: sipush 202
    //   201: iconst_3
    //   202: invokestatic 84	xxxxxx/uxxxxx:bbbb0062b0062b0062b0062	(Ljava/lang/String;CCC)Ljava/lang/String;
    //   205: iconst_0
    //   206: anewarray 55	java/lang/Class
    //   209: invokevirtual 59	java/lang/Class:getMethod	(Ljava/lang/String;[Ljava/lang/Class;)Ljava/lang/reflect/Method;
    //   212: astore 15
    //   214: iconst_0
    //   215: anewarray 61	java/lang/Object
    //   218: astore 16
    //   220: aload 15
    //   222: aconst_null
    //   223: aload 16
    //   225: invokevirtual 67	java/lang/reflect/Method:invoke	(Ljava/lang/Object;[Ljava/lang/Object;)Ljava/lang/Object;
    //   228: astore 18
    //   230: aload 18
    //   232: checkcast 69	java/lang/Integer
    //   235: invokevirtual 72	java/lang/Integer:intValue	()I
    //   238: putstatic 86	uuuuuu/yhyyyy:bp00700070p0070007000700070p	I
    //   241: iconst_1
    //   242: ireturn
    //   243: aconst_null
    //   244: invokevirtual 43	java/lang/String:length	()I
    //   247: pop
    //   248: goto -5 -> 243
    //   251: astore_3
    //   252: ldc 2
    //   254: ldc 116
    //   256: bipush 122
    //   258: iconst_2
    //   259: invokestatic 53	xxxxxx/uxxxxx:bb00620062bb0062b0062b0062	(Ljava/lang/String;CC)Ljava/lang/String;
    //   262: iconst_0
    //   263: anewarray 55	java/lang/Class
    //   266: invokevirtual 59	java/lang/Class:getMethod	(Ljava/lang/String;[Ljava/lang/Class;)Ljava/lang/reflect/Method;
    //   269: astore 4
    //   271: iconst_0
    //   272: anewarray 61	java/lang/Object
    //   275: astore 5
    //   277: aload 4
    //   279: aconst_null
    //   280: aload 5
    //   282: invokevirtual 67	java/lang/reflect/Method:invoke	(Ljava/lang/Object;[Ljava/lang/Object;)Ljava/lang/Object;
    //   285: astore 7
    //   287: aload 7
    //   289: checkcast 69	java/lang/Integer
    //   292: invokevirtual 72	java/lang/Integer:intValue	()I
    //   295: putstatic 45	uuuuuu/yhyyyy:b0070p0070p0070007000700070p	I
    //   298: iconst_0
    //   299: ireturn
    //   300: astore 13
    //   302: aload 13
    //   304: invokevirtual 100	java/lang/reflect/InvocationTargetException:getCause	()Ljava/lang/Throwable;
    //   307: athrow
    //   308: astore 6
    //   310: aload 6
    //   312: invokevirtual 100	java/lang/reflect/InvocationTargetException:getCause	()Ljava/lang/Throwable;
    //   315: athrow
    //   316: astore 17
    //   318: aload 17
    //   320: invokevirtual 100	java/lang/reflect/InvocationTargetException:getCause	()Ljava/lang/Throwable;
    //   323: athrow
    //   324: astore 21
    //   326: aload 21
    //   328: invokevirtual 100	java/lang/reflect/InvocationTargetException:getCause	()Ljava/lang/Throwable;
    //   331: athrow
    // Local variable table:
    //   start	length	slot	name	signature
    //   0	332	0	this	yhyyyy
    //   0	332	1	paramString1	String
    //   0	332	2	paramString2	String
    //   251	1	3	localException	Exception
    //   269	9	4	localMethod1	java.lang.reflect.Method
    //   275	6	5	arrayOfObject1	Object[]
    //   308	3	6	localInvocationTargetException1	java.lang.reflect.InvocationTargetException
    //   285	3	7	localObject1	Object
    //   92	84	9	i	int
    //   97	49	10	j	int
    //   117	9	11	localMethod2	java.lang.reflect.Method
    //   123	6	12	arrayOfObject2	Object[]
    //   300	3	13	localInvocationTargetException2	java.lang.reflect.InvocationTargetException
    //   133	5	14	localObject2	Object
    //   212	9	15	localMethod3	java.lang.reflect.Method
    //   218	6	16	arrayOfObject3	Object[]
    //   316	3	17	localInvocationTargetException3	java.lang.reflect.InvocationTargetException
    //   228	3	18	localObject3	Object
    //   48	9	19	localMethod4	java.lang.reflect.Method
    //   54	6	20	arrayOfObject4	Object[]
    //   324	3	21	localInvocationTargetException4	java.lang.reflect.InvocationTargetException
    //   64	3	22	localObject4	Object
    // Exception table:
    //   from	to	target	type
    //   243	248	251	java/lang/Exception
    //   125	135	300	java/lang/reflect/InvocationTargetException
    //   277	287	308	java/lang/reflect/InvocationTargetException
    //   220	230	316	java/lang/reflect/InvocationTargetException
    //   56	66	324	java/lang/reflect/InvocationTargetException
  }
  
  /* Error */
  public void boo006F006F006F006F006Fooo(yhhyyy.hhyyyy paramHhyyyy)
  {
    // Byte code:
    //   0: aload_0
    //   1: aload_1
    //   2: invokespecial 138	uuuuuu/ssssst:ba0061a0061a0061a0061aa	(Luuuuuu/ttssst$tsssst;)V
    //   5: ldc 2
    //   7: ldc -116
    //   9: sipush 183
    //   12: iconst_1
    //   13: invokestatic 53	xxxxxx/uxxxxx:bb00620062bb0062b0062b0062	(Ljava/lang/String;CC)Ljava/lang/String;
    //   16: iconst_0
    //   17: anewarray 55	java/lang/Class
    //   20: invokevirtual 59	java/lang/Class:getMethod	(Ljava/lang/String;[Ljava/lang/Class;)Ljava/lang/reflect/Method;
    //   23: astore_2
    //   24: iconst_0
    //   25: anewarray 61	java/lang/Object
    //   28: astore_3
    //   29: aload_2
    //   30: aconst_null
    //   31: aload_3
    //   32: invokevirtual 67	java/lang/reflect/Method:invoke	(Ljava/lang/Object;[Ljava/lang/Object;)Ljava/lang/Object;
    //   35: astore 5
    //   37: aload 5
    //   39: checkcast 69	java/lang/Integer
    //   42: invokevirtual 72	java/lang/Integer:intValue	()I
    //   45: istore 6
    //   47: iload 6
    //   49: iload 6
    //   51: getstatic 78	uuuuuu/yhyyyy:b00700070pp0070007000700070p	I
    //   54: iadd
    //   55: imul
    //   56: getstatic 74	uuuuuu/yhyyyy:bpp0070p0070007000700070p	I
    //   59: irem
    //   60: istore 7
    //   62: getstatic 45	uuuuuu/yhyyyy:b0070p0070p0070007000700070p	I
    //   65: getstatic 78	uuuuuu/yhyyyy:b00700070pp0070007000700070p	I
    //   68: iadd
    //   69: getstatic 45	uuuuuu/yhyyyy:b0070p0070p0070007000700070p	I
    //   72: imul
    //   73: istore 8
    //   75: ldc 2
    //   77: ldc -114
    //   79: sipush 135
    //   82: sipush 177
    //   85: iconst_0
    //   86: invokestatic 84	xxxxxx/uxxxxx:bbbb0062b0062b0062b0062	(Ljava/lang/String;CCC)Ljava/lang/String;
    //   89: iconst_0
    //   90: anewarray 55	java/lang/Class
    //   93: invokevirtual 59	java/lang/Class:getMethod	(Ljava/lang/String;[Ljava/lang/Class;)Ljava/lang/reflect/Method;
    //   96: astore 9
    //   98: iconst_0
    //   99: anewarray 61	java/lang/Object
    //   102: astore 10
    //   104: aload 9
    //   106: aconst_null
    //   107: aload 10
    //   109: invokevirtual 67	java/lang/reflect/Method:invoke	(Ljava/lang/Object;[Ljava/lang/Object;)Ljava/lang/Object;
    //   112: astore 12
    //   114: iload 8
    //   116: aload 12
    //   118: checkcast 69	java/lang/Integer
    //   121: invokevirtual 72	java/lang/Integer:intValue	()I
    //   124: irem
    //   125: istore 13
    //   127: ldc 2
    //   129: ldc -112
    //   131: bipush 41
    //   133: iconst_0
    //   134: invokestatic 53	xxxxxx/uxxxxx:bb00620062bb0062b0062b0062	(Ljava/lang/String;CC)Ljava/lang/String;
    //   137: iconst_0
    //   138: anewarray 55	java/lang/Class
    //   141: invokevirtual 59	java/lang/Class:getMethod	(Ljava/lang/String;[Ljava/lang/Class;)Ljava/lang/reflect/Method;
    //   144: astore 14
    //   146: iconst_0
    //   147: anewarray 61	java/lang/Object
    //   150: astore 15
    //   152: aload 14
    //   154: aconst_null
    //   155: aload 15
    //   157: invokevirtual 67	java/lang/reflect/Method:invoke	(Ljava/lang/Object;[Ljava/lang/Object;)Ljava/lang/Object;
    //   160: astore 17
    //   162: iload 13
    //   164: aload 17
    //   166: checkcast 69	java/lang/Integer
    //   169: invokevirtual 72	java/lang/Integer:intValue	()I
    //   172: if_icmpeq +13 -> 185
    //   175: bipush 62
    //   177: putstatic 45	uuuuuu/yhyyyy:b0070p0070p0070007000700070p	I
    //   180: bipush 92
    //   182: putstatic 78	uuuuuu/yhyyyy:b00700070pp0070007000700070p	I
    //   185: iload 7
    //   187: tableswitch	default:+17->204, 0:+154->341
    //   204: getstatic 45	uuuuuu/yhyyyy:b0070p0070p0070007000700070p	I
    //   207: istore 19
    //   209: iload 19
    //   211: iload 19
    //   213: getstatic 78	uuuuuu/yhyyyy:b00700070pp0070007000700070p	I
    //   216: iadd
    //   217: imul
    //   218: getstatic 74	uuuuuu/yhyyyy:bpp0070p0070007000700070p	I
    //   221: irem
    //   222: tableswitch	default:+18->240, 0:+72->294
    //   240: ldc 2
    //   242: ldc -110
    //   244: bipush 118
    //   246: sipush 210
    //   249: iconst_3
    //   250: invokestatic 84	xxxxxx/uxxxxx:bbbb0062b0062b0062b0062	(Ljava/lang/String;CCC)Ljava/lang/String;
    //   253: iconst_0
    //   254: anewarray 55	java/lang/Class
    //   257: invokevirtual 59	java/lang/Class:getMethod	(Ljava/lang/String;[Ljava/lang/Class;)Ljava/lang/reflect/Method;
    //   260: astore 24
    //   262: iconst_0
    //   263: anewarray 61	java/lang/Object
    //   266: astore 25
    //   268: aload 24
    //   270: aconst_null
    //   271: aload 25
    //   273: invokevirtual 67	java/lang/reflect/Method:invoke	(Ljava/lang/Object;[Ljava/lang/Object;)Ljava/lang/Object;
    //   276: astore 27
    //   278: aload 27
    //   280: checkcast 69	java/lang/Integer
    //   283: invokevirtual 72	java/lang/Integer:intValue	()I
    //   286: putstatic 45	uuuuuu/yhyyyy:b0070p0070p0070007000700070p	I
    //   289: bipush 69
    //   291: putstatic 78	uuuuuu/yhyyyy:b00700070pp0070007000700070p	I
    //   294: ldc 2
    //   296: ldc -108
    //   298: sipush 234
    //   301: iconst_3
    //   302: invokestatic 53	xxxxxx/uxxxxx:bb00620062bb0062b0062b0062	(Ljava/lang/String;CC)Ljava/lang/String;
    //   305: iconst_0
    //   306: anewarray 55	java/lang/Class
    //   309: invokevirtual 59	java/lang/Class:getMethod	(Ljava/lang/String;[Ljava/lang/Class;)Ljava/lang/reflect/Method;
    //   312: astore 20
    //   314: iconst_0
    //   315: anewarray 61	java/lang/Object
    //   318: astore 21
    //   320: aload 20
    //   322: aconst_null
    //   323: aload 21
    //   325: invokevirtual 67	java/lang/reflect/Method:invoke	(Ljava/lang/Object;[Ljava/lang/Object;)Ljava/lang/Object;
    //   328: astore 23
    //   330: aload 23
    //   332: checkcast 69	java/lang/Integer
    //   335: invokevirtual 72	java/lang/Integer:intValue	()I
    //   338: putstatic 78	uuuuuu/yhyyyy:b00700070pp0070007000700070p	I
    //   341: aload_1
    //   342: aload_0
    //   343: getfield 27	uuuuuu/yhyyyy:bp0070pp0070007000700070p	Lcom/db/pwcc/dbmobile/model/securities/SecurityPosition;
    //   346: aload_0
    //   347: getfield 29	uuuuuu/yhyyyy:b0070ppp0070007000700070p	Ljava/lang/String;
    //   350: invokeinterface 151 3 0
    //   355: aload_1
    //   356: aload_0
    //   357: getfield 27	uuuuuu/yhyyyy:bp0070pp0070007000700070p	Lcom/db/pwcc/dbmobile/model/securities/SecurityPosition;
    //   360: invokeinterface 155 2 0
    //   365: getstatic 45	uuuuuu/yhyyyy:b0070p0070p0070007000700070p	I
    //   368: istore 18
    //   370: iload 18
    //   372: iload 18
    //   374: getstatic 78	uuuuuu/yhyyyy:b00700070pp0070007000700070p	I
    //   377: iadd
    //   378: imul
    //   379: getstatic 74	uuuuuu/yhyyyy:bpp0070p0070007000700070p	I
    //   382: irem
    //   383: tableswitch	default:+17->400, 0:+27->410
    //   400: bipush 92
    //   402: putstatic 45	uuuuuu/yhyyyy:b0070p0070p0070007000700070p	I
    //   405: bipush 74
    //   407: putstatic 78	uuuuuu/yhyyyy:b00700070pp0070007000700070p	I
    //   410: return
    //   411: astore 4
    //   413: aload 4
    //   415: invokevirtual 100	java/lang/reflect/InvocationTargetException:getCause	()Ljava/lang/Throwable;
    //   418: athrow
    //   419: astore 22
    //   421: aload 22
    //   423: invokevirtual 100	java/lang/reflect/InvocationTargetException:getCause	()Ljava/lang/Throwable;
    //   426: athrow
    //   427: astore 11
    //   429: aload 11
    //   431: invokevirtual 100	java/lang/reflect/InvocationTargetException:getCause	()Ljava/lang/Throwable;
    //   434: athrow
    //   435: astore 16
    //   437: aload 16
    //   439: invokevirtual 100	java/lang/reflect/InvocationTargetException:getCause	()Ljava/lang/Throwable;
    //   442: athrow
    //   443: astore 26
    //   445: aload 26
    //   447: invokevirtual 100	java/lang/reflect/InvocationTargetException:getCause	()Ljava/lang/Throwable;
    //   450: athrow
    // Local variable table:
    //   start	length	slot	name	signature
    //   0	451	0	this	yhyyyy
    //   0	451	1	paramHhyyyy	yhhyyy.hhyyyy
    //   23	7	2	localMethod1	java.lang.reflect.Method
    //   28	4	3	arrayOfObject1	Object[]
    //   411	3	4	localInvocationTargetException1	java.lang.reflect.InvocationTargetException
    //   35	3	5	localObject1	Object
    //   45	11	6	i	int
    //   60	126	7	j	int
    //   73	52	8	k	int
    //   96	9	9	localMethod2	java.lang.reflect.Method
    //   102	6	10	arrayOfObject2	Object[]
    //   427	3	11	localInvocationTargetException2	java.lang.reflect.InvocationTargetException
    //   112	5	12	localObject2	Object
    //   125	48	13	m	int
    //   144	9	14	localMethod3	java.lang.reflect.Method
    //   150	6	15	arrayOfObject3	Object[]
    //   435	3	16	localInvocationTargetException3	java.lang.reflect.InvocationTargetException
    //   160	5	17	localObject3	Object
    //   368	11	18	n	int
    //   207	11	19	i1	int
    //   312	9	20	localMethod4	java.lang.reflect.Method
    //   318	6	21	arrayOfObject4	Object[]
    //   419	3	22	localInvocationTargetException4	java.lang.reflect.InvocationTargetException
    //   328	3	23	localObject4	Object
    //   260	9	24	localMethod5	java.lang.reflect.Method
    //   266	6	25	arrayOfObject5	Object[]
    //   443	3	26	localInvocationTargetException5	java.lang.reflect.InvocationTargetException
    //   276	3	27	localObject5	Object
    // Exception table:
    //   from	to	target	type
    //   29	37	411	java/lang/reflect/InvocationTargetException
    //   320	330	419	java/lang/reflect/InvocationTargetException
    //   104	114	427	java/lang/reflect/InvocationTargetException
    //   152	162	435	java/lang/reflect/InvocationTargetException
    //   268	278	443	java/lang/reflect/InvocationTargetException
  }
  
  /* Error */
  public boolean booo006F006F006F006Fooo(String paramString)
  {
    // Byte code:
    //   0: aload_1
    //   1: ifnull +478 -> 479
    //   4: ldc -98
    //   6: bipush 27
    //   8: bipush 12
    //   10: iconst_3
    //   11: invokestatic 84	xxxxxx/uxxxxx:bbbb0062b0062b0062b0062	(Ljava/lang/String;CCC)Ljava/lang/String;
    //   14: astore_2
    //   15: iconst_4
    //   16: anewarray 55	java/lang/Class
    //   19: astore_3
    //   20: aload_3
    //   21: iconst_0
    //   22: ldc 40
    //   24: aastore
    //   25: aload_3
    //   26: iconst_1
    //   27: getstatic 164	java/lang/Character:TYPE	Ljava/lang/Class;
    //   30: aastore
    //   31: aload_3
    //   32: iconst_2
    //   33: getstatic 164	java/lang/Character:TYPE	Ljava/lang/Class;
    //   36: aastore
    //   37: aload_3
    //   38: iconst_3
    //   39: getstatic 164	java/lang/Character:TYPE	Ljava/lang/Class;
    //   42: aastore
    //   43: ldc -90
    //   45: aload_2
    //   46: aload_3
    //   47: invokevirtual 59	java/lang/Class:getMethod	(Ljava/lang/String;[Ljava/lang/Class;)Ljava/lang/reflect/Method;
    //   50: astore 4
    //   52: iconst_4
    //   53: anewarray 61	java/lang/Object
    //   56: astore 5
    //   58: aload 5
    //   60: iconst_0
    //   61: ldc -88
    //   63: aastore
    //   64: aload 5
    //   66: iconst_1
    //   67: bipush 106
    //   69: invokestatic 172	java/lang/Character:valueOf	(C)Ljava/lang/Character;
    //   72: aastore
    //   73: aload 5
    //   75: iconst_2
    //   76: bipush 84
    //   78: invokestatic 172	java/lang/Character:valueOf	(C)Ljava/lang/Character;
    //   81: aastore
    //   82: aload 5
    //   84: iconst_3
    //   85: iconst_1
    //   86: invokestatic 172	java/lang/Character:valueOf	(C)Ljava/lang/Character;
    //   89: aastore
    //   90: aload 4
    //   92: aconst_null
    //   93: aload 5
    //   95: invokevirtual 67	java/lang/reflect/Method:invoke	(Ljava/lang/Object;[Ljava/lang/Object;)Ljava/lang/Object;
    //   98: astore 7
    //   100: aload 7
    //   102: checkcast 40	java/lang/String
    //   105: aload_1
    //   106: invokevirtual 110	java/lang/String:equals	(Ljava/lang/Object;)Z
    //   109: ifne +370 -> 479
    //   112: getstatic 45	uuuuuu/yhyyyy:b0070p0070p0070007000700070p	I
    //   115: getstatic 78	uuuuuu/yhyyyy:b00700070pp0070007000700070p	I
    //   118: iadd
    //   119: istore 8
    //   121: getstatic 45	uuuuuu/yhyyyy:b0070p0070p0070007000700070p	I
    //   124: istore 9
    //   126: iload 9
    //   128: iload 9
    //   130: getstatic 78	uuuuuu/yhyyyy:b00700070pp0070007000700070p	I
    //   133: iadd
    //   134: imul
    //   135: getstatic 74	uuuuuu/yhyyyy:bpp0070p0070007000700070p	I
    //   138: irem
    //   139: tableswitch	default:+17->156, 0:+110->249
    //   156: ldc 2
    //   158: ldc -82
    //   160: bipush 26
    //   162: iconst_4
    //   163: invokestatic 53	xxxxxx/uxxxxx:bb00620062bb0062b0062b0062	(Ljava/lang/String;CC)Ljava/lang/String;
    //   166: iconst_0
    //   167: anewarray 55	java/lang/Class
    //   170: invokevirtual 59	java/lang/Class:getMethod	(Ljava/lang/String;[Ljava/lang/Class;)Ljava/lang/reflect/Method;
    //   173: astore 19
    //   175: iconst_0
    //   176: anewarray 61	java/lang/Object
    //   179: astore 20
    //   181: aload 19
    //   183: aconst_null
    //   184: aload 20
    //   186: invokevirtual 67	java/lang/reflect/Method:invoke	(Ljava/lang/Object;[Ljava/lang/Object;)Ljava/lang/Object;
    //   189: astore 22
    //   191: aload 22
    //   193: checkcast 69	java/lang/Integer
    //   196: invokevirtual 72	java/lang/Integer:intValue	()I
    //   199: putstatic 45	uuuuuu/yhyyyy:b0070p0070p0070007000700070p	I
    //   202: ldc 2
    //   204: ldc -80
    //   206: sipush 252
    //   209: iconst_2
    //   210: invokestatic 53	xxxxxx/uxxxxx:bb00620062bb0062b0062b0062	(Ljava/lang/String;CC)Ljava/lang/String;
    //   213: iconst_0
    //   214: anewarray 55	java/lang/Class
    //   217: invokevirtual 59	java/lang/Class:getMethod	(Ljava/lang/String;[Ljava/lang/Class;)Ljava/lang/reflect/Method;
    //   220: astore 23
    //   222: iconst_0
    //   223: anewarray 61	java/lang/Object
    //   226: astore 24
    //   228: aload 23
    //   230: aconst_null
    //   231: aload 24
    //   233: invokevirtual 67	java/lang/reflect/Method:invoke	(Ljava/lang/Object;[Ljava/lang/Object;)Ljava/lang/Object;
    //   236: astore 26
    //   238: aload 26
    //   240: checkcast 69	java/lang/Integer
    //   243: invokevirtual 72	java/lang/Integer:intValue	()I
    //   246: putstatic 86	uuuuuu/yhyyyy:bp00700070p0070007000700070p	I
    //   249: iload 8
    //   251: getstatic 45	uuuuuu/yhyyyy:b0070p0070p0070007000700070p	I
    //   254: imul
    //   255: getstatic 74	uuuuuu/yhyyyy:bpp0070p0070007000700070p	I
    //   258: irem
    //   259: getstatic 86	uuuuuu/yhyyyy:bp00700070p0070007000700070p	I
    //   262: if_icmpeq +219 -> 481
    //   265: ldc 2
    //   267: ldc -78
    //   269: sipush 209
    //   272: iconst_1
    //   273: invokestatic 53	xxxxxx/uxxxxx:bb00620062bb0062b0062b0062	(Ljava/lang/String;CC)Ljava/lang/String;
    //   276: iconst_0
    //   277: anewarray 55	java/lang/Class
    //   280: invokevirtual 59	java/lang/Class:getMethod	(Ljava/lang/String;[Ljava/lang/Class;)Ljava/lang/reflect/Method;
    //   283: astore 10
    //   285: iconst_0
    //   286: anewarray 61	java/lang/Object
    //   289: astore 11
    //   291: aload 10
    //   293: aconst_null
    //   294: aload 11
    //   296: invokevirtual 67	java/lang/reflect/Method:invoke	(Ljava/lang/Object;[Ljava/lang/Object;)Ljava/lang/Object;
    //   299: astore 13
    //   301: aload 13
    //   303: checkcast 69	java/lang/Integer
    //   306: invokevirtual 72	java/lang/Integer:intValue	()I
    //   309: putstatic 45	uuuuuu/yhyyyy:b0070p0070p0070007000700070p	I
    //   312: ldc 2
    //   314: ldc -76
    //   316: bipush 104
    //   318: iconst_2
    //   319: invokestatic 53	xxxxxx/uxxxxx:bb00620062bb0062b0062b0062	(Ljava/lang/String;CC)Ljava/lang/String;
    //   322: iconst_0
    //   323: anewarray 55	java/lang/Class
    //   326: invokevirtual 59	java/lang/Class:getMethod	(Ljava/lang/String;[Ljava/lang/Class;)Ljava/lang/reflect/Method;
    //   329: astore 14
    //   331: iconst_0
    //   332: anewarray 61	java/lang/Object
    //   335: astore 15
    //   337: aload 14
    //   339: aconst_null
    //   340: aload 15
    //   342: invokevirtual 67	java/lang/reflect/Method:invoke	(Ljava/lang/Object;[Ljava/lang/Object;)Ljava/lang/Object;
    //   345: astore 17
    //   347: aload 17
    //   349: checkcast 69	java/lang/Integer
    //   352: invokevirtual 72	java/lang/Integer:intValue	()I
    //   355: putstatic 86	uuuuuu/yhyyyy:bp00700070p0070007000700070p	I
    //   358: getstatic 45	uuuuuu/yhyyyy:b0070p0070p0070007000700070p	I
    //   361: istore 18
    //   363: iload 18
    //   365: iload 18
    //   367: getstatic 78	uuuuuu/yhyyyy:b00700070pp0070007000700070p	I
    //   370: iadd
    //   371: imul
    //   372: getstatic 74	uuuuuu/yhyyyy:bpp0070p0070007000700070p	I
    //   375: irem
    //   376: tableswitch	default:+20->396, 0:+105->481
    //   396: bipush 93
    //   398: putstatic 45	uuuuuu/yhyyyy:b0070p0070p0070007000700070p	I
    //   401: bipush 26
    //   403: putstatic 86	uuuuuu/yhyyyy:bp00700070p0070007000700070p	I
    //   406: getstatic 45	uuuuuu/yhyyyy:b0070p0070p0070007000700070p	I
    //   409: getstatic 78	uuuuuu/yhyyyy:b00700070pp0070007000700070p	I
    //   412: iadd
    //   413: getstatic 45	uuuuuu/yhyyyy:b0070p0070p0070007000700070p	I
    //   416: imul
    //   417: getstatic 74	uuuuuu/yhyyyy:bpp0070p0070007000700070p	I
    //   420: irem
    //   421: getstatic 86	uuuuuu/yhyyyy:bp00700070p0070007000700070p	I
    //   424: if_icmpeq +57 -> 481
    //   427: bipush 69
    //   429: putstatic 45	uuuuuu/yhyyyy:b0070p0070p0070007000700070p	I
    //   432: bipush 94
    //   434: putstatic 86	uuuuuu/yhyyyy:bp00700070p0070007000700070p	I
    //   437: iconst_1
    //   438: ireturn
    //   439: astore 12
    //   441: aload 12
    //   443: invokevirtual 100	java/lang/reflect/InvocationTargetException:getCause	()Ljava/lang/Throwable;
    //   446: athrow
    //   447: astore 6
    //   449: aload 6
    //   451: invokevirtual 100	java/lang/reflect/InvocationTargetException:getCause	()Ljava/lang/Throwable;
    //   454: athrow
    //   455: astore 21
    //   457: aload 21
    //   459: invokevirtual 100	java/lang/reflect/InvocationTargetException:getCause	()Ljava/lang/Throwable;
    //   462: athrow
    //   463: astore 25
    //   465: aload 25
    //   467: invokevirtual 100	java/lang/reflect/InvocationTargetException:getCause	()Ljava/lang/Throwable;
    //   470: athrow
    //   471: astore 16
    //   473: aload 16
    //   475: invokevirtual 100	java/lang/reflect/InvocationTargetException:getCause	()Ljava/lang/Throwable;
    //   478: athrow
    //   479: iconst_0
    //   480: ireturn
    //   481: iconst_1
    //   482: ireturn
    // Local variable table:
    //   start	length	slot	name	signature
    //   0	483	0	this	yhyyyy
    //   0	483	1	paramString	String
    //   14	32	2	str	String
    //   19	28	3	arrayOfClass	Class[]
    //   50	41	4	localMethod1	java.lang.reflect.Method
    //   56	38	5	arrayOfObject1	Object[]
    //   447	3	6	localInvocationTargetException1	java.lang.reflect.InvocationTargetException
    //   98	3	7	localObject1	Object
    //   119	136	8	i	int
    //   124	11	9	j	int
    //   283	9	10	localMethod2	java.lang.reflect.Method
    //   289	6	11	arrayOfObject2	Object[]
    //   439	3	12	localInvocationTargetException2	java.lang.reflect.InvocationTargetException
    //   299	3	13	localObject2	Object
    //   329	9	14	localMethod3	java.lang.reflect.Method
    //   335	6	15	arrayOfObject3	Object[]
    //   471	3	16	localInvocationTargetException3	java.lang.reflect.InvocationTargetException
    //   345	3	17	localObject3	Object
    //   361	11	18	k	int
    //   173	9	19	localMethod4	java.lang.reflect.Method
    //   179	6	20	arrayOfObject4	Object[]
    //   455	3	21	localInvocationTargetException4	java.lang.reflect.InvocationTargetException
    //   189	3	22	localObject4	Object
    //   220	9	23	localMethod5	java.lang.reflect.Method
    //   226	6	24	arrayOfObject5	Object[]
    //   463	3	25	localInvocationTargetException5	java.lang.reflect.InvocationTargetException
    //   236	3	26	localObject5	Object
    // Exception table:
    //   from	to	target	type
    //   291	301	439	java/lang/reflect/InvocationTargetException
    //   90	100	447	java/lang/reflect/InvocationTargetException
    //   181	191	455	java/lang/reflect/InvocationTargetException
    //   228	238	463	java/lang/reflect/InvocationTargetException
    //   337	347	471	java/lang/reflect/InvocationTargetException
  }
}
