package uuuuuu;

import javax.inject.Inject;

public class ytyyyt
  implements ttttty.yyyyyt, vvpvvp.ppvvvp
{
  public static int b007800780078xx0078xx0078 = 2;
  public static int b0078xx0078x0078xx0078 = 0;
  public static int bx00780078xx0078xx0078 = 1;
  private static final String bx0078xxx0078xx0078;
  public static int bxxx0078x0078xx0078 = 82;
  @Inject
  public yttttt b00780078xxx0078xx0078;
  private ttttty.tyyyyt b0078x0078xx0078xx0078;
  public mffffm bxx0078xx0078xx0078;
  
  /* Error */
  static
  {
    // Byte code:
    //   0: ldc 2
    //   2: invokevirtual 36	java/lang/Class:getSimpleName	()Ljava/lang/String;
    //   5: astore_0
    //   6: ldc 2
    //   8: ldc 38
    //   10: sipush 237
    //   13: sipush 177
    //   16: iconst_3
    //   17: invokestatic 44	xxxxxx/uxxxxx:bbbb0062b0062b0062b0062	(Ljava/lang/String;CCC)Ljava/lang/String;
    //   20: iconst_0
    //   21: anewarray 32	java/lang/Class
    //   24: invokevirtual 48	java/lang/Class:getMethod	(Ljava/lang/String;[Ljava/lang/Class;)Ljava/lang/reflect/Method;
    //   27: astore_1
    //   28: iconst_0
    //   29: anewarray 4	java/lang/Object
    //   32: astore_2
    //   33: aload_1
    //   34: aconst_null
    //   35: aload_2
    //   36: invokevirtual 54	java/lang/reflect/Method:invoke	(Ljava/lang/Object;[Ljava/lang/Object;)Ljava/lang/Object;
    //   39: astore 4
    //   41: aload 4
    //   43: checkcast 56	java/lang/Integer
    //   46: invokevirtual 60	java/lang/Integer:intValue	()I
    //   49: getstatic 62	uuuuuu/ytyyyt:bx00780078xx0078xx0078	I
    //   52: iadd
    //   53: istore 5
    //   55: ldc 2
    //   57: ldc 64
    //   59: bipush 59
    //   61: iconst_1
    //   62: invokestatic 68	xxxxxx/uxxxxx:bb00620062bb0062b0062b0062	(Ljava/lang/String;CC)Ljava/lang/String;
    //   65: iconst_0
    //   66: anewarray 32	java/lang/Class
    //   69: invokevirtual 48	java/lang/Class:getMethod	(Ljava/lang/String;[Ljava/lang/Class;)Ljava/lang/reflect/Method;
    //   72: astore 6
    //   74: iconst_0
    //   75: anewarray 4	java/lang/Object
    //   78: astore 7
    //   80: aload 6
    //   82: aconst_null
    //   83: aload 7
    //   85: invokevirtual 54	java/lang/reflect/Method:invoke	(Ljava/lang/Object;[Ljava/lang/Object;)Ljava/lang/Object;
    //   88: astore 9
    //   90: iload 5
    //   92: aload 9
    //   94: checkcast 56	java/lang/Integer
    //   97: invokevirtual 60	java/lang/Integer:intValue	()I
    //   100: imul
    //   101: getstatic 70	uuuuuu/ytyyyt:b007800780078xx0078xx0078	I
    //   104: irem
    //   105: istore 10
    //   107: ldc 2
    //   109: ldc 72
    //   111: bipush 17
    //   113: bipush 10
    //   115: iconst_2
    //   116: invokestatic 44	xxxxxx/uxxxxx:bbbb0062b0062b0062b0062	(Ljava/lang/String;CCC)Ljava/lang/String;
    //   119: iconst_0
    //   120: anewarray 32	java/lang/Class
    //   123: invokevirtual 48	java/lang/Class:getMethod	(Ljava/lang/String;[Ljava/lang/Class;)Ljava/lang/reflect/Method;
    //   126: astore 11
    //   128: iconst_0
    //   129: anewarray 4	java/lang/Object
    //   132: astore 12
    //   134: aload 11
    //   136: aconst_null
    //   137: aload 12
    //   139: invokevirtual 54	java/lang/reflect/Method:invoke	(Ljava/lang/Object;[Ljava/lang/Object;)Ljava/lang/Object;
    //   142: astore 14
    //   144: iload 10
    //   146: aload 14
    //   148: checkcast 56	java/lang/Integer
    //   151: invokevirtual 60	java/lang/Integer:intValue	()I
    //   154: if_icmpeq +304 -> 458
    //   157: getstatic 74	uuuuuu/ytyyyt:bxxx0078x0078xx0078	I
    //   160: istore 15
    //   162: ldc 2
    //   164: ldc 76
    //   166: sipush 154
    //   169: iconst_1
    //   170: invokestatic 68	xxxxxx/uxxxxx:bb00620062bb0062b0062b0062	(Ljava/lang/String;CC)Ljava/lang/String;
    //   173: iconst_0
    //   174: anewarray 32	java/lang/Class
    //   177: invokevirtual 48	java/lang/Class:getMethod	(Ljava/lang/String;[Ljava/lang/Class;)Ljava/lang/reflect/Method;
    //   180: astore 16
    //   182: iconst_0
    //   183: anewarray 4	java/lang/Object
    //   186: astore 17
    //   188: aload 16
    //   190: aconst_null
    //   191: aload 17
    //   193: invokevirtual 54	java/lang/reflect/Method:invoke	(Ljava/lang/Object;[Ljava/lang/Object;)Ljava/lang/Object;
    //   196: astore 19
    //   198: iload 15
    //   200: aload 19
    //   202: checkcast 56	java/lang/Integer
    //   205: invokevirtual 60	java/lang/Integer:intValue	()I
    //   208: iadd
    //   209: getstatic 74	uuuuuu/ytyyyt:bxxx0078x0078xx0078	I
    //   212: imul
    //   213: getstatic 70	uuuuuu/ytyyyt:b007800780078xx0078xx0078	I
    //   216: irem
    //   217: getstatic 78	uuuuuu/ytyyyt:b0078xx0078x0078xx0078	I
    //   220: if_icmpeq +96 -> 316
    //   223: ldc 2
    //   225: ldc 80
    //   227: bipush 120
    //   229: iconst_4
    //   230: invokestatic 68	xxxxxx/uxxxxx:bb00620062bb0062b0062b0062	(Ljava/lang/String;CC)Ljava/lang/String;
    //   233: iconst_0
    //   234: anewarray 32	java/lang/Class
    //   237: invokevirtual 48	java/lang/Class:getMethod	(Ljava/lang/String;[Ljava/lang/Class;)Ljava/lang/reflect/Method;
    //   240: astore 26
    //   242: iconst_0
    //   243: anewarray 4	java/lang/Object
    //   246: astore 27
    //   248: aload 26
    //   250: aconst_null
    //   251: aload 27
    //   253: invokevirtual 54	java/lang/reflect/Method:invoke	(Ljava/lang/Object;[Ljava/lang/Object;)Ljava/lang/Object;
    //   256: astore 29
    //   258: aload 29
    //   260: checkcast 56	java/lang/Integer
    //   263: invokevirtual 60	java/lang/Integer:intValue	()I
    //   266: putstatic 74	uuuuuu/ytyyyt:bxxx0078x0078xx0078	I
    //   269: ldc 2
    //   271: ldc 82
    //   273: sipush 212
    //   276: iconst_3
    //   277: invokestatic 68	xxxxxx/uxxxxx:bb00620062bb0062b0062b0062	(Ljava/lang/String;CC)Ljava/lang/String;
    //   280: iconst_0
    //   281: anewarray 32	java/lang/Class
    //   284: invokevirtual 48	java/lang/Class:getMethod	(Ljava/lang/String;[Ljava/lang/Class;)Ljava/lang/reflect/Method;
    //   287: astore 30
    //   289: iconst_0
    //   290: anewarray 4	java/lang/Object
    //   293: astore 31
    //   295: aload 30
    //   297: aconst_null
    //   298: aload 31
    //   300: invokevirtual 54	java/lang/reflect/Method:invoke	(Ljava/lang/Object;[Ljava/lang/Object;)Ljava/lang/Object;
    //   303: astore 33
    //   305: aload 33
    //   307: checkcast 56	java/lang/Integer
    //   310: invokevirtual 60	java/lang/Integer:intValue	()I
    //   313: putstatic 78	uuuuuu/ytyyyt:b0078xx0078x0078xx0078	I
    //   316: bipush 53
    //   318: putstatic 62	uuuuuu/ytyyyt:bx00780078xx0078xx0078	I
    //   321: getstatic 74	uuuuuu/ytyyyt:bxxx0078x0078xx0078	I
    //   324: istore 20
    //   326: getstatic 74	uuuuuu/ytyyyt:bxxx0078x0078xx0078	I
    //   329: istore 21
    //   331: iload 21
    //   333: iload 21
    //   335: getstatic 62	uuuuuu/ytyyyt:bx00780078xx0078xx0078	I
    //   338: iadd
    //   339: imul
    //   340: getstatic 70	uuuuuu/ytyyyt:b007800780078xx0078xx0078	I
    //   343: irem
    //   344: tableswitch	default:+20->364, 0:+71->415
    //   364: bipush 72
    //   366: putstatic 74	uuuuuu/ytyyyt:bxxx0078x0078xx0078	I
    //   369: ldc 2
    //   371: ldc 84
    //   373: bipush 75
    //   375: iconst_1
    //   376: invokestatic 68	xxxxxx/uxxxxx:bb00620062bb0062b0062b0062	(Ljava/lang/String;CC)Ljava/lang/String;
    //   379: iconst_0
    //   380: anewarray 32	java/lang/Class
    //   383: invokevirtual 48	java/lang/Class:getMethod	(Ljava/lang/String;[Ljava/lang/Class;)Ljava/lang/reflect/Method;
    //   386: astore 22
    //   388: iconst_0
    //   389: anewarray 4	java/lang/Object
    //   392: astore 23
    //   394: aload 22
    //   396: aconst_null
    //   397: aload 23
    //   399: invokevirtual 54	java/lang/reflect/Method:invoke	(Ljava/lang/Object;[Ljava/lang/Object;)Ljava/lang/Object;
    //   402: astore 25
    //   404: aload 25
    //   406: checkcast 56	java/lang/Integer
    //   409: invokevirtual 60	java/lang/Integer:intValue	()I
    //   412: putstatic 78	uuuuuu/ytyyyt:b0078xx0078x0078xx0078	I
    //   415: iload 20
    //   417: iload 20
    //   419: getstatic 62	uuuuuu/ytyyyt:bx00780078xx0078xx0078	I
    //   422: iadd
    //   423: imul
    //   424: getstatic 70	uuuuuu/ytyyyt:b007800780078xx0078xx0078	I
    //   427: irem
    //   428: tableswitch	default:+20->448, 0:+30->458
    //   448: bipush 84
    //   450: putstatic 74	uuuuuu/ytyyyt:bxxx0078x0078xx0078	I
    //   453: bipush 22
    //   455: putstatic 62	uuuuuu/ytyyyt:bx00780078xx0078xx0078	I
    //   458: aload_0
    //   459: putstatic 86	uuuuuu/ytyyyt:bx0078xxx0078xx0078	Ljava/lang/String;
    //   462: return
    //   463: astore 13
    //   465: aload 13
    //   467: invokevirtual 90	java/lang/reflect/InvocationTargetException:getCause	()Ljava/lang/Throwable;
    //   470: athrow
    //   471: astore 18
    //   473: aload 18
    //   475: invokevirtual 90	java/lang/reflect/InvocationTargetException:getCause	()Ljava/lang/Throwable;
    //   478: athrow
    //   479: astore 28
    //   481: aload 28
    //   483: invokevirtual 90	java/lang/reflect/InvocationTargetException:getCause	()Ljava/lang/Throwable;
    //   486: athrow
    //   487: astore 32
    //   489: aload 32
    //   491: invokevirtual 90	java/lang/reflect/InvocationTargetException:getCause	()Ljava/lang/Throwable;
    //   494: athrow
    //   495: astore_3
    //   496: aload_3
    //   497: invokevirtual 90	java/lang/reflect/InvocationTargetException:getCause	()Ljava/lang/Throwable;
    //   500: athrow
    //   501: astore 8
    //   503: aload 8
    //   505: invokevirtual 90	java/lang/reflect/InvocationTargetException:getCause	()Ljava/lang/Throwable;
    //   508: athrow
    //   509: astore 24
    //   511: aload 24
    //   513: invokevirtual 90	java/lang/reflect/InvocationTargetException:getCause	()Ljava/lang/Throwable;
    //   516: athrow
    // Local variable table:
    //   start	length	slot	name	signature
    //   5	454	0	str	String
    //   27	7	1	localMethod1	java.lang.reflect.Method
    //   32	4	2	arrayOfObject1	Object[]
    //   495	2	3	localInvocationTargetException1	java.lang.reflect.InvocationTargetException
    //   39	3	4	localObject1	Object
    //   53	48	5	i	int
    //   72	9	6	localMethod2	java.lang.reflect.Method
    //   78	6	7	arrayOfObject2	Object[]
    //   501	3	8	localInvocationTargetException2	java.lang.reflect.InvocationTargetException
    //   88	5	9	localObject2	Object
    //   105	50	10	j	int
    //   126	9	11	localMethod3	java.lang.reflect.Method
    //   132	6	12	arrayOfObject3	Object[]
    //   463	3	13	localInvocationTargetException3	java.lang.reflect.InvocationTargetException
    //   142	5	14	localObject3	Object
    //   160	49	15	k	int
    //   180	9	16	localMethod4	java.lang.reflect.Method
    //   186	6	17	arrayOfObject4	Object[]
    //   471	3	18	localInvocationTargetException4	java.lang.reflect.InvocationTargetException
    //   196	5	19	localObject4	Object
    //   324	100	20	m	int
    //   329	11	21	n	int
    //   386	9	22	localMethod5	java.lang.reflect.Method
    //   392	6	23	arrayOfObject5	Object[]
    //   509	3	24	localInvocationTargetException5	java.lang.reflect.InvocationTargetException
    //   402	3	25	localObject5	Object
    //   240	9	26	localMethod6	java.lang.reflect.Method
    //   246	6	27	arrayOfObject6	Object[]
    //   479	3	28	localInvocationTargetException6	java.lang.reflect.InvocationTargetException
    //   256	3	29	localObject6	Object
    //   287	9	30	localMethod7	java.lang.reflect.Method
    //   293	6	31	arrayOfObject7	Object[]
    //   487	3	32	localInvocationTargetException7	java.lang.reflect.InvocationTargetException
    //   303	3	33	localObject7	Object
    // Exception table:
    //   from	to	target	type
    //   134	144	463	java/lang/reflect/InvocationTargetException
    //   188	198	471	java/lang/reflect/InvocationTargetException
    //   248	258	479	java/lang/reflect/InvocationTargetException
    //   295	305	487	java/lang/reflect/InvocationTargetException
    //   33	41	495	java/lang/reflect/InvocationTargetException
    //   80	90	501	java/lang/reflect/InvocationTargetException
    //   394	404	509	java/lang/reflect/InvocationTargetException
  }
  
  public ytyyyt(ttttty.tyyyyt paramTyyyyt)
  {
    tttyyt.bq0071qqqqq007100710071().bpppp0070ppppp(this);
    this.b0078x0078xx0078xx0078 = paramTyyyyt;
    this.bxx0078xx0078xx0078 = new mffffm();
  }
  
  public static int b007100710071q007100710071q00710071()
  {
    return 0;
  }
  
  public static int b0071q0071q007100710071q00710071()
  {
    return 1;
  }
  
  public static int bq00710071q007100710071q00710071()
  {
    return 99;
  }
  
  public static int bqqq0071007100710071q00710071()
  {
    return 2;
  }
  
  /* Error */
  public void b0061aa00610061aaa0061a(com.db.pwcc.dbmobile.model.profile.Profile paramProfile)
  {
    // Byte code:
    //   0: aload_1
    //   1: invokevirtual 124	com/db/pwcc/dbmobile/model/profile/Profile:getMandatorId	()Ljava/lang/String;
    //   4: invokevirtual 129	java/lang/String:toLowerCase	()Ljava/lang/String;
    //   7: astore_2
    //   8: ldc -125
    //   10: sipush 201
    //   13: bipush 101
    //   15: iconst_1
    //   16: invokestatic 44	xxxxxx/uxxxxx:bbbb0062b0062b0062b0062	(Ljava/lang/String;CCC)Ljava/lang/String;
    //   19: astore_3
    //   20: iconst_4
    //   21: anewarray 32	java/lang/Class
    //   24: astore 4
    //   26: aload 4
    //   28: iconst_0
    //   29: ldc 126
    //   31: aastore
    //   32: aload 4
    //   34: iconst_1
    //   35: getstatic 137	java/lang/Character:TYPE	Ljava/lang/Class;
    //   38: aastore
    //   39: aload 4
    //   41: iconst_2
    //   42: getstatic 137	java/lang/Character:TYPE	Ljava/lang/Class;
    //   45: aastore
    //   46: aload 4
    //   48: iconst_3
    //   49: getstatic 137	java/lang/Character:TYPE	Ljava/lang/Class;
    //   52: aastore
    //   53: ldc -117
    //   55: aload_3
    //   56: aload 4
    //   58: invokevirtual 48	java/lang/Class:getMethod	(Ljava/lang/String;[Ljava/lang/Class;)Ljava/lang/reflect/Method;
    //   61: astore 5
    //   63: iconst_4
    //   64: anewarray 4	java/lang/Object
    //   67: astore 6
    //   69: aload 6
    //   71: iconst_0
    //   72: ldc -115
    //   74: aastore
    //   75: aload 6
    //   77: iconst_1
    //   78: bipush 33
    //   80: invokestatic 145	java/lang/Character:valueOf	(C)Ljava/lang/Character;
    //   83: aastore
    //   84: aload 6
    //   86: iconst_2
    //   87: bipush 75
    //   89: invokestatic 145	java/lang/Character:valueOf	(C)Ljava/lang/Character;
    //   92: aastore
    //   93: aload 6
    //   95: iconst_3
    //   96: iconst_2
    //   97: invokestatic 145	java/lang/Character:valueOf	(C)Ljava/lang/Character;
    //   100: aastore
    //   101: aload 5
    //   103: aconst_null
    //   104: aload 6
    //   106: invokevirtual 54	java/lang/reflect/Method:invoke	(Ljava/lang/Object;[Ljava/lang/Object;)Ljava/lang/Object;
    //   109: astore 8
    //   111: aload_2
    //   112: aload 8
    //   114: checkcast 126	java/lang/String
    //   117: invokevirtual 149	java/lang/String:contains	(Ljava/lang/CharSequence;)Z
    //   120: ifeq +134 -> 254
    //   123: aload_0
    //   124: getfield 108	uuuuuu/ytyyyt:b0078x0078xx0078xx0078	Luuuuuu/ttttty$tyyyyt;
    //   127: astore 37
    //   129: ldc -105
    //   131: sipush 182
    //   134: iconst_0
    //   135: invokestatic 68	xxxxxx/uxxxxx:bb00620062bb0062b0062b0062	(Ljava/lang/String;CC)Ljava/lang/String;
    //   138: astore 38
    //   140: iconst_4
    //   141: anewarray 32	java/lang/Class
    //   144: astore 39
    //   146: aload 39
    //   148: iconst_0
    //   149: ldc 126
    //   151: aastore
    //   152: aload 39
    //   154: iconst_1
    //   155: getstatic 137	java/lang/Character:TYPE	Ljava/lang/Class;
    //   158: aastore
    //   159: aload 39
    //   161: iconst_2
    //   162: getstatic 137	java/lang/Character:TYPE	Ljava/lang/Class;
    //   165: aastore
    //   166: aload 39
    //   168: iconst_3
    //   169: getstatic 137	java/lang/Character:TYPE	Ljava/lang/Class;
    //   172: aastore
    //   173: ldc -117
    //   175: aload 38
    //   177: aload 39
    //   179: invokevirtual 48	java/lang/Class:getMethod	(Ljava/lang/String;[Ljava/lang/Class;)Ljava/lang/reflect/Method;
    //   182: astore 40
    //   184: iconst_4
    //   185: anewarray 4	java/lang/Object
    //   188: astore 41
    //   190: aload 41
    //   192: iconst_0
    //   193: ldc -103
    //   195: aastore
    //   196: aload 41
    //   198: iconst_1
    //   199: sipush 137
    //   202: invokestatic 145	java/lang/Character:valueOf	(C)Ljava/lang/Character;
    //   205: aastore
    //   206: aload 41
    //   208: iconst_2
    //   209: bipush 47
    //   211: invokestatic 145	java/lang/Character:valueOf	(C)Ljava/lang/Character;
    //   214: aastore
    //   215: aload 41
    //   217: iconst_3
    //   218: iconst_1
    //   219: invokestatic 145	java/lang/Character:valueOf	(C)Ljava/lang/Character;
    //   222: aastore
    //   223: aload 40
    //   225: aconst_null
    //   226: aload 41
    //   228: invokevirtual 54	java/lang/reflect/Method:invoke	(Ljava/lang/Object;[Ljava/lang/Object;)Ljava/lang/Object;
    //   231: astore 43
    //   233: aload 37
    //   235: aload 43
    //   237: checkcast 126	java/lang/String
    //   240: invokeinterface 159 2 0
    //   245: return
    //   246: astore 7
    //   248: aload 7
    //   250: invokevirtual 90	java/lang/reflect/InvocationTargetException:getCause	()Ljava/lang/Throwable;
    //   253: athrow
    //   254: aload_0
    //   255: getfield 108	uuuuuu/ytyyyt:b0078x0078xx0078xx0078	Luuuuuu/ttttty$tyyyyt;
    //   258: astore 9
    //   260: getstatic 74	uuuuuu/ytyyyt:bxxx0078x0078xx0078	I
    //   263: istore 10
    //   265: getstatic 62	uuuuuu/ytyyyt:bx00780078xx0078xx0078	I
    //   268: istore 11
    //   270: getstatic 74	uuuuuu/ytyyyt:bxxx0078x0078xx0078	I
    //   273: getstatic 62	uuuuuu/ytyyyt:bx00780078xx0078xx0078	I
    //   276: iadd
    //   277: getstatic 74	uuuuuu/ytyyyt:bxxx0078x0078xx0078	I
    //   280: imul
    //   281: getstatic 70	uuuuuu/ytyyyt:b007800780078xx0078xx0078	I
    //   284: irem
    //   285: getstatic 78	uuuuuu/ytyyyt:b0078xx0078x0078xx0078	I
    //   288: if_icmpeq +102 -> 390
    //   291: ldc 2
    //   293: ldc -95
    //   295: sipush 161
    //   298: sipush 172
    //   301: iconst_1
    //   302: invokestatic 44	xxxxxx/uxxxxx:bbbb0062b0062b0062b0062	(Ljava/lang/String;CCC)Ljava/lang/String;
    //   305: iconst_0
    //   306: anewarray 32	java/lang/Class
    //   309: invokevirtual 48	java/lang/Class:getMethod	(Ljava/lang/String;[Ljava/lang/Class;)Ljava/lang/reflect/Method;
    //   312: astore 29
    //   314: iconst_0
    //   315: anewarray 4	java/lang/Object
    //   318: astore 30
    //   320: aload 29
    //   322: aconst_null
    //   323: aload 30
    //   325: invokevirtual 54	java/lang/reflect/Method:invoke	(Ljava/lang/Object;[Ljava/lang/Object;)Ljava/lang/Object;
    //   328: astore 32
    //   330: aload 32
    //   332: checkcast 56	java/lang/Integer
    //   335: invokevirtual 60	java/lang/Integer:intValue	()I
    //   338: putstatic 74	uuuuuu/ytyyyt:bxxx0078x0078xx0078	I
    //   341: ldc 2
    //   343: ldc -93
    //   345: bipush 70
    //   347: sipush 240
    //   350: iconst_1
    //   351: invokestatic 44	xxxxxx/uxxxxx:bbbb0062b0062b0062b0062	(Ljava/lang/String;CCC)Ljava/lang/String;
    //   354: iconst_0
    //   355: anewarray 32	java/lang/Class
    //   358: invokevirtual 48	java/lang/Class:getMethod	(Ljava/lang/String;[Ljava/lang/Class;)Ljava/lang/reflect/Method;
    //   361: astore 33
    //   363: iconst_0
    //   364: anewarray 4	java/lang/Object
    //   367: astore 34
    //   369: aload 33
    //   371: aconst_null
    //   372: aload 34
    //   374: invokevirtual 54	java/lang/reflect/Method:invoke	(Ljava/lang/Object;[Ljava/lang/Object;)Ljava/lang/Object;
    //   377: astore 36
    //   379: aload 36
    //   381: checkcast 56	java/lang/Integer
    //   384: invokevirtual 60	java/lang/Integer:intValue	()I
    //   387: putstatic 78	uuuuuu/ytyyyt:b0078xx0078x0078xx0078	I
    //   390: iload 10
    //   392: iload 11
    //   394: iadd
    //   395: getstatic 74	uuuuuu/ytyyyt:bxxx0078x0078xx0078	I
    //   398: imul
    //   399: getstatic 70	uuuuuu/ytyyyt:b007800780078xx0078xx0078	I
    //   402: irem
    //   403: istore 12
    //   405: ldc 2
    //   407: ldc -91
    //   409: sipush 156
    //   412: bipush 15
    //   414: iconst_1
    //   415: invokestatic 44	xxxxxx/uxxxxx:bbbb0062b0062b0062b0062	(Ljava/lang/String;CCC)Ljava/lang/String;
    //   418: iconst_0
    //   419: anewarray 32	java/lang/Class
    //   422: invokevirtual 48	java/lang/Class:getMethod	(Ljava/lang/String;[Ljava/lang/Class;)Ljava/lang/reflect/Method;
    //   425: astore 13
    //   427: iconst_0
    //   428: anewarray 4	java/lang/Object
    //   431: astore 14
    //   433: aload 13
    //   435: aconst_null
    //   436: aload 14
    //   438: invokevirtual 54	java/lang/reflect/Method:invoke	(Ljava/lang/Object;[Ljava/lang/Object;)Ljava/lang/Object;
    //   441: astore 16
    //   443: iload 12
    //   445: aload 16
    //   447: checkcast 56	java/lang/Integer
    //   450: invokevirtual 60	java/lang/Integer:intValue	()I
    //   453: if_icmpeq +103 -> 556
    //   456: bipush 22
    //   458: putstatic 74	uuuuuu/ytyyyt:bxxx0078x0078xx0078	I
    //   461: bipush 33
    //   463: putstatic 78	uuuuuu/ytyyyt:b0078xx0078x0078xx0078	I
    //   466: getstatic 74	uuuuuu/ytyyyt:bxxx0078x0078xx0078	I
    //   469: istore 24
    //   471: iload 24
    //   473: iload 24
    //   475: getstatic 62	uuuuuu/ytyyyt:bx00780078xx0078xx0078	I
    //   478: iadd
    //   479: imul
    //   480: getstatic 70	uuuuuu/ytyyyt:b007800780078xx0078xx0078	I
    //   483: irem
    //   484: tableswitch	default:+20->504, 0:+72->556
    //   504: ldc 2
    //   506: ldc -89
    //   508: sipush 139
    //   511: iconst_4
    //   512: invokestatic 68	xxxxxx/uxxxxx:bb00620062bb0062b0062b0062	(Ljava/lang/String;CC)Ljava/lang/String;
    //   515: iconst_0
    //   516: anewarray 32	java/lang/Class
    //   519: invokevirtual 48	java/lang/Class:getMethod	(Ljava/lang/String;[Ljava/lang/Class;)Ljava/lang/reflect/Method;
    //   522: astore 25
    //   524: iconst_0
    //   525: anewarray 4	java/lang/Object
    //   528: astore 26
    //   530: aload 25
    //   532: aconst_null
    //   533: aload 26
    //   535: invokevirtual 54	java/lang/reflect/Method:invoke	(Ljava/lang/Object;[Ljava/lang/Object;)Ljava/lang/Object;
    //   538: astore 28
    //   540: aload 28
    //   542: checkcast 56	java/lang/Integer
    //   545: invokevirtual 60	java/lang/Integer:intValue	()I
    //   548: putstatic 74	uuuuuu/ytyyyt:bxxx0078x0078xx0078	I
    //   551: bipush 15
    //   553: putstatic 78	uuuuuu/ytyyyt:b0078xx0078x0078xx0078	I
    //   556: ldc -87
    //   558: sipush 140
    //   561: iconst_0
    //   562: invokestatic 68	xxxxxx/uxxxxx:bb00620062bb0062b0062b0062	(Ljava/lang/String;CC)Ljava/lang/String;
    //   565: astore 17
    //   567: iconst_3
    //   568: anewarray 32	java/lang/Class
    //   571: astore 18
    //   573: aload 18
    //   575: iconst_0
    //   576: ldc 126
    //   578: aastore
    //   579: aload 18
    //   581: iconst_1
    //   582: getstatic 137	java/lang/Character:TYPE	Ljava/lang/Class;
    //   585: aastore
    //   586: aload 18
    //   588: iconst_2
    //   589: getstatic 137	java/lang/Character:TYPE	Ljava/lang/Class;
    //   592: aastore
    //   593: ldc -117
    //   595: aload 17
    //   597: aload 18
    //   599: invokevirtual 48	java/lang/Class:getMethod	(Ljava/lang/String;[Ljava/lang/Class;)Ljava/lang/reflect/Method;
    //   602: astore 19
    //   604: iconst_3
    //   605: anewarray 4	java/lang/Object
    //   608: astore 20
    //   610: aload 20
    //   612: iconst_0
    //   613: ldc -85
    //   615: aastore
    //   616: aload 20
    //   618: iconst_1
    //   619: bipush 47
    //   621: invokestatic 145	java/lang/Character:valueOf	(C)Ljava/lang/Character;
    //   624: aastore
    //   625: aload 20
    //   627: iconst_2
    //   628: iconst_4
    //   629: invokestatic 145	java/lang/Character:valueOf	(C)Ljava/lang/Character;
    //   632: aastore
    //   633: aload 19
    //   635: aconst_null
    //   636: aload 20
    //   638: invokevirtual 54	java/lang/reflect/Method:invoke	(Ljava/lang/Object;[Ljava/lang/Object;)Ljava/lang/Object;
    //   641: astore 22
    //   643: aload 9
    //   645: aload 22
    //   647: checkcast 126	java/lang/String
    //   650: invokeinterface 159 2 0
    //   655: getstatic 74	uuuuuu/ytyyyt:bxxx0078x0078xx0078	I
    //   658: istore 23
    //   660: iload 23
    //   662: iload 23
    //   664: getstatic 62	uuuuuu/ytyyyt:bx00780078xx0078xx0078	I
    //   667: iadd
    //   668: imul
    //   669: getstatic 70	uuuuuu/ytyyyt:b007800780078xx0078xx0078	I
    //   672: irem
    //   673: tableswitch	default:+19->692, 0:+-428->245
    //   692: bipush 39
    //   694: putstatic 74	uuuuuu/ytyyyt:bxxx0078x0078xx0078	I
    //   697: bipush 86
    //   699: putstatic 78	uuuuuu/ytyyyt:b0078xx0078x0078xx0078	I
    //   702: return
    //   703: astore 42
    //   705: aload 42
    //   707: invokevirtual 90	java/lang/reflect/InvocationTargetException:getCause	()Ljava/lang/Throwable;
    //   710: athrow
    //   711: astore 21
    //   713: aload 21
    //   715: invokevirtual 90	java/lang/reflect/InvocationTargetException:getCause	()Ljava/lang/Throwable;
    //   718: athrow
    //   719: astore 27
    //   721: aload 27
    //   723: invokevirtual 90	java/lang/reflect/InvocationTargetException:getCause	()Ljava/lang/Throwable;
    //   726: athrow
    //   727: astore 15
    //   729: aload 15
    //   731: invokevirtual 90	java/lang/reflect/InvocationTargetException:getCause	()Ljava/lang/Throwable;
    //   734: athrow
    //   735: astore 31
    //   737: aload 31
    //   739: invokevirtual 90	java/lang/reflect/InvocationTargetException:getCause	()Ljava/lang/Throwable;
    //   742: athrow
    //   743: astore 35
    //   745: aload 35
    //   747: invokevirtual 90	java/lang/reflect/InvocationTargetException:getCause	()Ljava/lang/Throwable;
    //   750: athrow
    // Local variable table:
    //   start	length	slot	name	signature
    //   0	751	0	this	ytyyyt
    //   0	751	1	paramProfile	com.db.pwcc.dbmobile.model.profile.Profile
    //   7	105	2	str1	String
    //   19	37	3	str2	String
    //   24	33	4	arrayOfClass1	Class[]
    //   61	41	5	localMethod1	java.lang.reflect.Method
    //   67	38	6	arrayOfObject1	Object[]
    //   246	3	7	localInvocationTargetException1	java.lang.reflect.InvocationTargetException
    //   109	4	8	localObject1	Object
    //   258	386	9	localTyyyyt1	ttttty.tyyyyt
    //   263	132	10	i	int
    //   268	127	11	j	int
    //   403	51	12	k	int
    //   425	9	13	localMethod2	java.lang.reflect.Method
    //   431	6	14	arrayOfObject2	Object[]
    //   727	3	15	localInvocationTargetException2	java.lang.reflect.InvocationTargetException
    //   441	5	16	localObject2	Object
    //   565	31	17	str3	String
    //   571	27	18	arrayOfClass2	Class[]
    //   602	32	19	localMethod3	java.lang.reflect.Method
    //   608	29	20	arrayOfObject3	Object[]
    //   711	3	21	localInvocationTargetException3	java.lang.reflect.InvocationTargetException
    //   641	5	22	localObject3	Object
    //   658	11	23	m	int
    //   469	11	24	n	int
    //   522	9	25	localMethod4	java.lang.reflect.Method
    //   528	6	26	arrayOfObject4	Object[]
    //   719	3	27	localInvocationTargetException4	java.lang.reflect.InvocationTargetException
    //   538	3	28	localObject4	Object
    //   312	9	29	localMethod5	java.lang.reflect.Method
    //   318	6	30	arrayOfObject5	Object[]
    //   735	3	31	localInvocationTargetException5	java.lang.reflect.InvocationTargetException
    //   328	3	32	localObject5	Object
    //   361	9	33	localMethod6	java.lang.reflect.Method
    //   367	6	34	arrayOfObject6	Object[]
    //   743	3	35	localInvocationTargetException6	java.lang.reflect.InvocationTargetException
    //   377	3	36	localObject6	Object
    //   127	107	37	localTyyyyt2	ttttty.tyyyyt
    //   138	38	38	str4	String
    //   144	34	39	arrayOfClass3	Class[]
    //   182	42	40	localMethod7	java.lang.reflect.Method
    //   188	39	41	arrayOfObject7	Object[]
    //   703	3	42	localInvocationTargetException7	java.lang.reflect.InvocationTargetException
    //   231	5	43	localObject7	Object
    // Exception table:
    //   from	to	target	type
    //   101	111	246	java/lang/reflect/InvocationTargetException
    //   223	233	703	java/lang/reflect/InvocationTargetException
    //   633	643	711	java/lang/reflect/InvocationTargetException
    //   530	540	719	java/lang/reflect/InvocationTargetException
    //   433	443	727	java/lang/reflect/InvocationTargetException
    //   320	330	735	java/lang/reflect/InvocationTargetException
    //   369	379	743	java/lang/reflect/InvocationTargetException
  }
  
  /* Error */
  public void b00710071qq007100710071q00710071()
  {
    // Byte code:
    //   0: aload_0
    //   1: getfield 174	uuuuuu/ytyyyt:b00780078xxx0078xx0078	Luuuuuu/yttttt;
    //   4: invokeinterface 180 1 0
    //   9: ifeq +4 -> 13
    //   12: return
    //   13: aload_0
    //   14: getfield 174	uuuuuu/ytyyyt:b00780078xxx0078xx0078	Luuuuuu/yttttt;
    //   17: astore_1
    //   18: getstatic 74	uuuuuu/ytyyyt:bxxx0078x0078xx0078	I
    //   21: getstatic 62	uuuuuu/ytyyyt:bx00780078xx0078xx0078	I
    //   24: iadd
    //   25: istore_2
    //   26: getstatic 74	uuuuuu/ytyyyt:bxxx0078x0078xx0078	I
    //   29: istore_3
    //   30: getstatic 74	uuuuuu/ytyyyt:bxxx0078x0078xx0078	I
    //   33: getstatic 62	uuuuuu/ytyyyt:bx00780078xx0078xx0078	I
    //   36: iadd
    //   37: getstatic 74	uuuuuu/ytyyyt:bxxx0078x0078xx0078	I
    //   40: imul
    //   41: getstatic 70	uuuuuu/ytyyyt:b007800780078xx0078xx0078	I
    //   44: irem
    //   45: getstatic 78	uuuuuu/ytyyyt:b0078xx0078x0078xx0078	I
    //   48: if_icmpeq +12 -> 60
    //   51: iconst_1
    //   52: putstatic 74	uuuuuu/ytyyyt:bxxx0078x0078xx0078	I
    //   55: bipush 84
    //   57: putstatic 78	uuuuuu/ytyyyt:b0078xx0078x0078xx0078	I
    //   60: iload_2
    //   61: iload_3
    //   62: imul
    //   63: getstatic 70	uuuuuu/ytyyyt:b007800780078xx0078xx0078	I
    //   66: irem
    //   67: getstatic 78	uuuuuu/ytyyyt:b0078xx0078x0078xx0078	I
    //   70: if_icmpeq +400 -> 470
    //   73: ldc 2
    //   75: ldc -74
    //   77: sipush 203
    //   80: bipush 71
    //   82: iconst_3
    //   83: invokestatic 44	xxxxxx/uxxxxx:bbbb0062b0062b0062b0062	(Ljava/lang/String;CCC)Ljava/lang/String;
    //   86: iconst_0
    //   87: anewarray 32	java/lang/Class
    //   90: invokevirtual 48	java/lang/Class:getMethod	(Ljava/lang/String;[Ljava/lang/Class;)Ljava/lang/reflect/Method;
    //   93: astore 4
    //   95: iconst_0
    //   96: anewarray 4	java/lang/Object
    //   99: astore 5
    //   101: aload 4
    //   103: aconst_null
    //   104: aload 5
    //   106: invokevirtual 54	java/lang/reflect/Method:invoke	(Ljava/lang/Object;[Ljava/lang/Object;)Ljava/lang/Object;
    //   109: astore 7
    //   111: aload 7
    //   113: checkcast 56	java/lang/Integer
    //   116: invokevirtual 60	java/lang/Integer:intValue	()I
    //   119: getstatic 62	uuuuuu/ytyyyt:bx00780078xx0078xx0078	I
    //   122: iadd
    //   123: istore 8
    //   125: ldc 2
    //   127: ldc -72
    //   129: bipush 69
    //   131: sipush 176
    //   134: iconst_0
    //   135: invokestatic 44	xxxxxx/uxxxxx:bbbb0062b0062b0062b0062	(Ljava/lang/String;CCC)Ljava/lang/String;
    //   138: iconst_0
    //   139: anewarray 32	java/lang/Class
    //   142: invokevirtual 48	java/lang/Class:getMethod	(Ljava/lang/String;[Ljava/lang/Class;)Ljava/lang/reflect/Method;
    //   145: astore 9
    //   147: iconst_0
    //   148: anewarray 4	java/lang/Object
    //   151: astore 10
    //   153: aload 9
    //   155: aconst_null
    //   156: aload 10
    //   158: invokevirtual 54	java/lang/reflect/Method:invoke	(Ljava/lang/Object;[Ljava/lang/Object;)Ljava/lang/Object;
    //   161: astore 12
    //   163: iload 8
    //   165: aload 12
    //   167: checkcast 56	java/lang/Integer
    //   170: invokevirtual 60	java/lang/Integer:intValue	()I
    //   173: imul
    //   174: istore 13
    //   176: ldc 2
    //   178: ldc -70
    //   180: sipush 185
    //   183: sipush 192
    //   186: iconst_2
    //   187: invokestatic 44	xxxxxx/uxxxxx:bbbb0062b0062b0062b0062	(Ljava/lang/String;CCC)Ljava/lang/String;
    //   190: iconst_0
    //   191: anewarray 32	java/lang/Class
    //   194: invokevirtual 48	java/lang/Class:getMethod	(Ljava/lang/String;[Ljava/lang/Class;)Ljava/lang/reflect/Method;
    //   197: astore 14
    //   199: iconst_0
    //   200: anewarray 4	java/lang/Object
    //   203: astore 15
    //   205: aload 14
    //   207: aconst_null
    //   208: aload 15
    //   210: invokevirtual 54	java/lang/reflect/Method:invoke	(Ljava/lang/Object;[Ljava/lang/Object;)Ljava/lang/Object;
    //   213: astore 17
    //   215: iload 13
    //   217: aload 17
    //   219: checkcast 56	java/lang/Integer
    //   222: invokevirtual 60	java/lang/Integer:intValue	()I
    //   225: irem
    //   226: getstatic 78	uuuuuu/ytyyyt:b0078xx0078x0078xx0078	I
    //   229: if_icmpeq +96 -> 325
    //   232: ldc 2
    //   234: ldc -68
    //   236: sipush 183
    //   239: iconst_1
    //   240: invokestatic 68	xxxxxx/uxxxxx:bb00620062bb0062b0062b0062	(Ljava/lang/String;CC)Ljava/lang/String;
    //   243: iconst_0
    //   244: anewarray 32	java/lang/Class
    //   247: invokevirtual 48	java/lang/Class:getMethod	(Ljava/lang/String;[Ljava/lang/Class;)Ljava/lang/reflect/Method;
    //   250: astore 27
    //   252: iconst_0
    //   253: anewarray 4	java/lang/Object
    //   256: astore 28
    //   258: aload 27
    //   260: aconst_null
    //   261: aload 28
    //   263: invokevirtual 54	java/lang/reflect/Method:invoke	(Ljava/lang/Object;[Ljava/lang/Object;)Ljava/lang/Object;
    //   266: astore 30
    //   268: aload 30
    //   270: checkcast 56	java/lang/Integer
    //   273: invokevirtual 60	java/lang/Integer:intValue	()I
    //   276: putstatic 74	uuuuuu/ytyyyt:bxxx0078x0078xx0078	I
    //   279: ldc 2
    //   281: ldc -66
    //   283: bipush 41
    //   285: iconst_0
    //   286: invokestatic 68	xxxxxx/uxxxxx:bb00620062bb0062b0062b0062	(Ljava/lang/String;CC)Ljava/lang/String;
    //   289: iconst_0
    //   290: anewarray 32	java/lang/Class
    //   293: invokevirtual 48	java/lang/Class:getMethod	(Ljava/lang/String;[Ljava/lang/Class;)Ljava/lang/reflect/Method;
    //   296: astore 31
    //   298: iconst_0
    //   299: anewarray 4	java/lang/Object
    //   302: astore 32
    //   304: aload 31
    //   306: aconst_null
    //   307: aload 32
    //   309: invokevirtual 54	java/lang/reflect/Method:invoke	(Ljava/lang/Object;[Ljava/lang/Object;)Ljava/lang/Object;
    //   312: astore 34
    //   314: aload 34
    //   316: checkcast 56	java/lang/Integer
    //   319: invokevirtual 60	java/lang/Integer:intValue	()I
    //   322: putstatic 78	uuuuuu/ytyyyt:b0078xx0078x0078xx0078	I
    //   325: bipush 39
    //   327: putstatic 74	uuuuuu/ytyyyt:bxxx0078x0078xx0078	I
    //   330: bipush 95
    //   332: putstatic 78	uuuuuu/ytyyyt:b0078xx0078x0078xx0078	I
    //   335: getstatic 74	uuuuuu/ytyyyt:bxxx0078x0078xx0078	I
    //   338: istore 18
    //   340: iload 18
    //   342: iload 18
    //   344: getstatic 62	uuuuuu/ytyyyt:bx00780078xx0078xx0078	I
    //   347: iadd
    //   348: imul
    //   349: getstatic 70	uuuuuu/ytyyyt:b007800780078xx0078xx0078	I
    //   352: irem
    //   353: tableswitch	default:+19->372, 0:+117->470
    //   372: ldc 2
    //   374: ldc -64
    //   376: sipush 156
    //   379: bipush 56
    //   381: iconst_2
    //   382: invokestatic 44	xxxxxx/uxxxxx:bbbb0062b0062b0062b0062	(Ljava/lang/String;CCC)Ljava/lang/String;
    //   385: iconst_0
    //   386: anewarray 32	java/lang/Class
    //   389: invokevirtual 48	java/lang/Class:getMethod	(Ljava/lang/String;[Ljava/lang/Class;)Ljava/lang/reflect/Method;
    //   392: astore 19
    //   394: iconst_0
    //   395: anewarray 4	java/lang/Object
    //   398: astore 20
    //   400: aload 19
    //   402: aconst_null
    //   403: aload 20
    //   405: invokevirtual 54	java/lang/reflect/Method:invoke	(Ljava/lang/Object;[Ljava/lang/Object;)Ljava/lang/Object;
    //   408: astore 22
    //   410: aload 22
    //   412: checkcast 56	java/lang/Integer
    //   415: invokevirtual 60	java/lang/Integer:intValue	()I
    //   418: putstatic 74	uuuuuu/ytyyyt:bxxx0078x0078xx0078	I
    //   421: ldc 2
    //   423: ldc -62
    //   425: sipush 140
    //   428: bipush 81
    //   430: iconst_3
    //   431: invokestatic 44	xxxxxx/uxxxxx:bbbb0062b0062b0062b0062	(Ljava/lang/String;CCC)Ljava/lang/String;
    //   434: iconst_0
    //   435: anewarray 32	java/lang/Class
    //   438: invokevirtual 48	java/lang/Class:getMethod	(Ljava/lang/String;[Ljava/lang/Class;)Ljava/lang/reflect/Method;
    //   441: astore 23
    //   443: iconst_0
    //   444: anewarray 4	java/lang/Object
    //   447: astore 24
    //   449: aload 23
    //   451: aconst_null
    //   452: aload 24
    //   454: invokevirtual 54	java/lang/reflect/Method:invoke	(Ljava/lang/Object;[Ljava/lang/Object;)Ljava/lang/Object;
    //   457: astore 26
    //   459: aload 26
    //   461: checkcast 56	java/lang/Integer
    //   464: invokevirtual 60	java/lang/Integer:intValue	()I
    //   467: putstatic 78	uuuuuu/ytyyyt:b0078xx0078x0078xx0078	I
    //   470: aload_1
    //   471: invokeinterface 197 1 0
    //   476: return
    //   477: astore 6
    //   479: aload 6
    //   481: invokevirtual 90	java/lang/reflect/InvocationTargetException:getCause	()Ljava/lang/Throwable;
    //   484: athrow
    //   485: astore 11
    //   487: aload 11
    //   489: invokevirtual 90	java/lang/reflect/InvocationTargetException:getCause	()Ljava/lang/Throwable;
    //   492: athrow
    //   493: astore 16
    //   495: aload 16
    //   497: invokevirtual 90	java/lang/reflect/InvocationTargetException:getCause	()Ljava/lang/Throwable;
    //   500: athrow
    //   501: astore 21
    //   503: aload 21
    //   505: invokevirtual 90	java/lang/reflect/InvocationTargetException:getCause	()Ljava/lang/Throwable;
    //   508: athrow
    //   509: astore 25
    //   511: aload 25
    //   513: invokevirtual 90	java/lang/reflect/InvocationTargetException:getCause	()Ljava/lang/Throwable;
    //   516: athrow
    //   517: astore 29
    //   519: aload 29
    //   521: invokevirtual 90	java/lang/reflect/InvocationTargetException:getCause	()Ljava/lang/Throwable;
    //   524: athrow
    //   525: astore 33
    //   527: aload 33
    //   529: invokevirtual 90	java/lang/reflect/InvocationTargetException:getCause	()Ljava/lang/Throwable;
    //   532: athrow
    // Local variable table:
    //   start	length	slot	name	signature
    //   0	533	0	this	ytyyyt
    //   17	454	1	localYttttt	yttttt
    //   25	38	2	i	int
    //   29	34	3	j	int
    //   93	9	4	localMethod1	java.lang.reflect.Method
    //   99	6	5	arrayOfObject1	Object[]
    //   477	3	6	localInvocationTargetException1	java.lang.reflect.InvocationTargetException
    //   109	3	7	localObject1	Object
    //   123	51	8	k	int
    //   145	9	9	localMethod2	java.lang.reflect.Method
    //   151	6	10	arrayOfObject2	Object[]
    //   485	3	11	localInvocationTargetException2	java.lang.reflect.InvocationTargetException
    //   161	5	12	localObject2	Object
    //   174	52	13	m	int
    //   197	9	14	localMethod3	java.lang.reflect.Method
    //   203	6	15	arrayOfObject3	Object[]
    //   493	3	16	localInvocationTargetException3	java.lang.reflect.InvocationTargetException
    //   213	5	17	localObject3	Object
    //   338	11	18	n	int
    //   392	9	19	localMethod4	java.lang.reflect.Method
    //   398	6	20	arrayOfObject4	Object[]
    //   501	3	21	localInvocationTargetException4	java.lang.reflect.InvocationTargetException
    //   408	3	22	localObject4	Object
    //   441	9	23	localMethod5	java.lang.reflect.Method
    //   447	6	24	arrayOfObject5	Object[]
    //   509	3	25	localInvocationTargetException5	java.lang.reflect.InvocationTargetException
    //   457	3	26	localObject5	Object
    //   250	9	27	localMethod6	java.lang.reflect.Method
    //   256	6	28	arrayOfObject6	Object[]
    //   517	3	29	localInvocationTargetException6	java.lang.reflect.InvocationTargetException
    //   266	3	30	localObject6	Object
    //   296	9	31	localMethod7	java.lang.reflect.Method
    //   302	6	32	arrayOfObject7	Object[]
    //   525	3	33	localInvocationTargetException7	java.lang.reflect.InvocationTargetException
    //   312	3	34	localObject7	Object
    // Exception table:
    //   from	to	target	type
    //   101	111	477	java/lang/reflect/InvocationTargetException
    //   153	163	485	java/lang/reflect/InvocationTargetException
    //   205	215	493	java/lang/reflect/InvocationTargetException
    //   400	410	501	java/lang/reflect/InvocationTargetException
    //   449	459	509	java/lang/reflect/InvocationTargetException
    //   258	268	517	java/lang/reflect/InvocationTargetException
    //   304	314	525	java/lang/reflect/InvocationTargetException
  }
  
  /* Error */
  public void baaa00610061aaa0061a(com.db.pwcc.dbmobile.model.error.DbError paramDbError)
  {
    // Byte code:
    //   0: aload_0
    //   1: getfield 108	uuuuuu/ytyyyt:b0078x0078xx0078xx0078	Luuuuuu/ttttty$tyyyyt;
    //   4: astore_2
    //   5: getstatic 74	uuuuuu/ytyyyt:bxxx0078x0078xx0078	I
    //   8: istore_3
    //   9: iload_3
    //   10: iload_3
    //   11: getstatic 62	uuuuuu/ytyyyt:bx00780078xx0078xx0078	I
    //   14: iadd
    //   15: imul
    //   16: getstatic 70	uuuuuu/ytyyyt:b007800780078xx0078xx0078	I
    //   19: irem
    //   20: tableswitch	default:+20->40, 0:+485->505
    //   40: getstatic 74	uuuuuu/ytyyyt:bxxx0078x0078xx0078	I
    //   43: getstatic 62	uuuuuu/ytyyyt:bx00780078xx0078xx0078	I
    //   46: iadd
    //   47: getstatic 74	uuuuuu/ytyyyt:bxxx0078x0078xx0078	I
    //   50: imul
    //   51: getstatic 70	uuuuuu/ytyyyt:b007800780078xx0078xx0078	I
    //   54: irem
    //   55: getstatic 78	uuuuuu/ytyyyt:b0078xx0078x0078xx0078	I
    //   58: if_icmpeq +57 -> 115
    //   61: bipush 84
    //   63: putstatic 74	uuuuuu/ytyyyt:bxxx0078x0078xx0078	I
    //   66: ldc 2
    //   68: ldc -55
    //   70: bipush 50
    //   72: sipush 216
    //   75: iconst_1
    //   76: invokestatic 44	xxxxxx/uxxxxx:bbbb0062b0062b0062b0062	(Ljava/lang/String;CCC)Ljava/lang/String;
    //   79: iconst_0
    //   80: anewarray 32	java/lang/Class
    //   83: invokevirtual 48	java/lang/Class:getMethod	(Ljava/lang/String;[Ljava/lang/Class;)Ljava/lang/reflect/Method;
    //   86: astore 41
    //   88: iconst_0
    //   89: anewarray 4	java/lang/Object
    //   92: astore 42
    //   94: aload 41
    //   96: aconst_null
    //   97: aload 42
    //   99: invokevirtual 54	java/lang/reflect/Method:invoke	(Ljava/lang/Object;[Ljava/lang/Object;)Ljava/lang/Object;
    //   102: astore 44
    //   104: aload 44
    //   106: checkcast 56	java/lang/Integer
    //   109: invokevirtual 60	java/lang/Integer:intValue	()I
    //   112: putstatic 78	uuuuuu/ytyyyt:b0078xx0078x0078xx0078	I
    //   115: bipush 42
    //   117: putstatic 74	uuuuuu/ytyyyt:bxxx0078x0078xx0078	I
    //   120: ldc 2
    //   122: ldc -53
    //   124: bipush 82
    //   126: sipush 188
    //   129: iconst_2
    //   130: invokestatic 44	xxxxxx/uxxxxx:bbbb0062b0062b0062b0062	(Ljava/lang/String;CCC)Ljava/lang/String;
    //   133: iconst_0
    //   134: anewarray 32	java/lang/Class
    //   137: invokevirtual 48	java/lang/Class:getMethod	(Ljava/lang/String;[Ljava/lang/Class;)Ljava/lang/reflect/Method;
    //   140: astore 10
    //   142: iconst_0
    //   143: anewarray 4	java/lang/Object
    //   146: astore 11
    //   148: aload 10
    //   150: aconst_null
    //   151: aload 11
    //   153: invokevirtual 54	java/lang/reflect/Method:invoke	(Ljava/lang/Object;[Ljava/lang/Object;)Ljava/lang/Object;
    //   156: astore 13
    //   158: aload 13
    //   160: checkcast 56	java/lang/Integer
    //   163: invokevirtual 60	java/lang/Integer:intValue	()I
    //   166: putstatic 78	uuuuuu/ytyyyt:b0078xx0078x0078xx0078	I
    //   169: getstatic 74	uuuuuu/ytyyyt:bxxx0078x0078xx0078	I
    //   172: istore 14
    //   174: iload 14
    //   176: iload 14
    //   178: getstatic 62	uuuuuu/ytyyyt:bx00780078xx0078xx0078	I
    //   181: iadd
    //   182: imul
    //   183: getstatic 70	uuuuuu/ytyyyt:b007800780078xx0078xx0078	I
    //   186: irem
    //   187: tableswitch	default:+17->204, 0:+318->505
    //   204: ldc 2
    //   206: ldc -51
    //   208: bipush 74
    //   210: bipush 82
    //   212: iconst_2
    //   213: invokestatic 44	xxxxxx/uxxxxx:bbbb0062b0062b0062b0062	(Ljava/lang/String;CCC)Ljava/lang/String;
    //   216: iconst_0
    //   217: anewarray 32	java/lang/Class
    //   220: invokevirtual 48	java/lang/Class:getMethod	(Ljava/lang/String;[Ljava/lang/Class;)Ljava/lang/reflect/Method;
    //   223: astore 15
    //   225: iconst_0
    //   226: anewarray 4	java/lang/Object
    //   229: astore 16
    //   231: aload 15
    //   233: aconst_null
    //   234: aload 16
    //   236: invokevirtual 54	java/lang/reflect/Method:invoke	(Ljava/lang/Object;[Ljava/lang/Object;)Ljava/lang/Object;
    //   239: astore 18
    //   241: aload 18
    //   243: checkcast 56	java/lang/Integer
    //   246: invokevirtual 60	java/lang/Integer:intValue	()I
    //   249: putstatic 74	uuuuuu/ytyyyt:bxxx0078x0078xx0078	I
    //   252: bipush 73
    //   254: putstatic 78	uuuuuu/ytyyyt:b0078xx0078x0078xx0078	I
    //   257: ldc 2
    //   259: ldc -49
    //   261: bipush 92
    //   263: iconst_2
    //   264: invokestatic 68	xxxxxx/uxxxxx:bb00620062bb0062b0062b0062	(Ljava/lang/String;CC)Ljava/lang/String;
    //   267: iconst_0
    //   268: anewarray 32	java/lang/Class
    //   271: invokevirtual 48	java/lang/Class:getMethod	(Ljava/lang/String;[Ljava/lang/Class;)Ljava/lang/reflect/Method;
    //   274: astore 19
    //   276: iconst_0
    //   277: anewarray 4	java/lang/Object
    //   280: astore 20
    //   282: aload 19
    //   284: aconst_null
    //   285: aload 20
    //   287: invokevirtual 54	java/lang/reflect/Method:invoke	(Ljava/lang/Object;[Ljava/lang/Object;)Ljava/lang/Object;
    //   290: astore 22
    //   292: aload 22
    //   294: checkcast 56	java/lang/Integer
    //   297: invokevirtual 60	java/lang/Integer:intValue	()I
    //   300: getstatic 62	uuuuuu/ytyyyt:bx00780078xx0078xx0078	I
    //   303: iadd
    //   304: istore 23
    //   306: ldc 2
    //   308: ldc -47
    //   310: bipush 65
    //   312: bipush 29
    //   314: iconst_2
    //   315: invokestatic 44	xxxxxx/uxxxxx:bbbb0062b0062b0062b0062	(Ljava/lang/String;CCC)Ljava/lang/String;
    //   318: iconst_0
    //   319: anewarray 32	java/lang/Class
    //   322: invokevirtual 48	java/lang/Class:getMethod	(Ljava/lang/String;[Ljava/lang/Class;)Ljava/lang/reflect/Method;
    //   325: astore 24
    //   327: iconst_0
    //   328: anewarray 4	java/lang/Object
    //   331: astore 25
    //   333: aload 24
    //   335: aconst_null
    //   336: aload 25
    //   338: invokevirtual 54	java/lang/reflect/Method:invoke	(Ljava/lang/Object;[Ljava/lang/Object;)Ljava/lang/Object;
    //   341: astore 27
    //   343: iload 23
    //   345: aload 27
    //   347: checkcast 56	java/lang/Integer
    //   350: invokevirtual 60	java/lang/Integer:intValue	()I
    //   353: imul
    //   354: istore 28
    //   356: ldc 2
    //   358: ldc -45
    //   360: bipush 69
    //   362: bipush 17
    //   364: iconst_0
    //   365: invokestatic 44	xxxxxx/uxxxxx:bbbb0062b0062b0062b0062	(Ljava/lang/String;CCC)Ljava/lang/String;
    //   368: iconst_0
    //   369: anewarray 32	java/lang/Class
    //   372: invokevirtual 48	java/lang/Class:getMethod	(Ljava/lang/String;[Ljava/lang/Class;)Ljava/lang/reflect/Method;
    //   375: astore 29
    //   377: iconst_0
    //   378: anewarray 4	java/lang/Object
    //   381: astore 30
    //   383: aload 29
    //   385: aconst_null
    //   386: aload 30
    //   388: invokevirtual 54	java/lang/reflect/Method:invoke	(Ljava/lang/Object;[Ljava/lang/Object;)Ljava/lang/Object;
    //   391: astore 32
    //   393: iload 28
    //   395: aload 32
    //   397: checkcast 56	java/lang/Integer
    //   400: invokevirtual 60	java/lang/Integer:intValue	()I
    //   403: irem
    //   404: getstatic 78	uuuuuu/ytyyyt:b0078xx0078x0078xx0078	I
    //   407: if_icmpeq +98 -> 505
    //   410: ldc 2
    //   412: ldc -43
    //   414: sipush 145
    //   417: iconst_2
    //   418: invokestatic 68	xxxxxx/uxxxxx:bb00620062bb0062b0062b0062	(Ljava/lang/String;CC)Ljava/lang/String;
    //   421: iconst_0
    //   422: anewarray 32	java/lang/Class
    //   425: invokevirtual 48	java/lang/Class:getMethod	(Ljava/lang/String;[Ljava/lang/Class;)Ljava/lang/reflect/Method;
    //   428: astore 33
    //   430: iconst_0
    //   431: anewarray 4	java/lang/Object
    //   434: astore 34
    //   436: aload 33
    //   438: aconst_null
    //   439: aload 34
    //   441: invokevirtual 54	java/lang/reflect/Method:invoke	(Ljava/lang/Object;[Ljava/lang/Object;)Ljava/lang/Object;
    //   444: astore 36
    //   446: aload 36
    //   448: checkcast 56	java/lang/Integer
    //   451: invokevirtual 60	java/lang/Integer:intValue	()I
    //   454: putstatic 74	uuuuuu/ytyyyt:bxxx0078x0078xx0078	I
    //   457: ldc 2
    //   459: ldc -41
    //   461: bipush 117
    //   463: bipush 7
    //   465: iconst_0
    //   466: invokestatic 44	xxxxxx/uxxxxx:bbbb0062b0062b0062b0062	(Ljava/lang/String;CCC)Ljava/lang/String;
    //   469: iconst_0
    //   470: anewarray 32	java/lang/Class
    //   473: invokevirtual 48	java/lang/Class:getMethod	(Ljava/lang/String;[Ljava/lang/Class;)Ljava/lang/reflect/Method;
    //   476: astore 37
    //   478: iconst_0
    //   479: anewarray 4	java/lang/Object
    //   482: astore 38
    //   484: aload 37
    //   486: aconst_null
    //   487: aload 38
    //   489: invokevirtual 54	java/lang/reflect/Method:invoke	(Ljava/lang/Object;[Ljava/lang/Object;)Ljava/lang/Object;
    //   492: astore 40
    //   494: aload 40
    //   496: checkcast 56	java/lang/Integer
    //   499: invokevirtual 60	java/lang/Integer:intValue	()I
    //   502: putstatic 78	uuuuuu/ytyyyt:b0078xx0078x0078xx0078	I
    //   505: ldc -39
    //   507: bipush 46
    //   509: iconst_1
    //   510: invokestatic 68	xxxxxx/uxxxxx:bb00620062bb0062b0062b0062	(Ljava/lang/String;CC)Ljava/lang/String;
    //   513: astore 4
    //   515: iconst_3
    //   516: anewarray 32	java/lang/Class
    //   519: astore 5
    //   521: aload 5
    //   523: iconst_0
    //   524: ldc 126
    //   526: aastore
    //   527: aload 5
    //   529: iconst_1
    //   530: getstatic 137	java/lang/Character:TYPE	Ljava/lang/Class;
    //   533: aastore
    //   534: aload 5
    //   536: iconst_2
    //   537: getstatic 137	java/lang/Character:TYPE	Ljava/lang/Class;
    //   540: aastore
    //   541: ldc -117
    //   543: aload 4
    //   545: aload 5
    //   547: invokevirtual 48	java/lang/Class:getMethod	(Ljava/lang/String;[Ljava/lang/Class;)Ljava/lang/reflect/Method;
    //   550: astore 6
    //   552: iconst_3
    //   553: anewarray 4	java/lang/Object
    //   556: astore 7
    //   558: aload 7
    //   560: iconst_0
    //   561: ldc -37
    //   563: aastore
    //   564: aload 7
    //   566: iconst_1
    //   567: bipush 73
    //   569: invokestatic 145	java/lang/Character:valueOf	(C)Ljava/lang/Character;
    //   572: aastore
    //   573: aload 7
    //   575: iconst_2
    //   576: iconst_1
    //   577: invokestatic 145	java/lang/Character:valueOf	(C)Ljava/lang/Character;
    //   580: aastore
    //   581: aload 6
    //   583: aconst_null
    //   584: aload 7
    //   586: invokevirtual 54	java/lang/reflect/Method:invoke	(Ljava/lang/Object;[Ljava/lang/Object;)Ljava/lang/Object;
    //   589: astore 9
    //   591: aload_2
    //   592: aload 9
    //   594: checkcast 126	java/lang/String
    //   597: invokeinterface 159 2 0
    //   602: return
    //   603: astore 8
    //   605: aload 8
    //   607: invokevirtual 90	java/lang/reflect/InvocationTargetException:getCause	()Ljava/lang/Throwable;
    //   610: athrow
    //   611: astore 12
    //   613: aload 12
    //   615: invokevirtual 90	java/lang/reflect/InvocationTargetException:getCause	()Ljava/lang/Throwable;
    //   618: athrow
    //   619: astore 21
    //   621: aload 21
    //   623: invokevirtual 90	java/lang/reflect/InvocationTargetException:getCause	()Ljava/lang/Throwable;
    //   626: athrow
    //   627: astore 26
    //   629: aload 26
    //   631: invokevirtual 90	java/lang/reflect/InvocationTargetException:getCause	()Ljava/lang/Throwable;
    //   634: athrow
    //   635: astore 31
    //   637: aload 31
    //   639: invokevirtual 90	java/lang/reflect/InvocationTargetException:getCause	()Ljava/lang/Throwable;
    //   642: athrow
    //   643: astore 17
    //   645: aload 17
    //   647: invokevirtual 90	java/lang/reflect/InvocationTargetException:getCause	()Ljava/lang/Throwable;
    //   650: athrow
    //   651: astore 35
    //   653: aload 35
    //   655: invokevirtual 90	java/lang/reflect/InvocationTargetException:getCause	()Ljava/lang/Throwable;
    //   658: athrow
    //   659: astore 39
    //   661: aload 39
    //   663: invokevirtual 90	java/lang/reflect/InvocationTargetException:getCause	()Ljava/lang/Throwable;
    //   666: athrow
    //   667: astore 43
    //   669: aload 43
    //   671: invokevirtual 90	java/lang/reflect/InvocationTargetException:getCause	()Ljava/lang/Throwable;
    //   674: athrow
    // Local variable table:
    //   start	length	slot	name	signature
    //   0	675	0	this	ytyyyt
    //   0	675	1	paramDbError	com.db.pwcc.dbmobile.model.error.DbError
    //   4	588	2	localTyyyyt	ttttty.tyyyyt
    //   8	8	3	i	int
    //   513	31	4	str	String
    //   519	27	5	arrayOfClass	Class[]
    //   550	32	6	localMethod1	java.lang.reflect.Method
    //   556	29	7	arrayOfObject1	Object[]
    //   603	3	8	localInvocationTargetException1	java.lang.reflect.InvocationTargetException
    //   589	4	9	localObject1	Object
    //   140	9	10	localMethod2	java.lang.reflect.Method
    //   146	6	11	arrayOfObject2	Object[]
    //   611	3	12	localInvocationTargetException2	java.lang.reflect.InvocationTargetException
    //   156	3	13	localObject2	Object
    //   172	11	14	j	int
    //   223	9	15	localMethod3	java.lang.reflect.Method
    //   229	6	16	arrayOfObject3	Object[]
    //   643	3	17	localInvocationTargetException3	java.lang.reflect.InvocationTargetException
    //   239	3	18	localObject3	Object
    //   274	9	19	localMethod4	java.lang.reflect.Method
    //   280	6	20	arrayOfObject4	Object[]
    //   619	3	21	localInvocationTargetException4	java.lang.reflect.InvocationTargetException
    //   290	3	22	localObject4	Object
    //   304	50	23	k	int
    //   325	9	24	localMethod5	java.lang.reflect.Method
    //   331	6	25	arrayOfObject5	Object[]
    //   627	3	26	localInvocationTargetException5	java.lang.reflect.InvocationTargetException
    //   341	5	27	localObject5	Object
    //   354	50	28	m	int
    //   375	9	29	localMethod6	java.lang.reflect.Method
    //   381	6	30	arrayOfObject6	Object[]
    //   635	3	31	localInvocationTargetException6	java.lang.reflect.InvocationTargetException
    //   391	5	32	localObject6	Object
    //   428	9	33	localMethod7	java.lang.reflect.Method
    //   434	6	34	arrayOfObject7	Object[]
    //   651	3	35	localInvocationTargetException7	java.lang.reflect.InvocationTargetException
    //   444	3	36	localObject7	Object
    //   476	9	37	localMethod8	java.lang.reflect.Method
    //   482	6	38	arrayOfObject8	Object[]
    //   659	3	39	localInvocationTargetException8	java.lang.reflect.InvocationTargetException
    //   492	3	40	localObject8	Object
    //   86	9	41	localMethod9	java.lang.reflect.Method
    //   92	6	42	arrayOfObject9	Object[]
    //   667	3	43	localInvocationTargetException9	java.lang.reflect.InvocationTargetException
    //   102	3	44	localObject9	Object
    // Exception table:
    //   from	to	target	type
    //   581	591	603	java/lang/reflect/InvocationTargetException
    //   148	158	611	java/lang/reflect/InvocationTargetException
    //   282	292	619	java/lang/reflect/InvocationTargetException
    //   333	343	627	java/lang/reflect/InvocationTargetException
    //   383	393	635	java/lang/reflect/InvocationTargetException
    //   231	241	643	java/lang/reflect/InvocationTargetException
    //   436	446	651	java/lang/reflect/InvocationTargetException
    //   484	494	659	java/lang/reflect/InvocationTargetException
    //   94	104	667	java/lang/reflect/InvocationTargetException
  }
  
  /* Error */
  public void bqq0071q007100710071q00710071()
  {
    // Byte code:
    //   0: getstatic 74	uuuuuu/ytyyyt:bxxx0078x0078xx0078	I
    //   3: istore_1
    //   4: iload_1
    //   5: iload_1
    //   6: getstatic 62	uuuuuu/ytyyyt:bx00780078xx0078xx0078	I
    //   9: iadd
    //   10: imul
    //   11: getstatic 70	uuuuuu/ytyyyt:b007800780078xx0078xx0078	I
    //   14: irem
    //   15: tableswitch	default:+17->32, 0:+310->325
    //   32: getstatic 74	uuuuuu/ytyyyt:bxxx0078x0078xx0078	I
    //   35: getstatic 62	uuuuuu/ytyyyt:bx00780078xx0078xx0078	I
    //   38: iadd
    //   39: getstatic 74	uuuuuu/ytyyyt:bxxx0078x0078xx0078	I
    //   42: imul
    //   43: getstatic 70	uuuuuu/ytyyyt:b007800780078xx0078xx0078	I
    //   46: irem
    //   47: istore_2
    //   48: ldc 2
    //   50: ldc -34
    //   52: sipush 249
    //   55: bipush 26
    //   57: iconst_2
    //   58: invokestatic 44	xxxxxx/uxxxxx:bbbb0062b0062b0062b0062	(Ljava/lang/String;CCC)Ljava/lang/String;
    //   61: iconst_0
    //   62: anewarray 32	java/lang/Class
    //   65: invokevirtual 48	java/lang/Class:getMethod	(Ljava/lang/String;[Ljava/lang/Class;)Ljava/lang/reflect/Method;
    //   68: astore_3
    //   69: iconst_0
    //   70: anewarray 4	java/lang/Object
    //   73: astore 4
    //   75: aload_3
    //   76: aconst_null
    //   77: aload 4
    //   79: invokevirtual 54	java/lang/reflect/Method:invoke	(Ljava/lang/Object;[Ljava/lang/Object;)Ljava/lang/Object;
    //   82: astore 6
    //   84: iload_2
    //   85: aload 6
    //   87: checkcast 56	java/lang/Integer
    //   90: invokevirtual 60	java/lang/Integer:intValue	()I
    //   93: if_icmpeq +89 -> 182
    //   96: getstatic 74	uuuuuu/ytyyyt:bxxx0078x0078xx0078	I
    //   99: getstatic 62	uuuuuu/ytyyyt:bx00780078xx0078xx0078	I
    //   102: iadd
    //   103: getstatic 74	uuuuuu/ytyyyt:bxxx0078x0078xx0078	I
    //   106: imul
    //   107: getstatic 70	uuuuuu/ytyyyt:b007800780078xx0078xx0078	I
    //   110: irem
    //   111: getstatic 78	uuuuuu/ytyyyt:b0078xx0078x0078xx0078	I
    //   114: if_icmpeq +58 -> 172
    //   117: ldc 2
    //   119: ldc -32
    //   121: sipush 138
    //   124: sipush 238
    //   127: iconst_2
    //   128: invokestatic 44	xxxxxx/uxxxxx:bbbb0062b0062b0062b0062	(Ljava/lang/String;CCC)Ljava/lang/String;
    //   131: iconst_0
    //   132: anewarray 32	java/lang/Class
    //   135: invokevirtual 48	java/lang/Class:getMethod	(Ljava/lang/String;[Ljava/lang/Class;)Ljava/lang/reflect/Method;
    //   138: astore 16
    //   140: iconst_0
    //   141: anewarray 4	java/lang/Object
    //   144: astore 17
    //   146: aload 16
    //   148: aconst_null
    //   149: aload 17
    //   151: invokevirtual 54	java/lang/reflect/Method:invoke	(Ljava/lang/Object;[Ljava/lang/Object;)Ljava/lang/Object;
    //   154: astore 19
    //   156: aload 19
    //   158: checkcast 56	java/lang/Integer
    //   161: invokevirtual 60	java/lang/Integer:intValue	()I
    //   164: putstatic 74	uuuuuu/ytyyyt:bxxx0078x0078xx0078	I
    //   167: bipush 65
    //   169: putstatic 78	uuuuuu/ytyyyt:b0078xx0078x0078xx0078	I
    //   172: bipush 27
    //   174: putstatic 74	uuuuuu/ytyyyt:bxxx0078x0078xx0078	I
    //   177: bipush 72
    //   179: putstatic 78	uuuuuu/ytyyyt:b0078xx0078x0078xx0078	I
    //   182: getstatic 74	uuuuuu/ytyyyt:bxxx0078x0078xx0078	I
    //   185: istore 7
    //   187: iload 7
    //   189: iload 7
    //   191: getstatic 62	uuuuuu/ytyyyt:bx00780078xx0078xx0078	I
    //   194: iadd
    //   195: imul
    //   196: getstatic 70	uuuuuu/ytyyyt:b007800780078xx0078xx0078	I
    //   199: irem
    //   200: tableswitch	default:+20->220, 0:+115->315
    //   220: ldc 2
    //   222: ldc -30
    //   224: bipush 37
    //   226: bipush 110
    //   228: iconst_0
    //   229: invokestatic 44	xxxxxx/uxxxxx:bbbb0062b0062b0062b0062	(Ljava/lang/String;CCC)Ljava/lang/String;
    //   232: iconst_0
    //   233: anewarray 32	java/lang/Class
    //   236: invokevirtual 48	java/lang/Class:getMethod	(Ljava/lang/String;[Ljava/lang/Class;)Ljava/lang/reflect/Method;
    //   239: astore 8
    //   241: iconst_0
    //   242: anewarray 4	java/lang/Object
    //   245: astore 9
    //   247: aload 8
    //   249: aconst_null
    //   250: aload 9
    //   252: invokevirtual 54	java/lang/reflect/Method:invoke	(Ljava/lang/Object;[Ljava/lang/Object;)Ljava/lang/Object;
    //   255: astore 11
    //   257: aload 11
    //   259: checkcast 56	java/lang/Integer
    //   262: invokevirtual 60	java/lang/Integer:intValue	()I
    //   265: putstatic 74	uuuuuu/ytyyyt:bxxx0078x0078xx0078	I
    //   268: ldc 2
    //   270: ldc -28
    //   272: sipush 237
    //   275: iconst_3
    //   276: invokestatic 68	xxxxxx/uxxxxx:bb00620062bb0062b0062b0062	(Ljava/lang/String;CC)Ljava/lang/String;
    //   279: iconst_0
    //   280: anewarray 32	java/lang/Class
    //   283: invokevirtual 48	java/lang/Class:getMethod	(Ljava/lang/String;[Ljava/lang/Class;)Ljava/lang/reflect/Method;
    //   286: astore 12
    //   288: iconst_0
    //   289: anewarray 4	java/lang/Object
    //   292: astore 13
    //   294: aload 12
    //   296: aconst_null
    //   297: aload 13
    //   299: invokevirtual 54	java/lang/reflect/Method:invoke	(Ljava/lang/Object;[Ljava/lang/Object;)Ljava/lang/Object;
    //   302: astore 15
    //   304: aload 15
    //   306: checkcast 56	java/lang/Integer
    //   309: invokevirtual 60	java/lang/Integer:intValue	()I
    //   312: putstatic 78	uuuuuu/ytyyyt:b0078xx0078x0078xx0078	I
    //   315: bipush 71
    //   317: putstatic 74	uuuuuu/ytyyyt:bxxx0078x0078xx0078	I
    //   320: bipush 79
    //   322: putstatic 78	uuuuuu/ytyyyt:b0078xx0078x0078xx0078	I
    //   325: aload_0
    //   326: getfield 113	uuuuuu/ytyyyt:bxx0078xx0078xx0078	Luuuuuu/mffffm;
    //   329: aload_0
    //   330: invokevirtual 232	uuuuuu/mffffm:bpp0070pp0070p00700070p	(Luuuuuu/vvpvvp$ppvvvp;)V
    //   333: return
    //   334: astore 10
    //   336: aload 10
    //   338: invokevirtual 90	java/lang/reflect/InvocationTargetException:getCause	()Ljava/lang/Throwable;
    //   341: athrow
    //   342: astore 5
    //   344: aload 5
    //   346: invokevirtual 90	java/lang/reflect/InvocationTargetException:getCause	()Ljava/lang/Throwable;
    //   349: athrow
    //   350: astore 14
    //   352: aload 14
    //   354: invokevirtual 90	java/lang/reflect/InvocationTargetException:getCause	()Ljava/lang/Throwable;
    //   357: athrow
    //   358: astore 18
    //   360: aload 18
    //   362: invokevirtual 90	java/lang/reflect/InvocationTargetException:getCause	()Ljava/lang/Throwable;
    //   365: athrow
    // Local variable table:
    //   start	length	slot	name	signature
    //   0	366	0	this	ytyyyt
    //   3	8	1	i	int
    //   47	47	2	j	int
    //   68	8	3	localMethod1	java.lang.reflect.Method
    //   73	5	4	arrayOfObject1	Object[]
    //   342	3	5	localInvocationTargetException1	java.lang.reflect.InvocationTargetException
    //   82	4	6	localObject1	Object
    //   185	11	7	k	int
    //   239	9	8	localMethod2	java.lang.reflect.Method
    //   245	6	9	arrayOfObject2	Object[]
    //   334	3	10	localInvocationTargetException2	java.lang.reflect.InvocationTargetException
    //   255	3	11	localObject2	Object
    //   286	9	12	localMethod3	java.lang.reflect.Method
    //   292	6	13	arrayOfObject3	Object[]
    //   350	3	14	localInvocationTargetException3	java.lang.reflect.InvocationTargetException
    //   302	3	15	localObject3	Object
    //   138	9	16	localMethod4	java.lang.reflect.Method
    //   144	6	17	arrayOfObject4	Object[]
    //   358	3	18	localInvocationTargetException4	java.lang.reflect.InvocationTargetException
    //   154	3	19	localObject4	Object
    // Exception table:
    //   from	to	target	type
    //   247	257	334	java/lang/reflect/InvocationTargetException
    //   75	84	342	java/lang/reflect/InvocationTargetException
    //   294	304	350	java/lang/reflect/InvocationTargetException
    //   146	156	358	java/lang/reflect/InvocationTargetException
  }
}
