package com.google.android.gms.nearby.messages.internal;

import android.os.Binder;
import android.os.IBinder;
import android.os.IInterface;
import android.os.Parcel;
import android.os.RemoteException;

public abstract interface zza
  extends IInterface
{
  public abstract void zza(MessageWrapper paramMessageWrapper)
    throws RemoteException;
  
  public abstract void zza(MessageWrapper paramMessageWrapper, int paramInt)
    throws RemoteException;
  
  public abstract void zzb(MessageWrapper paramMessageWrapper)
    throws RemoteException;
  
  public static abstract class zza
    extends Binder
    implements zza
  {
    public static zza zzdd(IBinder paramIBinder)
    {
      if (paramIBinder == null) {
        return null;
      }
      IInterface localIInterface = paramIBinder.queryLocalInterface("com.google.android.gms.nearby.messages.internal.IMessageListener");
      if ((localIInterface != null) && ((localIInterface instanceof zza))) {
        return (zza)localIInterface;
      }
      return new zza(paramIBinder);
    }
    
    public IBinder asBinder()
    {
      return this;
    }
    
    public boolean onTransact(int paramInt1, Parcel paramParcel1, Parcel paramParcel2, int paramInt2)
      throws RemoteException
    {
      Object localObject2 = null;
      Object localObject3 = null;
      Object localObject1 = null;
      switch (paramInt1)
      {
      default: 
        return super.onTransact(paramInt1, paramParcel1, paramParcel2, paramInt2);
      case 1598968902: 
        paramParcel2.writeString("com.google.android.gms.nearby.messages.internal.IMessageListener");
        return true;
      case 1: 
        paramParcel1.enforceInterface("com.google.android.gms.nearby.messages.internal.IMessageListener");
        if (paramParcel1.readInt() != 0) {
          localObject1 = MessageWrapper.CREATOR.zzft(paramParcel1);
        }
        zza((MessageWrapper)localObject1);
        paramParcel2.writeNoException();
        return true;
      case 2: 
        paramParcel1.enforceInterface("com.google.android.gms.nearby.messages.internal.IMessageListener");
        localObject1 = localObject2;
        if (paramParcel1.readInt() != 0) {
          localObject1 = MessageWrapper.CREATOR.zzft(paramParcel1);
        }
        zzb((MessageWrapper)localObject1);
        paramParcel2.writeNoException();
        return true;
      }
      paramParcel1.enforceInterface("com.google.android.gms.nearby.messages.internal.IMessageListener");
      localObject1 = localObject3;
      if (paramParcel1.readInt() != 0) {
        localObject1 = MessageWrapper.CREATOR.zzft(paramParcel1);
      }
      zza((MessageWrapper)localObject1, paramParcel1.readInt());
      paramParcel2.writeNoException();
      return true;
    }
    
    private static class zza
      implements zza
    {
      private IBinder zznF;
      
      zza(IBinder paramIBinder)
      {
        this.zznF = paramIBinder;
      }
      
      public IBinder asBinder()
      {
        return this.zznF;
      }
      
      /* Error */
      public void zza(MessageWrapper paramMessageWrapper)
        throws RemoteException
      {
        // Byte code:
        //   0: invokestatic 30	android/os/Parcel:obtain	()Landroid/os/Parcel;
        //   3: astore_2
        //   4: invokestatic 30	android/os/Parcel:obtain	()Landroid/os/Parcel;
        //   7: astore_3
        //   8: aload_2
        //   9: ldc 32
        //   11: invokevirtual 36	android/os/Parcel:writeInterfaceToken	(Ljava/lang/String;)V
        //   14: aload_1
        //   15: ifnull +41 -> 56
        //   18: aload_2
        //   19: iconst_1
        //   20: invokevirtual 40	android/os/Parcel:writeInt	(I)V
        //   23: aload_1
        //   24: aload_2
        //   25: iconst_0
        //   26: invokevirtual 46	com/google/android/gms/nearby/messages/internal/MessageWrapper:writeToParcel	(Landroid/os/Parcel;I)V
        //   29: aload_0
        //   30: getfield 18	com/google/android/gms/nearby/messages/internal/zza$zza$zza:zznF	Landroid/os/IBinder;
        //   33: iconst_1
        //   34: aload_2
        //   35: aload_3
        //   36: iconst_0
        //   37: invokeinterface 52 5 0
        //   42: pop
        //   43: aload_3
        //   44: invokevirtual 55	android/os/Parcel:readException	()V
        //   47: aload_3
        //   48: invokevirtual 58	android/os/Parcel:recycle	()V
        //   51: aload_2
        //   52: invokevirtual 58	android/os/Parcel:recycle	()V
        //   55: return
        //   56: aload_2
        //   57: iconst_0
        //   58: invokevirtual 40	android/os/Parcel:writeInt	(I)V
        //   61: goto -32 -> 29
        //   64: astore_1
        //   65: aload_3
        //   66: invokevirtual 58	android/os/Parcel:recycle	()V
        //   69: aload_2
        //   70: invokevirtual 58	android/os/Parcel:recycle	()V
        //   73: aload_1
        //   74: athrow
        // Local variable table:
        //   start	length	slot	name	signature
        //   0	75	0	this	zza
        //   0	75	1	paramMessageWrapper	MessageWrapper
        //   3	67	2	localParcel1	Parcel
        //   7	59	3	localParcel2	Parcel
        // Exception table:
        //   from	to	target	type
        //   8	14	64	finally
        //   18	29	64	finally
        //   29	47	64	finally
        //   56	61	64	finally
      }
      
      /* Error */
      public void zza(MessageWrapper paramMessageWrapper, int paramInt)
        throws RemoteException
      {
        // Byte code:
        //   0: invokestatic 30	android/os/Parcel:obtain	()Landroid/os/Parcel;
        //   3: astore_3
        //   4: invokestatic 30	android/os/Parcel:obtain	()Landroid/os/Parcel;
        //   7: astore 4
        //   9: aload_3
        //   10: ldc 32
        //   12: invokevirtual 36	android/os/Parcel:writeInterfaceToken	(Ljava/lang/String;)V
        //   15: aload_1
        //   16: ifnull +49 -> 65
        //   19: aload_3
        //   20: iconst_1
        //   21: invokevirtual 40	android/os/Parcel:writeInt	(I)V
        //   24: aload_1
        //   25: aload_3
        //   26: iconst_0
        //   27: invokevirtual 46	com/google/android/gms/nearby/messages/internal/MessageWrapper:writeToParcel	(Landroid/os/Parcel;I)V
        //   30: aload_3
        //   31: iload_2
        //   32: invokevirtual 40	android/os/Parcel:writeInt	(I)V
        //   35: aload_0
        //   36: getfield 18	com/google/android/gms/nearby/messages/internal/zza$zza$zza:zznF	Landroid/os/IBinder;
        //   39: iconst_3
        //   40: aload_3
        //   41: aload 4
        //   43: iconst_0
        //   44: invokeinterface 52 5 0
        //   49: pop
        //   50: aload 4
        //   52: invokevirtual 55	android/os/Parcel:readException	()V
        //   55: aload 4
        //   57: invokevirtual 58	android/os/Parcel:recycle	()V
        //   60: aload_3
        //   61: invokevirtual 58	android/os/Parcel:recycle	()V
        //   64: return
        //   65: aload_3
        //   66: iconst_0
        //   67: invokevirtual 40	android/os/Parcel:writeInt	(I)V
        //   70: goto -40 -> 30
        //   73: astore_1
        //   74: aload 4
        //   76: invokevirtual 58	android/os/Parcel:recycle	()V
        //   79: aload_3
        //   80: invokevirtual 58	android/os/Parcel:recycle	()V
        //   83: aload_1
        //   84: athrow
        // Local variable table:
        //   start	length	slot	name	signature
        //   0	85	0	this	zza
        //   0	85	1	paramMessageWrapper	MessageWrapper
        //   0	85	2	paramInt	int
        //   3	77	3	localParcel1	Parcel
        //   7	68	4	localParcel2	Parcel
        // Exception table:
        //   from	to	target	type
        //   9	15	73	finally
        //   19	30	73	finally
        //   30	55	73	finally
        //   65	70	73	finally
      }
      
      /* Error */
      public void zzb(MessageWrapper paramMessageWrapper)
        throws RemoteException
      {
        // Byte code:
        //   0: invokestatic 30	android/os/Parcel:obtain	()Landroid/os/Parcel;
        //   3: astore_2
        //   4: invokestatic 30	android/os/Parcel:obtain	()Landroid/os/Parcel;
        //   7: astore_3
        //   8: aload_2
        //   9: ldc 32
        //   11: invokevirtual 36	android/os/Parcel:writeInterfaceToken	(Ljava/lang/String;)V
        //   14: aload_1
        //   15: ifnull +41 -> 56
        //   18: aload_2
        //   19: iconst_1
        //   20: invokevirtual 40	android/os/Parcel:writeInt	(I)V
        //   23: aload_1
        //   24: aload_2
        //   25: iconst_0
        //   26: invokevirtual 46	com/google/android/gms/nearby/messages/internal/MessageWrapper:writeToParcel	(Landroid/os/Parcel;I)V
        //   29: aload_0
        //   30: getfield 18	com/google/android/gms/nearby/messages/internal/zza$zza$zza:zznF	Landroid/os/IBinder;
        //   33: iconst_2
        //   34: aload_2
        //   35: aload_3
        //   36: iconst_0
        //   37: invokeinterface 52 5 0
        //   42: pop
        //   43: aload_3
        //   44: invokevirtual 55	android/os/Parcel:readException	()V
        //   47: aload_3
        //   48: invokevirtual 58	android/os/Parcel:recycle	()V
        //   51: aload_2
        //   52: invokevirtual 58	android/os/Parcel:recycle	()V
        //   55: return
        //   56: aload_2
        //   57: iconst_0
        //   58: invokevirtual 40	android/os/Parcel:writeInt	(I)V
        //   61: goto -32 -> 29
        //   64: astore_1
        //   65: aload_3
        //   66: invokevirtual 58	android/os/Parcel:recycle	()V
        //   69: aload_2
        //   70: invokevirtual 58	android/os/Parcel:recycle	()V
        //   73: aload_1
        //   74: athrow
        // Local variable table:
        //   start	length	slot	name	signature
        //   0	75	0	this	zza
        //   0	75	1	paramMessageWrapper	MessageWrapper
        //   3	67	2	localParcel1	Parcel
        //   7	59	3	localParcel2	Parcel
        // Exception table:
        //   from	to	target	type
        //   8	14	64	finally
        //   18	29	64	finally
        //   29	47	64	finally
        //   56	61	64	finally
      }
    }
  }
}
