package com.google.android.gms.internal;

import android.app.Application;
import android.content.Context;
import android.content.pm.ApplicationInfo;
import android.content.pm.PackageInfo;
import android.content.pm.PackageManager.NameNotFoundException;
import android.database.sqlite.SQLiteDatabase;
import android.database.sqlite.SQLiteException;
import android.os.Build;
import android.os.Build.VERSION;
import android.os.Bundle;
import android.provider.Settings.Secure;
import android.text.TextUtils;
import android.util.Pair;
import com.google.android.gms.common.api.internal.zzbz;
import com.google.android.gms.common.internal.zzbq;
import com.google.android.gms.common.util.zze;
import com.google.android.gms.common.util.zzi;
import com.google.android.gms.measurement.AppMeasurement;
import com.google.firebase.analytics.FirebaseAnalytics;
import java.io.File;
import java.io.FileNotFoundException;
import java.io.IOException;
import java.io.RandomAccessFile;
import java.net.MalformedURLException;
import java.net.URL;
import java.nio.ByteBuffer;
import java.nio.channels.FileChannel;
import java.nio.channels.FileLock;
import java.security.SecureRandom;
import java.util.ArrayList;
import java.util.Collections;
import java.util.Iterator;
import java.util.List;
import java.util.Locale;
import java.util.Map;
import java.util.concurrent.ExecutionException;
import java.util.concurrent.Future;
import java.util.concurrent.TimeUnit;
import java.util.concurrent.TimeoutException;
import java.util.concurrent.atomic.AtomicReference;

public class zzckk
{
  private static volatile zzckk zza;
  private boolean zzaa;
  private Boolean zzab;
  private long zzac;
  private FileLock zzad;
  private FileChannel zzae;
  private List<Long> zzaf;
  private List<Runnable> zzag;
  private int zzah;
  private int zzai;
  private long zzaj;
  private long zzak;
  private boolean zzal;
  private boolean zzam;
  private boolean zzan;
  private final long zzao;
  private final Context zzb;
  private final zzcil zzc;
  private final zzcjv zzd;
  private final zzcjk zze;
  private final zzckf zzf;
  private final zzcne zzg;
  private final zzcke zzh;
  private final AppMeasurement zzi;
  private final FirebaseAnalytics zzj;
  private final zzcnp zzk;
  private final zzcji zzl;
  private final zzcjo zzm;
  private final zze zzn;
  private final zzcmb zzo;
  private final zzcll zzp;
  private final zzcib zzq;
  private zzcim zzr;
  private zzcjg zzs;
  private zzcmf zzt;
  private zzcis zzu;
  private zzcjf zzv;
  private zzcjt zzw;
  private zzcnk zzx;
  private zzcii zzy;
  private boolean zzz = false;
  
  private zzckk(zzclk paramZzclk)
  {
    zzbq.zza(paramZzclk);
    this.zzb = paramZzclk.zza;
    this.zzaj = -1L;
    this.zzn = zzi.zzd();
    this.zzao = this.zzn.zza();
    this.zzc = new zzcil(this);
    zzcjv localZzcjv = new zzcjv(this);
    localZzcjv.zzar();
    this.zzd = localZzcjv;
    zzcjk localZzcjk = new zzcjk(this);
    localZzcjk.zzar();
    this.zze = localZzcjk;
    zzcnp localZzcnp = new zzcnp(this);
    localZzcnp.zzar();
    this.zzk = localZzcnp;
    zzcji localZzcji = new zzcji(this);
    localZzcji.zzar();
    this.zzl = localZzcji;
    this.zzq = new zzcib(this);
    zzcjo localZzcjo = new zzcjo(this);
    localZzcjo.zzar();
    this.zzm = localZzcjo;
    zzcmb localZzcmb = new zzcmb(this);
    localZzcmb.zzar();
    this.zzo = localZzcmb;
    zzcll localZzcll1 = new zzcll(this);
    localZzcll1.zzar();
    this.zzp = localZzcll1;
    this.zzi = new AppMeasurement(this);
    this.zzj = new FirebaseAnalytics(this);
    zzcne localZzcne = new zzcne(this);
    localZzcne.zzar();
    this.zzg = localZzcne;
    zzcke localZzcke = new zzcke(this);
    localZzcke.zzar();
    this.zzh = localZzcke;
    zzckf localZzckf = new zzckf(this);
    localZzckf.zzar();
    this.zzf = localZzckf;
    zzcjm localZzcjm;
    String str;
    if ((this.zzb.getApplicationContext() instanceof Application))
    {
      zzcll localZzcll2 = zzl();
      if (!(localZzcll2.zzl().getApplicationContext() instanceof Application)) {
        break label430;
      }
      Application localApplication = (Application)localZzcll2.zzl().getApplicationContext();
      if (localZzcll2.zza == null) {
        localZzcll2.zza = new zzclz(localZzcll2, null);
      }
      localApplication.unregisterActivityLifecycleCallbacks(localZzcll2.zza);
      localApplication.registerActivityLifecycleCallbacks(localZzcll2.zza);
      localZzcjm = localZzcll2.zzt().zzae();
      str = "Registered activity lifecycle callback";
    }
    else
    {
      localZzcjm = zzf().zzaa();
      str = "Application context is not an Application";
    }
    localZzcjm.zza(str);
    label430:
    this.zzf.zza(new zzckl(this, paramZzclk));
  }
  
  private final int zza(FileChannel paramFileChannel)
  {
    zzh().zzc();
    if ((paramFileChannel != null) && (paramFileChannel.isOpen()))
    {
      ByteBuffer localByteBuffer = ByteBuffer.allocate(4);
      try
      {
        paramFileChannel.position(0L);
        int i = paramFileChannel.read(localByteBuffer);
        if (i != 4)
        {
          if (i == -1) {
            break label117;
          }
          zzf().zzaa().zza("Unexpected data length. Bytes read", Integer.valueOf(i));
          return 0;
        }
        localByteBuffer.flip();
        int j = localByteBuffer.getInt();
        return j;
      }
      catch (IOException localIOException)
      {
        zzf().zzy().zza("Failed to read from channel", localIOException);
        return 0;
      }
    }
    zzf().zzy().zza("Bad channel to read from");
    return 0;
    label117:
    return 0;
  }
  
  /* Error */
  private final zzcig zza(Context paramContext, String paramString1, String paramString2, boolean paramBoolean1, boolean paramBoolean2)
  {
    // Byte code:
    //   0: ldc_w 309
    //   3: astore 6
    //   5: ldc_w 309
    //   8: astore 7
    //   10: ldc_w 309
    //   13: astore 8
    //   15: aload_1
    //   16: invokevirtual 313	android/content/Context:getPackageManager	()Landroid/content/pm/PackageManager;
    //   19: astore 9
    //   21: aload 9
    //   23: ifnonnull +18 -> 41
    //   26: aload_0
    //   27: invokevirtual 232	com/google/android/gms/internal/zzckk:zzf	()Lcom/google/android/gms/internal/zzcjk;
    //   30: invokevirtual 298	com/google/android/gms/internal/zzcjk:zzy	()Lcom/google/android/gms/internal/zzcjm;
    //   33: ldc_w 315
    //   36: invokevirtual 241	com/google/android/gms/internal/zzcjm:zza	(Ljava/lang/String;)V
    //   39: aconst_null
    //   40: areturn
    //   41: aload 9
    //   43: aload_2
    //   44: invokevirtual 321	android/content/pm/PackageManager:getInstallerPackageName	(Ljava/lang/String;)Ljava/lang/String;
    //   47: astore 16
    //   49: aload 16
    //   51: astore 6
    //   53: goto +20 -> 73
    //   56: aload_0
    //   57: invokevirtual 232	com/google/android/gms/internal/zzckk:zzf	()Lcom/google/android/gms/internal/zzcjk;
    //   60: invokevirtual 298	com/google/android/gms/internal/zzcjk:zzy	()Lcom/google/android/gms/internal/zzcjm;
    //   63: ldc_w 323
    //   66: aload_2
    //   67: invokestatic 326	com/google/android/gms/internal/zzcjk:zza	(Ljava/lang/String;)Ljava/lang/Object;
    //   70: invokevirtual 288	com/google/android/gms/internal/zzcjm:zza	(Ljava/lang/String;Ljava/lang/Object;)V
    //   73: aload 6
    //   75: ifnonnull +15 -> 90
    //   78: ldc_w 328
    //   81: astore 6
    //   83: aload 6
    //   85: astore 10
    //   87: goto +22 -> 109
    //   90: ldc_w 330
    //   93: aload 6
    //   95: invokevirtual 336	java/lang/String:equals	(Ljava/lang/Object;)Z
    //   98: ifeq -15 -> 83
    //   101: ldc_w 338
    //   104: astore 6
    //   106: goto -23 -> 83
    //   109: aload_1
    //   110: invokestatic 343	com/google/android/gms/internal/zzbii:zza	(Landroid/content/Context;)Lcom/google/android/gms/internal/zzbih;
    //   113: aload_2
    //   114: iconst_0
    //   115: invokevirtual 348	com/google/android/gms/internal/zzbih:zzb	(Ljava/lang/String;I)Landroid/content/pm/PackageInfo;
    //   118: astore 11
    //   120: aload 11
    //   122: ifnull +47 -> 169
    //   125: aload_1
    //   126: invokestatic 343	com/google/android/gms/internal/zzbii:zza	(Landroid/content/Context;)Lcom/google/android/gms/internal/zzbih;
    //   129: aload_2
    //   130: invokevirtual 351	com/google/android/gms/internal/zzbih:zzb	(Ljava/lang/String;)Ljava/lang/CharSequence;
    //   133: astore 12
    //   135: aload 12
    //   137: invokestatic 357	android/text/TextUtils:isEmpty	(Ljava/lang/CharSequence;)Z
    //   140: ifne +12 -> 152
    //   143: aload 12
    //   145: invokeinterface 363 1 0
    //   150: astore 8
    //   152: aload 11
    //   154: getfield 369	android/content/pm/PackageInfo:versionName	Ljava/lang/String;
    //   157: astore 7
    //   159: aload 11
    //   161: getfield 372	android/content/pm/PackageInfo:versionCode	I
    //   164: istore 13
    //   166: goto +8 -> 174
    //   169: ldc_w 373
    //   172: istore 13
    //   174: aload 7
    //   176: astore 14
    //   178: new 375	com/google/android/gms/internal/zzcig
    //   181: dup
    //   182: aload_2
    //   183: aload_3
    //   184: aload 14
    //   186: iload 13
    //   188: i2l
    //   189: aload 10
    //   191: ldc2_w 376
    //   194: aload_0
    //   195: invokevirtual 380	com/google/android/gms/internal/zzckk:zzo	()Lcom/google/android/gms/internal/zzcnp;
    //   198: aload_1
    //   199: aload_2
    //   200: invokevirtual 383	com/google/android/gms/internal/zzcnp:zzb	(Landroid/content/Context;Ljava/lang/String;)J
    //   203: aconst_null
    //   204: iload 4
    //   206: iconst_0
    //   207: ldc_w 338
    //   210: lconst_0
    //   211: lconst_0
    //   212: iconst_0
    //   213: iload 5
    //   215: invokespecial 386	com/google/android/gms/internal/zzcig:<init>	(Ljava/lang/String;Ljava/lang/String;Ljava/lang/String;JLjava/lang/String;JJLjava/lang/String;ZZLjava/lang/String;JJIZ)V
    //   218: astore 15
    //   220: aload 15
    //   222: areturn
    //   223: aload_0
    //   224: invokevirtual 232	com/google/android/gms/internal/zzckk:zzf	()Lcom/google/android/gms/internal/zzcjk;
    //   227: invokevirtual 298	com/google/android/gms/internal/zzcjk:zzy	()Lcom/google/android/gms/internal/zzcjm;
    //   230: ldc_w 388
    //   233: aload_2
    //   234: invokestatic 326	com/google/android/gms/internal/zzcjk:zza	(Ljava/lang/String;)Ljava/lang/Object;
    //   237: aload 8
    //   239: invokevirtual 391	com/google/android/gms/internal/zzcjm:zza	(Ljava/lang/String;Ljava/lang/Object;Ljava/lang/Object;)V
    //   242: aconst_null
    //   243: areturn
    // Local variable table:
    //   start	length	slot	name	signature
    //   0	244	0	this	zzckk
    //   0	244	1	paramContext	Context
    //   0	244	2	paramString1	String
    //   0	244	3	paramString2	String
    //   0	244	4	paramBoolean1	boolean
    //   0	244	5	paramBoolean2	boolean
    //   3	102	6	localObject1	Object
    //   8	167	7	str1	String
    //   13	225	8	str2	String
    //   19	23	9	localPackageManager	android.content.pm.PackageManager
    //   85	105	10	localObject2	Object
    //   118	42	11	localPackageInfo	PackageInfo
    //   133	11	12	localCharSequence	CharSequence
    //   164	23	13	i	int
    //   176	9	14	str3	String
    //   218	3	15	localZzcig	zzcig
    //   47	3	16	str4	String
    //   56	1	17	localIllegalArgumentException	IllegalArgumentException
    //   223	1	18	localNameNotFoundException	PackageManager.NameNotFoundException
    // Exception table:
    //   from	to	target	type
    //   41	49	56	java/lang/IllegalArgumentException
    //   109	120	223	android/content/pm/PackageManager$NameNotFoundException
    //   125	152	223	android/content/pm/PackageManager$NameNotFoundException
    //   152	166	223	android/content/pm/PackageManager$NameNotFoundException
  }
  
  public static zzckk zza(Context paramContext)
  {
    zzbq.zza(paramContext);
    zzbq.zza(paramContext.getApplicationContext());
    if (zza == null) {
      try
      {
        if (zza == null) {
          zza = new zzckk(new zzclk(paramContext));
        }
      }
      finally {}
    }
    return zza;
  }
  
  /* Error */
  private final void zza(zzcif paramZzcif)
  {
    // Byte code:
    //   0: aload_0
    //   1: invokevirtual 255	com/google/android/gms/internal/zzckk:zzh	()Lcom/google/android/gms/internal/zzckf;
    //   4: invokevirtual 257	com/google/android/gms/internal/zzcli:zzc	()V
    //   7: aload_1
    //   8: invokevirtual 406	com/google/android/gms/internal/zzcif:zzd	()Ljava/lang/String;
    //   11: invokestatic 357	android/text/TextUtils:isEmpty	(Ljava/lang/CharSequence;)Z
    //   14: ifeq +18 -> 32
    //   17: aload_0
    //   18: aload_1
    //   19: invokevirtual 408	com/google/android/gms/internal/zzcif:zzb	()Ljava/lang/String;
    //   22: sipush 204
    //   25: aconst_null
    //   26: aconst_null
    //   27: aconst_null
    //   28: invokevirtual 411	com/google/android/gms/internal/zzckk:zza	(Ljava/lang/String;ILjava/lang/Throwable;[BLjava/util/Map;)V
    //   31: return
    //   32: aload_1
    //   33: invokevirtual 406	com/google/android/gms/internal/zzcif:zzd	()Ljava/lang/String;
    //   36: astore_2
    //   37: aload_1
    //   38: invokevirtual 413	com/google/android/gms/internal/zzcif:zzc	()Ljava/lang/String;
    //   41: astore_3
    //   42: new 415	android/net/Uri$Builder
    //   45: dup
    //   46: invokespecial 416	android/net/Uri$Builder:<init>	()V
    //   49: astore 4
    //   51: aload 4
    //   53: getstatic 421	com/google/android/gms/internal/zzcja:zzk	Lcom/google/android/gms/internal/zzcjb;
    //   56: invokevirtual 426	com/google/android/gms/internal/zzcjb:zzb	()Ljava/lang/Object;
    //   59: checkcast 332	java/lang/String
    //   62: invokevirtual 430	android/net/Uri$Builder:scheme	(Ljava/lang/String;)Landroid/net/Uri$Builder;
    //   65: getstatic 432	com/google/android/gms/internal/zzcja:zzl	Lcom/google/android/gms/internal/zzcjb;
    //   68: invokevirtual 426	com/google/android/gms/internal/zzcjb:zzb	()Ljava/lang/Object;
    //   71: checkcast 332	java/lang/String
    //   74: invokevirtual 435	android/net/Uri$Builder:encodedAuthority	(Ljava/lang/String;)Landroid/net/Uri$Builder;
    //   77: astore 5
    //   79: aload_2
    //   80: invokestatic 438	java/lang/String:valueOf	(Ljava/lang/Object;)Ljava/lang/String;
    //   83: astore 6
    //   85: aload 6
    //   87: invokevirtual 441	java/lang/String:length	()I
    //   90: ifeq +16 -> 106
    //   93: ldc_w 443
    //   96: aload 6
    //   98: invokevirtual 446	java/lang/String:concat	(Ljava/lang/String;)Ljava/lang/String;
    //   101: astore 7
    //   103: goto +15 -> 118
    //   106: new 332	java/lang/String
    //   109: dup
    //   110: ldc_w 443
    //   113: invokespecial 448	java/lang/String:<init>	(Ljava/lang/String;)V
    //   116: astore 7
    //   118: aload 5
    //   120: aload 7
    //   122: invokevirtual 451	android/net/Uri$Builder:path	(Ljava/lang/String;)Landroid/net/Uri$Builder;
    //   125: ldc_w 453
    //   128: aload_3
    //   129: invokevirtual 457	android/net/Uri$Builder:appendQueryParameter	(Ljava/lang/String;Ljava/lang/String;)Landroid/net/Uri$Builder;
    //   132: ldc_w 459
    //   135: ldc_w 461
    //   138: invokevirtual 457	android/net/Uri$Builder:appendQueryParameter	(Ljava/lang/String;Ljava/lang/String;)Landroid/net/Uri$Builder;
    //   141: ldc_w 463
    //   144: ldc_w 465
    //   147: invokevirtual 457	android/net/Uri$Builder:appendQueryParameter	(Ljava/lang/String;Ljava/lang/String;)Landroid/net/Uri$Builder;
    //   150: pop
    //   151: aload 4
    //   153: invokevirtual 469	android/net/Uri$Builder:build	()Landroid/net/Uri;
    //   156: invokevirtual 472	android/net/Uri:toString	()Ljava/lang/String;
    //   159: astore 9
    //   161: new 474	java/net/URL
    //   164: dup
    //   165: aload 9
    //   167: invokespecial 475	java/net/URL:<init>	(Ljava/lang/String;)V
    //   170: astore 10
    //   172: aload_0
    //   173: invokevirtual 232	com/google/android/gms/internal/zzckk:zzf	()Lcom/google/android/gms/internal/zzcjk;
    //   176: invokevirtual 228	com/google/android/gms/internal/zzcjk:zzae	()Lcom/google/android/gms/internal/zzcjm;
    //   179: ldc_w 477
    //   182: aload_1
    //   183: invokevirtual 408	com/google/android/gms/internal/zzcif:zzb	()Ljava/lang/String;
    //   186: invokevirtual 288	com/google/android/gms/internal/zzcjm:zza	(Ljava/lang/String;Ljava/lang/Object;)V
    //   189: aload_0
    //   190: invokevirtual 480	com/google/android/gms/internal/zzckk:zzj	()Lcom/google/android/gms/internal/zzcke;
    //   193: aload_1
    //   194: invokevirtual 408	com/google/android/gms/internal/zzcif:zzb	()Ljava/lang/String;
    //   197: invokevirtual 483	com/google/android/gms/internal/zzcke:zza	(Ljava/lang/String;)Lcom/google/android/gms/internal/zzcnz;
    //   200: astore 11
    //   202: aload_0
    //   203: invokevirtual 480	com/google/android/gms/internal/zzckk:zzj	()Lcom/google/android/gms/internal/zzcke;
    //   206: aload_1
    //   207: invokevirtual 408	com/google/android/gms/internal/zzcif:zzb	()Ljava/lang/String;
    //   210: invokevirtual 485	com/google/android/gms/internal/zzcke:zzb	(Ljava/lang/String;)Ljava/lang/String;
    //   213: astore 12
    //   215: aload 11
    //   217: ifnull +147 -> 364
    //   220: aload 12
    //   222: invokestatic 357	android/text/TextUtils:isEmpty	(Ljava/lang/CharSequence;)Z
    //   225: ifne +139 -> 364
    //   228: new 487	android/support/v4/h/a
    //   231: dup
    //   232: invokespecial 488	android/support/v4/h/a:<init>	()V
    //   235: astore 13
    //   237: aload 13
    //   239: ldc_w 490
    //   242: aload 12
    //   244: invokeinterface 496 3 0
    //   249: pop
    //   250: aload 13
    //   252: astore 15
    //   254: goto +3 -> 257
    //   257: aload_0
    //   258: iconst_1
    //   259: putfield 498	com/google/android/gms/internal/zzckk:zzal	Z
    //   262: aload_0
    //   263: invokevirtual 501	com/google/android/gms/internal/zzckk:zzs	()Lcom/google/android/gms/internal/zzcjo;
    //   266: astore 16
    //   268: aload_1
    //   269: invokevirtual 408	com/google/android/gms/internal/zzcif:zzb	()Ljava/lang/String;
    //   272: astore 17
    //   274: new 503	com/google/android/gms/internal/zzcko
    //   277: dup
    //   278: aload_0
    //   279: invokespecial 504	com/google/android/gms/internal/zzcko:<init>	(Lcom/google/android/gms/internal/zzckk;)V
    //   282: astore 18
    //   284: aload 16
    //   286: invokevirtual 257	com/google/android/gms/internal/zzcli:zzc	()V
    //   289: aload 16
    //   291: invokevirtual 507	com/google/android/gms/internal/zzclj:zzaq	()V
    //   294: aload 10
    //   296: invokestatic 91	com/google/android/gms/common/internal/zzbq:zza	(Ljava/lang/Object;)Ljava/lang/Object;
    //   299: pop
    //   300: aload 18
    //   302: invokestatic 91	com/google/android/gms/common/internal/zzbq:zza	(Ljava/lang/Object;)Ljava/lang/Object;
    //   305: pop
    //   306: aload 16
    //   308: invokevirtual 509	com/google/android/gms/internal/zzcli:zzs	()Lcom/google/android/gms/internal/zzckf;
    //   311: astore 21
    //   313: new 511	com/google/android/gms/internal/zzcjs
    //   316: dup
    //   317: aload 16
    //   319: aload 17
    //   321: aload 10
    //   323: aconst_null
    //   324: aload 15
    //   326: aload 18
    //   328: invokespecial 514	com/google/android/gms/internal/zzcjs:<init>	(Lcom/google/android/gms/internal/zzcjo;Ljava/lang/String;Ljava/net/URL;[BLjava/util/Map;Lcom/google/android/gms/internal/zzcjq;)V
    //   331: astore 22
    //   333: aload 21
    //   335: aload 22
    //   337: invokevirtual 516	com/google/android/gms/internal/zzckf:zzb	(Ljava/lang/Runnable;)V
    //   340: return
    //   341: aload_0
    //   342: invokevirtual 232	com/google/android/gms/internal/zzckk:zzf	()Lcom/google/android/gms/internal/zzcjk;
    //   345: invokevirtual 298	com/google/android/gms/internal/zzcjk:zzy	()Lcom/google/android/gms/internal/zzcjm;
    //   348: ldc_w 518
    //   351: aload_1
    //   352: invokevirtual 408	com/google/android/gms/internal/zzcif:zzb	()Ljava/lang/String;
    //   355: invokestatic 326	com/google/android/gms/internal/zzcjk:zza	(Ljava/lang/String;)Ljava/lang/Object;
    //   358: aload 9
    //   360: invokevirtual 391	com/google/android/gms/internal/zzcjm:zza	(Ljava/lang/String;Ljava/lang/Object;Ljava/lang/Object;)V
    //   363: return
    //   364: aconst_null
    //   365: astore 15
    //   367: goto -110 -> 257
    // Local variable table:
    //   start	length	slot	name	signature
    //   0	370	0	this	zzckk
    //   0	370	1	paramZzcif	zzcif
    //   36	44	2	str1	String
    //   41	88	3	str2	String
    //   49	103	4	localBuilder1	android.net.Uri.Builder
    //   77	42	5	localBuilder2	android.net.Uri.Builder
    //   83	14	6	str3	String
    //   101	20	7	str4	String
    //   159	200	9	str5	String
    //   170	152	10	localURL	URL
    //   200	16	11	localZzcnz	zzcnz
    //   213	30	12	str6	String
    //   235	16	13	localA1	android.support.v4.h.a
    //   252	114	15	localA2	android.support.v4.h.a
    //   266	52	16	localZzcjo	zzcjo
    //   272	48	17	str7	String
    //   282	45	18	localZzcko	zzcko
    //   341	1	19	localMalformedURLException	MalformedURLException
    //   311	23	21	localZzckf	zzckf
    //   331	5	22	localZzcjs	zzcjs
    // Exception table:
    //   from	to	target	type
    //   161	215	341	java/net/MalformedURLException
    //   220	250	341	java/net/MalformedURLException
    //   257	340	341	java/net/MalformedURLException
  }
  
  private static void zza(zzcli paramZzcli)
  {
    if (paramZzcli == null) {
      throw new IllegalStateException("Component not created");
    }
  }
  
  private final void zza(zzclk paramZzclk)
  {
    zzh().zzc();
    zzcis localZzcis = new zzcis(this);
    localZzcis.zzar();
    this.zzu = localZzcis;
    zzcjf localZzcjf = new zzcjf(this);
    localZzcjf.zzar();
    this.zzv = localZzcjf;
    zzcim localZzcim = new zzcim(this);
    localZzcim.zzar();
    this.zzr = localZzcim;
    zzcjg localZzcjg = new zzcjg(this);
    localZzcjg.zzar();
    this.zzs = localZzcjg;
    zzcii localZzcii = new zzcii(this);
    localZzcii.zzar();
    this.zzy = localZzcii;
    zzcmf localZzcmf = new zzcmf(this);
    localZzcmf.zzar();
    this.zzt = localZzcmf;
    zzcnk localZzcnk = new zzcnk(this);
    localZzcnk.zzar();
    this.zzx = localZzcnk;
    this.zzw = new zzcjt(this);
    this.zzk.zzas();
    this.zzd.zzas();
    this.zzv.zzas();
    zzf().zzac().zza("App measurement is starting up, version", Long.valueOf(12197L));
    zzf().zzac().zza("To enable debug logging run: adb shell setprop log.tag.FA VERBOSE");
    String str1 = localZzcjf.zzz();
    zzcjm localZzcjm;
    String str3;
    if (zzo().zzi(str1))
    {
      localZzcjm = zzf().zzac();
      str3 = "Faster debug mode event logging enabled. To disable, run:\n  adb shell setprop debug.firebase.analytics.app .none.";
    }
    else
    {
      localZzcjm = zzf().zzac();
      String str2 = String.valueOf(str1);
      if (str2.length() != 0) {
        str3 = "To enable faster debug mode event logging run:\n  adb shell setprop debug.firebase.analytics.app ".concat(str2);
      } else {
        str3 = new String("To enable faster debug mode event logging run:\n  adb shell setprop debug.firebase.analytics.app ");
      }
    }
    localZzcjm.zza(str3);
    zzf().zzad().zza("Debug-level message logging enabled");
    if (this.zzah != this.zzai) {
      zzf().zzy().zza("Not all components initialized", Integer.valueOf(this.zzah), Integer.valueOf(this.zzai));
    }
    this.zzz = true;
  }
  
  private final boolean zza(int paramInt, FileChannel paramFileChannel)
  {
    zzh().zzc();
    if ((paramFileChannel != null) && (paramFileChannel.isOpen()))
    {
      ByteBuffer localByteBuffer = ByteBuffer.allocate(4);
      localByteBuffer.putInt(paramInt);
      localByteBuffer.flip();
      try
      {
        paramFileChannel.truncate(0L);
        paramFileChannel.write(localByteBuffer);
        paramFileChannel.force(true);
        if (paramFileChannel.size() != 4L) {
          zzf().zzy().zza("Error writing to channel. Bytes written", Long.valueOf(paramFileChannel.size()));
        }
        return true;
      }
      catch (IOException localIOException)
      {
        zzf().zzy().zza("Failed to write to channel", localIOException);
        return false;
      }
    }
    zzf().zzy().zza("Bad channel to read from");
    return false;
  }
  
  private static boolean zza(zzcoc paramZzcoc, String paramString, Object paramObject)
  {
    if (!TextUtils.isEmpty(paramString))
    {
      if (paramObject == null) {
        return false;
      }
      for (zzcod localZzcod : paramZzcoc.zza) {
        if (paramString.equals(localZzcod.zza)) {
          return (((paramObject instanceof Long)) && (paramObject.equals(localZzcod.zzc))) || (((paramObject instanceof String)) && (paramObject.equals(localZzcod.zzb))) || (((paramObject instanceof Double)) && (paramObject.equals(localZzcod.zzd)));
        }
      }
    }
    return false;
  }
  
  /* Error */
  private final boolean zza(String paramString, long paramLong)
  {
    // Byte code:
    //   0: aload_0
    //   1: invokevirtual 649	com/google/android/gms/internal/zzckk:zzq	()Lcom/google/android/gms/internal/zzcim;
    //   4: invokevirtual 651	com/google/android/gms/internal/zzcim:zzx	()V
    //   7: aconst_null
    //   8: astore 4
    //   10: new 653	com/google/android/gms/internal/zzckk$zza
    //   13: dup
    //   14: aload_0
    //   15: aconst_null
    //   16: invokespecial 656	com/google/android/gms/internal/zzckk$zza:<init>	(Lcom/google/android/gms/internal/zzckk;Lcom/google/android/gms/internal/zzckl;)V
    //   19: astore 5
    //   21: aload_0
    //   22: invokevirtual 649	com/google/android/gms/internal/zzckk:zzq	()Lcom/google/android/gms/internal/zzcim;
    //   25: astore 7
    //   27: aload_0
    //   28: getfield 101	com/google/android/gms/internal/zzckk:zzaj	J
    //   31: lstore 8
    //   33: aload 5
    //   35: invokestatic 91	com/google/android/gms/common/internal/zzbq:zza	(Ljava/lang/Object;)Ljava/lang/Object;
    //   38: pop
    //   39: aload 7
    //   41: invokevirtual 257	com/google/android/gms/internal/zzcli:zzc	()V
    //   44: aload 7
    //   46: invokevirtual 507	com/google/android/gms/internal/zzclj:zzaq	()V
    //   49: aload 7
    //   51: invokevirtual 659	com/google/android/gms/internal/zzcim:zzaa	()Landroid/database/sqlite/SQLiteDatabase;
    //   54: astore -106
    //   56: aconst_null
    //   57: invokestatic 357	android/text/TextUtils:isEmpty	(Ljava/lang/CharSequence;)Z
    //   60: istore -105
    //   62: iload -105
    //   64: ifeq +243 -> 307
    //   67: lload 8
    //   69: ldc2_w 98
    //   72: lcmp
    //   73: istore -65
    //   75: iload -65
    //   77: ifeq +57 -> 134
    //   80: iconst_2
    //   81: anewarray 332	java/lang/String
    //   84: astore -64
    //   86: aload -64
    //   88: iconst_0
    //   89: lload 8
    //   91: invokestatic 662	java/lang/String:valueOf	(J)Ljava/lang/String;
    //   94: aastore
    //   95: aload -64
    //   97: iconst_1
    //   98: lload_2
    //   99: invokestatic 662	java/lang/String:valueOf	(J)Ljava/lang/String;
    //   102: aastore
    //   103: goto +45 -> 148
    //   106: astore -66
    //   108: aload -66
    //   110: astore 16
    //   112: aload 4
    //   114: astore 13
    //   116: goto +4290 -> 4406
    //   119: astore -97
    //   121: aconst_null
    //   122: astore 13
    //   124: aconst_null
    //   125: astore 14
    //   127: aload -97
    //   129: astore 12
    //   131: goto +1021 -> 1152
    //   134: iconst_1
    //   135: anewarray 332	java/lang/String
    //   138: astore -64
    //   140: aload -64
    //   142: iconst_0
    //   143: lload_2
    //   144: invokestatic 662	java/lang/String:valueOf	(J)Ljava/lang/String;
    //   147: aastore
    //   148: iload -65
    //   150: ifeq +11 -> 161
    //   153: ldc_w 664
    //   156: astore -63
    //   158: goto +8 -> 166
    //   161: ldc_w 338
    //   164: astore -63
    //   166: new 666	java/lang/StringBuilder
    //   169: dup
    //   170: sipush 148
    //   173: aload -63
    //   175: invokestatic 438	java/lang/String:valueOf	(Ljava/lang/Object;)Ljava/lang/String;
    //   178: invokevirtual 441	java/lang/String:length	()I
    //   181: iadd
    //   182: invokespecial 669	java/lang/StringBuilder:<init>	(I)V
    //   185: astore -62
    //   187: aload -62
    //   189: ldc_w 671
    //   192: invokevirtual 675	java/lang/StringBuilder:append	(Ljava/lang/String;)Ljava/lang/StringBuilder;
    //   195: pop
    //   196: aload -62
    //   198: aload -63
    //   200: invokevirtual 675	java/lang/StringBuilder:append	(Ljava/lang/String;)Ljava/lang/StringBuilder;
    //   203: pop
    //   204: aload -62
    //   206: ldc_w 677
    //   209: invokevirtual 675	java/lang/StringBuilder:append	(Ljava/lang/String;)Ljava/lang/StringBuilder;
    //   212: pop
    //   213: aload -106
    //   215: aload -62
    //   217: invokevirtual 678	java/lang/StringBuilder:toString	()Ljava/lang/String;
    //   220: aload -64
    //   222: invokevirtual 684	android/database/sqlite/SQLiteDatabase:rawQuery	(Ljava/lang/String;[Ljava/lang/String;)Landroid/database/Cursor;
    //   225: astore 4
    //   227: aload 4
    //   229: invokeinterface 689 1 0
    //   234: istore -58
    //   236: iload -58
    //   238: ifne +18 -> 256
    //   241: aload 4
    //   243: ifnull +938 -> 1181
    //   246: aload 4
    //   248: invokeinterface 692 1 0
    //   253: goto +928 -> 1181
    //   256: aload 4
    //   258: iconst_0
    //   259: invokeinterface 696 2 0
    //   264: astore 14
    //   266: aload 4
    //   268: iconst_1
    //   269: invokeinterface 696 2 0
    //   274: astore -57
    //   276: aload 4
    //   278: invokeinterface 692 1 0
    //   283: aload 4
    //   285: astore -95
    //   287: aload 14
    //   289: astore -93
    //   291: aload -57
    //   293: astore -94
    //   295: goto +167 -> 462
    //   298: astore -97
    //   300: aload 4
    //   302: astore 13
    //   304: goto -177 -> 127
    //   307: lload 8
    //   309: ldc2_w 98
    //   312: lcmp
    //   313: istore -104
    //   315: iload -104
    //   317: ifeq +26 -> 343
    //   320: iconst_2
    //   321: anewarray 332	java/lang/String
    //   324: astore -103
    //   326: aload -103
    //   328: iconst_0
    //   329: aconst_null
    //   330: aastore
    //   331: aload -103
    //   333: iconst_1
    //   334: lload 8
    //   336: invokestatic 662	java/lang/String:valueOf	(J)Ljava/lang/String;
    //   339: aastore
    //   340: goto +4093 -> 4433
    //   343: iconst_1
    //   344: anewarray 332	java/lang/String
    //   347: dup
    //   348: iconst_0
    //   349: aconst_null
    //   350: aastore
    //   351: astore -103
    //   353: goto +4080 -> 4433
    //   356: new 666	java/lang/StringBuilder
    //   359: dup
    //   360: bipush 84
    //   362: aload -102
    //   364: invokestatic 438	java/lang/String:valueOf	(Ljava/lang/Object;)Ljava/lang/String;
    //   367: invokevirtual 441	java/lang/String:length	()I
    //   370: iadd
    //   371: invokespecial 669	java/lang/StringBuilder:<init>	(I)V
    //   374: astore -101
    //   376: aload -101
    //   378: ldc_w 698
    //   381: invokevirtual 675	java/lang/StringBuilder:append	(Ljava/lang/String;)Ljava/lang/StringBuilder;
    //   384: pop
    //   385: aload -101
    //   387: aload -102
    //   389: invokevirtual 675	java/lang/StringBuilder:append	(Ljava/lang/String;)Ljava/lang/StringBuilder;
    //   392: pop
    //   393: aload -101
    //   395: ldc_w 700
    //   398: invokevirtual 675	java/lang/StringBuilder:append	(Ljava/lang/String;)Ljava/lang/StringBuilder;
    //   401: pop
    //   402: aload -106
    //   404: aload -101
    //   406: invokevirtual 678	java/lang/StringBuilder:toString	()Ljava/lang/String;
    //   409: aload -103
    //   411: invokevirtual 684	android/database/sqlite/SQLiteDatabase:rawQuery	(Ljava/lang/String;[Ljava/lang/String;)Landroid/database/Cursor;
    //   414: astore 4
    //   416: aload 4
    //   418: invokeinterface 689 1 0
    //   423: ifne +11 -> 434
    //   426: aload 4
    //   428: ifnull +753 -> 1181
    //   431: goto -185 -> 246
    //   434: aload 4
    //   436: iconst_0
    //   437: invokeinterface 696 2 0
    //   442: astore -96
    //   444: aload 4
    //   446: invokeinterface 692 1 0
    //   451: aload 4
    //   453: astore -95
    //   455: aload -96
    //   457: astore -94
    //   459: aconst_null
    //   460: astore -93
    //   462: aload -106
    //   464: ldc_w 702
    //   467: iconst_1
    //   468: anewarray 332	java/lang/String
    //   471: dup
    //   472: iconst_0
    //   473: ldc_w 704
    //   476: aastore
    //   477: ldc_w 706
    //   480: iconst_2
    //   481: anewarray 332	java/lang/String
    //   484: dup
    //   485: iconst_0
    //   486: aload -93
    //   488: aastore
    //   489: dup
    //   490: iconst_1
    //   491: aload -94
    //   493: aastore
    //   494: aconst_null
    //   495: aconst_null
    //   496: ldc_w 708
    //   499: ldc_w 710
    //   502: invokevirtual 714	android/database/sqlite/SQLiteDatabase:query	(Ljava/lang/String;[Ljava/lang/String;Ljava/lang/String;[Ljava/lang/String;Ljava/lang/String;Ljava/lang/String;Ljava/lang/String;Ljava/lang/String;)Landroid/database/Cursor;
    //   505: astore -91
    //   507: aload -91
    //   509: invokeinterface 689 1 0
    //   514: istore -90
    //   516: iload -90
    //   518: ifne +63 -> 581
    //   521: aload 7
    //   523: invokevirtual 225	com/google/android/gms/internal/zzcli:zzt	()Lcom/google/android/gms/internal/zzcjk;
    //   526: invokevirtual 298	com/google/android/gms/internal/zzcjk:zzy	()Lcom/google/android/gms/internal/zzcjm;
    //   529: ldc_w 716
    //   532: aload -93
    //   534: invokestatic 326	com/google/android/gms/internal/zzcjk:zza	(Ljava/lang/String;)Ljava/lang/Object;
    //   537: invokevirtual 288	com/google/android/gms/internal/zzcjm:zza	(Ljava/lang/String;Ljava/lang/Object;)V
    //   540: aload -91
    //   542: ifnull +639 -> 1181
    //   545: aload -91
    //   547: invokeinterface 692 1 0
    //   552: goto +629 -> 1181
    //   555: astore -67
    //   557: aload -67
    //   559: astore 16
    //   561: aload -91
    //   563: astore 13
    //   565: goto +3841 -> 4406
    //   568: astore -97
    //   570: aload -93
    //   572: astore 14
    //   574: aload -91
    //   576: astore 13
    //   578: goto -451 -> 127
    //   581: aload -91
    //   583: iconst_0
    //   584: invokeinterface 720 2 0
    //   589: astore -89
    //   591: aload -89
    //   593: iconst_0
    //   594: aload -89
    //   596: arraylength
    //   597: invokestatic 725	com/google/android/gms/internal/zzetv:zza	([BII)Lcom/google/android/gms/internal/zzetv;
    //   600: astore -88
    //   602: new 727	com/google/android/gms/internal/zzcof
    //   605: dup
    //   606: invokespecial 728	com/google/android/gms/internal/zzcof:<init>	()V
    //   609: astore -87
    //   611: aload -87
    //   613: aload -88
    //   615: invokevirtual 733	com/google/android/gms/internal/zzeue:zza	(Lcom/google/android/gms/internal/zzetv;)Lcom/google/android/gms/internal/zzeue;
    //   618: pop
    //   619: aload -91
    //   621: invokeinterface 736 1 0
    //   626: istore -84
    //   628: iload -84
    //   630: ifeq +22 -> 652
    //   633: aload 7
    //   635: invokevirtual 225	com/google/android/gms/internal/zzcli:zzt	()Lcom/google/android/gms/internal/zzcjk;
    //   638: invokevirtual 234	com/google/android/gms/internal/zzcjk:zzaa	()Lcom/google/android/gms/internal/zzcjm;
    //   641: ldc_w 738
    //   644: aload -93
    //   646: invokestatic 326	com/google/android/gms/internal/zzcjk:zza	(Ljava/lang/String;)Ljava/lang/Object;
    //   649: invokevirtual 288	com/google/android/gms/internal/zzcjm:zza	(Ljava/lang/String;Ljava/lang/Object;)V
    //   652: aload -91
    //   654: invokeinterface 692 1 0
    //   659: aload 5
    //   661: aload -87
    //   663: invokeinterface 743 2 0
    //   668: lload 8
    //   670: ldc2_w 98
    //   673: lcmp
    //   674: ifeq +42 -> 716
    //   677: iconst_3
    //   678: anewarray 332	java/lang/String
    //   681: astore -68
    //   683: aload -68
    //   685: iconst_0
    //   686: aload -93
    //   688: aastore
    //   689: aload -68
    //   691: iconst_1
    //   692: aload -94
    //   694: aastore
    //   695: aload -68
    //   697: iconst_2
    //   698: lload 8
    //   700: invokestatic 662	java/lang/String:valueOf	(J)Ljava/lang/String;
    //   703: aastore
    //   704: ldc_w 745
    //   707: astore -83
    //   709: aload -68
    //   711: astore -82
    //   713: goto +24 -> 737
    //   716: ldc_w 706
    //   719: astore -83
    //   721: iconst_2
    //   722: anewarray 332	java/lang/String
    //   725: dup
    //   726: iconst_0
    //   727: aload -93
    //   729: aastore
    //   730: dup
    //   731: iconst_1
    //   732: aload -94
    //   734: aastore
    //   735: astore -82
    //   737: iconst_4
    //   738: anewarray 332	java/lang/String
    //   741: dup
    //   742: iconst_0
    //   743: ldc_w 708
    //   746: aastore
    //   747: dup
    //   748: iconst_1
    //   749: ldc_w 747
    //   752: aastore
    //   753: dup
    //   754: iconst_2
    //   755: ldc_w 749
    //   758: aastore
    //   759: dup
    //   760: iconst_3
    //   761: ldc_w 751
    //   764: aastore
    //   765: astore -81
    //   767: iconst_3
    //   768: istore -80
    //   770: aload -91
    //   772: astore 13
    //   774: aload -83
    //   776: astore -79
    //   778: aload -106
    //   780: ldc_w 753
    //   783: aload -81
    //   785: aload -79
    //   787: aload -82
    //   789: aconst_null
    //   790: aconst_null
    //   791: ldc_w 708
    //   794: aconst_null
    //   795: invokevirtual 714	android/database/sqlite/SQLiteDatabase:query	(Ljava/lang/String;[Ljava/lang/String;Ljava/lang/String;[Ljava/lang/String;Ljava/lang/String;Ljava/lang/String;Ljava/lang/String;Ljava/lang/String;)Landroid/database/Cursor;
    //   798: astore -78
    //   800: aload -78
    //   802: invokeinterface 689 1 0
    //   807: ifne +37 -> 844
    //   810: aload 7
    //   812: invokevirtual 225	com/google/android/gms/internal/zzcli:zzt	()Lcom/google/android/gms/internal/zzcjk;
    //   815: invokevirtual 234	com/google/android/gms/internal/zzcjk:zzaa	()Lcom/google/android/gms/internal/zzcjm;
    //   818: ldc_w 755
    //   821: aload -93
    //   823: invokestatic 326	com/google/android/gms/internal/zzcjk:zza	(Ljava/lang/String;)Ljava/lang/Object;
    //   826: invokevirtual 288	com/google/android/gms/internal/zzcjm:zza	(Ljava/lang/String;Ljava/lang/Object;)V
    //   829: aload -78
    //   831: ifnull +350 -> 1181
    //   834: aload -78
    //   836: invokeinterface 692 1 0
    //   841: goto +340 -> 1181
    //   844: aload -78
    //   846: iconst_0
    //   847: invokeinterface 759 2 0
    //   852: lstore -76
    //   854: aload -78
    //   856: iload -80
    //   858: invokeinterface 720 2 0
    //   863: astore -74
    //   865: aload -74
    //   867: iconst_0
    //   868: aload -74
    //   870: arraylength
    //   871: invokestatic 725	com/google/android/gms/internal/zzetv:zza	([BII)Lcom/google/android/gms/internal/zzetv;
    //   874: astore -73
    //   876: new 625	com/google/android/gms/internal/zzcoc
    //   879: dup
    //   880: invokespecial 760	com/google/android/gms/internal/zzcoc:<init>	()V
    //   883: astore -72
    //   885: aload -72
    //   887: aload -73
    //   889: invokevirtual 733	com/google/android/gms/internal/zzeue:zza	(Lcom/google/android/gms/internal/zzetv;)Lcom/google/android/gms/internal/zzeue;
    //   892: pop
    //   893: aload -72
    //   895: aload -78
    //   897: iconst_1
    //   898: invokeinterface 696 2 0
    //   903: putfield 761	com/google/android/gms/internal/zzcoc:zzb	Ljava/lang/String;
    //   906: aload -72
    //   908: aload -78
    //   910: iconst_2
    //   911: invokeinterface 759 2 0
    //   916: invokestatic 578	java/lang/Long:valueOf	(J)Ljava/lang/Long;
    //   919: putfield 762	com/google/android/gms/internal/zzcoc:zzc	Ljava/lang/Long;
    //   922: aload 5
    //   924: lload -76
    //   926: aload -72
    //   928: invokeinterface 765 4 0
    //   933: ifne +34 -> 967
    //   936: aload -78
    //   938: ifnull +243 -> 1181
    //   941: goto -107 -> 834
    //   944: astore -71
    //   946: aload 7
    //   948: invokevirtual 225	com/google/android/gms/internal/zzcli:zzt	()Lcom/google/android/gms/internal/zzcjk;
    //   951: invokevirtual 298	com/google/android/gms/internal/zzcjk:zzy	()Lcom/google/android/gms/internal/zzcjm;
    //   954: ldc_w 767
    //   957: aload -93
    //   959: invokestatic 326	com/google/android/gms/internal/zzcjk:zza	(Ljava/lang/String;)Ljava/lang/Object;
    //   962: aload -71
    //   964: invokevirtual 391	com/google/android/gms/internal/zzcjm:zza	(Ljava/lang/String;Ljava/lang/Object;Ljava/lang/Object;)V
    //   967: aload -78
    //   969: invokeinterface 736 1 0
    //   974: istore -70
    //   976: iload -70
    //   978: ifne +11 -> 989
    //   981: aload -78
    //   983: ifnull +198 -> 1181
    //   986: goto -152 -> 834
    //   989: iconst_3
    //   990: istore -80
    //   992: goto -148 -> 844
    //   995: astore -77
    //   997: aload -77
    //   999: astore 16
    //   1001: aload -78
    //   1003: astore 13
    //   1005: goto +3401 -> 4406
    //   1008: astore -97
    //   1010: aload -93
    //   1012: astore 14
    //   1014: aload -78
    //   1016: astore 13
    //   1018: goto -891 -> 127
    //   1021: astore -86
    //   1023: aload -91
    //   1025: astore 13
    //   1027: aload 7
    //   1029: invokevirtual 225	com/google/android/gms/internal/zzcli:zzt	()Lcom/google/android/gms/internal/zzcjk;
    //   1032: invokevirtual 298	com/google/android/gms/internal/zzcjk:zzy	()Lcom/google/android/gms/internal/zzcjm;
    //   1035: ldc_w 769
    //   1038: aload -93
    //   1040: invokestatic 326	com/google/android/gms/internal/zzcjk:zza	(Ljava/lang/String;)Ljava/lang/Object;
    //   1043: aload -86
    //   1045: invokevirtual 391	com/google/android/gms/internal/zzcjm:zza	(Ljava/lang/String;Ljava/lang/Object;Ljava/lang/Object;)V
    //   1048: aload 13
    //   1050: ifnull +131 -> 1181
    //   1053: aload 13
    //   1055: invokeinterface 692 1 0
    //   1060: goto +121 -> 1181
    //   1063: astore -97
    //   1065: goto +18 -> 1083
    //   1068: astore 15
    //   1070: aload -91
    //   1072: astore 13
    //   1074: goto +3328 -> 4402
    //   1077: astore -97
    //   1079: aload -91
    //   1081: astore 13
    //   1083: aload -93
    //   1085: astore 14
    //   1087: goto -960 -> 127
    //   1090: astore -92
    //   1092: aload -92
    //   1094: astore 16
    //   1096: aload -95
    //   1098: astore 13
    //   1100: goto +3306 -> 4406
    //   1103: astore -97
    //   1105: aload -93
    //   1107: astore 14
    //   1109: aload -95
    //   1111: astore 13
    //   1113: goto -986 -> 127
    //   1116: astore -97
    //   1118: aload 4
    //   1120: astore 13
    //   1122: aconst_null
    //   1123: astore 14
    //   1125: goto -998 -> 127
    //   1128: astore -107
    //   1130: aload -107
    //   1132: astore 16
    //   1134: aconst_null
    //   1135: astore 13
    //   1137: goto +3269 -> 4406
    //   1140: astore 11
    //   1142: aload 11
    //   1144: astore 12
    //   1146: aconst_null
    //   1147: astore 13
    //   1149: aconst_null
    //   1150: astore 14
    //   1152: aload 7
    //   1154: invokevirtual 225	com/google/android/gms/internal/zzcli:zzt	()Lcom/google/android/gms/internal/zzcjk;
    //   1157: invokevirtual 298	com/google/android/gms/internal/zzcjk:zzy	()Lcom/google/android/gms/internal/zzcjm;
    //   1160: ldc_w 771
    //   1163: aload 14
    //   1165: invokestatic 326	com/google/android/gms/internal/zzcjk:zza	(Ljava/lang/String;)Ljava/lang/Object;
    //   1168: aload 12
    //   1170: invokevirtual 391	com/google/android/gms/internal/zzcjm:zza	(Ljava/lang/String;Ljava/lang/Object;Ljava/lang/Object;)V
    //   1173: aload 13
    //   1175: ifnull +6 -> 1181
    //   1178: goto -125 -> 1053
    //   1181: aload 5
    //   1183: getfield 773	com/google/android/gms/internal/zzckk$zza:zzc	Ljava/util/List;
    //   1186: ifnull +3274 -> 4460
    //   1189: aload 5
    //   1191: getfield 773	com/google/android/gms/internal/zzckk$zza:zzc	Ljava/util/List;
    //   1194: invokeinterface 777 1 0
    //   1199: ifeq +3255 -> 4454
    //   1202: goto +3258 -> 4460
    //   1205: iload 17
    //   1207: ifne +3177 -> 4384
    //   1210: aload 5
    //   1212: getfield 780	com/google/android/gms/internal/zzckk$zza:zza	Lcom/google/android/gms/internal/zzcof;
    //   1215: astore 18
    //   1217: aload 18
    //   1219: aload 5
    //   1221: getfield 773	com/google/android/gms/internal/zzckk$zza:zzc	Ljava/util/List;
    //   1224: invokeinterface 782 1 0
    //   1229: anewarray 625	com/google/android/gms/internal/zzcoc
    //   1232: putfield 785	com/google/android/gms/internal/zzcof:zzb	[Lcom/google/android/gms/internal/zzcoc;
    //   1235: aload_0
    //   1236: getfield 122	com/google/android/gms/internal/zzckk:zzc	Lcom/google/android/gms/internal/zzcil;
    //   1239: aload 18
    //   1241: getfield 787	com/google/android/gms/internal/zzcof:zzo	Ljava/lang/String;
    //   1244: invokevirtual 789	com/google/android/gms/internal/zzcil:zzd	(Ljava/lang/String;)Z
    //   1247: istore 19
    //   1249: iconst_0
    //   1250: istore 20
    //   1252: iconst_0
    //   1253: istore 21
    //   1255: iconst_0
    //   1256: istore 22
    //   1258: lconst_0
    //   1259: lstore 23
    //   1261: iload 20
    //   1263: aload 5
    //   1265: getfield 773	com/google/android/gms/internal/zzckk$zza:zzc	Ljava/util/List;
    //   1268: invokeinterface 782 1 0
    //   1273: if_icmpge +1130 -> 2403
    //   1276: aload 5
    //   1278: getfield 773	com/google/android/gms/internal/zzckk$zza:zzc	Ljava/util/List;
    //   1281: iload 20
    //   1283: invokeinterface 793 2 0
    //   1288: checkcast 625	com/google/android/gms/internal/zzcoc
    //   1291: astore 112
    //   1293: aload_0
    //   1294: invokevirtual 480	com/google/android/gms/internal/zzckk:zzj	()Lcom/google/android/gms/internal/zzcke;
    //   1297: aload 5
    //   1299: getfield 780	com/google/android/gms/internal/zzckk$zza:zza	Lcom/google/android/gms/internal/zzcof;
    //   1302: getfield 787	com/google/android/gms/internal/zzcof:zzo	Ljava/lang/String;
    //   1305: aload 112
    //   1307: getfield 761	com/google/android/gms/internal/zzcoc:zzb	Ljava/lang/String;
    //   1310: invokevirtual 796	com/google/android/gms/internal/zzcke:zzb	(Ljava/lang/String;Ljava/lang/String;)Z
    //   1313: ifeq +126 -> 1439
    //   1316: aload_0
    //   1317: invokevirtual 232	com/google/android/gms/internal/zzckk:zzf	()Lcom/google/android/gms/internal/zzcjk;
    //   1320: invokevirtual 234	com/google/android/gms/internal/zzcjk:zzaa	()Lcom/google/android/gms/internal/zzcjm;
    //   1323: ldc_w 798
    //   1326: aload 5
    //   1328: getfield 780	com/google/android/gms/internal/zzckk$zza:zza	Lcom/google/android/gms/internal/zzcof;
    //   1331: getfield 787	com/google/android/gms/internal/zzcof:zzo	Ljava/lang/String;
    //   1334: invokestatic 326	com/google/android/gms/internal/zzcjk:zza	(Ljava/lang/String;)Ljava/lang/Object;
    //   1337: aload_0
    //   1338: invokevirtual 801	com/google/android/gms/internal/zzckk:zzp	()Lcom/google/android/gms/internal/zzcji;
    //   1341: aload 112
    //   1343: getfield 761	com/google/android/gms/internal/zzcoc:zzb	Ljava/lang/String;
    //   1346: invokevirtual 803	com/google/android/gms/internal/zzcji:zza	(Ljava/lang/String;)Ljava/lang/String;
    //   1349: invokevirtual 391	com/google/android/gms/internal/zzcjm:zza	(Ljava/lang/String;Ljava/lang/Object;Ljava/lang/Object;)V
    //   1352: aload_0
    //   1353: invokevirtual 380	com/google/android/gms/internal/zzckk:zzo	()Lcom/google/android/gms/internal/zzcnp;
    //   1356: aload 5
    //   1358: getfield 780	com/google/android/gms/internal/zzckk$zza:zza	Lcom/google/android/gms/internal/zzcof;
    //   1361: getfield 787	com/google/android/gms/internal/zzcof:zzo	Ljava/lang/String;
    //   1364: invokevirtual 805	com/google/android/gms/internal/zzcnp:zzk	(Ljava/lang/String;)Z
    //   1367: ifne +3105 -> 4472
    //   1370: aload_0
    //   1371: invokevirtual 380	com/google/android/gms/internal/zzckk:zzo	()Lcom/google/android/gms/internal/zzcnp;
    //   1374: aload 5
    //   1376: getfield 780	com/google/android/gms/internal/zzckk$zza:zza	Lcom/google/android/gms/internal/zzcof;
    //   1379: getfield 787	com/google/android/gms/internal/zzcof:zzo	Ljava/lang/String;
    //   1382: invokevirtual 807	com/google/android/gms/internal/zzcnp:zzl	(Ljava/lang/String;)Z
    //   1385: ifeq +3081 -> 4466
    //   1388: goto +3084 -> 4472
    //   1391: iload -108
    //   1393: ifne +3085 -> 4478
    //   1396: ldc_w 809
    //   1399: aload 112
    //   1401: getfield 761	com/google/android/gms/internal/zzcoc:zzb	Ljava/lang/String;
    //   1404: invokevirtual 336	java/lang/String:equals	(Ljava/lang/Object;)Z
    //   1407: ifne +3071 -> 4478
    //   1410: aload_0
    //   1411: invokevirtual 380	com/google/android/gms/internal/zzckk:zzo	()Lcom/google/android/gms/internal/zzcnp;
    //   1414: aload 5
    //   1416: getfield 780	com/google/android/gms/internal/zzckk$zza:zza	Lcom/google/android/gms/internal/zzcof;
    //   1419: getfield 787	com/google/android/gms/internal/zzcof:zzo	Ljava/lang/String;
    //   1422: bipush 11
    //   1424: ldc_w 811
    //   1427: aload 112
    //   1429: getfield 761	com/google/android/gms/internal/zzcoc:zzb	Ljava/lang/String;
    //   1432: iconst_0
    //   1433: invokevirtual 814	com/google/android/gms/internal/zzcnp:zza	(Ljava/lang/String;ILjava/lang/String;Ljava/lang/String;I)V
    //   1436: goto +3042 -> 4478
    //   1439: aload_0
    //   1440: invokevirtual 480	com/google/android/gms/internal/zzckk:zzj	()Lcom/google/android/gms/internal/zzcke;
    //   1443: aload 5
    //   1445: getfield 780	com/google/android/gms/internal/zzckk$zza:zza	Lcom/google/android/gms/internal/zzcof;
    //   1448: getfield 787	com/google/android/gms/internal/zzcof:zzo	Ljava/lang/String;
    //   1451: aload 112
    //   1453: getfield 761	com/google/android/gms/internal/zzcoc:zzb	Ljava/lang/String;
    //   1456: invokevirtual 816	com/google/android/gms/internal/zzcke:zzc	(Ljava/lang/String;Ljava/lang/String;)Z
    //   1459: istore 113
    //   1461: iload 113
    //   1463: ifne +22 -> 1485
    //   1466: aload_0
    //   1467: invokevirtual 380	com/google/android/gms/internal/zzckk:zzo	()Lcom/google/android/gms/internal/zzcnp;
    //   1470: pop
    //   1471: aload 112
    //   1473: getfield 761	com/google/android/gms/internal/zzcoc:zzb	Ljava/lang/String;
    //   1476: invokestatic 818	com/google/android/gms/internal/zzcnp:zzm	(Ljava/lang/String;)Z
    //   1479: ifeq +3006 -> 4485
    //   1482: goto +3 -> 1485
    //   1485: aload 112
    //   1487: getfield 628	com/google/android/gms/internal/zzcoc:zza	[Lcom/google/android/gms/internal/zzcod;
    //   1490: ifnonnull +12 -> 1502
    //   1493: aload 112
    //   1495: iconst_0
    //   1496: anewarray 630	com/google/android/gms/internal/zzcod
    //   1499: putfield 628	com/google/android/gms/internal/zzcoc:zza	[Lcom/google/android/gms/internal/zzcod;
    //   1502: aload 112
    //   1504: getfield 628	com/google/android/gms/internal/zzcoc:zza	[Lcom/google/android/gms/internal/zzcod;
    //   1507: astore 115
    //   1509: aload 115
    //   1511: arraylength
    //   1512: istore 116
    //   1514: iconst_0
    //   1515: istore 117
    //   1517: iconst_0
    //   1518: istore 118
    //   1520: iconst_0
    //   1521: istore 119
    //   1523: iload 117
    //   1525: iload 116
    //   1527: if_icmpge +88 -> 1615
    //   1530: iload 116
    //   1532: istore -113
    //   1534: aload 115
    //   1536: iload 117
    //   1538: aaload
    //   1539: astore -112
    //   1541: aload 115
    //   1543: astore -111
    //   1545: iload 21
    //   1547: istore -110
    //   1549: ldc_w 820
    //   1552: aload -112
    //   1554: getfield 632	com/google/android/gms/internal/zzcod:zza	Ljava/lang/String;
    //   1557: invokevirtual 336	java/lang/String:equals	(Ljava/lang/Object;)Z
    //   1560: ifeq +22 -> 1582
    //   1563: iload 20
    //   1565: istore -109
    //   1567: aload -112
    //   1569: lconst_1
    //   1570: invokestatic 578	java/lang/Long:valueOf	(J)Ljava/lang/Long;
    //   1573: putfield 635	com/google/android/gms/internal/zzcod:zzc	Ljava/lang/Long;
    //   1576: iconst_1
    //   1577: istore 118
    //   1579: goto +2913 -> 4492
    //   1582: iload 20
    //   1584: istore -109
    //   1586: ldc_w 822
    //   1589: aload -112
    //   1591: getfield 632	com/google/android/gms/internal/zzcod:zza	Ljava/lang/String;
    //   1594: invokevirtual 336	java/lang/String:equals	(Ljava/lang/Object;)Z
    //   1597: ifeq +2895 -> 4492
    //   1600: aload -112
    //   1602: lconst_1
    //   1603: invokestatic 578	java/lang/Long:valueOf	(J)Ljava/lang/Long;
    //   1606: putfield 635	com/google/android/gms/internal/zzcod:zzc	Ljava/lang/Long;
    //   1609: iconst_1
    //   1610: istore 119
    //   1612: goto +2880 -> 4492
    //   1615: iload 20
    //   1617: istore 120
    //   1619: iload 21
    //   1621: istore 121
    //   1623: iload 118
    //   1625: ifne +97 -> 1722
    //   1628: iload 113
    //   1630: ifeq +92 -> 1722
    //   1633: aload_0
    //   1634: invokevirtual 232	com/google/android/gms/internal/zzckk:zzf	()Lcom/google/android/gms/internal/zzcjk;
    //   1637: invokevirtual 228	com/google/android/gms/internal/zzcjk:zzae	()Lcom/google/android/gms/internal/zzcjm;
    //   1640: ldc_w 824
    //   1643: aload_0
    //   1644: invokevirtual 801	com/google/android/gms/internal/zzckk:zzp	()Lcom/google/android/gms/internal/zzcji;
    //   1647: aload 112
    //   1649: getfield 761	com/google/android/gms/internal/zzcoc:zzb	Ljava/lang/String;
    //   1652: invokevirtual 803	com/google/android/gms/internal/zzcji:zza	(Ljava/lang/String;)Ljava/lang/String;
    //   1655: invokevirtual 288	com/google/android/gms/internal/zzcjm:zza	(Ljava/lang/String;Ljava/lang/Object;)V
    //   1658: aload 112
    //   1660: getfield 628	com/google/android/gms/internal/zzcoc:zza	[Lcom/google/android/gms/internal/zzcod;
    //   1663: iconst_1
    //   1664: aload 112
    //   1666: getfield 628	com/google/android/gms/internal/zzcoc:zza	[Lcom/google/android/gms/internal/zzcod;
    //   1669: arraylength
    //   1670: iadd
    //   1671: invokestatic 830	java/util/Arrays:copyOf	([Ljava/lang/Object;I)[Ljava/lang/Object;
    //   1674: checkcast 831	[Lcom/google/android/gms/internal/zzcod;
    //   1677: astore -115
    //   1679: new 630	com/google/android/gms/internal/zzcod
    //   1682: dup
    //   1683: invokespecial 832	com/google/android/gms/internal/zzcod:<init>	()V
    //   1686: astore -114
    //   1688: aload -114
    //   1690: ldc_w 820
    //   1693: putfield 632	com/google/android/gms/internal/zzcod:zza	Ljava/lang/String;
    //   1696: aload -114
    //   1698: lconst_1
    //   1699: invokestatic 578	java/lang/Long:valueOf	(J)Ljava/lang/Long;
    //   1702: putfield 635	com/google/android/gms/internal/zzcod:zzc	Ljava/lang/Long;
    //   1705: aload -115
    //   1707: aload -115
    //   1709: arraylength
    //   1710: iconst_1
    //   1711: isub
    //   1712: aload -114
    //   1714: aastore
    //   1715: aload 112
    //   1717: aload -115
    //   1719: putfield 628	com/google/android/gms/internal/zzcoc:zza	[Lcom/google/android/gms/internal/zzcod;
    //   1722: iload 119
    //   1724: ifne +92 -> 1816
    //   1727: aload_0
    //   1728: invokevirtual 232	com/google/android/gms/internal/zzckk:zzf	()Lcom/google/android/gms/internal/zzcjk;
    //   1731: invokevirtual 228	com/google/android/gms/internal/zzcjk:zzae	()Lcom/google/android/gms/internal/zzcjm;
    //   1734: ldc_w 834
    //   1737: aload_0
    //   1738: invokevirtual 801	com/google/android/gms/internal/zzckk:zzp	()Lcom/google/android/gms/internal/zzcji;
    //   1741: aload 112
    //   1743: getfield 761	com/google/android/gms/internal/zzcoc:zzb	Ljava/lang/String;
    //   1746: invokevirtual 803	com/google/android/gms/internal/zzcji:zza	(Ljava/lang/String;)Ljava/lang/String;
    //   1749: invokevirtual 288	com/google/android/gms/internal/zzcjm:zza	(Ljava/lang/String;Ljava/lang/Object;)V
    //   1752: aload 112
    //   1754: getfield 628	com/google/android/gms/internal/zzcoc:zza	[Lcom/google/android/gms/internal/zzcod;
    //   1757: iconst_1
    //   1758: aload 112
    //   1760: getfield 628	com/google/android/gms/internal/zzcoc:zza	[Lcom/google/android/gms/internal/zzcod;
    //   1763: arraylength
    //   1764: iadd
    //   1765: invokestatic 830	java/util/Arrays:copyOf	([Ljava/lang/Object;I)[Ljava/lang/Object;
    //   1768: checkcast 831	[Lcom/google/android/gms/internal/zzcod;
    //   1771: astore 122
    //   1773: new 630	com/google/android/gms/internal/zzcod
    //   1776: dup
    //   1777: invokespecial 832	com/google/android/gms/internal/zzcod:<init>	()V
    //   1780: astore 123
    //   1782: aload 123
    //   1784: ldc_w 822
    //   1787: putfield 632	com/google/android/gms/internal/zzcod:zza	Ljava/lang/String;
    //   1790: aload 123
    //   1792: lconst_1
    //   1793: invokestatic 578	java/lang/Long:valueOf	(J)Ljava/lang/Long;
    //   1796: putfield 635	com/google/android/gms/internal/zzcod:zzc	Ljava/lang/Long;
    //   1799: aload 122
    //   1801: aload 122
    //   1803: arraylength
    //   1804: iconst_1
    //   1805: isub
    //   1806: aload 123
    //   1808: aastore
    //   1809: aload 112
    //   1811: aload 122
    //   1813: putfield 628	com/google/android/gms/internal/zzcoc:zza	[Lcom/google/android/gms/internal/zzcod;
    //   1816: aload_0
    //   1817: invokevirtual 649	com/google/android/gms/internal/zzckk:zzq	()Lcom/google/android/gms/internal/zzcim;
    //   1820: aload_0
    //   1821: invokespecial 836	com/google/android/gms/internal/zzckk:zzak	()J
    //   1824: aload 5
    //   1826: getfield 780	com/google/android/gms/internal/zzckk$zza:zza	Lcom/google/android/gms/internal/zzcof;
    //   1829: getfield 787	com/google/android/gms/internal/zzcof:zzo	Ljava/lang/String;
    //   1832: iconst_0
    //   1833: iconst_0
    //   1834: iconst_0
    //   1835: iconst_0
    //   1836: iconst_1
    //   1837: invokevirtual 839	com/google/android/gms/internal/zzcim:zza	(JLjava/lang/String;ZZZZZ)Lcom/google/android/gms/internal/zzcin;
    //   1840: getfield 843	com/google/android/gms/internal/zzcin:zze	J
    //   1843: aload_0
    //   1844: getfield 122	com/google/android/gms/internal/zzckk:zzc	Lcom/google/android/gms/internal/zzcil;
    //   1847: aload 5
    //   1849: getfield 780	com/google/android/gms/internal/zzckk$zza:zza	Lcom/google/android/gms/internal/zzcof;
    //   1852: getfield 787	com/google/android/gms/internal/zzcof:zzo	Ljava/lang/String;
    //   1855: invokevirtual 846	com/google/android/gms/internal/zzcil:zza	(Ljava/lang/String;)I
    //   1858: i2l
    //   1859: lcmp
    //   1860: ifle +2667 -> 4527
    //   1863: iconst_0
    //   1864: istore 124
    //   1866: iload 124
    //   1868: aload 112
    //   1870: getfield 628	com/google/android/gms/internal/zzcoc:zza	[Lcom/google/android/gms/internal/zzcod;
    //   1873: arraylength
    //   1874: if_icmpge +2646 -> 4520
    //   1877: ldc_w 822
    //   1880: aload 112
    //   1882: getfield 628	com/google/android/gms/internal/zzcoc:zza	[Lcom/google/android/gms/internal/zzcod;
    //   1885: iload 124
    //   1887: aaload
    //   1888: getfield 632	com/google/android/gms/internal/zzcod:zza	Ljava/lang/String;
    //   1891: invokevirtual 336	java/lang/String:equals	(Ljava/lang/Object;)Z
    //   1894: ifeq +2620 -> 4514
    //   1897: aload 112
    //   1899: getfield 628	com/google/android/gms/internal/zzcoc:zza	[Lcom/google/android/gms/internal/zzcod;
    //   1902: arraylength
    //   1903: iconst_1
    //   1904: isub
    //   1905: anewarray 630	com/google/android/gms/internal/zzcod
    //   1908: astore -116
    //   1910: iload 124
    //   1912: ifle +17 -> 1929
    //   1915: aload 112
    //   1917: getfield 628	com/google/android/gms/internal/zzcoc:zza	[Lcom/google/android/gms/internal/zzcod;
    //   1920: iconst_0
    //   1921: aload -116
    //   1923: iconst_0
    //   1924: iload 124
    //   1926: invokestatic 852	java/lang/System:arraycopy	(Ljava/lang/Object;ILjava/lang/Object;II)V
    //   1929: iload 124
    //   1931: aload -116
    //   1933: arraylength
    //   1934: if_icmpge +25 -> 1959
    //   1937: aload 112
    //   1939: getfield 628	com/google/android/gms/internal/zzcoc:zza	[Lcom/google/android/gms/internal/zzcod;
    //   1942: iload 124
    //   1944: iconst_1
    //   1945: iadd
    //   1946: aload -116
    //   1948: iload 124
    //   1950: aload -116
    //   1952: arraylength
    //   1953: iload 124
    //   1955: isub
    //   1956: invokestatic 852	java/lang/System:arraycopy	(Ljava/lang/Object;ILjava/lang/Object;II)V
    //   1959: aload 112
    //   1961: aload -116
    //   1963: putfield 628	com/google/android/gms/internal/zzcoc:zza	[Lcom/google/android/gms/internal/zzcod;
    //   1966: goto +2554 -> 4520
    //   1969: aload 112
    //   1971: getfield 761	com/google/android/gms/internal/zzcoc:zzb	Ljava/lang/String;
    //   1974: invokestatic 854	com/google/android/gms/internal/zzcnp:zza	(Ljava/lang/String;)Z
    //   1977: ifeq +255 -> 2232
    //   1980: iload 113
    //   1982: ifeq +250 -> 2232
    //   1985: aload_0
    //   1986: invokevirtual 649	com/google/android/gms/internal/zzckk:zzq	()Lcom/google/android/gms/internal/zzcim;
    //   1989: aload_0
    //   1990: invokespecial 836	com/google/android/gms/internal/zzckk:zzak	()J
    //   1993: aload 5
    //   1995: getfield 780	com/google/android/gms/internal/zzckk$zza:zza	Lcom/google/android/gms/internal/zzcof;
    //   1998: getfield 787	com/google/android/gms/internal/zzcof:zzo	Ljava/lang/String;
    //   2001: iconst_0
    //   2002: iconst_0
    //   2003: iconst_1
    //   2004: iconst_0
    //   2005: iconst_0
    //   2006: invokevirtual 839	com/google/android/gms/internal/zzcim:zza	(JLjava/lang/String;ZZZZZ)Lcom/google/android/gms/internal/zzcin;
    //   2009: getfield 856	com/google/android/gms/internal/zzcin:zzc	J
    //   2012: aload_0
    //   2013: getfield 122	com/google/android/gms/internal/zzckk:zzc	Lcom/google/android/gms/internal/zzcil;
    //   2016: aload 5
    //   2018: getfield 780	com/google/android/gms/internal/zzckk$zza:zza	Lcom/google/android/gms/internal/zzcof;
    //   2021: getfield 787	com/google/android/gms/internal/zzcof:zzo	Ljava/lang/String;
    //   2024: getstatic 858	com/google/android/gms/internal/zzcja:zzt	Lcom/google/android/gms/internal/zzcjb;
    //   2027: invokevirtual 861	com/google/android/gms/internal/zzcil:zzb	(Ljava/lang/String;Lcom/google/android/gms/internal/zzcjb;)I
    //   2030: i2l
    //   2031: lcmp
    //   2032: ifle +200 -> 2232
    //   2035: aload_0
    //   2036: invokevirtual 232	com/google/android/gms/internal/zzckk:zzf	()Lcom/google/android/gms/internal/zzcjk;
    //   2039: invokevirtual 234	com/google/android/gms/internal/zzcjk:zzaa	()Lcom/google/android/gms/internal/zzcjm;
    //   2042: ldc_w 863
    //   2045: aload 5
    //   2047: getfield 780	com/google/android/gms/internal/zzckk$zza:zza	Lcom/google/android/gms/internal/zzcof;
    //   2050: getfield 787	com/google/android/gms/internal/zzcof:zzo	Ljava/lang/String;
    //   2053: invokestatic 326	com/google/android/gms/internal/zzcjk:zza	(Ljava/lang/String;)Ljava/lang/Object;
    //   2056: invokevirtual 288	com/google/android/gms/internal/zzcjm:zza	(Ljava/lang/String;Ljava/lang/Object;)V
    //   2059: aload 112
    //   2061: getfield 628	com/google/android/gms/internal/zzcoc:zza	[Lcom/google/android/gms/internal/zzcod;
    //   2064: astore -124
    //   2066: aload -124
    //   2068: arraylength
    //   2069: istore -123
    //   2071: iconst_0
    //   2072: istore -122
    //   2074: iconst_0
    //   2075: istore -121
    //   2077: aconst_null
    //   2078: astore -120
    //   2080: iload -122
    //   2082: iload -123
    //   2084: if_icmpge +59 -> 2143
    //   2087: aload -124
    //   2089: iload -122
    //   2091: aaload
    //   2092: astore -119
    //   2094: aload -124
    //   2096: astore -118
    //   2098: iload -123
    //   2100: istore -117
    //   2102: ldc_w 820
    //   2105: aload -119
    //   2107: getfield 632	com/google/android/gms/internal/zzcod:zza	Ljava/lang/String;
    //   2110: invokevirtual 336	java/lang/String:equals	(Ljava/lang/Object;)Z
    //   2113: ifeq +10 -> 2123
    //   2116: aload -119
    //   2118: astore -120
    //   2120: goto +2413 -> 4533
    //   2123: ldc_w 809
    //   2126: aload -119
    //   2128: getfield 632	com/google/android/gms/internal/zzcod:zza	Ljava/lang/String;
    //   2131: invokevirtual 336	java/lang/String:equals	(Ljava/lang/Object;)Z
    //   2134: ifeq +2399 -> 4533
    //   2137: iconst_1
    //   2138: istore -121
    //   2140: goto +2393 -> 4533
    //   2143: iload -121
    //   2145: ifeq +36 -> 2181
    //   2148: aload -120
    //   2150: ifnull +31 -> 2181
    //   2153: aload 112
    //   2155: aload 112
    //   2157: getfield 628	com/google/android/gms/internal/zzcoc:zza	[Lcom/google/android/gms/internal/zzcod;
    //   2160: iconst_1
    //   2161: anewarray 630	com/google/android/gms/internal/zzcod
    //   2164: dup
    //   2165: iconst_0
    //   2166: aload -120
    //   2168: aastore
    //   2169: invokestatic 868	com/google/android/gms/common/util/zzb:zza	([Ljava/lang/Object;[Ljava/lang/Object;)[Ljava/lang/Object;
    //   2172: checkcast 831	[Lcom/google/android/gms/internal/zzcod;
    //   2175: putfield 628	com/google/android/gms/internal/zzcoc:zza	[Lcom/google/android/gms/internal/zzcod;
    //   2178: goto +54 -> 2232
    //   2181: aload -120
    //   2183: ifnull +25 -> 2208
    //   2186: aload -120
    //   2188: ldc_w 809
    //   2191: putfield 632	com/google/android/gms/internal/zzcod:zza	Ljava/lang/String;
    //   2194: aload -120
    //   2196: ldc2_w 869
    //   2199: invokestatic 578	java/lang/Long:valueOf	(J)Ljava/lang/Long;
    //   2202: putfield 635	com/google/android/gms/internal/zzcod:zzc	Ljava/lang/Long;
    //   2205: goto +27 -> 2232
    //   2208: aload_0
    //   2209: invokevirtual 232	com/google/android/gms/internal/zzckk:zzf	()Lcom/google/android/gms/internal/zzcjk;
    //   2212: invokevirtual 298	com/google/android/gms/internal/zzcjk:zzy	()Lcom/google/android/gms/internal/zzcjm;
    //   2215: ldc_w 872
    //   2218: aload 5
    //   2220: getfield 780	com/google/android/gms/internal/zzckk$zza:zza	Lcom/google/android/gms/internal/zzcof;
    //   2223: getfield 787	com/google/android/gms/internal/zzcof:zzo	Ljava/lang/String;
    //   2226: invokestatic 326	com/google/android/gms/internal/zzcjk:zza	(Ljava/lang/String;)Ljava/lang/Object;
    //   2229: invokevirtual 288	com/google/android/gms/internal/zzcjm:zza	(Ljava/lang/String;Ljava/lang/Object;)V
    //   2232: iload 19
    //   2234: ifeq +142 -> 2376
    //   2237: ldc_w 874
    //   2240: aload 112
    //   2242: getfield 761	com/google/android/gms/internal/zzcoc:zzb	Ljava/lang/String;
    //   2245: invokevirtual 336	java/lang/String:equals	(Ljava/lang/Object;)Z
    //   2248: ifeq +128 -> 2376
    //   2251: aload 112
    //   2253: getfield 628	com/google/android/gms/internal/zzcoc:zza	[Lcom/google/android/gms/internal/zzcod;
    //   2256: ifnull +90 -> 2346
    //   2259: aload 112
    //   2261: getfield 628	com/google/android/gms/internal/zzcoc:zza	[Lcom/google/android/gms/internal/zzcod;
    //   2264: arraylength
    //   2265: ifne +6 -> 2271
    //   2268: goto +78 -> 2346
    //   2271: aload_0
    //   2272: invokevirtual 380	com/google/android/gms/internal/zzckk:zzo	()Lcom/google/android/gms/internal/zzcnp;
    //   2275: pop
    //   2276: aload 112
    //   2278: ldc_w 876
    //   2281: invokestatic 879	com/google/android/gms/internal/zzcnp:zzb	(Lcom/google/android/gms/internal/zzcoc;Ljava/lang/String;)Ljava/lang/Object;
    //   2284: checkcast 575	java/lang/Long
    //   2287: astore -125
    //   2289: aload -125
    //   2291: ifnonnull +42 -> 2333
    //   2294: aload_0
    //   2295: invokevirtual 232	com/google/android/gms/internal/zzckk:zzf	()Lcom/google/android/gms/internal/zzcjk;
    //   2298: invokevirtual 234	com/google/android/gms/internal/zzcjk:zzaa	()Lcom/google/android/gms/internal/zzcjm;
    //   2301: astore 127
    //   2303: ldc_w 881
    //   2306: astore -128
    //   2308: aload 5
    //   2310: getfield 780	com/google/android/gms/internal/zzckk$zza:zza	Lcom/google/android/gms/internal/zzcof;
    //   2313: getfield 787	com/google/android/gms/internal/zzcof:zzo	Ljava/lang/String;
    //   2316: invokestatic 326	com/google/android/gms/internal/zzcjk:zza	(Ljava/lang/String;)Ljava/lang/Object;
    //   2319: astore -127
    //   2321: aload 127
    //   2323: aload -128
    //   2325: aload -127
    //   2327: invokevirtual 288	com/google/android/gms/internal/zzcjm:zza	(Ljava/lang/String;Ljava/lang/Object;)V
    //   2330: goto +46 -> 2376
    //   2333: lload 23
    //   2335: aload -125
    //   2337: invokevirtual 884	java/lang/Long:longValue	()J
    //   2340: ladd
    //   2341: lstore 23
    //   2343: goto +33 -> 2376
    //   2346: aload_0
    //   2347: invokevirtual 232	com/google/android/gms/internal/zzckk:zzf	()Lcom/google/android/gms/internal/zzcjk;
    //   2350: invokevirtual 234	com/google/android/gms/internal/zzcjk:zzaa	()Lcom/google/android/gms/internal/zzcjm;
    //   2353: astore 127
    //   2355: ldc_w 886
    //   2358: astore -128
    //   2360: aload 5
    //   2362: getfield 780	com/google/android/gms/internal/zzckk$zza:zza	Lcom/google/android/gms/internal/zzcof;
    //   2365: getfield 787	com/google/android/gms/internal/zzcof:zzo	Ljava/lang/String;
    //   2368: invokestatic 326	com/google/android/gms/internal/zzcjk:zza	(Ljava/lang/String;)Ljava/lang/Object;
    //   2371: astore -127
    //   2373: goto -52 -> 2321
    //   2376: aload 18
    //   2378: getfield 785	com/google/android/gms/internal/zzcof:zzb	[Lcom/google/android/gms/internal/zzcoc;
    //   2381: astore 125
    //   2383: iload 22
    //   2385: iconst_1
    //   2386: iadd
    //   2387: istore 126
    //   2389: aload 125
    //   2391: iload 22
    //   2393: aload 112
    //   2395: aastore
    //   2396: iload 126
    //   2398: istore 22
    //   2400: goto +2147 -> 4547
    //   2403: iload 21
    //   2405: istore 25
    //   2407: iload 22
    //   2409: aload 5
    //   2411: getfield 773	com/google/android/gms/internal/zzckk$zza:zzc	Ljava/util/List;
    //   2414: invokeinterface 782 1 0
    //   2419: if_icmpge +21 -> 2440
    //   2422: aload 18
    //   2424: aload 18
    //   2426: getfield 785	com/google/android/gms/internal/zzcof:zzb	[Lcom/google/android/gms/internal/zzcoc;
    //   2429: iload 22
    //   2431: invokestatic 830	java/util/Arrays:copyOf	([Ljava/lang/Object;I)[Ljava/lang/Object;
    //   2434: checkcast 887	[Lcom/google/android/gms/internal/zzcoc;
    //   2437: putfield 785	com/google/android/gms/internal/zzcof:zzb	[Lcom/google/android/gms/internal/zzcoc;
    //   2440: iload 19
    //   2442: ifeq +315 -> 2757
    //   2445: aload_0
    //   2446: invokevirtual 649	com/google/android/gms/internal/zzckk:zzq	()Lcom/google/android/gms/internal/zzcim;
    //   2449: aload 18
    //   2451: getfield 787	com/google/android/gms/internal/zzcof:zzo	Ljava/lang/String;
    //   2454: ldc_w 889
    //   2457: invokevirtual 892	com/google/android/gms/internal/zzcim:zzc	(Ljava/lang/String;Ljava/lang/String;)Lcom/google/android/gms/internal/zzcno;
    //   2460: astore 26
    //   2462: aload 26
    //   2464: ifnull +67 -> 2531
    //   2467: aload 26
    //   2469: getfield 897	com/google/android/gms/internal/zzcno:zze	Ljava/lang/Object;
    //   2472: ifnonnull +6 -> 2478
    //   2475: goto +56 -> 2531
    //   2478: new 894	com/google/android/gms/internal/zzcno
    //   2481: dup
    //   2482: aload 18
    //   2484: getfield 787	com/google/android/gms/internal/zzcof:zzo	Ljava/lang/String;
    //   2487: ldc_w 899
    //   2490: ldc_w 889
    //   2493: aload_0
    //   2494: getfield 108	com/google/android/gms/internal/zzckk:zzn	Lcom/google/android/gms/common/util/zze;
    //   2497: invokeinterface 113 1 0
    //   2502: lload 23
    //   2504: aload 26
    //   2506: getfield 897	com/google/android/gms/internal/zzcno:zze	Ljava/lang/Object;
    //   2509: checkcast 575	java/lang/Long
    //   2512: invokevirtual 884	java/lang/Long:longValue	()J
    //   2515: ladd
    //   2516: invokestatic 578	java/lang/Long:valueOf	(J)Ljava/lang/Long;
    //   2519: invokespecial 902	com/google/android/gms/internal/zzcno:<init>	(Ljava/lang/String;Ljava/lang/String;Ljava/lang/String;JLjava/lang/Object;)V
    //   2522: astore 111
    //   2524: aload 111
    //   2526: astore 31
    //   2528: goto +49 -> 2577
    //   2531: aload 18
    //   2533: getfield 787	com/google/android/gms/internal/zzcof:zzo	Ljava/lang/String;
    //   2536: astore 27
    //   2538: aload_0
    //   2539: getfield 108	com/google/android/gms/internal/zzckk:zzn	Lcom/google/android/gms/common/util/zze;
    //   2542: invokeinterface 113 1 0
    //   2547: lstore 28
    //   2549: lload 23
    //   2551: invokestatic 578	java/lang/Long:valueOf	(J)Ljava/lang/Long;
    //   2554: astore 30
    //   2556: new 894	com/google/android/gms/internal/zzcno
    //   2559: dup
    //   2560: aload 27
    //   2562: ldc_w 899
    //   2565: ldc_w 889
    //   2568: lload 28
    //   2570: aload 30
    //   2572: invokespecial 902	com/google/android/gms/internal/zzcno:<init>	(Ljava/lang/String;Ljava/lang/String;Ljava/lang/String;JLjava/lang/Object;)V
    //   2575: astore 31
    //   2577: new 904	com/google/android/gms/internal/zzcoh
    //   2580: dup
    //   2581: invokespecial 905	com/google/android/gms/internal/zzcoh:<init>	()V
    //   2584: astore 32
    //   2586: aload 32
    //   2588: ldc_w 889
    //   2591: putfield 906	com/google/android/gms/internal/zzcoh:zzb	Ljava/lang/String;
    //   2594: aload 32
    //   2596: aload_0
    //   2597: getfield 108	com/google/android/gms/internal/zzckk:zzn	Lcom/google/android/gms/common/util/zze;
    //   2600: invokeinterface 113 1 0
    //   2605: invokestatic 578	java/lang/Long:valueOf	(J)Ljava/lang/Long;
    //   2608: putfield 908	com/google/android/gms/internal/zzcoh:zza	Ljava/lang/Long;
    //   2611: aload 32
    //   2613: aload 31
    //   2615: getfield 897	com/google/android/gms/internal/zzcno:zze	Ljava/lang/Object;
    //   2618: checkcast 575	java/lang/Long
    //   2621: putfield 910	com/google/android/gms/internal/zzcoh:zzd	Ljava/lang/Long;
    //   2624: iconst_0
    //   2625: istore 33
    //   2627: iload 33
    //   2629: aload 18
    //   2631: getfield 913	com/google/android/gms/internal/zzcof:zzc	[Lcom/google/android/gms/internal/zzcoh;
    //   2634: arraylength
    //   2635: if_icmpge +1927 -> 4562
    //   2638: ldc_w 889
    //   2641: aload 18
    //   2643: getfield 913	com/google/android/gms/internal/zzcof:zzc	[Lcom/google/android/gms/internal/zzcoh;
    //   2646: iload 33
    //   2648: aaload
    //   2649: getfield 906	com/google/android/gms/internal/zzcoh:zzb	Ljava/lang/String;
    //   2652: invokevirtual 336	java/lang/String:equals	(Ljava/lang/Object;)Z
    //   2655: ifeq +1901 -> 4556
    //   2658: aload 18
    //   2660: getfield 913	com/google/android/gms/internal/zzcof:zzc	[Lcom/google/android/gms/internal/zzcoh;
    //   2663: iload 33
    //   2665: aload 32
    //   2667: aastore
    //   2668: iconst_1
    //   2669: istore 34
    //   2671: goto +3 -> 2674
    //   2674: iload 34
    //   2676: ifne +46 -> 2722
    //   2679: aload 18
    //   2681: aload 18
    //   2683: getfield 913	com/google/android/gms/internal/zzcof:zzc	[Lcom/google/android/gms/internal/zzcoh;
    //   2686: iconst_1
    //   2687: aload 18
    //   2689: getfield 913	com/google/android/gms/internal/zzcof:zzc	[Lcom/google/android/gms/internal/zzcoh;
    //   2692: arraylength
    //   2693: iadd
    //   2694: invokestatic 830	java/util/Arrays:copyOf	([Ljava/lang/Object;I)[Ljava/lang/Object;
    //   2697: checkcast 914	[Lcom/google/android/gms/internal/zzcoh;
    //   2700: putfield 913	com/google/android/gms/internal/zzcof:zzc	[Lcom/google/android/gms/internal/zzcoh;
    //   2703: aload 18
    //   2705: getfield 913	com/google/android/gms/internal/zzcof:zzc	[Lcom/google/android/gms/internal/zzcoh;
    //   2708: aload 5
    //   2710: getfield 780	com/google/android/gms/internal/zzckk$zza:zza	Lcom/google/android/gms/internal/zzcof;
    //   2713: getfield 913	com/google/android/gms/internal/zzcof:zzc	[Lcom/google/android/gms/internal/zzcoh;
    //   2716: arraylength
    //   2717: iconst_1
    //   2718: isub
    //   2719: aload 32
    //   2721: aastore
    //   2722: lload 23
    //   2724: lconst_0
    //   2725: lcmp
    //   2726: ifle +31 -> 2757
    //   2729: aload_0
    //   2730: invokevirtual 649	com/google/android/gms/internal/zzckk:zzq	()Lcom/google/android/gms/internal/zzcim;
    //   2733: aload 31
    //   2735: invokevirtual 917	com/google/android/gms/internal/zzcim:zza	(Lcom/google/android/gms/internal/zzcno;)Z
    //   2738: pop
    //   2739: aload_0
    //   2740: invokevirtual 232	com/google/android/gms/internal/zzckk:zzf	()Lcom/google/android/gms/internal/zzcjk;
    //   2743: invokevirtual 591	com/google/android/gms/internal/zzcjk:zzad	()Lcom/google/android/gms/internal/zzcjm;
    //   2746: ldc_w 919
    //   2749: aload 31
    //   2751: getfield 897	com/google/android/gms/internal/zzcno:zze	Ljava/lang/Object;
    //   2754: invokevirtual 288	com/google/android/gms/internal/zzcjm:zza	(Ljava/lang/String;Ljava/lang/Object;)V
    //   2757: aload 18
    //   2759: aload_0
    //   2760: aload 18
    //   2762: getfield 787	com/google/android/gms/internal/zzcof:zzo	Ljava/lang/String;
    //   2765: aload 18
    //   2767: getfield 913	com/google/android/gms/internal/zzcof:zzc	[Lcom/google/android/gms/internal/zzcoh;
    //   2770: aload 18
    //   2772: getfield 785	com/google/android/gms/internal/zzcof:zzb	[Lcom/google/android/gms/internal/zzcoc;
    //   2775: invokespecial 922	com/google/android/gms/internal/zzckk:zza	(Ljava/lang/String;[Lcom/google/android/gms/internal/zzcoh;[Lcom/google/android/gms/internal/zzcoc;)[Lcom/google/android/gms/internal/zzcob;
    //   2778: putfield 925	com/google/android/gms/internal/zzcof:zzaa	[Lcom/google/android/gms/internal/zzcob;
    //   2781: getstatic 927	com/google/android/gms/internal/zzcja:zzf	Lcom/google/android/gms/internal/zzcjb;
    //   2784: invokevirtual 426	com/google/android/gms/internal/zzcjb:zzb	()Ljava/lang/Object;
    //   2787: checkcast 929	java/lang/Boolean
    //   2790: invokevirtual 932	java/lang/Boolean:booleanValue	()Z
    //   2793: ifeq +1869 -> 4662
    //   2796: aload_0
    //   2797: getfield 122	com/google/android/gms/internal/zzckk:zzc	Lcom/google/android/gms/internal/zzcil;
    //   2800: astore 56
    //   2802: aload 5
    //   2804: getfield 780	com/google/android/gms/internal/zzckk$zza:zza	Lcom/google/android/gms/internal/zzcof;
    //   2807: getfield 787	com/google/android/gms/internal/zzcof:zzo	Ljava/lang/String;
    //   2810: astore 57
    //   2812: ldc_w 934
    //   2815: aload 56
    //   2817: invokevirtual 936	com/google/android/gms/internal/zzcli:zzq	()Lcom/google/android/gms/internal/zzcke;
    //   2820: aload 57
    //   2822: ldc_w 938
    //   2825: invokevirtual 941	com/google/android/gms/internal/zzcke:zza	(Ljava/lang/String;Ljava/lang/String;)Ljava/lang/String;
    //   2828: invokevirtual 336	java/lang/String:equals	(Ljava/lang/Object;)Z
    //   2831: ifeq +1831 -> 4662
    //   2834: new 943	java/util/HashMap
    //   2837: dup
    //   2838: invokespecial 944	java/util/HashMap:<init>	()V
    //   2841: astore 58
    //   2843: aload 18
    //   2845: getfield 785	com/google/android/gms/internal/zzcof:zzb	[Lcom/google/android/gms/internal/zzcoc;
    //   2848: arraylength
    //   2849: anewarray 625	com/google/android/gms/internal/zzcoc
    //   2852: astore 59
    //   2854: aload_0
    //   2855: invokevirtual 380	com/google/android/gms/internal/zzckk:zzo	()Lcom/google/android/gms/internal/zzcnp;
    //   2858: invokevirtual 947	com/google/android/gms/internal/zzcnp:zzz	()Ljava/security/SecureRandom;
    //   2861: astore 60
    //   2863: aload 18
    //   2865: getfield 785	com/google/android/gms/internal/zzcof:zzb	[Lcom/google/android/gms/internal/zzcoc;
    //   2868: astore 61
    //   2870: aload 61
    //   2872: arraylength
    //   2873: istore 62
    //   2875: iconst_0
    //   2876: istore 63
    //   2878: iconst_0
    //   2879: istore 64
    //   2881: iload 63
    //   2883: iload 62
    //   2885: if_icmpge +885 -> 3770
    //   2888: aload 61
    //   2890: iload 63
    //   2892: aaload
    //   2893: astore 65
    //   2895: aload 65
    //   2897: getfield 761	com/google/android/gms/internal/zzcoc:zzb	Ljava/lang/String;
    //   2900: ldc_w 949
    //   2903: invokevirtual 336	java/lang/String:equals	(Ljava/lang/Object;)Z
    //   2906: ifeq +189 -> 3095
    //   2909: aload_0
    //   2910: invokevirtual 380	com/google/android/gms/internal/zzckk:zzo	()Lcom/google/android/gms/internal/zzcnp;
    //   2913: pop
    //   2914: aload 65
    //   2916: ldc_w 951
    //   2919: invokestatic 879	com/google/android/gms/internal/zzcnp:zzb	(Lcom/google/android/gms/internal/zzcoc;Ljava/lang/String;)Ljava/lang/Object;
    //   2922: checkcast 332	java/lang/String
    //   2925: astore 103
    //   2927: aload 58
    //   2929: aload 103
    //   2931: invokeinterface 953 2 0
    //   2936: checkcast 955	com/google/android/gms/internal/zzciu
    //   2939: astore 104
    //   2941: aload 104
    //   2943: ifnonnull +34 -> 2977
    //   2946: aload_0
    //   2947: invokevirtual 649	com/google/android/gms/internal/zzckk:zzq	()Lcom/google/android/gms/internal/zzcim;
    //   2950: aload 5
    //   2952: getfield 780	com/google/android/gms/internal/zzckk$zza:zza	Lcom/google/android/gms/internal/zzcof;
    //   2955: getfield 787	com/google/android/gms/internal/zzcof:zzo	Ljava/lang/String;
    //   2958: aload 103
    //   2960: invokevirtual 958	com/google/android/gms/internal/zzcim:zza	(Ljava/lang/String;Ljava/lang/String;)Lcom/google/android/gms/internal/zzciu;
    //   2963: astore 104
    //   2965: aload 58
    //   2967: aload 103
    //   2969: aload 104
    //   2971: invokeinterface 496 3 0
    //   2976: pop
    //   2977: aload 104
    //   2979: getfield 960	com/google/android/gms/internal/zzciu:zzg	Ljava/lang/Long;
    //   2982: ifnonnull +1593 -> 4575
    //   2985: aload 104
    //   2987: getfield 962	com/google/android/gms/internal/zzciu:zzh	Ljava/lang/Long;
    //   2990: invokevirtual 884	java/lang/Long:longValue	()J
    //   2993: lconst_1
    //   2994: lcmp
    //   2995: ifle +29 -> 3024
    //   2998: aload_0
    //   2999: invokevirtual 380	com/google/android/gms/internal/zzckk:zzo	()Lcom/google/android/gms/internal/zzcnp;
    //   3002: pop
    //   3003: aload 65
    //   3005: aload 65
    //   3007: getfield 628	com/google/android/gms/internal/zzcoc:zza	[Lcom/google/android/gms/internal/zzcod;
    //   3010: ldc_w 964
    //   3013: aload 104
    //   3015: getfield 962	com/google/android/gms/internal/zzciu:zzh	Ljava/lang/Long;
    //   3018: invokestatic 967	com/google/android/gms/internal/zzcnp:zza	([Lcom/google/android/gms/internal/zzcod;Ljava/lang/String;Ljava/lang/Object;)[Lcom/google/android/gms/internal/zzcod;
    //   3021: putfield 628	com/google/android/gms/internal/zzcoc:zza	[Lcom/google/android/gms/internal/zzcod;
    //   3024: aload 104
    //   3026: getfield 969	com/google/android/gms/internal/zzciu:zzi	Ljava/lang/Boolean;
    //   3029: ifnull +1539 -> 4568
    //   3032: aload 104
    //   3034: getfield 969	com/google/android/gms/internal/zzciu:zzi	Ljava/lang/Boolean;
    //   3037: invokevirtual 932	java/lang/Boolean:booleanValue	()Z
    //   3040: ifeq +1528 -> 4568
    //   3043: aload_0
    //   3044: invokevirtual 380	com/google/android/gms/internal/zzckk:zzo	()Lcom/google/android/gms/internal/zzcnp;
    //   3047: pop
    //   3048: aload 65
    //   3050: getfield 628	com/google/android/gms/internal/zzcoc:zza	[Lcom/google/android/gms/internal/zzcod;
    //   3053: astore 107
    //   3055: aload 61
    //   3057: astore 66
    //   3059: aload 65
    //   3061: aload 107
    //   3063: ldc_w 971
    //   3066: lconst_1
    //   3067: invokestatic 578	java/lang/Long:valueOf	(J)Ljava/lang/Long;
    //   3070: invokestatic 967	com/google/android/gms/internal/zzcnp:zza	([Lcom/google/android/gms/internal/zzcod;Ljava/lang/String;Ljava/lang/Object;)[Lcom/google/android/gms/internal/zzcod;
    //   3073: putfield 628	com/google/android/gms/internal/zzcoc:zza	[Lcom/google/android/gms/internal/zzcod;
    //   3076: goto +3 -> 3079
    //   3079: iload 64
    //   3081: iconst_1
    //   3082: iadd
    //   3083: istore 68
    //   3085: aload 59
    //   3087: iload 64
    //   3089: aload 65
    //   3091: aastore
    //   3092: goto +1508 -> 4600
    //   3095: aload 61
    //   3097: astore 66
    //   3099: aload 65
    //   3101: ldc_w 973
    //   3104: lconst_1
    //   3105: invokestatic 578	java/lang/Long:valueOf	(J)Ljava/lang/Long;
    //   3108: invokestatic 975	com/google/android/gms/internal/zzckk:zza	(Lcom/google/android/gms/internal/zzcoc;Ljava/lang/String;Ljava/lang/Object;)Z
    //   3111: ifne +1483 -> 4594
    //   3114: aload_0
    //   3115: invokevirtual 480	com/google/android/gms/internal/zzckk:zzj	()Lcom/google/android/gms/internal/zzcke;
    //   3118: aload 5
    //   3120: getfield 780	com/google/android/gms/internal/zzckk$zza:zza	Lcom/google/android/gms/internal/zzcof;
    //   3123: getfield 787	com/google/android/gms/internal/zzcof:zzo	Ljava/lang/String;
    //   3126: aload 65
    //   3128: getfield 761	com/google/android/gms/internal/zzcoc:zzb	Ljava/lang/String;
    //   3131: invokevirtual 978	com/google/android/gms/internal/zzcke:zzd	(Ljava/lang/String;Ljava/lang/String;)I
    //   3134: istore 67
    //   3136: goto +3 -> 3139
    //   3139: iload 67
    //   3141: ifgt +42 -> 3183
    //   3144: aload_0
    //   3145: invokevirtual 232	com/google/android/gms/internal/zzckk:zzf	()Lcom/google/android/gms/internal/zzcjk;
    //   3148: invokevirtual 234	com/google/android/gms/internal/zzcjk:zzaa	()Lcom/google/android/gms/internal/zzcjm;
    //   3151: ldc_w 980
    //   3154: aload 65
    //   3156: getfield 761	com/google/android/gms/internal/zzcoc:zzb	Ljava/lang/String;
    //   3159: iload 67
    //   3161: invokestatic 285	java/lang/Integer:valueOf	(I)Ljava/lang/Integer;
    //   3164: invokevirtual 391	com/google/android/gms/internal/zzcjm:zza	(Ljava/lang/String;Ljava/lang/Object;Ljava/lang/Object;)V
    //   3167: iload 64
    //   3169: iconst_1
    //   3170: iadd
    //   3171: istore 68
    //   3173: aload 59
    //   3175: iload 64
    //   3177: aload 65
    //   3179: aastore
    //   3180: goto +1420 -> 4600
    //   3183: aload 58
    //   3185: aload 65
    //   3187: getfield 761	com/google/android/gms/internal/zzcoc:zzb	Ljava/lang/String;
    //   3190: invokeinterface 953 2 0
    //   3195: checkcast 955	com/google/android/gms/internal/zzciu
    //   3198: astore 74
    //   3200: aload 74
    //   3202: ifnonnull +104 -> 3306
    //   3205: aload_0
    //   3206: invokevirtual 649	com/google/android/gms/internal/zzckk:zzq	()Lcom/google/android/gms/internal/zzcim;
    //   3209: aload 5
    //   3211: getfield 780	com/google/android/gms/internal/zzckk$zza:zza	Lcom/google/android/gms/internal/zzcof;
    //   3214: getfield 787	com/google/android/gms/internal/zzcof:zzo	Ljava/lang/String;
    //   3217: aload 65
    //   3219: getfield 761	com/google/android/gms/internal/zzcoc:zzb	Ljava/lang/String;
    //   3222: invokevirtual 958	com/google/android/gms/internal/zzcim:zza	(Ljava/lang/String;Ljava/lang/String;)Lcom/google/android/gms/internal/zzciu;
    //   3225: astore 74
    //   3227: aload 74
    //   3229: ifnonnull +77 -> 3306
    //   3232: aload_0
    //   3233: invokevirtual 232	com/google/android/gms/internal/zzckk:zzf	()Lcom/google/android/gms/internal/zzcjk;
    //   3236: invokevirtual 234	com/google/android/gms/internal/zzcjk:zzaa	()Lcom/google/android/gms/internal/zzcjm;
    //   3239: ldc_w 982
    //   3242: aload 5
    //   3244: getfield 780	com/google/android/gms/internal/zzckk$zza:zza	Lcom/google/android/gms/internal/zzcof;
    //   3247: getfield 787	com/google/android/gms/internal/zzcof:zzo	Ljava/lang/String;
    //   3250: aload 65
    //   3252: getfield 761	com/google/android/gms/internal/zzcoc:zzb	Ljava/lang/String;
    //   3255: invokevirtual 391	com/google/android/gms/internal/zzcjm:zza	(Ljava/lang/String;Ljava/lang/Object;Ljava/lang/Object;)V
    //   3258: aload 5
    //   3260: getfield 780	com/google/android/gms/internal/zzckk$zza:zza	Lcom/google/android/gms/internal/zzcof;
    //   3263: getfield 787	com/google/android/gms/internal/zzcof:zzo	Ljava/lang/String;
    //   3266: astore 75
    //   3268: aload 65
    //   3270: getfield 761	com/google/android/gms/internal/zzcoc:zzb	Ljava/lang/String;
    //   3273: astore 76
    //   3275: aload 65
    //   3277: getfield 762	com/google/android/gms/internal/zzcoc:zzc	Ljava/lang/Long;
    //   3280: invokevirtual 884	java/lang/Long:longValue	()J
    //   3283: lstore 77
    //   3285: new 955	com/google/android/gms/internal/zzciu
    //   3288: dup
    //   3289: aload 75
    //   3291: aload 76
    //   3293: lconst_1
    //   3294: lconst_1
    //   3295: lload 77
    //   3297: lconst_0
    //   3298: aconst_null
    //   3299: aconst_null
    //   3300: aconst_null
    //   3301: invokespecial 985	com/google/android/gms/internal/zzciu:<init>	(Ljava/lang/String;Ljava/lang/String;JJJJLjava/lang/Long;Ljava/lang/Long;Ljava/lang/Boolean;)V
    //   3304: astore 74
    //   3306: aload_0
    //   3307: invokevirtual 380	com/google/android/gms/internal/zzckk:zzo	()Lcom/google/android/gms/internal/zzcnp;
    //   3310: pop
    //   3311: aload 65
    //   3313: ldc_w 987
    //   3316: invokestatic 879	com/google/android/gms/internal/zzcnp:zzb	(Lcom/google/android/gms/internal/zzcoc;Ljava/lang/String;)Ljava/lang/Object;
    //   3319: checkcast 575	java/lang/Long
    //   3322: astore 80
    //   3324: aload 80
    //   3326: ifnull +1301 -> 4627
    //   3329: iconst_1
    //   3330: istore 81
    //   3332: goto +3 -> 3335
    //   3335: iload 81
    //   3337: invokestatic 990	java/lang/Boolean:valueOf	(Z)Ljava/lang/Boolean;
    //   3340: astore 82
    //   3342: iload 67
    //   3344: iconst_1
    //   3345: if_icmpne +76 -> 3421
    //   3348: iload 64
    //   3350: iconst_1
    //   3351: iadd
    //   3352: istore 68
    //   3354: aload 59
    //   3356: iload 64
    //   3358: aload 65
    //   3360: aastore
    //   3361: aload 82
    //   3363: invokevirtual 932	java/lang/Boolean:booleanValue	()Z
    //   3366: ifeq +1234 -> 4600
    //   3369: aload 74
    //   3371: getfield 960	com/google/android/gms/internal/zzciu:zzg	Ljava/lang/Long;
    //   3374: ifnonnull +19 -> 3393
    //   3377: aload 74
    //   3379: getfield 962	com/google/android/gms/internal/zzciu:zzh	Ljava/lang/Long;
    //   3382: ifnonnull +11 -> 3393
    //   3385: aload 74
    //   3387: getfield 969	com/google/android/gms/internal/zzciu:zzi	Ljava/lang/Boolean;
    //   3390: ifnull +1210 -> 4600
    //   3393: aload 74
    //   3395: aconst_null
    //   3396: aconst_null
    //   3397: aconst_null
    //   3398: invokevirtual 993	com/google/android/gms/internal/zzciu:zza	(Ljava/lang/Long;Ljava/lang/Long;Ljava/lang/Boolean;)Lcom/google/android/gms/internal/zzciu;
    //   3401: astore 100
    //   3403: aload 58
    //   3405: aload 65
    //   3407: getfield 761	com/google/android/gms/internal/zzcoc:zzb	Ljava/lang/String;
    //   3410: aload 100
    //   3412: invokeinterface 496 3 0
    //   3417: pop
    //   3418: goto +1182 -> 4600
    //   3421: aload 60
    //   3423: iload 67
    //   3425: invokevirtual 999	java/security/SecureRandom:nextInt	(I)I
    //   3428: ifne +122 -> 3550
    //   3431: aload_0
    //   3432: invokevirtual 380	com/google/android/gms/internal/zzckk:zzo	()Lcom/google/android/gms/internal/zzcnp;
    //   3435: pop
    //   3436: aload 65
    //   3438: getfield 628	com/google/android/gms/internal/zzcoc:zza	[Lcom/google/android/gms/internal/zzcod;
    //   3441: astore 95
    //   3443: aload 60
    //   3445: astore 71
    //   3447: iload 67
    //   3449: i2l
    //   3450: lstore 96
    //   3452: iload 62
    //   3454: istore 72
    //   3456: aload 65
    //   3458: aload 95
    //   3460: ldc_w 964
    //   3463: lload 96
    //   3465: invokestatic 578	java/lang/Long:valueOf	(J)Ljava/lang/Long;
    //   3468: invokestatic 967	com/google/android/gms/internal/zzcnp:zza	([Lcom/google/android/gms/internal/zzcod;Ljava/lang/String;Ljava/lang/Object;)[Lcom/google/android/gms/internal/zzcod;
    //   3471: putfield 628	com/google/android/gms/internal/zzcoc:zza	[Lcom/google/android/gms/internal/zzcod;
    //   3474: iload 64
    //   3476: iconst_1
    //   3477: iadd
    //   3478: istore 98
    //   3480: aload 59
    //   3482: iload 64
    //   3484: aload 65
    //   3486: aastore
    //   3487: aload 82
    //   3489: invokevirtual 932	java/lang/Boolean:booleanValue	()Z
    //   3492: ifeq +17 -> 3509
    //   3495: aload 74
    //   3497: aconst_null
    //   3498: lload 96
    //   3500: invokestatic 578	java/lang/Long:valueOf	(J)Ljava/lang/Long;
    //   3503: aconst_null
    //   3504: invokevirtual 993	com/google/android/gms/internal/zzciu:zza	(Ljava/lang/Long;Ljava/lang/Long;Ljava/lang/Boolean;)Lcom/google/android/gms/internal/zzciu;
    //   3507: astore 74
    //   3509: aload 58
    //   3511: aload 65
    //   3513: getfield 761	com/google/android/gms/internal/zzcoc:zzb	Ljava/lang/String;
    //   3516: aload 74
    //   3518: aload 65
    //   3520: getfield 762	com/google/android/gms/internal/zzcoc:zzc	Ljava/lang/Long;
    //   3523: invokevirtual 884	java/lang/Long:longValue	()J
    //   3526: invokevirtual 1002	com/google/android/gms/internal/zzciu:zzb	(J)Lcom/google/android/gms/internal/zzciu;
    //   3529: invokeinterface 496 3 0
    //   3534: pop
    //   3535: aload 5
    //   3537: astore 69
    //   3539: aload 18
    //   3541: astore 70
    //   3543: iload 98
    //   3545: istore 64
    //   3547: goto +1073 -> 4620
    //   3550: aload 5
    //   3552: astore 69
    //   3554: aload 18
    //   3556: astore 70
    //   3558: aload 60
    //   3560: astore 71
    //   3562: iload 62
    //   3564: istore 72
    //   3566: aload 74
    //   3568: getfield 1004	com/google/android/gms/internal/zzciu:zzf	J
    //   3571: lstore 83
    //   3573: aload 65
    //   3575: getfield 762	com/google/android/gms/internal/zzcoc:zzc	Ljava/lang/Long;
    //   3578: invokevirtual 884	java/lang/Long:longValue	()J
    //   3581: lload 83
    //   3583: lsub
    //   3584: invokestatic 1010	java/lang/Math:abs	(J)J
    //   3587: ldc2_w 1011
    //   3590: lcmp
    //   3591: iflt +142 -> 3733
    //   3594: aload_0
    //   3595: invokevirtual 380	com/google/android/gms/internal/zzckk:zzo	()Lcom/google/android/gms/internal/zzcnp;
    //   3598: pop
    //   3599: aload 65
    //   3601: getfield 628	com/google/android/gms/internal/zzcoc:zza	[Lcom/google/android/gms/internal/zzcod;
    //   3604: astore 87
    //   3606: iload 63
    //   3608: istore 73
    //   3610: aload 65
    //   3612: aload 87
    //   3614: ldc_w 971
    //   3617: lconst_1
    //   3618: invokestatic 578	java/lang/Long:valueOf	(J)Ljava/lang/Long;
    //   3621: invokestatic 967	com/google/android/gms/internal/zzcnp:zza	([Lcom/google/android/gms/internal/zzcod;Ljava/lang/String;Ljava/lang/Object;)[Lcom/google/android/gms/internal/zzcod;
    //   3624: putfield 628	com/google/android/gms/internal/zzcoc:zza	[Lcom/google/android/gms/internal/zzcod;
    //   3627: aload_0
    //   3628: invokevirtual 380	com/google/android/gms/internal/zzckk:zzo	()Lcom/google/android/gms/internal/zzcnp;
    //   3631: pop
    //   3632: aload 65
    //   3634: getfield 628	com/google/android/gms/internal/zzcoc:zza	[Lcom/google/android/gms/internal/zzcod;
    //   3637: astore 89
    //   3639: iload 67
    //   3641: i2l
    //   3642: lstore 90
    //   3644: aload 65
    //   3646: aload 89
    //   3648: ldc_w 964
    //   3651: lload 90
    //   3653: invokestatic 578	java/lang/Long:valueOf	(J)Ljava/lang/Long;
    //   3656: invokestatic 967	com/google/android/gms/internal/zzcnp:zza	([Lcom/google/android/gms/internal/zzcod;Ljava/lang/String;Ljava/lang/Object;)[Lcom/google/android/gms/internal/zzcod;
    //   3659: putfield 628	com/google/android/gms/internal/zzcoc:zza	[Lcom/google/android/gms/internal/zzcod;
    //   3662: iload 64
    //   3664: iconst_1
    //   3665: iadd
    //   3666: istore 92
    //   3668: aload 59
    //   3670: iload 64
    //   3672: aload 65
    //   3674: aastore
    //   3675: aload 82
    //   3677: invokevirtual 932	java/lang/Boolean:booleanValue	()Z
    //   3680: ifeq +20 -> 3700
    //   3683: aload 74
    //   3685: aconst_null
    //   3686: lload 90
    //   3688: invokestatic 578	java/lang/Long:valueOf	(J)Ljava/lang/Long;
    //   3691: iconst_1
    //   3692: invokestatic 990	java/lang/Boolean:valueOf	(Z)Ljava/lang/Boolean;
    //   3695: invokevirtual 993	com/google/android/gms/internal/zzciu:zza	(Ljava/lang/Long;Ljava/lang/Long;Ljava/lang/Boolean;)Lcom/google/android/gms/internal/zzciu;
    //   3698: astore 74
    //   3700: aload 58
    //   3702: aload 65
    //   3704: getfield 761	com/google/android/gms/internal/zzcoc:zzb	Ljava/lang/String;
    //   3707: aload 74
    //   3709: aload 65
    //   3711: getfield 762	com/google/android/gms/internal/zzcoc:zzc	Ljava/lang/Long;
    //   3714: invokevirtual 884	java/lang/Long:longValue	()J
    //   3717: invokevirtual 1002	com/google/android/gms/internal/zzciu:zzb	(J)Lcom/google/android/gms/internal/zzciu;
    //   3720: invokeinterface 496 3 0
    //   3725: pop
    //   3726: iload 92
    //   3728: istore 64
    //   3730: goto +903 -> 4633
    //   3733: iload 63
    //   3735: istore 73
    //   3737: aload 82
    //   3739: invokevirtual 932	java/lang/Boolean:booleanValue	()Z
    //   3742: ifeq +891 -> 4633
    //   3745: aload 58
    //   3747: aload 65
    //   3749: getfield 761	com/google/android/gms/internal/zzcoc:zzb	Ljava/lang/String;
    //   3752: aload 74
    //   3754: aload 80
    //   3756: aconst_null
    //   3757: aconst_null
    //   3758: invokevirtual 993	com/google/android/gms/internal/zzciu:zza	(Ljava/lang/Long;Ljava/lang/Long;Ljava/lang/Boolean;)Lcom/google/android/gms/internal/zzciu;
    //   3761: invokeinterface 496 3 0
    //   3766: pop
    //   3767: goto +866 -> 4633
    //   3770: aload 5
    //   3772: astore 36
    //   3774: aload 18
    //   3776: astore 37
    //   3778: iload 64
    //   3780: aload 37
    //   3782: getfield 785	com/google/android/gms/internal/zzcof:zzb	[Lcom/google/android/gms/internal/zzcoc;
    //   3785: arraylength
    //   3786: if_icmpge +18 -> 3804
    //   3789: aload 37
    //   3791: aload 59
    //   3793: iload 64
    //   3795: invokestatic 830	java/util/Arrays:copyOf	([Ljava/lang/Object;I)[Ljava/lang/Object;
    //   3798: checkcast 887	[Lcom/google/android/gms/internal/zzcoc;
    //   3801: putfield 785	com/google/android/gms/internal/zzcof:zzb	[Lcom/google/android/gms/internal/zzcoc;
    //   3804: aload 58
    //   3806: invokeinterface 1016 1 0
    //   3811: invokeinterface 1022 1 0
    //   3816: astore 109
    //   3818: aload 109
    //   3820: invokeinterface 1027 1 0
    //   3825: ifeq +35 -> 3860
    //   3828: aload 109
    //   3830: invokeinterface 1030 1 0
    //   3835: checkcast 1032	java/util/Map$Entry
    //   3838: astore 110
    //   3840: aload_0
    //   3841: invokevirtual 649	com/google/android/gms/internal/zzckk:zzq	()Lcom/google/android/gms/internal/zzcim;
    //   3844: aload 110
    //   3846: invokeinterface 1035 1 0
    //   3851: checkcast 955	com/google/android/gms/internal/zzciu
    //   3854: invokevirtual 1038	com/google/android/gms/internal/zzcim:zza	(Lcom/google/android/gms/internal/zzciu;)V
    //   3857: goto -39 -> 3818
    //   3860: aload 37
    //   3862: ldc2_w 1039
    //   3865: invokestatic 578	java/lang/Long:valueOf	(J)Ljava/lang/Long;
    //   3868: putfield 1042	com/google/android/gms/internal/zzcof:zze	Ljava/lang/Long;
    //   3871: aload 37
    //   3873: ldc2_w 1043
    //   3876: invokestatic 578	java/lang/Long:valueOf	(J)Ljava/lang/Long;
    //   3879: putfield 1046	com/google/android/gms/internal/zzcof:zzf	Ljava/lang/Long;
    //   3882: iconst_0
    //   3883: istore 38
    //   3885: iload 38
    //   3887: aload 37
    //   3889: getfield 785	com/google/android/gms/internal/zzcof:zzb	[Lcom/google/android/gms/internal/zzcoc;
    //   3892: arraylength
    //   3893: if_icmpge +76 -> 3969
    //   3896: aload 37
    //   3898: getfield 785	com/google/android/gms/internal/zzcof:zzb	[Lcom/google/android/gms/internal/zzcoc;
    //   3901: iload 38
    //   3903: aaload
    //   3904: astore 55
    //   3906: aload 55
    //   3908: getfield 762	com/google/android/gms/internal/zzcoc:zzc	Ljava/lang/Long;
    //   3911: invokevirtual 884	java/lang/Long:longValue	()J
    //   3914: aload 37
    //   3916: getfield 1042	com/google/android/gms/internal/zzcof:zze	Ljava/lang/Long;
    //   3919: invokevirtual 884	java/lang/Long:longValue	()J
    //   3922: lcmp
    //   3923: ifge +13 -> 3936
    //   3926: aload 37
    //   3928: aload 55
    //   3930: getfield 762	com/google/android/gms/internal/zzcoc:zzc	Ljava/lang/Long;
    //   3933: putfield 1042	com/google/android/gms/internal/zzcof:zze	Ljava/lang/Long;
    //   3936: aload 55
    //   3938: getfield 762	com/google/android/gms/internal/zzcoc:zzc	Ljava/lang/Long;
    //   3941: invokevirtual 884	java/lang/Long:longValue	()J
    //   3944: aload 37
    //   3946: getfield 1046	com/google/android/gms/internal/zzcof:zzf	Ljava/lang/Long;
    //   3949: invokevirtual 884	java/lang/Long:longValue	()J
    //   3952: lcmp
    //   3953: ifle +720 -> 4673
    //   3956: aload 37
    //   3958: aload 55
    //   3960: getfield 762	com/google/android/gms/internal/zzcoc:zzc	Ljava/lang/Long;
    //   3963: putfield 1046	com/google/android/gms/internal/zzcof:zzf	Ljava/lang/Long;
    //   3966: goto +707 -> 4673
    //   3969: aload 36
    //   3971: astore 39
    //   3973: aload 39
    //   3975: getfield 780	com/google/android/gms/internal/zzckk$zza:zza	Lcom/google/android/gms/internal/zzcof;
    //   3978: getfield 787	com/google/android/gms/internal/zzcof:zzo	Ljava/lang/String;
    //   3981: astore 40
    //   3983: aload_0
    //   3984: invokevirtual 649	com/google/android/gms/internal/zzckk:zzq	()Lcom/google/android/gms/internal/zzcim;
    //   3987: aload 40
    //   3989: invokevirtual 1049	com/google/android/gms/internal/zzcim:zzb	(Ljava/lang/String;)Lcom/google/android/gms/internal/zzcif;
    //   3992: astore 41
    //   3994: aload 41
    //   3996: ifnonnull +30 -> 4026
    //   3999: aload_0
    //   4000: invokevirtual 232	com/google/android/gms/internal/zzckk:zzf	()Lcom/google/android/gms/internal/zzcjk;
    //   4003: invokevirtual 298	com/google/android/gms/internal/zzcjk:zzy	()Lcom/google/android/gms/internal/zzcjm;
    //   4006: ldc_w 1051
    //   4009: aload 39
    //   4011: getfield 780	com/google/android/gms/internal/zzckk$zza:zza	Lcom/google/android/gms/internal/zzcof;
    //   4014: getfield 787	com/google/android/gms/internal/zzcof:zzo	Ljava/lang/String;
    //   4017: invokestatic 326	com/google/android/gms/internal/zzcjk:zza	(Ljava/lang/String;)Ljava/lang/Object;
    //   4020: invokevirtual 288	com/google/android/gms/internal/zzcjm:zza	(Ljava/lang/String;Ljava/lang/Object;)V
    //   4023: goto +152 -> 4175
    //   4026: aload 37
    //   4028: getfield 785	com/google/android/gms/internal/zzcof:zzb	[Lcom/google/android/gms/internal/zzcoc;
    //   4031: arraylength
    //   4032: ifle +143 -> 4175
    //   4035: aload 41
    //   4037: invokevirtual 1053	com/google/android/gms/internal/zzcif:zzh	()J
    //   4040: lstore 48
    //   4042: lload 48
    //   4044: lconst_0
    //   4045: lcmp
    //   4046: ifeq +633 -> 4679
    //   4049: lload 48
    //   4051: invokestatic 578	java/lang/Long:valueOf	(J)Ljava/lang/Long;
    //   4054: astore 50
    //   4056: goto +3 -> 4059
    //   4059: aload 37
    //   4061: aload 50
    //   4063: putfield 1054	com/google/android/gms/internal/zzcof:zzh	Ljava/lang/Long;
    //   4066: aload 41
    //   4068: invokevirtual 1056	com/google/android/gms/internal/zzcif:zzg	()J
    //   4071: lstore 51
    //   4073: lload 51
    //   4075: lconst_0
    //   4076: lcmp
    //   4077: ifne +608 -> 4685
    //   4080: goto +3 -> 4083
    //   4083: lload 48
    //   4085: lconst_0
    //   4086: lcmp
    //   4087: istore 53
    //   4089: aconst_null
    //   4090: astore 54
    //   4092: iload 53
    //   4094: ifeq +10 -> 4104
    //   4097: lload 48
    //   4099: invokestatic 578	java/lang/Long:valueOf	(J)Ljava/lang/Long;
    //   4102: astore 54
    //   4104: aload 37
    //   4106: aload 54
    //   4108: putfield 1057	com/google/android/gms/internal/zzcof:zzg	Ljava/lang/Long;
    //   4111: aload 41
    //   4113: invokevirtual 1059	com/google/android/gms/internal/zzcif:zzr	()V
    //   4116: aload 37
    //   4118: aload 41
    //   4120: invokevirtual 1061	com/google/android/gms/internal/zzcif:zzo	()J
    //   4123: l2i
    //   4124: invokestatic 285	java/lang/Integer:valueOf	(I)Ljava/lang/Integer;
    //   4127: putfield 1064	com/google/android/gms/internal/zzcof:zzw	Ljava/lang/Integer;
    //   4130: aload 41
    //   4132: aload 37
    //   4134: getfield 1042	com/google/android/gms/internal/zzcof:zze	Ljava/lang/Long;
    //   4137: invokevirtual 884	java/lang/Long:longValue	()J
    //   4140: invokevirtual 1067	com/google/android/gms/internal/zzcif:zza	(J)V
    //   4143: aload 41
    //   4145: aload 37
    //   4147: getfield 1046	com/google/android/gms/internal/zzcof:zzf	Ljava/lang/Long;
    //   4150: invokevirtual 884	java/lang/Long:longValue	()J
    //   4153: invokevirtual 1069	com/google/android/gms/internal/zzcif:zzb	(J)V
    //   4156: aload 37
    //   4158: aload 41
    //   4160: invokevirtual 1070	com/google/android/gms/internal/zzcif:zzz	()Ljava/lang/String;
    //   4163: putfield 1072	com/google/android/gms/internal/zzcof:zzx	Ljava/lang/String;
    //   4166: aload_0
    //   4167: invokevirtual 649	com/google/android/gms/internal/zzckk:zzq	()Lcom/google/android/gms/internal/zzcim;
    //   4170: aload 41
    //   4172: invokevirtual 1074	com/google/android/gms/internal/zzcim:zza	(Lcom/google/android/gms/internal/zzcif;)V
    //   4175: aload 37
    //   4177: getfield 785	com/google/android/gms/internal/zzcof:zzb	[Lcom/google/android/gms/internal/zzcoc;
    //   4180: arraylength
    //   4181: ifle +114 -> 4295
    //   4184: aload_0
    //   4185: invokevirtual 480	com/google/android/gms/internal/zzckk:zzj	()Lcom/google/android/gms/internal/zzcke;
    //   4188: aload 39
    //   4190: getfield 780	com/google/android/gms/internal/zzckk$zza:zza	Lcom/google/android/gms/internal/zzcof;
    //   4193: getfield 787	com/google/android/gms/internal/zzcof:zzo	Ljava/lang/String;
    //   4196: invokevirtual 483	com/google/android/gms/internal/zzcke:zza	(Ljava/lang/String;)Lcom/google/android/gms/internal/zzcnz;
    //   4199: astore 45
    //   4201: aload 45
    //   4203: ifnull +31 -> 4234
    //   4206: aload 45
    //   4208: getfield 1077	com/google/android/gms/internal/zzcnz:zza	Ljava/lang/Long;
    //   4211: ifnonnull +6 -> 4217
    //   4214: goto +20 -> 4234
    //   4217: aload 45
    //   4219: getfield 1077	com/google/android/gms/internal/zzcnz:zza	Ljava/lang/Long;
    //   4222: astore 47
    //   4224: aload 37
    //   4226: aload 47
    //   4228: putfield 1079	com/google/android/gms/internal/zzcof:zzae	Ljava/lang/Long;
    //   4231: goto +52 -> 4283
    //   4234: aload 39
    //   4236: getfield 780	com/google/android/gms/internal/zzckk$zza:zza	Lcom/google/android/gms/internal/zzcof;
    //   4239: getfield 1081	com/google/android/gms/internal/zzcof:zzy	Ljava/lang/String;
    //   4242: invokestatic 357	android/text/TextUtils:isEmpty	(Ljava/lang/CharSequence;)Z
    //   4245: ifeq +14 -> 4259
    //   4248: ldc2_w 98
    //   4251: invokestatic 578	java/lang/Long:valueOf	(J)Ljava/lang/Long;
    //   4254: astore 47
    //   4256: goto -32 -> 4224
    //   4259: aload_0
    //   4260: invokevirtual 232	com/google/android/gms/internal/zzckk:zzf	()Lcom/google/android/gms/internal/zzcjk;
    //   4263: invokevirtual 234	com/google/android/gms/internal/zzcjk:zzaa	()Lcom/google/android/gms/internal/zzcjm;
    //   4266: ldc_w 1083
    //   4269: aload 39
    //   4271: getfield 780	com/google/android/gms/internal/zzckk$zza:zza	Lcom/google/android/gms/internal/zzcof;
    //   4274: getfield 787	com/google/android/gms/internal/zzcof:zzo	Ljava/lang/String;
    //   4277: invokestatic 326	com/google/android/gms/internal/zzcjk:zza	(Ljava/lang/String;)Ljava/lang/Object;
    //   4280: invokevirtual 288	com/google/android/gms/internal/zzcjm:zza	(Ljava/lang/String;Ljava/lang/Object;)V
    //   4283: aload_0
    //   4284: invokevirtual 649	com/google/android/gms/internal/zzckk:zzq	()Lcom/google/android/gms/internal/zzcim;
    //   4287: aload 37
    //   4289: iload 25
    //   4291: invokevirtual 1086	com/google/android/gms/internal/zzcim:zza	(Lcom/google/android/gms/internal/zzcof;Z)Z
    //   4294: pop
    //   4295: aload_0
    //   4296: invokevirtual 649	com/google/android/gms/internal/zzckk:zzq	()Lcom/google/android/gms/internal/zzcim;
    //   4299: aload 39
    //   4301: getfield 1088	com/google/android/gms/internal/zzckk$zza:zzb	Ljava/util/List;
    //   4304: invokevirtual 1091	com/google/android/gms/internal/zzcim:zza	(Ljava/util/List;)V
    //   4307: aload_0
    //   4308: invokevirtual 649	com/google/android/gms/internal/zzckk:zzq	()Lcom/google/android/gms/internal/zzcim;
    //   4311: astore 42
    //   4313: aload 42
    //   4315: invokevirtual 659	com/google/android/gms/internal/zzcim:zzaa	()Landroid/database/sqlite/SQLiteDatabase;
    //   4318: astore 43
    //   4320: aload 43
    //   4322: ldc_w 1093
    //   4325: iconst_2
    //   4326: anewarray 332	java/lang/String
    //   4329: dup
    //   4330: iconst_0
    //   4331: aload 40
    //   4333: aastore
    //   4334: dup
    //   4335: iconst_1
    //   4336: aload 40
    //   4338: aastore
    //   4339: invokevirtual 1097	android/database/sqlite/SQLiteDatabase:execSQL	(Ljava/lang/String;[Ljava/lang/Object;)V
    //   4342: goto +26 -> 4368
    //   4345: astore 44
    //   4347: aload 42
    //   4349: invokevirtual 225	com/google/android/gms/internal/zzcli:zzt	()Lcom/google/android/gms/internal/zzcjk;
    //   4352: invokevirtual 298	com/google/android/gms/internal/zzcjk:zzy	()Lcom/google/android/gms/internal/zzcjm;
    //   4355: ldc_w 1099
    //   4358: aload 40
    //   4360: invokestatic 326	com/google/android/gms/internal/zzcjk:zza	(Ljava/lang/String;)Ljava/lang/Object;
    //   4363: aload 44
    //   4365: invokevirtual 391	com/google/android/gms/internal/zzcjm:zza	(Ljava/lang/String;Ljava/lang/Object;Ljava/lang/Object;)V
    //   4368: aload_0
    //   4369: invokevirtual 649	com/google/android/gms/internal/zzckk:zzq	()Lcom/google/android/gms/internal/zzcim;
    //   4372: invokevirtual 1101	com/google/android/gms/internal/zzcim:zzy	()V
    //   4375: aload_0
    //   4376: invokevirtual 649	com/google/android/gms/internal/zzckk:zzq	()Lcom/google/android/gms/internal/zzcim;
    //   4379: invokevirtual 1103	com/google/android/gms/internal/zzcim:zzz	()V
    //   4382: iconst_1
    //   4383: ireturn
    //   4384: aload_0
    //   4385: invokevirtual 649	com/google/android/gms/internal/zzckk:zzq	()Lcom/google/android/gms/internal/zzcim;
    //   4388: invokevirtual 1101	com/google/android/gms/internal/zzcim:zzy	()V
    //   4391: aload_0
    //   4392: invokevirtual 649	com/google/android/gms/internal/zzckk:zzq	()Lcom/google/android/gms/internal/zzcim;
    //   4395: invokevirtual 1103	com/google/android/gms/internal/zzcim:zzz	()V
    //   4398: iconst_0
    //   4399: ireturn
    //   4400: astore 15
    //   4402: aload 15
    //   4404: astore 16
    //   4406: aload 13
    //   4408: ifnull +10 -> 4418
    //   4411: aload 13
    //   4413: invokeinterface 692 1 0
    //   4418: aload 16
    //   4420: athrow
    //   4421: astore 6
    //   4423: aload_0
    //   4424: invokevirtual 649	com/google/android/gms/internal/zzckk:zzq	()Lcom/google/android/gms/internal/zzcim;
    //   4427: invokevirtual 1103	com/google/android/gms/internal/zzcim:zzz	()V
    //   4430: aload 6
    //   4432: athrow
    //   4433: iload -104
    //   4435: ifeq +11 -> 4446
    //   4438: ldc_w 1105
    //   4441: astore -102
    //   4443: goto -4087 -> 356
    //   4446: ldc_w 338
    //   4449: astore -102
    //   4451: goto -4095 -> 356
    //   4454: iconst_0
    //   4455: istore 17
    //   4457: goto -3252 -> 1205
    //   4460: iconst_1
    //   4461: istore 17
    //   4463: goto -3258 -> 1205
    //   4466: iconst_0
    //   4467: istore -108
    //   4469: goto -3078 -> 1391
    //   4472: iconst_1
    //   4473: istore -108
    //   4475: goto -3084 -> 1391
    //   4478: iload 20
    //   4480: istore 120
    //   4482: goto +65 -> 4547
    //   4485: iload 20
    //   4487: istore 120
    //   4489: goto -2257 -> 2232
    //   4492: iinc 117 1
    //   4495: iload -113
    //   4497: istore 116
    //   4499: aload -111
    //   4501: astore 115
    //   4503: iload -110
    //   4505: istore 21
    //   4507: iload -109
    //   4509: istore 20
    //   4511: goto -2988 -> 1523
    //   4514: iinc 124 1
    //   4517: goto -2651 -> 1866
    //   4520: iload 121
    //   4522: istore 21
    //   4524: goto -2555 -> 1969
    //   4527: iconst_1
    //   4528: istore 21
    //   4530: goto -2561 -> 1969
    //   4533: iinc -122 1
    //   4536: aload -118
    //   4538: astore -124
    //   4540: iload -117
    //   4542: istore -123
    //   4544: goto -2464 -> 2080
    //   4547: iload 120
    //   4549: iconst_1
    //   4550: iadd
    //   4551: istore 20
    //   4553: goto -3292 -> 1261
    //   4556: iinc 33 1
    //   4559: goto -1932 -> 2627
    //   4562: iconst_0
    //   4563: istore 34
    //   4565: goto -1891 -> 2674
    //   4568: aload 61
    //   4570: astore 66
    //   4572: goto -1493 -> 3079
    //   4575: aload 61
    //   4577: astore 66
    //   4579: aload 5
    //   4581: astore 69
    //   4583: aload 18
    //   4585: astore 70
    //   4587: aload 60
    //   4589: astore 71
    //   4591: goto +25 -> 4616
    //   4594: iconst_1
    //   4595: istore 67
    //   4597: goto -1458 -> 3139
    //   4600: aload 5
    //   4602: astore 69
    //   4604: aload 18
    //   4606: astore 70
    //   4608: aload 60
    //   4610: astore 71
    //   4612: iload 68
    //   4614: istore 64
    //   4616: iload 62
    //   4618: istore 72
    //   4620: iload 63
    //   4622: istore 73
    //   4624: goto +9 -> 4633
    //   4627: iconst_0
    //   4628: istore 81
    //   4630: goto -1295 -> 3335
    //   4633: iload 73
    //   4635: iconst_1
    //   4636: iadd
    //   4637: istore 63
    //   4639: aload 66
    //   4641: astore 61
    //   4643: aload 71
    //   4645: astore 60
    //   4647: iload 72
    //   4649: istore 62
    //   4651: aload 69
    //   4653: astore 5
    //   4655: aload 70
    //   4657: astore 18
    //   4659: goto -1778 -> 2881
    //   4662: aload 5
    //   4664: astore 36
    //   4666: aload 18
    //   4668: astore 37
    //   4670: goto -810 -> 3860
    //   4673: iinc 38 1
    //   4676: goto -791 -> 3885
    //   4679: aconst_null
    //   4680: astore 50
    //   4682: goto -623 -> 4059
    //   4685: lload 51
    //   4687: lstore 48
    //   4689: goto -606 -> 4083
    // Local variable table:
    //   start	length	slot	name	signature
    //   4533	1	-122	???	int
    //   0	4692	0	this	zzckk
    //   0	4692	1	paramString	String
    //   0	4692	2	paramLong	long
    //   8	1111	4	localCursor1	android.database.Cursor
    //   19	4644	5	localObject1	Object
    //   4421	10	6	localObject2	Object
    //   25	1128	7	localZzcim1	zzcim
    //   31	668	8	l1	long
    //   1140	3	11	localSQLiteException1	SQLiteException
    //   129	1040	12	localObject3	Object
    //   114	4298	13	localObject4	Object
    //   125	1039	14	localObject5	Object
    //   1068	1	15	localObject6	Object
    //   4400	3	15	localObject7	Object
    //   110	4309	16	localObject8	Object
    //   1205	3257	17	i	int
    //   1215	3452	18	localObject9	Object
    //   1247	1194	19	bool1	boolean
    //   1250	3302	20	j	int
    //   1253	3276	21	bool2	boolean
    //   1256	1174	22	k	int
    //   1259	1464	23	l2	long
    //   2405	1885	25	bool3	boolean
    //   2460	45	26	localZzcno1	zzcno
    //   2536	25	27	str1	String
    //   2547	22	28	l3	long
    //   2554	17	30	localLong1	Long
    //   2526	224	31	localZzcno2	zzcno
    //   2584	136	32	localZzcoh	zzcoh
    //   2625	1932	33	m	int
    //   2669	1895	34	n	int
    //   3772	893	36	localObject10	Object
    //   3776	893	37	localObject11	Object
    //   3883	791	38	i1	int
    //   3971	329	39	localObject12	Object
    //   3981	378	40	str2	String
    //   3992	179	41	localZzcif	zzcif
    //   4311	37	42	localZzcim2	zzcim
    //   4318	3	43	localSQLiteDatabase1	SQLiteDatabase
    //   4345	19	44	localSQLiteException2	SQLiteException
    //   4199	19	45	localZzcnz	zzcnz
    //   4222	33	47	localLong2	Long
    //   4040	648	48	l4	long
    //   4054	627	50	localLong3	Long
    //   4071	615	51	l5	long
    //   4087	6	53	bool4	boolean
    //   4090	17	54	localLong4	Long
    //   3904	55	55	localZzcoc1	zzcoc
    //   2800	16	56	localZzcil	zzcil
    //   2810	11	57	str3	String
    //   2841	964	58	localHashMap	java.util.HashMap
    //   2852	940	59	arrayOfZzcoc1	zzcoc[]
    //   2861	1785	60	localObject13	Object
    //   2868	1774	61	localObject14	Object
    //   2873	1777	62	i2	int
    //   2876	1762	63	i3	int
    //   2879	1736	64	i4	int
    //   2893	855	65	localZzcoc2	zzcoc
    //   3057	1583	66	localObject15	Object
    //   3134	1462	67	i5	int
    //   3083	1530	68	i6	int
    //   3537	1115	69	localObject16	Object
    //   3541	1115	70	localObject17	Object
    //   3445	1199	71	localObject18	Object
    //   3454	1194	72	i7	int
    //   3608	1029	73	i8	int
    //   3198	555	74	localZzciu1	zzciu
    //   3266	24	75	str4	String
    //   3273	19	76	str5	String
    //   3283	13	77	l6	long
    //   3322	433	80	localLong5	Long
    //   3330	1299	81	bool5	boolean
    //   3340	398	82	localBoolean	Boolean
    //   3571	11	83	l7	long
    //   3604	9	87	arrayOfZzcod1	zzcod[]
    //   3637	10	89	arrayOfZzcod2	zzcod[]
    //   3642	45	90	l8	long
    //   3666	61	92	i9	int
    //   3441	18	95	arrayOfZzcod3	zzcod[]
    //   3450	49	96	l9	long
    //   3478	66	98	i10	int
    //   3401	10	100	localZzciu2	zzciu
    //   2925	43	103	str6	String
    //   2939	94	104	localZzciu3	zzciu
    //   3053	9	107	arrayOfZzcod4	zzcod[]
    //   3816	13	109	localIterator	Iterator
    //   3838	7	110	localEntry	java.util.Map.Entry
    //   2522	3	111	localZzcno3	zzcno
    //   1291	1103	112	localZzcoc3	zzcoc
    //   1459	522	113	bool6	boolean
    //   1507	2995	115	localObject19	Object
    //   1512	2986	116	i11	int
    //   1515	2978	117	i12	int
    //   1518	106	118	i13	int
    //   1521	202	119	i14	int
    //   1617	2934	120	i15	int
    //   1621	2900	121	bool7	boolean
    //   1771	41	122	arrayOfZzcod5	zzcod[]
    //   1780	27	123	localZzcod1	zzcod
    //   1864	2651	124	i16	int
    //   2381	9	125	arrayOfZzcoc2	zzcoc[]
    //   2387	10	126	i17	int
    //   2301	53	127	localZzcjm	zzcjm
    //   2306	53	128	str7	String
    //   2319	53	129	localObject20	Object
    //   2287	49	131	localLong6	Long
    //   2064	2475	132	localObject21	Object
    //   2069	2474	133	i18	int
    //   2072	18	134	i19	int
    //   2075	69	135	i20	int
    //   2078	117	136	localObject22	Object
    //   2092	35	137	localObject23	Object
    //   2096	2441	138	localObject24	Object
    //   2100	2441	139	i21	int
    //   1908	54	140	arrayOfZzcod6	zzcod[]
    //   1677	41	141	arrayOfZzcod7	zzcod[]
    //   1686	27	142	localZzcod2	zzcod
    //   1532	2964	143	i22	int
    //   1539	62	144	localObject25	Object
    //   1543	2957	145	localObject26	Object
    //   1547	2957	146	bool8	boolean
    //   1565	2943	147	i23	int
    //   1391	3083	148	i24	int
    //   1128	3	149	localObject27	Object
    //   54	725	150	localSQLiteDatabase2	SQLiteDatabase
    //   60	3	151	bool9	boolean
    //   313	4121	152	bool10	boolean
    //   324	86	153	arrayOfString1	String[]
    //   362	4088	154	localObject28	Object
    //   374	31	155	localStringBuilder1	StringBuilder
    //   119	9	159	localSQLiteException3	SQLiteException
    //   298	1	159	localSQLiteException4	SQLiteException
    //   568	1	159	localSQLiteException5	SQLiteException
    //   1008	1	159	localSQLiteException6	SQLiteException
    //   1063	1	159	localSQLiteException7	SQLiteException
    //   1077	1	159	localSQLiteException8	SQLiteException
    //   1103	1	159	localSQLiteException9	SQLiteException
    //   1116	1	159	localSQLiteException10	SQLiteException
    //   442	14	160	str8	String
    //   285	825	161	localCursor2	android.database.Cursor
    //   293	440	162	localObject29	Object
    //   289	817	163	localObject30	Object
    //   1090	3	164	localObject31	Object
    //   505	575	165	localCursor3	android.database.Cursor
    //   514	3	166	bool11	boolean
    //   589	6	167	arrayOfByte1	byte[]
    //   600	14	168	localZzetv1	zzetv
    //   609	53	169	localZzcof	zzcof
    //   1021	23	170	localIOException1	IOException
    //   626	3	172	bool12	boolean
    //   707	68	173	str9	String
    //   711	77	174	arrayOfString2	String[]
    //   765	19	175	arrayOfString3	String[]
    //   768	223	176	i25	int
    //   776	10	177	str10	String
    //   798	217	178	localCursor4	android.database.Cursor
    //   995	3	179	localObject32	Object
    //   852	73	180	l10	long
    //   863	6	182	arrayOfByte2	byte[]
    //   874	14	183	localZzetv2	zzetv
    //   883	44	184	localZzcoc4	zzcoc
    //   944	19	185	localIOException2	IOException
    //   974	3	186	bool13	boolean
    //   681	29	188	arrayOfString4	String[]
    //   555	3	189	localObject33	Object
    //   106	3	190	localObject34	Object
    //   73	76	191	bool14	boolean
    //   84	137	192	arrayOfString5	String[]
    //   156	43	193	str11	String
    //   185	31	194	localStringBuilder2	StringBuilder
    //   234	3	198	bool15	boolean
    //   274	18	199	str12	String
    // Exception table:
    //   from	to	target	type
    //   80	103	106	finally
    //   227	236	106	finally
    //   256	266	106	finally
    //   266	283	106	finally
    //   416	426	106	finally
    //   434	451	106	finally
    //   80	103	119	android/database/sqlite/SQLiteException
    //   266	283	298	android/database/sqlite/SQLiteException
    //   521	540	555	finally
    //   633	652	555	finally
    //   677	704	555	finally
    //   521	540	568	android/database/sqlite/SQLiteException
    //   633	652	568	android/database/sqlite/SQLiteException
    //   677	704	568	android/database/sqlite/SQLiteException
    //   885	893	944	java/io/IOException
    //   800	829	995	finally
    //   844	885	995	finally
    //   885	893	995	finally
    //   893	936	995	finally
    //   946	967	995	finally
    //   967	976	995	finally
    //   800	829	1008	android/database/sqlite/SQLiteException
    //   844	885	1008	android/database/sqlite/SQLiteException
    //   885	893	1008	android/database/sqlite/SQLiteException
    //   893	936	1008	android/database/sqlite/SQLiteException
    //   946	967	1008	android/database/sqlite/SQLiteException
    //   967	976	1008	android/database/sqlite/SQLiteException
    //   611	619	1021	java/io/IOException
    //   778	800	1063	android/database/sqlite/SQLiteException
    //   1027	1048	1063	android/database/sqlite/SQLiteException
    //   507	516	1068	finally
    //   581	611	1068	finally
    //   611	619	1068	finally
    //   619	628	1068	finally
    //   652	668	1068	finally
    //   721	737	1068	finally
    //   737	767	1068	finally
    //   507	516	1077	android/database/sqlite/SQLiteException
    //   581	611	1077	android/database/sqlite/SQLiteException
    //   611	619	1077	android/database/sqlite/SQLiteException
    //   619	628	1077	android/database/sqlite/SQLiteException
    //   652	668	1077	android/database/sqlite/SQLiteException
    //   721	737	1077	android/database/sqlite/SQLiteException
    //   737	767	1077	android/database/sqlite/SQLiteException
    //   462	507	1090	finally
    //   462	507	1103	android/database/sqlite/SQLiteException
    //   227	236	1116	android/database/sqlite/SQLiteException
    //   256	266	1116	android/database/sqlite/SQLiteException
    //   416	426	1116	android/database/sqlite/SQLiteException
    //   434	451	1116	android/database/sqlite/SQLiteException
    //   49	62	1128	finally
    //   134	148	1128	finally
    //   166	227	1128	finally
    //   320	340	1128	finally
    //   343	353	1128	finally
    //   356	416	1128	finally
    //   49	62	1140	android/database/sqlite/SQLiteException
    //   134	148	1140	android/database/sqlite/SQLiteException
    //   166	227	1140	android/database/sqlite/SQLiteException
    //   320	340	1140	android/database/sqlite/SQLiteException
    //   343	353	1140	android/database/sqlite/SQLiteException
    //   356	416	1140	android/database/sqlite/SQLiteException
    //   4320	4342	4345	android/database/sqlite/SQLiteException
    //   778	800	4400	finally
    //   1027	1048	4400	finally
    //   1152	1173	4400	finally
    //   10	49	4421	finally
    //   246	253	4421	finally
    //   545	552	4421	finally
    //   834	841	4421	finally
    //   1053	1060	4421	finally
    //   1181	1202	4421	finally
    //   1210	1249	4421	finally
    //   1261	1388	4421	finally
    //   1396	1436	4421	finally
    //   1439	1461	4421	finally
    //   1466	1482	4421	finally
    //   1485	1502	4421	finally
    //   1502	1514	4421	finally
    //   1534	1541	4421	finally
    //   1549	1563	4421	finally
    //   1567	1576	4421	finally
    //   1586	1609	4421	finally
    //   1633	1722	4421	finally
    //   1727	1816	4421	finally
    //   1816	1863	4421	finally
    //   1866	1910	4421	finally
    //   1915	1929	4421	finally
    //   1929	1959	4421	finally
    //   1959	1966	4421	finally
    //   1969	1980	4421	finally
    //   1985	2071	4421	finally
    //   2087	2094	4421	finally
    //   2102	2116	4421	finally
    //   2123	2137	4421	finally
    //   2153	2178	4421	finally
    //   2186	2205	4421	finally
    //   2208	2232	4421	finally
    //   2237	2268	4421	finally
    //   2271	2289	4421	finally
    //   2294	2303	4421	finally
    //   2308	2321	4421	finally
    //   2321	2330	4421	finally
    //   2333	2343	4421	finally
    //   2346	2355	4421	finally
    //   2360	2373	4421	finally
    //   2376	2383	4421	finally
    //   2389	2396	4421	finally
    //   2407	2440	4421	finally
    //   2445	2462	4421	finally
    //   2467	2475	4421	finally
    //   2478	2524	4421	finally
    //   2531	2577	4421	finally
    //   2577	2624	4421	finally
    //   2627	2668	4421	finally
    //   2679	2722	4421	finally
    //   2729	2757	4421	finally
    //   2757	2875	4421	finally
    //   2888	2941	4421	finally
    //   2946	2977	4421	finally
    //   2977	3024	4421	finally
    //   3024	3055	4421	finally
    //   3059	3076	4421	finally
    //   3085	3092	4421	finally
    //   3099	3136	4421	finally
    //   3144	3167	4421	finally
    //   3173	3180	4421	finally
    //   3183	3200	4421	finally
    //   3205	3227	4421	finally
    //   3232	3306	4421	finally
    //   3306	3324	4421	finally
    //   3335	3342	4421	finally
    //   3354	3393	4421	finally
    //   3393	3418	4421	finally
    //   3421	3443	4421	finally
    //   3456	3474	4421	finally
    //   3480	3509	4421	finally
    //   3509	3535	4421	finally
    //   3566	3606	4421	finally
    //   3610	3639	4421	finally
    //   3644	3662	4421	finally
    //   3668	3700	4421	finally
    //   3700	3726	4421	finally
    //   3737	3767	4421	finally
    //   3778	3804	4421	finally
    //   3804	3818	4421	finally
    //   3818	3857	4421	finally
    //   3860	3882	4421	finally
    //   3885	3936	4421	finally
    //   3936	3966	4421	finally
    //   3973	3994	4421	finally
    //   3999	4023	4421	finally
    //   4026	4042	4421	finally
    //   4049	4056	4421	finally
    //   4059	4073	4421	finally
    //   4097	4104	4421	finally
    //   4104	4175	4421	finally
    //   4175	4201	4421	finally
    //   4206	4214	4421	finally
    //   4217	4224	4421	finally
    //   4224	4231	4421	finally
    //   4234	4256	4421	finally
    //   4259	4283	4421	finally
    //   4283	4295	4421	finally
    //   4295	4320	4421	finally
    //   4320	4342	4421	finally
    //   4347	4368	4421	finally
    //   4368	4375	4421	finally
    //   4384	4391	4421	finally
    //   4411	4418	4421	finally
    //   4418	4421	4421	finally
  }
  
  private final boolean zza(String paramString, zzciy paramZzciy)
  {
    String str1 = paramZzciy.zzb.zzd("currency");
    long l1;
    if ("ecommerce_purchase".equals(paramZzciy.zza))
    {
      double d = 1000000.0D * paramZzciy.zzb.zzc("value").doubleValue();
      if (d == 0.0D) {
        d = 1000000.0D * paramZzciy.zzb.zzb("value").longValue();
      }
      if ((d <= 9.223372036854776E18D) && (d >= -9.223372036854776E18D))
      {
        l1 = Math.round(d);
      }
      else
      {
        zzf().zzaa().zza("Data lost. Currency value is too big. appId", zzcjk.zza(paramString), Double.valueOf(d));
        return false;
      }
    }
    else
    {
      l1 = paramZzciy.zzb.zzb("value").longValue();
    }
    if (!TextUtils.isEmpty(str1))
    {
      String str2 = str1.toUpperCase(Locale.US);
      if (str2.matches("[A-Z]{3}"))
      {
        String str3 = String.valueOf("_ltv_");
        String str4 = String.valueOf(str2);
        if (str4.length() != 0) {}
        String str6;
        for (String str5 = str3.concat(str4);; str5 = new String(str3))
        {
          str6 = str5;
          break;
        }
        zzcno localZzcno1 = zzq().zzc(paramString, str6);
        zzcno localZzcno2;
        if ((localZzcno1 != null) && ((localZzcno1.zze instanceof Long)))
        {
          long l3 = ((Long)localZzcno1.zze).longValue();
          zzcno localZzcno3 = new zzcno(paramString, paramZzciy.zzc, str6, this.zzn.zza(), Long.valueOf(l3 + l1));
          localZzcno2 = localZzcno3;
        }
        else
        {
          zzcim localZzcim = zzq();
          int i = this.zzc.zzb(paramString, zzcja.zzak) - 1;
          zzbq.zza(paramString);
          localZzcim.zzc();
          localZzcim.zzaq();
          try
          {
            SQLiteDatabase localSQLiteDatabase = localZzcim.zzaa();
            String[] arrayOfString = new String[3];
            arrayOfString[0] = paramString;
            arrayOfString[1] = paramString;
            arrayOfString[2] = String.valueOf(i);
            localSQLiteDatabase.execSQL("delete from user_attributes where app_id=? and name in (select name from user_attributes where app_id=? and name like '_ltv_%' order by set_timestamp desc limit ?,10);", arrayOfString);
          }
          catch (SQLiteException localSQLiteException)
          {
            localZzcim.zzt().zzy().zza("Error pruning currencies. appId", zzcjk.zza(paramString), localSQLiteException);
          }
          String str7 = paramZzciy.zzc;
          long l2 = this.zzn.zza();
          Long localLong = Long.valueOf(l1);
          localZzcno2 = new zzcno(paramString, str7, str6, l2, localLong);
        }
        if (!zzq().zza(localZzcno2))
        {
          zzf().zzy().zza("Too many unique user properties are set. Ignoring user property. appId", zzcjk.zza(paramString), zzp().zzc(localZzcno2.zzc), localZzcno2.zze);
          zzo().zza(paramString, 9, null, null, 0);
        }
      }
    }
    return true;
  }
  
  private final zzcob[] zza(String paramString, zzcoh[] paramArrayOfZzcoh, zzcoc[] paramArrayOfZzcoc)
  {
    zzbq.zza(paramString);
    return zzz().zza(paramString, paramArrayOfZzcoc, paramArrayOfZzcoh);
  }
  
  static void zzad()
  {
    throw new IllegalStateException("Unexpected call on client side");
  }
  
  private final zzcjt zzah()
  {
    if (this.zzw == null) {
      throw new IllegalStateException("Network broadcast receiver not created");
    }
    return this.zzw;
  }
  
  private final zzcnk zzai()
  {
    zzb(this.zzx);
    return this.zzx;
  }
  
  private final boolean zzaj()
  {
    zzh().zzc();
    File localFile = new File(this.zzb.getFilesDir(), "google_app_measurement.db");
    zzcjm localZzcjm;
    String str;
    try
    {
      this.zzae = new RandomAccessFile(localFile, "rw").getChannel();
      this.zzad = this.zzae.tryLock();
      if (this.zzad != null)
      {
        zzf().zzae().zza("Storage concurrent access okay");
        return true;
      }
      zzf().zzy().zza("Storage concurrent data access panic");
    }
    catch (IOException localIOException)
    {
      localZzcjm = zzf().zzy();
      str = "Failed to access storage lock file";
    }
    catch (FileNotFoundException localFileNotFoundException)
    {
      localZzcjm = zzf().zzy();
      str = "Failed to acquire storage lock";
    }
    localZzcjm.zza(str, localFileNotFoundException);
    return false;
  }
  
  private final long zzak()
  {
    long l1 = this.zzn.zza();
    zzcjv localZzcjv = zze();
    localZzcjv.zzaq();
    localZzcjv.zzc();
    long l2 = localZzcjv.zzg.zza();
    if (l2 == 0L)
    {
      l2 = 1 + localZzcjv.zzp().zzz().nextInt(86400000);
      localZzcjv.zzg.zza(l2);
    }
    return (l1 + l2) / 1000L / 60L / 60L / 24L;
  }
  
  private final boolean zzal()
  {
    zzh().zzc();
    zza();
    return (zzq().zzag()) || (!TextUtils.isEmpty(zzq().zzab()));
  }
  
  private final void zzam()
  {
    zzh().zzc();
    zza();
    if (!zzan()) {
      return;
    }
    if (this.zzak > 0L)
    {
      long l17 = 3600000L - Math.abs(this.zzn.zzb() - this.zzak);
      if (l17 > 0L)
      {
        zzf().zzae().zza("Upload has been suspended. Will update scheduling later in approximately ms", Long.valueOf(l17));
        zzah().zzb();
        zzai().zzy();
        return;
      }
      this.zzak = 0L;
    }
    if ((zzb()) && (zzal()))
    {
      long l1 = this.zzn.zza();
      long l2 = Math.max(0L, ((Long)zzcja.zzag.zzb()).longValue());
      int i;
      if ((!zzq().zzah()) && (!zzq().zzac())) {
        i = 0;
      } else {
        i = 1;
      }
      zzcjb localZzcjb;
      if (i != 0)
      {
        String str = this.zzc.zzaa();
        if ((!TextUtils.isEmpty(str)) && (!".none.".equals(str))) {
          localZzcjb = zzcja.zzab;
        } else {
          localZzcjb = zzcja.zzaa;
        }
      }
      else
      {
        localZzcjb = zzcja.zzz;
      }
      long l3 = Math.max(0L, ((Long)localZzcjb.zzb()).longValue());
      long l4 = zze().zzc.zza();
      long l5 = zze().zzd.zza();
      long l6 = zzq().zzae();
      zzcim localZzcim = zzq();
      int j = i;
      long l7 = Math.max(l6, localZzcim.zzaf());
      if (l7 == 0L) {}
      long l12;
      for (;;)
      {
        l12 = 0L;
        break;
        long l8 = l1 - Math.abs(l7 - l1);
        long l9 = l1 - Math.abs(l4 - l1);
        long l10 = l1 - Math.abs(l5 - l1);
        long l11 = Math.max(l9, l10);
        l12 = l2 + l8;
        if ((j != 0) && (l11 > 0L)) {
          l12 = l3 + Math.min(l8, l11);
        }
        if (!zzo().zza(l11, l3)) {
          l12 = l11 + l3;
        }
        if ((l10 == 0L) || (l10 < l8)) {
          break;
        }
        long l16 = l12;
        for (int k = 0; k < Math.min(20, Math.max(0, ((Integer)zzcja.zzai.zzb()).intValue())); k++)
        {
          l16 += (1 << k) * Math.max(0L, ((Long)zzcja.zzah.zzb()).longValue());
          if (l16 > l10)
          {
            l12 = l16;
            break label500;
          }
        }
      }
      label500:
      if (l12 == 0L)
      {
        zzf().zzae().zza("Next upload time is 0");
        zzah().zzb();
        zzai().zzy();
        return;
      }
      if (!zzs().zzy())
      {
        zzf().zzae().zza("No network");
        zzah().zza();
        zzai().zzy();
        return;
      }
      long l13 = zze().zze.zza();
      long l14 = Math.max(0L, ((Long)zzcja.zzx.zzb()).longValue());
      if (!zzo().zza(l13, l14)) {
        l12 = Math.max(l12, l13 + l14);
      }
      zzah().zzb();
      long l15 = l12 - this.zzn.zza();
      if (l15 <= 0L)
      {
        l15 = Math.max(0L, ((Long)zzcja.zzac.zzb()).longValue());
        zze().zzc.zza(this.zzn.zza());
      }
      zzf().zzae().zza("Upload scheduled in approximately ms", Long.valueOf(l15));
      zzai().zza(l15);
      return;
    }
    zzf().zzae().zza("Nothing to upload or uploading impossible");
    zzah().zzb();
    zzai().zzy();
  }
  
  private final boolean zzan()
  {
    zzh().zzc();
    zza();
    return this.zzaa;
  }
  
  private final void zzao()
  {
    zzh().zzc();
    if ((!this.zzal) && (!this.zzam) && (!this.zzan))
    {
      zzf().zzae().zza("Stopping uploading service(s)");
      if (this.zzag == null) {
        return;
      }
      Iterator localIterator = this.zzag.iterator();
      while (localIterator.hasNext()) {
        ((Runnable)localIterator.next()).run();
      }
      this.zzag.clear();
      return;
    }
    zzf().zzae().zza("Not stopping services. fetch, network, upload", Boolean.valueOf(this.zzal), Boolean.valueOf(this.zzam), Boolean.valueOf(this.zzan));
  }
  
  private final zzcig zzb(String paramString)
  {
    Object localObject = paramString;
    zzcif localZzcif = zzq().zzb((String)localObject);
    zzcjm localZzcjm;
    String str;
    if ((localZzcif != null) && (!TextUtils.isEmpty(localZzcif.zzi())))
    {
      Boolean localBoolean = zzb(localZzcif);
      if ((localBoolean != null) && (!localBoolean.booleanValue()))
      {
        localZzcjm = zzf().zzy();
        str = "App version does not match; dropping. appId";
        localObject = zzcjk.zza(paramString);
      }
    }
    for (;;)
    {
      localZzcjm.zza(str, localObject);
      return null;
      zzcig localZzcig = new zzcig((String)localObject, localZzcif.zzd(), localZzcif.zzi(), localZzcif.zzj(), localZzcif.zzk(), localZzcif.zzl(), localZzcif.zzm(), null, localZzcif.zzn(), false, localZzcif.zzf(), localZzcif.zzaa(), 0L, 0, localZzcif.zzab());
      return localZzcig;
      localZzcjm = zzf().zzad();
      str = "No app data available; dropping";
    }
  }
  
  /* Error */
  private final Boolean zzb(zzcif paramZzcif)
  {
    // Byte code:
    //   0: aload_1
    //   1: invokevirtual 1377	com/google/android/gms/internal/zzcif:zzj	()J
    //   4: ldc2_w 1394
    //   7: lcmp
    //   8: ifeq +39 -> 47
    //   11: aload_0
    //   12: getfield 97	com/google/android/gms/internal/zzckk:zzb	Landroid/content/Context;
    //   15: invokestatic 343	com/google/android/gms/internal/zzbii:zza	(Landroid/content/Context;)Lcom/google/android/gms/internal/zzbih;
    //   18: aload_1
    //   19: invokevirtual 408	com/google/android/gms/internal/zzcif:zzb	()Ljava/lang/String;
    //   22: iconst_0
    //   23: invokevirtual 348	com/google/android/gms/internal/zzbih:zzb	(Ljava/lang/String;I)Landroid/content/pm/PackageInfo;
    //   26: getfield 372	android/content/pm/PackageInfo:versionCode	I
    //   29: istore 4
    //   31: aload_1
    //   32: invokevirtual 1377	com/google/android/gms/internal/zzcif:zzj	()J
    //   35: iload 4
    //   37: i2l
    //   38: lcmp
    //   39: ifne +52 -> 91
    //   42: iconst_1
    //   43: invokestatic 990	java/lang/Boolean:valueOf	(Z)Ljava/lang/Boolean;
    //   46: areturn
    //   47: aload_0
    //   48: getfield 97	com/google/android/gms/internal/zzckk:zzb	Landroid/content/Context;
    //   51: invokestatic 343	com/google/android/gms/internal/zzbii:zza	(Landroid/content/Context;)Lcom/google/android/gms/internal/zzbih;
    //   54: aload_1
    //   55: invokevirtual 408	com/google/android/gms/internal/zzcif:zzb	()Ljava/lang/String;
    //   58: iconst_0
    //   59: invokevirtual 348	com/google/android/gms/internal/zzbih:zzb	(Ljava/lang/String;I)Landroid/content/pm/PackageInfo;
    //   62: getfield 369	android/content/pm/PackageInfo:versionName	Ljava/lang/String;
    //   65: astore_2
    //   66: aload_1
    //   67: invokevirtual 1370	com/google/android/gms/internal/zzcif:zzi	()Ljava/lang/String;
    //   70: ifnull +21 -> 91
    //   73: aload_1
    //   74: invokevirtual 1370	com/google/android/gms/internal/zzcif:zzi	()Ljava/lang/String;
    //   77: aload_2
    //   78: invokevirtual 336	java/lang/String:equals	(Ljava/lang/Object;)Z
    //   81: ifeq +10 -> 91
    //   84: iconst_1
    //   85: invokestatic 990	java/lang/Boolean:valueOf	(Z)Ljava/lang/Boolean;
    //   88: astore_3
    //   89: aload_3
    //   90: areturn
    //   91: iconst_0
    //   92: invokestatic 990	java/lang/Boolean:valueOf	(Z)Ljava/lang/Boolean;
    //   95: areturn
    //   96: aconst_null
    //   97: areturn
    // Local variable table:
    //   start	length	slot	name	signature
    //   0	98	0	this	zzckk
    //   0	98	1	paramZzcif	zzcif
    //   65	13	2	str	String
    //   88	2	3	localBoolean	Boolean
    //   29	7	4	i	int
    //   96	1	5	localNameNotFoundException	PackageManager.NameNotFoundException
    // Exception table:
    //   from	to	target	type
    //   0	47	96	android/content/pm/PackageManager$NameNotFoundException
    //   47	89	96	android/content/pm/PackageManager$NameNotFoundException
  }
  
  private final void zzb(zzciy paramZzciy, zzcig paramZzcig)
  {
    zzbq.zza(paramZzcig);
    zzbq.zza(paramZzcig.zza);
    long l1 = System.nanoTime();
    zzh().zzc();
    zza();
    String str1 = paramZzcig.zza;
    zzo();
    if (!zzcnp.zza(paramZzciy, paramZzcig)) {
      return;
    }
    if (!paramZzcig.zzh)
    {
      zzd(paramZzcig);
      return;
    }
    if (zzj().zzb(str1, paramZzciy.zza))
    {
      zzf().zzaa().zza("Dropping blacklisted event. appId", zzcjk.zza(str1), zzp().zza(paramZzciy.zza));
      int m;
      if ((!zzo().zzk(str1)) && (!zzo().zzl(str1))) {
        m = 0;
      } else {
        m = 1;
      }
      if ((m == 0) && (!"_err".equals(paramZzciy.zza))) {
        zzo().zza(str1, 11, "_ev", paramZzciy.zza, 0);
      }
      if (m != 0)
      {
        zzcif localZzcif2 = zzq().zzb(str1);
        if (localZzcif2 != null)
        {
          long l9 = Math.max(localZzcif2.zzq(), localZzcif2.zzp());
          if (Math.abs(this.zzn.zza() - l9) > ((Long)zzcja.zzaf.zzb()).longValue())
          {
            zzf().zzad().zza("Fetching config for blacklisted app");
            zza(localZzcif2);
          }
        }
      }
      return;
    }
    if (zzf().zza(2)) {
      zzf().zzae().zza("Logging event", zzp().zza(paramZzciy));
    }
    zzq().zzx();
    for (;;)
    {
      try
      {
        zzd(paramZzcig);
        if ((("_iap".equals(paramZzciy.zza)) || ("ecommerce_purchase".equals(paramZzciy.zza))) && (!zza(str1, paramZzciy)))
        {
          zzq().zzy();
          return;
        }
        boolean bool1 = zzcnp.zza(paramZzciy.zza);
        boolean bool2 = "_err".equals(paramZzciy.zza);
        zzcin localZzcin1 = zzq().zza(zzak(), str1, true, bool1, false, bool2, false);
        long l2 = localZzcin1.zzb - ((Integer)zzcja.zzq.zzb()).intValue();
        if (l2 > 0L)
        {
          if (l2 % 1000L == 1L) {
            zzf().zzy().zza("Data loss. Too many events logged. appId, count", zzcjk.zza(str1), Long.valueOf(localZzcin1.zzb));
          }
          zzq().zzy();
          return;
        }
        if (bool1)
        {
          long l8 = localZzcin1.zza - ((Integer)zzcja.zzs.zzb()).intValue();
          if (l8 > 0L)
          {
            if (l8 % 1000L == 1L) {
              zzf().zzy().zza("Data loss. Too many public events logged. appId, count", zzcjk.zza(str1), Long.valueOf(localZzcin1.zza));
            }
            zzo().zza(str1, 16, "_ev", paramZzciy.zza, 0);
            zzq().zzy();
            return;
          }
        }
        if (bool2)
        {
          long l7 = localZzcin1.zzd - Math.max(0, Math.min(1000000, this.zzc.zzb(paramZzcig.zza, zzcja.zzr)));
          if (l7 > 0L)
          {
            if (l7 == 1L) {
              zzf().zzy().zza("Too many error events logged. appId, count", zzcjk.zza(str1), Long.valueOf(localZzcin1.zzd));
            }
            zzq().zzy();
            return;
          }
        }
        Bundle localBundle = paramZzciy.zzb.zzb();
        zzo().zza(localBundle, "_o", paramZzciy.zzc);
        if (zzo().zzi(str1))
        {
          zzo().zza(localBundle, "_dbg", Long.valueOf(1L));
          zzo().zza(localBundle, "_r", Long.valueOf(1L));
        }
        long l3 = zzq().zzc(str1);
        if (l3 > 0L) {
          zzf().zzaa().zza("Data lost. Too many events stored on disk, deleted. appId", zzcjk.zza(str1), Long.valueOf(l3));
        }
        String str2 = paramZzciy.zzc;
        String str3 = paramZzciy.zza;
        long l4 = paramZzciy.zzd;
        Object localObject2 = localZzcit1;
        zzcit localZzcit1 = new zzcit(this, str2, str1, str3, l4, 0L, localBundle);
        zzciu localZzciu1 = zzq().zza(str1, ((zzcit)localObject2).zzb);
        zzciu localZzciu2;
        if (localZzciu1 == null)
        {
          if ((zzq().zzf(str1) >= 500L) && (bool1))
          {
            zzf().zzy().zza("Too many event names used, ignoring event. appId, name, supported count", zzcjk.zza(str1), zzp().zza(((zzcit)localObject2).zzb), Integer.valueOf(500));
            zzo().zza(str1, 8, null, null, 0);
            return;
          }
          String str4 = ((zzcit)localObject2).zzb;
          long l5 = ((zzcit)localObject2).zzc;
          localZzciu2 = new zzciu(str1, str4, 0L, 0L, l5, 0L, null, null, null);
        }
        else
        {
          zzcit localZzcit2 = ((zzcit)localObject2).zza(this, localZzciu1.zze);
          localZzciu2 = localZzciu1.zza(localZzcit2.zzc);
          localObject2 = localZzcit2;
        }
        zzq().zza(localZzciu2);
        zzh().zzc();
        zza();
        zzbq.zza(localObject2);
        zzbq.zza(paramZzcig);
        zzbq.zza(((zzcit)localObject2).zza);
        zzbq.zzb(((zzcit)localObject2).zza.equals(paramZzcig.zza));
        zzcof localZzcof = new zzcof();
        int i = 1;
        localZzcof.zza = Integer.valueOf(i);
        localZzcof.zzi = "android";
        localZzcof.zzo = paramZzcig.zza;
        localZzcof.zzn = paramZzcig.zzd;
        localZzcof.zzp = paramZzcig.zzc;
        Integer localInteger;
        if (paramZzcig.zzj == -2147483648L) {
          localInteger = null;
        } else {
          localInteger = Integer.valueOf((int)paramZzcig.zzj);
        }
        localZzcof.zzac = localInteger;
        localZzcof.zzq = Long.valueOf(paramZzcig.zze);
        localZzcof.zzy = paramZzcig.zzb;
        Long localLong;
        if (paramZzcig.zzf == 0L) {
          localLong = null;
        } else {
          localLong = Long.valueOf(paramZzcig.zzf);
        }
        localZzcof.zzv = localLong;
        Pair localPair = zze().zza(paramZzcig.zza);
        if ((localPair != null) && (!TextUtils.isEmpty((CharSequence)localPair.first)))
        {
          if (paramZzcig.zzo)
          {
            localZzcof.zzs = ((String)localPair.first);
            localZzcof.zzt = ((Boolean)localPair.second);
          }
        }
        else if (!zzx().zza(this.zzb))
        {
          String str5 = Settings.Secure.getString(this.zzb.getContentResolver(), "android_id");
          if (str5 == null)
          {
            zzf().zzaa().zza("null secure ID. appId", zzcjk.zza(localZzcof.zzo));
            str5 = "null";
          }
          else if (str5.isEmpty())
          {
            zzf().zzaa().zza("empty secure ID. appId", zzcjk.zza(localZzcof.zzo));
          }
          localZzcof.zzad = str5;
        }
        zzx().zzaq();
        localZzcof.zzk = Build.MODEL;
        zzx().zzaq();
        localZzcof.zzj = Build.VERSION.RELEASE;
        localZzcof.zzm = Integer.valueOf((int)zzx().zzx());
        localZzcof.zzl = zzx().zzy();
        localZzcof.zzr = null;
        localZzcof.zzd = null;
        localZzcof.zze = null;
        localZzcof.zzf = null;
        localZzcof.zzaf = Long.valueOf(paramZzcig.zzl);
        if ((zzab()) && (zzcil.zzab())) {
          localZzcof.zzag = null;
        }
        zzcif localZzcif1 = zzq().zzb(paramZzcig.zza);
        if (localZzcif1 == null)
        {
          localZzcif1 = new zzcif(this, paramZzcig.zza);
          localZzcif1.zza(zzy().zzy());
          localZzcif1.zzd(paramZzcig.zzk);
          localZzcif1.zzb(paramZzcig.zzb);
          localZzcif1.zzc(zze().zzb(paramZzcig.zza));
          localZzcif1.zzf(0L);
          localZzcif1.zza(0L);
          localZzcif1.zzb(0L);
          localZzcif1.zze(paramZzcig.zzc);
          localZzcif1.zzc(paramZzcig.zzj);
          localZzcif1.zzf(paramZzcig.zzd);
          localZzcif1.zzd(paramZzcig.zze);
          localZzcif1.zze(paramZzcig.zzf);
          localZzcif1.zza(paramZzcig.zzh);
          localZzcif1.zzo(paramZzcig.zzl);
          zzq().zza(localZzcif1);
        }
        localZzcof.zzu = localZzcif1.zzc();
        localZzcof.zzab = localZzcif1.zzf();
        List localList = zzq().zza(paramZzcig.zza);
        localZzcof.zzc = new zzcoh[localList.size()];
        int k = 0;
        if (k < localList.size())
        {
          zzcoh localZzcoh = new zzcoh();
          localZzcof.zzc[k] = localZzcoh;
          localZzcoh.zzb = ((zzcno)localList.get(k)).zzc;
          localZzcoh.zza = Long.valueOf(((zzcno)localList.get(k)).zzd);
          zzo().zza(localZzcoh, ((zzcno)localList.get(k)).zze);
          k++;
          continue;
        }
        try
        {
          long l6 = zzq().zza(localZzcof);
          zzcim localZzcim = zzq();
          if (((zzcit)localObject2).zze == null) {
            break label2083;
          }
          Iterator localIterator = ((zzcit)localObject2).zze.iterator();
          if (localIterator.hasNext())
          {
            if (!"_r".equals((String)localIterator.next())) {
              continue;
            }
          }
          else
          {
            boolean bool3 = zzj().zzc(((zzcit)localObject2).zza, ((zzcit)localObject2).zzb);
            zzcin localZzcin2 = zzq().zza(zzak(), ((zzcit)localObject2).zza, false, false, false, false, false);
            if ((!bool3) || (localZzcin2.zze >= this.zzc.zza(((zzcit)localObject2).zza))) {
              break label2083;
            }
          }
          if (localZzcim.zza((zzcit)localObject2, l6, i)) {
            this.zzak = 0L;
          }
        }
        catch (IOException localIOException)
        {
          zzf().zzy().zza("Data loss. Failed to insert raw event metadata. appId", zzcjk.zza(localZzcof.zzo), localIOException);
        }
        zzq().zzy();
        if (zzf().zza(2)) {
          zzf().zzae().zza("Event recorded", zzp().zza((zzcit)localObject2));
        }
        zzq().zzz();
        zzam();
        zzf().zzae().zza("Background event processing time, ms", Long.valueOf((500000L + (System.nanoTime() - l1)) / 1000000L));
        return;
      }
      finally
      {
        zzq().zzz();
      }
      label2083:
      int j = 0;
    }
  }
  
  private static void zzb(zzclj paramZzclj)
  {
    if (paramZzclj == null) {
      throw new IllegalStateException("Component not created");
    }
    if (!paramZzclj.zzap())
    {
      String str = String.valueOf(paramZzclj.getClass());
      StringBuilder localStringBuilder = new StringBuilder(27 + String.valueOf(str).length());
      localStringBuilder.append("Component not initialized: ");
      localStringBuilder.append(str);
      throw new IllegalStateException(localStringBuilder.toString());
    }
  }
  
  private final void zzd(zzcig paramZzcig)
  {
    zzh().zzc();
    zza();
    zzbq.zza(paramZzcig);
    zzbq.zza(paramZzcig.zza);
    zzcif localZzcif = zzq().zzb(paramZzcig.zza);
    String str = zze().zzb(paramZzcig.zza);
    if (localZzcif == null)
    {
      localZzcif = new zzcif(this, paramZzcig.zza);
      localZzcif.zza(zzy().zzy());
      localZzcif.zzc(str);
    }
    for (;;)
    {
      i = 1;
      break label132;
      if (str.equals(localZzcif.zze())) {
        break;
      }
      localZzcif.zzc(str);
      localZzcif.zza(zzy().zzy());
    }
    int i = 0;
    label132:
    if ((!TextUtils.isEmpty(paramZzcig.zzb)) && (!paramZzcig.zzb.equals(localZzcif.zzd())))
    {
      localZzcif.zzb(paramZzcig.zzb);
      i = 1;
    }
    if ((!TextUtils.isEmpty(paramZzcig.zzk)) && (!paramZzcig.zzk.equals(localZzcif.zzf())))
    {
      localZzcif.zzd(paramZzcig.zzk);
      i = 1;
    }
    if ((paramZzcig.zze != 0L) && (paramZzcig.zze != localZzcif.zzl()))
    {
      localZzcif.zzd(paramZzcig.zze);
      i = 1;
    }
    if ((!TextUtils.isEmpty(paramZzcig.zzc)) && (!paramZzcig.zzc.equals(localZzcif.zzi())))
    {
      localZzcif.zze(paramZzcig.zzc);
      i = 1;
    }
    if (paramZzcig.zzj != localZzcif.zzj())
    {
      localZzcif.zzc(paramZzcig.zzj);
      i = 1;
    }
    if ((paramZzcig.zzd != null) && (!paramZzcig.zzd.equals(localZzcif.zzk())))
    {
      localZzcif.zzf(paramZzcig.zzd);
      i = 1;
    }
    if (paramZzcig.zzf != localZzcif.zzm())
    {
      localZzcif.zze(paramZzcig.zzf);
      i = 1;
    }
    if (paramZzcig.zzh != localZzcif.zzn())
    {
      localZzcif.zza(paramZzcig.zzh);
      i = 1;
    }
    if ((!TextUtils.isEmpty(paramZzcig.zzg)) && (!paramZzcig.zzg.equals(localZzcif.zzy())))
    {
      localZzcif.zzg(paramZzcig.zzg);
      i = 1;
    }
    if (paramZzcig.zzl != localZzcif.zzaa())
    {
      localZzcif.zzo(paramZzcig.zzl);
      i = 1;
    }
    if (paramZzcig.zzo != localZzcif.zzab())
    {
      localZzcif.zzb(paramZzcig.zzo);
      i = 1;
    }
    if (i != 0) {
      zzq().zza(localZzcif);
    }
  }
  
  public final String zza(String paramString)
  {
    Future localFuture = zzh().zza(new zzckm(this, paramString));
    try
    {
      String str = (String)localFuture.get(30000L, TimeUnit.MILLISECONDS);
      return str;
    }
    catch (TimeoutException|InterruptedException|ExecutionException localTimeoutException)
    {
      zzf().zzy().zza("Failed to get app instance id. appId", zzcjk.zza(paramString), localTimeoutException);
    }
    return null;
  }
  
  final void zza()
  {
    if (!this.zzz) {
      throw new IllegalStateException("AppMeasurement is not initialized");
    }
  }
  
  protected final void zza(int paramInt, Throwable paramThrowable, byte[] paramArrayOfByte)
  {
    zzh().zzc();
    zza();
    if (paramArrayOfByte == null) {}
    try
    {
      paramArrayOfByte = new byte[0];
      List localList = this.zzaf;
      this.zzaf = null;
      i = 1;
      if (((paramInt == 200) || (paramInt == 204)) && (paramThrowable == null)) {
        try
        {
          zze().zzc.zza(this.zzn.zza());
          zze().zzd.zza(0L);
          zzam();
          zzf().zzae().zza("Successful upload. Got network response. code, size", Integer.valueOf(paramInt), Integer.valueOf(paramArrayOfByte.length));
          zzq().zzx();
          try
          {
            Iterator localIterator = localList.iterator();
            while (localIterator.hasNext())
            {
              Long localLong = (Long)localIterator.next();
              zzcim localZzcim = zzq();
              long l = localLong.longValue();
              localZzcim.zzc();
              localZzcim.zzaq();
              SQLiteDatabase localSQLiteDatabase = localZzcim.zzaa();
              String[] arrayOfString = new String[i];
              arrayOfString[0] = String.valueOf(l);
              try
              {
                if (localSQLiteDatabase.delete("queue", "rowid=?", arrayOfString) != i) {
                  throw new SQLiteException("Deleted fewer rows from queue than expected");
                }
              }
              catch (SQLiteException localSQLiteException2)
              {
                localZzcim.zzt().zzy().zza("Failed to delete a bundle in a queue table", localSQLiteException2);
                throw localSQLiteException2;
              }
            }
            zzq().zzy();
            zzq().zzz();
            if ((zzs().zzy()) && (zzal()))
            {
              zzae();
            }
            else
            {
              this.zzaj = -1L;
              zzam();
            }
            this.zzak = 0L;
          }
          finally
          {
            zzq().zzz();
          }
          zzf().zzae().zza("Network upload failed. Will retry later. code, error", Integer.valueOf(paramInt), paramThrowable);
        }
        catch (SQLiteException localSQLiteException1)
        {
          zzf().zzy().zza("Database error while trying to delete uploaded bundles", localSQLiteException1);
          this.zzak = this.zzn.zzb();
          zzf().zzae().zza("Disable upload, time", Long.valueOf(this.zzak));
        }
      }
      zze().zzd.zza(this.zzn.zza());
      if (paramInt != 503) {
        if (paramInt != 429) {
          break label475;
        }
      }
    }
    finally
    {
      for (;;)
      {
        Object localObject1;
        continue;
        int i = 0;
      }
    }
    if (i != 0) {
      zze().zze.zza(this.zzn.zza());
    }
    zzam();
    this.zzam = false;
    zzao();
    return;
    this.zzam = false;
    zzao();
    throw localObject1;
  }
  
  final void zza(zzcig paramZzcig)
  {
    zzq().zzb(paramZzcig.zza);
    zzcim localZzcim = zzq();
    String str = paramZzcig.zza;
    zzbq.zza(str);
    localZzcim.zzc();
    localZzcim.zzaq();
    try
    {
      SQLiteDatabase localSQLiteDatabase = localZzcim.zzaa();
      String[] arrayOfString = { str };
      int i = 0 + localSQLiteDatabase.delete("apps", "app_id=?", arrayOfString) + localSQLiteDatabase.delete("events", "app_id=?", arrayOfString) + localSQLiteDatabase.delete("user_attributes", "app_id=?", arrayOfString) + localSQLiteDatabase.delete("conditional_properties", "app_id=?", arrayOfString) + localSQLiteDatabase.delete("raw_events", "app_id=?", arrayOfString) + localSQLiteDatabase.delete("raw_events_metadata", "app_id=?", arrayOfString) + localSQLiteDatabase.delete("queue", "app_id=?", arrayOfString) + localSQLiteDatabase.delete("audience_filter_values", "app_id=?", arrayOfString) + localSQLiteDatabase.delete("main_event_params", "app_id=?", arrayOfString);
      if (i > 0) {
        localZzcim.zzt().zzae().zza("Reset analytics data. app, records", str, Integer.valueOf(i));
      }
    }
    catch (SQLiteException localSQLiteException)
    {
      localZzcim.zzt().zzy().zza("Error resetting analytics data. appId, error", zzcjk.zza(str), localSQLiteException);
    }
    zzc(zza(this.zzb, paramZzcig.zza, paramZzcig.zzb, paramZzcig.zzh, paramZzcig.zzo));
  }
  
  final void zza(zzcij paramZzcij)
  {
    zzcig localZzcig = zzb(paramZzcij.zza);
    if (localZzcig != null) {
      zza(paramZzcij, localZzcig);
    }
  }
  
  final void zza(zzcij paramZzcij, zzcig paramZzcig)
  {
    zzbq.zza(paramZzcij);
    zzbq.zza(paramZzcij.zza);
    zzbq.zza(paramZzcij.zzb);
    zzbq.zza(paramZzcij.zzc);
    zzbq.zza(paramZzcij.zzc.zza);
    zzh().zzc();
    zza();
    if (TextUtils.isEmpty(paramZzcig.zzb)) {
      return;
    }
    if (!paramZzcig.zzh)
    {
      zzd(paramZzcig);
      return;
    }
    zzcij localZzcij1 = new zzcij(paramZzcij);
    localZzcij1.zze = false;
    zzq().zzx();
    try
    {
      zzcij localZzcij2 = zzq().zzd(localZzcij1.zza, localZzcij1.zzc.zza);
      if ((localZzcij2 != null) && (!localZzcij2.zzb.equals(localZzcij1.zzb))) {
        zzf().zzaa().zza("Updating a conditional user property with different origin. name, origin, origin (from DB)", zzp().zzc(localZzcij1.zzc.zza), localZzcij1.zzb, localZzcij2.zzb);
      }
      int i;
      if ((localZzcij2 != null) && (localZzcij2.zze))
      {
        localZzcij1.zzb = localZzcij2.zzb;
        localZzcij1.zzd = localZzcij2.zzd;
        localZzcij1.zzh = localZzcij2.zzh;
        localZzcij1.zzf = localZzcij2.zzf;
        localZzcij1.zzi = localZzcij2.zzi;
        localZzcij1.zze = localZzcij2.zze;
        zzcnm localZzcnm3 = new zzcnm(localZzcij1.zzc.zza, localZzcij2.zzc.zzb, localZzcij1.zzc.zza(), localZzcij2.zzc.zzc);
        localZzcij1.zzc = localZzcnm3;
        i = 0;
      }
      else
      {
        boolean bool = TextUtils.isEmpty(localZzcij1.zzf);
        i = 0;
        if (bool)
        {
          zzcnm localZzcnm1 = new zzcnm(localZzcij1.zzc.zza, localZzcij1.zzd, localZzcij1.zzc.zza(), localZzcij1.zzc.zzc);
          localZzcij1.zzc = localZzcnm1;
          localZzcij1.zze = true;
          i = 1;
        }
      }
      if (localZzcij1.zze)
      {
        zzcnm localZzcnm2 = localZzcij1.zzc;
        zzcno localZzcno = new zzcno(localZzcij1.zza, localZzcij1.zzb, localZzcnm2.zza, localZzcnm2.zzb, localZzcnm2.zza());
        zzcjm localZzcjm2;
        String str3;
        Object localObject4;
        String str4;
        if (zzq().zza(localZzcno))
        {
          localZzcjm2 = zzf().zzad();
          str3 = "User property updated immediately";
          localObject4 = localZzcij1.zza;
          str4 = zzp().zzc(localZzcno.zzc);
        }
        for (Object localObject5 = localZzcno.zze;; localObject5 = localZzcno.zze)
        {
          localZzcjm2.zza(str3, localObject4, str4, localObject5);
          break;
          localZzcjm2 = zzf().zzy();
          str3 = "(2)Too many active user properties, ignoring";
          localObject4 = zzcjk.zza(localZzcij1.zza);
          str4 = zzp().zzc(localZzcno.zzc);
        }
        if ((i != 0) && (localZzcij1.zzi != null)) {
          zzb(new zzciy(localZzcij1.zzi, localZzcij1.zzd), paramZzcig);
        }
      }
      zzcjm localZzcjm1;
      String str1;
      Object localObject2;
      String str2;
      if (zzq().zza(localZzcij1))
      {
        localZzcjm1 = zzf().zzad();
        str1 = "Conditional property added";
        localObject2 = localZzcij1.zza;
        str2 = zzp().zzc(localZzcij1.zzc.zza);
      }
      for (Object localObject3 = localZzcij1.zzc.zza();; localObject3 = localZzcij1.zzc.zza())
      {
        localZzcjm1.zza(str1, localObject2, str2, localObject3);
        break;
        localZzcjm1 = zzf().zzy();
        str1 = "Too many conditional properties, ignoring";
        localObject2 = zzcjk.zza(localZzcij1.zza);
        str2 = zzp().zzc(localZzcij1.zzc.zza);
      }
      zzq().zzy();
      return;
    }
    finally
    {
      zzq().zzz();
    }
  }
  
  final void zza(zzciy paramZzciy, zzcig paramZzcig)
  {
    zzbq.zza(paramZzcig);
    zzbq.zza(paramZzcig.zza);
    zzh().zzc();
    zza();
    String str1 = paramZzcig.zza;
    long l = paramZzciy.zzd;
    zzo();
    if (!zzcnp.zza(paramZzciy, paramZzcig)) {
      return;
    }
    if (!paramZzcig.zzh)
    {
      zzd(paramZzcig);
      return;
    }
    zzq().zzx();
    try
    {
      zzcim localZzcim1 = zzq();
      zzbq.zza(str1);
      localZzcim1.zzc();
      localZzcim1.zzaq();
      boolean bool = l < 0L;
      List localList1;
      if (bool)
      {
        localZzcim1.zzt().zzaa().zza("Invalid time querying timed out conditional properties", zzcjk.zza(str1), Long.valueOf(l));
        localList1 = Collections.emptyList();
      }
      else
      {
        String[] arrayOfString3 = new String[2];
        arrayOfString3[0] = str1;
        arrayOfString3[1] = String.valueOf(l);
        localList1 = localZzcim1.zza("active=0 and app_id=? and abs(? - creation_timestamp) > trigger_timeout", arrayOfString3);
      }
      Iterator localIterator1 = localList1.iterator();
      while (localIterator1.hasNext())
      {
        zzcij localZzcij3 = (zzcij)localIterator1.next();
        if (localZzcij3 != null)
        {
          zzf().zzad().zza("User property timed out", localZzcij3.zza, zzp().zzc(localZzcij3.zzc.zza), localZzcij3.zzc.zza());
          if (localZzcij3.zzg != null) {
            zzb(new zzciy(localZzcij3.zzg, l), paramZzcig);
          }
          zzq().zze(str1, localZzcij3.zzc.zza);
        }
      }
      zzcim localZzcim2 = zzq();
      zzbq.zza(str1);
      localZzcim2.zzc();
      localZzcim2.zzaq();
      List localList2;
      if (bool)
      {
        localZzcim2.zzt().zzaa().zza("Invalid time querying expired conditional properties", zzcjk.zza(str1), Long.valueOf(l));
        localList2 = Collections.emptyList();
      }
      else
      {
        String[] arrayOfString2 = new String[2];
        arrayOfString2[0] = str1;
        arrayOfString2[1] = String.valueOf(l);
        localList2 = localZzcim2.zza("active<>0 and app_id=? and abs(? - triggered_timestamp) > time_to_live", arrayOfString2);
      }
      ArrayList localArrayList1 = new ArrayList(localList2.size());
      Iterator localIterator2 = localList2.iterator();
      while (localIterator2.hasNext())
      {
        zzcij localZzcij2 = (zzcij)localIterator2.next();
        if (localZzcij2 != null)
        {
          zzf().zzad().zza("User property expired", localZzcij2.zza, zzp().zzc(localZzcij2.zzc.zza), localZzcij2.zzc.zza());
          zzq().zzb(str1, localZzcij2.zzc.zza);
          if (localZzcij2.zzk != null) {
            localArrayList1.add(localZzcij2.zzk);
          }
          zzq().zze(str1, localZzcij2.zzc.zza);
        }
      }
      ArrayList localArrayList2 = (ArrayList)localArrayList1;
      int i = localArrayList2.size();
      int j = 0;
      while (j < i)
      {
        Object localObject2 = localArrayList2.get(j);
        j++;
        zzb(new zzciy((zzciy)localObject2, l), paramZzcig);
      }
      zzcim localZzcim3 = zzq();
      String str2 = paramZzciy.zza;
      zzbq.zza(str1);
      zzbq.zza(str2);
      localZzcim3.zzc();
      localZzcim3.zzaq();
      List localList3;
      if (bool)
      {
        localZzcim3.zzt().zzaa().zza("Invalid time querying triggered conditional properties", zzcjk.zza(str1), localZzcim3.zzo().zza(str2), Long.valueOf(l));
        localList3 = Collections.emptyList();
      }
      else
      {
        String[] arrayOfString1 = new String[3];
        arrayOfString1[0] = str1;
        arrayOfString1[1] = str2;
        arrayOfString1[2] = String.valueOf(l);
        localList3 = localZzcim3.zza("active=0 and app_id=? and trigger_event_name=? and abs(? - creation_timestamp) <= trigger_timeout", arrayOfString1);
      }
      ArrayList localArrayList3 = new ArrayList(localList3.size());
      Object localObject3 = localList3.iterator();
      while (((Iterator)localObject3).hasNext())
      {
        zzcij localZzcij1 = (zzcij)((Iterator)localObject3).next();
        if (localZzcij1 != null)
        {
          zzcnm localZzcnm = localZzcij1.zzc;
          String str3 = localZzcij1.zza;
          String str4 = localZzcij1.zzb;
          String str5 = localZzcnm.zza;
          Object localObject5 = localZzcnm.zza();
          Object localObject6 = localObject3;
          zzcno localZzcno = new zzcno(str3, str4, str5, l, localObject5);
          zzcjm localZzcjm;
          String str6;
          Object localObject7;
          String str7;
          if (zzq().zza(localZzcno))
          {
            localZzcjm = zzf().zzad();
            str6 = "User property triggered";
            localObject7 = localZzcij1.zza;
            str7 = zzp().zzc(localZzcno.zzc);
          }
          for (Object localObject8 = localZzcno.zze;; localObject8 = localZzcno.zze)
          {
            localZzcjm.zza(str6, localObject7, str7, localObject8);
            break;
            localZzcjm = zzf().zzy();
            str6 = "Too many active user properties, ignoring";
            localObject7 = zzcjk.zza(localZzcij1.zza);
            str7 = zzp().zzc(localZzcno.zzc);
          }
          if (localZzcij1.zzi != null) {
            localArrayList3.add(localZzcij1.zzi);
          }
          localZzcij1.zzc = new zzcnm(localZzcno);
          localZzcij1.zze = true;
          zzq().zza(localZzcij1);
          localObject3 = localObject6;
        }
      }
      zzb(paramZzciy, paramZzcig);
      ArrayList localArrayList4 = (ArrayList)localArrayList3;
      int k = localArrayList4.size();
      int m = 0;
      while (m < k)
      {
        Object localObject4 = localArrayList4.get(m);
        m++;
        zzb(new zzciy((zzciy)localObject4, l), paramZzcig);
      }
      zzq().zzy();
      return;
    }
    finally
    {
      zzq().zzz();
    }
  }
  
  final void zza(zzciy paramZzciy, String paramString)
  {
    zzcif localZzcif = zzq().zzb(paramString);
    if ((localZzcif != null) && (!TextUtils.isEmpty(localZzcif.zzi())))
    {
      Boolean localBoolean = zzb(localZzcif);
      if (localBoolean == null)
      {
        if (!"_ui".equals(paramZzciy.zza)) {
          zzf().zzaa().zza("Could not find package. appId", zzcjk.zza(paramString));
        }
      }
      else if (!localBoolean.booleanValue())
      {
        zzf().zzy().zza("App version does not match; dropping event. appId", zzcjk.zza(paramString));
        return;
      }
      zzcig localZzcig = new zzcig(paramString, localZzcif.zzd(), localZzcif.zzi(), localZzcif.zzj(), localZzcif.zzk(), localZzcif.zzl(), localZzcif.zzm(), null, localZzcif.zzn(), false, localZzcif.zzf(), localZzcif.zzaa(), 0L, 0, localZzcif.zzab());
      zza(paramZzciy, localZzcig);
      return;
    }
    zzf().zzad().zza("No app data available; dropping event", paramString);
  }
  
  final void zza(zzclj paramZzclj)
  {
    this.zzah = (1 + this.zzah);
  }
  
  final void zza(zzcnm paramZzcnm, zzcig paramZzcig)
  {
    zzh().zzc();
    zza();
    if (TextUtils.isEmpty(paramZzcig.zzb)) {
      return;
    }
    if (!paramZzcig.zzh)
    {
      zzd(paramZzcig);
      return;
    }
    int i = zzo().zzd(paramZzcnm.zza);
    if (i != 0)
    {
      zzo();
      String str2 = zzcnp.zza(paramZzcnm.zza, 24, true);
      int n;
      if (paramZzcnm.zza != null) {
        n = paramZzcnm.zza.length();
      } else {
        n = 0;
      }
      zzo().zza(paramZzcig.zza, i, "_ev", str2, n);
      return;
    }
    int j = zzo().zzb(paramZzcnm.zza, paramZzcnm.zza());
    if (j != 0)
    {
      zzo();
      String str1 = zzcnp.zza(paramZzcnm.zza, 24, true);
      Object localObject3 = paramZzcnm.zza();
      int k = 0;
      if (localObject3 != null) {
        if (!(localObject3 instanceof String))
        {
          boolean bool2 = localObject3 instanceof CharSequence;
          k = 0;
          if (!bool2) {}
        }
        else
        {
          k = String.valueOf(localObject3).length();
        }
      }
      int m = k;
      zzo().zza(paramZzcig.zza, j, "_ev", str1, m);
      return;
    }
    Object localObject1 = zzo().zzc(paramZzcnm.zza, paramZzcnm.zza());
    if (localObject1 == null) {
      return;
    }
    zzcno localZzcno = new zzcno(paramZzcig.zza, paramZzcnm.zzc, paramZzcnm.zza, paramZzcnm.zzb, localObject1);
    zzf().zzad().zza("Setting user property", zzp().zzc(localZzcno.zzc), localObject1);
    zzq().zzx();
    try
    {
      zzd(paramZzcig);
      boolean bool1 = zzq().zza(localZzcno);
      zzq().zzy();
      if (bool1)
      {
        zzf().zzad().zza("User property set", zzp().zzc(localZzcno.zzc), localZzcno.zze);
      }
      else
      {
        zzf().zzy().zza("Too many unique user properties are set. Ignoring user property", zzp().zzc(localZzcno.zzc), localZzcno.zze);
        zzo().zza(paramZzcig.zza, 9, null, null, 0);
      }
      return;
    }
    finally
    {
      zzq().zzz();
    }
  }
  
  final void zza(Runnable paramRunnable)
  {
    zzh().zzc();
    if (this.zzag == null) {
      this.zzag = new ArrayList();
    }
    this.zzag.add(paramRunnable);
  }
  
  final void zza(String paramString, int paramInt, Throwable paramThrowable, byte[] paramArrayOfByte, Map<String, List<String>> paramMap)
  {
    zzh().zzc();
    zza();
    zzbq.zza(paramString);
    if (paramArrayOfByte == null) {}
    for (;;)
    {
      try
      {
        paramArrayOfByte = new byte[0];
        zzf().zzae().zza("onConfigFetched. Response size", Integer.valueOf(paramArrayOfByte.length));
        zzq().zzx();
      }
      finally
      {
        zzcif localZzcif;
        boolean bool2;
        zzcim localZzcim;
        label455:
        Object localObject2;
        continue;
        if (paramThrowable != null) {
          continue;
        }
        int j = i;
        continue;
        j = 0;
        continue;
        if (j != 0) {
          continue;
        }
        if (paramInt != 404) {
          continue;
        }
        continue;
        int i = 0;
        continue;
        List localList = null;
        continue;
        String str = null;
        if (paramInt == 404) {
          continue;
        }
        if (paramInt != 304) {
          continue;
        }
        continue;
      }
      try
      {
        localZzcif = zzq().zzb(paramString);
        i = 1;
        if ((paramInt == 200) || (paramInt == 204)) {
          continue;
        }
        if (paramInt != 304) {
          continue;
        }
      }
      finally
      {
        zzq().zzz();
      }
    }
    if (localZzcif == null)
    {
      zzf().zzaa().zza("App does not exist in onConfigFetched. appId", zzcjk.zza(paramString));
      break label455;
      localZzcif.zzh(this.zzn.zza());
      zzq().zza(localZzcif);
      zzf().zzae().zza("Fetching config failed. code, error", Integer.valueOf(paramInt), paramThrowable);
      zzj().zzc(paramString);
      zze().zzd.zza(this.zzn.zza());
      if (paramInt != 503) {
        if (paramInt != 429) {
          break label532;
        }
      }
      if (i != 0) {
        zze().zze.zza(this.zzn.zza());
      }
      zzam();
      break label455;
      if (paramMap == null) {
        break label538;
      }
      localList = (List)paramMap.get("Last-Modified");
      if ((localList == null) || (localList.size() <= 0)) {
        break label544;
      }
      str = (String)localList.get(0);
      break label547;
      bool2 = zzj().zza(paramString, paramArrayOfByte, str);
      if (!bool2) {
        localZzcim = zzq();
      }
      for (;;)
      {
        localZzcim.zzz();
        this.zzal = false;
        zzao();
        return;
        if (zzj().zza(paramString) == null)
        {
          boolean bool1 = zzj().zza(paramString, null, null);
          if (!bool1)
          {
            localZzcim = zzq();
            continue;
          }
        }
        localZzcif.zzg(this.zzn.zza());
        zzq().zza(localZzcif);
        if (paramInt == 404) {
          zzf().zzab().zza("Config not found. Using empty config. appId", paramString);
        } else {
          zzf().zzae().zza("Successfully fetched config. Got network response. code, size", Integer.valueOf(paramInt), Integer.valueOf(paramArrayOfByte.length));
        }
        if ((!zzs().zzy()) || (!zzal())) {
          break;
        }
        zzae();
        zzq().zzy();
        localZzcim = zzq();
      }
      this.zzal = false;
      zzao();
      throw localObject2;
    }
  }
  
  public final void zza(boolean paramBoolean)
  {
    zzam();
  }
  
  public final zzcib zzaa()
  {
    zza(this.zzq);
    return this.zzq;
  }
  
  public final boolean zzab()
  {
    zzh().zzc();
    zza();
    if (this.zzc.zzx()) {
      return false;
    }
    Boolean localBoolean = this.zzc.zzb("firebase_analytics_collection_enabled");
    boolean bool2;
    if (localBoolean != null)
    {
      bool2 = localBoolean.booleanValue();
    }
    else
    {
      boolean bool1 = zzbz.zzb();
      bool2 = false;
      if (!bool1) {
        bool2 = true;
      }
    }
    return zze().zzc(bool2);
  }
  
  final long zzac()
  {
    Long localLong = Long.valueOf(zze().zzh.zza());
    if (localLong.longValue() == 0L) {
      return this.zzao;
    }
    return Math.min(this.zzao, localLong.longValue());
  }
  
  public final void zzae()
  {
    zzh().zzc();
    zza();
    this.zzan = true;
    for (;;)
    {
      int m;
      int n;
      int i1;
      try
      {
        Boolean localBoolean = zzw().zzad();
        zzcjm localZzcjm;
        String str1;
        if (localBoolean == null)
        {
          localZzcjm = zzf().zzaa();
          str1 = "Upload data called on the client side before use of service was decided";
          localZzcjm.zza(str1);
          return;
        }
        if (localBoolean.booleanValue())
        {
          localZzcjm = zzf().zzy();
          str1 = "Upload called in the client side when service should be used";
          continue;
        }
        if (this.zzak > 0L)
        {
          zzam();
          continue;
        }
        zzh().zzc();
        if (this.zzaf != null)
        {
          i = 1;
          if (i != 0)
          {
            localZzcjm = zzf().zzae();
            str1 = "Uploading requested multiple times";
            continue;
          }
          if (!zzs().zzy())
          {
            zzf().zzae().zza("Network not connected, ignoring upload request");
            continue;
          }
          long l1 = this.zzn.zza();
          zza(null, l1 - zzcil.zzz());
          long l2 = zze().zzc.zza();
          if (l2 != 0L) {
            zzf().zzad().zza("Uploading events. Elapsed time since last upload attempt (ms)", Long.valueOf(Math.abs(l1 - l2)));
          }
          String str2 = zzq().zzab();
          if (!TextUtils.isEmpty(str2))
          {
            if (this.zzaj == -1L) {
              this.zzaj = zzq().zzai();
            }
            int j = this.zzc.zzb(str2, zzcja.zzm);
            int k = Math.max(0, this.zzc.zzb(str2, zzcja.zzn));
            List localList = zzq().zza(str2, j, k);
            if (localList.isEmpty()) {
              continue;
            }
            Iterator localIterator = localList.iterator();
            if (!localIterator.hasNext()) {
              break label1002;
            }
            zzcof localZzcof2 = (zzcof)((Pair)localIterator.next()).first;
            if (TextUtils.isEmpty(localZzcof2.zzs)) {
              continue;
            }
            str4 = localZzcof2.zzs;
            break label1005;
            if (m < localList.size())
            {
              zzcof localZzcof1 = (zzcof)((Pair)localList.get(m)).first;
              if ((TextUtils.isEmpty(localZzcof1.zzs)) || (localZzcof1.zzs.equals(str4))) {
                break label1016;
              }
              localList = localList.subList(0, m);
            }
            zzcoe localZzcoe = new zzcoe();
            localZzcoe.zza = new zzcof[localList.size()];
            ArrayList localArrayList = new ArrayList(localList.size());
            if ((!zzcil.zzab()) || (!this.zzc.zzc(str2))) {
              break label1022;
            }
            n = 1;
            break label1025;
            if (i1 < localZzcoe.zza.length)
            {
              localZzcoe.zza[i1] = ((zzcof)((Pair)localList.get(i1)).first);
              localArrayList.add((Long)((Pair)localList.get(i1)).second);
              localZzcoe.zza[i1].zzr = Long.valueOf(12197L);
              localZzcoe.zza[i1].zzd = Long.valueOf(l1);
              localZzcoe.zza[i1].zzz = Boolean.valueOf(false);
              if (n != 0) {
                break label1031;
              }
              localZzcoe.zza[i1].zzag = null;
              break label1031;
            }
            boolean bool = zzf().zza(2);
            String str5 = null;
            if (bool) {
              str5 = zzp().zza(localZzcoe);
            }
            byte[] arrayOfByte = zzo().zza(localZzcoe);
            String str6 = (String)zzcja.zzw.zzb();
            try
            {
              URL localURL = new URL(str6);
              zzbq.zzb(true ^ localArrayList.isEmpty());
              if (this.zzaf != null) {
                zzf().zzy().zza("Set uploading progress before finishing the previous upload");
              } else {
                this.zzaf = new ArrayList(localArrayList);
              }
              zze().zzd.zza(l1);
              String str7 = "?";
              if (localZzcoe.zza.length > 0) {
                str7 = localZzcoe.zza[0].zzo;
              }
              zzf().zzae().zza("Uploading data. app, uncompressed size, data", str7, Integer.valueOf(arrayOfByte.length), str5);
              this.zzam = true;
              zzcjo localZzcjo = zzs();
              zzckn localZzckn = new zzckn(this);
              localZzcjo.zzc();
              localZzcjo.zzaq();
              zzbq.zza(localURL);
              zzbq.zza(arrayOfByte);
              zzbq.zza(localZzckn);
              zzckf localZzckf = localZzcjo.zzs();
              zzcjs localZzcjs = new zzcjs(localZzcjo, str2, localURL, arrayOfByte, null, localZzckn);
              localZzckf.zzb(localZzcjs);
            }
            catch (MalformedURLException localMalformedURLException)
            {
              zzf();;
            }
            continue;
          }
          this.zzaj = -1L;
          String str3 = zzq().zza(l1 - zzcil.zzz());
          if (TextUtils.isEmpty(str3)) {
            continue;
          }
          zzcif localZzcif = zzq().zzb(str3);
          if (localZzcif == null) {
            continue;
          }
          zza(localZzcif);
          continue;
        }
        int i = 0;
      }
      finally
      {
        this.zzan = false;
        zzao();
      }
      continue;
      label1002:
      String str4 = null;
      label1005:
      if (str4 != null)
      {
        m = 0;
        continue;
        label1016:
        m++;
        continue;
        label1022:
        n = 0;
        label1025:
        i1 = 0;
        continue;
        label1031:
        i1++;
      }
    }
  }
  
  final void zzaf()
  {
    this.zzai = (1 + this.zzai);
  }
  
  final void zzag()
  {
    zzh().zzc();
    zza();
    if (!this.zzaa)
    {
      zzf().zzac().zza("This instance being marked as an uploader");
      zzh().zzc();
      zza();
      if ((zzan()) && (zzaj()))
      {
        int i = zza(this.zzae);
        int j = zzy().zzab();
        zzh().zzc();
        zzcjm localZzcjm;
        String str;
        if (i > j)
        {
          localZzcjm = zzf().zzy();
          str = "Panic: can't downgrade version. Previous, current version";
        }
        for (;;)
        {
          localZzcjm.zza(str, Integer.valueOf(i), Integer.valueOf(j));
          break;
          if (i >= j) {
            break;
          }
          if (zza(j, this.zzae))
          {
            localZzcjm = zzf().zzae();
            str = "Storage version upgraded. Previous, current version";
          }
          else
          {
            localZzcjm = zzf().zzy();
            str = "Storage version upgrade failed. Previous, current version";
          }
        }
      }
      this.zzaa = true;
      zzam();
    }
  }
  
  final void zzb(zzcig paramZzcig)
  {
    zzh().zzc();
    zza();
    zzbq.zza(paramZzcig.zza);
    zzd(paramZzcig);
  }
  
  final void zzb(zzcij paramZzcij)
  {
    zzcig localZzcig = zzb(paramZzcij.zza);
    if (localZzcig != null) {
      zzb(paramZzcij, localZzcig);
    }
  }
  
  final void zzb(zzcij paramZzcij, zzcig paramZzcig)
  {
    zzbq.zza(paramZzcij);
    zzbq.zza(paramZzcij.zza);
    zzbq.zza(paramZzcij.zzc);
    zzbq.zza(paramZzcij.zzc.zza);
    zzh().zzc();
    zza();
    if (TextUtils.isEmpty(paramZzcig.zzb)) {
      return;
    }
    if (!paramZzcig.zzh)
    {
      zzd(paramZzcig);
      return;
    }
    zzq().zzx();
    try
    {
      zzd(paramZzcig);
      zzcij localZzcij = zzq().zzd(paramZzcij.zza, paramZzcij.zzc.zza);
      if (localZzcij != null)
      {
        zzf().zzad().zza("Removing conditional user property", paramZzcij.zza, zzp().zzc(paramZzcij.zzc.zza));
        zzq().zze(paramZzcij.zza, paramZzcij.zzc.zza);
        if (localZzcij.zze) {
          zzq().zzb(paramZzcij.zza, paramZzcij.zzc.zza);
        }
        if (paramZzcij.zzk != null)
        {
          zzciv localZzciv = paramZzcij.zzk.zzb;
          Bundle localBundle1 = null;
          if (localZzciv != null) {
            localBundle1 = paramZzcij.zzk.zzb.zzb();
          }
          Bundle localBundle2 = localBundle1;
          zzb(zzo().zza(paramZzcij.zzk.zza, localBundle2, localZzcij.zzb, paramZzcij.zzk.zzd, true, false), paramZzcig);
        }
      }
      else
      {
        zzf().zzaa().zza("Conditional user property doesn't exist", zzcjk.zza(paramZzcij.zza), zzp().zzc(paramZzcij.zzc.zza));
      }
      zzq().zzy();
      return;
    }
    finally
    {
      zzq().zzz();
    }
  }
  
  final void zzb(zzcnm paramZzcnm, zzcig paramZzcig)
  {
    zzh().zzc();
    zza();
    if (TextUtils.isEmpty(paramZzcig.zzb)) {
      return;
    }
    if (!paramZzcig.zzh)
    {
      zzd(paramZzcig);
      return;
    }
    zzf().zzad().zza("Removing user property", zzp().zzc(paramZzcnm.zza));
    zzq().zzx();
    try
    {
      zzd(paramZzcig);
      zzq().zzb(paramZzcig.zza, paramZzcnm.zza);
      zzq().zzy();
      zzf().zzad().zza("User property removed", zzp().zzc(paramZzcnm.zza));
      return;
    }
    finally
    {
      zzq().zzz();
    }
  }
  
  protected final boolean zzb()
  {
    zza();
    zzh().zzc();
    if ((this.zzab == null) || (this.zzac == 0L) || ((this.zzab != null) && (!this.zzab.booleanValue()) && (Math.abs(this.zzn.zzb() - this.zzac) > 1000L)))
    {
      this.zzac = this.zzn.zzb();
      boolean bool1 = zzo().zzg("android.permission.INTERNET");
      boolean bool2 = false;
      if (bool1)
      {
        boolean bool3 = zzo().zzg("android.permission.ACCESS_NETWORK_STATE");
        bool2 = false;
        if (bool3) {
          if (!zzbii.zza(this.zzb).zza())
          {
            boolean bool4 = zzckb.zza(this.zzb);
            bool2 = false;
            if (bool4)
            {
              boolean bool5 = zzcmz.zza(this.zzb, false);
              bool2 = false;
              if (!bool5) {}
            }
          }
          else
          {
            bool2 = true;
          }
        }
      }
      this.zzab = Boolean.valueOf(bool2);
      if (this.zzab.booleanValue()) {
        this.zzab = Boolean.valueOf(zzo().zze(zzy().zzaa()));
      }
    }
    return this.zzab.booleanValue();
  }
  
  /* Error */
  public final byte[] zzb(zzciy paramZzciy, String paramString)
  {
    // Byte code:
    //   0: aload_0
    //   1: invokevirtual 1257	com/google/android/gms/internal/zzckk:zza	()V
    //   4: aload_0
    //   5: invokevirtual 255	com/google/android/gms/internal/zzckk:zzh	()Lcom/google/android/gms/internal/zzckf;
    //   8: invokevirtual 257	com/google/android/gms/internal/zzcli:zzc	()V
    //   11: invokestatic 2046	com/google/android/gms/internal/zzckk:zzad	()V
    //   14: aload_1
    //   15: invokestatic 91	com/google/android/gms/common/internal/zzbq:zza	(Ljava/lang/Object;)Ljava/lang/Object;
    //   18: pop
    //   19: aload_2
    //   20: invokestatic 1169	com/google/android/gms/common/internal/zzbq:zza	(Ljava/lang/String;)Ljava/lang/String;
    //   23: pop
    //   24: new 1959	com/google/android/gms/internal/zzcoe
    //   27: dup
    //   28: invokespecial 1960	com/google/android/gms/internal/zzcoe:<init>	()V
    //   31: astore 5
    //   33: aload_0
    //   34: invokevirtual 649	com/google/android/gms/internal/zzckk:zzq	()Lcom/google/android/gms/internal/zzcim;
    //   37: invokevirtual 651	com/google/android/gms/internal/zzcim:zzx	()V
    //   40: aload_0
    //   41: invokevirtual 649	com/google/android/gms/internal/zzckk:zzq	()Lcom/google/android/gms/internal/zzcim;
    //   44: aload_2
    //   45: invokevirtual 1049	com/google/android/gms/internal/zzcim:zzb	(Ljava/lang/String;)Lcom/google/android/gms/internal/zzcif;
    //   48: astore 8
    //   50: aload 8
    //   52: ifnonnull +41 -> 93
    //   55: aload_0
    //   56: invokevirtual 232	com/google/android/gms/internal/zzckk:zzf	()Lcom/google/android/gms/internal/zzcjk;
    //   59: invokevirtual 591	com/google/android/gms/internal/zzcjk:zzad	()Lcom/google/android/gms/internal/zzcjm;
    //   62: ldc_w 2048
    //   65: aload_2
    //   66: invokevirtual 288	com/google/android/gms/internal/zzcjm:zza	(Ljava/lang/String;Ljava/lang/Object;)V
    //   69: iconst_0
    //   70: newarray byte
    //   72: astore 92
    //   74: aload_0
    //   75: invokevirtual 649	com/google/android/gms/internal/zzckk:zzq	()Lcom/google/android/gms/internal/zzcim;
    //   78: invokevirtual 1103	com/google/android/gms/internal/zzcim:zzz	()V
    //   81: aload 92
    //   83: areturn
    //   84: astore 73
    //   86: aload 73
    //   88: astore 7
    //   90: goto +1842 -> 1932
    //   93: aload 8
    //   95: invokevirtual 1385	com/google/android/gms/internal/zzcif:zzn	()Z
    //   98: istore 9
    //   100: iload 9
    //   102: ifne +20 -> 122
    //   105: aload_0
    //   106: invokevirtual 232	com/google/android/gms/internal/zzckk:zzf	()Lcom/google/android/gms/internal/zzcjk;
    //   109: invokevirtual 591	com/google/android/gms/internal/zzcjk:zzad	()Lcom/google/android/gms/internal/zzcjm;
    //   112: ldc_w 2050
    //   115: aload_2
    //   116: invokevirtual 288	com/google/android/gms/internal/zzcjm:zza	(Ljava/lang/String;Ljava/lang/Object;)V
    //   119: goto -50 -> 69
    //   122: ldc_w 1429
    //   125: aload_1
    //   126: getfield 1120	com/google/android/gms/internal/zzciy:zza	Ljava/lang/String;
    //   129: invokevirtual 336	java/lang/String:equals	(Ljava/lang/Object;)Z
    //   132: istore 10
    //   134: iload 10
    //   136: ifne +20 -> 156
    //   139: ldc_w 1119
    //   142: aload_1
    //   143: getfield 1120	com/google/android/gms/internal/zzciy:zza	Ljava/lang/String;
    //   146: invokevirtual 336	java/lang/String:equals	(Ljava/lang/Object;)Z
    //   149: istore 91
    //   151: iload 91
    //   153: ifeq +33 -> 186
    //   156: aload_0
    //   157: aload_2
    //   158: aload_1
    //   159: invokespecial 1431	com/google/android/gms/internal/zzckk:zza	(Ljava/lang/String;Lcom/google/android/gms/internal/zzciy;)Z
    //   162: istore 11
    //   164: iload 11
    //   166: ifne +20 -> 186
    //   169: aload_0
    //   170: invokevirtual 232	com/google/android/gms/internal/zzckk:zzf	()Lcom/google/android/gms/internal/zzcjk;
    //   173: invokevirtual 234	com/google/android/gms/internal/zzcjk:zzaa	()Lcom/google/android/gms/internal/zzcjm;
    //   176: ldc_w 2052
    //   179: aload_2
    //   180: invokestatic 326	com/google/android/gms/internal/zzcjk:zza	(Ljava/lang/String;)Ljava/lang/Object;
    //   183: invokevirtual 288	com/google/android/gms/internal/zzcjm:zza	(Ljava/lang/String;Ljava/lang/Object;)V
    //   186: aload_0
    //   187: getfield 122	com/google/android/gms/internal/zzckk:zzc	Lcom/google/android/gms/internal/zzcil;
    //   190: aload_2
    //   191: invokevirtual 789	com/google/android/gms/internal/zzcil:zzd	(Ljava/lang/String;)Z
    //   194: istore 12
    //   196: lconst_0
    //   197: invokestatic 578	java/lang/Long:valueOf	(J)Ljava/lang/Long;
    //   200: astore 13
    //   202: iload 12
    //   204: ifeq +119 -> 323
    //   207: ldc_w 874
    //   210: aload_1
    //   211: getfield 1120	com/google/android/gms/internal/zzciy:zza	Ljava/lang/String;
    //   214: invokevirtual 336	java/lang/String:equals	(Ljava/lang/Object;)Z
    //   217: ifeq +106 -> 323
    //   220: aload_1
    //   221: getfield 1111	com/google/android/gms/internal/zzciy:zzb	Lcom/google/android/gms/internal/zzciv;
    //   224: ifnull +76 -> 300
    //   227: aload_1
    //   228: getfield 1111	com/google/android/gms/internal/zzciy:zzb	Lcom/google/android/gms/internal/zzciv;
    //   231: invokevirtual 2054	com/google/android/gms/internal/zzciv:zza	()I
    //   234: ifne +6 -> 240
    //   237: goto +63 -> 300
    //   240: aload_1
    //   241: getfield 1111	com/google/android/gms/internal/zzciy:zzb	Lcom/google/android/gms/internal/zzciv;
    //   244: ldc_w 876
    //   247: invokevirtual 1134	com/google/android/gms/internal/zzciv:zzb	(Ljava/lang/String;)Ljava/lang/Long;
    //   250: ifnonnull +35 -> 285
    //   253: aload_0
    //   254: invokevirtual 232	com/google/android/gms/internal/zzckk:zzf	()Lcom/google/android/gms/internal/zzcjk;
    //   257: invokevirtual 234	com/google/android/gms/internal/zzcjk:zzaa	()Lcom/google/android/gms/internal/zzcjm;
    //   260: astore 88
    //   262: ldc_w 2056
    //   265: astore 89
    //   267: aload_2
    //   268: invokestatic 326	com/google/android/gms/internal/zzcjk:zza	(Ljava/lang/String;)Ljava/lang/Object;
    //   271: astore 90
    //   273: aload 88
    //   275: aload 89
    //   277: aload 90
    //   279: invokevirtual 288	com/google/android/gms/internal/zzcjm:zza	(Ljava/lang/String;Ljava/lang/Object;)V
    //   282: goto +41 -> 323
    //   285: aload_1
    //   286: getfield 1111	com/google/android/gms/internal/zzciy:zzb	Lcom/google/android/gms/internal/zzciv;
    //   289: ldc_w 876
    //   292: invokevirtual 1134	com/google/android/gms/internal/zzciv:zzb	(Ljava/lang/String;)Ljava/lang/Long;
    //   295: astore 13
    //   297: goto +26 -> 323
    //   300: aload_0
    //   301: invokevirtual 232	com/google/android/gms/internal/zzckk:zzf	()Lcom/google/android/gms/internal/zzcjk;
    //   304: invokevirtual 234	com/google/android/gms/internal/zzcjk:zzaa	()Lcom/google/android/gms/internal/zzcjm;
    //   307: astore 88
    //   309: ldc_w 2058
    //   312: astore 89
    //   314: aload_2
    //   315: invokestatic 326	com/google/android/gms/internal/zzcjk:zza	(Ljava/lang/String;)Ljava/lang/Object;
    //   318: astore 90
    //   320: goto -47 -> 273
    //   323: new 727	com/google/android/gms/internal/zzcof
    //   326: dup
    //   327: invokespecial 728	com/google/android/gms/internal/zzcof:<init>	()V
    //   330: astore 14
    //   332: aload 5
    //   334: iconst_1
    //   335: anewarray 727	com/google/android/gms/internal/zzcof
    //   338: dup
    //   339: iconst_0
    //   340: aload 14
    //   342: aastore
    //   343: putfield 1963	com/google/android/gms/internal/zzcoe:zza	[Lcom/google/android/gms/internal/zzcof;
    //   346: aload 14
    //   348: iconst_1
    //   349: invokestatic 285	java/lang/Integer:valueOf	(I)Ljava/lang/Integer;
    //   352: putfield 1488	com/google/android/gms/internal/zzcof:zza	Ljava/lang/Integer;
    //   355: aload 14
    //   357: ldc_w 461
    //   360: putfield 1490	com/google/android/gms/internal/zzcof:zzi	Ljava/lang/String;
    //   363: aload 14
    //   365: aload 8
    //   367: invokevirtual 408	com/google/android/gms/internal/zzcif:zzb	()Ljava/lang/String;
    //   370: putfield 787	com/google/android/gms/internal/zzcof:zzo	Ljava/lang/String;
    //   373: aload 14
    //   375: aload 8
    //   377: invokevirtual 1379	com/google/android/gms/internal/zzcif:zzk	()Ljava/lang/String;
    //   380: putfield 1494	com/google/android/gms/internal/zzcof:zzn	Ljava/lang/String;
    //   383: aload 14
    //   385: aload 8
    //   387: invokevirtual 1370	com/google/android/gms/internal/zzcif:zzi	()Ljava/lang/String;
    //   390: putfield 1497	com/google/android/gms/internal/zzcof:zzp	Ljava/lang/String;
    //   393: aload 8
    //   395: invokevirtual 1377	com/google/android/gms/internal/zzcif:zzj	()J
    //   398: lstore 15
    //   400: lload 15
    //   402: ldc2_w 1394
    //   405: lcmp
    //   406: ifne +9 -> 415
    //   409: aconst_null
    //   410: astore 17
    //   412: goto +11 -> 423
    //   415: lload 15
    //   417: l2i
    //   418: invokestatic 285	java/lang/Integer:valueOf	(I)Ljava/lang/Integer;
    //   421: astore 17
    //   423: aload 14
    //   425: aload 17
    //   427: putfield 1501	com/google/android/gms/internal/zzcof:zzac	Ljava/lang/Integer;
    //   430: aload 14
    //   432: aload 8
    //   434: invokevirtual 1381	com/google/android/gms/internal/zzcif:zzl	()J
    //   437: invokestatic 578	java/lang/Long:valueOf	(J)Ljava/lang/Long;
    //   440: putfield 1504	com/google/android/gms/internal/zzcof:zzq	Ljava/lang/Long;
    //   443: aload 14
    //   445: aload 8
    //   447: invokevirtual 406	com/google/android/gms/internal/zzcif:zzd	()Ljava/lang/String;
    //   450: putfield 1081	com/google/android/gms/internal/zzcof:zzy	Ljava/lang/String;
    //   453: aload 14
    //   455: aload 8
    //   457: invokevirtual 1383	com/google/android/gms/internal/zzcif:zzm	()J
    //   460: invokestatic 578	java/lang/Long:valueOf	(J)Ljava/lang/Long;
    //   463: putfield 1508	com/google/android/gms/internal/zzcof:zzv	Ljava/lang/Long;
    //   466: aload_0
    //   467: invokevirtual 1581	com/google/android/gms/internal/zzckk:zzab	()Z
    //   470: istore 18
    //   472: iload 18
    //   474: ifeq +30 -> 504
    //   477: invokestatic 1582	com/google/android/gms/internal/zzcil:zzab	()Z
    //   480: ifeq +24 -> 504
    //   483: aload_0
    //   484: getfield 122	com/google/android/gms/internal/zzckk:zzc	Lcom/google/android/gms/internal/zzcil;
    //   487: aload 14
    //   489: getfield 787	com/google/android/gms/internal/zzcof:zzo	Ljava/lang/String;
    //   492: invokevirtual 1965	com/google/android/gms/internal/zzcil:zzc	(Ljava/lang/String;)Z
    //   495: ifeq +9 -> 504
    //   498: aload 14
    //   500: aconst_null
    //   501: putfield 1584	com/google/android/gms/internal/zzcof:zzag	Ljava/lang/String;
    //   504: aload_0
    //   505: invokevirtual 1239	com/google/android/gms/internal/zzckk:zze	()Lcom/google/android/gms/internal/zzcjv;
    //   508: aload 8
    //   510: invokevirtual 408	com/google/android/gms/internal/zzcif:zzb	()Ljava/lang/String;
    //   513: invokevirtual 1511	com/google/android/gms/internal/zzcjv:zza	(Ljava/lang/String;)Landroid/util/Pair;
    //   516: astore 19
    //   518: aload 8
    //   520: invokevirtual 1391	com/google/android/gms/internal/zzcif:zzab	()Z
    //   523: istore 20
    //   525: iload 20
    //   527: ifeq +48 -> 575
    //   530: aload 19
    //   532: ifnull +43 -> 575
    //   535: aload 19
    //   537: getfield 1516	android/util/Pair:first	Ljava/lang/Object;
    //   540: checkcast 359	java/lang/CharSequence
    //   543: invokestatic 357	android/text/TextUtils:isEmpty	(Ljava/lang/CharSequence;)Z
    //   546: ifne +29 -> 575
    //   549: aload 14
    //   551: aload 19
    //   553: getfield 1516	android/util/Pair:first	Ljava/lang/Object;
    //   556: checkcast 332	java/lang/String
    //   559: putfield 1520	com/google/android/gms/internal/zzcof:zzs	Ljava/lang/String;
    //   562: aload 14
    //   564: aload 19
    //   566: getfield 1523	android/util/Pair:second	Ljava/lang/Object;
    //   569: checkcast 929	java/lang/Boolean
    //   572: putfield 1525	com/google/android/gms/internal/zzcof:zzt	Ljava/lang/Boolean;
    //   575: aload_0
    //   576: invokevirtual 1528	com/google/android/gms/internal/zzckk:zzx	()Lcom/google/android/gms/internal/zzcis;
    //   579: invokevirtual 507	com/google/android/gms/internal/zzclj:zzaq	()V
    //   582: aload 14
    //   584: getstatic 1556	android/os/Build:MODEL	Ljava/lang/String;
    //   587: putfield 1558	com/google/android/gms/internal/zzcof:zzk	Ljava/lang/String;
    //   590: aload_0
    //   591: invokevirtual 1528	com/google/android/gms/internal/zzckk:zzx	()Lcom/google/android/gms/internal/zzcis;
    //   594: invokevirtual 507	com/google/android/gms/internal/zzclj:zzaq	()V
    //   597: aload 14
    //   599: getstatic 1563	android/os/Build$VERSION:RELEASE	Ljava/lang/String;
    //   602: putfield 1565	com/google/android/gms/internal/zzcof:zzj	Ljava/lang/String;
    //   605: aload 14
    //   607: aload_0
    //   608: invokevirtual 1528	com/google/android/gms/internal/zzckk:zzx	()Lcom/google/android/gms/internal/zzcis;
    //   611: invokevirtual 1567	com/google/android/gms/internal/zzcis:zzx	()J
    //   614: l2i
    //   615: invokestatic 285	java/lang/Integer:valueOf	(I)Ljava/lang/Integer;
    //   618: putfield 1569	com/google/android/gms/internal/zzcof:zzm	Ljava/lang/Integer;
    //   621: aload 14
    //   623: aload_0
    //   624: invokevirtual 1528	com/google/android/gms/internal/zzckk:zzx	()Lcom/google/android/gms/internal/zzcis;
    //   627: invokevirtual 1571	com/google/android/gms/internal/zzcis:zzy	()Ljava/lang/String;
    //   630: putfield 1573	com/google/android/gms/internal/zzcof:zzl	Ljava/lang/String;
    //   633: aload 14
    //   635: aload 8
    //   637: invokevirtual 413	com/google/android/gms/internal/zzcif:zzc	()Ljava/lang/String;
    //   640: putfield 1618	com/google/android/gms/internal/zzcof:zzu	Ljava/lang/String;
    //   643: aload 14
    //   645: aload 8
    //   647: invokevirtual 1387	com/google/android/gms/internal/zzcif:zzf	()Ljava/lang/String;
    //   650: putfield 1620	com/google/android/gms/internal/zzcof:zzab	Ljava/lang/String;
    //   653: aload_0
    //   654: invokevirtual 649	com/google/android/gms/internal/zzckk:zzq	()Lcom/google/android/gms/internal/zzcim;
    //   657: aload 8
    //   659: invokevirtual 408	com/google/android/gms/internal/zzcif:zzb	()Ljava/lang/String;
    //   662: invokevirtual 1623	com/google/android/gms/internal/zzcim:zza	(Ljava/lang/String;)Ljava/util/List;
    //   665: astore 21
    //   667: aload 14
    //   669: aload 21
    //   671: invokeinterface 782 1 0
    //   676: anewarray 904	com/google/android/gms/internal/zzcoh
    //   679: putfield 913	com/google/android/gms/internal/zzcof:zzc	[Lcom/google/android/gms/internal/zzcoh;
    //   682: iload 12
    //   684: ifeq +148 -> 832
    //   687: aload_0
    //   688: invokevirtual 649	com/google/android/gms/internal/zzckk:zzq	()Lcom/google/android/gms/internal/zzcim;
    //   691: aload 14
    //   693: getfield 787	com/google/android/gms/internal/zzcof:zzo	Ljava/lang/String;
    //   696: ldc_w 889
    //   699: invokevirtual 892	com/google/android/gms/internal/zzcim:zzc	(Ljava/lang/String;Ljava/lang/String;)Lcom/google/android/gms/internal/zzcno;
    //   702: astore 82
    //   704: aload 82
    //   706: ifnull +88 -> 794
    //   709: aload 82
    //   711: getfield 897	com/google/android/gms/internal/zzcno:zze	Ljava/lang/Object;
    //   714: ifnonnull +6 -> 720
    //   717: goto +77 -> 794
    //   720: aload 13
    //   722: invokevirtual 884	java/lang/Long:longValue	()J
    //   725: lconst_0
    //   726: lcmp
    //   727: ifle +1215 -> 1942
    //   730: aload 14
    //   732: getfield 787	com/google/android/gms/internal/zzcof:zzo	Ljava/lang/String;
    //   735: astore 84
    //   737: aload_0
    //   738: getfield 108	com/google/android/gms/internal/zzckk:zzn	Lcom/google/android/gms/common/util/zze;
    //   741: invokeinterface 113 1 0
    //   746: lstore 85
    //   748: aload 82
    //   750: getfield 897	com/google/android/gms/internal/zzcno:zze	Ljava/lang/Object;
    //   753: checkcast 575	java/lang/Long
    //   756: invokevirtual 884	java/lang/Long:longValue	()J
    //   759: aload 13
    //   761: invokevirtual 884	java/lang/Long:longValue	()J
    //   764: ladd
    //   765: invokestatic 578	java/lang/Long:valueOf	(J)Ljava/lang/Long;
    //   768: astore 87
    //   770: new 894	com/google/android/gms/internal/zzcno
    //   773: dup
    //   774: aload 84
    //   776: ldc_w 899
    //   779: ldc_w 889
    //   782: lload 85
    //   784: aload 87
    //   786: invokespecial 902	com/google/android/gms/internal/zzcno:<init>	(Ljava/lang/String;Ljava/lang/String;Ljava/lang/String;JLjava/lang/Object;)V
    //   789: astore 22
    //   791: goto +44 -> 835
    //   794: new 894	com/google/android/gms/internal/zzcno
    //   797: dup
    //   798: aload 14
    //   800: getfield 787	com/google/android/gms/internal/zzcof:zzo	Ljava/lang/String;
    //   803: ldc_w 899
    //   806: ldc_w 889
    //   809: aload_0
    //   810: getfield 108	com/google/android/gms/internal/zzckk:zzn	Lcom/google/android/gms/common/util/zze;
    //   813: invokeinterface 113 1 0
    //   818: aload 13
    //   820: invokespecial 902	com/google/android/gms/internal/zzcno:<init>	(Ljava/lang/String;Ljava/lang/String;Ljava/lang/String;JLjava/lang/Object;)V
    //   823: astore 83
    //   825: aload 83
    //   827: astore 22
    //   829: goto +6 -> 835
    //   832: aconst_null
    //   833: astore 22
    //   835: iconst_0
    //   836: istore 23
    //   838: aconst_null
    //   839: astore 24
    //   841: aload 21
    //   843: invokeinterface 782 1 0
    //   848: istore 25
    //   850: iload 23
    //   852: iload 25
    //   854: if_icmpge +157 -> 1011
    //   857: new 904	com/google/android/gms/internal/zzcoh
    //   860: dup
    //   861: invokespecial 905	com/google/android/gms/internal/zzcoh:<init>	()V
    //   864: astore 78
    //   866: aload 14
    //   868: getfield 913	com/google/android/gms/internal/zzcof:zzc	[Lcom/google/android/gms/internal/zzcoh;
    //   871: iload 23
    //   873: aload 78
    //   875: aastore
    //   876: aload 78
    //   878: aload 21
    //   880: iload 23
    //   882: invokeinterface 793 2 0
    //   887: checkcast 894	com/google/android/gms/internal/zzcno
    //   890: getfield 1178	com/google/android/gms/internal/zzcno:zzc	Ljava/lang/String;
    //   893: putfield 906	com/google/android/gms/internal/zzcoh:zzb	Ljava/lang/String;
    //   896: aload 21
    //   898: iload 23
    //   900: invokeinterface 793 2 0
    //   905: checkcast 894	com/google/android/gms/internal/zzcno
    //   908: astore 79
    //   910: aload 5
    //   912: astore 80
    //   914: aload 8
    //   916: astore 81
    //   918: aload 78
    //   920: aload 79
    //   922: getfield 1624	com/google/android/gms/internal/zzcno:zzd	J
    //   925: invokestatic 578	java/lang/Long:valueOf	(J)Ljava/lang/Long;
    //   928: putfield 908	com/google/android/gms/internal/zzcoh:zza	Ljava/lang/Long;
    //   931: aload_0
    //   932: invokevirtual 380	com/google/android/gms/internal/zzckk:zzo	()Lcom/google/android/gms/internal/zzcnp;
    //   935: aload 78
    //   937: aload 21
    //   939: iload 23
    //   941: invokeinterface 793 2 0
    //   946: checkcast 894	com/google/android/gms/internal/zzcno
    //   949: getfield 897	com/google/android/gms/internal/zzcno:zze	Ljava/lang/Object;
    //   952: invokevirtual 1627	com/google/android/gms/internal/zzcnp:zza	(Lcom/google/android/gms/internal/zzcoh;Ljava/lang/Object;)V
    //   955: iload 12
    //   957: ifeq +992 -> 1949
    //   960: ldc_w 889
    //   963: aload 78
    //   965: getfield 906	com/google/android/gms/internal/zzcoh:zzb	Ljava/lang/String;
    //   968: invokevirtual 336	java/lang/String:equals	(Ljava/lang/Object;)Z
    //   971: ifeq +978 -> 1949
    //   974: aload 78
    //   976: aload 22
    //   978: getfield 897	com/google/android/gms/internal/zzcno:zze	Ljava/lang/Object;
    //   981: checkcast 575	java/lang/Long
    //   984: putfield 910	com/google/android/gms/internal/zzcoh:zzd	Ljava/lang/Long;
    //   987: aload 78
    //   989: aload_0
    //   990: getfield 108	com/google/android/gms/internal/zzckk:zzn	Lcom/google/android/gms/common/util/zze;
    //   993: invokeinterface 113 1 0
    //   998: invokestatic 578	java/lang/Long:valueOf	(J)Ljava/lang/Long;
    //   1001: putfield 908	com/google/android/gms/internal/zzcoh:zza	Ljava/lang/Long;
    //   1004: aload 78
    //   1006: astore 24
    //   1008: goto +941 -> 1949
    //   1011: aload 5
    //   1013: astore 26
    //   1015: aload 8
    //   1017: astore 27
    //   1019: iload 12
    //   1021: ifeq +110 -> 1131
    //   1024: aload 24
    //   1026: ifnonnull +105 -> 1131
    //   1029: new 904	com/google/android/gms/internal/zzcoh
    //   1032: dup
    //   1033: invokespecial 905	com/google/android/gms/internal/zzcoh:<init>	()V
    //   1036: astore 75
    //   1038: aload 75
    //   1040: ldc_w 889
    //   1043: putfield 906	com/google/android/gms/internal/zzcoh:zzb	Ljava/lang/String;
    //   1046: aload 75
    //   1048: aload_0
    //   1049: getfield 108	com/google/android/gms/internal/zzckk:zzn	Lcom/google/android/gms/common/util/zze;
    //   1052: invokeinterface 113 1 0
    //   1057: invokestatic 578	java/lang/Long:valueOf	(J)Ljava/lang/Long;
    //   1060: putfield 908	com/google/android/gms/internal/zzcoh:zza	Ljava/lang/Long;
    //   1063: aload 75
    //   1065: aload 22
    //   1067: getfield 897	com/google/android/gms/internal/zzcno:zze	Ljava/lang/Object;
    //   1070: checkcast 575	java/lang/Long
    //   1073: putfield 910	com/google/android/gms/internal/zzcoh:zzd	Ljava/lang/Long;
    //   1076: aload 14
    //   1078: aload 14
    //   1080: getfield 913	com/google/android/gms/internal/zzcof:zzc	[Lcom/google/android/gms/internal/zzcoh;
    //   1083: iconst_1
    //   1084: aload 14
    //   1086: getfield 913	com/google/android/gms/internal/zzcof:zzc	[Lcom/google/android/gms/internal/zzcoh;
    //   1089: arraylength
    //   1090: iadd
    //   1091: invokestatic 830	java/util/Arrays:copyOf	([Ljava/lang/Object;I)[Ljava/lang/Object;
    //   1094: checkcast 914	[Lcom/google/android/gms/internal/zzcoh;
    //   1097: putfield 913	com/google/android/gms/internal/zzcof:zzc	[Lcom/google/android/gms/internal/zzcoh;
    //   1100: aload 14
    //   1102: getfield 913	com/google/android/gms/internal/zzcof:zzc	[Lcom/google/android/gms/internal/zzcoh;
    //   1105: astore 76
    //   1107: aload 14
    //   1109: getfield 913	com/google/android/gms/internal/zzcof:zzc	[Lcom/google/android/gms/internal/zzcoh;
    //   1112: arraylength
    //   1113: istore 77
    //   1115: iconst_1
    //   1116: istore 28
    //   1118: aload 76
    //   1120: iload 77
    //   1122: iload 28
    //   1124: isub
    //   1125: aload 75
    //   1127: aastore
    //   1128: goto +6 -> 1134
    //   1131: iconst_1
    //   1132: istore 28
    //   1134: aload 13
    //   1136: invokevirtual 884	java/lang/Long:longValue	()J
    //   1139: lstore 29
    //   1141: lload 29
    //   1143: lconst_0
    //   1144: lcmp
    //   1145: ifle +13 -> 1158
    //   1148: aload_0
    //   1149: invokevirtual 649	com/google/android/gms/internal/zzckk:zzq	()Lcom/google/android/gms/internal/zzcim;
    //   1152: aload 22
    //   1154: invokevirtual 917	com/google/android/gms/internal/zzcim:zza	(Lcom/google/android/gms/internal/zzcno;)Z
    //   1157: pop
    //   1158: aload_1
    //   1159: getfield 1111	com/google/android/gms/internal/zzciy:zzb	Lcom/google/android/gms/internal/zzciv;
    //   1162: invokevirtual 1453	com/google/android/gms/internal/zzciv:zzb	()Landroid/os/Bundle;
    //   1165: astore 31
    //   1167: ldc_w 1429
    //   1170: aload_1
    //   1171: getfield 1120	com/google/android/gms/internal/zzciy:zza	Ljava/lang/String;
    //   1174: invokevirtual 336	java/lang/String:equals	(Ljava/lang/Object;)Z
    //   1177: istore 32
    //   1179: iload 32
    //   1181: ifeq +34 -> 1215
    //   1184: aload 31
    //   1186: ldc_w 820
    //   1189: lconst_1
    //   1190: invokevirtual 2064	android/os/Bundle:putLong	(Ljava/lang/String;J)V
    //   1193: aload_0
    //   1194: invokevirtual 232	com/google/android/gms/internal/zzckk:zzf	()Lcom/google/android/gms/internal/zzcjk;
    //   1197: invokevirtual 591	com/google/android/gms/internal/zzcjk:zzad	()Lcom/google/android/gms/internal/zzcjm;
    //   1200: ldc_w 2066
    //   1203: invokevirtual 241	com/google/android/gms/internal/zzcjm:zza	(Ljava/lang/String;)V
    //   1206: aload 31
    //   1208: ldc_w 822
    //   1211: lconst_1
    //   1212: invokevirtual 2064	android/os/Bundle:putLong	(Ljava/lang/String;J)V
    //   1215: aload 31
    //   1217: ldc_w 1455
    //   1220: aload_1
    //   1221: getfield 1166	com/google/android/gms/internal/zzciy:zzc	Ljava/lang/String;
    //   1224: invokevirtual 2069	android/os/Bundle:putString	(Ljava/lang/String;Ljava/lang/String;)V
    //   1227: aload_0
    //   1228: invokevirtual 380	com/google/android/gms/internal/zzckk:zzo	()Lcom/google/android/gms/internal/zzcnp;
    //   1231: aload 14
    //   1233: getfield 787	com/google/android/gms/internal/zzcof:zzo	Ljava/lang/String;
    //   1236: invokevirtual 585	com/google/android/gms/internal/zzcnp:zzi	(Ljava/lang/String;)Z
    //   1239: istore 33
    //   1241: iload 33
    //   1243: ifeq +35 -> 1278
    //   1246: aload_0
    //   1247: invokevirtual 380	com/google/android/gms/internal/zzckk:zzo	()Lcom/google/android/gms/internal/zzcnp;
    //   1250: aload 31
    //   1252: ldc_w 973
    //   1255: lconst_1
    //   1256: invokestatic 578	java/lang/Long:valueOf	(J)Ljava/lang/Long;
    //   1259: invokevirtual 1458	com/google/android/gms/internal/zzcnp:zza	(Landroid/os/Bundle;Ljava/lang/String;Ljava/lang/Object;)V
    //   1262: aload_0
    //   1263: invokevirtual 380	com/google/android/gms/internal/zzckk:zzo	()Lcom/google/android/gms/internal/zzcnp;
    //   1266: aload 31
    //   1268: ldc_w 822
    //   1271: lconst_1
    //   1272: invokestatic 578	java/lang/Long:valueOf	(J)Ljava/lang/Long;
    //   1275: invokevirtual 1458	com/google/android/gms/internal/zzcnp:zza	(Landroid/os/Bundle;Ljava/lang/String;Ljava/lang/Object;)V
    //   1278: aload_0
    //   1279: invokevirtual 649	com/google/android/gms/internal/zzckk:zzq	()Lcom/google/android/gms/internal/zzcim;
    //   1282: aload_2
    //   1283: aload_1
    //   1284: getfield 1120	com/google/android/gms/internal/zzciy:zza	Ljava/lang/String;
    //   1287: invokevirtual 958	com/google/android/gms/internal/zzcim:zza	(Ljava/lang/String;Ljava/lang/String;)Lcom/google/android/gms/internal/zzciu;
    //   1290: astore 34
    //   1292: aload 34
    //   1294: ifnonnull +54 -> 1348
    //   1297: aload_1
    //   1298: getfield 1120	com/google/android/gms/internal/zzciy:zza	Ljava/lang/String;
    //   1301: astore 69
    //   1303: aload_1
    //   1304: getfield 1464	com/google/android/gms/internal/zzciy:zzd	J
    //   1307: lstore 70
    //   1309: iload 28
    //   1311: istore 35
    //   1313: new 955	com/google/android/gms/internal/zzciu
    //   1316: dup
    //   1317: aload_2
    //   1318: aload 69
    //   1320: lconst_1
    //   1321: lconst_0
    //   1322: lload 70
    //   1324: lconst_0
    //   1325: aconst_null
    //   1326: aconst_null
    //   1327: aconst_null
    //   1328: invokespecial 985	com/google/android/gms/internal/zzciu:<init>	(Ljava/lang/String;Ljava/lang/String;JJJJLjava/lang/Long;Ljava/lang/Long;Ljava/lang/Boolean;)V
    //   1331: astore 72
    //   1333: aload_0
    //   1334: invokevirtual 649	com/google/android/gms/internal/zzckk:zzq	()Lcom/google/android/gms/internal/zzcim;
    //   1337: aload 72
    //   1339: invokevirtual 1038	com/google/android/gms/internal/zzcim:zza	(Lcom/google/android/gms/internal/zzciu;)V
    //   1342: lconst_0
    //   1343: lstore 36
    //   1345: goto +37 -> 1382
    //   1348: iload 28
    //   1350: istore 35
    //   1352: aload 34
    //   1354: getfield 1478	com/google/android/gms/internal/zzciu:zze	J
    //   1357: lstore 36
    //   1359: aload 34
    //   1361: aload_1
    //   1362: getfield 1464	com/google/android/gms/internal/zzciy:zzd	J
    //   1365: invokevirtual 1483	com/google/android/gms/internal/zzciu:zza	(J)Lcom/google/android/gms/internal/zzciu;
    //   1368: invokevirtual 2072	com/google/android/gms/internal/zzciu:zza	()Lcom/google/android/gms/internal/zzciu;
    //   1371: astore 38
    //   1373: aload_0
    //   1374: invokevirtual 649	com/google/android/gms/internal/zzckk:zzq	()Lcom/google/android/gms/internal/zzcim;
    //   1377: aload 38
    //   1379: invokevirtual 1038	com/google/android/gms/internal/zzcim:zza	(Lcom/google/android/gms/internal/zzciu;)V
    //   1382: aload_1
    //   1383: getfield 1166	com/google/android/gms/internal/zzciy:zzc	Ljava/lang/String;
    //   1386: astore 39
    //   1388: aload_1
    //   1389: getfield 1120	com/google/android/gms/internal/zzciy:zza	Ljava/lang/String;
    //   1392: astore 40
    //   1394: aload_1
    //   1395: getfield 1464	com/google/android/gms/internal/zzciy:zzd	J
    //   1398: lstore 41
    //   1400: aload 14
    //   1402: astore 43
    //   1404: iload 35
    //   1406: istore 44
    //   1408: lload 36
    //   1410: lstore 45
    //   1412: new 1466	com/google/android/gms/internal/zzcit
    //   1415: dup
    //   1416: aload_0
    //   1417: aload 39
    //   1419: aload_2
    //   1420: aload 40
    //   1422: lload 41
    //   1424: lload 45
    //   1426: aload 31
    //   1428: invokespecial 1469	com/google/android/gms/internal/zzcit:<init>	(Lcom/google/android/gms/internal/zzckk;Ljava/lang/String;Ljava/lang/String;Ljava/lang/String;JJLandroid/os/Bundle;)V
    //   1431: astore 47
    //   1433: new 625	com/google/android/gms/internal/zzcoc
    //   1436: dup
    //   1437: invokespecial 760	com/google/android/gms/internal/zzcoc:<init>	()V
    //   1440: astore 48
    //   1442: iload 44
    //   1444: anewarray 625	com/google/android/gms/internal/zzcoc
    //   1447: astore 49
    //   1449: aload 49
    //   1451: iconst_0
    //   1452: aload 48
    //   1454: aastore
    //   1455: aload 43
    //   1457: aload 49
    //   1459: putfield 785	com/google/android/gms/internal/zzcof:zzb	[Lcom/google/android/gms/internal/zzcoc;
    //   1462: aload 48
    //   1464: aload 47
    //   1466: getfield 1477	com/google/android/gms/internal/zzcit:zzc	J
    //   1469: invokestatic 578	java/lang/Long:valueOf	(J)Ljava/lang/Long;
    //   1472: putfield 762	com/google/android/gms/internal/zzcoc:zzc	Ljava/lang/Long;
    //   1475: aload 48
    //   1477: aload 47
    //   1479: getfield 1470	com/google/android/gms/internal/zzcit:zzb	Ljava/lang/String;
    //   1482: putfield 761	com/google/android/gms/internal/zzcoc:zzb	Ljava/lang/String;
    //   1485: aload 48
    //   1487: aload 47
    //   1489: getfield 2073	com/google/android/gms/internal/zzcit:zzd	J
    //   1492: invokestatic 578	java/lang/Long:valueOf	(J)Ljava/lang/Long;
    //   1495: putfield 2074	com/google/android/gms/internal/zzcoc:zzd	Ljava/lang/Long;
    //   1498: aload 48
    //   1500: aload 47
    //   1502: getfield 1632	com/google/android/gms/internal/zzcit:zze	Lcom/google/android/gms/internal/zzciv;
    //   1505: invokevirtual 2054	com/google/android/gms/internal/zzciv:zza	()I
    //   1508: anewarray 630	com/google/android/gms/internal/zzcod
    //   1511: putfield 628	com/google/android/gms/internal/zzcoc:zza	[Lcom/google/android/gms/internal/zzcod;
    //   1514: aload 47
    //   1516: getfield 1632	com/google/android/gms/internal/zzcit:zze	Lcom/google/android/gms/internal/zzciv;
    //   1519: invokevirtual 1633	com/google/android/gms/internal/zzciv:iterator	()Ljava/util/Iterator;
    //   1522: astore 50
    //   1524: iconst_0
    //   1525: istore 51
    //   1527: aload 50
    //   1529: invokeinterface 1027 1 0
    //   1534: ifeq +89 -> 1623
    //   1537: aload 50
    //   1539: invokeinterface 1030 1 0
    //   1544: checkcast 332	java/lang/String
    //   1547: astore 63
    //   1549: new 630	com/google/android/gms/internal/zzcod
    //   1552: dup
    //   1553: invokespecial 832	com/google/android/gms/internal/zzcod:<init>	()V
    //   1556: astore 64
    //   1558: aload 48
    //   1560: getfield 628	com/google/android/gms/internal/zzcoc:zza	[Lcom/google/android/gms/internal/zzcod;
    //   1563: astore 65
    //   1565: iload 51
    //   1567: iconst_1
    //   1568: iadd
    //   1569: istore 66
    //   1571: aload 65
    //   1573: iload 51
    //   1575: aload 64
    //   1577: aastore
    //   1578: aload 64
    //   1580: aload 63
    //   1582: putfield 632	com/google/android/gms/internal/zzcod:zza	Ljava/lang/String;
    //   1585: aload 47
    //   1587: getfield 1632	com/google/android/gms/internal/zzcit:zze	Lcom/google/android/gms/internal/zzciv;
    //   1590: aload 63
    //   1592: invokevirtual 2075	com/google/android/gms/internal/zzciv:zza	(Ljava/lang/String;)Ljava/lang/Object;
    //   1595: astore 67
    //   1597: aload 43
    //   1599: astore 68
    //   1601: aload_0
    //   1602: invokevirtual 380	com/google/android/gms/internal/zzckk:zzo	()Lcom/google/android/gms/internal/zzcnp;
    //   1605: aload 64
    //   1607: aload 67
    //   1609: invokevirtual 2078	com/google/android/gms/internal/zzcnp:zza	(Lcom/google/android/gms/internal/zzcod;Ljava/lang/Object;)V
    //   1612: aload 68
    //   1614: astore 43
    //   1616: iload 66
    //   1618: istore 51
    //   1620: goto -93 -> 1527
    //   1623: aload 43
    //   1625: astore 52
    //   1627: aload 52
    //   1629: aload_0
    //   1630: aload 27
    //   1632: invokevirtual 408	com/google/android/gms/internal/zzcif:zzb	()Ljava/lang/String;
    //   1635: aload 52
    //   1637: getfield 913	com/google/android/gms/internal/zzcof:zzc	[Lcom/google/android/gms/internal/zzcoh;
    //   1640: aload 52
    //   1642: getfield 785	com/google/android/gms/internal/zzcof:zzb	[Lcom/google/android/gms/internal/zzcoc;
    //   1645: invokespecial 922	com/google/android/gms/internal/zzckk:zza	(Ljava/lang/String;[Lcom/google/android/gms/internal/zzcoh;[Lcom/google/android/gms/internal/zzcoc;)[Lcom/google/android/gms/internal/zzcob;
    //   1648: putfield 925	com/google/android/gms/internal/zzcof:zzaa	[Lcom/google/android/gms/internal/zzcob;
    //   1651: aload 52
    //   1653: aload 48
    //   1655: getfield 762	com/google/android/gms/internal/zzcoc:zzc	Ljava/lang/Long;
    //   1658: putfield 1042	com/google/android/gms/internal/zzcof:zze	Ljava/lang/Long;
    //   1661: aload 52
    //   1663: aload 48
    //   1665: getfield 762	com/google/android/gms/internal/zzcoc:zzc	Ljava/lang/Long;
    //   1668: putfield 1046	com/google/android/gms/internal/zzcof:zzf	Ljava/lang/Long;
    //   1671: aload 27
    //   1673: invokevirtual 1053	com/google/android/gms/internal/zzcif:zzh	()J
    //   1676: lstore 53
    //   1678: lload 53
    //   1680: lconst_0
    //   1681: lcmp
    //   1682: ifeq +281 -> 1963
    //   1685: lload 53
    //   1687: invokestatic 578	java/lang/Long:valueOf	(J)Ljava/lang/Long;
    //   1690: astore 55
    //   1692: goto +3 -> 1695
    //   1695: aload 52
    //   1697: aload 55
    //   1699: putfield 1054	com/google/android/gms/internal/zzcof:zzh	Ljava/lang/Long;
    //   1702: aload 27
    //   1704: invokevirtual 1056	com/google/android/gms/internal/zzcif:zzg	()J
    //   1707: lstore 56
    //   1709: lload 56
    //   1711: lconst_0
    //   1712: lcmp
    //   1713: ifne +256 -> 1969
    //   1716: goto +3 -> 1719
    //   1719: lload 53
    //   1721: lconst_0
    //   1722: lcmp
    //   1723: ifeq +253 -> 1976
    //   1726: lload 53
    //   1728: invokestatic 578	java/lang/Long:valueOf	(J)Ljava/lang/Long;
    //   1731: astore 58
    //   1733: goto +3 -> 1736
    //   1736: aload 52
    //   1738: aload 58
    //   1740: putfield 1057	com/google/android/gms/internal/zzcof:zzg	Ljava/lang/Long;
    //   1743: aload 27
    //   1745: invokevirtual 1059	com/google/android/gms/internal/zzcif:zzr	()V
    //   1748: aload 52
    //   1750: aload 27
    //   1752: invokevirtual 1061	com/google/android/gms/internal/zzcif:zzo	()J
    //   1755: l2i
    //   1756: invokestatic 285	java/lang/Integer:valueOf	(I)Ljava/lang/Integer;
    //   1759: putfield 1064	com/google/android/gms/internal/zzcof:zzw	Ljava/lang/Integer;
    //   1762: aload 52
    //   1764: ldc2_w 376
    //   1767: invokestatic 578	java/lang/Long:valueOf	(J)Ljava/lang/Long;
    //   1770: putfield 1575	com/google/android/gms/internal/zzcof:zzr	Ljava/lang/Long;
    //   1773: aload 52
    //   1775: aload_0
    //   1776: getfield 108	com/google/android/gms/internal/zzckk:zzn	Lcom/google/android/gms/common/util/zze;
    //   1779: invokeinterface 113 1 0
    //   1784: invokestatic 578	java/lang/Long:valueOf	(J)Ljava/lang/Long;
    //   1787: putfield 1576	com/google/android/gms/internal/zzcof:zzd	Ljava/lang/Long;
    //   1790: aload 52
    //   1792: getstatic 2081	java/lang/Boolean:TRUE	Ljava/lang/Boolean;
    //   1795: putfield 1967	com/google/android/gms/internal/zzcof:zzz	Ljava/lang/Boolean;
    //   1798: aload 27
    //   1800: aload 52
    //   1802: getfield 1042	com/google/android/gms/internal/zzcof:zze	Ljava/lang/Long;
    //   1805: invokevirtual 884	java/lang/Long:longValue	()J
    //   1808: invokevirtual 1067	com/google/android/gms/internal/zzcif:zza	(J)V
    //   1811: aload 27
    //   1813: aload 52
    //   1815: getfield 1046	com/google/android/gms/internal/zzcof:zzf	Ljava/lang/Long;
    //   1818: invokevirtual 884	java/lang/Long:longValue	()J
    //   1821: invokevirtual 1069	com/google/android/gms/internal/zzcif:zzb	(J)V
    //   1824: aload_0
    //   1825: invokevirtual 649	com/google/android/gms/internal/zzckk:zzq	()Lcom/google/android/gms/internal/zzcim;
    //   1828: aload 27
    //   1830: invokevirtual 1074	com/google/android/gms/internal/zzcim:zza	(Lcom/google/android/gms/internal/zzcif;)V
    //   1833: aload_0
    //   1834: invokevirtual 649	com/google/android/gms/internal/zzckk:zzq	()Lcom/google/android/gms/internal/zzcim;
    //   1837: invokevirtual 1101	com/google/android/gms/internal/zzcim:zzy	()V
    //   1840: aload_0
    //   1841: invokevirtual 649	com/google/android/gms/internal/zzckk:zzq	()Lcom/google/android/gms/internal/zzcim;
    //   1844: invokevirtual 1103	com/google/android/gms/internal/zzcim:zzz	()V
    //   1847: aload 26
    //   1849: invokevirtual 2083	com/google/android/gms/internal/zzeue:zzf	()I
    //   1852: newarray byte
    //   1854: astore 60
    //   1856: aload 60
    //   1858: iconst_0
    //   1859: aload 60
    //   1861: arraylength
    //   1862: invokestatic 2088	com/google/android/gms/internal/zzetw:zza	([BII)Lcom/google/android/gms/internal/zzetw;
    //   1865: astore 61
    //   1867: aload 26
    //   1869: aload 61
    //   1871: invokevirtual 2091	com/google/android/gms/internal/zzeue:zza	(Lcom/google/android/gms/internal/zzetw;)V
    //   1874: aload 61
    //   1876: invokevirtual 2092	com/google/android/gms/internal/zzetw:zza	()V
    //   1879: aload_0
    //   1880: invokevirtual 380	com/google/android/gms/internal/zzckk:zzo	()Lcom/google/android/gms/internal/zzcnp;
    //   1883: aload 60
    //   1885: invokevirtual 2095	com/google/android/gms/internal/zzcnp:zza	([B)[B
    //   1888: astore 62
    //   1890: aload 62
    //   1892: areturn
    //   1893: astore 59
    //   1895: aload_0
    //   1896: invokevirtual 232	com/google/android/gms/internal/zzckk:zzf	()Lcom/google/android/gms/internal/zzcjk;
    //   1899: invokevirtual 298	com/google/android/gms/internal/zzcjk:zzy	()Lcom/google/android/gms/internal/zzcjm;
    //   1902: ldc_w 2097
    //   1905: aload_2
    //   1906: invokestatic 326	com/google/android/gms/internal/zzcjk:zza	(Ljava/lang/String;)Ljava/lang/Object;
    //   1909: aload 59
    //   1911: invokevirtual 391	com/google/android/gms/internal/zzcjm:zza	(Ljava/lang/String;Ljava/lang/Object;Ljava/lang/Object;)V
    //   1914: aconst_null
    //   1915: areturn
    //   1916: astore 6
    //   1918: goto +10 -> 1928
    //   1921: astore 6
    //   1923: goto +5 -> 1928
    //   1926: astore 6
    //   1928: aload 6
    //   1930: astore 7
    //   1932: aload_0
    //   1933: invokevirtual 649	com/google/android/gms/internal/zzckk:zzq	()Lcom/google/android/gms/internal/zzcim;
    //   1936: invokevirtual 1103	com/google/android/gms/internal/zzcim:zzz	()V
    //   1939: aload 7
    //   1941: athrow
    //   1942: aload 82
    //   1944: astore 22
    //   1946: goto -1111 -> 835
    //   1949: iinc 23 1
    //   1952: aload 80
    //   1954: astore 5
    //   1956: aload 81
    //   1958: astore 8
    //   1960: goto -1119 -> 841
    //   1963: aconst_null
    //   1964: astore 55
    //   1966: goto -271 -> 1695
    //   1969: lload 56
    //   1971: lstore 53
    //   1973: goto -254 -> 1719
    //   1976: aconst_null
    //   1977: astore 58
    //   1979: goto -243 -> 1736
    // Local variable table:
    //   start	length	slot	name	signature
    //   0	1982	0	this	zzckk
    //   0	1982	1	paramZzciy	zzciy
    //   0	1982	2	paramString	String
    //   31	1924	5	localObject1	Object
    //   1916	1	6	localObject2	Object
    //   1921	1	6	localObject3	Object
    //   1926	3	6	localObject4	Object
    //   88	1852	7	localObject5	Object
    //   48	1911	8	localObject6	Object
    //   98	3	9	bool1	boolean
    //   132	3	10	bool2	boolean
    //   162	3	11	bool3	boolean
    //   194	826	12	bool4	boolean
    //   200	935	13	localLong1	Long
    //   330	1071	14	localZzcof	zzcof
    //   398	18	15	l1	long
    //   410	16	17	localInteger	Integer
    //   470	3	18	bool5	boolean
    //   516	49	19	localPair	Pair
    //   523	3	20	bool6	boolean
    //   665	273	21	localList	List
    //   789	1156	22	localObject7	Object
    //   836	1114	23	i	int
    //   839	186	24	localObject8	Object
    //   848	7	25	j	int
    //   1013	855	26	localObject9	Object
    //   1017	812	27	localObject10	Object
    //   1116	233	28	k	int
    //   1139	3	29	l2	long
    //   1165	262	31	localBundle	Bundle
    //   1177	3	32	bool7	boolean
    //   1239	3	33	bool8	boolean
    //   1290	70	34	localZzciu1	zzciu
    //   1311	94	35	m	int
    //   1343	66	36	l3	long
    //   1371	7	38	localZzciu2	zzciu
    //   1386	32	39	str1	String
    //   1392	29	40	str2	String
    //   1398	25	41	l4	long
    //   1402	222	43	localObject11	Object
    //   1406	37	44	n	int
    //   1410	15	45	l5	long
    //   1431	155	47	localZzcit	zzcit
    //   1440	224	48	localZzcoc	zzcoc
    //   1447	11	49	arrayOfZzcoc	zzcoc[]
    //   1522	16	50	localIterator	Iterator
    //   1525	94	51	i1	int
    //   1625	189	52	localObject12	Object
    //   1676	296	53	l6	long
    //   1690	275	55	localLong2	Long
    //   1707	263	56	l7	long
    //   1731	247	58	localLong3	Long
    //   1893	17	59	localIOException	IOException
    //   1854	30	60	arrayOfByte1	byte[]
    //   1865	10	61	localZzetw	zzetw
    //   1888	3	62	arrayOfByte2	byte[]
    //   1547	44	63	str3	String
    //   1556	50	64	localZzcod	zzcod
    //   1563	9	65	arrayOfZzcod	zzcod[]
    //   1569	48	66	i2	int
    //   1595	13	67	localObject13	Object
    //   1599	14	68	localObject14	Object
    //   1301	18	69	str4	String
    //   1307	16	70	l8	long
    //   1331	7	72	localZzciu3	zzciu
    //   84	3	73	localObject15	Object
    //   1036	90	75	localZzcoh1	zzcoh
    //   1105	14	76	arrayOfZzcoh	zzcoh[]
    //   1113	12	77	i3	int
    //   864	141	78	localZzcoh2	zzcoh
    //   908	13	79	localZzcno1	zzcno
    //   912	1041	80	localObject16	Object
    //   916	1041	81	localObject17	Object
    //   702	1241	82	localZzcno2	zzcno
    //   823	3	83	localZzcno3	zzcno
    //   735	40	84	str5	String
    //   746	37	85	l9	long
    //   768	17	87	localLong4	Long
    //   260	48	88	localZzcjm	zzcjm
    //   265	48	89	str6	String
    //   271	48	90	localObject18	Object
    //   149	3	91	bool9	boolean
    //   72	10	92	arrayOfByte3	byte[]
    // Exception table:
    //   from	to	target	type
    //   55	69	84	finally
    //   69	74	84	finally
    //   105	119	84	finally
    //   139	151	84	finally
    //   169	186	84	finally
    //   207	237	84	finally
    //   240	262	84	finally
    //   267	273	84	finally
    //   273	282	84	finally
    //   285	297	84	finally
    //   300	309	84	finally
    //   314	320	84	finally
    //   477	504	84	finally
    //   535	575	84	finally
    //   687	704	84	finally
    //   709	717	84	finally
    //   720	791	84	finally
    //   794	825	84	finally
    //   857	910	84	finally
    //   918	955	84	finally
    //   960	1004	84	finally
    //   1029	1115	84	finally
    //   1118	1128	84	finally
    //   1148	1158	84	finally
    //   1184	1215	84	finally
    //   1246	1278	84	finally
    //   1297	1309	84	finally
    //   1313	1342	84	finally
    //   1847	1890	1893	java/io/IOException
    //   1601	1612	1916	finally
    //   1627	1678	1916	finally
    //   1685	1692	1916	finally
    //   1695	1709	1916	finally
    //   1726	1733	1916	finally
    //   1736	1840	1916	finally
    //   1412	1524	1921	finally
    //   1527	1565	1921	finally
    //   1571	1597	1921	finally
    //   40	50	1926	finally
    //   93	100	1926	finally
    //   122	134	1926	finally
    //   156	164	1926	finally
    //   186	202	1926	finally
    //   323	400	1926	finally
    //   415	423	1926	finally
    //   423	472	1926	finally
    //   504	525	1926	finally
    //   575	682	1926	finally
    //   841	850	1926	finally
    //   1134	1141	1926	finally
    //   1158	1179	1926	finally
    //   1215	1241	1926	finally
    //   1278	1292	1926	finally
    //   1352	1382	1926	finally
    //   1382	1400	1926	finally
  }
  
  protected final void zzc()
  {
    zzh().zzc();
    zzq().zzad();
    if (zze().zzc.zza() == 0L) {
      zze().zzc.zza(this.zzn.zza());
    }
    if (Long.valueOf(zze().zzh.zza()).longValue() == 0L)
    {
      zzf().zzae().zza("Persisting first open", Long.valueOf(this.zzao));
      zze().zzh.zza(this.zzao);
    }
    if (!zzb())
    {
      if (zzab())
      {
        if (!zzo().zzg("android.permission.INTERNET")) {
          zzf().zzy().zza("App is missing INTERNET permission");
        }
        if (!zzo().zzg("android.permission.ACCESS_NETWORK_STATE")) {
          zzf().zzy().zza("App is missing ACCESS_NETWORK_STATE permission");
        }
        if (!zzbii.zza(this.zzb).zza())
        {
          if (!zzckb.zza(this.zzb)) {
            zzf().zzy().zza("AppMeasurementReceiver not registered/enabled");
          }
          if (!zzcmz.zza(this.zzb, false)) {
            zzf().zzy().zza("AppMeasurementService not registered/enabled");
          }
        }
        zzf().zzy().zza("Uploading is not possible. App measurement disabled");
      }
    }
    else
    {
      if (!TextUtils.isEmpty(zzy().zzaa()))
      {
        String str2 = zze().zzy();
        if (str2 == null)
        {
          zze().zzc(zzy().zzaa());
        }
        else if (!str2.equals(zzy().zzaa()))
        {
          zzf().zzac().zza("Rechecking which service to use due to a GMP App Id change");
          zze().zzab();
          this.zzt.zzae();
          this.zzt.zzac();
          zze().zzc(zzy().zzaa());
          zze().zzh.zza(this.zzao);
          zze().zzi.zza(null);
        }
      }
      zzl().zza(zze().zzi.zza());
      if (!TextUtils.isEmpty(zzy().zzaa()))
      {
        zzcll localZzcll = zzl();
        localZzcll.zzc();
        localZzcll.zzaq();
        if (localZzcll.zzp.zzb())
        {
          localZzcll.zzi().zzab();
          String str1 = localZzcll.zzu().zzac();
          if (!TextUtils.isEmpty(str1))
          {
            localZzcll.zzh().zzaq();
            if (!str1.equals(Build.VERSION.RELEASE))
            {
              Bundle localBundle = new Bundle();
              localBundle.putString("_po", str1);
              localZzcll.zza("auto", "_ou", localBundle);
            }
          }
        }
        zzw().zza(new AtomicReference());
      }
    }
    zzam();
  }
  
  public final void zzc(zzcig paramZzcig)
  {
    zzh().zzc();
    zza();
    zzbq.zza(paramZzcig);
    zzbq.zza(paramZzcig.zza);
    if (TextUtils.isEmpty(paramZzcig.zzb)) {
      return;
    }
    zzcif localZzcif1 = zzq().zzb(paramZzcig.zza);
    if ((localZzcif1 != null) && (TextUtils.isEmpty(localZzcif1.zzd())) && (!TextUtils.isEmpty(paramZzcig.zzb)))
    {
      localZzcif1.zzg(0L);
      zzq().zza(localZzcif1);
      zzj().zzd(paramZzcig.zza);
    }
    if (!paramZzcig.zzh)
    {
      zzd(paramZzcig);
      return;
    }
    long l1 = paramZzcig.zzm;
    if (l1 == 0L) {
      l1 = this.zzn.zza();
    }
    int i = paramZzcig.zzn;
    if ((i != 0) && (i != 1))
    {
      zzf().zzaa().zza("Incorrect app type, assuming installed app. appId, appType", zzcjk.zza(paramZzcig.zza), Integer.valueOf(i));
      i = 0;
    }
    zzq().zzx();
    for (;;)
    {
      try
      {
        localZzcif2 = zzq().zzb(paramZzcig.zza);
        if ((localZzcif2 != null) && (localZzcif2.zzd() != null) && (!localZzcif2.zzd().equals(paramZzcig.zzb)))
        {
          zzf().zzaa().zza("New GMP App Id passed in. Removing cached database data. appId", zzcjk.zza(localZzcif2.zzb()));
          zzcim localZzcim3 = zzq();
          String str4 = localZzcif2.zzb();
          localZzcim3.zzaq();
          localZzcim3.zzc();
          zzbq.zza(str4);
          try
          {
            SQLiteDatabase localSQLiteDatabase = localZzcim3.zzaa();
            String[] arrayOfString = { str4 };
            int k = 0 + localSQLiteDatabase.delete("events", "app_id=?", arrayOfString) + localSQLiteDatabase.delete("user_attributes", "app_id=?", arrayOfString) + localSQLiteDatabase.delete("conditional_properties", "app_id=?", arrayOfString) + localSQLiteDatabase.delete("apps", "app_id=?", arrayOfString) + localSQLiteDatabase.delete("raw_events", "app_id=?", arrayOfString) + localSQLiteDatabase.delete("raw_events_metadata", "app_id=?", arrayOfString) + localSQLiteDatabase.delete("event_filters", "app_id=?", arrayOfString) + localSQLiteDatabase.delete("property_filters", "app_id=?", arrayOfString) + localSQLiteDatabase.delete("audience_filter_values", "app_id=?", arrayOfString);
            if (k <= 0) {
              break label1470;
            }
            localZzcim3.zzt().zzae().zza("Deleted application data. app, records", str4, Integer.valueOf(k));
          }
          catch (SQLiteException localSQLiteException)
          {
            localZzcim3.zzt().zzy().zza("Error deleting application data. appId, error", zzcjk.zza(str4), localSQLiteException);
          }
        }
        else
        {
          if (localZzcif2 != null)
          {
            zzciy localZzciy3;
            if (localZzcif2.zzj() != -2147483648L)
            {
              if (localZzcif2.zzj() != paramZzcig.zzj)
              {
                Bundle localBundle6 = new Bundle();
                localBundle6.putString("_pv", localZzcif2.zzi());
                zzciv localZzciv6 = new zzciv(localBundle6);
                localZzciy3 = new zzciy("_au", localZzciv6, "auto", l1);
                zza(localZzciy3, paramZzcig);
              }
            }
            else if ((localZzcif2.zzi() != null) && (!localZzcif2.zzi().equals(paramZzcig.zzc)))
            {
              Bundle localBundle5 = new Bundle();
              localBundle5.putString("_pv", localZzcif2.zzi());
              zzciv localZzciv5 = new zzciv(localBundle5);
              localZzciy3 = new zzciy("_au", localZzciv5, "auto", l1);
              continue;
            }
          }
          zzd(paramZzcig);
          zzcim localZzcim1;
          String str1;
          String str2;
          if (i == 0)
          {
            localZzcim1 = zzq();
            str1 = paramZzcig.zza;
            str2 = "_f";
            localZzciu = localZzcim1.zza(str1, str2);
          }
          else
          {
            if (i != 1) {
              break label1476;
            }
            localZzcim1 = zzq();
            str1 = paramZzcig.zza;
            str2 = "_v";
            continue;
          }
          zzciy localZzciy2;
          if (localZzciu == null)
          {
            long l2 = 3600000L * (1L + l1 / 3600000L);
            long l4;
            zzciy localZzciy1;
            if (i == 0)
            {
              Long localLong1 = Long.valueOf(l2);
              long l3 = l1;
              l4 = 1L;
              zzcnm localZzcnm1 = new zzcnm("_fot", l3, localLong1, "auto");
              zza(localZzcnm1, paramZzcig);
              zzh().zzc();
              zza();
              Bundle localBundle1 = new Bundle();
              localBundle1.putLong("_c", l4);
              localBundle1.putLong("_r", l4);
              localBundle1.putLong("_uwa", 0L);
              localBundle1.putLong("_pfo", 0L);
              localBundle1.putLong("_sys", 0L);
              localBundle1.putLong("_sysu", 0L);
              if (this.zzb.getPackageManager() == null)
              {
                zzf().zzy().zza("PackageManager is null, first open report might be inaccurate. appId", zzcjk.zza(paramZzcig.zza));
              }
              else
              {
                PackageInfo localPackageInfo;
                try
                {
                  localPackageInfo = zzbii.zza(this.zzb).zzb(paramZzcig.zza, 0);
                }
                catch (PackageManager.NameNotFoundException localNameNotFoundException1)
                {
                  zzf().zzy().zza("Package info is null, first open report might be inaccurate. appId", zzcjk.zza(paramZzcig.zza), localNameNotFoundException1);
                  localPackageInfo = null;
                }
                if ((localPackageInfo != null) && (localPackageInfo.firstInstallTime != 0L))
                {
                  if (localPackageInfo.firstInstallTime == localPackageInfo.lastUpdateTime) {
                    break label1482;
                  }
                  localBundle1.putLong("_uwa", l4);
                  j = 0;
                  if (j == 0) {
                    break label1488;
                  }
                  l6 = l4;
                  Long localLong2 = Long.valueOf(l6);
                  zzcnm localZzcnm2 = new zzcnm("_fi", l1, localLong2, "auto");
                  zza(localZzcnm2, paramZzcig);
                }
                ApplicationInfo localApplicationInfo;
                try
                {
                  localApplicationInfo = zzbii.zza(this.zzb).zza(paramZzcig.zza, 0);
                }
                catch (PackageManager.NameNotFoundException localNameNotFoundException2)
                {
                  zzf().zzy().zza("Application info is null, first open report might be inaccurate. appId", zzcjk.zza(paramZzcig.zza), localNameNotFoundException2);
                  localApplicationInfo = null;
                }
                if (localApplicationInfo != null)
                {
                  if ((0x1 & localApplicationInfo.flags) != 0) {
                    localBundle1.putLong("_sys", l4);
                  }
                  if ((0x80 & localApplicationInfo.flags) != 0) {
                    localBundle1.putLong("_sysu", l4);
                  }
                }
              }
              zzcim localZzcim2 = zzq();
              String str3 = paramZzcig.zza;
              zzbq.zza(str3);
              localZzcim2.zzc();
              localZzcim2.zzaq();
              long l5 = localZzcim2.zzh(str3, "first_open_count");
              if (l5 >= 0L) {
                localBundle1.putLong("_pfo", l5);
              }
              zzciv localZzciv1 = new zzciv(localBundle1);
              localZzciy1 = new zzciy("_f", localZzciv1, "auto", l1);
              zza(localZzciy1, paramZzcig);
            }
            else
            {
              l4 = 1L;
              if (i == 1)
              {
                Long localLong3 = Long.valueOf(l2);
                zzcnm localZzcnm3 = new zzcnm("_fvt", l1, localLong3, "auto");
                zza(localZzcnm3, paramZzcig);
                zzh().zzc();
                zza();
                Bundle localBundle3 = new Bundle();
                localBundle3.putLong("_c", l4);
                localBundle3.putLong("_r", l4);
                zzciv localZzciv3 = new zzciv(localBundle3);
                localZzciy1 = new zzciy("_v", localZzciv3, "auto", l1);
                continue;
              }
            }
            Bundle localBundle2 = new Bundle();
            localBundle2.putLong("_et", l4);
            zzciv localZzciv2 = new zzciv(localBundle2);
            localZzciy2 = new zzciy("_e", localZzciv2, "auto", l1);
            zza(localZzciy2, paramZzcig);
          }
          else if (paramZzcig.zzi)
          {
            Bundle localBundle4 = new Bundle();
            zzciv localZzciv4 = new zzciv(localBundle4);
            localZzciy2 = new zzciy("_cd", localZzciv4, "auto", l1);
            continue;
          }
          zzq().zzy();
          return;
        }
      }
      finally
      {
        zzq().zzz();
      }
      label1470:
      zzcif localZzcif2 = null;
      continue;
      label1476:
      zzciu localZzciu = null;
      continue;
      label1482:
      int j = 1;
      continue;
      label1488:
      long l6 = 0L;
    }
  }
  
  public final zzcil zzd()
  {
    return this.zzc;
  }
  
  public final zzcjv zze()
  {
    zza(this.zzd);
    return this.zzd;
  }
  
  public final zzcjk zzf()
  {
    zzb(this.zze);
    return this.zze;
  }
  
  public final zzcjk zzg()
  {
    if ((this.zze != null) && (this.zze.zzap())) {
      return this.zze;
    }
    return null;
  }
  
  public final zzckf zzh()
  {
    zzb(this.zzf);
    return this.zzf;
  }
  
  public final zzcne zzi()
  {
    zzb(this.zzg);
    return this.zzg;
  }
  
  public final zzcke zzj()
  {
    zzb(this.zzh);
    return this.zzh;
  }
  
  final zzckf zzk()
  {
    return this.zzf;
  }
  
  public final zzcll zzl()
  {
    zzb(this.zzp);
    return this.zzp;
  }
  
  public final AppMeasurement zzm()
  {
    return this.zzi;
  }
  
  public final FirebaseAnalytics zzn()
  {
    return this.zzj;
  }
  
  public final zzcnp zzo()
  {
    zza(this.zzk);
    return this.zzk;
  }
  
  public final zzcji zzp()
  {
    zza(this.zzl);
    return this.zzl;
  }
  
  public final zzcim zzq()
  {
    zzb(this.zzr);
    return this.zzr;
  }
  
  public final zzcjg zzr()
  {
    zzb(this.zzs);
    return this.zzs;
  }
  
  public final zzcjo zzs()
  {
    zzb(this.zzm);
    return this.zzm;
  }
  
  public final Context zzt()
  {
    return this.zzb;
  }
  
  public final zze zzu()
  {
    return this.zzn;
  }
  
  public final zzcmb zzv()
  {
    zzb(this.zzo);
    return this.zzo;
  }
  
  public final zzcmf zzw()
  {
    zzb(this.zzt);
    return this.zzt;
  }
  
  public final zzcis zzx()
  {
    zzb(this.zzu);
    return this.zzu;
  }
  
  public final zzcjf zzy()
  {
    zzb(this.zzv);
    return this.zzv;
  }
  
  public final zzcii zzz()
  {
    zzb(this.zzy);
    return this.zzy;
  }
}
