package com.db.pwcc.dbmobile.transfer.inputscreen.activities;

import android.app.Activity;
import android.content.Context;
import android.content.Intent;
import android.content.res.Resources;
import android.view.View;
import android.widget.TextView;
import com.db.pwcc.dbmobile.foundation.views.toolbar.DbToolbar;
import com.db.pwcc.dbmobile.foundation.widgets.UserAvatar;
import com.db.pwcc.dbmobile.model.sepa.SepaTransaction;
import com.db.pwcc.dbmobile.model.sepa.TransactionResponse;
import com.db.pwcc.dbmobile.model.tan.Authorization;
import com.db.pwcc.dbmobile.model.tan.AuthorizationStatus;
import com.db.pwcc.dbmobile.tan.ui.TanModule;
import com.db.pwcc.dbmobile.transfer.R.id;
import com.db.pwcc.dbmobile.transfer.R.layout;
import com.db.pwcc.dbmobile.transfer.R.string;
import java.lang.reflect.InvocationTargetException;
import java.lang.reflect.Method;
import java.math.BigDecimal;
import java.util.Currency;
import java.util.Locale;
import uuuuuu.hhhpph;
import uuuuuu.llkklk.lkkklk;
import uuuuuu.mbmbbb;
import uuuuuu.nnnntn;
import uuuuuu.oononn;
import uuuuuu.ppphhp;
import uuuuuu.pqpppq;
import uuuuuu.tnntnt.tttnnt;
import uuuuuu.vvrvrv;
import xxxxxx.uxxxxx;

public class SepaConfirmationActivity
  extends ConfirmationActivity
  implements tnntnt.tttnnt
{
  private static final String TAG = SepaConfirmationActivity.class.getSimpleName();
  public static int b00740074ttttt0074t = 28;
  public static int b0074tttttt0074t = 1;
  public static int bt0074ttttt0074t = 2;
  public static int bttttttt0074t;
  private boolean isSubaccountTransfer = false;
  private nnnntn presenter = null;
  private SepaTransaction transactionReceived = null;
  
  static
  {
    if ((b00740074ttttt0074t + b0074tttttt0074t) * b00740074ttttt0074t % bt0074ttttt0074t != bttttttt0074t)
    {
      b00740074ttttt0074t = 30;
      bttttttt0074t = 86;
      int j = b00740074ttttt0074t;
      switch (j * (j + btt0074tttt0074t()) % bt0074ttttt0074t)
      {
      default: 
        b00740074ttttt0074t = b0074007400740074007400740074tt();
        bttttttt0074t = 81;
      }
    }
    if ((b0074007400740074007400740074tt() + b0074tttttt0074t) * b0074007400740074007400740074tt() % bt0074ttttt0074t != bttttttt0074t)
    {
      int i = b00740074ttttt0074t;
      switch (i * (i + b0074tttttt0074t) % bt0074ttttt0074t)
      {
      default: 
        b00740074ttttt0074t = 60;
        bttttttt0074t = 97;
      }
      bttttttt0074t = 84;
    }
  }
  
  public SepaConfirmationActivity() {}
  
  public static int b0074007400740074007400740074tt()
  {
    return 13;
  }
  
  public static int b0074t0074tttt0074t()
  {
    return 2;
  }
  
  public static int bt00740074tttt0074t()
  {
    return 0;
  }
  
  public static int btt0074tttt0074t()
  {
    return 1;
  }
  
  public static Intent makeIntent(Context paramContext, String paramString1, boolean paramBoolean1, Authorization paramAuthorization, AuthorizationStatus paramAuthorizationStatus, String paramString2, boolean paramBoolean2, long paramLong)
  {
    if ((b00740074ttttt0074t + b0074tttttt0074t) * b00740074ttttt0074t % bt0074ttttt0074t != bttttttt0074t)
    {
      b00740074ttttt0074t = 7;
      bttttttt0074t = 60;
    }
    int i = b00740074ttttt0074t;
    int j = b0074tttttt0074t;
    int k = b00740074ttttt0074t;
    switch (k * (k + btt0074tttt0074t()) % b0074t0074tttt0074t())
    {
    default: 
      b00740074ttttt0074t = b0074007400740074007400740074tt();
      bttttttt0074t = b0074007400740074007400740074tt();
      if ((b00740074ttttt0074t + b0074tttttt0074t) * b00740074ttttt0074t % bt0074ttttt0074t != bttttttt0074t)
      {
        b00740074ttttt0074t = 98;
        bttttttt0074t = 49;
      }
      break;
    }
    switch (i * (j + i) % bt0074ttttt0074t)
    {
    default: 
      b00740074ttttt0074t = 37;
      bttttttt0074t = b0074007400740074007400740074tt();
    }
    return makeIntent(paramContext, paramString1, paramBoolean1, paramAuthorization, paramAuthorizationStatus, paramString2, paramBoolean2, paramLong, null);
  }
  
  /* Error */
  public static Intent makeIntent(Context paramContext, String paramString1, boolean paramBoolean1, Authorization paramAuthorization, AuthorizationStatus paramAuthorizationStatus, String paramString2, boolean paramBoolean2, long paramLong, String paramString3)
  {
    // Byte code:
    //   0: new 69	android/content/Intent
    //   3: dup
    //   4: aload_0
    //   5: ldc 2
    //   7: invokespecial 72	android/content/Intent:<init>	(Landroid/content/Context;Ljava/lang/Class;)V
    //   10: astore 10
    //   12: getstatic 26	com/db/pwcc/dbmobile/transfer/inputscreen/activities/SepaConfirmationActivity:b00740074ttttt0074t	I
    //   15: invokestatic 36	com/db/pwcc/dbmobile/transfer/inputscreen/activities/SepaConfirmationActivity:btt0074tttt0074t	()I
    //   18: iadd
    //   19: getstatic 26	com/db/pwcc/dbmobile/transfer/inputscreen/activities/SepaConfirmationActivity:b00740074ttttt0074t	I
    //   22: imul
    //   23: getstatic 30	com/db/pwcc/dbmobile/transfer/inputscreen/activities/SepaConfirmationActivity:bt0074ttttt0074t	I
    //   26: irem
    //   27: invokestatic 74	com/db/pwcc/dbmobile/transfer/inputscreen/activities/SepaConfirmationActivity:bt00740074tttt0074t	()I
    //   30: if_icmpeq +47 -> 77
    //   33: invokestatic 39	com/db/pwcc/dbmobile/transfer/inputscreen/activities/SepaConfirmationActivity:b0074007400740074007400740074tt	()I
    //   36: putstatic 26	com/db/pwcc/dbmobile/transfer/inputscreen/activities/SepaConfirmationActivity:b00740074ttttt0074t	I
    //   39: invokestatic 39	com/db/pwcc/dbmobile/transfer/inputscreen/activities/SepaConfirmationActivity:b0074007400740074007400740074tt	()I
    //   42: putstatic 32	com/db/pwcc/dbmobile/transfer/inputscreen/activities/SepaConfirmationActivity:bttttttt0074t	I
    //   45: getstatic 26	com/db/pwcc/dbmobile/transfer/inputscreen/activities/SepaConfirmationActivity:b00740074ttttt0074t	I
    //   48: getstatic 28	com/db/pwcc/dbmobile/transfer/inputscreen/activities/SepaConfirmationActivity:b0074tttttt0074t	I
    //   51: iadd
    //   52: getstatic 26	com/db/pwcc/dbmobile/transfer/inputscreen/activities/SepaConfirmationActivity:b00740074ttttt0074t	I
    //   55: imul
    //   56: getstatic 30	com/db/pwcc/dbmobile/transfer/inputscreen/activities/SepaConfirmationActivity:bt0074ttttt0074t	I
    //   59: irem
    //   60: getstatic 32	com/db/pwcc/dbmobile/transfer/inputscreen/activities/SepaConfirmationActivity:bttttttt0074t	I
    //   63: if_icmpeq +14 -> 77
    //   66: invokestatic 39	com/db/pwcc/dbmobile/transfer/inputscreen/activities/SepaConfirmationActivity:b0074007400740074007400740074tt	()I
    //   69: putstatic 26	com/db/pwcc/dbmobile/transfer/inputscreen/activities/SepaConfirmationActivity:b00740074ttttt0074t	I
    //   72: bipush 32
    //   74: putstatic 32	com/db/pwcc/dbmobile/transfer/inputscreen/activities/SepaConfirmationActivity:bttttttt0074t	I
    //   77: getstatic 26	com/db/pwcc/dbmobile/transfer/inputscreen/activities/SepaConfirmationActivity:b00740074ttttt0074t	I
    //   80: getstatic 28	com/db/pwcc/dbmobile/transfer/inputscreen/activities/SepaConfirmationActivity:b0074tttttt0074t	I
    //   83: iadd
    //   84: getstatic 26	com/db/pwcc/dbmobile/transfer/inputscreen/activities/SepaConfirmationActivity:b00740074ttttt0074t	I
    //   87: imul
    //   88: getstatic 30	com/db/pwcc/dbmobile/transfer/inputscreen/activities/SepaConfirmationActivity:bt0074ttttt0074t	I
    //   91: irem
    //   92: getstatic 32	com/db/pwcc/dbmobile/transfer/inputscreen/activities/SepaConfirmationActivity:bttttttt0074t	I
    //   95: if_icmpeq +14 -> 109
    //   98: invokestatic 39	com/db/pwcc/dbmobile/transfer/inputscreen/activities/SepaConfirmationActivity:b0074007400740074007400740074tt	()I
    //   101: putstatic 26	com/db/pwcc/dbmobile/transfer/inputscreen/activities/SepaConfirmationActivity:b00740074ttttt0074t	I
    //   104: bipush 95
    //   106: putstatic 32	com/db/pwcc/dbmobile/transfer/inputscreen/activities/SepaConfirmationActivity:bttttttt0074t	I
    //   109: ldc 76
    //   111: sipush 166
    //   114: bipush 67
    //   116: iconst_0
    //   117: invokestatic 82	xxxxxx/uxxxxx:bbbb0062b0062b0062b0062	(Ljava/lang/String;CCC)Ljava/lang/String;
    //   120: astore 11
    //   122: iconst_4
    //   123: anewarray 41	java/lang/Class
    //   126: astore 12
    //   128: aload 12
    //   130: iconst_0
    //   131: ldc 84
    //   133: aastore
    //   134: aload 12
    //   136: iconst_1
    //   137: getstatic 90	java/lang/Character:TYPE	Ljava/lang/Class;
    //   140: aastore
    //   141: aload 12
    //   143: iconst_2
    //   144: getstatic 90	java/lang/Character:TYPE	Ljava/lang/Class;
    //   147: aastore
    //   148: aload 12
    //   150: iconst_3
    //   151: getstatic 90	java/lang/Character:TYPE	Ljava/lang/Class;
    //   154: aastore
    //   155: ldc 92
    //   157: aload 11
    //   159: aload 12
    //   161: invokevirtual 96	java/lang/Class:getMethod	(Ljava/lang/String;[Ljava/lang/Class;)Ljava/lang/reflect/Method;
    //   164: astore 13
    //   166: iconst_4
    //   167: anewarray 98	java/lang/Object
    //   170: astore 14
    //   172: aload 14
    //   174: iconst_0
    //   175: ldc 100
    //   177: aastore
    //   178: aload 14
    //   180: iconst_1
    //   181: sipush 136
    //   184: invokestatic 104	java/lang/Character:valueOf	(C)Ljava/lang/Character;
    //   187: aastore
    //   188: aload 14
    //   190: iconst_2
    //   191: sipush 201
    //   194: invokestatic 104	java/lang/Character:valueOf	(C)Ljava/lang/Character;
    //   197: aastore
    //   198: aload 14
    //   200: iconst_3
    //   201: iconst_2
    //   202: invokestatic 104	java/lang/Character:valueOf	(C)Ljava/lang/Character;
    //   205: aastore
    //   206: aload 13
    //   208: aconst_null
    //   209: aload 14
    //   211: invokevirtual 110	java/lang/reflect/Method:invoke	(Ljava/lang/Object;[Ljava/lang/Object;)Ljava/lang/Object;
    //   214: astore 16
    //   216: aload 10
    //   218: aload 16
    //   220: checkcast 84	java/lang/String
    //   223: aload_1
    //   224: invokevirtual 114	android/content/Intent:putExtra	(Ljava/lang/String;Ljava/lang/String;)Landroid/content/Intent;
    //   227: pop
    //   228: ldc 116
    //   230: bipush 11
    //   232: iconst_0
    //   233: invokestatic 120	xxxxxx/uxxxxx:bb00620062bb0062b0062b0062	(Ljava/lang/String;CC)Ljava/lang/String;
    //   236: astore 18
    //   238: iconst_3
    //   239: anewarray 41	java/lang/Class
    //   242: astore 19
    //   244: aload 19
    //   246: iconst_0
    //   247: ldc 84
    //   249: aastore
    //   250: aload 19
    //   252: iconst_1
    //   253: getstatic 90	java/lang/Character:TYPE	Ljava/lang/Class;
    //   256: aastore
    //   257: aload 19
    //   259: iconst_2
    //   260: getstatic 90	java/lang/Character:TYPE	Ljava/lang/Class;
    //   263: aastore
    //   264: ldc 92
    //   266: aload 18
    //   268: aload 19
    //   270: invokevirtual 96	java/lang/Class:getMethod	(Ljava/lang/String;[Ljava/lang/Class;)Ljava/lang/reflect/Method;
    //   273: astore 20
    //   275: iconst_3
    //   276: anewarray 98	java/lang/Object
    //   279: astore 21
    //   281: aload 21
    //   283: iconst_0
    //   284: ldc 122
    //   286: aastore
    //   287: aload 21
    //   289: iconst_1
    //   290: bipush 124
    //   292: invokestatic 104	java/lang/Character:valueOf	(C)Ljava/lang/Character;
    //   295: aastore
    //   296: aload 21
    //   298: iconst_2
    //   299: iconst_3
    //   300: invokestatic 104	java/lang/Character:valueOf	(C)Ljava/lang/Character;
    //   303: aastore
    //   304: aload 20
    //   306: aconst_null
    //   307: aload 21
    //   309: invokevirtual 110	java/lang/reflect/Method:invoke	(Ljava/lang/Object;[Ljava/lang/Object;)Ljava/lang/Object;
    //   312: astore 23
    //   314: aload 10
    //   316: aload 23
    //   318: checkcast 84	java/lang/String
    //   321: iload_2
    //   322: invokevirtual 125	android/content/Intent:putExtra	(Ljava/lang/String;Z)Landroid/content/Intent;
    //   325: pop
    //   326: ldc 127
    //   328: iconst_4
    //   329: iconst_1
    //   330: invokestatic 120	xxxxxx/uxxxxx:bb00620062bb0062b0062b0062	(Ljava/lang/String;CC)Ljava/lang/String;
    //   333: astore 25
    //   335: iconst_3
    //   336: anewarray 41	java/lang/Class
    //   339: astore 26
    //   341: aload 26
    //   343: iconst_0
    //   344: ldc 84
    //   346: aastore
    //   347: aload 26
    //   349: iconst_1
    //   350: getstatic 90	java/lang/Character:TYPE	Ljava/lang/Class;
    //   353: aastore
    //   354: aload 26
    //   356: iconst_2
    //   357: getstatic 90	java/lang/Character:TYPE	Ljava/lang/Class;
    //   360: aastore
    //   361: ldc 92
    //   363: aload 25
    //   365: aload 26
    //   367: invokevirtual 96	java/lang/Class:getMethod	(Ljava/lang/String;[Ljava/lang/Class;)Ljava/lang/reflect/Method;
    //   370: astore 27
    //   372: iconst_3
    //   373: anewarray 98	java/lang/Object
    //   376: astore 28
    //   378: aload 28
    //   380: iconst_0
    //   381: ldc -127
    //   383: aastore
    //   384: aload 28
    //   386: iconst_1
    //   387: bipush 66
    //   389: invokestatic 104	java/lang/Character:valueOf	(C)Ljava/lang/Character;
    //   392: aastore
    //   393: aload 28
    //   395: iconst_2
    //   396: iconst_1
    //   397: invokestatic 104	java/lang/Character:valueOf	(C)Ljava/lang/Character;
    //   400: aastore
    //   401: aload 27
    //   403: aconst_null
    //   404: aload 28
    //   406: invokevirtual 110	java/lang/reflect/Method:invoke	(Ljava/lang/Object;[Ljava/lang/Object;)Ljava/lang/Object;
    //   409: astore 30
    //   411: aload 10
    //   413: aload 30
    //   415: checkcast 84	java/lang/String
    //   418: aload_3
    //   419: invokevirtual 132	android/content/Intent:putExtra	(Ljava/lang/String;Ljava/io/Serializable;)Landroid/content/Intent;
    //   422: pop
    //   423: getstatic 26	com/db/pwcc/dbmobile/transfer/inputscreen/activities/SepaConfirmationActivity:b00740074ttttt0074t	I
    //   426: getstatic 28	com/db/pwcc/dbmobile/transfer/inputscreen/activities/SepaConfirmationActivity:b0074tttttt0074t	I
    //   429: iadd
    //   430: getstatic 26	com/db/pwcc/dbmobile/transfer/inputscreen/activities/SepaConfirmationActivity:b00740074ttttt0074t	I
    //   433: imul
    //   434: getstatic 30	com/db/pwcc/dbmobile/transfer/inputscreen/activities/SepaConfirmationActivity:bt0074ttttt0074t	I
    //   437: irem
    //   438: getstatic 32	com/db/pwcc/dbmobile/transfer/inputscreen/activities/SepaConfirmationActivity:bttttttt0074t	I
    //   441: if_icmpeq +14 -> 455
    //   444: invokestatic 39	com/db/pwcc/dbmobile/transfer/inputscreen/activities/SepaConfirmationActivity:b0074007400740074007400740074tt	()I
    //   447: putstatic 26	com/db/pwcc/dbmobile/transfer/inputscreen/activities/SepaConfirmationActivity:b00740074ttttt0074t	I
    //   450: bipush 49
    //   452: putstatic 32	com/db/pwcc/dbmobile/transfer/inputscreen/activities/SepaConfirmationActivity:bttttttt0074t	I
    //   455: ldc -122
    //   457: sipush 185
    //   460: iconst_1
    //   461: invokestatic 120	xxxxxx/uxxxxx:bb00620062bb0062b0062b0062	(Ljava/lang/String;CC)Ljava/lang/String;
    //   464: astore 32
    //   466: iconst_3
    //   467: anewarray 41	java/lang/Class
    //   470: astore 33
    //   472: aload 33
    //   474: iconst_0
    //   475: ldc 84
    //   477: aastore
    //   478: aload 33
    //   480: iconst_1
    //   481: getstatic 90	java/lang/Character:TYPE	Ljava/lang/Class;
    //   484: aastore
    //   485: aload 33
    //   487: iconst_2
    //   488: getstatic 90	java/lang/Character:TYPE	Ljava/lang/Class;
    //   491: aastore
    //   492: ldc 92
    //   494: aload 32
    //   496: aload 33
    //   498: invokevirtual 96	java/lang/Class:getMethod	(Ljava/lang/String;[Ljava/lang/Class;)Ljava/lang/reflect/Method;
    //   501: astore 34
    //   503: iconst_3
    //   504: anewarray 98	java/lang/Object
    //   507: astore 35
    //   509: aload 35
    //   511: iconst_0
    //   512: ldc -120
    //   514: aastore
    //   515: aload 35
    //   517: iconst_1
    //   518: sipush 180
    //   521: invokestatic 104	java/lang/Character:valueOf	(C)Ljava/lang/Character;
    //   524: aastore
    //   525: aload 35
    //   527: iconst_2
    //   528: iconst_2
    //   529: invokestatic 104	java/lang/Character:valueOf	(C)Ljava/lang/Character;
    //   532: aastore
    //   533: aload 34
    //   535: aconst_null
    //   536: aload 35
    //   538: invokevirtual 110	java/lang/reflect/Method:invoke	(Ljava/lang/Object;[Ljava/lang/Object;)Ljava/lang/Object;
    //   541: astore 37
    //   543: aload 10
    //   545: aload 37
    //   547: checkcast 84	java/lang/String
    //   550: aload 4
    //   552: invokevirtual 132	android/content/Intent:putExtra	(Ljava/lang/String;Ljava/io/Serializable;)Landroid/content/Intent;
    //   555: pop
    //   556: ldc -118
    //   558: bipush 36
    //   560: iconst_4
    //   561: invokestatic 120	xxxxxx/uxxxxx:bb00620062bb0062b0062b0062	(Ljava/lang/String;CC)Ljava/lang/String;
    //   564: astore 39
    //   566: iconst_3
    //   567: anewarray 41	java/lang/Class
    //   570: astore 40
    //   572: aload 40
    //   574: iconst_0
    //   575: ldc 84
    //   577: aastore
    //   578: aload 40
    //   580: iconst_1
    //   581: getstatic 90	java/lang/Character:TYPE	Ljava/lang/Class;
    //   584: aastore
    //   585: aload 40
    //   587: iconst_2
    //   588: getstatic 90	java/lang/Character:TYPE	Ljava/lang/Class;
    //   591: aastore
    //   592: ldc 92
    //   594: aload 39
    //   596: aload 40
    //   598: invokevirtual 96	java/lang/Class:getMethod	(Ljava/lang/String;[Ljava/lang/Class;)Ljava/lang/reflect/Method;
    //   601: astore 41
    //   603: iconst_3
    //   604: anewarray 98	java/lang/Object
    //   607: astore 42
    //   609: aload 42
    //   611: iconst_0
    //   612: ldc -116
    //   614: aastore
    //   615: aload 42
    //   617: iconst_1
    //   618: bipush 47
    //   620: invokestatic 104	java/lang/Character:valueOf	(C)Ljava/lang/Character;
    //   623: aastore
    //   624: aload 42
    //   626: iconst_2
    //   627: iconst_5
    //   628: invokestatic 104	java/lang/Character:valueOf	(C)Ljava/lang/Character;
    //   631: aastore
    //   632: aload 41
    //   634: aconst_null
    //   635: aload 42
    //   637: invokevirtual 110	java/lang/reflect/Method:invoke	(Ljava/lang/Object;[Ljava/lang/Object;)Ljava/lang/Object;
    //   640: astore 44
    //   642: aload 10
    //   644: aload 44
    //   646: checkcast 84	java/lang/String
    //   649: aload 5
    //   651: invokevirtual 114	android/content/Intent:putExtra	(Ljava/lang/String;Ljava/lang/String;)Landroid/content/Intent;
    //   654: pop
    //   655: ldc -114
    //   657: sipush 138
    //   660: bipush 69
    //   662: iconst_0
    //   663: invokestatic 82	xxxxxx/uxxxxx:bbbb0062b0062b0062b0062	(Ljava/lang/String;CCC)Ljava/lang/String;
    //   666: astore 46
    //   668: iconst_4
    //   669: anewarray 41	java/lang/Class
    //   672: astore 47
    //   674: aload 47
    //   676: iconst_0
    //   677: ldc 84
    //   679: aastore
    //   680: aload 47
    //   682: iconst_1
    //   683: getstatic 90	java/lang/Character:TYPE	Ljava/lang/Class;
    //   686: aastore
    //   687: aload 47
    //   689: iconst_2
    //   690: getstatic 90	java/lang/Character:TYPE	Ljava/lang/Class;
    //   693: aastore
    //   694: aload 47
    //   696: iconst_3
    //   697: getstatic 90	java/lang/Character:TYPE	Ljava/lang/Class;
    //   700: aastore
    //   701: ldc 92
    //   703: aload 46
    //   705: aload 47
    //   707: invokevirtual 96	java/lang/Class:getMethod	(Ljava/lang/String;[Ljava/lang/Class;)Ljava/lang/reflect/Method;
    //   710: astore 48
    //   712: iconst_4
    //   713: anewarray 98	java/lang/Object
    //   716: astore 49
    //   718: aload 49
    //   720: iconst_0
    //   721: ldc -112
    //   723: aastore
    //   724: aload 49
    //   726: iconst_1
    //   727: bipush 71
    //   729: invokestatic 104	java/lang/Character:valueOf	(C)Ljava/lang/Character;
    //   732: aastore
    //   733: aload 49
    //   735: iconst_2
    //   736: sipush 197
    //   739: invokestatic 104	java/lang/Character:valueOf	(C)Ljava/lang/Character;
    //   742: aastore
    //   743: aload 49
    //   745: iconst_3
    //   746: iconst_1
    //   747: invokestatic 104	java/lang/Character:valueOf	(C)Ljava/lang/Character;
    //   750: aastore
    //   751: aload 48
    //   753: aconst_null
    //   754: aload 49
    //   756: invokevirtual 110	java/lang/reflect/Method:invoke	(Ljava/lang/Object;[Ljava/lang/Object;)Ljava/lang/Object;
    //   759: astore 51
    //   761: aload 10
    //   763: aload 51
    //   765: checkcast 84	java/lang/String
    //   768: iload 6
    //   770: invokevirtual 125	android/content/Intent:putExtra	(Ljava/lang/String;Z)Landroid/content/Intent;
    //   773: pop
    //   774: ldc -110
    //   776: sipush 160
    //   779: iconst_0
    //   780: invokestatic 120	xxxxxx/uxxxxx:bb00620062bb0062b0062b0062	(Ljava/lang/String;CC)Ljava/lang/String;
    //   783: astore 53
    //   785: iconst_3
    //   786: anewarray 41	java/lang/Class
    //   789: astore 54
    //   791: aload 54
    //   793: iconst_0
    //   794: ldc 84
    //   796: aastore
    //   797: aload 54
    //   799: iconst_1
    //   800: getstatic 90	java/lang/Character:TYPE	Ljava/lang/Class;
    //   803: aastore
    //   804: aload 54
    //   806: iconst_2
    //   807: getstatic 90	java/lang/Character:TYPE	Ljava/lang/Class;
    //   810: aastore
    //   811: ldc 92
    //   813: aload 53
    //   815: aload 54
    //   817: invokevirtual 96	java/lang/Class:getMethod	(Ljava/lang/String;[Ljava/lang/Class;)Ljava/lang/reflect/Method;
    //   820: astore 55
    //   822: iconst_3
    //   823: anewarray 98	java/lang/Object
    //   826: astore 56
    //   828: aload 56
    //   830: iconst_0
    //   831: ldc -108
    //   833: aastore
    //   834: aload 56
    //   836: iconst_1
    //   837: bipush 22
    //   839: invokestatic 104	java/lang/Character:valueOf	(C)Ljava/lang/Character;
    //   842: aastore
    //   843: aload 56
    //   845: iconst_2
    //   846: iconst_5
    //   847: invokestatic 104	java/lang/Character:valueOf	(C)Ljava/lang/Character;
    //   850: aastore
    //   851: aload 55
    //   853: aconst_null
    //   854: aload 56
    //   856: invokevirtual 110	java/lang/reflect/Method:invoke	(Ljava/lang/Object;[Ljava/lang/Object;)Ljava/lang/Object;
    //   859: astore 58
    //   861: aload 10
    //   863: aload 58
    //   865: checkcast 84	java/lang/String
    //   868: aload 9
    //   870: invokevirtual 114	android/content/Intent:putExtra	(Ljava/lang/String;Ljava/lang/String;)Landroid/content/Intent;
    //   873: pop
    //   874: lload 7
    //   876: ldc2_w 149
    //   879: lcmp
    //   880: ifle +119 -> 999
    //   883: ldc -104
    //   885: bipush 60
    //   887: iconst_4
    //   888: invokestatic 120	xxxxxx/uxxxxx:bb00620062bb0062b0062b0062	(Ljava/lang/String;CC)Ljava/lang/String;
    //   891: astore 60
    //   893: iconst_4
    //   894: anewarray 41	java/lang/Class
    //   897: astore 61
    //   899: aload 61
    //   901: iconst_0
    //   902: ldc 84
    //   904: aastore
    //   905: aload 61
    //   907: iconst_1
    //   908: getstatic 90	java/lang/Character:TYPE	Ljava/lang/Class;
    //   911: aastore
    //   912: aload 61
    //   914: iconst_2
    //   915: getstatic 90	java/lang/Character:TYPE	Ljava/lang/Class;
    //   918: aastore
    //   919: aload 61
    //   921: iconst_3
    //   922: getstatic 90	java/lang/Character:TYPE	Ljava/lang/Class;
    //   925: aastore
    //   926: ldc 92
    //   928: aload 60
    //   930: aload 61
    //   932: invokevirtual 96	java/lang/Class:getMethod	(Ljava/lang/String;[Ljava/lang/Class;)Ljava/lang/reflect/Method;
    //   935: astore 62
    //   937: iconst_4
    //   938: anewarray 98	java/lang/Object
    //   941: astore 63
    //   943: aload 63
    //   945: iconst_0
    //   946: ldc -102
    //   948: aastore
    //   949: aload 63
    //   951: iconst_1
    //   952: sipush 169
    //   955: invokestatic 104	java/lang/Character:valueOf	(C)Ljava/lang/Character;
    //   958: aastore
    //   959: aload 63
    //   961: iconst_2
    //   962: bipush 18
    //   964: invokestatic 104	java/lang/Character:valueOf	(C)Ljava/lang/Character;
    //   967: aastore
    //   968: aload 63
    //   970: iconst_3
    //   971: iconst_2
    //   972: invokestatic 104	java/lang/Character:valueOf	(C)Ljava/lang/Character;
    //   975: aastore
    //   976: aload 62
    //   978: aconst_null
    //   979: aload 63
    //   981: invokevirtual 110	java/lang/reflect/Method:invoke	(Ljava/lang/Object;[Ljava/lang/Object;)Ljava/lang/Object;
    //   984: astore 65
    //   986: aload 10
    //   988: aload 65
    //   990: checkcast 84	java/lang/String
    //   993: lload 7
    //   995: invokevirtual 157	android/content/Intent:putExtra	(Ljava/lang/String;J)Landroid/content/Intent;
    //   998: pop
    //   999: aload 10
    //   1001: areturn
    //   1002: astore 15
    //   1004: aload 15
    //   1006: invokevirtual 161	java/lang/reflect/InvocationTargetException:getCause	()Ljava/lang/Throwable;
    //   1009: athrow
    //   1010: astore 36
    //   1012: aload 36
    //   1014: invokevirtual 161	java/lang/reflect/InvocationTargetException:getCause	()Ljava/lang/Throwable;
    //   1017: athrow
    //   1018: astore 29
    //   1020: aload 29
    //   1022: invokevirtual 161	java/lang/reflect/InvocationTargetException:getCause	()Ljava/lang/Throwable;
    //   1025: athrow
    //   1026: astore 22
    //   1028: aload 22
    //   1030: invokevirtual 161	java/lang/reflect/InvocationTargetException:getCause	()Ljava/lang/Throwable;
    //   1033: athrow
    //   1034: astore 50
    //   1036: aload 50
    //   1038: invokevirtual 161	java/lang/reflect/InvocationTargetException:getCause	()Ljava/lang/Throwable;
    //   1041: athrow
    //   1042: astore 64
    //   1044: aload 64
    //   1046: invokevirtual 161	java/lang/reflect/InvocationTargetException:getCause	()Ljava/lang/Throwable;
    //   1049: athrow
    //   1050: astore 43
    //   1052: aload 43
    //   1054: invokevirtual 161	java/lang/reflect/InvocationTargetException:getCause	()Ljava/lang/Throwable;
    //   1057: athrow
    //   1058: astore 57
    //   1060: aload 57
    //   1062: invokevirtual 161	java/lang/reflect/InvocationTargetException:getCause	()Ljava/lang/Throwable;
    //   1065: athrow
    // Local variable table:
    //   start	length	slot	name	signature
    //   0	1066	0	paramContext	Context
    //   0	1066	1	paramString1	String
    //   0	1066	2	paramBoolean1	boolean
    //   0	1066	3	paramAuthorization	Authorization
    //   0	1066	4	paramAuthorizationStatus	AuthorizationStatus
    //   0	1066	5	paramString2	String
    //   0	1066	6	paramBoolean2	boolean
    //   0	1066	7	paramLong	long
    //   0	1066	9	paramString3	String
    //   10	990	10	localIntent	Intent
    //   120	38	11	str1	String
    //   126	34	12	arrayOfClass1	Class[]
    //   164	43	13	localMethod1	Method
    //   170	40	14	arrayOfObject1	Object[]
    //   1002	3	15	localInvocationTargetException1	InvocationTargetException
    //   214	5	16	localObject1	Object
    //   236	31	18	str2	String
    //   242	27	19	arrayOfClass2	Class[]
    //   273	32	20	localMethod2	Method
    //   279	29	21	arrayOfObject2	Object[]
    //   1026	3	22	localInvocationTargetException2	InvocationTargetException
    //   312	5	23	localObject2	Object
    //   333	31	25	str3	String
    //   339	27	26	arrayOfClass3	Class[]
    //   370	32	27	localMethod3	Method
    //   376	29	28	arrayOfObject3	Object[]
    //   1018	3	29	localInvocationTargetException3	InvocationTargetException
    //   409	5	30	localObject3	Object
    //   464	31	32	str4	String
    //   470	27	33	arrayOfClass4	Class[]
    //   501	33	34	localMethod4	Method
    //   507	30	35	arrayOfObject4	Object[]
    //   1010	3	36	localInvocationTargetException4	InvocationTargetException
    //   541	5	37	localObject4	Object
    //   564	31	39	str5	String
    //   570	27	40	arrayOfClass5	Class[]
    //   601	32	41	localMethod5	Method
    //   607	29	42	arrayOfObject5	Object[]
    //   1050	3	43	localInvocationTargetException5	InvocationTargetException
    //   640	5	44	localObject5	Object
    //   666	38	46	str6	String
    //   672	34	47	arrayOfClass6	Class[]
    //   710	42	48	localMethod6	Method
    //   716	39	49	arrayOfObject6	Object[]
    //   1034	3	50	localInvocationTargetException6	InvocationTargetException
    //   759	5	51	localObject6	Object
    //   783	31	53	str7	String
    //   789	27	54	arrayOfClass7	Class[]
    //   820	32	55	localMethod7	Method
    //   826	29	56	arrayOfObject7	Object[]
    //   1058	3	57	localInvocationTargetException7	InvocationTargetException
    //   859	5	58	localObject7	Object
    //   891	38	60	str8	String
    //   897	34	61	arrayOfClass8	Class[]
    //   935	42	62	localMethod8	Method
    //   941	39	63	arrayOfObject8	Object[]
    //   1042	3	64	localInvocationTargetException8	InvocationTargetException
    //   984	5	65	localObject8	Object
    // Exception table:
    //   from	to	target	type
    //   206	216	1002	java/lang/reflect/InvocationTargetException
    //   533	543	1010	java/lang/reflect/InvocationTargetException
    //   401	411	1018	java/lang/reflect/InvocationTargetException
    //   304	314	1026	java/lang/reflect/InvocationTargetException
    //   751	761	1034	java/lang/reflect/InvocationTargetException
    //   976	986	1042	java/lang/reflect/InvocationTargetException
    //   632	642	1050	java/lang/reflect/InvocationTargetException
    //   851	861	1058	java/lang/reflect/InvocationTargetException
  }
  
  public static Intent makeIntent(Context paramContext, String paramString1, boolean paramBoolean1, Authorization paramAuthorization, AuthorizationStatus paramAuthorizationStatus, String paramString2, boolean paramBoolean2, String paramString3)
  {
    int i = b00740074ttttt0074t + b0074tttttt0074t;
    int j = b00740074ttttt0074t;
    switch (j * (j + btt0074tttt0074t()) % bt0074ttttt0074t)
    {
    default: 
      b00740074ttttt0074t = 75;
      bttttttt0074t = b0074007400740074007400740074tt();
    }
    if (i * b00740074ttttt0074t % b0074t0074tttt0074t() != bttttttt0074t)
    {
      if ((b00740074ttttt0074t + b0074tttttt0074t) * b00740074ttttt0074t % bt0074ttttt0074t != bttttttt0074t)
      {
        b00740074ttttt0074t = 46;
        bttttttt0074t = 29;
      }
      b00740074ttttt0074t = 6;
      bttttttt0074t = 15;
    }
    if ((b00740074ttttt0074t + b0074tttttt0074t) * b00740074ttttt0074t % bt0074ttttt0074t != bttttttt0074t)
    {
      b00740074ttttt0074t = b0074007400740074007400740074tt();
      bttttttt0074t = 65;
    }
    return makeIntent(paramContext, paramString1, paramBoolean1, paramAuthorization, paramAuthorizationStatus, paramString2, paramBoolean2, -1L, paramString3);
  }
  
  public void closeActivity()
  {
    Intent localIntent = new Intent();
    if ((b00740074ttttt0074t + b0074tttttt0074t) * b00740074ttttt0074t % bt0074ttttt0074t != bttttttt0074t)
    {
      if ((b00740074ttttt0074t + b0074tttttt0074t) * b00740074ttttt0074t % bt0074ttttt0074t != bttttttt0074t)
      {
        b00740074ttttt0074t = 41;
        bttttttt0074t = 45;
      }
      b00740074ttttt0074t = 56;
      bttttttt0074t = 77;
      if ((b00740074ttttt0074t + b0074tttttt0074t) * b00740074ttttt0074t % bt0074ttttt0074t != bttttttt0074t)
      {
        b00740074ttttt0074t = 75;
        bttttttt0074t = 37;
      }
    }
    setResult(-1, localIntent);
    finish();
    int i = b00740074ttttt0074t;
    switch (i * (i + b0074tttttt0074t) % bt0074ttttt0074t)
    {
    default: 
      b00740074ttttt0074t = b0074007400740074007400740074tt();
      bttttttt0074t = 35;
    }
  }
  
  public int getLayout()
  {
    int i = R.layout.activity_sepa_confirmation;
    int j = b0074007400740074007400740074tt();
    switch (j * (j + b0074tttttt0074t) % bt0074ttttt0074t)
    {
    default: 
      b00740074ttttt0074t = 71;
      bttttttt0074t = b0074007400740074007400740074tt();
    }
    int k = b00740074ttttt0074t;
    int m = b0074tttttt0074t;
    if ((b00740074ttttt0074t + b0074tttttt0074t) * b00740074ttttt0074t % bt0074ttttt0074t != bttttttt0074t)
    {
      b00740074ttttt0074t = b0074007400740074007400740074tt();
      bttttttt0074t = 42;
    }
    if ((k + m) * b00740074ttttt0074t % b0074t0074tttt0074t() != bttttttt0074t)
    {
      b00740074ttttt0074t = b0074007400740074007400740074tt();
      bttttttt0074t = 85;
    }
    return i;
  }
  
  public vvrvrv getResultSharedMetric()
  {
    vvrvrv localVvrvrv = vvrvrv.bhh0068006800680068006800680068;
    int i = (b00740074ttttt0074t + b0074tttttt0074t) * b00740074ttttt0074t % bt0074ttttt0074t;
    int j = bttttttt0074t;
    if ((b00740074ttttt0074t + b0074tttttt0074t) * b00740074ttttt0074t % bt0074ttttt0074t != bttttttt0074t)
    {
      b00740074ttttt0074t = b0074007400740074007400740074tt();
      bttttttt0074t = 29;
    }
    if (i != j)
    {
      int k = b00740074ttttt0074t;
      int m = k * (k + b0074tttttt0074t) % bt0074ttttt0074t;
      int n = b00740074ttttt0074t;
      switch (n * (n + b0074tttttt0074t) % bt0074ttttt0074t)
      {
      default: 
        b00740074ttttt0074t = 71;
        bttttttt0074t = b0074007400740074007400740074tt();
      }
      switch (m)
      {
      default: 
        b00740074ttttt0074t = 81;
        bttttttt0074t = 46;
      }
      b00740074ttttt0074t = b0074007400740074007400740074tt();
      bttttttt0074t = b0074007400740074007400740074tt();
    }
    return localVvrvrv;
  }
  
  public llkklk.lkkklk getTanModule()
  {
    int i = b0074007400740074007400740074tt();
    switch (i * (i + b0074tttttt0074t) % bt0074ttttt0074t)
    {
    default: 
      b00740074ttttt0074t = b0074007400740074007400740074tt();
      bttttttt0074t = 25;
    }
    TanModule localTanModule = this.tanModule;
    int j = b00740074ttttt0074t + b0074tttttt0074t;
    int k = b00740074ttttt0074t;
    switch (k * (k + b0074tttttt0074t) % bt0074ttttt0074t)
    {
    default: 
      b00740074ttttt0074t = b0074007400740074007400740074tt();
      bttttttt0074t = b0074007400740074007400740074tt();
    }
    if (j * b00740074ttttt0074t % bt0074ttttt0074t != bttttttt0074t)
    {
      b00740074ttttt0074t = b0074007400740074007400740074tt();
      bttttttt0074t = 40;
    }
    return localTanModule;
  }
  
  public void goBackToInputScreen(boolean paramBoolean)
  {
    Intent localIntent1 = getIntent();
    String str1 = uxxxxx.bb00620062bb0062b0062b0062("CYZ[\\\026\027\037 \032\033#$e\037 ()#$,-n", 'ß', '\002');
    Class[] arrayOfClass1 = new Class[3];
    arrayOfClass1[0] = String.class;
    arrayOfClass1[1] = Character.TYPE;
    arrayOfClass1[2] = Character.TYPE;
    Method localMethod1 = ppphhp.class.getMethod(str1, arrayOfClass1);
    Object[] arrayOfObject1 = new Object[3];
    arrayOfObject1[0] = "\024! a\031\030d(0\035\036i! ,/#+/)r:9)7=11?{\030#0%(\026\026\031\032'.(/;10 .4((6";
    arrayOfObject1[1] = Character.valueOf('\020');
    arrayOfObject1[2] = Character.valueOf('\000');
    try
    {
      Object localObject1 = localMethod1.invoke(null, arrayOfObject1);
      boolean bool = localIntent1.getBooleanExtra((String)localObject1, false);
      if ((b00740074ttttt0074t + btt0074tttt0074t()) * b00740074ttttt0074t % bt0074ttttt0074t != bttttttt0074t)
      {
        b00740074ttttt0074t = 23;
        bttttttt0074t = 50;
      }
      if ((bool) && (paramBoolean))
      {
        startActivity(InputSubaccountActivity.makeIntent(this));
        closeActivity();
        return;
      }
    }
    catch (InvocationTargetException localInvocationTargetException1)
    {
      throw localInvocationTargetException1.getCause();
    }
    Intent localIntent2 = getIntent();
    String str2 = uxxxxx.bbbb0062b0062b0062b0062("u\f\r\016\017HIQRLMUV\030QRZ[UV^_!", '<', '¨', '\002');
    Class[] arrayOfClass2 = new Class[3];
    arrayOfClass2[0] = String.class;
    arrayOfClass2[1] = Character.TYPE;
    arrayOfClass2[2] = Character.TYPE;
    Method localMethod2 = ppphhp.class.getMethod(str2, arrayOfClass2);
    Object[] arrayOfObject2 = new Object[3];
    arrayOfObject2[0] = ";HG\t@?\fOWDE\021HGSVJRVP\032a`P^dXXf#?JWL?K=\\RQAOUIIW";
    arrayOfObject2[1] = Character.valueOf('');
    arrayOfObject2[2] = Character.valueOf('\000');
    try
    {
      Object localObject2 = localMethod2.invoke(null, arrayOfObject2);
      if ((localIntent2.getBooleanExtra((String)localObject2, false)) && (paramBoolean))
      {
        int i = (b0074007400740074007400740074tt() + b0074tttttt0074t) * b0074007400740074007400740074tt() % bt0074ttttt0074t;
        int j = bttttttt0074t;
        int k = b00740074ttttt0074t;
        int m = k * (k + b0074tttttt0074t) % bt0074ttttt0074t;
        int n = b00740074ttttt0074t;
        switch (n * (n + b0074tttttt0074t) % bt0074ttttt0074t)
        {
        default: 
          b00740074ttttt0074t = 24;
          bttttttt0074t = 86;
        }
        switch (m)
        {
        default: 
          b00740074ttttt0074t = b0074007400740074007400740074tt();
          bttttttt0074t = b0074007400740074007400740074tt();
        }
        if (i != j)
        {
          b00740074ttttt0074t = b0074007400740074007400740074tt();
          bttttttt0074t = 41;
        }
        this.redirectFacade.b0061a0061aaaa0061aa(this);
        startActivity(SepaTransferActivity.makeIntent(this));
        return;
      }
      finish();
      return;
    }
    catch (InvocationTargetException localInvocationTargetException2)
    {
      throw localInvocationTargetException2.getCause();
    }
  }
  
  public void hideExecutionDate(boolean paramBoolean)
  {
    if (paramBoolean)
    {
      View localView = findViewById(R.id.executionDateContainer);
      int i = (b00740074ttttt0074t + b0074tttttt0074t) * b00740074ttttt0074t % bt0074ttttt0074t;
      if ((b00740074ttttt0074t + b0074tttttt0074t) * b00740074ttttt0074t % bt0074ttttt0074t != bttttttt0074t)
      {
        b00740074ttttt0074t = 95;
        bttttttt0074t = 64;
      }
      if (i != bttttttt0074t)
      {
        int j = b0074007400740074007400740074tt();
        int k = j * (j + btt0074tttt0074t());
        int m = bt0074ttttt0074t;
        if ((b00740074ttttt0074t + b0074tttttt0074t) * b00740074ttttt0074t % b0074t0074tttt0074t() != bttttttt0074t)
        {
          b00740074ttttt0074t = b0074007400740074007400740074tt();
          bttttttt0074t = 99;
        }
        switch (k % m)
        {
        default: 
          b00740074ttttt0074t = 22;
          bttttttt0074t = 75;
        }
        b00740074ttttt0074t = 80;
        bttttttt0074t = 64;
      }
      localView.setVisibility(8);
    }
  }
  
  public void hidePicIfMultiline(Activity paramActivity)
  {
    final TextView localTextView1 = (TextView)paramActivity.findViewById(R.id.confirmation_beneficiaryName);
    int i = b00740074ttttt0074t;
    switch (i * (i + b0074tttttt0074t) % b0074t0074tttt0074t())
    {
    default: 
      b00740074ttttt0074t = b0074007400740074007400740074tt();
      bttttttt0074t = b0074007400740074007400740074tt();
    }
    final TextView localTextView2 = (TextView)paramActivity.findViewById(R.id.confirmation_beneficiaryIban);
    final TextView localTextView3 = (TextView)paramActivity.findViewById(R.id.bankName);
    final TextView localTextView4 = (TextView)paramActivity.findViewById(R.id.description);
    final TextView localTextView5 = (TextView)paramActivity.findViewById(R.id.confirmation_principalName);
    final TextView localTextView6 = (TextView)paramActivity.findViewById(R.id.confirmation_principalIban);
    int j = b00740074ttttt0074t;
    switch (j * (j + b0074tttttt0074t) % bt0074ttttt0074t)
    {
    default: 
      b00740074ttttt0074t = 83;
      bttttttt0074t = b0074007400740074007400740074tt();
    }
    int k = R.id.confirmation_principalCurrentBalance;
    if ((b00740074ttttt0074t + b0074tttttt0074t) * b00740074ttttt0074t % bt0074ttttt0074t != bttttttt0074t)
    {
      b00740074ttttt0074t = 61;
      bttttttt0074t = b0074007400740074007400740074tt();
    }
    final TextView localTextView7 = (TextView)paramActivity.findViewById(k);
    final TextView localTextView8 = (TextView)paramActivity.findViewById(R.id.confirmation_principalPrebookedBalance);
    localTextView1.post(new Runnable()
    {
      public static int b00620062bbb0062b00620062 = 0;
      public static int b0062b0062bb0062b00620062 = 2;
      public static int bb00620062bb0062b00620062 = 69;
      public static int bbb0062bb0062b00620062 = 1;
      
      public static int b0069i00690069iiiii0069()
      {
        return 16;
      }
      
      public static int bi006900690069iiiii0069()
      {
        return 1;
      }
      
      public void run()
      {
        int i = bb00620062bb0062b00620062;
        switch (i * (i + bi006900690069iiiii0069()) % b0062b0062bb0062b00620062)
        {
        default: 
          bb00620062bb0062b00620062 = b0069i00690069iiiii0069();
          b00620062bbb0062b00620062 = 62;
        }
        int j = b0069i00690069iiiii0069();
        int k = bbb0062bb0062b00620062;
        int m = bb00620062bb0062b00620062;
        switch (m * (m + bbb0062bb0062b00620062) % b0062b0062bb0062b00620062)
        {
        default: 
          bb00620062bb0062b00620062 = b0069i00690069iiiii0069();
          b00620062bbb0062b00620062 = 38;
        }
        int n = j + k;
        if ((bb00620062bb0062b00620062 + bbb0062bb0062b00620062) * bb00620062bb0062b00620062 % b0062b0062bb0062b00620062 != b00620062bbb0062b00620062)
        {
          bb00620062bb0062b00620062 = b0069i00690069iiiii0069();
          b00620062bbb0062b00620062 = b0069i00690069iiiii0069();
        }
        if (n * b0069i00690069iiiii0069() % b0062b0062bb0062b00620062 != b00620062bbb0062b00620062) {
          b00620062bbb0062b00620062 = b0069i00690069iiiii0069();
        }
        SepaConfirmationActivity.this.hidePictureIfNeeded(localTextView1);
      }
    });
    localTextView2.post(new Runnable()
    {
      public static int b00620062b0062b0062b00620062 = 1;
      public static int b0062bb0062b0062b00620062 = 26;
      public static int bb0062b0062b0062b00620062 = 0;
      public static int bbb00620062b0062b00620062 = 2;
      
      public static int b0069006900690069iiiii0069()
      {
        return 88;
      }
      
      public static int biiii0069iiii0069()
      {
        return 1;
      }
      
      public void run()
      {
        if ((b0062bb0062b0062b00620062 + b00620062b0062b0062b00620062) * b0062bb0062b0062b00620062 % bbb00620062b0062b00620062 != bb0062b0062b0062b00620062)
        {
          b0062bb0062b0062b00620062 = 33;
          bb0062b0062b0062b00620062 = b0069006900690069iiiii0069();
        }
        if ((b0062bb0062b0062b00620062 + b00620062b0062b0062b00620062) * b0062bb0062b0062b00620062 % bbb00620062b0062b00620062 != bb0062b0062b0062b00620062)
        {
          b0062bb0062b0062b00620062 = b0069006900690069iiiii0069();
          bb0062b0062b0062b00620062 = b0069006900690069iiiii0069();
        }
        int i = b0062bb0062b0062b00620062;
        switch (i * (i + b00620062b0062b0062b00620062) % bbb00620062b0062b00620062)
        {
        default: 
          b0062bb0062b0062b00620062 = 25;
          bb0062b0062b0062b00620062 = 24;
        }
        SepaConfirmationActivity.this.hidePictureIfNeeded(localTextView2);
        if ((b0062bb0062b0062b00620062 + biiii0069iiii0069()) * b0062bb0062b0062b00620062 % bbb00620062b0062b00620062 != bb0062b0062b0062b00620062)
        {
          b0062bb0062b0062b00620062 = b0069006900690069iiiii0069();
          bb0062b0062b0062b00620062 = b0069006900690069iiiii0069();
        }
      }
    });
    localTextView3.post(new Runnable()
    {
      public static int b0062006200620062b0062b00620062 = 2;
      public static int b0062bbb00620062b00620062 = 1;
      public static int bb0062bb00620062b00620062 = 0;
      public static int bbbbb00620062b00620062 = 17;
      
      public static int b0069iii0069iiii0069()
      {
        return 32;
      }
      
      public static int bi0069ii0069iiii0069()
      {
        return 1;
      }
      
      public void run()
      {
        int i = bbbbb00620062b00620062;
        switch (i * (i + b0062bbb00620062b00620062) % b0062006200620062b0062b00620062)
        {
        default: 
          bbbbb00620062b00620062 = b0069iii0069iiii0069();
          b0062bbb00620062b00620062 = 70;
        }
        int j = bbbbb00620062b00620062;
        switch (j * (j + b0062bbb00620062b00620062) % b0062006200620062b0062b00620062)
        {
        default: 
          bbbbb00620062b00620062 = 55;
          bb0062bb00620062b00620062 = b0069iii0069iiii0069();
        }
        SepaConfirmationActivity localSepaConfirmationActivity = SepaConfirmationActivity.this;
        int k = b0069iii0069iiii0069();
        switch (k * (k + bi0069ii0069iiii0069()) % b0062006200620062b0062b00620062)
        {
        default: 
          b0062006200620062b0062b00620062 = b0069iii0069iiii0069();
          if ((b0069iii0069iiii0069() + b0062bbb00620062b00620062) * b0069iii0069iiii0069() % b0062006200620062b0062b00620062 != bb0062bb00620062b00620062)
          {
            bbbbb00620062b00620062 = b0069iii0069iiii0069();
            bb0062bb00620062b00620062 = 58;
          }
          break;
        }
        localSepaConfirmationActivity.hidePictureIfNeeded(localTextView3);
      }
    });
    if ((b00740074ttttt0074t + b0074tttttt0074t) * b00740074ttttt0074t % bt0074ttttt0074t != bttttttt0074t)
    {
      b00740074ttttt0074t = b0074007400740074007400740074tt();
      bttttttt0074t = 9;
    }
    localTextView4.post(new Runnable()
    {
      public static int b006200620062b00620062b00620062 = 1;
      public static int b0062b0062b00620062b00620062 = 69;
      public static int bb00620062b00620062b00620062 = 0;
      public static int bbbb006200620062b00620062 = 2;
      
      public static int b00690069ii0069iiii0069()
      {
        return 30;
      }
      
      public void run()
      {
        SepaConfirmationActivity localSepaConfirmationActivity = SepaConfirmationActivity.this;
        TextView localTextView = localTextView4;
        int i = b0062b0062b00620062b00620062 + b006200620062b00620062b00620062;
        int j = b0062b0062b00620062b00620062;
        if ((b00690069ii0069iiii0069() + b006200620062b00620062b00620062) * b00690069ii0069iiii0069() % bbbb006200620062b00620062 != bb00620062b00620062b00620062)
        {
          b0062b0062b00620062b00620062 = b00690069ii0069iiii0069();
          bb00620062b00620062b00620062 = 23;
        }
        int k = i * j % bbbb006200620062b00620062;
        int m = bb00620062b00620062b00620062;
        if ((b0062b0062b00620062b00620062 + b006200620062b00620062b00620062) * b0062b0062b00620062b00620062 % bbbb006200620062b00620062 != bb00620062b00620062b00620062)
        {
          b0062b0062b00620062b00620062 = b00690069ii0069iiii0069();
          bb00620062b00620062b00620062 = b00690069ii0069iiii0069();
        }
        if (k != m)
        {
          b0062b0062b00620062b00620062 = b00690069ii0069iiii0069();
          bb00620062b00620062b00620062 = b00690069ii0069iiii0069();
        }
        localSepaConfirmationActivity.hidePictureIfNeeded(localTextView);
        if ((b0062b0062b00620062b00620062 + b006200620062b00620062b00620062) * b0062b0062b00620062b00620062 % bbbb006200620062b00620062 != bb00620062b00620062b00620062)
        {
          b0062b0062b00620062b00620062 = 44;
          bb00620062b00620062b00620062 = b00690069ii0069iiii0069();
        }
      }
    });
    localTextView5.post(new Runnable()
    {
      public static int b00620062b006200620062b00620062 = 0;
      public static int b0062b0062006200620062b00620062 = 55;
      public static int bb00620062006200620062b00620062 = 2;
      public static int bbb0062006200620062b00620062 = 1;
      
      public static int b0069i0069i0069iiii0069()
      {
        return 0;
      }
      
      public static int bi00690069i0069iiii0069()
      {
        return 74;
      }
      
      public static int bii0069i0069iiii0069()
      {
        return 2;
      }
      
      public void run()
      {
        if ((bi00690069i0069iiii0069() + bbb0062006200620062b00620062) * bi00690069i0069iiii0069() % bii0069i0069iiii0069() != b00620062b006200620062b00620062)
        {
          int i = b0062b0062006200620062b00620062;
          switch (i * (i + bbb0062006200620062b00620062) % bb00620062006200620062b00620062)
          {
          default: 
            b0062b0062006200620062b00620062 = 13;
            b00620062b006200620062b00620062 = 53;
          }
          if ((b0062b0062006200620062b00620062 + bbb0062006200620062b00620062) * b0062b0062006200620062b00620062 % bb00620062006200620062b00620062 != b00620062b006200620062b00620062)
          {
            b0062b0062006200620062b00620062 = 61;
            b00620062b006200620062b00620062 = bi00690069i0069iiii0069();
          }
          b00620062b006200620062b00620062 = bi00690069i0069iiii0069();
        }
        if ((b0062b0062006200620062b00620062 + bbb0062006200620062b00620062) * b0062b0062006200620062b00620062 % bb00620062006200620062b00620062 != b0069i0069i0069iiii0069())
        {
          b0062b0062006200620062b00620062 = 0;
          b00620062b006200620062b00620062 = bi00690069i0069iiii0069();
        }
        SepaConfirmationActivity.this.hidePictureIfNeeded(localTextView5);
      }
    });
    localTextView6.post(new Runnable()
    {
      public static int b00620062bbbb006200620062 = 1;
      public static int b0062bbbbb006200620062 = 22;
      public static int bb0062bbbb006200620062 = 0;
      public static int bbb0062bbb006200620062 = 2;
      
      public static int b006900690069i0069iiii0069()
      {
        return 95;
      }
      
      public static int b0069ii00690069iiii0069()
      {
        return 1;
      }
      
      public static int biii00690069iiii0069()
      {
        return 2;
      }
      
      public void run()
      {
        int i = b0062bbbbb006200620062;
        switch (i * (i + b00620062bbbb006200620062) % bbb0062bbb006200620062)
        {
        default: 
          b0062bbbbb006200620062 = 91;
          bb0062bbbb006200620062 = b006900690069i0069iiii0069();
        }
        SepaConfirmationActivity localSepaConfirmationActivity = SepaConfirmationActivity.this;
        int j = (b0062bbbbb006200620062 + b00620062bbbb006200620062) * b0062bbbbb006200620062 % bbb0062bbb006200620062;
        int k = b0062bbbbb006200620062;
        switch (k * (k + b0069ii00690069iiii0069()) % biii00690069iiii0069())
        {
        default: 
          b0062bbbbb006200620062 = b006900690069i0069iiii0069();
          bb0062bbbb006200620062 = 79;
        }
        if (j != bb0062bbbb006200620062)
        {
          b0062bbbbb006200620062 = b006900690069i0069iiii0069();
          bb0062bbbb006200620062 = 56;
        }
        TextView localTextView = localTextView6;
        if ((b0062bbbbb006200620062 + b00620062bbbb006200620062) * b0062bbbbb006200620062 % bbb0062bbb006200620062 != bb0062bbbb006200620062)
        {
          b0062bbbbb006200620062 = b006900690069i0069iiii0069();
          bb0062bbbb006200620062 = 87;
        }
        localSepaConfirmationActivity.hidePictureIfNeeded(localTextView);
      }
    });
    localTextView7.post(new Runnable()
    {
      public static int b006200620062bbb006200620062 = 43;
      public static int b0062bb0062bb006200620062 = 2;
      public static int bb0062b0062bb006200620062 = 0;
      public static int bbbb0062bb006200620062 = 1;
      
      public static int b00690069i00690069iiii0069()
      {
        return 1;
      }
      
      public static int bi0069i00690069iiii0069()
      {
        return 72;
      }
      
      public void run()
      {
        int i = b006200620062bbb006200620062;
        switch (i * (i + bbbb0062bb006200620062) % b0062bb0062bb006200620062)
        {
        default: 
          int m = b006200620062bbb006200620062;
          switch (m * (m + b00690069i00690069iiii0069()) % b0062bb0062bb006200620062)
          {
          default: 
            b006200620062bbb006200620062 = bi0069i00690069iiii0069();
            bbbb0062bb006200620062 = 7;
          }
          b006200620062bbb006200620062 = 31;
          bbbb0062bb006200620062 = bi0069i00690069iiii0069();
        }
        SepaConfirmationActivity localSepaConfirmationActivity = SepaConfirmationActivity.this;
        int j = b006200620062bbb006200620062;
        int k = bbbb0062bb006200620062;
        if ((b006200620062bbb006200620062 + b00690069i00690069iiii0069()) * b006200620062bbb006200620062 % b0062bb0062bb006200620062 != bb0062b0062bb006200620062)
        {
          b006200620062bbb006200620062 = bi0069i00690069iiii0069();
          bb0062b0062bb006200620062 = bi0069i00690069iiii0069();
        }
        switch (j * (k + j) % b0062bb0062bb006200620062)
        {
        default: 
          b006200620062bbb006200620062 = 23;
          bbbb0062bb006200620062 = bi0069i00690069iiii0069();
        }
        localSepaConfirmationActivity.hidePictureIfNeeded(localTextView7);
      }
    });
    localTextView8.post(new Runnable()
    {
      public static int b0062006200620062bb006200620062 = 2;
      public static int b0062b00620062bb006200620062 = 51;
      public static int bb006200620062bb006200620062 = 1;
      public static int bbbbb0062b006200620062;
      
      public static int bii006900690069iiii0069()
      {
        return 56;
      }
      
      public void run()
      {
        SepaConfirmationActivity localSepaConfirmationActivity = SepaConfirmationActivity.this;
        TextView localTextView = localTextView8;
        int i = b0062b00620062bb006200620062;
        int j = bb006200620062bb006200620062;
        int k = bii006900690069iiii0069();
        switch (k * (k + bb006200620062bb006200620062) % b0062006200620062bb006200620062)
        {
        default: 
          b0062b00620062bb006200620062 = bii006900690069iiii0069();
          bbbbb0062b006200620062 = bii006900690069iiii0069();
        }
        switch (i * (j + i) % b0062006200620062bb006200620062)
        {
        default: 
          b0062b00620062bb006200620062 = 20;
          int m = b0062b00620062bb006200620062 + bb006200620062bb006200620062;
          if ((b0062b00620062bb006200620062 + bb006200620062bb006200620062) * b0062b00620062bb006200620062 % b0062006200620062bb006200620062 != bbbbb0062b006200620062)
          {
            b0062b00620062bb006200620062 = bii006900690069iiii0069();
            bbbbb0062b006200620062 = bii006900690069iiii0069();
          }
          if (m * b0062b00620062bb006200620062 % b0062006200620062bb006200620062 != bbbbb0062b006200620062)
          {
            b0062b00620062bb006200620062 = bii006900690069iiii0069();
            bbbbb0062b006200620062 = bii006900690069iiii0069();
          }
          bb006200620062bb006200620062 = bii006900690069iiii0069();
        }
        localSepaConfirmationActivity.hidePictureIfNeeded(localTextView);
      }
    });
  }
  
  public void hidePrincipalAccountBalance()
  {
    int i = R.id.confirmation_principalCurrentBalance;
    if ((b00740074ttttt0074t + b0074tttttt0074t) * b00740074ttttt0074t % bt0074ttttt0074t != bttttttt0074t)
    {
      b00740074ttttt0074t = b0074007400740074007400740074tt();
      bttttttt0074t = b0074007400740074007400740074tt();
    }
    TextView localTextView1 = (TextView)findViewById(i);
    int j = R.id.confirmation_principalPrebookedBalance;
    int k = b00740074ttttt0074t;
    switch (k * (k + b0074tttttt0074t) % b0074t0074tttt0074t())
    {
    default: 
      b00740074ttttt0074t = b0074007400740074007400740074tt();
      bttttttt0074t = b0074007400740074007400740074tt();
      if ((b00740074ttttt0074t + b0074tttttt0074t) * b00740074ttttt0074t % bt0074ttttt0074t != bt00740074tttt0074t())
      {
        b00740074ttttt0074t = b0074007400740074007400740074tt();
        bttttttt0074t = b0074007400740074007400740074tt();
      }
      break;
    }
    TextView localTextView2 = (TextView)findViewById(j);
    int m = b00740074ttttt0074t;
    switch (m * (m + b0074tttttt0074t) % bt0074ttttt0074t)
    {
    default: 
      b00740074ttttt0074t = 95;
      bttttttt0074t = 96;
    }
    if (localTextView1 != null) {
      localTextView1.setVisibility(8);
    }
    if (localTextView2 != null) {
      localTextView2.setVisibility(8);
    }
  }
  
  public void initDbToolbar()
  {
    super.initDbToolbar();
    int i = b00740074ttttt0074t;
    int j = i + b0074tttttt0074t;
    int k = b00740074ttttt0074t;
    switch (k * (k + b0074tttttt0074t) % bt0074ttttt0074t)
    {
    default: 
      b00740074ttttt0074t = b0074007400740074007400740074tt();
      bttttttt0074t = 67;
    }
    switch (i * j % bt0074ttttt0074t)
    {
    default: 
      b00740074ttttt0074t = 56;
      bttttttt0074t = 51;
    }
    DbToolbar localDbToolbar = getActionToolbar();
    Resources localResources = getResources();
    int m;
    if (this.isSubaccountTransfer) {
      m = R.string.sepatransfer_subaccount_verify_title;
    }
    for (;;)
    {
      localDbToolbar.setTitle(localResources.getString(m));
      return;
      m = R.string.sepatransfer_verify_title;
      int n = b00740074ttttt0074t;
      switch (n * (n + b0074tttttt0074t) % b0074t0074tttt0074t())
      {
      default: 
        b00740074ttttt0074t = b0074007400740074007400740074tt();
        bttttttt0074t = b0074007400740074007400740074tt();
      }
      if ((b00740074ttttt0074t + b0074tttttt0074t) * b00740074ttttt0074t % bt0074ttttt0074t != bttttttt0074t)
      {
        b00740074ttttt0074t = 31;
        bttttttt0074t = 89;
      }
    }
  }
  
  /* Error */
  public void initView()
  {
    // Byte code:
    //   0: aload_0
    //   1: invokevirtual 197	com/db/pwcc/dbmobile/transfer/inputscreen/activities/SepaConfirmationActivity:getIntent	()Landroid/content/Intent;
    //   4: invokevirtual 347	android/content/Intent:getExtras	()Landroid/os/Bundle;
    //   7: astore_1
    //   8: ldc_w 349
    //   11: bipush 71
    //   13: iconst_5
    //   14: invokestatic 120	xxxxxx/uxxxxx:bb00620062bb0062b0062b0062	(Ljava/lang/String;CC)Ljava/lang/String;
    //   17: astore_2
    //   18: iconst_3
    //   19: anewarray 41	java/lang/Class
    //   22: astore_3
    //   23: aload_3
    //   24: iconst_0
    //   25: ldc 84
    //   27: aastore
    //   28: aload_3
    //   29: iconst_1
    //   30: getstatic 90	java/lang/Character:TYPE	Ljava/lang/Class;
    //   33: aastore
    //   34: aload_3
    //   35: iconst_2
    //   36: getstatic 90	java/lang/Character:TYPE	Ljava/lang/Class;
    //   39: aastore
    //   40: ldc 92
    //   42: aload_2
    //   43: aload_3
    //   44: invokevirtual 96	java/lang/Class:getMethod	(Ljava/lang/String;[Ljava/lang/Class;)Ljava/lang/reflect/Method;
    //   47: astore 4
    //   49: iconst_3
    //   50: anewarray 98	java/lang/Object
    //   53: astore 5
    //   55: aload 5
    //   57: iconst_0
    //   58: ldc_w 351
    //   61: aastore
    //   62: aload 5
    //   64: iconst_1
    //   65: bipush 64
    //   67: invokestatic 104	java/lang/Character:valueOf	(C)Ljava/lang/Character;
    //   70: aastore
    //   71: aload 5
    //   73: iconst_2
    //   74: iconst_0
    //   75: invokestatic 104	java/lang/Character:valueOf	(C)Ljava/lang/Character;
    //   78: aastore
    //   79: aload 4
    //   81: aconst_null
    //   82: aload 5
    //   84: invokevirtual 110	java/lang/reflect/Method:invoke	(Ljava/lang/Object;[Ljava/lang/Object;)Ljava/lang/Object;
    //   87: astore 7
    //   89: aload_1
    //   90: aload 7
    //   92: checkcast 84	java/lang/String
    //   95: invokevirtual 357	android/os/Bundle:getBoolean	(Ljava/lang/String;)Z
    //   98: istore 8
    //   100: getstatic 26	com/db/pwcc/dbmobile/transfer/inputscreen/activities/SepaConfirmationActivity:b00740074ttttt0074t	I
    //   103: istore 9
    //   105: iload 9
    //   107: iload 9
    //   109: getstatic 28	com/db/pwcc/dbmobile/transfer/inputscreen/activities/SepaConfirmationActivity:b0074tttttt0074t	I
    //   112: iadd
    //   113: imul
    //   114: getstatic 30	com/db/pwcc/dbmobile/transfer/inputscreen/activities/SepaConfirmationActivity:bt0074ttttt0074t	I
    //   117: irem
    //   118: tableswitch	default:+18->136, 0:+28->146
    //   136: bipush 24
    //   138: putstatic 26	com/db/pwcc/dbmobile/transfer/inputscreen/activities/SepaConfirmationActivity:b00740074ttttt0074t	I
    //   141: bipush 66
    //   143: putstatic 32	com/db/pwcc/dbmobile/transfer/inputscreen/activities/SepaConfirmationActivity:bttttttt0074t	I
    //   146: aload_0
    //   147: iload 8
    //   149: putfield 56	com/db/pwcc/dbmobile/transfer/inputscreen/activities/SepaConfirmationActivity:isSubaccountTransfer	Z
    //   152: aload_0
    //   153: new 359	uuuuuu/nnnntn
    //   156: dup
    //   157: aload_0
    //   158: getfield 56	com/db/pwcc/dbmobile/transfer/inputscreen/activities/SepaConfirmationActivity:isSubaccountTransfer	Z
    //   161: invokespecial 361	uuuuuu/nnnntn:<init>	(Z)V
    //   164: putfield 52	com/db/pwcc/dbmobile/transfer/inputscreen/activities/SepaConfirmationActivity:presenter	Luuuuuu/nnnntn;
    //   167: getstatic 26	com/db/pwcc/dbmobile/transfer/inputscreen/activities/SepaConfirmationActivity:b00740074ttttt0074t	I
    //   170: getstatic 28	com/db/pwcc/dbmobile/transfer/inputscreen/activities/SepaConfirmationActivity:b0074tttttt0074t	I
    //   173: iadd
    //   174: getstatic 26	com/db/pwcc/dbmobile/transfer/inputscreen/activities/SepaConfirmationActivity:b00740074ttttt0074t	I
    //   177: imul
    //   178: getstatic 30	com/db/pwcc/dbmobile/transfer/inputscreen/activities/SepaConfirmationActivity:bt0074ttttt0074t	I
    //   181: irem
    //   182: getstatic 32	com/db/pwcc/dbmobile/transfer/inputscreen/activities/SepaConfirmationActivity:bttttttt0074t	I
    //   185: if_icmpeq +14 -> 199
    //   188: bipush 28
    //   190: putstatic 26	com/db/pwcc/dbmobile/transfer/inputscreen/activities/SepaConfirmationActivity:b00740074ttttt0074t	I
    //   193: invokestatic 39	com/db/pwcc/dbmobile/transfer/inputscreen/activities/SepaConfirmationActivity:b0074007400740074007400740074tt	()I
    //   196: putstatic 32	com/db/pwcc/dbmobile/transfer/inputscreen/activities/SepaConfirmationActivity:bttttttt0074t	I
    //   199: aload_0
    //   200: getfield 52	com/db/pwcc/dbmobile/transfer/inputscreen/activities/SepaConfirmationActivity:presenter	Luuuuuu/nnnntn;
    //   203: aload_0
    //   204: invokevirtual 365	uuuuuu/nnnntn:ba0061a0061a0061a0061aa	(Luuuuuu/ttssst$tsssst;)V
    //   207: aload_0
    //   208: invokespecial 367	com/db/pwcc/dbmobile/transfer/inputscreen/activities/ConfirmationActivity:initView	()V
    //   211: aload_0
    //   212: getfield 191	com/db/pwcc/dbmobile/transfer/inputscreen/activities/SepaConfirmationActivity:tanModule	Lcom/db/pwcc/dbmobile/tan/ui/TanModule;
    //   215: astore 10
    //   217: invokestatic 39	com/db/pwcc/dbmobile/transfer/inputscreen/activities/SepaConfirmationActivity:b0074007400740074007400740074tt	()I
    //   220: istore 11
    //   222: iload 11
    //   224: iload 11
    //   226: getstatic 28	com/db/pwcc/dbmobile/transfer/inputscreen/activities/SepaConfirmationActivity:b0074tttttt0074t	I
    //   229: iadd
    //   230: imul
    //   231: getstatic 30	com/db/pwcc/dbmobile/transfer/inputscreen/activities/SepaConfirmationActivity:bt0074ttttt0074t	I
    //   234: irem
    //   235: tableswitch	default:+17->252, 0:+28->263
    //   252: bipush 47
    //   254: putstatic 26	com/db/pwcc/dbmobile/transfer/inputscreen/activities/SepaConfirmationActivity:b00740074ttttt0074t	I
    //   257: invokestatic 39	com/db/pwcc/dbmobile/transfer/inputscreen/activities/SepaConfirmationActivity:b0074007400740074007400740074tt	()I
    //   260: putstatic 32	com/db/pwcc/dbmobile/transfer/inputscreen/activities/SepaConfirmationActivity:bttttttt0074t	I
    //   263: aload 10
    //   265: aload_0
    //   266: getfield 52	com/db/pwcc/dbmobile/transfer/inputscreen/activities/SepaConfirmationActivity:presenter	Luuuuuu/nnnntn;
    //   269: invokevirtual 373	com/db/pwcc/dbmobile/tan/ui/TanModule:setTanModuleActivityActions	(Luuuuuu/kkkklk;)V
    //   272: aload_0
    //   273: getfield 52	com/db/pwcc/dbmobile/transfer/inputscreen/activities/SepaConfirmationActivity:presenter	Luuuuuu/nnnntn;
    //   276: invokevirtual 376	uuuuuu/nnnntn:b0069i0069iii0069ii0069	()V
    //   279: aload_0
    //   280: invokevirtual 197	com/db/pwcc/dbmobile/transfer/inputscreen/activities/SepaConfirmationActivity:getIntent	()Landroid/content/Intent;
    //   283: invokevirtual 347	android/content/Intent:getExtras	()Landroid/os/Bundle;
    //   286: astore 12
    //   288: ldc_w 378
    //   291: bipush 84
    //   293: sipush 166
    //   296: iconst_2
    //   297: invokestatic 82	xxxxxx/uxxxxx:bbbb0062b0062b0062b0062	(Ljava/lang/String;CCC)Ljava/lang/String;
    //   300: astore 13
    //   302: iconst_4
    //   303: anewarray 41	java/lang/Class
    //   306: astore 14
    //   308: aload 14
    //   310: iconst_0
    //   311: ldc 84
    //   313: aastore
    //   314: aload 14
    //   316: iconst_1
    //   317: getstatic 90	java/lang/Character:TYPE	Ljava/lang/Class;
    //   320: aastore
    //   321: aload 14
    //   323: iconst_2
    //   324: getstatic 90	java/lang/Character:TYPE	Ljava/lang/Class;
    //   327: aastore
    //   328: aload 14
    //   330: iconst_3
    //   331: getstatic 90	java/lang/Character:TYPE	Ljava/lang/Class;
    //   334: aastore
    //   335: ldc 92
    //   337: aload 13
    //   339: aload 14
    //   341: invokevirtual 96	java/lang/Class:getMethod	(Ljava/lang/String;[Ljava/lang/Class;)Ljava/lang/reflect/Method;
    //   344: astore 15
    //   346: iconst_4
    //   347: anewarray 98	java/lang/Object
    //   350: astore 16
    //   352: aload 16
    //   354: iconst_0
    //   355: ldc_w 380
    //   358: aastore
    //   359: aload 16
    //   361: iconst_1
    //   362: sipush 167
    //   365: invokestatic 104	java/lang/Character:valueOf	(C)Ljava/lang/Character;
    //   368: aastore
    //   369: aload 16
    //   371: iconst_2
    //   372: sipush 144
    //   375: invokestatic 104	java/lang/Character:valueOf	(C)Ljava/lang/Character;
    //   378: aastore
    //   379: aload 16
    //   381: iconst_3
    //   382: iconst_1
    //   383: invokestatic 104	java/lang/Character:valueOf	(C)Ljava/lang/Character;
    //   386: aastore
    //   387: aload 15
    //   389: aconst_null
    //   390: aload 16
    //   392: invokevirtual 110	java/lang/reflect/Method:invoke	(Ljava/lang/Object;[Ljava/lang/Object;)Ljava/lang/Object;
    //   395: astore 18
    //   397: aload 12
    //   399: aload 18
    //   401: checkcast 84	java/lang/String
    //   404: invokevirtual 383	android/os/Bundle:getString	(Ljava/lang/String;)Ljava/lang/String;
    //   407: astore 19
    //   409: aload_0
    //   410: invokevirtual 197	com/db/pwcc/dbmobile/transfer/inputscreen/activities/SepaConfirmationActivity:getIntent	()Landroid/content/Intent;
    //   413: invokevirtual 347	android/content/Intent:getExtras	()Landroid/os/Bundle;
    //   416: astore 20
    //   418: ldc_w 385
    //   421: iconst_3
    //   422: iconst_4
    //   423: invokestatic 120	xxxxxx/uxxxxx:bb00620062bb0062b0062b0062	(Ljava/lang/String;CC)Ljava/lang/String;
    //   426: astore 21
    //   428: iconst_3
    //   429: anewarray 41	java/lang/Class
    //   432: astore 22
    //   434: aload 22
    //   436: iconst_0
    //   437: ldc 84
    //   439: aastore
    //   440: aload 22
    //   442: iconst_1
    //   443: getstatic 90	java/lang/Character:TYPE	Ljava/lang/Class;
    //   446: aastore
    //   447: aload 22
    //   449: iconst_2
    //   450: getstatic 90	java/lang/Character:TYPE	Ljava/lang/Class;
    //   453: aastore
    //   454: ldc 92
    //   456: aload 21
    //   458: aload 22
    //   460: invokevirtual 96	java/lang/Class:getMethod	(Ljava/lang/String;[Ljava/lang/Class;)Ljava/lang/reflect/Method;
    //   463: astore 23
    //   465: iconst_3
    //   466: anewarray 98	java/lang/Object
    //   469: astore 24
    //   471: aload 24
    //   473: iconst_0
    //   474: ldc_w 387
    //   477: aastore
    //   478: aload 24
    //   480: iconst_1
    //   481: bipush 81
    //   483: invokestatic 104	java/lang/Character:valueOf	(C)Ljava/lang/Character;
    //   486: aastore
    //   487: aload 24
    //   489: iconst_2
    //   490: iconst_3
    //   491: invokestatic 104	java/lang/Character:valueOf	(C)Ljava/lang/Character;
    //   494: aastore
    //   495: aload 23
    //   497: aconst_null
    //   498: aload 24
    //   500: invokevirtual 110	java/lang/reflect/Method:invoke	(Ljava/lang/Object;[Ljava/lang/Object;)Ljava/lang/Object;
    //   503: astore 26
    //   505: aload 20
    //   507: aload 26
    //   509: checkcast 84	java/lang/String
    //   512: invokevirtual 357	android/os/Bundle:getBoolean	(Ljava/lang/String;)Z
    //   515: istore 27
    //   517: aload_0
    //   518: invokevirtual 197	com/db/pwcc/dbmobile/transfer/inputscreen/activities/SepaConfirmationActivity:getIntent	()Landroid/content/Intent;
    //   521: invokevirtual 347	android/content/Intent:getExtras	()Landroid/os/Bundle;
    //   524: astore 28
    //   526: ldc_w 389
    //   529: sipush 251
    //   532: iconst_3
    //   533: invokestatic 120	xxxxxx/uxxxxx:bb00620062bb0062b0062b0062	(Ljava/lang/String;CC)Ljava/lang/String;
    //   536: astore 29
    //   538: iconst_4
    //   539: anewarray 41	java/lang/Class
    //   542: astore 30
    //   544: aload 30
    //   546: iconst_0
    //   547: ldc 84
    //   549: aastore
    //   550: aload 30
    //   552: iconst_1
    //   553: getstatic 90	java/lang/Character:TYPE	Ljava/lang/Class;
    //   556: aastore
    //   557: aload 30
    //   559: iconst_2
    //   560: getstatic 90	java/lang/Character:TYPE	Ljava/lang/Class;
    //   563: aastore
    //   564: aload 30
    //   566: iconst_3
    //   567: getstatic 90	java/lang/Character:TYPE	Ljava/lang/Class;
    //   570: aastore
    //   571: ldc 92
    //   573: aload 29
    //   575: aload 30
    //   577: invokevirtual 96	java/lang/Class:getMethod	(Ljava/lang/String;[Ljava/lang/Class;)Ljava/lang/reflect/Method;
    //   580: astore 31
    //   582: iconst_4
    //   583: anewarray 98	java/lang/Object
    //   586: astore 32
    //   588: aload 32
    //   590: iconst_0
    //   591: ldc_w 391
    //   594: aastore
    //   595: aload 32
    //   597: iconst_1
    //   598: sipush 222
    //   601: invokestatic 104	java/lang/Character:valueOf	(C)Ljava/lang/Character;
    //   604: aastore
    //   605: aload 32
    //   607: iconst_2
    //   608: bipush 88
    //   610: invokestatic 104	java/lang/Character:valueOf	(C)Ljava/lang/Character;
    //   613: aastore
    //   614: aload 32
    //   616: iconst_3
    //   617: iconst_0
    //   618: invokestatic 104	java/lang/Character:valueOf	(C)Ljava/lang/Character;
    //   621: aastore
    //   622: aload 31
    //   624: aconst_null
    //   625: aload 32
    //   627: invokevirtual 110	java/lang/reflect/Method:invoke	(Ljava/lang/Object;[Ljava/lang/Object;)Ljava/lang/Object;
    //   630: astore 34
    //   632: aload 28
    //   634: aload 34
    //   636: checkcast 84	java/lang/String
    //   639: invokevirtual 395	android/os/Bundle:get	(Ljava/lang/String;)Ljava/lang/Object;
    //   642: checkcast 397	com/db/pwcc/dbmobile/model/tan/AuthorizationStatus
    //   645: astore 35
    //   647: aload_0
    //   648: invokevirtual 197	com/db/pwcc/dbmobile/transfer/inputscreen/activities/SepaConfirmationActivity:getIntent	()Landroid/content/Intent;
    //   651: invokevirtual 347	android/content/Intent:getExtras	()Landroid/os/Bundle;
    //   654: astore 36
    //   656: ldc_w 399
    //   659: bipush 94
    //   661: sipush 182
    //   664: iconst_2
    //   665: invokestatic 82	xxxxxx/uxxxxx:bbbb0062b0062b0062b0062	(Ljava/lang/String;CCC)Ljava/lang/String;
    //   668: astore 37
    //   670: iconst_4
    //   671: anewarray 41	java/lang/Class
    //   674: astore 38
    //   676: aload 38
    //   678: iconst_0
    //   679: ldc 84
    //   681: aastore
    //   682: aload 38
    //   684: iconst_1
    //   685: getstatic 90	java/lang/Character:TYPE	Ljava/lang/Class;
    //   688: aastore
    //   689: aload 38
    //   691: iconst_2
    //   692: getstatic 90	java/lang/Character:TYPE	Ljava/lang/Class;
    //   695: aastore
    //   696: aload 38
    //   698: iconst_3
    //   699: getstatic 90	java/lang/Character:TYPE	Ljava/lang/Class;
    //   702: aastore
    //   703: ldc 92
    //   705: aload 37
    //   707: aload 38
    //   709: invokevirtual 96	java/lang/Class:getMethod	(Ljava/lang/String;[Ljava/lang/Class;)Ljava/lang/reflect/Method;
    //   712: astore 39
    //   714: iconst_4
    //   715: anewarray 98	java/lang/Object
    //   718: astore 40
    //   720: aload 40
    //   722: iconst_0
    //   723: ldc_w 401
    //   726: aastore
    //   727: aload 40
    //   729: iconst_1
    //   730: sipush 159
    //   733: invokestatic 104	java/lang/Character:valueOf	(C)Ljava/lang/Character;
    //   736: aastore
    //   737: aload 40
    //   739: iconst_2
    //   740: sipush 225
    //   743: invokestatic 104	java/lang/Character:valueOf	(C)Ljava/lang/Character;
    //   746: aastore
    //   747: aload 40
    //   749: iconst_3
    //   750: iconst_0
    //   751: invokestatic 104	java/lang/Character:valueOf	(C)Ljava/lang/Character;
    //   754: aastore
    //   755: aload 39
    //   757: aconst_null
    //   758: aload 40
    //   760: invokevirtual 110	java/lang/reflect/Method:invoke	(Ljava/lang/Object;[Ljava/lang/Object;)Ljava/lang/Object;
    //   763: astore 42
    //   765: aload_0
    //   766: aload 19
    //   768: iload 27
    //   770: aload 36
    //   772: aload 42
    //   774: checkcast 84	java/lang/String
    //   777: invokevirtual 395	android/os/Bundle:get	(Ljava/lang/String;)Ljava/lang/Object;
    //   780: checkcast 403	com/db/pwcc/dbmobile/model/tan/Authorization
    //   783: aload 35
    //   785: invokevirtual 407	com/db/pwcc/dbmobile/transfer/inputscreen/activities/SepaConfirmationActivity:setTransactionData	(Ljava/lang/String;ZLcom/db/pwcc/dbmobile/model/tan/Authorization;Lcom/db/pwcc/dbmobile/model/tan/AuthorizationStatus;)V
    //   788: aload_0
    //   789: aload_0
    //   790: getfield 54	com/db/pwcc/dbmobile/transfer/inputscreen/activities/SepaConfirmationActivity:transactionReceived	Lcom/db/pwcc/dbmobile/model/sepa/SepaTransaction;
    //   793: invokevirtual 412	com/db/pwcc/dbmobile/model/sepa/SepaTransaction:getTargetAccount	()Ljava/lang/String;
    //   796: aload_0
    //   797: getfield 54	com/db/pwcc/dbmobile/transfer/inputscreen/activities/SepaConfirmationActivity:transactionReceived	Lcom/db/pwcc/dbmobile/model/sepa/SepaTransaction;
    //   800: invokevirtual 415	com/db/pwcc/dbmobile/model/sepa/SepaTransaction:getBeneficiary	()Ljava/lang/String;
    //   803: aload_0
    //   804: getfield 54	com/db/pwcc/dbmobile/transfer/inputscreen/activities/SepaConfirmationActivity:transactionReceived	Lcom/db/pwcc/dbmobile/model/sepa/SepaTransaction;
    //   807: invokevirtual 418	com/db/pwcc/dbmobile/model/sepa/SepaTransaction:getSourceAccount	()Ljava/lang/String;
    //   810: invokevirtual 422	com/db/pwcc/dbmobile/transfer/inputscreen/activities/SepaConfirmationActivity:setFriendPicture	(Ljava/lang/String;Ljava/lang/String;Ljava/lang/String;)V
    //   813: aload_0
    //   814: invokevirtual 197	com/db/pwcc/dbmobile/transfer/inputscreen/activities/SepaConfirmationActivity:getIntent	()Landroid/content/Intent;
    //   817: astore 43
    //   819: ldc_w 424
    //   822: bipush 97
    //   824: iconst_1
    //   825: invokestatic 120	xxxxxx/uxxxxx:bb00620062bb0062b0062b0062	(Ljava/lang/String;CC)Ljava/lang/String;
    //   828: astore 44
    //   830: iconst_3
    //   831: anewarray 41	java/lang/Class
    //   834: astore 45
    //   836: aload 45
    //   838: iconst_0
    //   839: ldc 84
    //   841: aastore
    //   842: aload 45
    //   844: iconst_1
    //   845: getstatic 90	java/lang/Character:TYPE	Ljava/lang/Class;
    //   848: aastore
    //   849: aload 45
    //   851: iconst_2
    //   852: getstatic 90	java/lang/Character:TYPE	Ljava/lang/Class;
    //   855: aastore
    //   856: ldc 92
    //   858: aload 44
    //   860: aload 45
    //   862: invokevirtual 96	java/lang/Class:getMethod	(Ljava/lang/String;[Ljava/lang/Class;)Ljava/lang/reflect/Method;
    //   865: astore 46
    //   867: iconst_3
    //   868: anewarray 98	java/lang/Object
    //   871: astore 47
    //   873: aload 47
    //   875: iconst_0
    //   876: ldc_w 426
    //   879: aastore
    //   880: aload 47
    //   882: iconst_1
    //   883: bipush 88
    //   885: invokestatic 104	java/lang/Character:valueOf	(C)Ljava/lang/Character;
    //   888: aastore
    //   889: aload 47
    //   891: iconst_2
    //   892: iconst_2
    //   893: invokestatic 104	java/lang/Character:valueOf	(C)Ljava/lang/Character;
    //   896: aastore
    //   897: aload 46
    //   899: aconst_null
    //   900: aload 47
    //   902: invokevirtual 110	java/lang/reflect/Method:invoke	(Ljava/lang/Object;[Ljava/lang/Object;)Ljava/lang/Object;
    //   905: astore 49
    //   907: aload 43
    //   909: aload 49
    //   911: checkcast 84	java/lang/String
    //   914: invokevirtual 429	android/content/Intent:hasExtra	(Ljava/lang/String;)Z
    //   917: ifeq +167 -> 1084
    //   920: invokestatic 39	com/db/pwcc/dbmobile/transfer/inputscreen/activities/SepaConfirmationActivity:b0074007400740074007400740074tt	()I
    //   923: invokestatic 36	com/db/pwcc/dbmobile/transfer/inputscreen/activities/SepaConfirmationActivity:btt0074tttt0074t	()I
    //   926: iadd
    //   927: invokestatic 39	com/db/pwcc/dbmobile/transfer/inputscreen/activities/SepaConfirmationActivity:b0074007400740074007400740074tt	()I
    //   930: imul
    //   931: getstatic 30	com/db/pwcc/dbmobile/transfer/inputscreen/activities/SepaConfirmationActivity:bt0074ttttt0074t	I
    //   934: irem
    //   935: getstatic 32	com/db/pwcc/dbmobile/transfer/inputscreen/activities/SepaConfirmationActivity:bttttttt0074t	I
    //   938: if_icmpeq +15 -> 953
    //   941: invokestatic 39	com/db/pwcc/dbmobile/transfer/inputscreen/activities/SepaConfirmationActivity:b0074007400740074007400740074tt	()I
    //   944: putstatic 26	com/db/pwcc/dbmobile/transfer/inputscreen/activities/SepaConfirmationActivity:b00740074ttttt0074t	I
    //   947: invokestatic 39	com/db/pwcc/dbmobile/transfer/inputscreen/activities/SepaConfirmationActivity:b0074007400740074007400740074tt	()I
    //   950: putstatic 32	com/db/pwcc/dbmobile/transfer/inputscreen/activities/SepaConfirmationActivity:bttttttt0074t	I
    //   953: aload_0
    //   954: getfield 433	com/db/pwcc/dbmobile/transfer/inputscreen/activities/SepaConfirmationActivity:friendsRepository	Luuuuuu/yyhhhh;
    //   957: astore 50
    //   959: aload_0
    //   960: invokevirtual 197	com/db/pwcc/dbmobile/transfer/inputscreen/activities/SepaConfirmationActivity:getIntent	()Landroid/content/Intent;
    //   963: invokevirtual 347	android/content/Intent:getExtras	()Landroid/os/Bundle;
    //   966: astore 51
    //   968: ldc_w 435
    //   971: bipush 44
    //   973: iconst_1
    //   974: invokestatic 120	xxxxxx/uxxxxx:bb00620062bb0062b0062b0062	(Ljava/lang/String;CC)Ljava/lang/String;
    //   977: astore 52
    //   979: iconst_3
    //   980: anewarray 41	java/lang/Class
    //   983: astore 53
    //   985: aload 53
    //   987: iconst_0
    //   988: ldc 84
    //   990: aastore
    //   991: aload 53
    //   993: iconst_1
    //   994: getstatic 90	java/lang/Character:TYPE	Ljava/lang/Class;
    //   997: aastore
    //   998: aload 53
    //   1000: iconst_2
    //   1001: getstatic 90	java/lang/Character:TYPE	Ljava/lang/Class;
    //   1004: aastore
    //   1005: ldc 92
    //   1007: aload 52
    //   1009: aload 53
    //   1011: invokevirtual 96	java/lang/Class:getMethod	(Ljava/lang/String;[Ljava/lang/Class;)Ljava/lang/reflect/Method;
    //   1014: astore 54
    //   1016: iconst_3
    //   1017: anewarray 98	java/lang/Object
    //   1020: astore 55
    //   1022: aload 55
    //   1024: iconst_0
    //   1025: ldc_w 437
    //   1028: aastore
    //   1029: aload 55
    //   1031: iconst_1
    //   1032: sipush 141
    //   1035: invokestatic 104	java/lang/Character:valueOf	(C)Ljava/lang/Character;
    //   1038: aastore
    //   1039: aload 55
    //   1041: iconst_2
    //   1042: iconst_5
    //   1043: invokestatic 104	java/lang/Character:valueOf	(C)Ljava/lang/Character;
    //   1046: aastore
    //   1047: aload 54
    //   1049: aconst_null
    //   1050: aload 55
    //   1052: invokevirtual 110	java/lang/reflect/Method:invoke	(Ljava/lang/Object;[Ljava/lang/Object;)Ljava/lang/Object;
    //   1055: astore 57
    //   1057: aload 50
    //   1059: aload 51
    //   1061: aload 57
    //   1063: checkcast 84	java/lang/String
    //   1066: invokevirtual 441	android/os/Bundle:getLong	(Ljava/lang/String;)J
    //   1069: invokeinterface 447 3 0
    //   1074: ifnull +10 -> 1084
    //   1077: aload_0
    //   1078: getfield 191	com/db/pwcc/dbmobile/transfer/inputscreen/activities/SepaConfirmationActivity:tanModule	Lcom/db/pwcc/dbmobile/tan/ui/TanModule;
    //   1081: invokevirtual 450	com/db/pwcc/dbmobile/tan/ui/TanModule:disableNewTransferButton	()V
    //   1084: aload_0
    //   1085: invokevirtual 451	com/db/pwcc/dbmobile/transfer/inputscreen/activities/SepaConfirmationActivity:initDbToolbar	()V
    //   1088: aload_0
    //   1089: aload_0
    //   1090: invokevirtual 454	com/db/pwcc/dbmobile/transfer/inputscreen/activities/SepaConfirmationActivity:setBoldText	(Landroid/app/Activity;)V
    //   1093: return
    //   1094: astore 56
    //   1096: aload 56
    //   1098: invokevirtual 161	java/lang/reflect/InvocationTargetException:getCause	()Ljava/lang/Throwable;
    //   1101: athrow
    //   1102: astore 6
    //   1104: aload 6
    //   1106: invokevirtual 161	java/lang/reflect/InvocationTargetException:getCause	()Ljava/lang/Throwable;
    //   1109: athrow
    //   1110: astore 33
    //   1112: aload 33
    //   1114: invokevirtual 161	java/lang/reflect/InvocationTargetException:getCause	()Ljava/lang/Throwable;
    //   1117: athrow
    //   1118: astore 41
    //   1120: aload 41
    //   1122: invokevirtual 161	java/lang/reflect/InvocationTargetException:getCause	()Ljava/lang/Throwable;
    //   1125: athrow
    //   1126: astore 17
    //   1128: aload 17
    //   1130: invokevirtual 161	java/lang/reflect/InvocationTargetException:getCause	()Ljava/lang/Throwable;
    //   1133: athrow
    //   1134: astore 48
    //   1136: aload 48
    //   1138: invokevirtual 161	java/lang/reflect/InvocationTargetException:getCause	()Ljava/lang/Throwable;
    //   1141: athrow
    //   1142: astore 25
    //   1144: aload 25
    //   1146: invokevirtual 161	java/lang/reflect/InvocationTargetException:getCause	()Ljava/lang/Throwable;
    //   1149: athrow
    // Local variable table:
    //   start	length	slot	name	signature
    //   0	1150	0	this	SepaConfirmationActivity
    //   7	83	1	localBundle1	android.os.Bundle
    //   17	26	2	str1	String
    //   22	22	3	arrayOfClass1	Class[]
    //   47	33	4	localMethod1	Method
    //   53	30	5	arrayOfObject1	Object[]
    //   1102	3	6	localInvocationTargetException1	InvocationTargetException
    //   87	4	7	localObject1	Object
    //   98	50	8	bool1	boolean
    //   103	11	9	i	int
    //   215	49	10	localTanModule	TanModule
    //   220	11	11	j	int
    //   286	112	12	localBundle2	android.os.Bundle
    //   300	38	13	str2	String
    //   306	34	14	arrayOfClass2	Class[]
    //   344	44	15	localMethod2	Method
    //   350	41	16	arrayOfObject2	Object[]
    //   1126	3	17	localInvocationTargetException2	InvocationTargetException
    //   395	5	18	localObject2	Object
    //   407	360	19	str3	String
    //   416	90	20	localBundle3	android.os.Bundle
    //   426	31	21	str4	String
    //   432	27	22	arrayOfClass3	Class[]
    //   463	33	23	localMethod3	Method
    //   469	30	24	arrayOfObject3	Object[]
    //   1142	3	25	localInvocationTargetException3	InvocationTargetException
    //   503	5	26	localObject3	Object
    //   515	254	27	bool2	boolean
    //   524	109	28	localBundle4	android.os.Bundle
    //   536	38	29	str5	String
    //   542	34	30	arrayOfClass4	Class[]
    //   580	43	31	localMethod4	Method
    //   586	40	32	arrayOfObject4	Object[]
    //   1110	3	33	localInvocationTargetException4	InvocationTargetException
    //   630	5	34	localObject4	Object
    //   645	139	35	localAuthorizationStatus	AuthorizationStatus
    //   654	117	36	localBundle5	android.os.Bundle
    //   668	38	37	str6	String
    //   674	34	38	arrayOfClass5	Class[]
    //   712	44	39	localMethod5	Method
    //   718	41	40	arrayOfObject5	Object[]
    //   1118	3	41	localInvocationTargetException5	InvocationTargetException
    //   763	10	42	localObject5	Object
    //   817	91	43	localIntent	Intent
    //   828	31	44	str7	String
    //   834	27	45	arrayOfClass6	Class[]
    //   865	33	46	localMethod6	Method
    //   871	30	47	arrayOfObject6	Object[]
    //   1134	3	48	localInvocationTargetException6	InvocationTargetException
    //   905	5	49	localObject6	Object
    //   957	101	50	localYyhhhh	uuuuuu.yyhhhh
    //   966	94	51	localBundle6	android.os.Bundle
    //   977	31	52	str8	String
    //   983	27	53	arrayOfClass7	Class[]
    //   1014	34	54	localMethod7	Method
    //   1020	31	55	arrayOfObject7	Object[]
    //   1094	3	56	localInvocationTargetException7	InvocationTargetException
    //   1055	7	57	localObject7	Object
    // Exception table:
    //   from	to	target	type
    //   1047	1057	1094	java/lang/reflect/InvocationTargetException
    //   79	89	1102	java/lang/reflect/InvocationTargetException
    //   622	632	1110	java/lang/reflect/InvocationTargetException
    //   755	765	1118	java/lang/reflect/InvocationTargetException
    //   387	397	1126	java/lang/reflect/InvocationTargetException
    //   897	907	1134	java/lang/reflect/InvocationTargetException
    //   495	505	1142	java/lang/reflect/InvocationTargetException
  }
  
  /* Error */
  public void onBackPressed()
  {
    // Byte code:
    //   0: aload_0
    //   1: getfield 460	com/db/pwcc/dbmobile/transfer/inputscreen/activities/SepaConfirmationActivity:isUiDisabled	Z
    //   4: ifne +129 -> 133
    //   7: aload_0
    //   8: invokespecial 462	com/db/pwcc/dbmobile/transfer/inputscreen/activities/ConfirmationActivity:onBackPressed	()V
    //   11: aload_0
    //   12: getfield 52	com/db/pwcc/dbmobile/transfer/inputscreen/activities/SepaConfirmationActivity:presenter	Luuuuuu/nnnntn;
    //   15: astore_1
    //   16: ldc_w 359
    //   19: ldc_w 464
    //   22: sipush 223
    //   25: iconst_3
    //   26: invokestatic 120	xxxxxx/uxxxxx:bb00620062bb0062b0062b0062	(Ljava/lang/String;CC)Ljava/lang/String;
    //   29: iconst_0
    //   30: anewarray 41	java/lang/Class
    //   33: invokevirtual 96	java/lang/Class:getMethod	(Ljava/lang/String;[Ljava/lang/Class;)Ljava/lang/reflect/Method;
    //   36: astore_2
    //   37: iconst_0
    //   38: anewarray 98	java/lang/Object
    //   41: astore_3
    //   42: aload_2
    //   43: aload_1
    //   44: aload_3
    //   45: invokevirtual 110	java/lang/reflect/Method:invoke	(Ljava/lang/Object;[Ljava/lang/Object;)Ljava/lang/Object;
    //   48: astore 5
    //   50: aload 5
    //   52: checkcast 466	java/lang/Boolean
    //   55: invokevirtual 470	java/lang/Boolean:booleanValue	()Z
    //   58: ifeq +14 -> 72
    //   61: aload_0
    //   62: invokevirtual 216	com/db/pwcc/dbmobile/transfer/inputscreen/activities/SepaConfirmationActivity:closeActivity	()V
    //   65: iconst_m1
    //   66: newarray int
    //   68: pop
    //   69: goto -4 -> 65
    //   72: aload_0
    //   73: getfield 52	com/db/pwcc/dbmobile/transfer/inputscreen/activities/SepaConfirmationActivity:presenter	Luuuuuu/nnnntn;
    //   76: astore 6
    //   78: ldc_w 359
    //   81: ldc_w 472
    //   84: sipush 143
    //   87: iconst_1
    //   88: invokestatic 120	xxxxxx/uxxxxx:bb00620062bb0062b0062b0062	(Ljava/lang/String;CC)Ljava/lang/String;
    //   91: iconst_0
    //   92: anewarray 41	java/lang/Class
    //   95: invokevirtual 96	java/lang/Class:getMethod	(Ljava/lang/String;[Ljava/lang/Class;)Ljava/lang/reflect/Method;
    //   98: astore 7
    //   100: iconst_0
    //   101: anewarray 98	java/lang/Object
    //   104: astore 8
    //   106: aload 7
    //   108: aload 6
    //   110: aload 8
    //   112: invokevirtual 110	java/lang/reflect/Method:invoke	(Ljava/lang/Object;[Ljava/lang/Object;)Ljava/lang/Object;
    //   115: astore 10
    //   117: aload 10
    //   119: checkcast 466	java/lang/Boolean
    //   122: invokevirtual 470	java/lang/Boolean:booleanValue	()Z
    //   125: ifeq +102 -> 227
    //   128: aload_0
    //   129: iconst_0
    //   130: invokevirtual 474	com/db/pwcc/dbmobile/transfer/inputscreen/activities/SepaConfirmationActivity:goBackToInputScreen	(Z)V
    //   133: return
    //   134: astore 15
    //   136: bipush 35
    //   138: putstatic 26	com/db/pwcc/dbmobile/transfer/inputscreen/activities/SepaConfirmationActivity:b00740074ttttt0074t	I
    //   141: getstatic 26	com/db/pwcc/dbmobile/transfer/inputscreen/activities/SepaConfirmationActivity:b00740074ttttt0074t	I
    //   144: getstatic 28	com/db/pwcc/dbmobile/transfer/inputscreen/activities/SepaConfirmationActivity:b0074tttttt0074t	I
    //   147: iadd
    //   148: getstatic 26	com/db/pwcc/dbmobile/transfer/inputscreen/activities/SepaConfirmationActivity:b00740074ttttt0074t	I
    //   151: imul
    //   152: invokestatic 62	com/db/pwcc/dbmobile/transfer/inputscreen/activities/SepaConfirmationActivity:b0074t0074tttt0074t	()I
    //   155: irem
    //   156: getstatic 32	com/db/pwcc/dbmobile/transfer/inputscreen/activities/SepaConfirmationActivity:bttttttt0074t	I
    //   159: if_icmpeq +50 -> 209
    //   162: invokestatic 39	com/db/pwcc/dbmobile/transfer/inputscreen/activities/SepaConfirmationActivity:b0074007400740074007400740074tt	()I
    //   165: putstatic 26	com/db/pwcc/dbmobile/transfer/inputscreen/activities/SepaConfirmationActivity:b00740074ttttt0074t	I
    //   168: invokestatic 39	com/db/pwcc/dbmobile/transfer/inputscreen/activities/SepaConfirmationActivity:b0074007400740074007400740074tt	()I
    //   171: istore 17
    //   173: getstatic 26	com/db/pwcc/dbmobile/transfer/inputscreen/activities/SepaConfirmationActivity:b00740074ttttt0074t	I
    //   176: getstatic 28	com/db/pwcc/dbmobile/transfer/inputscreen/activities/SepaConfirmationActivity:b0074tttttt0074t	I
    //   179: iadd
    //   180: getstatic 26	com/db/pwcc/dbmobile/transfer/inputscreen/activities/SepaConfirmationActivity:b00740074ttttt0074t	I
    //   183: imul
    //   184: getstatic 30	com/db/pwcc/dbmobile/transfer/inputscreen/activities/SepaConfirmationActivity:bt0074ttttt0074t	I
    //   187: irem
    //   188: getstatic 32	com/db/pwcc/dbmobile/transfer/inputscreen/activities/SepaConfirmationActivity:bttttttt0074t	I
    //   191: if_icmpeq +13 -> 204
    //   194: bipush 57
    //   196: putstatic 26	com/db/pwcc/dbmobile/transfer/inputscreen/activities/SepaConfirmationActivity:b00740074ttttt0074t	I
    //   199: bipush 7
    //   201: putstatic 32	com/db/pwcc/dbmobile/transfer/inputscreen/activities/SepaConfirmationActivity:bttttttt0074t	I
    //   204: iload 17
    //   206: putstatic 32	com/db/pwcc/dbmobile/transfer/inputscreen/activities/SepaConfirmationActivity:bttttttt0074t	I
    //   209: iload 14
    //   211: iconst_0
    //   212: idiv
    //   213: istore 14
    //   215: goto -74 -> 141
    //   218: astore 16
    //   220: invokestatic 39	com/db/pwcc/dbmobile/transfer/inputscreen/activities/SepaConfirmationActivity:b0074007400740074007400740074tt	()I
    //   223: putstatic 26	com/db/pwcc/dbmobile/transfer/inputscreen/activities/SepaConfirmationActivity:b00740074ttttt0074t	I
    //   226: return
    //   227: aload_0
    //   228: invokevirtual 216	com/db/pwcc/dbmobile/transfer/inputscreen/activities/SepaConfirmationActivity:closeActivity	()V
    //   231: iconst_m1
    //   232: newarray int
    //   234: pop
    //   235: goto -4 -> 231
    //   238: astore 11
    //   240: invokestatic 39	com/db/pwcc/dbmobile/transfer/inputscreen/activities/SepaConfirmationActivity:b0074007400740074007400740074tt	()I
    //   243: putstatic 26	com/db/pwcc/dbmobile/transfer/inputscreen/activities/SepaConfirmationActivity:b00740074ttttt0074t	I
    //   246: return
    //   247: astore 4
    //   249: aload 4
    //   251: invokevirtual 161	java/lang/reflect/InvocationTargetException:getCause	()Ljava/lang/Throwable;
    //   254: athrow
    //   255: astore 13
    //   257: bipush 58
    //   259: putstatic 26	com/db/pwcc/dbmobile/transfer/inputscreen/activities/SepaConfirmationActivity:b00740074ttttt0074t	I
    //   262: iconst_5
    //   263: istore 14
    //   265: iload 14
    //   267: iconst_0
    //   268: idiv
    //   269: istore 14
    //   271: goto -6 -> 265
    //   274: astore 9
    //   276: aload 9
    //   278: invokevirtual 161	java/lang/reflect/InvocationTargetException:getCause	()Ljava/lang/Throwable;
    //   281: athrow
    // Local variable table:
    //   start	length	slot	name	signature
    //   0	282	0	this	SepaConfirmationActivity
    //   15	29	1	localNnnntn1	nnnntn
    //   36	7	2	localMethod1	Method
    //   41	4	3	arrayOfObject1	Object[]
    //   247	3	4	localInvocationTargetException1	InvocationTargetException
    //   48	3	5	localObject1	Object
    //   76	33	6	localNnnntn2	nnnntn
    //   98	9	7	localMethod2	Method
    //   104	7	8	arrayOfObject2	Object[]
    //   274	3	9	localInvocationTargetException2	InvocationTargetException
    //   115	3	10	localObject2	Object
    //   238	1	11	localException1	Exception
    //   255	1	13	localException2	Exception
    //   209	61	14	i	int
    //   134	1	15	localException3	Exception
    //   218	1	16	localException4	Exception
    //   171	34	17	j	int
    // Exception table:
    //   from	to	target	type
    //   265	271	134	java/lang/Exception
    //   209	215	218	java/lang/Exception
    //   231	235	238	java/lang/Exception
    //   42	50	247	java/lang/reflect/InvocationTargetException
    //   65	69	255	java/lang/Exception
    //   106	117	274	java/lang/reflect/InvocationTargetException
  }
  
  /* Error */
  public void onCreate(android.os.Bundle paramBundle)
  {
    // Byte code:
    //   0: aload_0
    //   1: invokevirtual 480	com/db/pwcc/dbmobile/transfer/inputscreen/activities/SepaConfirmationActivity:getApplicationContext	()Landroid/content/Context;
    //   4: astore_2
    //   5: ldc_w 482
    //   8: ldc_w 484
    //   11: bipush 73
    //   13: iconst_1
    //   14: invokestatic 120	xxxxxx/uxxxxx:bb00620062bb0062b0062b0062	(Ljava/lang/String;CC)Ljava/lang/String;
    //   17: iconst_1
    //   18: anewarray 41	java/lang/Class
    //   21: dup
    //   22: iconst_0
    //   23: ldc_w 486
    //   26: aastore
    //   27: invokevirtual 96	java/lang/Class:getMethod	(Ljava/lang/String;[Ljava/lang/Class;)Ljava/lang/reflect/Method;
    //   30: astore_3
    //   31: iconst_1
    //   32: anewarray 98	java/lang/Object
    //   35: dup
    //   36: iconst_0
    //   37: aload_2
    //   38: aastore
    //   39: astore 4
    //   41: aload_3
    //   42: aconst_null
    //   43: aload 4
    //   45: invokevirtual 110	java/lang/reflect/Method:invoke	(Ljava/lang/Object;[Ljava/lang/Object;)Ljava/lang/Object;
    //   48: pop
    //   49: aload_0
    //   50: invokevirtual 480	com/db/pwcc/dbmobile/transfer/inputscreen/activities/SepaConfirmationActivity:getApplicationContext	()Landroid/content/Context;
    //   53: astore 7
    //   55: ldc_w 488
    //   58: ldc_w 490
    //   61: bipush 40
    //   63: bipush 15
    //   65: iconst_0
    //   66: invokestatic 82	xxxxxx/uxxxxx:bbbb0062b0062b0062b0062	(Ljava/lang/String;CCC)Ljava/lang/String;
    //   69: iconst_1
    //   70: anewarray 41	java/lang/Class
    //   73: dup
    //   74: iconst_0
    //   75: ldc_w 486
    //   78: aastore
    //   79: invokevirtual 96	java/lang/Class:getMethod	(Ljava/lang/String;[Ljava/lang/Class;)Ljava/lang/reflect/Method;
    //   82: astore 8
    //   84: iconst_1
    //   85: anewarray 98	java/lang/Object
    //   88: dup
    //   89: iconst_0
    //   90: aload 7
    //   92: aastore
    //   93: astore 9
    //   95: aload 8
    //   97: aconst_null
    //   98: aload 9
    //   100: invokevirtual 110	java/lang/reflect/Method:invoke	(Ljava/lang/Object;[Ljava/lang/Object;)Ljava/lang/Object;
    //   103: pop
    //   104: aload_0
    //   105: invokevirtual 480	com/db/pwcc/dbmobile/transfer/inputscreen/activities/SepaConfirmationActivity:getApplicationContext	()Landroid/content/Context;
    //   108: invokestatic 496	uuuuuu/uppupu:b0072r0072r00720072rr0072	(Landroid/content/Context;)V
    //   111: aload_0
    //   112: aload_1
    //   113: invokespecial 498	com/db/pwcc/dbmobile/transfer/inputscreen/activities/ConfirmationActivity:onCreate	(Landroid/os/Bundle;)V
    //   116: aload_0
    //   117: invokevirtual 499	com/db/pwcc/dbmobile/transfer/inputscreen/activities/SepaConfirmationActivity:initView	()V
    //   120: getstatic 26	com/db/pwcc/dbmobile/transfer/inputscreen/activities/SepaConfirmationActivity:b00740074ttttt0074t	I
    //   123: invokestatic 36	com/db/pwcc/dbmobile/transfer/inputscreen/activities/SepaConfirmationActivity:btt0074tttt0074t	()I
    //   126: iadd
    //   127: getstatic 26	com/db/pwcc/dbmobile/transfer/inputscreen/activities/SepaConfirmationActivity:b00740074ttttt0074t	I
    //   130: imul
    //   131: getstatic 30	com/db/pwcc/dbmobile/transfer/inputscreen/activities/SepaConfirmationActivity:bt0074ttttt0074t	I
    //   134: irem
    //   135: istore 12
    //   137: invokestatic 39	com/db/pwcc/dbmobile/transfer/inputscreen/activities/SepaConfirmationActivity:b0074007400740074007400740074tt	()I
    //   140: istore 13
    //   142: iload 13
    //   144: iload 13
    //   146: getstatic 28	com/db/pwcc/dbmobile/transfer/inputscreen/activities/SepaConfirmationActivity:b0074tttttt0074t	I
    //   149: iadd
    //   150: imul
    //   151: getstatic 30	com/db/pwcc/dbmobile/transfer/inputscreen/activities/SepaConfirmationActivity:bt0074ttttt0074t	I
    //   154: irem
    //   155: tableswitch	default:+17->172, 0:+28->183
    //   172: invokestatic 39	com/db/pwcc/dbmobile/transfer/inputscreen/activities/SepaConfirmationActivity:b0074007400740074007400740074tt	()I
    //   175: putstatic 26	com/db/pwcc/dbmobile/transfer/inputscreen/activities/SepaConfirmationActivity:b00740074ttttt0074t	I
    //   178: bipush 33
    //   180: putstatic 32	com/db/pwcc/dbmobile/transfer/inputscreen/activities/SepaConfirmationActivity:bttttttt0074t	I
    //   183: iload 12
    //   185: getstatic 32	com/db/pwcc/dbmobile/transfer/inputscreen/activities/SepaConfirmationActivity:bttttttt0074t	I
    //   188: if_icmpeq +93 -> 281
    //   191: invokestatic 39	com/db/pwcc/dbmobile/transfer/inputscreen/activities/SepaConfirmationActivity:b0074007400740074007400740074tt	()I
    //   194: putstatic 26	com/db/pwcc/dbmobile/transfer/inputscreen/activities/SepaConfirmationActivity:b00740074ttttt0074t	I
    //   197: getstatic 26	com/db/pwcc/dbmobile/transfer/inputscreen/activities/SepaConfirmationActivity:b00740074ttttt0074t	I
    //   200: istore 14
    //   202: iload 14
    //   204: iload 14
    //   206: getstatic 28	com/db/pwcc/dbmobile/transfer/inputscreen/activities/SepaConfirmationActivity:b0074tttttt0074t	I
    //   209: iadd
    //   210: imul
    //   211: getstatic 30	com/db/pwcc/dbmobile/transfer/inputscreen/activities/SepaConfirmationActivity:bt0074ttttt0074t	I
    //   214: irem
    //   215: tableswitch	default:+17->232, 0:+28->243
    //   232: invokestatic 39	com/db/pwcc/dbmobile/transfer/inputscreen/activities/SepaConfirmationActivity:b0074007400740074007400740074tt	()I
    //   235: putstatic 26	com/db/pwcc/dbmobile/transfer/inputscreen/activities/SepaConfirmationActivity:b00740074ttttt0074t	I
    //   238: bipush 53
    //   240: putstatic 32	com/db/pwcc/dbmobile/transfer/inputscreen/activities/SepaConfirmationActivity:bttttttt0074t	I
    //   243: getstatic 26	com/db/pwcc/dbmobile/transfer/inputscreen/activities/SepaConfirmationActivity:b00740074ttttt0074t	I
    //   246: getstatic 28	com/db/pwcc/dbmobile/transfer/inputscreen/activities/SepaConfirmationActivity:b0074tttttt0074t	I
    //   249: iadd
    //   250: getstatic 26	com/db/pwcc/dbmobile/transfer/inputscreen/activities/SepaConfirmationActivity:b00740074ttttt0074t	I
    //   253: imul
    //   254: getstatic 30	com/db/pwcc/dbmobile/transfer/inputscreen/activities/SepaConfirmationActivity:bt0074ttttt0074t	I
    //   257: irem
    //   258: getstatic 32	com/db/pwcc/dbmobile/transfer/inputscreen/activities/SepaConfirmationActivity:bttttttt0074t	I
    //   261: if_icmpeq +14 -> 275
    //   264: invokestatic 39	com/db/pwcc/dbmobile/transfer/inputscreen/activities/SepaConfirmationActivity:b0074007400740074007400740074tt	()I
    //   267: putstatic 26	com/db/pwcc/dbmobile/transfer/inputscreen/activities/SepaConfirmationActivity:b00740074ttttt0074t	I
    //   270: bipush 6
    //   272: putstatic 32	com/db/pwcc/dbmobile/transfer/inputscreen/activities/SepaConfirmationActivity:bttttttt0074t	I
    //   275: invokestatic 39	com/db/pwcc/dbmobile/transfer/inputscreen/activities/SepaConfirmationActivity:b0074007400740074007400740074tt	()I
    //   278: putstatic 32	com/db/pwcc/dbmobile/transfer/inputscreen/activities/SepaConfirmationActivity:bttttttt0074t	I
    //   281: aload_0
    //   282: getstatic 502	com/db/pwcc/dbmobile/transfer/R$id:confirmation_container	I
    //   285: invokevirtual 243	com/db/pwcc/dbmobile/transfer/inputscreen/activities/SepaConfirmationActivity:findViewById	(I)Landroid/view/View;
    //   288: invokestatic 508	uuuuuu/nononn:b006B006B006Bk006B006Bk006Bk006B	(Landroid/view/View;)V
    //   291: return
    //   292: astore 10
    //   294: aload 10
    //   296: invokevirtual 161	java/lang/reflect/InvocationTargetException:getCause	()Ljava/lang/Throwable;
    //   299: athrow
    //   300: astore 5
    //   302: aload 5
    //   304: invokevirtual 161	java/lang/reflect/InvocationTargetException:getCause	()Ljava/lang/Throwable;
    //   307: athrow
    // Local variable table:
    //   start	length	slot	name	signature
    //   0	308	0	this	SepaConfirmationActivity
    //   0	308	1	paramBundle	android.os.Bundle
    //   4	34	2	localContext1	Context
    //   30	12	3	localMethod1	Method
    //   39	5	4	arrayOfObject1	Object[]
    //   300	3	5	localInvocationTargetException1	InvocationTargetException
    //   53	38	7	localContext2	Context
    //   82	14	8	localMethod2	Method
    //   93	6	9	arrayOfObject2	Object[]
    //   292	3	10	localInvocationTargetException2	InvocationTargetException
    //   135	54	12	i	int
    //   140	11	13	j	int
    //   200	11	14	k	int
    // Exception table:
    //   from	to	target	type
    //   95	104	292	java/lang/reflect/InvocationTargetException
    //   41	49	300	java/lang/reflect/InvocationTargetException
  }
  
  /* Error */
  public void onRestoreInstanceState(android.os.Bundle paramBundle)
  {
    // Byte code:
    //   0: aload_0
    //   1: aload_1
    //   2: invokespecial 511	com/db/pwcc/dbmobile/transfer/inputscreen/activities/ConfirmationActivity:onRestoreInstanceState	(Landroid/os/Bundle;)V
    //   5: getstatic 26	com/db/pwcc/dbmobile/transfer/inputscreen/activities/SepaConfirmationActivity:b00740074ttttt0074t	I
    //   8: getstatic 28	com/db/pwcc/dbmobile/transfer/inputscreen/activities/SepaConfirmationActivity:b0074tttttt0074t	I
    //   11: iadd
    //   12: getstatic 26	com/db/pwcc/dbmobile/transfer/inputscreen/activities/SepaConfirmationActivity:b00740074ttttt0074t	I
    //   15: imul
    //   16: getstatic 30	com/db/pwcc/dbmobile/transfer/inputscreen/activities/SepaConfirmationActivity:bt0074ttttt0074t	I
    //   19: irem
    //   20: getstatic 32	com/db/pwcc/dbmobile/transfer/inputscreen/activities/SepaConfirmationActivity:bttttttt0074t	I
    //   23: if_icmpeq +14 -> 37
    //   26: bipush 93
    //   28: putstatic 26	com/db/pwcc/dbmobile/transfer/inputscreen/activities/SepaConfirmationActivity:b00740074ttttt0074t	I
    //   31: invokestatic 39	com/db/pwcc/dbmobile/transfer/inputscreen/activities/SepaConfirmationActivity:b0074007400740074007400740074tt	()I
    //   34: putstatic 32	com/db/pwcc/dbmobile/transfer/inputscreen/activities/SepaConfirmationActivity:bttttttt0074t	I
    //   37: ldc_w 513
    //   40: sipush 187
    //   43: iconst_1
    //   44: invokestatic 120	xxxxxx/uxxxxx:bb00620062bb0062b0062b0062	(Ljava/lang/String;CC)Ljava/lang/String;
    //   47: astore_2
    //   48: iconst_4
    //   49: anewarray 41	java/lang/Class
    //   52: astore_3
    //   53: aload_3
    //   54: iconst_0
    //   55: ldc 84
    //   57: aastore
    //   58: aload_3
    //   59: iconst_1
    //   60: getstatic 90	java/lang/Character:TYPE	Ljava/lang/Class;
    //   63: aastore
    //   64: aload_3
    //   65: iconst_2
    //   66: getstatic 90	java/lang/Character:TYPE	Ljava/lang/Class;
    //   69: aastore
    //   70: aload_3
    //   71: iconst_3
    //   72: getstatic 90	java/lang/Character:TYPE	Ljava/lang/Class;
    //   75: aastore
    //   76: ldc 92
    //   78: aload_2
    //   79: aload_3
    //   80: invokevirtual 96	java/lang/Class:getMethod	(Ljava/lang/String;[Ljava/lang/Class;)Ljava/lang/reflect/Method;
    //   83: astore 4
    //   85: iconst_4
    //   86: anewarray 98	java/lang/Object
    //   89: astore 5
    //   91: aload 5
    //   93: iconst_0
    //   94: ldc_w 515
    //   97: aastore
    //   98: aload 5
    //   100: iconst_1
    //   101: bipush 47
    //   103: invokestatic 104	java/lang/Character:valueOf	(C)Ljava/lang/Character;
    //   106: aastore
    //   107: aload 5
    //   109: iconst_2
    //   110: bipush 36
    //   112: invokestatic 104	java/lang/Character:valueOf	(C)Ljava/lang/Character;
    //   115: aastore
    //   116: aload 5
    //   118: iconst_3
    //   119: iconst_3
    //   120: invokestatic 104	java/lang/Character:valueOf	(C)Ljava/lang/Character;
    //   123: aastore
    //   124: aload 4
    //   126: aconst_null
    //   127: aload 5
    //   129: invokevirtual 110	java/lang/reflect/Method:invoke	(Ljava/lang/Object;[Ljava/lang/Object;)Ljava/lang/Object;
    //   132: astore 7
    //   134: aload_1
    //   135: aload 7
    //   137: checkcast 84	java/lang/String
    //   140: invokevirtual 357	android/os/Bundle:getBoolean	(Ljava/lang/String;)Z
    //   143: ifeq +192 -> 335
    //   146: ldc_w 517
    //   149: sipush 234
    //   152: iconst_1
    //   153: invokestatic 120	xxxxxx/uxxxxx:bb00620062bb0062b0062b0062	(Ljava/lang/String;CC)Ljava/lang/String;
    //   156: astore 8
    //   158: iconst_4
    //   159: anewarray 41	java/lang/Class
    //   162: astore 9
    //   164: aload 9
    //   166: iconst_0
    //   167: ldc 84
    //   169: aastore
    //   170: aload 9
    //   172: iconst_1
    //   173: getstatic 90	java/lang/Character:TYPE	Ljava/lang/Class;
    //   176: aastore
    //   177: aload 9
    //   179: iconst_2
    //   180: getstatic 90	java/lang/Character:TYPE	Ljava/lang/Class;
    //   183: aastore
    //   184: aload 9
    //   186: iconst_3
    //   187: getstatic 90	java/lang/Character:TYPE	Ljava/lang/Class;
    //   190: aastore
    //   191: ldc 92
    //   193: aload 8
    //   195: aload 9
    //   197: invokevirtual 96	java/lang/Class:getMethod	(Ljava/lang/String;[Ljava/lang/Class;)Ljava/lang/reflect/Method;
    //   200: astore 10
    //   202: iconst_4
    //   203: anewarray 98	java/lang/Object
    //   206: astore 11
    //   208: aload 11
    //   210: iconst_0
    //   211: ldc_w 519
    //   214: aastore
    //   215: aload 11
    //   217: iconst_1
    //   218: bipush 114
    //   220: invokestatic 104	java/lang/Character:valueOf	(C)Ljava/lang/Character;
    //   223: aastore
    //   224: aload 11
    //   226: iconst_2
    //   227: sipush 214
    //   230: invokestatic 104	java/lang/Character:valueOf	(C)Ljava/lang/Character;
    //   233: aastore
    //   234: aload 11
    //   236: iconst_3
    //   237: iconst_2
    //   238: invokestatic 104	java/lang/Character:valueOf	(C)Ljava/lang/Character;
    //   241: aastore
    //   242: aload 10
    //   244: aconst_null
    //   245: aload 11
    //   247: invokevirtual 110	java/lang/reflect/Method:invoke	(Ljava/lang/Object;[Ljava/lang/Object;)Ljava/lang/Object;
    //   250: astore 13
    //   252: aload_1
    //   253: aload 13
    //   255: checkcast 84	java/lang/String
    //   258: invokevirtual 523	android/os/Bundle:getSerializable	(Ljava/lang/String;)Ljava/io/Serializable;
    //   261: checkcast 525	com/db/pwcc/dbmobile/model/error/DbError
    //   264: astore 14
    //   266: aload 14
    //   268: ifnonnull +68 -> 336
    //   271: aload_0
    //   272: invokevirtual 527	com/db/pwcc/dbmobile/transfer/inputscreen/activities/SepaConfirmationActivity:getTanModule	()Luuuuuu/llkklk$lkkklk;
    //   275: invokeinterface 532 1 0
    //   280: aload_0
    //   281: invokevirtual 534	com/db/pwcc/dbmobile/transfer/inputscreen/activities/SepaConfirmationActivity:hidePrincipalAccountBalance	()V
    //   284: aload_0
    //   285: invokevirtual 537	com/db/pwcc/dbmobile/transfer/inputscreen/activities/SepaConfirmationActivity:showShareableToolbar	()V
    //   288: getstatic 26	com/db/pwcc/dbmobile/transfer/inputscreen/activities/SepaConfirmationActivity:b00740074ttttt0074t	I
    //   291: istore 34
    //   293: iload 34
    //   295: iload 34
    //   297: getstatic 28	com/db/pwcc/dbmobile/transfer/inputscreen/activities/SepaConfirmationActivity:b0074tttttt0074t	I
    //   300: iadd
    //   301: imul
    //   302: getstatic 30	com/db/pwcc/dbmobile/transfer/inputscreen/activities/SepaConfirmationActivity:bt0074ttttt0074t	I
    //   305: irem
    //   306: tableswitch	default:+18->324, 0:+29->335
    //   324: bipush 48
    //   326: putstatic 26	com/db/pwcc/dbmobile/transfer/inputscreen/activities/SepaConfirmationActivity:b00740074ttttt0074t	I
    //   329: invokestatic 39	com/db/pwcc/dbmobile/transfer/inputscreen/activities/SepaConfirmationActivity:b0074007400740074007400740074tt	()I
    //   332: putstatic 32	com/db/pwcc/dbmobile/transfer/inputscreen/activities/SepaConfirmationActivity:bttttttt0074t	I
    //   335: return
    //   336: aload 14
    //   338: invokestatic 543	uuuuuu/xxsxsx:bkk006Bk006B006Bk006B006B006B	(Lcom/db/pwcc/dbmobile/model/error/DbError;)Z
    //   341: ifeq +131 -> 472
    //   344: aload_0
    //   345: getfield 52	com/db/pwcc/dbmobile/transfer/inputscreen/activities/SepaConfirmationActivity:presenter	Luuuuuu/nnnntn;
    //   348: astore 25
    //   350: getstatic 546	com/db/pwcc/dbmobile/transfer/R$string:check_internet_connection	I
    //   353: istore 26
    //   355: ldc_w 548
    //   358: bipush 97
    //   360: iconst_1
    //   361: invokestatic 120	xxxxxx/uxxxxx:bb00620062bb0062b0062b0062	(Ljava/lang/String;CC)Ljava/lang/String;
    //   364: astore 27
    //   366: iconst_1
    //   367: anewarray 41	java/lang/Class
    //   370: astore 28
    //   372: aload 28
    //   374: iconst_0
    //   375: getstatic 551	java/lang/Integer:TYPE	Ljava/lang/Class;
    //   378: aastore
    //   379: ldc_w 359
    //   382: aload 27
    //   384: aload 28
    //   386: invokevirtual 96	java/lang/Class:getMethod	(Ljava/lang/String;[Ljava/lang/Class;)Ljava/lang/reflect/Method;
    //   389: astore 29
    //   391: iconst_1
    //   392: anewarray 98	java/lang/Object
    //   395: astore 30
    //   397: aload 30
    //   399: iconst_0
    //   400: iload 26
    //   402: invokestatic 554	java/lang/Integer:valueOf	(I)Ljava/lang/Integer;
    //   405: aastore
    //   406: aload 29
    //   408: aload 25
    //   410: aload 30
    //   412: invokevirtual 110	java/lang/reflect/Method:invoke	(Ljava/lang/Object;[Ljava/lang/Object;)Ljava/lang/Object;
    //   415: pop
    //   416: getstatic 26	com/db/pwcc/dbmobile/transfer/inputscreen/activities/SepaConfirmationActivity:b00740074ttttt0074t	I
    //   419: istore 33
    //   421: iload 33
    //   423: iload 33
    //   425: getstatic 28	com/db/pwcc/dbmobile/transfer/inputscreen/activities/SepaConfirmationActivity:b0074tttttt0074t	I
    //   428: iadd
    //   429: imul
    //   430: invokestatic 62	com/db/pwcc/dbmobile/transfer/inputscreen/activities/SepaConfirmationActivity:b0074t0074tttt0074t	()I
    //   433: irem
    //   434: tableswitch	default:+18->452, 0:+-99->335
    //   452: bipush 7
    //   454: putstatic 26	com/db/pwcc/dbmobile/transfer/inputscreen/activities/SepaConfirmationActivity:b00740074ttttt0074t	I
    //   457: invokestatic 39	com/db/pwcc/dbmobile/transfer/inputscreen/activities/SepaConfirmationActivity:b0074007400740074007400740074tt	()I
    //   460: putstatic 32	com/db/pwcc/dbmobile/transfer/inputscreen/activities/SepaConfirmationActivity:bttttttt0074t	I
    //   463: return
    //   464: astore 12
    //   466: aload 12
    //   468: invokevirtual 161	java/lang/reflect/InvocationTargetException:getCause	()Ljava/lang/Throwable;
    //   471: athrow
    //   472: aload 14
    //   474: invokestatic 558	uuuuuu/xxsxsx:b006B006B006B006Bk006Bk006B006B006B	(Lcom/db/pwcc/dbmobile/model/error/DbError;)Lcom/db/pwcc/dbmobile/model/tan/AuthorizationStatus;
    //   477: astore 15
    //   479: getstatic 47	com/db/pwcc/dbmobile/transfer/inputscreen/activities/SepaConfirmationActivity:TAG	Ljava/lang/String;
    //   482: astore 16
    //   484: new 560	java/lang/StringBuilder
    //   487: dup
    //   488: invokespecial 561	java/lang/StringBuilder:<init>	()V
    //   491: astore 17
    //   493: getstatic 26	com/db/pwcc/dbmobile/transfer/inputscreen/activities/SepaConfirmationActivity:b00740074ttttt0074t	I
    //   496: istore 18
    //   498: iload 18
    //   500: iload 18
    //   502: getstatic 28	com/db/pwcc/dbmobile/transfer/inputscreen/activities/SepaConfirmationActivity:b0074tttttt0074t	I
    //   505: iadd
    //   506: imul
    //   507: getstatic 30	com/db/pwcc/dbmobile/transfer/inputscreen/activities/SepaConfirmationActivity:bt0074ttttt0074t	I
    //   510: irem
    //   511: tableswitch	default:+17->528, 0:+29->540
    //   528: invokestatic 39	com/db/pwcc/dbmobile/transfer/inputscreen/activities/SepaConfirmationActivity:b0074007400740074007400740074tt	()I
    //   531: putstatic 26	com/db/pwcc/dbmobile/transfer/inputscreen/activities/SepaConfirmationActivity:b00740074ttttt0074t	I
    //   534: invokestatic 39	com/db/pwcc/dbmobile/transfer/inputscreen/activities/SepaConfirmationActivity:b0074007400740074007400740074tt	()I
    //   537: putstatic 32	com/db/pwcc/dbmobile/transfer/inputscreen/activities/SepaConfirmationActivity:bttttttt0074t	I
    //   540: ldc_w 563
    //   543: bipush 108
    //   545: bipush 35
    //   547: iconst_2
    //   548: invokestatic 82	xxxxxx/uxxxxx:bbbb0062b0062b0062b0062	(Ljava/lang/String;CCC)Ljava/lang/String;
    //   551: astore 19
    //   553: iconst_4
    //   554: anewarray 41	java/lang/Class
    //   557: astore 20
    //   559: aload 20
    //   561: iconst_0
    //   562: ldc 84
    //   564: aastore
    //   565: aload 20
    //   567: iconst_1
    //   568: getstatic 90	java/lang/Character:TYPE	Ljava/lang/Class;
    //   571: aastore
    //   572: aload 20
    //   574: iconst_2
    //   575: getstatic 90	java/lang/Character:TYPE	Ljava/lang/Class;
    //   578: aastore
    //   579: aload 20
    //   581: iconst_3
    //   582: getstatic 90	java/lang/Character:TYPE	Ljava/lang/Class;
    //   585: aastore
    //   586: ldc 92
    //   588: aload 19
    //   590: aload 20
    //   592: invokevirtual 96	java/lang/Class:getMethod	(Ljava/lang/String;[Ljava/lang/Class;)Ljava/lang/reflect/Method;
    //   595: astore 21
    //   597: iconst_4
    //   598: anewarray 98	java/lang/Object
    //   601: astore 22
    //   603: aload 22
    //   605: iconst_0
    //   606: ldc_w 565
    //   609: aastore
    //   610: aload 22
    //   612: iconst_1
    //   613: bipush 54
    //   615: invokestatic 104	java/lang/Character:valueOf	(C)Ljava/lang/Character;
    //   618: aastore
    //   619: aload 22
    //   621: iconst_2
    //   622: sipush 151
    //   625: invokestatic 104	java/lang/Character:valueOf	(C)Ljava/lang/Character;
    //   628: aastore
    //   629: aload 22
    //   631: iconst_3
    //   632: iconst_3
    //   633: invokestatic 104	java/lang/Character:valueOf	(C)Ljava/lang/Character;
    //   636: aastore
    //   637: aload 21
    //   639: aconst_null
    //   640: aload 22
    //   642: invokevirtual 110	java/lang/reflect/Method:invoke	(Ljava/lang/Object;[Ljava/lang/Object;)Ljava/lang/Object;
    //   645: astore 24
    //   647: aload 16
    //   649: aload 17
    //   651: aload 24
    //   653: checkcast 84	java/lang/String
    //   656: invokevirtual 569	java/lang/StringBuilder:append	(Ljava/lang/String;)Ljava/lang/StringBuilder;
    //   659: aload 14
    //   661: invokevirtual 572	com/db/pwcc/dbmobile/model/error/DbError:toString	()Ljava/lang/String;
    //   664: invokevirtual 569	java/lang/StringBuilder:append	(Ljava/lang/String;)Ljava/lang/StringBuilder;
    //   667: invokevirtual 573	java/lang/StringBuilder:toString	()Ljava/lang/String;
    //   670: invokestatic 579	uuuuuu/rvvvrv:bq0071qq00710071q0071q0071	(Ljava/lang/String;Ljava/lang/String;)V
    //   673: aload_0
    //   674: invokevirtual 527	com/db/pwcc/dbmobile/transfer/inputscreen/activities/SepaConfirmationActivity:getTanModule	()Luuuuuu/llkklk$lkkklk;
    //   677: aload 15
    //   679: invokeinterface 583 2 0
    //   684: aload_0
    //   685: invokevirtual 534	com/db/pwcc/dbmobile/transfer/inputscreen/activities/SepaConfirmationActivity:hidePrincipalAccountBalance	()V
    //   688: return
    //   689: astore 6
    //   691: aload 6
    //   693: invokevirtual 161	java/lang/reflect/InvocationTargetException:getCause	()Ljava/lang/Throwable;
    //   696: athrow
    //   697: astore 31
    //   699: aload 31
    //   701: invokevirtual 161	java/lang/reflect/InvocationTargetException:getCause	()Ljava/lang/Throwable;
    //   704: athrow
    //   705: astore 23
    //   707: aload 23
    //   709: invokevirtual 161	java/lang/reflect/InvocationTargetException:getCause	()Ljava/lang/Throwable;
    //   712: athrow
    // Local variable table:
    //   start	length	slot	name	signature
    //   0	713	0	this	SepaConfirmationActivity
    //   0	713	1	paramBundle	android.os.Bundle
    //   47	32	2	str1	String
    //   52	28	3	arrayOfClass1	Class[]
    //   83	42	4	localMethod1	Method
    //   89	39	5	arrayOfObject1	Object[]
    //   689	3	6	localInvocationTargetException1	InvocationTargetException
    //   132	4	7	localObject1	Object
    //   156	38	8	str2	String
    //   162	34	9	arrayOfClass2	Class[]
    //   200	43	10	localMethod2	Method
    //   206	40	11	arrayOfObject2	Object[]
    //   464	3	12	localInvocationTargetException2	InvocationTargetException
    //   250	4	13	localObject2	Object
    //   264	396	14	localDbError	com.db.pwcc.dbmobile.model.error.DbError
    //   477	201	15	localAuthorizationStatus	AuthorizationStatus
    //   482	166	16	str3	String
    //   491	159	17	localStringBuilder	StringBuilder
    //   496	11	18	i	int
    //   551	38	19	str4	String
    //   557	34	20	arrayOfClass3	Class[]
    //   595	43	21	localMethod3	Method
    //   601	40	22	arrayOfObject3	Object[]
    //   705	3	23	localInvocationTargetException3	InvocationTargetException
    //   645	7	24	localObject3	Object
    //   348	61	25	localNnnntn	nnnntn
    //   353	48	26	j	int
    //   364	19	27	str5	String
    //   370	15	28	arrayOfClass4	Class[]
    //   389	18	29	localMethod4	Method
    //   395	16	30	arrayOfObject4	Object[]
    //   697	3	31	localInvocationTargetException4	InvocationTargetException
    //   419	11	33	k	int
    //   291	11	34	m	int
    // Exception table:
    //   from	to	target	type
    //   242	252	464	java/lang/reflect/InvocationTargetException
    //   124	134	689	java/lang/reflect/InvocationTargetException
    //   406	416	697	java/lang/reflect/InvocationTargetException
    //   637	647	705	java/lang/reflect/InvocationTargetException
  }
  
  public void onResume()
  {
    super.onResume();
    int i = b00740074ttttt0074t;
    int j = b0074tttttt0074t;
    if ((b00740074ttttt0074t + b0074tttttt0074t) * b00740074ttttt0074t % bt0074ttttt0074t != bttttttt0074t)
    {
      b00740074ttttt0074t = b0074007400740074007400740074tt();
      bttttttt0074t = b0074007400740074007400740074tt();
    }
    int k = (i + j) * b00740074ttttt0074t % b0074t0074tttt0074t();
    if ((b00740074ttttt0074t + b0074tttttt0074t) * b00740074ttttt0074t % bt0074ttttt0074t != bttttttt0074t)
    {
      b00740074ttttt0074t = b0074007400740074007400740074tt();
      bttttttt0074t = 5;
    }
    if (k != bttttttt0074t)
    {
      b00740074ttttt0074t = b0074007400740074007400740074tt();
      bttttttt0074t = b0074007400740074007400740074tt();
      if ((b00740074ttttt0074t + b0074tttttt0074t) * b00740074ttttt0074t % bt0074ttttt0074t != bt00740074tttt0074t())
      {
        b00740074ttttt0074t = b0074007400740074007400740074tt();
        bttttttt0074t = b0074007400740074007400740074tt();
      }
    }
    hidePicIfMultiline(this);
  }
  
  /* Error */
  public void onSaveInstanceState(android.os.Bundle paramBundle)
  {
    // Byte code:
    //   0: aload_0
    //   1: getfield 52	com/db/pwcc/dbmobile/transfer/inputscreen/activities/SepaConfirmationActivity:presenter	Luuuuuu/nnnntn;
    //   4: astore_2
    //   5: ldc_w 359
    //   8: ldc_w 591
    //   11: sipush 174
    //   14: iconst_5
    //   15: invokestatic 120	xxxxxx/uxxxxx:bb00620062bb0062b0062b0062	(Ljava/lang/String;CC)Ljava/lang/String;
    //   18: iconst_0
    //   19: anewarray 41	java/lang/Class
    //   22: invokevirtual 96	java/lang/Class:getMethod	(Ljava/lang/String;[Ljava/lang/Class;)Ljava/lang/reflect/Method;
    //   25: astore_3
    //   26: iconst_0
    //   27: anewarray 98	java/lang/Object
    //   30: astore 4
    //   32: aload_3
    //   33: aload_2
    //   34: aload 4
    //   36: invokevirtual 110	java/lang/reflect/Method:invoke	(Ljava/lang/Object;[Ljava/lang/Object;)Ljava/lang/Object;
    //   39: astore 6
    //   41: aload 6
    //   43: checkcast 466	java/lang/Boolean
    //   46: invokevirtual 470	java/lang/Boolean:booleanValue	()Z
    //   49: ifeq +292 -> 341
    //   52: ldc_w 593
    //   55: bipush 18
    //   57: iconst_5
    //   58: invokestatic 120	xxxxxx/uxxxxx:bb00620062bb0062b0062b0062	(Ljava/lang/String;CC)Ljava/lang/String;
    //   61: astore 20
    //   63: iconst_3
    //   64: anewarray 41	java/lang/Class
    //   67: astore 21
    //   69: aload 21
    //   71: iconst_0
    //   72: ldc 84
    //   74: aastore
    //   75: aload 21
    //   77: iconst_1
    //   78: getstatic 90	java/lang/Character:TYPE	Ljava/lang/Class;
    //   81: aastore
    //   82: aload 21
    //   84: iconst_2
    //   85: getstatic 90	java/lang/Character:TYPE	Ljava/lang/Class;
    //   88: aastore
    //   89: ldc 92
    //   91: aload 20
    //   93: aload 21
    //   95: invokevirtual 96	java/lang/Class:getMethod	(Ljava/lang/String;[Ljava/lang/Class;)Ljava/lang/reflect/Method;
    //   98: astore 22
    //   100: iconst_3
    //   101: anewarray 98	java/lang/Object
    //   104: astore 23
    //   106: aload 23
    //   108: iconst_0
    //   109: ldc_w 595
    //   112: aastore
    //   113: aload 23
    //   115: iconst_1
    //   116: bipush 101
    //   118: invokestatic 104	java/lang/Character:valueOf	(C)Ljava/lang/Character;
    //   121: aastore
    //   122: aload 23
    //   124: iconst_2
    //   125: iconst_1
    //   126: invokestatic 104	java/lang/Character:valueOf	(C)Ljava/lang/Character;
    //   129: aastore
    //   130: aload 22
    //   132: aconst_null
    //   133: aload 23
    //   135: invokevirtual 110	java/lang/reflect/Method:invoke	(Ljava/lang/Object;[Ljava/lang/Object;)Ljava/lang/Object;
    //   138: astore 25
    //   140: aload_1
    //   141: aload 25
    //   143: checkcast 84	java/lang/String
    //   146: iconst_1
    //   147: invokevirtual 599	android/os/Bundle:putBoolean	(Ljava/lang/String;Z)V
    //   150: getstatic 26	com/db/pwcc/dbmobile/transfer/inputscreen/activities/SepaConfirmationActivity:b00740074ttttt0074t	I
    //   153: invokestatic 36	com/db/pwcc/dbmobile/transfer/inputscreen/activities/SepaConfirmationActivity:btt0074tttt0074t	()I
    //   156: iadd
    //   157: getstatic 26	com/db/pwcc/dbmobile/transfer/inputscreen/activities/SepaConfirmationActivity:b00740074ttttt0074t	I
    //   160: imul
    //   161: getstatic 30	com/db/pwcc/dbmobile/transfer/inputscreen/activities/SepaConfirmationActivity:bt0074ttttt0074t	I
    //   164: irem
    //   165: getstatic 32	com/db/pwcc/dbmobile/transfer/inputscreen/activities/SepaConfirmationActivity:bttttttt0074t	I
    //   168: if_icmpeq +14 -> 182
    //   171: bipush 26
    //   173: putstatic 26	com/db/pwcc/dbmobile/transfer/inputscreen/activities/SepaConfirmationActivity:b00740074ttttt0074t	I
    //   176: invokestatic 39	com/db/pwcc/dbmobile/transfer/inputscreen/activities/SepaConfirmationActivity:b0074007400740074007400740074tt	()I
    //   179: putstatic 32	com/db/pwcc/dbmobile/transfer/inputscreen/activities/SepaConfirmationActivity:bttttttt0074t	I
    //   182: ldc_w 601
    //   185: bipush 61
    //   187: sipush 181
    //   190: iconst_2
    //   191: invokestatic 82	xxxxxx/uxxxxx:bbbb0062b0062b0062b0062	(Ljava/lang/String;CCC)Ljava/lang/String;
    //   194: astore 26
    //   196: iconst_3
    //   197: anewarray 41	java/lang/Class
    //   200: astore 27
    //   202: aload 27
    //   204: iconst_0
    //   205: ldc 84
    //   207: aastore
    //   208: aload 27
    //   210: iconst_1
    //   211: getstatic 90	java/lang/Character:TYPE	Ljava/lang/Class;
    //   214: aastore
    //   215: aload 27
    //   217: iconst_2
    //   218: getstatic 90	java/lang/Character:TYPE	Ljava/lang/Class;
    //   221: aastore
    //   222: ldc 92
    //   224: aload 26
    //   226: aload 27
    //   228: invokevirtual 96	java/lang/Class:getMethod	(Ljava/lang/String;[Ljava/lang/Class;)Ljava/lang/reflect/Method;
    //   231: astore 28
    //   233: iconst_3
    //   234: anewarray 98	java/lang/Object
    //   237: astore 29
    //   239: aload 29
    //   241: iconst_0
    //   242: ldc_w 603
    //   245: aastore
    //   246: aload 29
    //   248: iconst_1
    //   249: bipush 18
    //   251: invokestatic 104	java/lang/Character:valueOf	(C)Ljava/lang/Character;
    //   254: aastore
    //   255: aload 29
    //   257: iconst_2
    //   258: iconst_2
    //   259: invokestatic 104	java/lang/Character:valueOf	(C)Ljava/lang/Character;
    //   262: aastore
    //   263: aload 28
    //   265: aconst_null
    //   266: aload 29
    //   268: invokevirtual 110	java/lang/reflect/Method:invoke	(Ljava/lang/Object;[Ljava/lang/Object;)Ljava/lang/Object;
    //   271: astore 31
    //   273: aload 31
    //   275: checkcast 84	java/lang/String
    //   278: astore 32
    //   280: aload_0
    //   281: getfield 52	com/db/pwcc/dbmobile/transfer/inputscreen/activities/SepaConfirmationActivity:presenter	Luuuuuu/nnnntn;
    //   284: astore 33
    //   286: ldc_w 359
    //   289: ldc_w 605
    //   292: bipush 125
    //   294: iconst_5
    //   295: invokestatic 120	xxxxxx/uxxxxx:bb00620062bb0062b0062b0062	(Ljava/lang/String;CC)Ljava/lang/String;
    //   298: iconst_0
    //   299: anewarray 41	java/lang/Class
    //   302: invokevirtual 96	java/lang/Class:getMethod	(Ljava/lang/String;[Ljava/lang/Class;)Ljava/lang/reflect/Method;
    //   305: astore 34
    //   307: iconst_0
    //   308: anewarray 98	java/lang/Object
    //   311: astore 35
    //   313: aload 34
    //   315: aload 33
    //   317: aload 35
    //   319: invokevirtual 110	java/lang/reflect/Method:invoke	(Ljava/lang/Object;[Ljava/lang/Object;)Ljava/lang/Object;
    //   322: astore 37
    //   324: aload_1
    //   325: aload 32
    //   327: aload 37
    //   329: checkcast 525	com/db/pwcc/dbmobile/model/error/DbError
    //   332: invokevirtual 609	android/os/Bundle:putSerializable	(Ljava/lang/String;Ljava/io/Serializable;)V
    //   335: aload_0
    //   336: aload_1
    //   337: invokespecial 611	com/db/pwcc/dbmobile/transfer/inputscreen/activities/ConfirmationActivity:onSaveInstanceState	(Landroid/os/Bundle;)V
    //   340: return
    //   341: getstatic 26	com/db/pwcc/dbmobile/transfer/inputscreen/activities/SepaConfirmationActivity:b00740074ttttt0074t	I
    //   344: istore 7
    //   346: getstatic 26	com/db/pwcc/dbmobile/transfer/inputscreen/activities/SepaConfirmationActivity:b00740074ttttt0074t	I
    //   349: invokestatic 36	com/db/pwcc/dbmobile/transfer/inputscreen/activities/SepaConfirmationActivity:btt0074tttt0074t	()I
    //   352: iadd
    //   353: getstatic 26	com/db/pwcc/dbmobile/transfer/inputscreen/activities/SepaConfirmationActivity:b00740074ttttt0074t	I
    //   356: imul
    //   357: getstatic 30	com/db/pwcc/dbmobile/transfer/inputscreen/activities/SepaConfirmationActivity:bt0074ttttt0074t	I
    //   360: irem
    //   361: getstatic 32	com/db/pwcc/dbmobile/transfer/inputscreen/activities/SepaConfirmationActivity:bttttttt0074t	I
    //   364: if_icmpeq +13 -> 377
    //   367: bipush 23
    //   369: putstatic 26	com/db/pwcc/dbmobile/transfer/inputscreen/activities/SepaConfirmationActivity:b00740074ttttt0074t	I
    //   372: bipush 26
    //   374: putstatic 32	com/db/pwcc/dbmobile/transfer/inputscreen/activities/SepaConfirmationActivity:bttttttt0074t	I
    //   377: iload 7
    //   379: invokestatic 36	com/db/pwcc/dbmobile/transfer/inputscreen/activities/SepaConfirmationActivity:btt0074tttt0074t	()I
    //   382: iadd
    //   383: getstatic 26	com/db/pwcc/dbmobile/transfer/inputscreen/activities/SepaConfirmationActivity:b00740074ttttt0074t	I
    //   386: imul
    //   387: getstatic 30	com/db/pwcc/dbmobile/transfer/inputscreen/activities/SepaConfirmationActivity:bt0074ttttt0074t	I
    //   390: irem
    //   391: getstatic 32	com/db/pwcc/dbmobile/transfer/inputscreen/activities/SepaConfirmationActivity:bttttttt0074t	I
    //   394: if_icmpeq +46 -> 440
    //   397: getstatic 26	com/db/pwcc/dbmobile/transfer/inputscreen/activities/SepaConfirmationActivity:b00740074ttttt0074t	I
    //   400: getstatic 28	com/db/pwcc/dbmobile/transfer/inputscreen/activities/SepaConfirmationActivity:b0074tttttt0074t	I
    //   403: iadd
    //   404: getstatic 26	com/db/pwcc/dbmobile/transfer/inputscreen/activities/SepaConfirmationActivity:b00740074ttttt0074t	I
    //   407: imul
    //   408: getstatic 30	com/db/pwcc/dbmobile/transfer/inputscreen/activities/SepaConfirmationActivity:bt0074ttttt0074t	I
    //   411: irem
    //   412: getstatic 32	com/db/pwcc/dbmobile/transfer/inputscreen/activities/SepaConfirmationActivity:bttttttt0074t	I
    //   415: if_icmpeq +14 -> 429
    //   418: invokestatic 39	com/db/pwcc/dbmobile/transfer/inputscreen/activities/SepaConfirmationActivity:b0074007400740074007400740074tt	()I
    //   421: putstatic 26	com/db/pwcc/dbmobile/transfer/inputscreen/activities/SepaConfirmationActivity:b00740074ttttt0074t	I
    //   424: bipush 22
    //   426: putstatic 32	com/db/pwcc/dbmobile/transfer/inputscreen/activities/SepaConfirmationActivity:bttttttt0074t	I
    //   429: invokestatic 39	com/db/pwcc/dbmobile/transfer/inputscreen/activities/SepaConfirmationActivity:b0074007400740074007400740074tt	()I
    //   432: putstatic 26	com/db/pwcc/dbmobile/transfer/inputscreen/activities/SepaConfirmationActivity:b00740074ttttt0074t	I
    //   435: bipush 83
    //   437: putstatic 32	com/db/pwcc/dbmobile/transfer/inputscreen/activities/SepaConfirmationActivity:bttttttt0074t	I
    //   440: ldc_w 613
    //   443: bipush 83
    //   445: iconst_3
    //   446: invokestatic 120	xxxxxx/uxxxxx:bb00620062bb0062b0062b0062	(Ljava/lang/String;CC)Ljava/lang/String;
    //   449: astore 8
    //   451: iconst_4
    //   452: anewarray 41	java/lang/Class
    //   455: astore 9
    //   457: aload 9
    //   459: iconst_0
    //   460: ldc 84
    //   462: aastore
    //   463: aload 9
    //   465: iconst_1
    //   466: getstatic 90	java/lang/Character:TYPE	Ljava/lang/Class;
    //   469: aastore
    //   470: aload 9
    //   472: iconst_2
    //   473: getstatic 90	java/lang/Character:TYPE	Ljava/lang/Class;
    //   476: aastore
    //   477: aload 9
    //   479: iconst_3
    //   480: getstatic 90	java/lang/Character:TYPE	Ljava/lang/Class;
    //   483: aastore
    //   484: ldc 92
    //   486: aload 8
    //   488: aload 9
    //   490: invokevirtual 96	java/lang/Class:getMethod	(Ljava/lang/String;[Ljava/lang/Class;)Ljava/lang/reflect/Method;
    //   493: astore 10
    //   495: iconst_4
    //   496: anewarray 98	java/lang/Object
    //   499: astore 11
    //   501: aload 11
    //   503: iconst_0
    //   504: ldc_w 615
    //   507: aastore
    //   508: aload 11
    //   510: iconst_1
    //   511: sipush 156
    //   514: invokestatic 104	java/lang/Character:valueOf	(C)Ljava/lang/Character;
    //   517: aastore
    //   518: aload 11
    //   520: iconst_2
    //   521: bipush 122
    //   523: invokestatic 104	java/lang/Character:valueOf	(C)Ljava/lang/Character;
    //   526: aastore
    //   527: aload 11
    //   529: iconst_3
    //   530: iconst_2
    //   531: invokestatic 104	java/lang/Character:valueOf	(C)Ljava/lang/Character;
    //   534: aastore
    //   535: aload 10
    //   537: aconst_null
    //   538: aload 11
    //   540: invokevirtual 110	java/lang/reflect/Method:invoke	(Ljava/lang/Object;[Ljava/lang/Object;)Ljava/lang/Object;
    //   543: astore 13
    //   545: aload_1
    //   546: aload 13
    //   548: checkcast 84	java/lang/String
    //   551: iconst_0
    //   552: invokevirtual 599	android/os/Bundle:putBoolean	(Ljava/lang/String;Z)V
    //   555: ldc_w 617
    //   558: bipush 56
    //   560: iconst_4
    //   561: invokestatic 120	xxxxxx/uxxxxx:bb00620062bb0062b0062b0062	(Ljava/lang/String;CC)Ljava/lang/String;
    //   564: astore 14
    //   566: iconst_3
    //   567: anewarray 41	java/lang/Class
    //   570: astore 15
    //   572: aload 15
    //   574: iconst_0
    //   575: ldc 84
    //   577: aastore
    //   578: aload 15
    //   580: iconst_1
    //   581: getstatic 90	java/lang/Character:TYPE	Ljava/lang/Class;
    //   584: aastore
    //   585: aload 15
    //   587: iconst_2
    //   588: getstatic 90	java/lang/Character:TYPE	Ljava/lang/Class;
    //   591: aastore
    //   592: ldc 92
    //   594: aload 14
    //   596: aload 15
    //   598: invokevirtual 96	java/lang/Class:getMethod	(Ljava/lang/String;[Ljava/lang/Class;)Ljava/lang/reflect/Method;
    //   601: astore 16
    //   603: iconst_3
    //   604: anewarray 98	java/lang/Object
    //   607: astore 17
    //   609: aload 17
    //   611: iconst_0
    //   612: ldc_w 619
    //   615: aastore
    //   616: aload 17
    //   618: iconst_1
    //   619: bipush 31
    //   621: invokestatic 104	java/lang/Character:valueOf	(C)Ljava/lang/Character;
    //   624: aastore
    //   625: aload 17
    //   627: iconst_2
    //   628: iconst_2
    //   629: invokestatic 104	java/lang/Character:valueOf	(C)Ljava/lang/Character;
    //   632: aastore
    //   633: aload 16
    //   635: aconst_null
    //   636: aload 17
    //   638: invokevirtual 110	java/lang/reflect/Method:invoke	(Ljava/lang/Object;[Ljava/lang/Object;)Ljava/lang/Object;
    //   641: astore 19
    //   643: aload_1
    //   644: aload 19
    //   646: checkcast 84	java/lang/String
    //   649: aconst_null
    //   650: invokevirtual 609	android/os/Bundle:putSerializable	(Ljava/lang/String;Ljava/io/Serializable;)V
    //   653: goto -318 -> 335
    //   656: astore 18
    //   658: aload 18
    //   660: invokevirtual 161	java/lang/reflect/InvocationTargetException:getCause	()Ljava/lang/Throwable;
    //   663: athrow
    //   664: astore 12
    //   666: aload 12
    //   668: invokevirtual 161	java/lang/reflect/InvocationTargetException:getCause	()Ljava/lang/Throwable;
    //   671: athrow
    //   672: astore 30
    //   674: aload 30
    //   676: invokevirtual 161	java/lang/reflect/InvocationTargetException:getCause	()Ljava/lang/Throwable;
    //   679: athrow
    //   680: astore 24
    //   682: aload 24
    //   684: invokevirtual 161	java/lang/reflect/InvocationTargetException:getCause	()Ljava/lang/Throwable;
    //   687: athrow
    //   688: astore 5
    //   690: aload 5
    //   692: invokevirtual 161	java/lang/reflect/InvocationTargetException:getCause	()Ljava/lang/Throwable;
    //   695: athrow
    //   696: astore 36
    //   698: aload 36
    //   700: invokevirtual 161	java/lang/reflect/InvocationTargetException:getCause	()Ljava/lang/Throwable;
    //   703: athrow
    // Local variable table:
    //   start	length	slot	name	signature
    //   0	704	0	this	SepaConfirmationActivity
    //   0	704	1	paramBundle	android.os.Bundle
    //   4	30	2	localNnnntn1	nnnntn
    //   25	8	3	localMethod1	Method
    //   30	5	4	arrayOfObject1	Object[]
    //   688	3	5	localInvocationTargetException1	InvocationTargetException
    //   39	3	6	localObject1	Object
    //   344	39	7	i	int
    //   449	38	8	str1	String
    //   455	34	9	arrayOfClass1	Class[]
    //   493	43	10	localMethod2	Method
    //   499	40	11	arrayOfObject2	Object[]
    //   664	3	12	localInvocationTargetException2	InvocationTargetException
    //   543	4	13	localObject2	Object
    //   564	31	14	str2	String
    //   570	27	15	arrayOfClass2	Class[]
    //   601	33	16	localMethod3	Method
    //   607	30	17	arrayOfObject3	Object[]
    //   656	3	18	localInvocationTargetException3	InvocationTargetException
    //   641	4	19	localObject3	Object
    //   61	31	20	str3	String
    //   67	27	21	arrayOfClass3	Class[]
    //   98	33	22	localMethod4	Method
    //   104	30	23	arrayOfObject4	Object[]
    //   680	3	24	localInvocationTargetException4	InvocationTargetException
    //   138	4	25	localObject4	Object
    //   194	31	26	str4	String
    //   200	27	27	arrayOfClass4	Class[]
    //   231	33	28	localMethod5	Method
    //   237	30	29	arrayOfObject5	Object[]
    //   672	3	30	localInvocationTargetException5	InvocationTargetException
    //   271	3	31	localObject5	Object
    //   278	48	32	str5	String
    //   284	32	33	localNnnntn2	nnnntn
    //   305	9	34	localMethod6	Method
    //   311	7	35	arrayOfObject6	Object[]
    //   696	3	36	localInvocationTargetException6	InvocationTargetException
    //   322	6	37	localObject6	Object
    // Exception table:
    //   from	to	target	type
    //   633	643	656	java/lang/reflect/InvocationTargetException
    //   535	545	664	java/lang/reflect/InvocationTargetException
    //   263	273	672	java/lang/reflect/InvocationTargetException
    //   130	140	680	java/lang/reflect/InvocationTargetException
    //   32	41	688	java/lang/reflect/InvocationTargetException
    //   313	324	696	java/lang/reflect/InvocationTargetException
  }
  
  public void retrievePrincipalAccountDetails(String paramString)
  {
    int i = b00740074ttttt0074t;
    int j = b0074tttttt0074t;
    if ((b00740074ttttt0074t + b0074tttttt0074t) * b00740074ttttt0074t % bt0074ttttt0074t != bttttttt0074t)
    {
      if ((b00740074ttttt0074t + b0074tttttt0074t) * b00740074ttttt0074t % bt0074ttttt0074t != bttttttt0074t)
      {
        b00740074ttttt0074t = b0074007400740074007400740074tt();
        bttttttt0074t = 85;
      }
      b00740074ttttt0074t = 4;
      bttttttt0074t = b0074007400740074007400740074tt();
    }
    if ((i + j) * b00740074ttttt0074t % bt0074ttttt0074t != bttttttt0074t)
    {
      b00740074ttttt0074t = 21;
      int k = b00740074ttttt0074t;
      switch (k * (k + b0074tttttt0074t) % bt0074ttttt0074t)
      {
      default: 
        b00740074ttttt0074t = 68;
        bttttttt0074t = 41;
      }
      bttttttt0074t = b0074007400740074007400740074tt();
    }
    nnnntn localNnnntn = this.presenter;
    Method localMethod = nnnntn.class.getMethod(uxxxxx.bb00620062bb0062b0062b0062("<B\b\007\f\016=\003\002\007\t87|{\001\00321vuz|", '', '\004'), new Class[] { String.class });
    Object[] arrayOfObject = { paramString };
    try
    {
      localMethod.invoke(localNnnntn, arrayOfObject);
      return;
    }
    catch (InvocationTargetException localInvocationTargetException)
    {
      throw localInvocationTargetException.getCause();
    }
  }
  
  public void returnToOriginActivity()
  {
    Intent localIntent = getIntent();
    int i = (b00740074ttttt0074t + b0074tttttt0074t) * b00740074ttttt0074t % bt0074ttttt0074t;
    int j = bttttttt0074t;
    int k = b00740074ttttt0074t;
    switch (k * (k + b0074tttttt0074t) % bt0074ttttt0074t)
    {
    default: 
      b00740074ttttt0074t = 48;
      bttttttt0074t = 62;
      if ((b00740074ttttt0074t + b0074tttttt0074t) * b00740074ttttt0074t % bt0074ttttt0074t != bttttttt0074t)
      {
        b00740074ttttt0074t = 63;
        bttttttt0074t = b0074007400740074007400740074tt();
      }
      break;
    }
    if (i != j)
    {
      if ((b00740074ttttt0074t + b0074tttttt0074t) * b00740074ttttt0074t % bt0074ttttt0074t != bttttttt0074t)
      {
        b00740074ttttt0074t = b0074007400740074007400740074tt();
        bttttttt0074t = 71;
      }
      b00740074ttttt0074t = b0074007400740074007400740074tt();
      bttttttt0074t = 8;
    }
    String str1 = uxxxxx.bb00620062bb0062b0062b0062("y\020\021\022\023LMUVPQYZ\034UV^_YZbc%", 'Ê', '\001');
    Class[] arrayOfClass = new Class[3];
    arrayOfClass[0] = String.class;
    arrayOfClass[1] = Character.TYPE;
    arrayOfClass[2] = Character.TYPE;
    Method localMethod = ppphhp.class.getMethod(str1, arrayOfClass);
    Object[] arrayOfObject = new Object[3];
    arrayOfObject[0] = "q\006\003\002q?`Tj^]Xl^yok|akatuqerk";
    arrayOfObject[1] = Character.valueOf('');
    arrayOfObject[2] = Character.valueOf('\002');
    try
    {
      Object localObject = localMethod.invoke(null, arrayOfObject);
      String str2 = localIntent.getStringExtra((String)localObject);
      this.redirectFacade.ba0061a0061006100610061aaa(this, str2);
      return;
    }
    catch (InvocationTargetException localInvocationTargetException)
    {
      throw localInvocationTargetException.getCause();
    }
  }
  
  public void setPrincipalAccountBalance(String paramString1, String paramString2)
  {
    TextView localTextView1 = (TextView)findViewById(R.id.confirmation_principalCurrentBalance);
    TextView localTextView2 = (TextView)findViewById(R.id.confirmation_principalPrebookedBalance);
    if (localTextView1 != null)
    {
      if (paramString1 != null) {
        break label147;
      }
      localTextView1.setVisibility(8);
    }
    for (;;)
    {
      if (localTextView2 != null)
      {
        if (paramString2 != null) {
          break label86;
        }
        localTextView2.setVisibility(8);
        if ((b00740074ttttt0074t + btt0074tttt0074t()) * b00740074ttttt0074t % bt0074ttttt0074t != bttttttt0074t)
        {
          b00740074ttttt0074t = b0074007400740074007400740074tt();
          bttttttt0074t = 8;
        }
      }
      label86:
      do
      {
        return;
        localTextView2.setVisibility(0);
        localTextView2.setText(String.format(getString(R.string.sepatransfer_verify_currentBalancePrebooked_label), new Object[] { paramString2 }));
      } while ((b00740074ttttt0074t + b0074tttttt0074t) * b00740074ttttt0074t % bt0074ttttt0074t == bttttttt0074t);
      b00740074ttttt0074t = 65;
      bttttttt0074t = 97;
      return;
      label147:
      localTextView1.setVisibility(0);
      String str = getString(R.string.sepatransfer_verify_currentBalance_label);
      int i = (b00740074ttttt0074t + b0074tttttt0074t) * b00740074ttttt0074t % bt0074ttttt0074t;
      int j = b00740074ttttt0074t;
      switch (j * (j + b0074tttttt0074t) % bt0074ttttt0074t)
      {
      default: 
        b00740074ttttt0074t = 79;
        bttttttt0074t = 86;
      }
      if (i != bttttttt0074t)
      {
        b00740074ttttt0074t = 30;
        bttttttt0074t = 1;
      }
      localTextView1.setText(String.format(str, new Object[] { paramString1 }));
    }
  }
  
  /* Error */
  public void setPrincipalName(String paramString1, String paramString2)
  {
    // Byte code:
    //   0: iconst_1
    //   1: istore_3
    //   2: iconst_m1
    //   3: newarray int
    //   5: pop
    //   6: goto -4 -> 2
    //   9: astore 5
    //   11: invokestatic 39	com/db/pwcc/dbmobile/transfer/inputscreen/activities/SepaConfirmationActivity:b0074007400740074007400740074tt	()I
    //   14: putstatic 26	com/db/pwcc/dbmobile/transfer/inputscreen/activities/SepaConfirmationActivity:b00740074ttttt0074t	I
    //   17: aload_0
    //   18: getstatic 654	com/db/pwcc/dbmobile/transfer/R$id:confirmation_principalInitials	I
    //   21: invokevirtual 243	com/db/pwcc/dbmobile/transfer/inputscreen/activities/SepaConfirmationActivity:findViewById	(I)Landroid/view/View;
    //   24: checkcast 258	android/widget/TextView
    //   27: astore 6
    //   29: getstatic 26	com/db/pwcc/dbmobile/transfer/inputscreen/activities/SepaConfirmationActivity:b00740074ttttt0074t	I
    //   32: istore 7
    //   34: iload 7
    //   36: iload 7
    //   38: invokestatic 36	com/db/pwcc/dbmobile/transfer/inputscreen/activities/SepaConfirmationActivity:btt0074tttt0074t	()I
    //   41: iadd
    //   42: imul
    //   43: invokestatic 62	com/db/pwcc/dbmobile/transfer/inputscreen/activities/SepaConfirmationActivity:b0074t0074tttt0074t	()I
    //   46: irem
    //   47: tableswitch	default:+17->64, 0:+61->108
    //   64: bipush 46
    //   66: putstatic 26	com/db/pwcc/dbmobile/transfer/inputscreen/activities/SepaConfirmationActivity:b00740074ttttt0074t	I
    //   69: invokestatic 39	com/db/pwcc/dbmobile/transfer/inputscreen/activities/SepaConfirmationActivity:b0074007400740074007400740074tt	()I
    //   72: putstatic 32	com/db/pwcc/dbmobile/transfer/inputscreen/activities/SepaConfirmationActivity:bttttttt0074t	I
    //   75: getstatic 26	com/db/pwcc/dbmobile/transfer/inputscreen/activities/SepaConfirmationActivity:b00740074ttttt0074t	I
    //   78: invokestatic 36	com/db/pwcc/dbmobile/transfer/inputscreen/activities/SepaConfirmationActivity:btt0074tttt0074t	()I
    //   81: iadd
    //   82: getstatic 26	com/db/pwcc/dbmobile/transfer/inputscreen/activities/SepaConfirmationActivity:b00740074ttttt0074t	I
    //   85: imul
    //   86: getstatic 30	com/db/pwcc/dbmobile/transfer/inputscreen/activities/SepaConfirmationActivity:bt0074ttttt0074t	I
    //   89: irem
    //   90: getstatic 32	com/db/pwcc/dbmobile/transfer/inputscreen/activities/SepaConfirmationActivity:bttttttt0074t	I
    //   93: if_icmpeq +15 -> 108
    //   96: invokestatic 39	com/db/pwcc/dbmobile/transfer/inputscreen/activities/SepaConfirmationActivity:b0074007400740074007400740074tt	()I
    //   99: putstatic 26	com/db/pwcc/dbmobile/transfer/inputscreen/activities/SepaConfirmationActivity:b00740074ttttt0074t	I
    //   102: invokestatic 39	com/db/pwcc/dbmobile/transfer/inputscreen/activities/SepaConfirmationActivity:b0074007400740074007400740074tt	()I
    //   105: putstatic 32	com/db/pwcc/dbmobile/transfer/inputscreen/activities/SepaConfirmationActivity:bttttttt0074t	I
    //   108: aload_0
    //   109: getstatic 270	com/db/pwcc/dbmobile/transfer/R$id:confirmation_principalName	I
    //   112: invokevirtual 243	com/db/pwcc/dbmobile/transfer/inputscreen/activities/SepaConfirmationActivity:findViewById	(I)Landroid/view/View;
    //   115: checkcast 258	android/widget/TextView
    //   118: aload_1
    //   119: invokevirtual 647	android/widget/TextView:setText	(Ljava/lang/CharSequence;)V
    //   122: invokestatic 39	com/db/pwcc/dbmobile/transfer/inputscreen/activities/SepaConfirmationActivity:b0074007400740074007400740074tt	()I
    //   125: getstatic 28	com/db/pwcc/dbmobile/transfer/inputscreen/activities/SepaConfirmationActivity:b0074tttttt0074t	I
    //   128: iadd
    //   129: invokestatic 39	com/db/pwcc/dbmobile/transfer/inputscreen/activities/SepaConfirmationActivity:b0074007400740074007400740074tt	()I
    //   132: imul
    //   133: getstatic 30	com/db/pwcc/dbmobile/transfer/inputscreen/activities/SepaConfirmationActivity:bt0074ttttt0074t	I
    //   136: irem
    //   137: getstatic 32	com/db/pwcc/dbmobile/transfer/inputscreen/activities/SepaConfirmationActivity:bttttttt0074t	I
    //   140: if_icmpeq +15 -> 155
    //   143: invokestatic 39	com/db/pwcc/dbmobile/transfer/inputscreen/activities/SepaConfirmationActivity:b0074007400740074007400740074tt	()I
    //   146: putstatic 26	com/db/pwcc/dbmobile/transfer/inputscreen/activities/SepaConfirmationActivity:b00740074ttttt0074t	I
    //   149: invokestatic 39	com/db/pwcc/dbmobile/transfer/inputscreen/activities/SepaConfirmationActivity:b0074007400740074007400740074tt	()I
    //   152: putstatic 32	com/db/pwcc/dbmobile/transfer/inputscreen/activities/SepaConfirmationActivity:bttttttt0074t	I
    //   155: aload 6
    //   157: aload_2
    //   158: invokevirtual 647	android/widget/TextView:setText	(Ljava/lang/CharSequence;)V
    //   161: aload_0
    //   162: getfield 56	com/db/pwcc/dbmobile/transfer/inputscreen/activities/SepaConfirmationActivity:isSubaccountTransfer	Z
    //   165: ifeq +11 -> 176
    //   168: aload_0
    //   169: getfield 658	com/db/pwcc/dbmobile/transfer/inputscreen/activities/SepaConfirmationActivity:beneficiaryAvatar	Lcom/db/pwcc/dbmobile/foundation/widgets/UserAvatar;
    //   172: aload_2
    //   173: invokevirtual 661	com/db/pwcc/dbmobile/foundation/widgets/UserAvatar:setText	(Ljava/lang/CharSequence;)V
    //   176: return
    //   177: astore 4
    //   179: bipush 7
    //   181: putstatic 26	com/db/pwcc/dbmobile/transfer/inputscreen/activities/SepaConfirmationActivity:b00740074ttttt0074t	I
    //   184: iload_3
    //   185: iconst_0
    //   186: idiv
    //   187: istore_3
    //   188: goto -4 -> 184
    // Local variable table:
    //   start	length	slot	name	signature
    //   0	191	0	this	SepaConfirmationActivity
    //   0	191	1	paramString1	String
    //   0	191	2	paramString2	String
    //   1	187	3	i	int
    //   177	1	4	localException1	Exception
    //   9	1	5	localException2	Exception
    //   27	129	6	localTextView	TextView
    //   32	11	7	j	int
    // Exception table:
    //   from	to	target	type
    //   184	188	9	java/lang/Exception
    //   2	6	177	java/lang/Exception
  }
  
  public void setTransactionData(String paramString, boolean paramBoolean, Authorization paramAuthorization, AuthorizationStatus paramAuthorizationStatus)
  {
    nnnntn localNnnntn = this.presenter;
    int i = b00740074ttttt0074t;
    int j = b00740074ttttt0074t;
    switch (j * (j + b0074tttttt0074t) % b0074t0074tttt0074t())
    {
    default: 
      b00740074ttttt0074t = 90;
      bttttttt0074t = b0074007400740074007400740074tt();
    }
    int k = (i + b0074tttttt0074t) * b00740074ttttt0074t;
    if ((b00740074ttttt0074t + b0074tttttt0074t) * b00740074ttttt0074t % bt0074ttttt0074t != bt00740074tttt0074t())
    {
      b00740074ttttt0074t = b0074007400740074007400740074tt();
      bttttttt0074t = b0074007400740074007400740074tt();
    }
    if (k % b0074t0074tttt0074t() != bttttttt0074t)
    {
      int m = b00740074ttttt0074t;
      switch (m * (m + b0074tttttt0074t) % b0074t0074tttt0074t())
      {
      default: 
        b00740074ttttt0074t = b0074007400740074007400740074tt();
        bttttttt0074t = b0074007400740074007400740074tt();
      }
      b00740074ttttt0074t = b0074007400740074007400740074tt();
      bttttttt0074t = b0074007400740074007400740074tt();
    }
    String str = uxxxxx.bb00620062bb0062b0062b0062("-{|\004\b\001\b\f=\005\006\r\021BC\013\f\023\027HI\021\022\031\035", 'J', '\002');
    Class[] arrayOfClass = new Class[4];
    arrayOfClass[0] = String.class;
    arrayOfClass[1] = Boolean.TYPE;
    arrayOfClass[2] = Authorization.class;
    arrayOfClass[3] = AuthorizationStatus.class;
    Method localMethod = nnnntn.class.getMethod(str, arrayOfClass);
    Object[] arrayOfObject = new Object[4];
    arrayOfObject[0] = paramString;
    arrayOfObject[1] = Boolean.valueOf(paramBoolean);
    arrayOfObject[2] = paramAuthorization;
    arrayOfObject[3] = paramAuthorizationStatus;
    try
    {
      localMethod.invoke(localNnnntn, arrayOfObject);
      return;
    }
    catch (InvocationTargetException localInvocationTargetException)
    {
      throw localInvocationTargetException.getCause();
    }
  }
  
  public void setValidatedTransferData(TransactionResponse paramTransactionResponse)
  {
    TextView localTextView1 = (TextView)findViewById(R.id.confirmation_beneficiaryName);
    if ((b00740074ttttt0074t + b0074tttttt0074t) * b00740074ttttt0074t % bt0074ttttt0074t != bttttttt0074t)
    {
      b00740074ttttt0074t = 77;
      bttttttt0074t = b0074007400740074007400740074tt();
    }
    TextView localTextView2 = (TextView)findViewById(R.id.confirmation_beneficiaryIban);
    TextView localTextView3 = (TextView)findViewById(R.id.bankName);
    TextView localTextView4 = (TextView)findViewById(R.id.description);
    TextView localTextView5 = (TextView)findViewById(R.id.amountValue);
    TextView localTextView6 = (TextView)findViewById(R.id.confirmation_executionDate);
    TextView localTextView7 = (TextView)findViewById(R.id.confirmation_principalIban);
    SepaTransaction localSepaTransaction;
    String str1;
    String str2;
    Locale localLocale;
    Method localMethod;
    Object[] arrayOfObject;
    if ((paramTransactionResponse != null) && (paramTransactionResponse.getTransaction() != null))
    {
      this.transactionReceived = paramTransactionResponse.getTransaction();
      localSepaTransaction = paramTransactionResponse.getTransaction();
      str1 = localSepaTransaction.getExecutionDate();
      str2 = localSepaTransaction.getPurpose();
      if (!this.isSubaccountTransfer) {
        break label466;
      }
      if ((b00740074ttttt0074t + btt0074tttt0074t()) * b00740074ttttt0074t % bt0074ttttt0074t != bttttttt0074t)
      {
        b00740074ttttt0074t = 84;
        bttttttt0074t = b0074007400740074007400740074tt();
      }
      localTextView1.setVisibility(8);
      localTextView3.setVisibility(8);
      localLocale = Locale.getDefault();
      if (str1 == null) {
        break label403;
      }
      String str6 = uxxxxx.bbbb0062b0062b0062b0062("y\016\r\f\013BAGF>=CB\00298>=54:9x", 'ï', '', '\001');
      Class[] arrayOfClass = new Class[3];
      arrayOfClass[0] = String.class;
      arrayOfClass[1] = Character.TYPE;
      arrayOfClass[2] = Character.TYPE;
      localMethod = ppphhp.class.getMethod(str6, arrayOfClass);
      arrayOfObject = new Object[3];
      arrayOfObject[0] = "\013\f\r\016BcdE}~";
      arrayOfObject[1] = Character.valueOf('');
      arrayOfObject[2] = Character.valueOf('\002');
    }
    for (;;)
    {
      try
      {
        Object localObject = localMethod.invoke(null, arrayOfObject);
        String str5 = pqpppq.b006B006B006Bkk006Bkkkk(localLocale, str1, (String)localObject);
        label403:
        int j;
        if ((str2 != null) && (!str2.trim().equals("")))
        {
          localTextView4.setText(str2);
          localTextView2.setText(localSepaTransaction.getTargetAccount());
          localTextView5.setText(hhhpph.bw0077wwwwww0077w(new BigDecimal(localSepaTransaction.getAmount()), hhhpph.by0079y007900790079yy0079.getCurrencyCode(), localLocale));
          localTextView6.setText(str5);
          localTextView7.setText(localSepaTransaction.getSourceAccount());
          return;
          localTextView6.setVisibility(8);
          j = b00740074ttttt0074t;
        }
        switch (j * (j + b0074tttttt0074t) % bt0074ttttt0074t)
        {
        default: 
          b00740074ttttt0074t = b0074007400740074007400740074tt();
          bttttttt0074t = 57;
          str5 = str1;
          continue;
          String str3 = localSepaTransaction.getBeneficiary();
          String str4 = oononn.b006Bk006B006Bk006Bk006Bk006B(str3);
          localTextView1.setText(str3);
          this.beneficiaryAvatar.setText(str4);
          int i = b00740074ttttt0074t;
          switch (i * (i + b0074tttttt0074t) % bt0074ttttt0074t)
          {
          default: 
            b00740074ttttt0074t = 73;
            bttttttt0074t = b0074007400740074007400740074tt();
          }
          localTextView3.setText(paramTransactionResponse.getTargetBankName());
          break;
          localTextView4.setVisibility(8);
          break;
        case 0: 
          label466:
          str5 = str1;
        }
      }
      catch (InvocationTargetException localInvocationTargetException)
      {
        throw localInvocationTargetException.getCause();
      }
    }
  }
}
