package com.db.pwcc.dbmobile.transfer.inputscreen.activities;

import android.content.Context;
import android.content.DialogInterface.OnClickListener;
import android.content.Intent;
import android.content.res.Resources;
import android.text.Editable;
import android.text.TextWatcher;
import android.view.MotionEvent;
import android.view.View;
import android.view.View.OnClickListener;
import android.view.Window;
import android.widget.AdapterView;
import android.widget.AdapterView.OnItemClickListener;
import android.widget.LinearLayout;
import com.appdynamics.eumagent.runtime.InstrumentationCallbacks;
import com.db.pwcc.dbmobile.foundation.activities.common.PopupActivity;
import com.db.pwcc.dbmobile.foundation.views.button.Button;
import com.db.pwcc.dbmobile.foundation.widgets.DbTextView;
import com.db.pwcc.dbmobile.foundation.widgets.dbPicker.DbPicker;
import com.db.pwcc.dbmobile.model.banking.Account;
import com.db.pwcc.dbmobile.model.banking.FinancialOverviewData;
import com.db.pwcc.dbmobile.model.tan.Authorization;
import com.db.pwcc.dbmobile.model.tan.AuthorizationStatus;
import com.db.pwcc.dbmobile.transfer.R.id;
import com.db.pwcc.dbmobile.transfer.R.layout;
import com.db.pwcc.dbmobile.transfer.R.string;
import com.db.pwcc.dbmobile.transfer.views.DbScrollview;
import com.db.pwcc.dbmobile.transfer.widgets.inputFields.AmountField;
import com.db.pwcc.dbmobile.transfer.widgets.inputFields.InputField;
import java.lang.reflect.InvocationTargetException;
import java.lang.reflect.Method;
import java.math.BigDecimal;
import java.util.ArrayList;
import java.util.List;
import uuuuuu.ggyggy;
import uuuuuu.gyyygy.yyyygy;
import uuuuuu.kvkvvv;
import uuuuuu.lolllo;
import uuuuuu.lvvvvv;
import uuuuuu.nnttnt.ntntnt;
import uuuuuu.nonnnn;
import uuuuuu.nononn;
import uuuuuu.oonoon;
import uuuuuu.ppphhp;
import uuuuuu.tnnntn;
import uuuuuu.vkkvvk;
import uuuuuu.vlvvlv;
import uuuuuu.vvllvv;
import uuuuuu.yyyggy;
import xxxxxx.uxxxxx;

public class InputSubaccountActivity
  extends PopupActivity
  implements nnttnt.ntntnt, vkkvvk
{
  private static final int CONFIRMATION_ACTIVITY_RETURNED = 99;
  private static final String EXTRA_PRINCIPLE_ACCOUNT_ID = "FG=A5:@;3,-.-8=5:$-'";
  private static final String STATE_ACCOUNT_POS = "xxdvf`a`kphmwgeh";
  private static final String STATE_AMOUNT = "JJ6H8Q2=>C;@";
  private static final String STATE_DESCRIPTION = " \"\020$\0261\027\031(\031)!).$++";
  private static final String STATE_SUBACCOUNT_POS = "qsaug\003wzhhkly\001z\002\016\005";
  private static final String TAG;
  public static int b007400740074ttt0074tt = 2;
  public static int b00740074tttt0074tt = 1;
  public static int b0074tt0074tt0074tt = 0;
  public static int bt0074tttt0074tt = 40;
  private lvvvvv accountAdapter = null;
  private DbPicker accountSelector = null;
  private AmountField amount = null;
  private DbTextView amountErrorMessage = null;
  private Button buttonDone = null;
  private InputField description = null;
  private DbScrollview mainScrollView = null;
  private tnnntn presenter = null;
  private LinearLayout principalContainer = null;
  private lvvvvv subaccountAdapter = null;
  private DbPicker subaccountSelector = null;
  private List<Account> subaccountsList = new ArrayList();
  
  /* Error */
  static
  {
    // Byte code:
    //   0: aconst_null
    //   1: invokevirtual 71	java/lang/String:length	()I
    //   4: pop
    //   5: goto -5 -> 0
    //   8: astore_0
    //   9: aconst_null
    //   10: invokevirtual 71	java/lang/String:length	()I
    //   13: pop
    //   14: getstatic 73	com/db/pwcc/dbmobile/transfer/inputscreen/activities/InputSubaccountActivity:bt0074tttt0074tt	I
    //   17: istore 39
    //   19: iload 39
    //   21: iload 39
    //   23: getstatic 75	com/db/pwcc/dbmobile/transfer/inputscreen/activities/InputSubaccountActivity:b00740074tttt0074tt	I
    //   26: iadd
    //   27: imul
    //   28: invokestatic 78	com/db/pwcc/dbmobile/transfer/inputscreen/activities/InputSubaccountActivity:btt0074ttt0074tt	()I
    //   31: irem
    //   32: tableswitch	default:+20->52, 0:+-23->9
    //   52: invokestatic 81	com/db/pwcc/dbmobile/transfer/inputscreen/activities/InputSubaccountActivity:b0074t0074ttt0074tt	()I
    //   55: putstatic 73	com/db/pwcc/dbmobile/transfer/inputscreen/activities/InputSubaccountActivity:bt0074tttt0074tt	I
    //   58: invokestatic 81	com/db/pwcc/dbmobile/transfer/inputscreen/activities/InputSubaccountActivity:b0074t0074ttt0074tt	()I
    //   61: putstatic 75	com/db/pwcc/dbmobile/transfer/inputscreen/activities/InputSubaccountActivity:b00740074tttt0074tt	I
    //   64: goto -55 -> 9
    //   67: astore_1
    //   68: getstatic 83	com/db/pwcc/dbmobile/transfer/inputscreen/activities/InputSubaccountActivity:EXTRA_PRINCIPLE_ACCOUNT_ID	Ljava/lang/String;
    //   71: astore_2
    //   72: ldc 85
    //   74: sipush 197
    //   77: bipush 41
    //   79: iconst_3
    //   80: invokestatic 91	xxxxxx/uxxxxx:bbbb0062b0062b0062b0062	(Ljava/lang/String;CCC)Ljava/lang/String;
    //   83: astore_3
    //   84: iconst_4
    //   85: anewarray 93	java/lang/Class
    //   88: astore 4
    //   90: aload 4
    //   92: iconst_0
    //   93: ldc 67
    //   95: aastore
    //   96: aload 4
    //   98: iconst_1
    //   99: getstatic 99	java/lang/Character:TYPE	Ljava/lang/Class;
    //   102: aastore
    //   103: aload 4
    //   105: iconst_2
    //   106: getstatic 99	java/lang/Character:TYPE	Ljava/lang/Class;
    //   109: aastore
    //   110: aload 4
    //   112: iconst_3
    //   113: getstatic 99	java/lang/Character:TYPE	Ljava/lang/Class;
    //   116: aastore
    //   117: ldc 101
    //   119: aload_3
    //   120: aload 4
    //   122: invokevirtual 105	java/lang/Class:getMethod	(Ljava/lang/String;[Ljava/lang/Class;)Ljava/lang/reflect/Method;
    //   125: astore 5
    //   127: iconst_4
    //   128: anewarray 107	java/lang/Object
    //   131: astore 6
    //   133: aload 6
    //   135: iconst_0
    //   136: aload_2
    //   137: aastore
    //   138: aload 6
    //   140: iconst_1
    //   141: bipush 121
    //   143: invokestatic 111	java/lang/Character:valueOf	(C)Ljava/lang/Character;
    //   146: aastore
    //   147: aload 6
    //   149: iconst_2
    //   150: sipush 175
    //   153: invokestatic 111	java/lang/Character:valueOf	(C)Ljava/lang/Character;
    //   156: aastore
    //   157: aload 6
    //   159: iconst_3
    //   160: iconst_0
    //   161: invokestatic 111	java/lang/Character:valueOf	(C)Ljava/lang/Character;
    //   164: aastore
    //   165: aload 5
    //   167: aconst_null
    //   168: aload 6
    //   170: invokevirtual 117	java/lang/reflect/Method:invoke	(Ljava/lang/Object;[Ljava/lang/Object;)Ljava/lang/Object;
    //   173: astore 8
    //   175: aload 8
    //   177: checkcast 67	java/lang/String
    //   180: putstatic 83	com/db/pwcc/dbmobile/transfer/inputscreen/activities/InputSubaccountActivity:EXTRA_PRINCIPLE_ACCOUNT_ID	Ljava/lang/String;
    //   183: getstatic 119	com/db/pwcc/dbmobile/transfer/inputscreen/activities/InputSubaccountActivity:STATE_ACCOUNT_POS	Ljava/lang/String;
    //   186: astore 9
    //   188: ldc 121
    //   190: sipush 245
    //   193: bipush 45
    //   195: iconst_3
    //   196: invokestatic 91	xxxxxx/uxxxxx:bbbb0062b0062b0062b0062	(Ljava/lang/String;CCC)Ljava/lang/String;
    //   199: astore 10
    //   201: iconst_3
    //   202: anewarray 93	java/lang/Class
    //   205: astore 11
    //   207: aload 11
    //   209: iconst_0
    //   210: ldc 67
    //   212: aastore
    //   213: aload 11
    //   215: iconst_1
    //   216: getstatic 99	java/lang/Character:TYPE	Ljava/lang/Class;
    //   219: aastore
    //   220: aload 11
    //   222: iconst_2
    //   223: getstatic 99	java/lang/Character:TYPE	Ljava/lang/Class;
    //   226: aastore
    //   227: ldc 101
    //   229: aload 10
    //   231: aload 11
    //   233: invokevirtual 105	java/lang/Class:getMethod	(Ljava/lang/String;[Ljava/lang/Class;)Ljava/lang/reflect/Method;
    //   236: astore 12
    //   238: iconst_3
    //   239: anewarray 107	java/lang/Object
    //   242: astore 13
    //   244: aload 13
    //   246: iconst_0
    //   247: aload 9
    //   249: aastore
    //   250: aload 13
    //   252: iconst_1
    //   253: bipush 30
    //   255: invokestatic 111	java/lang/Character:valueOf	(C)Ljava/lang/Character;
    //   258: aastore
    //   259: aload 13
    //   261: iconst_2
    //   262: iconst_5
    //   263: invokestatic 111	java/lang/Character:valueOf	(C)Ljava/lang/Character;
    //   266: aastore
    //   267: aload 12
    //   269: aconst_null
    //   270: aload 13
    //   272: invokevirtual 117	java/lang/reflect/Method:invoke	(Ljava/lang/Object;[Ljava/lang/Object;)Ljava/lang/Object;
    //   275: astore 15
    //   277: aload 15
    //   279: checkcast 67	java/lang/String
    //   282: putstatic 119	com/db/pwcc/dbmobile/transfer/inputscreen/activities/InputSubaccountActivity:STATE_ACCOUNT_POS	Ljava/lang/String;
    //   285: getstatic 123	com/db/pwcc/dbmobile/transfer/inputscreen/activities/InputSubaccountActivity:STATE_AMOUNT	Ljava/lang/String;
    //   288: astore 16
    //   290: ldc 125
    //   292: sipush 246
    //   295: bipush 65
    //   297: iconst_1
    //   298: invokestatic 91	xxxxxx/uxxxxx:bbbb0062b0062b0062b0062	(Ljava/lang/String;CCC)Ljava/lang/String;
    //   301: astore 17
    //   303: iconst_4
    //   304: anewarray 93	java/lang/Class
    //   307: astore 18
    //   309: aload 18
    //   311: iconst_0
    //   312: ldc 67
    //   314: aastore
    //   315: aload 18
    //   317: iconst_1
    //   318: getstatic 99	java/lang/Character:TYPE	Ljava/lang/Class;
    //   321: aastore
    //   322: aload 18
    //   324: iconst_2
    //   325: getstatic 99	java/lang/Character:TYPE	Ljava/lang/Class;
    //   328: aastore
    //   329: aload 18
    //   331: iconst_3
    //   332: getstatic 99	java/lang/Character:TYPE	Ljava/lang/Class;
    //   335: aastore
    //   336: ldc 101
    //   338: aload 17
    //   340: aload 18
    //   342: invokevirtual 105	java/lang/Class:getMethod	(Ljava/lang/String;[Ljava/lang/Class;)Ljava/lang/reflect/Method;
    //   345: astore 19
    //   347: iconst_4
    //   348: anewarray 107	java/lang/Object
    //   351: astore 20
    //   353: aload 20
    //   355: iconst_0
    //   356: aload 16
    //   358: aastore
    //   359: aload 20
    //   361: iconst_1
    //   362: sipush 248
    //   365: invokestatic 111	java/lang/Character:valueOf	(C)Ljava/lang/Character;
    //   368: aastore
    //   369: aload 20
    //   371: iconst_2
    //   372: bipush 112
    //   374: invokestatic 111	java/lang/Character:valueOf	(C)Ljava/lang/Character;
    //   377: aastore
    //   378: aload 20
    //   380: iconst_3
    //   381: iconst_1
    //   382: invokestatic 111	java/lang/Character:valueOf	(C)Ljava/lang/Character;
    //   385: aastore
    //   386: aload 19
    //   388: aconst_null
    //   389: aload 20
    //   391: invokevirtual 117	java/lang/reflect/Method:invoke	(Ljava/lang/Object;[Ljava/lang/Object;)Ljava/lang/Object;
    //   394: astore 22
    //   396: aload 22
    //   398: checkcast 67	java/lang/String
    //   401: putstatic 123	com/db/pwcc/dbmobile/transfer/inputscreen/activities/InputSubaccountActivity:STATE_AMOUNT	Ljava/lang/String;
    //   404: getstatic 127	com/db/pwcc/dbmobile/transfer/inputscreen/activities/InputSubaccountActivity:STATE_DESCRIPTION	Ljava/lang/String;
    //   407: astore 23
    //   409: getstatic 73	com/db/pwcc/dbmobile/transfer/inputscreen/activities/InputSubaccountActivity:bt0074tttt0074tt	I
    //   412: istore 24
    //   414: iload 24
    //   416: iload 24
    //   418: invokestatic 130	com/db/pwcc/dbmobile/transfer/inputscreen/activities/InputSubaccountActivity:bt00740074ttt0074tt	()I
    //   421: iadd
    //   422: imul
    //   423: getstatic 132	com/db/pwcc/dbmobile/transfer/inputscreen/activities/InputSubaccountActivity:b007400740074ttt0074tt	I
    //   426: irem
    //   427: tableswitch	default:+17->444, 0:+27->454
    //   444: bipush 48
    //   446: putstatic 73	com/db/pwcc/dbmobile/transfer/inputscreen/activities/InputSubaccountActivity:bt0074tttt0074tt	I
    //   449: bipush 72
    //   451: putstatic 75	com/db/pwcc/dbmobile/transfer/inputscreen/activities/InputSubaccountActivity:b00740074tttt0074tt	I
    //   454: ldc -122
    //   456: bipush 110
    //   458: iconst_5
    //   459: invokestatic 138	xxxxxx/uxxxxx:bb00620062bb0062b0062b0062	(Ljava/lang/String;CC)Ljava/lang/String;
    //   462: astore 25
    //   464: iconst_3
    //   465: anewarray 93	java/lang/Class
    //   468: astore 26
    //   470: aload 26
    //   472: iconst_0
    //   473: ldc 67
    //   475: aastore
    //   476: aload 26
    //   478: iconst_1
    //   479: getstatic 99	java/lang/Character:TYPE	Ljava/lang/Class;
    //   482: aastore
    //   483: aload 26
    //   485: iconst_2
    //   486: getstatic 99	java/lang/Character:TYPE	Ljava/lang/Class;
    //   489: aastore
    //   490: ldc 101
    //   492: aload 25
    //   494: aload 26
    //   496: invokevirtual 105	java/lang/Class:getMethod	(Ljava/lang/String;[Ljava/lang/Class;)Ljava/lang/reflect/Method;
    //   499: astore 27
    //   501: iconst_3
    //   502: anewarray 107	java/lang/Object
    //   505: astore 28
    //   507: aload 28
    //   509: iconst_0
    //   510: aload 23
    //   512: aastore
    //   513: aload 28
    //   515: iconst_1
    //   516: sipush 237
    //   519: invokestatic 111	java/lang/Character:valueOf	(C)Ljava/lang/Character;
    //   522: aastore
    //   523: aload 28
    //   525: iconst_2
    //   526: iconst_0
    //   527: invokestatic 111	java/lang/Character:valueOf	(C)Ljava/lang/Character;
    //   530: aastore
    //   531: aload 27
    //   533: aconst_null
    //   534: aload 28
    //   536: invokevirtual 117	java/lang/reflect/Method:invoke	(Ljava/lang/Object;[Ljava/lang/Object;)Ljava/lang/Object;
    //   539: astore 30
    //   541: aload 30
    //   543: checkcast 67	java/lang/String
    //   546: putstatic 127	com/db/pwcc/dbmobile/transfer/inputscreen/activities/InputSubaccountActivity:STATE_DESCRIPTION	Ljava/lang/String;
    //   549: getstatic 140	com/db/pwcc/dbmobile/transfer/inputscreen/activities/InputSubaccountActivity:STATE_SUBACCOUNT_POS	Ljava/lang/String;
    //   552: astore 31
    //   554: ldc -114
    //   556: bipush 67
    //   558: bipush 77
    //   560: iconst_1
    //   561: invokestatic 91	xxxxxx/uxxxxx:bbbb0062b0062b0062b0062	(Ljava/lang/String;CCC)Ljava/lang/String;
    //   564: astore 32
    //   566: iconst_4
    //   567: anewarray 93	java/lang/Class
    //   570: astore 33
    //   572: aload 33
    //   574: iconst_0
    //   575: ldc 67
    //   577: aastore
    //   578: aload 33
    //   580: iconst_1
    //   581: getstatic 99	java/lang/Character:TYPE	Ljava/lang/Class;
    //   584: aastore
    //   585: aload 33
    //   587: iconst_2
    //   588: getstatic 99	java/lang/Character:TYPE	Ljava/lang/Class;
    //   591: aastore
    //   592: aload 33
    //   594: iconst_3
    //   595: getstatic 99	java/lang/Character:TYPE	Ljava/lang/Class;
    //   598: aastore
    //   599: ldc 101
    //   601: aload 32
    //   603: aload 33
    //   605: invokevirtual 105	java/lang/Class:getMethod	(Ljava/lang/String;[Ljava/lang/Class;)Ljava/lang/reflect/Method;
    //   608: astore 34
    //   610: iconst_4
    //   611: anewarray 107	java/lang/Object
    //   614: astore 35
    //   616: aload 35
    //   618: iconst_0
    //   619: aload 31
    //   621: aastore
    //   622: aload 35
    //   624: iconst_1
    //   625: sipush 246
    //   628: invokestatic 111	java/lang/Character:valueOf	(C)Ljava/lang/Character;
    //   631: aastore
    //   632: aload 35
    //   634: iconst_2
    //   635: sipush 165
    //   638: invokestatic 111	java/lang/Character:valueOf	(C)Ljava/lang/Character;
    //   641: aastore
    //   642: aload 35
    //   644: iconst_3
    //   645: iconst_3
    //   646: invokestatic 111	java/lang/Character:valueOf	(C)Ljava/lang/Character;
    //   649: aastore
    //   650: aload 34
    //   652: aconst_null
    //   653: aload 35
    //   655: invokevirtual 117	java/lang/reflect/Method:invoke	(Ljava/lang/Object;[Ljava/lang/Object;)Ljava/lang/Object;
    //   658: astore 37
    //   660: aload 37
    //   662: checkcast 67	java/lang/String
    //   665: putstatic 140	com/db/pwcc/dbmobile/transfer/inputscreen/activities/InputSubaccountActivity:STATE_SUBACCOUNT_POS	Ljava/lang/String;
    //   668: ldc 2
    //   670: invokevirtual 146	java/lang/Class:getSimpleName	()Ljava/lang/String;
    //   673: putstatic 148	com/db/pwcc/dbmobile/transfer/inputscreen/activities/InputSubaccountActivity:TAG	Ljava/lang/String;
    //   676: return
    //   677: astore 29
    //   679: aload 29
    //   681: invokevirtual 152	java/lang/reflect/InvocationTargetException:getCause	()Ljava/lang/Throwable;
    //   684: athrow
    //   685: astore 14
    //   687: aload 14
    //   689: invokevirtual 152	java/lang/reflect/InvocationTargetException:getCause	()Ljava/lang/Throwable;
    //   692: athrow
    //   693: astore 36
    //   695: aload 36
    //   697: invokevirtual 152	java/lang/reflect/InvocationTargetException:getCause	()Ljava/lang/Throwable;
    //   700: athrow
    //   701: astore 21
    //   703: aload 21
    //   705: invokevirtual 152	java/lang/reflect/InvocationTargetException:getCause	()Ljava/lang/Throwable;
    //   708: athrow
    //   709: astore 7
    //   711: aload 7
    //   713: invokevirtual 152	java/lang/reflect/InvocationTargetException:getCause	()Ljava/lang/Throwable;
    //   716: athrow
    // Local variable table:
    //   start	length	slot	name	signature
    //   8	1	0	localException1	Exception
    //   67	1	1	localException2	Exception
    //   71	66	2	str1	String
    //   83	37	3	str2	String
    //   88	33	4	arrayOfClass1	Class[]
    //   125	41	5	localMethod1	Method
    //   131	38	6	arrayOfObject1	Object[]
    //   709	3	7	localInvocationTargetException1	InvocationTargetException
    //   173	3	8	localObject1	Object
    //   186	62	9	str3	String
    //   199	31	10	str4	String
    //   205	27	11	arrayOfClass2	Class[]
    //   236	32	12	localMethod2	Method
    //   242	29	13	arrayOfObject2	Object[]
    //   685	3	14	localInvocationTargetException2	InvocationTargetException
    //   275	3	15	localObject2	Object
    //   288	69	16	str5	String
    //   301	38	17	str6	String
    //   307	34	18	arrayOfClass3	Class[]
    //   345	42	19	localMethod3	Method
    //   351	39	20	arrayOfObject3	Object[]
    //   701	3	21	localInvocationTargetException3	InvocationTargetException
    //   394	3	22	localObject3	Object
    //   407	104	23	str7	String
    //   412	11	24	i	int
    //   462	31	25	str8	String
    //   468	27	26	arrayOfClass4	Class[]
    //   499	33	27	localMethod4	Method
    //   505	30	28	arrayOfObject4	Object[]
    //   677	3	29	localInvocationTargetException4	InvocationTargetException
    //   539	3	30	localObject4	Object
    //   552	68	31	str9	String
    //   564	38	32	str10	String
    //   570	34	33	arrayOfClass5	Class[]
    //   608	43	34	localMethod5	Method
    //   614	40	35	arrayOfObject5	Object[]
    //   693	3	36	localInvocationTargetException5	InvocationTargetException
    //   658	3	37	localObject5	Object
    //   17	11	39	j	int
    // Exception table:
    //   from	to	target	type
    //   0	5	8	java/lang/Exception
    //   9	14	67	java/lang/Exception
    //   531	541	677	java/lang/reflect/InvocationTargetException
    //   267	277	685	java/lang/reflect/InvocationTargetException
    //   650	660	693	java/lang/reflect/InvocationTargetException
    //   386	396	701	java/lang/reflect/InvocationTargetException
    //   165	175	709	java/lang/reflect/InvocationTargetException
  }
  
  public InputSubaccountActivity() {}
  
  public static int b0074t0074ttt0074tt()
  {
    return 97;
  }
  
  public static int bt00740074ttt0074tt()
  {
    return 1;
  }
  
  public static int btt0074ttt0074tt()
  {
    return 2;
  }
  
  public static int bttt0074tt0074tt()
  {
    return 0;
  }
  
  private void generateSubaccountsList(int paramInt)
  {
    int i = this.subaccountSelector.getSelectedItemPosition();
    Account localAccount1 = new Account();
    if (i > 0) {
      localAccount1 = this.subaccountAdapter.b0069ii0069ii0069006900690069(i);
    }
    lvvvvv localLvvvvv = this.accountAdapter;
    if ((bt0074tttt0074tt + b00740074tttt0074tt) * bt0074tttt0074tt % b007400740074ttt0074tt != bttt0074tt0074tt())
    {
      bt0074tttt0074tt = b0074t0074ttt0074tt();
      b0074tt0074tt0074tt = 72;
    }
    Account localAccount2 = localLvvvvv.b0069ii0069ii0069006900690069(paramInt);
    this.subaccountAdapter.clear();
    this.subaccountAdapter.addAll(this.subaccountsList);
    this.subaccountAdapter.remove(localAccount2);
    int k;
    DbPicker localDbPicker;
    if (i > 0)
    {
      int j = bt0074tttt0074tt;
      switch (j * (j + bt00740074ttt0074tt()) % b007400740074ttt0074tt)
      {
      default: 
        bt0074tttt0074tt = 74;
        b0074tt0074tt0074tt = b0074t0074ttt0074tt();
      }
      k = this.subaccountAdapter.getPosition(localAccount1);
      localDbPicker = this.subaccountSelector;
      if (k <= 0) {
        break label191;
      }
    }
    for (;;)
    {
      localDbPicker.setSelectedItemPosition(k);
      this.subaccountAdapter.notifyDataSetChanged();
      return;
      label191:
      int m = bt0074tttt0074tt;
      int n = b00740074tttt0074tt;
      if ((bt0074tttt0074tt + b00740074tttt0074tt) * bt0074tttt0074tt % b007400740074ttt0074tt != b0074tt0074tt0074tt)
      {
        bt0074tttt0074tt = 19;
        b0074tt0074tt0074tt = 34;
      }
      int i1 = (m + n) * bt0074tttt0074tt % b007400740074ttt0074tt;
      int i2 = b0074tt0074tt0074tt;
      k = 0;
      if (i1 != i2)
      {
        bt0074tttt0074tt = 81;
        b0074tt0074tt0074tt = 80;
        k = 0;
      }
    }
  }
  
  private void initDbToolbar()
  {
    int i = R.string.sepatransfer_verify_title;
    int j = R.string.sepatransfer_navigationitem_subtitle_subaccount;
    int k = bt0074tttt0074tt;
    switch (k * (k + bt00740074ttt0074tt()) % b007400740074ttt0074tt)
    {
    default: 
      int m = b0074t0074ttt0074tt();
      int n = b0074t0074ttt0074tt();
      switch (n * (n + bt00740074ttt0074tt()) % b007400740074ttt0074tt)
      {
      default: 
        bt0074tttt0074tt = b0074t0074ttt0074tt();
        b0074tt0074tt0074tt = b0074t0074ttt0074tt();
      }
      bt0074tttt0074tt = m;
      b0074tt0074tt0074tt = 97;
      if ((bt0074tttt0074tt + b00740074tttt0074tt) * bt0074tttt0074tt % b007400740074ttt0074tt != b0074tt0074tt0074tt)
      {
        bt0074tttt0074tt = b0074t0074ttt0074tt();
        b0074tt0074tt0074tt = b0074t0074ttt0074tt();
      }
      break;
    }
    if ((bt0074tttt0074tt + b00740074tttt0074tt) * bt0074tttt0074tt % b007400740074ttt0074tt != b0074tt0074tt0074tt)
    {
      bt0074tttt0074tt = b0074t0074ttt0074tt();
      b0074tt0074tt0074tt = 34;
    }
    setToolbarForPopupModeWithCloseButton(0, i, j, new View.OnClickListener()
    {
      public static int b0074tt0074007400740074tt = 1;
      public static int bt0074t0074007400740074tt = 2;
      public static int btt00740074007400740074tt = 0;
      public static int bttt0074007400740074tt = 91;
      
      public static int b00740074t0074007400740074tt()
      {
        return 47;
      }
      
      public static int b0074t00740074007400740074tt()
      {
        return 1;
      }
      
      public static int bt007400740074007400740074tt()
      {
        return 2;
      }
      
      public void onClick(View paramAnonymousView)
      {
        int i = (bttt0074007400740074tt + b0074t00740074007400740074tt()) * bttt0074007400740074tt % bt0074t0074007400740074tt;
        if ((b00740074t0074007400740074tt() + b0074tt0074007400740074tt) * b00740074t0074007400740074tt() % bt007400740074007400740074tt() != btt00740074007400740074tt)
        {
          bttt0074007400740074tt = b00740074t0074007400740074tt();
          btt00740074007400740074tt = b00740074t0074007400740074tt();
        }
        if (i != btt00740074007400740074tt)
        {
          bttt0074007400740074tt = 86;
          btt00740074007400740074tt = b00740074t0074007400740074tt();
        }
        InputSubaccountActivity.this.onBackPressed();
        int j = bttt0074007400740074tt;
        switch (j * (j + b0074tt0074007400740074tt) % bt0074t0074007400740074tt)
        {
        default: 
          int k = bttt0074007400740074tt;
          switch (k * (k + b0074tt0074007400740074tt) % bt0074t0074007400740074tt)
          {
          default: 
            bttt0074007400740074tt = 26;
            btt00740074007400740074tt = b00740074t0074007400740074tt();
          }
          bttt0074007400740074tt = 15;
          b0074tt0074007400740074tt = b00740074t0074007400740074tt();
        }
      }
    });
  }
  
  /* Error */
  private void initView()
  {
    // Byte code:
    //   0: aload_0
    //   1: aload_0
    //   2: getstatic 269	com/db/pwcc/dbmobile/transfer/R$id:input_subaccount_scroll_view	I
    //   5: invokevirtual 273	com/db/pwcc/dbmobile/transfer/inputscreen/activities/InputSubaccountActivity:findViewById	(I)Landroid/view/View;
    //   8: checkcast 275	com/db/pwcc/dbmobile/transfer/views/DbScrollview
    //   11: putfield 159	com/db/pwcc/dbmobile/transfer/inputscreen/activities/InputSubaccountActivity:mainScrollView	Lcom/db/pwcc/dbmobile/transfer/views/DbScrollview;
    //   14: aload_0
    //   15: aload_0
    //   16: getstatic 278	com/db/pwcc/dbmobile/transfer/R$id:input_subaccount_amount_field	I
    //   19: invokevirtual 273	com/db/pwcc/dbmobile/transfer/inputscreen/activities/InputSubaccountActivity:findViewById	(I)Landroid/view/View;
    //   22: checkcast 280	com/db/pwcc/dbmobile/transfer/widgets/inputFields/AmountField
    //   25: putfield 161	com/db/pwcc/dbmobile/transfer/inputscreen/activities/InputSubaccountActivity:amount	Lcom/db/pwcc/dbmobile/transfer/widgets/inputFields/AmountField;
    //   28: aload_0
    //   29: aload_0
    //   30: getstatic 283	com/db/pwcc/dbmobile/transfer/R$id:input_subaccount_description	I
    //   33: invokevirtual 273	com/db/pwcc/dbmobile/transfer/inputscreen/activities/InputSubaccountActivity:findViewById	(I)Landroid/view/View;
    //   36: checkcast 285	com/db/pwcc/dbmobile/transfer/widgets/inputFields/InputField
    //   39: putfield 163	com/db/pwcc/dbmobile/transfer/inputscreen/activities/InputSubaccountActivity:description	Lcom/db/pwcc/dbmobile/transfer/widgets/inputFields/InputField;
    //   42: aload_0
    //   43: aload_0
    //   44: getstatic 288	com/db/pwcc/dbmobile/transfer/R$id:input_subaccount_amount_error	I
    //   47: invokevirtual 273	com/db/pwcc/dbmobile/transfer/inputscreen/activities/InputSubaccountActivity:findViewById	(I)Landroid/view/View;
    //   50: checkcast 290	com/db/pwcc/dbmobile/foundation/widgets/DbTextView
    //   53: putfield 167	com/db/pwcc/dbmobile/transfer/inputscreen/activities/InputSubaccountActivity:amountErrorMessage	Lcom/db/pwcc/dbmobile/foundation/widgets/DbTextView;
    //   56: aload_0
    //   57: aload_0
    //   58: getstatic 293	com/db/pwcc/dbmobile/transfer/R$id:input_subaccount_account_picker	I
    //   61: invokevirtual 273	com/db/pwcc/dbmobile/transfer/inputscreen/activities/InputSubaccountActivity:findViewById	(I)Landroid/view/View;
    //   64: checkcast 213	com/db/pwcc/dbmobile/foundation/widgets/dbPicker/DbPicker
    //   67: putfield 169	com/db/pwcc/dbmobile/transfer/inputscreen/activities/InputSubaccountActivity:accountSelector	Lcom/db/pwcc/dbmobile/foundation/widgets/dbPicker/DbPicker;
    //   70: aload_0
    //   71: aload_0
    //   72: getstatic 296	com/db/pwcc/dbmobile/transfer/R$id:input_subaccount_subaccount_picker	I
    //   75: invokevirtual 273	com/db/pwcc/dbmobile/transfer/inputscreen/activities/InputSubaccountActivity:findViewById	(I)Landroid/view/View;
    //   78: checkcast 213	com/db/pwcc/dbmobile/foundation/widgets/dbPicker/DbPicker
    //   81: putfield 171	com/db/pwcc/dbmobile/transfer/inputscreen/activities/InputSubaccountActivity:subaccountSelector	Lcom/db/pwcc/dbmobile/foundation/widgets/dbPicker/DbPicker;
    //   84: aload_0
    //   85: aload_0
    //   86: getstatic 299	com/db/pwcc/dbmobile/transfer/R$id:input_subaccount_container_principal	I
    //   89: invokevirtual 273	com/db/pwcc/dbmobile/transfer/inputscreen/activities/InputSubaccountActivity:findViewById	(I)Landroid/view/View;
    //   92: checkcast 301	android/widget/LinearLayout
    //   95: putfield 177	com/db/pwcc/dbmobile/transfer/inputscreen/activities/InputSubaccountActivity:principalContainer	Landroid/widget/LinearLayout;
    //   98: getstatic 73	com/db/pwcc/dbmobile/transfer/inputscreen/activities/InputSubaccountActivity:bt0074tttt0074tt	I
    //   101: getstatic 75	com/db/pwcc/dbmobile/transfer/inputscreen/activities/InputSubaccountActivity:b00740074tttt0074tt	I
    //   104: iadd
    //   105: getstatic 73	com/db/pwcc/dbmobile/transfer/inputscreen/activities/InputSubaccountActivity:bt0074tttt0074tt	I
    //   108: imul
    //   109: getstatic 132	com/db/pwcc/dbmobile/transfer/inputscreen/activities/InputSubaccountActivity:b007400740074ttt0074tt	I
    //   112: irem
    //   113: getstatic 191	com/db/pwcc/dbmobile/transfer/inputscreen/activities/InputSubaccountActivity:b0074tt0074tt0074tt	I
    //   116: if_icmpeq +15 -> 131
    //   119: invokestatic 81	com/db/pwcc/dbmobile/transfer/inputscreen/activities/InputSubaccountActivity:b0074t0074ttt0074tt	()I
    //   122: putstatic 73	com/db/pwcc/dbmobile/transfer/inputscreen/activities/InputSubaccountActivity:bt0074tttt0074tt	I
    //   125: invokestatic 81	com/db/pwcc/dbmobile/transfer/inputscreen/activities/InputSubaccountActivity:b0074t0074ttt0074tt	()I
    //   128: putstatic 191	com/db/pwcc/dbmobile/transfer/inputscreen/activities/InputSubaccountActivity:b0074tt0074tt0074tt	I
    //   131: new 303	android/animation/LayoutTransition
    //   134: dup
    //   135: invokespecial 304	android/animation/LayoutTransition:<init>	()V
    //   138: astore_1
    //   139: aload_0
    //   140: getfield 177	com/db/pwcc/dbmobile/transfer/inputscreen/activities/InputSubaccountActivity:principalContainer	Landroid/widget/LinearLayout;
    //   143: aload_1
    //   144: invokevirtual 308	android/widget/LinearLayout:setLayoutTransition	(Landroid/animation/LayoutTransition;)V
    //   147: aload_1
    //   148: iconst_4
    //   149: invokevirtual 311	android/animation/LayoutTransition:enableTransitionType	(I)V
    //   152: aload_0
    //   153: getfield 177	com/db/pwcc/dbmobile/transfer/inputscreen/activities/InputSubaccountActivity:principalContainer	Landroid/widget/LinearLayout;
    //   156: iconst_0
    //   157: invokevirtual 315	android/widget/LinearLayout:setMotionEventSplittingEnabled	(Z)V
    //   160: aload_0
    //   161: getfield 161	com/db/pwcc/dbmobile/transfer/inputscreen/activities/InputSubaccountActivity:amount	Lcom/db/pwcc/dbmobile/transfer/widgets/inputFields/AmountField;
    //   164: iconst_0
    //   165: aload_0
    //   166: invokevirtual 319	com/db/pwcc/dbmobile/transfer/inputscreen/activities/InputSubaccountActivity:getResources	()Landroid/content/res/Resources;
    //   169: getstatic 324	com/db/pwcc/dbmobile/transfer/R$dimen:fs_input_amount	I
    //   172: invokevirtual 330	android/content/res/Resources:getDimension	(I)F
    //   175: invokevirtual 334	com/db/pwcc/dbmobile/transfer/widgets/inputFields/AmountField:setTextSize	(IF)V
    //   178: aload_0
    //   179: getfield 163	com/db/pwcc/dbmobile/transfer/inputscreen/activities/InputSubaccountActivity:description	Lcom/db/pwcc/dbmobile/transfer/widgets/inputFields/InputField;
    //   182: iconst_0
    //   183: aload_0
    //   184: invokevirtual 319	com/db/pwcc/dbmobile/transfer/inputscreen/activities/InputSubaccountActivity:getResources	()Landroid/content/res/Resources;
    //   187: getstatic 337	com/db/pwcc/dbmobile/transfer/R$dimen:fs_input_value	I
    //   190: invokevirtual 330	android/content/res/Resources:getDimension	(I)F
    //   193: invokevirtual 338	com/db/pwcc/dbmobile/transfer/widgets/inputFields/InputField:setTextSize	(IF)V
    //   196: aload_0
    //   197: getfield 169	com/db/pwcc/dbmobile/transfer/inputscreen/activities/InputSubaccountActivity:accountSelector	Lcom/db/pwcc/dbmobile/foundation/widgets/dbPicker/DbPicker;
    //   200: aload_0
    //   201: invokevirtual 319	com/db/pwcc/dbmobile/transfer/inputscreen/activities/InputSubaccountActivity:getResources	()Landroid/content/res/Resources;
    //   204: getstatic 341	com/db/pwcc/dbmobile/transfer/R$string:sepatransfer_input_selectAccount_label	I
    //   207: invokevirtual 345	android/content/res/Resources:getString	(I)Ljava/lang/String;
    //   210: invokevirtual 349	com/db/pwcc/dbmobile/foundation/widgets/dbPicker/DbPicker:setHint	(Ljava/lang/String;)V
    //   213: aload_0
    //   214: getfield 171	com/db/pwcc/dbmobile/transfer/inputscreen/activities/InputSubaccountActivity:subaccountSelector	Lcom/db/pwcc/dbmobile/foundation/widgets/dbPicker/DbPicker;
    //   217: aload_0
    //   218: invokevirtual 319	com/db/pwcc/dbmobile/transfer/inputscreen/activities/InputSubaccountActivity:getResources	()Landroid/content/res/Resources;
    //   221: getstatic 352	com/db/pwcc/dbmobile/transfer/R$string:sepatransfer_input_subaccount_picker_label	I
    //   224: invokevirtual 345	android/content/res/Resources:getString	(I)Ljava/lang/String;
    //   227: invokevirtual 349	com/db/pwcc/dbmobile/foundation/widgets/dbPicker/DbPicker:setHint	(Ljava/lang/String;)V
    //   230: aload_0
    //   231: getfield 163	com/db/pwcc/dbmobile/transfer/inputscreen/activities/InputSubaccountActivity:description	Lcom/db/pwcc/dbmobile/transfer/widgets/inputFields/InputField;
    //   234: astore_2
    //   235: getstatic 73	com/db/pwcc/dbmobile/transfer/inputscreen/activities/InputSubaccountActivity:bt0074tttt0074tt	I
    //   238: istore_3
    //   239: getstatic 75	com/db/pwcc/dbmobile/transfer/inputscreen/activities/InputSubaccountActivity:b00740074tttt0074tt	I
    //   242: istore 4
    //   244: getstatic 73	com/db/pwcc/dbmobile/transfer/inputscreen/activities/InputSubaccountActivity:bt0074tttt0074tt	I
    //   247: istore 5
    //   249: iload 5
    //   251: iload 5
    //   253: getstatic 75	com/db/pwcc/dbmobile/transfer/inputscreen/activities/InputSubaccountActivity:b00740074tttt0074tt	I
    //   256: iadd
    //   257: imul
    //   258: getstatic 132	com/db/pwcc/dbmobile/transfer/inputscreen/activities/InputSubaccountActivity:b007400740074ttt0074tt	I
    //   261: irem
    //   262: tableswitch	default:+18->280, 0:+30->292
    //   280: invokestatic 81	com/db/pwcc/dbmobile/transfer/inputscreen/activities/InputSubaccountActivity:b0074t0074ttt0074tt	()I
    //   283: putstatic 73	com/db/pwcc/dbmobile/transfer/inputscreen/activities/InputSubaccountActivity:bt0074tttt0074tt	I
    //   286: invokestatic 81	com/db/pwcc/dbmobile/transfer/inputscreen/activities/InputSubaccountActivity:b0074t0074ttt0074tt	()I
    //   289: putstatic 191	com/db/pwcc/dbmobile/transfer/inputscreen/activities/InputSubaccountActivity:b0074tt0074tt0074tt	I
    //   292: iload_3
    //   293: iload 4
    //   295: iadd
    //   296: getstatic 73	com/db/pwcc/dbmobile/transfer/inputscreen/activities/InputSubaccountActivity:bt0074tttt0074tt	I
    //   299: imul
    //   300: getstatic 132	com/db/pwcc/dbmobile/transfer/inputscreen/activities/InputSubaccountActivity:b007400740074ttt0074tt	I
    //   303: irem
    //   304: getstatic 191	com/db/pwcc/dbmobile/transfer/inputscreen/activities/InputSubaccountActivity:b0074tt0074tt0074tt	I
    //   307: if_icmpeq +46 -> 353
    //   310: bipush 52
    //   312: putstatic 73	com/db/pwcc/dbmobile/transfer/inputscreen/activities/InputSubaccountActivity:bt0074tttt0074tt	I
    //   315: invokestatic 81	com/db/pwcc/dbmobile/transfer/inputscreen/activities/InputSubaccountActivity:b0074t0074ttt0074tt	()I
    //   318: putstatic 191	com/db/pwcc/dbmobile/transfer/inputscreen/activities/InputSubaccountActivity:b0074tt0074tt0074tt	I
    //   321: getstatic 73	com/db/pwcc/dbmobile/transfer/inputscreen/activities/InputSubaccountActivity:bt0074tttt0074tt	I
    //   324: getstatic 75	com/db/pwcc/dbmobile/transfer/inputscreen/activities/InputSubaccountActivity:b00740074tttt0074tt	I
    //   327: iadd
    //   328: getstatic 73	com/db/pwcc/dbmobile/transfer/inputscreen/activities/InputSubaccountActivity:bt0074tttt0074tt	I
    //   331: imul
    //   332: getstatic 132	com/db/pwcc/dbmobile/transfer/inputscreen/activities/InputSubaccountActivity:b007400740074ttt0074tt	I
    //   335: irem
    //   336: getstatic 191	com/db/pwcc/dbmobile/transfer/inputscreen/activities/InputSubaccountActivity:b0074tt0074tt0074tt	I
    //   339: if_icmpeq +14 -> 353
    //   342: bipush 43
    //   344: putstatic 73	com/db/pwcc/dbmobile/transfer/inputscreen/activities/InputSubaccountActivity:bt0074tttt0074tt	I
    //   347: invokestatic 81	com/db/pwcc/dbmobile/transfer/inputscreen/activities/InputSubaccountActivity:b0074t0074ttt0074tt	()I
    //   350: putstatic 191	com/db/pwcc/dbmobile/transfer/inputscreen/activities/InputSubaccountActivity:b0074tt0074tt0074tt	I
    //   353: ldc_w 354
    //   356: sipush 214
    //   359: iconst_1
    //   360: invokestatic 138	xxxxxx/uxxxxx:bb00620062bb0062b0062b0062	(Ljava/lang/String;CC)Ljava/lang/String;
    //   363: astore 6
    //   365: iconst_4
    //   366: anewarray 93	java/lang/Class
    //   369: astore 7
    //   371: aload 7
    //   373: iconst_0
    //   374: ldc 67
    //   376: aastore
    //   377: aload 7
    //   379: iconst_1
    //   380: getstatic 99	java/lang/Character:TYPE	Ljava/lang/Class;
    //   383: aastore
    //   384: aload 7
    //   386: iconst_2
    //   387: getstatic 99	java/lang/Character:TYPE	Ljava/lang/Class;
    //   390: aastore
    //   391: aload 7
    //   393: iconst_3
    //   394: getstatic 99	java/lang/Character:TYPE	Ljava/lang/Class;
    //   397: aastore
    //   398: ldc 101
    //   400: aload 6
    //   402: aload 7
    //   404: invokevirtual 105	java/lang/Class:getMethod	(Ljava/lang/String;[Ljava/lang/Class;)Ljava/lang/reflect/Method;
    //   407: astore 8
    //   409: iconst_4
    //   410: anewarray 107	java/lang/Object
    //   413: astore 9
    //   415: aload 9
    //   417: iconst_0
    //   418: ldc_w 356
    //   421: aastore
    //   422: aload 9
    //   424: iconst_1
    //   425: sipush 213
    //   428: invokestatic 111	java/lang/Character:valueOf	(C)Ljava/lang/Character;
    //   431: aastore
    //   432: aload 9
    //   434: iconst_2
    //   435: sipush 192
    //   438: invokestatic 111	java/lang/Character:valueOf	(C)Ljava/lang/Character;
    //   441: aastore
    //   442: aload 9
    //   444: iconst_3
    //   445: iconst_2
    //   446: invokestatic 111	java/lang/Character:valueOf	(C)Ljava/lang/Character;
    //   449: aastore
    //   450: aload 8
    //   452: aconst_null
    //   453: aload 9
    //   455: invokevirtual 117	java/lang/reflect/Method:invoke	(Ljava/lang/Object;[Ljava/lang/Object;)Ljava/lang/Object;
    //   458: astore 11
    //   460: aload_2
    //   461: bipush 108
    //   463: aload 11
    //   465: checkcast 67	java/lang/String
    //   468: iconst_1
    //   469: invokevirtual 360	com/db/pwcc/dbmobile/transfer/widgets/inputFields/InputField:setRules	(ILjava/lang/String;Z)V
    //   472: aload_0
    //   473: new 362	uuuuuu/tnnntn
    //   476: dup
    //   477: invokespecial 363	uuuuuu/tnnntn:<init>	()V
    //   480: putfield 157	com/db/pwcc/dbmobile/transfer/inputscreen/activities/InputSubaccountActivity:presenter	Luuuuuu/tnnntn;
    //   483: aload_0
    //   484: getfield 157	com/db/pwcc/dbmobile/transfer/inputscreen/activities/InputSubaccountActivity:presenter	Luuuuuu/tnnntn;
    //   487: astore 12
    //   489: ldc_w 362
    //   492: ldc_w 365
    //   495: sipush 159
    //   498: bipush 117
    //   500: iconst_3
    //   501: invokestatic 91	xxxxxx/uxxxxx:bbbb0062b0062b0062b0062	(Ljava/lang/String;CCC)Ljava/lang/String;
    //   504: iconst_1
    //   505: anewarray 93	java/lang/Class
    //   508: dup
    //   509: iconst_0
    //   510: ldc 6
    //   512: aastore
    //   513: invokevirtual 105	java/lang/Class:getMethod	(Ljava/lang/String;[Ljava/lang/Class;)Ljava/lang/reflect/Method;
    //   516: astore 13
    //   518: iconst_1
    //   519: anewarray 107	java/lang/Object
    //   522: dup
    //   523: iconst_0
    //   524: aload_0
    //   525: aastore
    //   526: astore 14
    //   528: aload 13
    //   530: aload 12
    //   532: aload 14
    //   534: invokevirtual 117	java/lang/reflect/Method:invoke	(Ljava/lang/Object;[Ljava/lang/Object;)Ljava/lang/Object;
    //   537: pop
    //   538: return
    //   539: astore 10
    //   541: aload 10
    //   543: invokevirtual 152	java/lang/reflect/InvocationTargetException:getCause	()Ljava/lang/Throwable;
    //   546: athrow
    //   547: astore 15
    //   549: aload 15
    //   551: invokevirtual 152	java/lang/reflect/InvocationTargetException:getCause	()Ljava/lang/Throwable;
    //   554: athrow
    // Local variable table:
    //   start	length	slot	name	signature
    //   0	555	0	this	InputSubaccountActivity
    //   138	10	1	localLayoutTransition	android.animation.LayoutTransition
    //   234	227	2	localInputField	InputField
    //   238	58	3	i	int
    //   242	54	4	j	int
    //   247	11	5	k	int
    //   363	38	6	str	String
    //   369	34	7	arrayOfClass	Class[]
    //   407	44	8	localMethod1	Method
    //   413	41	9	arrayOfObject1	Object[]
    //   539	3	10	localInvocationTargetException1	InvocationTargetException
    //   458	6	11	localObject	Object
    //   487	44	12	localTnnntn	tnnntn
    //   516	13	13	localMethod2	Method
    //   526	7	14	arrayOfObject2	Object[]
    //   547	3	15	localInvocationTargetException2	InvocationTargetException
    // Exception table:
    //   from	to	target	type
    //   450	460	539	java/lang/reflect/InvocationTargetException
    //   528	538	547	java/lang/reflect/InvocationTargetException
  }
  
  public static Intent makeIntent(Context paramContext)
  {
    int i = (bt0074tttt0074tt + b00740074tttt0074tt) * bt0074tttt0074tt % b007400740074ttt0074tt;
    int j = bttt0074tt0074tt();
    if ((b0074t0074ttt0074tt() + b00740074tttt0074tt) * b0074t0074ttt0074tt() % b007400740074ttt0074tt != b0074tt0074tt0074tt)
    {
      bt0074tttt0074tt = 1;
      b0074tt0074tt0074tt = 62;
    }
    if (i != j)
    {
      if ((bt0074tttt0074tt + b00740074tttt0074tt) * bt0074tttt0074tt % b007400740074ttt0074tt != b0074tt0074tt0074tt)
      {
        bt0074tttt0074tt = 37;
        b0074tt0074tt0074tt = 72;
      }
      bt0074tttt0074tt = b0074t0074ttt0074tt();
      b0074tt0074tt0074tt = 20;
      if ((bt0074tttt0074tt + b00740074tttt0074tt) * bt0074tttt0074tt % b007400740074ttt0074tt != b0074tt0074tt0074tt)
      {
        bt0074tttt0074tt = b0074t0074ttt0074tt();
        b0074tt0074tt0074tt = 65;
      }
    }
    return makeIntent(paramContext, null, null);
  }
  
  /* Error */
  public static Intent makeIntent(Context paramContext, String paramString1, String paramString2)
  {
    // Byte code:
    //   0: getstatic 73	com/db/pwcc/dbmobile/transfer/inputscreen/activities/InputSubaccountActivity:bt0074tttt0074tt	I
    //   3: istore_3
    //   4: iload_3
    //   5: iload_3
    //   6: getstatic 75	com/db/pwcc/dbmobile/transfer/inputscreen/activities/InputSubaccountActivity:b00740074tttt0074tt	I
    //   9: iadd
    //   10: imul
    //   11: invokestatic 78	com/db/pwcc/dbmobile/transfer/inputscreen/activities/InputSubaccountActivity:btt0074ttt0074tt	()I
    //   14: irem
    //   15: tableswitch	default:+17->32, 0:+28->43
    //   32: bipush 94
    //   34: putstatic 73	com/db/pwcc/dbmobile/transfer/inputscreen/activities/InputSubaccountActivity:bt0074tttt0074tt	I
    //   37: invokestatic 81	com/db/pwcc/dbmobile/transfer/inputscreen/activities/InputSubaccountActivity:b0074t0074ttt0074tt	()I
    //   40: putstatic 191	com/db/pwcc/dbmobile/transfer/inputscreen/activities/InputSubaccountActivity:b0074tt0074tt0074tt	I
    //   43: new 372	android/content/Intent
    //   46: dup
    //   47: aload_0
    //   48: ldc 2
    //   50: invokespecial 375	android/content/Intent:<init>	(Landroid/content/Context;Ljava/lang/Class;)V
    //   53: astore 4
    //   55: aload_1
    //   56: ifnull +156 -> 212
    //   59: ldc_w 377
    //   62: sipush 166
    //   65: bipush 54
    //   67: iconst_0
    //   68: invokestatic 91	xxxxxx/uxxxxx:bbbb0062b0062b0062b0062	(Ljava/lang/String;CCC)Ljava/lang/String;
    //   71: astore 12
    //   73: iconst_3
    //   74: anewarray 93	java/lang/Class
    //   77: astore 13
    //   79: aload 13
    //   81: iconst_0
    //   82: ldc 67
    //   84: aastore
    //   85: aload 13
    //   87: iconst_1
    //   88: getstatic 99	java/lang/Character:TYPE	Ljava/lang/Class;
    //   91: aastore
    //   92: aload 13
    //   94: iconst_2
    //   95: getstatic 99	java/lang/Character:TYPE	Ljava/lang/Class;
    //   98: aastore
    //   99: ldc 101
    //   101: aload 12
    //   103: aload 13
    //   105: invokevirtual 105	java/lang/Class:getMethod	(Ljava/lang/String;[Ljava/lang/Class;)Ljava/lang/reflect/Method;
    //   108: astore 14
    //   110: iconst_3
    //   111: anewarray 107	java/lang/Object
    //   114: astore 15
    //   116: aload 15
    //   118: iconst_0
    //   119: ldc_w 379
    //   122: aastore
    //   123: aload 15
    //   125: iconst_1
    //   126: bipush 118
    //   128: invokestatic 111	java/lang/Character:valueOf	(C)Ljava/lang/Character;
    //   131: aastore
    //   132: aload 15
    //   134: iconst_2
    //   135: iconst_0
    //   136: invokestatic 111	java/lang/Character:valueOf	(C)Ljava/lang/Character;
    //   139: aastore
    //   140: aload 14
    //   142: aconst_null
    //   143: aload 15
    //   145: invokevirtual 117	java/lang/reflect/Method:invoke	(Ljava/lang/Object;[Ljava/lang/Object;)Ljava/lang/Object;
    //   148: astore 17
    //   150: aload 17
    //   152: checkcast 67	java/lang/String
    //   155: astore 18
    //   157: getstatic 73	com/db/pwcc/dbmobile/transfer/inputscreen/activities/InputSubaccountActivity:bt0074tttt0074tt	I
    //   160: istore 19
    //   162: iload 19
    //   164: iload 19
    //   166: getstatic 75	com/db/pwcc/dbmobile/transfer/inputscreen/activities/InputSubaccountActivity:b00740074tttt0074tt	I
    //   169: iadd
    //   170: imul
    //   171: invokestatic 78	com/db/pwcc/dbmobile/transfer/inputscreen/activities/InputSubaccountActivity:btt0074ttt0074tt	()I
    //   174: irem
    //   175: tableswitch	default:+17->192, 0:+28->203
    //   192: invokestatic 81	com/db/pwcc/dbmobile/transfer/inputscreen/activities/InputSubaccountActivity:b0074t0074ttt0074tt	()I
    //   195: putstatic 73	com/db/pwcc/dbmobile/transfer/inputscreen/activities/InputSubaccountActivity:bt0074tttt0074tt	I
    //   198: bipush 49
    //   200: putstatic 191	com/db/pwcc/dbmobile/transfer/inputscreen/activities/InputSubaccountActivity:b0074tt0074tt0074tt	I
    //   203: aload 4
    //   205: aload 18
    //   207: aload_1
    //   208: invokevirtual 383	android/content/Intent:putExtra	(Ljava/lang/String;Ljava/lang/String;)Landroid/content/Intent;
    //   211: pop
    //   212: getstatic 73	com/db/pwcc/dbmobile/transfer/inputscreen/activities/InputSubaccountActivity:bt0074tttt0074tt	I
    //   215: getstatic 75	com/db/pwcc/dbmobile/transfer/inputscreen/activities/InputSubaccountActivity:b00740074tttt0074tt	I
    //   218: iadd
    //   219: getstatic 73	com/db/pwcc/dbmobile/transfer/inputscreen/activities/InputSubaccountActivity:bt0074tttt0074tt	I
    //   222: imul
    //   223: getstatic 132	com/db/pwcc/dbmobile/transfer/inputscreen/activities/InputSubaccountActivity:b007400740074ttt0074tt	I
    //   226: irem
    //   227: invokestatic 187	com/db/pwcc/dbmobile/transfer/inputscreen/activities/InputSubaccountActivity:bttt0074tt0074tt	()I
    //   230: if_icmpeq +14 -> 244
    //   233: invokestatic 81	com/db/pwcc/dbmobile/transfer/inputscreen/activities/InputSubaccountActivity:b0074t0074ttt0074tt	()I
    //   236: putstatic 73	com/db/pwcc/dbmobile/transfer/inputscreen/activities/InputSubaccountActivity:bt0074tttt0074tt	I
    //   239: bipush 91
    //   241: putstatic 191	com/db/pwcc/dbmobile/transfer/inputscreen/activities/InputSubaccountActivity:b0074tt0074tt0074tt	I
    //   244: getstatic 73	com/db/pwcc/dbmobile/transfer/inputscreen/activities/InputSubaccountActivity:bt0074tttt0074tt	I
    //   247: getstatic 75	com/db/pwcc/dbmobile/transfer/inputscreen/activities/InputSubaccountActivity:b00740074tttt0074tt	I
    //   250: iadd
    //   251: getstatic 73	com/db/pwcc/dbmobile/transfer/inputscreen/activities/InputSubaccountActivity:bt0074tttt0074tt	I
    //   254: imul
    //   255: getstatic 132	com/db/pwcc/dbmobile/transfer/inputscreen/activities/InputSubaccountActivity:b007400740074ttt0074tt	I
    //   258: irem
    //   259: invokestatic 187	com/db/pwcc/dbmobile/transfer/inputscreen/activities/InputSubaccountActivity:bttt0074tt0074tt	()I
    //   262: if_icmpeq +15 -> 277
    //   265: invokestatic 81	com/db/pwcc/dbmobile/transfer/inputscreen/activities/InputSubaccountActivity:b0074t0074ttt0074tt	()I
    //   268: putstatic 73	com/db/pwcc/dbmobile/transfer/inputscreen/activities/InputSubaccountActivity:bt0074tttt0074tt	I
    //   271: invokestatic 81	com/db/pwcc/dbmobile/transfer/inputscreen/activities/InputSubaccountActivity:b0074t0074ttt0074tt	()I
    //   274: putstatic 191	com/db/pwcc/dbmobile/transfer/inputscreen/activities/InputSubaccountActivity:b0074tt0074tt0074tt	I
    //   277: ldc_w 385
    //   280: sipush 228
    //   283: sipush 154
    //   286: iconst_2
    //   287: invokestatic 91	xxxxxx/uxxxxx:bbbb0062b0062b0062b0062	(Ljava/lang/String;CCC)Ljava/lang/String;
    //   290: astore 5
    //   292: iconst_4
    //   293: anewarray 93	java/lang/Class
    //   296: astore 6
    //   298: aload 6
    //   300: iconst_0
    //   301: ldc 67
    //   303: aastore
    //   304: aload 6
    //   306: iconst_1
    //   307: getstatic 99	java/lang/Character:TYPE	Ljava/lang/Class;
    //   310: aastore
    //   311: aload 6
    //   313: iconst_2
    //   314: getstatic 99	java/lang/Character:TYPE	Ljava/lang/Class;
    //   317: aastore
    //   318: aload 6
    //   320: iconst_3
    //   321: getstatic 99	java/lang/Character:TYPE	Ljava/lang/Class;
    //   324: aastore
    //   325: ldc 101
    //   327: aload 5
    //   329: aload 6
    //   331: invokevirtual 105	java/lang/Class:getMethod	(Ljava/lang/String;[Ljava/lang/Class;)Ljava/lang/reflect/Method;
    //   334: astore 7
    //   336: iconst_4
    //   337: anewarray 107	java/lang/Object
    //   340: astore 8
    //   342: aload 8
    //   344: iconst_0
    //   345: ldc_w 387
    //   348: aastore
    //   349: aload 8
    //   351: iconst_1
    //   352: sipush 205
    //   355: invokestatic 111	java/lang/Character:valueOf	(C)Ljava/lang/Character;
    //   358: aastore
    //   359: aload 8
    //   361: iconst_2
    //   362: bipush 15
    //   364: invokestatic 111	java/lang/Character:valueOf	(C)Ljava/lang/Character;
    //   367: aastore
    //   368: aload 8
    //   370: iconst_3
    //   371: iconst_3
    //   372: invokestatic 111	java/lang/Character:valueOf	(C)Ljava/lang/Character;
    //   375: aastore
    //   376: aload 7
    //   378: aconst_null
    //   379: aload 8
    //   381: invokevirtual 117	java/lang/reflect/Method:invoke	(Ljava/lang/Object;[Ljava/lang/Object;)Ljava/lang/Object;
    //   384: astore 10
    //   386: aload 4
    //   388: aload 10
    //   390: checkcast 67	java/lang/String
    //   393: aload_2
    //   394: invokevirtual 383	android/content/Intent:putExtra	(Ljava/lang/String;Ljava/lang/String;)Landroid/content/Intent;
    //   397: pop
    //   398: aload 4
    //   400: areturn
    //   401: astore 16
    //   403: aload 16
    //   405: invokevirtual 152	java/lang/reflect/InvocationTargetException:getCause	()Ljava/lang/Throwable;
    //   408: athrow
    //   409: astore 9
    //   411: aload 9
    //   413: invokevirtual 152	java/lang/reflect/InvocationTargetException:getCause	()Ljava/lang/Throwable;
    //   416: athrow
    // Local variable table:
    //   start	length	slot	name	signature
    //   0	417	0	paramContext	Context
    //   0	417	1	paramString1	String
    //   0	417	2	paramString2	String
    //   3	8	3	i	int
    //   53	346	4	localIntent	Intent
    //   290	38	5	str1	String
    //   296	34	6	arrayOfClass1	Class[]
    //   334	43	7	localMethod1	Method
    //   340	40	8	arrayOfObject1	Object[]
    //   409	3	9	localInvocationTargetException1	InvocationTargetException
    //   384	5	10	localObject1	Object
    //   71	31	12	str2	String
    //   77	27	13	arrayOfClass2	Class[]
    //   108	33	14	localMethod2	Method
    //   114	30	15	arrayOfObject2	Object[]
    //   401	3	16	localInvocationTargetException2	InvocationTargetException
    //   148	3	17	localObject2	Object
    //   155	51	18	str3	String
    //   160	11	19	j	int
    // Exception table:
    //   from	to	target	type
    //   140	150	401	java/lang/reflect/InvocationTargetException
    //   376	386	409	java/lang/reflect/InvocationTargetException
  }
  
  private void resetUserInput()
  {
    this.accountSelector.setSelectedItemPosition(0);
    generateSubaccountsList(0);
    this.subaccountSelector.deselectWithText(getResources().getString(R.string.sepatransfer_input_subaccount_picker_default));
    if ((b0074t0074ttt0074tt() + b00740074tttt0074tt) * b0074t0074ttt0074tt() % b007400740074ttt0074tt != b0074tt0074tt0074tt)
    {
      bt0074tttt0074tt = 47;
      b0074tt0074tt0074tt = 14;
    }
    int i = bt0074tttt0074tt;
    switch (i * (i + b00740074tttt0074tt) % b007400740074ttt0074tt)
    {
    default: 
      bt0074tttt0074tt = 4;
      b0074tt0074tt0074tt = b0074t0074ttt0074tt();
    }
    int j = bt0074tttt0074tt;
    switch (j * (j + b00740074tttt0074tt) % btt0074ttt0074tt())
    {
    default: 
      bt0074tttt0074tt = 27;
      b0074tt0074tt0074tt = b0074t0074ttt0074tt();
    }
    this.amount.setText("");
    InputField localInputField = this.description;
    int k = b0074t0074ttt0074tt();
    switch (k * (k + b00740074tttt0074tt) % b007400740074ttt0074tt)
    {
    default: 
      bt0074tttt0074tt = 4;
      b0074tt0074tt0074tt = b0074t0074ttt0074tt();
    }
    localInputField.setText("");
  }
  
  private void selectPrincipleAccount()
  {
    Intent localIntent = getIntent();
    if ((bt0074tttt0074tt + bt00740074ttt0074tt()) * bt0074tttt0074tt % b007400740074ttt0074tt != b0074tt0074tt0074tt)
    {
      bt0074tttt0074tt = b0074t0074ttt0074tt();
      b0074tt0074tt0074tt = 20;
    }
    Method localMethod1;
    Object[] arrayOfObject1;
    if (localIntent != null)
    {
      String str1 = uxxxxx.bb00620062bb0062b0062b0062("H^_`a\033\034$%\037 ()j$%-.()12s", '', '\001');
      Class[] arrayOfClass1 = new Class[3];
      arrayOfClass1[0] = String.class;
      arrayOfClass1[1] = Character.TYPE;
      arrayOfClass1[2] = Character.TYPE;
      localMethod1 = ppphhp.class.getMethod(str1, arrayOfClass1);
      arrayOfObject1 = new Object[3];
      arrayOfObject1[0] = "wxnrfkqld]^_^infkU^X";
      arrayOfObject1[1] = Character.valueOf('x');
      arrayOfObject1[2] = Character.valueOf('\003');
    }
    label427:
    for (;;)
    {
      try
      {
        Object localObject1 = localMethod1.invoke(null, arrayOfObject1);
        lvvvvv localLvvvvv;
        Method localMethod2;
        Object[] arrayOfObject2;
        if (localIntent.hasExtra((String)localObject1))
        {
          localLvvvvv = this.accountAdapter;
          int i = bt0074tttt0074tt;
          switch (i * (i + b00740074tttt0074tt) % b007400740074ttt0074tt)
          {
          default: 
            bt0074tttt0074tt = 18;
            b0074tt0074tt0074tt = b0074t0074ttt0074tt();
          }
          int j = bt0074tttt0074tt;
          int k = j * (j + b00740074tttt0074tt);
          int m = bt0074tttt0074tt;
          switch (m * (m + b00740074tttt0074tt) % b007400740074ttt0074tt)
          {
          default: 
            bt0074tttt0074tt = b0074t0074ttt0074tt();
            b0074tt0074tt0074tt = 99;
          }
          switch (k % b007400740074ttt0074tt)
          {
          default: 
            bt0074tttt0074tt = 68;
            b0074tt0074tt0074tt = 33;
          }
          String str2 = uxxxxx.bbbb0062b0062b0062b0062("\020&'()bcklfgop2kltuopxy;", '\005', '(', '\003');
          Class[] arrayOfClass2 = new Class[3];
          arrayOfClass2[0] = String.class;
          arrayOfClass2[1] = Character.TYPE;
          arrayOfClass2[2] = Character.TYPE;
          localMethod2 = ppphhp.class.getMethod(str2, arrayOfClass2);
          arrayOfObject2 = new Object[3];
          arrayOfObject2[0] = "klbfZ_e`XQRSR]bZ_IRL";
          arrayOfObject2[1] = Character.valueOf('');
          arrayOfObject2[2] = Character.valueOf('\004');
        }
        Object localObject2;
        DbPicker localDbPicker;
        int n = 0;
      }
      catch (InvocationTargetException localInvocationTargetException1)
      {
        try
        {
          localObject2 = localMethod2.invoke(null, arrayOfObject2);
          n = localLvvvvv.bi0069i0069ii0069006900690069(localIntent.getStringExtra((String)localObject2));
          localDbPicker = this.accountSelector;
          if (n <= 0) {
            break label427;
          }
          localDbPicker.setSelectedItemPosition(n);
          return;
        }
        catch (InvocationTargetException localInvocationTargetException2)
        {
          throw localInvocationTargetException2.getCause();
        }
        localInvocationTargetException1 = localInvocationTargetException1;
        throw localInvocationTargetException1.getCause();
      }
    }
  }
  
  private void setDifferentPrefilledAccounts()
  {
    if ((this.accountAdapter == null) || (this.subaccountAdapter == null)) {}
    do
    {
      return;
      do
      {
        int i = this.accountAdapter.getCount();
        int j = bt0074tttt0074tt;
        switch (j * (j + b00740074tttt0074tt) % b007400740074ttt0074tt)
        {
        default: 
          bt0074tttt0074tt = b0074t0074ttt0074tt();
          b0074tt0074tt0074tt = 12;
          if ((bt0074tttt0074tt + b00740074tttt0074tt) * bt0074tttt0074tt % b007400740074ttt0074tt != b0074tt0074tt0074tt)
          {
            bt0074tttt0074tt = 15;
            b0074tt0074tt0074tt = 22;
          }
          break;
        }
        if (i <= 1) {
          break;
        }
        this.accountSelector.setSelectedItemPosition(1);
        int k = bt0074tttt0074tt;
        switch (k * (k + b00740074tttt0074tt) % b007400740074ttt0074tt)
        {
        }
        bt0074tttt0074tt = b0074t0074ttt0074tt();
        b0074tt0074tt0074tt = 41;
        return;
        if (!this.accountAdapter.b0069ii0069ii0069006900690069(0).getAccountNumber().equals(this.subaccountAdapter.b0069ii0069ii0069006900690069(0).getAccountNumber())) {
          break;
        }
      } while (this.subaccountAdapter.getCount() <= 1);
      this.subaccountSelector.setSelectedItemPosition(1);
    } while ((bt0074tttt0074tt + bt00740074ttt0074tt()) * bt0074tttt0074tt % b007400740074ttt0074tt == b0074tt0074tt0074tt);
    bt0074tttt0074tt = 21;
    b0074tt0074tt0074tt = 53;
  }
  
  private void updateAmountDefaultLabel()
  {
    int i = bt0074tttt0074tt;
    switch (i * (i + b00740074tttt0074tt) % b007400740074ttt0074tt)
    {
    default: 
      bt0074tttt0074tt = 70;
      b0074tt0074tt0074tt = b0074t0074ttt0074tt();
    }
    int j = bt0074tttt0074tt;
    switch (j * (j + b00740074tttt0074tt) % b007400740074ttt0074tt)
    {
    default: 
      bt0074tttt0074tt = 67;
      b0074tt0074tt0074tt = 25;
      int k = bt0074tttt0074tt;
      switch (k * (k + bt00740074ttt0074tt()) % b007400740074ttt0074tt)
      {
      default: 
        bt0074tttt0074tt = b0074t0074ttt0074tt();
        b0074tt0074tt0074tt = 29;
      }
      break;
    }
    DbTextView localDbTextView = this.amountErrorMessage;
    if ((bt0074tttt0074tt + b00740074tttt0074tt) * bt0074tttt0074tt % b007400740074ttt0074tt != b0074tt0074tt0074tt)
    {
      bt0074tttt0074tt = b0074t0074ttt0074tt();
      b0074tt0074tt0074tt = b0074t0074ttt0074tt();
    }
    localDbTextView.setVisibility(8);
  }
  
  private void updateButtonBackground()
  {
    if (isTheInputValid()) {
      this.buttonDone.changeButtonState(kvkvvv.bf00660066f0066f006600660066);
    }
    do
    {
      return;
      this.buttonDone.changeButtonState(kvkvvv.bff0066f0066f006600660066);
    } while ((bt0074tttt0074tt + b00740074tttt0074tt) * bt0074tttt0074tt % b007400740074ttt0074tt == b0074tt0074tt0074tt);
    int i = (bt0074tttt0074tt + b00740074tttt0074tt) * bt0074tttt0074tt % b007400740074ttt0074tt;
    int j = b0074tt0074tt0074tt;
    int k = bt0074tttt0074tt;
    switch (k * (k + b00740074tttt0074tt) % b007400740074ttt0074tt)
    {
    default: 
      bt0074tttt0074tt = 62;
      b0074tt0074tt0074tt = b0074t0074ttt0074tt();
    }
    if (i != j)
    {
      bt0074tttt0074tt = 33;
      b0074tt0074tt0074tt = 50;
    }
    bt0074tttt0074tt = b0074t0074ttt0074tt();
    b0074tt0074tt0074tt = b0074t0074ttt0074tt();
    int m = bt0074tttt0074tt;
    switch (m * (m + bt00740074ttt0074tt()) % b007400740074ttt0074tt)
    {
    }
    bt0074tttt0074tt = 1;
    b0074tt0074tt0074tt = b0074t0074ttt0074tt();
  }
  
  public boolean dispatchTouchEvent(MotionEvent paramMotionEvent)
  {
    vlvvlv.b00690069iiiii006900690069(paramMotionEvent, this.accountSelector, this.subaccountSelector);
    int i = b0074t0074ttt0074tt();
    int j = b0074t0074ttt0074tt();
    switch (j * (j + b00740074tttt0074tt) % b007400740074ttt0074tt)
    {
    default: 
      bt0074tttt0074tt = b0074t0074ttt0074tt();
      b0074tt0074tt0074tt = 94;
    }
    if ((i + b00740074tttt0074tt) * b0074t0074ttt0074tt() % btt0074ttt0074tt() != b0074tt0074tt0074tt)
    {
      int k = bt0074tttt0074tt;
      switch (k * (k + b00740074tttt0074tt) % b007400740074ttt0074tt)
      {
      default: 
        int m = b0074t0074ttt0074tt();
        if ((bt0074tttt0074tt + b00740074tttt0074tt) * bt0074tttt0074tt % b007400740074ttt0074tt != b0074tt0074tt0074tt)
        {
          bt0074tttt0074tt = 66;
          b0074tt0074tt0074tt = 3;
        }
        bt0074tttt0074tt = m;
        b0074tt0074tt0074tt = 7;
      }
      bt0074tttt0074tt = b0074t0074ttt0074tt();
      b0074tt0074tt0074tt = 99;
    }
    return super.dispatchTouchEvent(paramMotionEvent);
  }
  
  public BigDecimal getAmount()
  {
    int i = (bt0074tttt0074tt + b00740074tttt0074tt) * bt0074tttt0074tt;
    if ((bt0074tttt0074tt + b00740074tttt0074tt) * bt0074tttt0074tt % b007400740074ttt0074tt != b0074tt0074tt0074tt)
    {
      bt0074tttt0074tt = b0074t0074ttt0074tt();
      b0074tt0074tt0074tt = 96;
    }
    if (i % b007400740074ttt0074tt != b0074tt0074tt0074tt)
    {
      bt0074tttt0074tt = 19;
      b0074tt0074tt0074tt = b0074t0074ttt0074tt();
    }
    BigDecimal localBigDecimal = vvllvv.bi0069iii0069i006900690069(this.amount.getText().toString().trim());
    int j = bt0074tttt0074tt;
    switch (j * (j + b00740074tttt0074tt) % b007400740074ttt0074tt)
    {
    default: 
      bt0074tttt0074tt = b0074t0074ttt0074tt();
      b0074tt0074tt0074tt = b0074t0074ttt0074tt();
    }
    return localBigDecimal;
  }
  
  /* Error */
  public String getDescription()
  {
    // Byte code:
    //   0: getstatic 73	com/db/pwcc/dbmobile/transfer/inputscreen/activities/InputSubaccountActivity:bt0074tttt0074tt	I
    //   3: getstatic 75	com/db/pwcc/dbmobile/transfer/inputscreen/activities/InputSubaccountActivity:b00740074tttt0074tt	I
    //   6: iadd
    //   7: getstatic 73	com/db/pwcc/dbmobile/transfer/inputscreen/activities/InputSubaccountActivity:bt0074tttt0074tt	I
    //   10: imul
    //   11: getstatic 132	com/db/pwcc/dbmobile/transfer/inputscreen/activities/InputSubaccountActivity:b007400740074ttt0074tt	I
    //   14: irem
    //   15: getstatic 191	com/db/pwcc/dbmobile/transfer/inputscreen/activities/InputSubaccountActivity:b0074tt0074tt0074tt	I
    //   18: if_icmpeq +15 -> 33
    //   21: invokestatic 81	com/db/pwcc/dbmobile/transfer/inputscreen/activities/InputSubaccountActivity:b0074t0074ttt0074tt	()I
    //   24: putstatic 73	com/db/pwcc/dbmobile/transfer/inputscreen/activities/InputSubaccountActivity:bt0074tttt0074tt	I
    //   27: invokestatic 81	com/db/pwcc/dbmobile/transfer/inputscreen/activities/InputSubaccountActivity:b0074t0074ttt0074tt	()I
    //   30: putstatic 191	com/db/pwcc/dbmobile/transfer/inputscreen/activities/InputSubaccountActivity:b0074tt0074tt0074tt	I
    //   33: getstatic 73	com/db/pwcc/dbmobile/transfer/inputscreen/activities/InputSubaccountActivity:bt0074tttt0074tt	I
    //   36: istore_1
    //   37: iload_1
    //   38: iload_1
    //   39: getstatic 75	com/db/pwcc/dbmobile/transfer/inputscreen/activities/InputSubaccountActivity:b00740074tttt0074tt	I
    //   42: iadd
    //   43: imul
    //   44: getstatic 132	com/db/pwcc/dbmobile/transfer/inputscreen/activities/InputSubaccountActivity:b007400740074ttt0074tt	I
    //   47: irem
    //   48: tableswitch	default:+20->68, 0:+78->126
    //   68: getstatic 73	com/db/pwcc/dbmobile/transfer/inputscreen/activities/InputSubaccountActivity:bt0074tttt0074tt	I
    //   71: istore 17
    //   73: iload 17
    //   75: iload 17
    //   77: getstatic 75	com/db/pwcc/dbmobile/transfer/inputscreen/activities/InputSubaccountActivity:b00740074tttt0074tt	I
    //   80: iadd
    //   81: imul
    //   82: getstatic 132	com/db/pwcc/dbmobile/transfer/inputscreen/activities/InputSubaccountActivity:b007400740074ttt0074tt	I
    //   85: irem
    //   86: tableswitch	default:+18->104, 0:+30->116
    //   104: invokestatic 81	com/db/pwcc/dbmobile/transfer/inputscreen/activities/InputSubaccountActivity:b0074t0074ttt0074tt	()I
    //   107: putstatic 73	com/db/pwcc/dbmobile/transfer/inputscreen/activities/InputSubaccountActivity:bt0074tttt0074tt	I
    //   110: invokestatic 81	com/db/pwcc/dbmobile/transfer/inputscreen/activities/InputSubaccountActivity:b0074t0074ttt0074tt	()I
    //   113: putstatic 191	com/db/pwcc/dbmobile/transfer/inputscreen/activities/InputSubaccountActivity:b0074tt0074tt0074tt	I
    //   116: bipush 33
    //   118: putstatic 73	com/db/pwcc/dbmobile/transfer/inputscreen/activities/InputSubaccountActivity:bt0074tttt0074tt	I
    //   121: bipush 27
    //   123: putstatic 191	com/db/pwcc/dbmobile/transfer/inputscreen/activities/InputSubaccountActivity:b0074tt0074tt0074tt	I
    //   126: aload_0
    //   127: getfield 163	com/db/pwcc/dbmobile/transfer/inputscreen/activities/InputSubaccountActivity:description	Lcom/db/pwcc/dbmobile/transfer/widgets/inputFields/InputField;
    //   130: invokevirtual 489	com/db/pwcc/dbmobile/transfer/widgets/inputFields/InputField:getText	()Landroid/text/Editable;
    //   133: invokevirtual 478	java/lang/Object:toString	()Ljava/lang/String;
    //   136: invokevirtual 481	java/lang/String:trim	()Ljava/lang/String;
    //   139: astore_2
    //   140: ldc_w 491
    //   143: bipush 18
    //   145: sipush 128
    //   148: iconst_2
    //   149: invokestatic 91	xxxxxx/uxxxxx:bbbb0062b0062b0062b0062	(Ljava/lang/String;CCC)Ljava/lang/String;
    //   152: astore_3
    //   153: iconst_4
    //   154: anewarray 93	java/lang/Class
    //   157: astore 4
    //   159: aload 4
    //   161: iconst_0
    //   162: ldc 67
    //   164: aastore
    //   165: aload 4
    //   167: iconst_1
    //   168: getstatic 99	java/lang/Character:TYPE	Ljava/lang/Class;
    //   171: aastore
    //   172: aload 4
    //   174: iconst_2
    //   175: getstatic 99	java/lang/Character:TYPE	Ljava/lang/Class;
    //   178: aastore
    //   179: aload 4
    //   181: iconst_3
    //   182: getstatic 99	java/lang/Character:TYPE	Ljava/lang/Class;
    //   185: aastore
    //   186: ldc 101
    //   188: aload_3
    //   189: aload 4
    //   191: invokevirtual 105	java/lang/Class:getMethod	(Ljava/lang/String;[Ljava/lang/Class;)Ljava/lang/reflect/Method;
    //   194: astore 5
    //   196: iconst_4
    //   197: anewarray 107	java/lang/Object
    //   200: astore 6
    //   202: aload 6
    //   204: iconst_0
    //   205: ldc_w 493
    //   208: aastore
    //   209: aload 6
    //   211: iconst_1
    //   212: bipush 107
    //   214: invokestatic 111	java/lang/Character:valueOf	(C)Ljava/lang/Character;
    //   217: aastore
    //   218: aload 6
    //   220: iconst_2
    //   221: sipush 189
    //   224: invokestatic 111	java/lang/Character:valueOf	(C)Ljava/lang/Character;
    //   227: aastore
    //   228: aload 6
    //   230: iconst_3
    //   231: iconst_1
    //   232: invokestatic 111	java/lang/Character:valueOf	(C)Ljava/lang/Character;
    //   235: aastore
    //   236: aload 5
    //   238: aconst_null
    //   239: aload 6
    //   241: invokevirtual 117	java/lang/reflect/Method:invoke	(Ljava/lang/Object;[Ljava/lang/Object;)Ljava/lang/Object;
    //   244: astore 8
    //   246: aload 8
    //   248: checkcast 67	java/lang/String
    //   251: astore 9
    //   253: ldc_w 495
    //   256: sipush 235
    //   259: iconst_4
    //   260: invokestatic 138	xxxxxx/uxxxxx:bb00620062bb0062b0062b0062	(Ljava/lang/String;CC)Ljava/lang/String;
    //   263: astore 10
    //   265: iconst_3
    //   266: anewarray 93	java/lang/Class
    //   269: astore 11
    //   271: aload 11
    //   273: iconst_0
    //   274: ldc 67
    //   276: aastore
    //   277: aload 11
    //   279: iconst_1
    //   280: getstatic 99	java/lang/Character:TYPE	Ljava/lang/Class;
    //   283: aastore
    //   284: aload 11
    //   286: iconst_2
    //   287: getstatic 99	java/lang/Character:TYPE	Ljava/lang/Class;
    //   290: aastore
    //   291: ldc 101
    //   293: aload 10
    //   295: aload 11
    //   297: invokevirtual 105	java/lang/Class:getMethod	(Ljava/lang/String;[Ljava/lang/Class;)Ljava/lang/reflect/Method;
    //   300: astore 12
    //   302: iconst_3
    //   303: anewarray 107	java/lang/Object
    //   306: astore 13
    //   308: aload 13
    //   310: iconst_0
    //   311: ldc_w 497
    //   314: aastore
    //   315: aload 13
    //   317: iconst_1
    //   318: bipush 47
    //   320: invokestatic 111	java/lang/Character:valueOf	(C)Ljava/lang/Character;
    //   323: aastore
    //   324: aload 13
    //   326: iconst_2
    //   327: iconst_0
    //   328: invokestatic 111	java/lang/Character:valueOf	(C)Ljava/lang/Character;
    //   331: aastore
    //   332: aload 12
    //   334: aconst_null
    //   335: aload 13
    //   337: invokevirtual 117	java/lang/reflect/Method:invoke	(Ljava/lang/Object;[Ljava/lang/Object;)Ljava/lang/Object;
    //   340: astore 15
    //   342: aload_2
    //   343: aload 9
    //   345: aload 15
    //   347: checkcast 67	java/lang/String
    //   350: invokevirtual 501	java/lang/String:replaceAll	(Ljava/lang/String;Ljava/lang/String;)Ljava/lang/String;
    //   353: astore 16
    //   355: getstatic 73	com/db/pwcc/dbmobile/transfer/inputscreen/activities/InputSubaccountActivity:bt0074tttt0074tt	I
    //   358: getstatic 75	com/db/pwcc/dbmobile/transfer/inputscreen/activities/InputSubaccountActivity:b00740074tttt0074tt	I
    //   361: iadd
    //   362: getstatic 73	com/db/pwcc/dbmobile/transfer/inputscreen/activities/InputSubaccountActivity:bt0074tttt0074tt	I
    //   365: imul
    //   366: getstatic 132	com/db/pwcc/dbmobile/transfer/inputscreen/activities/InputSubaccountActivity:b007400740074ttt0074tt	I
    //   369: irem
    //   370: getstatic 191	com/db/pwcc/dbmobile/transfer/inputscreen/activities/InputSubaccountActivity:b0074tt0074tt0074tt	I
    //   373: if_icmpeq +13 -> 386
    //   376: iconst_1
    //   377: putstatic 73	com/db/pwcc/dbmobile/transfer/inputscreen/activities/InputSubaccountActivity:bt0074tttt0074tt	I
    //   380: invokestatic 81	com/db/pwcc/dbmobile/transfer/inputscreen/activities/InputSubaccountActivity:b0074t0074ttt0074tt	()I
    //   383: putstatic 191	com/db/pwcc/dbmobile/transfer/inputscreen/activities/InputSubaccountActivity:b0074tt0074tt0074tt	I
    //   386: aload 16
    //   388: areturn
    //   389: astore 7
    //   391: aload 7
    //   393: invokevirtual 152	java/lang/reflect/InvocationTargetException:getCause	()Ljava/lang/Throwable;
    //   396: athrow
    //   397: astore 14
    //   399: aload 14
    //   401: invokevirtual 152	java/lang/reflect/InvocationTargetException:getCause	()Ljava/lang/Throwable;
    //   404: athrow
    // Local variable table:
    //   start	length	slot	name	signature
    //   0	405	0	this	InputSubaccountActivity
    //   36	8	1	i	int
    //   139	204	2	str1	String
    //   152	37	3	str2	String
    //   157	33	4	arrayOfClass1	Class[]
    //   194	43	5	localMethod1	Method
    //   200	40	6	arrayOfObject1	Object[]
    //   389	3	7	localInvocationTargetException1	InvocationTargetException
    //   244	3	8	localObject1	Object
    //   251	93	9	str3	String
    //   263	31	10	str4	String
    //   269	27	11	arrayOfClass2	Class[]
    //   300	33	12	localMethod2	Method
    //   306	30	13	arrayOfObject2	Object[]
    //   397	3	14	localInvocationTargetException2	InvocationTargetException
    //   340	6	15	localObject2	Object
    //   353	34	16	str5	String
    //   71	11	17	j	int
    // Exception table:
    //   from	to	target	type
    //   236	246	389	java/lang/reflect/InvocationTargetException
    //   332	342	397	java/lang/reflect/InvocationTargetException
  }
  
  public DialogInterface.OnClickListener getHideProgressClickListener()
  {
    int i = bt0074tttt0074tt;
    int j = b00740074tttt0074tt;
    int k = bt0074tttt0074tt;
    switch (k * (k + b00740074tttt0074tt) % b007400740074ttt0074tt)
    {
    default: 
      bt0074tttt0074tt = 70;
      b0074tt0074tt0074tt = 97;
    }
    if ((i + j) * bt0074tttt0074tt % btt0074ttt0074tt() != b0074tt0074tt0074tt)
    {
      int m = bt0074tttt0074tt;
      switch (m * (m + b00740074tttt0074tt) % b007400740074ttt0074tt)
      {
      default: 
        bt0074tttt0074tt = 18;
        b0074tt0074tt0074tt = b0074t0074ttt0074tt();
      }
      if ((bt0074tttt0074tt + b00740074tttt0074tt) * bt0074tttt0074tt % b007400740074ttt0074tt != b0074tt0074tt0074tt)
      {
        bt0074tttt0074tt = b0074t0074ttt0074tt();
        b0074tt0074tt0074tt = 2;
      }
      bt0074tttt0074tt = b0074t0074ttt0074tt();
      b0074tt0074tt0074tt = b0074t0074ttt0074tt();
    }
    new DialogInterface.OnClickListener()
    {
      public static int b0062006200620062bbb00620062 = 0;
      public static int b0062b00620062bbb00620062 = 1;
      public static int bb006200620062bbb00620062 = 2;
      public static int bbb00620062bbb00620062 = 6;
      
      public static int b0069i0069iiiiii0069()
      {
        return 34;
      }
      
      /* Error */
      public void onClick(android.content.DialogInterface paramAnonymousDialogInterface, int paramAnonymousInt)
      {
        // Byte code:
        //   0: getstatic 37	com/db/pwcc/dbmobile/transfer/inputscreen/activities/InputSubaccountActivity$1:bbb00620062bbb00620062	I
        //   3: getstatic 39	com/db/pwcc/dbmobile/transfer/inputscreen/activities/InputSubaccountActivity$1:b0062b00620062bbb00620062	I
        //   6: iadd
        //   7: getstatic 37	com/db/pwcc/dbmobile/transfer/inputscreen/activities/InputSubaccountActivity$1:bbb00620062bbb00620062	I
        //   10: imul
        //   11: getstatic 41	com/db/pwcc/dbmobile/transfer/inputscreen/activities/InputSubaccountActivity$1:bb006200620062bbb00620062	I
        //   14: irem
        //   15: getstatic 43	com/db/pwcc/dbmobile/transfer/inputscreen/activities/InputSubaccountActivity$1:b0062006200620062bbb00620062	I
        //   18: if_icmpeq +14 -> 32
        //   21: invokestatic 45	com/db/pwcc/dbmobile/transfer/inputscreen/activities/InputSubaccountActivity$1:b0069i0069iiiiii0069	()I
        //   24: putstatic 37	com/db/pwcc/dbmobile/transfer/inputscreen/activities/InputSubaccountActivity$1:bbb00620062bbb00620062	I
        //   27: bipush 92
        //   29: putstatic 43	com/db/pwcc/dbmobile/transfer/inputscreen/activities/InputSubaccountActivity$1:b0062006200620062bbb00620062	I
        //   32: getstatic 37	com/db/pwcc/dbmobile/transfer/inputscreen/activities/InputSubaccountActivity$1:bbb00620062bbb00620062	I
        //   35: istore_3
        //   36: iload_3
        //   37: iload_3
        //   38: getstatic 39	com/db/pwcc/dbmobile/transfer/inputscreen/activities/InputSubaccountActivity$1:b0062b00620062bbb00620062	I
        //   41: iadd
        //   42: imul
        //   43: getstatic 41	com/db/pwcc/dbmobile/transfer/inputscreen/activities/InputSubaccountActivity$1:bb006200620062bbb00620062	I
        //   46: irem
        //   47: tableswitch	default:+17->64, 0:+28->75
        //   64: bipush 99
        //   66: putstatic 37	com/db/pwcc/dbmobile/transfer/inputscreen/activities/InputSubaccountActivity$1:bbb00620062bbb00620062	I
        //   69: invokestatic 45	com/db/pwcc/dbmobile/transfer/inputscreen/activities/InputSubaccountActivity$1:b0069i0069iiiiii0069	()I
        //   72: putstatic 39	com/db/pwcc/dbmobile/transfer/inputscreen/activities/InputSubaccountActivity$1:b0062b00620062bbb00620062	I
        //   75: aload_0
        //   76: getfield 26	com/db/pwcc/dbmobile/transfer/inputscreen/activities/InputSubaccountActivity$1:b00620062b0062bbb00620062	Lcom/db/pwcc/dbmobile/transfer/inputscreen/activities/InputSubaccountActivity;
        //   79: invokevirtual 48	com/db/pwcc/dbmobile/transfer/inputscreen/activities/InputSubaccountActivity:hideProgressAndEnableInput	()V
        //   82: aconst_null
        //   83: invokevirtual 53	java/lang/String:length	()I
        //   86: pop
        //   87: goto -5 -> 82
        //   90: astore 4
        //   92: aconst_null
        //   93: invokevirtual 53	java/lang/String:length	()I
        //   96: pop
        //   97: goto -5 -> 92
        //   100: astore 5
        //   102: return
        // Local variable table:
        //   start	length	slot	name	signature
        //   0	103	0	this	1
        //   0	103	1	paramAnonymousDialogInterface	android.content.DialogInterface
        //   0	103	2	paramAnonymousInt	int
        //   35	8	3	i	int
        //   90	1	4	localException1	Exception
        //   100	1	5	localException2	Exception
        // Exception table:
        //   from	to	target	type
        //   82	87	90	java/lang/Exception
        //   92	97	100	java/lang/Exception
      }
    };
  }
  
  public int getLayout()
  {
    int i = bt0074tttt0074tt;
    switch (i * (i + b00740074tttt0074tt) % btt0074ttt0074tt())
    {
    default: 
      bt0074tttt0074tt = 34;
      b0074tt0074tt0074tt = 56;
    }
    int j = R.layout.activity_input_subaccount;
    int k = bt0074tttt0074tt + b00740074tttt0074tt;
    int m = bt0074tttt0074tt;
    if ((b0074t0074ttt0074tt() + bt00740074ttt0074tt()) * b0074t0074ttt0074tt() % b007400740074ttt0074tt != b0074tt0074tt0074tt)
    {
      bt0074tttt0074tt = 71;
      b0074tt0074tt0074tt = 65;
    }
    if (k * m % b007400740074ttt0074tt != b0074tt0074tt0074tt)
    {
      if ((bt0074tttt0074tt + b00740074tttt0074tt) * bt0074tttt0074tt % btt0074ttt0074tt() != b0074tt0074tt0074tt)
      {
        bt0074tttt0074tt = 18;
        b0074tt0074tt0074tt = 50;
      }
      bt0074tttt0074tt = 48;
      b0074tt0074tt0074tt = 94;
    }
    return j;
  }
  
  public String getSelectedAccountId()
  {
    Account localAccount = this.accountAdapter.b0069ii0069ii0069006900690069(this.accountSelector.getSelectedItemPositionOrDefault());
    if ((bt0074tttt0074tt + bt00740074ttt0074tt()) * bt0074tttt0074tt % b007400740074ttt0074tt != b0074tt0074tt0074tt)
    {
      bt0074tttt0074tt = 35;
      b0074tt0074tt0074tt = 49;
    }
    String str = localAccount.getId();
    if ((bt0074tttt0074tt + b00740074tttt0074tt) * bt0074tttt0074tt % btt0074ttt0074tt() != bttt0074tt0074tt())
    {
      int i = bt0074tttt0074tt;
      switch (i * (i + b00740074tttt0074tt) % b007400740074ttt0074tt)
      {
      default: 
        bt0074tttt0074tt = 94;
        b0074tt0074tt0074tt = b0074t0074ttt0074tt();
      }
      bt0074tttt0074tt = b0074t0074ttt0074tt();
      b0074tt0074tt0074tt = 79;
      if ((b0074t0074ttt0074tt() + b00740074tttt0074tt) * b0074t0074ttt0074tt() % btt0074ttt0074tt() != b0074tt0074tt0074tt)
      {
        bt0074tttt0074tt = 72;
        b0074tt0074tt0074tt = 18;
      }
    }
    return str;
  }
  
  public String getSelectedSubaccountId()
  {
    lvvvvv localLvvvvv = this.subaccountAdapter;
    int i = bt0074tttt0074tt + b00740074tttt0074tt;
    int j = bt0074tttt0074tt;
    int k = bt0074tttt0074tt;
    int m = bt00740074ttt0074tt();
    int n = bt0074tttt0074tt;
    int i1 = n * (n + b00740074tttt0074tt);
    int i2 = bt0074tttt0074tt;
    switch (i2 * (i2 + b00740074tttt0074tt) % b007400740074ttt0074tt)
    {
    default: 
      bt0074tttt0074tt = b0074t0074ttt0074tt();
      b0074tt0074tt0074tt = 25;
    }
    switch (i1 % btt0074ttt0074tt())
    {
    default: 
      bt0074tttt0074tt = b0074t0074ttt0074tt();
      b0074tt0074tt0074tt = b0074t0074ttt0074tt();
    }
    switch (k * (m + k) % b007400740074ttt0074tt)
    {
    default: 
      bt0074tttt0074tt = b0074t0074ttt0074tt();
      b0074tt0074tt0074tt = 36;
    }
    if (i * j % b007400740074ttt0074tt != b0074tt0074tt0074tt)
    {
      bt0074tttt0074tt = b0074t0074ttt0074tt();
      b0074tt0074tt0074tt = 24;
    }
    return localLvvvvv.b0069ii0069ii0069006900690069(this.subaccountSelector.getSelectedItemPositionOrDefault()).getId();
  }
  
  /* Error */
  public String getSourceAccountIban()
  {
    // Byte code:
    //   0: aconst_null
    //   1: invokevirtual 71	java/lang/String:length	()I
    //   4: pop
    //   5: getstatic 73	com/db/pwcc/dbmobile/transfer/inputscreen/activities/InputSubaccountActivity:bt0074tttt0074tt	I
    //   8: getstatic 75	com/db/pwcc/dbmobile/transfer/inputscreen/activities/InputSubaccountActivity:b00740074tttt0074tt	I
    //   11: iadd
    //   12: getstatic 73	com/db/pwcc/dbmobile/transfer/inputscreen/activities/InputSubaccountActivity:bt0074tttt0074tt	I
    //   15: imul
    //   16: getstatic 132	com/db/pwcc/dbmobile/transfer/inputscreen/activities/InputSubaccountActivity:b007400740074ttt0074tt	I
    //   19: irem
    //   20: getstatic 191	com/db/pwcc/dbmobile/transfer/inputscreen/activities/InputSubaccountActivity:b0074tt0074tt0074tt	I
    //   23: if_icmpeq -23 -> 0
    //   26: bipush 35
    //   28: putstatic 73	com/db/pwcc/dbmobile/transfer/inputscreen/activities/InputSubaccountActivity:bt0074tttt0074tt	I
    //   31: bipush 95
    //   33: putstatic 191	com/db/pwcc/dbmobile/transfer/inputscreen/activities/InputSubaccountActivity:b0074tt0074tt0074tt	I
    //   36: goto -36 -> 0
    //   39: astore 4
    //   41: invokestatic 81	com/db/pwcc/dbmobile/transfer/inputscreen/activities/InputSubaccountActivity:b0074t0074ttt0074tt	()I
    //   44: putstatic 73	com/db/pwcc/dbmobile/transfer/inputscreen/activities/InputSubaccountActivity:bt0074tttt0074tt	I
    //   47: aload_0
    //   48: getfield 173	com/db/pwcc/dbmobile/transfer/inputscreen/activities/InputSubaccountActivity:accountAdapter	Luuuuuu/lvvvvv;
    //   51: aload_0
    //   52: getfield 169	com/db/pwcc/dbmobile/transfer/inputscreen/activities/InputSubaccountActivity:accountSelector	Lcom/db/pwcc/dbmobile/foundation/widgets/dbPicker/DbPicker;
    //   55: invokevirtual 516	com/db/pwcc/dbmobile/foundation/widgets/dbPicker/DbPicker:getSelectedItemPositionOrDefault	()I
    //   58: invokevirtual 225	uuuuuu/lvvvvv:b0069ii0069ii0069006900690069	(I)Lcom/db/pwcc/dbmobile/model/banking/Account;
    //   61: astore 5
    //   63: getstatic 73	com/db/pwcc/dbmobile/transfer/inputscreen/activities/InputSubaccountActivity:bt0074tttt0074tt	I
    //   66: istore 6
    //   68: iload 6
    //   70: iload 6
    //   72: getstatic 75	com/db/pwcc/dbmobile/transfer/inputscreen/activities/InputSubaccountActivity:b00740074tttt0074tt	I
    //   75: iadd
    //   76: imul
    //   77: getstatic 132	com/db/pwcc/dbmobile/transfer/inputscreen/activities/InputSubaccountActivity:b007400740074ttt0074tt	I
    //   80: irem
    //   81: tableswitch	default:+19->100, 0:+29->110
    //   100: bipush 71
    //   102: putstatic 73	com/db/pwcc/dbmobile/transfer/inputscreen/activities/InputSubaccountActivity:bt0074tttt0074tt	I
    //   105: bipush 68
    //   107: putstatic 191	com/db/pwcc/dbmobile/transfer/inputscreen/activities/InputSubaccountActivity:b0074tt0074tt0074tt	I
    //   110: aload 5
    //   112: invokevirtual 524	com/db/pwcc/dbmobile/model/banking/Account:getIban	()Ljava/lang/String;
    //   115: areturn
    //   116: astore_1
    //   117: invokestatic 81	com/db/pwcc/dbmobile/transfer/inputscreen/activities/InputSubaccountActivity:b0074t0074ttt0074tt	()I
    //   120: putstatic 73	com/db/pwcc/dbmobile/transfer/inputscreen/activities/InputSubaccountActivity:bt0074tttt0074tt	I
    //   123: iconst_m1
    //   124: newarray int
    //   126: pop
    //   127: getstatic 73	com/db/pwcc/dbmobile/transfer/inputscreen/activities/InputSubaccountActivity:bt0074tttt0074tt	I
    //   130: istore_3
    //   131: iload_3
    //   132: iload_3
    //   133: getstatic 75	com/db/pwcc/dbmobile/transfer/inputscreen/activities/InputSubaccountActivity:b00740074tttt0074tt	I
    //   136: iadd
    //   137: imul
    //   138: getstatic 132	com/db/pwcc/dbmobile/transfer/inputscreen/activities/InputSubaccountActivity:b007400740074ttt0074tt	I
    //   141: irem
    //   142: tableswitch	default:+18->160, 0:+-19->123
    //   160: invokestatic 81	com/db/pwcc/dbmobile/transfer/inputscreen/activities/InputSubaccountActivity:b0074t0074ttt0074tt	()I
    //   163: putstatic 73	com/db/pwcc/dbmobile/transfer/inputscreen/activities/InputSubaccountActivity:bt0074tttt0074tt	I
    //   166: iconst_3
    //   167: putstatic 191	com/db/pwcc/dbmobile/transfer/inputscreen/activities/InputSubaccountActivity:b0074tt0074tt0074tt	I
    //   170: goto -47 -> 123
    // Local variable table:
    //   start	length	slot	name	signature
    //   0	173	0	this	InputSubaccountActivity
    //   116	1	1	localException1	Exception
    //   130	8	3	i	int
    //   39	1	4	localException2	Exception
    //   61	50	5	localAccount	Account
    //   66	11	6	j	int
    // Exception table:
    //   from	to	target	type
    //   123	127	39	java/lang/Exception
    //   0	5	116	java/lang/Exception
  }
  
  public String getSourceAccountId()
  {
    lvvvvv localLvvvvv = this.accountAdapter;
    if ((bt0074tttt0074tt + b00740074tttt0074tt) * bt0074tttt0074tt % btt0074ttt0074tt() != b0074tt0074tt0074tt)
    {
      if ((bt0074tttt0074tt + b00740074tttt0074tt) * bt0074tttt0074tt % btt0074ttt0074tt() != b0074tt0074tt0074tt)
      {
        bt0074tttt0074tt = b0074t0074ttt0074tt();
        b0074tt0074tt0074tt = b0074t0074ttt0074tt();
      }
      int i = bt0074tttt0074tt;
      switch (i * (i + b00740074tttt0074tt) % btt0074ttt0074tt())
      {
      default: 
        bt0074tttt0074tt = b0074t0074ttt0074tt();
        b0074tt0074tt0074tt = b0074t0074ttt0074tt();
      }
      bt0074tttt0074tt = 86;
      b0074tt0074tt0074tt = b0074t0074ttt0074tt();
    }
    if ((bt0074tttt0074tt + b00740074tttt0074tt) * bt0074tttt0074tt % b007400740074ttt0074tt != b0074tt0074tt0074tt)
    {
      bt0074tttt0074tt = b0074t0074ttt0074tt();
      b0074tt0074tt0074tt = b0074t0074ttt0074tt();
    }
    return localLvvvvv.b0069ii0069ii0069006900690069(this.accountSelector.getSelectedItemPositionOrDefault()).getId();
  }
  
  public String getTargetAccountIban()
  {
    Account localAccount = this.subaccountAdapter.b0069ii0069ii0069006900690069(this.subaccountSelector.getSelectedItemPositionOrDefault());
    if ((bt0074tttt0074tt + b00740074tttt0074tt) * bt0074tttt0074tt % b007400740074ttt0074tt != b0074tt0074tt0074tt)
    {
      int i = bt0074tttt0074tt;
      switch (i * (i + b00740074tttt0074tt) % b007400740074ttt0074tt)
      {
      default: 
        int j = bt0074tttt0074tt;
        switch (j * (j + bt00740074ttt0074tt()) % b007400740074ttt0074tt)
        {
        default: 
          bt0074tttt0074tt = 7;
          b0074tt0074tt0074tt = 84;
        }
        bt0074tttt0074tt = b0074t0074ttt0074tt();
        b0074tt0074tt0074tt = 19;
      }
      bt0074tttt0074tt = 61;
      b0074tt0074tt0074tt = 95;
      if ((bt0074tttt0074tt + b00740074tttt0074tt) * bt0074tttt0074tt % b007400740074ttt0074tt != b0074tt0074tt0074tt)
      {
        bt0074tttt0074tt = b0074t0074ttt0074tt();
        b0074tt0074tt0074tt = 78;
      }
    }
    return localAccount.getIban();
  }
  
  public void hideProgressAndEnableInput()
  {
    nonnnn.bkkkk006Bk006B006Bk006B(getWindow());
    int i = bt0074tttt0074tt;
    if ((bt0074tttt0074tt + b00740074tttt0074tt) * bt0074tttt0074tt % btt0074ttt0074tt() != b0074tt0074tt0074tt)
    {
      bt0074tttt0074tt = b0074t0074ttt0074tt();
      b0074tt0074tt0074tt = b0074t0074ttt0074tt();
    }
    if ((bt0074tttt0074tt + bt00740074ttt0074tt()) * bt0074tttt0074tt % b007400740074ttt0074tt != b0074tt0074tt0074tt)
    {
      bt0074tttt0074tt = b0074t0074ttt0074tt();
      b0074tt0074tt0074tt = 85;
    }
    if ((i + b00740074tttt0074tt) * bt0074tttt0074tt % b007400740074ttt0074tt != bttt0074tt0074tt())
    {
      bt0074tttt0074tt = b0074t0074ttt0074tt();
      b0074tt0074tt0074tt = 56;
    }
    updateButtonBackground();
    if ((bt0074tttt0074tt + b00740074tttt0074tt) * bt0074tttt0074tt % b007400740074ttt0074tt != b0074tt0074tt0074tt)
    {
      bt0074tttt0074tt = b0074t0074ttt0074tt();
      b0074tt0074tt0074tt = 24;
    }
  }
  
  public boolean isTheInputValid()
  {
    boolean bool;
    if ((getAmount().compareTo(BigDecimal.ZERO) > 0) && (this.accountSelector.getSelectedItemPosition() >= 0) && (this.subaccountSelector.getSelectedItemPosition() >= 0)) {
      bool = true;
    }
    int k;
    int m;
    do
    {
      return bool;
      int i = bt0074tttt0074tt;
      int j = bt0074tttt0074tt;
      switch (j * (j + b00740074tttt0074tt) % btt0074ttt0074tt())
      {
      default: 
        bt0074tttt0074tt = 36;
        b0074tt0074tt0074tt = 37;
      }
      switch (i * (i + b00740074tttt0074tt) % b007400740074ttt0074tt)
      {
      default: 
        bt0074tttt0074tt = b0074t0074ttt0074tt();
        b0074tt0074tt0074tt = b0074t0074ttt0074tt();
      }
      k = (bt0074tttt0074tt + b00740074tttt0074tt) * bt0074tttt0074tt % b007400740074ttt0074tt;
      m = b0074tt0074tt0074tt;
      bool = false;
    } while (k == m);
    int n = bt0074tttt0074tt;
    switch (n * (n + b00740074tttt0074tt) % btt0074ttt0074tt())
    {
    default: 
      bt0074tttt0074tt = b0074t0074ttt0074tt();
      b0074tt0074tt0074tt = b0074t0074ttt0074tt();
    }
    bt0074tttt0074tt = 43;
    b0074tt0074tt0074tt = b0074t0074ttt0074tt();
    return false;
  }
  
  public void navigateToConfirmationPage(String paramString1, Authorization paramAuthorization, AuthorizationStatus paramAuthorizationStatus, String paramString2)
  {
    int i = (bt0074tttt0074tt + b00740074tttt0074tt) * bt0074tttt0074tt % b007400740074ttt0074tt;
    if ((b0074t0074ttt0074tt() + b00740074tttt0074tt) * b0074t0074ttt0074tt() % b007400740074ttt0074tt != b0074tt0074tt0074tt)
    {
      bt0074tttt0074tt = 96;
      b0074tt0074tt0074tt = b0074t0074ttt0074tt();
    }
    if (i != bttt0074tt0074tt())
    {
      bt0074tttt0074tt = 4;
      b0074tt0074tt0074tt = b0074t0074ttt0074tt();
    }
    Intent localIntent1 = getIntent();
    int j = bt0074tttt0074tt;
    switch (j * (j + b00740074tttt0074tt) % b007400740074ttt0074tt)
    {
    default: 
      bt0074tttt0074tt = b0074t0074ttt0074tt();
      b0074tt0074tt0074tt = b0074t0074ttt0074tt();
    }
    String str = uxxxxx.bb00620062bb0062b0062b0062("\b\034\033\032\031POUTLKQP\020GFLKCBHG\007", '', '\004');
    Class[] arrayOfClass = new Class[3];
    arrayOfClass[0] = String.class;
    arrayOfClass[1] = Character.TYPE;
    arrayOfClass[2] = Character.TYPE;
    Method localMethod = ppphhp.class.getMethod(str, arrayOfClass);
    Object[] arrayOfObject = new Object[3];
    arrayOfObject[0] = "!521!n\020\004\032\016\r\b\034\016)\037\033,\021\033\021$%!\025\"\033";
    arrayOfObject[1] = Character.valueOf('');
    arrayOfObject[2] = Character.valueOf('\001');
    try
    {
      Object localObject = localMethod.invoke(null, arrayOfObject);
      Intent localIntent2 = SepaConfirmationActivity.makeIntent(this, paramString1, true, paramAuthorization, paramAuthorizationStatus, paramString2, true, localIntent1.getStringExtra((String)localObject));
      int k = bt0074tttt0074tt;
      switch (k * (k + b00740074tttt0074tt) % b007400740074ttt0074tt)
      {
      default: 
        bt0074tttt0074tt = b0074t0074ttt0074tt();
        b0074tt0074tt0074tt = b0074t0074ttt0074tt();
      }
      startActivityForResult(localIntent2, 99);
      nononn.bk006B006Bk006B006Bk006Bk006B(this.buttonDone);
      return;
    }
    catch (InvocationTargetException localInvocationTargetException)
    {
      throw localInvocationTargetException.getCause();
    }
  }
  
  public void onActivityResult(int paramInt1, int paramInt2, Intent paramIntent)
  {
    super.onActivityResult(paramInt1, paramInt2, paramIntent);
    if (paramInt1 == 99)
    {
      int i = (bt0074tttt0074tt + b00740074tttt0074tt) * bt0074tttt0074tt % b007400740074ttt0074tt;
      int j = bt0074tttt0074tt;
      switch (j * (j + bt00740074ttt0074tt()) % b007400740074ttt0074tt)
      {
      default: 
        bt0074tttt0074tt = 86;
        b0074tt0074tt0074tt = b0074t0074ttt0074tt();
      }
      if (i != b0074tt0074tt0074tt)
      {
        bt0074tttt0074tt = 18;
        b0074tt0074tt0074tt = b0074t0074ttt0074tt();
      }
      if (paramInt2 == -1)
      {
        finish();
        int k = bt0074tttt0074tt;
        switch (k * (k + b00740074tttt0074tt) % b007400740074ttt0074tt)
        {
        default: 
          bt0074tttt0074tt = b0074t0074ttt0074tt();
          b0074tt0074tt0074tt = 10;
        }
      }
    }
  }
  
  public void onBackPressed()
  {
    yyyggy localYyyggy = this.backendFacade.b0070007000700070pp00700070pp(gyyygy.yyyygy.bkkk006Bk006Bk006Bk);
    Object[] arrayOfObject = new Object[2];
    lolllo localLolllo = lolllo.b00710071qqq0071qq0071;
    int i = bt0074tttt0074tt;
    int j = b00740074tttt0074tt;
    if ((bt0074tttt0074tt + b00740074tttt0074tt) * bt0074tttt0074tt % b007400740074ttt0074tt != b0074tt0074tt0074tt)
    {
      bt0074tttt0074tt = b0074t0074ttt0074tt();
      b0074tt0074tt0074tt = 15;
    }
    if ((i + j) * bt0074tttt0074tt % b007400740074ttt0074tt != b0074tt0074tt0074tt)
    {
      bt0074tttt0074tt = b0074t0074ttt0074tt();
      b0074tt0074tt0074tt = b0074t0074ttt0074tt();
    }
    arrayOfObject[0] = localLolllo.name();
    if ((bt0074tttt0074tt + b00740074tttt0074tt) * bt0074tttt0074tt % btt0074ttt0074tt() != b0074tt0074tt0074tt)
    {
      bt0074tttt0074tt = b0074t0074ttt0074tt();
      b0074tt0074tt0074tt = b0074t0074ttt0074tt();
      int k = bt0074tttt0074tt;
      switch (k * (k + b00740074tttt0074tt) % b007400740074ttt0074tt)
      {
      default: 
        bt0074tttt0074tt = 42;
        b0074tt0074tt0074tt = 79;
      }
    }
    arrayOfObject[1] = lolllo.bq0071007100710071qqq0071.name();
    localYyyggy.b00700070007000700070p00700070pp(arrayOfObject);
    super.onBackPressed();
  }
  
  /* Error */
  public void onCreate(android.os.Bundle paramBundle)
  {
    // Byte code:
    //   0: iconst_5
    //   1: istore_2
    //   2: aload_0
    //   3: invokevirtual 620	com/db/pwcc/dbmobile/transfer/inputscreen/activities/InputSubaccountActivity:getApplicationContext	()Landroid/content/Context;
    //   6: astore_3
    //   7: ldc_w 622
    //   10: ldc_w 624
    //   13: bipush 119
    //   15: sipush 200
    //   18: iconst_2
    //   19: invokestatic 91	xxxxxx/uxxxxx:bbbb0062b0062b0062b0062	(Ljava/lang/String;CCC)Ljava/lang/String;
    //   22: iconst_1
    //   23: anewarray 93	java/lang/Class
    //   26: dup
    //   27: iconst_0
    //   28: ldc_w 626
    //   31: aastore
    //   32: invokevirtual 105	java/lang/Class:getMethod	(Ljava/lang/String;[Ljava/lang/Class;)Ljava/lang/reflect/Method;
    //   35: astore 4
    //   37: iconst_1
    //   38: anewarray 107	java/lang/Object
    //   41: dup
    //   42: iconst_0
    //   43: aload_3
    //   44: aastore
    //   45: astore 5
    //   47: aload 4
    //   49: aconst_null
    //   50: aload 5
    //   52: invokevirtual 117	java/lang/reflect/Method:invoke	(Ljava/lang/Object;[Ljava/lang/Object;)Ljava/lang/Object;
    //   55: pop
    //   56: getstatic 73	com/db/pwcc/dbmobile/transfer/inputscreen/activities/InputSubaccountActivity:bt0074tttt0074tt	I
    //   59: getstatic 75	com/db/pwcc/dbmobile/transfer/inputscreen/activities/InputSubaccountActivity:b00740074tttt0074tt	I
    //   62: iadd
    //   63: getstatic 73	com/db/pwcc/dbmobile/transfer/inputscreen/activities/InputSubaccountActivity:bt0074tttt0074tt	I
    //   66: imul
    //   67: getstatic 132	com/db/pwcc/dbmobile/transfer/inputscreen/activities/InputSubaccountActivity:b007400740074ttt0074tt	I
    //   70: irem
    //   71: getstatic 191	com/db/pwcc/dbmobile/transfer/inputscreen/activities/InputSubaccountActivity:b0074tt0074tt0074tt	I
    //   74: if_icmpeq +13 -> 87
    //   77: bipush 91
    //   79: putstatic 73	com/db/pwcc/dbmobile/transfer/inputscreen/activities/InputSubaccountActivity:bt0074tttt0074tt	I
    //   82: bipush 37
    //   84: putstatic 191	com/db/pwcc/dbmobile/transfer/inputscreen/activities/InputSubaccountActivity:b0074tt0074tt0074tt	I
    //   87: aload_0
    //   88: invokevirtual 620	com/db/pwcc/dbmobile/transfer/inputscreen/activities/InputSubaccountActivity:getApplicationContext	()Landroid/content/Context;
    //   91: astore 8
    //   93: ldc_w 628
    //   96: ldc_w 630
    //   99: sipush 170
    //   102: iconst_0
    //   103: invokestatic 138	xxxxxx/uxxxxx:bb00620062bb0062b0062b0062	(Ljava/lang/String;CC)Ljava/lang/String;
    //   106: iconst_1
    //   107: anewarray 93	java/lang/Class
    //   110: dup
    //   111: iconst_0
    //   112: ldc_w 626
    //   115: aastore
    //   116: invokevirtual 105	java/lang/Class:getMethod	(Ljava/lang/String;[Ljava/lang/Class;)Ljava/lang/reflect/Method;
    //   119: astore 9
    //   121: iconst_1
    //   122: anewarray 107	java/lang/Object
    //   125: dup
    //   126: iconst_0
    //   127: aload 8
    //   129: aastore
    //   130: astore 10
    //   132: aload 9
    //   134: aconst_null
    //   135: aload 10
    //   137: invokevirtual 117	java/lang/reflect/Method:invoke	(Ljava/lang/Object;[Ljava/lang/Object;)Ljava/lang/Object;
    //   140: pop
    //   141: aload_0
    //   142: invokevirtual 620	com/db/pwcc/dbmobile/transfer/inputscreen/activities/InputSubaccountActivity:getApplicationContext	()Landroid/content/Context;
    //   145: invokestatic 636	uuuuuu/uppupu:b0072r0072r00720072rr0072	(Landroid/content/Context;)V
    //   148: aload_0
    //   149: aload_1
    //   150: invokespecial 638	com/db/pwcc/dbmobile/foundation/activities/common/PopupActivity:onCreate	(Landroid/os/Bundle;)V
    //   153: getstatic 73	com/db/pwcc/dbmobile/transfer/inputscreen/activities/InputSubaccountActivity:bt0074tttt0074tt	I
    //   156: getstatic 75	com/db/pwcc/dbmobile/transfer/inputscreen/activities/InputSubaccountActivity:b00740074tttt0074tt	I
    //   159: iadd
    //   160: getstatic 73	com/db/pwcc/dbmobile/transfer/inputscreen/activities/InputSubaccountActivity:bt0074tttt0074tt	I
    //   163: imul
    //   164: getstatic 132	com/db/pwcc/dbmobile/transfer/inputscreen/activities/InputSubaccountActivity:b007400740074ttt0074tt	I
    //   167: irem
    //   168: getstatic 191	com/db/pwcc/dbmobile/transfer/inputscreen/activities/InputSubaccountActivity:b0074tt0074tt0074tt	I
    //   171: if_icmpeq +13 -> 184
    //   174: bipush 60
    //   176: putstatic 73	com/db/pwcc/dbmobile/transfer/inputscreen/activities/InputSubaccountActivity:bt0074tttt0074tt	I
    //   179: bipush 90
    //   181: putstatic 191	com/db/pwcc/dbmobile/transfer/inputscreen/activities/InputSubaccountActivity:b0074tt0074tt0074tt	I
    //   184: aload_0
    //   185: invokespecial 640	com/db/pwcc/dbmobile/transfer/inputscreen/activities/InputSubaccountActivity:initDbToolbar	()V
    //   188: aload_0
    //   189: invokespecial 642	com/db/pwcc/dbmobile/transfer/inputscreen/activities/InputSubaccountActivity:initView	()V
    //   192: iload_2
    //   193: iconst_0
    //   194: idiv
    //   195: istore_2
    //   196: goto -4 -> 192
    //   199: astore 13
    //   201: invokestatic 81	com/db/pwcc/dbmobile/transfer/inputscreen/activities/InputSubaccountActivity:b0074t0074ttt0074tt	()I
    //   204: putstatic 73	com/db/pwcc/dbmobile/transfer/inputscreen/activities/InputSubaccountActivity:bt0074tttt0074tt	I
    //   207: iconst_2
    //   208: istore 14
    //   210: iload 14
    //   212: iconst_0
    //   213: idiv
    //   214: istore 14
    //   216: goto -6 -> 210
    //   219: astore 11
    //   221: aload 11
    //   223: invokevirtual 152	java/lang/reflect/InvocationTargetException:getCause	()Ljava/lang/Throwable;
    //   226: athrow
    //   227: astore 15
    //   229: invokestatic 81	com/db/pwcc/dbmobile/transfer/inputscreen/activities/InputSubaccountActivity:b0074t0074ttt0074tt	()I
    //   232: putstatic 73	com/db/pwcc/dbmobile/transfer/inputscreen/activities/InputSubaccountActivity:bt0074tttt0074tt	I
    //   235: aload_0
    //   236: getstatic 299	com/db/pwcc/dbmobile/transfer/R$id:input_subaccount_container_principal	I
    //   239: invokevirtual 273	com/db/pwcc/dbmobile/transfer/inputscreen/activities/InputSubaccountActivity:findViewById	(I)Landroid/view/View;
    //   242: invokestatic 645	uuuuuu/nononn:b006B006B006Bk006B006Bk006Bk006B	(Landroid/view/View;)V
    //   245: return
    //   246: astore 6
    //   248: aload 6
    //   250: invokevirtual 152	java/lang/reflect/InvocationTargetException:getCause	()Ljava/lang/Throwable;
    //   253: athrow
    // Local variable table:
    //   start	length	slot	name	signature
    //   0	254	0	this	InputSubaccountActivity
    //   0	254	1	paramBundle	android.os.Bundle
    //   1	195	2	i	int
    //   6	38	3	localContext1	Context
    //   35	13	4	localMethod1	Method
    //   45	6	5	arrayOfObject1	Object[]
    //   246	3	6	localInvocationTargetException1	InvocationTargetException
    //   91	37	8	localContext2	Context
    //   119	14	9	localMethod2	Method
    //   130	6	10	arrayOfObject2	Object[]
    //   219	3	11	localInvocationTargetException2	InvocationTargetException
    //   199	1	13	localException1	Exception
    //   208	7	14	j	int
    //   227	1	15	localException2	Exception
    // Exception table:
    //   from	to	target	type
    //   192	196	199	java/lang/Exception
    //   132	141	219	java/lang/reflect/InvocationTargetException
    //   210	216	227	java/lang/Exception
    //   47	56	246	java/lang/reflect/InvocationTargetException
  }
  
  public void onDestroy()
  {
    int i = bt0074tttt0074tt;
    switch (i * (i + b00740074tttt0074tt) % b007400740074ttt0074tt)
    {
    default: 
      bt0074tttt0074tt = b0074t0074ttt0074tt();
      b0074tt0074tt0074tt = 78;
    }
    tnnntn localTnnntn;
    Method localMethod;
    Object[] arrayOfObject;
    if (this.presenter != null)
    {
      localTnnntn = this.presenter;
      localMethod = tnnntn.class.getMethod(uxxxxx.bb00620062bb0062b0062b0062("\013\tVUZTRQVPNMRL{IHMGvuCBGAp", '', '\005'), new Class[0]);
      arrayOfObject = new Object[0];
    }
    try
    {
      localMethod.invoke(localTnnntn, arrayOfObject);
      int j = (bt0074tttt0074tt + bt00740074ttt0074tt()) * bt0074tttt0074tt;
      int k = bt0074tttt0074tt;
      switch (k * (k + b00740074tttt0074tt) % b007400740074ttt0074tt)
      {
      default: 
        bt0074tttt0074tt = 53;
        b0074tt0074tt0074tt = b0074t0074ttt0074tt();
      }
      if (j % b007400740074ttt0074tt != b0074tt0074tt0074tt)
      {
        bt0074tttt0074tt = 49;
        b0074tt0074tt0074tt = 85;
        if ((b0074t0074ttt0074tt() + b00740074tttt0074tt) * b0074t0074ttt0074tt() % b007400740074ttt0074tt != b0074tt0074tt0074tt)
        {
          bt0074tttt0074tt = b0074t0074ttt0074tt();
          b0074tt0074tt0074tt = 62;
        }
      }
      super.onDestroy();
      return;
    }
    catch (InvocationTargetException localInvocationTargetException)
    {
      throw localInvocationTargetException.getCause();
    }
  }
  
  public void onPause()
  {
    int i = bt0074tttt0074tt;
    switch (i * (i + b00740074tttt0074tt) % b007400740074ttt0074tt)
    {
    default: 
      int j = bt0074tttt0074tt;
      switch (j * (j + b00740074tttt0074tt) % btt0074ttt0074tt())
      {
      default: 
        bt0074tttt0074tt = b0074t0074ttt0074tt();
        b0074tt0074tt0074tt = 59;
      }
      if ((bt0074tttt0074tt + b00740074tttt0074tt) * bt0074tttt0074tt % b007400740074ttt0074tt != b0074tt0074tt0074tt)
      {
        bt0074tttt0074tt = 59;
        b0074tt0074tt0074tt = b0074t0074ttt0074tt();
        if ((bt0074tttt0074tt + b00740074tttt0074tt) * bt0074tttt0074tt % b007400740074ttt0074tt != b0074tt0074tt0074tt)
        {
          bt0074tttt0074tt = b0074t0074ttt0074tt();
          b0074tt0074tt0074tt = b0074t0074ttt0074tt();
        }
      }
      bt0074tttt0074tt = b0074t0074ttt0074tt();
      b0074tt0074tt0074tt = 99;
    }
    super.onPause();
  }
  
  /* Error */
  public void onPickerExpanded(DbPicker paramDbPicker)
  {
    // Byte code:
    //   0: iconst_4
    //   1: istore_2
    //   2: iconst_m1
    //   3: newarray int
    //   5: pop
    //   6: goto -4 -> 2
    //   9: astore_3
    //   10: invokestatic 81	com/db/pwcc/dbmobile/transfer/inputscreen/activities/InputSubaccountActivity:b0074t0074ttt0074tt	()I
    //   13: putstatic 73	com/db/pwcc/dbmobile/transfer/inputscreen/activities/InputSubaccountActivity:bt0074tttt0074tt	I
    //   16: iload_2
    //   17: iconst_0
    //   18: idiv
    //   19: istore_2
    //   20: goto -4 -> 16
    //   23: astore 4
    //   25: getstatic 73	com/db/pwcc/dbmobile/transfer/inputscreen/activities/InputSubaccountActivity:bt0074tttt0074tt	I
    //   28: istore 5
    //   30: iload 5
    //   32: iload 5
    //   34: getstatic 75	com/db/pwcc/dbmobile/transfer/inputscreen/activities/InputSubaccountActivity:b00740074tttt0074tt	I
    //   37: iadd
    //   38: imul
    //   39: getstatic 132	com/db/pwcc/dbmobile/transfer/inputscreen/activities/InputSubaccountActivity:b007400740074ttt0074tt	I
    //   42: irem
    //   43: tableswitch	default:+17->60, 0:+27->70
    //   60: bipush 70
    //   62: putstatic 73	com/db/pwcc/dbmobile/transfer/inputscreen/activities/InputSubaccountActivity:bt0074tttt0074tt	I
    //   65: bipush 38
    //   67: putstatic 191	com/db/pwcc/dbmobile/transfer/inputscreen/activities/InputSubaccountActivity:b0074tt0074tt0074tt	I
    //   70: iconst_2
    //   71: putstatic 73	com/db/pwcc/dbmobile/transfer/inputscreen/activities/InputSubaccountActivity:bt0074tttt0074tt	I
    //   74: getstatic 73	com/db/pwcc/dbmobile/transfer/inputscreen/activities/InputSubaccountActivity:bt0074tttt0074tt	I
    //   77: getstatic 75	com/db/pwcc/dbmobile/transfer/inputscreen/activities/InputSubaccountActivity:b00740074tttt0074tt	I
    //   80: iadd
    //   81: getstatic 73	com/db/pwcc/dbmobile/transfer/inputscreen/activities/InputSubaccountActivity:bt0074tttt0074tt	I
    //   84: imul
    //   85: getstatic 132	com/db/pwcc/dbmobile/transfer/inputscreen/activities/InputSubaccountActivity:b007400740074ttt0074tt	I
    //   88: irem
    //   89: getstatic 191	com/db/pwcc/dbmobile/transfer/inputscreen/activities/InputSubaccountActivity:b0074tt0074tt0074tt	I
    //   92: if_icmpeq +51 -> 143
    //   95: invokestatic 81	com/db/pwcc/dbmobile/transfer/inputscreen/activities/InputSubaccountActivity:b0074t0074ttt0074tt	()I
    //   98: putstatic 73	com/db/pwcc/dbmobile/transfer/inputscreen/activities/InputSubaccountActivity:bt0074tttt0074tt	I
    //   101: invokestatic 81	com/db/pwcc/dbmobile/transfer/inputscreen/activities/InputSubaccountActivity:b0074t0074ttt0074tt	()I
    //   104: istore 6
    //   106: getstatic 73	com/db/pwcc/dbmobile/transfer/inputscreen/activities/InputSubaccountActivity:bt0074tttt0074tt	I
    //   109: getstatic 75	com/db/pwcc/dbmobile/transfer/inputscreen/activities/InputSubaccountActivity:b00740074tttt0074tt	I
    //   112: iadd
    //   113: getstatic 73	com/db/pwcc/dbmobile/transfer/inputscreen/activities/InputSubaccountActivity:bt0074tttt0074tt	I
    //   116: imul
    //   117: getstatic 132	com/db/pwcc/dbmobile/transfer/inputscreen/activities/InputSubaccountActivity:b007400740074ttt0074tt	I
    //   120: irem
    //   121: getstatic 191	com/db/pwcc/dbmobile/transfer/inputscreen/activities/InputSubaccountActivity:b0074tt0074tt0074tt	I
    //   124: if_icmpeq +14 -> 138
    //   127: invokestatic 81	com/db/pwcc/dbmobile/transfer/inputscreen/activities/InputSubaccountActivity:b0074t0074ttt0074tt	()I
    //   130: putstatic 73	com/db/pwcc/dbmobile/transfer/inputscreen/activities/InputSubaccountActivity:bt0074tttt0074tt	I
    //   133: bipush 47
    //   135: putstatic 191	com/db/pwcc/dbmobile/transfer/inputscreen/activities/InputSubaccountActivity:b0074tt0074tt0074tt	I
    //   138: iload 6
    //   140: putstatic 191	com/db/pwcc/dbmobile/transfer/inputscreen/activities/InputSubaccountActivity:b0074tt0074tt0074tt	I
    //   143: aload_1
    //   144: invokestatic 570	uuuuuu/nononn:bk006B006Bk006B006Bk006Bk006B	(Landroid/view/View;)V
    //   147: return
    // Local variable table:
    //   start	length	slot	name	signature
    //   0	148	0	this	InputSubaccountActivity
    //   0	148	1	paramDbPicker	DbPicker
    //   1	19	2	i	int
    //   9	1	3	localException1	Exception
    //   23	1	4	localException2	Exception
    //   28	11	5	j	int
    //   104	35	6	k	int
    // Exception table:
    //   from	to	target	type
    //   2	6	9	java/lang/Exception
    //   16	20	23	java/lang/Exception
  }
  
  /* Error */
  public void onRestoreInstanceState(android.os.Bundle paramBundle)
  {
    // Byte code:
    //   0: ldc_w 658
    //   3: sipush 207
    //   6: iconst_0
    //   7: invokestatic 138	xxxxxx/uxxxxx:bb00620062bb0062b0062b0062	(Ljava/lang/String;CC)Ljava/lang/String;
    //   10: astore_2
    //   11: iconst_3
    //   12: anewarray 93	java/lang/Class
    //   15: astore_3
    //   16: aload_3
    //   17: iconst_0
    //   18: ldc 67
    //   20: aastore
    //   21: aload_3
    //   22: iconst_1
    //   23: getstatic 99	java/lang/Character:TYPE	Ljava/lang/Class;
    //   26: aastore
    //   27: aload_3
    //   28: iconst_2
    //   29: getstatic 99	java/lang/Character:TYPE	Ljava/lang/Class;
    //   32: aastore
    //   33: ldc 101
    //   35: aload_2
    //   36: aload_3
    //   37: invokevirtual 105	java/lang/Class:getMethod	(Ljava/lang/String;[Ljava/lang/Class;)Ljava/lang/reflect/Method;
    //   40: astore 4
    //   42: iconst_3
    //   43: anewarray 107	java/lang/Object
    //   46: astore 5
    //   48: aload 5
    //   50: iconst_0
    //   51: ldc_w 660
    //   54: aastore
    //   55: aload 5
    //   57: iconst_1
    //   58: sipush 241
    //   61: invokestatic 111	java/lang/Character:valueOf	(C)Ljava/lang/Character;
    //   64: aastore
    //   65: aload 5
    //   67: iconst_2
    //   68: iconst_1
    //   69: invokestatic 111	java/lang/Character:valueOf	(C)Ljava/lang/Character;
    //   72: aastore
    //   73: aload 4
    //   75: aconst_null
    //   76: aload 5
    //   78: invokevirtual 117	java/lang/reflect/Method:invoke	(Ljava/lang/Object;[Ljava/lang/Object;)Ljava/lang/Object;
    //   81: astore 7
    //   83: aload_1
    //   84: aload 7
    //   86: checkcast 67	java/lang/String
    //   89: iconst_0
    //   90: invokevirtual 666	android/os/Bundle:getInt	(Ljava/lang/String;I)I
    //   93: istore 8
    //   95: ldc_w 668
    //   98: sipush 156
    //   101: bipush 85
    //   103: iconst_3
    //   104: invokestatic 91	xxxxxx/uxxxxx:bbbb0062b0062b0062b0062	(Ljava/lang/String;CCC)Ljava/lang/String;
    //   107: astore 9
    //   109: iconst_3
    //   110: anewarray 93	java/lang/Class
    //   113: astore 10
    //   115: aload 10
    //   117: iconst_0
    //   118: ldc 67
    //   120: aastore
    //   121: aload 10
    //   123: iconst_1
    //   124: getstatic 99	java/lang/Character:TYPE	Ljava/lang/Class;
    //   127: aastore
    //   128: aload 10
    //   130: iconst_2
    //   131: getstatic 99	java/lang/Character:TYPE	Ljava/lang/Class;
    //   134: aastore
    //   135: ldc 101
    //   137: aload 9
    //   139: aload 10
    //   141: invokevirtual 105	java/lang/Class:getMethod	(Ljava/lang/String;[Ljava/lang/Class;)Ljava/lang/reflect/Method;
    //   144: astore 11
    //   146: iconst_3
    //   147: anewarray 107	java/lang/Object
    //   150: astore 12
    //   152: aload 12
    //   154: iconst_0
    //   155: ldc_w 670
    //   158: aastore
    //   159: aload 12
    //   161: iconst_1
    //   162: sipush 196
    //   165: invokestatic 111	java/lang/Character:valueOf	(C)Ljava/lang/Character;
    //   168: aastore
    //   169: aload 12
    //   171: iconst_2
    //   172: iconst_5
    //   173: invokestatic 111	java/lang/Character:valueOf	(C)Ljava/lang/Character;
    //   176: aastore
    //   177: aload 11
    //   179: aconst_null
    //   180: aload 12
    //   182: invokevirtual 117	java/lang/reflect/Method:invoke	(Ljava/lang/Object;[Ljava/lang/Object;)Ljava/lang/Object;
    //   185: astore 14
    //   187: aload_1
    //   188: aload 14
    //   190: checkcast 67	java/lang/String
    //   193: iconst_m1
    //   194: invokevirtual 666	android/os/Bundle:getInt	(Ljava/lang/String;I)I
    //   197: istore 15
    //   199: aload_0
    //   200: getfield 169	com/db/pwcc/dbmobile/transfer/inputscreen/activities/InputSubaccountActivity:accountSelector	Lcom/db/pwcc/dbmobile/foundation/widgets/dbPicker/DbPicker;
    //   203: iload 8
    //   205: invokevirtual 243	com/db/pwcc/dbmobile/foundation/widgets/dbPicker/DbPicker:setSelectedItemPosition	(I)V
    //   208: aload_0
    //   209: iload 8
    //   211: invokespecial 203	com/db/pwcc/dbmobile/transfer/inputscreen/activities/InputSubaccountActivity:generateSubaccountsList	(I)V
    //   214: iload 15
    //   216: iconst_m1
    //   217: if_icmple +12 -> 229
    //   220: aload_0
    //   221: getfield 171	com/db/pwcc/dbmobile/transfer/inputscreen/activities/InputSubaccountActivity:subaccountSelector	Lcom/db/pwcc/dbmobile/foundation/widgets/dbPicker/DbPicker;
    //   224: iload 15
    //   226: invokevirtual 243	com/db/pwcc/dbmobile/foundation/widgets/dbPicker/DbPicker:setSelectedItemPosition	(I)V
    //   229: getstatic 73	com/db/pwcc/dbmobile/transfer/inputscreen/activities/InputSubaccountActivity:bt0074tttt0074tt	I
    //   232: getstatic 75	com/db/pwcc/dbmobile/transfer/inputscreen/activities/InputSubaccountActivity:b00740074tttt0074tt	I
    //   235: iadd
    //   236: getstatic 73	com/db/pwcc/dbmobile/transfer/inputscreen/activities/InputSubaccountActivity:bt0074tttt0074tt	I
    //   239: imul
    //   240: getstatic 132	com/db/pwcc/dbmobile/transfer/inputscreen/activities/InputSubaccountActivity:b007400740074ttt0074tt	I
    //   243: irem
    //   244: getstatic 191	com/db/pwcc/dbmobile/transfer/inputscreen/activities/InputSubaccountActivity:b0074tt0074tt0074tt	I
    //   247: if_icmpeq +48 -> 295
    //   250: invokestatic 81	com/db/pwcc/dbmobile/transfer/inputscreen/activities/InputSubaccountActivity:b0074t0074ttt0074tt	()I
    //   253: getstatic 75	com/db/pwcc/dbmobile/transfer/inputscreen/activities/InputSubaccountActivity:b00740074tttt0074tt	I
    //   256: iadd
    //   257: invokestatic 81	com/db/pwcc/dbmobile/transfer/inputscreen/activities/InputSubaccountActivity:b0074t0074ttt0074tt	()I
    //   260: imul
    //   261: getstatic 132	com/db/pwcc/dbmobile/transfer/inputscreen/activities/InputSubaccountActivity:b007400740074ttt0074tt	I
    //   264: irem
    //   265: getstatic 191	com/db/pwcc/dbmobile/transfer/inputscreen/activities/InputSubaccountActivity:b0074tt0074tt0074tt	I
    //   268: if_icmpeq +15 -> 283
    //   271: invokestatic 81	com/db/pwcc/dbmobile/transfer/inputscreen/activities/InputSubaccountActivity:b0074t0074ttt0074tt	()I
    //   274: putstatic 73	com/db/pwcc/dbmobile/transfer/inputscreen/activities/InputSubaccountActivity:bt0074tttt0074tt	I
    //   277: invokestatic 81	com/db/pwcc/dbmobile/transfer/inputscreen/activities/InputSubaccountActivity:b0074t0074ttt0074tt	()I
    //   280: putstatic 191	com/db/pwcc/dbmobile/transfer/inputscreen/activities/InputSubaccountActivity:b0074tt0074tt0074tt	I
    //   283: invokestatic 81	com/db/pwcc/dbmobile/transfer/inputscreen/activities/InputSubaccountActivity:b0074t0074ttt0074tt	()I
    //   286: putstatic 73	com/db/pwcc/dbmobile/transfer/inputscreen/activities/InputSubaccountActivity:bt0074tttt0074tt	I
    //   289: invokestatic 81	com/db/pwcc/dbmobile/transfer/inputscreen/activities/InputSubaccountActivity:b0074t0074ttt0074tt	()I
    //   292: putstatic 191	com/db/pwcc/dbmobile/transfer/inputscreen/activities/InputSubaccountActivity:b0074tt0074tt0074tt	I
    //   295: aload_0
    //   296: getfield 161	com/db/pwcc/dbmobile/transfer/inputscreen/activities/InputSubaccountActivity:amount	Lcom/db/pwcc/dbmobile/transfer/widgets/inputFields/AmountField;
    //   299: astore 16
    //   301: ldc_w 672
    //   304: sipush 162
    //   307: iconst_0
    //   308: invokestatic 138	xxxxxx/uxxxxx:bb00620062bb0062b0062b0062	(Ljava/lang/String;CC)Ljava/lang/String;
    //   311: astore 17
    //   313: iconst_4
    //   314: anewarray 93	java/lang/Class
    //   317: astore 18
    //   319: aload 18
    //   321: iconst_0
    //   322: ldc 67
    //   324: aastore
    //   325: aload 18
    //   327: iconst_1
    //   328: getstatic 99	java/lang/Character:TYPE	Ljava/lang/Class;
    //   331: aastore
    //   332: aload 18
    //   334: iconst_2
    //   335: getstatic 99	java/lang/Character:TYPE	Ljava/lang/Class;
    //   338: aastore
    //   339: aload 18
    //   341: iconst_3
    //   342: getstatic 99	java/lang/Character:TYPE	Ljava/lang/Class;
    //   345: aastore
    //   346: ldc 101
    //   348: aload 17
    //   350: aload 18
    //   352: invokevirtual 105	java/lang/Class:getMethod	(Ljava/lang/String;[Ljava/lang/Class;)Ljava/lang/reflect/Method;
    //   355: astore 19
    //   357: iconst_4
    //   358: anewarray 107	java/lang/Object
    //   361: astore 20
    //   363: aload 20
    //   365: iconst_0
    //   366: ldc_w 674
    //   369: aastore
    //   370: aload 20
    //   372: iconst_1
    //   373: bipush 77
    //   375: invokestatic 111	java/lang/Character:valueOf	(C)Ljava/lang/Character;
    //   378: aastore
    //   379: aload 20
    //   381: iconst_2
    //   382: bipush 97
    //   384: invokestatic 111	java/lang/Character:valueOf	(C)Ljava/lang/Character;
    //   387: aastore
    //   388: aload 20
    //   390: iconst_3
    //   391: iconst_3
    //   392: invokestatic 111	java/lang/Character:valueOf	(C)Ljava/lang/Character;
    //   395: aastore
    //   396: aload 19
    //   398: aconst_null
    //   399: aload 20
    //   401: invokevirtual 117	java/lang/reflect/Method:invoke	(Ljava/lang/Object;[Ljava/lang/Object;)Ljava/lang/Object;
    //   404: astore 22
    //   406: aload 16
    //   408: aload_1
    //   409: aload 22
    //   411: checkcast 67	java/lang/String
    //   414: ldc_w 396
    //   417: invokevirtual 676	android/os/Bundle:getString	(Ljava/lang/String;Ljava/lang/String;)Ljava/lang/String;
    //   420: invokevirtual 400	com/db/pwcc/dbmobile/transfer/widgets/inputFields/AmountField:setText	(Ljava/lang/CharSequence;)V
    //   423: aload_0
    //   424: getfield 163	com/db/pwcc/dbmobile/transfer/inputscreen/activities/InputSubaccountActivity:description	Lcom/db/pwcc/dbmobile/transfer/widgets/inputFields/InputField;
    //   427: astore 23
    //   429: ldc_w 678
    //   432: bipush 86
    //   434: iconst_1
    //   435: invokestatic 138	xxxxxx/uxxxxx:bb00620062bb0062b0062b0062	(Ljava/lang/String;CC)Ljava/lang/String;
    //   438: astore 24
    //   440: iconst_4
    //   441: anewarray 93	java/lang/Class
    //   444: astore 25
    //   446: aload 25
    //   448: iconst_0
    //   449: ldc 67
    //   451: aastore
    //   452: aload 25
    //   454: iconst_1
    //   455: getstatic 99	java/lang/Character:TYPE	Ljava/lang/Class;
    //   458: aastore
    //   459: aload 25
    //   461: iconst_2
    //   462: getstatic 99	java/lang/Character:TYPE	Ljava/lang/Class;
    //   465: aastore
    //   466: aload 25
    //   468: iconst_3
    //   469: getstatic 99	java/lang/Character:TYPE	Ljava/lang/Class;
    //   472: aastore
    //   473: ldc 101
    //   475: aload 24
    //   477: aload 25
    //   479: invokevirtual 105	java/lang/Class:getMethod	(Ljava/lang/String;[Ljava/lang/Class;)Ljava/lang/reflect/Method;
    //   482: astore 26
    //   484: iconst_4
    //   485: anewarray 107	java/lang/Object
    //   488: astore 27
    //   490: aload 27
    //   492: iconst_0
    //   493: ldc_w 680
    //   496: aastore
    //   497: aload 27
    //   499: iconst_1
    //   500: bipush 41
    //   502: invokestatic 111	java/lang/Character:valueOf	(C)Ljava/lang/Character;
    //   505: aastore
    //   506: aload 27
    //   508: iconst_2
    //   509: bipush 84
    //   511: invokestatic 111	java/lang/Character:valueOf	(C)Ljava/lang/Character;
    //   514: aastore
    //   515: aload 27
    //   517: iconst_3
    //   518: iconst_2
    //   519: invokestatic 111	java/lang/Character:valueOf	(C)Ljava/lang/Character;
    //   522: aastore
    //   523: aload 26
    //   525: aconst_null
    //   526: aload 27
    //   528: invokevirtual 117	java/lang/reflect/Method:invoke	(Ljava/lang/Object;[Ljava/lang/Object;)Ljava/lang/Object;
    //   531: astore 29
    //   533: aload 29
    //   535: checkcast 67	java/lang/String
    //   538: astore 30
    //   540: getstatic 73	com/db/pwcc/dbmobile/transfer/inputscreen/activities/InputSubaccountActivity:bt0074tttt0074tt	I
    //   543: getstatic 75	com/db/pwcc/dbmobile/transfer/inputscreen/activities/InputSubaccountActivity:b00740074tttt0074tt	I
    //   546: iadd
    //   547: getstatic 73	com/db/pwcc/dbmobile/transfer/inputscreen/activities/InputSubaccountActivity:bt0074tttt0074tt	I
    //   550: imul
    //   551: invokestatic 78	com/db/pwcc/dbmobile/transfer/inputscreen/activities/InputSubaccountActivity:btt0074ttt0074tt	()I
    //   554: irem
    //   555: getstatic 191	com/db/pwcc/dbmobile/transfer/inputscreen/activities/InputSubaccountActivity:b0074tt0074tt0074tt	I
    //   558: if_icmpeq +47 -> 605
    //   561: invokestatic 81	com/db/pwcc/dbmobile/transfer/inputscreen/activities/InputSubaccountActivity:b0074t0074ttt0074tt	()I
    //   564: putstatic 73	com/db/pwcc/dbmobile/transfer/inputscreen/activities/InputSubaccountActivity:bt0074tttt0074tt	I
    //   567: bipush 52
    //   569: putstatic 191	com/db/pwcc/dbmobile/transfer/inputscreen/activities/InputSubaccountActivity:b0074tt0074tt0074tt	I
    //   572: getstatic 73	com/db/pwcc/dbmobile/transfer/inputscreen/activities/InputSubaccountActivity:bt0074tttt0074tt	I
    //   575: invokestatic 130	com/db/pwcc/dbmobile/transfer/inputscreen/activities/InputSubaccountActivity:bt00740074ttt0074tt	()I
    //   578: iadd
    //   579: getstatic 73	com/db/pwcc/dbmobile/transfer/inputscreen/activities/InputSubaccountActivity:bt0074tttt0074tt	I
    //   582: imul
    //   583: invokestatic 78	com/db/pwcc/dbmobile/transfer/inputscreen/activities/InputSubaccountActivity:btt0074ttt0074tt	()I
    //   586: irem
    //   587: getstatic 191	com/db/pwcc/dbmobile/transfer/inputscreen/activities/InputSubaccountActivity:b0074tt0074tt0074tt	I
    //   590: if_icmpeq +15 -> 605
    //   593: invokestatic 81	com/db/pwcc/dbmobile/transfer/inputscreen/activities/InputSubaccountActivity:b0074t0074ttt0074tt	()I
    //   596: putstatic 73	com/db/pwcc/dbmobile/transfer/inputscreen/activities/InputSubaccountActivity:bt0074tttt0074tt	I
    //   599: invokestatic 81	com/db/pwcc/dbmobile/transfer/inputscreen/activities/InputSubaccountActivity:b0074t0074ttt0074tt	()I
    //   602: putstatic 191	com/db/pwcc/dbmobile/transfer/inputscreen/activities/InputSubaccountActivity:b0074tt0074tt0074tt	I
    //   605: aload 23
    //   607: aload_1
    //   608: aload 30
    //   610: ldc_w 396
    //   613: invokevirtual 676	android/os/Bundle:getString	(Ljava/lang/String;Ljava/lang/String;)Ljava/lang/String;
    //   616: invokevirtual 401	com/db/pwcc/dbmobile/transfer/widgets/inputFields/InputField:setText	(Ljava/lang/CharSequence;)V
    //   619: return
    //   620: astore 13
    //   622: aload 13
    //   624: invokevirtual 152	java/lang/reflect/InvocationTargetException:getCause	()Ljava/lang/Throwable;
    //   627: athrow
    //   628: astore 28
    //   630: aload 28
    //   632: invokevirtual 152	java/lang/reflect/InvocationTargetException:getCause	()Ljava/lang/Throwable;
    //   635: athrow
    //   636: astore 21
    //   638: aload 21
    //   640: invokevirtual 152	java/lang/reflect/InvocationTargetException:getCause	()Ljava/lang/Throwable;
    //   643: athrow
    //   644: astore 6
    //   646: aload 6
    //   648: invokevirtual 152	java/lang/reflect/InvocationTargetException:getCause	()Ljava/lang/Throwable;
    //   651: athrow
    // Local variable table:
    //   start	length	slot	name	signature
    //   0	652	0	this	InputSubaccountActivity
    //   0	652	1	paramBundle	android.os.Bundle
    //   10	26	2	str1	String
    //   15	22	3	arrayOfClass1	Class[]
    //   40	34	4	localMethod1	Method
    //   46	31	5	arrayOfObject1	Object[]
    //   644	3	6	localInvocationTargetException1	InvocationTargetException
    //   81	4	7	localObject1	Object
    //   93	117	8	i	int
    //   107	31	9	str2	String
    //   113	27	10	arrayOfClass2	Class[]
    //   144	34	11	localMethod2	Method
    //   150	31	12	arrayOfObject2	Object[]
    //   620	3	13	localInvocationTargetException2	InvocationTargetException
    //   185	4	14	localObject2	Object
    //   197	28	15	j	int
    //   299	108	16	localAmountField	AmountField
    //   311	38	17	str3	String
    //   317	34	18	arrayOfClass3	Class[]
    //   355	42	19	localMethod3	Method
    //   361	39	20	arrayOfObject3	Object[]
    //   636	3	21	localInvocationTargetException3	InvocationTargetException
    //   404	6	22	localObject3	Object
    //   427	179	23	localInputField	InputField
    //   438	38	24	str4	String
    //   444	34	25	arrayOfClass4	Class[]
    //   482	42	26	localMethod4	Method
    //   488	39	27	arrayOfObject4	Object[]
    //   628	3	28	localInvocationTargetException4	InvocationTargetException
    //   531	3	29	localObject4	Object
    //   538	71	30	str5	String
    // Exception table:
    //   from	to	target	type
    //   177	187	620	java/lang/reflect/InvocationTargetException
    //   523	533	628	java/lang/reflect/InvocationTargetException
    //   396	406	636	java/lang/reflect/InvocationTargetException
    //   73	83	644	java/lang/reflect/InvocationTargetException
  }
  
  public void onResume()
  {
    int i = bt0074tttt0074tt;
    switch (i * (i + b00740074tttt0074tt) % b007400740074ttt0074tt)
    {
    default: 
      bt0074tttt0074tt = b0074t0074ttt0074tt();
      b0074tt0074tt0074tt = 6;
    }
    super.onResume();
    tnnntn localTnnntn;
    Method localMethod;
    Object[] arrayOfObject;
    if (!oonoon.bk006B006Bkk006B006Bkk006B().b006B006Bk006Bk006B006Bkk006B())
    {
      localTnnntn = this.presenter;
      localMethod = tnnntn.class.getMethod(uxxxxx.bbbb0062b0062b0062b0062("\023\031^]bdZY^`\020\017\016SRWY\t\bMLQS", '', '', '\000'), new Class[0]);
      arrayOfObject = new Object[0];
    }
    try
    {
      localMethod.invoke(localTnnntn, arrayOfObject);
      hideProgressAndEnableInput();
      if ((bt0074tttt0074tt + b00740074tttt0074tt) * bt0074tttt0074tt % b007400740074ttt0074tt != b0074tt0074tt0074tt)
      {
        bt0074tttt0074tt = 50;
        b0074tt0074tt0074tt = 14;
        int j = b0074t0074ttt0074tt();
        switch (j * (j + b00740074tttt0074tt) % b007400740074ttt0074tt)
        {
        default: 
          bt0074tttt0074tt = 38;
          b0074tt0074tt0074tt = 4;
        }
        if ((bt0074tttt0074tt + b00740074tttt0074tt) * bt0074tttt0074tt % b007400740074ttt0074tt != b0074tt0074tt0074tt)
        {
          bt0074tttt0074tt = b0074t0074ttt0074tt();
          b0074tt0074tt0074tt = 66;
        }
      }
      this.principalContainer.requestFocus();
      return;
    }
    catch (InvocationTargetException localInvocationTargetException)
    {
      throw localInvocationTargetException.getCause();
    }
  }
  
  /* Error */
  public void onSaveInstanceState(android.os.Bundle paramBundle)
  {
    // Byte code:
    //   0: getstatic 73	com/db/pwcc/dbmobile/transfer/inputscreen/activities/InputSubaccountActivity:bt0074tttt0074tt	I
    //   3: istore_2
    //   4: iload_2
    //   5: iload_2
    //   6: getstatic 75	com/db/pwcc/dbmobile/transfer/inputscreen/activities/InputSubaccountActivity:b00740074tttt0074tt	I
    //   9: iadd
    //   10: imul
    //   11: getstatic 132	com/db/pwcc/dbmobile/transfer/inputscreen/activities/InputSubaccountActivity:b007400740074ttt0074tt	I
    //   14: irem
    //   15: tableswitch	default:+17->32, 0:+29->44
    //   32: invokestatic 81	com/db/pwcc/dbmobile/transfer/inputscreen/activities/InputSubaccountActivity:b0074t0074ttt0074tt	()I
    //   35: putstatic 73	com/db/pwcc/dbmobile/transfer/inputscreen/activities/InputSubaccountActivity:bt0074tttt0074tt	I
    //   38: invokestatic 81	com/db/pwcc/dbmobile/transfer/inputscreen/activities/InputSubaccountActivity:b0074t0074ttt0074tt	()I
    //   41: putstatic 191	com/db/pwcc/dbmobile/transfer/inputscreen/activities/InputSubaccountActivity:b0074tt0074tt0074tt	I
    //   44: ldc_w 702
    //   47: bipush 93
    //   49: iconst_3
    //   50: invokestatic 138	xxxxxx/uxxxxx:bb00620062bb0062b0062b0062	(Ljava/lang/String;CC)Ljava/lang/String;
    //   53: astore_3
    //   54: iconst_4
    //   55: anewarray 93	java/lang/Class
    //   58: astore 4
    //   60: aload 4
    //   62: iconst_0
    //   63: ldc 67
    //   65: aastore
    //   66: aload 4
    //   68: iconst_1
    //   69: getstatic 99	java/lang/Character:TYPE	Ljava/lang/Class;
    //   72: aastore
    //   73: aload 4
    //   75: iconst_2
    //   76: getstatic 99	java/lang/Character:TYPE	Ljava/lang/Class;
    //   79: aastore
    //   80: aload 4
    //   82: iconst_3
    //   83: getstatic 99	java/lang/Character:TYPE	Ljava/lang/Class;
    //   86: aastore
    //   87: ldc 101
    //   89: aload_3
    //   90: aload 4
    //   92: invokevirtual 105	java/lang/Class:getMethod	(Ljava/lang/String;[Ljava/lang/Class;)Ljava/lang/reflect/Method;
    //   95: astore 5
    //   97: iconst_4
    //   98: anewarray 107	java/lang/Object
    //   101: astore 6
    //   103: aload 6
    //   105: iconst_0
    //   106: ldc_w 704
    //   109: aastore
    //   110: aload 6
    //   112: iconst_1
    //   113: sipush 172
    //   116: invokestatic 111	java/lang/Character:valueOf	(C)Ljava/lang/Character;
    //   119: aastore
    //   120: aload 6
    //   122: iconst_2
    //   123: bipush 95
    //   125: invokestatic 111	java/lang/Character:valueOf	(C)Ljava/lang/Character;
    //   128: aastore
    //   129: aload 6
    //   131: iconst_3
    //   132: iconst_2
    //   133: invokestatic 111	java/lang/Character:valueOf	(C)Ljava/lang/Character;
    //   136: aastore
    //   137: aload 5
    //   139: aconst_null
    //   140: aload 6
    //   142: invokevirtual 117	java/lang/reflect/Method:invoke	(Ljava/lang/Object;[Ljava/lang/Object;)Ljava/lang/Object;
    //   145: astore 8
    //   147: aload_1
    //   148: aload 8
    //   150: checkcast 67	java/lang/String
    //   153: aload_0
    //   154: getfield 169	com/db/pwcc/dbmobile/transfer/inputscreen/activities/InputSubaccountActivity:accountSelector	Lcom/db/pwcc/dbmobile/foundation/widgets/dbPicker/DbPicker;
    //   157: invokevirtual 216	com/db/pwcc/dbmobile/foundation/widgets/dbPicker/DbPicker:getSelectedItemPosition	()I
    //   160: invokevirtual 708	android/os/Bundle:putInt	(Ljava/lang/String;I)V
    //   163: ldc_w 710
    //   166: sipush 187
    //   169: iconst_1
    //   170: invokestatic 138	xxxxxx/uxxxxx:bb00620062bb0062b0062b0062	(Ljava/lang/String;CC)Ljava/lang/String;
    //   173: astore 9
    //   175: iconst_3
    //   176: anewarray 93	java/lang/Class
    //   179: astore 10
    //   181: aload 10
    //   183: iconst_0
    //   184: ldc 67
    //   186: aastore
    //   187: aload 10
    //   189: iconst_1
    //   190: getstatic 99	java/lang/Character:TYPE	Ljava/lang/Class;
    //   193: aastore
    //   194: aload 10
    //   196: iconst_2
    //   197: getstatic 99	java/lang/Character:TYPE	Ljava/lang/Class;
    //   200: aastore
    //   201: ldc 101
    //   203: aload 9
    //   205: aload 10
    //   207: invokevirtual 105	java/lang/Class:getMethod	(Ljava/lang/String;[Ljava/lang/Class;)Ljava/lang/reflect/Method;
    //   210: astore 11
    //   212: iconst_3
    //   213: anewarray 107	java/lang/Object
    //   216: astore 12
    //   218: aload 12
    //   220: iconst_0
    //   221: ldc_w 712
    //   224: aastore
    //   225: aload 12
    //   227: iconst_1
    //   228: bipush 66
    //   230: invokestatic 111	java/lang/Character:valueOf	(C)Ljava/lang/Character;
    //   233: aastore
    //   234: aload 12
    //   236: iconst_2
    //   237: iconst_2
    //   238: invokestatic 111	java/lang/Character:valueOf	(C)Ljava/lang/Character;
    //   241: aastore
    //   242: aload 11
    //   244: aconst_null
    //   245: aload 12
    //   247: invokevirtual 117	java/lang/reflect/Method:invoke	(Ljava/lang/Object;[Ljava/lang/Object;)Ljava/lang/Object;
    //   250: astore 14
    //   252: aload_1
    //   253: aload 14
    //   255: checkcast 67	java/lang/String
    //   258: aload_0
    //   259: getfield 171	com/db/pwcc/dbmobile/transfer/inputscreen/activities/InputSubaccountActivity:subaccountSelector	Lcom/db/pwcc/dbmobile/foundation/widgets/dbPicker/DbPicker;
    //   262: invokevirtual 216	com/db/pwcc/dbmobile/foundation/widgets/dbPicker/DbPicker:getSelectedItemPosition	()I
    //   265: invokevirtual 708	android/os/Bundle:putInt	(Ljava/lang/String;I)V
    //   268: getstatic 73	com/db/pwcc/dbmobile/transfer/inputscreen/activities/InputSubaccountActivity:bt0074tttt0074tt	I
    //   271: istore 15
    //   273: iload 15
    //   275: iload 15
    //   277: getstatic 75	com/db/pwcc/dbmobile/transfer/inputscreen/activities/InputSubaccountActivity:b00740074tttt0074tt	I
    //   280: iadd
    //   281: imul
    //   282: getstatic 132	com/db/pwcc/dbmobile/transfer/inputscreen/activities/InputSubaccountActivity:b007400740074ttt0074tt	I
    //   285: irem
    //   286: tableswitch	default:+18->304, 0:+95->381
    //   304: invokestatic 81	com/db/pwcc/dbmobile/transfer/inputscreen/activities/InputSubaccountActivity:b0074t0074ttt0074tt	()I
    //   307: putstatic 73	com/db/pwcc/dbmobile/transfer/inputscreen/activities/InputSubaccountActivity:bt0074tttt0074tt	I
    //   310: invokestatic 81	com/db/pwcc/dbmobile/transfer/inputscreen/activities/InputSubaccountActivity:b0074t0074ttt0074tt	()I
    //   313: invokestatic 130	com/db/pwcc/dbmobile/transfer/inputscreen/activities/InputSubaccountActivity:bt00740074ttt0074tt	()I
    //   316: iadd
    //   317: invokestatic 81	com/db/pwcc/dbmobile/transfer/inputscreen/activities/InputSubaccountActivity:b0074t0074ttt0074tt	()I
    //   320: imul
    //   321: invokestatic 78	com/db/pwcc/dbmobile/transfer/inputscreen/activities/InputSubaccountActivity:btt0074ttt0074tt	()I
    //   324: irem
    //   325: getstatic 191	com/db/pwcc/dbmobile/transfer/inputscreen/activities/InputSubaccountActivity:b0074tt0074tt0074tt	I
    //   328: if_icmpeq +48 -> 376
    //   331: getstatic 73	com/db/pwcc/dbmobile/transfer/inputscreen/activities/InputSubaccountActivity:bt0074tttt0074tt	I
    //   334: getstatic 75	com/db/pwcc/dbmobile/transfer/inputscreen/activities/InputSubaccountActivity:b00740074tttt0074tt	I
    //   337: iadd
    //   338: getstatic 73	com/db/pwcc/dbmobile/transfer/inputscreen/activities/InputSubaccountActivity:bt0074tttt0074tt	I
    //   341: imul
    //   342: getstatic 132	com/db/pwcc/dbmobile/transfer/inputscreen/activities/InputSubaccountActivity:b007400740074ttt0074tt	I
    //   345: irem
    //   346: getstatic 191	com/db/pwcc/dbmobile/transfer/inputscreen/activities/InputSubaccountActivity:b0074tt0074tt0074tt	I
    //   349: if_icmpeq +15 -> 364
    //   352: invokestatic 81	com/db/pwcc/dbmobile/transfer/inputscreen/activities/InputSubaccountActivity:b0074t0074ttt0074tt	()I
    //   355: putstatic 73	com/db/pwcc/dbmobile/transfer/inputscreen/activities/InputSubaccountActivity:bt0074tttt0074tt	I
    //   358: invokestatic 81	com/db/pwcc/dbmobile/transfer/inputscreen/activities/InputSubaccountActivity:b0074t0074ttt0074tt	()I
    //   361: putstatic 191	com/db/pwcc/dbmobile/transfer/inputscreen/activities/InputSubaccountActivity:b0074tt0074tt0074tt	I
    //   364: invokestatic 81	com/db/pwcc/dbmobile/transfer/inputscreen/activities/InputSubaccountActivity:b0074t0074ttt0074tt	()I
    //   367: putstatic 73	com/db/pwcc/dbmobile/transfer/inputscreen/activities/InputSubaccountActivity:bt0074tttt0074tt	I
    //   370: invokestatic 81	com/db/pwcc/dbmobile/transfer/inputscreen/activities/InputSubaccountActivity:b0074t0074ttt0074tt	()I
    //   373: putstatic 191	com/db/pwcc/dbmobile/transfer/inputscreen/activities/InputSubaccountActivity:b0074tt0074tt0074tt	I
    //   376: bipush 96
    //   378: putstatic 191	com/db/pwcc/dbmobile/transfer/inputscreen/activities/InputSubaccountActivity:b0074tt0074tt0074tt	I
    //   381: ldc_w 714
    //   384: bipush 112
    //   386: sipush 222
    //   389: iconst_3
    //   390: invokestatic 91	xxxxxx/uxxxxx:bbbb0062b0062b0062b0062	(Ljava/lang/String;CCC)Ljava/lang/String;
    //   393: astore 16
    //   395: iconst_3
    //   396: anewarray 93	java/lang/Class
    //   399: astore 17
    //   401: aload 17
    //   403: iconst_0
    //   404: ldc 67
    //   406: aastore
    //   407: aload 17
    //   409: iconst_1
    //   410: getstatic 99	java/lang/Character:TYPE	Ljava/lang/Class;
    //   413: aastore
    //   414: aload 17
    //   416: iconst_2
    //   417: getstatic 99	java/lang/Character:TYPE	Ljava/lang/Class;
    //   420: aastore
    //   421: ldc 101
    //   423: aload 16
    //   425: aload 17
    //   427: invokevirtual 105	java/lang/Class:getMethod	(Ljava/lang/String;[Ljava/lang/Class;)Ljava/lang/reflect/Method;
    //   430: astore 18
    //   432: iconst_3
    //   433: anewarray 107	java/lang/Object
    //   436: astore 19
    //   438: aload 19
    //   440: iconst_0
    //   441: ldc_w 716
    //   444: aastore
    //   445: aload 19
    //   447: iconst_1
    //   448: bipush 88
    //   450: invokestatic 111	java/lang/Character:valueOf	(C)Ljava/lang/Character;
    //   453: aastore
    //   454: aload 19
    //   456: iconst_2
    //   457: iconst_4
    //   458: invokestatic 111	java/lang/Character:valueOf	(C)Ljava/lang/Character;
    //   461: aastore
    //   462: aload 18
    //   464: aconst_null
    //   465: aload 19
    //   467: invokevirtual 117	java/lang/reflect/Method:invoke	(Ljava/lang/Object;[Ljava/lang/Object;)Ljava/lang/Object;
    //   470: astore 21
    //   472: aload_1
    //   473: aload 21
    //   475: checkcast 67	java/lang/String
    //   478: aload_0
    //   479: getfield 161	com/db/pwcc/dbmobile/transfer/inputscreen/activities/InputSubaccountActivity:amount	Lcom/db/pwcc/dbmobile/transfer/widgets/inputFields/AmountField;
    //   482: invokevirtual 475	com/db/pwcc/dbmobile/transfer/widgets/inputFields/AmountField:getText	()Landroid/text/Editable;
    //   485: invokevirtual 478	java/lang/Object:toString	()Ljava/lang/String;
    //   488: invokevirtual 720	android/os/Bundle:putString	(Ljava/lang/String;Ljava/lang/String;)V
    //   491: ldc_w 722
    //   494: bipush 101
    //   496: iconst_1
    //   497: invokestatic 138	xxxxxx/uxxxxx:bb00620062bb0062b0062b0062	(Ljava/lang/String;CC)Ljava/lang/String;
    //   500: astore 22
    //   502: iconst_3
    //   503: anewarray 93	java/lang/Class
    //   506: astore 23
    //   508: aload 23
    //   510: iconst_0
    //   511: ldc 67
    //   513: aastore
    //   514: aload 23
    //   516: iconst_1
    //   517: getstatic 99	java/lang/Character:TYPE	Ljava/lang/Class;
    //   520: aastore
    //   521: aload 23
    //   523: iconst_2
    //   524: getstatic 99	java/lang/Character:TYPE	Ljava/lang/Class;
    //   527: aastore
    //   528: ldc 101
    //   530: aload 22
    //   532: aload 23
    //   534: invokevirtual 105	java/lang/Class:getMethod	(Ljava/lang/String;[Ljava/lang/Class;)Ljava/lang/reflect/Method;
    //   537: astore 24
    //   539: iconst_3
    //   540: anewarray 107	java/lang/Object
    //   543: astore 25
    //   545: aload 25
    //   547: iconst_0
    //   548: ldc_w 724
    //   551: aastore
    //   552: aload 25
    //   554: iconst_1
    //   555: bipush 75
    //   557: invokestatic 111	java/lang/Character:valueOf	(C)Ljava/lang/Character;
    //   560: aastore
    //   561: aload 25
    //   563: iconst_2
    //   564: iconst_4
    //   565: invokestatic 111	java/lang/Character:valueOf	(C)Ljava/lang/Character;
    //   568: aastore
    //   569: aload 24
    //   571: aconst_null
    //   572: aload 25
    //   574: invokevirtual 117	java/lang/reflect/Method:invoke	(Ljava/lang/Object;[Ljava/lang/Object;)Ljava/lang/Object;
    //   577: astore 27
    //   579: aload_1
    //   580: aload 27
    //   582: checkcast 67	java/lang/String
    //   585: aload_0
    //   586: invokevirtual 726	com/db/pwcc/dbmobile/transfer/inputscreen/activities/InputSubaccountActivity:getDescription	()Ljava/lang/String;
    //   589: invokevirtual 720	android/os/Bundle:putString	(Ljava/lang/String;Ljava/lang/String;)V
    //   592: aload_0
    //   593: aload_1
    //   594: invokespecial 728	com/db/pwcc/dbmobile/foundation/activities/common/PopupActivity:onSaveInstanceState	(Landroid/os/Bundle;)V
    //   597: return
    //   598: astore 7
    //   600: aload 7
    //   602: invokevirtual 152	java/lang/reflect/InvocationTargetException:getCause	()Ljava/lang/Throwable;
    //   605: athrow
    //   606: astore 26
    //   608: aload 26
    //   610: invokevirtual 152	java/lang/reflect/InvocationTargetException:getCause	()Ljava/lang/Throwable;
    //   613: athrow
    //   614: astore 20
    //   616: aload 20
    //   618: invokevirtual 152	java/lang/reflect/InvocationTargetException:getCause	()Ljava/lang/Throwable;
    //   621: athrow
    //   622: astore 13
    //   624: aload 13
    //   626: invokevirtual 152	java/lang/reflect/InvocationTargetException:getCause	()Ljava/lang/Throwable;
    //   629: athrow
    // Local variable table:
    //   start	length	slot	name	signature
    //   0	630	0	this	InputSubaccountActivity
    //   0	630	1	paramBundle	android.os.Bundle
    //   3	8	2	i	int
    //   53	37	3	str1	String
    //   58	33	4	arrayOfClass1	Class[]
    //   95	43	5	localMethod1	Method
    //   101	40	6	arrayOfObject1	Object[]
    //   598	3	7	localInvocationTargetException1	InvocationTargetException
    //   145	4	8	localObject1	Object
    //   173	31	9	str2	String
    //   179	27	10	arrayOfClass2	Class[]
    //   210	33	11	localMethod2	Method
    //   216	30	12	arrayOfObject2	Object[]
    //   622	3	13	localInvocationTargetException2	InvocationTargetException
    //   250	4	14	localObject2	Object
    //   271	11	15	j	int
    //   393	31	16	str3	String
    //   399	27	17	arrayOfClass3	Class[]
    //   430	33	18	localMethod3	Method
    //   436	30	19	arrayOfObject3	Object[]
    //   614	3	20	localInvocationTargetException3	InvocationTargetException
    //   470	4	21	localObject3	Object
    //   500	31	22	str4	String
    //   506	27	23	arrayOfClass4	Class[]
    //   537	33	24	localMethod4	Method
    //   543	30	25	arrayOfObject4	Object[]
    //   606	3	26	localInvocationTargetException4	InvocationTargetException
    //   577	4	27	localObject4	Object
    // Exception table:
    //   from	to	target	type
    //   137	147	598	java/lang/reflect/InvocationTargetException
    //   569	579	606	java/lang/reflect/InvocationTargetException
    //   462	472	614	java/lang/reflect/InvocationTargetException
    //   242	252	622	java/lang/reflect/InvocationTargetException
  }
  
  public void setUI(FinancialOverviewData paramFinancialOverviewData)
  {
    setDifferentPrefilledAccounts();
    generateSubaccountsList(this.accountSelector.getSelectedItemPositionOrDefault());
    final String str = getResources().getString(R.string.sepatransfer_input_subaccount_picker_default);
    int i = bt0074tttt0074tt;
    switch (i * (i + b00740074tttt0074tt) % b007400740074ttt0074tt)
    {
    default: 
      bt0074tttt0074tt = 59;
      b0074tt0074tt0074tt = b0074t0074ttt0074tt();
    }
    this.subaccountSelector.deselectWithText(str);
    this.accountSelector.setOnItemClickedListener(new AdapterView.OnItemClickListener()
    {
      public static int b00620062bb0062bb00620062 = 2;
      public static int b0062b0062b0062bb00620062 = 0;
      public static int bb0062bb0062bb00620062 = 31;
      public static int bbb0062b0062bb00620062 = 1;
      
      public static int b006900690069iiiiii0069()
      {
        return 2;
      }
      
      public static int bi00690069iiiiii0069()
      {
        return 91;
      }
      
      public static int biii0069iiiii0069()
      {
        return 1;
      }
      
      public void onItemClick(AdapterView<?> paramAnonymousAdapterView, View paramAnonymousView, int paramAnonymousInt, long paramAnonymousLong)
      {
        int i = bb0062bb0062bb00620062;
        switch (i * (i + biii0069iiiii0069()) % b00620062bb0062bb00620062)
        {
        default: 
          int k = bb0062bb0062bb00620062;
          int m = bb0062bb0062bb00620062;
          switch (m * (m + bbb0062b0062bb00620062) % b00620062bb0062bb00620062)
          {
          default: 
            bb0062bb0062bb00620062 = 20;
            bbb0062b0062bb00620062 = 13;
          }
          switch (k * (k + bbb0062b0062bb00620062) % b00620062bb0062bb00620062)
          {
          default: 
            bb0062bb0062bb00620062 = 29;
            bbb0062b0062bb00620062 = 43;
          }
          bb0062bb0062bb00620062 = 35;
          b00620062bb0062bb00620062 = 89;
        }
        int j = InputSubaccountActivity.access$000(InputSubaccountActivity.this).getSelectedItemPosition();
        if (j >= 0)
        {
          Account localAccount = InputSubaccountActivity.access$100(InputSubaccountActivity.this).b0069ii0069ii0069006900690069(j);
          if (InputSubaccountActivity.access$200(InputSubaccountActivity.this).b0069ii0069ii0069006900690069(paramAnonymousInt).getAccountNumber().equals(localAccount.getAccountNumber()))
          {
            DbPicker localDbPicker = InputSubaccountActivity.access$000(InputSubaccountActivity.this);
            String str = str;
            if ((bb0062bb0062bb00620062 + bbb0062b0062bb00620062) * bb0062bb0062bb00620062 % b006900690069iiiiii0069() != b0062b0062b0062bb00620062)
            {
              bb0062bb0062bb00620062 = bi00690069iiiiii0069();
              b0062b0062b0062bb00620062 = 1;
            }
            localDbPicker.deselectWithText(str);
            InputSubaccountActivity.access$300(InputSubaccountActivity.this);
          }
        }
        InputSubaccountActivity.access$400(InputSubaccountActivity.this, paramAnonymousInt);
      }
    });
    this.subaccountSelector.setOnItemClickedListener(new AdapterView.OnItemClickListener()
    {
      public static int b006200620062b0062bb00620062 = 44;
      public static int b0062bb00620062bb00620062 = 1;
      public static int bb0062b00620062bb00620062 = 2;
      public static int bbbb00620062bb00620062;
      
      public static int b0069ii0069iiiii0069()
      {
        return 27;
      }
      
      public void onItemClick(AdapterView<?> paramAnonymousAdapterView, View paramAnonymousView, int paramAnonymousInt, long paramAnonymousLong)
      {
        int i = b006200620062b0062bb00620062;
        switch (i * (i + b0062bb00620062bb00620062) % bb0062b00620062bb00620062)
        {
        default: 
          b006200620062b0062bb00620062 = 87;
          bbbb00620062bb00620062 = b0069ii0069iiiii0069();
        }
        InputSubaccountActivity localInputSubaccountActivity = InputSubaccountActivity.this;
        int j = b006200620062b0062bb00620062 + b0062bb00620062bb00620062;
        int k = b006200620062b0062bb00620062;
        int m = b006200620062b0062bb00620062;
        int n = m * (m + b0062bb00620062bb00620062) % bb0062b00620062bb00620062;
        int i1 = b006200620062b0062bb00620062;
        switch (i1 * (i1 + b0062bb00620062bb00620062) % bb0062b00620062bb00620062)
        {
        default: 
          b006200620062b0062bb00620062 = 10;
          bbbb00620062bb00620062 = b0069ii0069iiiii0069();
        }
        switch (n)
        {
        default: 
          b006200620062b0062bb00620062 = 36;
          bbbb00620062bb00620062 = b0069ii0069iiiii0069();
        }
        if (j * k % bb0062b00620062bb00620062 != bbbb00620062bb00620062)
        {
          b006200620062b0062bb00620062 = b0069ii0069iiiii0069();
          bbbb00620062bb00620062 = 76;
        }
        InputSubaccountActivity.access$300(localInputSubaccountActivity);
      }
    });
    if (this.buttonDone == null)
    {
      int k = R.id.input_subaccount_done_btn;
      if ((bt0074tttt0074tt + b00740074tttt0074tt) * bt0074tttt0074tt % b007400740074ttt0074tt != b0074tt0074tt0074tt)
      {
        bt0074tttt0074tt = 90;
        b0074tt0074tt0074tt = 65;
      }
      int m = bt0074tttt0074tt;
      switch (m * (m + b00740074tttt0074tt) % b007400740074ttt0074tt)
      {
      default: 
        bt0074tttt0074tt = 38;
        b0074tt0074tt0074tt = b0074t0074ttt0074tt();
      }
      this.buttonDone = ((Button)findViewById(k));
    }
    InstrumentationCallbacks.setOnClickListenerCalled(this.buttonDone, new View.OnClickListener()
    {
      public static int b00740074t0074t00740074tt = 64;
      public static int b0074t00740074t00740074tt = 1;
      public static int bt007400740074t00740074tt = 2;
      public static int btttt007400740074tt;
      
      public static int b0074007400740074t00740074tt()
      {
        return 25;
      }
      
      public static int btt00740074t00740074tt()
      {
        return 0;
      }
      
      /* Error */
      public void onClick(View paramAnonymousView)
      {
        // Byte code:
        //   0: aload_0
        //   1: getfield 25	com/db/pwcc/dbmobile/transfer/inputscreen/activities/InputSubaccountActivity$4:this$0	Lcom/db/pwcc/dbmobile/transfer/inputscreen/activities/InputSubaccountActivity;
        //   4: invokestatic 39	com/db/pwcc/dbmobile/transfer/inputscreen/activities/InputSubaccountActivity:access$500	(Lcom/db/pwcc/dbmobile/transfer/inputscreen/activities/InputSubaccountActivity;)Lcom/db/pwcc/dbmobile/foundation/views/button/Button;
        //   7: invokevirtual 45	com/db/pwcc/dbmobile/foundation/views/button/Button:getButtonState	()Luuuuuu/kvkvvv;
        //   10: getstatic 51	uuuuuu/kvkvvv:bff0066f0066f006600660066	Luuuuuu/kvkvvv;
        //   13: if_acmpeq +267 -> 280
        //   16: aload_0
        //   17: getfield 25	com/db/pwcc/dbmobile/transfer/inputscreen/activities/InputSubaccountActivity$4:this$0	Lcom/db/pwcc/dbmobile/transfer/inputscreen/activities/InputSubaccountActivity;
        //   20: invokestatic 39	com/db/pwcc/dbmobile/transfer/inputscreen/activities/InputSubaccountActivity:access$500	(Lcom/db/pwcc/dbmobile/transfer/inputscreen/activities/InputSubaccountActivity;)Lcom/db/pwcc/dbmobile/foundation/views/button/Button;
        //   23: invokestatic 56	uuuuuu/nononn:bk006B006Bk006B006Bk006Bk006B	(Landroid/view/View;)V
        //   26: getstatic 58	com/db/pwcc/dbmobile/transfer/inputscreen/activities/InputSubaccountActivity$4:b00740074t0074t00740074tt	I
        //   29: getstatic 60	com/db/pwcc/dbmobile/transfer/inputscreen/activities/InputSubaccountActivity$4:b0074t00740074t00740074tt	I
        //   32: iadd
        //   33: getstatic 58	com/db/pwcc/dbmobile/transfer/inputscreen/activities/InputSubaccountActivity$4:b00740074t0074t00740074tt	I
        //   36: imul
        //   37: getstatic 62	com/db/pwcc/dbmobile/transfer/inputscreen/activities/InputSubaccountActivity$4:bt007400740074t00740074tt	I
        //   40: irem
        //   41: istore_2
        //   42: getstatic 58	com/db/pwcc/dbmobile/transfer/inputscreen/activities/InputSubaccountActivity$4:b00740074t0074t00740074tt	I
        //   45: istore_3
        //   46: iload_3
        //   47: iload_3
        //   48: getstatic 60	com/db/pwcc/dbmobile/transfer/inputscreen/activities/InputSubaccountActivity$4:b0074t00740074t00740074tt	I
        //   51: iadd
        //   52: imul
        //   53: getstatic 62	com/db/pwcc/dbmobile/transfer/inputscreen/activities/InputSubaccountActivity$4:bt007400740074t00740074tt	I
        //   56: irem
        //   57: tableswitch	default:+19->76, 0:+31->88
        //   76: invokestatic 64	com/db/pwcc/dbmobile/transfer/inputscreen/activities/InputSubaccountActivity$4:b0074007400740074t00740074tt	()I
        //   79: putstatic 58	com/db/pwcc/dbmobile/transfer/inputscreen/activities/InputSubaccountActivity$4:b00740074t0074t00740074tt	I
        //   82: invokestatic 64	com/db/pwcc/dbmobile/transfer/inputscreen/activities/InputSubaccountActivity$4:b0074007400740074t00740074tt	()I
        //   85: putstatic 60	com/db/pwcc/dbmobile/transfer/inputscreen/activities/InputSubaccountActivity$4:b0074t00740074t00740074tt	I
        //   88: iload_2
        //   89: invokestatic 66	com/db/pwcc/dbmobile/transfer/inputscreen/activities/InputSubaccountActivity$4:btt00740074t00740074tt	()I
        //   92: if_icmpeq +13 -> 105
        //   95: bipush 22
        //   97: putstatic 58	com/db/pwcc/dbmobile/transfer/inputscreen/activities/InputSubaccountActivity$4:b00740074t0074t00740074tt	I
        //   100: bipush 65
        //   102: putstatic 60	com/db/pwcc/dbmobile/transfer/inputscreen/activities/InputSubaccountActivity$4:b0074t00740074t00740074tt	I
        //   105: aload_0
        //   106: getfield 25	com/db/pwcc/dbmobile/transfer/inputscreen/activities/InputSubaccountActivity$4:this$0	Lcom/db/pwcc/dbmobile/transfer/inputscreen/activities/InputSubaccountActivity;
        //   109: invokestatic 70	com/db/pwcc/dbmobile/transfer/inputscreen/activities/InputSubaccountActivity:access$600	(Lcom/db/pwcc/dbmobile/transfer/inputscreen/activities/InputSubaccountActivity;)Luuuuuu/tnnntn;
        //   112: astore 4
        //   114: ldc 72
        //   116: ldc 74
        //   118: bipush 42
        //   120: sipush 224
        //   123: iconst_2
        //   124: invokestatic 80	xxxxxx/uxxxxx:bbbb0062b0062b0062b0062	(Ljava/lang/String;CCC)Ljava/lang/String;
        //   127: iconst_0
        //   128: anewarray 82	java/lang/Class
        //   131: invokevirtual 86	java/lang/Class:getMethod	(Ljava/lang/String;[Ljava/lang/Class;)Ljava/lang/reflect/Method;
        //   134: astore 5
        //   136: iconst_0
        //   137: anewarray 4	java/lang/Object
        //   140: astore 6
        //   142: aload 5
        //   144: aload 4
        //   146: aload 6
        //   148: invokevirtual 92	java/lang/reflect/Method:invoke	(Ljava/lang/Object;[Ljava/lang/Object;)Ljava/lang/Object;
        //   151: pop
        //   152: aload_0
        //   153: getfield 25	com/db/pwcc/dbmobile/transfer/inputscreen/activities/InputSubaccountActivity$4:this$0	Lcom/db/pwcc/dbmobile/transfer/inputscreen/activities/InputSubaccountActivity;
        //   156: astore 9
        //   158: getstatic 58	com/db/pwcc/dbmobile/transfer/inputscreen/activities/InputSubaccountActivity$4:b00740074t0074t00740074tt	I
        //   161: getstatic 60	com/db/pwcc/dbmobile/transfer/inputscreen/activities/InputSubaccountActivity$4:b0074t00740074t00740074tt	I
        //   164: iadd
        //   165: getstatic 58	com/db/pwcc/dbmobile/transfer/inputscreen/activities/InputSubaccountActivity$4:b00740074t0074t00740074tt	I
        //   168: imul
        //   169: getstatic 62	com/db/pwcc/dbmobile/transfer/inputscreen/activities/InputSubaccountActivity$4:bt007400740074t00740074tt	I
        //   172: irem
        //   173: getstatic 94	com/db/pwcc/dbmobile/transfer/inputscreen/activities/InputSubaccountActivity$4:btttt007400740074tt	I
        //   176: if_icmpeq +59 -> 235
        //   179: bipush 57
        //   181: putstatic 58	com/db/pwcc/dbmobile/transfer/inputscreen/activities/InputSubaccountActivity$4:b00740074t0074t00740074tt	I
        //   184: iconst_5
        //   185: putstatic 94	com/db/pwcc/dbmobile/transfer/inputscreen/activities/InputSubaccountActivity$4:btttt007400740074tt	I
        //   188: getstatic 58	com/db/pwcc/dbmobile/transfer/inputscreen/activities/InputSubaccountActivity$4:b00740074t0074t00740074tt	I
        //   191: istore 15
        //   193: iload 15
        //   195: iload 15
        //   197: getstatic 60	com/db/pwcc/dbmobile/transfer/inputscreen/activities/InputSubaccountActivity$4:b0074t00740074t00740074tt	I
        //   200: iadd
        //   201: imul
        //   202: getstatic 62	com/db/pwcc/dbmobile/transfer/inputscreen/activities/InputSubaccountActivity$4:bt007400740074t00740074tt	I
        //   205: irem
        //   206: tableswitch	default:+18->224, 0:+29->235
        //   224: bipush 37
        //   226: putstatic 58	com/db/pwcc/dbmobile/transfer/inputscreen/activities/InputSubaccountActivity$4:b00740074t0074t00740074tt	I
        //   229: invokestatic 64	com/db/pwcc/dbmobile/transfer/inputscreen/activities/InputSubaccountActivity$4:b0074007400740074t00740074tt	()I
        //   232: putstatic 94	com/db/pwcc/dbmobile/transfer/inputscreen/activities/InputSubaccountActivity$4:btttt007400740074tt	I
        //   235: aload 9
        //   237: invokestatic 70	com/db/pwcc/dbmobile/transfer/inputscreen/activities/InputSubaccountActivity:access$600	(Lcom/db/pwcc/dbmobile/transfer/inputscreen/activities/InputSubaccountActivity;)Luuuuuu/tnnntn;
        //   240: astore 10
        //   242: ldc 72
        //   244: ldc 96
        //   246: sipush 195
        //   249: bipush 35
        //   251: iconst_2
        //   252: invokestatic 80	xxxxxx/uxxxxx:bbbb0062b0062b0062b0062	(Ljava/lang/String;CCC)Ljava/lang/String;
        //   255: iconst_0
        //   256: anewarray 82	java/lang/Class
        //   259: invokevirtual 86	java/lang/Class:getMethod	(Ljava/lang/String;[Ljava/lang/Class;)Ljava/lang/reflect/Method;
        //   262: astore 11
        //   264: iconst_0
        //   265: anewarray 4	java/lang/Object
        //   268: astore 12
        //   270: aload 11
        //   272: aload 10
        //   274: aload 12
        //   276: invokevirtual 92	java/lang/reflect/Method:invoke	(Ljava/lang/Object;[Ljava/lang/Object;)Ljava/lang/Object;
        //   279: pop
        //   280: return
        //   281: astore 13
        //   283: aload 13
        //   285: invokevirtual 100	java/lang/reflect/InvocationTargetException:getCause	()Ljava/lang/Throwable;
        //   288: athrow
        //   289: astore 7
        //   291: aload 7
        //   293: invokevirtual 100	java/lang/reflect/InvocationTargetException:getCause	()Ljava/lang/Throwable;
        //   296: athrow
        // Local variable table:
        //   start	length	slot	name	signature
        //   0	297	0	this	4
        //   0	297	1	paramAnonymousView	View
        //   41	52	2	i	int
        //   45	8	3	j	int
        //   112	33	4	localTnnntn1	tnnntn
        //   134	9	5	localMethod1	Method
        //   140	7	6	arrayOfObject1	Object[]
        //   289	3	7	localInvocationTargetException1	InvocationTargetException
        //   156	80	9	localInputSubaccountActivity	InputSubaccountActivity
        //   240	33	10	localTnnntn2	tnnntn
        //   262	9	11	localMethod2	Method
        //   268	7	12	arrayOfObject2	Object[]
        //   281	3	13	localInvocationTargetException2	InvocationTargetException
        //   191	11	15	k	int
        // Exception table:
        //   from	to	target	type
        //   270	280	281	java/lang/reflect/InvocationTargetException
        //   142	152	289	java/lang/reflect/InvocationTargetException
      }
    });
    AmountField localAmountField = this.amount;
    int j = bt0074tttt0074tt;
    switch (j * (j + b00740074tttt0074tt) % b007400740074ttt0074tt)
    {
    default: 
      bt0074tttt0074tt = b0074t0074ttt0074tt();
      b0074tt0074tt0074tt = 25;
    }
    localAmountField.addTextChangedListener(new TextWatcher()
    {
      public static int b00620062006200620062bb00620062 = 1;
      public static int b0062b006200620062bb00620062 = 17;
      public static int bb0062006200620062bb00620062 = 0;
      public static int bbbbbb0062b00620062 = 2;
      public BigDecimal b00620062b00620062bb00620062;
      
      public static int b00690069i0069iiiii0069()
      {
        return 97;
      }
      
      public static int bi0069i0069iiiii0069()
      {
        return 2;
      }
      
      public static int bii00690069iiiii0069()
      {
        return 0;
      }
      
      public void afterTextChanged(Editable paramAnonymousEditable)
      {
        if (this.b00620062b00620062bb00620062.compareTo(InputSubaccountActivity.this.getAmount()) == 0)
        {
          if ((b0062b006200620062bb00620062 + b00620062006200620062bb00620062) * b0062b006200620062bb00620062 % bbbbbb0062b00620062 != bb0062006200620062bb00620062)
          {
            b0062b006200620062bb00620062 = b00690069i0069iiiii0069();
            bb0062006200620062bb00620062 = 3;
          }
          InputSubaccountActivity.access$700(InputSubaccountActivity.this);
          if ((b0062b006200620062bb00620062 + b00620062006200620062bb00620062) * b0062b006200620062bb00620062 % bbbbbb0062b00620062 != bb0062006200620062bb00620062)
          {
            if ((b0062b006200620062bb00620062 + b00620062006200620062bb00620062) * b0062b006200620062bb00620062 % bbbbbb0062b00620062 != bb0062006200620062bb00620062)
            {
              b0062b006200620062bb00620062 = 92;
              bb0062006200620062bb00620062 = b00690069i0069iiiii0069();
            }
            if ((b0062b006200620062bb00620062 + b00620062006200620062bb00620062) * b0062b006200620062bb00620062 % bbbbbb0062b00620062 != bb0062006200620062bb00620062)
            {
              b0062b006200620062bb00620062 = 36;
              bb0062006200620062bb00620062 = 39;
            }
            b0062b006200620062bb00620062 = 25;
            bb0062006200620062bb00620062 = b00690069i0069iiiii0069();
          }
        }
        InputSubaccountActivity.access$300(InputSubaccountActivity.this);
      }
      
      public void beforeTextChanged(CharSequence paramAnonymousCharSequence, int paramAnonymousInt1, int paramAnonymousInt2, int paramAnonymousInt3)
      {
        if ((b0062b006200620062bb00620062 + b00620062006200620062bb00620062) * b0062b006200620062bb00620062 % bi0069i0069iiiii0069() != bii00690069iiiii0069())
        {
          int i = b0062b006200620062bb00620062;
          switch (i * (i + b00620062006200620062bb00620062) % bbbbbb0062b00620062)
          {
          default: 
            b0062b006200620062bb00620062 = 28;
            bb0062006200620062bb00620062 = 30;
            if ((b0062b006200620062bb00620062 + b00620062006200620062bb00620062) * b0062b006200620062bb00620062 % bbbbbb0062b00620062 != bb0062006200620062bb00620062)
            {
              b0062b006200620062bb00620062 = 54;
              bb0062006200620062bb00620062 = 31;
            }
            break;
          }
          b0062b006200620062bb00620062 = b00690069i0069iiiii0069();
          bb0062006200620062bb00620062 = b00690069i0069iiiii0069();
          if ((b0062b006200620062bb00620062 + b00620062006200620062bb00620062) * b0062b006200620062bb00620062 % bbbbbb0062b00620062 != bb0062006200620062bb00620062)
          {
            b0062b006200620062bb00620062 = b00690069i0069iiiii0069();
            bb0062006200620062bb00620062 = 58;
          }
        }
        this.b00620062b00620062bb00620062 = InputSubaccountActivity.this.getAmount();
      }
      
      public void onTextChanged(CharSequence paramAnonymousCharSequence, int paramAnonymousInt1, int paramAnonymousInt2, int paramAnonymousInt3) {}
    });
  }
  
  public void showPrincipalAccounts(List<Account> paramList)
  {
    if ((bt0074tttt0074tt + b00740074tttt0074tt) * bt0074tttt0074tt % b007400740074ttt0074tt != b0074tt0074tt0074tt)
    {
      if ((bt0074tttt0074tt + b00740074tttt0074tt) * bt0074tttt0074tt % btt0074ttt0074tt() != b0074tt0074tt0074tt)
      {
        if ((bt0074tttt0074tt + b00740074tttt0074tt) * bt0074tttt0074tt % b007400740074ttt0074tt != b0074tt0074tt0074tt)
        {
          bt0074tttt0074tt = 23;
          b0074tt0074tt0074tt = b0074t0074ttt0074tt();
        }
        int i = bt0074tttt0074tt;
        switch (i * (i + b00740074tttt0074tt) % b007400740074ttt0074tt)
        {
        default: 
          bt0074tttt0074tt = 74;
          b0074tt0074tt0074tt = b0074t0074ttt0074tt();
        }
        bt0074tttt0074tt = 89;
        b0074tt0074tt0074tt = b0074t0074ttt0074tt();
      }
      bt0074tttt0074tt = b0074t0074ttt0074tt();
      b0074tt0074tt0074tt = b0074t0074ttt0074tt();
    }
    this.accountAdapter = new lvvvvv(this, R.layout.list_item, paramList);
    this.accountSelector.setAdapter(this.accountAdapter);
    selectPrincipleAccount();
  }
  
  public void showProgressAndDisableInput()
  {
    int i = bt0074tttt0074tt;
    switch (i * (i + b00740074tttt0074tt) % b007400740074ttt0074tt)
    {
    default: 
      bt0074tttt0074tt = b0074t0074ttt0074tt();
      b0074tt0074tt0074tt = 42;
    }
    Window localWindow = getWindow();
    int j = bt0074tttt0074tt;
    int k = b00740074tttt0074tt;
    int m = bt0074tttt0074tt;
    switch (m * (m + bt00740074ttt0074tt()) % b007400740074ttt0074tt)
    {
    default: 
      bt0074tttt0074tt = b0074t0074ttt0074tt();
      b0074tt0074tt0074tt = 80;
      if ((bt0074tttt0074tt + b00740074tttt0074tt) * bt0074tttt0074tt % b007400740074ttt0074tt != b0074tt0074tt0074tt)
      {
        bt0074tttt0074tt = b0074t0074ttt0074tt();
        b0074tt0074tt0074tt = 25;
      }
      break;
    }
    if ((j + k) * bt0074tttt0074tt % b007400740074ttt0074tt != b0074tt0074tt0074tt)
    {
      bt0074tttt0074tt = 45;
      b0074tt0074tt0074tt = 34;
    }
    nonnnn.b006B006B006B006Bkk006B006Bk006B(localWindow);
    this.buttonDone.changeButtonState(kvkvvv.b0066f0066f0066f006600660066);
  }
  
  public void showSubAccounts(List<Account> paramList)
  {
    this.subaccountsList.addAll(paramList);
    int i = b0074t0074ttt0074tt() + b00740074tttt0074tt;
    if ((bt0074tttt0074tt + b00740074tttt0074tt) * bt0074tttt0074tt % b007400740074ttt0074tt != b0074tt0074tt0074tt)
    {
      bt0074tttt0074tt = b0074t0074ttt0074tt();
      b0074tt0074tt0074tt = b0074t0074ttt0074tt();
    }
    if (i * b0074t0074ttt0074tt() % b007400740074ttt0074tt != bttt0074tt0074tt())
    {
      int j = bt0074tttt0074tt;
      if ((bt0074tttt0074tt + b00740074tttt0074tt) * bt0074tttt0074tt % b007400740074ttt0074tt != b0074tt0074tt0074tt)
      {
        bt0074tttt0074tt = 38;
        b0074tt0074tt0074tt = b0074t0074ttt0074tt();
      }
      switch (j * (j + b00740074tttt0074tt) % b007400740074ttt0074tt)
      {
      default: 
        bt0074tttt0074tt = 71;
        b0074tt0074tt0074tt = 16;
      }
      bt0074tttt0074tt = b0074t0074ttt0074tt();
      b0074tt0074tt0074tt = 47;
    }
    this.subaccountAdapter = new lvvvvv(this, R.layout.list_item, paramList);
    this.subaccountSelector.setAdapter(this.subaccountAdapter);
  }
  
  public void updateAmountErrorLabel()
  {
    DbTextView localDbTextView = this.amountErrorMessage;
    if ((bt0074tttt0074tt + b00740074tttt0074tt) * bt0074tttt0074tt % b007400740074ttt0074tt != bttt0074tt0074tt())
    {
      int j = bt0074tttt0074tt;
      switch (j * (j + b00740074tttt0074tt) % btt0074ttt0074tt())
      {
      default: 
        bt0074tttt0074tt = b0074t0074ttt0074tt();
        b0074tt0074tt0074tt = b0074t0074ttt0074tt();
      }
      bt0074tttt0074tt = 63;
      b0074tt0074tt0074tt = b0074t0074ttt0074tt();
      if ((bt0074tttt0074tt + b00740074tttt0074tt) * bt0074tttt0074tt % b007400740074ttt0074tt != b0074tt0074tt0074tt)
      {
        bt0074tttt0074tt = b0074t0074ttt0074tt();
        b0074tt0074tt0074tt = b0074t0074ttt0074tt();
      }
    }
    localDbTextView.setVisibility(0);
    this.buttonDone.changeButtonState(kvkvvv.bf00660066f0066f006600660066);
    nonnnn.bkkkk006Bk006B006Bk006B(getWindow());
    this.amount.requestFocus();
    int i = bt0074tttt0074tt;
    switch (i * (i + b00740074tttt0074tt) % b007400740074ttt0074tt)
    {
    default: 
      bt0074tttt0074tt = 74;
      b0074tt0074tt0074tt = 67;
    }
    nononn.bk006Bk006B006B006Bk006Bk006B(this, this.amount);
  }
}
