package com.datami.smi.e;

import java.util.Queue;
import java.util.concurrent.ConcurrentLinkedQueue;

class k
  extends Thread
{
  private static String a = "k";
  private static final byte[] d = { 33, -48, -27, -100, 50, -22, 1, 10, 3, -12, 5, -2, -79, 86, -15, 10, -13, -73, 82, -15, 6, -8, -3, 16, -6, 2, -71, -13, 86, -9, 2, -8, -7, 12, -83, 86, -15, 2, -1, -77, 65, 2, -70, 82, 0, -6, 0, -1, -12, -2, -68, 43, 5, -10, -9, -69, 77, 0, 4, -85, 66, 8, 2, 3, -15, -70, 82, -15, 6, -8, -3, 16, -6, 2, -83, 79, 1, -4, 0, -12, 12, -7, 12, -76, 25, -5, -19, 23, 2, -8, -7, 12 };
  private static int e = 144;
  private final Queue c;
  
  public k(ConcurrentLinkedQueue paramConcurrentLinkedQueue)
  {
    super(a(i + 1, j, j));
    this.c = paramConcurrentLinkedQueue;
  }
  
  private static String a(int paramInt1, int paramInt2, int paramInt3)
  {
    int i = 83 - paramInt2 * 2;
    Object localObject1 = new java/lang/String;
    paramInt2 = paramInt3 + 9;
    int k = paramInt1 + 4;
    Object localObject2 = d;
    byte[] arrayOfByte = new byte[paramInt2];
    int j = -1;
    paramInt3 = paramInt2 - 1;
    Object localObject4;
    Object localObject3;
    if (localObject2 == null)
    {
      localObject4 = localObject2;
      paramInt2 = paramInt3;
      localObject2 = localObject1;
      paramInt1 = j;
      localObject3 = localObject1;
      localObject1 = localObject4;
      j = k;
      k = paramInt3;
    }
    else
    {
      paramInt2 = k;
      paramInt1 = i;
      localObject3 = localObject1;
    }
    for (;;)
    {
      int m = j + 1;
      arrayOfByte[m] = ((byte)paramInt1);
      if (m == paramInt3)
      {
        ((String)localObject1).<init>(arrayOfByte, 0);
        return localObject3;
      }
      i = localObject2[paramInt2];
      localObject4 = localObject2;
      localObject2 = localObject1;
      k = paramInt1;
      j = paramInt2;
      localObject1 = localObject4;
      paramInt1 = m;
      paramInt2 = paramInt3;
      i = k + i + 1;
      k = j + 1;
      paramInt3 = paramInt2;
      localObject4 = localObject1;
      localObject1 = localObject2;
      localObject2 = localObject4;
      j = paramInt1;
      paramInt2 = k;
      paramInt1 = i;
    }
  }
  
  /* Error */
  public void run()
  {
    // Byte code:
    //   0: aconst_null
    //   1: astore 5
    //   3: aconst_null
    //   4: astore_3
    //   5: invokestatic 94	java/nio/channels/Selector:open	()Ljava/nio/channels/Selector;
    //   8: astore 4
    //   10: invokestatic 98	java/lang/Thread:interrupted	()Z
    //   13: ifne +100 -> 113
    //   16: aload_0
    //   17: getfield 80	com/datami/smi/e/k:c	Ljava/util/Queue;
    //   20: invokeinterface 104 1 0
    //   25: checkcast 106	com/datami/smi/e/d
    //   28: astore_3
    //   29: aload_3
    //   30: ifnull +11 -> 41
    //   33: aload_3
    //   34: aload 4
    //   36: invokeinterface 109 2 0
    //   41: aload 4
    //   43: ldc2_w 110
    //   46: invokevirtual 115	java/nio/channels/Selector:select	(J)I
    //   49: pop
    //   50: aload 4
    //   52: invokevirtual 119	java/nio/channels/Selector:selectedKeys	()Ljava/util/Set;
    //   55: astore_3
    //   56: aload_3
    //   57: invokeinterface 125 1 0
    //   62: astore 5
    //   64: aload 5
    //   66: invokeinterface 130 1 0
    //   71: ifeq +33 -> 104
    //   74: aload 5
    //   76: invokeinterface 133 1 0
    //   81: checkcast 135	java/nio/channels/SelectionKey
    //   84: astore 6
    //   86: aload 6
    //   88: invokevirtual 138	java/nio/channels/SelectionKey:attachment	()Ljava/lang/Object;
    //   91: checkcast 106	com/datami/smi/e/d
    //   94: aload 6
    //   96: invokeinterface 141 2 0
    //   101: goto -37 -> 64
    //   104: aload_3
    //   105: invokeinterface 144 1 0
    //   110: goto -100 -> 10
    //   113: aload 4
    //   115: ifnull +112 -> 227
    //   118: aload 4
    //   120: invokevirtual 147	java/nio/channels/Selector:close	()V
    //   123: return
    //   124: getstatic 69	com/datami/smi/e/k:d	[B
    //   127: bipush 61
    //   129: baload
    //   130: istore_2
    //   131: getstatic 69	com/datami/smi/e/k:d	[B
    //   134: bipush 84
    //   136: baload
    //   137: istore_1
    //   138: bipush 47
    //   140: iload_2
    //   141: iload_1
    //   142: invokestatic 75	com/datami/smi/e/k:a	(III)Ljava/lang/String;
    //   145: pop
    //   146: return
    //   147: astore_3
    //   148: goto +80 -> 228
    //   151: goto +14 -> 165
    //   154: astore 5
    //   156: aload_3
    //   157: astore 4
    //   159: aload 5
    //   161: astore_3
    //   162: goto +66 -> 228
    //   165: aload 4
    //   167: astore_3
    //   168: getstatic 69	com/datami/smi/e/k:d	[B
    //   171: bipush 44
    //   173: baload
    //   174: istore_1
    //   175: aload 4
    //   177: astore_3
    //   178: getstatic 69	com/datami/smi/e/k:d	[B
    //   181: bipush 32
    //   183: baload
    //   184: ineg
    //   185: istore_2
    //   186: aload 4
    //   188: astore_3
    //   189: iload_1
    //   190: iload_2
    //   191: iload_2
    //   192: bipush 32
    //   194: ior
    //   195: invokestatic 75	com/datami/smi/e/k:a	(III)Ljava/lang/String;
    //   198: pop
    //   199: aload 4
    //   201: ifnull +26 -> 227
    //   204: aload 4
    //   206: invokevirtual 147	java/nio/channels/Selector:close	()V
    //   209: return
    //   210: getstatic 69	com/datami/smi/e/k:d	[B
    //   213: bipush 61
    //   215: baload
    //   216: istore_2
    //   217: getstatic 69	com/datami/smi/e/k:d	[B
    //   220: bipush 84
    //   222: baload
    //   223: istore_1
    //   224: goto -86 -> 138
    //   227: return
    //   228: aload 4
    //   230: ifnull +29 -> 259
    //   233: aload 4
    //   235: invokevirtual 147	java/nio/channels/Selector:close	()V
    //   238: goto +21 -> 259
    //   241: bipush 47
    //   243: getstatic 69	com/datami/smi/e/k:d	[B
    //   246: bipush 61
    //   248: baload
    //   249: getstatic 69	com/datami/smi/e/k:d	[B
    //   252: bipush 84
    //   254: baload
    //   255: invokestatic 75	com/datami/smi/e/k:a	(III)Ljava/lang/String;
    //   258: pop
    //   259: aload_3
    //   260: athrow
    //   261: astore_3
    //   262: aload 5
    //   264: astore 4
    //   266: goto -101 -> 165
    //   269: astore_3
    //   270: goto -119 -> 151
    //   273: astore_3
    //   274: goto -150 -> 124
    //   277: astore_3
    //   278: goto -68 -> 210
    //   281: astore 4
    //   283: goto -42 -> 241
    // Local variable table:
    //   start	length	slot	name	signature
    //   0	286	0	this	k
    //   137	87	1	i	int
    //   130	87	2	j	int
    //   4	101	3	localObject1	Object
    //   147	10	3	localObject2	Object
    //   161	99	3	localObject3	Object
    //   261	1	3	localIOException1	java.io.IOException
    //   269	1	3	localIOException2	java.io.IOException
    //   273	1	3	localIOException3	java.io.IOException
    //   277	1	3	localIOException4	java.io.IOException
    //   8	257	4	localObject4	Object
    //   281	1	4	localIOException5	java.io.IOException
    //   1	74	5	localIterator	java.util.Iterator
    //   154	109	5	localObject5	Object
    //   84	11	6	localSelectionKey	java.nio.channels.SelectionKey
    // Exception table:
    //   from	to	target	type
    //   10	29	147	finally
    //   33	41	147	finally
    //   41	64	147	finally
    //   64	101	147	finally
    //   104	110	147	finally
    //   5	10	154	finally
    //   168	175	154	finally
    //   178	186	154	finally
    //   189	199	154	finally
    //   5	10	261	java/io/IOException
    //   10	29	269	java/io/IOException
    //   33	41	269	java/io/IOException
    //   41	64	269	java/io/IOException
    //   64	101	269	java/io/IOException
    //   104	110	269	java/io/IOException
    //   118	123	273	java/io/IOException
    //   204	209	277	java/io/IOException
    //   233	238	281	java/io/IOException
  }
}
