package com.mobile.ui.settings.fragment;

import android.os.Bundle;
import android.support.annotation.Nullable;
import android.view.LayoutInflater;
import android.view.View;
import android.view.ViewGroup;
import android.webkit.WebResourceResponse;
import android.widget.TextView;
import butterknife.BindView;
import com.mobile.ui.App;
import com.mobile.ui.R.layout;
import com.mobile.ui.R.string;
import com.mobile.ui.common.fragment.WebViewFragment;
import com.mobile.ui.common.view.SecureCoreWebView;
import kkkkkk.gguuuu;
import kkkkkk.hhqhhh;
import kkkkkk.hqhhhh;
import kkkkkk.iiccic.ciicic;
import kkkkkk.uyyyyy;

public class LegalInformationWebFragment
  extends WebViewFragment<hhqhhh, hqhhhh>
  implements hhqhhh
{
  private static final String ARG_CMS_PARAMS = "3C7N1:?J:*:(38";
  private static final String CSS_EXTENSION = "\033Qbc";
  private static final WebResourceResponse EMPTY_CSS_RESPONSE;
  public static int b04450445х0445ххххх = 2;
  public static int b0445хххххххх = 1;
  public static int bХ04250425042504250425042504250425 = 95;
  public static int bх0445х0445ххххх;
  private String mCurrentTitle;
  @BindView(2131493684)
  public TextView mTitle;
  @BindView(2131493685)
  public SecureCoreWebView mWebView;
  
  static
  {
    throw new Runtime("d2j fail translate: java.lang.IndexOutOfBoundsException: fromIndex < 0: -1\n\tat java.util.BitSet.nextSetBit(BitSet.java:712)\n\tat com.googlecode.dex2jar.ir.ts.array.FillArrayTransformer.makeSureAllElementAreAssigned(FillArrayTransformer.java:505)\n\tat com.googlecode.dex2jar.ir.ts.array.FillArrayTransformer.transformReportChanged(FillArrayTransformer.java:123)\n\tat com.googlecode.dex2jar.ir.ts.StatedTransformer.transform(StatedTransformer.java:10)\n\tat com.googlecode.d2j.dex.Dex2jar$2.optimize(Dex2jar.java:149)\n\tat com.googlecode.d2j.dex.Dex2Asm.convertCode(Dex2Asm.java:414)\n\tat com.googlecode.d2j.dex.ExDex2Asm.convertCode(ExDex2Asm.java:42)\n\tat com.googlecode.d2j.dex.Dex2jar$2.convertCode(Dex2jar.java:128)\n\tat com.googlecode.d2j.dex.Dex2Asm.convertMethod(Dex2Asm.java:509)\n\tat com.googlecode.d2j.dex.Dex2Asm.convertClass(Dex2Asm.java:406)\n\tat com.googlecode.d2j.dex.Dex2Asm.convertDex(Dex2Asm.java:422)\n\tat com.googlecode.d2j.dex.Dex2jar.doTranslate(Dex2jar.java:172)\n\tat com.googlecode.d2j.dex.Dex2jar.to(Dex2jar.java:272)\n\tat com.googlecode.dex2jar.tools.Dex2jarCmd.doCommandLine(Dex2jarCmd.java:108)\n\tat com.googlecode.dex2jar.tools.BaseCmd.doMain(BaseCmd.java:288)\n\tat com.googlecode.dex2jar.tools.Dex2jarCmd.main(Dex2jarCmd.java:32)\n");
  }
  
  public LegalInformationWebFragment() {}
  
  public static int b04450445ххххххх()
  {
    return 84;
  }
  
  public static int bх0445ххххххх()
  {
    return 2;
  }
  
  public static int bхх04450445ххххх()
  {
    return 1;
  }
  
  public static LegalInformationWebFragment newInstance(String paramString)
  {
    throw new Runtime("d2j fail translate: java.lang.IndexOutOfBoundsException: fromIndex < 0: -1\n\tat java.util.BitSet.nextSetBit(BitSet.java:712)\n\tat com.googlecode.dex2jar.ir.ts.array.FillArrayTransformer.makeSureAllElementAreAssigned(FillArrayTransformer.java:505)\n\tat com.googlecode.dex2jar.ir.ts.array.FillArrayTransformer.transformReportChanged(FillArrayTransformer.java:123)\n\tat com.googlecode.dex2jar.ir.ts.StatedTransformer.transform(StatedTransformer.java:10)\n\tat com.googlecode.d2j.dex.Dex2jar$2.optimize(Dex2jar.java:149)\n\tat com.googlecode.d2j.dex.Dex2Asm.convertCode(Dex2Asm.java:414)\n\tat com.googlecode.d2j.dex.ExDex2Asm.convertCode(ExDex2Asm.java:42)\n\tat com.googlecode.d2j.dex.Dex2jar$2.convertCode(Dex2jar.java:128)\n\tat com.googlecode.d2j.dex.Dex2Asm.convertMethod(Dex2Asm.java:509)\n\tat com.googlecode.d2j.dex.Dex2Asm.convertClass(Dex2Asm.java:406)\n\tat com.googlecode.d2j.dex.Dex2Asm.convertDex(Dex2Asm.java:422)\n\tat com.googlecode.d2j.dex.Dex2jar.doTranslate(Dex2jar.java:172)\n\tat com.googlecode.d2j.dex.Dex2jar.to(Dex2jar.java:272)\n\tat com.googlecode.dex2jar.tools.Dex2jarCmd.doCommandLine(Dex2jarCmd.java:108)\n\tat com.googlecode.dex2jar.tools.BaseCmd.doMain(BaseCmd.java:288)\n\tat com.googlecode.dex2jar.tools.Dex2jarCmd.main(Dex2jarCmd.java:32)\n");
  }
  
  public void onCreate(@Nullable Bundle paramBundle)
  {
    try
    {
      super.onCreate(paramBundle);
      paramBundle = App.get().getAppComponent();
      int i = b04450445ххххххх();
      switch (i * (b0445хххххххх + i) % b04450445х0445ххххх)
      {
      }
      for (;;)
      {
        bХ04250425042504250425042504250425 = b04450445ххххххх();
      }
    }
    catch (Exception paramBundle)
    {
      try
      {
        bх0445х0445ххххх = b04450445ххххххх();
        i = b04450445ххххххх();
        switch (i * (b0445хххххххх + i) % b04450445х0445ххххх)
        {
        default: 
          bХ04250425042504250425042504250425 = 88;
          bх0445х0445ххххх = 23;
        }
        paramBundle.bИ0418И04180418ИИИИ0418(this);
        switch (1)
        {
        case 0: 
        default: 
          for (;;)
          {
            switch (1)
            {
            }
          }
        }
        return;
      }
      catch (Exception paramBundle)
      {
        throw paramBundle;
      }
      paramBundle = paramBundle;
      throw paramBundle;
    }
  }
  
  @Nullable
  public View onCreateView(LayoutInflater paramLayoutInflater, @Nullable ViewGroup paramViewGroup, @Nullable Bundle paramBundle)
  {
    if ((bХ04250425042504250425042504250425 + bхх04450445ххххх()) * bХ04250425042504250425042504250425 % b04450445х0445ххххх != bх0445х0445ххххх)
    {
      bХ04250425042504250425042504250425 = b04450445ххххххх();
      bх0445х0445ххххх = b04450445ххххххх();
    }
    try
    {
      int i = R.layout.fragment_legal_information_web;
      int j = bХ04250425042504250425042504250425;
      switch (j * (b0445хххххххх + j) % b04450445х0445ххххх)
      {
      default: 
        bХ04250425042504250425042504250425 = b04450445ххххххх();
        bх0445х0445ххххх = b04450445ххххххх();
      }
      paramLayoutInflater = paramLayoutInflater.inflate(i, paramViewGroup, false);
      return paramLayoutInflater;
    }
    catch (Exception paramLayoutInflater)
    {
      throw paramLayoutInflater;
    }
  }
  
  /* Error */
  public void onStart()
  {
    // Byte code:
    //   0: getstatic 79	com/mobile/ui/settings/fragment/LegalInformationWebFragment:bХ04250425042504250425042504250425	I
    //   3: getstatic 75	com/mobile/ui/settings/fragment/LegalInformationWebFragment:b0445хххххххх	I
    //   6: iadd
    //   7: getstatic 79	com/mobile/ui/settings/fragment/LegalInformationWebFragment:bХ04250425042504250425042504250425	I
    //   10: imul
    //   11: getstatic 77	com/mobile/ui/settings/fragment/LegalInformationWebFragment:b04450445х0445ххххх	I
    //   14: irem
    //   15: getstatic 81	com/mobile/ui/settings/fragment/LegalInformationWebFragment:bх0445х0445ххххх	I
    //   18: if_icmpeq +109 -> 127
    //   21: iconst_1
    //   22: tableswitch	default:+22->44, 0:+-1->21, 1:+49->71
    //   44: iconst_1
    //   45: tableswitch	default:+23->68, 0:+-24->21, 1:+26->71
    //   68: goto -24 -> 44
    //   71: invokestatic 73	com/mobile/ui/settings/fragment/LegalInformationWebFragment:b04450445ххххххх	()I
    //   74: putstatic 79	com/mobile/ui/settings/fragment/LegalInformationWebFragment:bХ04250425042504250425042504250425	I
    //   77: getstatic 79	com/mobile/ui/settings/fragment/LegalInformationWebFragment:bХ04250425042504250425042504250425	I
    //   80: istore_1
    //   81: iload_1
    //   82: getstatic 75	com/mobile/ui/settings/fragment/LegalInformationWebFragment:b0445хххххххх	I
    //   85: iload_1
    //   86: iadd
    //   87: imul
    //   88: getstatic 77	com/mobile/ui/settings/fragment/LegalInformationWebFragment:b04450445х0445ххххх	I
    //   91: irem
    //   92: tableswitch	default:+20->112, 0:+30->122
    //   112: bipush 50
    //   114: putstatic 79	com/mobile/ui/settings/fragment/LegalInformationWebFragment:bХ04250425042504250425042504250425	I
    //   117: bipush 72
    //   119: putstatic 81	com/mobile/ui/settings/fragment/LegalInformationWebFragment:bх0445х0445ххххх	I
    //   122: bipush 19
    //   124: putstatic 81	com/mobile/ui/settings/fragment/LegalInformationWebFragment:bх0445х0445ххххх	I
    //   127: aload_0
    //   128: invokespecial 107	com/mobile/ui/common/fragment/WebViewFragment:onStart	()V
    //   131: aload_0
    //   132: getfield 109	com/mobile/ui/settings/fragment/LegalInformationWebFragment:mTitle	Landroid/widget/TextView;
    //   135: aload_0
    //   136: getfield 111	com/mobile/ui/settings/fragment/LegalInformationWebFragment:mCurrentTitle	Ljava/lang/String;
    //   139: invokevirtual 117	android/widget/TextView:setText	(Ljava/lang/CharSequence;)V
    //   142: return
    //   143: astore_2
    //   144: aload_2
    //   145: athrow
    //   146: astore_2
    //   147: aload_2
    //   148: athrow
    // Local variable table:
    //   start	length	slot	name	signature
    //   0	149	0	this	LegalInformationWebFragment
    //   80	8	1	i	int
    //   143	2	2	localException1	Exception
    //   146	2	2	localException2	Exception
    // Exception table:
    //   from	to	target	type
    //   131	142	143	java/lang/Exception
    //   127	131	146	java/lang/Exception
  }
  
  public void onViewCreated(View paramView, @Nullable Bundle paramBundle)
  {
    int i = bХ04250425042504250425042504250425;
    switch (i * (b0445хххххххх + i) % b04450445х0445ххххх)
    {
    default: 
      bХ04250425042504250425042504250425 = 44;
      bх0445х0445ххххх = b04450445ххххххх();
    }
    super.onViewCreated(paramView, paramBundle);
    this.mWebView.setWebViewLifecycle(getWebViewLifecycle());
    switch (1)
    {
    case 0: 
    default: 
      for (;;)
      {
        switch (0)
        {
        }
      }
    }
    paramView = this.mWebView;
    paramBundle = iiccic.ciicic.bВ04120412В041204120412ВВВ();
    LegalInformationWebFragment.1 local1 = new LegalInformationWebFragment.1(this);
    i = bХ04250425042504250425042504250425;
    switch (i * (bхх04450445ххххх() + i) % b04450445х0445ххххх)
    {
    default: 
      bХ04250425042504250425042504250425 = b04450445ххххххх();
      bх0445х0445ххххх = b04450445ххххххх();
    }
    paramView.setSecureCoreRequestFilter(paramBundle.b0412ВВВ041204120412ВВВ(local1, EMPTY_CSS_RESPONSE).bВ0412ВВ041204120412ВВВ());
    this.mWebView.loadCmsUrl(getArguments().getString(gguuuu.bк043Aккк043Aкк043A043A("GYOhMX_l^PbR_f", '6', 'O', '\003')), new String[0]);
  }
  
  public void trackScreenView()
  {
    String str = getArguments().getString(gguuuu.bккккк043Aкк043A043A("t\005x\020r{\001\f{k{ity", 'n', '\002'));
    if (getString(R.string.cms_mg_legal).equals(str))
    {
      switch (1)
      {
      case 0: 
      default: 
        for (;;)
        {
          switch (1)
          {
          }
        }
      }
      this.mCurrentTitle = getString(R.string.legal_information_legal_and_privacy_title);
      ((hqhhhh)this.mPresenter).b04480448ш0448шшшшш0448();
    }
    while (!getString(R.string.cms_mg_cookies).equals(str))
    {
      do
      {
        return;
        if ((bХ04250425042504250425042504250425 + b0445хххххххх) * bХ04250425042504250425042504250425 % b04450445х0445ххххх != bх0445х0445ххххх)
        {
          bХ04250425042504250425042504250425 = 54;
          bх0445х0445ххххх = 54;
        }
        this.mCurrentTitle = getString(R.string.legal_information_cookie_use_and_permissions_title);
        ((hqhhhh)this.mPresenter).bш0448ш0448шшшшш0448();
      } while ((bХ04250425042504250425042504250425 + b0445хххххххх) * bХ04250425042504250425042504250425 % b04450445х0445ххххх == bх0445х0445ххххх);
      bХ04250425042504250425042504250425 = b04450445ххххххх();
      bх0445х0445ххххх = 99;
      return;
    }
    switch (0)
    {
    }
    for (;;)
    {
      switch (0)
      {
      }
    }
  }
}
