package com.mobile.ui.settings.fragment;

import android.content.Context;
import android.os.Bundle;
import android.support.annotation.Nullable;
import android.view.LayoutInflater;
import android.view.View;
import android.view.ViewGroup;
import android.widget.ListView;
import butterknife.BindView;
import com.mobile.ui.App;
import com.mobile.ui.R.layout;
import com.mobile.ui.R.string;
import com.mobile.ui.common.fragment.BaseRequestFragment;
import kkkkkk.gguuuu;
import kkkkkk.hhqhhh;
import kkkkkk.hqhhhh;
import kkkkkk.ooooio;
import kkkkkk.rffrff;
import kkkkkk.uyyyyy;

public class LegalInformationListFragment
  extends BaseRequestFragment<hhqhhh, hqhhhh>
  implements hhqhhh
{
  public static int b0425042504250425ХХ042504250425 = 1;
  public static int b0425Х04250425ХХ042504250425 = 2;
  public static int bХ042504250425ХХ042504250425 = 0;
  public static int bХХХХ0425Х042504250425 = 2;
  @BindView(2131493682)
  public ListView mLegalInformationOptionsList;
  private rffrff mListener;
  
  public LegalInformationListFragment() {}
  
  public static int b0425ХХХ0425Х042504250425()
  {
    return 16;
  }
  
  public static int bХ0425ХХ0425Х042504250425()
  {
    return 1;
  }
  
  public static LegalInformationListFragment newInstance()
  {
    try
    {
      int i = b0425Х04250425ХХ042504250425;
      int j = bХ0425ХХ0425Х042504250425();
      int k = b0425Х04250425ХХ042504250425;
      int m = bХХХХ0425Х042504250425;
      int n = bХ042504250425ХХ042504250425;
      if ((i + j) * k % m != n)
      {
        if ((b0425Х04250425ХХ042504250425 + b0425042504250425ХХ042504250425) * b0425Х04250425ХХ042504250425 % bХХХХ0425Х042504250425 != bХ042504250425ХХ042504250425)
        {
          b0425Х04250425ХХ042504250425 = 50;
          bХ042504250425ХХ042504250425 = b0425ХХХ0425Х042504250425();
        }
        b0425Х04250425ХХ042504250425 = b0425ХХХ0425Х042504250425();
        bХ042504250425ХХ042504250425 = b0425ХХХ0425Х042504250425();
      }
      LegalInformationListFragment localLegalInformationListFragment = new LegalInformationListFragment();
      switch (1)
      {
      case 0: 
      default: 
        for (;;)
        {
          switch (1)
          {
          }
        }
      }
      return localLegalInformationListFragment;
    }
    catch (Exception localException)
    {
      throw localException;
    }
  }
  
  @Nullable
  public String getAccessibilityScreenTitle()
  {
    return getString(R.string.accessibility_legal_information_page_header);
  }
  
  public void onAttach(Context paramContext)
  {
    super.onAttach(paramContext);
    try
    {
      this.mListener = ((rffrff)paramContext);
      return;
    }
    catch (ClassCastException paramContext)
    {
      for (;;) {}
    }
    ooooio.bаа043004300430а0430ааа(paramContext);
    paramContext = new ClassCastException(getActivity().toString() + gguuuu.bк043Aккк043Aкк043A043A("e2966`),.)!(\037',V", 'í', 'K', '\002') + rffrff.class.getSimpleName());
    if ((b0425Х04250425ХХ042504250425 + b0425042504250425ХХ042504250425) * b0425Х04250425ХХ042504250425 % bХХХХ0425Х042504250425 != bХ042504250425ХХ042504250425)
    {
      b0425Х04250425ХХ042504250425 = 60;
      bХ042504250425ХХ042504250425 = 47;
    }
    if ((b0425ХХХ0425Х042504250425() + b0425042504250425ХХ042504250425) * b0425ХХХ0425Х042504250425() % bХХХХ0425Х042504250425 != bХ042504250425ХХ042504250425)
    {
      b0425Х04250425ХХ042504250425 = b0425ХХХ0425Х042504250425();
      bХ042504250425ХХ042504250425 = b0425ХХХ0425Х042504250425();
    }
    throw paramContext;
    for (;;)
    {
      switch (0)
      {
      case 0: 
      default: 
        break;
      case 1: 
        switch (0)
        {
        }
        break;
      }
    }
  }
  
  public void onCreate(@Nullable Bundle paramBundle)
  {
    if ((b0425ХХХ0425Х042504250425() + b0425042504250425ХХ042504250425) * b0425ХХХ0425Х042504250425() % bХХХХ0425Х042504250425 != bХ042504250425ХХ042504250425)
    {
      b0425Х04250425ХХ042504250425 = b0425ХХХ0425Х042504250425();
      bХ042504250425ХХ042504250425 = b0425ХХХ0425Х042504250425();
    }
    super.onCreate(paramBundle);
    paramBundle = App.get();
    switch (1)
    {
    case 0: 
    default: 
      for (;;)
      {
        switch (0)
        {
        }
      }
    }
    paramBundle.getAppComponent().bИИИ04180418ИИИИ0418(this);
  }
  
  @Nullable
  public View onCreateView(LayoutInflater paramLayoutInflater, @Nullable ViewGroup paramViewGroup, @Nullable Bundle paramBundle)
  {
    int i = R.layout.fragment_legal_information_list;
    if ((b0425Х04250425ХХ042504250425 + bХ0425ХХ0425Х042504250425()) * b0425Х04250425ХХ042504250425 % bХХХХ0425Х042504250425 != bХ042504250425ХХ042504250425)
    {
      b0425Х04250425ХХ042504250425 = b0425ХХХ0425Х042504250425();
      bХ042504250425ХХ042504250425 = 61;
      if ((b0425ХХХ0425Х042504250425() + b0425042504250425ХХ042504250425) * b0425ХХХ0425Х042504250425() % bХХХХ0425Х042504250425 != bХ042504250425ХХ042504250425)
      {
        b0425Х04250425ХХ042504250425 = b0425ХХХ0425Х042504250425();
        bХ042504250425ХХ042504250425 = 41;
      }
    }
    return paramLayoutInflater.inflate(i, paramViewGroup, false);
  }
  
  /* Error */
  public void onViewCreated(View paramView, @Nullable Bundle paramBundle)
  {
    // Byte code:
    //   0: getstatic 33	com/mobile/ui/settings/fragment/LegalInformationListFragment:b0425Х04250425ХХ042504250425	I
    //   3: getstatic 35	com/mobile/ui/settings/fragment/LegalInformationListFragment:b0425042504250425ХХ042504250425	I
    //   6: iadd
    //   7: getstatic 33	com/mobile/ui/settings/fragment/LegalInformationListFragment:b0425Х04250425ХХ042504250425	I
    //   10: imul
    //   11: getstatic 37	com/mobile/ui/settings/fragment/LegalInformationListFragment:bХХХХ0425Х042504250425	I
    //   14: irem
    //   15: getstatic 39	com/mobile/ui/settings/fragment/LegalInformationListFragment:bХ042504250425ХХ042504250425	I
    //   18: if_icmpeq +13 -> 31
    //   21: bipush 88
    //   23: putstatic 33	com/mobile/ui/settings/fragment/LegalInformationListFragment:b0425Х04250425ХХ042504250425	I
    //   26: bipush 52
    //   28: putstatic 39	com/mobile/ui/settings/fragment/LegalInformationListFragment:bХ042504250425ХХ042504250425	I
    //   31: aload_0
    //   32: aload_1
    //   33: aload_2
    //   34: invokespecial 149	com/mobile/ui/common/fragment/BaseRequestFragment:onViewCreated	(Landroid/view/View;Landroid/os/Bundle;)V
    //   37: new 151	kkkkkk/frrfff
    //   40: dup
    //   41: aload_0
    //   42: invokevirtual 85	com/mobile/ui/settings/fragment/LegalInformationListFragment:getActivity	()Landroid/support/v4/app/FragmentActivity;
    //   45: invokespecial 153	kkkkkk/frrfff:<init>	(Landroid/content/Context;)V
    //   48: astore_1
    //   49: aload_0
    //   50: getfield 155	com/mobile/ui/settings/fragment/LegalInformationListFragment:mLegalInformationOptionsList	Landroid/widget/ListView;
    //   53: astore_2
    //   54: aload_2
    //   55: aload_1
    //   56: invokevirtual 161	android/widget/ListView:setAdapter	(Landroid/widget/ListAdapter;)V
    //   59: getstatic 33	com/mobile/ui/settings/fragment/LegalInformationListFragment:b0425Х04250425ХХ042504250425	I
    //   62: getstatic 35	com/mobile/ui/settings/fragment/LegalInformationListFragment:b0425042504250425ХХ042504250425	I
    //   65: iadd
    //   66: getstatic 33	com/mobile/ui/settings/fragment/LegalInformationListFragment:b0425Х04250425ХХ042504250425	I
    //   69: imul
    //   70: getstatic 37	com/mobile/ui/settings/fragment/LegalInformationListFragment:bХХХХ0425Х042504250425	I
    //   73: irem
    //   74: getstatic 39	com/mobile/ui/settings/fragment/LegalInformationListFragment:bХ042504250425ХХ042504250425	I
    //   77: if_icmpeq +17 -> 94
    //   80: invokestatic 43	com/mobile/ui/settings/fragment/LegalInformationListFragment:b0425ХХХ0425Х042504250425	()I
    //   83: istore_3
    //   84: iload_3
    //   85: putstatic 33	com/mobile/ui/settings/fragment/LegalInformationListFragment:b0425Х04250425ХХ042504250425	I
    //   88: invokestatic 43	com/mobile/ui/settings/fragment/LegalInformationListFragment:b0425ХХХ0425Х042504250425	()I
    //   91: putstatic 39	com/mobile/ui/settings/fragment/LegalInformationListFragment:bХ042504250425ХХ042504250425	I
    //   94: aload_0
    //   95: getfield 155	com/mobile/ui/settings/fragment/LegalInformationListFragment:mLegalInformationOptionsList	Landroid/widget/ListView;
    //   98: new 163	com/mobile/ui/settings/fragment/LegalInformationListFragment$1
    //   101: dup
    //   102: aload_0
    //   103: invokespecial 165	com/mobile/ui/settings/fragment/LegalInformationListFragment$1:<init>	(Lcom/mobile/ui/settings/fragment/LegalInformationListFragment;)V
    //   106: invokevirtual 169	android/widget/ListView:setOnItemClickListener	(Landroid/widget/AdapterView$OnItemClickListener;)V
    //   109: return
    //   110: astore_1
    //   111: aload_1
    //   112: athrow
    //   113: astore_1
    //   114: aload_1
    //   115: athrow
    // Local variable table:
    //   start	length	slot	name	signature
    //   0	116	0	this	LegalInformationListFragment
    //   0	116	1	paramView	View
    //   0	116	2	paramBundle	Bundle
    //   83	2	3	i	int
    // Exception table:
    //   from	to	target	type
    //   31	49	110	java/lang/Exception
    //   54	84	110	java/lang/Exception
    //   94	109	110	java/lang/Exception
    //   49	54	113	java/lang/Exception
    //   84	94	113	java/lang/Exception
  }
  
  /* Error */
  public void trackScreenView()
  {
    // Byte code:
    //   0: aload_0
    //   1: getfield 174	com/mobile/ui/settings/fragment/LegalInformationListFragment:mPresenter	Lkkkkkk/gggggr;
    //   4: astore_1
    //   5: getstatic 33	com/mobile/ui/settings/fragment/LegalInformationListFragment:b0425Х04250425ХХ042504250425	I
    //   8: invokestatic 50	com/mobile/ui/settings/fragment/LegalInformationListFragment:bХ0425ХХ0425Х042504250425	()I
    //   11: iadd
    //   12: getstatic 33	com/mobile/ui/settings/fragment/LegalInformationListFragment:b0425Х04250425ХХ042504250425	I
    //   15: imul
    //   16: getstatic 37	com/mobile/ui/settings/fragment/LegalInformationListFragment:bХХХХ0425Х042504250425	I
    //   19: irem
    //   20: getstatic 39	com/mobile/ui/settings/fragment/LegalInformationListFragment:bХ042504250425ХХ042504250425	I
    //   23: if_icmpeq +45 -> 68
    //   26: getstatic 33	com/mobile/ui/settings/fragment/LegalInformationListFragment:b0425Х04250425ХХ042504250425	I
    //   29: getstatic 35	com/mobile/ui/settings/fragment/LegalInformationListFragment:b0425042504250425ХХ042504250425	I
    //   32: iadd
    //   33: getstatic 33	com/mobile/ui/settings/fragment/LegalInformationListFragment:b0425Х04250425ХХ042504250425	I
    //   36: imul
    //   37: getstatic 37	com/mobile/ui/settings/fragment/LegalInformationListFragment:bХХХХ0425Х042504250425	I
    //   40: irem
    //   41: getstatic 39	com/mobile/ui/settings/fragment/LegalInformationListFragment:bХ042504250425ХХ042504250425	I
    //   44: if_icmpeq +14 -> 58
    //   47: bipush 72
    //   49: putstatic 33	com/mobile/ui/settings/fragment/LegalInformationListFragment:b0425Х04250425ХХ042504250425	I
    //   52: invokestatic 43	com/mobile/ui/settings/fragment/LegalInformationListFragment:b0425ХХХ0425Х042504250425	()I
    //   55: putstatic 39	com/mobile/ui/settings/fragment/LegalInformationListFragment:bХ042504250425ХХ042504250425	I
    //   58: bipush 65
    //   60: putstatic 33	com/mobile/ui/settings/fragment/LegalInformationListFragment:b0425Х04250425ХХ042504250425	I
    //   63: bipush 50
    //   65: putstatic 39	com/mobile/ui/settings/fragment/LegalInformationListFragment:bХ042504250425ХХ042504250425	I
    //   68: aload_1
    //   69: checkcast 176	kkkkkk/hqhhhh
    //   72: astore_1
    //   73: aload_1
    //   74: invokevirtual 179	kkkkkk/hqhhhh:bшш04480448шшшшш0448	()V
    //   77: return
    //   78: astore_1
    //   79: aload_1
    //   80: athrow
    //   81: astore_1
    //   82: aload_1
    //   83: athrow
    // Local variable table:
    //   start	length	slot	name	signature
    //   0	84	0	this	LegalInformationListFragment
    //   4	70	1	localObject	Object
    //   78	2	1	localException1	Exception
    //   81	2	1	localException2	Exception
    // Exception table:
    //   from	to	target	type
    //   0	5	78	java/lang/Exception
    //   73	77	78	java/lang/Exception
    //   68	73	81	java/lang/Exception
  }
}
