package com.mobile.ui.common.view;

import android.support.v4.app.Fragment;
import com.mobile.ui.R.id;
import com.mobile.ui.R.string;
import com.mobile.ui.common.fragment.AlertDialogFragment;
import com.mobile.ui.common.fragment.BaseDialogFragment.wwbwbb;

public class WinBackDialogFragment
  extends AlertDialogFragment
{
  public static final int BACK_REQUEST = 12345;
  public static final int GDPR_LINK_REQUEST = 12344;
  public static final int GLOBAL_MENU_NAVIGATION_REQUEST = 60001;
  public static int b043004300430ааа04300430 = 2;
  public static int b0430а0430ааа04300430 = 0;
  public static int bа04300430ааа04300430 = 1;
  public static int bаа0430ааа04300430 = 67;
  
  public WinBackDialogFragment() {}
  
  public static int b0430аа0430аа04300430()
  {
    return 2;
  }
  
  public static int bа0430а0430аа04300430()
  {
    return 1;
  }
  
  public static int bааа0430аа04300430()
  {
    return 82;
  }
  
  public static WinBackDialogFragment newInstance()
  {
    switch (1)
    {
    case 0: 
    default: 
      for (;;)
      {
        switch (1)
        {
        }
      }
    }
    if ((bаа0430ааа04300430 + bа04300430ааа04300430) * bаа0430ааа04300430 % b043004300430ааа04300430 != b0430а0430ааа04300430)
    {
      int i = bаа0430ааа04300430;
      switch (i * (bа04300430ааа04300430 + i) % b043004300430ааа04300430)
      {
      default: 
        bаа0430ааа04300430 = 19;
        b0430а0430ааа04300430 = bааа0430аа04300430();
      }
      bаа0430ааа04300430 = 3;
      b0430а0430ааа04300430 = bааа0430аа04300430();
    }
    WinBackDialogFragment localWinBackDialogFragment = new WinBackDialogFragment();
    switch (1)
    {
    case 0: 
    default: 
      for (;;)
      {
        switch (0)
        {
        }
      }
    }
    return localWinBackDialogFragment;
  }
  
  public int getDialogId()
  {
    try
    {
      int i = R.id.winBackDialogModal;
      int j = bаа0430ааа04300430;
      int k = bа04300430ааа04300430;
      int m = bаа0430ааа04300430;
      switch (m * (bа04300430ааа04300430 + m) % b0430аа0430аа04300430())
      {
      default: 
        bаа0430ааа04300430 = bааа0430аа04300430();
        b0430а0430ааа04300430 = 46;
      }
      switch (j * (k + j) % b043004300430ааа04300430)
      {
      default: 
        bаа0430ааа04300430 = 57;
        b0430а0430ааа04300430 = bааа0430аа04300430();
      }
      return i;
    }
    catch (Exception localException)
    {
      throw localException;
    }
  }
  
  public String getDialogTitle()
  {
    try
    {
      String str = getString(R.string.dialog_winback_title_text);
      return str;
    }
    catch (Exception localException)
    {
      throw localException;
    }
  }
  
  /* Error */
  public CharSequence getMessage()
  {
    // Byte code:
    //   0: getstatic 67	com/mobile/ui/R$string:dialog_winback_message	I
    //   3: istore_1
    //   4: getstatic 32	com/mobile/ui/common/view/WinBackDialogFragment:bаа0430ааа04300430	I
    //   7: istore_2
    //   8: getstatic 34	com/mobile/ui/common/view/WinBackDialogFragment:bа04300430ааа04300430	I
    //   11: istore_3
    //   12: iload_2
    //   13: iload_3
    //   14: iload_2
    //   15: iadd
    //   16: imul
    //   17: getstatic 36	com/mobile/ui/common/view/WinBackDialogFragment:b043004300430ааа04300430	I
    //   20: irem
    //   21: tableswitch	default:+105->126, 0:+75->96
    //   40: bipush 63
    //   42: putstatic 32	com/mobile/ui/common/view/WinBackDialogFragment:bаа0430ааа04300430	I
    //   45: bipush 92
    //   47: putstatic 38	com/mobile/ui/common/view/WinBackDialogFragment:b0430а0430ааа04300430	I
    //   50: getstatic 32	com/mobile/ui/common/view/WinBackDialogFragment:bаа0430ааа04300430	I
    //   53: istore_2
    //   54: iload_2
    //   55: invokestatic 69	com/mobile/ui/common/view/WinBackDialogFragment:bа0430а0430аа04300430	()I
    //   58: iload_2
    //   59: iadd
    //   60: imul
    //   61: getstatic 36	com/mobile/ui/common/view/WinBackDialogFragment:b043004300430ааа04300430	I
    //   64: irem
    //   65: tableswitch	default:+19->84, 0:+31->96
    //   84: invokestatic 40	com/mobile/ui/common/view/WinBackDialogFragment:bааа0430аа04300430	()I
    //   87: putstatic 32	com/mobile/ui/common/view/WinBackDialogFragment:bаа0430ааа04300430	I
    //   90: invokestatic 40	com/mobile/ui/common/view/WinBackDialogFragment:bааа0430аа04300430	()I
    //   93: putstatic 38	com/mobile/ui/common/view/WinBackDialogFragment:b0430а0430ааа04300430	I
    //   96: aload_0
    //   97: iload_1
    //   98: invokevirtual 62	com/mobile/ui/common/view/WinBackDialogFragment:getString	(I)Ljava/lang/String;
    //   101: astore 4
    //   103: aload 4
    //   105: areturn
    //   106: astore 4
    //   108: aload 4
    //   110: athrow
    //   111: astore 4
    //   113: aload 4
    //   115: athrow
    //   116: astore 4
    //   118: aload 4
    //   120: athrow
    //   121: astore 4
    //   123: aload 4
    //   125: athrow
    //   126: goto -86 -> 40
    // Local variable table:
    //   start	length	slot	name	signature
    //   0	129	0	this	WinBackDialogFragment
    //   3	95	1	i	int
    //   7	54	2	j	int
    //   11	5	3	k	int
    //   101	3	4	str	String
    //   106	3	4	localException1	Exception
    //   111	3	4	localException2	Exception
    //   116	3	4	localException3	Exception
    //   121	3	4	localException4	Exception
    // Exception table:
    //   from	to	target	type
    //   96	103	106	java/lang/Exception
    //   4	8	111	java/lang/Exception
    //   12	40	111	java/lang/Exception
    //   40	45	111	java/lang/Exception
    //   108	111	111	java/lang/Exception
    //   0	4	116	java/lang/Exception
    //   8	12	121	java/lang/Exception
    //   45	50	121	java/lang/Exception
    //   118	121	121	java/lang/Exception
  }
  
  public BaseDialogFragment.wwbwbb getNegativeAction()
  {
    if ((bаа0430ааа04300430 + bа04300430ааа04300430) * bаа0430ааа04300430 % b043004300430ааа04300430 != b0430а0430ааа04300430)
    {
      if ((bаа0430ааа04300430 + bа04300430ааа04300430) * bаа0430ааа04300430 % b043004300430ааа04300430 != b0430а0430ааа04300430)
      {
        bаа0430ааа04300430 = bааа0430аа04300430();
        b0430а0430ааа04300430 = 67;
      }
      bаа0430ааа04300430 = 81;
      b0430а0430ааа04300430 = 81;
    }
    BaseDialogFragment.wwbwbb localWwbwbb = new BaseDialogFragment.wwbwbb(getString(R.string.dialog_winback_cancel_button_text), new WinBackDialogFragment.2(this));
    switch (0)
    {
    case 1: 
    default: 
      for (;;)
      {
        switch (1)
        {
        }
      }
    }
    return localWwbwbb;
  }
  
  public BaseDialogFragment.wwbwbb getPositiveAction()
  {
    try
    {
      throw new NullPointerException();
    }
    catch (Exception localException1)
    {
      try
      {
        bаа0430ааа04300430 = 45;
        BaseDialogFragment.wwbwbb localWwbwbb = new BaseDialogFragment.wwbwbb(getString(R.string.dialog_winback_ok_button_text), new WinBackDialogFragment.1(this));
        return localWwbwbb;
      }
      catch (Exception localException2)
      {
        throw localException2;
      }
    }
  }
  
  public void show(Fragment paramFragment)
  {
    try
    {
      show(paramFragment, 12345);
    }
    catch (Exception paramFragment)
    {
      try
      {
        int i;
        int j;
        int k;
        bаа0430ааа04300430 = bааа0430аа04300430();
        b0430а0430ааа04300430 = 81;
        return;
      }
      catch (Exception paramFragment)
      {
        throw paramFragment;
      }
      paramFragment = paramFragment;
      throw paramFragment;
    }
    i = bааа0430аа04300430();
    j = bа04300430ааа04300430;
    k = b043004300430ааа04300430;
    switch (i * (j + i) % k)
    {
    default: 
      i = bаа0430ааа04300430;
      switch (i * (bа04300430ааа04300430 + i) % b043004300430ааа04300430)
      {
      default: 
        bаа0430ааа04300430 = 37;
        b0430а0430ааа04300430 = bааа0430аа04300430();
      }
      break;
    }
    switch (0)
    {
    }
    for (;;)
    {
      switch (1)
      {
      }
    }
  }
  
  /* Error */
  public void show(Fragment paramFragment, int paramInt)
  {
    // Byte code:
    //   0: aload_0
    //   1: aload_1
    //   2: iload_2
    //   3: invokevirtual 102	com/mobile/ui/common/view/WinBackDialogFragment:setTargetFragment	(Landroid/support/v4/app/Fragment;I)V
    //   6: getstatic 32	com/mobile/ui/common/view/WinBackDialogFragment:bаа0430ааа04300430	I
    //   9: istore_2
    //   10: getstatic 34	com/mobile/ui/common/view/WinBackDialogFragment:bа04300430ааа04300430	I
    //   13: istore_3
    //   14: getstatic 32	com/mobile/ui/common/view/WinBackDialogFragment:bаа0430ааа04300430	I
    //   17: istore 4
    //   19: getstatic 36	com/mobile/ui/common/view/WinBackDialogFragment:b043004300430ааа04300430	I
    //   22: istore 5
    //   24: getstatic 38	com/mobile/ui/common/view/WinBackDialogFragment:b0430а0430ааа04300430	I
    //   27: istore 6
    //   29: iload_2
    //   30: iload_3
    //   31: iadd
    //   32: iload 4
    //   34: imul
    //   35: iload 5
    //   37: irem
    //   38: iload 6
    //   40: if_icmpeq +13 -> 53
    //   43: bipush 96
    //   45: putstatic 32	com/mobile/ui/common/view/WinBackDialogFragment:bаа0430ааа04300430	I
    //   48: bipush 43
    //   50: putstatic 38	com/mobile/ui/common/view/WinBackDialogFragment:b0430а0430ааа04300430	I
    //   53: aload_1
    //   54: invokevirtual 108	android/support/v4/app/Fragment:getActivity	()Landroid/support/v4/app/FragmentActivity;
    //   57: invokevirtual 114	android/support/v4/app/FragmentActivity:getSupportFragmentManager	()Landroid/support/v4/app/FragmentManager;
    //   60: astore_1
    //   61: getstatic 32	com/mobile/ui/common/view/WinBackDialogFragment:bаа0430ааа04300430	I
    //   64: istore_2
    //   65: iload_2
    //   66: invokestatic 69	com/mobile/ui/common/view/WinBackDialogFragment:bа0430а0430аа04300430	()I
    //   69: iload_2
    //   70: iadd
    //   71: imul
    //   72: getstatic 36	com/mobile/ui/common/view/WinBackDialogFragment:b043004300430ааа04300430	I
    //   75: irem
    //   76: tableswitch	default:+20->96, 0:+31->107
    //   96: invokestatic 40	com/mobile/ui/common/view/WinBackDialogFragment:bааа0430аа04300430	()I
    //   99: putstatic 32	com/mobile/ui/common/view/WinBackDialogFragment:bаа0430ааа04300430	I
    //   102: bipush 24
    //   104: putstatic 38	com/mobile/ui/common/view/WinBackDialogFragment:b0430а0430ааа04300430	I
    //   107: aload_0
    //   108: aload_1
    //   109: ldc 2
    //   111: invokevirtual 119	java/lang/Class:getName	()Ljava/lang/String;
    //   114: invokevirtual 122	com/mobile/ui/common/view/WinBackDialogFragment:show	(Landroid/support/v4/app/FragmentManager;Ljava/lang/String;)V
    //   117: return
    //   118: astore_1
    //   119: aload_1
    //   120: athrow
    //   121: astore_1
    //   122: aload_1
    //   123: athrow
    // Local variable table:
    //   start	length	slot	name	signature
    //   0	124	0	this	WinBackDialogFragment
    //   0	124	1	paramFragment	Fragment
    //   0	124	2	paramInt	int
    //   13	19	3	i	int
    //   17	18	4	j	int
    //   22	16	5	k	int
    //   27	14	6	m	int
    // Exception table:
    //   from	to	target	type
    //   0	29	118	java/lang/Exception
    //   53	61	118	java/lang/Exception
    //   107	117	118	java/lang/Exception
    //   43	53	121	java/lang/Exception
  }
}
