package com.db.pwcc.dbmobile.mobile_payment.tools;

import android.content.BroadcastReceiver;
import android.content.Context;
import android.content.IntentFilter;
import android.support.annotation.NonNull;
import java.lang.reflect.InvocationTargetException;
import java.lang.reflect.Method;
import uuuuuu.ppphhp;
import xxxxxx.uxxxxx;

public class NfcChangeReceiver
  extends BroadcastReceiver
{
  public static int b00760076007600760076vv0076 = 2;
  public static int b0076v007600760076vv0076 = 94;
  public static int b0076vvvv0076v0076 = 1;
  public static int bvvvvv0076v0076;
  private pooopp callback;
  
  public NfcChangeReceiver(@NonNull pooopp paramPooopp)
  {
    this.callback = paramPooopp;
  }
  
  public static int bv0076007600760076vv0076()
  {
    return 1;
  }
  
  public static int bv0076vvv0076v0076()
  {
    return 78;
  }
  
  /* Error */
  public void onReceive(Context paramContext, android.content.Intent paramIntent)
  {
    // Byte code:
    //   0: ldc 36
    //   2: ldc 38
    //   4: bipush 51
    //   6: iconst_2
    //   7: invokestatic 44	xxxxxx/uxxxxx:bb00620062bb0062b0062b0062	(Ljava/lang/String;CC)Ljava/lang/String;
    //   10: iconst_1
    //   11: anewarray 46	java/lang/Class
    //   14: dup
    //   15: iconst_0
    //   16: ldc 48
    //   18: aastore
    //   19: invokevirtual 52	java/lang/Class:getMethod	(Ljava/lang/String;[Ljava/lang/Class;)Ljava/lang/reflect/Method;
    //   22: astore 4
    //   24: aload 4
    //   26: aconst_null
    //   27: iconst_1
    //   28: anewarray 54	java/lang/Object
    //   31: dup
    //   32: iconst_0
    //   33: aload_1
    //   34: aastore
    //   35: invokevirtual 60	java/lang/reflect/Method:invoke	(Ljava/lang/Object;[Ljava/lang/Object;)Ljava/lang/Object;
    //   38: pop
    //   39: ldc 62
    //   41: ldc 64
    //   43: bipush 121
    //   45: iconst_3
    //   46: invokestatic 44	xxxxxx/uxxxxx:bb00620062bb0062b0062b0062	(Ljava/lang/String;CC)Ljava/lang/String;
    //   49: iconst_1
    //   50: anewarray 46	java/lang/Class
    //   53: dup
    //   54: iconst_0
    //   55: ldc 48
    //   57: aastore
    //   58: invokevirtual 52	java/lang/Class:getMethod	(Ljava/lang/String;[Ljava/lang/Class;)Ljava/lang/reflect/Method;
    //   61: astore 4
    //   63: aload 4
    //   65: aconst_null
    //   66: iconst_1
    //   67: anewarray 54	java/lang/Object
    //   70: dup
    //   71: iconst_0
    //   72: aload_1
    //   73: aastore
    //   74: invokevirtual 60	java/lang/reflect/Method:invoke	(Ljava/lang/Object;[Ljava/lang/Object;)Ljava/lang/Object;
    //   77: pop
    //   78: aload_1
    //   79: invokestatic 70	uuuuuu/uppupu:b0072r0072r00720072rr0072	(Landroid/content/Context;)V
    //   82: ldc 72
    //   84: ldc 74
    //   86: bipush 114
    //   88: iconst_5
    //   89: invokestatic 44	xxxxxx/uxxxxx:bb00620062bb0062b0062b0062	(Ljava/lang/String;CC)Ljava/lang/String;
    //   92: iconst_4
    //   93: anewarray 46	java/lang/Class
    //   96: dup
    //   97: iconst_0
    //   98: ldc 76
    //   100: aastore
    //   101: dup
    //   102: iconst_1
    //   103: getstatic 82	java/lang/Character:TYPE	Ljava/lang/Class;
    //   106: aastore
    //   107: dup
    //   108: iconst_2
    //   109: getstatic 82	java/lang/Character:TYPE	Ljava/lang/Class;
    //   112: aastore
    //   113: dup
    //   114: iconst_3
    //   115: getstatic 82	java/lang/Character:TYPE	Ljava/lang/Class;
    //   118: aastore
    //   119: invokevirtual 52	java/lang/Class:getMethod	(Ljava/lang/String;[Ljava/lang/Class;)Ljava/lang/reflect/Method;
    //   122: astore_1
    //   123: aload_1
    //   124: aconst_null
    //   125: iconst_4
    //   126: anewarray 54	java/lang/Object
    //   129: dup
    //   130: iconst_0
    //   131: ldc 84
    //   133: aastore
    //   134: dup
    //   135: iconst_1
    //   136: sipush 176
    //   139: invokestatic 88	java/lang/Character:valueOf	(C)Ljava/lang/Character;
    //   142: aastore
    //   143: dup
    //   144: iconst_2
    //   145: sipush 162
    //   148: invokestatic 88	java/lang/Character:valueOf	(C)Ljava/lang/Character;
    //   151: aastore
    //   152: dup
    //   153: iconst_3
    //   154: iconst_1
    //   155: invokestatic 88	java/lang/Character:valueOf	(C)Ljava/lang/Character;
    //   158: aastore
    //   159: invokevirtual 60	java/lang/reflect/Method:invoke	(Ljava/lang/Object;[Ljava/lang/Object;)Ljava/lang/Object;
    //   162: astore_1
    //   163: aload_1
    //   164: checkcast 76	java/lang/String
    //   167: astore_1
    //   168: getstatic 90	com/db/pwcc/dbmobile/mobile_payment/tools/NfcChangeReceiver:b0076v007600760076vv0076	I
    //   171: getstatic 92	com/db/pwcc/dbmobile/mobile_payment/tools/NfcChangeReceiver:b0076vvvv0076v0076	I
    //   174: iadd
    //   175: getstatic 90	com/db/pwcc/dbmobile/mobile_payment/tools/NfcChangeReceiver:b0076v007600760076vv0076	I
    //   178: imul
    //   179: getstatic 94	com/db/pwcc/dbmobile/mobile_payment/tools/NfcChangeReceiver:b00760076007600760076vv0076	I
    //   182: irem
    //   183: getstatic 96	com/db/pwcc/dbmobile/mobile_payment/tools/NfcChangeReceiver:bvvvvv0076v0076	I
    //   186: if_icmpeq +14 -> 200
    //   189: bipush 82
    //   191: putstatic 90	com/db/pwcc/dbmobile/mobile_payment/tools/NfcChangeReceiver:b0076v007600760076vv0076	I
    //   194: invokestatic 98	com/db/pwcc/dbmobile/mobile_payment/tools/NfcChangeReceiver:bv0076vvv0076v0076	()I
    //   197: putstatic 96	com/db/pwcc/dbmobile/mobile_payment/tools/NfcChangeReceiver:bvvvvv0076v0076	I
    //   200: aload_1
    //   201: aload_2
    //   202: invokevirtual 104	android/content/Intent:getAction	()Ljava/lang/String;
    //   205: invokevirtual 108	java/lang/String:equals	(Ljava/lang/Object;)Z
    //   208: ifeq +164 -> 372
    //   211: getstatic 90	com/db/pwcc/dbmobile/mobile_payment/tools/NfcChangeReceiver:b0076v007600760076vv0076	I
    //   214: istore_3
    //   215: iload_3
    //   216: invokestatic 110	com/db/pwcc/dbmobile/mobile_payment/tools/NfcChangeReceiver:bv0076007600760076vv0076	()I
    //   219: iload_3
    //   220: iadd
    //   221: imul
    //   222: getstatic 94	com/db/pwcc/dbmobile/mobile_payment/tools/NfcChangeReceiver:b00760076007600760076vv0076	I
    //   225: irem
    //   226: tableswitch	default:+18->244, 0:+28->254
    //   244: bipush 29
    //   246: putstatic 90	com/db/pwcc/dbmobile/mobile_payment/tools/NfcChangeReceiver:b0076v007600760076vv0076	I
    //   249: bipush 84
    //   251: putstatic 94	com/db/pwcc/dbmobile/mobile_payment/tools/NfcChangeReceiver:b00760076007600760076vv0076	I
    //   254: ldc 72
    //   256: ldc 74
    //   258: bipush 118
    //   260: bipush 30
    //   262: iconst_1
    //   263: invokestatic 114	xxxxxx/uxxxxx:bbbb0062b0062b0062b0062	(Ljava/lang/String;CCC)Ljava/lang/String;
    //   266: iconst_4
    //   267: anewarray 46	java/lang/Class
    //   270: dup
    //   271: iconst_0
    //   272: ldc 76
    //   274: aastore
    //   275: dup
    //   276: iconst_1
    //   277: getstatic 82	java/lang/Character:TYPE	Ljava/lang/Class;
    //   280: aastore
    //   281: dup
    //   282: iconst_2
    //   283: getstatic 82	java/lang/Character:TYPE	Ljava/lang/Class;
    //   286: aastore
    //   287: dup
    //   288: iconst_3
    //   289: getstatic 82	java/lang/Character:TYPE	Ljava/lang/Class;
    //   292: aastore
    //   293: invokevirtual 52	java/lang/Class:getMethod	(Ljava/lang/String;[Ljava/lang/Class;)Ljava/lang/reflect/Method;
    //   296: astore_1
    //   297: aload_1
    //   298: aconst_null
    //   299: iconst_4
    //   300: anewarray 54	java/lang/Object
    //   303: dup
    //   304: iconst_0
    //   305: ldc 116
    //   307: aastore
    //   308: dup
    //   309: iconst_1
    //   310: sipush 226
    //   313: invokestatic 88	java/lang/Character:valueOf	(C)Ljava/lang/Character;
    //   316: aastore
    //   317: dup
    //   318: iconst_2
    //   319: sipush 148
    //   322: invokestatic 88	java/lang/Character:valueOf	(C)Ljava/lang/Character;
    //   325: aastore
    //   326: dup
    //   327: iconst_3
    //   328: iconst_2
    //   329: invokestatic 88	java/lang/Character:valueOf	(C)Ljava/lang/Character;
    //   332: aastore
    //   333: invokevirtual 60	java/lang/reflect/Method:invoke	(Ljava/lang/Object;[Ljava/lang/Object;)Ljava/lang/Object;
    //   336: astore_1
    //   337: aload_2
    //   338: aload_1
    //   339: checkcast 76	java/lang/String
    //   342: iconst_1
    //   343: invokevirtual 120	android/content/Intent:getIntExtra	(Ljava/lang/String;I)I
    //   346: tableswitch	default:+26->372, 1:+39->385, 2:+26->372, 3:+50->396
    //   372: return
    //   373: astore_1
    //   374: aload_1
    //   375: invokevirtual 124	java/lang/reflect/InvocationTargetException:getCause	()Ljava/lang/Throwable;
    //   378: athrow
    //   379: astore_1
    //   380: aload_1
    //   381: invokevirtual 124	java/lang/reflect/InvocationTargetException:getCause	()Ljava/lang/Throwable;
    //   384: athrow
    //   385: aload_0
    //   386: getfield 25	com/db/pwcc/dbmobile/mobile_payment/tools/NfcChangeReceiver:callback	Lcom/db/pwcc/dbmobile/mobile_payment/tools/NfcChangeReceiver$pooopp;
    //   389: iconst_1
    //   390: invokeinterface 128 2 0
    //   395: return
    //   396: aload_0
    //   397: getfield 25	com/db/pwcc/dbmobile/mobile_payment/tools/NfcChangeReceiver:callback	Lcom/db/pwcc/dbmobile/mobile_payment/tools/NfcChangeReceiver$pooopp;
    //   400: iconst_3
    //   401: invokeinterface 128 2 0
    //   406: return
    //   407: astore_1
    //   408: aload_1
    //   409: invokevirtual 124	java/lang/reflect/InvocationTargetException:getCause	()Ljava/lang/Throwable;
    //   412: athrow
    //   413: astore_1
    //   414: aload_1
    //   415: invokevirtual 124	java/lang/reflect/InvocationTargetException:getCause	()Ljava/lang/Throwable;
    //   418: athrow
    // Local variable table:
    //   start	length	slot	name	signature
    //   0	419	0	this	NfcChangeReceiver
    //   0	419	1	paramContext	Context
    //   0	419	2	paramIntent	android.content.Intent
    //   214	8	3	i	int
    //   22	42	4	localMethod	Method
    // Exception table:
    //   from	to	target	type
    //   24	39	373	java/lang/reflect/InvocationTargetException
    //   63	78	379	java/lang/reflect/InvocationTargetException
    //   297	337	407	java/lang/reflect/InvocationTargetException
    //   123	163	413	java/lang/reflect/InvocationTargetException
  }
  
  public void registerReceiver(@NonNull Context paramContext)
  {
    if ((bv0076vvv0076v0076() + b0076vvvv0076v0076) * bv0076vvv0076v0076() % b00760076007600760076vv0076 != bvvvvv0076v0076)
    {
      b0076v007600760076vv0076 = 2;
      bvvvvv0076v0076 = 58;
      int i = b0076v007600760076vv0076;
      switch (i * (b0076vvvv0076v0076 + i) % b00760076007600760076vv0076)
      {
      default: 
        b0076v007600760076vv0076 = 68;
        bvvvvv0076v0076 = bv0076vvv0076v0076();
      }
    }
    Object localObject = ppphhp.class.getMethod(uxxxxx.bbbb0062b0062b0062b0062("J^]\\[\023\022\030\027\017\016\024\023R\n\t\017\016\006\005\013\nI", '', 'y', '\000'), new Class[] { String.class, Character.TYPE, Character.TYPE });
    try
    {
      localObject = ((Method)localObject).invoke(null, new Object[] { "\004\022\t\030\026\021\rW\031\022\020[\020\023%\033\"\"bvzx\t\016\016\034\021\023\001\025\007\"\007\r\007\025\017\016\016", Character.valueOf(''), Character.valueOf('\001') });
      paramContext.registerReceiver(this, new IntentFilter((String)localObject));
      return;
    }
    catch (InvocationTargetException paramContext)
    {
      throw paramContext.getCause();
    }
  }
  
  public void unregisterReceiver(@NonNull Context paramContext)
  {
    paramContext.unregisterReceiver(this);
    if ((bv0076vvv0076v0076() + b0076vvvv0076v0076) * bv0076vvv0076v0076() % b00760076007600760076vv0076 != bvvvvv0076v0076)
    {
      b0076v007600760076vv0076 = 66;
      if ((b0076v007600760076vv0076 + b0076vvvv0076v0076) * b0076v007600760076vv0076 % b00760076007600760076vv0076 != bvvvvv0076v0076)
      {
        b0076v007600760076vv0076 = bv0076vvv0076v0076();
        bvvvvv0076v0076 = bv0076vvv0076v0076();
      }
      bvvvvv0076v0076 = 51;
    }
  }
  
  public static abstract interface pooopp
  {
    public abstract void bu00750075uuu0075uuu(int paramInt);
  }
}
