package com.mobile.ui.logoff.activity;

import android.content.Context;
import android.content.Intent;
import android.os.Bundle;
import android.support.v4.app.FragmentManager;
import android.support.v4.app.FragmentTransaction;
import com.mobile.ui.R.id;
import com.mobile.ui.R.layout;
import com.mobile.ui.common.activity.BaseActivity;
import com.mobile.ui.common.activity.BaseActivity.rrrggg;
import com.mobile.ui.logoff.fragment.LoggedOffFragment;
import java.util.Map;
import kkkkkk.eieiee;
import kkkkkk.gguuuu;

public class LoggedOffActivity
  extends BaseActivity
{
  private static final String KEY_ERROR_SCREEN = "D?T[BPQOSaVGWKLV";
  private static final String KEY_OCIS_ID = "\017\b\033 \017\002\007\020\033\004}";
  public static int b043Dннн043Dн043Dн = 1;
  public static int bн043Dнн043Dн043Dн = 2;
  public static int bнн043Dн043Dн043Dн = 0;
  public static int bнннн043Dн043Dн = 14;
  
  static
  {
    String str = KEY_ERROR_SCREEN;
    int i = bнннн043Dн043Dн;
    switch (i * (b043Dннн043Dн043Dн + i) % bн043Dнн043Dн043Dн)
    {
    default: 
      bнннн043Dн043Dн = b043D043Dнн043Dн043Dн();
      bнн043Dн043Dн043Dн = b043D043Dнн043Dн043Dн();
    }
    KEY_ERROR_SCREEN = gguuuu.bккккк043Aкк043A043A(str, '÷', '\000');
    str = KEY_OCIS_ID;
    switch (1)
    {
    case 0: 
    default: 
      for (;;)
      {
        switch (0)
        {
        }
      }
    }
    KEY_OCIS_ID = gguuuu.bккккк043Aкк043A043A(str, '\036', '\003');
  }
  
  public LoggedOffActivity() {}
  
  public static int b043D043Dнн043Dн043Dн()
  {
    return 65;
  }
  
  public static int b043Dн043Dн043Dн043Dн()
  {
    return 1;
  }
  
  public static int bн043D043Dн043Dн043Dн()
  {
    return 2;
  }
  
  public static Intent getIntent(Context paramContext, eieiee paramEieiee, String paramString)
  {
    throw new Runtime("d2j fail translate: java.lang.IndexOutOfBoundsException: fromIndex < 0: -1\n\tat java.util.BitSet.nextSetBit(BitSet.java:712)\n\tat com.googlecode.dex2jar.ir.ts.array.FillArrayTransformer.makeSureAllElementAreAssigned(FillArrayTransformer.java:505)\n\tat com.googlecode.dex2jar.ir.ts.array.FillArrayTransformer.transformReportChanged(FillArrayTransformer.java:123)\n\tat com.googlecode.dex2jar.ir.ts.StatedTransformer.transform(StatedTransformer.java:10)\n\tat com.googlecode.d2j.dex.Dex2jar$2.optimize(Dex2jar.java:149)\n\tat com.googlecode.d2j.dex.Dex2Asm.convertCode(Dex2Asm.java:414)\n\tat com.googlecode.d2j.dex.ExDex2Asm.convertCode(ExDex2Asm.java:42)\n\tat com.googlecode.d2j.dex.Dex2jar$2.convertCode(Dex2jar.java:128)\n\tat com.googlecode.d2j.dex.Dex2Asm.convertMethod(Dex2Asm.java:509)\n\tat com.googlecode.d2j.dex.Dex2Asm.convertClass(Dex2Asm.java:406)\n\tat com.googlecode.d2j.dex.Dex2Asm.convertDex(Dex2Asm.java:422)\n\tat com.googlecode.d2j.dex.Dex2jar.doTranslate(Dex2jar.java:172)\n\tat com.googlecode.d2j.dex.Dex2jar.to(Dex2jar.java:272)\n\tat com.googlecode.dex2jar.tools.Dex2jarCmd.doCommandLine(Dex2jarCmd.java:108)\n\tat com.googlecode.dex2jar.tools.BaseCmd.doMain(BaseCmd.java:288)\n\tat com.googlecode.dex2jar.tools.Dex2jarCmd.main(Dex2jarCmd.java:32)\n");
  }
  
  private void showLoggedOffScreen(String paramString)
  {
    FragmentTransaction localFragmentTransaction = getSupportFragmentManager().beginTransaction();
    int i = R.id.logOffContainer;
    paramString = LoggedOffFragment.newInstance(paramString);
    switch (0)
    {
    case 1: 
    default: 
      for (;;)
      {
        switch (0)
        {
        }
      }
    }
    if ((bнннн043Dн043Dн + b043Dннн043Dн043Dн) * bнннн043Dн043Dн % bн043Dнн043Dн043Dн != bнн043Dн043Dн043Dн)
    {
      bнннн043Dн043Dн = b043D043Dнн043Dн043Dн();
      bнн043Dн043Dн043Dн = 24;
    }
    localFragmentTransaction.replace(i, paramString).commit();
  }
  
  public Map<String, Bundle> getDeepLinkMap(Context paramContext)
  {
    int i = bнннн043Dн043Dн;
    switch (i * (b043Dннн043Dн043Dн + i) % bн043D043Dн043Dн043Dн())
    {
    default: 
      bнннн043Dн043Dн = b043D043Dнн043Dн043Dн();
      bнн043Dн043Dн043Dн = b043D043Dнн043Dн043Dн();
    }
    try
    {
      paramContext = NOT_LINKABLE_MAP;
      i = b043D043Dнн043Dн043Dн();
      switch (i * (b043Dн043Dн043Dн043Dн() + i) % bн043Dнн043Dн043Dн)
      {
      default: 
        switch (0)
        {
        case 1: 
        default: 
          for (;;)
          {
            switch (0)
            {
            }
          }
        }
        bнннн043Dн043Dн = b043D043Dнн043Dн043Dн();
        bнн043Dн043Dн043Dн = b043D043Dнн043Dн043Dн();
      }
      return paramContext;
    }
    catch (Exception paramContext)
    {
      throw paramContext;
    }
  }
  
  protected int getLayoutId()
  {
    try
    {
      i = R.layout.activity_logged_off;
    }
    catch (Exception localException)
    {
      int i;
      int j;
      throw localException;
    }
    if ((bнннн043Dн043Dн + b043Dннн043Dн043Dн) * bнннн043Dн043Dн % bн043Dнн043Dн043Dн != bнн043Dн043Dн043Dн)
    {
      bнннн043Dн043Dн = 20;
      bнн043Dн043Dн043Dн = 96;
      j = bнннн043Dн043Dн;
      switch (j * (b043Dн043Dн043Dн043Dн() + j) % bн043Dнн043Dн043Dн)
      {
      default: 
        bнннн043Dн043Dн = b043D043Dнн043Dн043Dн();
        bнн043Dн043Dн043Dн = b043D043Dнн043Dн043Dн();
      }
    }
    return i;
    switch (0)
    {
    }
    for (;;)
    {
      switch (1)
      {
      }
    }
  }
  
  public eieiee getLogOffScreen()
  {
    int i = getIntent().getIntExtra(gguuuu.bккккк043Aкк043A043A("LG\\cJXYW[i^O_ST^", '¿', '\004'), -1);
    Object localObject = eieiee.values();
    if ((bнннн043Dн043Dн + b043Dннн043Dн043Dн) * bнннн043Dн043Dн % bн043Dнн043Dн043Dн != bнн043Dн043Dн043Dн)
    {
      bнннн043Dн043Dн = 54;
      bнн043Dн043Dн043Dн = 54;
    }
    localObject = localObject[i];
    i = bнннн043Dн043Dн;
    switch (i * (b043Dн043Dн043Dн043Dн() + i) % bн043Dнн043Dн043Dн)
    {
    default: 
      bнннн043Dн043Dн = b043D043Dнн043Dн043Dн();
      bнн043Dн043Dн043Dн = 94;
    }
    return localObject;
  }
  
  protected BaseActivity.rrrggg getMenuType()
  {
    try
    {
      BaseActivity.rrrggg localRrrggg = BaseActivity.rrrggg.PRE_AUTH;
      int i = bнннн043Dн043Dн;
      int j = b043Dннн043Dн043Dн;
      int k = bн043Dнн043Dн043Dн;
      int m = bнннн043Dн043Dн;
      switch (m * (b043Dннн043Dн043Dн + m) % bн043Dнн043Dн043Dн)
      {
      default: 
        bнннн043Dн043Dн = 31;
        bнн043Dн043Dн043Dн = b043D043Dнн043Dн043Dн();
      }
      switch (0)
      {
      case 1: 
      default: 
        for (;;)
        {
          switch (1)
          {
          }
        }
      }
      switch (i * (j + i) % k)
      {
      default: 
        bнннн043Dн043Dн = 75;
        bнн043Dн043Dн043Dн = 57;
      }
      return localRrrggg;
    }
    catch (Exception localException)
    {
      throw localException;
    }
  }
  
  /* Error */
  public void onCreate(Bundle paramBundle)
  {
    // Byte code:
    //   0: aload_0
    //   1: invokevirtual 145	com/mobile/ui/logoff/activity/LoggedOffActivity:getApplicationContext	()Landroid/content/Context;
    //   4: astore_3
    //   5: getstatic 26	com/mobile/ui/logoff/activity/LoggedOffActivity:bнннн043Dн043Dн	I
    //   8: getstatic 28	com/mobile/ui/logoff/activity/LoggedOffActivity:b043Dннн043Dн043Dн	I
    //   11: iadd
    //   12: getstatic 26	com/mobile/ui/logoff/activity/LoggedOffActivity:bнннн043Dн043Dн	I
    //   15: imul
    //   16: invokestatic 98	com/mobile/ui/logoff/activity/LoggedOffActivity:bн043D043Dн043Dн043Dн	()I
    //   19: irem
    //   20: getstatic 36	com/mobile/ui/logoff/activity/LoggedOffActivity:bнн043Dн043Dн043Dн	I
    //   23: if_icmpeq +14 -> 37
    //   26: invokestatic 34	com/mobile/ui/logoff/activity/LoggedOffActivity:b043D043Dнн043Dн043Dн	()I
    //   29: putstatic 26	com/mobile/ui/logoff/activity/LoggedOffActivity:bнннн043Dн043Dн	I
    //   32: bipush 32
    //   34: putstatic 36	com/mobile/ui/logoff/activity/LoggedOffActivity:bнн043Dн043Dн043Dн	I
    //   37: aload_3
    //   38: invokestatic 151	kkkkkk/nkkkkk:bЗЗ0417З0417З0417041704170417	(Landroid/content/Context;)V
    //   41: aload_0
    //   42: invokevirtual 145	com/mobile/ui/logoff/activity/LoggedOffActivity:getApplicationContext	()Landroid/content/Context;
    //   45: invokestatic 156	kkkkkk/nnnkkk:bхх0445ххххххх	(Landroid/content/Context;)V
    //   48: aload_0
    //   49: invokevirtual 145	com/mobile/ui/logoff/activity/LoggedOffActivity:getApplicationContext	()Landroid/content/Context;
    //   52: invokestatic 161	kkkkkk/nknnkk:bх0445ххх04450445ххх	(Landroid/content/Context;)V
    //   55: aload_0
    //   56: aload_1
    //   57: invokespecial 163	com/mobile/ui/common/activity/BaseActivity:onCreate	(Landroid/os/Bundle;)V
    //   60: aload_1
    //   61: ifnonnull +76 -> 137
    //   64: aload_0
    //   65: invokevirtual 117	com/mobile/ui/logoff/activity/LoggedOffActivity:getIntent	()Landroid/content/Intent;
    //   68: invokevirtual 167	android/content/Intent:getExtras	()Landroid/os/Bundle;
    //   71: ldc -87
    //   73: bipush 35
    //   75: bipush 82
    //   77: iconst_2
    //   78: invokestatic 173	kkkkkk/gguuuu:bк043Aккк043Aкк043A043A	(Ljava/lang/String;CCC)Ljava/lang/String;
    //   81: invokevirtual 179	android/os/Bundle:getString	(Ljava/lang/String;)Ljava/lang/String;
    //   84: astore_1
    //   85: getstatic 26	com/mobile/ui/logoff/activity/LoggedOffActivity:bнннн043Dн043Dн	I
    //   88: istore_2
    //   89: iload_2
    //   90: getstatic 28	com/mobile/ui/logoff/activity/LoggedOffActivity:b043Dннн043Dн043Dн	I
    //   93: iload_2
    //   94: iadd
    //   95: imul
    //   96: invokestatic 98	com/mobile/ui/logoff/activity/LoggedOffActivity:bн043D043Dн043Dн043Dн	()I
    //   99: irem
    //   100: tableswitch	default:+20->120, 0:+32->132
    //   120: invokestatic 34	com/mobile/ui/logoff/activity/LoggedOffActivity:b043D043Dнн043Dн043Dн	()I
    //   123: putstatic 26	com/mobile/ui/logoff/activity/LoggedOffActivity:bнннн043Dн043Dн	I
    //   126: invokestatic 34	com/mobile/ui/logoff/activity/LoggedOffActivity:b043D043Dнн043Dн043Dн	()I
    //   129: putstatic 36	com/mobile/ui/logoff/activity/LoggedOffActivity:bнн043Dн043Dн043Dн	I
    //   132: aload_0
    //   133: aload_1
    //   134: invokespecial 181	com/mobile/ui/logoff/activity/LoggedOffActivity:showLoggedOffScreen	(Ljava/lang/String;)V
    //   137: return
    //   138: astore_1
    //   139: aload_1
    //   140: athrow
    //   141: astore_1
    //   142: aload_1
    //   143: athrow
    // Local variable table:
    //   start	length	slot	name	signature
    //   0	144	0	this	LoggedOffActivity
    //   0	144	1	paramBundle	Bundle
    //   88	8	2	i	int
    //   4	34	3	localContext	Context
    // Exception table:
    //   from	to	target	type
    //   0	5	138	java/lang/Exception
    //   48	60	138	java/lang/Exception
    //   64	85	138	java/lang/Exception
    //   37	48	141	java/lang/Exception
    //   132	137	141	java/lang/Exception
  }
  
  protected boolean shouldRestartAppIfSecureCoreNotInitialized()
  {
    int i = bнннн043Dн043Dн;
    switch (i * (b043Dннн043Dн043Dн + i) % bн043Dнн043Dн043Dн)
    {
    default: 
      bнннн043Dн043Dн = b043D043Dнн043Dн043Dн();
      bнн043Dн043Dн043Dн = 52;
      i = bнннн043Dн043Dн;
      switch (i * (b043Dн043Dн043Dн043Dн() + i) % bн043D043Dн043Dн043Dн())
      {
      default: 
        bнннн043Dн043Dн = 75;
        bнн043Dн043Dн043Dн = b043D043Dнн043Dн043Dн();
      }
      break;
    }
    return true;
  }
}
