package uuuuuu;

public class alllaa
  implements alllll
{
  public static int b006C006Cl006Cl006C006Cll = 16;
  public static int b006Cl006C006Cl006C006Cll = 1;
  public static int bl006C006C006Cl006C006Cll = 2;
  public static int bll006C006Cl006C006Cll;
  
  public alllaa() {}
  
  public static int b0069i0069ii0069iiii()
  {
    return 60;
  }
  
  /* Error */
  public void b00750075uuu00750075007500750075(@android.support.annotation.NonNull alllll.lallll paramLallll)
  {
    // Byte code:
    //   0: invokestatic 32	uuuuuu/yyhyhh:bp0070pp0070p0070007000700070	()Luuuuuu/yyhyhh;
    //   3: astore_2
    //   4: invokestatic 38	uuuuuu/yyyyyg:bpp0070ppp00700070pp	()Landroid/content/Context;
    //   7: astore_3
    //   8: ldc 40
    //   10: ldc 42
    //   12: bipush 58
    //   14: sipush 235
    //   17: iconst_3
    //   18: invokestatic 48	xxxxxx/uxxxxx:bbbb0062b0062b0062b0062	(Ljava/lang/String;CCC)Ljava/lang/String;
    //   21: iconst_4
    //   22: anewarray 50	java/lang/Class
    //   25: dup
    //   26: iconst_0
    //   27: ldc 52
    //   29: aastore
    //   30: dup
    //   31: iconst_1
    //   32: getstatic 58	java/lang/Character:TYPE	Ljava/lang/Class;
    //   35: aastore
    //   36: dup
    //   37: iconst_2
    //   38: getstatic 58	java/lang/Character:TYPE	Ljava/lang/Class;
    //   41: aastore
    //   42: dup
    //   43: iconst_3
    //   44: getstatic 58	java/lang/Character:TYPE	Ljava/lang/Class;
    //   47: aastore
    //   48: invokevirtual 62	java/lang/Class:getMethod	(Ljava/lang/String;[Ljava/lang/Class;)Ljava/lang/reflect/Method;
    //   51: astore 4
    //   53: aload 4
    //   55: aconst_null
    //   56: iconst_4
    //   57: anewarray 4	java/lang/Object
    //   60: dup
    //   61: iconst_0
    //   62: ldc 64
    //   64: aastore
    //   65: dup
    //   66: iconst_1
    //   67: bipush 12
    //   69: invokestatic 68	java/lang/Character:valueOf	(C)Ljava/lang/Character;
    //   72: aastore
    //   73: dup
    //   74: iconst_2
    //   75: sipush 251
    //   78: invokestatic 68	java/lang/Character:valueOf	(C)Ljava/lang/Character;
    //   81: aastore
    //   82: dup
    //   83: iconst_3
    //   84: iconst_3
    //   85: invokestatic 68	java/lang/Character:valueOf	(C)Ljava/lang/Character;
    //   88: aastore
    //   89: invokevirtual 74	java/lang/reflect/Method:invoke	(Ljava/lang/Object;[Ljava/lang/Object;)Ljava/lang/Object;
    //   92: astore 4
    //   94: aload_2
    //   95: aload_3
    //   96: aload 4
    //   98: checkcast 52	java/lang/String
    //   101: invokevirtual 78	uuuuuu/yyhyhh:bpp0070p0070p0070007000700070	(Landroid/content/Context;Ljava/lang/String;)Ljava/lang/String;
    //   104: astore_2
    //   105: getstatic 80	uuuuuu/alllaa:b006C006Cl006Cl006C006Cll	I
    //   108: getstatic 82	uuuuuu/alllaa:b006Cl006C006Cl006C006Cll	I
    //   111: iadd
    //   112: getstatic 80	uuuuuu/alllaa:b006C006Cl006Cl006C006Cll	I
    //   115: imul
    //   116: getstatic 84	uuuuuu/alllaa:bl006C006C006Cl006C006Cll	I
    //   119: irem
    //   120: getstatic 86	uuuuuu/alllaa:bll006C006Cl006C006Cll	I
    //   123: if_icmpeq +45 -> 168
    //   126: invokestatic 88	uuuuuu/alllaa:b0069i0069ii0069iiii	()I
    //   129: putstatic 80	uuuuuu/alllaa:b006C006Cl006Cl006C006Cll	I
    //   132: bipush 54
    //   134: putstatic 86	uuuuuu/alllaa:bll006C006Cl006C006Cll	I
    //   137: getstatic 80	uuuuuu/alllaa:b006C006Cl006Cl006C006Cll	I
    //   140: getstatic 82	uuuuuu/alllaa:b006Cl006C006Cl006C006Cll	I
    //   143: iadd
    //   144: getstatic 80	uuuuuu/alllaa:b006C006Cl006Cl006C006Cll	I
    //   147: imul
    //   148: getstatic 84	uuuuuu/alllaa:bl006C006C006Cl006C006Cll	I
    //   151: irem
    //   152: getstatic 86	uuuuuu/alllaa:bll006C006Cl006C006Cll	I
    //   155: if_icmpeq +13 -> 168
    //   158: bipush 47
    //   160: putstatic 80	uuuuuu/alllaa:b006C006Cl006Cl006C006Cll	I
    //   163: bipush 79
    //   165: putstatic 86	uuuuuu/alllaa:bll006C006Cl006C006Cll	I
    //   168: aload_2
    //   169: ifnull +26 -> 195
    //   172: aload_1
    //   173: new 90	com/google/gson/Gson
    //   176: dup
    //   177: invokespecial 91	com/google/gson/Gson:<init>	()V
    //   180: aload_2
    //   181: ldc 93
    //   183: invokevirtual 97	com/google/gson/Gson:fromJson	(Ljava/lang/String;Ljava/lang/Class;)Ljava/lang/Object;
    //   186: checkcast 93	[Lcom/db/pwcc/dbmobile/multi_bank_aggregator/model/EfiSuggestion;
    //   189: invokeinterface 103 2 0
    //   194: return
    //   195: ldc 40
    //   197: ldc 105
    //   199: bipush 61
    //   201: bipush 60
    //   203: iconst_2
    //   204: invokestatic 48	xxxxxx/uxxxxx:bbbb0062b0062b0062b0062	(Ljava/lang/String;CCC)Ljava/lang/String;
    //   207: iconst_4
    //   208: anewarray 50	java/lang/Class
    //   211: dup
    //   212: iconst_0
    //   213: ldc 52
    //   215: aastore
    //   216: dup
    //   217: iconst_1
    //   218: getstatic 58	java/lang/Character:TYPE	Ljava/lang/Class;
    //   221: aastore
    //   222: dup
    //   223: iconst_2
    //   224: getstatic 58	java/lang/Character:TYPE	Ljava/lang/Class;
    //   227: aastore
    //   228: dup
    //   229: iconst_3
    //   230: getstatic 58	java/lang/Character:TYPE	Ljava/lang/Class;
    //   233: aastore
    //   234: invokevirtual 62	java/lang/Class:getMethod	(Ljava/lang/String;[Ljava/lang/Class;)Ljava/lang/reflect/Method;
    //   237: astore_2
    //   238: aload_2
    //   239: aconst_null
    //   240: iconst_4
    //   241: anewarray 4	java/lang/Object
    //   244: dup
    //   245: iconst_0
    //   246: ldc 107
    //   248: aastore
    //   249: dup
    //   250: iconst_1
    //   251: bipush 24
    //   253: invokestatic 68	java/lang/Character:valueOf	(C)Ljava/lang/Character;
    //   256: aastore
    //   257: dup
    //   258: iconst_2
    //   259: bipush 73
    //   261: invokestatic 68	java/lang/Character:valueOf	(C)Ljava/lang/Character;
    //   264: aastore
    //   265: dup
    //   266: iconst_3
    //   267: iconst_2
    //   268: invokestatic 68	java/lang/Character:valueOf	(C)Ljava/lang/Character;
    //   271: aastore
    //   272: invokevirtual 74	java/lang/reflect/Method:invoke	(Ljava/lang/Object;[Ljava/lang/Object;)Ljava/lang/Object;
    //   275: astore_2
    //   276: aload_1
    //   277: new 109	com/db/pwcc/dbmobile/model/error/DbError
    //   280: dup
    //   281: aload_2
    //   282: checkcast 52	java/lang/String
    //   285: invokespecial 112	com/db/pwcc/dbmobile/model/error/DbError:<init>	(Ljava/lang/String;)V
    //   288: invokeinterface 116 2 0
    //   293: return
    //   294: astore_1
    //   295: aload_1
    //   296: invokevirtual 120	java/lang/reflect/InvocationTargetException:getCause	()Ljava/lang/Throwable;
    //   299: athrow
    //   300: astore_1
    //   301: aload_1
    //   302: invokevirtual 120	java/lang/reflect/InvocationTargetException:getCause	()Ljava/lang/Throwable;
    //   305: athrow
    // Local variable table:
    //   start	length	slot	name	signature
    //   0	306	0	this	alllaa
    //   0	306	1	paramLallll	alllll.lallll
    //   3	279	2	localObject1	Object
    //   7	89	3	localContext	android.content.Context
    //   51	46	4	localObject2	Object
    // Exception table:
    //   from	to	target	type
    //   238	276	294	java/lang/reflect/InvocationTargetException
    //   53	94	300	java/lang/reflect/InvocationTargetException
  }
}
