package uuuuuu;

import android.os.Bundle;
import com.db.pwcc.dbmobile.financial_overview.R.string;
import com.db.pwcc.dbmobile.foundation.data.manager.broadcasting.ModelUpdatedBroadcastReceiver;
import com.db.pwcc.dbmobile.model.error.DbError;
import com.db.pwcc.dbmobile.model.error.DbErrorCode;
import java.lang.reflect.InvocationTargetException;
import java.lang.reflect.Method;
import javax.inject.Inject;
import xxxxxx.uxxxxx;

public abstract class bbmmmm
  implements bbmbmm.mmbbmm
{
  private static final String b007700770077007700770077w00770077 = bbmmmm.class.getSimpleName();
  public static int b00770077wwww007700770077 = 83;
  public static int b0077w0077www007700770077 = 2;
  public static int bw00770077www007700770077 = 0;
  public static int bww0077www007700770077 = 1;
  private ModelUpdatedBroadcastReceiver b0077wwwww007700770077;
  public bbmbmm.bmbbmm bw0077wwww007700770077;
  @Inject
  public qpqqqq bwwwwww007700770077;
  
  /* Error */
  static
  {
    // Byte code:
    //   0: ldc 2
    //   2: invokevirtual 37	java/lang/Class:getSimpleName	()Ljava/lang/String;
    //   5: putstatic 39	uuuuuu/bbmmmm:b007700770077007700770077w00770077	Ljava/lang/String;
    //   8: getstatic 41	uuuuuu/bbmmmm:b00770077wwww007700770077	I
    //   11: istore_0
    //   12: getstatic 43	uuuuuu/bbmmmm:bww0077www007700770077	I
    //   15: istore_1
    //   16: ldc 2
    //   18: ldc 45
    //   20: sipush 243
    //   23: sipush 145
    //   26: iconst_0
    //   27: invokestatic 51	xxxxxx/uxxxxx:bbbb0062b0062b0062b0062	(Ljava/lang/String;CCC)Ljava/lang/String;
    //   30: iconst_0
    //   31: anewarray 33	java/lang/Class
    //   34: invokevirtual 55	java/lang/Class:getMethod	(Ljava/lang/String;[Ljava/lang/Class;)Ljava/lang/reflect/Method;
    //   37: astore 6
    //   39: aload 6
    //   41: aconst_null
    //   42: iconst_0
    //   43: anewarray 4	java/lang/Object
    //   46: invokevirtual 61	java/lang/reflect/Method:invoke	(Ljava/lang/Object;[Ljava/lang/Object;)Ljava/lang/Object;
    //   49: astore 6
    //   51: aload 6
    //   53: checkcast 63	java/lang/Integer
    //   56: invokevirtual 67	java/lang/Integer:intValue	()I
    //   59: istore_2
    //   60: ldc 2
    //   62: ldc 69
    //   64: bipush 35
    //   66: iconst_3
    //   67: invokestatic 73	xxxxxx/uxxxxx:bb00620062bb0062b0062b0062	(Ljava/lang/String;CC)Ljava/lang/String;
    //   70: iconst_0
    //   71: anewarray 33	java/lang/Class
    //   74: invokevirtual 55	java/lang/Class:getMethod	(Ljava/lang/String;[Ljava/lang/Class;)Ljava/lang/reflect/Method;
    //   77: astore 6
    //   79: aload 6
    //   81: aconst_null
    //   82: iconst_0
    //   83: anewarray 4	java/lang/Object
    //   86: invokevirtual 61	java/lang/reflect/Method:invoke	(Ljava/lang/Object;[Ljava/lang/Object;)Ljava/lang/Object;
    //   89: astore 6
    //   91: aload 6
    //   93: checkcast 63	java/lang/Integer
    //   96: invokevirtual 67	java/lang/Integer:intValue	()I
    //   99: istore_3
    //   100: ldc 2
    //   102: ldc 75
    //   104: bipush 41
    //   106: iconst_5
    //   107: invokestatic 73	xxxxxx/uxxxxx:bb00620062bb0062b0062b0062	(Ljava/lang/String;CC)Ljava/lang/String;
    //   110: iconst_0
    //   111: anewarray 33	java/lang/Class
    //   114: invokevirtual 55	java/lang/Class:getMethod	(Ljava/lang/String;[Ljava/lang/Class;)Ljava/lang/reflect/Method;
    //   117: astore 6
    //   119: aload 6
    //   121: aconst_null
    //   122: iconst_0
    //   123: anewarray 4	java/lang/Object
    //   126: invokevirtual 61	java/lang/reflect/Method:invoke	(Ljava/lang/Object;[Ljava/lang/Object;)Ljava/lang/Object;
    //   129: astore 6
    //   131: aload 6
    //   133: checkcast 63	java/lang/Integer
    //   136: invokevirtual 67	java/lang/Integer:intValue	()I
    //   139: istore 4
    //   141: getstatic 77	uuuuuu/bbmmmm:b0077w0077www007700770077	I
    //   144: istore 5
    //   146: ldc 2
    //   148: ldc 79
    //   150: sipush 142
    //   153: iconst_2
    //   154: invokestatic 73	xxxxxx/uxxxxx:bb00620062bb0062b0062b0062	(Ljava/lang/String;CC)Ljava/lang/String;
    //   157: iconst_0
    //   158: anewarray 33	java/lang/Class
    //   161: invokevirtual 55	java/lang/Class:getMethod	(Ljava/lang/String;[Ljava/lang/Class;)Ljava/lang/reflect/Method;
    //   164: astore 6
    //   166: aload 6
    //   168: aconst_null
    //   169: iconst_0
    //   170: anewarray 4	java/lang/Object
    //   173: invokevirtual 61	java/lang/reflect/Method:invoke	(Ljava/lang/Object;[Ljava/lang/Object;)Ljava/lang/Object;
    //   176: astore 6
    //   178: iload 4
    //   180: iload_2
    //   181: iload_3
    //   182: iadd
    //   183: imul
    //   184: iload 5
    //   186: irem
    //   187: aload 6
    //   189: checkcast 63	java/lang/Integer
    //   192: invokevirtual 67	java/lang/Integer:intValue	()I
    //   195: if_icmpeq +13 -> 208
    //   198: bipush 42
    //   200: putstatic 41	uuuuuu/bbmmmm:b00770077wwww007700770077	I
    //   203: bipush 20
    //   205: putstatic 81	uuuuuu/bbmmmm:bw00770077www007700770077	I
    //   208: iload_0
    //   209: iload_1
    //   210: iadd
    //   211: iload_0
    //   212: imul
    //   213: getstatic 77	uuuuuu/bbmmmm:b0077w0077www007700770077	I
    //   216: irem
    //   217: tableswitch	default:+19->236, 0:+244->461
    //   236: ldc 2
    //   238: ldc 83
    //   240: sipush 185
    //   243: iconst_4
    //   244: invokestatic 73	xxxxxx/uxxxxx:bb00620062bb0062b0062b0062	(Ljava/lang/String;CC)Ljava/lang/String;
    //   247: iconst_0
    //   248: anewarray 33	java/lang/Class
    //   251: invokevirtual 55	java/lang/Class:getMethod	(Ljava/lang/String;[Ljava/lang/Class;)Ljava/lang/reflect/Method;
    //   254: astore 6
    //   256: aload 6
    //   258: aconst_null
    //   259: iconst_0
    //   260: anewarray 4	java/lang/Object
    //   263: invokevirtual 61	java/lang/reflect/Method:invoke	(Ljava/lang/Object;[Ljava/lang/Object;)Ljava/lang/Object;
    //   266: astore 6
    //   268: aload 6
    //   270: checkcast 63	java/lang/Integer
    //   273: invokevirtual 67	java/lang/Integer:intValue	()I
    //   276: putstatic 41	uuuuuu/bbmmmm:b00770077wwww007700770077	I
    //   279: bipush 62
    //   281: putstatic 43	uuuuuu/bbmmmm:bww0077www007700770077	I
    //   284: ldc 2
    //   286: ldc 85
    //   288: bipush 124
    //   290: iconst_0
    //   291: invokestatic 73	xxxxxx/uxxxxx:bb00620062bb0062b0062b0062	(Ljava/lang/String;CC)Ljava/lang/String;
    //   294: iconst_0
    //   295: anewarray 33	java/lang/Class
    //   298: invokevirtual 55	java/lang/Class:getMethod	(Ljava/lang/String;[Ljava/lang/Class;)Ljava/lang/reflect/Method;
    //   301: astore 6
    //   303: aload 6
    //   305: aconst_null
    //   306: iconst_0
    //   307: anewarray 4	java/lang/Object
    //   310: invokevirtual 61	java/lang/reflect/Method:invoke	(Ljava/lang/Object;[Ljava/lang/Object;)Ljava/lang/Object;
    //   313: astore 6
    //   315: aload 6
    //   317: checkcast 63	java/lang/Integer
    //   320: invokevirtual 67	java/lang/Integer:intValue	()I
    //   323: istore_0
    //   324: ldc 2
    //   326: ldc 87
    //   328: bipush 123
    //   330: bipush 95
    //   332: iconst_2
    //   333: invokestatic 51	xxxxxx/uxxxxx:bbbb0062b0062b0062b0062	(Ljava/lang/String;CCC)Ljava/lang/String;
    //   336: iconst_0
    //   337: anewarray 33	java/lang/Class
    //   340: invokevirtual 55	java/lang/Class:getMethod	(Ljava/lang/String;[Ljava/lang/Class;)Ljava/lang/reflect/Method;
    //   343: astore 6
    //   345: aload 6
    //   347: aconst_null
    //   348: iconst_0
    //   349: anewarray 4	java/lang/Object
    //   352: invokevirtual 61	java/lang/reflect/Method:invoke	(Ljava/lang/Object;[Ljava/lang/Object;)Ljava/lang/Object;
    //   355: astore 6
    //   357: aload 6
    //   359: checkcast 63	java/lang/Integer
    //   362: invokevirtual 67	java/lang/Integer:intValue	()I
    //   365: istore_1
    //   366: ldc 2
    //   368: ldc 89
    //   370: sipush 217
    //   373: iconst_1
    //   374: invokestatic 73	xxxxxx/uxxxxx:bb00620062bb0062b0062b0062	(Ljava/lang/String;CC)Ljava/lang/String;
    //   377: iconst_0
    //   378: anewarray 33	java/lang/Class
    //   381: invokevirtual 55	java/lang/Class:getMethod	(Ljava/lang/String;[Ljava/lang/Class;)Ljava/lang/reflect/Method;
    //   384: astore 6
    //   386: aload 6
    //   388: aconst_null
    //   389: iconst_0
    //   390: anewarray 4	java/lang/Object
    //   393: invokevirtual 61	java/lang/reflect/Method:invoke	(Ljava/lang/Object;[Ljava/lang/Object;)Ljava/lang/Object;
    //   396: astore 6
    //   398: aload 6
    //   400: checkcast 63	java/lang/Integer
    //   403: invokevirtual 67	java/lang/Integer:intValue	()I
    //   406: iload_0
    //   407: iload_1
    //   408: iadd
    //   409: imul
    //   410: getstatic 77	uuuuuu/bbmmmm:b0077w0077www007700770077	I
    //   413: irem
    //   414: getstatic 81	uuuuuu/bbmmmm:bw00770077www007700770077	I
    //   417: if_icmpeq +44 -> 461
    //   420: getstatic 41	uuuuuu/bbmmmm:b00770077wwww007700770077	I
    //   423: getstatic 43	uuuuuu/bbmmmm:bww0077www007700770077	I
    //   426: iadd
    //   427: getstatic 41	uuuuuu/bbmmmm:b00770077wwww007700770077	I
    //   430: imul
    //   431: getstatic 77	uuuuuu/bbmmmm:b0077w0077www007700770077	I
    //   434: irem
    //   435: getstatic 81	uuuuuu/bbmmmm:bw00770077www007700770077	I
    //   438: if_icmpeq +13 -> 451
    //   441: bipush 27
    //   443: putstatic 41	uuuuuu/bbmmmm:b00770077wwww007700770077	I
    //   446: bipush 19
    //   448: putstatic 81	uuuuuu/bbmmmm:bw00770077www007700770077	I
    //   451: bipush 7
    //   453: putstatic 41	uuuuuu/bbmmmm:b00770077wwww007700770077	I
    //   456: bipush 10
    //   458: putstatic 81	uuuuuu/bbmmmm:bw00770077www007700770077	I
    //   461: return
    //   462: astore 6
    //   464: aload 6
    //   466: invokevirtual 93	java/lang/reflect/InvocationTargetException:getCause	()Ljava/lang/Throwable;
    //   469: athrow
    //   470: astore 6
    //   472: aload 6
    //   474: invokevirtual 93	java/lang/reflect/InvocationTargetException:getCause	()Ljava/lang/Throwable;
    //   477: athrow
    //   478: astore 6
    //   480: aload 6
    //   482: invokevirtual 93	java/lang/reflect/InvocationTargetException:getCause	()Ljava/lang/Throwable;
    //   485: athrow
    //   486: astore 6
    //   488: aload 6
    //   490: invokevirtual 93	java/lang/reflect/InvocationTargetException:getCause	()Ljava/lang/Throwable;
    //   493: athrow
    //   494: astore 6
    //   496: aload 6
    //   498: invokevirtual 93	java/lang/reflect/InvocationTargetException:getCause	()Ljava/lang/Throwable;
    //   501: athrow
    //   502: astore 6
    //   504: aload 6
    //   506: invokevirtual 93	java/lang/reflect/InvocationTargetException:getCause	()Ljava/lang/Throwable;
    //   509: athrow
    //   510: astore 6
    //   512: aload 6
    //   514: invokevirtual 93	java/lang/reflect/InvocationTargetException:getCause	()Ljava/lang/Throwable;
    //   517: athrow
    //   518: astore 6
    //   520: aload 6
    //   522: invokevirtual 93	java/lang/reflect/InvocationTargetException:getCause	()Ljava/lang/Throwable;
    //   525: athrow
    // Local variable table:
    //   start	length	slot	name	signature
    //   11	398	0	i	int
    //   15	394	1	j	int
    //   59	124	2	k	int
    //   99	84	3	m	int
    //   139	45	4	n	int
    //   144	43	5	i1	int
    //   37	362	6	localObject	Object
    //   462	3	6	localInvocationTargetException1	InvocationTargetException
    //   470	3	6	localInvocationTargetException2	InvocationTargetException
    //   478	3	6	localInvocationTargetException3	InvocationTargetException
    //   486	3	6	localInvocationTargetException4	InvocationTargetException
    //   494	3	6	localInvocationTargetException5	InvocationTargetException
    //   502	3	6	localInvocationTargetException6	InvocationTargetException
    //   510	3	6	localInvocationTargetException7	InvocationTargetException
    //   518	3	6	localInvocationTargetException8	InvocationTargetException
    // Exception table:
    //   from	to	target	type
    //   39	51	462	java/lang/reflect/InvocationTargetException
    //   79	91	470	java/lang/reflect/InvocationTargetException
    //   119	131	478	java/lang/reflect/InvocationTargetException
    //   256	268	486	java/lang/reflect/InvocationTargetException
    //   303	315	494	java/lang/reflect/InvocationTargetException
    //   345	357	502	java/lang/reflect/InvocationTargetException
    //   386	398	510	java/lang/reflect/InvocationTargetException
    //   166	178	518	java/lang/reflect/InvocationTargetException
  }
  
  public bbmmmm(bbmbmm.bmbbmm paramBmbbmm)
  {
    this.bw0077wwww007700770077 = paramBmbbmm;
  }
  
  public static int b006F006Fo006F006Foo006Fo006F()
  {
    return 76;
  }
  
  /* Error */
  private void bo006F006F006F006Foo006Fo006F(com.db.pwcc.dbmobile.model.banking.FinancialOverviewData paramFinancialOverviewData)
  {
    // Byte code:
    //   0: aload_0
    //   1: getfield 100	uuuuuu/bbmmmm:bw0077wwww007700770077	Luuuuuu/bbmbmm$bmbbmm;
    //   4: aload_1
    //   5: invokeinterface 133 2 0
    //   10: getstatic 41	uuuuuu/bbmmmm:b00770077wwww007700770077	I
    //   13: istore_2
    //   14: getstatic 43	uuuuuu/bbmmmm:bww0077www007700770077	I
    //   17: istore_3
    //   18: getstatic 41	uuuuuu/bbmmmm:b00770077wwww007700770077	I
    //   21: istore 4
    //   23: getstatic 41	uuuuuu/bbmmmm:b00770077wwww007700770077	I
    //   26: istore 5
    //   28: iload 5
    //   30: getstatic 43	uuuuuu/bbmmmm:bww0077www007700770077	I
    //   33: iload 5
    //   35: iadd
    //   36: imul
    //   37: getstatic 77	uuuuuu/bbmmmm:b0077w0077www007700770077	I
    //   40: irem
    //   41: tableswitch	default:+19->60, 0:+29->70
    //   60: bipush 42
    //   62: putstatic 41	uuuuuu/bbmmmm:b00770077wwww007700770077	I
    //   65: bipush 16
    //   67: putstatic 81	uuuuuu/bbmmmm:bw00770077www007700770077	I
    //   70: ldc 2
    //   72: ldc -121
    //   74: bipush 25
    //   76: bipush 112
    //   78: iconst_1
    //   79: invokestatic 51	xxxxxx/uxxxxx:bbbb0062b0062b0062b0062	(Ljava/lang/String;CCC)Ljava/lang/String;
    //   82: iconst_0
    //   83: anewarray 33	java/lang/Class
    //   86: invokevirtual 55	java/lang/Class:getMethod	(Ljava/lang/String;[Ljava/lang/Class;)Ljava/lang/reflect/Method;
    //   89: astore_1
    //   90: aload_1
    //   91: aconst_null
    //   92: iconst_0
    //   93: anewarray 4	java/lang/Object
    //   96: invokevirtual 61	java/lang/reflect/Method:invoke	(Ljava/lang/Object;[Ljava/lang/Object;)Ljava/lang/Object;
    //   99: astore_1
    //   100: aload_1
    //   101: checkcast 63	java/lang/Integer
    //   104: invokevirtual 67	java/lang/Integer:intValue	()I
    //   107: istore 5
    //   109: iload 5
    //   111: getstatic 43	uuuuuu/bbmmmm:bww0077www007700770077	I
    //   114: iload 5
    //   116: iadd
    //   117: imul
    //   118: getstatic 77	uuuuuu/bbmmmm:b0077w0077www007700770077	I
    //   121: irem
    //   122: tableswitch	default:+18->140, 0:+64->186
    //   140: ldc 2
    //   142: ldc -119
    //   144: sipush 144
    //   147: bipush 119
    //   149: iconst_2
    //   150: invokestatic 51	xxxxxx/uxxxxx:bbbb0062b0062b0062b0062	(Ljava/lang/String;CCC)Ljava/lang/String;
    //   153: iconst_0
    //   154: anewarray 33	java/lang/Class
    //   157: invokevirtual 55	java/lang/Class:getMethod	(Ljava/lang/String;[Ljava/lang/Class;)Ljava/lang/reflect/Method;
    //   160: astore_1
    //   161: aload_1
    //   162: aconst_null
    //   163: iconst_0
    //   164: anewarray 4	java/lang/Object
    //   167: invokevirtual 61	java/lang/reflect/Method:invoke	(Ljava/lang/Object;[Ljava/lang/Object;)Ljava/lang/Object;
    //   170: astore_1
    //   171: aload_1
    //   172: checkcast 63	java/lang/Integer
    //   175: invokevirtual 67	java/lang/Integer:intValue	()I
    //   178: putstatic 41	uuuuuu/bbmmmm:b00770077wwww007700770077	I
    //   181: bipush 74
    //   183: putstatic 81	uuuuuu/bbmmmm:bw00770077www007700770077	I
    //   186: iload 4
    //   188: iload_2
    //   189: iload_3
    //   190: iadd
    //   191: imul
    //   192: getstatic 77	uuuuuu/bbmmmm:b0077w0077www007700770077	I
    //   195: irem
    //   196: getstatic 81	uuuuuu/bbmmmm:bw00770077www007700770077	I
    //   199: if_icmpeq +124 -> 323
    //   202: bipush 72
    //   204: putstatic 41	uuuuuu/bbmmmm:b00770077wwww007700770077	I
    //   207: ldc 2
    //   209: ldc -117
    //   211: bipush 61
    //   213: sipush 156
    //   216: iconst_1
    //   217: invokestatic 51	xxxxxx/uxxxxx:bbbb0062b0062b0062b0062	(Ljava/lang/String;CCC)Ljava/lang/String;
    //   220: iconst_0
    //   221: anewarray 33	java/lang/Class
    //   224: invokevirtual 55	java/lang/Class:getMethod	(Ljava/lang/String;[Ljava/lang/Class;)Ljava/lang/reflect/Method;
    //   227: astore_1
    //   228: aload_1
    //   229: aconst_null
    //   230: iconst_0
    //   231: anewarray 4	java/lang/Object
    //   234: invokevirtual 61	java/lang/reflect/Method:invoke	(Ljava/lang/Object;[Ljava/lang/Object;)Ljava/lang/Object;
    //   237: astore_1
    //   238: aload_1
    //   239: checkcast 63	java/lang/Integer
    //   242: invokevirtual 67	java/lang/Integer:intValue	()I
    //   245: putstatic 81	uuuuuu/bbmmmm:bw00770077www007700770077	I
    //   248: getstatic 41	uuuuuu/bbmmmm:b00770077wwww007700770077	I
    //   251: istore_2
    //   252: iload_2
    //   253: getstatic 43	uuuuuu/bbmmmm:bww0077www007700770077	I
    //   256: iload_2
    //   257: iadd
    //   258: imul
    //   259: getstatic 77	uuuuuu/bbmmmm:b0077w0077www007700770077	I
    //   262: irem
    //   263: tableswitch	default:+17->280, 0:+60->323
    //   280: bipush 39
    //   282: putstatic 41	uuuuuu/bbmmmm:b00770077wwww007700770077	I
    //   285: ldc 2
    //   287: ldc -115
    //   289: bipush 88
    //   291: iconst_4
    //   292: invokestatic 73	xxxxxx/uxxxxx:bb00620062bb0062b0062b0062	(Ljava/lang/String;CC)Ljava/lang/String;
    //   295: iconst_0
    //   296: anewarray 33	java/lang/Class
    //   299: invokevirtual 55	java/lang/Class:getMethod	(Ljava/lang/String;[Ljava/lang/Class;)Ljava/lang/reflect/Method;
    //   302: astore_1
    //   303: aload_1
    //   304: aconst_null
    //   305: iconst_0
    //   306: anewarray 4	java/lang/Object
    //   309: invokevirtual 61	java/lang/reflect/Method:invoke	(Ljava/lang/Object;[Ljava/lang/Object;)Ljava/lang/Object;
    //   312: astore_1
    //   313: aload_1
    //   314: checkcast 63	java/lang/Integer
    //   317: invokevirtual 67	java/lang/Integer:intValue	()I
    //   320: putstatic 81	uuuuuu/bbmmmm:bw00770077www007700770077	I
    //   323: return
    //   324: astore_1
    //   325: aload_1
    //   326: invokevirtual 93	java/lang/reflect/InvocationTargetException:getCause	()Ljava/lang/Throwable;
    //   329: athrow
    //   330: astore_1
    //   331: aload_1
    //   332: invokevirtual 93	java/lang/reflect/InvocationTargetException:getCause	()Ljava/lang/Throwable;
    //   335: athrow
    //   336: astore_1
    //   337: aload_1
    //   338: invokevirtual 93	java/lang/reflect/InvocationTargetException:getCause	()Ljava/lang/Throwable;
    //   341: athrow
    //   342: astore_1
    //   343: aload_1
    //   344: invokevirtual 93	java/lang/reflect/InvocationTargetException:getCause	()Ljava/lang/Throwable;
    //   347: athrow
    // Local variable table:
    //   start	length	slot	name	signature
    //   0	348	0	this	bbmmmm
    //   0	348	1	paramFinancialOverviewData	com.db.pwcc.dbmobile.model.banking.FinancialOverviewData
    //   13	246	2	i	int
    //   17	174	3	j	int
    //   21	171	4	k	int
    //   26	92	5	m	int
    // Exception table:
    //   from	to	target	type
    //   228	238	324	java/lang/reflect/InvocationTargetException
    //   90	100	330	java/lang/reflect/InvocationTargetException
    //   303	313	336	java/lang/reflect/InvocationTargetException
    //   161	171	342	java/lang/reflect/InvocationTargetException
  }
  
  public static int bo006Fo006F006Foo006Fo006F()
  {
    return 2;
  }
  
  public static int boo006F006F006Foo006Fo006F()
  {
    return 1;
  }
  
  public static int booo006F006Foo006Fo006F()
  {
    return 0;
  }
  
  /* Error */
  public heeehh b006F006F006F006F006Foo006Fo006F(com.db.pwcc.dbmobile.model.banking.FinancialOverviewData paramFinancialOverviewData)
  {
    // Byte code:
    //   0: ldc 2
    //   2: ldc -108
    //   4: bipush 12
    //   6: iconst_0
    //   7: invokestatic 73	xxxxxx/uxxxxx:bb00620062bb0062b0062b0062	(Ljava/lang/String;CC)Ljava/lang/String;
    //   10: iconst_0
    //   11: anewarray 33	java/lang/Class
    //   14: invokevirtual 55	java/lang/Class:getMethod	(Ljava/lang/String;[Ljava/lang/Class;)Ljava/lang/reflect/Method;
    //   17: astore_1
    //   18: aload_1
    //   19: aconst_null
    //   20: iconst_0
    //   21: anewarray 4	java/lang/Object
    //   24: invokevirtual 61	java/lang/reflect/Method:invoke	(Ljava/lang/Object;[Ljava/lang/Object;)Ljava/lang/Object;
    //   27: astore_1
    //   28: aload_1
    //   29: checkcast 63	java/lang/Integer
    //   32: invokevirtual 67	java/lang/Integer:intValue	()I
    //   35: istore_2
    //   36: getstatic 43	uuuuuu/bbmmmm:bww0077www007700770077	I
    //   39: istore_3
    //   40: ldc 2
    //   42: ldc -106
    //   44: sipush 199
    //   47: sipush 161
    //   50: iconst_2
    //   51: invokestatic 51	xxxxxx/uxxxxx:bbbb0062b0062b0062b0062	(Ljava/lang/String;CCC)Ljava/lang/String;
    //   54: iconst_0
    //   55: anewarray 33	java/lang/Class
    //   58: invokevirtual 55	java/lang/Class:getMethod	(Ljava/lang/String;[Ljava/lang/Class;)Ljava/lang/reflect/Method;
    //   61: astore_1
    //   62: aload_1
    //   63: aconst_null
    //   64: iconst_0
    //   65: anewarray 4	java/lang/Object
    //   68: invokevirtual 61	java/lang/reflect/Method:invoke	(Ljava/lang/Object;[Ljava/lang/Object;)Ljava/lang/Object;
    //   71: astore_1
    //   72: aload_1
    //   73: checkcast 63	java/lang/Integer
    //   76: invokevirtual 67	java/lang/Integer:intValue	()I
    //   79: iload_3
    //   80: iload_2
    //   81: iadd
    //   82: imul
    //   83: getstatic 77	uuuuuu/bbmmmm:b0077w0077www007700770077	I
    //   86: irem
    //   87: getstatic 81	uuuuuu/bbmmmm:bw00770077www007700770077	I
    //   90: if_icmpeq +79 -> 169
    //   93: ldc 2
    //   95: ldc -104
    //   97: bipush 75
    //   99: iconst_3
    //   100: invokestatic 73	xxxxxx/uxxxxx:bb00620062bb0062b0062b0062	(Ljava/lang/String;CC)Ljava/lang/String;
    //   103: iconst_0
    //   104: anewarray 33	java/lang/Class
    //   107: invokevirtual 55	java/lang/Class:getMethod	(Ljava/lang/String;[Ljava/lang/Class;)Ljava/lang/reflect/Method;
    //   110: astore_1
    //   111: aload_1
    //   112: aconst_null
    //   113: iconst_0
    //   114: anewarray 4	java/lang/Object
    //   117: invokevirtual 61	java/lang/reflect/Method:invoke	(Ljava/lang/Object;[Ljava/lang/Object;)Ljava/lang/Object;
    //   120: astore_1
    //   121: aload_1
    //   122: checkcast 63	java/lang/Integer
    //   125: invokevirtual 67	java/lang/Integer:intValue	()I
    //   128: putstatic 41	uuuuuu/bbmmmm:b00770077wwww007700770077	I
    //   131: ldc 2
    //   133: ldc -102
    //   135: bipush 85
    //   137: iconst_0
    //   138: invokestatic 73	xxxxxx/uxxxxx:bb00620062bb0062b0062b0062	(Ljava/lang/String;CC)Ljava/lang/String;
    //   141: iconst_0
    //   142: anewarray 33	java/lang/Class
    //   145: invokevirtual 55	java/lang/Class:getMethod	(Ljava/lang/String;[Ljava/lang/Class;)Ljava/lang/reflect/Method;
    //   148: astore_1
    //   149: aload_1
    //   150: aconst_null
    //   151: iconst_0
    //   152: anewarray 4	java/lang/Object
    //   155: invokevirtual 61	java/lang/reflect/Method:invoke	(Ljava/lang/Object;[Ljava/lang/Object;)Ljava/lang/Object;
    //   158: astore_1
    //   159: aload_1
    //   160: checkcast 63	java/lang/Integer
    //   163: invokevirtual 67	java/lang/Integer:intValue	()I
    //   166: putstatic 81	uuuuuu/bbmmmm:bw00770077www007700770077	I
    //   169: new 156	uuuuuu/heeehh
    //   172: dup
    //   173: getstatic 161	com/db/pwcc/dbmobile/financial_overview/R$layout:donut_default	I
    //   176: invokespecial 164	uuuuuu/heeehh:<init>	(I)V
    //   179: astore_1
    //   180: getstatic 41	uuuuuu/bbmmmm:b00770077wwww007700770077	I
    //   183: getstatic 43	uuuuuu/bbmmmm:bww0077www007700770077	I
    //   186: iadd
    //   187: getstatic 41	uuuuuu/bbmmmm:b00770077wwww007700770077	I
    //   190: imul
    //   191: getstatic 77	uuuuuu/bbmmmm:b0077w0077www007700770077	I
    //   194: irem
    //   195: getstatic 81	uuuuuu/bbmmmm:bw00770077www007700770077	I
    //   198: if_icmpeq +251 -> 449
    //   201: getstatic 41	uuuuuu/bbmmmm:b00770077wwww007700770077	I
    //   204: istore_2
    //   205: iload_2
    //   206: getstatic 43	uuuuuu/bbmmmm:bww0077www007700770077	I
    //   209: iload_2
    //   210: iadd
    //   211: imul
    //   212: getstatic 77	uuuuuu/bbmmmm:b0077w0077www007700770077	I
    //   215: irem
    //   216: tableswitch	default:+20->236, 0:+30->246
    //   236: bipush 62
    //   238: putstatic 41	uuuuuu/bbmmmm:b00770077wwww007700770077	I
    //   241: bipush 91
    //   243: putstatic 81	uuuuuu/bbmmmm:bw00770077www007700770077	I
    //   246: getstatic 41	uuuuuu/bbmmmm:b00770077wwww007700770077	I
    //   249: istore_2
    //   250: ldc 2
    //   252: ldc -90
    //   254: sipush 224
    //   257: iconst_5
    //   258: invokestatic 73	xxxxxx/uxxxxx:bb00620062bb0062b0062b0062	(Ljava/lang/String;CC)Ljava/lang/String;
    //   261: iconst_0
    //   262: anewarray 33	java/lang/Class
    //   265: invokevirtual 55	java/lang/Class:getMethod	(Ljava/lang/String;[Ljava/lang/Class;)Ljava/lang/reflect/Method;
    //   268: astore 4
    //   270: aload 4
    //   272: aconst_null
    //   273: iconst_0
    //   274: anewarray 4	java/lang/Object
    //   277: invokevirtual 61	java/lang/reflect/Method:invoke	(Ljava/lang/Object;[Ljava/lang/Object;)Ljava/lang/Object;
    //   280: astore 4
    //   282: aload 4
    //   284: checkcast 63	java/lang/Integer
    //   287: invokevirtual 67	java/lang/Integer:intValue	()I
    //   290: iload_2
    //   291: iadd
    //   292: getstatic 41	uuuuuu/bbmmmm:b00770077wwww007700770077	I
    //   295: imul
    //   296: getstatic 77	uuuuuu/bbmmmm:b0077w0077www007700770077	I
    //   299: irem
    //   300: getstatic 81	uuuuuu/bbmmmm:bw00770077www007700770077	I
    //   303: if_icmpeq +54 -> 357
    //   306: bipush 52
    //   308: putstatic 41	uuuuuu/bbmmmm:b00770077wwww007700770077	I
    //   311: ldc 2
    //   313: ldc -88
    //   315: sipush 162
    //   318: sipush 153
    //   321: iconst_0
    //   322: invokestatic 51	xxxxxx/uxxxxx:bbbb0062b0062b0062b0062	(Ljava/lang/String;CCC)Ljava/lang/String;
    //   325: iconst_0
    //   326: anewarray 33	java/lang/Class
    //   329: invokevirtual 55	java/lang/Class:getMethod	(Ljava/lang/String;[Ljava/lang/Class;)Ljava/lang/reflect/Method;
    //   332: astore 4
    //   334: aload 4
    //   336: aconst_null
    //   337: iconst_0
    //   338: anewarray 4	java/lang/Object
    //   341: invokevirtual 61	java/lang/reflect/Method:invoke	(Ljava/lang/Object;[Ljava/lang/Object;)Ljava/lang/Object;
    //   344: astore 4
    //   346: aload 4
    //   348: checkcast 63	java/lang/Integer
    //   351: invokevirtual 67	java/lang/Integer:intValue	()I
    //   354: putstatic 81	uuuuuu/bbmmmm:bw00770077www007700770077	I
    //   357: ldc 2
    //   359: ldc -86
    //   361: sipush 152
    //   364: sipush 145
    //   367: iconst_3
    //   368: invokestatic 51	xxxxxx/uxxxxx:bbbb0062b0062b0062b0062	(Ljava/lang/String;CCC)Ljava/lang/String;
    //   371: iconst_0
    //   372: anewarray 33	java/lang/Class
    //   375: invokevirtual 55	java/lang/Class:getMethod	(Ljava/lang/String;[Ljava/lang/Class;)Ljava/lang/reflect/Method;
    //   378: astore 4
    //   380: aload 4
    //   382: aconst_null
    //   383: iconst_0
    //   384: anewarray 4	java/lang/Object
    //   387: invokevirtual 61	java/lang/reflect/Method:invoke	(Ljava/lang/Object;[Ljava/lang/Object;)Ljava/lang/Object;
    //   390: astore 4
    //   392: aload 4
    //   394: checkcast 63	java/lang/Integer
    //   397: invokevirtual 67	java/lang/Integer:intValue	()I
    //   400: putstatic 41	uuuuuu/bbmmmm:b00770077wwww007700770077	I
    //   403: ldc 2
    //   405: ldc -84
    //   407: sipush 225
    //   410: sipush 142
    //   413: iconst_3
    //   414: invokestatic 51	xxxxxx/uxxxxx:bbbb0062b0062b0062b0062	(Ljava/lang/String;CCC)Ljava/lang/String;
    //   417: iconst_0
    //   418: anewarray 33	java/lang/Class
    //   421: invokevirtual 55	java/lang/Class:getMethod	(Ljava/lang/String;[Ljava/lang/Class;)Ljava/lang/reflect/Method;
    //   424: astore 4
    //   426: aload 4
    //   428: aconst_null
    //   429: iconst_0
    //   430: anewarray 4	java/lang/Object
    //   433: invokevirtual 61	java/lang/reflect/Method:invoke	(Ljava/lang/Object;[Ljava/lang/Object;)Ljava/lang/Object;
    //   436: astore 4
    //   438: aload 4
    //   440: checkcast 63	java/lang/Integer
    //   443: invokevirtual 67	java/lang/Integer:intValue	()I
    //   446: putstatic 81	uuuuuu/bbmmmm:bw00770077www007700770077	I
    //   449: aload_1
    //   450: areturn
    //   451: astore_1
    //   452: aload_1
    //   453: invokevirtual 93	java/lang/reflect/InvocationTargetException:getCause	()Ljava/lang/Throwable;
    //   456: athrow
    //   457: astore_1
    //   458: aload_1
    //   459: invokevirtual 93	java/lang/reflect/InvocationTargetException:getCause	()Ljava/lang/Throwable;
    //   462: athrow
    //   463: astore_1
    //   464: aload_1
    //   465: invokevirtual 93	java/lang/reflect/InvocationTargetException:getCause	()Ljava/lang/Throwable;
    //   468: athrow
    //   469: astore_1
    //   470: aload_1
    //   471: invokevirtual 93	java/lang/reflect/InvocationTargetException:getCause	()Ljava/lang/Throwable;
    //   474: athrow
    //   475: astore_1
    //   476: aload_1
    //   477: invokevirtual 93	java/lang/reflect/InvocationTargetException:getCause	()Ljava/lang/Throwable;
    //   480: athrow
    //   481: astore_1
    //   482: aload_1
    //   483: invokevirtual 93	java/lang/reflect/InvocationTargetException:getCause	()Ljava/lang/Throwable;
    //   486: athrow
    //   487: astore_1
    //   488: aload_1
    //   489: invokevirtual 93	java/lang/reflect/InvocationTargetException:getCause	()Ljava/lang/Throwable;
    //   492: athrow
    //   493: astore_1
    //   494: aload_1
    //   495: invokevirtual 93	java/lang/reflect/InvocationTargetException:getCause	()Ljava/lang/Throwable;
    //   498: athrow
    // Local variable table:
    //   start	length	slot	name	signature
    //   0	499	0	this	bbmmmm
    //   0	499	1	paramFinancialOverviewData	com.db.pwcc.dbmobile.model.banking.FinancialOverviewData
    //   35	257	2	i	int
    //   39	43	3	j	int
    //   268	171	4	localObject	Object
    // Exception table:
    //   from	to	target	type
    //   270	282	451	java/lang/reflect/InvocationTargetException
    //   18	28	457	java/lang/reflect/InvocationTargetException
    //   62	72	463	java/lang/reflect/InvocationTargetException
    //   380	392	469	java/lang/reflect/InvocationTargetException
    //   426	438	475	java/lang/reflect/InvocationTargetException
    //   111	121	481	java/lang/reflect/InvocationTargetException
    //   149	159	487	java/lang/reflect/InvocationTargetException
    //   334	346	493	java/lang/reflect/InvocationTargetException
  }
  
  /* Error */
  public void b006F006F006Foo006Fo006Fo006F(com.db.pwcc.dbmobile.model.banking.FinancialOverviewData paramFinancialOverviewData)
  {
    // Byte code:
    //   0: aload_1
    //   1: ifnonnull +4 -> 5
    //   4: return
    //   5: invokestatic 179	java/util/Locale:getDefault	()Ljava/util/Locale;
    //   8: astore 4
    //   10: aload_1
    //   11: aload 4
    //   13: invokevirtual 183	com/db/pwcc/dbmobile/model/banking/FinancialOverviewData:getBookedBalanceInBaseCurrencyLocalized	(Ljava/util/Locale;)Ljava/lang/String;
    //   16: astore 5
    //   18: getstatic 41	uuuuuu/bbmmmm:b00770077wwww007700770077	I
    //   21: getstatic 43	uuuuuu/bbmmmm:bww0077www007700770077	I
    //   24: iadd
    //   25: getstatic 41	uuuuuu/bbmmmm:b00770077wwww007700770077	I
    //   28: imul
    //   29: getstatic 77	uuuuuu/bbmmmm:b0077w0077www007700770077	I
    //   32: irem
    //   33: getstatic 81	uuuuuu/bbmmmm:bw00770077www007700770077	I
    //   36: if_icmpeq +53 -> 89
    //   39: bipush 6
    //   41: putstatic 41	uuuuuu/bbmmmm:b00770077wwww007700770077	I
    //   44: ldc 2
    //   46: ldc -71
    //   48: bipush 96
    //   50: sipush 204
    //   53: iconst_0
    //   54: invokestatic 51	xxxxxx/uxxxxx:bbbb0062b0062b0062b0062	(Ljava/lang/String;CCC)Ljava/lang/String;
    //   57: iconst_0
    //   58: anewarray 33	java/lang/Class
    //   61: invokevirtual 55	java/lang/Class:getMethod	(Ljava/lang/String;[Ljava/lang/Class;)Ljava/lang/reflect/Method;
    //   64: astore 6
    //   66: aload 6
    //   68: aconst_null
    //   69: iconst_0
    //   70: anewarray 4	java/lang/Object
    //   73: invokevirtual 61	java/lang/reflect/Method:invoke	(Ljava/lang/Object;[Ljava/lang/Object;)Ljava/lang/Object;
    //   76: astore 6
    //   78: aload 6
    //   80: checkcast 63	java/lang/Integer
    //   83: invokevirtual 67	java/lang/Integer:intValue	()I
    //   86: putstatic 81	uuuuuu/bbmmmm:bw00770077www007700770077	I
    //   89: aload_0
    //   90: getfield 100	uuuuuu/bbmmmm:bw0077wwww007700770077	Luuuuuu/bbmbmm$bmbbmm;
    //   93: getstatic 190	com/db/pwcc/dbmobile/financial_overview/R$string:default_bank_name	I
    //   96: invokeinterface 194 2 0
    //   101: astore 6
    //   103: aload_1
    //   104: invokevirtual 198	com/db/pwcc/dbmobile/model/banking/FinancialOverviewData:hasPrebookedBalanceLoadedAndIsValid	()Z
    //   107: ifeq +266 -> 373
    //   110: aload_1
    //   111: invokevirtual 202	com/db/pwcc/dbmobile/model/banking/FinancialOverviewData:getOnlineBalanceInBaseCurrency	()Ljava/math/BigDecimal;
    //   114: ifnull +259 -> 373
    //   117: aload_1
    //   118: invokevirtual 205	com/db/pwcc/dbmobile/model/banking/FinancialOverviewData:hasPrebookedBalanceInAccounts	()Z
    //   121: ifeq +252 -> 373
    //   124: getstatic 41	uuuuuu/bbmmmm:b00770077wwww007700770077	I
    //   127: istore_2
    //   128: iload_2
    //   129: getstatic 43	uuuuuu/bbmmmm:bww0077www007700770077	I
    //   132: iload_2
    //   133: iadd
    //   134: imul
    //   135: getstatic 77	uuuuuu/bbmmmm:b0077w0077www007700770077	I
    //   138: irem
    //   139: tableswitch	default:+17->156, 0:+64->203
    //   156: ldc 2
    //   158: ldc -49
    //   160: bipush 73
    //   162: iconst_5
    //   163: invokestatic 73	xxxxxx/uxxxxx:bb00620062bb0062b0062b0062	(Ljava/lang/String;CC)Ljava/lang/String;
    //   166: iconst_0
    //   167: anewarray 33	java/lang/Class
    //   170: invokevirtual 55	java/lang/Class:getMethod	(Ljava/lang/String;[Ljava/lang/Class;)Ljava/lang/reflect/Method;
    //   173: astore 7
    //   175: aload 7
    //   177: aconst_null
    //   178: iconst_0
    //   179: anewarray 4	java/lang/Object
    //   182: invokevirtual 61	java/lang/reflect/Method:invoke	(Ljava/lang/Object;[Ljava/lang/Object;)Ljava/lang/Object;
    //   185: astore 7
    //   187: aload 7
    //   189: checkcast 63	java/lang/Integer
    //   192: invokevirtual 67	java/lang/Integer:intValue	()I
    //   195: putstatic 41	uuuuuu/bbmmmm:b00770077wwww007700770077	I
    //   198: bipush 52
    //   200: putstatic 81	uuuuuu/bbmmmm:bw00770077www007700770077	I
    //   203: aload_0
    //   204: getfield 100	uuuuuu/bbmmmm:bw0077wwww007700770077	Luuuuuu/bbmbmm$bmbbmm;
    //   207: astore 7
    //   209: getstatic 41	uuuuuu/bbmmmm:b00770077wwww007700770077	I
    //   212: istore_2
    //   213: getstatic 43	uuuuuu/bbmmmm:bww0077www007700770077	I
    //   216: istore_3
    //   217: ldc 2
    //   219: ldc -47
    //   221: bipush 70
    //   223: iconst_5
    //   224: iconst_1
    //   225: invokestatic 51	xxxxxx/uxxxxx:bbbb0062b0062b0062b0062	(Ljava/lang/String;CCC)Ljava/lang/String;
    //   228: iconst_0
    //   229: anewarray 33	java/lang/Class
    //   232: invokevirtual 55	java/lang/Class:getMethod	(Ljava/lang/String;[Ljava/lang/Class;)Ljava/lang/reflect/Method;
    //   235: astore 8
    //   237: aload 8
    //   239: aconst_null
    //   240: iconst_0
    //   241: anewarray 4	java/lang/Object
    //   244: invokevirtual 61	java/lang/reflect/Method:invoke	(Ljava/lang/Object;[Ljava/lang/Object;)Ljava/lang/Object;
    //   247: astore 8
    //   249: iload_3
    //   250: iload_2
    //   251: iadd
    //   252: iload_2
    //   253: imul
    //   254: aload 8
    //   256: checkcast 63	java/lang/Integer
    //   259: invokevirtual 67	java/lang/Integer:intValue	()I
    //   262: irem
    //   263: tableswitch	default:+17->280, 0:+66->329
    //   280: bipush 6
    //   282: putstatic 41	uuuuuu/bbmmmm:b00770077wwww007700770077	I
    //   285: ldc 2
    //   287: ldc -45
    //   289: bipush 84
    //   291: bipush 39
    //   293: iconst_1
    //   294: invokestatic 51	xxxxxx/uxxxxx:bbbb0062b0062b0062b0062	(Ljava/lang/String;CCC)Ljava/lang/String;
    //   297: iconst_0
    //   298: anewarray 33	java/lang/Class
    //   301: invokevirtual 55	java/lang/Class:getMethod	(Ljava/lang/String;[Ljava/lang/Class;)Ljava/lang/reflect/Method;
    //   304: astore 8
    //   306: aload 8
    //   308: aconst_null
    //   309: iconst_0
    //   310: anewarray 4	java/lang/Object
    //   313: invokevirtual 61	java/lang/reflect/Method:invoke	(Ljava/lang/Object;[Ljava/lang/Object;)Ljava/lang/Object;
    //   316: astore 8
    //   318: aload 8
    //   320: checkcast 63	java/lang/Integer
    //   323: invokevirtual 67	java/lang/Integer:intValue	()I
    //   326: putstatic 81	uuuuuu/bbmmmm:bw00770077www007700770077	I
    //   329: aload 7
    //   331: getstatic 214	com/db/pwcc/dbmobile/financial_overview/R$string:label_overall_balance_incl_prebooked_items	I
    //   334: invokeinterface 194 2 0
    //   339: iconst_1
    //   340: anewarray 4	java/lang/Object
    //   343: dup
    //   344: iconst_0
    //   345: aload_1
    //   346: aload 4
    //   348: invokevirtual 217	com/db/pwcc/dbmobile/model/banking/FinancialOverviewData:getOnlineBalanceInBaseCurrencyLocalized	(Ljava/util/Locale;)Ljava/lang/String;
    //   351: aastore
    //   352: invokestatic 223	java/lang/String:format	(Ljava/lang/String;[Ljava/lang/Object;)Ljava/lang/String;
    //   355: astore_1
    //   356: aload_0
    //   357: getfield 100	uuuuuu/bbmmmm:bw0077wwww007700770077	Luuuuuu/bbmbmm$bmbbmm;
    //   360: aload 6
    //   362: aload 5
    //   364: aload_1
    //   365: aconst_null
    //   366: iconst_2
    //   367: invokeinterface 227 6 0
    //   372: return
    //   373: aconst_null
    //   374: astore 4
    //   376: getstatic 39	uuuuuu/bbmmmm:b007700770077007700770077w00770077	Ljava/lang/String;
    //   379: astore 7
    //   381: new 229	java/lang/StringBuilder
    //   384: dup
    //   385: invokespecial 230	java/lang/StringBuilder:<init>	()V
    //   388: astore 8
    //   390: ldc -24
    //   392: ldc -22
    //   394: sipush 170
    //   397: sipush 215
    //   400: iconst_1
    //   401: invokestatic 51	xxxxxx/uxxxxx:bbbb0062b0062b0062b0062	(Ljava/lang/String;CCC)Ljava/lang/String;
    //   404: iconst_3
    //   405: anewarray 33	java/lang/Class
    //   408: dup
    //   409: iconst_0
    //   410: ldc -37
    //   412: aastore
    //   413: dup
    //   414: iconst_1
    //   415: getstatic 240	java/lang/Character:TYPE	Ljava/lang/Class;
    //   418: aastore
    //   419: dup
    //   420: iconst_2
    //   421: getstatic 240	java/lang/Character:TYPE	Ljava/lang/Class;
    //   424: aastore
    //   425: invokevirtual 55	java/lang/Class:getMethod	(Ljava/lang/String;[Ljava/lang/Class;)Ljava/lang/reflect/Method;
    //   428: astore 9
    //   430: aload 9
    //   432: aconst_null
    //   433: iconst_3
    //   434: anewarray 4	java/lang/Object
    //   437: dup
    //   438: iconst_0
    //   439: ldc -14
    //   441: aastore
    //   442: dup
    //   443: iconst_1
    //   444: sipush 154
    //   447: invokestatic 246	java/lang/Character:valueOf	(C)Ljava/lang/Character;
    //   450: aastore
    //   451: dup
    //   452: iconst_2
    //   453: iconst_4
    //   454: invokestatic 246	java/lang/Character:valueOf	(C)Ljava/lang/Character;
    //   457: aastore
    //   458: invokevirtual 61	java/lang/reflect/Method:invoke	(Ljava/lang/Object;[Ljava/lang/Object;)Ljava/lang/Object;
    //   461: astore 9
    //   463: aload 8
    //   465: aload 9
    //   467: checkcast 219	java/lang/String
    //   470: invokevirtual 250	java/lang/StringBuilder:append	(Ljava/lang/String;)Ljava/lang/StringBuilder;
    //   473: aload_1
    //   474: invokevirtual 198	com/db/pwcc/dbmobile/model/banking/FinancialOverviewData:hasPrebookedBalanceLoadedAndIsValid	()Z
    //   477: invokevirtual 253	java/lang/StringBuilder:append	(Z)Ljava/lang/StringBuilder;
    //   480: astore 8
    //   482: getstatic 41	uuuuuu/bbmmmm:b00770077wwww007700770077	I
    //   485: getstatic 43	uuuuuu/bbmmmm:bww0077www007700770077	I
    //   488: iadd
    //   489: getstatic 41	uuuuuu/bbmmmm:b00770077wwww007700770077	I
    //   492: imul
    //   493: getstatic 77	uuuuuu/bbmmmm:b0077w0077www007700770077	I
    //   496: irem
    //   497: getstatic 81	uuuuuu/bbmmmm:bw00770077www007700770077	I
    //   500: if_icmpeq +53 -> 553
    //   503: bipush 28
    //   505: putstatic 41	uuuuuu/bbmmmm:b00770077wwww007700770077	I
    //   508: ldc 2
    //   510: ldc -1
    //   512: sipush 221
    //   515: bipush 38
    //   517: iconst_1
    //   518: invokestatic 51	xxxxxx/uxxxxx:bbbb0062b0062b0062b0062	(Ljava/lang/String;CCC)Ljava/lang/String;
    //   521: iconst_0
    //   522: anewarray 33	java/lang/Class
    //   525: invokevirtual 55	java/lang/Class:getMethod	(Ljava/lang/String;[Ljava/lang/Class;)Ljava/lang/reflect/Method;
    //   528: astore 9
    //   530: aload 9
    //   532: aconst_null
    //   533: iconst_0
    //   534: anewarray 4	java/lang/Object
    //   537: invokevirtual 61	java/lang/reflect/Method:invoke	(Ljava/lang/Object;[Ljava/lang/Object;)Ljava/lang/Object;
    //   540: astore 9
    //   542: aload 9
    //   544: checkcast 63	java/lang/Integer
    //   547: invokevirtual 67	java/lang/Integer:intValue	()I
    //   550: putstatic 81	uuuuuu/bbmmmm:bw00770077www007700770077	I
    //   553: ldc -24
    //   555: ldc_w 257
    //   558: bipush 89
    //   560: iconst_2
    //   561: invokestatic 73	xxxxxx/uxxxxx:bb00620062bb0062b0062b0062	(Ljava/lang/String;CC)Ljava/lang/String;
    //   564: iconst_4
    //   565: anewarray 33	java/lang/Class
    //   568: dup
    //   569: iconst_0
    //   570: ldc -37
    //   572: aastore
    //   573: dup
    //   574: iconst_1
    //   575: getstatic 240	java/lang/Character:TYPE	Ljava/lang/Class;
    //   578: aastore
    //   579: dup
    //   580: iconst_2
    //   581: getstatic 240	java/lang/Character:TYPE	Ljava/lang/Class;
    //   584: aastore
    //   585: dup
    //   586: iconst_3
    //   587: getstatic 240	java/lang/Character:TYPE	Ljava/lang/Class;
    //   590: aastore
    //   591: invokevirtual 55	java/lang/Class:getMethod	(Ljava/lang/String;[Ljava/lang/Class;)Ljava/lang/reflect/Method;
    //   594: astore 9
    //   596: aload 9
    //   598: aconst_null
    //   599: iconst_4
    //   600: anewarray 4	java/lang/Object
    //   603: dup
    //   604: iconst_0
    //   605: ldc_w 259
    //   608: aastore
    //   609: dup
    //   610: iconst_1
    //   611: sipush 152
    //   614: invokestatic 246	java/lang/Character:valueOf	(C)Ljava/lang/Character;
    //   617: aastore
    //   618: dup
    //   619: iconst_2
    //   620: bipush 26
    //   622: invokestatic 246	java/lang/Character:valueOf	(C)Ljava/lang/Character;
    //   625: aastore
    //   626: dup
    //   627: iconst_3
    //   628: iconst_2
    //   629: invokestatic 246	java/lang/Character:valueOf	(C)Ljava/lang/Character;
    //   632: aastore
    //   633: invokevirtual 61	java/lang/reflect/Method:invoke	(Ljava/lang/Object;[Ljava/lang/Object;)Ljava/lang/Object;
    //   636: astore 9
    //   638: aload 8
    //   640: aload 9
    //   642: checkcast 219	java/lang/String
    //   645: invokevirtual 250	java/lang/StringBuilder:append	(Ljava/lang/String;)Ljava/lang/StringBuilder;
    //   648: aload_1
    //   649: invokevirtual 202	com/db/pwcc/dbmobile/model/banking/FinancialOverviewData:getOnlineBalanceInBaseCurrency	()Ljava/math/BigDecimal;
    //   652: invokevirtual 262	java/lang/StringBuilder:append	(Ljava/lang/Object;)Ljava/lang/StringBuilder;
    //   655: astore 8
    //   657: ldc -24
    //   659: ldc_w 264
    //   662: iconst_1
    //   663: iconst_2
    //   664: invokestatic 73	xxxxxx/uxxxxx:bb00620062bb0062b0062b0062	(Ljava/lang/String;CC)Ljava/lang/String;
    //   667: iconst_3
    //   668: anewarray 33	java/lang/Class
    //   671: dup
    //   672: iconst_0
    //   673: ldc -37
    //   675: aastore
    //   676: dup
    //   677: iconst_1
    //   678: getstatic 240	java/lang/Character:TYPE	Ljava/lang/Class;
    //   681: aastore
    //   682: dup
    //   683: iconst_2
    //   684: getstatic 240	java/lang/Character:TYPE	Ljava/lang/Class;
    //   687: aastore
    //   688: invokevirtual 55	java/lang/Class:getMethod	(Ljava/lang/String;[Ljava/lang/Class;)Ljava/lang/reflect/Method;
    //   691: astore 9
    //   693: aload 9
    //   695: aconst_null
    //   696: iconst_3
    //   697: anewarray 4	java/lang/Object
    //   700: dup
    //   701: iconst_0
    //   702: ldc_w 266
    //   705: aastore
    //   706: dup
    //   707: iconst_1
    //   708: bipush 63
    //   710: invokestatic 246	java/lang/Character:valueOf	(C)Ljava/lang/Character;
    //   713: aastore
    //   714: dup
    //   715: iconst_2
    //   716: iconst_4
    //   717: invokestatic 246	java/lang/Character:valueOf	(C)Ljava/lang/Character;
    //   720: aastore
    //   721: invokevirtual 61	java/lang/reflect/Method:invoke	(Ljava/lang/Object;[Ljava/lang/Object;)Ljava/lang/Object;
    //   724: astore 9
    //   726: aload 7
    //   728: aload 8
    //   730: aload 9
    //   732: checkcast 219	java/lang/String
    //   735: invokevirtual 250	java/lang/StringBuilder:append	(Ljava/lang/String;)Ljava/lang/StringBuilder;
    //   738: aload_1
    //   739: invokevirtual 205	com/db/pwcc/dbmobile/model/banking/FinancialOverviewData:hasPrebookedBalanceInAccounts	()Z
    //   742: invokevirtual 253	java/lang/StringBuilder:append	(Z)Ljava/lang/StringBuilder;
    //   745: invokevirtual 269	java/lang/StringBuilder:toString	()Ljava/lang/String;
    //   748: invokestatic 275	uuuuuu/rvvvrv:bqq0071q00710071q0071q0071	(Ljava/lang/String;Ljava/lang/String;)V
    //   751: aload 4
    //   753: astore_1
    //   754: goto -398 -> 356
    //   757: astore_1
    //   758: aload_1
    //   759: invokevirtual 93	java/lang/reflect/InvocationTargetException:getCause	()Ljava/lang/Throwable;
    //   762: athrow
    //   763: astore_1
    //   764: aload_1
    //   765: invokevirtual 93	java/lang/reflect/InvocationTargetException:getCause	()Ljava/lang/Throwable;
    //   768: athrow
    //   769: astore_1
    //   770: aload_1
    //   771: invokevirtual 93	java/lang/reflect/InvocationTargetException:getCause	()Ljava/lang/Throwable;
    //   774: athrow
    //   775: astore_1
    //   776: aload_1
    //   777: invokevirtual 93	java/lang/reflect/InvocationTargetException:getCause	()Ljava/lang/Throwable;
    //   780: athrow
    //   781: astore_1
    //   782: aload_1
    //   783: invokevirtual 93	java/lang/reflect/InvocationTargetException:getCause	()Ljava/lang/Throwable;
    //   786: athrow
    //   787: astore_1
    //   788: aload_1
    //   789: invokevirtual 93	java/lang/reflect/InvocationTargetException:getCause	()Ljava/lang/Throwable;
    //   792: athrow
    //   793: astore_1
    //   794: aload_1
    //   795: invokevirtual 93	java/lang/reflect/InvocationTargetException:getCause	()Ljava/lang/Throwable;
    //   798: athrow
    //   799: astore_1
    //   800: aload_1
    //   801: invokevirtual 93	java/lang/reflect/InvocationTargetException:getCause	()Ljava/lang/Throwable;
    //   804: athrow
    // Local variable table:
    //   start	length	slot	name	signature
    //   0	805	0	this	bbmmmm
    //   0	805	1	paramFinancialOverviewData	com.db.pwcc.dbmobile.model.banking.FinancialOverviewData
    //   127	127	2	i	int
    //   216	36	3	j	int
    //   8	744	4	localLocale	java.util.Locale
    //   16	347	5	str	String
    //   64	297	6	localObject1	Object
    //   173	554	7	localObject2	Object
    //   235	494	8	localObject3	Object
    //   428	303	9	localObject4	Object
    // Exception table:
    //   from	to	target	type
    //   430	463	757	java/lang/reflect/InvocationTargetException
    //   237	249	763	java/lang/reflect/InvocationTargetException
    //   693	726	769	java/lang/reflect/InvocationTargetException
    //   596	638	775	java/lang/reflect/InvocationTargetException
    //   306	318	781	java/lang/reflect/InvocationTargetException
    //   175	187	787	java/lang/reflect/InvocationTargetException
    //   530	542	793	java/lang/reflect/InvocationTargetException
    //   66	78	799	java/lang/reflect/InvocationTargetException
  }
  
  /* Error */
  public void b006F006Fooo006Fo006Fo006F()
  {
    // Byte code:
    //   0: aload_0
    //   1: getfield 278	uuuuuu/bbmmmm:bwwwwww007700770077	Luuuuuu/qpqqqq;
    //   4: astore 4
    //   6: getstatic 41	uuuuuu/bbmmmm:b00770077wwww007700770077	I
    //   9: istore_1
    //   10: getstatic 43	uuuuuu/bbmmmm:bww0077www007700770077	I
    //   13: istore_2
    //   14: getstatic 41	uuuuuu/bbmmmm:b00770077wwww007700770077	I
    //   17: istore_3
    //   18: getstatic 41	uuuuuu/bbmmmm:b00770077wwww007700770077	I
    //   21: getstatic 43	uuuuuu/bbmmmm:bww0077www007700770077	I
    //   24: iadd
    //   25: getstatic 41	uuuuuu/bbmmmm:b00770077wwww007700770077	I
    //   28: imul
    //   29: getstatic 77	uuuuuu/bbmmmm:b0077w0077www007700770077	I
    //   32: irem
    //   33: getstatic 81	uuuuuu/bbmmmm:bw00770077www007700770077	I
    //   36: if_icmpeq +51 -> 87
    //   39: bipush 64
    //   41: putstatic 41	uuuuuu/bbmmmm:b00770077wwww007700770077	I
    //   44: ldc 2
    //   46: ldc_w 280
    //   49: bipush 83
    //   51: iconst_4
    //   52: invokestatic 73	xxxxxx/uxxxxx:bb00620062bb0062b0062b0062	(Ljava/lang/String;CC)Ljava/lang/String;
    //   55: iconst_0
    //   56: anewarray 33	java/lang/Class
    //   59: invokevirtual 55	java/lang/Class:getMethod	(Ljava/lang/String;[Ljava/lang/Class;)Ljava/lang/reflect/Method;
    //   62: astore 5
    //   64: aload 5
    //   66: aconst_null
    //   67: iconst_0
    //   68: anewarray 4	java/lang/Object
    //   71: invokevirtual 61	java/lang/reflect/Method:invoke	(Ljava/lang/Object;[Ljava/lang/Object;)Ljava/lang/Object;
    //   74: astore 5
    //   76: aload 5
    //   78: checkcast 63	java/lang/Integer
    //   81: invokevirtual 67	java/lang/Integer:intValue	()I
    //   84: putstatic 81	uuuuuu/bbmmmm:bw00770077www007700770077	I
    //   87: iload_3
    //   88: iload_1
    //   89: iload_2
    //   90: iadd
    //   91: imul
    //   92: getstatic 77	uuuuuu/bbmmmm:b0077w0077www007700770077	I
    //   95: irem
    //   96: getstatic 81	uuuuuu/bbmmmm:bw00770077www007700770077	I
    //   99: if_icmpeq +323 -> 422
    //   102: bipush 48
    //   104: putstatic 41	uuuuuu/bbmmmm:b00770077wwww007700770077	I
    //   107: bipush 96
    //   109: putstatic 81	uuuuuu/bbmmmm:bw00770077www007700770077	I
    //   112: getstatic 41	uuuuuu/bbmmmm:b00770077wwww007700770077	I
    //   115: istore_1
    //   116: ldc 2
    //   118: ldc_w 282
    //   121: bipush 96
    //   123: iconst_5
    //   124: invokestatic 73	xxxxxx/uxxxxx:bb00620062bb0062b0062b0062	(Ljava/lang/String;CC)Ljava/lang/String;
    //   127: iconst_0
    //   128: anewarray 33	java/lang/Class
    //   131: invokevirtual 55	java/lang/Class:getMethod	(Ljava/lang/String;[Ljava/lang/Class;)Ljava/lang/reflect/Method;
    //   134: astore 5
    //   136: aload 5
    //   138: aconst_null
    //   139: iconst_0
    //   140: anewarray 4	java/lang/Object
    //   143: invokevirtual 61	java/lang/reflect/Method:invoke	(Ljava/lang/Object;[Ljava/lang/Object;)Ljava/lang/Object;
    //   146: astore 5
    //   148: aload 5
    //   150: checkcast 63	java/lang/Integer
    //   153: invokevirtual 67	java/lang/Integer:intValue	()I
    //   156: iload_1
    //   157: iadd
    //   158: iload_1
    //   159: imul
    //   160: getstatic 77	uuuuuu/bbmmmm:b0077w0077www007700770077	I
    //   163: irem
    //   164: tableswitch	default:+20->184, 0:+258->422
    //   184: iconst_1
    //   185: putstatic 41	uuuuuu/bbmmmm:b00770077wwww007700770077	I
    //   188: bipush 6
    //   190: putstatic 81	uuuuuu/bbmmmm:bw00770077www007700770077	I
    //   193: ldc 2
    //   195: ldc_w 284
    //   198: sipush 137
    //   201: bipush 114
    //   203: iconst_1
    //   204: invokestatic 51	xxxxxx/uxxxxx:bbbb0062b0062b0062b0062	(Ljava/lang/String;CCC)Ljava/lang/String;
    //   207: iconst_0
    //   208: anewarray 33	java/lang/Class
    //   211: invokevirtual 55	java/lang/Class:getMethod	(Ljava/lang/String;[Ljava/lang/Class;)Ljava/lang/reflect/Method;
    //   214: astore 5
    //   216: aload 5
    //   218: aconst_null
    //   219: iconst_0
    //   220: anewarray 4	java/lang/Object
    //   223: invokevirtual 61	java/lang/reflect/Method:invoke	(Ljava/lang/Object;[Ljava/lang/Object;)Ljava/lang/Object;
    //   226: astore 5
    //   228: aload 5
    //   230: checkcast 63	java/lang/Integer
    //   233: invokevirtual 67	java/lang/Integer:intValue	()I
    //   236: istore_1
    //   237: ldc 2
    //   239: ldc_w 286
    //   242: bipush 104
    //   244: iconst_5
    //   245: invokestatic 73	xxxxxx/uxxxxx:bb00620062bb0062b0062b0062	(Ljava/lang/String;CC)Ljava/lang/String;
    //   248: iconst_0
    //   249: anewarray 33	java/lang/Class
    //   252: invokevirtual 55	java/lang/Class:getMethod	(Ljava/lang/String;[Ljava/lang/Class;)Ljava/lang/reflect/Method;
    //   255: astore 5
    //   257: aload 5
    //   259: aconst_null
    //   260: iconst_0
    //   261: anewarray 4	java/lang/Object
    //   264: invokevirtual 61	java/lang/reflect/Method:invoke	(Ljava/lang/Object;[Ljava/lang/Object;)Ljava/lang/Object;
    //   267: astore 5
    //   269: aload 5
    //   271: checkcast 63	java/lang/Integer
    //   274: invokevirtual 67	java/lang/Integer:intValue	()I
    //   277: istore_2
    //   278: ldc 2
    //   280: ldc_w 288
    //   283: bipush 105
    //   285: iconst_0
    //   286: invokestatic 73	xxxxxx/uxxxxx:bb00620062bb0062b0062b0062	(Ljava/lang/String;CC)Ljava/lang/String;
    //   289: iconst_0
    //   290: anewarray 33	java/lang/Class
    //   293: invokevirtual 55	java/lang/Class:getMethod	(Ljava/lang/String;[Ljava/lang/Class;)Ljava/lang/reflect/Method;
    //   296: astore 5
    //   298: aload 5
    //   300: aconst_null
    //   301: iconst_0
    //   302: anewarray 4	java/lang/Object
    //   305: invokevirtual 61	java/lang/reflect/Method:invoke	(Ljava/lang/Object;[Ljava/lang/Object;)Ljava/lang/Object;
    //   308: astore 5
    //   310: aload 5
    //   312: checkcast 63	java/lang/Integer
    //   315: invokevirtual 67	java/lang/Integer:intValue	()I
    //   318: istore_3
    //   319: ldc 2
    //   321: ldc_w 290
    //   324: bipush 56
    //   326: iconst_2
    //   327: invokestatic 73	xxxxxx/uxxxxx:bb00620062bb0062b0062b0062	(Ljava/lang/String;CC)Ljava/lang/String;
    //   330: iconst_0
    //   331: anewarray 33	java/lang/Class
    //   334: invokevirtual 55	java/lang/Class:getMethod	(Ljava/lang/String;[Ljava/lang/Class;)Ljava/lang/reflect/Method;
    //   337: astore 5
    //   339: aload 5
    //   341: aconst_null
    //   342: iconst_0
    //   343: anewarray 4	java/lang/Object
    //   346: invokevirtual 61	java/lang/reflect/Method:invoke	(Ljava/lang/Object;[Ljava/lang/Object;)Ljava/lang/Object;
    //   349: astore 5
    //   351: iload_1
    //   352: iload_2
    //   353: iadd
    //   354: iload_3
    //   355: imul
    //   356: aload 5
    //   358: checkcast 63	java/lang/Integer
    //   361: invokevirtual 67	java/lang/Integer:intValue	()I
    //   364: irem
    //   365: getstatic 81	uuuuuu/bbmmmm:bw00770077www007700770077	I
    //   368: if_icmpeq +54 -> 422
    //   371: iconst_1
    //   372: putstatic 41	uuuuuu/bbmmmm:b00770077wwww007700770077	I
    //   375: ldc 2
    //   377: ldc_w 292
    //   380: sipush 166
    //   383: sipush 238
    //   386: iconst_2
    //   387: invokestatic 51	xxxxxx/uxxxxx:bbbb0062b0062b0062b0062	(Ljava/lang/String;CCC)Ljava/lang/String;
    //   390: iconst_0
    //   391: anewarray 33	java/lang/Class
    //   394: invokevirtual 55	java/lang/Class:getMethod	(Ljava/lang/String;[Ljava/lang/Class;)Ljava/lang/reflect/Method;
    //   397: astore 5
    //   399: aload 5
    //   401: aconst_null
    //   402: iconst_0
    //   403: anewarray 4	java/lang/Object
    //   406: invokevirtual 61	java/lang/reflect/Method:invoke	(Ljava/lang/Object;[Ljava/lang/Object;)Ljava/lang/Object;
    //   409: astore 5
    //   411: aload 5
    //   413: checkcast 63	java/lang/Integer
    //   416: invokevirtual 67	java/lang/Integer:intValue	()I
    //   419: putstatic 81	uuuuuu/bbmmmm:bw00770077www007700770077	I
    //   422: aload 4
    //   424: invokeinterface 297 1 0
    //   429: return
    //   430: astore 4
    //   432: aload 4
    //   434: invokevirtual 93	java/lang/reflect/InvocationTargetException:getCause	()Ljava/lang/Throwable;
    //   437: athrow
    //   438: astore 4
    //   440: aload 4
    //   442: invokevirtual 93	java/lang/reflect/InvocationTargetException:getCause	()Ljava/lang/Throwable;
    //   445: athrow
    //   446: astore 4
    //   448: aload 4
    //   450: invokevirtual 93	java/lang/reflect/InvocationTargetException:getCause	()Ljava/lang/Throwable;
    //   453: athrow
    //   454: astore 4
    //   456: aload 4
    //   458: invokevirtual 93	java/lang/reflect/InvocationTargetException:getCause	()Ljava/lang/Throwable;
    //   461: athrow
    //   462: astore 4
    //   464: aload 4
    //   466: invokevirtual 93	java/lang/reflect/InvocationTargetException:getCause	()Ljava/lang/Throwable;
    //   469: athrow
    //   470: astore 4
    //   472: aload 4
    //   474: invokevirtual 93	java/lang/reflect/InvocationTargetException:getCause	()Ljava/lang/Throwable;
    //   477: athrow
    //   478: astore 4
    //   480: aload 4
    //   482: invokevirtual 93	java/lang/reflect/InvocationTargetException:getCause	()Ljava/lang/Throwable;
    //   485: athrow
    // Local variable table:
    //   start	length	slot	name	signature
    //   0	486	0	this	bbmmmm
    //   9	345	1	i	int
    //   13	341	2	j	int
    //   17	339	3	k	int
    //   4	419	4	localQpqqqq	qpqqqq
    //   430	3	4	localInvocationTargetException1	InvocationTargetException
    //   438	3	4	localInvocationTargetException2	InvocationTargetException
    //   446	3	4	localInvocationTargetException3	InvocationTargetException
    //   454	3	4	localInvocationTargetException4	InvocationTargetException
    //   462	3	4	localInvocationTargetException5	InvocationTargetException
    //   470	3	4	localInvocationTargetException6	InvocationTargetException
    //   478	3	4	localInvocationTargetException7	InvocationTargetException
    //   62	350	5	localObject	Object
    // Exception table:
    //   from	to	target	type
    //   64	76	430	java/lang/reflect/InvocationTargetException
    //   136	148	438	java/lang/reflect/InvocationTargetException
    //   216	228	446	java/lang/reflect/InvocationTargetException
    //   257	269	454	java/lang/reflect/InvocationTargetException
    //   298	310	462	java/lang/reflect/InvocationTargetException
    //   339	351	470	java/lang/reflect/InvocationTargetException
    //   399	411	478	java/lang/reflect/InvocationTargetException
  }
  
  /* Error */
  public void b006Fo006F006F006Foo006Fo006F(com.db.pwcc.dbmobile.model.banking.FinancialOverviewData paramFinancialOverviewData)
  {
    // Byte code:
    //   0: getstatic 41	uuuuuu/bbmmmm:b00770077wwww007700770077	I
    //   3: istore_2
    //   4: iload_2
    //   5: getstatic 43	uuuuuu/bbmmmm:bww0077www007700770077	I
    //   8: iload_2
    //   9: iadd
    //   10: imul
    //   11: getstatic 77	uuuuuu/bbmmmm:b0077w0077www007700770077	I
    //   14: irem
    //   15: tableswitch	default:+17->32, 0:+27->42
    //   32: bipush 63
    //   34: putstatic 41	uuuuuu/bbmmmm:b00770077wwww007700770077	I
    //   37: bipush 92
    //   39: putstatic 81	uuuuuu/bbmmmm:bw00770077www007700770077	I
    //   42: getstatic 41	uuuuuu/bbmmmm:b00770077wwww007700770077	I
    //   45: istore_2
    //   46: getstatic 43	uuuuuu/bbmmmm:bww0077www007700770077	I
    //   49: istore_3
    //   50: getstatic 41	uuuuuu/bbmmmm:b00770077wwww007700770077	I
    //   53: istore 4
    //   55: ldc 2
    //   57: ldc_w 300
    //   60: sipush 130
    //   63: iconst_0
    //   64: invokestatic 73	xxxxxx/uxxxxx:bb00620062bb0062b0062b0062	(Ljava/lang/String;CC)Ljava/lang/String;
    //   67: iconst_0
    //   68: anewarray 33	java/lang/Class
    //   71: invokevirtual 55	java/lang/Class:getMethod	(Ljava/lang/String;[Ljava/lang/Class;)Ljava/lang/reflect/Method;
    //   74: astore 6
    //   76: aload 6
    //   78: aconst_null
    //   79: iconst_0
    //   80: anewarray 4	java/lang/Object
    //   83: invokevirtual 61	java/lang/reflect/Method:invoke	(Ljava/lang/Object;[Ljava/lang/Object;)Ljava/lang/Object;
    //   86: astore 6
    //   88: aload 6
    //   90: checkcast 63	java/lang/Integer
    //   93: invokevirtual 67	java/lang/Integer:intValue	()I
    //   96: istore 5
    //   98: getstatic 41	uuuuuu/bbmmmm:b00770077wwww007700770077	I
    //   101: getstatic 43	uuuuuu/bbmmmm:bww0077www007700770077	I
    //   104: iadd
    //   105: getstatic 41	uuuuuu/bbmmmm:b00770077wwww007700770077	I
    //   108: imul
    //   109: getstatic 77	uuuuuu/bbmmmm:b0077w0077www007700770077	I
    //   112: irem
    //   113: getstatic 81	uuuuuu/bbmmmm:bw00770077www007700770077	I
    //   116: if_icmpeq +51 -> 167
    //   119: bipush 40
    //   121: putstatic 41	uuuuuu/bbmmmm:b00770077wwww007700770077	I
    //   124: ldc 2
    //   126: ldc_w 302
    //   129: bipush 37
    //   131: iconst_4
    //   132: invokestatic 73	xxxxxx/uxxxxx:bb00620062bb0062b0062b0062	(Ljava/lang/String;CC)Ljava/lang/String;
    //   135: iconst_0
    //   136: anewarray 33	java/lang/Class
    //   139: invokevirtual 55	java/lang/Class:getMethod	(Ljava/lang/String;[Ljava/lang/Class;)Ljava/lang/reflect/Method;
    //   142: astore 6
    //   144: aload 6
    //   146: aconst_null
    //   147: iconst_0
    //   148: anewarray 4	java/lang/Object
    //   151: invokevirtual 61	java/lang/reflect/Method:invoke	(Ljava/lang/Object;[Ljava/lang/Object;)Ljava/lang/Object;
    //   154: astore 6
    //   156: aload 6
    //   158: checkcast 63	java/lang/Integer
    //   161: invokevirtual 67	java/lang/Integer:intValue	()I
    //   164: putstatic 81	uuuuuu/bbmmmm:bw00770077www007700770077	I
    //   167: iload 4
    //   169: iload_2
    //   170: iload_3
    //   171: iadd
    //   172: imul
    //   173: iload 5
    //   175: irem
    //   176: getstatic 81	uuuuuu/bbmmmm:bw00770077www007700770077	I
    //   179: if_icmpeq +13 -> 192
    //   182: bipush 48
    //   184: putstatic 41	uuuuuu/bbmmmm:b00770077wwww007700770077	I
    //   187: bipush 56
    //   189: putstatic 81	uuuuuu/bbmmmm:bw00770077www007700770077	I
    //   192: getstatic 41	uuuuuu/bbmmmm:b00770077wwww007700770077	I
    //   195: getstatic 43	uuuuuu/bbmmmm:bww0077www007700770077	I
    //   198: iadd
    //   199: getstatic 41	uuuuuu/bbmmmm:b00770077wwww007700770077	I
    //   202: imul
    //   203: getstatic 77	uuuuuu/bbmmmm:b0077w0077www007700770077	I
    //   206: irem
    //   207: getstatic 81	uuuuuu/bbmmmm:bw00770077www007700770077	I
    //   210: if_icmpeq +52 -> 262
    //   213: ldc 2
    //   215: ldc_w 304
    //   218: sipush 134
    //   221: iconst_5
    //   222: invokestatic 73	xxxxxx/uxxxxx:bb00620062bb0062b0062b0062	(Ljava/lang/String;CC)Ljava/lang/String;
    //   225: iconst_0
    //   226: anewarray 33	java/lang/Class
    //   229: invokevirtual 55	java/lang/Class:getMethod	(Ljava/lang/String;[Ljava/lang/Class;)Ljava/lang/reflect/Method;
    //   232: astore 6
    //   234: aload 6
    //   236: aconst_null
    //   237: iconst_0
    //   238: anewarray 4	java/lang/Object
    //   241: invokevirtual 61	java/lang/reflect/Method:invoke	(Ljava/lang/Object;[Ljava/lang/Object;)Ljava/lang/Object;
    //   244: astore 6
    //   246: aload 6
    //   248: checkcast 63	java/lang/Integer
    //   251: invokevirtual 67	java/lang/Integer:intValue	()I
    //   254: putstatic 41	uuuuuu/bbmmmm:b00770077wwww007700770077	I
    //   257: bipush 30
    //   259: putstatic 81	uuuuuu/bbmmmm:bw00770077www007700770077	I
    //   262: ldc 2
    //   264: ldc_w 306
    //   267: bipush 28
    //   269: sipush 134
    //   272: iconst_3
    //   273: invokestatic 51	xxxxxx/uxxxxx:bbbb0062b0062b0062b0062	(Ljava/lang/String;CCC)Ljava/lang/String;
    //   276: iconst_1
    //   277: anewarray 33	java/lang/Class
    //   280: dup
    //   281: iconst_0
    //   282: ldc 122
    //   284: aastore
    //   285: invokevirtual 55	java/lang/Class:getMethod	(Ljava/lang/String;[Ljava/lang/Class;)Ljava/lang/reflect/Method;
    //   288: astore 6
    //   290: aload 6
    //   292: aload_0
    //   293: iconst_1
    //   294: anewarray 4	java/lang/Object
    //   297: dup
    //   298: iconst_0
    //   299: aload_1
    //   300: aastore
    //   301: invokevirtual 61	java/lang/reflect/Method:invoke	(Ljava/lang/Object;[Ljava/lang/Object;)Ljava/lang/Object;
    //   304: pop
    //   305: aload_0
    //   306: getfield 100	uuuuuu/bbmmmm:bw0077wwww007700770077	Luuuuuu/bbmbmm$bmbbmm;
    //   309: aload_1
    //   310: aconst_null
    //   311: iconst_0
    //   312: invokeinterface 310 4 0
    //   317: return
    //   318: astore_1
    //   319: aload_1
    //   320: invokevirtual 93	java/lang/reflect/InvocationTargetException:getCause	()Ljava/lang/Throwable;
    //   323: athrow
    //   324: astore_1
    //   325: aload_1
    //   326: invokevirtual 93	java/lang/reflect/InvocationTargetException:getCause	()Ljava/lang/Throwable;
    //   329: athrow
    //   330: astore_1
    //   331: aload_1
    //   332: invokevirtual 93	java/lang/reflect/InvocationTargetException:getCause	()Ljava/lang/Throwable;
    //   335: athrow
    //   336: astore_1
    //   337: aload_1
    //   338: invokevirtual 93	java/lang/reflect/InvocationTargetException:getCause	()Ljava/lang/Throwable;
    //   341: athrow
    // Local variable table:
    //   start	length	slot	name	signature
    //   0	342	0	this	bbmmmm
    //   0	342	1	paramFinancialOverviewData	com.db.pwcc.dbmobile.model.banking.FinancialOverviewData
    //   3	169	2	i	int
    //   49	123	3	j	int
    //   53	120	4	k	int
    //   96	80	5	m	int
    //   74	217	6	localObject	Object
    // Exception table:
    //   from	to	target	type
    //   234	246	318	java/lang/reflect/InvocationTargetException
    //   290	305	324	java/lang/reflect/InvocationTargetException
    //   76	88	330	java/lang/reflect/InvocationTargetException
    //   144	156	336	java/lang/reflect/InvocationTargetException
  }
  
  /* Error */
  public void b006Fo006Foo006Fo006Fo006F()
  {
    // Byte code:
    //   0: aload_0
    //   1: getfield 313	uuuuuu/bbmmmm:b0077wwwww007700770077	Lcom/db/pwcc/dbmobile/foundation/data/manager/broadcasting/ModelUpdatedBroadcastReceiver;
    //   4: ifnull +508 -> 512
    //   7: aload_0
    //   8: getfield 100	uuuuuu/bbmmmm:bw0077wwww007700770077	Luuuuuu/bbmbmm$bmbbmm;
    //   11: astore 6
    //   13: aload_0
    //   14: getfield 313	uuuuuu/bbmmmm:b0077wwwww007700770077	Lcom/db/pwcc/dbmobile/foundation/data/manager/broadcasting/ModelUpdatedBroadcastReceiver;
    //   17: astore 7
    //   19: getstatic 41	uuuuuu/bbmmmm:b00770077wwww007700770077	I
    //   22: istore_1
    //   23: getstatic 43	uuuuuu/bbmmmm:bww0077www007700770077	I
    //   26: istore_2
    //   27: getstatic 41	uuuuuu/bbmmmm:b00770077wwww007700770077	I
    //   30: istore_3
    //   31: getstatic 43	uuuuuu/bbmmmm:bww0077www007700770077	I
    //   34: istore 4
    //   36: ldc 2
    //   38: ldc_w 315
    //   41: bipush 69
    //   43: iconst_2
    //   44: invokestatic 73	xxxxxx/uxxxxx:bb00620062bb0062b0062b0062	(Ljava/lang/String;CC)Ljava/lang/String;
    //   47: iconst_0
    //   48: anewarray 33	java/lang/Class
    //   51: invokevirtual 55	java/lang/Class:getMethod	(Ljava/lang/String;[Ljava/lang/Class;)Ljava/lang/reflect/Method;
    //   54: astore 8
    //   56: aload 8
    //   58: aconst_null
    //   59: iconst_0
    //   60: anewarray 4	java/lang/Object
    //   63: invokevirtual 61	java/lang/reflect/Method:invoke	(Ljava/lang/Object;[Ljava/lang/Object;)Ljava/lang/Object;
    //   66: astore 8
    //   68: iload 4
    //   70: iload_3
    //   71: iadd
    //   72: iload_3
    //   73: imul
    //   74: aload 8
    //   76: checkcast 63	java/lang/Integer
    //   79: invokevirtual 67	java/lang/Integer:intValue	()I
    //   82: irem
    //   83: tableswitch	default:+17->100, 0:+65->148
    //   100: ldc 2
    //   102: ldc_w 317
    //   105: bipush 26
    //   107: iconst_0
    //   108: invokestatic 73	xxxxxx/uxxxxx:bb00620062bb0062b0062b0062	(Ljava/lang/String;CC)Ljava/lang/String;
    //   111: iconst_0
    //   112: anewarray 33	java/lang/Class
    //   115: invokevirtual 55	java/lang/Class:getMethod	(Ljava/lang/String;[Ljava/lang/Class;)Ljava/lang/reflect/Method;
    //   118: astore 8
    //   120: aload 8
    //   122: aconst_null
    //   123: iconst_0
    //   124: anewarray 4	java/lang/Object
    //   127: invokevirtual 61	java/lang/reflect/Method:invoke	(Ljava/lang/Object;[Ljava/lang/Object;)Ljava/lang/Object;
    //   130: astore 8
    //   132: aload 8
    //   134: checkcast 63	java/lang/Integer
    //   137: invokevirtual 67	java/lang/Integer:intValue	()I
    //   140: putstatic 41	uuuuuu/bbmmmm:b00770077wwww007700770077	I
    //   143: bipush 53
    //   145: putstatic 81	uuuuuu/bbmmmm:bw00770077www007700770077	I
    //   148: getstatic 41	uuuuuu/bbmmmm:b00770077wwww007700770077	I
    //   151: istore_3
    //   152: getstatic 77	uuuuuu/bbmmmm:b0077w0077www007700770077	I
    //   155: istore 4
    //   157: getstatic 41	uuuuuu/bbmmmm:b00770077wwww007700770077	I
    //   160: istore 5
    //   162: ldc 2
    //   164: ldc_w 319
    //   167: sipush 143
    //   170: bipush 14
    //   172: iconst_3
    //   173: invokestatic 51	xxxxxx/uxxxxx:bbbb0062b0062b0062b0062	(Ljava/lang/String;CCC)Ljava/lang/String;
    //   176: iconst_0
    //   177: anewarray 33	java/lang/Class
    //   180: invokevirtual 55	java/lang/Class:getMethod	(Ljava/lang/String;[Ljava/lang/Class;)Ljava/lang/reflect/Method;
    //   183: astore 8
    //   185: aload 8
    //   187: aconst_null
    //   188: iconst_0
    //   189: anewarray 4	java/lang/Object
    //   192: invokevirtual 61	java/lang/reflect/Method:invoke	(Ljava/lang/Object;[Ljava/lang/Object;)Ljava/lang/Object;
    //   195: astore 8
    //   197: aload 8
    //   199: checkcast 63	java/lang/Integer
    //   202: invokevirtual 67	java/lang/Integer:intValue	()I
    //   205: iload 5
    //   207: iadd
    //   208: getstatic 41	uuuuuu/bbmmmm:b00770077wwww007700770077	I
    //   211: imul
    //   212: getstatic 77	uuuuuu/bbmmmm:b0077w0077www007700770077	I
    //   215: irem
    //   216: getstatic 81	uuuuuu/bbmmmm:bw00770077www007700770077	I
    //   219: if_icmpeq +52 -> 271
    //   222: bipush 49
    //   224: putstatic 41	uuuuuu/bbmmmm:b00770077wwww007700770077	I
    //   227: ldc 2
    //   229: ldc_w 321
    //   232: sipush 200
    //   235: iconst_2
    //   236: invokestatic 73	xxxxxx/uxxxxx:bb00620062bb0062b0062b0062	(Ljava/lang/String;CC)Ljava/lang/String;
    //   239: iconst_0
    //   240: anewarray 33	java/lang/Class
    //   243: invokevirtual 55	java/lang/Class:getMethod	(Ljava/lang/String;[Ljava/lang/Class;)Ljava/lang/reflect/Method;
    //   246: astore 8
    //   248: aload 8
    //   250: aconst_null
    //   251: iconst_0
    //   252: anewarray 4	java/lang/Object
    //   255: invokevirtual 61	java/lang/reflect/Method:invoke	(Ljava/lang/Object;[Ljava/lang/Object;)Ljava/lang/Object;
    //   258: astore 8
    //   260: aload 8
    //   262: checkcast 63	java/lang/Integer
    //   265: invokevirtual 67	java/lang/Integer:intValue	()I
    //   268: putstatic 81	uuuuuu/bbmmmm:bw00770077www007700770077	I
    //   271: ldc 2
    //   273: ldc_w 323
    //   276: bipush 82
    //   278: bipush 109
    //   280: iconst_3
    //   281: invokestatic 51	xxxxxx/uxxxxx:bbbb0062b0062b0062b0062	(Ljava/lang/String;CCC)Ljava/lang/String;
    //   284: iconst_0
    //   285: anewarray 33	java/lang/Class
    //   288: invokevirtual 55	java/lang/Class:getMethod	(Ljava/lang/String;[Ljava/lang/Class;)Ljava/lang/reflect/Method;
    //   291: astore 8
    //   293: aload 8
    //   295: aconst_null
    //   296: iconst_0
    //   297: anewarray 4	java/lang/Object
    //   300: invokevirtual 61	java/lang/reflect/Method:invoke	(Ljava/lang/Object;[Ljava/lang/Object;)Ljava/lang/Object;
    //   303: astore 8
    //   305: iload_2
    //   306: iload_1
    //   307: iadd
    //   308: iload_3
    //   309: imul
    //   310: iload 4
    //   312: irem
    //   313: aload 8
    //   315: checkcast 63	java/lang/Integer
    //   318: invokevirtual 67	java/lang/Integer:intValue	()I
    //   321: if_icmpeq +174 -> 495
    //   324: ldc 2
    //   326: ldc_w 325
    //   329: sipush 235
    //   332: iconst_2
    //   333: invokestatic 73	xxxxxx/uxxxxx:bb00620062bb0062b0062b0062	(Ljava/lang/String;CC)Ljava/lang/String;
    //   336: iconst_0
    //   337: anewarray 33	java/lang/Class
    //   340: invokevirtual 55	java/lang/Class:getMethod	(Ljava/lang/String;[Ljava/lang/Class;)Ljava/lang/reflect/Method;
    //   343: astore 8
    //   345: aload 8
    //   347: aconst_null
    //   348: iconst_0
    //   349: anewarray 4	java/lang/Object
    //   352: invokevirtual 61	java/lang/reflect/Method:invoke	(Ljava/lang/Object;[Ljava/lang/Object;)Ljava/lang/Object;
    //   355: astore 8
    //   357: aload 8
    //   359: checkcast 63	java/lang/Integer
    //   362: invokevirtual 67	java/lang/Integer:intValue	()I
    //   365: putstatic 41	uuuuuu/bbmmmm:b00770077wwww007700770077	I
    //   368: ldc 2
    //   370: ldc_w 327
    //   373: sipush 233
    //   376: iconst_2
    //   377: invokestatic 73	xxxxxx/uxxxxx:bb00620062bb0062b0062b0062	(Ljava/lang/String;CC)Ljava/lang/String;
    //   380: iconst_0
    //   381: anewarray 33	java/lang/Class
    //   384: invokevirtual 55	java/lang/Class:getMethod	(Ljava/lang/String;[Ljava/lang/Class;)Ljava/lang/reflect/Method;
    //   387: astore 8
    //   389: aload 8
    //   391: aconst_null
    //   392: iconst_0
    //   393: anewarray 4	java/lang/Object
    //   396: invokevirtual 61	java/lang/reflect/Method:invoke	(Ljava/lang/Object;[Ljava/lang/Object;)Ljava/lang/Object;
    //   399: astore 8
    //   401: aload 8
    //   403: checkcast 63	java/lang/Integer
    //   406: invokevirtual 67	java/lang/Integer:intValue	()I
    //   409: putstatic 81	uuuuuu/bbmmmm:bw00770077www007700770077	I
    //   412: getstatic 41	uuuuuu/bbmmmm:b00770077wwww007700770077	I
    //   415: istore_1
    //   416: iload_1
    //   417: getstatic 43	uuuuuu/bbmmmm:bww0077www007700770077	I
    //   420: iload_1
    //   421: iadd
    //   422: imul
    //   423: getstatic 77	uuuuuu/bbmmmm:b0077w0077www007700770077	I
    //   426: irem
    //   427: tableswitch	default:+17->444, 0:+68->495
    //   444: bipush 21
    //   446: putstatic 41	uuuuuu/bbmmmm:b00770077wwww007700770077	I
    //   449: ldc 2
    //   451: ldc_w 329
    //   454: bipush 31
    //   456: sipush 139
    //   459: iconst_1
    //   460: invokestatic 51	xxxxxx/uxxxxx:bbbb0062b0062b0062b0062	(Ljava/lang/String;CCC)Ljava/lang/String;
    //   463: iconst_0
    //   464: anewarray 33	java/lang/Class
    //   467: invokevirtual 55	java/lang/Class:getMethod	(Ljava/lang/String;[Ljava/lang/Class;)Ljava/lang/reflect/Method;
    //   470: astore 8
    //   472: aload 8
    //   474: aconst_null
    //   475: iconst_0
    //   476: anewarray 4	java/lang/Object
    //   479: invokevirtual 61	java/lang/reflect/Method:invoke	(Ljava/lang/Object;[Ljava/lang/Object;)Ljava/lang/Object;
    //   482: astore 8
    //   484: aload 8
    //   486: checkcast 63	java/lang/Integer
    //   489: invokevirtual 67	java/lang/Integer:intValue	()I
    //   492: putstatic 81	uuuuuu/bbmmmm:bw00770077www007700770077	I
    //   495: aload 6
    //   497: aload 7
    //   499: invokeinterface 333 2 0
    //   504: ifeq +8 -> 512
    //   507: aload_0
    //   508: aconst_null
    //   509: putfield 313	uuuuuu/bbmmmm:b0077wwwww007700770077	Lcom/db/pwcc/dbmobile/foundation/data/manager/broadcasting/ModelUpdatedBroadcastReceiver;
    //   512: return
    //   513: astore 6
    //   515: aload 6
    //   517: invokevirtual 93	java/lang/reflect/InvocationTargetException:getCause	()Ljava/lang/Throwable;
    //   520: athrow
    //   521: astore 6
    //   523: aload 6
    //   525: invokevirtual 93	java/lang/reflect/InvocationTargetException:getCause	()Ljava/lang/Throwable;
    //   528: athrow
    //   529: astore 6
    //   531: aload 6
    //   533: invokevirtual 93	java/lang/reflect/InvocationTargetException:getCause	()Ljava/lang/Throwable;
    //   536: athrow
    //   537: astore 6
    //   539: aload 6
    //   541: invokevirtual 93	java/lang/reflect/InvocationTargetException:getCause	()Ljava/lang/Throwable;
    //   544: athrow
    //   545: astore 6
    //   547: aload 6
    //   549: invokevirtual 93	java/lang/reflect/InvocationTargetException:getCause	()Ljava/lang/Throwable;
    //   552: athrow
    //   553: astore 6
    //   555: aload 6
    //   557: invokevirtual 93	java/lang/reflect/InvocationTargetException:getCause	()Ljava/lang/Throwable;
    //   560: athrow
    //   561: astore 6
    //   563: aload 6
    //   565: invokevirtual 93	java/lang/reflect/InvocationTargetException:getCause	()Ljava/lang/Throwable;
    //   568: athrow
    //   569: astore 6
    //   571: aload 6
    //   573: invokevirtual 93	java/lang/reflect/InvocationTargetException:getCause	()Ljava/lang/Throwable;
    //   576: athrow
    // Local variable table:
    //   start	length	slot	name	signature
    //   0	577	0	this	bbmmmm
    //   22	401	1	i	int
    //   26	282	2	j	int
    //   30	280	3	k	int
    //   34	279	4	m	int
    //   160	48	5	n	int
    //   11	485	6	localBmbbmm	bbmbmm.bmbbmm
    //   513	3	6	localInvocationTargetException1	InvocationTargetException
    //   521	3	6	localInvocationTargetException2	InvocationTargetException
    //   529	3	6	localInvocationTargetException3	InvocationTargetException
    //   537	3	6	localInvocationTargetException4	InvocationTargetException
    //   545	3	6	localInvocationTargetException5	InvocationTargetException
    //   553	3	6	localInvocationTargetException6	InvocationTargetException
    //   561	3	6	localInvocationTargetException7	InvocationTargetException
    //   569	3	6	localInvocationTargetException8	InvocationTargetException
    //   17	481	7	localModelUpdatedBroadcastReceiver	ModelUpdatedBroadcastReceiver
    //   54	431	8	localObject	Object
    // Exception table:
    //   from	to	target	type
    //   248	260	513	java/lang/reflect/InvocationTargetException
    //   56	68	521	java/lang/reflect/InvocationTargetException
    //   120	132	529	java/lang/reflect/InvocationTargetException
    //   185	197	537	java/lang/reflect/InvocationTargetException
    //   293	305	545	java/lang/reflect/InvocationTargetException
    //   345	357	553	java/lang/reflect/InvocationTargetException
    //   389	401	561	java/lang/reflect/InvocationTargetException
    //   472	484	569	java/lang/reflect/InvocationTargetException
  }
  
  /* Error */
  public void b006Foo006F006Foo006Fo006F()
  {
    // Byte code:
    //   0: ldc 2
    //   2: ldc_w 336
    //   5: sipush 137
    //   8: iconst_0
    //   9: invokestatic 73	xxxxxx/uxxxxx:bb00620062bb0062b0062b0062	(Ljava/lang/String;CC)Ljava/lang/String;
    //   12: iconst_0
    //   13: anewarray 33	java/lang/Class
    //   16: invokevirtual 55	java/lang/Class:getMethod	(Ljava/lang/String;[Ljava/lang/Class;)Ljava/lang/reflect/Method;
    //   19: astore_3
    //   20: aload_3
    //   21: aload_0
    //   22: iconst_0
    //   23: anewarray 4	java/lang/Object
    //   26: invokevirtual 61	java/lang/reflect/Method:invoke	(Ljava/lang/Object;[Ljava/lang/Object;)Ljava/lang/Object;
    //   29: pop
    //   30: aload_0
    //   31: getfield 100	uuuuuu/bbmmmm:bw0077wwww007700770077	Luuuuuu/bbmbmm$bmbbmm;
    //   34: invokeinterface 339 1 0
    //   39: ifeq +413 -> 452
    //   42: aload_0
    //   43: getfield 278	uuuuuu/bbmmmm:bwwwwww007700770077	Luuuuuu/qpqqqq;
    //   46: invokeinterface 343 1 0
    //   51: astore_3
    //   52: getstatic 41	uuuuuu/bbmmmm:b00770077wwww007700770077	I
    //   55: getstatic 43	uuuuuu/bbmmmm:bww0077www007700770077	I
    //   58: iadd
    //   59: getstatic 41	uuuuuu/bbmmmm:b00770077wwww007700770077	I
    //   62: imul
    //   63: getstatic 77	uuuuuu/bbmmmm:b0077w0077www007700770077	I
    //   66: irem
    //   67: getstatic 81	uuuuuu/bbmmmm:bw00770077www007700770077	I
    //   70: if_icmpeq +331 -> 401
    //   73: ldc 2
    //   75: ldc_w 345
    //   78: bipush 46
    //   80: iconst_2
    //   81: invokestatic 73	xxxxxx/uxxxxx:bb00620062bb0062b0062b0062	(Ljava/lang/String;CC)Ljava/lang/String;
    //   84: iconst_0
    //   85: anewarray 33	java/lang/Class
    //   88: invokevirtual 55	java/lang/Class:getMethod	(Ljava/lang/String;[Ljava/lang/Class;)Ljava/lang/reflect/Method;
    //   91: astore 4
    //   93: aload 4
    //   95: aconst_null
    //   96: iconst_0
    //   97: anewarray 4	java/lang/Object
    //   100: invokevirtual 61	java/lang/reflect/Method:invoke	(Ljava/lang/Object;[Ljava/lang/Object;)Ljava/lang/Object;
    //   103: astore 4
    //   105: aload 4
    //   107: checkcast 63	java/lang/Integer
    //   110: invokevirtual 67	java/lang/Integer:intValue	()I
    //   113: putstatic 41	uuuuuu/bbmmmm:b00770077wwww007700770077	I
    //   116: getstatic 41	uuuuuu/bbmmmm:b00770077wwww007700770077	I
    //   119: getstatic 43	uuuuuu/bbmmmm:bww0077www007700770077	I
    //   122: iadd
    //   123: getstatic 41	uuuuuu/bbmmmm:b00770077wwww007700770077	I
    //   126: imul
    //   127: getstatic 77	uuuuuu/bbmmmm:b0077w0077www007700770077	I
    //   130: irem
    //   131: getstatic 81	uuuuuu/bbmmmm:bw00770077www007700770077	I
    //   134: if_icmpeq +262 -> 396
    //   137: getstatic 41	uuuuuu/bbmmmm:b00770077wwww007700770077	I
    //   140: istore_1
    //   141: iload_1
    //   142: getstatic 43	uuuuuu/bbmmmm:bww0077www007700770077	I
    //   145: iload_1
    //   146: iadd
    //   147: imul
    //   148: getstatic 77	uuuuuu/bbmmmm:b0077w0077www007700770077	I
    //   151: irem
    //   152: tableswitch	default:+20->172, 0:+110->262
    //   172: ldc 2
    //   174: ldc_w 347
    //   177: sipush 152
    //   180: bipush 105
    //   182: iconst_1
    //   183: invokestatic 51	xxxxxx/uxxxxx:bbbb0062b0062b0062b0062	(Ljava/lang/String;CCC)Ljava/lang/String;
    //   186: iconst_0
    //   187: anewarray 33	java/lang/Class
    //   190: invokevirtual 55	java/lang/Class:getMethod	(Ljava/lang/String;[Ljava/lang/Class;)Ljava/lang/reflect/Method;
    //   193: astore 4
    //   195: aload 4
    //   197: aconst_null
    //   198: iconst_0
    //   199: anewarray 4	java/lang/Object
    //   202: invokevirtual 61	java/lang/reflect/Method:invoke	(Ljava/lang/Object;[Ljava/lang/Object;)Ljava/lang/Object;
    //   205: astore 4
    //   207: aload 4
    //   209: checkcast 63	java/lang/Integer
    //   212: invokevirtual 67	java/lang/Integer:intValue	()I
    //   215: putstatic 41	uuuuuu/bbmmmm:b00770077wwww007700770077	I
    //   218: ldc 2
    //   220: ldc_w 349
    //   223: sipush 176
    //   226: iconst_0
    //   227: invokestatic 73	xxxxxx/uxxxxx:bb00620062bb0062b0062b0062	(Ljava/lang/String;CC)Ljava/lang/String;
    //   230: iconst_0
    //   231: anewarray 33	java/lang/Class
    //   234: invokevirtual 55	java/lang/Class:getMethod	(Ljava/lang/String;[Ljava/lang/Class;)Ljava/lang/reflect/Method;
    //   237: astore 4
    //   239: aload 4
    //   241: aconst_null
    //   242: iconst_0
    //   243: anewarray 4	java/lang/Object
    //   246: invokevirtual 61	java/lang/reflect/Method:invoke	(Ljava/lang/Object;[Ljava/lang/Object;)Ljava/lang/Object;
    //   249: astore 4
    //   251: aload 4
    //   253: checkcast 63	java/lang/Integer
    //   256: invokevirtual 67	java/lang/Integer:intValue	()I
    //   259: putstatic 81	uuuuuu/bbmmmm:bw00770077www007700770077	I
    //   262: ldc 2
    //   264: ldc_w 351
    //   267: sipush 191
    //   270: iconst_3
    //   271: invokestatic 73	xxxxxx/uxxxxx:bb00620062bb0062b0062b0062	(Ljava/lang/String;CC)Ljava/lang/String;
    //   274: iconst_0
    //   275: anewarray 33	java/lang/Class
    //   278: invokevirtual 55	java/lang/Class:getMethod	(Ljava/lang/String;[Ljava/lang/Class;)Ljava/lang/reflect/Method;
    //   281: astore 4
    //   283: aload 4
    //   285: aconst_null
    //   286: iconst_0
    //   287: anewarray 4	java/lang/Object
    //   290: invokevirtual 61	java/lang/reflect/Method:invoke	(Ljava/lang/Object;[Ljava/lang/Object;)Ljava/lang/Object;
    //   293: astore 4
    //   295: aload 4
    //   297: checkcast 63	java/lang/Integer
    //   300: invokevirtual 67	java/lang/Integer:intValue	()I
    //   303: istore_1
    //   304: getstatic 41	uuuuuu/bbmmmm:b00770077wwww007700770077	I
    //   307: istore_2
    //   308: iload_2
    //   309: getstatic 43	uuuuuu/bbmmmm:bww0077www007700770077	I
    //   312: iload_2
    //   313: iadd
    //   314: imul
    //   315: getstatic 77	uuuuuu/bbmmmm:b0077w0077www007700770077	I
    //   318: irem
    //   319: tableswitch	default:+17->336, 0:+68->387
    //   336: ldc 2
    //   338: ldc_w 353
    //   341: sipush 234
    //   344: bipush 89
    //   346: iconst_2
    //   347: invokestatic 51	xxxxxx/uxxxxx:bbbb0062b0062b0062b0062	(Ljava/lang/String;CCC)Ljava/lang/String;
    //   350: iconst_0
    //   351: anewarray 33	java/lang/Class
    //   354: invokevirtual 55	java/lang/Class:getMethod	(Ljava/lang/String;[Ljava/lang/Class;)Ljava/lang/reflect/Method;
    //   357: astore 4
    //   359: aload 4
    //   361: aconst_null
    //   362: iconst_0
    //   363: anewarray 4	java/lang/Object
    //   366: invokevirtual 61	java/lang/reflect/Method:invoke	(Ljava/lang/Object;[Ljava/lang/Object;)Ljava/lang/Object;
    //   369: astore 4
    //   371: aload 4
    //   373: checkcast 63	java/lang/Integer
    //   376: invokevirtual 67	java/lang/Integer:intValue	()I
    //   379: putstatic 41	uuuuuu/bbmmmm:b00770077wwww007700770077	I
    //   382: bipush 14
    //   384: putstatic 81	uuuuuu/bbmmmm:bw00770077www007700770077	I
    //   387: iload_1
    //   388: putstatic 41	uuuuuu/bbmmmm:b00770077wwww007700770077	I
    //   391: bipush 9
    //   393: putstatic 81	uuuuuu/bbmmmm:bw00770077www007700770077	I
    //   396: bipush 27
    //   398: putstatic 81	uuuuuu/bbmmmm:bw00770077www007700770077	I
    //   401: aload_3
    //   402: ifnull +43 -> 445
    //   405: ldc 2
    //   407: ldc_w 355
    //   410: bipush 87
    //   412: iconst_3
    //   413: invokestatic 73	xxxxxx/uxxxxx:bb00620062bb0062b0062b0062	(Ljava/lang/String;CC)Ljava/lang/String;
    //   416: iconst_1
    //   417: anewarray 33	java/lang/Class
    //   420: dup
    //   421: iconst_0
    //   422: ldc 122
    //   424: aastore
    //   425: invokevirtual 55	java/lang/Class:getMethod	(Ljava/lang/String;[Ljava/lang/Class;)Ljava/lang/reflect/Method;
    //   428: astore 4
    //   430: aload 4
    //   432: aload_0
    //   433: iconst_1
    //   434: anewarray 4	java/lang/Object
    //   437: dup
    //   438: iconst_0
    //   439: aload_3
    //   440: aastore
    //   441: invokevirtual 61	java/lang/reflect/Method:invoke	(Ljava/lang/Object;[Ljava/lang/Object;)Ljava/lang/Object;
    //   444: pop
    //   445: return
    //   446: astore_3
    //   447: aload_3
    //   448: invokevirtual 93	java/lang/reflect/InvocationTargetException:getCause	()Ljava/lang/Throwable;
    //   451: athrow
    //   452: aload_0
    //   453: getfield 100	uuuuuu/bbmmmm:bw0077wwww007700770077	Luuuuuu/bbmbmm$bmbbmm;
    //   456: invokeinterface 358 1 0
    //   461: return
    //   462: astore_3
    //   463: aload_3
    //   464: invokevirtual 93	java/lang/reflect/InvocationTargetException:getCause	()Ljava/lang/Throwable;
    //   467: athrow
    //   468: astore_3
    //   469: aload_3
    //   470: invokevirtual 93	java/lang/reflect/InvocationTargetException:getCause	()Ljava/lang/Throwable;
    //   473: athrow
    //   474: astore_3
    //   475: aload_3
    //   476: invokevirtual 93	java/lang/reflect/InvocationTargetException:getCause	()Ljava/lang/Throwable;
    //   479: athrow
    //   480: astore_3
    //   481: aload_3
    //   482: invokevirtual 93	java/lang/reflect/InvocationTargetException:getCause	()Ljava/lang/Throwable;
    //   485: athrow
    //   486: astore_3
    //   487: aload_3
    //   488: invokevirtual 93	java/lang/reflect/InvocationTargetException:getCause	()Ljava/lang/Throwable;
    //   491: athrow
    //   492: astore_3
    //   493: aload_3
    //   494: invokevirtual 93	java/lang/reflect/InvocationTargetException:getCause	()Ljava/lang/Throwable;
    //   497: athrow
    // Local variable table:
    //   start	length	slot	name	signature
    //   0	498	0	this	bbmmmm
    //   140	248	1	i	int
    //   307	8	2	j	int
    //   19	421	3	localObject1	Object
    //   446	2	3	localInvocationTargetException1	InvocationTargetException
    //   462	2	3	localInvocationTargetException2	InvocationTargetException
    //   468	2	3	localInvocationTargetException3	InvocationTargetException
    //   474	2	3	localInvocationTargetException4	InvocationTargetException
    //   480	2	3	localInvocationTargetException5	InvocationTargetException
    //   486	2	3	localInvocationTargetException6	InvocationTargetException
    //   492	2	3	localInvocationTargetException7	InvocationTargetException
    //   91	340	4	localObject2	Object
    // Exception table:
    //   from	to	target	type
    //   20	30	446	java/lang/reflect/InvocationTargetException
    //   93	105	462	java/lang/reflect/InvocationTargetException
    //   283	295	468	java/lang/reflect/InvocationTargetException
    //   430	445	474	java/lang/reflect/InvocationTargetException
    //   195	207	480	java/lang/reflect/InvocationTargetException
    //   239	251	486	java/lang/reflect/InvocationTargetException
    //   359	371	492	java/lang/reflect/InvocationTargetException
  }
  
  /* Error */
  public void b006Foooo006Fo006Fo006F(com.db.pwcc.dbmobile.model.banking.FinancialOverviewData paramFinancialOverviewData)
  {
    // Byte code:
    //   0: ldc 2
    //   2: ldc_w 361
    //   5: sipush 152
    //   8: iconst_1
    //   9: invokestatic 73	xxxxxx/uxxxxx:bb00620062bb0062b0062b0062	(Ljava/lang/String;CC)Ljava/lang/String;
    //   12: iconst_1
    //   13: anewarray 33	java/lang/Class
    //   16: dup
    //   17: iconst_0
    //   18: ldc 122
    //   20: aastore
    //   21: invokevirtual 55	java/lang/Class:getMethod	(Ljava/lang/String;[Ljava/lang/Class;)Ljava/lang/reflect/Method;
    //   24: astore 5
    //   26: aload 5
    //   28: aload_0
    //   29: iconst_1
    //   30: anewarray 4	java/lang/Object
    //   33: dup
    //   34: iconst_0
    //   35: aload_1
    //   36: aastore
    //   37: invokevirtual 61	java/lang/reflect/Method:invoke	(Ljava/lang/Object;[Ljava/lang/Object;)Ljava/lang/Object;
    //   40: pop
    //   41: aload_0
    //   42: getfield 100	uuuuuu/bbmmmm:bw0077wwww007700770077	Luuuuuu/bbmbmm$bmbbmm;
    //   45: astore 5
    //   47: getstatic 41	uuuuuu/bbmmmm:b00770077wwww007700770077	I
    //   50: getstatic 43	uuuuuu/bbmmmm:bww0077www007700770077	I
    //   53: iadd
    //   54: getstatic 41	uuuuuu/bbmmmm:b00770077wwww007700770077	I
    //   57: imul
    //   58: getstatic 77	uuuuuu/bbmmmm:b0077w0077www007700770077	I
    //   61: irem
    //   62: getstatic 81	uuuuuu/bbmmmm:bw00770077www007700770077	I
    //   65: if_icmpeq +320 -> 385
    //   68: getstatic 41	uuuuuu/bbmmmm:b00770077wwww007700770077	I
    //   71: istore_2
    //   72: ldc 2
    //   74: ldc_w 363
    //   77: bipush 22
    //   79: iconst_2
    //   80: invokestatic 73	xxxxxx/uxxxxx:bb00620062bb0062b0062b0062	(Ljava/lang/String;CC)Ljava/lang/String;
    //   83: iconst_0
    //   84: anewarray 33	java/lang/Class
    //   87: invokevirtual 55	java/lang/Class:getMethod	(Ljava/lang/String;[Ljava/lang/Class;)Ljava/lang/reflect/Method;
    //   90: astore 6
    //   92: aload 6
    //   94: aconst_null
    //   95: iconst_0
    //   96: anewarray 4	java/lang/Object
    //   99: invokevirtual 61	java/lang/reflect/Method:invoke	(Ljava/lang/Object;[Ljava/lang/Object;)Ljava/lang/Object;
    //   102: astore 6
    //   104: aload 6
    //   106: checkcast 63	java/lang/Integer
    //   109: invokevirtual 67	java/lang/Integer:intValue	()I
    //   112: istore_3
    //   113: getstatic 41	uuuuuu/bbmmmm:b00770077wwww007700770077	I
    //   116: istore 4
    //   118: getstatic 41	uuuuuu/bbmmmm:b00770077wwww007700770077	I
    //   121: getstatic 43	uuuuuu/bbmmmm:bww0077www007700770077	I
    //   124: iadd
    //   125: getstatic 41	uuuuuu/bbmmmm:b00770077wwww007700770077	I
    //   128: imul
    //   129: getstatic 77	uuuuuu/bbmmmm:b0077w0077www007700770077	I
    //   132: irem
    //   133: getstatic 81	uuuuuu/bbmmmm:bw00770077www007700770077	I
    //   136: if_icmpeq +53 -> 189
    //   139: bipush 44
    //   141: putstatic 41	uuuuuu/bbmmmm:b00770077wwww007700770077	I
    //   144: ldc 2
    //   146: ldc_w 365
    //   149: bipush 39
    //   151: bipush 8
    //   153: iconst_1
    //   154: invokestatic 51	xxxxxx/uxxxxx:bbbb0062b0062b0062b0062	(Ljava/lang/String;CCC)Ljava/lang/String;
    //   157: iconst_0
    //   158: anewarray 33	java/lang/Class
    //   161: invokevirtual 55	java/lang/Class:getMethod	(Ljava/lang/String;[Ljava/lang/Class;)Ljava/lang/reflect/Method;
    //   164: astore 6
    //   166: aload 6
    //   168: aconst_null
    //   169: iconst_0
    //   170: anewarray 4	java/lang/Object
    //   173: invokevirtual 61	java/lang/reflect/Method:invoke	(Ljava/lang/Object;[Ljava/lang/Object;)Ljava/lang/Object;
    //   176: astore 6
    //   178: aload 6
    //   180: checkcast 63	java/lang/Integer
    //   183: invokevirtual 67	java/lang/Integer:intValue	()I
    //   186: putstatic 81	uuuuuu/bbmmmm:bw00770077www007700770077	I
    //   189: iload_2
    //   190: iload_3
    //   191: iadd
    //   192: iload 4
    //   194: imul
    //   195: getstatic 77	uuuuuu/bbmmmm:b0077w0077www007700770077	I
    //   198: irem
    //   199: getstatic 81	uuuuuu/bbmmmm:bw00770077www007700770077	I
    //   202: if_icmpeq +52 -> 254
    //   205: ldc 2
    //   207: ldc_w 367
    //   210: sipush 229
    //   213: iconst_2
    //   214: invokestatic 73	xxxxxx/uxxxxx:bb00620062bb0062b0062b0062	(Ljava/lang/String;CC)Ljava/lang/String;
    //   217: iconst_0
    //   218: anewarray 33	java/lang/Class
    //   221: invokevirtual 55	java/lang/Class:getMethod	(Ljava/lang/String;[Ljava/lang/Class;)Ljava/lang/reflect/Method;
    //   224: astore 6
    //   226: aload 6
    //   228: aconst_null
    //   229: iconst_0
    //   230: anewarray 4	java/lang/Object
    //   233: invokevirtual 61	java/lang/reflect/Method:invoke	(Ljava/lang/Object;[Ljava/lang/Object;)Ljava/lang/Object;
    //   236: astore 6
    //   238: aload 6
    //   240: checkcast 63	java/lang/Integer
    //   243: invokevirtual 67	java/lang/Integer:intValue	()I
    //   246: putstatic 41	uuuuuu/bbmmmm:b00770077wwww007700770077	I
    //   249: bipush 98
    //   251: putstatic 81	uuuuuu/bbmmmm:bw00770077www007700770077	I
    //   254: bipush 10
    //   256: putstatic 41	uuuuuu/bbmmmm:b00770077wwww007700770077	I
    //   259: bipush 30
    //   261: putstatic 81	uuuuuu/bbmmmm:bw00770077www007700770077	I
    //   264: getstatic 41	uuuuuu/bbmmmm:b00770077wwww007700770077	I
    //   267: istore_2
    //   268: ldc 2
    //   270: ldc_w 369
    //   273: bipush 59
    //   275: bipush 38
    //   277: iconst_3
    //   278: invokestatic 51	xxxxxx/uxxxxx:bbbb0062b0062b0062b0062	(Ljava/lang/String;CCC)Ljava/lang/String;
    //   281: iconst_0
    //   282: anewarray 33	java/lang/Class
    //   285: invokevirtual 55	java/lang/Class:getMethod	(Ljava/lang/String;[Ljava/lang/Class;)Ljava/lang/reflect/Method;
    //   288: astore 6
    //   290: aload 6
    //   292: aconst_null
    //   293: iconst_0
    //   294: anewarray 4	java/lang/Object
    //   297: invokevirtual 61	java/lang/reflect/Method:invoke	(Ljava/lang/Object;[Ljava/lang/Object;)Ljava/lang/Object;
    //   300: astore 6
    //   302: aload 6
    //   304: checkcast 63	java/lang/Integer
    //   307: invokevirtual 67	java/lang/Integer:intValue	()I
    //   310: iload_2
    //   311: iadd
    //   312: iload_2
    //   313: imul
    //   314: getstatic 77	uuuuuu/bbmmmm:b0077w0077www007700770077	I
    //   317: irem
    //   318: tableswitch	default:+18->336, 0:+67->385
    //   336: bipush 39
    //   338: putstatic 41	uuuuuu/bbmmmm:b00770077wwww007700770077	I
    //   341: ldc 2
    //   343: ldc_w 371
    //   346: sipush 175
    //   349: iconst_5
    //   350: invokestatic 73	xxxxxx/uxxxxx:bb00620062bb0062b0062b0062	(Ljava/lang/String;CC)Ljava/lang/String;
    //   353: iconst_0
    //   354: anewarray 33	java/lang/Class
    //   357: invokevirtual 55	java/lang/Class:getMethod	(Ljava/lang/String;[Ljava/lang/Class;)Ljava/lang/reflect/Method;
    //   360: astore 6
    //   362: aload 6
    //   364: aconst_null
    //   365: iconst_0
    //   366: anewarray 4	java/lang/Object
    //   369: invokevirtual 61	java/lang/reflect/Method:invoke	(Ljava/lang/Object;[Ljava/lang/Object;)Ljava/lang/Object;
    //   372: astore 6
    //   374: aload 6
    //   376: checkcast 63	java/lang/Integer
    //   379: invokevirtual 67	java/lang/Integer:intValue	()I
    //   382: putstatic 81	uuuuuu/bbmmmm:bw00770077www007700770077	I
    //   385: aload 5
    //   387: aload_1
    //   388: invokeinterface 374 2 0
    //   393: return
    //   394: astore_1
    //   395: aload_1
    //   396: invokevirtual 93	java/lang/reflect/InvocationTargetException:getCause	()Ljava/lang/Throwable;
    //   399: athrow
    //   400: astore_1
    //   401: aload_1
    //   402: invokevirtual 93	java/lang/reflect/InvocationTargetException:getCause	()Ljava/lang/Throwable;
    //   405: athrow
    //   406: astore_1
    //   407: aload_1
    //   408: invokevirtual 93	java/lang/reflect/InvocationTargetException:getCause	()Ljava/lang/Throwable;
    //   411: athrow
    //   412: astore_1
    //   413: aload_1
    //   414: invokevirtual 93	java/lang/reflect/InvocationTargetException:getCause	()Ljava/lang/Throwable;
    //   417: athrow
    //   418: astore_1
    //   419: aload_1
    //   420: invokevirtual 93	java/lang/reflect/InvocationTargetException:getCause	()Ljava/lang/Throwable;
    //   423: athrow
    //   424: astore_1
    //   425: aload_1
    //   426: invokevirtual 93	java/lang/reflect/InvocationTargetException:getCause	()Ljava/lang/Throwable;
    //   429: athrow
    // Local variable table:
    //   start	length	slot	name	signature
    //   0	430	0	this	bbmmmm
    //   0	430	1	paramFinancialOverviewData	com.db.pwcc.dbmobile.model.banking.FinancialOverviewData
    //   71	243	2	i	int
    //   112	80	3	j	int
    //   116	79	4	k	int
    //   24	362	5	localObject1	Object
    //   90	285	6	localObject2	Object
    // Exception table:
    //   from	to	target	type
    //   226	238	394	java/lang/reflect/InvocationTargetException
    //   26	41	400	java/lang/reflect/InvocationTargetException
    //   92	104	406	java/lang/reflect/InvocationTargetException
    //   290	302	412	java/lang/reflect/InvocationTargetException
    //   362	374	418	java/lang/reflect/InvocationTargetException
    //   166	178	424	java/lang/reflect/InvocationTargetException
  }
  
  /* Error */
  public void bo006F006Foo006Fo006Fo006F()
  {
    // Byte code:
    //   0: ldc 2
    //   2: ldc_w 377
    //   5: sipush 190
    //   8: iconst_1
    //   9: invokestatic 73	xxxxxx/uxxxxx:bb00620062bb0062b0062b0062	(Ljava/lang/String;CC)Ljava/lang/String;
    //   12: iconst_0
    //   13: anewarray 33	java/lang/Class
    //   16: invokevirtual 55	java/lang/Class:getMethod	(Ljava/lang/String;[Ljava/lang/Class;)Ljava/lang/reflect/Method;
    //   19: astore_3
    //   20: aload_3
    //   21: aconst_null
    //   22: iconst_0
    //   23: anewarray 4	java/lang/Object
    //   26: invokevirtual 61	java/lang/reflect/Method:invoke	(Ljava/lang/Object;[Ljava/lang/Object;)Ljava/lang/Object;
    //   29: astore_3
    //   30: aload_3
    //   31: checkcast 63	java/lang/Integer
    //   34: invokevirtual 67	java/lang/Integer:intValue	()I
    //   37: istore_1
    //   38: getstatic 43	uuuuuu/bbmmmm:bww0077www007700770077	I
    //   41: istore_2
    //   42: ldc 2
    //   44: ldc_w 379
    //   47: bipush 115
    //   49: iconst_0
    //   50: invokestatic 73	xxxxxx/uxxxxx:bb00620062bb0062b0062b0062	(Ljava/lang/String;CC)Ljava/lang/String;
    //   53: iconst_0
    //   54: anewarray 33	java/lang/Class
    //   57: invokevirtual 55	java/lang/Class:getMethod	(Ljava/lang/String;[Ljava/lang/Class;)Ljava/lang/reflect/Method;
    //   60: astore_3
    //   61: aload_3
    //   62: aconst_null
    //   63: iconst_0
    //   64: anewarray 4	java/lang/Object
    //   67: invokevirtual 61	java/lang/reflect/Method:invoke	(Ljava/lang/Object;[Ljava/lang/Object;)Ljava/lang/Object;
    //   70: astore_3
    //   71: aload_3
    //   72: checkcast 63	java/lang/Integer
    //   75: invokevirtual 67	java/lang/Integer:intValue	()I
    //   78: iload_2
    //   79: iload_1
    //   80: iadd
    //   81: imul
    //   82: getstatic 77	uuuuuu/bbmmmm:b0077w0077www007700770077	I
    //   85: irem
    //   86: getstatic 81	uuuuuu/bbmmmm:bw00770077www007700770077	I
    //   89: if_icmpeq +317 -> 406
    //   92: getstatic 41	uuuuuu/bbmmmm:b00770077wwww007700770077	I
    //   95: getstatic 43	uuuuuu/bbmmmm:bww0077www007700770077	I
    //   98: iadd
    //   99: getstatic 41	uuuuuu/bbmmmm:b00770077wwww007700770077	I
    //   102: imul
    //   103: getstatic 77	uuuuuu/bbmmmm:b0077w0077www007700770077	I
    //   106: irem
    //   107: getstatic 81	uuuuuu/bbmmmm:bw00770077www007700770077	I
    //   110: if_icmpeq +47 -> 157
    //   113: bipush 17
    //   115: putstatic 41	uuuuuu/bbmmmm:b00770077wwww007700770077	I
    //   118: ldc 2
    //   120: ldc_w 381
    //   123: bipush 77
    //   125: iconst_2
    //   126: invokestatic 73	xxxxxx/uxxxxx:bb00620062bb0062b0062b0062	(Ljava/lang/String;CC)Ljava/lang/String;
    //   129: iconst_0
    //   130: anewarray 33	java/lang/Class
    //   133: invokevirtual 55	java/lang/Class:getMethod	(Ljava/lang/String;[Ljava/lang/Class;)Ljava/lang/reflect/Method;
    //   136: astore_3
    //   137: aload_3
    //   138: aconst_null
    //   139: iconst_0
    //   140: anewarray 4	java/lang/Object
    //   143: invokevirtual 61	java/lang/reflect/Method:invoke	(Ljava/lang/Object;[Ljava/lang/Object;)Ljava/lang/Object;
    //   146: astore_3
    //   147: aload_3
    //   148: checkcast 63	java/lang/Integer
    //   151: invokevirtual 67	java/lang/Integer:intValue	()I
    //   154: putstatic 81	uuuuuu/bbmmmm:bw00770077www007700770077	I
    //   157: getstatic 41	uuuuuu/bbmmmm:b00770077wwww007700770077	I
    //   160: getstatic 43	uuuuuu/bbmmmm:bww0077www007700770077	I
    //   163: iadd
    //   164: getstatic 41	uuuuuu/bbmmmm:b00770077wwww007700770077	I
    //   167: imul
    //   168: getstatic 77	uuuuuu/bbmmmm:b0077w0077www007700770077	I
    //   171: irem
    //   172: getstatic 81	uuuuuu/bbmmmm:bw00770077www007700770077	I
    //   175: if_icmpeq +150 -> 325
    //   178: iconst_4
    //   179: putstatic 41	uuuuuu/bbmmmm:b00770077wwww007700770077	I
    //   182: ldc 2
    //   184: ldc_w 383
    //   187: bipush 57
    //   189: bipush 22
    //   191: iconst_2
    //   192: invokestatic 51	xxxxxx/uxxxxx:bbbb0062b0062b0062b0062	(Ljava/lang/String;CCC)Ljava/lang/String;
    //   195: iconst_0
    //   196: anewarray 33	java/lang/Class
    //   199: invokevirtual 55	java/lang/Class:getMethod	(Ljava/lang/String;[Ljava/lang/Class;)Ljava/lang/reflect/Method;
    //   202: astore_3
    //   203: aload_3
    //   204: aconst_null
    //   205: iconst_0
    //   206: anewarray 4	java/lang/Object
    //   209: invokevirtual 61	java/lang/reflect/Method:invoke	(Ljava/lang/Object;[Ljava/lang/Object;)Ljava/lang/Object;
    //   212: astore_3
    //   213: aload_3
    //   214: checkcast 63	java/lang/Integer
    //   217: invokevirtual 67	java/lang/Integer:intValue	()I
    //   220: putstatic 81	uuuuuu/bbmmmm:bw00770077www007700770077	I
    //   223: ldc 2
    //   225: ldc_w 385
    //   228: bipush 69
    //   230: iconst_4
    //   231: invokestatic 73	xxxxxx/uxxxxx:bb00620062bb0062b0062b0062	(Ljava/lang/String;CC)Ljava/lang/String;
    //   234: iconst_0
    //   235: anewarray 33	java/lang/Class
    //   238: invokevirtual 55	java/lang/Class:getMethod	(Ljava/lang/String;[Ljava/lang/Class;)Ljava/lang/reflect/Method;
    //   241: astore_3
    //   242: aload_3
    //   243: aconst_null
    //   244: iconst_0
    //   245: anewarray 4	java/lang/Object
    //   248: invokevirtual 61	java/lang/reflect/Method:invoke	(Ljava/lang/Object;[Ljava/lang/Object;)Ljava/lang/Object;
    //   251: astore_3
    //   252: aload_3
    //   253: checkcast 63	java/lang/Integer
    //   256: invokevirtual 67	java/lang/Integer:intValue	()I
    //   259: istore_1
    //   260: getstatic 43	uuuuuu/bbmmmm:bww0077www007700770077	I
    //   263: istore_2
    //   264: ldc 2
    //   266: ldc_w 387
    //   269: sipush 204
    //   272: iconst_5
    //   273: invokestatic 73	xxxxxx/uxxxxx:bb00620062bb0062b0062b0062	(Ljava/lang/String;CC)Ljava/lang/String;
    //   276: iconst_0
    //   277: anewarray 33	java/lang/Class
    //   280: invokevirtual 55	java/lang/Class:getMethod	(Ljava/lang/String;[Ljava/lang/Class;)Ljava/lang/reflect/Method;
    //   283: astore_3
    //   284: aload_3
    //   285: aconst_null
    //   286: iconst_0
    //   287: anewarray 4	java/lang/Object
    //   290: invokevirtual 61	java/lang/reflect/Method:invoke	(Ljava/lang/Object;[Ljava/lang/Object;)Ljava/lang/Object;
    //   293: astore_3
    //   294: aload_3
    //   295: checkcast 63	java/lang/Integer
    //   298: invokevirtual 67	java/lang/Integer:intValue	()I
    //   301: iload_2
    //   302: iload_1
    //   303: iadd
    //   304: imul
    //   305: getstatic 77	uuuuuu/bbmmmm:b0077w0077www007700770077	I
    //   308: irem
    //   309: getstatic 81	uuuuuu/bbmmmm:bw00770077www007700770077	I
    //   312: if_icmpeq +13 -> 325
    //   315: bipush 47
    //   317: putstatic 41	uuuuuu/bbmmmm:b00770077wwww007700770077	I
    //   320: bipush 11
    //   322: putstatic 81	uuuuuu/bbmmmm:bw00770077www007700770077	I
    //   325: ldc 2
    //   327: ldc_w 389
    //   330: bipush 27
    //   332: bipush 53
    //   334: iconst_0
    //   335: invokestatic 51	xxxxxx/uxxxxx:bbbb0062b0062b0062b0062	(Ljava/lang/String;CCC)Ljava/lang/String;
    //   338: iconst_0
    //   339: anewarray 33	java/lang/Class
    //   342: invokevirtual 55	java/lang/Class:getMethod	(Ljava/lang/String;[Ljava/lang/Class;)Ljava/lang/reflect/Method;
    //   345: astore_3
    //   346: aload_3
    //   347: aconst_null
    //   348: iconst_0
    //   349: anewarray 4	java/lang/Object
    //   352: invokevirtual 61	java/lang/reflect/Method:invoke	(Ljava/lang/Object;[Ljava/lang/Object;)Ljava/lang/Object;
    //   355: astore_3
    //   356: aload_3
    //   357: checkcast 63	java/lang/Integer
    //   360: invokevirtual 67	java/lang/Integer:intValue	()I
    //   363: putstatic 41	uuuuuu/bbmmmm:b00770077wwww007700770077	I
    //   366: ldc 2
    //   368: ldc_w 391
    //   371: sipush 138
    //   374: iconst_2
    //   375: invokestatic 73	xxxxxx/uxxxxx:bb00620062bb0062b0062b0062	(Ljava/lang/String;CC)Ljava/lang/String;
    //   378: iconst_0
    //   379: anewarray 33	java/lang/Class
    //   382: invokevirtual 55	java/lang/Class:getMethod	(Ljava/lang/String;[Ljava/lang/Class;)Ljava/lang/reflect/Method;
    //   385: astore_3
    //   386: aload_3
    //   387: aconst_null
    //   388: iconst_0
    //   389: anewarray 4	java/lang/Object
    //   392: invokevirtual 61	java/lang/reflect/Method:invoke	(Ljava/lang/Object;[Ljava/lang/Object;)Ljava/lang/Object;
    //   395: astore_3
    //   396: aload_3
    //   397: checkcast 63	java/lang/Integer
    //   400: invokevirtual 67	java/lang/Integer:intValue	()I
    //   403: putstatic 81	uuuuuu/bbmmmm:bw00770077www007700770077	I
    //   406: ldc 2
    //   408: ldc_w 393
    //   411: sipush 237
    //   414: sipush 186
    //   417: iconst_1
    //   418: invokestatic 51	xxxxxx/uxxxxx:bbbb0062b0062b0062b0062	(Ljava/lang/String;CCC)Ljava/lang/String;
    //   421: iconst_0
    //   422: anewarray 33	java/lang/Class
    //   425: invokevirtual 55	java/lang/Class:getMethod	(Ljava/lang/String;[Ljava/lang/Class;)Ljava/lang/reflect/Method;
    //   428: astore_3
    //   429: aload_3
    //   430: aload_0
    //   431: iconst_0
    //   432: anewarray 4	java/lang/Object
    //   435: invokevirtual 61	java/lang/reflect/Method:invoke	(Ljava/lang/Object;[Ljava/lang/Object;)Ljava/lang/Object;
    //   438: pop
    //   439: return
    //   440: astore_3
    //   441: aload_3
    //   442: invokevirtual 93	java/lang/reflect/InvocationTargetException:getCause	()Ljava/lang/Throwable;
    //   445: athrow
    //   446: astore_3
    //   447: aload_3
    //   448: invokevirtual 93	java/lang/reflect/InvocationTargetException:getCause	()Ljava/lang/Throwable;
    //   451: athrow
    //   452: astore_3
    //   453: aload_3
    //   454: invokevirtual 93	java/lang/reflect/InvocationTargetException:getCause	()Ljava/lang/Throwable;
    //   457: athrow
    //   458: astore_3
    //   459: aload_3
    //   460: invokevirtual 93	java/lang/reflect/InvocationTargetException:getCause	()Ljava/lang/Throwable;
    //   463: athrow
    //   464: astore_3
    //   465: aload_3
    //   466: invokevirtual 93	java/lang/reflect/InvocationTargetException:getCause	()Ljava/lang/Throwable;
    //   469: athrow
    //   470: astore_3
    //   471: aload_3
    //   472: invokevirtual 93	java/lang/reflect/InvocationTargetException:getCause	()Ljava/lang/Throwable;
    //   475: athrow
    //   476: astore_3
    //   477: aload_3
    //   478: invokevirtual 93	java/lang/reflect/InvocationTargetException:getCause	()Ljava/lang/Throwable;
    //   481: athrow
    //   482: astore_3
    //   483: aload_3
    //   484: invokevirtual 93	java/lang/reflect/InvocationTargetException:getCause	()Ljava/lang/Throwable;
    //   487: athrow
    //   488: astore_3
    //   489: aload_3
    //   490: invokevirtual 93	java/lang/reflect/InvocationTargetException:getCause	()Ljava/lang/Throwable;
    //   493: athrow
    // Local variable table:
    //   start	length	slot	name	signature
    //   0	494	0	this	bbmmmm
    //   37	267	1	i	int
    //   41	263	2	j	int
    //   19	411	3	localObject	Object
    //   440	2	3	localInvocationTargetException1	InvocationTargetException
    //   446	2	3	localInvocationTargetException2	InvocationTargetException
    //   452	2	3	localInvocationTargetException3	InvocationTargetException
    //   458	2	3	localInvocationTargetException4	InvocationTargetException
    //   464	2	3	localInvocationTargetException5	InvocationTargetException
    //   470	2	3	localInvocationTargetException6	InvocationTargetException
    //   476	2	3	localInvocationTargetException7	InvocationTargetException
    //   482	2	3	localInvocationTargetException8	InvocationTargetException
    //   488	2	3	localInvocationTargetException9	InvocationTargetException
    // Exception table:
    //   from	to	target	type
    //   346	356	440	java/lang/reflect/InvocationTargetException
    //   429	439	446	java/lang/reflect/InvocationTargetException
    //   20	30	452	java/lang/reflect/InvocationTargetException
    //   61	71	458	java/lang/reflect/InvocationTargetException
    //   386	396	464	java/lang/reflect/InvocationTargetException
    //   203	213	470	java/lang/reflect/InvocationTargetException
    //   242	252	476	java/lang/reflect/InvocationTargetException
    //   284	294	482	java/lang/reflect/InvocationTargetException
    //   137	147	488	java/lang/reflect/InvocationTargetException
  }
  
  /* Error */
  public void bo006Fooo006Fo006Fo006F()
  {
    // Byte code:
    //   0: getstatic 41	uuuuuu/bbmmmm:b00770077wwww007700770077	I
    //   3: istore_1
    //   4: ldc 2
    //   6: ldc_w 398
    //   9: bipush 112
    //   11: iconst_2
    //   12: invokestatic 73	xxxxxx/uxxxxx:bb00620062bb0062b0062b0062	(Ljava/lang/String;CC)Ljava/lang/String;
    //   15: iconst_0
    //   16: anewarray 33	java/lang/Class
    //   19: invokevirtual 55	java/lang/Class:getMethod	(Ljava/lang/String;[Ljava/lang/Class;)Ljava/lang/reflect/Method;
    //   22: astore_2
    //   23: aload_2
    //   24: aconst_null
    //   25: iconst_0
    //   26: anewarray 4	java/lang/Object
    //   29: invokevirtual 61	java/lang/reflect/Method:invoke	(Ljava/lang/Object;[Ljava/lang/Object;)Ljava/lang/Object;
    //   32: astore_2
    //   33: aload_2
    //   34: checkcast 63	java/lang/Integer
    //   37: invokevirtual 67	java/lang/Integer:intValue	()I
    //   40: iload_1
    //   41: iadd
    //   42: iload_1
    //   43: imul
    //   44: getstatic 77	uuuuuu/bbmmmm:b0077w0077www007700770077	I
    //   47: irem
    //   48: tableswitch	default:+20->68, 0:+68->116
    //   68: ldc 2
    //   70: ldc_w 321
    //   73: sipush 188
    //   76: sipush 139
    //   79: iconst_3
    //   80: invokestatic 51	xxxxxx/uxxxxx:bbbb0062b0062b0062b0062	(Ljava/lang/String;CCC)Ljava/lang/String;
    //   83: iconst_0
    //   84: anewarray 33	java/lang/Class
    //   87: invokevirtual 55	java/lang/Class:getMethod	(Ljava/lang/String;[Ljava/lang/Class;)Ljava/lang/reflect/Method;
    //   90: astore_2
    //   91: aload_2
    //   92: aconst_null
    //   93: iconst_0
    //   94: anewarray 4	java/lang/Object
    //   97: invokevirtual 61	java/lang/reflect/Method:invoke	(Ljava/lang/Object;[Ljava/lang/Object;)Ljava/lang/Object;
    //   100: astore_2
    //   101: aload_2
    //   102: checkcast 63	java/lang/Integer
    //   105: invokevirtual 67	java/lang/Integer:intValue	()I
    //   108: putstatic 41	uuuuuu/bbmmmm:b00770077wwww007700770077	I
    //   111: bipush 14
    //   113: putstatic 81	uuuuuu/bbmmmm:bw00770077www007700770077	I
    //   116: aload_0
    //   117: getfield 313	uuuuuu/bbmmmm:b0077wwwww007700770077	Lcom/db/pwcc/dbmobile/foundation/data/manager/broadcasting/ModelUpdatedBroadcastReceiver;
    //   120: ifnonnull +269 -> 389
    //   123: aload_0
    //   124: new 8	uuuuuu/bbmmmm$1
    //   127: dup
    //   128: aload_0
    //   129: invokespecial 401	uuuuuu/bbmmmm$1:<init>	(Luuuuuu/bbmmmm;)V
    //   132: putfield 313	uuuuuu/bbmmmm:b0077wwwww007700770077	Lcom/db/pwcc/dbmobile/foundation/data/manager/broadcasting/ModelUpdatedBroadcastReceiver;
    //   135: iconst_2
    //   136: istore_1
    //   137: iload_1
    //   138: iconst_0
    //   139: idiv
    //   140: istore_1
    //   141: goto -4 -> 137
    //   144: astore_2
    //   145: bipush 87
    //   147: putstatic 41	uuuuuu/bbmmmm:b00770077wwww007700770077	I
    //   150: getstatic 41	uuuuuu/bbmmmm:b00770077wwww007700770077	I
    //   153: getstatic 43	uuuuuu/bbmmmm:bww0077www007700770077	I
    //   156: iadd
    //   157: getstatic 41	uuuuuu/bbmmmm:b00770077wwww007700770077	I
    //   160: imul
    //   161: getstatic 77	uuuuuu/bbmmmm:b0077w0077www007700770077	I
    //   164: irem
    //   165: getstatic 81	uuuuuu/bbmmmm:bw00770077www007700770077	I
    //   168: if_icmpeq +84 -> 252
    //   171: ldc 2
    //   173: ldc_w 403
    //   176: sipush 138
    //   179: iconst_0
    //   180: invokestatic 73	xxxxxx/uxxxxx:bb00620062bb0062b0062b0062	(Ljava/lang/String;CC)Ljava/lang/String;
    //   183: iconst_0
    //   184: anewarray 33	java/lang/Class
    //   187: invokevirtual 55	java/lang/Class:getMethod	(Ljava/lang/String;[Ljava/lang/Class;)Ljava/lang/reflect/Method;
    //   190: astore_2
    //   191: aload_2
    //   192: aconst_null
    //   193: iconst_0
    //   194: anewarray 4	java/lang/Object
    //   197: invokevirtual 61	java/lang/reflect/Method:invoke	(Ljava/lang/Object;[Ljava/lang/Object;)Ljava/lang/Object;
    //   200: astore_2
    //   201: aload_2
    //   202: checkcast 63	java/lang/Integer
    //   205: invokevirtual 67	java/lang/Integer:intValue	()I
    //   208: putstatic 41	uuuuuu/bbmmmm:b00770077wwww007700770077	I
    //   211: ldc 2
    //   213: ldc_w 405
    //   216: bipush 92
    //   218: bipush 124
    //   220: iconst_1
    //   221: invokestatic 51	xxxxxx/uxxxxx:bbbb0062b0062b0062b0062	(Ljava/lang/String;CCC)Ljava/lang/String;
    //   224: iconst_0
    //   225: anewarray 33	java/lang/Class
    //   228: invokevirtual 55	java/lang/Class:getMethod	(Ljava/lang/String;[Ljava/lang/Class;)Ljava/lang/reflect/Method;
    //   231: astore_2
    //   232: aload_2
    //   233: aconst_null
    //   234: iconst_0
    //   235: anewarray 4	java/lang/Object
    //   238: invokevirtual 61	java/lang/reflect/Method:invoke	(Ljava/lang/Object;[Ljava/lang/Object;)Ljava/lang/Object;
    //   241: astore_2
    //   242: aload_2
    //   243: checkcast 63	java/lang/Integer
    //   246: invokevirtual 67	java/lang/Integer:intValue	()I
    //   249: putstatic 81	uuuuuu/bbmmmm:bw00770077www007700770077	I
    //   252: aload_0
    //   253: getfield 100	uuuuuu/bbmmmm:bw0077wwww007700770077	Luuuuuu/bbmbmm$bmbbmm;
    //   256: astore_2
    //   257: getstatic 41	uuuuuu/bbmmmm:b00770077wwww007700770077	I
    //   260: istore_1
    //   261: ldc 2
    //   263: ldc_w 407
    //   266: bipush 13
    //   268: iconst_4
    //   269: invokestatic 73	xxxxxx/uxxxxx:bb00620062bb0062b0062b0062	(Ljava/lang/String;CC)Ljava/lang/String;
    //   272: iconst_0
    //   273: anewarray 33	java/lang/Class
    //   276: invokevirtual 55	java/lang/Class:getMethod	(Ljava/lang/String;[Ljava/lang/Class;)Ljava/lang/reflect/Method;
    //   279: astore_3
    //   280: aload_3
    //   281: aconst_null
    //   282: iconst_0
    //   283: anewarray 4	java/lang/Object
    //   286: invokevirtual 61	java/lang/reflect/Method:invoke	(Ljava/lang/Object;[Ljava/lang/Object;)Ljava/lang/Object;
    //   289: astore_3
    //   290: aload_3
    //   291: checkcast 63	java/lang/Integer
    //   294: invokevirtual 67	java/lang/Integer:intValue	()I
    //   297: iload_1
    //   298: iadd
    //   299: iload_1
    //   300: imul
    //   301: getstatic 77	uuuuuu/bbmmmm:b0077w0077www007700770077	I
    //   304: irem
    //   305: tableswitch	default:+19->324, 0:+63->368
    //   324: ldc 2
    //   326: ldc -84
    //   328: sipush 247
    //   331: iconst_1
    //   332: invokestatic 73	xxxxxx/uxxxxx:bb00620062bb0062b0062b0062	(Ljava/lang/String;CC)Ljava/lang/String;
    //   335: iconst_0
    //   336: anewarray 33	java/lang/Class
    //   339: invokevirtual 55	java/lang/Class:getMethod	(Ljava/lang/String;[Ljava/lang/Class;)Ljava/lang/reflect/Method;
    //   342: astore_3
    //   343: aload_3
    //   344: aconst_null
    //   345: iconst_0
    //   346: anewarray 4	java/lang/Object
    //   349: invokevirtual 61	java/lang/reflect/Method:invoke	(Ljava/lang/Object;[Ljava/lang/Object;)Ljava/lang/Object;
    //   352: astore_3
    //   353: aload_3
    //   354: checkcast 63	java/lang/Integer
    //   357: invokevirtual 67	java/lang/Integer:intValue	()I
    //   360: putstatic 41	uuuuuu/bbmmmm:b00770077wwww007700770077	I
    //   363: bipush 94
    //   365: putstatic 81	uuuuuu/bbmmmm:bw00770077www007700770077	I
    //   368: aload_2
    //   369: aload_0
    //   370: getfield 313	uuuuuu/bbmmmm:b0077wwwww007700770077	Lcom/db/pwcc/dbmobile/foundation/data/manager/broadcasting/ModelUpdatedBroadcastReceiver;
    //   373: invokestatic 413	com/db/pwcc/dbmobile/foundation/data/manager/broadcasting/ModelUpdatedBroadcastReceiver:makeModelUpdatedIntentFilter	()Landroid/content/IntentFilter;
    //   376: invokeinterface 417 3 0
    //   381: ifne +8 -> 389
    //   384: aload_0
    //   385: aconst_null
    //   386: putfield 313	uuuuuu/bbmmmm:b0077wwwww007700770077	Lcom/db/pwcc/dbmobile/foundation/data/manager/broadcasting/ModelUpdatedBroadcastReceiver;
    //   389: return
    //   390: astore_2
    //   391: aload_2
    //   392: invokevirtual 93	java/lang/reflect/InvocationTargetException:getCause	()Ljava/lang/Throwable;
    //   395: athrow
    //   396: astore_2
    //   397: aload_2
    //   398: invokevirtual 93	java/lang/reflect/InvocationTargetException:getCause	()Ljava/lang/Throwable;
    //   401: athrow
    //   402: astore_2
    //   403: aload_2
    //   404: invokevirtual 93	java/lang/reflect/InvocationTargetException:getCause	()Ljava/lang/Throwable;
    //   407: athrow
    //   408: astore_2
    //   409: aload_2
    //   410: invokevirtual 93	java/lang/reflect/InvocationTargetException:getCause	()Ljava/lang/Throwable;
    //   413: athrow
    //   414: astore_2
    //   415: aload_2
    //   416: invokevirtual 93	java/lang/reflect/InvocationTargetException:getCause	()Ljava/lang/Throwable;
    //   419: athrow
    //   420: astore_2
    //   421: aload_2
    //   422: invokevirtual 93	java/lang/reflect/InvocationTargetException:getCause	()Ljava/lang/Throwable;
    //   425: athrow
    // Local variable table:
    //   start	length	slot	name	signature
    //   0	426	0	this	bbmmmm
    //   3	298	1	i	int
    //   22	80	2	localObject1	Object
    //   144	1	2	localException	Exception
    //   190	179	2	localObject2	Object
    //   390	2	2	localInvocationTargetException1	InvocationTargetException
    //   396	2	2	localInvocationTargetException2	InvocationTargetException
    //   402	2	2	localInvocationTargetException3	InvocationTargetException
    //   408	2	2	localInvocationTargetException4	InvocationTargetException
    //   414	2	2	localInvocationTargetException5	InvocationTargetException
    //   420	2	2	localInvocationTargetException6	InvocationTargetException
    //   279	75	3	localObject3	Object
    // Exception table:
    //   from	to	target	type
    //   137	141	144	java/lang/Exception
    //   280	290	390	java/lang/reflect/InvocationTargetException
    //   232	242	396	java/lang/reflect/InvocationTargetException
    //   191	201	402	java/lang/reflect/InvocationTargetException
    //   23	33	408	java/lang/reflect/InvocationTargetException
    //   91	101	414	java/lang/reflect/InvocationTargetException
    //   343	353	420	java/lang/reflect/InvocationTargetException
  }
  
  /* Error */
  public void boo006Foo006Fo006Fo006F()
  {
    // Byte code:
    //   0: ldc 2
    //   2: ldc_w 420
    //   5: bipush 33
    //   7: iconst_1
    //   8: invokestatic 73	xxxxxx/uxxxxx:bb00620062bb0062b0062b0062	(Ljava/lang/String;CC)Ljava/lang/String;
    //   11: iconst_0
    //   12: anewarray 33	java/lang/Class
    //   15: invokevirtual 55	java/lang/Class:getMethod	(Ljava/lang/String;[Ljava/lang/Class;)Ljava/lang/reflect/Method;
    //   18: astore 5
    //   20: aload 5
    //   22: aload_0
    //   23: iconst_0
    //   24: anewarray 4	java/lang/Object
    //   27: invokevirtual 61	java/lang/reflect/Method:invoke	(Ljava/lang/Object;[Ljava/lang/Object;)Ljava/lang/Object;
    //   30: pop
    //   31: getstatic 41	uuuuuu/bbmmmm:b00770077wwww007700770077	I
    //   34: istore_1
    //   35: getstatic 43	uuuuuu/bbmmmm:bww0077www007700770077	I
    //   38: istore_2
    //   39: getstatic 41	uuuuuu/bbmmmm:b00770077wwww007700770077	I
    //   42: istore_3
    //   43: ldc 2
    //   45: ldc_w 422
    //   48: sipush 182
    //   51: sipush 164
    //   54: iconst_3
    //   55: invokestatic 51	xxxxxx/uxxxxx:bbbb0062b0062b0062b0062	(Ljava/lang/String;CCC)Ljava/lang/String;
    //   58: iconst_0
    //   59: anewarray 33	java/lang/Class
    //   62: invokevirtual 55	java/lang/Class:getMethod	(Ljava/lang/String;[Ljava/lang/Class;)Ljava/lang/reflect/Method;
    //   65: astore 5
    //   67: aload 5
    //   69: aconst_null
    //   70: iconst_0
    //   71: anewarray 4	java/lang/Object
    //   74: invokevirtual 61	java/lang/reflect/Method:invoke	(Ljava/lang/Object;[Ljava/lang/Object;)Ljava/lang/Object;
    //   77: astore 5
    //   79: aload 5
    //   81: checkcast 63	java/lang/Integer
    //   84: invokevirtual 67	java/lang/Integer:intValue	()I
    //   87: istore 4
    //   89: ldc 2
    //   91: ldc_w 424
    //   94: bipush 98
    //   96: iconst_1
    //   97: invokestatic 73	xxxxxx/uxxxxx:bb00620062bb0062b0062b0062	(Ljava/lang/String;CC)Ljava/lang/String;
    //   100: iconst_0
    //   101: anewarray 33	java/lang/Class
    //   104: invokevirtual 55	java/lang/Class:getMethod	(Ljava/lang/String;[Ljava/lang/Class;)Ljava/lang/reflect/Method;
    //   107: astore 5
    //   109: aload 5
    //   111: aconst_null
    //   112: iconst_0
    //   113: anewarray 4	java/lang/Object
    //   116: invokevirtual 61	java/lang/reflect/Method:invoke	(Ljava/lang/Object;[Ljava/lang/Object;)Ljava/lang/Object;
    //   119: astore 5
    //   121: iload_3
    //   122: iload_1
    //   123: iload_2
    //   124: iadd
    //   125: imul
    //   126: iload 4
    //   128: irem
    //   129: aload 5
    //   131: checkcast 63	java/lang/Integer
    //   134: invokevirtual 67	java/lang/Integer:intValue	()I
    //   137: if_icmpeq +166 -> 303
    //   140: getstatic 41	uuuuuu/bbmmmm:b00770077wwww007700770077	I
    //   143: getstatic 43	uuuuuu/bbmmmm:bww0077www007700770077	I
    //   146: iadd
    //   147: getstatic 41	uuuuuu/bbmmmm:b00770077wwww007700770077	I
    //   150: imul
    //   151: getstatic 77	uuuuuu/bbmmmm:b0077w0077www007700770077	I
    //   154: irem
    //   155: getstatic 81	uuuuuu/bbmmmm:bw00770077www007700770077	I
    //   158: if_icmpeq +91 -> 249
    //   161: ldc 2
    //   163: ldc_w 377
    //   166: bipush 46
    //   168: bipush 80
    //   170: iconst_3
    //   171: invokestatic 51	xxxxxx/uxxxxx:bbbb0062b0062b0062b0062	(Ljava/lang/String;CCC)Ljava/lang/String;
    //   174: iconst_0
    //   175: anewarray 33	java/lang/Class
    //   178: invokevirtual 55	java/lang/Class:getMethod	(Ljava/lang/String;[Ljava/lang/Class;)Ljava/lang/reflect/Method;
    //   181: astore 5
    //   183: aload 5
    //   185: aconst_null
    //   186: iconst_0
    //   187: anewarray 4	java/lang/Object
    //   190: invokevirtual 61	java/lang/reflect/Method:invoke	(Ljava/lang/Object;[Ljava/lang/Object;)Ljava/lang/Object;
    //   193: astore 5
    //   195: aload 5
    //   197: checkcast 63	java/lang/Integer
    //   200: invokevirtual 67	java/lang/Integer:intValue	()I
    //   203: putstatic 41	uuuuuu/bbmmmm:b00770077wwww007700770077	I
    //   206: ldc 2
    //   208: ldc -86
    //   210: sipush 226
    //   213: iconst_0
    //   214: invokestatic 73	xxxxxx/uxxxxx:bb00620062bb0062b0062b0062	(Ljava/lang/String;CC)Ljava/lang/String;
    //   217: iconst_0
    //   218: anewarray 33	java/lang/Class
    //   221: invokevirtual 55	java/lang/Class:getMethod	(Ljava/lang/String;[Ljava/lang/Class;)Ljava/lang/reflect/Method;
    //   224: astore 5
    //   226: aload 5
    //   228: aconst_null
    //   229: iconst_0
    //   230: anewarray 4	java/lang/Object
    //   233: invokevirtual 61	java/lang/reflect/Method:invoke	(Ljava/lang/Object;[Ljava/lang/Object;)Ljava/lang/Object;
    //   236: astore 5
    //   238: aload 5
    //   240: checkcast 63	java/lang/Integer
    //   243: invokevirtual 67	java/lang/Integer:intValue	()I
    //   246: putstatic 81	uuuuuu/bbmmmm:bw00770077www007700770077	I
    //   249: getstatic 41	uuuuuu/bbmmmm:b00770077wwww007700770077	I
    //   252: istore_1
    //   253: iload_1
    //   254: getstatic 43	uuuuuu/bbmmmm:bww0077www007700770077	I
    //   257: iload_1
    //   258: iadd
    //   259: imul
    //   260: getstatic 77	uuuuuu/bbmmmm:b0077w0077www007700770077	I
    //   263: irem
    //   264: tableswitch	default:+20->284, 0:+29->293
    //   284: iconst_5
    //   285: putstatic 41	uuuuuu/bbmmmm:b00770077wwww007700770077	I
    //   288: bipush 73
    //   290: putstatic 81	uuuuuu/bbmmmm:bw00770077www007700770077	I
    //   293: bipush 46
    //   295: putstatic 41	uuuuuu/bbmmmm:b00770077wwww007700770077	I
    //   298: bipush 82
    //   300: putstatic 81	uuuuuu/bbmmmm:bw00770077www007700770077	I
    //   303: getstatic 41	uuuuuu/bbmmmm:b00770077wwww007700770077	I
    //   306: istore_1
    //   307: iload_1
    //   308: getstatic 43	uuuuuu/bbmmmm:bww0077www007700770077	I
    //   311: iload_1
    //   312: iadd
    //   313: imul
    //   314: getstatic 77	uuuuuu/bbmmmm:b0077w0077www007700770077	I
    //   317: irem
    //   318: tableswitch	default:+18->336, 0:+28->346
    //   336: bipush 68
    //   338: putstatic 41	uuuuuu/bbmmmm:b00770077wwww007700770077	I
    //   341: bipush 78
    //   343: putstatic 81	uuuuuu/bbmmmm:bw00770077www007700770077	I
    //   346: aload_0
    //   347: getfield 278	uuuuuu/bbmmmm:bwwwwww007700770077	Luuuuuu/qpqqqq;
    //   350: invokeinterface 427 1 0
    //   355: return
    //   356: astore 5
    //   358: aload 5
    //   360: invokevirtual 93	java/lang/reflect/InvocationTargetException:getCause	()Ljava/lang/Throwable;
    //   363: athrow
    //   364: astore 5
    //   366: aload 5
    //   368: invokevirtual 93	java/lang/reflect/InvocationTargetException:getCause	()Ljava/lang/Throwable;
    //   371: athrow
    //   372: astore 5
    //   374: aload 5
    //   376: invokevirtual 93	java/lang/reflect/InvocationTargetException:getCause	()Ljava/lang/Throwable;
    //   379: athrow
    //   380: astore 5
    //   382: aload 5
    //   384: invokevirtual 93	java/lang/reflect/InvocationTargetException:getCause	()Ljava/lang/Throwable;
    //   387: athrow
    //   388: astore 5
    //   390: aload 5
    //   392: invokevirtual 93	java/lang/reflect/InvocationTargetException:getCause	()Ljava/lang/Throwable;
    //   395: athrow
    // Local variable table:
    //   start	length	slot	name	signature
    //   0	396	0	this	bbmmmm
    //   34	280	1	i	int
    //   38	87	2	j	int
    //   42	84	3	k	int
    //   87	42	4	m	int
    //   18	221	5	localObject	Object
    //   356	3	5	localInvocationTargetException1	InvocationTargetException
    //   364	3	5	localInvocationTargetException2	InvocationTargetException
    //   372	3	5	localInvocationTargetException3	InvocationTargetException
    //   380	3	5	localInvocationTargetException4	InvocationTargetException
    //   388	3	5	localInvocationTargetException5	InvocationTargetException
    // Exception table:
    //   from	to	target	type
    //   67	79	356	java/lang/reflect/InvocationTargetException
    //   109	121	364	java/lang/reflect/InvocationTargetException
    //   20	31	372	java/lang/reflect/InvocationTargetException
    //   183	195	380	java/lang/reflect/InvocationTargetException
    //   226	238	388	java/lang/reflect/InvocationTargetException
  }
  
  /* Error */
  public void booooo006Fo006Fo006F(com.db.pwcc.dbmobile.model.banking.FinancialOverviewData paramFinancialOverviewData)
  {
    // Byte code:
    //   0: ldc 2
    //   2: ldc_w 430
    //   5: bipush 30
    //   7: iconst_2
    //   8: invokestatic 73	xxxxxx/uxxxxx:bb00620062bb0062b0062b0062	(Ljava/lang/String;CC)Ljava/lang/String;
    //   11: iconst_1
    //   12: anewarray 33	java/lang/Class
    //   15: dup
    //   16: iconst_0
    //   17: ldc 122
    //   19: aastore
    //   20: invokevirtual 55	java/lang/Class:getMethod	(Ljava/lang/String;[Ljava/lang/Class;)Ljava/lang/reflect/Method;
    //   23: astore 4
    //   25: aload 4
    //   27: aload_0
    //   28: iconst_1
    //   29: anewarray 4	java/lang/Object
    //   32: dup
    //   33: iconst_0
    //   34: aload_1
    //   35: aastore
    //   36: invokevirtual 61	java/lang/reflect/Method:invoke	(Ljava/lang/Object;[Ljava/lang/Object;)Ljava/lang/Object;
    //   39: pop
    //   40: aload_0
    //   41: getfield 100	uuuuuu/bbmmmm:bw0077wwww007700770077	Luuuuuu/bbmbmm$bmbbmm;
    //   44: astore 4
    //   46: ldc 2
    //   48: ldc_w 432
    //   51: sipush 219
    //   54: iconst_3
    //   55: invokestatic 73	xxxxxx/uxxxxx:bb00620062bb0062b0062b0062	(Ljava/lang/String;CC)Ljava/lang/String;
    //   58: iconst_1
    //   59: anewarray 33	java/lang/Class
    //   62: dup
    //   63: iconst_0
    //   64: ldc 122
    //   66: aastore
    //   67: invokevirtual 55	java/lang/Class:getMethod	(Ljava/lang/String;[Ljava/lang/Class;)Ljava/lang/reflect/Method;
    //   70: astore 5
    //   72: aload 5
    //   74: aload_0
    //   75: iconst_1
    //   76: anewarray 4	java/lang/Object
    //   79: dup
    //   80: iconst_0
    //   81: aload_1
    //   82: aastore
    //   83: invokevirtual 61	java/lang/reflect/Method:invoke	(Ljava/lang/Object;[Ljava/lang/Object;)Ljava/lang/Object;
    //   86: astore 5
    //   88: aload 4
    //   90: aload_1
    //   91: aload 5
    //   93: checkcast 156	uuuuuu/heeehh
    //   96: invokeinterface 436 3 0
    //   101: ldc 2
    //   103: ldc_w 438
    //   106: sipush 164
    //   109: iconst_0
    //   110: invokestatic 73	xxxxxx/uxxxxx:bb00620062bb0062b0062b0062	(Ljava/lang/String;CC)Ljava/lang/String;
    //   113: iconst_0
    //   114: anewarray 33	java/lang/Class
    //   117: invokevirtual 55	java/lang/Class:getMethod	(Ljava/lang/String;[Ljava/lang/Class;)Ljava/lang/reflect/Method;
    //   120: astore_1
    //   121: aload_1
    //   122: aconst_null
    //   123: iconst_0
    //   124: anewarray 4	java/lang/Object
    //   127: invokevirtual 61	java/lang/reflect/Method:invoke	(Ljava/lang/Object;[Ljava/lang/Object;)Ljava/lang/Object;
    //   130: astore_1
    //   131: aload_1
    //   132: checkcast 63	java/lang/Integer
    //   135: invokevirtual 67	java/lang/Integer:intValue	()I
    //   138: istore_2
    //   139: getstatic 43	uuuuuu/bbmmmm:bww0077www007700770077	I
    //   142: istore_3
    //   143: ldc 2
    //   145: ldc -108
    //   147: bipush 18
    //   149: iconst_1
    //   150: invokestatic 73	xxxxxx/uxxxxx:bb00620062bb0062b0062b0062	(Ljava/lang/String;CC)Ljava/lang/String;
    //   153: iconst_0
    //   154: anewarray 33	java/lang/Class
    //   157: invokevirtual 55	java/lang/Class:getMethod	(Ljava/lang/String;[Ljava/lang/Class;)Ljava/lang/reflect/Method;
    //   160: astore_1
    //   161: aload_1
    //   162: aconst_null
    //   163: iconst_0
    //   164: anewarray 4	java/lang/Object
    //   167: invokevirtual 61	java/lang/reflect/Method:invoke	(Ljava/lang/Object;[Ljava/lang/Object;)Ljava/lang/Object;
    //   170: astore_1
    //   171: aload_1
    //   172: checkcast 63	java/lang/Integer
    //   175: invokevirtual 67	java/lang/Integer:intValue	()I
    //   178: iload_3
    //   179: iload_2
    //   180: iadd
    //   181: imul
    //   182: getstatic 77	uuuuuu/bbmmmm:b0077w0077www007700770077	I
    //   185: irem
    //   186: getstatic 81	uuuuuu/bbmmmm:bw00770077www007700770077	I
    //   189: if_icmpeq +176 -> 365
    //   192: getstatic 41	uuuuuu/bbmmmm:b00770077wwww007700770077	I
    //   195: getstatic 43	uuuuuu/bbmmmm:bww0077www007700770077	I
    //   198: iadd
    //   199: getstatic 41	uuuuuu/bbmmmm:b00770077wwww007700770077	I
    //   202: imul
    //   203: getstatic 77	uuuuuu/bbmmmm:b0077w0077www007700770077	I
    //   206: irem
    //   207: getstatic 81	uuuuuu/bbmmmm:bw00770077www007700770077	I
    //   210: if_icmpeq +13 -> 223
    //   213: bipush 34
    //   215: putstatic 41	uuuuuu/bbmmmm:b00770077wwww007700770077	I
    //   218: bipush 67
    //   220: putstatic 81	uuuuuu/bbmmmm:bw00770077www007700770077	I
    //   223: bipush 37
    //   225: putstatic 41	uuuuuu/bbmmmm:b00770077wwww007700770077	I
    //   228: bipush 32
    //   230: putstatic 81	uuuuuu/bbmmmm:bw00770077www007700770077	I
    //   233: getstatic 41	uuuuuu/bbmmmm:b00770077wwww007700770077	I
    //   236: getstatic 43	uuuuuu/bbmmmm:bww0077www007700770077	I
    //   239: iadd
    //   240: getstatic 41	uuuuuu/bbmmmm:b00770077wwww007700770077	I
    //   243: imul
    //   244: getstatic 77	uuuuuu/bbmmmm:b0077w0077www007700770077	I
    //   247: irem
    //   248: getstatic 81	uuuuuu/bbmmmm:bw00770077www007700770077	I
    //   251: if_icmpeq +114 -> 365
    //   254: bipush 86
    //   256: putstatic 41	uuuuuu/bbmmmm:b00770077wwww007700770077	I
    //   259: bipush 58
    //   261: putstatic 81	uuuuuu/bbmmmm:bw00770077www007700770077	I
    //   264: getstatic 41	uuuuuu/bbmmmm:b00770077wwww007700770077	I
    //   267: getstatic 43	uuuuuu/bbmmmm:bww0077www007700770077	I
    //   270: iadd
    //   271: getstatic 41	uuuuuu/bbmmmm:b00770077wwww007700770077	I
    //   274: imul
    //   275: getstatic 77	uuuuuu/bbmmmm:b0077w0077www007700770077	I
    //   278: irem
    //   279: getstatic 81	uuuuuu/bbmmmm:bw00770077www007700770077	I
    //   282: if_icmpeq +83 -> 365
    //   285: ldc 2
    //   287: ldc_w 440
    //   290: sipush 214
    //   293: iconst_0
    //   294: invokestatic 73	xxxxxx/uxxxxx:bb00620062bb0062b0062b0062	(Ljava/lang/String;CC)Ljava/lang/String;
    //   297: iconst_0
    //   298: anewarray 33	java/lang/Class
    //   301: invokevirtual 55	java/lang/Class:getMethod	(Ljava/lang/String;[Ljava/lang/Class;)Ljava/lang/reflect/Method;
    //   304: astore_1
    //   305: aload_1
    //   306: aconst_null
    //   307: iconst_0
    //   308: anewarray 4	java/lang/Object
    //   311: invokevirtual 61	java/lang/reflect/Method:invoke	(Ljava/lang/Object;[Ljava/lang/Object;)Ljava/lang/Object;
    //   314: astore_1
    //   315: aload_1
    //   316: checkcast 63	java/lang/Integer
    //   319: invokevirtual 67	java/lang/Integer:intValue	()I
    //   322: putstatic 41	uuuuuu/bbmmmm:b00770077wwww007700770077	I
    //   325: ldc 2
    //   327: ldc_w 442
    //   330: iconst_1
    //   331: bipush 51
    //   333: iconst_3
    //   334: invokestatic 51	xxxxxx/uxxxxx:bbbb0062b0062b0062b0062	(Ljava/lang/String;CCC)Ljava/lang/String;
    //   337: iconst_0
    //   338: anewarray 33	java/lang/Class
    //   341: invokevirtual 55	java/lang/Class:getMethod	(Ljava/lang/String;[Ljava/lang/Class;)Ljava/lang/reflect/Method;
    //   344: astore_1
    //   345: aload_1
    //   346: aconst_null
    //   347: iconst_0
    //   348: anewarray 4	java/lang/Object
    //   351: invokevirtual 61	java/lang/reflect/Method:invoke	(Ljava/lang/Object;[Ljava/lang/Object;)Ljava/lang/Object;
    //   354: astore_1
    //   355: aload_1
    //   356: checkcast 63	java/lang/Integer
    //   359: invokevirtual 67	java/lang/Integer:intValue	()I
    //   362: putstatic 81	uuuuuu/bbmmmm:bw00770077www007700770077	I
    //   365: return
    //   366: astore_1
    //   367: aload_1
    //   368: invokevirtual 93	java/lang/reflect/InvocationTargetException:getCause	()Ljava/lang/Throwable;
    //   371: athrow
    //   372: astore_1
    //   373: aload_1
    //   374: invokevirtual 93	java/lang/reflect/InvocationTargetException:getCause	()Ljava/lang/Throwable;
    //   377: athrow
    //   378: astore_1
    //   379: aload_1
    //   380: invokevirtual 93	java/lang/reflect/InvocationTargetException:getCause	()Ljava/lang/Throwable;
    //   383: athrow
    //   384: astore_1
    //   385: aload_1
    //   386: invokevirtual 93	java/lang/reflect/InvocationTargetException:getCause	()Ljava/lang/Throwable;
    //   389: athrow
    //   390: astore_1
    //   391: aload_1
    //   392: invokevirtual 93	java/lang/reflect/InvocationTargetException:getCause	()Ljava/lang/Throwable;
    //   395: athrow
    //   396: astore_1
    //   397: aload_1
    //   398: invokevirtual 93	java/lang/reflect/InvocationTargetException:getCause	()Ljava/lang/Throwable;
    //   401: athrow
    // Local variable table:
    //   start	length	slot	name	signature
    //   0	402	0	this	bbmmmm
    //   0	402	1	paramFinancialOverviewData	com.db.pwcc.dbmobile.model.banking.FinancialOverviewData
    //   138	43	2	i	int
    //   142	39	3	j	int
    //   23	66	4	localObject1	Object
    //   70	22	5	localObject2	Object
    // Exception table:
    //   from	to	target	type
    //   25	40	366	java/lang/reflect/InvocationTargetException
    //   72	88	372	java/lang/reflect/InvocationTargetException
    //   121	131	378	java/lang/reflect/InvocationTargetException
    //   161	171	384	java/lang/reflect/InvocationTargetException
    //   305	315	390	java/lang/reflect/InvocationTargetException
    //   345	355	396	java/lang/reflect/InvocationTargetException
  }
}
