package uuuuuu;

import android.support.annotation.RequiresApi;
import com.db.pwcc.dbmobile.model.fingerprint.SecureFingerprintData;

@RequiresApi(api=23)
public class bmmmbb
  extends ssssst<bmbbmb.mbbbmb>
  implements bmbbbm, bmbbmb.bbbbmb
{
  public static int b00730073s0073s0073s0073s = 0;
  public static int b0073ss0073s0073s0073s = 1;
  public static int bs0073s0073s0073s0073s = 2;
  public static int bsss0073s0073s0073s = 44;
  private SecureFingerprintData b007300730073ss0073s0073s;
  private mmmmmb b0073s0073ss0073s0073s;
  private String bs00730073ss0073s0073s;
  private mbmmbb bss0073ss0073s0073s;
  
  public bmmmbb() {}
  
  public static int b006F006F006Foo006Fo006F006F006F()
  {
    return 65;
  }
  
  public static int b006Fo006Foo006Fo006F006F006F()
  {
    return 2;
  }
  
  public static int b006Foo006Fo006Fo006F006F006F()
  {
    return 1;
  }
  
  public static int bo006F006Foo006Fo006F006F006F()
  {
    return 0;
  }
  
  /* Error */
  public void b006F006F006F006Fo006Foo006F006F()
  {
    // Byte code:
    //   0: getstatic 44	uuuuuu/bmmmbb:bsss0073s0073s0073s	I
    //   3: istore_1
    //   4: iload_1
    //   5: getstatic 46	uuuuuu/bmmmbb:b0073ss0073s0073s0073s	I
    //   8: iload_1
    //   9: iadd
    //   10: imul
    //   11: getstatic 48	uuuuuu/bmmmbb:bs0073s0073s0073s0073s	I
    //   14: irem
    //   15: tableswitch	default:+17->32, 0:+108->123
    //   32: bipush 41
    //   34: putstatic 44	uuuuuu/bmmmbb:bsss0073s0073s0073s	I
    //   37: bipush 83
    //   39: putstatic 50	uuuuuu/bmmmbb:b00730073s0073s0073s0073s	I
    //   42: getstatic 44	uuuuuu/bmmmbb:bsss0073s0073s0073s	I
    //   45: istore_1
    //   46: iload_1
    //   47: getstatic 46	uuuuuu/bmmmbb:b0073ss0073s0073s0073s	I
    //   50: iload_1
    //   51: iadd
    //   52: imul
    //   53: getstatic 48	uuuuuu/bmmmbb:bs0073s0073s0073s0073s	I
    //   56: irem
    //   57: tableswitch	default:+19->76, 0:+66->123
    //   76: ldc 2
    //   78: ldc 52
    //   80: sipush 176
    //   83: sipush 167
    //   86: iconst_3
    //   87: invokestatic 58	xxxxxx/uxxxxx:bbbb0062b0062b0062b0062	(Ljava/lang/String;CCC)Ljava/lang/String;
    //   90: iconst_0
    //   91: anewarray 60	java/lang/Class
    //   94: invokevirtual 64	java/lang/Class:getMethod	(Ljava/lang/String;[Ljava/lang/Class;)Ljava/lang/reflect/Method;
    //   97: astore_2
    //   98: aload_2
    //   99: aconst_null
    //   100: iconst_0
    //   101: anewarray 66	java/lang/Object
    //   104: invokevirtual 72	java/lang/reflect/Method:invoke	(Ljava/lang/Object;[Ljava/lang/Object;)Ljava/lang/Object;
    //   107: astore_2
    //   108: aload_2
    //   109: checkcast 74	java/lang/Integer
    //   112: invokevirtual 77	java/lang/Integer:intValue	()I
    //   115: putstatic 44	uuuuuu/bmmmbb:bsss0073s0073s0073s	I
    //   118: bipush 20
    //   120: putstatic 50	uuuuuu/bmmmbb:b00730073s0073s0073s0073s	I
    //   123: aload_0
    //   124: invokevirtual 81	uuuuuu/bmmmbb:bkk006Bk006Bk006Bk006Bk	()Z
    //   127: ifne +4 -> 131
    //   130: return
    //   131: aload_0
    //   132: getfield 85	uuuuuu/bmmmbb:bnnnnn006E006E006En	Luuuuuu/ttssst$tsssst;
    //   135: checkcast 87	uuuuuu/bmbbmb$mbbbmb
    //   138: astore_2
    //   139: getstatic 93	uuuuuu/mbbbbm:bs00730073sss0073ss	Luuuuuu/mbbbbm;
    //   142: astore_3
    //   143: getstatic 98	com/db/pwcc/dbmobile/fingerprint/R$string:fingerprint_dialog_message_not_recognized	I
    //   146: istore_1
    //   147: getstatic 44	uuuuuu/bmmmbb:bsss0073s0073s0073s	I
    //   150: getstatic 46	uuuuuu/bmmmbb:b0073ss0073s0073s0073s	I
    //   153: iadd
    //   154: getstatic 44	uuuuuu/bmmmbb:bsss0073s0073s0073s	I
    //   157: imul
    //   158: getstatic 48	uuuuuu/bmmmbb:bs0073s0073s0073s0073s	I
    //   161: irem
    //   162: getstatic 50	uuuuuu/bmmmbb:b00730073s0073s0073s0073s	I
    //   165: if_icmpeq +51 -> 216
    //   168: ldc 2
    //   170: ldc 100
    //   172: sipush 140
    //   175: iconst_0
    //   176: invokestatic 104	xxxxxx/uxxxxx:bb00620062bb0062b0062b0062	(Ljava/lang/String;CC)Ljava/lang/String;
    //   179: iconst_0
    //   180: anewarray 60	java/lang/Class
    //   183: invokevirtual 64	java/lang/Class:getMethod	(Ljava/lang/String;[Ljava/lang/Class;)Ljava/lang/reflect/Method;
    //   186: astore 4
    //   188: aload 4
    //   190: aconst_null
    //   191: iconst_0
    //   192: anewarray 66	java/lang/Object
    //   195: invokevirtual 72	java/lang/reflect/Method:invoke	(Ljava/lang/Object;[Ljava/lang/Object;)Ljava/lang/Object;
    //   198: astore 4
    //   200: aload 4
    //   202: checkcast 74	java/lang/Integer
    //   205: invokevirtual 77	java/lang/Integer:intValue	()I
    //   208: putstatic 44	uuuuuu/bmmmbb:bsss0073s0073s0073s	I
    //   211: bipush 86
    //   213: putstatic 50	uuuuuu/bmmmbb:b00730073s0073s0073s0073s	I
    //   216: aload_2
    //   217: aload_3
    //   218: iload_1
    //   219: invokeinterface 108 3 0
    //   224: getstatic 44	uuuuuu/bmmmbb:bsss0073s0073s0073s	I
    //   227: istore_1
    //   228: iload_1
    //   229: getstatic 46	uuuuuu/bmmmbb:b0073ss0073s0073s0073s	I
    //   232: iload_1
    //   233: iadd
    //   234: imul
    //   235: getstatic 48	uuuuuu/bmmmbb:bs0073s0073s0073s0073s	I
    //   238: irem
    //   239: tableswitch	default:+17->256, 0:+-109->130
    //   256: bipush 41
    //   258: putstatic 44	uuuuuu/bmmmbb:bsss0073s0073s0073s	I
    //   261: ldc 2
    //   263: ldc 110
    //   265: bipush 112
    //   267: iconst_4
    //   268: invokestatic 104	xxxxxx/uxxxxx:bb00620062bb0062b0062b0062	(Ljava/lang/String;CC)Ljava/lang/String;
    //   271: iconst_0
    //   272: anewarray 60	java/lang/Class
    //   275: invokevirtual 64	java/lang/Class:getMethod	(Ljava/lang/String;[Ljava/lang/Class;)Ljava/lang/reflect/Method;
    //   278: astore_2
    //   279: aload_2
    //   280: aconst_null
    //   281: iconst_0
    //   282: anewarray 66	java/lang/Object
    //   285: invokevirtual 72	java/lang/reflect/Method:invoke	(Ljava/lang/Object;[Ljava/lang/Object;)Ljava/lang/Object;
    //   288: astore_2
    //   289: aload_2
    //   290: checkcast 74	java/lang/Integer
    //   293: invokevirtual 77	java/lang/Integer:intValue	()I
    //   296: putstatic 50	uuuuuu/bmmmbb:b00730073s0073s0073s0073s	I
    //   299: return
    //   300: astore_2
    //   301: aload_2
    //   302: invokevirtual 114	java/lang/reflect/InvocationTargetException:getCause	()Ljava/lang/Throwable;
    //   305: athrow
    //   306: astore_2
    //   307: aload_2
    //   308: invokevirtual 114	java/lang/reflect/InvocationTargetException:getCause	()Ljava/lang/Throwable;
    //   311: athrow
    //   312: astore_2
    //   313: aload_2
    //   314: invokevirtual 114	java/lang/reflect/InvocationTargetException:getCause	()Ljava/lang/Throwable;
    //   317: athrow
    // Local variable table:
    //   start	length	slot	name	signature
    //   0	318	0	this	bmmmbb
    //   3	232	1	i	int
    //   97	193	2	localObject1	Object
    //   300	2	2	localInvocationTargetException1	java.lang.reflect.InvocationTargetException
    //   306	2	2	localInvocationTargetException2	java.lang.reflect.InvocationTargetException
    //   312	2	2	localInvocationTargetException3	java.lang.reflect.InvocationTargetException
    //   142	76	3	localMbbbbm	mbbbbm
    //   186	15	4	localObject2	Object
    // Exception table:
    //   from	to	target	type
    //   98	108	300	java/lang/reflect/InvocationTargetException
    //   279	289	306	java/lang/reflect/InvocationTargetException
    //   188	200	312	java/lang/reflect/InvocationTargetException
  }
  
  /* Error */
  public void b006Fo006F006F006Foo006F006F006F(mmmmmb paramMmmmmb, SecureFingerprintData paramSecureFingerprintData, String paramString, mbmmbb paramMbmmbb)
  {
    // Byte code:
    //   0: getstatic 44	uuuuuu/bmmmbb:bsss0073s0073s0073s	I
    //   3: istore 5
    //   5: getstatic 46	uuuuuu/bmmmbb:b0073ss0073s0073s0073s	I
    //   8: istore 6
    //   10: ldc 2
    //   12: ldc 118
    //   14: sipush 231
    //   17: iconst_0
    //   18: invokestatic 104	xxxxxx/uxxxxx:bb00620062bb0062b0062b0062	(Ljava/lang/String;CC)Ljava/lang/String;
    //   21: iconst_0
    //   22: anewarray 60	java/lang/Class
    //   25: invokevirtual 64	java/lang/Class:getMethod	(Ljava/lang/String;[Ljava/lang/Class;)Ljava/lang/reflect/Method;
    //   28: astore 8
    //   30: aload 8
    //   32: aconst_null
    //   33: iconst_0
    //   34: anewarray 66	java/lang/Object
    //   37: invokevirtual 72	java/lang/reflect/Method:invoke	(Ljava/lang/Object;[Ljava/lang/Object;)Ljava/lang/Object;
    //   40: astore 8
    //   42: iload 6
    //   44: iload 5
    //   46: iadd
    //   47: iload 5
    //   49: imul
    //   50: aload 8
    //   52: checkcast 74	java/lang/Integer
    //   55: invokevirtual 77	java/lang/Integer:intValue	()I
    //   58: irem
    //   59: tableswitch	default:+17->76, 0:+65->124
    //   76: ldc 2
    //   78: ldc 120
    //   80: sipush 251
    //   83: iconst_1
    //   84: invokestatic 104	xxxxxx/uxxxxx:bb00620062bb0062b0062b0062	(Ljava/lang/String;CC)Ljava/lang/String;
    //   87: iconst_0
    //   88: anewarray 60	java/lang/Class
    //   91: invokevirtual 64	java/lang/Class:getMethod	(Ljava/lang/String;[Ljava/lang/Class;)Ljava/lang/reflect/Method;
    //   94: astore 8
    //   96: aload 8
    //   98: aconst_null
    //   99: iconst_0
    //   100: anewarray 66	java/lang/Object
    //   103: invokevirtual 72	java/lang/reflect/Method:invoke	(Ljava/lang/Object;[Ljava/lang/Object;)Ljava/lang/Object;
    //   106: astore 8
    //   108: aload 8
    //   110: checkcast 74	java/lang/Integer
    //   113: invokevirtual 77	java/lang/Integer:intValue	()I
    //   116: putstatic 44	uuuuuu/bmmmbb:bsss0073s0073s0073s	I
    //   119: bipush 92
    //   121: putstatic 50	uuuuuu/bmmmbb:b00730073s0073s0073s0073s	I
    //   124: aload_0
    //   125: aload_1
    //   126: putfield 122	uuuuuu/bmmmbb:b0073s0073ss0073s0073s	Luuuuuu/mmmmmb;
    //   129: aload_0
    //   130: aload_2
    //   131: putfield 124	uuuuuu/bmmmbb:b007300730073ss0073s0073s	Lcom/db/pwcc/dbmobile/model/fingerprint/SecureFingerprintData;
    //   134: getstatic 44	uuuuuu/bmmmbb:bsss0073s0073s0073s	I
    //   137: istore 5
    //   139: getstatic 46	uuuuuu/bmmmbb:b0073ss0073s0073s0073s	I
    //   142: istore 6
    //   144: getstatic 44	uuuuuu/bmmmbb:bsss0073s0073s0073s	I
    //   147: istore 7
    //   149: iload 7
    //   151: getstatic 46	uuuuuu/bmmmbb:b0073ss0073s0073s0073s	I
    //   154: iload 7
    //   156: iadd
    //   157: imul
    //   158: getstatic 48	uuuuuu/bmmmbb:bs0073s0073s0073s0073s	I
    //   161: irem
    //   162: tableswitch	default:+18->180, 0:+144->306
    //   180: getstatic 44	uuuuuu/bmmmbb:bsss0073s0073s0073s	I
    //   183: istore 7
    //   185: iload 7
    //   187: getstatic 46	uuuuuu/bmmmbb:b0073ss0073s0073s0073s	I
    //   190: iload 7
    //   192: iadd
    //   193: imul
    //   194: getstatic 48	uuuuuu/bmmmbb:bs0073s0073s0073s0073s	I
    //   197: irem
    //   198: tableswitch	default:+18->216, 0:+61->259
    //   216: ldc 2
    //   218: ldc 126
    //   220: bipush 23
    //   222: iconst_3
    //   223: invokestatic 104	xxxxxx/uxxxxx:bb00620062bb0062b0062b0062	(Ljava/lang/String;CC)Ljava/lang/String;
    //   226: iconst_0
    //   227: anewarray 60	java/lang/Class
    //   230: invokevirtual 64	java/lang/Class:getMethod	(Ljava/lang/String;[Ljava/lang/Class;)Ljava/lang/reflect/Method;
    //   233: astore_1
    //   234: aload_1
    //   235: aconst_null
    //   236: iconst_0
    //   237: anewarray 66	java/lang/Object
    //   240: invokevirtual 72	java/lang/reflect/Method:invoke	(Ljava/lang/Object;[Ljava/lang/Object;)Ljava/lang/Object;
    //   243: astore_1
    //   244: aload_1
    //   245: checkcast 74	java/lang/Integer
    //   248: invokevirtual 77	java/lang/Integer:intValue	()I
    //   251: putstatic 44	uuuuuu/bmmmbb:bsss0073s0073s0073s	I
    //   254: bipush 41
    //   256: putstatic 50	uuuuuu/bmmmbb:b00730073s0073s0073s0073s	I
    //   259: ldc 2
    //   261: ldc -128
    //   263: sipush 215
    //   266: sipush 161
    //   269: iconst_2
    //   270: invokestatic 58	xxxxxx/uxxxxx:bbbb0062b0062b0062b0062	(Ljava/lang/String;CCC)Ljava/lang/String;
    //   273: iconst_0
    //   274: anewarray 60	java/lang/Class
    //   277: invokevirtual 64	java/lang/Class:getMethod	(Ljava/lang/String;[Ljava/lang/Class;)Ljava/lang/reflect/Method;
    //   280: astore_1
    //   281: aload_1
    //   282: aconst_null
    //   283: iconst_0
    //   284: anewarray 66	java/lang/Object
    //   287: invokevirtual 72	java/lang/reflect/Method:invoke	(Ljava/lang/Object;[Ljava/lang/Object;)Ljava/lang/Object;
    //   290: astore_1
    //   291: aload_1
    //   292: checkcast 74	java/lang/Integer
    //   295: invokevirtual 77	java/lang/Integer:intValue	()I
    //   298: putstatic 44	uuuuuu/bmmmbb:bsss0073s0073s0073s	I
    //   301: bipush 45
    //   303: putstatic 50	uuuuuu/bmmmbb:b00730073s0073s0073s0073s	I
    //   306: iload 5
    //   308: iload 6
    //   310: iadd
    //   311: getstatic 44	uuuuuu/bmmmbb:bsss0073s0073s0073s	I
    //   314: imul
    //   315: getstatic 48	uuuuuu/bmmmbb:bs0073s0073s0073s0073s	I
    //   318: irem
    //   319: getstatic 50	uuuuuu/bmmmbb:b00730073s0073s0073s0073s	I
    //   322: if_icmpeq +13 -> 335
    //   325: bipush 22
    //   327: putstatic 44	uuuuuu/bmmmbb:bsss0073s0073s0073s	I
    //   330: bipush 14
    //   332: putstatic 50	uuuuuu/bmmmbb:b00730073s0073s0073s0073s	I
    //   335: aload_0
    //   336: aload_3
    //   337: putfield 130	uuuuuu/bmmmbb:bs00730073ss0073s0073s	Ljava/lang/String;
    //   340: aload_0
    //   341: aload 4
    //   343: putfield 132	uuuuuu/bmmmbb:bss0073ss0073s0073s	Luuuuuu/mbmmbb;
    //   346: return
    //   347: astore_1
    //   348: aload_1
    //   349: invokevirtual 114	java/lang/reflect/InvocationTargetException:getCause	()Ljava/lang/Throwable;
    //   352: athrow
    //   353: astore_1
    //   354: aload_1
    //   355: invokevirtual 114	java/lang/reflect/InvocationTargetException:getCause	()Ljava/lang/Throwable;
    //   358: athrow
    //   359: astore_1
    //   360: aload_1
    //   361: invokevirtual 114	java/lang/reflect/InvocationTargetException:getCause	()Ljava/lang/Throwable;
    //   364: athrow
    //   365: astore_1
    //   366: aload_1
    //   367: invokevirtual 114	java/lang/reflect/InvocationTargetException:getCause	()Ljava/lang/Throwable;
    //   370: athrow
    // Local variable table:
    //   start	length	slot	name	signature
    //   0	371	0	this	bmmmbb
    //   0	371	1	paramMmmmmb	mmmmmb
    //   0	371	2	paramSecureFingerprintData	SecureFingerprintData
    //   0	371	3	paramString	String
    //   0	371	4	paramMbmmbb	mbmmbb
    //   3	308	5	i	int
    //   8	303	6	j	int
    //   147	47	7	k	int
    //   28	81	8	localObject	Object
    // Exception table:
    //   from	to	target	type
    //   30	42	347	java/lang/reflect/InvocationTargetException
    //   281	291	353	java/lang/reflect/InvocationTargetException
    //   96	108	359	java/lang/reflect/InvocationTargetException
    //   234	244	365	java/lang/reflect/InvocationTargetException
  }
  
  /* Error */
  public void b006Fooo006F006Foo006F006F(android.hardware.fingerprint.FingerprintManager.AuthenticationResult paramAuthenticationResult)
  {
    // Byte code:
    //   0: aload_0
    //   1: invokevirtual 81	uuuuuu/bmmmbb:bkk006Bk006Bk006Bk006Bk	()Z
    //   4: ifne +41 -> 45
    //   7: return
    //   8: astore_1
    //   9: bipush 50
    //   11: putstatic 44	uuuuuu/bmmmbb:bsss0073s0073s0073s	I
    //   14: aload_0
    //   15: getfield 85	uuuuuu/bmmmbb:bnnnnn006E006E006En	Luuuuuu/ttssst$tsssst;
    //   18: checkcast 87	uuuuuu/bmbbmb$mbbbmb
    //   21: invokeinterface 139 1 0
    //   26: ifeq -19 -> 7
    //   29: aload_0
    //   30: getfield 122	uuuuuu/bmmmbb:b0073s0073ss0073s0073s	Luuuuuu/mmmmmb;
    //   33: aload_0
    //   34: getfield 124	uuuuuu/bmmmbb:b007300730073ss0073s0073s	Lcom/db/pwcc/dbmobile/model/fingerprint/SecureFingerprintData;
    //   37: aload_0
    //   38: getfield 130	uuuuuu/bmmmbb:bs00730073ss0073s0073s	Ljava/lang/String;
    //   41: invokevirtual 145	uuuuuu/mmmmmb:b006F006Fo006F006Fo006Fo006F006F	(Lcom/db/pwcc/dbmobile/model/fingerprint/SecureFingerprintData;Ljava/lang/String;)V
    //   44: return
    //   45: aload_0
    //   46: getfield 85	uuuuuu/bmmmbb:bnnnnn006E006E006En	Luuuuuu/ttssst$tsssst;
    //   49: checkcast 87	uuuuuu/bmbbmb$mbbbmb
    //   52: getstatic 148	uuuuuu/mbbbbm:b007300730073sss0073ss	Luuuuuu/mbbbbm;
    //   55: getstatic 151	com/db/pwcc/dbmobile/fingerprint/R$string:fingerprint_dialog_message_touch	I
    //   58: invokeinterface 108 3 0
    //   63: aload_0
    //   64: getfield 132	uuuuuu/bmmmbb:bss0073ss0073s0073s	Luuuuuu/mbmmbb;
    //   67: getstatic 156	uuuuuu/mbmmbb:b0073s00730073s0073s0073s	Luuuuuu/mbmmbb;
    //   70: if_acmpne -56 -> 14
    //   73: getstatic 44	uuuuuu/bmmmbb:bsss0073s0073s0073s	I
    //   76: getstatic 46	uuuuuu/bmmmbb:b0073ss0073s0073s0073s	I
    //   79: iadd
    //   80: getstatic 44	uuuuuu/bmmmbb:bsss0073s0073s0073s	I
    //   83: imul
    //   84: getstatic 48	uuuuuu/bmmmbb:bs0073s0073s0073s0073s	I
    //   87: irem
    //   88: getstatic 50	uuuuuu/bmmmbb:b00730073s0073s0073s0073s	I
    //   91: if_icmpeq +82 -> 173
    //   94: ldc 2
    //   96: ldc -98
    //   98: bipush 104
    //   100: bipush 123
    //   102: iconst_2
    //   103: invokestatic 58	xxxxxx/uxxxxx:bbbb0062b0062b0062b0062	(Ljava/lang/String;CCC)Ljava/lang/String;
    //   106: iconst_0
    //   107: anewarray 60	java/lang/Class
    //   110: invokevirtual 64	java/lang/Class:getMethod	(Ljava/lang/String;[Ljava/lang/Class;)Ljava/lang/reflect/Method;
    //   113: astore_1
    //   114: aload_1
    //   115: aconst_null
    //   116: iconst_0
    //   117: anewarray 66	java/lang/Object
    //   120: invokevirtual 72	java/lang/reflect/Method:invoke	(Ljava/lang/Object;[Ljava/lang/Object;)Ljava/lang/Object;
    //   123: astore_1
    //   124: aload_1
    //   125: checkcast 74	java/lang/Integer
    //   128: invokevirtual 77	java/lang/Integer:intValue	()I
    //   131: putstatic 44	uuuuuu/bmmmbb:bsss0073s0073s0073s	I
    //   134: ldc 2
    //   136: ldc -96
    //   138: sipush 244
    //   141: iconst_4
    //   142: invokestatic 104	xxxxxx/uxxxxx:bb00620062bb0062b0062b0062	(Ljava/lang/String;CC)Ljava/lang/String;
    //   145: iconst_0
    //   146: anewarray 60	java/lang/Class
    //   149: invokevirtual 64	java/lang/Class:getMethod	(Ljava/lang/String;[Ljava/lang/Class;)Ljava/lang/reflect/Method;
    //   152: astore_1
    //   153: aload_1
    //   154: aconst_null
    //   155: iconst_0
    //   156: anewarray 66	java/lang/Object
    //   159: invokevirtual 72	java/lang/reflect/Method:invoke	(Ljava/lang/Object;[Ljava/lang/Object;)Ljava/lang/Object;
    //   162: astore_1
    //   163: aload_1
    //   164: checkcast 74	java/lang/Integer
    //   167: invokevirtual 77	java/lang/Integer:intValue	()I
    //   170: putstatic 50	uuuuuu/bmmmbb:b00730073s0073s0073s0073s	I
    //   173: aload_0
    //   174: getfield 164	uuuuuu/bmmmbb:b006E006E006E006E006En006E006En	Luuuuuu/hyhyhh;
    //   177: invokevirtual 169	uuuuuu/hyhyhh:bpppppp0070007000700070	()Z
    //   180: ifeq +17 -> 197
    //   183: getstatic 175	uuuuuu/vvrvrv:bhh00680068h00680068h0068	Luuuuuu/vvrvrv;
    //   186: invokestatic 181	uuuuuu/rrvvrv:b0071q0071qq0071q0071q0071	(Luuuuuu/vvrvrv;)V
    //   189: new 183	java/lang/NullPointerException
    //   192: dup
    //   193: invokespecial 184	java/lang/NullPointerException:<init>	()V
    //   196: athrow
    //   197: getstatic 187	uuuuuu/vvrvrv:bh0068h0068h00680068h0068	Luuuuuu/vvrvrv;
    //   200: invokestatic 181	uuuuuu/rrvvrv:b0071q0071qq0071q0071q0071	(Luuuuuu/vvrvrv;)V
    //   203: ldc 2
    //   205: ldc -67
    //   207: bipush 6
    //   209: iconst_4
    //   210: invokestatic 104	xxxxxx/uxxxxx:bb00620062bb0062b0062b0062	(Ljava/lang/String;CC)Ljava/lang/String;
    //   213: iconst_0
    //   214: anewarray 60	java/lang/Class
    //   217: invokevirtual 64	java/lang/Class:getMethod	(Ljava/lang/String;[Ljava/lang/Class;)Ljava/lang/reflect/Method;
    //   220: astore_1
    //   221: aload_1
    //   222: aconst_null
    //   223: iconst_0
    //   224: anewarray 66	java/lang/Object
    //   227: invokevirtual 72	java/lang/reflect/Method:invoke	(Ljava/lang/Object;[Ljava/lang/Object;)Ljava/lang/Object;
    //   230: astore_1
    //   231: aload_1
    //   232: checkcast 74	java/lang/Integer
    //   235: invokevirtual 77	java/lang/Integer:intValue	()I
    //   238: istore_3
    //   239: getstatic 46	uuuuuu/bmmmbb:b0073ss0073s0073s0073s	I
    //   242: istore_2
    //   243: ldc 2
    //   245: ldc -65
    //   247: bipush 31
    //   249: iconst_1
    //   250: invokestatic 104	xxxxxx/uxxxxx:bb00620062bb0062b0062b0062	(Ljava/lang/String;CC)Ljava/lang/String;
    //   253: iconst_0
    //   254: anewarray 60	java/lang/Class
    //   257: invokevirtual 64	java/lang/Class:getMethod	(Ljava/lang/String;[Ljava/lang/Class;)Ljava/lang/reflect/Method;
    //   260: astore_1
    //   261: aload_1
    //   262: aconst_null
    //   263: iconst_0
    //   264: anewarray 66	java/lang/Object
    //   267: invokevirtual 72	java/lang/reflect/Method:invoke	(Ljava/lang/Object;[Ljava/lang/Object;)Ljava/lang/Object;
    //   270: astore_1
    //   271: aload_1
    //   272: checkcast 74	java/lang/Integer
    //   275: invokevirtual 77	java/lang/Integer:intValue	()I
    //   278: iload_2
    //   279: iload_3
    //   280: iadd
    //   281: imul
    //   282: getstatic 48	uuuuuu/bmmmbb:bs0073s0073s0073s0073s	I
    //   285: irem
    //   286: getstatic 50	uuuuuu/bmmmbb:b00730073s0073s0073s0073s	I
    //   289: if_icmpeq -275 -> 14
    //   292: getstatic 44	uuuuuu/bmmmbb:bsss0073s0073s0073s	I
    //   295: istore_2
    //   296: iload_2
    //   297: getstatic 46	uuuuuu/bmmmbb:b0073ss0073s0073s0073s	I
    //   300: iload_2
    //   301: iadd
    //   302: imul
    //   303: getstatic 48	uuuuuu/bmmmbb:bs0073s0073s0073s0073s	I
    //   306: irem
    //   307: tableswitch	default:+17->324, 0:+27->334
    //   324: bipush 89
    //   326: putstatic 44	uuuuuu/bmmmbb:bsss0073s0073s0073s	I
    //   329: bipush 80
    //   331: putstatic 50	uuuuuu/bmmmbb:b00730073s0073s0073s0073s	I
    //   334: bipush 91
    //   336: putstatic 44	uuuuuu/bmmmbb:bsss0073s0073s0073s	I
    //   339: ldc 2
    //   341: ldc -63
    //   343: sipush 207
    //   346: bipush 27
    //   348: iconst_2
    //   349: invokestatic 58	xxxxxx/uxxxxx:bbbb0062b0062b0062b0062	(Ljava/lang/String;CCC)Ljava/lang/String;
    //   352: iconst_0
    //   353: anewarray 60	java/lang/Class
    //   356: invokevirtual 64	java/lang/Class:getMethod	(Ljava/lang/String;[Ljava/lang/Class;)Ljava/lang/reflect/Method;
    //   359: astore_1
    //   360: aload_1
    //   361: aconst_null
    //   362: iconst_0
    //   363: anewarray 66	java/lang/Object
    //   366: invokevirtual 72	java/lang/reflect/Method:invoke	(Ljava/lang/Object;[Ljava/lang/Object;)Ljava/lang/Object;
    //   369: astore_1
    //   370: aload_1
    //   371: checkcast 74	java/lang/Integer
    //   374: invokevirtual 77	java/lang/Integer:intValue	()I
    //   377: putstatic 50	uuuuuu/bmmmbb:b00730073s0073s0073s0073s	I
    //   380: goto -366 -> 14
    //   383: astore_1
    //   384: aload_1
    //   385: invokevirtual 114	java/lang/reflect/InvocationTargetException:getCause	()Ljava/lang/Throwable;
    //   388: athrow
    //   389: astore_1
    //   390: aload_1
    //   391: invokevirtual 114	java/lang/reflect/InvocationTargetException:getCause	()Ljava/lang/Throwable;
    //   394: athrow
    //   395: astore_1
    //   396: aload_1
    //   397: invokevirtual 114	java/lang/reflect/InvocationTargetException:getCause	()Ljava/lang/Throwable;
    //   400: athrow
    //   401: astore_1
    //   402: aload_1
    //   403: invokevirtual 114	java/lang/reflect/InvocationTargetException:getCause	()Ljava/lang/Throwable;
    //   406: athrow
    //   407: astore_1
    //   408: aload_1
    //   409: invokevirtual 114	java/lang/reflect/InvocationTargetException:getCause	()Ljava/lang/Throwable;
    //   412: athrow
    // Local variable table:
    //   start	length	slot	name	signature
    //   0	413	0	this	bmmmbb
    //   0	413	1	paramAuthenticationResult	android.hardware.fingerprint.FingerprintManager.AuthenticationResult
    //   242	61	2	i	int
    //   238	43	3	j	int
    // Exception table:
    //   from	to	target	type
    //   189	197	8	java/lang/Exception
    //   114	124	383	java/lang/reflect/InvocationTargetException
    //   153	163	389	java/lang/reflect/InvocationTargetException
    //   221	231	395	java/lang/reflect/InvocationTargetException
    //   261	271	401	java/lang/reflect/InvocationTargetException
    //   360	370	407	java/lang/reflect/InvocationTargetException
  }
  
  /* Error */
  public void ba006100610061a0061aa0061a()
  {
    // Byte code:
    //   0: getstatic 44	uuuuuu/bmmmbb:bsss0073s0073s0073s	I
    //   3: getstatic 46	uuuuuu/bmmmbb:b0073ss0073s0073s0073s	I
    //   6: iadd
    //   7: getstatic 44	uuuuuu/bmmmbb:bsss0073s0073s0073s	I
    //   10: imul
    //   11: getstatic 48	uuuuuu/bmmmbb:bs0073s0073s0073s0073s	I
    //   14: irem
    //   15: getstatic 50	uuuuuu/bmmmbb:b00730073s0073s0073s0073s	I
    //   18: if_icmpeq +47 -> 65
    //   21: bipush 52
    //   23: putstatic 44	uuuuuu/bmmmbb:bsss0073s0073s0073s	I
    //   26: ldc 2
    //   28: ldc -65
    //   30: sipush 189
    //   33: iconst_2
    //   34: invokestatic 104	xxxxxx/uxxxxx:bb00620062bb0062b0062b0062	(Ljava/lang/String;CC)Ljava/lang/String;
    //   37: iconst_0
    //   38: anewarray 60	java/lang/Class
    //   41: invokevirtual 64	java/lang/Class:getMethod	(Ljava/lang/String;[Ljava/lang/Class;)Ljava/lang/reflect/Method;
    //   44: astore_2
    //   45: aload_2
    //   46: aconst_null
    //   47: iconst_0
    //   48: anewarray 66	java/lang/Object
    //   51: invokevirtual 72	java/lang/reflect/Method:invoke	(Ljava/lang/Object;[Ljava/lang/Object;)Ljava/lang/Object;
    //   54: astore_2
    //   55: aload_2
    //   56: checkcast 74	java/lang/Integer
    //   59: invokevirtual 77	java/lang/Integer:intValue	()I
    //   62: putstatic 50	uuuuuu/bmmmbb:b00730073s0073s0073s0073s	I
    //   65: ldc 2
    //   67: ldc -60
    //   69: sipush 140
    //   72: iconst_0
    //   73: invokestatic 104	xxxxxx/uxxxxx:bb00620062bb0062b0062b0062	(Ljava/lang/String;CC)Ljava/lang/String;
    //   76: iconst_0
    //   77: anewarray 60	java/lang/Class
    //   80: invokevirtual 64	java/lang/Class:getMethod	(Ljava/lang/String;[Ljava/lang/Class;)Ljava/lang/reflect/Method;
    //   83: astore_2
    //   84: aload_2
    //   85: aload_0
    //   86: iconst_0
    //   87: anewarray 66	java/lang/Object
    //   90: invokevirtual 72	java/lang/reflect/Method:invoke	(Ljava/lang/Object;[Ljava/lang/Object;)Ljava/lang/Object;
    //   93: pop
    //   94: getstatic 44	uuuuuu/bmmmbb:bsss0073s0073s0073s	I
    //   97: getstatic 46	uuuuuu/bmmmbb:b0073ss0073s0073s0073s	I
    //   100: iadd
    //   101: getstatic 44	uuuuuu/bmmmbb:bsss0073s0073s0073s	I
    //   104: imul
    //   105: getstatic 48	uuuuuu/bmmmbb:bs0073s0073s0073s0073s	I
    //   108: irem
    //   109: getstatic 50	uuuuuu/bmmmbb:b00730073s0073s0073s0073s	I
    //   112: if_icmpeq +81 -> 193
    //   115: ldc 2
    //   117: ldc -58
    //   119: bipush 100
    //   121: bipush 115
    //   123: iconst_2
    //   124: invokestatic 58	xxxxxx/uxxxxx:bbbb0062b0062b0062b0062	(Ljava/lang/String;CCC)Ljava/lang/String;
    //   127: iconst_0
    //   128: anewarray 60	java/lang/Class
    //   131: invokevirtual 64	java/lang/Class:getMethod	(Ljava/lang/String;[Ljava/lang/Class;)Ljava/lang/reflect/Method;
    //   134: astore_2
    //   135: aload_2
    //   136: aconst_null
    //   137: iconst_0
    //   138: anewarray 66	java/lang/Object
    //   141: invokevirtual 72	java/lang/reflect/Method:invoke	(Ljava/lang/Object;[Ljava/lang/Object;)Ljava/lang/Object;
    //   144: astore_2
    //   145: aload_2
    //   146: checkcast 74	java/lang/Integer
    //   149: invokevirtual 77	java/lang/Integer:intValue	()I
    //   152: putstatic 44	uuuuuu/bmmmbb:bsss0073s0073s0073s	I
    //   155: ldc 2
    //   157: ldc -56
    //   159: bipush 115
    //   161: iconst_5
    //   162: invokestatic 104	xxxxxx/uxxxxx:bb00620062bb0062b0062b0062	(Ljava/lang/String;CC)Ljava/lang/String;
    //   165: iconst_0
    //   166: anewarray 60	java/lang/Class
    //   169: invokevirtual 64	java/lang/Class:getMethod	(Ljava/lang/String;[Ljava/lang/Class;)Ljava/lang/reflect/Method;
    //   172: astore_2
    //   173: aload_2
    //   174: aconst_null
    //   175: iconst_0
    //   176: anewarray 66	java/lang/Object
    //   179: invokevirtual 72	java/lang/reflect/Method:invoke	(Ljava/lang/Object;[Ljava/lang/Object;)Ljava/lang/Object;
    //   182: astore_2
    //   183: aload_2
    //   184: checkcast 74	java/lang/Integer
    //   187: invokevirtual 77	java/lang/Integer:intValue	()I
    //   190: putstatic 50	uuuuuu/bmmmbb:b00730073s0073s0073s0073s	I
    //   193: getstatic 44	uuuuuu/bmmmbb:bsss0073s0073s0073s	I
    //   196: istore_1
    //   197: iload_1
    //   198: getstatic 46	uuuuuu/bmmmbb:b0073ss0073s0073s0073s	I
    //   201: iload_1
    //   202: iadd
    //   203: imul
    //   204: getstatic 48	uuuuuu/bmmmbb:bs0073s0073s0073s0073s	I
    //   207: irem
    //   208: tableswitch	default:+20->228, 0:+64->272
    //   228: bipush 57
    //   230: putstatic 44	uuuuuu/bmmmbb:bsss0073s0073s0073s	I
    //   233: ldc 2
    //   235: ldc -54
    //   237: sipush 133
    //   240: iconst_2
    //   241: invokestatic 104	xxxxxx/uxxxxx:bb00620062bb0062b0062b0062	(Ljava/lang/String;CC)Ljava/lang/String;
    //   244: iconst_0
    //   245: anewarray 60	java/lang/Class
    //   248: invokevirtual 64	java/lang/Class:getMethod	(Ljava/lang/String;[Ljava/lang/Class;)Ljava/lang/reflect/Method;
    //   251: astore_2
    //   252: aload_2
    //   253: aconst_null
    //   254: iconst_0
    //   255: anewarray 66	java/lang/Object
    //   258: invokevirtual 72	java/lang/reflect/Method:invoke	(Ljava/lang/Object;[Ljava/lang/Object;)Ljava/lang/Object;
    //   261: astore_2
    //   262: aload_2
    //   263: checkcast 74	java/lang/Integer
    //   266: invokevirtual 77	java/lang/Integer:intValue	()I
    //   269: putstatic 50	uuuuuu/bmmmbb:b00730073s0073s0073s0073s	I
    //   272: aload_0
    //   273: invokespecial 204	uuuuuu/ssssst:ba006100610061a0061aa0061a	()V
    //   276: getstatic 44	uuuuuu/bmmmbb:bsss0073s0073s0073s	I
    //   279: istore_1
    //   280: iload_1
    //   281: getstatic 46	uuuuuu/bmmmbb:b0073ss0073s0073s0073s	I
    //   284: iload_1
    //   285: iadd
    //   286: imul
    //   287: getstatic 48	uuuuuu/bmmmbb:bs0073s0073s0073s0073s	I
    //   290: irem
    //   291: tableswitch	default:+17->308, 0:+95->386
    //   308: ldc 2
    //   310: ldc -50
    //   312: sipush 166
    //   315: iconst_5
    //   316: invokestatic 104	xxxxxx/uxxxxx:bb00620062bb0062b0062b0062	(Ljava/lang/String;CC)Ljava/lang/String;
    //   319: iconst_0
    //   320: anewarray 60	java/lang/Class
    //   323: invokevirtual 64	java/lang/Class:getMethod	(Ljava/lang/String;[Ljava/lang/Class;)Ljava/lang/reflect/Method;
    //   326: astore_2
    //   327: aload_2
    //   328: aconst_null
    //   329: iconst_0
    //   330: anewarray 66	java/lang/Object
    //   333: invokevirtual 72	java/lang/reflect/Method:invoke	(Ljava/lang/Object;[Ljava/lang/Object;)Ljava/lang/Object;
    //   336: astore_2
    //   337: aload_2
    //   338: checkcast 74	java/lang/Integer
    //   341: invokevirtual 77	java/lang/Integer:intValue	()I
    //   344: putstatic 44	uuuuuu/bmmmbb:bsss0073s0073s0073s	I
    //   347: ldc 2
    //   349: ldc -48
    //   351: sipush 143
    //   354: iconst_2
    //   355: invokestatic 104	xxxxxx/uxxxxx:bb00620062bb0062b0062b0062	(Ljava/lang/String;CC)Ljava/lang/String;
    //   358: iconst_0
    //   359: anewarray 60	java/lang/Class
    //   362: invokevirtual 64	java/lang/Class:getMethod	(Ljava/lang/String;[Ljava/lang/Class;)Ljava/lang/reflect/Method;
    //   365: astore_2
    //   366: aload_2
    //   367: aconst_null
    //   368: iconst_0
    //   369: anewarray 66	java/lang/Object
    //   372: invokevirtual 72	java/lang/reflect/Method:invoke	(Ljava/lang/Object;[Ljava/lang/Object;)Ljava/lang/Object;
    //   375: astore_2
    //   376: aload_2
    //   377: checkcast 74	java/lang/Integer
    //   380: invokevirtual 77	java/lang/Integer:intValue	()I
    //   383: putstatic 50	uuuuuu/bmmmbb:b00730073s0073s0073s0073s	I
    //   386: return
    //   387: astore_2
    //   388: aload_2
    //   389: invokevirtual 114	java/lang/reflect/InvocationTargetException:getCause	()Ljava/lang/Throwable;
    //   392: athrow
    //   393: astore_2
    //   394: aload_2
    //   395: invokevirtual 114	java/lang/reflect/InvocationTargetException:getCause	()Ljava/lang/Throwable;
    //   398: athrow
    //   399: astore_2
    //   400: aload_2
    //   401: invokevirtual 114	java/lang/reflect/InvocationTargetException:getCause	()Ljava/lang/Throwable;
    //   404: athrow
    //   405: astore_2
    //   406: aload_2
    //   407: invokevirtual 114	java/lang/reflect/InvocationTargetException:getCause	()Ljava/lang/Throwable;
    //   410: athrow
    //   411: astore_2
    //   412: aload_2
    //   413: invokevirtual 114	java/lang/reflect/InvocationTargetException:getCause	()Ljava/lang/Throwable;
    //   416: athrow
    //   417: astore_2
    //   418: aload_2
    //   419: invokevirtual 114	java/lang/reflect/InvocationTargetException:getCause	()Ljava/lang/Throwable;
    //   422: athrow
    //   423: astore_2
    //   424: aload_2
    //   425: invokevirtual 114	java/lang/reflect/InvocationTargetException:getCause	()Ljava/lang/Throwable;
    //   428: athrow
    // Local variable table:
    //   start	length	slot	name	signature
    //   0	429	0	this	bmmmbb
    //   196	91	1	i	int
    //   44	333	2	localObject	Object
    //   387	2	2	localInvocationTargetException1	java.lang.reflect.InvocationTargetException
    //   393	2	2	localInvocationTargetException2	java.lang.reflect.InvocationTargetException
    //   399	2	2	localInvocationTargetException3	java.lang.reflect.InvocationTargetException
    //   405	2	2	localInvocationTargetException4	java.lang.reflect.InvocationTargetException
    //   411	2	2	localInvocationTargetException5	java.lang.reflect.InvocationTargetException
    //   417	2	2	localInvocationTargetException6	java.lang.reflect.InvocationTargetException
    //   423	2	2	localInvocationTargetException7	java.lang.reflect.InvocationTargetException
    // Exception table:
    //   from	to	target	type
    //   45	55	387	java/lang/reflect/InvocationTargetException
    //   135	145	393	java/lang/reflect/InvocationTargetException
    //   173	183	399	java/lang/reflect/InvocationTargetException
    //   84	94	405	java/lang/reflect/InvocationTargetException
    //   327	337	411	java/lang/reflect/InvocationTargetException
    //   366	376	417	java/lang/reflect/InvocationTargetException
    //   252	262	423	java/lang/reflect/InvocationTargetException
  }
  
  /* Error */
  public void bo006F006F006F006Foo006F006F006F()
  {
    // Byte code:
    //   0: aload_0
    //   1: getfield 122	uuuuuu/bmmmbb:b0073s0073ss0073s0073s	Luuuuuu/mmmmmb;
    //   4: astore 5
    //   6: ldc 2
    //   8: ldc -17
    //   10: sipush 135
    //   13: iconst_3
    //   14: invokestatic 104	xxxxxx/uxxxxx:bb00620062bb0062b0062b0062	(Ljava/lang/String;CC)Ljava/lang/String;
    //   17: iconst_0
    //   18: anewarray 60	java/lang/Class
    //   21: invokevirtual 64	java/lang/Class:getMethod	(Ljava/lang/String;[Ljava/lang/Class;)Ljava/lang/reflect/Method;
    //   24: astore 6
    //   26: aload 6
    //   28: aconst_null
    //   29: iconst_0
    //   30: anewarray 66	java/lang/Object
    //   33: invokevirtual 72	java/lang/reflect/Method:invoke	(Ljava/lang/Object;[Ljava/lang/Object;)Ljava/lang/Object;
    //   36: astore 6
    //   38: aload 6
    //   40: checkcast 74	java/lang/Integer
    //   43: invokevirtual 77	java/lang/Integer:intValue	()I
    //   46: istore_1
    //   47: getstatic 44	uuuuuu/bmmmbb:bsss0073s0073s0073s	I
    //   50: getstatic 46	uuuuuu/bmmmbb:b0073ss0073s0073s0073s	I
    //   53: iadd
    //   54: getstatic 44	uuuuuu/bmmmbb:bsss0073s0073s0073s	I
    //   57: imul
    //   58: getstatic 48	uuuuuu/bmmmbb:bs0073s0073s0073s0073s	I
    //   61: irem
    //   62: getstatic 50	uuuuuu/bmmmbb:b00730073s0073s0073s0073s	I
    //   65: if_icmpeq +90 -> 155
    //   68: ldc 2
    //   70: ldc -15
    //   72: bipush 41
    //   74: iconst_2
    //   75: invokestatic 104	xxxxxx/uxxxxx:bb00620062bb0062b0062b0062	(Ljava/lang/String;CC)Ljava/lang/String;
    //   78: iconst_0
    //   79: anewarray 60	java/lang/Class
    //   82: invokevirtual 64	java/lang/Class:getMethod	(Ljava/lang/String;[Ljava/lang/Class;)Ljava/lang/reflect/Method;
    //   85: astore 6
    //   87: aload 6
    //   89: aconst_null
    //   90: iconst_0
    //   91: anewarray 66	java/lang/Object
    //   94: invokevirtual 72	java/lang/reflect/Method:invoke	(Ljava/lang/Object;[Ljava/lang/Object;)Ljava/lang/Object;
    //   97: astore 6
    //   99: aload 6
    //   101: checkcast 74	java/lang/Integer
    //   104: invokevirtual 77	java/lang/Integer:intValue	()I
    //   107: putstatic 44	uuuuuu/bmmmbb:bsss0073s0073s0073s	I
    //   110: ldc 2
    //   112: ldc -13
    //   114: bipush 34
    //   116: sipush 152
    //   119: iconst_3
    //   120: invokestatic 58	xxxxxx/uxxxxx:bbbb0062b0062b0062b0062	(Ljava/lang/String;CCC)Ljava/lang/String;
    //   123: iconst_0
    //   124: anewarray 60	java/lang/Class
    //   127: invokevirtual 64	java/lang/Class:getMethod	(Ljava/lang/String;[Ljava/lang/Class;)Ljava/lang/reflect/Method;
    //   130: astore 6
    //   132: aload 6
    //   134: aconst_null
    //   135: iconst_0
    //   136: anewarray 66	java/lang/Object
    //   139: invokevirtual 72	java/lang/reflect/Method:invoke	(Ljava/lang/Object;[Ljava/lang/Object;)Ljava/lang/Object;
    //   142: astore 6
    //   144: aload 6
    //   146: checkcast 74	java/lang/Integer
    //   149: invokevirtual 77	java/lang/Integer:intValue	()I
    //   152: putstatic 50	uuuuuu/bmmmbb:b00730073s0073s0073s0073s	I
    //   155: ldc 2
    //   157: ldc -11
    //   159: bipush 49
    //   161: iconst_1
    //   162: invokestatic 104	xxxxxx/uxxxxx:bb00620062bb0062b0062b0062	(Ljava/lang/String;CC)Ljava/lang/String;
    //   165: iconst_0
    //   166: anewarray 60	java/lang/Class
    //   169: invokevirtual 64	java/lang/Class:getMethod	(Ljava/lang/String;[Ljava/lang/Class;)Ljava/lang/reflect/Method;
    //   172: astore 6
    //   174: aload 6
    //   176: aconst_null
    //   177: iconst_0
    //   178: anewarray 66	java/lang/Object
    //   181: invokevirtual 72	java/lang/reflect/Method:invoke	(Ljava/lang/Object;[Ljava/lang/Object;)Ljava/lang/Object;
    //   184: astore 6
    //   186: aload 6
    //   188: checkcast 74	java/lang/Integer
    //   191: invokevirtual 77	java/lang/Integer:intValue	()I
    //   194: istore_2
    //   195: ldc 2
    //   197: ldc 100
    //   199: bipush 39
    //   201: iconst_2
    //   202: invokestatic 104	xxxxxx/uxxxxx:bb00620062bb0062b0062b0062	(Ljava/lang/String;CC)Ljava/lang/String;
    //   205: iconst_0
    //   206: anewarray 60	java/lang/Class
    //   209: invokevirtual 64	java/lang/Class:getMethod	(Ljava/lang/String;[Ljava/lang/Class;)Ljava/lang/reflect/Method;
    //   212: astore 6
    //   214: aload 6
    //   216: aconst_null
    //   217: iconst_0
    //   218: anewarray 66	java/lang/Object
    //   221: invokevirtual 72	java/lang/reflect/Method:invoke	(Ljava/lang/Object;[Ljava/lang/Object;)Ljava/lang/Object;
    //   224: astore 6
    //   226: aload 6
    //   228: checkcast 74	java/lang/Integer
    //   231: invokevirtual 77	java/lang/Integer:intValue	()I
    //   234: iload_1
    //   235: iload_2
    //   236: iadd
    //   237: imul
    //   238: getstatic 48	uuuuuu/bmmmbb:bs0073s0073s0073s0073s	I
    //   241: irem
    //   242: getstatic 50	uuuuuu/bmmmbb:b00730073s0073s0073s0073s	I
    //   245: if_icmpeq +374 -> 619
    //   248: getstatic 44	uuuuuu/bmmmbb:bsss0073s0073s0073s	I
    //   251: istore_1
    //   252: getstatic 46	uuuuuu/bmmmbb:b0073ss0073s0073s0073s	I
    //   255: istore_2
    //   256: ldc 2
    //   258: ldc -9
    //   260: bipush 52
    //   262: iconst_2
    //   263: invokestatic 104	xxxxxx/uxxxxx:bb00620062bb0062b0062b0062	(Ljava/lang/String;CC)Ljava/lang/String;
    //   266: iconst_0
    //   267: anewarray 60	java/lang/Class
    //   270: invokevirtual 64	java/lang/Class:getMethod	(Ljava/lang/String;[Ljava/lang/Class;)Ljava/lang/reflect/Method;
    //   273: astore 6
    //   275: aload 6
    //   277: aconst_null
    //   278: iconst_0
    //   279: anewarray 66	java/lang/Object
    //   282: invokevirtual 72	java/lang/reflect/Method:invoke	(Ljava/lang/Object;[Ljava/lang/Object;)Ljava/lang/Object;
    //   285: astore 6
    //   287: iload_2
    //   288: iload_1
    //   289: iadd
    //   290: iload_1
    //   291: imul
    //   292: aload 6
    //   294: checkcast 74	java/lang/Integer
    //   297: invokevirtual 77	java/lang/Integer:intValue	()I
    //   300: irem
    //   301: tableswitch	default:+19->320, 0:+109->410
    //   320: ldc 2
    //   322: ldc -7
    //   324: bipush 77
    //   326: sipush 191
    //   329: iconst_0
    //   330: invokestatic 58	xxxxxx/uxxxxx:bbbb0062b0062b0062b0062	(Ljava/lang/String;CCC)Ljava/lang/String;
    //   333: iconst_0
    //   334: anewarray 60	java/lang/Class
    //   337: invokevirtual 64	java/lang/Class:getMethod	(Ljava/lang/String;[Ljava/lang/Class;)Ljava/lang/reflect/Method;
    //   340: astore 6
    //   342: aload 6
    //   344: aconst_null
    //   345: iconst_0
    //   346: anewarray 66	java/lang/Object
    //   349: invokevirtual 72	java/lang/reflect/Method:invoke	(Ljava/lang/Object;[Ljava/lang/Object;)Ljava/lang/Object;
    //   352: astore 6
    //   354: aload 6
    //   356: checkcast 74	java/lang/Integer
    //   359: invokevirtual 77	java/lang/Integer:intValue	()I
    //   362: putstatic 44	uuuuuu/bmmmbb:bsss0073s0073s0073s	I
    //   365: ldc 2
    //   367: ldc -5
    //   369: bipush 125
    //   371: sipush 164
    //   374: iconst_1
    //   375: invokestatic 58	xxxxxx/uxxxxx:bbbb0062b0062b0062b0062	(Ljava/lang/String;CCC)Ljava/lang/String;
    //   378: iconst_0
    //   379: anewarray 60	java/lang/Class
    //   382: invokevirtual 64	java/lang/Class:getMethod	(Ljava/lang/String;[Ljava/lang/Class;)Ljava/lang/reflect/Method;
    //   385: astore 6
    //   387: aload 6
    //   389: aconst_null
    //   390: iconst_0
    //   391: anewarray 66	java/lang/Object
    //   394: invokevirtual 72	java/lang/reflect/Method:invoke	(Ljava/lang/Object;[Ljava/lang/Object;)Ljava/lang/Object;
    //   397: astore 6
    //   399: aload 6
    //   401: checkcast 74	java/lang/Integer
    //   404: invokevirtual 77	java/lang/Integer:intValue	()I
    //   407: putstatic 50	uuuuuu/bmmmbb:b00730073s0073s0073s0073s	I
    //   410: ldc 2
    //   412: ldc -3
    //   414: bipush 45
    //   416: iconst_3
    //   417: invokestatic 104	xxxxxx/uxxxxx:bb00620062bb0062b0062b0062	(Ljava/lang/String;CC)Ljava/lang/String;
    //   420: iconst_0
    //   421: anewarray 60	java/lang/Class
    //   424: invokevirtual 64	java/lang/Class:getMethod	(Ljava/lang/String;[Ljava/lang/Class;)Ljava/lang/reflect/Method;
    //   427: astore 6
    //   429: aload 6
    //   431: aconst_null
    //   432: iconst_0
    //   433: anewarray 66	java/lang/Object
    //   436: invokevirtual 72	java/lang/reflect/Method:invoke	(Ljava/lang/Object;[Ljava/lang/Object;)Ljava/lang/Object;
    //   439: astore 6
    //   441: aload 6
    //   443: checkcast 74	java/lang/Integer
    //   446: invokevirtual 77	java/lang/Integer:intValue	()I
    //   449: putstatic 44	uuuuuu/bmmmbb:bsss0073s0073s0073s	I
    //   452: ldc 2
    //   454: ldc -1
    //   456: bipush 13
    //   458: sipush 225
    //   461: iconst_3
    //   462: invokestatic 58	xxxxxx/uxxxxx:bbbb0062b0062b0062b0062	(Ljava/lang/String;CCC)Ljava/lang/String;
    //   465: iconst_0
    //   466: anewarray 60	java/lang/Class
    //   469: invokevirtual 64	java/lang/Class:getMethod	(Ljava/lang/String;[Ljava/lang/Class;)Ljava/lang/reflect/Method;
    //   472: astore 6
    //   474: aload 6
    //   476: aconst_null
    //   477: iconst_0
    //   478: anewarray 66	java/lang/Object
    //   481: invokevirtual 72	java/lang/reflect/Method:invoke	(Ljava/lang/Object;[Ljava/lang/Object;)Ljava/lang/Object;
    //   484: astore 6
    //   486: aload 6
    //   488: checkcast 74	java/lang/Integer
    //   491: invokevirtual 77	java/lang/Integer:intValue	()I
    //   494: putstatic 50	uuuuuu/bmmmbb:b00730073s0073s0073s0073s	I
    //   497: getstatic 44	uuuuuu/bmmmbb:bsss0073s0073s0073s	I
    //   500: istore_1
    //   501: getstatic 46	uuuuuu/bmmmbb:b0073ss0073s0073s0073s	I
    //   504: istore_2
    //   505: getstatic 44	uuuuuu/bmmmbb:bsss0073s0073s0073s	I
    //   508: istore_3
    //   509: getstatic 48	uuuuuu/bmmmbb:bs0073s0073s0073s0073s	I
    //   512: istore 4
    //   514: ldc 2
    //   516: ldc_w 257
    //   519: bipush 103
    //   521: sipush 192
    //   524: iconst_0
    //   525: invokestatic 58	xxxxxx/uxxxxx:bbbb0062b0062b0062b0062	(Ljava/lang/String;CCC)Ljava/lang/String;
    //   528: iconst_0
    //   529: anewarray 60	java/lang/Class
    //   532: invokevirtual 64	java/lang/Class:getMethod	(Ljava/lang/String;[Ljava/lang/Class;)Ljava/lang/reflect/Method;
    //   535: astore 6
    //   537: aload 6
    //   539: aconst_null
    //   540: iconst_0
    //   541: anewarray 66	java/lang/Object
    //   544: invokevirtual 72	java/lang/reflect/Method:invoke	(Ljava/lang/Object;[Ljava/lang/Object;)Ljava/lang/Object;
    //   547: astore 6
    //   549: iload_1
    //   550: iload_2
    //   551: iadd
    //   552: iload_3
    //   553: imul
    //   554: iload 4
    //   556: irem
    //   557: aload 6
    //   559: checkcast 74	java/lang/Integer
    //   562: invokevirtual 77	java/lang/Integer:intValue	()I
    //   565: if_icmpeq +54 -> 619
    //   568: bipush 70
    //   570: putstatic 44	uuuuuu/bmmmbb:bsss0073s0073s0073s	I
    //   573: ldc 2
    //   575: ldc_w 259
    //   578: sipush 133
    //   581: bipush 117
    //   583: iconst_3
    //   584: invokestatic 58	xxxxxx/uxxxxx:bbbb0062b0062b0062b0062	(Ljava/lang/String;CCC)Ljava/lang/String;
    //   587: iconst_0
    //   588: anewarray 60	java/lang/Class
    //   591: invokevirtual 64	java/lang/Class:getMethod	(Ljava/lang/String;[Ljava/lang/Class;)Ljava/lang/reflect/Method;
    //   594: astore 6
    //   596: aload 6
    //   598: aconst_null
    //   599: iconst_0
    //   600: anewarray 66	java/lang/Object
    //   603: invokevirtual 72	java/lang/reflect/Method:invoke	(Ljava/lang/Object;[Ljava/lang/Object;)Ljava/lang/Object;
    //   606: astore 6
    //   608: aload 6
    //   610: checkcast 74	java/lang/Integer
    //   613: invokevirtual 77	java/lang/Integer:intValue	()I
    //   616: putstatic 50	uuuuuu/bmmmbb:b00730073s0073s0073s0073s	I
    //   619: aload 5
    //   621: invokevirtual 262	uuuuuu/mmmmmb:bo006Fo006F006Fo006Fo006F006F	()V
    //   624: return
    //   625: astore 5
    //   627: aload 5
    //   629: invokevirtual 114	java/lang/reflect/InvocationTargetException:getCause	()Ljava/lang/Throwable;
    //   632: athrow
    //   633: astore 5
    //   635: aload 5
    //   637: invokevirtual 114	java/lang/reflect/InvocationTargetException:getCause	()Ljava/lang/Throwable;
    //   640: athrow
    //   641: astore 5
    //   643: aload 5
    //   645: invokevirtual 114	java/lang/reflect/InvocationTargetException:getCause	()Ljava/lang/Throwable;
    //   648: athrow
    //   649: astore 5
    //   651: aload 5
    //   653: invokevirtual 114	java/lang/reflect/InvocationTargetException:getCause	()Ljava/lang/Throwable;
    //   656: athrow
    //   657: astore 5
    //   659: aload 5
    //   661: invokevirtual 114	java/lang/reflect/InvocationTargetException:getCause	()Ljava/lang/Throwable;
    //   664: athrow
    //   665: astore 5
    //   667: aload 5
    //   669: invokevirtual 114	java/lang/reflect/InvocationTargetException:getCause	()Ljava/lang/Throwable;
    //   672: athrow
    //   673: astore 5
    //   675: aload 5
    //   677: invokevirtual 114	java/lang/reflect/InvocationTargetException:getCause	()Ljava/lang/Throwable;
    //   680: athrow
    //   681: astore 5
    //   683: aload 5
    //   685: invokevirtual 114	java/lang/reflect/InvocationTargetException:getCause	()Ljava/lang/Throwable;
    //   688: athrow
    //   689: astore 5
    //   691: aload 5
    //   693: invokevirtual 114	java/lang/reflect/InvocationTargetException:getCause	()Ljava/lang/Throwable;
    //   696: athrow
    //   697: astore 5
    //   699: aload 5
    //   701: invokevirtual 114	java/lang/reflect/InvocationTargetException:getCause	()Ljava/lang/Throwable;
    //   704: athrow
    //   705: astore 5
    //   707: aload 5
    //   709: invokevirtual 114	java/lang/reflect/InvocationTargetException:getCause	()Ljava/lang/Throwable;
    //   712: athrow
    //   713: astore 5
    //   715: aload 5
    //   717: invokevirtual 114	java/lang/reflect/InvocationTargetException:getCause	()Ljava/lang/Throwable;
    //   720: athrow
    // Local variable table:
    //   start	length	slot	name	signature
    //   0	721	0	this	bmmmbb
    //   46	506	1	i	int
    //   194	358	2	j	int
    //   508	46	3	k	int
    //   512	45	4	m	int
    //   4	616	5	localMmmmmb	mmmmmb
    //   625	3	5	localInvocationTargetException1	java.lang.reflect.InvocationTargetException
    //   633	3	5	localInvocationTargetException2	java.lang.reflect.InvocationTargetException
    //   641	3	5	localInvocationTargetException3	java.lang.reflect.InvocationTargetException
    //   649	3	5	localInvocationTargetException4	java.lang.reflect.InvocationTargetException
    //   657	3	5	localInvocationTargetException5	java.lang.reflect.InvocationTargetException
    //   665	3	5	localInvocationTargetException6	java.lang.reflect.InvocationTargetException
    //   673	3	5	localInvocationTargetException7	java.lang.reflect.InvocationTargetException
    //   681	3	5	localInvocationTargetException8	java.lang.reflect.InvocationTargetException
    //   689	3	5	localInvocationTargetException9	java.lang.reflect.InvocationTargetException
    //   697	3	5	localInvocationTargetException10	java.lang.reflect.InvocationTargetException
    //   705	3	5	localInvocationTargetException11	java.lang.reflect.InvocationTargetException
    //   713	3	5	localInvocationTargetException12	java.lang.reflect.InvocationTargetException
    //   24	585	6	localObject	Object
    // Exception table:
    //   from	to	target	type
    //   26	38	625	java/lang/reflect/InvocationTargetException
    //   174	186	633	java/lang/reflect/InvocationTargetException
    //   214	226	641	java/lang/reflect/InvocationTargetException
    //   342	354	649	java/lang/reflect/InvocationTargetException
    //   387	399	657	java/lang/reflect/InvocationTargetException
    //   429	441	665	java/lang/reflect/InvocationTargetException
    //   474	486	673	java/lang/reflect/InvocationTargetException
    //   537	549	681	java/lang/reflect/InvocationTargetException
    //   275	287	689	java/lang/reflect/InvocationTargetException
    //   596	608	697	java/lang/reflect/InvocationTargetException
    //   87	99	705	java/lang/reflect/InvocationTargetException
    //   132	144	713	java/lang/reflect/InvocationTargetException
  }
  
  /* Error */
  public void bo006F006F006Fo006Foo006F006F(int paramInt, CharSequence paramCharSequence)
  {
    // Byte code:
    //   0: aload_0
    //   1: invokevirtual 81	uuuuuu/bmmmbb:bkk006Bk006Bk006Bk006Bk	()Z
    //   4: ifeq +13 -> 17
    //   7: aload_0
    //   8: getfield 122	uuuuuu/bmmmbb:b0073s0073ss0073s0073s	Luuuuuu/mmmmmb;
    //   11: invokevirtual 267	uuuuuu/mmmmmb:b006F006F006F006Foo006Fo006F006F	()Z
    //   14: ifeq +4 -> 18
    //   17: return
    //   18: aload_0
    //   19: getfield 122	uuuuuu/bmmmbb:b0073s0073ss0073s0073s	Luuuuuu/mmmmmb;
    //   22: invokevirtual 262	uuuuuu/mmmmmb:bo006Fo006F006Fo006Fo006F006F	()V
    //   25: aload_0
    //   26: getfield 85	uuuuuu/bmmmbb:bnnnnn006E006E006En	Luuuuuu/ttssst$tsssst;
    //   29: checkcast 87	uuuuuu/bmbbmb$mbbbmb
    //   32: astore_2
    //   33: getstatic 270	uuuuuu/mbbbbm:b0073s0073sss0073ss	Luuuuuu/mbbbbm;
    //   36: astore 5
    //   38: getstatic 44	uuuuuu/bmmmbb:bsss0073s0073s0073s	I
    //   41: istore_1
    //   42: getstatic 46	uuuuuu/bmmmbb:b0073ss0073s0073s0073s	I
    //   45: istore_3
    //   46: getstatic 44	uuuuuu/bmmmbb:bsss0073s0073s0073s	I
    //   49: istore 4
    //   51: ldc 2
    //   53: ldc_w 272
    //   56: sipush 251
    //   59: iconst_3
    //   60: invokestatic 104	xxxxxx/uxxxxx:bb00620062bb0062b0062b0062	(Ljava/lang/String;CC)Ljava/lang/String;
    //   63: iconst_0
    //   64: anewarray 60	java/lang/Class
    //   67: invokevirtual 64	java/lang/Class:getMethod	(Ljava/lang/String;[Ljava/lang/Class;)Ljava/lang/reflect/Method;
    //   70: astore 6
    //   72: aload 6
    //   74: aconst_null
    //   75: iconst_0
    //   76: anewarray 66	java/lang/Object
    //   79: invokevirtual 72	java/lang/reflect/Method:invoke	(Ljava/lang/Object;[Ljava/lang/Object;)Ljava/lang/Object;
    //   82: astore 6
    //   84: iload 4
    //   86: iload_1
    //   87: iload_3
    //   88: iadd
    //   89: imul
    //   90: aload 6
    //   92: checkcast 74	java/lang/Integer
    //   95: invokevirtual 77	java/lang/Integer:intValue	()I
    //   98: irem
    //   99: getstatic 50	uuuuuu/bmmmbb:b00730073s0073s0073s0073s	I
    //   102: if_icmpeq +55 -> 157
    //   105: bipush 44
    //   107: putstatic 44	uuuuuu/bmmmbb:bsss0073s0073s0073s	I
    //   110: ldc 2
    //   112: ldc_w 274
    //   115: sipush 222
    //   118: sipush 142
    //   121: iconst_1
    //   122: invokestatic 58	xxxxxx/uxxxxx:bbbb0062b0062b0062b0062	(Ljava/lang/String;CCC)Ljava/lang/String;
    //   125: iconst_0
    //   126: anewarray 60	java/lang/Class
    //   129: invokevirtual 64	java/lang/Class:getMethod	(Ljava/lang/String;[Ljava/lang/Class;)Ljava/lang/reflect/Method;
    //   132: astore 6
    //   134: aload 6
    //   136: aconst_null
    //   137: iconst_0
    //   138: anewarray 66	java/lang/Object
    //   141: invokevirtual 72	java/lang/reflect/Method:invoke	(Ljava/lang/Object;[Ljava/lang/Object;)Ljava/lang/Object;
    //   144: astore 6
    //   146: aload 6
    //   148: checkcast 74	java/lang/Integer
    //   151: invokevirtual 77	java/lang/Integer:intValue	()I
    //   154: putstatic 50	uuuuuu/bmmmbb:b00730073s0073s0073s0073s	I
    //   157: aload_2
    //   158: aload 5
    //   160: getstatic 277	com/db/pwcc/dbmobile/fingerprint/R$string:fingerprint_dialog_message_max_attempts	I
    //   163: invokeinterface 108 3 0
    //   168: getstatic 44	uuuuuu/bmmmbb:bsss0073s0073s0073s	I
    //   171: istore_1
    //   172: getstatic 46	uuuuuu/bmmmbb:b0073ss0073s0073s0073s	I
    //   175: istore_3
    //   176: getstatic 44	uuuuuu/bmmmbb:bsss0073s0073s0073s	I
    //   179: istore 4
    //   181: ldc 2
    //   183: ldc_w 279
    //   186: bipush 120
    //   188: sipush 144
    //   191: iconst_3
    //   192: invokestatic 58	xxxxxx/uxxxxx:bbbb0062b0062b0062b0062	(Ljava/lang/String;CCC)Ljava/lang/String;
    //   195: iconst_0
    //   196: anewarray 60	java/lang/Class
    //   199: invokevirtual 64	java/lang/Class:getMethod	(Ljava/lang/String;[Ljava/lang/Class;)Ljava/lang/reflect/Method;
    //   202: astore_2
    //   203: aload_2
    //   204: aconst_null
    //   205: iconst_0
    //   206: anewarray 66	java/lang/Object
    //   209: invokevirtual 72	java/lang/reflect/Method:invoke	(Ljava/lang/Object;[Ljava/lang/Object;)Ljava/lang/Object;
    //   212: astore_2
    //   213: iload 4
    //   215: iload_1
    //   216: iload_3
    //   217: iadd
    //   218: imul
    //   219: aload_2
    //   220: checkcast 74	java/lang/Integer
    //   223: invokevirtual 77	java/lang/Integer:intValue	()I
    //   226: irem
    //   227: getstatic 50	uuuuuu/bmmmbb:b00730073s0073s0073s0073s	I
    //   230: if_icmpeq -213 -> 17
    //   233: getstatic 44	uuuuuu/bmmmbb:bsss0073s0073s0073s	I
    //   236: getstatic 46	uuuuuu/bmmmbb:b0073ss0073s0073s0073s	I
    //   239: iadd
    //   240: getstatic 44	uuuuuu/bmmmbb:bsss0073s0073s0073s	I
    //   243: imul
    //   244: getstatic 48	uuuuuu/bmmmbb:bs0073s0073s0073s0073s	I
    //   247: irem
    //   248: getstatic 50	uuuuuu/bmmmbb:b00730073s0073s0073s0073s	I
    //   251: if_icmpeq +197 -> 448
    //   254: bipush 12
    //   256: putstatic 44	uuuuuu/bmmmbb:bsss0073s0073s0073s	I
    //   259: ldc 2
    //   261: ldc_w 281
    //   264: sipush 232
    //   267: iconst_3
    //   268: invokestatic 104	xxxxxx/uxxxxx:bb00620062bb0062b0062b0062	(Ljava/lang/String;CC)Ljava/lang/String;
    //   271: iconst_0
    //   272: anewarray 60	java/lang/Class
    //   275: invokevirtual 64	java/lang/Class:getMethod	(Ljava/lang/String;[Ljava/lang/Class;)Ljava/lang/reflect/Method;
    //   278: astore_2
    //   279: aload_2
    //   280: aconst_null
    //   281: iconst_0
    //   282: anewarray 66	java/lang/Object
    //   285: invokevirtual 72	java/lang/reflect/Method:invoke	(Ljava/lang/Object;[Ljava/lang/Object;)Ljava/lang/Object;
    //   288: astore_2
    //   289: aload_2
    //   290: checkcast 74	java/lang/Integer
    //   293: invokevirtual 77	java/lang/Integer:intValue	()I
    //   296: putstatic 50	uuuuuu/bmmmbb:b00730073s0073s0073s0073s	I
    //   299: getstatic 44	uuuuuu/bmmmbb:bsss0073s0073s0073s	I
    //   302: istore_1
    //   303: getstatic 46	uuuuuu/bmmmbb:b0073ss0073s0073s0073s	I
    //   306: istore_3
    //   307: ldc 2
    //   309: ldc_w 283
    //   312: bipush 48
    //   314: iconst_4
    //   315: invokestatic 104	xxxxxx/uxxxxx:bb00620062bb0062b0062b0062	(Ljava/lang/String;CC)Ljava/lang/String;
    //   318: iconst_0
    //   319: anewarray 60	java/lang/Class
    //   322: invokevirtual 64	java/lang/Class:getMethod	(Ljava/lang/String;[Ljava/lang/Class;)Ljava/lang/reflect/Method;
    //   325: astore_2
    //   326: aload_2
    //   327: aconst_null
    //   328: iconst_0
    //   329: anewarray 66	java/lang/Object
    //   332: invokevirtual 72	java/lang/reflect/Method:invoke	(Ljava/lang/Object;[Ljava/lang/Object;)Ljava/lang/Object;
    //   335: astore_2
    //   336: iload_3
    //   337: iload_1
    //   338: iadd
    //   339: iload_1
    //   340: imul
    //   341: aload_2
    //   342: checkcast 74	java/lang/Integer
    //   345: invokevirtual 77	java/lang/Integer:intValue	()I
    //   348: irem
    //   349: tableswitch	default:+19->368, 0:+99->448
    //   368: ldc 2
    //   370: ldc -32
    //   372: bipush 26
    //   374: sipush 219
    //   377: iconst_0
    //   378: invokestatic 58	xxxxxx/uxxxxx:bbbb0062b0062b0062b0062	(Ljava/lang/String;CCC)Ljava/lang/String;
    //   381: iconst_0
    //   382: anewarray 60	java/lang/Class
    //   385: invokevirtual 64	java/lang/Class:getMethod	(Ljava/lang/String;[Ljava/lang/Class;)Ljava/lang/reflect/Method;
    //   388: astore_2
    //   389: aload_2
    //   390: aconst_null
    //   391: iconst_0
    //   392: anewarray 66	java/lang/Object
    //   395: invokevirtual 72	java/lang/reflect/Method:invoke	(Ljava/lang/Object;[Ljava/lang/Object;)Ljava/lang/Object;
    //   398: astore_2
    //   399: aload_2
    //   400: checkcast 74	java/lang/Integer
    //   403: invokevirtual 77	java/lang/Integer:intValue	()I
    //   406: putstatic 44	uuuuuu/bmmmbb:bsss0073s0073s0073s	I
    //   409: ldc 2
    //   411: ldc_w 285
    //   414: bipush 23
    //   416: iconst_1
    //   417: invokestatic 104	xxxxxx/uxxxxx:bb00620062bb0062b0062b0062	(Ljava/lang/String;CC)Ljava/lang/String;
    //   420: iconst_0
    //   421: anewarray 60	java/lang/Class
    //   424: invokevirtual 64	java/lang/Class:getMethod	(Ljava/lang/String;[Ljava/lang/Class;)Ljava/lang/reflect/Method;
    //   427: astore_2
    //   428: aload_2
    //   429: aconst_null
    //   430: iconst_0
    //   431: anewarray 66	java/lang/Object
    //   434: invokevirtual 72	java/lang/reflect/Method:invoke	(Ljava/lang/Object;[Ljava/lang/Object;)Ljava/lang/Object;
    //   437: astore_2
    //   438: aload_2
    //   439: checkcast 74	java/lang/Integer
    //   442: invokevirtual 77	java/lang/Integer:intValue	()I
    //   445: putstatic 50	uuuuuu/bmmmbb:b00730073s0073s0073s0073s	I
    //   448: bipush 98
    //   450: putstatic 44	uuuuuu/bmmmbb:bsss0073s0073s0073s	I
    //   453: ldc 2
    //   455: ldc_w 287
    //   458: sipush 220
    //   461: bipush 39
    //   463: iconst_1
    //   464: invokestatic 58	xxxxxx/uxxxxx:bbbb0062b0062b0062b0062	(Ljava/lang/String;CCC)Ljava/lang/String;
    //   467: iconst_0
    //   468: anewarray 60	java/lang/Class
    //   471: invokevirtual 64	java/lang/Class:getMethod	(Ljava/lang/String;[Ljava/lang/Class;)Ljava/lang/reflect/Method;
    //   474: astore_2
    //   475: aload_2
    //   476: aconst_null
    //   477: iconst_0
    //   478: anewarray 66	java/lang/Object
    //   481: invokevirtual 72	java/lang/reflect/Method:invoke	(Ljava/lang/Object;[Ljava/lang/Object;)Ljava/lang/Object;
    //   484: astore_2
    //   485: aload_2
    //   486: checkcast 74	java/lang/Integer
    //   489: invokevirtual 77	java/lang/Integer:intValue	()I
    //   492: putstatic 50	uuuuuu/bmmmbb:b00730073s0073s0073s0073s	I
    //   495: return
    //   496: astore_2
    //   497: aload_2
    //   498: invokevirtual 114	java/lang/reflect/InvocationTargetException:getCause	()Ljava/lang/Throwable;
    //   501: athrow
    //   502: astore_2
    //   503: aload_2
    //   504: invokevirtual 114	java/lang/reflect/InvocationTargetException:getCause	()Ljava/lang/Throwable;
    //   507: athrow
    //   508: astore_2
    //   509: aload_2
    //   510: invokevirtual 114	java/lang/reflect/InvocationTargetException:getCause	()Ljava/lang/Throwable;
    //   513: athrow
    //   514: astore_2
    //   515: aload_2
    //   516: invokevirtual 114	java/lang/reflect/InvocationTargetException:getCause	()Ljava/lang/Throwable;
    //   519: athrow
    //   520: astore_2
    //   521: aload_2
    //   522: invokevirtual 114	java/lang/reflect/InvocationTargetException:getCause	()Ljava/lang/Throwable;
    //   525: athrow
    //   526: astore_2
    //   527: aload_2
    //   528: invokevirtual 114	java/lang/reflect/InvocationTargetException:getCause	()Ljava/lang/Throwable;
    //   531: athrow
    //   532: astore_2
    //   533: aload_2
    //   534: invokevirtual 114	java/lang/reflect/InvocationTargetException:getCause	()Ljava/lang/Throwable;
    //   537: athrow
    //   538: astore_2
    //   539: aload_2
    //   540: invokevirtual 114	java/lang/reflect/InvocationTargetException:getCause	()Ljava/lang/Throwable;
    //   543: athrow
    // Local variable table:
    //   start	length	slot	name	signature
    //   0	544	0	this	bmmmbb
    //   0	544	1	paramInt	int
    //   0	544	2	paramCharSequence	CharSequence
    //   45	294	3	i	int
    //   49	170	4	j	int
    //   36	123	5	localMbbbbm	mbbbbm
    //   70	77	6	localObject	Object
    // Exception table:
    //   from	to	target	type
    //   475	485	496	java/lang/reflect/InvocationTargetException
    //   72	84	502	java/lang/reflect/InvocationTargetException
    //   134	146	508	java/lang/reflect/InvocationTargetException
    //   203	213	514	java/lang/reflect/InvocationTargetException
    //   279	289	520	java/lang/reflect/InvocationTargetException
    //   326	336	526	java/lang/reflect/InvocationTargetException
    //   389	399	532	java/lang/reflect/InvocationTargetException
    //   428	438	538	java/lang/reflect/InvocationTargetException
  }
  
  /* Error */
  public bmbbbm bo006Fo006Fo006Fo006F006F006F()
  {
    // Byte code:
    //   0: getstatic 44	uuuuuu/bmmmbb:bsss0073s0073s0073s	I
    //   3: getstatic 46	uuuuuu/bmmmbb:b0073ss0073s0073s0073s	I
    //   6: iadd
    //   7: getstatic 44	uuuuuu/bmmmbb:bsss0073s0073s0073s	I
    //   10: imul
    //   11: getstatic 48	uuuuuu/bmmmbb:bs0073s0073s0073s0073s	I
    //   14: irem
    //   15: getstatic 50	uuuuuu/bmmmbb:b00730073s0073s0073s0073s	I
    //   18: if_icmpeq +322 -> 340
    //   21: getstatic 44	uuuuuu/bmmmbb:bsss0073s0073s0073s	I
    //   24: istore_1
    //   25: getstatic 46	uuuuuu/bmmmbb:b0073ss0073s0073s0073s	I
    //   28: istore_2
    //   29: getstatic 44	uuuuuu/bmmmbb:bsss0073s0073s0073s	I
    //   32: istore_3
    //   33: iload_3
    //   34: getstatic 46	uuuuuu/bmmmbb:b0073ss0073s0073s0073s	I
    //   37: iload_3
    //   38: iadd
    //   39: imul
    //   40: getstatic 48	uuuuuu/bmmmbb:bs0073s0073s0073s0073s	I
    //   43: irem
    //   44: tableswitch	default:+20->64, 0:+69->113
    //   64: bipush 87
    //   66: putstatic 44	uuuuuu/bmmmbb:bsss0073s0073s0073s	I
    //   69: ldc 2
    //   71: ldc 110
    //   73: bipush 76
    //   75: bipush 21
    //   77: iconst_0
    //   78: invokestatic 58	xxxxxx/uxxxxx:bbbb0062b0062b0062b0062	(Ljava/lang/String;CCC)Ljava/lang/String;
    //   81: iconst_0
    //   82: anewarray 60	java/lang/Class
    //   85: invokevirtual 64	java/lang/Class:getMethod	(Ljava/lang/String;[Ljava/lang/Class;)Ljava/lang/reflect/Method;
    //   88: astore 4
    //   90: aload 4
    //   92: aconst_null
    //   93: iconst_0
    //   94: anewarray 66	java/lang/Object
    //   97: invokevirtual 72	java/lang/reflect/Method:invoke	(Ljava/lang/Object;[Ljava/lang/Object;)Ljava/lang/Object;
    //   100: astore 4
    //   102: aload 4
    //   104: checkcast 74	java/lang/Integer
    //   107: invokevirtual 77	java/lang/Integer:intValue	()I
    //   110: putstatic 50	uuuuuu/bmmmbb:b00730073s0073s0073s0073s	I
    //   113: iload_1
    //   114: iload_2
    //   115: iadd
    //   116: getstatic 44	uuuuuu/bmmmbb:bsss0073s0073s0073s	I
    //   119: imul
    //   120: getstatic 48	uuuuuu/bmmmbb:bs0073s0073s0073s0073s	I
    //   123: irem
    //   124: getstatic 50	uuuuuu/bmmmbb:b00730073s0073s0073s0073s	I
    //   127: if_icmpeq +94 -> 221
    //   130: ldc 2
    //   132: ldc_w 291
    //   135: sipush 205
    //   138: bipush 42
    //   140: iconst_3
    //   141: invokestatic 58	xxxxxx/uxxxxx:bbbb0062b0062b0062b0062	(Ljava/lang/String;CCC)Ljava/lang/String;
    //   144: iconst_0
    //   145: anewarray 60	java/lang/Class
    //   148: invokevirtual 64	java/lang/Class:getMethod	(Ljava/lang/String;[Ljava/lang/Class;)Ljava/lang/reflect/Method;
    //   151: astore 4
    //   153: aload 4
    //   155: aconst_null
    //   156: iconst_0
    //   157: anewarray 66	java/lang/Object
    //   160: invokevirtual 72	java/lang/reflect/Method:invoke	(Ljava/lang/Object;[Ljava/lang/Object;)Ljava/lang/Object;
    //   163: astore 4
    //   165: aload 4
    //   167: checkcast 74	java/lang/Integer
    //   170: invokevirtual 77	java/lang/Integer:intValue	()I
    //   173: putstatic 44	uuuuuu/bmmmbb:bsss0073s0073s0073s	I
    //   176: ldc 2
    //   178: ldc_w 293
    //   181: bipush 60
    //   183: bipush 47
    //   185: iconst_2
    //   186: invokestatic 58	xxxxxx/uxxxxx:bbbb0062b0062b0062b0062	(Ljava/lang/String;CCC)Ljava/lang/String;
    //   189: iconst_0
    //   190: anewarray 60	java/lang/Class
    //   193: invokevirtual 64	java/lang/Class:getMethod	(Ljava/lang/String;[Ljava/lang/Class;)Ljava/lang/reflect/Method;
    //   196: astore 4
    //   198: aload 4
    //   200: aconst_null
    //   201: iconst_0
    //   202: anewarray 66	java/lang/Object
    //   205: invokevirtual 72	java/lang/reflect/Method:invoke	(Ljava/lang/Object;[Ljava/lang/Object;)Ljava/lang/Object;
    //   208: astore 4
    //   210: aload 4
    //   212: checkcast 74	java/lang/Integer
    //   215: invokevirtual 77	java/lang/Integer:intValue	()I
    //   218: putstatic 50	uuuuuu/bmmmbb:b00730073s0073s0073s0073s	I
    //   221: ldc 2
    //   223: ldc_w 295
    //   226: sipush 227
    //   229: iconst_4
    //   230: invokestatic 104	xxxxxx/uxxxxx:bb00620062bb0062b0062b0062	(Ljava/lang/String;CC)Ljava/lang/String;
    //   233: iconst_0
    //   234: anewarray 60	java/lang/Class
    //   237: invokevirtual 64	java/lang/Class:getMethod	(Ljava/lang/String;[Ljava/lang/Class;)Ljava/lang/reflect/Method;
    //   240: astore 4
    //   242: aload 4
    //   244: aconst_null
    //   245: iconst_0
    //   246: anewarray 66	java/lang/Object
    //   249: invokevirtual 72	java/lang/reflect/Method:invoke	(Ljava/lang/Object;[Ljava/lang/Object;)Ljava/lang/Object;
    //   252: astore 4
    //   254: aload 4
    //   256: checkcast 74	java/lang/Integer
    //   259: invokevirtual 77	java/lang/Integer:intValue	()I
    //   262: putstatic 44	uuuuuu/bmmmbb:bsss0073s0073s0073s	I
    //   265: bipush 67
    //   267: putstatic 50	uuuuuu/bmmmbb:b00730073s0073s0073s0073s	I
    //   270: getstatic 44	uuuuuu/bmmmbb:bsss0073s0073s0073s	I
    //   273: getstatic 46	uuuuuu/bmmmbb:b0073ss0073s0073s0073s	I
    //   276: iadd
    //   277: getstatic 44	uuuuuu/bmmmbb:bsss0073s0073s0073s	I
    //   280: imul
    //   281: getstatic 48	uuuuuu/bmmmbb:bs0073s0073s0073s0073s	I
    //   284: irem
    //   285: getstatic 50	uuuuuu/bmmmbb:b00730073s0073s0073s0073s	I
    //   288: if_icmpeq +52 -> 340
    //   291: bipush 23
    //   293: putstatic 44	uuuuuu/bmmmbb:bsss0073s0073s0073s	I
    //   296: ldc 2
    //   298: ldc_w 297
    //   301: sipush 240
    //   304: iconst_0
    //   305: invokestatic 104	xxxxxx/uxxxxx:bb00620062bb0062b0062b0062	(Ljava/lang/String;CC)Ljava/lang/String;
    //   308: iconst_0
    //   309: anewarray 60	java/lang/Class
    //   312: invokevirtual 64	java/lang/Class:getMethod	(Ljava/lang/String;[Ljava/lang/Class;)Ljava/lang/reflect/Method;
    //   315: astore 4
    //   317: aload 4
    //   319: aconst_null
    //   320: iconst_0
    //   321: anewarray 66	java/lang/Object
    //   324: invokevirtual 72	java/lang/reflect/Method:invoke	(Ljava/lang/Object;[Ljava/lang/Object;)Ljava/lang/Object;
    //   327: astore 4
    //   329: aload 4
    //   331: checkcast 74	java/lang/Integer
    //   334: invokevirtual 77	java/lang/Integer:intValue	()I
    //   337: putstatic 50	uuuuuu/bmmmbb:b00730073s0073s0073s0073s	I
    //   340: aload_0
    //   341: areturn
    //   342: astore 4
    //   344: aload 4
    //   346: invokevirtual 114	java/lang/reflect/InvocationTargetException:getCause	()Ljava/lang/Throwable;
    //   349: athrow
    //   350: astore 4
    //   352: aload 4
    //   354: invokevirtual 114	java/lang/reflect/InvocationTargetException:getCause	()Ljava/lang/Throwable;
    //   357: athrow
    //   358: astore 4
    //   360: aload 4
    //   362: invokevirtual 114	java/lang/reflect/InvocationTargetException:getCause	()Ljava/lang/Throwable;
    //   365: athrow
    //   366: astore 4
    //   368: aload 4
    //   370: invokevirtual 114	java/lang/reflect/InvocationTargetException:getCause	()Ljava/lang/Throwable;
    //   373: athrow
    //   374: astore 4
    //   376: aload 4
    //   378: invokevirtual 114	java/lang/reflect/InvocationTargetException:getCause	()Ljava/lang/Throwable;
    //   381: athrow
    // Local variable table:
    //   start	length	slot	name	signature
    //   0	382	0	this	bmmmbb
    //   24	92	1	i	int
    //   28	88	2	j	int
    //   32	8	3	k	int
    //   88	242	4	localObject	Object
    //   342	3	4	localInvocationTargetException1	java.lang.reflect.InvocationTargetException
    //   350	3	4	localInvocationTargetException2	java.lang.reflect.InvocationTargetException
    //   358	3	4	localInvocationTargetException3	java.lang.reflect.InvocationTargetException
    //   366	3	4	localInvocationTargetException4	java.lang.reflect.InvocationTargetException
    //   374	3	4	localInvocationTargetException5	java.lang.reflect.InvocationTargetException
    // Exception table:
    //   from	to	target	type
    //   90	102	342	java/lang/reflect/InvocationTargetException
    //   242	254	350	java/lang/reflect/InvocationTargetException
    //   153	165	358	java/lang/reflect/InvocationTargetException
    //   198	210	366	java/lang/reflect/InvocationTargetException
    //   317	329	374	java/lang/reflect/InvocationTargetException
  }
  
  /* Error */
  public void booo006Fo006Fo006F006F006F(bmbbmb.mbbbmb paramMbbbmb)
  {
    // Byte code:
    //   0: aload_0
    //   1: aload_1
    //   2: invokespecial 301	uuuuuu/ssssst:ba0061a0061a0061a0061aa	(Luuuuuu/ttssst$tsssst;)V
    //   5: aload_1
    //   6: invokeinterface 304 1 0
    //   11: aload_0
    //   12: getfield 132	uuuuuu/bmmmbb:bss0073ss0073s0073s	Luuuuuu/mbmmbb;
    //   15: astore_1
    //   16: getstatic 44	uuuuuu/bmmmbb:bsss0073s0073s0073s	I
    //   19: istore_2
    //   20: iload_2
    //   21: getstatic 46	uuuuuu/bmmmbb:b0073ss0073s0073s0073s	I
    //   24: iload_2
    //   25: iadd
    //   26: imul
    //   27: getstatic 48	uuuuuu/bmmmbb:bs0073s0073s0073s0073s	I
    //   30: irem
    //   31: tableswitch	default:+17->48, 0:+106->137
    //   48: ldc 2
    //   50: ldc_w 306
    //   53: bipush 14
    //   55: iconst_0
    //   56: invokestatic 104	xxxxxx/uxxxxx:bb00620062bb0062b0062b0062	(Ljava/lang/String;CC)Ljava/lang/String;
    //   59: iconst_0
    //   60: anewarray 60	java/lang/Class
    //   63: invokevirtual 64	java/lang/Class:getMethod	(Ljava/lang/String;[Ljava/lang/Class;)Ljava/lang/reflect/Method;
    //   66: astore 5
    //   68: aload 5
    //   70: aconst_null
    //   71: iconst_0
    //   72: anewarray 66	java/lang/Object
    //   75: invokevirtual 72	java/lang/reflect/Method:invoke	(Ljava/lang/Object;[Ljava/lang/Object;)Ljava/lang/Object;
    //   78: astore 5
    //   80: aload 5
    //   82: checkcast 74	java/lang/Integer
    //   85: invokevirtual 77	java/lang/Integer:intValue	()I
    //   88: putstatic 44	uuuuuu/bmmmbb:bsss0073s0073s0073s	I
    //   91: ldc 2
    //   93: ldc_w 308
    //   96: bipush 98
    //   98: sipush 135
    //   101: iconst_0
    //   102: invokestatic 58	xxxxxx/uxxxxx:bbbb0062b0062b0062b0062	(Ljava/lang/String;CCC)Ljava/lang/String;
    //   105: iconst_0
    //   106: anewarray 60	java/lang/Class
    //   109: invokevirtual 64	java/lang/Class:getMethod	(Ljava/lang/String;[Ljava/lang/Class;)Ljava/lang/reflect/Method;
    //   112: astore 5
    //   114: aload 5
    //   116: aconst_null
    //   117: iconst_0
    //   118: anewarray 66	java/lang/Object
    //   121: invokevirtual 72	java/lang/reflect/Method:invoke	(Ljava/lang/Object;[Ljava/lang/Object;)Ljava/lang/Object;
    //   124: astore 5
    //   126: aload 5
    //   128: checkcast 74	java/lang/Integer
    //   131: invokevirtual 77	java/lang/Integer:intValue	()I
    //   134: putstatic 46	uuuuuu/bmmmbb:b0073ss0073s0073s0073s	I
    //   137: aload_1
    //   138: getstatic 311	uuuuuu/mbmmbb:b0073007300730073s0073s0073s	Luuuuuu/mbmmbb;
    //   141: if_acmpne +13 -> 154
    //   144: aload_0
    //   145: getfield 122	uuuuuu/bmmmbb:b0073s0073ss0073s0073s	Luuuuuu/mmmmmb;
    //   148: aload_0
    //   149: iconst_2
    //   150: invokevirtual 315	uuuuuu/mmmmmb:b006Foo006F006Fo006Fo006F006F	(Luuuuuu/bmbbbm;I)V
    //   153: return
    //   154: aload_0
    //   155: getfield 122	uuuuuu/bmmmbb:b0073s0073ss0073s0073s	Luuuuuu/mmmmmb;
    //   158: astore_1
    //   159: getstatic 44	uuuuuu/bmmmbb:bsss0073s0073s0073s	I
    //   162: istore_2
    //   163: getstatic 46	uuuuuu/bmmmbb:b0073ss0073s0073s0073s	I
    //   166: istore_3
    //   167: ldc 2
    //   169: ldc_w 317
    //   172: bipush 107
    //   174: bipush 102
    //   176: iconst_1
    //   177: invokestatic 58	xxxxxx/uxxxxx:bbbb0062b0062b0062b0062	(Ljava/lang/String;CCC)Ljava/lang/String;
    //   180: iconst_0
    //   181: anewarray 60	java/lang/Class
    //   184: invokevirtual 64	java/lang/Class:getMethod	(Ljava/lang/String;[Ljava/lang/Class;)Ljava/lang/reflect/Method;
    //   187: astore 5
    //   189: aload 5
    //   191: aconst_null
    //   192: iconst_0
    //   193: anewarray 66	java/lang/Object
    //   196: invokevirtual 72	java/lang/reflect/Method:invoke	(Ljava/lang/Object;[Ljava/lang/Object;)Ljava/lang/Object;
    //   199: astore 5
    //   201: aload 5
    //   203: checkcast 74	java/lang/Integer
    //   206: invokevirtual 77	java/lang/Integer:intValue	()I
    //   209: istore 4
    //   211: iload 4
    //   213: getstatic 46	uuuuuu/bmmmbb:b0073ss0073s0073s0073s	I
    //   216: iload 4
    //   218: iadd
    //   219: imul
    //   220: getstatic 48	uuuuuu/bmmmbb:bs0073s0073s0073s0073s	I
    //   223: irem
    //   224: tableswitch	default:+20->244, 0:+101->325
    //   244: getstatic 44	uuuuuu/bmmmbb:bsss0073s0073s0073s	I
    //   247: getstatic 46	uuuuuu/bmmmbb:b0073ss0073s0073s0073s	I
    //   250: iadd
    //   251: getstatic 44	uuuuuu/bmmmbb:bsss0073s0073s0073s	I
    //   254: imul
    //   255: getstatic 48	uuuuuu/bmmmbb:bs0073s0073s0073s0073s	I
    //   258: irem
    //   259: getstatic 50	uuuuuu/bmmmbb:b00730073s0073s0073s0073s	I
    //   262: if_icmpeq +13 -> 275
    //   265: bipush 33
    //   267: putstatic 44	uuuuuu/bmmmbb:bsss0073s0073s0073s	I
    //   270: bipush 17
    //   272: putstatic 50	uuuuuu/bmmmbb:b00730073s0073s0073s0073s	I
    //   275: bipush 12
    //   277: putstatic 44	uuuuuu/bmmmbb:bsss0073s0073s0073s	I
    //   280: ldc 2
    //   282: ldc_w 319
    //   285: bipush 80
    //   287: bipush 120
    //   289: iconst_2
    //   290: invokestatic 58	xxxxxx/uxxxxx:bbbb0062b0062b0062b0062	(Ljava/lang/String;CCC)Ljava/lang/String;
    //   293: iconst_0
    //   294: anewarray 60	java/lang/Class
    //   297: invokevirtual 64	java/lang/Class:getMethod	(Ljava/lang/String;[Ljava/lang/Class;)Ljava/lang/reflect/Method;
    //   300: astore 5
    //   302: aload 5
    //   304: aconst_null
    //   305: iconst_0
    //   306: anewarray 66	java/lang/Object
    //   309: invokevirtual 72	java/lang/reflect/Method:invoke	(Ljava/lang/Object;[Ljava/lang/Object;)Ljava/lang/Object;
    //   312: astore 5
    //   314: aload 5
    //   316: checkcast 74	java/lang/Integer
    //   319: invokevirtual 77	java/lang/Integer:intValue	()I
    //   322: putstatic 46	uuuuuu/bmmmbb:b0073ss0073s0073s0073s	I
    //   325: iload_2
    //   326: iload_3
    //   327: iadd
    //   328: iload_2
    //   329: imul
    //   330: getstatic 48	uuuuuu/bmmmbb:bs0073s0073s0073s0073s	I
    //   333: irem
    //   334: tableswitch	default:+18->352, 0:+28->362
    //   352: bipush 81
    //   354: putstatic 44	uuuuuu/bmmmbb:bsss0073s0073s0073s	I
    //   357: bipush 16
    //   359: putstatic 46	uuuuuu/bmmmbb:b0073ss0073s0073s0073s	I
    //   362: aload_1
    //   363: aload_0
    //   364: iconst_1
    //   365: invokevirtual 315	uuuuuu/mmmmmb:b006Foo006F006Fo006Fo006F006F	(Luuuuuu/bmbbbm;I)V
    //   368: return
    //   369: astore_1
    //   370: aload_1
    //   371: invokevirtual 114	java/lang/reflect/InvocationTargetException:getCause	()Ljava/lang/Throwable;
    //   374: athrow
    //   375: astore_1
    //   376: aload_1
    //   377: invokevirtual 114	java/lang/reflect/InvocationTargetException:getCause	()Ljava/lang/Throwable;
    //   380: athrow
    //   381: astore_1
    //   382: aload_1
    //   383: invokevirtual 114	java/lang/reflect/InvocationTargetException:getCause	()Ljava/lang/Throwable;
    //   386: athrow
    //   387: astore_1
    //   388: aload_1
    //   389: invokevirtual 114	java/lang/reflect/InvocationTargetException:getCause	()Ljava/lang/Throwable;
    //   392: athrow
    // Local variable table:
    //   start	length	slot	name	signature
    //   0	393	0	this	bmmmbb
    //   0	393	1	paramMbbbmb	bmbbmb.mbbbmb
    //   19	311	2	i	int
    //   166	162	3	j	int
    //   209	11	4	k	int
    //   66	249	5	localObject	Object
    // Exception table:
    //   from	to	target	type
    //   189	201	369	java/lang/reflect/InvocationTargetException
    //   302	314	375	java/lang/reflect/InvocationTargetException
    //   68	80	381	java/lang/reflect/InvocationTargetException
    //   114	126	387	java/lang/reflect/InvocationTargetException
  }
  
  /* Error */
  public void boooo006F006Foo006F006F(int paramInt, CharSequence paramCharSequence)
  {
    // Byte code:
    //   0: aload_0
    //   1: invokevirtual 81	uuuuuu/bmmmbb:bkk006Bk006Bk006Bk006Bk	()Z
    //   4: ifne +4 -> 8
    //   7: return
    //   8: aload_0
    //   9: getfield 85	uuuuuu/bmmmbb:bnnnnn006E006E006En	Luuuuuu/ttssst$tsssst;
    //   12: checkcast 87	uuuuuu/bmbbmb$mbbbmb
    //   15: astore 5
    //   17: getstatic 44	uuuuuu/bmmmbb:bsss0073s0073s0073s	I
    //   20: istore_1
    //   21: getstatic 46	uuuuuu/bmmmbb:b0073ss0073s0073s0073s	I
    //   24: istore_3
    //   25: getstatic 44	uuuuuu/bmmmbb:bsss0073s0073s0073s	I
    //   28: istore 4
    //   30: ldc 2
    //   32: ldc_w 322
    //   35: bipush 102
    //   37: iconst_1
    //   38: invokestatic 104	xxxxxx/uxxxxx:bb00620062bb0062b0062b0062	(Ljava/lang/String;CC)Ljava/lang/String;
    //   41: iconst_0
    //   42: anewarray 60	java/lang/Class
    //   45: invokevirtual 64	java/lang/Class:getMethod	(Ljava/lang/String;[Ljava/lang/Class;)Ljava/lang/reflect/Method;
    //   48: astore 6
    //   50: aload 6
    //   52: aconst_null
    //   53: iconst_0
    //   54: anewarray 66	java/lang/Object
    //   57: invokevirtual 72	java/lang/reflect/Method:invoke	(Ljava/lang/Object;[Ljava/lang/Object;)Ljava/lang/Object;
    //   60: astore 6
    //   62: iload 4
    //   64: iload_1
    //   65: iload_3
    //   66: iadd
    //   67: imul
    //   68: aload 6
    //   70: checkcast 74	java/lang/Integer
    //   73: invokevirtual 77	java/lang/Integer:intValue	()I
    //   76: irem
    //   77: getstatic 50	uuuuuu/bmmmbb:b00730073s0073s0073s0073s	I
    //   80: if_icmpeq +85 -> 165
    //   83: bipush 85
    //   85: putstatic 44	uuuuuu/bmmmbb:bsss0073s0073s0073s	I
    //   88: bipush 99
    //   90: putstatic 50	uuuuuu/bmmmbb:b00730073s0073s0073s0073s	I
    //   93: getstatic 44	uuuuuu/bmmmbb:bsss0073s0073s0073s	I
    //   96: getstatic 46	uuuuuu/bmmmbb:b0073ss0073s0073s0073s	I
    //   99: iadd
    //   100: getstatic 44	uuuuuu/bmmmbb:bsss0073s0073s0073s	I
    //   103: imul
    //   104: getstatic 48	uuuuuu/bmmmbb:bs0073s0073s0073s0073s	I
    //   107: irem
    //   108: getstatic 50	uuuuuu/bmmmbb:b00730073s0073s0073s0073s	I
    //   111: if_icmpeq +54 -> 165
    //   114: bipush 97
    //   116: putstatic 44	uuuuuu/bmmmbb:bsss0073s0073s0073s	I
    //   119: ldc 2
    //   121: ldc_w 324
    //   124: sipush 154
    //   127: bipush 29
    //   129: iconst_1
    //   130: invokestatic 58	xxxxxx/uxxxxx:bbbb0062b0062b0062b0062	(Ljava/lang/String;CCC)Ljava/lang/String;
    //   133: iconst_0
    //   134: anewarray 60	java/lang/Class
    //   137: invokevirtual 64	java/lang/Class:getMethod	(Ljava/lang/String;[Ljava/lang/Class;)Ljava/lang/reflect/Method;
    //   140: astore 6
    //   142: aload 6
    //   144: aconst_null
    //   145: iconst_0
    //   146: anewarray 66	java/lang/Object
    //   149: invokevirtual 72	java/lang/reflect/Method:invoke	(Ljava/lang/Object;[Ljava/lang/Object;)Ljava/lang/Object;
    //   152: astore 6
    //   154: aload 6
    //   156: checkcast 74	java/lang/Integer
    //   159: invokevirtual 77	java/lang/Integer:intValue	()I
    //   162: putstatic 50	uuuuuu/bmmmbb:b00730073s0073s0073s0073s	I
    //   165: aload 5
    //   167: getstatic 327	uuuuuu/mbbbbm:b00730073ssss0073ss	Luuuuuu/mbbbbm;
    //   170: aload_2
    //   171: invokeinterface 333 1 0
    //   176: invokeinterface 336 3 0
    //   181: getstatic 44	uuuuuu/bmmmbb:bsss0073s0073s0073s	I
    //   184: istore_1
    //   185: ldc 2
    //   187: ldc_w 338
    //   190: sipush 231
    //   193: bipush 38
    //   195: iconst_1
    //   196: invokestatic 58	xxxxxx/uxxxxx:bbbb0062b0062b0062b0062	(Ljava/lang/String;CCC)Ljava/lang/String;
    //   199: iconst_0
    //   200: anewarray 60	java/lang/Class
    //   203: invokevirtual 64	java/lang/Class:getMethod	(Ljava/lang/String;[Ljava/lang/Class;)Ljava/lang/reflect/Method;
    //   206: astore_2
    //   207: aload_2
    //   208: aconst_null
    //   209: iconst_0
    //   210: anewarray 66	java/lang/Object
    //   213: invokevirtual 72	java/lang/reflect/Method:invoke	(Ljava/lang/Object;[Ljava/lang/Object;)Ljava/lang/Object;
    //   216: astore_2
    //   217: aload_2
    //   218: checkcast 74	java/lang/Integer
    //   221: invokevirtual 77	java/lang/Integer:intValue	()I
    //   224: iload_1
    //   225: iadd
    //   226: iload_1
    //   227: imul
    //   228: getstatic 48	uuuuuu/bmmmbb:bs0073s0073s0073s0073s	I
    //   231: irem
    //   232: tableswitch	default:+20->252, 0:+-225->7
    //   252: bipush 55
    //   254: putstatic 44	uuuuuu/bmmmbb:bsss0073s0073s0073s	I
    //   257: getstatic 44	uuuuuu/bmmmbb:bsss0073s0073s0073s	I
    //   260: getstatic 46	uuuuuu/bmmmbb:b0073ss0073s0073s0073s	I
    //   263: iadd
    //   264: getstatic 44	uuuuuu/bmmmbb:bsss0073s0073s0073s	I
    //   267: imul
    //   268: getstatic 48	uuuuuu/bmmmbb:bs0073s0073s0073s0073s	I
    //   271: irem
    //   272: getstatic 50	uuuuuu/bmmmbb:b00730073s0073s0073s0073s	I
    //   275: if_icmpeq +13 -> 288
    //   278: bipush 43
    //   280: putstatic 44	uuuuuu/bmmmbb:bsss0073s0073s0073s	I
    //   283: bipush 93
    //   285: putstatic 50	uuuuuu/bmmmbb:b00730073s0073s0073s0073s	I
    //   288: ldc 2
    //   290: ldc_w 340
    //   293: sipush 180
    //   296: sipush 173
    //   299: iconst_0
    //   300: invokestatic 58	xxxxxx/uxxxxx:bbbb0062b0062b0062b0062	(Ljava/lang/String;CCC)Ljava/lang/String;
    //   303: iconst_0
    //   304: anewarray 60	java/lang/Class
    //   307: invokevirtual 64	java/lang/Class:getMethod	(Ljava/lang/String;[Ljava/lang/Class;)Ljava/lang/reflect/Method;
    //   310: astore_2
    //   311: aload_2
    //   312: aconst_null
    //   313: iconst_0
    //   314: anewarray 66	java/lang/Object
    //   317: invokevirtual 72	java/lang/reflect/Method:invoke	(Ljava/lang/Object;[Ljava/lang/Object;)Ljava/lang/Object;
    //   320: astore_2
    //   321: aload_2
    //   322: checkcast 74	java/lang/Integer
    //   325: invokevirtual 77	java/lang/Integer:intValue	()I
    //   328: putstatic 50	uuuuuu/bmmmbb:b00730073s0073s0073s0073s	I
    //   331: return
    //   332: astore_2
    //   333: aload_2
    //   334: invokevirtual 114	java/lang/reflect/InvocationTargetException:getCause	()Ljava/lang/Throwable;
    //   337: athrow
    //   338: astore_2
    //   339: aload_2
    //   340: invokevirtual 114	java/lang/reflect/InvocationTargetException:getCause	()Ljava/lang/Throwable;
    //   343: athrow
    //   344: astore_2
    //   345: aload_2
    //   346: invokevirtual 114	java/lang/reflect/InvocationTargetException:getCause	()Ljava/lang/Throwable;
    //   349: athrow
    //   350: astore_2
    //   351: aload_2
    //   352: invokevirtual 114	java/lang/reflect/InvocationTargetException:getCause	()Ljava/lang/Throwable;
    //   355: athrow
    // Local variable table:
    //   start	length	slot	name	signature
    //   0	356	0	this	bmmmbb
    //   0	356	1	paramInt	int
    //   0	356	2	paramCharSequence	CharSequence
    //   24	43	3	i	int
    //   28	40	4	j	int
    //   15	151	5	localMbbbmb	bmbbmb.mbbbmb
    //   48	107	6	localObject	Object
    // Exception table:
    //   from	to	target	type
    //   207	217	332	java/lang/reflect/InvocationTargetException
    //   311	321	338	java/lang/reflect/InvocationTargetException
    //   50	62	344	java/lang/reflect/InvocationTargetException
    //   142	154	350	java/lang/reflect/InvocationTargetException
  }
}
