package uuuuuu;

public class dvvdvv
  extends ssssst<vvddvv.vdvdvv>
  implements vvddvv.ddvdvv
{
  public static int b00680068hh006800680068hh = 60;
  public static int b0068hhh006800680068hh = 1;
  public static int bh0068hh006800680068hh = 2;
  public static int bhhhh006800680068hh;
  public String b0068006800680068h00680068hh;
  
  public dvvdvv() {}
  
  public static int b00710071q0071qqqqq0071()
  {
    return 60;
  }
  
  public static int b0071q00710071qqqqq0071()
  {
    return 0;
  }
  
  public static int bqq00710071qqqqq0071()
  {
    return 1;
  }
  
  /* Error */
  public void bq0071q0071qqqqq0071(android.os.Bundle paramBundle)
  {
    // Byte code:
    //   0: aload_1
    //   1: ifnull +960 -> 961
    //   4: ldc 32
    //   6: ldc 34
    //   8: bipush 73
    //   10: iconst_5
    //   11: invokestatic 40	xxxxxx/uxxxxx:bb00620062bb0062b0062b0062	(Ljava/lang/String;CC)Ljava/lang/String;
    //   14: iconst_4
    //   15: anewarray 42	java/lang/Class
    //   18: dup
    //   19: iconst_0
    //   20: ldc 44
    //   22: aastore
    //   23: dup
    //   24: iconst_1
    //   25: getstatic 50	java/lang/Character:TYPE	Ljava/lang/Class;
    //   28: aastore
    //   29: dup
    //   30: iconst_2
    //   31: getstatic 50	java/lang/Character:TYPE	Ljava/lang/Class;
    //   34: aastore
    //   35: dup
    //   36: iconst_3
    //   37: getstatic 50	java/lang/Character:TYPE	Ljava/lang/Class;
    //   40: aastore
    //   41: invokevirtual 54	java/lang/Class:getMethod	(Ljava/lang/String;[Ljava/lang/Class;)Ljava/lang/reflect/Method;
    //   44: astore 6
    //   46: aload 6
    //   48: aconst_null
    //   49: iconst_4
    //   50: anewarray 56	java/lang/Object
    //   53: dup
    //   54: iconst_0
    //   55: ldc 58
    //   57: aastore
    //   58: dup
    //   59: iconst_1
    //   60: sipush 176
    //   63: invokestatic 62	java/lang/Character:valueOf	(C)Ljava/lang/Character;
    //   66: aastore
    //   67: dup
    //   68: iconst_2
    //   69: bipush 124
    //   71: invokestatic 62	java/lang/Character:valueOf	(C)Ljava/lang/Character;
    //   74: aastore
    //   75: dup
    //   76: iconst_3
    //   77: iconst_2
    //   78: invokestatic 62	java/lang/Character:valueOf	(C)Ljava/lang/Character;
    //   81: aastore
    //   82: invokevirtual 68	java/lang/reflect/Method:invoke	(Ljava/lang/Object;[Ljava/lang/Object;)Ljava/lang/Object;
    //   85: astore 6
    //   87: aload_1
    //   88: aload 6
    //   90: checkcast 44	java/lang/String
    //   93: invokevirtual 74	android/os/Bundle:getSerializable	(Ljava/lang/String;)Ljava/io/Serializable;
    //   96: checkcast 76	com/db/pwcc/dbmobile/investment/model/OrderTypes
    //   99: astore 6
    //   101: ldc 32
    //   103: ldc 78
    //   105: sipush 250
    //   108: bipush 23
    //   110: iconst_2
    //   111: invokestatic 82	xxxxxx/uxxxxx:bbbb0062b0062b0062b0062	(Ljava/lang/String;CCC)Ljava/lang/String;
    //   114: iconst_4
    //   115: anewarray 42	java/lang/Class
    //   118: dup
    //   119: iconst_0
    //   120: ldc 44
    //   122: aastore
    //   123: dup
    //   124: iconst_1
    //   125: getstatic 50	java/lang/Character:TYPE	Ljava/lang/Class;
    //   128: aastore
    //   129: dup
    //   130: iconst_2
    //   131: getstatic 50	java/lang/Character:TYPE	Ljava/lang/Class;
    //   134: aastore
    //   135: dup
    //   136: iconst_3
    //   137: getstatic 50	java/lang/Character:TYPE	Ljava/lang/Class;
    //   140: aastore
    //   141: invokevirtual 54	java/lang/Class:getMethod	(Ljava/lang/String;[Ljava/lang/Class;)Ljava/lang/reflect/Method;
    //   144: astore 7
    //   146: aload 7
    //   148: aconst_null
    //   149: iconst_4
    //   150: anewarray 56	java/lang/Object
    //   153: dup
    //   154: iconst_0
    //   155: ldc 84
    //   157: aastore
    //   158: dup
    //   159: iconst_1
    //   160: bipush 14
    //   162: invokestatic 62	java/lang/Character:valueOf	(C)Ljava/lang/Character;
    //   165: aastore
    //   166: dup
    //   167: iconst_2
    //   168: sipush 243
    //   171: invokestatic 62	java/lang/Character:valueOf	(C)Ljava/lang/Character;
    //   174: aastore
    //   175: dup
    //   176: iconst_3
    //   177: iconst_1
    //   178: invokestatic 62	java/lang/Character:valueOf	(C)Ljava/lang/Character;
    //   181: aastore
    //   182: invokevirtual 68	java/lang/reflect/Method:invoke	(Ljava/lang/Object;[Ljava/lang/Object;)Ljava/lang/Object;
    //   185: astore 7
    //   187: aload_1
    //   188: aload 7
    //   190: checkcast 44	java/lang/String
    //   193: ldc 86
    //   195: invokevirtual 90	android/os/Bundle:getString	(Ljava/lang/String;Ljava/lang/String;)Ljava/lang/String;
    //   198: astore 7
    //   200: getstatic 92	uuuuuu/dvvdvv:b00680068hh006800680068hh	I
    //   203: istore_2
    //   204: getstatic 94	uuuuuu/dvvdvv:b0068hhh006800680068hh	I
    //   207: istore_3
    //   208: getstatic 92	uuuuuu/dvvdvv:b00680068hh006800680068hh	I
    //   211: istore 4
    //   213: getstatic 96	uuuuuu/dvvdvv:bh0068hh006800680068hh	I
    //   216: istore 5
    //   218: ldc 2
    //   220: ldc 98
    //   222: bipush 19
    //   224: iconst_3
    //   225: invokestatic 40	xxxxxx/uxxxxx:bb00620062bb0062b0062b0062	(Ljava/lang/String;CC)Ljava/lang/String;
    //   228: iconst_0
    //   229: anewarray 42	java/lang/Class
    //   232: invokevirtual 54	java/lang/Class:getMethod	(Ljava/lang/String;[Ljava/lang/Class;)Ljava/lang/reflect/Method;
    //   235: astore 8
    //   237: aload 8
    //   239: aconst_null
    //   240: iconst_0
    //   241: anewarray 56	java/lang/Object
    //   244: invokevirtual 68	java/lang/reflect/Method:invoke	(Ljava/lang/Object;[Ljava/lang/Object;)Ljava/lang/Object;
    //   247: astore 8
    //   249: iload_2
    //   250: iload_3
    //   251: iadd
    //   252: iload 4
    //   254: imul
    //   255: iload 5
    //   257: irem
    //   258: aload 8
    //   260: checkcast 100	java/lang/Integer
    //   263: invokevirtual 103	java/lang/Integer:intValue	()I
    //   266: if_icmpeq +50 -> 316
    //   269: ldc 2
    //   271: ldc 105
    //   273: bipush 46
    //   275: iconst_0
    //   276: invokestatic 40	xxxxxx/uxxxxx:bb00620062bb0062b0062b0062	(Ljava/lang/String;CC)Ljava/lang/String;
    //   279: iconst_0
    //   280: anewarray 42	java/lang/Class
    //   283: invokevirtual 54	java/lang/Class:getMethod	(Ljava/lang/String;[Ljava/lang/Class;)Ljava/lang/reflect/Method;
    //   286: astore 8
    //   288: aload 8
    //   290: aconst_null
    //   291: iconst_0
    //   292: anewarray 56	java/lang/Object
    //   295: invokevirtual 68	java/lang/reflect/Method:invoke	(Ljava/lang/Object;[Ljava/lang/Object;)Ljava/lang/Object;
    //   298: astore 8
    //   300: aload 8
    //   302: checkcast 100	java/lang/Integer
    //   305: invokevirtual 103	java/lang/Integer:intValue	()I
    //   308: putstatic 92	uuuuuu/dvvdvv:b00680068hh006800680068hh	I
    //   311: bipush 58
    //   313: putstatic 107	uuuuuu/dvvdvv:bhhhh006800680068hh	I
    //   316: ldc 32
    //   318: ldc 109
    //   320: sipush 200
    //   323: bipush 116
    //   325: iconst_3
    //   326: invokestatic 82	xxxxxx/uxxxxx:bbbb0062b0062b0062b0062	(Ljava/lang/String;CCC)Ljava/lang/String;
    //   329: iconst_3
    //   330: anewarray 42	java/lang/Class
    //   333: dup
    //   334: iconst_0
    //   335: ldc 44
    //   337: aastore
    //   338: dup
    //   339: iconst_1
    //   340: getstatic 50	java/lang/Character:TYPE	Ljava/lang/Class;
    //   343: aastore
    //   344: dup
    //   345: iconst_2
    //   346: getstatic 50	java/lang/Character:TYPE	Ljava/lang/Class;
    //   349: aastore
    //   350: invokevirtual 54	java/lang/Class:getMethod	(Ljava/lang/String;[Ljava/lang/Class;)Ljava/lang/reflect/Method;
    //   353: astore 8
    //   355: aload 8
    //   357: aconst_null
    //   358: iconst_3
    //   359: anewarray 56	java/lang/Object
    //   362: dup
    //   363: iconst_0
    //   364: ldc 111
    //   366: aastore
    //   367: dup
    //   368: iconst_1
    //   369: bipush 104
    //   371: invokestatic 62	java/lang/Character:valueOf	(C)Ljava/lang/Character;
    //   374: aastore
    //   375: dup
    //   376: iconst_2
    //   377: iconst_0
    //   378: invokestatic 62	java/lang/Character:valueOf	(C)Ljava/lang/Character;
    //   381: aastore
    //   382: invokevirtual 68	java/lang/reflect/Method:invoke	(Ljava/lang/Object;[Ljava/lang/Object;)Ljava/lang/Object;
    //   385: astore 8
    //   387: aload_1
    //   388: aload 8
    //   390: checkcast 44	java/lang/String
    //   393: ldc 86
    //   395: invokevirtual 90	android/os/Bundle:getString	(Ljava/lang/String;Ljava/lang/String;)Ljava/lang/String;
    //   398: astore 8
    //   400: getstatic 92	uuuuuu/dvvdvv:b00680068hh006800680068hh	I
    //   403: istore_2
    //   404: iload_2
    //   405: getstatic 94	uuuuuu/dvvdvv:b0068hhh006800680068hh	I
    //   408: iload_2
    //   409: iadd
    //   410: imul
    //   411: getstatic 96	uuuuuu/dvvdvv:bh0068hh006800680068hh	I
    //   414: irem
    //   415: tableswitch	default:+17->432, 0:+66->481
    //   432: bipush 42
    //   434: putstatic 92	uuuuuu/dvvdvv:b00680068hh006800680068hh	I
    //   437: ldc 2
    //   439: ldc 113
    //   441: bipush 27
    //   443: bipush 120
    //   445: iconst_0
    //   446: invokestatic 82	xxxxxx/uxxxxx:bbbb0062b0062b0062b0062	(Ljava/lang/String;CCC)Ljava/lang/String;
    //   449: iconst_0
    //   450: anewarray 42	java/lang/Class
    //   453: invokevirtual 54	java/lang/Class:getMethod	(Ljava/lang/String;[Ljava/lang/Class;)Ljava/lang/reflect/Method;
    //   456: astore 9
    //   458: aload 9
    //   460: aconst_null
    //   461: iconst_0
    //   462: anewarray 56	java/lang/Object
    //   465: invokevirtual 68	java/lang/reflect/Method:invoke	(Ljava/lang/Object;[Ljava/lang/Object;)Ljava/lang/Object;
    //   468: astore 9
    //   470: aload 9
    //   472: checkcast 100	java/lang/Integer
    //   475: invokevirtual 103	java/lang/Integer:intValue	()I
    //   478: putstatic 107	uuuuuu/dvvdvv:bhhhh006800680068hh	I
    //   481: getstatic 92	uuuuuu/dvvdvv:b00680068hh006800680068hh	I
    //   484: istore_2
    //   485: ldc 2
    //   487: ldc 115
    //   489: bipush 19
    //   491: sipush 144
    //   494: iconst_0
    //   495: invokestatic 82	xxxxxx/uxxxxx:bbbb0062b0062b0062b0062	(Ljava/lang/String;CCC)Ljava/lang/String;
    //   498: iconst_0
    //   499: anewarray 42	java/lang/Class
    //   502: invokevirtual 54	java/lang/Class:getMethod	(Ljava/lang/String;[Ljava/lang/Class;)Ljava/lang/reflect/Method;
    //   505: astore 9
    //   507: aload 9
    //   509: aconst_null
    //   510: iconst_0
    //   511: anewarray 56	java/lang/Object
    //   514: invokevirtual 68	java/lang/reflect/Method:invoke	(Ljava/lang/Object;[Ljava/lang/Object;)Ljava/lang/Object;
    //   517: astore 9
    //   519: aload 9
    //   521: checkcast 100	java/lang/Integer
    //   524: invokevirtual 103	java/lang/Integer:intValue	()I
    //   527: iload_2
    //   528: iadd
    //   529: iload_2
    //   530: imul
    //   531: getstatic 96	uuuuuu/dvvdvv:bh0068hh006800680068hh	I
    //   534: irem
    //   535: tableswitch	default:+17->552, 0:+103->638
    //   552: ldc 2
    //   554: ldc 117
    //   556: bipush 17
    //   558: bipush 41
    //   560: iconst_1
    //   561: invokestatic 82	xxxxxx/uxxxxx:bbbb0062b0062b0062b0062	(Ljava/lang/String;CCC)Ljava/lang/String;
    //   564: iconst_0
    //   565: anewarray 42	java/lang/Class
    //   568: invokevirtual 54	java/lang/Class:getMethod	(Ljava/lang/String;[Ljava/lang/Class;)Ljava/lang/reflect/Method;
    //   571: astore 9
    //   573: aload 9
    //   575: aconst_null
    //   576: iconst_0
    //   577: anewarray 56	java/lang/Object
    //   580: invokevirtual 68	java/lang/reflect/Method:invoke	(Ljava/lang/Object;[Ljava/lang/Object;)Ljava/lang/Object;
    //   583: astore 9
    //   585: aload 9
    //   587: checkcast 100	java/lang/Integer
    //   590: invokevirtual 103	java/lang/Integer:intValue	()I
    //   593: putstatic 92	uuuuuu/dvvdvv:b00680068hh006800680068hh	I
    //   596: ldc 2
    //   598: ldc 119
    //   600: bipush 102
    //   602: iconst_0
    //   603: invokestatic 40	xxxxxx/uxxxxx:bb00620062bb0062b0062b0062	(Ljava/lang/String;CC)Ljava/lang/String;
    //   606: iconst_0
    //   607: anewarray 42	java/lang/Class
    //   610: invokevirtual 54	java/lang/Class:getMethod	(Ljava/lang/String;[Ljava/lang/Class;)Ljava/lang/reflect/Method;
    //   613: astore 9
    //   615: aload 9
    //   617: aconst_null
    //   618: iconst_0
    //   619: anewarray 56	java/lang/Object
    //   622: invokevirtual 68	java/lang/reflect/Method:invoke	(Ljava/lang/Object;[Ljava/lang/Object;)Ljava/lang/Object;
    //   625: astore 9
    //   627: aload 9
    //   629: checkcast 100	java/lang/Integer
    //   632: invokevirtual 103	java/lang/Integer:intValue	()I
    //   635: putstatic 107	uuuuuu/dvvdvv:bhhhh006800680068hh	I
    //   638: ldc 32
    //   640: ldc 121
    //   642: bipush 56
    //   644: iconst_4
    //   645: invokestatic 40	xxxxxx/uxxxxx:bb00620062bb0062b0062b0062	(Ljava/lang/String;CC)Ljava/lang/String;
    //   648: iconst_4
    //   649: anewarray 42	java/lang/Class
    //   652: dup
    //   653: iconst_0
    //   654: ldc 44
    //   656: aastore
    //   657: dup
    //   658: iconst_1
    //   659: getstatic 50	java/lang/Character:TYPE	Ljava/lang/Class;
    //   662: aastore
    //   663: dup
    //   664: iconst_2
    //   665: getstatic 50	java/lang/Character:TYPE	Ljava/lang/Class;
    //   668: aastore
    //   669: dup
    //   670: iconst_3
    //   671: getstatic 50	java/lang/Character:TYPE	Ljava/lang/Class;
    //   674: aastore
    //   675: invokevirtual 54	java/lang/Class:getMethod	(Ljava/lang/String;[Ljava/lang/Class;)Ljava/lang/reflect/Method;
    //   678: astore 9
    //   680: aload 9
    //   682: aconst_null
    //   683: iconst_4
    //   684: anewarray 56	java/lang/Object
    //   687: dup
    //   688: iconst_0
    //   689: ldc 123
    //   691: aastore
    //   692: dup
    //   693: iconst_1
    //   694: bipush 75
    //   696: invokestatic 62	java/lang/Character:valueOf	(C)Ljava/lang/Character;
    //   699: aastore
    //   700: dup
    //   701: iconst_2
    //   702: bipush 113
    //   704: invokestatic 62	java/lang/Character:valueOf	(C)Ljava/lang/Character;
    //   707: aastore
    //   708: dup
    //   709: iconst_3
    //   710: iconst_2
    //   711: invokestatic 62	java/lang/Character:valueOf	(C)Ljava/lang/Character;
    //   714: aastore
    //   715: invokevirtual 68	java/lang/reflect/Method:invoke	(Ljava/lang/Object;[Ljava/lang/Object;)Ljava/lang/Object;
    //   718: astore 9
    //   720: aload_0
    //   721: aload_1
    //   722: aload 9
    //   724: checkcast 44	java/lang/String
    //   727: invokevirtual 126	android/os/Bundle:getString	(Ljava/lang/String;)Ljava/lang/String;
    //   730: putfield 128	uuuuuu/dvvdvv:b0068006800680068h00680068hh	Ljava/lang/String;
    //   733: ldc 2
    //   735: ldc -126
    //   737: sipush 174
    //   740: iconst_1
    //   741: invokestatic 40	xxxxxx/uxxxxx:bb00620062bb0062b0062b0062	(Ljava/lang/String;CC)Ljava/lang/String;
    //   744: iconst_0
    //   745: anewarray 42	java/lang/Class
    //   748: invokevirtual 54	java/lang/Class:getMethod	(Ljava/lang/String;[Ljava/lang/Class;)Ljava/lang/reflect/Method;
    //   751: astore 9
    //   753: aload 9
    //   755: aconst_null
    //   756: iconst_0
    //   757: anewarray 56	java/lang/Object
    //   760: invokevirtual 68	java/lang/reflect/Method:invoke	(Ljava/lang/Object;[Ljava/lang/Object;)Ljava/lang/Object;
    //   763: astore 9
    //   765: aload 9
    //   767: checkcast 100	java/lang/Integer
    //   770: invokevirtual 103	java/lang/Integer:intValue	()I
    //   773: istore_2
    //   774: getstatic 94	uuuuuu/dvvdvv:b0068hhh006800680068hh	I
    //   777: istore_3
    //   778: ldc 2
    //   780: ldc -124
    //   782: bipush 116
    //   784: iconst_2
    //   785: invokestatic 40	xxxxxx/uxxxxx:bb00620062bb0062b0062b0062	(Ljava/lang/String;CC)Ljava/lang/String;
    //   788: iconst_0
    //   789: anewarray 42	java/lang/Class
    //   792: invokevirtual 54	java/lang/Class:getMethod	(Ljava/lang/String;[Ljava/lang/Class;)Ljava/lang/reflect/Method;
    //   795: astore 9
    //   797: aload 9
    //   799: aconst_null
    //   800: iconst_0
    //   801: anewarray 56	java/lang/Object
    //   804: invokevirtual 68	java/lang/reflect/Method:invoke	(Ljava/lang/Object;[Ljava/lang/Object;)Ljava/lang/Object;
    //   807: astore 9
    //   809: aload 9
    //   811: checkcast 100	java/lang/Integer
    //   814: invokevirtual 103	java/lang/Integer:intValue	()I
    //   817: iload_3
    //   818: iload_2
    //   819: iadd
    //   820: imul
    //   821: getstatic 96	uuuuuu/dvvdvv:bh0068hh006800680068hh	I
    //   824: irem
    //   825: getstatic 107	uuuuuu/dvvdvv:bhhhh006800680068hh	I
    //   828: if_icmpeq +8 -> 836
    //   831: bipush 49
    //   833: putstatic 107	uuuuuu/dvvdvv:bhhhh006800680068hh	I
    //   836: ldc 32
    //   838: ldc -122
    //   840: bipush 38
    //   842: iconst_0
    //   843: invokestatic 40	xxxxxx/uxxxxx:bb00620062bb0062b0062b0062	(Ljava/lang/String;CC)Ljava/lang/String;
    //   846: iconst_4
    //   847: anewarray 42	java/lang/Class
    //   850: dup
    //   851: iconst_0
    //   852: ldc 44
    //   854: aastore
    //   855: dup
    //   856: iconst_1
    //   857: getstatic 50	java/lang/Character:TYPE	Ljava/lang/Class;
    //   860: aastore
    //   861: dup
    //   862: iconst_2
    //   863: getstatic 50	java/lang/Character:TYPE	Ljava/lang/Class;
    //   866: aastore
    //   867: dup
    //   868: iconst_3
    //   869: getstatic 50	java/lang/Character:TYPE	Ljava/lang/Class;
    //   872: aastore
    //   873: invokevirtual 54	java/lang/Class:getMethod	(Ljava/lang/String;[Ljava/lang/Class;)Ljava/lang/reflect/Method;
    //   876: astore 9
    //   878: aload 9
    //   880: aconst_null
    //   881: iconst_4
    //   882: anewarray 56	java/lang/Object
    //   885: dup
    //   886: iconst_0
    //   887: ldc -120
    //   889: aastore
    //   890: dup
    //   891: iconst_1
    //   892: sipush 163
    //   895: invokestatic 62	java/lang/Character:valueOf	(C)Ljava/lang/Character;
    //   898: aastore
    //   899: dup
    //   900: iconst_2
    //   901: sipush 235
    //   904: invokestatic 62	java/lang/Character:valueOf	(C)Ljava/lang/Character;
    //   907: aastore
    //   908: dup
    //   909: iconst_3
    //   910: iconst_2
    //   911: invokestatic 62	java/lang/Character:valueOf	(C)Ljava/lang/Character;
    //   914: aastore
    //   915: invokevirtual 68	java/lang/reflect/Method:invoke	(Ljava/lang/Object;[Ljava/lang/Object;)Ljava/lang/Object;
    //   918: astore 9
    //   920: aload_1
    //   921: aload 9
    //   923: checkcast 44	java/lang/String
    //   926: invokevirtual 126	android/os/Bundle:getString	(Ljava/lang/String;)Ljava/lang/String;
    //   929: astore_1
    //   930: aload_0
    //   931: getfield 140	uuuuuu/dvvdvv:bnnnnn006E006E006En	Luuuuuu/ttssst$tsssst;
    //   934: checkcast 142	uuuuuu/vvddvv$vdvdvv
    //   937: aload_1
    //   938: invokeinterface 146 2 0
    //   943: aload_0
    //   944: getfield 140	uuuuuu/dvvdvv:bnnnnn006E006E006En	Luuuuuu/ttssst$tsssst;
    //   947: checkcast 142	uuuuuu/vvddvv$vdvdvv
    //   950: aload 6
    //   952: aload 7
    //   954: aload 8
    //   956: invokeinterface 150 4 0
    //   961: return
    //   962: astore_1
    //   963: aload_1
    //   964: invokevirtual 154	java/lang/reflect/InvocationTargetException:getCause	()Ljava/lang/Throwable;
    //   967: athrow
    //   968: astore_1
    //   969: aload_1
    //   970: invokevirtual 154	java/lang/reflect/InvocationTargetException:getCause	()Ljava/lang/Throwable;
    //   973: athrow
    //   974: astore_1
    //   975: aload_1
    //   976: invokevirtual 154	java/lang/reflect/InvocationTargetException:getCause	()Ljava/lang/Throwable;
    //   979: athrow
    //   980: astore_1
    //   981: aload_1
    //   982: invokevirtual 154	java/lang/reflect/InvocationTargetException:getCause	()Ljava/lang/Throwable;
    //   985: athrow
    //   986: astore_1
    //   987: aload_1
    //   988: invokevirtual 154	java/lang/reflect/InvocationTargetException:getCause	()Ljava/lang/Throwable;
    //   991: athrow
    //   992: astore_1
    //   993: aload_1
    //   994: invokevirtual 154	java/lang/reflect/InvocationTargetException:getCause	()Ljava/lang/Throwable;
    //   997: athrow
    //   998: astore_1
    //   999: aload_1
    //   1000: invokevirtual 154	java/lang/reflect/InvocationTargetException:getCause	()Ljava/lang/Throwable;
    //   1003: athrow
    //   1004: astore_1
    //   1005: aload_1
    //   1006: invokevirtual 154	java/lang/reflect/InvocationTargetException:getCause	()Ljava/lang/Throwable;
    //   1009: athrow
    //   1010: astore_1
    //   1011: aload_1
    //   1012: invokevirtual 154	java/lang/reflect/InvocationTargetException:getCause	()Ljava/lang/Throwable;
    //   1015: athrow
    //   1016: astore_1
    //   1017: aload_1
    //   1018: invokevirtual 154	java/lang/reflect/InvocationTargetException:getCause	()Ljava/lang/Throwable;
    //   1021: athrow
    //   1022: astore_1
    //   1023: aload_1
    //   1024: invokevirtual 154	java/lang/reflect/InvocationTargetException:getCause	()Ljava/lang/Throwable;
    //   1027: athrow
    //   1028: astore_1
    //   1029: aload_1
    //   1030: invokevirtual 154	java/lang/reflect/InvocationTargetException:getCause	()Ljava/lang/Throwable;
    //   1033: athrow
    //   1034: astore_1
    //   1035: aload_1
    //   1036: invokevirtual 154	java/lang/reflect/InvocationTargetException:getCause	()Ljava/lang/Throwable;
    //   1039: athrow
    // Local variable table:
    //   start	length	slot	name	signature
    //   0	1040	0	this	dvvdvv
    //   0	1040	1	paramBundle	android.os.Bundle
    //   203	617	2	i	int
    //   207	613	3	j	int
    //   211	44	4	k	int
    //   216	42	5	m	int
    //   44	907	6	localObject1	Object
    //   144	809	7	localObject2	Object
    //   235	720	8	localObject3	Object
    //   456	466	9	localObject4	Object
    // Exception table:
    //   from	to	target	type
    //   355	387	962	java/lang/reflect/InvocationTargetException
    //   753	765	968	java/lang/reflect/InvocationTargetException
    //   146	187	974	java/lang/reflect/InvocationTargetException
    //   507	519	980	java/lang/reflect/InvocationTargetException
    //   680	720	986	java/lang/reflect/InvocationTargetException
    //   797	809	992	java/lang/reflect/InvocationTargetException
    //   46	87	998	java/lang/reflect/InvocationTargetException
    //   237	249	1004	java/lang/reflect/InvocationTargetException
    //   878	920	1010	java/lang/reflect/InvocationTargetException
    //   458	470	1016	java/lang/reflect/InvocationTargetException
    //   288	300	1022	java/lang/reflect/InvocationTargetException
    //   573	585	1028	java/lang/reflect/InvocationTargetException
    //   615	627	1034	java/lang/reflect/InvocationTargetException
  }
}
