package uuuuuu;

public class eehhee
  extends qppppp<heehee.hhehee>
  implements heehee.ehehee, vpppvp.pvppvp
{
  public static int b00770077ww0077ww0077w = 16;
  public static int b0077w0077w0077ww0077w = 2;
  public static int bw00770077w0077ww0077w = 0;
  public static int bww0077w0077ww0077w = 1;
  
  public eehhee() {}
  
  public static int b006F006F006F006F006F006Fo006F006Fo()
  {
    return 1;
  }
  
  public static int b006Fo006F006F006F006Fo006F006Fo()
  {
    return 2;
  }
  
  public static int bo006F006F006F006F006Fo006F006Fo()
  {
    return 13;
  }
  
  public static int boooooo006F006F006Fo()
  {
    return 0;
  }
  
  /* Error */
  public java.util.List<String> b006Fooooo006F006F006Fo(java.util.List<String> paramList)
  {
    // Byte code:
    //   0: getstatic 34	uuuuuu/eehhee:b00770077ww0077ww0077w	I
    //   3: istore_2
    //   4: iload_2
    //   5: getstatic 36	uuuuuu/eehhee:bww0077w0077ww0077w	I
    //   8: iload_2
    //   9: iadd
    //   10: imul
    //   11: getstatic 38	uuuuuu/eehhee:b0077w0077w0077ww0077w	I
    //   14: irem
    //   15: tableswitch	default:+17->32, 0:+104->119
    //   32: ldc 2
    //   34: ldc 40
    //   36: bipush 7
    //   38: iconst_3
    //   39: invokestatic 46	xxxxxx/uxxxxx:bb00620062bb0062b0062b0062	(Ljava/lang/String;CC)Ljava/lang/String;
    //   42: iconst_0
    //   43: anewarray 48	java/lang/Class
    //   46: invokevirtual 52	java/lang/Class:getMethod	(Ljava/lang/String;[Ljava/lang/Class;)Ljava/lang/reflect/Method;
    //   49: astore 7
    //   51: aload 7
    //   53: aconst_null
    //   54: iconst_0
    //   55: anewarray 54	java/lang/Object
    //   58: invokevirtual 60	java/lang/reflect/Method:invoke	(Ljava/lang/Object;[Ljava/lang/Object;)Ljava/lang/Object;
    //   61: astore 7
    //   63: aload 7
    //   65: checkcast 62	java/lang/Integer
    //   68: invokevirtual 65	java/lang/Integer:intValue	()I
    //   71: putstatic 34	uuuuuu/eehhee:b00770077ww0077ww0077w	I
    //   74: ldc 2
    //   76: ldc 67
    //   78: bipush 32
    //   80: sipush 244
    //   83: iconst_1
    //   84: invokestatic 71	xxxxxx/uxxxxx:bbbb0062b0062b0062b0062	(Ljava/lang/String;CCC)Ljava/lang/String;
    //   87: iconst_0
    //   88: anewarray 48	java/lang/Class
    //   91: invokevirtual 52	java/lang/Class:getMethod	(Ljava/lang/String;[Ljava/lang/Class;)Ljava/lang/reflect/Method;
    //   94: astore 7
    //   96: aload 7
    //   98: aconst_null
    //   99: iconst_0
    //   100: anewarray 54	java/lang/Object
    //   103: invokevirtual 60	java/lang/reflect/Method:invoke	(Ljava/lang/Object;[Ljava/lang/Object;)Ljava/lang/Object;
    //   106: astore 7
    //   108: aload 7
    //   110: checkcast 62	java/lang/Integer
    //   113: invokevirtual 65	java/lang/Integer:intValue	()I
    //   116: putstatic 36	uuuuuu/eehhee:bww0077w0077ww0077w	I
    //   119: new 73	uuuuuu/xsxxxx
    //   122: dup
    //   123: invokespecial 74	uuuuuu/xsxxxx:<init>	()V
    //   126: aload_1
    //   127: getstatic 80	uuuuuu/onooon$nnooon:bn006En006E006E006E006E006E006E	Luuuuuu/onooon$nnooon;
    //   130: invokevirtual 84	uuuuuu/xsxxxx:bqqq0071qqqqqq	(Ljava/util/List;Luuuuuu/onooon$nnooon;)Ljava/util/List;
    //   133: astore_1
    //   134: getstatic 34	uuuuuu/eehhee:b00770077ww0077ww0077w	I
    //   137: istore_2
    //   138: getstatic 34	uuuuuu/eehhee:b00770077ww0077ww0077w	I
    //   141: istore_3
    //   142: ldc 2
    //   144: ldc 86
    //   146: bipush 48
    //   148: iconst_3
    //   149: invokestatic 46	xxxxxx/uxxxxx:bb00620062bb0062b0062b0062	(Ljava/lang/String;CC)Ljava/lang/String;
    //   152: iconst_0
    //   153: anewarray 48	java/lang/Class
    //   156: invokevirtual 52	java/lang/Class:getMethod	(Ljava/lang/String;[Ljava/lang/Class;)Ljava/lang/reflect/Method;
    //   159: astore 7
    //   161: aload 7
    //   163: aconst_null
    //   164: iconst_0
    //   165: anewarray 54	java/lang/Object
    //   168: invokevirtual 60	java/lang/reflect/Method:invoke	(Ljava/lang/Object;[Ljava/lang/Object;)Ljava/lang/Object;
    //   171: astore 7
    //   173: aload 7
    //   175: checkcast 62	java/lang/Integer
    //   178: invokevirtual 65	java/lang/Integer:intValue	()I
    //   181: istore 4
    //   183: getstatic 34	uuuuuu/eehhee:b00770077ww0077ww0077w	I
    //   186: istore 5
    //   188: getstatic 38	uuuuuu/eehhee:b0077w0077w0077ww0077w	I
    //   191: istore 6
    //   193: ldc 2
    //   195: ldc 88
    //   197: sipush 178
    //   200: iconst_0
    //   201: invokestatic 46	xxxxxx/uxxxxx:bb00620062bb0062b0062b0062	(Ljava/lang/String;CC)Ljava/lang/String;
    //   204: iconst_0
    //   205: anewarray 48	java/lang/Class
    //   208: invokevirtual 52	java/lang/Class:getMethod	(Ljava/lang/String;[Ljava/lang/Class;)Ljava/lang/reflect/Method;
    //   211: astore 7
    //   213: aload 7
    //   215: aconst_null
    //   216: iconst_0
    //   217: anewarray 54	java/lang/Object
    //   220: invokevirtual 60	java/lang/reflect/Method:invoke	(Ljava/lang/Object;[Ljava/lang/Object;)Ljava/lang/Object;
    //   223: astore 7
    //   225: iload 4
    //   227: iload_3
    //   228: iadd
    //   229: iload 5
    //   231: imul
    //   232: iload 6
    //   234: irem
    //   235: aload 7
    //   237: checkcast 62	java/lang/Integer
    //   240: invokevirtual 65	java/lang/Integer:intValue	()I
    //   243: if_icmpeq +50 -> 293
    //   246: ldc 2
    //   248: ldc 90
    //   250: bipush 58
    //   252: iconst_1
    //   253: invokestatic 46	xxxxxx/uxxxxx:bb00620062bb0062b0062b0062	(Ljava/lang/String;CC)Ljava/lang/String;
    //   256: iconst_0
    //   257: anewarray 48	java/lang/Class
    //   260: invokevirtual 52	java/lang/Class:getMethod	(Ljava/lang/String;[Ljava/lang/Class;)Ljava/lang/reflect/Method;
    //   263: astore 7
    //   265: aload 7
    //   267: aconst_null
    //   268: iconst_0
    //   269: anewarray 54	java/lang/Object
    //   272: invokevirtual 60	java/lang/reflect/Method:invoke	(Ljava/lang/Object;[Ljava/lang/Object;)Ljava/lang/Object;
    //   275: astore 7
    //   277: aload 7
    //   279: checkcast 62	java/lang/Integer
    //   282: invokevirtual 65	java/lang/Integer:intValue	()I
    //   285: putstatic 34	uuuuuu/eehhee:b00770077ww0077ww0077w	I
    //   288: bipush 83
    //   290: putstatic 36	uuuuuu/eehhee:bww0077w0077ww0077w	I
    //   293: getstatic 36	uuuuuu/eehhee:bww0077w0077ww0077w	I
    //   296: iload_2
    //   297: iadd
    //   298: iload_2
    //   299: imul
    //   300: getstatic 38	uuuuuu/eehhee:b0077w0077w0077ww0077w	I
    //   303: irem
    //   304: tableswitch	default:+20->324, 0:+113->417
    //   324: bipush 40
    //   326: putstatic 34	uuuuuu/eehhee:b00770077ww0077ww0077w	I
    //   329: bipush 40
    //   331: putstatic 36	uuuuuu/eehhee:bww0077w0077ww0077w	I
    //   334: getstatic 34	uuuuuu/eehhee:b00770077ww0077ww0077w	I
    //   337: istore_2
    //   338: iload_2
    //   339: getstatic 36	uuuuuu/eehhee:bww0077w0077ww0077w	I
    //   342: iload_2
    //   343: iadd
    //   344: imul
    //   345: getstatic 38	uuuuuu/eehhee:b0077w0077w0077ww0077w	I
    //   348: irem
    //   349: tableswitch	default:+19->368, 0:+68->417
    //   368: ldc 2
    //   370: ldc 92
    //   372: bipush 11
    //   374: bipush 88
    //   376: iconst_2
    //   377: invokestatic 71	xxxxxx/uxxxxx:bbbb0062b0062b0062b0062	(Ljava/lang/String;CCC)Ljava/lang/String;
    //   380: iconst_0
    //   381: anewarray 48	java/lang/Class
    //   384: invokevirtual 52	java/lang/Class:getMethod	(Ljava/lang/String;[Ljava/lang/Class;)Ljava/lang/reflect/Method;
    //   387: astore 7
    //   389: aload 7
    //   391: aconst_null
    //   392: iconst_0
    //   393: anewarray 54	java/lang/Object
    //   396: invokevirtual 60	java/lang/reflect/Method:invoke	(Ljava/lang/Object;[Ljava/lang/Object;)Ljava/lang/Object;
    //   399: astore 7
    //   401: aload 7
    //   403: checkcast 62	java/lang/Integer
    //   406: invokevirtual 65	java/lang/Integer:intValue	()I
    //   409: putstatic 34	uuuuuu/eehhee:b00770077ww0077ww0077w	I
    //   412: bipush 90
    //   414: putstatic 36	uuuuuu/eehhee:bww0077w0077ww0077w	I
    //   417: aload_1
    //   418: areturn
    //   419: astore_1
    //   420: aload_1
    //   421: invokevirtual 96	java/lang/reflect/InvocationTargetException:getCause	()Ljava/lang/Throwable;
    //   424: athrow
    //   425: astore_1
    //   426: aload_1
    //   427: invokevirtual 96	java/lang/reflect/InvocationTargetException:getCause	()Ljava/lang/Throwable;
    //   430: athrow
    //   431: astore_1
    //   432: aload_1
    //   433: invokevirtual 96	java/lang/reflect/InvocationTargetException:getCause	()Ljava/lang/Throwable;
    //   436: athrow
    //   437: astore_1
    //   438: aload_1
    //   439: invokevirtual 96	java/lang/reflect/InvocationTargetException:getCause	()Ljava/lang/Throwable;
    //   442: athrow
    //   443: astore_1
    //   444: aload_1
    //   445: invokevirtual 96	java/lang/reflect/InvocationTargetException:getCause	()Ljava/lang/Throwable;
    //   448: athrow
    //   449: astore_1
    //   450: aload_1
    //   451: invokevirtual 96	java/lang/reflect/InvocationTargetException:getCause	()Ljava/lang/Throwable;
    //   454: athrow
    // Local variable table:
    //   start	length	slot	name	signature
    //   0	455	0	this	eehhee
    //   0	455	1	paramList	java.util.List<String>
    //   3	342	2	i	int
    //   141	88	3	j	int
    //   181	48	4	k	int
    //   186	46	5	m	int
    //   191	44	6	n	int
    //   49	353	7	localObject	Object
    // Exception table:
    //   from	to	target	type
    //   389	401	419	java/lang/reflect/InvocationTargetException
    //   96	108	425	java/lang/reflect/InvocationTargetException
    //   51	63	431	java/lang/reflect/InvocationTargetException
    //   161	173	437	java/lang/reflect/InvocationTargetException
    //   213	225	443	java/lang/reflect/InvocationTargetException
    //   265	277	449	java/lang/reflect/InvocationTargetException
  }
  
  /* Error */
  public void b007000700070p0070pp00700070p(com.db.pwcc.dbmobile.model.card.CreditCardTransactionsData paramCreditCardTransactionsData)
  {
    // Byte code:
    //   0: getstatic 106	java/math/BigDecimal:ZERO	Ljava/math/BigDecimal;
    //   3: astore 6
    //   5: aload_1
    //   6: invokevirtual 112	com/db/pwcc/dbmobile/model/card/CreditCardTransactionsData:getAccount	()Lcom/db/pwcc/dbmobile/model/banking/Account;
    //   9: astore 7
    //   11: aload 6
    //   13: astore 5
    //   15: aload 7
    //   17: ifnull +104 -> 121
    //   20: ldc 2
    //   22: ldc 114
    //   24: sipush 229
    //   27: sipush 167
    //   30: iconst_1
    //   31: invokestatic 71	xxxxxx/uxxxxx:bbbb0062b0062b0062b0062	(Ljava/lang/String;CCC)Ljava/lang/String;
    //   34: iconst_0
    //   35: anewarray 48	java/lang/Class
    //   38: invokevirtual 52	java/lang/Class:getMethod	(Ljava/lang/String;[Ljava/lang/Class;)Ljava/lang/reflect/Method;
    //   41: astore 5
    //   43: aload 5
    //   45: aconst_null
    //   46: iconst_0
    //   47: anewarray 54	java/lang/Object
    //   50: invokevirtual 60	java/lang/reflect/Method:invoke	(Ljava/lang/Object;[Ljava/lang/Object;)Ljava/lang/Object;
    //   53: astore 5
    //   55: aload 5
    //   57: checkcast 62	java/lang/Integer
    //   60: invokevirtual 65	java/lang/Integer:intValue	()I
    //   63: istore_2
    //   64: iload_2
    //   65: getstatic 36	uuuuuu/eehhee:bww0077w0077ww0077w	I
    //   68: iload_2
    //   69: iadd
    //   70: imul
    //   71: getstatic 38	uuuuuu/eehhee:b0077w0077w0077ww0077w	I
    //   74: irem
    //   75: tableswitch	default:+17->92, 0:+27->102
    //   92: bipush 93
    //   94: putstatic 34	uuuuuu/eehhee:b00770077ww0077ww0077w	I
    //   97: bipush 62
    //   99: putstatic 116	uuuuuu/eehhee:bw00770077w0077ww0077w	I
    //   102: aload 6
    //   104: astore 5
    //   106: aload 7
    //   108: invokevirtual 122	com/db/pwcc/dbmobile/model/banking/Account:getOnlineBalanceInBaseCurrency	()Ljava/math/BigDecimal;
    //   111: ifnull +10 -> 121
    //   114: aload 7
    //   116: invokevirtual 122	com/db/pwcc/dbmobile/model/banking/Account:getOnlineBalanceInBaseCurrency	()Ljava/math/BigDecimal;
    //   119: astore 5
    //   121: aload_1
    //   122: invokevirtual 126	com/db/pwcc/dbmobile/model/card/CreditCardTransactionsData:getCreditLimit	()Ljava/lang/String;
    //   125: aload 5
    //   127: invokestatic 132	uuuuuu/hphpph:b0077www00770077ww0077w	(Ljava/lang/String;Ljava/math/BigDecimal;)Ljava/math/BigDecimal;
    //   130: astore 6
    //   132: getstatic 34	uuuuuu/eehhee:b00770077ww0077ww0077w	I
    //   135: istore_2
    //   136: iload_2
    //   137: getstatic 36	uuuuuu/eehhee:bww0077w0077ww0077w	I
    //   140: iload_2
    //   141: iadd
    //   142: imul
    //   143: getstatic 38	uuuuuu/eehhee:b0077w0077w0077ww0077w	I
    //   146: irem
    //   147: tableswitch	default:+17->164, 0:+103->250
    //   164: ldc 2
    //   166: ldc -122
    //   168: sipush 166
    //   171: iconst_0
    //   172: invokestatic 46	xxxxxx/uxxxxx:bb00620062bb0062b0062b0062	(Ljava/lang/String;CC)Ljava/lang/String;
    //   175: iconst_0
    //   176: anewarray 48	java/lang/Class
    //   179: invokevirtual 52	java/lang/Class:getMethod	(Ljava/lang/String;[Ljava/lang/Class;)Ljava/lang/reflect/Method;
    //   182: astore 7
    //   184: aload 7
    //   186: aconst_null
    //   187: iconst_0
    //   188: anewarray 54	java/lang/Object
    //   191: invokevirtual 60	java/lang/reflect/Method:invoke	(Ljava/lang/Object;[Ljava/lang/Object;)Ljava/lang/Object;
    //   194: astore 7
    //   196: aload 7
    //   198: checkcast 62	java/lang/Integer
    //   201: invokevirtual 65	java/lang/Integer:intValue	()I
    //   204: putstatic 34	uuuuuu/eehhee:b00770077ww0077ww0077w	I
    //   207: ldc 2
    //   209: ldc -120
    //   211: sipush 217
    //   214: iconst_5
    //   215: invokestatic 46	xxxxxx/uxxxxx:bb00620062bb0062b0062b0062	(Ljava/lang/String;CC)Ljava/lang/String;
    //   218: iconst_0
    //   219: anewarray 48	java/lang/Class
    //   222: invokevirtual 52	java/lang/Class:getMethod	(Ljava/lang/String;[Ljava/lang/Class;)Ljava/lang/reflect/Method;
    //   225: astore 7
    //   227: aload 7
    //   229: aconst_null
    //   230: iconst_0
    //   231: anewarray 54	java/lang/Object
    //   234: invokevirtual 60	java/lang/reflect/Method:invoke	(Ljava/lang/Object;[Ljava/lang/Object;)Ljava/lang/Object;
    //   237: astore 7
    //   239: aload 7
    //   241: checkcast 62	java/lang/Integer
    //   244: invokevirtual 65	java/lang/Integer:intValue	()I
    //   247: putstatic 116	uuuuuu/eehhee:bw00770077w0077ww0077w	I
    //   250: aload_0
    //   251: invokevirtual 140	uuuuuu/eehhee:bkk006Bk006Bk006Bk006Bk	()Z
    //   254: ifeq +287 -> 541
    //   257: aload_0
    //   258: getfield 144	uuuuuu/eehhee:bnnnnn006E006E006En	Luuuuuu/ttssst$tsssst;
    //   261: checkcast 146	uuuuuu/heehee$hhehee
    //   264: invokeinterface 149 1 0
    //   269: getstatic 34	uuuuuu/eehhee:b00770077ww0077ww0077w	I
    //   272: getstatic 36	uuuuuu/eehhee:bww0077w0077ww0077w	I
    //   275: iadd
    //   276: getstatic 34	uuuuuu/eehhee:b00770077ww0077ww0077w	I
    //   279: imul
    //   280: getstatic 38	uuuuuu/eehhee:b0077w0077w0077ww0077w	I
    //   283: irem
    //   284: getstatic 116	uuuuuu/eehhee:bw00770077w0077ww0077w	I
    //   287: if_icmpeq +167 -> 454
    //   290: getstatic 34	uuuuuu/eehhee:b00770077ww0077ww0077w	I
    //   293: istore_2
    //   294: getstatic 36	uuuuuu/eehhee:bww0077w0077ww0077w	I
    //   297: istore_3
    //   298: getstatic 34	uuuuuu/eehhee:b00770077ww0077ww0077w	I
    //   301: istore 4
    //   303: ldc 2
    //   305: ldc -105
    //   307: bipush 25
    //   309: sipush 177
    //   312: iconst_1
    //   313: invokestatic 71	xxxxxx/uxxxxx:bbbb0062b0062b0062b0062	(Ljava/lang/String;CCC)Ljava/lang/String;
    //   316: iconst_0
    //   317: anewarray 48	java/lang/Class
    //   320: invokevirtual 52	java/lang/Class:getMethod	(Ljava/lang/String;[Ljava/lang/Class;)Ljava/lang/reflect/Method;
    //   323: astore 7
    //   325: aload 7
    //   327: aconst_null
    //   328: iconst_0
    //   329: anewarray 54	java/lang/Object
    //   332: invokevirtual 60	java/lang/reflect/Method:invoke	(Ljava/lang/Object;[Ljava/lang/Object;)Ljava/lang/Object;
    //   335: astore 7
    //   337: iload 4
    //   339: iload_2
    //   340: iload_3
    //   341: iadd
    //   342: imul
    //   343: aload 7
    //   345: checkcast 62	java/lang/Integer
    //   348: invokevirtual 65	java/lang/Integer:intValue	()I
    //   351: irem
    //   352: getstatic 116	uuuuuu/eehhee:bw00770077w0077ww0077w	I
    //   355: if_icmpeq +13 -> 368
    //   358: bipush 59
    //   360: putstatic 34	uuuuuu/eehhee:b00770077ww0077ww0077w	I
    //   363: bipush 31
    //   365: putstatic 116	uuuuuu/eehhee:bw00770077w0077ww0077w	I
    //   368: ldc 2
    //   370: ldc -103
    //   372: sipush 165
    //   375: iconst_1
    //   376: invokestatic 46	xxxxxx/uxxxxx:bb00620062bb0062b0062b0062	(Ljava/lang/String;CC)Ljava/lang/String;
    //   379: iconst_0
    //   380: anewarray 48	java/lang/Class
    //   383: invokevirtual 52	java/lang/Class:getMethod	(Ljava/lang/String;[Ljava/lang/Class;)Ljava/lang/reflect/Method;
    //   386: astore 7
    //   388: aload 7
    //   390: aconst_null
    //   391: iconst_0
    //   392: anewarray 54	java/lang/Object
    //   395: invokevirtual 60	java/lang/reflect/Method:invoke	(Ljava/lang/Object;[Ljava/lang/Object;)Ljava/lang/Object;
    //   398: astore 7
    //   400: aload 7
    //   402: checkcast 62	java/lang/Integer
    //   405: invokevirtual 65	java/lang/Integer:intValue	()I
    //   408: putstatic 34	uuuuuu/eehhee:b00770077ww0077ww0077w	I
    //   411: ldc 2
    //   413: ldc -101
    //   415: sipush 230
    //   418: iconst_5
    //   419: invokestatic 46	xxxxxx/uxxxxx:bb00620062bb0062b0062b0062	(Ljava/lang/String;CC)Ljava/lang/String;
    //   422: iconst_0
    //   423: anewarray 48	java/lang/Class
    //   426: invokevirtual 52	java/lang/Class:getMethod	(Ljava/lang/String;[Ljava/lang/Class;)Ljava/lang/reflect/Method;
    //   429: astore 7
    //   431: aload 7
    //   433: aconst_null
    //   434: iconst_0
    //   435: anewarray 54	java/lang/Object
    //   438: invokevirtual 60	java/lang/reflect/Method:invoke	(Ljava/lang/Object;[Ljava/lang/Object;)Ljava/lang/Object;
    //   441: astore 7
    //   443: aload 7
    //   445: checkcast 62	java/lang/Integer
    //   448: invokevirtual 65	java/lang/Integer:intValue	()I
    //   451: putstatic 116	uuuuuu/eehhee:bw00770077w0077ww0077w	I
    //   454: aload_0
    //   455: getfield 144	uuuuuu/eehhee:bnnnnn006E006E006En	Luuuuuu/ttssst$tsssst;
    //   458: checkcast 146	uuuuuu/heehee$hhehee
    //   461: aload_1
    //   462: invokevirtual 126	com/db/pwcc/dbmobile/model/card/CreditCardTransactionsData:getCreditLimit	()Ljava/lang/String;
    //   465: aload_1
    //   466: invokevirtual 158	com/db/pwcc/dbmobile/model/card/CreditCardTransactionsData:getBaseCurrency	()Ljava/lang/String;
    //   469: aload 5
    //   471: aload 6
    //   473: invokeinterface 162 5 0
    //   478: aload_1
    //   479: invokevirtual 166	com/db/pwcc/dbmobile/model/card/CreditCardTransactionsData:getBillingDates	()Ljava/util/List;
    //   482: astore_1
    //   483: ldc 2
    //   485: ldc -88
    //   487: sipush 162
    //   490: iconst_5
    //   491: invokestatic 46	xxxxxx/uxxxxx:bb00620062bb0062b0062b0062	(Ljava/lang/String;CC)Ljava/lang/String;
    //   494: iconst_1
    //   495: anewarray 48	java/lang/Class
    //   498: dup
    //   499: iconst_0
    //   500: ldc -86
    //   502: aastore
    //   503: invokevirtual 52	java/lang/Class:getMethod	(Ljava/lang/String;[Ljava/lang/Class;)Ljava/lang/reflect/Method;
    //   506: astore 5
    //   508: aload 5
    //   510: aload_0
    //   511: iconst_1
    //   512: anewarray 54	java/lang/Object
    //   515: dup
    //   516: iconst_0
    //   517: aload_1
    //   518: aastore
    //   519: invokevirtual 60	java/lang/reflect/Method:invoke	(Ljava/lang/Object;[Ljava/lang/Object;)Ljava/lang/Object;
    //   522: astore_1
    //   523: aload_1
    //   524: checkcast 170	java/util/List
    //   527: astore_1
    //   528: aload_0
    //   529: getfield 144	uuuuuu/eehhee:bnnnnn006E006E006En	Luuuuuu/ttssst$tsssst;
    //   532: checkcast 146	uuuuuu/heehee$hhehee
    //   535: aload_1
    //   536: invokeinterface 174 2 0
    //   541: return
    //   542: astore_1
    //   543: aload_1
    //   544: invokevirtual 96	java/lang/reflect/InvocationTargetException:getCause	()Ljava/lang/Throwable;
    //   547: athrow
    //   548: astore_1
    //   549: aload_1
    //   550: invokevirtual 96	java/lang/reflect/InvocationTargetException:getCause	()Ljava/lang/Throwable;
    //   553: athrow
    //   554: astore_1
    //   555: aload_1
    //   556: invokevirtual 96	java/lang/reflect/InvocationTargetException:getCause	()Ljava/lang/Throwable;
    //   559: athrow
    //   560: astore_1
    //   561: aload_1
    //   562: invokevirtual 96	java/lang/reflect/InvocationTargetException:getCause	()Ljava/lang/Throwable;
    //   565: athrow
    //   566: astore_1
    //   567: aload_1
    //   568: invokevirtual 96	java/lang/reflect/InvocationTargetException:getCause	()Ljava/lang/Throwable;
    //   571: athrow
    //   572: astore_1
    //   573: aload_1
    //   574: invokevirtual 96	java/lang/reflect/InvocationTargetException:getCause	()Ljava/lang/Throwable;
    //   577: athrow
    //   578: astore_1
    //   579: aload_1
    //   580: invokevirtual 96	java/lang/reflect/InvocationTargetException:getCause	()Ljava/lang/Throwable;
    //   583: athrow
    // Local variable table:
    //   start	length	slot	name	signature
    //   0	584	0	this	eehhee
    //   0	584	1	paramCreditCardTransactionsData	com.db.pwcc.dbmobile.model.card.CreditCardTransactionsData
    //   63	279	2	i	int
    //   297	45	3	j	int
    //   301	42	4	k	int
    //   13	496	5	localObject1	Object
    //   3	469	6	localBigDecimal	java.math.BigDecimal
    //   9	435	7	localObject2	Object
    // Exception table:
    //   from	to	target	type
    //   508	523	542	java/lang/reflect/InvocationTargetException
    //   43	55	548	java/lang/reflect/InvocationTargetException
    //   388	400	554	java/lang/reflect/InvocationTargetException
    //   431	443	560	java/lang/reflect/InvocationTargetException
    //   325	337	566	java/lang/reflect/InvocationTargetException
    //   184	196	572	java/lang/reflect/InvocationTargetException
    //   227	239	578	java/lang/reflect/InvocationTargetException
  }
  
  /* Error */
  public void boo006F006F006F006Fo006F006Fo(@android.support.annotation.NonNull String paramString)
  {
    // Byte code:
    //   0: aload_0
    //   1: invokevirtual 140	uuuuuu/eehhee:bkk006Bk006Bk006Bk006Bk	()Z
    //   4: ifeq +312 -> 316
    //   7: getstatic 34	uuuuuu/eehhee:b00770077ww0077ww0077w	I
    //   10: getstatic 36	uuuuuu/eehhee:bww0077w0077ww0077w	I
    //   13: iadd
    //   14: getstatic 34	uuuuuu/eehhee:b00770077ww0077ww0077w	I
    //   17: imul
    //   18: getstatic 38	uuuuuu/eehhee:b0077w0077w0077ww0077w	I
    //   21: irem
    //   22: getstatic 116	uuuuuu/eehhee:bw00770077w0077ww0077w	I
    //   25: if_icmpeq +279 -> 304
    //   28: getstatic 34	uuuuuu/eehhee:b00770077ww0077ww0077w	I
    //   31: istore_2
    //   32: ldc 2
    //   34: ldc -77
    //   36: sipush 135
    //   39: sipush 221
    //   42: iconst_3
    //   43: invokestatic 71	xxxxxx/uxxxxx:bbbb0062b0062b0062b0062	(Ljava/lang/String;CCC)Ljava/lang/String;
    //   46: iconst_0
    //   47: anewarray 48	java/lang/Class
    //   50: invokevirtual 52	java/lang/Class:getMethod	(Ljava/lang/String;[Ljava/lang/Class;)Ljava/lang/reflect/Method;
    //   53: astore 6
    //   55: aload 6
    //   57: aconst_null
    //   58: iconst_0
    //   59: anewarray 54	java/lang/Object
    //   62: invokevirtual 60	java/lang/reflect/Method:invoke	(Ljava/lang/Object;[Ljava/lang/Object;)Ljava/lang/Object;
    //   65: astore 6
    //   67: aload 6
    //   69: checkcast 62	java/lang/Integer
    //   72: invokevirtual 65	java/lang/Integer:intValue	()I
    //   75: istore_3
    //   76: getstatic 34	uuuuuu/eehhee:b00770077ww0077ww0077w	I
    //   79: istore 4
    //   81: getstatic 38	uuuuuu/eehhee:b0077w0077w0077ww0077w	I
    //   84: istore 5
    //   86: ldc 2
    //   88: ldc -75
    //   90: bipush 21
    //   92: iconst_0
    //   93: invokestatic 46	xxxxxx/uxxxxx:bb00620062bb0062b0062b0062	(Ljava/lang/String;CC)Ljava/lang/String;
    //   96: iconst_0
    //   97: anewarray 48	java/lang/Class
    //   100: invokevirtual 52	java/lang/Class:getMethod	(Ljava/lang/String;[Ljava/lang/Class;)Ljava/lang/reflect/Method;
    //   103: astore 6
    //   105: aload 6
    //   107: aconst_null
    //   108: iconst_0
    //   109: anewarray 54	java/lang/Object
    //   112: invokevirtual 60	java/lang/reflect/Method:invoke	(Ljava/lang/Object;[Ljava/lang/Object;)Ljava/lang/Object;
    //   115: astore 6
    //   117: iload_3
    //   118: iload_2
    //   119: iadd
    //   120: iload 4
    //   122: imul
    //   123: iload 5
    //   125: irem
    //   126: aload 6
    //   128: checkcast 62	java/lang/Integer
    //   131: invokevirtual 65	java/lang/Integer:intValue	()I
    //   134: if_icmpeq +13 -> 147
    //   137: bipush 92
    //   139: putstatic 34	uuuuuu/eehhee:b00770077ww0077ww0077w	I
    //   142: bipush 77
    //   144: putstatic 116	uuuuuu/eehhee:bw00770077w0077ww0077w	I
    //   147: ldc 2
    //   149: ldc -73
    //   151: bipush 52
    //   153: sipush 147
    //   156: iconst_0
    //   157: invokestatic 71	xxxxxx/uxxxxx:bbbb0062b0062b0062b0062	(Ljava/lang/String;CCC)Ljava/lang/String;
    //   160: iconst_0
    //   161: anewarray 48	java/lang/Class
    //   164: invokevirtual 52	java/lang/Class:getMethod	(Ljava/lang/String;[Ljava/lang/Class;)Ljava/lang/reflect/Method;
    //   167: astore 6
    //   169: aload 6
    //   171: aconst_null
    //   172: iconst_0
    //   173: anewarray 54	java/lang/Object
    //   176: invokevirtual 60	java/lang/reflect/Method:invoke	(Ljava/lang/Object;[Ljava/lang/Object;)Ljava/lang/Object;
    //   179: astore 6
    //   181: aload 6
    //   183: checkcast 62	java/lang/Integer
    //   186: invokevirtual 65	java/lang/Integer:intValue	()I
    //   189: putstatic 34	uuuuuu/eehhee:b00770077ww0077ww0077w	I
    //   192: ldc 2
    //   194: ldc -71
    //   196: bipush 73
    //   198: iconst_1
    //   199: invokestatic 46	xxxxxx/uxxxxx:bb00620062bb0062b0062b0062	(Ljava/lang/String;CC)Ljava/lang/String;
    //   202: iconst_0
    //   203: anewarray 48	java/lang/Class
    //   206: invokevirtual 52	java/lang/Class:getMethod	(Ljava/lang/String;[Ljava/lang/Class;)Ljava/lang/reflect/Method;
    //   209: astore 6
    //   211: aload 6
    //   213: aconst_null
    //   214: iconst_0
    //   215: anewarray 54	java/lang/Object
    //   218: invokevirtual 60	java/lang/reflect/Method:invoke	(Ljava/lang/Object;[Ljava/lang/Object;)Ljava/lang/Object;
    //   221: astore 6
    //   223: aload 6
    //   225: checkcast 62	java/lang/Integer
    //   228: invokevirtual 65	java/lang/Integer:intValue	()I
    //   231: istore_2
    //   232: getstatic 34	uuuuuu/eehhee:b00770077ww0077ww0077w	I
    //   235: getstatic 36	uuuuuu/eehhee:bww0077w0077ww0077w	I
    //   238: iadd
    //   239: getstatic 34	uuuuuu/eehhee:b00770077ww0077ww0077w	I
    //   242: imul
    //   243: getstatic 38	uuuuuu/eehhee:b0077w0077w0077ww0077w	I
    //   246: irem
    //   247: getstatic 116	uuuuuu/eehhee:bw00770077w0077ww0077w	I
    //   250: if_icmpeq +50 -> 300
    //   253: bipush 60
    //   255: putstatic 34	uuuuuu/eehhee:b00770077ww0077ww0077w	I
    //   258: ldc 2
    //   260: ldc -69
    //   262: bipush 50
    //   264: iconst_4
    //   265: invokestatic 46	xxxxxx/uxxxxx:bb00620062bb0062b0062b0062	(Ljava/lang/String;CC)Ljava/lang/String;
    //   268: iconst_0
    //   269: anewarray 48	java/lang/Class
    //   272: invokevirtual 52	java/lang/Class:getMethod	(Ljava/lang/String;[Ljava/lang/Class;)Ljava/lang/reflect/Method;
    //   275: astore 6
    //   277: aload 6
    //   279: aconst_null
    //   280: iconst_0
    //   281: anewarray 54	java/lang/Object
    //   284: invokevirtual 60	java/lang/reflect/Method:invoke	(Ljava/lang/Object;[Ljava/lang/Object;)Ljava/lang/Object;
    //   287: astore 6
    //   289: aload 6
    //   291: checkcast 62	java/lang/Integer
    //   294: invokevirtual 65	java/lang/Integer:intValue	()I
    //   297: putstatic 116	uuuuuu/eehhee:bw00770077w0077ww0077w	I
    //   300: iload_2
    //   301: putstatic 116	uuuuuu/eehhee:bw00770077w0077ww0077w	I
    //   304: aload_0
    //   305: getfield 144	uuuuuu/eehhee:bnnnnn006E006E006En	Luuuuuu/ttssst$tsssst;
    //   308: checkcast 146	uuuuuu/heehee$hhehee
    //   311: invokeinterface 190 1 0
    //   316: getstatic 34	uuuuuu/eehhee:b00770077ww0077ww0077w	I
    //   319: getstatic 36	uuuuuu/eehhee:bww0077w0077ww0077w	I
    //   322: iadd
    //   323: getstatic 34	uuuuuu/eehhee:b00770077ww0077ww0077w	I
    //   326: imul
    //   327: getstatic 38	uuuuuu/eehhee:b0077w0077w0077ww0077w	I
    //   330: irem
    //   331: getstatic 116	uuuuuu/eehhee:bw00770077w0077ww0077w	I
    //   334: if_icmpeq +51 -> 385
    //   337: bipush 93
    //   339: putstatic 34	uuuuuu/eehhee:b00770077ww0077ww0077w	I
    //   342: ldc 2
    //   344: ldc -64
    //   346: sipush 232
    //   349: iconst_5
    //   350: invokestatic 46	xxxxxx/uxxxxx:bb00620062bb0062b0062b0062	(Ljava/lang/String;CC)Ljava/lang/String;
    //   353: iconst_0
    //   354: anewarray 48	java/lang/Class
    //   357: invokevirtual 52	java/lang/Class:getMethod	(Ljava/lang/String;[Ljava/lang/Class;)Ljava/lang/reflect/Method;
    //   360: astore 6
    //   362: aload 6
    //   364: aconst_null
    //   365: iconst_0
    //   366: anewarray 54	java/lang/Object
    //   369: invokevirtual 60	java/lang/reflect/Method:invoke	(Ljava/lang/Object;[Ljava/lang/Object;)Ljava/lang/Object;
    //   372: astore 6
    //   374: aload 6
    //   376: checkcast 62	java/lang/Integer
    //   379: invokevirtual 65	java/lang/Integer:intValue	()I
    //   382: putstatic 116	uuuuuu/eehhee:bw00770077w0077ww0077w	I
    //   385: new 194	uuuuuu/fmffmm
    //   388: dup
    //   389: invokespecial 195	uuuuuu/fmffmm:<init>	()V
    //   392: aload_0
    //   393: aload_1
    //   394: invokevirtual 199	uuuuuu/fmffmm:bppp00700070pp00700070p	(Luuuuuu/vpppvp$pvppvp;Ljava/lang/String;)V
    //   397: return
    //   398: astore_1
    //   399: aload_1
    //   400: invokevirtual 96	java/lang/reflect/InvocationTargetException:getCause	()Ljava/lang/Throwable;
    //   403: athrow
    //   404: astore_1
    //   405: aload_1
    //   406: invokevirtual 96	java/lang/reflect/InvocationTargetException:getCause	()Ljava/lang/Throwable;
    //   409: athrow
    //   410: astore_1
    //   411: aload_1
    //   412: invokevirtual 96	java/lang/reflect/InvocationTargetException:getCause	()Ljava/lang/Throwable;
    //   415: athrow
    //   416: astore_1
    //   417: aload_1
    //   418: invokevirtual 96	java/lang/reflect/InvocationTargetException:getCause	()Ljava/lang/Throwable;
    //   421: athrow
    //   422: astore_1
    //   423: aload_1
    //   424: invokevirtual 96	java/lang/reflect/InvocationTargetException:getCause	()Ljava/lang/Throwable;
    //   427: athrow
    //   428: astore_1
    //   429: aload_1
    //   430: invokevirtual 96	java/lang/reflect/InvocationTargetException:getCause	()Ljava/lang/Throwable;
    //   433: athrow
    // Local variable table:
    //   start	length	slot	name	signature
    //   0	434	0	this	eehhee
    //   0	434	1	paramString	String
    //   31	270	2	i	int
    //   75	45	3	j	int
    //   79	44	4	k	int
    //   84	42	5	m	int
    //   53	322	6	localObject	Object
    // Exception table:
    //   from	to	target	type
    //   55	67	398	java/lang/reflect/InvocationTargetException
    //   105	117	404	java/lang/reflect/InvocationTargetException
    //   362	374	410	java/lang/reflect/InvocationTargetException
    //   169	181	416	java/lang/reflect/InvocationTargetException
    //   211	223	422	java/lang/reflect/InvocationTargetException
    //   277	289	428	java/lang/reflect/InvocationTargetException
  }
  
  /* Error */
  public void bp00700070p0070pp00700070p(com.db.pwcc.dbmobile.model.error.DbError paramDbError)
  {
    // Byte code:
    //   0: getstatic 34	uuuuuu/eehhee:b00770077ww0077ww0077w	I
    //   3: getstatic 36	uuuuuu/eehhee:bww0077w0077ww0077w	I
    //   6: iadd
    //   7: getstatic 34	uuuuuu/eehhee:b00770077ww0077ww0077w	I
    //   10: imul
    //   11: getstatic 38	uuuuuu/eehhee:b0077w0077w0077ww0077w	I
    //   14: irem
    //   15: getstatic 116	uuuuuu/eehhee:bw00770077w0077ww0077w	I
    //   18: if_icmpeq +162 -> 180
    //   21: getstatic 34	uuuuuu/eehhee:b00770077ww0077ww0077w	I
    //   24: getstatic 36	uuuuuu/eehhee:bww0077w0077ww0077w	I
    //   27: iadd
    //   28: getstatic 34	uuuuuu/eehhee:b00770077ww0077ww0077w	I
    //   31: imul
    //   32: getstatic 38	uuuuuu/eehhee:b0077w0077w0077ww0077w	I
    //   35: irem
    //   36: getstatic 116	uuuuuu/eehhee:bw00770077w0077ww0077w	I
    //   39: if_icmpeq +131 -> 170
    //   42: getstatic 34	uuuuuu/eehhee:b00770077ww0077ww0077w	I
    //   45: istore_2
    //   46: iload_2
    //   47: getstatic 36	uuuuuu/eehhee:bww0077w0077ww0077w	I
    //   50: iload_2
    //   51: iadd
    //   52: imul
    //   53: getstatic 38	uuuuuu/eehhee:b0077w0077w0077ww0077w	I
    //   56: irem
    //   57: tableswitch	default:+19->76, 0:+66->123
    //   76: bipush 22
    //   78: putstatic 34	uuuuuu/eehhee:b00770077ww0077ww0077w	I
    //   81: ldc 2
    //   83: ldc -52
    //   85: sipush 142
    //   88: sipush 144
    //   91: iconst_3
    //   92: invokestatic 71	xxxxxx/uxxxxx:bbbb0062b0062b0062b0062	(Ljava/lang/String;CCC)Ljava/lang/String;
    //   95: iconst_0
    //   96: anewarray 48	java/lang/Class
    //   99: invokevirtual 52	java/lang/Class:getMethod	(Ljava/lang/String;[Ljava/lang/Class;)Ljava/lang/reflect/Method;
    //   102: astore_3
    //   103: aload_3
    //   104: aconst_null
    //   105: iconst_0
    //   106: anewarray 54	java/lang/Object
    //   109: invokevirtual 60	java/lang/reflect/Method:invoke	(Ljava/lang/Object;[Ljava/lang/Object;)Ljava/lang/Object;
    //   112: astore_3
    //   113: aload_3
    //   114: checkcast 62	java/lang/Integer
    //   117: invokevirtual 65	java/lang/Integer:intValue	()I
    //   120: putstatic 116	uuuuuu/eehhee:bw00770077w0077ww0077w	I
    //   123: bipush 92
    //   125: putstatic 34	uuuuuu/eehhee:b00770077ww0077ww0077w	I
    //   128: ldc 2
    //   130: ldc -50
    //   132: sipush 245
    //   135: sipush 242
    //   138: iconst_3
    //   139: invokestatic 71	xxxxxx/uxxxxx:bbbb0062b0062b0062b0062	(Ljava/lang/String;CCC)Ljava/lang/String;
    //   142: iconst_0
    //   143: anewarray 48	java/lang/Class
    //   146: invokevirtual 52	java/lang/Class:getMethod	(Ljava/lang/String;[Ljava/lang/Class;)Ljava/lang/reflect/Method;
    //   149: astore_3
    //   150: aload_3
    //   151: aconst_null
    //   152: iconst_0
    //   153: anewarray 54	java/lang/Object
    //   156: invokevirtual 60	java/lang/reflect/Method:invoke	(Ljava/lang/Object;[Ljava/lang/Object;)Ljava/lang/Object;
    //   159: astore_3
    //   160: aload_3
    //   161: checkcast 62	java/lang/Integer
    //   164: invokevirtual 65	java/lang/Integer:intValue	()I
    //   167: putstatic 116	uuuuuu/eehhee:bw00770077w0077ww0077w	I
    //   170: bipush 91
    //   172: putstatic 34	uuuuuu/eehhee:b00770077ww0077ww0077w	I
    //   175: bipush 49
    //   177: putstatic 116	uuuuuu/eehhee:bw00770077w0077ww0077w	I
    //   180: aload_0
    //   181: invokevirtual 140	uuuuuu/eehhee:bkk006Bk006Bk006Bk006Bk	()Z
    //   184: ifeq +49 -> 233
    //   187: aload_0
    //   188: getfield 144	uuuuuu/eehhee:bnnnnn006E006E006En	Luuuuuu/ttssst$tsssst;
    //   191: checkcast 146	uuuuuu/heehee$hhehee
    //   194: astore_3
    //   195: getstatic 34	uuuuuu/eehhee:b00770077ww0077ww0077w	I
    //   198: getstatic 36	uuuuuu/eehhee:bww0077w0077ww0077w	I
    //   201: iadd
    //   202: getstatic 34	uuuuuu/eehhee:b00770077ww0077ww0077w	I
    //   205: imul
    //   206: getstatic 38	uuuuuu/eehhee:b0077w0077w0077ww0077w	I
    //   209: irem
    //   210: getstatic 116	uuuuuu/eehhee:bw00770077w0077ww0077w	I
    //   213: if_icmpeq +13 -> 226
    //   216: bipush 85
    //   218: putstatic 34	uuuuuu/eehhee:b00770077ww0077ww0077w	I
    //   221: bipush 37
    //   223: putstatic 116	uuuuuu/eehhee:bw00770077w0077ww0077w	I
    //   226: aload_3
    //   227: aload_1
    //   228: invokeinterface 209 2 0
    //   233: return
    //   234: astore_1
    //   235: aload_1
    //   236: invokevirtual 96	java/lang/reflect/InvocationTargetException:getCause	()Ljava/lang/Throwable;
    //   239: athrow
    //   240: astore_1
    //   241: aload_1
    //   242: invokevirtual 96	java/lang/reflect/InvocationTargetException:getCause	()Ljava/lang/Throwable;
    //   245: athrow
    // Local variable table:
    //   start	length	slot	name	signature
    //   0	246	0	this	eehhee
    //   0	246	1	paramDbError	com.db.pwcc.dbmobile.model.error.DbError
    //   45	8	2	i	int
    //   102	125	3	localObject	Object
    // Exception table:
    //   from	to	target	type
    //   150	160	234	java/lang/reflect/InvocationTargetException
    //   103	113	240	java/lang/reflect/InvocationTargetException
  }
}
