package uuuuuu;

import javax.inject.Inject;

public class gaaaaa
  extends ssssst<aagaaa.agaaaa>
  implements aagaaa.ggaaaa
{
  public static int b00790079y0079y007900790079y = 1;
  public static int b0079yy0079y007900790079y = 0;
  public static int by0079y0079y007900790079y = 2;
  public static int byyy0079y007900790079y = 10;
  @Inject
  public gaaaga b007900790079yy007900790079y;
  @Inject
  public xxsxxs by00790079yy007900790079y;
  
  public gaaaaa() {}
  
  public static int b0077007700770077w0077w0077ww()
  {
    return 0;
  }
  
  /* Error */
  private void b0077w0077w00770077w0077ww()
  {
    // Byte code:
    //   0: aload_0
    //   1: getfield 33	uuuuuu/gaaaaa:b007900790079yy007900790079y	Luuuuuu/gaaaga;
    //   4: astore 6
    //   6: getstatic 35	uuuuuu/gaaaaa:byyy0079y007900790079y	I
    //   9: getstatic 37	uuuuuu/gaaaaa:b00790079y0079y007900790079y	I
    //   12: iadd
    //   13: getstatic 35	uuuuuu/gaaaaa:byyy0079y007900790079y	I
    //   16: imul
    //   17: getstatic 39	uuuuuu/gaaaaa:by0079y0079y007900790079y	I
    //   20: irem
    //   21: getstatic 41	uuuuuu/gaaaaa:b0079yy0079y007900790079y	I
    //   24: if_icmpeq +171 -> 195
    //   27: getstatic 35	uuuuuu/gaaaaa:byyy0079y007900790079y	I
    //   30: istore_1
    //   31: iload_1
    //   32: getstatic 37	uuuuuu/gaaaaa:b00790079y0079y007900790079y	I
    //   35: iload_1
    //   36: iadd
    //   37: imul
    //   38: getstatic 39	uuuuuu/gaaaaa:by0079y0079y007900790079y	I
    //   41: irem
    //   42: tableswitch	default:+18->60, 0:+104->146
    //   60: ldc 2
    //   62: ldc 43
    //   64: sipush 155
    //   67: iconst_2
    //   68: invokestatic 49	xxxxxx/uxxxxx:bb00620062bb0062b0062b0062	(Ljava/lang/String;CC)Ljava/lang/String;
    //   71: iconst_0
    //   72: anewarray 51	java/lang/Class
    //   75: invokevirtual 55	java/lang/Class:getMethod	(Ljava/lang/String;[Ljava/lang/Class;)Ljava/lang/reflect/Method;
    //   78: astore 7
    //   80: aload 7
    //   82: aconst_null
    //   83: iconst_0
    //   84: anewarray 57	java/lang/Object
    //   87: invokevirtual 63	java/lang/reflect/Method:invoke	(Ljava/lang/Object;[Ljava/lang/Object;)Ljava/lang/Object;
    //   90: astore 7
    //   92: aload 7
    //   94: checkcast 65	java/lang/Integer
    //   97: invokevirtual 68	java/lang/Integer:intValue	()I
    //   100: putstatic 35	uuuuuu/gaaaaa:byyy0079y007900790079y	I
    //   103: ldc 2
    //   105: ldc 70
    //   107: sipush 164
    //   110: iconst_3
    //   111: invokestatic 49	xxxxxx/uxxxxx:bb00620062bb0062b0062b0062	(Ljava/lang/String;CC)Ljava/lang/String;
    //   114: iconst_0
    //   115: anewarray 51	java/lang/Class
    //   118: invokevirtual 55	java/lang/Class:getMethod	(Ljava/lang/String;[Ljava/lang/Class;)Ljava/lang/reflect/Method;
    //   121: astore 7
    //   123: aload 7
    //   125: aconst_null
    //   126: iconst_0
    //   127: anewarray 57	java/lang/Object
    //   130: invokevirtual 63	java/lang/reflect/Method:invoke	(Ljava/lang/Object;[Ljava/lang/Object;)Ljava/lang/Object;
    //   133: astore 7
    //   135: aload 7
    //   137: checkcast 65	java/lang/Integer
    //   140: invokevirtual 68	java/lang/Integer:intValue	()I
    //   143: putstatic 41	uuuuuu/gaaaaa:b0079yy0079y007900790079y	I
    //   146: bipush 33
    //   148: putstatic 35	uuuuuu/gaaaaa:byyy0079y007900790079y	I
    //   151: ldc 2
    //   153: ldc 72
    //   155: bipush 18
    //   157: bipush 127
    //   159: iconst_1
    //   160: invokestatic 76	xxxxxx/uxxxxx:bbbb0062b0062b0062b0062	(Ljava/lang/String;CCC)Ljava/lang/String;
    //   163: iconst_0
    //   164: anewarray 51	java/lang/Class
    //   167: invokevirtual 55	java/lang/Class:getMethod	(Ljava/lang/String;[Ljava/lang/Class;)Ljava/lang/reflect/Method;
    //   170: astore 7
    //   172: aload 7
    //   174: aconst_null
    //   175: iconst_0
    //   176: anewarray 57	java/lang/Object
    //   179: invokevirtual 63	java/lang/reflect/Method:invoke	(Ljava/lang/Object;[Ljava/lang/Object;)Ljava/lang/Object;
    //   182: astore 7
    //   184: aload 7
    //   186: checkcast 65	java/lang/Integer
    //   189: invokevirtual 68	java/lang/Integer:intValue	()I
    //   192: putstatic 41	uuuuuu/gaaaaa:b0079yy0079y007900790079y	I
    //   195: aload 6
    //   197: iconst_1
    //   198: invokevirtual 82	uuuuuu/gaaaga:b0077w0077wwww0077ww	(I)Lcom/db/pwcc/dbmobile/treatments/model/TreatmentCache;
    //   201: astore 6
    //   203: aload 6
    //   205: invokevirtual 88	com/db/pwcc/dbmobile/treatments/model/TreatmentCache:getCategory	()Lcom/db/pwcc/dbmobile/treatments/model/TreatmentCategory;
    //   208: getstatic 94	com/db/pwcc/dbmobile/treatments/model/TreatmentCategory:INFORMATION	Lcom/db/pwcc/dbmobile/treatments/model/TreatmentCategory;
    //   211: if_acmpne +229 -> 440
    //   214: aload_0
    //   215: getfield 98	uuuuuu/gaaaaa:bnnnnn006E006E006En	Luuuuuu/ttssst$tsssst;
    //   218: checkcast 100	uuuuuu/aagaaa$agaaaa
    //   221: astore 7
    //   223: getstatic 35	uuuuuu/gaaaaa:byyy0079y007900790079y	I
    //   226: istore_1
    //   227: getstatic 37	uuuuuu/gaaaaa:b00790079y0079y007900790079y	I
    //   230: istore_2
    //   231: getstatic 35	uuuuuu/gaaaaa:byyy0079y007900790079y	I
    //   234: istore_3
    //   235: getstatic 37	uuuuuu/gaaaaa:b00790079y0079y007900790079y	I
    //   238: istore 4
    //   240: getstatic 35	uuuuuu/gaaaaa:byyy0079y007900790079y	I
    //   243: istore 5
    //   245: ldc 2
    //   247: ldc 102
    //   249: sipush 239
    //   252: sipush 181
    //   255: iconst_0
    //   256: invokestatic 76	xxxxxx/uxxxxx:bbbb0062b0062b0062b0062	(Ljava/lang/String;CCC)Ljava/lang/String;
    //   259: iconst_0
    //   260: anewarray 51	java/lang/Class
    //   263: invokevirtual 55	java/lang/Class:getMethod	(Ljava/lang/String;[Ljava/lang/Class;)Ljava/lang/reflect/Method;
    //   266: astore 8
    //   268: aload 8
    //   270: aconst_null
    //   271: iconst_0
    //   272: anewarray 57	java/lang/Object
    //   275: invokevirtual 63	java/lang/reflect/Method:invoke	(Ljava/lang/Object;[Ljava/lang/Object;)Ljava/lang/Object;
    //   278: astore 8
    //   280: iload 5
    //   282: iload_3
    //   283: iload 4
    //   285: iadd
    //   286: imul
    //   287: aload 8
    //   289: checkcast 65	java/lang/Integer
    //   292: invokevirtual 68	java/lang/Integer:intValue	()I
    //   295: irem
    //   296: getstatic 41	uuuuuu/gaaaaa:b0079yy0079y007900790079y	I
    //   299: if_icmpeq +50 -> 349
    //   302: bipush 71
    //   304: putstatic 35	uuuuuu/gaaaaa:byyy0079y007900790079y	I
    //   307: ldc 2
    //   309: ldc 104
    //   311: bipush 92
    //   313: iconst_1
    //   314: invokestatic 49	xxxxxx/uxxxxx:bb00620062bb0062b0062b0062	(Ljava/lang/String;CC)Ljava/lang/String;
    //   317: iconst_0
    //   318: anewarray 51	java/lang/Class
    //   321: invokevirtual 55	java/lang/Class:getMethod	(Ljava/lang/String;[Ljava/lang/Class;)Ljava/lang/reflect/Method;
    //   324: astore 8
    //   326: aload 8
    //   328: aconst_null
    //   329: iconst_0
    //   330: anewarray 57	java/lang/Object
    //   333: invokevirtual 63	java/lang/reflect/Method:invoke	(Ljava/lang/Object;[Ljava/lang/Object;)Ljava/lang/Object;
    //   336: astore 8
    //   338: aload 8
    //   340: checkcast 65	java/lang/Integer
    //   343: invokevirtual 68	java/lang/Integer:intValue	()I
    //   346: putstatic 41	uuuuuu/gaaaaa:b0079yy0079y007900790079y	I
    //   349: ldc 2
    //   351: ldc 106
    //   353: bipush 72
    //   355: iconst_5
    //   356: invokestatic 49	xxxxxx/uxxxxx:bb00620062bb0062b0062b0062	(Ljava/lang/String;CC)Ljava/lang/String;
    //   359: iconst_0
    //   360: anewarray 51	java/lang/Class
    //   363: invokevirtual 55	java/lang/Class:getMethod	(Ljava/lang/String;[Ljava/lang/Class;)Ljava/lang/reflect/Method;
    //   366: astore 8
    //   368: aload 8
    //   370: aconst_null
    //   371: iconst_0
    //   372: anewarray 57	java/lang/Object
    //   375: invokevirtual 63	java/lang/reflect/Method:invoke	(Ljava/lang/Object;[Ljava/lang/Object;)Ljava/lang/Object;
    //   378: astore 8
    //   380: iload_1
    //   381: iload_1
    //   382: iload_2
    //   383: iadd
    //   384: imul
    //   385: aload 8
    //   387: checkcast 65	java/lang/Integer
    //   390: invokevirtual 68	java/lang/Integer:intValue	()I
    //   393: irem
    //   394: tableswitch	default:+18->412, 0:+28->422
    //   412: bipush 74
    //   414: putstatic 35	uuuuuu/gaaaaa:byyy0079y007900790079y	I
    //   417: bipush 73
    //   419: putstatic 41	uuuuuu/gaaaaa:b0079yy0079y007900790079y	I
    //   422: aload 7
    //   424: aload 6
    //   426: invokevirtual 110	com/db/pwcc/dbmobile/treatments/model/TreatmentCache:getHeadline	()Ljava/lang/String;
    //   429: aload 6
    //   431: invokevirtual 113	com/db/pwcc/dbmobile/treatments/model/TreatmentCache:getText	()Ljava/lang/String;
    //   434: invokeinterface 117 3 0
    //   439: return
    //   440: aload 6
    //   442: invokevirtual 88	com/db/pwcc/dbmobile/treatments/model/TreatmentCache:getCategory	()Lcom/db/pwcc/dbmobile/treatments/model/TreatmentCategory;
    //   445: getstatic 120	com/db/pwcc/dbmobile/treatments/model/TreatmentCategory:ADVERTISEMENT	Lcom/db/pwcc/dbmobile/treatments/model/TreatmentCategory;
    //   448: if_acmpne -9 -> 439
    //   451: ldc 2
    //   453: ldc 122
    //   455: sipush 215
    //   458: sipush 138
    //   461: iconst_0
    //   462: invokestatic 76	xxxxxx/uxxxxx:bbbb0062b0062b0062b0062	(Ljava/lang/String;CCC)Ljava/lang/String;
    //   465: iconst_0
    //   466: anewarray 51	java/lang/Class
    //   469: invokevirtual 125	java/lang/Class:getDeclaredMethod	(Ljava/lang/String;[Ljava/lang/Class;)Ljava/lang/reflect/Method;
    //   472: astore 6
    //   474: aload 6
    //   476: aload_0
    //   477: iconst_0
    //   478: anewarray 57	java/lang/Object
    //   481: invokevirtual 63	java/lang/reflect/Method:invoke	(Ljava/lang/Object;[Ljava/lang/Object;)Ljava/lang/Object;
    //   484: pop
    //   485: return
    //   486: astore 6
    //   488: aload 6
    //   490: invokevirtual 129	java/lang/reflect/InvocationTargetException:getCause	()Ljava/lang/Throwable;
    //   493: athrow
    //   494: astore 6
    //   496: aload 6
    //   498: invokevirtual 129	java/lang/reflect/InvocationTargetException:getCause	()Ljava/lang/Throwable;
    //   501: athrow
    //   502: astore 6
    //   504: aload 6
    //   506: invokevirtual 129	java/lang/reflect/InvocationTargetException:getCause	()Ljava/lang/Throwable;
    //   509: athrow
    //   510: astore 6
    //   512: aload 6
    //   514: invokevirtual 129	java/lang/reflect/InvocationTargetException:getCause	()Ljava/lang/Throwable;
    //   517: athrow
    //   518: astore 6
    //   520: aload 6
    //   522: invokevirtual 129	java/lang/reflect/InvocationTargetException:getCause	()Ljava/lang/Throwable;
    //   525: athrow
    //   526: astore 6
    //   528: aload 6
    //   530: invokevirtual 129	java/lang/reflect/InvocationTargetException:getCause	()Ljava/lang/Throwable;
    //   533: athrow
    //   534: astore 6
    //   536: aload 6
    //   538: invokevirtual 129	java/lang/reflect/InvocationTargetException:getCause	()Ljava/lang/Throwable;
    //   541: athrow
    // Local variable table:
    //   start	length	slot	name	signature
    //   0	542	0	this	gaaaaa
    //   30	355	1	i	int
    //   230	154	2	j	int
    //   234	52	3	k	int
    //   238	48	4	m	int
    //   243	44	5	n	int
    //   4	471	6	localObject1	Object
    //   486	3	6	localInvocationTargetException1	java.lang.reflect.InvocationTargetException
    //   494	3	6	localInvocationTargetException2	java.lang.reflect.InvocationTargetException
    //   502	3	6	localInvocationTargetException3	java.lang.reflect.InvocationTargetException
    //   510	3	6	localInvocationTargetException4	java.lang.reflect.InvocationTargetException
    //   518	3	6	localInvocationTargetException5	java.lang.reflect.InvocationTargetException
    //   526	3	6	localInvocationTargetException6	java.lang.reflect.InvocationTargetException
    //   534	3	6	localInvocationTargetException7	java.lang.reflect.InvocationTargetException
    //   78	345	7	localObject2	Object
    //   266	120	8	localObject3	Object
    // Exception table:
    //   from	to	target	type
    //   474	485	486	java/lang/reflect/InvocationTargetException
    //   326	338	494	java/lang/reflect/InvocationTargetException
    //   368	380	502	java/lang/reflect/InvocationTargetException
    //   268	280	510	java/lang/reflect/InvocationTargetException
    //   172	184	518	java/lang/reflect/InvocationTargetException
    //   80	92	526	java/lang/reflect/InvocationTargetException
    //   123	135	534	java/lang/reflect/InvocationTargetException
  }
  
  public static int b0077www00770077w0077ww()
  {
    return 2;
  }
  
  public static int bw0077ww00770077w0077ww()
  {
    return 1;
  }
  
  /* Error */
  private void bww0077w00770077w0077ww()
  {
    // Byte code:
    //   0: aload_0
    //   1: getfield 33	uuuuuu/gaaaaa:b007900790079yy007900790079y	Luuuuuu/gaaaga;
    //   4: invokevirtual 136	uuuuuu/gaaaga:b0077wwwwww0077ww	()Landroid/graphics/Bitmap;
    //   7: astore_3
    //   8: getstatic 35	uuuuuu/gaaaaa:byyy0079y007900790079y	I
    //   11: getstatic 37	uuuuuu/gaaaaa:b00790079y0079y007900790079y	I
    //   14: iadd
    //   15: getstatic 35	uuuuuu/gaaaaa:byyy0079y007900790079y	I
    //   18: imul
    //   19: getstatic 39	uuuuuu/gaaaaa:by0079y0079y007900790079y	I
    //   22: irem
    //   23: getstatic 41	uuuuuu/gaaaaa:b0079yy0079y007900790079y	I
    //   26: if_icmpeq +13 -> 39
    //   29: bipush 34
    //   31: putstatic 35	uuuuuu/gaaaaa:byyy0079y007900790079y	I
    //   34: bipush 85
    //   36: putstatic 41	uuuuuu/gaaaaa:b0079yy0079y007900790079y	I
    //   39: getstatic 35	uuuuuu/gaaaaa:byyy0079y007900790079y	I
    //   42: istore_1
    //   43: getstatic 37	uuuuuu/gaaaaa:b00790079y0079y007900790079y	I
    //   46: istore_2
    //   47: ldc 2
    //   49: ldc -118
    //   51: bipush 33
    //   53: iconst_3
    //   54: invokestatic 49	xxxxxx/uxxxxx:bb00620062bb0062b0062b0062	(Ljava/lang/String;CC)Ljava/lang/String;
    //   57: iconst_0
    //   58: anewarray 51	java/lang/Class
    //   61: invokevirtual 55	java/lang/Class:getMethod	(Ljava/lang/String;[Ljava/lang/Class;)Ljava/lang/reflect/Method;
    //   64: astore 4
    //   66: aload 4
    //   68: aconst_null
    //   69: iconst_0
    //   70: anewarray 57	java/lang/Object
    //   73: invokevirtual 63	java/lang/reflect/Method:invoke	(Ljava/lang/Object;[Ljava/lang/Object;)Ljava/lang/Object;
    //   76: astore 4
    //   78: iload_2
    //   79: iload_1
    //   80: iadd
    //   81: iload_1
    //   82: imul
    //   83: aload 4
    //   85: checkcast 65	java/lang/Integer
    //   88: invokevirtual 68	java/lang/Integer:intValue	()I
    //   91: irem
    //   92: tableswitch	default:+20->112, 0:+69->161
    //   112: bipush 7
    //   114: putstatic 35	uuuuuu/gaaaaa:byyy0079y007900790079y	I
    //   117: ldc 2
    //   119: ldc -116
    //   121: iconst_4
    //   122: sipush 207
    //   125: iconst_1
    //   126: invokestatic 76	xxxxxx/uxxxxx:bbbb0062b0062b0062b0062	(Ljava/lang/String;CCC)Ljava/lang/String;
    //   129: iconst_0
    //   130: anewarray 51	java/lang/Class
    //   133: invokevirtual 55	java/lang/Class:getMethod	(Ljava/lang/String;[Ljava/lang/Class;)Ljava/lang/reflect/Method;
    //   136: astore 4
    //   138: aload 4
    //   140: aconst_null
    //   141: iconst_0
    //   142: anewarray 57	java/lang/Object
    //   145: invokevirtual 63	java/lang/reflect/Method:invoke	(Ljava/lang/Object;[Ljava/lang/Object;)Ljava/lang/Object;
    //   148: astore 4
    //   150: aload 4
    //   152: checkcast 65	java/lang/Integer
    //   155: invokevirtual 68	java/lang/Integer:intValue	()I
    //   158: putstatic 41	uuuuuu/gaaaaa:b0079yy0079y007900790079y	I
    //   161: aload_3
    //   162: ifnull +29 -> 191
    //   165: aload_0
    //   166: getfield 98	uuuuuu/gaaaaa:bnnnnn006E006E006En	Luuuuuu/ttssst$tsssst;
    //   169: checkcast 100	uuuuuu/aagaaa$agaaaa
    //   172: aload_3
    //   173: invokeinterface 144 2 0
    //   178: getstatic 150	uuuuuu/vvrvrv:b0078x0078x0078xxxx	Luuuuuu/vvrvrv;
    //   181: invokestatic 156	uuuuuu/rrvvrv:b0071q0071qq0071q0071q0071	(Luuuuuu/vvrvrv;)V
    //   184: return
    //   185: astore_3
    //   186: aload_3
    //   187: invokevirtual 129	java/lang/reflect/InvocationTargetException:getCause	()Ljava/lang/Throwable;
    //   190: athrow
    //   191: getstatic 159	uuuuuu/vvrvrv:b0078xxx0078xxxx	Luuuuuu/vvrvrv;
    //   194: invokestatic 156	uuuuuu/rrvvrv:b0071q0071qq0071q0071q0071	(Luuuuuu/vvrvrv;)V
    //   197: getstatic 35	uuuuuu/gaaaaa:byyy0079y007900790079y	I
    //   200: istore_1
    //   201: ldc 2
    //   203: ldc -95
    //   205: bipush 90
    //   207: iconst_2
    //   208: invokestatic 49	xxxxxx/uxxxxx:bb00620062bb0062b0062b0062	(Ljava/lang/String;CC)Ljava/lang/String;
    //   211: iconst_0
    //   212: anewarray 51	java/lang/Class
    //   215: invokevirtual 55	java/lang/Class:getMethod	(Ljava/lang/String;[Ljava/lang/Class;)Ljava/lang/reflect/Method;
    //   218: astore_3
    //   219: aload_3
    //   220: aconst_null
    //   221: iconst_0
    //   222: anewarray 57	java/lang/Object
    //   225: invokevirtual 63	java/lang/reflect/Method:invoke	(Ljava/lang/Object;[Ljava/lang/Object;)Ljava/lang/Object;
    //   228: astore_3
    //   229: aload_3
    //   230: checkcast 65	java/lang/Integer
    //   233: invokevirtual 68	java/lang/Integer:intValue	()I
    //   236: iload_1
    //   237: iadd
    //   238: getstatic 35	uuuuuu/gaaaaa:byyy0079y007900790079y	I
    //   241: imul
    //   242: getstatic 39	uuuuuu/gaaaaa:by0079y0079y007900790079y	I
    //   245: irem
    //   246: getstatic 41	uuuuuu/gaaaaa:b0079yy0079y007900790079y	I
    //   249: if_icmpeq -65 -> 184
    //   252: getstatic 35	uuuuuu/gaaaaa:byyy0079y007900790079y	I
    //   255: getstatic 37	uuuuuu/gaaaaa:b00790079y0079y007900790079y	I
    //   258: iadd
    //   259: getstatic 35	uuuuuu/gaaaaa:byyy0079y007900790079y	I
    //   262: imul
    //   263: getstatic 39	uuuuuu/gaaaaa:by0079y0079y007900790079y	I
    //   266: irem
    //   267: getstatic 41	uuuuuu/gaaaaa:b0079yy0079y007900790079y	I
    //   270: if_icmpeq +13 -> 283
    //   273: bipush 13
    //   275: putstatic 35	uuuuuu/gaaaaa:byyy0079y007900790079y	I
    //   278: bipush 44
    //   280: putstatic 41	uuuuuu/gaaaaa:b0079yy0079y007900790079y	I
    //   283: bipush 59
    //   285: putstatic 35	uuuuuu/gaaaaa:byyy0079y007900790079y	I
    //   288: ldc 2
    //   290: ldc -93
    //   292: sipush 229
    //   295: iconst_4
    //   296: invokestatic 49	xxxxxx/uxxxxx:bb00620062bb0062b0062b0062	(Ljava/lang/String;CC)Ljava/lang/String;
    //   299: iconst_0
    //   300: anewarray 51	java/lang/Class
    //   303: invokevirtual 55	java/lang/Class:getMethod	(Ljava/lang/String;[Ljava/lang/Class;)Ljava/lang/reflect/Method;
    //   306: astore_3
    //   307: aload_3
    //   308: aconst_null
    //   309: iconst_0
    //   310: anewarray 57	java/lang/Object
    //   313: invokevirtual 63	java/lang/reflect/Method:invoke	(Ljava/lang/Object;[Ljava/lang/Object;)Ljava/lang/Object;
    //   316: astore_3
    //   317: aload_3
    //   318: checkcast 65	java/lang/Integer
    //   321: invokevirtual 68	java/lang/Integer:intValue	()I
    //   324: putstatic 41	uuuuuu/gaaaaa:b0079yy0079y007900790079y	I
    //   327: return
    //   328: astore_3
    //   329: aload_3
    //   330: invokevirtual 129	java/lang/reflect/InvocationTargetException:getCause	()Ljava/lang/Throwable;
    //   333: athrow
    //   334: astore_3
    //   335: aload_3
    //   336: invokevirtual 129	java/lang/reflect/InvocationTargetException:getCause	()Ljava/lang/Throwable;
    //   339: athrow
    //   340: astore_3
    //   341: aload_3
    //   342: invokevirtual 129	java/lang/reflect/InvocationTargetException:getCause	()Ljava/lang/Throwable;
    //   345: athrow
    // Local variable table:
    //   start	length	slot	name	signature
    //   0	346	0	this	gaaaaa
    //   42	196	1	i	int
    //   46	35	2	j	int
    //   7	166	3	localBitmap	android.graphics.Bitmap
    //   185	2	3	localInvocationTargetException1	java.lang.reflect.InvocationTargetException
    //   218	100	3	localObject1	Object
    //   328	2	3	localInvocationTargetException2	java.lang.reflect.InvocationTargetException
    //   334	2	3	localInvocationTargetException3	java.lang.reflect.InvocationTargetException
    //   340	2	3	localInvocationTargetException4	java.lang.reflect.InvocationTargetException
    //   64	87	4	localObject2	Object
    // Exception table:
    //   from	to	target	type
    //   66	78	185	java/lang/reflect/InvocationTargetException
    //   307	317	328	java/lang/reflect/InvocationTargetException
    //   138	150	334	java/lang/reflect/InvocationTargetException
    //   219	229	340	java/lang/reflect/InvocationTargetException
  }
  
  public static int bwwww00770077w0077ww()
  {
    return 81;
  }
  
  public void b00770077w0077w0077w0077ww()
  {
    throw new Runtime("d2j fail translate: java.lang.IndexOutOfBoundsException: fromIndex < 0: -1\n\tat java.util.BitSet.nextSetBit(BitSet.java:712)\n\tat com.googlecode.dex2jar.ir.ts.array.FillArrayTransformer.makeSureAllElementAreAssigned(FillArrayTransformer.java:505)\n\tat com.googlecode.dex2jar.ir.ts.array.FillArrayTransformer.transformReportChanged(FillArrayTransformer.java:123)\n\tat com.googlecode.dex2jar.ir.ts.StatedTransformer.transform(StatedTransformer.java:10)\n\tat com.googlecode.d2j.dex.Dex2jar$2.optimize(Dex2jar.java:149)\n\tat com.googlecode.d2j.dex.Dex2Asm.convertCode(Dex2Asm.java:414)\n\tat com.googlecode.d2j.dex.ExDex2Asm.convertCode(ExDex2Asm.java:42)\n\tat com.googlecode.d2j.dex.Dex2jar$2.convertCode(Dex2jar.java:128)\n\tat com.googlecode.d2j.dex.Dex2Asm.convertMethod(Dex2Asm.java:509)\n\tat com.googlecode.d2j.dex.Dex2Asm.convertClass(Dex2Asm.java:406)\n\tat com.googlecode.d2j.dex.Dex2Asm.convertDex(Dex2Asm.java:422)\n\tat com.googlecode.d2j.dex.Dex2jar.doTranslate(Dex2jar.java:172)\n\tat com.googlecode.d2j.dex.Dex2jar.to(Dex2jar.java:272)\n\tat com.googlecode.dex2jar.tools.Dex2jarCmd.doCommandLine(Dex2jarCmd.java:108)\n\tat com.googlecode.dex2jar.tools.BaseCmd.doMain(BaseCmd.java:288)\n\tat com.googlecode.dex2jar.tools.Dex2jarCmd.main(Dex2jarCmd.java:32)\n");
  }
  
  /* Error */
  public void b00770077ww00770077w0077ww(aagaaa.agaaaa paramAgaaaa)
  {
    // Byte code:
    //   0: getstatic 35	uuuuuu/gaaaaa:byyy0079y007900790079y	I
    //   3: getstatic 37	uuuuuu/gaaaaa:b00790079y0079y007900790079y	I
    //   6: iadd
    //   7: getstatic 35	uuuuuu/gaaaaa:byyy0079y007900790079y	I
    //   10: imul
    //   11: getstatic 39	uuuuuu/gaaaaa:by0079y0079y007900790079y	I
    //   14: irem
    //   15: getstatic 41	uuuuuu/gaaaaa:b0079yy0079y007900790079y	I
    //   18: if_icmpeq +91 -> 109
    //   21: ldc 2
    //   23: ldc -78
    //   25: sipush 215
    //   28: iconst_5
    //   29: invokestatic 49	xxxxxx/uxxxxx:bb00620062bb0062b0062b0062	(Ljava/lang/String;CC)Ljava/lang/String;
    //   32: iconst_0
    //   33: anewarray 51	java/lang/Class
    //   36: invokevirtual 55	java/lang/Class:getMethod	(Ljava/lang/String;[Ljava/lang/Class;)Ljava/lang/reflect/Method;
    //   39: astore 7
    //   41: aload 7
    //   43: aconst_null
    //   44: iconst_0
    //   45: anewarray 57	java/lang/Object
    //   48: invokevirtual 63	java/lang/reflect/Method:invoke	(Ljava/lang/Object;[Ljava/lang/Object;)Ljava/lang/Object;
    //   51: astore 7
    //   53: aload 7
    //   55: checkcast 65	java/lang/Integer
    //   58: invokevirtual 68	java/lang/Integer:intValue	()I
    //   61: putstatic 35	uuuuuu/gaaaaa:byyy0079y007900790079y	I
    //   64: ldc 2
    //   66: ldc -76
    //   68: sipush 232
    //   71: bipush 23
    //   73: iconst_3
    //   74: invokestatic 76	xxxxxx/uxxxxx:bbbb0062b0062b0062b0062	(Ljava/lang/String;CCC)Ljava/lang/String;
    //   77: iconst_0
    //   78: anewarray 51	java/lang/Class
    //   81: invokevirtual 55	java/lang/Class:getMethod	(Ljava/lang/String;[Ljava/lang/Class;)Ljava/lang/reflect/Method;
    //   84: astore 7
    //   86: aload 7
    //   88: aconst_null
    //   89: iconst_0
    //   90: anewarray 57	java/lang/Object
    //   93: invokevirtual 63	java/lang/reflect/Method:invoke	(Ljava/lang/Object;[Ljava/lang/Object;)Ljava/lang/Object;
    //   96: astore 7
    //   98: aload 7
    //   100: checkcast 65	java/lang/Integer
    //   103: invokevirtual 68	java/lang/Integer:intValue	()I
    //   106: putstatic 41	uuuuuu/gaaaaa:b0079yy0079y007900790079y	I
    //   109: getstatic 35	uuuuuu/gaaaaa:byyy0079y007900790079y	I
    //   112: istore_2
    //   113: getstatic 37	uuuuuu/gaaaaa:b00790079y0079y007900790079y	I
    //   116: istore_3
    //   117: getstatic 35	uuuuuu/gaaaaa:byyy0079y007900790079y	I
    //   120: istore 4
    //   122: ldc 2
    //   124: ldc -74
    //   126: sipush 221
    //   129: iconst_5
    //   130: invokestatic 49	xxxxxx/uxxxxx:bb00620062bb0062b0062b0062	(Ljava/lang/String;CC)Ljava/lang/String;
    //   133: iconst_0
    //   134: anewarray 51	java/lang/Class
    //   137: invokevirtual 55	java/lang/Class:getMethod	(Ljava/lang/String;[Ljava/lang/Class;)Ljava/lang/reflect/Method;
    //   140: astore 7
    //   142: aload 7
    //   144: aconst_null
    //   145: iconst_0
    //   146: anewarray 57	java/lang/Object
    //   149: invokevirtual 63	java/lang/reflect/Method:invoke	(Ljava/lang/Object;[Ljava/lang/Object;)Ljava/lang/Object;
    //   152: astore 7
    //   154: aload 7
    //   156: checkcast 65	java/lang/Integer
    //   159: invokevirtual 68	java/lang/Integer:intValue	()I
    //   162: istore 5
    //   164: getstatic 35	uuuuuu/gaaaaa:byyy0079y007900790079y	I
    //   167: istore 6
    //   169: iload 6
    //   171: getstatic 37	uuuuuu/gaaaaa:b00790079y0079y007900790079y	I
    //   174: iload 6
    //   176: iadd
    //   177: imul
    //   178: getstatic 39	uuuuuu/gaaaaa:by0079y0079y007900790079y	I
    //   181: irem
    //   182: tableswitch	default:+18->200, 0:+28->210
    //   200: bipush 80
    //   202: putstatic 35	uuuuuu/gaaaaa:byyy0079y007900790079y	I
    //   205: bipush 62
    //   207: putstatic 41	uuuuuu/gaaaaa:b0079yy0079y007900790079y	I
    //   210: iload 5
    //   212: getstatic 37	uuuuuu/gaaaaa:b00790079y0079y007900790079y	I
    //   215: iload 5
    //   217: iadd
    //   218: imul
    //   219: getstatic 39	uuuuuu/gaaaaa:by0079y0079y007900790079y	I
    //   222: irem
    //   223: tableswitch	default:+17->240, 0:+64->287
    //   240: bipush 35
    //   242: putstatic 35	uuuuuu/gaaaaa:byyy0079y007900790079y	I
    //   245: ldc 2
    //   247: ldc -72
    //   249: bipush 93
    //   251: iconst_2
    //   252: invokestatic 49	xxxxxx/uxxxxx:bb00620062bb0062b0062b0062	(Ljava/lang/String;CC)Ljava/lang/String;
    //   255: iconst_0
    //   256: anewarray 51	java/lang/Class
    //   259: invokevirtual 55	java/lang/Class:getMethod	(Ljava/lang/String;[Ljava/lang/Class;)Ljava/lang/reflect/Method;
    //   262: astore 7
    //   264: aload 7
    //   266: aconst_null
    //   267: iconst_0
    //   268: anewarray 57	java/lang/Object
    //   271: invokevirtual 63	java/lang/reflect/Method:invoke	(Ljava/lang/Object;[Ljava/lang/Object;)Ljava/lang/Object;
    //   274: astore 7
    //   276: aload 7
    //   278: checkcast 65	java/lang/Integer
    //   281: invokevirtual 68	java/lang/Integer:intValue	()I
    //   284: putstatic 41	uuuuuu/gaaaaa:b0079yy0079y007900790079y	I
    //   287: iload_3
    //   288: iload_2
    //   289: iadd
    //   290: iload 4
    //   292: imul
    //   293: getstatic 39	uuuuuu/gaaaaa:by0079y0079y007900790079y	I
    //   296: irem
    //   297: getstatic 41	uuuuuu/gaaaaa:b0079yy0079y007900790079y	I
    //   300: if_icmpeq +50 -> 350
    //   303: ldc 2
    //   305: ldc -70
    //   307: bipush 78
    //   309: iconst_2
    //   310: invokestatic 49	xxxxxx/uxxxxx:bb00620062bb0062b0062b0062	(Ljava/lang/String;CC)Ljava/lang/String;
    //   313: iconst_0
    //   314: anewarray 51	java/lang/Class
    //   317: invokevirtual 55	java/lang/Class:getMethod	(Ljava/lang/String;[Ljava/lang/Class;)Ljava/lang/reflect/Method;
    //   320: astore 7
    //   322: aload 7
    //   324: aconst_null
    //   325: iconst_0
    //   326: anewarray 57	java/lang/Object
    //   329: invokevirtual 63	java/lang/reflect/Method:invoke	(Ljava/lang/Object;[Ljava/lang/Object;)Ljava/lang/Object;
    //   332: astore 7
    //   334: aload 7
    //   336: checkcast 65	java/lang/Integer
    //   339: invokevirtual 68	java/lang/Integer:intValue	()I
    //   342: putstatic 35	uuuuuu/gaaaaa:byyy0079y007900790079y	I
    //   345: bipush 18
    //   347: putstatic 41	uuuuuu/gaaaaa:b0079yy0079y007900790079y	I
    //   350: aload_0
    //   351: aload_1
    //   352: invokespecial 190	uuuuuu/ssssst:ba0061a0061a0061a0061aa	(Luuuuuu/ttssst$tsssst;)V
    //   355: ldc 2
    //   357: ldc -64
    //   359: bipush 63
    //   361: iconst_3
    //   362: invokestatic 49	xxxxxx/uxxxxx:bb00620062bb0062b0062b0062	(Ljava/lang/String;CC)Ljava/lang/String;
    //   365: iconst_0
    //   366: anewarray 51	java/lang/Class
    //   369: invokevirtual 125	java/lang/Class:getDeclaredMethod	(Ljava/lang/String;[Ljava/lang/Class;)Ljava/lang/reflect/Method;
    //   372: astore_1
    //   373: aload_1
    //   374: aload_0
    //   375: iconst_0
    //   376: anewarray 57	java/lang/Object
    //   379: invokevirtual 63	java/lang/reflect/Method:invoke	(Ljava/lang/Object;[Ljava/lang/Object;)Ljava/lang/Object;
    //   382: pop
    //   383: return
    //   384: astore_1
    //   385: aload_1
    //   386: invokevirtual 129	java/lang/reflect/InvocationTargetException:getCause	()Ljava/lang/Throwable;
    //   389: athrow
    //   390: astore_1
    //   391: aload_1
    //   392: invokevirtual 129	java/lang/reflect/InvocationTargetException:getCause	()Ljava/lang/Throwable;
    //   395: athrow
    //   396: astore_1
    //   397: aload_1
    //   398: invokevirtual 129	java/lang/reflect/InvocationTargetException:getCause	()Ljava/lang/Throwable;
    //   401: athrow
    //   402: astore_1
    //   403: aload_1
    //   404: invokevirtual 129	java/lang/reflect/InvocationTargetException:getCause	()Ljava/lang/Throwable;
    //   407: athrow
    //   408: astore_1
    //   409: aload_1
    //   410: invokevirtual 129	java/lang/reflect/InvocationTargetException:getCause	()Ljava/lang/Throwable;
    //   413: athrow
    //   414: astore_1
    //   415: aload_1
    //   416: invokevirtual 129	java/lang/reflect/InvocationTargetException:getCause	()Ljava/lang/Throwable;
    //   419: athrow
    // Local variable table:
    //   start	length	slot	name	signature
    //   0	420	0	this	gaaaaa
    //   0	420	1	paramAgaaaa	aagaaa.agaaaa
    //   112	178	2	i	int
    //   116	174	3	j	int
    //   120	173	4	k	int
    //   162	57	5	m	int
    //   167	11	6	n	int
    //   39	296	7	localObject	Object
    // Exception table:
    //   from	to	target	type
    //   142	154	384	java/lang/reflect/InvocationTargetException
    //   322	334	390	java/lang/reflect/InvocationTargetException
    //   373	383	396	java/lang/reflect/InvocationTargetException
    //   264	276	402	java/lang/reflect/InvocationTargetException
    //   41	53	408	java/lang/reflect/InvocationTargetException
    //   86	98	414	java/lang/reflect/InvocationTargetException
  }
  
  /* Error */
  public void b0077w00770077w0077w0077ww(@android.support.annotation.NonNull android.content.Context paramContext)
  {
    // Byte code:
    //   0: getstatic 35	uuuuuu/gaaaaa:byyy0079y007900790079y	I
    //   3: getstatic 37	uuuuuu/gaaaaa:b00790079y0079y007900790079y	I
    //   6: iadd
    //   7: getstatic 35	uuuuuu/gaaaaa:byyy0079y007900790079y	I
    //   10: imul
    //   11: getstatic 39	uuuuuu/gaaaaa:by0079y0079y007900790079y	I
    //   14: irem
    //   15: getstatic 41	uuuuuu/gaaaaa:b0079yy0079y007900790079y	I
    //   18: if_icmpeq +244 -> 262
    //   21: bipush 44
    //   23: putstatic 35	uuuuuu/gaaaaa:byyy0079y007900790079y	I
    //   26: ldc 2
    //   28: ldc -59
    //   30: sipush 244
    //   33: bipush 78
    //   35: iconst_2
    //   36: invokestatic 76	xxxxxx/uxxxxx:bbbb0062b0062b0062b0062	(Ljava/lang/String;CCC)Ljava/lang/String;
    //   39: iconst_0
    //   40: anewarray 51	java/lang/Class
    //   43: invokevirtual 55	java/lang/Class:getMethod	(Ljava/lang/String;[Ljava/lang/Class;)Ljava/lang/reflect/Method;
    //   46: astore 4
    //   48: aload 4
    //   50: aconst_null
    //   51: iconst_0
    //   52: anewarray 57	java/lang/Object
    //   55: invokevirtual 63	java/lang/reflect/Method:invoke	(Ljava/lang/Object;[Ljava/lang/Object;)Ljava/lang/Object;
    //   58: astore 4
    //   60: aload 4
    //   62: checkcast 65	java/lang/Integer
    //   65: invokevirtual 68	java/lang/Integer:intValue	()I
    //   68: putstatic 41	uuuuuu/gaaaaa:b0079yy0079y007900790079y	I
    //   71: ldc 2
    //   73: ldc -57
    //   75: bipush 35
    //   77: iconst_5
    //   78: invokestatic 49	xxxxxx/uxxxxx:bb00620062bb0062b0062b0062	(Ljava/lang/String;CC)Ljava/lang/String;
    //   81: iconst_0
    //   82: anewarray 51	java/lang/Class
    //   85: invokevirtual 55	java/lang/Class:getMethod	(Ljava/lang/String;[Ljava/lang/Class;)Ljava/lang/reflect/Method;
    //   88: astore 4
    //   90: aload 4
    //   92: aconst_null
    //   93: iconst_0
    //   94: anewarray 57	java/lang/Object
    //   97: invokevirtual 63	java/lang/reflect/Method:invoke	(Ljava/lang/Object;[Ljava/lang/Object;)Ljava/lang/Object;
    //   100: astore 4
    //   102: aload 4
    //   104: checkcast 65	java/lang/Integer
    //   107: invokevirtual 68	java/lang/Integer:intValue	()I
    //   110: istore_2
    //   111: getstatic 37	uuuuuu/gaaaaa:b00790079y0079y007900790079y	I
    //   114: istore_3
    //   115: ldc 2
    //   117: ldc -55
    //   119: sipush 178
    //   122: sipush 212
    //   125: iconst_3
    //   126: invokestatic 76	xxxxxx/uxxxxx:bbbb0062b0062b0062b0062	(Ljava/lang/String;CCC)Ljava/lang/String;
    //   129: iconst_0
    //   130: anewarray 51	java/lang/Class
    //   133: invokevirtual 55	java/lang/Class:getMethod	(Ljava/lang/String;[Ljava/lang/Class;)Ljava/lang/reflect/Method;
    //   136: astore 4
    //   138: aload 4
    //   140: aconst_null
    //   141: iconst_0
    //   142: anewarray 57	java/lang/Object
    //   145: invokevirtual 63	java/lang/reflect/Method:invoke	(Ljava/lang/Object;[Ljava/lang/Object;)Ljava/lang/Object;
    //   148: astore 4
    //   150: aload 4
    //   152: checkcast 65	java/lang/Integer
    //   155: invokevirtual 68	java/lang/Integer:intValue	()I
    //   158: iload_3
    //   159: iload_2
    //   160: iadd
    //   161: imul
    //   162: getstatic 39	uuuuuu/gaaaaa:by0079y0079y007900790079y	I
    //   165: irem
    //   166: getstatic 41	uuuuuu/gaaaaa:b0079yy0079y007900790079y	I
    //   169: if_icmpeq +93 -> 262
    //   172: ldc 2
    //   174: ldc -55
    //   176: bipush 126
    //   178: bipush 117
    //   180: iconst_2
    //   181: invokestatic 76	xxxxxx/uxxxxx:bbbb0062b0062b0062b0062	(Ljava/lang/String;CCC)Ljava/lang/String;
    //   184: iconst_0
    //   185: anewarray 51	java/lang/Class
    //   188: invokevirtual 55	java/lang/Class:getMethod	(Ljava/lang/String;[Ljava/lang/Class;)Ljava/lang/reflect/Method;
    //   191: astore 4
    //   193: aload 4
    //   195: aconst_null
    //   196: iconst_0
    //   197: anewarray 57	java/lang/Object
    //   200: invokevirtual 63	java/lang/reflect/Method:invoke	(Ljava/lang/Object;[Ljava/lang/Object;)Ljava/lang/Object;
    //   203: astore 4
    //   205: aload 4
    //   207: checkcast 65	java/lang/Integer
    //   210: invokevirtual 68	java/lang/Integer:intValue	()I
    //   213: putstatic 35	uuuuuu/gaaaaa:byyy0079y007900790079y	I
    //   216: ldc 2
    //   218: ldc -53
    //   220: sipush 153
    //   223: sipush 226
    //   226: iconst_2
    //   227: invokestatic 76	xxxxxx/uxxxxx:bbbb0062b0062b0062b0062	(Ljava/lang/String;CCC)Ljava/lang/String;
    //   230: iconst_0
    //   231: anewarray 51	java/lang/Class
    //   234: invokevirtual 55	java/lang/Class:getMethod	(Ljava/lang/String;[Ljava/lang/Class;)Ljava/lang/reflect/Method;
    //   237: astore 4
    //   239: aload 4
    //   241: aconst_null
    //   242: iconst_0
    //   243: anewarray 57	java/lang/Object
    //   246: invokevirtual 63	java/lang/reflect/Method:invoke	(Ljava/lang/Object;[Ljava/lang/Object;)Ljava/lang/Object;
    //   249: astore 4
    //   251: aload 4
    //   253: checkcast 65	java/lang/Integer
    //   256: invokevirtual 68	java/lang/Integer:intValue	()I
    //   259: putstatic 41	uuuuuu/gaaaaa:b0079yy0079y007900790079y	I
    //   262: getstatic 35	uuuuuu/gaaaaa:byyy0079y007900790079y	I
    //   265: istore_2
    //   266: ldc 2
    //   268: ldc -51
    //   270: bipush 6
    //   272: bipush 95
    //   274: iconst_0
    //   275: invokestatic 76	xxxxxx/uxxxxx:bbbb0062b0062b0062b0062	(Ljava/lang/String;CCC)Ljava/lang/String;
    //   278: iconst_0
    //   279: anewarray 51	java/lang/Class
    //   282: invokevirtual 55	java/lang/Class:getMethod	(Ljava/lang/String;[Ljava/lang/Class;)Ljava/lang/reflect/Method;
    //   285: astore 4
    //   287: aload 4
    //   289: aconst_null
    //   290: iconst_0
    //   291: anewarray 57	java/lang/Object
    //   294: invokevirtual 63	java/lang/reflect/Method:invoke	(Ljava/lang/Object;[Ljava/lang/Object;)Ljava/lang/Object;
    //   297: astore 4
    //   299: aload 4
    //   301: checkcast 65	java/lang/Integer
    //   304: invokevirtual 68	java/lang/Integer:intValue	()I
    //   307: iload_2
    //   308: iadd
    //   309: iload_2
    //   310: imul
    //   311: getstatic 39	uuuuuu/gaaaaa:by0079y0079y007900790079y	I
    //   314: irem
    //   315: tableswitch	default:+17->332, 0:+113->428
    //   332: getstatic 35	uuuuuu/gaaaaa:byyy0079y007900790079y	I
    //   335: istore_2
    //   336: getstatic 37	uuuuuu/gaaaaa:b00790079y0079y007900790079y	I
    //   339: istore_3
    //   340: ldc 2
    //   342: ldc -49
    //   344: sipush 136
    //   347: sipush 205
    //   350: iconst_0
    //   351: invokestatic 76	xxxxxx/uxxxxx:bbbb0062b0062b0062b0062	(Ljava/lang/String;CCC)Ljava/lang/String;
    //   354: iconst_0
    //   355: anewarray 51	java/lang/Class
    //   358: invokevirtual 55	java/lang/Class:getMethod	(Ljava/lang/String;[Ljava/lang/Class;)Ljava/lang/reflect/Method;
    //   361: astore 4
    //   363: aload 4
    //   365: aconst_null
    //   366: iconst_0
    //   367: anewarray 57	java/lang/Object
    //   370: invokevirtual 63	java/lang/reflect/Method:invoke	(Ljava/lang/Object;[Ljava/lang/Object;)Ljava/lang/Object;
    //   373: astore 4
    //   375: iload_3
    //   376: iload_2
    //   377: iadd
    //   378: iload_2
    //   379: imul
    //   380: aload 4
    //   382: checkcast 65	java/lang/Integer
    //   385: invokevirtual 68	java/lang/Integer:intValue	()I
    //   388: irem
    //   389: tableswitch	default:+19->408, 0:+29->418
    //   408: bipush 64
    //   410: putstatic 35	uuuuuu/gaaaaa:byyy0079y007900790079y	I
    //   413: bipush 8
    //   415: putstatic 41	uuuuuu/gaaaaa:b0079yy0079y007900790079y	I
    //   418: bipush 23
    //   420: putstatic 35	uuuuuu/gaaaaa:byyy0079y007900790079y	I
    //   423: bipush 49
    //   425: putstatic 41	uuuuuu/gaaaaa:b0079yy0079y007900790079y	I
    //   428: aload_1
    //   429: invokestatic 213	uuuuuu/gaagga:b007700770077www0077www	(Landroid/content/Context;)Luuuuuu/aaagga;
    //   432: aload_0
    //   433: invokeinterface 219 2 0
    //   438: return
    //   439: astore_1
    //   440: aload_1
    //   441: invokevirtual 129	java/lang/reflect/InvocationTargetException:getCause	()Ljava/lang/Throwable;
    //   444: athrow
    //   445: astore_1
    //   446: aload_1
    //   447: invokevirtual 129	java/lang/reflect/InvocationTargetException:getCause	()Ljava/lang/Throwable;
    //   450: athrow
    //   451: astore_1
    //   452: aload_1
    //   453: invokevirtual 129	java/lang/reflect/InvocationTargetException:getCause	()Ljava/lang/Throwable;
    //   456: athrow
    //   457: astore_1
    //   458: aload_1
    //   459: invokevirtual 129	java/lang/reflect/InvocationTargetException:getCause	()Ljava/lang/Throwable;
    //   462: athrow
    //   463: astore_1
    //   464: aload_1
    //   465: invokevirtual 129	java/lang/reflect/InvocationTargetException:getCause	()Ljava/lang/Throwable;
    //   468: athrow
    //   469: astore_1
    //   470: aload_1
    //   471: invokevirtual 129	java/lang/reflect/InvocationTargetException:getCause	()Ljava/lang/Throwable;
    //   474: athrow
    //   475: astore_1
    //   476: aload_1
    //   477: invokevirtual 129	java/lang/reflect/InvocationTargetException:getCause	()Ljava/lang/Throwable;
    //   480: athrow
    // Local variable table:
    //   start	length	slot	name	signature
    //   0	481	0	this	gaaaaa
    //   0	481	1	paramContext	android.content.Context
    //   110	270	2	i	int
    //   114	264	3	j	int
    //   46	335	4	localObject	Object
    // Exception table:
    //   from	to	target	type
    //   48	60	439	java/lang/reflect/InvocationTargetException
    //   90	102	445	java/lang/reflect/InvocationTargetException
    //   138	150	451	java/lang/reflect/InvocationTargetException
    //   193	205	457	java/lang/reflect/InvocationTargetException
    //   363	375	463	java/lang/reflect/InvocationTargetException
    //   287	299	469	java/lang/reflect/InvocationTargetException
    //   239	251	475	java/lang/reflect/InvocationTargetException
  }
  
  /* Error */
  public void bw007700770077w0077w0077ww(android.content.Context paramContext)
  {
    // Byte code:
    //   0: aload_0
    //   1: getfield 33	uuuuuu/gaaaaa:b007900790079yy007900790079y	Luuuuuu/gaaaga;
    //   4: invokevirtual 224	uuuuuu/gaaaga:bw0077wwwww0077ww	()Ljava/lang/String;
    //   7: astore 6
    //   9: ldc 2
    //   11: ldc -30
    //   13: bipush 110
    //   15: iconst_5
    //   16: invokestatic 49	xxxxxx/uxxxxx:bb00620062bb0062b0062b0062	(Ljava/lang/String;CC)Ljava/lang/String;
    //   19: iconst_0
    //   20: anewarray 51	java/lang/Class
    //   23: invokevirtual 55	java/lang/Class:getMethod	(Ljava/lang/String;[Ljava/lang/Class;)Ljava/lang/reflect/Method;
    //   26: astore 7
    //   28: aload 7
    //   30: aconst_null
    //   31: iconst_0
    //   32: anewarray 57	java/lang/Object
    //   35: invokevirtual 63	java/lang/reflect/Method:invoke	(Ljava/lang/Object;[Ljava/lang/Object;)Ljava/lang/Object;
    //   38: astore 7
    //   40: aload 7
    //   42: checkcast 65	java/lang/Integer
    //   45: invokevirtual 68	java/lang/Integer:intValue	()I
    //   48: istore_2
    //   49: getstatic 37	uuuuuu/gaaaaa:b00790079y0079y007900790079y	I
    //   52: istore_3
    //   53: ldc 2
    //   55: ldc -28
    //   57: bipush 22
    //   59: iconst_4
    //   60: invokestatic 49	xxxxxx/uxxxxx:bb00620062bb0062b0062b0062	(Ljava/lang/String;CC)Ljava/lang/String;
    //   63: iconst_0
    //   64: anewarray 51	java/lang/Class
    //   67: invokevirtual 55	java/lang/Class:getMethod	(Ljava/lang/String;[Ljava/lang/Class;)Ljava/lang/reflect/Method;
    //   70: astore 7
    //   72: aload 7
    //   74: aconst_null
    //   75: iconst_0
    //   76: anewarray 57	java/lang/Object
    //   79: invokevirtual 63	java/lang/reflect/Method:invoke	(Ljava/lang/Object;[Ljava/lang/Object;)Ljava/lang/Object;
    //   82: astore 7
    //   84: aload 7
    //   86: checkcast 65	java/lang/Integer
    //   89: invokevirtual 68	java/lang/Integer:intValue	()I
    //   92: iload_3
    //   93: iload_2
    //   94: iadd
    //   95: imul
    //   96: getstatic 39	uuuuuu/gaaaaa:by0079y0079y007900790079y	I
    //   99: irem
    //   100: getstatic 41	uuuuuu/gaaaaa:b0079yy0079y007900790079y	I
    //   103: if_icmpeq +53 -> 156
    //   106: bipush 82
    //   108: putstatic 35	uuuuuu/gaaaaa:byyy0079y007900790079y	I
    //   111: ldc 2
    //   113: ldc -26
    //   115: sipush 201
    //   118: bipush 86
    //   120: iconst_1
    //   121: invokestatic 76	xxxxxx/uxxxxx:bbbb0062b0062b0062b0062	(Ljava/lang/String;CCC)Ljava/lang/String;
    //   124: iconst_0
    //   125: anewarray 51	java/lang/Class
    //   128: invokevirtual 55	java/lang/Class:getMethod	(Ljava/lang/String;[Ljava/lang/Class;)Ljava/lang/reflect/Method;
    //   131: astore 7
    //   133: aload 7
    //   135: aconst_null
    //   136: iconst_0
    //   137: anewarray 57	java/lang/Object
    //   140: invokevirtual 63	java/lang/reflect/Method:invoke	(Ljava/lang/Object;[Ljava/lang/Object;)Ljava/lang/Object;
    //   143: astore 7
    //   145: aload 7
    //   147: checkcast 65	java/lang/Integer
    //   150: invokevirtual 68	java/lang/Integer:intValue	()I
    //   153: putstatic 41	uuuuuu/gaaaaa:b0079yy0079y007900790079y	I
    //   156: aload 6
    //   158: invokestatic 236	uuuuuu/sxsxsx:b006Bkkkk006Bk006B006B006B	(Ljava/lang/String;)Z
    //   161: ifne +323 -> 484
    //   164: aload_0
    //   165: getfield 238	uuuuuu/gaaaaa:by00790079yy007900790079y	Luuuuuu/xxsxxs;
    //   168: astore 7
    //   170: getstatic 35	uuuuuu/gaaaaa:byyy0079y007900790079y	I
    //   173: istore_2
    //   174: getstatic 37	uuuuuu/gaaaaa:b00790079y0079y007900790079y	I
    //   177: istore_3
    //   178: getstatic 35	uuuuuu/gaaaaa:byyy0079y007900790079y	I
    //   181: istore 4
    //   183: getstatic 35	uuuuuu/gaaaaa:byyy0079y007900790079y	I
    //   186: istore 5
    //   188: iload 5
    //   190: getstatic 37	uuuuuu/gaaaaa:b00790079y0079y007900790079y	I
    //   193: iload 5
    //   195: iadd
    //   196: imul
    //   197: getstatic 39	uuuuuu/gaaaaa:by0079y0079y007900790079y	I
    //   200: irem
    //   201: tableswitch	default:+19->220, 0:+66->267
    //   220: bipush 8
    //   222: putstatic 35	uuuuuu/gaaaaa:byyy0079y007900790079y	I
    //   225: ldc 2
    //   227: ldc -16
    //   229: bipush 99
    //   231: iconst_0
    //   232: invokestatic 49	xxxxxx/uxxxxx:bb00620062bb0062b0062b0062	(Ljava/lang/String;CC)Ljava/lang/String;
    //   235: iconst_0
    //   236: anewarray 51	java/lang/Class
    //   239: invokevirtual 55	java/lang/Class:getMethod	(Ljava/lang/String;[Ljava/lang/Class;)Ljava/lang/reflect/Method;
    //   242: astore 8
    //   244: aload 8
    //   246: aconst_null
    //   247: iconst_0
    //   248: anewarray 57	java/lang/Object
    //   251: invokevirtual 63	java/lang/reflect/Method:invoke	(Ljava/lang/Object;[Ljava/lang/Object;)Ljava/lang/Object;
    //   254: astore 8
    //   256: aload 8
    //   258: checkcast 65	java/lang/Integer
    //   261: invokevirtual 68	java/lang/Integer:intValue	()I
    //   264: putstatic 41	uuuuuu/gaaaaa:b0079yy0079y007900790079y	I
    //   267: ldc 2
    //   269: ldc -14
    //   271: sipush 229
    //   274: iconst_3
    //   275: invokestatic 49	xxxxxx/uxxxxx:bb00620062bb0062b0062b0062	(Ljava/lang/String;CC)Ljava/lang/String;
    //   278: iconst_0
    //   279: anewarray 51	java/lang/Class
    //   282: invokevirtual 55	java/lang/Class:getMethod	(Ljava/lang/String;[Ljava/lang/Class;)Ljava/lang/reflect/Method;
    //   285: astore 8
    //   287: aload 8
    //   289: aconst_null
    //   290: iconst_0
    //   291: anewarray 57	java/lang/Object
    //   294: invokevirtual 63	java/lang/reflect/Method:invoke	(Ljava/lang/Object;[Ljava/lang/Object;)Ljava/lang/Object;
    //   297: astore 8
    //   299: iload 4
    //   301: iload_2
    //   302: iload_3
    //   303: iadd
    //   304: imul
    //   305: aload 8
    //   307: checkcast 65	java/lang/Integer
    //   310: invokevirtual 68	java/lang/Integer:intValue	()I
    //   313: irem
    //   314: getstatic 41	uuuuuu/gaaaaa:b0079yy0079y007900790079y	I
    //   317: if_icmpeq +13 -> 330
    //   320: bipush 62
    //   322: putstatic 35	uuuuuu/gaaaaa:byyy0079y007900790079y	I
    //   325: bipush 59
    //   327: putstatic 41	uuuuuu/gaaaaa:b0079yy0079y007900790079y	I
    //   330: aload 7
    //   332: aload 6
    //   334: aload_1
    //   335: iconst_1
    //   336: invokevirtual 248	uuuuuu/xxsxxs:b006Bkkk006Bk006Bk006B006B	(Ljava/lang/String;Landroid/content/Context;Z)V
    //   339: ldc 2
    //   341: ldc -6
    //   343: sipush 244
    //   346: bipush 40
    //   348: iconst_0
    //   349: invokestatic 76	xxxxxx/uxxxxx:bbbb0062b0062b0062b0062	(Ljava/lang/String;CCC)Ljava/lang/String;
    //   352: iconst_0
    //   353: anewarray 51	java/lang/Class
    //   356: invokevirtual 55	java/lang/Class:getMethod	(Ljava/lang/String;[Ljava/lang/Class;)Ljava/lang/reflect/Method;
    //   359: astore_1
    //   360: aload_1
    //   361: aconst_null
    //   362: iconst_0
    //   363: anewarray 57	java/lang/Object
    //   366: invokevirtual 63	java/lang/reflect/Method:invoke	(Ljava/lang/Object;[Ljava/lang/Object;)Ljava/lang/Object;
    //   369: astore_1
    //   370: aload_1
    //   371: checkcast 65	java/lang/Integer
    //   374: invokevirtual 68	java/lang/Integer:intValue	()I
    //   377: istore_2
    //   378: ldc 2
    //   380: ldc -4
    //   382: sipush 247
    //   385: iconst_2
    //   386: invokestatic 49	xxxxxx/uxxxxx:bb00620062bb0062b0062b0062	(Ljava/lang/String;CC)Ljava/lang/String;
    //   389: iconst_0
    //   390: anewarray 51	java/lang/Class
    //   393: invokevirtual 55	java/lang/Class:getMethod	(Ljava/lang/String;[Ljava/lang/Class;)Ljava/lang/reflect/Method;
    //   396: astore_1
    //   397: aload_1
    //   398: aconst_null
    //   399: iconst_0
    //   400: anewarray 57	java/lang/Object
    //   403: invokevirtual 63	java/lang/reflect/Method:invoke	(Ljava/lang/Object;[Ljava/lang/Object;)Ljava/lang/Object;
    //   406: astore_1
    //   407: aload_1
    //   408: checkcast 65	java/lang/Integer
    //   411: invokevirtual 68	java/lang/Integer:intValue	()I
    //   414: istore_3
    //   415: ldc 2
    //   417: ldc -2
    //   419: sipush 238
    //   422: sipush 155
    //   425: iconst_1
    //   426: invokestatic 76	xxxxxx/uxxxxx:bbbb0062b0062b0062b0062	(Ljava/lang/String;CCC)Ljava/lang/String;
    //   429: iconst_0
    //   430: anewarray 51	java/lang/Class
    //   433: invokevirtual 55	java/lang/Class:getMethod	(Ljava/lang/String;[Ljava/lang/Class;)Ljava/lang/reflect/Method;
    //   436: astore_1
    //   437: aload_1
    //   438: aconst_null
    //   439: iconst_0
    //   440: anewarray 57	java/lang/Object
    //   443: invokevirtual 63	java/lang/reflect/Method:invoke	(Ljava/lang/Object;[Ljava/lang/Object;)Ljava/lang/Object;
    //   446: astore_1
    //   447: aload_1
    //   448: checkcast 65	java/lang/Integer
    //   451: invokevirtual 68	java/lang/Integer:intValue	()I
    //   454: iload_2
    //   455: iload_3
    //   456: iadd
    //   457: imul
    //   458: getstatic 39	uuuuuu/gaaaaa:by0079y0079y007900790079y	I
    //   461: irem
    //   462: getstatic 41	uuuuuu/gaaaaa:b0079yy0079y007900790079y	I
    //   465: if_icmpeq +13 -> 478
    //   468: bipush 32
    //   470: putstatic 35	uuuuuu/gaaaaa:byyy0079y007900790079y	I
    //   473: bipush 22
    //   475: putstatic 41	uuuuuu/gaaaaa:b0079yy0079y007900790079y	I
    //   478: getstatic 257	uuuuuu/vvrvrv:b00780078xx0078xxxx	Luuuuuu/vvrvrv;
    //   481: invokestatic 156	uuuuuu/rrvvrv:b0071q0071qq0071q0071q0071	(Luuuuuu/vvrvrv;)V
    //   484: return
    //   485: astore_1
    //   486: aload_1
    //   487: invokevirtual 129	java/lang/reflect/InvocationTargetException:getCause	()Ljava/lang/Throwable;
    //   490: athrow
    //   491: astore_1
    //   492: aload_1
    //   493: invokevirtual 129	java/lang/reflect/InvocationTargetException:getCause	()Ljava/lang/Throwable;
    //   496: athrow
    //   497: astore_1
    //   498: aload_1
    //   499: invokevirtual 129	java/lang/reflect/InvocationTargetException:getCause	()Ljava/lang/Throwable;
    //   502: athrow
    //   503: astore_1
    //   504: aload_1
    //   505: invokevirtual 129	java/lang/reflect/InvocationTargetException:getCause	()Ljava/lang/Throwable;
    //   508: athrow
    //   509: astore_1
    //   510: aload_1
    //   511: invokevirtual 129	java/lang/reflect/InvocationTargetException:getCause	()Ljava/lang/Throwable;
    //   514: athrow
    //   515: astore_1
    //   516: aload_1
    //   517: invokevirtual 129	java/lang/reflect/InvocationTargetException:getCause	()Ljava/lang/Throwable;
    //   520: athrow
    //   521: astore_1
    //   522: aload_1
    //   523: invokevirtual 129	java/lang/reflect/InvocationTargetException:getCause	()Ljava/lang/Throwable;
    //   526: athrow
    //   527: astore_1
    //   528: aload_1
    //   529: invokevirtual 129	java/lang/reflect/InvocationTargetException:getCause	()Ljava/lang/Throwable;
    //   532: athrow
    // Local variable table:
    //   start	length	slot	name	signature
    //   0	533	0	this	gaaaaa
    //   0	533	1	paramContext	android.content.Context
    //   48	409	2	i	int
    //   52	405	3	j	int
    //   181	124	4	k	int
    //   186	11	5	m	int
    //   7	326	6	str	String
    //   26	305	7	localObject1	Object
    //   242	64	8	localObject2	Object
    // Exception table:
    //   from	to	target	type
    //   287	299	485	java/lang/reflect/InvocationTargetException
    //   72	84	491	java/lang/reflect/InvocationTargetException
    //   133	145	497	java/lang/reflect/InvocationTargetException
    //   244	256	503	java/lang/reflect/InvocationTargetException
    //   28	40	509	java/lang/reflect/InvocationTargetException
    //   360	370	515	java/lang/reflect/InvocationTargetException
    //   397	407	521	java/lang/reflect/InvocationTargetException
    //   437	447	527	java/lang/reflect/InvocationTargetException
  }
  
  /* Error */
  public void bw0077w0077w0077w0077ww()
  {
    // Byte code:
    //   0: getstatic 35	uuuuuu/gaaaaa:byyy0079y007900790079y	I
    //   3: istore_1
    //   4: getstatic 37	uuuuuu/gaaaaa:b00790079y0079y007900790079y	I
    //   7: istore_2
    //   8: getstatic 35	uuuuuu/gaaaaa:byyy0079y007900790079y	I
    //   11: istore_3
    //   12: getstatic 39	uuuuuu/gaaaaa:by0079y0079y007900790079y	I
    //   15: istore 4
    //   17: getstatic 41	uuuuuu/gaaaaa:b0079yy0079y007900790079y	I
    //   20: istore 5
    //   22: getstatic 35	uuuuuu/gaaaaa:byyy0079y007900790079y	I
    //   25: istore 6
    //   27: iload 6
    //   29: getstatic 37	uuuuuu/gaaaaa:b00790079y0079y007900790079y	I
    //   32: iload 6
    //   34: iadd
    //   35: imul
    //   36: getstatic 39	uuuuuu/gaaaaa:by0079y0079y007900790079y	I
    //   39: irem
    //   40: tableswitch	default:+20->60, 0:+118->158
    //   60: ldc 2
    //   62: ldc_w 260
    //   65: bipush 25
    //   67: bipush 72
    //   69: iconst_1
    //   70: invokestatic 76	xxxxxx/uxxxxx:bbbb0062b0062b0062b0062	(Ljava/lang/String;CCC)Ljava/lang/String;
    //   73: iconst_0
    //   74: anewarray 51	java/lang/Class
    //   77: invokevirtual 55	java/lang/Class:getMethod	(Ljava/lang/String;[Ljava/lang/Class;)Ljava/lang/reflect/Method;
    //   80: astore 7
    //   82: aload 7
    //   84: aconst_null
    //   85: iconst_0
    //   86: anewarray 57	java/lang/Object
    //   89: invokevirtual 63	java/lang/reflect/Method:invoke	(Ljava/lang/Object;[Ljava/lang/Object;)Ljava/lang/Object;
    //   92: astore 7
    //   94: aload 7
    //   96: checkcast 65	java/lang/Integer
    //   99: invokevirtual 68	java/lang/Integer:intValue	()I
    //   102: putstatic 35	uuuuuu/gaaaaa:byyy0079y007900790079y	I
    //   105: bipush 64
    //   107: putstatic 41	uuuuuu/gaaaaa:b0079yy0079y007900790079y	I
    //   110: getstatic 35	uuuuuu/gaaaaa:byyy0079y007900790079y	I
    //   113: istore 6
    //   115: iload 6
    //   117: getstatic 37	uuuuuu/gaaaaa:b00790079y0079y007900790079y	I
    //   120: iload 6
    //   122: iadd
    //   123: imul
    //   124: getstatic 39	uuuuuu/gaaaaa:by0079y0079y007900790079y	I
    //   127: irem
    //   128: tableswitch	default:+20->148, 0:+30->158
    //   148: bipush 31
    //   150: putstatic 35	uuuuuu/gaaaaa:byyy0079y007900790079y	I
    //   153: bipush 84
    //   155: putstatic 41	uuuuuu/gaaaaa:b0079yy0079y007900790079y	I
    //   158: iload_1
    //   159: iload_2
    //   160: iadd
    //   161: iload_3
    //   162: imul
    //   163: iload 4
    //   165: irem
    //   166: iload 5
    //   168: if_icmpeq +138 -> 306
    //   171: getstatic 35	uuuuuu/gaaaaa:byyy0079y007900790079y	I
    //   174: istore_1
    //   175: iload_1
    //   176: getstatic 37	uuuuuu/gaaaaa:b00790079y0079y007900790079y	I
    //   179: iload_1
    //   180: iadd
    //   181: imul
    //   182: getstatic 39	uuuuuu/gaaaaa:by0079y0079y007900790079y	I
    //   185: irem
    //   186: tableswitch	default:+18->204, 0:+110->296
    //   204: ldc 2
    //   206: ldc_w 262
    //   209: sipush 176
    //   212: bipush 14
    //   214: iconst_0
    //   215: invokestatic 76	xxxxxx/uxxxxx:bbbb0062b0062b0062b0062	(Ljava/lang/String;CCC)Ljava/lang/String;
    //   218: iconst_0
    //   219: anewarray 51	java/lang/Class
    //   222: invokevirtual 55	java/lang/Class:getMethod	(Ljava/lang/String;[Ljava/lang/Class;)Ljava/lang/reflect/Method;
    //   225: astore 7
    //   227: aload 7
    //   229: aconst_null
    //   230: iconst_0
    //   231: anewarray 57	java/lang/Object
    //   234: invokevirtual 63	java/lang/reflect/Method:invoke	(Ljava/lang/Object;[Ljava/lang/Object;)Ljava/lang/Object;
    //   237: astore 7
    //   239: aload 7
    //   241: checkcast 65	java/lang/Integer
    //   244: invokevirtual 68	java/lang/Integer:intValue	()I
    //   247: putstatic 35	uuuuuu/gaaaaa:byyy0079y007900790079y	I
    //   250: ldc 2
    //   252: ldc_w 264
    //   255: bipush 16
    //   257: sipush 144
    //   260: iconst_3
    //   261: invokestatic 76	xxxxxx/uxxxxx:bbbb0062b0062b0062b0062	(Ljava/lang/String;CCC)Ljava/lang/String;
    //   264: iconst_0
    //   265: anewarray 51	java/lang/Class
    //   268: invokevirtual 55	java/lang/Class:getMethod	(Ljava/lang/String;[Ljava/lang/Class;)Ljava/lang/reflect/Method;
    //   271: astore 7
    //   273: aload 7
    //   275: aconst_null
    //   276: iconst_0
    //   277: anewarray 57	java/lang/Object
    //   280: invokevirtual 63	java/lang/reflect/Method:invoke	(Ljava/lang/Object;[Ljava/lang/Object;)Ljava/lang/Object;
    //   283: astore 7
    //   285: aload 7
    //   287: checkcast 65	java/lang/Integer
    //   290: invokevirtual 68	java/lang/Integer:intValue	()I
    //   293: putstatic 41	uuuuuu/gaaaaa:b0079yy0079y007900790079y	I
    //   296: bipush 59
    //   298: putstatic 35	uuuuuu/gaaaaa:byyy0079y007900790079y	I
    //   301: bipush 43
    //   303: putstatic 41	uuuuuu/gaaaaa:b0079yy0079y007900790079y	I
    //   306: aload_0
    //   307: getfield 33	uuuuuu/gaaaaa:b007900790079yy007900790079y	Luuuuuu/gaaaga;
    //   310: invokevirtual 267	uuuuuu/gaaaga:b007700770077w0077ww0077ww	()V
    //   313: return
    //   314: astore 7
    //   316: aload 7
    //   318: invokevirtual 129	java/lang/reflect/InvocationTargetException:getCause	()Ljava/lang/Throwable;
    //   321: athrow
    //   322: astore 7
    //   324: aload 7
    //   326: invokevirtual 129	java/lang/reflect/InvocationTargetException:getCause	()Ljava/lang/Throwable;
    //   329: athrow
    //   330: astore 7
    //   332: aload 7
    //   334: invokevirtual 129	java/lang/reflect/InvocationTargetException:getCause	()Ljava/lang/Throwable;
    //   337: athrow
    // Local variable table:
    //   start	length	slot	name	signature
    //   0	338	0	this	gaaaaa
    //   3	179	1	i	int
    //   7	154	2	j	int
    //   11	152	3	k	int
    //   15	151	4	m	int
    //   20	149	5	n	int
    //   25	99	6	i1	int
    //   80	206	7	localObject	Object
    //   314	3	7	localInvocationTargetException1	java.lang.reflect.InvocationTargetException
    //   322	3	7	localInvocationTargetException2	java.lang.reflect.InvocationTargetException
    //   330	3	7	localInvocationTargetException3	java.lang.reflect.InvocationTargetException
    // Exception table:
    //   from	to	target	type
    //   82	94	314	java/lang/reflect/InvocationTargetException
    //   227	239	322	java/lang/reflect/InvocationTargetException
    //   273	285	330	java/lang/reflect/InvocationTargetException
  }
  
  /* Error */
  public boolean bww00770077w0077w0077ww()
  {
    // Byte code:
    //   0: getstatic 35	uuuuuu/gaaaaa:byyy0079y007900790079y	I
    //   3: istore_1
    //   4: iload_1
    //   5: getstatic 37	uuuuuu/gaaaaa:b00790079y0079y007900790079y	I
    //   8: iload_1
    //   9: iadd
    //   10: imul
    //   11: getstatic 39	uuuuuu/gaaaaa:by0079y0079y007900790079y	I
    //   14: irem
    //   15: tableswitch	default:+17->32, 0:+68->83
    //   32: ldc 2
    //   34: ldc_w 271
    //   37: sipush 191
    //   40: bipush 110
    //   42: iconst_3
    //   43: invokestatic 76	xxxxxx/uxxxxx:bbbb0062b0062b0062b0062	(Ljava/lang/String;CCC)Ljava/lang/String;
    //   46: iconst_0
    //   47: anewarray 51	java/lang/Class
    //   50: invokevirtual 55	java/lang/Class:getMethod	(Ljava/lang/String;[Ljava/lang/Class;)Ljava/lang/reflect/Method;
    //   53: astore 4
    //   55: aload 4
    //   57: aconst_null
    //   58: iconst_0
    //   59: anewarray 57	java/lang/Object
    //   62: invokevirtual 63	java/lang/reflect/Method:invoke	(Ljava/lang/Object;[Ljava/lang/Object;)Ljava/lang/Object;
    //   65: astore 4
    //   67: aload 4
    //   69: checkcast 65	java/lang/Integer
    //   72: invokevirtual 68	java/lang/Integer:intValue	()I
    //   75: putstatic 35	uuuuuu/gaaaaa:byyy0079y007900790079y	I
    //   78: bipush 83
    //   80: putstatic 41	uuuuuu/gaaaaa:b0079yy0079y007900790079y	I
    //   83: aload_0
    //   84: getfield 33	uuuuuu/gaaaaa:b007900790079yy007900790079y	Luuuuuu/gaaaga;
    //   87: invokevirtual 224	uuuuuu/gaaaga:bw0077wwwww0077ww	()Ljava/lang/String;
    //   90: invokestatic 236	uuuuuu/sxsxsx:b006Bkkkk006Bk006B006B006B	(Ljava/lang/String;)Z
    //   93: istore_3
    //   94: getstatic 35	uuuuuu/gaaaaa:byyy0079y007900790079y	I
    //   97: istore_1
    //   98: iload_1
    //   99: getstatic 37	uuuuuu/gaaaaa:b00790079y0079y007900790079y	I
    //   102: iload_1
    //   103: iadd
    //   104: imul
    //   105: getstatic 39	uuuuuu/gaaaaa:by0079y0079y007900790079y	I
    //   108: irem
    //   109: tableswitch	default:+19->128, 0:+383->492
    //   128: ldc 2
    //   130: ldc_w 273
    //   133: bipush 47
    //   135: sipush 180
    //   138: iconst_3
    //   139: invokestatic 76	xxxxxx/uxxxxx:bbbb0062b0062b0062b0062	(Ljava/lang/String;CCC)Ljava/lang/String;
    //   142: iconst_0
    //   143: anewarray 51	java/lang/Class
    //   146: invokevirtual 55	java/lang/Class:getMethod	(Ljava/lang/String;[Ljava/lang/Class;)Ljava/lang/reflect/Method;
    //   149: astore 4
    //   151: aload 4
    //   153: aconst_null
    //   154: iconst_0
    //   155: anewarray 57	java/lang/Object
    //   158: invokevirtual 63	java/lang/reflect/Method:invoke	(Ljava/lang/Object;[Ljava/lang/Object;)Ljava/lang/Object;
    //   161: astore 4
    //   163: aload 4
    //   165: checkcast 65	java/lang/Integer
    //   168: invokevirtual 68	java/lang/Integer:intValue	()I
    //   171: istore_1
    //   172: getstatic 37	uuuuuu/gaaaaa:b00790079y0079y007900790079y	I
    //   175: istore_2
    //   176: ldc 2
    //   178: ldc_w 275
    //   181: bipush 97
    //   183: iconst_3
    //   184: invokestatic 49	xxxxxx/uxxxxx:bb00620062bb0062b0062b0062	(Ljava/lang/String;CC)Ljava/lang/String;
    //   187: iconst_0
    //   188: anewarray 51	java/lang/Class
    //   191: invokevirtual 55	java/lang/Class:getMethod	(Ljava/lang/String;[Ljava/lang/Class;)Ljava/lang/reflect/Method;
    //   194: astore 4
    //   196: aload 4
    //   198: aconst_null
    //   199: iconst_0
    //   200: anewarray 57	java/lang/Object
    //   203: invokevirtual 63	java/lang/reflect/Method:invoke	(Ljava/lang/Object;[Ljava/lang/Object;)Ljava/lang/Object;
    //   206: astore 4
    //   208: aload 4
    //   210: checkcast 65	java/lang/Integer
    //   213: invokevirtual 68	java/lang/Integer:intValue	()I
    //   216: iload_2
    //   217: iload_1
    //   218: iadd
    //   219: imul
    //   220: getstatic 39	uuuuuu/gaaaaa:by0079y0079y007900790079y	I
    //   223: irem
    //   224: getstatic 41	uuuuuu/gaaaaa:b0079yy0079y007900790079y	I
    //   227: if_icmpeq +53 -> 280
    //   230: ldc 2
    //   232: ldc_w 277
    //   235: bipush 18
    //   237: bipush 77
    //   239: iconst_3
    //   240: invokestatic 76	xxxxxx/uxxxxx:bbbb0062b0062b0062b0062	(Ljava/lang/String;CCC)Ljava/lang/String;
    //   243: iconst_0
    //   244: anewarray 51	java/lang/Class
    //   247: invokevirtual 55	java/lang/Class:getMethod	(Ljava/lang/String;[Ljava/lang/Class;)Ljava/lang/reflect/Method;
    //   250: astore 4
    //   252: aload 4
    //   254: aconst_null
    //   255: iconst_0
    //   256: anewarray 57	java/lang/Object
    //   259: invokevirtual 63	java/lang/reflect/Method:invoke	(Ljava/lang/Object;[Ljava/lang/Object;)Ljava/lang/Object;
    //   262: astore 4
    //   264: aload 4
    //   266: checkcast 65	java/lang/Integer
    //   269: invokevirtual 68	java/lang/Integer:intValue	()I
    //   272: putstatic 35	uuuuuu/gaaaaa:byyy0079y007900790079y	I
    //   275: bipush 21
    //   277: putstatic 41	uuuuuu/gaaaaa:b0079yy0079y007900790079y	I
    //   280: ldc 2
    //   282: ldc_w 279
    //   285: sipush 199
    //   288: bipush 8
    //   290: iconst_3
    //   291: invokestatic 76	xxxxxx/uxxxxx:bbbb0062b0062b0062b0062	(Ljava/lang/String;CCC)Ljava/lang/String;
    //   294: iconst_0
    //   295: anewarray 51	java/lang/Class
    //   298: invokevirtual 55	java/lang/Class:getMethod	(Ljava/lang/String;[Ljava/lang/Class;)Ljava/lang/reflect/Method;
    //   301: astore 4
    //   303: aload 4
    //   305: aconst_null
    //   306: iconst_0
    //   307: anewarray 57	java/lang/Object
    //   310: invokevirtual 63	java/lang/reflect/Method:invoke	(Ljava/lang/Object;[Ljava/lang/Object;)Ljava/lang/Object;
    //   313: astore 4
    //   315: aload 4
    //   317: checkcast 65	java/lang/Integer
    //   320: invokevirtual 68	java/lang/Integer:intValue	()I
    //   323: putstatic 35	uuuuuu/gaaaaa:byyy0079y007900790079y	I
    //   326: ldc 2
    //   328: ldc_w 281
    //   331: bipush 104
    //   333: iconst_4
    //   334: invokestatic 49	xxxxxx/uxxxxx:bb00620062bb0062b0062b0062	(Ljava/lang/String;CC)Ljava/lang/String;
    //   337: iconst_0
    //   338: anewarray 51	java/lang/Class
    //   341: invokevirtual 55	java/lang/Class:getMethod	(Ljava/lang/String;[Ljava/lang/Class;)Ljava/lang/reflect/Method;
    //   344: astore 4
    //   346: aload 4
    //   348: aconst_null
    //   349: iconst_0
    //   350: anewarray 57	java/lang/Object
    //   353: invokevirtual 63	java/lang/reflect/Method:invoke	(Ljava/lang/Object;[Ljava/lang/Object;)Ljava/lang/Object;
    //   356: astore 4
    //   358: aload 4
    //   360: checkcast 65	java/lang/Integer
    //   363: invokevirtual 68	java/lang/Integer:intValue	()I
    //   366: putstatic 41	uuuuuu/gaaaaa:b0079yy0079y007900790079y	I
    //   369: getstatic 35	uuuuuu/gaaaaa:byyy0079y007900790079y	I
    //   372: istore_1
    //   373: ldc 2
    //   375: ldc_w 283
    //   378: sipush 207
    //   381: bipush 53
    //   383: iconst_3
    //   384: invokestatic 76	xxxxxx/uxxxxx:bbbb0062b0062b0062b0062	(Ljava/lang/String;CCC)Ljava/lang/String;
    //   387: iconst_0
    //   388: anewarray 51	java/lang/Class
    //   391: invokevirtual 55	java/lang/Class:getMethod	(Ljava/lang/String;[Ljava/lang/Class;)Ljava/lang/reflect/Method;
    //   394: astore 4
    //   396: aload 4
    //   398: aconst_null
    //   399: iconst_0
    //   400: anewarray 57	java/lang/Object
    //   403: invokevirtual 63	java/lang/reflect/Method:invoke	(Ljava/lang/Object;[Ljava/lang/Object;)Ljava/lang/Object;
    //   406: astore 4
    //   408: aload 4
    //   410: checkcast 65	java/lang/Integer
    //   413: invokevirtual 68	java/lang/Integer:intValue	()I
    //   416: iload_1
    //   417: iadd
    //   418: iload_1
    //   419: imul
    //   420: getstatic 39	uuuuuu/gaaaaa:by0079y0079y007900790079y	I
    //   423: irem
    //   424: tableswitch	default:+20->444, 0:+68->492
    //   444: ldc 2
    //   446: ldc_w 285
    //   449: bipush 116
    //   451: iconst_1
    //   452: invokestatic 49	xxxxxx/uxxxxx:bb00620062bb0062b0062b0062	(Ljava/lang/String;CC)Ljava/lang/String;
    //   455: iconst_0
    //   456: anewarray 51	java/lang/Class
    //   459: invokevirtual 55	java/lang/Class:getMethod	(Ljava/lang/String;[Ljava/lang/Class;)Ljava/lang/reflect/Method;
    //   462: astore 4
    //   464: aload 4
    //   466: aconst_null
    //   467: iconst_0
    //   468: anewarray 57	java/lang/Object
    //   471: invokevirtual 63	java/lang/reflect/Method:invoke	(Ljava/lang/Object;[Ljava/lang/Object;)Ljava/lang/Object;
    //   474: astore 4
    //   476: aload 4
    //   478: checkcast 65	java/lang/Integer
    //   481: invokevirtual 68	java/lang/Integer:intValue	()I
    //   484: putstatic 35	uuuuuu/gaaaaa:byyy0079y007900790079y	I
    //   487: bipush 31
    //   489: putstatic 41	uuuuuu/gaaaaa:b0079yy0079y007900790079y	I
    //   492: iload_3
    //   493: ireturn
    //   494: astore 4
    //   496: aload 4
    //   498: invokevirtual 129	java/lang/reflect/InvocationTargetException:getCause	()Ljava/lang/Throwable;
    //   501: athrow
    //   502: astore 4
    //   504: aload 4
    //   506: invokevirtual 129	java/lang/reflect/InvocationTargetException:getCause	()Ljava/lang/Throwable;
    //   509: athrow
    //   510: astore 4
    //   512: aload 4
    //   514: invokevirtual 129	java/lang/reflect/InvocationTargetException:getCause	()Ljava/lang/Throwable;
    //   517: athrow
    //   518: astore 4
    //   520: aload 4
    //   522: invokevirtual 129	java/lang/reflect/InvocationTargetException:getCause	()Ljava/lang/Throwable;
    //   525: athrow
    //   526: astore 4
    //   528: aload 4
    //   530: invokevirtual 129	java/lang/reflect/InvocationTargetException:getCause	()Ljava/lang/Throwable;
    //   533: athrow
    //   534: astore 4
    //   536: aload 4
    //   538: invokevirtual 129	java/lang/reflect/InvocationTargetException:getCause	()Ljava/lang/Throwable;
    //   541: athrow
    //   542: astore 4
    //   544: aload 4
    //   546: invokevirtual 129	java/lang/reflect/InvocationTargetException:getCause	()Ljava/lang/Throwable;
    //   549: athrow
    //   550: astore 4
    //   552: aload 4
    //   554: invokevirtual 129	java/lang/reflect/InvocationTargetException:getCause	()Ljava/lang/Throwable;
    //   557: athrow
    // Local variable table:
    //   start	length	slot	name	signature
    //   0	558	0	this	gaaaaa
    //   3	417	1	i	int
    //   175	44	2	j	int
    //   93	400	3	bool	boolean
    //   53	424	4	localObject	Object
    //   494	3	4	localInvocationTargetException1	java.lang.reflect.InvocationTargetException
    //   502	3	4	localInvocationTargetException2	java.lang.reflect.InvocationTargetException
    //   510	3	4	localInvocationTargetException3	java.lang.reflect.InvocationTargetException
    //   518	3	4	localInvocationTargetException4	java.lang.reflect.InvocationTargetException
    //   526	3	4	localInvocationTargetException5	java.lang.reflect.InvocationTargetException
    //   534	3	4	localInvocationTargetException6	java.lang.reflect.InvocationTargetException
    //   542	3	4	localInvocationTargetException7	java.lang.reflect.InvocationTargetException
    //   550	3	4	localInvocationTargetException8	java.lang.reflect.InvocationTargetException
    // Exception table:
    //   from	to	target	type
    //   303	315	494	java/lang/reflect/InvocationTargetException
    //   346	358	502	java/lang/reflect/InvocationTargetException
    //   396	408	510	java/lang/reflect/InvocationTargetException
    //   151	163	518	java/lang/reflect/InvocationTargetException
    //   196	208	526	java/lang/reflect/InvocationTargetException
    //   464	476	534	java/lang/reflect/InvocationTargetException
    //   252	264	542	java/lang/reflect/InvocationTargetException
    //   55	67	550	java/lang/reflect/InvocationTargetException
  }
}
