package uuuuuu;

import android.support.annotation.NonNull;
import com.android.volley.Cache.Entry;
import com.db.pwcc.dbmobile.model.error.DbError;
import com.db.pwcc.dbmobile.model.error.DbErrorsPayload;
import com.google.gson.Gson;
import java.lang.reflect.InvocationTargetException;
import java.lang.reflect.Method;
import java.util.Locale;
import java.util.Map;
import org.apache.http.impl.EnglishReasonPhraseCatalog;
import xxxxxx.uxxxxx;

public abstract class gyggyy
  extends yggygy
{
  public static int b006B006Bk006B006B006Bk006Bk = 0;
  private static final int b006B006Bkk006B006Bk006Bk = 911;
  public static int b006Bkk006B006B006Bk006Bk = 2;
  public static int bk006Bk006B006B006Bk006Bk = 82;
  private static final String bkk006Bk006B006Bk006Bk = gyggyy.class.getSimpleName();
  public static int bkkk006B006B006Bk006Bk = 1;
  private yhyyhh b006B006B006Bk006B006Bk006Bk = new yhyyhh();
  private fmfmmm b006Bk006Bk006B006Bk006Bk = new fmfmmm();
  private yyggyy bk006B006Bk006B006Bk006Bk = new yyggyy();
  
  static
  {
    int i = b0070p00700070p0070pp0070p();
    int j = bkkk006B006B006Bk006Bk;
    int k = b006Bkk006B006B006Bk006Bk;
    if ((bk006Bk006B006B006Bk006Bk + bkkk006B006B006Bk006Bk) * bk006Bk006B006B006Bk006Bk % b006Bkk006B006B006Bk006Bk != b006B006Bk006B006B006Bk006Bk)
    {
      bk006Bk006B006B006Bk006Bk = b0070p00700070p0070pp0070p();
      b006B006Bk006B006B006Bk006Bk = 93;
    }
    switch (i * (j + i) % k)
    {
    default: 
      bkkk006B006B006Bk006Bk = 60;
    }
  }
  
  public gyggyy(ygyygy paramYgyygy)
  {
    super(paramYgyygy);
    this.bk006B006B006B006B006B006Bkk = new ffmmmm();
  }
  
  private void b0070007000700070p0070pp0070p(String paramString1, String paramString2)
  {
    long l = System.currentTimeMillis();
    Cache.Entry localEntry = new Cache.Entry();
    localEntry.data = paramString2.getBytes();
    localEntry.serverDate = l;
    localEntry.softTtl = (180000L + l);
    if ((bk006Bk006B006B006Bk006Bk + b00700070p0070p0070pp0070p()) * bk006Bk006B006B006Bk006Bk % b006Bkk006B006B006Bk006Bk != b006B006Bk006B006B006Bk006Bk)
    {
      bk006Bk006B006B006Bk006Bk = 76;
      b006B006Bk006B006B006Bk006Bk = b0070p00700070p0070pp0070p();
      int i = bk006Bk006B006B006Bk006Bk;
      switch (i * (bkkk006B006B006Bk006Bk + i) % b006Bkk006B006B006Bk006Bk)
      {
      default: 
        bk006Bk006B006B006Bk006Bk = b0070p00700070p0070pp0070p();
        b006B006Bk006B006B006Bk006Bk = b0070p00700070p0070pp0070p();
      }
    }
    localEntry.ttl = (l + 86400000L);
    b00700070p0070p007000700070pp(paramString1, localEntry);
  }
  
  public static int b00700070p0070p0070pp0070p()
  {
    return 1;
  }
  
  public static int b0070p00700070p0070pp0070p()
  {
    return 72;
  }
  
  private ggygyy b0070ppp00700070pp0070p(String paramString)
  {
    if ((bk006Bk006B006B006Bk006Bk + bkkk006B006B006Bk006Bk) * bk006Bk006B006B006Bk006Bk % b006Bkk006B006B006Bk006Bk != b006B006Bk006B006B006Bk006Bk)
    {
      bk006Bk006B006B006Bk006Bk = b0070p00700070p0070pp0070p();
      b006B006Bk006B006B006Bk006Bk = 98;
    }
    Object localObject = this.bk006B006Bk006B006Bk006Bk;
    if ((bk006Bk006B006B006Bk006Bk + bkkk006B006B006Bk006Bk) * bk006Bk006B006B006Bk006Bk % b006Bkk006B006B006Bk006Bk != b006B006Bk006B006B006Bk006Bk)
    {
      bk006Bk006B006B006Bk006Bk = b0070p00700070p0070pp0070p();
      b006B006Bk006B006B006Bk006Bk = b0070p00700070p0070pp0070p();
    }
    localObject = bp0070p0070p0070pp0070p(((yyggyy)localObject).bp0070p007000700070pp0070p(paramString));
    if ((localObject != null) && (((ggygyy)localObject).b0070ppppp0070p0070p() != 0) && (((ggygyy)localObject).b0070ppppp0070p0070p() == 200) && (((ggygyy)localObject).bpppppp0070p0070p() != null)) {
      b0070007000700070p0070pp0070p(paramString, ((ggygyy)localObject).bpppppp0070p0070p());
    }
    return localObject;
  }
  
  public static int bp007000700070p0070pp0070p()
  {
    return 0;
  }
  
  private ggygyy bp0070p0070p0070pp0070p(ggygyy paramGgygyy)
  {
    if ((paramGgygyy == null) || (paramGgygyy.bpppppp0070p0070p() == null)) {}
    for (;;)
    {
      if ((bk006Bk006B006B006Bk006Bk + b00700070p0070p0070pp0070p()) * bk006Bk006B006B006Bk006Bk % b006Bkk006B006B006Bk006Bk != b006B006Bk006B006B006Bk006Bk)
      {
        bk006Bk006B006B006Bk006Bk = b0070p00700070p0070pp0070p();
        b006B006Bk006B006B006Bk006Bk = b0070p00700070p0070pp0070p();
      }
      return paramGgygyy;
      String str = paramGgygyy.bpppppp0070p0070p();
      str = this.b006B006B006Bk006B006Bk006Bk.bpp0070pp00700070007000700070(this, str, paramGgygyy.b007000700070007000700070pp0070p());
      if ((b0070p00700070p0070pp0070p() + bkkk006B006B006Bk006Bk) * b0070p00700070p0070pp0070p() % b006Bkk006B006B006Bk006Bk != b006B006Bk006B006B006Bk006Bk)
      {
        bk006Bk006B006B006Bk006Bk = b0070p00700070p0070pp0070p();
        b006B006Bk006B006B006Bk006Bk = b0070p00700070p0070pp0070p();
      }
      paramGgygyy.b00700070pppp0070p0070p(str);
    }
  }
  
  public static int bpp00700070p0070pp0070p()
  {
    return 2;
  }
  
  private String bpppp00700070pp0070p(String paramString, Cache.Entry paramEntry)
  {
    StringBuilder localStringBuilder = new StringBuilder();
    if ((bk006Bk006B006B006Bk006Bk + bkkk006B006B006Bk006Bk) * bk006Bk006B006B006Bk006Bk % b006Bkk006B006B006Bk006Bk != b006B006Bk006B006B006Bk006Bk)
    {
      bk006Bk006B006B006Bk006Bk = b0070p00700070p0070pp0070p();
      b006B006Bk006B006B006Bk006Bk = b0070p00700070p0070pp0070p();
    }
    paramString = localStringBuilder.append(paramString);
    if ((bk006Bk006B006B006Bk006Bk + bkkk006B006B006Bk006Bk) * bk006Bk006B006B006Bk006Bk % b006Bkk006B006B006Bk006Bk != bp007000700070p0070pp0070p())
    {
      bk006Bk006B006B006Bk006Bk = 89;
      b006B006Bk006B006B006Bk006Bk = 50;
    }
    return paramEntry.lastModified;
  }
  
  public void b00700070007000700070p00700070pp(@NonNull Object... paramVarArgs) {}
  
  public void b00700070p0070p007000700070pp(String paramString, Cache.Entry paramEntry)
  {
    int i = bk006Bk006B006B006Bk006Bk;
    switch (i * (bkkk006B006B006Bk006Bk + i) % bpp00700070p0070pp0070p())
    {
    default: 
      bk006Bk006B006B006Bk006Bk = 22;
      b006B006Bk006B006B006Bk006Bk = b0070p00700070p0070pp0070p();
      if ((bk006Bk006B006B006Bk006Bk + bkkk006B006B006Bk006Bk) * bk006Bk006B006B006Bk006Bk % b006Bkk006B006B006Bk006Bk != b006B006Bk006B006B006Bk006Bk)
      {
        bk006Bk006B006B006Bk006Bk = b0070p00700070p0070pp0070p();
        b006B006Bk006B006B006Bk006Bk = b0070p00700070p0070pp0070p();
      }
      break;
    }
    this.b006Bk006Bk006B006Bk006Bk.put(paramString, paramEntry);
  }
  
  public <T> void b0070p00700070p007000700070pp(String paramString, T paramT, Gson paramGson)
  {
    Cache.Entry localEntry = bpp0070pp007000700070pp(paramString);
    if (localEntry != null)
    {
      if ((bk006Bk006B006B006Bk006Bk + bkkk006B006B006Bk006Bk) * bk006Bk006B006B006Bk006Bk % b006Bkk006B006B006Bk006Bk != b006B006Bk006B006B006Bk006Bk)
      {
        bk006Bk006B006B006Bk006Bk = b0070p00700070p0070pp0070p();
        b006B006Bk006B006B006Bk006Bk = 21;
      }
      Map localMap = this.bkkkkkkk006Bk;
      if ((b0070p00700070p0070pp0070p() + bkkk006B006B006Bk006Bk) * b0070p00700070p0070pp0070p() % b006Bkk006B006B006Bk006Bk != b006B006Bk006B006B006Bk006Bk)
      {
        bk006Bk006B006B006Bk006Bk = 38;
        b006B006Bk006B006B006Bk006Bk = b0070p00700070p0070pp0070p();
      }
      localMap.remove(bpppp00700070pp0070p(paramString, localEntry));
      localEntry.data = paramGson.toJson(paramT).getBytes();
      this.bk006B006B006B006B006B006Bkk.b007000700070pp0070007000700070p(paramString, paramT);
    }
  }
  
  public String b0070p0070pp007000700070pp(String paramString)
  {
    int i = bk006Bk006B006B006Bk006Bk;
    int j = bk006Bk006B006B006Bk006Bk;
    switch (j * (bkkk006B006B006Bk006Bk + j) % b006Bkk006B006B006Bk006Bk)
    {
    default: 
      bk006Bk006B006B006Bk006Bk = b0070p00700070p0070pp0070p();
      b006B006Bk006B006B006Bk006Bk = b0070p00700070p0070pp0070p();
    }
    if ((i + bkkk006B006B006Bk006Bk) * bk006Bk006B006B006Bk006Bk % bpp00700070p0070pp0070p() != b006B006Bk006B006B006Bk006Bk)
    {
      bk006Bk006B006B006Bk006Bk = b0070p00700070p0070pp0070p();
      b006B006Bk006B006B006Bk006Bk = 37;
    }
    paramString = ppphhp.class.getMethod(uxxxxx.bbbb0062b0062b0062b0062("\002\026\025\024\023JIONFEKJ\nA@FE=<BA\001", 'Ã', '', '\000'), new Class[] { String.class, Character.TYPE, Character.TYPE });
    try
    {
      paramString = paramString.invoke(null, new Object[] { "vwjq", Character.valueOf('õ'), Character.valueOf('\003') });
      return (String)paramString;
    }
    catch (InvocationTargetException paramString)
    {
      throw paramString.getCause();
    }
  }
  
  public void b0070pp0070p007000700070pp(String paramString)
  {
    Cache.Entry localEntry = bpp0070pp007000700070pp(paramString);
    if (localEntry == null)
    {
      int i = bk006Bk006B006B006Bk006Bk;
      switch (i * (bkkk006B006B006Bk006Bk + i) % b006Bkk006B006B006Bk006Bk)
      {
      default: 
        bk006Bk006B006B006Bk006Bk = b0070p00700070p0070pp0070p();
        b006B006Bk006B006B006Bk006Bk = b0070p00700070p0070pp0070p();
      }
      return;
    }
    this.b006Bk006Bk006B006Bk006Bk.invalidate(paramString, true);
    if ((bk006Bk006B006B006Bk006Bk + bkkk006B006B006Bk006Bk) * bk006Bk006B006B006Bk006Bk % b006Bkk006B006B006Bk006Bk != b006B006Bk006B006B006Bk006Bk)
    {
      bk006Bk006B006B006Bk006Bk = b0070p00700070p0070pp0070p();
      b006B006Bk006B006B006Bk006Bk = 8;
    }
    this.bkkkkkkk006Bk.remove(bpppp00700070pp0070p(paramString, localEntry));
  }
  
  public void bp0070007000700070p00700070pp(ololol paramOlolol)
  {
    Object localObject1 = b0070ppp00700070pp0070p(paramOlolol.b007000700070p00700070pp00700070());
    if (localObject1 != null)
    {
      if (((ggygyy)localObject1).b0070ppppp0070p0070p() != 911) {
        break label223;
      }
      paramOlolol = paramOlolol.b0070007000700070p0070pp00700070();
      localObject1 = ppphhp.class.getMethod(uxxxxx.bbbb0062b0062b0062b0062("g{zyx0/54,+10o'&,+#\"('f", 'l', '', '\000'), new Class[] { String.class, Character.TYPE, Character.TYPE });
    }
    try
    {
      localObject1 = ((Method)localObject1).invoke(null, new Object[] { "Twlutzt.}1{\002\tz\t\006}\016:~\f\f\r\005\004\026\f\023\023S", Character.valueOf('\007'), Character.valueOf('\002') });
      paramOlolol.b006100610061aaa006100610061a(bpp007000700070007000700070pp(new RuntimeException((String)localObject1)));
      return;
    }
    catch (InvocationTargetException paramOlolol)
    {
      Object localObject2;
      throw paramOlolol.getCause();
    }
    localObject1 = new DbErrorsPayload();
    localObject2 = ppphhp.class.getMethod(uxxxxx.bb00620062bb0062b0062b0062("\r! \037\036UTZYQPVU\025LKQPHGML\f", 'Ô', '\003'), new Class[] { String.class, Character.TYPE, Character.TYPE });
    try
    {
      localObject2 = ((Method)localObject2).invoke(null, new Object[] { "6XKHR)EWC\001.NR|\"JOG<", Character.valueOf(''), Character.valueOf('\004') });
      ((DbErrorsPayload)localObject1).addError(new DbError((String)localObject2));
      paramOlolol.b0070007000700070p0070pp00700070().b006100610061aaa006100610061a((DbErrorsPayload)localObject1);
      return;
    }
    catch (InvocationTargetException paramOlolol)
    {
      label223:
      Gson localGson;
      lolool.lllool localLllool;
      int i;
      throw paramOlolol.getCause();
    }
    localObject2 = EnglishReasonPhraseCatalog.INSTANCE.getReason(((ggygyy)localObject1).b0070ppppp0070p0070p(), Locale.ENGLISH);
    localGson = paramOlolol.b0070p00700070p0070pp00700070();
    localLllool = new lolool.lllool();
    if ((bk006Bk006B006B006Bk006Bk + bkkk006B006B006Bk006Bk) * bk006Bk006B006B006Bk006Bk % b006Bkk006B006B006Bk006Bk != b006B006Bk006B006B006Bk006Bk)
    {
      bk006Bk006B006B006Bk006Bk = 80;
      b006B006Bk006B006B006Bk006Bk = b0070p00700070p0070pp0070p();
    }
    localObject1 = b00700070007000700070007000700070pp(localGson, localLllool.bp0070007000700070007000700070p0070((String)localObject2).b0070p007000700070007000700070p0070(((ggygyy)localObject1).bpppppp0070p0070p()).bp0070p00700070007000700070p0070(((ggygyy)localObject1).b0070ppppp0070p0070p()).b00700070007000700070007000700070p0070(paramOlolol), ((ggygyy)localObject1).b0070ppppp0070p0070p());
    paramOlolol.b0070007000700070p0070pp00700070().bp0070007000700070ppp00700070((ooolol)localObject1);
    i = bk006Bk006B006B006Bk006Bk;
    switch (i * (bkkk006B006B006Bk006Bk + i) % b006Bkk006B006B006Bk006Bk)
    {
    }
    bk006Bk006B006B006Bk006Bk = 13;
    b006B006Bk006B006B006Bk006Bk = 79;
  }
  
  /* Error */
  public <T> T bp00700070pp007000700070pp(String paramString, java.lang.reflect.Type paramType)
  {
    // Byte code:
    //   0: aload_0
    //   1: aload_1
    //   2: invokevirtual 182	uuuuuu/gyggyy:bpp0070pp007000700070pp	(Ljava/lang/String;)Lcom/android/volley/Cache$Entry;
    //   5: astore_1
    //   6: aload_1
    //   7: ifnonnull +207 -> 214
    //   10: getstatic 35	uuuuuu/gyggyy:bk006Bk006B006B006Bk006Bk	I
    //   13: getstatic 31	uuuuuu/gyggyy:bkkk006B006B006Bk006Bk	I
    //   16: iadd
    //   17: getstatic 35	uuuuuu/gyggyy:bk006Bk006B006B006Bk006Bk	I
    //   20: imul
    //   21: getstatic 33	uuuuuu/gyggyy:b006Bkk006B006B006Bk006Bk	I
    //   24: irem
    //   25: getstatic 37	uuuuuu/gyggyy:b006B006Bk006B006B006Bk006Bk	I
    //   28: if_icmpeq +55 -> 83
    //   31: getstatic 35	uuuuuu/gyggyy:bk006Bk006B006B006Bk006Bk	I
    //   34: istore_3
    //   35: iload_3
    //   36: getstatic 31	uuuuuu/gyggyy:bkkk006B006B006Bk006Bk	I
    //   39: iload_3
    //   40: iadd
    //   41: imul
    //   42: getstatic 33	uuuuuu/gyggyy:b006Bkk006B006B006Bk006Bk	I
    //   45: irem
    //   46: tableswitch	default:+18->64, 0:+27->73
    //   64: bipush 55
    //   66: putstatic 35	uuuuuu/gyggyy:bk006Bk006B006B006Bk006Bk	I
    //   69: iconst_1
    //   70: putstatic 37	uuuuuu/gyggyy:b006B006Bk006B006B006Bk006Bk	I
    //   73: bipush 20
    //   75: putstatic 35	uuuuuu/gyggyy:bk006Bk006B006B006Bk006Bk	I
    //   78: bipush 40
    //   80: putstatic 37	uuuuuu/gyggyy:b006B006Bk006B006B006Bk006Bk	I
    //   83: aconst_null
    //   84: areturn
    //   85: astore_1
    //   86: getstatic 45	uuuuuu/gyggyy:bkk006Bk006B006Bk006Bk	Ljava/lang/String;
    //   89: astore_2
    //   90: new 151	java/lang/StringBuilder
    //   93: dup
    //   94: invokespecial 152	java/lang/StringBuilder:<init>	()V
    //   97: astore 4
    //   99: ldc -44
    //   101: ldc_w 354
    //   104: bipush 28
    //   106: iconst_5
    //   107: invokestatic 293	xxxxxx/uxxxxx:bb00620062bb0062b0062b0062	(Ljava/lang/String;CC)Ljava/lang/String;
    //   110: iconst_4
    //   111: anewarray 39	java/lang/Class
    //   114: dup
    //   115: iconst_0
    //   116: ldc 86
    //   118: aastore
    //   119: dup
    //   120: iconst_1
    //   121: getstatic 226	java/lang/Character:TYPE	Ljava/lang/Class;
    //   124: aastore
    //   125: dup
    //   126: iconst_2
    //   127: getstatic 226	java/lang/Character:TYPE	Ljava/lang/Class;
    //   130: aastore
    //   131: dup
    //   132: iconst_3
    //   133: getstatic 226	java/lang/Character:TYPE	Ljava/lang/Class;
    //   136: aastore
    //   137: invokevirtual 230	java/lang/Class:getMethod	(Ljava/lang/String;[Ljava/lang/Class;)Ljava/lang/reflect/Method;
    //   140: astore 5
    //   142: aload 5
    //   144: aconst_null
    //   145: iconst_4
    //   146: anewarray 232	java/lang/Object
    //   149: dup
    //   150: iconst_0
    //   151: ldc_w 356
    //   154: aastore
    //   155: dup
    //   156: iconst_1
    //   157: sipush 212
    //   160: invokestatic 238	java/lang/Character:valueOf	(C)Ljava/lang/Character;
    //   163: aastore
    //   164: dup
    //   165: iconst_2
    //   166: sipush 162
    //   169: invokestatic 238	java/lang/Character:valueOf	(C)Ljava/lang/Character;
    //   172: aastore
    //   173: dup
    //   174: iconst_3
    //   175: iconst_2
    //   176: invokestatic 238	java/lang/Character:valueOf	(C)Ljava/lang/Character;
    //   179: aastore
    //   180: invokevirtual 244	java/lang/reflect/Method:invoke	(Ljava/lang/Object;[Ljava/lang/Object;)Ljava/lang/Object;
    //   183: astore 5
    //   185: aload_2
    //   186: aload 4
    //   188: aload 5
    //   190: checkcast 86	java/lang/String
    //   193: invokevirtual 156	java/lang/StringBuilder:append	(Ljava/lang/String;)Ljava/lang/StringBuilder;
    //   196: aload_1
    //   197: invokevirtual 359	java/lang/StringBuilder:append	(Ljava/lang/Object;)Ljava/lang/StringBuilder;
    //   200: invokevirtual 167	java/lang/StringBuilder:toString	()Ljava/lang/String;
    //   203: invokestatic 364	uuuuuu/rvvvrv:bq0071qq00710071q0071q0071	(Ljava/lang/String;Ljava/lang/String;)V
    //   206: aconst_null
    //   207: areturn
    //   208: astore_1
    //   209: aload_1
    //   210: invokevirtual 248	java/lang/reflect/InvocationTargetException:getCause	()Ljava/lang/Throwable;
    //   213: athrow
    //   214: new 86	java/lang/String
    //   217: dup
    //   218: aload_1
    //   219: getfield 94	com/android/volley/Cache$Entry:data	[B
    //   222: invokespecial 367	java/lang/String:<init>	([B)V
    //   225: astore_1
    //   226: new 196	com/google/gson/Gson
    //   229: dup
    //   230: invokespecial 368	com/google/gson/Gson:<init>	()V
    //   233: aload_1
    //   234: aload_2
    //   235: invokevirtual 371	com/google/gson/Gson:fromJson	(Ljava/lang/String;Ljava/lang/reflect/Type;)Ljava/lang/Object;
    //   238: astore_1
    //   239: aload_1
    //   240: areturn
    // Local variable table:
    //   start	length	slot	name	signature
    //   0	241	0	this	gyggyy
    //   0	241	1	paramString	String
    //   0	241	2	paramType	java.lang.reflect.Type
    //   34	8	3	i	int
    //   97	90	4	localStringBuilder	StringBuilder
    //   140	49	5	localObject	Object
    // Exception table:
    //   from	to	target	type
    //   226	239	85	com/google/gson/JsonSyntaxException
    //   142	185	208	java/lang/reflect/InvocationTargetException
  }
  
  public boolean bp0070p0070p007000700070pp()
  {
    if ((bk006Bk006B006B006Bk006Bk + bkkk006B006B006Bk006Bk) * bk006Bk006B006B006Bk006Bk % bpp00700070p0070pp0070p() != b006B006Bk006B006B006Bk006Bk)
    {
      bk006Bk006B006B006Bk006Bk = 5;
      b006B006Bk006B006B006Bk006Bk = 59;
      int i = bk006Bk006B006B006Bk006Bk;
      switch (i * (bkkk006B006B006Bk006Bk + i) % b006Bkk006B006B006Bk006Bk)
      {
      default: 
        bk006Bk006B006B006Bk006Bk = 57;
        b006B006Bk006B006B006Bk006Bk = 30;
      }
    }
    return this.b006Bk006Bk006B006Bk006Bk.b00700070p0070p0070007000700070p();
  }
  
  public void bp0070pp00700070pp0070p(String paramString)
  {
    yyggyy localYyggyy = this.bk006B006Bk006B006Bk006Bk;
    paramString = bppp0070p0070pp0070p(paramString);
    if ((bk006Bk006B006B006Bk006Bk + bkkk006B006B006Bk006Bk) * bk006Bk006B006B006Bk006Bk % b006Bkk006B006B006Bk006Bk != b006B006Bk006B006B006Bk006Bk)
    {
      bk006Bk006B006B006Bk006Bk = 72;
      b006B006Bk006B006B006Bk006Bk = b0070p00700070p0070pp0070p();
      int i = bk006Bk006B006B006Bk006Bk;
      switch (i * (b00700070p0070p0070pp0070p() + i) % b006Bkk006B006B006Bk006Bk)
      {
      default: 
        bk006Bk006B006B006Bk006Bk = 69;
        b006B006Bk006B006B006Bk006Bk = 58;
      }
    }
    localYyggyy.b00700070p007000700070pp0070p(this, paramString);
  }
  
  public <T> void bpp00700070p007000700070pp(String paramString, T paramT)
  {
    int i = bk006Bk006B006B006Bk006Bk;
    switch (i * (bkkk006B006B006Bk006Bk + i) % b006Bkk006B006B006Bk006Bk)
    {
    default: 
      if ((bk006Bk006B006B006Bk006Bk + bkkk006B006B006Bk006Bk) * bk006Bk006B006B006Bk006Bk % b006Bkk006B006B006Bk006Bk != b006B006Bk006B006B006Bk006Bk)
      {
        bk006Bk006B006B006Bk006Bk = 86;
        b006B006Bk006B006B006Bk006Bk = 84;
      }
      bk006Bk006B006B006Bk006Bk = b0070p00700070p0070pp0070p();
      b006B006Bk006B006B006Bk006Bk = 55;
    }
    b0070p00700070p007000700070pp(paramString, paramT, new Gson());
  }
  
  public Cache.Entry bpp0070pp007000700070pp(String paramString)
  {
    fmfmmm localFmfmmm = this.b006Bk006Bk006B006Bk006Bk;
    int i = bk006Bk006B006B006Bk006Bk;
    int j = bkkk006B006B006Bk006Bk;
    int k = bk006Bk006B006B006Bk006Bk;
    switch (k * (bkkk006B006B006Bk006Bk + k) % b006Bkk006B006B006Bk006Bk)
    {
    default: 
      bk006Bk006B006B006Bk006Bk = 29;
      b006B006Bk006B006B006Bk006Bk = b0070p00700070p0070pp0070p();
    }
    if ((i + j) * bk006Bk006B006B006Bk006Bk % b006Bkk006B006B006Bk006Bk != b006B006Bk006B006B006Bk006Bk)
    {
      bk006Bk006B006B006Bk006Bk = 33;
      b006B006Bk006B006B006Bk006Bk = 29;
    }
    return localFmfmmm.get(paramString);
  }
  
  public abstract String bppp0070p0070pp0070p(String paramString);
  
  public void bppppp007000700070pp()
  {
    if (!bp0070p0070p007000700070pp()) {
      this.b006Bk006Bk006B006Bk006Bk.clear();
    }
    int i = bk006Bk006B006B006Bk006Bk;
    switch (i * (bkkk006B006B006Bk006Bk + i) % bpp00700070p0070pp0070p())
    {
    default: 
      bk006Bk006B006B006Bk006Bk = b0070p00700070p0070pp0070p();
      b006B006Bk006B006B006Bk006Bk = b0070p00700070p0070pp0070p();
      if ((bk006Bk006B006B006Bk006Bk + bkkk006B006B006Bk006Bk) * bk006Bk006B006B006Bk006Bk % bpp00700070p0070pp0070p() != b006B006Bk006B006B006Bk006Bk)
      {
        bk006Bk006B006B006Bk006Bk = b0070p00700070p0070pp0070p();
        b006B006Bk006B006B006Bk006Bk = b0070p00700070p0070pp0070p();
      }
      break;
    }
    this.bkkkkkkk006Bk.clear();
  }
}
