package uuuuuu;

import android.content.Context;
import com.db.pwcc.dbmobile.foundation.features.Feature;
import com.db.pwcc.dbmobile.secure.SecurityUtils;
import dagger.Module;
import dagger.Provides;
import javax.inject.Singleton;

@Module
public class gygygg
{
  public static int b006A006A006A006Ajj006A006A006A = 1;
  public static int b006Ajjj006Aj006A006A006A = 0;
  public static int bj006A006A006Ajj006A006A006A = 30;
  public static int bjjjj006Aj006A006A006A = 2;
  private final Context b006Aj006A006Ajj006A006A006A;
  
  public gygygg(Context paramContext)
  {
    this.b006Aj006A006Ajj006A006A006A = paramContext;
  }
  
  public static int b007000700070p00700070pppp()
  {
    return 1;
  }
  
  public static int b0070p0070p00700070pppp()
  {
    return 0;
  }
  
  public static int bp00700070p00700070pppp()
  {
    return 55;
  }
  
  public static int bpp0070p00700070pppp()
  {
    return 2;
  }
  
  @Provides
  public yygggy b007000700070007000700070pppp()
  {
    Context localContext = this.b006Aj006A006Ajj006A006A006A;
    int i = bj006A006A006Ajj006A006A006A;
    switch (i * (b006A006A006A006Ajj006A006A006A + i) % bjjjj006Aj006A006A006A)
    {
    default: 
      bj006A006A006Ajj006A006A006A = bp00700070p00700070pppp();
      if ((bj006A006A006Ajj006A006A006A + b006A006A006A006Ajj006A006A006A) * bj006A006A006Ajj006A006A006A % bjjjj006Aj006A006A006A != b006Ajjj006Aj006A006A006A)
      {
        bj006A006A006Ajj006A006A006A = bp00700070p00700070pppp();
        b006Ajjj006Aj006A006A006A = 32;
      }
      b006Ajjj006Aj006A006A006A = 95;
    }
    return (yygggy)localContext;
  }
  
  @Provides
  public mbmbbb b007000700070ppp0070ppp()
  {
    if ((bj006A006A006Ajj006A006A006A + b006A006A006A006Ajj006A006A006A) * bj006A006A006Ajj006A006A006A % bjjjj006Aj006A006A006A != b006Ajjj006Aj006A006A006A)
    {
      int i = bj006A006A006Ajj006A006A006A;
      switch (i * (b006A006A006A006Ajj006A006A006A + i) % bjjjj006Aj006A006A006A)
      {
      default: 
        bj006A006A006Ajj006A006A006A = bp00700070p00700070pppp();
        b006Ajjj006Aj006A006A006A = bp00700070p00700070pppp();
      }
      bj006A006A006Ajj006A006A006A = 32;
      b006Ajjj006Aj006A006A006A = 0;
    }
    return new uuuuup();
  }
  
  @Provides
  public Context b00700070p007000700070pppp()
  {
    if ((bj006A006A006Ajj006A006A006A + b006A006A006A006Ajj006A006A006A) * bj006A006A006Ajj006A006A006A % bjjjj006Aj006A006A006A != b0070p0070p00700070pppp())
    {
      bj006A006A006Ajj006A006A006A = bp00700070p00700070pppp();
      b006Ajjj006Aj006A006A006A = 36;
      int i = bj006A006A006Ajj006A006A006A;
      switch (i * (b006A006A006A006Ajj006A006A006A + i) % bjjjj006Aj006A006A006A)
      {
      default: 
        bj006A006A006Ajj006A006A006A = 95;
        b006Ajjj006Aj006A006A006A = bp00700070p00700070pppp();
      }
    }
    return this.b006Aj006A006Ajj006A006A006A;
  }
  
  /* Error */
  @Provides
  @Singleton
  public yyhhyh b00700070p0070pp0070ppp()
  {
    // Byte code:
    //   0: new 61	uuuuuu/ygyygy
    //   3: dup
    //   4: invokespecial 62	uuuuuu/ygyygy:<init>	()V
    //   7: astore_1
    //   8: new 64	java/util/HashMap
    //   11: dup
    //   12: invokespecial 65	java/util/HashMap:<init>	()V
    //   15: astore_2
    //   16: ldc 67
    //   18: ldc 69
    //   20: sipush 251
    //   23: sipush 151
    //   26: iconst_1
    //   27: invokestatic 75	xxxxxx/uxxxxx:bbbb0062b0062b0062b0062	(Ljava/lang/String;CCC)Ljava/lang/String;
    //   30: iconst_4
    //   31: anewarray 77	java/lang/Class
    //   34: dup
    //   35: iconst_0
    //   36: ldc 79
    //   38: aastore
    //   39: dup
    //   40: iconst_1
    //   41: getstatic 85	java/lang/Character:TYPE	Ljava/lang/Class;
    //   44: aastore
    //   45: dup
    //   46: iconst_2
    //   47: getstatic 85	java/lang/Character:TYPE	Ljava/lang/Class;
    //   50: aastore
    //   51: dup
    //   52: iconst_3
    //   53: getstatic 85	java/lang/Character:TYPE	Ljava/lang/Class;
    //   56: aastore
    //   57: invokevirtual 89	java/lang/Class:getMethod	(Ljava/lang/String;[Ljava/lang/Class;)Ljava/lang/reflect/Method;
    //   60: astore_3
    //   61: aload_3
    //   62: aconst_null
    //   63: iconst_4
    //   64: anewarray 4	java/lang/Object
    //   67: dup
    //   68: iconst_0
    //   69: ldc 91
    //   71: aastore
    //   72: dup
    //   73: iconst_1
    //   74: bipush 9
    //   76: invokestatic 95	java/lang/Character:valueOf	(C)Ljava/lang/Character;
    //   79: aastore
    //   80: dup
    //   81: iconst_2
    //   82: sipush 242
    //   85: invokestatic 95	java/lang/Character:valueOf	(C)Ljava/lang/Character;
    //   88: aastore
    //   89: dup
    //   90: iconst_3
    //   91: iconst_2
    //   92: invokestatic 95	java/lang/Character:valueOf	(C)Ljava/lang/Character;
    //   95: aastore
    //   96: invokevirtual 101	java/lang/reflect/Method:invoke	(Ljava/lang/Object;[Ljava/lang/Object;)Ljava/lang/Object;
    //   99: astore_3
    //   100: aload_3
    //   101: checkcast 79	java/lang/String
    //   104: astore_3
    //   105: ldc 67
    //   107: ldc 103
    //   109: sipush 189
    //   112: iconst_5
    //   113: invokestatic 107	xxxxxx/uxxxxx:bb00620062bb0062b0062b0062	(Ljava/lang/String;CC)Ljava/lang/String;
    //   116: iconst_4
    //   117: anewarray 77	java/lang/Class
    //   120: dup
    //   121: iconst_0
    //   122: ldc 79
    //   124: aastore
    //   125: dup
    //   126: iconst_1
    //   127: getstatic 85	java/lang/Character:TYPE	Ljava/lang/Class;
    //   130: aastore
    //   131: dup
    //   132: iconst_2
    //   133: getstatic 85	java/lang/Character:TYPE	Ljava/lang/Class;
    //   136: aastore
    //   137: dup
    //   138: iconst_3
    //   139: getstatic 85	java/lang/Character:TYPE	Ljava/lang/Class;
    //   142: aastore
    //   143: invokevirtual 89	java/lang/Class:getMethod	(Ljava/lang/String;[Ljava/lang/Class;)Ljava/lang/reflect/Method;
    //   146: astore 4
    //   148: aload 4
    //   150: aconst_null
    //   151: iconst_4
    //   152: anewarray 4	java/lang/Object
    //   155: dup
    //   156: iconst_0
    //   157: ldc 109
    //   159: aastore
    //   160: dup
    //   161: iconst_1
    //   162: sipush 153
    //   165: invokestatic 95	java/lang/Character:valueOf	(C)Ljava/lang/Character;
    //   168: aastore
    //   169: dup
    //   170: iconst_2
    //   171: bipush 55
    //   173: invokestatic 95	java/lang/Character:valueOf	(C)Ljava/lang/Character;
    //   176: aastore
    //   177: dup
    //   178: iconst_3
    //   179: iconst_1
    //   180: invokestatic 95	java/lang/Character:valueOf	(C)Ljava/lang/Character;
    //   183: aastore
    //   184: invokevirtual 101	java/lang/reflect/Method:invoke	(Ljava/lang/Object;[Ljava/lang/Object;)Ljava/lang/Object;
    //   187: astore 4
    //   189: aload_2
    //   190: aload_3
    //   191: aload 4
    //   193: checkcast 79	java/lang/String
    //   196: invokeinterface 115 3 0
    //   201: pop
    //   202: ldc 67
    //   204: ldc 117
    //   206: sipush 149
    //   209: iconst_4
    //   210: invokestatic 107	xxxxxx/uxxxxx:bb00620062bb0062b0062b0062	(Ljava/lang/String;CC)Ljava/lang/String;
    //   213: iconst_3
    //   214: anewarray 77	java/lang/Class
    //   217: dup
    //   218: iconst_0
    //   219: ldc 79
    //   221: aastore
    //   222: dup
    //   223: iconst_1
    //   224: getstatic 85	java/lang/Character:TYPE	Ljava/lang/Class;
    //   227: aastore
    //   228: dup
    //   229: iconst_2
    //   230: getstatic 85	java/lang/Character:TYPE	Ljava/lang/Class;
    //   233: aastore
    //   234: invokevirtual 89	java/lang/Class:getMethod	(Ljava/lang/String;[Ljava/lang/Class;)Ljava/lang/reflect/Method;
    //   237: astore_3
    //   238: aload_3
    //   239: aconst_null
    //   240: iconst_3
    //   241: anewarray 4	java/lang/Object
    //   244: dup
    //   245: iconst_0
    //   246: ldc 119
    //   248: aastore
    //   249: dup
    //   250: iconst_1
    //   251: bipush 121
    //   253: invokestatic 95	java/lang/Character:valueOf	(C)Ljava/lang/Character;
    //   256: aastore
    //   257: dup
    //   258: iconst_2
    //   259: iconst_5
    //   260: invokestatic 95	java/lang/Character:valueOf	(C)Ljava/lang/Character;
    //   263: aastore
    //   264: invokevirtual 101	java/lang/reflect/Method:invoke	(Ljava/lang/Object;[Ljava/lang/Object;)Ljava/lang/Object;
    //   267: astore_3
    //   268: aload_3
    //   269: checkcast 79	java/lang/String
    //   272: astore_3
    //   273: invokestatic 40	uuuuuu/gygygg:bp00700070p00700070pppp	()I
    //   276: getstatic 36	uuuuuu/gygygg:b006A006A006A006Ajj006A006A006A	I
    //   279: iadd
    //   280: invokestatic 40	uuuuuu/gygygg:bp00700070p00700070pppp	()I
    //   283: imul
    //   284: getstatic 38	uuuuuu/gygygg:bjjjj006Aj006A006A006A	I
    //   287: irem
    //   288: getstatic 42	uuuuuu/gygygg:b006Ajjj006Aj006A006A006A	I
    //   291: if_icmpeq +45 -> 336
    //   294: getstatic 34	uuuuuu/gygygg:bj006A006A006Ajj006A006A006A	I
    //   297: getstatic 36	uuuuuu/gygygg:b006A006A006A006Ajj006A006A006A	I
    //   300: iadd
    //   301: getstatic 34	uuuuuu/gygygg:bj006A006A006Ajj006A006A006A	I
    //   304: imul
    //   305: getstatic 38	uuuuuu/gygygg:bjjjj006Aj006A006A006A	I
    //   308: irem
    //   309: getstatic 42	uuuuuu/gygygg:b006Ajjj006Aj006A006A006A	I
    //   312: if_icmpeq +14 -> 326
    //   315: invokestatic 40	uuuuuu/gygygg:bp00700070p00700070pppp	()I
    //   318: putstatic 34	uuuuuu/gygygg:bj006A006A006Ajj006A006A006A	I
    //   321: bipush 81
    //   323: putstatic 42	uuuuuu/gygygg:b006Ajjj006Aj006A006A006A	I
    //   326: bipush 23
    //   328: putstatic 34	uuuuuu/gygygg:bj006A006A006Ajj006A006A006A	I
    //   331: bipush 47
    //   333: putstatic 42	uuuuuu/gygygg:b006Ajjj006Aj006A006A006A	I
    //   336: ldc 67
    //   338: ldc 121
    //   340: bipush 93
    //   342: iconst_2
    //   343: invokestatic 107	xxxxxx/uxxxxx:bb00620062bb0062b0062b0062	(Ljava/lang/String;CC)Ljava/lang/String;
    //   346: iconst_3
    //   347: anewarray 77	java/lang/Class
    //   350: dup
    //   351: iconst_0
    //   352: ldc 79
    //   354: aastore
    //   355: dup
    //   356: iconst_1
    //   357: getstatic 85	java/lang/Character:TYPE	Ljava/lang/Class;
    //   360: aastore
    //   361: dup
    //   362: iconst_2
    //   363: getstatic 85	java/lang/Character:TYPE	Ljava/lang/Class;
    //   366: aastore
    //   367: invokevirtual 89	java/lang/Class:getMethod	(Ljava/lang/String;[Ljava/lang/Class;)Ljava/lang/reflect/Method;
    //   370: astore 4
    //   372: aload 4
    //   374: aconst_null
    //   375: iconst_3
    //   376: anewarray 4	java/lang/Object
    //   379: dup
    //   380: iconst_0
    //   381: ldc 123
    //   383: aastore
    //   384: dup
    //   385: iconst_1
    //   386: sipush 132
    //   389: invokestatic 95	java/lang/Character:valueOf	(C)Ljava/lang/Character;
    //   392: aastore
    //   393: dup
    //   394: iconst_2
    //   395: iconst_5
    //   396: invokestatic 95	java/lang/Character:valueOf	(C)Ljava/lang/Character;
    //   399: aastore
    //   400: invokevirtual 101	java/lang/reflect/Method:invoke	(Ljava/lang/Object;[Ljava/lang/Object;)Ljava/lang/Object;
    //   403: astore 4
    //   405: aload_2
    //   406: aload_3
    //   407: aload 4
    //   409: checkcast 79	java/lang/String
    //   412: invokeinterface 115 3 0
    //   417: pop
    //   418: aload_1
    //   419: aload_2
    //   420: invokevirtual 127	uuuuuu/ygyygy:bpp0070p0070ppp0070p	(Ljava/util/Map;)Luuuuuu/ygyygy;
    //   423: pop
    //   424: ldc 67
    //   426: ldc -127
    //   428: bipush 93
    //   430: iconst_4
    //   431: invokestatic 107	xxxxxx/uxxxxx:bb00620062bb0062b0062b0062	(Ljava/lang/String;CC)Ljava/lang/String;
    //   434: iconst_3
    //   435: anewarray 77	java/lang/Class
    //   438: dup
    //   439: iconst_0
    //   440: ldc 79
    //   442: aastore
    //   443: dup
    //   444: iconst_1
    //   445: getstatic 85	java/lang/Character:TYPE	Ljava/lang/Class;
    //   448: aastore
    //   449: dup
    //   450: iconst_2
    //   451: getstatic 85	java/lang/Character:TYPE	Ljava/lang/Class;
    //   454: aastore
    //   455: invokevirtual 89	java/lang/Class:getMethod	(Ljava/lang/String;[Ljava/lang/Class;)Ljava/lang/reflect/Method;
    //   458: astore_2
    //   459: aload_2
    //   460: aconst_null
    //   461: iconst_3
    //   462: anewarray 4	java/lang/Object
    //   465: dup
    //   466: iconst_0
    //   467: ldc -125
    //   469: aastore
    //   470: dup
    //   471: iconst_1
    //   472: bipush 25
    //   474: invokestatic 95	java/lang/Character:valueOf	(C)Ljava/lang/Character;
    //   477: aastore
    //   478: dup
    //   479: iconst_2
    //   480: iconst_2
    //   481: invokestatic 95	java/lang/Character:valueOf	(C)Ljava/lang/Character;
    //   484: aastore
    //   485: invokevirtual 101	java/lang/reflect/Method:invoke	(Ljava/lang/Object;[Ljava/lang/Object;)Ljava/lang/Object;
    //   488: astore_2
    //   489: aload_1
    //   490: aload_2
    //   491: checkcast 79	java/lang/String
    //   494: invokevirtual 135	uuuuuu/ygyygy:bp00700070p0070ppp0070p	(Ljava/lang/String;)Luuuuuu/ygyygy;
    //   497: pop
    //   498: new 137	uuuuuu/yyhhyh
    //   501: dup
    //   502: aload_1
    //   503: invokespecial 140	uuuuuu/yyhhyh:<init>	(Luuuuuu/ygyygy;)V
    //   506: areturn
    //   507: astore_1
    //   508: aload_1
    //   509: invokevirtual 144	java/lang/reflect/InvocationTargetException:getCause	()Ljava/lang/Throwable;
    //   512: athrow
    //   513: astore_1
    //   514: aload_1
    //   515: invokevirtual 144	java/lang/reflect/InvocationTargetException:getCause	()Ljava/lang/Throwable;
    //   518: athrow
    //   519: astore_1
    //   520: aload_1
    //   521: invokevirtual 144	java/lang/reflect/InvocationTargetException:getCause	()Ljava/lang/Throwable;
    //   524: athrow
    //   525: astore_1
    //   526: aload_1
    //   527: invokevirtual 144	java/lang/reflect/InvocationTargetException:getCause	()Ljava/lang/Throwable;
    //   530: athrow
    //   531: astore_1
    //   532: aload_1
    //   533: invokevirtual 144	java/lang/reflect/InvocationTargetException:getCause	()Ljava/lang/Throwable;
    //   536: athrow
    // Local variable table:
    //   start	length	slot	name	signature
    //   0	537	0	this	gygygg
    //   7	496	1	localYgyygy	ygyygy
    //   507	2	1	localInvocationTargetException1	java.lang.reflect.InvocationTargetException
    //   513	2	1	localInvocationTargetException2	java.lang.reflect.InvocationTargetException
    //   519	2	1	localInvocationTargetException3	java.lang.reflect.InvocationTargetException
    //   525	2	1	localInvocationTargetException4	java.lang.reflect.InvocationTargetException
    //   531	2	1	localInvocationTargetException5	java.lang.reflect.InvocationTargetException
    //   15	476	2	localObject1	Object
    //   60	347	3	localObject2	Object
    //   146	262	4	localObject3	Object
    // Exception table:
    //   from	to	target	type
    //   61	100	507	java/lang/reflect/InvocationTargetException
    //   148	189	513	java/lang/reflect/InvocationTargetException
    //   238	268	519	java/lang/reflect/InvocationTargetException
    //   372	405	525	java/lang/reflect/InvocationTargetException
    //   459	489	531	java/lang/reflect/InvocationTargetException
  }
  
  @Provides
  public vvppvv b00700070pppp0070ppp()
  {
    int i = bj006A006A006Ajj006A006A006A;
    switch (i * (b006A006A006A006Ajj006A006A006A + i) % bjjjj006Aj006A006A006A)
    {
    default: 
      bj006A006A006Ajj006A006A006A = bp00700070p00700070pppp();
      b006Ajjj006Aj006A006A006A = bp00700070p00700070pppp();
    }
    oloooo localOloooo = new oloooo();
    i = bj006A006A006Ajj006A006A006A;
    switch (i * (b006A006A006A006Ajj006A006A006A + i) % bjjjj006Aj006A006A006A)
    {
    default: 
      bj006A006A006Ajj006A006A006A = bp00700070p00700070pppp();
      b006Ajjj006Aj006A006A006A = 58;
    }
    return localOloooo;
  }
  
  @Provides
  @Singleton
  public ygggyy b0070p0070007000700070pppp(Context paramContext)
  {
    if ((bp00700070p00700070pppp() + b006A006A006A006Ajj006A006A006A) * bp00700070p00700070pppp() % bjjjj006Aj006A006A006A != b006Ajjj006Aj006A006A006A)
    {
      int i = bj006A006A006Ajj006A006A006A;
      switch (i * (b006A006A006A006Ajj006A006A006A + i) % bjjjj006Aj006A006A006A)
      {
      default: 
        bj006A006A006Ajj006A006A006A = bp00700070p00700070pppp();
        b006Ajjj006Aj006A006A006A = 16;
      }
      bj006A006A006Ajj006A006A006A = bp00700070p00700070pppp();
      b006Ajjj006Aj006A006A006A = 41;
    }
    return new ygggyy(paramContext, new ygygyy());
  }
  
  @Provides
  @Singleton
  public gyygyy b0070p0070ppp0070ppp()
  {
    gyygyy localGyygyy = new gyygyy(new ygygyy());
    int i = bp00700070p00700070pppp();
    int j = b006A006A006A006Ajj006A006A006A;
    int k = bp00700070p00700070pppp();
    if ((bp00700070p00700070pppp() + b006A006A006A006Ajj006A006A006A) * bp00700070p00700070pppp() % bjjjj006Aj006A006A006A != b006Ajjj006Aj006A006A006A)
    {
      bj006A006A006Ajj006A006A006A = 13;
      b006Ajjj006Aj006A006A006A = 56;
    }
    if ((i + j) * k % bjjjj006Aj006A006A006A != b006Ajjj006Aj006A006A006A)
    {
      bj006A006A006Ajj006A006A006A = 22;
      b006Ajjj006Aj006A006A006A = 35;
    }
    return localGyygyy;
  }
  
  @Provides
  public xxsxxs b0070pp007000700070pppp()
  {
    xxsxxs localXxsxxs = new xxsxxs();
    if ((bj006A006A006Ajj006A006A006A + b006A006A006A006Ajj006A006A006A) * bj006A006A006Ajj006A006A006A % bjjjj006Aj006A006A006A != b0070p0070p00700070pppp())
    {
      if ((bj006A006A006Ajj006A006A006A + b006A006A006A006Ajj006A006A006A) * bj006A006A006Ajj006A006A006A % bjjjj006Aj006A006A006A != b006Ajjj006Aj006A006A006A)
      {
        bj006A006A006Ajj006A006A006A = bp00700070p00700070pppp();
        b006Ajjj006Aj006A006A006A = bp00700070p00700070pppp();
      }
      bj006A006A006Ajj006A006A006A = bp00700070p00700070pppp();
      b006Ajjj006Aj006A006A006A = bp00700070p00700070pppp();
    }
    return localXxsxxs;
  }
  
  @Provides
  public ooooon b0070pp0070pp0070ppp()
  {
    int i = bj006A006A006Ajj006A006A006A;
    switch (i * (b006A006A006A006Ajj006A006A006A + i) % bjjjj006Aj006A006A006A)
    {
    default: 
      bj006A006A006Ajj006A006A006A = 64;
      b006Ajjj006Aj006A006A006A = 97;
    }
    ooooon localOoooon = ooooon.bk006Bkkkk006Bkk006B();
    if ((bj006A006A006Ajj006A006A006A + b006A006A006A006Ajj006A006A006A) * bj006A006A006Ajj006A006A006A % bjjjj006Aj006A006A006A != b006Ajjj006Aj006A006A006A)
    {
      bj006A006A006Ajj006A006A006A = 17;
      b006Ajjj006Aj006A006A006A = 21;
    }
    return localOoooon;
  }
  
  @Provides
  public qpqqqq b0070ppppp0070ppp(qqpqqq paramQqpqqq)
  {
    paramQqpqqq = (qpqqqq)paramQqpqqq.b006Bk006Bk006B006Bk006Bkk(hheeeh.class);
    if ((bj006A006A006Ajj006A006A006A + b006A006A006A006Ajj006A006A006A) * bj006A006A006Ajj006A006A006A % bjjjj006Aj006A006A006A != b006Ajjj006Aj006A006A006A)
    {
      int i = bp00700070p00700070pppp();
      if ((bj006A006A006Ajj006A006A006A + b006A006A006A006Ajj006A006A006A) * bj006A006A006Ajj006A006A006A % bjjjj006Aj006A006A006A != b006Ajjj006Aj006A006A006A)
      {
        bj006A006A006Ajj006A006A006A = 26;
        b006Ajjj006Aj006A006A006A = 71;
      }
      bj006A006A006Ajj006A006A006A = i;
      b006Ajjj006Aj006A006A006A = bp00700070p00700070pppp();
    }
    return paramQqpqqq;
  }
  
  @Provides
  @Singleton
  public xxxsss bp00700070007000700070pppp()
  {
    int i = bj006A006A006Ajj006A006A006A;
    switch (i * (b006A006A006A006Ajj006A006A006A + i) % bjjjj006Aj006A006A006A)
    {
    default: 
      if ((bj006A006A006Ajj006A006A006A + b006A006A006A006Ajj006A006A006A) * bj006A006A006Ajj006A006A006A % bpp0070p00700070pppp() != b006Ajjj006Aj006A006A006A)
      {
        bj006A006A006Ajj006A006A006A = 29;
        b006Ajjj006Aj006A006A006A = bp00700070p00700070pppp();
      }
      bj006A006A006Ajj006A006A006A = bp00700070p00700070pppp();
      b006Ajjj006Aj006A006A006A = 65;
    }
    return new xxxsss();
  }
  
  /* Error */
  @Provides
  @Singleton
  public yyygyy bp00700070ppp0070ppp()
  {
    // Byte code:
    //   0: new 155	uuuuuu/ygygyy
    //   3: dup
    //   4: invokespecial 156	uuuuuu/ygygyy:<init>	()V
    //   7: astore_2
    //   8: getstatic 34	uuuuuu/gygygg:bj006A006A006Ajj006A006A006A	I
    //   11: istore_1
    //   12: iload_1
    //   13: getstatic 36	uuuuuu/gygygg:b006A006A006A006Ajj006A006A006A	I
    //   16: iload_1
    //   17: iadd
    //   18: imul
    //   19: getstatic 38	uuuuuu/gygygg:bjjjj006Aj006A006A006A	I
    //   22: irem
    //   23: tableswitch	default:+17->40, 0:+28->51
    //   40: bipush 77
    //   42: putstatic 34	uuuuuu/gygygg:bj006A006A006Ajj006A006A006A	I
    //   45: invokestatic 40	uuuuuu/gygygg:bp00700070p00700070pppp	()I
    //   48: putstatic 42	uuuuuu/gygygg:b006Ajjj006Aj006A006A006A	I
    //   51: new 64	java/util/HashMap
    //   54: dup
    //   55: invokespecial 65	java/util/HashMap:<init>	()V
    //   58: astore_3
    //   59: ldc 67
    //   61: ldc -57
    //   63: sipush 253
    //   66: sipush 246
    //   69: iconst_1
    //   70: invokestatic 75	xxxxxx/uxxxxx:bbbb0062b0062b0062b0062	(Ljava/lang/String;CCC)Ljava/lang/String;
    //   73: iconst_4
    //   74: anewarray 77	java/lang/Class
    //   77: dup
    //   78: iconst_0
    //   79: ldc 79
    //   81: aastore
    //   82: dup
    //   83: iconst_1
    //   84: getstatic 85	java/lang/Character:TYPE	Ljava/lang/Class;
    //   87: aastore
    //   88: dup
    //   89: iconst_2
    //   90: getstatic 85	java/lang/Character:TYPE	Ljava/lang/Class;
    //   93: aastore
    //   94: dup
    //   95: iconst_3
    //   96: getstatic 85	java/lang/Character:TYPE	Ljava/lang/Class;
    //   99: aastore
    //   100: invokevirtual 89	java/lang/Class:getMethod	(Ljava/lang/String;[Ljava/lang/Class;)Ljava/lang/reflect/Method;
    //   103: astore 4
    //   105: aload 4
    //   107: aconst_null
    //   108: iconst_4
    //   109: anewarray 4	java/lang/Object
    //   112: dup
    //   113: iconst_0
    //   114: ldc -55
    //   116: aastore
    //   117: dup
    //   118: iconst_1
    //   119: sipush 178
    //   122: invokestatic 95	java/lang/Character:valueOf	(C)Ljava/lang/Character;
    //   125: aastore
    //   126: dup
    //   127: iconst_2
    //   128: sipush 184
    //   131: invokestatic 95	java/lang/Character:valueOf	(C)Ljava/lang/Character;
    //   134: aastore
    //   135: dup
    //   136: iconst_3
    //   137: iconst_1
    //   138: invokestatic 95	java/lang/Character:valueOf	(C)Ljava/lang/Character;
    //   141: aastore
    //   142: invokevirtual 101	java/lang/reflect/Method:invoke	(Ljava/lang/Object;[Ljava/lang/Object;)Ljava/lang/Object;
    //   145: astore 4
    //   147: aload 4
    //   149: checkcast 79	java/lang/String
    //   152: astore 4
    //   154: ldc 67
    //   156: ldc -53
    //   158: sipush 233
    //   161: sipush 133
    //   164: iconst_3
    //   165: invokestatic 75	xxxxxx/uxxxxx:bbbb0062b0062b0062b0062	(Ljava/lang/String;CCC)Ljava/lang/String;
    //   168: iconst_3
    //   169: anewarray 77	java/lang/Class
    //   172: dup
    //   173: iconst_0
    //   174: ldc 79
    //   176: aastore
    //   177: dup
    //   178: iconst_1
    //   179: getstatic 85	java/lang/Character:TYPE	Ljava/lang/Class;
    //   182: aastore
    //   183: dup
    //   184: iconst_2
    //   185: getstatic 85	java/lang/Character:TYPE	Ljava/lang/Class;
    //   188: aastore
    //   189: invokevirtual 89	java/lang/Class:getMethod	(Ljava/lang/String;[Ljava/lang/Class;)Ljava/lang/reflect/Method;
    //   192: astore 5
    //   194: aload 5
    //   196: aconst_null
    //   197: iconst_3
    //   198: anewarray 4	java/lang/Object
    //   201: dup
    //   202: iconst_0
    //   203: ldc -51
    //   205: aastore
    //   206: dup
    //   207: iconst_1
    //   208: bipush 65
    //   210: invokestatic 95	java/lang/Character:valueOf	(C)Ljava/lang/Character;
    //   213: aastore
    //   214: dup
    //   215: iconst_2
    //   216: iconst_5
    //   217: invokestatic 95	java/lang/Character:valueOf	(C)Ljava/lang/Character;
    //   220: aastore
    //   221: invokevirtual 101	java/lang/reflect/Method:invoke	(Ljava/lang/Object;[Ljava/lang/Object;)Ljava/lang/Object;
    //   224: astore 5
    //   226: aload_3
    //   227: aload 4
    //   229: aload 5
    //   231: checkcast 79	java/lang/String
    //   234: invokeinterface 115 3 0
    //   239: pop
    //   240: ldc 67
    //   242: ldc -49
    //   244: bipush 87
    //   246: iconst_0
    //   247: invokestatic 107	xxxxxx/uxxxxx:bb00620062bb0062b0062b0062	(Ljava/lang/String;CC)Ljava/lang/String;
    //   250: iconst_3
    //   251: anewarray 77	java/lang/Class
    //   254: dup
    //   255: iconst_0
    //   256: ldc 79
    //   258: aastore
    //   259: dup
    //   260: iconst_1
    //   261: getstatic 85	java/lang/Character:TYPE	Ljava/lang/Class;
    //   264: aastore
    //   265: dup
    //   266: iconst_2
    //   267: getstatic 85	java/lang/Character:TYPE	Ljava/lang/Class;
    //   270: aastore
    //   271: invokevirtual 89	java/lang/Class:getMethod	(Ljava/lang/String;[Ljava/lang/Class;)Ljava/lang/reflect/Method;
    //   274: astore 4
    //   276: aload 4
    //   278: aconst_null
    //   279: iconst_3
    //   280: anewarray 4	java/lang/Object
    //   283: dup
    //   284: iconst_0
    //   285: ldc -47
    //   287: aastore
    //   288: dup
    //   289: iconst_1
    //   290: bipush 122
    //   292: invokestatic 95	java/lang/Character:valueOf	(C)Ljava/lang/Character;
    //   295: aastore
    //   296: dup
    //   297: iconst_2
    //   298: iconst_5
    //   299: invokestatic 95	java/lang/Character:valueOf	(C)Ljava/lang/Character;
    //   302: aastore
    //   303: invokevirtual 101	java/lang/reflect/Method:invoke	(Ljava/lang/Object;[Ljava/lang/Object;)Ljava/lang/Object;
    //   306: astore 4
    //   308: aload 4
    //   310: checkcast 79	java/lang/String
    //   313: astore 4
    //   315: ldc 67
    //   317: ldc -45
    //   319: sipush 152
    //   322: iconst_2
    //   323: invokestatic 107	xxxxxx/uxxxxx:bb00620062bb0062b0062b0062	(Ljava/lang/String;CC)Ljava/lang/String;
    //   326: iconst_4
    //   327: anewarray 77	java/lang/Class
    //   330: dup
    //   331: iconst_0
    //   332: ldc 79
    //   334: aastore
    //   335: dup
    //   336: iconst_1
    //   337: getstatic 85	java/lang/Character:TYPE	Ljava/lang/Class;
    //   340: aastore
    //   341: dup
    //   342: iconst_2
    //   343: getstatic 85	java/lang/Character:TYPE	Ljava/lang/Class;
    //   346: aastore
    //   347: dup
    //   348: iconst_3
    //   349: getstatic 85	java/lang/Character:TYPE	Ljava/lang/Class;
    //   352: aastore
    //   353: invokevirtual 89	java/lang/Class:getMethod	(Ljava/lang/String;[Ljava/lang/Class;)Ljava/lang/reflect/Method;
    //   356: astore 5
    //   358: aload 5
    //   360: aconst_null
    //   361: iconst_4
    //   362: anewarray 4	java/lang/Object
    //   365: dup
    //   366: iconst_0
    //   367: ldc -43
    //   369: aastore
    //   370: dup
    //   371: iconst_1
    //   372: bipush 57
    //   374: invokestatic 95	java/lang/Character:valueOf	(C)Ljava/lang/Character;
    //   377: aastore
    //   378: dup
    //   379: iconst_2
    //   380: sipush 235
    //   383: invokestatic 95	java/lang/Character:valueOf	(C)Ljava/lang/Character;
    //   386: aastore
    //   387: dup
    //   388: iconst_3
    //   389: iconst_1
    //   390: invokestatic 95	java/lang/Character:valueOf	(C)Ljava/lang/Character;
    //   393: aastore
    //   394: invokevirtual 101	java/lang/reflect/Method:invoke	(Ljava/lang/Object;[Ljava/lang/Object;)Ljava/lang/Object;
    //   397: astore 5
    //   399: aload_3
    //   400: aload 4
    //   402: aload 5
    //   404: checkcast 79	java/lang/String
    //   407: invokeinterface 115 3 0
    //   412: pop
    //   413: aload_2
    //   414: aload_3
    //   415: invokevirtual 214	uuuuuu/ygygyy:bpp0070p0070ppp0070p	(Ljava/util/Map;)Luuuuuu/ygyygy;
    //   418: pop
    //   419: new 216	uuuuuu/yyygyy
    //   422: dup
    //   423: aload_2
    //   424: invokespecial 217	uuuuuu/yyygyy:<init>	(Luuuuuu/ygyygy;)V
    //   427: astore_2
    //   428: getstatic 34	uuuuuu/gygygg:bj006A006A006Ajj006A006A006A	I
    //   431: getstatic 36	uuuuuu/gygygg:b006A006A006A006Ajj006A006A006A	I
    //   434: iadd
    //   435: getstatic 34	uuuuuu/gygygg:bj006A006A006Ajj006A006A006A	I
    //   438: imul
    //   439: getstatic 38	uuuuuu/gygygg:bjjjj006Aj006A006A006A	I
    //   442: irem
    //   443: getstatic 42	uuuuuu/gygygg:b006Ajjj006Aj006A006A006A	I
    //   446: if_icmpeq +14 -> 460
    //   449: bipush 16
    //   451: putstatic 34	uuuuuu/gygygg:bj006A006A006Ajj006A006A006A	I
    //   454: invokestatic 40	uuuuuu/gygygg:bp00700070p00700070pppp	()I
    //   457: putstatic 42	uuuuuu/gygygg:b006Ajjj006Aj006A006A006A	I
    //   460: aload_2
    //   461: areturn
    //   462: astore_2
    //   463: aload_2
    //   464: invokevirtual 144	java/lang/reflect/InvocationTargetException:getCause	()Ljava/lang/Throwable;
    //   467: athrow
    //   468: astore_2
    //   469: aload_2
    //   470: invokevirtual 144	java/lang/reflect/InvocationTargetException:getCause	()Ljava/lang/Throwable;
    //   473: athrow
    //   474: astore_2
    //   475: aload_2
    //   476: invokevirtual 144	java/lang/reflect/InvocationTargetException:getCause	()Ljava/lang/Throwable;
    //   479: athrow
    //   480: astore_2
    //   481: aload_2
    //   482: invokevirtual 144	java/lang/reflect/InvocationTargetException:getCause	()Ljava/lang/Throwable;
    //   485: athrow
    // Local variable table:
    //   start	length	slot	name	signature
    //   0	486	0	this	gygygg
    //   11	8	1	i	int
    //   7	454	2	localObject1	Object
    //   462	2	2	localInvocationTargetException1	java.lang.reflect.InvocationTargetException
    //   468	2	2	localInvocationTargetException2	java.lang.reflect.InvocationTargetException
    //   474	2	2	localInvocationTargetException3	java.lang.reflect.InvocationTargetException
    //   480	2	2	localInvocationTargetException4	java.lang.reflect.InvocationTargetException
    //   58	357	3	localHashMap	java.util.HashMap
    //   103	298	4	localObject2	Object
    //   192	211	5	localObject3	Object
    // Exception table:
    //   from	to	target	type
    //   276	308	462	java/lang/reflect/InvocationTargetException
    //   358	399	468	java/lang/reflect/InvocationTargetException
    //   194	226	474	java/lang/reflect/InvocationTargetException
    //   105	147	480	java/lang/reflect/InvocationTargetException
  }
  
  @Provides
  public bmmbbb bp0070p007000700070pppp()
  {
    pppppu localPppppu = new pppppu();
    int i = bj006A006A006Ajj006A006A006A;
    switch (i * (b006A006A006A006Ajj006A006A006A + i) % bjjjj006Aj006A006A006A)
    {
    default: 
      bj006A006A006Ajj006A006A006A = bp00700070p00700070pppp();
      b006Ajjj006Aj006A006A006A = 52;
      if ((bj006A006A006Ajj006A006A006A + b006A006A006A006Ajj006A006A006A) * bj006A006A006Ajj006A006A006A % bjjjj006Aj006A006A006A != b006Ajjj006Aj006A006A006A)
      {
        bj006A006A006Ajj006A006A006A = 41;
        b006Ajjj006Aj006A006A006A = 55;
      }
      break;
    }
    return localPppppu;
  }
  
  /* Error */
  @Provides
  @Singleton
  public yggyyy bp0070p0070pp0070ppp()
  {
    // Byte code:
    //   0: getstatic 34	uuuuuu/gygygg:bj006A006A006Ajj006A006A006A	I
    //   3: istore_1
    //   4: iload_1
    //   5: getstatic 36	uuuuuu/gygygg:b006A006A006A006Ajj006A006A006A	I
    //   8: iload_1
    //   9: iadd
    //   10: imul
    //   11: getstatic 38	uuuuuu/gygygg:bjjjj006Aj006A006A006A	I
    //   14: irem
    //   15: tableswitch	default:+17->32, 0:+59->74
    //   32: invokestatic 40	uuuuuu/gygygg:bp00700070p00700070pppp	()I
    //   35: getstatic 36	uuuuuu/gygygg:b006A006A006A006Ajj006A006A006A	I
    //   38: iadd
    //   39: invokestatic 40	uuuuuu/gygygg:bp00700070p00700070pppp	()I
    //   42: imul
    //   43: getstatic 38	uuuuuu/gygygg:bjjjj006Aj006A006A006A	I
    //   46: irem
    //   47: getstatic 42	uuuuuu/gygygg:b006Ajjj006Aj006A006A006A	I
    //   50: if_icmpeq +14 -> 64
    //   53: invokestatic 40	uuuuuu/gygygg:bp00700070p00700070pppp	()I
    //   56: putstatic 34	uuuuuu/gygygg:bj006A006A006Ajj006A006A006A	I
    //   59: bipush 43
    //   61: putstatic 42	uuuuuu/gygygg:b006Ajjj006Aj006A006A006A	I
    //   64: bipush 73
    //   66: putstatic 34	uuuuuu/gygygg:bj006A006A006Ajj006A006A006A	I
    //   69: bipush 92
    //   71: putstatic 42	uuuuuu/gygygg:b006Ajjj006Aj006A006A006A	I
    //   74: new 61	uuuuuu/ygyygy
    //   77: dup
    //   78: invokespecial 62	uuuuuu/ygyygy:<init>	()V
    //   81: astore_2
    //   82: ldc 67
    //   84: ldc 103
    //   86: sipush 189
    //   89: iconst_5
    //   90: invokestatic 107	xxxxxx/uxxxxx:bb00620062bb0062b0062b0062	(Ljava/lang/String;CC)Ljava/lang/String;
    //   93: iconst_4
    //   94: anewarray 77	java/lang/Class
    //   97: dup
    //   98: iconst_0
    //   99: ldc 79
    //   101: aastore
    //   102: dup
    //   103: iconst_1
    //   104: getstatic 85	java/lang/Character:TYPE	Ljava/lang/Class;
    //   107: aastore
    //   108: dup
    //   109: iconst_2
    //   110: getstatic 85	java/lang/Character:TYPE	Ljava/lang/Class;
    //   113: aastore
    //   114: dup
    //   115: iconst_3
    //   116: getstatic 85	java/lang/Character:TYPE	Ljava/lang/Class;
    //   119: aastore
    //   120: invokevirtual 89	java/lang/Class:getMethod	(Ljava/lang/String;[Ljava/lang/Class;)Ljava/lang/reflect/Method;
    //   123: astore_3
    //   124: aload_3
    //   125: aconst_null
    //   126: iconst_4
    //   127: anewarray 4	java/lang/Object
    //   130: dup
    //   131: iconst_0
    //   132: ldc -30
    //   134: aastore
    //   135: dup
    //   136: iconst_1
    //   137: bipush 48
    //   139: invokestatic 95	java/lang/Character:valueOf	(C)Ljava/lang/Character;
    //   142: aastore
    //   143: dup
    //   144: iconst_2
    //   145: bipush 54
    //   147: invokestatic 95	java/lang/Character:valueOf	(C)Ljava/lang/Character;
    //   150: aastore
    //   151: dup
    //   152: iconst_3
    //   153: iconst_0
    //   154: invokestatic 95	java/lang/Character:valueOf	(C)Ljava/lang/Character;
    //   157: aastore
    //   158: invokevirtual 101	java/lang/reflect/Method:invoke	(Ljava/lang/Object;[Ljava/lang/Object;)Ljava/lang/Object;
    //   161: astore_3
    //   162: aload_2
    //   163: aload_3
    //   164: checkcast 79	java/lang/String
    //   167: invokevirtual 135	uuuuuu/ygyygy:bp00700070p0070ppp0070p	(Ljava/lang/String;)Luuuuuu/ygyygy;
    //   170: pop
    //   171: ldc 67
    //   173: ldc -28
    //   175: bipush 7
    //   177: iconst_0
    //   178: invokestatic 107	xxxxxx/uxxxxx:bb00620062bb0062b0062b0062	(Ljava/lang/String;CC)Ljava/lang/String;
    //   181: iconst_3
    //   182: anewarray 77	java/lang/Class
    //   185: dup
    //   186: iconst_0
    //   187: ldc 79
    //   189: aastore
    //   190: dup
    //   191: iconst_1
    //   192: getstatic 85	java/lang/Character:TYPE	Ljava/lang/Class;
    //   195: aastore
    //   196: dup
    //   197: iconst_2
    //   198: getstatic 85	java/lang/Character:TYPE	Ljava/lang/Class;
    //   201: aastore
    //   202: invokevirtual 89	java/lang/Class:getMethod	(Ljava/lang/String;[Ljava/lang/Class;)Ljava/lang/reflect/Method;
    //   205: astore_3
    //   206: aload_3
    //   207: aconst_null
    //   208: iconst_3
    //   209: anewarray 4	java/lang/Object
    //   212: dup
    //   213: iconst_0
    //   214: ldc -26
    //   216: aastore
    //   217: dup
    //   218: iconst_1
    //   219: sipush 130
    //   222: invokestatic 95	java/lang/Character:valueOf	(C)Ljava/lang/Character;
    //   225: aastore
    //   226: dup
    //   227: iconst_2
    //   228: iconst_4
    //   229: invokestatic 95	java/lang/Character:valueOf	(C)Ljava/lang/Character;
    //   232: aastore
    //   233: invokevirtual 101	java/lang/reflect/Method:invoke	(Ljava/lang/Object;[Ljava/lang/Object;)Ljava/lang/Object;
    //   236: astore_3
    //   237: aload_2
    //   238: aload_3
    //   239: checkcast 79	java/lang/String
    //   242: invokevirtual 233	uuuuuu/ygyygy:b0070p0070p0070ppp0070p	(Ljava/lang/String;)Luuuuuu/ygyygy;
    //   245: pop
    //   246: new 235	uuuuuu/yggyyy
    //   249: dup
    //   250: aload_2
    //   251: invokespecial 236	uuuuuu/yggyyy:<init>	(Luuuuuu/ygyygy;)V
    //   254: areturn
    //   255: astore_2
    //   256: aload_2
    //   257: invokevirtual 144	java/lang/reflect/InvocationTargetException:getCause	()Ljava/lang/Throwable;
    //   260: athrow
    //   261: astore_2
    //   262: aload_2
    //   263: invokevirtual 144	java/lang/reflect/InvocationTargetException:getCause	()Ljava/lang/Throwable;
    //   266: athrow
    // Local variable table:
    //   start	length	slot	name	signature
    //   0	267	0	this	gygygg
    //   3	8	1	i	int
    //   81	170	2	localYgyygy	ygyygy
    //   255	2	2	localInvocationTargetException1	java.lang.reflect.InvocationTargetException
    //   261	2	2	localInvocationTargetException2	java.lang.reflect.InvocationTargetException
    //   123	116	3	localObject	Object
    // Exception table:
    //   from	to	target	type
    //   124	162	255	java/lang/reflect/InvocationTargetException
    //   206	237	261	java/lang/reflect/InvocationTargetException
  }
  
  @Provides
  public vpppvv bp0070pppp0070ppp()
  {
    int i = bj006A006A006Ajj006A006A006A;
    switch (i * (b006A006A006A006Ajj006A006A006A + i) % bjjjj006Aj006A006A006A)
    {
    default: 
      bj006A006A006Ajj006A006A006A = bp00700070p00700070pppp();
      b006Ajjj006Aj006A006A006A = bp00700070p00700070pppp();
      if ((bj006A006A006Ajj006A006A006A + b006A006A006A006Ajj006A006A006A) * bj006A006A006Ajj006A006A006A % bjjjj006Aj006A006A006A != b006Ajjj006Aj006A006A006A)
      {
        bj006A006A006Ajj006A006A006A = bp00700070p00700070pppp();
        b006Ajjj006Aj006A006A006A = 81;
      }
      break;
    }
    return new mfffff();
  }
  
  @Provides
  @Singleton
  public qqpqqq bpp0070007000700070pppp(Context paramContext, xxxsss paramXxxsss, ggyggy paramGgyggy)
  {
    if ((bp00700070p00700070pppp() + b006A006A006A006Ajj006A006A006A) * bp00700070p00700070pppp() % bjjjj006Aj006A006A006A != b006Ajjj006Aj006A006A006A)
    {
      int i = bj006A006A006Ajj006A006A006A;
      switch (i * (b006A006A006A006Ajj006A006A006A + i) % bjjjj006Aj006A006A006A)
      {
      default: 
        bj006A006A006Ajj006A006A006A = bp00700070p00700070pppp();
        b006Ajjj006Aj006A006A006A = bp00700070p00700070pppp();
      }
      bj006A006A006Ajj006A006A006A = 43;
      b006Ajjj006Aj006A006A006A = bp00700070p00700070pppp();
    }
    return new qqpqqq(paramContext, paramXxxsss, paramGgyggy);
  }
  
  @Provides
  public pqqqqq bpp0070ppp0070ppp(qqpqqq paramQqpqqq)
  {
    paramQqpqqq = paramQqpqqq.b006Bk006Bk006B006Bk006Bkk(vxvvvx.class);
    int i = bp00700070p00700070pppp();
    switch (i * (b006A006A006A006Ajj006A006A006A + i) % bjjjj006Aj006A006A006A)
    {
    default: 
      i = bj006A006A006Ajj006A006A006A;
      switch (i * (b006A006A006A006Ajj006A006A006A + i) % bjjjj006Aj006A006A006A)
      {
      default: 
        bj006A006A006Ajj006A006A006A = bp00700070p00700070pppp();
        b006Ajjj006Aj006A006A006A = 80;
      }
      bj006A006A006Ajj006A006A006A = bp00700070p00700070pppp();
      b006Ajjj006Aj006A006A006A = 50;
    }
    return (pqqqqq)paramQqpqqq;
  }
  
  @Provides
  @Singleton
  public ygyyyy bppp007000700070pppp(Context paramContext)
  {
    paramContext = new ygyyyy(paramContext);
    int i = bj006A006A006Ajj006A006A006A;
    switch (i * (b006A006A006A006Ajj006A006A006A + i) % bjjjj006Aj006A006A006A)
    {
    default: 
      bj006A006A006Ajj006A006A006A = bp00700070p00700070pppp();
      b006A006A006A006Ajj006A006A006A = 43;
      if ((bj006A006A006Ajj006A006A006A + b006A006A006A006Ajj006A006A006A) * bj006A006A006Ajj006A006A006A % bjjjj006Aj006A006A006A != b006Ajjj006Aj006A006A006A)
      {
        bj006A006A006Ajj006A006A006A = 77;
        b006Ajjj006Aj006A006A006A = 69;
      }
      break;
    }
    return paramContext;
  }
  
  @Provides
  public SecurityUtils bppp0070pp0070ppp()
  {
    if ((bj006A006A006Ajj006A006A006A + b006A006A006A006Ajj006A006A006A) * bj006A006A006Ajj006A006A006A % bjjjj006Aj006A006A006A != b006Ajjj006Aj006A006A006A)
    {
      if ((bj006A006A006Ajj006A006A006A + b006A006A006A006Ajj006A006A006A) * bj006A006A006Ajj006A006A006A % bjjjj006Aj006A006A006A != b006Ajjj006Aj006A006A006A)
      {
        bj006A006A006Ajj006A006A006A = bp00700070p00700070pppp();
        b006Ajjj006Aj006A006A006A = bp00700070p00700070pppp();
      }
      bj006A006A006Ajj006A006A006A = 89;
      b006Ajjj006Aj006A006A006A = bp00700070p00700070pppp();
    }
    return new SecurityUtils();
  }
  
  @Provides
  @Singleton
  public sssttt bpppppp0070ppp(oossoo paramOossoo, wnwnwn paramWnwnwn, phpphh paramPhpphh, gagaaa paramGagaaa, uvvuvu paramUvvuvu, bbbmbb paramBbbmbb, ttyytt paramTtyytt, vvvyvv paramVvvyvv, mvvmvv paramMvvmvv, vvvdvv paramVvvdvv, llkllk paramLlkllk)
  {
    sssttt localSssttt = new sssttt();
    localSssttt.bkk006Bkk006B006B006Bkk(Feature.MBA, paramOossoo);
    if ((bj006A006A006Ajj006A006A006A + b006A006A006A006Ajj006A006A006A) * bj006A006A006Ajj006A006A006A % bjjjj006Aj006A006A006A != b006Ajjj006Aj006A006A006A)
    {
      bj006A006A006Ajj006A006A006A = 41;
      b006Ajjj006Aj006A006A006A = 11;
    }
    localSssttt.bkk006Bkk006B006B006Bkk(Feature.GINI, paramWnwnwn);
    paramOossoo = Feature.FINGERPRINT;
    if ((bj006A006A006Ajj006A006A006A + b007000700070p00700070pppp()) * bj006A006A006Ajj006A006A006A % bjjjj006Aj006A006A006A != b006Ajjj006Aj006A006A006A)
    {
      bj006A006A006Ajj006A006A006A = 63;
      b006Ajjj006Aj006A006A006A = bp00700070p00700070pppp();
    }
    localSssttt.bkk006Bkk006B006B006Bkk(paramOossoo, paramBbbmbb);
    localSssttt.bkk006Bkk006B006B006Bkk(Feature.BRANCHFINDER, paramUvvuvu);
    localSssttt.bkk006Bkk006B006B006Bkk(Feature.REVIEW, paramPhpphh);
    localSssttt.bkk006Bkk006B006B006Bkk(Feature.TREATMENTS, paramGagaaa);
    localSssttt.bkk006Bkk006B006B006Bkk(Feature.MOPAY, paramTtyytt);
    localSssttt.bkk006Bkk006B006B006Bkk(Feature.MORTGAGES, paramVvvyvv);
    localSssttt.bkk006Bkk006B006B006Bkk(Feature.CLICK4CREDIT, paramMvvmvv);
    localSssttt.bkk006Bkk006B006B006Bkk(Feature.INVESTMENTS, paramVvvdvv);
    localSssttt.bkk006Bkk006B006B006Bkk(Feature.SEPAFLOW, paramLlkllk);
    return localSssttt;
  }
}
