package uuuuuu;

import java.util.Objects;

public class gyyygy
{
  public static int b006B006Bkkk006Bk006Bk = 78;
  public static int b006Bk006Bkk006Bk006Bk = 2;
  public static int bk006B006Bkk006Bk006Bk = 0;
  public static int bkk006Bkk006Bk006Bk = 1;
  private final yyyygy b006Bkkkk006Bk006Bk;
  private final ggggyy bk006Bkkk006Bk006Bk;
  
  public gyyygy(yyyygy paramYyyygy, ggggyy paramGgggyy)
  {
    this.b006Bkkkk006Bk006Bk = paramYyyygy;
    this.bk006Bkkk006Bk006Bk = paramGgggyy;
  }
  
  public static int b0070pppp0070pp0070p()
  {
    return 1;
  }
  
  public static int bp0070ppp0070pp0070p()
  {
    return 49;
  }
  
  public yyyygy b00700070ppp0070pp0070p()
  {
    int i = b006B006Bkkk006Bk006Bk;
    switch (i * (bkk006Bkk006Bk006Bk + i) % b006Bk006Bkk006Bk006Bk)
    {
    default: 
      b006B006Bkkk006Bk006Bk = bp0070ppp0070pp0070p();
      bk006B006Bkk006Bk006Bk = bp0070ppp0070pp0070p();
    }
    return this.b006Bkkkk006Bk006Bk;
  }
  
  public ggggyy bpp0070pp0070pp0070p()
  {
    int i = b006B006Bkkk006Bk006Bk;
    switch (i * (bkk006Bkk006Bk006Bk + i) % b006Bk006Bkk006Bk006Bk)
    {
    default: 
      if ((b006B006Bkkk006Bk006Bk + b0070pppp0070pp0070p()) * b006B006Bkkk006Bk006Bk % b006Bk006Bkk006Bk006Bk != bk006B006Bkk006Bk006Bk)
      {
        b006B006Bkkk006Bk006Bk = 99;
        bk006B006Bkk006Bk006Bk = 43;
      }
      b006B006Bkkk006Bk006Bk = bp0070ppp0070pp0070p();
      bk006B006Bkk006Bk006Bk = 35;
    }
    return this.bk006Bkkk006Bk006Bk;
  }
  
  public boolean equals(Object paramObject)
  {
    boolean bool2 = false;
    boolean bool1;
    if (this == paramObject)
    {
      bool1 = true;
      return bool1;
    }
    Class localClass;
    do
    {
      paramObject = (gyyygy)paramObject;
      bool1 = bool2;
      if (this.b006Bkkkk006Bk006Bk != paramObject.b006Bkkkk006Bk006Bk) {
        break;
      }
      bool1 = bool2;
      if (this.bk006Bkkk006Bk006Bk != paramObject.bk006Bkkk006Bk006Bk) {
        break;
      }
      return true;
      int i = b006B006Bkkk006Bk006Bk;
      switch (i * (bkk006Bkk006Bk006Bk + i) % b006Bk006Bkk006Bk006Bk)
      {
      default: 
        b006B006Bkkk006Bk006Bk = bp0070ppp0070pp0070p();
        bkk006Bkk006Bk006Bk = bp0070ppp0070pp0070p();
      }
      bool1 = bool2;
      if (paramObject == null) {
        break;
      }
      localClass = getClass();
      if ((b006B006Bkkk006Bk006Bk + b0070pppp0070pp0070p()) * b006B006Bkkk006Bk006Bk % b006Bk006Bkk006Bk006Bk != bk006B006Bkk006Bk006Bk)
      {
        b006B006Bkkk006Bk006Bk = bp0070ppp0070pp0070p();
        bk006B006Bkk006Bk006Bk = bp0070ppp0070pp0070p();
      }
    } while (localClass == paramObject.getClass());
    return false;
  }
  
  public int hashCode()
  {
    yyyygy localYyyygy = this.b006Bkkkk006Bk006Bk;
    int i = b006B006Bkkk006Bk006Bk;
    switch (i * (bkk006Bkk006Bk006Bk + i) % b006Bk006Bkk006Bk006Bk)
    {
    default: 
      i = b006B006Bkkk006Bk006Bk;
      switch (i * (bkk006Bkk006Bk006Bk + i) % b006Bk006Bkk006Bk006Bk)
      {
      default: 
        b006B006Bkkk006Bk006Bk = bp0070ppp0070pp0070p();
        bk006B006Bkk006Bk006Bk = bp0070ppp0070pp0070p();
      }
      b006B006Bkkk006Bk006Bk = 14;
      bk006B006Bkk006Bk006Bk = 40;
    }
    return Objects.hash(new Object[] { localYyyygy, this.bk006Bkkk006Bk006Bk });
  }
  
  /* Error */
  public String toString()
  {
    // Byte code:
    //   0: new 71	java/lang/StringBuilder
    //   3: dup
    //   4: invokespecial 72	java/lang/StringBuilder:<init>	()V
    //   7: astore_1
    //   8: getstatic 40	uuuuuu/gyyygy:b006B006Bkkk006Bk006Bk	I
    //   11: getstatic 42	uuuuuu/gyyygy:bkk006Bkk006Bk006Bk	I
    //   14: iadd
    //   15: getstatic 40	uuuuuu/gyyygy:b006B006Bkkk006Bk006Bk	I
    //   18: imul
    //   19: getstatic 44	uuuuuu/gyyygy:b006Bk006Bkk006Bk006Bk	I
    //   22: irem
    //   23: getstatic 48	uuuuuu/gyyygy:bk006B006Bkk006Bk006Bk	I
    //   26: if_icmpeq +12 -> 38
    //   29: iconst_3
    //   30: putstatic 40	uuuuuu/gyyygy:b006B006Bkkk006Bk006Bk	I
    //   33: bipush 70
    //   35: putstatic 48	uuuuuu/gyyygy:bk006B006Bkk006Bk006Bk	I
    //   38: ldc 74
    //   40: ldc 76
    //   42: sipush 244
    //   45: sipush 182
    //   48: iconst_0
    //   49: invokestatic 82	xxxxxx/uxxxxx:bbbb0062b0062b0062b0062	(Ljava/lang/String;CCC)Ljava/lang/String;
    //   52: iconst_3
    //   53: anewarray 84	java/lang/Class
    //   56: dup
    //   57: iconst_0
    //   58: ldc 86
    //   60: aastore
    //   61: dup
    //   62: iconst_1
    //   63: getstatic 92	java/lang/Character:TYPE	Ljava/lang/Class;
    //   66: aastore
    //   67: dup
    //   68: iconst_2
    //   69: getstatic 92	java/lang/Character:TYPE	Ljava/lang/Class;
    //   72: aastore
    //   73: invokevirtual 96	java/lang/Class:getMethod	(Ljava/lang/String;[Ljava/lang/Class;)Ljava/lang/reflect/Method;
    //   76: astore_2
    //   77: aload_2
    //   78: aconst_null
    //   79: iconst_3
    //   80: anewarray 4	java/lang/Object
    //   83: dup
    //   84: iconst_0
    //   85: ldc 98
    //   87: aastore
    //   88: dup
    //   89: iconst_1
    //   90: sipush 143
    //   93: invokestatic 102	java/lang/Character:valueOf	(C)Ljava/lang/Character;
    //   96: aastore
    //   97: dup
    //   98: iconst_2
    //   99: iconst_4
    //   100: invokestatic 102	java/lang/Character:valueOf	(C)Ljava/lang/Character;
    //   103: aastore
    //   104: invokevirtual 108	java/lang/reflect/Method:invoke	(Ljava/lang/Object;[Ljava/lang/Object;)Ljava/lang/Object;
    //   107: astore_2
    //   108: aload_1
    //   109: aload_2
    //   110: checkcast 86	java/lang/String
    //   113: invokevirtual 112	java/lang/StringBuilder:append	(Ljava/lang/String;)Ljava/lang/StringBuilder;
    //   116: aload_0
    //   117: getfield 30	uuuuuu/gyyygy:b006Bkkkk006Bk006Bk	Luuuuuu/gyyygy$yyyygy;
    //   120: invokevirtual 115	java/lang/StringBuilder:append	(Ljava/lang/Object;)Ljava/lang/StringBuilder;
    //   123: astore_1
    //   124: ldc 74
    //   126: ldc 117
    //   128: sipush 187
    //   131: sipush 183
    //   134: iconst_3
    //   135: invokestatic 82	xxxxxx/uxxxxx:bbbb0062b0062b0062b0062	(Ljava/lang/String;CCC)Ljava/lang/String;
    //   138: iconst_4
    //   139: anewarray 84	java/lang/Class
    //   142: dup
    //   143: iconst_0
    //   144: ldc 86
    //   146: aastore
    //   147: dup
    //   148: iconst_1
    //   149: getstatic 92	java/lang/Character:TYPE	Ljava/lang/Class;
    //   152: aastore
    //   153: dup
    //   154: iconst_2
    //   155: getstatic 92	java/lang/Character:TYPE	Ljava/lang/Class;
    //   158: aastore
    //   159: dup
    //   160: iconst_3
    //   161: getstatic 92	java/lang/Character:TYPE	Ljava/lang/Class;
    //   164: aastore
    //   165: invokevirtual 96	java/lang/Class:getMethod	(Ljava/lang/String;[Ljava/lang/Class;)Ljava/lang/reflect/Method;
    //   168: astore_2
    //   169: aload_2
    //   170: aconst_null
    //   171: iconst_4
    //   172: anewarray 4	java/lang/Object
    //   175: dup
    //   176: iconst_0
    //   177: ldc 119
    //   179: aastore
    //   180: dup
    //   181: iconst_1
    //   182: bipush 24
    //   184: invokestatic 102	java/lang/Character:valueOf	(C)Ljava/lang/Character;
    //   187: aastore
    //   188: dup
    //   189: iconst_2
    //   190: bipush 30
    //   192: invokestatic 102	java/lang/Character:valueOf	(C)Ljava/lang/Character;
    //   195: aastore
    //   196: dup
    //   197: iconst_3
    //   198: iconst_1
    //   199: invokestatic 102	java/lang/Character:valueOf	(C)Ljava/lang/Character;
    //   202: aastore
    //   203: invokevirtual 108	java/lang/reflect/Method:invoke	(Ljava/lang/Object;[Ljava/lang/Object;)Ljava/lang/Object;
    //   206: astore_2
    //   207: aload_2
    //   208: checkcast 86	java/lang/String
    //   211: astore_2
    //   212: getstatic 40	uuuuuu/gyyygy:b006B006Bkkk006Bk006Bk	I
    //   215: getstatic 42	uuuuuu/gyyygy:bkk006Bkk006Bk006Bk	I
    //   218: iadd
    //   219: getstatic 40	uuuuuu/gyyygy:b006B006Bkkk006Bk006Bk	I
    //   222: imul
    //   223: getstatic 44	uuuuuu/gyyygy:b006Bk006Bkk006Bk006Bk	I
    //   226: irem
    //   227: getstatic 48	uuuuuu/gyyygy:bk006B006Bkk006Bk006Bk	I
    //   230: if_icmpeq +14 -> 244
    //   233: invokestatic 46	uuuuuu/gyyygy:bp0070ppp0070pp0070p	()I
    //   236: putstatic 40	uuuuuu/gyyygy:b006B006Bkkk006Bk006Bk	I
    //   239: bipush 75
    //   241: putstatic 48	uuuuuu/gyyygy:bk006B006Bkk006Bk006Bk	I
    //   244: aload_1
    //   245: aload_2
    //   246: invokevirtual 112	java/lang/StringBuilder:append	(Ljava/lang/String;)Ljava/lang/StringBuilder;
    //   249: aload_0
    //   250: getfield 32	uuuuuu/gyyygy:bk006Bkkk006Bk006Bk	Luuuuuu/gyyygy$ggggyy;
    //   253: invokevirtual 115	java/lang/StringBuilder:append	(Ljava/lang/Object;)Ljava/lang/StringBuilder;
    //   256: bipush 125
    //   258: invokevirtual 122	java/lang/StringBuilder:append	(C)Ljava/lang/StringBuilder;
    //   261: invokevirtual 124	java/lang/StringBuilder:toString	()Ljava/lang/String;
    //   264: areturn
    //   265: astore_1
    //   266: aload_1
    //   267: invokevirtual 128	java/lang/reflect/InvocationTargetException:getCause	()Ljava/lang/Throwable;
    //   270: athrow
    //   271: astore_1
    //   272: aload_1
    //   273: invokevirtual 128	java/lang/reflect/InvocationTargetException:getCause	()Ljava/lang/Throwable;
    //   276: athrow
    // Local variable table:
    //   start	length	slot	name	signature
    //   0	277	0	this	gyyygy
    //   7	238	1	localStringBuilder	StringBuilder
    //   265	2	1	localInvocationTargetException1	java.lang.reflect.InvocationTargetException
    //   271	2	1	localInvocationTargetException2	java.lang.reflect.InvocationTargetException
    //   76	170	2	localObject	Object
    // Exception table:
    //   from	to	target	type
    //   169	207	265	java/lang/reflect/InvocationTargetException
    //   77	108	271	java/lang/reflect/InvocationTargetException
  }
  
  public static enum ggggyy
  {
    /* Error */
    static
    {
      // Byte code:
      //   0: ldc 20
      //   2: ldc 22
      //   4: bipush 16
      //   6: iconst_4
      //   7: invokestatic 28	xxxxxx/uxxxxx:bb00620062bb0062b0062b0062	(Ljava/lang/String;CC)Ljava/lang/String;
      //   10: iconst_3
      //   11: anewarray 30	java/lang/Class
      //   14: dup
      //   15: iconst_0
      //   16: ldc 32
      //   18: aastore
      //   19: dup
      //   20: iconst_1
      //   21: getstatic 38	java/lang/Character:TYPE	Ljava/lang/Class;
      //   24: aastore
      //   25: dup
      //   26: iconst_2
      //   27: getstatic 38	java/lang/Character:TYPE	Ljava/lang/Class;
      //   30: aastore
      //   31: invokevirtual 42	java/lang/Class:getMethod	(Ljava/lang/String;[Ljava/lang/Class;)Ljava/lang/reflect/Method;
      //   34: astore_0
      //   35: aload_0
      //   36: aconst_null
      //   37: iconst_3
      //   38: anewarray 44	java/lang/Object
      //   41: dup
      //   42: iconst_0
      //   43: ldc 46
      //   45: aastore
      //   46: dup
      //   47: iconst_1
      //   48: bipush 70
      //   50: invokestatic 50	java/lang/Character:valueOf	(C)Ljava/lang/Character;
      //   53: aastore
      //   54: dup
      //   55: iconst_2
      //   56: iconst_3
      //   57: invokestatic 50	java/lang/Character:valueOf	(C)Ljava/lang/Character;
      //   60: aastore
      //   61: invokevirtual 56	java/lang/reflect/Method:invoke	(Ljava/lang/Object;[Ljava/lang/Object;)Ljava/lang/Object;
      //   64: astore_0
      //   65: new 2	uuuuuu/gyyygy$ggggyy
      //   68: dup
      //   69: aload_0
      //   70: checkcast 32	java/lang/String
      //   73: iconst_0
      //   74: invokespecial 60	uuuuuu/gyyygy$ggggyy:<init>	(Ljava/lang/String;I)V
      //   77: putstatic 62	uuuuuu/gyyygy$ggggyy:b006B006Bk006Bk006Bk006Bk	Luuuuuu/gyyygy$ggggyy;
      //   80: invokestatic 66	uuuuuu/gyyygy$ggggyy:b00700070007000700070ppp0070p	()I
      //   83: invokestatic 69	uuuuuu/gyyygy$ggggyy:bp0070007000700070ppp0070p	()I
      //   86: iadd
      //   87: invokestatic 66	uuuuuu/gyyygy$ggggyy:b00700070007000700070ppp0070p	()I
      //   90: imul
      //   91: invokestatic 72	uuuuuu/gyyygy$ggggyy:bpp007000700070ppp0070p	()I
      //   94: irem
      //   95: invokestatic 75	uuuuuu/gyyygy$ggggyy:b0070p007000700070ppp0070p	()I
      //   98: if_icmpeq +3 -> 101
      //   101: ldc 20
      //   103: ldc 77
      //   105: sipush 241
      //   108: iconst_3
      //   109: invokestatic 28	xxxxxx/uxxxxx:bb00620062bb0062b0062b0062	(Ljava/lang/String;CC)Ljava/lang/String;
      //   112: iconst_4
      //   113: anewarray 30	java/lang/Class
      //   116: dup
      //   117: iconst_0
      //   118: ldc 32
      //   120: aastore
      //   121: dup
      //   122: iconst_1
      //   123: getstatic 38	java/lang/Character:TYPE	Ljava/lang/Class;
      //   126: aastore
      //   127: dup
      //   128: iconst_2
      //   129: getstatic 38	java/lang/Character:TYPE	Ljava/lang/Class;
      //   132: aastore
      //   133: dup
      //   134: iconst_3
      //   135: getstatic 38	java/lang/Character:TYPE	Ljava/lang/Class;
      //   138: aastore
      //   139: invokevirtual 42	java/lang/Class:getMethod	(Ljava/lang/String;[Ljava/lang/Class;)Ljava/lang/reflect/Method;
      //   142: astore_0
      //   143: aload_0
      //   144: aconst_null
      //   145: iconst_4
      //   146: anewarray 44	java/lang/Object
      //   149: dup
      //   150: iconst_0
      //   151: ldc 79
      //   153: aastore
      //   154: dup
      //   155: iconst_1
      //   156: sipush 167
      //   159: invokestatic 50	java/lang/Character:valueOf	(C)Ljava/lang/Character;
      //   162: aastore
      //   163: dup
      //   164: iconst_2
      //   165: sipush 217
      //   168: invokestatic 50	java/lang/Character:valueOf	(C)Ljava/lang/Character;
      //   171: aastore
      //   172: dup
      //   173: iconst_3
      //   174: iconst_0
      //   175: invokestatic 50	java/lang/Character:valueOf	(C)Ljava/lang/Character;
      //   178: aastore
      //   179: invokevirtual 56	java/lang/reflect/Method:invoke	(Ljava/lang/Object;[Ljava/lang/Object;)Ljava/lang/Object;
      //   182: astore_0
      //   183: new 2	uuuuuu/gyyygy$ggggyy
      //   186: dup
      //   187: aload_0
      //   188: checkcast 32	java/lang/String
      //   191: iconst_1
      //   192: invokespecial 60	uuuuuu/gyyygy$ggggyy:<init>	(Ljava/lang/String;I)V
      //   195: putstatic 81	uuuuuu/gyyygy$ggggyy:bkk006B006Bk006Bk006Bk	Luuuuuu/gyyygy$ggggyy;
      //   198: ldc 20
      //   200: ldc 83
      //   202: sipush 134
      //   205: bipush 81
      //   207: iconst_2
      //   208: invokestatic 87	xxxxxx/uxxxxx:bbbb0062b0062b0062b0062	(Ljava/lang/String;CCC)Ljava/lang/String;
      //   211: iconst_3
      //   212: anewarray 30	java/lang/Class
      //   215: dup
      //   216: iconst_0
      //   217: ldc 32
      //   219: aastore
      //   220: dup
      //   221: iconst_1
      //   222: getstatic 38	java/lang/Character:TYPE	Ljava/lang/Class;
      //   225: aastore
      //   226: dup
      //   227: iconst_2
      //   228: getstatic 38	java/lang/Character:TYPE	Ljava/lang/Class;
      //   231: aastore
      //   232: invokevirtual 42	java/lang/Class:getMethod	(Ljava/lang/String;[Ljava/lang/Class;)Ljava/lang/reflect/Method;
      //   235: astore_0
      //   236: aload_0
      //   237: aconst_null
      //   238: iconst_3
      //   239: anewarray 44	java/lang/Object
      //   242: dup
      //   243: iconst_0
      //   244: ldc 89
      //   246: aastore
      //   247: dup
      //   248: iconst_1
      //   249: sipush 219
      //   252: invokestatic 50	java/lang/Character:valueOf	(C)Ljava/lang/Character;
      //   255: aastore
      //   256: dup
      //   257: iconst_2
      //   258: iconst_1
      //   259: invokestatic 50	java/lang/Character:valueOf	(C)Ljava/lang/Character;
      //   262: aastore
      //   263: invokevirtual 56	java/lang/reflect/Method:invoke	(Ljava/lang/Object;[Ljava/lang/Object;)Ljava/lang/Object;
      //   266: astore_0
      //   267: new 2	uuuuuu/gyyygy$ggggyy
      //   270: dup
      //   271: aload_0
      //   272: checkcast 32	java/lang/String
      //   275: iconst_2
      //   276: invokespecial 60	uuuuuu/gyyygy$ggggyy:<init>	(Ljava/lang/String;I)V
      //   279: putstatic 91	uuuuuu/gyyygy$ggggyy:b006Bk006B006Bk006Bk006Bk	Luuuuuu/gyyygy$ggggyy;
      //   282: invokestatic 66	uuuuuu/gyyygy$ggggyy:b00700070007000700070ppp0070p	()I
      //   285: invokestatic 69	uuuuuu/gyyygy$ggggyy:bp0070007000700070ppp0070p	()I
      //   288: iadd
      //   289: invokestatic 66	uuuuuu/gyyygy$ggggyy:b00700070007000700070ppp0070p	()I
      //   292: imul
      //   293: invokestatic 72	uuuuuu/gyyygy$ggggyy:bpp007000700070ppp0070p	()I
      //   296: irem
      //   297: invokestatic 75	uuuuuu/gyyygy$ggggyy:b0070p007000700070ppp0070p	()I
      //   300: if_icmpeq +3 -> 303
      //   303: iconst_3
      //   304: anewarray 2	uuuuuu/gyyygy$ggggyy
      //   307: dup
      //   308: iconst_0
      //   309: getstatic 62	uuuuuu/gyyygy$ggggyy:b006B006Bk006Bk006Bk006Bk	Luuuuuu/gyyygy$ggggyy;
      //   312: aastore
      //   313: dup
      //   314: iconst_1
      //   315: getstatic 81	uuuuuu/gyyygy$ggggyy:bkk006B006Bk006Bk006Bk	Luuuuuu/gyyygy$ggggyy;
      //   318: aastore
      //   319: dup
      //   320: iconst_2
      //   321: getstatic 91	uuuuuu/gyyygy$ggggyy:b006Bk006B006Bk006Bk006Bk	Luuuuuu/gyyygy$ggggyy;
      //   324: aastore
      //   325: putstatic 93	uuuuuu/gyyygy$ggggyy:bk006Bk006Bk006Bk006Bk	[Luuuuuu/gyyygy$ggggyy;
      //   328: return
      //   329: astore_0
      //   330: aload_0
      //   331: invokevirtual 97	java/lang/reflect/InvocationTargetException:getCause	()Ljava/lang/Throwable;
      //   334: athrow
      //   335: astore_0
      //   336: aload_0
      //   337: invokevirtual 97	java/lang/reflect/InvocationTargetException:getCause	()Ljava/lang/Throwable;
      //   340: athrow
      //   341: astore_0
      //   342: aload_0
      //   343: invokevirtual 97	java/lang/reflect/InvocationTargetException:getCause	()Ljava/lang/Throwable;
      //   346: athrow
      // Local variable table:
      //   start	length	slot	name	signature
      //   34	238	0	localObject	Object
      //   329	2	0	localInvocationTargetException1	java.lang.reflect.InvocationTargetException
      //   335	2	0	localInvocationTargetException2	java.lang.reflect.InvocationTargetException
      //   341	2	0	localInvocationTargetException3	java.lang.reflect.InvocationTargetException
      // Exception table:
      //   from	to	target	type
      //   236	267	329	java/lang/reflect/InvocationTargetException
      //   35	65	335	java/lang/reflect/InvocationTargetException
      //   143	183	341	java/lang/reflect/InvocationTargetException
    }
    
    private ggggyy() {}
    
    public static int b00700070007000700070ppp0070p()
    {
      return 32;
    }
    
    public static int b0070p007000700070ppp0070p()
    {
      return 0;
    }
    
    public static int bp0070007000700070ppp0070p()
    {
      return 1;
    }
    
    public static int bpp007000700070ppp0070p()
    {
      return 2;
    }
    
    public static ggggyy bppppp0070pp0070p(String paramString)
    {
      if ((b00700070007000700070ppp0070p() + bp0070007000700070ppp0070p()) * b00700070007000700070ppp0070p() % bpp007000700070ppp0070p() != b0070p007000700070ppp0070p()) {}
      paramString = (ggggyy)Enum.valueOf(ggggyy.class, paramString);
      if ((b00700070007000700070ppp0070p() + bp0070007000700070ppp0070p()) * b00700070007000700070ppp0070p() % bpp007000700070ppp0070p() != b0070p007000700070ppp0070p()) {}
      return paramString;
    }
  }
  
  public static enum yyyygy
  {
    /* Error */
    static
    {
      // Byte code:
      //   0: ldc 19
      //   2: ldc 21
      //   4: sipush 240
      //   7: iconst_5
      //   8: invokestatic 27	xxxxxx/uxxxxx:bb00620062bb0062b0062b0062	(Ljava/lang/String;CC)Ljava/lang/String;
      //   11: iconst_4
      //   12: anewarray 29	java/lang/Class
      //   15: dup
      //   16: iconst_0
      //   17: ldc 31
      //   19: aastore
      //   20: dup
      //   21: iconst_1
      //   22: getstatic 37	java/lang/Character:TYPE	Ljava/lang/Class;
      //   25: aastore
      //   26: dup
      //   27: iconst_2
      //   28: getstatic 37	java/lang/Character:TYPE	Ljava/lang/Class;
      //   31: aastore
      //   32: dup
      //   33: iconst_3
      //   34: getstatic 37	java/lang/Character:TYPE	Ljava/lang/Class;
      //   37: aastore
      //   38: invokevirtual 41	java/lang/Class:getMethod	(Ljava/lang/String;[Ljava/lang/Class;)Ljava/lang/reflect/Method;
      //   41: astore_1
      //   42: aload_1
      //   43: aconst_null
      //   44: iconst_4
      //   45: anewarray 43	java/lang/Object
      //   48: dup
      //   49: iconst_0
      //   50: ldc 45
      //   52: aastore
      //   53: dup
      //   54: iconst_1
      //   55: bipush 107
      //   57: invokestatic 49	java/lang/Character:valueOf	(C)Ljava/lang/Character;
      //   60: aastore
      //   61: dup
      //   62: iconst_2
      //   63: bipush 81
      //   65: invokestatic 49	java/lang/Character:valueOf	(C)Ljava/lang/Character;
      //   68: aastore
      //   69: dup
      //   70: iconst_3
      //   71: iconst_2
      //   72: invokestatic 49	java/lang/Character:valueOf	(C)Ljava/lang/Character;
      //   75: aastore
      //   76: invokevirtual 55	java/lang/reflect/Method:invoke	(Ljava/lang/Object;[Ljava/lang/Object;)Ljava/lang/Object;
      //   79: astore_1
      //   80: new 2	uuuuuu/gyyygy$yyyygy
      //   83: dup
      //   84: aload_1
      //   85: checkcast 31	java/lang/String
      //   88: iconst_0
      //   89: invokespecial 59	uuuuuu/gyyygy$yyyygy:<init>	(Ljava/lang/String;I)V
      //   92: putstatic 61	uuuuuu/gyyygy$yyyygy:bkkk006Bk006Bk006Bk	Luuuuuu/gyyygy$yyyygy;
      //   95: ldc 19
      //   97: ldc 63
      //   99: bipush 59
      //   101: bipush 67
      //   103: iconst_3
      //   104: invokestatic 67	xxxxxx/uxxxxx:bbbb0062b0062b0062b0062	(Ljava/lang/String;CCC)Ljava/lang/String;
      //   107: iconst_4
      //   108: anewarray 29	java/lang/Class
      //   111: dup
      //   112: iconst_0
      //   113: ldc 31
      //   115: aastore
      //   116: dup
      //   117: iconst_1
      //   118: getstatic 37	java/lang/Character:TYPE	Ljava/lang/Class;
      //   121: aastore
      //   122: dup
      //   123: iconst_2
      //   124: getstatic 37	java/lang/Character:TYPE	Ljava/lang/Class;
      //   127: aastore
      //   128: dup
      //   129: iconst_3
      //   130: getstatic 37	java/lang/Character:TYPE	Ljava/lang/Class;
      //   133: aastore
      //   134: invokevirtual 41	java/lang/Class:getMethod	(Ljava/lang/String;[Ljava/lang/Class;)Ljava/lang/reflect/Method;
      //   137: astore_1
      //   138: aload_1
      //   139: aconst_null
      //   140: iconst_4
      //   141: anewarray 43	java/lang/Object
      //   144: dup
      //   145: iconst_0
      //   146: ldc 69
      //   148: aastore
      //   149: dup
      //   150: iconst_1
      //   151: bipush 62
      //   153: invokestatic 49	java/lang/Character:valueOf	(C)Ljava/lang/Character;
      //   156: aastore
      //   157: dup
      //   158: iconst_2
      //   159: sipush 148
      //   162: invokestatic 49	java/lang/Character:valueOf	(C)Ljava/lang/Character;
      //   165: aastore
      //   166: dup
      //   167: iconst_3
      //   168: iconst_0
      //   169: invokestatic 49	java/lang/Character:valueOf	(C)Ljava/lang/Character;
      //   172: aastore
      //   173: invokevirtual 55	java/lang/reflect/Method:invoke	(Ljava/lang/Object;[Ljava/lang/Object;)Ljava/lang/Object;
      //   176: astore_1
      //   177: new 2	uuuuuu/gyyygy$yyyygy
      //   180: dup
      //   181: aload_1
      //   182: checkcast 31	java/lang/String
      //   185: iconst_1
      //   186: invokespecial 59	uuuuuu/gyyygy$yyyygy:<init>	(Ljava/lang/String;I)V
      //   189: putstatic 71	uuuuuu/gyyygy$yyyygy:b006Bkk006Bk006Bk006Bk	Luuuuuu/gyyygy$yyyygy;
      //   192: getstatic 61	uuuuuu/gyyygy$yyyygy:bkkk006Bk006Bk006Bk	Luuuuuu/gyyygy$yyyygy;
      //   195: astore_1
      //   196: getstatic 71	uuuuuu/gyyygy$yyyygy:b006Bkk006Bk006Bk006Bk	Luuuuuu/gyyygy$yyyygy;
      //   199: astore_2
      //   200: invokestatic 75	uuuuuu/gyyygy$yyyygy:bp0070p00700070ppp0070p	()I
      //   203: istore_0
      //   204: iload_0
      //   205: invokestatic 78	uuuuuu/gyyygy$yyyygy:bppp00700070ppp0070p	()I
      //   208: iload_0
      //   209: iadd
      //   210: imul
      //   211: invokestatic 81	uuuuuu/gyyygy$yyyygy:b0070pp00700070ppp0070p	()I
      //   214: irem
      //   215: tableswitch	default:+17->232, 0:+38->253
      //   232: invokestatic 75	uuuuuu/gyyygy$yyyygy:bp0070p00700070ppp0070p	()I
      //   235: invokestatic 78	uuuuuu/gyyygy$yyyygy:bppp00700070ppp0070p	()I
      //   238: iadd
      //   239: invokestatic 75	uuuuuu/gyyygy$yyyygy:bp0070p00700070ppp0070p	()I
      //   242: imul
      //   243: invokestatic 81	uuuuuu/gyyygy$yyyygy:b0070pp00700070ppp0070p	()I
      //   246: irem
      //   247: invokestatic 84	uuuuuu/gyyygy$yyyygy:b007000700070p0070ppp0070p	()I
      //   250: if_icmpeq +3 -> 253
      //   253: iconst_2
      //   254: anewarray 2	uuuuuu/gyyygy$yyyygy
      //   257: dup
      //   258: iconst_0
      //   259: aload_1
      //   260: aastore
      //   261: dup
      //   262: iconst_1
      //   263: aload_2
      //   264: aastore
      //   265: putstatic 86	uuuuuu/gyyygy$yyyygy:b006B006B006Bkk006Bk006Bk	[Luuuuuu/gyyygy$yyyygy;
      //   268: return
      //   269: astore_1
      //   270: aload_1
      //   271: invokevirtual 90	java/lang/reflect/InvocationTargetException:getCause	()Ljava/lang/Throwable;
      //   274: athrow
      //   275: astore_1
      //   276: aload_1
      //   277: invokevirtual 90	java/lang/reflect/InvocationTargetException:getCause	()Ljava/lang/Throwable;
      //   280: athrow
      // Local variable table:
      //   start	length	slot	name	signature
      //   203	8	0	i	int
      //   41	219	1	localObject	Object
      //   269	2	1	localInvocationTargetException1	java.lang.reflect.InvocationTargetException
      //   275	2	1	localInvocationTargetException2	java.lang.reflect.InvocationTargetException
      //   199	65	2	localYyyygy	yyyygy
      // Exception table:
      //   from	to	target	type
      //   42	80	269	java/lang/reflect/InvocationTargetException
      //   138	177	275	java/lang/reflect/InvocationTargetException
    }
    
    private yyyygy() {}
    
    public static int b007000700070p0070ppp0070p()
    {
      return 0;
    }
    
    public static yyyygy b00700070p00700070ppp0070p(String paramString)
    {
      paramString = Enum.valueOf(yyyygy.class, paramString);
      int i = bp0070p00700070ppp0070p();
      switch (i * (bppp00700070ppp0070p() + i) % b0070pp00700070ppp0070p())
      {
      }
      paramString = (yyyygy)paramString;
      i = bp0070p00700070ppp0070p();
      switch (i * (bppp00700070ppp0070p() + i) % b0070pp00700070ppp0070p())
      {
      }
      return paramString;
    }
    
    public static int b0070pp00700070ppp0070p()
    {
      return 2;
    }
    
    public static int bp0070p00700070ppp0070p()
    {
      return 28;
    }
    
    public static int bppp00700070ppp0070p()
    {
      return 1;
    }
  }
}
