package uuuuuu;

public enum hhhhyh
{
  /* Error */
  static
  {
    // Byte code:
    //   0: ldc 23
    //   2: ldc 25
    //   4: sipush 199
    //   7: iconst_0
    //   8: invokestatic 31	xxxxxx/uxxxxx:bb00620062bb0062b0062b0062	(Ljava/lang/String;CC)Ljava/lang/String;
    //   11: iconst_3
    //   12: anewarray 33	java/lang/Class
    //   15: dup
    //   16: iconst_0
    //   17: ldc 35
    //   19: aastore
    //   20: dup
    //   21: iconst_1
    //   22: getstatic 41	java/lang/Character:TYPE	Ljava/lang/Class;
    //   25: aastore
    //   26: dup
    //   27: iconst_2
    //   28: getstatic 41	java/lang/Character:TYPE	Ljava/lang/Class;
    //   31: aastore
    //   32: invokevirtual 45	java/lang/Class:getMethod	(Ljava/lang/String;[Ljava/lang/Class;)Ljava/lang/reflect/Method;
    //   35: astore_1
    //   36: aload_1
    //   37: aconst_null
    //   38: iconst_3
    //   39: anewarray 47	java/lang/Object
    //   42: dup
    //   43: iconst_0
    //   44: ldc 49
    //   46: aastore
    //   47: dup
    //   48: iconst_1
    //   49: sipush 195
    //   52: invokestatic 53	java/lang/Character:valueOf	(C)Ljava/lang/Character;
    //   55: aastore
    //   56: dup
    //   57: iconst_2
    //   58: iconst_1
    //   59: invokestatic 53	java/lang/Character:valueOf	(C)Ljava/lang/Character;
    //   62: aastore
    //   63: invokevirtual 59	java/lang/reflect/Method:invoke	(Ljava/lang/Object;[Ljava/lang/Object;)Ljava/lang/Object;
    //   66: astore_1
    //   67: new 2	uuuuuu/hhhhyh
    //   70: dup
    //   71: aload_1
    //   72: checkcast 35	java/lang/String
    //   75: iconst_0
    //   76: invokespecial 63	uuuuuu/hhhhyh:<init>	(Ljava/lang/String;I)V
    //   79: putstatic 65	uuuuuu/hhhhyh:b00700070pp00700070ppp	Luuuuuu/hhhhyh;
    //   82: ldc 23
    //   84: ldc 67
    //   86: bipush 90
    //   88: bipush 126
    //   90: iconst_2
    //   91: invokestatic 71	xxxxxx/uxxxxx:bbbb0062b0062b0062b0062	(Ljava/lang/String;CCC)Ljava/lang/String;
    //   94: iconst_3
    //   95: anewarray 33	java/lang/Class
    //   98: dup
    //   99: iconst_0
    //   100: ldc 35
    //   102: aastore
    //   103: dup
    //   104: iconst_1
    //   105: getstatic 41	java/lang/Character:TYPE	Ljava/lang/Class;
    //   108: aastore
    //   109: dup
    //   110: iconst_2
    //   111: getstatic 41	java/lang/Character:TYPE	Ljava/lang/Class;
    //   114: aastore
    //   115: invokevirtual 45	java/lang/Class:getMethod	(Ljava/lang/String;[Ljava/lang/Class;)Ljava/lang/reflect/Method;
    //   118: astore_1
    //   119: aload_1
    //   120: aconst_null
    //   121: iconst_3
    //   122: anewarray 47	java/lang/Object
    //   125: dup
    //   126: iconst_0
    //   127: ldc 73
    //   129: aastore
    //   130: dup
    //   131: iconst_1
    //   132: sipush 171
    //   135: invokestatic 53	java/lang/Character:valueOf	(C)Ljava/lang/Character;
    //   138: aastore
    //   139: dup
    //   140: iconst_2
    //   141: iconst_0
    //   142: invokestatic 53	java/lang/Character:valueOf	(C)Ljava/lang/Character;
    //   145: aastore
    //   146: invokevirtual 59	java/lang/reflect/Method:invoke	(Ljava/lang/Object;[Ljava/lang/Object;)Ljava/lang/Object;
    //   149: astore_1
    //   150: new 2	uuuuuu/hhhhyh
    //   153: dup
    //   154: aload_1
    //   155: checkcast 35	java/lang/String
    //   158: iconst_1
    //   159: invokespecial 63	uuuuuu/hhhhyh:<init>	(Ljava/lang/String;I)V
    //   162: putstatic 75	uuuuuu/hhhhyh:b007000700070p00700070ppp	Luuuuuu/hhhhyh;
    //   165: ldc 23
    //   167: ldc 77
    //   169: sipush 214
    //   172: iconst_3
    //   173: invokestatic 31	xxxxxx/uxxxxx:bb00620062bb0062b0062b0062	(Ljava/lang/String;CC)Ljava/lang/String;
    //   176: iconst_3
    //   177: anewarray 33	java/lang/Class
    //   180: dup
    //   181: iconst_0
    //   182: ldc 35
    //   184: aastore
    //   185: dup
    //   186: iconst_1
    //   187: getstatic 41	java/lang/Character:TYPE	Ljava/lang/Class;
    //   190: aastore
    //   191: dup
    //   192: iconst_2
    //   193: getstatic 41	java/lang/Character:TYPE	Ljava/lang/Class;
    //   196: aastore
    //   197: invokevirtual 45	java/lang/Class:getMethod	(Ljava/lang/String;[Ljava/lang/Class;)Ljava/lang/reflect/Method;
    //   200: astore_1
    //   201: aload_1
    //   202: aconst_null
    //   203: iconst_3
    //   204: anewarray 47	java/lang/Object
    //   207: dup
    //   208: iconst_0
    //   209: ldc 79
    //   211: aastore
    //   212: dup
    //   213: iconst_1
    //   214: bipush 21
    //   216: invokestatic 53	java/lang/Character:valueOf	(C)Ljava/lang/Character;
    //   219: aastore
    //   220: dup
    //   221: iconst_2
    //   222: iconst_1
    //   223: invokestatic 53	java/lang/Character:valueOf	(C)Ljava/lang/Character;
    //   226: aastore
    //   227: invokevirtual 59	java/lang/reflect/Method:invoke	(Ljava/lang/Object;[Ljava/lang/Object;)Ljava/lang/Object;
    //   230: astore_1
    //   231: new 2	uuuuuu/hhhhyh
    //   234: dup
    //   235: aload_1
    //   236: checkcast 35	java/lang/String
    //   239: iconst_2
    //   240: invokespecial 63	uuuuuu/hhhhyh:<init>	(Ljava/lang/String;I)V
    //   243: putstatic 81	uuuuuu/hhhhyh:bp00700070p00700070ppp	Luuuuuu/hhhhyh;
    //   246: ldc 23
    //   248: ldc 83
    //   250: bipush 31
    //   252: iconst_2
    //   253: invokestatic 31	xxxxxx/uxxxxx:bb00620062bb0062b0062b0062	(Ljava/lang/String;CC)Ljava/lang/String;
    //   256: iconst_4
    //   257: anewarray 33	java/lang/Class
    //   260: dup
    //   261: iconst_0
    //   262: ldc 35
    //   264: aastore
    //   265: dup
    //   266: iconst_1
    //   267: getstatic 41	java/lang/Character:TYPE	Ljava/lang/Class;
    //   270: aastore
    //   271: dup
    //   272: iconst_2
    //   273: getstatic 41	java/lang/Character:TYPE	Ljava/lang/Class;
    //   276: aastore
    //   277: dup
    //   278: iconst_3
    //   279: getstatic 41	java/lang/Character:TYPE	Ljava/lang/Class;
    //   282: aastore
    //   283: invokevirtual 45	java/lang/Class:getMethod	(Ljava/lang/String;[Ljava/lang/Class;)Ljava/lang/reflect/Method;
    //   286: astore_1
    //   287: aload_1
    //   288: aconst_null
    //   289: iconst_4
    //   290: anewarray 47	java/lang/Object
    //   293: dup
    //   294: iconst_0
    //   295: ldc 85
    //   297: aastore
    //   298: dup
    //   299: iconst_1
    //   300: sipush 152
    //   303: invokestatic 53	java/lang/Character:valueOf	(C)Ljava/lang/Character;
    //   306: aastore
    //   307: dup
    //   308: iconst_2
    //   309: bipush 35
    //   311: invokestatic 53	java/lang/Character:valueOf	(C)Ljava/lang/Character;
    //   314: aastore
    //   315: dup
    //   316: iconst_3
    //   317: iconst_2
    //   318: invokestatic 53	java/lang/Character:valueOf	(C)Ljava/lang/Character;
    //   321: aastore
    //   322: invokevirtual 59	java/lang/reflect/Method:invoke	(Ljava/lang/Object;[Ljava/lang/Object;)Ljava/lang/Object;
    //   325: astore_1
    //   326: new 2	uuuuuu/hhhhyh
    //   329: dup
    //   330: aload_1
    //   331: checkcast 35	java/lang/String
    //   334: iconst_3
    //   335: invokespecial 63	uuuuuu/hhhhyh:<init>	(Ljava/lang/String;I)V
    //   338: putstatic 87	uuuuuu/hhhhyh:bpp0070p00700070ppp	Luuuuuu/hhhhyh;
    //   341: ldc 23
    //   343: ldc 89
    //   345: iconst_4
    //   346: iconst_5
    //   347: invokestatic 31	xxxxxx/uxxxxx:bb00620062bb0062b0062b0062	(Ljava/lang/String;CC)Ljava/lang/String;
    //   350: iconst_4
    //   351: anewarray 33	java/lang/Class
    //   354: dup
    //   355: iconst_0
    //   356: ldc 35
    //   358: aastore
    //   359: dup
    //   360: iconst_1
    //   361: getstatic 41	java/lang/Character:TYPE	Ljava/lang/Class;
    //   364: aastore
    //   365: dup
    //   366: iconst_2
    //   367: getstatic 41	java/lang/Character:TYPE	Ljava/lang/Class;
    //   370: aastore
    //   371: dup
    //   372: iconst_3
    //   373: getstatic 41	java/lang/Character:TYPE	Ljava/lang/Class;
    //   376: aastore
    //   377: invokevirtual 45	java/lang/Class:getMethod	(Ljava/lang/String;[Ljava/lang/Class;)Ljava/lang/reflect/Method;
    //   380: astore_1
    //   381: aload_1
    //   382: aconst_null
    //   383: iconst_4
    //   384: anewarray 47	java/lang/Object
    //   387: dup
    //   388: iconst_0
    //   389: ldc 91
    //   391: aastore
    //   392: dup
    //   393: iconst_1
    //   394: sipush 246
    //   397: invokestatic 53	java/lang/Character:valueOf	(C)Ljava/lang/Character;
    //   400: aastore
    //   401: dup
    //   402: iconst_2
    //   403: bipush 98
    //   405: invokestatic 53	java/lang/Character:valueOf	(C)Ljava/lang/Character;
    //   408: aastore
    //   409: dup
    //   410: iconst_3
    //   411: iconst_0
    //   412: invokestatic 53	java/lang/Character:valueOf	(C)Ljava/lang/Character;
    //   415: aastore
    //   416: invokevirtual 59	java/lang/reflect/Method:invoke	(Ljava/lang/Object;[Ljava/lang/Object;)Ljava/lang/Object;
    //   419: astore_1
    //   420: new 2	uuuuuu/hhhhyh
    //   423: dup
    //   424: aload_1
    //   425: checkcast 35	java/lang/String
    //   428: iconst_4
    //   429: invokespecial 63	uuuuuu/hhhhyh:<init>	(Ljava/lang/String;I)V
    //   432: putstatic 93	uuuuuu/hhhhyh:bppp007000700070ppp	Luuuuuu/hhhhyh;
    //   435: ldc 23
    //   437: ldc 95
    //   439: sipush 212
    //   442: iconst_0
    //   443: invokestatic 31	xxxxxx/uxxxxx:bb00620062bb0062b0062b0062	(Ljava/lang/String;CC)Ljava/lang/String;
    //   446: iconst_3
    //   447: anewarray 33	java/lang/Class
    //   450: dup
    //   451: iconst_0
    //   452: ldc 35
    //   454: aastore
    //   455: dup
    //   456: iconst_1
    //   457: getstatic 41	java/lang/Character:TYPE	Ljava/lang/Class;
    //   460: aastore
    //   461: dup
    //   462: iconst_2
    //   463: getstatic 41	java/lang/Character:TYPE	Ljava/lang/Class;
    //   466: aastore
    //   467: invokevirtual 45	java/lang/Class:getMethod	(Ljava/lang/String;[Ljava/lang/Class;)Ljava/lang/reflect/Method;
    //   470: astore_1
    //   471: aload_1
    //   472: aconst_null
    //   473: iconst_3
    //   474: anewarray 47	java/lang/Object
    //   477: dup
    //   478: iconst_0
    //   479: ldc 97
    //   481: aastore
    //   482: dup
    //   483: iconst_1
    //   484: sipush 148
    //   487: invokestatic 53	java/lang/Character:valueOf	(C)Ljava/lang/Character;
    //   490: aastore
    //   491: dup
    //   492: iconst_2
    //   493: iconst_5
    //   494: invokestatic 53	java/lang/Character:valueOf	(C)Ljava/lang/Character;
    //   497: aastore
    //   498: invokevirtual 59	java/lang/reflect/Method:invoke	(Ljava/lang/Object;[Ljava/lang/Object;)Ljava/lang/Object;
    //   501: astore_1
    //   502: new 2	uuuuuu/hhhhyh
    //   505: dup
    //   506: aload_1
    //   507: checkcast 35	java/lang/String
    //   510: iconst_5
    //   511: invokespecial 63	uuuuuu/hhhhyh:<init>	(Ljava/lang/String;I)V
    //   514: putstatic 99	uuuuuu/hhhhyh:b0070pp007000700070ppp	Luuuuuu/hhhhyh;
    //   517: ldc 23
    //   519: ldc 101
    //   521: bipush 23
    //   523: iconst_5
    //   524: invokestatic 31	xxxxxx/uxxxxx:bb00620062bb0062b0062b0062	(Ljava/lang/String;CC)Ljava/lang/String;
    //   527: iconst_3
    //   528: anewarray 33	java/lang/Class
    //   531: dup
    //   532: iconst_0
    //   533: ldc 35
    //   535: aastore
    //   536: dup
    //   537: iconst_1
    //   538: getstatic 41	java/lang/Character:TYPE	Ljava/lang/Class;
    //   541: aastore
    //   542: dup
    //   543: iconst_2
    //   544: getstatic 41	java/lang/Character:TYPE	Ljava/lang/Class;
    //   547: aastore
    //   548: invokevirtual 45	java/lang/Class:getMethod	(Ljava/lang/String;[Ljava/lang/Class;)Ljava/lang/reflect/Method;
    //   551: astore_1
    //   552: aload_1
    //   553: aconst_null
    //   554: iconst_3
    //   555: anewarray 47	java/lang/Object
    //   558: dup
    //   559: iconst_0
    //   560: ldc 103
    //   562: aastore
    //   563: dup
    //   564: iconst_1
    //   565: bipush 21
    //   567: invokestatic 53	java/lang/Character:valueOf	(C)Ljava/lang/Character;
    //   570: aastore
    //   571: dup
    //   572: iconst_2
    //   573: iconst_2
    //   574: invokestatic 53	java/lang/Character:valueOf	(C)Ljava/lang/Character;
    //   577: aastore
    //   578: invokevirtual 59	java/lang/reflect/Method:invoke	(Ljava/lang/Object;[Ljava/lang/Object;)Ljava/lang/Object;
    //   581: astore_1
    //   582: new 2	uuuuuu/hhhhyh
    //   585: dup
    //   586: aload_1
    //   587: checkcast 35	java/lang/String
    //   590: bipush 6
    //   592: invokespecial 63	uuuuuu/hhhhyh:<init>	(Ljava/lang/String;I)V
    //   595: putstatic 105	uuuuuu/hhhhyh:b0070p0070p00700070ppp	Luuuuuu/hhhhyh;
    //   598: invokestatic 109	uuuuuu/hhhhyh:bpppp007000700070007000700070	()I
    //   601: istore_0
    //   602: iload_0
    //   603: invokestatic 112	uuuuuu/hhhhyh:b00700070pp007000700070007000700070	()I
    //   606: iload_0
    //   607: iadd
    //   608: imul
    //   609: invokestatic 115	uuuuuu/hhhhyh:b0070ppp007000700070007000700070	()I
    //   612: irem
    //   613: tableswitch	default:+19->632, 0:+19->632
    //   632: ldc 23
    //   634: ldc 117
    //   636: sipush 148
    //   639: iconst_0
    //   640: invokestatic 31	xxxxxx/uxxxxx:bb00620062bb0062b0062b0062	(Ljava/lang/String;CC)Ljava/lang/String;
    //   643: iconst_3
    //   644: anewarray 33	java/lang/Class
    //   647: dup
    //   648: iconst_0
    //   649: ldc 35
    //   651: aastore
    //   652: dup
    //   653: iconst_1
    //   654: getstatic 41	java/lang/Character:TYPE	Ljava/lang/Class;
    //   657: aastore
    //   658: dup
    //   659: iconst_2
    //   660: getstatic 41	java/lang/Character:TYPE	Ljava/lang/Class;
    //   663: aastore
    //   664: invokevirtual 45	java/lang/Class:getMethod	(Ljava/lang/String;[Ljava/lang/Class;)Ljava/lang/reflect/Method;
    //   667: astore_1
    //   668: aload_1
    //   669: aconst_null
    //   670: iconst_3
    //   671: anewarray 47	java/lang/Object
    //   674: dup
    //   675: iconst_0
    //   676: ldc 119
    //   678: aastore
    //   679: dup
    //   680: iconst_1
    //   681: bipush 118
    //   683: invokestatic 53	java/lang/Character:valueOf	(C)Ljava/lang/Character;
    //   686: aastore
    //   687: dup
    //   688: iconst_2
    //   689: iconst_5
    //   690: invokestatic 53	java/lang/Character:valueOf	(C)Ljava/lang/Character;
    //   693: aastore
    //   694: invokevirtual 59	java/lang/reflect/Method:invoke	(Ljava/lang/Object;[Ljava/lang/Object;)Ljava/lang/Object;
    //   697: astore_1
    //   698: new 2	uuuuuu/hhhhyh
    //   701: dup
    //   702: aload_1
    //   703: checkcast 35	java/lang/String
    //   706: bipush 7
    //   708: invokespecial 63	uuuuuu/hhhhyh:<init>	(Ljava/lang/String;I)V
    //   711: putstatic 121	uuuuuu/hhhhyh:b00700070p007000700070ppp	Luuuuuu/hhhhyh;
    //   714: ldc 23
    //   716: ldc 123
    //   718: bipush 28
    //   720: sipush 134
    //   723: iconst_3
    //   724: invokestatic 71	xxxxxx/uxxxxx:bbbb0062b0062b0062b0062	(Ljava/lang/String;CCC)Ljava/lang/String;
    //   727: iconst_3
    //   728: anewarray 33	java/lang/Class
    //   731: dup
    //   732: iconst_0
    //   733: ldc 35
    //   735: aastore
    //   736: dup
    //   737: iconst_1
    //   738: getstatic 41	java/lang/Character:TYPE	Ljava/lang/Class;
    //   741: aastore
    //   742: dup
    //   743: iconst_2
    //   744: getstatic 41	java/lang/Character:TYPE	Ljava/lang/Class;
    //   747: aastore
    //   748: invokevirtual 45	java/lang/Class:getMethod	(Ljava/lang/String;[Ljava/lang/Class;)Ljava/lang/reflect/Method;
    //   751: astore_1
    //   752: aload_1
    //   753: aconst_null
    //   754: iconst_3
    //   755: anewarray 47	java/lang/Object
    //   758: dup
    //   759: iconst_0
    //   760: ldc 125
    //   762: aastore
    //   763: dup
    //   764: iconst_1
    //   765: sipush 207
    //   768: invokestatic 53	java/lang/Character:valueOf	(C)Ljava/lang/Character;
    //   771: aastore
    //   772: dup
    //   773: iconst_2
    //   774: iconst_3
    //   775: invokestatic 53	java/lang/Character:valueOf	(C)Ljava/lang/Character;
    //   778: aastore
    //   779: invokevirtual 59	java/lang/reflect/Method:invoke	(Ljava/lang/Object;[Ljava/lang/Object;)Ljava/lang/Object;
    //   782: astore_1
    //   783: new 2	uuuuuu/hhhhyh
    //   786: dup
    //   787: aload_1
    //   788: checkcast 35	java/lang/String
    //   791: bipush 8
    //   793: invokespecial 63	uuuuuu/hhhhyh:<init>	(Ljava/lang/String;I)V
    //   796: putstatic 127	uuuuuu/hhhhyh:bp0070p007000700070ppp	Luuuuuu/hhhhyh;
    //   799: getstatic 65	uuuuuu/hhhhyh:b00700070pp00700070ppp	Luuuuuu/hhhhyh;
    //   802: astore_1
    //   803: getstatic 75	uuuuuu/hhhhyh:b007000700070p00700070ppp	Luuuuuu/hhhhyh;
    //   806: astore_2
    //   807: getstatic 81	uuuuuu/hhhhyh:bp00700070p00700070ppp	Luuuuuu/hhhhyh;
    //   810: astore_3
    //   811: getstatic 87	uuuuuu/hhhhyh:bpp0070p00700070ppp	Luuuuuu/hhhhyh;
    //   814: astore 4
    //   816: getstatic 93	uuuuuu/hhhhyh:bppp007000700070ppp	Luuuuuu/hhhhyh;
    //   819: astore 5
    //   821: getstatic 99	uuuuuu/hhhhyh:b0070pp007000700070ppp	Luuuuuu/hhhhyh;
    //   824: astore 6
    //   826: invokestatic 109	uuuuuu/hhhhyh:bpppp007000700070007000700070	()I
    //   829: istore_0
    //   830: iload_0
    //   831: invokestatic 112	uuuuuu/hhhhyh:b00700070pp007000700070007000700070	()I
    //   834: iload_0
    //   835: iadd
    //   836: imul
    //   837: invokestatic 115	uuuuuu/hhhhyh:b0070ppp007000700070007000700070	()I
    //   840: irem
    //   841: tableswitch	default:+19->860, 0:+19->860
    //   860: bipush 9
    //   862: anewarray 2	uuuuuu/hhhhyh
    //   865: dup
    //   866: iconst_0
    //   867: aload_1
    //   868: aastore
    //   869: dup
    //   870: iconst_1
    //   871: aload_2
    //   872: aastore
    //   873: dup
    //   874: iconst_2
    //   875: aload_3
    //   876: aastore
    //   877: dup
    //   878: iconst_3
    //   879: aload 4
    //   881: aastore
    //   882: dup
    //   883: iconst_4
    //   884: aload 5
    //   886: aastore
    //   887: dup
    //   888: iconst_5
    //   889: aload 6
    //   891: aastore
    //   892: dup
    //   893: bipush 6
    //   895: getstatic 105	uuuuuu/hhhhyh:b0070p0070p00700070ppp	Luuuuuu/hhhhyh;
    //   898: aastore
    //   899: dup
    //   900: bipush 7
    //   902: getstatic 121	uuuuuu/hhhhyh:b00700070p007000700070ppp	Luuuuuu/hhhhyh;
    //   905: aastore
    //   906: dup
    //   907: bipush 8
    //   909: getstatic 127	uuuuuu/hhhhyh:bp0070p007000700070ppp	Luuuuuu/hhhhyh;
    //   912: aastore
    //   913: putstatic 129	uuuuuu/hhhhyh:bp0070pp00700070ppp	[Luuuuuu/hhhhyh;
    //   916: return
    //   917: astore_1
    //   918: aload_1
    //   919: invokevirtual 133	java/lang/reflect/InvocationTargetException:getCause	()Ljava/lang/Throwable;
    //   922: athrow
    //   923: astore_1
    //   924: aload_1
    //   925: invokevirtual 133	java/lang/reflect/InvocationTargetException:getCause	()Ljava/lang/Throwable;
    //   928: athrow
    //   929: astore_1
    //   930: aload_1
    //   931: invokevirtual 133	java/lang/reflect/InvocationTargetException:getCause	()Ljava/lang/Throwable;
    //   934: athrow
    //   935: astore_1
    //   936: aload_1
    //   937: invokevirtual 133	java/lang/reflect/InvocationTargetException:getCause	()Ljava/lang/Throwable;
    //   940: athrow
    //   941: astore_1
    //   942: aload_1
    //   943: invokevirtual 133	java/lang/reflect/InvocationTargetException:getCause	()Ljava/lang/Throwable;
    //   946: athrow
    //   947: astore_1
    //   948: aload_1
    //   949: invokevirtual 133	java/lang/reflect/InvocationTargetException:getCause	()Ljava/lang/Throwable;
    //   952: athrow
    //   953: astore_1
    //   954: aload_1
    //   955: invokevirtual 133	java/lang/reflect/InvocationTargetException:getCause	()Ljava/lang/Throwable;
    //   958: athrow
    //   959: astore_1
    //   960: aload_1
    //   961: invokevirtual 133	java/lang/reflect/InvocationTargetException:getCause	()Ljava/lang/Throwable;
    //   964: athrow
    //   965: astore_1
    //   966: aload_1
    //   967: invokevirtual 133	java/lang/reflect/InvocationTargetException:getCause	()Ljava/lang/Throwable;
    //   970: athrow
    // Local variable table:
    //   start	length	slot	name	signature
    //   601	236	0	i	int
    //   35	833	1	localObject	Object
    //   917	2	1	localInvocationTargetException1	java.lang.reflect.InvocationTargetException
    //   923	2	1	localInvocationTargetException2	java.lang.reflect.InvocationTargetException
    //   929	2	1	localInvocationTargetException3	java.lang.reflect.InvocationTargetException
    //   935	2	1	localInvocationTargetException4	java.lang.reflect.InvocationTargetException
    //   941	2	1	localInvocationTargetException5	java.lang.reflect.InvocationTargetException
    //   947	2	1	localInvocationTargetException6	java.lang.reflect.InvocationTargetException
    //   953	2	1	localInvocationTargetException7	java.lang.reflect.InvocationTargetException
    //   959	2	1	localInvocationTargetException8	java.lang.reflect.InvocationTargetException
    //   965	2	1	localInvocationTargetException9	java.lang.reflect.InvocationTargetException
    //   806	66	2	localHhhhyh1	hhhhyh
    //   810	66	3	localHhhhyh2	hhhhyh
    //   814	66	4	localHhhhyh3	hhhhyh
    //   819	66	5	localHhhhyh4	hhhhyh
    //   824	66	6	localHhhhyh5	hhhhyh
    // Exception table:
    //   from	to	target	type
    //   36	67	917	java/lang/reflect/InvocationTargetException
    //   201	231	923	java/lang/reflect/InvocationTargetException
    //   119	150	929	java/lang/reflect/InvocationTargetException
    //   668	698	935	java/lang/reflect/InvocationTargetException
    //   287	326	941	java/lang/reflect/InvocationTargetException
    //   471	502	947	java/lang/reflect/InvocationTargetException
    //   381	420	953	java/lang/reflect/InvocationTargetException
    //   552	582	959	java/lang/reflect/InvocationTargetException
    //   752	783	965	java/lang/reflect/InvocationTargetException
  }
  
  private hhhhyh() {}
  
  public static int b00700070pp007000700070007000700070()
  {
    return 1;
  }
  
  public static int b0070ppp007000700070007000700070()
  {
    return 2;
  }
  
  public static int bp0070pp007000700070007000700070()
  {
    return 0;
  }
  
  public static hhhhyh bpp0070p007000700070007000700070(String paramString)
  {
    if (((bpppp007000700070007000700070() + b00700070pp007000700070007000700070()) * bpppp007000700070007000700070() % b0070ppp007000700070007000700070() == bp0070pp007000700070007000700070()) || ((bpppp007000700070007000700070() + b00700070pp007000700070007000700070()) * bpppp007000700070007000700070() % b0070ppp007000700070007000700070() != bp0070pp007000700070007000700070())) {}
    return (hhhhyh)Enum.valueOf(hhhhyh.class, paramString);
  }
  
  public static int bpppp007000700070007000700070()
  {
    return 9;
  }
}
