package uuuuuu;

import android.support.annotation.NonNull;
import java.lang.reflect.InvocationTargetException;
import java.lang.reflect.Method;
import java.math.BigDecimal;
import java.math.RoundingMode;
import java.text.NumberFormat;
import java.util.Currency;
import java.util.Locale;
import xxxxxx.uxxxxx;

public final class hhhpph
{
  public static int b007900790079007900790079yy0079 = 2;
  private static final String b00790079y007900790079yy0079 = "";
  public static int b0079y0079007900790079yy0079 = 0;
  public static int by00790079007900790079yy0079 = 1;
  public static final Currency by0079y007900790079yy0079;
  public static int byy0079007900790079yy0079 = 41;
  
  static
  {
    Object localObject = ppphhp.class.getMethod(uxxxxx.bbbb0062b0062b0062b0062(">TUVW\021\022\032\033\025\026\036\037`\032\033#$\036\037'(i", '', 'J', '\003'), new Class[] { String.class, Character.TYPE, Character.TYPE });
    try
    {
      localObject = ((Method)localObject).invoke(null, new Object[] { "p{", Character.valueOf('Ó'), Character.valueOf('\003') });
      by0079y007900790079yy0079 = Currency.getInstance((String)localObject);
      if ((byy0079007900790079yy0079 + by00790079007900790079yy0079) * byy0079007900790079yy0079 % bw0077w00770077007700770077ww() != b0079y0079007900790079yy0079)
      {
        byy0079007900790079yy0079 = bwww00770077007700770077ww();
        if ((byy0079007900790079yy0079 + by00790079007900790079yy0079) * byy0079007900790079yy0079 % b007900790079007900790079yy0079 != b0079y0079007900790079yy0079)
        {
          byy0079007900790079yy0079 = bwww00770077007700770077ww();
          b0079y0079007900790079yy0079 = bwww00770077007700770077ww();
        }
        b0079y0079007900790079yy0079 = 48;
      }
      return;
    }
    catch (InvocationTargetException localInvocationTargetException)
    {
      throw localInvocationTargetException.getCause();
    }
  }
  
  private hhhpph() {}
  
  @NonNull
  public static String b00770077007700770077007700770077ww(BigDecimal paramBigDecimal, String paramString, Locale paramLocale)
  {
    Currency localCurrency = Currency.getInstance(paramString);
    paramLocale = NumberFormat.getInstance(paramLocale);
    paramLocale.setMaximumFractionDigits(localCurrency.getDefaultFractionDigits());
    paramLocale.setMinimumFractionDigits(localCurrency.getDefaultFractionDigits());
    int i = byy0079007900790079yy0079;
    switch (i * (by00790079007900790079yy0079 + i) % b007900790079007900790079yy0079)
    {
    default: 
      byy0079007900790079yy0079 = 45;
      b0079y0079007900790079yy0079 = bwww00770077007700770077ww();
    }
    try
    {
      paramBigDecimal = new StringBuilder().append(paramLocale.format(paramBigDecimal));
      paramLocale = ppphhp.class.getMethod(uxxxxx.bbbb0062b0062b0062b0062("m\00298>=|{3287/.43r*)/.&%+*i", 'Z', 'e', '\001'), new Class[] { String.class, Character.TYPE, Character.TYPE, Character.TYPE });
      try
      {
        paramLocale = paramLocale.invoke(null, new Object[] { "3", Character.valueOf('3'), Character.valueOf(''), Character.valueOf('\002') });
        paramLocale = (String)paramLocale;
        return paramLocale + paramString;
      }
      catch (InvocationTargetException paramBigDecimal)
      {
        throw paramBigDecimal.getCause();
      }
      return "";
    }
    catch (IllegalArgumentException paramBigDecimal)
    {
      i = byy0079007900790079yy0079;
      switch (i * (b00770077w00770077007700770077ww() + i) % b007900790079007900790079yy0079)
      {
      default: 
        byy0079007900790079yy0079 = bwww00770077007700770077ww();
        b0079y0079007900790079yy0079 = 58;
      }
    }
  }
  
  public static String b0077007700770077wwww0077w(BigDecimal paramBigDecimal, String paramString)
  {
    if (paramBigDecimal == null)
    {
      if ((byy0079007900790079yy0079 + by00790079007900790079yy0079) * byy0079007900790079yy0079 % b007900790079007900790079yy0079 != b0079y0079007900790079yy0079)
      {
        byy0079007900790079yy0079 = bwww00770077007700770077ww();
        b0079y0079007900790079yy0079 = bwww00770077007700770077ww();
      }
      return "";
    }
    if ((byy0079007900790079yy0079 + by00790079007900790079yy0079) * byy0079007900790079yy0079 % b007900790079007900790079yy0079 != b0079y0079007900790079yy0079)
    {
      byy0079007900790079yy0079 = bwww00770077007700770077ww();
      b0079y0079007900790079yy0079 = bwww00770077007700770077ww();
    }
    return bw0077wwwwww0077w(paramBigDecimal, paramString, Locale.getDefault());
  }
  
  @NonNull
  public static String b007700770077wwwww0077w(@NonNull BigDecimal paramBigDecimal, int paramInt, @NonNull Locale paramLocale)
  {
    paramLocale = NumberFormat.getInstance(paramLocale);
    paramLocale.setMaximumFractionDigits(paramInt);
    if ((bwww00770077007700770077ww() + by00790079007900790079yy0079) * bwww00770077007700770077ww() % bw0077w00770077007700770077ww() != b0079y0079007900790079yy0079)
    {
      int i = byy0079007900790079yy0079;
      switch (i * (b00770077w00770077007700770077ww() + i) % b007900790079007900790079yy0079)
      {
      default: 
        byy0079007900790079yy0079 = 5;
        b0079y0079007900790079yy0079 = 78;
      }
      byy0079007900790079yy0079 = 36;
      b0079y0079007900790079yy0079 = 23;
    }
    try
    {
      paramBigDecimal = paramLocale.format(paramBigDecimal.setScale(paramInt, RoundingMode.HALF_UP));
      return paramBigDecimal;
    }
    catch (ArithmeticException paramBigDecimal)
    {
      return "";
    }
    catch (IllegalArgumentException paramBigDecimal)
    {
      for (;;) {}
    }
  }
  
  public static int b00770077w00770077007700770077ww()
  {
    return 1;
  }
  
  public static boolean b00770077w0077wwww0077w(String paramString)
  {
    if ((paramString == null) || (paramString.isEmpty())) {
      return false;
    }
    int i;
    while (Character.isDigit(paramString.charAt(i)))
    {
      i += 1;
      int j;
      while (i >= j)
      {
        return true;
        j = paramString.length();
        i = byy0079007900790079yy0079;
        switch (i * (by00790079007900790079yy0079 + i) % b007900790079007900790079yy0079)
        {
        default: 
          byy0079007900790079yy0079 = 4;
          b0079y0079007900790079yy0079 = 96;
          if ((byy0079007900790079yy0079 + by00790079007900790079yy0079) * byy0079007900790079yy0079 % b007900790079007900790079yy0079 != b0079y0079007900790079yy0079)
          {
            byy0079007900790079yy0079 = bwww00770077007700770077ww();
            b0079y0079007900790079yy0079 = 33;
          }
          break;
        }
        i = 0;
      }
    }
  }
  
  @NonNull
  public static String b00770077wwwwww0077w(BigDecimal paramBigDecimal, String paramString, boolean paramBoolean, Locale paramLocale)
  {
    paramString = Currency.getInstance(paramString);
    int i = paramString.getDefaultFractionDigits();
    int j = bwww00770077007700770077ww();
    int k = by00790079007900790079yy0079;
    int m = bwww00770077007700770077ww();
    int n = b007900790079007900790079yy0079;
    int i1 = b0079y0079007900790079yy0079;
    int i2 = byy0079007900790079yy0079;
    switch (i2 * (by00790079007900790079yy0079 + i2) % b007900790079007900790079yy0079)
    {
    default: 
      byy0079007900790079yy0079 = 3;
      b0079y0079007900790079yy0079 = bwww00770077007700770077ww();
    }
    if ((j + k) * m % n != i1)
    {
      byy0079007900790079yy0079 = 26;
      b0079y0079007900790079yy0079 = bwww00770077007700770077ww();
    }
    return bww0077wwwww0077w(paramBigDecimal, paramString, i, paramBoolean, paramLocale);
  }
  
  public static String b0077w007700770077007700770077ww(@NonNull String paramString, @NonNull Locale paramLocale)
  {
    paramString = bww007700770077007700770077ww(paramString, 2, paramLocale);
    int i = byy0079007900790079yy0079;
    switch (i * (by00790079007900790079yy0079 + i) % b007900790079007900790079yy0079)
    {
    default: 
      if ((byy0079007900790079yy0079 + by00790079007900790079yy0079) * byy0079007900790079yy0079 % b007900790079007900790079yy0079 != b0077ww00770077007700770077ww())
      {
        byy0079007900790079yy0079 = 88;
        b0079y0079007900790079yy0079 = 66;
      }
      byy0079007900790079yy0079 = 97;
      b0079y0079007900790079yy0079 = bwww00770077007700770077ww();
    }
    return paramString;
  }
  
  public static boolean b0077w00770077wwww0077w(@NonNull BigDecimal paramBigDecimal)
  {
    if (paramBigDecimal.compareTo(BigDecimal.ZERO) == 0)
    {
      int i = byy0079007900790079yy0079;
      int j = by00790079007900790079yy0079;
      int k = byy0079007900790079yy0079;
      int m = b007900790079007900790079yy0079;
      int n = b0079y0079007900790079yy0079;
      int i1 = byy0079007900790079yy0079;
      switch (i1 * (b00770077w00770077007700770077ww() + i1) % b007900790079007900790079yy0079)
      {
      default: 
        byy0079007900790079yy0079 = 44;
        b0079y0079007900790079yy0079 = bwww00770077007700770077ww();
      }
      if ((i + j) * k % m != n)
      {
        byy0079007900790079yy0079 = bwww00770077007700770077ww();
        b0079y0079007900790079yy0079 = 19;
      }
      return true;
    }
    return false;
  }
  
  @NonNull
  public static String b0077w0077wwwww0077w(String paramString1, String paramString2, Locale paramLocale)
  {
    int i = byy0079007900790079yy0079;
    int j = by00790079007900790079yy0079;
    int k = byy0079007900790079yy0079;
    int m = b007900790079007900790079yy0079;
    int n = byy0079007900790079yy0079;
    switch (n * (by00790079007900790079yy0079 + n) % b007900790079007900790079yy0079)
    {
    default: 
      byy0079007900790079yy0079 = 2;
      b0079y0079007900790079yy0079 = bwww00770077007700770077ww();
    }
    if ((i + j) * k % m != b0079y0079007900790079yy0079)
    {
      byy0079007900790079yy0079 = bwww00770077007700770077ww();
      b0079y0079007900790079yy0079 = bwww00770077007700770077ww();
    }
    return bw0077wwwwww0077w(new BigDecimal(paramString1), paramString2, paramLocale);
  }
  
  public static int b0077ww00770077007700770077ww()
  {
    return 0;
  }
  
  private static boolean b0077ww0077wwww0077w(BigDecimal paramBigDecimal)
  {
    boolean bool2;
    if ((paramBigDecimal.signum() == 0) || (paramBigDecimal.scale() <= 0) || (paramBigDecimal.stripTrailingZeros().scale() <= 0))
    {
      bool2 = true;
      int i = byy0079007900790079yy0079;
      bool1 = bool2;
      switch (i * (by00790079007900790079yy0079 + i) % b007900790079007900790079yy0079)
      {
      default: 
        byy0079007900790079yy0079 = 69;
        b0079y0079007900790079yy0079 = bwww00770077007700770077ww();
      }
    }
    for (boolean bool1 = bool2;; bool1 = false)
    {
      if ((byy0079007900790079yy0079 + b00770077w00770077007700770077ww()) * byy0079007900790079yy0079 % b007900790079007900790079yy0079 != b0079y0079007900790079yy0079)
      {
        byy0079007900790079yy0079 = 87;
        b0079y0079007900790079yy0079 = 92;
      }
      return bool1;
    }
  }
  
  @NonNull
  public static String b0077wwwwwww0077w(BigDecimal paramBigDecimal, String paramString, int paramInt, Locale paramLocale)
  {
    paramString = Currency.getInstance(paramString);
    if ((byy0079007900790079yy0079 + by00790079007900790079yy0079) * byy0079007900790079yy0079 % b007900790079007900790079yy0079 != b0079y0079007900790079yy0079)
    {
      if ((byy0079007900790079yy0079 + by00790079007900790079yy0079) * byy0079007900790079yy0079 % b007900790079007900790079yy0079 != b0079y0079007900790079yy0079)
      {
        byy0079007900790079yy0079 = 29;
        b0079y0079007900790079yy0079 = bwww00770077007700770077ww();
      }
      byy0079007900790079yy0079 = 57;
      b0079y0079007900790079yy0079 = bwww00770077007700770077ww();
    }
    return bww0077wwwww0077w(paramBigDecimal, paramString, paramInt, false, paramLocale);
  }
  
  /* Error */
  public static String bw0077007700770077007700770077ww(@NonNull String paramString1, @NonNull String paramString2, @NonNull Locale paramLocale)
  {
    // Byte code:
    //   0: ldc 25
    //   2: ldc -28
    //   4: bipush 70
    //   6: iconst_0
    //   7: invokestatic 232	xxxxxx/uxxxxx:bb00620062bb0062b0062b0062	(Ljava/lang/String;CC)Ljava/lang/String;
    //   10: iconst_4
    //   11: anewarray 35	java/lang/Class
    //   14: dup
    //   15: iconst_0
    //   16: ldc 37
    //   18: aastore
    //   19: dup
    //   20: iconst_1
    //   21: getstatic 43	java/lang/Character:TYPE	Ljava/lang/Class;
    //   24: aastore
    //   25: dup
    //   26: iconst_2
    //   27: getstatic 43	java/lang/Character:TYPE	Ljava/lang/Class;
    //   30: aastore
    //   31: dup
    //   32: iconst_3
    //   33: getstatic 43	java/lang/Character:TYPE	Ljava/lang/Class;
    //   36: aastore
    //   37: invokevirtual 47	java/lang/Class:getMethod	(Ljava/lang/String;[Ljava/lang/Class;)Ljava/lang/reflect/Method;
    //   40: astore_3
    //   41: aload_3
    //   42: aconst_null
    //   43: iconst_4
    //   44: anewarray 4	java/lang/Object
    //   47: dup
    //   48: iconst_0
    //   49: ldc -22
    //   51: aastore
    //   52: dup
    //   53: iconst_1
    //   54: sipush 203
    //   57: invokestatic 53	java/lang/Character:valueOf	(C)Ljava/lang/Character;
    //   60: aastore
    //   61: dup
    //   62: iconst_2
    //   63: bipush 120
    //   65: invokestatic 53	java/lang/Character:valueOf	(C)Ljava/lang/Character;
    //   68: aastore
    //   69: dup
    //   70: iconst_3
    //   71: iconst_1
    //   72: invokestatic 53	java/lang/Character:valueOf	(C)Ljava/lang/Character;
    //   75: aastore
    //   76: invokevirtual 59	java/lang/reflect/Method:invoke	(Ljava/lang/Object;[Ljava/lang/Object;)Ljava/lang/Object;
    //   79: astore_3
    //   80: aload_3
    //   81: checkcast 37	java/lang/String
    //   84: astore_3
    //   85: new 156	java/math/BigDecimal
    //   88: dup
    //   89: aload_0
    //   90: invokespecial 208	java/math/BigDecimal:<init>	(Ljava/lang/String;)V
    //   93: astore_0
    //   94: aload_2
    //   95: invokestatic 237	java/text/NumberFormat:getNumberInstance	(Ljava/util/Locale;)Ljava/text/NumberFormat;
    //   98: astore 4
    //   100: getstatic 69	uuuuuu/hhhpph:byy0079007900790079yy0079	I
    //   103: getstatic 71	uuuuuu/hhhpph:by00790079007900790079yy0079	I
    //   106: iadd
    //   107: getstatic 69	uuuuuu/hhhpph:byy0079007900790079yy0079	I
    //   110: imul
    //   111: getstatic 82	uuuuuu/hhhpph:b007900790079007900790079yy0079	I
    //   114: irem
    //   115: getstatic 77	uuuuuu/hhhpph:b0079y0079007900790079yy0079	I
    //   118: if_icmpeq +14 -> 132
    //   121: bipush 59
    //   123: putstatic 69	uuuuuu/hhhpph:byy0079007900790079yy0079	I
    //   126: invokestatic 80	uuuuuu/hhhpph:bwww00770077007700770077ww	()I
    //   129: putstatic 77	uuuuuu/hhhpph:b0079y0079007900790079yy0079	I
    //   132: aload_0
    //   133: invokestatic 240	uuuuuu/hhhpph:bwww0077wwww0077w	(Ljava/math/BigDecimal;)Z
    //   136: ifeq +137 -> 273
    //   139: aload 4
    //   141: iconst_4
    //   142: invokevirtual 110	java/text/NumberFormat:setMinimumFractionDigits	(I)V
    //   145: aload 4
    //   147: iconst_4
    //   148: invokevirtual 107	java/text/NumberFormat:setMaximumFractionDigits	(I)V
    //   151: aload 4
    //   153: aload_0
    //   154: invokevirtual 117	java/text/NumberFormat:format	(Ljava/lang/Object;)Ljava/lang/String;
    //   157: astore_0
    //   158: new 242	java/util/Formatter
    //   161: dup
    //   162: aload_2
    //   163: invokespecial 245	java/util/Formatter:<init>	(Ljava/util/Locale;)V
    //   166: astore_2
    //   167: aload_2
    //   168: aload_1
    //   169: iconst_1
    //   170: anewarray 4	java/lang/Object
    //   173: dup
    //   174: iconst_0
    //   175: aload_0
    //   176: aastore
    //   177: invokevirtual 248	java/util/Formatter:format	(Ljava/lang/String;[Ljava/lang/Object;)Ljava/util/Formatter;
    //   180: invokevirtual 249	java/util/Formatter:toString	()Ljava/lang/String;
    //   183: astore_0
    //   184: aload_2
    //   185: ifnull +7 -> 192
    //   188: aload_2
    //   189: invokevirtual 252	java/util/Formatter:close	()V
    //   192: aload_0
    //   193: areturn
    //   194: astore_0
    //   195: aload_0
    //   196: invokevirtual 86	java/lang/reflect/InvocationTargetException:getCause	()Ljava/lang/Throwable;
    //   199: athrow
    //   200: astore_1
    //   201: aconst_null
    //   202: astore_0
    //   203: aload_2
    //   204: ifnull +44 -> 248
    //   207: getstatic 69	uuuuuu/hhhpph:byy0079007900790079yy0079	I
    //   210: getstatic 71	uuuuuu/hhhpph:by00790079007900790079yy0079	I
    //   213: iadd
    //   214: getstatic 69	uuuuuu/hhhpph:byy0079007900790079yy0079	I
    //   217: imul
    //   218: invokestatic 75	uuuuuu/hhhpph:bw0077w00770077007700770077ww	()I
    //   221: irem
    //   222: getstatic 77	uuuuuu/hhhpph:b0079y0079007900790079yy0079	I
    //   225: if_icmpeq +15 -> 240
    //   228: invokestatic 80	uuuuuu/hhhpph:bwww00770077007700770077ww	()I
    //   231: putstatic 69	uuuuuu/hhhpph:byy0079007900790079yy0079	I
    //   234: invokestatic 80	uuuuuu/hhhpph:bwww00770077007700770077ww	()I
    //   237: putstatic 77	uuuuuu/hhhpph:b0079y0079007900790079yy0079	I
    //   240: aload_0
    //   241: ifnull +18 -> 259
    //   244: aload_2
    //   245: invokevirtual 252	java/util/Formatter:close	()V
    //   248: aload_1
    //   249: athrow
    //   250: astore_2
    //   251: aload_0
    //   252: aload_2
    //   253: invokevirtual 256	java/lang/Throwable:addSuppressed	(Ljava/lang/Throwable;)V
    //   256: goto -8 -> 248
    //   259: aload_2
    //   260: invokevirtual 252	java/util/Formatter:close	()V
    //   263: goto -15 -> 248
    //   266: astore_0
    //   267: aload_0
    //   268: athrow
    //   269: astore_1
    //   270: goto -67 -> 203
    //   273: aload 4
    //   275: iconst_0
    //   276: invokevirtual 110	java/text/NumberFormat:setMinimumFractionDigits	(I)V
    //   279: aload 4
    //   281: iconst_0
    //   282: invokevirtual 107	java/text/NumberFormat:setMaximumFractionDigits	(I)V
    //   285: goto -134 -> 151
    //   288: astore_0
    //   289: aload_3
    //   290: astore_0
    //   291: goto -133 -> 158
    // Local variable table:
    //   start	length	slot	name	signature
    //   0	294	0	paramString1	String
    //   0	294	1	paramString2	String
    //   0	294	2	paramLocale	Locale
    //   40	250	3	localObject	Object
    //   98	182	4	localNumberFormat	NumberFormat
    // Exception table:
    //   from	to	target	type
    //   41	80	194	java/lang/reflect/InvocationTargetException
    //   167	184	200	finally
    //   244	248	250	java/lang/Throwable
    //   167	184	266	java/lang/Throwable
    //   267	269	269	finally
    //   85	100	288	java/lang/NumberFormatException
    //   132	151	288	java/lang/NumberFormatException
    //   151	158	288	java/lang/NumberFormatException
    //   273	285	288	java/lang/NumberFormatException
  }
  
  public static boolean bw007700770077wwww0077w(@NonNull BigDecimal paramBigDecimal)
  {
    if ((b0077w00770077wwww0077w(paramBigDecimal)) || (bww00770077wwww0077w(paramBigDecimal)))
    {
      bool = true;
      return bool;
    }
    boolean bool = false;
    int i = bwww00770077007700770077ww();
    switch (i * (by00790079007900790079yy0079 + i) % b007900790079007900790079yy0079)
    {
    default: 
      byy0079007900790079yy0079 = 11;
      b0079y0079007900790079yy0079 = bwww00770077007700770077ww();
    }
    i = byy0079007900790079yy0079;
    switch (i * (by00790079007900790079yy0079 + i) % b007900790079007900790079yy0079)
    {
    }
    byy0079007900790079yy0079 = bwww00770077007700770077ww();
    b0079y0079007900790079yy0079 = 78;
    return false;
  }
  
  @NonNull
  public static String bw00770077wwwww0077w(BigDecimal paramBigDecimal, int paramInt, Locale paramLocale, boolean paramBoolean)
  {
    paramLocale = NumberFormat.getInstance(paramLocale);
    if ((byy0079007900790079yy0079 + by00790079007900790079yy0079) * byy0079007900790079yy0079 % b007900790079007900790079yy0079 != b0079y0079007900790079yy0079)
    {
      byy0079007900790079yy0079 = 80;
      b0079y0079007900790079yy0079 = 40;
    }
    paramLocale.setMaximumFractionDigits(paramInt);
    paramLocale.setMinimumFractionDigits(paramInt);
    if (paramBoolean) {
      if ((byy0079007900790079yy0079 + by00790079007900790079yy0079) * byy0079007900790079yy0079 % b007900790079007900790079yy0079 != b0079y0079007900790079yy0079)
      {
        byy0079007900790079yy0079 = 19;
        b0079y0079007900790079yy0079 = 54;
      }
    }
    try
    {
      return paramLocale.format(paramBigDecimal);
    }
    catch (IllegalArgumentException paramBigDecimal) {}
    paramLocale.setGroupingUsed(false);
    paramBigDecimal = paramLocale.format(paramBigDecimal);
    return paramBigDecimal;
    return "";
  }
  
  public static int bw0077w00770077007700770077ww()
  {
    return 2;
  }
  
  public static boolean bw0077w0077wwww0077w(@NonNull BigDecimal paramBigDecimal)
  {
    if ((byy0079007900790079yy0079 + by00790079007900790079yy0079) * byy0079007900790079yy0079 % bw0077w00770077007700770077ww() != b0079y0079007900790079yy0079)
    {
      byy0079007900790079yy0079 = bwww00770077007700770077ww();
      b0079y0079007900790079yy0079 = 85;
      int i = byy0079007900790079yy0079;
      switch (i * (by00790079007900790079yy0079 + i) % bw0077w00770077007700770077ww())
      {
      default: 
        byy0079007900790079yy0079 = bwww00770077007700770077ww();
        b0079y0079007900790079yy0079 = 84;
      }
    }
    return paramBigDecimal.compareTo(BigDecimal.ZERO) < 0;
  }
  
  @NonNull
  public static String bw0077wwwwww0077w(BigDecimal paramBigDecimal, String paramString, Locale paramLocale)
  {
    int i = byy0079007900790079yy0079;
    switch (i * (by00790079007900790079yy0079 + i) % b007900790079007900790079yy0079)
    {
    default: 
      byy0079007900790079yy0079 = 15;
      b0079y0079007900790079yy0079 = bwww00770077007700770077ww();
    }
    if ((byy0079007900790079yy0079 + by00790079007900790079yy0079) * byy0079007900790079yy0079 % b007900790079007900790079yy0079 != b0077ww00770077007700770077ww())
    {
      byy0079007900790079yy0079 = bwww00770077007700770077ww();
      b0079y0079007900790079yy0079 = bwww00770077007700770077ww();
    }
    return b00770077wwwwww0077w(paramBigDecimal, paramString, false, paramLocale);
  }
  
  public static String bww007700770077007700770077ww(@NonNull String paramString, int paramInt, @NonNull Locale paramLocale)
  {
    paramString = new BigDecimal(paramString);
    int i = byy0079007900790079yy0079;
    switch (i * (by00790079007900790079yy0079 + i) % b007900790079007900790079yy0079)
    {
    default: 
      byy0079007900790079yy0079 = 27;
      b0079y0079007900790079yy0079 = 19;
    }
    paramLocale = NumberFormat.getInstance(paramLocale);
    paramLocale.setMinimumFractionDigits(paramInt);
    i = byy0079007900790079yy0079;
    switch (i * (by00790079007900790079yy0079 + i) % b007900790079007900790079yy0079)
    {
    default: 
      byy0079007900790079yy0079 = bwww00770077007700770077ww();
      b0079y0079007900790079yy0079 = bwww00770077007700770077ww();
    }
    paramLocale.setMaximumFractionDigits(paramInt);
    paramString = new StringBuilder().append(paramLocale.format(paramString));
    paramLocale = ppphhp.class.getMethod(uxxxxx.bbbb0062b0062b0062b0062("\007\035\036\037 YZbc]^fg)bcklfgop2", 'D', '_', '\003'), new Class[] { String.class, Character.TYPE, Character.TYPE });
    try
    {
      paramLocale = paramLocale.invoke(null, new Object[] { ";A", Character.valueOf(''), Character.valueOf('\000') });
      return (String)paramLocale;
    }
    catch (InvocationTargetException paramString)
    {
      throw paramString.getCause();
    }
  }
  
  public static boolean bww00770077wwww0077w(@NonNull BigDecimal paramBigDecimal)
  {
    int i = paramBigDecimal.compareTo(BigDecimal.ZERO);
    if ((byy0079007900790079yy0079 + by00790079007900790079yy0079) * byy0079007900790079yy0079 % b007900790079007900790079yy0079 != b0079y0079007900790079yy0079)
    {
      byy0079007900790079yy0079 = 30;
      b0079y0079007900790079yy0079 = 94;
      if ((byy0079007900790079yy0079 + by00790079007900790079yy0079) * byy0079007900790079yy0079 % bw0077w00770077007700770077ww() != b0079y0079007900790079yy0079)
      {
        byy0079007900790079yy0079 = 6;
        b0079y0079007900790079yy0079 = 24;
      }
    }
    return i > 0;
  }
  
  @NonNull
  public static String bww0077wwwww0077w(BigDecimal paramBigDecimal, Currency paramCurrency, int paramInt, boolean paramBoolean, Locale paramLocale)
  {
    if (paramBigDecimal == null)
    {
      paramBigDecimal = "";
      return paramBigDecimal;
    }
    try
    {
      paramLocale = NumberFormat.getCurrencyInstance(paramLocale);
      paramLocale.setCurrency(paramCurrency);
      paramLocale.setMaximumFractionDigits(paramInt);
      paramCurrency = paramLocale.format(paramBigDecimal);
      if ((paramBoolean) && (bww00770077wwww0077w(paramBigDecimal)))
      {
        paramBigDecimal = new StringBuilder();
        if ((byy0079007900790079yy0079 + by00790079007900790079yy0079) * byy0079007900790079yy0079 % b007900790079007900790079yy0079 != b0079y0079007900790079yy0079)
        {
          byy0079007900790079yy0079 = 51;
          b0079y0079007900790079yy0079 = 38;
        }
        paramLocale = ppphhp.class.getMethod(uxxxxx.bbbb0062b0062b0062b0062("Oefgh\"#+,&'/0q+,45/089z", 'ó', 'w', '\003'), new Class[] { String.class, Character.TYPE, Character.TYPE });
        try
        {
          paramLocale = paramLocale.invoke(null, new Object[] { "\002", Character.valueOf('ª'), Character.valueOf('\001') });
          paramLocale = (String)paramLocale;
          paramCurrency = paramLocale + paramCurrency;
          paramInt = bwww00770077007700770077ww();
          paramBigDecimal = paramCurrency;
          switch (paramInt * (by00790079007900790079yy0079 + paramInt) % b007900790079007900790079yy0079)
          {
          }
          byy0079007900790079yy0079 = bwww00770077007700770077ww();
          b0079y0079007900790079yy0079 = 73;
          return paramCurrency;
        }
        catch (InvocationTargetException paramBigDecimal)
        {
          throw paramBigDecimal.getCause();
        }
      }
      return paramCurrency;
    }
    catch (IllegalArgumentException paramBigDecimal)
    {
      return "";
    }
  }
  
  public static int bwww00770077007700770077ww()
  {
    return 17;
  }
  
  public static boolean bwww0077wwww0077w(BigDecimal paramBigDecimal)
  {
    if (!b0077ww0077wwww0077w(paramBigDecimal))
    {
      if ((byy0079007900790079yy0079 + by00790079007900790079yy0079) * byy0079007900790079yy0079 % b007900790079007900790079yy0079 != b0079y0079007900790079yy0079)
      {
        byy0079007900790079yy0079 = bwww00770077007700770077ww();
        b0079y0079007900790079yy0079 = bwww00770077007700770077ww();
      }
      int i = byy0079007900790079yy0079;
      switch (i * (b00770077w00770077007700770077ww() + i) % b007900790079007900790079yy0079)
      {
      default: 
        byy0079007900790079yy0079 = bwww00770077007700770077ww();
        b0079y0079007900790079yy0079 = 42;
      }
      return true;
    }
    return false;
  }
  
  @NonNull
  public static String bwwwwwwww0077w(String paramString)
  {
    if ((byy0079007900790079yy0079 + by00790079007900790079yy0079) * byy0079007900790079yy0079 % b007900790079007900790079yy0079 != b0079y0079007900790079yy0079)
    {
      byy0079007900790079yy0079 = 69;
      b0079y0079007900790079yy0079 = 91;
    }
    Locale localLocale = Locale.getDefault();
    paramString = Currency.getInstance(paramString);
    NumberFormat.getCurrencyInstance(localLocale).setCurrency(paramString);
    paramString = paramString.getSymbol();
    if ((byy0079007900790079yy0079 + b00770077w00770077007700770077ww()) * byy0079007900790079yy0079 % b007900790079007900790079yy0079 != b0079y0079007900790079yy0079)
    {
      byy0079007900790079yy0079 = bwww00770077007700770077ww();
      b0079y0079007900790079yy0079 = 16;
    }
    return paramString;
  }
}
