package uuuuuu;

import com.db.pwcc.dbmobile.model.securities.SecurityPositions;
import rx.Observable;

public class hhyhyy
  extends hyyhhy<SecurityPositions>
{
  public static int b00700070p00700070p00700070p = 0;
  public static int b0070pp00700070p00700070p = 1;
  public static int bp0070p00700070p00700070p = 2;
  public static int bppp00700070p00700070p = 42;
  public Observable<SecurityPositions> b007000700070p0070p00700070p;
  public ffmmmf bp00700070p0070p00700070p = new ffmmmf();
  
  public hhyhyy() {}
  
  public static int b006F006Fo006Fo006F006Fooo()
  {
    return 1;
  }
  
  public static int b006Fo006F006Fo006F006Fooo()
  {
    return 0;
  }
  
  public static int bo006F006F006Fo006F006Fooo()
  {
    return 2;
  }
  
  public static int boo006F006Fo006F006Fooo()
  {
    return 88;
  }
  
  /* Error */
  public boolean b006F006F006F006Fo006F006Fooo(SecurityPositions paramSecurityPositions)
  {
    // Byte code:
    //   0: aload_1
    //   1: ifnonnull +200 -> 201
    //   4: getstatic 46	uuuuuu/hhyhyy:bppp00700070p00700070p	I
    //   7: istore_2
    //   8: getstatic 46	uuuuuu/hhyhyy:bppp00700070p00700070p	I
    //   11: getstatic 48	uuuuuu/hhyhyy:b0070pp00700070p00700070p	I
    //   14: iadd
    //   15: getstatic 46	uuuuuu/hhyhyy:bppp00700070p00700070p	I
    //   18: imul
    //   19: getstatic 50	uuuuuu/hhyhyy:bp0070p00700070p00700070p	I
    //   22: irem
    //   23: getstatic 52	uuuuuu/hhyhyy:b00700070p00700070p00700070p	I
    //   26: if_icmpeq +47 -> 73
    //   29: ldc 2
    //   31: ldc 54
    //   33: sipush 226
    //   36: iconst_5
    //   37: invokestatic 60	xxxxxx/uxxxxx:bb00620062bb0062b0062b0062	(Ljava/lang/String;CC)Ljava/lang/String;
    //   40: iconst_0
    //   41: anewarray 62	java/lang/Class
    //   44: invokevirtual 66	java/lang/Class:getMethod	(Ljava/lang/String;[Ljava/lang/Class;)Ljava/lang/reflect/Method;
    //   47: astore_1
    //   48: aload_1
    //   49: aconst_null
    //   50: iconst_0
    //   51: anewarray 68	java/lang/Object
    //   54: invokevirtual 74	java/lang/reflect/Method:invoke	(Ljava/lang/Object;[Ljava/lang/Object;)Ljava/lang/Object;
    //   57: astore_1
    //   58: aload_1
    //   59: checkcast 76	java/lang/Integer
    //   62: invokevirtual 79	java/lang/Integer:intValue	()I
    //   65: putstatic 46	uuuuuu/hhyhyy:bppp00700070p00700070p	I
    //   68: bipush 62
    //   70: putstatic 52	uuuuuu/hhyhyy:b00700070p00700070p00700070p	I
    //   73: getstatic 48	uuuuuu/hhyhyy:b0070pp00700070p00700070p	I
    //   76: iload_2
    //   77: iadd
    //   78: getstatic 46	uuuuuu/hhyhyy:bppp00700070p00700070p	I
    //   81: imul
    //   82: getstatic 50	uuuuuu/hhyhyy:bp0070p00700070p00700070p	I
    //   85: irem
    //   86: getstatic 52	uuuuuu/hhyhyy:b00700070p00700070p00700070p	I
    //   89: if_icmpeq +49 -> 138
    //   92: bipush 9
    //   94: putstatic 46	uuuuuu/hhyhyy:bppp00700070p00700070p	I
    //   97: ldc 2
    //   99: ldc 81
    //   101: sipush 198
    //   104: bipush 44
    //   106: iconst_3
    //   107: invokestatic 85	xxxxxx/uxxxxx:bbbb0062b0062b0062b0062	(Ljava/lang/String;CCC)Ljava/lang/String;
    //   110: iconst_0
    //   111: anewarray 62	java/lang/Class
    //   114: invokevirtual 66	java/lang/Class:getMethod	(Ljava/lang/String;[Ljava/lang/Class;)Ljava/lang/reflect/Method;
    //   117: astore_1
    //   118: aload_1
    //   119: aconst_null
    //   120: iconst_0
    //   121: anewarray 68	java/lang/Object
    //   124: invokevirtual 74	java/lang/reflect/Method:invoke	(Ljava/lang/Object;[Ljava/lang/Object;)Ljava/lang/Object;
    //   127: astore_1
    //   128: aload_1
    //   129: checkcast 76	java/lang/Integer
    //   132: invokevirtual 79	java/lang/Integer:intValue	()I
    //   135: putstatic 52	uuuuuu/hhyhyy:b00700070p00700070p00700070p	I
    //   138: iconst_0
    //   139: ireturn
    //   140: astore 4
    //   142: ldc 2
    //   144: ldc 87
    //   146: bipush 43
    //   148: bipush 56
    //   150: iconst_1
    //   151: invokestatic 85	xxxxxx/uxxxxx:bbbb0062b0062b0062b0062	(Ljava/lang/String;CCC)Ljava/lang/String;
    //   154: iconst_0
    //   155: anewarray 62	java/lang/Class
    //   158: invokevirtual 66	java/lang/Class:getMethod	(Ljava/lang/String;[Ljava/lang/Class;)Ljava/lang/reflect/Method;
    //   161: astore 4
    //   163: aload 4
    //   165: aconst_null
    //   166: iconst_0
    //   167: anewarray 68	java/lang/Object
    //   170: invokevirtual 74	java/lang/reflect/Method:invoke	(Ljava/lang/Object;[Ljava/lang/Object;)Ljava/lang/Object;
    //   173: astore 4
    //   175: aload 4
    //   177: checkcast 76	java/lang/Integer
    //   180: invokevirtual 79	java/lang/Integer:intValue	()I
    //   183: putstatic 46	uuuuuu/hhyhyy:bppp00700070p00700070p	I
    //   186: aload_1
    //   187: invokevirtual 93	com/db/pwcc/dbmobile/model/securities/SecurityPosition:getSecurity	()Lcom/db/pwcc/dbmobile/model/securities/Security;
    //   190: ifnull +156 -> 346
    //   193: iconst_1
    //   194: ireturn
    //   195: astore_1
    //   196: aload_1
    //   197: invokevirtual 97	java/lang/reflect/InvocationTargetException:getCause	()Ljava/lang/Throwable;
    //   200: athrow
    //   201: aload_1
    //   202: invokevirtual 103	com/db/pwcc/dbmobile/model/securities/SecurityPositions:getSecurityPositions	()Ljava/util/List;
    //   205: ifnull +141 -> 346
    //   208: getstatic 46	uuuuuu/hhyhyy:bppp00700070p00700070p	I
    //   211: istore_2
    //   212: getstatic 48	uuuuuu/hhyhyy:b0070pp00700070p00700070p	I
    //   215: istore_3
    //   216: ldc 2
    //   218: ldc 105
    //   220: sipush 217
    //   223: iconst_4
    //   224: invokestatic 60	xxxxxx/uxxxxx:bb00620062bb0062b0062b0062	(Ljava/lang/String;CC)Ljava/lang/String;
    //   227: iconst_0
    //   228: anewarray 62	java/lang/Class
    //   231: invokevirtual 66	java/lang/Class:getMethod	(Ljava/lang/String;[Ljava/lang/Class;)Ljava/lang/reflect/Method;
    //   234: astore 4
    //   236: aload 4
    //   238: aconst_null
    //   239: iconst_0
    //   240: anewarray 68	java/lang/Object
    //   243: invokevirtual 74	java/lang/reflect/Method:invoke	(Ljava/lang/Object;[Ljava/lang/Object;)Ljava/lang/Object;
    //   246: astore 4
    //   248: iload_3
    //   249: iload_2
    //   250: iadd
    //   251: iload_2
    //   252: imul
    //   253: aload 4
    //   255: checkcast 76	java/lang/Integer
    //   258: invokevirtual 79	java/lang/Integer:intValue	()I
    //   261: irem
    //   262: tableswitch	default:+18->280, 0:+28->290
    //   280: bipush 27
    //   282: putstatic 46	uuuuuu/hhyhyy:bppp00700070p00700070p	I
    //   285: bipush 30
    //   287: putstatic 52	uuuuuu/hhyhyy:b00700070p00700070p00700070p	I
    //   290: aload_1
    //   291: invokevirtual 103	com/db/pwcc/dbmobile/model/securities/SecurityPositions:getSecurityPositions	()Ljava/util/List;
    //   294: invokeinterface 111 1 0
    //   299: ifne +47 -> 346
    //   302: aload_1
    //   303: invokevirtual 103	com/db/pwcc/dbmobile/model/securities/SecurityPositions:getSecurityPositions	()Ljava/util/List;
    //   306: iconst_0
    //   307: invokeinterface 115 2 0
    //   312: checkcast 89	com/db/pwcc/dbmobile/model/securities/SecurityPosition
    //   315: astore_1
    //   316: aload_1
    //   317: ifnull +29 -> 346
    //   320: new 117	java/lang/NullPointerException
    //   323: dup
    //   324: invokespecial 118	java/lang/NullPointerException:<init>	()V
    //   327: athrow
    //   328: astore_1
    //   329: aload_1
    //   330: invokevirtual 97	java/lang/reflect/InvocationTargetException:getCause	()Ljava/lang/Throwable;
    //   333: athrow
    //   334: astore_1
    //   335: aload_1
    //   336: invokevirtual 97	java/lang/reflect/InvocationTargetException:getCause	()Ljava/lang/Throwable;
    //   339: athrow
    //   340: astore_1
    //   341: aload_1
    //   342: invokevirtual 97	java/lang/reflect/InvocationTargetException:getCause	()Ljava/lang/Throwable;
    //   345: athrow
    //   346: iconst_0
    //   347: ireturn
    // Local variable table:
    //   start	length	slot	name	signature
    //   0	348	0	this	hhyhyy
    //   0	348	1	paramSecurityPositions	SecurityPositions
    //   7	246	2	i	int
    //   215	36	3	j	int
    //   140	1	4	localException	Exception
    //   161	93	4	localObject	Object
    // Exception table:
    //   from	to	target	type
    //   320	328	140	java/lang/Exception
    //   163	175	195	java/lang/reflect/InvocationTargetException
    //   236	248	328	java/lang/reflect/InvocationTargetException
    //   118	128	334	java/lang/reflect/InvocationTargetException
    //   48	58	340	java/lang/reflect/InvocationTargetException
  }
  
  /* Error */
  public void b006Fo006F006F006F006Foooo()
  {
    // Byte code:
    //   0: aload_0
    //   1: getfield 153	uuuuuu/hhyhyy:b007000700070p0070p00700070p	Lrx/Observable;
    //   4: ifnonnull +4 -> 8
    //   7: return
    //   8: aload_0
    //   9: getfield 153	uuuuuu/hhyhyy:b007000700070p0070p00700070p	Lrx/Observable;
    //   12: invokestatic 159	rx/schedulers/Schedulers:io	()Lrx/Scheduler;
    //   15: invokevirtual 165	rx/Observable:subscribeOn	(Lrx/Scheduler;)Lrx/Observable;
    //   18: invokestatic 170	rx/android/schedulers/AndroidSchedulers:mainThread	()Lrx/Scheduler;
    //   21: invokevirtual 173	rx/Observable:observeOn	(Lrx/Scheduler;)Lrx/Observable;
    //   24: astore 5
    //   26: getstatic 46	uuuuuu/hhyhyy:bppp00700070p00700070p	I
    //   29: istore_1
    //   30: getstatic 48	uuuuuu/hhyhyy:b0070pp00700070p00700070p	I
    //   33: istore_2
    //   34: getstatic 46	uuuuuu/hhyhyy:bppp00700070p00700070p	I
    //   37: istore_3
    //   38: getstatic 50	uuuuuu/hhyhyy:bp0070p00700070p00700070p	I
    //   41: istore 4
    //   43: ldc 2
    //   45: ldc -81
    //   47: sipush 162
    //   50: sipush 158
    //   53: iconst_3
    //   54: invokestatic 85	xxxxxx/uxxxxx:bbbb0062b0062b0062b0062	(Ljava/lang/String;CCC)Ljava/lang/String;
    //   57: iconst_0
    //   58: anewarray 62	java/lang/Class
    //   61: invokevirtual 66	java/lang/Class:getMethod	(Ljava/lang/String;[Ljava/lang/Class;)Ljava/lang/reflect/Method;
    //   64: astore 6
    //   66: aload 6
    //   68: aconst_null
    //   69: iconst_0
    //   70: anewarray 68	java/lang/Object
    //   73: invokevirtual 74	java/lang/reflect/Method:invoke	(Ljava/lang/Object;[Ljava/lang/Object;)Ljava/lang/Object;
    //   76: astore 6
    //   78: iload_1
    //   79: iload_2
    //   80: iadd
    //   81: iload_3
    //   82: imul
    //   83: iload 4
    //   85: irem
    //   86: aload 6
    //   88: checkcast 76	java/lang/Integer
    //   91: invokevirtual 79	java/lang/Integer:intValue	()I
    //   94: if_icmpeq +379 -> 473
    //   97: getstatic 46	uuuuuu/hhyhyy:bppp00700070p00700070p	I
    //   100: istore_1
    //   101: ldc 2
    //   103: ldc -79
    //   105: sipush 246
    //   108: sipush 150
    //   111: iconst_1
    //   112: invokestatic 85	xxxxxx/uxxxxx:bbbb0062b0062b0062b0062	(Ljava/lang/String;CCC)Ljava/lang/String;
    //   115: iconst_0
    //   116: anewarray 62	java/lang/Class
    //   119: invokevirtual 66	java/lang/Class:getMethod	(Ljava/lang/String;[Ljava/lang/Class;)Ljava/lang/reflect/Method;
    //   122: astore 6
    //   124: aload 6
    //   126: aconst_null
    //   127: iconst_0
    //   128: anewarray 68	java/lang/Object
    //   131: invokevirtual 74	java/lang/reflect/Method:invoke	(Ljava/lang/Object;[Ljava/lang/Object;)Ljava/lang/Object;
    //   134: astore 6
    //   136: aload 6
    //   138: checkcast 76	java/lang/Integer
    //   141: invokevirtual 79	java/lang/Integer:intValue	()I
    //   144: istore_2
    //   145: getstatic 46	uuuuuu/hhyhyy:bppp00700070p00700070p	I
    //   148: istore_3
    //   149: ldc 2
    //   151: ldc -77
    //   153: bipush 64
    //   155: iconst_0
    //   156: invokestatic 60	xxxxxx/uxxxxx:bb00620062bb0062b0062b0062	(Ljava/lang/String;CC)Ljava/lang/String;
    //   159: iconst_0
    //   160: anewarray 62	java/lang/Class
    //   163: invokevirtual 66	java/lang/Class:getMethod	(Ljava/lang/String;[Ljava/lang/Class;)Ljava/lang/reflect/Method;
    //   166: astore 6
    //   168: aload 6
    //   170: aconst_null
    //   171: iconst_0
    //   172: anewarray 68	java/lang/Object
    //   175: invokevirtual 74	java/lang/reflect/Method:invoke	(Ljava/lang/Object;[Ljava/lang/Object;)Ljava/lang/Object;
    //   178: astore 6
    //   180: iload_3
    //   181: iload_2
    //   182: iload_1
    //   183: iadd
    //   184: imul
    //   185: aload 6
    //   187: checkcast 76	java/lang/Integer
    //   190: invokevirtual 79	java/lang/Integer:intValue	()I
    //   193: irem
    //   194: getstatic 52	uuuuuu/hhyhyy:b00700070p00700070p00700070p	I
    //   197: if_icmpeq +92 -> 289
    //   200: ldc 2
    //   202: ldc -75
    //   204: sipush 183
    //   207: iconst_5
    //   208: invokestatic 60	xxxxxx/uxxxxx:bb00620062bb0062b0062b0062	(Ljava/lang/String;CC)Ljava/lang/String;
    //   211: iconst_0
    //   212: anewarray 62	java/lang/Class
    //   215: invokevirtual 66	java/lang/Class:getMethod	(Ljava/lang/String;[Ljava/lang/Class;)Ljava/lang/reflect/Method;
    //   218: astore 6
    //   220: aload 6
    //   222: aconst_null
    //   223: iconst_0
    //   224: anewarray 68	java/lang/Object
    //   227: invokevirtual 74	java/lang/reflect/Method:invoke	(Ljava/lang/Object;[Ljava/lang/Object;)Ljava/lang/Object;
    //   230: astore 6
    //   232: aload 6
    //   234: checkcast 76	java/lang/Integer
    //   237: invokevirtual 79	java/lang/Integer:intValue	()I
    //   240: putstatic 46	uuuuuu/hhyhyy:bppp00700070p00700070p	I
    //   243: ldc 2
    //   245: ldc -73
    //   247: sipush 188
    //   250: sipush 236
    //   253: iconst_2
    //   254: invokestatic 85	xxxxxx/uxxxxx:bbbb0062b0062b0062b0062	(Ljava/lang/String;CCC)Ljava/lang/String;
    //   257: iconst_0
    //   258: anewarray 62	java/lang/Class
    //   261: invokevirtual 66	java/lang/Class:getMethod	(Ljava/lang/String;[Ljava/lang/Class;)Ljava/lang/reflect/Method;
    //   264: astore 6
    //   266: aload 6
    //   268: aconst_null
    //   269: iconst_0
    //   270: anewarray 68	java/lang/Object
    //   273: invokevirtual 74	java/lang/reflect/Method:invoke	(Ljava/lang/Object;[Ljava/lang/Object;)Ljava/lang/Object;
    //   276: astore 6
    //   278: aload 6
    //   280: checkcast 76	java/lang/Integer
    //   283: invokevirtual 79	java/lang/Integer:intValue	()I
    //   286: putstatic 52	uuuuuu/hhyhyy:b00700070p00700070p00700070p	I
    //   289: getstatic 46	uuuuuu/hhyhyy:bppp00700070p00700070p	I
    //   292: getstatic 48	uuuuuu/hhyhyy:b0070pp00700070p00700070p	I
    //   295: iadd
    //   296: getstatic 46	uuuuuu/hhyhyy:bppp00700070p00700070p	I
    //   299: imul
    //   300: getstatic 50	uuuuuu/hhyhyy:bp0070p00700070p00700070p	I
    //   303: irem
    //   304: getstatic 52	uuuuuu/hhyhyy:b00700070p00700070p00700070p	I
    //   307: if_icmpeq +13 -> 320
    //   310: bipush 7
    //   312: putstatic 46	uuuuuu/hhyhyy:bppp00700070p00700070p	I
    //   315: bipush 53
    //   317: putstatic 52	uuuuuu/hhyhyy:b00700070p00700070p00700070p	I
    //   320: iconst_3
    //   321: putstatic 46	uuuuuu/hhyhyy:bppp00700070p00700070p	I
    //   324: getstatic 46	uuuuuu/hhyhyy:bppp00700070p00700070p	I
    //   327: getstatic 48	uuuuuu/hhyhyy:b0070pp00700070p00700070p	I
    //   330: iadd
    //   331: getstatic 46	uuuuuu/hhyhyy:bppp00700070p00700070p	I
    //   334: imul
    //   335: getstatic 50	uuuuuu/hhyhyy:bp0070p00700070p00700070p	I
    //   338: irem
    //   339: getstatic 52	uuuuuu/hhyhyy:b00700070p00700070p00700070p	I
    //   342: if_icmpeq +88 -> 430
    //   345: ldc 2
    //   347: ldc -71
    //   349: sipush 202
    //   352: iconst_0
    //   353: invokestatic 60	xxxxxx/uxxxxx:bb00620062bb0062b0062b0062	(Ljava/lang/String;CC)Ljava/lang/String;
    //   356: iconst_0
    //   357: anewarray 62	java/lang/Class
    //   360: invokevirtual 66	java/lang/Class:getMethod	(Ljava/lang/String;[Ljava/lang/Class;)Ljava/lang/reflect/Method;
    //   363: astore 6
    //   365: aload 6
    //   367: aconst_null
    //   368: iconst_0
    //   369: anewarray 68	java/lang/Object
    //   372: invokevirtual 74	java/lang/reflect/Method:invoke	(Ljava/lang/Object;[Ljava/lang/Object;)Ljava/lang/Object;
    //   375: astore 6
    //   377: aload 6
    //   379: checkcast 76	java/lang/Integer
    //   382: invokevirtual 79	java/lang/Integer:intValue	()I
    //   385: putstatic 46	uuuuuu/hhyhyy:bppp00700070p00700070p	I
    //   388: ldc 2
    //   390: ldc -69
    //   392: bipush 56
    //   394: iconst_1
    //   395: invokestatic 60	xxxxxx/uxxxxx:bb00620062bb0062b0062b0062	(Ljava/lang/String;CC)Ljava/lang/String;
    //   398: iconst_0
    //   399: anewarray 62	java/lang/Class
    //   402: invokevirtual 66	java/lang/Class:getMethod	(Ljava/lang/String;[Ljava/lang/Class;)Ljava/lang/reflect/Method;
    //   405: astore 6
    //   407: aload 6
    //   409: aconst_null
    //   410: iconst_0
    //   411: anewarray 68	java/lang/Object
    //   414: invokevirtual 74	java/lang/reflect/Method:invoke	(Ljava/lang/Object;[Ljava/lang/Object;)Ljava/lang/Object;
    //   417: astore 6
    //   419: aload 6
    //   421: checkcast 76	java/lang/Integer
    //   424: invokevirtual 79	java/lang/Integer:intValue	()I
    //   427: putstatic 52	uuuuuu/hhyhyy:b00700070p00700070p00700070p	I
    //   430: ldc 2
    //   432: ldc -67
    //   434: sipush 143
    //   437: iconst_3
    //   438: invokestatic 60	xxxxxx/uxxxxx:bb00620062bb0062b0062b0062	(Ljava/lang/String;CC)Ljava/lang/String;
    //   441: iconst_0
    //   442: anewarray 62	java/lang/Class
    //   445: invokevirtual 66	java/lang/Class:getMethod	(Ljava/lang/String;[Ljava/lang/Class;)Ljava/lang/reflect/Method;
    //   448: astore 6
    //   450: aload 6
    //   452: aconst_null
    //   453: iconst_0
    //   454: anewarray 68	java/lang/Object
    //   457: invokevirtual 74	java/lang/reflect/Method:invoke	(Ljava/lang/Object;[Ljava/lang/Object;)Ljava/lang/Object;
    //   460: astore 6
    //   462: aload 6
    //   464: checkcast 76	java/lang/Integer
    //   467: invokevirtual 79	java/lang/Integer:intValue	()I
    //   470: putstatic 52	uuuuuu/hhyhyy:b00700070p00700070p00700070p	I
    //   473: aload 5
    //   475: new 191	uuuuuu/hhyhyy$1
    //   478: dup
    //   479: aload_0
    //   480: invokespecial 194	uuuuuu/hhyhyy$1:<init>	(Luuuuuu/hhyhyy;)V
    //   483: new 196	uuuuuu/hhyhyy$2
    //   486: dup
    //   487: aload_0
    //   488: invokespecial 197	uuuuuu/hhyhyy$2:<init>	(Luuuuuu/hhyhyy;)V
    //   491: invokevirtual 201	rx/Observable:subscribe	(Lrx/functions/Action1;Lrx/functions/Action1;)Lrx/Subscription;
    //   494: pop
    //   495: return
    //   496: astore 5
    //   498: aload 5
    //   500: invokevirtual 97	java/lang/reflect/InvocationTargetException:getCause	()Ljava/lang/Throwable;
    //   503: athrow
    //   504: astore 5
    //   506: aload 5
    //   508: invokevirtual 97	java/lang/reflect/InvocationTargetException:getCause	()Ljava/lang/Throwable;
    //   511: athrow
    //   512: astore 5
    //   514: aload 5
    //   516: invokevirtual 97	java/lang/reflect/InvocationTargetException:getCause	()Ljava/lang/Throwable;
    //   519: athrow
    //   520: astore 5
    //   522: aload 5
    //   524: invokevirtual 97	java/lang/reflect/InvocationTargetException:getCause	()Ljava/lang/Throwable;
    //   527: athrow
    //   528: astore 5
    //   530: aload 5
    //   532: invokevirtual 97	java/lang/reflect/InvocationTargetException:getCause	()Ljava/lang/Throwable;
    //   535: athrow
    //   536: astore 5
    //   538: aload 5
    //   540: invokevirtual 97	java/lang/reflect/InvocationTargetException:getCause	()Ljava/lang/Throwable;
    //   543: athrow
    //   544: astore 5
    //   546: aload 5
    //   548: invokevirtual 97	java/lang/reflect/InvocationTargetException:getCause	()Ljava/lang/Throwable;
    //   551: athrow
    //   552: astore 5
    //   554: aload 5
    //   556: invokevirtual 97	java/lang/reflect/InvocationTargetException:getCause	()Ljava/lang/Throwable;
    //   559: athrow
    // Local variable table:
    //   start	length	slot	name	signature
    //   0	560	0	this	hhyhyy
    //   29	155	1	i	int
    //   33	151	2	j	int
    //   37	148	3	k	int
    //   41	45	4	m	int
    //   24	450	5	localObservable	Observable
    //   496	3	5	localInvocationTargetException1	java.lang.reflect.InvocationTargetException
    //   504	3	5	localInvocationTargetException2	java.lang.reflect.InvocationTargetException
    //   512	3	5	localInvocationTargetException3	java.lang.reflect.InvocationTargetException
    //   520	3	5	localInvocationTargetException4	java.lang.reflect.InvocationTargetException
    //   528	3	5	localInvocationTargetException5	java.lang.reflect.InvocationTargetException
    //   536	3	5	localInvocationTargetException6	java.lang.reflect.InvocationTargetException
    //   544	3	5	localInvocationTargetException7	java.lang.reflect.InvocationTargetException
    //   552	3	5	localInvocationTargetException8	java.lang.reflect.InvocationTargetException
    //   64	399	6	localObject	Object
    // Exception table:
    //   from	to	target	type
    //   365	377	496	java/lang/reflect/InvocationTargetException
    //   407	419	504	java/lang/reflect/InvocationTargetException
    //   66	78	512	java/lang/reflect/InvocationTargetException
    //   124	136	520	java/lang/reflect/InvocationTargetException
    //   168	180	528	java/lang/reflect/InvocationTargetException
    //   450	462	536	java/lang/reflect/InvocationTargetException
    //   220	232	544	java/lang/reflect/InvocationTargetException
    //   266	278	552	java/lang/reflect/InvocationTargetException
  }
  
  /* Error */
  public void bo006F006Fo006F006Foooo()
  {
    // Byte code:
    //   0: getstatic 46	uuuuuu/hhyhyy:bppp00700070p00700070p	I
    //   3: getstatic 48	uuuuuu/hhyhyy:b0070pp00700070p00700070p	I
    //   6: iadd
    //   7: getstatic 46	uuuuuu/hhyhyy:bppp00700070p00700070p	I
    //   10: imul
    //   11: getstatic 50	uuuuuu/hhyhyy:bp0070p00700070p00700070p	I
    //   14: irem
    //   15: getstatic 52	uuuuuu/hhyhyy:b00700070p00700070p00700070p	I
    //   18: if_icmpeq +393 -> 411
    //   21: getstatic 46	uuuuuu/hhyhyy:bppp00700070p00700070p	I
    //   24: istore_1
    //   25: iload_1
    //   26: getstatic 48	uuuuuu/hhyhyy:b0070pp00700070p00700070p	I
    //   29: iload_1
    //   30: iadd
    //   31: imul
    //   32: getstatic 50	uuuuuu/hhyhyy:bp0070p00700070p00700070p	I
    //   35: irem
    //   36: tableswitch	default:+20->56, 0:+214->250
    //   56: ldc 2
    //   58: ldc -110
    //   60: bipush 114
    //   62: sipush 209
    //   65: iconst_3
    //   66: invokestatic 85	xxxxxx/uxxxxx:bbbb0062b0062b0062b0062	(Ljava/lang/String;CCC)Ljava/lang/String;
    //   69: iconst_0
    //   70: anewarray 62	java/lang/Class
    //   73: invokevirtual 66	java/lang/Class:getMethod	(Ljava/lang/String;[Ljava/lang/Class;)Ljava/lang/reflect/Method;
    //   76: astore_3
    //   77: aload_3
    //   78: aconst_null
    //   79: iconst_0
    //   80: anewarray 68	java/lang/Object
    //   83: invokevirtual 74	java/lang/reflect/Method:invoke	(Ljava/lang/Object;[Ljava/lang/Object;)Ljava/lang/Object;
    //   86: astore_3
    //   87: aload_3
    //   88: checkcast 76	java/lang/Integer
    //   91: invokevirtual 79	java/lang/Integer:intValue	()I
    //   94: putstatic 46	uuuuuu/hhyhyy:bppp00700070p00700070p	I
    //   97: bipush 41
    //   99: putstatic 52	uuuuuu/hhyhyy:b00700070p00700070p00700070p	I
    //   102: getstatic 46	uuuuuu/hhyhyy:bppp00700070p00700070p	I
    //   105: istore_1
    //   106: getstatic 48	uuuuuu/hhyhyy:b0070pp00700070p00700070p	I
    //   109: istore_2
    //   110: ldc 2
    //   112: ldc -19
    //   114: bipush 80
    //   116: iconst_2
    //   117: invokestatic 60	xxxxxx/uxxxxx:bb00620062bb0062b0062b0062	(Ljava/lang/String;CC)Ljava/lang/String;
    //   120: iconst_0
    //   121: anewarray 62	java/lang/Class
    //   124: invokevirtual 66	java/lang/Class:getMethod	(Ljava/lang/String;[Ljava/lang/Class;)Ljava/lang/reflect/Method;
    //   127: astore_3
    //   128: aload_3
    //   129: aconst_null
    //   130: iconst_0
    //   131: anewarray 68	java/lang/Object
    //   134: invokevirtual 74	java/lang/reflect/Method:invoke	(Ljava/lang/Object;[Ljava/lang/Object;)Ljava/lang/Object;
    //   137: astore_3
    //   138: iload_2
    //   139: iload_1
    //   140: iadd
    //   141: iload_1
    //   142: imul
    //   143: aload_3
    //   144: checkcast 76	java/lang/Integer
    //   147: invokevirtual 79	java/lang/Integer:intValue	()I
    //   150: irem
    //   151: tableswitch	default:+17->168, 0:+99->250
    //   168: ldc 2
    //   170: ldc -17
    //   172: bipush 59
    //   174: bipush 41
    //   176: iconst_1
    //   177: invokestatic 85	xxxxxx/uxxxxx:bbbb0062b0062b0062b0062	(Ljava/lang/String;CCC)Ljava/lang/String;
    //   180: iconst_0
    //   181: anewarray 62	java/lang/Class
    //   184: invokevirtual 66	java/lang/Class:getMethod	(Ljava/lang/String;[Ljava/lang/Class;)Ljava/lang/reflect/Method;
    //   187: astore_3
    //   188: aload_3
    //   189: aconst_null
    //   190: iconst_0
    //   191: anewarray 68	java/lang/Object
    //   194: invokevirtual 74	java/lang/reflect/Method:invoke	(Ljava/lang/Object;[Ljava/lang/Object;)Ljava/lang/Object;
    //   197: astore_3
    //   198: aload_3
    //   199: checkcast 76	java/lang/Integer
    //   202: invokevirtual 79	java/lang/Integer:intValue	()I
    //   205: putstatic 46	uuuuuu/hhyhyy:bppp00700070p00700070p	I
    //   208: ldc 2
    //   210: ldc -15
    //   212: sipush 175
    //   215: sipush 140
    //   218: iconst_0
    //   219: invokestatic 85	xxxxxx/uxxxxx:bbbb0062b0062b0062b0062	(Ljava/lang/String;CCC)Ljava/lang/String;
    //   222: iconst_0
    //   223: anewarray 62	java/lang/Class
    //   226: invokevirtual 66	java/lang/Class:getMethod	(Ljava/lang/String;[Ljava/lang/Class;)Ljava/lang/reflect/Method;
    //   229: astore_3
    //   230: aload_3
    //   231: aconst_null
    //   232: iconst_0
    //   233: anewarray 68	java/lang/Object
    //   236: invokevirtual 74	java/lang/reflect/Method:invoke	(Ljava/lang/Object;[Ljava/lang/Object;)Ljava/lang/Object;
    //   239: astore_3
    //   240: aload_3
    //   241: checkcast 76	java/lang/Integer
    //   244: invokevirtual 79	java/lang/Integer:intValue	()I
    //   247: putstatic 52	uuuuuu/hhyhyy:b00700070p00700070p00700070p	I
    //   250: bipush 73
    //   252: putstatic 46	uuuuuu/hhyhyy:bppp00700070p00700070p	I
    //   255: ldc 2
    //   257: ldc -13
    //   259: sipush 155
    //   262: iconst_1
    //   263: invokestatic 60	xxxxxx/uxxxxx:bb00620062bb0062b0062b0062	(Ljava/lang/String;CC)Ljava/lang/String;
    //   266: iconst_0
    //   267: anewarray 62	java/lang/Class
    //   270: invokevirtual 66	java/lang/Class:getMethod	(Ljava/lang/String;[Ljava/lang/Class;)Ljava/lang/reflect/Method;
    //   273: astore_3
    //   274: aload_3
    //   275: aconst_null
    //   276: iconst_0
    //   277: anewarray 68	java/lang/Object
    //   280: invokevirtual 74	java/lang/reflect/Method:invoke	(Ljava/lang/Object;[Ljava/lang/Object;)Ljava/lang/Object;
    //   283: astore_3
    //   284: aload_3
    //   285: checkcast 76	java/lang/Integer
    //   288: invokevirtual 79	java/lang/Integer:intValue	()I
    //   291: istore_1
    //   292: getstatic 46	uuuuuu/hhyhyy:bppp00700070p00700070p	I
    //   295: istore_2
    //   296: iload_2
    //   297: getstatic 48	uuuuuu/hhyhyy:b0070pp00700070p00700070p	I
    //   300: iload_2
    //   301: iadd
    //   302: imul
    //   303: getstatic 50	uuuuuu/hhyhyy:bp0070p00700070p00700070p	I
    //   306: irem
    //   307: tableswitch	default:+17->324, 0:+100->407
    //   324: ldc 2
    //   326: ldc -11
    //   328: sipush 197
    //   331: sipush 147
    //   334: iconst_2
    //   335: invokestatic 85	xxxxxx/uxxxxx:bbbb0062b0062b0062b0062	(Ljava/lang/String;CCC)Ljava/lang/String;
    //   338: iconst_0
    //   339: anewarray 62	java/lang/Class
    //   342: invokevirtual 66	java/lang/Class:getMethod	(Ljava/lang/String;[Ljava/lang/Class;)Ljava/lang/reflect/Method;
    //   345: astore_3
    //   346: aload_3
    //   347: aconst_null
    //   348: iconst_0
    //   349: anewarray 68	java/lang/Object
    //   352: invokevirtual 74	java/lang/reflect/Method:invoke	(Ljava/lang/Object;[Ljava/lang/Object;)Ljava/lang/Object;
    //   355: astore_3
    //   356: aload_3
    //   357: checkcast 76	java/lang/Integer
    //   360: invokevirtual 79	java/lang/Integer:intValue	()I
    //   363: putstatic 46	uuuuuu/hhyhyy:bppp00700070p00700070p	I
    //   366: ldc 2
    //   368: ldc -9
    //   370: bipush 42
    //   372: sipush 197
    //   375: iconst_0
    //   376: invokestatic 85	xxxxxx/uxxxxx:bbbb0062b0062b0062b0062	(Ljava/lang/String;CCC)Ljava/lang/String;
    //   379: iconst_0
    //   380: anewarray 62	java/lang/Class
    //   383: invokevirtual 66	java/lang/Class:getMethod	(Ljava/lang/String;[Ljava/lang/Class;)Ljava/lang/reflect/Method;
    //   386: astore_3
    //   387: aload_3
    //   388: aconst_null
    //   389: iconst_0
    //   390: anewarray 68	java/lang/Object
    //   393: invokevirtual 74	java/lang/reflect/Method:invoke	(Ljava/lang/Object;[Ljava/lang/Object;)Ljava/lang/Object;
    //   396: astore_3
    //   397: aload_3
    //   398: checkcast 76	java/lang/Integer
    //   401: invokevirtual 79	java/lang/Integer:intValue	()I
    //   404: putstatic 52	uuuuuu/hhyhyy:b00700070p00700070p00700070p	I
    //   407: iload_1
    //   408: putstatic 52	uuuuuu/hhyhyy:b00700070p00700070p00700070p	I
    //   411: aload_0
    //   412: aload_0
    //   413: getfield 32	uuuuuu/hhyhyy:bp00700070p0070p00700070p	Luuuuuu/ffmmmf;
    //   416: aload_0
    //   417: getfield 251	uuuuuu/hhyhyy:bpppp0070pp0070p	Ljava/lang/String;
    //   420: invokevirtual 255	uuuuuu/ffmmmf:b00700070p007000700070ppp0070	(Ljava/lang/String;)Lrx/Observable;
    //   423: putfield 153	uuuuuu/hhyhyy:b007000700070p0070p00700070p	Lrx/Observable;
    //   426: return
    //   427: astore_3
    //   428: aload_3
    //   429: invokevirtual 97	java/lang/reflect/InvocationTargetException:getCause	()Ljava/lang/Throwable;
    //   432: athrow
    //   433: astore_3
    //   434: aload_3
    //   435: invokevirtual 97	java/lang/reflect/InvocationTargetException:getCause	()Ljava/lang/Throwable;
    //   438: athrow
    //   439: astore_3
    //   440: aload_3
    //   441: invokevirtual 97	java/lang/reflect/InvocationTargetException:getCause	()Ljava/lang/Throwable;
    //   444: athrow
    //   445: astore_3
    //   446: aload_3
    //   447: invokevirtual 97	java/lang/reflect/InvocationTargetException:getCause	()Ljava/lang/Throwable;
    //   450: athrow
    //   451: astore_3
    //   452: aload_3
    //   453: invokevirtual 97	java/lang/reflect/InvocationTargetException:getCause	()Ljava/lang/Throwable;
    //   456: athrow
    //   457: astore_3
    //   458: aload_3
    //   459: invokevirtual 97	java/lang/reflect/InvocationTargetException:getCause	()Ljava/lang/Throwable;
    //   462: athrow
    //   463: astore_3
    //   464: aload_3
    //   465: invokevirtual 97	java/lang/reflect/InvocationTargetException:getCause	()Ljava/lang/Throwable;
    //   468: athrow
    // Local variable table:
    //   start	length	slot	name	signature
    //   0	469	0	this	hhyhyy
    //   24	384	1	i	int
    //   109	194	2	j	int
    //   76	322	3	localObject	Object
    //   427	2	3	localInvocationTargetException1	java.lang.reflect.InvocationTargetException
    //   433	2	3	localInvocationTargetException2	java.lang.reflect.InvocationTargetException
    //   439	2	3	localInvocationTargetException3	java.lang.reflect.InvocationTargetException
    //   445	2	3	localInvocationTargetException4	java.lang.reflect.InvocationTargetException
    //   451	2	3	localInvocationTargetException5	java.lang.reflect.InvocationTargetException
    //   457	2	3	localInvocationTargetException6	java.lang.reflect.InvocationTargetException
    //   463	2	3	localInvocationTargetException7	java.lang.reflect.InvocationTargetException
    // Exception table:
    //   from	to	target	type
    //   346	356	427	java/lang/reflect/InvocationTargetException
    //   387	397	433	java/lang/reflect/InvocationTargetException
    //   274	284	439	java/lang/reflect/InvocationTargetException
    //   77	87	445	java/lang/reflect/InvocationTargetException
    //   128	138	451	java/lang/reflect/InvocationTargetException
    //   188	198	457	java/lang/reflect/InvocationTargetException
    //   230	240	463	java/lang/reflect/InvocationTargetException
  }
  
  /* Error */
  public void boooo006F006F006Fooo(SecurityPositions paramSecurityPositions)
  {
    // Byte code:
    //   0: aload_0
    //   1: invokevirtual 296	uuuuuu/hhyhyy:bkk006Bk006Bk006Bk006Bk	()Z
    //   4: ifeq +183 -> 187
    //   7: aload_0
    //   8: getfield 300	uuuuuu/hhyhyy:bnnnnn006E006E006En	Luuuuuu/ttssst$tsssst;
    //   11: checkcast 302	uuuuuu/yhhhyy$yyhhyy
    //   14: astore 5
    //   16: getstatic 46	uuuuuu/hhyhyy:bppp00700070p00700070p	I
    //   19: istore_2
    //   20: getstatic 48	uuuuuu/hhyhyy:b0070pp00700070p00700070p	I
    //   23: istore_3
    //   24: ldc 2
    //   26: ldc_w 304
    //   29: bipush 11
    //   31: iconst_3
    //   32: invokestatic 60	xxxxxx/uxxxxx:bb00620062bb0062b0062b0062	(Ljava/lang/String;CC)Ljava/lang/String;
    //   35: iconst_0
    //   36: anewarray 62	java/lang/Class
    //   39: invokevirtual 66	java/lang/Class:getMethod	(Ljava/lang/String;[Ljava/lang/Class;)Ljava/lang/reflect/Method;
    //   42: astore 6
    //   44: aload 6
    //   46: aconst_null
    //   47: iconst_0
    //   48: anewarray 68	java/lang/Object
    //   51: invokevirtual 74	java/lang/reflect/Method:invoke	(Ljava/lang/Object;[Ljava/lang/Object;)Ljava/lang/Object;
    //   54: astore 6
    //   56: iload_3
    //   57: iload_2
    //   58: iadd
    //   59: iload_2
    //   60: imul
    //   61: aload 6
    //   63: checkcast 76	java/lang/Integer
    //   66: invokevirtual 79	java/lang/Integer:intValue	()I
    //   69: irem
    //   70: tableswitch	default:+18->88, 0:+107->177
    //   88: ldc 2
    //   90: ldc_w 306
    //   93: bipush 40
    //   95: iconst_2
    //   96: invokestatic 60	xxxxxx/uxxxxx:bb00620062bb0062b0062b0062	(Ljava/lang/String;CC)Ljava/lang/String;
    //   99: iconst_0
    //   100: anewarray 62	java/lang/Class
    //   103: invokevirtual 66	java/lang/Class:getMethod	(Ljava/lang/String;[Ljava/lang/Class;)Ljava/lang/reflect/Method;
    //   106: astore 6
    //   108: aload 6
    //   110: aconst_null
    //   111: iconst_0
    //   112: anewarray 68	java/lang/Object
    //   115: invokevirtual 74	java/lang/reflect/Method:invoke	(Ljava/lang/Object;[Ljava/lang/Object;)Ljava/lang/Object;
    //   118: astore 6
    //   120: aload 6
    //   122: checkcast 76	java/lang/Integer
    //   125: invokevirtual 79	java/lang/Integer:intValue	()I
    //   128: putstatic 46	uuuuuu/hhyhyy:bppp00700070p00700070p	I
    //   131: ldc 2
    //   133: ldc_w 308
    //   136: sipush 229
    //   139: bipush 48
    //   141: iconst_2
    //   142: invokestatic 85	xxxxxx/uxxxxx:bbbb0062b0062b0062b0062	(Ljava/lang/String;CCC)Ljava/lang/String;
    //   145: iconst_0
    //   146: anewarray 62	java/lang/Class
    //   149: invokevirtual 66	java/lang/Class:getMethod	(Ljava/lang/String;[Ljava/lang/Class;)Ljava/lang/reflect/Method;
    //   152: astore 6
    //   154: aload 6
    //   156: aconst_null
    //   157: iconst_0
    //   158: anewarray 68	java/lang/Object
    //   161: invokevirtual 74	java/lang/reflect/Method:invoke	(Ljava/lang/Object;[Ljava/lang/Object;)Ljava/lang/Object;
    //   164: astore 6
    //   166: aload 6
    //   168: checkcast 76	java/lang/Integer
    //   171: invokevirtual 79	java/lang/Integer:intValue	()I
    //   174: putstatic 52	uuuuuu/hhyhyy:b00700070p00700070p00700070p	I
    //   177: aload 5
    //   179: invokeinterface 311 1 0
    //   184: ifeq +46 -> 230
    //   187: return
    //   188: astore_1
    //   189: ldc 2
    //   191: ldc_w 313
    //   194: sipush 210
    //   197: iconst_2
    //   198: invokestatic 60	xxxxxx/uxxxxx:bb00620062bb0062b0062b0062	(Ljava/lang/String;CC)Ljava/lang/String;
    //   201: iconst_0
    //   202: anewarray 62	java/lang/Class
    //   205: invokevirtual 66	java/lang/Class:getMethod	(Ljava/lang/String;[Ljava/lang/Class;)Ljava/lang/reflect/Method;
    //   208: astore_1
    //   209: aload_1
    //   210: aconst_null
    //   211: iconst_0
    //   212: anewarray 68	java/lang/Object
    //   215: invokevirtual 74	java/lang/reflect/Method:invoke	(Ljava/lang/Object;[Ljava/lang/Object;)Ljava/lang/Object;
    //   218: astore_1
    //   219: aload_1
    //   220: checkcast 76	java/lang/Integer
    //   223: invokevirtual 79	java/lang/Integer:intValue	()I
    //   226: putstatic 46	uuuuuu/hhyhyy:bppp00700070p00700070p	I
    //   229: return
    //   230: new 315	uuuuuu/ehhhhe
    //   233: dup
    //   234: invokespecial 316	uuuuuu/ehhhhe:<init>	()V
    //   237: astore 5
    //   239: ldc 2
    //   241: ldc_w 318
    //   244: bipush 123
    //   246: sipush 196
    //   249: iconst_1
    //   250: invokestatic 85	xxxxxx/uxxxxx:bbbb0062b0062b0062b0062	(Ljava/lang/String;CCC)Ljava/lang/String;
    //   253: iconst_1
    //   254: anewarray 62	java/lang/Class
    //   257: dup
    //   258: iconst_0
    //   259: ldc 99
    //   261: aastore
    //   262: invokevirtual 66	java/lang/Class:getMethod	(Ljava/lang/String;[Ljava/lang/Class;)Ljava/lang/reflect/Method;
    //   265: astore 6
    //   267: aload 6
    //   269: aload_0
    //   270: iconst_1
    //   271: anewarray 68	java/lang/Object
    //   274: dup
    //   275: iconst_0
    //   276: aload_1
    //   277: aastore
    //   278: invokevirtual 74	java/lang/reflect/Method:invoke	(Ljava/lang/Object;[Ljava/lang/Object;)Ljava/lang/Object;
    //   281: astore 6
    //   283: aload 6
    //   285: checkcast 288	java/lang/Boolean
    //   288: invokevirtual 291	java/lang/Boolean:booleanValue	()Z
    //   291: istore 4
    //   293: getstatic 46	uuuuuu/hhyhyy:bppp00700070p00700070p	I
    //   296: getstatic 48	uuuuuu/hhyhyy:b0070pp00700070p00700070p	I
    //   299: iadd
    //   300: getstatic 46	uuuuuu/hhyhyy:bppp00700070p00700070p	I
    //   303: imul
    //   304: getstatic 50	uuuuuu/hhyhyy:bp0070p00700070p00700070p	I
    //   307: irem
    //   308: getstatic 52	uuuuuu/hhyhyy:b00700070p00700070p00700070p	I
    //   311: if_icmpeq +51 -> 362
    //   314: bipush 25
    //   316: putstatic 46	uuuuuu/hhyhyy:bppp00700070p00700070p	I
    //   319: ldc 2
    //   321: ldc_w 320
    //   324: bipush 81
    //   326: iconst_4
    //   327: invokestatic 60	xxxxxx/uxxxxx:bb00620062bb0062b0062b0062	(Ljava/lang/String;CC)Ljava/lang/String;
    //   330: iconst_0
    //   331: anewarray 62	java/lang/Class
    //   334: invokevirtual 66	java/lang/Class:getMethod	(Ljava/lang/String;[Ljava/lang/Class;)Ljava/lang/reflect/Method;
    //   337: astore 6
    //   339: aload 6
    //   341: aconst_null
    //   342: iconst_0
    //   343: anewarray 68	java/lang/Object
    //   346: invokevirtual 74	java/lang/reflect/Method:invoke	(Ljava/lang/Object;[Ljava/lang/Object;)Ljava/lang/Object;
    //   349: astore 6
    //   351: aload 6
    //   353: checkcast 76	java/lang/Integer
    //   356: invokevirtual 79	java/lang/Integer:intValue	()I
    //   359: putstatic 52	uuuuuu/hhyhyy:b00700070p00700070p00700070p	I
    //   362: iload 4
    //   364: ifeq +322 -> 686
    //   367: aload_1
    //   368: invokevirtual 103	com/db/pwcc/dbmobile/model/securities/SecurityPositions:getSecurityPositions	()Ljava/util/List;
    //   371: astore 7
    //   373: aload 7
    //   375: invokeinterface 324 1 0
    //   380: astore 6
    //   382: aload 6
    //   384: invokeinterface 329 1 0
    //   389: ifeq +159 -> 548
    //   392: aload 6
    //   394: invokeinterface 333 1 0
    //   399: checkcast 89	com/db/pwcc/dbmobile/model/securities/SecurityPosition
    //   402: astore 8
    //   404: aload 8
    //   406: invokevirtual 93	com/db/pwcc/dbmobile/model/securities/SecurityPosition:getSecurity	()Lcom/db/pwcc/dbmobile/model/securities/Security;
    //   409: invokevirtual 339	com/db/pwcc/dbmobile/model/securities/Security:getCategories	()Lcom/db/pwcc/dbmobile/model/securities/Categories;
    //   412: ifnull +22 -> 434
    //   415: aload 5
    //   417: aload 8
    //   419: invokevirtual 93	com/db/pwcc/dbmobile/model/securities/SecurityPosition:getSecurity	()Lcom/db/pwcc/dbmobile/model/securities/Security;
    //   422: invokevirtual 339	com/db/pwcc/dbmobile/model/securities/Security:getCategories	()Lcom/db/pwcc/dbmobile/model/securities/Categories;
    //   425: invokevirtual 345	com/db/pwcc/dbmobile/model/securities/Categories:getAssetClass	()Ljava/lang/String;
    //   428: invokevirtual 349	uuuuuu/ehhhhe:boo006Fo006F006F006F006F006Fo	(Ljava/lang/String;)Z
    //   431: ifne -49 -> 382
    //   434: aload 8
    //   436: invokevirtual 93	com/db/pwcc/dbmobile/model/securities/SecurityPosition:getSecurity	()Lcom/db/pwcc/dbmobile/model/securities/Security;
    //   439: invokevirtual 339	com/db/pwcc/dbmobile/model/securities/Security:getCategories	()Lcom/db/pwcc/dbmobile/model/securities/Categories;
    //   442: astore 8
    //   444: ldc_w 351
    //   447: ldc_w 353
    //   450: sipush 242
    //   453: iconst_5
    //   454: invokestatic 60	xxxxxx/uxxxxx:bb00620062bb0062b0062b0062	(Ljava/lang/String;CC)Ljava/lang/String;
    //   457: iconst_3
    //   458: anewarray 62	java/lang/Class
    //   461: dup
    //   462: iconst_0
    //   463: ldc_w 355
    //   466: aastore
    //   467: dup
    //   468: iconst_1
    //   469: getstatic 361	java/lang/Character:TYPE	Ljava/lang/Class;
    //   472: aastore
    //   473: dup
    //   474: iconst_2
    //   475: getstatic 361	java/lang/Character:TYPE	Ljava/lang/Class;
    //   478: aastore
    //   479: invokevirtual 66	java/lang/Class:getMethod	(Ljava/lang/String;[Ljava/lang/Class;)Ljava/lang/reflect/Method;
    //   482: astore 9
    //   484: aload 9
    //   486: aconst_null
    //   487: iconst_3
    //   488: anewarray 68	java/lang/Object
    //   491: dup
    //   492: iconst_0
    //   493: ldc_w 363
    //   496: aastore
    //   497: dup
    //   498: iconst_1
    //   499: bipush 93
    //   501: invokestatic 367	java/lang/Character:valueOf	(C)Ljava/lang/Character;
    //   504: aastore
    //   505: dup
    //   506: iconst_2
    //   507: iconst_0
    //   508: invokestatic 367	java/lang/Character:valueOf	(C)Ljava/lang/Character;
    //   511: aastore
    //   512: invokevirtual 74	java/lang/reflect/Method:invoke	(Ljava/lang/Object;[Ljava/lang/Object;)Ljava/lang/Object;
    //   515: astore 9
    //   517: aload 8
    //   519: aload 9
    //   521: checkcast 355	java/lang/String
    //   524: invokevirtual 370	com/db/pwcc/dbmobile/model/securities/Categories:setAssetClass	(Ljava/lang/String;)V
    //   527: goto -145 -> 382
    //   530: astore_1
    //   531: aload_1
    //   532: invokevirtual 97	java/lang/reflect/InvocationTargetException:getCause	()Ljava/lang/Throwable;
    //   535: athrow
    //   536: astore_1
    //   537: aload_1
    //   538: invokevirtual 97	java/lang/reflect/InvocationTargetException:getCause	()Ljava/lang/Throwable;
    //   541: athrow
    //   542: astore_1
    //   543: aload_1
    //   544: invokevirtual 97	java/lang/reflect/InvocationTargetException:getCause	()Ljava/lang/Throwable;
    //   547: athrow
    //   548: aload 7
    //   550: new 9	uuuuuu/hhyhyy$SecurityNameComparator
    //   553: dup
    //   554: invokespecial 371	uuuuuu/hhyhyy$SecurityNameComparator:<init>	()V
    //   557: invokestatic 377	java/util/Collections:sort	(Ljava/util/List;Ljava/util/Comparator;)V
    //   560: aload 7
    //   562: new 7	uuuuuu/hhyhyy$AssetClassComparator
    //   565: dup
    //   566: invokespecial 378	uuuuuu/hhyhyy$AssetClassComparator:<init>	()V
    //   569: invokestatic 377	java/util/Collections:sort	(Ljava/util/List;Ljava/util/Comparator;)V
    //   572: aload_0
    //   573: getfield 300	uuuuuu/hhyhyy:bnnnnn006E006E006En	Luuuuuu/ttssst$tsssst;
    //   576: checkcast 302	uuuuuu/yhhhyy$yyhhyy
    //   579: aload_1
    //   580: invokeinterface 381 2 0
    //   585: getstatic 46	uuuuuu/hhyhyy:bppp00700070p00700070p	I
    //   588: istore_2
    //   589: iload_2
    //   590: getstatic 48	uuuuuu/hhyhyy:b0070pp00700070p00700070p	I
    //   593: iload_2
    //   594: iadd
    //   595: imul
    //   596: getstatic 50	uuuuuu/hhyhyy:bp0070p00700070p00700070p	I
    //   599: irem
    //   600: tableswitch	default:+20->620, 0:+66->666
    //   620: ldc 2
    //   622: ldc_w 383
    //   625: bipush 99
    //   627: bipush 34
    //   629: iconst_1
    //   630: invokestatic 85	xxxxxx/uxxxxx:bbbb0062b0062b0062b0062	(Ljava/lang/String;CCC)Ljava/lang/String;
    //   633: iconst_0
    //   634: anewarray 62	java/lang/Class
    //   637: invokevirtual 66	java/lang/Class:getMethod	(Ljava/lang/String;[Ljava/lang/Class;)Ljava/lang/reflect/Method;
    //   640: astore_1
    //   641: aload_1
    //   642: aconst_null
    //   643: iconst_0
    //   644: anewarray 68	java/lang/Object
    //   647: invokevirtual 74	java/lang/reflect/Method:invoke	(Ljava/lang/Object;[Ljava/lang/Object;)Ljava/lang/Object;
    //   650: astore_1
    //   651: aload_1
    //   652: checkcast 76	java/lang/Integer
    //   655: invokevirtual 79	java/lang/Integer:intValue	()I
    //   658: putstatic 46	uuuuuu/hhyhyy:bppp00700070p00700070p	I
    //   661: bipush 55
    //   663: putstatic 52	uuuuuu/hhyhyy:b00700070p00700070p00700070p	I
    //   666: new 117	java/lang/NullPointerException
    //   669: dup
    //   670: invokespecial 118	java/lang/NullPointerException:<init>	()V
    //   673: athrow
    //   674: astore_1
    //   675: aload_1
    //   676: invokevirtual 97	java/lang/reflect/InvocationTargetException:getCause	()Ljava/lang/Throwable;
    //   679: athrow
    //   680: astore_1
    //   681: aload_1
    //   682: invokevirtual 97	java/lang/reflect/InvocationTargetException:getCause	()Ljava/lang/Throwable;
    //   685: athrow
    //   686: aload_0
    //   687: getfield 300	uuuuuu/hhyhyy:bnnnnn006E006E006En	Luuuuuu/ttssst$tsssst;
    //   690: checkcast 302	uuuuuu/yhhhyy$yyhhyy
    //   693: invokeinterface 386 1 0
    //   698: return
    //   699: astore_1
    //   700: aload_1
    //   701: invokevirtual 97	java/lang/reflect/InvocationTargetException:getCause	()Ljava/lang/Throwable;
    //   704: athrow
    //   705: astore_1
    //   706: aload_1
    //   707: invokevirtual 97	java/lang/reflect/InvocationTargetException:getCause	()Ljava/lang/Throwable;
    //   710: athrow
    //   711: astore_1
    //   712: aload_1
    //   713: invokevirtual 97	java/lang/reflect/InvocationTargetException:getCause	()Ljava/lang/Throwable;
    //   716: athrow
    // Local variable table:
    //   start	length	slot	name	signature
    //   0	717	0	this	hhyhyy
    //   0	717	1	paramSecurityPositions	SecurityPositions
    //   19	577	2	i	int
    //   23	36	3	j	int
    //   291	72	4	bool	boolean
    //   14	402	5	localObject1	Object
    //   42	351	6	localObject2	Object
    //   371	190	7	localList	java.util.List
    //   402	116	8	localObject3	Object
    //   482	38	9	localObject4	Object
    // Exception table:
    //   from	to	target	type
    //   666	674	188	java/lang/Exception
    //   339	351	530	java/lang/reflect/InvocationTargetException
    //   484	517	536	java/lang/reflect/InvocationTargetException
    //   44	56	542	java/lang/reflect/InvocationTargetException
    //   641	651	674	java/lang/reflect/InvocationTargetException
    //   267	283	680	java/lang/reflect/InvocationTargetException
    //   209	219	699	java/lang/reflect/InvocationTargetException
    //   108	120	705	java/lang/reflect/InvocationTargetException
    //   154	166	711	java/lang/reflect/InvocationTargetException
  }
}
