package uuuuuu;

import java.lang.annotation.Annotation;
import java.lang.annotation.Retention;
import java.lang.annotation.RetentionPolicy;

public final class hphhhh
{
  private static final String b007900790079y0079007900790079y = "Bncple_NZZc[iKDJ81";
  public static int b00790079y00790079007900790079y = 2;
  private static final String b00790079yy0079007900790079y = "?k`mib\\NG=8\036";
  private static final String b0079y0079y0079007900790079y = "9eZgc\\VHA72";
  public static int b0079yy00790079007900790079y = 41;
  private static final String by00790079y0079007900790079y = "\0020'64/+\034*,71A\037'\027\022";
  public static int by0079y00790079007900790079y = 0;
  private static final String byy0079y0079007900790079y = "v%\034+)$ \016\006\003j";
  public static int byyy00790079007900790079y = 1;
  
  private hphhhh() {}
  
  /* Error */
  public static String b007700770077007700770077w0077ww(java.math.BigDecimal paramBigDecimal)
  {
    // Byte code:
    //   0: invokestatic 45	uuuuuu/hphhhh:bw00770077007700770077w0077ww	()I
    //   3: istore_1
    //   4: iload_1
    //   5: getstatic 47	uuuuuu/hphhhh:byyy00790079007900790079y	I
    //   8: iload_1
    //   9: iadd
    //   10: imul
    //   11: invokestatic 50	uuuuuu/hphhhh:b0077w0077007700770077w0077ww	()I
    //   14: irem
    //   15: tableswitch	default:+17->32, 0:+22->37
    //   32: bipush 98
    //   34: putstatic 47	uuuuuu/hphhhh:byyy00790079007900790079y	I
    //   37: aload_0
    //   38: ldc2_w 51
    //   41: iconst_2
    //   42: invokestatic 58	uuuuuu/onoonn:bk006Bkkk006Bk006Bk006B	(DI)Ljava/math/BigDecimal;
    //   45: invokevirtual 64	java/math/BigDecimal:compareTo	(Ljava/math/BigDecimal;)I
    //   48: ifne +397 -> 445
    //   51: ldc 66
    //   53: ldc 68
    //   55: sipush 160
    //   58: iconst_5
    //   59: invokestatic 74	xxxxxx/uxxxxx:bb00620062bb0062b0062b0062	(Ljava/lang/String;CC)Ljava/lang/String;
    //   62: iconst_3
    //   63: anewarray 76	java/lang/Class
    //   66: dup
    //   67: iconst_0
    //   68: ldc 78
    //   70: aastore
    //   71: dup
    //   72: iconst_1
    //   73: getstatic 84	java/lang/Character:TYPE	Ljava/lang/Class;
    //   76: aastore
    //   77: dup
    //   78: iconst_2
    //   79: getstatic 84	java/lang/Character:TYPE	Ljava/lang/Class;
    //   82: aastore
    //   83: invokevirtual 88	java/lang/Class:getMethod	(Ljava/lang/String;[Ljava/lang/Class;)Ljava/lang/reflect/Method;
    //   86: astore_0
    //   87: aload_0
    //   88: aconst_null
    //   89: iconst_3
    //   90: anewarray 4	java/lang/Object
    //   93: dup
    //   94: iconst_0
    //   95: ldc 90
    //   97: aastore
    //   98: dup
    //   99: iconst_1
    //   100: bipush 85
    //   102: invokestatic 94	java/lang/Character:valueOf	(C)Ljava/lang/Character;
    //   105: aastore
    //   106: dup
    //   107: iconst_2
    //   108: iconst_1
    //   109: invokestatic 94	java/lang/Character:valueOf	(C)Ljava/lang/Character;
    //   112: aastore
    //   113: invokevirtual 100	java/lang/reflect/Method:invoke	(Ljava/lang/Object;[Ljava/lang/Object;)Ljava/lang/Object;
    //   116: astore_0
    //   117: aload_0
    //   118: checkcast 78	java/lang/String
    //   121: areturn
    //   122: aload_0
    //   123: ldc2_w 101
    //   126: iconst_2
    //   127: invokestatic 58	uuuuuu/onoonn:bk006Bkkk006Bk006Bk006B	(DI)Ljava/math/BigDecimal;
    //   130: invokevirtual 64	java/math/BigDecimal:compareTo	(Ljava/math/BigDecimal;)I
    //   133: ifne +187 -> 320
    //   136: ldc 66
    //   138: ldc 104
    //   140: sipush 183
    //   143: iconst_3
    //   144: invokestatic 74	xxxxxx/uxxxxx:bb00620062bb0062b0062b0062	(Ljava/lang/String;CC)Ljava/lang/String;
    //   147: iconst_4
    //   148: anewarray 76	java/lang/Class
    //   151: dup
    //   152: iconst_0
    //   153: ldc 78
    //   155: aastore
    //   156: dup
    //   157: iconst_1
    //   158: getstatic 84	java/lang/Character:TYPE	Ljava/lang/Class;
    //   161: aastore
    //   162: dup
    //   163: iconst_2
    //   164: getstatic 84	java/lang/Character:TYPE	Ljava/lang/Class;
    //   167: aastore
    //   168: dup
    //   169: iconst_3
    //   170: getstatic 84	java/lang/Character:TYPE	Ljava/lang/Class;
    //   173: aastore
    //   174: invokevirtual 88	java/lang/Class:getMethod	(Ljava/lang/String;[Ljava/lang/Class;)Ljava/lang/reflect/Method;
    //   177: astore_0
    //   178: aload_0
    //   179: aconst_null
    //   180: iconst_4
    //   181: anewarray 4	java/lang/Object
    //   184: dup
    //   185: iconst_0
    //   186: ldc 106
    //   188: aastore
    //   189: dup
    //   190: iconst_1
    //   191: bipush 79
    //   193: invokestatic 94	java/lang/Character:valueOf	(C)Ljava/lang/Character;
    //   196: aastore
    //   197: dup
    //   198: iconst_2
    //   199: bipush 98
    //   201: invokestatic 94	java/lang/Character:valueOf	(C)Ljava/lang/Character;
    //   204: aastore
    //   205: dup
    //   206: iconst_3
    //   207: iconst_3
    //   208: invokestatic 94	java/lang/Character:valueOf	(C)Ljava/lang/Character;
    //   211: aastore
    //   212: invokevirtual 100	java/lang/reflect/Method:invoke	(Ljava/lang/Object;[Ljava/lang/Object;)Ljava/lang/Object;
    //   215: astore_0
    //   216: aload_0
    //   217: checkcast 78	java/lang/String
    //   220: areturn
    //   221: astore_0
    //   222: aload_0
    //   223: invokevirtual 110	java/lang/reflect/InvocationTargetException:getCause	()Ljava/lang/Throwable;
    //   226: athrow
    //   227: aload_0
    //   228: ldc2_w 111
    //   231: iconst_2
    //   232: invokestatic 58	uuuuuu/onoonn:bk006Bkkk006Bk006Bk006B	(DI)Ljava/math/BigDecimal;
    //   235: invokevirtual 64	java/math/BigDecimal:compareTo	(Ljava/math/BigDecimal;)I
    //   238: ifne -116 -> 122
    //   241: ldc 66
    //   243: ldc 114
    //   245: sipush 188
    //   248: bipush 126
    //   250: iconst_3
    //   251: invokestatic 118	xxxxxx/uxxxxx:bbbb0062b0062b0062b0062	(Ljava/lang/String;CCC)Ljava/lang/String;
    //   254: iconst_3
    //   255: anewarray 76	java/lang/Class
    //   258: dup
    //   259: iconst_0
    //   260: ldc 78
    //   262: aastore
    //   263: dup
    //   264: iconst_1
    //   265: getstatic 84	java/lang/Character:TYPE	Ljava/lang/Class;
    //   268: aastore
    //   269: dup
    //   270: iconst_2
    //   271: getstatic 84	java/lang/Character:TYPE	Ljava/lang/Class;
    //   274: aastore
    //   275: invokevirtual 88	java/lang/Class:getMethod	(Ljava/lang/String;[Ljava/lang/Class;)Ljava/lang/reflect/Method;
    //   278: astore_0
    //   279: aload_0
    //   280: aconst_null
    //   281: iconst_3
    //   282: anewarray 4	java/lang/Object
    //   285: dup
    //   286: iconst_0
    //   287: ldc 120
    //   289: aastore
    //   290: dup
    //   291: iconst_1
    //   292: bipush 27
    //   294: invokestatic 94	java/lang/Character:valueOf	(C)Ljava/lang/Character;
    //   297: aastore
    //   298: dup
    //   299: iconst_2
    //   300: iconst_5
    //   301: invokestatic 94	java/lang/Character:valueOf	(C)Ljava/lang/Character;
    //   304: aastore
    //   305: invokevirtual 100	java/lang/reflect/Method:invoke	(Ljava/lang/Object;[Ljava/lang/Object;)Ljava/lang/Object;
    //   308: astore_0
    //   309: aload_0
    //   310: checkcast 78	java/lang/String
    //   313: areturn
    //   314: astore_0
    //   315: aload_0
    //   316: invokevirtual 110	java/lang/reflect/InvocationTargetException:getCause	()Ljava/lang/Throwable;
    //   319: athrow
    //   320: getstatic 122	uuuuuu/hphhhh:b0079yy00790079007900790079y	I
    //   323: getstatic 47	uuuuuu/hphhhh:byyy00790079007900790079y	I
    //   326: iadd
    //   327: getstatic 122	uuuuuu/hphhhh:b0079yy00790079007900790079y	I
    //   330: imul
    //   331: getstatic 124	uuuuuu/hphhhh:b00790079y00790079007900790079y	I
    //   334: irem
    //   335: getstatic 126	uuuuuu/hphhhh:by0079y00790079007900790079y	I
    //   338: if_icmpeq +15 -> 353
    //   341: invokestatic 45	uuuuuu/hphhhh:bw00770077007700770077w0077ww	()I
    //   344: putstatic 122	uuuuuu/hphhhh:b0079yy00790079007900790079y	I
    //   347: invokestatic 45	uuuuuu/hphhhh:bw00770077007700770077w0077ww	()I
    //   350: putstatic 126	uuuuuu/hphhhh:by0079y00790079007900790079y	I
    //   353: ldc 66
    //   355: ldc -128
    //   357: bipush 28
    //   359: iconst_1
    //   360: invokestatic 74	xxxxxx/uxxxxx:bb00620062bb0062b0062b0062	(Ljava/lang/String;CC)Ljava/lang/String;
    //   363: iconst_4
    //   364: anewarray 76	java/lang/Class
    //   367: dup
    //   368: iconst_0
    //   369: ldc 78
    //   371: aastore
    //   372: dup
    //   373: iconst_1
    //   374: getstatic 84	java/lang/Character:TYPE	Ljava/lang/Class;
    //   377: aastore
    //   378: dup
    //   379: iconst_2
    //   380: getstatic 84	java/lang/Character:TYPE	Ljava/lang/Class;
    //   383: aastore
    //   384: dup
    //   385: iconst_3
    //   386: getstatic 84	java/lang/Character:TYPE	Ljava/lang/Class;
    //   389: aastore
    //   390: invokevirtual 88	java/lang/Class:getMethod	(Ljava/lang/String;[Ljava/lang/Class;)Ljava/lang/reflect/Method;
    //   393: astore_0
    //   394: aload_0
    //   395: aconst_null
    //   396: iconst_4
    //   397: anewarray 4	java/lang/Object
    //   400: dup
    //   401: iconst_0
    //   402: ldc -126
    //   404: aastore
    //   405: dup
    //   406: iconst_1
    //   407: sipush 223
    //   410: invokestatic 94	java/lang/Character:valueOf	(C)Ljava/lang/Character;
    //   413: aastore
    //   414: dup
    //   415: iconst_2
    //   416: sipush 228
    //   419: invokestatic 94	java/lang/Character:valueOf	(C)Ljava/lang/Character;
    //   422: aastore
    //   423: dup
    //   424: iconst_3
    //   425: iconst_3
    //   426: invokestatic 94	java/lang/Character:valueOf	(C)Ljava/lang/Character;
    //   429: aastore
    //   430: invokevirtual 100	java/lang/reflect/Method:invoke	(Ljava/lang/Object;[Ljava/lang/Object;)Ljava/lang/Object;
    //   433: astore_0
    //   434: aload_0
    //   435: checkcast 78	java/lang/String
    //   438: areturn
    //   439: astore_0
    //   440: aload_0
    //   441: invokevirtual 110	java/lang/reflect/InvocationTargetException:getCause	()Ljava/lang/Throwable;
    //   444: athrow
    //   445: aload_0
    //   446: ldc2_w 131
    //   449: iconst_2
    //   450: invokestatic 58	uuuuuu/onoonn:bk006Bkkk006Bk006Bk006B	(DI)Ljava/math/BigDecimal;
    //   453: invokevirtual 64	java/math/BigDecimal:compareTo	(Ljava/math/BigDecimal;)I
    //   456: ifne -229 -> 227
    //   459: ldc 66
    //   461: ldc -122
    //   463: bipush 12
    //   465: iconst_1
    //   466: invokestatic 74	xxxxxx/uxxxxx:bb00620062bb0062b0062b0062	(Ljava/lang/String;CC)Ljava/lang/String;
    //   469: iconst_4
    //   470: anewarray 76	java/lang/Class
    //   473: dup
    //   474: iconst_0
    //   475: ldc 78
    //   477: aastore
    //   478: dup
    //   479: iconst_1
    //   480: getstatic 84	java/lang/Character:TYPE	Ljava/lang/Class;
    //   483: aastore
    //   484: dup
    //   485: iconst_2
    //   486: getstatic 84	java/lang/Character:TYPE	Ljava/lang/Class;
    //   489: aastore
    //   490: dup
    //   491: iconst_3
    //   492: getstatic 84	java/lang/Character:TYPE	Ljava/lang/Class;
    //   495: aastore
    //   496: invokevirtual 88	java/lang/Class:getMethod	(Ljava/lang/String;[Ljava/lang/Class;)Ljava/lang/reflect/Method;
    //   499: astore_0
    //   500: aload_0
    //   501: aconst_null
    //   502: iconst_4
    //   503: anewarray 4	java/lang/Object
    //   506: dup
    //   507: iconst_0
    //   508: ldc -120
    //   510: aastore
    //   511: dup
    //   512: iconst_1
    //   513: sipush 168
    //   516: invokestatic 94	java/lang/Character:valueOf	(C)Ljava/lang/Character;
    //   519: aastore
    //   520: dup
    //   521: iconst_2
    //   522: sipush 134
    //   525: invokestatic 94	java/lang/Character:valueOf	(C)Ljava/lang/Character;
    //   528: aastore
    //   529: dup
    //   530: iconst_3
    //   531: iconst_2
    //   532: invokestatic 94	java/lang/Character:valueOf	(C)Ljava/lang/Character;
    //   535: aastore
    //   536: invokevirtual 100	java/lang/reflect/Method:invoke	(Ljava/lang/Object;[Ljava/lang/Object;)Ljava/lang/Object;
    //   539: astore_0
    //   540: aload_0
    //   541: checkcast 78	java/lang/String
    //   544: areturn
    //   545: astore_0
    //   546: aload_0
    //   547: invokevirtual 110	java/lang/reflect/InvocationTargetException:getCause	()Ljava/lang/Throwable;
    //   550: athrow
    //   551: astore_0
    //   552: aload_0
    //   553: invokevirtual 110	java/lang/reflect/InvocationTargetException:getCause	()Ljava/lang/Throwable;
    //   556: athrow
    // Local variable table:
    //   start	length	slot	name	signature
    //   0	557	0	paramBigDecimal	java.math.BigDecimal
    //   3	8	1	i	int
    // Exception table:
    //   from	to	target	type
    //   178	216	221	java/lang/reflect/InvocationTargetException
    //   279	309	314	java/lang/reflect/InvocationTargetException
    //   87	117	439	java/lang/reflect/InvocationTargetException
    //   394	434	545	java/lang/reflect/InvocationTargetException
    //   500	540	551	java/lang/reflect/InvocationTargetException
  }
  
  public static int b0077w0077007700770077w0077ww()
  {
    return 2;
  }
  
  public static int bw00770077007700770077w0077ww()
  {
    return 86;
  }
  
  @Retention(RetentionPolicy.SOURCE)
  public static @interface pphhhh {}
}
