package uuuuuu;

public abstract class hyyhhy<T>
  extends qppppp<yhhhyy.yyhhyy>
  implements yhhhyy.hyhhyy
{
  public static int b00700070pp0070pp0070p = 1;
  public static int b0070ppp0070pp0070p = 71;
  public static int bp0070pp0070pp0070p = 0;
  public static int bpp0070p0070pp0070p = 2;
  public String bpppp0070pp0070p;
  
  public hyyhhy() {}
  
  public static int b006F006Foo006F006Foooo()
  {
    return 0;
  }
  
  public static int bo006Foo006F006Foooo()
  {
    return 1;
  }
  
  public static int boo006Fo006F006Foooo()
  {
    return 95;
  }
  
  /* Error */
  public void b006F006F006Fo006F006Foooo(String paramString)
  {
    // Byte code:
    //   0: aload_0
    //   1: aload_1
    //   2: putfield 33	uuuuuu/hyyhhy:bpppp0070pp0070p	Ljava/lang/String;
    //   5: getstatic 35	uuuuuu/hyyhhy:b0070ppp0070pp0070p	I
    //   8: getstatic 37	uuuuuu/hyyhhy:b00700070pp0070pp0070p	I
    //   11: iadd
    //   12: getstatic 35	uuuuuu/hyyhhy:b0070ppp0070pp0070p	I
    //   15: imul
    //   16: getstatic 39	uuuuuu/hyyhhy:bpp0070p0070pp0070p	I
    //   19: irem
    //   20: getstatic 41	uuuuuu/hyyhhy:bp0070pp0070pp0070p	I
    //   23: if_icmpeq +235 -> 258
    //   26: bipush 8
    //   28: putstatic 35	uuuuuu/hyyhhy:b0070ppp0070pp0070p	I
    //   31: ldc 2
    //   33: ldc 43
    //   35: sipush 243
    //   38: bipush 89
    //   40: iconst_0
    //   41: invokestatic 49	xxxxxx/uxxxxx:bbbb0062b0062b0062b0062	(Ljava/lang/String;CCC)Ljava/lang/String;
    //   44: iconst_0
    //   45: anewarray 51	java/lang/Class
    //   48: invokevirtual 55	java/lang/Class:getMethod	(Ljava/lang/String;[Ljava/lang/Class;)Ljava/lang/reflect/Method;
    //   51: astore_1
    //   52: aload_1
    //   53: aconst_null
    //   54: iconst_0
    //   55: anewarray 57	java/lang/Object
    //   58: invokevirtual 63	java/lang/reflect/Method:invoke	(Ljava/lang/Object;[Ljava/lang/Object;)Ljava/lang/Object;
    //   61: astore_1
    //   62: aload_1
    //   63: checkcast 65	java/lang/Integer
    //   66: invokevirtual 68	java/lang/Integer:intValue	()I
    //   69: istore_2
    //   70: getstatic 35	uuuuuu/hyyhhy:b0070ppp0070pp0070p	I
    //   73: istore_3
    //   74: iload_3
    //   75: getstatic 37	uuuuuu/hyyhhy:b00700070pp0070pp0070p	I
    //   78: iload_3
    //   79: iadd
    //   80: imul
    //   81: getstatic 39	uuuuuu/hyyhhy:bpp0070p0070pp0070p	I
    //   84: irem
    //   85: tableswitch	default:+19->104, 0:+169->254
    //   104: ldc 2
    //   106: ldc 70
    //   108: sipush 230
    //   111: iconst_0
    //   112: invokestatic 74	xxxxxx/uxxxxx:bb00620062bb0062b0062b0062	(Ljava/lang/String;CC)Ljava/lang/String;
    //   115: iconst_0
    //   116: anewarray 51	java/lang/Class
    //   119: invokevirtual 55	java/lang/Class:getMethod	(Ljava/lang/String;[Ljava/lang/Class;)Ljava/lang/reflect/Method;
    //   122: astore_1
    //   123: aload_1
    //   124: aconst_null
    //   125: iconst_0
    //   126: anewarray 57	java/lang/Object
    //   129: invokevirtual 63	java/lang/reflect/Method:invoke	(Ljava/lang/Object;[Ljava/lang/Object;)Ljava/lang/Object;
    //   132: astore_1
    //   133: aload_1
    //   134: checkcast 65	java/lang/Integer
    //   137: invokevirtual 68	java/lang/Integer:intValue	()I
    //   140: putstatic 35	uuuuuu/hyyhhy:b0070ppp0070pp0070p	I
    //   143: bipush 63
    //   145: putstatic 41	uuuuuu/hyyhhy:bp0070pp0070pp0070p	I
    //   148: getstatic 35	uuuuuu/hyyhhy:b0070ppp0070pp0070p	I
    //   151: getstatic 37	uuuuuu/hyyhhy:b00700070pp0070pp0070p	I
    //   154: iadd
    //   155: getstatic 35	uuuuuu/hyyhhy:b0070ppp0070pp0070p	I
    //   158: imul
    //   159: getstatic 39	uuuuuu/hyyhhy:bpp0070p0070pp0070p	I
    //   162: irem
    //   163: getstatic 41	uuuuuu/hyyhhy:bp0070pp0070pp0070p	I
    //   166: if_icmpeq +46 -> 212
    //   169: ldc 2
    //   171: ldc 76
    //   173: bipush 47
    //   175: iconst_0
    //   176: invokestatic 74	xxxxxx/uxxxxx:bb00620062bb0062b0062b0062	(Ljava/lang/String;CC)Ljava/lang/String;
    //   179: iconst_0
    //   180: anewarray 51	java/lang/Class
    //   183: invokevirtual 55	java/lang/Class:getMethod	(Ljava/lang/String;[Ljava/lang/Class;)Ljava/lang/reflect/Method;
    //   186: astore_1
    //   187: aload_1
    //   188: aconst_null
    //   189: iconst_0
    //   190: anewarray 57	java/lang/Object
    //   193: invokevirtual 63	java/lang/reflect/Method:invoke	(Ljava/lang/Object;[Ljava/lang/Object;)Ljava/lang/Object;
    //   196: astore_1
    //   197: aload_1
    //   198: checkcast 65	java/lang/Integer
    //   201: invokevirtual 68	java/lang/Integer:intValue	()I
    //   204: putstatic 35	uuuuuu/hyyhhy:b0070ppp0070pp0070p	I
    //   207: bipush 79
    //   209: putstatic 41	uuuuuu/hyyhhy:bp0070pp0070pp0070p	I
    //   212: getstatic 35	uuuuuu/hyyhhy:b0070ppp0070pp0070p	I
    //   215: istore_3
    //   216: iload_3
    //   217: getstatic 37	uuuuuu/hyyhhy:b00700070pp0070pp0070p	I
    //   220: iload_3
    //   221: iadd
    //   222: imul
    //   223: getstatic 39	uuuuuu/hyyhhy:bpp0070p0070pp0070p	I
    //   226: irem
    //   227: tableswitch	default:+17->244, 0:+27->254
    //   244: bipush 71
    //   246: putstatic 35	uuuuuu/hyyhhy:b0070ppp0070pp0070p	I
    //   249: bipush 68
    //   251: putstatic 41	uuuuuu/hyyhhy:bp0070pp0070pp0070p	I
    //   254: iload_2
    //   255: putstatic 41	uuuuuu/hyyhhy:bp0070pp0070pp0070p	I
    //   258: ldc 2
    //   260: ldc 78
    //   262: sipush 229
    //   265: bipush 30
    //   267: iconst_2
    //   268: invokestatic 49	xxxxxx/uxxxxx:bbbb0062b0062b0062b0062	(Ljava/lang/String;CCC)Ljava/lang/String;
    //   271: iconst_0
    //   272: anewarray 51	java/lang/Class
    //   275: invokevirtual 55	java/lang/Class:getMethod	(Ljava/lang/String;[Ljava/lang/Class;)Ljava/lang/reflect/Method;
    //   278: astore_1
    //   279: aload_1
    //   280: aload_0
    //   281: iconst_0
    //   282: anewarray 57	java/lang/Object
    //   285: invokevirtual 63	java/lang/reflect/Method:invoke	(Ljava/lang/Object;[Ljava/lang/Object;)Ljava/lang/Object;
    //   288: pop
    //   289: return
    //   290: astore_1
    //   291: aload_1
    //   292: invokevirtual 82	java/lang/reflect/InvocationTargetException:getCause	()Ljava/lang/Throwable;
    //   295: athrow
    //   296: astore_1
    //   297: aload_1
    //   298: invokevirtual 82	java/lang/reflect/InvocationTargetException:getCause	()Ljava/lang/Throwable;
    //   301: athrow
    //   302: astore_1
    //   303: aload_1
    //   304: invokevirtual 82	java/lang/reflect/InvocationTargetException:getCause	()Ljava/lang/Throwable;
    //   307: athrow
    //   308: astore_1
    //   309: aload_1
    //   310: invokevirtual 82	java/lang/reflect/InvocationTargetException:getCause	()Ljava/lang/Throwable;
    //   313: athrow
    // Local variable table:
    //   start	length	slot	name	signature
    //   0	314	0	this	hyyhhy
    //   0	314	1	paramString	String
    //   69	186	2	i	int
    //   73	150	3	j	int
    // Exception table:
    //   from	to	target	type
    //   52	62	290	java/lang/reflect/InvocationTargetException
    //   279	289	296	java/lang/reflect/InvocationTargetException
    //   123	133	302	java/lang/reflect/InvocationTargetException
    //   187	197	308	java/lang/reflect/InvocationTargetException
  }
  
  public abstract void b006F006Fo006F006F006Foooo(T paramT);
  
  public abstract void b006Fo006F006F006F006Foooo();
  
  public void b006Fo006Fo006F006Foooo() {}
  
  /* Error */
  public void b006Foo006F006F006Foooo()
  {
    // Byte code:
    //   0: aload_0
    //   1: invokevirtual 91	uuuuuu/hyyhhy:bkk006Bk006Bk006Bk006Bk	()Z
    //   4: ifeq +15 -> 19
    //   7: aload_0
    //   8: getfield 95	uuuuuu/hyyhhy:bnnnnn006E006E006En	Luuuuuu/ttssst$tsssst;
    //   11: checkcast 97	uuuuuu/yhhhyy$yyhhyy
    //   14: invokeinterface 100 1 0
    //   19: getstatic 35	uuuuuu/hyyhhy:b0070ppp0070pp0070p	I
    //   22: istore_1
    //   23: ldc 2
    //   25: ldc 102
    //   27: bipush 60
    //   29: iconst_1
    //   30: invokestatic 74	xxxxxx/uxxxxx:bb00620062bb0062b0062b0062	(Ljava/lang/String;CC)Ljava/lang/String;
    //   33: iconst_0
    //   34: anewarray 51	java/lang/Class
    //   37: invokevirtual 55	java/lang/Class:getMethod	(Ljava/lang/String;[Ljava/lang/Class;)Ljava/lang/reflect/Method;
    //   40: astore_3
    //   41: aload_3
    //   42: aconst_null
    //   43: iconst_0
    //   44: anewarray 57	java/lang/Object
    //   47: invokevirtual 63	java/lang/reflect/Method:invoke	(Ljava/lang/Object;[Ljava/lang/Object;)Ljava/lang/Object;
    //   50: astore_3
    //   51: aload_3
    //   52: checkcast 65	java/lang/Integer
    //   55: invokevirtual 68	java/lang/Integer:intValue	()I
    //   58: iload_1
    //   59: iadd
    //   60: iload_1
    //   61: imul
    //   62: getstatic 39	uuuuuu/hyyhhy:bpp0070p0070pp0070p	I
    //   65: irem
    //   66: tableswitch	default:+18->84, 0:+61->127
    //   84: ldc 2
    //   86: ldc 104
    //   88: bipush 104
    //   90: iconst_0
    //   91: invokestatic 74	xxxxxx/uxxxxx:bb00620062bb0062b0062b0062	(Ljava/lang/String;CC)Ljava/lang/String;
    //   94: iconst_0
    //   95: anewarray 51	java/lang/Class
    //   98: invokevirtual 55	java/lang/Class:getMethod	(Ljava/lang/String;[Ljava/lang/Class;)Ljava/lang/reflect/Method;
    //   101: astore_3
    //   102: aload_3
    //   103: aconst_null
    //   104: iconst_0
    //   105: anewarray 57	java/lang/Object
    //   108: invokevirtual 63	java/lang/reflect/Method:invoke	(Ljava/lang/Object;[Ljava/lang/Object;)Ljava/lang/Object;
    //   111: astore_3
    //   112: aload_3
    //   113: checkcast 65	java/lang/Integer
    //   116: invokevirtual 68	java/lang/Integer:intValue	()I
    //   119: putstatic 35	uuuuuu/hyyhhy:b0070ppp0070pp0070p	I
    //   122: bipush 48
    //   124: putstatic 41	uuuuuu/hyyhhy:bp0070pp0070pp0070p	I
    //   127: aload_0
    //   128: getfield 108	uuuuuu/hyyhhy:b006En006E006E006En006E006En	Luuuuuu/ggyggy;
    //   131: getstatic 114	uuuuuu/gyyygy$yyyygy:bkkk006Bk006Bk006Bk	Luuuuuu/gyyygy$yyyygy;
    //   134: invokevirtual 120	uuuuuu/ggyggy:b0070007000700070pp00700070pp	(Luuuuuu/gyyygy$yyyygy;)Luuuuuu/yyyggy;
    //   137: astore_3
    //   138: ldc 2
    //   140: ldc 122
    //   142: sipush 180
    //   145: bipush 33
    //   147: iconst_0
    //   148: invokestatic 49	xxxxxx/uxxxxx:bbbb0062b0062b0062b0062	(Ljava/lang/String;CCC)Ljava/lang/String;
    //   151: iconst_0
    //   152: anewarray 51	java/lang/Class
    //   155: invokevirtual 55	java/lang/Class:getMethod	(Ljava/lang/String;[Ljava/lang/Class;)Ljava/lang/reflect/Method;
    //   158: astore 4
    //   160: aload 4
    //   162: aconst_null
    //   163: iconst_0
    //   164: anewarray 57	java/lang/Object
    //   167: invokevirtual 63	java/lang/reflect/Method:invoke	(Ljava/lang/Object;[Ljava/lang/Object;)Ljava/lang/Object;
    //   170: astore 4
    //   172: aload 4
    //   174: checkcast 65	java/lang/Integer
    //   177: invokevirtual 68	java/lang/Integer:intValue	()I
    //   180: istore_1
    //   181: getstatic 37	uuuuuu/hyyhhy:b00700070pp0070pp0070p	I
    //   184: istore_2
    //   185: getstatic 35	uuuuuu/hyyhhy:b0070ppp0070pp0070p	I
    //   188: getstatic 37	uuuuuu/hyyhhy:b00700070pp0070pp0070p	I
    //   191: iadd
    //   192: getstatic 35	uuuuuu/hyyhhy:b0070ppp0070pp0070p	I
    //   195: imul
    //   196: getstatic 39	uuuuuu/hyyhhy:bpp0070p0070pp0070p	I
    //   199: irem
    //   200: getstatic 41	uuuuuu/hyyhhy:bp0070pp0070pp0070p	I
    //   203: if_icmpeq +51 -> 254
    //   206: iconst_3
    //   207: putstatic 35	uuuuuu/hyyhhy:b0070ppp0070pp0070p	I
    //   210: ldc 2
    //   212: ldc 124
    //   214: bipush 49
    //   216: bipush 121
    //   218: iconst_1
    //   219: invokestatic 49	xxxxxx/uxxxxx:bbbb0062b0062b0062b0062	(Ljava/lang/String;CCC)Ljava/lang/String;
    //   222: iconst_0
    //   223: anewarray 51	java/lang/Class
    //   226: invokevirtual 55	java/lang/Class:getMethod	(Ljava/lang/String;[Ljava/lang/Class;)Ljava/lang/reflect/Method;
    //   229: astore 4
    //   231: aload 4
    //   233: aconst_null
    //   234: iconst_0
    //   235: anewarray 57	java/lang/Object
    //   238: invokevirtual 63	java/lang/reflect/Method:invoke	(Ljava/lang/Object;[Ljava/lang/Object;)Ljava/lang/Object;
    //   241: astore 4
    //   243: aload 4
    //   245: checkcast 65	java/lang/Integer
    //   248: invokevirtual 68	java/lang/Integer:intValue	()I
    //   251: putstatic 41	uuuuuu/hyyhhy:bp0070pp0070pp0070p	I
    //   254: getstatic 35	uuuuuu/hyyhhy:b0070ppp0070pp0070p	I
    //   257: getstatic 37	uuuuuu/hyyhhy:b00700070pp0070pp0070p	I
    //   260: iadd
    //   261: getstatic 35	uuuuuu/hyyhhy:b0070ppp0070pp0070p	I
    //   264: imul
    //   265: getstatic 39	uuuuuu/hyyhhy:bpp0070p0070pp0070p	I
    //   268: irem
    //   269: getstatic 41	uuuuuu/hyyhhy:bp0070pp0070pp0070p	I
    //   272: if_icmpeq +51 -> 323
    //   275: bipush 99
    //   277: putstatic 35	uuuuuu/hyyhhy:b0070ppp0070pp0070p	I
    //   280: ldc 2
    //   282: ldc 126
    //   284: sipush 207
    //   287: iconst_2
    //   288: invokestatic 74	xxxxxx/uxxxxx:bb00620062bb0062b0062b0062	(Ljava/lang/String;CC)Ljava/lang/String;
    //   291: iconst_0
    //   292: anewarray 51	java/lang/Class
    //   295: invokevirtual 55	java/lang/Class:getMethod	(Ljava/lang/String;[Ljava/lang/Class;)Ljava/lang/reflect/Method;
    //   298: astore 4
    //   300: aload 4
    //   302: aconst_null
    //   303: iconst_0
    //   304: anewarray 57	java/lang/Object
    //   307: invokevirtual 63	java/lang/reflect/Method:invoke	(Ljava/lang/Object;[Ljava/lang/Object;)Ljava/lang/Object;
    //   310: astore 4
    //   312: aload 4
    //   314: checkcast 65	java/lang/Integer
    //   317: invokevirtual 68	java/lang/Integer:intValue	()I
    //   320: putstatic 41	uuuuuu/hyyhhy:bp0070pp0070pp0070p	I
    //   323: ldc 2
    //   325: ldc -128
    //   327: sipush 199
    //   330: iconst_4
    //   331: invokestatic 74	xxxxxx/uxxxxx:bb00620062bb0062b0062b0062	(Ljava/lang/String;CC)Ljava/lang/String;
    //   334: iconst_0
    //   335: anewarray 51	java/lang/Class
    //   338: invokevirtual 55	java/lang/Class:getMethod	(Ljava/lang/String;[Ljava/lang/Class;)Ljava/lang/reflect/Method;
    //   341: astore 4
    //   343: aload 4
    //   345: aconst_null
    //   346: iconst_0
    //   347: anewarray 57	java/lang/Object
    //   350: invokevirtual 63	java/lang/reflect/Method:invoke	(Ljava/lang/Object;[Ljava/lang/Object;)Ljava/lang/Object;
    //   353: astore 4
    //   355: aload 4
    //   357: checkcast 65	java/lang/Integer
    //   360: invokevirtual 68	java/lang/Integer:intValue	()I
    //   363: iload_1
    //   364: iload_2
    //   365: iadd
    //   366: imul
    //   367: getstatic 39	uuuuuu/hyyhhy:bpp0070p0070pp0070p	I
    //   370: irem
    //   371: getstatic 41	uuuuuu/hyyhhy:bp0070pp0070pp0070p	I
    //   374: if_icmpeq +90 -> 464
    //   377: ldc 2
    //   379: ldc -126
    //   381: sipush 247
    //   384: bipush 38
    //   386: iconst_2
    //   387: invokestatic 49	xxxxxx/uxxxxx:bbbb0062b0062b0062b0062	(Ljava/lang/String;CCC)Ljava/lang/String;
    //   390: iconst_0
    //   391: anewarray 51	java/lang/Class
    //   394: invokevirtual 55	java/lang/Class:getMethod	(Ljava/lang/String;[Ljava/lang/Class;)Ljava/lang/reflect/Method;
    //   397: astore 4
    //   399: aload 4
    //   401: aconst_null
    //   402: iconst_0
    //   403: anewarray 57	java/lang/Object
    //   406: invokevirtual 63	java/lang/reflect/Method:invoke	(Ljava/lang/Object;[Ljava/lang/Object;)Ljava/lang/Object;
    //   409: astore 4
    //   411: aload 4
    //   413: checkcast 65	java/lang/Integer
    //   416: invokevirtual 68	java/lang/Integer:intValue	()I
    //   419: putstatic 35	uuuuuu/hyyhhy:b0070ppp0070pp0070p	I
    //   422: ldc 2
    //   424: ldc -124
    //   426: bipush 11
    //   428: iconst_0
    //   429: invokestatic 74	xxxxxx/uxxxxx:bb00620062bb0062b0062b0062	(Ljava/lang/String;CC)Ljava/lang/String;
    //   432: iconst_0
    //   433: anewarray 51	java/lang/Class
    //   436: invokevirtual 55	java/lang/Class:getMethod	(Ljava/lang/String;[Ljava/lang/Class;)Ljava/lang/reflect/Method;
    //   439: astore 4
    //   441: aload 4
    //   443: aconst_null
    //   444: iconst_0
    //   445: anewarray 57	java/lang/Object
    //   448: invokevirtual 63	java/lang/reflect/Method:invoke	(Ljava/lang/Object;[Ljava/lang/Object;)Ljava/lang/Object;
    //   451: astore 4
    //   453: aload 4
    //   455: checkcast 65	java/lang/Integer
    //   458: invokevirtual 68	java/lang/Integer:intValue	()I
    //   461: putstatic 41	uuuuuu/hyyhhy:bp0070pp0070pp0070p	I
    //   464: aload_3
    //   465: iconst_1
    //   466: anewarray 57	java/lang/Object
    //   469: dup
    //   470: iconst_0
    //   471: getstatic 138	uuuuuu/lolllo:bq0071q00710071qqq0071	Luuuuuu/lolllo;
    //   474: invokevirtual 142	uuuuuu/lolllo:name	()Ljava/lang/String;
    //   477: aastore
    //   478: invokeinterface 148 2 0
    //   483: return
    //   484: astore_3
    //   485: aload_3
    //   486: invokevirtual 82	java/lang/reflect/InvocationTargetException:getCause	()Ljava/lang/Throwable;
    //   489: athrow
    //   490: astore_3
    //   491: aload_3
    //   492: invokevirtual 82	java/lang/reflect/InvocationTargetException:getCause	()Ljava/lang/Throwable;
    //   495: athrow
    //   496: astore_3
    //   497: aload_3
    //   498: invokevirtual 82	java/lang/reflect/InvocationTargetException:getCause	()Ljava/lang/Throwable;
    //   501: athrow
    //   502: astore_3
    //   503: aload_3
    //   504: invokevirtual 82	java/lang/reflect/InvocationTargetException:getCause	()Ljava/lang/Throwable;
    //   507: athrow
    //   508: astore_3
    //   509: aload_3
    //   510: invokevirtual 82	java/lang/reflect/InvocationTargetException:getCause	()Ljava/lang/Throwable;
    //   513: athrow
    //   514: astore_3
    //   515: aload_3
    //   516: invokevirtual 82	java/lang/reflect/InvocationTargetException:getCause	()Ljava/lang/Throwable;
    //   519: athrow
    //   520: astore_3
    //   521: aload_3
    //   522: invokevirtual 82	java/lang/reflect/InvocationTargetException:getCause	()Ljava/lang/Throwable;
    //   525: athrow
    //   526: astore_3
    //   527: aload_3
    //   528: invokevirtual 82	java/lang/reflect/InvocationTargetException:getCause	()Ljava/lang/Throwable;
    //   531: athrow
    // Local variable table:
    //   start	length	slot	name	signature
    //   0	532	0	this	hyyhhy
    //   22	344	1	i	int
    //   184	182	2	j	int
    //   40	425	3	localObject1	Object
    //   484	2	3	localInvocationTargetException1	java.lang.reflect.InvocationTargetException
    //   490	2	3	localInvocationTargetException2	java.lang.reflect.InvocationTargetException
    //   496	2	3	localInvocationTargetException3	java.lang.reflect.InvocationTargetException
    //   502	2	3	localInvocationTargetException4	java.lang.reflect.InvocationTargetException
    //   508	2	3	localInvocationTargetException5	java.lang.reflect.InvocationTargetException
    //   514	2	3	localInvocationTargetException6	java.lang.reflect.InvocationTargetException
    //   520	2	3	localInvocationTargetException7	java.lang.reflect.InvocationTargetException
    //   526	2	3	localInvocationTargetException8	java.lang.reflect.InvocationTargetException
    //   158	296	4	localObject2	Object
    // Exception table:
    //   from	to	target	type
    //   300	312	484	java/lang/reflect/InvocationTargetException
    //   102	112	490	java/lang/reflect/InvocationTargetException
    //   41	51	496	java/lang/reflect/InvocationTargetException
    //   399	411	502	java/lang/reflect/InvocationTargetException
    //   441	453	508	java/lang/reflect/InvocationTargetException
    //   343	355	514	java/lang/reflect/InvocationTargetException
    //   160	172	520	java/lang/reflect/InvocationTargetException
    //   231	243	526	java/lang/reflect/InvocationTargetException
  }
  
  /* Error */
  public void bo006F006F006F006F006Foooo()
  {
    // Byte code:
    //   0: aload_0
    //   1: getfield 95	uuuuuu/hyyhhy:bnnnnn006E006E006En	Luuuuuu/ttssst$tsssst;
    //   4: checkcast 97	uuuuuu/yhhhyy$yyhhyy
    //   7: invokeinterface 152 1 0
    //   12: ldc 2
    //   14: ldc -102
    //   16: sipush 150
    //   19: iconst_4
    //   20: invokestatic 74	xxxxxx/uxxxxx:bb00620062bb0062b0062b0062	(Ljava/lang/String;CC)Ljava/lang/String;
    //   23: iconst_0
    //   24: anewarray 51	java/lang/Class
    //   27: invokevirtual 55	java/lang/Class:getMethod	(Ljava/lang/String;[Ljava/lang/Class;)Ljava/lang/reflect/Method;
    //   30: astore_2
    //   31: aload_2
    //   32: aconst_null
    //   33: iconst_0
    //   34: anewarray 57	java/lang/Object
    //   37: invokevirtual 63	java/lang/reflect/Method:invoke	(Ljava/lang/Object;[Ljava/lang/Object;)Ljava/lang/Object;
    //   40: astore_2
    //   41: aload_2
    //   42: checkcast 65	java/lang/Integer
    //   45: invokevirtual 68	java/lang/Integer:intValue	()I
    //   48: istore_1
    //   49: iload_1
    //   50: getstatic 37	uuuuuu/hyyhhy:b00700070pp0070pp0070p	I
    //   53: iload_1
    //   54: iadd
    //   55: imul
    //   56: getstatic 39	uuuuuu/hyyhhy:bpp0070p0070pp0070p	I
    //   59: irem
    //   60: tableswitch	default:+20->80, 0:+63->123
    //   80: bipush 86
    //   82: putstatic 35	uuuuuu/hyyhhy:b0070ppp0070pp0070p	I
    //   85: ldc 2
    //   87: ldc -100
    //   89: bipush 86
    //   91: iconst_4
    //   92: invokestatic 74	xxxxxx/uxxxxx:bb00620062bb0062b0062b0062	(Ljava/lang/String;CC)Ljava/lang/String;
    //   95: iconst_0
    //   96: anewarray 51	java/lang/Class
    //   99: invokevirtual 55	java/lang/Class:getMethod	(Ljava/lang/String;[Ljava/lang/Class;)Ljava/lang/reflect/Method;
    //   102: astore_2
    //   103: aload_2
    //   104: aconst_null
    //   105: iconst_0
    //   106: anewarray 57	java/lang/Object
    //   109: invokevirtual 63	java/lang/reflect/Method:invoke	(Ljava/lang/Object;[Ljava/lang/Object;)Ljava/lang/Object;
    //   112: astore_2
    //   113: aload_2
    //   114: checkcast 65	java/lang/Integer
    //   117: invokevirtual 68	java/lang/Integer:intValue	()I
    //   120: putstatic 41	uuuuuu/hyyhhy:bp0070pp0070pp0070p	I
    //   123: ldc 2
    //   125: ldc -98
    //   127: bipush 111
    //   129: iconst_5
    //   130: invokestatic 74	xxxxxx/uxxxxx:bb00620062bb0062b0062b0062	(Ljava/lang/String;CC)Ljava/lang/String;
    //   133: iconst_0
    //   134: anewarray 51	java/lang/Class
    //   137: invokevirtual 55	java/lang/Class:getMethod	(Ljava/lang/String;[Ljava/lang/Class;)Ljava/lang/reflect/Method;
    //   140: astore_2
    //   141: aload_2
    //   142: aload_0
    //   143: iconst_0
    //   144: anewarray 57	java/lang/Object
    //   147: invokevirtual 63	java/lang/reflect/Method:invoke	(Ljava/lang/Object;[Ljava/lang/Object;)Ljava/lang/Object;
    //   150: pop
    //   151: ldc 2
    //   153: ldc -96
    //   155: bipush 79
    //   157: iconst_5
    //   158: invokestatic 74	xxxxxx/uxxxxx:bb00620062bb0062b0062b0062	(Ljava/lang/String;CC)Ljava/lang/String;
    //   161: iconst_0
    //   162: anewarray 51	java/lang/Class
    //   165: invokevirtual 55	java/lang/Class:getMethod	(Ljava/lang/String;[Ljava/lang/Class;)Ljava/lang/reflect/Method;
    //   168: astore_2
    //   169: aload_2
    //   170: aload_0
    //   171: iconst_0
    //   172: anewarray 57	java/lang/Object
    //   175: invokevirtual 63	java/lang/reflect/Method:invoke	(Ljava/lang/Object;[Ljava/lang/Object;)Ljava/lang/Object;
    //   178: pop
    //   179: getstatic 35	uuuuuu/hyyhhy:b0070ppp0070pp0070p	I
    //   182: getstatic 37	uuuuuu/hyyhhy:b00700070pp0070pp0070p	I
    //   185: iadd
    //   186: getstatic 35	uuuuuu/hyyhhy:b0070ppp0070pp0070p	I
    //   189: imul
    //   190: getstatic 39	uuuuuu/hyyhhy:bpp0070p0070pp0070p	I
    //   193: irem
    //   194: getstatic 41	uuuuuu/hyyhhy:bp0070pp0070pp0070p	I
    //   197: if_icmpeq +76 -> 273
    //   200: iconst_2
    //   201: putstatic 35	uuuuuu/hyyhhy:b0070ppp0070pp0070p	I
    //   204: getstatic 35	uuuuuu/hyyhhy:b0070ppp0070pp0070p	I
    //   207: getstatic 37	uuuuuu/hyyhhy:b00700070pp0070pp0070p	I
    //   210: iadd
    //   211: getstatic 35	uuuuuu/hyyhhy:b0070ppp0070pp0070p	I
    //   214: imul
    //   215: getstatic 39	uuuuuu/hyyhhy:bpp0070p0070pp0070p	I
    //   218: irem
    //   219: getstatic 41	uuuuuu/hyyhhy:bp0070pp0070pp0070p	I
    //   222: if_icmpeq +13 -> 235
    //   225: bipush 54
    //   227: putstatic 35	uuuuuu/hyyhhy:b0070ppp0070pp0070p	I
    //   230: bipush 72
    //   232: putstatic 41	uuuuuu/hyyhhy:bp0070pp0070pp0070p	I
    //   235: ldc 2
    //   237: ldc -94
    //   239: bipush 37
    //   241: iconst_2
    //   242: invokestatic 74	xxxxxx/uxxxxx:bb00620062bb0062b0062b0062	(Ljava/lang/String;CC)Ljava/lang/String;
    //   245: iconst_0
    //   246: anewarray 51	java/lang/Class
    //   249: invokevirtual 55	java/lang/Class:getMethod	(Ljava/lang/String;[Ljava/lang/Class;)Ljava/lang/reflect/Method;
    //   252: astore_2
    //   253: aload_2
    //   254: aconst_null
    //   255: iconst_0
    //   256: anewarray 57	java/lang/Object
    //   259: invokevirtual 63	java/lang/reflect/Method:invoke	(Ljava/lang/Object;[Ljava/lang/Object;)Ljava/lang/Object;
    //   262: astore_2
    //   263: aload_2
    //   264: checkcast 65	java/lang/Integer
    //   267: invokevirtual 68	java/lang/Integer:intValue	()I
    //   270: putstatic 41	uuuuuu/hyyhhy:bp0070pp0070pp0070p	I
    //   273: getstatic 35	uuuuuu/hyyhhy:b0070ppp0070pp0070p	I
    //   276: istore_1
    //   277: iload_1
    //   278: getstatic 37	uuuuuu/hyyhhy:b00700070pp0070pp0070p	I
    //   281: iload_1
    //   282: iadd
    //   283: imul
    //   284: getstatic 39	uuuuuu/hyyhhy:bpp0070p0070pp0070p	I
    //   287: irem
    //   288: tableswitch	default:+20->308, 0:+64->352
    //   308: bipush 6
    //   310: putstatic 35	uuuuuu/hyyhhy:b0070ppp0070pp0070p	I
    //   313: ldc 2
    //   315: ldc -92
    //   317: sipush 211
    //   320: iconst_5
    //   321: invokestatic 74	xxxxxx/uxxxxx:bb00620062bb0062b0062b0062	(Ljava/lang/String;CC)Ljava/lang/String;
    //   324: iconst_0
    //   325: anewarray 51	java/lang/Class
    //   328: invokevirtual 55	java/lang/Class:getMethod	(Ljava/lang/String;[Ljava/lang/Class;)Ljava/lang/reflect/Method;
    //   331: astore_2
    //   332: aload_2
    //   333: aconst_null
    //   334: iconst_0
    //   335: anewarray 57	java/lang/Object
    //   338: invokevirtual 63	java/lang/reflect/Method:invoke	(Ljava/lang/Object;[Ljava/lang/Object;)Ljava/lang/Object;
    //   341: astore_2
    //   342: aload_2
    //   343: checkcast 65	java/lang/Integer
    //   346: invokevirtual 68	java/lang/Integer:intValue	()I
    //   349: putstatic 41	uuuuuu/hyyhhy:bp0070pp0070pp0070p	I
    //   352: return
    //   353: astore_2
    //   354: aload_2
    //   355: invokevirtual 82	java/lang/reflect/InvocationTargetException:getCause	()Ljava/lang/Throwable;
    //   358: athrow
    //   359: astore_2
    //   360: aload_2
    //   361: invokevirtual 82	java/lang/reflect/InvocationTargetException:getCause	()Ljava/lang/Throwable;
    //   364: athrow
    //   365: astore_2
    //   366: aload_2
    //   367: invokevirtual 82	java/lang/reflect/InvocationTargetException:getCause	()Ljava/lang/Throwable;
    //   370: athrow
    //   371: astore_2
    //   372: aload_2
    //   373: invokevirtual 82	java/lang/reflect/InvocationTargetException:getCause	()Ljava/lang/Throwable;
    //   376: athrow
    //   377: astore_2
    //   378: aload_2
    //   379: invokevirtual 82	java/lang/reflect/InvocationTargetException:getCause	()Ljava/lang/Throwable;
    //   382: athrow
    //   383: astore_2
    //   384: aload_2
    //   385: invokevirtual 82	java/lang/reflect/InvocationTargetException:getCause	()Ljava/lang/Throwable;
    //   388: athrow
    // Local variable table:
    //   start	length	slot	name	signature
    //   0	389	0	this	hyyhhy
    //   48	236	1	i	int
    //   30	313	2	localObject	Object
    //   353	2	2	localInvocationTargetException1	java.lang.reflect.InvocationTargetException
    //   359	2	2	localInvocationTargetException2	java.lang.reflect.InvocationTargetException
    //   365	2	2	localInvocationTargetException3	java.lang.reflect.InvocationTargetException
    //   371	2	2	localInvocationTargetException4	java.lang.reflect.InvocationTargetException
    //   377	2	2	localInvocationTargetException5	java.lang.reflect.InvocationTargetException
    //   383	2	2	localInvocationTargetException6	java.lang.reflect.InvocationTargetException
    // Exception table:
    //   from	to	target	type
    //   141	151	353	java/lang/reflect/InvocationTargetException
    //   169	179	359	java/lang/reflect/InvocationTargetException
    //   31	41	365	java/lang/reflect/InvocationTargetException
    //   253	263	371	java/lang/reflect/InvocationTargetException
    //   103	113	377	java/lang/reflect/InvocationTargetException
    //   332	342	383	java/lang/reflect/InvocationTargetException
  }
  
  public abstract void bo006F006Fo006F006Foooo();
  
  /* Error */
  public void bo006Fo006F006F006Foooo(com.db.pwcc.dbmobile.model.error.DbError paramDbError)
  {
    // Byte code:
    //   0: aload_0
    //   1: invokevirtual 91	uuuuuu/hyyhhy:bkk006Bk006Bk006Bk006Bk	()Z
    //   4: ifeq +18 -> 22
    //   7: aload_0
    //   8: getfield 95	uuuuuu/hyyhhy:bnnnnn006E006E006En	Luuuuuu/ttssst$tsssst;
    //   11: checkcast 97	uuuuuu/yhhhyy$yyhhyy
    //   14: invokeinterface 170 1 0
    //   19: ifeq +4 -> 23
    //   22: return
    //   23: ldc 2
    //   25: ldc -84
    //   27: bipush 104
    //   29: iconst_5
    //   30: invokestatic 74	xxxxxx/uxxxxx:bb00620062bb0062b0062b0062	(Ljava/lang/String;CC)Ljava/lang/String;
    //   33: iconst_0
    //   34: anewarray 51	java/lang/Class
    //   37: invokevirtual 55	java/lang/Class:getMethod	(Ljava/lang/String;[Ljava/lang/Class;)Ljava/lang/reflect/Method;
    //   40: astore 6
    //   42: aload 6
    //   44: aconst_null
    //   45: iconst_0
    //   46: anewarray 57	java/lang/Object
    //   49: invokevirtual 63	java/lang/reflect/Method:invoke	(Ljava/lang/Object;[Ljava/lang/Object;)Ljava/lang/Object;
    //   52: astore 6
    //   54: aload 6
    //   56: checkcast 65	java/lang/Integer
    //   59: invokevirtual 68	java/lang/Integer:intValue	()I
    //   62: istore_2
    //   63: getstatic 37	uuuuuu/hyyhhy:b00700070pp0070pp0070p	I
    //   66: istore_3
    //   67: getstatic 35	uuuuuu/hyyhhy:b0070ppp0070pp0070p	I
    //   70: getstatic 37	uuuuuu/hyyhhy:b00700070pp0070pp0070p	I
    //   73: iadd
    //   74: getstatic 35	uuuuuu/hyyhhy:b0070ppp0070pp0070p	I
    //   77: imul
    //   78: getstatic 39	uuuuuu/hyyhhy:bpp0070p0070pp0070p	I
    //   81: irem
    //   82: getstatic 41	uuuuuu/hyyhhy:bp0070pp0070pp0070p	I
    //   85: if_icmpeq +51 -> 136
    //   88: bipush 60
    //   90: putstatic 35	uuuuuu/hyyhhy:b0070ppp0070pp0070p	I
    //   93: ldc 2
    //   95: ldc -82
    //   97: sipush 233
    //   100: iconst_0
    //   101: invokestatic 74	xxxxxx/uxxxxx:bb00620062bb0062b0062b0062	(Ljava/lang/String;CC)Ljava/lang/String;
    //   104: iconst_0
    //   105: anewarray 51	java/lang/Class
    //   108: invokevirtual 55	java/lang/Class:getMethod	(Ljava/lang/String;[Ljava/lang/Class;)Ljava/lang/reflect/Method;
    //   111: astore 6
    //   113: aload 6
    //   115: aconst_null
    //   116: iconst_0
    //   117: anewarray 57	java/lang/Object
    //   120: invokevirtual 63	java/lang/reflect/Method:invoke	(Ljava/lang/Object;[Ljava/lang/Object;)Ljava/lang/Object;
    //   123: astore 6
    //   125: aload 6
    //   127: checkcast 65	java/lang/Integer
    //   130: invokevirtual 68	java/lang/Integer:intValue	()I
    //   133: putstatic 41	uuuuuu/hyyhhy:bp0070pp0070pp0070p	I
    //   136: ldc 2
    //   138: ldc -128
    //   140: bipush 48
    //   142: sipush 223
    //   145: iconst_0
    //   146: invokestatic 49	xxxxxx/uxxxxx:bbbb0062b0062b0062b0062	(Ljava/lang/String;CCC)Ljava/lang/String;
    //   149: iconst_0
    //   150: anewarray 51	java/lang/Class
    //   153: invokevirtual 55	java/lang/Class:getMethod	(Ljava/lang/String;[Ljava/lang/Class;)Ljava/lang/reflect/Method;
    //   156: astore 6
    //   158: aload 6
    //   160: aconst_null
    //   161: iconst_0
    //   162: anewarray 57	java/lang/Object
    //   165: invokevirtual 63	java/lang/reflect/Method:invoke	(Ljava/lang/Object;[Ljava/lang/Object;)Ljava/lang/Object;
    //   168: astore 6
    //   170: aload 6
    //   172: checkcast 65	java/lang/Integer
    //   175: invokevirtual 68	java/lang/Integer:intValue	()I
    //   178: iload_2
    //   179: iload_3
    //   180: iadd
    //   181: imul
    //   182: getstatic 39	uuuuuu/hyyhhy:bpp0070p0070pp0070p	I
    //   185: irem
    //   186: getstatic 41	uuuuuu/hyyhhy:bp0070pp0070pp0070p	I
    //   189: if_icmpeq +51 -> 240
    //   192: bipush 43
    //   194: putstatic 35	uuuuuu/hyyhhy:b0070ppp0070pp0070p	I
    //   197: ldc 2
    //   199: ldc -80
    //   201: sipush 169
    //   204: iconst_5
    //   205: invokestatic 74	xxxxxx/uxxxxx:bb00620062bb0062b0062b0062	(Ljava/lang/String;CC)Ljava/lang/String;
    //   208: iconst_0
    //   209: anewarray 51	java/lang/Class
    //   212: invokevirtual 55	java/lang/Class:getMethod	(Ljava/lang/String;[Ljava/lang/Class;)Ljava/lang/reflect/Method;
    //   215: astore 6
    //   217: aload 6
    //   219: aconst_null
    //   220: iconst_0
    //   221: anewarray 57	java/lang/Object
    //   224: invokevirtual 63	java/lang/reflect/Method:invoke	(Ljava/lang/Object;[Ljava/lang/Object;)Ljava/lang/Object;
    //   227: astore 6
    //   229: aload 6
    //   231: checkcast 65	java/lang/Integer
    //   234: invokevirtual 68	java/lang/Integer:intValue	()I
    //   237: putstatic 41	uuuuuu/hyyhhy:bp0070pp0070pp0070p	I
    //   240: ldc -78
    //   242: ldc -76
    //   244: sipush 132
    //   247: bipush 117
    //   249: iconst_1
    //   250: invokestatic 49	xxxxxx/uxxxxx:bbbb0062b0062b0062b0062	(Ljava/lang/String;CCC)Ljava/lang/String;
    //   253: iconst_3
    //   254: anewarray 51	java/lang/Class
    //   257: dup
    //   258: iconst_0
    //   259: ldc -74
    //   261: aastore
    //   262: dup
    //   263: iconst_1
    //   264: getstatic 188	java/lang/Character:TYPE	Ljava/lang/Class;
    //   267: aastore
    //   268: dup
    //   269: iconst_2
    //   270: getstatic 188	java/lang/Character:TYPE	Ljava/lang/Class;
    //   273: aastore
    //   274: invokevirtual 55	java/lang/Class:getMethod	(Ljava/lang/String;[Ljava/lang/Class;)Ljava/lang/reflect/Method;
    //   277: astore 6
    //   279: aload 6
    //   281: aconst_null
    //   282: iconst_3
    //   283: anewarray 57	java/lang/Object
    //   286: dup
    //   287: iconst_0
    //   288: ldc -66
    //   290: aastore
    //   291: dup
    //   292: iconst_1
    //   293: bipush 14
    //   295: invokestatic 194	java/lang/Character:valueOf	(C)Ljava/lang/Character;
    //   298: aastore
    //   299: dup
    //   300: iconst_2
    //   301: iconst_5
    //   302: invokestatic 194	java/lang/Character:valueOf	(C)Ljava/lang/Character;
    //   305: aastore
    //   306: invokevirtual 63	java/lang/reflect/Method:invoke	(Ljava/lang/Object;[Ljava/lang/Object;)Ljava/lang/Object;
    //   309: astore 6
    //   311: aload 6
    //   313: checkcast 182	java/lang/String
    //   316: astore 6
    //   318: new 196	java/lang/StringBuilder
    //   321: dup
    //   322: invokespecial 197	java/lang/StringBuilder:<init>	()V
    //   325: astore 7
    //   327: ldc 2
    //   329: ldc -57
    //   331: bipush 41
    //   333: sipush 219
    //   336: iconst_2
    //   337: invokestatic 49	xxxxxx/uxxxxx:bbbb0062b0062b0062b0062	(Ljava/lang/String;CCC)Ljava/lang/String;
    //   340: iconst_0
    //   341: anewarray 51	java/lang/Class
    //   344: invokevirtual 55	java/lang/Class:getMethod	(Ljava/lang/String;[Ljava/lang/Class;)Ljava/lang/reflect/Method;
    //   347: astore 8
    //   349: aload 8
    //   351: aconst_null
    //   352: iconst_0
    //   353: anewarray 57	java/lang/Object
    //   356: invokevirtual 63	java/lang/reflect/Method:invoke	(Ljava/lang/Object;[Ljava/lang/Object;)Ljava/lang/Object;
    //   359: astore 8
    //   361: aload 8
    //   363: checkcast 65	java/lang/Integer
    //   366: invokevirtual 68	java/lang/Integer:intValue	()I
    //   369: istore_2
    //   370: getstatic 37	uuuuuu/hyyhhy:b00700070pp0070pp0070p	I
    //   373: istore_3
    //   374: ldc 2
    //   376: ldc -55
    //   378: bipush 64
    //   380: sipush 234
    //   383: iconst_2
    //   384: invokestatic 49	xxxxxx/uxxxxx:bbbb0062b0062b0062b0062	(Ljava/lang/String;CCC)Ljava/lang/String;
    //   387: iconst_0
    //   388: anewarray 51	java/lang/Class
    //   391: invokevirtual 55	java/lang/Class:getMethod	(Ljava/lang/String;[Ljava/lang/Class;)Ljava/lang/reflect/Method;
    //   394: astore 8
    //   396: aload 8
    //   398: aconst_null
    //   399: iconst_0
    //   400: anewarray 57	java/lang/Object
    //   403: invokevirtual 63	java/lang/reflect/Method:invoke	(Ljava/lang/Object;[Ljava/lang/Object;)Ljava/lang/Object;
    //   406: astore 8
    //   408: aload 8
    //   410: checkcast 65	java/lang/Integer
    //   413: invokevirtual 68	java/lang/Integer:intValue	()I
    //   416: istore 4
    //   418: getstatic 39	uuuuuu/hyyhhy:bpp0070p0070pp0070p	I
    //   421: istore 5
    //   423: ldc 2
    //   425: ldc -53
    //   427: bipush 73
    //   429: iconst_1
    //   430: invokestatic 74	xxxxxx/uxxxxx:bb00620062bb0062b0062b0062	(Ljava/lang/String;CC)Ljava/lang/String;
    //   433: iconst_0
    //   434: anewarray 51	java/lang/Class
    //   437: invokevirtual 55	java/lang/Class:getMethod	(Ljava/lang/String;[Ljava/lang/Class;)Ljava/lang/reflect/Method;
    //   440: astore 8
    //   442: aload 8
    //   444: aconst_null
    //   445: iconst_0
    //   446: anewarray 57	java/lang/Object
    //   449: invokevirtual 63	java/lang/reflect/Method:invoke	(Ljava/lang/Object;[Ljava/lang/Object;)Ljava/lang/Object;
    //   452: astore 8
    //   454: iload 4
    //   456: iload_3
    //   457: iload_2
    //   458: iadd
    //   459: imul
    //   460: iload 5
    //   462: irem
    //   463: aload 8
    //   465: checkcast 65	java/lang/Integer
    //   468: invokevirtual 68	java/lang/Integer:intValue	()I
    //   471: if_icmpeq +51 -> 522
    //   474: ldc 2
    //   476: ldc -51
    //   478: sipush 159
    //   481: iconst_3
    //   482: invokestatic 74	xxxxxx/uxxxxx:bb00620062bb0062b0062b0062	(Ljava/lang/String;CC)Ljava/lang/String;
    //   485: iconst_0
    //   486: anewarray 51	java/lang/Class
    //   489: invokevirtual 55	java/lang/Class:getMethod	(Ljava/lang/String;[Ljava/lang/Class;)Ljava/lang/reflect/Method;
    //   492: astore 8
    //   494: aload 8
    //   496: aconst_null
    //   497: iconst_0
    //   498: anewarray 57	java/lang/Object
    //   501: invokevirtual 63	java/lang/reflect/Method:invoke	(Ljava/lang/Object;[Ljava/lang/Object;)Ljava/lang/Object;
    //   504: astore 8
    //   506: aload 8
    //   508: checkcast 65	java/lang/Integer
    //   511: invokevirtual 68	java/lang/Integer:intValue	()I
    //   514: putstatic 35	uuuuuu/hyyhhy:b0070ppp0070pp0070p	I
    //   517: bipush 83
    //   519: putstatic 41	uuuuuu/hyyhhy:bp0070pp0070pp0070p	I
    //   522: getstatic 35	uuuuuu/hyyhhy:b0070ppp0070pp0070p	I
    //   525: istore_2
    //   526: iload_2
    //   527: getstatic 37	uuuuuu/hyyhhy:b00700070pp0070pp0070p	I
    //   530: iload_2
    //   531: iadd
    //   532: imul
    //   533: getstatic 39	uuuuuu/hyyhhy:bpp0070p0070pp0070p	I
    //   536: irem
    //   537: tableswitch	default:+19->556, 0:+29->566
    //   556: bipush 9
    //   558: putstatic 35	uuuuuu/hyyhhy:b0070ppp0070pp0070p	I
    //   561: bipush 23
    //   563: putstatic 41	uuuuuu/hyyhhy:bp0070pp0070pp0070p	I
    //   566: ldc -78
    //   568: ldc -49
    //   570: bipush 66
    //   572: iconst_3
    //   573: invokestatic 74	xxxxxx/uxxxxx:bb00620062bb0062b0062b0062	(Ljava/lang/String;CC)Ljava/lang/String;
    //   576: iconst_3
    //   577: anewarray 51	java/lang/Class
    //   580: dup
    //   581: iconst_0
    //   582: ldc -74
    //   584: aastore
    //   585: dup
    //   586: iconst_1
    //   587: getstatic 188	java/lang/Character:TYPE	Ljava/lang/Class;
    //   590: aastore
    //   591: dup
    //   592: iconst_2
    //   593: getstatic 188	java/lang/Character:TYPE	Ljava/lang/Class;
    //   596: aastore
    //   597: invokevirtual 55	java/lang/Class:getMethod	(Ljava/lang/String;[Ljava/lang/Class;)Ljava/lang/reflect/Method;
    //   600: astore 8
    //   602: aload 8
    //   604: aconst_null
    //   605: iconst_3
    //   606: anewarray 57	java/lang/Object
    //   609: dup
    //   610: iconst_0
    //   611: ldc -47
    //   613: aastore
    //   614: dup
    //   615: iconst_1
    //   616: sipush 239
    //   619: invokestatic 194	java/lang/Character:valueOf	(C)Ljava/lang/Character;
    //   622: aastore
    //   623: dup
    //   624: iconst_2
    //   625: iconst_3
    //   626: invokestatic 194	java/lang/Character:valueOf	(C)Ljava/lang/Character;
    //   629: aastore
    //   630: invokevirtual 63	java/lang/reflect/Method:invoke	(Ljava/lang/Object;[Ljava/lang/Object;)Ljava/lang/Object;
    //   633: astore 8
    //   635: aload 6
    //   637: aload 7
    //   639: aload 8
    //   641: checkcast 182	java/lang/String
    //   644: invokevirtual 213	java/lang/StringBuilder:append	(Ljava/lang/String;)Ljava/lang/StringBuilder;
    //   647: aload_1
    //   648: invokevirtual 218	com/db/pwcc/dbmobile/model/error/DbError:toString	()Ljava/lang/String;
    //   651: invokevirtual 213	java/lang/StringBuilder:append	(Ljava/lang/String;)Ljava/lang/StringBuilder;
    //   654: invokevirtual 219	java/lang/StringBuilder:toString	()Ljava/lang/String;
    //   657: invokestatic 225	uuuuuu/rvvvrv:bqq0071q00710071q0071q0071	(Ljava/lang/String;Ljava/lang/String;)V
    //   660: aload_0
    //   661: getfield 95	uuuuuu/hyyhhy:bnnnnn006E006E006En	Luuuuuu/ttssst$tsssst;
    //   664: checkcast 97	uuuuuu/yhhhyy$yyhhyy
    //   667: invokeinterface 228 1 0
    //   672: getstatic 234	com/db/pwcc/dbmobile/model/error/DbErrorCode:NO_INTERNET_ERROR	Lcom/db/pwcc/dbmobile/model/error/DbErrorCode;
    //   675: aload_1
    //   676: invokevirtual 238	com/db/pwcc/dbmobile/model/error/DbError:getDbCode	()Lcom/db/pwcc/dbmobile/model/error/DbErrorCode;
    //   679: if_acmpne +19 -> 698
    //   682: aload_0
    //   683: getfield 95	uuuuuu/hyyhhy:bnnnnn006E006E006En	Luuuuuu/ttssst$tsssst;
    //   686: checkcast 97	uuuuuu/yhhhyy$yyhhyy
    //   689: getstatic 243	com/db/pwcc/dbmobile/financial_overview/R$string:check_internet_connection	I
    //   692: invokeinterface 247 2 0
    //   697: return
    //   698: aload_0
    //   699: getfield 95	uuuuuu/hyyhhy:bnnnnn006E006E006En	Luuuuuu/ttssst$tsssst;
    //   702: checkcast 97	uuuuuu/yhhhyy$yyhhyy
    //   705: getstatic 250	com/db/pwcc/dbmobile/financial_overview/R$string:technical_error_retry	I
    //   708: invokeinterface 247 2 0
    //   713: return
    //   714: astore_1
    //   715: aload_1
    //   716: invokevirtual 82	java/lang/reflect/InvocationTargetException:getCause	()Ljava/lang/Throwable;
    //   719: athrow
    //   720: astore_1
    //   721: aload_1
    //   722: invokevirtual 82	java/lang/reflect/InvocationTargetException:getCause	()Ljava/lang/Throwable;
    //   725: athrow
    //   726: astore_1
    //   727: aload_1
    //   728: invokevirtual 82	java/lang/reflect/InvocationTargetException:getCause	()Ljava/lang/Throwable;
    //   731: athrow
    //   732: astore_1
    //   733: aload_1
    //   734: invokevirtual 82	java/lang/reflect/InvocationTargetException:getCause	()Ljava/lang/Throwable;
    //   737: athrow
    //   738: astore_1
    //   739: aload_1
    //   740: invokevirtual 82	java/lang/reflect/InvocationTargetException:getCause	()Ljava/lang/Throwable;
    //   743: athrow
    //   744: astore_1
    //   745: aload_1
    //   746: invokevirtual 82	java/lang/reflect/InvocationTargetException:getCause	()Ljava/lang/Throwable;
    //   749: athrow
    //   750: astore_1
    //   751: aload_1
    //   752: invokevirtual 82	java/lang/reflect/InvocationTargetException:getCause	()Ljava/lang/Throwable;
    //   755: athrow
    //   756: astore_1
    //   757: aload_1
    //   758: invokevirtual 82	java/lang/reflect/InvocationTargetException:getCause	()Ljava/lang/Throwable;
    //   761: athrow
    //   762: astore_1
    //   763: aload_1
    //   764: invokevirtual 82	java/lang/reflect/InvocationTargetException:getCause	()Ljava/lang/Throwable;
    //   767: athrow
    //   768: astore_1
    //   769: aload_1
    //   770: invokevirtual 82	java/lang/reflect/InvocationTargetException:getCause	()Ljava/lang/Throwable;
    //   773: athrow
    // Local variable table:
    //   start	length	slot	name	signature
    //   0	774	0	this	hyyhhy
    //   0	774	1	paramDbError	com.db.pwcc.dbmobile.model.error.DbError
    //   62	471	2	i	int
    //   66	393	3	j	int
    //   416	44	4	k	int
    //   421	42	5	m	int
    //   40	596	6	localObject1	Object
    //   325	313	7	localStringBuilder	StringBuilder
    //   347	293	8	localObject2	Object
    // Exception table:
    //   from	to	target	type
    //   442	454	714	java/lang/reflect/InvocationTargetException
    //   349	361	720	java/lang/reflect/InvocationTargetException
    //   396	408	726	java/lang/reflect/InvocationTargetException
    //   217	229	732	java/lang/reflect/InvocationTargetException
    //   602	635	738	java/lang/reflect/InvocationTargetException
    //   494	506	744	java/lang/reflect/InvocationTargetException
    //   158	170	750	java/lang/reflect/InvocationTargetException
    //   42	54	756	java/lang/reflect/InvocationTargetException
    //   279	311	762	java/lang/reflect/InvocationTargetException
    //   113	125	768	java/lang/reflect/InvocationTargetException
  }
  
  /* Error */
  public void boo006F006F006F006Foooo(String paramString)
  {
    // Byte code:
    //   0: getstatic 35	uuuuuu/hyyhhy:b0070ppp0070pp0070p	I
    //   3: getstatic 37	uuuuuu/hyyhhy:b00700070pp0070pp0070p	I
    //   6: iadd
    //   7: getstatic 35	uuuuuu/hyyhhy:b0070ppp0070pp0070p	I
    //   10: imul
    //   11: getstatic 39	uuuuuu/hyyhhy:bpp0070p0070pp0070p	I
    //   14: irem
    //   15: getstatic 41	uuuuuu/hyyhhy:bp0070pp0070pp0070p	I
    //   18: if_icmpeq +205 -> 223
    //   21: bipush 69
    //   23: putstatic 35	uuuuuu/hyyhhy:b0070ppp0070pp0070p	I
    //   26: ldc 2
    //   28: ldc -3
    //   30: sipush 135
    //   33: iconst_2
    //   34: invokestatic 74	xxxxxx/uxxxxx:bb00620062bb0062b0062b0062	(Ljava/lang/String;CC)Ljava/lang/String;
    //   37: iconst_0
    //   38: anewarray 51	java/lang/Class
    //   41: invokevirtual 55	java/lang/Class:getMethod	(Ljava/lang/String;[Ljava/lang/Class;)Ljava/lang/reflect/Method;
    //   44: astore 6
    //   46: aload 6
    //   48: aconst_null
    //   49: iconst_0
    //   50: anewarray 57	java/lang/Object
    //   53: invokevirtual 63	java/lang/reflect/Method:invoke	(Ljava/lang/Object;[Ljava/lang/Object;)Ljava/lang/Object;
    //   56: astore 6
    //   58: aload 6
    //   60: checkcast 65	java/lang/Integer
    //   63: invokevirtual 68	java/lang/Integer:intValue	()I
    //   66: putstatic 41	uuuuuu/hyyhhy:bp0070pp0070pp0070p	I
    //   69: getstatic 35	uuuuuu/hyyhhy:b0070ppp0070pp0070p	I
    //   72: istore_2
    //   73: getstatic 37	uuuuuu/hyyhhy:b00700070pp0070pp0070p	I
    //   76: istore_3
    //   77: getstatic 35	uuuuuu/hyyhhy:b0070ppp0070pp0070p	I
    //   80: istore 4
    //   82: getstatic 39	uuuuuu/hyyhhy:bpp0070p0070pp0070p	I
    //   85: istore 5
    //   87: getstatic 35	uuuuuu/hyyhhy:b0070ppp0070pp0070p	I
    //   90: getstatic 37	uuuuuu/hyyhhy:b00700070pp0070pp0070p	I
    //   93: iadd
    //   94: getstatic 35	uuuuuu/hyyhhy:b0070ppp0070pp0070p	I
    //   97: imul
    //   98: getstatic 39	uuuuuu/hyyhhy:bpp0070p0070pp0070p	I
    //   101: irem
    //   102: getstatic 41	uuuuuu/hyyhhy:bp0070pp0070pp0070p	I
    //   105: if_icmpeq +13 -> 118
    //   108: bipush 61
    //   110: putstatic 35	uuuuuu/hyyhhy:b0070ppp0070pp0070p	I
    //   113: bipush 61
    //   115: putstatic 41	uuuuuu/hyyhhy:bp0070pp0070pp0070p	I
    //   118: iload_2
    //   119: iload_3
    //   120: iadd
    //   121: iload 4
    //   123: imul
    //   124: iload 5
    //   126: irem
    //   127: getstatic 41	uuuuuu/hyyhhy:bp0070pp0070pp0070p	I
    //   130: if_icmpeq +93 -> 223
    //   133: bipush 51
    //   135: putstatic 35	uuuuuu/hyyhhy:b0070ppp0070pp0070p	I
    //   138: bipush 76
    //   140: putstatic 41	uuuuuu/hyyhhy:bp0070pp0070pp0070p	I
    //   143: getstatic 35	uuuuuu/hyyhhy:b0070ppp0070pp0070p	I
    //   146: istore_2
    //   147: iload_2
    //   148: getstatic 37	uuuuuu/hyyhhy:b00700070pp0070pp0070p	I
    //   151: iload_2
    //   152: iadd
    //   153: imul
    //   154: getstatic 39	uuuuuu/hyyhhy:bpp0070p0070pp0070p	I
    //   157: irem
    //   158: tableswitch	default:+18->176, 0:+65->223
    //   176: bipush 37
    //   178: putstatic 35	uuuuuu/hyyhhy:b0070ppp0070pp0070p	I
    //   181: ldc 2
    //   183: ldc -1
    //   185: bipush 20
    //   187: iconst_2
    //   188: invokestatic 74	xxxxxx/uxxxxx:bb00620062bb0062b0062b0062	(Ljava/lang/String;CC)Ljava/lang/String;
    //   191: iconst_0
    //   192: anewarray 51	java/lang/Class
    //   195: invokevirtual 55	java/lang/Class:getMethod	(Ljava/lang/String;[Ljava/lang/Class;)Ljava/lang/reflect/Method;
    //   198: astore 6
    //   200: aload 6
    //   202: aconst_null
    //   203: iconst_0
    //   204: anewarray 57	java/lang/Object
    //   207: invokevirtual 63	java/lang/reflect/Method:invoke	(Ljava/lang/Object;[Ljava/lang/Object;)Ljava/lang/Object;
    //   210: astore 6
    //   212: aload 6
    //   214: checkcast 65	java/lang/Integer
    //   217: invokevirtual 68	java/lang/Integer:intValue	()I
    //   220: putstatic 41	uuuuuu/hyyhhy:bp0070pp0070pp0070p	I
    //   223: aload_0
    //   224: aload_1
    //   225: putfield 33	uuuuuu/hyyhhy:bpppp0070pp0070p	Ljava/lang/String;
    //   228: return
    //   229: astore_1
    //   230: aload_1
    //   231: invokevirtual 82	java/lang/reflect/InvocationTargetException:getCause	()Ljava/lang/Throwable;
    //   234: athrow
    //   235: astore_1
    //   236: aload_1
    //   237: invokevirtual 82	java/lang/reflect/InvocationTargetException:getCause	()Ljava/lang/Throwable;
    //   240: athrow
    // Local variable table:
    //   start	length	slot	name	signature
    //   0	241	0	this	hyyhhy
    //   0	241	1	paramString	String
    //   72	82	2	i	int
    //   76	45	3	j	int
    //   80	44	4	k	int
    //   85	42	5	m	int
    //   44	169	6	localObject	Object
    // Exception table:
    //   from	to	target	type
    //   46	58	229	java/lang/reflect/InvocationTargetException
    //   200	212	235	java/lang/reflect/InvocationTargetException
  }
  
  public abstract boolean booo006F006F006Foooo(T paramT);
}
