package uuuuuu;

public enum kkkvkk
{
  /* Error */
  static
  {
    // Byte code:
    //   0: ldc 19
    //   2: ldc 21
    //   4: sipush 204
    //   7: sipush 170
    //   10: iconst_2
    //   11: invokestatic 27	xxxxxx/uxxxxx:bbbb0062b0062b0062b0062	(Ljava/lang/String;CCC)Ljava/lang/String;
    //   14: iconst_3
    //   15: anewarray 29	java/lang/Class
    //   18: dup
    //   19: iconst_0
    //   20: ldc 31
    //   22: aastore
    //   23: dup
    //   24: iconst_1
    //   25: getstatic 37	java/lang/Character:TYPE	Ljava/lang/Class;
    //   28: aastore
    //   29: dup
    //   30: iconst_2
    //   31: getstatic 37	java/lang/Character:TYPE	Ljava/lang/Class;
    //   34: aastore
    //   35: invokevirtual 41	java/lang/Class:getMethod	(Ljava/lang/String;[Ljava/lang/Class;)Ljava/lang/reflect/Method;
    //   38: astore_1
    //   39: aload_1
    //   40: aconst_null
    //   41: iconst_3
    //   42: anewarray 43	java/lang/Object
    //   45: dup
    //   46: iconst_0
    //   47: ldc 45
    //   49: aastore
    //   50: dup
    //   51: iconst_1
    //   52: bipush 73
    //   54: invokestatic 49	java/lang/Character:valueOf	(C)Ljava/lang/Character;
    //   57: aastore
    //   58: dup
    //   59: iconst_2
    //   60: iconst_3
    //   61: invokestatic 49	java/lang/Character:valueOf	(C)Ljava/lang/Character;
    //   64: aastore
    //   65: invokevirtual 55	java/lang/reflect/Method:invoke	(Ljava/lang/Object;[Ljava/lang/Object;)Ljava/lang/Object;
    //   68: astore_1
    //   69: new 2	uuuuuu/kkkvkk
    //   72: dup
    //   73: aload_1
    //   74: checkcast 31	java/lang/String
    //   77: iconst_0
    //   78: invokespecial 59	uuuuuu/kkkvkk:<init>	(Ljava/lang/String;I)V
    //   81: putstatic 61	uuuuuu/kkkvkk:bcc00630063ccc0063c	Luuuuuu/kkkvkk;
    //   84: ldc 19
    //   86: ldc 63
    //   88: bipush 93
    //   90: bipush 99
    //   92: iconst_1
    //   93: invokestatic 27	xxxxxx/uxxxxx:bbbb0062b0062b0062b0062	(Ljava/lang/String;CCC)Ljava/lang/String;
    //   96: iconst_3
    //   97: anewarray 29	java/lang/Class
    //   100: dup
    //   101: iconst_0
    //   102: ldc 31
    //   104: aastore
    //   105: dup
    //   106: iconst_1
    //   107: getstatic 37	java/lang/Character:TYPE	Ljava/lang/Class;
    //   110: aastore
    //   111: dup
    //   112: iconst_2
    //   113: getstatic 37	java/lang/Character:TYPE	Ljava/lang/Class;
    //   116: aastore
    //   117: invokevirtual 41	java/lang/Class:getMethod	(Ljava/lang/String;[Ljava/lang/Class;)Ljava/lang/reflect/Method;
    //   120: astore_1
    //   121: aload_1
    //   122: aconst_null
    //   123: iconst_3
    //   124: anewarray 43	java/lang/Object
    //   127: dup
    //   128: iconst_0
    //   129: ldc 65
    //   131: aastore
    //   132: dup
    //   133: iconst_1
    //   134: bipush 29
    //   136: invokestatic 49	java/lang/Character:valueOf	(C)Ljava/lang/Character;
    //   139: aastore
    //   140: dup
    //   141: iconst_2
    //   142: iconst_3
    //   143: invokestatic 49	java/lang/Character:valueOf	(C)Ljava/lang/Character;
    //   146: aastore
    //   147: invokevirtual 55	java/lang/reflect/Method:invoke	(Ljava/lang/Object;[Ljava/lang/Object;)Ljava/lang/Object;
    //   150: astore_1
    //   151: aload_1
    //   152: checkcast 31	java/lang/String
    //   155: astore_1
    //   156: invokestatic 69	uuuuuu/kkkvkk:bqqq0071q0071q0071qq	()I
    //   159: invokestatic 72	uuuuuu/kkkvkk:b007100710071qq0071q0071qq	()I
    //   162: iadd
    //   163: invokestatic 69	uuuuuu/kkkvkk:bqqq0071q0071q0071qq	()I
    //   166: imul
    //   167: invokestatic 75	uuuuuu/kkkvkk:b0071q0071qq0071q0071qq	()I
    //   170: irem
    //   171: invokestatic 78	uuuuuu/kkkvkk:bq00710071qq0071q0071qq	()I
    //   174: if_icmpeq +3 -> 177
    //   177: new 2	uuuuuu/kkkvkk
    //   180: dup
    //   181: aload_1
    //   182: iconst_1
    //   183: invokespecial 59	uuuuuu/kkkvkk:<init>	(Ljava/lang/String;I)V
    //   186: putstatic 80	uuuuuu/kkkvkk:b0063006300630063ccc0063c	Luuuuuu/kkkvkk;
    //   189: ldc 19
    //   191: ldc 82
    //   193: bipush 45
    //   195: sipush 219
    //   198: iconst_3
    //   199: invokestatic 27	xxxxxx/uxxxxx:bbbb0062b0062b0062b0062	(Ljava/lang/String;CCC)Ljava/lang/String;
    //   202: iconst_4
    //   203: anewarray 29	java/lang/Class
    //   206: dup
    //   207: iconst_0
    //   208: ldc 31
    //   210: aastore
    //   211: dup
    //   212: iconst_1
    //   213: getstatic 37	java/lang/Character:TYPE	Ljava/lang/Class;
    //   216: aastore
    //   217: dup
    //   218: iconst_2
    //   219: getstatic 37	java/lang/Character:TYPE	Ljava/lang/Class;
    //   222: aastore
    //   223: dup
    //   224: iconst_3
    //   225: getstatic 37	java/lang/Character:TYPE	Ljava/lang/Class;
    //   228: aastore
    //   229: invokevirtual 41	java/lang/Class:getMethod	(Ljava/lang/String;[Ljava/lang/Class;)Ljava/lang/reflect/Method;
    //   232: astore_1
    //   233: aload_1
    //   234: aconst_null
    //   235: iconst_4
    //   236: anewarray 43	java/lang/Object
    //   239: dup
    //   240: iconst_0
    //   241: ldc 84
    //   243: aastore
    //   244: dup
    //   245: iconst_1
    //   246: sipush 163
    //   249: invokestatic 49	java/lang/Character:valueOf	(C)Ljava/lang/Character;
    //   252: aastore
    //   253: dup
    //   254: iconst_2
    //   255: sipush 193
    //   258: invokestatic 49	java/lang/Character:valueOf	(C)Ljava/lang/Character;
    //   261: aastore
    //   262: dup
    //   263: iconst_3
    //   264: iconst_1
    //   265: invokestatic 49	java/lang/Character:valueOf	(C)Ljava/lang/Character;
    //   268: aastore
    //   269: invokevirtual 55	java/lang/reflect/Method:invoke	(Ljava/lang/Object;[Ljava/lang/Object;)Ljava/lang/Object;
    //   272: astore_1
    //   273: new 2	uuuuuu/kkkvkk
    //   276: dup
    //   277: aload_1
    //   278: checkcast 31	java/lang/String
    //   281: iconst_2
    //   282: invokespecial 59	uuuuuu/kkkvkk:<init>	(Ljava/lang/String;I)V
    //   285: putstatic 86	uuuuuu/kkkvkk:b00630063c0063ccc0063c	Luuuuuu/kkkvkk;
    //   288: ldc 19
    //   290: ldc 88
    //   292: bipush 122
    //   294: iconst_5
    //   295: invokestatic 92	xxxxxx/uxxxxx:bb00620062bb0062b0062b0062	(Ljava/lang/String;CC)Ljava/lang/String;
    //   298: iconst_4
    //   299: anewarray 29	java/lang/Class
    //   302: dup
    //   303: iconst_0
    //   304: ldc 31
    //   306: aastore
    //   307: dup
    //   308: iconst_1
    //   309: getstatic 37	java/lang/Character:TYPE	Ljava/lang/Class;
    //   312: aastore
    //   313: dup
    //   314: iconst_2
    //   315: getstatic 37	java/lang/Character:TYPE	Ljava/lang/Class;
    //   318: aastore
    //   319: dup
    //   320: iconst_3
    //   321: getstatic 37	java/lang/Character:TYPE	Ljava/lang/Class;
    //   324: aastore
    //   325: invokevirtual 41	java/lang/Class:getMethod	(Ljava/lang/String;[Ljava/lang/Class;)Ljava/lang/reflect/Method;
    //   328: astore_1
    //   329: aload_1
    //   330: aconst_null
    //   331: iconst_4
    //   332: anewarray 43	java/lang/Object
    //   335: dup
    //   336: iconst_0
    //   337: ldc 94
    //   339: aastore
    //   340: dup
    //   341: iconst_1
    //   342: sipush 254
    //   345: invokestatic 49	java/lang/Character:valueOf	(C)Ljava/lang/Character;
    //   348: aastore
    //   349: dup
    //   350: iconst_2
    //   351: bipush 21
    //   353: invokestatic 49	java/lang/Character:valueOf	(C)Ljava/lang/Character;
    //   356: aastore
    //   357: dup
    //   358: iconst_3
    //   359: iconst_1
    //   360: invokestatic 49	java/lang/Character:valueOf	(C)Ljava/lang/Character;
    //   363: aastore
    //   364: invokevirtual 55	java/lang/reflect/Method:invoke	(Ljava/lang/Object;[Ljava/lang/Object;)Ljava/lang/Object;
    //   367: astore_1
    //   368: new 2	uuuuuu/kkkvkk
    //   371: dup
    //   372: aload_1
    //   373: checkcast 31	java/lang/String
    //   376: iconst_3
    //   377: invokespecial 59	uuuuuu/kkkvkk:<init>	(Ljava/lang/String;I)V
    //   380: putstatic 96	uuuuuu/kkkvkk:bc006300630063ccc0063c	Luuuuuu/kkkvkk;
    //   383: ldc 19
    //   385: ldc 98
    //   387: iconst_2
    //   388: bipush 48
    //   390: iconst_0
    //   391: invokestatic 27	xxxxxx/uxxxxx:bbbb0062b0062b0062b0062	(Ljava/lang/String;CCC)Ljava/lang/String;
    //   394: iconst_3
    //   395: anewarray 29	java/lang/Class
    //   398: dup
    //   399: iconst_0
    //   400: ldc 31
    //   402: aastore
    //   403: dup
    //   404: iconst_1
    //   405: getstatic 37	java/lang/Character:TYPE	Ljava/lang/Class;
    //   408: aastore
    //   409: dup
    //   410: iconst_2
    //   411: getstatic 37	java/lang/Character:TYPE	Ljava/lang/Class;
    //   414: aastore
    //   415: invokevirtual 41	java/lang/Class:getMethod	(Ljava/lang/String;[Ljava/lang/Class;)Ljava/lang/reflect/Method;
    //   418: astore_1
    //   419: aload_1
    //   420: aconst_null
    //   421: iconst_3
    //   422: anewarray 43	java/lang/Object
    //   425: dup
    //   426: iconst_0
    //   427: ldc 100
    //   429: aastore
    //   430: dup
    //   431: iconst_1
    //   432: sipush 211
    //   435: invokestatic 49	java/lang/Character:valueOf	(C)Ljava/lang/Character;
    //   438: aastore
    //   439: dup
    //   440: iconst_2
    //   441: iconst_0
    //   442: invokestatic 49	java/lang/Character:valueOf	(C)Ljava/lang/Character;
    //   445: aastore
    //   446: invokevirtual 55	java/lang/reflect/Method:invoke	(Ljava/lang/Object;[Ljava/lang/Object;)Ljava/lang/Object;
    //   449: astore_1
    //   450: new 2	uuuuuu/kkkvkk
    //   453: dup
    //   454: aload_1
    //   455: checkcast 31	java/lang/String
    //   458: iconst_4
    //   459: invokespecial 59	uuuuuu/kkkvkk:<init>	(Ljava/lang/String;I)V
    //   462: putstatic 102	uuuuuu/kkkvkk:b0063c00630063ccc0063c	Luuuuuu/kkkvkk;
    //   465: getstatic 61	uuuuuu/kkkvkk:bcc00630063ccc0063c	Luuuuuu/kkkvkk;
    //   468: astore_1
    //   469: getstatic 80	uuuuuu/kkkvkk:b0063006300630063ccc0063c	Luuuuuu/kkkvkk;
    //   472: astore_2
    //   473: getstatic 86	uuuuuu/kkkvkk:b00630063c0063ccc0063c	Luuuuuu/kkkvkk;
    //   476: astore_3
    //   477: getstatic 96	uuuuuu/kkkvkk:bc006300630063ccc0063c	Luuuuuu/kkkvkk;
    //   480: astore 4
    //   482: invokestatic 69	uuuuuu/kkkvkk:bqqq0071q0071q0071qq	()I
    //   485: istore_0
    //   486: iload_0
    //   487: invokestatic 72	uuuuuu/kkkvkk:b007100710071qq0071q0071qq	()I
    //   490: iload_0
    //   491: iadd
    //   492: imul
    //   493: invokestatic 75	uuuuuu/kkkvkk:b0071q0071qq0071q0071qq	()I
    //   496: irem
    //   497: tableswitch	default:+19->516, 0:+19->516
    //   516: iconst_5
    //   517: anewarray 2	uuuuuu/kkkvkk
    //   520: dup
    //   521: iconst_0
    //   522: aload_1
    //   523: aastore
    //   524: dup
    //   525: iconst_1
    //   526: aload_2
    //   527: aastore
    //   528: dup
    //   529: iconst_2
    //   530: aload_3
    //   531: aastore
    //   532: dup
    //   533: iconst_3
    //   534: aload 4
    //   536: aastore
    //   537: dup
    //   538: iconst_4
    //   539: getstatic 102	uuuuuu/kkkvkk:b0063c00630063ccc0063c	Luuuuuu/kkkvkk;
    //   542: aastore
    //   543: putstatic 104	uuuuuu/kkkvkk:bc0063c0063ccc0063c	[Luuuuuu/kkkvkk;
    //   546: return
    //   547: astore_1
    //   548: aload_1
    //   549: invokevirtual 108	java/lang/reflect/InvocationTargetException:getCause	()Ljava/lang/Throwable;
    //   552: athrow
    //   553: astore_1
    //   554: aload_1
    //   555: invokevirtual 108	java/lang/reflect/InvocationTargetException:getCause	()Ljava/lang/Throwable;
    //   558: athrow
    //   559: astore_1
    //   560: aload_1
    //   561: invokevirtual 108	java/lang/reflect/InvocationTargetException:getCause	()Ljava/lang/Throwable;
    //   564: athrow
    //   565: astore_1
    //   566: aload_1
    //   567: invokevirtual 108	java/lang/reflect/InvocationTargetException:getCause	()Ljava/lang/Throwable;
    //   570: athrow
    //   571: astore_1
    //   572: aload_1
    //   573: invokevirtual 108	java/lang/reflect/InvocationTargetException:getCause	()Ljava/lang/Throwable;
    //   576: athrow
    // Local variable table:
    //   start	length	slot	name	signature
    //   485	8	0	i	int
    //   38	485	1	localObject	Object
    //   547	2	1	localInvocationTargetException1	java.lang.reflect.InvocationTargetException
    //   553	2	1	localInvocationTargetException2	java.lang.reflect.InvocationTargetException
    //   559	2	1	localInvocationTargetException3	java.lang.reflect.InvocationTargetException
    //   565	2	1	localInvocationTargetException4	java.lang.reflect.InvocationTargetException
    //   571	2	1	localInvocationTargetException5	java.lang.reflect.InvocationTargetException
    //   472	55	2	localKkkvkk1	kkkvkk
    //   476	55	3	localKkkvkk2	kkkvkk
    //   480	55	4	localKkkvkk3	kkkvkk
    // Exception table:
    //   from	to	target	type
    //   39	69	547	java/lang/reflect/InvocationTargetException
    //   329	368	553	java/lang/reflect/InvocationTargetException
    //   121	151	559	java/lang/reflect/InvocationTargetException
    //   233	273	565	java/lang/reflect/InvocationTargetException
    //   419	450	571	java/lang/reflect/InvocationTargetException
  }
  
  private kkkvkk() {}
  
  public static int b007100710071qq0071q0071qq()
  {
    return 1;
  }
  
  public static int b0071q0071qq0071q0071qq()
  {
    return 2;
  }
  
  public static kkkvkk b0071qq0071q0071q0071qq(String paramString)
  {
    paramString = Enum.valueOf(kkkvkk.class, paramString);
    int i = bqqq0071q0071q0071qq();
    switch (i * (b007100710071qq0071q0071qq() + i) % b0071q0071qq0071q0071qq())
    {
    default: 
      i = bqqq0071q0071q0071qq();
      switch (i * (b007100710071qq0071q0071qq() + i) % b0071q0071qq0071q0071qq())
      {
      }
      break;
    }
    return (kkkvkk)paramString;
  }
  
  public static int bq00710071qq0071q0071qq()
  {
    return 0;
  }
  
  public static int bqqq0071q0071q0071qq()
  {
    return 94;
  }
}
