package uuuuuu;

public enum kvkvvv
{
  private final int bfff00660066f006600660066;
  
  /* Error */
  static
  {
    // Byte code:
    //   0: ldc 21
    //   2: ldc 23
    //   4: sipush 199
    //   7: iconst_3
    //   8: invokestatic 29	xxxxxx/uxxxxx:bb00620062bb0062b0062b0062	(Ljava/lang/String;CC)Ljava/lang/String;
    //   11: iconst_3
    //   12: anewarray 31	java/lang/Class
    //   15: dup
    //   16: iconst_0
    //   17: ldc 33
    //   19: aastore
    //   20: dup
    //   21: iconst_1
    //   22: getstatic 39	java/lang/Character:TYPE	Ljava/lang/Class;
    //   25: aastore
    //   26: dup
    //   27: iconst_2
    //   28: getstatic 39	java/lang/Character:TYPE	Ljava/lang/Class;
    //   31: aastore
    //   32: invokevirtual 43	java/lang/Class:getMethod	(Ljava/lang/String;[Ljava/lang/Class;)Ljava/lang/reflect/Method;
    //   35: astore_1
    //   36: aload_1
    //   37: aconst_null
    //   38: iconst_3
    //   39: anewarray 45	java/lang/Object
    //   42: dup
    //   43: iconst_0
    //   44: ldc 47
    //   46: aastore
    //   47: dup
    //   48: iconst_1
    //   49: bipush 114
    //   51: invokestatic 51	java/lang/Character:valueOf	(C)Ljava/lang/Character;
    //   54: aastore
    //   55: dup
    //   56: iconst_2
    //   57: iconst_4
    //   58: invokestatic 51	java/lang/Character:valueOf	(C)Ljava/lang/Character;
    //   61: aastore
    //   62: invokevirtual 57	java/lang/reflect/Method:invoke	(Ljava/lang/Object;[Ljava/lang/Object;)Ljava/lang/Object;
    //   65: astore_1
    //   66: new 2	uuuuuu/kvkvvv
    //   69: dup
    //   70: aload_1
    //   71: checkcast 33	java/lang/String
    //   74: iconst_0
    //   75: iconst_0
    //   76: invokespecial 61	uuuuuu/kvkvvv:<init>	(Ljava/lang/String;II)V
    //   79: putstatic 63	uuuuuu/kvkvvv:bf00660066f0066f006600660066	Luuuuuu/kvkvvv;
    //   82: invokestatic 67	uuuuuu/kvkvvv:b007100710071q0071qqqqq	()I
    //   85: invokestatic 70	uuuuuu/kvkvvv:bqqq00710071qqqqq	()I
    //   88: iadd
    //   89: invokestatic 67	uuuuuu/kvkvvv:b007100710071q0071qqqqq	()I
    //   92: imul
    //   93: invokestatic 73	uuuuuu/kvkvvv:bq00710071q0071qqqqq	()I
    //   96: irem
    //   97: invokestatic 76	uuuuuu/kvkvvv:b0071q0071q0071qqqqq	()I
    //   100: if_icmpeq +3 -> 103
    //   103: ldc 21
    //   105: ldc 78
    //   107: bipush 114
    //   109: iconst_1
    //   110: invokestatic 29	xxxxxx/uxxxxx:bb00620062bb0062b0062b0062	(Ljava/lang/String;CC)Ljava/lang/String;
    //   113: iconst_3
    //   114: anewarray 31	java/lang/Class
    //   117: dup
    //   118: iconst_0
    //   119: ldc 33
    //   121: aastore
    //   122: dup
    //   123: iconst_1
    //   124: getstatic 39	java/lang/Character:TYPE	Ljava/lang/Class;
    //   127: aastore
    //   128: dup
    //   129: iconst_2
    //   130: getstatic 39	java/lang/Character:TYPE	Ljava/lang/Class;
    //   133: aastore
    //   134: invokevirtual 43	java/lang/Class:getMethod	(Ljava/lang/String;[Ljava/lang/Class;)Ljava/lang/reflect/Method;
    //   137: astore_1
    //   138: aload_1
    //   139: aconst_null
    //   140: iconst_3
    //   141: anewarray 45	java/lang/Object
    //   144: dup
    //   145: iconst_0
    //   146: ldc 80
    //   148: aastore
    //   149: dup
    //   150: iconst_1
    //   151: bipush 7
    //   153: invokestatic 51	java/lang/Character:valueOf	(C)Ljava/lang/Character;
    //   156: aastore
    //   157: dup
    //   158: iconst_2
    //   159: iconst_4
    //   160: invokestatic 51	java/lang/Character:valueOf	(C)Ljava/lang/Character;
    //   163: aastore
    //   164: invokevirtual 57	java/lang/reflect/Method:invoke	(Ljava/lang/Object;[Ljava/lang/Object;)Ljava/lang/Object;
    //   167: astore_1
    //   168: new 2	uuuuuu/kvkvvv
    //   171: dup
    //   172: aload_1
    //   173: checkcast 33	java/lang/String
    //   176: iconst_1
    //   177: iconst_1
    //   178: invokespecial 61	uuuuuu/kvkvvv:<init>	(Ljava/lang/String;II)V
    //   181: putstatic 82	uuuuuu/kvkvvv:b006600660066f0066f006600660066	Luuuuuu/kvkvvv;
    //   184: ldc 21
    //   186: ldc 84
    //   188: sipush 202
    //   191: bipush 65
    //   193: iconst_3
    //   194: invokestatic 88	xxxxxx/uxxxxx:bbbb0062b0062b0062b0062	(Ljava/lang/String;CCC)Ljava/lang/String;
    //   197: iconst_4
    //   198: anewarray 31	java/lang/Class
    //   201: dup
    //   202: iconst_0
    //   203: ldc 33
    //   205: aastore
    //   206: dup
    //   207: iconst_1
    //   208: getstatic 39	java/lang/Character:TYPE	Ljava/lang/Class;
    //   211: aastore
    //   212: dup
    //   213: iconst_2
    //   214: getstatic 39	java/lang/Character:TYPE	Ljava/lang/Class;
    //   217: aastore
    //   218: dup
    //   219: iconst_3
    //   220: getstatic 39	java/lang/Character:TYPE	Ljava/lang/Class;
    //   223: aastore
    //   224: invokevirtual 43	java/lang/Class:getMethod	(Ljava/lang/String;[Ljava/lang/Class;)Ljava/lang/reflect/Method;
    //   227: astore_1
    //   228: aload_1
    //   229: aconst_null
    //   230: iconst_4
    //   231: anewarray 45	java/lang/Object
    //   234: dup
    //   235: iconst_0
    //   236: ldc 90
    //   238: aastore
    //   239: dup
    //   240: iconst_1
    //   241: sipush 209
    //   244: invokestatic 51	java/lang/Character:valueOf	(C)Ljava/lang/Character;
    //   247: aastore
    //   248: dup
    //   249: iconst_2
    //   250: sipush 222
    //   253: invokestatic 51	java/lang/Character:valueOf	(C)Ljava/lang/Character;
    //   256: aastore
    //   257: dup
    //   258: iconst_3
    //   259: iconst_2
    //   260: invokestatic 51	java/lang/Character:valueOf	(C)Ljava/lang/Character;
    //   263: aastore
    //   264: invokevirtual 57	java/lang/reflect/Method:invoke	(Ljava/lang/Object;[Ljava/lang/Object;)Ljava/lang/Object;
    //   267: astore_1
    //   268: aload_1
    //   269: checkcast 33	java/lang/String
    //   272: astore_1
    //   273: invokestatic 67	uuuuuu/kvkvvv:b007100710071q0071qqqqq	()I
    //   276: istore_0
    //   277: iload_0
    //   278: invokestatic 70	uuuuuu/kvkvvv:bqqq00710071qqqqq	()I
    //   281: iload_0
    //   282: iadd
    //   283: imul
    //   284: invokestatic 73	uuuuuu/kvkvvv:bq00710071q0071qqqqq	()I
    //   287: irem
    //   288: tableswitch	default:+20->308, 0:+20->308
    //   308: new 2	uuuuuu/kvkvvv
    //   311: dup
    //   312: aload_1
    //   313: iconst_2
    //   314: iconst_2
    //   315: invokespecial 61	uuuuuu/kvkvvv:<init>	(Ljava/lang/String;II)V
    //   318: putstatic 92	uuuuuu/kvkvvv:bff0066f0066f006600660066	Luuuuuu/kvkvvv;
    //   321: ldc 21
    //   323: ldc 94
    //   325: sipush 240
    //   328: iconst_5
    //   329: invokestatic 29	xxxxxx/uxxxxx:bb00620062bb0062b0062b0062	(Ljava/lang/String;CC)Ljava/lang/String;
    //   332: iconst_3
    //   333: anewarray 31	java/lang/Class
    //   336: dup
    //   337: iconst_0
    //   338: ldc 33
    //   340: aastore
    //   341: dup
    //   342: iconst_1
    //   343: getstatic 39	java/lang/Character:TYPE	Ljava/lang/Class;
    //   346: aastore
    //   347: dup
    //   348: iconst_2
    //   349: getstatic 39	java/lang/Character:TYPE	Ljava/lang/Class;
    //   352: aastore
    //   353: invokevirtual 43	java/lang/Class:getMethod	(Ljava/lang/String;[Ljava/lang/Class;)Ljava/lang/reflect/Method;
    //   356: astore_1
    //   357: aload_1
    //   358: aconst_null
    //   359: iconst_3
    //   360: anewarray 45	java/lang/Object
    //   363: dup
    //   364: iconst_0
    //   365: ldc 96
    //   367: aastore
    //   368: dup
    //   369: iconst_1
    //   370: sipush 218
    //   373: invokestatic 51	java/lang/Character:valueOf	(C)Ljava/lang/Character;
    //   376: aastore
    //   377: dup
    //   378: iconst_2
    //   379: iconst_1
    //   380: invokestatic 51	java/lang/Character:valueOf	(C)Ljava/lang/Character;
    //   383: aastore
    //   384: invokevirtual 57	java/lang/reflect/Method:invoke	(Ljava/lang/Object;[Ljava/lang/Object;)Ljava/lang/Object;
    //   387: astore_1
    //   388: new 2	uuuuuu/kvkvvv
    //   391: dup
    //   392: aload_1
    //   393: checkcast 33	java/lang/String
    //   396: iconst_3
    //   397: iconst_3
    //   398: invokespecial 61	uuuuuu/kvkvvv:<init>	(Ljava/lang/String;II)V
    //   401: putstatic 98	uuuuuu/kvkvvv:b00660066ff0066f006600660066	Luuuuuu/kvkvvv;
    //   404: ldc 21
    //   406: ldc 100
    //   408: sipush 230
    //   411: iconst_0
    //   412: invokestatic 29	xxxxxx/uxxxxx:bb00620062bb0062b0062b0062	(Ljava/lang/String;CC)Ljava/lang/String;
    //   415: iconst_4
    //   416: anewarray 31	java/lang/Class
    //   419: dup
    //   420: iconst_0
    //   421: ldc 33
    //   423: aastore
    //   424: dup
    //   425: iconst_1
    //   426: getstatic 39	java/lang/Character:TYPE	Ljava/lang/Class;
    //   429: aastore
    //   430: dup
    //   431: iconst_2
    //   432: getstatic 39	java/lang/Character:TYPE	Ljava/lang/Class;
    //   435: aastore
    //   436: dup
    //   437: iconst_3
    //   438: getstatic 39	java/lang/Character:TYPE	Ljava/lang/Class;
    //   441: aastore
    //   442: invokevirtual 43	java/lang/Class:getMethod	(Ljava/lang/String;[Ljava/lang/Class;)Ljava/lang/reflect/Method;
    //   445: astore_1
    //   446: aload_1
    //   447: aconst_null
    //   448: iconst_4
    //   449: anewarray 45	java/lang/Object
    //   452: dup
    //   453: iconst_0
    //   454: ldc 102
    //   456: aastore
    //   457: dup
    //   458: iconst_1
    //   459: bipush 32
    //   461: invokestatic 51	java/lang/Character:valueOf	(C)Ljava/lang/Character;
    //   464: aastore
    //   465: dup
    //   466: iconst_2
    //   467: bipush 25
    //   469: invokestatic 51	java/lang/Character:valueOf	(C)Ljava/lang/Character;
    //   472: aastore
    //   473: dup
    //   474: iconst_3
    //   475: iconst_2
    //   476: invokestatic 51	java/lang/Character:valueOf	(C)Ljava/lang/Character;
    //   479: aastore
    //   480: invokevirtual 57	java/lang/reflect/Method:invoke	(Ljava/lang/Object;[Ljava/lang/Object;)Ljava/lang/Object;
    //   483: astore_1
    //   484: new 2	uuuuuu/kvkvvv
    //   487: dup
    //   488: aload_1
    //   489: checkcast 33	java/lang/String
    //   492: iconst_4
    //   493: iconst_4
    //   494: invokespecial 61	uuuuuu/kvkvvv:<init>	(Ljava/lang/String;II)V
    //   497: putstatic 104	uuuuuu/kvkvvv:b0066f0066f0066f006600660066	Luuuuuu/kvkvvv;
    //   500: iconst_5
    //   501: anewarray 2	uuuuuu/kvkvvv
    //   504: dup
    //   505: iconst_0
    //   506: getstatic 63	uuuuuu/kvkvvv:bf00660066f0066f006600660066	Luuuuuu/kvkvvv;
    //   509: aastore
    //   510: dup
    //   511: iconst_1
    //   512: getstatic 82	uuuuuu/kvkvvv:b006600660066f0066f006600660066	Luuuuuu/kvkvvv;
    //   515: aastore
    //   516: dup
    //   517: iconst_2
    //   518: getstatic 92	uuuuuu/kvkvvv:bff0066f0066f006600660066	Luuuuuu/kvkvvv;
    //   521: aastore
    //   522: dup
    //   523: iconst_3
    //   524: getstatic 98	uuuuuu/kvkvvv:b00660066ff0066f006600660066	Luuuuuu/kvkvvv;
    //   527: aastore
    //   528: dup
    //   529: iconst_4
    //   530: getstatic 104	uuuuuu/kvkvvv:b0066f0066f0066f006600660066	Luuuuuu/kvkvvv;
    //   533: aastore
    //   534: putstatic 106	uuuuuu/kvkvvv:bf0066ff0066f006600660066	[Luuuuuu/kvkvvv;
    //   537: return
    //   538: astore_1
    //   539: aload_1
    //   540: invokevirtual 110	java/lang/reflect/InvocationTargetException:getCause	()Ljava/lang/Throwable;
    //   543: athrow
    //   544: astore_1
    //   545: aload_1
    //   546: invokevirtual 110	java/lang/reflect/InvocationTargetException:getCause	()Ljava/lang/Throwable;
    //   549: athrow
    //   550: astore_1
    //   551: aload_1
    //   552: invokevirtual 110	java/lang/reflect/InvocationTargetException:getCause	()Ljava/lang/Throwable;
    //   555: athrow
    //   556: astore_1
    //   557: aload_1
    //   558: invokevirtual 110	java/lang/reflect/InvocationTargetException:getCause	()Ljava/lang/Throwable;
    //   561: athrow
    //   562: astore_1
    //   563: aload_1
    //   564: invokevirtual 110	java/lang/reflect/InvocationTargetException:getCause	()Ljava/lang/Throwable;
    //   567: athrow
    // Local variable table:
    //   start	length	slot	name	signature
    //   276	8	0	i	int
    //   35	454	1	localObject	Object
    //   538	2	1	localInvocationTargetException1	java.lang.reflect.InvocationTargetException
    //   544	2	1	localInvocationTargetException2	java.lang.reflect.InvocationTargetException
    //   550	2	1	localInvocationTargetException3	java.lang.reflect.InvocationTargetException
    //   556	2	1	localInvocationTargetException4	java.lang.reflect.InvocationTargetException
    //   562	2	1	localInvocationTargetException5	java.lang.reflect.InvocationTargetException
    // Exception table:
    //   from	to	target	type
    //   36	66	538	java/lang/reflect/InvocationTargetException
    //   138	168	544	java/lang/reflect/InvocationTargetException
    //   357	388	550	java/lang/reflect/InvocationTargetException
    //   228	268	556	java/lang/reflect/InvocationTargetException
    //   446	484	562	java/lang/reflect/InvocationTargetException
  }
  
  private kvkvvv(int paramInt)
  {
    this.bfff00660066f006600660066 = paramInt;
  }
  
  public static int b007100710071q0071qqqqq()
  {
    return 55;
  }
  
  public static int b0071q0071q0071qqqqq()
  {
    return 0;
  }
  
  public static kvkvvv b0071qq00710071qqqqq(int paramInt)
  {
    kvkvvv[] arrayOfKvkvvv = values();
    int j = arrayOfKvkvvv.length;
    int i = 0;
    for (;;)
    {
      if (i < j)
      {
        kvkvvv localKvkvvv = arrayOfKvkvvv[i];
        int k = b007100710071q0071qqqqq();
        switch (k * (bqqq00710071qqqqq() + k) % bq00710071q0071qqqqq())
        {
        }
        if (localKvkvvv.bfff00660066f006600660066 == paramInt) {
          return localKvkvvv;
        }
      }
      else
      {
        return bf00660066f0066f006600660066;
      }
      i += 1;
      if ((b007100710071q0071qqqqq() + bqqq00710071qqqqq()) * b007100710071q0071qqqqq() % bq00710071q0071qqqqq() != b0071q0071q0071qqqqq()) {}
    }
  }
  
  public static int bq00710071q0071qqqqq()
  {
    return 2;
  }
  
  public static kvkvvv bq0071q00710071qqqqq(String paramString)
  {
    int i = b007100710071q0071qqqqq();
    switch (i * (bqqq00710071qqqqq() + i) % bq00710071q0071qqqqq())
    {
    }
    return (kvkvvv)Enum.valueOf(kvkvvv.class, paramString);
  }
  
  public static int bqqq00710071qqqqq()
  {
    return 1;
  }
}
