package uuuuuu;

public class lklklk
  extends ssssst<kkkllk.kllklk>
  implements kkkllk.lllklk
{
  public static int b00620062bb0062b0062bb = 2;
  public static int b0062bbb0062b0062bb = 7;
  private static final String bb006200620062bb0062bb = lklklk.class.getSimpleName();
  public static int bb0062bb0062b0062bb = 1;
  public static int bbb0062b0062b0062bb;
  public vpvppv.pvvppv b0062006200620062bb0062bb = new lklklk.1(this);
  public vpvppv bbbbb0062b0062bb = new oooloo();
  
  /* Error */
  static
  {
    // Byte code:
    //   0: ldc 2
    //   2: invokevirtual 31	java/lang/Class:getSimpleName	()Ljava/lang/String;
    //   5: putstatic 33	uuuuuu/lklklk:bb006200620062bb0062bb	Ljava/lang/String;
    //   8: getstatic 35	uuuuuu/lklklk:b0062bbb0062b0062bb	I
    //   11: istore_0
    //   12: getstatic 37	uuuuuu/lklklk:bb0062bb0062b0062bb	I
    //   15: istore_1
    //   16: getstatic 35	uuuuuu/lklklk:b0062bbb0062b0062bb	I
    //   19: istore_2
    //   20: ldc 2
    //   22: ldc 39
    //   24: sipush 190
    //   27: bipush 83
    //   29: iconst_2
    //   30: invokestatic 45	xxxxxx/uxxxxx:bbbb0062b0062b0062b0062	(Ljava/lang/String;CCC)Ljava/lang/String;
    //   33: iconst_0
    //   34: anewarray 27	java/lang/Class
    //   37: invokevirtual 49	java/lang/Class:getMethod	(Ljava/lang/String;[Ljava/lang/Class;)Ljava/lang/reflect/Method;
    //   40: astore_3
    //   41: aload_3
    //   42: aconst_null
    //   43: iconst_0
    //   44: anewarray 51	java/lang/Object
    //   47: invokevirtual 57	java/lang/reflect/Method:invoke	(Ljava/lang/Object;[Ljava/lang/Object;)Ljava/lang/Object;
    //   50: astore_3
    //   51: aload_3
    //   52: checkcast 59	java/lang/Integer
    //   55: invokevirtual 63	java/lang/Integer:intValue	()I
    //   58: iload_2
    //   59: iadd
    //   60: getstatic 35	uuuuuu/lklklk:b0062bbb0062b0062bb	I
    //   63: imul
    //   64: getstatic 65	uuuuuu/lklklk:b00620062bb0062b0062bb	I
    //   67: irem
    //   68: getstatic 67	uuuuuu/lklklk:bbb0062b0062b0062bb	I
    //   71: if_icmpeq +146 -> 217
    //   74: getstatic 35	uuuuuu/lklklk:b0062bbb0062b0062bb	I
    //   77: getstatic 37	uuuuuu/lklklk:bb0062bb0062b0062bb	I
    //   80: iadd
    //   81: getstatic 35	uuuuuu/lklklk:b0062bbb0062b0062bb	I
    //   84: imul
    //   85: getstatic 65	uuuuuu/lklklk:b00620062bb0062b0062bb	I
    //   88: irem
    //   89: getstatic 67	uuuuuu/lklklk:bbb0062b0062b0062bb	I
    //   92: if_icmpeq +46 -> 138
    //   95: ldc 2
    //   97: ldc 69
    //   99: bipush 120
    //   101: iconst_4
    //   102: invokestatic 73	xxxxxx/uxxxxx:bb00620062bb0062b0062b0062	(Ljava/lang/String;CC)Ljava/lang/String;
    //   105: iconst_0
    //   106: anewarray 27	java/lang/Class
    //   109: invokevirtual 49	java/lang/Class:getMethod	(Ljava/lang/String;[Ljava/lang/Class;)Ljava/lang/reflect/Method;
    //   112: astore_3
    //   113: aload_3
    //   114: aconst_null
    //   115: iconst_0
    //   116: anewarray 51	java/lang/Object
    //   119: invokevirtual 57	java/lang/reflect/Method:invoke	(Ljava/lang/Object;[Ljava/lang/Object;)Ljava/lang/Object;
    //   122: astore_3
    //   123: aload_3
    //   124: checkcast 59	java/lang/Integer
    //   127: invokevirtual 63	java/lang/Integer:intValue	()I
    //   130: putstatic 35	uuuuuu/lklklk:b0062bbb0062b0062bb	I
    //   133: bipush 66
    //   135: putstatic 67	uuuuuu/lklklk:bbb0062b0062b0062bb	I
    //   138: ldc 2
    //   140: ldc 75
    //   142: bipush 119
    //   144: sipush 224
    //   147: iconst_0
    //   148: invokestatic 45	xxxxxx/uxxxxx:bbbb0062b0062b0062b0062	(Ljava/lang/String;CCC)Ljava/lang/String;
    //   151: iconst_0
    //   152: anewarray 27	java/lang/Class
    //   155: invokevirtual 49	java/lang/Class:getMethod	(Ljava/lang/String;[Ljava/lang/Class;)Ljava/lang/reflect/Method;
    //   158: astore_3
    //   159: aload_3
    //   160: aconst_null
    //   161: iconst_0
    //   162: anewarray 51	java/lang/Object
    //   165: invokevirtual 57	java/lang/reflect/Method:invoke	(Ljava/lang/Object;[Ljava/lang/Object;)Ljava/lang/Object;
    //   168: astore_3
    //   169: aload_3
    //   170: checkcast 59	java/lang/Integer
    //   173: invokevirtual 63	java/lang/Integer:intValue	()I
    //   176: putstatic 35	uuuuuu/lklklk:b0062bbb0062b0062bb	I
    //   179: ldc 2
    //   181: ldc 77
    //   183: bipush 106
    //   185: iconst_5
    //   186: invokestatic 73	xxxxxx/uxxxxx:bb00620062bb0062b0062b0062	(Ljava/lang/String;CC)Ljava/lang/String;
    //   189: iconst_0
    //   190: anewarray 27	java/lang/Class
    //   193: invokevirtual 49	java/lang/Class:getMethod	(Ljava/lang/String;[Ljava/lang/Class;)Ljava/lang/reflect/Method;
    //   196: astore_3
    //   197: aload_3
    //   198: aconst_null
    //   199: iconst_0
    //   200: anewarray 51	java/lang/Object
    //   203: invokevirtual 57	java/lang/reflect/Method:invoke	(Ljava/lang/Object;[Ljava/lang/Object;)Ljava/lang/Object;
    //   206: astore_3
    //   207: aload_3
    //   208: checkcast 59	java/lang/Integer
    //   211: invokevirtual 63	java/lang/Integer:intValue	()I
    //   214: putstatic 67	uuuuuu/lklklk:bbb0062b0062b0062bb	I
    //   217: getstatic 35	uuuuuu/lklklk:b0062bbb0062b0062bb	I
    //   220: getstatic 37	uuuuuu/lklklk:bb0062bb0062b0062bb	I
    //   223: iadd
    //   224: getstatic 35	uuuuuu/lklklk:b0062bbb0062b0062bb	I
    //   227: imul
    //   228: getstatic 65	uuuuuu/lklklk:b00620062bb0062b0062bb	I
    //   231: irem
    //   232: getstatic 67	uuuuuu/lklklk:bbb0062b0062b0062bb	I
    //   235: if_icmpeq +46 -> 281
    //   238: bipush 59
    //   240: putstatic 35	uuuuuu/lklklk:b0062bbb0062b0062bb	I
    //   243: ldc 2
    //   245: ldc 79
    //   247: bipush 57
    //   249: iconst_2
    //   250: invokestatic 73	xxxxxx/uxxxxx:bb00620062bb0062b0062b0062	(Ljava/lang/String;CC)Ljava/lang/String;
    //   253: iconst_0
    //   254: anewarray 27	java/lang/Class
    //   257: invokevirtual 49	java/lang/Class:getMethod	(Ljava/lang/String;[Ljava/lang/Class;)Ljava/lang/reflect/Method;
    //   260: astore_3
    //   261: aload_3
    //   262: aconst_null
    //   263: iconst_0
    //   264: anewarray 51	java/lang/Object
    //   267: invokevirtual 57	java/lang/reflect/Method:invoke	(Ljava/lang/Object;[Ljava/lang/Object;)Ljava/lang/Object;
    //   270: astore_3
    //   271: aload_3
    //   272: checkcast 59	java/lang/Integer
    //   275: invokevirtual 63	java/lang/Integer:intValue	()I
    //   278: putstatic 67	uuuuuu/lklklk:bbb0062b0062b0062bb	I
    //   281: iload_0
    //   282: iload_1
    //   283: iload_0
    //   284: iadd
    //   285: imul
    //   286: getstatic 65	uuuuuu/lklklk:b00620062bb0062b0062bb	I
    //   289: irem
    //   290: tableswitch	default:+18->308, 0:+100->390
    //   308: ldc 2
    //   310: ldc 81
    //   312: sipush 147
    //   315: sipush 171
    //   318: iconst_3
    //   319: invokestatic 45	xxxxxx/uxxxxx:bbbb0062b0062b0062b0062	(Ljava/lang/String;CCC)Ljava/lang/String;
    //   322: iconst_0
    //   323: anewarray 27	java/lang/Class
    //   326: invokevirtual 49	java/lang/Class:getMethod	(Ljava/lang/String;[Ljava/lang/Class;)Ljava/lang/reflect/Method;
    //   329: astore_3
    //   330: aload_3
    //   331: aconst_null
    //   332: iconst_0
    //   333: anewarray 51	java/lang/Object
    //   336: invokevirtual 57	java/lang/reflect/Method:invoke	(Ljava/lang/Object;[Ljava/lang/Object;)Ljava/lang/Object;
    //   339: astore_3
    //   340: aload_3
    //   341: checkcast 59	java/lang/Integer
    //   344: invokevirtual 63	java/lang/Integer:intValue	()I
    //   347: putstatic 35	uuuuuu/lklklk:b0062bbb0062b0062bb	I
    //   350: ldc 2
    //   352: ldc 83
    //   354: bipush 30
    //   356: bipush 60
    //   358: iconst_0
    //   359: invokestatic 45	xxxxxx/uxxxxx:bbbb0062b0062b0062b0062	(Ljava/lang/String;CCC)Ljava/lang/String;
    //   362: iconst_0
    //   363: anewarray 27	java/lang/Class
    //   366: invokevirtual 49	java/lang/Class:getMethod	(Ljava/lang/String;[Ljava/lang/Class;)Ljava/lang/reflect/Method;
    //   369: astore_3
    //   370: aload_3
    //   371: aconst_null
    //   372: iconst_0
    //   373: anewarray 51	java/lang/Object
    //   376: invokevirtual 57	java/lang/reflect/Method:invoke	(Ljava/lang/Object;[Ljava/lang/Object;)Ljava/lang/Object;
    //   379: astore_3
    //   380: aload_3
    //   381: checkcast 59	java/lang/Integer
    //   384: invokevirtual 63	java/lang/Integer:intValue	()I
    //   387: putstatic 37	uuuuuu/lklklk:bb0062bb0062b0062bb	I
    //   390: return
    //   391: astore_3
    //   392: aload_3
    //   393: invokevirtual 87	java/lang/reflect/InvocationTargetException:getCause	()Ljava/lang/Throwable;
    //   396: athrow
    //   397: astore_3
    //   398: aload_3
    //   399: invokevirtual 87	java/lang/reflect/InvocationTargetException:getCause	()Ljava/lang/Throwable;
    //   402: athrow
    //   403: astore_3
    //   404: aload_3
    //   405: invokevirtual 87	java/lang/reflect/InvocationTargetException:getCause	()Ljava/lang/Throwable;
    //   408: athrow
    //   409: astore_3
    //   410: aload_3
    //   411: invokevirtual 87	java/lang/reflect/InvocationTargetException:getCause	()Ljava/lang/Throwable;
    //   414: athrow
    //   415: astore_3
    //   416: aload_3
    //   417: invokevirtual 87	java/lang/reflect/InvocationTargetException:getCause	()Ljava/lang/Throwable;
    //   420: athrow
    //   421: astore_3
    //   422: aload_3
    //   423: invokevirtual 87	java/lang/reflect/InvocationTargetException:getCause	()Ljava/lang/Throwable;
    //   426: athrow
    //   427: astore_3
    //   428: aload_3
    //   429: invokevirtual 87	java/lang/reflect/InvocationTargetException:getCause	()Ljava/lang/Throwable;
    //   432: athrow
    // Local variable table:
    //   start	length	slot	name	signature
    //   11	275	0	i	int
    //   15	270	1	j	int
    //   19	41	2	k	int
    //   40	341	3	localObject	Object
    //   391	2	3	localInvocationTargetException1	java.lang.reflect.InvocationTargetException
    //   397	2	3	localInvocationTargetException2	java.lang.reflect.InvocationTargetException
    //   403	2	3	localInvocationTargetException3	java.lang.reflect.InvocationTargetException
    //   409	2	3	localInvocationTargetException4	java.lang.reflect.InvocationTargetException
    //   415	2	3	localInvocationTargetException5	java.lang.reflect.InvocationTargetException
    //   421	2	3	localInvocationTargetException6	java.lang.reflect.InvocationTargetException
    //   427	2	3	localInvocationTargetException7	java.lang.reflect.InvocationTargetException
    // Exception table:
    //   from	to	target	type
    //   370	380	391	java/lang/reflect/InvocationTargetException
    //   330	340	397	java/lang/reflect/InvocationTargetException
    //   41	51	403	java/lang/reflect/InvocationTargetException
    //   261	271	409	java/lang/reflect/InvocationTargetException
    //   159	169	415	java/lang/reflect/InvocationTargetException
    //   197	207	421	java/lang/reflect/InvocationTargetException
    //   113	123	427	java/lang/reflect/InvocationTargetException
  }
  
  public lklklk() {}
  
  public static int b00690069006900690069i0069i0069i()
  {
    return 1;
  }
  
  public static int b0069i006900690069i0069i0069i()
  {
    return 4;
  }
  
  public static int bi0069006900690069i0069i0069i()
  {
    return 0;
  }
  
  public static int biiiii00690069i0069i()
  {
    return 2;
  }
  
  /* Error */
  public void b0069iiii00690069i0069i(kkkllk.kllklk paramKllklk)
  {
    // Byte code:
    //   0: aload_0
    //   1: aload_1
    //   2: invokespecial 153	uuuuuu/ssssst:ba0061a0061a0061a0061aa	(Luuuuuu/ttssst$tsssst;)V
    //   5: aload_0
    //   6: getfield 96	uuuuuu/lklklk:bbbbb0062b0062bb	Luuuuuu/vpvppv;
    //   9: aload_0
    //   10: getfield 103	uuuuuu/lklklk:b0062006200620062bb0062bb	Luuuuuu/vpvppv$pvvppv;
    //   13: aconst_null
    //   14: invokeinterface 159 3 0
    //   19: getstatic 35	uuuuuu/lklklk:b0062bbb0062b0062bb	I
    //   22: istore_2
    //   23: getstatic 37	uuuuuu/lklklk:bb0062bb0062b0062bb	I
    //   26: istore_3
    //   27: getstatic 35	uuuuuu/lklklk:b0062bbb0062b0062bb	I
    //   30: istore 4
    //   32: iload 4
    //   34: getstatic 37	uuuuuu/lklklk:bb0062bb0062b0062bb	I
    //   37: iload 4
    //   39: iadd
    //   40: imul
    //   41: getstatic 65	uuuuuu/lklklk:b00620062bb0062b0062bb	I
    //   44: irem
    //   45: tableswitch	default:+19->64, 0:+161->206
    //   64: ldc 2
    //   66: ldc -95
    //   68: sipush 192
    //   71: iconst_2
    //   72: invokestatic 73	xxxxxx/uxxxxx:bb00620062bb0062b0062b0062	(Ljava/lang/String;CC)Ljava/lang/String;
    //   75: iconst_0
    //   76: anewarray 27	java/lang/Class
    //   79: invokevirtual 49	java/lang/Class:getMethod	(Ljava/lang/String;[Ljava/lang/Class;)Ljava/lang/reflect/Method;
    //   82: astore_1
    //   83: aload_1
    //   84: aconst_null
    //   85: iconst_0
    //   86: anewarray 51	java/lang/Object
    //   89: invokevirtual 57	java/lang/reflect/Method:invoke	(Ljava/lang/Object;[Ljava/lang/Object;)Ljava/lang/Object;
    //   92: astore_1
    //   93: aload_1
    //   94: checkcast 59	java/lang/Integer
    //   97: invokevirtual 63	java/lang/Integer:intValue	()I
    //   100: putstatic 35	uuuuuu/lklklk:b0062bbb0062b0062bb	I
    //   103: bipush 93
    //   105: putstatic 67	uuuuuu/lklklk:bbb0062b0062b0062bb	I
    //   108: getstatic 35	uuuuuu/lklklk:b0062bbb0062b0062bb	I
    //   111: getstatic 37	uuuuuu/lklklk:bb0062bb0062b0062bb	I
    //   114: iadd
    //   115: getstatic 35	uuuuuu/lklklk:b0062bbb0062b0062bb	I
    //   118: imul
    //   119: getstatic 65	uuuuuu/lklklk:b00620062bb0062b0062bb	I
    //   122: irem
    //   123: getstatic 67	uuuuuu/lklklk:bbb0062b0062b0062bb	I
    //   126: if_icmpeq +80 -> 206
    //   129: ldc 2
    //   131: ldc -93
    //   133: sipush 184
    //   136: iconst_1
    //   137: invokestatic 73	xxxxxx/uxxxxx:bb00620062bb0062b0062b0062	(Ljava/lang/String;CC)Ljava/lang/String;
    //   140: iconst_0
    //   141: anewarray 27	java/lang/Class
    //   144: invokevirtual 49	java/lang/Class:getMethod	(Ljava/lang/String;[Ljava/lang/Class;)Ljava/lang/reflect/Method;
    //   147: astore_1
    //   148: aload_1
    //   149: aconst_null
    //   150: iconst_0
    //   151: anewarray 51	java/lang/Object
    //   154: invokevirtual 57	java/lang/reflect/Method:invoke	(Ljava/lang/Object;[Ljava/lang/Object;)Ljava/lang/Object;
    //   157: astore_1
    //   158: aload_1
    //   159: checkcast 59	java/lang/Integer
    //   162: invokevirtual 63	java/lang/Integer:intValue	()I
    //   165: putstatic 35	uuuuuu/lklklk:b0062bbb0062b0062bb	I
    //   168: ldc 2
    //   170: ldc -91
    //   172: bipush 9
    //   174: iconst_1
    //   175: invokestatic 73	xxxxxx/uxxxxx:bb00620062bb0062b0062b0062	(Ljava/lang/String;CC)Ljava/lang/String;
    //   178: iconst_0
    //   179: anewarray 27	java/lang/Class
    //   182: invokevirtual 49	java/lang/Class:getMethod	(Ljava/lang/String;[Ljava/lang/Class;)Ljava/lang/reflect/Method;
    //   185: astore_1
    //   186: aload_1
    //   187: aconst_null
    //   188: iconst_0
    //   189: anewarray 51	java/lang/Object
    //   192: invokevirtual 57	java/lang/reflect/Method:invoke	(Ljava/lang/Object;[Ljava/lang/Object;)Ljava/lang/Object;
    //   195: astore_1
    //   196: aload_1
    //   197: checkcast 59	java/lang/Integer
    //   200: invokevirtual 63	java/lang/Integer:intValue	()I
    //   203: putstatic 67	uuuuuu/lklklk:bbb0062b0062b0062bb	I
    //   206: ldc 2
    //   208: ldc -89
    //   210: sipush 223
    //   213: iconst_0
    //   214: invokestatic 73	xxxxxx/uxxxxx:bb00620062bb0062b0062b0062	(Ljava/lang/String;CC)Ljava/lang/String;
    //   217: iconst_0
    //   218: anewarray 27	java/lang/Class
    //   221: invokevirtual 49	java/lang/Class:getMethod	(Ljava/lang/String;[Ljava/lang/Class;)Ljava/lang/reflect/Method;
    //   224: astore_1
    //   225: aload_1
    //   226: aconst_null
    //   227: iconst_0
    //   228: anewarray 51	java/lang/Object
    //   231: invokevirtual 57	java/lang/reflect/Method:invoke	(Ljava/lang/Object;[Ljava/lang/Object;)Ljava/lang/Object;
    //   234: astore_1
    //   235: iload_2
    //   236: iload_2
    //   237: iload_3
    //   238: iadd
    //   239: imul
    //   240: aload_1
    //   241: checkcast 59	java/lang/Integer
    //   244: invokevirtual 63	java/lang/Integer:intValue	()I
    //   247: irem
    //   248: tableswitch	default:+20->268, 0:+103->351
    //   268: getstatic 35	uuuuuu/lklklk:b0062bbb0062b0062bb	I
    //   271: istore_2
    //   272: iload_2
    //   273: getstatic 37	uuuuuu/lklklk:bb0062bb0062b0062bb	I
    //   276: iload_2
    //   277: iadd
    //   278: imul
    //   279: getstatic 65	uuuuuu/lklklk:b00620062bb0062b0062bb	I
    //   282: irem
    //   283: tableswitch	default:+17->300, 0:+27->310
    //   300: bipush 46
    //   302: putstatic 35	uuuuuu/lklklk:b0062bbb0062b0062bb	I
    //   305: bipush 38
    //   307: putstatic 67	uuuuuu/lklklk:bbb0062b0062b0062bb	I
    //   310: ldc 2
    //   312: ldc -87
    //   314: iconst_4
    //   315: iconst_3
    //   316: invokestatic 73	xxxxxx/uxxxxx:bb00620062bb0062b0062b0062	(Ljava/lang/String;CC)Ljava/lang/String;
    //   319: iconst_0
    //   320: anewarray 27	java/lang/Class
    //   323: invokevirtual 49	java/lang/Class:getMethod	(Ljava/lang/String;[Ljava/lang/Class;)Ljava/lang/reflect/Method;
    //   326: astore_1
    //   327: aload_1
    //   328: aconst_null
    //   329: iconst_0
    //   330: anewarray 51	java/lang/Object
    //   333: invokevirtual 57	java/lang/reflect/Method:invoke	(Ljava/lang/Object;[Ljava/lang/Object;)Ljava/lang/Object;
    //   336: astore_1
    //   337: aload_1
    //   338: checkcast 59	java/lang/Integer
    //   341: invokevirtual 63	java/lang/Integer:intValue	()I
    //   344: putstatic 35	uuuuuu/lklklk:b0062bbb0062b0062bb	I
    //   347: iconst_1
    //   348: putstatic 67	uuuuuu/lklklk:bbb0062b0062b0062bb	I
    //   351: return
    //   352: astore_1
    //   353: aload_1
    //   354: invokevirtual 87	java/lang/reflect/InvocationTargetException:getCause	()Ljava/lang/Throwable;
    //   357: athrow
    //   358: astore_1
    //   359: aload_1
    //   360: invokevirtual 87	java/lang/reflect/InvocationTargetException:getCause	()Ljava/lang/Throwable;
    //   363: athrow
    //   364: astore_1
    //   365: aload_1
    //   366: invokevirtual 87	java/lang/reflect/InvocationTargetException:getCause	()Ljava/lang/Throwable;
    //   369: athrow
    //   370: astore_1
    //   371: aload_1
    //   372: invokevirtual 87	java/lang/reflect/InvocationTargetException:getCause	()Ljava/lang/Throwable;
    //   375: athrow
    //   376: astore_1
    //   377: aload_1
    //   378: invokevirtual 87	java/lang/reflect/InvocationTargetException:getCause	()Ljava/lang/Throwable;
    //   381: athrow
    // Local variable table:
    //   start	length	slot	name	signature
    //   0	382	0	this	lklklk
    //   0	382	1	paramKllklk	kkkllk.kllklk
    //   22	257	2	i	int
    //   26	213	3	j	int
    //   30	11	4	k	int
    // Exception table:
    //   from	to	target	type
    //   83	93	352	java/lang/reflect/InvocationTargetException
    //   225	235	358	java/lang/reflect/InvocationTargetException
    //   327	337	364	java/lang/reflect/InvocationTargetException
    //   148	158	370	java/lang/reflect/InvocationTargetException
    //   186	196	376	java/lang/reflect/InvocationTargetException
  }
  
  /* Error */
  public void bi00690069i0069i0069i0069i()
  {
    // Byte code:
    //   0: getstatic 35	uuuuuu/lklklk:b0062bbb0062b0062bb	I
    //   3: istore_1
    //   4: ldc 2
    //   6: ldc -69
    //   8: bipush 75
    //   10: bipush 58
    //   12: iconst_1
    //   13: invokestatic 45	xxxxxx/uxxxxx:bbbb0062b0062b0062b0062	(Ljava/lang/String;CCC)Ljava/lang/String;
    //   16: iconst_0
    //   17: anewarray 27	java/lang/Class
    //   20: invokevirtual 49	java/lang/Class:getMethod	(Ljava/lang/String;[Ljava/lang/Class;)Ljava/lang/reflect/Method;
    //   23: astore_3
    //   24: aload_3
    //   25: aconst_null
    //   26: iconst_0
    //   27: anewarray 51	java/lang/Object
    //   30: invokevirtual 57	java/lang/reflect/Method:invoke	(Ljava/lang/Object;[Ljava/lang/Object;)Ljava/lang/Object;
    //   33: astore_3
    //   34: aload_3
    //   35: checkcast 59	java/lang/Integer
    //   38: invokevirtual 63	java/lang/Integer:intValue	()I
    //   41: iload_1
    //   42: iadd
    //   43: iload_1
    //   44: imul
    //   45: getstatic 65	uuuuuu/lklklk:b00620062bb0062b0062bb	I
    //   48: irem
    //   49: tableswitch	default:+19->68, 0:+273->322
    //   68: ldc 2
    //   70: ldc -67
    //   72: bipush 120
    //   74: iconst_3
    //   75: invokestatic 73	xxxxxx/uxxxxx:bb00620062bb0062b0062b0062	(Ljava/lang/String;CC)Ljava/lang/String;
    //   78: iconst_0
    //   79: anewarray 27	java/lang/Class
    //   82: invokevirtual 49	java/lang/Class:getMethod	(Ljava/lang/String;[Ljava/lang/Class;)Ljava/lang/reflect/Method;
    //   85: astore_3
    //   86: aload_3
    //   87: aconst_null
    //   88: iconst_0
    //   89: anewarray 51	java/lang/Object
    //   92: invokevirtual 57	java/lang/reflect/Method:invoke	(Ljava/lang/Object;[Ljava/lang/Object;)Ljava/lang/Object;
    //   95: astore_3
    //   96: aload_3
    //   97: checkcast 59	java/lang/Integer
    //   100: invokevirtual 63	java/lang/Integer:intValue	()I
    //   103: putstatic 35	uuuuuu/lklklk:b0062bbb0062b0062bb	I
    //   106: ldc 2
    //   108: ldc -65
    //   110: sipush 182
    //   113: iconst_3
    //   114: invokestatic 73	xxxxxx/uxxxxx:bb00620062bb0062b0062b0062	(Ljava/lang/String;CC)Ljava/lang/String;
    //   117: iconst_0
    //   118: anewarray 27	java/lang/Class
    //   121: invokevirtual 49	java/lang/Class:getMethod	(Ljava/lang/String;[Ljava/lang/Class;)Ljava/lang/reflect/Method;
    //   124: astore_3
    //   125: aload_3
    //   126: aconst_null
    //   127: iconst_0
    //   128: anewarray 51	java/lang/Object
    //   131: invokevirtual 57	java/lang/reflect/Method:invoke	(Ljava/lang/Object;[Ljava/lang/Object;)Ljava/lang/Object;
    //   134: astore_3
    //   135: aload_3
    //   136: checkcast 59	java/lang/Integer
    //   139: invokevirtual 63	java/lang/Integer:intValue	()I
    //   142: istore_1
    //   143: getstatic 37	uuuuuu/lklklk:bb0062bb0062b0062bb	I
    //   146: istore_2
    //   147: ldc 2
    //   149: ldc -63
    //   151: sipush 231
    //   154: iconst_1
    //   155: invokestatic 73	xxxxxx/uxxxxx:bb00620062bb0062b0062b0062	(Ljava/lang/String;CC)Ljava/lang/String;
    //   158: iconst_0
    //   159: anewarray 27	java/lang/Class
    //   162: invokevirtual 49	java/lang/Class:getMethod	(Ljava/lang/String;[Ljava/lang/Class;)Ljava/lang/reflect/Method;
    //   165: astore_3
    //   166: aload_3
    //   167: aconst_null
    //   168: iconst_0
    //   169: anewarray 51	java/lang/Object
    //   172: invokevirtual 57	java/lang/reflect/Method:invoke	(Ljava/lang/Object;[Ljava/lang/Object;)Ljava/lang/Object;
    //   175: astore_3
    //   176: aload_3
    //   177: checkcast 59	java/lang/Integer
    //   180: invokevirtual 63	java/lang/Integer:intValue	()I
    //   183: iload_2
    //   184: iload_1
    //   185: iadd
    //   186: imul
    //   187: getstatic 65	uuuuuu/lklklk:b00620062bb0062b0062bb	I
    //   190: irem
    //   191: getstatic 67	uuuuuu/lklklk:bbb0062b0062b0062bb	I
    //   194: if_icmpeq +13 -> 207
    //   197: bipush 9
    //   199: putstatic 35	uuuuuu/lklklk:b0062bbb0062b0062bb	I
    //   202: bipush 53
    //   204: putstatic 67	uuuuuu/lklklk:bbb0062b0062b0062bb	I
    //   207: bipush 79
    //   209: putstatic 67	uuuuuu/lklklk:bbb0062b0062b0062bb	I
    //   212: getstatic 35	uuuuuu/lklklk:b0062bbb0062b0062bb	I
    //   215: getstatic 37	uuuuuu/lklklk:bb0062bb0062b0062bb	I
    //   218: iadd
    //   219: getstatic 35	uuuuuu/lklklk:b0062bbb0062b0062bb	I
    //   222: imul
    //   223: getstatic 65	uuuuuu/lklklk:b00620062bb0062b0062bb	I
    //   226: irem
    //   227: getstatic 67	uuuuuu/lklklk:bbb0062b0062b0062bb	I
    //   230: if_icmpeq +92 -> 322
    //   233: bipush 89
    //   235: putstatic 35	uuuuuu/lklklk:b0062bbb0062b0062bb	I
    //   238: bipush 79
    //   240: putstatic 67	uuuuuu/lklklk:bbb0062b0062b0062bb	I
    //   243: getstatic 35	uuuuuu/lklklk:b0062bbb0062b0062bb	I
    //   246: istore_1
    //   247: iload_1
    //   248: getstatic 37	uuuuuu/lklklk:bb0062bb0062b0062bb	I
    //   251: iload_1
    //   252: iadd
    //   253: imul
    //   254: getstatic 65	uuuuuu/lklklk:b00620062bb0062b0062bb	I
    //   257: irem
    //   258: tableswitch	default:+18->276, 0:+64->322
    //   276: bipush 98
    //   278: putstatic 35	uuuuuu/lklklk:b0062bbb0062b0062bb	I
    //   281: ldc 2
    //   283: ldc -61
    //   285: bipush 118
    //   287: sipush 137
    //   290: iconst_1
    //   291: invokestatic 45	xxxxxx/uxxxxx:bbbb0062b0062b0062b0062	(Ljava/lang/String;CCC)Ljava/lang/String;
    //   294: iconst_0
    //   295: anewarray 27	java/lang/Class
    //   298: invokevirtual 49	java/lang/Class:getMethod	(Ljava/lang/String;[Ljava/lang/Class;)Ljava/lang/reflect/Method;
    //   301: astore_3
    //   302: aload_3
    //   303: aconst_null
    //   304: iconst_0
    //   305: anewarray 51	java/lang/Object
    //   308: invokevirtual 57	java/lang/reflect/Method:invoke	(Ljava/lang/Object;[Ljava/lang/Object;)Ljava/lang/Object;
    //   311: astore_3
    //   312: aload_3
    //   313: checkcast 59	java/lang/Integer
    //   316: invokevirtual 63	java/lang/Integer:intValue	()I
    //   319: putstatic 67	uuuuuu/lklklk:bbb0062b0062b0062bb	I
    //   322: aload_0
    //   323: getfield 110	uuuuuu/lklklk:bnnnnn006E006E006En	Luuuuuu/ttssst$tsssst;
    //   326: checkcast 177	uuuuuu/kkkllk$kllklk
    //   329: invokeinterface 198 1 0
    //   334: return
    //   335: astore_3
    //   336: aload_3
    //   337: invokevirtual 87	java/lang/reflect/InvocationTargetException:getCause	()Ljava/lang/Throwable;
    //   340: athrow
    //   341: astore_3
    //   342: aload_3
    //   343: invokevirtual 87	java/lang/reflect/InvocationTargetException:getCause	()Ljava/lang/Throwable;
    //   346: athrow
    //   347: astore_3
    //   348: aload_3
    //   349: invokevirtual 87	java/lang/reflect/InvocationTargetException:getCause	()Ljava/lang/Throwable;
    //   352: athrow
    //   353: astore_3
    //   354: aload_3
    //   355: invokevirtual 87	java/lang/reflect/InvocationTargetException:getCause	()Ljava/lang/Throwable;
    //   358: athrow
    //   359: astore_3
    //   360: aload_3
    //   361: invokevirtual 87	java/lang/reflect/InvocationTargetException:getCause	()Ljava/lang/Throwable;
    //   364: athrow
    // Local variable table:
    //   start	length	slot	name	signature
    //   0	365	0	this	lklklk
    //   3	251	1	i	int
    //   146	40	2	j	int
    //   23	290	3	localObject	Object
    //   335	2	3	localInvocationTargetException1	java.lang.reflect.InvocationTargetException
    //   341	2	3	localInvocationTargetException2	java.lang.reflect.InvocationTargetException
    //   347	2	3	localInvocationTargetException3	java.lang.reflect.InvocationTargetException
    //   353	2	3	localInvocationTargetException4	java.lang.reflect.InvocationTargetException
    //   359	2	3	localInvocationTargetException5	java.lang.reflect.InvocationTargetException
    // Exception table:
    //   from	to	target	type
    //   24	34	335	java/lang/reflect/InvocationTargetException
    //   125	135	341	java/lang/reflect/InvocationTargetException
    //   166	176	347	java/lang/reflect/InvocationTargetException
    //   86	96	353	java/lang/reflect/InvocationTargetException
    //   302	312	359	java/lang/reflect/InvocationTargetException
  }
  
  /* Error */
  public android.graphics.Bitmap bi0069iii00690069i0069i(com.db.pwcc.dbmobile.model.tan.ChallengeResponse paramChallengeResponse)
  {
    // Byte code:
    //   0: aload_1
    //   1: ifnull +572 -> 573
    //   4: aload_1
    //   5: invokevirtual 208	com/db/pwcc/dbmobile/model/tan/ChallengeResponse:getChallenge	()Lcom/db/pwcc/dbmobile/model/tan/Challenge;
    //   8: ifnull +565 -> 573
    //   11: aload_1
    //   12: invokevirtual 208	com/db/pwcc/dbmobile/model/tan/ChallengeResponse:getChallenge	()Lcom/db/pwcc/dbmobile/model/tan/Challenge;
    //   15: invokevirtual 213	com/db/pwcc/dbmobile/model/tan/Challenge:getTanImage	()Ljava/lang/String;
    //   18: ifnonnull +5 -> 23
    //   21: aconst_null
    //   22: areturn
    //   23: aload_1
    //   24: invokevirtual 208	com/db/pwcc/dbmobile/model/tan/ChallengeResponse:getChallenge	()Lcom/db/pwcc/dbmobile/model/tan/Challenge;
    //   27: invokevirtual 213	com/db/pwcc/dbmobile/model/tan/Challenge:getTanImage	()Ljava/lang/String;
    //   30: iconst_0
    //   31: invokestatic 219	android/util/Base64:decode	(Ljava/lang/String;I)[B
    //   34: astore_1
    //   35: getstatic 35	uuuuuu/lklklk:b0062bbb0062b0062bb	I
    //   38: istore_2
    //   39: getstatic 37	uuuuuu/lklklk:bb0062bb0062b0062bb	I
    //   42: istore_3
    //   43: ldc 2
    //   45: ldc -35
    //   47: bipush 14
    //   49: iconst_3
    //   50: invokestatic 73	xxxxxx/uxxxxx:bb00620062bb0062b0062b0062	(Ljava/lang/String;CC)Ljava/lang/String;
    //   53: iconst_0
    //   54: anewarray 27	java/lang/Class
    //   57: invokevirtual 49	java/lang/Class:getMethod	(Ljava/lang/String;[Ljava/lang/Class;)Ljava/lang/reflect/Method;
    //   60: astore 4
    //   62: aload 4
    //   64: aconst_null
    //   65: iconst_0
    //   66: anewarray 51	java/lang/Object
    //   69: invokevirtual 57	java/lang/reflect/Method:invoke	(Ljava/lang/Object;[Ljava/lang/Object;)Ljava/lang/Object;
    //   72: astore 4
    //   74: iload_3
    //   75: iload_2
    //   76: iadd
    //   77: iload_2
    //   78: imul
    //   79: aload 4
    //   81: checkcast 59	java/lang/Integer
    //   84: invokevirtual 63	java/lang/Integer:intValue	()I
    //   87: irem
    //   88: tableswitch	default:+20->108, 0:+247->335
    //   108: bipush 66
    //   110: putstatic 35	uuuuuu/lklklk:b0062bbb0062b0062bb	I
    //   113: bipush 37
    //   115: putstatic 67	uuuuuu/lklklk:bbb0062b0062b0062bb	I
    //   118: getstatic 35	uuuuuu/lklklk:b0062bbb0062b0062bb	I
    //   121: istore_2
    //   122: ldc 2
    //   124: ldc -33
    //   126: bipush 78
    //   128: sipush 231
    //   131: iconst_2
    //   132: invokestatic 45	xxxxxx/uxxxxx:bbbb0062b0062b0062b0062	(Ljava/lang/String;CCC)Ljava/lang/String;
    //   135: iconst_0
    //   136: anewarray 27	java/lang/Class
    //   139: invokevirtual 49	java/lang/Class:getMethod	(Ljava/lang/String;[Ljava/lang/Class;)Ljava/lang/reflect/Method;
    //   142: astore 4
    //   144: aload 4
    //   146: aconst_null
    //   147: iconst_0
    //   148: anewarray 51	java/lang/Object
    //   151: invokevirtual 57	java/lang/reflect/Method:invoke	(Ljava/lang/Object;[Ljava/lang/Object;)Ljava/lang/Object;
    //   154: astore 4
    //   156: aload 4
    //   158: checkcast 59	java/lang/Integer
    //   161: invokevirtual 63	java/lang/Integer:intValue	()I
    //   164: iload_2
    //   165: iadd
    //   166: getstatic 35	uuuuuu/lklklk:b0062bbb0062b0062bb	I
    //   169: imul
    //   170: getstatic 65	uuuuuu/lklklk:b00620062bb0062b0062bb	I
    //   173: irem
    //   174: getstatic 67	uuuuuu/lklklk:bbb0062b0062b0062bb	I
    //   177: if_icmpeq +158 -> 335
    //   180: ldc 2
    //   182: ldc -31
    //   184: bipush 106
    //   186: sipush 231
    //   189: iconst_1
    //   190: invokestatic 45	xxxxxx/uxxxxx:bbbb0062b0062b0062b0062	(Ljava/lang/String;CCC)Ljava/lang/String;
    //   193: iconst_0
    //   194: anewarray 27	java/lang/Class
    //   197: invokevirtual 49	java/lang/Class:getMethod	(Ljava/lang/String;[Ljava/lang/Class;)Ljava/lang/reflect/Method;
    //   200: astore 4
    //   202: aload 4
    //   204: aconst_null
    //   205: iconst_0
    //   206: anewarray 51	java/lang/Object
    //   209: invokevirtual 57	java/lang/reflect/Method:invoke	(Ljava/lang/Object;[Ljava/lang/Object;)Ljava/lang/Object;
    //   212: astore 4
    //   214: aload 4
    //   216: checkcast 59	java/lang/Integer
    //   219: invokevirtual 63	java/lang/Integer:intValue	()I
    //   222: putstatic 35	uuuuuu/lklklk:b0062bbb0062b0062bb	I
    //   225: bipush 24
    //   227: putstatic 67	uuuuuu/lklklk:bbb0062b0062b0062bb	I
    //   230: getstatic 35	uuuuuu/lklklk:b0062bbb0062b0062bb	I
    //   233: getstatic 37	uuuuuu/lklklk:bb0062bb0062b0062bb	I
    //   236: iadd
    //   237: getstatic 35	uuuuuu/lklklk:b0062bbb0062b0062bb	I
    //   240: imul
    //   241: getstatic 65	uuuuuu/lklklk:b00620062bb0062b0062bb	I
    //   244: irem
    //   245: getstatic 67	uuuuuu/lklklk:bbb0062b0062b0062bb	I
    //   248: if_icmpeq +87 -> 335
    //   251: ldc 2
    //   253: ldc -29
    //   255: bipush 110
    //   257: iconst_3
    //   258: invokestatic 73	xxxxxx/uxxxxx:bb00620062bb0062b0062b0062	(Ljava/lang/String;CC)Ljava/lang/String;
    //   261: iconst_0
    //   262: anewarray 27	java/lang/Class
    //   265: invokevirtual 49	java/lang/Class:getMethod	(Ljava/lang/String;[Ljava/lang/Class;)Ljava/lang/reflect/Method;
    //   268: astore 4
    //   270: aload 4
    //   272: aconst_null
    //   273: iconst_0
    //   274: anewarray 51	java/lang/Object
    //   277: invokevirtual 57	java/lang/reflect/Method:invoke	(Ljava/lang/Object;[Ljava/lang/Object;)Ljava/lang/Object;
    //   280: astore 4
    //   282: aload 4
    //   284: checkcast 59	java/lang/Integer
    //   287: invokevirtual 63	java/lang/Integer:intValue	()I
    //   290: putstatic 35	uuuuuu/lklklk:b0062bbb0062b0062bb	I
    //   293: ldc 2
    //   295: ldc -65
    //   297: bipush 103
    //   299: iconst_5
    //   300: invokestatic 73	xxxxxx/uxxxxx:bb00620062bb0062b0062b0062	(Ljava/lang/String;CC)Ljava/lang/String;
    //   303: iconst_0
    //   304: anewarray 27	java/lang/Class
    //   307: invokevirtual 49	java/lang/Class:getMethod	(Ljava/lang/String;[Ljava/lang/Class;)Ljava/lang/reflect/Method;
    //   310: astore 4
    //   312: aload 4
    //   314: aconst_null
    //   315: iconst_0
    //   316: anewarray 51	java/lang/Object
    //   319: invokevirtual 57	java/lang/reflect/Method:invoke	(Ljava/lang/Object;[Ljava/lang/Object;)Ljava/lang/Object;
    //   322: astore 4
    //   324: aload 4
    //   326: checkcast 59	java/lang/Integer
    //   329: invokevirtual 63	java/lang/Integer:intValue	()I
    //   332: putstatic 67	uuuuuu/lklklk:bbb0062b0062b0062bb	I
    //   335: aload_1
    //   336: ifnull +237 -> 573
    //   339: aload_1
    //   340: iconst_0
    //   341: aload_1
    //   342: arraylength
    //   343: invokestatic 233	android/graphics/BitmapFactory:decodeByteArray	([BII)Landroid/graphics/Bitmap;
    //   346: astore_1
    //   347: getstatic 35	uuuuuu/lklklk:b0062bbb0062b0062bb	I
    //   350: istore_2
    //   351: iload_2
    //   352: getstatic 37	uuuuuu/lklklk:bb0062bb0062b0062bb	I
    //   355: iload_2
    //   356: iadd
    //   357: imul
    //   358: getstatic 65	uuuuuu/lklklk:b00620062bb0062b0062bb	I
    //   361: irem
    //   362: tableswitch	default:+18->380, 0:+66->428
    //   380: ldc 2
    //   382: ldc -21
    //   384: sipush 138
    //   387: iconst_2
    //   388: invokestatic 73	xxxxxx/uxxxxx:bb00620062bb0062b0062b0062	(Ljava/lang/String;CC)Ljava/lang/String;
    //   391: iconst_0
    //   392: anewarray 27	java/lang/Class
    //   395: invokevirtual 49	java/lang/Class:getMethod	(Ljava/lang/String;[Ljava/lang/Class;)Ljava/lang/reflect/Method;
    //   398: astore 4
    //   400: aload 4
    //   402: aconst_null
    //   403: iconst_0
    //   404: anewarray 51	java/lang/Object
    //   407: invokevirtual 57	java/lang/reflect/Method:invoke	(Ljava/lang/Object;[Ljava/lang/Object;)Ljava/lang/Object;
    //   410: astore 4
    //   412: aload 4
    //   414: checkcast 59	java/lang/Integer
    //   417: invokevirtual 63	java/lang/Integer:intValue	()I
    //   420: putstatic 35	uuuuuu/lklklk:b0062bbb0062b0062bb	I
    //   423: bipush 14
    //   425: putstatic 67	uuuuuu/lklklk:bbb0062b0062b0062bb	I
    //   428: aload_1
    //   429: areturn
    //   430: astore_1
    //   431: getstatic 33	uuuuuu/lklklk:bb006200620062bb0062bb	Ljava/lang/String;
    //   434: astore 4
    //   436: ldc -19
    //   438: ldc -17
    //   440: bipush 33
    //   442: iconst_1
    //   443: invokestatic 73	xxxxxx/uxxxxx:bb00620062bb0062b0062b0062	(Ljava/lang/String;CC)Ljava/lang/String;
    //   446: iconst_4
    //   447: anewarray 27	java/lang/Class
    //   450: dup
    //   451: iconst_0
    //   452: ldc -15
    //   454: aastore
    //   455: dup
    //   456: iconst_1
    //   457: getstatic 247	java/lang/Character:TYPE	Ljava/lang/Class;
    //   460: aastore
    //   461: dup
    //   462: iconst_2
    //   463: getstatic 247	java/lang/Character:TYPE	Ljava/lang/Class;
    //   466: aastore
    //   467: dup
    //   468: iconst_3
    //   469: getstatic 247	java/lang/Character:TYPE	Ljava/lang/Class;
    //   472: aastore
    //   473: invokevirtual 49	java/lang/Class:getMethod	(Ljava/lang/String;[Ljava/lang/Class;)Ljava/lang/reflect/Method;
    //   476: astore 5
    //   478: aload 5
    //   480: aconst_null
    //   481: iconst_4
    //   482: anewarray 51	java/lang/Object
    //   485: dup
    //   486: iconst_0
    //   487: ldc -7
    //   489: aastore
    //   490: dup
    //   491: iconst_1
    //   492: bipush 43
    //   494: invokestatic 253	java/lang/Character:valueOf	(C)Ljava/lang/Character;
    //   497: aastore
    //   498: dup
    //   499: iconst_2
    //   500: bipush 58
    //   502: invokestatic 253	java/lang/Character:valueOf	(C)Ljava/lang/Character;
    //   505: aastore
    //   506: dup
    //   507: iconst_3
    //   508: iconst_2
    //   509: invokestatic 253	java/lang/Character:valueOf	(C)Ljava/lang/Character;
    //   512: aastore
    //   513: invokevirtual 57	java/lang/reflect/Method:invoke	(Ljava/lang/Object;[Ljava/lang/Object;)Ljava/lang/Object;
    //   516: astore 5
    //   518: aload 4
    //   520: aload 5
    //   522: checkcast 241	java/lang/String
    //   525: aload_1
    //   526: invokestatic 259	uuuuuu/rvvvrv:b00710071qq00710071q0071q0071	(Ljava/lang/String;Ljava/lang/String;Ljava/lang/Throwable;)V
    //   529: aconst_null
    //   530: areturn
    //   531: astore_1
    //   532: aload_1
    //   533: invokevirtual 87	java/lang/reflect/InvocationTargetException:getCause	()Ljava/lang/Throwable;
    //   536: athrow
    //   537: astore_1
    //   538: aload_1
    //   539: invokevirtual 87	java/lang/reflect/InvocationTargetException:getCause	()Ljava/lang/Throwable;
    //   542: athrow
    //   543: astore_1
    //   544: aload_1
    //   545: invokevirtual 87	java/lang/reflect/InvocationTargetException:getCause	()Ljava/lang/Throwable;
    //   548: athrow
    //   549: astore_1
    //   550: aload_1
    //   551: invokevirtual 87	java/lang/reflect/InvocationTargetException:getCause	()Ljava/lang/Throwable;
    //   554: athrow
    //   555: astore_1
    //   556: aload_1
    //   557: invokevirtual 87	java/lang/reflect/InvocationTargetException:getCause	()Ljava/lang/Throwable;
    //   560: athrow
    //   561: astore_1
    //   562: aload_1
    //   563: invokevirtual 87	java/lang/reflect/InvocationTargetException:getCause	()Ljava/lang/Throwable;
    //   566: athrow
    //   567: astore_1
    //   568: aload_1
    //   569: invokevirtual 87	java/lang/reflect/InvocationTargetException:getCause	()Ljava/lang/Throwable;
    //   572: athrow
    //   573: aconst_null
    //   574: areturn
    // Local variable table:
    //   start	length	slot	name	signature
    //   0	575	0	this	lklklk
    //   0	575	1	paramChallengeResponse	com.db.pwcc.dbmobile.model.tan.ChallengeResponse
    //   38	320	2	i	int
    //   42	35	3	j	int
    //   60	459	4	localObject1	Object
    //   476	45	5	localObject2	Object
    // Exception table:
    //   from	to	target	type
    //   23	35	430	java/lang/IllegalArgumentException
    //   339	347	430	java/lang/IllegalArgumentException
    //   478	518	531	java/lang/reflect/InvocationTargetException
    //   144	156	537	java/lang/reflect/InvocationTargetException
    //   62	74	543	java/lang/reflect/InvocationTargetException
    //   400	412	549	java/lang/reflect/InvocationTargetException
    //   202	214	555	java/lang/reflect/InvocationTargetException
    //   270	282	561	java/lang/reflect/InvocationTargetException
    //   312	324	567	java/lang/reflect/InvocationTargetException
  }
}
