package uuuuuu;

import android.text.TextWatcher;
import android.widget.EditText;
import java.util.regex.Pattern;

public class llvlvv
  implements TextWatcher
{
  public static int b006F006Foo006F006Fo006F006F = 0;
  public static int b006Fo006Fo006F006Fo006F006F = 1;
  public static int bo006Foo006F006Fo006F006F = 28;
  public static int boo006Fo006F006Fo006F006F = 2;
  private String b006F006F006F006Fo006Fo006F006F;
  private EditText b006F006Fo006Fo006Fo006F006F;
  private Pattern b006Fo006F006Fo006Fo006F006F;
  private int b006Fooo006F006Fo006F006F;
  private boolean bo006F006F006Fo006Fo006F006F;
  private int boo006F006Fo006Fo006F006F;
  private String boooo006F006Fo006F006F;
  
  public llvlvv(EditText paramEditText, String paramString, boolean paramBoolean)
  {
    this.b006F006Fo006Fo006Fo006F006F = paramEditText;
    this.boooo006F006Fo006F006F = paramString;
    this.b006Fo006F006Fo006Fo006F006F = Pattern.compile(paramString);
    this.bo006F006F006Fo006Fo006F006F = paramBoolean;
  }
  
  public static int b0069i0069ii0069i006900690069()
  {
    return 93;
  }
  
  public static int bii0069ii0069i006900690069()
  {
    return 1;
  }
  
  /* Error */
  public void afterTextChanged(android.text.Editable paramEditable)
  {
    // Byte code:
    //   0: aload_1
    //   1: invokevirtual 59	java/lang/Object:toString	()Ljava/lang/String;
    //   4: astore_1
    //   5: ldc 61
    //   7: ldc 63
    //   9: sipush 206
    //   12: sipush 254
    //   15: iconst_0
    //   16: invokestatic 69	xxxxxx/uxxxxx:bbbb0062b0062b0062b0062	(Ljava/lang/String;CCC)Ljava/lang/String;
    //   19: iconst_4
    //   20: anewarray 71	java/lang/Class
    //   23: dup
    //   24: iconst_0
    //   25: ldc 73
    //   27: aastore
    //   28: dup
    //   29: iconst_1
    //   30: getstatic 79	java/lang/Character:TYPE	Ljava/lang/Class;
    //   33: aastore
    //   34: dup
    //   35: iconst_2
    //   36: getstatic 79	java/lang/Character:TYPE	Ljava/lang/Class;
    //   39: aastore
    //   40: dup
    //   41: iconst_3
    //   42: getstatic 79	java/lang/Character:TYPE	Ljava/lang/Class;
    //   45: aastore
    //   46: invokevirtual 83	java/lang/Class:getMethod	(Ljava/lang/String;[Ljava/lang/Class;)Ljava/lang/reflect/Method;
    //   49: astore_3
    //   50: aload_3
    //   51: aconst_null
    //   52: iconst_4
    //   53: anewarray 4	java/lang/Object
    //   56: dup
    //   57: iconst_0
    //   58: ldc 85
    //   60: aastore
    //   61: dup
    //   62: iconst_1
    //   63: bipush 62
    //   65: invokestatic 89	java/lang/Character:valueOf	(C)Ljava/lang/Character;
    //   68: aastore
    //   69: dup
    //   70: iconst_2
    //   71: sipush 151
    //   74: invokestatic 89	java/lang/Character:valueOf	(C)Ljava/lang/Character;
    //   77: aastore
    //   78: dup
    //   79: iconst_3
    //   80: iconst_3
    //   81: invokestatic 89	java/lang/Character:valueOf	(C)Ljava/lang/Character;
    //   84: aastore
    //   85: invokevirtual 95	java/lang/reflect/Method:invoke	(Ljava/lang/Object;[Ljava/lang/Object;)Ljava/lang/Object;
    //   88: astore_3
    //   89: aload_1
    //   90: aload_3
    //   91: checkcast 73	java/lang/String
    //   94: ldc 97
    //   96: invokevirtual 101	java/lang/String:replaceAll	(Ljava/lang/String;Ljava/lang/String;)Ljava/lang/String;
    //   99: astore_3
    //   100: aload_0
    //   101: getfield 103	uuuuuu/llvlvv:b006F006F006F006Fo006Fo006F006F	Ljava/lang/String;
    //   104: astore 4
    //   106: ldc 61
    //   108: ldc 105
    //   110: sipush 187
    //   113: bipush 35
    //   115: iconst_2
    //   116: invokestatic 69	xxxxxx/uxxxxx:bbbb0062b0062b0062b0062	(Ljava/lang/String;CCC)Ljava/lang/String;
    //   119: iconst_4
    //   120: anewarray 71	java/lang/Class
    //   123: dup
    //   124: iconst_0
    //   125: ldc 73
    //   127: aastore
    //   128: dup
    //   129: iconst_1
    //   130: getstatic 79	java/lang/Character:TYPE	Ljava/lang/Class;
    //   133: aastore
    //   134: dup
    //   135: iconst_2
    //   136: getstatic 79	java/lang/Character:TYPE	Ljava/lang/Class;
    //   139: aastore
    //   140: dup
    //   141: iconst_3
    //   142: getstatic 79	java/lang/Character:TYPE	Ljava/lang/Class;
    //   145: aastore
    //   146: invokevirtual 83	java/lang/Class:getMethod	(Ljava/lang/String;[Ljava/lang/Class;)Ljava/lang/reflect/Method;
    //   149: astore 5
    //   151: aload 5
    //   153: aconst_null
    //   154: iconst_4
    //   155: anewarray 4	java/lang/Object
    //   158: dup
    //   159: iconst_0
    //   160: ldc 107
    //   162: aastore
    //   163: dup
    //   164: iconst_1
    //   165: bipush 27
    //   167: invokestatic 89	java/lang/Character:valueOf	(C)Ljava/lang/Character;
    //   170: aastore
    //   171: dup
    //   172: iconst_2
    //   173: bipush 105
    //   175: invokestatic 89	java/lang/Character:valueOf	(C)Ljava/lang/Character;
    //   178: aastore
    //   179: dup
    //   180: iconst_3
    //   181: iconst_0
    //   182: invokestatic 89	java/lang/Character:valueOf	(C)Ljava/lang/Character;
    //   185: aastore
    //   186: invokevirtual 95	java/lang/reflect/Method:invoke	(Ljava/lang/Object;[Ljava/lang/Object;)Ljava/lang/Object;
    //   189: astore 5
    //   191: aload_3
    //   192: aload 4
    //   194: aload 5
    //   196: checkcast 73	java/lang/String
    //   199: ldc 97
    //   201: invokevirtual 101	java/lang/String:replaceAll	(Ljava/lang/String;Ljava/lang/String;)Ljava/lang/String;
    //   204: invokevirtual 111	java/lang/String:equalsIgnoreCase	(Ljava/lang/String;)Z
    //   207: ifeq +95 -> 302
    //   210: return
    //   211: aload_0
    //   212: getfield 33	uuuuuu/llvlvv:b006F006Fo006Fo006Fo006F006F	Landroid/widget/EditText;
    //   215: aload_0
    //   216: getfield 103	uuuuuu/llvlvv:b006F006F006F006Fo006Fo006F006F	Ljava/lang/String;
    //   219: invokevirtual 117	android/widget/EditText:setText	(Ljava/lang/CharSequence;)V
    //   222: aload_0
    //   223: getfield 33	uuuuuu/llvlvv:b006F006Fo006Fo006Fo006F006F	Landroid/widget/EditText;
    //   226: astore_1
    //   227: getstatic 119	uuuuuu/llvlvv:bo006Foo006F006Fo006F006F	I
    //   230: invokestatic 121	uuuuuu/llvlvv:bii0069ii0069i006900690069	()I
    //   233: iadd
    //   234: getstatic 119	uuuuuu/llvlvv:bo006Foo006F006Fo006F006F	I
    //   237: imul
    //   238: getstatic 123	uuuuuu/llvlvv:boo006Fo006F006Fo006F006F	I
    //   241: irem
    //   242: getstatic 125	uuuuuu/llvlvv:b006F006Foo006F006Fo006F006F	I
    //   245: if_icmpeq +45 -> 290
    //   248: getstatic 119	uuuuuu/llvlvv:bo006Foo006F006Fo006F006F	I
    //   251: getstatic 127	uuuuuu/llvlvv:b006Fo006Fo006F006Fo006F006F	I
    //   254: iadd
    //   255: getstatic 119	uuuuuu/llvlvv:bo006Foo006F006Fo006F006F	I
    //   258: imul
    //   259: getstatic 123	uuuuuu/llvlvv:boo006Fo006F006Fo006F006F	I
    //   262: irem
    //   263: getstatic 125	uuuuuu/llvlvv:b006F006Foo006F006Fo006F006F	I
    //   266: if_icmpeq +14 -> 280
    //   269: bipush 14
    //   271: putstatic 119	uuuuuu/llvlvv:bo006Foo006F006Fo006F006F	I
    //   274: invokestatic 129	uuuuuu/llvlvv:b0069i0069ii0069i006900690069	()I
    //   277: putstatic 125	uuuuuu/llvlvv:b006F006Foo006F006Fo006F006F	I
    //   280: bipush 90
    //   282: putstatic 119	uuuuuu/llvlvv:bo006Foo006F006Fo006F006F	I
    //   285: bipush 88
    //   287: putstatic 125	uuuuuu/llvlvv:b006F006Foo006F006Fo006F006F	I
    //   290: aload_1
    //   291: aload_0
    //   292: getfield 103	uuuuuu/llvlvv:b006F006F006F006Fo006Fo006F006F	Ljava/lang/String;
    //   295: invokevirtual 132	java/lang/String:length	()I
    //   298: invokevirtual 136	android/widget/EditText:setSelection	(I)V
    //   301: return
    //   302: aload_0
    //   303: getfield 138	uuuuuu/llvlvv:boo006F006Fo006Fo006F006F	I
    //   306: ifle +242 -> 548
    //   309: aload_1
    //   310: aload_0
    //   311: getfield 140	uuuuuu/llvlvv:b006Fooo006F006Fo006F006F	I
    //   314: aload_0
    //   315: getfield 140	uuuuuu/llvlvv:b006Fooo006F006Fo006F006F	I
    //   318: aload_0
    //   319: getfield 138	uuuuuu/llvlvv:boo006F006Fo006Fo006F006F	I
    //   322: iadd
    //   323: invokevirtual 144	java/lang/String:subSequence	(II)Ljava/lang/CharSequence;
    //   326: invokeinterface 147 1 0
    //   331: astore_1
    //   332: ldc 61
    //   334: ldc -107
    //   336: bipush 93
    //   338: sipush 143
    //   341: iconst_2
    //   342: invokestatic 69	xxxxxx/uxxxxx:bbbb0062b0062b0062b0062	(Ljava/lang/String;CCC)Ljava/lang/String;
    //   345: iconst_4
    //   346: anewarray 71	java/lang/Class
    //   349: dup
    //   350: iconst_0
    //   351: ldc 73
    //   353: aastore
    //   354: dup
    //   355: iconst_1
    //   356: getstatic 79	java/lang/Character:TYPE	Ljava/lang/Class;
    //   359: aastore
    //   360: dup
    //   361: iconst_2
    //   362: getstatic 79	java/lang/Character:TYPE	Ljava/lang/Class;
    //   365: aastore
    //   366: dup
    //   367: iconst_3
    //   368: getstatic 79	java/lang/Character:TYPE	Ljava/lang/Class;
    //   371: aastore
    //   372: invokevirtual 83	java/lang/Class:getMethod	(Ljava/lang/String;[Ljava/lang/Class;)Ljava/lang/reflect/Method;
    //   375: astore_3
    //   376: aload_3
    //   377: aconst_null
    //   378: iconst_4
    //   379: anewarray 4	java/lang/Object
    //   382: dup
    //   383: iconst_0
    //   384: ldc -105
    //   386: aastore
    //   387: dup
    //   388: iconst_1
    //   389: bipush 9
    //   391: invokestatic 89	java/lang/Character:valueOf	(C)Ljava/lang/Character;
    //   394: aastore
    //   395: dup
    //   396: iconst_2
    //   397: iconst_3
    //   398: invokestatic 89	java/lang/Character:valueOf	(C)Ljava/lang/Character;
    //   401: aastore
    //   402: dup
    //   403: iconst_3
    //   404: iconst_2
    //   405: invokestatic 89	java/lang/Character:valueOf	(C)Ljava/lang/Character;
    //   408: aastore
    //   409: invokevirtual 95	java/lang/reflect/Method:invoke	(Ljava/lang/Object;[Ljava/lang/Object;)Ljava/lang/Object;
    //   412: astore_3
    //   413: aload_1
    //   414: aload_3
    //   415: checkcast 73	java/lang/String
    //   418: ldc 97
    //   420: invokevirtual 101	java/lang/String:replaceAll	(Ljava/lang/String;Ljava/lang/String;)Ljava/lang/String;
    //   423: astore 4
    //   425: aload_0
    //   426: getfield 43	uuuuuu/llvlvv:b006Fo006F006Fo006Fo006F006F	Ljava/util/regex/Pattern;
    //   429: aload 4
    //   431: invokevirtual 155	java/util/regex/Pattern:matcher	(Ljava/lang/CharSequence;)Ljava/util/regex/Matcher;
    //   434: invokevirtual 161	java/util/regex/Matcher:matches	()Z
    //   437: ifne -227 -> 210
    //   440: aload_0
    //   441: getfield 103	uuuuuu/llvlvv:b006F006F006F006Fo006Fo006F006F	Ljava/lang/String;
    //   444: astore_3
    //   445: aload_3
    //   446: astore_1
    //   447: aload_0
    //   448: getfield 45	uuuuuu/llvlvv:bo006F006F006Fo006Fo006F006F	Z
    //   451: ifeq +30 -> 481
    //   454: new 163	java/lang/StringBuilder
    //   457: dup
    //   458: invokespecial 164	java/lang/StringBuilder:<init>	()V
    //   461: aload_3
    //   462: invokevirtual 168	java/lang/StringBuilder:append	(Ljava/lang/String;)Ljava/lang/StringBuilder;
    //   465: aload 4
    //   467: aload_0
    //   468: getfield 35	uuuuuu/llvlvv:boooo006F006Fo006F006F	Ljava/lang/String;
    //   471: invokestatic 173	uuuuuu/sxsxsx:b006B006B006B006B006Bkk006B006B006B	(Ljava/lang/String;Ljava/lang/String;)Ljava/lang/String;
    //   474: invokevirtual 168	java/lang/StringBuilder:append	(Ljava/lang/String;)Ljava/lang/StringBuilder;
    //   477: invokevirtual 174	java/lang/StringBuilder:toString	()Ljava/lang/String;
    //   480: astore_1
    //   481: aload_0
    //   482: getfield 33	uuuuuu/llvlvv:b006F006Fo006Fo006Fo006F006F	Landroid/widget/EditText;
    //   485: aload_1
    //   486: invokevirtual 117	android/widget/EditText:setText	(Ljava/lang/CharSequence;)V
    //   489: aload_0
    //   490: getfield 33	uuuuuu/llvlvv:b006F006Fo006Fo006Fo006F006F	Landroid/widget/EditText;
    //   493: aload_1
    //   494: invokevirtual 132	java/lang/String:length	()I
    //   497: invokevirtual 136	android/widget/EditText:setSelection	(I)V
    //   500: return
    //   501: astore_3
    //   502: aload_0
    //   503: getfield 33	uuuuuu/llvlvv:b006F006Fo006Fo006Fo006F006F	Landroid/widget/EditText;
    //   506: astore_3
    //   507: getstatic 119	uuuuuu/llvlvv:bo006Foo006F006Fo006F006F	I
    //   510: getstatic 127	uuuuuu/llvlvv:b006Fo006Fo006F006Fo006F006F	I
    //   513: iadd
    //   514: getstatic 119	uuuuuu/llvlvv:bo006Foo006F006Fo006F006F	I
    //   517: imul
    //   518: getstatic 123	uuuuuu/llvlvv:boo006Fo006F006Fo006F006F	I
    //   521: irem
    //   522: getstatic 125	uuuuuu/llvlvv:b006F006Foo006F006Fo006F006F	I
    //   525: if_icmpeq +14 -> 539
    //   528: bipush 28
    //   530: putstatic 119	uuuuuu/llvlvv:bo006Foo006F006Fo006F006F	I
    //   533: invokestatic 129	uuuuuu/llvlvv:b0069i0069ii0069i006900690069	()I
    //   536: putstatic 125	uuuuuu/llvlvv:b006F006Foo006F006Fo006F006F	I
    //   539: aload_3
    //   540: aload_1
    //   541: invokevirtual 132	java/lang/String:length	()I
    //   544: invokevirtual 136	android/widget/EditText:setSelection	(I)V
    //   547: return
    //   548: aload_0
    //   549: getfield 140	uuuuuu/llvlvv:b006Fooo006F006Fo006F006F	I
    //   552: aload_0
    //   553: getfield 138	uuuuuu/llvlvv:boo006F006Fo006Fo006F006F	I
    //   556: iadd
    //   557: ifle -347 -> 210
    //   560: aload_0
    //   561: getfield 43	uuuuuu/llvlvv:b006Fo006F006Fo006Fo006F006F	Ljava/util/regex/Pattern;
    //   564: aload_1
    //   565: invokevirtual 155	java/util/regex/Pattern:matcher	(Ljava/lang/CharSequence;)Ljava/util/regex/Matcher;
    //   568: invokevirtual 161	java/util/regex/Matcher:matches	()Z
    //   571: ifne -361 -> 210
    //   574: aload_0
    //   575: getfield 45	uuuuuu/llvlvv:bo006F006F006Fo006Fo006F006F	Z
    //   578: ifeq -367 -> 211
    //   581: aload_1
    //   582: aload_0
    //   583: getfield 35	uuuuuu/llvlvv:boooo006F006Fo006F006F	Ljava/lang/String;
    //   586: invokestatic 173	uuuuuu/sxsxsx:b006B006B006B006B006Bkk006B006B006B	(Ljava/lang/String;Ljava/lang/String;)Ljava/lang/String;
    //   589: astore_1
    //   590: aload_0
    //   591: getfield 33	uuuuuu/llvlvv:b006F006Fo006Fo006Fo006F006F	Landroid/widget/EditText;
    //   594: aload_1
    //   595: invokevirtual 117	android/widget/EditText:setText	(Ljava/lang/CharSequence;)V
    //   598: iconst_4
    //   599: istore_2
    //   600: iload_2
    //   601: iconst_0
    //   602: idiv
    //   603: istore_2
    //   604: goto -4 -> 600
    //   607: astore_1
    //   608: aload_1
    //   609: invokevirtual 178	java/lang/reflect/InvocationTargetException:getCause	()Ljava/lang/Throwable;
    //   612: athrow
    //   613: astore_1
    //   614: aload_1
    //   615: invokevirtual 178	java/lang/reflect/InvocationTargetException:getCause	()Ljava/lang/Throwable;
    //   618: athrow
    //   619: astore_1
    //   620: aload_1
    //   621: invokevirtual 178	java/lang/reflect/InvocationTargetException:getCause	()Ljava/lang/Throwable;
    //   624: athrow
    // Local variable table:
    //   start	length	slot	name	signature
    //   0	625	0	this	llvlvv
    //   0	625	1	paramEditable	android.text.Editable
    //   599	5	2	i	int
    //   49	413	3	localObject1	Object
    //   501	1	3	localException	Exception
    //   506	34	3	localEditText	EditText
    //   104	362	4	str	String
    //   149	46	5	localObject2	Object
    // Exception table:
    //   from	to	target	type
    //   600	604	501	java/lang/Exception
    //   50	89	607	java/lang/reflect/InvocationTargetException
    //   376	413	613	java/lang/reflect/InvocationTargetException
    //   151	191	619	java/lang/reflect/InvocationTargetException
  }
  
  public void beforeTextChanged(CharSequence paramCharSequence, int paramInt1, int paramInt2, int paramInt3)
  {
    if ((bo006Foo006F006Fo006F006F + b006Fo006Fo006F006Fo006F006F) * bo006Foo006F006Fo006F006F % boo006Fo006F006Fo006F006F != b006F006Foo006F006Fo006F006F)
    {
      int i = bo006Foo006F006Fo006F006F;
      switch (i * (b006Fo006Fo006F006Fo006F006F + i) % boo006Fo006F006Fo006F006F)
      {
      default: 
        bo006Foo006F006Fo006F006F = b0069i0069ii0069i006900690069();
        b006F006Foo006F006Fo006F006F = 38;
      }
      if ((bo006Foo006F006Fo006F006F + b006Fo006Fo006F006Fo006F006F) * bo006Foo006F006Fo006F006F % boo006Fo006F006Fo006F006F != b006F006Foo006F006Fo006F006F)
      {
        bo006Foo006F006Fo006F006F = 85;
        b006F006Foo006F006Fo006F006F = b0069i0069ii0069i006900690069();
      }
      bo006Foo006F006Fo006F006F = 14;
      b006F006Foo006F006Fo006F006F = b0069i0069ii0069i006900690069();
    }
    paramCharSequence = paramCharSequence.toString();
    if ((bo006Foo006F006Fo006F006F + bii0069ii0069i006900690069()) * bo006Foo006F006Fo006F006F % boo006Fo006F006Fo006F006F != b006F006Foo006F006Fo006F006F)
    {
      bo006Foo006F006Fo006F006F = 70;
      b006F006Foo006F006Fo006F006F = b0069i0069ii0069i006900690069();
    }
    this.b006F006F006F006Fo006Fo006F006F = paramCharSequence;
    this.b006Fooo006F006Fo006F006F = (paramInt1 + paramInt2);
    this.boo006F006Fo006Fo006F006F = (paramInt3 - paramInt2);
  }
  
  public void onTextChanged(CharSequence paramCharSequence, int paramInt1, int paramInt2, int paramInt3) {}
}
