package uuuuuu;

import java.lang.reflect.InvocationTargetException;
import java.lang.reflect.Method;
import xxxxxx.uxxxxx;

public class lqlqll
  extends lqqlll
  implements qqllll.llqlll
{
  public static int b00700070pp00700070pp0070 = 2;
  public static int b0070ppp00700070pp0070 = 19;
  public static int bp0070pp00700070pp0070 = 1;
  public static int bpp0070p00700070pp0070;
  private sxxxsx b0070007000700070p0070pp0070;
  public String b0070p00700070p0070pp0070;
  public boolean bp007000700070p0070pp0070;
  public sxxxsx.xsxsxx bpppp00700070pp0070;
  
  public lqlqll(qqllll.qlqlll paramQlqlll)
  {
    super(paramQlqlll);
    this.bnnnnn006E006E006En = paramQlqlll;
    this.b0070007000700070p0070pp0070 = new sxxxsx();
    paramQlqlll = lqlqll.class.getDeclaredMethod(uxxxxx.bb00620062bb0062b0062b0062("iu549Hpon.-2Ai)(-<dc", '(', '\005'), new Class[0]);
    try
    {
      paramQlqlll.invoke(this, new Object[0]);
      return;
    }
    catch (InvocationTargetException paramQlqlll)
    {
      throw paramQlqlll.getCause();
    }
  }
  
  public static int b006F006F006F006F006Foo006Foo()
  {
    return 2;
  }
  
  public static int b006Foooo006Fo006Foo()
  {
    return 0;
  }
  
  /* Error */
  private void bo006Fooo006Fo006Foo()
  {
    // Byte code:
    //   0: getstatic 73	uuuuuu/lqlqll:b0070ppp00700070pp0070	I
    //   3: istore_1
    //   4: iload_1
    //   5: getstatic 75	uuuuuu/lqlqll:bp0070pp00700070pp0070	I
    //   8: iload_1
    //   9: iadd
    //   10: imul
    //   11: getstatic 77	uuuuuu/lqlqll:b00700070pp00700070pp0070	I
    //   14: irem
    //   15: tableswitch	default:+17->32, 0:+373->388
    //   32: bipush 33
    //   34: putstatic 73	uuuuuu/lqlqll:b0070ppp00700070pp0070	I
    //   37: bipush 90
    //   39: putstatic 79	uuuuuu/lqlqll:bpp0070p00700070pp0070	I
    //   42: getstatic 73	uuuuuu/lqlqll:b0070ppp00700070pp0070	I
    //   45: istore_1
    //   46: getstatic 75	uuuuuu/lqlqll:bp0070pp00700070pp0070	I
    //   49: istore_2
    //   50: getstatic 73	uuuuuu/lqlqll:b0070ppp00700070pp0070	I
    //   53: istore_3
    //   54: ldc 2
    //   56: ldc 102
    //   58: bipush 86
    //   60: iconst_4
    //   61: invokestatic 47	xxxxxx/uxxxxx:bb00620062bb0062b0062b0062	(Ljava/lang/String;CC)Ljava/lang/String;
    //   64: iconst_0
    //   65: anewarray 49	java/lang/Class
    //   68: invokevirtual 84	java/lang/Class:getMethod	(Ljava/lang/String;[Ljava/lang/Class;)Ljava/lang/reflect/Method;
    //   71: astore 4
    //   73: aload 4
    //   75: aconst_null
    //   76: iconst_0
    //   77: anewarray 55	java/lang/Object
    //   80: invokevirtual 61	java/lang/reflect/Method:invoke	(Ljava/lang/Object;[Ljava/lang/Object;)Ljava/lang/Object;
    //   83: astore 4
    //   85: iload_3
    //   86: iload_1
    //   87: iload_2
    //   88: iadd
    //   89: imul
    //   90: aload 4
    //   92: checkcast 86	java/lang/Integer
    //   95: invokevirtual 89	java/lang/Integer:intValue	()I
    //   98: irem
    //   99: getstatic 79	uuuuuu/lqlqll:bpp0070p00700070pp0070	I
    //   102: if_icmpeq +286 -> 388
    //   105: getstatic 73	uuuuuu/lqlqll:b0070ppp00700070pp0070	I
    //   108: istore_1
    //   109: getstatic 75	uuuuuu/lqlqll:bp0070pp00700070pp0070	I
    //   112: istore_2
    //   113: getstatic 73	uuuuuu/lqlqll:b0070ppp00700070pp0070	I
    //   116: getstatic 75	uuuuuu/lqlqll:bp0070pp00700070pp0070	I
    //   119: iadd
    //   120: getstatic 73	uuuuuu/lqlqll:b0070ppp00700070pp0070	I
    //   123: imul
    //   124: getstatic 77	uuuuuu/lqlqll:b00700070pp00700070pp0070	I
    //   127: irem
    //   128: getstatic 79	uuuuuu/lqlqll:bpp0070p00700070pp0070	I
    //   131: if_icmpeq +90 -> 221
    //   134: ldc 2
    //   136: ldc 104
    //   138: bipush 126
    //   140: sipush 175
    //   143: iconst_0
    //   144: invokestatic 97	xxxxxx/uxxxxx:bbbb0062b0062b0062b0062	(Ljava/lang/String;CCC)Ljava/lang/String;
    //   147: iconst_0
    //   148: anewarray 49	java/lang/Class
    //   151: invokevirtual 84	java/lang/Class:getMethod	(Ljava/lang/String;[Ljava/lang/Class;)Ljava/lang/reflect/Method;
    //   154: astore 4
    //   156: aload 4
    //   158: aconst_null
    //   159: iconst_0
    //   160: anewarray 55	java/lang/Object
    //   163: invokevirtual 61	java/lang/reflect/Method:invoke	(Ljava/lang/Object;[Ljava/lang/Object;)Ljava/lang/Object;
    //   166: astore 4
    //   168: aload 4
    //   170: checkcast 86	java/lang/Integer
    //   173: invokevirtual 89	java/lang/Integer:intValue	()I
    //   176: putstatic 73	uuuuuu/lqlqll:b0070ppp00700070pp0070	I
    //   179: ldc 2
    //   181: ldc 106
    //   183: bipush 34
    //   185: iconst_0
    //   186: invokestatic 47	xxxxxx/uxxxxx:bb00620062bb0062b0062b0062	(Ljava/lang/String;CC)Ljava/lang/String;
    //   189: iconst_0
    //   190: anewarray 49	java/lang/Class
    //   193: invokevirtual 84	java/lang/Class:getMethod	(Ljava/lang/String;[Ljava/lang/Class;)Ljava/lang/reflect/Method;
    //   196: astore 4
    //   198: aload 4
    //   200: aconst_null
    //   201: iconst_0
    //   202: anewarray 55	java/lang/Object
    //   205: invokevirtual 61	java/lang/reflect/Method:invoke	(Ljava/lang/Object;[Ljava/lang/Object;)Ljava/lang/Object;
    //   208: astore 4
    //   210: aload 4
    //   212: checkcast 86	java/lang/Integer
    //   215: invokevirtual 89	java/lang/Integer:intValue	()I
    //   218: putstatic 79	uuuuuu/lqlqll:bpp0070p00700070pp0070	I
    //   221: iload_2
    //   222: iload_1
    //   223: iadd
    //   224: iload_1
    //   225: imul
    //   226: getstatic 77	uuuuuu/lqlqll:b00700070pp00700070pp0070	I
    //   229: irem
    //   230: tableswitch	default:+18->248, 0:+108->338
    //   248: ldc 2
    //   250: ldc 108
    //   252: sipush 199
    //   255: bipush 63
    //   257: iconst_3
    //   258: invokestatic 97	xxxxxx/uxxxxx:bbbb0062b0062b0062b0062	(Ljava/lang/String;CCC)Ljava/lang/String;
    //   261: iconst_0
    //   262: anewarray 49	java/lang/Class
    //   265: invokevirtual 84	java/lang/Class:getMethod	(Ljava/lang/String;[Ljava/lang/Class;)Ljava/lang/reflect/Method;
    //   268: astore 4
    //   270: aload 4
    //   272: aconst_null
    //   273: iconst_0
    //   274: anewarray 55	java/lang/Object
    //   277: invokevirtual 61	java/lang/reflect/Method:invoke	(Ljava/lang/Object;[Ljava/lang/Object;)Ljava/lang/Object;
    //   280: astore 4
    //   282: aload 4
    //   284: checkcast 86	java/lang/Integer
    //   287: invokevirtual 89	java/lang/Integer:intValue	()I
    //   290: putstatic 73	uuuuuu/lqlqll:b0070ppp00700070pp0070	I
    //   293: ldc 2
    //   295: ldc 110
    //   297: sipush 133
    //   300: bipush 69
    //   302: iconst_0
    //   303: invokestatic 97	xxxxxx/uxxxxx:bbbb0062b0062b0062b0062	(Ljava/lang/String;CCC)Ljava/lang/String;
    //   306: iconst_0
    //   307: anewarray 49	java/lang/Class
    //   310: invokevirtual 84	java/lang/Class:getMethod	(Ljava/lang/String;[Ljava/lang/Class;)Ljava/lang/reflect/Method;
    //   313: astore 4
    //   315: aload 4
    //   317: aconst_null
    //   318: iconst_0
    //   319: anewarray 55	java/lang/Object
    //   322: invokevirtual 61	java/lang/reflect/Method:invoke	(Ljava/lang/Object;[Ljava/lang/Object;)Ljava/lang/Object;
    //   325: astore 4
    //   327: aload 4
    //   329: checkcast 86	java/lang/Integer
    //   332: invokevirtual 89	java/lang/Integer:intValue	()I
    //   335: putstatic 79	uuuuuu/lqlqll:bpp0070p00700070pp0070	I
    //   338: bipush 17
    //   340: putstatic 73	uuuuuu/lqlqll:b0070ppp00700070pp0070	I
    //   343: ldc 2
    //   345: ldc 112
    //   347: sipush 211
    //   350: bipush 103
    //   352: iconst_1
    //   353: invokestatic 97	xxxxxx/uxxxxx:bbbb0062b0062b0062b0062	(Ljava/lang/String;CCC)Ljava/lang/String;
    //   356: iconst_0
    //   357: anewarray 49	java/lang/Class
    //   360: invokevirtual 84	java/lang/Class:getMethod	(Ljava/lang/String;[Ljava/lang/Class;)Ljava/lang/reflect/Method;
    //   363: astore 4
    //   365: aload 4
    //   367: aconst_null
    //   368: iconst_0
    //   369: anewarray 55	java/lang/Object
    //   372: invokevirtual 61	java/lang/reflect/Method:invoke	(Ljava/lang/Object;[Ljava/lang/Object;)Ljava/lang/Object;
    //   375: astore 4
    //   377: aload 4
    //   379: checkcast 86	java/lang/Integer
    //   382: invokevirtual 89	java/lang/Integer:intValue	()I
    //   385: putstatic 79	uuuuuu/lqlqll:bpp0070p00700070pp0070	I
    //   388: aload_0
    //   389: new 114	uuuuuu/lqlqll$1
    //   392: dup
    //   393: aload_0
    //   394: invokespecial 117	uuuuuu/lqlqll$1:<init>	(Luuuuuu/lqlqll;)V
    //   397: putfield 119	uuuuuu/lqlqll:bpppp00700070pp0070	Luuuuuu/sxxxsx$xsxsxx;
    //   400: return
    //   401: astore 4
    //   403: aload 4
    //   405: invokevirtual 65	java/lang/reflect/InvocationTargetException:getCause	()Ljava/lang/Throwable;
    //   408: athrow
    //   409: astore 4
    //   411: aload 4
    //   413: invokevirtual 65	java/lang/reflect/InvocationTargetException:getCause	()Ljava/lang/Throwable;
    //   416: athrow
    //   417: astore 4
    //   419: aload 4
    //   421: invokevirtual 65	java/lang/reflect/InvocationTargetException:getCause	()Ljava/lang/Throwable;
    //   424: athrow
    //   425: astore 4
    //   427: aload 4
    //   429: invokevirtual 65	java/lang/reflect/InvocationTargetException:getCause	()Ljava/lang/Throwable;
    //   432: athrow
    //   433: astore 4
    //   435: aload 4
    //   437: invokevirtual 65	java/lang/reflect/InvocationTargetException:getCause	()Ljava/lang/Throwable;
    //   440: athrow
    //   441: astore 4
    //   443: aload 4
    //   445: invokevirtual 65	java/lang/reflect/InvocationTargetException:getCause	()Ljava/lang/Throwable;
    //   448: athrow
    // Local variable table:
    //   start	length	slot	name	signature
    //   0	449	0	this	lqlqll
    //   3	223	1	i	int
    //   49	175	2	j	int
    //   53	37	3	k	int
    //   71	307	4	localObject	Object
    //   401	3	4	localInvocationTargetException1	InvocationTargetException
    //   409	3	4	localInvocationTargetException2	InvocationTargetException
    //   417	3	4	localInvocationTargetException3	InvocationTargetException
    //   425	3	4	localInvocationTargetException4	InvocationTargetException
    //   433	3	4	localInvocationTargetException5	InvocationTargetException
    //   441	3	4	localInvocationTargetException6	InvocationTargetException
    // Exception table:
    //   from	to	target	type
    //   73	85	401	java/lang/reflect/InvocationTargetException
    //   270	282	409	java/lang/reflect/InvocationTargetException
    //   365	377	417	java/lang/reflect/InvocationTargetException
    //   315	327	425	java/lang/reflect/InvocationTargetException
    //   156	168	433	java/lang/reflect/InvocationTargetException
    //   198	210	441	java/lang/reflect/InvocationTargetException
  }
  
  public static int booooo006Fo006Foo()
  {
    return 89;
  }
  
  public void b006F006Fo006Fooo006Foo() {}
  
  /* Error */
  public String b006Foo006Fooo006Foo(com.db.pwcc.dbmobile.model.banking.CashAccountTransaction paramCashAccountTransaction, String paramString)
  {
    // Byte code:
    //   0: getstatic 73	uuuuuu/lqlqll:b0070ppp00700070pp0070	I
    //   3: getstatic 75	uuuuuu/lqlqll:bp0070pp00700070pp0070	I
    //   6: iadd
    //   7: getstatic 73	uuuuuu/lqlqll:b0070ppp00700070pp0070	I
    //   10: imul
    //   11: getstatic 77	uuuuuu/lqlqll:b00700070pp00700070pp0070	I
    //   14: irem
    //   15: getstatic 79	uuuuuu/lqlqll:bpp0070p00700070pp0070	I
    //   18: if_icmpeq +114 -> 132
    //   21: getstatic 73	uuuuuu/lqlqll:b0070ppp00700070pp0070	I
    //   24: getstatic 75	uuuuuu/lqlqll:bp0070pp00700070pp0070	I
    //   27: iadd
    //   28: getstatic 73	uuuuuu/lqlqll:b0070ppp00700070pp0070	I
    //   31: imul
    //   32: getstatic 77	uuuuuu/lqlqll:b00700070pp00700070pp0070	I
    //   35: irem
    //   36: getstatic 79	uuuuuu/lqlqll:bpp0070p00700070pp0070	I
    //   39: if_icmpeq +47 -> 86
    //   42: ldc 2
    //   44: ldc 125
    //   46: sipush 191
    //   49: iconst_1
    //   50: invokestatic 47	xxxxxx/uxxxxx:bb00620062bb0062b0062b0062	(Ljava/lang/String;CC)Ljava/lang/String;
    //   53: iconst_0
    //   54: anewarray 49	java/lang/Class
    //   57: invokevirtual 84	java/lang/Class:getMethod	(Ljava/lang/String;[Ljava/lang/Class;)Ljava/lang/reflect/Method;
    //   60: astore_2
    //   61: aload_2
    //   62: aconst_null
    //   63: iconst_0
    //   64: anewarray 55	java/lang/Object
    //   67: invokevirtual 61	java/lang/reflect/Method:invoke	(Ljava/lang/Object;[Ljava/lang/Object;)Ljava/lang/Object;
    //   70: astore_2
    //   71: aload_2
    //   72: checkcast 86	java/lang/Integer
    //   75: invokevirtual 89	java/lang/Integer:intValue	()I
    //   78: putstatic 73	uuuuuu/lqlqll:b0070ppp00700070pp0070	I
    //   81: bipush 74
    //   83: putstatic 79	uuuuuu/lqlqll:bpp0070p00700070pp0070	I
    //   86: ldc 2
    //   88: ldc 127
    //   90: sipush 192
    //   93: bipush 122
    //   95: iconst_3
    //   96: invokestatic 97	xxxxxx/uxxxxx:bbbb0062b0062b0062b0062	(Ljava/lang/String;CCC)Ljava/lang/String;
    //   99: iconst_0
    //   100: anewarray 49	java/lang/Class
    //   103: invokevirtual 84	java/lang/Class:getMethod	(Ljava/lang/String;[Ljava/lang/Class;)Ljava/lang/reflect/Method;
    //   106: astore_2
    //   107: aload_2
    //   108: aconst_null
    //   109: iconst_0
    //   110: anewarray 55	java/lang/Object
    //   113: invokevirtual 61	java/lang/reflect/Method:invoke	(Ljava/lang/Object;[Ljava/lang/Object;)Ljava/lang/Object;
    //   116: astore_2
    //   117: aload_2
    //   118: checkcast 86	java/lang/Integer
    //   121: invokevirtual 89	java/lang/Integer:intValue	()I
    //   124: putstatic 73	uuuuuu/lqlqll:b0070ppp00700070pp0070	I
    //   127: bipush 79
    //   129: putstatic 79	uuuuuu/lqlqll:bpp0070p00700070pp0070	I
    //   132: aload_1
    //   133: invokevirtual 133	com/db/pwcc/dbmobile/model/banking/CashAccountTransaction:getCurrency	()Ljava/lang/String;
    //   136: astore_1
    //   137: getstatic 73	uuuuuu/lqlqll:b0070ppp00700070pp0070	I
    //   140: istore_3
    //   141: iload_3
    //   142: getstatic 75	uuuuuu/lqlqll:bp0070pp00700070pp0070	I
    //   145: iload_3
    //   146: iadd
    //   147: imul
    //   148: getstatic 77	uuuuuu/lqlqll:b00700070pp00700070pp0070	I
    //   151: irem
    //   152: tableswitch	default:+20->172, 0:+141->293
    //   172: bipush 65
    //   174: putstatic 73	uuuuuu/lqlqll:b0070ppp00700070pp0070	I
    //   177: ldc 2
    //   179: ldc -121
    //   181: bipush 114
    //   183: iconst_0
    //   184: invokestatic 47	xxxxxx/uxxxxx:bb00620062bb0062b0062b0062	(Ljava/lang/String;CC)Ljava/lang/String;
    //   187: iconst_0
    //   188: anewarray 49	java/lang/Class
    //   191: invokevirtual 84	java/lang/Class:getMethod	(Ljava/lang/String;[Ljava/lang/Class;)Ljava/lang/reflect/Method;
    //   194: astore_2
    //   195: aload_2
    //   196: aconst_null
    //   197: iconst_0
    //   198: anewarray 55	java/lang/Object
    //   201: invokevirtual 61	java/lang/reflect/Method:invoke	(Ljava/lang/Object;[Ljava/lang/Object;)Ljava/lang/Object;
    //   204: astore_2
    //   205: aload_2
    //   206: checkcast 86	java/lang/Integer
    //   209: invokevirtual 89	java/lang/Integer:intValue	()I
    //   212: putstatic 79	uuuuuu/lqlqll:bpp0070p00700070pp0070	I
    //   215: getstatic 73	uuuuuu/lqlqll:b0070ppp00700070pp0070	I
    //   218: istore_3
    //   219: iload_3
    //   220: getstatic 75	uuuuuu/lqlqll:bp0070pp00700070pp0070	I
    //   223: iload_3
    //   224: iadd
    //   225: imul
    //   226: getstatic 77	uuuuuu/lqlqll:b00700070pp00700070pp0070	I
    //   229: irem
    //   230: tableswitch	default:+18->248, 0:+63->293
    //   248: bipush 12
    //   250: putstatic 73	uuuuuu/lqlqll:b0070ppp00700070pp0070	I
    //   253: ldc 2
    //   255: ldc -119
    //   257: bipush 16
    //   259: bipush 12
    //   261: iconst_3
    //   262: invokestatic 97	xxxxxx/uxxxxx:bbbb0062b0062b0062b0062	(Ljava/lang/String;CCC)Ljava/lang/String;
    //   265: iconst_0
    //   266: anewarray 49	java/lang/Class
    //   269: invokevirtual 84	java/lang/Class:getMethod	(Ljava/lang/String;[Ljava/lang/Class;)Ljava/lang/reflect/Method;
    //   272: astore_2
    //   273: aload_2
    //   274: aconst_null
    //   275: iconst_0
    //   276: anewarray 55	java/lang/Object
    //   279: invokevirtual 61	java/lang/reflect/Method:invoke	(Ljava/lang/Object;[Ljava/lang/Object;)Ljava/lang/Object;
    //   282: astore_2
    //   283: aload_2
    //   284: checkcast 86	java/lang/Integer
    //   287: invokevirtual 89	java/lang/Integer:intValue	()I
    //   290: putstatic 79	uuuuuu/lqlqll:bpp0070p00700070pp0070	I
    //   293: aload_1
    //   294: areturn
    //   295: astore_1
    //   296: aload_1
    //   297: invokevirtual 65	java/lang/reflect/InvocationTargetException:getCause	()Ljava/lang/Throwable;
    //   300: athrow
    //   301: astore_1
    //   302: aload_1
    //   303: invokevirtual 65	java/lang/reflect/InvocationTargetException:getCause	()Ljava/lang/Throwable;
    //   306: athrow
    //   307: astore_1
    //   308: aload_1
    //   309: invokevirtual 65	java/lang/reflect/InvocationTargetException:getCause	()Ljava/lang/Throwable;
    //   312: athrow
    //   313: astore_1
    //   314: aload_1
    //   315: invokevirtual 65	java/lang/reflect/InvocationTargetException:getCause	()Ljava/lang/Throwable;
    //   318: athrow
    // Local variable table:
    //   start	length	slot	name	signature
    //   0	319	0	this	lqlqll
    //   0	319	1	paramCashAccountTransaction	com.db.pwcc.dbmobile.model.banking.CashAccountTransaction
    //   0	319	2	paramString	String
    //   140	86	3	i	int
    // Exception table:
    //   from	to	target	type
    //   195	205	295	java/lang/reflect/InvocationTargetException
    //   107	117	301	java/lang/reflect/InvocationTargetException
    //   61	71	307	java/lang/reflect/InvocationTargetException
    //   273	283	313	java/lang/reflect/InvocationTargetException
  }
  
  public void bo006Fo006Fooo006Foo() {}
  
  /* Error */
  public void boo006F006Fooo006Foo(com.db.pwcc.dbmobile.model.banking.CashAccountTransaction paramCashAccountTransaction, boolean paramBoolean)
  {
    // Byte code:
    //   0: aload_0
    //   1: aload_1
    //   2: invokevirtual 143	com/db/pwcc/dbmobile/model/banking/CashAccountTransaction:getPayerIban	()Ljava/lang/String;
    //   5: putfield 145	uuuuuu/lqlqll:b0070p00700070p0070pp0070	Ljava/lang/String;
    //   8: aload_0
    //   9: iload_2
    //   10: putfield 147	uuuuuu/lqlqll:bp007000700070p0070pp0070	Z
    //   13: aload_0
    //   14: getfield 39	uuuuuu/lqlqll:b0070007000700070p0070pp0070	Luuuuuu/sxxxsx;
    //   17: astore_1
    //   18: aload_0
    //   19: getfield 119	uuuuuu/lqlqll:bpppp00700070pp0070	Luuuuuu/sxxxsx$xsxsxx;
    //   22: astore 8
    //   24: getstatic 73	uuuuuu/lqlqll:b0070ppp00700070pp0070	I
    //   27: istore_3
    //   28: getstatic 75	uuuuuu/lqlqll:bp0070pp00700070pp0070	I
    //   31: istore 4
    //   33: getstatic 73	uuuuuu/lqlqll:b0070ppp00700070pp0070	I
    //   36: istore 5
    //   38: iload 5
    //   40: getstatic 75	uuuuuu/lqlqll:bp0070pp00700070pp0070	I
    //   43: iload 5
    //   45: iadd
    //   46: imul
    //   47: getstatic 77	uuuuuu/lqlqll:b00700070pp00700070pp0070	I
    //   50: irem
    //   51: tableswitch	default:+17->68, 0:+65->116
    //   68: ldc 2
    //   70: ldc -107
    //   72: sipush 132
    //   75: iconst_3
    //   76: invokestatic 47	xxxxxx/uxxxxx:bb00620062bb0062b0062b0062	(Ljava/lang/String;CC)Ljava/lang/String;
    //   79: iconst_0
    //   80: anewarray 49	java/lang/Class
    //   83: invokevirtual 84	java/lang/Class:getMethod	(Ljava/lang/String;[Ljava/lang/Class;)Ljava/lang/reflect/Method;
    //   86: astore 9
    //   88: aload 9
    //   90: aconst_null
    //   91: iconst_0
    //   92: anewarray 55	java/lang/Object
    //   95: invokevirtual 61	java/lang/reflect/Method:invoke	(Ljava/lang/Object;[Ljava/lang/Object;)Ljava/lang/Object;
    //   98: astore 9
    //   100: aload 9
    //   102: checkcast 86	java/lang/Integer
    //   105: invokevirtual 89	java/lang/Integer:intValue	()I
    //   108: putstatic 73	uuuuuu/lqlqll:b0070ppp00700070pp0070	I
    //   111: bipush 40
    //   113: putstatic 79	uuuuuu/lqlqll:bpp0070p00700070pp0070	I
    //   116: iload 4
    //   118: iload_3
    //   119: iadd
    //   120: iload_3
    //   121: imul
    //   122: getstatic 77	uuuuuu/lqlqll:b00700070pp00700070pp0070	I
    //   125: irem
    //   126: tableswitch	default:+18->144, 0:+351->477
    //   144: ldc 2
    //   146: ldc 110
    //   148: bipush 101
    //   150: iconst_4
    //   151: invokestatic 47	xxxxxx/uxxxxx:bb00620062bb0062b0062b0062	(Ljava/lang/String;CC)Ljava/lang/String;
    //   154: iconst_0
    //   155: anewarray 49	java/lang/Class
    //   158: invokevirtual 84	java/lang/Class:getMethod	(Ljava/lang/String;[Ljava/lang/Class;)Ljava/lang/reflect/Method;
    //   161: astore 9
    //   163: aload 9
    //   165: aconst_null
    //   166: iconst_0
    //   167: anewarray 55	java/lang/Object
    //   170: invokevirtual 61	java/lang/reflect/Method:invoke	(Ljava/lang/Object;[Ljava/lang/Object;)Ljava/lang/Object;
    //   173: astore 9
    //   175: aload 9
    //   177: checkcast 86	java/lang/Integer
    //   180: invokevirtual 89	java/lang/Integer:intValue	()I
    //   183: putstatic 73	uuuuuu/lqlqll:b0070ppp00700070pp0070	I
    //   186: ldc 2
    //   188: ldc -105
    //   190: sipush 179
    //   193: bipush 15
    //   195: iconst_1
    //   196: invokestatic 97	xxxxxx/uxxxxx:bbbb0062b0062b0062b0062	(Ljava/lang/String;CCC)Ljava/lang/String;
    //   199: iconst_0
    //   200: anewarray 49	java/lang/Class
    //   203: invokevirtual 84	java/lang/Class:getMethod	(Ljava/lang/String;[Ljava/lang/Class;)Ljava/lang/reflect/Method;
    //   206: astore 9
    //   208: aload 9
    //   210: aconst_null
    //   211: iconst_0
    //   212: anewarray 55	java/lang/Object
    //   215: invokevirtual 61	java/lang/reflect/Method:invoke	(Ljava/lang/Object;[Ljava/lang/Object;)Ljava/lang/Object;
    //   218: astore 9
    //   220: aload 9
    //   222: checkcast 86	java/lang/Integer
    //   225: invokevirtual 89	java/lang/Integer:intValue	()I
    //   228: istore_3
    //   229: getstatic 73	uuuuuu/lqlqll:b0070ppp00700070pp0070	I
    //   232: istore 4
    //   234: iload 4
    //   236: getstatic 75	uuuuuu/lqlqll:bp0070pp00700070pp0070	I
    //   239: iload 4
    //   241: iadd
    //   242: imul
    //   243: getstatic 77	uuuuuu/lqlqll:b00700070pp00700070pp0070	I
    //   246: irem
    //   247: tableswitch	default:+17->264, 0:+226->473
    //   264: ldc 2
    //   266: ldc -103
    //   268: bipush 71
    //   270: sipush 236
    //   273: iconst_1
    //   274: invokestatic 97	xxxxxx/uxxxxx:bbbb0062b0062b0062b0062	(Ljava/lang/String;CCC)Ljava/lang/String;
    //   277: iconst_0
    //   278: anewarray 49	java/lang/Class
    //   281: invokevirtual 84	java/lang/Class:getMethod	(Ljava/lang/String;[Ljava/lang/Class;)Ljava/lang/reflect/Method;
    //   284: astore 9
    //   286: aload 9
    //   288: aconst_null
    //   289: iconst_0
    //   290: anewarray 55	java/lang/Object
    //   293: invokevirtual 61	java/lang/reflect/Method:invoke	(Ljava/lang/Object;[Ljava/lang/Object;)Ljava/lang/Object;
    //   296: astore 9
    //   298: aload 9
    //   300: checkcast 86	java/lang/Integer
    //   303: invokevirtual 89	java/lang/Integer:intValue	()I
    //   306: putstatic 73	uuuuuu/lqlqll:b0070ppp00700070pp0070	I
    //   309: getstatic 73	uuuuuu/lqlqll:b0070ppp00700070pp0070	I
    //   312: istore 4
    //   314: getstatic 75	uuuuuu/lqlqll:bp0070pp00700070pp0070	I
    //   317: istore 5
    //   319: getstatic 73	uuuuuu/lqlqll:b0070ppp00700070pp0070	I
    //   322: istore 6
    //   324: getstatic 77	uuuuuu/lqlqll:b00700070pp00700070pp0070	I
    //   327: istore 7
    //   329: ldc 2
    //   331: ldc -101
    //   333: bipush 76
    //   335: iconst_1
    //   336: invokestatic 47	xxxxxx/uxxxxx:bb00620062bb0062b0062b0062	(Ljava/lang/String;CC)Ljava/lang/String;
    //   339: iconst_0
    //   340: anewarray 49	java/lang/Class
    //   343: invokevirtual 84	java/lang/Class:getMethod	(Ljava/lang/String;[Ljava/lang/Class;)Ljava/lang/reflect/Method;
    //   346: astore 9
    //   348: aload 9
    //   350: aconst_null
    //   351: iconst_0
    //   352: anewarray 55	java/lang/Object
    //   355: invokevirtual 61	java/lang/reflect/Method:invoke	(Ljava/lang/Object;[Ljava/lang/Object;)Ljava/lang/Object;
    //   358: astore 9
    //   360: iload 4
    //   362: iload 5
    //   364: iadd
    //   365: iload 6
    //   367: imul
    //   368: iload 7
    //   370: irem
    //   371: aload 9
    //   373: checkcast 86	java/lang/Integer
    //   376: invokevirtual 89	java/lang/Integer:intValue	()I
    //   379: if_icmpeq +89 -> 468
    //   382: ldc 2
    //   384: ldc 93
    //   386: bipush 32
    //   388: iconst_0
    //   389: invokestatic 47	xxxxxx/uxxxxx:bb00620062bb0062b0062b0062	(Ljava/lang/String;CC)Ljava/lang/String;
    //   392: iconst_0
    //   393: anewarray 49	java/lang/Class
    //   396: invokevirtual 84	java/lang/Class:getMethod	(Ljava/lang/String;[Ljava/lang/Class;)Ljava/lang/reflect/Method;
    //   399: astore 9
    //   401: aload 9
    //   403: aconst_null
    //   404: iconst_0
    //   405: anewarray 55	java/lang/Object
    //   408: invokevirtual 61	java/lang/reflect/Method:invoke	(Ljava/lang/Object;[Ljava/lang/Object;)Ljava/lang/Object;
    //   411: astore 9
    //   413: aload 9
    //   415: checkcast 86	java/lang/Integer
    //   418: invokevirtual 89	java/lang/Integer:intValue	()I
    //   421: putstatic 73	uuuuuu/lqlqll:b0070ppp00700070pp0070	I
    //   424: ldc 2
    //   426: ldc -99
    //   428: bipush 27
    //   430: bipush 53
    //   432: iconst_2
    //   433: invokestatic 97	xxxxxx/uxxxxx:bbbb0062b0062b0062b0062	(Ljava/lang/String;CCC)Ljava/lang/String;
    //   436: iconst_0
    //   437: anewarray 49	java/lang/Class
    //   440: invokevirtual 84	java/lang/Class:getMethod	(Ljava/lang/String;[Ljava/lang/Class;)Ljava/lang/reflect/Method;
    //   443: astore 9
    //   445: aload 9
    //   447: aconst_null
    //   448: iconst_0
    //   449: anewarray 55	java/lang/Object
    //   452: invokevirtual 61	java/lang/reflect/Method:invoke	(Ljava/lang/Object;[Ljava/lang/Object;)Ljava/lang/Object;
    //   455: astore 9
    //   457: aload 9
    //   459: checkcast 86	java/lang/Integer
    //   462: invokevirtual 89	java/lang/Integer:intValue	()I
    //   465: putstatic 79	uuuuuu/lqlqll:bpp0070p00700070pp0070	I
    //   468: bipush 97
    //   470: putstatic 79	uuuuuu/lqlqll:bpp0070p00700070pp0070	I
    //   473: iload_3
    //   474: putstatic 79	uuuuuu/lqlqll:bpp0070p00700070pp0070	I
    //   477: aload_1
    //   478: aload 8
    //   480: iconst_1
    //   481: newarray int
    //   483: dup
    //   484: iconst_0
    //   485: iconst_0
    //   486: iastore
    //   487: invokevirtual 161	uuuuuu/sxxxsx:bk006B006B006B006Bk006B006B006B006B	(Luuuuuu/sxxxsx$xsxsxx;[I)V
    //   490: return
    //   491: astore_1
    //   492: aload_1
    //   493: invokevirtual 65	java/lang/reflect/InvocationTargetException:getCause	()Ljava/lang/Throwable;
    //   496: athrow
    //   497: astore_1
    //   498: aload_1
    //   499: invokevirtual 65	java/lang/reflect/InvocationTargetException:getCause	()Ljava/lang/Throwable;
    //   502: athrow
    //   503: astore_1
    //   504: aload_1
    //   505: invokevirtual 65	java/lang/reflect/InvocationTargetException:getCause	()Ljava/lang/Throwable;
    //   508: athrow
    //   509: astore_1
    //   510: aload_1
    //   511: invokevirtual 65	java/lang/reflect/InvocationTargetException:getCause	()Ljava/lang/Throwable;
    //   514: athrow
    //   515: astore_1
    //   516: aload_1
    //   517: invokevirtual 65	java/lang/reflect/InvocationTargetException:getCause	()Ljava/lang/Throwable;
    //   520: athrow
    //   521: astore_1
    //   522: aload_1
    //   523: invokevirtual 65	java/lang/reflect/InvocationTargetException:getCause	()Ljava/lang/Throwable;
    //   526: athrow
    //   527: astore_1
    //   528: aload_1
    //   529: invokevirtual 65	java/lang/reflect/InvocationTargetException:getCause	()Ljava/lang/Throwable;
    //   532: athrow
    // Local variable table:
    //   start	length	slot	name	signature
    //   0	533	0	this	lqlqll
    //   0	533	1	paramCashAccountTransaction	com.db.pwcc.dbmobile.model.banking.CashAccountTransaction
    //   0	533	2	paramBoolean	boolean
    //   27	447	3	i	int
    //   31	334	4	j	int
    //   36	329	5	k	int
    //   322	46	6	m	int
    //   327	44	7	n	int
    //   22	457	8	localXsxsxx	sxxxsx.xsxsxx
    //   86	372	9	localObject	Object
    // Exception table:
    //   from	to	target	type
    //   208	220	491	java/lang/reflect/InvocationTargetException
    //   163	175	497	java/lang/reflect/InvocationTargetException
    //   286	298	503	java/lang/reflect/InvocationTargetException
    //   348	360	509	java/lang/reflect/InvocationTargetException
    //   401	413	515	java/lang/reflect/InvocationTargetException
    //   445	457	521	java/lang/reflect/InvocationTargetException
    //   88	100	527	java/lang/reflect/InvocationTargetException
  }
}
