package uuuuuu;

import com.db.pwcc.dbmobile.financial_overview.R.id;
import com.db.pwcc.dbmobile.model.banking.CashAccountTransaction;

public abstract class lqqlll
  extends qppppp<qqllll.qlqlll>
{
  public static int b007000700070p0070ppp0070 = 2;
  public static final int b00700070pp0070ppp0070;
  public static int b0070p0070p0070ppp0070 = 0;
  public static final int b0070ppp0070ppp0070 = R.id.menu_item_create_contact;
  public static int bp00700070p0070ppp0070 = 1;
  public static final int bp0070pp0070ppp0070;
  public static int bpp0070p0070ppp0070 = 78;
  
  /* Error */
  static
  {
    // Byte code:
    //   0: getstatic 26	com/db/pwcc/dbmobile/financial_overview/R$id:menu_item_create_contact	I
    //   3: putstatic 28	uuuuuu/lqqlll:b0070ppp0070ppp0070	I
    //   6: getstatic 31	com/db/pwcc/dbmobile/financial_overview/R$id:menu_item_create_transaction	I
    //   9: putstatic 33	uuuuuu/lqqlll:b00700070pp0070ppp0070	I
    //   12: getstatic 35	uuuuuu/lqqlll:bpp0070p0070ppp0070	I
    //   15: getstatic 37	uuuuuu/lqqlll:bp00700070p0070ppp0070	I
    //   18: iadd
    //   19: getstatic 35	uuuuuu/lqqlll:bpp0070p0070ppp0070	I
    //   22: imul
    //   23: getstatic 39	uuuuuu/lqqlll:b007000700070p0070ppp0070	I
    //   26: irem
    //   27: getstatic 41	uuuuuu/lqqlll:b0070p0070p0070ppp0070	I
    //   30: if_icmpeq +321 -> 351
    //   33: getstatic 35	uuuuuu/lqqlll:bpp0070p0070ppp0070	I
    //   36: istore_0
    //   37: getstatic 37	uuuuuu/lqqlll:bp00700070p0070ppp0070	I
    //   40: istore_1
    //   41: getstatic 35	uuuuuu/lqqlll:bpp0070p0070ppp0070	I
    //   44: istore_2
    //   45: ldc 2
    //   47: ldc 43
    //   49: bipush 74
    //   51: sipush 129
    //   54: iconst_1
    //   55: invokestatic 49	xxxxxx/uxxxxx:bbbb0062b0062b0062b0062	(Ljava/lang/String;CCC)Ljava/lang/String;
    //   58: iconst_0
    //   59: anewarray 51	java/lang/Class
    //   62: invokevirtual 55	java/lang/Class:getMethod	(Ljava/lang/String;[Ljava/lang/Class;)Ljava/lang/reflect/Method;
    //   65: astore 4
    //   67: aload 4
    //   69: aconst_null
    //   70: iconst_0
    //   71: anewarray 57	java/lang/Object
    //   74: invokevirtual 63	java/lang/reflect/Method:invoke	(Ljava/lang/Object;[Ljava/lang/Object;)Ljava/lang/Object;
    //   77: astore 4
    //   79: aload 4
    //   81: checkcast 65	java/lang/Integer
    //   84: invokevirtual 69	java/lang/Integer:intValue	()I
    //   87: istore_3
    //   88: ldc 2
    //   90: ldc 71
    //   92: sipush 207
    //   95: iconst_5
    //   96: invokestatic 75	xxxxxx/uxxxxx:bb00620062bb0062b0062b0062	(Ljava/lang/String;CC)Ljava/lang/String;
    //   99: iconst_0
    //   100: anewarray 51	java/lang/Class
    //   103: invokevirtual 55	java/lang/Class:getMethod	(Ljava/lang/String;[Ljava/lang/Class;)Ljava/lang/reflect/Method;
    //   106: astore 4
    //   108: aload 4
    //   110: aconst_null
    //   111: iconst_0
    //   112: anewarray 57	java/lang/Object
    //   115: invokevirtual 63	java/lang/reflect/Method:invoke	(Ljava/lang/Object;[Ljava/lang/Object;)Ljava/lang/Object;
    //   118: astore 4
    //   120: iload_2
    //   121: iload_0
    //   122: iload_1
    //   123: iadd
    //   124: imul
    //   125: iload_3
    //   126: irem
    //   127: aload 4
    //   129: checkcast 65	java/lang/Integer
    //   132: invokevirtual 69	java/lang/Integer:intValue	()I
    //   135: if_icmpeq +206 -> 341
    //   138: ldc 2
    //   140: ldc 77
    //   142: bipush 88
    //   144: iconst_4
    //   145: iconst_2
    //   146: invokestatic 49	xxxxxx/uxxxxx:bbbb0062b0062b0062b0062	(Ljava/lang/String;CCC)Ljava/lang/String;
    //   149: iconst_0
    //   150: anewarray 51	java/lang/Class
    //   153: invokevirtual 55	java/lang/Class:getMethod	(Ljava/lang/String;[Ljava/lang/Class;)Ljava/lang/reflect/Method;
    //   156: astore 4
    //   158: aload 4
    //   160: aconst_null
    //   161: iconst_0
    //   162: anewarray 57	java/lang/Object
    //   165: invokevirtual 63	java/lang/reflect/Method:invoke	(Ljava/lang/Object;[Ljava/lang/Object;)Ljava/lang/Object;
    //   168: astore 4
    //   170: aload 4
    //   172: checkcast 65	java/lang/Integer
    //   175: invokevirtual 69	java/lang/Integer:intValue	()I
    //   178: putstatic 35	uuuuuu/lqqlll:bpp0070p0070ppp0070	I
    //   181: ldc 2
    //   183: ldc 79
    //   185: iconst_3
    //   186: iconst_4
    //   187: invokestatic 75	xxxxxx/uxxxxx:bb00620062bb0062b0062b0062	(Ljava/lang/String;CC)Ljava/lang/String;
    //   190: iconst_0
    //   191: anewarray 51	java/lang/Class
    //   194: invokevirtual 55	java/lang/Class:getMethod	(Ljava/lang/String;[Ljava/lang/Class;)Ljava/lang/reflect/Method;
    //   197: astore 4
    //   199: aload 4
    //   201: aconst_null
    //   202: iconst_0
    //   203: anewarray 57	java/lang/Object
    //   206: invokevirtual 63	java/lang/reflect/Method:invoke	(Ljava/lang/Object;[Ljava/lang/Object;)Ljava/lang/Object;
    //   209: astore 4
    //   211: aload 4
    //   213: checkcast 65	java/lang/Integer
    //   216: invokevirtual 69	java/lang/Integer:intValue	()I
    //   219: putstatic 41	uuuuuu/lqqlll:b0070p0070p0070ppp0070	I
    //   222: ldc 2
    //   224: ldc 81
    //   226: sipush 228
    //   229: iconst_4
    //   230: invokestatic 75	xxxxxx/uxxxxx:bb00620062bb0062b0062b0062	(Ljava/lang/String;CC)Ljava/lang/String;
    //   233: iconst_0
    //   234: anewarray 51	java/lang/Class
    //   237: invokevirtual 55	java/lang/Class:getMethod	(Ljava/lang/String;[Ljava/lang/Class;)Ljava/lang/reflect/Method;
    //   240: astore 4
    //   242: aload 4
    //   244: aconst_null
    //   245: iconst_0
    //   246: anewarray 57	java/lang/Object
    //   249: invokevirtual 63	java/lang/reflect/Method:invoke	(Ljava/lang/Object;[Ljava/lang/Object;)Ljava/lang/Object;
    //   252: astore 4
    //   254: aload 4
    //   256: checkcast 65	java/lang/Integer
    //   259: invokevirtual 69	java/lang/Integer:intValue	()I
    //   262: istore_0
    //   263: iload_0
    //   264: getstatic 37	uuuuuu/lqqlll:bp00700070p0070ppp0070	I
    //   267: iload_0
    //   268: iadd
    //   269: imul
    //   270: getstatic 39	uuuuuu/lqqlll:b007000700070p0070ppp0070	I
    //   273: irem
    //   274: tableswitch	default:+18->292, 0:+67->341
    //   292: ldc 2
    //   294: ldc 83
    //   296: bipush 126
    //   298: bipush 64
    //   300: iconst_1
    //   301: invokestatic 49	xxxxxx/uxxxxx:bbbb0062b0062b0062b0062	(Ljava/lang/String;CCC)Ljava/lang/String;
    //   304: iconst_0
    //   305: anewarray 51	java/lang/Class
    //   308: invokevirtual 55	java/lang/Class:getMethod	(Ljava/lang/String;[Ljava/lang/Class;)Ljava/lang/reflect/Method;
    //   311: astore 4
    //   313: aload 4
    //   315: aconst_null
    //   316: iconst_0
    //   317: anewarray 57	java/lang/Object
    //   320: invokevirtual 63	java/lang/reflect/Method:invoke	(Ljava/lang/Object;[Ljava/lang/Object;)Ljava/lang/Object;
    //   323: astore 4
    //   325: aload 4
    //   327: checkcast 65	java/lang/Integer
    //   330: invokevirtual 69	java/lang/Integer:intValue	()I
    //   333: putstatic 35	uuuuuu/lqqlll:bpp0070p0070ppp0070	I
    //   336: bipush 63
    //   338: putstatic 41	uuuuuu/lqqlll:b0070p0070p0070ppp0070	I
    //   341: bipush 13
    //   343: putstatic 35	uuuuuu/lqqlll:bpp0070p0070ppp0070	I
    //   346: bipush 52
    //   348: putstatic 41	uuuuuu/lqqlll:b0070p0070p0070ppp0070	I
    //   351: getstatic 86	com/db/pwcc/dbmobile/financial_overview/R$id:menu_item_create_standing_order	I
    //   354: putstatic 88	uuuuuu/lqqlll:bp0070pp0070ppp0070	I
    //   357: getstatic 35	uuuuuu/lqqlll:bpp0070p0070ppp0070	I
    //   360: istore_0
    //   361: iload_0
    //   362: getstatic 37	uuuuuu/lqqlll:bp00700070p0070ppp0070	I
    //   365: iload_0
    //   366: iadd
    //   367: imul
    //   368: getstatic 39	uuuuuu/lqqlll:b007000700070p0070ppp0070	I
    //   371: irem
    //   372: tableswitch	default:+20->392, 0:+105->477
    //   392: ldc 2
    //   394: ldc 90
    //   396: bipush 40
    //   398: iconst_3
    //   399: invokestatic 75	xxxxxx/uxxxxx:bb00620062bb0062b0062b0062	(Ljava/lang/String;CC)Ljava/lang/String;
    //   402: iconst_0
    //   403: anewarray 51	java/lang/Class
    //   406: invokevirtual 55	java/lang/Class:getMethod	(Ljava/lang/String;[Ljava/lang/Class;)Ljava/lang/reflect/Method;
    //   409: astore 4
    //   411: aload 4
    //   413: aconst_null
    //   414: iconst_0
    //   415: anewarray 57	java/lang/Object
    //   418: invokevirtual 63	java/lang/reflect/Method:invoke	(Ljava/lang/Object;[Ljava/lang/Object;)Ljava/lang/Object;
    //   421: astore 4
    //   423: aload 4
    //   425: checkcast 65	java/lang/Integer
    //   428: invokevirtual 69	java/lang/Integer:intValue	()I
    //   431: putstatic 35	uuuuuu/lqqlll:bpp0070p0070ppp0070	I
    //   434: ldc 2
    //   436: ldc 92
    //   438: sipush 162
    //   441: iconst_3
    //   442: invokestatic 75	xxxxxx/uxxxxx:bb00620062bb0062b0062b0062	(Ljava/lang/String;CC)Ljava/lang/String;
    //   445: iconst_0
    //   446: anewarray 51	java/lang/Class
    //   449: invokevirtual 55	java/lang/Class:getMethod	(Ljava/lang/String;[Ljava/lang/Class;)Ljava/lang/reflect/Method;
    //   452: astore 4
    //   454: aload 4
    //   456: aconst_null
    //   457: iconst_0
    //   458: anewarray 57	java/lang/Object
    //   461: invokevirtual 63	java/lang/reflect/Method:invoke	(Ljava/lang/Object;[Ljava/lang/Object;)Ljava/lang/Object;
    //   464: astore 4
    //   466: aload 4
    //   468: checkcast 65	java/lang/Integer
    //   471: invokevirtual 69	java/lang/Integer:intValue	()I
    //   474: putstatic 41	uuuuuu/lqqlll:b0070p0070p0070ppp0070	I
    //   477: return
    //   478: astore 4
    //   480: aload 4
    //   482: invokevirtual 96	java/lang/reflect/InvocationTargetException:getCause	()Ljava/lang/Throwable;
    //   485: athrow
    //   486: astore 4
    //   488: aload 4
    //   490: invokevirtual 96	java/lang/reflect/InvocationTargetException:getCause	()Ljava/lang/Throwable;
    //   493: athrow
    //   494: astore 4
    //   496: aload 4
    //   498: invokevirtual 96	java/lang/reflect/InvocationTargetException:getCause	()Ljava/lang/Throwable;
    //   501: athrow
    //   502: astore 4
    //   504: aload 4
    //   506: invokevirtual 96	java/lang/reflect/InvocationTargetException:getCause	()Ljava/lang/Throwable;
    //   509: athrow
    //   510: astore 4
    //   512: aload 4
    //   514: invokevirtual 96	java/lang/reflect/InvocationTargetException:getCause	()Ljava/lang/Throwable;
    //   517: athrow
    //   518: astore 4
    //   520: aload 4
    //   522: invokevirtual 96	java/lang/reflect/InvocationTargetException:getCause	()Ljava/lang/Throwable;
    //   525: athrow
    //   526: astore 4
    //   528: aload 4
    //   530: invokevirtual 96	java/lang/reflect/InvocationTargetException:getCause	()Ljava/lang/Throwable;
    //   533: athrow
    //   534: astore 4
    //   536: aload 4
    //   538: invokevirtual 96	java/lang/reflect/InvocationTargetException:getCause	()Ljava/lang/Throwable;
    //   541: athrow
    // Local variable table:
    //   start	length	slot	name	signature
    //   36	332	0	i	int
    //   40	84	1	j	int
    //   44	81	2	k	int
    //   87	40	3	m	int
    //   65	402	4	localObject	Object
    //   478	3	4	localInvocationTargetException1	java.lang.reflect.InvocationTargetException
    //   486	3	4	localInvocationTargetException2	java.lang.reflect.InvocationTargetException
    //   494	3	4	localInvocationTargetException3	java.lang.reflect.InvocationTargetException
    //   502	3	4	localInvocationTargetException4	java.lang.reflect.InvocationTargetException
    //   510	3	4	localInvocationTargetException5	java.lang.reflect.InvocationTargetException
    //   518	3	4	localInvocationTargetException6	java.lang.reflect.InvocationTargetException
    //   526	3	4	localInvocationTargetException7	java.lang.reflect.InvocationTargetException
    //   534	3	4	localInvocationTargetException8	java.lang.reflect.InvocationTargetException
    // Exception table:
    //   from	to	target	type
    //   108	120	478	java/lang/reflect/InvocationTargetException
    //   67	79	486	java/lang/reflect/InvocationTargetException
    //   158	170	494	java/lang/reflect/InvocationTargetException
    //   199	211	502	java/lang/reflect/InvocationTargetException
    //   242	254	510	java/lang/reflect/InvocationTargetException
    //   411	423	518	java/lang/reflect/InvocationTargetException
    //   454	466	526	java/lang/reflect/InvocationTargetException
    //   313	325	534	java/lang/reflect/InvocationTargetException
  }
  
  public lqqlll() {}
  
  public lqqlll(qqllll.qlqlll paramQlqlll)
  {
    this.bnnnnn006E006E006En = paramQlqlll;
  }
  
  public static int b006F006F006F006Fooo006Foo()
  {
    return 0;
  }
  
  public static int b006Fo006F006Fooo006Foo()
  {
    return 2;
  }
  
  public static int bo006F006F006Fooo006Foo()
  {
    return 83;
  }
  
  /* Error */
  public void b006F006F006Foooo006Foo()
  {
    // Byte code:
    //   0: getstatic 35	uuuuuu/lqqlll:bpp0070p0070ppp0070	I
    //   3: istore_1
    //   4: iload_1
    //   5: getstatic 37	uuuuuu/lqqlll:bp00700070p0070ppp0070	I
    //   8: iload_1
    //   9: iadd
    //   10: imul
    //   11: getstatic 39	uuuuuu/lqqlll:b007000700070p0070ppp0070	I
    //   14: irem
    //   15: tableswitch	default:+17->32, 0:+68->83
    //   32: ldc 2
    //   34: ldc 111
    //   36: sipush 198
    //   39: sipush 211
    //   42: iconst_1
    //   43: invokestatic 49	xxxxxx/uxxxxx:bbbb0062b0062b0062b0062	(Ljava/lang/String;CCC)Ljava/lang/String;
    //   46: iconst_0
    //   47: anewarray 51	java/lang/Class
    //   50: invokevirtual 55	java/lang/Class:getMethod	(Ljava/lang/String;[Ljava/lang/Class;)Ljava/lang/reflect/Method;
    //   53: astore 6
    //   55: aload 6
    //   57: aconst_null
    //   58: iconst_0
    //   59: anewarray 57	java/lang/Object
    //   62: invokevirtual 63	java/lang/reflect/Method:invoke	(Ljava/lang/Object;[Ljava/lang/Object;)Ljava/lang/Object;
    //   65: astore 6
    //   67: aload 6
    //   69: checkcast 65	java/lang/Integer
    //   72: invokevirtual 69	java/lang/Integer:intValue	()I
    //   75: putstatic 35	uuuuuu/lqqlll:bpp0070p0070ppp0070	I
    //   78: bipush 93
    //   80: putstatic 41	uuuuuu/lqqlll:b0070p0070p0070ppp0070	I
    //   83: getstatic 35	uuuuuu/lqqlll:bpp0070p0070ppp0070	I
    //   86: istore_1
    //   87: getstatic 37	uuuuuu/lqqlll:bp00700070p0070ppp0070	I
    //   90: istore_2
    //   91: getstatic 39	uuuuuu/lqqlll:b007000700070p0070ppp0070	I
    //   94: istore_3
    //   95: getstatic 35	uuuuuu/lqqlll:bpp0070p0070ppp0070	I
    //   98: istore 4
    //   100: getstatic 35	uuuuuu/lqqlll:bpp0070p0070ppp0070	I
    //   103: istore 5
    //   105: iload 5
    //   107: getstatic 37	uuuuuu/lqqlll:bp00700070p0070ppp0070	I
    //   110: iload 5
    //   112: iadd
    //   113: imul
    //   114: getstatic 39	uuuuuu/lqqlll:b007000700070p0070ppp0070	I
    //   117: irem
    //   118: tableswitch	default:+18->136, 0:+68->186
    //   136: bipush 37
    //   138: putstatic 35	uuuuuu/lqqlll:bpp0070p0070ppp0070	I
    //   141: ldc 2
    //   143: ldc 113
    //   145: sipush 173
    //   148: bipush 24
    //   150: iconst_1
    //   151: invokestatic 49	xxxxxx/uxxxxx:bbbb0062b0062b0062b0062	(Ljava/lang/String;CCC)Ljava/lang/String;
    //   154: iconst_0
    //   155: anewarray 51	java/lang/Class
    //   158: invokevirtual 55	java/lang/Class:getMethod	(Ljava/lang/String;[Ljava/lang/Class;)Ljava/lang/reflect/Method;
    //   161: astore 6
    //   163: aload 6
    //   165: aconst_null
    //   166: iconst_0
    //   167: anewarray 57	java/lang/Object
    //   170: invokevirtual 63	java/lang/reflect/Method:invoke	(Ljava/lang/Object;[Ljava/lang/Object;)Ljava/lang/Object;
    //   173: astore 6
    //   175: aload 6
    //   177: checkcast 65	java/lang/Integer
    //   180: invokevirtual 69	java/lang/Integer:intValue	()I
    //   183: putstatic 41	uuuuuu/lqqlll:b0070p0070p0070ppp0070	I
    //   186: getstatic 37	uuuuuu/lqqlll:bp00700070p0070ppp0070	I
    //   189: iload 4
    //   191: iadd
    //   192: iload 4
    //   194: imul
    //   195: getstatic 39	uuuuuu/lqqlll:b007000700070p0070ppp0070	I
    //   198: irem
    //   199: tableswitch	default:+17->216, 0:+65->264
    //   216: ldc 2
    //   218: ldc 115
    //   220: sipush 159
    //   223: iconst_5
    //   224: invokestatic 75	xxxxxx/uxxxxx:bb00620062bb0062b0062b0062	(Ljava/lang/String;CC)Ljava/lang/String;
    //   227: iconst_0
    //   228: anewarray 51	java/lang/Class
    //   231: invokevirtual 55	java/lang/Class:getMethod	(Ljava/lang/String;[Ljava/lang/Class;)Ljava/lang/reflect/Method;
    //   234: astore 6
    //   236: aload 6
    //   238: aconst_null
    //   239: iconst_0
    //   240: anewarray 57	java/lang/Object
    //   243: invokevirtual 63	java/lang/reflect/Method:invoke	(Ljava/lang/Object;[Ljava/lang/Object;)Ljava/lang/Object;
    //   246: astore 6
    //   248: aload 6
    //   250: checkcast 65	java/lang/Integer
    //   253: invokevirtual 69	java/lang/Integer:intValue	()I
    //   256: putstatic 35	uuuuuu/lqqlll:bpp0070p0070ppp0070	I
    //   259: bipush 9
    //   261: putstatic 41	uuuuuu/lqqlll:b0070p0070p0070ppp0070	I
    //   264: iload_2
    //   265: iload_1
    //   266: iadd
    //   267: iload_1
    //   268: imul
    //   269: iload_3
    //   270: irem
    //   271: tableswitch	default:+17->288, 0:+64->335
    //   288: bipush 70
    //   290: putstatic 35	uuuuuu/lqqlll:bpp0070p0070ppp0070	I
    //   293: ldc 2
    //   295: ldc 117
    //   297: bipush 37
    //   299: iconst_0
    //   300: invokestatic 75	xxxxxx/uxxxxx:bb00620062bb0062b0062b0062	(Ljava/lang/String;CC)Ljava/lang/String;
    //   303: iconst_0
    //   304: anewarray 51	java/lang/Class
    //   307: invokevirtual 55	java/lang/Class:getMethod	(Ljava/lang/String;[Ljava/lang/Class;)Ljava/lang/reflect/Method;
    //   310: astore 6
    //   312: aload 6
    //   314: aconst_null
    //   315: iconst_0
    //   316: anewarray 57	java/lang/Object
    //   319: invokevirtual 63	java/lang/reflect/Method:invoke	(Ljava/lang/Object;[Ljava/lang/Object;)Ljava/lang/Object;
    //   322: astore 6
    //   324: aload 6
    //   326: checkcast 65	java/lang/Integer
    //   329: invokevirtual 69	java/lang/Integer:intValue	()I
    //   332: putstatic 41	uuuuuu/lqqlll:b0070p0070p0070ppp0070	I
    //   335: aload_0
    //   336: getfield 105	uuuuuu/lqqlll:bnnnnn006E006E006En	Luuuuuu/ttssst$tsssst;
    //   339: checkcast 119	uuuuuu/qqllll$qlqlll
    //   342: astore 6
    //   344: ldc 121
    //   346: ldc 123
    //   348: sipush 162
    //   351: iconst_5
    //   352: invokestatic 75	xxxxxx/uxxxxx:bb00620062bb0062b0062b0062	(Ljava/lang/String;CC)Ljava/lang/String;
    //   355: iconst_0
    //   356: anewarray 51	java/lang/Class
    //   359: invokevirtual 55	java/lang/Class:getMethod	(Ljava/lang/String;[Ljava/lang/Class;)Ljava/lang/reflect/Method;
    //   362: astore 7
    //   364: aload 7
    //   366: aconst_null
    //   367: iconst_0
    //   368: anewarray 57	java/lang/Object
    //   371: invokevirtual 63	java/lang/reflect/Method:invoke	(Ljava/lang/Object;[Ljava/lang/Object;)Ljava/lang/Object;
    //   374: astore 7
    //   376: aload 7
    //   378: checkcast 121	com/db/pwcc/dbmobile/secure/preferences/SharedPreferencesHelper
    //   381: astore 7
    //   383: ldc 121
    //   385: ldc 125
    //   387: sipush 206
    //   390: bipush 42
    //   392: iconst_3
    //   393: invokestatic 49	xxxxxx/uxxxxx:bbbb0062b0062b0062b0062	(Ljava/lang/String;CCC)Ljava/lang/String;
    //   396: iconst_0
    //   397: anewarray 51	java/lang/Class
    //   400: invokevirtual 55	java/lang/Class:getMethod	(Ljava/lang/String;[Ljava/lang/Class;)Ljava/lang/reflect/Method;
    //   403: astore 8
    //   405: aload 8
    //   407: aload 7
    //   409: iconst_0
    //   410: anewarray 57	java/lang/Object
    //   413: invokevirtual 63	java/lang/reflect/Method:invoke	(Ljava/lang/Object;[Ljava/lang/Object;)Ljava/lang/Object;
    //   416: astore 7
    //   418: aload 6
    //   420: aload 7
    //   422: checkcast 127	java/lang/Boolean
    //   425: invokevirtual 131	java/lang/Boolean:booleanValue	()Z
    //   428: invokeinterface 135 2 0
    //   433: return
    //   434: astore 6
    //   436: aload 6
    //   438: invokevirtual 96	java/lang/reflect/InvocationTargetException:getCause	()Ljava/lang/Throwable;
    //   441: athrow
    //   442: astore 6
    //   444: aload 6
    //   446: invokevirtual 96	java/lang/reflect/InvocationTargetException:getCause	()Ljava/lang/Throwable;
    //   449: athrow
    //   450: astore 6
    //   452: aload 6
    //   454: invokevirtual 96	java/lang/reflect/InvocationTargetException:getCause	()Ljava/lang/Throwable;
    //   457: athrow
    //   458: astore 6
    //   460: aload 6
    //   462: invokevirtual 96	java/lang/reflect/InvocationTargetException:getCause	()Ljava/lang/Throwable;
    //   465: athrow
    //   466: astore 6
    //   468: aload 6
    //   470: invokevirtual 96	java/lang/reflect/InvocationTargetException:getCause	()Ljava/lang/Throwable;
    //   473: athrow
    //   474: astore 6
    //   476: aload 6
    //   478: invokevirtual 96	java/lang/reflect/InvocationTargetException:getCause	()Ljava/lang/Throwable;
    //   481: athrow
    // Local variable table:
    //   start	length	slot	name	signature
    //   0	482	0	this	lqqlll
    //   3	266	1	i	int
    //   90	177	2	j	int
    //   94	177	3	k	int
    //   98	97	4	m	int
    //   103	11	5	n	int
    //   53	366	6	localObject1	Object
    //   434	3	6	localInvocationTargetException1	java.lang.reflect.InvocationTargetException
    //   442	3	6	localInvocationTargetException2	java.lang.reflect.InvocationTargetException
    //   450	3	6	localInvocationTargetException3	java.lang.reflect.InvocationTargetException
    //   458	3	6	localInvocationTargetException4	java.lang.reflect.InvocationTargetException
    //   466	3	6	localInvocationTargetException5	java.lang.reflect.InvocationTargetException
    //   474	3	6	localInvocationTargetException6	java.lang.reflect.InvocationTargetException
    //   362	59	7	localObject2	Object
    //   403	3	8	localMethod	java.lang.reflect.Method
    // Exception table:
    //   from	to	target	type
    //   364	376	434	java/lang/reflect/InvocationTargetException
    //   405	418	442	java/lang/reflect/InvocationTargetException
    //   55	67	450	java/lang/reflect/InvocationTargetException
    //   312	324	458	java/lang/reflect/InvocationTargetException
    //   236	248	466	java/lang/reflect/InvocationTargetException
    //   163	175	474	java/lang/reflect/InvocationTargetException
  }
  
  public abstract void boo006F006Fooo006Foo(CashAccountTransaction paramCashAccountTransaction, boolean paramBoolean);
  
  /* Error */
  public com.db.pwcc.dbmobile.model.friend.Friend booo006Fooo006Foo(String paramString1, String paramString2, String paramString3)
  {
    // Byte code:
    //   0: getstatic 35	uuuuuu/lqqlll:bpp0070p0070ppp0070	I
    //   3: istore 4
    //   5: getstatic 35	uuuuuu/lqqlll:bpp0070p0070ppp0070	I
    //   8: istore 5
    //   10: iload 5
    //   12: getstatic 37	uuuuuu/lqqlll:bp00700070p0070ppp0070	I
    //   15: iload 5
    //   17: iadd
    //   18: imul
    //   19: getstatic 39	uuuuuu/lqqlll:b007000700070p0070ppp0070	I
    //   22: irem
    //   23: tableswitch	default:+17->40, 0:+106->129
    //   40: ldc 2
    //   42: ldc -115
    //   44: sipush 214
    //   47: sipush 204
    //   50: iconst_2
    //   51: invokestatic 49	xxxxxx/uxxxxx:bbbb0062b0062b0062b0062	(Ljava/lang/String;CCC)Ljava/lang/String;
    //   54: iconst_0
    //   55: anewarray 51	java/lang/Class
    //   58: invokevirtual 55	java/lang/Class:getMethod	(Ljava/lang/String;[Ljava/lang/Class;)Ljava/lang/reflect/Method;
    //   61: astore 12
    //   63: aload 12
    //   65: aconst_null
    //   66: iconst_0
    //   67: anewarray 57	java/lang/Object
    //   70: invokevirtual 63	java/lang/reflect/Method:invoke	(Ljava/lang/Object;[Ljava/lang/Object;)Ljava/lang/Object;
    //   73: astore 12
    //   75: aload 12
    //   77: checkcast 65	java/lang/Integer
    //   80: invokevirtual 69	java/lang/Integer:intValue	()I
    //   83: putstatic 35	uuuuuu/lqqlll:bpp0070p0070ppp0070	I
    //   86: ldc 2
    //   88: ldc -113
    //   90: sipush 189
    //   93: iconst_5
    //   94: invokestatic 75	xxxxxx/uxxxxx:bb00620062bb0062b0062b0062	(Ljava/lang/String;CC)Ljava/lang/String;
    //   97: iconst_0
    //   98: anewarray 51	java/lang/Class
    //   101: invokevirtual 55	java/lang/Class:getMethod	(Ljava/lang/String;[Ljava/lang/Class;)Ljava/lang/reflect/Method;
    //   104: astore 12
    //   106: aload 12
    //   108: aconst_null
    //   109: iconst_0
    //   110: anewarray 57	java/lang/Object
    //   113: invokevirtual 63	java/lang/reflect/Method:invoke	(Ljava/lang/Object;[Ljava/lang/Object;)Ljava/lang/Object;
    //   116: astore 12
    //   118: aload 12
    //   120: checkcast 65	java/lang/Integer
    //   123: invokevirtual 69	java/lang/Integer:intValue	()I
    //   126: putstatic 41	uuuuuu/lqqlll:b0070p0070p0070ppp0070	I
    //   129: getstatic 37	uuuuuu/lqqlll:bp00700070p0070ppp0070	I
    //   132: istore 5
    //   134: getstatic 35	uuuuuu/lqqlll:bpp0070p0070ppp0070	I
    //   137: istore 6
    //   139: getstatic 39	uuuuuu/lqqlll:b007000700070p0070ppp0070	I
    //   142: istore 7
    //   144: getstatic 35	uuuuuu/lqqlll:bpp0070p0070ppp0070	I
    //   147: istore 8
    //   149: getstatic 37	uuuuuu/lqqlll:bp00700070p0070ppp0070	I
    //   152: istore 9
    //   154: getstatic 35	uuuuuu/lqqlll:bpp0070p0070ppp0070	I
    //   157: istore 10
    //   159: getstatic 39	uuuuuu/lqqlll:b007000700070p0070ppp0070	I
    //   162: istore 11
    //   164: ldc 2
    //   166: ldc -111
    //   168: sipush 154
    //   171: iconst_2
    //   172: invokestatic 75	xxxxxx/uxxxxx:bb00620062bb0062b0062b0062	(Ljava/lang/String;CC)Ljava/lang/String;
    //   175: iconst_0
    //   176: anewarray 51	java/lang/Class
    //   179: invokevirtual 55	java/lang/Class:getMethod	(Ljava/lang/String;[Ljava/lang/Class;)Ljava/lang/reflect/Method;
    //   182: astore 12
    //   184: aload 12
    //   186: aconst_null
    //   187: iconst_0
    //   188: anewarray 57	java/lang/Object
    //   191: invokevirtual 63	java/lang/reflect/Method:invoke	(Ljava/lang/Object;[Ljava/lang/Object;)Ljava/lang/Object;
    //   194: astore 12
    //   196: iload 8
    //   198: iload 9
    //   200: iadd
    //   201: iload 10
    //   203: imul
    //   204: iload 11
    //   206: irem
    //   207: aload 12
    //   209: checkcast 65	java/lang/Integer
    //   212: invokevirtual 69	java/lang/Integer:intValue	()I
    //   215: if_icmpeq +50 -> 265
    //   218: bipush 37
    //   220: putstatic 35	uuuuuu/lqqlll:bpp0070p0070ppp0070	I
    //   223: ldc 2
    //   225: ldc -109
    //   227: bipush 40
    //   229: iconst_2
    //   230: invokestatic 75	xxxxxx/uxxxxx:bb00620062bb0062b0062b0062	(Ljava/lang/String;CC)Ljava/lang/String;
    //   233: iconst_0
    //   234: anewarray 51	java/lang/Class
    //   237: invokevirtual 55	java/lang/Class:getMethod	(Ljava/lang/String;[Ljava/lang/Class;)Ljava/lang/reflect/Method;
    //   240: astore 12
    //   242: aload 12
    //   244: aconst_null
    //   245: iconst_0
    //   246: anewarray 57	java/lang/Object
    //   249: invokevirtual 63	java/lang/reflect/Method:invoke	(Ljava/lang/Object;[Ljava/lang/Object;)Ljava/lang/Object;
    //   252: astore 12
    //   254: aload 12
    //   256: checkcast 65	java/lang/Integer
    //   259: invokevirtual 69	java/lang/Integer:intValue	()I
    //   262: putstatic 41	uuuuuu/lqqlll:b0070p0070p0070ppp0070	I
    //   265: ldc 2
    //   267: ldc -107
    //   269: bipush 65
    //   271: iconst_5
    //   272: invokestatic 75	xxxxxx/uxxxxx:bb00620062bb0062b0062b0062	(Ljava/lang/String;CC)Ljava/lang/String;
    //   275: iconst_0
    //   276: anewarray 51	java/lang/Class
    //   279: invokevirtual 55	java/lang/Class:getMethod	(Ljava/lang/String;[Ljava/lang/Class;)Ljava/lang/reflect/Method;
    //   282: astore 12
    //   284: aload 12
    //   286: aconst_null
    //   287: iconst_0
    //   288: anewarray 57	java/lang/Object
    //   291: invokevirtual 63	java/lang/reflect/Method:invoke	(Ljava/lang/Object;[Ljava/lang/Object;)Ljava/lang/Object;
    //   294: astore 12
    //   296: iload 6
    //   298: iload 5
    //   300: iload 4
    //   302: iadd
    //   303: imul
    //   304: iload 7
    //   306: irem
    //   307: aload 12
    //   309: checkcast 65	java/lang/Integer
    //   312: invokevirtual 69	java/lang/Integer:intValue	()I
    //   315: if_icmpeq +135 -> 450
    //   318: bipush 95
    //   320: putstatic 35	uuuuuu/lqqlll:bpp0070p0070ppp0070	I
    //   323: ldc 2
    //   325: ldc -105
    //   327: bipush 30
    //   329: iconst_0
    //   330: invokestatic 75	xxxxxx/uxxxxx:bb00620062bb0062b0062b0062	(Ljava/lang/String;CC)Ljava/lang/String;
    //   333: iconst_0
    //   334: anewarray 51	java/lang/Class
    //   337: invokevirtual 55	java/lang/Class:getMethod	(Ljava/lang/String;[Ljava/lang/Class;)Ljava/lang/reflect/Method;
    //   340: astore 12
    //   342: aload 12
    //   344: aconst_null
    //   345: iconst_0
    //   346: anewarray 57	java/lang/Object
    //   349: invokevirtual 63	java/lang/reflect/Method:invoke	(Ljava/lang/Object;[Ljava/lang/Object;)Ljava/lang/Object;
    //   352: astore 12
    //   354: aload 12
    //   356: checkcast 65	java/lang/Integer
    //   359: invokevirtual 69	java/lang/Integer:intValue	()I
    //   362: putstatic 41	uuuuuu/lqqlll:b0070p0070p0070ppp0070	I
    //   365: getstatic 35	uuuuuu/lqqlll:bpp0070p0070ppp0070	I
    //   368: istore 4
    //   370: iload 4
    //   372: getstatic 37	uuuuuu/lqqlll:bp00700070p0070ppp0070	I
    //   375: iload 4
    //   377: iadd
    //   378: imul
    //   379: getstatic 39	uuuuuu/lqqlll:b007000700070p0070ppp0070	I
    //   382: irem
    //   383: tableswitch	default:+17->400, 0:+67->450
    //   400: bipush 8
    //   402: putstatic 35	uuuuuu/lqqlll:bpp0070p0070ppp0070	I
    //   405: ldc 2
    //   407: ldc -103
    //   409: bipush 109
    //   411: sipush 190
    //   414: iconst_1
    //   415: invokestatic 49	xxxxxx/uxxxxx:bbbb0062b0062b0062b0062	(Ljava/lang/String;CCC)Ljava/lang/String;
    //   418: iconst_0
    //   419: anewarray 51	java/lang/Class
    //   422: invokevirtual 55	java/lang/Class:getMethod	(Ljava/lang/String;[Ljava/lang/Class;)Ljava/lang/reflect/Method;
    //   425: astore 12
    //   427: aload 12
    //   429: aconst_null
    //   430: iconst_0
    //   431: anewarray 57	java/lang/Object
    //   434: invokevirtual 63	java/lang/reflect/Method:invoke	(Ljava/lang/Object;[Ljava/lang/Object;)Ljava/lang/Object;
    //   437: astore 12
    //   439: aload 12
    //   441: checkcast 65	java/lang/Integer
    //   444: invokevirtual 69	java/lang/Integer:intValue	()I
    //   447: putstatic 41	uuuuuu/lqqlll:b0070p0070p0070ppp0070	I
    //   450: new 155	com/db/pwcc/dbmobile/model/friend/Friend
    //   453: dup
    //   454: aload_1
    //   455: aload_2
    //   456: aload_3
    //   457: invokespecial 158	com/db/pwcc/dbmobile/model/friend/Friend:<init>	(Ljava/lang/String;Ljava/lang/String;Ljava/lang/String;)V
    //   460: areturn
    //   461: astore_1
    //   462: aload_1
    //   463: invokevirtual 96	java/lang/reflect/InvocationTargetException:getCause	()Ljava/lang/Throwable;
    //   466: athrow
    //   467: astore_1
    //   468: aload_1
    //   469: invokevirtual 96	java/lang/reflect/InvocationTargetException:getCause	()Ljava/lang/Throwable;
    //   472: athrow
    //   473: astore_1
    //   474: aload_1
    //   475: invokevirtual 96	java/lang/reflect/InvocationTargetException:getCause	()Ljava/lang/Throwable;
    //   478: athrow
    //   479: astore_1
    //   480: aload_1
    //   481: invokevirtual 96	java/lang/reflect/InvocationTargetException:getCause	()Ljava/lang/Throwable;
    //   484: athrow
    //   485: astore_1
    //   486: aload_1
    //   487: invokevirtual 96	java/lang/reflect/InvocationTargetException:getCause	()Ljava/lang/Throwable;
    //   490: athrow
    //   491: astore_1
    //   492: aload_1
    //   493: invokevirtual 96	java/lang/reflect/InvocationTargetException:getCause	()Ljava/lang/Throwable;
    //   496: athrow
    //   497: astore_1
    //   498: aload_1
    //   499: invokevirtual 96	java/lang/reflect/InvocationTargetException:getCause	()Ljava/lang/Throwable;
    //   502: athrow
    // Local variable table:
    //   start	length	slot	name	signature
    //   0	503	0	this	lqqlll
    //   0	503	1	paramString1	String
    //   0	503	2	paramString2	String
    //   0	503	3	paramString3	String
    //   3	376	4	i	int
    //   8	295	5	j	int
    //   137	167	6	k	int
    //   142	165	7	m	int
    //   147	54	8	n	int
    //   152	49	9	i1	int
    //   157	47	10	i2	int
    //   162	45	11	i3	int
    //   61	379	12	localObject	Object
    // Exception table:
    //   from	to	target	type
    //   63	75	461	java/lang/reflect/InvocationTargetException
    //   106	118	467	java/lang/reflect/InvocationTargetException
    //   284	296	473	java/lang/reflect/InvocationTargetException
    //   184	196	479	java/lang/reflect/InvocationTargetException
    //   342	354	485	java/lang/reflect/InvocationTargetException
    //   427	439	491	java/lang/reflect/InvocationTargetException
    //   242	254	497	java/lang/reflect/InvocationTargetException
  }
}
