package uuuuuu;

import android.content.Context;
import com.db.pwcc.dbmobile.multi_bank_aggregator.model.EfiSuggestion;
import com.db.pwcc.dbmobile.multi_bank_aggregator.model.ExternalFinancialInstitute;
import java.lang.reflect.InvocationTargetException;
import java.lang.reflect.Method;
import java.util.ArrayList;
import java.util.Arrays;
import java.util.Iterator;
import java.util.List;
import javax.inject.Inject;
import xxxxxx.uxxxxx;

public class mmmmmq
  extends qppppp<qqmmmq.qmmmmq>
  implements qqmmmq.mqmmmq, vxvvvv.xvvvvv, alllll.lallll, mmqqqm
{
  public static int b007600760076vvvv0076v = 13;
  public static int b0076vv0076vvv0076v = 1;
  public static int bv0076v0076vvv0076v = 2;
  public static int bvvv0076vvv0076v;
  public final List<ExternalFinancialInstitute> b00760076vvvvv0076v = new ArrayList();
  private vxvxvx b0076v0076vvvv0076v;
  @Inject
  public Context b0076vvvvvv0076v;
  private String bv00760076vvvv0076v;
  public boolean bv0076vvvvv0076v = false;
  private boolean bvv0076vvvv0076v;
  
  public mmmmmq()
  {
    xvvvxx.b0075uu00750075007500750075u0075().b0070pp00700070ppppp(this);
    this.b0076v0076vvvv0076v = new vxvxvx(this.b0076vvvvvv0076v);
    this.bvv0076vvvv0076v = true;
  }
  
  public static int b0075007500750075u0075uuu0075()
  {
    return 53;
  }
  
  private void b00750075u007500750075uuu0075(List<ExternalFinancialInstitute> paramList)
  {
    throw new Runtime("d2j fail translate: java.lang.IndexOutOfBoundsException: fromIndex < 0: -1\n\tat java.util.BitSet.nextSetBit(BitSet.java:712)\n\tat com.googlecode.dex2jar.ir.ts.array.FillArrayTransformer.makeSureAllElementAreAssigned(FillArrayTransformer.java:505)\n\tat com.googlecode.dex2jar.ir.ts.array.FillArrayTransformer.transformReportChanged(FillArrayTransformer.java:123)\n\tat com.googlecode.dex2jar.ir.ts.StatedTransformer.transform(StatedTransformer.java:10)\n\tat com.googlecode.d2j.dex.Dex2jar$2.optimize(Dex2jar.java:149)\n\tat com.googlecode.d2j.dex.Dex2Asm.convertCode(Dex2Asm.java:414)\n\tat com.googlecode.d2j.dex.ExDex2Asm.convertCode(ExDex2Asm.java:42)\n\tat com.googlecode.d2j.dex.Dex2jar$2.convertCode(Dex2jar.java:128)\n\tat com.googlecode.d2j.dex.Dex2Asm.convertMethod(Dex2Asm.java:509)\n\tat com.googlecode.d2j.dex.Dex2Asm.convertClass(Dex2Asm.java:406)\n\tat com.googlecode.d2j.dex.Dex2Asm.convertDex(Dex2Asm.java:422)\n\tat com.googlecode.d2j.dex.Dex2jar.doTranslate(Dex2jar.java:172)\n\tat com.googlecode.d2j.dex.Dex2jar.to(Dex2jar.java:272)\n\tat com.googlecode.dex2jar.tools.Dex2jarCmd.doCommandLine(Dex2jarCmd.java:108)\n\tat com.googlecode.dex2jar.tools.BaseCmd.doMain(BaseCmd.java:288)\n\tat com.googlecode.dex2jar.tools.Dex2jarCmd.main(Dex2jarCmd.java:32)\n");
  }
  
  /* Error */
  private void b00750075uu00750075uuu0075(List<ExternalFinancialInstitute> paramList)
  {
    // Byte code:
    //   0: aload_1
    //   1: astore 5
    //   3: aload_1
    //   4: ifnonnull +76 -> 80
    //   7: getstatic 89	uuuuuu/mmmmmq:b007600760076vvvv0076v	I
    //   10: getstatic 91	uuuuuu/mmmmmq:b0076vv0076vvv0076v	I
    //   13: iadd
    //   14: getstatic 89	uuuuuu/mmmmmq:b007600760076vvvv0076v	I
    //   17: imul
    //   18: getstatic 93	uuuuuu/mmmmmq:bv0076v0076vvv0076v	I
    //   21: irem
    //   22: getstatic 95	uuuuuu/mmmmmq:bvvv0076vvv0076v	I
    //   25: if_icmpeq +46 -> 71
    //   28: ldc 2
    //   30: ldc 97
    //   32: bipush 116
    //   34: iconst_1
    //   35: invokestatic 103	xxxxxx/uxxxxx:bb00620062bb0062b0062b0062	(Ljava/lang/String;CC)Ljava/lang/String;
    //   38: iconst_0
    //   39: anewarray 105	java/lang/Class
    //   42: invokevirtual 109	java/lang/Class:getMethod	(Ljava/lang/String;[Ljava/lang/Class;)Ljava/lang/reflect/Method;
    //   45: astore_1
    //   46: aload_1
    //   47: aconst_null
    //   48: iconst_0
    //   49: anewarray 111	java/lang/Object
    //   52: invokevirtual 117	java/lang/reflect/Method:invoke	(Ljava/lang/Object;[Ljava/lang/Object;)Ljava/lang/Object;
    //   55: astore_1
    //   56: aload_1
    //   57: checkcast 119	java/lang/Integer
    //   60: invokevirtual 122	java/lang/Integer:intValue	()I
    //   63: putstatic 89	uuuuuu/mmmmmq:b007600760076vvvv0076v	I
    //   66: bipush 13
    //   68: putstatic 95	uuuuuu/mmmmmq:bvvv0076vvv0076v	I
    //   71: new 40	java/util/ArrayList
    //   74: dup
    //   75: invokespecial 41	java/util/ArrayList:<init>	()V
    //   78: astore 5
    //   80: aload 5
    //   82: invokeinterface 128 1 0
    //   87: ifne +98 -> 185
    //   90: ldc 2
    //   92: ldc -126
    //   94: bipush 81
    //   96: iconst_5
    //   97: invokestatic 103	xxxxxx/uxxxxx:bb00620062bb0062b0062b0062	(Ljava/lang/String;CC)Ljava/lang/String;
    //   100: iconst_1
    //   101: anewarray 105	java/lang/Class
    //   104: dup
    //   105: iconst_0
    //   106: ldc 124
    //   108: aastore
    //   109: invokevirtual 133	java/lang/Class:getDeclaredMethod	(Ljava/lang/String;[Ljava/lang/Class;)Ljava/lang/reflect/Method;
    //   112: astore_1
    //   113: aload_1
    //   114: aload_0
    //   115: iconst_1
    //   116: anewarray 111	java/lang/Object
    //   119: dup
    //   120: iconst_0
    //   121: aload 5
    //   123: aastore
    //   124: invokevirtual 117	java/lang/reflect/Method:invoke	(Ljava/lang/Object;[Ljava/lang/Object;)Ljava/lang/Object;
    //   127: pop
    //   128: aload 5
    //   130: invokeinterface 137 1 0
    //   135: astore 7
    //   137: aconst_null
    //   138: astore_1
    //   139: iconst_0
    //   140: istore_2
    //   141: aload 7
    //   143: invokeinterface 142 1 0
    //   148: ifeq +369 -> 517
    //   151: aload 7
    //   153: invokeinterface 146 1 0
    //   158: checkcast 148	com/db/pwcc/dbmobile/multi_bank_aggregator/model/ExternalFinancialInstitute
    //   161: astore 6
    //   163: aload 6
    //   165: aload_0
    //   166: getfield 150	uuuuuu/mmmmmq:bv00760076vvvv0076v	Ljava/lang/String;
    //   169: invokevirtual 154	com/db/pwcc/dbmobile/multi_bank_aggregator/model/ExternalFinancialInstitute:matches	(Ljava/lang/String;)Z
    //   172: ifeq -31 -> 141
    //   175: iload_2
    //   176: iconst_1
    //   177: iadd
    //   178: istore_2
    //   179: aload 6
    //   181: astore_1
    //   182: goto -41 -> 141
    //   185: aload_0
    //   186: getfield 158	uuuuuu/mmmmmq:bnnnnn006E006E006En	Luuuuuu/ttssst$tsssst;
    //   189: checkcast 160	uuuuuu/qqmmmq$qmmmmq
    //   192: astore_1
    //   193: getstatic 89	uuuuuu/mmmmmq:b007600760076vvvv0076v	I
    //   196: istore_2
    //   197: getstatic 91	uuuuuu/mmmmmq:b0076vv0076vvv0076v	I
    //   200: istore_3
    //   201: getstatic 89	uuuuuu/mmmmmq:b007600760076vvvv0076v	I
    //   204: istore 4
    //   206: ldc 2
    //   208: ldc -94
    //   210: sipush 252
    //   213: iconst_1
    //   214: invokestatic 103	xxxxxx/uxxxxx:bb00620062bb0062b0062b0062	(Ljava/lang/String;CC)Ljava/lang/String;
    //   217: iconst_0
    //   218: anewarray 105	java/lang/Class
    //   221: invokevirtual 109	java/lang/Class:getMethod	(Ljava/lang/String;[Ljava/lang/Class;)Ljava/lang/reflect/Method;
    //   224: astore 6
    //   226: aload 6
    //   228: aconst_null
    //   229: iconst_0
    //   230: anewarray 111	java/lang/Object
    //   233: invokevirtual 117	java/lang/reflect/Method:invoke	(Ljava/lang/Object;[Ljava/lang/Object;)Ljava/lang/Object;
    //   236: astore 6
    //   238: iload 4
    //   240: iload_2
    //   241: iload_3
    //   242: iadd
    //   243: imul
    //   244: aload 6
    //   246: checkcast 119	java/lang/Integer
    //   249: invokevirtual 122	java/lang/Integer:intValue	()I
    //   252: irem
    //   253: getstatic 95	uuuuuu/mmmmmq:bvvv0076vvv0076v	I
    //   256: if_icmpeq +157 -> 413
    //   259: getstatic 89	uuuuuu/mmmmmq:b007600760076vvvv0076v	I
    //   262: getstatic 91	uuuuuu/mmmmmq:b0076vv0076vvv0076v	I
    //   265: iadd
    //   266: getstatic 89	uuuuuu/mmmmmq:b007600760076vvvv0076v	I
    //   269: imul
    //   270: getstatic 93	uuuuuu/mmmmmq:bv0076v0076vvv0076v	I
    //   273: irem
    //   274: getstatic 95	uuuuuu/mmmmmq:bvvv0076vvv0076v	I
    //   277: if_icmpeq +89 -> 366
    //   280: ldc 2
    //   282: ldc -92
    //   284: bipush 20
    //   286: iconst_3
    //   287: invokestatic 103	xxxxxx/uxxxxx:bb00620062bb0062b0062b0062	(Ljava/lang/String;CC)Ljava/lang/String;
    //   290: iconst_0
    //   291: anewarray 105	java/lang/Class
    //   294: invokevirtual 109	java/lang/Class:getMethod	(Ljava/lang/String;[Ljava/lang/Class;)Ljava/lang/reflect/Method;
    //   297: astore 6
    //   299: aload 6
    //   301: aconst_null
    //   302: iconst_0
    //   303: anewarray 111	java/lang/Object
    //   306: invokevirtual 117	java/lang/reflect/Method:invoke	(Ljava/lang/Object;[Ljava/lang/Object;)Ljava/lang/Object;
    //   309: astore 6
    //   311: aload 6
    //   313: checkcast 119	java/lang/Integer
    //   316: invokevirtual 122	java/lang/Integer:intValue	()I
    //   319: putstatic 89	uuuuuu/mmmmmq:b007600760076vvvv0076v	I
    //   322: ldc 2
    //   324: ldc -90
    //   326: bipush 11
    //   328: bipush 96
    //   330: iconst_1
    //   331: invokestatic 170	xxxxxx/uxxxxx:bbbb0062b0062b0062b0062	(Ljava/lang/String;CCC)Ljava/lang/String;
    //   334: iconst_0
    //   335: anewarray 105	java/lang/Class
    //   338: invokevirtual 109	java/lang/Class:getMethod	(Ljava/lang/String;[Ljava/lang/Class;)Ljava/lang/reflect/Method;
    //   341: astore 6
    //   343: aload 6
    //   345: aconst_null
    //   346: iconst_0
    //   347: anewarray 111	java/lang/Object
    //   350: invokevirtual 117	java/lang/reflect/Method:invoke	(Ljava/lang/Object;[Ljava/lang/Object;)Ljava/lang/Object;
    //   353: astore 6
    //   355: aload 6
    //   357: checkcast 119	java/lang/Integer
    //   360: invokevirtual 122	java/lang/Integer:intValue	()I
    //   363: putstatic 95	uuuuuu/mmmmmq:bvvv0076vvv0076v	I
    //   366: ldc 2
    //   368: ldc -84
    //   370: bipush 18
    //   372: iconst_0
    //   373: invokestatic 103	xxxxxx/uxxxxx:bb00620062bb0062b0062b0062	(Ljava/lang/String;CC)Ljava/lang/String;
    //   376: iconst_0
    //   377: anewarray 105	java/lang/Class
    //   380: invokevirtual 109	java/lang/Class:getMethod	(Ljava/lang/String;[Ljava/lang/Class;)Ljava/lang/reflect/Method;
    //   383: astore 6
    //   385: aload 6
    //   387: aconst_null
    //   388: iconst_0
    //   389: anewarray 111	java/lang/Object
    //   392: invokevirtual 117	java/lang/reflect/Method:invoke	(Ljava/lang/Object;[Ljava/lang/Object;)Ljava/lang/Object;
    //   395: astore 6
    //   397: aload 6
    //   399: checkcast 119	java/lang/Integer
    //   402: invokevirtual 122	java/lang/Integer:intValue	()I
    //   405: putstatic 89	uuuuuu/mmmmmq:b007600760076vvvv0076v	I
    //   408: bipush 75
    //   410: putstatic 95	uuuuuu/mmmmmq:bvvv0076vvv0076v	I
    //   413: aload_1
    //   414: aload_0
    //   415: getfield 150	uuuuuu/mmmmmq:bv00760076vvvv0076v	Ljava/lang/String;
    //   418: invokeinterface 175 2 0
    //   423: aload_0
    //   424: getfield 158	uuuuuu/mmmmmq:bnnnnn006E006E006En	Luuuuuu/ttssst$tsssst;
    //   427: checkcast 160	uuuuuu/qqmmmq$qmmmmq
    //   430: astore_1
    //   431: getstatic 89	uuuuuu/mmmmmq:b007600760076vvvv0076v	I
    //   434: getstatic 91	uuuuuu/mmmmmq:b0076vv0076vvv0076v	I
    //   437: iadd
    //   438: getstatic 89	uuuuuu/mmmmmq:b007600760076vvvv0076v	I
    //   441: imul
    //   442: getstatic 93	uuuuuu/mmmmmq:bv0076v0076vvv0076v	I
    //   445: irem
    //   446: getstatic 95	uuuuuu/mmmmmq:bvvv0076vvv0076v	I
    //   449: if_icmpeq +53 -> 502
    //   452: bipush 64
    //   454: putstatic 89	uuuuuu/mmmmmq:b007600760076vvvv0076v	I
    //   457: ldc 2
    //   459: ldc -79
    //   461: bipush 16
    //   463: sipush 215
    //   466: iconst_3
    //   467: invokestatic 170	xxxxxx/uxxxxx:bbbb0062b0062b0062b0062	(Ljava/lang/String;CCC)Ljava/lang/String;
    //   470: iconst_0
    //   471: anewarray 105	java/lang/Class
    //   474: invokevirtual 109	java/lang/Class:getMethod	(Ljava/lang/String;[Ljava/lang/Class;)Ljava/lang/reflect/Method;
    //   477: astore 6
    //   479: aload 6
    //   481: aconst_null
    //   482: iconst_0
    //   483: anewarray 111	java/lang/Object
    //   486: invokevirtual 117	java/lang/reflect/Method:invoke	(Ljava/lang/Object;[Ljava/lang/Object;)Ljava/lang/Object;
    //   489: astore 6
    //   491: aload 6
    //   493: checkcast 119	java/lang/Integer
    //   496: invokevirtual 122	java/lang/Integer:intValue	()I
    //   499: putstatic 95	uuuuuu/mmmmmq:bvvv0076vvv0076v	I
    //   502: aload_1
    //   503: aload 5
    //   505: invokeinterface 180 2 0
    //   510: return
    //   511: astore_1
    //   512: aload_1
    //   513: invokevirtual 184	java/lang/reflect/InvocationTargetException:getCause	()Ljava/lang/Throwable;
    //   516: athrow
    //   517: aload_1
    //   518: ifnull -333 -> 185
    //   521: iload_2
    //   522: iconst_1
    //   523: if_icmpne -338 -> 185
    //   526: aload_0
    //   527: getfield 158	uuuuuu/mmmmmq:bnnnnn006E006E006En	Luuuuuu/ttssst$tsssst;
    //   530: checkcast 160	uuuuuu/qqmmmq$qmmmmq
    //   533: aload_1
    //   534: invokevirtual 188	com/db/pwcc/dbmobile/multi_bank_aggregator/model/ExternalFinancialInstitute:getId	()Ljava/lang/Integer;
    //   537: invokevirtual 122	java/lang/Integer:intValue	()I
    //   540: aload_0
    //   541: getfield 66	uuuuuu/mmmmmq:b0076v0076vvvv0076v	Luuuuuu/vxvxvx;
    //   544: aload_1
    //   545: invokevirtual 192	com/db/pwcc/dbmobile/multi_bank_aggregator/model/ExternalFinancialInstitute:getBlz	()Ljava/lang/String;
    //   548: invokevirtual 196	uuuuuu/vxvxvx:b00750075uu0075uuu00750075	(Ljava/lang/String;)I
    //   551: invokeinterface 200 3 0
    //   556: aload_0
    //   557: ldc -54
    //   559: putfield 150	uuuuuu/mmmmmq:bv00760076vvvv0076v	Ljava/lang/String;
    //   562: return
    //   563: astore_1
    //   564: aload_1
    //   565: invokevirtual 184	java/lang/reflect/InvocationTargetException:getCause	()Ljava/lang/Throwable;
    //   568: athrow
    //   569: astore_1
    //   570: aload_1
    //   571: invokevirtual 184	java/lang/reflect/InvocationTargetException:getCause	()Ljava/lang/Throwable;
    //   574: athrow
    //   575: astore_1
    //   576: aload_1
    //   577: invokevirtual 184	java/lang/reflect/InvocationTargetException:getCause	()Ljava/lang/Throwable;
    //   580: athrow
    //   581: astore_1
    //   582: aload_1
    //   583: invokevirtual 184	java/lang/reflect/InvocationTargetException:getCause	()Ljava/lang/Throwable;
    //   586: athrow
    //   587: astore_1
    //   588: aload_1
    //   589: invokevirtual 184	java/lang/reflect/InvocationTargetException:getCause	()Ljava/lang/Throwable;
    //   592: athrow
    //   593: astore_1
    //   594: aload_1
    //   595: invokevirtual 184	java/lang/reflect/InvocationTargetException:getCause	()Ljava/lang/Throwable;
    //   598: athrow
    // Local variable table:
    //   start	length	slot	name	signature
    //   0	599	0	this	mmmmmq
    //   0	599	1	paramList	List<ExternalFinancialInstitute>
    //   140	384	2	i	int
    //   200	43	3	j	int
    //   204	40	4	k	int
    //   1	503	5	localObject1	Object
    //   161	331	6	localObject2	Object
    //   135	17	7	localIterator	Iterator
    // Exception table:
    //   from	to	target	type
    //   226	238	511	java/lang/reflect/InvocationTargetException
    //   385	397	563	java/lang/reflect/InvocationTargetException
    //   113	128	569	java/lang/reflect/InvocationTargetException
    //   299	311	575	java/lang/reflect/InvocationTargetException
    //   343	355	581	java/lang/reflect/InvocationTargetException
    //   479	491	587	java/lang/reflect/InvocationTargetException
    //   46	56	593	java/lang/reflect/InvocationTargetException
  }
  
  /* Error */
  private void b0075u0075u00750075uuu0075(List<ExternalFinancialInstitute> paramList)
  {
    // Byte code:
    //   0: getstatic 89	uuuuuu/mmmmmq:b007600760076vvvv0076v	I
    //   3: istore_2
    //   4: iload_2
    //   5: getstatic 91	uuuuuu/mmmmmq:b0076vv0076vvv0076v	I
    //   8: iload_2
    //   9: iadd
    //   10: imul
    //   11: getstatic 93	uuuuuu/mmmmmq:bv0076v0076vvv0076v	I
    //   14: irem
    //   15: tableswitch	default:+17->32, 0:+64->79
    //   32: iconst_5
    //   33: putstatic 89	uuuuuu/mmmmmq:b007600760076vvvv0076v	I
    //   36: ldc 2
    //   38: ldc -51
    //   40: sipush 214
    //   43: iconst_2
    //   44: invokestatic 103	xxxxxx/uxxxxx:bb00620062bb0062b0062b0062	(Ljava/lang/String;CC)Ljava/lang/String;
    //   47: iconst_0
    //   48: anewarray 105	java/lang/Class
    //   51: invokevirtual 109	java/lang/Class:getMethod	(Ljava/lang/String;[Ljava/lang/Class;)Ljava/lang/reflect/Method;
    //   54: astore 6
    //   56: aload 6
    //   58: aconst_null
    //   59: iconst_0
    //   60: anewarray 111	java/lang/Object
    //   63: invokevirtual 117	java/lang/reflect/Method:invoke	(Ljava/lang/Object;[Ljava/lang/Object;)Ljava/lang/Object;
    //   66: astore 6
    //   68: aload 6
    //   70: checkcast 119	java/lang/Integer
    //   73: invokevirtual 122	java/lang/Integer:intValue	()I
    //   76: putstatic 95	uuuuuu/mmmmmq:bvvv0076vvv0076v	I
    //   79: aload_0
    //   80: getfield 43	uuuuuu/mmmmmq:b00760076vvvvv0076v	Ljava/util/List;
    //   83: invokeinterface 208 1 0
    //   88: aload_0
    //   89: getfield 43	uuuuuu/mmmmmq:b00760076vvvvv0076v	Ljava/util/List;
    //   92: aload_1
    //   93: invokeinterface 212 2 0
    //   98: pop
    //   99: aload_0
    //   100: getfield 158	uuuuuu/mmmmmq:bnnnnn006E006E006En	Luuuuuu/ttssst$tsssst;
    //   103: checkcast 160	uuuuuu/qqmmmq$qmmmmq
    //   106: invokeinterface 215 1 0
    //   111: ifeq +298 -> 409
    //   114: getstatic 89	uuuuuu/mmmmmq:b007600760076vvvv0076v	I
    //   117: istore_2
    //   118: getstatic 91	uuuuuu/mmmmmq:b0076vv0076vvv0076v	I
    //   121: istore_3
    //   122: getstatic 89	uuuuuu/mmmmmq:b007600760076vvvv0076v	I
    //   125: istore 4
    //   127: getstatic 93	uuuuuu/mmmmmq:bv0076v0076vvv0076v	I
    //   130: istore 5
    //   132: getstatic 89	uuuuuu/mmmmmq:b007600760076vvvv0076v	I
    //   135: getstatic 91	uuuuuu/mmmmmq:b0076vv0076vvv0076v	I
    //   138: iadd
    //   139: getstatic 89	uuuuuu/mmmmmq:b007600760076vvvv0076v	I
    //   142: imul
    //   143: getstatic 93	uuuuuu/mmmmmq:bv0076v0076vvv0076v	I
    //   146: irem
    //   147: getstatic 95	uuuuuu/mmmmmq:bvvv0076vvv0076v	I
    //   150: if_icmpeq +47 -> 197
    //   153: bipush 20
    //   155: putstatic 89	uuuuuu/mmmmmq:b007600760076vvvv0076v	I
    //   158: ldc 2
    //   160: ldc -39
    //   162: sipush 211
    //   165: iconst_4
    //   166: invokestatic 103	xxxxxx/uxxxxx:bb00620062bb0062b0062b0062	(Ljava/lang/String;CC)Ljava/lang/String;
    //   169: iconst_0
    //   170: anewarray 105	java/lang/Class
    //   173: invokevirtual 109	java/lang/Class:getMethod	(Ljava/lang/String;[Ljava/lang/Class;)Ljava/lang/reflect/Method;
    //   176: astore_1
    //   177: aload_1
    //   178: aconst_null
    //   179: iconst_0
    //   180: anewarray 111	java/lang/Object
    //   183: invokevirtual 117	java/lang/reflect/Method:invoke	(Ljava/lang/Object;[Ljava/lang/Object;)Ljava/lang/Object;
    //   186: astore_1
    //   187: aload_1
    //   188: checkcast 119	java/lang/Integer
    //   191: invokevirtual 122	java/lang/Integer:intValue	()I
    //   194: putstatic 95	uuuuuu/mmmmmq:bvvv0076vvv0076v	I
    //   197: iload 4
    //   199: iload_2
    //   200: iload_3
    //   201: iadd
    //   202: imul
    //   203: iload 5
    //   205: irem
    //   206: getstatic 95	uuuuuu/mmmmmq:bvvv0076vvv0076v	I
    //   209: if_icmpeq +144 -> 353
    //   212: bipush 20
    //   214: putstatic 89	uuuuuu/mmmmmq:b007600760076vvvv0076v	I
    //   217: getstatic 89	uuuuuu/mmmmmq:b007600760076vvvv0076v	I
    //   220: getstatic 91	uuuuuu/mmmmmq:b0076vv0076vvv0076v	I
    //   223: iadd
    //   224: getstatic 89	uuuuuu/mmmmmq:b007600760076vvvv0076v	I
    //   227: imul
    //   228: getstatic 93	uuuuuu/mmmmmq:bv0076v0076vvv0076v	I
    //   231: irem
    //   232: getstatic 95	uuuuuu/mmmmmq:bvvv0076vvv0076v	I
    //   235: if_icmpeq +79 -> 314
    //   238: ldc 2
    //   240: ldc -37
    //   242: bipush 117
    //   244: iconst_1
    //   245: invokestatic 103	xxxxxx/uxxxxx:bb00620062bb0062b0062b0062	(Ljava/lang/String;CC)Ljava/lang/String;
    //   248: iconst_0
    //   249: anewarray 105	java/lang/Class
    //   252: invokevirtual 109	java/lang/Class:getMethod	(Ljava/lang/String;[Ljava/lang/Class;)Ljava/lang/reflect/Method;
    //   255: astore_1
    //   256: aload_1
    //   257: aconst_null
    //   258: iconst_0
    //   259: anewarray 111	java/lang/Object
    //   262: invokevirtual 117	java/lang/reflect/Method:invoke	(Ljava/lang/Object;[Ljava/lang/Object;)Ljava/lang/Object;
    //   265: astore_1
    //   266: aload_1
    //   267: checkcast 119	java/lang/Integer
    //   270: invokevirtual 122	java/lang/Integer:intValue	()I
    //   273: putstatic 89	uuuuuu/mmmmmq:b007600760076vvvv0076v	I
    //   276: ldc 2
    //   278: ldc -35
    //   280: bipush 50
    //   282: iconst_1
    //   283: invokestatic 103	xxxxxx/uxxxxx:bb00620062bb0062b0062b0062	(Ljava/lang/String;CC)Ljava/lang/String;
    //   286: iconst_0
    //   287: anewarray 105	java/lang/Class
    //   290: invokevirtual 109	java/lang/Class:getMethod	(Ljava/lang/String;[Ljava/lang/Class;)Ljava/lang/reflect/Method;
    //   293: astore_1
    //   294: aload_1
    //   295: aconst_null
    //   296: iconst_0
    //   297: anewarray 111	java/lang/Object
    //   300: invokevirtual 117	java/lang/reflect/Method:invoke	(Ljava/lang/Object;[Ljava/lang/Object;)Ljava/lang/Object;
    //   303: astore_1
    //   304: aload_1
    //   305: checkcast 119	java/lang/Integer
    //   308: invokevirtual 122	java/lang/Integer:intValue	()I
    //   311: putstatic 95	uuuuuu/mmmmmq:bvvv0076vvv0076v	I
    //   314: ldc 2
    //   316: ldc -33
    //   318: sipush 187
    //   321: iconst_4
    //   322: invokestatic 103	xxxxxx/uxxxxx:bb00620062bb0062b0062b0062	(Ljava/lang/String;CC)Ljava/lang/String;
    //   325: iconst_0
    //   326: anewarray 105	java/lang/Class
    //   329: invokevirtual 109	java/lang/Class:getMethod	(Ljava/lang/String;[Ljava/lang/Class;)Ljava/lang/reflect/Method;
    //   332: astore_1
    //   333: aload_1
    //   334: aconst_null
    //   335: iconst_0
    //   336: anewarray 111	java/lang/Object
    //   339: invokevirtual 117	java/lang/reflect/Method:invoke	(Ljava/lang/Object;[Ljava/lang/Object;)Ljava/lang/Object;
    //   342: astore_1
    //   343: aload_1
    //   344: checkcast 119	java/lang/Integer
    //   347: invokevirtual 122	java/lang/Integer:intValue	()I
    //   350: putstatic 95	uuuuuu/mmmmmq:bvvv0076vvv0076v	I
    //   353: aload_0
    //   354: getfield 43	uuuuuu/mmmmmq:b00760076vvvvv0076v	Ljava/util/List;
    //   357: astore_1
    //   358: ldc 2
    //   360: ldc -31
    //   362: bipush 66
    //   364: iconst_3
    //   365: invokestatic 103	xxxxxx/uxxxxx:bb00620062bb0062b0062b0062	(Ljava/lang/String;CC)Ljava/lang/String;
    //   368: iconst_1
    //   369: anewarray 105	java/lang/Class
    //   372: dup
    //   373: iconst_0
    //   374: ldc 124
    //   376: aastore
    //   377: invokevirtual 133	java/lang/Class:getDeclaredMethod	(Ljava/lang/String;[Ljava/lang/Class;)Ljava/lang/reflect/Method;
    //   380: astore 6
    //   382: aload 6
    //   384: aload_0
    //   385: iconst_1
    //   386: anewarray 111	java/lang/Object
    //   389: dup
    //   390: iconst_0
    //   391: aload_1
    //   392: aastore
    //   393: invokevirtual 117	java/lang/reflect/Method:invoke	(Ljava/lang/Object;[Ljava/lang/Object;)Ljava/lang/Object;
    //   396: pop
    //   397: aload_0
    //   398: getfield 158	uuuuuu/mmmmmq:bnnnnn006E006E006En	Luuuuuu/ttssst$tsssst;
    //   401: checkcast 160	uuuuuu/qqmmmq$qmmmmq
    //   404: invokeinterface 228 1 0
    //   409: return
    //   410: astore_1
    //   411: aload_1
    //   412: invokevirtual 184	java/lang/reflect/InvocationTargetException:getCause	()Ljava/lang/Throwable;
    //   415: athrow
    //   416: astore_1
    //   417: aload_1
    //   418: invokevirtual 184	java/lang/reflect/InvocationTargetException:getCause	()Ljava/lang/Throwable;
    //   421: athrow
    //   422: astore_1
    //   423: aload_1
    //   424: invokevirtual 184	java/lang/reflect/InvocationTargetException:getCause	()Ljava/lang/Throwable;
    //   427: athrow
    //   428: astore_1
    //   429: aload_1
    //   430: invokevirtual 184	java/lang/reflect/InvocationTargetException:getCause	()Ljava/lang/Throwable;
    //   433: athrow
    //   434: astore_1
    //   435: aload_1
    //   436: invokevirtual 184	java/lang/reflect/InvocationTargetException:getCause	()Ljava/lang/Throwable;
    //   439: athrow
    //   440: astore_1
    //   441: aload_1
    //   442: invokevirtual 184	java/lang/reflect/InvocationTargetException:getCause	()Ljava/lang/Throwable;
    //   445: athrow
    // Local variable table:
    //   start	length	slot	name	signature
    //   0	446	0	this	mmmmmq
    //   0	446	1	paramList	List<ExternalFinancialInstitute>
    //   3	199	2	i	int
    //   121	81	3	j	int
    //   125	78	4	k	int
    //   130	76	5	m	int
    //   54	329	6	localObject	Object
    // Exception table:
    //   from	to	target	type
    //   333	343	410	java/lang/reflect/InvocationTargetException
    //   382	397	416	java/lang/reflect/InvocationTargetException
    //   56	68	422	java/lang/reflect/InvocationTargetException
    //   177	187	428	java/lang/reflect/InvocationTargetException
    //   256	266	434	java/lang/reflect/InvocationTargetException
    //   294	304	440	java/lang/reflect/InvocationTargetException
  }
  
  public static int b0075uuu00750075uuu0075()
  {
    return 0;
  }
  
  public static int bu0075uu00750075uuu0075()
  {
    return 2;
  }
  
  public static int buuuu00750075uuu0075()
  {
    return 1;
  }
  
  /* Error */
  public void b007500750075u00750075uuu0075(com.db.pwcc.dbmobile.model.error.DbError paramDbError)
  {
    // Byte code:
    //   0: getstatic 89	uuuuuu/mmmmmq:b007600760076vvvv0076v	I
    //   3: istore_2
    //   4: ldc 2
    //   6: ldc -21
    //   8: sipush 166
    //   11: sipush 148
    //   14: iconst_0
    //   15: invokestatic 170	xxxxxx/uxxxxx:bbbb0062b0062b0062b0062	(Ljava/lang/String;CCC)Ljava/lang/String;
    //   18: iconst_0
    //   19: anewarray 105	java/lang/Class
    //   22: invokevirtual 109	java/lang/Class:getMethod	(Ljava/lang/String;[Ljava/lang/Class;)Ljava/lang/reflect/Method;
    //   25: astore 5
    //   27: aload 5
    //   29: aconst_null
    //   30: iconst_0
    //   31: anewarray 111	java/lang/Object
    //   34: invokevirtual 117	java/lang/reflect/Method:invoke	(Ljava/lang/Object;[Ljava/lang/Object;)Ljava/lang/Object;
    //   37: astore 5
    //   39: aload 5
    //   41: checkcast 119	java/lang/Integer
    //   44: invokevirtual 122	java/lang/Integer:intValue	()I
    //   47: istore_3
    //   48: getstatic 91	uuuuuu/mmmmmq:b0076vv0076vvv0076v	I
    //   51: istore 4
    //   53: ldc 2
    //   55: ldc -19
    //   57: bipush 71
    //   59: sipush 246
    //   62: iconst_1
    //   63: invokestatic 170	xxxxxx/uxxxxx:bbbb0062b0062b0062b0062	(Ljava/lang/String;CCC)Ljava/lang/String;
    //   66: iconst_0
    //   67: anewarray 105	java/lang/Class
    //   70: invokevirtual 109	java/lang/Class:getMethod	(Ljava/lang/String;[Ljava/lang/Class;)Ljava/lang/reflect/Method;
    //   73: astore 5
    //   75: aload 5
    //   77: aconst_null
    //   78: iconst_0
    //   79: anewarray 111	java/lang/Object
    //   82: invokevirtual 117	java/lang/reflect/Method:invoke	(Ljava/lang/Object;[Ljava/lang/Object;)Ljava/lang/Object;
    //   85: astore 5
    //   87: aload 5
    //   89: checkcast 119	java/lang/Integer
    //   92: invokevirtual 122	java/lang/Integer:intValue	()I
    //   95: iload 4
    //   97: iload_3
    //   98: iadd
    //   99: imul
    //   100: getstatic 93	uuuuuu/mmmmmq:bv0076v0076vvv0076v	I
    //   103: irem
    //   104: getstatic 95	uuuuuu/mmmmmq:bvvv0076vvv0076v	I
    //   107: if_icmpeq +13 -> 120
    //   110: bipush 51
    //   112: putstatic 89	uuuuuu/mmmmmq:b007600760076vvvv0076v	I
    //   115: bipush 52
    //   117: putstatic 95	uuuuuu/mmmmmq:bvvv0076vvv0076v	I
    //   120: getstatic 91	uuuuuu/mmmmmq:b0076vv0076vvv0076v	I
    //   123: istore_3
    //   124: getstatic 89	uuuuuu/mmmmmq:b007600760076vvvv0076v	I
    //   127: getstatic 91	uuuuuu/mmmmmq:b0076vv0076vvv0076v	I
    //   130: iadd
    //   131: getstatic 89	uuuuuu/mmmmmq:b007600760076vvvv0076v	I
    //   134: imul
    //   135: getstatic 93	uuuuuu/mmmmmq:bv0076v0076vvv0076v	I
    //   138: irem
    //   139: getstatic 95	uuuuuu/mmmmmq:bvvv0076vvv0076v	I
    //   142: if_icmpeq +173 -> 315
    //   145: bipush 8
    //   147: putstatic 89	uuuuuu/mmmmmq:b007600760076vvvv0076v	I
    //   150: ldc 2
    //   152: ldc -17
    //   154: sipush 243
    //   157: iconst_2
    //   158: invokestatic 103	xxxxxx/uxxxxx:bb00620062bb0062b0062b0062	(Ljava/lang/String;CC)Ljava/lang/String;
    //   161: iconst_0
    //   162: anewarray 105	java/lang/Class
    //   165: invokevirtual 109	java/lang/Class:getMethod	(Ljava/lang/String;[Ljava/lang/Class;)Ljava/lang/reflect/Method;
    //   168: astore 5
    //   170: aload 5
    //   172: aconst_null
    //   173: iconst_0
    //   174: anewarray 111	java/lang/Object
    //   177: invokevirtual 117	java/lang/reflect/Method:invoke	(Ljava/lang/Object;[Ljava/lang/Object;)Ljava/lang/Object;
    //   180: astore 5
    //   182: aload 5
    //   184: checkcast 119	java/lang/Integer
    //   187: invokevirtual 122	java/lang/Integer:intValue	()I
    //   190: putstatic 95	uuuuuu/mmmmmq:bvvv0076vvv0076v	I
    //   193: getstatic 89	uuuuuu/mmmmmq:b007600760076vvvv0076v	I
    //   196: istore 4
    //   198: iload 4
    //   200: getstatic 91	uuuuuu/mmmmmq:b0076vv0076vvv0076v	I
    //   203: iload 4
    //   205: iadd
    //   206: imul
    //   207: getstatic 93	uuuuuu/mmmmmq:bv0076v0076vvv0076v	I
    //   210: irem
    //   211: tableswitch	default:+17->228, 0:+104->315
    //   228: ldc 2
    //   230: ldc -15
    //   232: sipush 157
    //   235: bipush 117
    //   237: iconst_3
    //   238: invokestatic 170	xxxxxx/uxxxxx:bbbb0062b0062b0062b0062	(Ljava/lang/String;CCC)Ljava/lang/String;
    //   241: iconst_0
    //   242: anewarray 105	java/lang/Class
    //   245: invokevirtual 109	java/lang/Class:getMethod	(Ljava/lang/String;[Ljava/lang/Class;)Ljava/lang/reflect/Method;
    //   248: astore 5
    //   250: aload 5
    //   252: aconst_null
    //   253: iconst_0
    //   254: anewarray 111	java/lang/Object
    //   257: invokevirtual 117	java/lang/reflect/Method:invoke	(Ljava/lang/Object;[Ljava/lang/Object;)Ljava/lang/Object;
    //   260: astore 5
    //   262: aload 5
    //   264: checkcast 119	java/lang/Integer
    //   267: invokevirtual 122	java/lang/Integer:intValue	()I
    //   270: putstatic 89	uuuuuu/mmmmmq:b007600760076vvvv0076v	I
    //   273: ldc 2
    //   275: ldc -13
    //   277: bipush 47
    //   279: iconst_0
    //   280: invokestatic 103	xxxxxx/uxxxxx:bb00620062bb0062b0062b0062	(Ljava/lang/String;CC)Ljava/lang/String;
    //   283: iconst_0
    //   284: anewarray 105	java/lang/Class
    //   287: invokevirtual 109	java/lang/Class:getMethod	(Ljava/lang/String;[Ljava/lang/Class;)Ljava/lang/reflect/Method;
    //   290: astore 5
    //   292: aload 5
    //   294: aconst_null
    //   295: iconst_0
    //   296: anewarray 111	java/lang/Object
    //   299: invokevirtual 117	java/lang/reflect/Method:invoke	(Ljava/lang/Object;[Ljava/lang/Object;)Ljava/lang/Object;
    //   302: astore 5
    //   304: aload 5
    //   306: checkcast 119	java/lang/Integer
    //   309: invokevirtual 122	java/lang/Integer:intValue	()I
    //   312: putstatic 95	uuuuuu/mmmmmq:bvvv0076vvv0076v	I
    //   315: ldc 2
    //   317: ldc -11
    //   319: sipush 162
    //   322: sipush 203
    //   325: iconst_3
    //   326: invokestatic 170	xxxxxx/uxxxxx:bbbb0062b0062b0062b0062	(Ljava/lang/String;CCC)Ljava/lang/String;
    //   329: iconst_0
    //   330: anewarray 105	java/lang/Class
    //   333: invokevirtual 109	java/lang/Class:getMethod	(Ljava/lang/String;[Ljava/lang/Class;)Ljava/lang/reflect/Method;
    //   336: astore 5
    //   338: aload 5
    //   340: aconst_null
    //   341: iconst_0
    //   342: anewarray 111	java/lang/Object
    //   345: invokevirtual 117	java/lang/reflect/Method:invoke	(Ljava/lang/Object;[Ljava/lang/Object;)Ljava/lang/Object;
    //   348: astore 5
    //   350: iload_2
    //   351: iload_2
    //   352: iload_3
    //   353: iadd
    //   354: imul
    //   355: aload 5
    //   357: checkcast 119	java/lang/Integer
    //   360: invokevirtual 122	java/lang/Integer:intValue	()I
    //   363: irem
    //   364: tableswitch	default:+20->384, 0:+30->394
    //   384: bipush 95
    //   386: putstatic 89	uuuuuu/mmmmmq:b007600760076vvvv0076v	I
    //   389: bipush 23
    //   391: putstatic 95	uuuuuu/mmmmmq:bvvv0076vvv0076v	I
    //   394: ldc 2
    //   396: ldc -9
    //   398: sipush 254
    //   401: iconst_0
    //   402: invokestatic 103	xxxxxx/uxxxxx:bb00620062bb0062b0062b0062	(Ljava/lang/String;CC)Ljava/lang/String;
    //   405: iconst_1
    //   406: anewarray 105	java/lang/Class
    //   409: dup
    //   410: iconst_0
    //   411: ldc -7
    //   413: aastore
    //   414: invokevirtual 109	java/lang/Class:getMethod	(Ljava/lang/String;[Ljava/lang/Class;)Ljava/lang/reflect/Method;
    //   417: astore 5
    //   419: aload 5
    //   421: aload_0
    //   422: iconst_1
    //   423: anewarray 111	java/lang/Object
    //   426: dup
    //   427: iconst_0
    //   428: aload_1
    //   429: aastore
    //   430: invokevirtual 117	java/lang/reflect/Method:invoke	(Ljava/lang/Object;[Ljava/lang/Object;)Ljava/lang/Object;
    //   433: pop
    //   434: return
    //   435: astore_1
    //   436: aload_1
    //   437: invokevirtual 184	java/lang/reflect/InvocationTargetException:getCause	()Ljava/lang/Throwable;
    //   440: athrow
    //   441: astore_1
    //   442: aload_1
    //   443: invokevirtual 184	java/lang/reflect/InvocationTargetException:getCause	()Ljava/lang/Throwable;
    //   446: athrow
    //   447: astore_1
    //   448: aload_1
    //   449: invokevirtual 184	java/lang/reflect/InvocationTargetException:getCause	()Ljava/lang/Throwable;
    //   452: athrow
    //   453: astore_1
    //   454: aload_1
    //   455: invokevirtual 184	java/lang/reflect/InvocationTargetException:getCause	()Ljava/lang/Throwable;
    //   458: athrow
    //   459: astore_1
    //   460: aload_1
    //   461: invokevirtual 184	java/lang/reflect/InvocationTargetException:getCause	()Ljava/lang/Throwable;
    //   464: athrow
    //   465: astore_1
    //   466: aload_1
    //   467: invokevirtual 184	java/lang/reflect/InvocationTargetException:getCause	()Ljava/lang/Throwable;
    //   470: athrow
    //   471: astore_1
    //   472: aload_1
    //   473: invokevirtual 184	java/lang/reflect/InvocationTargetException:getCause	()Ljava/lang/Throwable;
    //   476: athrow
    // Local variable table:
    //   start	length	slot	name	signature
    //   0	477	0	this	mmmmmq
    //   0	477	1	paramDbError	com.db.pwcc.dbmobile.model.error.DbError
    //   3	352	2	i	int
    //   47	307	3	j	int
    //   51	156	4	k	int
    //   25	395	5	localObject	Object
    // Exception table:
    //   from	to	target	type
    //   170	182	435	java/lang/reflect/InvocationTargetException
    //   419	434	441	java/lang/reflect/InvocationTargetException
    //   338	350	447	java/lang/reflect/InvocationTargetException
    //   27	39	453	java/lang/reflect/InvocationTargetException
    //   75	87	459	java/lang/reflect/InvocationTargetException
    //   250	262	465	java/lang/reflect/InvocationTargetException
    //   292	304	471	java/lang/reflect/InvocationTargetException
  }
  
  /* Error */
  public void b0075u00750075u0075uuu0075(String paramString)
  {
    // Byte code:
    //   0: aload_0
    //   1: aload_1
    //   2: putfield 150	uuuuuu/mmmmmq:bv00760076vvvv0076v	Ljava/lang/String;
    //   5: aload_0
    //   6: getfield 68	uuuuuu/mmmmmq:bvv0076vvvv0076v	Z
    //   9: ifeq +337 -> 346
    //   12: aload_0
    //   13: iconst_0
    //   14: putfield 68	uuuuuu/mmmmmq:bvv0076vvvv0076v	Z
    //   17: ldc 2
    //   19: ldc -4
    //   21: sipush 238
    //   24: sipush 239
    //   27: iconst_1
    //   28: invokestatic 170	xxxxxx/uxxxxx:bbbb0062b0062b0062b0062	(Ljava/lang/String;CCC)Ljava/lang/String;
    //   31: iconst_0
    //   32: anewarray 105	java/lang/Class
    //   35: invokevirtual 109	java/lang/Class:getMethod	(Ljava/lang/String;[Ljava/lang/Class;)Ljava/lang/reflect/Method;
    //   38: astore_1
    //   39: aload_1
    //   40: aload_0
    //   41: iconst_0
    //   42: anewarray 111	java/lang/Object
    //   45: invokevirtual 117	java/lang/reflect/Method:invoke	(Ljava/lang/Object;[Ljava/lang/Object;)Ljava/lang/Object;
    //   48: pop
    //   49: ldc -2
    //   51: ldc_w 256
    //   54: sipush 152
    //   57: iconst_4
    //   58: invokestatic 103	xxxxxx/uxxxxx:bb00620062bb0062b0062b0062	(Ljava/lang/String;CC)Ljava/lang/String;
    //   61: iconst_0
    //   62: anewarray 105	java/lang/Class
    //   65: invokevirtual 109	java/lang/Class:getMethod	(Ljava/lang/String;[Ljava/lang/Class;)Ljava/lang/reflect/Method;
    //   68: astore_1
    //   69: aload_1
    //   70: aconst_null
    //   71: iconst_0
    //   72: anewarray 111	java/lang/Object
    //   75: invokevirtual 117	java/lang/reflect/Method:invoke	(Ljava/lang/Object;[Ljava/lang/Object;)Ljava/lang/Object;
    //   78: astore_1
    //   79: aload_1
    //   80: checkcast 254	com/db/pwcc/dbmobile/secure/preferences/SharedPreferencesHelper
    //   83: astore_1
    //   84: ldc -2
    //   86: ldc_w 258
    //   89: bipush 100
    //   91: iconst_1
    //   92: invokestatic 103	xxxxxx/uxxxxx:bb00620062bb0062b0062b0062	(Ljava/lang/String;CC)Ljava/lang/String;
    //   95: iconst_0
    //   96: anewarray 105	java/lang/Class
    //   99: invokevirtual 109	java/lang/Class:getMethod	(Ljava/lang/String;[Ljava/lang/Class;)Ljava/lang/reflect/Method;
    //   102: astore 5
    //   104: aload 5
    //   106: aload_1
    //   107: iconst_0
    //   108: anewarray 111	java/lang/Object
    //   111: invokevirtual 117	java/lang/reflect/Method:invoke	(Ljava/lang/Object;[Ljava/lang/Object;)Ljava/lang/Object;
    //   114: astore_1
    //   115: aload_1
    //   116: checkcast 260	java/lang/String
    //   119: astore_1
    //   120: getstatic 89	uuuuuu/mmmmmq:b007600760076vvvv0076v	I
    //   123: istore_2
    //   124: getstatic 91	uuuuuu/mmmmmq:b0076vv0076vvv0076v	I
    //   127: istore_3
    //   128: getstatic 89	uuuuuu/mmmmmq:b007600760076vvvv0076v	I
    //   131: istore 4
    //   133: ldc 2
    //   135: ldc_w 262
    //   138: bipush 50
    //   140: bipush 35
    //   142: iconst_0
    //   143: invokestatic 170	xxxxxx/uxxxxx:bbbb0062b0062b0062b0062	(Ljava/lang/String;CCC)Ljava/lang/String;
    //   146: iconst_0
    //   147: anewarray 105	java/lang/Class
    //   150: invokevirtual 109	java/lang/Class:getMethod	(Ljava/lang/String;[Ljava/lang/Class;)Ljava/lang/reflect/Method;
    //   153: astore 5
    //   155: aload 5
    //   157: aconst_null
    //   158: iconst_0
    //   159: anewarray 111	java/lang/Object
    //   162: invokevirtual 117	java/lang/reflect/Method:invoke	(Ljava/lang/Object;[Ljava/lang/Object;)Ljava/lang/Object;
    //   165: astore 5
    //   167: iload 4
    //   169: iload_2
    //   170: iload_3
    //   171: iadd
    //   172: imul
    //   173: aload 5
    //   175: checkcast 119	java/lang/Integer
    //   178: invokevirtual 122	java/lang/Integer:intValue	()I
    //   181: irem
    //   182: getstatic 95	uuuuuu/mmmmmq:bvvv0076vvv0076v	I
    //   185: if_icmpeq +91 -> 276
    //   188: ldc 2
    //   190: ldc_w 264
    //   193: sipush 144
    //   196: iconst_1
    //   197: invokestatic 103	xxxxxx/uxxxxx:bb00620062bb0062b0062b0062	(Ljava/lang/String;CC)Ljava/lang/String;
    //   200: iconst_0
    //   201: anewarray 105	java/lang/Class
    //   204: invokevirtual 109	java/lang/Class:getMethod	(Ljava/lang/String;[Ljava/lang/Class;)Ljava/lang/reflect/Method;
    //   207: astore 5
    //   209: aload 5
    //   211: aconst_null
    //   212: iconst_0
    //   213: anewarray 111	java/lang/Object
    //   216: invokevirtual 117	java/lang/reflect/Method:invoke	(Ljava/lang/Object;[Ljava/lang/Object;)Ljava/lang/Object;
    //   219: astore 5
    //   221: aload 5
    //   223: checkcast 119	java/lang/Integer
    //   226: invokevirtual 122	java/lang/Integer:intValue	()I
    //   229: putstatic 89	uuuuuu/mmmmmq:b007600760076vvvv0076v	I
    //   232: ldc 2
    //   234: ldc_w 266
    //   237: sipush 255
    //   240: iconst_4
    //   241: invokestatic 103	xxxxxx/uxxxxx:bb00620062bb0062b0062b0062	(Ljava/lang/String;CC)Ljava/lang/String;
    //   244: iconst_0
    //   245: anewarray 105	java/lang/Class
    //   248: invokevirtual 109	java/lang/Class:getMethod	(Ljava/lang/String;[Ljava/lang/Class;)Ljava/lang/reflect/Method;
    //   251: astore 5
    //   253: aload 5
    //   255: aconst_null
    //   256: iconst_0
    //   257: anewarray 111	java/lang/Object
    //   260: invokevirtual 117	java/lang/reflect/Method:invoke	(Ljava/lang/Object;[Ljava/lang/Object;)Ljava/lang/Object;
    //   263: astore 5
    //   265: aload 5
    //   267: checkcast 119	java/lang/Integer
    //   270: invokevirtual 122	java/lang/Integer:intValue	()I
    //   273: putstatic 95	uuuuuu/mmmmmq:bvvv0076vvv0076v	I
    //   276: new 268	uuuuuu/aaaala
    //   279: dup
    //   280: invokespecial 269	uuuuuu/aaaala:<init>	()V
    //   283: astore 5
    //   285: aload_0
    //   286: getfield 273	uuuuuu/mmmmmq:b006E006E006E006E006En006E006En	Luuuuuu/hyhyhh;
    //   289: astore 6
    //   291: getstatic 89	uuuuuu/mmmmmq:b007600760076vvvv0076v	I
    //   294: istore_2
    //   295: iload_2
    //   296: getstatic 91	uuuuuu/mmmmmq:b0076vv0076vvv0076v	I
    //   299: iload_2
    //   300: iadd
    //   301: imul
    //   302: getstatic 93	uuuuuu/mmmmmq:bv0076v0076vvv0076v	I
    //   305: irem
    //   306: tableswitch	default:+18->324, 0:+27->333
    //   324: iconst_4
    //   325: putstatic 89	uuuuuu/mmmmmq:b007600760076vvvv0076v	I
    //   328: bipush 54
    //   330: putstatic 95	uuuuuu/mmmmmq:bvvv0076vvv0076v	I
    //   333: aload 5
    //   335: aload_0
    //   336: aload 6
    //   338: invokevirtual 278	uuuuuu/hyhyhh:b0070pp007000700070p007000700070	()Ljava/lang/String;
    //   341: aload_1
    //   342: invokevirtual 282	uuuuuu/aaaala:bu0075uuu00750075007500750075	(Luuuuuu/vxvvvv$xvvvvv;Ljava/lang/String;Ljava/lang/String;)V
    //   345: return
    //   346: aload_0
    //   347: getfield 45	uuuuuu/mmmmmq:bv0076vvvvv0076v	Z
    //   350: ifne +32 -> 382
    //   353: aload_0
    //   354: getfield 43	uuuuuu/mmmmmq:b00760076vvvvv0076v	Ljava/util/List;
    //   357: invokeinterface 208 1 0
    //   362: aload_0
    //   363: getfield 43	uuuuuu/mmmmmq:b00760076vvvvv0076v	Ljava/util/List;
    //   366: aload_0
    //   367: getfield 61	uuuuuu/mmmmmq:b0076vvvvvv0076v	Landroid/content/Context;
    //   370: invokestatic 288	uuuuuu/xxvvvx:bu0075uuuu0075u00750075	(Landroid/content/Context;)Luuuuuu/xxvvvx;
    //   373: invokevirtual 292	uuuuuu/xxvvvx:b00750075uuuu0075u00750075	()Ljava/util/List;
    //   376: invokeinterface 212 2 0
    //   381: pop
    //   382: aload_0
    //   383: getfield 43	uuuuuu/mmmmmq:b00760076vvvvv0076v	Ljava/util/List;
    //   386: invokeinterface 128 1 0
    //   391: ifeq +362 -> 753
    //   394: aload_0
    //   395: getfield 158	uuuuuu/mmmmmq:bnnnnn006E006E006En	Luuuuuu/ttssst$tsssst;
    //   398: checkcast 160	uuuuuu/qqmmmq$qmmmmq
    //   401: invokeinterface 295 1 0
    //   406: ldc -2
    //   408: ldc_w 297
    //   411: sipush 209
    //   414: iconst_4
    //   415: invokestatic 103	xxxxxx/uxxxxx:bb00620062bb0062b0062b0062	(Ljava/lang/String;CC)Ljava/lang/String;
    //   418: iconst_0
    //   419: anewarray 105	java/lang/Class
    //   422: invokevirtual 109	java/lang/Class:getMethod	(Ljava/lang/String;[Ljava/lang/Class;)Ljava/lang/reflect/Method;
    //   425: astore_1
    //   426: aload_1
    //   427: aconst_null
    //   428: iconst_0
    //   429: anewarray 111	java/lang/Object
    //   432: invokevirtual 117	java/lang/reflect/Method:invoke	(Ljava/lang/Object;[Ljava/lang/Object;)Ljava/lang/Object;
    //   435: astore_1
    //   436: aload_1
    //   437: checkcast 254	com/db/pwcc/dbmobile/secure/preferences/SharedPreferencesHelper
    //   440: astore_1
    //   441: ldc -2
    //   443: ldc_w 299
    //   446: sipush 131
    //   449: bipush 101
    //   451: iconst_0
    //   452: invokestatic 170	xxxxxx/uxxxxx:bbbb0062b0062b0062b0062	(Ljava/lang/String;CCC)Ljava/lang/String;
    //   455: iconst_0
    //   456: anewarray 105	java/lang/Class
    //   459: invokevirtual 109	java/lang/Class:getMethod	(Ljava/lang/String;[Ljava/lang/Class;)Ljava/lang/reflect/Method;
    //   462: astore 5
    //   464: aload 5
    //   466: aload_1
    //   467: iconst_0
    //   468: anewarray 111	java/lang/Object
    //   471: invokevirtual 117	java/lang/reflect/Method:invoke	(Ljava/lang/Object;[Ljava/lang/Object;)Ljava/lang/Object;
    //   474: astore_1
    //   475: aload_1
    //   476: checkcast 260	java/lang/String
    //   479: astore_1
    //   480: new 268	uuuuuu/aaaala
    //   483: dup
    //   484: invokespecial 269	uuuuuu/aaaala:<init>	()V
    //   487: astore 5
    //   489: getstatic 89	uuuuuu/mmmmmq:b007600760076vvvv0076v	I
    //   492: istore_2
    //   493: ldc 2
    //   495: ldc_w 301
    //   498: sipush 238
    //   501: iconst_5
    //   502: invokestatic 103	xxxxxx/uxxxxx:bb00620062bb0062b0062b0062	(Ljava/lang/String;CC)Ljava/lang/String;
    //   505: iconst_0
    //   506: anewarray 105	java/lang/Class
    //   509: invokevirtual 109	java/lang/Class:getMethod	(Ljava/lang/String;[Ljava/lang/Class;)Ljava/lang/reflect/Method;
    //   512: astore 6
    //   514: aload 6
    //   516: aconst_null
    //   517: iconst_0
    //   518: anewarray 111	java/lang/Object
    //   521: invokevirtual 117	java/lang/reflect/Method:invoke	(Ljava/lang/Object;[Ljava/lang/Object;)Ljava/lang/Object;
    //   524: astore 6
    //   526: aload 6
    //   528: checkcast 119	java/lang/Integer
    //   531: invokevirtual 122	java/lang/Integer:intValue	()I
    //   534: iload_2
    //   535: iadd
    //   536: getstatic 89	uuuuuu/mmmmmq:b007600760076vvvv0076v	I
    //   539: imul
    //   540: getstatic 93	uuuuuu/mmmmmq:bv0076v0076vvv0076v	I
    //   543: irem
    //   544: getstatic 95	uuuuuu/mmmmmq:bvvv0076vvv0076v	I
    //   547: if_icmpeq +173 -> 720
    //   550: getstatic 89	uuuuuu/mmmmmq:b007600760076vvvv0076v	I
    //   553: istore_2
    //   554: getstatic 91	uuuuuu/mmmmmq:b0076vv0076vvv0076v	I
    //   557: istore_3
    //   558: ldc 2
    //   560: ldc_w 303
    //   563: sipush 162
    //   566: iconst_4
    //   567: invokestatic 103	xxxxxx/uxxxxx:bb00620062bb0062b0062b0062	(Ljava/lang/String;CC)Ljava/lang/String;
    //   570: iconst_0
    //   571: anewarray 105	java/lang/Class
    //   574: invokevirtual 109	java/lang/Class:getMethod	(Ljava/lang/String;[Ljava/lang/Class;)Ljava/lang/reflect/Method;
    //   577: astore 6
    //   579: aload 6
    //   581: aconst_null
    //   582: iconst_0
    //   583: anewarray 111	java/lang/Object
    //   586: invokevirtual 117	java/lang/reflect/Method:invoke	(Ljava/lang/Object;[Ljava/lang/Object;)Ljava/lang/Object;
    //   589: astore 6
    //   591: iload_3
    //   592: iload_2
    //   593: iadd
    //   594: iload_2
    //   595: imul
    //   596: aload 6
    //   598: checkcast 119	java/lang/Integer
    //   601: invokevirtual 122	java/lang/Integer:intValue	()I
    //   604: irem
    //   605: tableswitch	default:+19->624, 0:+68->673
    //   624: bipush 94
    //   626: putstatic 89	uuuuuu/mmmmmq:b007600760076vvvv0076v	I
    //   629: ldc 2
    //   631: ldc_w 305
    //   634: sipush 198
    //   637: iconst_1
    //   638: invokestatic 103	xxxxxx/uxxxxx:bb00620062bb0062b0062b0062	(Ljava/lang/String;CC)Ljava/lang/String;
    //   641: iconst_0
    //   642: anewarray 105	java/lang/Class
    //   645: invokevirtual 109	java/lang/Class:getMethod	(Ljava/lang/String;[Ljava/lang/Class;)Ljava/lang/reflect/Method;
    //   648: astore 6
    //   650: aload 6
    //   652: aconst_null
    //   653: iconst_0
    //   654: anewarray 111	java/lang/Object
    //   657: invokevirtual 117	java/lang/reflect/Method:invoke	(Ljava/lang/Object;[Ljava/lang/Object;)Ljava/lang/Object;
    //   660: astore 6
    //   662: aload 6
    //   664: checkcast 119	java/lang/Integer
    //   667: invokevirtual 122	java/lang/Integer:intValue	()I
    //   670: putstatic 95	uuuuuu/mmmmmq:bvvv0076vvv0076v	I
    //   673: ldc 2
    //   675: ldc_w 307
    //   678: iconst_4
    //   679: iconst_2
    //   680: invokestatic 103	xxxxxx/uxxxxx:bb00620062bb0062b0062b0062	(Ljava/lang/String;CC)Ljava/lang/String;
    //   683: iconst_0
    //   684: anewarray 105	java/lang/Class
    //   687: invokevirtual 109	java/lang/Class:getMethod	(Ljava/lang/String;[Ljava/lang/Class;)Ljava/lang/reflect/Method;
    //   690: astore 6
    //   692: aload 6
    //   694: aconst_null
    //   695: iconst_0
    //   696: anewarray 111	java/lang/Object
    //   699: invokevirtual 117	java/lang/reflect/Method:invoke	(Ljava/lang/Object;[Ljava/lang/Object;)Ljava/lang/Object;
    //   702: astore 6
    //   704: aload 6
    //   706: checkcast 119	java/lang/Integer
    //   709: invokevirtual 122	java/lang/Integer:intValue	()I
    //   712: putstatic 89	uuuuuu/mmmmmq:b007600760076vvvv0076v	I
    //   715: bipush 98
    //   717: putstatic 95	uuuuuu/mmmmmq:bvvv0076vvv0076v	I
    //   720: aload 5
    //   722: aload_0
    //   723: aload_0
    //   724: getfield 273	uuuuuu/mmmmmq:b006E006E006E006E006En006E006En	Luuuuuu/hyhyhh;
    //   727: invokevirtual 278	uuuuuu/hyhyhh:b0070pp007000700070p007000700070	()Ljava/lang/String;
    //   730: aload_1
    //   731: invokevirtual 282	uuuuuu/aaaala:bu0075uuu00750075007500750075	(Luuuuuu/vxvvvv$xvvvvv;Ljava/lang/String;Ljava/lang/String;)V
    //   734: return
    //   735: astore_1
    //   736: aload_1
    //   737: invokevirtual 184	java/lang/reflect/InvocationTargetException:getCause	()Ljava/lang/Throwable;
    //   740: athrow
    //   741: astore_1
    //   742: aload_1
    //   743: invokevirtual 184	java/lang/reflect/InvocationTargetException:getCause	()Ljava/lang/Throwable;
    //   746: athrow
    //   747: astore_1
    //   748: aload_1
    //   749: invokevirtual 184	java/lang/reflect/InvocationTargetException:getCause	()Ljava/lang/Throwable;
    //   752: athrow
    //   753: aload_0
    //   754: getfield 43	uuuuuu/mmmmmq:b00760076vvvvv0076v	Ljava/util/List;
    //   757: astore_1
    //   758: ldc 2
    //   760: ldc_w 309
    //   763: bipush 67
    //   765: sipush 225
    //   768: iconst_1
    //   769: invokestatic 170	xxxxxx/uxxxxx:bbbb0062b0062b0062b0062	(Ljava/lang/String;CCC)Ljava/lang/String;
    //   772: iconst_1
    //   773: anewarray 105	java/lang/Class
    //   776: dup
    //   777: iconst_0
    //   778: ldc 124
    //   780: aastore
    //   781: invokevirtual 133	java/lang/Class:getDeclaredMethod	(Ljava/lang/String;[Ljava/lang/Class;)Ljava/lang/reflect/Method;
    //   784: astore 5
    //   786: aload 5
    //   788: aload_0
    //   789: iconst_1
    //   790: anewarray 111	java/lang/Object
    //   793: dup
    //   794: iconst_0
    //   795: aload_1
    //   796: aastore
    //   797: invokevirtual 117	java/lang/reflect/Method:invoke	(Ljava/lang/Object;[Ljava/lang/Object;)Ljava/lang/Object;
    //   800: pop
    //   801: return
    //   802: astore_1
    //   803: aload_1
    //   804: invokevirtual 184	java/lang/reflect/InvocationTargetException:getCause	()Ljava/lang/Throwable;
    //   807: athrow
    //   808: astore_1
    //   809: aload_1
    //   810: invokevirtual 184	java/lang/reflect/InvocationTargetException:getCause	()Ljava/lang/Throwable;
    //   813: athrow
    //   814: astore_1
    //   815: aload_1
    //   816: invokevirtual 184	java/lang/reflect/InvocationTargetException:getCause	()Ljava/lang/Throwable;
    //   819: athrow
    //   820: astore_1
    //   821: aload_1
    //   822: invokevirtual 184	java/lang/reflect/InvocationTargetException:getCause	()Ljava/lang/Throwable;
    //   825: athrow
    //   826: astore_1
    //   827: aload_1
    //   828: invokevirtual 184	java/lang/reflect/InvocationTargetException:getCause	()Ljava/lang/Throwable;
    //   831: athrow
    //   832: astore_1
    //   833: aload_1
    //   834: invokevirtual 184	java/lang/reflect/InvocationTargetException:getCause	()Ljava/lang/Throwable;
    //   837: athrow
    //   838: astore_1
    //   839: aload_1
    //   840: invokevirtual 184	java/lang/reflect/InvocationTargetException:getCause	()Ljava/lang/Throwable;
    //   843: athrow
    //   844: astore_1
    //   845: aload_1
    //   846: invokevirtual 184	java/lang/reflect/InvocationTargetException:getCause	()Ljava/lang/Throwable;
    //   849: athrow
    //   850: astore_1
    //   851: aload_1
    //   852: invokevirtual 184	java/lang/reflect/InvocationTargetException:getCause	()Ljava/lang/Throwable;
    //   855: athrow
    //   856: astore_1
    //   857: aload_1
    //   858: invokevirtual 184	java/lang/reflect/InvocationTargetException:getCause	()Ljava/lang/Throwable;
    //   861: athrow
    // Local variable table:
    //   start	length	slot	name	signature
    //   0	862	0	this	mmmmmq
    //   0	862	1	paramString	String
    //   123	473	2	i	int
    //   127	467	3	j	int
    //   131	42	4	k	int
    //   102	685	5	localObject1	Object
    //   289	416	6	localObject2	Object
    // Exception table:
    //   from	to	target	type
    //   104	115	735	java/lang/reflect/InvocationTargetException
    //   514	526	741	java/lang/reflect/InvocationTargetException
    //   579	591	747	java/lang/reflect/InvocationTargetException
    //   786	801	802	java/lang/reflect/InvocationTargetException
    //   209	221	808	java/lang/reflect/InvocationTargetException
    //   253	265	814	java/lang/reflect/InvocationTargetException
    //   39	49	820	java/lang/reflect/InvocationTargetException
    //   69	79	826	java/lang/reflect/InvocationTargetException
    //   426	436	832	java/lang/reflect/InvocationTargetException
    //   464	475	838	java/lang/reflect/InvocationTargetException
    //   692	704	844	java/lang/reflect/InvocationTargetException
    //   155	167	850	java/lang/reflect/InvocationTargetException
    //   650	662	856	java/lang/reflect/InvocationTargetException
  }
  
  /* Error */
  public void b0075uu007500750075uuu0075(com.db.pwcc.dbmobile.model.error.DbError paramDbError)
  {
    // Byte code:
    //   0: getstatic 89	uuuuuu/mmmmmq:b007600760076vvvv0076v	I
    //   3: getstatic 91	uuuuuu/mmmmmq:b0076vv0076vvv0076v	I
    //   6: iadd
    //   7: getstatic 89	uuuuuu/mmmmmq:b007600760076vvvv0076v	I
    //   10: imul
    //   11: getstatic 93	uuuuuu/mmmmmq:bv0076v0076vvv0076v	I
    //   14: irem
    //   15: getstatic 95	uuuuuu/mmmmmq:bvvv0076vvv0076v	I
    //   18: if_icmpeq +85 -> 103
    //   21: bipush 84
    //   23: putstatic 89	uuuuuu/mmmmmq:b007600760076vvvv0076v	I
    //   26: bipush 48
    //   28: putstatic 95	uuuuuu/mmmmmq:bvvv0076vvv0076v	I
    //   31: getstatic 89	uuuuuu/mmmmmq:b007600760076vvvv0076v	I
    //   34: getstatic 91	uuuuuu/mmmmmq:b0076vv0076vvv0076v	I
    //   37: iadd
    //   38: getstatic 89	uuuuuu/mmmmmq:b007600760076vvvv0076v	I
    //   41: imul
    //   42: getstatic 93	uuuuuu/mmmmmq:bv0076v0076vvv0076v	I
    //   45: irem
    //   46: getstatic 95	uuuuuu/mmmmmq:bvvv0076vvv0076v	I
    //   49: if_icmpeq +54 -> 103
    //   52: ldc 2
    //   54: ldc_w 312
    //   57: bipush 23
    //   59: sipush 236
    //   62: iconst_0
    //   63: invokestatic 170	xxxxxx/uxxxxx:bbbb0062b0062b0062b0062	(Ljava/lang/String;CCC)Ljava/lang/String;
    //   66: iconst_0
    //   67: anewarray 105	java/lang/Class
    //   70: invokevirtual 109	java/lang/Class:getMethod	(Ljava/lang/String;[Ljava/lang/Class;)Ljava/lang/reflect/Method;
    //   73: astore 6
    //   75: aload 6
    //   77: aconst_null
    //   78: iconst_0
    //   79: anewarray 111	java/lang/Object
    //   82: invokevirtual 117	java/lang/reflect/Method:invoke	(Ljava/lang/Object;[Ljava/lang/Object;)Ljava/lang/Object;
    //   85: astore 6
    //   87: aload 6
    //   89: checkcast 119	java/lang/Integer
    //   92: invokevirtual 122	java/lang/Integer:intValue	()I
    //   95: putstatic 89	uuuuuu/mmmmmq:b007600760076vvvv0076v	I
    //   98: bipush 43
    //   100: putstatic 95	uuuuuu/mmmmmq:bvvv0076vvv0076v	I
    //   103: getstatic 89	uuuuuu/mmmmmq:b007600760076vvvv0076v	I
    //   106: istore_2
    //   107: getstatic 91	uuuuuu/mmmmmq:b0076vv0076vvv0076v	I
    //   110: istore_3
    //   111: getstatic 93	uuuuuu/mmmmmq:bv0076v0076vvv0076v	I
    //   114: istore 4
    //   116: getstatic 89	uuuuuu/mmmmmq:b007600760076vvvv0076v	I
    //   119: istore 5
    //   121: iload 5
    //   123: getstatic 91	uuuuuu/mmmmmq:b0076vv0076vvv0076v	I
    //   126: iload 5
    //   128: iadd
    //   129: imul
    //   130: getstatic 93	uuuuuu/mmmmmq:bv0076v0076vvv0076v	I
    //   133: irem
    //   134: tableswitch	default:+18->152, 0:+66->200
    //   152: bipush 69
    //   154: putstatic 89	uuuuuu/mmmmmq:b007600760076vvvv0076v	I
    //   157: ldc 2
    //   159: ldc_w 314
    //   162: bipush 70
    //   164: iconst_5
    //   165: invokestatic 103	xxxxxx/uxxxxx:bb00620062bb0062b0062b0062	(Ljava/lang/String;CC)Ljava/lang/String;
    //   168: iconst_0
    //   169: anewarray 105	java/lang/Class
    //   172: invokevirtual 109	java/lang/Class:getMethod	(Ljava/lang/String;[Ljava/lang/Class;)Ljava/lang/reflect/Method;
    //   175: astore 6
    //   177: aload 6
    //   179: aconst_null
    //   180: iconst_0
    //   181: anewarray 111	java/lang/Object
    //   184: invokevirtual 117	java/lang/reflect/Method:invoke	(Ljava/lang/Object;[Ljava/lang/Object;)Ljava/lang/Object;
    //   187: astore 6
    //   189: aload 6
    //   191: checkcast 119	java/lang/Integer
    //   194: invokevirtual 122	java/lang/Integer:intValue	()I
    //   197: putstatic 95	uuuuuu/mmmmmq:bvvv0076vvv0076v	I
    //   200: iload_3
    //   201: iload_2
    //   202: iadd
    //   203: iload_2
    //   204: imul
    //   205: iload 4
    //   207: irem
    //   208: tableswitch	default:+20->228, 0:+30->238
    //   228: bipush 84
    //   230: putstatic 89	uuuuuu/mmmmmq:b007600760076vvvv0076v	I
    //   233: bipush 80
    //   235: putstatic 95	uuuuuu/mmmmmq:bvvv0076vvv0076v	I
    //   238: ldc 2
    //   240: ldc_w 316
    //   243: sipush 251
    //   246: bipush 37
    //   248: iconst_1
    //   249: invokestatic 170	xxxxxx/uxxxxx:bbbb0062b0062b0062b0062	(Ljava/lang/String;CCC)Ljava/lang/String;
    //   252: iconst_1
    //   253: anewarray 105	java/lang/Class
    //   256: dup
    //   257: iconst_0
    //   258: ldc -7
    //   260: aastore
    //   261: invokevirtual 109	java/lang/Class:getMethod	(Ljava/lang/String;[Ljava/lang/Class;)Ljava/lang/reflect/Method;
    //   264: astore 6
    //   266: aload 6
    //   268: aload_0
    //   269: iconst_1
    //   270: anewarray 111	java/lang/Object
    //   273: dup
    //   274: iconst_0
    //   275: aload_1
    //   276: aastore
    //   277: invokevirtual 117	java/lang/reflect/Method:invoke	(Ljava/lang/Object;[Ljava/lang/Object;)Ljava/lang/Object;
    //   280: pop
    //   281: return
    //   282: astore_1
    //   283: aload_1
    //   284: invokevirtual 184	java/lang/reflect/InvocationTargetException:getCause	()Ljava/lang/Throwable;
    //   287: athrow
    //   288: astore_1
    //   289: aload_1
    //   290: invokevirtual 184	java/lang/reflect/InvocationTargetException:getCause	()Ljava/lang/Throwable;
    //   293: athrow
    //   294: astore_1
    //   295: aload_1
    //   296: invokevirtual 184	java/lang/reflect/InvocationTargetException:getCause	()Ljava/lang/Throwable;
    //   299: athrow
    // Local variable table:
    //   start	length	slot	name	signature
    //   0	300	0	this	mmmmmq
    //   0	300	1	paramDbError	com.db.pwcc.dbmobile.model.error.DbError
    //   106	99	2	i	int
    //   110	93	3	j	int
    //   114	94	4	k	int
    //   119	11	5	m	int
    //   73	194	6	localObject	Object
    // Exception table:
    //   from	to	target	type
    //   177	189	282	java/lang/reflect/InvocationTargetException
    //   266	281	288	java/lang/reflect/InvocationTargetException
    //   75	87	294	java/lang/reflect/InvocationTargetException
  }
  
  /* Error */
  public void bu007500750075u0075uuu0075()
  {
    // Byte code:
    //   0: getstatic 89	uuuuuu/mmmmmq:b007600760076vvvv0076v	I
    //   3: istore_1
    //   4: ldc 2
    //   6: ldc_w 319
    //   9: bipush 48
    //   11: sipush 166
    //   14: iconst_0
    //   15: invokestatic 170	xxxxxx/uxxxxx:bbbb0062b0062b0062b0062	(Ljava/lang/String;CCC)Ljava/lang/String;
    //   18: iconst_0
    //   19: anewarray 105	java/lang/Class
    //   22: invokevirtual 109	java/lang/Class:getMethod	(Ljava/lang/String;[Ljava/lang/Class;)Ljava/lang/reflect/Method;
    //   25: astore 5
    //   27: aload 5
    //   29: aconst_null
    //   30: iconst_0
    //   31: anewarray 111	java/lang/Object
    //   34: invokevirtual 117	java/lang/reflect/Method:invoke	(Ljava/lang/Object;[Ljava/lang/Object;)Ljava/lang/Object;
    //   37: astore 5
    //   39: aload 5
    //   41: checkcast 119	java/lang/Integer
    //   44: invokevirtual 122	java/lang/Integer:intValue	()I
    //   47: istore_2
    //   48: getstatic 89	uuuuuu/mmmmmq:b007600760076vvvv0076v	I
    //   51: istore_3
    //   52: getstatic 93	uuuuuu/mmmmmq:bv0076v0076vvv0076v	I
    //   55: istore 4
    //   57: ldc 2
    //   59: ldc_w 321
    //   62: sipush 157
    //   65: iconst_3
    //   66: invokestatic 103	xxxxxx/uxxxxx:bb00620062bb0062b0062b0062	(Ljava/lang/String;CC)Ljava/lang/String;
    //   69: iconst_0
    //   70: anewarray 105	java/lang/Class
    //   73: invokevirtual 109	java/lang/Class:getMethod	(Ljava/lang/String;[Ljava/lang/Class;)Ljava/lang/reflect/Method;
    //   76: astore 5
    //   78: aload 5
    //   80: aconst_null
    //   81: iconst_0
    //   82: anewarray 111	java/lang/Object
    //   85: invokevirtual 117	java/lang/reflect/Method:invoke	(Ljava/lang/Object;[Ljava/lang/Object;)Ljava/lang/Object;
    //   88: astore 5
    //   90: iload_2
    //   91: iload_1
    //   92: iadd
    //   93: iload_3
    //   94: imul
    //   95: iload 4
    //   97: irem
    //   98: aload 5
    //   100: checkcast 119	java/lang/Integer
    //   103: invokevirtual 122	java/lang/Integer:intValue	()I
    //   106: if_icmpeq +52 -> 158
    //   109: bipush 91
    //   111: putstatic 89	uuuuuu/mmmmmq:b007600760076vvvv0076v	I
    //   114: ldc 2
    //   116: ldc_w 323
    //   119: sipush 161
    //   122: iconst_0
    //   123: invokestatic 103	xxxxxx/uxxxxx:bb00620062bb0062b0062b0062	(Ljava/lang/String;CC)Ljava/lang/String;
    //   126: iconst_0
    //   127: anewarray 105	java/lang/Class
    //   130: invokevirtual 109	java/lang/Class:getMethod	(Ljava/lang/String;[Ljava/lang/Class;)Ljava/lang/reflect/Method;
    //   133: astore 5
    //   135: aload 5
    //   137: aconst_null
    //   138: iconst_0
    //   139: anewarray 111	java/lang/Object
    //   142: invokevirtual 117	java/lang/reflect/Method:invoke	(Ljava/lang/Object;[Ljava/lang/Object;)Ljava/lang/Object;
    //   145: astore 5
    //   147: aload 5
    //   149: checkcast 119	java/lang/Integer
    //   152: invokevirtual 122	java/lang/Integer:intValue	()I
    //   155: putstatic 95	uuuuuu/mmmmmq:bvvv0076vvv0076v	I
    //   158: new 325	uuuuuu/alllaa
    //   161: dup
    //   162: invokespecial 326	uuuuuu/alllaa:<init>	()V
    //   165: astore 5
    //   167: getstatic 89	uuuuuu/mmmmmq:b007600760076vvvv0076v	I
    //   170: istore_1
    //   171: ldc 2
    //   173: ldc_w 328
    //   176: sipush 153
    //   179: iconst_0
    //   180: invokestatic 103	xxxxxx/uxxxxx:bb00620062bb0062b0062b0062	(Ljava/lang/String;CC)Ljava/lang/String;
    //   183: iconst_0
    //   184: anewarray 105	java/lang/Class
    //   187: invokevirtual 109	java/lang/Class:getMethod	(Ljava/lang/String;[Ljava/lang/Class;)Ljava/lang/reflect/Method;
    //   190: astore 6
    //   192: aload 6
    //   194: aconst_null
    //   195: iconst_0
    //   196: anewarray 111	java/lang/Object
    //   199: invokevirtual 117	java/lang/reflect/Method:invoke	(Ljava/lang/Object;[Ljava/lang/Object;)Ljava/lang/Object;
    //   202: astore 6
    //   204: aload 6
    //   206: checkcast 119	java/lang/Integer
    //   209: invokevirtual 122	java/lang/Integer:intValue	()I
    //   212: iload_1
    //   213: iadd
    //   214: getstatic 89	uuuuuu/mmmmmq:b007600760076vvvv0076v	I
    //   217: imul
    //   218: getstatic 93	uuuuuu/mmmmmq:bv0076v0076vvv0076v	I
    //   221: irem
    //   222: getstatic 95	uuuuuu/mmmmmq:bvvv0076vvv0076v	I
    //   225: if_icmpeq +169 -> 394
    //   228: ldc 2
    //   230: ldc_w 330
    //   233: sipush 240
    //   236: iconst_2
    //   237: invokestatic 103	xxxxxx/uxxxxx:bb00620062bb0062b0062b0062	(Ljava/lang/String;CC)Ljava/lang/String;
    //   240: iconst_0
    //   241: anewarray 105	java/lang/Class
    //   244: invokevirtual 109	java/lang/Class:getMethod	(Ljava/lang/String;[Ljava/lang/Class;)Ljava/lang/reflect/Method;
    //   247: astore 6
    //   249: aload 6
    //   251: aconst_null
    //   252: iconst_0
    //   253: anewarray 111	java/lang/Object
    //   256: invokevirtual 117	java/lang/reflect/Method:invoke	(Ljava/lang/Object;[Ljava/lang/Object;)Ljava/lang/Object;
    //   259: astore 6
    //   261: aload 6
    //   263: checkcast 119	java/lang/Integer
    //   266: invokevirtual 122	java/lang/Integer:intValue	()I
    //   269: istore_1
    //   270: getstatic 89	uuuuuu/mmmmmq:b007600760076vvvv0076v	I
    //   273: getstatic 91	uuuuuu/mmmmmq:b0076vv0076vvv0076v	I
    //   276: iadd
    //   277: getstatic 89	uuuuuu/mmmmmq:b007600760076vvvv0076v	I
    //   280: imul
    //   281: getstatic 93	uuuuuu/mmmmmq:bv0076v0076vvv0076v	I
    //   284: irem
    //   285: getstatic 95	uuuuuu/mmmmmq:bvvv0076vvv0076v	I
    //   288: if_icmpeq +55 -> 343
    //   291: bipush 68
    //   293: putstatic 89	uuuuuu/mmmmmq:b007600760076vvvv0076v	I
    //   296: ldc 2
    //   298: ldc_w 332
    //   301: sipush 247
    //   304: sipush 205
    //   307: iconst_2
    //   308: invokestatic 170	xxxxxx/uxxxxx:bbbb0062b0062b0062b0062	(Ljava/lang/String;CCC)Ljava/lang/String;
    //   311: iconst_0
    //   312: anewarray 105	java/lang/Class
    //   315: invokevirtual 109	java/lang/Class:getMethod	(Ljava/lang/String;[Ljava/lang/Class;)Ljava/lang/reflect/Method;
    //   318: astore 6
    //   320: aload 6
    //   322: aconst_null
    //   323: iconst_0
    //   324: anewarray 111	java/lang/Object
    //   327: invokevirtual 117	java/lang/reflect/Method:invoke	(Ljava/lang/Object;[Ljava/lang/Object;)Ljava/lang/Object;
    //   330: astore 6
    //   332: aload 6
    //   334: checkcast 119	java/lang/Integer
    //   337: invokevirtual 122	java/lang/Integer:intValue	()I
    //   340: putstatic 95	uuuuuu/mmmmmq:bvvv0076vvv0076v	I
    //   343: iload_1
    //   344: putstatic 89	uuuuuu/mmmmmq:b007600760076vvvv0076v	I
    //   347: ldc 2
    //   349: ldc_w 334
    //   352: sipush 193
    //   355: sipush 236
    //   358: iconst_0
    //   359: invokestatic 170	xxxxxx/uxxxxx:bbbb0062b0062b0062b0062	(Ljava/lang/String;CCC)Ljava/lang/String;
    //   362: iconst_0
    //   363: anewarray 105	java/lang/Class
    //   366: invokevirtual 109	java/lang/Class:getMethod	(Ljava/lang/String;[Ljava/lang/Class;)Ljava/lang/reflect/Method;
    //   369: astore 6
    //   371: aload 6
    //   373: aconst_null
    //   374: iconst_0
    //   375: anewarray 111	java/lang/Object
    //   378: invokevirtual 117	java/lang/reflect/Method:invoke	(Ljava/lang/Object;[Ljava/lang/Object;)Ljava/lang/Object;
    //   381: astore 6
    //   383: aload 6
    //   385: checkcast 119	java/lang/Integer
    //   388: invokevirtual 122	java/lang/Integer:intValue	()I
    //   391: putstatic 95	uuuuuu/mmmmmq:bvvv0076vvv0076v	I
    //   394: aload 5
    //   396: aload_0
    //   397: invokevirtual 338	uuuuuu/alllaa:b00750075uuu00750075007500750075	(Luuuuuu/alllll$lallll;)V
    //   400: return
    //   401: astore 5
    //   403: aload 5
    //   405: invokevirtual 184	java/lang/reflect/InvocationTargetException:getCause	()Ljava/lang/Throwable;
    //   408: athrow
    //   409: astore 5
    //   411: aload 5
    //   413: invokevirtual 184	java/lang/reflect/InvocationTargetException:getCause	()Ljava/lang/Throwable;
    //   416: athrow
    //   417: astore 5
    //   419: aload 5
    //   421: invokevirtual 184	java/lang/reflect/InvocationTargetException:getCause	()Ljava/lang/Throwable;
    //   424: athrow
    //   425: astore 5
    //   427: aload 5
    //   429: invokevirtual 184	java/lang/reflect/InvocationTargetException:getCause	()Ljava/lang/Throwable;
    //   432: athrow
    //   433: astore 5
    //   435: aload 5
    //   437: invokevirtual 184	java/lang/reflect/InvocationTargetException:getCause	()Ljava/lang/Throwable;
    //   440: athrow
    //   441: astore 5
    //   443: aload 5
    //   445: invokevirtual 184	java/lang/reflect/InvocationTargetException:getCause	()Ljava/lang/Throwable;
    //   448: athrow
    //   449: astore 5
    //   451: aload 5
    //   453: invokevirtual 184	java/lang/reflect/InvocationTargetException:getCause	()Ljava/lang/Throwable;
    //   456: athrow
    // Local variable table:
    //   start	length	slot	name	signature
    //   0	457	0	this	mmmmmq
    //   3	341	1	i	int
    //   47	46	2	j	int
    //   51	44	3	k	int
    //   55	43	4	m	int
    //   25	370	5	localObject1	Object
    //   401	3	5	localInvocationTargetException1	InvocationTargetException
    //   409	3	5	localInvocationTargetException2	InvocationTargetException
    //   417	3	5	localInvocationTargetException3	InvocationTargetException
    //   425	3	5	localInvocationTargetException4	InvocationTargetException
    //   433	3	5	localInvocationTargetException5	InvocationTargetException
    //   441	3	5	localInvocationTargetException6	InvocationTargetException
    //   449	3	5	localInvocationTargetException7	InvocationTargetException
    //   190	194	6	localObject2	Object
    // Exception table:
    //   from	to	target	type
    //   371	383	401	java/lang/reflect/InvocationTargetException
    //   249	261	409	java/lang/reflect/InvocationTargetException
    //   78	90	417	java/lang/reflect/InvocationTargetException
    //   192	204	425	java/lang/reflect/InvocationTargetException
    //   27	39	433	java/lang/reflect/InvocationTargetException
    //   135	147	441	java/lang/reflect/InvocationTargetException
    //   320	332	449	java/lang/reflect/InvocationTargetException
  }
  
  /* Error */
  public void bu00750075u00750075uuu0075(List<ExternalFinancialInstitute> paramList, String paramString)
  {
    // Byte code:
    //   0: aload_0
    //   1: getfield 43	uuuuuu/mmmmmq:b00760076vvvvv0076v	Ljava/util/List;
    //   4: invokeinterface 208 1 0
    //   9: aload_0
    //   10: getfield 43	uuuuuu/mmmmmq:b00760076vvvvv0076v	Ljava/util/List;
    //   13: astore_2
    //   14: getstatic 89	uuuuuu/mmmmmq:b007600760076vvvv0076v	I
    //   17: istore_3
    //   18: iload_3
    //   19: getstatic 91	uuuuuu/mmmmmq:b0076vv0076vvv0076v	I
    //   22: iload_3
    //   23: iadd
    //   24: imul
    //   25: getstatic 93	uuuuuu/mmmmmq:bv0076v0076vvv0076v	I
    //   28: irem
    //   29: tableswitch	default:+19->48, 0:+111->140
    //   48: ldc 2
    //   50: ldc_w 342
    //   53: bipush 67
    //   55: sipush 203
    //   58: iconst_3
    //   59: invokestatic 170	xxxxxx/uxxxxx:bbbb0062b0062b0062b0062	(Ljava/lang/String;CCC)Ljava/lang/String;
    //   62: iconst_0
    //   63: anewarray 105	java/lang/Class
    //   66: invokevirtual 109	java/lang/Class:getMethod	(Ljava/lang/String;[Ljava/lang/Class;)Ljava/lang/reflect/Method;
    //   69: astore 4
    //   71: aload 4
    //   73: aconst_null
    //   74: iconst_0
    //   75: anewarray 111	java/lang/Object
    //   78: invokevirtual 117	java/lang/reflect/Method:invoke	(Ljava/lang/Object;[Ljava/lang/Object;)Ljava/lang/Object;
    //   81: astore 4
    //   83: aload 4
    //   85: checkcast 119	java/lang/Integer
    //   88: invokevirtual 122	java/lang/Integer:intValue	()I
    //   91: putstatic 89	uuuuuu/mmmmmq:b007600760076vvvv0076v	I
    //   94: ldc 2
    //   96: ldc_w 344
    //   99: sipush 216
    //   102: bipush 12
    //   104: iconst_1
    //   105: invokestatic 170	xxxxxx/uxxxxx:bbbb0062b0062b0062b0062	(Ljava/lang/String;CCC)Ljava/lang/String;
    //   108: iconst_0
    //   109: anewarray 105	java/lang/Class
    //   112: invokevirtual 109	java/lang/Class:getMethod	(Ljava/lang/String;[Ljava/lang/Class;)Ljava/lang/reflect/Method;
    //   115: astore 4
    //   117: aload 4
    //   119: aconst_null
    //   120: iconst_0
    //   121: anewarray 111	java/lang/Object
    //   124: invokevirtual 117	java/lang/reflect/Method:invoke	(Ljava/lang/Object;[Ljava/lang/Object;)Ljava/lang/Object;
    //   127: astore 4
    //   129: aload 4
    //   131: checkcast 119	java/lang/Integer
    //   134: invokevirtual 122	java/lang/Integer:intValue	()I
    //   137: putstatic 95	uuuuuu/mmmmmq:bvvv0076vvv0076v	I
    //   140: aload_2
    //   141: aload_1
    //   142: invokeinterface 212 2 0
    //   147: pop
    //   148: getstatic 89	uuuuuu/mmmmmq:b007600760076vvvv0076v	I
    //   151: getstatic 91	uuuuuu/mmmmmq:b0076vv0076vvv0076v	I
    //   154: iadd
    //   155: getstatic 89	uuuuuu/mmmmmq:b007600760076vvvv0076v	I
    //   158: imul
    //   159: getstatic 93	uuuuuu/mmmmmq:bv0076v0076vvv0076v	I
    //   162: irem
    //   163: getstatic 95	uuuuuu/mmmmmq:bvvv0076vvv0076v	I
    //   166: if_icmpeq +49 -> 215
    //   169: ldc 2
    //   171: ldc_w 346
    //   174: bipush 12
    //   176: bipush 22
    //   178: iconst_2
    //   179: invokestatic 170	xxxxxx/uxxxxx:bbbb0062b0062b0062b0062	(Ljava/lang/String;CCC)Ljava/lang/String;
    //   182: iconst_0
    //   183: anewarray 105	java/lang/Class
    //   186: invokevirtual 109	java/lang/Class:getMethod	(Ljava/lang/String;[Ljava/lang/Class;)Ljava/lang/reflect/Method;
    //   189: astore_1
    //   190: aload_1
    //   191: aconst_null
    //   192: iconst_0
    //   193: anewarray 111	java/lang/Object
    //   196: invokevirtual 117	java/lang/reflect/Method:invoke	(Ljava/lang/Object;[Ljava/lang/Object;)Ljava/lang/Object;
    //   199: astore_1
    //   200: aload_1
    //   201: checkcast 119	java/lang/Integer
    //   204: invokevirtual 122	java/lang/Integer:intValue	()I
    //   207: putstatic 89	uuuuuu/mmmmmq:b007600760076vvvv0076v	I
    //   210: bipush 29
    //   212: putstatic 95	uuuuuu/mmmmmq:bvvv0076vvv0076v	I
    //   215: getstatic 89	uuuuuu/mmmmmq:b007600760076vvvv0076v	I
    //   218: istore_3
    //   219: ldc 2
    //   221: ldc_w 348
    //   224: sipush 190
    //   227: sipush 204
    //   230: iconst_3
    //   231: invokestatic 170	xxxxxx/uxxxxx:bbbb0062b0062b0062b0062	(Ljava/lang/String;CCC)Ljava/lang/String;
    //   234: iconst_0
    //   235: anewarray 105	java/lang/Class
    //   238: invokevirtual 109	java/lang/Class:getMethod	(Ljava/lang/String;[Ljava/lang/Class;)Ljava/lang/reflect/Method;
    //   241: astore_1
    //   242: aload_1
    //   243: aconst_null
    //   244: iconst_0
    //   245: anewarray 111	java/lang/Object
    //   248: invokevirtual 117	java/lang/reflect/Method:invoke	(Ljava/lang/Object;[Ljava/lang/Object;)Ljava/lang/Object;
    //   251: astore_1
    //   252: aload_1
    //   253: checkcast 119	java/lang/Integer
    //   256: invokevirtual 122	java/lang/Integer:intValue	()I
    //   259: iload_3
    //   260: iadd
    //   261: getstatic 89	uuuuuu/mmmmmq:b007600760076vvvv0076v	I
    //   264: imul
    //   265: getstatic 93	uuuuuu/mmmmmq:bv0076v0076vvv0076v	I
    //   268: irem
    //   269: getstatic 95	uuuuuu/mmmmmq:bvvv0076vvv0076v	I
    //   272: if_icmpeq +116 -> 388
    //   275: bipush 37
    //   277: putstatic 89	uuuuuu/mmmmmq:b007600760076vvvv0076v	I
    //   280: iconst_2
    //   281: putstatic 95	uuuuuu/mmmmmq:bvvv0076vvv0076v	I
    //   284: getstatic 89	uuuuuu/mmmmmq:b007600760076vvvv0076v	I
    //   287: istore_3
    //   288: ldc 2
    //   290: ldc_w 350
    //   293: sipush 147
    //   296: sipush 132
    //   299: iconst_0
    //   300: invokestatic 170	xxxxxx/uxxxxx:bbbb0062b0062b0062b0062	(Ljava/lang/String;CCC)Ljava/lang/String;
    //   303: iconst_0
    //   304: anewarray 105	java/lang/Class
    //   307: invokevirtual 109	java/lang/Class:getMethod	(Ljava/lang/String;[Ljava/lang/Class;)Ljava/lang/reflect/Method;
    //   310: astore_1
    //   311: aload_1
    //   312: aconst_null
    //   313: iconst_0
    //   314: anewarray 111	java/lang/Object
    //   317: invokevirtual 117	java/lang/reflect/Method:invoke	(Ljava/lang/Object;[Ljava/lang/Object;)Ljava/lang/Object;
    //   320: astore_1
    //   321: aload_1
    //   322: checkcast 119	java/lang/Integer
    //   325: invokevirtual 122	java/lang/Integer:intValue	()I
    //   328: iload_3
    //   329: iadd
    //   330: getstatic 89	uuuuuu/mmmmmq:b007600760076vvvv0076v	I
    //   333: imul
    //   334: getstatic 93	uuuuuu/mmmmmq:bv0076v0076vvv0076v	I
    //   337: irem
    //   338: getstatic 95	uuuuuu/mmmmmq:bvvv0076vvv0076v	I
    //   341: if_icmpeq +47 -> 388
    //   344: bipush 69
    //   346: putstatic 89	uuuuuu/mmmmmq:b007600760076vvvv0076v	I
    //   349: ldc 2
    //   351: ldc_w 352
    //   354: bipush 17
    //   356: iconst_4
    //   357: invokestatic 103	xxxxxx/uxxxxx:bb00620062bb0062b0062b0062	(Ljava/lang/String;CC)Ljava/lang/String;
    //   360: iconst_0
    //   361: anewarray 105	java/lang/Class
    //   364: invokevirtual 109	java/lang/Class:getMethod	(Ljava/lang/String;[Ljava/lang/Class;)Ljava/lang/reflect/Method;
    //   367: astore_1
    //   368: aload_1
    //   369: aconst_null
    //   370: iconst_0
    //   371: anewarray 111	java/lang/Object
    //   374: invokevirtual 117	java/lang/reflect/Method:invoke	(Ljava/lang/Object;[Ljava/lang/Object;)Ljava/lang/Object;
    //   377: astore_1
    //   378: aload_1
    //   379: checkcast 119	java/lang/Integer
    //   382: invokevirtual 122	java/lang/Integer:intValue	()I
    //   385: putstatic 95	uuuuuu/mmmmmq:bvvv0076vvv0076v	I
    //   388: aload_0
    //   389: iconst_0
    //   390: putfield 45	uuuuuu/mmmmmq:bv0076vvvvv0076v	Z
    //   393: return
    //   394: astore_1
    //   395: aload_1
    //   396: invokevirtual 184	java/lang/reflect/InvocationTargetException:getCause	()Ljava/lang/Throwable;
    //   399: athrow
    //   400: astore_1
    //   401: aload_1
    //   402: invokevirtual 184	java/lang/reflect/InvocationTargetException:getCause	()Ljava/lang/Throwable;
    //   405: athrow
    //   406: astore_1
    //   407: aload_1
    //   408: invokevirtual 184	java/lang/reflect/InvocationTargetException:getCause	()Ljava/lang/Throwable;
    //   411: athrow
    //   412: astore_1
    //   413: aload_1
    //   414: invokevirtual 184	java/lang/reflect/InvocationTargetException:getCause	()Ljava/lang/Throwable;
    //   417: athrow
    //   418: astore_1
    //   419: aload_1
    //   420: invokevirtual 184	java/lang/reflect/InvocationTargetException:getCause	()Ljava/lang/Throwable;
    //   423: athrow
    //   424: astore_1
    //   425: aload_1
    //   426: invokevirtual 184	java/lang/reflect/InvocationTargetException:getCause	()Ljava/lang/Throwable;
    //   429: athrow
    // Local variable table:
    //   start	length	slot	name	signature
    //   0	430	0	this	mmmmmq
    //   0	430	1	paramList	List<ExternalFinancialInstitute>
    //   0	430	2	paramString	String
    //   17	313	3	i	int
    //   69	61	4	localObject	Object
    // Exception table:
    //   from	to	target	type
    //   242	252	394	java/lang/reflect/InvocationTargetException
    //   71	83	400	java/lang/reflect/InvocationTargetException
    //   311	321	406	java/lang/reflect/InvocationTargetException
    //   117	129	412	java/lang/reflect/InvocationTargetException
    //   368	378	418	java/lang/reflect/InvocationTargetException
    //   190	200	424	java/lang/reflect/InvocationTargetException
  }
  
  public void bu0075u007500750075uuu0075(EfiSuggestion[] paramArrayOfEfiSuggestion)
  {
    paramArrayOfEfiSuggestion = Arrays.asList(paramArrayOfEfiSuggestion);
    if (!paramArrayOfEfiSuggestion.isEmpty())
    {
      Iterator localIterator = paramArrayOfEfiSuggestion.iterator();
      while (localIterator.hasNext())
      {
        Object localObject = (EfiSuggestion)localIterator.next();
        ((EfiSuggestion)localObject).setIconRes(Integer.valueOf(this.b0076v0076vvvv0076v.buu0075u0075uuu00750075(((EfiSuggestion)localObject).getGroupName())));
        int i = b007600760076vvvv0076v;
        int j = b0076vv0076vvv0076v;
        int k = b007600760076vvvv0076v;
        int m = bv0076v0076vvv0076v;
        int n = b007600760076vvvv0076v;
        switch (n * (b0076vv0076vvv0076v + n) % bv0076v0076vvv0076v)
        {
        default: 
          b007600760076vvvv0076v = 51;
          localObject = mmmmmq.class.getMethod(uxxxxx.bb00620062bb0062b0062b0062("c23;:67?>:;CB>?GF\bCDLK\r\016\017JKSR", '\001', '\002'), new Class[0]);
        }
        try
        {
          localObject = ((Method)localObject).invoke(null, new Object[0]);
          bvvv0076vvv0076v = ((Integer)localObject).intValue();
          if (k * (i + j) % m != bvvv0076vvv0076v)
          {
            i = b007600760076vvvv0076v;
            switch (i * (b0076vv0076vvv0076v + i) % bv0076v0076vvv0076v)
            {
            default: 
              b007600760076vvvv0076v = 70;
              localObject = mmmmmq.class.getMethod(uxxxxx.bbbb0062b0062b0062b0062("P\037 ('#$,+'(0/+,43t0198yz{78@?", '', '`', '\003'), new Class[0]);
            }
          }
        }
        catch (InvocationTargetException paramArrayOfEfiSuggestion)
        {
          try
          {
            localObject = ((Method)localObject).invoke(null, new Object[0]);
            bvvv0076vvv0076v = ((Integer)localObject).intValue();
            b007600760076vvvv0076v = 55;
            localObject = mmmmmq.class.getMethod(uxxxxx.bbbb0062b0062b0062b0062("m:9?<65;82174.-30o)(.+jih\"!'$", '', '', '\001'), new Class[0]);
            try
            {
              localObject = ((Method)localObject).invoke(null, new Object[0]);
              bvvv0076vvv0076v = ((Integer)localObject).intValue();
              i = b007600760076vvvv0076v;
              switch (i * (b0076vv0076vvv0076v + i) % bv0076v0076vvv0076v)
              {
              }
              localObject = mmmmmq.class.getMethod(uxxxxx.bb00620062bb0062b0062b0062("F\023\022\030\025\017\016\024\021\013\n\020\r\007\006\f\tH\002\001\007\004CBAzy|", '', '\003'), new Class[0]);
            }
            catch (InvocationTargetException paramArrayOfEfiSuggestion)
            {
              throw paramArrayOfEfiSuggestion.getCause();
            }
          }
          catch (InvocationTargetException paramArrayOfEfiSuggestion)
          {
            throw paramArrayOfEfiSuggestion.getCause();
          }
          try
          {
            localObject = ((Method)localObject).invoke(null, new Object[0]);
            b007600760076vvvv0076v = ((Integer)localObject).intValue();
            localObject = mmmmmq.class.getMethod(uxxxxx.bb00620062bb0062b0062b0062("k:;CB>?GFBCKJFGON\020KLTS\025\026\027RS[Z", '\003', '\000'), new Class[0]);
          }
          catch (InvocationTargetException paramArrayOfEfiSuggestion)
          {
            throw paramArrayOfEfiSuggestion.getCause();
          }
          try
          {
            localObject = ((Method)localObject).invoke(null, new Object[0]);
            bvvv0076vvv0076v = ((Integer)localObject).intValue();
          }
          catch (InvocationTargetException paramArrayOfEfiSuggestion)
          {
            throw paramArrayOfEfiSuggestion.getCause();
          }
          paramArrayOfEfiSuggestion = paramArrayOfEfiSuggestion;
          throw paramArrayOfEfiSuggestion.getCause();
        }
      }
    }
    ((qqmmmq.qmmmmq)this.bnnnnn006E006E006En).showEfiSuggestionsList(paramArrayOfEfiSuggestion);
  }
  
  /* Error */
  public void buu0075u00750075uuu0075(com.db.pwcc.dbmobile.model.error.DbError paramDbError)
  {
    // Byte code:
    //   0: iconst_5
    //   1: istore_2
    //   2: aload_0
    //   3: invokevirtual 396	uuuuuu/mmmmmq:bkk006Bk006Bk006Bk006Bk	()Z
    //   6: ifne +4 -> 10
    //   9: return
    //   10: aload_0
    //   11: aload_1
    //   12: invokevirtual 400	uuuuuu/mmmmmq:boo006F006F006F006Fo006F006F006F	(Lcom/db/pwcc/dbmobile/model/error/DbError;)Z
    //   15: ifeq +286 -> 301
    //   18: aload_0
    //   19: aload_1
    //   20: invokevirtual 404	com/db/pwcc/dbmobile/model/error/DbError:getDbCode	()Lcom/db/pwcc/dbmobile/model/error/DbErrorCode;
    //   23: invokevirtual 408	uuuuuu/mmmmmq:bo006Fo006F006F006Fo006F006F006F	(Lcom/db/pwcc/dbmobile/model/error/DbErrorCode;)V
    //   26: iload_2
    //   27: iconst_0
    //   28: idiv
    //   29: istore_2
    //   30: getstatic 89	uuuuuu/mmmmmq:b007600760076vvvv0076v	I
    //   33: istore_3
    //   34: getstatic 91	uuuuuu/mmmmmq:b0076vv0076vvv0076v	I
    //   37: istore 4
    //   39: ldc 2
    //   41: ldc_w 410
    //   44: sipush 169
    //   47: iconst_4
    //   48: invokestatic 103	xxxxxx/uxxxxx:bb00620062bb0062b0062b0062	(Ljava/lang/String;CC)Ljava/lang/String;
    //   51: iconst_0
    //   52: anewarray 105	java/lang/Class
    //   55: invokevirtual 109	java/lang/Class:getMethod	(Ljava/lang/String;[Ljava/lang/Class;)Ljava/lang/reflect/Method;
    //   58: astore_1
    //   59: aload_1
    //   60: aconst_null
    //   61: iconst_0
    //   62: anewarray 111	java/lang/Object
    //   65: invokevirtual 117	java/lang/reflect/Method:invoke	(Ljava/lang/Object;[Ljava/lang/Object;)Ljava/lang/Object;
    //   68: astore_1
    //   69: iload 4
    //   71: iload_3
    //   72: iadd
    //   73: iload_3
    //   74: imul
    //   75: aload_1
    //   76: checkcast 119	java/lang/Integer
    //   79: invokevirtual 122	java/lang/Integer:intValue	()I
    //   82: irem
    //   83: tableswitch	default:+17->100, 0:+209->292
    //   100: ldc 2
    //   102: ldc_w 412
    //   105: sipush 243
    //   108: sipush 145
    //   111: iconst_0
    //   112: invokestatic 170	xxxxxx/uxxxxx:bbbb0062b0062b0062b0062	(Ljava/lang/String;CCC)Ljava/lang/String;
    //   115: iconst_0
    //   116: anewarray 105	java/lang/Class
    //   119: invokevirtual 109	java/lang/Class:getMethod	(Ljava/lang/String;[Ljava/lang/Class;)Ljava/lang/reflect/Method;
    //   122: astore_1
    //   123: aload_1
    //   124: aconst_null
    //   125: iconst_0
    //   126: anewarray 111	java/lang/Object
    //   129: invokevirtual 117	java/lang/reflect/Method:invoke	(Ljava/lang/Object;[Ljava/lang/Object;)Ljava/lang/Object;
    //   132: astore_1
    //   133: aload_1
    //   134: checkcast 119	java/lang/Integer
    //   137: invokevirtual 122	java/lang/Integer:intValue	()I
    //   140: putstatic 89	uuuuuu/mmmmmq:b007600760076vvvv0076v	I
    //   143: iconst_1
    //   144: putstatic 95	uuuuuu/mmmmmq:bvvv0076vvv0076v	I
    //   147: getstatic 89	uuuuuu/mmmmmq:b007600760076vvvv0076v	I
    //   150: istore_3
    //   151: getstatic 91	uuuuuu/mmmmmq:b0076vv0076vvv0076v	I
    //   154: istore 4
    //   156: getstatic 89	uuuuuu/mmmmmq:b007600760076vvvv0076v	I
    //   159: istore 5
    //   161: ldc 2
    //   163: ldc_w 414
    //   166: sipush 234
    //   169: iconst_2
    //   170: invokestatic 103	xxxxxx/uxxxxx:bb00620062bb0062b0062b0062	(Ljava/lang/String;CC)Ljava/lang/String;
    //   173: iconst_0
    //   174: anewarray 105	java/lang/Class
    //   177: invokevirtual 109	java/lang/Class:getMethod	(Ljava/lang/String;[Ljava/lang/Class;)Ljava/lang/reflect/Method;
    //   180: astore_1
    //   181: aload_1
    //   182: aconst_null
    //   183: iconst_0
    //   184: anewarray 111	java/lang/Object
    //   187: invokevirtual 117	java/lang/reflect/Method:invoke	(Ljava/lang/Object;[Ljava/lang/Object;)Ljava/lang/Object;
    //   190: astore_1
    //   191: iload 5
    //   193: iload_3
    //   194: iload 4
    //   196: iadd
    //   197: imul
    //   198: aload_1
    //   199: checkcast 119	java/lang/Integer
    //   202: invokevirtual 122	java/lang/Integer:intValue	()I
    //   205: irem
    //   206: getstatic 95	uuuuuu/mmmmmq:bvvv0076vvv0076v	I
    //   209: if_icmpeq +83 -> 292
    //   212: ldc 2
    //   214: ldc_w 416
    //   217: bipush 123
    //   219: sipush 179
    //   222: iconst_2
    //   223: invokestatic 170	xxxxxx/uxxxxx:bbbb0062b0062b0062b0062	(Ljava/lang/String;CCC)Ljava/lang/String;
    //   226: iconst_0
    //   227: anewarray 105	java/lang/Class
    //   230: invokevirtual 109	java/lang/Class:getMethod	(Ljava/lang/String;[Ljava/lang/Class;)Ljava/lang/reflect/Method;
    //   233: astore_1
    //   234: aload_1
    //   235: aconst_null
    //   236: iconst_0
    //   237: anewarray 111	java/lang/Object
    //   240: invokevirtual 117	java/lang/reflect/Method:invoke	(Ljava/lang/Object;[Ljava/lang/Object;)Ljava/lang/Object;
    //   243: astore_1
    //   244: aload_1
    //   245: checkcast 119	java/lang/Integer
    //   248: invokevirtual 122	java/lang/Integer:intValue	()I
    //   251: putstatic 89	uuuuuu/mmmmmq:b007600760076vvvv0076v	I
    //   254: ldc 2
    //   256: ldc -90
    //   258: bipush 21
    //   260: iconst_4
    //   261: invokestatic 103	xxxxxx/uxxxxx:bb00620062bb0062b0062b0062	(Ljava/lang/String;CC)Ljava/lang/String;
    //   264: iconst_0
    //   265: anewarray 105	java/lang/Class
    //   268: invokevirtual 109	java/lang/Class:getMethod	(Ljava/lang/String;[Ljava/lang/Class;)Ljava/lang/reflect/Method;
    //   271: astore_1
    //   272: aload_1
    //   273: aconst_null
    //   274: iconst_0
    //   275: anewarray 111	java/lang/Object
    //   278: invokevirtual 117	java/lang/reflect/Method:invoke	(Ljava/lang/Object;[Ljava/lang/Object;)Ljava/lang/Object;
    //   281: astore_1
    //   282: aload_1
    //   283: checkcast 119	java/lang/Integer
    //   286: invokevirtual 122	java/lang/Integer:intValue	()I
    //   289: putstatic 95	uuuuuu/mmmmmq:bvvv0076vvv0076v	I
    //   292: goto -266 -> 26
    //   295: astore_1
    //   296: aload_1
    //   297: invokevirtual 184	java/lang/reflect/InvocationTargetException:getCause	()Ljava/lang/Throwable;
    //   300: athrow
    //   301: aload_1
    //   302: iconst_0
    //   303: invokestatic 422	uuuuuu/ooooso:b0069iii006900690069iii	(Lcom/db/pwcc/dbmobile/model/error/DbError;Z)Lcom/db/pwcc/dbmobile/multi_bank_aggregator/model/MbaErrorCode;
    //   306: astore_1
    //   307: ldc 2
    //   309: ldc_w 424
    //   312: bipush 19
    //   314: sipush 210
    //   317: iconst_2
    //   318: invokestatic 170	xxxxxx/uxxxxx:bbbb0062b0062b0062b0062	(Ljava/lang/String;CCC)Ljava/lang/String;
    //   321: iconst_0
    //   322: anewarray 105	java/lang/Class
    //   325: invokevirtual 109	java/lang/Class:getMethod	(Ljava/lang/String;[Ljava/lang/Class;)Ljava/lang/reflect/Method;
    //   328: astore 6
    //   330: aload 6
    //   332: aconst_null
    //   333: iconst_0
    //   334: anewarray 111	java/lang/Object
    //   337: invokevirtual 117	java/lang/reflect/Method:invoke	(Ljava/lang/Object;[Ljava/lang/Object;)Ljava/lang/Object;
    //   340: astore 6
    //   342: aload 6
    //   344: checkcast 119	java/lang/Integer
    //   347: invokevirtual 122	java/lang/Integer:intValue	()I
    //   350: istore_2
    //   351: getstatic 91	uuuuuu/mmmmmq:b0076vv0076vvv0076v	I
    //   354: istore_3
    //   355: ldc 2
    //   357: ldc_w 426
    //   360: bipush 86
    //   362: bipush 89
    //   364: iconst_3
    //   365: invokestatic 170	xxxxxx/uxxxxx:bbbb0062b0062b0062b0062	(Ljava/lang/String;CCC)Ljava/lang/String;
    //   368: iconst_0
    //   369: anewarray 105	java/lang/Class
    //   372: invokevirtual 109	java/lang/Class:getMethod	(Ljava/lang/String;[Ljava/lang/Class;)Ljava/lang/reflect/Method;
    //   375: astore 6
    //   377: aload 6
    //   379: aconst_null
    //   380: iconst_0
    //   381: anewarray 111	java/lang/Object
    //   384: invokevirtual 117	java/lang/reflect/Method:invoke	(Ljava/lang/Object;[Ljava/lang/Object;)Ljava/lang/Object;
    //   387: astore 6
    //   389: aload 6
    //   391: checkcast 119	java/lang/Integer
    //   394: invokevirtual 122	java/lang/Integer:intValue	()I
    //   397: iload_3
    //   398: iload_2
    //   399: iadd
    //   400: imul
    //   401: getstatic 93	uuuuuu/mmmmmq:bv0076v0076vvv0076v	I
    //   404: irem
    //   405: getstatic 95	uuuuuu/mmmmmq:bvvv0076vvv0076v	I
    //   408: if_icmpeq +93 -> 501
    //   411: ldc 2
    //   413: ldc_w 428
    //   416: bipush 33
    //   418: iconst_0
    //   419: invokestatic 103	xxxxxx/uxxxxx:bb00620062bb0062b0062b0062	(Ljava/lang/String;CC)Ljava/lang/String;
    //   422: iconst_0
    //   423: anewarray 105	java/lang/Class
    //   426: invokevirtual 109	java/lang/Class:getMethod	(Ljava/lang/String;[Ljava/lang/Class;)Ljava/lang/reflect/Method;
    //   429: astore 6
    //   431: aload 6
    //   433: aconst_null
    //   434: iconst_0
    //   435: anewarray 111	java/lang/Object
    //   438: invokevirtual 117	java/lang/reflect/Method:invoke	(Ljava/lang/Object;[Ljava/lang/Object;)Ljava/lang/Object;
    //   441: astore 6
    //   443: aload 6
    //   445: checkcast 119	java/lang/Integer
    //   448: invokevirtual 122	java/lang/Integer:intValue	()I
    //   451: putstatic 89	uuuuuu/mmmmmq:b007600760076vvvv0076v	I
    //   454: ldc 2
    //   456: ldc_w 430
    //   459: sipush 211
    //   462: sipush 214
    //   465: iconst_3
    //   466: invokestatic 170	xxxxxx/uxxxxx:bbbb0062b0062b0062b0062	(Ljava/lang/String;CCC)Ljava/lang/String;
    //   469: iconst_0
    //   470: anewarray 105	java/lang/Class
    //   473: invokevirtual 109	java/lang/Class:getMethod	(Ljava/lang/String;[Ljava/lang/Class;)Ljava/lang/reflect/Method;
    //   476: astore 6
    //   478: aload 6
    //   480: aconst_null
    //   481: iconst_0
    //   482: anewarray 111	java/lang/Object
    //   485: invokevirtual 117	java/lang/reflect/Method:invoke	(Ljava/lang/Object;[Ljava/lang/Object;)Ljava/lang/Object;
    //   488: astore 6
    //   490: aload 6
    //   492: checkcast 119	java/lang/Integer
    //   495: invokevirtual 122	java/lang/Integer:intValue	()I
    //   498: putstatic 95	uuuuuu/mmmmmq:bvvv0076vvv0076v	I
    //   501: aload_0
    //   502: getfield 158	uuuuuu/mmmmmq:bnnnnn006E006E006En	Luuuuuu/ttssst$tsssst;
    //   505: checkcast 160	uuuuuu/qqmmmq$qmmmmq
    //   508: aload_1
    //   509: invokeinterface 434 2 0
    //   514: return
    //   515: astore_1
    //   516: ldc 2
    //   518: ldc_w 436
    //   521: bipush 126
    //   523: iconst_2
    //   524: invokestatic 103	xxxxxx/uxxxxx:bb00620062bb0062b0062b0062	(Ljava/lang/String;CC)Ljava/lang/String;
    //   527: iconst_0
    //   528: anewarray 105	java/lang/Class
    //   531: invokevirtual 109	java/lang/Class:getMethod	(Ljava/lang/String;[Ljava/lang/Class;)Ljava/lang/reflect/Method;
    //   534: astore_1
    //   535: aload_1
    //   536: aconst_null
    //   537: iconst_0
    //   538: anewarray 111	java/lang/Object
    //   541: invokevirtual 117	java/lang/reflect/Method:invoke	(Ljava/lang/Object;[Ljava/lang/Object;)Ljava/lang/Object;
    //   544: astore_1
    //   545: aload_1
    //   546: checkcast 119	java/lang/Integer
    //   549: invokevirtual 122	java/lang/Integer:intValue	()I
    //   552: putstatic 89	uuuuuu/mmmmmq:b007600760076vvvv0076v	I
    //   555: return
    //   556: astore_1
    //   557: aload_1
    //   558: invokevirtual 184	java/lang/reflect/InvocationTargetException:getCause	()Ljava/lang/Throwable;
    //   561: athrow
    //   562: astore_1
    //   563: aload_1
    //   564: invokevirtual 184	java/lang/reflect/InvocationTargetException:getCause	()Ljava/lang/Throwable;
    //   567: athrow
    //   568: astore_1
    //   569: aload_1
    //   570: invokevirtual 184	java/lang/reflect/InvocationTargetException:getCause	()Ljava/lang/Throwable;
    //   573: athrow
    //   574: astore_1
    //   575: aload_1
    //   576: invokevirtual 184	java/lang/reflect/InvocationTargetException:getCause	()Ljava/lang/Throwable;
    //   579: athrow
    //   580: astore_1
    //   581: aload_1
    //   582: invokevirtual 184	java/lang/reflect/InvocationTargetException:getCause	()Ljava/lang/Throwable;
    //   585: athrow
    //   586: astore_1
    //   587: aload_1
    //   588: invokevirtual 184	java/lang/reflect/InvocationTargetException:getCause	()Ljava/lang/Throwable;
    //   591: athrow
    //   592: astore_1
    //   593: aload_1
    //   594: invokevirtual 184	java/lang/reflect/InvocationTargetException:getCause	()Ljava/lang/Throwable;
    //   597: athrow
    //   598: astore_1
    //   599: aload_1
    //   600: invokevirtual 184	java/lang/reflect/InvocationTargetException:getCause	()Ljava/lang/Throwable;
    //   603: athrow
    //   604: astore_1
    //   605: aload_1
    //   606: invokevirtual 184	java/lang/reflect/InvocationTargetException:getCause	()Ljava/lang/Throwable;
    //   609: athrow
    // Local variable table:
    //   start	length	slot	name	signature
    //   0	610	0	this	mmmmmq
    //   0	610	1	paramDbError	com.db.pwcc.dbmobile.model.error.DbError
    //   1	399	2	i	int
    //   33	367	3	j	int
    //   37	160	4	k	int
    //   159	39	5	m	int
    //   328	163	6	localObject	Object
    // Exception table:
    //   from	to	target	type
    //   59	69	295	java/lang/reflect/InvocationTargetException
    //   26	30	515	java/lang/Exception
    //   535	545	556	java/lang/reflect/InvocationTargetException
    //   330	342	562	java/lang/reflect/InvocationTargetException
    //   377	389	568	java/lang/reflect/InvocationTargetException
    //   431	443	574	java/lang/reflect/InvocationTargetException
    //   478	490	580	java/lang/reflect/InvocationTargetException
    //   123	133	586	java/lang/reflect/InvocationTargetException
    //   181	191	592	java/lang/reflect/InvocationTargetException
    //   234	244	598	java/lang/reflect/InvocationTargetException
    //   272	282	604	java/lang/reflect/InvocationTargetException
  }
  
  /* Error */
  public void buuu007500750075uuu0075(com.db.pwcc.dbmobile.multi_bank_aggregator.model.GetAllMbaInstitutesResponse paramGetAllMbaInstitutesResponse, String paramString)
  {
    // Byte code:
    //   0: ldc 2
    //   2: ldc_w 440
    //   5: sipush 174
    //   8: iconst_5
    //   9: invokestatic 103	xxxxxx/uxxxxx:bb00620062bb0062b0062b0062	(Ljava/lang/String;CC)Ljava/lang/String;
    //   12: iconst_0
    //   13: anewarray 105	java/lang/Class
    //   16: invokevirtual 109	java/lang/Class:getMethod	(Ljava/lang/String;[Ljava/lang/Class;)Ljava/lang/reflect/Method;
    //   19: astore 5
    //   21: aload 5
    //   23: aconst_null
    //   24: iconst_0
    //   25: anewarray 111	java/lang/Object
    //   28: invokevirtual 117	java/lang/reflect/Method:invoke	(Ljava/lang/Object;[Ljava/lang/Object;)Ljava/lang/Object;
    //   31: astore 5
    //   33: aload 5
    //   35: checkcast 119	java/lang/Integer
    //   38: invokevirtual 122	java/lang/Integer:intValue	()I
    //   41: istore_3
    //   42: ldc 2
    //   44: ldc_w 442
    //   47: sipush 221
    //   50: iconst_2
    //   51: invokestatic 103	xxxxxx/uxxxxx:bb00620062bb0062b0062b0062	(Ljava/lang/String;CC)Ljava/lang/String;
    //   54: iconst_0
    //   55: anewarray 105	java/lang/Class
    //   58: invokevirtual 109	java/lang/Class:getMethod	(Ljava/lang/String;[Ljava/lang/Class;)Ljava/lang/reflect/Method;
    //   61: astore 5
    //   63: aload 5
    //   65: aconst_null
    //   66: iconst_0
    //   67: anewarray 111	java/lang/Object
    //   70: invokevirtual 117	java/lang/reflect/Method:invoke	(Ljava/lang/Object;[Ljava/lang/Object;)Ljava/lang/Object;
    //   73: astore 5
    //   75: aload 5
    //   77: checkcast 119	java/lang/Integer
    //   80: invokevirtual 122	java/lang/Integer:intValue	()I
    //   83: istore 4
    //   85: ldc 2
    //   87: ldc_w 444
    //   90: sipush 196
    //   93: sipush 202
    //   96: iconst_3
    //   97: invokestatic 170	xxxxxx/uxxxxx:bbbb0062b0062b0062b0062	(Ljava/lang/String;CCC)Ljava/lang/String;
    //   100: iconst_0
    //   101: anewarray 105	java/lang/Class
    //   104: invokevirtual 109	java/lang/Class:getMethod	(Ljava/lang/String;[Ljava/lang/Class;)Ljava/lang/reflect/Method;
    //   107: astore 5
    //   109: aload 5
    //   111: aconst_null
    //   112: iconst_0
    //   113: anewarray 111	java/lang/Object
    //   116: invokevirtual 117	java/lang/reflect/Method:invoke	(Ljava/lang/Object;[Ljava/lang/Object;)Ljava/lang/Object;
    //   119: astore 5
    //   121: aload 5
    //   123: checkcast 119	java/lang/Integer
    //   126: invokevirtual 122	java/lang/Integer:intValue	()I
    //   129: iload_3
    //   130: iload 4
    //   132: iadd
    //   133: imul
    //   134: getstatic 93	uuuuuu/mmmmmq:bv0076v0076vvv0076v	I
    //   137: irem
    //   138: getstatic 95	uuuuuu/mmmmmq:bvvv0076vvv0076v	I
    //   141: if_icmpeq +51 -> 192
    //   144: bipush 22
    //   146: putstatic 89	uuuuuu/mmmmmq:b007600760076vvvv0076v	I
    //   149: ldc 2
    //   151: ldc_w 446
    //   154: bipush 73
    //   156: iconst_2
    //   157: invokestatic 103	xxxxxx/uxxxxx:bb00620062bb0062b0062b0062	(Ljava/lang/String;CC)Ljava/lang/String;
    //   160: iconst_0
    //   161: anewarray 105	java/lang/Class
    //   164: invokevirtual 109	java/lang/Class:getMethod	(Ljava/lang/String;[Ljava/lang/Class;)Ljava/lang/reflect/Method;
    //   167: astore 5
    //   169: aload 5
    //   171: aconst_null
    //   172: iconst_0
    //   173: anewarray 111	java/lang/Object
    //   176: invokevirtual 117	java/lang/reflect/Method:invoke	(Ljava/lang/Object;[Ljava/lang/Object;)Ljava/lang/Object;
    //   179: astore 5
    //   181: aload 5
    //   183: checkcast 119	java/lang/Integer
    //   186: invokevirtual 122	java/lang/Integer:intValue	()I
    //   189: putstatic 95	uuuuuu/mmmmmq:bvvv0076vvv0076v	I
    //   192: aload_0
    //   193: invokevirtual 396	uuuuuu/mmmmmq:bkk006Bk006Bk006Bk006Bk	()Z
    //   196: ifne +22 -> 218
    //   199: return
    //   200: astore_1
    //   201: aload_1
    //   202: invokevirtual 184	java/lang/reflect/InvocationTargetException:getCause	()Ljava/lang/Throwable;
    //   205: athrow
    //   206: astore_1
    //   207: aload_1
    //   208: invokevirtual 184	java/lang/reflect/InvocationTargetException:getCause	()Ljava/lang/Throwable;
    //   211: athrow
    //   212: astore_1
    //   213: aload_1
    //   214: invokevirtual 184	java/lang/reflect/InvocationTargetException:getCause	()Ljava/lang/Throwable;
    //   217: athrow
    //   218: aload_0
    //   219: iconst_1
    //   220: putfield 45	uuuuuu/mmmmmq:bv0076vvvvv0076v	Z
    //   223: aload_1
    //   224: invokevirtual 451	com/db/pwcc/dbmobile/multi_bank_aggregator/model/GetAllMbaInstitutesResponse:getInstitutes	()Ljava/util/List;
    //   227: astore 5
    //   229: ldc 2
    //   231: ldc_w 453
    //   234: sipush 163
    //   237: iconst_4
    //   238: invokestatic 103	xxxxxx/uxxxxx:bb00620062bb0062b0062b0062	(Ljava/lang/String;CC)Ljava/lang/String;
    //   241: iconst_1
    //   242: anewarray 105	java/lang/Class
    //   245: dup
    //   246: iconst_0
    //   247: ldc 124
    //   249: aastore
    //   250: invokevirtual 133	java/lang/Class:getDeclaredMethod	(Ljava/lang/String;[Ljava/lang/Class;)Ljava/lang/reflect/Method;
    //   253: astore 6
    //   255: aload 6
    //   257: aload_0
    //   258: iconst_1
    //   259: anewarray 111	java/lang/Object
    //   262: dup
    //   263: iconst_0
    //   264: aload 5
    //   266: aastore
    //   267: invokevirtual 117	java/lang/reflect/Method:invoke	(Ljava/lang/Object;[Ljava/lang/Object;)Ljava/lang/Object;
    //   270: pop
    //   271: new 455	uuuuuu/qmqqqm
    //   274: dup
    //   275: aload_1
    //   276: invokevirtual 451	com/db/pwcc/dbmobile/multi_bank_aggregator/model/GetAllMbaInstitutesResponse:getInstitutes	()Ljava/util/List;
    //   279: aload_2
    //   280: aload_0
    //   281: invokespecial 458	uuuuuu/qmqqqm:<init>	(Ljava/util/List;Ljava/lang/String;Luuuuuu/mmqqqm;)V
    //   284: getstatic 464	android/os/AsyncTask:THREAD_POOL_EXECUTOR	Ljava/util/concurrent/Executor;
    //   287: iconst_0
    //   288: anewarray 466	java/lang/Void
    //   291: invokevirtual 470	uuuuuu/qmqqqm:executeOnExecutor	(Ljava/util/concurrent/Executor;[Ljava/lang/Object;)Landroid/os/AsyncTask;
    //   294: pop
    //   295: getstatic 89	uuuuuu/mmmmmq:b007600760076vvvv0076v	I
    //   298: istore_3
    //   299: getstatic 89	uuuuuu/mmmmmq:b007600760076vvvv0076v	I
    //   302: getstatic 91	uuuuuu/mmmmmq:b0076vv0076vvv0076v	I
    //   305: iadd
    //   306: getstatic 89	uuuuuu/mmmmmq:b007600760076vvvv0076v	I
    //   309: imul
    //   310: getstatic 93	uuuuuu/mmmmmq:bv0076v0076vvv0076v	I
    //   313: irem
    //   314: getstatic 95	uuuuuu/mmmmmq:bvvv0076vvv0076v	I
    //   317: if_icmpeq +48 -> 365
    //   320: bipush 24
    //   322: putstatic 89	uuuuuu/mmmmmq:b007600760076vvvv0076v	I
    //   325: ldc 2
    //   327: ldc_w 472
    //   330: sipush 177
    //   333: iconst_5
    //   334: invokestatic 103	xxxxxx/uxxxxx:bb00620062bb0062b0062b0062	(Ljava/lang/String;CC)Ljava/lang/String;
    //   337: iconst_0
    //   338: anewarray 105	java/lang/Class
    //   341: invokevirtual 109	java/lang/Class:getMethod	(Ljava/lang/String;[Ljava/lang/Class;)Ljava/lang/reflect/Method;
    //   344: astore_1
    //   345: aload_1
    //   346: aconst_null
    //   347: iconst_0
    //   348: anewarray 111	java/lang/Object
    //   351: invokevirtual 117	java/lang/reflect/Method:invoke	(Ljava/lang/Object;[Ljava/lang/Object;)Ljava/lang/Object;
    //   354: astore_1
    //   355: aload_1
    //   356: checkcast 119	java/lang/Integer
    //   359: invokevirtual 122	java/lang/Integer:intValue	()I
    //   362: putstatic 95	uuuuuu/mmmmmq:bvvv0076vvv0076v	I
    //   365: ldc 2
    //   367: ldc_w 474
    //   370: sipush 241
    //   373: iconst_5
    //   374: invokestatic 103	xxxxxx/uxxxxx:bb00620062bb0062b0062b0062	(Ljava/lang/String;CC)Ljava/lang/String;
    //   377: iconst_0
    //   378: anewarray 105	java/lang/Class
    //   381: invokevirtual 109	java/lang/Class:getMethod	(Ljava/lang/String;[Ljava/lang/Class;)Ljava/lang/reflect/Method;
    //   384: astore_1
    //   385: aload_1
    //   386: aconst_null
    //   387: iconst_0
    //   388: anewarray 111	java/lang/Object
    //   391: invokevirtual 117	java/lang/reflect/Method:invoke	(Ljava/lang/Object;[Ljava/lang/Object;)Ljava/lang/Object;
    //   394: astore_1
    //   395: aload_1
    //   396: checkcast 119	java/lang/Integer
    //   399: invokevirtual 122	java/lang/Integer:intValue	()I
    //   402: iload_3
    //   403: iadd
    //   404: getstatic 89	uuuuuu/mmmmmq:b007600760076vvvv0076v	I
    //   407: imul
    //   408: getstatic 93	uuuuuu/mmmmmq:bv0076v0076vvv0076v	I
    //   411: irem
    //   412: getstatic 95	uuuuuu/mmmmmq:bvvv0076vvv0076v	I
    //   415: if_icmpeq -216 -> 199
    //   418: ldc 2
    //   420: ldc -84
    //   422: sipush 181
    //   425: iconst_2
    //   426: invokestatic 103	xxxxxx/uxxxxx:bb00620062bb0062b0062b0062	(Ljava/lang/String;CC)Ljava/lang/String;
    //   429: iconst_0
    //   430: anewarray 105	java/lang/Class
    //   433: invokevirtual 109	java/lang/Class:getMethod	(Ljava/lang/String;[Ljava/lang/Class;)Ljava/lang/reflect/Method;
    //   436: astore_1
    //   437: aload_1
    //   438: aconst_null
    //   439: iconst_0
    //   440: anewarray 111	java/lang/Object
    //   443: invokevirtual 117	java/lang/reflect/Method:invoke	(Ljava/lang/Object;[Ljava/lang/Object;)Ljava/lang/Object;
    //   446: astore_1
    //   447: aload_1
    //   448: checkcast 119	java/lang/Integer
    //   451: invokevirtual 122	java/lang/Integer:intValue	()I
    //   454: putstatic 89	uuuuuu/mmmmmq:b007600760076vvvv0076v	I
    //   457: bipush 23
    //   459: putstatic 95	uuuuuu/mmmmmq:bvvv0076vvv0076v	I
    //   462: getstatic 89	uuuuuu/mmmmmq:b007600760076vvvv0076v	I
    //   465: getstatic 91	uuuuuu/mmmmmq:b0076vv0076vvv0076v	I
    //   468: iadd
    //   469: getstatic 89	uuuuuu/mmmmmq:b007600760076vvvv0076v	I
    //   472: imul
    //   473: getstatic 93	uuuuuu/mmmmmq:bv0076v0076vvv0076v	I
    //   476: irem
    //   477: getstatic 95	uuuuuu/mmmmmq:bvvv0076vvv0076v	I
    //   480: if_icmpeq -281 -> 199
    //   483: ldc 2
    //   485: ldc_w 476
    //   488: bipush 79
    //   490: iconst_1
    //   491: invokestatic 103	xxxxxx/uxxxxx:bb00620062bb0062b0062b0062	(Ljava/lang/String;CC)Ljava/lang/String;
    //   494: iconst_0
    //   495: anewarray 105	java/lang/Class
    //   498: invokevirtual 109	java/lang/Class:getMethod	(Ljava/lang/String;[Ljava/lang/Class;)Ljava/lang/reflect/Method;
    //   501: astore_1
    //   502: aload_1
    //   503: aconst_null
    //   504: iconst_0
    //   505: anewarray 111	java/lang/Object
    //   508: invokevirtual 117	java/lang/reflect/Method:invoke	(Ljava/lang/Object;[Ljava/lang/Object;)Ljava/lang/Object;
    //   511: astore_1
    //   512: aload_1
    //   513: checkcast 119	java/lang/Integer
    //   516: invokevirtual 122	java/lang/Integer:intValue	()I
    //   519: putstatic 89	uuuuuu/mmmmmq:b007600760076vvvv0076v	I
    //   522: ldc 2
    //   524: ldc_w 478
    //   527: sipush 208
    //   530: iconst_1
    //   531: invokestatic 103	xxxxxx/uxxxxx:bb00620062bb0062b0062b0062	(Ljava/lang/String;CC)Ljava/lang/String;
    //   534: iconst_0
    //   535: anewarray 105	java/lang/Class
    //   538: invokevirtual 109	java/lang/Class:getMethod	(Ljava/lang/String;[Ljava/lang/Class;)Ljava/lang/reflect/Method;
    //   541: astore_1
    //   542: aload_1
    //   543: aconst_null
    //   544: iconst_0
    //   545: anewarray 111	java/lang/Object
    //   548: invokevirtual 117	java/lang/reflect/Method:invoke	(Ljava/lang/Object;[Ljava/lang/Object;)Ljava/lang/Object;
    //   551: astore_1
    //   552: aload_1
    //   553: checkcast 119	java/lang/Integer
    //   556: invokevirtual 122	java/lang/Integer:intValue	()I
    //   559: putstatic 95	uuuuuu/mmmmmq:bvvv0076vvv0076v	I
    //   562: return
    //   563: astore_1
    //   564: aload_1
    //   565: invokevirtual 184	java/lang/reflect/InvocationTargetException:getCause	()Ljava/lang/Throwable;
    //   568: athrow
    //   569: astore_1
    //   570: aload_1
    //   571: invokevirtual 184	java/lang/reflect/InvocationTargetException:getCause	()Ljava/lang/Throwable;
    //   574: athrow
    //   575: astore_1
    //   576: aload_1
    //   577: invokevirtual 184	java/lang/reflect/InvocationTargetException:getCause	()Ljava/lang/Throwable;
    //   580: athrow
    //   581: astore_1
    //   582: aload_1
    //   583: invokevirtual 184	java/lang/reflect/InvocationTargetException:getCause	()Ljava/lang/Throwable;
    //   586: athrow
    //   587: astore_1
    //   588: aload_1
    //   589: invokevirtual 184	java/lang/reflect/InvocationTargetException:getCause	()Ljava/lang/Throwable;
    //   592: athrow
    //   593: astore_1
    //   594: aload_1
    //   595: invokevirtual 184	java/lang/reflect/InvocationTargetException:getCause	()Ljava/lang/Throwable;
    //   598: athrow
    //   599: astore_1
    //   600: aload_1
    //   601: invokevirtual 184	java/lang/reflect/InvocationTargetException:getCause	()Ljava/lang/Throwable;
    //   604: athrow
    // Local variable table:
    //   start	length	slot	name	signature
    //   0	605	0	this	mmmmmq
    //   0	605	1	paramGetAllMbaInstitutesResponse	com.db.pwcc.dbmobile.multi_bank_aggregator.model.GetAllMbaInstitutesResponse
    //   0	605	2	paramString	String
    //   41	363	3	i	int
    //   83	50	4	j	int
    //   19	246	5	localObject	Object
    //   253	3	6	localMethod	Method
    // Exception table:
    //   from	to	target	type
    //   21	33	200	java/lang/reflect/InvocationTargetException
    //   63	75	206	java/lang/reflect/InvocationTargetException
    //   109	121	212	java/lang/reflect/InvocationTargetException
    //   169	181	563	java/lang/reflect/InvocationTargetException
    //   255	271	569	java/lang/reflect/InvocationTargetException
    //   437	447	575	java/lang/reflect/InvocationTargetException
    //   385	395	581	java/lang/reflect/InvocationTargetException
    //   502	512	587	java/lang/reflect/InvocationTargetException
    //   542	552	593	java/lang/reflect/InvocationTargetException
    //   345	355	599	java/lang/reflect/InvocationTargetException
  }
}
