package uuuuuu;

public class nnnoon
{
  public static int b00660066ff0066ffff = 25;
  public static int b0066f0066f0066ffff = 2;
  public static int bf00660066f0066ffff = 1;
  private static final String bf0066ff0066ffff;
  public static int bff0066f0066ffff;
  
  /* Error */
  static
  {
    // Byte code:
    //   0: getstatic 20	uuuuuu/nnnoon:b00660066ff0066ffff	I
    //   3: istore_0
    //   4: ldc 2
    //   6: ldc 22
    //   8: bipush 73
    //   10: sipush 136
    //   13: iconst_2
    //   14: invokestatic 28	xxxxxx/uxxxxx:bbbb0062b0062b0062b0062	(Ljava/lang/String;CCC)Ljava/lang/String;
    //   17: iconst_0
    //   18: anewarray 30	java/lang/Class
    //   21: invokevirtual 34	java/lang/Class:getMethod	(Ljava/lang/String;[Ljava/lang/Class;)Ljava/lang/reflect/Method;
    //   24: astore_1
    //   25: aload_1
    //   26: aconst_null
    //   27: iconst_0
    //   28: anewarray 4	java/lang/Object
    //   31: invokevirtual 40	java/lang/reflect/Method:invoke	(Ljava/lang/Object;[Ljava/lang/Object;)Ljava/lang/Object;
    //   34: astore_1
    //   35: aload_1
    //   36: checkcast 42	java/lang/Integer
    //   39: invokevirtual 46	java/lang/Integer:intValue	()I
    //   42: iload_0
    //   43: iadd
    //   44: getstatic 20	uuuuuu/nnnoon:b00660066ff0066ffff	I
    //   47: imul
    //   48: getstatic 48	uuuuuu/nnnoon:b0066f0066f0066ffff	I
    //   51: irem
    //   52: getstatic 50	uuuuuu/nnnoon:bff0066f0066ffff	I
    //   55: if_icmpeq +163 -> 218
    //   58: getstatic 20	uuuuuu/nnnoon:b00660066ff0066ffff	I
    //   61: istore_0
    //   62: iload_0
    //   63: getstatic 52	uuuuuu/nnnoon:bf00660066f0066ffff	I
    //   66: iload_0
    //   67: iadd
    //   68: imul
    //   69: getstatic 48	uuuuuu/nnnoon:b0066f0066f0066ffff	I
    //   72: irem
    //   73: tableswitch	default:+19->92, 0:+100->173
    //   92: ldc 2
    //   94: ldc 54
    //   96: sipush 241
    //   99: sipush 180
    //   102: iconst_2
    //   103: invokestatic 28	xxxxxx/uxxxxx:bbbb0062b0062b0062b0062	(Ljava/lang/String;CCC)Ljava/lang/String;
    //   106: iconst_0
    //   107: anewarray 30	java/lang/Class
    //   110: invokevirtual 34	java/lang/Class:getMethod	(Ljava/lang/String;[Ljava/lang/Class;)Ljava/lang/reflect/Method;
    //   113: astore_1
    //   114: aload_1
    //   115: aconst_null
    //   116: iconst_0
    //   117: anewarray 4	java/lang/Object
    //   120: invokevirtual 40	java/lang/reflect/Method:invoke	(Ljava/lang/Object;[Ljava/lang/Object;)Ljava/lang/Object;
    //   123: astore_1
    //   124: aload_1
    //   125: checkcast 42	java/lang/Integer
    //   128: invokevirtual 46	java/lang/Integer:intValue	()I
    //   131: putstatic 20	uuuuuu/nnnoon:b00660066ff0066ffff	I
    //   134: ldc 2
    //   136: ldc 56
    //   138: sipush 170
    //   141: iconst_1
    //   142: invokestatic 60	xxxxxx/uxxxxx:bb00620062bb0062b0062b0062	(Ljava/lang/String;CC)Ljava/lang/String;
    //   145: iconst_0
    //   146: anewarray 30	java/lang/Class
    //   149: invokevirtual 34	java/lang/Class:getMethod	(Ljava/lang/String;[Ljava/lang/Class;)Ljava/lang/reflect/Method;
    //   152: astore_1
    //   153: aload_1
    //   154: aconst_null
    //   155: iconst_0
    //   156: anewarray 4	java/lang/Object
    //   159: invokevirtual 40	java/lang/reflect/Method:invoke	(Ljava/lang/Object;[Ljava/lang/Object;)Ljava/lang/Object;
    //   162: astore_1
    //   163: aload_1
    //   164: checkcast 42	java/lang/Integer
    //   167: invokevirtual 46	java/lang/Integer:intValue	()I
    //   170: putstatic 50	uuuuuu/nnnoon:bff0066f0066ffff	I
    //   173: bipush 62
    //   175: putstatic 20	uuuuuu/nnnoon:b00660066ff0066ffff	I
    //   178: ldc 2
    //   180: ldc 62
    //   182: bipush 41
    //   184: bipush 112
    //   186: iconst_0
    //   187: invokestatic 28	xxxxxx/uxxxxx:bbbb0062b0062b0062b0062	(Ljava/lang/String;CCC)Ljava/lang/String;
    //   190: iconst_0
    //   191: anewarray 30	java/lang/Class
    //   194: invokevirtual 34	java/lang/Class:getMethod	(Ljava/lang/String;[Ljava/lang/Class;)Ljava/lang/reflect/Method;
    //   197: astore_1
    //   198: aload_1
    //   199: aconst_null
    //   200: iconst_0
    //   201: anewarray 4	java/lang/Object
    //   204: invokevirtual 40	java/lang/reflect/Method:invoke	(Ljava/lang/Object;[Ljava/lang/Object;)Ljava/lang/Object;
    //   207: astore_1
    //   208: aload_1
    //   209: checkcast 42	java/lang/Integer
    //   212: invokevirtual 46	java/lang/Integer:intValue	()I
    //   215: putstatic 50	uuuuuu/nnnoon:bff0066f0066ffff	I
    //   218: ldc 2
    //   220: invokevirtual 66	java/lang/Class:getSimpleName	()Ljava/lang/String;
    //   223: putstatic 68	uuuuuu/nnnoon:bf0066ff0066ffff	Ljava/lang/String;
    //   226: return
    //   227: astore_1
    //   228: aload_1
    //   229: invokevirtual 72	java/lang/reflect/InvocationTargetException:getCause	()Ljava/lang/Throwable;
    //   232: athrow
    //   233: astore_1
    //   234: aload_1
    //   235: invokevirtual 72	java/lang/reflect/InvocationTargetException:getCause	()Ljava/lang/Throwable;
    //   238: athrow
    //   239: astore_1
    //   240: aload_1
    //   241: invokevirtual 72	java/lang/reflect/InvocationTargetException:getCause	()Ljava/lang/Throwable;
    //   244: athrow
    //   245: astore_1
    //   246: aload_1
    //   247: invokevirtual 72	java/lang/reflect/InvocationTargetException:getCause	()Ljava/lang/Throwable;
    //   250: athrow
    // Local variable table:
    //   start	length	slot	name	signature
    //   3	66	0	i	int
    //   24	185	1	localObject	Object
    //   227	2	1	localInvocationTargetException1	java.lang.reflect.InvocationTargetException
    //   233	2	1	localInvocationTargetException2	java.lang.reflect.InvocationTargetException
    //   239	2	1	localInvocationTargetException3	java.lang.reflect.InvocationTargetException
    //   245	2	1	localInvocationTargetException4	java.lang.reflect.InvocationTargetException
    // Exception table:
    //   from	to	target	type
    //   198	208	227	java/lang/reflect/InvocationTargetException
    //   25	35	233	java/lang/reflect/InvocationTargetException
    //   114	124	239	java/lang/reflect/InvocationTargetException
    //   153	163	245	java/lang/reflect/InvocationTargetException
  }
  
  public nnnoon() {}
  
  public static int b006B006B006B006Bk006B006Bkk006B()
  {
    return 2;
  }
  
  /* Error */
  public static java.security.interfaces.RSAPublicKey b006B006Bkk006B006B006Bkk006B(String paramString, Integer paramInteger)
  {
    // Byte code:
    //   0: ldc 85
    //   2: ldc 87
    //   4: sipush 172
    //   7: iconst_3
    //   8: invokestatic 60	xxxxxx/uxxxxx:bb00620062bb0062b0062b0062	(Ljava/lang/String;CC)Ljava/lang/String;
    //   11: iconst_3
    //   12: anewarray 30	java/lang/Class
    //   15: dup
    //   16: iconst_0
    //   17: ldc 89
    //   19: aastore
    //   20: dup
    //   21: iconst_1
    //   22: getstatic 95	java/lang/Character:TYPE	Ljava/lang/Class;
    //   25: aastore
    //   26: dup
    //   27: iconst_2
    //   28: getstatic 95	java/lang/Character:TYPE	Ljava/lang/Class;
    //   31: aastore
    //   32: invokevirtual 34	java/lang/Class:getMethod	(Ljava/lang/String;[Ljava/lang/Class;)Ljava/lang/reflect/Method;
    //   35: astore_3
    //   36: aload_3
    //   37: aconst_null
    //   38: iconst_3
    //   39: anewarray 4	java/lang/Object
    //   42: dup
    //   43: iconst_0
    //   44: ldc 96
    //   46: aastore
    //   47: dup
    //   48: iconst_1
    //   49: sipush 132
    //   52: invokestatic 100	java/lang/Character:valueOf	(C)Ljava/lang/Character;
    //   55: aastore
    //   56: dup
    //   57: iconst_2
    //   58: iconst_0
    //   59: invokestatic 100	java/lang/Character:valueOf	(C)Ljava/lang/Character;
    //   62: aastore
    //   63: invokevirtual 40	java/lang/reflect/Method:invoke	(Ljava/lang/Object;[Ljava/lang/Object;)Ljava/lang/Object;
    //   66: astore_3
    //   67: new 102	java/security/spec/RSAPublicKeySpec
    //   70: dup
    //   71: new 104	java/math/BigInteger
    //   74: dup
    //   75: aload_0
    //   76: aload_3
    //   77: checkcast 89	java/lang/String
    //   80: ldc 106
    //   82: invokevirtual 110	java/lang/String:replace	(Ljava/lang/CharSequence;Ljava/lang/CharSequence;)Ljava/lang/String;
    //   85: bipush 16
    //   87: invokespecial 113	java/math/BigInteger:<init>	(Ljava/lang/String;I)V
    //   90: aload_1
    //   91: invokevirtual 46	java/lang/Integer:intValue	()I
    //   94: i2l
    //   95: invokestatic 116	java/math/BigInteger:valueOf	(J)Ljava/math/BigInteger;
    //   98: invokespecial 119	java/security/spec/RSAPublicKeySpec:<init>	(Ljava/math/BigInteger;Ljava/math/BigInteger;)V
    //   101: astore_0
    //   102: ldc 85
    //   104: ldc 121
    //   106: sipush 172
    //   109: sipush 244
    //   112: iconst_3
    //   113: invokestatic 28	xxxxxx/uxxxxx:bbbb0062b0062b0062b0062	(Ljava/lang/String;CCC)Ljava/lang/String;
    //   116: iconst_3
    //   117: anewarray 30	java/lang/Class
    //   120: dup
    //   121: iconst_0
    //   122: ldc 89
    //   124: aastore
    //   125: dup
    //   126: iconst_1
    //   127: getstatic 95	java/lang/Character:TYPE	Ljava/lang/Class;
    //   130: aastore
    //   131: dup
    //   132: iconst_2
    //   133: getstatic 95	java/lang/Character:TYPE	Ljava/lang/Class;
    //   136: aastore
    //   137: invokevirtual 34	java/lang/Class:getMethod	(Ljava/lang/String;[Ljava/lang/Class;)Ljava/lang/reflect/Method;
    //   140: astore_1
    //   141: aload_1
    //   142: aconst_null
    //   143: iconst_3
    //   144: anewarray 4	java/lang/Object
    //   147: dup
    //   148: iconst_0
    //   149: ldc 123
    //   151: aastore
    //   152: dup
    //   153: iconst_1
    //   154: bipush 108
    //   156: invokestatic 100	java/lang/Character:valueOf	(C)Ljava/lang/Character;
    //   159: aastore
    //   160: dup
    //   161: iconst_2
    //   162: iconst_1
    //   163: invokestatic 100	java/lang/Character:valueOf	(C)Ljava/lang/Character;
    //   166: aastore
    //   167: invokevirtual 40	java/lang/reflect/Method:invoke	(Ljava/lang/Object;[Ljava/lang/Object;)Ljava/lang/Object;
    //   170: astore_1
    //   171: aload_1
    //   172: checkcast 89	java/lang/String
    //   175: astore_1
    //   176: aload_1
    //   177: invokestatic 129	java/security/KeyFactory:getInstance	(Ljava/lang/String;)Ljava/security/KeyFactory;
    //   180: aload_0
    //   181: invokevirtual 133	java/security/KeyFactory:generatePublic	(Ljava/security/spec/KeySpec;)Ljava/security/PublicKey;
    //   184: checkcast 135	java/security/interfaces/RSAPublicKey
    //   187: areturn
    //   188: astore_0
    //   189: aload_0
    //   190: invokevirtual 72	java/lang/reflect/InvocationTargetException:getCause	()Ljava/lang/Throwable;
    //   193: athrow
    //   194: astore_0
    //   195: getstatic 68	uuuuuu/nnnoon:bf0066ff0066ffff	Ljava/lang/String;
    //   198: astore_0
    //   199: ldc 85
    //   201: ldc -119
    //   203: sipush 201
    //   206: iconst_5
    //   207: invokestatic 60	xxxxxx/uxxxxx:bb00620062bb0062b0062b0062	(Ljava/lang/String;CC)Ljava/lang/String;
    //   210: iconst_4
    //   211: anewarray 30	java/lang/Class
    //   214: dup
    //   215: iconst_0
    //   216: ldc 89
    //   218: aastore
    //   219: dup
    //   220: iconst_1
    //   221: getstatic 95	java/lang/Character:TYPE	Ljava/lang/Class;
    //   224: aastore
    //   225: dup
    //   226: iconst_2
    //   227: getstatic 95	java/lang/Character:TYPE	Ljava/lang/Class;
    //   230: aastore
    //   231: dup
    //   232: iconst_3
    //   233: getstatic 95	java/lang/Character:TYPE	Ljava/lang/Class;
    //   236: aastore
    //   237: invokevirtual 34	java/lang/Class:getMethod	(Ljava/lang/String;[Ljava/lang/Class;)Ljava/lang/reflect/Method;
    //   240: astore_1
    //   241: aload_1
    //   242: aconst_null
    //   243: iconst_4
    //   244: anewarray 4	java/lang/Object
    //   247: dup
    //   248: iconst_0
    //   249: ldc -117
    //   251: aastore
    //   252: dup
    //   253: iconst_1
    //   254: bipush 122
    //   256: invokestatic 100	java/lang/Character:valueOf	(C)Ljava/lang/Character;
    //   259: aastore
    //   260: dup
    //   261: iconst_2
    //   262: sipush 219
    //   265: invokestatic 100	java/lang/Character:valueOf	(C)Ljava/lang/Character;
    //   268: aastore
    //   269: dup
    //   270: iconst_3
    //   271: iconst_1
    //   272: invokestatic 100	java/lang/Character:valueOf	(C)Ljava/lang/Character;
    //   275: aastore
    //   276: invokevirtual 40	java/lang/reflect/Method:invoke	(Ljava/lang/Object;[Ljava/lang/Object;)Ljava/lang/Object;
    //   279: astore_1
    //   280: aload_0
    //   281: aload_1
    //   282: checkcast 89	java/lang/String
    //   285: invokestatic 145	uuuuuu/rvvvrv:bqqqq00710071q0071q0071	(Ljava/lang/String;Ljava/lang/String;)V
    //   288: getstatic 20	uuuuuu/nnnoon:b00660066ff0066ffff	I
    //   291: istore_2
    //   292: iload_2
    //   293: getstatic 52	uuuuuu/nnnoon:bf00660066f0066ffff	I
    //   296: iload_2
    //   297: iadd
    //   298: imul
    //   299: getstatic 48	uuuuuu/nnnoon:b0066f0066f0066ffff	I
    //   302: irem
    //   303: tableswitch	default:+17->320, 0:+94->397
    //   320: ldc 2
    //   322: ldc -109
    //   324: bipush 125
    //   326: iconst_2
    //   327: invokestatic 60	xxxxxx/uxxxxx:bb00620062bb0062b0062b0062	(Ljava/lang/String;CC)Ljava/lang/String;
    //   330: iconst_0
    //   331: anewarray 30	java/lang/Class
    //   334: invokevirtual 34	java/lang/Class:getMethod	(Ljava/lang/String;[Ljava/lang/Class;)Ljava/lang/reflect/Method;
    //   337: astore_0
    //   338: aload_0
    //   339: aconst_null
    //   340: iconst_0
    //   341: anewarray 4	java/lang/Object
    //   344: invokevirtual 40	java/lang/reflect/Method:invoke	(Ljava/lang/Object;[Ljava/lang/Object;)Ljava/lang/Object;
    //   347: astore_0
    //   348: aload_0
    //   349: checkcast 42	java/lang/Integer
    //   352: invokevirtual 46	java/lang/Integer:intValue	()I
    //   355: putstatic 20	uuuuuu/nnnoon:b00660066ff0066ffff	I
    //   358: ldc 2
    //   360: ldc -107
    //   362: sipush 138
    //   365: iconst_4
    //   366: invokestatic 60	xxxxxx/uxxxxx:bb00620062bb0062b0062b0062	(Ljava/lang/String;CC)Ljava/lang/String;
    //   369: iconst_0
    //   370: anewarray 30	java/lang/Class
    //   373: invokevirtual 34	java/lang/Class:getMethod	(Ljava/lang/String;[Ljava/lang/Class;)Ljava/lang/reflect/Method;
    //   376: astore_0
    //   377: aload_0
    //   378: aconst_null
    //   379: iconst_0
    //   380: anewarray 4	java/lang/Object
    //   383: invokevirtual 40	java/lang/reflect/Method:invoke	(Ljava/lang/Object;[Ljava/lang/Object;)Ljava/lang/Object;
    //   386: astore_0
    //   387: aload_0
    //   388: checkcast 42	java/lang/Integer
    //   391: invokevirtual 46	java/lang/Integer:intValue	()I
    //   394: putstatic 50	uuuuuu/nnnoon:bff0066f0066ffff	I
    //   397: aconst_null
    //   398: areturn
    //   399: astore_0
    //   400: aload_0
    //   401: invokevirtual 72	java/lang/reflect/InvocationTargetException:getCause	()Ljava/lang/Throwable;
    //   404: athrow
    //   405: astore_0
    //   406: aload_0
    //   407: invokevirtual 72	java/lang/reflect/InvocationTargetException:getCause	()Ljava/lang/Throwable;
    //   410: athrow
    //   411: astore_0
    //   412: aload_0
    //   413: invokevirtual 72	java/lang/reflect/InvocationTargetException:getCause	()Ljava/lang/Throwable;
    //   416: athrow
    //   417: astore_0
    //   418: aload_0
    //   419: invokevirtual 72	java/lang/reflect/InvocationTargetException:getCause	()Ljava/lang/Throwable;
    //   422: athrow
    //   423: astore_0
    //   424: getstatic 68	uuuuuu/nnnoon:bf0066ff0066ffff	Ljava/lang/String;
    //   427: astore_0
    //   428: ldc 85
    //   430: ldc -105
    //   432: bipush 116
    //   434: sipush 242
    //   437: iconst_1
    //   438: invokestatic 28	xxxxxx/uxxxxx:bbbb0062b0062b0062b0062	(Ljava/lang/String;CCC)Ljava/lang/String;
    //   441: iconst_3
    //   442: anewarray 30	java/lang/Class
    //   445: dup
    //   446: iconst_0
    //   447: ldc 89
    //   449: aastore
    //   450: dup
    //   451: iconst_1
    //   452: getstatic 95	java/lang/Character:TYPE	Ljava/lang/Class;
    //   455: aastore
    //   456: dup
    //   457: iconst_2
    //   458: getstatic 95	java/lang/Character:TYPE	Ljava/lang/Class;
    //   461: aastore
    //   462: invokevirtual 34	java/lang/Class:getMethod	(Ljava/lang/String;[Ljava/lang/Class;)Ljava/lang/reflect/Method;
    //   465: astore_1
    //   466: aload_1
    //   467: aconst_null
    //   468: iconst_3
    //   469: anewarray 4	java/lang/Object
    //   472: dup
    //   473: iconst_0
    //   474: ldc -103
    //   476: aastore
    //   477: dup
    //   478: iconst_1
    //   479: sipush 208
    //   482: invokestatic 100	java/lang/Character:valueOf	(C)Ljava/lang/Character;
    //   485: aastore
    //   486: dup
    //   487: iconst_2
    //   488: iconst_4
    //   489: invokestatic 100	java/lang/Character:valueOf	(C)Ljava/lang/Character;
    //   492: aastore
    //   493: invokevirtual 40	java/lang/reflect/Method:invoke	(Ljava/lang/Object;[Ljava/lang/Object;)Ljava/lang/Object;
    //   496: astore_1
    //   497: aload_0
    //   498: aload_1
    //   499: checkcast 89	java/lang/String
    //   502: invokestatic 145	uuuuuu/rvvvrv:bqqqq00710071q0071q0071	(Ljava/lang/String;Ljava/lang/String;)V
    //   505: getstatic 20	uuuuuu/nnnoon:b00660066ff0066ffff	I
    //   508: getstatic 52	uuuuuu/nnnoon:bf00660066f0066ffff	I
    //   511: iadd
    //   512: getstatic 20	uuuuuu/nnnoon:b00660066ff0066ffff	I
    //   515: imul
    //   516: getstatic 48	uuuuuu/nnnoon:b0066f0066f0066ffff	I
    //   519: irem
    //   520: getstatic 50	uuuuuu/nnnoon:bff0066f0066ffff	I
    //   523: if_icmpeq -235 -> 288
    //   526: bipush 8
    //   528: putstatic 20	uuuuuu/nnnoon:b00660066ff0066ffff	I
    //   531: bipush 49
    //   533: putstatic 50	uuuuuu/nnnoon:bff0066f0066ffff	I
    //   536: goto -248 -> 288
    //   539: astore_0
    //   540: aload_0
    //   541: invokevirtual 72	java/lang/reflect/InvocationTargetException:getCause	()Ljava/lang/Throwable;
    //   544: athrow
    // Local variable table:
    //   start	length	slot	name	signature
    //   0	545	0	paramString	String
    //   0	545	1	paramInteger	Integer
    //   291	8	2	i	int
    //   35	42	3	localObject	Object
    // Exception table:
    //   from	to	target	type
    //   141	171	188	java/lang/reflect/InvocationTargetException
    //   141	171	194	java/security/NoSuchAlgorithmException
    //   176	188	194	java/security/NoSuchAlgorithmException
    //   189	194	194	java/security/NoSuchAlgorithmException
    //   241	280	399	java/lang/reflect/InvocationTargetException
    //   36	67	405	java/lang/reflect/InvocationTargetException
    //   338	348	411	java/lang/reflect/InvocationTargetException
    //   377	387	417	java/lang/reflect/InvocationTargetException
    //   141	171	423	java/security/spec/InvalidKeySpecException
    //   176	188	423	java/security/spec/InvalidKeySpecException
    //   189	194	423	java/security/spec/InvalidKeySpecException
    //   466	497	539	java/lang/reflect/InvocationTargetException
  }
  
  public static int b006Bkkk006B006B006Bkk006B()
  {
    return 62;
  }
  
  /* Error */
  public static String bk006Bkk006B006B006Bkk006B(String paramString, java.security.interfaces.RSAPublicKey paramRSAPublicKey)
  {
    // Byte code:
    //   0: new 160	org/spongycastle/jce/provider/BouncyCastleProvider
    //   3: dup
    //   4: invokespecial 161	org/spongycastle/jce/provider/BouncyCastleProvider:<init>	()V
    //   7: iconst_1
    //   8: invokestatic 167	java/security/Security:insertProviderAt	(Ljava/security/Provider;I)I
    //   11: pop
    //   12: new 169	com/nimbusds/jose/JWEObject
    //   15: dup
    //   16: new 171	com/nimbusds/jose/JWEHeader
    //   19: dup
    //   20: getstatic 177	com/nimbusds/jose/JWEAlgorithm:RSA_OAEP	Lcom/nimbusds/jose/JWEAlgorithm;
    //   23: getstatic 183	com/nimbusds/jose/EncryptionMethod:A256GCM	Lcom/nimbusds/jose/EncryptionMethod;
    //   26: invokespecial 186	com/nimbusds/jose/JWEHeader:<init>	(Lcom/nimbusds/jose/JWEAlgorithm;Lcom/nimbusds/jose/EncryptionMethod;)V
    //   29: new 188	com/nimbusds/jose/Payload
    //   32: dup
    //   33: aload_0
    //   34: invokespecial 191	com/nimbusds/jose/Payload:<init>	(Ljava/lang/String;)V
    //   37: invokespecial 194	com/nimbusds/jose/JWEObject:<init>	(Lcom/nimbusds/jose/JWEHeader;Lcom/nimbusds/jose/Payload;)V
    //   40: astore_0
    //   41: new 196	com/nimbusds/jose/crypto/RSAEncrypter
    //   44: dup
    //   45: aload_1
    //   46: invokespecial 199	com/nimbusds/jose/crypto/RSAEncrypter:<init>	(Ljava/security/interfaces/RSAPublicKey;)V
    //   49: astore_1
    //   50: aload_0
    //   51: aload_1
    //   52: invokevirtual 203	com/nimbusds/jose/JWEObject:encrypt	(Lcom/nimbusds/jose/JWEEncrypter;)V
    //   55: aload_0
    //   56: invokevirtual 206	com/nimbusds/jose/JWEObject:serialize	()Ljava/lang/String;
    //   59: astore_0
    //   60: aload_0
    //   61: areturn
    //   62: astore_0
    //   63: getstatic 68	uuuuuu/nnnoon:bf0066ff0066ffff	Ljava/lang/String;
    //   66: astore_0
    //   67: getstatic 20	uuuuuu/nnnoon:b00660066ff0066ffff	I
    //   70: istore_2
    //   71: getstatic 52	uuuuuu/nnnoon:bf00660066f0066ffff	I
    //   74: istore_3
    //   75: getstatic 20	uuuuuu/nnnoon:b00660066ff0066ffff	I
    //   78: istore 4
    //   80: ldc 2
    //   82: ldc -48
    //   84: sipush 230
    //   87: sipush 133
    //   90: iconst_0
    //   91: invokestatic 28	xxxxxx/uxxxxx:bbbb0062b0062b0062b0062	(Ljava/lang/String;CCC)Ljava/lang/String;
    //   94: iconst_0
    //   95: anewarray 30	java/lang/Class
    //   98: invokevirtual 34	java/lang/Class:getMethod	(Ljava/lang/String;[Ljava/lang/Class;)Ljava/lang/reflect/Method;
    //   101: astore_1
    //   102: aload_1
    //   103: aconst_null
    //   104: iconst_0
    //   105: anewarray 4	java/lang/Object
    //   108: invokevirtual 40	java/lang/reflect/Method:invoke	(Ljava/lang/Object;[Ljava/lang/Object;)Ljava/lang/Object;
    //   111: astore_1
    //   112: iload 4
    //   114: iload_2
    //   115: iload_3
    //   116: iadd
    //   117: imul
    //   118: aload_1
    //   119: checkcast 42	java/lang/Integer
    //   122: invokevirtual 46	java/lang/Integer:intValue	()I
    //   125: irem
    //   126: getstatic 50	uuuuuu/nnnoon:bff0066f0066ffff	I
    //   129: if_icmpeq +79 -> 208
    //   132: ldc 2
    //   134: ldc -46
    //   136: bipush 111
    //   138: iconst_1
    //   139: invokestatic 60	xxxxxx/uxxxxx:bb00620062bb0062b0062b0062	(Ljava/lang/String;CC)Ljava/lang/String;
    //   142: iconst_0
    //   143: anewarray 30	java/lang/Class
    //   146: invokevirtual 34	java/lang/Class:getMethod	(Ljava/lang/String;[Ljava/lang/Class;)Ljava/lang/reflect/Method;
    //   149: astore_1
    //   150: aload_1
    //   151: aconst_null
    //   152: iconst_0
    //   153: anewarray 4	java/lang/Object
    //   156: invokevirtual 40	java/lang/reflect/Method:invoke	(Ljava/lang/Object;[Ljava/lang/Object;)Ljava/lang/Object;
    //   159: astore_1
    //   160: aload_1
    //   161: checkcast 42	java/lang/Integer
    //   164: invokevirtual 46	java/lang/Integer:intValue	()I
    //   167: putstatic 20	uuuuuu/nnnoon:b00660066ff0066ffff	I
    //   170: ldc 2
    //   172: ldc -44
    //   174: bipush 119
    //   176: iconst_5
    //   177: invokestatic 60	xxxxxx/uxxxxx:bb00620062bb0062b0062b0062	(Ljava/lang/String;CC)Ljava/lang/String;
    //   180: iconst_0
    //   181: anewarray 30	java/lang/Class
    //   184: invokevirtual 34	java/lang/Class:getMethod	(Ljava/lang/String;[Ljava/lang/Class;)Ljava/lang/reflect/Method;
    //   187: astore_1
    //   188: aload_1
    //   189: aconst_null
    //   190: iconst_0
    //   191: anewarray 4	java/lang/Object
    //   194: invokevirtual 40	java/lang/reflect/Method:invoke	(Ljava/lang/Object;[Ljava/lang/Object;)Ljava/lang/Object;
    //   197: astore_1
    //   198: aload_1
    //   199: checkcast 42	java/lang/Integer
    //   202: invokevirtual 46	java/lang/Integer:intValue	()I
    //   205: putstatic 50	uuuuuu/nnnoon:bff0066f0066ffff	I
    //   208: ldc 85
    //   210: ldc -42
    //   212: bipush 46
    //   214: sipush 233
    //   217: iconst_3
    //   218: invokestatic 28	xxxxxx/uxxxxx:bbbb0062b0062b0062b0062	(Ljava/lang/String;CCC)Ljava/lang/String;
    //   221: iconst_4
    //   222: anewarray 30	java/lang/Class
    //   225: dup
    //   226: iconst_0
    //   227: ldc 89
    //   229: aastore
    //   230: dup
    //   231: iconst_1
    //   232: getstatic 95	java/lang/Character:TYPE	Ljava/lang/Class;
    //   235: aastore
    //   236: dup
    //   237: iconst_2
    //   238: getstatic 95	java/lang/Character:TYPE	Ljava/lang/Class;
    //   241: aastore
    //   242: dup
    //   243: iconst_3
    //   244: getstatic 95	java/lang/Character:TYPE	Ljava/lang/Class;
    //   247: aastore
    //   248: invokevirtual 34	java/lang/Class:getMethod	(Ljava/lang/String;[Ljava/lang/Class;)Ljava/lang/reflect/Method;
    //   251: astore_1
    //   252: aload_1
    //   253: aconst_null
    //   254: iconst_4
    //   255: anewarray 4	java/lang/Object
    //   258: dup
    //   259: iconst_0
    //   260: ldc -40
    //   262: aastore
    //   263: dup
    //   264: iconst_1
    //   265: sipush 147
    //   268: invokestatic 100	java/lang/Character:valueOf	(C)Ljava/lang/Character;
    //   271: aastore
    //   272: dup
    //   273: iconst_2
    //   274: sipush 207
    //   277: invokestatic 100	java/lang/Character:valueOf	(C)Ljava/lang/Character;
    //   280: aastore
    //   281: dup
    //   282: iconst_3
    //   283: iconst_0
    //   284: invokestatic 100	java/lang/Character:valueOf	(C)Ljava/lang/Character;
    //   287: aastore
    //   288: invokevirtual 40	java/lang/reflect/Method:invoke	(Ljava/lang/Object;[Ljava/lang/Object;)Ljava/lang/Object;
    //   291: astore_1
    //   292: aload_1
    //   293: checkcast 89	java/lang/String
    //   296: astore_1
    //   297: getstatic 20	uuuuuu/nnnoon:b00660066ff0066ffff	I
    //   300: getstatic 52	uuuuuu/nnnoon:bf00660066f0066ffff	I
    //   303: iadd
    //   304: getstatic 20	uuuuuu/nnnoon:b00660066ff0066ffff	I
    //   307: imul
    //   308: getstatic 48	uuuuuu/nnnoon:b0066f0066f0066ffff	I
    //   311: irem
    //   312: getstatic 50	uuuuuu/nnnoon:bff0066f0066ffff	I
    //   315: if_icmpeq +88 -> 403
    //   318: ldc 2
    //   320: ldc -38
    //   322: sipush 200
    //   325: iconst_3
    //   326: invokestatic 60	xxxxxx/uxxxxx:bb00620062bb0062b0062b0062	(Ljava/lang/String;CC)Ljava/lang/String;
    //   329: iconst_0
    //   330: anewarray 30	java/lang/Class
    //   333: invokevirtual 34	java/lang/Class:getMethod	(Ljava/lang/String;[Ljava/lang/Class;)Ljava/lang/reflect/Method;
    //   336: astore 5
    //   338: aload 5
    //   340: aconst_null
    //   341: iconst_0
    //   342: anewarray 4	java/lang/Object
    //   345: invokevirtual 40	java/lang/reflect/Method:invoke	(Ljava/lang/Object;[Ljava/lang/Object;)Ljava/lang/Object;
    //   348: astore 5
    //   350: aload 5
    //   352: checkcast 42	java/lang/Integer
    //   355: invokevirtual 46	java/lang/Integer:intValue	()I
    //   358: putstatic 20	uuuuuu/nnnoon:b00660066ff0066ffff	I
    //   361: ldc 2
    //   363: ldc -36
    //   365: bipush 77
    //   367: iconst_3
    //   368: invokestatic 60	xxxxxx/uxxxxx:bb00620062bb0062b0062b0062	(Ljava/lang/String;CC)Ljava/lang/String;
    //   371: iconst_0
    //   372: anewarray 30	java/lang/Class
    //   375: invokevirtual 34	java/lang/Class:getMethod	(Ljava/lang/String;[Ljava/lang/Class;)Ljava/lang/reflect/Method;
    //   378: astore 5
    //   380: aload 5
    //   382: aconst_null
    //   383: iconst_0
    //   384: anewarray 4	java/lang/Object
    //   387: invokevirtual 40	java/lang/reflect/Method:invoke	(Ljava/lang/Object;[Ljava/lang/Object;)Ljava/lang/Object;
    //   390: astore 5
    //   392: aload 5
    //   394: checkcast 42	java/lang/Integer
    //   397: invokevirtual 46	java/lang/Integer:intValue	()I
    //   400: putstatic 50	uuuuuu/nnnoon:bff0066f0066ffff	I
    //   403: aload_0
    //   404: aload_1
    //   405: invokestatic 145	uuuuuu/rvvvrv:bqqqq00710071q0071q0071	(Ljava/lang/String;Ljava/lang/String;)V
    //   408: aconst_null
    //   409: areturn
    //   410: astore_0
    //   411: aload_0
    //   412: invokevirtual 72	java/lang/reflect/InvocationTargetException:getCause	()Ljava/lang/Throwable;
    //   415: athrow
    //   416: astore_0
    //   417: aload_0
    //   418: invokevirtual 72	java/lang/reflect/InvocationTargetException:getCause	()Ljava/lang/Throwable;
    //   421: athrow
    //   422: astore_0
    //   423: aload_0
    //   424: invokevirtual 72	java/lang/reflect/InvocationTargetException:getCause	()Ljava/lang/Throwable;
    //   427: athrow
    //   428: astore_0
    //   429: aload_0
    //   430: invokevirtual 72	java/lang/reflect/InvocationTargetException:getCause	()Ljava/lang/Throwable;
    //   433: athrow
    //   434: astore_0
    //   435: aload_0
    //   436: invokevirtual 72	java/lang/reflect/InvocationTargetException:getCause	()Ljava/lang/Throwable;
    //   439: athrow
    //   440: astore_0
    //   441: aload_0
    //   442: invokevirtual 72	java/lang/reflect/InvocationTargetException:getCause	()Ljava/lang/Throwable;
    //   445: athrow
    // Local variable table:
    //   start	length	slot	name	signature
    //   0	446	0	paramString	String
    //   0	446	1	paramRSAPublicKey	java.security.interfaces.RSAPublicKey
    //   70	47	2	i	int
    //   74	43	3	j	int
    //   78	40	4	k	int
    //   336	57	5	localObject	Object
    // Exception table:
    //   from	to	target	type
    //   50	60	62	com/nimbusds/jose/JOSEException
    //   102	112	410	java/lang/reflect/InvocationTargetException
    //   338	350	416	java/lang/reflect/InvocationTargetException
    //   252	292	422	java/lang/reflect/InvocationTargetException
    //   380	392	428	java/lang/reflect/InvocationTargetException
    //   150	160	434	java/lang/reflect/InvocationTargetException
    //   188	198	440	java/lang/reflect/InvocationTargetException
  }
  
  public static int bkkkk006B006B006Bkk006B()
  {
    return 1;
  }
}
