package uuuuuu;

import com.db.pwcc.dbmobile.secure.preferences.SharedPreferencesHelper;
import rx.subscriptions.CompositeSubscription;

public class nnnono
  extends ssssst<oonono.onnono>
  implements oonono.nonono
{
  public static int b006E006En006Enn006E006E006E = 2;
  private static final String b006E006Ennnn006E006E006E;
  public static int b006Enn006Enn006E006E006E = 0;
  public static int bn006En006Enn006E006E006E = 1;
  public static int bnnn006Enn006E006E006E = 24;
  private CompositeSubscription b006E006E006Ennn006E006E006E = new CompositeSubscription();
  private nnoono b006En006Ennn006E006E006E;
  private SharedPreferencesHelper bn006E006Ennn006E006E006E;
  private sssttt bnn006Ennn006E006E006E;
  
  /* Error */
  static
  {
    // Byte code:
    //   0: ldc 2
    //   2: invokevirtual 38	java/lang/Class:getSimpleName	()Ljava/lang/String;
    //   5: astore 4
    //   7: getstatic 40	uuuuuu/nnnono:bnnn006Enn006E006E006E	I
    //   10: istore_0
    //   11: getstatic 42	uuuuuu/nnnono:bn006En006Enn006E006E006E	I
    //   14: istore_1
    //   15: getstatic 40	uuuuuu/nnnono:bnnn006Enn006E006E006E	I
    //   18: istore_2
    //   19: ldc 2
    //   21: ldc 44
    //   23: sipush 226
    //   26: iconst_4
    //   27: invokestatic 50	xxxxxx/uxxxxx:bb00620062bb0062b0062b0062	(Ljava/lang/String;CC)Ljava/lang/String;
    //   30: iconst_0
    //   31: anewarray 34	java/lang/Class
    //   34: invokevirtual 54	java/lang/Class:getMethod	(Ljava/lang/String;[Ljava/lang/Class;)Ljava/lang/reflect/Method;
    //   37: astore 5
    //   39: aload 5
    //   41: aconst_null
    //   42: iconst_0
    //   43: anewarray 56	java/lang/Object
    //   46: invokevirtual 62	java/lang/reflect/Method:invoke	(Ljava/lang/Object;[Ljava/lang/Object;)Ljava/lang/Object;
    //   49: astore 5
    //   51: iload_2
    //   52: iload_0
    //   53: iload_1
    //   54: iadd
    //   55: imul
    //   56: aload 5
    //   58: checkcast 64	java/lang/Integer
    //   61: invokevirtual 68	java/lang/Integer:intValue	()I
    //   64: irem
    //   65: getstatic 70	uuuuuu/nnnono:b006Enn006Enn006E006E006E	I
    //   68: if_icmpeq +447 -> 515
    //   71: getstatic 40	uuuuuu/nnnono:bnnn006Enn006E006E006E	I
    //   74: istore_0
    //   75: ldc 2
    //   77: ldc 72
    //   79: sipush 144
    //   82: bipush 29
    //   84: iconst_0
    //   85: invokestatic 76	xxxxxx/uxxxxx:bbbb0062b0062b0062b0062	(Ljava/lang/String;CCC)Ljava/lang/String;
    //   88: iconst_0
    //   89: anewarray 34	java/lang/Class
    //   92: invokevirtual 54	java/lang/Class:getMethod	(Ljava/lang/String;[Ljava/lang/Class;)Ljava/lang/reflect/Method;
    //   95: astore 5
    //   97: aload 5
    //   99: aconst_null
    //   100: iconst_0
    //   101: anewarray 56	java/lang/Object
    //   104: invokevirtual 62	java/lang/reflect/Method:invoke	(Ljava/lang/Object;[Ljava/lang/Object;)Ljava/lang/Object;
    //   107: astore 5
    //   109: aload 5
    //   111: checkcast 64	java/lang/Integer
    //   114: invokevirtual 68	java/lang/Integer:intValue	()I
    //   117: istore_1
    //   118: getstatic 40	uuuuuu/nnnono:bnnn006Enn006E006E006E	I
    //   121: istore_2
    //   122: getstatic 78	uuuuuu/nnnono:b006E006En006Enn006E006E006E	I
    //   125: istore_3
    //   126: ldc 2
    //   128: ldc 80
    //   130: sipush 251
    //   133: iconst_1
    //   134: invokestatic 50	xxxxxx/uxxxxx:bb00620062bb0062b0062b0062	(Ljava/lang/String;CC)Ljava/lang/String;
    //   137: iconst_0
    //   138: anewarray 34	java/lang/Class
    //   141: invokevirtual 54	java/lang/Class:getMethod	(Ljava/lang/String;[Ljava/lang/Class;)Ljava/lang/reflect/Method;
    //   144: astore 5
    //   146: aload 5
    //   148: aconst_null
    //   149: iconst_0
    //   150: anewarray 56	java/lang/Object
    //   153: invokevirtual 62	java/lang/reflect/Method:invoke	(Ljava/lang/Object;[Ljava/lang/Object;)Ljava/lang/Object;
    //   156: astore 5
    //   158: iload_1
    //   159: iload_0
    //   160: iadd
    //   161: iload_2
    //   162: imul
    //   163: iload_3
    //   164: irem
    //   165: aload 5
    //   167: checkcast 64	java/lang/Integer
    //   170: invokevirtual 68	java/lang/Integer:intValue	()I
    //   173: if_icmpeq +89 -> 262
    //   176: ldc 2
    //   178: ldc 82
    //   180: sipush 140
    //   183: iconst_1
    //   184: invokestatic 50	xxxxxx/uxxxxx:bb00620062bb0062b0062b0062	(Ljava/lang/String;CC)Ljava/lang/String;
    //   187: iconst_0
    //   188: anewarray 34	java/lang/Class
    //   191: invokevirtual 54	java/lang/Class:getMethod	(Ljava/lang/String;[Ljava/lang/Class;)Ljava/lang/reflect/Method;
    //   194: astore 5
    //   196: aload 5
    //   198: aconst_null
    //   199: iconst_0
    //   200: anewarray 56	java/lang/Object
    //   203: invokevirtual 62	java/lang/reflect/Method:invoke	(Ljava/lang/Object;[Ljava/lang/Object;)Ljava/lang/Object;
    //   206: astore 5
    //   208: aload 5
    //   210: checkcast 64	java/lang/Integer
    //   213: invokevirtual 68	java/lang/Integer:intValue	()I
    //   216: putstatic 40	uuuuuu/nnnono:bnnn006Enn006E006E006E	I
    //   219: ldc 2
    //   221: ldc 84
    //   223: sipush 245
    //   226: iconst_5
    //   227: invokestatic 50	xxxxxx/uxxxxx:bb00620062bb0062b0062b0062	(Ljava/lang/String;CC)Ljava/lang/String;
    //   230: iconst_0
    //   231: anewarray 34	java/lang/Class
    //   234: invokevirtual 54	java/lang/Class:getMethod	(Ljava/lang/String;[Ljava/lang/Class;)Ljava/lang/reflect/Method;
    //   237: astore 5
    //   239: aload 5
    //   241: aconst_null
    //   242: iconst_0
    //   243: anewarray 56	java/lang/Object
    //   246: invokevirtual 62	java/lang/reflect/Method:invoke	(Ljava/lang/Object;[Ljava/lang/Object;)Ljava/lang/Object;
    //   249: astore 5
    //   251: aload 5
    //   253: checkcast 64	java/lang/Integer
    //   256: invokevirtual 68	java/lang/Integer:intValue	()I
    //   259: putstatic 70	uuuuuu/nnnono:b006Enn006Enn006E006E006E	I
    //   262: getstatic 40	uuuuuu/nnnono:bnnn006Enn006E006E006E	I
    //   265: istore_0
    //   266: iload_0
    //   267: getstatic 42	uuuuuu/nnnono:bn006En006Enn006E006E006E	I
    //   270: iload_0
    //   271: iadd
    //   272: imul
    //   273: getstatic 78	uuuuuu/nnnono:b006E006En006Enn006E006E006E	I
    //   276: irem
    //   277: tableswitch	default:+19->296, 0:+228->505
    //   296: ldc 2
    //   298: ldc 86
    //   300: bipush 121
    //   302: iconst_4
    //   303: invokestatic 50	xxxxxx/uxxxxx:bb00620062bb0062b0062b0062	(Ljava/lang/String;CC)Ljava/lang/String;
    //   306: iconst_0
    //   307: anewarray 34	java/lang/Class
    //   310: invokevirtual 54	java/lang/Class:getMethod	(Ljava/lang/String;[Ljava/lang/Class;)Ljava/lang/reflect/Method;
    //   313: astore 5
    //   315: aload 5
    //   317: aconst_null
    //   318: iconst_0
    //   319: anewarray 56	java/lang/Object
    //   322: invokevirtual 62	java/lang/reflect/Method:invoke	(Ljava/lang/Object;[Ljava/lang/Object;)Ljava/lang/Object;
    //   325: astore 5
    //   327: aload 5
    //   329: checkcast 64	java/lang/Integer
    //   332: invokevirtual 68	java/lang/Integer:intValue	()I
    //   335: putstatic 40	uuuuuu/nnnono:bnnn006Enn006E006E006E	I
    //   338: ldc 2
    //   340: ldc 88
    //   342: bipush 19
    //   344: sipush 221
    //   347: iconst_3
    //   348: invokestatic 76	xxxxxx/uxxxxx:bbbb0062b0062b0062b0062	(Ljava/lang/String;CCC)Ljava/lang/String;
    //   351: iconst_0
    //   352: anewarray 34	java/lang/Class
    //   355: invokevirtual 54	java/lang/Class:getMethod	(Ljava/lang/String;[Ljava/lang/Class;)Ljava/lang/reflect/Method;
    //   358: astore 5
    //   360: aload 5
    //   362: aconst_null
    //   363: iconst_0
    //   364: anewarray 56	java/lang/Object
    //   367: invokevirtual 62	java/lang/reflect/Method:invoke	(Ljava/lang/Object;[Ljava/lang/Object;)Ljava/lang/Object;
    //   370: astore 5
    //   372: aload 5
    //   374: checkcast 64	java/lang/Integer
    //   377: invokevirtual 68	java/lang/Integer:intValue	()I
    //   380: istore_0
    //   381: getstatic 40	uuuuuu/nnnono:bnnn006Enn006E006E006E	I
    //   384: istore_1
    //   385: iload_1
    //   386: getstatic 42	uuuuuu/nnnono:bn006En006Enn006E006E006E	I
    //   389: iload_1
    //   390: iadd
    //   391: imul
    //   392: getstatic 78	uuuuuu/nnnono:b006E006En006Enn006E006E006E	I
    //   395: irem
    //   396: tableswitch	default:+20->416, 0:+105->501
    //   416: ldc 2
    //   418: ldc 90
    //   420: bipush 88
    //   422: iconst_1
    //   423: invokestatic 50	xxxxxx/uxxxxx:bb00620062bb0062b0062b0062	(Ljava/lang/String;CC)Ljava/lang/String;
    //   426: iconst_0
    //   427: anewarray 34	java/lang/Class
    //   430: invokevirtual 54	java/lang/Class:getMethod	(Ljava/lang/String;[Ljava/lang/Class;)Ljava/lang/reflect/Method;
    //   433: astore 5
    //   435: aload 5
    //   437: aconst_null
    //   438: iconst_0
    //   439: anewarray 56	java/lang/Object
    //   442: invokevirtual 62	java/lang/reflect/Method:invoke	(Ljava/lang/Object;[Ljava/lang/Object;)Ljava/lang/Object;
    //   445: astore 5
    //   447: aload 5
    //   449: checkcast 64	java/lang/Integer
    //   452: invokevirtual 68	java/lang/Integer:intValue	()I
    //   455: putstatic 40	uuuuuu/nnnono:bnnn006Enn006E006E006E	I
    //   458: ldc 2
    //   460: ldc 92
    //   462: sipush 158
    //   465: iconst_4
    //   466: invokestatic 50	xxxxxx/uxxxxx:bb00620062bb0062b0062b0062	(Ljava/lang/String;CC)Ljava/lang/String;
    //   469: iconst_0
    //   470: anewarray 34	java/lang/Class
    //   473: invokevirtual 54	java/lang/Class:getMethod	(Ljava/lang/String;[Ljava/lang/Class;)Ljava/lang/reflect/Method;
    //   476: astore 5
    //   478: aload 5
    //   480: aconst_null
    //   481: iconst_0
    //   482: anewarray 56	java/lang/Object
    //   485: invokevirtual 62	java/lang/reflect/Method:invoke	(Ljava/lang/Object;[Ljava/lang/Object;)Ljava/lang/Object;
    //   488: astore 5
    //   490: aload 5
    //   492: checkcast 64	java/lang/Integer
    //   495: invokevirtual 68	java/lang/Integer:intValue	()I
    //   498: putstatic 70	uuuuuu/nnnono:b006Enn006Enn006E006E006E	I
    //   501: iload_0
    //   502: putstatic 70	uuuuuu/nnnono:b006Enn006Enn006E006E006E	I
    //   505: bipush 76
    //   507: putstatic 40	uuuuuu/nnnono:bnnn006Enn006E006E006E	I
    //   510: bipush 91
    //   512: putstatic 70	uuuuuu/nnnono:b006Enn006Enn006E006E006E	I
    //   515: aload 4
    //   517: putstatic 94	uuuuuu/nnnono:b006E006Ennnn006E006E006E	Ljava/lang/String;
    //   520: return
    //   521: astore 4
    //   523: aload 4
    //   525: invokevirtual 98	java/lang/reflect/InvocationTargetException:getCause	()Ljava/lang/Throwable;
    //   528: athrow
    //   529: astore 4
    //   531: aload 4
    //   533: invokevirtual 98	java/lang/reflect/InvocationTargetException:getCause	()Ljava/lang/Throwable;
    //   536: athrow
    //   537: astore 4
    //   539: aload 4
    //   541: invokevirtual 98	java/lang/reflect/InvocationTargetException:getCause	()Ljava/lang/Throwable;
    //   544: athrow
    //   545: astore 4
    //   547: aload 4
    //   549: invokevirtual 98	java/lang/reflect/InvocationTargetException:getCause	()Ljava/lang/Throwable;
    //   552: athrow
    //   553: astore 4
    //   555: aload 4
    //   557: invokevirtual 98	java/lang/reflect/InvocationTargetException:getCause	()Ljava/lang/Throwable;
    //   560: athrow
    //   561: astore 4
    //   563: aload 4
    //   565: invokevirtual 98	java/lang/reflect/InvocationTargetException:getCause	()Ljava/lang/Throwable;
    //   568: athrow
    //   569: astore 4
    //   571: aload 4
    //   573: invokevirtual 98	java/lang/reflect/InvocationTargetException:getCause	()Ljava/lang/Throwable;
    //   576: athrow
    //   577: astore 4
    //   579: aload 4
    //   581: invokevirtual 98	java/lang/reflect/InvocationTargetException:getCause	()Ljava/lang/Throwable;
    //   584: athrow
    //   585: astore 4
    //   587: aload 4
    //   589: invokevirtual 98	java/lang/reflect/InvocationTargetException:getCause	()Ljava/lang/Throwable;
    //   592: athrow
    // Local variable table:
    //   start	length	slot	name	signature
    //   10	492	0	i	int
    //   14	378	1	j	int
    //   18	145	2	k	int
    //   125	40	3	m	int
    //   5	511	4	str	String
    //   521	3	4	localInvocationTargetException1	java.lang.reflect.InvocationTargetException
    //   529	3	4	localInvocationTargetException2	java.lang.reflect.InvocationTargetException
    //   537	3	4	localInvocationTargetException3	java.lang.reflect.InvocationTargetException
    //   545	3	4	localInvocationTargetException4	java.lang.reflect.InvocationTargetException
    //   553	3	4	localInvocationTargetException5	java.lang.reflect.InvocationTargetException
    //   561	3	4	localInvocationTargetException6	java.lang.reflect.InvocationTargetException
    //   569	3	4	localInvocationTargetException7	java.lang.reflect.InvocationTargetException
    //   577	3	4	localInvocationTargetException8	java.lang.reflect.InvocationTargetException
    //   585	3	4	localInvocationTargetException9	java.lang.reflect.InvocationTargetException
    //   37	454	5	localObject	Object
    // Exception table:
    //   from	to	target	type
    //   39	51	521	java/lang/reflect/InvocationTargetException
    //   97	109	529	java/lang/reflect/InvocationTargetException
    //   146	158	537	java/lang/reflect/InvocationTargetException
    //   315	327	545	java/lang/reflect/InvocationTargetException
    //   360	372	553	java/lang/reflect/InvocationTargetException
    //   196	208	561	java/lang/reflect/InvocationTargetException
    //   239	251	569	java/lang/reflect/InvocationTargetException
    //   435	447	577	java/lang/reflect/InvocationTargetException
    //   478	490	585	java/lang/reflect/InvocationTargetException
  }
  
  public nnnono(sssttt paramSssttt, SharedPreferencesHelper paramSharedPreferencesHelper, nnoono paramNnoono)
  {
    this.bnn006Ennn006E006E006E = paramSssttt;
    this.bn006E006Ennn006E006E006E = paramSharedPreferencesHelper;
    this.b006En006Ennn006E006E006E = paramNnoono;
  }
  
  public static int b006B006B006B006B006Bkkkk006B()
  {
    return 1;
  }
  
  public static int bk006B006B006B006Bkkkk006B()
  {
    return 2;
  }
  
  public static int bkk006B006B006Bkkkk006B()
  {
    return 0;
  }
  
  public static int bkkkkk006Bkkk006B()
  {
    return 97;
  }
  
  /* Error */
  public void b006B006Bkk006Bkkkk006B()
  {
    // Byte code:
    //   0: aload_0
    //   1: getfield 127	uuuuuu/nnnono:bnnnnn006E006E006En	Luuuuuu/ttssst$tsssst;
    //   4: checkcast 167	uuuuuu/oonono$onnono
    //   7: astore 6
    //   9: aload_0
    //   10: getfield 114	uuuuuu/nnnono:b006En006Ennn006E006E006E	Luuuuuu/nnoono;
    //   13: astore 7
    //   15: ldc 2
    //   17: ldc -87
    //   19: bipush 40
    //   21: iconst_5
    //   22: invokestatic 50	xxxxxx/uxxxxx:bb00620062bb0062b0062b0062	(Ljava/lang/String;CC)Ljava/lang/String;
    //   25: iconst_0
    //   26: anewarray 34	java/lang/Class
    //   29: invokevirtual 54	java/lang/Class:getMethod	(Ljava/lang/String;[Ljava/lang/Class;)Ljava/lang/reflect/Method;
    //   32: astore 8
    //   34: aload 8
    //   36: aconst_null
    //   37: iconst_0
    //   38: anewarray 56	java/lang/Object
    //   41: invokevirtual 62	java/lang/reflect/Method:invoke	(Ljava/lang/Object;[Ljava/lang/Object;)Ljava/lang/Object;
    //   44: astore 8
    //   46: aload 8
    //   48: checkcast 64	java/lang/Integer
    //   51: invokevirtual 68	java/lang/Integer:intValue	()I
    //   54: istore_1
    //   55: iload_1
    //   56: getstatic 42	uuuuuu/nnnono:bn006En006Enn006E006E006E	I
    //   59: iload_1
    //   60: iadd
    //   61: imul
    //   62: getstatic 78	uuuuuu/nnnono:b006E006En006Enn006E006E006E	I
    //   65: irem
    //   66: tableswitch	default:+18->84, 0:+341->407
    //   84: getstatic 40	uuuuuu/nnnono:bnnn006Enn006E006E006E	I
    //   87: istore_1
    //   88: ldc 2
    //   90: ldc -85
    //   92: sipush 251
    //   95: iconst_0
    //   96: invokestatic 50	xxxxxx/uxxxxx:bb00620062bb0062b0062b0062	(Ljava/lang/String;CC)Ljava/lang/String;
    //   99: iconst_0
    //   100: anewarray 34	java/lang/Class
    //   103: invokevirtual 54	java/lang/Class:getMethod	(Ljava/lang/String;[Ljava/lang/Class;)Ljava/lang/reflect/Method;
    //   106: astore 8
    //   108: aload 8
    //   110: aconst_null
    //   111: iconst_0
    //   112: anewarray 56	java/lang/Object
    //   115: invokevirtual 62	java/lang/reflect/Method:invoke	(Ljava/lang/Object;[Ljava/lang/Object;)Ljava/lang/Object;
    //   118: astore 8
    //   120: aload 8
    //   122: checkcast 64	java/lang/Integer
    //   125: invokevirtual 68	java/lang/Integer:intValue	()I
    //   128: iload_1
    //   129: iadd
    //   130: iload_1
    //   131: imul
    //   132: getstatic 78	uuuuuu/nnnono:b006E006En006Enn006E006E006E	I
    //   135: irem
    //   136: tableswitch	default:+20->156, 0:+30->166
    //   156: bipush 46
    //   158: putstatic 40	uuuuuu/nnnono:bnnn006Enn006E006E006E	I
    //   161: bipush 56
    //   163: putstatic 70	uuuuuu/nnnono:b006Enn006Enn006E006E006E	I
    //   166: ldc 2
    //   168: ldc -83
    //   170: bipush 66
    //   172: iconst_3
    //   173: invokestatic 50	xxxxxx/uxxxxx:bb00620062bb0062b0062b0062	(Ljava/lang/String;CC)Ljava/lang/String;
    //   176: iconst_0
    //   177: anewarray 34	java/lang/Class
    //   180: invokevirtual 54	java/lang/Class:getMethod	(Ljava/lang/String;[Ljava/lang/Class;)Ljava/lang/reflect/Method;
    //   183: astore 8
    //   185: aload 8
    //   187: aconst_null
    //   188: iconst_0
    //   189: anewarray 56	java/lang/Object
    //   192: invokevirtual 62	java/lang/reflect/Method:invoke	(Ljava/lang/Object;[Ljava/lang/Object;)Ljava/lang/Object;
    //   195: astore 8
    //   197: aload 8
    //   199: checkcast 64	java/lang/Integer
    //   202: invokevirtual 68	java/lang/Integer:intValue	()I
    //   205: putstatic 40	uuuuuu/nnnono:bnnn006Enn006E006E006E	I
    //   208: bipush 6
    //   210: putstatic 70	uuuuuu/nnnono:b006Enn006Enn006E006E006E	I
    //   213: getstatic 40	uuuuuu/nnnono:bnnn006Enn006E006E006E	I
    //   216: istore_1
    //   217: getstatic 42	uuuuuu/nnnono:bn006En006Enn006E006E006E	I
    //   220: istore_2
    //   221: getstatic 40	uuuuuu/nnnono:bnnn006Enn006E006E006E	I
    //   224: istore_3
    //   225: getstatic 42	uuuuuu/nnnono:bn006En006Enn006E006E006E	I
    //   228: istore 4
    //   230: getstatic 40	uuuuuu/nnnono:bnnn006Enn006E006E006E	I
    //   233: istore 5
    //   235: ldc 2
    //   237: ldc -81
    //   239: sipush 204
    //   242: sipush 240
    //   245: iconst_0
    //   246: invokestatic 76	xxxxxx/uxxxxx:bbbb0062b0062b0062b0062	(Ljava/lang/String;CCC)Ljava/lang/String;
    //   249: iconst_0
    //   250: anewarray 34	java/lang/Class
    //   253: invokevirtual 54	java/lang/Class:getMethod	(Ljava/lang/String;[Ljava/lang/Class;)Ljava/lang/reflect/Method;
    //   256: astore 8
    //   258: aload 8
    //   260: aconst_null
    //   261: iconst_0
    //   262: anewarray 56	java/lang/Object
    //   265: invokevirtual 62	java/lang/reflect/Method:invoke	(Ljava/lang/Object;[Ljava/lang/Object;)Ljava/lang/Object;
    //   268: astore 8
    //   270: iload 5
    //   272: iload_3
    //   273: iload 4
    //   275: iadd
    //   276: imul
    //   277: aload 8
    //   279: checkcast 64	java/lang/Integer
    //   282: invokevirtual 68	java/lang/Integer:intValue	()I
    //   285: irem
    //   286: getstatic 70	uuuuuu/nnnono:b006Enn006Enn006E006E006E	I
    //   289: if_icmpeq +51 -> 340
    //   292: bipush 80
    //   294: putstatic 40	uuuuuu/nnnono:bnnn006Enn006E006E006E	I
    //   297: ldc 2
    //   299: ldc -79
    //   301: sipush 197
    //   304: iconst_2
    //   305: invokestatic 50	xxxxxx/uxxxxx:bb00620062bb0062b0062b0062	(Ljava/lang/String;CC)Ljava/lang/String;
    //   308: iconst_0
    //   309: anewarray 34	java/lang/Class
    //   312: invokevirtual 54	java/lang/Class:getMethod	(Ljava/lang/String;[Ljava/lang/Class;)Ljava/lang/reflect/Method;
    //   315: astore 8
    //   317: aload 8
    //   319: aconst_null
    //   320: iconst_0
    //   321: anewarray 56	java/lang/Object
    //   324: invokevirtual 62	java/lang/reflect/Method:invoke	(Ljava/lang/Object;[Ljava/lang/Object;)Ljava/lang/Object;
    //   327: astore 8
    //   329: aload 8
    //   331: checkcast 64	java/lang/Integer
    //   334: invokevirtual 68	java/lang/Integer:intValue	()I
    //   337: putstatic 70	uuuuuu/nnnono:b006Enn006Enn006E006E006E	I
    //   340: iload_1
    //   341: iload_2
    //   342: iadd
    //   343: getstatic 40	uuuuuu/nnnono:bnnn006Enn006E006E006E	I
    //   346: imul
    //   347: getstatic 78	uuuuuu/nnnono:b006E006En006Enn006E006E006E	I
    //   350: irem
    //   351: getstatic 70	uuuuuu/nnnono:b006Enn006Enn006E006E006E	I
    //   354: if_icmpeq +53 -> 407
    //   357: ldc 2
    //   359: ldc -77
    //   361: sipush 156
    //   364: bipush 107
    //   366: iconst_3
    //   367: invokestatic 76	xxxxxx/uxxxxx:bbbb0062b0062b0062b0062	(Ljava/lang/String;CCC)Ljava/lang/String;
    //   370: iconst_0
    //   371: anewarray 34	java/lang/Class
    //   374: invokevirtual 54	java/lang/Class:getMethod	(Ljava/lang/String;[Ljava/lang/Class;)Ljava/lang/reflect/Method;
    //   377: astore 8
    //   379: aload 8
    //   381: aconst_null
    //   382: iconst_0
    //   383: anewarray 56	java/lang/Object
    //   386: invokevirtual 62	java/lang/reflect/Method:invoke	(Ljava/lang/Object;[Ljava/lang/Object;)Ljava/lang/Object;
    //   389: astore 8
    //   391: aload 8
    //   393: checkcast 64	java/lang/Integer
    //   396: invokevirtual 68	java/lang/Integer:intValue	()I
    //   399: putstatic 40	uuuuuu/nnnono:bnnn006Enn006E006E006E	I
    //   402: bipush 46
    //   404: putstatic 70	uuuuuu/nnnono:b006Enn006Enn006E006E006E	I
    //   407: aload 6
    //   409: aload 7
    //   411: invokeinterface 183 2 0
    //   416: return
    //   417: astore 6
    //   419: aload 6
    //   421: invokevirtual 98	java/lang/reflect/InvocationTargetException:getCause	()Ljava/lang/Throwable;
    //   424: athrow
    //   425: astore 6
    //   427: aload 6
    //   429: invokevirtual 98	java/lang/reflect/InvocationTargetException:getCause	()Ljava/lang/Throwable;
    //   432: athrow
    //   433: astore 6
    //   435: aload 6
    //   437: invokevirtual 98	java/lang/reflect/InvocationTargetException:getCause	()Ljava/lang/Throwable;
    //   440: athrow
    //   441: astore 6
    //   443: aload 6
    //   445: invokevirtual 98	java/lang/reflect/InvocationTargetException:getCause	()Ljava/lang/Throwable;
    //   448: athrow
    //   449: astore 6
    //   451: aload 6
    //   453: invokevirtual 98	java/lang/reflect/InvocationTargetException:getCause	()Ljava/lang/Throwable;
    //   456: athrow
    //   457: astore 6
    //   459: aload 6
    //   461: invokevirtual 98	java/lang/reflect/InvocationTargetException:getCause	()Ljava/lang/Throwable;
    //   464: athrow
    // Local variable table:
    //   start	length	slot	name	signature
    //   0	465	0	this	nnnono
    //   54	289	1	i	int
    //   220	123	2	j	int
    //   224	52	3	k	int
    //   228	48	4	m	int
    //   233	44	5	n	int
    //   7	401	6	localOnnono	oonono.onnono
    //   417	3	6	localInvocationTargetException1	java.lang.reflect.InvocationTargetException
    //   425	3	6	localInvocationTargetException2	java.lang.reflect.InvocationTargetException
    //   433	3	6	localInvocationTargetException3	java.lang.reflect.InvocationTargetException
    //   441	3	6	localInvocationTargetException4	java.lang.reflect.InvocationTargetException
    //   449	3	6	localInvocationTargetException5	java.lang.reflect.InvocationTargetException
    //   457	3	6	localInvocationTargetException6	java.lang.reflect.InvocationTargetException
    //   13	397	7	localNnoono	nnoono
    //   32	360	8	localObject	Object
    // Exception table:
    //   from	to	target	type
    //   185	197	417	java/lang/reflect/InvocationTargetException
    //   108	120	425	java/lang/reflect/InvocationTargetException
    //   34	46	433	java/lang/reflect/InvocationTargetException
    //   258	270	441	java/lang/reflect/InvocationTargetException
    //   379	391	449	java/lang/reflect/InvocationTargetException
    //   317	329	457	java/lang/reflect/InvocationTargetException
  }
  
  /* Error */
  public void b006B006Bkkk006Bkkk006B()
  {
    // Byte code:
    //   0: ldc 2
    //   2: ldc -70
    //   4: bipush 53
    //   6: bipush 127
    //   8: iconst_0
    //   9: invokestatic 76	xxxxxx/uxxxxx:bbbb0062b0062b0062b0062	(Ljava/lang/String;CCC)Ljava/lang/String;
    //   12: iconst_0
    //   13: anewarray 34	java/lang/Class
    //   16: invokevirtual 54	java/lang/Class:getMethod	(Ljava/lang/String;[Ljava/lang/Class;)Ljava/lang/reflect/Method;
    //   19: astore 5
    //   21: aload 5
    //   23: aload_0
    //   24: iconst_0
    //   25: anewarray 56	java/lang/Object
    //   28: invokevirtual 62	java/lang/reflect/Method:invoke	(Ljava/lang/Object;[Ljava/lang/Object;)Ljava/lang/Object;
    //   31: astore 5
    //   33: aload 5
    //   35: checkcast 188	java/lang/Boolean
    //   38: invokevirtual 192	java/lang/Boolean:booleanValue	()Z
    //   41: ifeq +387 -> 428
    //   44: aload_0
    //   45: getfield 114	uuuuuu/nnnono:b006En006Ennn006E006E006E	Luuuuuu/nnoono;
    //   48: invokeinterface 197 1 0
    //   53: istore 4
    //   55: iload 4
    //   57: ifeq +372 -> 429
    //   60: getstatic 202	com/db/pwcc/dbmobile/foundation/R$string:settings_label_active	I
    //   63: istore_1
    //   64: getstatic 40	uuuuuu/nnnono:bnnn006Enn006E006E006E	I
    //   67: getstatic 42	uuuuuu/nnnono:bn006En006Enn006E006E006E	I
    //   70: iadd
    //   71: getstatic 40	uuuuuu/nnnono:bnnn006Enn006E006E006E	I
    //   74: imul
    //   75: getstatic 78	uuuuuu/nnnono:b006E006En006Enn006E006E006E	I
    //   78: irem
    //   79: getstatic 70	uuuuuu/nnnono:b006Enn006Enn006E006E006E	I
    //   82: if_icmpeq +12 -> 94
    //   85: iconst_3
    //   86: putstatic 40	uuuuuu/nnnono:bnnn006Enn006E006E006E	I
    //   89: bipush 8
    //   91: putstatic 70	uuuuuu/nnnono:b006Enn006Enn006E006E006E	I
    //   94: iload 4
    //   96: ifne +340 -> 436
    //   99: getstatic 205	com/db/pwcc/dbmobile/foundation/R$string:settings_item_mobile_payment_button_activate	I
    //   102: istore_2
    //   103: aload_0
    //   104: getfield 114	uuuuuu/nnnono:b006En006Ennn006E006E006E	Luuuuuu/nnoono;
    //   107: invokeinterface 208 1 0
    //   112: ifne +339 -> 451
    //   115: iconst_1
    //   116: istore 4
    //   118: aload_0
    //   119: getfield 114	uuuuuu/nnnono:b006En006Ennn006E006E006E	Luuuuuu/nnoono;
    //   122: invokeinterface 208 1 0
    //   127: ifeq +357 -> 484
    //   130: getstatic 40	uuuuuu/nnnono:bnnn006Enn006E006E006E	I
    //   133: istore_1
    //   134: iload_1
    //   135: getstatic 42	uuuuuu/nnnono:bn006En006Enn006E006E006E	I
    //   138: iload_1
    //   139: iadd
    //   140: imul
    //   141: getstatic 78	uuuuuu/nnnono:b006E006En006Enn006E006E006E	I
    //   144: irem
    //   145: tableswitch	default:+19->164, 0:+29->174
    //   164: bipush 74
    //   166: putstatic 40	uuuuuu/nnnono:bnnn006Enn006E006E006E	I
    //   169: bipush 16
    //   171: putstatic 70	uuuuuu/nnnono:b006Enn006Enn006E006E006E	I
    //   174: getstatic 211	com/db/pwcc/dbmobile/foundation/R$string:setting_mobile_payment_status_activate_another_user	I
    //   177: istore_1
    //   178: aload_0
    //   179: getfield 110	uuuuuu/nnnono:bnn006Ennn006E006E006E	Luuuuuu/sssttt;
    //   182: getstatic 217	com/db/pwcc/dbmobile/foundation/features/Feature:MOPAY	Lcom/db/pwcc/dbmobile/foundation/features/Feature;
    //   185: invokevirtual 223	uuuuuu/sssttt:bk006Bkkk006B006B006Bkk	(Lcom/db/pwcc/dbmobile/foundation/features/Feature;)Luuuuuu/sststt;
    //   188: astore 5
    //   190: getstatic 229	uuuuuu/sststt:bnn006En006Enn006En	Luuuuuu/sststt;
    //   193: astore 6
    //   195: getstatic 40	uuuuuu/nnnono:bnnn006Enn006E006E006E	I
    //   198: istore_3
    //   199: iload_3
    //   200: getstatic 42	uuuuuu/nnnono:bn006En006Enn006E006E006E	I
    //   203: iload_3
    //   204: iadd
    //   205: imul
    //   206: getstatic 78	uuuuuu/nnnono:b006E006En006Enn006E006E006E	I
    //   209: irem
    //   210: tableswitch	default:+18->228, 0:+65->275
    //   228: ldc 2
    //   230: ldc -25
    //   232: bipush 120
    //   234: iconst_4
    //   235: invokestatic 50	xxxxxx/uxxxxx:bb00620062bb0062b0062b0062	(Ljava/lang/String;CC)Ljava/lang/String;
    //   238: iconst_0
    //   239: anewarray 34	java/lang/Class
    //   242: invokevirtual 54	java/lang/Class:getMethod	(Ljava/lang/String;[Ljava/lang/Class;)Ljava/lang/reflect/Method;
    //   245: astore 7
    //   247: aload 7
    //   249: aconst_null
    //   250: iconst_0
    //   251: anewarray 56	java/lang/Object
    //   254: invokevirtual 62	java/lang/reflect/Method:invoke	(Ljava/lang/Object;[Ljava/lang/Object;)Ljava/lang/Object;
    //   257: astore 7
    //   259: aload 7
    //   261: checkcast 64	java/lang/Integer
    //   264: invokevirtual 68	java/lang/Integer:intValue	()I
    //   267: putstatic 40	uuuuuu/nnnono:bnnn006Enn006E006E006E	I
    //   270: bipush 54
    //   272: putstatic 70	uuuuuu/nnnono:b006Enn006Enn006E006E006E	I
    //   275: aload 5
    //   277: aload 6
    //   279: if_acmpne +202 -> 481
    //   282: getstatic 234	com/db/pwcc/dbmobile/foundation/R$string:temporarily_unavailable	I
    //   285: istore_1
    //   286: iconst_0
    //   287: istore 4
    //   289: aload_0
    //   290: getfield 127	uuuuuu/nnnono:bnnnnn006E006E006En	Luuuuuu/ttssst$tsssst;
    //   293: checkcast 167	uuuuuu/oonono$onnono
    //   296: astore 5
    //   298: getstatic 40	uuuuuu/nnnono:bnnn006Enn006E006E006E	I
    //   301: istore_3
    //   302: iload_3
    //   303: getstatic 42	uuuuuu/nnnono:bn006En006Enn006E006E006E	I
    //   306: iload_3
    //   307: iadd
    //   308: imul
    //   309: getstatic 78	uuuuuu/nnnono:b006E006En006Enn006E006E006E	I
    //   312: irem
    //   313: tableswitch	default:+19->332, 0:+104->417
    //   332: ldc 2
    //   334: ldc -20
    //   336: bipush 111
    //   338: iconst_3
    //   339: invokestatic 50	xxxxxx/uxxxxx:bb00620062bb0062b0062b0062	(Ljava/lang/String;CC)Ljava/lang/String;
    //   342: iconst_0
    //   343: anewarray 34	java/lang/Class
    //   346: invokevirtual 54	java/lang/Class:getMethod	(Ljava/lang/String;[Ljava/lang/Class;)Ljava/lang/reflect/Method;
    //   349: astore 6
    //   351: aload 6
    //   353: aconst_null
    //   354: iconst_0
    //   355: anewarray 56	java/lang/Object
    //   358: invokevirtual 62	java/lang/reflect/Method:invoke	(Ljava/lang/Object;[Ljava/lang/Object;)Ljava/lang/Object;
    //   361: astore 6
    //   363: aload 6
    //   365: checkcast 64	java/lang/Integer
    //   368: invokevirtual 68	java/lang/Integer:intValue	()I
    //   371: putstatic 40	uuuuuu/nnnono:bnnn006Enn006E006E006E	I
    //   374: ldc 2
    //   376: ldc -18
    //   378: sipush 178
    //   381: iconst_3
    //   382: invokestatic 50	xxxxxx/uxxxxx:bb00620062bb0062b0062b0062	(Ljava/lang/String;CC)Ljava/lang/String;
    //   385: iconst_0
    //   386: anewarray 34	java/lang/Class
    //   389: invokevirtual 54	java/lang/Class:getMethod	(Ljava/lang/String;[Ljava/lang/Class;)Ljava/lang/reflect/Method;
    //   392: astore 6
    //   394: aload 6
    //   396: aconst_null
    //   397: iconst_0
    //   398: anewarray 56	java/lang/Object
    //   401: invokevirtual 62	java/lang/reflect/Method:invoke	(Ljava/lang/Object;[Ljava/lang/Object;)Ljava/lang/Object;
    //   404: astore 6
    //   406: aload 6
    //   408: checkcast 64	java/lang/Integer
    //   411: invokevirtual 68	java/lang/Integer:intValue	()I
    //   414: putstatic 70	uuuuuu/nnnono:b006Enn006Enn006E006E006E	I
    //   417: aload 5
    //   419: iload_1
    //   420: iload_2
    //   421: iload 4
    //   423: invokeinterface 242 4 0
    //   428: return
    //   429: getstatic 245	com/db/pwcc/dbmobile/foundation/R$string:settings_label_inactive	I
    //   432: istore_1
    //   433: goto -369 -> 64
    //   436: getstatic 248	com/db/pwcc/dbmobile/foundation/R$string:settings_item_mobile_payment_button_deactivate	I
    //   439: istore_2
    //   440: goto -337 -> 103
    //   443: astore 5
    //   445: aload 5
    //   447: invokevirtual 98	java/lang/reflect/InvocationTargetException:getCause	()Ljava/lang/Throwable;
    //   450: athrow
    //   451: iconst_0
    //   452: istore 4
    //   454: goto -336 -> 118
    //   457: astore 5
    //   459: aload 5
    //   461: invokevirtual 98	java/lang/reflect/InvocationTargetException:getCause	()Ljava/lang/Throwable;
    //   464: athrow
    //   465: astore 5
    //   467: aload 5
    //   469: invokevirtual 98	java/lang/reflect/InvocationTargetException:getCause	()Ljava/lang/Throwable;
    //   472: athrow
    //   473: astore 5
    //   475: aload 5
    //   477: invokevirtual 98	java/lang/reflect/InvocationTargetException:getCause	()Ljava/lang/Throwable;
    //   480: athrow
    //   481: goto -192 -> 289
    //   484: goto -306 -> 178
    // Local variable table:
    //   start	length	slot	name	signature
    //   0	487	0	this	nnnono
    //   63	370	1	i	int
    //   102	338	2	j	int
    //   198	111	3	k	int
    //   53	400	4	bool	boolean
    //   19	399	5	localObject1	Object
    //   443	3	5	localInvocationTargetException1	java.lang.reflect.InvocationTargetException
    //   457	3	5	localInvocationTargetException2	java.lang.reflect.InvocationTargetException
    //   465	3	5	localInvocationTargetException3	java.lang.reflect.InvocationTargetException
    //   473	3	5	localInvocationTargetException4	java.lang.reflect.InvocationTargetException
    //   193	214	6	localObject2	Object
    //   245	15	7	localObject3	Object
    // Exception table:
    //   from	to	target	type
    //   21	33	443	java/lang/reflect/InvocationTargetException
    //   351	363	457	java/lang/reflect/InvocationTargetException
    //   394	406	465	java/lang/reflect/InvocationTargetException
    //   247	259	473	java/lang/reflect/InvocationTargetException
  }
  
  /* Error */
  public void b006Bk006B006B006Bkkkk006B(oonono.onnono paramOnnono)
  {
    // Byte code:
    //   0: aload_0
    //   1: aload_1
    //   2: invokespecial 254	uuuuuu/ssssst:ba0061a0061a0061a0061aa	(Luuuuuu/ttssst$tsssst;)V
    //   5: getstatic 40	uuuuuu/nnnono:bnnn006Enn006E006E006E	I
    //   8: istore_2
    //   9: getstatic 42	uuuuuu/nnnono:bn006En006Enn006E006E006E	I
    //   12: istore_3
    //   13: getstatic 40	uuuuuu/nnnono:bnnn006Enn006E006E006E	I
    //   16: istore 4
    //   18: getstatic 78	uuuuuu/nnnono:b006E006En006Enn006E006E006E	I
    //   21: istore 5
    //   23: getstatic 40	uuuuuu/nnnono:bnnn006Enn006E006E006E	I
    //   26: istore 6
    //   28: ldc 2
    //   30: ldc_w 256
    //   33: bipush 38
    //   35: iconst_0
    //   36: invokestatic 50	xxxxxx/uxxxxx:bb00620062bb0062b0062b0062	(Ljava/lang/String;CC)Ljava/lang/String;
    //   39: iconst_0
    //   40: anewarray 34	java/lang/Class
    //   43: invokevirtual 54	java/lang/Class:getMethod	(Ljava/lang/String;[Ljava/lang/Class;)Ljava/lang/reflect/Method;
    //   46: astore_1
    //   47: aload_1
    //   48: aconst_null
    //   49: iconst_0
    //   50: anewarray 56	java/lang/Object
    //   53: invokevirtual 62	java/lang/reflect/Method:invoke	(Ljava/lang/Object;[Ljava/lang/Object;)Ljava/lang/Object;
    //   56: astore_1
    //   57: aload_1
    //   58: checkcast 64	java/lang/Integer
    //   61: invokevirtual 68	java/lang/Integer:intValue	()I
    //   64: iload 6
    //   66: iadd
    //   67: getstatic 40	uuuuuu/nnnono:bnnn006Enn006E006E006E	I
    //   70: imul
    //   71: getstatic 78	uuuuuu/nnnono:b006E006En006Enn006E006E006E	I
    //   74: irem
    //   75: getstatic 70	uuuuuu/nnnono:b006Enn006Enn006E006E006E	I
    //   78: if_icmpeq +47 -> 125
    //   81: ldc 2
    //   83: ldc_w 258
    //   86: bipush 41
    //   88: iconst_0
    //   89: invokestatic 50	xxxxxx/uxxxxx:bb00620062bb0062b0062b0062	(Ljava/lang/String;CC)Ljava/lang/String;
    //   92: iconst_0
    //   93: anewarray 34	java/lang/Class
    //   96: invokevirtual 54	java/lang/Class:getMethod	(Ljava/lang/String;[Ljava/lang/Class;)Ljava/lang/reflect/Method;
    //   99: astore_1
    //   100: aload_1
    //   101: aconst_null
    //   102: iconst_0
    //   103: anewarray 56	java/lang/Object
    //   106: invokevirtual 62	java/lang/reflect/Method:invoke	(Ljava/lang/Object;[Ljava/lang/Object;)Ljava/lang/Object;
    //   109: astore_1
    //   110: aload_1
    //   111: checkcast 64	java/lang/Integer
    //   114: invokevirtual 68	java/lang/Integer:intValue	()I
    //   117: putstatic 40	uuuuuu/nnnono:bnnn006Enn006E006E006E	I
    //   120: bipush 53
    //   122: putstatic 70	uuuuuu/nnnono:b006Enn006Enn006E006E006E	I
    //   125: iload 4
    //   127: iload_2
    //   128: iload_3
    //   129: iadd
    //   130: imul
    //   131: iload 5
    //   133: irem
    //   134: getstatic 70	uuuuuu/nnnono:b006Enn006Enn006E006E006E	I
    //   137: if_icmpeq +85 -> 222
    //   140: ldc 2
    //   142: ldc_w 260
    //   145: sipush 142
    //   148: iconst_4
    //   149: invokestatic 50	xxxxxx/uxxxxx:bb00620062bb0062b0062b0062	(Ljava/lang/String;CC)Ljava/lang/String;
    //   152: iconst_0
    //   153: anewarray 34	java/lang/Class
    //   156: invokevirtual 54	java/lang/Class:getMethod	(Ljava/lang/String;[Ljava/lang/Class;)Ljava/lang/reflect/Method;
    //   159: astore_1
    //   160: aload_1
    //   161: aconst_null
    //   162: iconst_0
    //   163: anewarray 56	java/lang/Object
    //   166: invokevirtual 62	java/lang/reflect/Method:invoke	(Ljava/lang/Object;[Ljava/lang/Object;)Ljava/lang/Object;
    //   169: astore_1
    //   170: aload_1
    //   171: checkcast 64	java/lang/Integer
    //   174: invokevirtual 68	java/lang/Integer:intValue	()I
    //   177: putstatic 40	uuuuuu/nnnono:bnnn006Enn006E006E006E	I
    //   180: ldc 2
    //   182: ldc_w 262
    //   185: bipush 125
    //   187: sipush 190
    //   190: iconst_2
    //   191: invokestatic 76	xxxxxx/uxxxxx:bbbb0062b0062b0062b0062	(Ljava/lang/String;CCC)Ljava/lang/String;
    //   194: iconst_0
    //   195: anewarray 34	java/lang/Class
    //   198: invokevirtual 54	java/lang/Class:getMethod	(Ljava/lang/String;[Ljava/lang/Class;)Ljava/lang/reflect/Method;
    //   201: astore_1
    //   202: aload_1
    //   203: aconst_null
    //   204: iconst_0
    //   205: anewarray 56	java/lang/Object
    //   208: invokevirtual 62	java/lang/reflect/Method:invoke	(Ljava/lang/Object;[Ljava/lang/Object;)Ljava/lang/Object;
    //   211: astore_1
    //   212: aload_1
    //   213: checkcast 64	java/lang/Integer
    //   216: invokevirtual 68	java/lang/Integer:intValue	()I
    //   219: putstatic 70	uuuuuu/nnnono:b006Enn006Enn006E006E006E	I
    //   222: ldc 2
    //   224: ldc_w 264
    //   227: bipush 123
    //   229: iconst_1
    //   230: invokestatic 50	xxxxxx/uxxxxx:bb00620062bb0062b0062b0062	(Ljava/lang/String;CC)Ljava/lang/String;
    //   233: iconst_0
    //   234: anewarray 34	java/lang/Class
    //   237: invokevirtual 54	java/lang/Class:getMethod	(Ljava/lang/String;[Ljava/lang/Class;)Ljava/lang/reflect/Method;
    //   240: astore_1
    //   241: aload_1
    //   242: aload_0
    //   243: iconst_0
    //   244: anewarray 56	java/lang/Object
    //   247: invokevirtual 62	java/lang/reflect/Method:invoke	(Ljava/lang/Object;[Ljava/lang/Object;)Ljava/lang/Object;
    //   250: pop
    //   251: ldc 2
    //   253: ldc_w 266
    //   256: bipush 94
    //   258: iconst_3
    //   259: invokestatic 50	xxxxxx/uxxxxx:bb00620062bb0062b0062b0062	(Ljava/lang/String;CC)Ljava/lang/String;
    //   262: iconst_0
    //   263: anewarray 34	java/lang/Class
    //   266: invokevirtual 54	java/lang/Class:getMethod	(Ljava/lang/String;[Ljava/lang/Class;)Ljava/lang/reflect/Method;
    //   269: astore_1
    //   270: aload_1
    //   271: aload_0
    //   272: iconst_0
    //   273: anewarray 56	java/lang/Object
    //   276: invokevirtual 62	java/lang/reflect/Method:invoke	(Ljava/lang/Object;[Ljava/lang/Object;)Ljava/lang/Object;
    //   279: pop
    //   280: getstatic 40	uuuuuu/nnnono:bnnn006Enn006E006E006E	I
    //   283: istore_2
    //   284: getstatic 42	uuuuuu/nnnono:bn006En006Enn006E006E006E	I
    //   287: istore_3
    //   288: getstatic 40	uuuuuu/nnnono:bnnn006Enn006E006E006E	I
    //   291: istore 4
    //   293: getstatic 78	uuuuuu/nnnono:b006E006En006Enn006E006E006E	I
    //   296: istore 5
    //   298: getstatic 40	uuuuuu/nnnono:bnnn006Enn006E006E006E	I
    //   301: istore 6
    //   303: getstatic 42	uuuuuu/nnnono:bn006En006Enn006E006E006E	I
    //   306: istore 7
    //   308: ldc 2
    //   310: ldc_w 268
    //   313: sipush 249
    //   316: iconst_4
    //   317: invokestatic 50	xxxxxx/uxxxxx:bb00620062bb0062b0062b0062	(Ljava/lang/String;CC)Ljava/lang/String;
    //   320: iconst_0
    //   321: anewarray 34	java/lang/Class
    //   324: invokevirtual 54	java/lang/Class:getMethod	(Ljava/lang/String;[Ljava/lang/Class;)Ljava/lang/reflect/Method;
    //   327: astore_1
    //   328: aload_1
    //   329: aconst_null
    //   330: iconst_0
    //   331: anewarray 56	java/lang/Object
    //   334: invokevirtual 62	java/lang/reflect/Method:invoke	(Ljava/lang/Object;[Ljava/lang/Object;)Ljava/lang/Object;
    //   337: astore_1
    //   338: iload 7
    //   340: iload 6
    //   342: iadd
    //   343: iload 6
    //   345: imul
    //   346: aload_1
    //   347: checkcast 64	java/lang/Integer
    //   350: invokevirtual 68	java/lang/Integer:intValue	()I
    //   353: irem
    //   354: tableswitch	default:+18->372, 0:+99->453
    //   372: ldc 2
    //   374: ldc_w 270
    //   377: bipush 127
    //   379: sipush 237
    //   382: iconst_2
    //   383: invokestatic 76	xxxxxx/uxxxxx:bbbb0062b0062b0062b0062	(Ljava/lang/String;CCC)Ljava/lang/String;
    //   386: iconst_0
    //   387: anewarray 34	java/lang/Class
    //   390: invokevirtual 54	java/lang/Class:getMethod	(Ljava/lang/String;[Ljava/lang/Class;)Ljava/lang/reflect/Method;
    //   393: astore_1
    //   394: aload_1
    //   395: aconst_null
    //   396: iconst_0
    //   397: anewarray 56	java/lang/Object
    //   400: invokevirtual 62	java/lang/reflect/Method:invoke	(Ljava/lang/Object;[Ljava/lang/Object;)Ljava/lang/Object;
    //   403: astore_1
    //   404: aload_1
    //   405: checkcast 64	java/lang/Integer
    //   408: invokevirtual 68	java/lang/Integer:intValue	()I
    //   411: putstatic 40	uuuuuu/nnnono:bnnn006Enn006E006E006E	I
    //   414: ldc 2
    //   416: ldc_w 272
    //   419: bipush 83
    //   421: iconst_5
    //   422: invokestatic 50	xxxxxx/uxxxxx:bb00620062bb0062b0062b0062	(Ljava/lang/String;CC)Ljava/lang/String;
    //   425: iconst_0
    //   426: anewarray 34	java/lang/Class
    //   429: invokevirtual 54	java/lang/Class:getMethod	(Ljava/lang/String;[Ljava/lang/Class;)Ljava/lang/reflect/Method;
    //   432: astore_1
    //   433: aload_1
    //   434: aconst_null
    //   435: iconst_0
    //   436: anewarray 56	java/lang/Object
    //   439: invokevirtual 62	java/lang/reflect/Method:invoke	(Ljava/lang/Object;[Ljava/lang/Object;)Ljava/lang/Object;
    //   442: astore_1
    //   443: aload_1
    //   444: checkcast 64	java/lang/Integer
    //   447: invokevirtual 68	java/lang/Integer:intValue	()I
    //   450: putstatic 70	uuuuuu/nnnono:b006Enn006Enn006E006E006E	I
    //   453: iload 4
    //   455: iload_2
    //   456: iload_3
    //   457: iadd
    //   458: imul
    //   459: iload 5
    //   461: irem
    //   462: getstatic 70	uuuuuu/nnnono:b006Enn006Enn006E006E006E	I
    //   465: if_icmpeq +83 -> 548
    //   468: ldc 2
    //   470: ldc_w 274
    //   473: sipush 221
    //   476: iconst_2
    //   477: invokestatic 50	xxxxxx/uxxxxx:bb00620062bb0062b0062b0062	(Ljava/lang/String;CC)Ljava/lang/String;
    //   480: iconst_0
    //   481: anewarray 34	java/lang/Class
    //   484: invokevirtual 54	java/lang/Class:getMethod	(Ljava/lang/String;[Ljava/lang/Class;)Ljava/lang/reflect/Method;
    //   487: astore_1
    //   488: aload_1
    //   489: aconst_null
    //   490: iconst_0
    //   491: anewarray 56	java/lang/Object
    //   494: invokevirtual 62	java/lang/reflect/Method:invoke	(Ljava/lang/Object;[Ljava/lang/Object;)Ljava/lang/Object;
    //   497: astore_1
    //   498: aload_1
    //   499: checkcast 64	java/lang/Integer
    //   502: invokevirtual 68	java/lang/Integer:intValue	()I
    //   505: putstatic 40	uuuuuu/nnnono:bnnn006Enn006E006E006E	I
    //   508: ldc 2
    //   510: ldc_w 276
    //   513: sipush 143
    //   516: iconst_1
    //   517: invokestatic 50	xxxxxx/uxxxxx:bb00620062bb0062b0062b0062	(Ljava/lang/String;CC)Ljava/lang/String;
    //   520: iconst_0
    //   521: anewarray 34	java/lang/Class
    //   524: invokevirtual 54	java/lang/Class:getMethod	(Ljava/lang/String;[Ljava/lang/Class;)Ljava/lang/reflect/Method;
    //   527: astore_1
    //   528: aload_1
    //   529: aconst_null
    //   530: iconst_0
    //   531: anewarray 56	java/lang/Object
    //   534: invokevirtual 62	java/lang/reflect/Method:invoke	(Ljava/lang/Object;[Ljava/lang/Object;)Ljava/lang/Object;
    //   537: astore_1
    //   538: aload_1
    //   539: checkcast 64	java/lang/Integer
    //   542: invokevirtual 68	java/lang/Integer:intValue	()I
    //   545: putstatic 70	uuuuuu/nnnono:b006Enn006Enn006E006E006E	I
    //   548: return
    //   549: astore_1
    //   550: aload_1
    //   551: invokevirtual 98	java/lang/reflect/InvocationTargetException:getCause	()Ljava/lang/Throwable;
    //   554: athrow
    //   555: astore_1
    //   556: aload_1
    //   557: invokevirtual 98	java/lang/reflect/InvocationTargetException:getCause	()Ljava/lang/Throwable;
    //   560: athrow
    //   561: astore_1
    //   562: aload_1
    //   563: invokevirtual 98	java/lang/reflect/InvocationTargetException:getCause	()Ljava/lang/Throwable;
    //   566: athrow
    //   567: astore_1
    //   568: aload_1
    //   569: invokevirtual 98	java/lang/reflect/InvocationTargetException:getCause	()Ljava/lang/Throwable;
    //   572: athrow
    //   573: astore_1
    //   574: aload_1
    //   575: invokevirtual 98	java/lang/reflect/InvocationTargetException:getCause	()Ljava/lang/Throwable;
    //   578: athrow
    //   579: astore_1
    //   580: aload_1
    //   581: invokevirtual 98	java/lang/reflect/InvocationTargetException:getCause	()Ljava/lang/Throwable;
    //   584: athrow
    //   585: astore_1
    //   586: aload_1
    //   587: invokevirtual 98	java/lang/reflect/InvocationTargetException:getCause	()Ljava/lang/Throwable;
    //   590: athrow
    //   591: astore_1
    //   592: aload_1
    //   593: invokevirtual 98	java/lang/reflect/InvocationTargetException:getCause	()Ljava/lang/Throwable;
    //   596: athrow
    //   597: astore_1
    //   598: aload_1
    //   599: invokevirtual 98	java/lang/reflect/InvocationTargetException:getCause	()Ljava/lang/Throwable;
    //   602: athrow
    //   603: astore_1
    //   604: aload_1
    //   605: invokevirtual 98	java/lang/reflect/InvocationTargetException:getCause	()Ljava/lang/Throwable;
    //   608: athrow
    //   609: astore_1
    //   610: aload_1
    //   611: invokevirtual 98	java/lang/reflect/InvocationTargetException:getCause	()Ljava/lang/Throwable;
    //   614: athrow
    // Local variable table:
    //   start	length	slot	name	signature
    //   0	615	0	this	nnnono
    //   0	615	1	paramOnnono	oonono.onnono
    //   8	450	2	i	int
    //   12	446	3	j	int
    //   16	443	4	k	int
    //   21	441	5	m	int
    //   26	320	6	n	int
    //   306	37	7	i1	int
    // Exception table:
    //   from	to	target	type
    //   241	251	549	java/lang/reflect/InvocationTargetException
    //   202	212	555	java/lang/reflect/InvocationTargetException
    //   47	57	561	java/lang/reflect/InvocationTargetException
    //   328	338	567	java/lang/reflect/InvocationTargetException
    //   160	170	573	java/lang/reflect/InvocationTargetException
    //   488	498	579	java/lang/reflect/InvocationTargetException
    //   528	538	585	java/lang/reflect/InvocationTargetException
    //   270	280	591	java/lang/reflect/InvocationTargetException
    //   100	110	597	java/lang/reflect/InvocationTargetException
    //   394	404	603	java/lang/reflect/InvocationTargetException
    //   433	443	609	java/lang/reflect/InvocationTargetException
  }
  
  public boolean b006Bkkkk006Bkkk006B()
  {
    throw new Runtime("d2j fail translate: java.lang.IndexOutOfBoundsException: fromIndex < 0: -1\n\tat java.util.BitSet.nextSetBit(BitSet.java:712)\n\tat com.googlecode.dex2jar.ir.ts.array.FillArrayTransformer.makeSureAllElementAreAssigned(FillArrayTransformer.java:505)\n\tat com.googlecode.dex2jar.ir.ts.array.FillArrayTransformer.transformReportChanged(FillArrayTransformer.java:123)\n\tat com.googlecode.dex2jar.ir.ts.StatedTransformer.transform(StatedTransformer.java:10)\n\tat com.googlecode.d2j.dex.Dex2jar$2.optimize(Dex2jar.java:149)\n\tat com.googlecode.d2j.dex.Dex2Asm.convertCode(Dex2Asm.java:414)\n\tat com.googlecode.d2j.dex.ExDex2Asm.convertCode(ExDex2Asm.java:42)\n\tat com.googlecode.d2j.dex.Dex2jar$2.convertCode(Dex2jar.java:128)\n\tat com.googlecode.d2j.dex.Dex2Asm.convertMethod(Dex2Asm.java:509)\n\tat com.googlecode.d2j.dex.Dex2Asm.convertClass(Dex2Asm.java:406)\n\tat com.googlecode.d2j.dex.Dex2Asm.convertDex(Dex2Asm.java:422)\n\tat com.googlecode.d2j.dex.Dex2jar.doTranslate(Dex2jar.java:172)\n\tat com.googlecode.d2j.dex.Dex2jar.to(Dex2jar.java:272)\n\tat com.googlecode.dex2jar.tools.Dex2jarCmd.doCommandLine(Dex2jarCmd.java:108)\n\tat com.googlecode.dex2jar.tools.BaseCmd.doMain(BaseCmd.java:288)\n\tat com.googlecode.dex2jar.tools.Dex2jarCmd.main(Dex2jarCmd.java:32)\n");
  }
  
  /* Error */
  public void ba006100610061a0061aa0061a()
  {
    // Byte code:
    //   0: aload_0
    //   1: getfield 108	uuuuuu/nnnono:b006E006E006Ennn006E006E006E	Lrx/subscriptions/CompositeSubscription;
    //   4: astore 5
    //   6: getstatic 40	uuuuuu/nnnono:bnnn006Enn006E006E006E	I
    //   9: getstatic 42	uuuuuu/nnnono:bn006En006Enn006E006E006E	I
    //   12: iadd
    //   13: getstatic 40	uuuuuu/nnnono:bnnn006Enn006E006E006E	I
    //   16: imul
    //   17: getstatic 78	uuuuuu/nnnono:b006E006En006Enn006E006E006E	I
    //   20: irem
    //   21: getstatic 70	uuuuuu/nnnono:b006Enn006Enn006E006E006E	I
    //   24: if_icmpeq +51 -> 75
    //   27: ldc 2
    //   29: ldc_w 289
    //   32: bipush 125
    //   34: iconst_5
    //   35: invokestatic 50	xxxxxx/uxxxxx:bb00620062bb0062b0062b0062	(Ljava/lang/String;CC)Ljava/lang/String;
    //   38: iconst_0
    //   39: anewarray 34	java/lang/Class
    //   42: invokevirtual 54	java/lang/Class:getMethod	(Ljava/lang/String;[Ljava/lang/Class;)Ljava/lang/reflect/Method;
    //   45: astore 6
    //   47: aload 6
    //   49: aconst_null
    //   50: iconst_0
    //   51: anewarray 56	java/lang/Object
    //   54: invokevirtual 62	java/lang/reflect/Method:invoke	(Ljava/lang/Object;[Ljava/lang/Object;)Ljava/lang/Object;
    //   57: astore 6
    //   59: aload 6
    //   61: checkcast 64	java/lang/Integer
    //   64: invokevirtual 68	java/lang/Integer:intValue	()I
    //   67: putstatic 40	uuuuuu/nnnono:bnnn006Enn006E006E006E	I
    //   70: bipush 36
    //   72: putstatic 70	uuuuuu/nnnono:b006Enn006Enn006E006E006E	I
    //   75: aload 5
    //   77: ifnull +406 -> 483
    //   80: getstatic 40	uuuuuu/nnnono:bnnn006Enn006E006E006E	I
    //   83: getstatic 42	uuuuuu/nnnono:bn006En006Enn006E006E006E	I
    //   86: iadd
    //   87: getstatic 40	uuuuuu/nnnono:bnnn006Enn006E006E006E	I
    //   90: imul
    //   91: getstatic 78	uuuuuu/nnnono:b006E006En006Enn006E006E006E	I
    //   94: irem
    //   95: getstatic 70	uuuuuu/nnnono:b006Enn006Enn006E006E006E	I
    //   98: if_icmpeq +213 -> 311
    //   101: ldc 2
    //   103: ldc -118
    //   105: sipush 162
    //   108: bipush 14
    //   110: iconst_0
    //   111: invokestatic 76	xxxxxx/uxxxxx:bbbb0062b0062b0062b0062	(Ljava/lang/String;CCC)Ljava/lang/String;
    //   114: iconst_0
    //   115: anewarray 34	java/lang/Class
    //   118: invokevirtual 54	java/lang/Class:getMethod	(Ljava/lang/String;[Ljava/lang/Class;)Ljava/lang/reflect/Method;
    //   121: astore 5
    //   123: aload 5
    //   125: aconst_null
    //   126: iconst_0
    //   127: anewarray 56	java/lang/Object
    //   130: invokevirtual 62	java/lang/reflect/Method:invoke	(Ljava/lang/Object;[Ljava/lang/Object;)Ljava/lang/Object;
    //   133: astore 5
    //   135: aload 5
    //   137: checkcast 64	java/lang/Integer
    //   140: invokevirtual 68	java/lang/Integer:intValue	()I
    //   143: istore_1
    //   144: getstatic 42	uuuuuu/nnnono:bn006En006Enn006E006E006E	I
    //   147: istore_2
    //   148: ldc 2
    //   150: ldc_w 291
    //   153: bipush 35
    //   155: iconst_2
    //   156: invokestatic 50	xxxxxx/uxxxxx:bb00620062bb0062b0062b0062	(Ljava/lang/String;CC)Ljava/lang/String;
    //   159: iconst_0
    //   160: anewarray 34	java/lang/Class
    //   163: invokevirtual 54	java/lang/Class:getMethod	(Ljava/lang/String;[Ljava/lang/Class;)Ljava/lang/reflect/Method;
    //   166: astore 5
    //   168: aload 5
    //   170: aconst_null
    //   171: iconst_0
    //   172: anewarray 56	java/lang/Object
    //   175: invokevirtual 62	java/lang/reflect/Method:invoke	(Ljava/lang/Object;[Ljava/lang/Object;)Ljava/lang/Object;
    //   178: astore 5
    //   180: iload_2
    //   181: iload_1
    //   182: iadd
    //   183: iload_1
    //   184: imul
    //   185: aload 5
    //   187: checkcast 64	java/lang/Integer
    //   190: invokevirtual 68	java/lang/Integer:intValue	()I
    //   193: irem
    //   194: tableswitch	default:+18->212, 0:+28->222
    //   212: bipush 92
    //   214: putstatic 40	uuuuuu/nnnono:bnnn006Enn006E006E006E	I
    //   217: bipush 19
    //   219: putstatic 70	uuuuuu/nnnono:b006Enn006Enn006E006E006E	I
    //   222: ldc 2
    //   224: ldc_w 293
    //   227: sipush 196
    //   230: bipush 81
    //   232: iconst_2
    //   233: invokestatic 76	xxxxxx/uxxxxx:bbbb0062b0062b0062b0062	(Ljava/lang/String;CCC)Ljava/lang/String;
    //   236: iconst_0
    //   237: anewarray 34	java/lang/Class
    //   240: invokevirtual 54	java/lang/Class:getMethod	(Ljava/lang/String;[Ljava/lang/Class;)Ljava/lang/reflect/Method;
    //   243: astore 5
    //   245: aload 5
    //   247: aconst_null
    //   248: iconst_0
    //   249: anewarray 56	java/lang/Object
    //   252: invokevirtual 62	java/lang/reflect/Method:invoke	(Ljava/lang/Object;[Ljava/lang/Object;)Ljava/lang/Object;
    //   255: astore 5
    //   257: aload 5
    //   259: checkcast 64	java/lang/Integer
    //   262: invokevirtual 68	java/lang/Integer:intValue	()I
    //   265: putstatic 40	uuuuuu/nnnono:bnnn006Enn006E006E006E	I
    //   268: ldc 2
    //   270: ldc_w 295
    //   273: bipush 35
    //   275: iconst_5
    //   276: invokestatic 50	xxxxxx/uxxxxx:bb00620062bb0062b0062b0062	(Ljava/lang/String;CC)Ljava/lang/String;
    //   279: iconst_0
    //   280: anewarray 34	java/lang/Class
    //   283: invokevirtual 54	java/lang/Class:getMethod	(Ljava/lang/String;[Ljava/lang/Class;)Ljava/lang/reflect/Method;
    //   286: astore 5
    //   288: aload 5
    //   290: aconst_null
    //   291: iconst_0
    //   292: anewarray 56	java/lang/Object
    //   295: invokevirtual 62	java/lang/reflect/Method:invoke	(Ljava/lang/Object;[Ljava/lang/Object;)Ljava/lang/Object;
    //   298: astore 5
    //   300: aload 5
    //   302: checkcast 64	java/lang/Integer
    //   305: invokevirtual 68	java/lang/Integer:intValue	()I
    //   308: putstatic 70	uuuuuu/nnnono:b006Enn006Enn006E006E006E	I
    //   311: aload_0
    //   312: getfield 108	uuuuuu/nnnono:b006E006E006Ennn006E006E006E	Lrx/subscriptions/CompositeSubscription;
    //   315: invokevirtual 298	rx/subscriptions/CompositeSubscription:hasSubscriptions	()Z
    //   318: istore 4
    //   320: getstatic 40	uuuuuu/nnnono:bnnn006Enn006E006E006E	I
    //   323: istore_1
    //   324: ldc 2
    //   326: ldc_w 300
    //   329: sipush 239
    //   332: iconst_0
    //   333: invokestatic 50	xxxxxx/uxxxxx:bb00620062bb0062b0062b0062	(Ljava/lang/String;CC)Ljava/lang/String;
    //   336: iconst_0
    //   337: anewarray 34	java/lang/Class
    //   340: invokevirtual 54	java/lang/Class:getMethod	(Ljava/lang/String;[Ljava/lang/Class;)Ljava/lang/reflect/Method;
    //   343: astore 5
    //   345: aload 5
    //   347: aconst_null
    //   348: iconst_0
    //   349: anewarray 56	java/lang/Object
    //   352: invokevirtual 62	java/lang/reflect/Method:invoke	(Ljava/lang/Object;[Ljava/lang/Object;)Ljava/lang/Object;
    //   355: astore 5
    //   357: aload 5
    //   359: checkcast 64	java/lang/Integer
    //   362: invokevirtual 68	java/lang/Integer:intValue	()I
    //   365: istore_2
    //   366: getstatic 40	uuuuuu/nnnono:bnnn006Enn006E006E006E	I
    //   369: istore_3
    //   370: ldc 2
    //   372: ldc_w 302
    //   375: bipush 68
    //   377: iconst_2
    //   378: invokestatic 50	xxxxxx/uxxxxx:bb00620062bb0062b0062b0062	(Ljava/lang/String;CC)Ljava/lang/String;
    //   381: iconst_0
    //   382: anewarray 34	java/lang/Class
    //   385: invokevirtual 54	java/lang/Class:getMethod	(Ljava/lang/String;[Ljava/lang/Class;)Ljava/lang/reflect/Method;
    //   388: astore 5
    //   390: aload 5
    //   392: aconst_null
    //   393: iconst_0
    //   394: anewarray 56	java/lang/Object
    //   397: invokevirtual 62	java/lang/reflect/Method:invoke	(Ljava/lang/Object;[Ljava/lang/Object;)Ljava/lang/Object;
    //   400: astore 5
    //   402: iload_3
    //   403: iload_2
    //   404: iload_1
    //   405: iadd
    //   406: imul
    //   407: aload 5
    //   409: checkcast 64	java/lang/Integer
    //   412: invokevirtual 68	java/lang/Integer:intValue	()I
    //   415: irem
    //   416: getstatic 70	uuuuuu/nnnono:b006Enn006Enn006E006E006E	I
    //   419: if_icmpeq +52 -> 471
    //   422: bipush 85
    //   424: putstatic 40	uuuuuu/nnnono:bnnn006Enn006E006E006E	I
    //   427: ldc 2
    //   429: ldc_w 304
    //   432: sipush 232
    //   435: iconst_0
    //   436: invokestatic 50	xxxxxx/uxxxxx:bb00620062bb0062b0062b0062	(Ljava/lang/String;CC)Ljava/lang/String;
    //   439: iconst_0
    //   440: anewarray 34	java/lang/Class
    //   443: invokevirtual 54	java/lang/Class:getMethod	(Ljava/lang/String;[Ljava/lang/Class;)Ljava/lang/reflect/Method;
    //   446: astore 5
    //   448: aload 5
    //   450: aconst_null
    //   451: iconst_0
    //   452: anewarray 56	java/lang/Object
    //   455: invokevirtual 62	java/lang/reflect/Method:invoke	(Ljava/lang/Object;[Ljava/lang/Object;)Ljava/lang/Object;
    //   458: astore 5
    //   460: aload 5
    //   462: checkcast 64	java/lang/Integer
    //   465: invokevirtual 68	java/lang/Integer:intValue	()I
    //   468: putstatic 70	uuuuuu/nnnono:b006Enn006Enn006E006E006E	I
    //   471: iload 4
    //   473: ifeq +10 -> 483
    //   476: aload_0
    //   477: getfield 108	uuuuuu/nnnono:b006E006E006Ennn006E006E006E	Lrx/subscriptions/CompositeSubscription;
    //   480: invokevirtual 307	rx/subscriptions/CompositeSubscription:clear	()V
    //   483: aload_0
    //   484: invokespecial 309	uuuuuu/ssssst:ba006100610061a0061aa0061a	()V
    //   487: return
    //   488: astore 5
    //   490: aload 5
    //   492: invokevirtual 98	java/lang/reflect/InvocationTargetException:getCause	()Ljava/lang/Throwable;
    //   495: athrow
    //   496: astore 5
    //   498: aload 5
    //   500: invokevirtual 98	java/lang/reflect/InvocationTargetException:getCause	()Ljava/lang/Throwable;
    //   503: athrow
    //   504: astore 5
    //   506: aload 5
    //   508: invokevirtual 98	java/lang/reflect/InvocationTargetException:getCause	()Ljava/lang/Throwable;
    //   511: athrow
    //   512: astore 5
    //   514: aload 5
    //   516: invokevirtual 98	java/lang/reflect/InvocationTargetException:getCause	()Ljava/lang/Throwable;
    //   519: athrow
    //   520: astore 5
    //   522: aload 5
    //   524: invokevirtual 98	java/lang/reflect/InvocationTargetException:getCause	()Ljava/lang/Throwable;
    //   527: athrow
    //   528: astore 5
    //   530: aload 5
    //   532: invokevirtual 98	java/lang/reflect/InvocationTargetException:getCause	()Ljava/lang/Throwable;
    //   535: athrow
    //   536: astore 5
    //   538: aload 5
    //   540: invokevirtual 98	java/lang/reflect/InvocationTargetException:getCause	()Ljava/lang/Throwable;
    //   543: athrow
    //   544: astore 5
    //   546: aload 5
    //   548: invokevirtual 98	java/lang/reflect/InvocationTargetException:getCause	()Ljava/lang/Throwable;
    //   551: athrow
    // Local variable table:
    //   start	length	slot	name	signature
    //   0	552	0	this	nnnono
    //   143	263	1	i	int
    //   147	259	2	j	int
    //   369	38	3	k	int
    //   318	154	4	bool	boolean
    //   4	457	5	localObject1	Object
    //   488	3	5	localInvocationTargetException1	java.lang.reflect.InvocationTargetException
    //   496	3	5	localInvocationTargetException2	java.lang.reflect.InvocationTargetException
    //   504	3	5	localInvocationTargetException3	java.lang.reflect.InvocationTargetException
    //   512	3	5	localInvocationTargetException4	java.lang.reflect.InvocationTargetException
    //   520	3	5	localInvocationTargetException5	java.lang.reflect.InvocationTargetException
    //   528	3	5	localInvocationTargetException6	java.lang.reflect.InvocationTargetException
    //   536	3	5	localInvocationTargetException7	java.lang.reflect.InvocationTargetException
    //   544	3	5	localInvocationTargetException8	java.lang.reflect.InvocationTargetException
    //   45	15	6	localObject2	Object
    // Exception table:
    //   from	to	target	type
    //   390	402	488	java/lang/reflect/InvocationTargetException
    //   245	257	496	java/lang/reflect/InvocationTargetException
    //   288	300	504	java/lang/reflect/InvocationTargetException
    //   168	180	512	java/lang/reflect/InvocationTargetException
    //   123	135	520	java/lang/reflect/InvocationTargetException
    //   345	357	528	java/lang/reflect/InvocationTargetException
    //   448	460	536	java/lang/reflect/InvocationTargetException
    //   47	59	544	java/lang/reflect/InvocationTargetException
  }
  
  /* Error */
  public void bk006Bkk006Bkkkk006B()
  {
    // Byte code:
    //   0: getstatic 40	uuuuuu/nnnono:bnnn006Enn006E006E006E	I
    //   3: istore_1
    //   4: iload_1
    //   5: getstatic 42	uuuuuu/nnnono:bn006En006Enn006E006E006E	I
    //   8: iload_1
    //   9: iadd
    //   10: imul
    //   11: getstatic 78	uuuuuu/nnnono:b006E006En006Enn006E006E006E	I
    //   14: irem
    //   15: tableswitch	default:+17->32, 0:+62->77
    //   32: bipush 90
    //   34: putstatic 40	uuuuuu/nnnono:bnnn006Enn006E006E006E	I
    //   37: ldc 2
    //   39: ldc_w 314
    //   42: sipush 146
    //   45: iconst_4
    //   46: invokestatic 50	xxxxxx/uxxxxx:bb00620062bb0062b0062b0062	(Ljava/lang/String;CC)Ljava/lang/String;
    //   49: iconst_0
    //   50: anewarray 34	java/lang/Class
    //   53: invokevirtual 54	java/lang/Class:getMethod	(Ljava/lang/String;[Ljava/lang/Class;)Ljava/lang/reflect/Method;
    //   56: astore_2
    //   57: aload_2
    //   58: aconst_null
    //   59: iconst_0
    //   60: anewarray 56	java/lang/Object
    //   63: invokevirtual 62	java/lang/reflect/Method:invoke	(Ljava/lang/Object;[Ljava/lang/Object;)Ljava/lang/Object;
    //   66: astore_2
    //   67: aload_2
    //   68: checkcast 64	java/lang/Integer
    //   71: invokevirtual 68	java/lang/Integer:intValue	()I
    //   74: putstatic 70	uuuuuu/nnnono:b006Enn006Enn006E006E006E	I
    //   77: aload_0
    //   78: getfield 114	uuuuuu/nnnono:b006En006Ennn006E006E006E	Luuuuuu/nnoono;
    //   81: invokeinterface 197 1 0
    //   86: ifeq +78 -> 164
    //   89: getstatic 320	uuuuuu/vvrvrv:b0068h0068hh0068h00680068	Luuuuuu/vvrvrv;
    //   92: invokestatic 326	uuuuuu/rrvvrv:b0071q0071qq0071q0071q0071	(Luuuuuu/vvrvrv;)V
    //   95: aload_0
    //   96: getfield 127	uuuuuu/nnnono:bnnnnn006E006E006En	Luuuuuu/ttssst$tsssst;
    //   99: checkcast 167	uuuuuu/oonono$onnono
    //   102: invokeinterface 329 1 0
    //   107: new 331	java/lang/NullPointerException
    //   110: dup
    //   111: invokespecial 332	java/lang/NullPointerException:<init>	()V
    //   114: athrow
    //   115: astore_2
    //   116: ldc 2
    //   118: ldc_w 334
    //   121: bipush 90
    //   123: iconst_0
    //   124: invokestatic 50	xxxxxx/uxxxxx:bb00620062bb0062b0062b0062	(Ljava/lang/String;CC)Ljava/lang/String;
    //   127: iconst_0
    //   128: anewarray 34	java/lang/Class
    //   131: invokevirtual 54	java/lang/Class:getMethod	(Ljava/lang/String;[Ljava/lang/Class;)Ljava/lang/reflect/Method;
    //   134: astore_2
    //   135: aload_2
    //   136: aconst_null
    //   137: iconst_0
    //   138: anewarray 56	java/lang/Object
    //   141: invokevirtual 62	java/lang/reflect/Method:invoke	(Ljava/lang/Object;[Ljava/lang/Object;)Ljava/lang/Object;
    //   144: astore_2
    //   145: aload_2
    //   146: checkcast 64	java/lang/Integer
    //   149: invokevirtual 68	java/lang/Integer:intValue	()I
    //   152: putstatic 40	uuuuuu/nnnono:bnnn006Enn006E006E006E	I
    //   155: iconst_2
    //   156: istore_1
    //   157: iload_1
    //   158: iconst_0
    //   159: idiv
    //   160: istore_1
    //   161: goto -4 -> 157
    //   164: getstatic 337	uuuuuu/vvrvrv:bhh0068hh0068h00680068	Luuuuuu/vvrvrv;
    //   167: invokestatic 326	uuuuuu/rrvvrv:b0071q0071qq0071q0071q0071	(Luuuuuu/vvrvrv;)V
    //   170: aload_0
    //   171: getfield 127	uuuuuu/nnnono:bnnnnn006E006E006En	Luuuuuu/ttssst$tsssst;
    //   174: checkcast 167	uuuuuu/oonono$onnono
    //   177: astore_2
    //   178: getstatic 40	uuuuuu/nnnono:bnnn006Enn006E006E006E	I
    //   181: istore_1
    //   182: iload_1
    //   183: getstatic 42	uuuuuu/nnnono:bn006En006Enn006E006E006E	I
    //   186: iload_1
    //   187: iadd
    //   188: imul
    //   189: getstatic 78	uuuuuu/nnnono:b006E006En006Enn006E006E006E	I
    //   192: irem
    //   193: tableswitch	default:+19->212, 0:+29->222
    //   212: bipush 62
    //   214: putstatic 40	uuuuuu/nnnono:bnnn006Enn006E006E006E	I
    //   217: bipush 61
    //   219: putstatic 70	uuuuuu/nnnono:b006Enn006Enn006E006E006E	I
    //   222: aload_2
    //   223: aload_0
    //   224: getfield 114	uuuuuu/nnnono:b006En006Ennn006E006E006E	Luuuuuu/nnoono;
    //   227: invokeinterface 340 2 0
    //   232: return
    //   233: astore_2
    //   234: aload_2
    //   235: invokevirtual 98	java/lang/reflect/InvocationTargetException:getCause	()Ljava/lang/Throwable;
    //   238: athrow
    //   239: astore_2
    //   240: aload_2
    //   241: invokevirtual 98	java/lang/reflect/InvocationTargetException:getCause	()Ljava/lang/Throwable;
    //   244: athrow
    //   245: astore_2
    //   246: ldc 2
    //   248: ldc_w 262
    //   251: sipush 189
    //   254: iconst_2
    //   255: invokestatic 50	xxxxxx/uxxxxx:bb00620062bb0062b0062b0062	(Ljava/lang/String;CC)Ljava/lang/String;
    //   258: iconst_0
    //   259: anewarray 34	java/lang/Class
    //   262: invokevirtual 54	java/lang/Class:getMethod	(Ljava/lang/String;[Ljava/lang/Class;)Ljava/lang/reflect/Method;
    //   265: astore_2
    //   266: aload_2
    //   267: aconst_null
    //   268: iconst_0
    //   269: anewarray 56	java/lang/Object
    //   272: invokevirtual 62	java/lang/reflect/Method:invoke	(Ljava/lang/Object;[Ljava/lang/Object;)Ljava/lang/Object;
    //   275: astore_2
    //   276: aload_2
    //   277: checkcast 64	java/lang/Integer
    //   280: invokevirtual 68	java/lang/Integer:intValue	()I
    //   283: putstatic 40	uuuuuu/nnnono:bnnn006Enn006E006E006E	I
    //   286: getstatic 40	uuuuuu/nnnono:bnnn006Enn006E006E006E	I
    //   289: getstatic 42	uuuuuu/nnnono:bn006En006Enn006E006E006E	I
    //   292: iadd
    //   293: getstatic 40	uuuuuu/nnnono:bnnn006Enn006E006E006E	I
    //   296: imul
    //   297: getstatic 78	uuuuuu/nnnono:b006E006En006Enn006E006E006E	I
    //   300: irem
    //   301: getstatic 70	uuuuuu/nnnono:b006Enn006Enn006E006E006E	I
    //   304: if_icmpeq -72 -> 232
    //   307: ldc 2
    //   309: ldc 123
    //   311: sipush 255
    //   314: bipush 35
    //   316: iconst_0
    //   317: invokestatic 76	xxxxxx/uxxxxx:bbbb0062b0062b0062b0062	(Ljava/lang/String;CCC)Ljava/lang/String;
    //   320: iconst_0
    //   321: anewarray 34	java/lang/Class
    //   324: invokevirtual 54	java/lang/Class:getMethod	(Ljava/lang/String;[Ljava/lang/Class;)Ljava/lang/reflect/Method;
    //   327: astore_2
    //   328: aload_2
    //   329: aconst_null
    //   330: iconst_0
    //   331: anewarray 56	java/lang/Object
    //   334: invokevirtual 62	java/lang/reflect/Method:invoke	(Ljava/lang/Object;[Ljava/lang/Object;)Ljava/lang/Object;
    //   337: astore_2
    //   338: aload_2
    //   339: checkcast 64	java/lang/Integer
    //   342: invokevirtual 68	java/lang/Integer:intValue	()I
    //   345: putstatic 40	uuuuuu/nnnono:bnnn006Enn006E006E006E	I
    //   348: ldc 2
    //   350: ldc_w 342
    //   353: bipush 58
    //   355: iconst_4
    //   356: invokestatic 50	xxxxxx/uxxxxx:bb00620062bb0062b0062b0062	(Ljava/lang/String;CC)Ljava/lang/String;
    //   359: iconst_0
    //   360: anewarray 34	java/lang/Class
    //   363: invokevirtual 54	java/lang/Class:getMethod	(Ljava/lang/String;[Ljava/lang/Class;)Ljava/lang/reflect/Method;
    //   366: astore_2
    //   367: aload_2
    //   368: aconst_null
    //   369: iconst_0
    //   370: anewarray 56	java/lang/Object
    //   373: invokevirtual 62	java/lang/reflect/Method:invoke	(Ljava/lang/Object;[Ljava/lang/Object;)Ljava/lang/Object;
    //   376: astore_2
    //   377: aload_2
    //   378: checkcast 64	java/lang/Integer
    //   381: invokevirtual 68	java/lang/Integer:intValue	()I
    //   384: putstatic 70	uuuuuu/nnnono:b006Enn006Enn006E006E006E	I
    //   387: return
    //   388: astore_2
    //   389: aload_2
    //   390: invokevirtual 98	java/lang/reflect/InvocationTargetException:getCause	()Ljava/lang/Throwable;
    //   393: athrow
    //   394: astore_2
    //   395: aload_2
    //   396: invokevirtual 98	java/lang/reflect/InvocationTargetException:getCause	()Ljava/lang/Throwable;
    //   399: athrow
    //   400: astore_2
    //   401: aload_2
    //   402: invokevirtual 98	java/lang/reflect/InvocationTargetException:getCause	()Ljava/lang/Throwable;
    //   405: athrow
    // Local variable table:
    //   start	length	slot	name	signature
    //   0	406	0	this	nnnono
    //   3	186	1	i	int
    //   56	12	2	localObject1	Object
    //   115	1	2	localException1	Exception
    //   134	89	2	localObject2	Object
    //   233	2	2	localInvocationTargetException1	java.lang.reflect.InvocationTargetException
    //   239	2	2	localInvocationTargetException2	java.lang.reflect.InvocationTargetException
    //   245	1	2	localException2	Exception
    //   265	113	2	localObject3	Object
    //   388	2	2	localInvocationTargetException3	java.lang.reflect.InvocationTargetException
    //   394	2	2	localInvocationTargetException4	java.lang.reflect.InvocationTargetException
    //   400	2	2	localInvocationTargetException5	java.lang.reflect.InvocationTargetException
    // Exception table:
    //   from	to	target	type
    //   107	115	115	java/lang/Exception
    //   57	67	233	java/lang/reflect/InvocationTargetException
    //   135	145	239	java/lang/reflect/InvocationTargetException
    //   157	161	245	java/lang/Exception
    //   266	276	388	java/lang/reflect/InvocationTargetException
    //   328	338	394	java/lang/reflect/InvocationTargetException
    //   367	377	400	java/lang/reflect/InvocationTargetException
  }
  
  /* Error */
  public void bk006Bkkk006Bkkk006B()
  {
    // Byte code:
    //   0: aload_0
    //   1: getfield 108	uuuuuu/nnnono:b006E006E006Ennn006E006E006E	Lrx/subscriptions/CompositeSubscription;
    //   4: invokevirtual 298	rx/subscriptions/CompositeSubscription:hasSubscriptions	()Z
    //   7: ifeq +69 -> 76
    //   10: getstatic 40	uuuuuu/nnnono:bnnn006Enn006E006E006E	I
    //   13: getstatic 42	uuuuuu/nnnono:bn006En006Enn006E006E006E	I
    //   16: iadd
    //   17: getstatic 40	uuuuuu/nnnono:bnnn006Enn006E006E006E	I
    //   20: imul
    //   21: getstatic 78	uuuuuu/nnnono:b006E006En006Enn006E006E006E	I
    //   24: irem
    //   25: getstatic 70	uuuuuu/nnnono:b006Enn006Enn006E006E006E	I
    //   28: if_icmpeq +47 -> 75
    //   31: bipush 19
    //   33: putstatic 40	uuuuuu/nnnono:bnnn006Enn006E006E006E	I
    //   36: ldc 2
    //   38: ldc_w 345
    //   41: bipush 99
    //   43: iconst_3
    //   44: invokestatic 50	xxxxxx/uxxxxx:bb00620062bb0062b0062b0062	(Ljava/lang/String;CC)Ljava/lang/String;
    //   47: iconst_0
    //   48: anewarray 34	java/lang/Class
    //   51: invokevirtual 54	java/lang/Class:getMethod	(Ljava/lang/String;[Ljava/lang/Class;)Ljava/lang/reflect/Method;
    //   54: astore_3
    //   55: aload_3
    //   56: aconst_null
    //   57: iconst_0
    //   58: anewarray 56	java/lang/Object
    //   61: invokevirtual 62	java/lang/reflect/Method:invoke	(Ljava/lang/Object;[Ljava/lang/Object;)Ljava/lang/Object;
    //   64: astore_3
    //   65: aload_3
    //   66: checkcast 64	java/lang/Integer
    //   69: invokevirtual 68	java/lang/Integer:intValue	()I
    //   72: putstatic 70	uuuuuu/nnnono:b006Enn006Enn006E006E006E	I
    //   75: return
    //   76: aload_0
    //   77: getfield 127	uuuuuu/nnnono:bnnnnn006E006E006En	Luuuuuu/ttssst$tsssst;
    //   80: checkcast 167	uuuuuu/oonono$onnono
    //   83: invokeinterface 349 1 0
    //   88: astore_3
    //   89: getstatic 40	uuuuuu/nnnono:bnnn006Enn006E006E006E	I
    //   92: getstatic 42	uuuuuu/nnnono:bn006En006Enn006E006E006E	I
    //   95: iadd
    //   96: getstatic 40	uuuuuu/nnnono:bnnn006Enn006E006E006E	I
    //   99: imul
    //   100: getstatic 78	uuuuuu/nnnono:b006E006En006Enn006E006E006E	I
    //   103: irem
    //   104: getstatic 70	uuuuuu/nnnono:b006Enn006Enn006E006E006E	I
    //   107: if_icmpeq +164 -> 271
    //   110: ldc 2
    //   112: ldc_w 351
    //   115: bipush 82
    //   117: bipush 92
    //   119: iconst_2
    //   120: invokestatic 76	xxxxxx/uxxxxx:bbbb0062b0062b0062b0062	(Ljava/lang/String;CCC)Ljava/lang/String;
    //   123: iconst_0
    //   124: anewarray 34	java/lang/Class
    //   127: invokevirtual 54	java/lang/Class:getMethod	(Ljava/lang/String;[Ljava/lang/Class;)Ljava/lang/reflect/Method;
    //   130: astore 4
    //   132: aload 4
    //   134: aconst_null
    //   135: iconst_0
    //   136: anewarray 56	java/lang/Object
    //   139: invokevirtual 62	java/lang/reflect/Method:invoke	(Ljava/lang/Object;[Ljava/lang/Object;)Ljava/lang/Object;
    //   142: astore 4
    //   144: aload 4
    //   146: checkcast 64	java/lang/Integer
    //   149: invokevirtual 68	java/lang/Integer:intValue	()I
    //   152: istore_1
    //   153: getstatic 42	uuuuuu/nnnono:bn006En006Enn006E006E006E	I
    //   156: istore_2
    //   157: ldc 2
    //   159: ldc_w 353
    //   162: bipush 13
    //   164: bipush 14
    //   166: iconst_0
    //   167: invokestatic 76	xxxxxx/uxxxxx:bbbb0062b0062b0062b0062	(Ljava/lang/String;CCC)Ljava/lang/String;
    //   170: iconst_0
    //   171: anewarray 34	java/lang/Class
    //   174: invokevirtual 54	java/lang/Class:getMethod	(Ljava/lang/String;[Ljava/lang/Class;)Ljava/lang/reflect/Method;
    //   177: astore 4
    //   179: aload 4
    //   181: aconst_null
    //   182: iconst_0
    //   183: anewarray 56	java/lang/Object
    //   186: invokevirtual 62	java/lang/reflect/Method:invoke	(Ljava/lang/Object;[Ljava/lang/Object;)Ljava/lang/Object;
    //   189: astore 4
    //   191: aload 4
    //   193: checkcast 64	java/lang/Integer
    //   196: invokevirtual 68	java/lang/Integer:intValue	()I
    //   199: iload_2
    //   200: iload_1
    //   201: iadd
    //   202: imul
    //   203: getstatic 78	uuuuuu/nnnono:b006E006En006Enn006E006E006E	I
    //   206: irem
    //   207: getstatic 70	uuuuuu/nnnono:b006Enn006Enn006E006E006E	I
    //   210: if_icmpeq +51 -> 261
    //   213: iconst_3
    //   214: putstatic 40	uuuuuu/nnnono:bnnn006Enn006E006E006E	I
    //   217: ldc 2
    //   219: ldc_w 355
    //   222: sipush 186
    //   225: iconst_3
    //   226: invokestatic 50	xxxxxx/uxxxxx:bb00620062bb0062b0062b0062	(Ljava/lang/String;CC)Ljava/lang/String;
    //   229: iconst_0
    //   230: anewarray 34	java/lang/Class
    //   233: invokevirtual 54	java/lang/Class:getMethod	(Ljava/lang/String;[Ljava/lang/Class;)Ljava/lang/reflect/Method;
    //   236: astore 4
    //   238: aload 4
    //   240: aconst_null
    //   241: iconst_0
    //   242: anewarray 56	java/lang/Object
    //   245: invokevirtual 62	java/lang/reflect/Method:invoke	(Ljava/lang/Object;[Ljava/lang/Object;)Ljava/lang/Object;
    //   248: astore 4
    //   250: aload 4
    //   252: checkcast 64	java/lang/Integer
    //   255: invokevirtual 68	java/lang/Integer:intValue	()I
    //   258: putstatic 70	uuuuuu/nnnono:b006Enn006Enn006E006E006E	I
    //   261: bipush 60
    //   263: putstatic 40	uuuuuu/nnnono:bnnn006Enn006E006E006E	I
    //   266: bipush 83
    //   268: putstatic 70	uuuuuu/nnnono:b006Enn006Enn006E006E006E	I
    //   271: ldc_w 357
    //   274: ldc_w 359
    //   277: bipush 90
    //   279: bipush 11
    //   281: iconst_1
    //   282: invokestatic 76	xxxxxx/uxxxxx:bbbb0062b0062b0062b0062	(Ljava/lang/String;CCC)Ljava/lang/String;
    //   285: iconst_3
    //   286: anewarray 34	java/lang/Class
    //   289: dup
    //   290: iconst_0
    //   291: ldc_w 361
    //   294: aastore
    //   295: dup
    //   296: iconst_1
    //   297: getstatic 367	java/lang/Character:TYPE	Ljava/lang/Class;
    //   300: aastore
    //   301: dup
    //   302: iconst_2
    //   303: getstatic 367	java/lang/Character:TYPE	Ljava/lang/Class;
    //   306: aastore
    //   307: invokevirtual 54	java/lang/Class:getMethod	(Ljava/lang/String;[Ljava/lang/Class;)Ljava/lang/reflect/Method;
    //   310: astore 4
    //   312: aload 4
    //   314: aconst_null
    //   315: iconst_3
    //   316: anewarray 56	java/lang/Object
    //   319: dup
    //   320: iconst_0
    //   321: ldc_w 369
    //   324: aastore
    //   325: dup
    //   326: iconst_1
    //   327: bipush 57
    //   329: invokestatic 373	java/lang/Character:valueOf	(C)Ljava/lang/Character;
    //   332: aastore
    //   333: dup
    //   334: iconst_2
    //   335: iconst_5
    //   336: invokestatic 373	java/lang/Character:valueOf	(C)Ljava/lang/Character;
    //   339: aastore
    //   340: invokevirtual 62	java/lang/reflect/Method:invoke	(Ljava/lang/Object;[Ljava/lang/Object;)Ljava/lang/Object;
    //   343: astore 4
    //   345: new 375	android/content/IntentFilter
    //   348: dup
    //   349: aload 4
    //   351: checkcast 361	java/lang/String
    //   354: invokespecial 376	android/content/IntentFilter:<init>	(Ljava/lang/String;)V
    //   357: astore 4
    //   359: ldc 2
    //   361: ldc 92
    //   363: sipush 160
    //   366: sipush 225
    //   369: iconst_1
    //   370: invokestatic 76	xxxxxx/uxxxxx:bbbb0062b0062b0062b0062	(Ljava/lang/String;CCC)Ljava/lang/String;
    //   373: iconst_0
    //   374: anewarray 34	java/lang/Class
    //   377: invokevirtual 54	java/lang/Class:getMethod	(Ljava/lang/String;[Ljava/lang/Class;)Ljava/lang/reflect/Method;
    //   380: astore 5
    //   382: aload 5
    //   384: aconst_null
    //   385: iconst_0
    //   386: anewarray 56	java/lang/Object
    //   389: invokevirtual 62	java/lang/reflect/Method:invoke	(Ljava/lang/Object;[Ljava/lang/Object;)Ljava/lang/Object;
    //   392: astore 5
    //   394: aload 5
    //   396: checkcast 64	java/lang/Integer
    //   399: invokevirtual 68	java/lang/Integer:intValue	()I
    //   402: istore_1
    //   403: iload_1
    //   404: getstatic 42	uuuuuu/nnnono:bn006En006Enn006E006E006E	I
    //   407: iload_1
    //   408: iadd
    //   409: imul
    //   410: getstatic 78	uuuuuu/nnnono:b006E006En006Enn006E006E006E	I
    //   413: irem
    //   414: tableswitch	default:+18->432, 0:+67->481
    //   432: bipush 37
    //   434: putstatic 40	uuuuuu/nnnono:bnnn006Enn006E006E006E	I
    //   437: ldc 2
    //   439: ldc_w 378
    //   442: sipush 137
    //   445: iconst_0
    //   446: invokestatic 50	xxxxxx/uxxxxx:bb00620062bb0062b0062b0062	(Ljava/lang/String;CC)Ljava/lang/String;
    //   449: iconst_0
    //   450: anewarray 34	java/lang/Class
    //   453: invokevirtual 54	java/lang/Class:getMethod	(Ljava/lang/String;[Ljava/lang/Class;)Ljava/lang/reflect/Method;
    //   456: astore 5
    //   458: aload 5
    //   460: aconst_null
    //   461: iconst_0
    //   462: anewarray 56	java/lang/Object
    //   465: invokevirtual 62	java/lang/reflect/Method:invoke	(Ljava/lang/Object;[Ljava/lang/Object;)Ljava/lang/Object;
    //   468: astore 5
    //   470: aload 5
    //   472: checkcast 64	java/lang/Integer
    //   475: invokevirtual 68	java/lang/Integer:intValue	()I
    //   478: putstatic 70	uuuuuu/nnnono:b006Enn006Enn006E006E006E	I
    //   481: aload_3
    //   482: aload 4
    //   484: invokestatic 384	uuuuuu/noonon:bk006B006B006B006B006B006Bkk006B	(Landroid/content/Context;Landroid/content/IntentFilter;)Lrx/Observable;
    //   487: invokestatic 390	rx/schedulers/Schedulers:newThread	()Lrx/Scheduler;
    //   490: invokevirtual 396	rx/Observable:subscribeOn	(Lrx/Scheduler;)Lrx/Observable;
    //   493: invokestatic 401	rx/android/schedulers/AndroidSchedulers:mainThread	()Lrx/Scheduler;
    //   496: invokevirtual 404	rx/Observable:observeOn	(Lrx/Scheduler;)Lrx/Observable;
    //   499: new 9	uuuuuu/nnnono$noonno
    //   502: dup
    //   503: aload_0
    //   504: aconst_null
    //   505: invokespecial 407	uuuuuu/nnnono$noonno:<init>	(Luuuuuu/nnnono;Luuuuuu/nnnono$1;)V
    //   508: invokevirtual 411	rx/Observable:subscribe	(Lrx/Subscriber;)Lrx/Subscription;
    //   511: astore_3
    //   512: aload_0
    //   513: getfield 108	uuuuuu/nnnono:b006E006E006Ennn006E006E006E	Lrx/subscriptions/CompositeSubscription;
    //   516: aload_3
    //   517: invokevirtual 415	rx/subscriptions/CompositeSubscription:add	(Lrx/Subscription;)V
    //   520: return
    //   521: astore_3
    //   522: aload_3
    //   523: invokevirtual 98	java/lang/reflect/InvocationTargetException:getCause	()Ljava/lang/Throwable;
    //   526: athrow
    //   527: astore_3
    //   528: aload_3
    //   529: invokevirtual 98	java/lang/reflect/InvocationTargetException:getCause	()Ljava/lang/Throwable;
    //   532: athrow
    //   533: astore_3
    //   534: aload_3
    //   535: invokevirtual 98	java/lang/reflect/InvocationTargetException:getCause	()Ljava/lang/Throwable;
    //   538: athrow
    //   539: astore_3
    //   540: aload_3
    //   541: invokevirtual 98	java/lang/reflect/InvocationTargetException:getCause	()Ljava/lang/Throwable;
    //   544: athrow
    //   545: astore_3
    //   546: aload_3
    //   547: invokevirtual 98	java/lang/reflect/InvocationTargetException:getCause	()Ljava/lang/Throwable;
    //   550: athrow
    //   551: astore_3
    //   552: aload_3
    //   553: invokevirtual 98	java/lang/reflect/InvocationTargetException:getCause	()Ljava/lang/Throwable;
    //   556: athrow
    //   557: astore_3
    //   558: aload_3
    //   559: invokevirtual 98	java/lang/reflect/InvocationTargetException:getCause	()Ljava/lang/Throwable;
    //   562: athrow
    // Local variable table:
    //   start	length	slot	name	signature
    //   0	563	0	this	nnnono
    //   152	258	1	i	int
    //   156	46	2	j	int
    //   54	463	3	localObject1	Object
    //   521	2	3	localInvocationTargetException1	java.lang.reflect.InvocationTargetException
    //   527	2	3	localInvocationTargetException2	java.lang.reflect.InvocationTargetException
    //   533	2	3	localInvocationTargetException3	java.lang.reflect.InvocationTargetException
    //   539	2	3	localInvocationTargetException4	java.lang.reflect.InvocationTargetException
    //   545	2	3	localInvocationTargetException5	java.lang.reflect.InvocationTargetException
    //   551	2	3	localInvocationTargetException6	java.lang.reflect.InvocationTargetException
    //   557	2	3	localInvocationTargetException7	java.lang.reflect.InvocationTargetException
    //   130	353	4	localObject2	Object
    //   380	91	5	localObject3	Object
    // Exception table:
    //   from	to	target	type
    //   458	470	521	java/lang/reflect/InvocationTargetException
    //   382	394	527	java/lang/reflect/InvocationTargetException
    //   132	144	533	java/lang/reflect/InvocationTargetException
    //   179	191	539	java/lang/reflect/InvocationTargetException
    //   238	250	545	java/lang/reflect/InvocationTargetException
    //   312	345	551	java/lang/reflect/InvocationTargetException
    //   55	65	557	java/lang/reflect/InvocationTargetException
  }
  
  /* Error */
  public boolean bkk006Bkk006Bkkk006B()
  {
    // Byte code:
    //   0: aload_0
    //   1: invokevirtual 419	uuuuuu/nnnono:b006Bk006B006Bkk006Bk006Bk	()Z
    //   4: ifne +430 -> 434
    //   7: aload_0
    //   8: getfield 423	uuuuuu/nnnono:b006E006E006E006E006En006E006En	Luuuuuu/hyhyhh;
    //   11: invokevirtual 428	uuuuuu/hyhyhh:b0070pp007000700070p007000700070	()Ljava/lang/String;
    //   14: ifnull +420 -> 434
    //   17: getstatic 40	uuuuuu/nnnono:bnnn006Enn006E006E006E	I
    //   20: getstatic 42	uuuuuu/nnnono:bn006En006Enn006E006E006E	I
    //   23: iadd
    //   24: getstatic 40	uuuuuu/nnnono:bnnn006Enn006E006E006E	I
    //   27: imul
    //   28: getstatic 78	uuuuuu/nnnono:b006E006En006Enn006E006E006E	I
    //   31: irem
    //   32: getstatic 70	uuuuuu/nnnono:b006Enn006Enn006E006E006E	I
    //   35: if_icmpeq +120 -> 155
    //   38: bipush 65
    //   40: putstatic 40	uuuuuu/nnnono:bnnn006Enn006E006E006E	I
    //   43: ldc 2
    //   45: ldc_w 430
    //   48: bipush 58
    //   50: iconst_1
    //   51: invokestatic 50	xxxxxx/uxxxxx:bb00620062bb0062b0062b0062	(Ljava/lang/String;CC)Ljava/lang/String;
    //   54: iconst_0
    //   55: anewarray 34	java/lang/Class
    //   58: invokevirtual 54	java/lang/Class:getMethod	(Ljava/lang/String;[Ljava/lang/Class;)Ljava/lang/reflect/Method;
    //   61: astore 5
    //   63: aload 5
    //   65: aconst_null
    //   66: iconst_0
    //   67: anewarray 56	java/lang/Object
    //   70: invokevirtual 62	java/lang/reflect/Method:invoke	(Ljava/lang/Object;[Ljava/lang/Object;)Ljava/lang/Object;
    //   73: astore 5
    //   75: aload 5
    //   77: checkcast 64	java/lang/Integer
    //   80: invokevirtual 68	java/lang/Integer:intValue	()I
    //   83: putstatic 70	uuuuuu/nnnono:b006Enn006Enn006E006E006E	I
    //   86: getstatic 40	uuuuuu/nnnono:bnnn006Enn006E006E006E	I
    //   89: getstatic 42	uuuuuu/nnnono:bn006En006Enn006E006E006E	I
    //   92: iadd
    //   93: getstatic 40	uuuuuu/nnnono:bnnn006Enn006E006E006E	I
    //   96: imul
    //   97: getstatic 78	uuuuuu/nnnono:b006E006En006Enn006E006E006E	I
    //   100: irem
    //   101: getstatic 70	uuuuuu/nnnono:b006Enn006Enn006E006E006E	I
    //   104: if_icmpeq +51 -> 155
    //   107: bipush 94
    //   109: putstatic 40	uuuuuu/nnnono:bnnn006Enn006E006E006E	I
    //   112: ldc 2
    //   114: ldc_w 432
    //   117: bipush 67
    //   119: iconst_1
    //   120: invokestatic 50	xxxxxx/uxxxxx:bb00620062bb0062b0062b0062	(Ljava/lang/String;CC)Ljava/lang/String;
    //   123: iconst_0
    //   124: anewarray 34	java/lang/Class
    //   127: invokevirtual 54	java/lang/Class:getMethod	(Ljava/lang/String;[Ljava/lang/Class;)Ljava/lang/reflect/Method;
    //   130: astore 5
    //   132: aload 5
    //   134: aconst_null
    //   135: iconst_0
    //   136: anewarray 56	java/lang/Object
    //   139: invokevirtual 62	java/lang/reflect/Method:invoke	(Ljava/lang/Object;[Ljava/lang/Object;)Ljava/lang/Object;
    //   142: astore 5
    //   144: aload 5
    //   146: checkcast 64	java/lang/Integer
    //   149: invokevirtual 68	java/lang/Integer:intValue	()I
    //   152: putstatic 70	uuuuuu/nnnono:b006Enn006Enn006E006E006E	I
    //   155: getstatic 40	uuuuuu/nnnono:bnnn006Enn006E006E006E	I
    //   158: istore_1
    //   159: getstatic 42	uuuuuu/nnnono:bn006En006Enn006E006E006E	I
    //   162: istore_2
    //   163: getstatic 40	uuuuuu/nnnono:bnnn006Enn006E006E006E	I
    //   166: istore_3
    //   167: getstatic 78	uuuuuu/nnnono:b006E006En006Enn006E006E006E	I
    //   170: istore 4
    //   172: getstatic 40	uuuuuu/nnnono:bnnn006Enn006E006E006E	I
    //   175: getstatic 42	uuuuuu/nnnono:bn006En006Enn006E006E006E	I
    //   178: iadd
    //   179: getstatic 40	uuuuuu/nnnono:bnnn006Enn006E006E006E	I
    //   182: imul
    //   183: getstatic 78	uuuuuu/nnnono:b006E006En006Enn006E006E006E	I
    //   186: irem
    //   187: getstatic 70	uuuuuu/nnnono:b006Enn006Enn006E006E006E	I
    //   190: if_icmpeq +53 -> 243
    //   193: bipush 32
    //   195: putstatic 40	uuuuuu/nnnono:bnnn006Enn006E006E006E	I
    //   198: ldc 2
    //   200: ldc_w 434
    //   203: bipush 89
    //   205: bipush 65
    //   207: iconst_2
    //   208: invokestatic 76	xxxxxx/uxxxxx:bbbb0062b0062b0062b0062	(Ljava/lang/String;CCC)Ljava/lang/String;
    //   211: iconst_0
    //   212: anewarray 34	java/lang/Class
    //   215: invokevirtual 54	java/lang/Class:getMethod	(Ljava/lang/String;[Ljava/lang/Class;)Ljava/lang/reflect/Method;
    //   218: astore 5
    //   220: aload 5
    //   222: aconst_null
    //   223: iconst_0
    //   224: anewarray 56	java/lang/Object
    //   227: invokevirtual 62	java/lang/reflect/Method:invoke	(Ljava/lang/Object;[Ljava/lang/Object;)Ljava/lang/Object;
    //   230: astore 5
    //   232: aload 5
    //   234: checkcast 64	java/lang/Integer
    //   237: invokevirtual 68	java/lang/Integer:intValue	()I
    //   240: putstatic 70	uuuuuu/nnnono:b006Enn006Enn006E006E006E	I
    //   243: iload_1
    //   244: iload_2
    //   245: iadd
    //   246: iload_3
    //   247: imul
    //   248: iload 4
    //   250: irem
    //   251: getstatic 70	uuuuuu/nnnono:b006Enn006Enn006E006E006E	I
    //   254: if_icmpeq +90 -> 344
    //   257: ldc 2
    //   259: ldc_w 436
    //   262: bipush 65
    //   264: iconst_1
    //   265: invokestatic 50	xxxxxx/uxxxxx:bb00620062bb0062b0062b0062	(Ljava/lang/String;CC)Ljava/lang/String;
    //   268: iconst_0
    //   269: anewarray 34	java/lang/Class
    //   272: invokevirtual 54	java/lang/Class:getMethod	(Ljava/lang/String;[Ljava/lang/Class;)Ljava/lang/reflect/Method;
    //   275: astore 5
    //   277: aload 5
    //   279: aconst_null
    //   280: iconst_0
    //   281: anewarray 56	java/lang/Object
    //   284: invokevirtual 62	java/lang/reflect/Method:invoke	(Ljava/lang/Object;[Ljava/lang/Object;)Ljava/lang/Object;
    //   287: astore 5
    //   289: aload 5
    //   291: checkcast 64	java/lang/Integer
    //   294: invokevirtual 68	java/lang/Integer:intValue	()I
    //   297: putstatic 40	uuuuuu/nnnono:bnnn006Enn006E006E006E	I
    //   300: ldc 2
    //   302: ldc_w 438
    //   305: sipush 251
    //   308: iconst_1
    //   309: invokestatic 50	xxxxxx/uxxxxx:bb00620062bb0062b0062b0062	(Ljava/lang/String;CC)Ljava/lang/String;
    //   312: iconst_0
    //   313: anewarray 34	java/lang/Class
    //   316: invokevirtual 54	java/lang/Class:getMethod	(Ljava/lang/String;[Ljava/lang/Class;)Ljava/lang/reflect/Method;
    //   319: astore 5
    //   321: aload 5
    //   323: aconst_null
    //   324: iconst_0
    //   325: anewarray 56	java/lang/Object
    //   328: invokevirtual 62	java/lang/reflect/Method:invoke	(Ljava/lang/Object;[Ljava/lang/Object;)Ljava/lang/Object;
    //   331: astore 5
    //   333: aload 5
    //   335: checkcast 64	java/lang/Integer
    //   338: invokevirtual 68	java/lang/Integer:intValue	()I
    //   341: putstatic 70	uuuuuu/nnnono:b006Enn006Enn006E006E006E	I
    //   344: aload_0
    //   345: getfield 114	uuuuuu/nnnono:b006En006Ennn006E006E006E	Luuuuuu/nnoono;
    //   348: invokeinterface 441 1 0
    //   353: ifeq +81 -> 434
    //   356: ldc 2
    //   358: ldc_w 443
    //   361: sipush 166
    //   364: iconst_5
    //   365: invokestatic 50	xxxxxx/uxxxxx:bb00620062bb0062b0062b0062	(Ljava/lang/String;CC)Ljava/lang/String;
    //   368: iconst_0
    //   369: anewarray 34	java/lang/Class
    //   372: invokevirtual 54	java/lang/Class:getMethod	(Ljava/lang/String;[Ljava/lang/Class;)Ljava/lang/reflect/Method;
    //   375: astore 5
    //   377: aload 5
    //   379: aload_0
    //   380: iconst_0
    //   381: anewarray 56	java/lang/Object
    //   384: invokevirtual 62	java/lang/reflect/Method:invoke	(Ljava/lang/Object;[Ljava/lang/Object;)Ljava/lang/Object;
    //   387: astore 5
    //   389: aload 5
    //   391: checkcast 188	java/lang/Boolean
    //   394: invokevirtual 192	java/lang/Boolean:booleanValue	()Z
    //   397: ifeq +37 -> 434
    //   400: iconst_1
    //   401: ireturn
    //   402: astore 5
    //   404: aload 5
    //   406: invokevirtual 98	java/lang/reflect/InvocationTargetException:getCause	()Ljava/lang/Throwable;
    //   409: athrow
    //   410: astore 5
    //   412: aload 5
    //   414: invokevirtual 98	java/lang/reflect/InvocationTargetException:getCause	()Ljava/lang/Throwable;
    //   417: athrow
    //   418: astore 5
    //   420: aload 5
    //   422: invokevirtual 98	java/lang/reflect/InvocationTargetException:getCause	()Ljava/lang/Throwable;
    //   425: athrow
    //   426: astore 5
    //   428: aload 5
    //   430: invokevirtual 98	java/lang/reflect/InvocationTargetException:getCause	()Ljava/lang/Throwable;
    //   433: athrow
    //   434: iconst_0
    //   435: ireturn
    //   436: astore 5
    //   438: aload 5
    //   440: invokevirtual 98	java/lang/reflect/InvocationTargetException:getCause	()Ljava/lang/Throwable;
    //   443: athrow
    //   444: astore 5
    //   446: aload 5
    //   448: invokevirtual 98	java/lang/reflect/InvocationTargetException:getCause	()Ljava/lang/Throwable;
    //   451: athrow
    // Local variable table:
    //   start	length	slot	name	signature
    //   0	452	0	this	nnnono
    //   158	88	1	i	int
    //   162	84	2	j	int
    //   166	82	3	k	int
    //   170	81	4	m	int
    //   61	329	5	localObject	Object
    //   402	3	5	localInvocationTargetException1	java.lang.reflect.InvocationTargetException
    //   410	3	5	localInvocationTargetException2	java.lang.reflect.InvocationTargetException
    //   418	3	5	localInvocationTargetException3	java.lang.reflect.InvocationTargetException
    //   426	3	5	localInvocationTargetException4	java.lang.reflect.InvocationTargetException
    //   436	3	5	localInvocationTargetException5	java.lang.reflect.InvocationTargetException
    //   444	3	5	localInvocationTargetException6	java.lang.reflect.InvocationTargetException
    // Exception table:
    //   from	to	target	type
    //   63	75	402	java/lang/reflect/InvocationTargetException
    //   377	389	410	java/lang/reflect/InvocationTargetException
    //   277	289	418	java/lang/reflect/InvocationTargetException
    //   321	333	426	java/lang/reflect/InvocationTargetException
    //   132	144	436	java/lang/reflect/InvocationTargetException
    //   220	232	444	java/lang/reflect/InvocationTargetException
  }
}
