package uuuuuu;

import com.db.pwcc.dbmobile.secure.preferences.SharedPreferencesHelper;
import javax.inject.Inject;

public class nnoooo
  extends ssssst<tsssss.onoooo>
  implements tsssss.nooooo
{
  public static int b006E006E006E006E006E006E006En006E = 15;
  public static int b006Ennnnnn006E006E = 2;
  public static int bn006Ennnnn006E006E = 0;
  public static int bnnnnnnn006E006E = 1;
  @Inject
  public SharedPreferencesHelper bn006E006E006E006E006E006En006E;
  
  public nnoooo()
  {
    pqqppq.b006B006B006Bkkk006Bkkk().baaa0061006100610061006100610061(this);
  }
  
  public static int b006B006B006Bkkk006B006B006Bk()
  {
    return 1;
  }
  
  public static int b006B006Bk006Bkk006B006B006Bk()
  {
    return 0;
  }
  
  public static int b006Bkk006Bkk006B006B006Bk()
  {
    return 2;
  }
  
  public static int bk006Bk006Bkk006B006B006Bk()
  {
    return 15;
  }
  
  /* Error */
  public boolean b006Bk006B006Bkk006B006B006Bk()
  {
    // Byte code:
    //   0: aload_0
    //   1: getfield 49	uuuuuu/nnoooo:b006E006E006E006E006En006E006En	Luuuuuu/hyhyhh;
    //   4: invokevirtual 55	uuuuuu/hyhyhh:b0070pp007000700070p007000700070	()Ljava/lang/String;
    //   7: ifnull +107 -> 114
    //   10: getstatic 57	uuuuuu/nnoooo:b006E006E006E006E006E006E006En006E	I
    //   13: getstatic 59	uuuuuu/nnoooo:bnnnnnnn006E006E	I
    //   16: iadd
    //   17: getstatic 57	uuuuuu/nnoooo:b006E006E006E006E006E006E006En006E	I
    //   20: imul
    //   21: getstatic 61	uuuuuu/nnoooo:b006Ennnnnn006E006E	I
    //   24: irem
    //   25: getstatic 63	uuuuuu/nnoooo:bn006Ennnnn006E006E	I
    //   28: if_icmpeq +446 -> 474
    //   31: ldc 2
    //   33: ldc 65
    //   35: sipush 174
    //   38: sipush 223
    //   41: iconst_1
    //   42: invokestatic 71	xxxxxx/uxxxxx:bbbb0062b0062b0062b0062	(Ljava/lang/String;CCC)Ljava/lang/String;
    //   45: iconst_0
    //   46: anewarray 73	java/lang/Class
    //   49: invokevirtual 77	java/lang/Class:getMethod	(Ljava/lang/String;[Ljava/lang/Class;)Ljava/lang/reflect/Method;
    //   52: astore_3
    //   53: aload_3
    //   54: aconst_null
    //   55: iconst_0
    //   56: anewarray 79	java/lang/Object
    //   59: invokevirtual 85	java/lang/reflect/Method:invoke	(Ljava/lang/Object;[Ljava/lang/Object;)Ljava/lang/Object;
    //   62: astore_3
    //   63: aload_3
    //   64: checkcast 87	java/lang/Integer
    //   67: invokevirtual 90	java/lang/Integer:intValue	()I
    //   70: putstatic 57	uuuuuu/nnoooo:b006E006E006E006E006E006E006En006E	I
    //   73: ldc 2
    //   75: ldc 92
    //   77: sipush 129
    //   80: iconst_3
    //   81: invokestatic 96	xxxxxx/uxxxxx:bb00620062bb0062b0062b0062	(Ljava/lang/String;CC)Ljava/lang/String;
    //   84: iconst_0
    //   85: anewarray 73	java/lang/Class
    //   88: invokevirtual 77	java/lang/Class:getMethod	(Ljava/lang/String;[Ljava/lang/Class;)Ljava/lang/reflect/Method;
    //   91: astore_3
    //   92: aload_3
    //   93: aconst_null
    //   94: iconst_0
    //   95: anewarray 79	java/lang/Object
    //   98: invokevirtual 85	java/lang/reflect/Method:invoke	(Ljava/lang/Object;[Ljava/lang/Object;)Ljava/lang/Object;
    //   101: astore_3
    //   102: aload_3
    //   103: checkcast 87	java/lang/Integer
    //   106: invokevirtual 90	java/lang/Integer:intValue	()I
    //   109: putstatic 63	uuuuuu/nnoooo:bn006Ennnnn006E006E	I
    //   112: iconst_1
    //   113: ireturn
    //   114: getstatic 57	uuuuuu/nnoooo:b006E006E006E006E006E006E006En006E	I
    //   117: getstatic 59	uuuuuu/nnoooo:bnnnnnnn006E006E	I
    //   120: iadd
    //   121: getstatic 57	uuuuuu/nnoooo:b006E006E006E006E006E006E006En006E	I
    //   124: imul
    //   125: getstatic 61	uuuuuu/nnoooo:b006Ennnnnn006E006E	I
    //   128: irem
    //   129: getstatic 63	uuuuuu/nnoooo:bn006Ennnnn006E006E	I
    //   132: if_icmpeq +292 -> 424
    //   135: bipush 72
    //   137: putstatic 57	uuuuuu/nnoooo:b006E006E006E006E006E006E006En006E	I
    //   140: ldc 2
    //   142: ldc 98
    //   144: sipush 148
    //   147: iconst_4
    //   148: invokestatic 96	xxxxxx/uxxxxx:bb00620062bb0062b0062b0062	(Ljava/lang/String;CC)Ljava/lang/String;
    //   151: iconst_0
    //   152: anewarray 73	java/lang/Class
    //   155: invokevirtual 77	java/lang/Class:getMethod	(Ljava/lang/String;[Ljava/lang/Class;)Ljava/lang/reflect/Method;
    //   158: astore_3
    //   159: aload_3
    //   160: aconst_null
    //   161: iconst_0
    //   162: anewarray 79	java/lang/Object
    //   165: invokevirtual 85	java/lang/reflect/Method:invoke	(Ljava/lang/Object;[Ljava/lang/Object;)Ljava/lang/Object;
    //   168: astore_3
    //   169: aload_3
    //   170: checkcast 87	java/lang/Integer
    //   173: invokevirtual 90	java/lang/Integer:intValue	()I
    //   176: putstatic 63	uuuuuu/nnoooo:bn006Ennnnn006E006E	I
    //   179: getstatic 57	uuuuuu/nnoooo:b006E006E006E006E006E006E006En006E	I
    //   182: istore_1
    //   183: getstatic 59	uuuuuu/nnoooo:bnnnnnnn006E006E	I
    //   186: istore_2
    //   187: ldc 2
    //   189: ldc 100
    //   191: bipush 118
    //   193: iconst_3
    //   194: invokestatic 96	xxxxxx/uxxxxx:bb00620062bb0062b0062b0062	(Ljava/lang/String;CC)Ljava/lang/String;
    //   197: iconst_0
    //   198: anewarray 73	java/lang/Class
    //   201: invokevirtual 77	java/lang/Class:getMethod	(Ljava/lang/String;[Ljava/lang/Class;)Ljava/lang/reflect/Method;
    //   204: astore_3
    //   205: aload_3
    //   206: aconst_null
    //   207: iconst_0
    //   208: anewarray 79	java/lang/Object
    //   211: invokevirtual 85	java/lang/reflect/Method:invoke	(Ljava/lang/Object;[Ljava/lang/Object;)Ljava/lang/Object;
    //   214: astore_3
    //   215: iload_2
    //   216: iload_1
    //   217: iadd
    //   218: iload_1
    //   219: imul
    //   220: aload_3
    //   221: checkcast 87	java/lang/Integer
    //   224: invokevirtual 90	java/lang/Integer:intValue	()I
    //   227: irem
    //   228: tableswitch	default:+20->248, 0:+196->424
    //   248: ldc 2
    //   250: ldc 102
    //   252: bipush 86
    //   254: iconst_0
    //   255: invokestatic 96	xxxxxx/uxxxxx:bb00620062bb0062b0062b0062	(Ljava/lang/String;CC)Ljava/lang/String;
    //   258: iconst_0
    //   259: anewarray 73	java/lang/Class
    //   262: invokevirtual 77	java/lang/Class:getMethod	(Ljava/lang/String;[Ljava/lang/Class;)Ljava/lang/reflect/Method;
    //   265: astore_3
    //   266: aload_3
    //   267: aconst_null
    //   268: iconst_0
    //   269: anewarray 79	java/lang/Object
    //   272: invokevirtual 85	java/lang/reflect/Method:invoke	(Ljava/lang/Object;[Ljava/lang/Object;)Ljava/lang/Object;
    //   275: astore_3
    //   276: aload_3
    //   277: checkcast 87	java/lang/Integer
    //   280: invokevirtual 90	java/lang/Integer:intValue	()I
    //   283: putstatic 57	uuuuuu/nnoooo:b006E006E006E006E006E006E006En006E	I
    //   286: getstatic 57	uuuuuu/nnoooo:b006E006E006E006E006E006E006En006E	I
    //   289: istore_1
    //   290: ldc 2
    //   292: ldc 104
    //   294: sipush 255
    //   297: iconst_2
    //   298: invokestatic 96	xxxxxx/uxxxxx:bb00620062bb0062b0062b0062	(Ljava/lang/String;CC)Ljava/lang/String;
    //   301: iconst_0
    //   302: anewarray 73	java/lang/Class
    //   305: invokevirtual 77	java/lang/Class:getMethod	(Ljava/lang/String;[Ljava/lang/Class;)Ljava/lang/reflect/Method;
    //   308: astore_3
    //   309: aload_3
    //   310: aconst_null
    //   311: iconst_0
    //   312: anewarray 79	java/lang/Object
    //   315: invokevirtual 85	java/lang/reflect/Method:invoke	(Ljava/lang/Object;[Ljava/lang/Object;)Ljava/lang/Object;
    //   318: astore_3
    //   319: aload_3
    //   320: checkcast 87	java/lang/Integer
    //   323: invokevirtual 90	java/lang/Integer:intValue	()I
    //   326: iload_1
    //   327: iadd
    //   328: getstatic 57	uuuuuu/nnoooo:b006E006E006E006E006E006E006En006E	I
    //   331: imul
    //   332: getstatic 61	uuuuuu/nnoooo:b006Ennnnnn006E006E	I
    //   335: irem
    //   336: getstatic 63	uuuuuu/nnoooo:bn006Ennnnn006E006E	I
    //   339: if_icmpeq +81 -> 420
    //   342: ldc 2
    //   344: ldc 106
    //   346: sipush 222
    //   349: iconst_0
    //   350: invokestatic 96	xxxxxx/uxxxxx:bb00620062bb0062b0062b0062	(Ljava/lang/String;CC)Ljava/lang/String;
    //   353: iconst_0
    //   354: anewarray 73	java/lang/Class
    //   357: invokevirtual 77	java/lang/Class:getMethod	(Ljava/lang/String;[Ljava/lang/Class;)Ljava/lang/reflect/Method;
    //   360: astore_3
    //   361: aload_3
    //   362: aconst_null
    //   363: iconst_0
    //   364: anewarray 79	java/lang/Object
    //   367: invokevirtual 85	java/lang/reflect/Method:invoke	(Ljava/lang/Object;[Ljava/lang/Object;)Ljava/lang/Object;
    //   370: astore_3
    //   371: aload_3
    //   372: checkcast 87	java/lang/Integer
    //   375: invokevirtual 90	java/lang/Integer:intValue	()I
    //   378: putstatic 57	uuuuuu/nnoooo:b006E006E006E006E006E006E006En006E	I
    //   381: ldc 2
    //   383: ldc 108
    //   385: sipush 156
    //   388: iconst_5
    //   389: invokestatic 96	xxxxxx/uxxxxx:bb00620062bb0062b0062b0062	(Ljava/lang/String;CC)Ljava/lang/String;
    //   392: iconst_0
    //   393: anewarray 73	java/lang/Class
    //   396: invokevirtual 77	java/lang/Class:getMethod	(Ljava/lang/String;[Ljava/lang/Class;)Ljava/lang/reflect/Method;
    //   399: astore_3
    //   400: aload_3
    //   401: aconst_null
    //   402: iconst_0
    //   403: anewarray 79	java/lang/Object
    //   406: invokevirtual 85	java/lang/reflect/Method:invoke	(Ljava/lang/Object;[Ljava/lang/Object;)Ljava/lang/Object;
    //   409: astore_3
    //   410: aload_3
    //   411: checkcast 87	java/lang/Integer
    //   414: invokevirtual 90	java/lang/Integer:intValue	()I
    //   417: putstatic 63	uuuuuu/nnoooo:bn006Ennnnn006E006E	I
    //   420: iconst_1
    //   421: putstatic 63	uuuuuu/nnoooo:bn006Ennnnn006E006E	I
    //   424: iconst_0
    //   425: ireturn
    //   426: astore_3
    //   427: aload_3
    //   428: invokevirtual 112	java/lang/reflect/InvocationTargetException:getCause	()Ljava/lang/Throwable;
    //   431: athrow
    //   432: astore_3
    //   433: aload_3
    //   434: invokevirtual 112	java/lang/reflect/InvocationTargetException:getCause	()Ljava/lang/Throwable;
    //   437: athrow
    //   438: astore_3
    //   439: aload_3
    //   440: invokevirtual 112	java/lang/reflect/InvocationTargetException:getCause	()Ljava/lang/Throwable;
    //   443: athrow
    //   444: astore_3
    //   445: aload_3
    //   446: invokevirtual 112	java/lang/reflect/InvocationTargetException:getCause	()Ljava/lang/Throwable;
    //   449: athrow
    //   450: astore_3
    //   451: aload_3
    //   452: invokevirtual 112	java/lang/reflect/InvocationTargetException:getCause	()Ljava/lang/Throwable;
    //   455: athrow
    //   456: astore_3
    //   457: aload_3
    //   458: invokevirtual 112	java/lang/reflect/InvocationTargetException:getCause	()Ljava/lang/Throwable;
    //   461: athrow
    //   462: astore_3
    //   463: aload_3
    //   464: invokevirtual 112	java/lang/reflect/InvocationTargetException:getCause	()Ljava/lang/Throwable;
    //   467: athrow
    //   468: astore_3
    //   469: aload_3
    //   470: invokevirtual 112	java/lang/reflect/InvocationTargetException:getCause	()Ljava/lang/Throwable;
    //   473: athrow
    //   474: iconst_1
    //   475: ireturn
    // Local variable table:
    //   start	length	slot	name	signature
    //   0	476	0	this	nnoooo
    //   182	146	1	i	int
    //   186	32	2	j	int
    //   52	359	3	localObject	Object
    //   426	2	3	localInvocationTargetException1	java.lang.reflect.InvocationTargetException
    //   432	2	3	localInvocationTargetException2	java.lang.reflect.InvocationTargetException
    //   438	2	3	localInvocationTargetException3	java.lang.reflect.InvocationTargetException
    //   444	2	3	localInvocationTargetException4	java.lang.reflect.InvocationTargetException
    //   450	2	3	localInvocationTargetException5	java.lang.reflect.InvocationTargetException
    //   456	2	3	localInvocationTargetException6	java.lang.reflect.InvocationTargetException
    //   462	2	3	localInvocationTargetException7	java.lang.reflect.InvocationTargetException
    //   468	2	3	localInvocationTargetException8	java.lang.reflect.InvocationTargetException
    // Exception table:
    //   from	to	target	type
    //   159	169	426	java/lang/reflect/InvocationTargetException
    //   309	319	432	java/lang/reflect/InvocationTargetException
    //   205	215	438	java/lang/reflect/InvocationTargetException
    //   266	276	444	java/lang/reflect/InvocationTargetException
    //   53	63	450	java/lang/reflect/InvocationTargetException
    //   92	102	456	java/lang/reflect/InvocationTargetException
    //   361	371	462	java/lang/reflect/InvocationTargetException
    //   400	410	468	java/lang/reflect/InvocationTargetException
  }
  
  /* Error */
  public void bk006B006Bkkk006B006B006Bk(boolean paramBoolean)
  {
    // Byte code:
    //   0: getstatic 146	uuuuuu/vvrvrv:bh0068h0068h0068006800680068	Luuuuuu/vvrvrv;
    //   3: invokestatic 152	uuuuuu/rrvvrv:b0071q0071qq0071q0071q0071	(Luuuuuu/vvrvrv;)V
    //   6: aload_0
    //   7: getfield 154	uuuuuu/nnoooo:bn006E006E006E006E006E006En006E	Lcom/db/pwcc/dbmobile/secure/preferences/SharedPreferencesHelper;
    //   10: astore 9
    //   12: getstatic 57	uuuuuu/nnoooo:b006E006E006E006E006E006E006En006E	I
    //   15: istore_2
    //   16: getstatic 59	uuuuuu/nnoooo:bnnnnnnn006E006E	I
    //   19: istore_3
    //   20: getstatic 57	uuuuuu/nnoooo:b006E006E006E006E006E006E006En006E	I
    //   23: getstatic 59	uuuuuu/nnoooo:bnnnnnnn006E006E	I
    //   26: iadd
    //   27: getstatic 57	uuuuuu/nnoooo:b006E006E006E006E006E006E006En006E	I
    //   30: imul
    //   31: getstatic 61	uuuuuu/nnoooo:b006Ennnnnn006E006E	I
    //   34: irem
    //   35: getstatic 63	uuuuuu/nnoooo:bn006Ennnnn006E006E	I
    //   38: if_icmpeq +13 -> 51
    //   41: bipush 21
    //   43: putstatic 57	uuuuuu/nnoooo:b006E006E006E006E006E006E006En006E	I
    //   46: bipush 34
    //   48: putstatic 63	uuuuuu/nnoooo:bn006Ennnnn006E006E	I
    //   51: getstatic 57	uuuuuu/nnoooo:b006E006E006E006E006E006E006En006E	I
    //   54: istore 4
    //   56: getstatic 57	uuuuuu/nnoooo:b006E006E006E006E006E006E006En006E	I
    //   59: istore 5
    //   61: getstatic 59	uuuuuu/nnoooo:bnnnnnnn006E006E	I
    //   64: istore 6
    //   66: getstatic 57	uuuuuu/nnoooo:b006E006E006E006E006E006E006En006E	I
    //   69: istore 7
    //   71: getstatic 61	uuuuuu/nnoooo:b006Ennnnnn006E006E	I
    //   74: istore 8
    //   76: ldc 2
    //   78: ldc -100
    //   80: sipush 149
    //   83: sipush 140
    //   86: iconst_0
    //   87: invokestatic 71	xxxxxx/uxxxxx:bbbb0062b0062b0062b0062	(Ljava/lang/String;CCC)Ljava/lang/String;
    //   90: iconst_0
    //   91: anewarray 73	java/lang/Class
    //   94: invokevirtual 77	java/lang/Class:getMethod	(Ljava/lang/String;[Ljava/lang/Class;)Ljava/lang/reflect/Method;
    //   97: astore 10
    //   99: aload 10
    //   101: aconst_null
    //   102: iconst_0
    //   103: anewarray 79	java/lang/Object
    //   106: invokevirtual 85	java/lang/reflect/Method:invoke	(Ljava/lang/Object;[Ljava/lang/Object;)Ljava/lang/Object;
    //   109: astore 10
    //   111: iload 5
    //   113: iload 6
    //   115: iadd
    //   116: iload 7
    //   118: imul
    //   119: iload 8
    //   121: irem
    //   122: aload 10
    //   124: checkcast 87	java/lang/Integer
    //   127: invokevirtual 90	java/lang/Integer:intValue	()I
    //   130: if_icmpeq +13 -> 143
    //   133: bipush 44
    //   135: putstatic 57	uuuuuu/nnoooo:b006E006E006E006E006E006E006En006E	I
    //   138: bipush 84
    //   140: putstatic 63	uuuuuu/nnoooo:bn006Ennnnn006E006E	I
    //   143: iload_3
    //   144: iload_2
    //   145: iadd
    //   146: iload 4
    //   148: imul
    //   149: getstatic 61	uuuuuu/nnoooo:b006Ennnnnn006E006E	I
    //   152: irem
    //   153: getstatic 63	uuuuuu/nnoooo:bn006Ennnnn006E006E	I
    //   156: if_icmpeq +119 -> 275
    //   159: getstatic 57	uuuuuu/nnoooo:b006E006E006E006E006E006E006En006E	I
    //   162: getstatic 59	uuuuuu/nnoooo:bnnnnnnn006E006E	I
    //   165: iadd
    //   166: getstatic 57	uuuuuu/nnoooo:b006E006E006E006E006E006E006En006E	I
    //   169: imul
    //   170: getstatic 61	uuuuuu/nnoooo:b006Ennnnnn006E006E	I
    //   173: irem
    //   174: getstatic 63	uuuuuu/nnoooo:bn006Ennnnn006E006E	I
    //   177: if_icmpeq +88 -> 265
    //   180: ldc 2
    //   182: ldc -98
    //   184: sipush 190
    //   187: iconst_3
    //   188: invokestatic 96	xxxxxx/uxxxxx:bb00620062bb0062b0062b0062	(Ljava/lang/String;CC)Ljava/lang/String;
    //   191: iconst_0
    //   192: anewarray 73	java/lang/Class
    //   195: invokevirtual 77	java/lang/Class:getMethod	(Ljava/lang/String;[Ljava/lang/Class;)Ljava/lang/reflect/Method;
    //   198: astore 10
    //   200: aload 10
    //   202: aconst_null
    //   203: iconst_0
    //   204: anewarray 79	java/lang/Object
    //   207: invokevirtual 85	java/lang/reflect/Method:invoke	(Ljava/lang/Object;[Ljava/lang/Object;)Ljava/lang/Object;
    //   210: astore 10
    //   212: aload 10
    //   214: checkcast 87	java/lang/Integer
    //   217: invokevirtual 90	java/lang/Integer:intValue	()I
    //   220: putstatic 57	uuuuuu/nnoooo:b006E006E006E006E006E006E006En006E	I
    //   223: ldc 2
    //   225: ldc -96
    //   227: bipush 85
    //   229: iconst_0
    //   230: invokestatic 96	xxxxxx/uxxxxx:bb00620062bb0062b0062b0062	(Ljava/lang/String;CC)Ljava/lang/String;
    //   233: iconst_0
    //   234: anewarray 73	java/lang/Class
    //   237: invokevirtual 77	java/lang/Class:getMethod	(Ljava/lang/String;[Ljava/lang/Class;)Ljava/lang/reflect/Method;
    //   240: astore 10
    //   242: aload 10
    //   244: aconst_null
    //   245: iconst_0
    //   246: anewarray 79	java/lang/Object
    //   249: invokevirtual 85	java/lang/reflect/Method:invoke	(Ljava/lang/Object;[Ljava/lang/Object;)Ljava/lang/Object;
    //   252: astore 10
    //   254: aload 10
    //   256: checkcast 87	java/lang/Integer
    //   259: invokevirtual 90	java/lang/Integer:intValue	()I
    //   262: putstatic 63	uuuuuu/nnoooo:bn006Ennnnn006E006E	I
    //   265: bipush 98
    //   267: putstatic 57	uuuuuu/nnoooo:b006E006E006E006E006E006E006En006E	I
    //   270: bipush 64
    //   272: putstatic 63	uuuuuu/nnoooo:bn006Ennnnn006E006E	I
    //   275: ldc -94
    //   277: ldc -92
    //   279: bipush 122
    //   281: iconst_4
    //   282: invokestatic 96	xxxxxx/uxxxxx:bb00620062bb0062b0062b0062	(Ljava/lang/String;CC)Ljava/lang/String;
    //   285: iconst_1
    //   286: anewarray 73	java/lang/Class
    //   289: dup
    //   290: iconst_0
    //   291: getstatic 170	java/lang/Boolean:TYPE	Ljava/lang/Class;
    //   294: aastore
    //   295: invokevirtual 77	java/lang/Class:getMethod	(Ljava/lang/String;[Ljava/lang/Class;)Ljava/lang/reflect/Method;
    //   298: astore 10
    //   300: aload 10
    //   302: aload 9
    //   304: iconst_1
    //   305: anewarray 79	java/lang/Object
    //   308: dup
    //   309: iconst_0
    //   310: iload_1
    //   311: invokestatic 174	java/lang/Boolean:valueOf	(Z)Ljava/lang/Boolean;
    //   314: aastore
    //   315: invokevirtual 85	java/lang/reflect/Method:invoke	(Ljava/lang/Object;[Ljava/lang/Object;)Ljava/lang/Object;
    //   318: pop
    //   319: ldc 2
    //   321: ldc -80
    //   323: sipush 133
    //   326: iconst_4
    //   327: invokestatic 96	xxxxxx/uxxxxx:bb00620062bb0062b0062b0062	(Ljava/lang/String;CC)Ljava/lang/String;
    //   330: iconst_0
    //   331: anewarray 73	java/lang/Class
    //   334: invokevirtual 77	java/lang/Class:getMethod	(Ljava/lang/String;[Ljava/lang/Class;)Ljava/lang/reflect/Method;
    //   337: astore 9
    //   339: aload 9
    //   341: aload_0
    //   342: iconst_0
    //   343: anewarray 79	java/lang/Object
    //   346: invokevirtual 85	java/lang/reflect/Method:invoke	(Ljava/lang/Object;[Ljava/lang/Object;)Ljava/lang/Object;
    //   349: pop
    //   350: return
    //   351: astore 9
    //   353: aload 9
    //   355: invokevirtual 112	java/lang/reflect/InvocationTargetException:getCause	()Ljava/lang/Throwable;
    //   358: athrow
    //   359: astore 9
    //   361: aload 9
    //   363: invokevirtual 112	java/lang/reflect/InvocationTargetException:getCause	()Ljava/lang/Throwable;
    //   366: athrow
    //   367: astore 9
    //   369: aload 9
    //   371: invokevirtual 112	java/lang/reflect/InvocationTargetException:getCause	()Ljava/lang/Throwable;
    //   374: athrow
    //   375: astore 9
    //   377: aload 9
    //   379: invokevirtual 112	java/lang/reflect/InvocationTargetException:getCause	()Ljava/lang/Throwable;
    //   382: athrow
    //   383: astore 9
    //   385: aload 9
    //   387: invokevirtual 112	java/lang/reflect/InvocationTargetException:getCause	()Ljava/lang/Throwable;
    //   390: athrow
    // Local variable table:
    //   start	length	slot	name	signature
    //   0	391	0	this	nnoooo
    //   0	391	1	paramBoolean	boolean
    //   15	131	2	i	int
    //   19	127	3	j	int
    //   54	95	4	k	int
    //   59	57	5	m	int
    //   64	52	6	n	int
    //   69	50	7	i1	int
    //   74	48	8	i2	int
    //   10	330	9	localObject1	Object
    //   351	3	9	localInvocationTargetException1	java.lang.reflect.InvocationTargetException
    //   359	3	9	localInvocationTargetException2	java.lang.reflect.InvocationTargetException
    //   367	3	9	localInvocationTargetException3	java.lang.reflect.InvocationTargetException
    //   375	3	9	localInvocationTargetException4	java.lang.reflect.InvocationTargetException
    //   383	3	9	localInvocationTargetException5	java.lang.reflect.InvocationTargetException
    //   97	204	10	localObject2	Object
    // Exception table:
    //   from	to	target	type
    //   99	111	351	java/lang/reflect/InvocationTargetException
    //   300	319	359	java/lang/reflect/InvocationTargetException
    //   339	350	367	java/lang/reflect/InvocationTargetException
    //   200	212	375	java/lang/reflect/InvocationTargetException
    //   242	254	383	java/lang/reflect/InvocationTargetException
  }
  
  /* Error */
  public void bkk006B006Bkk006B006B006Bk()
  {
    // Byte code:
    //   0: getstatic 57	uuuuuu/nnoooo:b006E006E006E006E006E006E006En006E	I
    //   3: istore_1
    //   4: iload_1
    //   5: getstatic 59	uuuuuu/nnoooo:bnnnnnnn006E006E	I
    //   8: iload_1
    //   9: iadd
    //   10: imul
    //   11: getstatic 61	uuuuuu/nnoooo:b006Ennnnnn006E006E	I
    //   14: irem
    //   15: tableswitch	default:+17->32, 0:+63->78
    //   32: ldc 2
    //   34: ldc -77
    //   36: bipush 85
    //   38: sipush 182
    //   41: iconst_3
    //   42: invokestatic 71	xxxxxx/uxxxxx:bbbb0062b0062b0062b0062	(Ljava/lang/String;CCC)Ljava/lang/String;
    //   45: iconst_0
    //   46: anewarray 73	java/lang/Class
    //   49: invokevirtual 77	java/lang/Class:getMethod	(Ljava/lang/String;[Ljava/lang/Class;)Ljava/lang/reflect/Method;
    //   52: astore_3
    //   53: aload_3
    //   54: aconst_null
    //   55: iconst_0
    //   56: anewarray 79	java/lang/Object
    //   59: invokevirtual 85	java/lang/reflect/Method:invoke	(Ljava/lang/Object;[Ljava/lang/Object;)Ljava/lang/Object;
    //   62: astore_3
    //   63: aload_3
    //   64: checkcast 87	java/lang/Integer
    //   67: invokevirtual 90	java/lang/Integer:intValue	()I
    //   70: putstatic 57	uuuuuu/nnoooo:b006E006E006E006E006E006E006En006E	I
    //   73: bipush 74
    //   75: putstatic 63	uuuuuu/nnoooo:bn006Ennnnn006E006E	I
    //   78: ldc 2
    //   80: ldc -75
    //   82: bipush 45
    //   84: bipush 117
    //   86: iconst_0
    //   87: invokestatic 71	xxxxxx/uxxxxx:bbbb0062b0062b0062b0062	(Ljava/lang/String;CCC)Ljava/lang/String;
    //   90: iconst_0
    //   91: anewarray 73	java/lang/Class
    //   94: invokevirtual 77	java/lang/Class:getMethod	(Ljava/lang/String;[Ljava/lang/Class;)Ljava/lang/reflect/Method;
    //   97: astore_3
    //   98: aload_3
    //   99: aload_0
    //   100: iconst_0
    //   101: anewarray 79	java/lang/Object
    //   104: invokevirtual 85	java/lang/reflect/Method:invoke	(Ljava/lang/Object;[Ljava/lang/Object;)Ljava/lang/Object;
    //   107: astore_3
    //   108: aload_3
    //   109: checkcast 166	java/lang/Boolean
    //   112: invokevirtual 184	java/lang/Boolean:booleanValue	()Z
    //   115: istore_2
    //   116: getstatic 57	uuuuuu/nnoooo:b006E006E006E006E006E006E006En006E	I
    //   119: istore_1
    //   120: iload_1
    //   121: getstatic 59	uuuuuu/nnoooo:bnnnnnnn006E006E	I
    //   124: iload_1
    //   125: iadd
    //   126: imul
    //   127: getstatic 61	uuuuuu/nnoooo:b006Ennnnnn006E006E	I
    //   130: irem
    //   131: tableswitch	default:+17->148, 0:+60->191
    //   148: ldc 2
    //   150: ldc -70
    //   152: bipush 13
    //   154: iconst_4
    //   155: invokestatic 96	xxxxxx/uxxxxx:bb00620062bb0062b0062b0062	(Ljava/lang/String;CC)Ljava/lang/String;
    //   158: iconst_0
    //   159: anewarray 73	java/lang/Class
    //   162: invokevirtual 77	java/lang/Class:getMethod	(Ljava/lang/String;[Ljava/lang/Class;)Ljava/lang/reflect/Method;
    //   165: astore_3
    //   166: aload_3
    //   167: aconst_null
    //   168: iconst_0
    //   169: anewarray 79	java/lang/Object
    //   172: invokevirtual 85	java/lang/reflect/Method:invoke	(Ljava/lang/Object;[Ljava/lang/Object;)Ljava/lang/Object;
    //   175: astore_3
    //   176: aload_3
    //   177: checkcast 87	java/lang/Integer
    //   180: invokevirtual 90	java/lang/Integer:intValue	()I
    //   183: putstatic 57	uuuuuu/nnoooo:b006E006E006E006E006E006E006En006E	I
    //   186: bipush 30
    //   188: putstatic 63	uuuuuu/nnoooo:bn006Ennnnn006E006E	I
    //   191: iload_2
    //   192: ifeq +213 -> 405
    //   195: aload_0
    //   196: getfield 154	uuuuuu/nnoooo:bn006E006E006E006E006E006En006E	Lcom/db/pwcc/dbmobile/secure/preferences/SharedPreferencesHelper;
    //   199: astore_3
    //   200: ldc -94
    //   202: ldc -68
    //   204: bipush 43
    //   206: iconst_1
    //   207: invokestatic 96	xxxxxx/uxxxxx:bb00620062bb0062b0062b0062	(Ljava/lang/String;CC)Ljava/lang/String;
    //   210: iconst_1
    //   211: anewarray 73	java/lang/Class
    //   214: dup
    //   215: iconst_0
    //   216: getstatic 170	java/lang/Boolean:TYPE	Ljava/lang/Class;
    //   219: aastore
    //   220: invokevirtual 77	java/lang/Class:getMethod	(Ljava/lang/String;[Ljava/lang/Class;)Ljava/lang/reflect/Method;
    //   223: astore 4
    //   225: aload 4
    //   227: aload_3
    //   228: iconst_1
    //   229: anewarray 79	java/lang/Object
    //   232: dup
    //   233: iconst_0
    //   234: iconst_1
    //   235: invokestatic 174	java/lang/Boolean:valueOf	(Z)Ljava/lang/Boolean;
    //   238: aastore
    //   239: invokevirtual 85	java/lang/reflect/Method:invoke	(Ljava/lang/Object;[Ljava/lang/Object;)Ljava/lang/Object;
    //   242: astore_3
    //   243: aload_3
    //   244: checkcast 166	java/lang/Boolean
    //   247: invokevirtual 184	java/lang/Boolean:booleanValue	()Z
    //   250: istore_2
    //   251: iload_2
    //   252: ifeq +160 -> 412
    //   255: getstatic 193	com/db/pwcc/dbmobile/foundation/R$string:settings_label_active	I
    //   258: istore_1
    //   259: getstatic 57	uuuuuu/nnoooo:b006E006E006E006E006E006E006En006E	I
    //   262: getstatic 59	uuuuuu/nnoooo:bnnnnnnn006E006E	I
    //   265: iadd
    //   266: getstatic 57	uuuuuu/nnoooo:b006E006E006E006E006E006E006En006E	I
    //   269: imul
    //   270: getstatic 61	uuuuuu/nnoooo:b006Ennnnnn006E006E	I
    //   273: irem
    //   274: getstatic 63	uuuuuu/nnoooo:bn006Ennnnn006E006E	I
    //   277: if_icmpeq +114 -> 391
    //   280: bipush 61
    //   282: putstatic 57	uuuuuu/nnoooo:b006E006E006E006E006E006E006En006E	I
    //   285: ldc 2
    //   287: ldc -61
    //   289: sipush 242
    //   292: iconst_1
    //   293: invokestatic 96	xxxxxx/uxxxxx:bb00620062bb0062b0062b0062	(Ljava/lang/String;CC)Ljava/lang/String;
    //   296: iconst_0
    //   297: anewarray 73	java/lang/Class
    //   300: invokevirtual 77	java/lang/Class:getMethod	(Ljava/lang/String;[Ljava/lang/Class;)Ljava/lang/reflect/Method;
    //   303: astore_3
    //   304: aload_3
    //   305: aconst_null
    //   306: iconst_0
    //   307: anewarray 79	java/lang/Object
    //   310: invokevirtual 85	java/lang/reflect/Method:invoke	(Ljava/lang/Object;[Ljava/lang/Object;)Ljava/lang/Object;
    //   313: astore_3
    //   314: aload_3
    //   315: checkcast 87	java/lang/Integer
    //   318: invokevirtual 90	java/lang/Integer:intValue	()I
    //   321: putstatic 63	uuuuuu/nnoooo:bn006Ennnnn006E006E	I
    //   324: getstatic 57	uuuuuu/nnoooo:b006E006E006E006E006E006E006En006E	I
    //   327: getstatic 59	uuuuuu/nnoooo:bnnnnnnn006E006E	I
    //   330: iadd
    //   331: getstatic 57	uuuuuu/nnoooo:b006E006E006E006E006E006E006En006E	I
    //   334: imul
    //   335: getstatic 61	uuuuuu/nnoooo:b006Ennnnnn006E006E	I
    //   338: irem
    //   339: getstatic 63	uuuuuu/nnoooo:bn006Ennnnn006E006E	I
    //   342: if_icmpeq +49 -> 391
    //   345: ldc 2
    //   347: ldc -59
    //   349: bipush 87
    //   351: sipush 245
    //   354: iconst_2
    //   355: invokestatic 71	xxxxxx/uxxxxx:bbbb0062b0062b0062b0062	(Ljava/lang/String;CCC)Ljava/lang/String;
    //   358: iconst_0
    //   359: anewarray 73	java/lang/Class
    //   362: invokevirtual 77	java/lang/Class:getMethod	(Ljava/lang/String;[Ljava/lang/Class;)Ljava/lang/reflect/Method;
    //   365: astore_3
    //   366: aload_3
    //   367: aconst_null
    //   368: iconst_0
    //   369: anewarray 79	java/lang/Object
    //   372: invokevirtual 85	java/lang/reflect/Method:invoke	(Ljava/lang/Object;[Ljava/lang/Object;)Ljava/lang/Object;
    //   375: astore_3
    //   376: aload_3
    //   377: checkcast 87	java/lang/Integer
    //   380: invokevirtual 90	java/lang/Integer:intValue	()I
    //   383: putstatic 57	uuuuuu/nnoooo:b006E006E006E006E006E006E006En006E	I
    //   386: bipush 49
    //   388: putstatic 63	uuuuuu/nnoooo:bn006Ennnnn006E006E	I
    //   391: aload_0
    //   392: getfield 201	uuuuuu/nnoooo:bnnnnn006E006E006En	Luuuuuu/ttssst$tsssst;
    //   395: checkcast 136	uuuuuu/tsssss$onoooo
    //   398: iload_2
    //   399: iload_1
    //   400: invokeinterface 205 3 0
    //   405: return
    //   406: astore_3
    //   407: aload_3
    //   408: invokevirtual 112	java/lang/reflect/InvocationTargetException:getCause	()Ljava/lang/Throwable;
    //   411: athrow
    //   412: getstatic 208	com/db/pwcc/dbmobile/foundation/R$string:settings_label_inactive	I
    //   415: istore_1
    //   416: goto -157 -> 259
    //   419: astore_3
    //   420: aload_3
    //   421: invokevirtual 112	java/lang/reflect/InvocationTargetException:getCause	()Ljava/lang/Throwable;
    //   424: athrow
    //   425: astore_3
    //   426: aload_3
    //   427: invokevirtual 112	java/lang/reflect/InvocationTargetException:getCause	()Ljava/lang/Throwable;
    //   430: athrow
    //   431: astore_3
    //   432: aload_3
    //   433: invokevirtual 112	java/lang/reflect/InvocationTargetException:getCause	()Ljava/lang/Throwable;
    //   436: athrow
    //   437: astore_3
    //   438: aload_3
    //   439: invokevirtual 112	java/lang/reflect/InvocationTargetException:getCause	()Ljava/lang/Throwable;
    //   442: athrow
    //   443: astore_3
    //   444: aload_3
    //   445: invokevirtual 112	java/lang/reflect/InvocationTargetException:getCause	()Ljava/lang/Throwable;
    //   448: athrow
    // Local variable table:
    //   start	length	slot	name	signature
    //   0	449	0	this	nnoooo
    //   3	413	1	i	int
    //   115	284	2	bool	boolean
    //   52	325	3	localObject	Object
    //   406	2	3	localInvocationTargetException1	java.lang.reflect.InvocationTargetException
    //   419	2	3	localInvocationTargetException2	java.lang.reflect.InvocationTargetException
    //   425	2	3	localInvocationTargetException3	java.lang.reflect.InvocationTargetException
    //   431	2	3	localInvocationTargetException4	java.lang.reflect.InvocationTargetException
    //   437	2	3	localInvocationTargetException5	java.lang.reflect.InvocationTargetException
    //   443	2	3	localInvocationTargetException6	java.lang.reflect.InvocationTargetException
    //   223	3	4	localMethod	java.lang.reflect.Method
    // Exception table:
    //   from	to	target	type
    //   166	176	406	java/lang/reflect/InvocationTargetException
    //   98	108	419	java/lang/reflect/InvocationTargetException
    //   225	243	425	java/lang/reflect/InvocationTargetException
    //   304	314	431	java/lang/reflect/InvocationTargetException
    //   53	63	437	java/lang/reflect/InvocationTargetException
    //   366	376	443	java/lang/reflect/InvocationTargetException
  }
  
  /* Error */
  public void bkkk006Bkk006B006B006Bk(tsssss.onoooo paramOnoooo)
  {
    // Byte code:
    //   0: aload_0
    //   1: aload_1
    //   2: invokespecial 214	uuuuuu/ssssst:ba0061a0061a0061a0061aa	(Luuuuuu/ttssst$tsssst;)V
    //   5: ldc 2
    //   7: ldc -40
    //   9: sipush 203
    //   12: bipush 88
    //   14: iconst_2
    //   15: invokestatic 71	xxxxxx/uxxxxx:bbbb0062b0062b0062b0062	(Ljava/lang/String;CCC)Ljava/lang/String;
    //   18: iconst_0
    //   19: anewarray 73	java/lang/Class
    //   22: invokevirtual 77	java/lang/Class:getMethod	(Ljava/lang/String;[Ljava/lang/Class;)Ljava/lang/reflect/Method;
    //   25: astore_1
    //   26: aload_1
    //   27: aconst_null
    //   28: iconst_0
    //   29: anewarray 79	java/lang/Object
    //   32: invokevirtual 85	java/lang/reflect/Method:invoke	(Ljava/lang/Object;[Ljava/lang/Object;)Ljava/lang/Object;
    //   35: astore_1
    //   36: aload_1
    //   37: checkcast 87	java/lang/Integer
    //   40: invokevirtual 90	java/lang/Integer:intValue	()I
    //   43: istore_2
    //   44: iload_2
    //   45: getstatic 59	uuuuuu/nnoooo:bnnnnnnn006E006E	I
    //   48: iload_2
    //   49: iadd
    //   50: imul
    //   51: getstatic 61	uuuuuu/nnoooo:b006Ennnnnn006E006E	I
    //   54: irem
    //   55: tableswitch	default:+17->72, 0:+60->115
    //   72: ldc 2
    //   74: ldc -38
    //   76: bipush 52
    //   78: iconst_5
    //   79: invokestatic 96	xxxxxx/uxxxxx:bb00620062bb0062b0062b0062	(Ljava/lang/String;CC)Ljava/lang/String;
    //   82: iconst_0
    //   83: anewarray 73	java/lang/Class
    //   86: invokevirtual 77	java/lang/Class:getMethod	(Ljava/lang/String;[Ljava/lang/Class;)Ljava/lang/reflect/Method;
    //   89: astore_1
    //   90: aload_1
    //   91: aconst_null
    //   92: iconst_0
    //   93: anewarray 79	java/lang/Object
    //   96: invokevirtual 85	java/lang/reflect/Method:invoke	(Ljava/lang/Object;[Ljava/lang/Object;)Ljava/lang/Object;
    //   99: astore_1
    //   100: aload_1
    //   101: checkcast 87	java/lang/Integer
    //   104: invokevirtual 90	java/lang/Integer:intValue	()I
    //   107: putstatic 57	uuuuuu/nnoooo:b006E006E006E006E006E006E006En006E	I
    //   110: bipush 13
    //   112: putstatic 63	uuuuuu/nnoooo:bn006Ennnnn006E006E	I
    //   115: ldc 2
    //   117: ldc -36
    //   119: bipush 76
    //   121: iconst_0
    //   122: invokestatic 96	xxxxxx/uxxxxx:bb00620062bb0062b0062b0062	(Ljava/lang/String;CC)Ljava/lang/String;
    //   125: iconst_0
    //   126: anewarray 73	java/lang/Class
    //   129: invokevirtual 77	java/lang/Class:getMethod	(Ljava/lang/String;[Ljava/lang/Class;)Ljava/lang/reflect/Method;
    //   132: astore_1
    //   133: aload_1
    //   134: aload_0
    //   135: iconst_0
    //   136: anewarray 79	java/lang/Object
    //   139: invokevirtual 85	java/lang/reflect/Method:invoke	(Ljava/lang/Object;[Ljava/lang/Object;)Ljava/lang/Object;
    //   142: pop
    //   143: iconst_2
    //   144: istore_2
    //   145: iload_2
    //   146: iconst_0
    //   147: idiv
    //   148: istore_2
    //   149: goto -4 -> 145
    //   152: astore_1
    //   153: aload_1
    //   154: invokevirtual 112	java/lang/reflect/InvocationTargetException:getCause	()Ljava/lang/Throwable;
    //   157: athrow
    //   158: new 222	java/lang/NullPointerException
    //   161: dup
    //   162: invokespecial 223	java/lang/NullPointerException:<init>	()V
    //   165: athrow
    //   166: astore_1
    //   167: ldc 2
    //   169: ldc -31
    //   171: sipush 202
    //   174: sipush 211
    //   177: iconst_2
    //   178: invokestatic 71	xxxxxx/uxxxxx:bbbb0062b0062b0062b0062	(Ljava/lang/String;CCC)Ljava/lang/String;
    //   181: iconst_0
    //   182: anewarray 73	java/lang/Class
    //   185: invokevirtual 77	java/lang/Class:getMethod	(Ljava/lang/String;[Ljava/lang/Class;)Ljava/lang/reflect/Method;
    //   188: astore_1
    //   189: aload_1
    //   190: aconst_null
    //   191: iconst_0
    //   192: anewarray 79	java/lang/Object
    //   195: invokevirtual 85	java/lang/reflect/Method:invoke	(Ljava/lang/Object;[Ljava/lang/Object;)Ljava/lang/Object;
    //   198: astore_1
    //   199: aload_1
    //   200: checkcast 87	java/lang/Integer
    //   203: invokevirtual 90	java/lang/Integer:intValue	()I
    //   206: putstatic 57	uuuuuu/nnoooo:b006E006E006E006E006E006E006En006E	I
    //   209: getstatic 57	uuuuuu/nnoooo:b006E006E006E006E006E006E006En006E	I
    //   212: getstatic 59	uuuuuu/nnoooo:bnnnnnnn006E006E	I
    //   215: iadd
    //   216: getstatic 57	uuuuuu/nnoooo:b006E006E006E006E006E006E006En006E	I
    //   219: imul
    //   220: getstatic 61	uuuuuu/nnoooo:b006Ennnnnn006E006E	I
    //   223: irem
    //   224: getstatic 63	uuuuuu/nnoooo:bn006Ennnnn006E006E	I
    //   227: if_icmpeq +50 -> 277
    //   230: ldc 2
    //   232: ldc -29
    //   234: sipush 159
    //   237: sipush 170
    //   240: iconst_3
    //   241: invokestatic 71	xxxxxx/uxxxxx:bbbb0062b0062b0062b0062	(Ljava/lang/String;CCC)Ljava/lang/String;
    //   244: iconst_0
    //   245: anewarray 73	java/lang/Class
    //   248: invokevirtual 77	java/lang/Class:getMethod	(Ljava/lang/String;[Ljava/lang/Class;)Ljava/lang/reflect/Method;
    //   251: astore_1
    //   252: aload_1
    //   253: aconst_null
    //   254: iconst_0
    //   255: anewarray 79	java/lang/Object
    //   258: invokevirtual 85	java/lang/reflect/Method:invoke	(Ljava/lang/Object;[Ljava/lang/Object;)Ljava/lang/Object;
    //   261: astore_1
    //   262: aload_1
    //   263: checkcast 87	java/lang/Integer
    //   266: invokevirtual 90	java/lang/Integer:intValue	()I
    //   269: putstatic 57	uuuuuu/nnoooo:b006E006E006E006E006E006E006En006E	I
    //   272: bipush 71
    //   274: putstatic 63	uuuuuu/nnoooo:bn006Ennnnn006E006E	I
    //   277: return
    //   278: astore_1
    //   279: aload_1
    //   280: invokevirtual 112	java/lang/reflect/InvocationTargetException:getCause	()Ljava/lang/Throwable;
    //   283: athrow
    //   284: astore_1
    //   285: bipush 39
    //   287: putstatic 57	uuuuuu/nnoooo:b006E006E006E006E006E006E006En006E	I
    //   290: goto -132 -> 158
    //   293: astore_1
    //   294: aload_1
    //   295: invokevirtual 112	java/lang/reflect/InvocationTargetException:getCause	()Ljava/lang/Throwable;
    //   298: athrow
    //   299: astore_1
    //   300: aload_1
    //   301: invokevirtual 112	java/lang/reflect/InvocationTargetException:getCause	()Ljava/lang/Throwable;
    //   304: athrow
    //   305: astore_1
    //   306: aload_1
    //   307: invokevirtual 112	java/lang/reflect/InvocationTargetException:getCause	()Ljava/lang/Throwable;
    //   310: athrow
    // Local variable table:
    //   start	length	slot	name	signature
    //   0	311	0	this	nnoooo
    //   0	311	1	paramOnoooo	tsssss.onoooo
    //   43	106	2	i	int
    // Exception table:
    //   from	to	target	type
    //   26	36	152	java/lang/reflect/InvocationTargetException
    //   158	166	166	java/lang/Exception
    //   189	199	278	java/lang/reflect/InvocationTargetException
    //   145	149	284	java/lang/Exception
    //   133	143	293	java/lang/reflect/InvocationTargetException
    //   90	100	299	java/lang/reflect/InvocationTargetException
    //   252	262	305	java/lang/reflect/InvocationTargetException
  }
}
