package uuuuuu;

import android.view.View.OnClickListener;
import java.lang.reflect.InvocationTargetException;
import java.lang.reflect.Method;
import net.gini.android.vision.Document;
import xxxxxx.uxxxxx;

public class nnwwnn
  extends ssssst<wnnwnn.wwnwnn>
  implements wnnwnn.nwnwnn, vkvkkk.wwnnnn
{
  public static int b00630063c00630063006300630063c = 1;
  public static int b0063c006300630063006300630063c = 14;
  private static final String bc00630063c0063006300630063c;
  public static int bc0063c00630063006300630063c = 0;
  public static int bcc006300630063006300630063c = 2;
  private boolean b006300630063c0063006300630063c = false;
  private vkvkkk b0063cc00630063006300630063c;
  private Document bccc00630063006300630063c;
  
  static
  {
    throw new Runtime("d2j fail translate: java.lang.IndexOutOfBoundsException: fromIndex < 0: -1\n\tat java.util.BitSet.nextSetBit(BitSet.java:712)\n\tat com.googlecode.dex2jar.ir.ts.array.FillArrayTransformer.makeSureAllElementAreAssigned(FillArrayTransformer.java:505)\n\tat com.googlecode.dex2jar.ir.ts.array.FillArrayTransformer.transformReportChanged(FillArrayTransformer.java:123)\n\tat com.googlecode.dex2jar.ir.ts.StatedTransformer.transform(StatedTransformer.java:10)\n\tat com.googlecode.d2j.dex.Dex2jar$2.optimize(Dex2jar.java:149)\n\tat com.googlecode.d2j.dex.Dex2Asm.convertCode(Dex2Asm.java:414)\n\tat com.googlecode.d2j.dex.ExDex2Asm.convertCode(ExDex2Asm.java:42)\n\tat com.googlecode.d2j.dex.Dex2jar$2.convertCode(Dex2jar.java:128)\n\tat com.googlecode.d2j.dex.Dex2Asm.convertMethod(Dex2Asm.java:509)\n\tat com.googlecode.d2j.dex.Dex2Asm.convertClass(Dex2Asm.java:406)\n\tat com.googlecode.d2j.dex.Dex2Asm.convertDex(Dex2Asm.java:422)\n\tat com.googlecode.d2j.dex.Dex2jar.doTranslate(Dex2jar.java:172)\n\tat com.googlecode.d2j.dex.Dex2jar.to(Dex2jar.java:272)\n\tat com.googlecode.dex2jar.tools.Dex2jarCmd.doCommandLine(Dex2jarCmd.java:108)\n\tat com.googlecode.dex2jar.tools.BaseCmd.doMain(BaseCmd.java:288)\n\tat com.googlecode.dex2jar.tools.Dex2jarCmd.main(Dex2jarCmd.java:32)\n");
  }
  
  public nnwwnn() {}
  
  public static int b00710071qqqqqq0071q()
  {
    return 2;
  }
  
  public static int b0071qqqqqqq0071q()
  {
    return 1;
  }
  
  public static int bq0071qqqqqq0071q()
  {
    return 0;
  }
  
  public static int bqqqqqqqq0071q()
  {
    return 24;
  }
  
  /* Error */
  public void b007100710071q0071007100710071qq(final Document paramDocument)
  {
    // Byte code:
    //   0: aload_0
    //   1: getfield 117	uuuuuu/nnwwnn:b0063cc00630063006300630063c	Luuuuuu/vkvkkk;
    //   4: astore 6
    //   6: getstatic 57	uuuuuu/nnwwnn:b0063c006300630063006300630063c	I
    //   9: istore_2
    //   10: iload_2
    //   11: getstatic 59	uuuuuu/nnwwnn:b00630063c00630063006300630063c	I
    //   14: iload_2
    //   15: iadd
    //   16: imul
    //   17: getstatic 61	uuuuuu/nnwwnn:bcc006300630063006300630063c	I
    //   20: irem
    //   21: tableswitch	default:+19->40, 0:+424->445
    //   40: ldc 2
    //   42: ldc -92
    //   44: sipush 145
    //   47: iconst_0
    //   48: invokestatic 97	xxxxxx/uxxxxx:bb00620062bb0062b0062b0062	(Ljava/lang/String;CC)Ljava/lang/String;
    //   51: iconst_0
    //   52: anewarray 73	java/lang/Class
    //   55: invokevirtual 77	java/lang/Class:getMethod	(Ljava/lang/String;[Ljava/lang/Class;)Ljava/lang/reflect/Method;
    //   58: astore 7
    //   60: aload 7
    //   62: aconst_null
    //   63: iconst_0
    //   64: anewarray 79	java/lang/Object
    //   67: invokevirtual 85	java/lang/reflect/Method:invoke	(Ljava/lang/Object;[Ljava/lang/Object;)Ljava/lang/Object;
    //   70: astore 7
    //   72: aload 7
    //   74: checkcast 87	java/lang/Integer
    //   77: invokevirtual 91	java/lang/Integer:intValue	()I
    //   80: putstatic 57	uuuuuu/nnwwnn:b0063c006300630063006300630063c	I
    //   83: ldc 2
    //   85: ldc -90
    //   87: sipush 142
    //   90: sipush 165
    //   93: iconst_3
    //   94: invokestatic 71	xxxxxx/uxxxxx:bbbb0062b0062b0062b0062	(Ljava/lang/String;CCC)Ljava/lang/String;
    //   97: iconst_0
    //   98: anewarray 73	java/lang/Class
    //   101: invokevirtual 77	java/lang/Class:getMethod	(Ljava/lang/String;[Ljava/lang/Class;)Ljava/lang/reflect/Method;
    //   104: astore 7
    //   106: aload 7
    //   108: aconst_null
    //   109: iconst_0
    //   110: anewarray 79	java/lang/Object
    //   113: invokevirtual 85	java/lang/reflect/Method:invoke	(Ljava/lang/Object;[Ljava/lang/Object;)Ljava/lang/Object;
    //   116: astore 7
    //   118: aload 7
    //   120: checkcast 87	java/lang/Integer
    //   123: invokevirtual 91	java/lang/Integer:intValue	()I
    //   126: putstatic 63	uuuuuu/nnwwnn:bc0063c00630063006300630063c	I
    //   129: getstatic 57	uuuuuu/nnwwnn:b0063c006300630063006300630063c	I
    //   132: istore_2
    //   133: getstatic 59	uuuuuu/nnwwnn:b00630063c00630063006300630063c	I
    //   136: istore_3
    //   137: getstatic 57	uuuuuu/nnwwnn:b0063c006300630063006300630063c	I
    //   140: istore 4
    //   142: getstatic 61	uuuuuu/nnwwnn:bcc006300630063006300630063c	I
    //   145: istore 5
    //   147: ldc 2
    //   149: ldc -88
    //   151: bipush 118
    //   153: iconst_1
    //   154: invokestatic 97	xxxxxx/uxxxxx:bb00620062bb0062b0062b0062	(Ljava/lang/String;CC)Ljava/lang/String;
    //   157: iconst_0
    //   158: anewarray 73	java/lang/Class
    //   161: invokevirtual 77	java/lang/Class:getMethod	(Ljava/lang/String;[Ljava/lang/Class;)Ljava/lang/reflect/Method;
    //   164: astore 7
    //   166: aload 7
    //   168: aconst_null
    //   169: iconst_0
    //   170: anewarray 79	java/lang/Object
    //   173: invokevirtual 85	java/lang/reflect/Method:invoke	(Ljava/lang/Object;[Ljava/lang/Object;)Ljava/lang/Object;
    //   176: astore 7
    //   178: iload_2
    //   179: iload_3
    //   180: iadd
    //   181: iload 4
    //   183: imul
    //   184: iload 5
    //   186: irem
    //   187: aload 7
    //   189: checkcast 87	java/lang/Integer
    //   192: invokevirtual 91	java/lang/Integer:intValue	()I
    //   195: if_icmpeq +250 -> 445
    //   198: ldc 2
    //   200: ldc -124
    //   202: sipush 239
    //   205: sipush 178
    //   208: iconst_2
    //   209: invokestatic 71	xxxxxx/uxxxxx:bbbb0062b0062b0062b0062	(Ljava/lang/String;CCC)Ljava/lang/String;
    //   212: iconst_0
    //   213: anewarray 73	java/lang/Class
    //   216: invokevirtual 77	java/lang/Class:getMethod	(Ljava/lang/String;[Ljava/lang/Class;)Ljava/lang/reflect/Method;
    //   219: astore 7
    //   221: aload 7
    //   223: aconst_null
    //   224: iconst_0
    //   225: anewarray 79	java/lang/Object
    //   228: invokevirtual 85	java/lang/reflect/Method:invoke	(Ljava/lang/Object;[Ljava/lang/Object;)Ljava/lang/Object;
    //   231: astore 7
    //   233: aload 7
    //   235: checkcast 87	java/lang/Integer
    //   238: invokevirtual 91	java/lang/Integer:intValue	()I
    //   241: putstatic 57	uuuuuu/nnwwnn:b0063c006300630063006300630063c	I
    //   244: ldc 2
    //   246: ldc -86
    //   248: bipush 34
    //   250: sipush 191
    //   253: iconst_0
    //   254: invokestatic 71	xxxxxx/uxxxxx:bbbb0062b0062b0062b0062	(Ljava/lang/String;CCC)Ljava/lang/String;
    //   257: iconst_0
    //   258: anewarray 73	java/lang/Class
    //   261: invokevirtual 77	java/lang/Class:getMethod	(Ljava/lang/String;[Ljava/lang/Class;)Ljava/lang/reflect/Method;
    //   264: astore 7
    //   266: aload 7
    //   268: aconst_null
    //   269: iconst_0
    //   270: anewarray 79	java/lang/Object
    //   273: invokevirtual 85	java/lang/reflect/Method:invoke	(Ljava/lang/Object;[Ljava/lang/Object;)Ljava/lang/Object;
    //   276: astore 7
    //   278: aload 7
    //   280: checkcast 87	java/lang/Integer
    //   283: invokevirtual 91	java/lang/Integer:intValue	()I
    //   286: putstatic 63	uuuuuu/nnwwnn:bc0063c00630063006300630063c	I
    //   289: getstatic 57	uuuuuu/nnwwnn:b0063c006300630063006300630063c	I
    //   292: getstatic 59	uuuuuu/nnwwnn:b00630063c00630063006300630063c	I
    //   295: iadd
    //   296: getstatic 57	uuuuuu/nnwwnn:b0063c006300630063006300630063c	I
    //   299: imul
    //   300: getstatic 61	uuuuuu/nnwwnn:bcc006300630063006300630063c	I
    //   303: irem
    //   304: getstatic 63	uuuuuu/nnwwnn:bc0063c00630063006300630063c	I
    //   307: if_icmpeq +138 -> 445
    //   310: getstatic 57	uuuuuu/nnwwnn:b0063c006300630063006300630063c	I
    //   313: istore_2
    //   314: iload_2
    //   315: getstatic 59	uuuuuu/nnwwnn:b00630063c00630063006300630063c	I
    //   318: iload_2
    //   319: iadd
    //   320: imul
    //   321: getstatic 61	uuuuuu/nnwwnn:bcc006300630063006300630063c	I
    //   324: irem
    //   325: tableswitch	default:+19->344, 0:+29->354
    //   344: bipush 73
    //   346: putstatic 57	uuuuuu/nnwwnn:b0063c006300630063006300630063c	I
    //   349: bipush 37
    //   351: putstatic 63	uuuuuu/nnwwnn:bc0063c00630063006300630063c	I
    //   354: ldc 2
    //   356: ldc -84
    //   358: sipush 243
    //   361: bipush 18
    //   363: iconst_3
    //   364: invokestatic 71	xxxxxx/uxxxxx:bbbb0062b0062b0062b0062	(Ljava/lang/String;CCC)Ljava/lang/String;
    //   367: iconst_0
    //   368: anewarray 73	java/lang/Class
    //   371: invokevirtual 77	java/lang/Class:getMethod	(Ljava/lang/String;[Ljava/lang/Class;)Ljava/lang/reflect/Method;
    //   374: astore 7
    //   376: aload 7
    //   378: aconst_null
    //   379: iconst_0
    //   380: anewarray 79	java/lang/Object
    //   383: invokevirtual 85	java/lang/reflect/Method:invoke	(Ljava/lang/Object;[Ljava/lang/Object;)Ljava/lang/Object;
    //   386: astore 7
    //   388: aload 7
    //   390: checkcast 87	java/lang/Integer
    //   393: invokevirtual 91	java/lang/Integer:intValue	()I
    //   396: putstatic 57	uuuuuu/nnwwnn:b0063c006300630063006300630063c	I
    //   399: ldc 2
    //   401: ldc -82
    //   403: sipush 174
    //   406: sipush 153
    //   409: iconst_3
    //   410: invokestatic 71	xxxxxx/uxxxxx:bbbb0062b0062b0062b0062	(Ljava/lang/String;CCC)Ljava/lang/String;
    //   413: iconst_0
    //   414: anewarray 73	java/lang/Class
    //   417: invokevirtual 77	java/lang/Class:getMethod	(Ljava/lang/String;[Ljava/lang/Class;)Ljava/lang/reflect/Method;
    //   420: astore 7
    //   422: aload 7
    //   424: aconst_null
    //   425: iconst_0
    //   426: anewarray 79	java/lang/Object
    //   429: invokevirtual 85	java/lang/reflect/Method:invoke	(Ljava/lang/Object;[Ljava/lang/Object;)Ljava/lang/Object;
    //   432: astore 7
    //   434: aload 7
    //   436: checkcast 87	java/lang/Integer
    //   439: invokevirtual 91	java/lang/Integer:intValue	()I
    //   442: putstatic 63	uuuuuu/nnwwnn:bc0063c00630063006300630063c	I
    //   445: aload 6
    //   447: aload_1
    //   448: new 11	uuuuuu/nnwwnn$1
    //   451: dup
    //   452: aload_0
    //   453: aload_1
    //   454: invokespecial 177	uuuuuu/nnwwnn$1:<init>	(Luuuuuu/nnwwnn;Lnet/gini/android/vision/Document;)V
    //   457: invokevirtual 183	uuuuuu/vkvkkk:b0071q007100710071q00710071qq	(Lnet/gini/android/vision/Document;Luuuuuu/vkvkkk$wwnnnn;)V
    //   460: return
    //   461: astore_1
    //   462: aload_1
    //   463: invokevirtual 113	java/lang/reflect/InvocationTargetException:getCause	()Ljava/lang/Throwable;
    //   466: athrow
    //   467: astore_1
    //   468: aload_1
    //   469: invokevirtual 113	java/lang/reflect/InvocationTargetException:getCause	()Ljava/lang/Throwable;
    //   472: athrow
    //   473: astore_1
    //   474: aload_1
    //   475: invokevirtual 113	java/lang/reflect/InvocationTargetException:getCause	()Ljava/lang/Throwable;
    //   478: athrow
    //   479: astore_1
    //   480: aload_1
    //   481: invokevirtual 113	java/lang/reflect/InvocationTargetException:getCause	()Ljava/lang/Throwable;
    //   484: athrow
    //   485: astore_1
    //   486: aload_1
    //   487: invokevirtual 113	java/lang/reflect/InvocationTargetException:getCause	()Ljava/lang/Throwable;
    //   490: athrow
    //   491: astore_1
    //   492: aload_1
    //   493: invokevirtual 113	java/lang/reflect/InvocationTargetException:getCause	()Ljava/lang/Throwable;
    //   496: athrow
    //   497: astore_1
    //   498: aload_1
    //   499: invokevirtual 113	java/lang/reflect/InvocationTargetException:getCause	()Ljava/lang/Throwable;
    //   502: athrow
    // Local variable table:
    //   start	length	slot	name	signature
    //   0	503	0	this	nnwwnn
    //   0	503	1	paramDocument	Document
    //   9	312	2	i	int
    //   136	45	3	j	int
    //   140	44	4	k	int
    //   145	42	5	m	int
    //   4	442	6	localVkvkkk	vkvkkk
    //   58	377	7	localObject	Object
    // Exception table:
    //   from	to	target	type
    //   60	72	461	java/lang/reflect/InvocationTargetException
    //   266	278	467	java/lang/reflect/InvocationTargetException
    //   106	118	473	java/lang/reflect/InvocationTargetException
    //   166	178	479	java/lang/reflect/InvocationTargetException
    //   221	233	485	java/lang/reflect/InvocationTargetException
    //   376	388	491	java/lang/reflect/InvocationTargetException
    //   422	434	497	java/lang/reflect/InvocationTargetException
  }
  
  /* Error */
  public boolean b00710071qq0071007100710071qq()
  {
    // Byte code:
    //   0: aload_0
    //   1: getfield 49	uuuuuu/nnwwnn:b006300630063c0063006300630063c	Z
    //   4: istore 5
    //   6: getstatic 57	uuuuuu/nnwwnn:b0063c006300630063006300630063c	I
    //   9: istore_1
    //   10: iload_1
    //   11: getstatic 59	uuuuuu/nnwwnn:b00630063c00630063006300630063c	I
    //   14: iload_1
    //   15: iadd
    //   16: imul
    //   17: getstatic 61	uuuuuu/nnwwnn:bcc006300630063006300630063c	I
    //   20: irem
    //   21: tableswitch	default:+19->40, 0:+381->402
    //   40: ldc 2
    //   42: ldc 65
    //   44: bipush 121
    //   46: sipush 182
    //   49: iconst_2
    //   50: invokestatic 71	xxxxxx/uxxxxx:bbbb0062b0062b0062b0062	(Ljava/lang/String;CCC)Ljava/lang/String;
    //   53: iconst_0
    //   54: anewarray 73	java/lang/Class
    //   57: invokevirtual 77	java/lang/Class:getMethod	(Ljava/lang/String;[Ljava/lang/Class;)Ljava/lang/reflect/Method;
    //   60: astore 6
    //   62: aload 6
    //   64: aconst_null
    //   65: iconst_0
    //   66: anewarray 79	java/lang/Object
    //   69: invokevirtual 85	java/lang/reflect/Method:invoke	(Ljava/lang/Object;[Ljava/lang/Object;)Ljava/lang/Object;
    //   72: astore 6
    //   74: aload 6
    //   76: checkcast 87	java/lang/Integer
    //   79: invokevirtual 91	java/lang/Integer:intValue	()I
    //   82: putstatic 57	uuuuuu/nnwwnn:b0063c006300630063006300630063c	I
    //   85: bipush 58
    //   87: putstatic 63	uuuuuu/nnwwnn:bc0063c00630063006300630063c	I
    //   90: ldc 2
    //   92: ldc -69
    //   94: bipush 117
    //   96: iconst_4
    //   97: invokestatic 97	xxxxxx/uxxxxx:bb00620062bb0062b0062b0062	(Ljava/lang/String;CC)Ljava/lang/String;
    //   100: iconst_0
    //   101: anewarray 73	java/lang/Class
    //   104: invokevirtual 77	java/lang/Class:getMethod	(Ljava/lang/String;[Ljava/lang/Class;)Ljava/lang/reflect/Method;
    //   107: astore 6
    //   109: aload 6
    //   111: aconst_null
    //   112: iconst_0
    //   113: anewarray 79	java/lang/Object
    //   116: invokevirtual 85	java/lang/reflect/Method:invoke	(Ljava/lang/Object;[Ljava/lang/Object;)Ljava/lang/Object;
    //   119: astore 6
    //   121: aload 6
    //   123: checkcast 87	java/lang/Integer
    //   126: invokevirtual 91	java/lang/Integer:intValue	()I
    //   129: istore_1
    //   130: getstatic 59	uuuuuu/nnwwnn:b00630063c00630063006300630063c	I
    //   133: istore_2
    //   134: ldc 2
    //   136: ldc -67
    //   138: bipush 43
    //   140: iconst_2
    //   141: invokestatic 97	xxxxxx/uxxxxx:bb00620062bb0062b0062b0062	(Ljava/lang/String;CC)Ljava/lang/String;
    //   144: iconst_0
    //   145: anewarray 73	java/lang/Class
    //   148: invokevirtual 77	java/lang/Class:getMethod	(Ljava/lang/String;[Ljava/lang/Class;)Ljava/lang/reflect/Method;
    //   151: astore 6
    //   153: aload 6
    //   155: aconst_null
    //   156: iconst_0
    //   157: anewarray 79	java/lang/Object
    //   160: invokevirtual 85	java/lang/reflect/Method:invoke	(Ljava/lang/Object;[Ljava/lang/Object;)Ljava/lang/Object;
    //   163: astore 6
    //   165: iload_2
    //   166: iload_1
    //   167: iadd
    //   168: iload_1
    //   169: imul
    //   170: aload 6
    //   172: checkcast 87	java/lang/Integer
    //   175: invokevirtual 91	java/lang/Integer:intValue	()I
    //   178: irem
    //   179: tableswitch	default:+17->196, 0:+223->402
    //   196: ldc 2
    //   198: ldc -65
    //   200: sipush 198
    //   203: iconst_2
    //   204: invokestatic 97	xxxxxx/uxxxxx:bb00620062bb0062b0062b0062	(Ljava/lang/String;CC)Ljava/lang/String;
    //   207: iconst_0
    //   208: anewarray 73	java/lang/Class
    //   211: invokevirtual 77	java/lang/Class:getMethod	(Ljava/lang/String;[Ljava/lang/Class;)Ljava/lang/reflect/Method;
    //   214: astore 6
    //   216: aload 6
    //   218: aconst_null
    //   219: iconst_0
    //   220: anewarray 79	java/lang/Object
    //   223: invokevirtual 85	java/lang/reflect/Method:invoke	(Ljava/lang/Object;[Ljava/lang/Object;)Ljava/lang/Object;
    //   226: astore 6
    //   228: aload 6
    //   230: checkcast 87	java/lang/Integer
    //   233: invokevirtual 91	java/lang/Integer:intValue	()I
    //   236: putstatic 57	uuuuuu/nnwwnn:b0063c006300630063006300630063c	I
    //   239: bipush 76
    //   241: putstatic 63	uuuuuu/nnwwnn:bc0063c00630063006300630063c	I
    //   244: getstatic 57	uuuuuu/nnwwnn:b0063c006300630063006300630063c	I
    //   247: istore_1
    //   248: getstatic 59	uuuuuu/nnwwnn:b00630063c00630063006300630063c	I
    //   251: istore_2
    //   252: getstatic 57	uuuuuu/nnwwnn:b0063c006300630063006300630063c	I
    //   255: istore_3
    //   256: getstatic 61	uuuuuu/nnwwnn:bcc006300630063006300630063c	I
    //   259: istore 4
    //   261: ldc 2
    //   263: ldc -103
    //   265: sipush 175
    //   268: iconst_5
    //   269: invokestatic 97	xxxxxx/uxxxxx:bb00620062bb0062b0062b0062	(Ljava/lang/String;CC)Ljava/lang/String;
    //   272: iconst_0
    //   273: anewarray 73	java/lang/Class
    //   276: invokevirtual 77	java/lang/Class:getMethod	(Ljava/lang/String;[Ljava/lang/Class;)Ljava/lang/reflect/Method;
    //   279: astore 6
    //   281: aload 6
    //   283: aconst_null
    //   284: iconst_0
    //   285: anewarray 79	java/lang/Object
    //   288: invokevirtual 85	java/lang/reflect/Method:invoke	(Ljava/lang/Object;[Ljava/lang/Object;)Ljava/lang/Object;
    //   291: astore 6
    //   293: iload_1
    //   294: iload_2
    //   295: iadd
    //   296: iload_3
    //   297: imul
    //   298: iload 4
    //   300: irem
    //   301: aload 6
    //   303: checkcast 87	java/lang/Integer
    //   306: invokevirtual 91	java/lang/Integer:intValue	()I
    //   309: if_icmpeq +93 -> 402
    //   312: getstatic 57	uuuuuu/nnwwnn:b0063c006300630063006300630063c	I
    //   315: istore_1
    //   316: iload_1
    //   317: getstatic 59	uuuuuu/nnwwnn:b00630063c00630063006300630063c	I
    //   320: iload_1
    //   321: iadd
    //   322: imul
    //   323: getstatic 61	uuuuuu/nnwwnn:bcc006300630063006300630063c	I
    //   326: irem
    //   327: tableswitch	default:+17->344, 0:+65->392
    //   344: bipush 25
    //   346: putstatic 57	uuuuuu/nnwwnn:b0063c006300630063006300630063c	I
    //   349: ldc 2
    //   351: ldc -63
    //   353: sipush 181
    //   356: iconst_0
    //   357: invokestatic 97	xxxxxx/uxxxxx:bb00620062bb0062b0062b0062	(Ljava/lang/String;CC)Ljava/lang/String;
    //   360: iconst_0
    //   361: anewarray 73	java/lang/Class
    //   364: invokevirtual 77	java/lang/Class:getMethod	(Ljava/lang/String;[Ljava/lang/Class;)Ljava/lang/reflect/Method;
    //   367: astore 6
    //   369: aload 6
    //   371: aconst_null
    //   372: iconst_0
    //   373: anewarray 79	java/lang/Object
    //   376: invokevirtual 85	java/lang/reflect/Method:invoke	(Ljava/lang/Object;[Ljava/lang/Object;)Ljava/lang/Object;
    //   379: astore 6
    //   381: aload 6
    //   383: checkcast 87	java/lang/Integer
    //   386: invokevirtual 91	java/lang/Integer:intValue	()I
    //   389: putstatic 63	uuuuuu/nnwwnn:bc0063c00630063006300630063c	I
    //   392: bipush 78
    //   394: putstatic 57	uuuuuu/nnwwnn:b0063c006300630063006300630063c	I
    //   397: bipush 51
    //   399: putstatic 63	uuuuuu/nnwwnn:bc0063c00630063006300630063c	I
    //   402: iload 5
    //   404: ireturn
    //   405: astore 6
    //   407: aload 6
    //   409: invokevirtual 113	java/lang/reflect/InvocationTargetException:getCause	()Ljava/lang/Throwable;
    //   412: athrow
    //   413: astore 6
    //   415: aload 6
    //   417: invokevirtual 113	java/lang/reflect/InvocationTargetException:getCause	()Ljava/lang/Throwable;
    //   420: athrow
    //   421: astore 6
    //   423: aload 6
    //   425: invokevirtual 113	java/lang/reflect/InvocationTargetException:getCause	()Ljava/lang/Throwable;
    //   428: athrow
    //   429: astore 6
    //   431: aload 6
    //   433: invokevirtual 113	java/lang/reflect/InvocationTargetException:getCause	()Ljava/lang/Throwable;
    //   436: athrow
    //   437: astore 6
    //   439: aload 6
    //   441: invokevirtual 113	java/lang/reflect/InvocationTargetException:getCause	()Ljava/lang/Throwable;
    //   444: athrow
    //   445: astore 6
    //   447: aload 6
    //   449: invokevirtual 113	java/lang/reflect/InvocationTargetException:getCause	()Ljava/lang/Throwable;
    //   452: athrow
    // Local variable table:
    //   start	length	slot	name	signature
    //   0	453	0	this	nnwwnn
    //   9	314	1	i	int
    //   133	163	2	j	int
    //   255	43	3	k	int
    //   259	42	4	m	int
    //   4	399	5	bool	boolean
    //   60	322	6	localObject	Object
    //   405	3	6	localInvocationTargetException1	InvocationTargetException
    //   413	3	6	localInvocationTargetException2	InvocationTargetException
    //   421	3	6	localInvocationTargetException3	InvocationTargetException
    //   429	3	6	localInvocationTargetException4	InvocationTargetException
    //   437	3	6	localInvocationTargetException5	InvocationTargetException
    //   445	3	6	localInvocationTargetException6	InvocationTargetException
    // Exception table:
    //   from	to	target	type
    //   62	74	405	java/lang/reflect/InvocationTargetException
    //   109	121	413	java/lang/reflect/InvocationTargetException
    //   216	228	421	java/lang/reflect/InvocationTargetException
    //   153	165	429	java/lang/reflect/InvocationTargetException
    //   281	293	437	java/lang/reflect/InvocationTargetException
    //   369	381	445	java/lang/reflect/InvocationTargetException
  }
  
  /* Error */
  public void b0071q0071007100710071q0071qq(java.util.Map<String, net.gini.android.models.SpecificExtraction> paramMap)
  {
    // Byte code:
    //   0: aload_0
    //   1: invokevirtual 198	uuuuuu/nnwwnn:bkk006Bk006Bk006Bk006Bk	()Z
    //   4: ifeq +523 -> 527
    //   7: ldc 2
    //   9: ldc -56
    //   11: sipush 161
    //   14: sipush 243
    //   17: iconst_0
    //   18: invokestatic 71	xxxxxx/uxxxxx:bbbb0062b0062b0062b0062	(Ljava/lang/String;CCC)Ljava/lang/String;
    //   21: iconst_0
    //   22: anewarray 73	java/lang/Class
    //   25: invokevirtual 77	java/lang/Class:getMethod	(Ljava/lang/String;[Ljava/lang/Class;)Ljava/lang/reflect/Method;
    //   28: astore 6
    //   30: aload 6
    //   32: aconst_null
    //   33: iconst_0
    //   34: anewarray 79	java/lang/Object
    //   37: invokevirtual 85	java/lang/reflect/Method:invoke	(Ljava/lang/Object;[Ljava/lang/Object;)Ljava/lang/Object;
    //   40: astore 6
    //   42: aload 6
    //   44: checkcast 87	java/lang/Integer
    //   47: invokevirtual 91	java/lang/Integer:intValue	()I
    //   50: istore_2
    //   51: getstatic 59	uuuuuu/nnwwnn:b00630063c00630063006300630063c	I
    //   54: istore_3
    //   55: ldc 2
    //   57: ldc -54
    //   59: sipush 215
    //   62: iconst_4
    //   63: invokestatic 97	xxxxxx/uxxxxx:bb00620062bb0062b0062b0062	(Ljava/lang/String;CC)Ljava/lang/String;
    //   66: iconst_0
    //   67: anewarray 73	java/lang/Class
    //   70: invokevirtual 77	java/lang/Class:getMethod	(Ljava/lang/String;[Ljava/lang/Class;)Ljava/lang/reflect/Method;
    //   73: astore 6
    //   75: aload 6
    //   77: aconst_null
    //   78: iconst_0
    //   79: anewarray 79	java/lang/Object
    //   82: invokevirtual 85	java/lang/reflect/Method:invoke	(Ljava/lang/Object;[Ljava/lang/Object;)Ljava/lang/Object;
    //   85: astore 6
    //   87: aload 6
    //   89: checkcast 87	java/lang/Integer
    //   92: invokevirtual 91	java/lang/Integer:intValue	()I
    //   95: iload_3
    //   96: iload_2
    //   97: iadd
    //   98: imul
    //   99: getstatic 61	uuuuuu/nnwwnn:bcc006300630063006300630063c	I
    //   102: irem
    //   103: getstatic 63	uuuuuu/nnwwnn:bc0063c00630063006300630063c	I
    //   106: if_icmpeq +289 -> 395
    //   109: getstatic 57	uuuuuu/nnwwnn:b0063c006300630063006300630063c	I
    //   112: istore_2
    //   113: iload_2
    //   114: getstatic 59	uuuuuu/nnwwnn:b00630063c00630063006300630063c	I
    //   117: iload_2
    //   118: iadd
    //   119: imul
    //   120: getstatic 61	uuuuuu/nnwwnn:bcc006300630063006300630063c	I
    //   123: irem
    //   124: tableswitch	default:+20->144, 0:+67->191
    //   144: ldc 2
    //   146: ldc -52
    //   148: bipush 102
    //   150: iconst_2
    //   151: invokestatic 97	xxxxxx/uxxxxx:bb00620062bb0062b0062b0062	(Ljava/lang/String;CC)Ljava/lang/String;
    //   154: iconst_0
    //   155: anewarray 73	java/lang/Class
    //   158: invokevirtual 77	java/lang/Class:getMethod	(Ljava/lang/String;[Ljava/lang/Class;)Ljava/lang/reflect/Method;
    //   161: astore 6
    //   163: aload 6
    //   165: aconst_null
    //   166: iconst_0
    //   167: anewarray 79	java/lang/Object
    //   170: invokevirtual 85	java/lang/reflect/Method:invoke	(Ljava/lang/Object;[Ljava/lang/Object;)Ljava/lang/Object;
    //   173: astore 6
    //   175: aload 6
    //   177: checkcast 87	java/lang/Integer
    //   180: invokevirtual 91	java/lang/Integer:intValue	()I
    //   183: putstatic 57	uuuuuu/nnwwnn:b0063c006300630063006300630063c	I
    //   186: bipush 89
    //   188: putstatic 63	uuuuuu/nnwwnn:bc0063c00630063006300630063c	I
    //   191: bipush 66
    //   193: putstatic 57	uuuuuu/nnwwnn:b0063c006300630063006300630063c	I
    //   196: bipush 17
    //   198: putstatic 63	uuuuuu/nnwwnn:bc0063c00630063006300630063c	I
    //   201: ldc 2
    //   203: ldc -50
    //   205: sipush 224
    //   208: sipush 191
    //   211: iconst_1
    //   212: invokestatic 71	xxxxxx/uxxxxx:bbbb0062b0062b0062b0062	(Ljava/lang/String;CCC)Ljava/lang/String;
    //   215: iconst_0
    //   216: anewarray 73	java/lang/Class
    //   219: invokevirtual 77	java/lang/Class:getMethod	(Ljava/lang/String;[Ljava/lang/Class;)Ljava/lang/reflect/Method;
    //   222: astore 6
    //   224: aload 6
    //   226: aconst_null
    //   227: iconst_0
    //   228: anewarray 79	java/lang/Object
    //   231: invokevirtual 85	java/lang/reflect/Method:invoke	(Ljava/lang/Object;[Ljava/lang/Object;)Ljava/lang/Object;
    //   234: astore 6
    //   236: aload 6
    //   238: checkcast 87	java/lang/Integer
    //   241: invokevirtual 91	java/lang/Integer:intValue	()I
    //   244: istore_2
    //   245: getstatic 59	uuuuuu/nnwwnn:b00630063c00630063006300630063c	I
    //   248: istore_3
    //   249: ldc 2
    //   251: ldc -48
    //   253: sipush 255
    //   256: iconst_1
    //   257: invokestatic 97	xxxxxx/uxxxxx:bb00620062bb0062b0062b0062	(Ljava/lang/String;CC)Ljava/lang/String;
    //   260: iconst_0
    //   261: anewarray 73	java/lang/Class
    //   264: invokevirtual 77	java/lang/Class:getMethod	(Ljava/lang/String;[Ljava/lang/Class;)Ljava/lang/reflect/Method;
    //   267: astore 6
    //   269: aload 6
    //   271: aconst_null
    //   272: iconst_0
    //   273: anewarray 79	java/lang/Object
    //   276: invokevirtual 85	java/lang/reflect/Method:invoke	(Ljava/lang/Object;[Ljava/lang/Object;)Ljava/lang/Object;
    //   279: astore 6
    //   281: aload 6
    //   283: checkcast 87	java/lang/Integer
    //   286: invokevirtual 91	java/lang/Integer:intValue	()I
    //   289: istore 4
    //   291: getstatic 61	uuuuuu/nnwwnn:bcc006300630063006300630063c	I
    //   294: istore 5
    //   296: ldc 2
    //   298: ldc -46
    //   300: bipush 90
    //   302: iconst_4
    //   303: invokestatic 97	xxxxxx/uxxxxx:bb00620062bb0062b0062b0062	(Ljava/lang/String;CC)Ljava/lang/String;
    //   306: iconst_0
    //   307: anewarray 73	java/lang/Class
    //   310: invokevirtual 77	java/lang/Class:getMethod	(Ljava/lang/String;[Ljava/lang/Class;)Ljava/lang/reflect/Method;
    //   313: astore 6
    //   315: aload 6
    //   317: aconst_null
    //   318: iconst_0
    //   319: anewarray 79	java/lang/Object
    //   322: invokevirtual 85	java/lang/reflect/Method:invoke	(Ljava/lang/Object;[Ljava/lang/Object;)Ljava/lang/Object;
    //   325: astore 6
    //   327: iload 4
    //   329: iload_3
    //   330: iload_2
    //   331: iadd
    //   332: imul
    //   333: iload 5
    //   335: irem
    //   336: aload 6
    //   338: checkcast 87	java/lang/Integer
    //   341: invokevirtual 91	java/lang/Integer:intValue	()I
    //   344: if_icmpeq +51 -> 395
    //   347: ldc 2
    //   349: ldc -44
    //   351: sipush 233
    //   354: iconst_1
    //   355: invokestatic 97	xxxxxx/uxxxxx:bb00620062bb0062b0062b0062	(Ljava/lang/String;CC)Ljava/lang/String;
    //   358: iconst_0
    //   359: anewarray 73	java/lang/Class
    //   362: invokevirtual 77	java/lang/Class:getMethod	(Ljava/lang/String;[Ljava/lang/Class;)Ljava/lang/reflect/Method;
    //   365: astore 6
    //   367: aload 6
    //   369: aconst_null
    //   370: iconst_0
    //   371: anewarray 79	java/lang/Object
    //   374: invokevirtual 85	java/lang/reflect/Method:invoke	(Ljava/lang/Object;[Ljava/lang/Object;)Ljava/lang/Object;
    //   377: astore 6
    //   379: aload 6
    //   381: checkcast 87	java/lang/Integer
    //   384: invokevirtual 91	java/lang/Integer:intValue	()I
    //   387: putstatic 57	uuuuuu/nnwwnn:b0063c006300630063006300630063c	I
    //   390: bipush 20
    //   392: putstatic 63	uuuuuu/nnwwnn:bc0063c00630063006300630063c	I
    //   395: aload_0
    //   396: getfield 141	uuuuuu/nnwwnn:bnnnnn006E006E006En	Luuuuuu/ttssst$tsssst;
    //   399: checkcast 214	uuuuuu/wnnwnn$wwnwnn
    //   402: astore 6
    //   404: ldc 2
    //   406: ldc -56
    //   408: bipush 75
    //   410: iconst_4
    //   411: invokestatic 97	xxxxxx/uxxxxx:bb00620062bb0062b0062b0062	(Ljava/lang/String;CC)Ljava/lang/String;
    //   414: iconst_0
    //   415: anewarray 73	java/lang/Class
    //   418: invokevirtual 77	java/lang/Class:getMethod	(Ljava/lang/String;[Ljava/lang/Class;)Ljava/lang/reflect/Method;
    //   421: astore 7
    //   423: aload 7
    //   425: aconst_null
    //   426: iconst_0
    //   427: anewarray 79	java/lang/Object
    //   430: invokevirtual 85	java/lang/reflect/Method:invoke	(Ljava/lang/Object;[Ljava/lang/Object;)Ljava/lang/Object;
    //   433: astore 7
    //   435: aload 7
    //   437: checkcast 87	java/lang/Integer
    //   440: invokevirtual 91	java/lang/Integer:intValue	()I
    //   443: istore_2
    //   444: getstatic 59	uuuuuu/nnwwnn:b00630063c00630063006300630063c	I
    //   447: istore_3
    //   448: ldc 2
    //   450: ldc -40
    //   452: sipush 205
    //   455: iconst_0
    //   456: invokestatic 97	xxxxxx/uxxxxx:bb00620062bb0062b0062b0062	(Ljava/lang/String;CC)Ljava/lang/String;
    //   459: iconst_0
    //   460: anewarray 73	java/lang/Class
    //   463: invokevirtual 77	java/lang/Class:getMethod	(Ljava/lang/String;[Ljava/lang/Class;)Ljava/lang/reflect/Method;
    //   466: astore 7
    //   468: aload 7
    //   470: aconst_null
    //   471: iconst_0
    //   472: anewarray 79	java/lang/Object
    //   475: invokevirtual 85	java/lang/reflect/Method:invoke	(Ljava/lang/Object;[Ljava/lang/Object;)Ljava/lang/Object;
    //   478: astore 7
    //   480: aload 7
    //   482: checkcast 87	java/lang/Integer
    //   485: invokevirtual 91	java/lang/Integer:intValue	()I
    //   488: iload_3
    //   489: iload_2
    //   490: iadd
    //   491: imul
    //   492: getstatic 61	uuuuuu/nnwwnn:bcc006300630063006300630063c	I
    //   495: irem
    //   496: getstatic 63	uuuuuu/nnwwnn:bc0063c00630063006300630063c	I
    //   499: if_icmpeq +13 -> 512
    //   502: bipush 28
    //   504: putstatic 57	uuuuuu/nnwwnn:b0063c006300630063006300630063c	I
    //   507: bipush 57
    //   509: putstatic 63	uuuuuu/nnwwnn:bc0063c00630063006300630063c	I
    //   512: aload 6
    //   514: aload_0
    //   515: getfield 117	uuuuuu/nnwwnn:b0063cc00630063006300630063c	Luuuuuu/vkvkkk;
    //   518: invokevirtual 220	uuuuuu/vkvkkk:b00710071qqq007100710071qq	()Lnet/gini/android/models/Document;
    //   521: aload_1
    //   522: invokeinterface 224 3 0
    //   527: return
    //   528: astore_1
    //   529: aload_1
    //   530: invokevirtual 113	java/lang/reflect/InvocationTargetException:getCause	()Ljava/lang/Throwable;
    //   533: athrow
    //   534: astore_1
    //   535: aload_1
    //   536: invokevirtual 113	java/lang/reflect/InvocationTargetException:getCause	()Ljava/lang/Throwable;
    //   539: athrow
    //   540: astore_1
    //   541: aload_1
    //   542: invokevirtual 113	java/lang/reflect/InvocationTargetException:getCause	()Ljava/lang/Throwable;
    //   545: athrow
    //   546: astore_1
    //   547: aload_1
    //   548: invokevirtual 113	java/lang/reflect/InvocationTargetException:getCause	()Ljava/lang/Throwable;
    //   551: athrow
    //   552: astore_1
    //   553: aload_1
    //   554: invokevirtual 113	java/lang/reflect/InvocationTargetException:getCause	()Ljava/lang/Throwable;
    //   557: athrow
    //   558: astore_1
    //   559: aload_1
    //   560: invokevirtual 113	java/lang/reflect/InvocationTargetException:getCause	()Ljava/lang/Throwable;
    //   563: athrow
    //   564: astore_1
    //   565: aload_1
    //   566: invokevirtual 113	java/lang/reflect/InvocationTargetException:getCause	()Ljava/lang/Throwable;
    //   569: athrow
    //   570: astore_1
    //   571: aload_1
    //   572: invokevirtual 113	java/lang/reflect/InvocationTargetException:getCause	()Ljava/lang/Throwable;
    //   575: athrow
    //   576: astore_1
    //   577: aload_1
    //   578: invokevirtual 113	java/lang/reflect/InvocationTargetException:getCause	()Ljava/lang/Throwable;
    //   581: athrow
    // Local variable table:
    //   start	length	slot	name	signature
    //   0	582	0	this	nnwwnn
    //   0	582	1	paramMap	java.util.Map<String, net.gini.android.models.SpecificExtraction>
    //   50	441	2	i	int
    //   54	437	3	j	int
    //   289	44	4	k	int
    //   294	42	5	m	int
    //   28	485	6	localObject1	Object
    //   421	60	7	localObject2	Object
    // Exception table:
    //   from	to	target	type
    //   423	435	528	java/lang/reflect/InvocationTargetException
    //   30	42	534	java/lang/reflect/InvocationTargetException
    //   75	87	540	java/lang/reflect/InvocationTargetException
    //   224	236	546	java/lang/reflect/InvocationTargetException
    //   269	281	552	java/lang/reflect/InvocationTargetException
    //   315	327	558	java/lang/reflect/InvocationTargetException
    //   468	480	564	java/lang/reflect/InvocationTargetException
    //   163	175	570	java/lang/reflect/InvocationTargetException
    //   367	379	576	java/lang/reflect/InvocationTargetException
  }
  
  /* Error */
  public void b0071q0071q0071007100710071qq(boolean paramBoolean)
  {
    // Byte code:
    //   0: aload_0
    //   1: iload_1
    //   2: putfield 49	uuuuuu/nnwwnn:b006300630063c0063006300630063c	Z
    //   5: getstatic 57	uuuuuu/nnwwnn:b0063c006300630063006300630063c	I
    //   8: istore_2
    //   9: iload_2
    //   10: getstatic 59	uuuuuu/nnwwnn:b00630063c00630063006300630063c	I
    //   13: iload_2
    //   14: iadd
    //   15: imul
    //   16: getstatic 61	uuuuuu/nnwwnn:bcc006300630063006300630063c	I
    //   19: irem
    //   20: tableswitch	default:+20->40, 0:+468->488
    //   40: ldc 2
    //   42: ldc -26
    //   44: bipush 62
    //   46: sipush 248
    //   49: iconst_2
    //   50: invokestatic 71	xxxxxx/uxxxxx:bbbb0062b0062b0062b0062	(Ljava/lang/String;CCC)Ljava/lang/String;
    //   53: iconst_0
    //   54: anewarray 73	java/lang/Class
    //   57: invokevirtual 77	java/lang/Class:getMethod	(Ljava/lang/String;[Ljava/lang/Class;)Ljava/lang/reflect/Method;
    //   60: astore_3
    //   61: aload_3
    //   62: aconst_null
    //   63: iconst_0
    //   64: anewarray 79	java/lang/Object
    //   67: invokevirtual 85	java/lang/reflect/Method:invoke	(Ljava/lang/Object;[Ljava/lang/Object;)Ljava/lang/Object;
    //   70: astore_3
    //   71: aload_3
    //   72: checkcast 87	java/lang/Integer
    //   75: invokevirtual 91	java/lang/Integer:intValue	()I
    //   78: istore_2
    //   79: ldc 2
    //   81: ldc -24
    //   83: bipush 88
    //   85: bipush 63
    //   87: iconst_3
    //   88: invokestatic 71	xxxxxx/uxxxxx:bbbb0062b0062b0062b0062	(Ljava/lang/String;CCC)Ljava/lang/String;
    //   91: iconst_0
    //   92: anewarray 73	java/lang/Class
    //   95: invokevirtual 77	java/lang/Class:getMethod	(Ljava/lang/String;[Ljava/lang/Class;)Ljava/lang/reflect/Method;
    //   98: astore_3
    //   99: aload_3
    //   100: aconst_null
    //   101: iconst_0
    //   102: anewarray 79	java/lang/Object
    //   105: invokevirtual 85	java/lang/reflect/Method:invoke	(Ljava/lang/Object;[Ljava/lang/Object;)Ljava/lang/Object;
    //   108: astore_3
    //   109: aload_3
    //   110: checkcast 87	java/lang/Integer
    //   113: invokevirtual 91	java/lang/Integer:intValue	()I
    //   116: iload_2
    //   117: iadd
    //   118: iload_2
    //   119: imul
    //   120: getstatic 61	uuuuuu/nnwwnn:bcc006300630063006300630063c	I
    //   123: irem
    //   124: tableswitch	default:+20->144, 0:+96->220
    //   144: ldc 2
    //   146: ldc -22
    //   148: bipush 30
    //   150: iconst_1
    //   151: invokestatic 97	xxxxxx/uxxxxx:bb00620062bb0062b0062b0062	(Ljava/lang/String;CC)Ljava/lang/String;
    //   154: iconst_0
    //   155: anewarray 73	java/lang/Class
    //   158: invokevirtual 77	java/lang/Class:getMethod	(Ljava/lang/String;[Ljava/lang/Class;)Ljava/lang/reflect/Method;
    //   161: astore_3
    //   162: aload_3
    //   163: aconst_null
    //   164: iconst_0
    //   165: anewarray 79	java/lang/Object
    //   168: invokevirtual 85	java/lang/reflect/Method:invoke	(Ljava/lang/Object;[Ljava/lang/Object;)Ljava/lang/Object;
    //   171: astore_3
    //   172: aload_3
    //   173: checkcast 87	java/lang/Integer
    //   176: invokevirtual 91	java/lang/Integer:intValue	()I
    //   179: putstatic 57	uuuuuu/nnwwnn:b0063c006300630063006300630063c	I
    //   182: ldc 2
    //   184: ldc -20
    //   186: bipush 24
    //   188: iconst_1
    //   189: invokestatic 97	xxxxxx/uxxxxx:bb00620062bb0062b0062b0062	(Ljava/lang/String;CC)Ljava/lang/String;
    //   192: iconst_0
    //   193: anewarray 73	java/lang/Class
    //   196: invokevirtual 77	java/lang/Class:getMethod	(Ljava/lang/String;[Ljava/lang/Class;)Ljava/lang/reflect/Method;
    //   199: astore_3
    //   200: aload_3
    //   201: aconst_null
    //   202: iconst_0
    //   203: anewarray 79	java/lang/Object
    //   206: invokevirtual 85	java/lang/reflect/Method:invoke	(Ljava/lang/Object;[Ljava/lang/Object;)Ljava/lang/Object;
    //   209: astore_3
    //   210: aload_3
    //   211: checkcast 87	java/lang/Integer
    //   214: invokevirtual 91	java/lang/Integer:intValue	()I
    //   217: putstatic 63	uuuuuu/nnwwnn:bc0063c00630063006300630063c	I
    //   220: bipush 90
    //   222: putstatic 57	uuuuuu/nnwwnn:b0063c006300630063006300630063c	I
    //   225: ldc 2
    //   227: ldc -18
    //   229: sipush 157
    //   232: iconst_2
    //   233: invokestatic 97	xxxxxx/uxxxxx:bb00620062bb0062b0062b0062	(Ljava/lang/String;CC)Ljava/lang/String;
    //   236: iconst_0
    //   237: anewarray 73	java/lang/Class
    //   240: invokevirtual 77	java/lang/Class:getMethod	(Ljava/lang/String;[Ljava/lang/Class;)Ljava/lang/reflect/Method;
    //   243: astore_3
    //   244: aload_3
    //   245: aconst_null
    //   246: iconst_0
    //   247: anewarray 79	java/lang/Object
    //   250: invokevirtual 85	java/lang/reflect/Method:invoke	(Ljava/lang/Object;[Ljava/lang/Object;)Ljava/lang/Object;
    //   253: astore_3
    //   254: aload_3
    //   255: checkcast 87	java/lang/Integer
    //   258: invokevirtual 91	java/lang/Integer:intValue	()I
    //   261: putstatic 63	uuuuuu/nnwwnn:bc0063c00630063006300630063c	I
    //   264: getstatic 57	uuuuuu/nnwwnn:b0063c006300630063006300630063c	I
    //   267: istore_2
    //   268: iload_2
    //   269: getstatic 59	uuuuuu/nnwwnn:b00630063c00630063006300630063c	I
    //   272: iload_2
    //   273: iadd
    //   274: imul
    //   275: getstatic 61	uuuuuu/nnwwnn:bcc006300630063006300630063c	I
    //   278: irem
    //   279: tableswitch	default:+17->296, 0:+209->488
    //   296: ldc 2
    //   298: ldc -16
    //   300: bipush 70
    //   302: iconst_3
    //   303: invokestatic 97	xxxxxx/uxxxxx:bb00620062bb0062b0062b0062	(Ljava/lang/String;CC)Ljava/lang/String;
    //   306: iconst_0
    //   307: anewarray 73	java/lang/Class
    //   310: invokevirtual 77	java/lang/Class:getMethod	(Ljava/lang/String;[Ljava/lang/Class;)Ljava/lang/reflect/Method;
    //   313: astore_3
    //   314: aload_3
    //   315: aconst_null
    //   316: iconst_0
    //   317: anewarray 79	java/lang/Object
    //   320: invokevirtual 85	java/lang/reflect/Method:invoke	(Ljava/lang/Object;[Ljava/lang/Object;)Ljava/lang/Object;
    //   323: astore_3
    //   324: aload_3
    //   325: checkcast 87	java/lang/Integer
    //   328: invokevirtual 91	java/lang/Integer:intValue	()I
    //   331: putstatic 57	uuuuuu/nnwwnn:b0063c006300630063006300630063c	I
    //   334: ldc 2
    //   336: ldc -14
    //   338: sipush 204
    //   341: iconst_0
    //   342: invokestatic 97	xxxxxx/uxxxxx:bb00620062bb0062b0062b0062	(Ljava/lang/String;CC)Ljava/lang/String;
    //   345: iconst_0
    //   346: anewarray 73	java/lang/Class
    //   349: invokevirtual 77	java/lang/Class:getMethod	(Ljava/lang/String;[Ljava/lang/Class;)Ljava/lang/reflect/Method;
    //   352: astore_3
    //   353: aload_3
    //   354: aconst_null
    //   355: iconst_0
    //   356: anewarray 79	java/lang/Object
    //   359: invokevirtual 85	java/lang/reflect/Method:invoke	(Ljava/lang/Object;[Ljava/lang/Object;)Ljava/lang/Object;
    //   362: astore_3
    //   363: aload_3
    //   364: checkcast 87	java/lang/Integer
    //   367: invokevirtual 91	java/lang/Integer:intValue	()I
    //   370: putstatic 63	uuuuuu/nnwwnn:bc0063c00630063006300630063c	I
    //   373: getstatic 57	uuuuuu/nnwwnn:b0063c006300630063006300630063c	I
    //   376: istore_2
    //   377: iload_2
    //   378: getstatic 59	uuuuuu/nnwwnn:b00630063c00630063006300630063c	I
    //   381: iload_2
    //   382: iadd
    //   383: imul
    //   384: getstatic 61	uuuuuu/nnwwnn:bcc006300630063006300630063c	I
    //   387: irem
    //   388: tableswitch	default:+20->408, 0:+100->488
    //   408: ldc 2
    //   410: ldc -12
    //   412: sipush 180
    //   415: bipush 52
    //   417: iconst_3
    //   418: invokestatic 71	xxxxxx/uxxxxx:bbbb0062b0062b0062b0062	(Ljava/lang/String;CCC)Ljava/lang/String;
    //   421: iconst_0
    //   422: anewarray 73	java/lang/Class
    //   425: invokevirtual 77	java/lang/Class:getMethod	(Ljava/lang/String;[Ljava/lang/Class;)Ljava/lang/reflect/Method;
    //   428: astore_3
    //   429: aload_3
    //   430: aconst_null
    //   431: iconst_0
    //   432: anewarray 79	java/lang/Object
    //   435: invokevirtual 85	java/lang/reflect/Method:invoke	(Ljava/lang/Object;[Ljava/lang/Object;)Ljava/lang/Object;
    //   438: astore_3
    //   439: aload_3
    //   440: checkcast 87	java/lang/Integer
    //   443: invokevirtual 91	java/lang/Integer:intValue	()I
    //   446: putstatic 57	uuuuuu/nnwwnn:b0063c006300630063006300630063c	I
    //   449: ldc 2
    //   451: ldc 121
    //   453: sipush 149
    //   456: iconst_4
    //   457: invokestatic 97	xxxxxx/uxxxxx:bb00620062bb0062b0062b0062	(Ljava/lang/String;CC)Ljava/lang/String;
    //   460: iconst_0
    //   461: anewarray 73	java/lang/Class
    //   464: invokevirtual 77	java/lang/Class:getMethod	(Ljava/lang/String;[Ljava/lang/Class;)Ljava/lang/reflect/Method;
    //   467: astore_3
    //   468: aload_3
    //   469: aconst_null
    //   470: iconst_0
    //   471: anewarray 79	java/lang/Object
    //   474: invokevirtual 85	java/lang/reflect/Method:invoke	(Ljava/lang/Object;[Ljava/lang/Object;)Ljava/lang/Object;
    //   477: astore_3
    //   478: aload_3
    //   479: checkcast 87	java/lang/Integer
    //   482: invokevirtual 91	java/lang/Integer:intValue	()I
    //   485: putstatic 63	uuuuuu/nnwwnn:bc0063c00630063006300630063c	I
    //   488: return
    //   489: astore_3
    //   490: aload_3
    //   491: invokevirtual 113	java/lang/reflect/InvocationTargetException:getCause	()Ljava/lang/Throwable;
    //   494: athrow
    //   495: astore_3
    //   496: aload_3
    //   497: invokevirtual 113	java/lang/reflect/InvocationTargetException:getCause	()Ljava/lang/Throwable;
    //   500: athrow
    //   501: astore_3
    //   502: aload_3
    //   503: invokevirtual 113	java/lang/reflect/InvocationTargetException:getCause	()Ljava/lang/Throwable;
    //   506: athrow
    //   507: astore_3
    //   508: aload_3
    //   509: invokevirtual 113	java/lang/reflect/InvocationTargetException:getCause	()Ljava/lang/Throwable;
    //   512: athrow
    //   513: astore_3
    //   514: aload_3
    //   515: invokevirtual 113	java/lang/reflect/InvocationTargetException:getCause	()Ljava/lang/Throwable;
    //   518: athrow
    //   519: astore_3
    //   520: aload_3
    //   521: invokevirtual 113	java/lang/reflect/InvocationTargetException:getCause	()Ljava/lang/Throwable;
    //   524: athrow
    //   525: astore_3
    //   526: aload_3
    //   527: invokevirtual 113	java/lang/reflect/InvocationTargetException:getCause	()Ljava/lang/Throwable;
    //   530: athrow
    //   531: astore_3
    //   532: aload_3
    //   533: invokevirtual 113	java/lang/reflect/InvocationTargetException:getCause	()Ljava/lang/Throwable;
    //   536: athrow
    //   537: astore_3
    //   538: aload_3
    //   539: invokevirtual 113	java/lang/reflect/InvocationTargetException:getCause	()Ljava/lang/Throwable;
    //   542: athrow
    // Local variable table:
    //   start	length	slot	name	signature
    //   0	543	0	this	nnwwnn
    //   0	543	1	paramBoolean	boolean
    //   8	376	2	i	int
    //   60	419	3	localObject	Object
    //   489	2	3	localInvocationTargetException1	InvocationTargetException
    //   495	2	3	localInvocationTargetException2	InvocationTargetException
    //   501	2	3	localInvocationTargetException3	InvocationTargetException
    //   507	2	3	localInvocationTargetException4	InvocationTargetException
    //   513	2	3	localInvocationTargetException5	InvocationTargetException
    //   519	2	3	localInvocationTargetException6	InvocationTargetException
    //   525	2	3	localInvocationTargetException7	InvocationTargetException
    //   531	2	3	localInvocationTargetException8	InvocationTargetException
    //   537	2	3	localInvocationTargetException9	InvocationTargetException
    // Exception table:
    //   from	to	target	type
    //   61	71	489	java/lang/reflect/InvocationTargetException
    //   99	109	495	java/lang/reflect/InvocationTargetException
    //   244	254	501	java/lang/reflect/InvocationTargetException
    //   314	324	507	java/lang/reflect/InvocationTargetException
    //   353	363	513	java/lang/reflect/InvocationTargetException
    //   429	439	519	java/lang/reflect/InvocationTargetException
    //   468	478	525	java/lang/reflect/InvocationTargetException
    //   162	172	531	java/lang/reflect/InvocationTargetException
    //   200	210	537	java/lang/reflect/InvocationTargetException
  }
  
  /* Error */
  public void ba006100610061a0061aa0061a()
  {
    // Byte code:
    //   0: aload_0
    //   1: getfield 117	uuuuuu/nnwwnn:b0063cc00630063006300630063c	Luuuuuu/vkvkkk;
    //   4: astore_2
    //   5: getstatic 57	uuuuuu/nnwwnn:b0063c006300630063006300630063c	I
    //   8: istore_1
    //   9: getstatic 57	uuuuuu/nnwwnn:b0063c006300630063006300630063c	I
    //   12: getstatic 59	uuuuuu/nnwwnn:b00630063c00630063006300630063c	I
    //   15: iadd
    //   16: getstatic 57	uuuuuu/nnwwnn:b0063c006300630063006300630063c	I
    //   19: imul
    //   20: getstatic 61	uuuuuu/nnwwnn:bcc006300630063006300630063c	I
    //   23: irem
    //   24: getstatic 63	uuuuuu/nnwwnn:bc0063c00630063006300630063c	I
    //   27: if_icmpeq +81 -> 108
    //   30: ldc 2
    //   32: ldc -9
    //   34: sipush 227
    //   37: iconst_3
    //   38: invokestatic 97	xxxxxx/uxxxxx:bb00620062bb0062b0062b0062	(Ljava/lang/String;CC)Ljava/lang/String;
    //   41: iconst_0
    //   42: anewarray 73	java/lang/Class
    //   45: invokevirtual 77	java/lang/Class:getMethod	(Ljava/lang/String;[Ljava/lang/Class;)Ljava/lang/reflect/Method;
    //   48: astore_3
    //   49: aload_3
    //   50: aconst_null
    //   51: iconst_0
    //   52: anewarray 79	java/lang/Object
    //   55: invokevirtual 85	java/lang/reflect/Method:invoke	(Ljava/lang/Object;[Ljava/lang/Object;)Ljava/lang/Object;
    //   58: astore_3
    //   59: aload_3
    //   60: checkcast 87	java/lang/Integer
    //   63: invokevirtual 91	java/lang/Integer:intValue	()I
    //   66: putstatic 57	uuuuuu/nnwwnn:b0063c006300630063006300630063c	I
    //   69: ldc 2
    //   71: ldc -7
    //   73: sipush 204
    //   76: iconst_3
    //   77: invokestatic 97	xxxxxx/uxxxxx:bb00620062bb0062b0062b0062	(Ljava/lang/String;CC)Ljava/lang/String;
    //   80: iconst_0
    //   81: anewarray 73	java/lang/Class
    //   84: invokevirtual 77	java/lang/Class:getMethod	(Ljava/lang/String;[Ljava/lang/Class;)Ljava/lang/reflect/Method;
    //   87: astore_3
    //   88: aload_3
    //   89: aconst_null
    //   90: iconst_0
    //   91: anewarray 79	java/lang/Object
    //   94: invokevirtual 85	java/lang/reflect/Method:invoke	(Ljava/lang/Object;[Ljava/lang/Object;)Ljava/lang/Object;
    //   97: astore_3
    //   98: aload_3
    //   99: checkcast 87	java/lang/Integer
    //   102: invokevirtual 91	java/lang/Integer:intValue	()I
    //   105: putstatic 63	uuuuuu/nnwwnn:bc0063c00630063006300630063c	I
    //   108: getstatic 59	uuuuuu/nnwwnn:b00630063c00630063006300630063c	I
    //   111: iload_1
    //   112: iadd
    //   113: getstatic 57	uuuuuu/nnwwnn:b0063c006300630063006300630063c	I
    //   116: imul
    //   117: getstatic 61	uuuuuu/nnwwnn:bcc006300630063006300630063c	I
    //   120: irem
    //   121: getstatic 63	uuuuuu/nnwwnn:bc0063c00630063006300630063c	I
    //   124: if_icmpeq +93 -> 217
    //   127: getstatic 57	uuuuuu/nnwwnn:b0063c006300630063006300630063c	I
    //   130: istore_1
    //   131: iload_1
    //   132: getstatic 59	uuuuuu/nnwwnn:b00630063c00630063006300630063c	I
    //   135: iload_1
    //   136: iadd
    //   137: imul
    //   138: getstatic 61	uuuuuu/nnwwnn:bcc006300630063006300630063c	I
    //   141: irem
    //   142: tableswitch	default:+18->160, 0:+28->170
    //   160: bipush 23
    //   162: putstatic 57	uuuuuu/nnwwnn:b0063c006300630063006300630063c	I
    //   165: bipush 25
    //   167: putstatic 63	uuuuuu/nnwwnn:bc0063c00630063006300630063c	I
    //   170: ldc 2
    //   172: ldc -5
    //   174: sipush 142
    //   177: sipush 149
    //   180: iconst_1
    //   181: invokestatic 71	xxxxxx/uxxxxx:bbbb0062b0062b0062b0062	(Ljava/lang/String;CCC)Ljava/lang/String;
    //   184: iconst_0
    //   185: anewarray 73	java/lang/Class
    //   188: invokevirtual 77	java/lang/Class:getMethod	(Ljava/lang/String;[Ljava/lang/Class;)Ljava/lang/reflect/Method;
    //   191: astore_3
    //   192: aload_3
    //   193: aconst_null
    //   194: iconst_0
    //   195: anewarray 79	java/lang/Object
    //   198: invokevirtual 85	java/lang/reflect/Method:invoke	(Ljava/lang/Object;[Ljava/lang/Object;)Ljava/lang/Object;
    //   201: astore_3
    //   202: aload_3
    //   203: checkcast 87	java/lang/Integer
    //   206: invokevirtual 91	java/lang/Integer:intValue	()I
    //   209: putstatic 57	uuuuuu/nnwwnn:b0063c006300630063006300630063c	I
    //   212: bipush 90
    //   214: putstatic 63	uuuuuu/nnwwnn:bc0063c00630063006300630063c	I
    //   217: aload_2
    //   218: invokevirtual 254	uuuuuu/vkvkkk:bq0071qqq007100710071qq	()V
    //   221: getstatic 57	uuuuuu/nnwwnn:b0063c006300630063006300630063c	I
    //   224: istore_1
    //   225: iload_1
    //   226: getstatic 59	uuuuuu/nnwwnn:b00630063c00630063006300630063c	I
    //   229: iload_1
    //   230: iadd
    //   231: imul
    //   232: getstatic 61	uuuuuu/nnwwnn:bcc006300630063006300630063c	I
    //   235: irem
    //   236: tableswitch	default:+20->256, 0:+64->300
    //   256: ldc 2
    //   258: ldc -101
    //   260: sipush 200
    //   263: iconst_3
    //   264: invokestatic 97	xxxxxx/uxxxxx:bb00620062bb0062b0062b0062	(Ljava/lang/String;CC)Ljava/lang/String;
    //   267: iconst_0
    //   268: anewarray 73	java/lang/Class
    //   271: invokevirtual 77	java/lang/Class:getMethod	(Ljava/lang/String;[Ljava/lang/Class;)Ljava/lang/reflect/Method;
    //   274: astore_2
    //   275: aload_2
    //   276: aconst_null
    //   277: iconst_0
    //   278: anewarray 79	java/lang/Object
    //   281: invokevirtual 85	java/lang/reflect/Method:invoke	(Ljava/lang/Object;[Ljava/lang/Object;)Ljava/lang/Object;
    //   284: astore_2
    //   285: aload_2
    //   286: checkcast 87	java/lang/Integer
    //   289: invokevirtual 91	java/lang/Integer:intValue	()I
    //   292: putstatic 57	uuuuuu/nnwwnn:b0063c006300630063006300630063c	I
    //   295: bipush 8
    //   297: putstatic 63	uuuuuu/nnwwnn:bc0063c00630063006300630063c	I
    //   300: aload_0
    //   301: aconst_null
    //   302: putfield 117	uuuuuu/nnwwnn:b0063cc00630063006300630063c	Luuuuuu/vkvkkk;
    //   305: aload_0
    //   306: invokespecial 256	uuuuuu/ssssst:ba006100610061a0061aa0061a	()V
    //   309: return
    //   310: astore_2
    //   311: aload_2
    //   312: invokevirtual 113	java/lang/reflect/InvocationTargetException:getCause	()Ljava/lang/Throwable;
    //   315: athrow
    //   316: astore_2
    //   317: aload_2
    //   318: invokevirtual 113	java/lang/reflect/InvocationTargetException:getCause	()Ljava/lang/Throwable;
    //   321: athrow
    //   322: astore_2
    //   323: aload_2
    //   324: invokevirtual 113	java/lang/reflect/InvocationTargetException:getCause	()Ljava/lang/Throwable;
    //   327: athrow
    //   328: astore_2
    //   329: aload_2
    //   330: invokevirtual 113	java/lang/reflect/InvocationTargetException:getCause	()Ljava/lang/Throwable;
    //   333: athrow
    // Local variable table:
    //   start	length	slot	name	signature
    //   0	334	0	this	nnwwnn
    //   8	224	1	i	int
    //   4	282	2	localObject1	Object
    //   310	2	2	localInvocationTargetException1	InvocationTargetException
    //   316	2	2	localInvocationTargetException2	InvocationTargetException
    //   322	2	2	localInvocationTargetException3	InvocationTargetException
    //   328	2	2	localInvocationTargetException4	InvocationTargetException
    //   48	155	3	localObject2	Object
    // Exception table:
    //   from	to	target	type
    //   49	59	310	java/lang/reflect/InvocationTargetException
    //   88	98	316	java/lang/reflect/InvocationTargetException
    //   192	202	322	java/lang/reflect/InvocationTargetException
    //   275	285	328	java/lang/reflect/InvocationTargetException
  }
  
  /* Error */
  public void bq00710071q0071007100710071qq(Document paramDocument)
  {
    // Byte code:
    //   0: getstatic 57	uuuuuu/nnwwnn:b0063c006300630063006300630063c	I
    //   3: istore_2
    //   4: iload_2
    //   5: getstatic 59	uuuuuu/nnwwnn:b00630063c00630063006300630063c	I
    //   8: iload_2
    //   9: iadd
    //   10: imul
    //   11: getstatic 61	uuuuuu/nnwwnn:bcc006300630063006300630063c	I
    //   14: irem
    //   15: tableswitch	default:+17->32, 0:+365->380
    //   32: ldc 2
    //   34: ldc -124
    //   36: bipush 108
    //   38: bipush 47
    //   40: iconst_2
    //   41: invokestatic 71	xxxxxx/uxxxxx:bbbb0062b0062b0062b0062	(Ljava/lang/String;CCC)Ljava/lang/String;
    //   44: iconst_0
    //   45: anewarray 73	java/lang/Class
    //   48: invokevirtual 77	java/lang/Class:getMethod	(Ljava/lang/String;[Ljava/lang/Class;)Ljava/lang/reflect/Method;
    //   51: astore 4
    //   53: aload 4
    //   55: aconst_null
    //   56: iconst_0
    //   57: anewarray 79	java/lang/Object
    //   60: invokevirtual 85	java/lang/reflect/Method:invoke	(Ljava/lang/Object;[Ljava/lang/Object;)Ljava/lang/Object;
    //   63: astore 4
    //   65: aload 4
    //   67: checkcast 87	java/lang/Integer
    //   70: invokevirtual 91	java/lang/Integer:intValue	()I
    //   73: istore_2
    //   74: getstatic 57	uuuuuu/nnwwnn:b0063c006300630063006300630063c	I
    //   77: istore_3
    //   78: ldc 2
    //   80: ldc_w 259
    //   83: sipush 150
    //   86: iconst_0
    //   87: invokestatic 97	xxxxxx/uxxxxx:bb00620062bb0062b0062b0062	(Ljava/lang/String;CC)Ljava/lang/String;
    //   90: iconst_0
    //   91: anewarray 73	java/lang/Class
    //   94: invokevirtual 77	java/lang/Class:getMethod	(Ljava/lang/String;[Ljava/lang/Class;)Ljava/lang/reflect/Method;
    //   97: astore 4
    //   99: aload 4
    //   101: aconst_null
    //   102: iconst_0
    //   103: anewarray 79	java/lang/Object
    //   106: invokevirtual 85	java/lang/reflect/Method:invoke	(Ljava/lang/Object;[Ljava/lang/Object;)Ljava/lang/Object;
    //   109: astore 4
    //   111: aload 4
    //   113: checkcast 87	java/lang/Integer
    //   116: invokevirtual 91	java/lang/Integer:intValue	()I
    //   119: iload_3
    //   120: iadd
    //   121: getstatic 57	uuuuuu/nnwwnn:b0063c006300630063006300630063c	I
    //   124: imul
    //   125: getstatic 61	uuuuuu/nnwwnn:bcc006300630063006300630063c	I
    //   128: irem
    //   129: getstatic 63	uuuuuu/nnwwnn:bc0063c00630063006300630063c	I
    //   132: if_icmpeq +90 -> 222
    //   135: ldc 2
    //   137: ldc_w 261
    //   140: sipush 156
    //   143: iconst_3
    //   144: invokestatic 97	xxxxxx/uxxxxx:bb00620062bb0062b0062b0062	(Ljava/lang/String;CC)Ljava/lang/String;
    //   147: iconst_0
    //   148: anewarray 73	java/lang/Class
    //   151: invokevirtual 77	java/lang/Class:getMethod	(Ljava/lang/String;[Ljava/lang/Class;)Ljava/lang/reflect/Method;
    //   154: astore 4
    //   156: aload 4
    //   158: aconst_null
    //   159: iconst_0
    //   160: anewarray 79	java/lang/Object
    //   163: invokevirtual 85	java/lang/reflect/Method:invoke	(Ljava/lang/Object;[Ljava/lang/Object;)Ljava/lang/Object;
    //   166: astore 4
    //   168: aload 4
    //   170: checkcast 87	java/lang/Integer
    //   173: invokevirtual 91	java/lang/Integer:intValue	()I
    //   176: putstatic 57	uuuuuu/nnwwnn:b0063c006300630063006300630063c	I
    //   179: ldc 2
    //   181: ldc_w 263
    //   184: bipush 64
    //   186: iconst_1
    //   187: invokestatic 97	xxxxxx/uxxxxx:bb00620062bb0062b0062b0062	(Ljava/lang/String;CC)Ljava/lang/String;
    //   190: iconst_0
    //   191: anewarray 73	java/lang/Class
    //   194: invokevirtual 77	java/lang/Class:getMethod	(Ljava/lang/String;[Ljava/lang/Class;)Ljava/lang/reflect/Method;
    //   197: astore 4
    //   199: aload 4
    //   201: aconst_null
    //   202: iconst_0
    //   203: anewarray 79	java/lang/Object
    //   206: invokevirtual 85	java/lang/reflect/Method:invoke	(Ljava/lang/Object;[Ljava/lang/Object;)Ljava/lang/Object;
    //   209: astore 4
    //   211: aload 4
    //   213: checkcast 87	java/lang/Integer
    //   216: invokevirtual 91	java/lang/Integer:intValue	()I
    //   219: putstatic 63	uuuuuu/nnwwnn:bc0063c00630063006300630063c	I
    //   222: iload_2
    //   223: putstatic 57	uuuuuu/nnwwnn:b0063c006300630063006300630063c	I
    //   226: ldc 2
    //   228: ldc_w 265
    //   231: sipush 148
    //   234: bipush 117
    //   236: iconst_2
    //   237: invokestatic 71	xxxxxx/uxxxxx:bbbb0062b0062b0062b0062	(Ljava/lang/String;CCC)Ljava/lang/String;
    //   240: iconst_0
    //   241: anewarray 73	java/lang/Class
    //   244: invokevirtual 77	java/lang/Class:getMethod	(Ljava/lang/String;[Ljava/lang/Class;)Ljava/lang/reflect/Method;
    //   247: astore 4
    //   249: aload 4
    //   251: aconst_null
    //   252: iconst_0
    //   253: anewarray 79	java/lang/Object
    //   256: invokevirtual 85	java/lang/reflect/Method:invoke	(Ljava/lang/Object;[Ljava/lang/Object;)Ljava/lang/Object;
    //   259: astore 4
    //   261: aload 4
    //   263: checkcast 87	java/lang/Integer
    //   266: invokevirtual 91	java/lang/Integer:intValue	()I
    //   269: putstatic 63	uuuuuu/nnwwnn:bc0063c00630063006300630063c	I
    //   272: getstatic 57	uuuuuu/nnwwnn:b0063c006300630063006300630063c	I
    //   275: getstatic 59	uuuuuu/nnwwnn:b00630063c00630063006300630063c	I
    //   278: iadd
    //   279: getstatic 57	uuuuuu/nnwwnn:b0063c006300630063006300630063c	I
    //   282: imul
    //   283: getstatic 61	uuuuuu/nnwwnn:bcc006300630063006300630063c	I
    //   286: irem
    //   287: getstatic 63	uuuuuu/nnwwnn:bc0063c00630063006300630063c	I
    //   290: if_icmpeq +90 -> 380
    //   293: ldc 2
    //   295: ldc_w 265
    //   298: sipush 206
    //   301: iconst_1
    //   302: invokestatic 97	xxxxxx/uxxxxx:bb00620062bb0062b0062b0062	(Ljava/lang/String;CC)Ljava/lang/String;
    //   305: iconst_0
    //   306: anewarray 73	java/lang/Class
    //   309: invokevirtual 77	java/lang/Class:getMethod	(Ljava/lang/String;[Ljava/lang/Class;)Ljava/lang/reflect/Method;
    //   312: astore 4
    //   314: aload 4
    //   316: aconst_null
    //   317: iconst_0
    //   318: anewarray 79	java/lang/Object
    //   321: invokevirtual 85	java/lang/reflect/Method:invoke	(Ljava/lang/Object;[Ljava/lang/Object;)Ljava/lang/Object;
    //   324: astore 4
    //   326: aload 4
    //   328: checkcast 87	java/lang/Integer
    //   331: invokevirtual 91	java/lang/Integer:intValue	()I
    //   334: putstatic 57	uuuuuu/nnwwnn:b0063c006300630063006300630063c	I
    //   337: ldc 2
    //   339: ldc_w 267
    //   342: bipush 108
    //   344: iconst_2
    //   345: invokestatic 97	xxxxxx/uxxxxx:bb00620062bb0062b0062b0062	(Ljava/lang/String;CC)Ljava/lang/String;
    //   348: iconst_0
    //   349: anewarray 73	java/lang/Class
    //   352: invokevirtual 77	java/lang/Class:getMethod	(Ljava/lang/String;[Ljava/lang/Class;)Ljava/lang/reflect/Method;
    //   355: astore 4
    //   357: aload 4
    //   359: aconst_null
    //   360: iconst_0
    //   361: anewarray 79	java/lang/Object
    //   364: invokevirtual 85	java/lang/reflect/Method:invoke	(Ljava/lang/Object;[Ljava/lang/Object;)Ljava/lang/Object;
    //   367: astore 4
    //   369: aload 4
    //   371: checkcast 87	java/lang/Integer
    //   374: invokevirtual 91	java/lang/Integer:intValue	()I
    //   377: putstatic 63	uuuuuu/nnwwnn:bc0063c00630063006300630063c	I
    //   380: aload_0
    //   381: aload_1
    //   382: putfield 55	uuuuuu/nnwwnn:bccc00630063006300630063c	Lnet/gini/android/vision/Document;
    //   385: aload_0
    //   386: getfield 117	uuuuuu/nnwwnn:b0063cc00630063006300630063c	Luuuuuu/vkvkkk;
    //   389: astore 4
    //   391: getstatic 57	uuuuuu/nnwwnn:b0063c006300630063006300630063c	I
    //   394: istore_2
    //   395: iload_2
    //   396: getstatic 59	uuuuuu/nnwwnn:b00630063c00630063006300630063c	I
    //   399: iload_2
    //   400: iadd
    //   401: imul
    //   402: getstatic 61	uuuuuu/nnwwnn:bcc006300630063006300630063c	I
    //   405: irem
    //   406: tableswitch	default:+18->424, 0:+28->434
    //   424: bipush 45
    //   426: putstatic 57	uuuuuu/nnwwnn:b0063c006300630063006300630063c	I
    //   429: bipush 20
    //   431: putstatic 63	uuuuuu/nnwwnn:bc0063c00630063006300630063c	I
    //   434: aload 4
    //   436: aload_1
    //   437: aload_0
    //   438: invokevirtual 183	uuuuuu/vkvkkk:b0071q007100710071q00710071qq	(Lnet/gini/android/vision/Document;Luuuuuu/vkvkkk$wwnnnn;)V
    //   441: return
    //   442: astore_1
    //   443: aload_1
    //   444: invokevirtual 113	java/lang/reflect/InvocationTargetException:getCause	()Ljava/lang/Throwable;
    //   447: athrow
    //   448: astore_1
    //   449: aload_1
    //   450: invokevirtual 113	java/lang/reflect/InvocationTargetException:getCause	()Ljava/lang/Throwable;
    //   453: athrow
    //   454: astore_1
    //   455: aload_1
    //   456: invokevirtual 113	java/lang/reflect/InvocationTargetException:getCause	()Ljava/lang/Throwable;
    //   459: athrow
    //   460: astore_1
    //   461: aload_1
    //   462: invokevirtual 113	java/lang/reflect/InvocationTargetException:getCause	()Ljava/lang/Throwable;
    //   465: athrow
    //   466: astore_1
    //   467: aload_1
    //   468: invokevirtual 113	java/lang/reflect/InvocationTargetException:getCause	()Ljava/lang/Throwable;
    //   471: athrow
    //   472: astore_1
    //   473: aload_1
    //   474: invokevirtual 113	java/lang/reflect/InvocationTargetException:getCause	()Ljava/lang/Throwable;
    //   477: athrow
    //   478: astore_1
    //   479: aload_1
    //   480: invokevirtual 113	java/lang/reflect/InvocationTargetException:getCause	()Ljava/lang/Throwable;
    //   483: athrow
    // Local variable table:
    //   start	length	slot	name	signature
    //   0	484	0	this	nnwwnn
    //   0	484	1	paramDocument	Document
    //   3	399	2	i	int
    //   77	44	3	j	int
    //   51	384	4	localObject	Object
    // Exception table:
    //   from	to	target	type
    //   249	261	442	java/lang/reflect/InvocationTargetException
    //   53	65	448	java/lang/reflect/InvocationTargetException
    //   99	111	454	java/lang/reflect/InvocationTargetException
    //   314	326	460	java/lang/reflect/InvocationTargetException
    //   357	369	466	java/lang/reflect/InvocationTargetException
    //   156	168	472	java/lang/reflect/InvocationTargetException
    //   199	211	478	java/lang/reflect/InvocationTargetException
  }
  
  /* Error */
  public void bq0071qq0071007100710071qq(wnnwnn.wwnwnn paramWwnwnn, vkvkkk paramVkvkkk)
  {
    // Byte code:
    //   0: getstatic 57	uuuuuu/nnwwnn:b0063c006300630063006300630063c	I
    //   3: getstatic 59	uuuuuu/nnwwnn:b00630063c00630063006300630063c	I
    //   6: iadd
    //   7: getstatic 57	uuuuuu/nnwwnn:b0063c006300630063006300630063c	I
    //   10: imul
    //   11: getstatic 61	uuuuuu/nnwwnn:bcc006300630063006300630063c	I
    //   14: irem
    //   15: getstatic 63	uuuuuu/nnwwnn:bc0063c00630063006300630063c	I
    //   18: if_icmpeq +51 -> 69
    //   21: bipush 87
    //   23: putstatic 57	uuuuuu/nnwwnn:b0063c006300630063006300630063c	I
    //   26: ldc 2
    //   28: ldc_w 271
    //   31: bipush 71
    //   33: iconst_5
    //   34: invokestatic 97	xxxxxx/uxxxxx:bb00620062bb0062b0062b0062	(Ljava/lang/String;CC)Ljava/lang/String;
    //   37: iconst_0
    //   38: anewarray 73	java/lang/Class
    //   41: invokevirtual 77	java/lang/Class:getMethod	(Ljava/lang/String;[Ljava/lang/Class;)Ljava/lang/reflect/Method;
    //   44: astore 5
    //   46: aload 5
    //   48: aconst_null
    //   49: iconst_0
    //   50: anewarray 79	java/lang/Object
    //   53: invokevirtual 85	java/lang/reflect/Method:invoke	(Ljava/lang/Object;[Ljava/lang/Object;)Ljava/lang/Object;
    //   56: astore 5
    //   58: aload 5
    //   60: checkcast 87	java/lang/Integer
    //   63: invokevirtual 91	java/lang/Integer:intValue	()I
    //   66: putstatic 63	uuuuuu/nnwwnn:bc0063c00630063006300630063c	I
    //   69: aload_0
    //   70: aload_1
    //   71: invokespecial 275	uuuuuu/ssssst:ba0061a0061a0061a0061aa	(Luuuuuu/ttssst$tsssst;)V
    //   74: getstatic 57	uuuuuu/nnwwnn:b0063c006300630063006300630063c	I
    //   77: getstatic 59	uuuuuu/nnwwnn:b00630063c00630063006300630063c	I
    //   80: iadd
    //   81: getstatic 57	uuuuuu/nnwwnn:b0063c006300630063006300630063c	I
    //   84: imul
    //   85: getstatic 61	uuuuuu/nnwwnn:bcc006300630063006300630063c	I
    //   88: irem
    //   89: getstatic 63	uuuuuu/nnwwnn:bc0063c00630063006300630063c	I
    //   92: if_icmpeq +84 -> 176
    //   95: ldc 2
    //   97: ldc_w 277
    //   100: sipush 151
    //   103: iconst_5
    //   104: invokestatic 97	xxxxxx/uxxxxx:bb00620062bb0062b0062b0062	(Ljava/lang/String;CC)Ljava/lang/String;
    //   107: iconst_0
    //   108: anewarray 73	java/lang/Class
    //   111: invokevirtual 77	java/lang/Class:getMethod	(Ljava/lang/String;[Ljava/lang/Class;)Ljava/lang/reflect/Method;
    //   114: astore_1
    //   115: aload_1
    //   116: aconst_null
    //   117: iconst_0
    //   118: anewarray 79	java/lang/Object
    //   121: invokevirtual 85	java/lang/reflect/Method:invoke	(Ljava/lang/Object;[Ljava/lang/Object;)Ljava/lang/Object;
    //   124: astore_1
    //   125: aload_1
    //   126: checkcast 87	java/lang/Integer
    //   129: invokevirtual 91	java/lang/Integer:intValue	()I
    //   132: putstatic 57	uuuuuu/nnwwnn:b0063c006300630063006300630063c	I
    //   135: ldc 2
    //   137: ldc_w 279
    //   140: bipush 84
    //   142: bipush 54
    //   144: iconst_0
    //   145: invokestatic 71	xxxxxx/uxxxxx:bbbb0062b0062b0062b0062	(Ljava/lang/String;CCC)Ljava/lang/String;
    //   148: iconst_0
    //   149: anewarray 73	java/lang/Class
    //   152: invokevirtual 77	java/lang/Class:getMethod	(Ljava/lang/String;[Ljava/lang/Class;)Ljava/lang/reflect/Method;
    //   155: astore_1
    //   156: aload_1
    //   157: aconst_null
    //   158: iconst_0
    //   159: anewarray 79	java/lang/Object
    //   162: invokevirtual 85	java/lang/reflect/Method:invoke	(Ljava/lang/Object;[Ljava/lang/Object;)Ljava/lang/Object;
    //   165: astore_1
    //   166: aload_1
    //   167: checkcast 87	java/lang/Integer
    //   170: invokevirtual 91	java/lang/Integer:intValue	()I
    //   173: putstatic 63	uuuuuu/nnwwnn:bc0063c00630063006300630063c	I
    //   176: getstatic 57	uuuuuu/nnwwnn:b0063c006300630063006300630063c	I
    //   179: istore_3
    //   180: iload_3
    //   181: getstatic 59	uuuuuu/nnwwnn:b00630063c00630063006300630063c	I
    //   184: iload_3
    //   185: iadd
    //   186: imul
    //   187: getstatic 61	uuuuuu/nnwwnn:bcc006300630063006300630063c	I
    //   190: irem
    //   191: tableswitch	default:+17->208, 0:+218->409
    //   208: ldc 2
    //   210: ldc_w 281
    //   213: bipush 71
    //   215: sipush 163
    //   218: iconst_1
    //   219: invokestatic 71	xxxxxx/uxxxxx:bbbb0062b0062b0062b0062	(Ljava/lang/String;CCC)Ljava/lang/String;
    //   222: iconst_0
    //   223: anewarray 73	java/lang/Class
    //   226: invokevirtual 77	java/lang/Class:getMethod	(Ljava/lang/String;[Ljava/lang/Class;)Ljava/lang/reflect/Method;
    //   229: astore_1
    //   230: aload_1
    //   231: aconst_null
    //   232: iconst_0
    //   233: anewarray 79	java/lang/Object
    //   236: invokevirtual 85	java/lang/reflect/Method:invoke	(Ljava/lang/Object;[Ljava/lang/Object;)Ljava/lang/Object;
    //   239: astore_1
    //   240: aload_1
    //   241: checkcast 87	java/lang/Integer
    //   244: invokevirtual 91	java/lang/Integer:intValue	()I
    //   247: istore_3
    //   248: getstatic 57	uuuuuu/nnwwnn:b0063c006300630063006300630063c	I
    //   251: istore 4
    //   253: iload 4
    //   255: getstatic 59	uuuuuu/nnwwnn:b00630063c00630063006300630063c	I
    //   258: iload 4
    //   260: iadd
    //   261: imul
    //   262: getstatic 61	uuuuuu/nnwwnn:bcc006300630063006300630063c	I
    //   265: irem
    //   266: tableswitch	default:+18->284, 0:+97->363
    //   284: ldc 2
    //   286: ldc_w 283
    //   289: sipush 173
    //   292: iconst_1
    //   293: invokestatic 97	xxxxxx/uxxxxx:bb00620062bb0062b0062b0062	(Ljava/lang/String;CC)Ljava/lang/String;
    //   296: iconst_0
    //   297: anewarray 73	java/lang/Class
    //   300: invokevirtual 77	java/lang/Class:getMethod	(Ljava/lang/String;[Ljava/lang/Class;)Ljava/lang/reflect/Method;
    //   303: astore_1
    //   304: aload_1
    //   305: aconst_null
    //   306: iconst_0
    //   307: anewarray 79	java/lang/Object
    //   310: invokevirtual 85	java/lang/reflect/Method:invoke	(Ljava/lang/Object;[Ljava/lang/Object;)Ljava/lang/Object;
    //   313: astore_1
    //   314: aload_1
    //   315: checkcast 87	java/lang/Integer
    //   318: invokevirtual 91	java/lang/Integer:intValue	()I
    //   321: putstatic 57	uuuuuu/nnwwnn:b0063c006300630063006300630063c	I
    //   324: ldc 2
    //   326: ldc_w 285
    //   329: bipush 24
    //   331: iconst_3
    //   332: invokestatic 97	xxxxxx/uxxxxx:bb00620062bb0062b0062b0062	(Ljava/lang/String;CC)Ljava/lang/String;
    //   335: iconst_0
    //   336: anewarray 73	java/lang/Class
    //   339: invokevirtual 77	java/lang/Class:getMethod	(Ljava/lang/String;[Ljava/lang/Class;)Ljava/lang/reflect/Method;
    //   342: astore_1
    //   343: aload_1
    //   344: aconst_null
    //   345: iconst_0
    //   346: anewarray 79	java/lang/Object
    //   349: invokevirtual 85	java/lang/reflect/Method:invoke	(Ljava/lang/Object;[Ljava/lang/Object;)Ljava/lang/Object;
    //   352: astore_1
    //   353: aload_1
    //   354: checkcast 87	java/lang/Integer
    //   357: invokevirtual 91	java/lang/Integer:intValue	()I
    //   360: putstatic 63	uuuuuu/nnwwnn:bc0063c00630063006300630063c	I
    //   363: iload_3
    //   364: putstatic 57	uuuuuu/nnwwnn:b0063c006300630063006300630063c	I
    //   367: ldc 2
    //   369: ldc_w 287
    //   372: bipush 88
    //   374: sipush 141
    //   377: iconst_2
    //   378: invokestatic 71	xxxxxx/uxxxxx:bbbb0062b0062b0062b0062	(Ljava/lang/String;CCC)Ljava/lang/String;
    //   381: iconst_0
    //   382: anewarray 73	java/lang/Class
    //   385: invokevirtual 77	java/lang/Class:getMethod	(Ljava/lang/String;[Ljava/lang/Class;)Ljava/lang/reflect/Method;
    //   388: astore_1
    //   389: aload_1
    //   390: aconst_null
    //   391: iconst_0
    //   392: anewarray 79	java/lang/Object
    //   395: invokevirtual 85	java/lang/reflect/Method:invoke	(Ljava/lang/Object;[Ljava/lang/Object;)Ljava/lang/Object;
    //   398: astore_1
    //   399: aload_1
    //   400: checkcast 87	java/lang/Integer
    //   403: invokevirtual 91	java/lang/Integer:intValue	()I
    //   406: putstatic 63	uuuuuu/nnwwnn:bc0063c00630063006300630063c	I
    //   409: aload_0
    //   410: aload_2
    //   411: putfield 117	uuuuuu/nnwwnn:b0063cc00630063006300630063c	Luuuuuu/vkvkkk;
    //   414: return
    //   415: astore_1
    //   416: aload_1
    //   417: invokevirtual 113	java/lang/reflect/InvocationTargetException:getCause	()Ljava/lang/Throwable;
    //   420: athrow
    //   421: astore_1
    //   422: aload_1
    //   423: invokevirtual 113	java/lang/reflect/InvocationTargetException:getCause	()Ljava/lang/Throwable;
    //   426: athrow
    //   427: astore_1
    //   428: aload_1
    //   429: invokevirtual 113	java/lang/reflect/InvocationTargetException:getCause	()Ljava/lang/Throwable;
    //   432: athrow
    //   433: astore_1
    //   434: aload_1
    //   435: invokevirtual 113	java/lang/reflect/InvocationTargetException:getCause	()Ljava/lang/Throwable;
    //   438: athrow
    //   439: astore_1
    //   440: aload_1
    //   441: invokevirtual 113	java/lang/reflect/InvocationTargetException:getCause	()Ljava/lang/Throwable;
    //   444: athrow
    //   445: astore_1
    //   446: aload_1
    //   447: invokevirtual 113	java/lang/reflect/InvocationTargetException:getCause	()Ljava/lang/Throwable;
    //   450: athrow
    //   451: astore_1
    //   452: aload_1
    //   453: invokevirtual 113	java/lang/reflect/InvocationTargetException:getCause	()Ljava/lang/Throwable;
    //   456: athrow
    // Local variable table:
    //   start	length	slot	name	signature
    //   0	457	0	this	nnwwnn
    //   0	457	1	paramWwnwnn	wnnwnn.wwnwnn
    //   0	457	2	paramVkvkkk	vkvkkk
    //   179	185	3	i	int
    //   251	11	4	j	int
    //   44	15	5	localObject	Object
    // Exception table:
    //   from	to	target	type
    //   230	240	415	java/lang/reflect/InvocationTargetException
    //   389	399	421	java/lang/reflect/InvocationTargetException
    //   46	58	427	java/lang/reflect/InvocationTargetException
    //   115	125	433	java/lang/reflect/InvocationTargetException
    //   156	166	439	java/lang/reflect/InvocationTargetException
    //   304	314	445	java/lang/reflect/InvocationTargetException
    //   343	353	451	java/lang/reflect/InvocationTargetException
  }
  
  /* Error */
  public void bqq0071007100710071q0071qq(Exception paramException)
  {
    // Byte code:
    //   0: getstatic 291	uuuuuu/nnwwnn:bc00630063c0063006300630063c	Ljava/lang/String;
    //   3: astore 6
    //   5: ldc_w 293
    //   8: ldc_w 295
    //   11: sipush 232
    //   14: sipush 254
    //   17: iconst_3
    //   18: invokestatic 71	xxxxxx/uxxxxx:bbbb0062b0062b0062b0062	(Ljava/lang/String;CCC)Ljava/lang/String;
    //   21: iconst_3
    //   22: anewarray 73	java/lang/Class
    //   25: dup
    //   26: iconst_0
    //   27: ldc_w 297
    //   30: aastore
    //   31: dup
    //   32: iconst_1
    //   33: getstatic 303	java/lang/Character:TYPE	Ljava/lang/Class;
    //   36: aastore
    //   37: dup
    //   38: iconst_2
    //   39: getstatic 303	java/lang/Character:TYPE	Ljava/lang/Class;
    //   42: aastore
    //   43: invokevirtual 77	java/lang/Class:getMethod	(Ljava/lang/String;[Ljava/lang/Class;)Ljava/lang/reflect/Method;
    //   46: astore 7
    //   48: aload 7
    //   50: aconst_null
    //   51: iconst_3
    //   52: anewarray 79	java/lang/Object
    //   55: dup
    //   56: iconst_0
    //   57: ldc_w 305
    //   60: aastore
    //   61: dup
    //   62: iconst_1
    //   63: sipush 169
    //   66: invokestatic 309	java/lang/Character:valueOf	(C)Ljava/lang/Character;
    //   69: aastore
    //   70: dup
    //   71: iconst_2
    //   72: iconst_3
    //   73: invokestatic 309	java/lang/Character:valueOf	(C)Ljava/lang/Character;
    //   76: aastore
    //   77: invokevirtual 85	java/lang/reflect/Method:invoke	(Ljava/lang/Object;[Ljava/lang/Object;)Ljava/lang/Object;
    //   80: astore 7
    //   82: aload 6
    //   84: aload 7
    //   86: checkcast 297	java/lang/String
    //   89: aload_1
    //   90: invokestatic 315	uuuuuu/rvvvrv:b00710071qq00710071q0071q0071	(Ljava/lang/String;Ljava/lang/String;Ljava/lang/Throwable;)V
    //   93: aload_0
    //   94: invokevirtual 198	uuuuuu/nnwwnn:bkk006Bk006Bk006Bk006Bk	()Z
    //   97: ifne +4 -> 101
    //   100: return
    //   101: aload_0
    //   102: getfield 141	uuuuuu/nnwwnn:bnnnnn006E006E006En	Luuuuuu/ttssst$tsssst;
    //   105: checkcast 214	uuuuuu/wnnwnn$wwnwnn
    //   108: invokeinterface 318 1 0
    //   113: getstatic 57	uuuuuu/nnwwnn:b0063c006300630063006300630063c	I
    //   116: istore_2
    //   117: iload_2
    //   118: getstatic 59	uuuuuu/nnwwnn:b00630063c00630063006300630063c	I
    //   121: iload_2
    //   122: iadd
    //   123: imul
    //   124: getstatic 61	uuuuuu/nnwwnn:bcc006300630063006300630063c	I
    //   127: irem
    //   128: tableswitch	default:+20->148, 0:+30->158
    //   148: bipush 67
    //   150: putstatic 57	uuuuuu/nnwwnn:b0063c006300630063006300630063c	I
    //   153: bipush 63
    //   155: putstatic 63	uuuuuu/nnwwnn:bc0063c00630063006300630063c	I
    //   158: ldc_w 293
    //   161: ldc_w 320
    //   164: sipush 240
    //   167: iconst_5
    //   168: invokestatic 97	xxxxxx/uxxxxx:bb00620062bb0062b0062b0062	(Ljava/lang/String;CC)Ljava/lang/String;
    //   171: iconst_4
    //   172: anewarray 73	java/lang/Class
    //   175: dup
    //   176: iconst_0
    //   177: ldc_w 297
    //   180: aastore
    //   181: dup
    //   182: iconst_1
    //   183: getstatic 303	java/lang/Character:TYPE	Ljava/lang/Class;
    //   186: aastore
    //   187: dup
    //   188: iconst_2
    //   189: getstatic 303	java/lang/Character:TYPE	Ljava/lang/Class;
    //   192: aastore
    //   193: dup
    //   194: iconst_3
    //   195: getstatic 303	java/lang/Character:TYPE	Ljava/lang/Class;
    //   198: aastore
    //   199: invokevirtual 77	java/lang/Class:getMethod	(Ljava/lang/String;[Ljava/lang/Class;)Ljava/lang/reflect/Method;
    //   202: astore 6
    //   204: aload 6
    //   206: aconst_null
    //   207: iconst_4
    //   208: anewarray 79	java/lang/Object
    //   211: dup
    //   212: iconst_0
    //   213: ldc_w 322
    //   216: aastore
    //   217: dup
    //   218: iconst_1
    //   219: bipush 8
    //   221: invokestatic 309	java/lang/Character:valueOf	(C)Ljava/lang/Character;
    //   224: aastore
    //   225: dup
    //   226: iconst_2
    //   227: sipush 135
    //   230: invokestatic 309	java/lang/Character:valueOf	(C)Ljava/lang/Character;
    //   233: aastore
    //   234: dup
    //   235: iconst_3
    //   236: iconst_1
    //   237: invokestatic 309	java/lang/Character:valueOf	(C)Ljava/lang/Character;
    //   240: aastore
    //   241: invokevirtual 85	java/lang/reflect/Method:invoke	(Ljava/lang/Object;[Ljava/lang/Object;)Ljava/lang/Object;
    //   244: astore 6
    //   246: aload 6
    //   248: checkcast 297	java/lang/String
    //   251: astore 6
    //   253: aload_1
    //   254: invokevirtual 326	java/lang/Exception:getMessage	()Ljava/lang/String;
    //   257: ifnull +646 -> 903
    //   260: aload_1
    //   261: invokevirtual 326	java/lang/Exception:getMessage	()Ljava/lang/String;
    //   264: astore 6
    //   266: getstatic 57	uuuuuu/nnwwnn:b0063c006300630063006300630063c	I
    //   269: getstatic 59	uuuuuu/nnwwnn:b00630063c00630063006300630063c	I
    //   272: iadd
    //   273: getstatic 57	uuuuuu/nnwwnn:b0063c006300630063006300630063c	I
    //   276: imul
    //   277: getstatic 61	uuuuuu/nnwwnn:bcc006300630063006300630063c	I
    //   280: irem
    //   281: getstatic 63	uuuuuu/nnwwnn:bc0063c00630063006300630063c	I
    //   284: if_icmpeq +616 -> 900
    //   287: bipush 88
    //   289: putstatic 57	uuuuuu/nnwwnn:b0063c006300630063006300630063c	I
    //   292: ldc 2
    //   294: ldc_w 328
    //   297: sipush 192
    //   300: sipush 229
    //   303: iconst_1
    //   304: invokestatic 71	xxxxxx/uxxxxx:bbbb0062b0062b0062b0062	(Ljava/lang/String;CCC)Ljava/lang/String;
    //   307: iconst_0
    //   308: anewarray 73	java/lang/Class
    //   311: invokevirtual 77	java/lang/Class:getMethod	(Ljava/lang/String;[Ljava/lang/Class;)Ljava/lang/reflect/Method;
    //   314: astore 7
    //   316: aload 7
    //   318: aconst_null
    //   319: iconst_0
    //   320: anewarray 79	java/lang/Object
    //   323: invokevirtual 85	java/lang/reflect/Method:invoke	(Ljava/lang/Object;[Ljava/lang/Object;)Ljava/lang/Object;
    //   326: astore 7
    //   328: aload 7
    //   330: checkcast 87	java/lang/Integer
    //   333: invokevirtual 91	java/lang/Integer:intValue	()I
    //   336: putstatic 63	uuuuuu/nnwwnn:bc0063c00630063006300630063c	I
    //   339: aload_0
    //   340: getfield 141	uuuuuu/nnwwnn:bnnnnn006E006E006En	Luuuuuu/ttssst$tsssst;
    //   343: checkcast 214	uuuuuu/wnnwnn$wwnwnn
    //   346: invokeinterface 332 1 0
    //   351: astore 7
    //   353: getstatic 57	uuuuuu/nnwwnn:b0063c006300630063006300630063c	I
    //   356: istore_2
    //   357: ldc 2
    //   359: ldc_w 334
    //   362: bipush 116
    //   364: iconst_2
    //   365: invokestatic 97	xxxxxx/uxxxxx:bb00620062bb0062b0062b0062	(Ljava/lang/String;CC)Ljava/lang/String;
    //   368: iconst_0
    //   369: anewarray 73	java/lang/Class
    //   372: invokevirtual 77	java/lang/Class:getMethod	(Ljava/lang/String;[Ljava/lang/Class;)Ljava/lang/reflect/Method;
    //   375: astore 8
    //   377: aload 8
    //   379: aconst_null
    //   380: iconst_0
    //   381: anewarray 79	java/lang/Object
    //   384: invokevirtual 85	java/lang/reflect/Method:invoke	(Ljava/lang/Object;[Ljava/lang/Object;)Ljava/lang/Object;
    //   387: astore 8
    //   389: aload 8
    //   391: checkcast 87	java/lang/Integer
    //   394: invokevirtual 91	java/lang/Integer:intValue	()I
    //   397: istore_3
    //   398: getstatic 57	uuuuuu/nnwwnn:b0063c006300630063006300630063c	I
    //   401: istore 4
    //   403: ldc 2
    //   405: ldc_w 336
    //   408: sipush 206
    //   411: iconst_0
    //   412: invokestatic 97	xxxxxx/uxxxxx:bb00620062bb0062b0062b0062	(Ljava/lang/String;CC)Ljava/lang/String;
    //   415: iconst_0
    //   416: anewarray 73	java/lang/Class
    //   419: invokevirtual 77	java/lang/Class:getMethod	(Ljava/lang/String;[Ljava/lang/Class;)Ljava/lang/reflect/Method;
    //   422: astore 8
    //   424: aload 8
    //   426: aconst_null
    //   427: iconst_0
    //   428: anewarray 79	java/lang/Object
    //   431: invokevirtual 85	java/lang/reflect/Method:invoke	(Ljava/lang/Object;[Ljava/lang/Object;)Ljava/lang/Object;
    //   434: astore 8
    //   436: aload 8
    //   438: checkcast 87	java/lang/Integer
    //   441: invokevirtual 91	java/lang/Integer:intValue	()I
    //   444: istore 5
    //   446: ldc 2
    //   448: ldc_w 338
    //   451: bipush 101
    //   453: sipush 165
    //   456: iconst_2
    //   457: invokestatic 71	xxxxxx/uxxxxx:bbbb0062b0062b0062b0062	(Ljava/lang/String;CCC)Ljava/lang/String;
    //   460: iconst_0
    //   461: anewarray 73	java/lang/Class
    //   464: invokevirtual 77	java/lang/Class:getMethod	(Ljava/lang/String;[Ljava/lang/Class;)Ljava/lang/reflect/Method;
    //   467: astore 8
    //   469: aload 8
    //   471: aconst_null
    //   472: iconst_0
    //   473: anewarray 79	java/lang/Object
    //   476: invokevirtual 85	java/lang/reflect/Method:invoke	(Ljava/lang/Object;[Ljava/lang/Object;)Ljava/lang/Object;
    //   479: astore 8
    //   481: iload 4
    //   483: iload_3
    //   484: iload_2
    //   485: iadd
    //   486: imul
    //   487: iload 5
    //   489: irem
    //   490: aload 8
    //   492: checkcast 87	java/lang/Integer
    //   495: invokevirtual 91	java/lang/Integer:intValue	()I
    //   498: if_icmpeq +92 -> 590
    //   501: ldc 2
    //   503: ldc_w 340
    //   506: sipush 128
    //   509: sipush 203
    //   512: iconst_1
    //   513: invokestatic 71	xxxxxx/uxxxxx:bbbb0062b0062b0062b0062	(Ljava/lang/String;CCC)Ljava/lang/String;
    //   516: iconst_0
    //   517: anewarray 73	java/lang/Class
    //   520: invokevirtual 77	java/lang/Class:getMethod	(Ljava/lang/String;[Ljava/lang/Class;)Ljava/lang/reflect/Method;
    //   523: astore 8
    //   525: aload 8
    //   527: aconst_null
    //   528: iconst_0
    //   529: anewarray 79	java/lang/Object
    //   532: invokevirtual 85	java/lang/reflect/Method:invoke	(Ljava/lang/Object;[Ljava/lang/Object;)Ljava/lang/Object;
    //   535: astore 8
    //   537: aload 8
    //   539: checkcast 87	java/lang/Integer
    //   542: invokevirtual 91	java/lang/Integer:intValue	()I
    //   545: putstatic 57	uuuuuu/nnwwnn:b0063c006300630063006300630063c	I
    //   548: ldc 2
    //   550: ldc -44
    //   552: bipush 85
    //   554: iconst_2
    //   555: invokestatic 97	xxxxxx/uxxxxx:bb00620062bb0062b0062b0062	(Ljava/lang/String;CC)Ljava/lang/String;
    //   558: iconst_0
    //   559: anewarray 73	java/lang/Class
    //   562: invokevirtual 77	java/lang/Class:getMethod	(Ljava/lang/String;[Ljava/lang/Class;)Ljava/lang/reflect/Method;
    //   565: astore 8
    //   567: aload 8
    //   569: aconst_null
    //   570: iconst_0
    //   571: anewarray 79	java/lang/Object
    //   574: invokevirtual 85	java/lang/reflect/Method:invoke	(Ljava/lang/Object;[Ljava/lang/Object;)Ljava/lang/Object;
    //   577: astore 8
    //   579: aload 8
    //   581: checkcast 87	java/lang/Integer
    //   584: invokevirtual 91	java/lang/Integer:intValue	()I
    //   587: putstatic 63	uuuuuu/nnwwnn:bc0063c00630063006300630063c	I
    //   590: aload 7
    //   592: getstatic 346	uuuuuu/kkkvkk:b00630063c0063ccc0063c	Luuuuuu/kkkvkk;
    //   595: if_acmpne +118 -> 713
    //   598: aload_0
    //   599: getfield 141	uuuuuu/nnwwnn:bnnnnn006E006E006En	Luuuuuu/ttssst$tsssst;
    //   602: checkcast 214	uuuuuu/wnnwnn$wwnwnn
    //   605: astore 7
    //   607: getstatic 351	com/db/pwcc/dbmobile/gini/R$string:retry_analysis	I
    //   610: istore_2
    //   611: getstatic 57	uuuuuu/nnwwnn:b0063c006300630063006300630063c	I
    //   614: istore_3
    //   615: iload_3
    //   616: getstatic 59	uuuuuu/nnwwnn:b00630063c00630063006300630063c	I
    //   619: iload_3
    //   620: iadd
    //   621: imul
    //   622: getstatic 61	uuuuuu/nnwwnn:bcc006300630063006300630063c	I
    //   625: irem
    //   626: tableswitch	default:+18->644, 0:+69->695
    //   644: bipush 12
    //   646: putstatic 57	uuuuuu/nnwwnn:b0063c006300630063006300630063c	I
    //   649: ldc 2
    //   651: ldc_w 353
    //   654: bipush 25
    //   656: sipush 253
    //   659: iconst_3
    //   660: invokestatic 71	xxxxxx/uxxxxx:bbbb0062b0062b0062b0062	(Ljava/lang/String;CCC)Ljava/lang/String;
    //   663: iconst_0
    //   664: anewarray 73	java/lang/Class
    //   667: invokevirtual 77	java/lang/Class:getMethod	(Ljava/lang/String;[Ljava/lang/Class;)Ljava/lang/reflect/Method;
    //   670: astore 8
    //   672: aload 8
    //   674: aconst_null
    //   675: iconst_0
    //   676: anewarray 79	java/lang/Object
    //   679: invokevirtual 85	java/lang/reflect/Method:invoke	(Ljava/lang/Object;[Ljava/lang/Object;)Ljava/lang/Object;
    //   682: astore 8
    //   684: aload 8
    //   686: checkcast 87	java/lang/Integer
    //   689: invokevirtual 91	java/lang/Integer:intValue	()I
    //   692: putstatic 63	uuuuuu/nnwwnn:bc0063c00630063006300630063c	I
    //   695: aload 7
    //   697: aload 6
    //   699: iload_2
    //   700: new 14	uuuuuu/nnwwnn$2
    //   703: dup
    //   704: aload_0
    //   705: invokespecial 356	uuuuuu/nnwwnn$2:<init>	(Luuuuuu/nnwwnn;)V
    //   708: invokeinterface 360 4 0
    //   713: getstatic 291	uuuuuu/nnwwnn:bc00630063c0063006300630063c	Ljava/lang/String;
    //   716: astore 6
    //   718: new 362	java/lang/StringBuilder
    //   721: dup
    //   722: invokespecial 363	java/lang/StringBuilder:<init>	()V
    //   725: astore 7
    //   727: ldc_w 293
    //   730: ldc_w 365
    //   733: sipush 163
    //   736: sipush 251
    //   739: iconst_1
    //   740: invokestatic 71	xxxxxx/uxxxxx:bbbb0062b0062b0062b0062	(Ljava/lang/String;CCC)Ljava/lang/String;
    //   743: iconst_4
    //   744: anewarray 73	java/lang/Class
    //   747: dup
    //   748: iconst_0
    //   749: ldc_w 297
    //   752: aastore
    //   753: dup
    //   754: iconst_1
    //   755: getstatic 303	java/lang/Character:TYPE	Ljava/lang/Class;
    //   758: aastore
    //   759: dup
    //   760: iconst_2
    //   761: getstatic 303	java/lang/Character:TYPE	Ljava/lang/Class;
    //   764: aastore
    //   765: dup
    //   766: iconst_3
    //   767: getstatic 303	java/lang/Character:TYPE	Ljava/lang/Class;
    //   770: aastore
    //   771: invokevirtual 77	java/lang/Class:getMethod	(Ljava/lang/String;[Ljava/lang/Class;)Ljava/lang/reflect/Method;
    //   774: astore 8
    //   776: aload 8
    //   778: aconst_null
    //   779: iconst_4
    //   780: anewarray 79	java/lang/Object
    //   783: dup
    //   784: iconst_0
    //   785: ldc_w 367
    //   788: aastore
    //   789: dup
    //   790: iconst_1
    //   791: bipush 108
    //   793: invokestatic 309	java/lang/Character:valueOf	(C)Ljava/lang/Character;
    //   796: aastore
    //   797: dup
    //   798: iconst_2
    //   799: bipush 98
    //   801: invokestatic 309	java/lang/Character:valueOf	(C)Ljava/lang/Character;
    //   804: aastore
    //   805: dup
    //   806: iconst_3
    //   807: iconst_3
    //   808: invokestatic 309	java/lang/Character:valueOf	(C)Ljava/lang/Character;
    //   811: aastore
    //   812: invokevirtual 85	java/lang/reflect/Method:invoke	(Ljava/lang/Object;[Ljava/lang/Object;)Ljava/lang/Object;
    //   815: astore 8
    //   817: aload 6
    //   819: aload 7
    //   821: aload 8
    //   823: checkcast 297	java/lang/String
    //   826: invokevirtual 371	java/lang/StringBuilder:append	(Ljava/lang/String;)Ljava/lang/StringBuilder;
    //   829: aload_1
    //   830: invokevirtual 374	java/lang/StringBuilder:append	(Ljava/lang/Object;)Ljava/lang/StringBuilder;
    //   833: invokevirtual 377	java/lang/StringBuilder:toString	()Ljava/lang/String;
    //   836: invokestatic 381	uuuuuu/rvvvrv:bqqqq00710071q0071q0071	(Ljava/lang/String;Ljava/lang/String;)V
    //   839: return
    //   840: astore_1
    //   841: aload_1
    //   842: invokevirtual 113	java/lang/reflect/InvocationTargetException:getCause	()Ljava/lang/Throwable;
    //   845: athrow
    //   846: astore_1
    //   847: aload_1
    //   848: invokevirtual 113	java/lang/reflect/InvocationTargetException:getCause	()Ljava/lang/Throwable;
    //   851: athrow
    //   852: astore_1
    //   853: aload_1
    //   854: invokevirtual 113	java/lang/reflect/InvocationTargetException:getCause	()Ljava/lang/Throwable;
    //   857: athrow
    //   858: astore_1
    //   859: aload_1
    //   860: invokevirtual 113	java/lang/reflect/InvocationTargetException:getCause	()Ljava/lang/Throwable;
    //   863: athrow
    //   864: astore_1
    //   865: aload_1
    //   866: invokevirtual 113	java/lang/reflect/InvocationTargetException:getCause	()Ljava/lang/Throwable;
    //   869: athrow
    //   870: astore_1
    //   871: aload_1
    //   872: invokevirtual 113	java/lang/reflect/InvocationTargetException:getCause	()Ljava/lang/Throwable;
    //   875: athrow
    //   876: astore_1
    //   877: aload_1
    //   878: invokevirtual 113	java/lang/reflect/InvocationTargetException:getCause	()Ljava/lang/Throwable;
    //   881: athrow
    //   882: astore_1
    //   883: aload_1
    //   884: invokevirtual 113	java/lang/reflect/InvocationTargetException:getCause	()Ljava/lang/Throwable;
    //   887: athrow
    //   888: astore_1
    //   889: aload_1
    //   890: invokevirtual 113	java/lang/reflect/InvocationTargetException:getCause	()Ljava/lang/Throwable;
    //   893: athrow
    //   894: astore_1
    //   895: aload_1
    //   896: invokevirtual 113	java/lang/reflect/InvocationTargetException:getCause	()Ljava/lang/Throwable;
    //   899: athrow
    //   900: goto -561 -> 339
    //   903: goto -564 -> 339
    // Local variable table:
    //   start	length	slot	name	signature
    //   0	906	0	this	nnwwnn
    //   0	906	1	paramException	Exception
    //   116	584	2	i	int
    //   397	225	3	j	int
    //   401	86	4	k	int
    //   444	46	5	m	int
    //   3	815	6	localObject1	Object
    //   46	774	7	localObject2	Object
    //   375	447	8	localObject3	Object
    // Exception table:
    //   from	to	target	type
    //   316	328	840	java/lang/reflect/InvocationTargetException
    //   377	389	846	java/lang/reflect/InvocationTargetException
    //   424	436	852	java/lang/reflect/InvocationTargetException
    //   469	481	858	java/lang/reflect/InvocationTargetException
    //   204	246	864	java/lang/reflect/InvocationTargetException
    //   776	817	870	java/lang/reflect/InvocationTargetException
    //   48	82	876	java/lang/reflect/InvocationTargetException
    //   672	684	882	java/lang/reflect/InvocationTargetException
    //   525	537	888	java/lang/reflect/InvocationTargetException
    //   567	579	894	java/lang/reflect/InvocationTargetException
  }
  
  /* Error */
  public void bqq0071q0071007100710071qq()
  {
    // Byte code:
    //   0: aload_0
    //   1: getfield 117	uuuuuu/nnwwnn:b0063cc00630063006300630063c	Luuuuuu/vkvkkk;
    //   4: ifnull +278 -> 282
    //   7: aload_0
    //   8: getfield 117	uuuuuu/nnwwnn:b0063cc00630063006300630063c	Luuuuuu/vkvkkk;
    //   11: invokevirtual 385	uuuuuu/vkvkkk:bqq0071qq007100710071qq	()V
    //   14: getstatic 57	uuuuuu/nnwwnn:b0063c006300630063006300630063c	I
    //   17: istore_1
    //   18: getstatic 57	uuuuuu/nnwwnn:b0063c006300630063006300630063c	I
    //   21: istore_2
    //   22: iload_2
    //   23: getstatic 59	uuuuuu/nnwwnn:b00630063c00630063006300630063c	I
    //   26: iload_2
    //   27: iadd
    //   28: imul
    //   29: getstatic 61	uuuuuu/nnwwnn:bcc006300630063006300630063c	I
    //   32: irem
    //   33: tableswitch	default:+19->52, 0:+97->130
    //   52: ldc 2
    //   54: ldc -97
    //   56: bipush 107
    //   58: iconst_1
    //   59: invokestatic 97	xxxxxx/uxxxxx:bb00620062bb0062b0062b0062	(Ljava/lang/String;CC)Ljava/lang/String;
    //   62: iconst_0
    //   63: anewarray 73	java/lang/Class
    //   66: invokevirtual 77	java/lang/Class:getMethod	(Ljava/lang/String;[Ljava/lang/Class;)Ljava/lang/reflect/Method;
    //   69: astore_3
    //   70: aload_3
    //   71: aconst_null
    //   72: iconst_0
    //   73: anewarray 79	java/lang/Object
    //   76: invokevirtual 85	java/lang/reflect/Method:invoke	(Ljava/lang/Object;[Ljava/lang/Object;)Ljava/lang/Object;
    //   79: astore_3
    //   80: aload_3
    //   81: checkcast 87	java/lang/Integer
    //   84: invokevirtual 91	java/lang/Integer:intValue	()I
    //   87: putstatic 57	uuuuuu/nnwwnn:b0063c006300630063006300630063c	I
    //   90: ldc 2
    //   92: ldc_w 387
    //   95: sipush 219
    //   98: iconst_0
    //   99: invokestatic 97	xxxxxx/uxxxxx:bb00620062bb0062b0062b0062	(Ljava/lang/String;CC)Ljava/lang/String;
    //   102: iconst_0
    //   103: anewarray 73	java/lang/Class
    //   106: invokevirtual 77	java/lang/Class:getMethod	(Ljava/lang/String;[Ljava/lang/Class;)Ljava/lang/reflect/Method;
    //   109: astore_3
    //   110: aload_3
    //   111: aconst_null
    //   112: iconst_0
    //   113: anewarray 79	java/lang/Object
    //   116: invokevirtual 85	java/lang/reflect/Method:invoke	(Ljava/lang/Object;[Ljava/lang/Object;)Ljava/lang/Object;
    //   119: astore_3
    //   120: aload_3
    //   121: checkcast 87	java/lang/Integer
    //   124: invokevirtual 91	java/lang/Integer:intValue	()I
    //   127: putstatic 63	uuuuuu/nnwwnn:bc0063c00630063006300630063c	I
    //   130: getstatic 59	uuuuuu/nnwwnn:b00630063c00630063006300630063c	I
    //   133: iload_1
    //   134: iadd
    //   135: iload_1
    //   136: imul
    //   137: getstatic 61	uuuuuu/nnwwnn:bcc006300630063006300630063c	I
    //   140: irem
    //   141: tableswitch	default:+19->160, 0:+141->282
    //   160: ldc 2
    //   162: ldc_w 389
    //   165: bipush 113
    //   167: bipush 79
    //   169: iconst_3
    //   170: invokestatic 71	xxxxxx/uxxxxx:bbbb0062b0062b0062b0062	(Ljava/lang/String;CCC)Ljava/lang/String;
    //   173: iconst_0
    //   174: anewarray 73	java/lang/Class
    //   177: invokevirtual 77	java/lang/Class:getMethod	(Ljava/lang/String;[Ljava/lang/Class;)Ljava/lang/reflect/Method;
    //   180: astore_3
    //   181: aload_3
    //   182: aconst_null
    //   183: iconst_0
    //   184: anewarray 79	java/lang/Object
    //   187: invokevirtual 85	java/lang/reflect/Method:invoke	(Ljava/lang/Object;[Ljava/lang/Object;)Ljava/lang/Object;
    //   190: astore_3
    //   191: aload_3
    //   192: checkcast 87	java/lang/Integer
    //   195: invokevirtual 91	java/lang/Integer:intValue	()I
    //   198: istore_1
    //   199: getstatic 57	uuuuuu/nnwwnn:b0063c006300630063006300630063c	I
    //   202: istore_2
    //   203: iload_2
    //   204: getstatic 59	uuuuuu/nnwwnn:b00630063c00630063006300630063c	I
    //   207: iload_2
    //   208: iadd
    //   209: imul
    //   210: getstatic 61	uuuuuu/nnwwnn:bcc006300630063006300630063c	I
    //   213: irem
    //   214: tableswitch	default:+18->232, 0:+28->242
    //   232: bipush 32
    //   234: putstatic 57	uuuuuu/nnwwnn:b0063c006300630063006300630063c	I
    //   237: bipush 27
    //   239: putstatic 63	uuuuuu/nnwwnn:bc0063c00630063006300630063c	I
    //   242: getstatic 57	uuuuuu/nnwwnn:b0063c006300630063006300630063c	I
    //   245: getstatic 59	uuuuuu/nnwwnn:b00630063c00630063006300630063c	I
    //   248: iadd
    //   249: getstatic 57	uuuuuu/nnwwnn:b0063c006300630063006300630063c	I
    //   252: imul
    //   253: getstatic 61	uuuuuu/nnwwnn:bcc006300630063006300630063c	I
    //   256: irem
    //   257: getstatic 63	uuuuuu/nnwwnn:bc0063c00630063006300630063c	I
    //   260: if_icmpeq +13 -> 273
    //   263: bipush 88
    //   265: putstatic 57	uuuuuu/nnwwnn:b0063c006300630063006300630063c	I
    //   268: bipush 52
    //   270: putstatic 63	uuuuuu/nnwwnn:bc0063c00630063006300630063c	I
    //   273: iload_1
    //   274: putstatic 57	uuuuuu/nnwwnn:b0063c006300630063006300630063c	I
    //   277: bipush 67
    //   279: putstatic 63	uuuuuu/nnwwnn:bc0063c00630063006300630063c	I
    //   282: return
    //   283: astore_3
    //   284: aload_3
    //   285: invokevirtual 113	java/lang/reflect/InvocationTargetException:getCause	()Ljava/lang/Throwable;
    //   288: athrow
    //   289: astore_3
    //   290: aload_3
    //   291: invokevirtual 113	java/lang/reflect/InvocationTargetException:getCause	()Ljava/lang/Throwable;
    //   294: athrow
    //   295: astore_3
    //   296: aload_3
    //   297: invokevirtual 113	java/lang/reflect/InvocationTargetException:getCause	()Ljava/lang/Throwable;
    //   300: athrow
    // Local variable table:
    //   start	length	slot	name	signature
    //   0	301	0	this	nnwwnn
    //   17	257	1	i	int
    //   21	189	2	j	int
    //   69	123	3	localObject	Object
    //   283	2	3	localInvocationTargetException1	InvocationTargetException
    //   289	2	3	localInvocationTargetException2	InvocationTargetException
    //   295	2	3	localInvocationTargetException3	InvocationTargetException
    // Exception table:
    //   from	to	target	type
    //   181	191	283	java/lang/reflect/InvocationTargetException
    //   110	120	289	java/lang/reflect/InvocationTargetException
    //   70	80	295	java/lang/reflect/InvocationTargetException
  }
  
  /* Error */
  public void bqqq00710071007100710071qq()
  {
    // Byte code:
    //   0: aload_0
    //   1: getfield 117	uuuuuu/nnwwnn:b0063cc00630063006300630063c	Luuuuuu/vkvkkk;
    //   4: ifnull +544 -> 548
    //   7: ldc 2
    //   9: ldc_w 392
    //   12: sipush 173
    //   15: iconst_4
    //   16: invokestatic 97	xxxxxx/uxxxxx:bb00620062bb0062b0062b0062	(Ljava/lang/String;CC)Ljava/lang/String;
    //   19: iconst_0
    //   20: anewarray 73	java/lang/Class
    //   23: invokevirtual 77	java/lang/Class:getMethod	(Ljava/lang/String;[Ljava/lang/Class;)Ljava/lang/reflect/Method;
    //   26: astore 5
    //   28: aload 5
    //   30: aconst_null
    //   31: iconst_0
    //   32: anewarray 79	java/lang/Object
    //   35: invokevirtual 85	java/lang/reflect/Method:invoke	(Ljava/lang/Object;[Ljava/lang/Object;)Ljava/lang/Object;
    //   38: astore 5
    //   40: aload 5
    //   42: checkcast 87	java/lang/Integer
    //   45: invokevirtual 91	java/lang/Integer:intValue	()I
    //   48: istore_1
    //   49: getstatic 57	uuuuuu/nnwwnn:b0063c006300630063006300630063c	I
    //   52: getstatic 59	uuuuuu/nnwwnn:b00630063c00630063006300630063c	I
    //   55: iadd
    //   56: getstatic 57	uuuuuu/nnwwnn:b0063c006300630063006300630063c	I
    //   59: imul
    //   60: getstatic 61	uuuuuu/nnwwnn:bcc006300630063006300630063c	I
    //   63: irem
    //   64: getstatic 63	uuuuuu/nnwwnn:bc0063c00630063006300630063c	I
    //   67: if_icmpeq +13 -> 80
    //   70: bipush 19
    //   72: putstatic 57	uuuuuu/nnwwnn:b0063c006300630063006300630063c	I
    //   75: bipush 59
    //   77: putstatic 63	uuuuuu/nnwwnn:bc0063c00630063006300630063c	I
    //   80: ldc 2
    //   82: ldc_w 394
    //   85: bipush 44
    //   87: iconst_4
    //   88: invokestatic 97	xxxxxx/uxxxxx:bb00620062bb0062b0062b0062	(Ljava/lang/String;CC)Ljava/lang/String;
    //   91: iconst_0
    //   92: anewarray 73	java/lang/Class
    //   95: invokevirtual 77	java/lang/Class:getMethod	(Ljava/lang/String;[Ljava/lang/Class;)Ljava/lang/reflect/Method;
    //   98: astore 5
    //   100: aload 5
    //   102: aconst_null
    //   103: iconst_0
    //   104: anewarray 79	java/lang/Object
    //   107: invokevirtual 85	java/lang/reflect/Method:invoke	(Ljava/lang/Object;[Ljava/lang/Object;)Ljava/lang/Object;
    //   110: astore 5
    //   112: aload 5
    //   114: checkcast 87	java/lang/Integer
    //   117: invokevirtual 91	java/lang/Integer:intValue	()I
    //   120: istore_2
    //   121: getstatic 57	uuuuuu/nnwwnn:b0063c006300630063006300630063c	I
    //   124: istore_3
    //   125: getstatic 59	uuuuuu/nnwwnn:b00630063c00630063006300630063c	I
    //   128: istore 4
    //   130: ldc 2
    //   132: ldc_w 396
    //   135: sipush 238
    //   138: iconst_3
    //   139: invokestatic 97	xxxxxx/uxxxxx:bb00620062bb0062b0062b0062	(Ljava/lang/String;CC)Ljava/lang/String;
    //   142: iconst_0
    //   143: anewarray 73	java/lang/Class
    //   146: invokevirtual 77	java/lang/Class:getMethod	(Ljava/lang/String;[Ljava/lang/Class;)Ljava/lang/reflect/Method;
    //   149: astore 5
    //   151: aload 5
    //   153: aconst_null
    //   154: iconst_0
    //   155: anewarray 79	java/lang/Object
    //   158: invokevirtual 85	java/lang/reflect/Method:invoke	(Ljava/lang/Object;[Ljava/lang/Object;)Ljava/lang/Object;
    //   161: astore 5
    //   163: iload 4
    //   165: iload_3
    //   166: iadd
    //   167: iload_3
    //   168: imul
    //   169: aload 5
    //   171: checkcast 87	java/lang/Integer
    //   174: invokevirtual 91	java/lang/Integer:intValue	()I
    //   177: irem
    //   178: tableswitch	default:+18->196, 0:+27->205
    //   196: bipush 94
    //   198: putstatic 57	uuuuuu/nnwwnn:b0063c006300630063006300630063c	I
    //   201: iconst_2
    //   202: putstatic 63	uuuuuu/nnwwnn:bc0063c00630063006300630063c	I
    //   205: ldc 2
    //   207: ldc_w 398
    //   210: bipush 14
    //   212: bipush 119
    //   214: iconst_3
    //   215: invokestatic 71	xxxxxx/uxxxxx:bbbb0062b0062b0062b0062	(Ljava/lang/String;CCC)Ljava/lang/String;
    //   218: iconst_0
    //   219: anewarray 73	java/lang/Class
    //   222: invokevirtual 77	java/lang/Class:getMethod	(Ljava/lang/String;[Ljava/lang/Class;)Ljava/lang/reflect/Method;
    //   225: astore 5
    //   227: aload 5
    //   229: aconst_null
    //   230: iconst_0
    //   231: anewarray 79	java/lang/Object
    //   234: invokevirtual 85	java/lang/reflect/Method:invoke	(Ljava/lang/Object;[Ljava/lang/Object;)Ljava/lang/Object;
    //   237: astore 5
    //   239: aload 5
    //   241: checkcast 87	java/lang/Integer
    //   244: invokevirtual 91	java/lang/Integer:intValue	()I
    //   247: iload_1
    //   248: iload_2
    //   249: iadd
    //   250: imul
    //   251: getstatic 61	uuuuuu/nnwwnn:bcc006300630063006300630063c	I
    //   254: irem
    //   255: getstatic 63	uuuuuu/nnwwnn:bc0063c00630063006300630063c	I
    //   258: if_icmpeq +283 -> 541
    //   261: ldc 2
    //   263: ldc_w 263
    //   266: bipush 64
    //   268: iconst_1
    //   269: invokestatic 97	xxxxxx/uxxxxx:bb00620062bb0062b0062b0062	(Ljava/lang/String;CC)Ljava/lang/String;
    //   272: iconst_0
    //   273: anewarray 73	java/lang/Class
    //   276: invokevirtual 77	java/lang/Class:getMethod	(Ljava/lang/String;[Ljava/lang/Class;)Ljava/lang/reflect/Method;
    //   279: astore 5
    //   281: aload 5
    //   283: aconst_null
    //   284: iconst_0
    //   285: anewarray 79	java/lang/Object
    //   288: invokevirtual 85	java/lang/reflect/Method:invoke	(Ljava/lang/Object;[Ljava/lang/Object;)Ljava/lang/Object;
    //   291: astore 5
    //   293: aload 5
    //   295: checkcast 87	java/lang/Integer
    //   298: invokevirtual 91	java/lang/Integer:intValue	()I
    //   301: putstatic 57	uuuuuu/nnwwnn:b0063c006300630063006300630063c	I
    //   304: ldc 2
    //   306: ldc -5
    //   308: sipush 169
    //   311: bipush 78
    //   313: iconst_0
    //   314: invokestatic 71	xxxxxx/uxxxxx:bbbb0062b0062b0062b0062	(Ljava/lang/String;CCC)Ljava/lang/String;
    //   317: iconst_0
    //   318: anewarray 73	java/lang/Class
    //   321: invokevirtual 77	java/lang/Class:getMethod	(Ljava/lang/String;[Ljava/lang/Class;)Ljava/lang/reflect/Method;
    //   324: astore 5
    //   326: aload 5
    //   328: aconst_null
    //   329: iconst_0
    //   330: anewarray 79	java/lang/Object
    //   333: invokevirtual 85	java/lang/reflect/Method:invoke	(Ljava/lang/Object;[Ljava/lang/Object;)Ljava/lang/Object;
    //   336: astore 5
    //   338: aload 5
    //   340: checkcast 87	java/lang/Integer
    //   343: invokevirtual 91	java/lang/Integer:intValue	()I
    //   346: putstatic 63	uuuuuu/nnwwnn:bc0063c00630063006300630063c	I
    //   349: ldc 2
    //   351: ldc_w 400
    //   354: sipush 185
    //   357: sipush 253
    //   360: iconst_2
    //   361: invokestatic 71	xxxxxx/uxxxxx:bbbb0062b0062b0062b0062	(Ljava/lang/String;CCC)Ljava/lang/String;
    //   364: iconst_0
    //   365: anewarray 73	java/lang/Class
    //   368: invokevirtual 77	java/lang/Class:getMethod	(Ljava/lang/String;[Ljava/lang/Class;)Ljava/lang/reflect/Method;
    //   371: astore 5
    //   373: aload 5
    //   375: aconst_null
    //   376: iconst_0
    //   377: anewarray 79	java/lang/Object
    //   380: invokevirtual 85	java/lang/reflect/Method:invoke	(Ljava/lang/Object;[Ljava/lang/Object;)Ljava/lang/Object;
    //   383: astore 5
    //   385: aload 5
    //   387: checkcast 87	java/lang/Integer
    //   390: invokevirtual 91	java/lang/Integer:intValue	()I
    //   393: istore_1
    //   394: getstatic 59	uuuuuu/nnwwnn:b00630063c00630063006300630063c	I
    //   397: istore_2
    //   398: ldc 2
    //   400: ldc -82
    //   402: bipush 109
    //   404: iconst_0
    //   405: invokestatic 97	xxxxxx/uxxxxx:bb00620062bb0062b0062b0062	(Ljava/lang/String;CC)Ljava/lang/String;
    //   408: iconst_0
    //   409: anewarray 73	java/lang/Class
    //   412: invokevirtual 77	java/lang/Class:getMethod	(Ljava/lang/String;[Ljava/lang/Class;)Ljava/lang/reflect/Method;
    //   415: astore 5
    //   417: aload 5
    //   419: aconst_null
    //   420: iconst_0
    //   421: anewarray 79	java/lang/Object
    //   424: invokevirtual 85	java/lang/reflect/Method:invoke	(Ljava/lang/Object;[Ljava/lang/Object;)Ljava/lang/Object;
    //   427: astore 5
    //   429: aload 5
    //   431: checkcast 87	java/lang/Integer
    //   434: invokevirtual 91	java/lang/Integer:intValue	()I
    //   437: istore_3
    //   438: ldc 2
    //   440: ldc_w 402
    //   443: bipush 31
    //   445: iconst_0
    //   446: invokestatic 97	xxxxxx/uxxxxx:bb00620062bb0062b0062b0062	(Ljava/lang/String;CC)Ljava/lang/String;
    //   449: iconst_0
    //   450: anewarray 73	java/lang/Class
    //   453: invokevirtual 77	java/lang/Class:getMethod	(Ljava/lang/String;[Ljava/lang/Class;)Ljava/lang/reflect/Method;
    //   456: astore 5
    //   458: aload 5
    //   460: aconst_null
    //   461: iconst_0
    //   462: anewarray 79	java/lang/Object
    //   465: invokevirtual 85	java/lang/reflect/Method:invoke	(Ljava/lang/Object;[Ljava/lang/Object;)Ljava/lang/Object;
    //   468: astore 5
    //   470: iload_2
    //   471: iload_1
    //   472: iadd
    //   473: iload_3
    //   474: imul
    //   475: aload 5
    //   477: checkcast 87	java/lang/Integer
    //   480: invokevirtual 91	java/lang/Integer:intValue	()I
    //   483: irem
    //   484: getstatic 63	uuuuuu/nnwwnn:bc0063c00630063006300630063c	I
    //   487: if_icmpeq +54 -> 541
    //   490: bipush 72
    //   492: putstatic 57	uuuuuu/nnwwnn:b0063c006300630063006300630063c	I
    //   495: ldc 2
    //   497: ldc_w 404
    //   500: bipush 122
    //   502: sipush 136
    //   505: iconst_0
    //   506: invokestatic 71	xxxxxx/uxxxxx:bbbb0062b0062b0062b0062	(Ljava/lang/String;CCC)Ljava/lang/String;
    //   509: iconst_0
    //   510: anewarray 73	java/lang/Class
    //   513: invokevirtual 77	java/lang/Class:getMethod	(Ljava/lang/String;[Ljava/lang/Class;)Ljava/lang/reflect/Method;
    //   516: astore 5
    //   518: aload 5
    //   520: aconst_null
    //   521: iconst_0
    //   522: anewarray 79	java/lang/Object
    //   525: invokevirtual 85	java/lang/reflect/Method:invoke	(Ljava/lang/Object;[Ljava/lang/Object;)Ljava/lang/Object;
    //   528: astore 5
    //   530: aload 5
    //   532: checkcast 87	java/lang/Integer
    //   535: invokevirtual 91	java/lang/Integer:intValue	()I
    //   538: putstatic 63	uuuuuu/nnwwnn:bc0063c00630063006300630063c	I
    //   541: aload_0
    //   542: getfield 117	uuuuuu/nnwwnn:b0063cc00630063006300630063c	Luuuuuu/vkvkkk;
    //   545: invokevirtual 254	uuuuuu/vkvkkk:bq0071qqq007100710071qq	()V
    //   548: return
    //   549: astore 5
    //   551: aload 5
    //   553: invokevirtual 113	java/lang/reflect/InvocationTargetException:getCause	()Ljava/lang/Throwable;
    //   556: athrow
    //   557: astore 5
    //   559: aload 5
    //   561: invokevirtual 113	java/lang/reflect/InvocationTargetException:getCause	()Ljava/lang/Throwable;
    //   564: athrow
    //   565: astore 5
    //   567: aload 5
    //   569: invokevirtual 113	java/lang/reflect/InvocationTargetException:getCause	()Ljava/lang/Throwable;
    //   572: athrow
    //   573: astore 5
    //   575: aload 5
    //   577: invokevirtual 113	java/lang/reflect/InvocationTargetException:getCause	()Ljava/lang/Throwable;
    //   580: athrow
    //   581: astore 5
    //   583: aload 5
    //   585: invokevirtual 113	java/lang/reflect/InvocationTargetException:getCause	()Ljava/lang/Throwable;
    //   588: athrow
    //   589: astore 5
    //   591: aload 5
    //   593: invokevirtual 113	java/lang/reflect/InvocationTargetException:getCause	()Ljava/lang/Throwable;
    //   596: athrow
    //   597: astore 5
    //   599: aload 5
    //   601: invokevirtual 113	java/lang/reflect/InvocationTargetException:getCause	()Ljava/lang/Throwable;
    //   604: athrow
    //   605: astore 5
    //   607: aload 5
    //   609: invokevirtual 113	java/lang/reflect/InvocationTargetException:getCause	()Ljava/lang/Throwable;
    //   612: athrow
    //   613: astore 5
    //   615: aload 5
    //   617: invokevirtual 113	java/lang/reflect/InvocationTargetException:getCause	()Ljava/lang/Throwable;
    //   620: athrow
    //   621: astore 5
    //   623: aload 5
    //   625: invokevirtual 113	java/lang/reflect/InvocationTargetException:getCause	()Ljava/lang/Throwable;
    //   628: athrow
    // Local variable table:
    //   start	length	slot	name	signature
    //   0	629	0	this	nnwwnn
    //   48	425	1	i	int
    //   120	353	2	j	int
    //   124	351	3	k	int
    //   128	39	4	m	int
    //   26	505	5	localObject	Object
    //   549	3	5	localInvocationTargetException1	InvocationTargetException
    //   557	3	5	localInvocationTargetException2	InvocationTargetException
    //   565	3	5	localInvocationTargetException3	InvocationTargetException
    //   573	3	5	localInvocationTargetException4	InvocationTargetException
    //   581	3	5	localInvocationTargetException5	InvocationTargetException
    //   589	3	5	localInvocationTargetException6	InvocationTargetException
    //   597	3	5	localInvocationTargetException7	InvocationTargetException
    //   605	3	5	localInvocationTargetException8	InvocationTargetException
    //   613	3	5	localInvocationTargetException9	InvocationTargetException
    //   621	3	5	localInvocationTargetException10	InvocationTargetException
    // Exception table:
    //   from	to	target	type
    //   28	40	549	java/lang/reflect/InvocationTargetException
    //   373	385	557	java/lang/reflect/InvocationTargetException
    //   417	429	565	java/lang/reflect/InvocationTargetException
    //   458	470	573	java/lang/reflect/InvocationTargetException
    //   100	112	581	java/lang/reflect/InvocationTargetException
    //   151	163	589	java/lang/reflect/InvocationTargetException
    //   281	293	597	java/lang/reflect/InvocationTargetException
    //   326	338	605	java/lang/reflect/InvocationTargetException
    //   227	239	613	java/lang/reflect/InvocationTargetException
    //   518	530	621	java/lang/reflect/InvocationTargetException
  }
}
