package uuuuuu;

import android.content.res.ColorStateList;
import android.graphics.drawable.Drawable;
import android.os.Build.VERSION;
import android.support.v4.graphics.drawable.DrawableCompat;

public class nooonn
{
  public static int b006600660066fff0066ff = 0;
  private static final int b00660066ffff0066ff = 16842912;
  private static final int b0066f0066fff0066ff = 16842919;
  public static int b0066ff0066ff0066ff = 2;
  public static int bf00660066fff0066ff = 49;
  private static final int bff0066fff0066ff = 16842910;
  public static int bfff0066ff0066ff = 1;
  
  public nooonn() {}
  
  public static int b006B006B006B006Bkkk006Bk006B()
  {
    return 21;
  }
  
  /* Error */
  public static int b006B006Bkk006Bkk006Bk006B(android.content.Context paramContext)
  {
    // Byte code:
    //   0: getstatic 35	android/os/Build$VERSION:SDK_INT	I
    //   3: bipush 21
    //   5: if_icmplt +33 -> 38
    //   8: ldc 36
    //   10: istore_1
    //   11: new 38	android/util/TypedValue
    //   14: dup
    //   15: invokespecial 39	android/util/TypedValue:<init>	()V
    //   18: astore 4
    //   20: aload_0
    //   21: invokevirtual 45	android/content/Context:getTheme	()Landroid/content/res/Resources$Theme;
    //   24: iload_1
    //   25: aload 4
    //   27: iconst_1
    //   28: invokevirtual 51	android/content/res/Resources$Theme:resolveAttribute	(ILandroid/util/TypedValue;Z)Z
    //   31: pop
    //   32: aload 4
    //   34: getfield 54	android/util/TypedValue:data	I
    //   37: ireturn
    //   38: aload_0
    //   39: invokevirtual 58	android/content/Context:getResources	()Landroid/content/res/Resources;
    //   42: astore 4
    //   44: ldc 60
    //   46: ldc 62
    //   48: sipush 157
    //   51: iconst_1
    //   52: invokestatic 68	xxxxxx/uxxxxx:bb00620062bb0062b0062b0062	(Ljava/lang/String;CC)Ljava/lang/String;
    //   55: iconst_4
    //   56: anewarray 70	java/lang/Class
    //   59: dup
    //   60: iconst_0
    //   61: ldc 72
    //   63: aastore
    //   64: dup
    //   65: iconst_1
    //   66: getstatic 78	java/lang/Character:TYPE	Ljava/lang/Class;
    //   69: aastore
    //   70: dup
    //   71: iconst_2
    //   72: getstatic 78	java/lang/Character:TYPE	Ljava/lang/Class;
    //   75: aastore
    //   76: dup
    //   77: iconst_3
    //   78: getstatic 78	java/lang/Character:TYPE	Ljava/lang/Class;
    //   81: aastore
    //   82: invokevirtual 82	java/lang/Class:getMethod	(Ljava/lang/String;[Ljava/lang/Class;)Ljava/lang/reflect/Method;
    //   85: astore 5
    //   87: aload 5
    //   89: aconst_null
    //   90: iconst_4
    //   91: anewarray 4	java/lang/Object
    //   94: dup
    //   95: iconst_0
    //   96: ldc 84
    //   98: aastore
    //   99: dup
    //   100: iconst_1
    //   101: sipush 182
    //   104: invokestatic 88	java/lang/Character:valueOf	(C)Ljava/lang/Character;
    //   107: aastore
    //   108: dup
    //   109: iconst_2
    //   110: sipush 218
    //   113: invokestatic 88	java/lang/Character:valueOf	(C)Ljava/lang/Character;
    //   116: aastore
    //   117: dup
    //   118: iconst_3
    //   119: iconst_3
    //   120: invokestatic 88	java/lang/Character:valueOf	(C)Ljava/lang/Character;
    //   123: aastore
    //   124: invokevirtual 94	java/lang/reflect/Method:invoke	(Ljava/lang/Object;[Ljava/lang/Object;)Ljava/lang/Object;
    //   127: astore 5
    //   129: aload 5
    //   131: checkcast 72	java/lang/String
    //   134: astore 5
    //   136: ldc 60
    //   138: ldc 96
    //   140: bipush 104
    //   142: iconst_0
    //   143: invokestatic 68	xxxxxx/uxxxxx:bb00620062bb0062b0062b0062	(Ljava/lang/String;CC)Ljava/lang/String;
    //   146: iconst_3
    //   147: anewarray 70	java/lang/Class
    //   150: dup
    //   151: iconst_0
    //   152: ldc 72
    //   154: aastore
    //   155: dup
    //   156: iconst_1
    //   157: getstatic 78	java/lang/Character:TYPE	Ljava/lang/Class;
    //   160: aastore
    //   161: dup
    //   162: iconst_2
    //   163: getstatic 78	java/lang/Character:TYPE	Ljava/lang/Class;
    //   166: aastore
    //   167: invokevirtual 82	java/lang/Class:getMethod	(Ljava/lang/String;[Ljava/lang/Class;)Ljava/lang/reflect/Method;
    //   170: astore 6
    //   172: aload 6
    //   174: aconst_null
    //   175: iconst_3
    //   176: anewarray 4	java/lang/Object
    //   179: dup
    //   180: iconst_0
    //   181: ldc 98
    //   183: aastore
    //   184: dup
    //   185: iconst_1
    //   186: bipush 104
    //   188: invokestatic 88	java/lang/Character:valueOf	(C)Ljava/lang/Character;
    //   191: aastore
    //   192: dup
    //   193: iconst_2
    //   194: iconst_0
    //   195: invokestatic 88	java/lang/Character:valueOf	(C)Ljava/lang/Character;
    //   198: aastore
    //   199: invokevirtual 94	java/lang/reflect/Method:invoke	(Ljava/lang/Object;[Ljava/lang/Object;)Ljava/lang/Object;
    //   202: astore 6
    //   204: aload 4
    //   206: aload 5
    //   208: aload 6
    //   210: checkcast 72	java/lang/String
    //   213: aload_0
    //   214: invokevirtual 102	android/content/Context:getPackageName	()Ljava/lang/String;
    //   217: invokevirtual 108	android/content/res/Resources:getIdentifier	(Ljava/lang/String;Ljava/lang/String;Ljava/lang/String;)I
    //   220: istore_2
    //   221: iload_2
    //   222: istore_1
    //   223: getstatic 110	uuuuuu/nooonn:bf00660066fff0066ff	I
    //   226: getstatic 112	uuuuuu/nooonn:bfff0066ff0066ff	I
    //   229: iadd
    //   230: getstatic 110	uuuuuu/nooonn:bf00660066fff0066ff	I
    //   233: imul
    //   234: getstatic 114	uuuuuu/nooonn:b0066ff0066ff0066ff	I
    //   237: irem
    //   238: getstatic 116	uuuuuu/nooonn:b006600660066fff0066ff	I
    //   241: if_icmpeq -230 -> 11
    //   244: bipush 27
    //   246: putstatic 110	uuuuuu/nooonn:bf00660066fff0066ff	I
    //   249: bipush 68
    //   251: putstatic 116	uuuuuu/nooonn:b006600660066fff0066ff	I
    //   254: getstatic 110	uuuuuu/nooonn:bf00660066fff0066ff	I
    //   257: istore_3
    //   258: iload_2
    //   259: istore_1
    //   260: iload_3
    //   261: getstatic 112	uuuuuu/nooonn:bfff0066ff0066ff	I
    //   264: iload_3
    //   265: iadd
    //   266: imul
    //   267: getstatic 114	uuuuuu/nooonn:b0066ff0066ff0066ff	I
    //   270: irem
    //   271: tableswitch	default:+17->288, 0:+-260->11
    //   288: invokestatic 118	uuuuuu/nooonn:b006B006B006B006Bkkk006Bk006B	()I
    //   291: putstatic 110	uuuuuu/nooonn:bf00660066fff0066ff	I
    //   294: bipush 38
    //   296: putstatic 116	uuuuuu/nooonn:b006600660066fff0066ff	I
    //   299: iload_2
    //   300: istore_1
    //   301: goto -290 -> 11
    //   304: astore_0
    //   305: aload_0
    //   306: invokevirtual 122	java/lang/reflect/InvocationTargetException:getCause	()Ljava/lang/Throwable;
    //   309: athrow
    //   310: astore_0
    //   311: aload_0
    //   312: invokevirtual 122	java/lang/reflect/InvocationTargetException:getCause	()Ljava/lang/Throwable;
    //   315: athrow
    // Local variable table:
    //   start	length	slot	name	signature
    //   0	316	0	paramContext	android.content.Context
    //   10	291	1	i	int
    //   220	80	2	j	int
    //   257	10	3	k	int
    //   18	187	4	localObject1	Object
    //   85	122	5	localObject2	Object
    //   170	39	6	localObject3	Object
    // Exception table:
    //   from	to	target	type
    //   172	204	304	java/lang/reflect/InvocationTargetException
    //   87	129	310	java/lang/reflect/InvocationTargetException
  }
  
  public static ColorStateList b006Bkkk006Bkk006Bk006B(int paramInt)
  {
    int[] arrayOfInt1 = { -16842910, 16842912 };
    int[] arrayOfInt2 = { -16842910 };
    int[] arrayOfInt3 = { 16842919, -16842912 };
    int[] arrayOfInt4 = { 16842912 };
    if ((bf00660066fff0066ff + bfff0066ff0066ff) * bf00660066fff0066ff % b0066ff0066ff0066ff != b006600660066fff0066ff)
    {
      bf00660066fff0066ff = b006B006B006B006Bkkk006Bk006B();
      b006600660066fff0066ff = 33;
    }
    int[] arrayOfInt5 = { -16842912 };
    int i = bf00660066fff0066ff;
    switch (i * (bfff0066ff0066ff + i) % b0066ff0066ff0066ff)
    {
    default: 
      bf00660066fff0066ff = b006B006B006B006Bkkk006Bk006B();
      b006600660066fff0066ff = 73;
    }
    return new ColorStateList(new int[][] { arrayOfInt1, arrayOfInt2, arrayOfInt3, { 16842919, 16842912 }, arrayOfInt4, arrayOfInt5 }, new int[] { 1442840576 + paramInt, -4539718, 1728053248 + paramInt, 1728053248 + paramInt, 0xFF000000 | paramInt, -1118482 });
  }
  
  public static int bk006B006B006Bkkk006Bk006B()
  {
    return 1;
  }
  
  public static Drawable bk006Bkk006Bkk006Bk006B(Drawable paramDrawable, int paramInt)
  {
    paramDrawable = DrawableCompat.wrap(paramDrawable);
    if (Build.VERSION.SDK_INT >= 21)
    {
      if ((bf00660066fff0066ff + bfff0066ff0066ff) * bf00660066fff0066ff % b0066ff0066ff0066ff != b006600660066fff0066ff)
      {
        bf00660066fff0066ff = b006B006B006B006Bkkk006Bk006B();
        b006600660066fff0066ff = b006B006B006B006Bkkk006Bk006B();
      }
      paramDrawable.mutate().setTint(paramInt);
    }
    do
    {
      return paramDrawable;
      DrawableCompat.setTint(paramDrawable.mutate(), paramInt);
    } while ((bf00660066fff0066ff + bk006B006B006Bkkk006Bk006B()) * bf00660066fff0066ff % b0066ff0066ff0066ff == b006600660066fff0066ff);
    bf00660066fff0066ff = 14;
    b006600660066fff0066ff = 44;
    return paramDrawable;
  }
  
  public static ColorStateList bkkkk006Bkk006Bk006B(int paramInt)
  {
    int[] arrayOfInt1 = { -16842910, 16842912 };
    int i = bf00660066fff0066ff;
    switch (i * (bfff0066ff0066ff + i) % b0066ff0066ff0066ff)
    {
    default: 
      bf00660066fff0066ff = b006B006B006B006Bkkk006Bk006B();
      b006600660066fff0066ff = 73;
    }
    int[] arrayOfInt2 = { 16842912, 16842919 };
    int[] arrayOfInt3 = { -16842912, 16842919 };
    int[] arrayOfInt4 = { 16842912 };
    int[] arrayOfInt5 = { -16842912 };
    if ((bf00660066fff0066ff + bfff0066ff0066ff) * bf00660066fff0066ff % b0066ff0066ff0066ff != b006600660066fff0066ff)
    {
      bf00660066fff0066ff = b006B006B006B006Bkkk006Bk006B();
      b006600660066fff0066ff = 4;
    }
    return new ColorStateList(new int[][] { arrayOfInt1, { -16842910 }, arrayOfInt2, arrayOfInt3, arrayOfInt4, arrayOfInt5 }, new int[] { 520093696 + paramInt, 268435456, 805306368 + paramInt, 536870912, 805306368 + paramInt, 536870912 });
  }
}
