package uuuuuu;

import com.db.pwcc.dbmobile.model.error.DbErrorsPayload;
import com.google.gson.Gson;
import java.lang.reflect.InvocationTargetException;
import java.lang.reflect.Method;
import java.util.HashMap;
import java.util.Map;
import xxxxxx.uxxxxx;

public class ololol<R>
{
  private static final String b0071007100710071q00710071q0071 = "\"u\0240)*26'm\013$7";
  private static final String b007100710071qq00710071q0071 = "1\005\030FE\001)7CC8=;";
  private static final int b00710071q0071q00710071q0071 = 0;
  private static final String b00710071qq007100710071q0071 = "yOu\n\027\034\r\034\036Wtp";
  public static int b00710071qqqqq00710071 = 0;
  private static final int b0071q00710071q00710071q0071;
  private static final String b0071qq0071q00710071q0071 = "@mmtfpw1Ywm";
  private static final String b0071qqq007100710071q0071 = "}Sv{V\001\021\037!\030\037\037";
  public static int b0071qqqqqq00710071 = 1;
  public static final String bq007100710071q00710071q0071 = "9U\033;[YO\0265HZHL";
  private static final String bq0071q0071q00710071q0071 = "?\025,Y]^RZPdZaa!>:";
  private static final String bq0071qq007100710071q0071 = "\034\016\024\f\007\030\tP\030\006\022\b\004\006~{\016\002\007\005";
  public static int bq0071qqqqq00710071 = 2;
  private static final String bqq00710071q00710071q0071 = "\016\f|bl";
  private static final String bqqq0071q00710071q0071 = "\032OODLPHZBVLSS";
  private static final String bqqqq007100710071q0071;
  public static int bqqqqqqq00710071 = 39;
  private hyyhhh b0071007100710071007100710071q0071;
  private int b007100710071q007100710071q0071 = 0;
  private Map<String, String> b00710071q0071007100710071q0071 = new HashMap();
  private int b0071q00710071007100710071q0071;
  private int b0071q0071q007100710071q0071 = b0071q00710071q00710071q0071;
  private Map<String, String> b0071qq0071007100710071q0071 = new HashMap();
  private String bq007100710071007100710071q0071;
  private loolol<R> bq00710071q007100710071q0071;
  private Object bq0071q0071007100710071q0071;
  private boolean bqq00710071007100710071q0071;
  private Gson bqq0071q007100710071q0071;
  private int bqqq0071007100710071q0071;
  
  /* Error */
  static
  {
    // Byte code:
    //   0: getstatic 80	uuuuuu/ololol:b007100710071qq00710071q0071	Ljava/lang/String;
    //   3: astore_3
    //   4: ldc 82
    //   6: ldc 84
    //   8: bipush 11
    //   10: iconst_5
    //   11: invokestatic 90	xxxxxx/uxxxxx:bb00620062bb0062b0062b0062	(Ljava/lang/String;CC)Ljava/lang/String;
    //   14: iconst_3
    //   15: anewarray 92	java/lang/Class
    //   18: dup
    //   19: iconst_0
    //   20: ldc 94
    //   22: aastore
    //   23: dup
    //   24: iconst_1
    //   25: getstatic 100	java/lang/Character:TYPE	Ljava/lang/Class;
    //   28: aastore
    //   29: dup
    //   30: iconst_2
    //   31: getstatic 100	java/lang/Character:TYPE	Ljava/lang/Class;
    //   34: aastore
    //   35: invokevirtual 104	java/lang/Class:getMethod	(Ljava/lang/String;[Ljava/lang/Class;)Ljava/lang/reflect/Method;
    //   38: astore 4
    //   40: aload 4
    //   42: aconst_null
    //   43: iconst_3
    //   44: anewarray 5	java/lang/Object
    //   47: dup
    //   48: iconst_0
    //   49: aload_3
    //   50: aastore
    //   51: dup
    //   52: iconst_1
    //   53: sipush 140
    //   56: invokestatic 108	java/lang/Character:valueOf	(C)Ljava/lang/Character;
    //   59: aastore
    //   60: dup
    //   61: iconst_2
    //   62: iconst_5
    //   63: invokestatic 108	java/lang/Character:valueOf	(C)Ljava/lang/Character;
    //   66: aastore
    //   67: invokevirtual 114	java/lang/reflect/Method:invoke	(Ljava/lang/Object;[Ljava/lang/Object;)Ljava/lang/Object;
    //   70: astore_3
    //   71: aload_3
    //   72: checkcast 94	java/lang/String
    //   75: putstatic 80	uuuuuu/ololol:b007100710071qq00710071q0071	Ljava/lang/String;
    //   78: getstatic 116	uuuuuu/ololol:bqqq0071q00710071q0071	Ljava/lang/String;
    //   81: astore_3
    //   82: ldc 82
    //   84: ldc 118
    //   86: bipush 37
    //   88: iconst_4
    //   89: invokestatic 90	xxxxxx/uxxxxx:bb00620062bb0062b0062b0062	(Ljava/lang/String;CC)Ljava/lang/String;
    //   92: iconst_3
    //   93: anewarray 92	java/lang/Class
    //   96: dup
    //   97: iconst_0
    //   98: ldc 94
    //   100: aastore
    //   101: dup
    //   102: iconst_1
    //   103: getstatic 100	java/lang/Character:TYPE	Ljava/lang/Class;
    //   106: aastore
    //   107: dup
    //   108: iconst_2
    //   109: getstatic 100	java/lang/Character:TYPE	Ljava/lang/Class;
    //   112: aastore
    //   113: invokevirtual 104	java/lang/Class:getMethod	(Ljava/lang/String;[Ljava/lang/Class;)Ljava/lang/reflect/Method;
    //   116: astore 4
    //   118: aload 4
    //   120: aconst_null
    //   121: iconst_3
    //   122: anewarray 5	java/lang/Object
    //   125: dup
    //   126: iconst_0
    //   127: aload_3
    //   128: aastore
    //   129: dup
    //   130: iconst_1
    //   131: bipush 44
    //   133: invokestatic 108	java/lang/Character:valueOf	(C)Ljava/lang/Character;
    //   136: aastore
    //   137: dup
    //   138: iconst_2
    //   139: iconst_1
    //   140: invokestatic 108	java/lang/Character:valueOf	(C)Ljava/lang/Character;
    //   143: aastore
    //   144: invokevirtual 114	java/lang/reflect/Method:invoke	(Ljava/lang/Object;[Ljava/lang/Object;)Ljava/lang/Object;
    //   147: astore_3
    //   148: aload_3
    //   149: checkcast 94	java/lang/String
    //   152: putstatic 116	uuuuuu/ololol:bqqq0071q00710071q0071	Ljava/lang/String;
    //   155: getstatic 120	uuuuuu/ololol:b0071qq0071q00710071q0071	Ljava/lang/String;
    //   158: astore_3
    //   159: ldc 82
    //   161: ldc 122
    //   163: bipush 39
    //   165: iconst_2
    //   166: invokestatic 90	xxxxxx/uxxxxx:bb00620062bb0062b0062b0062	(Ljava/lang/String;CC)Ljava/lang/String;
    //   169: iconst_3
    //   170: anewarray 92	java/lang/Class
    //   173: dup
    //   174: iconst_0
    //   175: ldc 94
    //   177: aastore
    //   178: dup
    //   179: iconst_1
    //   180: getstatic 100	java/lang/Character:TYPE	Ljava/lang/Class;
    //   183: aastore
    //   184: dup
    //   185: iconst_2
    //   186: getstatic 100	java/lang/Character:TYPE	Ljava/lang/Class;
    //   189: aastore
    //   190: invokevirtual 104	java/lang/Class:getMethod	(Ljava/lang/String;[Ljava/lang/Class;)Ljava/lang/reflect/Method;
    //   193: astore 4
    //   195: aload 4
    //   197: aconst_null
    //   198: iconst_3
    //   199: anewarray 5	java/lang/Object
    //   202: dup
    //   203: iconst_0
    //   204: aload_3
    //   205: aastore
    //   206: dup
    //   207: iconst_1
    //   208: bipush 62
    //   210: invokestatic 108	java/lang/Character:valueOf	(C)Ljava/lang/Character;
    //   213: aastore
    //   214: dup
    //   215: iconst_2
    //   216: iconst_1
    //   217: invokestatic 108	java/lang/Character:valueOf	(C)Ljava/lang/Character;
    //   220: aastore
    //   221: invokevirtual 114	java/lang/reflect/Method:invoke	(Ljava/lang/Object;[Ljava/lang/Object;)Ljava/lang/Object;
    //   224: astore_3
    //   225: aload_3
    //   226: checkcast 94	java/lang/String
    //   229: putstatic 120	uuuuuu/ololol:b0071qq0071q00710071q0071	Ljava/lang/String;
    //   232: getstatic 124	uuuuuu/ololol:bq0071q0071q00710071q0071	Ljava/lang/String;
    //   235: astore_3
    //   236: ldc 82
    //   238: ldc 126
    //   240: sipush 157
    //   243: iconst_3
    //   244: invokestatic 90	xxxxxx/uxxxxx:bb00620062bb0062b0062b0062	(Ljava/lang/String;CC)Ljava/lang/String;
    //   247: iconst_3
    //   248: anewarray 92	java/lang/Class
    //   251: dup
    //   252: iconst_0
    //   253: ldc 94
    //   255: aastore
    //   256: dup
    //   257: iconst_1
    //   258: getstatic 100	java/lang/Character:TYPE	Ljava/lang/Class;
    //   261: aastore
    //   262: dup
    //   263: iconst_2
    //   264: getstatic 100	java/lang/Character:TYPE	Ljava/lang/Class;
    //   267: aastore
    //   268: invokevirtual 104	java/lang/Class:getMethod	(Ljava/lang/String;[Ljava/lang/Class;)Ljava/lang/reflect/Method;
    //   271: astore 4
    //   273: aload 4
    //   275: aconst_null
    //   276: iconst_3
    //   277: anewarray 5	java/lang/Object
    //   280: dup
    //   281: iconst_0
    //   282: aload_3
    //   283: aastore
    //   284: dup
    //   285: iconst_1
    //   286: sipush 178
    //   289: invokestatic 108	java/lang/Character:valueOf	(C)Ljava/lang/Character;
    //   292: aastore
    //   293: dup
    //   294: iconst_2
    //   295: iconst_1
    //   296: invokestatic 108	java/lang/Character:valueOf	(C)Ljava/lang/Character;
    //   299: aastore
    //   300: invokevirtual 114	java/lang/reflect/Method:invoke	(Ljava/lang/Object;[Ljava/lang/Object;)Ljava/lang/Object;
    //   303: astore_3
    //   304: aload_3
    //   305: checkcast 94	java/lang/String
    //   308: putstatic 124	uuuuuu/ololol:bq0071q0071q00710071q0071	Ljava/lang/String;
    //   311: getstatic 128	uuuuuu/ololol:bqq00710071q00710071q0071	Ljava/lang/String;
    //   314: astore_3
    //   315: ldc 82
    //   317: ldc -126
    //   319: bipush 109
    //   321: bipush 112
    //   323: iconst_1
    //   324: invokestatic 134	xxxxxx/uxxxxx:bbbb0062b0062b0062b0062	(Ljava/lang/String;CCC)Ljava/lang/String;
    //   327: iconst_4
    //   328: anewarray 92	java/lang/Class
    //   331: dup
    //   332: iconst_0
    //   333: ldc 94
    //   335: aastore
    //   336: dup
    //   337: iconst_1
    //   338: getstatic 100	java/lang/Character:TYPE	Ljava/lang/Class;
    //   341: aastore
    //   342: dup
    //   343: iconst_2
    //   344: getstatic 100	java/lang/Character:TYPE	Ljava/lang/Class;
    //   347: aastore
    //   348: dup
    //   349: iconst_3
    //   350: getstatic 100	java/lang/Character:TYPE	Ljava/lang/Class;
    //   353: aastore
    //   354: invokevirtual 104	java/lang/Class:getMethod	(Ljava/lang/String;[Ljava/lang/Class;)Ljava/lang/reflect/Method;
    //   357: astore 4
    //   359: aload 4
    //   361: aconst_null
    //   362: iconst_4
    //   363: anewarray 5	java/lang/Object
    //   366: dup
    //   367: iconst_0
    //   368: aload_3
    //   369: aastore
    //   370: dup
    //   371: iconst_1
    //   372: sipush 211
    //   375: invokestatic 108	java/lang/Character:valueOf	(C)Ljava/lang/Character;
    //   378: aastore
    //   379: dup
    //   380: iconst_2
    //   381: bipush 114
    //   383: invokestatic 108	java/lang/Character:valueOf	(C)Ljava/lang/Character;
    //   386: aastore
    //   387: dup
    //   388: iconst_3
    //   389: iconst_0
    //   390: invokestatic 108	java/lang/Character:valueOf	(C)Ljava/lang/Character;
    //   393: aastore
    //   394: invokevirtual 114	java/lang/reflect/Method:invoke	(Ljava/lang/Object;[Ljava/lang/Object;)Ljava/lang/Object;
    //   397: astore_3
    //   398: aload_3
    //   399: checkcast 94	java/lang/String
    //   402: putstatic 128	uuuuuu/ololol:bqq00710071q00710071q0071	Ljava/lang/String;
    //   405: getstatic 136	uuuuuu/ololol:bq007100710071q00710071q0071	Ljava/lang/String;
    //   408: astore_3
    //   409: ldc 82
    //   411: ldc -118
    //   413: bipush 12
    //   415: iconst_3
    //   416: invokestatic 90	xxxxxx/uxxxxx:bb00620062bb0062b0062b0062	(Ljava/lang/String;CC)Ljava/lang/String;
    //   419: iconst_4
    //   420: anewarray 92	java/lang/Class
    //   423: dup
    //   424: iconst_0
    //   425: ldc 94
    //   427: aastore
    //   428: dup
    //   429: iconst_1
    //   430: getstatic 100	java/lang/Character:TYPE	Ljava/lang/Class;
    //   433: aastore
    //   434: dup
    //   435: iconst_2
    //   436: getstatic 100	java/lang/Character:TYPE	Ljava/lang/Class;
    //   439: aastore
    //   440: dup
    //   441: iconst_3
    //   442: getstatic 100	java/lang/Character:TYPE	Ljava/lang/Class;
    //   445: aastore
    //   446: invokevirtual 104	java/lang/Class:getMethod	(Ljava/lang/String;[Ljava/lang/Class;)Ljava/lang/reflect/Method;
    //   449: astore 4
    //   451: aload 4
    //   453: aconst_null
    //   454: iconst_4
    //   455: anewarray 5	java/lang/Object
    //   458: dup
    //   459: iconst_0
    //   460: aload_3
    //   461: aastore
    //   462: dup
    //   463: iconst_1
    //   464: sipush 231
    //   467: invokestatic 108	java/lang/Character:valueOf	(C)Ljava/lang/Character;
    //   470: aastore
    //   471: dup
    //   472: iconst_2
    //   473: sipush 166
    //   476: invokestatic 108	java/lang/Character:valueOf	(C)Ljava/lang/Character;
    //   479: aastore
    //   480: dup
    //   481: iconst_3
    //   482: iconst_0
    //   483: invokestatic 108	java/lang/Character:valueOf	(C)Ljava/lang/Character;
    //   486: aastore
    //   487: invokevirtual 114	java/lang/reflect/Method:invoke	(Ljava/lang/Object;[Ljava/lang/Object;)Ljava/lang/Object;
    //   490: astore_3
    //   491: aload_3
    //   492: checkcast 94	java/lang/String
    //   495: putstatic 136	uuuuuu/ololol:bq007100710071q00710071q0071	Ljava/lang/String;
    //   498: getstatic 140	uuuuuu/ololol:b0071007100710071q00710071q0071	Ljava/lang/String;
    //   501: astore_3
    //   502: ldc 82
    //   504: ldc -114
    //   506: sipush 152
    //   509: iconst_0
    //   510: invokestatic 90	xxxxxx/uxxxxx:bb00620062bb0062b0062b0062	(Ljava/lang/String;CC)Ljava/lang/String;
    //   513: iconst_4
    //   514: anewarray 92	java/lang/Class
    //   517: dup
    //   518: iconst_0
    //   519: ldc 94
    //   521: aastore
    //   522: dup
    //   523: iconst_1
    //   524: getstatic 100	java/lang/Character:TYPE	Ljava/lang/Class;
    //   527: aastore
    //   528: dup
    //   529: iconst_2
    //   530: getstatic 100	java/lang/Character:TYPE	Ljava/lang/Class;
    //   533: aastore
    //   534: dup
    //   535: iconst_3
    //   536: getstatic 100	java/lang/Character:TYPE	Ljava/lang/Class;
    //   539: aastore
    //   540: invokevirtual 104	java/lang/Class:getMethod	(Ljava/lang/String;[Ljava/lang/Class;)Ljava/lang/reflect/Method;
    //   543: astore 4
    //   545: aload 4
    //   547: aconst_null
    //   548: iconst_4
    //   549: anewarray 5	java/lang/Object
    //   552: dup
    //   553: iconst_0
    //   554: aload_3
    //   555: aastore
    //   556: dup
    //   557: iconst_1
    //   558: sipush 249
    //   561: invokestatic 108	java/lang/Character:valueOf	(C)Ljava/lang/Character;
    //   564: aastore
    //   565: dup
    //   566: iconst_2
    //   567: sipush 195
    //   570: invokestatic 108	java/lang/Character:valueOf	(C)Ljava/lang/Character;
    //   573: aastore
    //   574: dup
    //   575: iconst_3
    //   576: iconst_1
    //   577: invokestatic 108	java/lang/Character:valueOf	(C)Ljava/lang/Character;
    //   580: aastore
    //   581: invokevirtual 114	java/lang/reflect/Method:invoke	(Ljava/lang/Object;[Ljava/lang/Object;)Ljava/lang/Object;
    //   584: astore_3
    //   585: aload_3
    //   586: checkcast 94	java/lang/String
    //   589: putstatic 140	uuuuuu/ololol:b0071007100710071q00710071q0071	Ljava/lang/String;
    //   592: getstatic 144	uuuuuu/ololol:b0071qqq007100710071q0071	Ljava/lang/String;
    //   595: astore_3
    //   596: ldc 82
    //   598: ldc -110
    //   600: sipush 230
    //   603: iconst_4
    //   604: invokestatic 90	xxxxxx/uxxxxx:bb00620062bb0062b0062b0062	(Ljava/lang/String;CC)Ljava/lang/String;
    //   607: iconst_4
    //   608: anewarray 92	java/lang/Class
    //   611: dup
    //   612: iconst_0
    //   613: ldc 94
    //   615: aastore
    //   616: dup
    //   617: iconst_1
    //   618: getstatic 100	java/lang/Character:TYPE	Ljava/lang/Class;
    //   621: aastore
    //   622: dup
    //   623: iconst_2
    //   624: getstatic 100	java/lang/Character:TYPE	Ljava/lang/Class;
    //   627: aastore
    //   628: dup
    //   629: iconst_3
    //   630: getstatic 100	java/lang/Character:TYPE	Ljava/lang/Class;
    //   633: aastore
    //   634: invokevirtual 104	java/lang/Class:getMethod	(Ljava/lang/String;[Ljava/lang/Class;)Ljava/lang/reflect/Method;
    //   637: astore 4
    //   639: aload 4
    //   641: aconst_null
    //   642: iconst_4
    //   643: anewarray 5	java/lang/Object
    //   646: dup
    //   647: iconst_0
    //   648: aload_3
    //   649: aastore
    //   650: dup
    //   651: iconst_1
    //   652: sipush 192
    //   655: invokestatic 108	java/lang/Character:valueOf	(C)Ljava/lang/Character;
    //   658: aastore
    //   659: dup
    //   660: iconst_2
    //   661: sipush 226
    //   664: invokestatic 108	java/lang/Character:valueOf	(C)Ljava/lang/Character;
    //   667: aastore
    //   668: dup
    //   669: iconst_3
    //   670: iconst_3
    //   671: invokestatic 108	java/lang/Character:valueOf	(C)Ljava/lang/Character;
    //   674: aastore
    //   675: invokevirtual 114	java/lang/reflect/Method:invoke	(Ljava/lang/Object;[Ljava/lang/Object;)Ljava/lang/Object;
    //   678: astore_3
    //   679: aload_3
    //   680: checkcast 94	java/lang/String
    //   683: putstatic 144	uuuuuu/ololol:b0071qqq007100710071q0071	Ljava/lang/String;
    //   686: getstatic 148	uuuuuu/ololol:bq0071qq007100710071q0071	Ljava/lang/String;
    //   689: astore_3
    //   690: ldc 82
    //   692: ldc -106
    //   694: bipush 121
    //   696: iconst_5
    //   697: invokestatic 90	xxxxxx/uxxxxx:bb00620062bb0062b0062b0062	(Ljava/lang/String;CC)Ljava/lang/String;
    //   700: iconst_4
    //   701: anewarray 92	java/lang/Class
    //   704: dup
    //   705: iconst_0
    //   706: ldc 94
    //   708: aastore
    //   709: dup
    //   710: iconst_1
    //   711: getstatic 100	java/lang/Character:TYPE	Ljava/lang/Class;
    //   714: aastore
    //   715: dup
    //   716: iconst_2
    //   717: getstatic 100	java/lang/Character:TYPE	Ljava/lang/Class;
    //   720: aastore
    //   721: dup
    //   722: iconst_3
    //   723: getstatic 100	java/lang/Character:TYPE	Ljava/lang/Class;
    //   726: aastore
    //   727: invokevirtual 104	java/lang/Class:getMethod	(Ljava/lang/String;[Ljava/lang/Class;)Ljava/lang/reflect/Method;
    //   730: astore 4
    //   732: aload 4
    //   734: aconst_null
    //   735: iconst_4
    //   736: anewarray 5	java/lang/Object
    //   739: dup
    //   740: iconst_0
    //   741: aload_3
    //   742: aastore
    //   743: dup
    //   744: iconst_1
    //   745: sipush 136
    //   748: invokestatic 108	java/lang/Character:valueOf	(C)Ljava/lang/Character;
    //   751: aastore
    //   752: dup
    //   753: iconst_2
    //   754: bipush 50
    //   756: invokestatic 108	java/lang/Character:valueOf	(C)Ljava/lang/Character;
    //   759: aastore
    //   760: dup
    //   761: iconst_3
    //   762: iconst_1
    //   763: invokestatic 108	java/lang/Character:valueOf	(C)Ljava/lang/Character;
    //   766: aastore
    //   767: invokevirtual 114	java/lang/reflect/Method:invoke	(Ljava/lang/Object;[Ljava/lang/Object;)Ljava/lang/Object;
    //   770: astore_3
    //   771: aload_3
    //   772: checkcast 94	java/lang/String
    //   775: putstatic 148	uuuuuu/ololol:bq0071qq007100710071q0071	Ljava/lang/String;
    //   778: getstatic 152	uuuuuu/ololol:b00710071qq007100710071q0071	Ljava/lang/String;
    //   781: astore_3
    //   782: ldc 82
    //   784: ldc -102
    //   786: bipush 107
    //   788: iconst_3
    //   789: invokestatic 90	xxxxxx/uxxxxx:bb00620062bb0062b0062b0062	(Ljava/lang/String;CC)Ljava/lang/String;
    //   792: iconst_3
    //   793: anewarray 92	java/lang/Class
    //   796: dup
    //   797: iconst_0
    //   798: ldc 94
    //   800: aastore
    //   801: dup
    //   802: iconst_1
    //   803: getstatic 100	java/lang/Character:TYPE	Ljava/lang/Class;
    //   806: aastore
    //   807: dup
    //   808: iconst_2
    //   809: getstatic 100	java/lang/Character:TYPE	Ljava/lang/Class;
    //   812: aastore
    //   813: invokevirtual 104	java/lang/Class:getMethod	(Ljava/lang/String;[Ljava/lang/Class;)Ljava/lang/reflect/Method;
    //   816: astore 4
    //   818: aload 4
    //   820: aconst_null
    //   821: iconst_3
    //   822: anewarray 5	java/lang/Object
    //   825: dup
    //   826: iconst_0
    //   827: aload_3
    //   828: aastore
    //   829: dup
    //   830: iconst_1
    //   831: bipush 11
    //   833: invokestatic 108	java/lang/Character:valueOf	(C)Ljava/lang/Character;
    //   836: aastore
    //   837: dup
    //   838: iconst_2
    //   839: iconst_0
    //   840: invokestatic 108	java/lang/Character:valueOf	(C)Ljava/lang/Character;
    //   843: aastore
    //   844: invokevirtual 114	java/lang/reflect/Method:invoke	(Ljava/lang/Object;[Ljava/lang/Object;)Ljava/lang/Object;
    //   847: astore_3
    //   848: aload_3
    //   849: checkcast 94	java/lang/String
    //   852: putstatic 152	uuuuuu/ololol:b00710071qq007100710071q0071	Ljava/lang/String;
    //   855: ldc 2
    //   857: invokevirtual 158	java/lang/Class:getSimpleName	()Ljava/lang/String;
    //   860: putstatic 160	uuuuuu/ololol:bqqqq007100710071q0071	Ljava/lang/String;
    //   863: getstatic 166	java/util/concurrent/TimeUnit:SECONDS	Ljava/util/concurrent/TimeUnit;
    //   866: ldc2_w 167
    //   869: invokevirtual 172	java/util/concurrent/TimeUnit:toMillis	(J)J
    //   872: lstore_1
    //   873: getstatic 174	uuuuuu/ololol:bqqqqqqq00710071	I
    //   876: istore_0
    //   877: iload_0
    //   878: getstatic 176	uuuuuu/ololol:b0071qqqqqq00710071	I
    //   881: iload_0
    //   882: iadd
    //   883: imul
    //   884: getstatic 178	uuuuuu/ololol:bq0071qqqqq00710071	I
    //   887: irem
    //   888: tableswitch	default:+20->908, 0:+64->952
    //   908: invokestatic 182	uuuuuu/ololol:b00700070p0070p0070pp00700070	()I
    //   911: putstatic 174	uuuuuu/ololol:bqqqqqqq00710071	I
    //   914: invokestatic 182	uuuuuu/ololol:b00700070p0070p0070pp00700070	()I
    //   917: putstatic 176	uuuuuu/ololol:b0071qqqqqq00710071	I
    //   920: getstatic 174	uuuuuu/ololol:bqqqqqqq00710071	I
    //   923: getstatic 176	uuuuuu/ololol:b0071qqqqqq00710071	I
    //   926: iadd
    //   927: getstatic 174	uuuuuu/ololol:bqqqqqqq00710071	I
    //   930: imul
    //   931: getstatic 178	uuuuuu/ololol:bq0071qqqqq00710071	I
    //   934: irem
    //   935: getstatic 184	uuuuuu/ololol:b00710071qqqqq00710071	I
    //   938: if_icmpeq +14 -> 952
    //   941: invokestatic 182	uuuuuu/ololol:b00700070p0070p0070pp00700070	()I
    //   944: putstatic 174	uuuuuu/ololol:bqqqqqqq00710071	I
    //   947: bipush 56
    //   949: putstatic 184	uuuuuu/ololol:b00710071qqqqq00710071	I
    //   952: lload_1
    //   953: l2i
    //   954: putstatic 186	uuuuuu/ololol:b0071q00710071q00710071q0071	I
    //   957: return
    //   958: astore_3
    //   959: aload_3
    //   960: invokevirtual 190	java/lang/reflect/InvocationTargetException:getCause	()Ljava/lang/Throwable;
    //   963: athrow
    //   964: astore_3
    //   965: aload_3
    //   966: invokevirtual 190	java/lang/reflect/InvocationTargetException:getCause	()Ljava/lang/Throwable;
    //   969: athrow
    //   970: astore_3
    //   971: aload_3
    //   972: invokevirtual 190	java/lang/reflect/InvocationTargetException:getCause	()Ljava/lang/Throwable;
    //   975: athrow
    //   976: astore_3
    //   977: aload_3
    //   978: invokevirtual 190	java/lang/reflect/InvocationTargetException:getCause	()Ljava/lang/Throwable;
    //   981: athrow
    //   982: astore_3
    //   983: aload_3
    //   984: invokevirtual 190	java/lang/reflect/InvocationTargetException:getCause	()Ljava/lang/Throwable;
    //   987: athrow
    //   988: astore_3
    //   989: aload_3
    //   990: invokevirtual 190	java/lang/reflect/InvocationTargetException:getCause	()Ljava/lang/Throwable;
    //   993: athrow
    //   994: astore_3
    //   995: aload_3
    //   996: invokevirtual 190	java/lang/reflect/InvocationTargetException:getCause	()Ljava/lang/Throwable;
    //   999: athrow
    //   1000: astore_3
    //   1001: aload_3
    //   1002: invokevirtual 190	java/lang/reflect/InvocationTargetException:getCause	()Ljava/lang/Throwable;
    //   1005: athrow
    //   1006: astore_3
    //   1007: aload_3
    //   1008: invokevirtual 190	java/lang/reflect/InvocationTargetException:getCause	()Ljava/lang/Throwable;
    //   1011: athrow
    //   1012: astore_3
    //   1013: aload_3
    //   1014: invokevirtual 190	java/lang/reflect/InvocationTargetException:getCause	()Ljava/lang/Throwable;
    //   1017: athrow
    // Local variable table:
    //   start	length	slot	name	signature
    //   876	8	0	i	int
    //   872	81	1	l	long
    //   3	846	3	localObject	Object
    //   958	2	3	localInvocationTargetException1	InvocationTargetException
    //   964	2	3	localInvocationTargetException2	InvocationTargetException
    //   970	2	3	localInvocationTargetException3	InvocationTargetException
    //   976	2	3	localInvocationTargetException4	InvocationTargetException
    //   982	2	3	localInvocationTargetException5	InvocationTargetException
    //   988	2	3	localInvocationTargetException6	InvocationTargetException
    //   994	2	3	localInvocationTargetException7	InvocationTargetException
    //   1000	2	3	localInvocationTargetException8	InvocationTargetException
    //   1006	2	3	localInvocationTargetException9	InvocationTargetException
    //   1012	2	3	localInvocationTargetException10	InvocationTargetException
    //   38	781	4	localMethod	Method
    // Exception table:
    //   from	to	target	type
    //   545	585	958	java/lang/reflect/InvocationTargetException
    //   359	398	964	java/lang/reflect/InvocationTargetException
    //   639	679	970	java/lang/reflect/InvocationTargetException
    //   195	225	976	java/lang/reflect/InvocationTargetException
    //   118	148	982	java/lang/reflect/InvocationTargetException
    //   451	491	988	java/lang/reflect/InvocationTargetException
    //   273	304	994	java/lang/reflect/InvocationTargetException
    //   818	848	1000	java/lang/reflect/InvocationTargetException
    //   40	71	1006	java/lang/reflect/InvocationTargetException
    //   732	771	1012	java/lang/reflect/InvocationTargetException
  }
  
  public ololol(int paramInt, String paramString)
  {
    this(paramInt, paramString, new loolol()
    {
      public static int b007100710071qqqq00710071 = 2;
      public static int b0071q0071qqqq00710071 = 41;
      public static int bq00710071qqqq00710071 = 1;
      
      public static int b00700070007000700070ppp00700070()
      {
        return 0;
      }
      
      public static int bppppp0070pp00700070()
      {
        return 4;
      }
      
      public void b006100610061aaa006100610061a(DbErrorsPayload paramAnonymousDbErrorsPayload)
      {
        paramAnonymousDbErrorsPayload = ololol.bp00700070pp0070pp00700070();
        StringBuilder localStringBuilder = new StringBuilder();
        int i = bppppp0070pp00700070();
        switch (i * (bq00710071qqqq00710071 + i) % b007100710071qqqq00710071)
        {
        default: 
          b0071q0071qqqq00710071 = bppppp0070pp00700070();
          bq00710071qqqq00710071 = bppppp0070pp00700070();
        }
        Object localObject = ppphhp.class.getMethod(uxxxxx.bbbb0062b0062b0062b0062(">T\016\017\027\030YZ\024\025\035\036\030\031!\"c\035\036&'!\"*+l", '¯', 'T', '\002'), new Class[] { String.class, Character.TYPE, Character.TYPE, Character.TYPE });
        try
        {
          localObject = ((Method)localObject).invoke(null, new Object[] { "\b6759g;/><<<B5p;:BDH<<x@JN\027}", Character.valueOf('Î'), Character.valueOf('r'), Character.valueOf('\003') });
          localStringBuilder = localStringBuilder.append((String)localObject);
          localObject = ololol.this;
          i = b0071q0071qqqq00710071;
          switch (i * (bq00710071qqqq00710071 + i) % b007100710071qqqq00710071)
          {
          default: 
            b0071q0071qqqq00710071 = bppppp0070pp00700070();
            bq00710071qqqq00710071 = bppppp0070pp00700070();
          }
          rvvvrv.bqqqq00710071q0071q0071(paramAnonymousDbErrorsPayload, (String)localObject);
          return;
        }
        catch (InvocationTargetException paramAnonymousDbErrorsPayload)
        {
          throw paramAnonymousDbErrorsPayload.getCause();
        }
      }
      
      public void baaa0061aa006100610061a(ooolol<R> paramAnonymousOoolol)
      {
        if ((b0071q0071qqqq00710071 + bq00710071qqqq00710071) * b0071q0071qqqq00710071 % b007100710071qqqq00710071 != b00700070007000700070ppp00700070())
        {
          b0071q0071qqqq00710071 = 78;
          bq00710071qqqq00710071 = bppppp0070pp00700070();
          int i = b0071q0071qqqq00710071;
          switch (i * (bq00710071qqqq00710071 + i) % b007100710071qqqq00710071)
          {
          default: 
            b0071q0071qqqq00710071 = bppppp0070pp00700070();
            bq00710071qqqq00710071 = 6;
          }
        }
        paramAnonymousOoolol = ololol.bp00700070pp0070pp00700070();
        StringBuilder localStringBuilder = new StringBuilder();
        Object localObject = ppphhp.class.getMethod(uxxxxx.bbbb0062b0062b0062b0062("\n\036\035\034\033RQWVNMSR\022IHNMEDJI\t", '¼', 'd', '\001'), new Class[] { String.class, Character.TYPE, Character.TYPE });
        try
        {
          localObject = ((Method)localObject).invoke(null, new Object[] { "J^mkkkqd jiqswkk(oy}F-", Character.valueOf('ú'), Character.valueOf('\001') });
          rvvvrv.bqqqq00710071q0071q0071(paramAnonymousOoolol, (String)localObject + ololol.this);
          return;
        }
        catch (InvocationTargetException paramAnonymousOoolol)
        {
          throw paramAnonymousOoolol.getCause();
        }
      }
    });
  }
  
  public ololol(int paramInt, String paramString, loolol<R> paramLoolol)
  {
    this.bqqq0071007100710071q0071 = paramInt;
    this.bq007100710071007100710071q0071 = paramString;
    this.bq00710071q007100710071q0071 = paramLoolol;
    this.bqq0071q007100710071q0071 = new Gson();
    this.bqq00710071007100710071q0071 = false;
    bp00700070007000700070pp00700070(b0071q00710071q00710071q0071, 0);
  }
  
  public static int b00700070p0070p0070pp00700070()
  {
    return 12;
  }
  
  public static int b0070pp0070p0070pp00700070()
  {
    return 2;
  }
  
  public static int bp0070p0070p0070pp00700070()
  {
    return 0;
  }
  
  public static int bpp00700070p0070pp00700070()
  {
    return 1;
  }
  
  public void b007000700070007000700070pp00700070(hyyhhh paramHyyhhh)
  {
    int i = bqqqqqqq00710071;
    switch (i * (b0071qqqqqq00710071 + i) % bq0071qqqqq00710071)
    {
    default: 
      bqqqqqqq00710071 = b00700070p0070p0070pp00700070();
      b00710071qqqqq00710071 = b00700070p0070p0070pp00700070();
    }
    this.b0071007100710071007100710071q0071 = paramHyyhhh;
    if ((bqqqqqqq00710071 + b0071qqqqqq00710071) * bqqqqqqq00710071 % bq0071qqqqq00710071 != b00710071qqqqq00710071)
    {
      bqqqqqqq00710071 = b00700070p0070p0070pp00700070();
      b00710071qqqqq00710071 = 96;
    }
  }
  
  public loolol<R> b0070007000700070p0070pp00700070()
  {
    if ((bqqqqqqq00710071 + b0071qqqqqq00710071) * bqqqqqqq00710071 % b0070pp0070p0070pp00700070() != b00710071qqqqq00710071)
    {
      bqqqqqqq00710071 = 50;
      b00710071qqqqq00710071 = b00700070p0070p0070pp00700070();
    }
    return this.bq00710071q007100710071q0071;
  }
  
  public String b007000700070p00700070pp00700070()
  {
    if ((bqqqqqqq00710071 + b0071qqqqqq00710071) * bqqqqqqq00710071 % bq0071qqqqq00710071 != b00710071qqqqq00710071)
    {
      if ((bqqqqqqq00710071 + b0071qqqqqq00710071) * bqqqqqqq00710071 % bq0071qqqqq00710071 != b00710071qqqqq00710071)
      {
        bqqqqqqq00710071 = b00700070p0070p0070pp00700070();
        b00710071qqqqq00710071 = b00700070p0070p0070pp00700070();
      }
      bqqqqqqq00710071 = 84;
      b00710071qqqqq00710071 = b00700070p0070p0070pp00700070();
    }
    return this.bq007100710071007100710071q0071;
  }
  
  public void b007000700070pp0070pp00700070(String paramString1, String paramString2)
  {
    int i = bqqqqqqq00710071;
    switch (i * (b0071qqqqqq00710071 + i) % bq0071qqqqq00710071)
    {
    default: 
      bqqqqqqq00710071 = 48;
      b00710071qqqqq00710071 = 94;
    }
    Object localObject = ppphhp.class.getMethod(uxxxxx.bb00620062bb0062b0062b0062("\031/012kltuopxy;tu}~xy\002\003D", '', '\000'), new Class[] { String.class, Character.TYPE, Character.TYPE });
    try
    {
      localObject = ((Method)localObject).invoke(null, new Object[] { "#PPWISZ\024<bZP", Character.valueOf('î'), Character.valueOf('\001') });
      if (paramString1.equalsIgnoreCase((String)localObject)) {
        paramString1 = ppphhp.class.getMethod(uxxxxx.bbbb0062b0062b0062b0062("\021%$#\"YX^]UTZY\031POUTLKQP\020", 'µ', 'ã', '\001'), new Class[] { String.class, Character.TYPE, Character.TYPE });
      }
      try
      {
        paramString1 = paramString1.invoke(null, new Object[] { "\0359j?2BnD97r7DDK=GN\bPVNDQNHEXK\007W_O]^VRX^X\022g\\Z\026\032_^n=kawBoovhryZ\001xn24,zs\004x\001vA", Character.valueOf('£'), Character.valueOf('\001') });
        throw new IllegalArgumentException((String)paramString1);
      }
      catch (InvocationTargetException paramString1)
      {
        throw paramString1.getCause();
      }
      if ((bqqqqqqq00710071 + b0071qqqqqq00710071) * bqqqqqqq00710071 % bq0071qqqqq00710071 != b00710071qqqqq00710071)
      {
        bqqqqqqq00710071 = 95;
        b00710071qqqqq00710071 = 41;
      }
      this.b0071qq0071007100710071q0071.put(paramString1, paramString2);
      return;
    }
    catch (InvocationTargetException paramString1)
    {
      throw paramString1.getCause();
    }
  }
  
  public void b00700070p007000700070pp00700070(boolean paramBoolean)
  {
    this.bqq00710071007100710071q0071 = paramBoolean;
    if ((b00700070p0070p0070pp00700070() + b0071qqqqqq00710071) * b00700070p0070p0070pp00700070() % b0070pp0070p0070pp00700070() != b00710071qqqqq00710071)
    {
      if ((b00700070p0070p0070pp00700070() + bpp00700070p0070pp00700070()) * b00700070p0070p0070pp00700070() % b0070pp0070p0070pp00700070() != b00710071qqqqq00710071)
      {
        bqqqqqqq00710071 = b00700070p0070p0070pp00700070();
        b00710071qqqqq00710071 = b00700070p0070p0070pp00700070();
      }
      bqqqqqqq00710071 = 68;
      b00710071qqqqq00710071 = b00700070p0070p0070pp00700070();
    }
  }
  
  public Map<String, String> b00700070pp00700070pp00700070()
  {
    int i = bqqqqqqq00710071;
    switch (i * (b0071qqqqqq00710071 + i) % bq0071qqqqq00710071)
    {
    default: 
      bqqqqqqq00710071 = 33;
      if ((bqqqqqqq00710071 + bpp00700070p0070pp00700070()) * bqqqqqqq00710071 % bq0071qqqqq00710071 != b00710071qqqqq00710071)
      {
        bqqqqqqq00710071 = b00700070p0070p0070pp00700070();
        b00710071qqqqq00710071 = b00700070p0070p0070pp00700070();
      }
      b00710071qqqqq00710071 = 41;
    }
    return this.b0071qq0071007100710071q0071;
  }
  
  public void b0070p0070007000700070pp00700070(Object paramObject)
  {
    this.bq0071q0071007100710071q0071 = paramObject;
    int i = bqqqqqqq00710071;
    if ((bqqqqqqq00710071 + b0071qqqqqq00710071) * bqqqqqqq00710071 % bq0071qqqqq00710071 != b00710071qqqqq00710071)
    {
      bqqqqqqq00710071 = b00700070p0070p0070pp00700070();
      b00710071qqqqq00710071 = b00700070p0070p0070pp00700070();
    }
    if ((i + b0071qqqqqq00710071) * bqqqqqqq00710071 % bq0071qqqqq00710071 != b00710071qqqqq00710071)
    {
      bqqqqqqq00710071 = b00700070p0070p0070pp00700070();
      b00710071qqqqq00710071 = b00700070p0070p0070pp00700070();
    }
  }
  
  public Gson b0070p00700070p0070pp00700070()
  {
    if ((bqqqqqqq00710071 + b0071qqqqqq00710071) * bqqqqqqq00710071 % bq0071qqqqq00710071 != b00710071qqqqq00710071)
    {
      int i = bqqqqqqq00710071;
      switch (i * (bpp00700070p0070pp00700070() + i) % bq0071qqqqq00710071)
      {
      default: 
        bqqqqqqq00710071 = b00700070p0070p0070pp00700070();
        b00710071qqqqq00710071 = b00700070p0070p0070pp00700070();
      }
      bqqqqqqq00710071 = 41;
      b00710071qqqqq00710071 = 93;
    }
    return this.bqq0071q007100710071q0071;
  }
  
  public int b0070p0070p00700070pp00700070()
  {
    int i = bqqqqqqq00710071;
    switch (i * (b0071qqqqqq00710071 + i) % b0070pp0070p0070pp00700070())
    {
    default: 
      bqqqqqqq00710071 = b00700070p0070p0070pp00700070();
      i = bqqqqqqq00710071;
      switch (i * (b0071qqqqqq00710071 + i) % bq0071qqqqq00710071)
      {
      default: 
        bqqqqqqq00710071 = b00700070p0070p0070pp00700070();
        b00710071qqqqq00710071 = 34;
      }
      b00710071qqqqq00710071 = 17;
    }
    return this.b0071q00710071007100710071q0071;
  }
  
  public void b0070pp007000700070pp00700070(Gson paramGson)
  {
    this.bqq0071q007100710071q0071 = paramGson;
    int i = bqqqqqqq00710071;
    switch (i * (b0071qqqqqq00710071 + i) % bq0071qqqqq00710071)
    {
    default: 
      if ((bqqqqqqq00710071 + b0071qqqqqq00710071) * bqqqqqqq00710071 % bq0071qqqqq00710071 != b00710071qqqqq00710071)
      {
        bqqqqqqq00710071 = 82;
        b00710071qqqqq00710071 = 77;
      }
      bqqqqqqq00710071 = b00700070p0070p0070pp00700070();
      b00710071qqqqq00710071 = b00700070p0070p0070pp00700070();
    }
  }
  
  public int b0070ppp00700070pp00700070()
  {
    int i = this.bqqq0071007100710071q0071;
    int j = bqqqqqqq00710071;
    switch (j * (b0071qqqqqq00710071 + j) % bq0071qqqqq00710071)
    {
    default: 
      bqqqqqqq00710071 = 42;
      j = bqqqqqqq00710071;
      switch (j * (b0071qqqqqq00710071 + j) % bq0071qqqqq00710071)
      {
      default: 
        bqqqqqqq00710071 = b00700070p0070p0070pp00700070();
        b00710071qqqqq00710071 = b00700070p0070p0070pp00700070();
      }
      b00710071qqqqq00710071 = b00700070p0070p0070pp00700070();
    }
    return i;
  }
  
  public final void bp00700070007000700070pp00700070(int paramInt1, int paramInt2)
  {
    this.b0071q0071q007100710071q0071 = paramInt1;
    if ((bqqqqqqq00710071 + b0071qqqqqq00710071) * bqqqqqqq00710071 % bq0071qqqqq00710071 != bp0070p0070p0070pp00700070())
    {
      if ((bqqqqqqq00710071 + bpp00700070p0070pp00700070()) * bqqqqqqq00710071 % bq0071qqqqq00710071 != b00710071qqqqq00710071)
      {
        bqqqqqqq00710071 = b00700070p0070p0070pp00700070();
        b00710071qqqqq00710071 = 97;
      }
      bqqqqqqq00710071 = 72;
      b00710071qqqqq00710071 = b00700070p0070p0070pp00700070();
    }
    this.b007100710071q007100710071q0071 = paramInt2;
  }
  
  public int bp007000700070p0070pp00700070()
  {
    int i = bqqqqqqq00710071;
    switch (i * (b0071qqqqqq00710071 + i) % bq0071qqqqq00710071)
    {
    default: 
      bqqqqqqq00710071 = 23;
      b00710071qqqqq00710071 = b00700070p0070p0070pp00700070();
    }
    i = bqqqqqqq00710071;
    switch (i * (b0071qqqqqq00710071 + i) % bq0071qqqqq00710071)
    {
    default: 
      bqqqqqqq00710071 = 18;
      b00710071qqqqq00710071 = b00700070p0070p0070pp00700070();
    }
    return this.b0071q0071q007100710071q0071;
  }
  
  public Object bp00700070p00700070pp00700070()
  {
    Object localObject = this.bq0071q0071007100710071q0071;
    if ((bqqqqqqq00710071 + b0071qqqqqq00710071) * bqqqqqqq00710071 % bq0071qqqqq00710071 != b00710071qqqqq00710071)
    {
      int i = b00700070p0070p0070pp00700070();
      switch (i * (bpp00700070p0070pp00700070() + i) % bq0071qqqqq00710071)
      {
      default: 
        bqqqqqqq00710071 = b00700070p0070p0070pp00700070();
        b00710071qqqqq00710071 = b00700070p0070p0070pp00700070();
      }
      bqqqqqqq00710071 = b00700070p0070p0070pp00700070();
      b00710071qqqqq00710071 = b00700070p0070p0070pp00700070();
    }
    return localObject;
  }
  
  public void bp0070p007000700070pp00700070(Map<String, String> paramMap)
  {
    int i = bqqqqqqq00710071;
    switch (i * (b0071qqqqqq00710071 + i) % bq0071qqqqq00710071)
    {
    default: 
      bqqqqqqq00710071 = b00700070p0070p0070pp00700070();
      b00710071qqqqq00710071 = 48;
    }
    this.b00710071q0071007100710071q0071 = paramMap;
    i = bqqqqqqq00710071;
    switch (i * (b0071qqqqqq00710071 + i) % b0070pp0070p0070pp00700070())
    {
    default: 
      bqqqqqqq00710071 = 66;
      b00710071qqqqq00710071 = b00700070p0070p0070pp00700070();
    }
  }
  
  public String bp0070pp00700070pp00700070()
  {
    int i = bqqqqqqq00710071;
    int j = b0071qqqqqq00710071;
    int k = bqqqqqqq00710071;
    int m = bq0071qqqqq00710071;
    if ((b00700070p0070p0070pp00700070() + b0071qqqqqq00710071) * b00700070p0070p0070pp00700070() % bq0071qqqqq00710071 != b00710071qqqqq00710071)
    {
      bqqqqqqq00710071 = b00700070p0070p0070pp00700070();
      b00710071qqqqq00710071 = b00700070p0070p0070pp00700070();
    }
    if ((i + j) * k % m != b00710071qqqqq00710071)
    {
      bqqqqqqq00710071 = b00700070p0070p0070pp00700070();
      b00710071qqqqq00710071 = b00700070p0070p0070pp00700070();
    }
    Object localObject = ppphhp.class.getMethod(uxxxxx.bb00620062bb0062b0062b0062("DZ\024\025\035\036_`\032\033#$\036\037'(i#$,-'(01r", 'ï', '\001'), new Class[] { String.class, Character.TYPE, Character.TYPE, Character.TYPE });
    try
    {
      localObject = ((Method)localObject).invoke(null, new Object[] { "53$\n\024", Character.valueOf('Ä'), Character.valueOf('¤'), Character.valueOf('\001') });
      return (String)localObject;
    }
    catch (InvocationTargetException localInvocationTargetException)
    {
      throw localInvocationTargetException.getCause();
    }
  }
  
  public void bpp0070007000700070pp00700070(int paramInt)
  {
    int i = bqqqqqqq00710071;
    int j = b0071qqqqqq00710071;
    int k = bqqqqqqq00710071;
    int m = b0070pp0070p0070pp00700070();
    if ((b00700070p0070p0070pp00700070() + b0071qqqqqq00710071) * b00700070p0070p0070pp00700070() % bq0071qqqqq00710071 != b00710071qqqqq00710071)
    {
      bqqqqqqq00710071 = 83;
      b00710071qqqqq00710071 = b00700070p0070p0070pp00700070();
    }
    if ((i + j) * k % m != b00710071qqqqq00710071)
    {
      bqqqqqqq00710071 = b00700070p0070p0070pp00700070();
      b00710071qqqqq00710071 = b00700070p0070p0070pp00700070();
    }
    this.b0071q00710071007100710071q0071 = paramInt;
  }
  
  public Map<String, String> bpp0070p00700070pp00700070()
  {
    if ((bqqqqqqq00710071 + bpp00700070p0070pp00700070()) * bqqqqqqq00710071 % bq0071qqqqq00710071 != bp0070p0070p0070pp00700070())
    {
      bqqqqqqq00710071 = 6;
      b00710071qqqqq00710071 = b00700070p0070p0070pp00700070();
    }
    return this.b00710071q0071007100710071q0071;
  }
  
  public hyyhhh bppp007000700070pp00700070()
  {
    if ((bqqqqqqq00710071 + b0071qqqqqq00710071) * bqqqqqqq00710071 % bq0071qqqqq00710071 != b00710071qqqqq00710071)
    {
      int i = bqqqqqqq00710071;
      switch (i * (b0071qqqqqq00710071 + i) % bq0071qqqqq00710071)
      {
      default: 
        bqqqqqqq00710071 = 73;
        b00710071qqqqq00710071 = 37;
      }
      bqqqqqqq00710071 = b00700070p0070p0070pp00700070();
      b00710071qqqqq00710071 = b00700070p0070p0070pp00700070();
    }
    return this.b0071007100710071007100710071q0071;
  }
  
  /* Error */
  public void bppp0070p0070pp00700070(ygyygy paramYgyygy, ggyygy paramGgyygy)
  {
    // Byte code:
    //   0: getstatic 174	uuuuuu/ololol:bqqqqqqq00710071	I
    //   3: istore_3
    //   4: iload_3
    //   5: invokestatic 272	uuuuuu/ololol:bpp00700070p0070pp00700070	()I
    //   8: iload_3
    //   9: iadd
    //   10: imul
    //   11: getstatic 178	uuuuuu/ololol:bq0071qqqqq00710071	I
    //   14: irem
    //   15: tableswitch	default:+17->32, 0:+28->43
    //   32: invokestatic 182	uuuuuu/ololol:b00700070p0070p0070pp00700070	()I
    //   35: putstatic 174	uuuuuu/ololol:bqqqqqqq00710071	I
    //   38: bipush 94
    //   40: putstatic 184	uuuuuu/ololol:b00710071qqqqq00710071	I
    //   43: aload_1
    //   44: invokevirtual 312	uuuuuu/ygyygy:b0070ppp0070ppp0070p	()Ljava/lang/String;
    //   47: astore_1
    //   48: aload_1
    //   49: ifnull +88 -> 137
    //   52: ldc 82
    //   54: ldc_w 314
    //   57: sipush 159
    //   60: sipush 174
    //   63: iconst_3
    //   64: invokestatic 134	xxxxxx/uxxxxx:bbbb0062b0062b0062b0062	(Ljava/lang/String;CCC)Ljava/lang/String;
    //   67: iconst_3
    //   68: anewarray 92	java/lang/Class
    //   71: dup
    //   72: iconst_0
    //   73: ldc 94
    //   75: aastore
    //   76: dup
    //   77: iconst_1
    //   78: getstatic 100	java/lang/Character:TYPE	Ljava/lang/Class;
    //   81: aastore
    //   82: dup
    //   83: iconst_2
    //   84: getstatic 100	java/lang/Character:TYPE	Ljava/lang/Class;
    //   87: aastore
    //   88: invokevirtual 104	java/lang/Class:getMethod	(Ljava/lang/String;[Ljava/lang/Class;)Ljava/lang/reflect/Method;
    //   91: astore 4
    //   93: aload 4
    //   95: aconst_null
    //   96: iconst_3
    //   97: anewarray 5	java/lang/Object
    //   100: dup
    //   101: iconst_0
    //   102: ldc_w 316
    //   105: aastore
    //   106: dup
    //   107: iconst_1
    //   108: sipush 222
    //   111: invokestatic 108	java/lang/Character:valueOf	(C)Ljava/lang/Character;
    //   114: aastore
    //   115: dup
    //   116: iconst_2
    //   117: iconst_2
    //   118: invokestatic 108	java/lang/Character:valueOf	(C)Ljava/lang/Character;
    //   121: aastore
    //   122: invokevirtual 114	java/lang/reflect/Method:invoke	(Ljava/lang/Object;[Ljava/lang/Object;)Ljava/lang/Object;
    //   125: astore 4
    //   127: aload_0
    //   128: aload 4
    //   130: checkcast 94	java/lang/String
    //   133: aload_1
    //   134: invokevirtual 318	uuuuuu/ololol:b007000700070pp0070pp00700070	(Ljava/lang/String;Ljava/lang/String;)V
    //   137: ldc 82
    //   139: ldc_w 320
    //   142: bipush 49
    //   144: sipush 148
    //   147: iconst_3
    //   148: invokestatic 134	xxxxxx/uxxxxx:bbbb0062b0062b0062b0062	(Ljava/lang/String;CCC)Ljava/lang/String;
    //   151: iconst_3
    //   152: anewarray 92	java/lang/Class
    //   155: dup
    //   156: iconst_0
    //   157: ldc 94
    //   159: aastore
    //   160: dup
    //   161: iconst_1
    //   162: getstatic 100	java/lang/Character:TYPE	Ljava/lang/Class;
    //   165: aastore
    //   166: dup
    //   167: iconst_2
    //   168: getstatic 100	java/lang/Character:TYPE	Ljava/lang/Class;
    //   171: aastore
    //   172: invokevirtual 104	java/lang/Class:getMethod	(Ljava/lang/String;[Ljava/lang/Class;)Ljava/lang/reflect/Method;
    //   175: astore_1
    //   176: aload_1
    //   177: aconst_null
    //   178: iconst_3
    //   179: anewarray 5	java/lang/Object
    //   182: dup
    //   183: iconst_0
    //   184: ldc_w 322
    //   187: aastore
    //   188: dup
    //   189: iconst_1
    //   190: bipush 17
    //   192: invokestatic 108	java/lang/Character:valueOf	(C)Ljava/lang/Character;
    //   195: aastore
    //   196: dup
    //   197: iconst_2
    //   198: iconst_2
    //   199: invokestatic 108	java/lang/Character:valueOf	(C)Ljava/lang/Character;
    //   202: aastore
    //   203: invokevirtual 114	java/lang/reflect/Method:invoke	(Ljava/lang/Object;[Ljava/lang/Object;)Ljava/lang/Object;
    //   206: astore_1
    //   207: aload_0
    //   208: aload_1
    //   209: checkcast 94	java/lang/String
    //   212: invokestatic 328	java/util/UUID:randomUUID	()Ljava/util/UUID;
    //   215: invokevirtual 331	java/util/UUID:toString	()Ljava/lang/String;
    //   218: invokevirtual 318	uuuuuu/ololol:b007000700070pp0070pp00700070	(Ljava/lang/String;Ljava/lang/String;)V
    //   221: aload_2
    //   222: invokevirtual 336	uuuuuu/ggyygy:bpp0070ppppp0070p	()Ljava/lang/String;
    //   225: astore_1
    //   226: aload_1
    //   227: invokestatic 342	android/text/TextUtils:isEmpty	(Ljava/lang/CharSequence;)Z
    //   230: ifne +185 -> 415
    //   233: ldc 82
    //   235: ldc_w 344
    //   238: sipush 212
    //   241: iconst_3
    //   242: invokestatic 90	xxxxxx/uxxxxx:bb00620062bb0062b0062b0062	(Ljava/lang/String;CC)Ljava/lang/String;
    //   245: iconst_3
    //   246: anewarray 92	java/lang/Class
    //   249: dup
    //   250: iconst_0
    //   251: ldc 94
    //   253: aastore
    //   254: dup
    //   255: iconst_1
    //   256: getstatic 100	java/lang/Character:TYPE	Ljava/lang/Class;
    //   259: aastore
    //   260: dup
    //   261: iconst_2
    //   262: getstatic 100	java/lang/Character:TYPE	Ljava/lang/Class;
    //   265: aastore
    //   266: invokevirtual 104	java/lang/Class:getMethod	(Ljava/lang/String;[Ljava/lang/Class;)Ljava/lang/reflect/Method;
    //   269: astore 4
    //   271: aload 4
    //   273: aconst_null
    //   274: iconst_3
    //   275: anewarray 5	java/lang/Object
    //   278: dup
    //   279: iconst_0
    //   280: ldc_w 346
    //   283: aastore
    //   284: dup
    //   285: iconst_1
    //   286: sipush 229
    //   289: invokestatic 108	java/lang/Character:valueOf	(C)Ljava/lang/Character;
    //   292: aastore
    //   293: dup
    //   294: iconst_2
    //   295: iconst_1
    //   296: invokestatic 108	java/lang/Character:valueOf	(C)Ljava/lang/Character;
    //   299: aastore
    //   300: invokevirtual 114	java/lang/reflect/Method:invoke	(Ljava/lang/Object;[Ljava/lang/Object;)Ljava/lang/Object;
    //   303: astore 4
    //   305: aload 4
    //   307: checkcast 94	java/lang/String
    //   310: astore 4
    //   312: new 348	java/lang/StringBuilder
    //   315: dup
    //   316: invokespecial 349	java/lang/StringBuilder:<init>	()V
    //   319: astore 5
    //   321: ldc 82
    //   323: ldc_w 351
    //   326: sipush 247
    //   329: iconst_2
    //   330: invokestatic 90	xxxxxx/uxxxxx:bb00620062bb0062b0062b0062	(Ljava/lang/String;CC)Ljava/lang/String;
    //   333: iconst_3
    //   334: anewarray 92	java/lang/Class
    //   337: dup
    //   338: iconst_0
    //   339: ldc 94
    //   341: aastore
    //   342: dup
    //   343: iconst_1
    //   344: getstatic 100	java/lang/Character:TYPE	Ljava/lang/Class;
    //   347: aastore
    //   348: dup
    //   349: iconst_2
    //   350: getstatic 100	java/lang/Character:TYPE	Ljava/lang/Class;
    //   353: aastore
    //   354: invokevirtual 104	java/lang/Class:getMethod	(Ljava/lang/String;[Ljava/lang/Class;)Ljava/lang/reflect/Method;
    //   357: astore 6
    //   359: aload 6
    //   361: aconst_null
    //   362: iconst_3
    //   363: anewarray 5	java/lang/Object
    //   366: dup
    //   367: iconst_0
    //   368: ldc_w 353
    //   371: aastore
    //   372: dup
    //   373: iconst_1
    //   374: bipush 111
    //   376: invokestatic 108	java/lang/Character:valueOf	(C)Ljava/lang/Character;
    //   379: aastore
    //   380: dup
    //   381: iconst_2
    //   382: iconst_4
    //   383: invokestatic 108	java/lang/Character:valueOf	(C)Ljava/lang/Character;
    //   386: aastore
    //   387: invokevirtual 114	java/lang/reflect/Method:invoke	(Ljava/lang/Object;[Ljava/lang/Object;)Ljava/lang/Object;
    //   390: astore 6
    //   392: aload_0
    //   393: aload 4
    //   395: aload 5
    //   397: aload 6
    //   399: checkcast 94	java/lang/String
    //   402: invokevirtual 357	java/lang/StringBuilder:append	(Ljava/lang/String;)Ljava/lang/StringBuilder;
    //   405: aload_1
    //   406: invokevirtual 357	java/lang/StringBuilder:append	(Ljava/lang/String;)Ljava/lang/StringBuilder;
    //   409: invokevirtual 358	java/lang/StringBuilder:toString	()Ljava/lang/String;
    //   412: invokevirtual 318	uuuuuu/ololol:b007000700070pp0070pp00700070	(Ljava/lang/String;Ljava/lang/String;)V
    //   415: aload_2
    //   416: invokevirtual 362	uuuuuu/ggyygy:bp00700070ppppp0070p	()Z
    //   419: ifeq +103 -> 522
    //   422: ldc 82
    //   424: ldc_w 364
    //   427: bipush 124
    //   429: sipush 252
    //   432: iconst_1
    //   433: invokestatic 134	xxxxxx/uxxxxx:bbbb0062b0062b0062b0062	(Ljava/lang/String;CCC)Ljava/lang/String;
    //   436: iconst_4
    //   437: anewarray 92	java/lang/Class
    //   440: dup
    //   441: iconst_0
    //   442: ldc 94
    //   444: aastore
    //   445: dup
    //   446: iconst_1
    //   447: getstatic 100	java/lang/Character:TYPE	Ljava/lang/Class;
    //   450: aastore
    //   451: dup
    //   452: iconst_2
    //   453: getstatic 100	java/lang/Character:TYPE	Ljava/lang/Class;
    //   456: aastore
    //   457: dup
    //   458: iconst_3
    //   459: getstatic 100	java/lang/Character:TYPE	Ljava/lang/Class;
    //   462: aastore
    //   463: invokevirtual 104	java/lang/Class:getMethod	(Ljava/lang/String;[Ljava/lang/Class;)Ljava/lang/reflect/Method;
    //   466: astore_1
    //   467: aload_1
    //   468: aconst_null
    //   469: iconst_4
    //   470: anewarray 5	java/lang/Object
    //   473: dup
    //   474: iconst_0
    //   475: ldc_w 366
    //   478: aastore
    //   479: dup
    //   480: iconst_1
    //   481: sipush 188
    //   484: invokestatic 108	java/lang/Character:valueOf	(C)Ljava/lang/Character;
    //   487: aastore
    //   488: dup
    //   489: iconst_2
    //   490: sipush 214
    //   493: invokestatic 108	java/lang/Character:valueOf	(C)Ljava/lang/Character;
    //   496: aastore
    //   497: dup
    //   498: iconst_3
    //   499: iconst_2
    //   500: invokestatic 108	java/lang/Character:valueOf	(C)Ljava/lang/Character;
    //   503: aastore
    //   504: invokevirtual 114	java/lang/reflect/Method:invoke	(Ljava/lang/Object;[Ljava/lang/Object;)Ljava/lang/Object;
    //   507: astore_1
    //   508: aload_0
    //   509: aload_1
    //   510: checkcast 94	java/lang/String
    //   513: getstatic 372	java/lang/Boolean:TRUE	Ljava/lang/Boolean;
    //   516: invokevirtual 373	java/lang/Boolean:toString	()Ljava/lang/String;
    //   519: invokevirtual 318	uuuuuu/ololol:b007000700070pp0070pp00700070	(Ljava/lang/String;Ljava/lang/String;)V
    //   522: ldc 82
    //   524: ldc_w 375
    //   527: sipush 129
    //   530: iconst_4
    //   531: invokestatic 90	xxxxxx/uxxxxx:bb00620062bb0062b0062b0062	(Ljava/lang/String;CC)Ljava/lang/String;
    //   534: iconst_4
    //   535: anewarray 92	java/lang/Class
    //   538: dup
    //   539: iconst_0
    //   540: ldc 94
    //   542: aastore
    //   543: dup
    //   544: iconst_1
    //   545: getstatic 100	java/lang/Character:TYPE	Ljava/lang/Class;
    //   548: aastore
    //   549: dup
    //   550: iconst_2
    //   551: getstatic 100	java/lang/Character:TYPE	Ljava/lang/Class;
    //   554: aastore
    //   555: dup
    //   556: iconst_3
    //   557: getstatic 100	java/lang/Character:TYPE	Ljava/lang/Class;
    //   560: aastore
    //   561: invokevirtual 104	java/lang/Class:getMethod	(Ljava/lang/String;[Ljava/lang/Class;)Ljava/lang/reflect/Method;
    //   564: astore_1
    //   565: aload_1
    //   566: aconst_null
    //   567: iconst_4
    //   568: anewarray 5	java/lang/Object
    //   571: dup
    //   572: iconst_0
    //   573: ldc_w 377
    //   576: aastore
    //   577: dup
    //   578: iconst_1
    //   579: bipush 89
    //   581: invokestatic 108	java/lang/Character:valueOf	(C)Ljava/lang/Character;
    //   584: aastore
    //   585: dup
    //   586: iconst_2
    //   587: bipush 21
    //   589: invokestatic 108	java/lang/Character:valueOf	(C)Ljava/lang/Character;
    //   592: aastore
    //   593: dup
    //   594: iconst_3
    //   595: iconst_2
    //   596: invokestatic 108	java/lang/Character:valueOf	(C)Ljava/lang/Character;
    //   599: aastore
    //   600: invokevirtual 114	java/lang/reflect/Method:invoke	(Ljava/lang/Object;[Ljava/lang/Object;)Ljava/lang/Object;
    //   603: astore_1
    //   604: aload_0
    //   605: aload_1
    //   606: checkcast 94	java/lang/String
    //   609: getstatic 382	android/os/Build$VERSION:RELEASE	Ljava/lang/String;
    //   612: invokevirtual 318	uuuuuu/ololol:b007000700070pp0070pp00700070	(Ljava/lang/String;Ljava/lang/String;)V
    //   615: ldc 82
    //   617: ldc_w 384
    //   620: sipush 134
    //   623: sipush 200
    //   626: iconst_3
    //   627: invokestatic 134	xxxxxx/uxxxxx:bbbb0062b0062b0062b0062	(Ljava/lang/String;CCC)Ljava/lang/String;
    //   630: iconst_3
    //   631: anewarray 92	java/lang/Class
    //   634: dup
    //   635: iconst_0
    //   636: ldc 94
    //   638: aastore
    //   639: dup
    //   640: iconst_1
    //   641: getstatic 100	java/lang/Character:TYPE	Ljava/lang/Class;
    //   644: aastore
    //   645: dup
    //   646: iconst_2
    //   647: getstatic 100	java/lang/Character:TYPE	Ljava/lang/Class;
    //   650: aastore
    //   651: invokevirtual 104	java/lang/Class:getMethod	(Ljava/lang/String;[Ljava/lang/Class;)Ljava/lang/reflect/Method;
    //   654: astore_1
    //   655: aload_1
    //   656: aconst_null
    //   657: iconst_3
    //   658: anewarray 5	java/lang/Object
    //   661: dup
    //   662: iconst_0
    //   663: ldc_w 386
    //   666: aastore
    //   667: dup
    //   668: iconst_1
    //   669: sipush 231
    //   672: invokestatic 108	java/lang/Character:valueOf	(C)Ljava/lang/Character;
    //   675: aastore
    //   676: dup
    //   677: iconst_2
    //   678: iconst_1
    //   679: invokestatic 108	java/lang/Character:valueOf	(C)Ljava/lang/Character;
    //   682: aastore
    //   683: invokevirtual 114	java/lang/reflect/Method:invoke	(Ljava/lang/Object;[Ljava/lang/Object;)Ljava/lang/Object;
    //   686: astore_1
    //   687: aload_1
    //   688: checkcast 94	java/lang/String
    //   691: astore_1
    //   692: ldc 82
    //   694: ldc_w 388
    //   697: sipush 210
    //   700: iconst_4
    //   701: invokestatic 90	xxxxxx/uxxxxx:bb00620062bb0062b0062b0062	(Ljava/lang/String;CC)Ljava/lang/String;
    //   704: iconst_4
    //   705: anewarray 92	java/lang/Class
    //   708: dup
    //   709: iconst_0
    //   710: ldc 94
    //   712: aastore
    //   713: dup
    //   714: iconst_1
    //   715: getstatic 100	java/lang/Character:TYPE	Ljava/lang/Class;
    //   718: aastore
    //   719: dup
    //   720: iconst_2
    //   721: getstatic 100	java/lang/Character:TYPE	Ljava/lang/Class;
    //   724: aastore
    //   725: dup
    //   726: iconst_3
    //   727: getstatic 100	java/lang/Character:TYPE	Ljava/lang/Class;
    //   730: aastore
    //   731: invokevirtual 104	java/lang/Class:getMethod	(Ljava/lang/String;[Ljava/lang/Class;)Ljava/lang/reflect/Method;
    //   734: astore 4
    //   736: aload 4
    //   738: aconst_null
    //   739: iconst_4
    //   740: anewarray 5	java/lang/Object
    //   743: dup
    //   744: iconst_0
    //   745: ldc_w 390
    //   748: aastore
    //   749: dup
    //   750: iconst_1
    //   751: sipush 179
    //   754: invokestatic 108	java/lang/Character:valueOf	(C)Ljava/lang/Character;
    //   757: aastore
    //   758: dup
    //   759: iconst_2
    //   760: sipush 207
    //   763: invokestatic 108	java/lang/Character:valueOf	(C)Ljava/lang/Character;
    //   766: aastore
    //   767: dup
    //   768: iconst_3
    //   769: iconst_3
    //   770: invokestatic 108	java/lang/Character:valueOf	(C)Ljava/lang/Character;
    //   773: aastore
    //   774: invokevirtual 114	java/lang/reflect/Method:invoke	(Ljava/lang/Object;[Ljava/lang/Object;)Ljava/lang/Object;
    //   777: astore 4
    //   779: aload_0
    //   780: aload_1
    //   781: aload 4
    //   783: checkcast 94	java/lang/String
    //   786: invokevirtual 318	uuuuuu/ololol:b007000700070pp0070pp00700070	(Ljava/lang/String;Ljava/lang/String;)V
    //   789: aload_2
    //   790: invokevirtual 393	uuuuuu/ggyygy:b0070p0070ppppp0070p	()Ljava/lang/String;
    //   793: invokestatic 342	android/text/TextUtils:isEmpty	(Ljava/lang/CharSequence;)Z
    //   796: ifne +99 -> 895
    //   799: ldc 82
    //   801: ldc_w 395
    //   804: bipush 93
    //   806: bipush 51
    //   808: iconst_1
    //   809: invokestatic 134	xxxxxx/uxxxxx:bbbb0062b0062b0062b0062	(Ljava/lang/String;CCC)Ljava/lang/String;
    //   812: iconst_4
    //   813: anewarray 92	java/lang/Class
    //   816: dup
    //   817: iconst_0
    //   818: ldc 94
    //   820: aastore
    //   821: dup
    //   822: iconst_1
    //   823: getstatic 100	java/lang/Character:TYPE	Ljava/lang/Class;
    //   826: aastore
    //   827: dup
    //   828: iconst_2
    //   829: getstatic 100	java/lang/Character:TYPE	Ljava/lang/Class;
    //   832: aastore
    //   833: dup
    //   834: iconst_3
    //   835: getstatic 100	java/lang/Character:TYPE	Ljava/lang/Class;
    //   838: aastore
    //   839: invokevirtual 104	java/lang/Class:getMethod	(Ljava/lang/String;[Ljava/lang/Class;)Ljava/lang/reflect/Method;
    //   842: astore_1
    //   843: aload_1
    //   844: aconst_null
    //   845: iconst_4
    //   846: anewarray 5	java/lang/Object
    //   849: dup
    //   850: iconst_0
    //   851: ldc_w 397
    //   854: aastore
    //   855: dup
    //   856: iconst_1
    //   857: sipush 180
    //   860: invokestatic 108	java/lang/Character:valueOf	(C)Ljava/lang/Character;
    //   863: aastore
    //   864: dup
    //   865: iconst_2
    //   866: bipush 87
    //   868: invokestatic 108	java/lang/Character:valueOf	(C)Ljava/lang/Character;
    //   871: aastore
    //   872: dup
    //   873: iconst_3
    //   874: iconst_1
    //   875: invokestatic 108	java/lang/Character:valueOf	(C)Ljava/lang/Character;
    //   878: aastore
    //   879: invokevirtual 114	java/lang/reflect/Method:invoke	(Ljava/lang/Object;[Ljava/lang/Object;)Ljava/lang/Object;
    //   882: astore_1
    //   883: aload_0
    //   884: aload_1
    //   885: checkcast 94	java/lang/String
    //   888: aload_2
    //   889: invokevirtual 393	uuuuuu/ggyygy:b0070p0070ppppp0070p	()Ljava/lang/String;
    //   892: invokevirtual 318	uuuuuu/ololol:b007000700070pp0070pp00700070	(Ljava/lang/String;Ljava/lang/String;)V
    //   895: getstatic 160	uuuuuu/ololol:bqqqq007100710071q0071	Ljava/lang/String;
    //   898: astore_1
    //   899: new 348	java/lang/StringBuilder
    //   902: dup
    //   903: invokespecial 349	java/lang/StringBuilder:<init>	()V
    //   906: aload_0
    //   907: invokevirtual 399	uuuuuu/ololol:b007000700070p00700070pp00700070	()Ljava/lang/String;
    //   910: invokevirtual 357	java/lang/StringBuilder:append	(Ljava/lang/String;)Ljava/lang/StringBuilder;
    //   913: astore_2
    //   914: getstatic 174	uuuuuu/ololol:bqqqqqqq00710071	I
    //   917: istore_3
    //   918: iload_3
    //   919: getstatic 176	uuuuuu/ololol:b0071qqqqqq00710071	I
    //   922: iload_3
    //   923: iadd
    //   924: imul
    //   925: getstatic 178	uuuuuu/ololol:bq0071qqqqq00710071	I
    //   928: irem
    //   929: tableswitch	default:+19->948, 0:+30->959
    //   948: invokestatic 182	uuuuuu/ololol:b00700070p0070p0070pp00700070	()I
    //   951: putstatic 174	uuuuuu/ololol:bqqqqqqq00710071	I
    //   954: bipush 66
    //   956: putstatic 184	uuuuuu/ololol:b00710071qqqqq00710071	I
    //   959: ldc 82
    //   961: ldc_w 401
    //   964: bipush 10
    //   966: iconst_5
    //   967: invokestatic 90	xxxxxx/uxxxxx:bb00620062bb0062b0062b0062	(Ljava/lang/String;CC)Ljava/lang/String;
    //   970: iconst_4
    //   971: anewarray 92	java/lang/Class
    //   974: dup
    //   975: iconst_0
    //   976: ldc 94
    //   978: aastore
    //   979: dup
    //   980: iconst_1
    //   981: getstatic 100	java/lang/Character:TYPE	Ljava/lang/Class;
    //   984: aastore
    //   985: dup
    //   986: iconst_2
    //   987: getstatic 100	java/lang/Character:TYPE	Ljava/lang/Class;
    //   990: aastore
    //   991: dup
    //   992: iconst_3
    //   993: getstatic 100	java/lang/Character:TYPE	Ljava/lang/Class;
    //   996: aastore
    //   997: invokevirtual 104	java/lang/Class:getMethod	(Ljava/lang/String;[Ljava/lang/Class;)Ljava/lang/reflect/Method;
    //   1000: astore 4
    //   1002: aload 4
    //   1004: aconst_null
    //   1005: iconst_4
    //   1006: anewarray 5	java/lang/Object
    //   1009: dup
    //   1010: iconst_0
    //   1011: ldc_w 403
    //   1014: aastore
    //   1015: dup
    //   1016: iconst_1
    //   1017: bipush 30
    //   1019: invokestatic 108	java/lang/Character:valueOf	(C)Ljava/lang/Character;
    //   1022: aastore
    //   1023: dup
    //   1024: iconst_2
    //   1025: bipush 112
    //   1027: invokestatic 108	java/lang/Character:valueOf	(C)Ljava/lang/Character;
    //   1030: aastore
    //   1031: dup
    //   1032: iconst_3
    //   1033: iconst_0
    //   1034: invokestatic 108	java/lang/Character:valueOf	(C)Ljava/lang/Character;
    //   1037: aastore
    //   1038: invokevirtual 114	java/lang/reflect/Method:invoke	(Ljava/lang/Object;[Ljava/lang/Object;)Ljava/lang/Object;
    //   1041: astore 4
    //   1043: aload_1
    //   1044: aload_2
    //   1045: aload 4
    //   1047: checkcast 94	java/lang/String
    //   1050: invokevirtual 357	java/lang/StringBuilder:append	(Ljava/lang/String;)Ljava/lang/StringBuilder;
    //   1053: aload_0
    //   1054: getfield 206	uuuuuu/ololol:b0071qq0071007100710071q0071	Ljava/util/Map;
    //   1057: invokeinterface 406 1 0
    //   1062: invokevirtual 409	java/lang/StringBuilder:append	(I)Ljava/lang/StringBuilder;
    //   1065: invokevirtual 358	java/lang/StringBuilder:toString	()Ljava/lang/String;
    //   1068: invokestatic 414	uuuuuu/rvvvrv:b007100710071q00710071q0071q0071	(Ljava/lang/String;Ljava/lang/String;)V
    //   1071: return
    //   1072: astore_1
    //   1073: aload_1
    //   1074: invokevirtual 190	java/lang/reflect/InvocationTargetException:getCause	()Ljava/lang/Throwable;
    //   1077: athrow
    //   1078: astore_1
    //   1079: aload_1
    //   1080: invokevirtual 190	java/lang/reflect/InvocationTargetException:getCause	()Ljava/lang/Throwable;
    //   1083: athrow
    //   1084: astore_1
    //   1085: aload_1
    //   1086: invokevirtual 190	java/lang/reflect/InvocationTargetException:getCause	()Ljava/lang/Throwable;
    //   1089: athrow
    //   1090: astore_1
    //   1091: aload_1
    //   1092: invokevirtual 190	java/lang/reflect/InvocationTargetException:getCause	()Ljava/lang/Throwable;
    //   1095: athrow
    //   1096: astore_1
    //   1097: aload_1
    //   1098: invokevirtual 190	java/lang/reflect/InvocationTargetException:getCause	()Ljava/lang/Throwable;
    //   1101: athrow
    //   1102: astore_1
    //   1103: aload_1
    //   1104: invokevirtual 190	java/lang/reflect/InvocationTargetException:getCause	()Ljava/lang/Throwable;
    //   1107: athrow
    //   1108: astore_1
    //   1109: aload_1
    //   1110: invokevirtual 190	java/lang/reflect/InvocationTargetException:getCause	()Ljava/lang/Throwable;
    //   1113: athrow
    //   1114: astore_1
    //   1115: aload_1
    //   1116: invokevirtual 190	java/lang/reflect/InvocationTargetException:getCause	()Ljava/lang/Throwable;
    //   1119: athrow
    //   1120: astore_1
    //   1121: aload_1
    //   1122: invokevirtual 190	java/lang/reflect/InvocationTargetException:getCause	()Ljava/lang/Throwable;
    //   1125: athrow
    //   1126: astore_1
    //   1127: aload_1
    //   1128: invokevirtual 190	java/lang/reflect/InvocationTargetException:getCause	()Ljava/lang/Throwable;
    //   1131: athrow
    // Local variable table:
    //   start	length	slot	name	signature
    //   0	1132	0	this	ololol
    //   0	1132	1	paramYgyygy	ygyygy
    //   0	1132	2	paramGgyygy	ggyygy
    //   3	922	3	i	int
    //   91	955	4	localObject1	Object
    //   319	77	5	localStringBuilder	StringBuilder
    //   357	41	6	localObject2	Object
    // Exception table:
    //   from	to	target	type
    //   93	127	1072	java/lang/reflect/InvocationTargetException
    //   565	604	1078	java/lang/reflect/InvocationTargetException
    //   655	687	1084	java/lang/reflect/InvocationTargetException
    //   736	779	1090	java/lang/reflect/InvocationTargetException
    //   176	207	1096	java/lang/reflect/InvocationTargetException
    //   359	392	1102	java/lang/reflect/InvocationTargetException
    //   467	508	1108	java/lang/reflect/InvocationTargetException
    //   271	305	1114	java/lang/reflect/InvocationTargetException
    //   843	883	1120	java/lang/reflect/InvocationTargetException
    //   1002	1043	1126	java/lang/reflect/InvocationTargetException
  }
  
  public int bpppp00700070pp00700070()
  {
    int i = bqqqqqqq00710071;
    switch (i * (b0071qqqqqq00710071 + i) % bq0071qqqqq00710071)
    {
    default: 
      bqqqqqqq00710071 = b00700070p0070p0070pp00700070();
      b00710071qqqqq00710071 = 78;
      i = bqqqqqqq00710071;
      switch (i * (b0071qqqqqq00710071 + i) % bq0071qqqqq00710071)
      {
      default: 
        bqqqqqqq00710071 = b00700070p0070p0070pp00700070();
        b00710071qqqqq00710071 = b00700070p0070p0070pp00700070();
      }
      break;
    }
    return this.b007100710071q007100710071q0071;
  }
  
  public boolean bpppppp0070p00700070()
  {
    boolean bool = this.bqq00710071007100710071q0071;
    if ((bqqqqqqq00710071 + b0071qqqqqq00710071) * bqqqqqqq00710071 % bq0071qqqqq00710071 != bp0070p0070p0070pp00700070())
    {
      bqqqqqqq00710071 = b00700070p0070p0070pp00700070();
      b00710071qqqqq00710071 = b00700070p0070p0070pp00700070();
      if ((bqqqqqqq00710071 + b0071qqqqqq00710071) * bqqqqqqq00710071 % bq0071qqqqq00710071 != bp0070p0070p0070pp00700070())
      {
        bqqqqqqq00710071 = 71;
        b00710071qqqqq00710071 = 56;
      }
    }
    return bool;
  }
  
  public static class oollol
  {
    public static int b00710071q0071qqq00710071 = 0;
    public static int b0071q00710071qqq00710071 = 2;
    public static int bq0071q0071qqq00710071 = 43;
    public static int bqq00710071qqq00710071 = 1;
    private String b0071qq0071qqq00710071;
    private int bqqq0071qqq00710071 = 0;
    
    public oollol() {}
    
    public static int b00700070ppp0070pp00700070()
    {
      return 85;
    }
    
    public static int b0070pppp0070pp00700070()
    {
      return 1;
    }
    
    public static int bp0070ppp0070pp00700070()
    {
      return 2;
    }
    
    public oollol b0070p0070pp0070pp00700070(String paramString)
    {
      this.b0071qq0071qqq00710071 = paramString;
      if ((bq0071q0071qqq00710071 + b0070pppp0070pp00700070()) * bq0071q0071qqq00710071 % bp0070ppp0070pp00700070() != b00710071q0071qqq00710071)
      {
        bq0071q0071qqq00710071 = 51;
        b00710071q0071qqq00710071 = 32;
        if ((bq0071q0071qqq00710071 + bqq00710071qqq00710071) * bq0071q0071qqq00710071 % b0071q00710071qqq00710071 != b00710071q0071qqq00710071)
        {
          bq0071q0071qqq00710071 = 19;
          b00710071q0071qqq00710071 = 11;
        }
      }
      return this;
    }
    
    public ololol bpp0070pp0070pp00700070()
    {
      int i = this.bqqq0071qqq00710071;
      if ((bq0071q0071qqq00710071 + bqq00710071qqq00710071) * bq0071q0071qqq00710071 % b0071q00710071qqq00710071 != b00710071q0071qqq00710071)
      {
        bq0071q0071qqq00710071 = 32;
        b00710071q0071qqq00710071 = b00700070ppp0070pp00700070();
        int j = bq0071q0071qqq00710071;
        switch (j * (b0070pppp0070pp00700070() + j) % b0071q00710071qqq00710071)
        {
        default: 
          bq0071q0071qqq00710071 = 65;
          b00710071q0071qqq00710071 = 50;
        }
      }
      return new ololol(i, this.b0071qq0071qqq00710071);
    }
  }
}
