package uuuuuu;

import android.content.Context;
import javax.inject.Inject;

public class ononoo
  extends ssssst<nnnooo.noonoo>
  implements nnnooo.ooonoo, onnooo
{
  public static int b006E006E006En006Enn006E006E = 0;
  public static int b006Enn006E006Enn006E006E = 2;
  public static int bn006E006En006Enn006E006E = 84;
  public static int bnnn006E006Enn006E006E = 1;
  @Inject
  public Context b006E006E006E006Ennn006E006E;
  @Inject
  public vpppvv b006E006Enn006Enn006E006E;
  private String b006En006En006Enn006E006E = null;
  @Inject
  public sssttt b006Ennn006Enn006E006E;
  @Inject
  public onoono bn006Enn006Enn006E006E;
  @Inject
  public vvppvv bnn006En006Enn006E006E;
  @Inject
  public xxsxxs bnnnn006Enn006E006E;
  
  public ononoo()
  {
    pqqppq.b006B006B006Bkkk006Bkkk().ba0061a0061006100610061006100610061(this);
  }
  
  public static int b006B006B006Bkk006B006B006B006Bk()
  {
    return 0;
  }
  
  public static int b006B006Bkkk006B006B006B006Bk()
  {
    return 2;
  }
  
  public static int bk006B006Bkk006B006B006B006Bk()
  {
    return 86;
  }
  
  /* Error */
  private boolean bk006Bk006Bk006B006B006B006Bk(com.db.pwcc.dbmobile.model.error.DbError paramDbError, boolean paramBoolean)
  {
    // Byte code:
    //   0: getstatic 61	uuuuuu/ononoo:bn006E006En006Enn006E006E	I
    //   3: istore_3
    //   4: iload_3
    //   5: getstatic 63	uuuuuu/ononoo:bnnn006E006Enn006E006E	I
    //   8: iload_3
    //   9: iadd
    //   10: imul
    //   11: getstatic 65	uuuuuu/ononoo:b006Enn006E006Enn006E006E	I
    //   14: irem
    //   15: tableswitch	default:+17->32, 0:+67->82
    //   32: ldc 2
    //   34: ldc 111
    //   36: sipush 175
    //   39: bipush 122
    //   41: iconst_1
    //   42: invokestatic 115	xxxxxx/uxxxxx:bbbb0062b0062b0062b0062	(Ljava/lang/String;CCC)Ljava/lang/String;
    //   45: iconst_0
    //   46: anewarray 77	java/lang/Class
    //   49: invokevirtual 81	java/lang/Class:getMethod	(Ljava/lang/String;[Ljava/lang/Class;)Ljava/lang/reflect/Method;
    //   52: astore 4
    //   54: aload 4
    //   56: aconst_null
    //   57: iconst_0
    //   58: anewarray 83	java/lang/Object
    //   61: invokevirtual 89	java/lang/reflect/Method:invoke	(Ljava/lang/Object;[Ljava/lang/Object;)Ljava/lang/Object;
    //   64: astore 4
    //   66: aload 4
    //   68: checkcast 91	java/lang/Integer
    //   71: invokevirtual 94	java/lang/Integer:intValue	()I
    //   74: putstatic 61	uuuuuu/ononoo:bn006E006En006Enn006E006E	I
    //   77: bipush 84
    //   79: putstatic 67	uuuuuu/ononoo:b006E006E006En006Enn006E006E	I
    //   82: aload_1
    //   83: ifnull +325 -> 408
    //   86: getstatic 61	uuuuuu/ononoo:bn006E006En006Enn006E006E	I
    //   89: getstatic 63	uuuuuu/ononoo:bnnn006E006Enn006E006E	I
    //   92: iadd
    //   93: getstatic 61	uuuuuu/ononoo:bn006E006En006Enn006E006E	I
    //   96: imul
    //   97: getstatic 65	uuuuuu/ononoo:b006Enn006E006Enn006E006E	I
    //   100: irem
    //   101: getstatic 67	uuuuuu/ononoo:b006E006E006En006Enn006E006E	I
    //   104: if_icmpeq +90 -> 194
    //   107: ldc 2
    //   109: ldc 117
    //   111: bipush 82
    //   113: bipush 116
    //   115: iconst_3
    //   116: invokestatic 115	xxxxxx/uxxxxx:bbbb0062b0062b0062b0062	(Ljava/lang/String;CCC)Ljava/lang/String;
    //   119: iconst_0
    //   120: anewarray 77	java/lang/Class
    //   123: invokevirtual 81	java/lang/Class:getMethod	(Ljava/lang/String;[Ljava/lang/Class;)Ljava/lang/reflect/Method;
    //   126: astore 4
    //   128: aload 4
    //   130: aconst_null
    //   131: iconst_0
    //   132: anewarray 83	java/lang/Object
    //   135: invokevirtual 89	java/lang/reflect/Method:invoke	(Ljava/lang/Object;[Ljava/lang/Object;)Ljava/lang/Object;
    //   138: astore 4
    //   140: aload 4
    //   142: checkcast 91	java/lang/Integer
    //   145: invokevirtual 94	java/lang/Integer:intValue	()I
    //   148: putstatic 61	uuuuuu/ononoo:bn006E006En006Enn006E006E	I
    //   151: ldc 2
    //   153: ldc 119
    //   155: sipush 172
    //   158: iconst_3
    //   159: invokestatic 75	xxxxxx/uxxxxx:bb00620062bb0062b0062b0062	(Ljava/lang/String;CC)Ljava/lang/String;
    //   162: iconst_0
    //   163: anewarray 77	java/lang/Class
    //   166: invokevirtual 81	java/lang/Class:getMethod	(Ljava/lang/String;[Ljava/lang/Class;)Ljava/lang/reflect/Method;
    //   169: astore 4
    //   171: aload 4
    //   173: aconst_null
    //   174: iconst_0
    //   175: anewarray 83	java/lang/Object
    //   178: invokevirtual 89	java/lang/reflect/Method:invoke	(Ljava/lang/Object;[Ljava/lang/Object;)Ljava/lang/Object;
    //   181: astore 4
    //   183: aload 4
    //   185: checkcast 91	java/lang/Integer
    //   188: invokevirtual 94	java/lang/Integer:intValue	()I
    //   191: putstatic 67	uuuuuu/ononoo:b006E006E006En006Enn006E006E	I
    //   194: aload_1
    //   195: invokevirtual 125	com/db/pwcc/dbmobile/model/error/DbError:getDbCode	()Lcom/db/pwcc/dbmobile/model/error/DbErrorCode;
    //   198: ifnonnull +147 -> 345
    //   201: iconst_0
    //   202: ireturn
    //   203: astore_1
    //   204: bipush 77
    //   206: putstatic 61	uuuuuu/ononoo:bn006E006En006Enn006E006E	I
    //   209: iconst_1
    //   210: ireturn
    //   211: new 127	java/lang/NullPointerException
    //   214: dup
    //   215: invokespecial 128	java/lang/NullPointerException:<init>	()V
    //   218: athrow
    //   219: aload_1
    //   220: invokevirtual 125	com/db/pwcc/dbmobile/model/error/DbError:getDbCode	()Lcom/db/pwcc/dbmobile/model/error/DbErrorCode;
    //   223: getstatic 134	com/db/pwcc/dbmobile/model/error/DbErrorCode:NO_INTERNET_ERROR	Lcom/db/pwcc/dbmobile/model/error/DbErrorCode;
    //   226: if_acmpne +182 -> 408
    //   229: aload_0
    //   230: getfield 98	uuuuuu/ononoo:bnnnnn006E006E006En	Luuuuuu/ttssst$tsssst;
    //   233: checkcast 136	uuuuuu/nnnooo$noonoo
    //   236: iload_2
    //   237: invokeinterface 140 2 0
    //   242: getstatic 61	uuuuuu/ononoo:bn006E006En006Enn006E006E	I
    //   245: getstatic 63	uuuuuu/ononoo:bnnn006E006Enn006E006E	I
    //   248: iadd
    //   249: getstatic 61	uuuuuu/ononoo:bn006E006En006Enn006E006E	I
    //   252: imul
    //   253: getstatic 65	uuuuuu/ononoo:b006Enn006E006Enn006E006E	I
    //   256: irem
    //   257: getstatic 67	uuuuuu/ononoo:b006E006E006En006Enn006E006E	I
    //   260: if_icmpeq +146 -> 406
    //   263: ldc 2
    //   265: ldc -114
    //   267: sipush 186
    //   270: sipush 248
    //   273: iconst_3
    //   274: invokestatic 115	xxxxxx/uxxxxx:bbbb0062b0062b0062b0062	(Ljava/lang/String;CCC)Ljava/lang/String;
    //   277: iconst_0
    //   278: anewarray 77	java/lang/Class
    //   281: invokevirtual 81	java/lang/Class:getMethod	(Ljava/lang/String;[Ljava/lang/Class;)Ljava/lang/reflect/Method;
    //   284: astore_1
    //   285: aload_1
    //   286: aconst_null
    //   287: iconst_0
    //   288: anewarray 83	java/lang/Object
    //   291: invokevirtual 89	java/lang/reflect/Method:invoke	(Ljava/lang/Object;[Ljava/lang/Object;)Ljava/lang/Object;
    //   294: astore_1
    //   295: aload_1
    //   296: checkcast 91	java/lang/Integer
    //   299: invokevirtual 94	java/lang/Integer:intValue	()I
    //   302: putstatic 61	uuuuuu/ononoo:bn006E006En006Enn006E006E	I
    //   305: ldc 2
    //   307: ldc -112
    //   309: bipush 77
    //   311: iconst_4
    //   312: invokestatic 75	xxxxxx/uxxxxx:bb00620062bb0062b0062b0062	(Ljava/lang/String;CC)Ljava/lang/String;
    //   315: iconst_0
    //   316: anewarray 77	java/lang/Class
    //   319: invokevirtual 81	java/lang/Class:getMethod	(Ljava/lang/String;[Ljava/lang/Class;)Ljava/lang/reflect/Method;
    //   322: astore_1
    //   323: aload_1
    //   324: aconst_null
    //   325: iconst_0
    //   326: anewarray 83	java/lang/Object
    //   329: invokevirtual 89	java/lang/reflect/Method:invoke	(Ljava/lang/Object;[Ljava/lang/Object;)Ljava/lang/Object;
    //   332: astore_1
    //   333: aload_1
    //   334: checkcast 91	java/lang/Integer
    //   337: invokevirtual 94	java/lang/Integer:intValue	()I
    //   340: putstatic 67	uuuuuu/ononoo:b006E006E006En006Enn006E006E	I
    //   343: iconst_1
    //   344: ireturn
    //   345: aload_1
    //   346: invokevirtual 125	com/db/pwcc/dbmobile/model/error/DbError:getDbCode	()Lcom/db/pwcc/dbmobile/model/error/DbErrorCode;
    //   349: getstatic 147	com/db/pwcc/dbmobile/model/error/DbErrorCode:INSECURE_CONNECTION_ERROR	Lcom/db/pwcc/dbmobile/model/error/DbErrorCode;
    //   352: if_acmpne -133 -> 219
    //   355: aload_0
    //   356: getfield 98	uuuuuu/ononoo:bnnnnn006E006E006En	Luuuuuu/ttssst$tsssst;
    //   359: checkcast 136	uuuuuu/nnnooo$noonoo
    //   362: invokeinterface 150 1 0
    //   367: getstatic 156	uuuuuu/vvrvrv:bh0068h00680068h0068h0068	Luuuuuu/vvrvrv;
    //   370: invokestatic 162	uuuuuu/rrvvrv:b00710071qqq0071q0071q0071	(Luuuuuu/vvrvrv;)V
    //   373: goto -162 -> 211
    //   376: astore_1
    //   377: aload_1
    //   378: invokevirtual 104	java/lang/reflect/InvocationTargetException:getCause	()Ljava/lang/Throwable;
    //   381: athrow
    //   382: astore_1
    //   383: aload_1
    //   384: invokevirtual 104	java/lang/reflect/InvocationTargetException:getCause	()Ljava/lang/Throwable;
    //   387: athrow
    //   388: astore_1
    //   389: aload_1
    //   390: invokevirtual 104	java/lang/reflect/InvocationTargetException:getCause	()Ljava/lang/Throwable;
    //   393: athrow
    //   394: astore_1
    //   395: aload_1
    //   396: invokevirtual 104	java/lang/reflect/InvocationTargetException:getCause	()Ljava/lang/Throwable;
    //   399: athrow
    //   400: astore_1
    //   401: aload_1
    //   402: invokevirtual 104	java/lang/reflect/InvocationTargetException:getCause	()Ljava/lang/Throwable;
    //   405: athrow
    //   406: iconst_1
    //   407: ireturn
    //   408: iconst_0
    //   409: ireturn
    // Local variable table:
    //   start	length	slot	name	signature
    //   0	410	0	this	ononoo
    //   0	410	1	paramDbError	com.db.pwcc.dbmobile.model.error.DbError
    //   0	410	2	paramBoolean	boolean
    //   3	8	3	i	int
    //   52	132	4	localObject	Object
    // Exception table:
    //   from	to	target	type
    //   211	219	203	java/lang/Exception
    //   54	66	376	java/lang/reflect/InvocationTargetException
    //   285	295	382	java/lang/reflect/InvocationTargetException
    //   323	333	388	java/lang/reflect/InvocationTargetException
    //   128	140	394	java/lang/reflect/InvocationTargetException
    //   171	183	400	java/lang/reflect/InvocationTargetException
  }
  
  public static int bkk006Bkk006B006B006B006Bk()
  {
    return 1;
  }
  
  /* Error */
  public void b00610061006100610061aaa0061a(com.db.pwcc.dbmobile.model.auth.LoginResponse paramLoginResponse, String paramString1, String paramString2)
  {
    // Byte code:
    //   0: getstatic 61	uuuuuu/ononoo:bn006E006En006Enn006E006E	I
    //   3: getstatic 63	uuuuuu/ononoo:bnnn006E006Enn006E006E	I
    //   6: iadd
    //   7: getstatic 61	uuuuuu/ononoo:bn006E006En006Enn006E006E	I
    //   10: imul
    //   11: getstatic 65	uuuuuu/ononoo:b006Enn006E006Enn006E006E	I
    //   14: irem
    //   15: getstatic 67	uuuuuu/ononoo:b006E006E006En006Enn006E006E	I
    //   18: if_icmpeq +46 -> 64
    //   21: bipush 48
    //   23: putstatic 61	uuuuuu/ononoo:bn006E006En006Enn006E006E	I
    //   26: ldc 2
    //   28: ldc -89
    //   30: bipush 18
    //   32: iconst_0
    //   33: invokestatic 75	xxxxxx/uxxxxx:bb00620062bb0062b0062b0062	(Ljava/lang/String;CC)Ljava/lang/String;
    //   36: iconst_0
    //   37: anewarray 77	java/lang/Class
    //   40: invokevirtual 81	java/lang/Class:getMethod	(Ljava/lang/String;[Ljava/lang/Class;)Ljava/lang/reflect/Method;
    //   43: astore_2
    //   44: aload_2
    //   45: aconst_null
    //   46: iconst_0
    //   47: anewarray 83	java/lang/Object
    //   50: invokevirtual 89	java/lang/reflect/Method:invoke	(Ljava/lang/Object;[Ljava/lang/Object;)Ljava/lang/Object;
    //   53: astore_2
    //   54: aload_2
    //   55: checkcast 91	java/lang/Integer
    //   58: invokevirtual 94	java/lang/Integer:intValue	()I
    //   61: putstatic 67	uuuuuu/ononoo:b006E006E006En006Enn006E006E	I
    //   64: aload_0
    //   65: invokevirtual 171	uuuuuu/ononoo:bkk006Bk006Bk006Bk006Bk	()Z
    //   68: ifne +4 -> 72
    //   71: return
    //   72: new 173	com/db/pwcc/dbmobile/model/fingerprint/SecureFingerprintData
    //   75: dup
    //   76: aload_1
    //   77: invokevirtual 179	com/db/pwcc/dbmobile/model/auth/LoginResponse:getFingerprintToken	()Ljava/lang/String;
    //   80: aload_1
    //   81: invokevirtual 182	com/db/pwcc/dbmobile/model/auth/LoginResponse:getFingerprintTokenVersion	()Ljava/lang/String;
    //   84: invokespecial 185	com/db/pwcc/dbmobile/model/fingerprint/SecureFingerprintData:<init>	(Ljava/lang/String;Ljava/lang/String;)V
    //   87: astore_2
    //   88: aload_0
    //   89: getfield 98	uuuuuu/ononoo:bnnnnn006E006E006En	Luuuuuu/ttssst$tsssst;
    //   92: checkcast 136	uuuuuu/nnnooo$noonoo
    //   95: invokeinterface 188 1 0
    //   100: aload_0
    //   101: getfield 190	uuuuuu/ononoo:bn006Enn006Enn006E006E	Luuuuuu/onoono;
    //   104: astore_3
    //   105: aload_0
    //   106: getfield 194	uuuuuu/ononoo:b006E006E006E006E006En006E006En	Luuuuuu/hyhyhh;
    //   109: invokevirtual 199	uuuuuu/hyhyhh:b0070pp007000700070p007000700070	()Ljava/lang/String;
    //   112: astore 6
    //   114: aload_0
    //   115: getfield 98	uuuuuu/ononoo:bnnnnn006E006E006En	Luuuuuu/ttssst$tsssst;
    //   118: astore 7
    //   120: getstatic 61	uuuuuu/ononoo:bn006E006En006Enn006E006E	I
    //   123: getstatic 63	uuuuuu/ononoo:bnnn006E006Enn006E006E	I
    //   126: iadd
    //   127: getstatic 61	uuuuuu/ononoo:bn006E006En006Enn006E006E	I
    //   130: imul
    //   131: getstatic 65	uuuuuu/ononoo:b006Enn006E006Enn006E006E	I
    //   134: irem
    //   135: getstatic 67	uuuuuu/ononoo:b006E006E006En006Enn006E006E	I
    //   138: if_icmpeq +12 -> 150
    //   141: bipush 67
    //   143: putstatic 61	uuuuuu/ononoo:bn006E006En006Enn006E006E	I
    //   146: iconst_3
    //   147: putstatic 67	uuuuuu/ononoo:b006E006E006En006Enn006E006E	I
    //   150: aload_3
    //   151: aload_2
    //   152: aload_0
    //   153: aload 6
    //   155: aload 7
    //   157: checkcast 136	uuuuuu/nnnooo$noonoo
    //   160: invokeinterface 203 1 0
    //   165: invokeinterface 209 5 0
    //   170: aload_0
    //   171: getfield 213	uuuuuu/ononoo:b006En006E006E006En006E006En	Luuuuuu/ggyggy;
    //   174: getstatic 219	uuuuuu/gyyygy$yyyygy:bkkk006Bk006Bk006Bk	Luuuuuu/gyyygy$yyyygy;
    //   177: invokevirtual 225	uuuuuu/ggyggy:b0070007000700070pp00700070pp	(Luuuuuu/gyyygy$yyyygy;)Luuuuuu/yyyggy;
    //   180: invokeinterface 231 1 0
    //   185: astore_2
    //   186: ldc 2
    //   188: ldc -23
    //   190: sipush 185
    //   193: iconst_2
    //   194: invokestatic 75	xxxxxx/uxxxxx:bb00620062bb0062b0062b0062	(Ljava/lang/String;CC)Ljava/lang/String;
    //   197: iconst_0
    //   198: anewarray 77	java/lang/Class
    //   201: invokevirtual 81	java/lang/Class:getMethod	(Ljava/lang/String;[Ljava/lang/Class;)Ljava/lang/reflect/Method;
    //   204: astore_3
    //   205: aload_3
    //   206: aconst_null
    //   207: iconst_0
    //   208: anewarray 83	java/lang/Object
    //   211: invokevirtual 89	java/lang/reflect/Method:invoke	(Ljava/lang/Object;[Ljava/lang/Object;)Ljava/lang/Object;
    //   214: astore_3
    //   215: aload_3
    //   216: checkcast 91	java/lang/Integer
    //   219: invokevirtual 94	java/lang/Integer:intValue	()I
    //   222: istore 4
    //   224: getstatic 63	uuuuuu/ononoo:bnnn006E006Enn006E006E	I
    //   227: istore 5
    //   229: ldc 2
    //   231: ldc -21
    //   233: bipush 8
    //   235: iconst_3
    //   236: invokestatic 75	xxxxxx/uxxxxx:bb00620062bb0062b0062b0062	(Ljava/lang/String;CC)Ljava/lang/String;
    //   239: iconst_0
    //   240: anewarray 77	java/lang/Class
    //   243: invokevirtual 81	java/lang/Class:getMethod	(Ljava/lang/String;[Ljava/lang/Class;)Ljava/lang/reflect/Method;
    //   246: astore_3
    //   247: aload_3
    //   248: aconst_null
    //   249: iconst_0
    //   250: anewarray 83	java/lang/Object
    //   253: invokevirtual 89	java/lang/reflect/Method:invoke	(Ljava/lang/Object;[Ljava/lang/Object;)Ljava/lang/Object;
    //   256: astore_3
    //   257: aload_3
    //   258: checkcast 91	java/lang/Integer
    //   261: invokevirtual 94	java/lang/Integer:intValue	()I
    //   264: iload 5
    //   266: iload 4
    //   268: iadd
    //   269: imul
    //   270: getstatic 65	uuuuuu/ononoo:b006Enn006E006Enn006E006E	I
    //   273: irem
    //   274: getstatic 67	uuuuuu/ononoo:b006E006E006En006Enn006E006E	I
    //   277: if_icmpeq +82 -> 359
    //   280: ldc 2
    //   282: ldc -19
    //   284: bipush 41
    //   286: iconst_0
    //   287: invokestatic 75	xxxxxx/uxxxxx:bb00620062bb0062b0062b0062	(Ljava/lang/String;CC)Ljava/lang/String;
    //   290: iconst_0
    //   291: anewarray 77	java/lang/Class
    //   294: invokevirtual 81	java/lang/Class:getMethod	(Ljava/lang/String;[Ljava/lang/Class;)Ljava/lang/reflect/Method;
    //   297: astore_3
    //   298: aload_3
    //   299: aconst_null
    //   300: iconst_0
    //   301: anewarray 83	java/lang/Object
    //   304: invokevirtual 89	java/lang/reflect/Method:invoke	(Ljava/lang/Object;[Ljava/lang/Object;)Ljava/lang/Object;
    //   307: astore_3
    //   308: aload_3
    //   309: checkcast 91	java/lang/Integer
    //   312: invokevirtual 94	java/lang/Integer:intValue	()I
    //   315: putstatic 61	uuuuuu/ononoo:bn006E006En006Enn006E006E	I
    //   318: ldc 2
    //   320: ldc -17
    //   322: bipush 21
    //   324: sipush 248
    //   327: iconst_3
    //   328: invokestatic 115	xxxxxx/uxxxxx:bbbb0062b0062b0062b0062	(Ljava/lang/String;CCC)Ljava/lang/String;
    //   331: iconst_0
    //   332: anewarray 77	java/lang/Class
    //   335: invokevirtual 81	java/lang/Class:getMethod	(Ljava/lang/String;[Ljava/lang/Class;)Ljava/lang/reflect/Method;
    //   338: astore_3
    //   339: aload_3
    //   340: aconst_null
    //   341: iconst_0
    //   342: anewarray 83	java/lang/Object
    //   345: invokevirtual 89	java/lang/reflect/Method:invoke	(Ljava/lang/Object;[Ljava/lang/Object;)Ljava/lang/Object;
    //   348: astore_3
    //   349: aload_3
    //   350: checkcast 91	java/lang/Integer
    //   353: invokevirtual 94	java/lang/Integer:intValue	()I
    //   356: putstatic 67	uuuuuu/ononoo:b006E006E006En006Enn006E006E	I
    //   359: aload_2
    //   360: aload_1
    //   361: invokevirtual 242	com/db/pwcc/dbmobile/model/auth/LoginResponse:getAccessToken	()Ljava/lang/String;
    //   364: invokevirtual 248	uuuuuu/ggyygy:b007000700070ppppp0070p	(Ljava/lang/String;)V
    //   367: aload_0
    //   368: getfield 250	uuuuuu/ononoo:bnn006En006Enn006E006E	Luuuuuu/vvppvv;
    //   371: invokeinterface 255 1 0
    //   376: aload_2
    //   377: aload_0
    //   378: getfield 39	uuuuuu/ononoo:b006En006En006Enn006E006E	Ljava/lang/String;
    //   381: invokevirtual 248	uuuuuu/ggyygy:b007000700070ppppp0070p	(Ljava/lang/String;)V
    //   384: getstatic 61	uuuuuu/ononoo:bn006E006En006Enn006E006E	I
    //   387: istore 4
    //   389: iload 4
    //   391: getstatic 63	uuuuuu/ononoo:bnnn006E006Enn006E006E	I
    //   394: iload 4
    //   396: iadd
    //   397: imul
    //   398: getstatic 65	uuuuuu/ononoo:b006Enn006E006Enn006E006E	I
    //   401: irem
    //   402: tableswitch	default:+18->420, 0:+-331->71
    //   420: bipush 49
    //   422: putstatic 61	uuuuuu/ononoo:bn006E006En006Enn006E006E	I
    //   425: ldc 2
    //   427: ldc_w 257
    //   430: bipush 6
    //   432: iconst_3
    //   433: invokestatic 75	xxxxxx/uxxxxx:bb00620062bb0062b0062b0062	(Ljava/lang/String;CC)Ljava/lang/String;
    //   436: iconst_0
    //   437: anewarray 77	java/lang/Class
    //   440: invokevirtual 81	java/lang/Class:getMethod	(Ljava/lang/String;[Ljava/lang/Class;)Ljava/lang/reflect/Method;
    //   443: astore_1
    //   444: aload_1
    //   445: aconst_null
    //   446: iconst_0
    //   447: anewarray 83	java/lang/Object
    //   450: invokevirtual 89	java/lang/reflect/Method:invoke	(Ljava/lang/Object;[Ljava/lang/Object;)Ljava/lang/Object;
    //   453: astore_1
    //   454: aload_1
    //   455: checkcast 91	java/lang/Integer
    //   458: invokevirtual 94	java/lang/Integer:intValue	()I
    //   461: putstatic 67	uuuuuu/ononoo:b006E006E006En006Enn006E006E	I
    //   464: return
    //   465: astore_1
    //   466: aload_1
    //   467: invokevirtual 104	java/lang/reflect/InvocationTargetException:getCause	()Ljava/lang/Throwable;
    //   470: athrow
    //   471: astore_1
    //   472: aload_1
    //   473: invokevirtual 104	java/lang/reflect/InvocationTargetException:getCause	()Ljava/lang/Throwable;
    //   476: athrow
    //   477: astore_1
    //   478: aload_1
    //   479: invokevirtual 104	java/lang/reflect/InvocationTargetException:getCause	()Ljava/lang/Throwable;
    //   482: athrow
    //   483: astore_1
    //   484: aload_1
    //   485: invokevirtual 104	java/lang/reflect/InvocationTargetException:getCause	()Ljava/lang/Throwable;
    //   488: athrow
    //   489: astore_1
    //   490: aload_1
    //   491: invokevirtual 104	java/lang/reflect/InvocationTargetException:getCause	()Ljava/lang/Throwable;
    //   494: athrow
    //   495: astore_1
    //   496: aload_1
    //   497: invokevirtual 104	java/lang/reflect/InvocationTargetException:getCause	()Ljava/lang/Throwable;
    //   500: athrow
    // Local variable table:
    //   start	length	slot	name	signature
    //   0	501	0	this	ononoo
    //   0	501	1	paramLoginResponse	com.db.pwcc.dbmobile.model.auth.LoginResponse
    //   0	501	2	paramString1	String
    //   0	501	3	paramString2	String
    //   222	176	4	i	int
    //   227	42	5	j	int
    //   112	42	6	str	String
    //   118	38	7	localTsssst	ttssst.tsssst
    // Exception table:
    //   from	to	target	type
    //   205	215	465	java/lang/reflect/InvocationTargetException
    //   247	257	471	java/lang/reflect/InvocationTargetException
    //   444	454	477	java/lang/reflect/InvocationTargetException
    //   44	54	483	java/lang/reflect/InvocationTargetException
    //   298	308	489	java/lang/reflect/InvocationTargetException
    //   339	349	495	java/lang/reflect/InvocationTargetException
  }
  
  /* Error */
  public void b006100610061aaa0061a0061a()
  {
    // Byte code:
    //   0: ldc 2
    //   2: ldc_w 260
    //   5: bipush 63
    //   7: iconst_1
    //   8: invokestatic 75	xxxxxx/uxxxxx:bb00620062bb0062b0062b0062	(Ljava/lang/String;CC)Ljava/lang/String;
    //   11: iconst_0
    //   12: anewarray 77	java/lang/Class
    //   15: invokevirtual 81	java/lang/Class:getMethod	(Ljava/lang/String;[Ljava/lang/Class;)Ljava/lang/reflect/Method;
    //   18: astore 5
    //   20: aload 5
    //   22: aconst_null
    //   23: iconst_0
    //   24: anewarray 83	java/lang/Object
    //   27: invokevirtual 89	java/lang/reflect/Method:invoke	(Ljava/lang/Object;[Ljava/lang/Object;)Ljava/lang/Object;
    //   30: astore 5
    //   32: aload 5
    //   34: checkcast 91	java/lang/Integer
    //   37: invokevirtual 94	java/lang/Integer:intValue	()I
    //   40: istore_1
    //   41: getstatic 63	uuuuuu/ononoo:bnnn006E006Enn006E006E	I
    //   44: istore_2
    //   45: ldc 2
    //   47: ldc -114
    //   49: bipush 90
    //   51: iconst_1
    //   52: invokestatic 75	xxxxxx/uxxxxx:bb00620062bb0062b0062b0062	(Ljava/lang/String;CC)Ljava/lang/String;
    //   55: iconst_0
    //   56: anewarray 77	java/lang/Class
    //   59: invokevirtual 81	java/lang/Class:getMethod	(Ljava/lang/String;[Ljava/lang/Class;)Ljava/lang/reflect/Method;
    //   62: astore 5
    //   64: aload 5
    //   66: aconst_null
    //   67: iconst_0
    //   68: anewarray 83	java/lang/Object
    //   71: invokevirtual 89	java/lang/reflect/Method:invoke	(Ljava/lang/Object;[Ljava/lang/Object;)Ljava/lang/Object;
    //   74: astore 5
    //   76: aload 5
    //   78: checkcast 91	java/lang/Integer
    //   81: invokevirtual 94	java/lang/Integer:intValue	()I
    //   84: istore_3
    //   85: getstatic 65	uuuuuu/ononoo:b006Enn006E006Enn006E006E	I
    //   88: istore 4
    //   90: ldc 2
    //   92: ldc_w 262
    //   95: bipush 12
    //   97: iconst_4
    //   98: invokestatic 75	xxxxxx/uxxxxx:bb00620062bb0062b0062b0062	(Ljava/lang/String;CC)Ljava/lang/String;
    //   101: iconst_0
    //   102: anewarray 77	java/lang/Class
    //   105: invokevirtual 81	java/lang/Class:getMethod	(Ljava/lang/String;[Ljava/lang/Class;)Ljava/lang/reflect/Method;
    //   108: astore 5
    //   110: aload 5
    //   112: aconst_null
    //   113: iconst_0
    //   114: anewarray 83	java/lang/Object
    //   117: invokevirtual 89	java/lang/reflect/Method:invoke	(Ljava/lang/Object;[Ljava/lang/Object;)Ljava/lang/Object;
    //   120: astore 5
    //   122: iload_3
    //   123: iload_2
    //   124: iload_1
    //   125: iadd
    //   126: imul
    //   127: iload 4
    //   129: irem
    //   130: aload 5
    //   132: checkcast 91	java/lang/Integer
    //   135: invokevirtual 94	java/lang/Integer:intValue	()I
    //   138: if_icmpeq +170 -> 308
    //   141: getstatic 61	uuuuuu/ononoo:bn006E006En006Enn006E006E	I
    //   144: istore_1
    //   145: iload_1
    //   146: getstatic 63	uuuuuu/ononoo:bnnn006E006Enn006E006E	I
    //   149: iload_1
    //   150: iadd
    //   151: imul
    //   152: getstatic 65	uuuuuu/ononoo:b006Enn006E006Enn006E006E	I
    //   155: irem
    //   156: tableswitch	default:+20->176, 0:+102->258
    //   176: ldc 2
    //   178: ldc_w 264
    //   181: bipush 123
    //   183: sipush 213
    //   186: iconst_0
    //   187: invokestatic 115	xxxxxx/uxxxxx:bbbb0062b0062b0062b0062	(Ljava/lang/String;CCC)Ljava/lang/String;
    //   190: iconst_0
    //   191: anewarray 77	java/lang/Class
    //   194: invokevirtual 81	java/lang/Class:getMethod	(Ljava/lang/String;[Ljava/lang/Class;)Ljava/lang/reflect/Method;
    //   197: astore 5
    //   199: aload 5
    //   201: aconst_null
    //   202: iconst_0
    //   203: anewarray 83	java/lang/Object
    //   206: invokevirtual 89	java/lang/reflect/Method:invoke	(Ljava/lang/Object;[Ljava/lang/Object;)Ljava/lang/Object;
    //   209: astore 5
    //   211: aload 5
    //   213: checkcast 91	java/lang/Integer
    //   216: invokevirtual 94	java/lang/Integer:intValue	()I
    //   219: putstatic 61	uuuuuu/ononoo:bn006E006En006Enn006E006E	I
    //   222: bipush 18
    //   224: putstatic 67	uuuuuu/ononoo:b006E006E006En006Enn006E006E	I
    //   227: getstatic 61	uuuuuu/ononoo:bn006E006En006Enn006E006E	I
    //   230: getstatic 63	uuuuuu/ononoo:bnnn006E006Enn006E006E	I
    //   233: iadd
    //   234: getstatic 61	uuuuuu/ononoo:bn006E006En006Enn006E006E	I
    //   237: imul
    //   238: getstatic 65	uuuuuu/ononoo:b006Enn006E006Enn006E006E	I
    //   241: irem
    //   242: getstatic 67	uuuuuu/ononoo:b006E006E006En006Enn006E006E	I
    //   245: if_icmpeq +13 -> 258
    //   248: bipush 82
    //   250: putstatic 61	uuuuuu/ononoo:bn006E006En006Enn006E006E	I
    //   253: bipush 86
    //   255: putstatic 67	uuuuuu/ononoo:b006E006E006En006Enn006E006E	I
    //   258: bipush 42
    //   260: putstatic 61	uuuuuu/ononoo:bn006E006En006Enn006E006E	I
    //   263: ldc 2
    //   265: ldc_w 266
    //   268: bipush 50
    //   270: bipush 59
    //   272: iconst_3
    //   273: invokestatic 115	xxxxxx/uxxxxx:bbbb0062b0062b0062b0062	(Ljava/lang/String;CCC)Ljava/lang/String;
    //   276: iconst_0
    //   277: anewarray 77	java/lang/Class
    //   280: invokevirtual 81	java/lang/Class:getMethod	(Ljava/lang/String;[Ljava/lang/Class;)Ljava/lang/reflect/Method;
    //   283: astore 5
    //   285: aload 5
    //   287: aconst_null
    //   288: iconst_0
    //   289: anewarray 83	java/lang/Object
    //   292: invokevirtual 89	java/lang/reflect/Method:invoke	(Ljava/lang/Object;[Ljava/lang/Object;)Ljava/lang/Object;
    //   295: astore 5
    //   297: aload 5
    //   299: checkcast 91	java/lang/Integer
    //   302: invokevirtual 94	java/lang/Integer:intValue	()I
    //   305: putstatic 67	uuuuuu/ononoo:b006E006E006En006Enn006E006E	I
    //   308: getstatic 269	uuuuuu/vvrvrv:b00680068h0068h00680068h0068	Luuuuuu/vvrvrv;
    //   311: invokestatic 272	uuuuuu/rrvvrv:b0071q0071qq0071q0071q0071	(Luuuuuu/vvrvrv;)V
    //   314: getstatic 61	uuuuuu/ononoo:bn006E006En006Enn006E006E	I
    //   317: getstatic 63	uuuuuu/ononoo:bnnn006E006Enn006E006E	I
    //   320: iadd
    //   321: getstatic 61	uuuuuu/ononoo:bn006E006En006Enn006E006E	I
    //   324: imul
    //   325: getstatic 65	uuuuuu/ononoo:b006Enn006E006Enn006E006E	I
    //   328: irem
    //   329: getstatic 67	uuuuuu/ononoo:b006E006E006En006Enn006E006E	I
    //   332: if_icmpeq +13 -> 345
    //   335: bipush 46
    //   337: putstatic 61	uuuuuu/ononoo:bn006E006En006Enn006E006E	I
    //   340: bipush 88
    //   342: putstatic 67	uuuuuu/ononoo:b006E006E006En006Enn006E006E	I
    //   345: aload_0
    //   346: getfield 190	uuuuuu/ononoo:bn006Enn006Enn006E006E	Luuuuuu/onoono;
    //   349: invokeinterface 275 1 0
    //   354: ldc 2
    //   356: ldc_w 277
    //   359: bipush 21
    //   361: iconst_4
    //   362: invokestatic 75	xxxxxx/uxxxxx:bb00620062bb0062b0062b0062	(Ljava/lang/String;CC)Ljava/lang/String;
    //   365: iconst_0
    //   366: anewarray 77	java/lang/Class
    //   369: invokevirtual 81	java/lang/Class:getMethod	(Ljava/lang/String;[Ljava/lang/Class;)Ljava/lang/reflect/Method;
    //   372: astore 5
    //   374: aload 5
    //   376: aload_0
    //   377: iconst_0
    //   378: anewarray 83	java/lang/Object
    //   381: invokevirtual 89	java/lang/reflect/Method:invoke	(Ljava/lang/Object;[Ljava/lang/Object;)Ljava/lang/Object;
    //   384: pop
    //   385: return
    //   386: astore 5
    //   388: aload 5
    //   390: invokevirtual 104	java/lang/reflect/InvocationTargetException:getCause	()Ljava/lang/Throwable;
    //   393: athrow
    //   394: astore 5
    //   396: aload 5
    //   398: invokevirtual 104	java/lang/reflect/InvocationTargetException:getCause	()Ljava/lang/Throwable;
    //   401: athrow
    //   402: astore 5
    //   404: aload 5
    //   406: invokevirtual 104	java/lang/reflect/InvocationTargetException:getCause	()Ljava/lang/Throwable;
    //   409: athrow
    //   410: astore 5
    //   412: aload 5
    //   414: invokevirtual 104	java/lang/reflect/InvocationTargetException:getCause	()Ljava/lang/Throwable;
    //   417: athrow
    //   418: astore 5
    //   420: aload 5
    //   422: invokevirtual 104	java/lang/reflect/InvocationTargetException:getCause	()Ljava/lang/Throwable;
    //   425: athrow
    //   426: astore 5
    //   428: aload 5
    //   430: invokevirtual 104	java/lang/reflect/InvocationTargetException:getCause	()Ljava/lang/Throwable;
    //   433: athrow
    // Local variable table:
    //   start	length	slot	name	signature
    //   0	434	0	this	ononoo
    //   40	112	1	i	int
    //   44	82	2	j	int
    //   84	43	3	k	int
    //   88	42	4	m	int
    //   18	357	5	localObject	Object
    //   386	3	5	localInvocationTargetException1	java.lang.reflect.InvocationTargetException
    //   394	3	5	localInvocationTargetException2	java.lang.reflect.InvocationTargetException
    //   402	3	5	localInvocationTargetException3	java.lang.reflect.InvocationTargetException
    //   410	3	5	localInvocationTargetException4	java.lang.reflect.InvocationTargetException
    //   418	3	5	localInvocationTargetException5	java.lang.reflect.InvocationTargetException
    //   426	3	5	localInvocationTargetException6	java.lang.reflect.InvocationTargetException
    // Exception table:
    //   from	to	target	type
    //   20	32	386	java/lang/reflect/InvocationTargetException
    //   64	76	394	java/lang/reflect/InvocationTargetException
    //   374	385	402	java/lang/reflect/InvocationTargetException
    //   110	122	410	java/lang/reflect/InvocationTargetException
    //   285	297	418	java/lang/reflect/InvocationTargetException
    //   199	211	426	java/lang/reflect/InvocationTargetException
  }
  
  public void b0061aa0061aa0061a0061a() {}
  
  /* Error */
  public void b006B006B006B006B006Bk006B006B006Bk()
  {
    // Byte code:
    //   0: getstatic 61	uuuuuu/ononoo:bn006E006En006Enn006E006E	I
    //   3: getstatic 63	uuuuuu/ononoo:bnnn006E006Enn006E006E	I
    //   6: iadd
    //   7: getstatic 61	uuuuuu/ononoo:bn006E006En006Enn006E006E	I
    //   10: imul
    //   11: getstatic 65	uuuuuu/ononoo:b006Enn006E006Enn006E006E	I
    //   14: irem
    //   15: getstatic 67	uuuuuu/ononoo:b006E006E006En006Enn006E006E	I
    //   18: if_icmpeq +13 -> 31
    //   21: bipush 84
    //   23: putstatic 61	uuuuuu/ononoo:bn006E006En006Enn006E006E	I
    //   26: bipush 86
    //   28: putstatic 67	uuuuuu/ononoo:b006E006E006En006Enn006E006E	I
    //   31: aload_0
    //   32: getfield 281	uuuuuu/ononoo:bnnnn006Enn006E006E	Luuuuuu/xxsxxs;
    //   35: astore_2
    //   36: aload_0
    //   37: getfield 283	uuuuuu/ononoo:b006E006E006E006Ennn006E006E	Landroid/content/Context;
    //   40: astore_3
    //   41: getstatic 61	uuuuuu/ononoo:bn006E006En006Enn006E006E	I
    //   44: getstatic 63	uuuuuu/ononoo:bnnn006E006Enn006E006E	I
    //   47: iadd
    //   48: getstatic 61	uuuuuu/ononoo:bn006E006En006Enn006E006E	I
    //   51: imul
    //   52: getstatic 65	uuuuuu/ononoo:b006Enn006E006Enn006E006E	I
    //   55: irem
    //   56: getstatic 67	uuuuuu/ononoo:b006E006E006En006Enn006E006E	I
    //   59: if_icmpeq +256 -> 315
    //   62: getstatic 61	uuuuuu/ononoo:bn006E006En006Enn006E006E	I
    //   65: istore_1
    //   66: iload_1
    //   67: getstatic 63	uuuuuu/ononoo:bnnn006E006Enn006E006E	I
    //   70: iload_1
    //   71: iadd
    //   72: imul
    //   73: getstatic 65	uuuuuu/ononoo:b006Enn006E006Enn006E006E	I
    //   76: irem
    //   77: tableswitch	default:+19->96, 0:+66->143
    //   96: ldc 2
    //   98: ldc -21
    //   100: bipush 8
    //   102: iconst_3
    //   103: invokestatic 75	xxxxxx/uxxxxx:bb00620062bb0062b0062b0062	(Ljava/lang/String;CC)Ljava/lang/String;
    //   106: iconst_0
    //   107: anewarray 77	java/lang/Class
    //   110: invokevirtual 81	java/lang/Class:getMethod	(Ljava/lang/String;[Ljava/lang/Class;)Ljava/lang/reflect/Method;
    //   113: astore 4
    //   115: aload 4
    //   117: aconst_null
    //   118: iconst_0
    //   119: anewarray 83	java/lang/Object
    //   122: invokevirtual 89	java/lang/reflect/Method:invoke	(Ljava/lang/Object;[Ljava/lang/Object;)Ljava/lang/Object;
    //   125: astore 4
    //   127: aload 4
    //   129: checkcast 91	java/lang/Integer
    //   132: invokevirtual 94	java/lang/Integer:intValue	()I
    //   135: putstatic 61	uuuuuu/ononoo:bn006E006En006Enn006E006E	I
    //   138: bipush 24
    //   140: putstatic 67	uuuuuu/ononoo:b006E006E006En006Enn006E006E	I
    //   143: getstatic 61	uuuuuu/ononoo:bn006E006En006Enn006E006E	I
    //   146: istore_1
    //   147: ldc 2
    //   149: ldc_w 285
    //   152: sipush 133
    //   155: iconst_4
    //   156: invokestatic 75	xxxxxx/uxxxxx:bb00620062bb0062b0062b0062	(Ljava/lang/String;CC)Ljava/lang/String;
    //   159: iconst_0
    //   160: anewarray 77	java/lang/Class
    //   163: invokevirtual 81	java/lang/Class:getMethod	(Ljava/lang/String;[Ljava/lang/Class;)Ljava/lang/reflect/Method;
    //   166: astore 4
    //   168: aload 4
    //   170: aconst_null
    //   171: iconst_0
    //   172: anewarray 83	java/lang/Object
    //   175: invokevirtual 89	java/lang/reflect/Method:invoke	(Ljava/lang/Object;[Ljava/lang/Object;)Ljava/lang/Object;
    //   178: astore 4
    //   180: aload 4
    //   182: checkcast 91	java/lang/Integer
    //   185: invokevirtual 94	java/lang/Integer:intValue	()I
    //   188: iload_1
    //   189: iadd
    //   190: iload_1
    //   191: imul
    //   192: getstatic 65	uuuuuu/ononoo:b006Enn006E006Enn006E006E	I
    //   195: irem
    //   196: tableswitch	default:+20->216, 0:+67->263
    //   216: ldc 2
    //   218: ldc -112
    //   220: bipush 9
    //   222: iconst_5
    //   223: invokestatic 75	xxxxxx/uxxxxx:bb00620062bb0062b0062b0062	(Ljava/lang/String;CC)Ljava/lang/String;
    //   226: iconst_0
    //   227: anewarray 77	java/lang/Class
    //   230: invokevirtual 81	java/lang/Class:getMethod	(Ljava/lang/String;[Ljava/lang/Class;)Ljava/lang/reflect/Method;
    //   233: astore 4
    //   235: aload 4
    //   237: aconst_null
    //   238: iconst_0
    //   239: anewarray 83	java/lang/Object
    //   242: invokevirtual 89	java/lang/reflect/Method:invoke	(Ljava/lang/Object;[Ljava/lang/Object;)Ljava/lang/Object;
    //   245: astore 4
    //   247: aload 4
    //   249: checkcast 91	java/lang/Integer
    //   252: invokevirtual 94	java/lang/Integer:intValue	()I
    //   255: putstatic 61	uuuuuu/ononoo:bn006E006En006Enn006E006E	I
    //   258: bipush 60
    //   260: putstatic 67	uuuuuu/ononoo:b006E006E006En006Enn006E006E	I
    //   263: ldc 2
    //   265: ldc_w 287
    //   268: sipush 150
    //   271: sipush 174
    //   274: iconst_0
    //   275: invokestatic 115	xxxxxx/uxxxxx:bbbb0062b0062b0062b0062	(Ljava/lang/String;CCC)Ljava/lang/String;
    //   278: iconst_0
    //   279: anewarray 77	java/lang/Class
    //   282: invokevirtual 81	java/lang/Class:getMethod	(Ljava/lang/String;[Ljava/lang/Class;)Ljava/lang/reflect/Method;
    //   285: astore 4
    //   287: aload 4
    //   289: aconst_null
    //   290: iconst_0
    //   291: anewarray 83	java/lang/Object
    //   294: invokevirtual 89	java/lang/reflect/Method:invoke	(Ljava/lang/Object;[Ljava/lang/Object;)Ljava/lang/Object;
    //   297: astore 4
    //   299: aload 4
    //   301: checkcast 91	java/lang/Integer
    //   304: invokevirtual 94	java/lang/Integer:intValue	()I
    //   307: putstatic 61	uuuuuu/ononoo:bn006E006En006Enn006E006E	I
    //   310: bipush 11
    //   312: putstatic 67	uuuuuu/ononoo:b006E006E006En006Enn006E006E	I
    //   315: aload_2
    //   316: aload_3
    //   317: invokevirtual 293	uuuuuu/xxsxxs:bkkkk006Bk006Bk006B006B	(Landroid/content/Context;)V
    //   320: return
    //   321: astore_2
    //   322: aload_2
    //   323: invokevirtual 104	java/lang/reflect/InvocationTargetException:getCause	()Ljava/lang/Throwable;
    //   326: athrow
    //   327: astore_2
    //   328: aload_2
    //   329: invokevirtual 104	java/lang/reflect/InvocationTargetException:getCause	()Ljava/lang/Throwable;
    //   332: athrow
    //   333: astore_2
    //   334: aload_2
    //   335: invokevirtual 104	java/lang/reflect/InvocationTargetException:getCause	()Ljava/lang/Throwable;
    //   338: athrow
    //   339: astore_2
    //   340: aload_2
    //   341: invokevirtual 104	java/lang/reflect/InvocationTargetException:getCause	()Ljava/lang/Throwable;
    //   344: athrow
    // Local variable table:
    //   start	length	slot	name	signature
    //   0	345	0	this	ononoo
    //   65	127	1	i	int
    //   35	281	2	localXxsxxs	xxsxxs
    //   321	2	2	localInvocationTargetException1	java.lang.reflect.InvocationTargetException
    //   327	2	2	localInvocationTargetException2	java.lang.reflect.InvocationTargetException
    //   333	2	2	localInvocationTargetException3	java.lang.reflect.InvocationTargetException
    //   339	2	2	localInvocationTargetException4	java.lang.reflect.InvocationTargetException
    //   40	277	3	localContext	Context
    //   113	187	4	localObject	Object
    // Exception table:
    //   from	to	target	type
    //   287	299	321	java/lang/reflect/InvocationTargetException
    //   168	180	327	java/lang/reflect/InvocationTargetException
    //   235	247	333	java/lang/reflect/InvocationTargetException
    //   115	127	339	java/lang/reflect/InvocationTargetException
  }
  
  /* Error */
  public void b006B006B006B006Bk006B006B006B006Bk(String paramString)
  {
    // Byte code:
    //   0: aload_0
    //   1: getfield 194	uuuuuu/ononoo:b006E006E006E006E006En006E006En	Luuuuuu/hyhyhh;
    //   4: invokevirtual 199	uuuuuu/hyhyhh:b0070pp007000700070p007000700070	()Ljava/lang/String;
    //   7: ifnull +158 -> 165
    //   10: aload_0
    //   11: getfield 194	uuuuuu/ononoo:b006E006E006E006E006En006E006En	Luuuuuu/hyhyhh;
    //   14: invokevirtual 297	uuuuuu/hyhyhh:bp00700070007000700070p007000700070	()Ljava/lang/String;
    //   17: astore 4
    //   19: getstatic 61	uuuuuu/ononoo:bn006E006En006Enn006E006E	I
    //   22: getstatic 63	uuuuuu/ononoo:bnnn006E006Enn006E006E	I
    //   25: iadd
    //   26: getstatic 61	uuuuuu/ononoo:bn006E006En006Enn006E006E	I
    //   29: imul
    //   30: getstatic 65	uuuuuu/ononoo:b006Enn006E006Enn006E006E	I
    //   33: irem
    //   34: getstatic 67	uuuuuu/ononoo:b006E006E006En006Enn006E006E	I
    //   37: if_icmpeq +123 -> 160
    //   40: bipush 72
    //   42: putstatic 61	uuuuuu/ononoo:bn006E006En006Enn006E006E	I
    //   45: ldc 2
    //   47: ldc_w 299
    //   50: bipush 100
    //   52: iconst_1
    //   53: invokestatic 75	xxxxxx/uxxxxx:bb00620062bb0062b0062b0062	(Ljava/lang/String;CC)Ljava/lang/String;
    //   56: iconst_0
    //   57: anewarray 77	java/lang/Class
    //   60: invokevirtual 81	java/lang/Class:getMethod	(Ljava/lang/String;[Ljava/lang/Class;)Ljava/lang/reflect/Method;
    //   63: astore 5
    //   65: aload 5
    //   67: aconst_null
    //   68: iconst_0
    //   69: anewarray 83	java/lang/Object
    //   72: invokevirtual 89	java/lang/reflect/Method:invoke	(Ljava/lang/Object;[Ljava/lang/Object;)Ljava/lang/Object;
    //   75: astore 5
    //   77: aload 5
    //   79: checkcast 91	java/lang/Integer
    //   82: invokevirtual 94	java/lang/Integer:intValue	()I
    //   85: istore_2
    //   86: getstatic 61	uuuuuu/ononoo:bn006E006En006Enn006E006E	I
    //   89: getstatic 63	uuuuuu/ononoo:bnnn006E006Enn006E006E	I
    //   92: iadd
    //   93: getstatic 61	uuuuuu/ononoo:bn006E006En006Enn006E006E	I
    //   96: imul
    //   97: getstatic 65	uuuuuu/ononoo:b006Enn006E006Enn006E006E	I
    //   100: irem
    //   101: getstatic 67	uuuuuu/ononoo:b006E006E006En006Enn006E006E	I
    //   104: if_icmpeq +52 -> 156
    //   107: bipush 56
    //   109: putstatic 61	uuuuuu/ononoo:bn006E006En006Enn006E006E	I
    //   112: ldc 2
    //   114: ldc_w 301
    //   117: sipush 176
    //   120: iconst_0
    //   121: invokestatic 75	xxxxxx/uxxxxx:bb00620062bb0062b0062b0062	(Ljava/lang/String;CC)Ljava/lang/String;
    //   124: iconst_0
    //   125: anewarray 77	java/lang/Class
    //   128: invokevirtual 81	java/lang/Class:getMethod	(Ljava/lang/String;[Ljava/lang/Class;)Ljava/lang/reflect/Method;
    //   131: astore 5
    //   133: aload 5
    //   135: aconst_null
    //   136: iconst_0
    //   137: anewarray 83	java/lang/Object
    //   140: invokevirtual 89	java/lang/reflect/Method:invoke	(Ljava/lang/Object;[Ljava/lang/Object;)Ljava/lang/Object;
    //   143: astore 5
    //   145: aload 5
    //   147: checkcast 91	java/lang/Integer
    //   150: invokevirtual 94	java/lang/Integer:intValue	()I
    //   153: putstatic 67	uuuuuu/ononoo:b006E006E006En006Enn006E006E	I
    //   156: iload_2
    //   157: putstatic 67	uuuuuu/ononoo:b006E006E006En006Enn006E006E	I
    //   160: aload 4
    //   162: ifnonnull +46 -> 208
    //   165: ldc 2
    //   167: ldc_w 303
    //   170: bipush 99
    //   172: sipush 249
    //   175: iconst_0
    //   176: invokestatic 115	xxxxxx/uxxxxx:bbbb0062b0062b0062b0062	(Ljava/lang/String;CCC)Ljava/lang/String;
    //   179: iconst_1
    //   180: anewarray 77	java/lang/Class
    //   183: dup
    //   184: iconst_0
    //   185: ldc 121
    //   187: aastore
    //   188: invokevirtual 81	java/lang/Class:getMethod	(Ljava/lang/String;[Ljava/lang/Class;)Ljava/lang/reflect/Method;
    //   191: astore 4
    //   193: aload 4
    //   195: aload_0
    //   196: iconst_1
    //   197: anewarray 83	java/lang/Object
    //   200: dup
    //   201: iconst_0
    //   202: aconst_null
    //   203: aastore
    //   204: invokevirtual 89	java/lang/reflect/Method:invoke	(Ljava/lang/Object;[Ljava/lang/Object;)Ljava/lang/Object;
    //   207: pop
    //   208: aload_0
    //   209: getfield 98	uuuuuu/ononoo:bnnnnn006E006E006En	Luuuuuu/ttssst$tsssst;
    //   212: checkcast 136	uuuuuu/nnnooo$noonoo
    //   215: invokeinterface 306 1 0
    //   220: aload_0
    //   221: getfield 213	uuuuuu/ononoo:b006En006E006E006En006E006En	Luuuuuu/ggyggy;
    //   224: getstatic 219	uuuuuu/gyyygy$yyyygy:bkkk006Bk006Bk006Bk	Luuuuuu/gyyygy$yyyygy;
    //   227: invokevirtual 225	uuuuuu/ggyggy:b0070007000700070pp00700070pp	(Luuuuuu/gyyygy$yyyygy;)Luuuuuu/yyyggy;
    //   230: invokeinterface 231 1 0
    //   235: astore 4
    //   237: aload_0
    //   238: aload 4
    //   240: invokevirtual 309	uuuuuu/ggyygy:bpp0070ppppp0070p	()Ljava/lang/String;
    //   243: putfield 39	uuuuuu/ononoo:b006En006En006Enn006E006E	Ljava/lang/String;
    //   246: aload 4
    //   248: aconst_null
    //   249: invokevirtual 248	uuuuuu/ggyygy:b007000700070ppppp0070p	(Ljava/lang/String;)V
    //   252: aload_0
    //   253: getfield 311	uuuuuu/ononoo:b006E006Enn006Enn006E006E	Luuuuuu/vpppvv;
    //   256: astore 5
    //   258: aload_0
    //   259: getfield 194	uuuuuu/ononoo:b006E006E006E006E006En006E006En	Luuuuuu/hyhyhh;
    //   262: astore 6
    //   264: getstatic 61	uuuuuu/ononoo:bn006E006En006Enn006E006E	I
    //   267: istore_2
    //   268: getstatic 63	uuuuuu/ononoo:bnnn006E006Enn006E006E	I
    //   271: istore_3
    //   272: getstatic 61	uuuuuu/ononoo:bn006E006En006Enn006E006E	I
    //   275: getstatic 63	uuuuuu/ononoo:bnnn006E006Enn006E006E	I
    //   278: iadd
    //   279: getstatic 61	uuuuuu/ononoo:bn006E006En006Enn006E006E	I
    //   282: imul
    //   283: getstatic 65	uuuuuu/ononoo:b006Enn006E006Enn006E006E	I
    //   286: irem
    //   287: getstatic 67	uuuuuu/ononoo:b006E006E006En006Enn006E006E	I
    //   290: if_icmpeq +91 -> 381
    //   293: ldc 2
    //   295: ldc_w 313
    //   298: sipush 219
    //   301: iconst_3
    //   302: invokestatic 75	xxxxxx/uxxxxx:bb00620062bb0062b0062b0062	(Ljava/lang/String;CC)Ljava/lang/String;
    //   305: iconst_0
    //   306: anewarray 77	java/lang/Class
    //   309: invokevirtual 81	java/lang/Class:getMethod	(Ljava/lang/String;[Ljava/lang/Class;)Ljava/lang/reflect/Method;
    //   312: astore 7
    //   314: aload 7
    //   316: aconst_null
    //   317: iconst_0
    //   318: anewarray 83	java/lang/Object
    //   321: invokevirtual 89	java/lang/reflect/Method:invoke	(Ljava/lang/Object;[Ljava/lang/Object;)Ljava/lang/Object;
    //   324: astore 7
    //   326: aload 7
    //   328: checkcast 91	java/lang/Integer
    //   331: invokevirtual 94	java/lang/Integer:intValue	()I
    //   334: putstatic 61	uuuuuu/ononoo:bn006E006En006Enn006E006E	I
    //   337: ldc 2
    //   339: ldc_w 315
    //   342: sipush 156
    //   345: iconst_0
    //   346: invokestatic 75	xxxxxx/uxxxxx:bb00620062bb0062b0062b0062	(Ljava/lang/String;CC)Ljava/lang/String;
    //   349: iconst_0
    //   350: anewarray 77	java/lang/Class
    //   353: invokevirtual 81	java/lang/Class:getMethod	(Ljava/lang/String;[Ljava/lang/Class;)Ljava/lang/reflect/Method;
    //   356: astore 7
    //   358: aload 7
    //   360: aconst_null
    //   361: iconst_0
    //   362: anewarray 83	java/lang/Object
    //   365: invokevirtual 89	java/lang/reflect/Method:invoke	(Ljava/lang/Object;[Ljava/lang/Object;)Ljava/lang/Object;
    //   368: astore 7
    //   370: aload 7
    //   372: checkcast 91	java/lang/Integer
    //   375: invokevirtual 94	java/lang/Integer:intValue	()I
    //   378: putstatic 67	uuuuuu/ononoo:b006E006E006En006Enn006E006E	I
    //   381: getstatic 61	uuuuuu/ononoo:bn006E006En006Enn006E006E	I
    //   384: iload_3
    //   385: iload_2
    //   386: iadd
    //   387: imul
    //   388: getstatic 65	uuuuuu/ononoo:b006Enn006E006Enn006E006E	I
    //   391: irem
    //   392: getstatic 67	uuuuuu/ononoo:b006E006E006En006Enn006E006E	I
    //   395: if_icmpeq +50 -> 445
    //   398: ldc 2
    //   400: ldc 100
    //   402: bipush 16
    //   404: iconst_1
    //   405: invokestatic 75	xxxxxx/uxxxxx:bb00620062bb0062b0062b0062	(Ljava/lang/String;CC)Ljava/lang/String;
    //   408: iconst_0
    //   409: anewarray 77	java/lang/Class
    //   412: invokevirtual 81	java/lang/Class:getMethod	(Ljava/lang/String;[Ljava/lang/Class;)Ljava/lang/reflect/Method;
    //   415: astore 7
    //   417: aload 7
    //   419: aconst_null
    //   420: iconst_0
    //   421: anewarray 83	java/lang/Object
    //   424: invokevirtual 89	java/lang/reflect/Method:invoke	(Ljava/lang/Object;[Ljava/lang/Object;)Ljava/lang/Object;
    //   427: astore 7
    //   429: aload 7
    //   431: checkcast 91	java/lang/Integer
    //   434: invokevirtual 94	java/lang/Integer:intValue	()I
    //   437: putstatic 61	uuuuuu/ononoo:bn006E006En006Enn006E006E	I
    //   440: bipush 47
    //   442: putstatic 67	uuuuuu/ononoo:b006E006E006En006Enn006E006E	I
    //   445: aload 5
    //   447: aload_0
    //   448: aload 6
    //   450: invokevirtual 199	uuuuuu/hyhyhh:b0070pp007000700070p007000700070	()Ljava/lang/String;
    //   453: aload_0
    //   454: getfield 194	uuuuuu/ononoo:b006E006E006E006E006En006E006En	Luuuuuu/hyhyhh;
    //   457: invokevirtual 297	uuuuuu/hyhyhh:bp00700070007000700070p007000700070	()Ljava/lang/String;
    //   460: aload_1
    //   461: iconst_1
    //   462: invokeinterface 321 6 0
    //   467: aload 4
    //   469: aload_0
    //   470: getfield 39	uuuuuu/ononoo:b006En006En006Enn006E006E	Ljava/lang/String;
    //   473: invokevirtual 248	uuuuuu/ggyygy:b007000700070ppppp0070p	(Ljava/lang/String;)V
    //   476: return
    //   477: astore_1
    //   478: aload_1
    //   479: invokevirtual 104	java/lang/reflect/InvocationTargetException:getCause	()Ljava/lang/Throwable;
    //   482: athrow
    //   483: astore_1
    //   484: aload_1
    //   485: invokevirtual 104	java/lang/reflect/InvocationTargetException:getCause	()Ljava/lang/Throwable;
    //   488: athrow
    //   489: astore_1
    //   490: aload_1
    //   491: invokevirtual 104	java/lang/reflect/InvocationTargetException:getCause	()Ljava/lang/Throwable;
    //   494: athrow
    //   495: astore_1
    //   496: aload_1
    //   497: invokevirtual 104	java/lang/reflect/InvocationTargetException:getCause	()Ljava/lang/Throwable;
    //   500: athrow
    //   501: astore_1
    //   502: aload_1
    //   503: invokevirtual 104	java/lang/reflect/InvocationTargetException:getCause	()Ljava/lang/Throwable;
    //   506: athrow
    //   507: astore_1
    //   508: aload_1
    //   509: invokevirtual 104	java/lang/reflect/InvocationTargetException:getCause	()Ljava/lang/Throwable;
    //   512: athrow
    // Local variable table:
    //   start	length	slot	name	signature
    //   0	513	0	this	ononoo
    //   0	513	1	paramString	String
    //   85	302	2	i	int
    //   271	116	3	j	int
    //   17	451	4	localObject1	Object
    //   63	383	5	localObject2	Object
    //   262	187	6	localHyhyhh	hyhyhh
    //   312	118	7	localObject3	Object
    // Exception table:
    //   from	to	target	type
    //   417	429	477	java/lang/reflect/InvocationTargetException
    //   193	208	483	java/lang/reflect/InvocationTargetException
    //   314	326	489	java/lang/reflect/InvocationTargetException
    //   358	370	495	java/lang/reflect/InvocationTargetException
    //   65	77	501	java/lang/reflect/InvocationTargetException
    //   133	145	507	java/lang/reflect/InvocationTargetException
  }
  
  /* Error */
  public void b006B006Bk006B006Bk006B006B006Bk(boolean paramBoolean)
  {
    // Byte code:
    //   0: aload_0
    //   1: getfield 190	uuuuuu/ononoo:bn006Enn006Enn006E006E	Luuuuuu/onoono;
    //   4: invokeinterface 325 1 0
    //   9: ifne +40 -> 49
    //   12: iload_1
    //   13: ifeq +36 -> 49
    //   16: ldc 2
    //   18: ldc_w 327
    //   21: sipush 140
    //   24: iconst_2
    //   25: invokestatic 75	xxxxxx/uxxxxx:bb00620062bb0062b0062b0062	(Ljava/lang/String;CC)Ljava/lang/String;
    //   28: iconst_0
    //   29: anewarray 77	java/lang/Class
    //   32: invokevirtual 81	java/lang/Class:getMethod	(Ljava/lang/String;[Ljava/lang/Class;)Ljava/lang/reflect/Method;
    //   35: astore 5
    //   37: aload 5
    //   39: aload_0
    //   40: iconst_0
    //   41: anewarray 83	java/lang/Object
    //   44: invokevirtual 89	java/lang/reflect/Method:invoke	(Ljava/lang/Object;[Ljava/lang/Object;)Ljava/lang/Object;
    //   47: pop
    //   48: return
    //   49: getstatic 61	uuuuuu/ononoo:bn006E006En006Enn006E006E	I
    //   52: istore_2
    //   53: getstatic 63	uuuuuu/ononoo:bnnn006E006Enn006E006E	I
    //   56: istore_3
    //   57: getstatic 61	uuuuuu/ononoo:bn006E006En006Enn006E006E	I
    //   60: istore 4
    //   62: iload 4
    //   64: getstatic 63	uuuuuu/ononoo:bnnn006E006Enn006E006E	I
    //   67: iload 4
    //   69: iadd
    //   70: imul
    //   71: getstatic 65	uuuuuu/ononoo:b006Enn006E006Enn006E006E	I
    //   74: irem
    //   75: tableswitch	default:+17->92, 0:+68->143
    //   92: bipush 11
    //   94: putstatic 61	uuuuuu/ononoo:bn006E006En006Enn006E006E	I
    //   97: ldc 2
    //   99: ldc_w 329
    //   102: bipush 14
    //   104: sipush 160
    //   107: iconst_2
    //   108: invokestatic 115	xxxxxx/uxxxxx:bbbb0062b0062b0062b0062	(Ljava/lang/String;CCC)Ljava/lang/String;
    //   111: iconst_0
    //   112: anewarray 77	java/lang/Class
    //   115: invokevirtual 81	java/lang/Class:getMethod	(Ljava/lang/String;[Ljava/lang/Class;)Ljava/lang/reflect/Method;
    //   118: astore 5
    //   120: aload 5
    //   122: aconst_null
    //   123: iconst_0
    //   124: anewarray 83	java/lang/Object
    //   127: invokevirtual 89	java/lang/reflect/Method:invoke	(Ljava/lang/Object;[Ljava/lang/Object;)Ljava/lang/Object;
    //   130: astore 5
    //   132: aload 5
    //   134: checkcast 91	java/lang/Integer
    //   137: invokevirtual 94	java/lang/Integer:intValue	()I
    //   140: putstatic 67	uuuuuu/ononoo:b006E006E006En006Enn006E006E	I
    //   143: iload_2
    //   144: iload_3
    //   145: iadd
    //   146: getstatic 61	uuuuuu/ononoo:bn006E006En006Enn006E006E	I
    //   149: imul
    //   150: getstatic 65	uuuuuu/ononoo:b006Enn006E006Enn006E006E	I
    //   153: irem
    //   154: getstatic 67	uuuuuu/ononoo:b006E006E006En006Enn006E006E	I
    //   157: if_icmpeq +12 -> 169
    //   160: bipush 72
    //   162: putstatic 61	uuuuuu/ononoo:bn006E006En006Enn006E006E	I
    //   165: iconst_3
    //   166: putstatic 67	uuuuuu/ononoo:b006E006E006En006Enn006E006E	I
    //   169: aload_0
    //   170: getfield 190	uuuuuu/ononoo:bn006Enn006Enn006E006E	Luuuuuu/onoono;
    //   173: invokeinterface 325 1 0
    //   178: ifeq -130 -> 48
    //   181: ldc 2
    //   183: ldc_w 331
    //   186: sipush 146
    //   189: sipush 164
    //   192: iconst_0
    //   193: invokestatic 115	xxxxxx/uxxxxx:bbbb0062b0062b0062b0062	(Ljava/lang/String;CCC)Ljava/lang/String;
    //   196: iconst_0
    //   197: anewarray 77	java/lang/Class
    //   200: invokevirtual 81	java/lang/Class:getMethod	(Ljava/lang/String;[Ljava/lang/Class;)Ljava/lang/reflect/Method;
    //   203: astore 5
    //   205: aload 5
    //   207: aconst_null
    //   208: iconst_0
    //   209: anewarray 83	java/lang/Object
    //   212: invokevirtual 89	java/lang/reflect/Method:invoke	(Ljava/lang/Object;[Ljava/lang/Object;)Ljava/lang/Object;
    //   215: astore 5
    //   217: aload 5
    //   219: checkcast 91	java/lang/Integer
    //   222: invokevirtual 94	java/lang/Integer:intValue	()I
    //   225: istore_2
    //   226: getstatic 63	uuuuuu/ononoo:bnnn006E006Enn006E006E	I
    //   229: istore_3
    //   230: ldc 2
    //   232: ldc_w 333
    //   235: sipush 168
    //   238: iconst_3
    //   239: invokestatic 75	xxxxxx/uxxxxx:bb00620062bb0062b0062b0062	(Ljava/lang/String;CC)Ljava/lang/String;
    //   242: iconst_0
    //   243: anewarray 77	java/lang/Class
    //   246: invokevirtual 81	java/lang/Class:getMethod	(Ljava/lang/String;[Ljava/lang/Class;)Ljava/lang/reflect/Method;
    //   249: astore 5
    //   251: aload 5
    //   253: aconst_null
    //   254: iconst_0
    //   255: anewarray 83	java/lang/Object
    //   258: invokevirtual 89	java/lang/reflect/Method:invoke	(Ljava/lang/Object;[Ljava/lang/Object;)Ljava/lang/Object;
    //   261: astore 5
    //   263: aload 5
    //   265: checkcast 91	java/lang/Integer
    //   268: invokevirtual 94	java/lang/Integer:intValue	()I
    //   271: iload_3
    //   272: iload_2
    //   273: iadd
    //   274: imul
    //   275: getstatic 65	uuuuuu/ononoo:b006Enn006E006Enn006E006E	I
    //   278: irem
    //   279: getstatic 67	uuuuuu/ononoo:b006E006E006En006Enn006E006E	I
    //   282: if_icmpeq +91 -> 373
    //   285: ldc 2
    //   287: ldc_w 335
    //   290: sipush 230
    //   293: iconst_2
    //   294: invokestatic 75	xxxxxx/uxxxxx:bb00620062bb0062b0062b0062	(Ljava/lang/String;CC)Ljava/lang/String;
    //   297: iconst_0
    //   298: anewarray 77	java/lang/Class
    //   301: invokevirtual 81	java/lang/Class:getMethod	(Ljava/lang/String;[Ljava/lang/Class;)Ljava/lang/reflect/Method;
    //   304: astore 5
    //   306: aload 5
    //   308: aconst_null
    //   309: iconst_0
    //   310: anewarray 83	java/lang/Object
    //   313: invokevirtual 89	java/lang/reflect/Method:invoke	(Ljava/lang/Object;[Ljava/lang/Object;)Ljava/lang/Object;
    //   316: astore 5
    //   318: aload 5
    //   320: checkcast 91	java/lang/Integer
    //   323: invokevirtual 94	java/lang/Integer:intValue	()I
    //   326: putstatic 61	uuuuuu/ononoo:bn006E006En006Enn006E006E	I
    //   329: ldc 2
    //   331: ldc_w 337
    //   334: sipush 170
    //   337: iconst_2
    //   338: invokestatic 75	xxxxxx/uxxxxx:bb00620062bb0062b0062b0062	(Ljava/lang/String;CC)Ljava/lang/String;
    //   341: iconst_0
    //   342: anewarray 77	java/lang/Class
    //   345: invokevirtual 81	java/lang/Class:getMethod	(Ljava/lang/String;[Ljava/lang/Class;)Ljava/lang/reflect/Method;
    //   348: astore 5
    //   350: aload 5
    //   352: aconst_null
    //   353: iconst_0
    //   354: anewarray 83	java/lang/Object
    //   357: invokevirtual 89	java/lang/reflect/Method:invoke	(Ljava/lang/Object;[Ljava/lang/Object;)Ljava/lang/Object;
    //   360: astore 5
    //   362: aload 5
    //   364: checkcast 91	java/lang/Integer
    //   367: invokevirtual 94	java/lang/Integer:intValue	()I
    //   370: putstatic 67	uuuuuu/ononoo:b006E006E006En006Enn006E006E	I
    //   373: iload_1
    //   374: ifne -326 -> 48
    //   377: ldc 2
    //   379: ldc_w 339
    //   382: sipush 198
    //   385: iconst_3
    //   386: invokestatic 75	xxxxxx/uxxxxx:bb00620062bb0062b0062b0062	(Ljava/lang/String;CC)Ljava/lang/String;
    //   389: iconst_0
    //   390: anewarray 77	java/lang/Class
    //   393: invokevirtual 81	java/lang/Class:getMethod	(Ljava/lang/String;[Ljava/lang/Class;)Ljava/lang/reflect/Method;
    //   396: astore 5
    //   398: aload 5
    //   400: aload_0
    //   401: iconst_0
    //   402: anewarray 83	java/lang/Object
    //   405: invokevirtual 89	java/lang/reflect/Method:invoke	(Ljava/lang/Object;[Ljava/lang/Object;)Ljava/lang/Object;
    //   408: pop
    //   409: ldc 2
    //   411: ldc_w 341
    //   414: sipush 183
    //   417: bipush 35
    //   419: iconst_3
    //   420: invokestatic 115	xxxxxx/uxxxxx:bbbb0062b0062b0062b0062	(Ljava/lang/String;CCC)Ljava/lang/String;
    //   423: iconst_0
    //   424: anewarray 77	java/lang/Class
    //   427: invokevirtual 81	java/lang/Class:getMethod	(Ljava/lang/String;[Ljava/lang/Class;)Ljava/lang/reflect/Method;
    //   430: astore 5
    //   432: aload 5
    //   434: aconst_null
    //   435: iconst_0
    //   436: anewarray 83	java/lang/Object
    //   439: invokevirtual 89	java/lang/reflect/Method:invoke	(Ljava/lang/Object;[Ljava/lang/Object;)Ljava/lang/Object;
    //   442: astore 5
    //   444: aload 5
    //   446: checkcast 91	java/lang/Integer
    //   449: invokevirtual 94	java/lang/Integer:intValue	()I
    //   452: istore_2
    //   453: iload_2
    //   454: getstatic 63	uuuuuu/ononoo:bnnn006E006Enn006E006E	I
    //   457: iload_2
    //   458: iadd
    //   459: imul
    //   460: getstatic 65	uuuuuu/ononoo:b006Enn006E006Enn006E006E	I
    //   463: irem
    //   464: tableswitch	default:+20->484, 0:+-416->48
    //   484: ldc 2
    //   486: ldc_w 343
    //   489: sipush 143
    //   492: bipush 105
    //   494: iconst_0
    //   495: invokestatic 115	xxxxxx/uxxxxx:bbbb0062b0062b0062b0062	(Ljava/lang/String;CCC)Ljava/lang/String;
    //   498: iconst_0
    //   499: anewarray 77	java/lang/Class
    //   502: invokevirtual 81	java/lang/Class:getMethod	(Ljava/lang/String;[Ljava/lang/Class;)Ljava/lang/reflect/Method;
    //   505: astore 5
    //   507: aload 5
    //   509: aconst_null
    //   510: iconst_0
    //   511: anewarray 83	java/lang/Object
    //   514: invokevirtual 89	java/lang/reflect/Method:invoke	(Ljava/lang/Object;[Ljava/lang/Object;)Ljava/lang/Object;
    //   517: astore 5
    //   519: aload 5
    //   521: checkcast 91	java/lang/Integer
    //   524: invokevirtual 94	java/lang/Integer:intValue	()I
    //   527: putstatic 61	uuuuuu/ononoo:bn006E006En006Enn006E006E	I
    //   530: ldc 2
    //   532: ldc_w 345
    //   535: bipush 11
    //   537: iconst_0
    //   538: invokestatic 75	xxxxxx/uxxxxx:bb00620062bb0062b0062b0062	(Ljava/lang/String;CC)Ljava/lang/String;
    //   541: iconst_0
    //   542: anewarray 77	java/lang/Class
    //   545: invokevirtual 81	java/lang/Class:getMethod	(Ljava/lang/String;[Ljava/lang/Class;)Ljava/lang/reflect/Method;
    //   548: astore 5
    //   550: aload 5
    //   552: aconst_null
    //   553: iconst_0
    //   554: anewarray 83	java/lang/Object
    //   557: invokevirtual 89	java/lang/reflect/Method:invoke	(Ljava/lang/Object;[Ljava/lang/Object;)Ljava/lang/Object;
    //   560: astore 5
    //   562: aload 5
    //   564: checkcast 91	java/lang/Integer
    //   567: invokevirtual 94	java/lang/Integer:intValue	()I
    //   570: putstatic 67	uuuuuu/ononoo:b006E006E006En006Enn006E006E	I
    //   573: return
    //   574: astore 5
    //   576: aload 5
    //   578: invokevirtual 104	java/lang/reflect/InvocationTargetException:getCause	()Ljava/lang/Throwable;
    //   581: athrow
    //   582: astore 5
    //   584: aload 5
    //   586: invokevirtual 104	java/lang/reflect/InvocationTargetException:getCause	()Ljava/lang/Throwable;
    //   589: athrow
    //   590: astore 5
    //   592: aload 5
    //   594: invokevirtual 104	java/lang/reflect/InvocationTargetException:getCause	()Ljava/lang/Throwable;
    //   597: athrow
    //   598: astore 5
    //   600: aload 5
    //   602: invokevirtual 104	java/lang/reflect/InvocationTargetException:getCause	()Ljava/lang/Throwable;
    //   605: athrow
    //   606: astore 5
    //   608: aload 5
    //   610: invokevirtual 104	java/lang/reflect/InvocationTargetException:getCause	()Ljava/lang/Throwable;
    //   613: athrow
    //   614: astore 5
    //   616: aload 5
    //   618: invokevirtual 104	java/lang/reflect/InvocationTargetException:getCause	()Ljava/lang/Throwable;
    //   621: athrow
    //   622: astore 5
    //   624: aload 5
    //   626: invokevirtual 104	java/lang/reflect/InvocationTargetException:getCause	()Ljava/lang/Throwable;
    //   629: athrow
    //   630: astore 5
    //   632: aload 5
    //   634: invokevirtual 104	java/lang/reflect/InvocationTargetException:getCause	()Ljava/lang/Throwable;
    //   637: athrow
    //   638: astore 5
    //   640: aload 5
    //   642: invokevirtual 104	java/lang/reflect/InvocationTargetException:getCause	()Ljava/lang/Throwable;
    //   645: athrow
    //   646: astore 5
    //   648: aload 5
    //   650: invokevirtual 104	java/lang/reflect/InvocationTargetException:getCause	()Ljava/lang/Throwable;
    //   653: athrow
    // Local variable table:
    //   start	length	slot	name	signature
    //   0	654	0	this	ononoo
    //   0	654	1	paramBoolean	boolean
    //   52	408	2	i	int
    //   56	218	3	j	int
    //   60	11	4	k	int
    //   35	528	5	localObject	Object
    //   574	3	5	localInvocationTargetException1	java.lang.reflect.InvocationTargetException
    //   582	3	5	localInvocationTargetException2	java.lang.reflect.InvocationTargetException
    //   590	3	5	localInvocationTargetException3	java.lang.reflect.InvocationTargetException
    //   598	3	5	localInvocationTargetException4	java.lang.reflect.InvocationTargetException
    //   606	3	5	localInvocationTargetException5	java.lang.reflect.InvocationTargetException
    //   614	3	5	localInvocationTargetException6	java.lang.reflect.InvocationTargetException
    //   622	3	5	localInvocationTargetException7	java.lang.reflect.InvocationTargetException
    //   630	3	5	localInvocationTargetException8	java.lang.reflect.InvocationTargetException
    //   638	3	5	localInvocationTargetException9	java.lang.reflect.InvocationTargetException
    //   646	3	5	localInvocationTargetException10	java.lang.reflect.InvocationTargetException
    // Exception table:
    //   from	to	target	type
    //   507	519	574	java/lang/reflect/InvocationTargetException
    //   550	562	582	java/lang/reflect/InvocationTargetException
    //   205	217	590	java/lang/reflect/InvocationTargetException
    //   251	263	598	java/lang/reflect/InvocationTargetException
    //   37	48	606	java/lang/reflect/InvocationTargetException
    //   398	409	614	java/lang/reflect/InvocationTargetException
    //   432	444	622	java/lang/reflect/InvocationTargetException
    //   350	362	630	java/lang/reflect/InvocationTargetException
    //   306	318	638	java/lang/reflect/InvocationTargetException
    //   120	132	646	java/lang/reflect/InvocationTargetException
  }
  
  /* Error */
  public boolean b006B006Bk006Bk006B006B006B006Bk()
  {
    // Byte code:
    //   0: aload_0
    //   1: getfield 190	uuuuuu/ononoo:bn006Enn006Enn006E006E	Luuuuuu/onoono;
    //   4: invokeinterface 349 1 0
    //   9: ifeq +296 -> 305
    //   12: getstatic 61	uuuuuu/ononoo:bn006E006En006Enn006E006E	I
    //   15: istore_1
    //   16: getstatic 63	uuuuuu/ononoo:bnnn006E006Enn006E006E	I
    //   19: istore_2
    //   20: getstatic 61	uuuuuu/ononoo:bn006E006En006Enn006E006E	I
    //   23: istore_3
    //   24: getstatic 61	uuuuuu/ononoo:bn006E006En006Enn006E006E	I
    //   27: istore 4
    //   29: getstatic 63	uuuuuu/ononoo:bnnn006E006Enn006E006E	I
    //   32: istore 5
    //   34: getstatic 61	uuuuuu/ononoo:bn006E006En006Enn006E006E	I
    //   37: getstatic 63	uuuuuu/ononoo:bnnn006E006Enn006E006E	I
    //   40: iadd
    //   41: getstatic 61	uuuuuu/ononoo:bn006E006En006Enn006E006E	I
    //   44: imul
    //   45: getstatic 65	uuuuuu/ononoo:b006Enn006E006Enn006E006E	I
    //   48: irem
    //   49: getstatic 67	uuuuuu/ononoo:b006E006E006En006Enn006E006E	I
    //   52: if_icmpeq +93 -> 145
    //   55: ldc 2
    //   57: ldc_w 351
    //   60: bipush 110
    //   62: sipush 241
    //   65: iconst_0
    //   66: invokestatic 115	xxxxxx/uxxxxx:bbbb0062b0062b0062b0062	(Ljava/lang/String;CCC)Ljava/lang/String;
    //   69: iconst_0
    //   70: anewarray 77	java/lang/Class
    //   73: invokevirtual 81	java/lang/Class:getMethod	(Ljava/lang/String;[Ljava/lang/Class;)Ljava/lang/reflect/Method;
    //   76: astore 6
    //   78: aload 6
    //   80: aconst_null
    //   81: iconst_0
    //   82: anewarray 83	java/lang/Object
    //   85: invokevirtual 89	java/lang/reflect/Method:invoke	(Ljava/lang/Object;[Ljava/lang/Object;)Ljava/lang/Object;
    //   88: astore 6
    //   90: aload 6
    //   92: checkcast 91	java/lang/Integer
    //   95: invokevirtual 94	java/lang/Integer:intValue	()I
    //   98: putstatic 61	uuuuuu/ononoo:bn006E006En006Enn006E006E	I
    //   101: ldc 2
    //   103: ldc_w 351
    //   106: sipush 224
    //   109: iconst_3
    //   110: invokestatic 75	xxxxxx/uxxxxx:bb00620062bb0062b0062b0062	(Ljava/lang/String;CC)Ljava/lang/String;
    //   113: iconst_0
    //   114: anewarray 77	java/lang/Class
    //   117: invokevirtual 81	java/lang/Class:getMethod	(Ljava/lang/String;[Ljava/lang/Class;)Ljava/lang/reflect/Method;
    //   120: astore 6
    //   122: aload 6
    //   124: aconst_null
    //   125: iconst_0
    //   126: anewarray 83	java/lang/Object
    //   129: invokevirtual 89	java/lang/reflect/Method:invoke	(Ljava/lang/Object;[Ljava/lang/Object;)Ljava/lang/Object;
    //   132: astore 6
    //   134: aload 6
    //   136: checkcast 91	java/lang/Integer
    //   139: invokevirtual 94	java/lang/Integer:intValue	()I
    //   142: putstatic 67	uuuuuu/ononoo:b006E006E006En006Enn006E006E	I
    //   145: iload 5
    //   147: iload 4
    //   149: iadd
    //   150: iload 4
    //   152: imul
    //   153: getstatic 65	uuuuuu/ononoo:b006Enn006E006Enn006E006E	I
    //   156: irem
    //   157: tableswitch	default:+19->176, 0:+74->231
    //   176: getstatic 61	uuuuuu/ononoo:bn006E006En006Enn006E006E	I
    //   179: istore 4
    //   181: iload 4
    //   183: getstatic 63	uuuuuu/ononoo:bnnn006E006Enn006E006E	I
    //   186: iload 4
    //   188: iadd
    //   189: imul
    //   190: getstatic 65	uuuuuu/ononoo:b006Enn006E006Enn006E006E	I
    //   193: irem
    //   194: tableswitch	default:+18->212, 0:+28->222
    //   212: bipush 48
    //   214: putstatic 61	uuuuuu/ononoo:bn006E006En006Enn006E006E	I
    //   217: bipush 6
    //   219: putstatic 67	uuuuuu/ononoo:b006E006E006En006Enn006E006E	I
    //   222: bipush 80
    //   224: putstatic 61	uuuuuu/ononoo:bn006E006En006Enn006E006E	I
    //   227: iconst_1
    //   228: putstatic 67	uuuuuu/ononoo:b006E006E006En006Enn006E006E	I
    //   231: iload_2
    //   232: iload_1
    //   233: iadd
    //   234: iload_3
    //   235: imul
    //   236: getstatic 65	uuuuuu/ononoo:b006Enn006E006Enn006E006E	I
    //   239: irem
    //   240: getstatic 67	uuuuuu/ononoo:b006E006E006En006Enn006E006E	I
    //   243: if_icmpeq +52 -> 295
    //   246: bipush 42
    //   248: putstatic 61	uuuuuu/ononoo:bn006E006En006Enn006E006E	I
    //   251: ldc 2
    //   253: ldc_w 353
    //   256: sipush 194
    //   259: iconst_3
    //   260: invokestatic 75	xxxxxx/uxxxxx:bb00620062bb0062b0062b0062	(Ljava/lang/String;CC)Ljava/lang/String;
    //   263: iconst_0
    //   264: anewarray 77	java/lang/Class
    //   267: invokevirtual 81	java/lang/Class:getMethod	(Ljava/lang/String;[Ljava/lang/Class;)Ljava/lang/reflect/Method;
    //   270: astore 6
    //   272: aload 6
    //   274: aconst_null
    //   275: iconst_0
    //   276: anewarray 83	java/lang/Object
    //   279: invokevirtual 89	java/lang/reflect/Method:invoke	(Ljava/lang/Object;[Ljava/lang/Object;)Ljava/lang/Object;
    //   282: astore 6
    //   284: aload 6
    //   286: checkcast 91	java/lang/Integer
    //   289: invokevirtual 94	java/lang/Integer:intValue	()I
    //   292: putstatic 67	uuuuuu/ononoo:b006E006E006En006Enn006E006E	I
    //   295: aload_0
    //   296: getfield 190	uuuuuu/ononoo:bn006Enn006Enn006E006E	Luuuuuu/onoono;
    //   299: invokeinterface 325 1 0
    //   304: ireturn
    //   305: aload_0
    //   306: getfield 190	uuuuuu/ononoo:bn006Enn006Enn006E006E	Luuuuuu/onoono;
    //   309: invokeinterface 356 1 0
    //   314: iconst_0
    //   315: ireturn
    //   316: astore 6
    //   318: aload 6
    //   320: invokevirtual 104	java/lang/reflect/InvocationTargetException:getCause	()Ljava/lang/Throwable;
    //   323: athrow
    //   324: astore 6
    //   326: aload 6
    //   328: invokevirtual 104	java/lang/reflect/InvocationTargetException:getCause	()Ljava/lang/Throwable;
    //   331: athrow
    //   332: astore 6
    //   334: aload 6
    //   336: invokevirtual 104	java/lang/reflect/InvocationTargetException:getCause	()Ljava/lang/Throwable;
    //   339: athrow
    // Local variable table:
    //   start	length	slot	name	signature
    //   0	340	0	this	ononoo
    //   15	219	1	i	int
    //   19	215	2	j	int
    //   23	213	3	k	int
    //   27	163	4	m	int
    //   32	118	5	n	int
    //   76	209	6	localObject	Object
    //   316	3	6	localInvocationTargetException1	java.lang.reflect.InvocationTargetException
    //   324	3	6	localInvocationTargetException2	java.lang.reflect.InvocationTargetException
    //   332	3	6	localInvocationTargetException3	java.lang.reflect.InvocationTargetException
    // Exception table:
    //   from	to	target	type
    //   272	284	316	java/lang/reflect/InvocationTargetException
    //   78	90	324	java/lang/reflect/InvocationTargetException
    //   122	134	332	java/lang/reflect/InvocationTargetException
  }
  
  /* Error */
  public void b006Bk006B006B006Bk006B006B006Bk(String paramString)
  {
    // Byte code:
    //   0: aload_0
    //   1: invokevirtual 171	uuuuuu/ononoo:bkk006Bk006Bk006Bk006Bk	()Z
    //   4: istore 4
    //   6: getstatic 61	uuuuuu/ononoo:bn006E006En006Enn006E006E	I
    //   9: istore_2
    //   10: iload_2
    //   11: getstatic 63	uuuuuu/ononoo:bnnn006E006Enn006E006E	I
    //   14: iload_2
    //   15: iadd
    //   16: imul
    //   17: getstatic 65	uuuuuu/ononoo:b006Enn006E006Enn006E006E	I
    //   20: irem
    //   21: tableswitch	default:+19->40, 0:+302->323
    //   40: ldc 2
    //   42: ldc_w 359
    //   45: sipush 215
    //   48: iconst_5
    //   49: invokestatic 75	xxxxxx/uxxxxx:bb00620062bb0062b0062b0062	(Ljava/lang/String;CC)Ljava/lang/String;
    //   52: iconst_0
    //   53: anewarray 77	java/lang/Class
    //   56: invokevirtual 81	java/lang/Class:getMethod	(Ljava/lang/String;[Ljava/lang/Class;)Ljava/lang/reflect/Method;
    //   59: astore 5
    //   61: aload 5
    //   63: aconst_null
    //   64: iconst_0
    //   65: anewarray 83	java/lang/Object
    //   68: invokevirtual 89	java/lang/reflect/Method:invoke	(Ljava/lang/Object;[Ljava/lang/Object;)Ljava/lang/Object;
    //   71: astore 5
    //   73: aload 5
    //   75: checkcast 91	java/lang/Integer
    //   78: invokevirtual 94	java/lang/Integer:intValue	()I
    //   81: putstatic 61	uuuuuu/ononoo:bn006E006En006Enn006E006E	I
    //   84: getstatic 61	uuuuuu/ononoo:bn006E006En006Enn006E006E	I
    //   87: istore_2
    //   88: getstatic 63	uuuuuu/ononoo:bnnn006E006Enn006E006E	I
    //   91: istore_3
    //   92: getstatic 61	uuuuuu/ononoo:bn006E006En006Enn006E006E	I
    //   95: getstatic 63	uuuuuu/ononoo:bnnn006E006Enn006E006E	I
    //   98: iadd
    //   99: getstatic 61	uuuuuu/ononoo:bn006E006En006Enn006E006E	I
    //   102: imul
    //   103: getstatic 65	uuuuuu/ononoo:b006Enn006E006Enn006E006E	I
    //   106: irem
    //   107: getstatic 67	uuuuuu/ononoo:b006E006E006En006Enn006E006E	I
    //   110: if_icmpeq +90 -> 200
    //   113: ldc 2
    //   115: ldc_w 266
    //   118: bipush 109
    //   120: iconst_2
    //   121: invokestatic 75	xxxxxx/uxxxxx:bb00620062bb0062b0062b0062	(Ljava/lang/String;CC)Ljava/lang/String;
    //   124: iconst_0
    //   125: anewarray 77	java/lang/Class
    //   128: invokevirtual 81	java/lang/Class:getMethod	(Ljava/lang/String;[Ljava/lang/Class;)Ljava/lang/reflect/Method;
    //   131: astore 5
    //   133: aload 5
    //   135: aconst_null
    //   136: iconst_0
    //   137: anewarray 83	java/lang/Object
    //   140: invokevirtual 89	java/lang/reflect/Method:invoke	(Ljava/lang/Object;[Ljava/lang/Object;)Ljava/lang/Object;
    //   143: astore 5
    //   145: aload 5
    //   147: checkcast 91	java/lang/Integer
    //   150: invokevirtual 94	java/lang/Integer:intValue	()I
    //   153: putstatic 61	uuuuuu/ononoo:bn006E006En006Enn006E006E	I
    //   156: ldc 2
    //   158: ldc_w 361
    //   161: sipush 156
    //   164: iconst_5
    //   165: invokestatic 75	xxxxxx/uxxxxx:bb00620062bb0062b0062b0062	(Ljava/lang/String;CC)Ljava/lang/String;
    //   168: iconst_0
    //   169: anewarray 77	java/lang/Class
    //   172: invokevirtual 81	java/lang/Class:getMethod	(Ljava/lang/String;[Ljava/lang/Class;)Ljava/lang/reflect/Method;
    //   175: astore 5
    //   177: aload 5
    //   179: aconst_null
    //   180: iconst_0
    //   181: anewarray 83	java/lang/Object
    //   184: invokevirtual 89	java/lang/reflect/Method:invoke	(Ljava/lang/Object;[Ljava/lang/Object;)Ljava/lang/Object;
    //   187: astore 5
    //   189: aload 5
    //   191: checkcast 91	java/lang/Integer
    //   194: invokevirtual 94	java/lang/Integer:intValue	()I
    //   197: putstatic 67	uuuuuu/ononoo:b006E006E006En006Enn006E006E	I
    //   200: iload_2
    //   201: iload_3
    //   202: iadd
    //   203: iload_2
    //   204: imul
    //   205: getstatic 65	uuuuuu/ononoo:b006Enn006E006Enn006E006E	I
    //   208: irem
    //   209: tableswitch	default:+19->228, 0:+67->276
    //   228: ldc 2
    //   230: ldc_w 363
    //   233: bipush 75
    //   235: iconst_2
    //   236: invokestatic 75	xxxxxx/uxxxxx:bb00620062bb0062b0062b0062	(Ljava/lang/String;CC)Ljava/lang/String;
    //   239: iconst_0
    //   240: anewarray 77	java/lang/Class
    //   243: invokevirtual 81	java/lang/Class:getMethod	(Ljava/lang/String;[Ljava/lang/Class;)Ljava/lang/reflect/Method;
    //   246: astore 5
    //   248: aload 5
    //   250: aconst_null
    //   251: iconst_0
    //   252: anewarray 83	java/lang/Object
    //   255: invokevirtual 89	java/lang/reflect/Method:invoke	(Ljava/lang/Object;[Ljava/lang/Object;)Ljava/lang/Object;
    //   258: astore 5
    //   260: aload 5
    //   262: checkcast 91	java/lang/Integer
    //   265: invokevirtual 94	java/lang/Integer:intValue	()I
    //   268: putstatic 61	uuuuuu/ononoo:bn006E006En006Enn006E006E	I
    //   271: bipush 49
    //   273: putstatic 67	uuuuuu/ononoo:b006E006E006En006Enn006E006E	I
    //   276: getstatic 61	uuuuuu/ononoo:bn006E006En006Enn006E006E	I
    //   279: istore_2
    //   280: iload_2
    //   281: getstatic 63	uuuuuu/ononoo:bnnn006E006Enn006E006E	I
    //   284: iload_2
    //   285: iadd
    //   286: imul
    //   287: getstatic 65	uuuuuu/ononoo:b006Enn006E006Enn006E006E	I
    //   290: irem
    //   291: tableswitch	default:+17->308, 0:+27->318
    //   308: bipush 78
    //   310: putstatic 61	uuuuuu/ononoo:bn006E006En006Enn006E006E	I
    //   313: bipush 19
    //   315: putstatic 67	uuuuuu/ononoo:b006E006E006En006Enn006E006E	I
    //   318: bipush 29
    //   320: putstatic 67	uuuuuu/ononoo:b006E006E006En006Enn006E006E	I
    //   323: iload 4
    //   325: ifne +16 -> 341
    //   328: return
    //   329: astore_1
    //   330: aload_1
    //   331: invokevirtual 104	java/lang/reflect/InvocationTargetException:getCause	()Ljava/lang/Throwable;
    //   334: athrow
    //   335: astore_1
    //   336: aload_1
    //   337: invokevirtual 104	java/lang/reflect/InvocationTargetException:getCause	()Ljava/lang/Throwable;
    //   340: athrow
    //   341: ldc 2
    //   343: ldc_w 365
    //   346: sipush 195
    //   349: bipush 16
    //   351: iconst_2
    //   352: invokestatic 115	xxxxxx/uxxxxx:bbbb0062b0062b0062b0062	(Ljava/lang/String;CCC)Ljava/lang/String;
    //   355: iconst_1
    //   356: anewarray 77	java/lang/Class
    //   359: dup
    //   360: iconst_0
    //   361: ldc_w 367
    //   364: aastore
    //   365: invokevirtual 81	java/lang/Class:getMethod	(Ljava/lang/String;[Ljava/lang/Class;)Ljava/lang/reflect/Method;
    //   368: astore 5
    //   370: aload 5
    //   372: aload_0
    //   373: iconst_1
    //   374: anewarray 83	java/lang/Object
    //   377: dup
    //   378: iconst_0
    //   379: aload_1
    //   380: aastore
    //   381: invokevirtual 89	java/lang/reflect/Method:invoke	(Ljava/lang/Object;[Ljava/lang/Object;)Ljava/lang/Object;
    //   384: pop
    //   385: return
    //   386: astore_1
    //   387: aload_1
    //   388: invokevirtual 104	java/lang/reflect/InvocationTargetException:getCause	()Ljava/lang/Throwable;
    //   391: athrow
    //   392: astore_1
    //   393: aload_1
    //   394: invokevirtual 104	java/lang/reflect/InvocationTargetException:getCause	()Ljava/lang/Throwable;
    //   397: athrow
    //   398: astore_1
    //   399: aload_1
    //   400: invokevirtual 104	java/lang/reflect/InvocationTargetException:getCause	()Ljava/lang/Throwable;
    //   403: athrow
    // Local variable table:
    //   start	length	slot	name	signature
    //   0	404	0	this	ononoo
    //   0	404	1	paramString	String
    //   9	278	2	i	int
    //   91	112	3	j	int
    //   4	320	4	bool	boolean
    //   59	312	5	localObject	Object
    // Exception table:
    //   from	to	target	type
    //   61	73	329	java/lang/reflect/InvocationTargetException
    //   248	260	335	java/lang/reflect/InvocationTargetException
    //   370	385	386	java/lang/reflect/InvocationTargetException
    //   133	145	392	java/lang/reflect/InvocationTargetException
    //   177	189	398	java/lang/reflect/InvocationTargetException
  }
  
  /* Error */
  public void b006Bk006B006Bk006B006B006B006Bk()
  {
    // Byte code:
    //   0: getstatic 61	uuuuuu/ononoo:bn006E006En006Enn006E006E	I
    //   3: getstatic 63	uuuuuu/ononoo:bnnn006E006Enn006E006E	I
    //   6: iadd
    //   7: getstatic 61	uuuuuu/ononoo:bn006E006En006Enn006E006E	I
    //   10: imul
    //   11: getstatic 65	uuuuuu/ononoo:b006Enn006E006Enn006E006E	I
    //   14: irem
    //   15: getstatic 67	uuuuuu/ononoo:b006E006E006En006Enn006E006E	I
    //   18: if_icmpeq +13 -> 31
    //   21: bipush 45
    //   23: putstatic 61	uuuuuu/ononoo:bn006E006En006Enn006E006E	I
    //   26: bipush 27
    //   28: putstatic 67	uuuuuu/ononoo:b006E006E006En006Enn006E006E	I
    //   31: getstatic 61	uuuuuu/ononoo:bn006E006En006Enn006E006E	I
    //   34: istore_1
    //   35: getstatic 63	uuuuuu/ononoo:bnnn006E006Enn006E006E	I
    //   38: istore_2
    //   39: getstatic 61	uuuuuu/ononoo:bn006E006En006Enn006E006E	I
    //   42: istore_3
    //   43: ldc 2
    //   45: ldc_w 370
    //   48: sipush 209
    //   51: sipush 230
    //   54: iconst_3
    //   55: invokestatic 115	xxxxxx/uxxxxx:bbbb0062b0062b0062b0062	(Ljava/lang/String;CCC)Ljava/lang/String;
    //   58: iconst_0
    //   59: anewarray 77	java/lang/Class
    //   62: invokevirtual 81	java/lang/Class:getMethod	(Ljava/lang/String;[Ljava/lang/Class;)Ljava/lang/reflect/Method;
    //   65: astore 5
    //   67: aload 5
    //   69: aconst_null
    //   70: iconst_0
    //   71: anewarray 83	java/lang/Object
    //   74: invokevirtual 89	java/lang/reflect/Method:invoke	(Ljava/lang/Object;[Ljava/lang/Object;)Ljava/lang/Object;
    //   77: astore 5
    //   79: iload_3
    //   80: iload_1
    //   81: iload_2
    //   82: iadd
    //   83: imul
    //   84: aload 5
    //   86: checkcast 91	java/lang/Integer
    //   89: invokevirtual 94	java/lang/Integer:intValue	()I
    //   92: irem
    //   93: getstatic 67	uuuuuu/ononoo:b006E006E006En006Enn006E006E	I
    //   96: if_icmpeq +91 -> 187
    //   99: ldc 2
    //   101: ldc_w 372
    //   104: sipush 242
    //   107: iconst_4
    //   108: invokestatic 75	xxxxxx/uxxxxx:bb00620062bb0062b0062b0062	(Ljava/lang/String;CC)Ljava/lang/String;
    //   111: iconst_0
    //   112: anewarray 77	java/lang/Class
    //   115: invokevirtual 81	java/lang/Class:getMethod	(Ljava/lang/String;[Ljava/lang/Class;)Ljava/lang/reflect/Method;
    //   118: astore 5
    //   120: aload 5
    //   122: aconst_null
    //   123: iconst_0
    //   124: anewarray 83	java/lang/Object
    //   127: invokevirtual 89	java/lang/reflect/Method:invoke	(Ljava/lang/Object;[Ljava/lang/Object;)Ljava/lang/Object;
    //   130: astore 5
    //   132: aload 5
    //   134: checkcast 91	java/lang/Integer
    //   137: invokevirtual 94	java/lang/Integer:intValue	()I
    //   140: putstatic 61	uuuuuu/ononoo:bn006E006En006Enn006E006E	I
    //   143: ldc 2
    //   145: ldc_w 374
    //   148: sipush 246
    //   151: iconst_2
    //   152: invokestatic 75	xxxxxx/uxxxxx:bb00620062bb0062b0062b0062	(Ljava/lang/String;CC)Ljava/lang/String;
    //   155: iconst_0
    //   156: anewarray 77	java/lang/Class
    //   159: invokevirtual 81	java/lang/Class:getMethod	(Ljava/lang/String;[Ljava/lang/Class;)Ljava/lang/reflect/Method;
    //   162: astore 5
    //   164: aload 5
    //   166: aconst_null
    //   167: iconst_0
    //   168: anewarray 83	java/lang/Object
    //   171: invokevirtual 89	java/lang/reflect/Method:invoke	(Ljava/lang/Object;[Ljava/lang/Object;)Ljava/lang/Object;
    //   174: astore 5
    //   176: aload 5
    //   178: checkcast 91	java/lang/Integer
    //   181: invokevirtual 94	java/lang/Integer:intValue	()I
    //   184: putstatic 67	uuuuuu/ononoo:b006E006E006En006Enn006E006E	I
    //   187: aload_0
    //   188: invokevirtual 171	uuuuuu/ononoo:bkk006Bk006Bk006Bk006Bk	()Z
    //   191: ifne +208 -> 399
    //   194: return
    //   195: getstatic 379	com/db/pwcc/dbmobile/foundation/R$string:settings_label_inactive	I
    //   198: istore_1
    //   199: aload_0
    //   200: getfield 98	uuuuuu/ononoo:bnnnnn006E006E006En	Luuuuuu/ttssst$tsssst;
    //   203: astore 5
    //   205: getstatic 61	uuuuuu/ononoo:bn006E006En006Enn006E006E	I
    //   208: istore_2
    //   209: ldc 2
    //   211: ldc_w 381
    //   214: sipush 229
    //   217: iconst_4
    //   218: invokestatic 75	xxxxxx/uxxxxx:bb00620062bb0062b0062b0062	(Ljava/lang/String;CC)Ljava/lang/String;
    //   221: iconst_0
    //   222: anewarray 77	java/lang/Class
    //   225: invokevirtual 81	java/lang/Class:getMethod	(Ljava/lang/String;[Ljava/lang/Class;)Ljava/lang/reflect/Method;
    //   228: astore 6
    //   230: aload 6
    //   232: aconst_null
    //   233: iconst_0
    //   234: anewarray 83	java/lang/Object
    //   237: invokevirtual 89	java/lang/reflect/Method:invoke	(Ljava/lang/Object;[Ljava/lang/Object;)Ljava/lang/Object;
    //   240: astore 6
    //   242: aload 6
    //   244: checkcast 91	java/lang/Integer
    //   247: invokevirtual 94	java/lang/Integer:intValue	()I
    //   250: iload_2
    //   251: iadd
    //   252: iload_2
    //   253: imul
    //   254: getstatic 65	uuuuuu/ononoo:b006Enn006E006Enn006E006E	I
    //   257: irem
    //   258: tableswitch	default:+18->276, 0:+111->369
    //   276: ldc 2
    //   278: ldc_w 383
    //   281: sipush 255
    //   284: sipush 150
    //   287: iconst_1
    //   288: invokestatic 115	xxxxxx/uxxxxx:bbbb0062b0062b0062b0062	(Ljava/lang/String;CCC)Ljava/lang/String;
    //   291: iconst_0
    //   292: anewarray 77	java/lang/Class
    //   295: invokevirtual 81	java/lang/Class:getMethod	(Ljava/lang/String;[Ljava/lang/Class;)Ljava/lang/reflect/Method;
    //   298: astore 6
    //   300: aload 6
    //   302: aconst_null
    //   303: iconst_0
    //   304: anewarray 83	java/lang/Object
    //   307: invokevirtual 89	java/lang/reflect/Method:invoke	(Ljava/lang/Object;[Ljava/lang/Object;)Ljava/lang/Object;
    //   310: astore 6
    //   312: aload 6
    //   314: checkcast 91	java/lang/Integer
    //   317: invokevirtual 94	java/lang/Integer:intValue	()I
    //   320: putstatic 61	uuuuuu/ononoo:bn006E006En006Enn006E006E	I
    //   323: ldc 2
    //   325: ldc_w 385
    //   328: bipush 37
    //   330: sipush 153
    //   333: iconst_0
    //   334: invokestatic 115	xxxxxx/uxxxxx:bbbb0062b0062b0062b0062	(Ljava/lang/String;CCC)Ljava/lang/String;
    //   337: iconst_0
    //   338: anewarray 77	java/lang/Class
    //   341: invokevirtual 81	java/lang/Class:getMethod	(Ljava/lang/String;[Ljava/lang/Class;)Ljava/lang/reflect/Method;
    //   344: astore 6
    //   346: aload 6
    //   348: aconst_null
    //   349: iconst_0
    //   350: anewarray 83	java/lang/Object
    //   353: invokevirtual 89	java/lang/reflect/Method:invoke	(Ljava/lang/Object;[Ljava/lang/Object;)Ljava/lang/Object;
    //   356: astore 6
    //   358: aload 6
    //   360: checkcast 91	java/lang/Integer
    //   363: invokevirtual 94	java/lang/Integer:intValue	()I
    //   366: putstatic 67	uuuuuu/ononoo:b006E006E006En006Enn006E006E	I
    //   369: aload 5
    //   371: checkcast 136	uuuuuu/nnnooo$noonoo
    //   374: iload 4
    //   376: iload_1
    //   377: invokeinterface 389 3 0
    //   382: return
    //   383: astore 5
    //   385: aload 5
    //   387: invokevirtual 104	java/lang/reflect/InvocationTargetException:getCause	()Ljava/lang/Throwable;
    //   390: athrow
    //   391: astore 5
    //   393: aload 5
    //   395: invokevirtual 104	java/lang/reflect/InvocationTargetException:getCause	()Ljava/lang/Throwable;
    //   398: athrow
    //   399: ldc 2
    //   401: ldc_w 391
    //   404: sipush 168
    //   407: iconst_0
    //   408: invokestatic 75	xxxxxx/uxxxxx:bb00620062bb0062b0062b0062	(Ljava/lang/String;CC)Ljava/lang/String;
    //   411: iconst_0
    //   412: anewarray 77	java/lang/Class
    //   415: invokevirtual 81	java/lang/Class:getMethod	(Ljava/lang/String;[Ljava/lang/Class;)Ljava/lang/reflect/Method;
    //   418: astore 5
    //   420: aload 5
    //   422: aload_0
    //   423: iconst_0
    //   424: anewarray 83	java/lang/Object
    //   427: invokevirtual 89	java/lang/reflect/Method:invoke	(Ljava/lang/Object;[Ljava/lang/Object;)Ljava/lang/Object;
    //   430: astore 5
    //   432: aload 5
    //   434: checkcast 393	java/lang/Boolean
    //   437: invokevirtual 396	java/lang/Boolean:booleanValue	()Z
    //   440: istore 4
    //   442: ldc 2
    //   444: ldc_w 398
    //   447: sipush 212
    //   450: sipush 187
    //   453: iconst_3
    //   454: invokestatic 115	xxxxxx/uxxxxx:bbbb0062b0062b0062b0062	(Ljava/lang/String;CCC)Ljava/lang/String;
    //   457: iconst_0
    //   458: anewarray 77	java/lang/Class
    //   461: invokevirtual 81	java/lang/Class:getMethod	(Ljava/lang/String;[Ljava/lang/Class;)Ljava/lang/reflect/Method;
    //   464: astore 5
    //   466: aload 5
    //   468: aconst_null
    //   469: iconst_0
    //   470: anewarray 83	java/lang/Object
    //   473: invokevirtual 89	java/lang/reflect/Method:invoke	(Ljava/lang/Object;[Ljava/lang/Object;)Ljava/lang/Object;
    //   476: astore 5
    //   478: aload 5
    //   480: checkcast 91	java/lang/Integer
    //   483: invokevirtual 94	java/lang/Integer:intValue	()I
    //   486: istore_1
    //   487: getstatic 63	uuuuuu/ononoo:bnnn006E006Enn006E006E	I
    //   490: istore_2
    //   491: ldc 2
    //   493: ldc_w 400
    //   496: sipush 139
    //   499: iconst_4
    //   500: invokestatic 75	xxxxxx/uxxxxx:bb00620062bb0062b0062b0062	(Ljava/lang/String;CC)Ljava/lang/String;
    //   503: iconst_0
    //   504: anewarray 77	java/lang/Class
    //   507: invokevirtual 81	java/lang/Class:getMethod	(Ljava/lang/String;[Ljava/lang/Class;)Ljava/lang/reflect/Method;
    //   510: astore 5
    //   512: aload 5
    //   514: aconst_null
    //   515: iconst_0
    //   516: anewarray 83	java/lang/Object
    //   519: invokevirtual 89	java/lang/reflect/Method:invoke	(Ljava/lang/Object;[Ljava/lang/Object;)Ljava/lang/Object;
    //   522: astore 5
    //   524: aload 5
    //   526: checkcast 91	java/lang/Integer
    //   529: invokevirtual 94	java/lang/Integer:intValue	()I
    //   532: iload_2
    //   533: iload_1
    //   534: iadd
    //   535: imul
    //   536: getstatic 65	uuuuuu/ononoo:b006Enn006E006Enn006E006E	I
    //   539: irem
    //   540: getstatic 67	uuuuuu/ononoo:b006E006E006En006Enn006E006E	I
    //   543: if_icmpeq +51 -> 594
    //   546: bipush 75
    //   548: putstatic 61	uuuuuu/ononoo:bn006E006En006Enn006E006E	I
    //   551: ldc 2
    //   553: ldc_w 345
    //   556: bipush 11
    //   558: iconst_0
    //   559: invokestatic 75	xxxxxx/uxxxxx:bb00620062bb0062b0062b0062	(Ljava/lang/String;CC)Ljava/lang/String;
    //   562: iconst_0
    //   563: anewarray 77	java/lang/Class
    //   566: invokevirtual 81	java/lang/Class:getMethod	(Ljava/lang/String;[Ljava/lang/Class;)Ljava/lang/reflect/Method;
    //   569: astore 5
    //   571: aload 5
    //   573: aconst_null
    //   574: iconst_0
    //   575: anewarray 83	java/lang/Object
    //   578: invokevirtual 89	java/lang/reflect/Method:invoke	(Ljava/lang/Object;[Ljava/lang/Object;)Ljava/lang/Object;
    //   581: astore 5
    //   583: aload 5
    //   585: checkcast 91	java/lang/Integer
    //   588: invokevirtual 94	java/lang/Integer:intValue	()I
    //   591: putstatic 67	uuuuuu/ononoo:b006E006E006En006Enn006E006E	I
    //   594: iload 4
    //   596: ifeq -402 -> 194
    //   599: ldc 2
    //   601: ldc_w 402
    //   604: sipush 143
    //   607: iconst_2
    //   608: invokestatic 75	xxxxxx/uxxxxx:bb00620062bb0062b0062b0062	(Ljava/lang/String;CC)Ljava/lang/String;
    //   611: iconst_0
    //   612: anewarray 77	java/lang/Class
    //   615: invokevirtual 81	java/lang/Class:getMethod	(Ljava/lang/String;[Ljava/lang/Class;)Ljava/lang/reflect/Method;
    //   618: astore 5
    //   620: aload 5
    //   622: aload_0
    //   623: iconst_0
    //   624: anewarray 83	java/lang/Object
    //   627: invokevirtual 89	java/lang/reflect/Method:invoke	(Ljava/lang/Object;[Ljava/lang/Object;)Ljava/lang/Object;
    //   630: astore 5
    //   632: aload 5
    //   634: checkcast 393	java/lang/Boolean
    //   637: invokevirtual 396	java/lang/Boolean:booleanValue	()Z
    //   640: istore 4
    //   642: iload 4
    //   644: ifeq -449 -> 195
    //   647: getstatic 405	com/db/pwcc/dbmobile/foundation/R$string:settings_label_active	I
    //   650: istore_1
    //   651: goto -452 -> 199
    //   654: astore 5
    //   656: aload 5
    //   658: invokevirtual 104	java/lang/reflect/InvocationTargetException:getCause	()Ljava/lang/Throwable;
    //   661: athrow
    //   662: astore 5
    //   664: aload 5
    //   666: invokevirtual 104	java/lang/reflect/InvocationTargetException:getCause	()Ljava/lang/Throwable;
    //   669: athrow
    //   670: astore 5
    //   672: aload 5
    //   674: invokevirtual 104	java/lang/reflect/InvocationTargetException:getCause	()Ljava/lang/Throwable;
    //   677: athrow
    //   678: astore 5
    //   680: aload 5
    //   682: invokevirtual 104	java/lang/reflect/InvocationTargetException:getCause	()Ljava/lang/Throwable;
    //   685: athrow
    //   686: astore 5
    //   688: aload 5
    //   690: invokevirtual 104	java/lang/reflect/InvocationTargetException:getCause	()Ljava/lang/Throwable;
    //   693: athrow
    //   694: astore 5
    //   696: aload 5
    //   698: invokevirtual 104	java/lang/reflect/InvocationTargetException:getCause	()Ljava/lang/Throwable;
    //   701: athrow
    //   702: astore 5
    //   704: aload 5
    //   706: invokevirtual 104	java/lang/reflect/InvocationTargetException:getCause	()Ljava/lang/Throwable;
    //   709: athrow
    //   710: astore 5
    //   712: aload 5
    //   714: invokevirtual 104	java/lang/reflect/InvocationTargetException:getCause	()Ljava/lang/Throwable;
    //   717: athrow
    //   718: astore 5
    //   720: aload 5
    //   722: invokevirtual 104	java/lang/reflect/InvocationTargetException:getCause	()Ljava/lang/Throwable;
    //   725: athrow
    // Local variable table:
    //   start	length	slot	name	signature
    //   0	726	0	this	ononoo
    //   34	617	1	i	int
    //   38	497	2	j	int
    //   42	42	3	k	int
    //   374	269	4	bool	boolean
    //   65	305	5	localObject1	Object
    //   383	3	5	localInvocationTargetException1	java.lang.reflect.InvocationTargetException
    //   391	3	5	localInvocationTargetException2	java.lang.reflect.InvocationTargetException
    //   418	215	5	localObject2	Object
    //   654	3	5	localInvocationTargetException3	java.lang.reflect.InvocationTargetException
    //   662	3	5	localInvocationTargetException4	java.lang.reflect.InvocationTargetException
    //   670	3	5	localInvocationTargetException5	java.lang.reflect.InvocationTargetException
    //   678	3	5	localInvocationTargetException6	java.lang.reflect.InvocationTargetException
    //   686	3	5	localInvocationTargetException7	java.lang.reflect.InvocationTargetException
    //   694	3	5	localInvocationTargetException8	java.lang.reflect.InvocationTargetException
    //   702	3	5	localInvocationTargetException9	java.lang.reflect.InvocationTargetException
    //   710	3	5	localInvocationTargetException10	java.lang.reflect.InvocationTargetException
    //   718	3	5	localInvocationTargetException11	java.lang.reflect.InvocationTargetException
    //   228	131	6	localObject3	Object
    // Exception table:
    //   from	to	target	type
    //   230	242	383	java/lang/reflect/InvocationTargetException
    //   67	79	391	java/lang/reflect/InvocationTargetException
    //   420	432	654	java/lang/reflect/InvocationTargetException
    //   466	478	662	java/lang/reflect/InvocationTargetException
    //   512	524	670	java/lang/reflect/InvocationTargetException
    //   300	312	678	java/lang/reflect/InvocationTargetException
    //   120	132	686	java/lang/reflect/InvocationTargetException
    //   620	632	694	java/lang/reflect/InvocationTargetException
    //   346	358	702	java/lang/reflect/InvocationTargetException
    //   164	176	710	java/lang/reflect/InvocationTargetException
    //   571	583	718	java/lang/reflect/InvocationTargetException
  }
  
  /* Error */
  public void b006Bk006Bkk006B006B006B006Bk(nnnooo.noonoo paramNoonoo)
  {
    // Byte code:
    //   0: aload_0
    //   1: aload_1
    //   2: invokespecial 411	uuuuuu/ssssst:ba0061a0061a0061a0061aa	(Luuuuuu/ttssst$tsssst;)V
    //   5: getstatic 61	uuuuuu/ononoo:bn006E006En006Enn006E006E	I
    //   8: istore_2
    //   9: ldc 2
    //   11: ldc_w 413
    //   14: sipush 161
    //   17: sipush 230
    //   20: iconst_0
    //   21: invokestatic 115	xxxxxx/uxxxxx:bbbb0062b0062b0062b0062	(Ljava/lang/String;CCC)Ljava/lang/String;
    //   24: iconst_0
    //   25: anewarray 77	java/lang/Class
    //   28: invokevirtual 81	java/lang/Class:getMethod	(Ljava/lang/String;[Ljava/lang/Class;)Ljava/lang/reflect/Method;
    //   31: astore_1
    //   32: aload_1
    //   33: aconst_null
    //   34: iconst_0
    //   35: anewarray 83	java/lang/Object
    //   38: invokevirtual 89	java/lang/reflect/Method:invoke	(Ljava/lang/Object;[Ljava/lang/Object;)Ljava/lang/Object;
    //   41: astore_1
    //   42: aload_1
    //   43: checkcast 91	java/lang/Integer
    //   46: invokevirtual 94	java/lang/Integer:intValue	()I
    //   49: iload_2
    //   50: iadd
    //   51: iload_2
    //   52: imul
    //   53: getstatic 65	uuuuuu/ononoo:b006Enn006E006Enn006E006E	I
    //   56: irem
    //   57: tableswitch	default:+19->76, 0:+62->119
    //   76: ldc 2
    //   78: ldc -19
    //   80: bipush 123
    //   82: iconst_2
    //   83: invokestatic 75	xxxxxx/uxxxxx:bb00620062bb0062b0062b0062	(Ljava/lang/String;CC)Ljava/lang/String;
    //   86: iconst_0
    //   87: anewarray 77	java/lang/Class
    //   90: invokevirtual 81	java/lang/Class:getMethod	(Ljava/lang/String;[Ljava/lang/Class;)Ljava/lang/reflect/Method;
    //   93: astore_1
    //   94: aload_1
    //   95: aconst_null
    //   96: iconst_0
    //   97: anewarray 83	java/lang/Object
    //   100: invokevirtual 89	java/lang/reflect/Method:invoke	(Ljava/lang/Object;[Ljava/lang/Object;)Ljava/lang/Object;
    //   103: astore_1
    //   104: aload_1
    //   105: checkcast 91	java/lang/Integer
    //   108: invokevirtual 94	java/lang/Integer:intValue	()I
    //   111: putstatic 61	uuuuuu/ononoo:bn006E006En006Enn006E006E	I
    //   114: bipush 86
    //   116: putstatic 67	uuuuuu/ononoo:b006E006E006En006Enn006E006E	I
    //   119: ldc 2
    //   121: ldc_w 415
    //   124: sipush 217
    //   127: bipush 71
    //   129: iconst_3
    //   130: invokestatic 115	xxxxxx/uxxxxx:bbbb0062b0062b0062b0062	(Ljava/lang/String;CCC)Ljava/lang/String;
    //   133: iconst_0
    //   134: anewarray 77	java/lang/Class
    //   137: invokevirtual 81	java/lang/Class:getMethod	(Ljava/lang/String;[Ljava/lang/Class;)Ljava/lang/reflect/Method;
    //   140: astore_1
    //   141: aload_1
    //   142: aload_0
    //   143: iconst_0
    //   144: anewarray 83	java/lang/Object
    //   147: invokevirtual 89	java/lang/reflect/Method:invoke	(Ljava/lang/Object;[Ljava/lang/Object;)Ljava/lang/Object;
    //   150: pop
    //   151: getstatic 61	uuuuuu/ononoo:bn006E006En006Enn006E006E	I
    //   154: getstatic 63	uuuuuu/ononoo:bnnn006E006Enn006E006E	I
    //   157: iadd
    //   158: getstatic 61	uuuuuu/ononoo:bn006E006En006Enn006E006E	I
    //   161: imul
    //   162: getstatic 65	uuuuuu/ononoo:b006Enn006E006Enn006E006E	I
    //   165: irem
    //   166: getstatic 67	uuuuuu/ononoo:b006E006E006En006Enn006E006E	I
    //   169: if_icmpeq +226 -> 395
    //   172: bipush 22
    //   174: putstatic 61	uuuuuu/ononoo:bn006E006En006Enn006E006E	I
    //   177: bipush 60
    //   179: putstatic 67	uuuuuu/ononoo:b006E006E006En006Enn006E006E	I
    //   182: getstatic 61	uuuuuu/ononoo:bn006E006En006Enn006E006E	I
    //   185: getstatic 63	uuuuuu/ononoo:bnnn006E006Enn006E006E	I
    //   188: iadd
    //   189: getstatic 61	uuuuuu/ononoo:bn006E006En006Enn006E006E	I
    //   192: imul
    //   193: getstatic 65	uuuuuu/ononoo:b006Enn006E006Enn006E006E	I
    //   196: irem
    //   197: getstatic 67	uuuuuu/ononoo:b006E006E006En006Enn006E006E	I
    //   200: if_icmpeq +195 -> 395
    //   203: getstatic 61	uuuuuu/ononoo:bn006E006En006Enn006E006E	I
    //   206: istore_2
    //   207: getstatic 63	uuuuuu/ononoo:bnnn006E006Enn006E006E	I
    //   210: istore_3
    //   211: getstatic 61	uuuuuu/ononoo:bn006E006En006Enn006E006E	I
    //   214: istore 4
    //   216: getstatic 65	uuuuuu/ononoo:b006Enn006E006Enn006E006E	I
    //   219: istore 5
    //   221: ldc 2
    //   223: ldc_w 417
    //   226: bipush 47
    //   228: iconst_4
    //   229: invokestatic 75	xxxxxx/uxxxxx:bb00620062bb0062b0062b0062	(Ljava/lang/String;CC)Ljava/lang/String;
    //   232: iconst_0
    //   233: anewarray 77	java/lang/Class
    //   236: invokevirtual 81	java/lang/Class:getMethod	(Ljava/lang/String;[Ljava/lang/Class;)Ljava/lang/reflect/Method;
    //   239: astore_1
    //   240: aload_1
    //   241: aconst_null
    //   242: iconst_0
    //   243: anewarray 83	java/lang/Object
    //   246: invokevirtual 89	java/lang/reflect/Method:invoke	(Ljava/lang/Object;[Ljava/lang/Object;)Ljava/lang/Object;
    //   249: astore_1
    //   250: iload_2
    //   251: iload_3
    //   252: iadd
    //   253: iload 4
    //   255: imul
    //   256: iload 5
    //   258: irem
    //   259: aload_1
    //   260: checkcast 91	java/lang/Integer
    //   263: invokevirtual 94	java/lang/Integer:intValue	()I
    //   266: if_icmpeq +82 -> 348
    //   269: ldc 2
    //   271: ldc_w 419
    //   274: sipush 176
    //   277: iconst_1
    //   278: invokestatic 75	xxxxxx/uxxxxx:bb00620062bb0062b0062b0062	(Ljava/lang/String;CC)Ljava/lang/String;
    //   281: iconst_0
    //   282: anewarray 77	java/lang/Class
    //   285: invokevirtual 81	java/lang/Class:getMethod	(Ljava/lang/String;[Ljava/lang/Class;)Ljava/lang/reflect/Method;
    //   288: astore_1
    //   289: aload_1
    //   290: aconst_null
    //   291: iconst_0
    //   292: anewarray 83	java/lang/Object
    //   295: invokevirtual 89	java/lang/reflect/Method:invoke	(Ljava/lang/Object;[Ljava/lang/Object;)Ljava/lang/Object;
    //   298: astore_1
    //   299: aload_1
    //   300: checkcast 91	java/lang/Integer
    //   303: invokevirtual 94	java/lang/Integer:intValue	()I
    //   306: putstatic 61	uuuuuu/ononoo:bn006E006En006Enn006E006E	I
    //   309: ldc 2
    //   311: ldc_w 351
    //   314: bipush 117
    //   316: iconst_5
    //   317: invokestatic 75	xxxxxx/uxxxxx:bb00620062bb0062b0062b0062	(Ljava/lang/String;CC)Ljava/lang/String;
    //   320: iconst_0
    //   321: anewarray 77	java/lang/Class
    //   324: invokevirtual 81	java/lang/Class:getMethod	(Ljava/lang/String;[Ljava/lang/Class;)Ljava/lang/reflect/Method;
    //   327: astore_1
    //   328: aload_1
    //   329: aconst_null
    //   330: iconst_0
    //   331: anewarray 83	java/lang/Object
    //   334: invokevirtual 89	java/lang/reflect/Method:invoke	(Ljava/lang/Object;[Ljava/lang/Object;)Ljava/lang/Object;
    //   337: astore_1
    //   338: aload_1
    //   339: checkcast 91	java/lang/Integer
    //   342: invokevirtual 94	java/lang/Integer:intValue	()I
    //   345: putstatic 67	uuuuuu/ononoo:b006E006E006En006Enn006E006E	I
    //   348: ldc 2
    //   350: ldc_w 421
    //   353: sipush 165
    //   356: bipush 35
    //   358: iconst_1
    //   359: invokestatic 115	xxxxxx/uxxxxx:bbbb0062b0062b0062b0062	(Ljava/lang/String;CCC)Ljava/lang/String;
    //   362: iconst_0
    //   363: anewarray 77	java/lang/Class
    //   366: invokevirtual 81	java/lang/Class:getMethod	(Ljava/lang/String;[Ljava/lang/Class;)Ljava/lang/reflect/Method;
    //   369: astore_1
    //   370: aload_1
    //   371: aconst_null
    //   372: iconst_0
    //   373: anewarray 83	java/lang/Object
    //   376: invokevirtual 89	java/lang/reflect/Method:invoke	(Ljava/lang/Object;[Ljava/lang/Object;)Ljava/lang/Object;
    //   379: astore_1
    //   380: aload_1
    //   381: checkcast 91	java/lang/Integer
    //   384: invokevirtual 94	java/lang/Integer:intValue	()I
    //   387: putstatic 61	uuuuuu/ononoo:bn006E006En006Enn006E006E	I
    //   390: bipush 90
    //   392: putstatic 67	uuuuuu/ononoo:b006E006E006En006Enn006E006E	I
    //   395: return
    //   396: astore_1
    //   397: aload_1
    //   398: invokevirtual 104	java/lang/reflect/InvocationTargetException:getCause	()Ljava/lang/Throwable;
    //   401: athrow
    //   402: astore_1
    //   403: aload_1
    //   404: invokevirtual 104	java/lang/reflect/InvocationTargetException:getCause	()Ljava/lang/Throwable;
    //   407: athrow
    //   408: astore_1
    //   409: aload_1
    //   410: invokevirtual 104	java/lang/reflect/InvocationTargetException:getCause	()Ljava/lang/Throwable;
    //   413: athrow
    //   414: astore_1
    //   415: aload_1
    //   416: invokevirtual 104	java/lang/reflect/InvocationTargetException:getCause	()Ljava/lang/Throwable;
    //   419: athrow
    //   420: astore_1
    //   421: aload_1
    //   422: invokevirtual 104	java/lang/reflect/InvocationTargetException:getCause	()Ljava/lang/Throwable;
    //   425: athrow
    //   426: astore_1
    //   427: aload_1
    //   428: invokevirtual 104	java/lang/reflect/InvocationTargetException:getCause	()Ljava/lang/Throwable;
    //   431: athrow
    //   432: astore_1
    //   433: aload_1
    //   434: invokevirtual 104	java/lang/reflect/InvocationTargetException:getCause	()Ljava/lang/Throwable;
    //   437: athrow
    // Local variable table:
    //   start	length	slot	name	signature
    //   0	438	0	this	ononoo
    //   0	438	1	paramNoonoo	nnnooo.noonoo
    //   8	245	2	i	int
    //   210	43	3	j	int
    //   214	42	4	k	int
    //   219	40	5	m	int
    // Exception table:
    //   from	to	target	type
    //   370	380	396	java/lang/reflect/InvocationTargetException
    //   240	250	402	java/lang/reflect/InvocationTargetException
    //   141	151	408	java/lang/reflect/InvocationTargetException
    //   32	42	414	java/lang/reflect/InvocationTargetException
    //   94	104	420	java/lang/reflect/InvocationTargetException
    //   289	299	426	java/lang/reflect/InvocationTargetException
    //   328	338	432	java/lang/reflect/InvocationTargetException
  }
  
  /* Error */
  public void b006Bkk006Bk006B006B006B006Bk()
  {
    // Byte code:
    //   0: aload_0
    //   1: getfield 190	uuuuuu/ononoo:bn006Enn006Enn006E006E	Luuuuuu/onoono;
    //   4: astore 10
    //   6: getstatic 61	uuuuuu/ononoo:bn006E006En006Enn006E006E	I
    //   9: istore_1
    //   10: getstatic 63	uuuuuu/ononoo:bnnn006E006Enn006E006E	I
    //   13: istore_2
    //   14: getstatic 65	uuuuuu/ononoo:b006Enn006E006Enn006E006E	I
    //   17: istore_3
    //   18: getstatic 61	uuuuuu/ononoo:bn006E006En006Enn006E006E	I
    //   21: istore 4
    //   23: getstatic 63	uuuuuu/ononoo:bnnn006E006Enn006E006E	I
    //   26: istore 5
    //   28: getstatic 61	uuuuuu/ononoo:bn006E006En006Enn006E006E	I
    //   31: istore 6
    //   33: getstatic 63	uuuuuu/ononoo:bnnn006E006Enn006E006E	I
    //   36: istore 7
    //   38: getstatic 61	uuuuuu/ononoo:bn006E006En006Enn006E006E	I
    //   41: istore 8
    //   43: getstatic 65	uuuuuu/ononoo:b006Enn006E006Enn006E006E	I
    //   46: istore 9
    //   48: ldc 2
    //   50: ldc_w 424
    //   53: bipush 26
    //   55: iconst_1
    //   56: invokestatic 75	xxxxxx/uxxxxx:bb00620062bb0062b0062b0062	(Ljava/lang/String;CC)Ljava/lang/String;
    //   59: iconst_0
    //   60: anewarray 77	java/lang/Class
    //   63: invokevirtual 81	java/lang/Class:getMethod	(Ljava/lang/String;[Ljava/lang/Class;)Ljava/lang/reflect/Method;
    //   66: astore 11
    //   68: aload 11
    //   70: aconst_null
    //   71: iconst_0
    //   72: anewarray 83	java/lang/Object
    //   75: invokevirtual 89	java/lang/reflect/Method:invoke	(Ljava/lang/Object;[Ljava/lang/Object;)Ljava/lang/Object;
    //   78: astore 11
    //   80: iload 6
    //   82: iload 7
    //   84: iadd
    //   85: iload 8
    //   87: imul
    //   88: iload 9
    //   90: irem
    //   91: aload 11
    //   93: checkcast 91	java/lang/Integer
    //   96: invokevirtual 94	java/lang/Integer:intValue	()I
    //   99: if_icmpeq +51 -> 150
    //   102: bipush 29
    //   104: putstatic 61	uuuuuu/ononoo:bn006E006En006Enn006E006E	I
    //   107: ldc 2
    //   109: ldc_w 426
    //   112: bipush 110
    //   114: iconst_3
    //   115: invokestatic 75	xxxxxx/uxxxxx:bb00620062bb0062b0062b0062	(Ljava/lang/String;CC)Ljava/lang/String;
    //   118: iconst_0
    //   119: anewarray 77	java/lang/Class
    //   122: invokevirtual 81	java/lang/Class:getMethod	(Ljava/lang/String;[Ljava/lang/Class;)Ljava/lang/reflect/Method;
    //   125: astore 11
    //   127: aload 11
    //   129: aconst_null
    //   130: iconst_0
    //   131: anewarray 83	java/lang/Object
    //   134: invokevirtual 89	java/lang/reflect/Method:invoke	(Ljava/lang/Object;[Ljava/lang/Object;)Ljava/lang/Object;
    //   137: astore 11
    //   139: aload 11
    //   141: checkcast 91	java/lang/Integer
    //   144: invokevirtual 94	java/lang/Integer:intValue	()I
    //   147: putstatic 67	uuuuuu/ononoo:b006E006E006En006Enn006E006E	I
    //   150: iload 5
    //   152: iload 4
    //   154: iadd
    //   155: iload 4
    //   157: imul
    //   158: getstatic 65	uuuuuu/ononoo:b006Enn006E006Enn006E006E	I
    //   161: irem
    //   162: tableswitch	default:+18->180, 0:+66->228
    //   180: iconst_1
    //   181: putstatic 61	uuuuuu/ononoo:bn006E006En006Enn006E006E	I
    //   184: ldc 2
    //   186: ldc_w 428
    //   189: sipush 228
    //   192: iconst_4
    //   193: invokestatic 75	xxxxxx/uxxxxx:bb00620062bb0062b0062b0062	(Ljava/lang/String;CC)Ljava/lang/String;
    //   196: iconst_0
    //   197: anewarray 77	java/lang/Class
    //   200: invokevirtual 81	java/lang/Class:getMethod	(Ljava/lang/String;[Ljava/lang/Class;)Ljava/lang/reflect/Method;
    //   203: astore 11
    //   205: aload 11
    //   207: aconst_null
    //   208: iconst_0
    //   209: anewarray 83	java/lang/Object
    //   212: invokevirtual 89	java/lang/reflect/Method:invoke	(Ljava/lang/Object;[Ljava/lang/Object;)Ljava/lang/Object;
    //   215: astore 11
    //   217: aload 11
    //   219: checkcast 91	java/lang/Integer
    //   222: invokevirtual 94	java/lang/Integer:intValue	()I
    //   225: putstatic 67	uuuuuu/ononoo:b006E006E006En006Enn006E006E	I
    //   228: iload_2
    //   229: iload_1
    //   230: iadd
    //   231: iload_1
    //   232: imul
    //   233: iload_3
    //   234: irem
    //   235: tableswitch	default:+17->252, 0:+267->502
    //   252: ldc 2
    //   254: ldc_w 301
    //   257: sipush 204
    //   260: sipush 184
    //   263: iconst_2
    //   264: invokestatic 115	xxxxxx/uxxxxx:bbbb0062b0062b0062b0062	(Ljava/lang/String;CCC)Ljava/lang/String;
    //   267: iconst_0
    //   268: anewarray 77	java/lang/Class
    //   271: invokevirtual 81	java/lang/Class:getMethod	(Ljava/lang/String;[Ljava/lang/Class;)Ljava/lang/reflect/Method;
    //   274: astore 11
    //   276: aload 11
    //   278: aconst_null
    //   279: iconst_0
    //   280: anewarray 83	java/lang/Object
    //   283: invokevirtual 89	java/lang/reflect/Method:invoke	(Ljava/lang/Object;[Ljava/lang/Object;)Ljava/lang/Object;
    //   286: astore 11
    //   288: aload 11
    //   290: checkcast 91	java/lang/Integer
    //   293: invokevirtual 94	java/lang/Integer:intValue	()I
    //   296: putstatic 61	uuuuuu/ononoo:bn006E006En006Enn006E006E	I
    //   299: ldc 2
    //   301: ldc_w 430
    //   304: bipush 127
    //   306: iconst_1
    //   307: invokestatic 75	xxxxxx/uxxxxx:bb00620062bb0062b0062b0062	(Ljava/lang/String;CC)Ljava/lang/String;
    //   310: iconst_0
    //   311: anewarray 77	java/lang/Class
    //   314: invokevirtual 81	java/lang/Class:getMethod	(Ljava/lang/String;[Ljava/lang/Class;)Ljava/lang/reflect/Method;
    //   317: astore 11
    //   319: aload 11
    //   321: aconst_null
    //   322: iconst_0
    //   323: anewarray 83	java/lang/Object
    //   326: invokevirtual 89	java/lang/reflect/Method:invoke	(Ljava/lang/Object;[Ljava/lang/Object;)Ljava/lang/Object;
    //   329: astore 11
    //   331: aload 11
    //   333: checkcast 91	java/lang/Integer
    //   336: invokevirtual 94	java/lang/Integer:intValue	()I
    //   339: putstatic 67	uuuuuu/ononoo:b006E006E006En006Enn006E006E	I
    //   342: ldc 2
    //   344: ldc_w 432
    //   347: sipush 200
    //   350: iconst_3
    //   351: invokestatic 75	xxxxxx/uxxxxx:bb00620062bb0062b0062b0062	(Ljava/lang/String;CC)Ljava/lang/String;
    //   354: iconst_0
    //   355: anewarray 77	java/lang/Class
    //   358: invokevirtual 81	java/lang/Class:getMethod	(Ljava/lang/String;[Ljava/lang/Class;)Ljava/lang/reflect/Method;
    //   361: astore 11
    //   363: aload 11
    //   365: aconst_null
    //   366: iconst_0
    //   367: anewarray 83	java/lang/Object
    //   370: invokevirtual 89	java/lang/reflect/Method:invoke	(Ljava/lang/Object;[Ljava/lang/Object;)Ljava/lang/Object;
    //   373: astore 11
    //   375: aload 11
    //   377: checkcast 91	java/lang/Integer
    //   380: invokevirtual 94	java/lang/Integer:intValue	()I
    //   383: istore_1
    //   384: iload_1
    //   385: getstatic 63	uuuuuu/ononoo:bnnn006E006Enn006E006E	I
    //   388: iload_1
    //   389: iadd
    //   390: imul
    //   391: getstatic 65	uuuuuu/ononoo:b006Enn006E006Enn006E006E	I
    //   394: irem
    //   395: tableswitch	default:+17->412, 0:+107->502
    //   412: ldc 2
    //   414: ldc_w 434
    //   417: bipush 91
    //   419: sipush 219
    //   422: iconst_1
    //   423: invokestatic 115	xxxxxx/uxxxxx:bbbb0062b0062b0062b0062	(Ljava/lang/String;CCC)Ljava/lang/String;
    //   426: iconst_0
    //   427: anewarray 77	java/lang/Class
    //   430: invokevirtual 81	java/lang/Class:getMethod	(Ljava/lang/String;[Ljava/lang/Class;)Ljava/lang/reflect/Method;
    //   433: astore 11
    //   435: aload 11
    //   437: aconst_null
    //   438: iconst_0
    //   439: anewarray 83	java/lang/Object
    //   442: invokevirtual 89	java/lang/reflect/Method:invoke	(Ljava/lang/Object;[Ljava/lang/Object;)Ljava/lang/Object;
    //   445: astore 11
    //   447: aload 11
    //   449: checkcast 91	java/lang/Integer
    //   452: invokevirtual 94	java/lang/Integer:intValue	()I
    //   455: putstatic 61	uuuuuu/ononoo:bn006E006En006Enn006E006E	I
    //   458: ldc 2
    //   460: ldc_w 436
    //   463: sipush 228
    //   466: iconst_5
    //   467: invokestatic 75	xxxxxx/uxxxxx:bb00620062bb0062b0062b0062	(Ljava/lang/String;CC)Ljava/lang/String;
    //   470: iconst_0
    //   471: anewarray 77	java/lang/Class
    //   474: invokevirtual 81	java/lang/Class:getMethod	(Ljava/lang/String;[Ljava/lang/Class;)Ljava/lang/reflect/Method;
    //   477: astore 11
    //   479: aload 11
    //   481: aconst_null
    //   482: iconst_0
    //   483: anewarray 83	java/lang/Object
    //   486: invokevirtual 89	java/lang/reflect/Method:invoke	(Ljava/lang/Object;[Ljava/lang/Object;)Ljava/lang/Object;
    //   489: astore 11
    //   491: aload 11
    //   493: checkcast 91	java/lang/Integer
    //   496: invokevirtual 94	java/lang/Integer:intValue	()I
    //   499: putstatic 67	uuuuuu/ononoo:b006E006E006En006Enn006E006E	I
    //   502: aload 10
    //   504: invokeinterface 439 1 0
    //   509: getstatic 442	uuuuuu/vvrvrv:b0068hhh006800680068h0068	Luuuuuu/vvrvrv;
    //   512: invokestatic 272	uuuuuu/rrvvrv:b0071q0071qq0071q0071q0071	(Luuuuuu/vvrvrv;)V
    //   515: aload_0
    //   516: getfield 98	uuuuuu/ononoo:bnnnnn006E006E006En	Luuuuuu/ttssst$tsssst;
    //   519: checkcast 136	uuuuuu/nnnooo$noonoo
    //   522: iconst_0
    //   523: getstatic 379	com/db/pwcc/dbmobile/foundation/R$string:settings_label_inactive	I
    //   526: invokeinterface 389 3 0
    //   531: return
    //   532: astore 10
    //   534: aload 10
    //   536: invokevirtual 104	java/lang/reflect/InvocationTargetException:getCause	()Ljava/lang/Throwable;
    //   539: athrow
    //   540: astore 10
    //   542: aload 10
    //   544: invokevirtual 104	java/lang/reflect/InvocationTargetException:getCause	()Ljava/lang/Throwable;
    //   547: athrow
    //   548: astore 10
    //   550: aload 10
    //   552: invokevirtual 104	java/lang/reflect/InvocationTargetException:getCause	()Ljava/lang/Throwable;
    //   555: athrow
    //   556: astore 10
    //   558: aload 10
    //   560: invokevirtual 104	java/lang/reflect/InvocationTargetException:getCause	()Ljava/lang/Throwable;
    //   563: athrow
    //   564: astore 10
    //   566: aload 10
    //   568: invokevirtual 104	java/lang/reflect/InvocationTargetException:getCause	()Ljava/lang/Throwable;
    //   571: athrow
    //   572: astore 10
    //   574: aload 10
    //   576: invokevirtual 104	java/lang/reflect/InvocationTargetException:getCause	()Ljava/lang/Throwable;
    //   579: athrow
    //   580: astore 10
    //   582: aload 10
    //   584: invokevirtual 104	java/lang/reflect/InvocationTargetException:getCause	()Ljava/lang/Throwable;
    //   587: athrow
    //   588: astore 10
    //   590: aload 10
    //   592: invokevirtual 104	java/lang/reflect/InvocationTargetException:getCause	()Ljava/lang/Throwable;
    //   595: athrow
    // Local variable table:
    //   start	length	slot	name	signature
    //   0	596	0	this	ononoo
    //   9	382	1	i	int
    //   13	218	2	j	int
    //   17	218	3	k	int
    //   21	137	4	m	int
    //   26	129	5	n	int
    //   31	54	6	i1	int
    //   36	49	7	i2	int
    //   41	47	8	i3	int
    //   46	45	9	i4	int
    //   4	499	10	localOnoono	onoono
    //   532	3	10	localInvocationTargetException1	java.lang.reflect.InvocationTargetException
    //   540	3	10	localInvocationTargetException2	java.lang.reflect.InvocationTargetException
    //   548	3	10	localInvocationTargetException3	java.lang.reflect.InvocationTargetException
    //   556	3	10	localInvocationTargetException4	java.lang.reflect.InvocationTargetException
    //   564	3	10	localInvocationTargetException5	java.lang.reflect.InvocationTargetException
    //   572	3	10	localInvocationTargetException6	java.lang.reflect.InvocationTargetException
    //   580	3	10	localInvocationTargetException7	java.lang.reflect.InvocationTargetException
    //   588	3	10	localInvocationTargetException8	java.lang.reflect.InvocationTargetException
    //   66	426	11	localObject	Object
    // Exception table:
    //   from	to	target	type
    //   68	80	532	java/lang/reflect/InvocationTargetException
    //   205	217	540	java/lang/reflect/InvocationTargetException
    //   276	288	548	java/lang/reflect/InvocationTargetException
    //   319	331	556	java/lang/reflect/InvocationTargetException
    //   363	375	564	java/lang/reflect/InvocationTargetException
    //   435	447	572	java/lang/reflect/InvocationTargetException
    //   479	491	580	java/lang/reflect/InvocationTargetException
    //   127	139	588	java/lang/reflect/InvocationTargetException
  }
  
  /* Error */
  public void ba0061006100610061aaa0061a(com.db.pwcc.dbmobile.model.error.DbError paramDbError)
  {
    // Byte code:
    //   0: aload_0
    //   1: invokevirtual 171	uuuuuu/ononoo:bkk006Bk006Bk006Bk006Bk	()Z
    //   4: ifne +4 -> 8
    //   7: return
    //   8: getstatic 61	uuuuuu/ononoo:bn006E006En006Enn006E006E	I
    //   11: istore_2
    //   12: getstatic 63	uuuuuu/ononoo:bnnn006E006Enn006E006E	I
    //   15: istore_3
    //   16: getstatic 61	uuuuuu/ononoo:bn006E006En006Enn006E006E	I
    //   19: istore 4
    //   21: iload 4
    //   23: getstatic 63	uuuuuu/ononoo:bnnn006E006Enn006E006E	I
    //   26: iload 4
    //   28: iadd
    //   29: imul
    //   30: getstatic 65	uuuuuu/ononoo:b006Enn006E006Enn006E006E	I
    //   33: irem
    //   34: tableswitch	default:+18->52, 0:+69->103
    //   52: bipush 61
    //   54: putstatic 61	uuuuuu/ononoo:bn006E006En006Enn006E006E	I
    //   57: ldc 2
    //   59: ldc_w 446
    //   62: sipush 230
    //   65: bipush 119
    //   67: iconst_0
    //   68: invokestatic 115	xxxxxx/uxxxxx:bbbb0062b0062b0062b0062	(Ljava/lang/String;CCC)Ljava/lang/String;
    //   71: iconst_0
    //   72: anewarray 77	java/lang/Class
    //   75: invokevirtual 81	java/lang/Class:getMethod	(Ljava/lang/String;[Ljava/lang/Class;)Ljava/lang/reflect/Method;
    //   78: astore 5
    //   80: aload 5
    //   82: aconst_null
    //   83: iconst_0
    //   84: anewarray 83	java/lang/Object
    //   87: invokevirtual 89	java/lang/reflect/Method:invoke	(Ljava/lang/Object;[Ljava/lang/Object;)Ljava/lang/Object;
    //   90: astore 5
    //   92: aload 5
    //   94: checkcast 91	java/lang/Integer
    //   97: invokevirtual 94	java/lang/Integer:intValue	()I
    //   100: putstatic 67	uuuuuu/ononoo:b006E006E006En006Enn006E006E	I
    //   103: iload_2
    //   104: iload_2
    //   105: iload_3
    //   106: iadd
    //   107: imul
    //   108: getstatic 65	uuuuuu/ononoo:b006Enn006E006Enn006E006E	I
    //   111: irem
    //   112: tableswitch	default:+20->132, 0:+105->217
    //   132: ldc 2
    //   134: ldc_w 448
    //   137: iconst_4
    //   138: iconst_5
    //   139: invokestatic 75	xxxxxx/uxxxxx:bb00620062bb0062b0062b0062	(Ljava/lang/String;CC)Ljava/lang/String;
    //   142: iconst_0
    //   143: anewarray 77	java/lang/Class
    //   146: invokevirtual 81	java/lang/Class:getMethod	(Ljava/lang/String;[Ljava/lang/Class;)Ljava/lang/reflect/Method;
    //   149: astore 5
    //   151: aload 5
    //   153: aconst_null
    //   154: iconst_0
    //   155: anewarray 83	java/lang/Object
    //   158: invokevirtual 89	java/lang/reflect/Method:invoke	(Ljava/lang/Object;[Ljava/lang/Object;)Ljava/lang/Object;
    //   161: astore 5
    //   163: aload 5
    //   165: checkcast 91	java/lang/Integer
    //   168: invokevirtual 94	java/lang/Integer:intValue	()I
    //   171: putstatic 61	uuuuuu/ononoo:bn006E006En006Enn006E006E	I
    //   174: ldc 2
    //   176: ldc_w 450
    //   179: bipush 104
    //   181: iconst_1
    //   182: invokestatic 75	xxxxxx/uxxxxx:bb00620062bb0062b0062b0062	(Ljava/lang/String;CC)Ljava/lang/String;
    //   185: iconst_0
    //   186: anewarray 77	java/lang/Class
    //   189: invokevirtual 81	java/lang/Class:getMethod	(Ljava/lang/String;[Ljava/lang/Class;)Ljava/lang/reflect/Method;
    //   192: astore 5
    //   194: aload 5
    //   196: aconst_null
    //   197: iconst_0
    //   198: anewarray 83	java/lang/Object
    //   201: invokevirtual 89	java/lang/reflect/Method:invoke	(Ljava/lang/Object;[Ljava/lang/Object;)Ljava/lang/Object;
    //   204: astore 5
    //   206: aload 5
    //   208: checkcast 91	java/lang/Integer
    //   211: invokevirtual 94	java/lang/Integer:intValue	()I
    //   214: putstatic 67	uuuuuu/ononoo:b006E006E006En006Enn006E006E	I
    //   217: ldc 2
    //   219: ldc_w 452
    //   222: bipush 117
    //   224: iconst_4
    //   225: invokestatic 75	xxxxxx/uxxxxx:bb00620062bb0062b0062b0062	(Ljava/lang/String;CC)Ljava/lang/String;
    //   228: iconst_1
    //   229: anewarray 77	java/lang/Class
    //   232: dup
    //   233: iconst_0
    //   234: ldc 121
    //   236: aastore
    //   237: invokevirtual 81	java/lang/Class:getMethod	(Ljava/lang/String;[Ljava/lang/Class;)Ljava/lang/reflect/Method;
    //   240: astore 5
    //   242: aload 5
    //   244: aload_0
    //   245: iconst_1
    //   246: anewarray 83	java/lang/Object
    //   249: dup
    //   250: iconst_0
    //   251: aload_1
    //   252: aastore
    //   253: invokevirtual 89	java/lang/reflect/Method:invoke	(Ljava/lang/Object;[Ljava/lang/Object;)Ljava/lang/Object;
    //   256: pop
    //   257: getstatic 61	uuuuuu/ononoo:bn006E006En006Enn006E006E	I
    //   260: getstatic 63	uuuuuu/ononoo:bnnn006E006Enn006E006E	I
    //   263: iadd
    //   264: getstatic 61	uuuuuu/ononoo:bn006E006En006Enn006E006E	I
    //   267: imul
    //   268: getstatic 65	uuuuuu/ononoo:b006Enn006E006Enn006E006E	I
    //   271: irem
    //   272: getstatic 67	uuuuuu/ononoo:b006E006E006En006Enn006E006E	I
    //   275: if_icmpeq -268 -> 7
    //   278: bipush 57
    //   280: putstatic 61	uuuuuu/ononoo:bn006E006En006Enn006E006E	I
    //   283: ldc 2
    //   285: ldc_w 454
    //   288: sipush 159
    //   291: bipush 76
    //   293: iconst_2
    //   294: invokestatic 115	xxxxxx/uxxxxx:bbbb0062b0062b0062b0062	(Ljava/lang/String;CCC)Ljava/lang/String;
    //   297: iconst_0
    //   298: anewarray 77	java/lang/Class
    //   301: invokevirtual 81	java/lang/Class:getMethod	(Ljava/lang/String;[Ljava/lang/Class;)Ljava/lang/reflect/Method;
    //   304: astore_1
    //   305: aload_1
    //   306: aconst_null
    //   307: iconst_0
    //   308: anewarray 83	java/lang/Object
    //   311: invokevirtual 89	java/lang/reflect/Method:invoke	(Ljava/lang/Object;[Ljava/lang/Object;)Ljava/lang/Object;
    //   314: astore_1
    //   315: aload_1
    //   316: checkcast 91	java/lang/Integer
    //   319: invokevirtual 94	java/lang/Integer:intValue	()I
    //   322: putstatic 67	uuuuuu/ononoo:b006E006E006En006Enn006E006E	I
    //   325: getstatic 61	uuuuuu/ononoo:bn006E006En006Enn006E006E	I
    //   328: getstatic 63	uuuuuu/ononoo:bnnn006E006Enn006E006E	I
    //   331: iadd
    //   332: getstatic 61	uuuuuu/ononoo:bn006E006En006Enn006E006E	I
    //   335: imul
    //   336: getstatic 65	uuuuuu/ononoo:b006Enn006E006Enn006E006E	I
    //   339: irem
    //   340: getstatic 67	uuuuuu/ononoo:b006E006E006En006Enn006E006E	I
    //   343: if_icmpeq -336 -> 7
    //   346: bipush 65
    //   348: putstatic 61	uuuuuu/ononoo:bn006E006En006Enn006E006E	I
    //   351: bipush 15
    //   353: putstatic 67	uuuuuu/ononoo:b006E006E006En006Enn006E006E	I
    //   356: return
    //   357: astore_1
    //   358: aload_1
    //   359: invokevirtual 104	java/lang/reflect/InvocationTargetException:getCause	()Ljava/lang/Throwable;
    //   362: athrow
    //   363: astore_1
    //   364: aload_1
    //   365: invokevirtual 104	java/lang/reflect/InvocationTargetException:getCause	()Ljava/lang/Throwable;
    //   368: athrow
    //   369: astore_1
    //   370: aload_1
    //   371: invokevirtual 104	java/lang/reflect/InvocationTargetException:getCause	()Ljava/lang/Throwable;
    //   374: athrow
    //   375: astore_1
    //   376: aload_1
    //   377: invokevirtual 104	java/lang/reflect/InvocationTargetException:getCause	()Ljava/lang/Throwable;
    //   380: athrow
    //   381: astore_1
    //   382: aload_1
    //   383: invokevirtual 104	java/lang/reflect/InvocationTargetException:getCause	()Ljava/lang/Throwable;
    //   386: athrow
    // Local variable table:
    //   start	length	slot	name	signature
    //   0	387	0	this	ononoo
    //   0	387	1	paramDbError	com.db.pwcc.dbmobile.model.error.DbError
    //   11	97	2	i	int
    //   15	92	3	j	int
    //   19	11	4	k	int
    //   78	165	5	localObject	Object
    // Exception table:
    //   from	to	target	type
    //   151	163	357	java/lang/reflect/InvocationTargetException
    //   194	206	363	java/lang/reflect/InvocationTargetException
    //   242	257	369	java/lang/reflect/InvocationTargetException
    //   305	315	375	java/lang/reflect/InvocationTargetException
    //   80	92	381	java/lang/reflect/InvocationTargetException
  }
  
  /* Error */
  public void ba006100610061a0061aa0061a()
  {
    // Byte code:
    //   0: ldc 2
    //   2: ldc_w 457
    //   5: sipush 187
    //   8: bipush 50
    //   10: iconst_1
    //   11: invokestatic 115	xxxxxx/uxxxxx:bbbb0062b0062b0062b0062	(Ljava/lang/String;CCC)Ljava/lang/String;
    //   14: iconst_0
    //   15: anewarray 77	java/lang/Class
    //   18: invokevirtual 81	java/lang/Class:getMethod	(Ljava/lang/String;[Ljava/lang/Class;)Ljava/lang/reflect/Method;
    //   21: astore 5
    //   23: aload 5
    //   25: aload_0
    //   26: iconst_0
    //   27: anewarray 83	java/lang/Object
    //   30: invokevirtual 89	java/lang/reflect/Method:invoke	(Ljava/lang/Object;[Ljava/lang/Object;)Ljava/lang/Object;
    //   33: pop
    //   34: aload_0
    //   35: getfield 190	uuuuuu/ononoo:bn006Enn006Enn006E006E	Luuuuuu/onoono;
    //   38: invokeinterface 275 1 0
    //   43: aload_0
    //   44: getfield 98	uuuuuu/ononoo:bnnnnn006E006E006En	Luuuuuu/ttssst$tsssst;
    //   47: checkcast 136	uuuuuu/nnnooo$noonoo
    //   50: invokeinterface 460 1 0
    //   55: aload_0
    //   56: getfield 98	uuuuuu/ononoo:bnnnnn006E006E006En	Luuuuuu/ttssst$tsssst;
    //   59: astore 5
    //   61: getstatic 61	uuuuuu/ononoo:bn006E006En006Enn006E006E	I
    //   64: istore_1
    //   65: ldc 2
    //   67: ldc_w 462
    //   70: sipush 174
    //   73: sipush 185
    //   76: iconst_2
    //   77: invokestatic 115	xxxxxx/uxxxxx:bbbb0062b0062b0062b0062	(Ljava/lang/String;CCC)Ljava/lang/String;
    //   80: iconst_0
    //   81: anewarray 77	java/lang/Class
    //   84: invokevirtual 81	java/lang/Class:getMethod	(Ljava/lang/String;[Ljava/lang/Class;)Ljava/lang/reflect/Method;
    //   87: astore 6
    //   89: aload 6
    //   91: aconst_null
    //   92: iconst_0
    //   93: anewarray 83	java/lang/Object
    //   96: invokevirtual 89	java/lang/reflect/Method:invoke	(Ljava/lang/Object;[Ljava/lang/Object;)Ljava/lang/Object;
    //   99: astore 6
    //   101: aload 6
    //   103: checkcast 91	java/lang/Integer
    //   106: invokevirtual 94	java/lang/Integer:intValue	()I
    //   109: iload_1
    //   110: iadd
    //   111: getstatic 61	uuuuuu/ononoo:bn006E006En006Enn006E006E	I
    //   114: imul
    //   115: getstatic 65	uuuuuu/ononoo:b006Enn006E006Enn006E006E	I
    //   118: irem
    //   119: getstatic 67	uuuuuu/ononoo:b006E006E006En006Enn006E006E	I
    //   122: if_icmpeq +296 -> 418
    //   125: getstatic 61	uuuuuu/ononoo:bn006E006En006Enn006E006E	I
    //   128: istore_1
    //   129: getstatic 63	uuuuuu/ononoo:bnnn006E006Enn006E006E	I
    //   132: istore_2
    //   133: getstatic 61	uuuuuu/ononoo:bn006E006En006Enn006E006E	I
    //   136: istore_3
    //   137: getstatic 61	uuuuuu/ononoo:bn006E006En006Enn006E006E	I
    //   140: istore 4
    //   142: iload 4
    //   144: getstatic 63	uuuuuu/ononoo:bnnn006E006Enn006E006E	I
    //   147: iload 4
    //   149: iadd
    //   150: imul
    //   151: getstatic 65	uuuuuu/ononoo:b006Enn006E006Enn006E006E	I
    //   154: irem
    //   155: tableswitch	default:+17->172, 0:+107->262
    //   172: ldc 2
    //   174: ldc_w 257
    //   177: sipush 190
    //   180: bipush 57
    //   182: iconst_1
    //   183: invokestatic 115	xxxxxx/uxxxxx:bbbb0062b0062b0062b0062	(Ljava/lang/String;CCC)Ljava/lang/String;
    //   186: iconst_0
    //   187: anewarray 77	java/lang/Class
    //   190: invokevirtual 81	java/lang/Class:getMethod	(Ljava/lang/String;[Ljava/lang/Class;)Ljava/lang/reflect/Method;
    //   193: astore 6
    //   195: aload 6
    //   197: aconst_null
    //   198: iconst_0
    //   199: anewarray 83	java/lang/Object
    //   202: invokevirtual 89	java/lang/reflect/Method:invoke	(Ljava/lang/Object;[Ljava/lang/Object;)Ljava/lang/Object;
    //   205: astore 6
    //   207: aload 6
    //   209: checkcast 91	java/lang/Integer
    //   212: invokevirtual 94	java/lang/Integer:intValue	()I
    //   215: putstatic 61	uuuuuu/ononoo:bn006E006En006Enn006E006E	I
    //   218: ldc 2
    //   220: ldc_w 464
    //   223: sipush 163
    //   226: iconst_2
    //   227: invokestatic 75	xxxxxx/uxxxxx:bb00620062bb0062b0062b0062	(Ljava/lang/String;CC)Ljava/lang/String;
    //   230: iconst_0
    //   231: anewarray 77	java/lang/Class
    //   234: invokevirtual 81	java/lang/Class:getMethod	(Ljava/lang/String;[Ljava/lang/Class;)Ljava/lang/reflect/Method;
    //   237: astore 6
    //   239: aload 6
    //   241: aconst_null
    //   242: iconst_0
    //   243: anewarray 83	java/lang/Object
    //   246: invokevirtual 89	java/lang/reflect/Method:invoke	(Ljava/lang/Object;[Ljava/lang/Object;)Ljava/lang/Object;
    //   249: astore 6
    //   251: aload 6
    //   253: checkcast 91	java/lang/Integer
    //   256: invokevirtual 94	java/lang/Integer:intValue	()I
    //   259: putstatic 67	uuuuuu/ononoo:b006E006E006En006Enn006E006E	I
    //   262: iload_3
    //   263: iload_1
    //   264: iload_2
    //   265: iadd
    //   266: imul
    //   267: getstatic 65	uuuuuu/ononoo:b006Enn006E006Enn006E006E	I
    //   270: irem
    //   271: getstatic 67	uuuuuu/ononoo:b006E006E006En006Enn006E006E	I
    //   274: if_icmpeq +134 -> 408
    //   277: bipush 61
    //   279: putstatic 61	uuuuuu/ononoo:bn006E006En006Enn006E006E	I
    //   282: ldc 2
    //   284: ldc_w 343
    //   287: sipush 248
    //   290: iconst_3
    //   291: invokestatic 75	xxxxxx/uxxxxx:bb00620062bb0062b0062b0062	(Ljava/lang/String;CC)Ljava/lang/String;
    //   294: iconst_0
    //   295: anewarray 77	java/lang/Class
    //   298: invokevirtual 81	java/lang/Class:getMethod	(Ljava/lang/String;[Ljava/lang/Class;)Ljava/lang/reflect/Method;
    //   301: astore 6
    //   303: aload 6
    //   305: aconst_null
    //   306: iconst_0
    //   307: anewarray 83	java/lang/Object
    //   310: invokevirtual 89	java/lang/reflect/Method:invoke	(Ljava/lang/Object;[Ljava/lang/Object;)Ljava/lang/Object;
    //   313: astore 6
    //   315: aload 6
    //   317: checkcast 91	java/lang/Integer
    //   320: invokevirtual 94	java/lang/Integer:intValue	()I
    //   323: putstatic 67	uuuuuu/ononoo:b006E006E006En006Enn006E006E	I
    //   326: getstatic 61	uuuuuu/ononoo:bn006E006En006Enn006E006E	I
    //   329: istore_1
    //   330: iload_1
    //   331: getstatic 63	uuuuuu/ononoo:bnnn006E006Enn006E006E	I
    //   334: iload_1
    //   335: iadd
    //   336: imul
    //   337: getstatic 65	uuuuuu/ononoo:b006Enn006E006Enn006E006E	I
    //   340: irem
    //   341: tableswitch	default:+19->360, 0:+67->408
    //   360: ldc 2
    //   362: ldc_w 466
    //   365: bipush 69
    //   367: iconst_4
    //   368: invokestatic 75	xxxxxx/uxxxxx:bb00620062bb0062b0062b0062	(Ljava/lang/String;CC)Ljava/lang/String;
    //   371: iconst_0
    //   372: anewarray 77	java/lang/Class
    //   375: invokevirtual 81	java/lang/Class:getMethod	(Ljava/lang/String;[Ljava/lang/Class;)Ljava/lang/reflect/Method;
    //   378: astore 6
    //   380: aload 6
    //   382: aconst_null
    //   383: iconst_0
    //   384: anewarray 83	java/lang/Object
    //   387: invokevirtual 89	java/lang/reflect/Method:invoke	(Ljava/lang/Object;[Ljava/lang/Object;)Ljava/lang/Object;
    //   390: astore 6
    //   392: aload 6
    //   394: checkcast 91	java/lang/Integer
    //   397: invokevirtual 94	java/lang/Integer:intValue	()I
    //   400: putstatic 61	uuuuuu/ononoo:bn006E006En006Enn006E006E	I
    //   403: bipush 48
    //   405: putstatic 67	uuuuuu/ononoo:b006E006E006En006Enn006E006E	I
    //   408: bipush 29
    //   410: putstatic 61	uuuuuu/ononoo:bn006E006En006Enn006E006E	I
    //   413: bipush 53
    //   415: putstatic 67	uuuuuu/ononoo:b006E006E006En006Enn006E006E	I
    //   418: aload 5
    //   420: checkcast 136	uuuuuu/nnnooo$noonoo
    //   423: invokeinterface 188 1 0
    //   428: aload_0
    //   429: invokespecial 468	uuuuuu/ssssst:ba006100610061a0061aa0061a	()V
    //   432: return
    //   433: astore 5
    //   435: aload 5
    //   437: invokevirtual 104	java/lang/reflect/InvocationTargetException:getCause	()Ljava/lang/Throwable;
    //   440: athrow
    //   441: astore 5
    //   443: aload 5
    //   445: invokevirtual 104	java/lang/reflect/InvocationTargetException:getCause	()Ljava/lang/Throwable;
    //   448: athrow
    //   449: astore 5
    //   451: aload 5
    //   453: invokevirtual 104	java/lang/reflect/InvocationTargetException:getCause	()Ljava/lang/Throwable;
    //   456: athrow
    //   457: astore 5
    //   459: aload 5
    //   461: invokevirtual 104	java/lang/reflect/InvocationTargetException:getCause	()Ljava/lang/Throwable;
    //   464: athrow
    //   465: astore 5
    //   467: aload 5
    //   469: invokevirtual 104	java/lang/reflect/InvocationTargetException:getCause	()Ljava/lang/Throwable;
    //   472: athrow
    //   473: astore 5
    //   475: aload 5
    //   477: invokevirtual 104	java/lang/reflect/InvocationTargetException:getCause	()Ljava/lang/Throwable;
    //   480: athrow
    // Local variable table:
    //   start	length	slot	name	signature
    //   0	481	0	this	ononoo
    //   64	273	1	i	int
    //   132	134	2	j	int
    //   136	131	3	k	int
    //   140	11	4	m	int
    //   21	398	5	localObject1	Object
    //   433	3	5	localInvocationTargetException1	java.lang.reflect.InvocationTargetException
    //   441	3	5	localInvocationTargetException2	java.lang.reflect.InvocationTargetException
    //   449	3	5	localInvocationTargetException3	java.lang.reflect.InvocationTargetException
    //   457	3	5	localInvocationTargetException4	java.lang.reflect.InvocationTargetException
    //   465	3	5	localInvocationTargetException5	java.lang.reflect.InvocationTargetException
    //   473	3	5	localInvocationTargetException6	java.lang.reflect.InvocationTargetException
    //   87	306	6	localObject2	Object
    // Exception table:
    //   from	to	target	type
    //   380	392	433	java/lang/reflect/InvocationTargetException
    //   303	315	441	java/lang/reflect/InvocationTargetException
    //   23	34	449	java/lang/reflect/InvocationTargetException
    //   89	101	457	java/lang/reflect/InvocationTargetException
    //   195	207	465	java/lang/reflect/InvocationTargetException
    //   239	251	473	java/lang/reflect/InvocationTargetException
  }
  
  /* Error */
  public void ba00610061aaa0061a0061a()
  {
    // Byte code:
    //   0: ldc 2
    //   2: ldc_w 471
    //   5: bipush 58
    //   7: bipush 53
    //   9: iconst_0
    //   10: invokestatic 115	xxxxxx/uxxxxx:bbbb0062b0062b0062b0062	(Ljava/lang/String;CCC)Ljava/lang/String;
    //   13: iconst_0
    //   14: anewarray 77	java/lang/Class
    //   17: invokevirtual 81	java/lang/Class:getMethod	(Ljava/lang/String;[Ljava/lang/Class;)Ljava/lang/reflect/Method;
    //   20: astore 8
    //   22: aload 8
    //   24: aload_0
    //   25: iconst_0
    //   26: anewarray 83	java/lang/Object
    //   29: invokevirtual 89	java/lang/reflect/Method:invoke	(Ljava/lang/Object;[Ljava/lang/Object;)Ljava/lang/Object;
    //   32: pop
    //   33: getstatic 61	uuuuuu/ononoo:bn006E006En006Enn006E006E	I
    //   36: istore_1
    //   37: getstatic 63	uuuuuu/ononoo:bnnn006E006Enn006E006E	I
    //   40: istore_2
    //   41: getstatic 61	uuuuuu/ononoo:bn006E006En006Enn006E006E	I
    //   44: istore_3
    //   45: getstatic 61	uuuuuu/ononoo:bn006E006En006Enn006E006E	I
    //   48: istore 4
    //   50: getstatic 63	uuuuuu/ononoo:bnnn006E006Enn006E006E	I
    //   53: istore 5
    //   55: getstatic 61	uuuuuu/ononoo:bn006E006En006Enn006E006E	I
    //   58: istore 6
    //   60: getstatic 65	uuuuuu/ononoo:b006Enn006E006Enn006E006E	I
    //   63: istore 7
    //   65: ldc 2
    //   67: ldc_w 473
    //   70: sipush 222
    //   73: iconst_5
    //   74: iconst_0
    //   75: invokestatic 115	xxxxxx/uxxxxx:bbbb0062b0062b0062b0062	(Ljava/lang/String;CCC)Ljava/lang/String;
    //   78: iconst_0
    //   79: anewarray 77	java/lang/Class
    //   82: invokevirtual 81	java/lang/Class:getMethod	(Ljava/lang/String;[Ljava/lang/Class;)Ljava/lang/reflect/Method;
    //   85: astore 8
    //   87: aload 8
    //   89: aconst_null
    //   90: iconst_0
    //   91: anewarray 83	java/lang/Object
    //   94: invokevirtual 89	java/lang/reflect/Method:invoke	(Ljava/lang/Object;[Ljava/lang/Object;)Ljava/lang/Object;
    //   97: astore 8
    //   99: iload 4
    //   101: iload 5
    //   103: iadd
    //   104: iload 6
    //   106: imul
    //   107: iload 7
    //   109: irem
    //   110: aload 8
    //   112: checkcast 91	java/lang/Integer
    //   115: invokevirtual 94	java/lang/Integer:intValue	()I
    //   118: if_icmpeq +91 -> 209
    //   121: ldc 2
    //   123: ldc_w 430
    //   126: sipush 254
    //   129: iconst_1
    //   130: invokestatic 75	xxxxxx/uxxxxx:bb00620062bb0062b0062b0062	(Ljava/lang/String;CC)Ljava/lang/String;
    //   133: iconst_0
    //   134: anewarray 77	java/lang/Class
    //   137: invokevirtual 81	java/lang/Class:getMethod	(Ljava/lang/String;[Ljava/lang/Class;)Ljava/lang/reflect/Method;
    //   140: astore 8
    //   142: aload 8
    //   144: aconst_null
    //   145: iconst_0
    //   146: anewarray 83	java/lang/Object
    //   149: invokevirtual 89	java/lang/reflect/Method:invoke	(Ljava/lang/Object;[Ljava/lang/Object;)Ljava/lang/Object;
    //   152: astore 8
    //   154: aload 8
    //   156: checkcast 91	java/lang/Integer
    //   159: invokevirtual 94	java/lang/Integer:intValue	()I
    //   162: putstatic 61	uuuuuu/ononoo:bn006E006En006Enn006E006E	I
    //   165: ldc 2
    //   167: ldc_w 260
    //   170: sipush 190
    //   173: iconst_1
    //   174: invokestatic 75	xxxxxx/uxxxxx:bb00620062bb0062b0062b0062	(Ljava/lang/String;CC)Ljava/lang/String;
    //   177: iconst_0
    //   178: anewarray 77	java/lang/Class
    //   181: invokevirtual 81	java/lang/Class:getMethod	(Ljava/lang/String;[Ljava/lang/Class;)Ljava/lang/reflect/Method;
    //   184: astore 8
    //   186: aload 8
    //   188: aconst_null
    //   189: iconst_0
    //   190: anewarray 83	java/lang/Object
    //   193: invokevirtual 89	java/lang/reflect/Method:invoke	(Ljava/lang/Object;[Ljava/lang/Object;)Ljava/lang/Object;
    //   196: astore 8
    //   198: aload 8
    //   200: checkcast 91	java/lang/Integer
    //   203: invokevirtual 94	java/lang/Integer:intValue	()I
    //   206: putstatic 67	uuuuuu/ononoo:b006E006E006En006Enn006E006E	I
    //   209: getstatic 65	uuuuuu/ononoo:b006Enn006E006Enn006E006E	I
    //   212: istore 4
    //   214: getstatic 67	uuuuuu/ononoo:b006E006E006En006Enn006E006E	I
    //   217: istore 5
    //   219: getstatic 61	uuuuuu/ononoo:bn006E006En006Enn006E006E	I
    //   222: istore 6
    //   224: getstatic 63	uuuuuu/ononoo:bnnn006E006Enn006E006E	I
    //   227: istore 7
    //   229: ldc 2
    //   231: ldc_w 475
    //   234: bipush 32
    //   236: iconst_4
    //   237: invokestatic 75	xxxxxx/uxxxxx:bb00620062bb0062b0062b0062	(Ljava/lang/String;CC)Ljava/lang/String;
    //   240: iconst_0
    //   241: anewarray 77	java/lang/Class
    //   244: invokevirtual 81	java/lang/Class:getMethod	(Ljava/lang/String;[Ljava/lang/Class;)Ljava/lang/reflect/Method;
    //   247: astore 8
    //   249: aload 8
    //   251: aconst_null
    //   252: iconst_0
    //   253: anewarray 83	java/lang/Object
    //   256: invokevirtual 89	java/lang/reflect/Method:invoke	(Ljava/lang/Object;[Ljava/lang/Object;)Ljava/lang/Object;
    //   259: astore 8
    //   261: iload 7
    //   263: iload 6
    //   265: iadd
    //   266: iload 6
    //   268: imul
    //   269: aload 8
    //   271: checkcast 91	java/lang/Integer
    //   274: invokevirtual 94	java/lang/Integer:intValue	()I
    //   277: irem
    //   278: tableswitch	default:+18->296, 0:+109->387
    //   296: ldc 2
    //   298: ldc_w 477
    //   301: bipush 13
    //   303: bipush 47
    //   305: iconst_3
    //   306: invokestatic 115	xxxxxx/uxxxxx:bbbb0062b0062b0062b0062	(Ljava/lang/String;CCC)Ljava/lang/String;
    //   309: iconst_0
    //   310: anewarray 77	java/lang/Class
    //   313: invokevirtual 81	java/lang/Class:getMethod	(Ljava/lang/String;[Ljava/lang/Class;)Ljava/lang/reflect/Method;
    //   316: astore 8
    //   318: aload 8
    //   320: aconst_null
    //   321: iconst_0
    //   322: anewarray 83	java/lang/Object
    //   325: invokevirtual 89	java/lang/reflect/Method:invoke	(Ljava/lang/Object;[Ljava/lang/Object;)Ljava/lang/Object;
    //   328: astore 8
    //   330: aload 8
    //   332: checkcast 91	java/lang/Integer
    //   335: invokevirtual 94	java/lang/Integer:intValue	()I
    //   338: putstatic 61	uuuuuu/ononoo:bn006E006En006Enn006E006E	I
    //   341: ldc 2
    //   343: ldc_w 479
    //   346: bipush 43
    //   348: sipush 181
    //   351: iconst_1
    //   352: invokestatic 115	xxxxxx/uxxxxx:bbbb0062b0062b0062b0062	(Ljava/lang/String;CCC)Ljava/lang/String;
    //   355: iconst_0
    //   356: anewarray 77	java/lang/Class
    //   359: invokevirtual 81	java/lang/Class:getMethod	(Ljava/lang/String;[Ljava/lang/Class;)Ljava/lang/reflect/Method;
    //   362: astore 8
    //   364: aload 8
    //   366: aconst_null
    //   367: iconst_0
    //   368: anewarray 83	java/lang/Object
    //   371: invokevirtual 89	java/lang/reflect/Method:invoke	(Ljava/lang/Object;[Ljava/lang/Object;)Ljava/lang/Object;
    //   374: astore 8
    //   376: aload 8
    //   378: checkcast 91	java/lang/Integer
    //   381: invokevirtual 94	java/lang/Integer:intValue	()I
    //   384: putstatic 67	uuuuuu/ononoo:b006E006E006En006Enn006E006E	I
    //   387: iload_2
    //   388: iload_1
    //   389: iadd
    //   390: iload_3
    //   391: imul
    //   392: iload 4
    //   394: irem
    //   395: iload 5
    //   397: if_icmpeq +246 -> 643
    //   400: ldc 2
    //   402: ldc_w 481
    //   405: sipush 179
    //   408: iconst_3
    //   409: invokestatic 75	xxxxxx/uxxxxx:bb00620062bb0062b0062b0062	(Ljava/lang/String;CC)Ljava/lang/String;
    //   412: iconst_0
    //   413: anewarray 77	java/lang/Class
    //   416: invokevirtual 81	java/lang/Class:getMethod	(Ljava/lang/String;[Ljava/lang/Class;)Ljava/lang/reflect/Method;
    //   419: astore 8
    //   421: aload 8
    //   423: aconst_null
    //   424: iconst_0
    //   425: anewarray 83	java/lang/Object
    //   428: invokevirtual 89	java/lang/reflect/Method:invoke	(Ljava/lang/Object;[Ljava/lang/Object;)Ljava/lang/Object;
    //   431: astore 8
    //   433: aload 8
    //   435: checkcast 91	java/lang/Integer
    //   438: invokevirtual 94	java/lang/Integer:intValue	()I
    //   441: istore_1
    //   442: getstatic 63	uuuuuu/ononoo:bnnn006E006Enn006E006E	I
    //   445: istore_2
    //   446: ldc 2
    //   448: ldc_w 483
    //   451: sipush 186
    //   454: bipush 81
    //   456: iconst_3
    //   457: invokestatic 115	xxxxxx/uxxxxx:bbbb0062b0062b0062b0062	(Ljava/lang/String;CCC)Ljava/lang/String;
    //   460: iconst_0
    //   461: anewarray 77	java/lang/Class
    //   464: invokevirtual 81	java/lang/Class:getMethod	(Ljava/lang/String;[Ljava/lang/Class;)Ljava/lang/reflect/Method;
    //   467: astore 8
    //   469: aload 8
    //   471: aconst_null
    //   472: iconst_0
    //   473: anewarray 83	java/lang/Object
    //   476: invokevirtual 89	java/lang/reflect/Method:invoke	(Ljava/lang/Object;[Ljava/lang/Object;)Ljava/lang/Object;
    //   479: astore 8
    //   481: aload 8
    //   483: checkcast 91	java/lang/Integer
    //   486: invokevirtual 94	java/lang/Integer:intValue	()I
    //   489: iload_2
    //   490: iload_1
    //   491: iadd
    //   492: imul
    //   493: getstatic 65	uuuuuu/ononoo:b006Enn006E006Enn006E006E	I
    //   496: irem
    //   497: getstatic 67	uuuuuu/ononoo:b006E006E006En006Enn006E006E	I
    //   500: if_icmpeq +51 -> 551
    //   503: ldc 2
    //   505: ldc_w 260
    //   508: bipush 126
    //   510: iconst_2
    //   511: invokestatic 75	xxxxxx/uxxxxx:bb00620062bb0062b0062b0062	(Ljava/lang/String;CC)Ljava/lang/String;
    //   514: iconst_0
    //   515: anewarray 77	java/lang/Class
    //   518: invokevirtual 81	java/lang/Class:getMethod	(Ljava/lang/String;[Ljava/lang/Class;)Ljava/lang/reflect/Method;
    //   521: astore 8
    //   523: aload 8
    //   525: aconst_null
    //   526: iconst_0
    //   527: anewarray 83	java/lang/Object
    //   530: invokevirtual 89	java/lang/reflect/Method:invoke	(Ljava/lang/Object;[Ljava/lang/Object;)Ljava/lang/Object;
    //   533: astore 8
    //   535: aload 8
    //   537: checkcast 91	java/lang/Integer
    //   540: invokevirtual 94	java/lang/Integer:intValue	()I
    //   543: putstatic 61	uuuuuu/ononoo:bn006E006En006Enn006E006E	I
    //   546: bipush 64
    //   548: putstatic 67	uuuuuu/ononoo:b006E006E006En006Enn006E006E	I
    //   551: ldc 2
    //   553: ldc_w 485
    //   556: sipush 137
    //   559: sipush 216
    //   562: iconst_2
    //   563: invokestatic 115	xxxxxx/uxxxxx:bbbb0062b0062b0062b0062	(Ljava/lang/String;CCC)Ljava/lang/String;
    //   566: iconst_0
    //   567: anewarray 77	java/lang/Class
    //   570: invokevirtual 81	java/lang/Class:getMethod	(Ljava/lang/String;[Ljava/lang/Class;)Ljava/lang/reflect/Method;
    //   573: astore 8
    //   575: aload 8
    //   577: aconst_null
    //   578: iconst_0
    //   579: anewarray 83	java/lang/Object
    //   582: invokevirtual 89	java/lang/reflect/Method:invoke	(Ljava/lang/Object;[Ljava/lang/Object;)Ljava/lang/Object;
    //   585: astore 8
    //   587: aload 8
    //   589: checkcast 91	java/lang/Integer
    //   592: invokevirtual 94	java/lang/Integer:intValue	()I
    //   595: putstatic 61	uuuuuu/ononoo:bn006E006En006Enn006E006E	I
    //   598: ldc 2
    //   600: ldc_w 487
    //   603: bipush 101
    //   605: bipush 54
    //   607: iconst_2
    //   608: invokestatic 115	xxxxxx/uxxxxx:bbbb0062b0062b0062b0062	(Ljava/lang/String;CCC)Ljava/lang/String;
    //   611: iconst_0
    //   612: anewarray 77	java/lang/Class
    //   615: invokevirtual 81	java/lang/Class:getMethod	(Ljava/lang/String;[Ljava/lang/Class;)Ljava/lang/reflect/Method;
    //   618: astore 8
    //   620: aload 8
    //   622: aconst_null
    //   623: iconst_0
    //   624: anewarray 83	java/lang/Object
    //   627: invokevirtual 89	java/lang/reflect/Method:invoke	(Ljava/lang/Object;[Ljava/lang/Object;)Ljava/lang/Object;
    //   630: astore 8
    //   632: aload 8
    //   634: checkcast 91	java/lang/Integer
    //   637: invokevirtual 94	java/lang/Integer:intValue	()I
    //   640: putstatic 67	uuuuuu/ononoo:b006E006E006En006Enn006E006E	I
    //   643: return
    //   644: astore 8
    //   646: aload 8
    //   648: invokevirtual 104	java/lang/reflect/InvocationTargetException:getCause	()Ljava/lang/Throwable;
    //   651: athrow
    //   652: astore 8
    //   654: aload 8
    //   656: invokevirtual 104	java/lang/reflect/InvocationTargetException:getCause	()Ljava/lang/Throwable;
    //   659: athrow
    //   660: astore 8
    //   662: aload 8
    //   664: invokevirtual 104	java/lang/reflect/InvocationTargetException:getCause	()Ljava/lang/Throwable;
    //   667: athrow
    //   668: astore 8
    //   670: aload 8
    //   672: invokevirtual 104	java/lang/reflect/InvocationTargetException:getCause	()Ljava/lang/Throwable;
    //   675: athrow
    //   676: astore 8
    //   678: aload 8
    //   680: invokevirtual 104	java/lang/reflect/InvocationTargetException:getCause	()Ljava/lang/Throwable;
    //   683: athrow
    //   684: astore 8
    //   686: aload 8
    //   688: invokevirtual 104	java/lang/reflect/InvocationTargetException:getCause	()Ljava/lang/Throwable;
    //   691: athrow
    //   692: astore 8
    //   694: aload 8
    //   696: invokevirtual 104	java/lang/reflect/InvocationTargetException:getCause	()Ljava/lang/Throwable;
    //   699: athrow
    //   700: astore 8
    //   702: aload 8
    //   704: invokevirtual 104	java/lang/reflect/InvocationTargetException:getCause	()Ljava/lang/Throwable;
    //   707: athrow
    //   708: astore 8
    //   710: aload 8
    //   712: invokevirtual 104	java/lang/reflect/InvocationTargetException:getCause	()Ljava/lang/Throwable;
    //   715: athrow
    //   716: astore 8
    //   718: aload 8
    //   720: invokevirtual 104	java/lang/reflect/InvocationTargetException:getCause	()Ljava/lang/Throwable;
    //   723: athrow
    //   724: astore 8
    //   726: aload 8
    //   728: invokevirtual 104	java/lang/reflect/InvocationTargetException:getCause	()Ljava/lang/Throwable;
    //   731: athrow
    //   732: astore 8
    //   734: aload 8
    //   736: invokevirtual 104	java/lang/reflect/InvocationTargetException:getCause	()Ljava/lang/Throwable;
    //   739: athrow
    // Local variable table:
    //   start	length	slot	name	signature
    //   0	740	0	this	ononoo
    //   36	456	1	i	int
    //   40	452	2	j	int
    //   44	348	3	k	int
    //   48	347	4	m	int
    //   53	345	5	n	int
    //   58	211	6	i1	int
    //   63	203	7	i2	int
    //   20	613	8	localObject	Object
    //   644	3	8	localInvocationTargetException1	java.lang.reflect.InvocationTargetException
    //   652	3	8	localInvocationTargetException2	java.lang.reflect.InvocationTargetException
    //   660	3	8	localInvocationTargetException3	java.lang.reflect.InvocationTargetException
    //   668	3	8	localInvocationTargetException4	java.lang.reflect.InvocationTargetException
    //   676	3	8	localInvocationTargetException5	java.lang.reflect.InvocationTargetException
    //   684	3	8	localInvocationTargetException6	java.lang.reflect.InvocationTargetException
    //   692	3	8	localInvocationTargetException7	java.lang.reflect.InvocationTargetException
    //   700	3	8	localInvocationTargetException8	java.lang.reflect.InvocationTargetException
    //   708	3	8	localInvocationTargetException9	java.lang.reflect.InvocationTargetException
    //   716	3	8	localInvocationTargetException10	java.lang.reflect.InvocationTargetException
    //   724	3	8	localInvocationTargetException11	java.lang.reflect.InvocationTargetException
    //   732	3	8	localInvocationTargetException12	java.lang.reflect.InvocationTargetException
    // Exception table:
    //   from	to	target	type
    //   469	481	644	java/lang/reflect/InvocationTargetException
    //   249	261	652	java/lang/reflect/InvocationTargetException
    //   421	433	660	java/lang/reflect/InvocationTargetException
    //   22	33	668	java/lang/reflect/InvocationTargetException
    //   87	99	676	java/lang/reflect/InvocationTargetException
    //   575	587	684	java/lang/reflect/InvocationTargetException
    //   620	632	692	java/lang/reflect/InvocationTargetException
    //   318	330	700	java/lang/reflect/InvocationTargetException
    //   364	376	708	java/lang/reflect/InvocationTargetException
    //   523	535	716	java/lang/reflect/InvocationTargetException
    //   142	154	724	java/lang/reflect/InvocationTargetException
    //   186	198	732	java/lang/reflect/InvocationTargetException
  }
  
  public void baaa0061aa0061a0061a() {}
  
  /* Error */
  public void bk006B006B006B006Bk006B006B006Bk()
  {
    // Byte code:
    //   0: getstatic 61	uuuuuu/ononoo:bn006E006En006Enn006E006E	I
    //   3: istore_1
    //   4: getstatic 63	uuuuuu/ononoo:bnnn006E006Enn006E006E	I
    //   7: istore_2
    //   8: getstatic 61	uuuuuu/ononoo:bn006E006En006Enn006E006E	I
    //   11: istore_3
    //   12: ldc 2
    //   14: ldc_w 507
    //   17: sipush 254
    //   20: sipush 237
    //   23: iconst_1
    //   24: invokestatic 115	xxxxxx/uxxxxx:bbbb0062b0062b0062b0062	(Ljava/lang/String;CCC)Ljava/lang/String;
    //   27: iconst_0
    //   28: anewarray 77	java/lang/Class
    //   31: invokevirtual 81	java/lang/Class:getMethod	(Ljava/lang/String;[Ljava/lang/Class;)Ljava/lang/reflect/Method;
    //   34: astore 4
    //   36: aload 4
    //   38: aconst_null
    //   39: iconst_0
    //   40: anewarray 83	java/lang/Object
    //   43: invokevirtual 89	java/lang/reflect/Method:invoke	(Ljava/lang/Object;[Ljava/lang/Object;)Ljava/lang/Object;
    //   46: astore 4
    //   48: iload_3
    //   49: iload_1
    //   50: iload_2
    //   51: iadd
    //   52: imul
    //   53: aload 4
    //   55: checkcast 91	java/lang/Integer
    //   58: invokevirtual 94	java/lang/Integer:intValue	()I
    //   61: irem
    //   62: getstatic 67	uuuuuu/ononoo:b006E006E006En006Enn006E006E	I
    //   65: if_icmpeq +269 -> 334
    //   68: getstatic 61	uuuuuu/ononoo:bn006E006En006Enn006E006E	I
    //   71: istore_1
    //   72: getstatic 63	uuuuuu/ononoo:bnnn006E006Enn006E006E	I
    //   75: istore_2
    //   76: getstatic 61	uuuuuu/ononoo:bn006E006En006Enn006E006E	I
    //   79: getstatic 63	uuuuuu/ononoo:bnnn006E006Enn006E006E	I
    //   82: iadd
    //   83: getstatic 61	uuuuuu/ononoo:bn006E006En006Enn006E006E	I
    //   86: imul
    //   87: getstatic 65	uuuuuu/ononoo:b006Enn006E006Enn006E006E	I
    //   90: irem
    //   91: getstatic 67	uuuuuu/ononoo:b006E006E006En006Enn006E006E	I
    //   94: if_icmpeq +13 -> 107
    //   97: bipush 26
    //   99: putstatic 61	uuuuuu/ononoo:bn006E006En006Enn006E006E	I
    //   102: bipush 47
    //   104: putstatic 67	uuuuuu/ononoo:b006E006E006En006Enn006E006E	I
    //   107: iload_1
    //   108: iload_2
    //   109: iadd
    //   110: getstatic 61	uuuuuu/ononoo:bn006E006En006Enn006E006E	I
    //   113: imul
    //   114: getstatic 65	uuuuuu/ononoo:b006Enn006E006Enn006E006E	I
    //   117: irem
    //   118: getstatic 67	uuuuuu/ononoo:b006E006E006En006Enn006E006E	I
    //   121: if_icmpeq +123 -> 244
    //   124: bipush 30
    //   126: putstatic 61	uuuuuu/ononoo:bn006E006En006Enn006E006E	I
    //   129: bipush 91
    //   131: putstatic 67	uuuuuu/ononoo:b006E006E006En006Enn006E006E	I
    //   134: getstatic 61	uuuuuu/ononoo:bn006E006En006Enn006E006E	I
    //   137: istore_1
    //   138: ldc 2
    //   140: ldc_w 509
    //   143: iconst_3
    //   144: bipush 12
    //   146: iconst_0
    //   147: invokestatic 115	xxxxxx/uxxxxx:bbbb0062b0062b0062b0062	(Ljava/lang/String;CCC)Ljava/lang/String;
    //   150: iconst_0
    //   151: anewarray 77	java/lang/Class
    //   154: invokevirtual 81	java/lang/Class:getMethod	(Ljava/lang/String;[Ljava/lang/Class;)Ljava/lang/reflect/Method;
    //   157: astore 4
    //   159: aload 4
    //   161: aconst_null
    //   162: iconst_0
    //   163: anewarray 83	java/lang/Object
    //   166: invokevirtual 89	java/lang/reflect/Method:invoke	(Ljava/lang/Object;[Ljava/lang/Object;)Ljava/lang/Object;
    //   169: astore 4
    //   171: aload 4
    //   173: checkcast 91	java/lang/Integer
    //   176: invokevirtual 94	java/lang/Integer:intValue	()I
    //   179: iload_1
    //   180: iadd
    //   181: getstatic 61	uuuuuu/ononoo:bn006E006En006Enn006E006E	I
    //   184: imul
    //   185: getstatic 65	uuuuuu/ononoo:b006Enn006E006Enn006E006E	I
    //   188: irem
    //   189: getstatic 67	uuuuuu/ononoo:b006E006E006En006Enn006E006E	I
    //   192: if_icmpeq +52 -> 244
    //   195: bipush 36
    //   197: putstatic 61	uuuuuu/ononoo:bn006E006En006Enn006E006E	I
    //   200: ldc 2
    //   202: ldc_w 436
    //   205: sipush 176
    //   208: iconst_3
    //   209: invokestatic 75	xxxxxx/uxxxxx:bb00620062bb0062b0062b0062	(Ljava/lang/String;CC)Ljava/lang/String;
    //   212: iconst_0
    //   213: anewarray 77	java/lang/Class
    //   216: invokevirtual 81	java/lang/Class:getMethod	(Ljava/lang/String;[Ljava/lang/Class;)Ljava/lang/reflect/Method;
    //   219: astore 4
    //   221: aload 4
    //   223: aconst_null
    //   224: iconst_0
    //   225: anewarray 83	java/lang/Object
    //   228: invokevirtual 89	java/lang/reflect/Method:invoke	(Ljava/lang/Object;[Ljava/lang/Object;)Ljava/lang/Object;
    //   231: astore 4
    //   233: aload 4
    //   235: checkcast 91	java/lang/Integer
    //   238: invokevirtual 94	java/lang/Integer:intValue	()I
    //   241: putstatic 67	uuuuuu/ononoo:b006E006E006En006Enn006E006E	I
    //   244: ldc 2
    //   246: ldc_w 511
    //   249: bipush 93
    //   251: sipush 247
    //   254: iconst_3
    //   255: invokestatic 115	xxxxxx/uxxxxx:bbbb0062b0062b0062b0062	(Ljava/lang/String;CCC)Ljava/lang/String;
    //   258: iconst_0
    //   259: anewarray 77	java/lang/Class
    //   262: invokevirtual 81	java/lang/Class:getMethod	(Ljava/lang/String;[Ljava/lang/Class;)Ljava/lang/reflect/Method;
    //   265: astore 4
    //   267: aload 4
    //   269: aconst_null
    //   270: iconst_0
    //   271: anewarray 83	java/lang/Object
    //   274: invokevirtual 89	java/lang/reflect/Method:invoke	(Ljava/lang/Object;[Ljava/lang/Object;)Ljava/lang/Object;
    //   277: astore 4
    //   279: aload 4
    //   281: checkcast 91	java/lang/Integer
    //   284: invokevirtual 94	java/lang/Integer:intValue	()I
    //   287: putstatic 61	uuuuuu/ononoo:bn006E006En006Enn006E006E	I
    //   290: ldc 2
    //   292: ldc_w 513
    //   295: sipush 224
    //   298: iconst_1
    //   299: invokestatic 75	xxxxxx/uxxxxx:bb00620062bb0062b0062b0062	(Ljava/lang/String;CC)Ljava/lang/String;
    //   302: iconst_0
    //   303: anewarray 77	java/lang/Class
    //   306: invokevirtual 81	java/lang/Class:getMethod	(Ljava/lang/String;[Ljava/lang/Class;)Ljava/lang/reflect/Method;
    //   309: astore 4
    //   311: aload 4
    //   313: aconst_null
    //   314: iconst_0
    //   315: anewarray 83	java/lang/Object
    //   318: invokevirtual 89	java/lang/reflect/Method:invoke	(Ljava/lang/Object;[Ljava/lang/Object;)Ljava/lang/Object;
    //   321: astore 4
    //   323: aload 4
    //   325: checkcast 91	java/lang/Integer
    //   328: invokevirtual 94	java/lang/Integer:intValue	()I
    //   331: putstatic 67	uuuuuu/ononoo:b006E006E006En006Enn006E006E	I
    //   334: ldc 2
    //   336: ldc_w 515
    //   339: bipush 50
    //   341: iconst_5
    //   342: invokestatic 75	xxxxxx/uxxxxx:bb00620062bb0062b0062b0062	(Ljava/lang/String;CC)Ljava/lang/String;
    //   345: iconst_0
    //   346: anewarray 77	java/lang/Class
    //   349: invokevirtual 81	java/lang/Class:getMethod	(Ljava/lang/String;[Ljava/lang/Class;)Ljava/lang/reflect/Method;
    //   352: astore 4
    //   354: aload 4
    //   356: aload_0
    //   357: iconst_0
    //   358: anewarray 83	java/lang/Object
    //   361: invokevirtual 89	java/lang/reflect/Method:invoke	(Ljava/lang/Object;[Ljava/lang/Object;)Ljava/lang/Object;
    //   364: pop
    //   365: return
    //   366: astore 4
    //   368: aload 4
    //   370: invokevirtual 104	java/lang/reflect/InvocationTargetException:getCause	()Ljava/lang/Throwable;
    //   373: athrow
    //   374: astore 4
    //   376: aload 4
    //   378: invokevirtual 104	java/lang/reflect/InvocationTargetException:getCause	()Ljava/lang/Throwable;
    //   381: athrow
    //   382: astore 4
    //   384: aload 4
    //   386: invokevirtual 104	java/lang/reflect/InvocationTargetException:getCause	()Ljava/lang/Throwable;
    //   389: athrow
    //   390: astore 4
    //   392: aload 4
    //   394: invokevirtual 104	java/lang/reflect/InvocationTargetException:getCause	()Ljava/lang/Throwable;
    //   397: athrow
    //   398: astore 4
    //   400: aload 4
    //   402: invokevirtual 104	java/lang/reflect/InvocationTargetException:getCause	()Ljava/lang/Throwable;
    //   405: athrow
    //   406: astore 4
    //   408: aload 4
    //   410: invokevirtual 104	java/lang/reflect/InvocationTargetException:getCause	()Ljava/lang/Throwable;
    //   413: athrow
    // Local variable table:
    //   start	length	slot	name	signature
    //   0	414	0	this	ononoo
    //   3	178	1	i	int
    //   7	103	2	j	int
    //   11	42	3	k	int
    //   34	321	4	localObject	Object
    //   366	3	4	localInvocationTargetException1	java.lang.reflect.InvocationTargetException
    //   374	3	4	localInvocationTargetException2	java.lang.reflect.InvocationTargetException
    //   382	3	4	localInvocationTargetException3	java.lang.reflect.InvocationTargetException
    //   390	3	4	localInvocationTargetException4	java.lang.reflect.InvocationTargetException
    //   398	3	4	localInvocationTargetException5	java.lang.reflect.InvocationTargetException
    //   406	3	4	localInvocationTargetException6	java.lang.reflect.InvocationTargetException
    // Exception table:
    //   from	to	target	type
    //   267	279	366	java/lang/reflect/InvocationTargetException
    //   311	323	374	java/lang/reflect/InvocationTargetException
    //   354	365	382	java/lang/reflect/InvocationTargetException
    //   36	48	390	java/lang/reflect/InvocationTargetException
    //   159	171	398	java/lang/reflect/InvocationTargetException
    //   221	233	406	java/lang/reflect/InvocationTargetException
  }
  
  /* Error */
  public boolean bk006B006B006Bk006B006B006B006Bk()
  {
    // Byte code:
    //   0: aload_0
    //   1: getfield 518	uuuuuu/ononoo:b006Ennn006Enn006E006E	Luuuuuu/sssttt;
    //   4: getstatic 524	com/db/pwcc/dbmobile/foundation/features/Feature:FINGERPRINT	Lcom/db/pwcc/dbmobile/foundation/features/Feature;
    //   7: invokevirtual 530	uuuuuu/sssttt:bk006Bkkk006B006B006Bkk	(Lcom/db/pwcc/dbmobile/foundation/features/Feature;)Luuuuuu/sststt;
    //   10: astore_3
    //   11: getstatic 536	uuuuuu/sststt:b006En006En006Enn006En	Luuuuuu/sststt;
    //   14: astore 4
    //   16: getstatic 61	uuuuuu/ononoo:bn006E006En006Enn006E006E	I
    //   19: istore_1
    //   20: getstatic 63	uuuuuu/ononoo:bnnn006E006Enn006E006E	I
    //   23: istore_2
    //   24: ldc 2
    //   26: ldc_w 538
    //   29: bipush 67
    //   31: iconst_5
    //   32: invokestatic 75	xxxxxx/uxxxxx:bb00620062bb0062b0062b0062	(Ljava/lang/String;CC)Ljava/lang/String;
    //   35: iconst_0
    //   36: anewarray 77	java/lang/Class
    //   39: invokevirtual 81	java/lang/Class:getMethod	(Ljava/lang/String;[Ljava/lang/Class;)Ljava/lang/reflect/Method;
    //   42: astore 5
    //   44: aload 5
    //   46: aconst_null
    //   47: iconst_0
    //   48: anewarray 83	java/lang/Object
    //   51: invokevirtual 89	java/lang/reflect/Method:invoke	(Ljava/lang/Object;[Ljava/lang/Object;)Ljava/lang/Object;
    //   54: astore 5
    //   56: iload_2
    //   57: iload_1
    //   58: iadd
    //   59: iload_1
    //   60: imul
    //   61: aload 5
    //   63: checkcast 91	java/lang/Integer
    //   66: invokevirtual 94	java/lang/Integer:intValue	()I
    //   69: irem
    //   70: tableswitch	default:+18->88, 0:+105->175
    //   88: ldc 2
    //   90: ldc_w 540
    //   93: sipush 229
    //   96: iconst_0
    //   97: invokestatic 75	xxxxxx/uxxxxx:bb00620062bb0062b0062b0062	(Ljava/lang/String;CC)Ljava/lang/String;
    //   100: iconst_0
    //   101: anewarray 77	java/lang/Class
    //   104: invokevirtual 81	java/lang/Class:getMethod	(Ljava/lang/String;[Ljava/lang/Class;)Ljava/lang/reflect/Method;
    //   107: astore 5
    //   109: aload 5
    //   111: aconst_null
    //   112: iconst_0
    //   113: anewarray 83	java/lang/Object
    //   116: invokevirtual 89	java/lang/reflect/Method:invoke	(Ljava/lang/Object;[Ljava/lang/Object;)Ljava/lang/Object;
    //   119: astore 5
    //   121: aload 5
    //   123: checkcast 91	java/lang/Integer
    //   126: invokevirtual 94	java/lang/Integer:intValue	()I
    //   129: putstatic 61	uuuuuu/ononoo:bn006E006En006Enn006E006E	I
    //   132: ldc 2
    //   134: ldc_w 542
    //   137: bipush 105
    //   139: iconst_2
    //   140: invokestatic 75	xxxxxx/uxxxxx:bb00620062bb0062b0062b0062	(Ljava/lang/String;CC)Ljava/lang/String;
    //   143: iconst_0
    //   144: anewarray 77	java/lang/Class
    //   147: invokevirtual 81	java/lang/Class:getMethod	(Ljava/lang/String;[Ljava/lang/Class;)Ljava/lang/reflect/Method;
    //   150: astore 5
    //   152: aload 5
    //   154: aconst_null
    //   155: iconst_0
    //   156: anewarray 83	java/lang/Object
    //   159: invokevirtual 89	java/lang/reflect/Method:invoke	(Ljava/lang/Object;[Ljava/lang/Object;)Ljava/lang/Object;
    //   162: astore 5
    //   164: aload 5
    //   166: checkcast 91	java/lang/Integer
    //   169: invokevirtual 94	java/lang/Integer:intValue	()I
    //   172: putstatic 67	uuuuuu/ononoo:b006E006E006En006Enn006E006E	I
    //   175: aload_3
    //   176: aload 4
    //   178: if_acmpne +111 -> 289
    //   181: getstatic 61	uuuuuu/ononoo:bn006E006En006Enn006E006E	I
    //   184: istore_1
    //   185: iload_1
    //   186: getstatic 63	uuuuuu/ononoo:bnnn006E006Enn006E006E	I
    //   189: iload_1
    //   190: iadd
    //   191: imul
    //   192: getstatic 65	uuuuuu/ononoo:b006Enn006E006Enn006E006E	I
    //   195: irem
    //   196: tableswitch	default:+20->216, 0:+30->226
    //   216: bipush 60
    //   218: putstatic 61	uuuuuu/ononoo:bn006E006En006Enn006E006E	I
    //   221: bipush 34
    //   223: putstatic 67	uuuuuu/ononoo:b006E006E006En006Enn006E006E	I
    //   226: aload_0
    //   227: invokevirtual 545	uuuuuu/ononoo:b006Bk006B006Bkk006Bk006Bk	()Z
    //   230: ifne +59 -> 289
    //   233: aload_0
    //   234: getfield 190	uuuuuu/ononoo:bn006Enn006Enn006E006E	Luuuuuu/onoono;
    //   237: astore_3
    //   238: getstatic 61	uuuuuu/ononoo:bn006E006En006Enn006E006E	I
    //   241: getstatic 63	uuuuuu/ononoo:bnnn006E006Enn006E006E	I
    //   244: iadd
    //   245: getstatic 61	uuuuuu/ononoo:bn006E006En006Enn006E006E	I
    //   248: imul
    //   249: getstatic 65	uuuuuu/ononoo:b006Enn006E006Enn006E006E	I
    //   252: irem
    //   253: getstatic 67	uuuuuu/ononoo:b006E006E006En006Enn006E006E	I
    //   256: if_icmpeq +12 -> 268
    //   259: iconst_1
    //   260: putstatic 61	uuuuuu/ononoo:bn006E006En006Enn006E006E	I
    //   263: bipush 99
    //   265: putstatic 67	uuuuuu/ononoo:b006E006E006En006Enn006E006E	I
    //   268: aload_3
    //   269: invokeinterface 548 1 0
    //   274: ifeq +15 -> 289
    //   277: aload_0
    //   278: getfield 194	uuuuuu/ononoo:b006E006E006E006E006En006E006En	Luuuuuu/hyhyhh;
    //   281: invokevirtual 199	uuuuuu/hyhyhh:b0070pp007000700070p007000700070	()Ljava/lang/String;
    //   284: ifnull +5 -> 289
    //   287: iconst_1
    //   288: ireturn
    //   289: getstatic 61	uuuuuu/ononoo:bn006E006En006Enn006E006E	I
    //   292: istore_1
    //   293: iload_1
    //   294: getstatic 63	uuuuuu/ononoo:bnnn006E006Enn006E006E	I
    //   297: iload_1
    //   298: iadd
    //   299: imul
    //   300: getstatic 65	uuuuuu/ononoo:b006Enn006E006Enn006E006E	I
    //   303: irem
    //   304: tableswitch	default:+20->324, 0:+67->371
    //   324: ldc 2
    //   326: ldc_w 550
    //   329: sipush 150
    //   332: bipush 55
    //   334: iconst_0
    //   335: invokestatic 115	xxxxxx/uxxxxx:bbbb0062b0062b0062b0062	(Ljava/lang/String;CCC)Ljava/lang/String;
    //   338: iconst_0
    //   339: anewarray 77	java/lang/Class
    //   342: invokevirtual 81	java/lang/Class:getMethod	(Ljava/lang/String;[Ljava/lang/Class;)Ljava/lang/reflect/Method;
    //   345: astore_3
    //   346: aload_3
    //   347: aconst_null
    //   348: iconst_0
    //   349: anewarray 83	java/lang/Object
    //   352: invokevirtual 89	java/lang/reflect/Method:invoke	(Ljava/lang/Object;[Ljava/lang/Object;)Ljava/lang/Object;
    //   355: astore_3
    //   356: aload_3
    //   357: checkcast 91	java/lang/Integer
    //   360: invokevirtual 94	java/lang/Integer:intValue	()I
    //   363: putstatic 61	uuuuuu/ononoo:bn006E006En006Enn006E006E	I
    //   366: bipush 99
    //   368: putstatic 67	uuuuuu/ononoo:b006E006E006En006Enn006E006E	I
    //   371: iconst_0
    //   372: ireturn
    //   373: astore_3
    //   374: aload_3
    //   375: invokevirtual 104	java/lang/reflect/InvocationTargetException:getCause	()Ljava/lang/Throwable;
    //   378: athrow
    //   379: astore_3
    //   380: aload_3
    //   381: invokevirtual 104	java/lang/reflect/InvocationTargetException:getCause	()Ljava/lang/Throwable;
    //   384: athrow
    //   385: astore_3
    //   386: aload_3
    //   387: invokevirtual 104	java/lang/reflect/InvocationTargetException:getCause	()Ljava/lang/Throwable;
    //   390: athrow
    //   391: astore_3
    //   392: aload_3
    //   393: invokevirtual 104	java/lang/reflect/InvocationTargetException:getCause	()Ljava/lang/Throwable;
    //   396: athrow
    // Local variable table:
    //   start	length	slot	name	signature
    //   0	397	0	this	ononoo
    //   19	281	1	i	int
    //   23	36	2	j	int
    //   10	347	3	localObject1	Object
    //   373	2	3	localInvocationTargetException1	java.lang.reflect.InvocationTargetException
    //   379	2	3	localInvocationTargetException2	java.lang.reflect.InvocationTargetException
    //   385	2	3	localInvocationTargetException3	java.lang.reflect.InvocationTargetException
    //   391	2	3	localInvocationTargetException4	java.lang.reflect.InvocationTargetException
    //   14	163	4	localSststt	sststt
    //   42	123	5	localObject2	Object
    // Exception table:
    //   from	to	target	type
    //   44	56	373	java/lang/reflect/InvocationTargetException
    //   152	164	379	java/lang/reflect/InvocationTargetException
    //   109	121	385	java/lang/reflect/InvocationTargetException
    //   346	356	391	java/lang/reflect/InvocationTargetException
  }
  
  /* Error */
  public void bk006Bkkk006B006B006B006Bk()
  {
    // Byte code:
    //   0: aload_0
    //   1: getfield 190	uuuuuu/ononoo:bn006Enn006Enn006E006E	Luuuuuu/onoono;
    //   4: invokeinterface 554 1 0
    //   9: ifeq +103 -> 112
    //   12: aload_0
    //   13: getfield 98	uuuuuu/ononoo:bnnnnn006E006E006En	Luuuuuu/ttssst$tsssst;
    //   16: checkcast 136	uuuuuu/nnnooo$noonoo
    //   19: astore 4
    //   21: getstatic 557	com/db/pwcc/dbmobile/foundation/R$string:fingerprint_error_other_fkn_title	I
    //   24: istore_1
    //   25: getstatic 560	com/db/pwcc/dbmobile/foundation/R$string:fingerprint_error_other_fkn_message	I
    //   28: istore_2
    //   29: getstatic 61	uuuuuu/ononoo:bn006E006En006Enn006E006E	I
    //   32: getstatic 63	uuuuuu/ononoo:bnnn006E006Enn006E006E	I
    //   35: iadd
    //   36: getstatic 61	uuuuuu/ononoo:bn006E006En006Enn006E006E	I
    //   39: imul
    //   40: getstatic 65	uuuuuu/ononoo:b006Enn006E006Enn006E006E	I
    //   43: irem
    //   44: getstatic 67	uuuuuu/ononoo:b006E006E006En006Enn006E006E	I
    //   47: if_icmpeq +13 -> 60
    //   50: bipush 21
    //   52: putstatic 61	uuuuuu/ononoo:bn006E006En006Enn006E006E	I
    //   55: bipush 58
    //   57: putstatic 67	uuuuuu/ononoo:b006E006E006En006Enn006E006E	I
    //   60: aload 4
    //   62: iload_1
    //   63: iload_2
    //   64: aconst_null
    //   65: invokeinterface 564 4 0
    //   70: getstatic 567	uuuuuu/vvrvrv:b0068006800680068h00680068h0068	Luuuuuu/vvrvrv;
    //   73: invokestatic 272	uuuuuu/rrvvrv:b0071q0071qq0071q0071q0071	(Luuuuuu/vvrvrv;)V
    //   76: aload_0
    //   77: getfield 98	uuuuuu/ononoo:bnnnnn006E006E006En	Luuuuuu/ttssst$tsssst;
    //   80: checkcast 136	uuuuuu/nnnooo$noonoo
    //   83: iconst_0
    //   84: getstatic 379	com/db/pwcc/dbmobile/foundation/R$string:settings_label_inactive	I
    //   87: invokeinterface 389 3 0
    //   92: return
    //   93: getstatic 570	uuuuuu/vvrvrv:b0068h00680068h00680068h0068	Luuuuuu/vvrvrv;
    //   96: invokestatic 272	uuuuuu/rrvvrv:b0071q0071qq0071q0071q0071	(Luuuuuu/vvrvrv;)V
    //   99: aload_0
    //   100: getfield 98	uuuuuu/ononoo:bnnnnn006E006E006En	Luuuuuu/ttssst$tsssst;
    //   103: checkcast 136	uuuuuu/nnnooo$noonoo
    //   106: invokeinterface 573 1 0
    //   111: return
    //   112: aload_0
    //   113: getfield 190	uuuuuu/ononoo:bn006Enn006Enn006E006E	Luuuuuu/onoono;
    //   116: invokeinterface 349 1 0
    //   121: ifeq -28 -> 93
    //   124: aload_0
    //   125: getfield 98	uuuuuu/ononoo:bnnnnn006E006E006En	Luuuuuu/ttssst$tsssst;
    //   128: checkcast 136	uuuuuu/nnnooo$noonoo
    //   131: invokeinterface 576 1 0
    //   136: getstatic 61	uuuuuu/ononoo:bn006E006En006Enn006E006E	I
    //   139: istore_1
    //   140: getstatic 63	uuuuuu/ononoo:bnnn006E006Enn006E006E	I
    //   143: istore_2
    //   144: getstatic 65	uuuuuu/ononoo:b006Enn006E006Enn006E006E	I
    //   147: istore_3
    //   148: getstatic 61	uuuuuu/ononoo:bn006E006En006Enn006E006E	I
    //   151: getstatic 63	uuuuuu/ononoo:bnnn006E006Enn006E006E	I
    //   154: iadd
    //   155: getstatic 61	uuuuuu/ononoo:bn006E006En006Enn006E006E	I
    //   158: imul
    //   159: getstatic 65	uuuuuu/ononoo:b006Enn006E006Enn006E006E	I
    //   162: irem
    //   163: getstatic 67	uuuuuu/ononoo:b006E006E006En006Enn006E006E	I
    //   166: if_icmpeq +52 -> 218
    //   169: bipush 51
    //   171: putstatic 61	uuuuuu/ononoo:bn006E006En006Enn006E006E	I
    //   174: ldc 2
    //   176: ldc_w 578
    //   179: sipush 253
    //   182: iconst_5
    //   183: invokestatic 75	xxxxxx/uxxxxx:bb00620062bb0062b0062b0062	(Ljava/lang/String;CC)Ljava/lang/String;
    //   186: iconst_0
    //   187: anewarray 77	java/lang/Class
    //   190: invokevirtual 81	java/lang/Class:getMethod	(Ljava/lang/String;[Ljava/lang/Class;)Ljava/lang/reflect/Method;
    //   193: astore 4
    //   195: aload 4
    //   197: aconst_null
    //   198: iconst_0
    //   199: anewarray 83	java/lang/Object
    //   202: invokevirtual 89	java/lang/reflect/Method:invoke	(Ljava/lang/Object;[Ljava/lang/Object;)Ljava/lang/Object;
    //   205: astore 4
    //   207: aload 4
    //   209: checkcast 91	java/lang/Integer
    //   212: invokevirtual 94	java/lang/Integer:intValue	()I
    //   215: putstatic 67	uuuuuu/ononoo:b006E006E006En006Enn006E006E	I
    //   218: iload_2
    //   219: iload_1
    //   220: iadd
    //   221: iload_1
    //   222: imul
    //   223: iload_3
    //   224: irem
    //   225: tableswitch	default:+19->244, 0:+-133->92
    //   244: ldc 2
    //   246: ldc_w 450
    //   249: sipush 232
    //   252: bipush 103
    //   254: iconst_3
    //   255: invokestatic 115	xxxxxx/uxxxxx:bbbb0062b0062b0062b0062	(Ljava/lang/String;CCC)Ljava/lang/String;
    //   258: iconst_0
    //   259: anewarray 77	java/lang/Class
    //   262: invokevirtual 81	java/lang/Class:getMethod	(Ljava/lang/String;[Ljava/lang/Class;)Ljava/lang/reflect/Method;
    //   265: astore 4
    //   267: aload 4
    //   269: aconst_null
    //   270: iconst_0
    //   271: anewarray 83	java/lang/Object
    //   274: invokevirtual 89	java/lang/reflect/Method:invoke	(Ljava/lang/Object;[Ljava/lang/Object;)Ljava/lang/Object;
    //   277: astore 4
    //   279: aload 4
    //   281: checkcast 91	java/lang/Integer
    //   284: invokevirtual 94	java/lang/Integer:intValue	()I
    //   287: putstatic 61	uuuuuu/ononoo:bn006E006En006Enn006E006E	I
    //   290: ldc 2
    //   292: ldc_w 315
    //   295: bipush 118
    //   297: sipush 158
    //   300: iconst_2
    //   301: invokestatic 115	xxxxxx/uxxxxx:bbbb0062b0062b0062b0062	(Ljava/lang/String;CCC)Ljava/lang/String;
    //   304: iconst_0
    //   305: anewarray 77	java/lang/Class
    //   308: invokevirtual 81	java/lang/Class:getMethod	(Ljava/lang/String;[Ljava/lang/Class;)Ljava/lang/reflect/Method;
    //   311: astore 4
    //   313: aload 4
    //   315: aconst_null
    //   316: iconst_0
    //   317: anewarray 83	java/lang/Object
    //   320: invokevirtual 89	java/lang/reflect/Method:invoke	(Ljava/lang/Object;[Ljava/lang/Object;)Ljava/lang/Object;
    //   323: astore 4
    //   325: aload 4
    //   327: checkcast 91	java/lang/Integer
    //   330: invokevirtual 94	java/lang/Integer:intValue	()I
    //   333: putstatic 67	uuuuuu/ononoo:b006E006E006En006Enn006E006E	I
    //   336: getstatic 61	uuuuuu/ononoo:bn006E006En006Enn006E006E	I
    //   339: istore_1
    //   340: ldc 2
    //   342: ldc_w 580
    //   345: sipush 144
    //   348: bipush 119
    //   350: iconst_0
    //   351: invokestatic 115	xxxxxx/uxxxxx:bbbb0062b0062b0062b0062	(Ljava/lang/String;CCC)Ljava/lang/String;
    //   354: iconst_0
    //   355: anewarray 77	java/lang/Class
    //   358: invokevirtual 81	java/lang/Class:getMethod	(Ljava/lang/String;[Ljava/lang/Class;)Ljava/lang/reflect/Method;
    //   361: astore 4
    //   363: aload 4
    //   365: aconst_null
    //   366: iconst_0
    //   367: anewarray 83	java/lang/Object
    //   370: invokevirtual 89	java/lang/reflect/Method:invoke	(Ljava/lang/Object;[Ljava/lang/Object;)Ljava/lang/Object;
    //   373: astore 4
    //   375: aload 4
    //   377: checkcast 91	java/lang/Integer
    //   380: invokevirtual 94	java/lang/Integer:intValue	()I
    //   383: iload_1
    //   384: iadd
    //   385: iload_1
    //   386: imul
    //   387: getstatic 65	uuuuuu/ononoo:b006Enn006E006Enn006E006E	I
    //   390: irem
    //   391: tableswitch	default:+17->408, 0:+-299->92
    //   408: bipush 67
    //   410: putstatic 61	uuuuuu/ononoo:bn006E006En006Enn006E006E	I
    //   413: ldc 2
    //   415: ldc_w 493
    //   418: sipush 241
    //   421: sipush 179
    //   424: iconst_0
    //   425: invokestatic 115	xxxxxx/uxxxxx:bbbb0062b0062b0062b0062	(Ljava/lang/String;CCC)Ljava/lang/String;
    //   428: iconst_0
    //   429: anewarray 77	java/lang/Class
    //   432: invokevirtual 81	java/lang/Class:getMethod	(Ljava/lang/String;[Ljava/lang/Class;)Ljava/lang/reflect/Method;
    //   435: astore 4
    //   437: aload 4
    //   439: aconst_null
    //   440: iconst_0
    //   441: anewarray 83	java/lang/Object
    //   444: invokevirtual 89	java/lang/reflect/Method:invoke	(Ljava/lang/Object;[Ljava/lang/Object;)Ljava/lang/Object;
    //   447: astore 4
    //   449: aload 4
    //   451: checkcast 91	java/lang/Integer
    //   454: invokevirtual 94	java/lang/Integer:intValue	()I
    //   457: putstatic 67	uuuuuu/ononoo:b006E006E006En006Enn006E006E	I
    //   460: return
    //   461: astore 4
    //   463: aload 4
    //   465: invokevirtual 104	java/lang/reflect/InvocationTargetException:getCause	()Ljava/lang/Throwable;
    //   468: athrow
    //   469: astore 4
    //   471: aload 4
    //   473: invokevirtual 104	java/lang/reflect/InvocationTargetException:getCause	()Ljava/lang/Throwable;
    //   476: athrow
    //   477: astore 4
    //   479: aload 4
    //   481: invokevirtual 104	java/lang/reflect/InvocationTargetException:getCause	()Ljava/lang/Throwable;
    //   484: athrow
    //   485: astore 4
    //   487: aload 4
    //   489: invokevirtual 104	java/lang/reflect/InvocationTargetException:getCause	()Ljava/lang/Throwable;
    //   492: athrow
    //   493: astore 4
    //   495: aload 4
    //   497: invokevirtual 104	java/lang/reflect/InvocationTargetException:getCause	()Ljava/lang/Throwable;
    //   500: athrow
    // Local variable table:
    //   start	length	slot	name	signature
    //   0	501	0	this	ononoo
    //   24	363	1	i	int
    //   28	193	2	j	int
    //   147	78	3	k	int
    //   19	431	4	localObject	Object
    //   461	3	4	localInvocationTargetException1	java.lang.reflect.InvocationTargetException
    //   469	3	4	localInvocationTargetException2	java.lang.reflect.InvocationTargetException
    //   477	3	4	localInvocationTargetException3	java.lang.reflect.InvocationTargetException
    //   485	3	4	localInvocationTargetException4	java.lang.reflect.InvocationTargetException
    //   493	3	4	localInvocationTargetException5	java.lang.reflect.InvocationTargetException
    // Exception table:
    //   from	to	target	type
    //   313	325	461	java/lang/reflect/InvocationTargetException
    //   363	375	469	java/lang/reflect/InvocationTargetException
    //   267	279	477	java/lang/reflect/InvocationTargetException
    //   195	207	485	java/lang/reflect/InvocationTargetException
    //   437	449	493	java/lang/reflect/InvocationTargetException
  }
  
  /* Error */
  public void bkk006B006B006Bk006B006B006Bk()
  {
    // Byte code:
    //   0: aload_0
    //   1: invokevirtual 171	uuuuuu/ononoo:bkk006Bk006Bk006Bk006Bk	()Z
    //   4: ifne +4 -> 8
    //   7: return
    //   8: ldc 2
    //   10: ldc_w 583
    //   13: sipush 193
    //   16: iconst_4
    //   17: invokestatic 75	xxxxxx/uxxxxx:bb00620062bb0062b0062b0062	(Ljava/lang/String;CC)Ljava/lang/String;
    //   20: iconst_0
    //   21: anewarray 77	java/lang/Class
    //   24: invokevirtual 81	java/lang/Class:getMethod	(Ljava/lang/String;[Ljava/lang/Class;)Ljava/lang/reflect/Method;
    //   27: astore 6
    //   29: aload 6
    //   31: aload_0
    //   32: iconst_0
    //   33: anewarray 83	java/lang/Object
    //   36: invokevirtual 89	java/lang/reflect/Method:invoke	(Ljava/lang/Object;[Ljava/lang/Object;)Ljava/lang/Object;
    //   39: pop
    //   40: getstatic 61	uuuuuu/ononoo:bn006E006En006Enn006E006E	I
    //   43: getstatic 63	uuuuuu/ononoo:bnnn006E006Enn006E006E	I
    //   46: iadd
    //   47: getstatic 61	uuuuuu/ononoo:bn006E006En006Enn006E006E	I
    //   50: imul
    //   51: getstatic 65	uuuuuu/ononoo:b006Enn006E006Enn006E006E	I
    //   54: irem
    //   55: getstatic 67	uuuuuu/ononoo:b006E006E006En006Enn006E006E	I
    //   58: if_icmpeq -51 -> 7
    //   61: getstatic 61	uuuuuu/ononoo:bn006E006En006Enn006E006E	I
    //   64: istore_1
    //   65: getstatic 63	uuuuuu/ononoo:bnnn006E006Enn006E006E	I
    //   68: istore_2
    //   69: getstatic 61	uuuuuu/ononoo:bn006E006En006Enn006E006E	I
    //   72: istore_3
    //   73: getstatic 65	uuuuuu/ononoo:b006Enn006E006Enn006E006E	I
    //   76: istore 4
    //   78: getstatic 61	uuuuuu/ononoo:bn006E006En006Enn006E006E	I
    //   81: istore 5
    //   83: iload 5
    //   85: getstatic 63	uuuuuu/ononoo:bnnn006E006Enn006E006E	I
    //   88: iload 5
    //   90: iadd
    //   91: imul
    //   92: getstatic 65	uuuuuu/ononoo:b006Enn006E006Enn006E006E	I
    //   95: irem
    //   96: tableswitch	default:+20->116, 0:+71->167
    //   116: ldc 2
    //   118: ldc_w 585
    //   121: sipush 226
    //   124: bipush 30
    //   126: iconst_1
    //   127: invokestatic 115	xxxxxx/uxxxxx:bbbb0062b0062b0062b0062	(Ljava/lang/String;CCC)Ljava/lang/String;
    //   130: iconst_0
    //   131: anewarray 77	java/lang/Class
    //   134: invokevirtual 81	java/lang/Class:getMethod	(Ljava/lang/String;[Ljava/lang/Class;)Ljava/lang/reflect/Method;
    //   137: astore 6
    //   139: aload 6
    //   141: aconst_null
    //   142: iconst_0
    //   143: anewarray 83	java/lang/Object
    //   146: invokevirtual 89	java/lang/reflect/Method:invoke	(Ljava/lang/Object;[Ljava/lang/Object;)Ljava/lang/Object;
    //   149: astore 6
    //   151: aload 6
    //   153: checkcast 91	java/lang/Integer
    //   156: invokevirtual 94	java/lang/Integer:intValue	()I
    //   159: putstatic 61	uuuuuu/ononoo:bn006E006En006Enn006E006E	I
    //   162: bipush 36
    //   164: putstatic 67	uuuuuu/ononoo:b006E006E006En006Enn006E006E	I
    //   167: iload_1
    //   168: iload_2
    //   169: iadd
    //   170: iload_3
    //   171: imul
    //   172: iload 4
    //   174: irem
    //   175: getstatic 67	uuuuuu/ononoo:b006E006E006En006Enn006E006E	I
    //   178: if_icmpeq +206 -> 384
    //   181: getstatic 61	uuuuuu/ononoo:bn006E006En006Enn006E006E	I
    //   184: istore_1
    //   185: getstatic 63	uuuuuu/ononoo:bnnn006E006Enn006E006E	I
    //   188: istore_2
    //   189: getstatic 61	uuuuuu/ononoo:bn006E006En006Enn006E006E	I
    //   192: istore_3
    //   193: ldc 2
    //   195: ldc_w 587
    //   198: sipush 223
    //   201: iconst_5
    //   202: invokestatic 75	xxxxxx/uxxxxx:bb00620062bb0062b0062b0062	(Ljava/lang/String;CC)Ljava/lang/String;
    //   205: iconst_0
    //   206: anewarray 77	java/lang/Class
    //   209: invokevirtual 81	java/lang/Class:getMethod	(Ljava/lang/String;[Ljava/lang/Class;)Ljava/lang/reflect/Method;
    //   212: astore 6
    //   214: aload 6
    //   216: aconst_null
    //   217: iconst_0
    //   218: anewarray 83	java/lang/Object
    //   221: invokevirtual 89	java/lang/reflect/Method:invoke	(Ljava/lang/Object;[Ljava/lang/Object;)Ljava/lang/Object;
    //   224: astore 6
    //   226: iload_3
    //   227: iload_1
    //   228: iload_2
    //   229: iadd
    //   230: imul
    //   231: aload 6
    //   233: checkcast 91	java/lang/Integer
    //   236: invokevirtual 94	java/lang/Integer:intValue	()I
    //   239: irem
    //   240: getstatic 67	uuuuuu/ononoo:b006E006E006En006Enn006E006E	I
    //   243: if_icmpeq +93 -> 336
    //   246: ldc 2
    //   248: ldc_w 589
    //   251: sipush 177
    //   254: sipush 160
    //   257: iconst_0
    //   258: invokestatic 115	xxxxxx/uxxxxx:bbbb0062b0062b0062b0062	(Ljava/lang/String;CCC)Ljava/lang/String;
    //   261: iconst_0
    //   262: anewarray 77	java/lang/Class
    //   265: invokevirtual 81	java/lang/Class:getMethod	(Ljava/lang/String;[Ljava/lang/Class;)Ljava/lang/reflect/Method;
    //   268: astore 6
    //   270: aload 6
    //   272: aconst_null
    //   273: iconst_0
    //   274: anewarray 83	java/lang/Object
    //   277: invokevirtual 89	java/lang/reflect/Method:invoke	(Ljava/lang/Object;[Ljava/lang/Object;)Ljava/lang/Object;
    //   280: astore 6
    //   282: aload 6
    //   284: checkcast 91	java/lang/Integer
    //   287: invokevirtual 94	java/lang/Integer:intValue	()I
    //   290: putstatic 61	uuuuuu/ononoo:bn006E006En006Enn006E006E	I
    //   293: ldc 2
    //   295: ldc_w 499
    //   298: bipush 34
    //   300: iconst_3
    //   301: invokestatic 75	xxxxxx/uxxxxx:bb00620062bb0062b0062b0062	(Ljava/lang/String;CC)Ljava/lang/String;
    //   304: iconst_0
    //   305: anewarray 77	java/lang/Class
    //   308: invokevirtual 81	java/lang/Class:getMethod	(Ljava/lang/String;[Ljava/lang/Class;)Ljava/lang/reflect/Method;
    //   311: astore 6
    //   313: aload 6
    //   315: aconst_null
    //   316: iconst_0
    //   317: anewarray 83	java/lang/Object
    //   320: invokevirtual 89	java/lang/reflect/Method:invoke	(Ljava/lang/Object;[Ljava/lang/Object;)Ljava/lang/Object;
    //   323: astore 6
    //   325: aload 6
    //   327: checkcast 91	java/lang/Integer
    //   330: invokevirtual 94	java/lang/Integer:intValue	()I
    //   333: putstatic 67	uuuuuu/ononoo:b006E006E006En006Enn006E006E	I
    //   336: bipush 8
    //   338: putstatic 61	uuuuuu/ononoo:bn006E006En006Enn006E006E	I
    //   341: ldc 2
    //   343: ldc_w 481
    //   346: bipush 26
    //   348: iconst_4
    //   349: invokestatic 75	xxxxxx/uxxxxx:bb00620062bb0062b0062b0062	(Ljava/lang/String;CC)Ljava/lang/String;
    //   352: iconst_0
    //   353: anewarray 77	java/lang/Class
    //   356: invokevirtual 81	java/lang/Class:getMethod	(Ljava/lang/String;[Ljava/lang/Class;)Ljava/lang/reflect/Method;
    //   359: astore 6
    //   361: aload 6
    //   363: aconst_null
    //   364: iconst_0
    //   365: anewarray 83	java/lang/Object
    //   368: invokevirtual 89	java/lang/reflect/Method:invoke	(Ljava/lang/Object;[Ljava/lang/Object;)Ljava/lang/Object;
    //   371: astore 6
    //   373: aload 6
    //   375: checkcast 91	java/lang/Integer
    //   378: invokevirtual 94	java/lang/Integer:intValue	()I
    //   381: putstatic 67	uuuuuu/ononoo:b006E006E006En006Enn006E006E	I
    //   384: bipush 96
    //   386: putstatic 61	uuuuuu/ononoo:bn006E006En006Enn006E006E	I
    //   389: ldc 2
    //   391: ldc_w 511
    //   394: sipush 209
    //   397: sipush 250
    //   400: iconst_2
    //   401: invokestatic 115	xxxxxx/uxxxxx:bbbb0062b0062b0062b0062	(Ljava/lang/String;CCC)Ljava/lang/String;
    //   404: iconst_0
    //   405: anewarray 77	java/lang/Class
    //   408: invokevirtual 81	java/lang/Class:getMethod	(Ljava/lang/String;[Ljava/lang/Class;)Ljava/lang/reflect/Method;
    //   411: astore 6
    //   413: aload 6
    //   415: aconst_null
    //   416: iconst_0
    //   417: anewarray 83	java/lang/Object
    //   420: invokevirtual 89	java/lang/reflect/Method:invoke	(Ljava/lang/Object;[Ljava/lang/Object;)Ljava/lang/Object;
    //   423: astore 6
    //   425: aload 6
    //   427: checkcast 91	java/lang/Integer
    //   430: invokevirtual 94	java/lang/Integer:intValue	()I
    //   433: putstatic 67	uuuuuu/ononoo:b006E006E006En006Enn006E006E	I
    //   436: return
    //   437: astore 6
    //   439: aload 6
    //   441: invokevirtual 104	java/lang/reflect/InvocationTargetException:getCause	()Ljava/lang/Throwable;
    //   444: athrow
    //   445: astore 6
    //   447: aload 6
    //   449: invokevirtual 104	java/lang/reflect/InvocationTargetException:getCause	()Ljava/lang/Throwable;
    //   452: athrow
    //   453: astore 6
    //   455: aload 6
    //   457: invokevirtual 104	java/lang/reflect/InvocationTargetException:getCause	()Ljava/lang/Throwable;
    //   460: athrow
    //   461: astore 6
    //   463: aload 6
    //   465: invokevirtual 104	java/lang/reflect/InvocationTargetException:getCause	()Ljava/lang/Throwable;
    //   468: athrow
    //   469: astore 6
    //   471: aload 6
    //   473: invokevirtual 104	java/lang/reflect/InvocationTargetException:getCause	()Ljava/lang/Throwable;
    //   476: athrow
    //   477: astore 6
    //   479: aload 6
    //   481: invokevirtual 104	java/lang/reflect/InvocationTargetException:getCause	()Ljava/lang/Throwable;
    //   484: athrow
    //   485: astore 6
    //   487: aload 6
    //   489: invokevirtual 104	java/lang/reflect/InvocationTargetException:getCause	()Ljava/lang/Throwable;
    //   492: athrow
    // Local variable table:
    //   start	length	slot	name	signature
    //   0	493	0	this	ononoo
    //   64	166	1	i	int
    //   68	162	2	j	int
    //   72	159	3	k	int
    //   76	99	4	m	int
    //   81	11	5	n	int
    //   27	399	6	localObject	Object
    //   437	3	6	localInvocationTargetException1	java.lang.reflect.InvocationTargetException
    //   445	3	6	localInvocationTargetException2	java.lang.reflect.InvocationTargetException
    //   453	3	6	localInvocationTargetException3	java.lang.reflect.InvocationTargetException
    //   461	3	6	localInvocationTargetException4	java.lang.reflect.InvocationTargetException
    //   469	3	6	localInvocationTargetException5	java.lang.reflect.InvocationTargetException
    //   477	3	6	localInvocationTargetException6	java.lang.reflect.InvocationTargetException
    //   485	3	6	localInvocationTargetException7	java.lang.reflect.InvocationTargetException
    // Exception table:
    //   from	to	target	type
    //   214	226	437	java/lang/reflect/InvocationTargetException
    //   29	40	445	java/lang/reflect/InvocationTargetException
    //   413	425	453	java/lang/reflect/InvocationTargetException
    //   361	373	461	java/lang/reflect/InvocationTargetException
    //   139	151	469	java/lang/reflect/InvocationTargetException
    //   270	282	477	java/lang/reflect/InvocationTargetException
    //   313	325	485	java/lang/reflect/InvocationTargetException
  }
  
  /* Error */
  public void bkk006B006Bk006B006B006B006Bk(com.db.pwcc.dbmobile.model.error.DbError paramDbError)
  {
    // Byte code:
    //   0: aload_0
    //   1: invokevirtual 171	uuuuuu/ononoo:bkk006Bk006Bk006Bk006Bk	()Z
    //   4: ifne +4 -> 8
    //   7: return
    //   8: aload_0
    //   9: getfield 98	uuuuuu/ononoo:bnnnnn006E006E006En	Luuuuuu/ttssst$tsssst;
    //   12: checkcast 136	uuuuuu/nnnooo$noonoo
    //   15: invokeinterface 188 1 0
    //   20: ldc 2
    //   22: ldc_w 592
    //   25: iconst_3
    //   26: bipush 71
    //   28: iconst_0
    //   29: invokestatic 115	xxxxxx/uxxxxx:bbbb0062b0062b0062b0062	(Ljava/lang/String;CCC)Ljava/lang/String;
    //   32: iconst_0
    //   33: anewarray 77	java/lang/Class
    //   36: invokevirtual 81	java/lang/Class:getMethod	(Ljava/lang/String;[Ljava/lang/Class;)Ljava/lang/reflect/Method;
    //   39: astore 4
    //   41: aload 4
    //   43: aload_0
    //   44: iconst_0
    //   45: anewarray 83	java/lang/Object
    //   48: invokevirtual 89	java/lang/reflect/Method:invoke	(Ljava/lang/Object;[Ljava/lang/Object;)Ljava/lang/Object;
    //   51: pop
    //   52: aload_0
    //   53: getfield 213	uuuuuu/ononoo:b006En006E006E006En006E006En	Luuuuuu/ggyggy;
    //   56: getstatic 219	uuuuuu/gyyygy$yyyygy:bkkk006Bk006Bk006Bk	Luuuuuu/gyyygy$yyyygy;
    //   59: invokevirtual 225	uuuuuu/ggyggy:b0070007000700070pp00700070pp	(Luuuuuu/gyyygy$yyyygy;)Luuuuuu/yyyggy;
    //   62: invokeinterface 231 1 0
    //   67: aload_0
    //   68: getfield 39	uuuuuu/ononoo:b006En006En006Enn006E006E	Ljava/lang/String;
    //   71: invokevirtual 248	uuuuuu/ggyygy:b007000700070ppppp0070p	(Ljava/lang/String;)V
    //   74: getstatic 61	uuuuuu/ononoo:bn006E006En006Enn006E006E	I
    //   77: istore_2
    //   78: iload_2
    //   79: getstatic 63	uuuuuu/ononoo:bnnn006E006Enn006E006E	I
    //   82: iload_2
    //   83: iadd
    //   84: imul
    //   85: getstatic 65	uuuuuu/ononoo:b006Enn006E006Enn006E006E	I
    //   88: irem
    //   89: tableswitch	default:+19->108, 0:+29->118
    //   108: bipush 48
    //   110: putstatic 61	uuuuuu/ononoo:bn006E006En006Enn006E006E	I
    //   113: bipush 44
    //   115: putstatic 67	uuuuuu/ononoo:b006E006E006En006Enn006E006E	I
    //   118: ldc 2
    //   120: ldc_w 594
    //   123: sipush 147
    //   126: iconst_2
    //   127: invokestatic 75	xxxxxx/uxxxxx:bb00620062bb0062b0062b0062	(Ljava/lang/String;CC)Ljava/lang/String;
    //   130: iconst_2
    //   131: anewarray 77	java/lang/Class
    //   134: dup
    //   135: iconst_0
    //   136: ldc 121
    //   138: aastore
    //   139: dup
    //   140: iconst_1
    //   141: getstatic 598	java/lang/Boolean:TYPE	Ljava/lang/Class;
    //   144: aastore
    //   145: invokevirtual 601	java/lang/Class:getDeclaredMethod	(Ljava/lang/String;[Ljava/lang/Class;)Ljava/lang/reflect/Method;
    //   148: astore 4
    //   150: aload 4
    //   152: aload_0
    //   153: iconst_2
    //   154: anewarray 83	java/lang/Object
    //   157: dup
    //   158: iconst_0
    //   159: aload_1
    //   160: aastore
    //   161: dup
    //   162: iconst_1
    //   163: iconst_1
    //   164: invokestatic 605	java/lang/Boolean:valueOf	(Z)Ljava/lang/Boolean;
    //   167: aastore
    //   168: invokevirtual 89	java/lang/reflect/Method:invoke	(Ljava/lang/Object;[Ljava/lang/Object;)Ljava/lang/Object;
    //   171: astore 4
    //   173: aload 4
    //   175: checkcast 393	java/lang/Boolean
    //   178: invokevirtual 396	java/lang/Boolean:booleanValue	()Z
    //   181: ifne -174 -> 7
    //   184: aload_1
    //   185: invokestatic 611	uuuuuu/kvvvvv:bqqqq0071qqqqq	(Lcom/db/pwcc/dbmobile/model/error/DbError;)Lcom/db/pwcc/dbmobile/foundation/utils/login/LoginErrorCode;
    //   188: astore_1
    //   189: aload_1
    //   190: getstatic 617	com/db/pwcc/dbmobile/foundation/utils/login/LoginErrorCode:INCORRECT_LOGIN_CREDENTIAL	Lcom/db/pwcc/dbmobile/foundation/utils/login/LoginErrorCode;
    //   193: if_acmpne +243 -> 436
    //   196: getstatic 620	com/db/pwcc/dbmobile/foundation/R$string:incorrect_credentials	I
    //   199: istore_2
    //   200: aload_1
    //   201: getstatic 623	com/db/pwcc/dbmobile/foundation/utils/login/LoginErrorCode:LOCKED_ACCOUNT	Lcom/db/pwcc/dbmobile/foundation/utils/login/LoginErrorCode;
    //   204: if_acmpne +276 -> 480
    //   207: aload_0
    //   208: getfield 98	uuuuuu/ononoo:bnnnnn006E006E006En	Luuuuuu/ttssst$tsssst;
    //   211: checkcast 136	uuuuuu/nnnooo$noonoo
    //   214: astore_1
    //   215: getstatic 61	uuuuuu/ononoo:bn006E006En006Enn006E006E	I
    //   218: istore_3
    //   219: iload_3
    //   220: getstatic 63	uuuuuu/ononoo:bnnn006E006Enn006E006E	I
    //   223: iload_3
    //   224: iadd
    //   225: imul
    //   226: getstatic 65	uuuuuu/ononoo:b006Enn006E006Enn006E006E	I
    //   229: irem
    //   230: tableswitch	default:+18->248, 0:+66->296
    //   248: bipush 20
    //   250: putstatic 61	uuuuuu/ononoo:bn006E006En006Enn006E006E	I
    //   253: ldc 2
    //   255: ldc_w 466
    //   258: bipush 11
    //   260: iconst_3
    //   261: invokestatic 75	xxxxxx/uxxxxx:bb00620062bb0062b0062b0062	(Ljava/lang/String;CC)Ljava/lang/String;
    //   264: iconst_0
    //   265: anewarray 77	java/lang/Class
    //   268: invokevirtual 81	java/lang/Class:getMethod	(Ljava/lang/String;[Ljava/lang/Class;)Ljava/lang/reflect/Method;
    //   271: astore 4
    //   273: aload 4
    //   275: aconst_null
    //   276: iconst_0
    //   277: anewarray 83	java/lang/Object
    //   280: invokevirtual 89	java/lang/reflect/Method:invoke	(Ljava/lang/Object;[Ljava/lang/Object;)Ljava/lang/Object;
    //   283: astore 4
    //   285: aload 4
    //   287: checkcast 91	java/lang/Integer
    //   290: invokevirtual 94	java/lang/Integer:intValue	()I
    //   293: putstatic 67	uuuuuu/ononoo:b006E006E006En006Enn006E006E	I
    //   296: new 625	uuuuuu/ononoo$1
    //   299: dup
    //   300: aload_0
    //   301: invokespecial 627	uuuuuu/ononoo$1:<init>	(Luuuuuu/ononoo;)V
    //   304: astore 4
    //   306: getstatic 61	uuuuuu/ononoo:bn006E006En006Enn006E006E	I
    //   309: istore_3
    //   310: ldc 2
    //   312: ldc_w 629
    //   315: sipush 162
    //   318: iconst_2
    //   319: invokestatic 75	xxxxxx/uxxxxx:bb00620062bb0062b0062b0062	(Ljava/lang/String;CC)Ljava/lang/String;
    //   322: iconst_0
    //   323: anewarray 77	java/lang/Class
    //   326: invokevirtual 81	java/lang/Class:getMethod	(Ljava/lang/String;[Ljava/lang/Class;)Ljava/lang/reflect/Method;
    //   329: astore 5
    //   331: aload 5
    //   333: aconst_null
    //   334: iconst_0
    //   335: anewarray 83	java/lang/Object
    //   338: invokevirtual 89	java/lang/reflect/Method:invoke	(Ljava/lang/Object;[Ljava/lang/Object;)Ljava/lang/Object;
    //   341: astore 5
    //   343: aload 5
    //   345: checkcast 91	java/lang/Integer
    //   348: invokevirtual 94	java/lang/Integer:intValue	()I
    //   351: iload_3
    //   352: iadd
    //   353: iload_3
    //   354: imul
    //   355: getstatic 65	uuuuuu/ononoo:b006Enn006E006Enn006E006E	I
    //   358: irem
    //   359: tableswitch	default:+17->376, 0:+66->425
    //   376: ldc 2
    //   378: ldc_w 497
    //   381: sipush 208
    //   384: iconst_1
    //   385: invokestatic 75	xxxxxx/uxxxxx:bb00620062bb0062b0062b0062	(Ljava/lang/String;CC)Ljava/lang/String;
    //   388: iconst_0
    //   389: anewarray 77	java/lang/Class
    //   392: invokevirtual 81	java/lang/Class:getMethod	(Ljava/lang/String;[Ljava/lang/Class;)Ljava/lang/reflect/Method;
    //   395: astore 5
    //   397: aload 5
    //   399: aconst_null
    //   400: iconst_0
    //   401: anewarray 83	java/lang/Object
    //   404: invokevirtual 89	java/lang/reflect/Method:invoke	(Ljava/lang/Object;[Ljava/lang/Object;)Ljava/lang/Object;
    //   407: astore 5
    //   409: aload 5
    //   411: checkcast 91	java/lang/Integer
    //   414: invokevirtual 94	java/lang/Integer:intValue	()I
    //   417: putstatic 61	uuuuuu/ononoo:bn006E006En006Enn006E006E	I
    //   420: bipush 46
    //   422: putstatic 67	uuuuuu/ononoo:b006E006E006En006Enn006E006E	I
    //   425: aload_1
    //   426: iconst_0
    //   427: iload_2
    //   428: aload 4
    //   430: invokeinterface 564 4 0
    //   435: return
    //   436: aload_1
    //   437: invokestatic 633	uuuuuu/kvvvvv:b0071qqq0071qqqqq	(Lcom/db/pwcc/dbmobile/foundation/utils/login/LoginErrorCode;)I
    //   440: istore_2
    //   441: getstatic 61	uuuuuu/ononoo:bn006E006En006Enn006E006E	I
    //   444: getstatic 63	uuuuuu/ononoo:bnnn006E006Enn006E006E	I
    //   447: iadd
    //   448: getstatic 61	uuuuuu/ononoo:bn006E006En006Enn006E006E	I
    //   451: imul
    //   452: getstatic 65	uuuuuu/ononoo:b006Enn006E006Enn006E006E	I
    //   455: irem
    //   456: getstatic 67	uuuuuu/ononoo:b006E006E006En006Enn006E006E	I
    //   459: if_icmpeq +61 -> 520
    //   462: iconst_2
    //   463: putstatic 61	uuuuuu/ononoo:bn006E006En006Enn006E006E	I
    //   466: bipush 75
    //   468: putstatic 67	uuuuuu/ononoo:b006E006E006En006Enn006E006E	I
    //   471: goto -271 -> 200
    //   474: astore_1
    //   475: aload_1
    //   476: invokevirtual 104	java/lang/reflect/InvocationTargetException:getCause	()Ljava/lang/Throwable;
    //   479: athrow
    //   480: aload_0
    //   481: getfield 98	uuuuuu/ononoo:bnnnnn006E006E006En	Luuuuuu/ttssst$tsssst;
    //   484: checkcast 136	uuuuuu/nnnooo$noonoo
    //   487: iconst_0
    //   488: iload_2
    //   489: aconst_null
    //   490: invokeinterface 564 4 0
    //   495: return
    //   496: astore_1
    //   497: aload_1
    //   498: invokevirtual 104	java/lang/reflect/InvocationTargetException:getCause	()Ljava/lang/Throwable;
    //   501: athrow
    //   502: astore_1
    //   503: aload_1
    //   504: invokevirtual 104	java/lang/reflect/InvocationTargetException:getCause	()Ljava/lang/Throwable;
    //   507: athrow
    //   508: astore_1
    //   509: aload_1
    //   510: invokevirtual 104	java/lang/reflect/InvocationTargetException:getCause	()Ljava/lang/Throwable;
    //   513: athrow
    //   514: astore_1
    //   515: aload_1
    //   516: invokevirtual 104	java/lang/reflect/InvocationTargetException:getCause	()Ljava/lang/Throwable;
    //   519: athrow
    //   520: goto -320 -> 200
    // Local variable table:
    //   start	length	slot	name	signature
    //   0	523	0	this	ononoo
    //   0	523	1	paramDbError	com.db.pwcc.dbmobile.model.error.DbError
    //   77	412	2	i	int
    //   218	137	3	j	int
    //   39	390	4	localObject1	Object
    //   329	81	5	localObject2	Object
    // Exception table:
    //   from	to	target	type
    //   41	52	474	java/lang/reflect/InvocationTargetException
    //   331	343	496	java/lang/reflect/InvocationTargetException
    //   397	409	502	java/lang/reflect/InvocationTargetException
    //   150	173	508	java/lang/reflect/InvocationTargetException
    //   273	285	514	java/lang/reflect/InvocationTargetException
  }
  
  /* Error */
  public void bkkk006Bk006B006B006B006Bk()
  {
    // Byte code:
    //   0: aload_0
    //   1: getfield 213	uuuuuu/ononoo:b006En006E006E006En006E006En	Luuuuuu/ggyggy;
    //   4: getstatic 219	uuuuuu/gyyygy$yyyygy:bkkk006Bk006Bk006Bk	Luuuuuu/gyyygy$yyyygy;
    //   7: invokevirtual 225	uuuuuu/ggyggy:b0070007000700070pp00700070pp	(Luuuuuu/gyyygy$yyyygy;)Luuuuuu/yyyggy;
    //   10: astore 4
    //   12: getstatic 61	uuuuuu/ononoo:bn006E006En006Enn006E006E	I
    //   15: istore_1
    //   16: iload_1
    //   17: getstatic 63	uuuuuu/ononoo:bnnn006E006Enn006E006E	I
    //   20: iload_1
    //   21: iadd
    //   22: imul
    //   23: getstatic 65	uuuuuu/ononoo:b006Enn006E006Enn006E006E	I
    //   26: irem
    //   27: tableswitch	default:+17->44, 0:+27->54
    //   44: bipush 27
    //   46: putstatic 61	uuuuuu/ononoo:bn006E006En006Enn006E006E	I
    //   49: bipush 9
    //   51: putstatic 67	uuuuuu/ononoo:b006E006E006En006Enn006E006E	I
    //   54: getstatic 61	uuuuuu/ononoo:bn006E006En006Enn006E006E	I
    //   57: istore_1
    //   58: getstatic 63	uuuuuu/ononoo:bnnn006E006Enn006E006E	I
    //   61: istore_2
    //   62: ldc 2
    //   64: ldc_w 636
    //   67: sipush 180
    //   70: bipush 91
    //   72: iconst_1
    //   73: invokestatic 115	xxxxxx/uxxxxx:bbbb0062b0062b0062b0062	(Ljava/lang/String;CCC)Ljava/lang/String;
    //   76: iconst_0
    //   77: anewarray 77	java/lang/Class
    //   80: invokevirtual 81	java/lang/Class:getMethod	(Ljava/lang/String;[Ljava/lang/Class;)Ljava/lang/reflect/Method;
    //   83: astore 5
    //   85: aload 5
    //   87: aconst_null
    //   88: iconst_0
    //   89: anewarray 83	java/lang/Object
    //   92: invokevirtual 89	java/lang/reflect/Method:invoke	(Ljava/lang/Object;[Ljava/lang/Object;)Ljava/lang/Object;
    //   95: astore 5
    //   97: iload_2
    //   98: iload_1
    //   99: iadd
    //   100: iload_1
    //   101: imul
    //   102: aload 5
    //   104: checkcast 91	java/lang/Integer
    //   107: invokevirtual 94	java/lang/Integer:intValue	()I
    //   110: irem
    //   111: tableswitch	default:+17->128, 0:+65->176
    //   128: bipush 87
    //   130: putstatic 61	uuuuuu/ononoo:bn006E006En006Enn006E006E	I
    //   133: ldc 2
    //   135: ldc_w 638
    //   138: bipush 59
    //   140: iconst_2
    //   141: invokestatic 75	xxxxxx/uxxxxx:bb00620062bb0062b0062b0062	(Ljava/lang/String;CC)Ljava/lang/String;
    //   144: iconst_0
    //   145: anewarray 77	java/lang/Class
    //   148: invokevirtual 81	java/lang/Class:getMethod	(Ljava/lang/String;[Ljava/lang/Class;)Ljava/lang/reflect/Method;
    //   151: astore 5
    //   153: aload 5
    //   155: aconst_null
    //   156: iconst_0
    //   157: anewarray 83	java/lang/Object
    //   160: invokevirtual 89	java/lang/reflect/Method:invoke	(Ljava/lang/Object;[Ljava/lang/Object;)Ljava/lang/Object;
    //   163: astore 5
    //   165: aload 5
    //   167: checkcast 91	java/lang/Integer
    //   170: invokevirtual 94	java/lang/Integer:intValue	()I
    //   173: putstatic 67	uuuuuu/ononoo:b006E006E006En006Enn006E006E	I
    //   176: getstatic 644	uuuuuu/lolllo:bqq00710071qqqq0071	Luuuuuu/lolllo;
    //   179: astore 5
    //   181: getstatic 61	uuuuuu/ononoo:bn006E006En006Enn006E006E	I
    //   184: istore_1
    //   185: getstatic 63	uuuuuu/ononoo:bnnn006E006Enn006E006E	I
    //   188: istore_2
    //   189: getstatic 61	uuuuuu/ononoo:bn006E006En006Enn006E006E	I
    //   192: istore_3
    //   193: ldc 2
    //   195: ldc_w 646
    //   198: sipush 223
    //   201: bipush 44
    //   203: iconst_2
    //   204: invokestatic 115	xxxxxx/uxxxxx:bbbb0062b0062b0062b0062	(Ljava/lang/String;CCC)Ljava/lang/String;
    //   207: iconst_0
    //   208: anewarray 77	java/lang/Class
    //   211: invokevirtual 81	java/lang/Class:getMethod	(Ljava/lang/String;[Ljava/lang/Class;)Ljava/lang/reflect/Method;
    //   214: astore 6
    //   216: aload 6
    //   218: aconst_null
    //   219: iconst_0
    //   220: anewarray 83	java/lang/Object
    //   223: invokevirtual 89	java/lang/reflect/Method:invoke	(Ljava/lang/Object;[Ljava/lang/Object;)Ljava/lang/Object;
    //   226: astore 6
    //   228: iload_3
    //   229: iload_1
    //   230: iload_2
    //   231: iadd
    //   232: imul
    //   233: aload 6
    //   235: checkcast 91	java/lang/Integer
    //   238: invokevirtual 94	java/lang/Integer:intValue	()I
    //   241: irem
    //   242: getstatic 67	uuuuuu/ononoo:b006E006E006En006Enn006E006E	I
    //   245: if_icmpeq +11 -> 256
    //   248: iconst_2
    //   249: putstatic 61	uuuuuu/ononoo:bn006E006En006Enn006E006E	I
    //   252: iconst_4
    //   253: putstatic 67	uuuuuu/ononoo:b006E006E006En006Enn006E006E	I
    //   256: getstatic 61	uuuuuu/ononoo:bn006E006En006Enn006E006E	I
    //   259: istore_1
    //   260: iload_1
    //   261: getstatic 63	uuuuuu/ononoo:bnnn006E006Enn006E006E	I
    //   264: iload_1
    //   265: iadd
    //   266: imul
    //   267: getstatic 65	uuuuuu/ononoo:b006Enn006E006Enn006E006E	I
    //   270: irem
    //   271: tableswitch	default:+17->288, 0:+68->339
    //   288: ldc 2
    //   290: ldc_w 648
    //   293: sipush 186
    //   296: sipush 246
    //   299: iconst_0
    //   300: invokestatic 115	xxxxxx/uxxxxx:bbbb0062b0062b0062b0062	(Ljava/lang/String;CCC)Ljava/lang/String;
    //   303: iconst_0
    //   304: anewarray 77	java/lang/Class
    //   307: invokevirtual 81	java/lang/Class:getMethod	(Ljava/lang/String;[Ljava/lang/Class;)Ljava/lang/reflect/Method;
    //   310: astore 6
    //   312: aload 6
    //   314: aconst_null
    //   315: iconst_0
    //   316: anewarray 83	java/lang/Object
    //   319: invokevirtual 89	java/lang/reflect/Method:invoke	(Ljava/lang/Object;[Ljava/lang/Object;)Ljava/lang/Object;
    //   322: astore 6
    //   324: aload 6
    //   326: checkcast 91	java/lang/Integer
    //   329: invokevirtual 94	java/lang/Integer:intValue	()I
    //   332: putstatic 61	uuuuuu/ononoo:bn006E006En006Enn006E006E	I
    //   335: iconst_0
    //   336: putstatic 67	uuuuuu/ononoo:b006E006E006En006Enn006E006E	I
    //   339: aload 4
    //   341: iconst_2
    //   342: anewarray 83	java/lang/Object
    //   345: dup
    //   346: iconst_0
    //   347: aload 5
    //   349: aastore
    //   350: dup
    //   351: iconst_1
    //   352: getstatic 651	uuuuuu/lolllo:b007100710071qq007100710071q	Luuuuuu/lolllo;
    //   355: aastore
    //   356: invokeinterface 655 2 0
    //   361: return
    //   362: astore 4
    //   364: aload 4
    //   366: invokevirtual 104	java/lang/reflect/InvocationTargetException:getCause	()Ljava/lang/Throwable;
    //   369: athrow
    //   370: astore 4
    //   372: aload 4
    //   374: invokevirtual 104	java/lang/reflect/InvocationTargetException:getCause	()Ljava/lang/Throwable;
    //   377: athrow
    //   378: astore 4
    //   380: aload 4
    //   382: invokevirtual 104	java/lang/reflect/InvocationTargetException:getCause	()Ljava/lang/Throwable;
    //   385: athrow
    //   386: astore 4
    //   388: aload 4
    //   390: invokevirtual 104	java/lang/reflect/InvocationTargetException:getCause	()Ljava/lang/Throwable;
    //   393: athrow
    // Local variable table:
    //   start	length	slot	name	signature
    //   0	394	0	this	ononoo
    //   15	252	1	i	int
    //   61	171	2	j	int
    //   192	41	3	k	int
    //   10	330	4	localYyyggy	yyyggy
    //   362	3	4	localInvocationTargetException1	java.lang.reflect.InvocationTargetException
    //   370	3	4	localInvocationTargetException2	java.lang.reflect.InvocationTargetException
    //   378	3	4	localInvocationTargetException3	java.lang.reflect.InvocationTargetException
    //   386	3	4	localInvocationTargetException4	java.lang.reflect.InvocationTargetException
    //   83	265	5	localObject1	Object
    //   214	111	6	localObject2	Object
    // Exception table:
    //   from	to	target	type
    //   312	324	362	java/lang/reflect/InvocationTargetException
    //   216	228	370	java/lang/reflect/InvocationTargetException
    //   85	97	378	java/lang/reflect/InvocationTargetException
    //   153	165	386	java/lang/reflect/InvocationTargetException
  }
  
  /* Error */
  public void bkkkkk006B006B006B006Bk()
  {
    // Byte code:
    //   0: getstatic 61	uuuuuu/ononoo:bn006E006En006Enn006E006E	I
    //   3: istore_1
    //   4: iload_1
    //   5: getstatic 63	uuuuuu/ononoo:bnnn006E006Enn006E006E	I
    //   8: iload_1
    //   9: iadd
    //   10: imul
    //   11: getstatic 65	uuuuuu/ononoo:b006Enn006E006Enn006E006E	I
    //   14: irem
    //   15: tableswitch	default:+17->32, 0:+27->42
    //   32: bipush 46
    //   34: putstatic 61	uuuuuu/ononoo:bn006E006En006Enn006E006E	I
    //   37: bipush 81
    //   39: putstatic 67	uuuuuu/ononoo:b006E006E006En006Enn006E006E	I
    //   42: getstatic 61	uuuuuu/ononoo:bn006E006En006Enn006E006E	I
    //   45: istore_1
    //   46: ldc 2
    //   48: ldc_w 658
    //   51: sipush 191
    //   54: iconst_3
    //   55: invokestatic 75	xxxxxx/uxxxxx:bb00620062bb0062b0062b0062	(Ljava/lang/String;CC)Ljava/lang/String;
    //   58: iconst_0
    //   59: anewarray 77	java/lang/Class
    //   62: invokevirtual 81	java/lang/Class:getMethod	(Ljava/lang/String;[Ljava/lang/Class;)Ljava/lang/reflect/Method;
    //   65: astore 6
    //   67: aload 6
    //   69: aconst_null
    //   70: iconst_0
    //   71: anewarray 83	java/lang/Object
    //   74: invokevirtual 89	java/lang/reflect/Method:invoke	(Ljava/lang/Object;[Ljava/lang/Object;)Ljava/lang/Object;
    //   77: astore 6
    //   79: aload 6
    //   81: checkcast 91	java/lang/Integer
    //   84: invokevirtual 94	java/lang/Integer:intValue	()I
    //   87: istore_2
    //   88: getstatic 61	uuuuuu/ononoo:bn006E006En006Enn006E006E	I
    //   91: istore_3
    //   92: getstatic 65	uuuuuu/ononoo:b006Enn006E006Enn006E006E	I
    //   95: istore 4
    //   97: getstatic 61	uuuuuu/ononoo:bn006E006En006Enn006E006E	I
    //   100: istore 5
    //   102: iload 5
    //   104: getstatic 63	uuuuuu/ononoo:bnnn006E006Enn006E006E	I
    //   107: iload 5
    //   109: iadd
    //   110: imul
    //   111: getstatic 65	uuuuuu/ononoo:b006Enn006E006Enn006E006E	I
    //   114: irem
    //   115: tableswitch	default:+17->132, 0:+66->181
    //   132: ldc 2
    //   134: ldc_w 489
    //   137: sipush 174
    //   140: iconst_5
    //   141: invokestatic 75	xxxxxx/uxxxxx:bb00620062bb0062b0062b0062	(Ljava/lang/String;CC)Ljava/lang/String;
    //   144: iconst_0
    //   145: anewarray 77	java/lang/Class
    //   148: invokevirtual 81	java/lang/Class:getMethod	(Ljava/lang/String;[Ljava/lang/Class;)Ljava/lang/reflect/Method;
    //   151: astore 6
    //   153: aload 6
    //   155: aconst_null
    //   156: iconst_0
    //   157: anewarray 83	java/lang/Object
    //   160: invokevirtual 89	java/lang/reflect/Method:invoke	(Ljava/lang/Object;[Ljava/lang/Object;)Ljava/lang/Object;
    //   163: astore 6
    //   165: aload 6
    //   167: checkcast 91	java/lang/Integer
    //   170: invokevirtual 94	java/lang/Integer:intValue	()I
    //   173: putstatic 61	uuuuuu/ononoo:bn006E006En006Enn006E006E	I
    //   176: bipush 18
    //   178: putstatic 67	uuuuuu/ononoo:b006E006E006En006Enn006E006E	I
    //   181: iload_3
    //   182: iload_2
    //   183: iload_1
    //   184: iadd
    //   185: imul
    //   186: iload 4
    //   188: irem
    //   189: getstatic 67	uuuuuu/ononoo:b006E006E006En006Enn006E006E	I
    //   192: if_icmpeq +221 -> 413
    //   195: bipush 50
    //   197: putstatic 61	uuuuuu/ononoo:bn006E006En006Enn006E006E	I
    //   200: ldc 2
    //   202: ldc_w 660
    //   205: bipush 57
    //   207: iconst_0
    //   208: invokestatic 75	xxxxxx/uxxxxx:bb00620062bb0062b0062b0062	(Ljava/lang/String;CC)Ljava/lang/String;
    //   211: iconst_0
    //   212: anewarray 77	java/lang/Class
    //   215: invokevirtual 81	java/lang/Class:getMethod	(Ljava/lang/String;[Ljava/lang/Class;)Ljava/lang/reflect/Method;
    //   218: astore 6
    //   220: aload 6
    //   222: aconst_null
    //   223: iconst_0
    //   224: anewarray 83	java/lang/Object
    //   227: invokevirtual 89	java/lang/reflect/Method:invoke	(Ljava/lang/Object;[Ljava/lang/Object;)Ljava/lang/Object;
    //   230: astore 6
    //   232: aload 6
    //   234: checkcast 91	java/lang/Integer
    //   237: invokevirtual 94	java/lang/Integer:intValue	()I
    //   240: putstatic 67	uuuuuu/ononoo:b006E006E006En006Enn006E006E	I
    //   243: getstatic 61	uuuuuu/ononoo:bn006E006En006Enn006E006E	I
    //   246: istore_1
    //   247: getstatic 63	uuuuuu/ononoo:bnnn006E006Enn006E006E	I
    //   250: istore_2
    //   251: ldc 2
    //   253: ldc_w 662
    //   256: bipush 37
    //   258: sipush 224
    //   261: iconst_2
    //   262: invokestatic 115	xxxxxx/uxxxxx:bbbb0062b0062b0062b0062	(Ljava/lang/String;CCC)Ljava/lang/String;
    //   265: iconst_0
    //   266: anewarray 77	java/lang/Class
    //   269: invokevirtual 81	java/lang/Class:getMethod	(Ljava/lang/String;[Ljava/lang/Class;)Ljava/lang/reflect/Method;
    //   272: astore 6
    //   274: aload 6
    //   276: aconst_null
    //   277: iconst_0
    //   278: anewarray 83	java/lang/Object
    //   281: invokevirtual 89	java/lang/reflect/Method:invoke	(Ljava/lang/Object;[Ljava/lang/Object;)Ljava/lang/Object;
    //   284: astore 6
    //   286: iload_2
    //   287: iload_1
    //   288: iadd
    //   289: iload_1
    //   290: imul
    //   291: aload 6
    //   293: checkcast 91	java/lang/Integer
    //   296: invokevirtual 94	java/lang/Integer:intValue	()I
    //   299: irem
    //   300: tableswitch	default:+20->320, 0:+113->413
    //   320: ldc 2
    //   322: ldc_w 331
    //   325: sipush 177
    //   328: sipush 248
    //   331: iconst_1
    //   332: invokestatic 115	xxxxxx/uxxxxx:bbbb0062b0062b0062b0062	(Ljava/lang/String;CCC)Ljava/lang/String;
    //   335: iconst_0
    //   336: anewarray 77	java/lang/Class
    //   339: invokevirtual 81	java/lang/Class:getMethod	(Ljava/lang/String;[Ljava/lang/Class;)Ljava/lang/reflect/Method;
    //   342: astore 6
    //   344: aload 6
    //   346: aconst_null
    //   347: iconst_0
    //   348: anewarray 83	java/lang/Object
    //   351: invokevirtual 89	java/lang/reflect/Method:invoke	(Ljava/lang/Object;[Ljava/lang/Object;)Ljava/lang/Object;
    //   354: astore 6
    //   356: aload 6
    //   358: checkcast 91	java/lang/Integer
    //   361: invokevirtual 94	java/lang/Integer:intValue	()I
    //   364: putstatic 61	uuuuuu/ononoo:bn006E006En006Enn006E006E	I
    //   367: ldc 2
    //   369: ldc_w 664
    //   372: bipush 50
    //   374: sipush 198
    //   377: iconst_2
    //   378: invokestatic 115	xxxxxx/uxxxxx:bbbb0062b0062b0062b0062	(Ljava/lang/String;CCC)Ljava/lang/String;
    //   381: iconst_0
    //   382: anewarray 77	java/lang/Class
    //   385: invokevirtual 81	java/lang/Class:getMethod	(Ljava/lang/String;[Ljava/lang/Class;)Ljava/lang/reflect/Method;
    //   388: astore 6
    //   390: aload 6
    //   392: aconst_null
    //   393: iconst_0
    //   394: anewarray 83	java/lang/Object
    //   397: invokevirtual 89	java/lang/reflect/Method:invoke	(Ljava/lang/Object;[Ljava/lang/Object;)Ljava/lang/Object;
    //   400: astore 6
    //   402: aload 6
    //   404: checkcast 91	java/lang/Integer
    //   407: invokevirtual 94	java/lang/Integer:intValue	()I
    //   410: putstatic 67	uuuuuu/ononoo:b006E006E006En006Enn006E006E	I
    //   413: ldc 2
    //   415: ldc_w 666
    //   418: bipush 84
    //   420: sipush 234
    //   423: iconst_0
    //   424: invokestatic 115	xxxxxx/uxxxxx:bbbb0062b0062b0062b0062	(Ljava/lang/String;CCC)Ljava/lang/String;
    //   427: iconst_0
    //   428: anewarray 77	java/lang/Class
    //   431: invokevirtual 81	java/lang/Class:getMethod	(Ljava/lang/String;[Ljava/lang/Class;)Ljava/lang/reflect/Method;
    //   434: astore 6
    //   436: aload 6
    //   438: aload_0
    //   439: iconst_0
    //   440: anewarray 83	java/lang/Object
    //   443: invokevirtual 89	java/lang/reflect/Method:invoke	(Ljava/lang/Object;[Ljava/lang/Object;)Ljava/lang/Object;
    //   446: pop
    //   447: return
    //   448: astore 6
    //   450: aload 6
    //   452: invokevirtual 104	java/lang/reflect/InvocationTargetException:getCause	()Ljava/lang/Throwable;
    //   455: athrow
    //   456: astore 6
    //   458: aload 6
    //   460: invokevirtual 104	java/lang/reflect/InvocationTargetException:getCause	()Ljava/lang/Throwable;
    //   463: athrow
    //   464: astore 6
    //   466: aload 6
    //   468: invokevirtual 104	java/lang/reflect/InvocationTargetException:getCause	()Ljava/lang/Throwable;
    //   471: athrow
    //   472: astore 6
    //   474: aload 6
    //   476: invokevirtual 104	java/lang/reflect/InvocationTargetException:getCause	()Ljava/lang/Throwable;
    //   479: athrow
    //   480: astore 6
    //   482: aload 6
    //   484: invokevirtual 104	java/lang/reflect/InvocationTargetException:getCause	()Ljava/lang/Throwable;
    //   487: athrow
    //   488: astore 6
    //   490: aload 6
    //   492: invokevirtual 104	java/lang/reflect/InvocationTargetException:getCause	()Ljava/lang/Throwable;
    //   495: athrow
    //   496: astore 6
    //   498: aload 6
    //   500: invokevirtual 104	java/lang/reflect/InvocationTargetException:getCause	()Ljava/lang/Throwable;
    //   503: athrow
    // Local variable table:
    //   start	length	slot	name	signature
    //   0	504	0	this	ononoo
    //   3	288	1	i	int
    //   87	202	2	j	int
    //   91	95	3	k	int
    //   95	94	4	m	int
    //   100	11	5	n	int
    //   65	372	6	localObject	Object
    //   448	3	6	localInvocationTargetException1	java.lang.reflect.InvocationTargetException
    //   456	3	6	localInvocationTargetException2	java.lang.reflect.InvocationTargetException
    //   464	3	6	localInvocationTargetException3	java.lang.reflect.InvocationTargetException
    //   472	3	6	localInvocationTargetException4	java.lang.reflect.InvocationTargetException
    //   480	3	6	localInvocationTargetException5	java.lang.reflect.InvocationTargetException
    //   488	3	6	localInvocationTargetException6	java.lang.reflect.InvocationTargetException
    //   496	3	6	localInvocationTargetException7	java.lang.reflect.InvocationTargetException
    // Exception table:
    //   from	to	target	type
    //   390	402	448	java/lang/reflect/InvocationTargetException
    //   344	356	456	java/lang/reflect/InvocationTargetException
    //   67	79	464	java/lang/reflect/InvocationTargetException
    //   220	232	472	java/lang/reflect/InvocationTargetException
    //   274	286	480	java/lang/reflect/InvocationTargetException
    //   436	447	488	java/lang/reflect/InvocationTargetException
    //   153	165	496	java/lang/reflect/InvocationTargetException
  }
}
