package uuuuuu;

public class oononn
{
  public static int b00660066ff0066f0066ff = 75;
  public static int b0066f0066f0066f0066ff = 2;
  public static int bf00660066f0066f0066ff = 0;
  private static final String bf0066ff0066f0066ff;
  public static int bff0066f0066f0066ff = 1;
  
  static
  {
    int i = b00660066ff0066f0066ff;
    switch (i * (bff0066f0066f0066ff + i) % b0066f0066f0066f0066ff)
    {
    default: 
      b00660066ff0066f0066ff = 63;
      bff0066f0066f0066ff = bk006Bk006Bk006Bk006Bk006B();
    }
    bf0066ff0066f0066ff = oononn.class.getSimpleName();
    if ((b00660066ff0066f0066ff + bff0066f0066f0066ff) * b00660066ff0066f0066ff % b0066f0066f0066f0066ff != b006B006Bk006Bk006Bk006Bk006B())
    {
      b00660066ff0066f0066ff = 20;
      bff0066f0066f0066ff = bk006Bk006Bk006Bk006Bk006B();
    }
  }
  
  public oononn() {}
  
  /* Error */
  private static String b006B006B006B006Bk006Bk006Bk006B(String paramString)
  {
    // Byte code:
    //   0: getstatic 19	uuuuuu/oononn:b00660066ff0066f0066ff	I
    //   3: getstatic 21	uuuuuu/oononn:bff0066f0066f0066ff	I
    //   6: iadd
    //   7: getstatic 19	uuuuuu/oononn:b00660066ff0066f0066ff	I
    //   10: imul
    //   11: invokestatic 49	uuuuuu/oononn:b006Bkk006Bk006Bk006Bk006B	()I
    //   14: irem
    //   15: getstatic 51	uuuuuu/oononn:bf00660066f0066f0066ff	I
    //   18: if_icmpeq +15 -> 33
    //   21: invokestatic 27	uuuuuu/oononn:bk006Bk006Bk006Bk006Bk006B	()I
    //   24: putstatic 19	uuuuuu/oononn:b00660066ff0066f0066ff	I
    //   27: invokestatic 27	uuuuuu/oononn:bk006Bk006Bk006Bk006Bk006B	()I
    //   30: putstatic 51	uuuuuu/oononn:bf00660066f0066f0066ff	I
    //   33: getstatic 19	uuuuuu/oononn:b00660066ff0066f0066ff	I
    //   36: getstatic 21	uuuuuu/oononn:bff0066f0066f0066ff	I
    //   39: iadd
    //   40: getstatic 19	uuuuuu/oononn:b00660066ff0066f0066ff	I
    //   43: imul
    //   44: getstatic 23	uuuuuu/oononn:b0066f0066f0066f0066ff	I
    //   47: irem
    //   48: invokestatic 38	uuuuuu/oononn:b006B006Bk006Bk006Bk006Bk006B	()I
    //   51: if_icmpeq +14 -> 65
    //   54: bipush 83
    //   56: putstatic 19	uuuuuu/oononn:b00660066ff0066f0066ff	I
    //   59: invokestatic 27	uuuuuu/oononn:bk006Bk006Bk006Bk006Bk006B	()I
    //   62: putstatic 51	uuuuuu/oononn:bf00660066f0066f0066ff	I
    //   65: ldc 53
    //   67: ldc 55
    //   69: sipush 136
    //   72: bipush 25
    //   74: iconst_0
    //   75: invokestatic 61	xxxxxx/uxxxxx:bbbb0062b0062b0062b0062	(Ljava/lang/String;CCC)Ljava/lang/String;
    //   78: iconst_4
    //   79: anewarray 29	java/lang/Class
    //   82: dup
    //   83: iconst_0
    //   84: ldc 63
    //   86: aastore
    //   87: dup
    //   88: iconst_1
    //   89: getstatic 69	java/lang/Character:TYPE	Ljava/lang/Class;
    //   92: aastore
    //   93: dup
    //   94: iconst_2
    //   95: getstatic 69	java/lang/Character:TYPE	Ljava/lang/Class;
    //   98: aastore
    //   99: dup
    //   100: iconst_3
    //   101: getstatic 69	java/lang/Character:TYPE	Ljava/lang/Class;
    //   104: aastore
    //   105: invokevirtual 73	java/lang/Class:getMethod	(Ljava/lang/String;[Ljava/lang/Class;)Ljava/lang/reflect/Method;
    //   108: astore_1
    //   109: aload_1
    //   110: aconst_null
    //   111: iconst_4
    //   112: anewarray 4	java/lang/Object
    //   115: dup
    //   116: iconst_0
    //   117: ldc 75
    //   119: aastore
    //   120: dup
    //   121: iconst_1
    //   122: sipush 222
    //   125: invokestatic 79	java/lang/Character:valueOf	(C)Ljava/lang/Character;
    //   128: aastore
    //   129: dup
    //   130: iconst_2
    //   131: bipush 25
    //   133: invokestatic 79	java/lang/Character:valueOf	(C)Ljava/lang/Character;
    //   136: aastore
    //   137: dup
    //   138: iconst_3
    //   139: iconst_2
    //   140: invokestatic 79	java/lang/Character:valueOf	(C)Ljava/lang/Character;
    //   143: aastore
    //   144: invokevirtual 85	java/lang/reflect/Method:invoke	(Ljava/lang/Object;[Ljava/lang/Object;)Ljava/lang/Object;
    //   147: astore_1
    //   148: aload_0
    //   149: aload_1
    //   150: checkcast 63	java/lang/String
    //   153: ldc 87
    //   155: invokevirtual 91	java/lang/String:replaceFirst	(Ljava/lang/String;Ljava/lang/String;)Ljava/lang/String;
    //   158: astore_0
    //   159: ldc 53
    //   161: ldc 93
    //   163: bipush 109
    //   165: bipush 107
    //   167: iconst_3
    //   168: invokestatic 61	xxxxxx/uxxxxx:bbbb0062b0062b0062b0062	(Ljava/lang/String;CCC)Ljava/lang/String;
    //   171: iconst_4
    //   172: anewarray 29	java/lang/Class
    //   175: dup
    //   176: iconst_0
    //   177: ldc 63
    //   179: aastore
    //   180: dup
    //   181: iconst_1
    //   182: getstatic 69	java/lang/Character:TYPE	Ljava/lang/Class;
    //   185: aastore
    //   186: dup
    //   187: iconst_2
    //   188: getstatic 69	java/lang/Character:TYPE	Ljava/lang/Class;
    //   191: aastore
    //   192: dup
    //   193: iconst_3
    //   194: getstatic 69	java/lang/Character:TYPE	Ljava/lang/Class;
    //   197: aastore
    //   198: invokevirtual 73	java/lang/Class:getMethod	(Ljava/lang/String;[Ljava/lang/Class;)Ljava/lang/reflect/Method;
    //   201: astore_1
    //   202: aload_1
    //   203: aconst_null
    //   204: iconst_4
    //   205: anewarray 4	java/lang/Object
    //   208: dup
    //   209: iconst_0
    //   210: ldc 95
    //   212: aastore
    //   213: dup
    //   214: iconst_1
    //   215: sipush 164
    //   218: invokestatic 79	java/lang/Character:valueOf	(C)Ljava/lang/Character;
    //   221: aastore
    //   222: dup
    //   223: iconst_2
    //   224: bipush 96
    //   226: invokestatic 79	java/lang/Character:valueOf	(C)Ljava/lang/Character;
    //   229: aastore
    //   230: dup
    //   231: iconst_3
    //   232: iconst_2
    //   233: invokestatic 79	java/lang/Character:valueOf	(C)Ljava/lang/Character;
    //   236: aastore
    //   237: invokevirtual 85	java/lang/reflect/Method:invoke	(Ljava/lang/Object;[Ljava/lang/Object;)Ljava/lang/Object;
    //   240: astore_1
    //   241: aload_0
    //   242: aload_1
    //   243: checkcast 63	java/lang/String
    //   246: ldc 87
    //   248: invokevirtual 91	java/lang/String:replaceFirst	(Ljava/lang/String;Ljava/lang/String;)Ljava/lang/String;
    //   251: areturn
    //   252: astore_0
    //   253: aload_0
    //   254: invokevirtual 99	java/lang/reflect/InvocationTargetException:getCause	()Ljava/lang/Throwable;
    //   257: athrow
    //   258: astore_0
    //   259: aload_0
    //   260: invokevirtual 99	java/lang/reflect/InvocationTargetException:getCause	()Ljava/lang/Throwable;
    //   263: athrow
    // Local variable table:
    //   start	length	slot	name	signature
    //   0	264	0	paramString	String
    //   108	135	1	localObject	Object
    // Exception table:
    //   from	to	target	type
    //   202	241	252	java/lang/reflect/InvocationTargetException
    //   109	148	258	java/lang/reflect/InvocationTargetException
  }
  
  public static int b006B006Bk006Bk006Bk006Bk006B()
  {
    return 0;
  }
  
  public static String b006Bk006B006Bk006Bk006Bk006B(String paramString)
  {
    int i = b00660066ff0066f0066ff;
    switch (i * (bkkk006Bk006Bk006Bk006B() + i) % b0066f0066f0066f0066ff)
    {
    default: 
      b00660066ff0066f0066ff = bk006Bk006Bk006Bk006Bk006B();
      bff0066f0066f0066ff = 57;
      if ((b00660066ff0066f0066ff + bff0066f0066f0066ff) * b00660066ff0066f0066ff % b0066f0066f0066f0066ff != bf00660066f0066f0066ff)
      {
        b00660066ff0066f0066ff = 86;
        bf00660066f0066f0066ff = bk006Bk006Bk006Bk006Bk006B();
      }
      break;
    }
    return bk006B006B006Bk006Bk006Bk006B(paramString, false);
  }
  
  public static int b006Bkk006Bk006Bk006Bk006B()
  {
    return 2;
  }
  
  /* Error */
  private static String bk006B006B006Bk006Bk006Bk006B(String paramString, boolean paramBoolean)
  {
    // Byte code:
    //   0: aload_0
    //   1: ifnonnull +107 -> 108
    //   4: ldc 87
    //   6: astore_0
    //   7: aload_0
    //   8: areturn
    //   9: ldc 53
    //   11: ldc 109
    //   13: bipush 81
    //   15: bipush 80
    //   17: iconst_3
    //   18: invokestatic 61	xxxxxx/uxxxxx:bbbb0062b0062b0062b0062	(Ljava/lang/String;CCC)Ljava/lang/String;
    //   21: iconst_3
    //   22: anewarray 29	java/lang/Class
    //   25: dup
    //   26: iconst_0
    //   27: ldc 63
    //   29: aastore
    //   30: dup
    //   31: iconst_1
    //   32: getstatic 69	java/lang/Character:TYPE	Ljava/lang/Class;
    //   35: aastore
    //   36: dup
    //   37: iconst_2
    //   38: getstatic 69	java/lang/Character:TYPE	Ljava/lang/Class;
    //   41: aastore
    //   42: invokevirtual 73	java/lang/Class:getMethod	(Ljava/lang/String;[Ljava/lang/Class;)Ljava/lang/reflect/Method;
    //   45: astore 4
    //   47: aload 4
    //   49: aconst_null
    //   50: iconst_3
    //   51: anewarray 4	java/lang/Object
    //   54: dup
    //   55: iconst_0
    //   56: ldc 111
    //   58: aastore
    //   59: dup
    //   60: iconst_1
    //   61: sipush 176
    //   64: invokestatic 79	java/lang/Character:valueOf	(C)Ljava/lang/Character;
    //   67: aastore
    //   68: dup
    //   69: iconst_2
    //   70: iconst_1
    //   71: invokestatic 79	java/lang/Character:valueOf	(C)Ljava/lang/Character;
    //   74: aastore
    //   75: invokevirtual 85	java/lang/reflect/Method:invoke	(Ljava/lang/Object;[Ljava/lang/Object;)Ljava/lang/Object;
    //   78: astore 4
    //   80: aload_0
    //   81: aload 4
    //   83: checkcast 63	java/lang/String
    //   86: invokevirtual 115	java/lang/String:split	(Ljava/lang/String;)[Ljava/lang/String;
    //   89: astore_0
    //   90: aload_0
    //   91: arraylength
    //   92: iconst_1
    //   93: if_icmpne +237 -> 330
    //   96: aload_0
    //   97: iconst_0
    //   98: aaload
    //   99: iconst_0
    //   100: iconst_1
    //   101: invokevirtual 119	java/lang/String:substring	(II)Ljava/lang/String;
    //   104: invokevirtual 122	java/lang/String:toUpperCase	()Ljava/lang/String;
    //   107: areturn
    //   108: aload_0
    //   109: invokestatic 124	uuuuuu/oononn:b006B006B006B006Bk006Bk006Bk006B	(Ljava/lang/String;)Ljava/lang/String;
    //   112: invokevirtual 127	java/lang/String:trim	()Ljava/lang/String;
    //   115: astore_0
    //   116: aload_0
    //   117: invokevirtual 131	java/lang/String:isEmpty	()Z
    //   120: ifeq -111 -> 9
    //   123: getstatic 35	uuuuuu/oononn:bf0066ff0066f0066ff	Ljava/lang/String;
    //   126: astore_0
    //   127: ldc 53
    //   129: ldc -123
    //   131: bipush 38
    //   133: bipush 27
    //   135: iconst_1
    //   136: invokestatic 61	xxxxxx/uxxxxx:bbbb0062b0062b0062b0062	(Ljava/lang/String;CCC)Ljava/lang/String;
    //   139: iconst_3
    //   140: anewarray 29	java/lang/Class
    //   143: dup
    //   144: iconst_0
    //   145: ldc 63
    //   147: aastore
    //   148: dup
    //   149: iconst_1
    //   150: getstatic 69	java/lang/Character:TYPE	Ljava/lang/Class;
    //   153: aastore
    //   154: dup
    //   155: iconst_2
    //   156: getstatic 69	java/lang/Character:TYPE	Ljava/lang/Class;
    //   159: aastore
    //   160: invokevirtual 73	java/lang/Class:getMethod	(Ljava/lang/String;[Ljava/lang/Class;)Ljava/lang/reflect/Method;
    //   163: astore 4
    //   165: aload 4
    //   167: aconst_null
    //   168: iconst_3
    //   169: anewarray 4	java/lang/Object
    //   172: dup
    //   173: iconst_0
    //   174: ldc -121
    //   176: aastore
    //   177: dup
    //   178: iconst_1
    //   179: bipush 8
    //   181: invokestatic 79	java/lang/Character:valueOf	(C)Ljava/lang/Character;
    //   184: aastore
    //   185: dup
    //   186: iconst_2
    //   187: iconst_2
    //   188: invokestatic 79	java/lang/Character:valueOf	(C)Ljava/lang/Character;
    //   191: aastore
    //   192: invokevirtual 85	java/lang/reflect/Method:invoke	(Ljava/lang/Object;[Ljava/lang/Object;)Ljava/lang/Object;
    //   195: astore 4
    //   197: aload_0
    //   198: aload 4
    //   200: checkcast 63	java/lang/String
    //   203: invokestatic 141	uuuuuu/rvvvrv:bq0071qq00710071q0071q0071	(Ljava/lang/String;Ljava/lang/String;)V
    //   206: ldc 87
    //   208: areturn
    //   209: aload_0
    //   210: arraylength
    //   211: iconst_1
    //   212: isub
    //   213: istore_2
    //   214: new 143	java/lang/StringBuilder
    //   217: dup
    //   218: invokespecial 144	java/lang/StringBuilder:<init>	()V
    //   221: aload_0
    //   222: iconst_0
    //   223: aaload
    //   224: iconst_0
    //   225: iconst_1
    //   226: invokevirtual 119	java/lang/String:substring	(II)Ljava/lang/String;
    //   229: invokevirtual 148	java/lang/StringBuilder:append	(Ljava/lang/String;)Ljava/lang/StringBuilder;
    //   232: aload_0
    //   233: iload_2
    //   234: aaload
    //   235: iconst_0
    //   236: iconst_1
    //   237: invokevirtual 119	java/lang/String:substring	(II)Ljava/lang/String;
    //   240: invokevirtual 148	java/lang/StringBuilder:append	(Ljava/lang/String;)Ljava/lang/StringBuilder;
    //   243: invokevirtual 151	java/lang/StringBuilder:toString	()Ljava/lang/String;
    //   246: invokevirtual 122	java/lang/String:toUpperCase	()Ljava/lang/String;
    //   249: astore 4
    //   251: getstatic 19	uuuuuu/oononn:b00660066ff0066f0066ff	I
    //   254: istore_2
    //   255: getstatic 21	uuuuuu/oononn:bff0066f0066f0066ff	I
    //   258: istore_3
    //   259: getstatic 19	uuuuuu/oononn:b00660066ff0066f0066ff	I
    //   262: getstatic 21	uuuuuu/oononn:bff0066f0066f0066ff	I
    //   265: iadd
    //   266: getstatic 19	uuuuuu/oononn:b00660066ff0066f0066ff	I
    //   269: imul
    //   270: getstatic 23	uuuuuu/oononn:b0066f0066f0066f0066ff	I
    //   273: irem
    //   274: getstatic 51	uuuuuu/oononn:bf00660066f0066f0066ff	I
    //   277: if_icmpeq +15 -> 292
    //   280: invokestatic 27	uuuuuu/oononn:bk006Bk006Bk006Bk006Bk006B	()I
    //   283: putstatic 19	uuuuuu/oononn:b00660066ff0066f0066ff	I
    //   286: invokestatic 27	uuuuuu/oononn:bk006Bk006Bk006Bk006Bk006B	()I
    //   289: putstatic 51	uuuuuu/oononn:bf00660066f0066f0066ff	I
    //   292: aload 4
    //   294: astore_0
    //   295: iload_2
    //   296: iload_3
    //   297: iadd
    //   298: getstatic 19	uuuuuu/oononn:b00660066ff0066f0066ff	I
    //   301: imul
    //   302: getstatic 23	uuuuuu/oononn:b0066f0066f0066f0066ff	I
    //   305: irem
    //   306: getstatic 51	uuuuuu/oononn:bf00660066f0066f0066ff	I
    //   309: if_icmpeq -302 -> 7
    //   312: bipush 74
    //   314: putstatic 19	uuuuuu/oononn:b00660066ff0066f0066ff	I
    //   317: iconst_2
    //   318: putstatic 51	uuuuuu/oononn:bf00660066f0066f0066ff	I
    //   321: aload 4
    //   323: areturn
    //   324: astore_0
    //   325: aload_0
    //   326: invokevirtual 99	java/lang/reflect/InvocationTargetException:getCause	()Ljava/lang/Throwable;
    //   329: athrow
    //   330: iload_1
    //   331: ifeq -122 -> 209
    //   334: iconst_1
    //   335: istore_2
    //   336: goto -122 -> 214
    //   339: astore_0
    //   340: aload_0
    //   341: invokevirtual 99	java/lang/reflect/InvocationTargetException:getCause	()Ljava/lang/Throwable;
    //   344: athrow
    // Local variable table:
    //   start	length	slot	name	signature
    //   0	345	0	paramString	String
    //   0	345	1	paramBoolean	boolean
    //   213	123	2	i	int
    //   258	40	3	j	int
    //   45	277	4	localObject	Object
    // Exception table:
    //   from	to	target	type
    //   165	197	324	java/lang/reflect/InvocationTargetException
    //   47	80	339	java/lang/reflect/InvocationTargetException
  }
  
  public static int bk006Bk006Bk006Bk006Bk006B()
  {
    return 70;
  }
  
  public static String bkk006B006Bk006Bk006Bk006B(String paramString)
  {
    int i = b00660066ff0066f0066ff;
    switch (i * (bff0066f0066f0066ff + i) % b0066f0066f0066f0066ff)
    {
    default: 
      i = b00660066ff0066f0066ff;
      switch (i * (bff0066f0066f0066ff + i) % b0066f0066f0066f0066ff)
      {
      default: 
        b00660066ff0066f0066ff = bk006Bk006Bk006Bk006Bk006B();
        bff0066f0066f0066ff = 51;
      }
      b00660066ff0066f0066ff = 50;
      bff0066f0066f0066ff = 52;
    }
    return bk006B006B006Bk006Bk006Bk006B(paramString, true);
  }
  
  public static int bkkk006Bk006Bk006Bk006B()
  {
    return 1;
  }
}
