package uuuuuu;

import android.app.Activity;
import android.app.Application;
import android.app.Application.ActivityLifecycleCallbacks;
import android.os.Bundle;
import android.os.Handler;
import android.os.Looper;
import java.util.ArrayList;
import java.util.List;

public class oonoon
  implements Application.ActivityLifecycleCallbacks
{
  public static int b00660066f0066fffff = 1;
  public static int b0066ff0066fffff = 32;
  private static final String b006En006E006E006E006E006E006E006E = oonoon.class.getSimpleName();
  public static int bf0066f0066fffff = 0;
  public static int bff00660066fffff = 2;
  private static oonoon bn006E006E006E006E006E006E006E006E;
  private int b006600660066ffffff = 0;
  private Handler b00660066fffffff = new Handler(Looper.getMainLooper());
  private final List<onnoon> b0066f0066ffffff = new ArrayList();
  private final int b0066ffffffff = 500;
  private int bf00660066ffffff = 0;
  private boolean bf0066fffffff = false;
  private boolean bff0066ffffff = true;
  private Runnable bfff0066fffff = null;
  
  static
  {
    int i = b0066ff0066fffff;
    int j = b00660066f0066fffff;
    if ((b0066ff0066fffff + b00660066f0066fffff) * b0066ff0066fffff % bff00660066fffff != bf0066f0066fffff)
    {
      b0066ff0066fffff = bkk006Bkk006B006Bkk006B();
      bf0066f0066fffff = 11;
    }
    if ((i + j) * b0066ff0066fffff % b006Bkkkk006B006Bkk006B() != bf0066f0066fffff)
    {
      b0066ff0066fffff = bkk006Bkk006B006Bkk006B();
      bf0066f0066fffff = bkk006Bkk006B006Bkk006B();
    }
  }
  
  public oonoon() {}
  
  public static int b006B006Bkkk006B006Bkk006B()
  {
    return 1;
  }
  
  public static void b006Bkk006Bk006B006Bkk006B(Application paramApplication)
  {
    if (bn006E006E006E006E006E006E006E006E == null)
    {
      bn006E006E006E006E006E006E006E006E = new oonoon();
      int i = b0066ff0066fffff;
      int j = b00660066f0066fffff;
      int k = b0066ff0066fffff;
      int m = bff00660066fffff;
      if ((b0066ff0066fffff + b00660066f0066fffff) * b0066ff0066fffff % bff00660066fffff != bf0066f0066fffff)
      {
        b0066ff0066fffff = 10;
        bf0066f0066fffff = bkk006Bkk006B006Bkk006B();
      }
      if ((i + j) * k % m != bk006Bkkk006B006Bkk006B())
      {
        b0066ff0066fffff = 77;
        bf0066f0066fffff = bkk006Bkk006B006Bkk006B();
      }
      paramApplication.registerActivityLifecycleCallbacks(bn006E006E006E006E006E006E006E006E);
    }
  }
  
  public static int b006Bkkkk006B006Bkk006B()
  {
    return 2;
  }
  
  public static void bk006B006B006Bk006B006Bkk006B(Application paramApplication)
  {
    paramApplication.unregisterActivityLifecycleCallbacks(bn006E006E006E006E006E006E006E006E);
    bn006E006E006E006E006E006E006E006E = null;
    if ((b0066ff0066fffff + b00660066f0066fffff) * b0066ff0066fffff % bff00660066fffff != bf0066f0066fffff)
    {
      b0066ff0066fffff = 77;
      bf0066f0066fffff = bkk006Bkk006B006Bkk006B();
      if ((b0066ff0066fffff + b00660066f0066fffff) * b0066ff0066fffff % b006Bkkkk006B006Bkk006B() != bf0066f0066fffff)
      {
        b0066ff0066fffff = bkk006Bkk006B006Bkk006B();
        bf0066f0066fffff = 60;
      }
    }
  }
  
  public static oonoon bk006B006Bkk006B006Bkk006B()
  {
    oonoon localOonoon = bn006E006E006E006E006E006E006E006E;
    int i = b0066ff0066fffff;
    int j = b00660066f0066fffff;
    int k = b006Bkkkk006B006Bkk006B();
    if ((b0066ff0066fffff + b00660066f0066fffff) * b0066ff0066fffff % bff00660066fffff != bk006Bkkk006B006Bkk006B())
    {
      b0066ff0066fffff = 85;
      bf0066f0066fffff = 59;
    }
    switch (i * (j + i) % k)
    {
    default: 
      b0066ff0066fffff = 76;
      bf0066f0066fffff = 30;
    }
    return localOonoon;
  }
  
  public static int bk006Bkkk006B006Bkk006B()
  {
    return 0;
  }
  
  public static int bkk006Bkk006B006Bkk006B()
  {
    return 50;
  }
  
  public int b006B006B006Bkk006B006Bkk006B()
  {
    int i = b0066ff0066fffff;
    switch (i * (b00660066f0066fffff + i) % bff00660066fffff)
    {
    default: 
      b0066ff0066fffff = 34;
      bf0066f0066fffff = 66;
      i = b0066ff0066fffff;
      switch (i * (b00660066f0066fffff + i) % bff00660066fffff)
      {
      default: 
        b0066ff0066fffff = bkk006Bkk006B006Bkk006B();
        bf0066f0066fffff = 59;
      }
      break;
    }
    return this.bf00660066ffffff;
  }
  
  public boolean b006B006Bk006Bk006B006Bkk006B()
  {
    if ((b0066ff0066fffff + b00660066f0066fffff) * b0066ff0066fffff % bff00660066fffff != bf0066f0066fffff)
    {
      int i = bkk006Bkk006B006Bkk006B();
      switch (i * (b00660066f0066fffff + i) % bff00660066fffff)
      {
      default: 
        b0066ff0066fffff = bkk006Bkk006B006Bkk006B();
        bf0066f0066fffff = 32;
      }
      b0066ff0066fffff = bkk006Bkk006B006Bkk006B();
      bf0066f0066fffff = 98;
    }
    return this.bf0066fffffff;
  }
  
  public void b006Bk006B006Bk006B006Bkk006B(onnoon paramOnnoon)
  {
    if ((paramOnnoon != null) && (this.b0066f0066ffffff.contains(paramOnnoon)))
    {
      List localList = this.b0066f0066ffffff;
      int i = b0066ff0066fffff;
      switch (i * (b00660066f0066fffff + i) % bff00660066fffff)
      {
      default: 
        b0066ff0066fffff = 97;
        if ((b0066ff0066fffff + b00660066f0066fffff) * b0066ff0066fffff % bff00660066fffff != bf0066f0066fffff)
        {
          b0066ff0066fffff = bkk006Bkk006B006Bkk006B();
          bf0066f0066fffff = bkk006Bkk006B006Bkk006B();
        }
        bf0066f0066fffff = 68;
      }
      localList.remove(paramOnnoon);
    }
  }
  
  public void b006Bk006Bkk006B006Bkk006B()
  {
    List localList = this.b0066f0066ffffff;
    if ((b0066ff0066fffff + b00660066f0066fffff) * b0066ff0066fffff % bff00660066fffff != bf0066f0066fffff)
    {
      b0066ff0066fffff = 52;
      bf0066f0066fffff = 19;
      int i = b0066ff0066fffff;
      switch (i * (b00660066f0066fffff + i) % bff00660066fffff)
      {
      default: 
        b0066ff0066fffff = 17;
        bf0066f0066fffff = 31;
      }
    }
    localList.clear();
  }
  
  public boolean bk006Bk006Bk006B006Bkk006B()
  {
    boolean bool;
    if (!this.bf0066fffffff) {
      bool = true;
    }
    do
    {
      return bool;
      bool = false;
    } while ((b0066ff0066fffff + b00660066f0066fffff) * b0066ff0066fffff % bff00660066fffff == bf0066f0066fffff);
    int i = b0066ff0066fffff;
    switch (i * (b00660066f0066fffff + i) % bff00660066fffff)
    {
    default: 
      b0066ff0066fffff = bkk006Bkk006B006Bkk006B();
      bf0066f0066fffff = bkk006Bkk006B006Bkk006B();
    }
    b0066ff0066fffff = bkk006Bkk006B006Bkk006B();
    bf0066f0066fffff = bkk006Bkk006B006Bkk006B();
    return false;
  }
  
  public boolean bkk006B006Bk006B006Bkk006B()
  {
    boolean bool = this.bff0066ffffff;
    if ((b0066ff0066fffff + b00660066f0066fffff) * b0066ff0066fffff % bff00660066fffff != bk006Bkkk006B006Bkk006B())
    {
      b0066ff0066fffff = 92;
      bf0066f0066fffff = 21;
      if ((b0066ff0066fffff + b00660066f0066fffff) * b0066ff0066fffff % bff00660066fffff != bf0066f0066fffff)
      {
        b0066ff0066fffff = bkk006Bkk006B006Bkk006B();
        bf0066f0066fffff = bkk006Bkk006B006Bkk006B();
      }
    }
    return bool;
  }
  
  public int bkkk006Bk006B006Bkk006B()
  {
    int i = b0066ff0066fffff;
    switch (i * (b00660066f0066fffff + i) % bff00660066fffff)
    {
    default: 
      b0066ff0066fffff = 12;
      bf0066f0066fffff = bkk006Bkk006B006Bkk006B();
    }
    i = this.b006600660066ffffff;
    int j = b0066ff0066fffff;
    switch (j * (b00660066f0066fffff + j) % bff00660066fffff)
    {
    default: 
      b0066ff0066fffff = bkk006Bkk006B006Bkk006B();
      bf0066f0066fffff = 27;
    }
    return i;
  }
  
  public void bkkkkk006B006Bkk006B(onnoon paramOnnoon)
  {
    int i = b0066ff0066fffff;
    switch (i * (b00660066f0066fffff + i) % bff00660066fffff)
    {
    default: 
      b0066ff0066fffff = 87;
      bf0066f0066fffff = bkk006Bkk006B006Bkk006B();
    }
    if (!this.b0066f0066ffffff.contains(paramOnnoon))
    {
      i = bkk006Bkk006B006Bkk006B();
      switch (i * (b00660066f0066fffff + i) % bff00660066fffff)
      {
      default: 
        b0066ff0066fffff = 45;
        bf0066f0066fffff = bkk006Bkk006B006Bkk006B();
      }
      this.b0066f0066ffffff.add(paramOnnoon);
    }
  }
  
  public void onActivityCreated(Activity paramActivity, Bundle paramBundle) {}
  
  public void onActivityDestroyed(Activity paramActivity) {}
  
  public void onActivityPaused(Activity paramActivity)
  {
    if ((b0066ff0066fffff + b00660066f0066fffff) * b0066ff0066fffff % bff00660066fffff != bf0066f0066fffff)
    {
      b0066ff0066fffff = 13;
      bf0066f0066fffff = bkk006Bkk006B006Bkk006B();
    }
    this.bf00660066ffffff += 1;
    this.bff0066ffffff = true;
    if (this.bfff0066fffff != null) {
      this.b00660066fffffff.removeCallbacks(this.bfff0066fffff);
    }
    if ((b0066ff0066fffff + b00660066f0066fffff) * b0066ff0066fffff % bff00660066fffff != bk006Bkkk006B006Bkk006B())
    {
      b0066ff0066fffff = bkk006Bkk006B006Bkk006B();
      bf0066f0066fffff = bkk006Bkk006B006Bkk006B();
    }
    this.bfff0066fffff = new oonoon.1(this);
    this.b00660066fffffff.postDelayed(this.bfff0066fffff, 500L);
  }
  
  /* Error */
  public void onActivityResumed(Activity paramActivity)
  {
    // Byte code:
    //   0: aload_0
    //   1: iconst_0
    //   2: putfield 75	uuuuuu/oonoon:bff0066ffffff	Z
    //   5: aload_0
    //   6: aload_0
    //   7: getfield 79	uuuuuu/oonoon:b006600660066ffffff	I
    //   10: iconst_1
    //   11: iadd
    //   12: putfield 79	uuuuuu/oonoon:b006600660066ffffff	I
    //   15: getstatic 47	uuuuuu/oonoon:b0066ff0066fffff	I
    //   18: getstatic 49	uuuuuu/oonoon:b00660066f0066fffff	I
    //   21: iadd
    //   22: getstatic 47	uuuuuu/oonoon:b0066ff0066fffff	I
    //   25: imul
    //   26: getstatic 51	uuuuuu/oonoon:bff00660066fffff	I
    //   29: irem
    //   30: invokestatic 108	uuuuuu/oonoon:bk006Bkkk006B006Bkk006B	()I
    //   33: if_icmpeq +14 -> 47
    //   36: bipush 9
    //   38: putstatic 47	uuuuuu/oonoon:b0066ff0066fffff	I
    //   41: invokestatic 57	uuuuuu/oonoon:bkk006Bkk006B006Bkk006B	()I
    //   44: putstatic 53	uuuuuu/oonoon:bf0066f0066fffff	I
    //   47: aload_0
    //   48: getfield 73	uuuuuu/oonoon:bf0066fffffff	Z
    //   51: ifne +398 -> 449
    //   54: iconst_1
    //   55: istore_2
    //   56: aload_0
    //   57: iconst_1
    //   58: putfield 73	uuuuuu/oonoon:bf0066fffffff	Z
    //   61: aload_0
    //   62: getfield 94	uuuuuu/oonoon:bfff0066fffff	Ljava/lang/Runnable;
    //   65: ifnull +14 -> 79
    //   68: aload_0
    //   69: getfield 92	uuuuuu/oonoon:b00660066fffffff	Landroid/os/Handler;
    //   72: aload_0
    //   73: getfield 94	uuuuuu/oonoon:bfff0066fffff	Ljava/lang/Runnable;
    //   76: invokevirtual 159	android/os/Handler:removeCallbacks	(Ljava/lang/Runnable;)V
    //   79: iload_2
    //   80: ifeq +270 -> 350
    //   83: getstatic 45	uuuuuu/oonoon:b006En006E006E006E006E006E006E006E	Ljava/lang/String;
    //   86: astore_1
    //   87: ldc -79
    //   89: ldc -77
    //   91: sipush 158
    //   94: iconst_4
    //   95: invokestatic 185	xxxxxx/uxxxxx:bb00620062bb0062b0062b0062	(Ljava/lang/String;CC)Ljava/lang/String;
    //   98: iconst_4
    //   99: anewarray 39	java/lang/Class
    //   102: dup
    //   103: iconst_0
    //   104: ldc -69
    //   106: aastore
    //   107: dup
    //   108: iconst_1
    //   109: getstatic 193	java/lang/Character:TYPE	Ljava/lang/Class;
    //   112: aastore
    //   113: dup
    //   114: iconst_2
    //   115: getstatic 193	java/lang/Character:TYPE	Ljava/lang/Class;
    //   118: aastore
    //   119: dup
    //   120: iconst_3
    //   121: getstatic 193	java/lang/Character:TYPE	Ljava/lang/Class;
    //   124: aastore
    //   125: invokevirtual 197	java/lang/Class:getMethod	(Ljava/lang/String;[Ljava/lang/Class;)Ljava/lang/reflect/Method;
    //   128: astore_3
    //   129: aload_3
    //   130: aconst_null
    //   131: iconst_4
    //   132: anewarray 4	java/lang/Object
    //   135: dup
    //   136: iconst_0
    //   137: ldc -57
    //   139: aastore
    //   140: dup
    //   141: iconst_1
    //   142: sipush 240
    //   145: invokestatic 203	java/lang/Character:valueOf	(C)Ljava/lang/Character;
    //   148: aastore
    //   149: dup
    //   150: iconst_2
    //   151: bipush 30
    //   153: invokestatic 203	java/lang/Character:valueOf	(C)Ljava/lang/Character;
    //   156: aastore
    //   157: dup
    //   158: iconst_3
    //   159: iconst_2
    //   160: invokestatic 203	java/lang/Character:valueOf	(C)Ljava/lang/Character;
    //   163: aastore
    //   164: invokevirtual 209	java/lang/reflect/Method:invoke	(Ljava/lang/Object;[Ljava/lang/Object;)Ljava/lang/Object;
    //   167: astore_3
    //   168: aload_1
    //   169: aload_3
    //   170: checkcast 187	java/lang/String
    //   173: invokestatic 215	uuuuuu/rvvvrv:bqq0071q00710071q0071q0071	(Ljava/lang/String;Ljava/lang/String;)V
    //   176: aload_0
    //   177: getfield 71	uuuuuu/oonoon:b0066f0066ffffff	Ljava/util/List;
    //   180: invokeinterface 219 1 0
    //   185: astore_1
    //   186: getstatic 47	uuuuuu/oonoon:b0066ff0066fffff	I
    //   189: istore_2
    //   190: iload_2
    //   191: getstatic 49	uuuuuu/oonoon:b00660066f0066fffff	I
    //   194: iload_2
    //   195: iadd
    //   196: imul
    //   197: getstatic 51	uuuuuu/oonoon:bff00660066fffff	I
    //   200: irem
    //   201: tableswitch	default:+19->220, 0:+30->231
    //   220: bipush 44
    //   222: putstatic 47	uuuuuu/oonoon:b0066ff0066fffff	I
    //   225: invokestatic 57	uuuuuu/oonoon:bkk006Bkk006B006Bkk006B	()I
    //   228: putstatic 53	uuuuuu/oonoon:bf0066f0066fffff	I
    //   231: aload_1
    //   232: invokeinterface 224 1 0
    //   237: ifeq +193 -> 430
    //   240: aload_1
    //   241: invokeinterface 228 1 0
    //   246: checkcast 8	uuuuuu/oonoon$onnoon
    //   249: astore_3
    //   250: aload_3
    //   251: invokeinterface 231 1 0
    //   256: goto -25 -> 231
    //   259: astore_3
    //   260: getstatic 45	uuuuuu/oonoon:b006En006E006E006E006E006E006E006E	Ljava/lang/String;
    //   263: astore 4
    //   265: ldc -79
    //   267: ldc -23
    //   269: bipush 97
    //   271: bipush 32
    //   273: iconst_2
    //   274: invokestatic 237	xxxxxx/uxxxxx:bbbb0062b0062b0062b0062	(Ljava/lang/String;CCC)Ljava/lang/String;
    //   277: iconst_3
    //   278: anewarray 39	java/lang/Class
    //   281: dup
    //   282: iconst_0
    //   283: ldc -69
    //   285: aastore
    //   286: dup
    //   287: iconst_1
    //   288: getstatic 193	java/lang/Character:TYPE	Ljava/lang/Class;
    //   291: aastore
    //   292: dup
    //   293: iconst_2
    //   294: getstatic 193	java/lang/Character:TYPE	Ljava/lang/Class;
    //   297: aastore
    //   298: invokevirtual 197	java/lang/Class:getMethod	(Ljava/lang/String;[Ljava/lang/Class;)Ljava/lang/reflect/Method;
    //   301: astore 5
    //   303: aload 5
    //   305: aconst_null
    //   306: iconst_3
    //   307: anewarray 4	java/lang/Object
    //   310: dup
    //   311: iconst_0
    //   312: ldc -17
    //   314: aastore
    //   315: dup
    //   316: iconst_1
    //   317: sipush 219
    //   320: invokestatic 203	java/lang/Character:valueOf	(C)Ljava/lang/Character;
    //   323: aastore
    //   324: dup
    //   325: iconst_2
    //   326: iconst_0
    //   327: invokestatic 203	java/lang/Character:valueOf	(C)Ljava/lang/Character;
    //   330: aastore
    //   331: invokevirtual 209	java/lang/reflect/Method:invoke	(Ljava/lang/Object;[Ljava/lang/Object;)Ljava/lang/Object;
    //   334: astore 5
    //   336: aload 4
    //   338: aload 5
    //   340: checkcast 187	java/lang/String
    //   343: aload_3
    //   344: invokestatic 243	uuuuuu/rvvvrv:b00710071qq00710071q0071q0071	(Ljava/lang/String;Ljava/lang/String;Ljava/lang/Throwable;)V
    //   347: goto -116 -> 231
    //   350: getstatic 45	uuuuuu/oonoon:b006En006E006E006E006E006E006E006E	Ljava/lang/String;
    //   353: astore_1
    //   354: ldc -79
    //   356: ldc -11
    //   358: sipush 225
    //   361: bipush 12
    //   363: iconst_0
    //   364: invokestatic 237	xxxxxx/uxxxxx:bbbb0062b0062b0062b0062	(Ljava/lang/String;CCC)Ljava/lang/String;
    //   367: iconst_3
    //   368: anewarray 39	java/lang/Class
    //   371: dup
    //   372: iconst_0
    //   373: ldc -69
    //   375: aastore
    //   376: dup
    //   377: iconst_1
    //   378: getstatic 193	java/lang/Character:TYPE	Ljava/lang/Class;
    //   381: aastore
    //   382: dup
    //   383: iconst_2
    //   384: getstatic 193	java/lang/Character:TYPE	Ljava/lang/Class;
    //   387: aastore
    //   388: invokevirtual 197	java/lang/Class:getMethod	(Ljava/lang/String;[Ljava/lang/Class;)Ljava/lang/reflect/Method;
    //   391: astore_3
    //   392: aload_3
    //   393: aconst_null
    //   394: iconst_3
    //   395: anewarray 4	java/lang/Object
    //   398: dup
    //   399: iconst_0
    //   400: ldc -9
    //   402: aastore
    //   403: dup
    //   404: iconst_1
    //   405: bipush 8
    //   407: invokestatic 203	java/lang/Character:valueOf	(C)Ljava/lang/Character;
    //   410: aastore
    //   411: dup
    //   412: iconst_2
    //   413: iconst_5
    //   414: invokestatic 203	java/lang/Character:valueOf	(C)Ljava/lang/Character;
    //   417: aastore
    //   418: invokevirtual 209	java/lang/reflect/Method:invoke	(Ljava/lang/Object;[Ljava/lang/Object;)Ljava/lang/Object;
    //   421: astore_3
    //   422: aload_1
    //   423: aload_3
    //   424: checkcast 187	java/lang/String
    //   427: invokestatic 215	uuuuuu/rvvvrv:bqq0071q00710071q0071q0071	(Ljava/lang/String;Ljava/lang/String;)V
    //   430: return
    //   431: astore_1
    //   432: aload_1
    //   433: invokevirtual 251	java/lang/reflect/InvocationTargetException:getCause	()Ljava/lang/Throwable;
    //   436: athrow
    //   437: astore_1
    //   438: aload_1
    //   439: invokevirtual 251	java/lang/reflect/InvocationTargetException:getCause	()Ljava/lang/Throwable;
    //   442: athrow
    //   443: astore_1
    //   444: aload_1
    //   445: invokevirtual 251	java/lang/reflect/InvocationTargetException:getCause	()Ljava/lang/Throwable;
    //   448: athrow
    //   449: iconst_0
    //   450: istore_2
    //   451: goto -395 -> 56
    // Local variable table:
    //   start	length	slot	name	signature
    //   0	454	0	this	oonoon
    //   0	454	1	paramActivity	Activity
    //   55	396	2	i	int
    //   128	123	3	localObject1	Object
    //   259	85	3	localException	Exception
    //   391	33	3	localObject2	Object
    //   263	74	4	str	String
    //   301	38	5	localObject3	Object
    // Exception table:
    //   from	to	target	type
    //   250	256	259	java/lang/Exception
    //   392	422	431	java/lang/reflect/InvocationTargetException
    //   129	168	437	java/lang/reflect/InvocationTargetException
    //   303	336	443	java/lang/reflect/InvocationTargetException
  }
  
  public void onActivitySaveInstanceState(Activity paramActivity, Bundle paramBundle) {}
  
  public void onActivityStarted(Activity paramActivity) {}
  
  public void onActivityStopped(Activity paramActivity) {}
  
  public static abstract interface onnoon
  {
    public abstract void onBecameBackground();
    
    public abstract void onBecameForeground();
  }
}
