package uuuuuu;

import com.google.gson.Gson;
import java.io.UnsupportedEncodingException;
import java.lang.reflect.InvocationTargetException;
import java.lang.reflect.Method;
import java.net.URLEncoder;
import java.util.HashMap;
import java.util.Iterator;
import java.util.Map;
import java.util.Map.Entry;
import java.util.Set;
import xxxxxx.uxxxxx;

public class ooooll<T, R>
  extends ololol<R>
{
  public static int b00710071qq0071qq00710071 = 0;
  public static int b0071q0071q0071qq00710071 = 2;
  private static final String bq007100710071qqq00710071 = ooooll.class.getName();
  public static int bq0071qq0071qq00710071 = 64;
  public static int bqq0071q0071qq00710071 = 1;
  private String b0071007100710071qqq00710071;
  private String b0071qqq0071qq00710071;
  private Map<String, String> bqqqq0071qq00710071;
  
  static
  {
    if ((bq0071qq0071qq00710071 + bqq0071q0071qq00710071) * bq0071qq0071qq00710071 % b0071q0071q0071qq00710071 != b00710071qq0071qq00710071)
    {
      bq0071qq0071qq00710071 = 68;
      int i = bq0071qq0071qq00710071;
      switch (i * (b0070p0070ppp0070p00700070() + i) % b0071q0071q0071qq00710071)
      {
      default: 
        bq0071qq0071qq00710071 = b007000700070ppp0070p00700070();
        b00710071qq0071qq00710071 = 60;
      }
      b00710071qq0071qq00710071 = 93;
    }
  }
  
  public ooooll(int paramInt, String paramString, T paramT, Gson paramGson, loolol<R> paramLoolol)
  {
    this(paramInt, paramString, paramLoolol);
    bp0070pppp0070p00700070(paramT, paramGson);
  }
  
  public ooooll(int paramInt, String paramString, T paramT, loolol<R> paramLoolol)
  {
    this(paramInt, paramString, paramLoolol);
    b0070ppppp0070p00700070(paramT);
  }
  
  private ooooll(int paramInt, String paramString, loolol<R> paramLoolol)
  {
    super(paramInt, paramString, paramLoolol);
    paramString = ppphhp.class.getMethod(uxxxxx.bbbb0062b0062b0062b0062("Wkjih \037%$\034\033! _\027\026\034\033\023\022\030\027V", '±', '\'', '\001'), new Class[] { String.class, Character.TYPE, Character.TYPE });
    try
    {
      paramString = paramString.invoke(null, new Object[] { "9IJGE@?SIPP\022NXUU#\tMSM_aTd.GG:\".", Character.valueOf('\035'), Character.valueOf('\000') });
      this.b0071007100710071qqq00710071 = ((String)paramString);
      return;
    }
    catch (InvocationTargetException paramString)
    {
      throw paramString.getCause();
    }
  }
  
  public ooooll(String paramString)
  {
    super(1, paramString);
    paramString = ppphhp.class.getMethod(uxxxxx.bbbb0062b0062b0062b0062("&:987nmsrjion.edjia`fe%", '&', 'i', '\001'), new Class[] { String.class, Character.TYPE, Character.TYPE });
    try
    {
      paramString = paramString.invoke(null, new Object[] { ".<;62+(:.31p+3.,w[\036\"\032**\033)p\b\006v\\f", Character.valueOf('²'), Character.valueOf('\003') });
      this.b0071007100710071qqq00710071 = ((String)paramString);
      return;
    }
    catch (InvocationTargetException paramString)
    {
      throw paramString.getCause();
    }
  }
  
  public ooooll(String paramString, T paramT, Gson paramGson, loolol<R> paramLoolol)
  {
    this(1, paramString, paramT, paramGson, paramLoolol);
  }
  
  public ooooll(String paramString, T paramT, loolol<R> paramLoolol)
  {
    this(1, paramString, paramT, paramLoolol);
  }
  
  public ooooll(String paramString, Map<String, String> paramMap, loolol<R> paramLoolol)
  {
    this(1, paramString, paramLoolol);
    bpp0070ppp0070p00700070(paramMap);
  }
  
  public static int b007000700070ppp0070p00700070()
  {
    return 34;
  }
  
  private void b00700070pppp0070p00700070(String paramString1, String paramString2)
  {
    if (this.b0071qqq0071qq00710071 != null) {
      paramString1 = ppphhp.class.getMethod(uxxxxx.bb00620062bb0062b0062b0062("cw/.43rq)(.-%$*)h \037%$\034\033! _", '©', '\005'), new Class[] { String.class, Character.TYPE, Character.TYPE, Character.TYPE });
    }
    try
    {
      paramString1 = paramString1.invoke(null, new Object[] { "&PXMR{H?:FvJDs@3<5nB55>i*g1942b$0$8]/!,/\036++U$&R\023P\026\036 \032X \034\025\r\025\t\024\b\b\006@\022\004\017\022\001\016\016W7_{4|\0078\004/o-rz|v(ku%rrv!urc\035\037\\^]:fZn\034\034", Character.valueOf('ê'), Character.valueOf('M'), Character.valueOf('\001') });
      throw new IllegalArgumentException((String)paramString1);
    }
    catch (InvocationTargetException paramString1)
    {
      try
      {
        StringBuilder localStringBuilder;
        int i;
        int j;
        int k;
        Object localObject = ((Method)localObject).invoke(null, new Object[] { "\001\017\016\t\005}z\r\001\006\004C\f?\t\b\007;s{}w6}yrjrfqeec9\035_c[kk\\j2", Character.valueOf('¾'), Character.valueOf('^'), Character.valueOf('\001') });
        this.b0071007100710071qqq00710071 = ((String)localObject + bp0070pp00700070pp00700070());
        if (this.bqqqq0071qq00710071 == null) {
          this.bqqqq0071qq00710071 = new HashMap();
        }
        this.bqqqq0071qq00710071.put(paramString1, paramString2);
        return;
      }
      catch (InvocationTargetException paramString1)
      {
        throw paramString1.getCause();
      }
      paramString1 = paramString1;
      throw paramString1.getCause();
    }
    localStringBuilder = new StringBuilder();
    i = bq0071qq0071qq00710071;
    j = bqq0071q0071qq00710071;
    k = bq0071qq0071qq00710071;
    switch (k * (bqq0071q0071qq00710071 + k) % b0071q0071q0071qq00710071)
    {
    default: 
      bq0071qq0071qq00710071 = 10;
      b00710071qq0071qq00710071 = 35;
    }
    if ((i + j) * bq0071qq0071qq00710071 % b0071q0071q0071qq00710071 != b00710071qq0071qq00710071)
    {
      bq0071qq0071qq00710071 = 13;
      b00710071qq0071qq00710071 = 5;
    }
    localObject = ppphhp.class.getMethod(uxxxxx.bbbb0062b0062b0062b0062("\0375nowx:;tu}~xy\002\003D}~\007\b\002\003\013\fM", '', '»', '\003'), new Class[] { String.class, Character.TYPE, Character.TYPE, Character.TYPE });
  }
  
  public static int b0070p0070ppp0070p00700070()
  {
    return 1;
  }
  
  private void b0070ppppp0070p00700070(T paramT)
  {
    Gson localGson = new Gson();
    int i = bq0071qq0071qq00710071;
    int j = bqq0071q0071qq00710071;
    if ((bq0071qq0071qq00710071 + bqq0071q0071qq00710071) * bq0071qq0071qq00710071 % b0071q0071q0071qq00710071 != b00710071qq0071qq00710071)
    {
      bq0071qq0071qq00710071 = 63;
      b00710071qq0071qq00710071 = 29;
    }
    if ((i + j) * bq0071qq0071qq00710071 % b0071q0071q0071qq00710071 != b00710071qq0071qq00710071)
    {
      bq0071qq0071qq00710071 = b007000700070ppp0070p00700070();
      b00710071qq0071qq00710071 = b007000700070ppp0070p00700070();
    }
    bp0070pppp0070p00700070(paramT, localGson);
  }
  
  public static int bp00700070ppp0070p00700070()
  {
    return 2;
  }
  
  private String bp0070p0070pp0070p00700070(Map<String, String> paramMap, String paramString)
    throws UnsupportedEncodingException
  {
    StringBuilder localStringBuilder = new StringBuilder();
    paramMap = paramMap.entrySet().iterator();
    while (paramMap.hasNext())
    {
      Map.Entry localEntry = (Map.Entry)paramMap.next();
      localStringBuilder.append(URLEncoder.encode((String)localEntry.getKey(), paramString));
      if ((bq0071qq0071qq00710071 + b0070p0070ppp0070p00700070()) * bq0071qq0071qq00710071 % b0071q0071q0071qq00710071 != b00710071qq0071qq00710071)
      {
        bq0071qq0071qq00710071 = b007000700070ppp0070p00700070();
        b00710071qq0071qq00710071 = 2;
        int i = bq0071qq0071qq00710071;
        switch (i * (b0070p0070ppp0070p00700070() + i) % b0071q0071q0071qq00710071)
        {
        default: 
          bq0071qq0071qq00710071 = b007000700070ppp0070p00700070();
          b00710071qq0071qq00710071 = 96;
        }
      }
      localStringBuilder.append('=');
      localStringBuilder.append(URLEncoder.encode((String)localEntry.getValue(), paramString));
      localStringBuilder.append('&');
    }
    return localStringBuilder.toString();
  }
  
  /* Error */
  private void bp0070pppp0070p00700070(T paramT, Gson paramGson)
  {
    // Byte code:
    //   0: aload_0
    //   1: getfield 168	uuuuuu/ooooll:bqqqq0071qq00710071	Ljava/util/Map;
    //   4: ifnull +81 -> 85
    //   7: ldc 69
    //   9: ldc -29
    //   11: sipush 143
    //   14: iconst_1
    //   15: invokestatic 142	xxxxxx/uxxxxx:bb00620062bb0062b0062b0062	(Ljava/lang/String;CC)Ljava/lang/String;
    //   18: iconst_3
    //   19: anewarray 25	java/lang/Class
    //   22: dup
    //   23: iconst_0
    //   24: ldc 79
    //   26: aastore
    //   27: dup
    //   28: iconst_1
    //   29: getstatic 85	java/lang/Character:TYPE	Ljava/lang/Class;
    //   32: aastore
    //   33: dup
    //   34: iconst_2
    //   35: getstatic 85	java/lang/Character:TYPE	Ljava/lang/Class;
    //   38: aastore
    //   39: invokevirtual 89	java/lang/Class:getMethod	(Ljava/lang/String;[Ljava/lang/Class;)Ljava/lang/reflect/Method;
    //   42: astore_1
    //   43: aload_1
    //   44: aconst_null
    //   45: iconst_3
    //   46: anewarray 91	java/lang/Object
    //   49: dup
    //   50: iconst_0
    //   51: ldc -27
    //   53: aastore
    //   54: dup
    //   55: iconst_1
    //   56: bipush 48
    //   58: invokestatic 97	java/lang/Character:valueOf	(C)Ljava/lang/Character;
    //   61: aastore
    //   62: dup
    //   63: iconst_2
    //   64: iconst_0
    //   65: invokestatic 97	java/lang/Character:valueOf	(C)Ljava/lang/Character;
    //   68: aastore
    //   69: invokevirtual 103	java/lang/reflect/Method:invoke	(Ljava/lang/Object;[Ljava/lang/Object;)Ljava/lang/Object;
    //   72: astore_1
    //   73: new 146	java/lang/IllegalArgumentException
    //   76: dup
    //   77: aload_1
    //   78: checkcast 79	java/lang/String
    //   81: invokespecial 148	java/lang/IllegalArgumentException:<init>	(Ljava/lang/String;)V
    //   84: athrow
    //   85: new 150	java/lang/StringBuilder
    //   88: dup
    //   89: invokespecial 152	java/lang/StringBuilder:<init>	()V
    //   92: astore 4
    //   94: ldc 69
    //   96: ldc -25
    //   98: bipush 41
    //   100: iconst_0
    //   101: invokestatic 142	xxxxxx/uxxxxx:bb00620062bb0062b0062b0062	(Ljava/lang/String;CC)Ljava/lang/String;
    //   104: iconst_3
    //   105: anewarray 25	java/lang/Class
    //   108: dup
    //   109: iconst_0
    //   110: ldc 79
    //   112: aastore
    //   113: dup
    //   114: iconst_1
    //   115: getstatic 85	java/lang/Character:TYPE	Ljava/lang/Class;
    //   118: aastore
    //   119: dup
    //   120: iconst_2
    //   121: getstatic 85	java/lang/Character:TYPE	Ljava/lang/Class;
    //   124: aastore
    //   125: invokevirtual 89	java/lang/Class:getMethod	(Ljava/lang/String;[Ljava/lang/Class;)Ljava/lang/reflect/Method;
    //   128: astore 5
    //   130: aload 5
    //   132: aconst_null
    //   133: iconst_3
    //   134: anewarray 91	java/lang/Object
    //   137: dup
    //   138: iconst_0
    //   139: ldc -23
    //   141: aastore
    //   142: dup
    //   143: iconst_1
    //   144: sipush 210
    //   147: invokestatic 97	java/lang/Character:valueOf	(C)Ljava/lang/Character;
    //   150: aastore
    //   151: dup
    //   152: iconst_2
    //   153: iconst_3
    //   154: invokestatic 97	java/lang/Character:valueOf	(C)Ljava/lang/Character;
    //   157: aastore
    //   158: invokevirtual 103	java/lang/reflect/Method:invoke	(Ljava/lang/Object;[Ljava/lang/Object;)Ljava/lang/Object;
    //   161: astore 5
    //   163: aload 4
    //   165: aload 5
    //   167: checkcast 79	java/lang/String
    //   170: invokevirtual 160	java/lang/StringBuilder:append	(Ljava/lang/String;)Ljava/lang/StringBuilder;
    //   173: astore 4
    //   175: aload_0
    //   176: invokevirtual 163	uuuuuu/ooooll:bp0070pp00700070pp00700070	()Ljava/lang/String;
    //   179: astore 5
    //   181: getstatic 33	uuuuuu/ooooll:bq0071qq0071qq00710071	I
    //   184: istore_3
    //   185: iload_3
    //   186: getstatic 35	uuuuuu/ooooll:bqq0071q0071qq00710071	I
    //   189: iload_3
    //   190: iadd
    //   191: imul
    //   192: getstatic 37	uuuuuu/ooooll:b0071q0071q0071qq00710071	I
    //   195: irem
    //   196: tableswitch	default:+20->216, 0:+31->227
    //   216: invokestatic 46	uuuuuu/ooooll:b007000700070ppp0070p00700070	()I
    //   219: putstatic 33	uuuuuu/ooooll:bq0071qq0071qq00710071	I
    //   222: bipush 91
    //   224: putstatic 39	uuuuuu/ooooll:b00710071qq0071qq00710071	I
    //   227: aload 4
    //   229: aload 5
    //   231: invokevirtual 160	java/lang/StringBuilder:append	(Ljava/lang/String;)Ljava/lang/StringBuilder;
    //   234: astore 4
    //   236: getstatic 33	uuuuuu/ooooll:bq0071qq0071qq00710071	I
    //   239: istore_3
    //   240: iload_3
    //   241: getstatic 35	uuuuuu/ooooll:bqq0071q0071qq00710071	I
    //   244: iload_3
    //   245: iadd
    //   246: imul
    //   247: getstatic 37	uuuuuu/ooooll:b0071q0071q0071qq00710071	I
    //   250: irem
    //   251: tableswitch	default:+17->268, 0:+29->280
    //   268: invokestatic 46	uuuuuu/ooooll:b007000700070ppp0070p00700070	()I
    //   271: putstatic 33	uuuuuu/ooooll:bq0071qq0071qq00710071	I
    //   274: invokestatic 46	uuuuuu/ooooll:b007000700070ppp0070p00700070	()I
    //   277: putstatic 39	uuuuuu/ooooll:b00710071qq0071qq00710071	I
    //   280: aload_0
    //   281: aload 4
    //   283: invokevirtual 166	java/lang/StringBuilder:toString	()Ljava/lang/String;
    //   286: putfield 105	uuuuuu/ooooll:b0071007100710071qqq00710071	Ljava/lang/String;
    //   289: aload_0
    //   290: aload_2
    //   291: aload_1
    //   292: invokevirtual 237	com/google/gson/Gson:toJson	(Ljava/lang/Object;)Ljava/lang/String;
    //   295: putfield 136	uuuuuu/ooooll:b0071qqq0071qq00710071	Ljava/lang/String;
    //   298: getstatic 31	uuuuuu/ooooll:bq007100710071qqq00710071	Ljava/lang/String;
    //   301: astore_1
    //   302: new 150	java/lang/StringBuilder
    //   305: dup
    //   306: invokespecial 152	java/lang/StringBuilder:<init>	()V
    //   309: aload_0
    //   310: invokevirtual 240	uuuuuu/ooooll:b007000700070p00700070pp00700070	()Ljava/lang/String;
    //   313: invokevirtual 160	java/lang/StringBuilder:append	(Ljava/lang/String;)Ljava/lang/StringBuilder;
    //   316: astore_2
    //   317: ldc 69
    //   319: ldc -14
    //   321: sipush 150
    //   324: sipush 135
    //   327: iconst_2
    //   328: invokestatic 77	xxxxxx/uxxxxx:bbbb0062b0062b0062b0062	(Ljava/lang/String;CCC)Ljava/lang/String;
    //   331: iconst_3
    //   332: anewarray 25	java/lang/Class
    //   335: dup
    //   336: iconst_0
    //   337: ldc 79
    //   339: aastore
    //   340: dup
    //   341: iconst_1
    //   342: getstatic 85	java/lang/Character:TYPE	Ljava/lang/Class;
    //   345: aastore
    //   346: dup
    //   347: iconst_2
    //   348: getstatic 85	java/lang/Character:TYPE	Ljava/lang/Class;
    //   351: aastore
    //   352: invokevirtual 89	java/lang/Class:getMethod	(Ljava/lang/String;[Ljava/lang/Class;)Ljava/lang/reflect/Method;
    //   355: astore 4
    //   357: aload 4
    //   359: aconst_null
    //   360: iconst_3
    //   361: anewarray 91	java/lang/Object
    //   364: dup
    //   365: iconst_0
    //   366: ldc -12
    //   368: aastore
    //   369: dup
    //   370: iconst_1
    //   371: bipush 61
    //   373: invokestatic 97	java/lang/Character:valueOf	(C)Ljava/lang/Character;
    //   376: aastore
    //   377: dup
    //   378: iconst_2
    //   379: iconst_4
    //   380: invokestatic 97	java/lang/Character:valueOf	(C)Ljava/lang/Character;
    //   383: aastore
    //   384: invokevirtual 103	java/lang/reflect/Method:invoke	(Ljava/lang/Object;[Ljava/lang/Object;)Ljava/lang/Object;
    //   387: astore 4
    //   389: aload_1
    //   390: aload_2
    //   391: aload 4
    //   393: checkcast 79	java/lang/String
    //   396: invokevirtual 160	java/lang/StringBuilder:append	(Ljava/lang/String;)Ljava/lang/StringBuilder;
    //   399: aload_0
    //   400: getfield 136	uuuuuu/ooooll:b0071qqq0071qq00710071	Ljava/lang/String;
    //   403: invokevirtual 247	java/lang/String:length	()I
    //   406: invokevirtual 250	java/lang/StringBuilder:append	(I)Ljava/lang/StringBuilder;
    //   409: invokevirtual 166	java/lang/StringBuilder:toString	()Ljava/lang/String;
    //   412: invokestatic 255	uuuuuu/rvvvrv:b007100710071q00710071q0071q0071	(Ljava/lang/String;Ljava/lang/String;)V
    //   415: return
    //   416: astore_1
    //   417: aload_1
    //   418: invokevirtual 109	java/lang/reflect/InvocationTargetException:getCause	()Ljava/lang/Throwable;
    //   421: athrow
    //   422: astore_1
    //   423: aload_1
    //   424: invokevirtual 109	java/lang/reflect/InvocationTargetException:getCause	()Ljava/lang/Throwable;
    //   427: athrow
    //   428: astore_1
    //   429: aload_1
    //   430: invokevirtual 109	java/lang/reflect/InvocationTargetException:getCause	()Ljava/lang/Throwable;
    //   433: athrow
    // Local variable table:
    //   start	length	slot	name	signature
    //   0	434	0	this	ooooll
    //   0	434	1	paramT	T
    //   0	434	2	paramGson	Gson
    //   184	63	3	i	int
    //   92	300	4	localObject1	Object
    //   128	102	5	localObject2	Object
    // Exception table:
    //   from	to	target	type
    //   130	163	416	java/lang/reflect/InvocationTargetException
    //   43	73	422	java/lang/reflect/InvocationTargetException
    //   357	389	428	java/lang/reflect/InvocationTargetException
  }
  
  private void bpp0070ppp0070p00700070(Map<String, String> paramMap)
  {
    paramMap = paramMap.entrySet().iterator();
    for (;;)
    {
      boolean bool = paramMap.hasNext();
      if ((bq0071qq0071qq00710071 + bqq0071q0071qq00710071) * bq0071qq0071qq00710071 % b0071q0071q0071qq00710071 != b00710071qq0071qq00710071)
      {
        bq0071qq0071qq00710071 = 18;
        b00710071qq0071qq00710071 = 43;
      }
      if (!bool) {
        break;
      }
      Map.Entry localEntry = (Map.Entry)paramMap.next();
      b00700070pppp0070p00700070((String)localEntry.getKey(), (String)localEntry.getValue());
      if ((bq0071qq0071qq00710071 + bqq0071q0071qq00710071) * bq0071qq0071qq00710071 % bp00700070ppp0070p00700070() != b00710071qq0071qq00710071)
      {
        bq0071qq0071qq00710071 = 54;
        b00710071qq0071qq00710071 = b007000700070ppp0070p00700070();
      }
    }
  }
  
  public Map<String, String> b00700070p0070pp0070p00700070()
  {
    String str = bq007100710071qqq00710071;
    StringBuilder localStringBuilder = new StringBuilder().append(b007000700070p00700070pp00700070());
    if ((b007000700070ppp0070p00700070() + bqq0071q0071qq00710071) * b007000700070ppp0070p00700070() % b0071q0071q0071qq00710071 != b00710071qq0071qq00710071)
    {
      if ((bq0071qq0071qq00710071 + bqq0071q0071qq00710071) * bq0071qq0071qq00710071 % b0071q0071q0071qq00710071 != b00710071qq0071qq00710071)
      {
        bq0071qq0071qq00710071 = b007000700070ppp0070p00700070();
        b00710071qq0071qq00710071 = 70;
      }
      bq0071qq0071qq00710071 = 94;
      b00710071qq0071qq00710071 = 60;
    }
    Object localObject = ppphhp.class.getMethod(uxxxxx.bb00620062bb0062b0062b0062("\022(abjk-.ghpqkltu7pqyztu}~@", '¹', '\000'), new Class[] { String.class, Character.TYPE, Character.TYPE, Character.TYPE });
    try
    {
      localObject = ((Method)localObject).invoke(null, new Object[] { "\013Thuzkz|)Lzp\007.}\006~tx\0075\006}8\n{\016}\013\022Y@", Character.valueOf('°'), Character.valueOf('Î'), Character.valueOf('\003') });
      rvvvrv.b007100710071q00710071q0071q0071(str, (String)localObject + this.bqqqq0071qq00710071.size());
      return this.bqqqq0071qq00710071;
    }
    catch (InvocationTargetException localInvocationTargetException)
    {
      throw localInvocationTargetException.getCause();
    }
  }
  
  public String b0070pp0070pp0070p00700070()
  {
    String str = this.b0071007100710071qqq00710071;
    if ((bq0071qq0071qq00710071 + bqq0071q0071qq00710071) * bq0071qq0071qq00710071 % b0071q0071q0071qq00710071 != b00710071qq0071qq00710071)
    {
      int i = bq0071qq0071qq00710071;
      switch (i * (bqq0071q0071qq00710071 + i) % b0071q0071q0071qq00710071)
      {
      default: 
        bq0071qq0071qq00710071 = b007000700070ppp0070p00700070();
        b00710071qq0071qq00710071 = b007000700070ppp0070p00700070();
      }
      bq0071qq0071qq00710071 = 35;
      b00710071qq0071qq00710071 = b007000700070ppp0070p00700070();
    }
    return str;
  }
  
  /* Error */
  public byte[] bppp0070pp0070p00700070()
    throws com.android.volley.AuthFailureError
  {
    // Byte code:
    //   0: aload_0
    //   1: getfield 168	uuuuuu/ooooll:bqqqq0071qq00710071	Ljava/util/Map;
    //   4: ifnull +429 -> 433
    //   7: aload_0
    //   8: getfield 168	uuuuuu/ooooll:bqqqq0071qq00710071	Ljava/util/Map;
    //   11: invokeinterface 270 1 0
    //   16: ifle +417 -> 433
    //   19: aload_0
    //   20: aload_0
    //   21: getfield 168	uuuuuu/ooooll:bqqqq0071qq00710071	Ljava/util/Map;
    //   24: aload_0
    //   25: invokevirtual 163	uuuuuu/ooooll:bp0070pp00700070pp00700070	()Ljava/lang/String;
    //   28: invokespecial 278	uuuuuu/ooooll:bp0070p0070pp0070p00700070	(Ljava/util/Map;Ljava/lang/String;)Ljava/lang/String;
    //   31: aload_0
    //   32: invokevirtual 163	uuuuuu/ooooll:bp0070pp00700070pp00700070	()Ljava/lang/String;
    //   35: invokevirtual 282	java/lang/String:getBytes	(Ljava/lang/String;)[B
    //   38: astore_1
    //   39: aload_1
    //   40: areturn
    //   41: astore_1
    //   42: new 150	java/lang/StringBuilder
    //   45: dup
    //   46: invokespecial 152	java/lang/StringBuilder:<init>	()V
    //   49: astore_2
    //   50: ldc 69
    //   52: ldc_w 284
    //   55: bipush 87
    //   57: sipush 210
    //   60: iconst_1
    //   61: invokestatic 77	xxxxxx/uxxxxx:bbbb0062b0062b0062b0062	(Ljava/lang/String;CCC)Ljava/lang/String;
    //   64: iconst_4
    //   65: anewarray 25	java/lang/Class
    //   68: dup
    //   69: iconst_0
    //   70: ldc 79
    //   72: aastore
    //   73: dup
    //   74: iconst_1
    //   75: getstatic 85	java/lang/Character:TYPE	Ljava/lang/Class;
    //   78: aastore
    //   79: dup
    //   80: iconst_2
    //   81: getstatic 85	java/lang/Character:TYPE	Ljava/lang/Class;
    //   84: aastore
    //   85: dup
    //   86: iconst_3
    //   87: getstatic 85	java/lang/Character:TYPE	Ljava/lang/Class;
    //   90: aastore
    //   91: invokevirtual 89	java/lang/Class:getMethod	(Ljava/lang/String;[Ljava/lang/Class;)Ljava/lang/reflect/Method;
    //   94: astore_3
    //   95: aload_3
    //   96: aconst_null
    //   97: iconst_4
    //   98: anewarray 91	java/lang/Object
    //   101: dup
    //   102: iconst_0
    //   103: ldc_w 286
    //   106: aastore
    //   107: dup
    //   108: iconst_1
    //   109: sipush 192
    //   112: invokestatic 97	java/lang/Character:valueOf	(C)Ljava/lang/Character;
    //   115: aastore
    //   116: dup
    //   117: iconst_2
    //   118: sipush 148
    //   121: invokestatic 97	java/lang/Character:valueOf	(C)Ljava/lang/Character;
    //   124: aastore
    //   125: dup
    //   126: iconst_3
    //   127: iconst_0
    //   128: invokestatic 97	java/lang/Character:valueOf	(C)Ljava/lang/Character;
    //   131: aastore
    //   132: invokevirtual 103	java/lang/reflect/Method:invoke	(Ljava/lang/Object;[Ljava/lang/Object;)Ljava/lang/Object;
    //   135: astore_3
    //   136: new 288	java/lang/IllegalStateException
    //   139: dup
    //   140: aload_2
    //   141: aload_3
    //   142: checkcast 79	java/lang/String
    //   145: invokevirtual 160	java/lang/StringBuilder:append	(Ljava/lang/String;)Ljava/lang/StringBuilder;
    //   148: aload_0
    //   149: invokevirtual 163	uuuuuu/ooooll:bp0070pp00700070pp00700070	()Ljava/lang/String;
    //   152: invokevirtual 160	java/lang/StringBuilder:append	(Ljava/lang/String;)Ljava/lang/StringBuilder;
    //   155: invokevirtual 166	java/lang/StringBuilder:toString	()Ljava/lang/String;
    //   158: aload_1
    //   159: invokespecial 291	java/lang/IllegalStateException:<init>	(Ljava/lang/String;Ljava/lang/Throwable;)V
    //   162: astore_1
    //   163: invokestatic 46	uuuuuu/ooooll:b007000700070ppp0070p00700070	()I
    //   166: invokestatic 43	uuuuuu/ooooll:b0070p0070ppp0070p00700070	()I
    //   169: iadd
    //   170: invokestatic 46	uuuuuu/ooooll:b007000700070ppp0070p00700070	()I
    //   173: imul
    //   174: getstatic 37	uuuuuu/ooooll:b0071q0071q0071qq00710071	I
    //   177: irem
    //   178: getstatic 39	uuuuuu/ooooll:b00710071qq0071qq00710071	I
    //   181: if_icmpeq +13 -> 194
    //   184: bipush 53
    //   186: putstatic 33	uuuuuu/ooooll:bq0071qq0071qq00710071	I
    //   189: bipush 37
    //   191: putstatic 39	uuuuuu/ooooll:b00710071qq0071qq00710071	I
    //   194: aload_1
    //   195: athrow
    //   196: astore_1
    //   197: aload_1
    //   198: invokevirtual 109	java/lang/reflect/InvocationTargetException:getCause	()Ljava/lang/Throwable;
    //   201: athrow
    //   202: astore_1
    //   203: getstatic 31	uuuuuu/ooooll:bq007100710071qqq00710071	Ljava/lang/String;
    //   206: astore_1
    //   207: new 150	java/lang/StringBuilder
    //   210: dup
    //   211: invokespecial 152	java/lang/StringBuilder:<init>	()V
    //   214: astore_2
    //   215: ldc 69
    //   217: ldc_w 293
    //   220: sipush 129
    //   223: iconst_5
    //   224: invokestatic 142	xxxxxx/uxxxxx:bb00620062bb0062b0062b0062	(Ljava/lang/String;CC)Ljava/lang/String;
    //   227: iconst_3
    //   228: anewarray 25	java/lang/Class
    //   231: dup
    //   232: iconst_0
    //   233: ldc 79
    //   235: aastore
    //   236: dup
    //   237: iconst_1
    //   238: getstatic 85	java/lang/Character:TYPE	Ljava/lang/Class;
    //   241: aastore
    //   242: dup
    //   243: iconst_2
    //   244: getstatic 85	java/lang/Character:TYPE	Ljava/lang/Class;
    //   247: aastore
    //   248: invokevirtual 89	java/lang/Class:getMethod	(Ljava/lang/String;[Ljava/lang/Class;)Ljava/lang/reflect/Method;
    //   251: astore_3
    //   252: aload_3
    //   253: aconst_null
    //   254: iconst_3
    //   255: anewarray 91	java/lang/Object
    //   258: dup
    //   259: iconst_0
    //   260: ldc_w 295
    //   263: aastore
    //   264: dup
    //   265: iconst_1
    //   266: sipush 163
    //   269: invokestatic 97	java/lang/Character:valueOf	(C)Ljava/lang/Character;
    //   272: aastore
    //   273: dup
    //   274: iconst_2
    //   275: iconst_1
    //   276: invokestatic 97	java/lang/Character:valueOf	(C)Ljava/lang/Character;
    //   279: aastore
    //   280: invokevirtual 103	java/lang/reflect/Method:invoke	(Ljava/lang/Object;[Ljava/lang/Object;)Ljava/lang/Object;
    //   283: astore_3
    //   284: aload_2
    //   285: aload_3
    //   286: checkcast 79	java/lang/String
    //   289: invokevirtual 160	java/lang/StringBuilder:append	(Ljava/lang/String;)Ljava/lang/StringBuilder;
    //   292: aload_0
    //   293: getfield 136	uuuuuu/ooooll:b0071qqq0071qq00710071	Ljava/lang/String;
    //   296: invokevirtual 247	java/lang/String:length	()I
    //   299: invokevirtual 250	java/lang/StringBuilder:append	(I)Ljava/lang/StringBuilder;
    //   302: astore_2
    //   303: getstatic 33	uuuuuu/ooooll:bq0071qq0071qq00710071	I
    //   306: invokestatic 43	uuuuuu/ooooll:b0070p0070ppp0070p00700070	()I
    //   309: iadd
    //   310: getstatic 33	uuuuuu/ooooll:bq0071qq0071qq00710071	I
    //   313: imul
    //   314: getstatic 37	uuuuuu/ooooll:b0071q0071q0071qq00710071	I
    //   317: irem
    //   318: getstatic 39	uuuuuu/ooooll:b00710071qq0071qq00710071	I
    //   321: if_icmpeq +13 -> 334
    //   324: bipush 36
    //   326: putstatic 33	uuuuuu/ooooll:bq0071qq0071qq00710071	I
    //   329: bipush 70
    //   331: putstatic 39	uuuuuu/ooooll:b00710071qq0071qq00710071	I
    //   334: ldc 69
    //   336: ldc_w 297
    //   339: bipush 68
    //   341: bipush 14
    //   343: iconst_1
    //   344: invokestatic 77	xxxxxx/uxxxxx:bbbb0062b0062b0062b0062	(Ljava/lang/String;CCC)Ljava/lang/String;
    //   347: iconst_3
    //   348: anewarray 25	java/lang/Class
    //   351: dup
    //   352: iconst_0
    //   353: ldc 79
    //   355: aastore
    //   356: dup
    //   357: iconst_1
    //   358: getstatic 85	java/lang/Character:TYPE	Ljava/lang/Class;
    //   361: aastore
    //   362: dup
    //   363: iconst_2
    //   364: getstatic 85	java/lang/Character:TYPE	Ljava/lang/Class;
    //   367: aastore
    //   368: invokevirtual 89	java/lang/Class:getMethod	(Ljava/lang/String;[Ljava/lang/Class;)Ljava/lang/reflect/Method;
    //   371: astore_3
    //   372: aload_3
    //   373: aconst_null
    //   374: iconst_3
    //   375: anewarray 91	java/lang/Object
    //   378: dup
    //   379: iconst_0
    //   380: ldc_w 299
    //   383: aastore
    //   384: dup
    //   385: iconst_1
    //   386: bipush 123
    //   388: invokestatic 97	java/lang/Character:valueOf	(C)Ljava/lang/Character;
    //   391: aastore
    //   392: dup
    //   393: iconst_2
    //   394: iconst_4
    //   395: invokestatic 97	java/lang/Character:valueOf	(C)Ljava/lang/Character;
    //   398: aastore
    //   399: invokevirtual 103	java/lang/reflect/Method:invoke	(Ljava/lang/Object;[Ljava/lang/Object;)Ljava/lang/Object;
    //   402: astore_3
    //   403: aload_1
    //   404: aload_2
    //   405: aload_3
    //   406: checkcast 79	java/lang/String
    //   409: invokevirtual 160	java/lang/StringBuilder:append	(Ljava/lang/String;)Ljava/lang/StringBuilder;
    //   412: aload_0
    //   413: invokevirtual 163	uuuuuu/ooooll:bp0070pp00700070pp00700070	()Ljava/lang/String;
    //   416: invokevirtual 160	java/lang/StringBuilder:append	(Ljava/lang/String;)Ljava/lang/StringBuilder;
    //   419: invokevirtual 166	java/lang/StringBuilder:toString	()Ljava/lang/String;
    //   422: invokestatic 302	uuuuuu/rvvvrv:bq0071qq00710071q0071q0071	(Ljava/lang/String;Ljava/lang/String;)V
    //   425: aconst_null
    //   426: areturn
    //   427: astore_1
    //   428: aload_1
    //   429: invokevirtual 109	java/lang/reflect/InvocationTargetException:getCause	()Ljava/lang/Throwable;
    //   432: athrow
    //   433: aload_0
    //   434: getfield 136	uuuuuu/ooooll:b0071qqq0071qq00710071	Ljava/lang/String;
    //   437: ifnull +23 -> 460
    //   440: aload_0
    //   441: getfield 136	uuuuuu/ooooll:b0071qqq0071qq00710071	Ljava/lang/String;
    //   444: aload_0
    //   445: invokevirtual 163	uuuuuu/ooooll:bp0070pp00700070pp00700070	()Ljava/lang/String;
    //   448: invokevirtual 282	java/lang/String:getBytes	(Ljava/lang/String;)[B
    //   451: astore_1
    //   452: aload_1
    //   453: areturn
    //   454: astore_1
    //   455: aload_1
    //   456: invokevirtual 109	java/lang/reflect/InvocationTargetException:getCause	()Ljava/lang/Throwable;
    //   459: athrow
    //   460: aconst_null
    //   461: areturn
    // Local variable table:
    //   start	length	slot	name	signature
    //   0	462	0	this	ooooll
    //   38	2	1	arrayOfByte1	byte[]
    //   41	118	1	localUnsupportedEncodingException1	UnsupportedEncodingException
    //   162	33	1	localIllegalStateException	IllegalStateException
    //   196	2	1	localInvocationTargetException1	InvocationTargetException
    //   202	1	1	localUnsupportedEncodingException2	UnsupportedEncodingException
    //   206	198	1	str	String
    //   427	2	1	localInvocationTargetException2	InvocationTargetException
    //   451	2	1	arrayOfByte2	byte[]
    //   454	2	1	localInvocationTargetException3	InvocationTargetException
    //   49	356	2	localStringBuilder	StringBuilder
    //   94	312	3	localObject	Object
    // Exception table:
    //   from	to	target	type
    //   19	39	41	java/io/UnsupportedEncodingException
    //   95	136	196	java/lang/reflect/InvocationTargetException
    //   433	452	202	java/io/UnsupportedEncodingException
    //   372	403	427	java/lang/reflect/InvocationTargetException
    //   252	284	454	java/lang/reflect/InvocationTargetException
  }
}
