package uuuuuu;

import com.db.pwcc.dbmobile.secure.preferences.SharedPreferencesHelper;

public class opoooo
{
  public static int b00780078x0078x0078007800780078 = 2;
  public static int b0078xx0078x0078007800780078 = 0;
  public static int bx0078x0078x0078007800780078 = 1;
  public static int bxxx0078x0078007800780078 = 45;
  private SharedPreferencesHelper b007800780078xx0078007800780078;
  private yttttt bx00780078xx0078007800780078;
  
  public opoooo(yttttt paramYttttt, SharedPreferencesHelper paramSharedPreferencesHelper)
  {
    this.bx00780078xx0078007800780078 = paramYttttt;
    this.b007800780078xx0078007800780078 = paramSharedPreferencesHelper;
  }
  
  public static int b0075uu00750075uuuuu()
  {
    return 10;
  }
  
  public static int buuu00750075uuuuu()
  {
    return 2;
  }
  
  /* Error */
  public void bu0075u00750075uuuuu()
  {
    // Byte code:
    //   0: getstatic 35	uuuuuu/opoooo:bxxx0078x0078007800780078	I
    //   3: getstatic 37	uuuuuu/opoooo:bx0078x0078x0078007800780078	I
    //   6: iadd
    //   7: getstatic 35	uuuuuu/opoooo:bxxx0078x0078007800780078	I
    //   10: imul
    //   11: invokestatic 39	uuuuuu/opoooo:buuu00750075uuuuu	()I
    //   14: irem
    //   15: getstatic 41	uuuuuu/opoooo:b0078xx0078x0078007800780078	I
    //   18: if_icmpeq +13 -> 31
    //   21: bipush 64
    //   23: putstatic 35	uuuuuu/opoooo:bxxx0078x0078007800780078	I
    //   26: bipush 14
    //   28: putstatic 41	uuuuuu/opoooo:b0078xx0078x0078007800780078	I
    //   31: aload_0
    //   32: getfield 26	uuuuuu/opoooo:b007800780078xx0078007800780078	Lcom/db/pwcc/dbmobile/secure/preferences/SharedPreferencesHelper;
    //   35: astore_2
    //   36: ldc 43
    //   38: ldc 45
    //   40: sipush 238
    //   43: iconst_1
    //   44: invokestatic 51	xxxxxx/uxxxxx:bb00620062bb0062b0062b0062	(Ljava/lang/String;CC)Ljava/lang/String;
    //   47: iconst_0
    //   48: anewarray 53	java/lang/Class
    //   51: invokevirtual 57	java/lang/Class:getMethod	(Ljava/lang/String;[Ljava/lang/Class;)Ljava/lang/reflect/Method;
    //   54: astore_3
    //   55: aload_3
    //   56: aload_2
    //   57: iconst_0
    //   58: anewarray 4	java/lang/Object
    //   61: invokevirtual 63	java/lang/reflect/Method:invoke	(Ljava/lang/Object;[Ljava/lang/Object;)Ljava/lang/Object;
    //   64: astore_2
    //   65: aload_2
    //   66: checkcast 65	java/lang/Boolean
    //   69: invokevirtual 69	java/lang/Boolean:booleanValue	()Z
    //   72: ifeq +4 -> 76
    //   75: return
    //   76: aload_0
    //   77: getfield 24	uuuuuu/opoooo:bx00780078xx0078007800780078	Luuuuuu/yttttt;
    //   80: invokeinterface 74 1 0
    //   85: istore_1
    //   86: getstatic 35	uuuuuu/opoooo:bxxx0078x0078007800780078	I
    //   89: getstatic 37	uuuuuu/opoooo:bx0078x0078x0078007800780078	I
    //   92: iadd
    //   93: getstatic 35	uuuuuu/opoooo:bxxx0078x0078007800780078	I
    //   96: imul
    //   97: getstatic 76	uuuuuu/opoooo:b00780078x0078x0078007800780078	I
    //   100: irem
    //   101: getstatic 41	uuuuuu/opoooo:b0078xx0078x0078007800780078	I
    //   104: if_icmpeq +14 -> 118
    //   107: bipush 81
    //   109: putstatic 35	uuuuuu/opoooo:bxxx0078x0078007800780078	I
    //   112: invokestatic 78	uuuuuu/opoooo:b0075uu00750075uuuuu	()I
    //   115: putstatic 41	uuuuuu/opoooo:b0078xx0078x0078007800780078	I
    //   118: iload_1
    //   119: ifne +12 -> 131
    //   122: aload_0
    //   123: getfield 24	uuuuuu/opoooo:bx00780078xx0078007800780078	Luuuuuu/yttttt;
    //   126: invokeinterface 81 1 0
    //   131: aload_0
    //   132: getfield 24	uuuuuu/opoooo:bx00780078xx0078007800780078	Luuuuuu/yttttt;
    //   135: invokeinterface 84 1 0
    //   140: aload_0
    //   141: getfield 26	uuuuuu/opoooo:b007800780078xx0078007800780078	Lcom/db/pwcc/dbmobile/secure/preferences/SharedPreferencesHelper;
    //   144: astore_2
    //   145: ldc 43
    //   147: ldc 86
    //   149: bipush 24
    //   151: iconst_4
    //   152: invokestatic 51	xxxxxx/uxxxxx:bb00620062bb0062b0062b0062	(Ljava/lang/String;CC)Ljava/lang/String;
    //   155: iconst_1
    //   156: anewarray 53	java/lang/Class
    //   159: dup
    //   160: iconst_0
    //   161: getstatic 90	java/lang/Boolean:TYPE	Ljava/lang/Class;
    //   164: aastore
    //   165: invokevirtual 57	java/lang/Class:getMethod	(Ljava/lang/String;[Ljava/lang/Class;)Ljava/lang/reflect/Method;
    //   168: astore_3
    //   169: aload_3
    //   170: aload_2
    //   171: iconst_1
    //   172: anewarray 4	java/lang/Object
    //   175: dup
    //   176: iconst_0
    //   177: iconst_1
    //   178: invokestatic 94	java/lang/Boolean:valueOf	(Z)Ljava/lang/Boolean;
    //   181: aastore
    //   182: invokevirtual 63	java/lang/reflect/Method:invoke	(Ljava/lang/Object;[Ljava/lang/Object;)Ljava/lang/Object;
    //   185: astore_2
    //   186: aload_2
    //   187: checkcast 65	java/lang/Boolean
    //   190: invokevirtual 69	java/lang/Boolean:booleanValue	()Z
    //   193: pop
    //   194: return
    //   195: astore_2
    //   196: aload_2
    //   197: invokevirtual 98	java/lang/reflect/InvocationTargetException:getCause	()Ljava/lang/Throwable;
    //   200: athrow
    //   201: astore_2
    //   202: aload_2
    //   203: invokevirtual 98	java/lang/reflect/InvocationTargetException:getCause	()Ljava/lang/Throwable;
    //   206: athrow
    // Local variable table:
    //   start	length	slot	name	signature
    //   0	207	0	this	opoooo
    //   85	34	1	bool	boolean
    //   35	152	2	localObject	Object
    //   195	2	2	localInvocationTargetException1	java.lang.reflect.InvocationTargetException
    //   201	2	2	localInvocationTargetException2	java.lang.reflect.InvocationTargetException
    //   54	116	3	localMethod	java.lang.reflect.Method
    // Exception table:
    //   from	to	target	type
    //   55	65	195	java/lang/reflect/InvocationTargetException
    //   169	186	201	java/lang/reflect/InvocationTargetException
  }
}
