package uuuuuu;

public enum pphpph
{
  /* Error */
  static
  {
    // Byte code:
    //   0: ldc 31
    //   2: ldc 33
    //   4: bipush 63
    //   6: sipush 151
    //   9: iconst_3
    //   10: invokestatic 39	xxxxxx/uxxxxx:bbbb0062b0062b0062b0062	(Ljava/lang/String;CCC)Ljava/lang/String;
    //   13: iconst_4
    //   14: anewarray 41	java/lang/Class
    //   17: dup
    //   18: iconst_0
    //   19: ldc 43
    //   21: aastore
    //   22: dup
    //   23: iconst_1
    //   24: getstatic 49	java/lang/Character:TYPE	Ljava/lang/Class;
    //   27: aastore
    //   28: dup
    //   29: iconst_2
    //   30: getstatic 49	java/lang/Character:TYPE	Ljava/lang/Class;
    //   33: aastore
    //   34: dup
    //   35: iconst_3
    //   36: getstatic 49	java/lang/Character:TYPE	Ljava/lang/Class;
    //   39: aastore
    //   40: invokevirtual 53	java/lang/Class:getMethod	(Ljava/lang/String;[Ljava/lang/Class;)Ljava/lang/reflect/Method;
    //   43: astore_0
    //   44: aload_0
    //   45: aconst_null
    //   46: iconst_4
    //   47: anewarray 55	java/lang/Object
    //   50: dup
    //   51: iconst_0
    //   52: ldc 57
    //   54: aastore
    //   55: dup
    //   56: iconst_1
    //   57: bipush 118
    //   59: invokestatic 61	java/lang/Character:valueOf	(C)Ljava/lang/Character;
    //   62: aastore
    //   63: dup
    //   64: iconst_2
    //   65: sipush 158
    //   68: invokestatic 61	java/lang/Character:valueOf	(C)Ljava/lang/Character;
    //   71: aastore
    //   72: dup
    //   73: iconst_3
    //   74: iconst_2
    //   75: invokestatic 61	java/lang/Character:valueOf	(C)Ljava/lang/Character;
    //   78: aastore
    //   79: invokevirtual 67	java/lang/reflect/Method:invoke	(Ljava/lang/Object;[Ljava/lang/Object;)Ljava/lang/Object;
    //   82: astore_0
    //   83: new 2	uuuuuu/pphpph
    //   86: dup
    //   87: aload_0
    //   88: checkcast 43	java/lang/String
    //   91: iconst_0
    //   92: invokespecial 71	uuuuuu/pphpph:<init>	(Ljava/lang/String;I)V
    //   95: putstatic 73	uuuuuu/pphpph:b0079yy00790079y0079y0079	Luuuuuu/pphpph;
    //   98: ldc 31
    //   100: ldc 75
    //   102: bipush 86
    //   104: bipush 10
    //   106: iconst_1
    //   107: invokestatic 39	xxxxxx/uxxxxx:bbbb0062b0062b0062b0062	(Ljava/lang/String;CCC)Ljava/lang/String;
    //   110: iconst_4
    //   111: anewarray 41	java/lang/Class
    //   114: dup
    //   115: iconst_0
    //   116: ldc 43
    //   118: aastore
    //   119: dup
    //   120: iconst_1
    //   121: getstatic 49	java/lang/Character:TYPE	Ljava/lang/Class;
    //   124: aastore
    //   125: dup
    //   126: iconst_2
    //   127: getstatic 49	java/lang/Character:TYPE	Ljava/lang/Class;
    //   130: aastore
    //   131: dup
    //   132: iconst_3
    //   133: getstatic 49	java/lang/Character:TYPE	Ljava/lang/Class;
    //   136: aastore
    //   137: invokevirtual 53	java/lang/Class:getMethod	(Ljava/lang/String;[Ljava/lang/Class;)Ljava/lang/reflect/Method;
    //   140: astore_0
    //   141: aload_0
    //   142: aconst_null
    //   143: iconst_4
    //   144: anewarray 55	java/lang/Object
    //   147: dup
    //   148: iconst_0
    //   149: ldc 77
    //   151: aastore
    //   152: dup
    //   153: iconst_1
    //   154: sipush 144
    //   157: invokestatic 61	java/lang/Character:valueOf	(C)Ljava/lang/Character;
    //   160: aastore
    //   161: dup
    //   162: iconst_2
    //   163: bipush 119
    //   165: invokestatic 61	java/lang/Character:valueOf	(C)Ljava/lang/Character;
    //   168: aastore
    //   169: dup
    //   170: iconst_3
    //   171: iconst_0
    //   172: invokestatic 61	java/lang/Character:valueOf	(C)Ljava/lang/Character;
    //   175: aastore
    //   176: invokevirtual 67	java/lang/reflect/Method:invoke	(Ljava/lang/Object;[Ljava/lang/Object;)Ljava/lang/Object;
    //   179: astore_0
    //   180: new 2	uuuuuu/pphpph
    //   183: dup
    //   184: aload_0
    //   185: checkcast 43	java/lang/String
    //   188: iconst_1
    //   189: invokespecial 71	uuuuuu/pphpph:<init>	(Ljava/lang/String;I)V
    //   192: putstatic 79	uuuuuu/pphpph:b00790079007900790079y0079y0079	Luuuuuu/pphpph;
    //   195: ldc 31
    //   197: ldc 81
    //   199: sipush 254
    //   202: iconst_0
    //   203: invokestatic 85	xxxxxx/uxxxxx:bb00620062bb0062b0062b0062	(Ljava/lang/String;CC)Ljava/lang/String;
    //   206: iconst_4
    //   207: anewarray 41	java/lang/Class
    //   210: dup
    //   211: iconst_0
    //   212: ldc 43
    //   214: aastore
    //   215: dup
    //   216: iconst_1
    //   217: getstatic 49	java/lang/Character:TYPE	Ljava/lang/Class;
    //   220: aastore
    //   221: dup
    //   222: iconst_2
    //   223: getstatic 49	java/lang/Character:TYPE	Ljava/lang/Class;
    //   226: aastore
    //   227: dup
    //   228: iconst_3
    //   229: getstatic 49	java/lang/Character:TYPE	Ljava/lang/Class;
    //   232: aastore
    //   233: invokevirtual 53	java/lang/Class:getMethod	(Ljava/lang/String;[Ljava/lang/Class;)Ljava/lang/reflect/Method;
    //   236: astore_0
    //   237: aload_0
    //   238: aconst_null
    //   239: iconst_4
    //   240: anewarray 55	java/lang/Object
    //   243: dup
    //   244: iconst_0
    //   245: ldc 87
    //   247: aastore
    //   248: dup
    //   249: iconst_1
    //   250: sipush 232
    //   253: invokestatic 61	java/lang/Character:valueOf	(C)Ljava/lang/Character;
    //   256: aastore
    //   257: dup
    //   258: iconst_2
    //   259: bipush 103
    //   261: invokestatic 61	java/lang/Character:valueOf	(C)Ljava/lang/Character;
    //   264: aastore
    //   265: dup
    //   266: iconst_3
    //   267: iconst_3
    //   268: invokestatic 61	java/lang/Character:valueOf	(C)Ljava/lang/Character;
    //   271: aastore
    //   272: invokevirtual 67	java/lang/reflect/Method:invoke	(Ljava/lang/Object;[Ljava/lang/Object;)Ljava/lang/Object;
    //   275: astore_0
    //   276: new 2	uuuuuu/pphpph
    //   279: dup
    //   280: aload_0
    //   281: checkcast 43	java/lang/String
    //   284: iconst_2
    //   285: invokespecial 71	uuuuuu/pphpph:<init>	(Ljava/lang/String;I)V
    //   288: putstatic 89	uuuuuu/pphpph:b00790079yyy00790079y0079	Luuuuuu/pphpph;
    //   291: ldc 31
    //   293: ldc 91
    //   295: sipush 192
    //   298: sipush 187
    //   301: iconst_0
    //   302: invokestatic 39	xxxxxx/uxxxxx:bbbb0062b0062b0062b0062	(Ljava/lang/String;CCC)Ljava/lang/String;
    //   305: iconst_3
    //   306: anewarray 41	java/lang/Class
    //   309: dup
    //   310: iconst_0
    //   311: ldc 43
    //   313: aastore
    //   314: dup
    //   315: iconst_1
    //   316: getstatic 49	java/lang/Character:TYPE	Ljava/lang/Class;
    //   319: aastore
    //   320: dup
    //   321: iconst_2
    //   322: getstatic 49	java/lang/Character:TYPE	Ljava/lang/Class;
    //   325: aastore
    //   326: invokevirtual 53	java/lang/Class:getMethod	(Ljava/lang/String;[Ljava/lang/Class;)Ljava/lang/reflect/Method;
    //   329: astore_0
    //   330: aload_0
    //   331: aconst_null
    //   332: iconst_3
    //   333: anewarray 55	java/lang/Object
    //   336: dup
    //   337: iconst_0
    //   338: ldc 93
    //   340: aastore
    //   341: dup
    //   342: iconst_1
    //   343: sipush 253
    //   346: invokestatic 61	java/lang/Character:valueOf	(C)Ljava/lang/Character;
    //   349: aastore
    //   350: dup
    //   351: iconst_2
    //   352: iconst_5
    //   353: invokestatic 61	java/lang/Character:valueOf	(C)Ljava/lang/Character;
    //   356: aastore
    //   357: invokevirtual 67	java/lang/reflect/Method:invoke	(Ljava/lang/Object;[Ljava/lang/Object;)Ljava/lang/Object;
    //   360: astore_0
    //   361: new 2	uuuuuu/pphpph
    //   364: dup
    //   365: aload_0
    //   366: checkcast 43	java/lang/String
    //   369: iconst_3
    //   370: invokespecial 71	uuuuuu/pphpph:<init>	(Ljava/lang/String;I)V
    //   373: putstatic 95	uuuuuu/pphpph:byy0079y0079y0079y0079	Luuuuuu/pphpph;
    //   376: invokestatic 99	uuuuuu/pphpph:b007700770077w00770077ww0077w	()I
    //   379: invokestatic 102	uuuuuu/pphpph:bwww007700770077ww0077w	()I
    //   382: iadd
    //   383: invokestatic 99	uuuuuu/pphpph:b007700770077w00770077ww0077w	()I
    //   386: imul
    //   387: invokestatic 105	uuuuuu/pphpph:b0077ww007700770077ww0077w	()I
    //   390: irem
    //   391: invokestatic 108	uuuuuu/pphpph:bw0077w007700770077ww0077w	()I
    //   394: if_icmpeq +3 -> 397
    //   397: ldc 31
    //   399: ldc 110
    //   401: bipush 103
    //   403: iconst_1
    //   404: invokestatic 85	xxxxxx/uxxxxx:bb00620062bb0062b0062b0062	(Ljava/lang/String;CC)Ljava/lang/String;
    //   407: iconst_4
    //   408: anewarray 41	java/lang/Class
    //   411: dup
    //   412: iconst_0
    //   413: ldc 43
    //   415: aastore
    //   416: dup
    //   417: iconst_1
    //   418: getstatic 49	java/lang/Character:TYPE	Ljava/lang/Class;
    //   421: aastore
    //   422: dup
    //   423: iconst_2
    //   424: getstatic 49	java/lang/Character:TYPE	Ljava/lang/Class;
    //   427: aastore
    //   428: dup
    //   429: iconst_3
    //   430: getstatic 49	java/lang/Character:TYPE	Ljava/lang/Class;
    //   433: aastore
    //   434: invokevirtual 53	java/lang/Class:getMethod	(Ljava/lang/String;[Ljava/lang/Class;)Ljava/lang/reflect/Method;
    //   437: astore_0
    //   438: aload_0
    //   439: aconst_null
    //   440: iconst_4
    //   441: anewarray 55	java/lang/Object
    //   444: dup
    //   445: iconst_0
    //   446: ldc 112
    //   448: aastore
    //   449: dup
    //   450: iconst_1
    //   451: sipush 241
    //   454: invokestatic 61	java/lang/Character:valueOf	(C)Ljava/lang/Character;
    //   457: aastore
    //   458: dup
    //   459: iconst_2
    //   460: sipush 179
    //   463: invokestatic 61	java/lang/Character:valueOf	(C)Ljava/lang/Character;
    //   466: aastore
    //   467: dup
    //   468: iconst_3
    //   469: iconst_0
    //   470: invokestatic 61	java/lang/Character:valueOf	(C)Ljava/lang/Character;
    //   473: aastore
    //   474: invokevirtual 67	java/lang/reflect/Method:invoke	(Ljava/lang/Object;[Ljava/lang/Object;)Ljava/lang/Object;
    //   477: astore_0
    //   478: new 2	uuuuuu/pphpph
    //   481: dup
    //   482: aload_0
    //   483: checkcast 43	java/lang/String
    //   486: iconst_4
    //   487: invokespecial 71	uuuuuu/pphpph:<init>	(Ljava/lang/String;I)V
    //   490: putstatic 114	uuuuuu/pphpph:b00790079y00790079y0079y0079	Luuuuuu/pphpph;
    //   493: ldc 31
    //   495: ldc 116
    //   497: sipush 147
    //   500: iconst_0
    //   501: invokestatic 85	xxxxxx/uxxxxx:bb00620062bb0062b0062b0062	(Ljava/lang/String;CC)Ljava/lang/String;
    //   504: iconst_3
    //   505: anewarray 41	java/lang/Class
    //   508: dup
    //   509: iconst_0
    //   510: ldc 43
    //   512: aastore
    //   513: dup
    //   514: iconst_1
    //   515: getstatic 49	java/lang/Character:TYPE	Ljava/lang/Class;
    //   518: aastore
    //   519: dup
    //   520: iconst_2
    //   521: getstatic 49	java/lang/Character:TYPE	Ljava/lang/Class;
    //   524: aastore
    //   525: invokevirtual 53	java/lang/Class:getMethod	(Ljava/lang/String;[Ljava/lang/Class;)Ljava/lang/reflect/Method;
    //   528: astore_0
    //   529: aload_0
    //   530: aconst_null
    //   531: iconst_3
    //   532: anewarray 55	java/lang/Object
    //   535: dup
    //   536: iconst_0
    //   537: ldc 118
    //   539: aastore
    //   540: dup
    //   541: iconst_1
    //   542: sipush 172
    //   545: invokestatic 61	java/lang/Character:valueOf	(C)Ljava/lang/Character;
    //   548: aastore
    //   549: dup
    //   550: iconst_2
    //   551: iconst_0
    //   552: invokestatic 61	java/lang/Character:valueOf	(C)Ljava/lang/Character;
    //   555: aastore
    //   556: invokevirtual 67	java/lang/reflect/Method:invoke	(Ljava/lang/Object;[Ljava/lang/Object;)Ljava/lang/Object;
    //   559: astore_0
    //   560: new 2	uuuuuu/pphpph
    //   563: dup
    //   564: aload_0
    //   565: checkcast 43	java/lang/String
    //   568: iconst_5
    //   569: invokespecial 71	uuuuuu/pphpph:<init>	(Ljava/lang/String;I)V
    //   572: putstatic 120	uuuuuu/pphpph:b007900790079y0079y0079y0079	Luuuuuu/pphpph;
    //   575: ldc 31
    //   577: ldc 91
    //   579: bipush 87
    //   581: sipush 165
    //   584: iconst_0
    //   585: invokestatic 39	xxxxxx/uxxxxx:bbbb0062b0062b0062b0062	(Ljava/lang/String;CCC)Ljava/lang/String;
    //   588: iconst_3
    //   589: anewarray 41	java/lang/Class
    //   592: dup
    //   593: iconst_0
    //   594: ldc 43
    //   596: aastore
    //   597: dup
    //   598: iconst_1
    //   599: getstatic 49	java/lang/Character:TYPE	Ljava/lang/Class;
    //   602: aastore
    //   603: dup
    //   604: iconst_2
    //   605: getstatic 49	java/lang/Character:TYPE	Ljava/lang/Class;
    //   608: aastore
    //   609: invokevirtual 53	java/lang/Class:getMethod	(Ljava/lang/String;[Ljava/lang/Class;)Ljava/lang/reflect/Method;
    //   612: astore_0
    //   613: aload_0
    //   614: aconst_null
    //   615: iconst_3
    //   616: anewarray 55	java/lang/Object
    //   619: dup
    //   620: iconst_0
    //   621: ldc 122
    //   623: aastore
    //   624: dup
    //   625: iconst_1
    //   626: bipush 47
    //   628: invokestatic 61	java/lang/Character:valueOf	(C)Ljava/lang/Character;
    //   631: aastore
    //   632: dup
    //   633: iconst_2
    //   634: iconst_5
    //   635: invokestatic 61	java/lang/Character:valueOf	(C)Ljava/lang/Character;
    //   638: aastore
    //   639: invokevirtual 67	java/lang/reflect/Method:invoke	(Ljava/lang/Object;[Ljava/lang/Object;)Ljava/lang/Object;
    //   642: astore_0
    //   643: new 2	uuuuuu/pphpph
    //   646: dup
    //   647: aload_0
    //   648: checkcast 43	java/lang/String
    //   651: bipush 6
    //   653: invokespecial 71	uuuuuu/pphpph:<init>	(Ljava/lang/String;I)V
    //   656: putstatic 124	uuuuuu/pphpph:b0079yyyy00790079y0079	Luuuuuu/pphpph;
    //   659: ldc 31
    //   661: ldc 126
    //   663: bipush 11
    //   665: iconst_2
    //   666: invokestatic 85	xxxxxx/uxxxxx:bb00620062bb0062b0062b0062	(Ljava/lang/String;CC)Ljava/lang/String;
    //   669: iconst_3
    //   670: anewarray 41	java/lang/Class
    //   673: dup
    //   674: iconst_0
    //   675: ldc 43
    //   677: aastore
    //   678: dup
    //   679: iconst_1
    //   680: getstatic 49	java/lang/Character:TYPE	Ljava/lang/Class;
    //   683: aastore
    //   684: dup
    //   685: iconst_2
    //   686: getstatic 49	java/lang/Character:TYPE	Ljava/lang/Class;
    //   689: aastore
    //   690: invokevirtual 53	java/lang/Class:getMethod	(Ljava/lang/String;[Ljava/lang/Class;)Ljava/lang/reflect/Method;
    //   693: astore_0
    //   694: aload_0
    //   695: aconst_null
    //   696: iconst_3
    //   697: anewarray 55	java/lang/Object
    //   700: dup
    //   701: iconst_0
    //   702: ldc -128
    //   704: aastore
    //   705: dup
    //   706: iconst_1
    //   707: bipush 17
    //   709: invokestatic 61	java/lang/Character:valueOf	(C)Ljava/lang/Character;
    //   712: aastore
    //   713: dup
    //   714: iconst_2
    //   715: iconst_3
    //   716: invokestatic 61	java/lang/Character:valueOf	(C)Ljava/lang/Character;
    //   719: aastore
    //   720: invokevirtual 67	java/lang/reflect/Method:invoke	(Ljava/lang/Object;[Ljava/lang/Object;)Ljava/lang/Object;
    //   723: astore_0
    //   724: new 2	uuuuuu/pphpph
    //   727: dup
    //   728: aload_0
    //   729: checkcast 43	java/lang/String
    //   732: bipush 7
    //   734: invokespecial 71	uuuuuu/pphpph:<init>	(Ljava/lang/String;I)V
    //   737: putstatic 130	uuuuuu/pphpph:by0079y00790079y0079y0079	Luuuuuu/pphpph;
    //   740: ldc 31
    //   742: ldc -124
    //   744: sipush 204
    //   747: iconst_4
    //   748: invokestatic 85	xxxxxx/uxxxxx:bb00620062bb0062b0062b0062	(Ljava/lang/String;CC)Ljava/lang/String;
    //   751: iconst_3
    //   752: anewarray 41	java/lang/Class
    //   755: dup
    //   756: iconst_0
    //   757: ldc 43
    //   759: aastore
    //   760: dup
    //   761: iconst_1
    //   762: getstatic 49	java/lang/Character:TYPE	Ljava/lang/Class;
    //   765: aastore
    //   766: dup
    //   767: iconst_2
    //   768: getstatic 49	java/lang/Character:TYPE	Ljava/lang/Class;
    //   771: aastore
    //   772: invokevirtual 53	java/lang/Class:getMethod	(Ljava/lang/String;[Ljava/lang/Class;)Ljava/lang/reflect/Method;
    //   775: astore_0
    //   776: aload_0
    //   777: aconst_null
    //   778: iconst_3
    //   779: anewarray 55	java/lang/Object
    //   782: dup
    //   783: iconst_0
    //   784: ldc -122
    //   786: aastore
    //   787: dup
    //   788: iconst_1
    //   789: sipush 210
    //   792: invokestatic 61	java/lang/Character:valueOf	(C)Ljava/lang/Character;
    //   795: aastore
    //   796: dup
    //   797: iconst_2
    //   798: iconst_4
    //   799: invokestatic 61	java/lang/Character:valueOf	(C)Ljava/lang/Character;
    //   802: aastore
    //   803: invokevirtual 67	java/lang/reflect/Method:invoke	(Ljava/lang/Object;[Ljava/lang/Object;)Ljava/lang/Object;
    //   806: astore_0
    //   807: new 2	uuuuuu/pphpph
    //   810: dup
    //   811: aload_0
    //   812: checkcast 43	java/lang/String
    //   815: bipush 8
    //   817: invokespecial 71	uuuuuu/pphpph:<init>	(Ljava/lang/String;I)V
    //   820: putstatic 136	uuuuuu/pphpph:by00790079y0079y0079y0079	Luuuuuu/pphpph;
    //   823: invokestatic 99	uuuuuu/pphpph:b007700770077w00770077ww0077w	()I
    //   826: invokestatic 102	uuuuuu/pphpph:bwww007700770077ww0077w	()I
    //   829: iadd
    //   830: invokestatic 99	uuuuuu/pphpph:b007700770077w00770077ww0077w	()I
    //   833: imul
    //   834: invokestatic 105	uuuuuu/pphpph:b0077ww007700770077ww0077w	()I
    //   837: irem
    //   838: invokestatic 108	uuuuuu/pphpph:bw0077w007700770077ww0077w	()I
    //   841: if_icmpeq +3 -> 844
    //   844: ldc 31
    //   846: ldc -118
    //   848: sipush 236
    //   851: iconst_3
    //   852: invokestatic 85	xxxxxx/uxxxxx:bb00620062bb0062b0062b0062	(Ljava/lang/String;CC)Ljava/lang/String;
    //   855: iconst_3
    //   856: anewarray 41	java/lang/Class
    //   859: dup
    //   860: iconst_0
    //   861: ldc 43
    //   863: aastore
    //   864: dup
    //   865: iconst_1
    //   866: getstatic 49	java/lang/Character:TYPE	Ljava/lang/Class;
    //   869: aastore
    //   870: dup
    //   871: iconst_2
    //   872: getstatic 49	java/lang/Character:TYPE	Ljava/lang/Class;
    //   875: aastore
    //   876: invokevirtual 53	java/lang/Class:getMethod	(Ljava/lang/String;[Ljava/lang/Class;)Ljava/lang/reflect/Method;
    //   879: astore_0
    //   880: aload_0
    //   881: aconst_null
    //   882: iconst_3
    //   883: anewarray 55	java/lang/Object
    //   886: dup
    //   887: iconst_0
    //   888: ldc -116
    //   890: aastore
    //   891: dup
    //   892: iconst_1
    //   893: bipush 10
    //   895: invokestatic 61	java/lang/Character:valueOf	(C)Ljava/lang/Character;
    //   898: aastore
    //   899: dup
    //   900: iconst_2
    //   901: iconst_1
    //   902: invokestatic 61	java/lang/Character:valueOf	(C)Ljava/lang/Character;
    //   905: aastore
    //   906: invokevirtual 67	java/lang/reflect/Method:invoke	(Ljava/lang/Object;[Ljava/lang/Object;)Ljava/lang/Object;
    //   909: astore_0
    //   910: new 2	uuuuuu/pphpph
    //   913: dup
    //   914: aload_0
    //   915: checkcast 43	java/lang/String
    //   918: bipush 9
    //   920: invokespecial 71	uuuuuu/pphpph:<init>	(Ljava/lang/String;I)V
    //   923: putstatic 142	uuuuuu/pphpph:byyyyy00790079y0079	Luuuuuu/pphpph;
    //   926: ldc 31
    //   928: ldc -112
    //   930: sipush 140
    //   933: bipush 60
    //   935: iconst_0
    //   936: invokestatic 39	xxxxxx/uxxxxx:bbbb0062b0062b0062b0062	(Ljava/lang/String;CCC)Ljava/lang/String;
    //   939: iconst_3
    //   940: anewarray 41	java/lang/Class
    //   943: dup
    //   944: iconst_0
    //   945: ldc 43
    //   947: aastore
    //   948: dup
    //   949: iconst_1
    //   950: getstatic 49	java/lang/Character:TYPE	Ljava/lang/Class;
    //   953: aastore
    //   954: dup
    //   955: iconst_2
    //   956: getstatic 49	java/lang/Character:TYPE	Ljava/lang/Class;
    //   959: aastore
    //   960: invokevirtual 53	java/lang/Class:getMethod	(Ljava/lang/String;[Ljava/lang/Class;)Ljava/lang/reflect/Method;
    //   963: astore_0
    //   964: aload_0
    //   965: aconst_null
    //   966: iconst_3
    //   967: anewarray 55	java/lang/Object
    //   970: dup
    //   971: iconst_0
    //   972: ldc -110
    //   974: aastore
    //   975: dup
    //   976: iconst_1
    //   977: bipush 11
    //   979: invokestatic 61	java/lang/Character:valueOf	(C)Ljava/lang/Character;
    //   982: aastore
    //   983: dup
    //   984: iconst_2
    //   985: iconst_3
    //   986: invokestatic 61	java/lang/Character:valueOf	(C)Ljava/lang/Character;
    //   989: aastore
    //   990: invokevirtual 67	java/lang/reflect/Method:invoke	(Ljava/lang/Object;[Ljava/lang/Object;)Ljava/lang/Object;
    //   993: astore_0
    //   994: new 2	uuuuuu/pphpph
    //   997: dup
    //   998: aload_0
    //   999: checkcast 43	java/lang/String
    //   1002: bipush 10
    //   1004: invokespecial 71	uuuuuu/pphpph:<init>	(Ljava/lang/String;I)V
    //   1007: putstatic 148	uuuuuu/pphpph:b0079y007900790079y0079y0079	Luuuuuu/pphpph;
    //   1010: ldc 31
    //   1012: ldc -106
    //   1014: sipush 197
    //   1017: iconst_0
    //   1018: invokestatic 85	xxxxxx/uxxxxx:bb00620062bb0062b0062b0062	(Ljava/lang/String;CC)Ljava/lang/String;
    //   1021: iconst_3
    //   1022: anewarray 41	java/lang/Class
    //   1025: dup
    //   1026: iconst_0
    //   1027: ldc 43
    //   1029: aastore
    //   1030: dup
    //   1031: iconst_1
    //   1032: getstatic 49	java/lang/Character:TYPE	Ljava/lang/Class;
    //   1035: aastore
    //   1036: dup
    //   1037: iconst_2
    //   1038: getstatic 49	java/lang/Character:TYPE	Ljava/lang/Class;
    //   1041: aastore
    //   1042: invokevirtual 53	java/lang/Class:getMethod	(Ljava/lang/String;[Ljava/lang/Class;)Ljava/lang/reflect/Method;
    //   1045: astore_0
    //   1046: aload_0
    //   1047: aconst_null
    //   1048: iconst_3
    //   1049: anewarray 55	java/lang/Object
    //   1052: dup
    //   1053: iconst_0
    //   1054: ldc -104
    //   1056: aastore
    //   1057: dup
    //   1058: iconst_1
    //   1059: sipush 249
    //   1062: invokestatic 61	java/lang/Character:valueOf	(C)Ljava/lang/Character;
    //   1065: aastore
    //   1066: dup
    //   1067: iconst_2
    //   1068: iconst_1
    //   1069: invokestatic 61	java/lang/Character:valueOf	(C)Ljava/lang/Character;
    //   1072: aastore
    //   1073: invokevirtual 67	java/lang/reflect/Method:invoke	(Ljava/lang/Object;[Ljava/lang/Object;)Ljava/lang/Object;
    //   1076: astore_0
    //   1077: new 2	uuuuuu/pphpph
    //   1080: dup
    //   1081: aload_0
    //   1082: checkcast 43	java/lang/String
    //   1085: bipush 11
    //   1087: invokespecial 71	uuuuuu/pphpph:<init>	(Ljava/lang/String;I)V
    //   1090: putstatic 154	uuuuuu/pphpph:byy007900790079y0079y0079	Luuuuuu/pphpph;
    //   1093: ldc 31
    //   1095: ldc -100
    //   1097: bipush 34
    //   1099: iconst_1
    //   1100: invokestatic 85	xxxxxx/uxxxxx:bb00620062bb0062b0062b0062	(Ljava/lang/String;CC)Ljava/lang/String;
    //   1103: iconst_3
    //   1104: anewarray 41	java/lang/Class
    //   1107: dup
    //   1108: iconst_0
    //   1109: ldc 43
    //   1111: aastore
    //   1112: dup
    //   1113: iconst_1
    //   1114: getstatic 49	java/lang/Character:TYPE	Ljava/lang/Class;
    //   1117: aastore
    //   1118: dup
    //   1119: iconst_2
    //   1120: getstatic 49	java/lang/Character:TYPE	Ljava/lang/Class;
    //   1123: aastore
    //   1124: invokevirtual 53	java/lang/Class:getMethod	(Ljava/lang/String;[Ljava/lang/Class;)Ljava/lang/reflect/Method;
    //   1127: astore_0
    //   1128: aload_0
    //   1129: aconst_null
    //   1130: iconst_3
    //   1131: anewarray 55	java/lang/Object
    //   1134: dup
    //   1135: iconst_0
    //   1136: ldc -98
    //   1138: aastore
    //   1139: dup
    //   1140: iconst_1
    //   1141: sipush 208
    //   1144: invokestatic 61	java/lang/Character:valueOf	(C)Ljava/lang/Character;
    //   1147: aastore
    //   1148: dup
    //   1149: iconst_2
    //   1150: iconst_1
    //   1151: invokestatic 61	java/lang/Character:valueOf	(C)Ljava/lang/Character;
    //   1154: aastore
    //   1155: invokevirtual 67	java/lang/reflect/Method:invoke	(Ljava/lang/Object;[Ljava/lang/Object;)Ljava/lang/Object;
    //   1158: astore_0
    //   1159: new 2	uuuuuu/pphpph
    //   1162: dup
    //   1163: aload_0
    //   1164: checkcast 43	java/lang/String
    //   1167: bipush 12
    //   1169: invokespecial 71	uuuuuu/pphpph:<init>	(Ljava/lang/String;I)V
    //   1172: putstatic 160	uuuuuu/pphpph:byyy00790079y0079y0079	Luuuuuu/pphpph;
    //   1175: ldc 31
    //   1177: ldc -94
    //   1179: sipush 243
    //   1182: iconst_2
    //   1183: invokestatic 85	xxxxxx/uxxxxx:bb00620062bb0062b0062b0062	(Ljava/lang/String;CC)Ljava/lang/String;
    //   1186: iconst_3
    //   1187: anewarray 41	java/lang/Class
    //   1190: dup
    //   1191: iconst_0
    //   1192: ldc 43
    //   1194: aastore
    //   1195: dup
    //   1196: iconst_1
    //   1197: getstatic 49	java/lang/Character:TYPE	Ljava/lang/Class;
    //   1200: aastore
    //   1201: dup
    //   1202: iconst_2
    //   1203: getstatic 49	java/lang/Character:TYPE	Ljava/lang/Class;
    //   1206: aastore
    //   1207: invokevirtual 53	java/lang/Class:getMethod	(Ljava/lang/String;[Ljava/lang/Class;)Ljava/lang/reflect/Method;
    //   1210: astore_0
    //   1211: aload_0
    //   1212: aconst_null
    //   1213: iconst_3
    //   1214: anewarray 55	java/lang/Object
    //   1217: dup
    //   1218: iconst_0
    //   1219: ldc -92
    //   1221: aastore
    //   1222: dup
    //   1223: iconst_1
    //   1224: bipush 17
    //   1226: invokestatic 61	java/lang/Character:valueOf	(C)Ljava/lang/Character;
    //   1229: aastore
    //   1230: dup
    //   1231: iconst_2
    //   1232: iconst_4
    //   1233: invokestatic 61	java/lang/Character:valueOf	(C)Ljava/lang/Character;
    //   1236: aastore
    //   1237: invokevirtual 67	java/lang/reflect/Method:invoke	(Ljava/lang/Object;[Ljava/lang/Object;)Ljava/lang/Object;
    //   1240: astore_0
    //   1241: new 2	uuuuuu/pphpph
    //   1244: dup
    //   1245: aload_0
    //   1246: checkcast 43	java/lang/String
    //   1249: bipush 13
    //   1251: invokespecial 71	uuuuuu/pphpph:<init>	(Ljava/lang/String;I)V
    //   1254: putstatic 166	uuuuuu/pphpph:by0079yyy00790079y0079	Luuuuuu/pphpph;
    //   1257: ldc 31
    //   1259: ldc -88
    //   1261: sipush 160
    //   1264: bipush 98
    //   1266: iconst_0
    //   1267: invokestatic 39	xxxxxx/uxxxxx:bbbb0062b0062b0062b0062	(Ljava/lang/String;CCC)Ljava/lang/String;
    //   1270: iconst_4
    //   1271: anewarray 41	java/lang/Class
    //   1274: dup
    //   1275: iconst_0
    //   1276: ldc 43
    //   1278: aastore
    //   1279: dup
    //   1280: iconst_1
    //   1281: getstatic 49	java/lang/Character:TYPE	Ljava/lang/Class;
    //   1284: aastore
    //   1285: dup
    //   1286: iconst_2
    //   1287: getstatic 49	java/lang/Character:TYPE	Ljava/lang/Class;
    //   1290: aastore
    //   1291: dup
    //   1292: iconst_3
    //   1293: getstatic 49	java/lang/Character:TYPE	Ljava/lang/Class;
    //   1296: aastore
    //   1297: invokevirtual 53	java/lang/Class:getMethod	(Ljava/lang/String;[Ljava/lang/Class;)Ljava/lang/reflect/Method;
    //   1300: astore_0
    //   1301: aload_0
    //   1302: aconst_null
    //   1303: iconst_4
    //   1304: anewarray 55	java/lang/Object
    //   1307: dup
    //   1308: iconst_0
    //   1309: ldc -86
    //   1311: aastore
    //   1312: dup
    //   1313: iconst_1
    //   1314: sipush 165
    //   1317: invokestatic 61	java/lang/Character:valueOf	(C)Ljava/lang/Character;
    //   1320: aastore
    //   1321: dup
    //   1322: iconst_2
    //   1323: bipush 35
    //   1325: invokestatic 61	java/lang/Character:valueOf	(C)Ljava/lang/Character;
    //   1328: aastore
    //   1329: dup
    //   1330: iconst_3
    //   1331: iconst_1
    //   1332: invokestatic 61	java/lang/Character:valueOf	(C)Ljava/lang/Character;
    //   1335: aastore
    //   1336: invokevirtual 67	java/lang/reflect/Method:invoke	(Ljava/lang/Object;[Ljava/lang/Object;)Ljava/lang/Object;
    //   1339: astore_0
    //   1340: new 2	uuuuuu/pphpph
    //   1343: dup
    //   1344: aload_0
    //   1345: checkcast 43	java/lang/String
    //   1348: bipush 14
    //   1350: invokespecial 71	uuuuuu/pphpph:<init>	(Ljava/lang/String;I)V
    //   1353: putstatic 172	uuuuuu/pphpph:by0079007900790079y0079y0079	Luuuuuu/pphpph;
    //   1356: ldc 31
    //   1358: ldc -82
    //   1360: bipush 38
    //   1362: iconst_3
    //   1363: invokestatic 85	xxxxxx/uxxxxx:bb00620062bb0062b0062b0062	(Ljava/lang/String;CC)Ljava/lang/String;
    //   1366: iconst_3
    //   1367: anewarray 41	java/lang/Class
    //   1370: dup
    //   1371: iconst_0
    //   1372: ldc 43
    //   1374: aastore
    //   1375: dup
    //   1376: iconst_1
    //   1377: getstatic 49	java/lang/Character:TYPE	Ljava/lang/Class;
    //   1380: aastore
    //   1381: dup
    //   1382: iconst_2
    //   1383: getstatic 49	java/lang/Character:TYPE	Ljava/lang/Class;
    //   1386: aastore
    //   1387: invokevirtual 53	java/lang/Class:getMethod	(Ljava/lang/String;[Ljava/lang/Class;)Ljava/lang/reflect/Method;
    //   1390: astore_0
    //   1391: aload_0
    //   1392: aconst_null
    //   1393: iconst_3
    //   1394: anewarray 55	java/lang/Object
    //   1397: dup
    //   1398: iconst_0
    //   1399: ldc -80
    //   1401: aastore
    //   1402: dup
    //   1403: iconst_1
    //   1404: bipush 47
    //   1406: invokestatic 61	java/lang/Character:valueOf	(C)Ljava/lang/Character;
    //   1409: aastore
    //   1410: dup
    //   1411: iconst_2
    //   1412: iconst_4
    //   1413: invokestatic 61	java/lang/Character:valueOf	(C)Ljava/lang/Character;
    //   1416: aastore
    //   1417: invokevirtual 67	java/lang/reflect/Method:invoke	(Ljava/lang/Object;[Ljava/lang/Object;)Ljava/lang/Object;
    //   1420: astore_0
    //   1421: new 2	uuuuuu/pphpph
    //   1424: dup
    //   1425: aload_0
    //   1426: checkcast 43	java/lang/String
    //   1429: bipush 15
    //   1431: invokespecial 71	uuuuuu/pphpph:<init>	(Ljava/lang/String;I)V
    //   1434: putstatic 178	uuuuuu/pphpph:b0079y0079y0079y0079y0079	Luuuuuu/pphpph;
    //   1437: ldc 31
    //   1439: ldc -76
    //   1441: bipush 94
    //   1443: bipush 113
    //   1445: iconst_3
    //   1446: invokestatic 39	xxxxxx/uxxxxx:bbbb0062b0062b0062b0062	(Ljava/lang/String;CCC)Ljava/lang/String;
    //   1449: iconst_4
    //   1450: anewarray 41	java/lang/Class
    //   1453: dup
    //   1454: iconst_0
    //   1455: ldc 43
    //   1457: aastore
    //   1458: dup
    //   1459: iconst_1
    //   1460: getstatic 49	java/lang/Character:TYPE	Ljava/lang/Class;
    //   1463: aastore
    //   1464: dup
    //   1465: iconst_2
    //   1466: getstatic 49	java/lang/Character:TYPE	Ljava/lang/Class;
    //   1469: aastore
    //   1470: dup
    //   1471: iconst_3
    //   1472: getstatic 49	java/lang/Character:TYPE	Ljava/lang/Class;
    //   1475: aastore
    //   1476: invokevirtual 53	java/lang/Class:getMethod	(Ljava/lang/String;[Ljava/lang/Class;)Ljava/lang/reflect/Method;
    //   1479: astore_0
    //   1480: aload_0
    //   1481: aconst_null
    //   1482: iconst_4
    //   1483: anewarray 55	java/lang/Object
    //   1486: dup
    //   1487: iconst_0
    //   1488: ldc -74
    //   1490: aastore
    //   1491: dup
    //   1492: iconst_1
    //   1493: sipush 217
    //   1496: invokestatic 61	java/lang/Character:valueOf	(C)Ljava/lang/Character;
    //   1499: aastore
    //   1500: dup
    //   1501: iconst_2
    //   1502: bipush 71
    //   1504: invokestatic 61	java/lang/Character:valueOf	(C)Ljava/lang/Character;
    //   1507: aastore
    //   1508: dup
    //   1509: iconst_3
    //   1510: iconst_3
    //   1511: invokestatic 61	java/lang/Character:valueOf	(C)Ljava/lang/Character;
    //   1514: aastore
    //   1515: invokevirtual 67	java/lang/reflect/Method:invoke	(Ljava/lang/Object;[Ljava/lang/Object;)Ljava/lang/Object;
    //   1518: astore_0
    //   1519: new 2	uuuuuu/pphpph
    //   1522: dup
    //   1523: aload_0
    //   1524: checkcast 43	java/lang/String
    //   1527: bipush 16
    //   1529: invokespecial 71	uuuuuu/pphpph:<init>	(Ljava/lang/String;I)V
    //   1532: putstatic 184	uuuuuu/pphpph:b00790079yy0079y0079y0079	Luuuuuu/pphpph;
    //   1535: bipush 17
    //   1537: anewarray 2	uuuuuu/pphpph
    //   1540: dup
    //   1541: iconst_0
    //   1542: getstatic 73	uuuuuu/pphpph:b0079yy00790079y0079y0079	Luuuuuu/pphpph;
    //   1545: aastore
    //   1546: dup
    //   1547: iconst_1
    //   1548: getstatic 79	uuuuuu/pphpph:b00790079007900790079y0079y0079	Luuuuuu/pphpph;
    //   1551: aastore
    //   1552: dup
    //   1553: iconst_2
    //   1554: getstatic 89	uuuuuu/pphpph:b00790079yyy00790079y0079	Luuuuuu/pphpph;
    //   1557: aastore
    //   1558: dup
    //   1559: iconst_3
    //   1560: getstatic 95	uuuuuu/pphpph:byy0079y0079y0079y0079	Luuuuuu/pphpph;
    //   1563: aastore
    //   1564: dup
    //   1565: iconst_4
    //   1566: getstatic 114	uuuuuu/pphpph:b00790079y00790079y0079y0079	Luuuuuu/pphpph;
    //   1569: aastore
    //   1570: dup
    //   1571: iconst_5
    //   1572: getstatic 120	uuuuuu/pphpph:b007900790079y0079y0079y0079	Luuuuuu/pphpph;
    //   1575: aastore
    //   1576: dup
    //   1577: bipush 6
    //   1579: getstatic 124	uuuuuu/pphpph:b0079yyyy00790079y0079	Luuuuuu/pphpph;
    //   1582: aastore
    //   1583: dup
    //   1584: bipush 7
    //   1586: getstatic 130	uuuuuu/pphpph:by0079y00790079y0079y0079	Luuuuuu/pphpph;
    //   1589: aastore
    //   1590: dup
    //   1591: bipush 8
    //   1593: getstatic 136	uuuuuu/pphpph:by00790079y0079y0079y0079	Luuuuuu/pphpph;
    //   1596: aastore
    //   1597: dup
    //   1598: bipush 9
    //   1600: getstatic 142	uuuuuu/pphpph:byyyyy00790079y0079	Luuuuuu/pphpph;
    //   1603: aastore
    //   1604: dup
    //   1605: bipush 10
    //   1607: getstatic 148	uuuuuu/pphpph:b0079y007900790079y0079y0079	Luuuuuu/pphpph;
    //   1610: aastore
    //   1611: dup
    //   1612: bipush 11
    //   1614: getstatic 154	uuuuuu/pphpph:byy007900790079y0079y0079	Luuuuuu/pphpph;
    //   1617: aastore
    //   1618: dup
    //   1619: bipush 12
    //   1621: getstatic 160	uuuuuu/pphpph:byyy00790079y0079y0079	Luuuuuu/pphpph;
    //   1624: aastore
    //   1625: dup
    //   1626: bipush 13
    //   1628: getstatic 166	uuuuuu/pphpph:by0079yyy00790079y0079	Luuuuuu/pphpph;
    //   1631: aastore
    //   1632: dup
    //   1633: bipush 14
    //   1635: getstatic 172	uuuuuu/pphpph:by0079007900790079y0079y0079	Luuuuuu/pphpph;
    //   1638: aastore
    //   1639: dup
    //   1640: bipush 15
    //   1642: getstatic 178	uuuuuu/pphpph:b0079y0079y0079y0079y0079	Luuuuuu/pphpph;
    //   1645: aastore
    //   1646: dup
    //   1647: bipush 16
    //   1649: getstatic 184	uuuuuu/pphpph:b00790079yy0079y0079y0079	Luuuuuu/pphpph;
    //   1652: aastore
    //   1653: putstatic 186	uuuuuu/pphpph:by0079yy0079y0079y0079	[Luuuuuu/pphpph;
    //   1656: return
    //   1657: astore_0
    //   1658: aload_0
    //   1659: invokevirtual 190	java/lang/reflect/InvocationTargetException:getCause	()Ljava/lang/Throwable;
    //   1662: athrow
    //   1663: astore_0
    //   1664: aload_0
    //   1665: invokevirtual 190	java/lang/reflect/InvocationTargetException:getCause	()Ljava/lang/Throwable;
    //   1668: athrow
    //   1669: astore_0
    //   1670: aload_0
    //   1671: invokevirtual 190	java/lang/reflect/InvocationTargetException:getCause	()Ljava/lang/Throwable;
    //   1674: athrow
    //   1675: astore_0
    //   1676: aload_0
    //   1677: invokevirtual 190	java/lang/reflect/InvocationTargetException:getCause	()Ljava/lang/Throwable;
    //   1680: athrow
    //   1681: astore_0
    //   1682: aload_0
    //   1683: invokevirtual 190	java/lang/reflect/InvocationTargetException:getCause	()Ljava/lang/Throwable;
    //   1686: athrow
    //   1687: astore_0
    //   1688: aload_0
    //   1689: invokevirtual 190	java/lang/reflect/InvocationTargetException:getCause	()Ljava/lang/Throwable;
    //   1692: athrow
    //   1693: astore_0
    //   1694: aload_0
    //   1695: invokevirtual 190	java/lang/reflect/InvocationTargetException:getCause	()Ljava/lang/Throwable;
    //   1698: athrow
    //   1699: astore_0
    //   1700: aload_0
    //   1701: invokevirtual 190	java/lang/reflect/InvocationTargetException:getCause	()Ljava/lang/Throwable;
    //   1704: athrow
    //   1705: astore_0
    //   1706: aload_0
    //   1707: invokevirtual 190	java/lang/reflect/InvocationTargetException:getCause	()Ljava/lang/Throwable;
    //   1710: athrow
    //   1711: astore_0
    //   1712: aload_0
    //   1713: invokevirtual 190	java/lang/reflect/InvocationTargetException:getCause	()Ljava/lang/Throwable;
    //   1716: athrow
    //   1717: astore_0
    //   1718: aload_0
    //   1719: invokevirtual 190	java/lang/reflect/InvocationTargetException:getCause	()Ljava/lang/Throwable;
    //   1722: athrow
    //   1723: astore_0
    //   1724: aload_0
    //   1725: invokevirtual 190	java/lang/reflect/InvocationTargetException:getCause	()Ljava/lang/Throwable;
    //   1728: athrow
    //   1729: astore_0
    //   1730: aload_0
    //   1731: invokevirtual 190	java/lang/reflect/InvocationTargetException:getCause	()Ljava/lang/Throwable;
    //   1734: athrow
    //   1735: astore_0
    //   1736: aload_0
    //   1737: invokevirtual 190	java/lang/reflect/InvocationTargetException:getCause	()Ljava/lang/Throwable;
    //   1740: athrow
    //   1741: astore_0
    //   1742: aload_0
    //   1743: invokevirtual 190	java/lang/reflect/InvocationTargetException:getCause	()Ljava/lang/Throwable;
    //   1746: athrow
    //   1747: astore_0
    //   1748: aload_0
    //   1749: invokevirtual 190	java/lang/reflect/InvocationTargetException:getCause	()Ljava/lang/Throwable;
    //   1752: athrow
    //   1753: astore_0
    //   1754: aload_0
    //   1755: invokevirtual 190	java/lang/reflect/InvocationTargetException:getCause	()Ljava/lang/Throwable;
    //   1758: athrow
    // Local variable table:
    //   start	length	slot	name	signature
    //   43	1481	0	localObject	Object
    //   1657	2	0	localInvocationTargetException1	java.lang.reflect.InvocationTargetException
    //   1663	2	0	localInvocationTargetException2	java.lang.reflect.InvocationTargetException
    //   1669	2	0	localInvocationTargetException3	java.lang.reflect.InvocationTargetException
    //   1675	2	0	localInvocationTargetException4	java.lang.reflect.InvocationTargetException
    //   1681	2	0	localInvocationTargetException5	java.lang.reflect.InvocationTargetException
    //   1687	2	0	localInvocationTargetException6	java.lang.reflect.InvocationTargetException
    //   1693	2	0	localInvocationTargetException7	java.lang.reflect.InvocationTargetException
    //   1699	2	0	localInvocationTargetException8	java.lang.reflect.InvocationTargetException
    //   1705	2	0	localInvocationTargetException9	java.lang.reflect.InvocationTargetException
    //   1711	2	0	localInvocationTargetException10	java.lang.reflect.InvocationTargetException
    //   1717	2	0	localInvocationTargetException11	java.lang.reflect.InvocationTargetException
    //   1723	2	0	localInvocationTargetException12	java.lang.reflect.InvocationTargetException
    //   1729	2	0	localInvocationTargetException13	java.lang.reflect.InvocationTargetException
    //   1735	2	0	localInvocationTargetException14	java.lang.reflect.InvocationTargetException
    //   1741	2	0	localInvocationTargetException15	java.lang.reflect.InvocationTargetException
    //   1747	2	0	localInvocationTargetException16	java.lang.reflect.InvocationTargetException
    //   1753	2	0	localInvocationTargetException17	java.lang.reflect.InvocationTargetException
    // Exception table:
    //   from	to	target	type
    //   1128	1159	1657	java/lang/reflect/InvocationTargetException
    //   141	180	1663	java/lang/reflect/InvocationTargetException
    //   613	643	1669	java/lang/reflect/InvocationTargetException
    //   694	724	1675	java/lang/reflect/InvocationTargetException
    //   1046	1077	1681	java/lang/reflect/InvocationTargetException
    //   1301	1340	1687	java/lang/reflect/InvocationTargetException
    //   1211	1241	1693	java/lang/reflect/InvocationTargetException
    //   1391	1421	1699	java/lang/reflect/InvocationTargetException
    //   44	83	1705	java/lang/reflect/InvocationTargetException
    //   237	276	1711	java/lang/reflect/InvocationTargetException
    //   1480	1519	1717	java/lang/reflect/InvocationTargetException
    //   776	807	1723	java/lang/reflect/InvocationTargetException
    //   964	994	1729	java/lang/reflect/InvocationTargetException
    //   880	910	1735	java/lang/reflect/InvocationTargetException
    //   529	560	1741	java/lang/reflect/InvocationTargetException
    //   330	361	1747	java/lang/reflect/InvocationTargetException
    //   438	478	1753	java/lang/reflect/InvocationTargetException
  }
  
  private pphpph() {}
  
  public static int b007700770077w00770077ww0077w()
  {
    return 25;
  }
  
  public static pphpph b00770077w007700770077ww0077w(String paramString)
  {
    paramString = Enum.valueOf(pphpph.class, paramString);
    int i = b007700770077w00770077ww0077w();
    int j = bwww007700770077ww0077w();
    if (((b007700770077w00770077ww0077w() + bwww007700770077ww0077w()) * b007700770077w00770077ww0077w() % b0077ww007700770077ww0077w() == bw0077w007700770077ww0077w()) || ((i + j) * b007700770077w00770077ww0077w() % b0077ww007700770077ww0077w() != bw0077w007700770077ww0077w())) {}
    return (pphpph)paramString;
  }
  
  public static int b0077ww007700770077ww0077w()
  {
    return 2;
  }
  
  public static int bw0077w007700770077ww0077w()
  {
    return 0;
  }
  
  public static int bwww007700770077ww0077w()
  {
    return 1;
  }
}
