package uuuuuu;

import com.db.pwcc.dbmobile.model.banking.Account;
import java.util.List;

public class pqppqp
  extends qppppp<qqqqpp.qpppqp>
  implements qqqqpp.ppppqp<qqqqpp.qpppqp>
{
  public static int b00730073ss0073sss0073 = 0;
  public static int b0073sss0073sss0073 = 1;
  public static int bs0073ss0073sss0073 = 2;
  public static int bssss0073sss0073 = 31;
  private String b0073007300730073ssss0073;
  private List<Account> bs007300730073ssss0073;
  
  public pqppqp() {}
  
  public static int b006B006B006Bkkkkkkk()
  {
    return 64;
  }
  
  public static int bk006B006Bkkkkkkk()
  {
    return 1;
  }
  
  public static int bkk006Bkkkkkkk()
  {
    return 2;
  }
  
  /* Error */
  public void b006B006Bkkkkkkkk(List<Account> paramList, String paramString)
  {
    // Byte code:
    //   0: getstatic 36	uuuuuu/pqppqp:bssss0073sss0073	I
    //   3: istore_3
    //   4: iload_3
    //   5: getstatic 38	uuuuuu/pqppqp:b0073sss0073sss0073	I
    //   8: iload_3
    //   9: iadd
    //   10: imul
    //   11: getstatic 40	uuuuuu/pqppqp:bs0073ss0073sss0073	I
    //   14: irem
    //   15: tableswitch	default:+17->32, 0:+245->260
    //   32: ldc 2
    //   34: ldc 42
    //   36: bipush 80
    //   38: iconst_4
    //   39: invokestatic 48	xxxxxx/uxxxxx:bb00620062bb0062b0062b0062	(Ljava/lang/String;CC)Ljava/lang/String;
    //   42: iconst_0
    //   43: anewarray 50	java/lang/Class
    //   46: invokevirtual 54	java/lang/Class:getMethod	(Ljava/lang/String;[Ljava/lang/Class;)Ljava/lang/reflect/Method;
    //   49: astore 5
    //   51: aload 5
    //   53: aconst_null
    //   54: iconst_0
    //   55: anewarray 56	java/lang/Object
    //   58: invokevirtual 62	java/lang/reflect/Method:invoke	(Ljava/lang/Object;[Ljava/lang/Object;)Ljava/lang/Object;
    //   61: astore 5
    //   63: aload 5
    //   65: checkcast 64	java/lang/Integer
    //   68: invokevirtual 67	java/lang/Integer:intValue	()I
    //   71: putstatic 36	uuuuuu/pqppqp:bssss0073sss0073	I
    //   74: bipush 96
    //   76: putstatic 69	uuuuuu/pqppqp:b00730073ss0073sss0073	I
    //   79: getstatic 36	uuuuuu/pqppqp:bssss0073sss0073	I
    //   82: istore_3
    //   83: getstatic 38	uuuuuu/pqppqp:b0073sss0073sss0073	I
    //   86: istore 4
    //   88: getstatic 36	uuuuuu/pqppqp:bssss0073sss0073	I
    //   91: getstatic 38	uuuuuu/pqppqp:b0073sss0073sss0073	I
    //   94: iadd
    //   95: getstatic 36	uuuuuu/pqppqp:bssss0073sss0073	I
    //   98: imul
    //   99: getstatic 40	uuuuuu/pqppqp:bs0073ss0073sss0073	I
    //   102: irem
    //   103: getstatic 69	uuuuuu/pqppqp:b00730073ss0073sss0073	I
    //   106: if_icmpeq +53 -> 159
    //   109: ldc 2
    //   111: ldc 71
    //   113: sipush 136
    //   116: sipush 128
    //   119: iconst_1
    //   120: invokestatic 75	xxxxxx/uxxxxx:bbbb0062b0062b0062b0062	(Ljava/lang/String;CCC)Ljava/lang/String;
    //   123: iconst_0
    //   124: anewarray 50	java/lang/Class
    //   127: invokevirtual 54	java/lang/Class:getMethod	(Ljava/lang/String;[Ljava/lang/Class;)Ljava/lang/reflect/Method;
    //   130: astore 5
    //   132: aload 5
    //   134: aconst_null
    //   135: iconst_0
    //   136: anewarray 56	java/lang/Object
    //   139: invokevirtual 62	java/lang/reflect/Method:invoke	(Ljava/lang/Object;[Ljava/lang/Object;)Ljava/lang/Object;
    //   142: astore 5
    //   144: aload 5
    //   146: checkcast 64	java/lang/Integer
    //   149: invokevirtual 67	java/lang/Integer:intValue	()I
    //   152: putstatic 36	uuuuuu/pqppqp:bssss0073sss0073	I
    //   155: iconst_2
    //   156: putstatic 69	uuuuuu/pqppqp:b00730073ss0073sss0073	I
    //   159: iload_3
    //   160: iload 4
    //   162: iadd
    //   163: getstatic 36	uuuuuu/pqppqp:bssss0073sss0073	I
    //   166: imul
    //   167: getstatic 40	uuuuuu/pqppqp:bs0073ss0073sss0073	I
    //   170: irem
    //   171: getstatic 69	uuuuuu/pqppqp:b00730073ss0073sss0073	I
    //   174: if_icmpeq +86 -> 260
    //   177: ldc 2
    //   179: ldc 77
    //   181: bipush 116
    //   183: iconst_3
    //   184: invokestatic 48	xxxxxx/uxxxxx:bb00620062bb0062b0062b0062	(Ljava/lang/String;CC)Ljava/lang/String;
    //   187: iconst_0
    //   188: anewarray 50	java/lang/Class
    //   191: invokevirtual 54	java/lang/Class:getMethod	(Ljava/lang/String;[Ljava/lang/Class;)Ljava/lang/reflect/Method;
    //   194: astore 5
    //   196: aload 5
    //   198: aconst_null
    //   199: iconst_0
    //   200: anewarray 56	java/lang/Object
    //   203: invokevirtual 62	java/lang/reflect/Method:invoke	(Ljava/lang/Object;[Ljava/lang/Object;)Ljava/lang/Object;
    //   206: astore 5
    //   208: aload 5
    //   210: checkcast 64	java/lang/Integer
    //   213: invokevirtual 67	java/lang/Integer:intValue	()I
    //   216: putstatic 36	uuuuuu/pqppqp:bssss0073sss0073	I
    //   219: ldc 2
    //   221: ldc 79
    //   223: iconst_5
    //   224: iconst_4
    //   225: invokestatic 48	xxxxxx/uxxxxx:bb00620062bb0062b0062b0062	(Ljava/lang/String;CC)Ljava/lang/String;
    //   228: iconst_0
    //   229: anewarray 50	java/lang/Class
    //   232: invokevirtual 54	java/lang/Class:getMethod	(Ljava/lang/String;[Ljava/lang/Class;)Ljava/lang/reflect/Method;
    //   235: astore 5
    //   237: aload 5
    //   239: aconst_null
    //   240: iconst_0
    //   241: anewarray 56	java/lang/Object
    //   244: invokevirtual 62	java/lang/reflect/Method:invoke	(Ljava/lang/Object;[Ljava/lang/Object;)Ljava/lang/Object;
    //   247: astore 5
    //   249: aload 5
    //   251: checkcast 64	java/lang/Integer
    //   254: invokevirtual 67	java/lang/Integer:intValue	()I
    //   257: putstatic 69	uuuuuu/pqppqp:b00730073ss0073sss0073	I
    //   260: aload_0
    //   261: aload_1
    //   262: putfield 81	uuuuuu/pqppqp:bs007300730073ssss0073	Ljava/util/List;
    //   265: getstatic 36	uuuuuu/pqppqp:bssss0073sss0073	I
    //   268: istore_3
    //   269: ldc 2
    //   271: ldc 83
    //   273: bipush 121
    //   275: iconst_3
    //   276: invokestatic 48	xxxxxx/uxxxxx:bb00620062bb0062b0062b0062	(Ljava/lang/String;CC)Ljava/lang/String;
    //   279: iconst_0
    //   280: anewarray 50	java/lang/Class
    //   283: invokevirtual 54	java/lang/Class:getMethod	(Ljava/lang/String;[Ljava/lang/Class;)Ljava/lang/reflect/Method;
    //   286: astore_1
    //   287: aload_1
    //   288: aconst_null
    //   289: iconst_0
    //   290: anewarray 56	java/lang/Object
    //   293: invokevirtual 62	java/lang/reflect/Method:invoke	(Ljava/lang/Object;[Ljava/lang/Object;)Ljava/lang/Object;
    //   296: astore_1
    //   297: aload_1
    //   298: checkcast 64	java/lang/Integer
    //   301: invokevirtual 67	java/lang/Integer:intValue	()I
    //   304: iload_3
    //   305: iadd
    //   306: iload_3
    //   307: imul
    //   308: getstatic 40	uuuuuu/pqppqp:bs0073ss0073sss0073	I
    //   311: irem
    //   312: tableswitch	default:+20->332, 0:+30->342
    //   332: bipush 33
    //   334: putstatic 36	uuuuuu/pqppqp:bssss0073sss0073	I
    //   337: bipush 34
    //   339: putstatic 69	uuuuuu/pqppqp:b00730073ss0073sss0073	I
    //   342: aload_0
    //   343: aload_2
    //   344: putfield 85	uuuuuu/pqppqp:b0073007300730073ssss0073	Ljava/lang/String;
    //   347: return
    //   348: astore_1
    //   349: aload_1
    //   350: invokevirtual 89	java/lang/reflect/InvocationTargetException:getCause	()Ljava/lang/Throwable;
    //   353: athrow
    //   354: astore_1
    //   355: aload_1
    //   356: invokevirtual 89	java/lang/reflect/InvocationTargetException:getCause	()Ljava/lang/Throwable;
    //   359: athrow
    //   360: astore_1
    //   361: aload_1
    //   362: invokevirtual 89	java/lang/reflect/InvocationTargetException:getCause	()Ljava/lang/Throwable;
    //   365: athrow
    //   366: astore_1
    //   367: aload_1
    //   368: invokevirtual 89	java/lang/reflect/InvocationTargetException:getCause	()Ljava/lang/Throwable;
    //   371: athrow
    //   372: astore_1
    //   373: aload_1
    //   374: invokevirtual 89	java/lang/reflect/InvocationTargetException:getCause	()Ljava/lang/Throwable;
    //   377: athrow
    // Local variable table:
    //   start	length	slot	name	signature
    //   0	378	0	this	pqppqp
    //   0	378	1	paramList	List<Account>
    //   0	378	2	paramString	String
    //   3	305	3	i	int
    //   86	77	4	j	int
    //   49	201	5	localObject	Object
    // Exception table:
    //   from	to	target	type
    //   51	63	348	java/lang/reflect/InvocationTargetException
    //   287	297	354	java/lang/reflect/InvocationTargetException
    //   196	208	360	java/lang/reflect/InvocationTargetException
    //   237	249	366	java/lang/reflect/InvocationTargetException
    //   132	144	372	java/lang/reflect/InvocationTargetException
  }
  
  /* Error */
  public void b006Bk006Bkkkkkkk(qqqqpp.qpppqp paramQpppqp)
  {
    // Byte code:
    //   0: aload_0
    //   1: aload_1
    //   2: invokespecial 97	uuuuuu/qppppp:ba0061a0061a0061a0061aa	(Luuuuuu/ttssst$tsssst;)V
    //   5: aload_1
    //   6: aload_0
    //   7: getfield 81	uuuuuu/pqppqp:bs007300730073ssss0073	Ljava/util/List;
    //   10: invokeinterface 103 2 0
    //   15: getstatic 36	uuuuuu/pqppqp:bssss0073sss0073	I
    //   18: getstatic 38	uuuuuu/pqppqp:b0073sss0073sss0073	I
    //   21: iadd
    //   22: getstatic 36	uuuuuu/pqppqp:bssss0073sss0073	I
    //   25: imul
    //   26: getstatic 40	uuuuuu/pqppqp:bs0073ss0073sss0073	I
    //   29: irem
    //   30: getstatic 69	uuuuuu/pqppqp:b00730073ss0073sss0073	I
    //   33: if_icmpeq +50 -> 83
    //   36: ldc 2
    //   38: ldc 105
    //   40: bipush 45
    //   42: iconst_1
    //   43: invokestatic 48	xxxxxx/uxxxxx:bb00620062bb0062b0062b0062	(Ljava/lang/String;CC)Ljava/lang/String;
    //   46: iconst_0
    //   47: anewarray 50	java/lang/Class
    //   50: invokevirtual 54	java/lang/Class:getMethod	(Ljava/lang/String;[Ljava/lang/Class;)Ljava/lang/reflect/Method;
    //   53: astore 6
    //   55: aload 6
    //   57: aconst_null
    //   58: iconst_0
    //   59: anewarray 56	java/lang/Object
    //   62: invokevirtual 62	java/lang/reflect/Method:invoke	(Ljava/lang/Object;[Ljava/lang/Object;)Ljava/lang/Object;
    //   65: astore 6
    //   67: aload 6
    //   69: checkcast 64	java/lang/Integer
    //   72: invokevirtual 67	java/lang/Integer:intValue	()I
    //   75: putstatic 36	uuuuuu/pqppqp:bssss0073sss0073	I
    //   78: bipush 56
    //   80: putstatic 69	uuuuuu/pqppqp:b00730073ss0073sss0073	I
    //   83: getstatic 36	uuuuuu/pqppqp:bssss0073sss0073	I
    //   86: istore_2
    //   87: getstatic 38	uuuuuu/pqppqp:b0073sss0073sss0073	I
    //   90: istore_3
    //   91: ldc 2
    //   93: ldc 107
    //   95: sipush 141
    //   98: sipush 193
    //   101: iconst_2
    //   102: invokestatic 75	xxxxxx/uxxxxx:bbbb0062b0062b0062b0062	(Ljava/lang/String;CCC)Ljava/lang/String;
    //   105: iconst_0
    //   106: anewarray 50	java/lang/Class
    //   109: invokevirtual 54	java/lang/Class:getMethod	(Ljava/lang/String;[Ljava/lang/Class;)Ljava/lang/reflect/Method;
    //   112: astore 6
    //   114: aload 6
    //   116: aconst_null
    //   117: iconst_0
    //   118: anewarray 56	java/lang/Object
    //   121: invokevirtual 62	java/lang/reflect/Method:invoke	(Ljava/lang/Object;[Ljava/lang/Object;)Ljava/lang/Object;
    //   124: astore 6
    //   126: aload 6
    //   128: checkcast 64	java/lang/Integer
    //   131: invokevirtual 67	java/lang/Integer:intValue	()I
    //   134: istore 4
    //   136: ldc 2
    //   138: ldc 109
    //   140: bipush 102
    //   142: sipush 144
    //   145: iconst_1
    //   146: invokestatic 75	xxxxxx/uxxxxx:bbbb0062b0062b0062b0062	(Ljava/lang/String;CCC)Ljava/lang/String;
    //   149: iconst_0
    //   150: anewarray 50	java/lang/Class
    //   153: invokevirtual 54	java/lang/Class:getMethod	(Ljava/lang/String;[Ljava/lang/Class;)Ljava/lang/reflect/Method;
    //   156: astore 6
    //   158: aload 6
    //   160: aconst_null
    //   161: iconst_0
    //   162: anewarray 56	java/lang/Object
    //   165: invokevirtual 62	java/lang/reflect/Method:invoke	(Ljava/lang/Object;[Ljava/lang/Object;)Ljava/lang/Object;
    //   168: astore 6
    //   170: aload 6
    //   172: checkcast 64	java/lang/Integer
    //   175: invokevirtual 67	java/lang/Integer:intValue	()I
    //   178: istore 5
    //   180: ldc 2
    //   182: ldc 111
    //   184: bipush 45
    //   186: bipush 29
    //   188: iconst_3
    //   189: invokestatic 75	xxxxxx/uxxxxx:bbbb0062b0062b0062b0062	(Ljava/lang/String;CCC)Ljava/lang/String;
    //   192: iconst_0
    //   193: anewarray 50	java/lang/Class
    //   196: invokevirtual 54	java/lang/Class:getMethod	(Ljava/lang/String;[Ljava/lang/Class;)Ljava/lang/reflect/Method;
    //   199: astore 6
    //   201: aload 6
    //   203: aconst_null
    //   204: iconst_0
    //   205: anewarray 56	java/lang/Object
    //   208: invokevirtual 62	java/lang/reflect/Method:invoke	(Ljava/lang/Object;[Ljava/lang/Object;)Ljava/lang/Object;
    //   211: astore 6
    //   213: aload 6
    //   215: checkcast 64	java/lang/Integer
    //   218: invokevirtual 67	java/lang/Integer:intValue	()I
    //   221: iload 4
    //   223: iload 5
    //   225: iadd
    //   226: imul
    //   227: getstatic 40	uuuuuu/pqppqp:bs0073ss0073sss0073	I
    //   230: irem
    //   231: getstatic 69	uuuuuu/pqppqp:b00730073ss0073sss0073	I
    //   234: if_icmpeq +13 -> 247
    //   237: bipush 59
    //   239: putstatic 36	uuuuuu/pqppqp:bssss0073sss0073	I
    //   242: bipush 42
    //   244: putstatic 69	uuuuuu/pqppqp:b00730073ss0073sss0073	I
    //   247: iload_2
    //   248: iload_2
    //   249: iload_3
    //   250: iadd
    //   251: imul
    //   252: getstatic 40	uuuuuu/pqppqp:bs0073ss0073sss0073	I
    //   255: irem
    //   256: tableswitch	default:+20->276, 0:+147->403
    //   276: getstatic 36	uuuuuu/pqppqp:bssss0073sss0073	I
    //   279: istore_2
    //   280: iload_2
    //   281: getstatic 38	uuuuuu/pqppqp:b0073sss0073sss0073	I
    //   284: iload_2
    //   285: iadd
    //   286: imul
    //   287: getstatic 40	uuuuuu/pqppqp:bs0073ss0073sss0073	I
    //   290: irem
    //   291: tableswitch	default:+17->308, 0:+64->355
    //   308: ldc 2
    //   310: ldc 113
    //   312: bipush 55
    //   314: iconst_1
    //   315: invokestatic 48	xxxxxx/uxxxxx:bb00620062bb0062b0062b0062	(Ljava/lang/String;CC)Ljava/lang/String;
    //   318: iconst_0
    //   319: anewarray 50	java/lang/Class
    //   322: invokevirtual 54	java/lang/Class:getMethod	(Ljava/lang/String;[Ljava/lang/Class;)Ljava/lang/reflect/Method;
    //   325: astore 6
    //   327: aload 6
    //   329: aconst_null
    //   330: iconst_0
    //   331: anewarray 56	java/lang/Object
    //   334: invokevirtual 62	java/lang/reflect/Method:invoke	(Ljava/lang/Object;[Ljava/lang/Object;)Ljava/lang/Object;
    //   337: astore 6
    //   339: aload 6
    //   341: checkcast 64	java/lang/Integer
    //   344: invokevirtual 67	java/lang/Integer:intValue	()I
    //   347: putstatic 36	uuuuuu/pqppqp:bssss0073sss0073	I
    //   350: bipush 8
    //   352: putstatic 69	uuuuuu/pqppqp:b00730073ss0073sss0073	I
    //   355: ldc 2
    //   357: ldc 115
    //   359: sipush 156
    //   362: iconst_4
    //   363: invokestatic 48	xxxxxx/uxxxxx:bb00620062bb0062b0062b0062	(Ljava/lang/String;CC)Ljava/lang/String;
    //   366: iconst_0
    //   367: anewarray 50	java/lang/Class
    //   370: invokevirtual 54	java/lang/Class:getMethod	(Ljava/lang/String;[Ljava/lang/Class;)Ljava/lang/reflect/Method;
    //   373: astore 6
    //   375: aload 6
    //   377: aconst_null
    //   378: iconst_0
    //   379: anewarray 56	java/lang/Object
    //   382: invokevirtual 62	java/lang/reflect/Method:invoke	(Ljava/lang/Object;[Ljava/lang/Object;)Ljava/lang/Object;
    //   385: astore 6
    //   387: aload 6
    //   389: checkcast 64	java/lang/Integer
    //   392: invokevirtual 67	java/lang/Integer:intValue	()I
    //   395: putstatic 36	uuuuuu/pqppqp:bssss0073sss0073	I
    //   398: bipush 76
    //   400: putstatic 38	uuuuuu/pqppqp:b0073sss0073sss0073	I
    //   403: aload_1
    //   404: aload_0
    //   405: getfield 85	uuuuuu/pqppqp:b0073007300730073ssss0073	Ljava/lang/String;
    //   408: invokeinterface 119 2 0
    //   413: return
    //   414: astore_1
    //   415: aload_1
    //   416: invokevirtual 89	java/lang/reflect/InvocationTargetException:getCause	()Ljava/lang/Throwable;
    //   419: athrow
    //   420: astore_1
    //   421: aload_1
    //   422: invokevirtual 89	java/lang/reflect/InvocationTargetException:getCause	()Ljava/lang/Throwable;
    //   425: athrow
    //   426: astore_1
    //   427: aload_1
    //   428: invokevirtual 89	java/lang/reflect/InvocationTargetException:getCause	()Ljava/lang/Throwable;
    //   431: athrow
    //   432: astore_1
    //   433: aload_1
    //   434: invokevirtual 89	java/lang/reflect/InvocationTargetException:getCause	()Ljava/lang/Throwable;
    //   437: athrow
    //   438: astore_1
    //   439: aload_1
    //   440: invokevirtual 89	java/lang/reflect/InvocationTargetException:getCause	()Ljava/lang/Throwable;
    //   443: athrow
    //   444: astore_1
    //   445: aload_1
    //   446: invokevirtual 89	java/lang/reflect/InvocationTargetException:getCause	()Ljava/lang/Throwable;
    //   449: athrow
    // Local variable table:
    //   start	length	slot	name	signature
    //   0	450	0	this	pqppqp
    //   0	450	1	paramQpppqp	qqqqpp.qpppqp
    //   86	201	2	i	int
    //   90	161	3	j	int
    //   134	92	4	k	int
    //   178	48	5	m	int
    //   53	335	6	localObject	Object
    // Exception table:
    //   from	to	target	type
    //   375	387	414	java/lang/reflect/InvocationTargetException
    //   55	67	420	java/lang/reflect/InvocationTargetException
    //   114	126	426	java/lang/reflect/InvocationTargetException
    //   158	170	432	java/lang/reflect/InvocationTargetException
    //   201	213	438	java/lang/reflect/InvocationTargetException
    //   327	339	444	java/lang/reflect/InvocationTargetException
  }
  
  /* Error */
  public void b006Bkkkkkkkkk(String paramString)
  {
    // Byte code:
    //   0: getstatic 36	uuuuuu/pqppqp:bssss0073sss0073	I
    //   3: istore_2
    //   4: iload_2
    //   5: getstatic 38	uuuuuu/pqppqp:b0073sss0073sss0073	I
    //   8: iload_2
    //   9: iadd
    //   10: imul
    //   11: getstatic 40	uuuuuu/pqppqp:bs0073ss0073sss0073	I
    //   14: irem
    //   15: tableswitch	default:+17->32, 0:+99->114
    //   32: ldc 2
    //   34: ldc 122
    //   36: bipush 28
    //   38: sipush 131
    //   41: iconst_1
    //   42: invokestatic 75	xxxxxx/uxxxxx:bbbb0062b0062b0062b0062	(Ljava/lang/String;CCC)Ljava/lang/String;
    //   45: iconst_0
    //   46: anewarray 50	java/lang/Class
    //   49: invokevirtual 54	java/lang/Class:getMethod	(Ljava/lang/String;[Ljava/lang/Class;)Ljava/lang/reflect/Method;
    //   52: astore_3
    //   53: aload_3
    //   54: aconst_null
    //   55: iconst_0
    //   56: anewarray 56	java/lang/Object
    //   59: invokevirtual 62	java/lang/reflect/Method:invoke	(Ljava/lang/Object;[Ljava/lang/Object;)Ljava/lang/Object;
    //   62: astore_3
    //   63: aload_3
    //   64: checkcast 64	java/lang/Integer
    //   67: invokevirtual 67	java/lang/Integer:intValue	()I
    //   70: putstatic 36	uuuuuu/pqppqp:bssss0073sss0073	I
    //   73: ldc 2
    //   75: ldc 124
    //   77: sipush 136
    //   80: bipush 122
    //   82: iconst_2
    //   83: invokestatic 75	xxxxxx/uxxxxx:bbbb0062b0062b0062b0062	(Ljava/lang/String;CCC)Ljava/lang/String;
    //   86: iconst_0
    //   87: anewarray 50	java/lang/Class
    //   90: invokevirtual 54	java/lang/Class:getMethod	(Ljava/lang/String;[Ljava/lang/Class;)Ljava/lang/reflect/Method;
    //   93: astore_3
    //   94: aload_3
    //   95: aconst_null
    //   96: iconst_0
    //   97: anewarray 56	java/lang/Object
    //   100: invokevirtual 62	java/lang/reflect/Method:invoke	(Ljava/lang/Object;[Ljava/lang/Object;)Ljava/lang/Object;
    //   103: astore_3
    //   104: aload_3
    //   105: checkcast 64	java/lang/Integer
    //   108: invokevirtual 67	java/lang/Integer:intValue	()I
    //   111: putstatic 69	uuuuuu/pqppqp:b00730073ss0073sss0073	I
    //   114: aload_1
    //   115: aload_0
    //   116: getfield 85	uuuuuu/pqppqp:b0073007300730073ssss0073	Ljava/lang/String;
    //   119: invokevirtual 130	java/lang/String:equals	(Ljava/lang/Object;)Z
    //   122: ifeq +19 -> 141
    //   125: aload_0
    //   126: getfield 134	uuuuuu/pqppqp:bnnnnn006E006E006En	Luuuuuu/ttssst$tsssst;
    //   129: checkcast 99	uuuuuu/qqqqpp$qpppqp
    //   132: aload_0
    //   133: getfield 85	uuuuuu/pqppqp:b0073007300730073ssss0073	Ljava/lang/String;
    //   136: invokeinterface 137 2 0
    //   141: aload_0
    //   142: aload_1
    //   143: putfield 85	uuuuuu/pqppqp:b0073007300730073ssss0073	Ljava/lang/String;
    //   146: aload_0
    //   147: getfield 134	uuuuuu/pqppqp:bnnnnn006E006E006En	Luuuuuu/ttssst$tsssst;
    //   150: checkcast 99	uuuuuu/qqqqpp$qpppqp
    //   153: astore_1
    //   154: ldc 2
    //   156: ldc -117
    //   158: bipush 106
    //   160: bipush 56
    //   162: iconst_2
    //   163: invokestatic 75	xxxxxx/uxxxxx:bbbb0062b0062b0062b0062	(Ljava/lang/String;CCC)Ljava/lang/String;
    //   166: iconst_0
    //   167: anewarray 50	java/lang/Class
    //   170: invokevirtual 54	java/lang/Class:getMethod	(Ljava/lang/String;[Ljava/lang/Class;)Ljava/lang/reflect/Method;
    //   173: astore_3
    //   174: aload_3
    //   175: aconst_null
    //   176: iconst_0
    //   177: anewarray 56	java/lang/Object
    //   180: invokevirtual 62	java/lang/reflect/Method:invoke	(Ljava/lang/Object;[Ljava/lang/Object;)Ljava/lang/Object;
    //   183: astore_3
    //   184: aload_3
    //   185: checkcast 64	java/lang/Integer
    //   188: invokevirtual 67	java/lang/Integer:intValue	()I
    //   191: istore_2
    //   192: iload_2
    //   193: getstatic 38	uuuuuu/pqppqp:b0073sss0073sss0073	I
    //   196: iload_2
    //   197: iadd
    //   198: imul
    //   199: getstatic 40	uuuuuu/pqppqp:bs0073ss0073sss0073	I
    //   202: irem
    //   203: tableswitch	default:+17->220, 0:+64->267
    //   220: bipush 89
    //   222: putstatic 36	uuuuuu/pqppqp:bssss0073sss0073	I
    //   225: ldc 2
    //   227: ldc -115
    //   229: sipush 193
    //   232: sipush 175
    //   235: iconst_1
    //   236: invokestatic 75	xxxxxx/uxxxxx:bbbb0062b0062b0062b0062	(Ljava/lang/String;CCC)Ljava/lang/String;
    //   239: iconst_0
    //   240: anewarray 50	java/lang/Class
    //   243: invokevirtual 54	java/lang/Class:getMethod	(Ljava/lang/String;[Ljava/lang/Class;)Ljava/lang/reflect/Method;
    //   246: astore_3
    //   247: aload_3
    //   248: aconst_null
    //   249: iconst_0
    //   250: anewarray 56	java/lang/Object
    //   253: invokevirtual 62	java/lang/reflect/Method:invoke	(Ljava/lang/Object;[Ljava/lang/Object;)Ljava/lang/Object;
    //   256: astore_3
    //   257: aload_3
    //   258: checkcast 64	java/lang/Integer
    //   261: invokevirtual 67	java/lang/Integer:intValue	()I
    //   264: putstatic 69	uuuuuu/pqppqp:b00730073ss0073sss0073	I
    //   267: getstatic 36	uuuuuu/pqppqp:bssss0073sss0073	I
    //   270: istore_2
    //   271: iload_2
    //   272: getstatic 38	uuuuuu/pqppqp:b0073sss0073sss0073	I
    //   275: iload_2
    //   276: iadd
    //   277: imul
    //   278: getstatic 40	uuuuuu/pqppqp:bs0073ss0073sss0073	I
    //   281: irem
    //   282: tableswitch	default:+18->300, 0:+140->422
    //   300: bipush 14
    //   302: putstatic 36	uuuuuu/pqppqp:bssss0073sss0073	I
    //   305: ldc 2
    //   307: ldc -113
    //   309: bipush 113
    //   311: sipush 227
    //   314: iconst_0
    //   315: invokestatic 75	xxxxxx/uxxxxx:bbbb0062b0062b0062b0062	(Ljava/lang/String;CCC)Ljava/lang/String;
    //   318: iconst_0
    //   319: anewarray 50	java/lang/Class
    //   322: invokevirtual 54	java/lang/Class:getMethod	(Ljava/lang/String;[Ljava/lang/Class;)Ljava/lang/reflect/Method;
    //   325: astore_3
    //   326: aload_3
    //   327: aconst_null
    //   328: iconst_0
    //   329: anewarray 56	java/lang/Object
    //   332: invokevirtual 62	java/lang/reflect/Method:invoke	(Ljava/lang/Object;[Ljava/lang/Object;)Ljava/lang/Object;
    //   335: astore_3
    //   336: aload_3
    //   337: checkcast 64	java/lang/Integer
    //   340: invokevirtual 67	java/lang/Integer:intValue	()I
    //   343: putstatic 69	uuuuuu/pqppqp:b00730073ss0073sss0073	I
    //   346: getstatic 36	uuuuuu/pqppqp:bssss0073sss0073	I
    //   349: istore_2
    //   350: iload_2
    //   351: getstatic 38	uuuuuu/pqppqp:b0073sss0073sss0073	I
    //   354: iload_2
    //   355: iadd
    //   356: imul
    //   357: getstatic 40	uuuuuu/pqppqp:bs0073ss0073sss0073	I
    //   360: irem
    //   361: tableswitch	default:+19->380, 0:+61->422
    //   380: bipush 97
    //   382: putstatic 36	uuuuuu/pqppqp:bssss0073sss0073	I
    //   385: ldc 2
    //   387: ldc -111
    //   389: iconst_3
    //   390: iconst_0
    //   391: invokestatic 48	xxxxxx/uxxxxx:bb00620062bb0062b0062b0062	(Ljava/lang/String;CC)Ljava/lang/String;
    //   394: iconst_0
    //   395: anewarray 50	java/lang/Class
    //   398: invokevirtual 54	java/lang/Class:getMethod	(Ljava/lang/String;[Ljava/lang/Class;)Ljava/lang/reflect/Method;
    //   401: astore_3
    //   402: aload_3
    //   403: aconst_null
    //   404: iconst_0
    //   405: anewarray 56	java/lang/Object
    //   408: invokevirtual 62	java/lang/reflect/Method:invoke	(Ljava/lang/Object;[Ljava/lang/Object;)Ljava/lang/Object;
    //   411: astore_3
    //   412: aload_3
    //   413: checkcast 64	java/lang/Integer
    //   416: invokevirtual 67	java/lang/Integer:intValue	()I
    //   419: putstatic 69	uuuuuu/pqppqp:b00730073ss0073sss0073	I
    //   422: aload_1
    //   423: aload_0
    //   424: getfield 85	uuuuuu/pqppqp:b0073007300730073ssss0073	Ljava/lang/String;
    //   427: invokeinterface 119 2 0
    //   432: return
    //   433: astore_1
    //   434: aload_1
    //   435: invokevirtual 89	java/lang/reflect/InvocationTargetException:getCause	()Ljava/lang/Throwable;
    //   438: athrow
    //   439: astore_1
    //   440: aload_1
    //   441: invokevirtual 89	java/lang/reflect/InvocationTargetException:getCause	()Ljava/lang/Throwable;
    //   444: athrow
    //   445: astore_1
    //   446: aload_1
    //   447: invokevirtual 89	java/lang/reflect/InvocationTargetException:getCause	()Ljava/lang/Throwable;
    //   450: athrow
    //   451: astore_1
    //   452: aload_1
    //   453: invokevirtual 89	java/lang/reflect/InvocationTargetException:getCause	()Ljava/lang/Throwable;
    //   456: athrow
    //   457: astore_1
    //   458: aload_1
    //   459: invokevirtual 89	java/lang/reflect/InvocationTargetException:getCause	()Ljava/lang/Throwable;
    //   462: athrow
    //   463: astore_1
    //   464: aload_1
    //   465: invokevirtual 89	java/lang/reflect/InvocationTargetException:getCause	()Ljava/lang/Throwable;
    //   468: athrow
    // Local variable table:
    //   start	length	slot	name	signature
    //   0	469	0	this	pqppqp
    //   0	469	1	paramString	String
    //   3	354	2	i	int
    //   52	361	3	localObject	Object
    // Exception table:
    //   from	to	target	type
    //   174	184	433	java/lang/reflect/InvocationTargetException
    //   53	63	439	java/lang/reflect/InvocationTargetException
    //   94	104	445	java/lang/reflect/InvocationTargetException
    //   326	336	451	java/lang/reflect/InvocationTargetException
    //   247	257	457	java/lang/reflect/InvocationTargetException
    //   402	412	463	java/lang/reflect/InvocationTargetException
  }
  
  /* Error */
  public void bk006Bkkkkkkkk()
  {
    // Byte code:
    //   0: getstatic 36	uuuuuu/pqppqp:bssss0073sss0073	I
    //   3: istore_1
    //   4: ldc 2
    //   6: ldc -100
    //   8: sipush 155
    //   11: bipush 116
    //   13: iconst_3
    //   14: invokestatic 75	xxxxxx/uxxxxx:bbbb0062b0062b0062b0062	(Ljava/lang/String;CCC)Ljava/lang/String;
    //   17: iconst_0
    //   18: anewarray 50	java/lang/Class
    //   21: invokevirtual 54	java/lang/Class:getMethod	(Ljava/lang/String;[Ljava/lang/Class;)Ljava/lang/reflect/Method;
    //   24: astore_3
    //   25: aload_3
    //   26: aconst_null
    //   27: iconst_0
    //   28: anewarray 56	java/lang/Object
    //   31: invokevirtual 62	java/lang/reflect/Method:invoke	(Ljava/lang/Object;[Ljava/lang/Object;)Ljava/lang/Object;
    //   34: astore_3
    //   35: aload_3
    //   36: checkcast 64	java/lang/Integer
    //   39: invokevirtual 67	java/lang/Integer:intValue	()I
    //   42: iload_1
    //   43: iadd
    //   44: iload_1
    //   45: imul
    //   46: getstatic 40	uuuuuu/pqppqp:bs0073ss0073sss0073	I
    //   49: irem
    //   50: tableswitch	default:+18->68, 0:+94->144
    //   68: ldc 2
    //   70: ldc -98
    //   72: bipush 127
    //   74: iconst_1
    //   75: invokestatic 48	xxxxxx/uxxxxx:bb00620062bb0062b0062b0062	(Ljava/lang/String;CC)Ljava/lang/String;
    //   78: iconst_0
    //   79: anewarray 50	java/lang/Class
    //   82: invokevirtual 54	java/lang/Class:getMethod	(Ljava/lang/String;[Ljava/lang/Class;)Ljava/lang/reflect/Method;
    //   85: astore_3
    //   86: aload_3
    //   87: aconst_null
    //   88: iconst_0
    //   89: anewarray 56	java/lang/Object
    //   92: invokevirtual 62	java/lang/reflect/Method:invoke	(Ljava/lang/Object;[Ljava/lang/Object;)Ljava/lang/Object;
    //   95: astore_3
    //   96: aload_3
    //   97: checkcast 64	java/lang/Integer
    //   100: invokevirtual 67	java/lang/Integer:intValue	()I
    //   103: putstatic 36	uuuuuu/pqppqp:bssss0073sss0073	I
    //   106: ldc 2
    //   108: ldc -96
    //   110: bipush 51
    //   112: iconst_2
    //   113: invokestatic 48	xxxxxx/uxxxxx:bb00620062bb0062b0062b0062	(Ljava/lang/String;CC)Ljava/lang/String;
    //   116: iconst_0
    //   117: anewarray 50	java/lang/Class
    //   120: invokevirtual 54	java/lang/Class:getMethod	(Ljava/lang/String;[Ljava/lang/Class;)Ljava/lang/reflect/Method;
    //   123: astore_3
    //   124: aload_3
    //   125: aconst_null
    //   126: iconst_0
    //   127: anewarray 56	java/lang/Object
    //   130: invokevirtual 62	java/lang/reflect/Method:invoke	(Ljava/lang/Object;[Ljava/lang/Object;)Ljava/lang/Object;
    //   133: astore_3
    //   134: aload_3
    //   135: checkcast 64	java/lang/Integer
    //   138: invokevirtual 67	java/lang/Integer:intValue	()I
    //   141: putstatic 69	uuuuuu/pqppqp:b00730073ss0073sss0073	I
    //   144: aload_0
    //   145: getfield 134	uuuuuu/pqppqp:bnnnnn006E006E006En	Luuuuuu/ttssst$tsssst;
    //   148: checkcast 99	uuuuuu/qqqqpp$qpppqp
    //   151: astore_3
    //   152: getstatic 36	uuuuuu/pqppqp:bssss0073sss0073	I
    //   155: istore_1
    //   156: ldc 2
    //   158: ldc -94
    //   160: bipush 45
    //   162: iconst_4
    //   163: invokestatic 48	xxxxxx/uxxxxx:bb00620062bb0062b0062b0062	(Ljava/lang/String;CC)Ljava/lang/String;
    //   166: iconst_0
    //   167: anewarray 50	java/lang/Class
    //   170: invokevirtual 54	java/lang/Class:getMethod	(Ljava/lang/String;[Ljava/lang/Class;)Ljava/lang/reflect/Method;
    //   173: astore 4
    //   175: aload 4
    //   177: aconst_null
    //   178: iconst_0
    //   179: anewarray 56	java/lang/Object
    //   182: invokevirtual 62	java/lang/reflect/Method:invoke	(Ljava/lang/Object;[Ljava/lang/Object;)Ljava/lang/Object;
    //   185: astore 4
    //   187: aload 4
    //   189: checkcast 64	java/lang/Integer
    //   192: invokevirtual 67	java/lang/Integer:intValue	()I
    //   195: iload_1
    //   196: iadd
    //   197: getstatic 36	uuuuuu/pqppqp:bssss0073sss0073	I
    //   200: imul
    //   201: getstatic 40	uuuuuu/pqppqp:bs0073ss0073sss0073	I
    //   204: irem
    //   205: getstatic 69	uuuuuu/pqppqp:b00730073ss0073sss0073	I
    //   208: if_icmpeq +280 -> 488
    //   211: getstatic 36	uuuuuu/pqppqp:bssss0073sss0073	I
    //   214: getstatic 38	uuuuuu/pqppqp:b0073sss0073sss0073	I
    //   217: iadd
    //   218: getstatic 36	uuuuuu/pqppqp:bssss0073sss0073	I
    //   221: imul
    //   222: getstatic 40	uuuuuu/pqppqp:bs0073ss0073sss0073	I
    //   225: irem
    //   226: getstatic 69	uuuuuu/pqppqp:b00730073ss0073sss0073	I
    //   229: if_icmpeq +249 -> 478
    //   232: bipush 21
    //   234: putstatic 36	uuuuuu/pqppqp:bssss0073sss0073	I
    //   237: bipush 92
    //   239: putstatic 69	uuuuuu/pqppqp:b00730073ss0073sss0073	I
    //   242: ldc 2
    //   244: ldc -92
    //   246: sipush 238
    //   249: iconst_4
    //   250: invokestatic 48	xxxxxx/uxxxxx:bb00620062bb0062b0062b0062	(Ljava/lang/String;CC)Ljava/lang/String;
    //   253: iconst_0
    //   254: anewarray 50	java/lang/Class
    //   257: invokevirtual 54	java/lang/Class:getMethod	(Ljava/lang/String;[Ljava/lang/Class;)Ljava/lang/reflect/Method;
    //   260: astore 4
    //   262: aload 4
    //   264: aconst_null
    //   265: iconst_0
    //   266: anewarray 56	java/lang/Object
    //   269: invokevirtual 62	java/lang/reflect/Method:invoke	(Ljava/lang/Object;[Ljava/lang/Object;)Ljava/lang/Object;
    //   272: astore 4
    //   274: aload 4
    //   276: checkcast 64	java/lang/Integer
    //   279: invokevirtual 67	java/lang/Integer:intValue	()I
    //   282: istore_1
    //   283: ldc 2
    //   285: ldc -90
    //   287: bipush 61
    //   289: bipush 72
    //   291: iconst_3
    //   292: invokestatic 75	xxxxxx/uxxxxx:bbbb0062b0062b0062b0062	(Ljava/lang/String;CCC)Ljava/lang/String;
    //   295: iconst_0
    //   296: anewarray 50	java/lang/Class
    //   299: invokevirtual 54	java/lang/Class:getMethod	(Ljava/lang/String;[Ljava/lang/Class;)Ljava/lang/reflect/Method;
    //   302: astore 4
    //   304: aload 4
    //   306: aconst_null
    //   307: iconst_0
    //   308: anewarray 56	java/lang/Object
    //   311: invokevirtual 62	java/lang/reflect/Method:invoke	(Ljava/lang/Object;[Ljava/lang/Object;)Ljava/lang/Object;
    //   314: astore 4
    //   316: aload 4
    //   318: checkcast 64	java/lang/Integer
    //   321: invokevirtual 67	java/lang/Integer:intValue	()I
    //   324: istore_2
    //   325: ldc 2
    //   327: ldc -88
    //   329: bipush 80
    //   331: iconst_5
    //   332: invokestatic 48	xxxxxx/uxxxxx:bb00620062bb0062b0062b0062	(Ljava/lang/String;CC)Ljava/lang/String;
    //   335: iconst_0
    //   336: anewarray 50	java/lang/Class
    //   339: invokevirtual 54	java/lang/Class:getMethod	(Ljava/lang/String;[Ljava/lang/Class;)Ljava/lang/reflect/Method;
    //   342: astore 4
    //   344: aload 4
    //   346: aconst_null
    //   347: iconst_0
    //   348: anewarray 56	java/lang/Object
    //   351: invokevirtual 62	java/lang/reflect/Method:invoke	(Ljava/lang/Object;[Ljava/lang/Object;)Ljava/lang/Object;
    //   354: astore 4
    //   356: iload_1
    //   357: iload_2
    //   358: iload_1
    //   359: iadd
    //   360: imul
    //   361: aload 4
    //   363: checkcast 64	java/lang/Integer
    //   366: invokevirtual 67	java/lang/Integer:intValue	()I
    //   369: irem
    //   370: tableswitch	default:+18->388, 0:+108->478
    //   388: ldc 2
    //   390: ldc -86
    //   392: bipush 116
    //   394: sipush 200
    //   397: iconst_3
    //   398: invokestatic 75	xxxxxx/uxxxxx:bbbb0062b0062b0062b0062	(Ljava/lang/String;CCC)Ljava/lang/String;
    //   401: iconst_0
    //   402: anewarray 50	java/lang/Class
    //   405: invokevirtual 54	java/lang/Class:getMethod	(Ljava/lang/String;[Ljava/lang/Class;)Ljava/lang/reflect/Method;
    //   408: astore 4
    //   410: aload 4
    //   412: aconst_null
    //   413: iconst_0
    //   414: anewarray 56	java/lang/Object
    //   417: invokevirtual 62	java/lang/reflect/Method:invoke	(Ljava/lang/Object;[Ljava/lang/Object;)Ljava/lang/Object;
    //   420: astore 4
    //   422: aload 4
    //   424: checkcast 64	java/lang/Integer
    //   427: invokevirtual 67	java/lang/Integer:intValue	()I
    //   430: putstatic 36	uuuuuu/pqppqp:bssss0073sss0073	I
    //   433: ldc 2
    //   435: ldc -84
    //   437: bipush 19
    //   439: sipush 149
    //   442: iconst_0
    //   443: invokestatic 75	xxxxxx/uxxxxx:bbbb0062b0062b0062b0062	(Ljava/lang/String;CCC)Ljava/lang/String;
    //   446: iconst_0
    //   447: anewarray 50	java/lang/Class
    //   450: invokevirtual 54	java/lang/Class:getMethod	(Ljava/lang/String;[Ljava/lang/Class;)Ljava/lang/reflect/Method;
    //   453: astore 4
    //   455: aload 4
    //   457: aconst_null
    //   458: iconst_0
    //   459: anewarray 56	java/lang/Object
    //   462: invokevirtual 62	java/lang/reflect/Method:invoke	(Ljava/lang/Object;[Ljava/lang/Object;)Ljava/lang/Object;
    //   465: astore 4
    //   467: aload 4
    //   469: checkcast 64	java/lang/Integer
    //   472: invokevirtual 67	java/lang/Integer:intValue	()I
    //   475: putstatic 69	uuuuuu/pqppqp:b00730073ss0073sss0073	I
    //   478: bipush 30
    //   480: putstatic 36	uuuuuu/pqppqp:bssss0073sss0073	I
    //   483: bipush 34
    //   485: putstatic 69	uuuuuu/pqppqp:b00730073ss0073sss0073	I
    //   488: aload_3
    //   489: aload_0
    //   490: getfield 85	uuuuuu/pqppqp:b0073007300730073ssss0073	Ljava/lang/String;
    //   493: invokeinterface 137 2 0
    //   498: return
    //   499: astore_3
    //   500: aload_3
    //   501: invokevirtual 89	java/lang/reflect/InvocationTargetException:getCause	()Ljava/lang/Throwable;
    //   504: athrow
    //   505: astore_3
    //   506: aload_3
    //   507: invokevirtual 89	java/lang/reflect/InvocationTargetException:getCause	()Ljava/lang/Throwable;
    //   510: athrow
    //   511: astore_3
    //   512: aload_3
    //   513: invokevirtual 89	java/lang/reflect/InvocationTargetException:getCause	()Ljava/lang/Throwable;
    //   516: athrow
    //   517: astore_3
    //   518: aload_3
    //   519: invokevirtual 89	java/lang/reflect/InvocationTargetException:getCause	()Ljava/lang/Throwable;
    //   522: athrow
    //   523: astore_3
    //   524: aload_3
    //   525: invokevirtual 89	java/lang/reflect/InvocationTargetException:getCause	()Ljava/lang/Throwable;
    //   528: athrow
    //   529: astore_3
    //   530: aload_3
    //   531: invokevirtual 89	java/lang/reflect/InvocationTargetException:getCause	()Ljava/lang/Throwable;
    //   534: athrow
    //   535: astore_3
    //   536: aload_3
    //   537: invokevirtual 89	java/lang/reflect/InvocationTargetException:getCause	()Ljava/lang/Throwable;
    //   540: athrow
    //   541: astore_3
    //   542: aload_3
    //   543: invokevirtual 89	java/lang/reflect/InvocationTargetException:getCause	()Ljava/lang/Throwable;
    //   546: athrow
    //   547: astore_3
    //   548: aload_3
    //   549: invokevirtual 89	java/lang/reflect/InvocationTargetException:getCause	()Ljava/lang/Throwable;
    //   552: athrow
    // Local variable table:
    //   start	length	slot	name	signature
    //   0	553	0	this	pqppqp
    //   3	358	1	i	int
    //   324	36	2	j	int
    //   24	465	3	localObject1	Object
    //   499	2	3	localInvocationTargetException1	java.lang.reflect.InvocationTargetException
    //   505	2	3	localInvocationTargetException2	java.lang.reflect.InvocationTargetException
    //   511	2	3	localInvocationTargetException3	java.lang.reflect.InvocationTargetException
    //   517	2	3	localInvocationTargetException4	java.lang.reflect.InvocationTargetException
    //   523	2	3	localInvocationTargetException5	java.lang.reflect.InvocationTargetException
    //   529	2	3	localInvocationTargetException6	java.lang.reflect.InvocationTargetException
    //   535	2	3	localInvocationTargetException7	java.lang.reflect.InvocationTargetException
    //   541	2	3	localInvocationTargetException8	java.lang.reflect.InvocationTargetException
    //   547	2	3	localInvocationTargetException9	java.lang.reflect.InvocationTargetException
    //   173	295	4	localObject2	Object
    // Exception table:
    //   from	to	target	type
    //   86	96	499	java/lang/reflect/InvocationTargetException
    //   175	187	505	java/lang/reflect/InvocationTargetException
    //   124	134	511	java/lang/reflect/InvocationTargetException
    //   262	274	517	java/lang/reflect/InvocationTargetException
    //   304	316	523	java/lang/reflect/InvocationTargetException
    //   344	356	529	java/lang/reflect/InvocationTargetException
    //   25	35	535	java/lang/reflect/InvocationTargetException
    //   410	422	541	java/lang/reflect/InvocationTargetException
    //   455	467	547	java/lang/reflect/InvocationTargetException
  }
}
