package uuuuuu;

import android.content.Context;
import android.support.annotation.NonNull;
import android.text.format.DateUtils;
import com.db.pwcc.dbmobile.foundation.R.string;
import java.lang.reflect.InvocationTargetException;
import java.lang.reflect.Method;
import java.text.DateFormat;
import java.text.ParseException;
import java.text.SimpleDateFormat;
import java.util.Calendar;
import java.util.Date;
import java.util.GregorianCalendar;
import java.util.Locale;
import java.util.TimeZone;
import java.util.concurrent.TimeUnit;
import xxxxxx.uxxxxx;

public class pqpppq
{
  private static final String b007300730073007300730073ss0073 = "XWV(\001~}";
  public static final String b007300730073sss0073s0073 = "\033\034\035\036RstU\016\017R\001Tvwj\037 m()]\022_";
  public static final String b00730073s007300730073ss0073 = "PO\03065\025_^]\\\016\001('\030JI";
  public static int b00730073s0073ss0073s0073 = 2;
  private static final String b00730073ssss0073s0073 = "\n\013}23";
  private static final String b0073s0073007300730073ss0073 = "\003\004\005la\020\021s*+vBCDE";
  public static int b0073s00730073ss0073s0073 = 0;
  public static final String b0073s0073sss0073s0073 = "\013\f\r\016BcdE}~";
  private static final String b0073ss0073ss0073s0073 = "-^\\Z\\R\0351Uc^\\b";
  public static final String b0073sssss0073s0073 = "\007\bj!\"m9:;<od\016\017\00267";
  public static final String bs00730073007300730073ss0073 = ";<=>\022lmno";
  public static final String bs00730073sss0073s0073 = ">?@Au\027\030x12u$w\032\033\016BC\021KL\b./0\0059\007";
  private static final String bs0073s007300730073ss0073 = "_`+KL.z{|}";
  public static int bs0073s0073ss0073s0073 = 81;
  public static final String bs0073ssss0073s0073 = "}~a\030\031d0123f[%&x-.a$";
  private static final String bss0073007300730073ss0073 = "<;: \023VU\036<;\033edcb";
  public static int bss00730073ss0073s0073 = 1;
  public static final String bss0073sss0073s0073 = "*)('Yxw";
  private static final String bsss0073ss0073s0073;
  private static final String bssssss0073s0073 = "\027\030z12}IJKL";
  
  /* Error */
  static
  {
    // Byte code:
    //   0: getstatic 66	uuuuuu/pqpppq:bs0073s007300730073ss0073	Ljava/lang/String;
    //   3: astore_1
    //   4: ldc 68
    //   6: ldc 70
    //   8: bipush 10
    //   10: sipush 140
    //   13: iconst_2
    //   14: invokestatic 76	xxxxxx/uxxxxx:bbbb0062b0062b0062b0062	(Ljava/lang/String;CCC)Ljava/lang/String;
    //   17: iconst_4
    //   18: anewarray 78	java/lang/Class
    //   21: dup
    //   22: iconst_0
    //   23: ldc 80
    //   25: aastore
    //   26: dup
    //   27: iconst_1
    //   28: getstatic 86	java/lang/Character:TYPE	Ljava/lang/Class;
    //   31: aastore
    //   32: dup
    //   33: iconst_2
    //   34: getstatic 86	java/lang/Character:TYPE	Ljava/lang/Class;
    //   37: aastore
    //   38: dup
    //   39: iconst_3
    //   40: getstatic 86	java/lang/Character:TYPE	Ljava/lang/Class;
    //   43: aastore
    //   44: invokevirtual 90	java/lang/Class:getMethod	(Ljava/lang/String;[Ljava/lang/Class;)Ljava/lang/reflect/Method;
    //   47: astore_2
    //   48: aload_2
    //   49: aconst_null
    //   50: iconst_4
    //   51: anewarray 4	java/lang/Object
    //   54: dup
    //   55: iconst_0
    //   56: aload_1
    //   57: aastore
    //   58: dup
    //   59: iconst_1
    //   60: sipush 169
    //   63: invokestatic 94	java/lang/Character:valueOf	(C)Ljava/lang/Character;
    //   66: aastore
    //   67: dup
    //   68: iconst_2
    //   69: sipush 207
    //   72: invokestatic 94	java/lang/Character:valueOf	(C)Ljava/lang/Character;
    //   75: aastore
    //   76: dup
    //   77: iconst_3
    //   78: iconst_3
    //   79: invokestatic 94	java/lang/Character:valueOf	(C)Ljava/lang/Character;
    //   82: aastore
    //   83: invokevirtual 100	java/lang/reflect/Method:invoke	(Ljava/lang/Object;[Ljava/lang/Object;)Ljava/lang/Object;
    //   86: astore_1
    //   87: aload_1
    //   88: checkcast 80	java/lang/String
    //   91: putstatic 66	uuuuuu/pqpppq:bs0073s007300730073ss0073	Ljava/lang/String;
    //   94: getstatic 102	uuuuuu/pqpppq:b00730073s007300730073ss0073	Ljava/lang/String;
    //   97: astore_1
    //   98: ldc 68
    //   100: ldc 104
    //   102: sipush 178
    //   105: iconst_0
    //   106: invokestatic 108	xxxxxx/uxxxxx:bb00620062bb0062b0062b0062	(Ljava/lang/String;CC)Ljava/lang/String;
    //   109: iconst_3
    //   110: anewarray 78	java/lang/Class
    //   113: dup
    //   114: iconst_0
    //   115: ldc 80
    //   117: aastore
    //   118: dup
    //   119: iconst_1
    //   120: getstatic 86	java/lang/Character:TYPE	Ljava/lang/Class;
    //   123: aastore
    //   124: dup
    //   125: iconst_2
    //   126: getstatic 86	java/lang/Character:TYPE	Ljava/lang/Class;
    //   129: aastore
    //   130: invokevirtual 90	java/lang/Class:getMethod	(Ljava/lang/String;[Ljava/lang/Class;)Ljava/lang/reflect/Method;
    //   133: astore_2
    //   134: aload_2
    //   135: aconst_null
    //   136: iconst_3
    //   137: anewarray 4	java/lang/Object
    //   140: dup
    //   141: iconst_0
    //   142: aload_1
    //   143: aastore
    //   144: dup
    //   145: iconst_1
    //   146: bipush 20
    //   148: invokestatic 94	java/lang/Character:valueOf	(C)Ljava/lang/Character;
    //   151: aastore
    //   152: dup
    //   153: iconst_2
    //   154: iconst_3
    //   155: invokestatic 94	java/lang/Character:valueOf	(C)Ljava/lang/Character;
    //   158: aastore
    //   159: invokevirtual 100	java/lang/reflect/Method:invoke	(Ljava/lang/Object;[Ljava/lang/Object;)Ljava/lang/Object;
    //   162: astore_1
    //   163: aload_1
    //   164: checkcast 80	java/lang/String
    //   167: putstatic 102	uuuuuu/pqpppq:b00730073s007300730073ss0073	Ljava/lang/String;
    //   170: getstatic 110	uuuuuu/pqpppq:bss0073007300730073ss0073	Ljava/lang/String;
    //   173: astore_1
    //   174: ldc 68
    //   176: ldc 112
    //   178: sipush 131
    //   181: iconst_2
    //   182: invokestatic 108	xxxxxx/uxxxxx:bb00620062bb0062b0062b0062	(Ljava/lang/String;CC)Ljava/lang/String;
    //   185: iconst_3
    //   186: anewarray 78	java/lang/Class
    //   189: dup
    //   190: iconst_0
    //   191: ldc 80
    //   193: aastore
    //   194: dup
    //   195: iconst_1
    //   196: getstatic 86	java/lang/Character:TYPE	Ljava/lang/Class;
    //   199: aastore
    //   200: dup
    //   201: iconst_2
    //   202: getstatic 86	java/lang/Character:TYPE	Ljava/lang/Class;
    //   205: aastore
    //   206: invokevirtual 90	java/lang/Class:getMethod	(Ljava/lang/String;[Ljava/lang/Class;)Ljava/lang/reflect/Method;
    //   209: astore_2
    //   210: aload_2
    //   211: aconst_null
    //   212: iconst_3
    //   213: anewarray 4	java/lang/Object
    //   216: dup
    //   217: iconst_0
    //   218: aload_1
    //   219: aastore
    //   220: dup
    //   221: iconst_1
    //   222: sipush 195
    //   225: invokestatic 94	java/lang/Character:valueOf	(C)Ljava/lang/Character;
    //   228: aastore
    //   229: dup
    //   230: iconst_2
    //   231: iconst_4
    //   232: invokestatic 94	java/lang/Character:valueOf	(C)Ljava/lang/Character;
    //   235: aastore
    //   236: invokevirtual 100	java/lang/reflect/Method:invoke	(Ljava/lang/Object;[Ljava/lang/Object;)Ljava/lang/Object;
    //   239: astore_1
    //   240: aload_1
    //   241: checkcast 80	java/lang/String
    //   244: putstatic 110	uuuuuu/pqpppq:bss0073007300730073ss0073	Ljava/lang/String;
    //   247: getstatic 114	uuuuuu/pqpppq:b0073s0073007300730073ss0073	Ljava/lang/String;
    //   250: astore_1
    //   251: ldc 68
    //   253: ldc 116
    //   255: sipush 196
    //   258: iconst_5
    //   259: invokestatic 108	xxxxxx/uxxxxx:bb00620062bb0062b0062b0062	(Ljava/lang/String;CC)Ljava/lang/String;
    //   262: iconst_3
    //   263: anewarray 78	java/lang/Class
    //   266: dup
    //   267: iconst_0
    //   268: ldc 80
    //   270: aastore
    //   271: dup
    //   272: iconst_1
    //   273: getstatic 86	java/lang/Character:TYPE	Ljava/lang/Class;
    //   276: aastore
    //   277: dup
    //   278: iconst_2
    //   279: getstatic 86	java/lang/Character:TYPE	Ljava/lang/Class;
    //   282: aastore
    //   283: invokevirtual 90	java/lang/Class:getMethod	(Ljava/lang/String;[Ljava/lang/Class;)Ljava/lang/reflect/Method;
    //   286: astore_2
    //   287: aload_2
    //   288: aconst_null
    //   289: iconst_3
    //   290: anewarray 4	java/lang/Object
    //   293: dup
    //   294: iconst_0
    //   295: aload_1
    //   296: aastore
    //   297: dup
    //   298: iconst_1
    //   299: bipush 105
    //   301: invokestatic 94	java/lang/Character:valueOf	(C)Ljava/lang/Character;
    //   304: aastore
    //   305: dup
    //   306: iconst_2
    //   307: iconst_0
    //   308: invokestatic 94	java/lang/Character:valueOf	(C)Ljava/lang/Character;
    //   311: aastore
    //   312: invokevirtual 100	java/lang/reflect/Method:invoke	(Ljava/lang/Object;[Ljava/lang/Object;)Ljava/lang/Object;
    //   315: astore_1
    //   316: aload_1
    //   317: checkcast 80	java/lang/String
    //   320: putstatic 114	uuuuuu/pqpppq:b0073s0073007300730073ss0073	Ljava/lang/String;
    //   323: getstatic 118	uuuuuu/pqpppq:bs00730073007300730073ss0073	Ljava/lang/String;
    //   326: astore_1
    //   327: ldc 68
    //   329: ldc 120
    //   331: bipush 91
    //   333: sipush 215
    //   336: iconst_0
    //   337: invokestatic 76	xxxxxx/uxxxxx:bbbb0062b0062b0062b0062	(Ljava/lang/String;CCC)Ljava/lang/String;
    //   340: iconst_3
    //   341: anewarray 78	java/lang/Class
    //   344: dup
    //   345: iconst_0
    //   346: ldc 80
    //   348: aastore
    //   349: dup
    //   350: iconst_1
    //   351: getstatic 86	java/lang/Character:TYPE	Ljava/lang/Class;
    //   354: aastore
    //   355: dup
    //   356: iconst_2
    //   357: getstatic 86	java/lang/Character:TYPE	Ljava/lang/Class;
    //   360: aastore
    //   361: invokevirtual 90	java/lang/Class:getMethod	(Ljava/lang/String;[Ljava/lang/Class;)Ljava/lang/reflect/Method;
    //   364: astore_2
    //   365: aload_2
    //   366: aconst_null
    //   367: iconst_3
    //   368: anewarray 4	java/lang/Object
    //   371: dup
    //   372: iconst_0
    //   373: aload_1
    //   374: aastore
    //   375: dup
    //   376: iconst_1
    //   377: sipush 236
    //   380: invokestatic 94	java/lang/Character:valueOf	(C)Ljava/lang/Character;
    //   383: aastore
    //   384: dup
    //   385: iconst_2
    //   386: iconst_2
    //   387: invokestatic 94	java/lang/Character:valueOf	(C)Ljava/lang/Character;
    //   390: aastore
    //   391: invokevirtual 100	java/lang/reflect/Method:invoke	(Ljava/lang/Object;[Ljava/lang/Object;)Ljava/lang/Object;
    //   394: astore_1
    //   395: aload_1
    //   396: checkcast 80	java/lang/String
    //   399: putstatic 118	uuuuuu/pqpppq:bs00730073007300730073ss0073	Ljava/lang/String;
    //   402: getstatic 122	uuuuuu/pqpppq:b007300730073007300730073ss0073	Ljava/lang/String;
    //   405: astore_1
    //   406: ldc 68
    //   408: ldc 124
    //   410: bipush 11
    //   412: iconst_1
    //   413: invokestatic 108	xxxxxx/uxxxxx:bb00620062bb0062b0062b0062	(Ljava/lang/String;CC)Ljava/lang/String;
    //   416: iconst_3
    //   417: anewarray 78	java/lang/Class
    //   420: dup
    //   421: iconst_0
    //   422: ldc 80
    //   424: aastore
    //   425: dup
    //   426: iconst_1
    //   427: getstatic 86	java/lang/Character:TYPE	Ljava/lang/Class;
    //   430: aastore
    //   431: dup
    //   432: iconst_2
    //   433: getstatic 86	java/lang/Character:TYPE	Ljava/lang/Class;
    //   436: aastore
    //   437: invokevirtual 90	java/lang/Class:getMethod	(Ljava/lang/String;[Ljava/lang/Class;)Ljava/lang/reflect/Method;
    //   440: astore_2
    //   441: aload_2
    //   442: aconst_null
    //   443: iconst_3
    //   444: anewarray 4	java/lang/Object
    //   447: dup
    //   448: iconst_0
    //   449: aload_1
    //   450: aastore
    //   451: dup
    //   452: iconst_1
    //   453: sipush 185
    //   456: invokestatic 94	java/lang/Character:valueOf	(C)Ljava/lang/Character;
    //   459: aastore
    //   460: dup
    //   461: iconst_2
    //   462: iconst_4
    //   463: invokestatic 94	java/lang/Character:valueOf	(C)Ljava/lang/Character;
    //   466: aastore
    //   467: invokevirtual 100	java/lang/reflect/Method:invoke	(Ljava/lang/Object;[Ljava/lang/Object;)Ljava/lang/Object;
    //   470: astore_1
    //   471: aload_1
    //   472: checkcast 80	java/lang/String
    //   475: putstatic 122	uuuuuu/pqpppq:b007300730073007300730073ss0073	Ljava/lang/String;
    //   478: getstatic 126	uuuuuu/pqpppq:bssssss0073s0073	Ljava/lang/String;
    //   481: astore_1
    //   482: ldc 68
    //   484: ldc -128
    //   486: bipush 99
    //   488: iconst_0
    //   489: invokestatic 108	xxxxxx/uxxxxx:bb00620062bb0062b0062b0062	(Ljava/lang/String;CC)Ljava/lang/String;
    //   492: iconst_4
    //   493: anewarray 78	java/lang/Class
    //   496: dup
    //   497: iconst_0
    //   498: ldc 80
    //   500: aastore
    //   501: dup
    //   502: iconst_1
    //   503: getstatic 86	java/lang/Character:TYPE	Ljava/lang/Class;
    //   506: aastore
    //   507: dup
    //   508: iconst_2
    //   509: getstatic 86	java/lang/Character:TYPE	Ljava/lang/Class;
    //   512: aastore
    //   513: dup
    //   514: iconst_3
    //   515: getstatic 86	java/lang/Character:TYPE	Ljava/lang/Class;
    //   518: aastore
    //   519: invokevirtual 90	java/lang/Class:getMethod	(Ljava/lang/String;[Ljava/lang/Class;)Ljava/lang/reflect/Method;
    //   522: astore_2
    //   523: aload_2
    //   524: aconst_null
    //   525: iconst_4
    //   526: anewarray 4	java/lang/Object
    //   529: dup
    //   530: iconst_0
    //   531: aload_1
    //   532: aastore
    //   533: dup
    //   534: iconst_1
    //   535: bipush 35
    //   537: invokestatic 94	java/lang/Character:valueOf	(C)Ljava/lang/Character;
    //   540: aastore
    //   541: dup
    //   542: iconst_2
    //   543: bipush 89
    //   545: invokestatic 94	java/lang/Character:valueOf	(C)Ljava/lang/Character;
    //   548: aastore
    //   549: dup
    //   550: iconst_3
    //   551: iconst_2
    //   552: invokestatic 94	java/lang/Character:valueOf	(C)Ljava/lang/Character;
    //   555: aastore
    //   556: invokevirtual 100	java/lang/reflect/Method:invoke	(Ljava/lang/Object;[Ljava/lang/Object;)Ljava/lang/Object;
    //   559: astore_1
    //   560: aload_1
    //   561: checkcast 80	java/lang/String
    //   564: putstatic 126	uuuuuu/pqpppq:bssssss0073s0073	Ljava/lang/String;
    //   567: getstatic 130	uuuuuu/pqpppq:b0073sssss0073s0073	Ljava/lang/String;
    //   570: astore_1
    //   571: ldc 68
    //   573: ldc -124
    //   575: sipush 180
    //   578: iconst_0
    //   579: invokestatic 108	xxxxxx/uxxxxx:bb00620062bb0062b0062b0062	(Ljava/lang/String;CC)Ljava/lang/String;
    //   582: iconst_3
    //   583: anewarray 78	java/lang/Class
    //   586: dup
    //   587: iconst_0
    //   588: ldc 80
    //   590: aastore
    //   591: dup
    //   592: iconst_1
    //   593: getstatic 86	java/lang/Character:TYPE	Ljava/lang/Class;
    //   596: aastore
    //   597: dup
    //   598: iconst_2
    //   599: getstatic 86	java/lang/Character:TYPE	Ljava/lang/Class;
    //   602: aastore
    //   603: invokevirtual 90	java/lang/Class:getMethod	(Ljava/lang/String;[Ljava/lang/Class;)Ljava/lang/reflect/Method;
    //   606: astore_2
    //   607: aload_2
    //   608: aconst_null
    //   609: iconst_3
    //   610: anewarray 4	java/lang/Object
    //   613: dup
    //   614: iconst_0
    //   615: aload_1
    //   616: aastore
    //   617: dup
    //   618: iconst_1
    //   619: sipush 219
    //   622: invokestatic 94	java/lang/Character:valueOf	(C)Ljava/lang/Character;
    //   625: aastore
    //   626: dup
    //   627: iconst_2
    //   628: iconst_1
    //   629: invokestatic 94	java/lang/Character:valueOf	(C)Ljava/lang/Character;
    //   632: aastore
    //   633: invokevirtual 100	java/lang/reflect/Method:invoke	(Ljava/lang/Object;[Ljava/lang/Object;)Ljava/lang/Object;
    //   636: astore_1
    //   637: aload_1
    //   638: checkcast 80	java/lang/String
    //   641: putstatic 130	uuuuuu/pqpppq:b0073sssss0073s0073	Ljava/lang/String;
    //   644: getstatic 134	uuuuuu/pqpppq:bs0073ssss0073s0073	Ljava/lang/String;
    //   647: astore_1
    //   648: ldc 68
    //   650: ldc -120
    //   652: bipush 54
    //   654: iconst_4
    //   655: invokestatic 108	xxxxxx/uxxxxx:bb00620062bb0062b0062b0062	(Ljava/lang/String;CC)Ljava/lang/String;
    //   658: iconst_4
    //   659: anewarray 78	java/lang/Class
    //   662: dup
    //   663: iconst_0
    //   664: ldc 80
    //   666: aastore
    //   667: dup
    //   668: iconst_1
    //   669: getstatic 86	java/lang/Character:TYPE	Ljava/lang/Class;
    //   672: aastore
    //   673: dup
    //   674: iconst_2
    //   675: getstatic 86	java/lang/Character:TYPE	Ljava/lang/Class;
    //   678: aastore
    //   679: dup
    //   680: iconst_3
    //   681: getstatic 86	java/lang/Character:TYPE	Ljava/lang/Class;
    //   684: aastore
    //   685: invokevirtual 90	java/lang/Class:getMethod	(Ljava/lang/String;[Ljava/lang/Class;)Ljava/lang/reflect/Method;
    //   688: astore_2
    //   689: aload_2
    //   690: aconst_null
    //   691: iconst_4
    //   692: anewarray 4	java/lang/Object
    //   695: dup
    //   696: iconst_0
    //   697: aload_1
    //   698: aastore
    //   699: dup
    //   700: iconst_1
    //   701: sipush 175
    //   704: invokestatic 94	java/lang/Character:valueOf	(C)Ljava/lang/Character;
    //   707: aastore
    //   708: dup
    //   709: iconst_2
    //   710: bipush 127
    //   712: invokestatic 94	java/lang/Character:valueOf	(C)Ljava/lang/Character;
    //   715: aastore
    //   716: dup
    //   717: iconst_3
    //   718: iconst_3
    //   719: invokestatic 94	java/lang/Character:valueOf	(C)Ljava/lang/Character;
    //   722: aastore
    //   723: invokevirtual 100	java/lang/reflect/Method:invoke	(Ljava/lang/Object;[Ljava/lang/Object;)Ljava/lang/Object;
    //   726: astore_1
    //   727: aload_1
    //   728: checkcast 80	java/lang/String
    //   731: putstatic 134	uuuuuu/pqpppq:bs0073ssss0073s0073	Ljava/lang/String;
    //   734: getstatic 138	uuuuuu/pqpppq:b00730073ssss0073s0073	Ljava/lang/String;
    //   737: astore_1
    //   738: getstatic 140	uuuuuu/pqpppq:bs0073s0073ss0073s0073	I
    //   741: istore_0
    //   742: iload_0
    //   743: invokestatic 144	uuuuuu/pqpppq:b006B006Bkkk006Bkkkk	()I
    //   746: iload_0
    //   747: iadd
    //   748: imul
    //   749: getstatic 146	uuuuuu/pqpppq:b00730073s0073ss0073s0073	I
    //   752: irem
    //   753: tableswitch	default:+19->772, 0:+29->782
    //   772: bipush 13
    //   774: putstatic 140	uuuuuu/pqpppq:bs0073s0073ss0073s0073	I
    //   777: bipush 10
    //   779: putstatic 146	uuuuuu/pqpppq:b00730073s0073ss0073s0073	I
    //   782: ldc 68
    //   784: ldc -108
    //   786: sipush 172
    //   789: bipush 62
    //   791: iconst_1
    //   792: invokestatic 76	xxxxxx/uxxxxx:bbbb0062b0062b0062b0062	(Ljava/lang/String;CCC)Ljava/lang/String;
    //   795: iconst_4
    //   796: anewarray 78	java/lang/Class
    //   799: dup
    //   800: iconst_0
    //   801: ldc 80
    //   803: aastore
    //   804: dup
    //   805: iconst_1
    //   806: getstatic 86	java/lang/Character:TYPE	Ljava/lang/Class;
    //   809: aastore
    //   810: dup
    //   811: iconst_2
    //   812: getstatic 86	java/lang/Character:TYPE	Ljava/lang/Class;
    //   815: aastore
    //   816: dup
    //   817: iconst_3
    //   818: getstatic 86	java/lang/Character:TYPE	Ljava/lang/Class;
    //   821: aastore
    //   822: invokevirtual 90	java/lang/Class:getMethod	(Ljava/lang/String;[Ljava/lang/Class;)Ljava/lang/reflect/Method;
    //   825: astore_2
    //   826: aload_2
    //   827: aconst_null
    //   828: iconst_4
    //   829: anewarray 4	java/lang/Object
    //   832: dup
    //   833: iconst_0
    //   834: aload_1
    //   835: aastore
    //   836: dup
    //   837: iconst_1
    //   838: sipush 236
    //   841: invokestatic 94	java/lang/Character:valueOf	(C)Ljava/lang/Character;
    //   844: aastore
    //   845: dup
    //   846: iconst_2
    //   847: bipush 44
    //   849: invokestatic 94	java/lang/Character:valueOf	(C)Ljava/lang/Character;
    //   852: aastore
    //   853: dup
    //   854: iconst_3
    //   855: iconst_2
    //   856: invokestatic 94	java/lang/Character:valueOf	(C)Ljava/lang/Character;
    //   859: aastore
    //   860: invokevirtual 100	java/lang/reflect/Method:invoke	(Ljava/lang/Object;[Ljava/lang/Object;)Ljava/lang/Object;
    //   863: astore_1
    //   864: aload_1
    //   865: checkcast 80	java/lang/String
    //   868: putstatic 138	uuuuuu/pqpppq:b00730073ssss0073s0073	Ljava/lang/String;
    //   871: getstatic 150	uuuuuu/pqpppq:bss0073sss0073s0073	Ljava/lang/String;
    //   874: astore_1
    //   875: ldc 68
    //   877: ldc -104
    //   879: sipush 148
    //   882: iconst_2
    //   883: invokestatic 108	xxxxxx/uxxxxx:bb00620062bb0062b0062b0062	(Ljava/lang/String;CC)Ljava/lang/String;
    //   886: iconst_3
    //   887: anewarray 78	java/lang/Class
    //   890: dup
    //   891: iconst_0
    //   892: ldc 80
    //   894: aastore
    //   895: dup
    //   896: iconst_1
    //   897: getstatic 86	java/lang/Character:TYPE	Ljava/lang/Class;
    //   900: aastore
    //   901: dup
    //   902: iconst_2
    //   903: getstatic 86	java/lang/Character:TYPE	Ljava/lang/Class;
    //   906: aastore
    //   907: invokevirtual 90	java/lang/Class:getMethod	(Ljava/lang/String;[Ljava/lang/Class;)Ljava/lang/reflect/Method;
    //   910: astore_2
    //   911: aload_2
    //   912: aconst_null
    //   913: iconst_3
    //   914: anewarray 4	java/lang/Object
    //   917: dup
    //   918: iconst_0
    //   919: aload_1
    //   920: aastore
    //   921: dup
    //   922: iconst_1
    //   923: sipush 238
    //   926: invokestatic 94	java/lang/Character:valueOf	(C)Ljava/lang/Character;
    //   929: aastore
    //   930: dup
    //   931: iconst_2
    //   932: iconst_5
    //   933: invokestatic 94	java/lang/Character:valueOf	(C)Ljava/lang/Character;
    //   936: aastore
    //   937: invokevirtual 100	java/lang/reflect/Method:invoke	(Ljava/lang/Object;[Ljava/lang/Object;)Ljava/lang/Object;
    //   940: astore_1
    //   941: aload_1
    //   942: checkcast 80	java/lang/String
    //   945: putstatic 150	uuuuuu/pqpppq:bss0073sss0073s0073	Ljava/lang/String;
    //   948: getstatic 154	uuuuuu/pqpppq:b0073s0073sss0073s0073	Ljava/lang/String;
    //   951: astore_1
    //   952: invokestatic 157	uuuuuu/pqpppq:bk006Bkkk006Bkkkk	()I
    //   955: istore_0
    //   956: iload_0
    //   957: getstatic 159	uuuuuu/pqpppq:bss00730073ss0073s0073	I
    //   960: iload_0
    //   961: iadd
    //   962: imul
    //   963: getstatic 146	uuuuuu/pqpppq:b00730073s0073ss0073s0073	I
    //   966: irem
    //   967: tableswitch	default:+17->984, 0:+29->996
    //   984: invokestatic 157	uuuuuu/pqpppq:bk006Bkkk006Bkkkk	()I
    //   987: putstatic 140	uuuuuu/pqpppq:bs0073s0073ss0073s0073	I
    //   990: invokestatic 157	uuuuuu/pqpppq:bk006Bkkk006Bkkkk	()I
    //   993: putstatic 159	uuuuuu/pqpppq:bss00730073ss0073s0073	I
    //   996: ldc 68
    //   998: ldc -95
    //   1000: sipush 219
    //   1003: sipush 183
    //   1006: iconst_1
    //   1007: invokestatic 76	xxxxxx/uxxxxx:bbbb0062b0062b0062b0062	(Ljava/lang/String;CCC)Ljava/lang/String;
    //   1010: iconst_4
    //   1011: anewarray 78	java/lang/Class
    //   1014: dup
    //   1015: iconst_0
    //   1016: ldc 80
    //   1018: aastore
    //   1019: dup
    //   1020: iconst_1
    //   1021: getstatic 86	java/lang/Character:TYPE	Ljava/lang/Class;
    //   1024: aastore
    //   1025: dup
    //   1026: iconst_2
    //   1027: getstatic 86	java/lang/Character:TYPE	Ljava/lang/Class;
    //   1030: aastore
    //   1031: dup
    //   1032: iconst_3
    //   1033: getstatic 86	java/lang/Character:TYPE	Ljava/lang/Class;
    //   1036: aastore
    //   1037: invokevirtual 90	java/lang/Class:getMethod	(Ljava/lang/String;[Ljava/lang/Class;)Ljava/lang/reflect/Method;
    //   1040: astore_2
    //   1041: aload_2
    //   1042: aconst_null
    //   1043: iconst_4
    //   1044: anewarray 4	java/lang/Object
    //   1047: dup
    //   1048: iconst_0
    //   1049: aload_1
    //   1050: aastore
    //   1051: dup
    //   1052: iconst_1
    //   1053: bipush 88
    //   1055: invokestatic 94	java/lang/Character:valueOf	(C)Ljava/lang/Character;
    //   1058: aastore
    //   1059: dup
    //   1060: iconst_2
    //   1061: bipush 56
    //   1063: invokestatic 94	java/lang/Character:valueOf	(C)Ljava/lang/Character;
    //   1066: aastore
    //   1067: dup
    //   1068: iconst_3
    //   1069: iconst_3
    //   1070: invokestatic 94	java/lang/Character:valueOf	(C)Ljava/lang/Character;
    //   1073: aastore
    //   1074: invokevirtual 100	java/lang/reflect/Method:invoke	(Ljava/lang/Object;[Ljava/lang/Object;)Ljava/lang/Object;
    //   1077: astore_1
    //   1078: aload_1
    //   1079: checkcast 80	java/lang/String
    //   1082: putstatic 154	uuuuuu/pqpppq:b0073s0073sss0073s0073	Ljava/lang/String;
    //   1085: getstatic 163	uuuuuu/pqpppq:bs00730073sss0073s0073	Ljava/lang/String;
    //   1088: astore_1
    //   1089: ldc 68
    //   1091: ldc -91
    //   1093: bipush 85
    //   1095: iconst_2
    //   1096: invokestatic 108	xxxxxx/uxxxxx:bb00620062bb0062b0062b0062	(Ljava/lang/String;CC)Ljava/lang/String;
    //   1099: iconst_3
    //   1100: anewarray 78	java/lang/Class
    //   1103: dup
    //   1104: iconst_0
    //   1105: ldc 80
    //   1107: aastore
    //   1108: dup
    //   1109: iconst_1
    //   1110: getstatic 86	java/lang/Character:TYPE	Ljava/lang/Class;
    //   1113: aastore
    //   1114: dup
    //   1115: iconst_2
    //   1116: getstatic 86	java/lang/Character:TYPE	Ljava/lang/Class;
    //   1119: aastore
    //   1120: invokevirtual 90	java/lang/Class:getMethod	(Ljava/lang/String;[Ljava/lang/Class;)Ljava/lang/reflect/Method;
    //   1123: astore_2
    //   1124: aload_2
    //   1125: aconst_null
    //   1126: iconst_3
    //   1127: anewarray 4	java/lang/Object
    //   1130: dup
    //   1131: iconst_0
    //   1132: aload_1
    //   1133: aastore
    //   1134: dup
    //   1135: iconst_1
    //   1136: bipush 65
    //   1138: invokestatic 94	java/lang/Character:valueOf	(C)Ljava/lang/Character;
    //   1141: aastore
    //   1142: dup
    //   1143: iconst_2
    //   1144: iconst_0
    //   1145: invokestatic 94	java/lang/Character:valueOf	(C)Ljava/lang/Character;
    //   1148: aastore
    //   1149: invokevirtual 100	java/lang/reflect/Method:invoke	(Ljava/lang/Object;[Ljava/lang/Object;)Ljava/lang/Object;
    //   1152: astore_1
    //   1153: aload_1
    //   1154: checkcast 80	java/lang/String
    //   1157: putstatic 163	uuuuuu/pqpppq:bs00730073sss0073s0073	Ljava/lang/String;
    //   1160: getstatic 167	uuuuuu/pqpppq:b007300730073sss0073s0073	Ljava/lang/String;
    //   1163: astore_1
    //   1164: ldc 68
    //   1166: ldc -87
    //   1168: sipush 196
    //   1171: bipush 41
    //   1173: iconst_0
    //   1174: invokestatic 76	xxxxxx/uxxxxx:bbbb0062b0062b0062b0062	(Ljava/lang/String;CCC)Ljava/lang/String;
    //   1177: iconst_3
    //   1178: anewarray 78	java/lang/Class
    //   1181: dup
    //   1182: iconst_0
    //   1183: ldc 80
    //   1185: aastore
    //   1186: dup
    //   1187: iconst_1
    //   1188: getstatic 86	java/lang/Character:TYPE	Ljava/lang/Class;
    //   1191: aastore
    //   1192: dup
    //   1193: iconst_2
    //   1194: getstatic 86	java/lang/Character:TYPE	Ljava/lang/Class;
    //   1197: aastore
    //   1198: invokevirtual 90	java/lang/Class:getMethod	(Ljava/lang/String;[Ljava/lang/Class;)Ljava/lang/reflect/Method;
    //   1201: astore_2
    //   1202: aload_2
    //   1203: aconst_null
    //   1204: iconst_3
    //   1205: anewarray 4	java/lang/Object
    //   1208: dup
    //   1209: iconst_0
    //   1210: aload_1
    //   1211: aastore
    //   1212: dup
    //   1213: iconst_1
    //   1214: sipush 207
    //   1217: invokestatic 94	java/lang/Character:valueOf	(C)Ljava/lang/Character;
    //   1220: aastore
    //   1221: dup
    //   1222: iconst_2
    //   1223: iconst_1
    //   1224: invokestatic 94	java/lang/Character:valueOf	(C)Ljava/lang/Character;
    //   1227: aastore
    //   1228: invokevirtual 100	java/lang/reflect/Method:invoke	(Ljava/lang/Object;[Ljava/lang/Object;)Ljava/lang/Object;
    //   1231: astore_1
    //   1232: aload_1
    //   1233: checkcast 80	java/lang/String
    //   1236: putstatic 167	uuuuuu/pqpppq:b007300730073sss0073s0073	Ljava/lang/String;
    //   1239: getstatic 171	uuuuuu/pqpppq:b0073ss0073ss0073s0073	Ljava/lang/String;
    //   1242: astore_1
    //   1243: ldc 68
    //   1245: ldc -83
    //   1247: sipush 225
    //   1250: iconst_1
    //   1251: invokestatic 108	xxxxxx/uxxxxx:bb00620062bb0062b0062b0062	(Ljava/lang/String;CC)Ljava/lang/String;
    //   1254: iconst_3
    //   1255: anewarray 78	java/lang/Class
    //   1258: dup
    //   1259: iconst_0
    //   1260: ldc 80
    //   1262: aastore
    //   1263: dup
    //   1264: iconst_1
    //   1265: getstatic 86	java/lang/Character:TYPE	Ljava/lang/Class;
    //   1268: aastore
    //   1269: dup
    //   1270: iconst_2
    //   1271: getstatic 86	java/lang/Character:TYPE	Ljava/lang/Class;
    //   1274: aastore
    //   1275: invokevirtual 90	java/lang/Class:getMethod	(Ljava/lang/String;[Ljava/lang/Class;)Ljava/lang/reflect/Method;
    //   1278: astore_2
    //   1279: aload_2
    //   1280: aconst_null
    //   1281: iconst_3
    //   1282: anewarray 4	java/lang/Object
    //   1285: dup
    //   1286: iconst_0
    //   1287: aload_1
    //   1288: aastore
    //   1289: dup
    //   1290: iconst_1
    //   1291: bipush 103
    //   1293: invokestatic 94	java/lang/Character:valueOf	(C)Ljava/lang/Character;
    //   1296: aastore
    //   1297: dup
    //   1298: iconst_2
    //   1299: iconst_2
    //   1300: invokestatic 94	java/lang/Character:valueOf	(C)Ljava/lang/Character;
    //   1303: aastore
    //   1304: invokevirtual 100	java/lang/reflect/Method:invoke	(Ljava/lang/Object;[Ljava/lang/Object;)Ljava/lang/Object;
    //   1307: astore_1
    //   1308: aload_1
    //   1309: checkcast 80	java/lang/String
    //   1312: putstatic 171	uuuuuu/pqpppq:b0073ss0073ss0073s0073	Ljava/lang/String;
    //   1315: ldc 2
    //   1317: invokevirtual 177	java/lang/Class:getSimpleName	()Ljava/lang/String;
    //   1320: putstatic 179	uuuuuu/pqpppq:bsss0073ss0073s0073	Ljava/lang/String;
    //   1323: return
    //   1324: astore_1
    //   1325: aload_1
    //   1326: invokevirtual 183	java/lang/reflect/InvocationTargetException:getCause	()Ljava/lang/Throwable;
    //   1329: athrow
    //   1330: astore_1
    //   1331: aload_1
    //   1332: invokevirtual 183	java/lang/reflect/InvocationTargetException:getCause	()Ljava/lang/Throwable;
    //   1335: athrow
    //   1336: astore_1
    //   1337: aload_1
    //   1338: invokevirtual 183	java/lang/reflect/InvocationTargetException:getCause	()Ljava/lang/Throwable;
    //   1341: athrow
    //   1342: astore_1
    //   1343: aload_1
    //   1344: invokevirtual 183	java/lang/reflect/InvocationTargetException:getCause	()Ljava/lang/Throwable;
    //   1347: athrow
    //   1348: astore_1
    //   1349: aload_1
    //   1350: invokevirtual 183	java/lang/reflect/InvocationTargetException:getCause	()Ljava/lang/Throwable;
    //   1353: athrow
    //   1354: astore_1
    //   1355: aload_1
    //   1356: invokevirtual 183	java/lang/reflect/InvocationTargetException:getCause	()Ljava/lang/Throwable;
    //   1359: athrow
    //   1360: astore_1
    //   1361: aload_1
    //   1362: invokevirtual 183	java/lang/reflect/InvocationTargetException:getCause	()Ljava/lang/Throwable;
    //   1365: athrow
    //   1366: astore_1
    //   1367: aload_1
    //   1368: invokevirtual 183	java/lang/reflect/InvocationTargetException:getCause	()Ljava/lang/Throwable;
    //   1371: athrow
    //   1372: astore_1
    //   1373: aload_1
    //   1374: invokevirtual 183	java/lang/reflect/InvocationTargetException:getCause	()Ljava/lang/Throwable;
    //   1377: athrow
    //   1378: astore_1
    //   1379: aload_1
    //   1380: invokevirtual 183	java/lang/reflect/InvocationTargetException:getCause	()Ljava/lang/Throwable;
    //   1383: athrow
    //   1384: astore_1
    //   1385: aload_1
    //   1386: invokevirtual 183	java/lang/reflect/InvocationTargetException:getCause	()Ljava/lang/Throwable;
    //   1389: athrow
    //   1390: astore_1
    //   1391: aload_1
    //   1392: invokevirtual 183	java/lang/reflect/InvocationTargetException:getCause	()Ljava/lang/Throwable;
    //   1395: athrow
    //   1396: astore_1
    //   1397: aload_1
    //   1398: invokevirtual 183	java/lang/reflect/InvocationTargetException:getCause	()Ljava/lang/Throwable;
    //   1401: athrow
    //   1402: astore_1
    //   1403: aload_1
    //   1404: invokevirtual 183	java/lang/reflect/InvocationTargetException:getCause	()Ljava/lang/Throwable;
    //   1407: athrow
    //   1408: astore_1
    //   1409: aload_1
    //   1410: invokevirtual 183	java/lang/reflect/InvocationTargetException:getCause	()Ljava/lang/Throwable;
    //   1413: athrow
    // Local variable table:
    //   start	length	slot	name	signature
    //   741	222	0	i	int
    //   3	1306	1	localObject	Object
    //   1324	2	1	localInvocationTargetException1	InvocationTargetException
    //   1330	2	1	localInvocationTargetException2	InvocationTargetException
    //   1336	2	1	localInvocationTargetException3	InvocationTargetException
    //   1342	2	1	localInvocationTargetException4	InvocationTargetException
    //   1348	2	1	localInvocationTargetException5	InvocationTargetException
    //   1354	2	1	localInvocationTargetException6	InvocationTargetException
    //   1360	2	1	localInvocationTargetException7	InvocationTargetException
    //   1366	2	1	localInvocationTargetException8	InvocationTargetException
    //   1372	2	1	localInvocationTargetException9	InvocationTargetException
    //   1378	2	1	localInvocationTargetException10	InvocationTargetException
    //   1384	2	1	localInvocationTargetException11	InvocationTargetException
    //   1390	2	1	localInvocationTargetException12	InvocationTargetException
    //   1396	2	1	localInvocationTargetException13	InvocationTargetException
    //   1402	2	1	localInvocationTargetException14	InvocationTargetException
    //   1408	2	1	localInvocationTargetException15	InvocationTargetException
    //   47	1233	2	localMethod	Method
    // Exception table:
    //   from	to	target	type
    //   48	87	1324	java/lang/reflect/InvocationTargetException
    //   287	316	1330	java/lang/reflect/InvocationTargetException
    //   441	471	1336	java/lang/reflect/InvocationTargetException
    //   1124	1153	1342	java/lang/reflect/InvocationTargetException
    //   1202	1232	1348	java/lang/reflect/InvocationTargetException
    //   1279	1308	1354	java/lang/reflect/InvocationTargetException
    //   523	560	1360	java/lang/reflect/InvocationTargetException
    //   134	163	1366	java/lang/reflect/InvocationTargetException
    //   210	240	1372	java/lang/reflect/InvocationTargetException
    //   1041	1078	1378	java/lang/reflect/InvocationTargetException
    //   911	941	1384	java/lang/reflect/InvocationTargetException
    //   826	864	1390	java/lang/reflect/InvocationTargetException
    //   689	727	1396	java/lang/reflect/InvocationTargetException
    //   365	395	1402	java/lang/reflect/InvocationTargetException
    //   607	637	1408	java/lang/reflect/InvocationTargetException
  }
  
  public pqpppq() {}
  
  /* Error */
  public static String b006B006B006B006Bk006Bkkkk(Context paramContext, String paramString)
  {
    // Byte code:
    //   0: aload_1
    //   1: ifnull +10 -> 11
    //   4: aload_1
    //   5: invokevirtual 195	java/lang/String:isEmpty	()Z
    //   8: ifeq +6 -> 14
    //   11: ldc -59
    //   13: areturn
    //   14: ldc 68
    //   16: ldc -57
    //   18: sipush 164
    //   21: iconst_1
    //   22: invokestatic 108	xxxxxx/uxxxxx:bb00620062bb0062b0062b0062	(Ljava/lang/String;CC)Ljava/lang/String;
    //   25: iconst_3
    //   26: anewarray 78	java/lang/Class
    //   29: dup
    //   30: iconst_0
    //   31: ldc 80
    //   33: aastore
    //   34: dup
    //   35: iconst_1
    //   36: getstatic 86	java/lang/Character:TYPE	Ljava/lang/Class;
    //   39: aastore
    //   40: dup
    //   41: iconst_2
    //   42: getstatic 86	java/lang/Character:TYPE	Ljava/lang/Class;
    //   45: aastore
    //   46: invokevirtual 90	java/lang/Class:getMethod	(Ljava/lang/String;[Ljava/lang/Class;)Ljava/lang/reflect/Method;
    //   49: astore 12
    //   51: aload 12
    //   53: aconst_null
    //   54: iconst_3
    //   55: anewarray 4	java/lang/Object
    //   58: dup
    //   59: iconst_0
    //   60: ldc -55
    //   62: aastore
    //   63: dup
    //   64: iconst_1
    //   65: bipush 122
    //   67: invokestatic 94	java/lang/Character:valueOf	(C)Ljava/lang/Character;
    //   70: aastore
    //   71: dup
    //   72: iconst_2
    //   73: iconst_4
    //   74: invokestatic 94	java/lang/Character:valueOf	(C)Ljava/lang/Character;
    //   77: aastore
    //   78: invokevirtual 100	java/lang/reflect/Method:invoke	(Ljava/lang/Object;[Ljava/lang/Object;)Ljava/lang/Object;
    //   81: astore 12
    //   83: aload 12
    //   85: checkcast 80	java/lang/String
    //   88: astore 12
    //   90: new 203	java/text/SimpleDateFormat
    //   93: dup
    //   94: aload 12
    //   96: invokespecial 206	java/text/SimpleDateFormat:<init>	(Ljava/lang/String;)V
    //   99: astore 12
    //   101: ldc 68
    //   103: ldc -48
    //   105: bipush 95
    //   107: sipush 158
    //   110: iconst_2
    //   111: invokestatic 76	xxxxxx/uxxxxx:bbbb0062b0062b0062b0062	(Ljava/lang/String;CCC)Ljava/lang/String;
    //   114: iconst_3
    //   115: anewarray 78	java/lang/Class
    //   118: dup
    //   119: iconst_0
    //   120: ldc 80
    //   122: aastore
    //   123: dup
    //   124: iconst_1
    //   125: getstatic 86	java/lang/Character:TYPE	Ljava/lang/Class;
    //   128: aastore
    //   129: dup
    //   130: iconst_2
    //   131: getstatic 86	java/lang/Character:TYPE	Ljava/lang/Class;
    //   134: aastore
    //   135: invokevirtual 90	java/lang/Class:getMethod	(Ljava/lang/String;[Ljava/lang/Class;)Ljava/lang/reflect/Method;
    //   138: astore 13
    //   140: aload 13
    //   142: aconst_null
    //   143: iconst_3
    //   144: anewarray 4	java/lang/Object
    //   147: dup
    //   148: iconst_0
    //   149: ldc -46
    //   151: aastore
    //   152: dup
    //   153: iconst_1
    //   154: sipush 142
    //   157: invokestatic 94	java/lang/Character:valueOf	(C)Ljava/lang/Character;
    //   160: aastore
    //   161: dup
    //   162: iconst_2
    //   163: iconst_5
    //   164: invokestatic 94	java/lang/Character:valueOf	(C)Ljava/lang/Character;
    //   167: aastore
    //   168: invokevirtual 100	java/lang/reflect/Method:invoke	(Ljava/lang/Object;[Ljava/lang/Object;)Ljava/lang/Object;
    //   171: astore 13
    //   173: aload 13
    //   175: checkcast 80	java/lang/String
    //   178: astore 13
    //   180: aload 12
    //   182: aload 13
    //   184: invokestatic 216	java/util/TimeZone:getTimeZone	(Ljava/lang/String;)Ljava/util/TimeZone;
    //   187: invokevirtual 222	java/text/DateFormat:setTimeZone	(Ljava/util/TimeZone;)V
    //   190: aload 12
    //   192: aload_1
    //   193: invokevirtual 226	java/text/DateFormat:parse	(Ljava/lang/String;)Ljava/util/Date;
    //   196: astore_1
    //   197: aload_1
    //   198: invokevirtual 232	java/util/Date:getTime	()J
    //   201: lstore 4
    //   203: invokestatic 236	java/util/TimeZone:getDefault	()Ljava/util/TimeZone;
    //   206: invokevirtual 239	java/util/TimeZone:getRawOffset	()I
    //   209: i2l
    //   210: lstore 6
    //   212: invokestatic 236	java/util/TimeZone:getDefault	()Ljava/util/TimeZone;
    //   215: aload_1
    //   216: invokevirtual 243	java/util/TimeZone:inDaylightTime	(Ljava/util/Date;)Z
    //   219: ifeq +492 -> 711
    //   222: invokestatic 157	uuuuuu/pqpppq:bk006Bkkk006Bkkkk	()I
    //   225: getstatic 159	uuuuuu/pqpppq:bss00730073ss0073s0073	I
    //   228: iadd
    //   229: invokestatic 157	uuuuuu/pqpppq:bk006Bkkk006Bkkkk	()I
    //   232: imul
    //   233: getstatic 146	uuuuuu/pqpppq:b00730073s0073ss0073s0073	I
    //   236: irem
    //   237: getstatic 245	uuuuuu/pqpppq:b0073s00730073ss0073s0073	I
    //   240: if_icmpeq +15 -> 255
    //   243: invokestatic 157	uuuuuu/pqpppq:bk006Bkkk006Bkkkk	()I
    //   246: putstatic 140	uuuuuu/pqpppq:bs0073s0073ss0073s0073	I
    //   249: invokestatic 157	uuuuuu/pqpppq:bk006Bkkk006Bkkkk	()I
    //   252: putstatic 245	uuuuuu/pqpppq:b0073s00730073ss0073s0073	I
    //   255: invokestatic 236	java/util/TimeZone:getDefault	()Ljava/util/TimeZone;
    //   258: invokevirtual 248	java/util/TimeZone:getDSTSavings	()I
    //   261: istore_2
    //   262: ldc 68
    //   264: ldc -6
    //   266: bipush 104
    //   268: sipush 196
    //   271: iconst_3
    //   272: invokestatic 76	xxxxxx/uxxxxx:bbbb0062b0062b0062b0062	(Ljava/lang/String;CCC)Ljava/lang/String;
    //   275: iconst_4
    //   276: anewarray 78	java/lang/Class
    //   279: dup
    //   280: iconst_0
    //   281: ldc 80
    //   283: aastore
    //   284: dup
    //   285: iconst_1
    //   286: getstatic 86	java/lang/Character:TYPE	Ljava/lang/Class;
    //   289: aastore
    //   290: dup
    //   291: iconst_2
    //   292: getstatic 86	java/lang/Character:TYPE	Ljava/lang/Class;
    //   295: aastore
    //   296: dup
    //   297: iconst_3
    //   298: getstatic 86	java/lang/Character:TYPE	Ljava/lang/Class;
    //   301: aastore
    //   302: invokevirtual 90	java/lang/Class:getMethod	(Ljava/lang/String;[Ljava/lang/Class;)Ljava/lang/reflect/Method;
    //   305: astore 12
    //   307: aload 12
    //   309: aconst_null
    //   310: iconst_4
    //   311: anewarray 4	java/lang/Object
    //   314: dup
    //   315: iconst_0
    //   316: ldc -4
    //   318: aastore
    //   319: dup
    //   320: iconst_1
    //   321: bipush 28
    //   323: invokestatic 94	java/lang/Character:valueOf	(C)Ljava/lang/Character;
    //   326: aastore
    //   327: dup
    //   328: iconst_2
    //   329: bipush 101
    //   331: invokestatic 94	java/lang/Character:valueOf	(C)Ljava/lang/Character;
    //   334: aastore
    //   335: dup
    //   336: iconst_3
    //   337: iconst_2
    //   338: invokestatic 94	java/lang/Character:valueOf	(C)Ljava/lang/Character;
    //   341: aastore
    //   342: invokevirtual 100	java/lang/reflect/Method:invoke	(Ljava/lang/Object;[Ljava/lang/Object;)Ljava/lang/Object;
    //   345: astore 12
    //   347: aload 12
    //   349: checkcast 80	java/lang/String
    //   352: invokestatic 216	java/util/TimeZone:getTimeZone	(Ljava/lang/String;)Ljava/util/TimeZone;
    //   355: invokevirtual 239	java/util/TimeZone:getRawOffset	()I
    //   358: i2l
    //   359: lstore 8
    //   361: getstatic 140	uuuuuu/pqpppq:bs0073s0073ss0073s0073	I
    //   364: getstatic 159	uuuuuu/pqpppq:bss00730073ss0073s0073	I
    //   367: iadd
    //   368: getstatic 140	uuuuuu/pqpppq:bs0073s0073ss0073s0073	I
    //   371: imul
    //   372: getstatic 146	uuuuuu/pqpppq:b00730073s0073ss0073s0073	I
    //   375: irem
    //   376: getstatic 245	uuuuuu/pqpppq:b0073s00730073ss0073s0073	I
    //   379: if_icmpeq +11 -> 390
    //   382: iconst_4
    //   383: putstatic 140	uuuuuu/pqpppq:bs0073s0073ss0073s0073	I
    //   386: iconst_5
    //   387: putstatic 245	uuuuuu/pqpppq:b0073s00730073ss0073s0073	I
    //   390: ldc 68
    //   392: ldc -2
    //   394: bipush 57
    //   396: iconst_1
    //   397: invokestatic 108	xxxxxx/uxxxxx:bb00620062bb0062b0062b0062	(Ljava/lang/String;CC)Ljava/lang/String;
    //   400: iconst_3
    //   401: anewarray 78	java/lang/Class
    //   404: dup
    //   405: iconst_0
    //   406: ldc 80
    //   408: aastore
    //   409: dup
    //   410: iconst_1
    //   411: getstatic 86	java/lang/Character:TYPE	Ljava/lang/Class;
    //   414: aastore
    //   415: dup
    //   416: iconst_2
    //   417: getstatic 86	java/lang/Character:TYPE	Ljava/lang/Class;
    //   420: aastore
    //   421: invokevirtual 90	java/lang/Class:getMethod	(Ljava/lang/String;[Ljava/lang/Class;)Ljava/lang/reflect/Method;
    //   424: astore 12
    //   426: aload 12
    //   428: aconst_null
    //   429: iconst_3
    //   430: anewarray 4	java/lang/Object
    //   433: dup
    //   434: iconst_0
    //   435: ldc_w 256
    //   438: aastore
    //   439: dup
    //   440: iconst_1
    //   441: sipush 235
    //   444: invokestatic 94	java/lang/Character:valueOf	(C)Ljava/lang/Character;
    //   447: aastore
    //   448: dup
    //   449: iconst_2
    //   450: iconst_5
    //   451: invokestatic 94	java/lang/Character:valueOf	(C)Ljava/lang/Character;
    //   454: aastore
    //   455: invokevirtual 100	java/lang/reflect/Method:invoke	(Ljava/lang/Object;[Ljava/lang/Object;)Ljava/lang/Object;
    //   458: astore 12
    //   460: aload 12
    //   462: checkcast 80	java/lang/String
    //   465: invokestatic 216	java/util/TimeZone:getTimeZone	(Ljava/lang/String;)Ljava/util/TimeZone;
    //   468: aload_1
    //   469: invokevirtual 243	java/util/TimeZone:inDaylightTime	(Ljava/util/Date;)Z
    //   472: ifeq +244 -> 716
    //   475: ldc 68
    //   477: ldc_w 258
    //   480: bipush 127
    //   482: sipush 175
    //   485: iconst_3
    //   486: invokestatic 76	xxxxxx/uxxxxx:bbbb0062b0062b0062b0062	(Ljava/lang/String;CCC)Ljava/lang/String;
    //   489: iconst_3
    //   490: anewarray 78	java/lang/Class
    //   493: dup
    //   494: iconst_0
    //   495: ldc 80
    //   497: aastore
    //   498: dup
    //   499: iconst_1
    //   500: getstatic 86	java/lang/Character:TYPE	Ljava/lang/Class;
    //   503: aastore
    //   504: dup
    //   505: iconst_2
    //   506: getstatic 86	java/lang/Character:TYPE	Ljava/lang/Class;
    //   509: aastore
    //   510: invokevirtual 90	java/lang/Class:getMethod	(Ljava/lang/String;[Ljava/lang/Class;)Ljava/lang/reflect/Method;
    //   513: astore_1
    //   514: aload_1
    //   515: aconst_null
    //   516: iconst_3
    //   517: anewarray 4	java/lang/Object
    //   520: dup
    //   521: iconst_0
    //   522: ldc_w 260
    //   525: aastore
    //   526: dup
    //   527: iconst_1
    //   528: sipush 185
    //   531: invokestatic 94	java/lang/Character:valueOf	(C)Ljava/lang/Character;
    //   534: aastore
    //   535: dup
    //   536: iconst_2
    //   537: iconst_3
    //   538: invokestatic 94	java/lang/Character:valueOf	(C)Ljava/lang/Character;
    //   541: aastore
    //   542: invokevirtual 100	java/lang/reflect/Method:invoke	(Ljava/lang/Object;[Ljava/lang/Object;)Ljava/lang/Object;
    //   545: astore_1
    //   546: aload_1
    //   547: checkcast 80	java/lang/String
    //   550: invokestatic 216	java/util/TimeZone:getTimeZone	(Ljava/lang/String;)Ljava/util/TimeZone;
    //   553: invokevirtual 248	java/util/TimeZone:getDSTSavings	()I
    //   556: istore_3
    //   557: iload_2
    //   558: i2l
    //   559: lstore 10
    //   561: aload_0
    //   562: iload_3
    //   563: i2l
    //   564: lload 8
    //   566: ladd
    //   567: lload 4
    //   569: lload 10
    //   571: lload 6
    //   573: ladd
    //   574: lsub
    //   575: ladd
    //   576: ldc_w 261
    //   579: invokestatic 267	android/text/format/DateUtils:formatDateTime	(Landroid/content/Context;JI)Ljava/lang/String;
    //   582: areturn
    //   583: astore_0
    //   584: aload_0
    //   585: invokevirtual 183	java/lang/reflect/InvocationTargetException:getCause	()Ljava/lang/Throwable;
    //   588: athrow
    //   589: astore_0
    //   590: getstatic 179	uuuuuu/pqpppq:bsss0073ss0073s0073	Ljava/lang/String;
    //   593: astore_1
    //   594: ldc 68
    //   596: ldc_w 269
    //   599: sipush 170
    //   602: bipush 19
    //   604: iconst_1
    //   605: invokestatic 76	xxxxxx/uxxxxx:bbbb0062b0062b0062b0062	(Ljava/lang/String;CCC)Ljava/lang/String;
    //   608: iconst_3
    //   609: anewarray 78	java/lang/Class
    //   612: dup
    //   613: iconst_0
    //   614: ldc 80
    //   616: aastore
    //   617: dup
    //   618: iconst_1
    //   619: getstatic 86	java/lang/Character:TYPE	Ljava/lang/Class;
    //   622: aastore
    //   623: dup
    //   624: iconst_2
    //   625: getstatic 86	java/lang/Character:TYPE	Ljava/lang/Class;
    //   628: aastore
    //   629: invokevirtual 90	java/lang/Class:getMethod	(Ljava/lang/String;[Ljava/lang/Class;)Ljava/lang/reflect/Method;
    //   632: astore 12
    //   634: aload 12
    //   636: aconst_null
    //   637: iconst_3
    //   638: anewarray 4	java/lang/Object
    //   641: dup
    //   642: iconst_0
    //   643: ldc_w 271
    //   646: aastore
    //   647: dup
    //   648: iconst_1
    //   649: sipush 244
    //   652: invokestatic 94	java/lang/Character:valueOf	(C)Ljava/lang/Character;
    //   655: aastore
    //   656: dup
    //   657: iconst_2
    //   658: iconst_2
    //   659: invokestatic 94	java/lang/Character:valueOf	(C)Ljava/lang/Character;
    //   662: aastore
    //   663: invokevirtual 100	java/lang/reflect/Method:invoke	(Ljava/lang/Object;[Ljava/lang/Object;)Ljava/lang/Object;
    //   666: astore 12
    //   668: aload_1
    //   669: aload 12
    //   671: checkcast 80	java/lang/String
    //   674: aload_0
    //   675: invokestatic 277	uuuuuu/rvvvrv:b00710071qq00710071q0071q0071	(Ljava/lang/String;Ljava/lang/String;Ljava/lang/Throwable;)V
    //   678: ldc -59
    //   680: areturn
    //   681: astore_0
    //   682: aload_0
    //   683: invokevirtual 183	java/lang/reflect/InvocationTargetException:getCause	()Ljava/lang/Throwable;
    //   686: athrow
    //   687: astore_0
    //   688: aload_0
    //   689: invokevirtual 183	java/lang/reflect/InvocationTargetException:getCause	()Ljava/lang/Throwable;
    //   692: athrow
    //   693: astore_0
    //   694: aload_0
    //   695: invokevirtual 183	java/lang/reflect/InvocationTargetException:getCause	()Ljava/lang/Throwable;
    //   698: athrow
    //   699: astore_0
    //   700: aload_0
    //   701: invokevirtual 183	java/lang/reflect/InvocationTargetException:getCause	()Ljava/lang/Throwable;
    //   704: athrow
    //   705: astore_0
    //   706: aload_0
    //   707: invokevirtual 183	java/lang/reflect/InvocationTargetException:getCause	()Ljava/lang/Throwable;
    //   710: athrow
    //   711: iconst_0
    //   712: istore_2
    //   713: goto -451 -> 262
    //   716: iconst_0
    //   717: istore_3
    //   718: goto -161 -> 557
    // Local variable table:
    //   start	length	slot	name	signature
    //   0	721	0	paramContext	Context
    //   0	721	1	paramString	String
    //   261	452	2	i	int
    //   556	162	3	j	int
    //   201	367	4	l1	long
    //   210	362	6	l2	long
    //   359	206	8	l3	long
    //   559	11	10	l4	long
    //   49	621	12	localObject1	Object
    //   138	45	13	localObject2	Object
    // Exception table:
    //   from	to	target	type
    //   51	83	583	java/lang/reflect/InvocationTargetException
    //   51	83	589	java/text/ParseException
    //   90	101	589	java/text/ParseException
    //   140	173	589	java/text/ParseException
    //   180	197	589	java/text/ParseException
    //   584	589	589	java/text/ParseException
    //   682	687	589	java/text/ParseException
    //   140	173	681	java/lang/reflect/InvocationTargetException
    //   426	460	687	java/lang/reflect/InvocationTargetException
    //   514	546	693	java/lang/reflect/InvocationTargetException
    //   307	347	699	java/lang/reflect/InvocationTargetException
    //   634	668	705	java/lang/reflect/InvocationTargetException
  }
  
  public static int b006B006B006Bk006B006Bkkkk(String paramString1, String paramString2, String paramString3)
  {
    paramString3 = new SimpleDateFormat(paramString3, Locale.getDefault());
    if ((bs0073s0073ss0073s0073 + bss00730073ss0073s0073) * bs0073s0073ss0073s0073 % b00730073s0073ss0073s0073 != b0073s00730073ss0073s0073)
    {
      int i = bs0073s0073ss0073s0073;
      switch (i * (bss00730073ss0073s0073 + i) % b00730073s0073ss0073s0073)
      {
      default: 
        bs0073s0073ss0073s0073 = bk006Bkkk006Bkkkk();
        b0073s00730073ss0073s0073 = 97;
      }
      bs0073s0073ss0073s0073 = bk006Bkkk006Bkkkk();
      b0073s00730073ss0073s0073 = bk006Bkkk006Bkkkk();
    }
    try
    {
      paramString1 = paramString3.parse(paramString1);
      paramString2 = paramString3.parse(paramString2);
      long l1 = paramString2.getTime();
      long l2 = paramString1.getTime();
      return (int)TimeUnit.MILLISECONDS.toDays(l1 - l2);
    }
    catch (ParseException paramString1)
    {
      paramString2 = bsss0073ss0073s0073;
      paramString3 = ppphhp.class.getMethod(uxxxxx.bbbb0062b0062b0062b0062(":PQRS\r\016\026\027\021\022\032\033\\\026\027\037 \032\033#$e", '!', '6', '\003'), new Class[] { String.class, Character.TYPE, Character.TYPE });
      try
      {
        paramString3 = paramString3.invoke(null, new Object[] { "p\013\022\024\f\nD\030\022A\004\001\013\001\022\b{\016}7\013}y3vr\n\003.oq\002nmu&ylh\"tekc`p`^\031\\XjZg", Character.valueOf('j'), Character.valueOf('\004') });
        rvvvrv.b00710071qq00710071q0071q0071(paramString2, (String)paramString3, paramString1);
        return 0;
      }
      catch (InvocationTargetException paramString1)
      {
        throw paramString1.getCause();
      }
    }
  }
  
  public static String b006B006B006Bkk006Bkkkk(Locale paramLocale, String paramString1, String paramString2)
  {
    try
    {
      paramString2 = new SimpleDateFormat(paramString2);
      int i = bs0073s0073ss0073s0073;
      switch (i * (b006B006Bkkk006Bkkkk() + i) % bkkkkk006Bkkkk())
      {
      default: 
        bs0073s0073ss0073s0073 = bk006Bkkk006Bkkkk();
        b0073s00730073ss0073s0073 = 20;
      }
      paramString1 = paramString2.parse(paramString1);
      return bkkk006Bk006Bkkkk(paramLocale, paramString1);
    }
    catch (ParseException paramLocale)
    {
      paramString1 = bsss0073ss0073s0073;
      if ((bs0073s0073ss0073s0073 + bss00730073ss0073s0073) * bs0073s0073ss0073s0073 % b00730073s0073ss0073s0073 != b0073s00730073ss0073s0073)
      {
        bs0073s0073ss0073s0073 = bk006Bkkk006Bkkkk();
        b0073s00730073ss0073s0073 = 10;
      }
      paramString2 = ppphhp.class.getMethod(uxxxxx.bb00620062bb0062b0062b0062("f|}~9:BC=>FG\tBCKLFGOP\022", '', '\002'), new Class[] { String.class, Character.TYPE, Character.TYPE });
      try
      {
        paramString2 = paramString2.invoke(null, new Object[] { "Hbikca\034oi\031^fhbUg\022]_ROYQ\013LJ[LJ\005HDVF", Character.valueOf(''), Character.valueOf('\004') });
        rvvvrv.b00710071qq00710071q0071q0071(paramString1, (String)paramString2, paramLocale);
        return null;
      }
      catch (InvocationTargetException paramLocale)
      {
        throw paramLocale.getCause();
      }
    }
  }
  
  public static String b006B006Bk006Bk006Bkkkk(Locale paramLocale, Date paramDate)
  {
    int i;
    label8:
    Date localDate;
    if (paramDate == null)
    {
      return null;
      i = 0;
      int j = TimeZone.getDefault().getRawOffset();
      localDate = new Date(paramDate.getTime() + (i + j));
      if (!Locale.GERMAN.getLanguage().equals(paramLocale.getLanguage())) {
        break label268;
      }
      i = bs0073s0073ss0073s0073;
      switch (i * (bss00730073ss0073s0073 + i) % b00730073s0073ss0073s0073)
      {
      default: 
        bs0073s0073ss0073s0073 = bk006Bkkk006Bkkkk();
        b0073s00730073ss0073s0073 = 58;
      }
      paramDate = ppphhp.class.getMethod(uxxxxx.bbbb0062b0062b0062b0062("'=>?@yz\003\004}~\007\bI\003\004\f\r\007\b\020\021R", '1', '', '\002'), new Class[] { String.class, Character.TYPE, Character.TYPE });
    }
    for (;;)
    {
      try
      {
        paramDate = paramDate.invoke(null, new Object[] { "\024\023[yxX#\"! QDkj[\016\r", Character.valueOf(''), Character.valueOf('\005') });
        paramDate = (String)paramDate;
        paramLocale = new SimpleDateFormat(paramDate, paramLocale);
        i = bs0073s0073ss0073s0073;
        switch (i * (bss00730073ss0073s0073 + i) % b00730073s0073ss0073s0073)
        {
        default: 
          bs0073s0073ss0073s0073 = bk006Bkkk006Bkkkk();
          b0073s00730073ss0073s0073 = bk006Bkkk006Bkkkk();
        }
        paramLocale.setTimeZone(TimeZone.getDefault());
        return paramLocale.format(localDate);
      }
      catch (InvocationTargetException paramLocale)
      {
        throw paramLocale.getCause();
      }
      if (!TimeZone.getDefault().inDaylightTime(paramDate)) {
        break;
      }
      i = TimeZone.getDefault().getDSTSavings();
      break label8;
      label268:
      paramDate = ppphhp.class.getMethod(uxxxxx.bbbb0062b0062b0062b0062("Pdcba\031\030\036\035\025\024\032\031X\020\017\025\024\f\013\021\020O", '\022', '', '\001'), new Class[] { String.class, Character.TYPE, Character.TYPE });
      try
      {
        paramDate = paramDate.invoke(null, new Object[] { "^_BxyE\021\022\023\024G<\006\007Y\016\017B\005", Character.valueOf(''), Character.valueOf('\002') });
        paramDate = (String)paramDate;
      }
      catch (InvocationTargetException paramLocale)
      {
        throw paramLocale.getCause();
      }
    }
  }
  
  public static int b006B006Bkkk006Bkkkk()
  {
    return 1;
  }
  
  /* Error */
  public static String b006Bk006B006Bk006Bkkkk(Context paramContext, String paramString)
  {
    // Byte code:
    //   0: aload_1
    //   1: ifnull +10 -> 11
    //   4: aload_1
    //   5: invokevirtual 195	java/lang/String:isEmpty	()Z
    //   8: ifeq +34 -> 42
    //   11: ldc -59
    //   13: areturn
    //   14: iconst_0
    //   15: istore_3
    //   16: iload_2
    //   17: i2l
    //   18: lstore 4
    //   20: aload_0
    //   21: iload_3
    //   22: i2l
    //   23: lload 10
    //   25: ladd
    //   26: lload 6
    //   28: lload 4
    //   30: lload 8
    //   32: ladd
    //   33: lsub
    //   34: ladd
    //   35: ldc_w 342
    //   38: invokestatic 267	android/text/format/DateUtils:formatDateTime	(Landroid/content/Context;JI)Ljava/lang/String;
    //   41: areturn
    //   42: getstatic 140	uuuuuu/pqpppq:bs0073s0073ss0073s0073	I
    //   45: getstatic 159	uuuuuu/pqpppq:bss00730073ss0073s0073	I
    //   48: iadd
    //   49: getstatic 140	uuuuuu/pqpppq:bs0073s0073ss0073s0073	I
    //   52: imul
    //   53: getstatic 146	uuuuuu/pqpppq:b00730073s0073ss0073s0073	I
    //   56: irem
    //   57: getstatic 245	uuuuuu/pqpppq:b0073s00730073ss0073s0073	I
    //   60: if_icmpeq +15 -> 75
    //   63: invokestatic 157	uuuuuu/pqpppq:bk006Bkkk006Bkkkk	()I
    //   66: putstatic 140	uuuuuu/pqpppq:bs0073s0073ss0073s0073	I
    //   69: invokestatic 157	uuuuuu/pqpppq:bk006Bkkk006Bkkkk	()I
    //   72: putstatic 245	uuuuuu/pqpppq:b0073s00730073ss0073s0073	I
    //   75: ldc 68
    //   77: ldc_w 344
    //   80: bipush 32
    //   82: iconst_3
    //   83: invokestatic 108	xxxxxx/uxxxxx:bb00620062bb0062b0062b0062	(Ljava/lang/String;CC)Ljava/lang/String;
    //   86: iconst_3
    //   87: anewarray 78	java/lang/Class
    //   90: dup
    //   91: iconst_0
    //   92: ldc 80
    //   94: aastore
    //   95: dup
    //   96: iconst_1
    //   97: getstatic 86	java/lang/Character:TYPE	Ljava/lang/Class;
    //   100: aastore
    //   101: dup
    //   102: iconst_2
    //   103: getstatic 86	java/lang/Character:TYPE	Ljava/lang/Class;
    //   106: aastore
    //   107: invokevirtual 90	java/lang/Class:getMethod	(Ljava/lang/String;[Ljava/lang/Class;)Ljava/lang/reflect/Method;
    //   110: astore 12
    //   112: aload 12
    //   114: aconst_null
    //   115: iconst_3
    //   116: anewarray 4	java/lang/Object
    //   119: dup
    //   120: iconst_0
    //   121: ldc_w 346
    //   124: aastore
    //   125: dup
    //   126: iconst_1
    //   127: bipush 127
    //   129: invokestatic 94	java/lang/Character:valueOf	(C)Ljava/lang/Character;
    //   132: aastore
    //   133: dup
    //   134: iconst_2
    //   135: iconst_1
    //   136: invokestatic 94	java/lang/Character:valueOf	(C)Ljava/lang/Character;
    //   139: aastore
    //   140: invokevirtual 100	java/lang/reflect/Method:invoke	(Ljava/lang/Object;[Ljava/lang/Object;)Ljava/lang/Object;
    //   143: astore 12
    //   145: aload 12
    //   147: checkcast 80	java/lang/String
    //   150: astore 12
    //   152: new 203	java/text/SimpleDateFormat
    //   155: dup
    //   156: aload 12
    //   158: invokespecial 206	java/text/SimpleDateFormat:<init>	(Ljava/lang/String;)V
    //   161: astore 12
    //   163: ldc 68
    //   165: ldc_w 348
    //   168: sipush 161
    //   171: bipush 28
    //   173: iconst_0
    //   174: invokestatic 76	xxxxxx/uxxxxx:bbbb0062b0062b0062b0062	(Ljava/lang/String;CCC)Ljava/lang/String;
    //   177: iconst_3
    //   178: anewarray 78	java/lang/Class
    //   181: dup
    //   182: iconst_0
    //   183: ldc 80
    //   185: aastore
    //   186: dup
    //   187: iconst_1
    //   188: getstatic 86	java/lang/Character:TYPE	Ljava/lang/Class;
    //   191: aastore
    //   192: dup
    //   193: iconst_2
    //   194: getstatic 86	java/lang/Character:TYPE	Ljava/lang/Class;
    //   197: aastore
    //   198: invokevirtual 90	java/lang/Class:getMethod	(Ljava/lang/String;[Ljava/lang/Class;)Ljava/lang/reflect/Method;
    //   201: astore 13
    //   203: aload 13
    //   205: aconst_null
    //   206: iconst_3
    //   207: anewarray 4	java/lang/Object
    //   210: dup
    //   211: iconst_0
    //   212: ldc_w 350
    //   215: aastore
    //   216: dup
    //   217: iconst_1
    //   218: sipush 241
    //   221: invokestatic 94	java/lang/Character:valueOf	(C)Ljava/lang/Character;
    //   224: aastore
    //   225: dup
    //   226: iconst_2
    //   227: iconst_2
    //   228: invokestatic 94	java/lang/Character:valueOf	(C)Ljava/lang/Character;
    //   231: aastore
    //   232: invokevirtual 100	java/lang/reflect/Method:invoke	(Ljava/lang/Object;[Ljava/lang/Object;)Ljava/lang/Object;
    //   235: astore 13
    //   237: aload 13
    //   239: checkcast 80	java/lang/String
    //   242: astore 13
    //   244: aload 12
    //   246: aload 13
    //   248: invokestatic 216	java/util/TimeZone:getTimeZone	(Ljava/lang/String;)Ljava/util/TimeZone;
    //   251: invokevirtual 222	java/text/DateFormat:setTimeZone	(Ljava/util/TimeZone;)V
    //   254: aload 12
    //   256: aload_1
    //   257: invokevirtual 226	java/text/DateFormat:parse	(Ljava/lang/String;)Ljava/util/Date;
    //   260: astore_1
    //   261: aload_1
    //   262: invokevirtual 232	java/util/Date:getTime	()J
    //   265: lstore 6
    //   267: invokestatic 236	java/util/TimeZone:getDefault	()Ljava/util/TimeZone;
    //   270: invokevirtual 239	java/util/TimeZone:getRawOffset	()I
    //   273: i2l
    //   274: lstore 8
    //   276: invokestatic 236	java/util/TimeZone:getDefault	()Ljava/util/TimeZone;
    //   279: aload_1
    //   280: invokevirtual 243	java/util/TimeZone:inDaylightTime	(Ljava/util/Date;)Z
    //   283: ifeq +464 -> 747
    //   286: invokestatic 236	java/util/TimeZone:getDefault	()Ljava/util/TimeZone;
    //   289: invokevirtual 248	java/util/TimeZone:getDSTSavings	()I
    //   292: istore_2
    //   293: invokestatic 157	uuuuuu/pqpppq:bk006Bkkk006Bkkkk	()I
    //   296: getstatic 159	uuuuuu/pqpppq:bss00730073ss0073s0073	I
    //   299: iadd
    //   300: invokestatic 157	uuuuuu/pqpppq:bk006Bkkk006Bkkkk	()I
    //   303: imul
    //   304: getstatic 146	uuuuuu/pqpppq:b00730073s0073ss0073s0073	I
    //   307: irem
    //   308: getstatic 245	uuuuuu/pqpppq:b0073s00730073ss0073s0073	I
    //   311: if_icmpeq +441 -> 752
    //   314: invokestatic 157	uuuuuu/pqpppq:bk006Bkkk006Bkkkk	()I
    //   317: putstatic 140	uuuuuu/pqpppq:bs0073s0073ss0073s0073	I
    //   320: bipush 89
    //   322: putstatic 245	uuuuuu/pqpppq:b0073s00730073ss0073s0073	I
    //   325: ldc 68
    //   327: ldc_w 352
    //   330: bipush 54
    //   332: iconst_0
    //   333: invokestatic 108	xxxxxx/uxxxxx:bb00620062bb0062b0062b0062	(Ljava/lang/String;CC)Ljava/lang/String;
    //   336: iconst_4
    //   337: anewarray 78	java/lang/Class
    //   340: dup
    //   341: iconst_0
    //   342: ldc 80
    //   344: aastore
    //   345: dup
    //   346: iconst_1
    //   347: getstatic 86	java/lang/Character:TYPE	Ljava/lang/Class;
    //   350: aastore
    //   351: dup
    //   352: iconst_2
    //   353: getstatic 86	java/lang/Character:TYPE	Ljava/lang/Class;
    //   356: aastore
    //   357: dup
    //   358: iconst_3
    //   359: getstatic 86	java/lang/Character:TYPE	Ljava/lang/Class;
    //   362: aastore
    //   363: invokevirtual 90	java/lang/Class:getMethod	(Ljava/lang/String;[Ljava/lang/Class;)Ljava/lang/reflect/Method;
    //   366: astore 12
    //   368: aload 12
    //   370: aconst_null
    //   371: iconst_4
    //   372: anewarray 4	java/lang/Object
    //   375: dup
    //   376: iconst_0
    //   377: ldc_w 354
    //   380: aastore
    //   381: dup
    //   382: iconst_1
    //   383: sipush 246
    //   386: invokestatic 94	java/lang/Character:valueOf	(C)Ljava/lang/Character;
    //   389: aastore
    //   390: dup
    //   391: iconst_2
    //   392: sipush 236
    //   395: invokestatic 94	java/lang/Character:valueOf	(C)Ljava/lang/Character;
    //   398: aastore
    //   399: dup
    //   400: iconst_3
    //   401: iconst_2
    //   402: invokestatic 94	java/lang/Character:valueOf	(C)Ljava/lang/Character;
    //   405: aastore
    //   406: invokevirtual 100	java/lang/reflect/Method:invoke	(Ljava/lang/Object;[Ljava/lang/Object;)Ljava/lang/Object;
    //   409: astore 12
    //   411: aload 12
    //   413: checkcast 80	java/lang/String
    //   416: invokestatic 216	java/util/TimeZone:getTimeZone	(Ljava/lang/String;)Ljava/util/TimeZone;
    //   419: invokevirtual 239	java/util/TimeZone:getRawOffset	()I
    //   422: i2l
    //   423: lstore 10
    //   425: ldc 68
    //   427: ldc_w 356
    //   430: sipush 228
    //   433: iconst_5
    //   434: invokestatic 108	xxxxxx/uxxxxx:bb00620062bb0062b0062b0062	(Ljava/lang/String;CC)Ljava/lang/String;
    //   437: iconst_4
    //   438: anewarray 78	java/lang/Class
    //   441: dup
    //   442: iconst_0
    //   443: ldc 80
    //   445: aastore
    //   446: dup
    //   447: iconst_1
    //   448: getstatic 86	java/lang/Character:TYPE	Ljava/lang/Class;
    //   451: aastore
    //   452: dup
    //   453: iconst_2
    //   454: getstatic 86	java/lang/Character:TYPE	Ljava/lang/Class;
    //   457: aastore
    //   458: dup
    //   459: iconst_3
    //   460: getstatic 86	java/lang/Character:TYPE	Ljava/lang/Class;
    //   463: aastore
    //   464: invokevirtual 90	java/lang/Class:getMethod	(Ljava/lang/String;[Ljava/lang/Class;)Ljava/lang/reflect/Method;
    //   467: astore 12
    //   469: aload 12
    //   471: aconst_null
    //   472: iconst_4
    //   473: anewarray 4	java/lang/Object
    //   476: dup
    //   477: iconst_0
    //   478: ldc_w 358
    //   481: aastore
    //   482: dup
    //   483: iconst_1
    //   484: bipush 101
    //   486: invokestatic 94	java/lang/Character:valueOf	(C)Ljava/lang/Character;
    //   489: aastore
    //   490: dup
    //   491: iconst_2
    //   492: bipush 99
    //   494: invokestatic 94	java/lang/Character:valueOf	(C)Ljava/lang/Character;
    //   497: aastore
    //   498: dup
    //   499: iconst_3
    //   500: iconst_3
    //   501: invokestatic 94	java/lang/Character:valueOf	(C)Ljava/lang/Character;
    //   504: aastore
    //   505: invokevirtual 100	java/lang/reflect/Method:invoke	(Ljava/lang/Object;[Ljava/lang/Object;)Ljava/lang/Object;
    //   508: astore 12
    //   510: aload 12
    //   512: checkcast 80	java/lang/String
    //   515: invokestatic 216	java/util/TimeZone:getTimeZone	(Ljava/lang/String;)Ljava/util/TimeZone;
    //   518: aload_1
    //   519: invokevirtual 243	java/util/TimeZone:inDaylightTime	(Ljava/util/Date;)Z
    //   522: ifeq -508 -> 14
    //   525: ldc 68
    //   527: ldc_w 360
    //   530: sipush 219
    //   533: iconst_3
    //   534: invokestatic 108	xxxxxx/uxxxxx:bb00620062bb0062b0062b0062	(Ljava/lang/String;CC)Ljava/lang/String;
    //   537: iconst_4
    //   538: anewarray 78	java/lang/Class
    //   541: dup
    //   542: iconst_0
    //   543: ldc 80
    //   545: aastore
    //   546: dup
    //   547: iconst_1
    //   548: getstatic 86	java/lang/Character:TYPE	Ljava/lang/Class;
    //   551: aastore
    //   552: dup
    //   553: iconst_2
    //   554: getstatic 86	java/lang/Character:TYPE	Ljava/lang/Class;
    //   557: aastore
    //   558: dup
    //   559: iconst_3
    //   560: getstatic 86	java/lang/Character:TYPE	Ljava/lang/Class;
    //   563: aastore
    //   564: invokevirtual 90	java/lang/Class:getMethod	(Ljava/lang/String;[Ljava/lang/Class;)Ljava/lang/reflect/Method;
    //   567: astore_1
    //   568: aload_1
    //   569: aconst_null
    //   570: iconst_4
    //   571: anewarray 4	java/lang/Object
    //   574: dup
    //   575: iconst_0
    //   576: ldc_w 362
    //   579: aastore
    //   580: dup
    //   581: iconst_1
    //   582: bipush 45
    //   584: invokestatic 94	java/lang/Character:valueOf	(C)Ljava/lang/Character;
    //   587: aastore
    //   588: dup
    //   589: iconst_2
    //   590: sipush 232
    //   593: invokestatic 94	java/lang/Character:valueOf	(C)Ljava/lang/Character;
    //   596: aastore
    //   597: dup
    //   598: iconst_3
    //   599: iconst_0
    //   600: invokestatic 94	java/lang/Character:valueOf	(C)Ljava/lang/Character;
    //   603: aastore
    //   604: invokevirtual 100	java/lang/reflect/Method:invoke	(Ljava/lang/Object;[Ljava/lang/Object;)Ljava/lang/Object;
    //   607: astore_1
    //   608: aload_1
    //   609: checkcast 80	java/lang/String
    //   612: invokestatic 216	java/util/TimeZone:getTimeZone	(Ljava/lang/String;)Ljava/util/TimeZone;
    //   615: invokevirtual 248	java/util/TimeZone:getDSTSavings	()I
    //   618: istore_3
    //   619: goto -603 -> 16
    //   622: astore_0
    //   623: aload_0
    //   624: invokevirtual 183	java/lang/reflect/InvocationTargetException:getCause	()Ljava/lang/Throwable;
    //   627: athrow
    //   628: astore_0
    //   629: aload_0
    //   630: invokevirtual 183	java/lang/reflect/InvocationTargetException:getCause	()Ljava/lang/Throwable;
    //   633: athrow
    //   634: astore_0
    //   635: aload_0
    //   636: invokevirtual 183	java/lang/reflect/InvocationTargetException:getCause	()Ljava/lang/Throwable;
    //   639: athrow
    //   640: astore_0
    //   641: getstatic 179	uuuuuu/pqpppq:bsss0073ss0073s0073	Ljava/lang/String;
    //   644: astore_1
    //   645: ldc 68
    //   647: ldc_w 364
    //   650: sipush 243
    //   653: iconst_5
    //   654: invokestatic 108	xxxxxx/uxxxxx:bb00620062bb0062b0062b0062	(Ljava/lang/String;CC)Ljava/lang/String;
    //   657: iconst_3
    //   658: anewarray 78	java/lang/Class
    //   661: dup
    //   662: iconst_0
    //   663: ldc 80
    //   665: aastore
    //   666: dup
    //   667: iconst_1
    //   668: getstatic 86	java/lang/Character:TYPE	Ljava/lang/Class;
    //   671: aastore
    //   672: dup
    //   673: iconst_2
    //   674: getstatic 86	java/lang/Character:TYPE	Ljava/lang/Class;
    //   677: aastore
    //   678: invokevirtual 90	java/lang/Class:getMethod	(Ljava/lang/String;[Ljava/lang/Class;)Ljava/lang/reflect/Method;
    //   681: astore 12
    //   683: aload 12
    //   685: aconst_null
    //   686: iconst_3
    //   687: anewarray 4	java/lang/Object
    //   690: dup
    //   691: iconst_0
    //   692: ldc_w 366
    //   695: aastore
    //   696: dup
    //   697: iconst_1
    //   698: bipush 114
    //   700: invokestatic 94	java/lang/Character:valueOf	(C)Ljava/lang/Character;
    //   703: aastore
    //   704: dup
    //   705: iconst_2
    //   706: iconst_3
    //   707: invokestatic 94	java/lang/Character:valueOf	(C)Ljava/lang/Character;
    //   710: aastore
    //   711: invokevirtual 100	java/lang/reflect/Method:invoke	(Ljava/lang/Object;[Ljava/lang/Object;)Ljava/lang/Object;
    //   714: astore 12
    //   716: aload_1
    //   717: aload 12
    //   719: checkcast 80	java/lang/String
    //   722: aload_0
    //   723: invokestatic 277	uuuuuu/rvvvrv:b00710071qq00710071q0071q0071	(Ljava/lang/String;Ljava/lang/String;Ljava/lang/Throwable;)V
    //   726: ldc -59
    //   728: areturn
    //   729: astore_0
    //   730: aload_0
    //   731: invokevirtual 183	java/lang/reflect/InvocationTargetException:getCause	()Ljava/lang/Throwable;
    //   734: athrow
    //   735: astore_0
    //   736: aload_0
    //   737: invokevirtual 183	java/lang/reflect/InvocationTargetException:getCause	()Ljava/lang/Throwable;
    //   740: athrow
    //   741: astore_0
    //   742: aload_0
    //   743: invokevirtual 183	java/lang/reflect/InvocationTargetException:getCause	()Ljava/lang/Throwable;
    //   746: athrow
    //   747: iconst_0
    //   748: istore_2
    //   749: goto -424 -> 325
    //   752: goto -427 -> 325
    // Local variable table:
    //   start	length	slot	name	signature
    //   0	755	0	paramContext	Context
    //   0	755	1	paramString	String
    //   16	733	2	i	int
    //   15	604	3	j	int
    //   18	11	4	l1	long
    //   26	1	6	localObject1	Object
    //   265	1	6	l2	long
    //   30	1	8	localObject2	Object
    //   274	1	8	l3	long
    //   23	1	10	localObject3	Object
    //   423	1	10	l4	long
    //   110	608	12	localObject4	Object
    //   201	46	13	localObject5	Object
    // Exception table:
    //   from	to	target	type
    //   368	411	622	java/lang/reflect/InvocationTargetException
    //   568	608	628	java/lang/reflect/InvocationTargetException
    //   112	145	634	java/lang/reflect/InvocationTargetException
    //   112	145	640	java/text/ParseException
    //   152	163	640	java/text/ParseException
    //   203	237	640	java/text/ParseException
    //   244	261	640	java/text/ParseException
    //   635	640	640	java/text/ParseException
    //   736	741	640	java/text/ParseException
    //   469	510	729	java/lang/reflect/InvocationTargetException
    //   203	237	735	java/lang/reflect/InvocationTargetException
    //   683	716	741	java/lang/reflect/InvocationTargetException
  }
  
  public static long b006Bk006Bk006B006Bkkkk(String paramString1, String paramString2)
  {
    paramString2 = new SimpleDateFormat(paramString2, Locale.getDefault());
    long l;
    try
    {
      paramString1 = paramString2.parse(paramString1);
      paramString2 = new GregorianCalendar();
      paramString2.setTime(paramString1);
      l = paramString2.getTimeInMillis() - Calendar.getInstance().getTimeInMillis();
      if (l > 0L) {
        break label212;
      }
    }
    catch (ParseException paramString1)
    {
      for (;;)
      {
        paramString2 = bsss0073ss0073s0073;
        Object localObject = ppphhp.class.getMethod(uxxxxx.bb00620062bb0062b0062b0062("x\r\f\013\nA@FE=<BA\00187=<4398w", 't', '\004'), new Class[] { String.class, Character.TYPE, Character.TYPE });
        try
        {
          localObject = ((Method)localObject).invoke(null, new Object[] { "y\024\033\035\025\023M!\033J\r\n\024\n\033\021\005\027\007@\024\007\003<{\023\f7xz\t\013wv~/q\003~}ow|'jfxh\"bnc\036^\034aommi[\025[\\hV^\017RN`P", Character.valueOf('&'), Character.valueOf('\004') });
          rvvvrv.b00710071qq00710071q0071q0071(paramString2, (String)localObject, paramString1);
          int i = bs0073s0073ss0073s0073;
          int j = bss00730073ss0073s0073;
          if ((bs0073s0073ss0073s0073 + bss00730073ss0073s0073) * bs0073s0073ss0073s0073 % b00730073s0073ss0073s0073 == b0073s00730073ss0073s0073) {
            break label177;
          }
          bs0073s0073ss0073s0073 = 51;
          b0073s00730073ss0073s0073 = 76;
          label177:
          if ((i + j) * bs0073s0073ss0073s0073 % b00730073s0073ss0073s0073 == b006Bkkkk006Bkkkk()) {
            continue;
          }
          bs0073s0073ss0073s0073 = 89;
          b0073s00730073ss0073s0073 = 72;
          return 0L;
        }
        catch (InvocationTargetException paramString1)
        {
          throw paramString1.getCause();
        }
      }
    }
    return 0L;
    label212:
    return TimeUnit.MILLISECONDS.toDays(l);
  }
  
  public static String b006Bk006Bkk006Bkkkk(Date paramDate, String paramString)
  {
    paramDate = new SimpleDateFormat(paramString, Locale.ENGLISH).format(paramDate);
    if ((bk006Bkkk006Bkkkk() + bss00730073ss0073s0073) * bk006Bkkk006Bkkkk() % b00730073s0073ss0073s0073 != b0073s00730073ss0073s0073)
    {
      int i = bs0073s0073ss0073s0073;
      switch (i * (bss00730073ss0073s0073 + i) % b00730073s0073ss0073s0073)
      {
      default: 
        bs0073s0073ss0073s0073 = bk006Bkkk006Bkkkk();
        b0073s00730073ss0073s0073 = bk006Bkkk006Bkkkk();
      }
      bs0073s0073ss0073s0073 = bk006Bkkk006Bkkkk();
      b0073s00730073ss0073s0073 = bk006Bkkk006Bkkkk();
    }
    return paramDate;
  }
  
  /* Error */
  public static String b006Bkk006Bk006Bkkkk(Locale paramLocale, String paramString1, String paramString2)
  {
    // Byte code:
    //   0: new 203	java/text/SimpleDateFormat
    //   3: dup
    //   4: aload_2
    //   5: invokespecial 206	java/text/SimpleDateFormat:<init>	(Ljava/lang/String;)V
    //   8: aload_1
    //   9: invokevirtual 226	java/text/DateFormat:parse	(Ljava/lang/String;)Ljava/util/Date;
    //   12: astore_1
    //   13: aload_0
    //   14: invokevirtual 324	java/util/Locale:getLanguage	()Ljava/lang/String;
    //   17: getstatic 321	java/util/Locale:GERMAN	Ljava/util/Locale;
    //   20: invokevirtual 324	java/util/Locale:getLanguage	()Ljava/lang/String;
    //   23: invokevirtual 328	java/lang/String:equals	(Ljava/lang/Object;)Z
    //   26: ifeq +217 -> 243
    //   29: ldc 68
    //   31: ldc_w 399
    //   34: sipush 230
    //   37: iconst_3
    //   38: invokestatic 108	xxxxxx/uxxxxx:bb00620062bb0062b0062b0062	(Ljava/lang/String;CC)Ljava/lang/String;
    //   41: iconst_3
    //   42: anewarray 78	java/lang/Class
    //   45: dup
    //   46: iconst_0
    //   47: ldc 80
    //   49: aastore
    //   50: dup
    //   51: iconst_1
    //   52: getstatic 86	java/lang/Character:TYPE	Ljava/lang/Class;
    //   55: aastore
    //   56: dup
    //   57: iconst_2
    //   58: getstatic 86	java/lang/Character:TYPE	Ljava/lang/Class;
    //   61: aastore
    //   62: invokevirtual 90	java/lang/Class:getMethod	(Ljava/lang/String;[Ljava/lang/Class;)Ljava/lang/reflect/Method;
    //   65: astore_0
    //   66: aload_0
    //   67: aconst_null
    //   68: iconst_3
    //   69: anewarray 4	java/lang/Object
    //   72: dup
    //   73: iconst_0
    //   74: ldc_w 401
    //   77: aastore
    //   78: dup
    //   79: iconst_1
    //   80: sipush 201
    //   83: invokestatic 94	java/lang/Character:valueOf	(C)Ljava/lang/Character;
    //   86: aastore
    //   87: dup
    //   88: iconst_2
    //   89: iconst_2
    //   90: invokestatic 94	java/lang/Character:valueOf	(C)Ljava/lang/Character;
    //   93: aastore
    //   94: invokevirtual 100	java/lang/reflect/Method:invoke	(Ljava/lang/Object;[Ljava/lang/Object;)Ljava/lang/Object;
    //   97: astore_0
    //   98: new 203	java/text/SimpleDateFormat
    //   101: dup
    //   102: aload_0
    //   103: checkcast 80	java/lang/String
    //   106: invokespecial 206	java/text/SimpleDateFormat:<init>	(Ljava/lang/String;)V
    //   109: astore_0
    //   110: aload_0
    //   111: aload_1
    //   112: invokevirtual 336	java/text/DateFormat:format	(Ljava/util/Date;)Ljava/lang/String;
    //   115: astore_0
    //   116: aload_0
    //   117: areturn
    //   118: astore_0
    //   119: getstatic 179	uuuuuu/pqpppq:bsss0073ss0073s0073	Ljava/lang/String;
    //   122: astore_1
    //   123: ldc 68
    //   125: ldc_w 403
    //   128: bipush 45
    //   130: iconst_5
    //   131: invokestatic 108	xxxxxx/uxxxxx:bb00620062bb0062b0062b0062	(Ljava/lang/String;CC)Ljava/lang/String;
    //   134: iconst_3
    //   135: anewarray 78	java/lang/Class
    //   138: dup
    //   139: iconst_0
    //   140: ldc 80
    //   142: aastore
    //   143: dup
    //   144: iconst_1
    //   145: getstatic 86	java/lang/Character:TYPE	Ljava/lang/Class;
    //   148: aastore
    //   149: dup
    //   150: iconst_2
    //   151: getstatic 86	java/lang/Character:TYPE	Ljava/lang/Class;
    //   154: aastore
    //   155: invokevirtual 90	java/lang/Class:getMethod	(Ljava/lang/String;[Ljava/lang/Class;)Ljava/lang/reflect/Method;
    //   158: astore_2
    //   159: aload_2
    //   160: aconst_null
    //   161: iconst_3
    //   162: anewarray 4	java/lang/Object
    //   165: dup
    //   166: iconst_0
    //   167: ldc_w 405
    //   170: aastore
    //   171: dup
    //   172: iconst_1
    //   173: sipush 250
    //   176: invokestatic 94	java/lang/Character:valueOf	(C)Ljava/lang/Character;
    //   179: aastore
    //   180: dup
    //   181: iconst_2
    //   182: iconst_4
    //   183: invokestatic 94	java/lang/Character:valueOf	(C)Ljava/lang/Character;
    //   186: aastore
    //   187: invokevirtual 100	java/lang/reflect/Method:invoke	(Ljava/lang/Object;[Ljava/lang/Object;)Ljava/lang/Object;
    //   190: astore_2
    //   191: aload_1
    //   192: aload_2
    //   193: checkcast 80	java/lang/String
    //   196: aload_0
    //   197: invokestatic 277	uuuuuu/rvvvrv:b00710071qq00710071q0071q0071	(Ljava/lang/String;Ljava/lang/String;Ljava/lang/Throwable;)V
    //   200: aconst_null
    //   201: astore_0
    //   202: getstatic 140	uuuuuu/pqpppq:bs0073s0073ss0073s0073	I
    //   205: getstatic 159	uuuuuu/pqpppq:bss00730073ss0073s0073	I
    //   208: iadd
    //   209: getstatic 140	uuuuuu/pqpppq:bs0073s0073ss0073s0073	I
    //   212: imul
    //   213: getstatic 146	uuuuuu/pqpppq:b00730073s0073ss0073s0073	I
    //   216: irem
    //   217: getstatic 245	uuuuuu/pqpppq:b0073s00730073ss0073s0073	I
    //   220: if_icmpeq -104 -> 116
    //   223: invokestatic 157	uuuuuu/pqpppq:bk006Bkkk006Bkkkk	()I
    //   226: putstatic 140	uuuuuu/pqpppq:bs0073s0073ss0073s0073	I
    //   229: invokestatic 157	uuuuuu/pqpppq:bk006Bkkk006Bkkkk	()I
    //   232: putstatic 245	uuuuuu/pqpppq:b0073s00730073ss0073s0073	I
    //   235: aconst_null
    //   236: areturn
    //   237: astore_0
    //   238: aload_0
    //   239: invokevirtual 183	java/lang/reflect/InvocationTargetException:getCause	()Ljava/lang/Throwable;
    //   242: athrow
    //   243: ldc 68
    //   245: ldc_w 407
    //   248: bipush 6
    //   250: iconst_1
    //   251: invokestatic 108	xxxxxx/uxxxxx:bb00620062bb0062b0062b0062	(Ljava/lang/String;CC)Ljava/lang/String;
    //   254: iconst_3
    //   255: anewarray 78	java/lang/Class
    //   258: dup
    //   259: iconst_0
    //   260: ldc 80
    //   262: aastore
    //   263: dup
    //   264: iconst_1
    //   265: getstatic 86	java/lang/Character:TYPE	Ljava/lang/Class;
    //   268: aastore
    //   269: dup
    //   270: iconst_2
    //   271: getstatic 86	java/lang/Character:TYPE	Ljava/lang/Class;
    //   274: aastore
    //   275: invokevirtual 90	java/lang/Class:getMethod	(Ljava/lang/String;[Ljava/lang/Class;)Ljava/lang/reflect/Method;
    //   278: astore_0
    //   279: aload_0
    //   280: aconst_null
    //   281: iconst_3
    //   282: anewarray 4	java/lang/Object
    //   285: dup
    //   286: iconst_0
    //   287: ldc_w 409
    //   290: aastore
    //   291: dup
    //   292: iconst_1
    //   293: bipush 120
    //   295: invokestatic 94	java/lang/Character:valueOf	(C)Ljava/lang/Character;
    //   298: aastore
    //   299: dup
    //   300: iconst_2
    //   301: iconst_1
    //   302: invokestatic 94	java/lang/Character:valueOf	(C)Ljava/lang/Character;
    //   305: aastore
    //   306: invokevirtual 100	java/lang/reflect/Method:invoke	(Ljava/lang/Object;[Ljava/lang/Object;)Ljava/lang/Object;
    //   309: astore_0
    //   310: aload_0
    //   311: checkcast 80	java/lang/String
    //   314: astore_0
    //   315: getstatic 412	java/util/Locale:US	Ljava/util/Locale;
    //   318: astore_2
    //   319: getstatic 140	uuuuuu/pqpppq:bs0073s0073ss0073s0073	I
    //   322: istore_3
    //   323: iload_3
    //   324: getstatic 159	uuuuuu/pqpppq:bss00730073ss0073s0073	I
    //   327: iload_3
    //   328: iadd
    //   329: imul
    //   330: getstatic 146	uuuuuu/pqpppq:b00730073s0073ss0073s0073	I
    //   333: irem
    //   334: tableswitch	default:+18->352, 0:+28->362
    //   352: bipush 85
    //   354: putstatic 140	uuuuuu/pqpppq:bs0073s0073ss0073s0073	I
    //   357: bipush 66
    //   359: putstatic 245	uuuuuu/pqpppq:b0073s00730073ss0073s0073	I
    //   362: new 203	java/text/SimpleDateFormat
    //   365: dup
    //   366: aload_0
    //   367: aload_2
    //   368: invokespecial 287	java/text/SimpleDateFormat:<init>	(Ljava/lang/String;Ljava/util/Locale;)V
    //   371: astore_0
    //   372: goto -262 -> 110
    //   375: astore_0
    //   376: aload_0
    //   377: invokevirtual 183	java/lang/reflect/InvocationTargetException:getCause	()Ljava/lang/Throwable;
    //   380: athrow
    //   381: astore_0
    //   382: aload_0
    //   383: invokevirtual 183	java/lang/reflect/InvocationTargetException:getCause	()Ljava/lang/Throwable;
    //   386: athrow
    // Local variable table:
    //   start	length	slot	name	signature
    //   0	387	0	paramLocale	Locale
    //   0	387	1	paramString1	String
    //   0	387	2	paramString2	String
    //   322	8	3	i	int
    // Exception table:
    //   from	to	target	type
    //   0	13	118	java/text/ParseException
    //   159	191	237	java/lang/reflect/InvocationTargetException
    //   279	310	375	java/lang/reflect/InvocationTargetException
    //   66	98	381	java/lang/reflect/InvocationTargetException
  }
  
  public static String b006Bkkk006B006Bkkkk(Locale paramLocale, Date paramDate)
  {
    if ((bk006Bkkk006Bkkkk() + bss00730073ss0073s0073) * bk006Bkkk006Bkkkk() % b00730073s0073ss0073s0073 != b006Bkkkk006Bkkkk())
    {
      bs0073s0073ss0073s0073 = 59;
      b0073s00730073ss0073s0073 = 20;
    }
    Object localObject = ppphhp.class.getMethod(uxxxxx.bbbb0062b0062b0062b0062("dxwvu-,21)(.-l$#)( \037%$c", '', '', '\001'), new Class[] { String.class, Character.TYPE, Character.TYPE });
    try
    {
      localObject = ((Method)localObject).invoke(null, new Object[] { "\035\034\033lEDCB", Character.valueOf('\030'), Character.valueOf('\004') });
      paramLocale = new SimpleDateFormat((String)localObject, paramLocale);
      if ((bs0073s0073ss0073s0073 + bss00730073ss0073s0073) * bs0073s0073ss0073s0073 % b00730073s0073ss0073s0073 != b0073s00730073ss0073s0073)
      {
        bs0073s0073ss0073s0073 = 3;
        b0073s00730073ss0073s0073 = bk006Bkkk006Bkkkk();
      }
      return paramLocale.format(paramDate);
    }
    catch (InvocationTargetException paramLocale)
    {
      throw paramLocale.getCause();
    }
  }
  
  public static int b006Bkkkk006Bkkkk()
  {
    return 0;
  }
  
  public static String bk006B006B006Bk006Bkkkk(Context paramContext, String paramString)
  {
    Object localObject = ppphhp.class.getMethod(uxxxxx.bb00620062bb0062b0062b0062("K_\027\026\034\033ZY\021\020\026\025\r\f\022\021P\b\007\r\f\004\003\t\bG", '', '\004'), new Class[] { String.class, Character.TYPE, Character.TYPE, Character.TYPE });
    for (;;)
    {
      try
      {
        localObject = ((Method)localObject).invoke(null, new Object[] { "\026\025\024\023EdcBxw", Character.valueOf(''), Character.valueOf(';'), Character.valueOf('\001') });
        localObject = (String)localObject;
        paramString = new SimpleDateFormat((String)localObject).parse(paramString);
        long l1 = paramString.getTime();
        long l2 = TimeZone.getDefault().getRawOffset();
        if (TimeZone.getDefault().inDaylightTime(paramString))
        {
          i = TimeZone.getDefault().getDSTSavings();
          if ((bs0073s0073ss0073s0073 + bss00730073ss0073s0073) * bs0073s0073ss0073s0073 % bkkkkk006Bkkkk() != b0073s00730073ss0073s0073)
          {
            bs0073s0073ss0073s0073 = bk006Bkkk006Bkkkk();
            b0073s00730073ss0073s0073 = bk006Bkkk006Bkkkk();
            if ((bs0073s0073ss0073s0073 + bss00730073ss0073s0073) * bs0073s0073ss0073s0073 % b00730073s0073ss0073s0073 != b0073s00730073ss0073s0073)
            {
              bs0073s0073ss0073s0073 = 93;
              b0073s00730073ss0073s0073 = bk006Bkkk006Bkkkk();
            }
          }
          return DateUtils.formatDateTime(paramContext, i + (l1 + l2), 131096);
        }
      }
      catch (ParseException paramContext)
      {
        paramString = bsss0073ss0073s0073;
        localObject = ppphhp.class.getMethod(uxxxxx.bb00620062bb0062b0062b0062(".DEFG\001\002\n\013\005\006\016\017P\n\013\023\024\016\017\027\030Y", '', '\002'), new Class[] { String.class, Character.TYPE, Character.TYPE });
        try
        {
          localObject = ((Method)localObject).invoke(null, new Object[] { "\0324;=53mA;j08:4'9c'#5%^ \036/ \036X'%U*'\030$P\034\036\021\016 \024\031\027", Character.valueOf(''), Character.valueOf('\004') });
          rvvvrv.b00710071qq00710071q0071q0071(paramString, (String)localObject, paramContext);
          return "";
        }
        catch (InvocationTargetException paramContext)
        {
          throw paramContext.getCause();
        }
      }
      catch (InvocationTargetException paramContext)
      {
        throw paramContext.getCause();
      }
      int i = 0;
    }
  }
  
  @NonNull
  private String bk006B006Bkk006Bkkkk(Date paramDate, String paramString, Locale paramLocale)
  {
    int i = bs0073s0073ss0073s0073;
    switch (i * (bss00730073ss0073s0073 + i) % b00730073s0073ss0073s0073)
    {
    default: 
      bs0073s0073ss0073s0073 = 22;
      b0073s00730073ss0073s0073 = 49;
    }
    if (paramDate == null) {
      return "";
    }
    paramString = new SimpleDateFormat(paramString, paramLocale);
    if ((bs0073s0073ss0073s0073 + bss00730073ss0073s0073) * bs0073s0073ss0073s0073 % b00730073s0073ss0073s0073 != b0073s00730073ss0073s0073)
    {
      bs0073s0073ss0073s0073 = bk006Bkkk006Bkkkk();
      b0073s00730073ss0073s0073 = bk006Bkkk006Bkkkk();
    }
    return paramString.format(paramDate);
  }
  
  public static String bk006Bk006Bk006Bkkkk(Locale paramLocale, String paramString1, String paramString2)
  {
    if (paramString1 != null)
    {
      if (paramString1.isEmpty()) {
        return null;
      }
      for (int i = 0;; i = TimeZone.getDefault().getDSTSavings())
      {
        for (;;)
        {
          try
          {
            int j = TimeZone.getDefault().getRawOffset();
            paramString1 = new Date(paramString1.getTime() + (i + j));
            if (paramLocale.getLanguage().equals(Locale.GERMAN.getLanguage())) {
              paramLocale = ppphhp.class.getMethod(uxxxxx.bb00620062bb0062b0062b0062("t\013\f\r\016GHPQKLTU\027PQYZTU]^ ", '', '\002'), new Class[] { String.class, Character.TYPE, Character.TYPE });
            }
          }
          catch (ParseException paramLocale)
          {
            paramString1 = bsss0073ss0073s0073;
            paramString2 = ppphhp.class.getMethod(uxxxxx.bb00620062bb0062b0062b0062("\005\033\034\035\036WX`a[\\de'`aijdemn0", '\021', '\001'), new Class[] { String.class, Character.TYPE, Character.TYPE });
            try
            {
              paramString2 = paramString2.invoke(null, new Object[] { "5QZ^XX\025jf\030_imi^r\037Lpedpj&ii|oo,qo\004u1\007|\002z", Character.valueOf(''), Character.valueOf('\002') });
              rvvvrv.b00710071qq00710071q0071q0071(paramString1, (String)paramString2, paramLocale);
              return null;
            }
            catch (InvocationTargetException paramLocale)
            {
              throw paramLocale.getCause();
            }
            paramLocale = ppphhp.class.getMethod(uxxxxx.bbbb0062b0062b0062b0062("o\006\007\b\tBCKLFGOP\022KLTUOPXY\033", '', '7', '\003'), new Class[] { String.class, Character.TYPE, Character.TYPE });
            try
            {
              paramLocale = paramLocale.invoke(null, new Object[] { "$%\b>?\013VWXY\r\002+,\037ST", Character.valueOf('G'), Character.valueOf('\000') });
              paramLocale = new SimpleDateFormat((String)paramLocale);
            }
            catch (InvocationTargetException paramLocale)
            {
              throw paramLocale.getCause();
            }
          }
          try
          {
            paramLocale = paramLocale.invoke(null, new Object[] { "cd/OP2~\001\0025*STG{|", Character.valueOf('~'), Character.valueOf('\002') });
            paramLocale = new SimpleDateFormat((String)paramLocale);
            if ((bs0073s0073ss0073s0073 + bss00730073ss0073s0073) * bs0073s0073ss0073s0073 % b00730073s0073ss0073s0073 != b0073s00730073ss0073s0073)
            {
              bs0073s0073ss0073s0073 = bk006Bkkk006Bkkkk();
              b0073s00730073ss0073s0073 = bk006Bkkk006Bkkkk();
            }
            return paramLocale.format(paramString1);
          }
          catch (InvocationTargetException paramLocale)
          {
            throw paramLocale.getCause();
          }
        }
        paramString2 = new SimpleDateFormat(paramString2);
        if ((bs0073s0073ss0073s0073 + bss00730073ss0073s0073) * bs0073s0073ss0073s0073 % b00730073s0073ss0073s0073 != b0073s00730073ss0073s0073)
        {
          bs0073s0073ss0073s0073 = bk006Bkkk006Bkkkk();
          b0073s00730073ss0073s0073 = bk006Bkkk006Bkkkk();
        }
        paramString1 = paramString2.parse(paramString1);
        if (!TimeZone.getDefault().inDaylightTime(paramString1)) {
          break;
        }
      }
    }
    return null;
  }
  
  public static String bk006Bkk006B006Bkkkk(Date paramDate, Locale paramLocale)
  {
    paramLocale = DateFormat.getDateInstance(2, paramLocale);
    if ((bs0073s0073ss0073s0073 + bss00730073ss0073s0073) * bs0073s0073ss0073s0073 % b00730073s0073ss0073s0073 != b0073s00730073ss0073s0073)
    {
      bs0073s0073ss0073s0073 = 21;
      b0073s00730073ss0073s0073 = 11;
      if ((bs0073s0073ss0073s0073 + bss00730073ss0073s0073) * bs0073s0073ss0073s0073 % b00730073s0073ss0073s0073 != b0073s00730073ss0073s0073)
      {
        bs0073s0073ss0073s0073 = bk006Bkkk006Bkkkk();
        b0073s00730073ss0073s0073 = bk006Bkkk006Bkkkk();
      }
    }
    return paramLocale.format(paramDate);
  }
  
  public static int bk006Bkkk006Bkkkk()
  {
    return 62;
  }
  
  /* Error */
  public static String bkk006B006Bk006Bkkkk(Context paramContext, String paramString)
  {
    // Byte code:
    //   0: aload_1
    //   1: ifnull +10 -> 11
    //   4: aload_1
    //   5: invokevirtual 195	java/lang/String:isEmpty	()Z
    //   8: ifeq +6 -> 14
    //   11: ldc -59
    //   13: areturn
    //   14: ldc 68
    //   16: ldc_w 453
    //   19: sipush 190
    //   22: iconst_2
    //   23: invokestatic 108	xxxxxx/uxxxxx:bb00620062bb0062b0062b0062	(Ljava/lang/String;CC)Ljava/lang/String;
    //   26: iconst_3
    //   27: anewarray 78	java/lang/Class
    //   30: dup
    //   31: iconst_0
    //   32: ldc 80
    //   34: aastore
    //   35: dup
    //   36: iconst_1
    //   37: getstatic 86	java/lang/Character:TYPE	Ljava/lang/Class;
    //   40: aastore
    //   41: dup
    //   42: iconst_2
    //   43: getstatic 86	java/lang/Character:TYPE	Ljava/lang/Class;
    //   46: aastore
    //   47: invokevirtual 90	java/lang/Class:getMethod	(Ljava/lang/String;[Ljava/lang/Class;)Ljava/lang/reflect/Method;
    //   50: astore 7
    //   52: aload 7
    //   54: aconst_null
    //   55: iconst_3
    //   56: anewarray 4	java/lang/Object
    //   59: dup
    //   60: iconst_0
    //   61: ldc_w 455
    //   64: aastore
    //   65: dup
    //   66: iconst_1
    //   67: sipush 255
    //   70: invokestatic 94	java/lang/Character:valueOf	(C)Ljava/lang/Character;
    //   73: aastore
    //   74: dup
    //   75: iconst_2
    //   76: iconst_3
    //   77: invokestatic 94	java/lang/Character:valueOf	(C)Ljava/lang/Character;
    //   80: aastore
    //   81: invokevirtual 100	java/lang/reflect/Method:invoke	(Ljava/lang/Object;[Ljava/lang/Object;)Ljava/lang/Object;
    //   84: astore 7
    //   86: aload 7
    //   88: checkcast 80	java/lang/String
    //   91: astore 7
    //   93: new 203	java/text/SimpleDateFormat
    //   96: dup
    //   97: aload 7
    //   99: invokespecial 206	java/text/SimpleDateFormat:<init>	(Ljava/lang/String;)V
    //   102: aload_1
    //   103: invokevirtual 226	java/text/DateFormat:parse	(Ljava/lang/String;)Ljava/util/Date;
    //   106: astore_1
    //   107: aload_1
    //   108: invokevirtual 232	java/util/Date:getTime	()J
    //   111: lstore_3
    //   112: invokestatic 236	java/util/TimeZone:getDefault	()Ljava/util/TimeZone;
    //   115: invokevirtual 239	java/util/TimeZone:getRawOffset	()I
    //   118: i2l
    //   119: lstore 5
    //   121: invokestatic 236	java/util/TimeZone:getDefault	()Ljava/util/TimeZone;
    //   124: aload_1
    //   125: invokevirtual 243	java/util/TimeZone:inDaylightTime	(Ljava/util/Date;)Z
    //   128: ifeq +92 -> 220
    //   131: invokestatic 236	java/util/TimeZone:getDefault	()Ljava/util/TimeZone;
    //   134: astore_1
    //   135: getstatic 140	uuuuuu/pqpppq:bs0073s0073ss0073s0073	I
    //   138: getstatic 159	uuuuuu/pqpppq:bss00730073ss0073s0073	I
    //   141: iadd
    //   142: getstatic 140	uuuuuu/pqpppq:bs0073s0073ss0073s0073	I
    //   145: imul
    //   146: getstatic 146	uuuuuu/pqpppq:b00730073s0073ss0073s0073	I
    //   149: irem
    //   150: getstatic 245	uuuuuu/pqpppq:b0073s00730073ss0073s0073	I
    //   153: if_icmpeq +47 -> 200
    //   156: invokestatic 157	uuuuuu/pqpppq:bk006Bkkk006Bkkkk	()I
    //   159: putstatic 140	uuuuuu/pqpppq:bs0073s0073ss0073s0073	I
    //   162: invokestatic 157	uuuuuu/pqpppq:bk006Bkkk006Bkkkk	()I
    //   165: istore_2
    //   166: invokestatic 157	uuuuuu/pqpppq:bk006Bkkk006Bkkkk	()I
    //   169: getstatic 159	uuuuuu/pqpppq:bss00730073ss0073s0073	I
    //   172: iadd
    //   173: invokestatic 157	uuuuuu/pqpppq:bk006Bkkk006Bkkkk	()I
    //   176: imul
    //   177: getstatic 146	uuuuuu/pqpppq:b00730073s0073ss0073s0073	I
    //   180: irem
    //   181: getstatic 245	uuuuuu/pqpppq:b0073s00730073ss0073s0073	I
    //   184: if_icmpeq +12 -> 196
    //   187: iconst_0
    //   188: putstatic 140	uuuuuu/pqpppq:bs0073s0073ss0073s0073	I
    //   191: bipush 31
    //   193: putstatic 245	uuuuuu/pqpppq:b0073s00730073ss0073s0073	I
    //   196: iload_2
    //   197: putstatic 245	uuuuuu/pqpppq:b0073s00730073ss0073s0073	I
    //   200: aload_1
    //   201: invokevirtual 248	java/util/TimeZone:getDSTSavings	()I
    //   204: istore_2
    //   205: aload_0
    //   206: iload_2
    //   207: i2l
    //   208: lload_3
    //   209: lload 5
    //   211: ladd
    //   212: ladd
    //   213: ldc_w 342
    //   216: invokestatic 267	android/text/format/DateUtils:formatDateTime	(Landroid/content/Context;JI)Ljava/lang/String;
    //   219: areturn
    //   220: iconst_0
    //   221: istore_2
    //   222: goto -17 -> 205
    //   225: astore_0
    //   226: aload_0
    //   227: invokevirtual 183	java/lang/reflect/InvocationTargetException:getCause	()Ljava/lang/Throwable;
    //   230: athrow
    //   231: astore_0
    //   232: getstatic 179	uuuuuu/pqpppq:bsss0073ss0073s0073	Ljava/lang/String;
    //   235: astore_1
    //   236: ldc 68
    //   238: ldc_w 457
    //   241: bipush 63
    //   243: iconst_4
    //   244: invokestatic 108	xxxxxx/uxxxxx:bb00620062bb0062b0062b0062	(Ljava/lang/String;CC)Ljava/lang/String;
    //   247: iconst_3
    //   248: anewarray 78	java/lang/Class
    //   251: dup
    //   252: iconst_0
    //   253: ldc 80
    //   255: aastore
    //   256: dup
    //   257: iconst_1
    //   258: getstatic 86	java/lang/Character:TYPE	Ljava/lang/Class;
    //   261: aastore
    //   262: dup
    //   263: iconst_2
    //   264: getstatic 86	java/lang/Character:TYPE	Ljava/lang/Class;
    //   267: aastore
    //   268: invokevirtual 90	java/lang/Class:getMethod	(Ljava/lang/String;[Ljava/lang/Class;)Ljava/lang/reflect/Method;
    //   271: astore 7
    //   273: aload 7
    //   275: aconst_null
    //   276: iconst_3
    //   277: anewarray 4	java/lang/Object
    //   280: dup
    //   281: iconst_0
    //   282: ldc_w 459
    //   285: aastore
    //   286: dup
    //   287: iconst_1
    //   288: sipush 235
    //   291: invokestatic 94	java/lang/Character:valueOf	(C)Ljava/lang/Character;
    //   294: aastore
    //   295: dup
    //   296: iconst_2
    //   297: iconst_4
    //   298: invokestatic 94	java/lang/Character:valueOf	(C)Ljava/lang/Character;
    //   301: aastore
    //   302: invokevirtual 100	java/lang/reflect/Method:invoke	(Ljava/lang/Object;[Ljava/lang/Object;)Ljava/lang/Object;
    //   305: astore 7
    //   307: aload_1
    //   308: aload 7
    //   310: checkcast 80	java/lang/String
    //   313: aload_0
    //   314: invokestatic 277	uuuuuu/rvvvrv:b00710071qq00710071q0071q0071	(Ljava/lang/String;Ljava/lang/String;Ljava/lang/Throwable;)V
    //   317: ldc -59
    //   319: areturn
    //   320: astore_0
    //   321: aload_0
    //   322: invokevirtual 183	java/lang/reflect/InvocationTargetException:getCause	()Ljava/lang/Throwable;
    //   325: athrow
    // Local variable table:
    //   start	length	slot	name	signature
    //   0	326	0	paramContext	Context
    //   0	326	1	paramString	String
    //   165	57	2	i	int
    //   111	98	3	l1	long
    //   119	91	5	l2	long
    //   50	259	7	localObject	Object
    // Exception table:
    //   from	to	target	type
    //   52	86	225	java/lang/reflect/InvocationTargetException
    //   52	86	231	java/text/ParseException
    //   93	107	231	java/text/ParseException
    //   226	231	231	java/text/ParseException
    //   273	307	320	java/lang/reflect/InvocationTargetException
  }
  
  /* Error */
  public static String bkk006Bk006B006Bkkkk(Locale paramLocale, int paramInt)
  {
    // Byte code:
    //   0: aload_0
    //   1: invokevirtual 324	java/util/Locale:getLanguage	()Ljava/lang/String;
    //   4: getstatic 321	java/util/Locale:GERMAN	Ljava/util/Locale;
    //   7: invokevirtual 324	java/util/Locale:getLanguage	()Ljava/lang/String;
    //   10: invokevirtual 328	java/lang/String:equals	(Ljava/lang/Object;)Z
    //   13: ifeq +79 -> 92
    //   16: ldc 68
    //   18: ldc_w 463
    //   21: bipush 101
    //   23: bipush 51
    //   25: iconst_1
    //   26: invokestatic 76	xxxxxx/uxxxxx:bbbb0062b0062b0062b0062	(Ljava/lang/String;CCC)Ljava/lang/String;
    //   29: iconst_3
    //   30: anewarray 78	java/lang/Class
    //   33: dup
    //   34: iconst_0
    //   35: ldc 80
    //   37: aastore
    //   38: dup
    //   39: iconst_1
    //   40: getstatic 86	java/lang/Character:TYPE	Ljava/lang/Class;
    //   43: aastore
    //   44: dup
    //   45: iconst_2
    //   46: getstatic 86	java/lang/Character:TYPE	Ljava/lang/Class;
    //   49: aastore
    //   50: invokevirtual 90	java/lang/Class:getMethod	(Ljava/lang/String;[Ljava/lang/Class;)Ljava/lang/reflect/Method;
    //   53: astore_0
    //   54: aload_0
    //   55: aconst_null
    //   56: iconst_3
    //   57: anewarray 4	java/lang/Object
    //   60: dup
    //   61: iconst_0
    //   62: ldc_w 465
    //   65: aastore
    //   66: dup
    //   67: iconst_1
    //   68: bipush 44
    //   70: invokestatic 94	java/lang/Character:valueOf	(C)Ljava/lang/Character;
    //   73: aastore
    //   74: dup
    //   75: iconst_2
    //   76: iconst_1
    //   77: invokestatic 94	java/lang/Character:valueOf	(C)Ljava/lang/Character;
    //   80: aastore
    //   81: invokevirtual 100	java/lang/reflect/Method:invoke	(Ljava/lang/Object;[Ljava/lang/Object;)Ljava/lang/Object;
    //   84: astore_0
    //   85: aload_0
    //   86: checkcast 80	java/lang/String
    //   89: astore_0
    //   90: aload_0
    //   91: areturn
    //   92: aload_0
    //   93: invokevirtual 324	java/util/Locale:getLanguage	()Ljava/lang/String;
    //   96: getstatic 396	java/util/Locale:ENGLISH	Ljava/util/Locale;
    //   99: invokevirtual 324	java/util/Locale:getLanguage	()Ljava/lang/String;
    //   102: invokevirtual 328	java/lang/String:equals	(Ljava/lang/Object;)Z
    //   105: ifeq +489 -> 594
    //   108: getstatic 140	uuuuuu/pqpppq:bs0073s0073ss0073s0073	I
    //   111: getstatic 159	uuuuuu/pqpppq:bss00730073ss0073s0073	I
    //   114: iadd
    //   115: getstatic 140	uuuuuu/pqpppq:bs0073s0073ss0073s0073	I
    //   118: imul
    //   119: getstatic 146	uuuuuu/pqpppq:b00730073s0073ss0073s0073	I
    //   122: irem
    //   123: getstatic 245	uuuuuu/pqpppq:b0073s00730073ss0073s0073	I
    //   126: if_icmpeq +14 -> 140
    //   129: bipush 84
    //   131: putstatic 140	uuuuuu/pqpppq:bs0073s0073ss0073s0073	I
    //   134: invokestatic 157	uuuuuu/pqpppq:bk006Bkkk006Bkkkk	()I
    //   137: putstatic 245	uuuuuu/pqpppq:b0073s00730073ss0073s0073	I
    //   140: iload_1
    //   141: lookupswitch	default:+67->208, 1:+219->360, 2:+139->280, 3:+312->453, 21:+219->360, 22:+139->280, 23:+312->453, 31:+219->360
    //   208: ldc 68
    //   210: ldc_w 467
    //   213: bipush 38
    //   215: iconst_4
    //   216: invokestatic 108	xxxxxx/uxxxxx:bb00620062bb0062b0062b0062	(Ljava/lang/String;CC)Ljava/lang/String;
    //   219: iconst_3
    //   220: anewarray 78	java/lang/Class
    //   223: dup
    //   224: iconst_0
    //   225: ldc 80
    //   227: aastore
    //   228: dup
    //   229: iconst_1
    //   230: getstatic 86	java/lang/Character:TYPE	Ljava/lang/Class;
    //   233: aastore
    //   234: dup
    //   235: iconst_2
    //   236: getstatic 86	java/lang/Character:TYPE	Ljava/lang/Class;
    //   239: aastore
    //   240: invokevirtual 90	java/lang/Class:getMethod	(Ljava/lang/String;[Ljava/lang/Class;)Ljava/lang/reflect/Method;
    //   243: astore_0
    //   244: aload_0
    //   245: aconst_null
    //   246: iconst_3
    //   247: anewarray 4	java/lang/Object
    //   250: dup
    //   251: iconst_0
    //   252: ldc_w 469
    //   255: aastore
    //   256: dup
    //   257: iconst_1
    //   258: bipush 21
    //   260: invokestatic 94	java/lang/Character:valueOf	(C)Ljava/lang/Character;
    //   263: aastore
    //   264: dup
    //   265: iconst_2
    //   266: iconst_3
    //   267: invokestatic 94	java/lang/Character:valueOf	(C)Ljava/lang/Character;
    //   270: aastore
    //   271: invokevirtual 100	java/lang/reflect/Method:invoke	(Ljava/lang/Object;[Ljava/lang/Object;)Ljava/lang/Object;
    //   274: astore_0
    //   275: aload_0
    //   276: checkcast 80	java/lang/String
    //   279: areturn
    //   280: ldc 68
    //   282: ldc_w 471
    //   285: sipush 236
    //   288: iconst_4
    //   289: invokestatic 108	xxxxxx/uxxxxx:bb00620062bb0062b0062b0062	(Ljava/lang/String;CC)Ljava/lang/String;
    //   292: iconst_3
    //   293: anewarray 78	java/lang/Class
    //   296: dup
    //   297: iconst_0
    //   298: ldc 80
    //   300: aastore
    //   301: dup
    //   302: iconst_1
    //   303: getstatic 86	java/lang/Character:TYPE	Ljava/lang/Class;
    //   306: aastore
    //   307: dup
    //   308: iconst_2
    //   309: getstatic 86	java/lang/Character:TYPE	Ljava/lang/Class;
    //   312: aastore
    //   313: invokevirtual 90	java/lang/Class:getMethod	(Ljava/lang/String;[Ljava/lang/Class;)Ljava/lang/reflect/Method;
    //   316: astore_0
    //   317: aload_0
    //   318: aconst_null
    //   319: iconst_3
    //   320: anewarray 4	java/lang/Object
    //   323: dup
    //   324: iconst_0
    //   325: ldc_w 473
    //   328: aastore
    //   329: dup
    //   330: iconst_1
    //   331: sipush 191
    //   334: invokestatic 94	java/lang/Character:valueOf	(C)Ljava/lang/Character;
    //   337: aastore
    //   338: dup
    //   339: iconst_2
    //   340: iconst_3
    //   341: invokestatic 94	java/lang/Character:valueOf	(C)Ljava/lang/Character;
    //   344: aastore
    //   345: invokevirtual 100	java/lang/reflect/Method:invoke	(Ljava/lang/Object;[Ljava/lang/Object;)Ljava/lang/Object;
    //   348: astore_0
    //   349: aload_0
    //   350: checkcast 80	java/lang/String
    //   353: areturn
    //   354: astore_0
    //   355: aload_0
    //   356: invokevirtual 183	java/lang/reflect/InvocationTargetException:getCause	()Ljava/lang/Throwable;
    //   359: athrow
    //   360: ldc 68
    //   362: ldc_w 475
    //   365: bipush 123
    //   367: iconst_1
    //   368: invokestatic 108	xxxxxx/uxxxxx:bb00620062bb0062b0062b0062	(Ljava/lang/String;CC)Ljava/lang/String;
    //   371: iconst_4
    //   372: anewarray 78	java/lang/Class
    //   375: dup
    //   376: iconst_0
    //   377: ldc 80
    //   379: aastore
    //   380: dup
    //   381: iconst_1
    //   382: getstatic 86	java/lang/Character:TYPE	Ljava/lang/Class;
    //   385: aastore
    //   386: dup
    //   387: iconst_2
    //   388: getstatic 86	java/lang/Character:TYPE	Ljava/lang/Class;
    //   391: aastore
    //   392: dup
    //   393: iconst_3
    //   394: getstatic 86	java/lang/Character:TYPE	Ljava/lang/Class;
    //   397: aastore
    //   398: invokevirtual 90	java/lang/Class:getMethod	(Ljava/lang/String;[Ljava/lang/Class;)Ljava/lang/reflect/Method;
    //   401: astore_0
    //   402: aload_0
    //   403: aconst_null
    //   404: iconst_4
    //   405: anewarray 4	java/lang/Object
    //   408: dup
    //   409: iconst_0
    //   410: ldc_w 477
    //   413: aastore
    //   414: dup
    //   415: iconst_1
    //   416: sipush 165
    //   419: invokestatic 94	java/lang/Character:valueOf	(C)Ljava/lang/Character;
    //   422: aastore
    //   423: dup
    //   424: iconst_2
    //   425: bipush 92
    //   427: invokestatic 94	java/lang/Character:valueOf	(C)Ljava/lang/Character;
    //   430: aastore
    //   431: dup
    //   432: iconst_3
    //   433: iconst_0
    //   434: invokestatic 94	java/lang/Character:valueOf	(C)Ljava/lang/Character;
    //   437: aastore
    //   438: invokevirtual 100	java/lang/reflect/Method:invoke	(Ljava/lang/Object;[Ljava/lang/Object;)Ljava/lang/Object;
    //   441: astore_0
    //   442: aload_0
    //   443: checkcast 80	java/lang/String
    //   446: areturn
    //   447: astore_0
    //   448: aload_0
    //   449: invokevirtual 183	java/lang/reflect/InvocationTargetException:getCause	()Ljava/lang/Throwable;
    //   452: athrow
    //   453: ldc 68
    //   455: ldc_w 479
    //   458: sipush 138
    //   461: iconst_4
    //   462: invokestatic 108	xxxxxx/uxxxxx:bb00620062bb0062b0062b0062	(Ljava/lang/String;CC)Ljava/lang/String;
    //   465: iconst_4
    //   466: anewarray 78	java/lang/Class
    //   469: dup
    //   470: iconst_0
    //   471: ldc 80
    //   473: aastore
    //   474: dup
    //   475: iconst_1
    //   476: getstatic 86	java/lang/Character:TYPE	Ljava/lang/Class;
    //   479: aastore
    //   480: dup
    //   481: iconst_2
    //   482: getstatic 86	java/lang/Character:TYPE	Ljava/lang/Class;
    //   485: aastore
    //   486: dup
    //   487: iconst_3
    //   488: getstatic 86	java/lang/Character:TYPE	Ljava/lang/Class;
    //   491: aastore
    //   492: invokevirtual 90	java/lang/Class:getMethod	(Ljava/lang/String;[Ljava/lang/Class;)Ljava/lang/reflect/Method;
    //   495: astore_0
    //   496: aload_0
    //   497: aconst_null
    //   498: iconst_4
    //   499: anewarray 4	java/lang/Object
    //   502: dup
    //   503: iconst_0
    //   504: ldc_w 481
    //   507: aastore
    //   508: dup
    //   509: iconst_1
    //   510: bipush 84
    //   512: invokestatic 94	java/lang/Character:valueOf	(C)Ljava/lang/Character;
    //   515: aastore
    //   516: dup
    //   517: iconst_2
    //   518: bipush 52
    //   520: invokestatic 94	java/lang/Character:valueOf	(C)Ljava/lang/Character;
    //   523: aastore
    //   524: dup
    //   525: iconst_3
    //   526: iconst_2
    //   527: invokestatic 94	java/lang/Character:valueOf	(C)Ljava/lang/Character;
    //   530: aastore
    //   531: invokevirtual 100	java/lang/reflect/Method:invoke	(Ljava/lang/Object;[Ljava/lang/Object;)Ljava/lang/Object;
    //   534: astore_0
    //   535: aload_0
    //   536: checkcast 80	java/lang/String
    //   539: astore_2
    //   540: getstatic 140	uuuuuu/pqpppq:bs0073s0073ss0073s0073	I
    //   543: istore_1
    //   544: aload_2
    //   545: astore_0
    //   546: iload_1
    //   547: invokestatic 144	uuuuuu/pqpppq:b006B006Bkkk006Bkkkk	()I
    //   550: iload_1
    //   551: iadd
    //   552: imul
    //   553: getstatic 146	uuuuuu/pqpppq:b00730073s0073ss0073s0073	I
    //   556: irem
    //   557: tableswitch	default:+19->576, 0:+-467->90
    //   576: bipush 42
    //   578: putstatic 140	uuuuuu/pqpppq:bs0073s0073ss0073s0073	I
    //   581: bipush 57
    //   583: putstatic 245	uuuuuu/pqpppq:b0073s00730073ss0073s0073	I
    //   586: aload_2
    //   587: areturn
    //   588: astore_0
    //   589: aload_0
    //   590: invokevirtual 183	java/lang/reflect/InvocationTargetException:getCause	()Ljava/lang/Throwable;
    //   593: athrow
    //   594: ldc -59
    //   596: areturn
    //   597: astore_0
    //   598: aload_0
    //   599: invokevirtual 183	java/lang/reflect/InvocationTargetException:getCause	()Ljava/lang/Throwable;
    //   602: athrow
    //   603: astore_0
    //   604: aload_0
    //   605: invokevirtual 183	java/lang/reflect/InvocationTargetException:getCause	()Ljava/lang/Throwable;
    //   608: athrow
    // Local variable table:
    //   start	length	slot	name	signature
    //   0	609	0	paramLocale	Locale
    //   0	609	1	paramInt	int
    //   539	48	2	str	String
    // Exception table:
    //   from	to	target	type
    //   317	349	354	java/lang/reflect/InvocationTargetException
    //   402	442	447	java/lang/reflect/InvocationTargetException
    //   54	85	588	java/lang/reflect/InvocationTargetException
    //   244	275	597	java/lang/reflect/InvocationTargetException
    //   496	535	603	java/lang/reflect/InvocationTargetException
  }
  
  public static String bkk006Bkk006Bkkkk(String paramString1, String paramString2, String paramString3)
  {
    paramString2 = new SimpleDateFormat(paramString2, Locale.getDefault());
    if ((bs0073s0073ss0073s0073 + bss00730073ss0073s0073) * bs0073s0073ss0073s0073 % b00730073s0073ss0073s0073 != b0073s00730073ss0073s0073)
    {
      bs0073s0073ss0073s0073 = 20;
      b0073s00730073ss0073s0073 = 81;
    }
    paramString3 = new SimpleDateFormat(paramString3, Locale.getDefault());
    int i = bs0073s0073ss0073s0073;
    switch (i * (bss00730073ss0073s0073 + i) % b00730073s0073ss0073s0073)
    {
    default: 
      bs0073s0073ss0073s0073 = bk006Bkkk006Bkkkk();
      b0073s00730073ss0073s0073 = 92;
    }
    try
    {
      paramString1 = paramString3.format(paramString2.parse(paramString1));
      return paramString1;
    }
    catch (ParseException paramString1)
    {
      paramString2 = bsss0073ss0073s0073;
      paramString3 = ppphhp.class.getMethod(uxxxxx.bb00620062bb0062b0062b0062("Pf !)*kl&'/0*+34u/08934<=~", 'y', '\000'), new Class[] { String.class, Character.TYPE, Character.TYPE, Character.TYPE });
      try
      {
        paramString3 = paramString3.invoke(null, new Object[] { "\00505+\"\\**.X\033&$+\031%&P\024\020\"\022K\021\031\033\025\b\032", Character.valueOf(''), Character.valueOf(''), Character.valueOf('\000') });
        rvvvrv.b00710071qq00710071q0071q0071(paramString2, (String)paramString3, paramString1);
        return null;
      }
      catch (InvocationTargetException paramString1)
      {
        throw paramString1.getCause();
      }
    }
  }
  
  public static String bkkk006B006B006Bkkkk(String paramString1, String paramString2, int paramInt)
  {
    paramString2 = new SimpleDateFormat(paramString2, Locale.getDefault());
    int i = bs0073s0073ss0073s0073;
    switch (i * (bss00730073ss0073s0073 + i) % b00730073s0073ss0073s0073)
    {
    default: 
      bs0073s0073ss0073s0073 = 25;
      b0073s00730073ss0073s0073 = 98;
    }
    i = bs0073s0073ss0073s0073;
    switch (i * (b006B006Bkkk006Bkkkk() + i) % b00730073s0073ss0073s0073)
    {
    default: 
      bs0073s0073ss0073s0073 = 28;
      b0073s00730073ss0073s0073 = 27;
    }
    try
    {
      paramString1 = paramString2.parse(paramString1);
      localObject = Calendar.getInstance();
      ((Calendar)localObject).setTime(paramString1);
      ((Calendar)localObject).add(6, paramInt);
      return paramString2.format(((Calendar)localObject).getTime());
    }
    catch (ParseException paramString1)
    {
      paramString2 = bsss0073ss0073s0073;
      Object localObject = ppphhp.class.getMethod(uxxxxx.bb00620062bb0062b0062b0062("\03510/.edjia`fe%\\[a`XW]\\\034", '', '\004'), new Class[] { String.class, Character.TYPE, Character.TYPE });
      try
      {
        localObject = ((Method)localObject).invoke(null, new Object[] { "\t%.2,,h>:k0/;3F>4H:uK@>yIAUR~DB[", Character.valueOf('B'), Character.valueOf('\002') });
        rvvvrv.b00710071qq00710071q0071q0071(paramString2, (String)localObject, paramString1);
        return null;
      }
      catch (InvocationTargetException paramString1)
      {
        throw paramString1.getCause();
      }
    }
  }
  
  public static String bkkk006Bk006Bkkkk(Locale paramLocale, Date paramDate)
  {
    Object localObject;
    if (paramDate == null)
    {
      return "";
      localObject = ppphhp.class.getMethod(uxxxxx.bb00620062bb0062b0062b0062("g}78@A\003\004=>FGABJK\rFGOPJKST\026", '', '\001'), new Class[] { String.class, Character.TYPE, Character.TYPE, Character.TYPE });
    }
    for (;;)
    {
      try
      {
        localObject = ((Method)localObject).invoke(null, new Object[] { "*+\016DE\021\\]^_", Character.valueOf('\020'), Character.valueOf('3'), Character.valueOf('\002') });
        localObject = (String)localObject;
        return new SimpleDateFormat((String)localObject, paramLocale).format(paramDate);
      }
      catch (InvocationTargetException paramLocale)
      {
        throw paramLocale.getCause();
      }
      if (!Locale.GERMAN.getLanguage().equals(paramLocale.getLanguage())) {
        break;
      }
      int i = bs0073s0073ss0073s0073;
      switch (i * (bss00730073ss0073s0073 + i) % b00730073s0073ss0073s0073)
      {
      default: 
        bs0073s0073ss0073s0073 = 5;
        b0073s00730073ss0073s0073 = bk006Bkkk006Bkkkk();
        i = bs0073s0073ss0073s0073;
        switch (i * (bss00730073ss0073s0073 + i) % b00730073s0073ss0073s0073)
        {
        default: 
          bs0073s0073ss0073s0073 = 55;
          b0073s00730073ss0073s0073 = bk006Bkkk006Bkkkk();
        }
        break;
      }
      localObject = ppphhp.class.getMethod(uxxxxx.bb00620062bb0062b0062b0062("o\004;:@?~}54:91065t,+10('-,k", 'r', '\003'), new Class[] { String.class, Character.TYPE, Character.TYPE, Character.TYPE });
      try
      {
        localObject = ((Method)localObject).invoke(null, new Object[] { "HI\02445\027cdef", Character.valueOf(''), Character.valueOf('\r'), Character.valueOf('\003') });
        localObject = (String)localObject;
      }
      catch (InvocationTargetException paramLocale)
      {
        throw paramLocale.getCause();
      }
    }
  }
  
  public static int bkkkkk006Bkkkk()
  {
    return 2;
  }
  
  public String b006B006Bkk006B006Bkkkk(Context paramContext, String paramString)
  {
    if ((paramString == null) || (paramString.length() < 24))
    {
      paramContext = bsss0073ss0073s0073;
      paramString = ppphhp.class.getMethod(uxxxxx.bbbb0062b0062b0062b0062("Pf !)*kl&'/0*+34u/08934<=~", '', ';', '\002'), new Class[] { String.class, Character.TYPE, Character.TYPE, Character.TYPE });
    }
    try
    {
      paramString = paramString.invoke(null, new Object[] { "m\002\005{\t\tt\0020x\002-Z`VU(vx%{uqog\037dlnh[m", Character.valueOf(''), Character.valueOf(''), Character.valueOf('\001') });
      rvvvrv.bq0071qq00710071q0071q0071(paramContext, (String)paramString);
      i = bs0073s0073ss0073s0073;
      switch (i * (bss00730073ss0073s0073 + i) % b00730073s0073ss0073s0073)
      {
      default: 
        bs0073s0073ss0073s0073 = 40;
        b0073s00730073ss0073s0073 = 27;
      }
      return "";
    }
    catch (InvocationTargetException paramContext)
    {
      label297:
      throw paramContext.getCause();
    }
    localObject = ppphhp.class.getMethod(uxxxxx.bbbb0062b0062b0062b0062("@T\f\013\021\020ON\006\005\013\n\002\001\007\006E|{\002\001xw}|<", '', 'N', '\001'), new Class[] { String.class, Character.TYPE, Character.TYPE, Character.TYPE });
    try
    {
      localObject = ((Method)localObject).invoke(null, new Object[] { "]^_`\02567\030PQ\025C\0279:-ab0jk'MNO$X&", Character.valueOf('\030'), Character.valueOf('4'), Character.valueOf('\002') });
      localObject = new SimpleDateFormat((String)localObject);
    }
    catch (InvocationTargetException paramContext)
    {
      long l1;
      long l2;
      throw paramContext.getCause();
    }
    try
    {
      paramString = ((DateFormat)localObject).parse(paramString);
      l1 = paramString.getTime();
      l2 = TimeZone.getDefault().getRawOffset();
      if (!TimeZone.getDefault().inDaylightTime(paramString)) {
        break label495;
      }
      i = TimeZone.getDefault().getDSTSavings();
    }
    catch (ParseException paramContext)
    {
      paramString = bsss0073ss0073s0073;
      localObject = ppphhp.class.getMethod(uxxxxx.bbbb0062b0062b0062b0062("H\\\024\023\031\030WV\016\r\023\022\n\t\017\016M\005\004\n\t\001\006\005D", '', 'Q', '\000'), new Class[] { String.class, Character.TYPE, Character.TYPE, Character.TYPE });
      try
      {
        localObject = ((Method)localObject).invoke(null, new Object[] { "-GNPHF\001TN}M=MM>wC7HHr>@78<", Character.valueOf('*'), Character.valueOf('\021'), Character.valueOf('\001') });
        rvvvrv.b00710071qq00710071q0071q0071(paramString, (String)localObject, paramContext);
        return "";
      }
      catch (InvocationTargetException paramContext)
      {
        throw paramContext.getCause();
      }
      i = 0;
      break label297;
    }
    paramString = DateUtils.formatDateTime(paramContext, i + (l1 + l2), 131093);
    paramContext = new StringBuilder().append(paramString).append(paramContext.getString(R.string.lastlogin_suffix));
    if ((bs0073s0073ss0073s0073 + bss00730073ss0073s0073) * bs0073s0073ss0073s0073 % b00730073s0073ss0073s0073 != b006Bkkkk006Bkkkk())
    {
      bs0073s0073ss0073s0073 = 93;
      b0073s00730073ss0073s0073 = bk006Bkkk006Bkkkk();
    }
    return paramContext.toString();
  }
  
  public String b006Bkk006B006B006Bkkkk(Date paramDate, Locale paramLocale)
  {
    Object localObject = ppphhp.class.getMethod(uxxxxx.bbbb0062b0062b0062b0062("\004\030\027\026\025LKQPHGML\fCBHG?>DC\003", '', '', '\001'), new Class[] { String.class, Character.TYPE, Character.TYPE });
    try
    {
      localObject = ((Method)localObject).invoke(null, new Object[] { "/.\037QP", Character.valueOf(']'), Character.valueOf('\005') });
      localObject = (String)localObject;
      if ((bs0073s0073ss0073s0073 + bss00730073ss0073s0073) * bs0073s0073ss0073s0073 % b00730073s0073ss0073s0073 != b0073s00730073ss0073s0073)
      {
        bs0073s0073ss0073s0073 = 83;
        if ((bs0073s0073ss0073s0073 + bss00730073ss0073s0073) * bs0073s0073ss0073s0073 % b00730073s0073ss0073s0073 != b0073s00730073ss0073s0073)
        {
          bs0073s0073ss0073s0073 = bk006Bkkk006Bkkkk();
          b0073s00730073ss0073s0073 = 95;
        }
        b0073s00730073ss0073s0073 = 0;
      }
      return bk006B006Bkk006Bkkkk(paramDate, (String)localObject, paramLocale);
    }
    catch (InvocationTargetException paramDate)
    {
      throw paramDate.getCause();
    }
  }
  
  public String bk006B006Bk006B006Bkkkk(Date paramDate)
  {
    TimeZone localTimeZone = TimeZone.getDefault();
    if ((bk006Bkkk006Bkkkk() + bss00730073ss0073s0073) * bk006Bkkk006Bkkkk() % b00730073s0073ss0073s0073 != b0073s00730073ss0073s0073)
    {
      bs0073s0073ss0073s0073 = bk006Bkkk006Bkkkk();
      b0073s00730073ss0073s0073 = bk006Bkkk006Bkkkk();
    }
    boolean bool = localTimeZone.inDaylightTime(paramDate);
    if ((bk006Bkkk006Bkkkk() + bss00730073ss0073s0073) * bk006Bkkk006Bkkkk() % b00730073s0073ss0073s0073 != b0073s00730073ss0073s0073)
    {
      bs0073s0073ss0073s0073 = bk006Bkkk006Bkkkk();
      b0073s00730073ss0073s0073 = 89;
    }
    return localTimeZone.getDisplayName(bool, 0);
  }
  
  /* Error */
  public String bkkkk006B006Bkkkk(Locale paramLocale, String paramString1, String paramString2)
  {
    // Byte code:
    //   0: new 203	java/text/SimpleDateFormat
    //   3: dup
    //   4: aload_3
    //   5: getstatic 412	java/util/Locale:US	Ljava/util/Locale;
    //   8: invokespecial 287	java/text/SimpleDateFormat:<init>	(Ljava/lang/String;Ljava/util/Locale;)V
    //   11: aload_2
    //   12: invokevirtual 226	java/text/DateFormat:parse	(Ljava/lang/String;)Ljava/util/Date;
    //   15: astore_2
    //   16: getstatic 140	uuuuuu/pqpppq:bs0073s0073ss0073s0073	I
    //   19: invokestatic 144	uuuuuu/pqpppq:b006B006Bkkk006Bkkkk	()I
    //   22: iadd
    //   23: getstatic 140	uuuuuu/pqpppq:bs0073s0073ss0073s0073	I
    //   26: imul
    //   27: getstatic 146	uuuuuu/pqpppq:b00730073s0073ss0073s0073	I
    //   30: irem
    //   31: getstatic 245	uuuuuu/pqpppq:b0073s00730073ss0073s0073	I
    //   34: if_icmpeq +14 -> 48
    //   37: bipush 68
    //   39: putstatic 140	uuuuuu/pqpppq:bs0073s0073ss0073s0073	I
    //   42: invokestatic 157	uuuuuu/pqpppq:bk006Bkkk006Bkkkk	()I
    //   45: putstatic 245	uuuuuu/pqpppq:b0073s00730073ss0073s0073	I
    //   48: ldc 68
    //   50: ldc_w 562
    //   53: bipush 6
    //   55: sipush 216
    //   58: iconst_3
    //   59: invokestatic 76	xxxxxx/uxxxxx:bbbb0062b0062b0062b0062	(Ljava/lang/String;CCC)Ljava/lang/String;
    //   62: iconst_3
    //   63: anewarray 78	java/lang/Class
    //   66: dup
    //   67: iconst_0
    //   68: ldc 80
    //   70: aastore
    //   71: dup
    //   72: iconst_1
    //   73: getstatic 86	java/lang/Character:TYPE	Ljava/lang/Class;
    //   76: aastore
    //   77: dup
    //   78: iconst_2
    //   79: getstatic 86	java/lang/Character:TYPE	Ljava/lang/Class;
    //   82: aastore
    //   83: invokevirtual 90	java/lang/Class:getMethod	(Ljava/lang/String;[Ljava/lang/Class;)Ljava/lang/reflect/Method;
    //   86: astore_3
    //   87: aload_3
    //   88: aconst_null
    //   89: iconst_3
    //   90: anewarray 4	java/lang/Object
    //   93: dup
    //   94: iconst_0
    //   95: ldc_w 564
    //   98: aastore
    //   99: dup
    //   100: iconst_1
    //   101: sipush 209
    //   104: invokestatic 94	java/lang/Character:valueOf	(C)Ljava/lang/Character;
    //   107: aastore
    //   108: dup
    //   109: iconst_2
    //   110: iconst_0
    //   111: invokestatic 94	java/lang/Character:valueOf	(C)Ljava/lang/Character;
    //   114: aastore
    //   115: invokevirtual 100	java/lang/reflect/Method:invoke	(Ljava/lang/Object;[Ljava/lang/Object;)Ljava/lang/Object;
    //   118: astore_3
    //   119: new 203	java/text/SimpleDateFormat
    //   122: dup
    //   123: aload_3
    //   124: checkcast 80	java/lang/String
    //   127: aload_1
    //   128: invokespecial 287	java/text/SimpleDateFormat:<init>	(Ljava/lang/String;Ljava/util/Locale;)V
    //   131: aload_2
    //   132: invokevirtual 336	java/text/DateFormat:format	(Ljava/util/Date;)Ljava/lang/String;
    //   135: areturn
    //   136: astore_1
    //   137: aload_1
    //   138: invokevirtual 183	java/lang/reflect/InvocationTargetException:getCause	()Ljava/lang/Throwable;
    //   141: athrow
    //   142: astore_1
    //   143: getstatic 140	uuuuuu/pqpppq:bs0073s0073ss0073s0073	I
    //   146: getstatic 159	uuuuuu/pqpppq:bss00730073ss0073s0073	I
    //   149: iadd
    //   150: getstatic 140	uuuuuu/pqpppq:bs0073s0073ss0073s0073	I
    //   153: imul
    //   154: getstatic 146	uuuuuu/pqpppq:b00730073s0073ss0073s0073	I
    //   157: irem
    //   158: getstatic 245	uuuuuu/pqpppq:b0073s00730073ss0073s0073	I
    //   161: if_icmpeq +15 -> 176
    //   164: invokestatic 157	uuuuuu/pqpppq:bk006Bkkk006Bkkkk	()I
    //   167: putstatic 140	uuuuuu/pqpppq:bs0073s0073ss0073s0073	I
    //   170: invokestatic 157	uuuuuu/pqpppq:bk006Bkkk006Bkkkk	()I
    //   173: putstatic 245	uuuuuu/pqpppq:b0073s00730073ss0073s0073	I
    //   176: getstatic 179	uuuuuu/pqpppq:bsss0073ss0073s0073	Ljava/lang/String;
    //   179: astore_2
    //   180: ldc 68
    //   182: ldc_w 566
    //   185: bipush 32
    //   187: bipush 113
    //   189: iconst_1
    //   190: invokestatic 76	xxxxxx/uxxxxx:bbbb0062b0062b0062b0062	(Ljava/lang/String;CCC)Ljava/lang/String;
    //   193: iconst_3
    //   194: anewarray 78	java/lang/Class
    //   197: dup
    //   198: iconst_0
    //   199: ldc 80
    //   201: aastore
    //   202: dup
    //   203: iconst_1
    //   204: getstatic 86	java/lang/Character:TYPE	Ljava/lang/Class;
    //   207: aastore
    //   208: dup
    //   209: iconst_2
    //   210: getstatic 86	java/lang/Character:TYPE	Ljava/lang/Class;
    //   213: aastore
    //   214: invokevirtual 90	java/lang/Class:getMethod	(Ljava/lang/String;[Ljava/lang/Class;)Ljava/lang/reflect/Method;
    //   217: astore_3
    //   218: aload_3
    //   219: aconst_null
    //   220: iconst_3
    //   221: anewarray 4	java/lang/Object
    //   224: dup
    //   225: iconst_0
    //   226: ldc_w 568
    //   229: aastore
    //   230: dup
    //   231: iconst_1
    //   232: bipush 47
    //   234: invokestatic 94	java/lang/Character:valueOf	(C)Ljava/lang/Character;
    //   237: aastore
    //   238: dup
    //   239: iconst_2
    //   240: iconst_4
    //   241: invokestatic 94	java/lang/Character:valueOf	(C)Ljava/lang/Character;
    //   244: aastore
    //   245: invokevirtual 100	java/lang/reflect/Method:invoke	(Ljava/lang/Object;[Ljava/lang/Object;)Ljava/lang/Object;
    //   248: astore_3
    //   249: aload_2
    //   250: aload_3
    //   251: checkcast 80	java/lang/String
    //   254: aload_1
    //   255: invokestatic 277	uuuuuu/rvvvrv:b00710071qq00710071q0071q0071	(Ljava/lang/String;Ljava/lang/String;Ljava/lang/Throwable;)V
    //   258: aconst_null
    //   259: areturn
    //   260: astore_1
    //   261: aload_1
    //   262: invokevirtual 183	java/lang/reflect/InvocationTargetException:getCause	()Ljava/lang/Throwable;
    //   265: athrow
    // Local variable table:
    //   start	length	slot	name	signature
    //   0	266	0	this	pqpppq
    //   0	266	1	paramLocale	Locale
    //   0	266	2	paramString1	String
    //   0	266	3	paramString2	String
    // Exception table:
    //   from	to	target	type
    //   87	119	136	java/lang/reflect/InvocationTargetException
    //   0	16	142	java/text/ParseException
    //   218	249	260	java/lang/reflect/InvocationTargetException
  }
}
