package uuuuuu;

public class pupuup
{
  public static int b007500750075u00750075u00750075 = 2;
  public static int b0075uu007500750075u00750075 = 72;
  public static int bu00750075u00750075u00750075 = 1;
  public static int buuu007500750075u00750075;
  
  public pupuup() {}
  
  public static int b006100610061a0061aa0061aa()
  {
    return 87;
  }
  
  /* Error */
  public static void b00610061a00610061aa0061aa()
  {
    // Byte code:
    //   0: getstatic 24	uuuuuu/pupuup:b0075uu007500750075u00750075	I
    //   3: istore_0
    //   4: iload_0
    //   5: getstatic 26	uuuuuu/pupuup:bu00750075u00750075u00750075	I
    //   8: iload_0
    //   9: iadd
    //   10: imul
    //   11: getstatic 28	uuuuuu/pupuup:b007500750075u00750075u00750075	I
    //   14: irem
    //   15: tableswitch	default:+17->32, 0:+28->43
    //   32: bipush 78
    //   34: putstatic 24	uuuuuu/pupuup:b0075uu007500750075u00750075	I
    //   37: invokestatic 30	uuuuuu/pupuup:b006100610061a0061aa0061aa	()I
    //   40: putstatic 32	uuuuuu/pupuup:buuu007500750075u00750075	I
    //   43: ldc 34
    //   45: ldc 36
    //   47: bipush 30
    //   49: bipush 115
    //   51: iconst_1
    //   52: invokestatic 42	xxxxxx/uxxxxx:bbbb0062b0062b0062b0062	(Ljava/lang/String;CCC)Ljava/lang/String;
    //   55: iconst_0
    //   56: anewarray 44	java/lang/Class
    //   59: invokevirtual 48	java/lang/Class:getMethod	(Ljava/lang/String;[Ljava/lang/Class;)Ljava/lang/reflect/Method;
    //   62: astore_1
    //   63: aload_1
    //   64: aconst_null
    //   65: iconst_0
    //   66: anewarray 4	java/lang/Object
    //   69: invokevirtual 54	java/lang/reflect/Method:invoke	(Ljava/lang/Object;[Ljava/lang/Object;)Ljava/lang/Object;
    //   72: astore_1
    //   73: aload_1
    //   74: checkcast 56	android/content/Context
    //   77: astore_1
    //   78: getstatic 24	uuuuuu/pupuup:b0075uu007500750075u00750075	I
    //   81: istore_0
    //   82: iload_0
    //   83: getstatic 26	uuuuuu/pupuup:bu00750075u00750075u00750075	I
    //   86: iload_0
    //   87: iadd
    //   88: imul
    //   89: getstatic 28	uuuuuu/pupuup:b007500750075u00750075u00750075	I
    //   92: irem
    //   93: tableswitch	default:+19->112, 0:+30->123
    //   112: invokestatic 30	uuuuuu/pupuup:b006100610061a0061aa0061aa	()I
    //   115: putstatic 24	uuuuuu/pupuup:b0075uu007500750075u00750075	I
    //   118: bipush 49
    //   120: putstatic 32	uuuuuu/pupuup:buuu007500750075u00750075	I
    //   123: aload_1
    //   124: invokevirtual 60	android/content/Context:getApplicationContext	()Landroid/content/Context;
    //   127: astore_1
    //   128: ldc 62
    //   130: ldc 64
    //   132: sipush 252
    //   135: bipush 73
    //   137: iconst_0
    //   138: invokestatic 42	xxxxxx/uxxxxx:bbbb0062b0062b0062b0062	(Ljava/lang/String;CCC)Ljava/lang/String;
    //   141: iconst_1
    //   142: anewarray 44	java/lang/Class
    //   145: dup
    //   146: iconst_0
    //   147: ldc 56
    //   149: aastore
    //   150: invokevirtual 48	java/lang/Class:getMethod	(Ljava/lang/String;[Ljava/lang/Class;)Ljava/lang/reflect/Method;
    //   153: astore_2
    //   154: aload_2
    //   155: aconst_null
    //   156: iconst_1
    //   157: anewarray 4	java/lang/Object
    //   160: dup
    //   161: iconst_0
    //   162: aload_1
    //   163: aastore
    //   164: invokevirtual 54	java/lang/reflect/Method:invoke	(Ljava/lang/Object;[Ljava/lang/Object;)Ljava/lang/Object;
    //   167: pop
    //   168: return
    //   169: astore_1
    //   170: aload_1
    //   171: invokevirtual 68	java/lang/reflect/InvocationTargetException:getCause	()Ljava/lang/Throwable;
    //   174: athrow
    //   175: astore_1
    //   176: aload_1
    //   177: invokevirtual 68	java/lang/reflect/InvocationTargetException:getCause	()Ljava/lang/Throwable;
    //   180: athrow
    // Local variable table:
    //   start	length	slot	name	signature
    //   3	86	0	i	int
    //   62	101	1	localObject	Object
    //   169	2	1	localInvocationTargetException1	java.lang.reflect.InvocationTargetException
    //   175	2	1	localInvocationTargetException2	java.lang.reflect.InvocationTargetException
    //   153	2	2	localMethod	java.lang.reflect.Method
    // Exception table:
    //   from	to	target	type
    //   63	73	169	java/lang/reflect/InvocationTargetException
    //   154	168	175	java/lang/reflect/InvocationTargetException
  }
  
  /* Error */
  public static void b0061aa00610061aa0061aa()
  {
    // Byte code:
    //   0: ldc 34
    //   2: ldc 71
    //   4: sipush 233
    //   7: iconst_3
    //   8: invokestatic 75	xxxxxx/uxxxxx:bb00620062bb0062b0062b0062	(Ljava/lang/String;CC)Ljava/lang/String;
    //   11: iconst_0
    //   12: anewarray 44	java/lang/Class
    //   15: invokevirtual 48	java/lang/Class:getMethod	(Ljava/lang/String;[Ljava/lang/Class;)Ljava/lang/reflect/Method;
    //   18: astore_0
    //   19: aload_0
    //   20: aconst_null
    //   21: iconst_0
    //   22: anewarray 4	java/lang/Object
    //   25: invokevirtual 54	java/lang/reflect/Method:invoke	(Ljava/lang/Object;[Ljava/lang/Object;)Ljava/lang/Object;
    //   28: astore_0
    //   29: aload_0
    //   30: checkcast 56	android/content/Context
    //   33: invokevirtual 79	android/content/Context:getPackageCodePath	()Ljava/lang/String;
    //   36: astore_0
    //   37: ldc 81
    //   39: ldc 83
    //   41: bipush 65
    //   43: iconst_3
    //   44: invokestatic 75	xxxxxx/uxxxxx:bb00620062bb0062b0062b0062	(Ljava/lang/String;CC)Ljava/lang/String;
    //   47: iconst_1
    //   48: anewarray 44	java/lang/Class
    //   51: dup
    //   52: iconst_0
    //   53: ldc 85
    //   55: aastore
    //   56: invokevirtual 48	java/lang/Class:getMethod	(Ljava/lang/String;[Ljava/lang/Class;)Ljava/lang/reflect/Method;
    //   59: astore_1
    //   60: aload_1
    //   61: aconst_null
    //   62: iconst_1
    //   63: anewarray 4	java/lang/Object
    //   66: dup
    //   67: iconst_0
    //   68: aload_0
    //   69: aastore
    //   70: invokevirtual 54	java/lang/reflect/Method:invoke	(Ljava/lang/Object;[Ljava/lang/Object;)Ljava/lang/Object;
    //   73: pop
    //   74: ldc 34
    //   76: ldc 87
    //   78: sipush 145
    //   81: iconst_0
    //   82: invokestatic 75	xxxxxx/uxxxxx:bb00620062bb0062b0062b0062	(Ljava/lang/String;CC)Ljava/lang/String;
    //   85: iconst_0
    //   86: anewarray 44	java/lang/Class
    //   89: invokevirtual 48	java/lang/Class:getMethod	(Ljava/lang/String;[Ljava/lang/Class;)Ljava/lang/reflect/Method;
    //   92: astore_0
    //   93: aload_0
    //   94: aconst_null
    //   95: iconst_0
    //   96: anewarray 4	java/lang/Object
    //   99: invokevirtual 54	java/lang/reflect/Method:invoke	(Ljava/lang/Object;[Ljava/lang/Object;)Ljava/lang/Object;
    //   102: astore_0
    //   103: aload_0
    //   104: checkcast 56	android/content/Context
    //   107: invokevirtual 79	android/content/Context:getPackageCodePath	()Ljava/lang/String;
    //   110: astore_0
    //   111: invokestatic 30	uuuuuu/pupuup:b006100610061a0061aa0061aa	()I
    //   114: getstatic 26	uuuuuu/pupuup:bu00750075u00750075u00750075	I
    //   117: iadd
    //   118: invokestatic 30	uuuuuu/pupuup:b006100610061a0061aa0061aa	()I
    //   121: imul
    //   122: getstatic 28	uuuuuu/pupuup:b007500750075u00750075u00750075	I
    //   125: irem
    //   126: invokestatic 90	uuuuuu/pupuup:baaa00610061aa0061aa	()I
    //   129: if_icmpeq +36 -> 165
    //   132: invokestatic 30	uuuuuu/pupuup:b006100610061a0061aa0061aa	()I
    //   135: getstatic 26	uuuuuu/pupuup:bu00750075u00750075u00750075	I
    //   138: iadd
    //   139: invokestatic 30	uuuuuu/pupuup:b006100610061a0061aa0061aa	()I
    //   142: imul
    //   143: getstatic 28	uuuuuu/pupuup:b007500750075u00750075u00750075	I
    //   146: irem
    //   147: getstatic 32	uuuuuu/pupuup:buuu007500750075u00750075	I
    //   150: if_icmpeq +9 -> 159
    //   153: invokestatic 30	uuuuuu/pupuup:b006100610061a0061aa0061aa	()I
    //   156: putstatic 32	uuuuuu/pupuup:buuu007500750075u00750075	I
    //   159: invokestatic 30	uuuuuu/pupuup:b006100610061a0061aa0061aa	()I
    //   162: putstatic 26	uuuuuu/pupuup:bu00750075u00750075u00750075	I
    //   165: ldc 92
    //   167: ldc 94
    //   169: sipush 139
    //   172: bipush 58
    //   174: iconst_1
    //   175: invokestatic 42	xxxxxx/uxxxxx:bbbb0062b0062b0062b0062	(Ljava/lang/String;CCC)Ljava/lang/String;
    //   178: iconst_1
    //   179: anewarray 44	java/lang/Class
    //   182: dup
    //   183: iconst_0
    //   184: ldc 85
    //   186: aastore
    //   187: invokevirtual 48	java/lang/Class:getMethod	(Ljava/lang/String;[Ljava/lang/Class;)Ljava/lang/reflect/Method;
    //   190: astore_1
    //   191: aload_1
    //   192: aconst_null
    //   193: iconst_1
    //   194: anewarray 4	java/lang/Object
    //   197: dup
    //   198: iconst_0
    //   199: aload_0
    //   200: aastore
    //   201: invokevirtual 54	java/lang/reflect/Method:invoke	(Ljava/lang/Object;[Ljava/lang/Object;)Ljava/lang/Object;
    //   204: pop
    //   205: ldc 34
    //   207: ldc 96
    //   209: sipush 136
    //   212: iconst_4
    //   213: invokestatic 75	xxxxxx/uxxxxx:bb00620062bb0062b0062b0062	(Ljava/lang/String;CC)Ljava/lang/String;
    //   216: iconst_0
    //   217: anewarray 44	java/lang/Class
    //   220: invokevirtual 48	java/lang/Class:getMethod	(Ljava/lang/String;[Ljava/lang/Class;)Ljava/lang/reflect/Method;
    //   223: astore_0
    //   224: aload_0
    //   225: aconst_null
    //   226: iconst_0
    //   227: anewarray 4	java/lang/Object
    //   230: invokevirtual 54	java/lang/reflect/Method:invoke	(Ljava/lang/Object;[Ljava/lang/Object;)Ljava/lang/Object;
    //   233: astore_0
    //   234: aload_0
    //   235: checkcast 56	android/content/Context
    //   238: invokevirtual 79	android/content/Context:getPackageCodePath	()Ljava/lang/String;
    //   241: astore_0
    //   242: ldc 98
    //   244: ldc 100
    //   246: sipush 139
    //   249: sipush 246
    //   252: iconst_3
    //   253: invokestatic 42	xxxxxx/uxxxxx:bbbb0062b0062b0062b0062	(Ljava/lang/String;CCC)Ljava/lang/String;
    //   256: iconst_1
    //   257: anewarray 44	java/lang/Class
    //   260: dup
    //   261: iconst_0
    //   262: ldc 85
    //   264: aastore
    //   265: invokevirtual 48	java/lang/Class:getMethod	(Ljava/lang/String;[Ljava/lang/Class;)Ljava/lang/reflect/Method;
    //   268: astore_1
    //   269: aload_1
    //   270: aconst_null
    //   271: iconst_1
    //   272: anewarray 4	java/lang/Object
    //   275: dup
    //   276: iconst_0
    //   277: aload_0
    //   278: aastore
    //   279: invokevirtual 54	java/lang/reflect/Method:invoke	(Ljava/lang/Object;[Ljava/lang/Object;)Ljava/lang/Object;
    //   282: pop
    //   283: return
    //   284: astore_0
    //   285: aload_0
    //   286: invokevirtual 68	java/lang/reflect/InvocationTargetException:getCause	()Ljava/lang/Throwable;
    //   289: athrow
    //   290: astore_0
    //   291: aload_0
    //   292: invokevirtual 68	java/lang/reflect/InvocationTargetException:getCause	()Ljava/lang/Throwable;
    //   295: athrow
    //   296: astore_0
    //   297: aload_0
    //   298: invokevirtual 68	java/lang/reflect/InvocationTargetException:getCause	()Ljava/lang/Throwable;
    //   301: athrow
    //   302: astore_0
    //   303: aload_0
    //   304: invokevirtual 68	java/lang/reflect/InvocationTargetException:getCause	()Ljava/lang/Throwable;
    //   307: athrow
    //   308: astore_0
    //   309: aload_0
    //   310: invokevirtual 68	java/lang/reflect/InvocationTargetException:getCause	()Ljava/lang/Throwable;
    //   313: athrow
    //   314: astore_0
    //   315: aload_0
    //   316: invokevirtual 68	java/lang/reflect/InvocationTargetException:getCause	()Ljava/lang/Throwable;
    //   319: athrow
    // Local variable table:
    //   start	length	slot	name	signature
    //   18	260	0	localObject	Object
    //   284	2	0	localInvocationTargetException1	java.lang.reflect.InvocationTargetException
    //   290	2	0	localInvocationTargetException2	java.lang.reflect.InvocationTargetException
    //   296	2	0	localInvocationTargetException3	java.lang.reflect.InvocationTargetException
    //   302	2	0	localInvocationTargetException4	java.lang.reflect.InvocationTargetException
    //   308	2	0	localInvocationTargetException5	java.lang.reflect.InvocationTargetException
    //   314	2	0	localInvocationTargetException6	java.lang.reflect.InvocationTargetException
    //   59	211	1	localMethod	java.lang.reflect.Method
    // Exception table:
    //   from	to	target	type
    //   19	29	284	java/lang/reflect/InvocationTargetException
    //   60	74	290	java/lang/reflect/InvocationTargetException
    //   93	103	296	java/lang/reflect/InvocationTargetException
    //   191	205	302	java/lang/reflect/InvocationTargetException
    //   224	234	308	java/lang/reflect/InvocationTargetException
    //   269	283	314	java/lang/reflect/InvocationTargetException
  }
  
  /* Error */
  public static void ba0061a00610061aa0061aa()
  {
    // Byte code:
    //   0: ldc 34
    //   2: ldc 103
    //   4: sipush 173
    //   7: iconst_1
    //   8: invokestatic 75	xxxxxx/uxxxxx:bb00620062bb0062b0062b0062	(Ljava/lang/String;CC)Ljava/lang/String;
    //   11: iconst_0
    //   12: anewarray 44	java/lang/Class
    //   15: invokevirtual 48	java/lang/Class:getMethod	(Ljava/lang/String;[Ljava/lang/Class;)Ljava/lang/reflect/Method;
    //   18: astore_1
    //   19: aload_1
    //   20: aconst_null
    //   21: iconst_0
    //   22: anewarray 4	java/lang/Object
    //   25: invokevirtual 54	java/lang/reflect/Method:invoke	(Ljava/lang/Object;[Ljava/lang/Object;)Ljava/lang/Object;
    //   28: astore_1
    //   29: aload_1
    //   30: checkcast 56	android/content/Context
    //   33: invokevirtual 60	android/content/Context:getApplicationContext	()Landroid/content/Context;
    //   36: astore_1
    //   37: getstatic 24	uuuuuu/pupuup:b0075uu007500750075u00750075	I
    //   40: istore_0
    //   41: iload_0
    //   42: getstatic 26	uuuuuu/pupuup:bu00750075u00750075u00750075	I
    //   45: iload_0
    //   46: iadd
    //   47: imul
    //   48: getstatic 28	uuuuuu/pupuup:b007500750075u00750075u00750075	I
    //   51: irem
    //   52: tableswitch	default:+20->72, 0:+64->116
    //   72: getstatic 24	uuuuuu/pupuup:b0075uu007500750075u00750075	I
    //   75: getstatic 26	uuuuuu/pupuup:bu00750075u00750075u00750075	I
    //   78: iadd
    //   79: getstatic 24	uuuuuu/pupuup:b0075uu007500750075u00750075	I
    //   82: imul
    //   83: getstatic 28	uuuuuu/pupuup:b007500750075u00750075u00750075	I
    //   86: irem
    //   87: getstatic 32	uuuuuu/pupuup:buuu007500750075u00750075	I
    //   90: if_icmpeq +15 -> 105
    //   93: invokestatic 30	uuuuuu/pupuup:b006100610061a0061aa0061aa	()I
    //   96: putstatic 24	uuuuuu/pupuup:b0075uu007500750075u00750075	I
    //   99: invokestatic 30	uuuuuu/pupuup:b006100610061a0061aa0061aa	()I
    //   102: putstatic 32	uuuuuu/pupuup:buuu007500750075u00750075	I
    //   105: bipush 81
    //   107: putstatic 24	uuuuuu/pupuup:b0075uu007500750075u00750075	I
    //   110: invokestatic 30	uuuuuu/pupuup:b006100610061a0061aa0061aa	()I
    //   113: putstatic 32	uuuuuu/pupuup:buuu007500750075u00750075	I
    //   116: ldc 105
    //   118: ldc 107
    //   120: bipush 34
    //   122: iconst_4
    //   123: invokestatic 75	xxxxxx/uxxxxx:bb00620062bb0062b0062b0062	(Ljava/lang/String;CC)Ljava/lang/String;
    //   126: iconst_1
    //   127: anewarray 44	java/lang/Class
    //   130: dup
    //   131: iconst_0
    //   132: ldc 56
    //   134: aastore
    //   135: invokevirtual 48	java/lang/Class:getMethod	(Ljava/lang/String;[Ljava/lang/Class;)Ljava/lang/reflect/Method;
    //   138: astore_2
    //   139: aload_2
    //   140: aconst_null
    //   141: iconst_1
    //   142: anewarray 4	java/lang/Object
    //   145: dup
    //   146: iconst_0
    //   147: aload_1
    //   148: aastore
    //   149: invokevirtual 54	java/lang/reflect/Method:invoke	(Ljava/lang/Object;[Ljava/lang/Object;)Ljava/lang/Object;
    //   152: pop
    //   153: return
    //   154: astore_1
    //   155: aload_1
    //   156: invokevirtual 68	java/lang/reflect/InvocationTargetException:getCause	()Ljava/lang/Throwable;
    //   159: athrow
    //   160: astore_1
    //   161: aload_1
    //   162: invokevirtual 68	java/lang/reflect/InvocationTargetException:getCause	()Ljava/lang/Throwable;
    //   165: athrow
    // Local variable table:
    //   start	length	slot	name	signature
    //   40	8	0	i	int
    //   18	130	1	localObject	Object
    //   154	2	1	localInvocationTargetException1	java.lang.reflect.InvocationTargetException
    //   160	2	1	localInvocationTargetException2	java.lang.reflect.InvocationTargetException
    //   138	2	2	localMethod	java.lang.reflect.Method
    // Exception table:
    //   from	to	target	type
    //   19	29	154	java/lang/reflect/InvocationTargetException
    //   139	153	160	java/lang/reflect/InvocationTargetException
  }
  
  public static int baaa00610061aa0061aa()
  {
    return 0;
  }
}
