package uuuuuu;

public abstract class qppppp<V extends mmbbbb.mbbbbb>
  extends ssssst<V>
{
  public static int b0073007300730073ss00730073s = 73;
  public static int b0073sss0073s00730073s = 2;
  public static int bs0073ss0073s00730073s = 1;
  public static int bssss0073s00730073s;
  
  public qppppp() {}
  
  public static int b006F006F006Fo006F006Fo006F006F006F()
  {
    return 46;
  }
  
  public static int b006Foo006F006F006Fo006F006F006F()
  {
    return 1;
  }
  
  public static int booo006F006F006Fo006F006F006F()
  {
    return 2;
  }
  
  /* Error */
  public void b006F006Fo006F006F006Fo006F006F006F(com.db.pwcc.dbmobile.model.error.DbErrorCode paramDbErrorCode, boolean paramBoolean, android.content.DialogInterface.OnClickListener paramOnClickListener)
  {
    // Byte code:
    //   0: aload_1
    //   1: getstatic 32	com/db/pwcc/dbmobile/model/error/DbErrorCode:INSECURE_CONNECTION_ERROR	Lcom/db/pwcc/dbmobile/model/error/DbErrorCode;
    //   4: if_acmpne +227 -> 231
    //   7: getstatic 34	uuuuuu/qppppp:b0073007300730073ss00730073s	I
    //   10: istore 4
    //   12: iload 4
    //   14: getstatic 36	uuuuuu/qppppp:bs0073ss0073s00730073s	I
    //   17: iload 4
    //   19: iadd
    //   20: imul
    //   21: getstatic 38	uuuuuu/qppppp:b0073sss0073s00730073s	I
    //   24: irem
    //   25: tableswitch	default:+19->44, 0:+104->129
    //   44: ldc 2
    //   46: ldc 40
    //   48: sipush 225
    //   51: iconst_0
    //   52: invokestatic 46	xxxxxx/uxxxxx:bb00620062bb0062b0062b0062	(Ljava/lang/String;CC)Ljava/lang/String;
    //   55: iconst_0
    //   56: anewarray 48	java/lang/Class
    //   59: invokevirtual 52	java/lang/Class:getMethod	(Ljava/lang/String;[Ljava/lang/Class;)Ljava/lang/reflect/Method;
    //   62: astore 7
    //   64: aload 7
    //   66: aconst_null
    //   67: iconst_0
    //   68: anewarray 54	java/lang/Object
    //   71: invokevirtual 60	java/lang/reflect/Method:invoke	(Ljava/lang/Object;[Ljava/lang/Object;)Ljava/lang/Object;
    //   74: astore 7
    //   76: aload 7
    //   78: checkcast 62	java/lang/Integer
    //   81: invokevirtual 65	java/lang/Integer:intValue	()I
    //   84: putstatic 34	uuuuuu/qppppp:b0073007300730073ss00730073s	I
    //   87: ldc 2
    //   89: ldc 67
    //   91: bipush 55
    //   93: iconst_1
    //   94: invokestatic 46	xxxxxx/uxxxxx:bb00620062bb0062b0062b0062	(Ljava/lang/String;CC)Ljava/lang/String;
    //   97: iconst_0
    //   98: anewarray 48	java/lang/Class
    //   101: invokevirtual 52	java/lang/Class:getMethod	(Ljava/lang/String;[Ljava/lang/Class;)Ljava/lang/reflect/Method;
    //   104: astore 7
    //   106: aload 7
    //   108: aconst_null
    //   109: iconst_0
    //   110: anewarray 54	java/lang/Object
    //   113: invokevirtual 60	java/lang/reflect/Method:invoke	(Ljava/lang/Object;[Ljava/lang/Object;)Ljava/lang/Object;
    //   116: astore 7
    //   118: aload 7
    //   120: checkcast 62	java/lang/Integer
    //   123: invokevirtual 65	java/lang/Integer:intValue	()I
    //   126: putstatic 69	uuuuuu/qppppp:bssss0073s00730073s	I
    //   129: aload_0
    //   130: getfield 73	uuuuuu/qppppp:bnnnnn006E006E006En	Luuuuuu/ttssst$tsssst;
    //   133: checkcast 75	uuuuuu/mmbbbb$mbbbbb
    //   136: aload_3
    //   137: invokeinterface 79 2 0
    //   142: getstatic 85	uuuuuu/vvrvrv:bh00680068h0068h0068h0068	Luuuuuu/vvrvrv;
    //   145: invokestatic 91	uuuuuu/rrvvrv:b00710071qqq0071q0071q0071	(Luuuuuu/vvrvrv;)V
    //   148: getstatic 34	uuuuuu/qppppp:b0073007300730073ss00730073s	I
    //   151: istore 4
    //   153: iload 4
    //   155: getstatic 36	uuuuuu/qppppp:bs0073ss0073s00730073s	I
    //   158: iload 4
    //   160: iadd
    //   161: imul
    //   162: getstatic 38	uuuuuu/qppppp:b0073sss0073s00730073s	I
    //   165: irem
    //   166: tableswitch	default:+18->184, 0:+65->231
    //   184: bipush 39
    //   186: putstatic 34	uuuuuu/qppppp:b0073007300730073ss00730073s	I
    //   189: ldc 2
    //   191: ldc 93
    //   193: bipush 58
    //   195: iconst_2
    //   196: invokestatic 46	xxxxxx/uxxxxx:bb00620062bb0062b0062b0062	(Ljava/lang/String;CC)Ljava/lang/String;
    //   199: iconst_0
    //   200: anewarray 48	java/lang/Class
    //   203: invokevirtual 52	java/lang/Class:getMethod	(Ljava/lang/String;[Ljava/lang/Class;)Ljava/lang/reflect/Method;
    //   206: astore 7
    //   208: aload 7
    //   210: aconst_null
    //   211: iconst_0
    //   212: anewarray 54	java/lang/Object
    //   215: invokevirtual 60	java/lang/reflect/Method:invoke	(Ljava/lang/Object;[Ljava/lang/Object;)Ljava/lang/Object;
    //   218: astore 7
    //   220: aload 7
    //   222: checkcast 62	java/lang/Integer
    //   225: invokevirtual 65	java/lang/Integer:intValue	()I
    //   228: putstatic 69	uuuuuu/qppppp:bssss0073s00730073s	I
    //   231: aload_1
    //   232: getstatic 96	com/db/pwcc/dbmobile/model/error/DbErrorCode:NO_INTERNET_ERROR	Lcom/db/pwcc/dbmobile/model/error/DbErrorCode;
    //   235: if_acmpne +251 -> 486
    //   238: getstatic 34	uuuuuu/qppppp:b0073007300730073ss00730073s	I
    //   241: istore 4
    //   243: getstatic 36	uuuuuu/qppppp:bs0073ss0073s00730073s	I
    //   246: istore 5
    //   248: ldc 2
    //   250: ldc 98
    //   252: bipush 101
    //   254: sipush 180
    //   257: iconst_1
    //   258: invokestatic 102	xxxxxx/uxxxxx:bbbb0062b0062b0062b0062	(Ljava/lang/String;CCC)Ljava/lang/String;
    //   261: iconst_0
    //   262: anewarray 48	java/lang/Class
    //   265: invokevirtual 52	java/lang/Class:getMethod	(Ljava/lang/String;[Ljava/lang/Class;)Ljava/lang/reflect/Method;
    //   268: astore_1
    //   269: aload_1
    //   270: aconst_null
    //   271: iconst_0
    //   272: anewarray 54	java/lang/Object
    //   275: invokevirtual 60	java/lang/reflect/Method:invoke	(Ljava/lang/Object;[Ljava/lang/Object;)Ljava/lang/Object;
    //   278: astore_1
    //   279: aload_1
    //   280: checkcast 62	java/lang/Integer
    //   283: invokevirtual 65	java/lang/Integer:intValue	()I
    //   286: istore 6
    //   288: iload 6
    //   290: getstatic 36	uuuuuu/qppppp:bs0073ss0073s00730073s	I
    //   293: iload 6
    //   295: iadd
    //   296: imul
    //   297: getstatic 38	uuuuuu/qppppp:b0073sss0073s00730073s	I
    //   300: irem
    //   301: tableswitch	default:+19->320, 0:+63->364
    //   320: ldc 2
    //   322: ldc 104
    //   324: sipush 179
    //   327: iconst_3
    //   328: invokestatic 46	xxxxxx/uxxxxx:bb00620062bb0062b0062b0062	(Ljava/lang/String;CC)Ljava/lang/String;
    //   331: iconst_0
    //   332: anewarray 48	java/lang/Class
    //   335: invokevirtual 52	java/lang/Class:getMethod	(Ljava/lang/String;[Ljava/lang/Class;)Ljava/lang/reflect/Method;
    //   338: astore_1
    //   339: aload_1
    //   340: aconst_null
    //   341: iconst_0
    //   342: anewarray 54	java/lang/Object
    //   345: invokevirtual 60	java/lang/reflect/Method:invoke	(Ljava/lang/Object;[Ljava/lang/Object;)Ljava/lang/Object;
    //   348: astore_1
    //   349: aload_1
    //   350: checkcast 62	java/lang/Integer
    //   353: invokevirtual 65	java/lang/Integer:intValue	()I
    //   356: putstatic 34	uuuuuu/qppppp:b0073007300730073ss00730073s	I
    //   359: bipush 97
    //   361: putstatic 69	uuuuuu/qppppp:bssss0073s00730073s	I
    //   364: iload 4
    //   366: iload 4
    //   368: iload 5
    //   370: iadd
    //   371: imul
    //   372: getstatic 38	uuuuuu/qppppp:b0073sss0073s00730073s	I
    //   375: irem
    //   376: tableswitch	default:+20->396, 0:+96->472
    //   396: ldc 2
    //   398: ldc 106
    //   400: bipush 76
    //   402: iconst_2
    //   403: invokestatic 46	xxxxxx/uxxxxx:bb00620062bb0062b0062b0062	(Ljava/lang/String;CC)Ljava/lang/String;
    //   406: iconst_0
    //   407: anewarray 48	java/lang/Class
    //   410: invokevirtual 52	java/lang/Class:getMethod	(Ljava/lang/String;[Ljava/lang/Class;)Ljava/lang/reflect/Method;
    //   413: astore_1
    //   414: aload_1
    //   415: aconst_null
    //   416: iconst_0
    //   417: anewarray 54	java/lang/Object
    //   420: invokevirtual 60	java/lang/reflect/Method:invoke	(Ljava/lang/Object;[Ljava/lang/Object;)Ljava/lang/Object;
    //   423: astore_1
    //   424: aload_1
    //   425: checkcast 62	java/lang/Integer
    //   428: invokevirtual 65	java/lang/Integer:intValue	()I
    //   431: putstatic 34	uuuuuu/qppppp:b0073007300730073ss00730073s	I
    //   434: ldc 2
    //   436: ldc 108
    //   438: bipush 81
    //   440: iconst_2
    //   441: invokestatic 46	xxxxxx/uxxxxx:bb00620062bb0062b0062b0062	(Ljava/lang/String;CC)Ljava/lang/String;
    //   444: iconst_0
    //   445: anewarray 48	java/lang/Class
    //   448: invokevirtual 52	java/lang/Class:getMethod	(Ljava/lang/String;[Ljava/lang/Class;)Ljava/lang/reflect/Method;
    //   451: astore_1
    //   452: aload_1
    //   453: aconst_null
    //   454: iconst_0
    //   455: anewarray 54	java/lang/Object
    //   458: invokevirtual 60	java/lang/reflect/Method:invoke	(Ljava/lang/Object;[Ljava/lang/Object;)Ljava/lang/Object;
    //   461: astore_1
    //   462: aload_1
    //   463: checkcast 62	java/lang/Integer
    //   466: invokevirtual 65	java/lang/Integer:intValue	()I
    //   469: putstatic 69	uuuuuu/qppppp:bssss0073s00730073s	I
    //   472: aload_0
    //   473: getfield 73	uuuuuu/qppppp:bnnnnn006E006E006En	Luuuuuu/ttssst$tsssst;
    //   476: checkcast 75	uuuuuu/mmbbbb$mbbbbb
    //   479: iload_2
    //   480: aload_3
    //   481: invokeinterface 112 3 0
    //   486: return
    //   487: astore_1
    //   488: aload_1
    //   489: invokevirtual 116	java/lang/reflect/InvocationTargetException:getCause	()Ljava/lang/Throwable;
    //   492: athrow
    //   493: astore_1
    //   494: aload_1
    //   495: invokevirtual 116	java/lang/reflect/InvocationTargetException:getCause	()Ljava/lang/Throwable;
    //   498: athrow
    //   499: astore_1
    //   500: aload_1
    //   501: invokevirtual 116	java/lang/reflect/InvocationTargetException:getCause	()Ljava/lang/Throwable;
    //   504: athrow
    //   505: astore_1
    //   506: aload_1
    //   507: invokevirtual 116	java/lang/reflect/InvocationTargetException:getCause	()Ljava/lang/Throwable;
    //   510: athrow
    //   511: astore_1
    //   512: aload_1
    //   513: invokevirtual 116	java/lang/reflect/InvocationTargetException:getCause	()Ljava/lang/Throwable;
    //   516: athrow
    //   517: astore_1
    //   518: aload_1
    //   519: invokevirtual 116	java/lang/reflect/InvocationTargetException:getCause	()Ljava/lang/Throwable;
    //   522: athrow
    //   523: astore_1
    //   524: aload_1
    //   525: invokevirtual 116	java/lang/reflect/InvocationTargetException:getCause	()Ljava/lang/Throwable;
    //   528: athrow
    // Local variable table:
    //   start	length	slot	name	signature
    //   0	529	0	this	qppppp
    //   0	529	1	paramDbErrorCode	com.db.pwcc.dbmobile.model.error.DbErrorCode
    //   0	529	2	paramBoolean	boolean
    //   0	529	3	paramOnClickListener	android.content.DialogInterface.OnClickListener
    //   10	362	4	i	int
    //   246	125	5	j	int
    //   286	11	6	k	int
    //   62	159	7	localObject	Object
    // Exception table:
    //   from	to	target	type
    //   208	220	487	java/lang/reflect/InvocationTargetException
    //   414	424	493	java/lang/reflect/InvocationTargetException
    //   452	462	499	java/lang/reflect/InvocationTargetException
    //   269	279	505	java/lang/reflect/InvocationTargetException
    //   339	349	511	java/lang/reflect/InvocationTargetException
    //   64	76	517	java/lang/reflect/InvocationTargetException
    //   106	118	523	java/lang/reflect/InvocationTargetException
  }
  
  /* Error */
  public void bo006Fo006F006F006Fo006F006F006F(com.db.pwcc.dbmobile.model.error.DbErrorCode paramDbErrorCode)
  {
    // Byte code:
    //   0: getstatic 34	uuuuuu/qppppp:b0073007300730073ss00730073s	I
    //   3: istore_2
    //   4: ldc 2
    //   6: ldc 120
    //   8: bipush 85
    //   10: iconst_5
    //   11: invokestatic 46	xxxxxx/uxxxxx:bb00620062bb0062b0062b0062	(Ljava/lang/String;CC)Ljava/lang/String;
    //   14: iconst_0
    //   15: anewarray 48	java/lang/Class
    //   18: invokevirtual 52	java/lang/Class:getMethod	(Ljava/lang/String;[Ljava/lang/Class;)Ljava/lang/reflect/Method;
    //   21: astore 5
    //   23: aload 5
    //   25: aconst_null
    //   26: iconst_0
    //   27: anewarray 54	java/lang/Object
    //   30: invokevirtual 60	java/lang/reflect/Method:invoke	(Ljava/lang/Object;[Ljava/lang/Object;)Ljava/lang/Object;
    //   33: astore 5
    //   35: aload 5
    //   37: checkcast 62	java/lang/Integer
    //   40: invokevirtual 65	java/lang/Integer:intValue	()I
    //   43: iload_2
    //   44: iadd
    //   45: getstatic 34	uuuuuu/qppppp:b0073007300730073ss00730073s	I
    //   48: imul
    //   49: getstatic 38	uuuuuu/qppppp:b0073sss0073s00730073s	I
    //   52: irem
    //   53: getstatic 69	uuuuuu/qppppp:bssss0073s00730073s	I
    //   56: if_icmpeq +50 -> 106
    //   59: iconst_0
    //   60: putstatic 34	uuuuuu/qppppp:b0073007300730073ss00730073s	I
    //   63: ldc 2
    //   65: ldc 122
    //   67: sipush 236
    //   70: iconst_3
    //   71: invokestatic 46	xxxxxx/uxxxxx:bb00620062bb0062b0062b0062	(Ljava/lang/String;CC)Ljava/lang/String;
    //   74: iconst_0
    //   75: anewarray 48	java/lang/Class
    //   78: invokevirtual 52	java/lang/Class:getMethod	(Ljava/lang/String;[Ljava/lang/Class;)Ljava/lang/reflect/Method;
    //   81: astore 5
    //   83: aload 5
    //   85: aconst_null
    //   86: iconst_0
    //   87: anewarray 54	java/lang/Object
    //   90: invokevirtual 60	java/lang/reflect/Method:invoke	(Ljava/lang/Object;[Ljava/lang/Object;)Ljava/lang/Object;
    //   93: astore 5
    //   95: aload 5
    //   97: checkcast 62	java/lang/Integer
    //   100: invokevirtual 65	java/lang/Integer:intValue	()I
    //   103: putstatic 69	uuuuuu/qppppp:bssss0073s00730073s	I
    //   106: getstatic 34	uuuuuu/qppppp:b0073007300730073ss00730073s	I
    //   109: istore_2
    //   110: getstatic 36	uuuuuu/qppppp:bs0073ss0073s00730073s	I
    //   113: istore_3
    //   114: getstatic 34	uuuuuu/qppppp:b0073007300730073ss00730073s	I
    //   117: istore 4
    //   119: ldc 2
    //   121: ldc 124
    //   123: sipush 211
    //   126: sipush 136
    //   129: iconst_0
    //   130: invokestatic 102	xxxxxx/uxxxxx:bbbb0062b0062b0062b0062	(Ljava/lang/String;CCC)Ljava/lang/String;
    //   133: iconst_0
    //   134: anewarray 48	java/lang/Class
    //   137: invokevirtual 52	java/lang/Class:getMethod	(Ljava/lang/String;[Ljava/lang/Class;)Ljava/lang/reflect/Method;
    //   140: astore 5
    //   142: aload 5
    //   144: aconst_null
    //   145: iconst_0
    //   146: anewarray 54	java/lang/Object
    //   149: invokevirtual 60	java/lang/reflect/Method:invoke	(Ljava/lang/Object;[Ljava/lang/Object;)Ljava/lang/Object;
    //   152: astore 5
    //   154: iload 4
    //   156: iload_2
    //   157: iload_3
    //   158: iadd
    //   159: imul
    //   160: aload 5
    //   162: checkcast 62	java/lang/Integer
    //   165: invokevirtual 65	java/lang/Integer:intValue	()I
    //   168: irem
    //   169: getstatic 69	uuuuuu/qppppp:bssss0073s00730073s	I
    //   172: if_icmpeq +198 -> 370
    //   175: ldc 2
    //   177: ldc 126
    //   179: sipush 255
    //   182: iconst_4
    //   183: iconst_0
    //   184: invokestatic 102	xxxxxx/uxxxxx:bbbb0062b0062b0062b0062	(Ljava/lang/String;CCC)Ljava/lang/String;
    //   187: iconst_0
    //   188: anewarray 48	java/lang/Class
    //   191: invokevirtual 52	java/lang/Class:getMethod	(Ljava/lang/String;[Ljava/lang/Class;)Ljava/lang/reflect/Method;
    //   194: astore 5
    //   196: aload 5
    //   198: aconst_null
    //   199: iconst_0
    //   200: anewarray 54	java/lang/Object
    //   203: invokevirtual 60	java/lang/reflect/Method:invoke	(Ljava/lang/Object;[Ljava/lang/Object;)Ljava/lang/Object;
    //   206: astore 5
    //   208: aload 5
    //   210: checkcast 62	java/lang/Integer
    //   213: invokevirtual 65	java/lang/Integer:intValue	()I
    //   216: putstatic 34	uuuuuu/qppppp:b0073007300730073ss00730073s	I
    //   219: ldc 2
    //   221: ldc -128
    //   223: bipush 75
    //   225: sipush 142
    //   228: iconst_1
    //   229: invokestatic 102	xxxxxx/uxxxxx:bbbb0062b0062b0062b0062	(Ljava/lang/String;CCC)Ljava/lang/String;
    //   232: iconst_0
    //   233: anewarray 48	java/lang/Class
    //   236: invokevirtual 52	java/lang/Class:getMethod	(Ljava/lang/String;[Ljava/lang/Class;)Ljava/lang/reflect/Method;
    //   239: astore 5
    //   241: aload 5
    //   243: aconst_null
    //   244: iconst_0
    //   245: anewarray 54	java/lang/Object
    //   248: invokevirtual 60	java/lang/reflect/Method:invoke	(Ljava/lang/Object;[Ljava/lang/Object;)Ljava/lang/Object;
    //   251: astore 5
    //   253: aload 5
    //   255: checkcast 62	java/lang/Integer
    //   258: invokevirtual 65	java/lang/Integer:intValue	()I
    //   261: putstatic 69	uuuuuu/qppppp:bssss0073s00730073s	I
    //   264: getstatic 34	uuuuuu/qppppp:b0073007300730073ss00730073s	I
    //   267: istore_2
    //   268: ldc 2
    //   270: ldc -126
    //   272: bipush 104
    //   274: iconst_2
    //   275: invokestatic 46	xxxxxx/uxxxxx:bb00620062bb0062b0062b0062	(Ljava/lang/String;CC)Ljava/lang/String;
    //   278: iconst_0
    //   279: anewarray 48	java/lang/Class
    //   282: invokevirtual 52	java/lang/Class:getMethod	(Ljava/lang/String;[Ljava/lang/Class;)Ljava/lang/reflect/Method;
    //   285: astore 5
    //   287: aload 5
    //   289: aconst_null
    //   290: iconst_0
    //   291: anewarray 54	java/lang/Object
    //   294: invokevirtual 60	java/lang/reflect/Method:invoke	(Ljava/lang/Object;[Ljava/lang/Object;)Ljava/lang/Object;
    //   297: astore 5
    //   299: aload 5
    //   301: checkcast 62	java/lang/Integer
    //   304: invokevirtual 65	java/lang/Integer:intValue	()I
    //   307: iload_2
    //   308: iadd
    //   309: getstatic 34	uuuuuu/qppppp:b0073007300730073ss00730073s	I
    //   312: imul
    //   313: getstatic 38	uuuuuu/qppppp:b0073sss0073s00730073s	I
    //   316: irem
    //   317: getstatic 69	uuuuuu/qppppp:bssss0073s00730073s	I
    //   320: if_icmpeq +50 -> 370
    //   323: bipush 49
    //   325: putstatic 34	uuuuuu/qppppp:b0073007300730073ss00730073s	I
    //   328: ldc 2
    //   330: ldc -124
    //   332: bipush 75
    //   334: iconst_5
    //   335: invokestatic 46	xxxxxx/uxxxxx:bb00620062bb0062b0062b0062	(Ljava/lang/String;CC)Ljava/lang/String;
    //   338: iconst_0
    //   339: anewarray 48	java/lang/Class
    //   342: invokevirtual 52	java/lang/Class:getMethod	(Ljava/lang/String;[Ljava/lang/Class;)Ljava/lang/reflect/Method;
    //   345: astore 5
    //   347: aload 5
    //   349: aconst_null
    //   350: iconst_0
    //   351: anewarray 54	java/lang/Object
    //   354: invokevirtual 60	java/lang/reflect/Method:invoke	(Ljava/lang/Object;[Ljava/lang/Object;)Ljava/lang/Object;
    //   357: astore 5
    //   359: aload 5
    //   361: checkcast 62	java/lang/Integer
    //   364: invokevirtual 65	java/lang/Integer:intValue	()I
    //   367: putstatic 69	uuuuuu/qppppp:bssss0073s00730073s	I
    //   370: ldc 2
    //   372: ldc -122
    //   374: bipush 108
    //   376: iconst_4
    //   377: invokestatic 46	xxxxxx/uxxxxx:bb00620062bb0062b0062b0062	(Ljava/lang/String;CC)Ljava/lang/String;
    //   380: iconst_0
    //   381: anewarray 48	java/lang/Class
    //   384: invokevirtual 52	java/lang/Class:getMethod	(Ljava/lang/String;[Ljava/lang/Class;)Ljava/lang/reflect/Method;
    //   387: astore 5
    //   389: aload 5
    //   391: aconst_null
    //   392: iconst_0
    //   393: anewarray 54	java/lang/Object
    //   396: invokevirtual 60	java/lang/reflect/Method:invoke	(Ljava/lang/Object;[Ljava/lang/Object;)Ljava/lang/Object;
    //   399: astore 5
    //   401: aload 5
    //   403: checkcast 62	java/lang/Integer
    //   406: invokevirtual 65	java/lang/Integer:intValue	()I
    //   409: istore_2
    //   410: iload_2
    //   411: getstatic 36	uuuuuu/qppppp:bs0073ss0073s00730073s	I
    //   414: iload_2
    //   415: iadd
    //   416: imul
    //   417: getstatic 38	uuuuuu/qppppp:b0073sss0073s00730073s	I
    //   420: irem
    //   421: tableswitch	default:+19->440, 0:+104->525
    //   440: ldc 2
    //   442: ldc -120
    //   444: sipush 141
    //   447: iconst_5
    //   448: invokestatic 46	xxxxxx/uxxxxx:bb00620062bb0062b0062b0062	(Ljava/lang/String;CC)Ljava/lang/String;
    //   451: iconst_0
    //   452: anewarray 48	java/lang/Class
    //   455: invokevirtual 52	java/lang/Class:getMethod	(Ljava/lang/String;[Ljava/lang/Class;)Ljava/lang/reflect/Method;
    //   458: astore 5
    //   460: aload 5
    //   462: aconst_null
    //   463: iconst_0
    //   464: anewarray 54	java/lang/Object
    //   467: invokevirtual 60	java/lang/reflect/Method:invoke	(Ljava/lang/Object;[Ljava/lang/Object;)Ljava/lang/Object;
    //   470: astore 5
    //   472: aload 5
    //   474: checkcast 62	java/lang/Integer
    //   477: invokevirtual 65	java/lang/Integer:intValue	()I
    //   480: putstatic 34	uuuuuu/qppppp:b0073007300730073ss00730073s	I
    //   483: ldc 2
    //   485: ldc -118
    //   487: bipush 94
    //   489: iconst_5
    //   490: invokestatic 46	xxxxxx/uxxxxx:bb00620062bb0062b0062b0062	(Ljava/lang/String;CC)Ljava/lang/String;
    //   493: iconst_0
    //   494: anewarray 48	java/lang/Class
    //   497: invokevirtual 52	java/lang/Class:getMethod	(Ljava/lang/String;[Ljava/lang/Class;)Ljava/lang/reflect/Method;
    //   500: astore 5
    //   502: aload 5
    //   504: aconst_null
    //   505: iconst_0
    //   506: anewarray 54	java/lang/Object
    //   509: invokevirtual 60	java/lang/reflect/Method:invoke	(Ljava/lang/Object;[Ljava/lang/Object;)Ljava/lang/Object;
    //   512: astore 5
    //   514: aload 5
    //   516: checkcast 62	java/lang/Integer
    //   519: invokevirtual 65	java/lang/Integer:intValue	()I
    //   522: putstatic 69	uuuuuu/qppppp:bssss0073s00730073s	I
    //   525: ldc 2
    //   527: ldc -116
    //   529: bipush 35
    //   531: iconst_2
    //   532: invokestatic 46	xxxxxx/uxxxxx:bb00620062bb0062b0062b0062	(Ljava/lang/String;CC)Ljava/lang/String;
    //   535: iconst_3
    //   536: anewarray 48	java/lang/Class
    //   539: dup
    //   540: iconst_0
    //   541: ldc 28
    //   543: aastore
    //   544: dup
    //   545: iconst_1
    //   546: getstatic 146	java/lang/Boolean:TYPE	Ljava/lang/Class;
    //   549: aastore
    //   550: dup
    //   551: iconst_2
    //   552: ldc -108
    //   554: aastore
    //   555: invokevirtual 52	java/lang/Class:getMethod	(Ljava/lang/String;[Ljava/lang/Class;)Ljava/lang/reflect/Method;
    //   558: astore 5
    //   560: aload 5
    //   562: aload_0
    //   563: iconst_3
    //   564: anewarray 54	java/lang/Object
    //   567: dup
    //   568: iconst_0
    //   569: aload_1
    //   570: aastore
    //   571: dup
    //   572: iconst_1
    //   573: iconst_0
    //   574: invokestatic 152	java/lang/Boolean:valueOf	(Z)Ljava/lang/Boolean;
    //   577: aastore
    //   578: dup
    //   579: iconst_2
    //   580: aconst_null
    //   581: aastore
    //   582: invokevirtual 60	java/lang/reflect/Method:invoke	(Ljava/lang/Object;[Ljava/lang/Object;)Ljava/lang/Object;
    //   585: pop
    //   586: return
    //   587: astore_1
    //   588: aload_1
    //   589: invokevirtual 116	java/lang/reflect/InvocationTargetException:getCause	()Ljava/lang/Throwable;
    //   592: athrow
    //   593: astore_1
    //   594: aload_1
    //   595: invokevirtual 116	java/lang/reflect/InvocationTargetException:getCause	()Ljava/lang/Throwable;
    //   598: athrow
    //   599: astore_1
    //   600: aload_1
    //   601: invokevirtual 116	java/lang/reflect/InvocationTargetException:getCause	()Ljava/lang/Throwable;
    //   604: athrow
    //   605: astore_1
    //   606: aload_1
    //   607: invokevirtual 116	java/lang/reflect/InvocationTargetException:getCause	()Ljava/lang/Throwable;
    //   610: athrow
    //   611: astore_1
    //   612: aload_1
    //   613: invokevirtual 116	java/lang/reflect/InvocationTargetException:getCause	()Ljava/lang/Throwable;
    //   616: athrow
    //   617: astore_1
    //   618: aload_1
    //   619: invokevirtual 116	java/lang/reflect/InvocationTargetException:getCause	()Ljava/lang/Throwable;
    //   622: athrow
    //   623: astore_1
    //   624: aload_1
    //   625: invokevirtual 116	java/lang/reflect/InvocationTargetException:getCause	()Ljava/lang/Throwable;
    //   628: athrow
    //   629: astore_1
    //   630: aload_1
    //   631: invokevirtual 116	java/lang/reflect/InvocationTargetException:getCause	()Ljava/lang/Throwable;
    //   634: athrow
    //   635: astore_1
    //   636: aload_1
    //   637: invokevirtual 116	java/lang/reflect/InvocationTargetException:getCause	()Ljava/lang/Throwable;
    //   640: athrow
    //   641: astore_1
    //   642: aload_1
    //   643: invokevirtual 116	java/lang/reflect/InvocationTargetException:getCause	()Ljava/lang/Throwable;
    //   646: athrow
    //   647: astore_1
    //   648: aload_1
    //   649: invokevirtual 116	java/lang/reflect/InvocationTargetException:getCause	()Ljava/lang/Throwable;
    //   652: athrow
    // Local variable table:
    //   start	length	slot	name	signature
    //   0	653	0	this	qppppp
    //   0	653	1	paramDbErrorCode	com.db.pwcc.dbmobile.model.error.DbErrorCode
    //   3	414	2	i	int
    //   113	46	3	j	int
    //   117	43	4	k	int
    //   21	540	5	localObject	Object
    // Exception table:
    //   from	to	target	type
    //   23	35	587	java/lang/reflect/InvocationTargetException
    //   83	95	593	java/lang/reflect/InvocationTargetException
    //   389	401	599	java/lang/reflect/InvocationTargetException
    //   460	472	605	java/lang/reflect/InvocationTargetException
    //   502	514	611	java/lang/reflect/InvocationTargetException
    //   196	208	617	java/lang/reflect/InvocationTargetException
    //   241	253	623	java/lang/reflect/InvocationTargetException
    //   287	299	629	java/lang/reflect/InvocationTargetException
    //   142	154	635	java/lang/reflect/InvocationTargetException
    //   560	586	641	java/lang/reflect/InvocationTargetException
    //   347	359	647	java/lang/reflect/InvocationTargetException
  }
  
  /* Error */
  public boolean boo006F006F006F006Fo006F006F006F(com.db.pwcc.dbmobile.model.error.DbError paramDbError)
  {
    // Byte code:
    //   0: iconst_1
    //   1: istore 4
    //   3: aload_1
    //   4: ifnull +385 -> 389
    //   7: aload_1
    //   8: invokevirtual 160	com/db/pwcc/dbmobile/model/error/DbError:getDbCode	()Lcom/db/pwcc/dbmobile/model/error/DbErrorCode;
    //   11: getstatic 32	com/db/pwcc/dbmobile/model/error/DbErrorCode:INSECURE_CONNECTION_ERROR	Lcom/db/pwcc/dbmobile/model/error/DbErrorCode;
    //   14: if_acmpeq +164 -> 178
    //   17: aload_1
    //   18: invokevirtual 160	com/db/pwcc/dbmobile/model/error/DbError:getDbCode	()Lcom/db/pwcc/dbmobile/model/error/DbErrorCode;
    //   21: getstatic 96	com/db/pwcc/dbmobile/model/error/DbErrorCode:NO_INTERNET_ERROR	Lcom/db/pwcc/dbmobile/model/error/DbErrorCode;
    //   24: if_acmpne +365 -> 389
    //   27: ldc 2
    //   29: ldc -94
    //   31: bipush 121
    //   33: iconst_1
    //   34: invokestatic 46	xxxxxx/uxxxxx:bb00620062bb0062b0062b0062	(Ljava/lang/String;CC)Ljava/lang/String;
    //   37: iconst_0
    //   38: anewarray 48	java/lang/Class
    //   41: invokevirtual 52	java/lang/Class:getMethod	(Ljava/lang/String;[Ljava/lang/Class;)Ljava/lang/reflect/Method;
    //   44: astore_1
    //   45: aload_1
    //   46: aconst_null
    //   47: iconst_0
    //   48: anewarray 54	java/lang/Object
    //   51: invokevirtual 60	java/lang/reflect/Method:invoke	(Ljava/lang/Object;[Ljava/lang/Object;)Ljava/lang/Object;
    //   54: astore_1
    //   55: aload_1
    //   56: checkcast 62	java/lang/Integer
    //   59: invokevirtual 65	java/lang/Integer:intValue	()I
    //   62: istore_2
    //   63: iload_2
    //   64: getstatic 36	uuuuuu/qppppp:bs0073ss0073s00730073s	I
    //   67: iload_2
    //   68: iadd
    //   69: imul
    //   70: getstatic 38	uuuuuu/qppppp:b0073sss0073s00730073s	I
    //   73: irem
    //   74: tableswitch	default:+18->92, 0:+104->178
    //   92: bipush 39
    //   94: putstatic 34	uuuuuu/qppppp:b0073007300730073ss00730073s	I
    //   97: ldc 2
    //   99: ldc -92
    //   101: sipush 249
    //   104: iconst_4
    //   105: invokestatic 46	xxxxxx/uxxxxx:bb00620062bb0062b0062b0062	(Ljava/lang/String;CC)Ljava/lang/String;
    //   108: iconst_0
    //   109: anewarray 48	java/lang/Class
    //   112: invokevirtual 52	java/lang/Class:getMethod	(Ljava/lang/String;[Ljava/lang/Class;)Ljava/lang/reflect/Method;
    //   115: astore_1
    //   116: aload_1
    //   117: aconst_null
    //   118: iconst_0
    //   119: anewarray 54	java/lang/Object
    //   122: invokevirtual 60	java/lang/reflect/Method:invoke	(Ljava/lang/Object;[Ljava/lang/Object;)Ljava/lang/Object;
    //   125: astore_1
    //   126: aload_1
    //   127: checkcast 62	java/lang/Integer
    //   130: invokevirtual 65	java/lang/Integer:intValue	()I
    //   133: putstatic 69	uuuuuu/qppppp:bssss0073s00730073s	I
    //   136: getstatic 34	uuuuuu/qppppp:b0073007300730073ss00730073s	I
    //   139: istore_2
    //   140: iload_2
    //   141: getstatic 36	uuuuuu/qppppp:bs0073ss0073s00730073s	I
    //   144: iload_2
    //   145: iadd
    //   146: imul
    //   147: getstatic 38	uuuuuu/qppppp:b0073sss0073s00730073s	I
    //   150: irem
    //   151: tableswitch	default:+17->168, 0:+27->178
    //   168: bipush 51
    //   170: putstatic 34	uuuuuu/qppppp:b0073007300730073ss00730073s	I
    //   173: bipush 30
    //   175: putstatic 69	uuuuuu/qppppp:bssss0073s00730073s	I
    //   178: getstatic 34	uuuuuu/qppppp:b0073007300730073ss00730073s	I
    //   181: istore_2
    //   182: iload 4
    //   184: istore_3
    //   185: iload_2
    //   186: getstatic 36	uuuuuu/qppppp:bs0073ss0073s00730073s	I
    //   189: iload_2
    //   190: iadd
    //   191: imul
    //   192: getstatic 38	uuuuuu/qppppp:b0073sss0073s00730073s	I
    //   195: irem
    //   196: tableswitch	default:+20->216, 0:+103->299
    //   216: ldc 2
    //   218: ldc -90
    //   220: sipush 174
    //   223: iconst_3
    //   224: invokestatic 46	xxxxxx/uxxxxx:bb00620062bb0062b0062b0062	(Ljava/lang/String;CC)Ljava/lang/String;
    //   227: iconst_0
    //   228: anewarray 48	java/lang/Class
    //   231: invokevirtual 52	java/lang/Class:getMethod	(Ljava/lang/String;[Ljava/lang/Class;)Ljava/lang/reflect/Method;
    //   234: astore_1
    //   235: aload_1
    //   236: aconst_null
    //   237: iconst_0
    //   238: anewarray 54	java/lang/Object
    //   241: invokevirtual 60	java/lang/reflect/Method:invoke	(Ljava/lang/Object;[Ljava/lang/Object;)Ljava/lang/Object;
    //   244: astore_1
    //   245: aload_1
    //   246: checkcast 62	java/lang/Integer
    //   249: invokevirtual 65	java/lang/Integer:intValue	()I
    //   252: putstatic 34	uuuuuu/qppppp:b0073007300730073ss00730073s	I
    //   255: ldc 2
    //   257: ldc -88
    //   259: bipush 67
    //   261: sipush 224
    //   264: iconst_3
    //   265: invokestatic 102	xxxxxx/uxxxxx:bbbb0062b0062b0062b0062	(Ljava/lang/String;CCC)Ljava/lang/String;
    //   268: iconst_0
    //   269: anewarray 48	java/lang/Class
    //   272: invokevirtual 52	java/lang/Class:getMethod	(Ljava/lang/String;[Ljava/lang/Class;)Ljava/lang/reflect/Method;
    //   275: astore_1
    //   276: aload_1
    //   277: aconst_null
    //   278: iconst_0
    //   279: anewarray 54	java/lang/Object
    //   282: invokevirtual 60	java/lang/reflect/Method:invoke	(Ljava/lang/Object;[Ljava/lang/Object;)Ljava/lang/Object;
    //   285: astore_1
    //   286: aload_1
    //   287: checkcast 62	java/lang/Integer
    //   290: invokevirtual 65	java/lang/Integer:intValue	()I
    //   293: putstatic 69	uuuuuu/qppppp:bssss0073s00730073s	I
    //   296: iload 4
    //   298: istore_3
    //   299: getstatic 34	uuuuuu/qppppp:b0073007300730073ss00730073s	I
    //   302: istore_2
    //   303: iload_2
    //   304: getstatic 36	uuuuuu/qppppp:bs0073ss0073s00730073s	I
    //   307: iload_2
    //   308: iadd
    //   309: imul
    //   310: getstatic 38	uuuuuu/qppppp:b0073sss0073s00730073s	I
    //   313: irem
    //   314: tableswitch	default:+18->332, 0:+61->375
    //   332: ldc 2
    //   334: ldc -92
    //   336: bipush 122
    //   338: iconst_4
    //   339: invokestatic 46	xxxxxx/uxxxxx:bb00620062bb0062b0062b0062	(Ljava/lang/String;CC)Ljava/lang/String;
    //   342: iconst_0
    //   343: anewarray 48	java/lang/Class
    //   346: invokevirtual 52	java/lang/Class:getMethod	(Ljava/lang/String;[Ljava/lang/Class;)Ljava/lang/reflect/Method;
    //   349: astore_1
    //   350: aload_1
    //   351: aconst_null
    //   352: iconst_0
    //   353: anewarray 54	java/lang/Object
    //   356: invokevirtual 60	java/lang/reflect/Method:invoke	(Ljava/lang/Object;[Ljava/lang/Object;)Ljava/lang/Object;
    //   359: astore_1
    //   360: aload_1
    //   361: checkcast 62	java/lang/Integer
    //   364: invokevirtual 65	java/lang/Integer:intValue	()I
    //   367: putstatic 34	uuuuuu/qppppp:b0073007300730073ss00730073s	I
    //   370: bipush 93
    //   372: putstatic 69	uuuuuu/qppppp:bssss0073s00730073s	I
    //   375: iload_3
    //   376: ireturn
    //   377: astore_1
    //   378: aload_1
    //   379: invokevirtual 116	java/lang/reflect/InvocationTargetException:getCause	()Ljava/lang/Throwable;
    //   382: athrow
    //   383: astore_1
    //   384: aload_1
    //   385: invokevirtual 116	java/lang/reflect/InvocationTargetException:getCause	()Ljava/lang/Throwable;
    //   388: athrow
    //   389: iconst_0
    //   390: istore_3
    //   391: goto -92 -> 299
    //   394: astore_1
    //   395: aload_1
    //   396: invokevirtual 116	java/lang/reflect/InvocationTargetException:getCause	()Ljava/lang/Throwable;
    //   399: athrow
    //   400: astore_1
    //   401: aload_1
    //   402: invokevirtual 116	java/lang/reflect/InvocationTargetException:getCause	()Ljava/lang/Throwable;
    //   405: athrow
    //   406: astore_1
    //   407: aload_1
    //   408: invokevirtual 116	java/lang/reflect/InvocationTargetException:getCause	()Ljava/lang/Throwable;
    //   411: athrow
    // Local variable table:
    //   start	length	slot	name	signature
    //   0	412	0	this	qppppp
    //   0	412	1	paramDbError	com.db.pwcc.dbmobile.model.error.DbError
    //   62	248	2	i	int
    //   184	207	3	bool1	boolean
    //   1	296	4	bool2	boolean
    // Exception table:
    //   from	to	target	type
    //   45	55	377	java/lang/reflect/InvocationTargetException
    //   350	360	383	java/lang/reflect/InvocationTargetException
    //   116	126	394	java/lang/reflect/InvocationTargetException
    //   235	245	400	java/lang/reflect/InvocationTargetException
    //   276	286	406	java/lang/reflect/InvocationTargetException
  }
}
