package uuuuuu;

public class qqllql
  extends qqqqll
  implements aallll.llalll
{
  public static int b00700070p00700070p0070p0070 = 0;
  public static int b0070p007000700070p0070p0070 = 2;
  public static int bp0070p00700070p0070p0070 = 56;
  public static int bpp007000700070p0070p0070 = 1;
  private static final String bppp00700070p0070p0070;
  public alalaa b0070pp00700070p0070p0070 = new alalaa();
  
  /* Error */
  static
  {
    // Byte code:
    //   0: ldc 2
    //   2: invokevirtual 29	java/lang/Class:getSimpleName	()Ljava/lang/String;
    //   5: astore_2
    //   6: getstatic 31	uuuuuu/qqllql:bp0070p00700070p0070p0070	I
    //   9: getstatic 33	uuuuuu/qqllql:bpp007000700070p0070p0070	I
    //   12: iadd
    //   13: getstatic 31	uuuuuu/qqllql:bp0070p00700070p0070p0070	I
    //   16: imul
    //   17: getstatic 35	uuuuuu/qqllql:b0070p007000700070p0070p0070	I
    //   20: irem
    //   21: getstatic 37	uuuuuu/qqllql:b00700070p00700070p0070p0070	I
    //   24: if_icmpeq +154 -> 178
    //   27: getstatic 31	uuuuuu/qqllql:bp0070p00700070p0070p0070	I
    //   30: getstatic 33	uuuuuu/qqllql:bpp007000700070p0070p0070	I
    //   33: iadd
    //   34: getstatic 31	uuuuuu/qqllql:bp0070p00700070p0070p0070	I
    //   37: imul
    //   38: getstatic 35	uuuuuu/qqllql:b0070p007000700070p0070p0070	I
    //   41: irem
    //   42: getstatic 37	uuuuuu/qqllql:b00700070p00700070p0070p0070	I
    //   45: if_icmpeq +90 -> 135
    //   48: ldc 2
    //   50: ldc 39
    //   52: bipush 97
    //   54: iconst_5
    //   55: invokestatic 45	xxxxxx/uxxxxx:bb00620062bb0062b0062b0062	(Ljava/lang/String;CC)Ljava/lang/String;
    //   58: iconst_0
    //   59: anewarray 25	java/lang/Class
    //   62: invokevirtual 49	java/lang/Class:getMethod	(Ljava/lang/String;[Ljava/lang/Class;)Ljava/lang/reflect/Method;
    //   65: astore_3
    //   66: aload_3
    //   67: aconst_null
    //   68: iconst_0
    //   69: anewarray 51	java/lang/Object
    //   72: invokevirtual 57	java/lang/reflect/Method:invoke	(Ljava/lang/Object;[Ljava/lang/Object;)Ljava/lang/Object;
    //   75: astore_3
    //   76: aload_3
    //   77: checkcast 59	java/lang/Integer
    //   80: invokevirtual 63	java/lang/Integer:intValue	()I
    //   83: putstatic 31	uuuuuu/qqllql:bp0070p00700070p0070p0070	I
    //   86: getstatic 31	uuuuuu/qqllql:bp0070p00700070p0070p0070	I
    //   89: istore_0
    //   90: iload_0
    //   91: getstatic 33	uuuuuu/qqllql:bpp007000700070p0070p0070	I
    //   94: iload_0
    //   95: iadd
    //   96: imul
    //   97: getstatic 35	uuuuuu/qqllql:b0070p007000700070p0070p0070	I
    //   100: irem
    //   101: tableswitch	default:+19->120, 0:+29->130
    //   120: bipush 63
    //   122: putstatic 31	uuuuuu/qqllql:bp0070p00700070p0070p0070	I
    //   125: bipush 23
    //   127: putstatic 37	uuuuuu/qqllql:b00700070p00700070p0070p0070	I
    //   130: bipush 54
    //   132: putstatic 37	uuuuuu/qqllql:b00700070p00700070p0070p0070	I
    //   135: bipush 26
    //   137: putstatic 31	uuuuuu/qqllql:bp0070p00700070p0070p0070	I
    //   140: ldc 2
    //   142: ldc 65
    //   144: bipush 106
    //   146: iconst_3
    //   147: invokestatic 45	xxxxxx/uxxxxx:bb00620062bb0062b0062b0062	(Ljava/lang/String;CC)Ljava/lang/String;
    //   150: iconst_0
    //   151: anewarray 25	java/lang/Class
    //   154: invokevirtual 49	java/lang/Class:getMethod	(Ljava/lang/String;[Ljava/lang/Class;)Ljava/lang/reflect/Method;
    //   157: astore_3
    //   158: aload_3
    //   159: aconst_null
    //   160: iconst_0
    //   161: anewarray 51	java/lang/Object
    //   164: invokevirtual 57	java/lang/reflect/Method:invoke	(Ljava/lang/Object;[Ljava/lang/Object;)Ljava/lang/Object;
    //   167: astore_3
    //   168: aload_3
    //   169: checkcast 59	java/lang/Integer
    //   172: invokevirtual 63	java/lang/Integer:intValue	()I
    //   175: putstatic 37	uuuuuu/qqllql:b00700070p00700070p0070p0070	I
    //   178: aload_2
    //   179: putstatic 67	uuuuuu/qqllql:bppp00700070p0070p0070	Ljava/lang/String;
    //   182: getstatic 31	uuuuuu/qqllql:bp0070p00700070p0070p0070	I
    //   185: istore_0
    //   186: getstatic 33	uuuuuu/qqllql:bpp007000700070p0070p0070	I
    //   189: istore_1
    //   190: ldc 2
    //   192: ldc 69
    //   194: sipush 149
    //   197: iconst_1
    //   198: invokestatic 45	xxxxxx/uxxxxx:bb00620062bb0062b0062b0062	(Ljava/lang/String;CC)Ljava/lang/String;
    //   201: iconst_0
    //   202: anewarray 25	java/lang/Class
    //   205: invokevirtual 49	java/lang/Class:getMethod	(Ljava/lang/String;[Ljava/lang/Class;)Ljava/lang/reflect/Method;
    //   208: astore_2
    //   209: aload_2
    //   210: aconst_null
    //   211: iconst_0
    //   212: anewarray 51	java/lang/Object
    //   215: invokevirtual 57	java/lang/reflect/Method:invoke	(Ljava/lang/Object;[Ljava/lang/Object;)Ljava/lang/Object;
    //   218: astore_2
    //   219: iload_1
    //   220: iload_0
    //   221: iadd
    //   222: iload_0
    //   223: imul
    //   224: aload_2
    //   225: checkcast 59	java/lang/Integer
    //   228: invokevirtual 63	java/lang/Integer:intValue	()I
    //   231: irem
    //   232: tableswitch	default:+20->252, 0:+98->330
    //   252: ldc 2
    //   254: ldc 71
    //   256: sipush 194
    //   259: iconst_1
    //   260: invokestatic 45	xxxxxx/uxxxxx:bb00620062bb0062b0062b0062	(Ljava/lang/String;CC)Ljava/lang/String;
    //   263: iconst_0
    //   264: anewarray 25	java/lang/Class
    //   267: invokevirtual 49	java/lang/Class:getMethod	(Ljava/lang/String;[Ljava/lang/Class;)Ljava/lang/reflect/Method;
    //   270: astore_2
    //   271: aload_2
    //   272: aconst_null
    //   273: iconst_0
    //   274: anewarray 51	java/lang/Object
    //   277: invokevirtual 57	java/lang/reflect/Method:invoke	(Ljava/lang/Object;[Ljava/lang/Object;)Ljava/lang/Object;
    //   280: astore_2
    //   281: aload_2
    //   282: checkcast 59	java/lang/Integer
    //   285: invokevirtual 63	java/lang/Integer:intValue	()I
    //   288: putstatic 31	uuuuuu/qqllql:bp0070p00700070p0070p0070	I
    //   291: ldc 2
    //   293: ldc 73
    //   295: bipush 115
    //   297: iconst_1
    //   298: iconst_2
    //   299: invokestatic 77	xxxxxx/uxxxxx:bbbb0062b0062b0062b0062	(Ljava/lang/String;CCC)Ljava/lang/String;
    //   302: iconst_0
    //   303: anewarray 25	java/lang/Class
    //   306: invokevirtual 49	java/lang/Class:getMethod	(Ljava/lang/String;[Ljava/lang/Class;)Ljava/lang/reflect/Method;
    //   309: astore_2
    //   310: aload_2
    //   311: aconst_null
    //   312: iconst_0
    //   313: anewarray 51	java/lang/Object
    //   316: invokevirtual 57	java/lang/reflect/Method:invoke	(Ljava/lang/Object;[Ljava/lang/Object;)Ljava/lang/Object;
    //   319: astore_2
    //   320: aload_2
    //   321: checkcast 59	java/lang/Integer
    //   324: invokevirtual 63	java/lang/Integer:intValue	()I
    //   327: putstatic 37	uuuuuu/qqllql:b00700070p00700070p0070p0070	I
    //   330: return
    //   331: astore_2
    //   332: aload_2
    //   333: invokevirtual 81	java/lang/reflect/InvocationTargetException:getCause	()Ljava/lang/Throwable;
    //   336: athrow
    //   337: astore_2
    //   338: aload_2
    //   339: invokevirtual 81	java/lang/reflect/InvocationTargetException:getCause	()Ljava/lang/Throwable;
    //   342: athrow
    //   343: astore_2
    //   344: aload_2
    //   345: invokevirtual 81	java/lang/reflect/InvocationTargetException:getCause	()Ljava/lang/Throwable;
    //   348: athrow
    //   349: astore_2
    //   350: aload_2
    //   351: invokevirtual 81	java/lang/reflect/InvocationTargetException:getCause	()Ljava/lang/Throwable;
    //   354: athrow
    //   355: astore_2
    //   356: aload_2
    //   357: invokevirtual 81	java/lang/reflect/InvocationTargetException:getCause	()Ljava/lang/Throwable;
    //   360: athrow
    // Local variable table:
    //   start	length	slot	name	signature
    //   89	135	0	i	int
    //   189	33	1	j	int
    //   5	316	2	localObject1	Object
    //   331	2	2	localInvocationTargetException1	java.lang.reflect.InvocationTargetException
    //   337	2	2	localInvocationTargetException2	java.lang.reflect.InvocationTargetException
    //   343	2	2	localInvocationTargetException3	java.lang.reflect.InvocationTargetException
    //   349	2	2	localInvocationTargetException4	java.lang.reflect.InvocationTargetException
    //   355	2	2	localInvocationTargetException5	java.lang.reflect.InvocationTargetException
    //   65	104	3	localObject2	Object
    // Exception table:
    //   from	to	target	type
    //   158	168	331	java/lang/reflect/InvocationTargetException
    //   209	219	337	java/lang/reflect/InvocationTargetException
    //   66	76	343	java/lang/reflect/InvocationTargetException
    //   271	281	349	java/lang/reflect/InvocationTargetException
    //   310	320	355	java/lang/reflect/InvocationTargetException
  }
  
  public qqllql(String paramString)
  {
    super(paramString);
  }
  
  public static int b006Fo006F006F006F006Fo006Foo()
  {
    return 16;
  }
  
  public static int bo006F006F006F006F006Fo006Foo()
  {
    return 2;
  }
  
  public static int boo006F006F006F006Fo006Foo()
  {
    return 1;
  }
  
  /* Error */
  public void b006F006F006F006F006F006Fo006Foo(com.db.pwcc.dbmobile.model.error.DbError paramDbError)
  {
    // Byte code:
    //   0: getstatic 31	uuuuuu/qqllql:bp0070p00700070p0070p0070	I
    //   3: getstatic 33	uuuuuu/qqllql:bpp007000700070p0070p0070	I
    //   6: iadd
    //   7: getstatic 31	uuuuuu/qqllql:bp0070p00700070p0070p0070	I
    //   10: imul
    //   11: getstatic 35	uuuuuu/qqllql:b0070p007000700070p0070p0070	I
    //   14: irem
    //   15: getstatic 37	uuuuuu/qqllql:b00700070p00700070p0070p0070	I
    //   18: if_icmpeq +52 -> 70
    //   21: ldc 2
    //   23: ldc 99
    //   25: bipush 36
    //   27: bipush 100
    //   29: iconst_2
    //   30: invokestatic 77	xxxxxx/uxxxxx:bbbb0062b0062b0062b0062	(Ljava/lang/String;CCC)Ljava/lang/String;
    //   33: iconst_0
    //   34: anewarray 25	java/lang/Class
    //   37: invokevirtual 49	java/lang/Class:getMethod	(Ljava/lang/String;[Ljava/lang/Class;)Ljava/lang/reflect/Method;
    //   40: astore 4
    //   42: aload 4
    //   44: aconst_null
    //   45: iconst_0
    //   46: anewarray 51	java/lang/Object
    //   49: invokevirtual 57	java/lang/reflect/Method:invoke	(Ljava/lang/Object;[Ljava/lang/Object;)Ljava/lang/Object;
    //   52: astore 4
    //   54: aload 4
    //   56: checkcast 59	java/lang/Integer
    //   59: invokevirtual 63	java/lang/Integer:intValue	()I
    //   62: putstatic 31	uuuuuu/qqllql:bp0070p00700070p0070p0070	I
    //   65: bipush 69
    //   67: putstatic 37	uuuuuu/qqllql:b00700070p00700070p0070p0070	I
    //   70: aload_0
    //   71: invokevirtual 103	uuuuuu/qqllql:bkk006Bk006Bk006Bk006Bk	()Z
    //   74: ifne +88 -> 162
    //   77: getstatic 31	uuuuuu/qqllql:bp0070p00700070p0070p0070	I
    //   80: istore_2
    //   81: iload_2
    //   82: getstatic 33	uuuuuu/qqllql:bpp007000700070p0070p0070	I
    //   85: iload_2
    //   86: iadd
    //   87: imul
    //   88: getstatic 35	uuuuuu/qqllql:b0070p007000700070p0070p0070	I
    //   91: irem
    //   92: tableswitch	default:+20->112, 0:+63->155
    //   112: ldc 2
    //   114: ldc 105
    //   116: bipush 37
    //   118: iconst_4
    //   119: invokestatic 45	xxxxxx/uxxxxx:bb00620062bb0062b0062b0062	(Ljava/lang/String;CC)Ljava/lang/String;
    //   122: iconst_0
    //   123: anewarray 25	java/lang/Class
    //   126: invokevirtual 49	java/lang/Class:getMethod	(Ljava/lang/String;[Ljava/lang/Class;)Ljava/lang/reflect/Method;
    //   129: astore_1
    //   130: aload_1
    //   131: aconst_null
    //   132: iconst_0
    //   133: anewarray 51	java/lang/Object
    //   136: invokevirtual 57	java/lang/reflect/Method:invoke	(Ljava/lang/Object;[Ljava/lang/Object;)Ljava/lang/Object;
    //   139: astore_1
    //   140: aload_1
    //   141: checkcast 59	java/lang/Integer
    //   144: invokevirtual 63	java/lang/Integer:intValue	()I
    //   147: putstatic 31	uuuuuu/qqllql:bp0070p00700070p0070p0070	I
    //   150: bipush 85
    //   152: putstatic 37	uuuuuu/qqllql:b00700070p00700070p0070p0070	I
    //   155: return
    //   156: astore_1
    //   157: aload_1
    //   158: invokevirtual 81	java/lang/reflect/InvocationTargetException:getCause	()Ljava/lang/Throwable;
    //   161: athrow
    //   162: getstatic 31	uuuuuu/qqllql:bp0070p00700070p0070p0070	I
    //   165: istore_2
    //   166: ldc 2
    //   168: ldc 107
    //   170: sipush 213
    //   173: iconst_2
    //   174: invokestatic 45	xxxxxx/uxxxxx:bb00620062bb0062b0062b0062	(Ljava/lang/String;CC)Ljava/lang/String;
    //   177: iconst_0
    //   178: anewarray 25	java/lang/Class
    //   181: invokevirtual 49	java/lang/Class:getMethod	(Ljava/lang/String;[Ljava/lang/Class;)Ljava/lang/reflect/Method;
    //   184: astore 4
    //   186: aload 4
    //   188: aconst_null
    //   189: iconst_0
    //   190: anewarray 51	java/lang/Object
    //   193: invokevirtual 57	java/lang/reflect/Method:invoke	(Ljava/lang/Object;[Ljava/lang/Object;)Ljava/lang/Object;
    //   196: astore 4
    //   198: aload 4
    //   200: checkcast 59	java/lang/Integer
    //   203: invokevirtual 63	java/lang/Integer:intValue	()I
    //   206: iload_2
    //   207: iadd
    //   208: getstatic 31	uuuuuu/qqllql:bp0070p00700070p0070p0070	I
    //   211: imul
    //   212: getstatic 35	uuuuuu/qqllql:b0070p007000700070p0070p0070	I
    //   215: irem
    //   216: getstatic 37	uuuuuu/qqllql:b00700070p00700070p0070p0070	I
    //   219: if_icmpeq +90 -> 309
    //   222: ldc 2
    //   224: ldc 109
    //   226: sipush 182
    //   229: bipush 50
    //   231: iconst_0
    //   232: invokestatic 77	xxxxxx/uxxxxx:bbbb0062b0062b0062b0062	(Ljava/lang/String;CCC)Ljava/lang/String;
    //   235: iconst_0
    //   236: anewarray 25	java/lang/Class
    //   239: invokevirtual 49	java/lang/Class:getMethod	(Ljava/lang/String;[Ljava/lang/Class;)Ljava/lang/reflect/Method;
    //   242: astore 4
    //   244: aload 4
    //   246: aconst_null
    //   247: iconst_0
    //   248: anewarray 51	java/lang/Object
    //   251: invokevirtual 57	java/lang/reflect/Method:invoke	(Ljava/lang/Object;[Ljava/lang/Object;)Ljava/lang/Object;
    //   254: astore 4
    //   256: aload 4
    //   258: checkcast 59	java/lang/Integer
    //   261: invokevirtual 63	java/lang/Integer:intValue	()I
    //   264: putstatic 31	uuuuuu/qqllql:bp0070p00700070p0070p0070	I
    //   267: ldc 2
    //   269: ldc 111
    //   271: bipush 65
    //   273: iconst_1
    //   274: invokestatic 45	xxxxxx/uxxxxx:bb00620062bb0062b0062b0062	(Ljava/lang/String;CC)Ljava/lang/String;
    //   277: iconst_0
    //   278: anewarray 25	java/lang/Class
    //   281: invokevirtual 49	java/lang/Class:getMethod	(Ljava/lang/String;[Ljava/lang/Class;)Ljava/lang/reflect/Method;
    //   284: astore 4
    //   286: aload 4
    //   288: aconst_null
    //   289: iconst_0
    //   290: anewarray 51	java/lang/Object
    //   293: invokevirtual 57	java/lang/reflect/Method:invoke	(Ljava/lang/Object;[Ljava/lang/Object;)Ljava/lang/Object;
    //   296: astore 4
    //   298: aload 4
    //   300: checkcast 59	java/lang/Integer
    //   303: invokevirtual 63	java/lang/Integer:intValue	()I
    //   306: putstatic 37	uuuuuu/qqllql:b00700070p00700070p0070p0070	I
    //   309: aload_0
    //   310: getfield 115	uuuuuu/qqllql:bnnnnn006E006E006En	Luuuuuu/ttssst$tsssst;
    //   313: checkcast 117	uuuuuu/llqqll$lqqqll
    //   316: aload_1
    //   317: invokeinterface 120 2 0
    //   322: ldc 2
    //   324: ldc 122
    //   326: sipush 206
    //   329: iconst_0
    //   330: invokestatic 45	xxxxxx/uxxxxx:bb00620062bb0062b0062b0062	(Ljava/lang/String;CC)Ljava/lang/String;
    //   333: iconst_0
    //   334: anewarray 25	java/lang/Class
    //   337: invokevirtual 49	java/lang/Class:getMethod	(Ljava/lang/String;[Ljava/lang/Class;)Ljava/lang/reflect/Method;
    //   340: astore_1
    //   341: aload_1
    //   342: aconst_null
    //   343: iconst_0
    //   344: anewarray 51	java/lang/Object
    //   347: invokevirtual 57	java/lang/reflect/Method:invoke	(Ljava/lang/Object;[Ljava/lang/Object;)Ljava/lang/Object;
    //   350: astore_1
    //   351: aload_1
    //   352: checkcast 59	java/lang/Integer
    //   355: invokevirtual 63	java/lang/Integer:intValue	()I
    //   358: istore_2
    //   359: getstatic 33	uuuuuu/qqllql:bpp007000700070p0070p0070	I
    //   362: istore_3
    //   363: ldc 2
    //   365: ldc 124
    //   367: sipush 214
    //   370: iconst_2
    //   371: invokestatic 45	xxxxxx/uxxxxx:bb00620062bb0062b0062b0062	(Ljava/lang/String;CC)Ljava/lang/String;
    //   374: iconst_0
    //   375: anewarray 25	java/lang/Class
    //   378: invokevirtual 49	java/lang/Class:getMethod	(Ljava/lang/String;[Ljava/lang/Class;)Ljava/lang/reflect/Method;
    //   381: astore_1
    //   382: aload_1
    //   383: aconst_null
    //   384: iconst_0
    //   385: anewarray 51	java/lang/Object
    //   388: invokevirtual 57	java/lang/reflect/Method:invoke	(Ljava/lang/Object;[Ljava/lang/Object;)Ljava/lang/Object;
    //   391: astore_1
    //   392: iload_3
    //   393: iload_2
    //   394: iadd
    //   395: iload_2
    //   396: imul
    //   397: aload_1
    //   398: checkcast 59	java/lang/Integer
    //   401: invokevirtual 63	java/lang/Integer:intValue	()I
    //   404: irem
    //   405: tableswitch	default:+19->424, 0:+-250->155
    //   424: ldc 2
    //   426: ldc 126
    //   428: sipush 204
    //   431: iconst_0
    //   432: invokestatic 45	xxxxxx/uxxxxx:bb00620062bb0062b0062b0062	(Ljava/lang/String;CC)Ljava/lang/String;
    //   435: iconst_0
    //   436: anewarray 25	java/lang/Class
    //   439: invokevirtual 49	java/lang/Class:getMethod	(Ljava/lang/String;[Ljava/lang/Class;)Ljava/lang/reflect/Method;
    //   442: astore_1
    //   443: aload_1
    //   444: aconst_null
    //   445: iconst_0
    //   446: anewarray 51	java/lang/Object
    //   449: invokevirtual 57	java/lang/reflect/Method:invoke	(Ljava/lang/Object;[Ljava/lang/Object;)Ljava/lang/Object;
    //   452: astore_1
    //   453: aload_1
    //   454: checkcast 59	java/lang/Integer
    //   457: invokevirtual 63	java/lang/Integer:intValue	()I
    //   460: putstatic 31	uuuuuu/qqllql:bp0070p00700070p0070p0070	I
    //   463: bipush 59
    //   465: putstatic 37	uuuuuu/qqllql:b00700070p00700070p0070p0070	I
    //   468: return
    //   469: astore_1
    //   470: aload_1
    //   471: invokevirtual 81	java/lang/reflect/InvocationTargetException:getCause	()Ljava/lang/Throwable;
    //   474: athrow
    //   475: astore_1
    //   476: aload_1
    //   477: invokevirtual 81	java/lang/reflect/InvocationTargetException:getCause	()Ljava/lang/Throwable;
    //   480: athrow
    //   481: astore_1
    //   482: aload_1
    //   483: invokevirtual 81	java/lang/reflect/InvocationTargetException:getCause	()Ljava/lang/Throwable;
    //   486: athrow
    //   487: astore_1
    //   488: aload_1
    //   489: invokevirtual 81	java/lang/reflect/InvocationTargetException:getCause	()Ljava/lang/Throwable;
    //   492: athrow
    //   493: astore_1
    //   494: aload_1
    //   495: invokevirtual 81	java/lang/reflect/InvocationTargetException:getCause	()Ljava/lang/Throwable;
    //   498: athrow
    //   499: astore_1
    //   500: aload_1
    //   501: invokevirtual 81	java/lang/reflect/InvocationTargetException:getCause	()Ljava/lang/Throwable;
    //   504: athrow
    //   505: astore_1
    //   506: aload_1
    //   507: invokevirtual 81	java/lang/reflect/InvocationTargetException:getCause	()Ljava/lang/Throwable;
    //   510: athrow
    // Local variable table:
    //   start	length	slot	name	signature
    //   0	511	0	this	qqllql
    //   0	511	1	paramDbError	com.db.pwcc.dbmobile.model.error.DbError
    //   80	317	2	i	int
    //   362	33	3	j	int
    //   40	259	4	localObject	Object
    // Exception table:
    //   from	to	target	type
    //   42	54	156	java/lang/reflect/InvocationTargetException
    //   186	198	469	java/lang/reflect/InvocationTargetException
    //   341	351	475	java/lang/reflect/InvocationTargetException
    //   382	392	481	java/lang/reflect/InvocationTargetException
    //   244	256	487	java/lang/reflect/InvocationTargetException
    //   286	298	493	java/lang/reflect/InvocationTargetException
    //   130	140	499	java/lang/reflect/InvocationTargetException
    //   443	453	505	java/lang/reflect/InvocationTargetException
  }
  
  /* Error */
  public void b006Fo006F006Fo006Fo006Foo()
  {
    // Byte code:
    //   0: getstatic 31	uuuuuu/qqllql:bp0070p00700070p0070p0070	I
    //   3: getstatic 33	uuuuuu/qqllql:bpp007000700070p0070p0070	I
    //   6: iadd
    //   7: getstatic 31	uuuuuu/qqllql:bp0070p00700070p0070p0070	I
    //   10: imul
    //   11: getstatic 35	uuuuuu/qqllql:b0070p007000700070p0070p0070	I
    //   14: irem
    //   15: getstatic 37	uuuuuu/qqllql:b00700070p00700070p0070p0070	I
    //   18: if_icmpeq +51 -> 69
    //   21: ldc 2
    //   23: ldc -127
    //   25: sipush 140
    //   28: iconst_5
    //   29: invokestatic 45	xxxxxx/uxxxxx:bb00620062bb0062b0062b0062	(Ljava/lang/String;CC)Ljava/lang/String;
    //   32: iconst_0
    //   33: anewarray 25	java/lang/Class
    //   36: invokevirtual 49	java/lang/Class:getMethod	(Ljava/lang/String;[Ljava/lang/Class;)Ljava/lang/reflect/Method;
    //   39: astore 4
    //   41: aload 4
    //   43: aconst_null
    //   44: iconst_0
    //   45: anewarray 51	java/lang/Object
    //   48: invokevirtual 57	java/lang/reflect/Method:invoke	(Ljava/lang/Object;[Ljava/lang/Object;)Ljava/lang/Object;
    //   51: astore 4
    //   53: aload 4
    //   55: checkcast 59	java/lang/Integer
    //   58: invokevirtual 63	java/lang/Integer:intValue	()I
    //   61: putstatic 31	uuuuuu/qqllql:bp0070p00700070p0070p0070	I
    //   64: bipush 6
    //   66: putstatic 37	uuuuuu/qqllql:b00700070p00700070p0070p0070	I
    //   69: aload_0
    //   70: getfield 92	uuuuuu/qqllql:b0070pp00700070p0070p0070	Luuuuuu/alalaa;
    //   73: astore 4
    //   75: aload_0
    //   76: getfield 133	uuuuuu/qqllql:b006E006E006E006E006En006E006En	Luuuuuu/hyhyhh;
    //   79: invokevirtual 138	uuuuuu/hyhyhh:b0070pp007000700070p007000700070	()Ljava/lang/String;
    //   82: astore 5
    //   84: getstatic 31	uuuuuu/qqllql:bp0070p00700070p0070p0070	I
    //   87: istore_1
    //   88: getstatic 33	uuuuuu/qqllql:bpp007000700070p0070p0070	I
    //   91: istore_2
    //   92: ldc 2
    //   94: ldc -116
    //   96: bipush 64
    //   98: iconst_3
    //   99: invokestatic 45	xxxxxx/uxxxxx:bb00620062bb0062b0062b0062	(Ljava/lang/String;CC)Ljava/lang/String;
    //   102: iconst_0
    //   103: anewarray 25	java/lang/Class
    //   106: invokevirtual 49	java/lang/Class:getMethod	(Ljava/lang/String;[Ljava/lang/Class;)Ljava/lang/reflect/Method;
    //   109: astore 6
    //   111: aload 6
    //   113: aconst_null
    //   114: iconst_0
    //   115: anewarray 51	java/lang/Object
    //   118: invokevirtual 57	java/lang/reflect/Method:invoke	(Ljava/lang/Object;[Ljava/lang/Object;)Ljava/lang/Object;
    //   121: astore 6
    //   123: aload 6
    //   125: checkcast 59	java/lang/Integer
    //   128: invokevirtual 63	java/lang/Integer:intValue	()I
    //   131: istore_3
    //   132: iload_3
    //   133: getstatic 33	uuuuuu/qqllql:bpp007000700070p0070p0070	I
    //   136: iload_3
    //   137: iadd
    //   138: imul
    //   139: getstatic 35	uuuuuu/qqllql:b0070p007000700070p0070p0070	I
    //   142: irem
    //   143: tableswitch	default:+17->160, 0:+103->246
    //   160: ldc 2
    //   162: ldc -114
    //   164: sipush 241
    //   167: iconst_5
    //   168: invokestatic 45	xxxxxx/uxxxxx:bb00620062bb0062b0062b0062	(Ljava/lang/String;CC)Ljava/lang/String;
    //   171: iconst_0
    //   172: anewarray 25	java/lang/Class
    //   175: invokevirtual 49	java/lang/Class:getMethod	(Ljava/lang/String;[Ljava/lang/Class;)Ljava/lang/reflect/Method;
    //   178: astore 6
    //   180: aload 6
    //   182: aconst_null
    //   183: iconst_0
    //   184: anewarray 51	java/lang/Object
    //   187: invokevirtual 57	java/lang/reflect/Method:invoke	(Ljava/lang/Object;[Ljava/lang/Object;)Ljava/lang/Object;
    //   190: astore 6
    //   192: aload 6
    //   194: checkcast 59	java/lang/Integer
    //   197: invokevirtual 63	java/lang/Integer:intValue	()I
    //   200: putstatic 31	uuuuuu/qqllql:bp0070p00700070p0070p0070	I
    //   203: ldc 2
    //   205: ldc -112
    //   207: sipush 210
    //   210: iconst_0
    //   211: invokestatic 45	xxxxxx/uxxxxx:bb00620062bb0062b0062b0062	(Ljava/lang/String;CC)Ljava/lang/String;
    //   214: iconst_0
    //   215: anewarray 25	java/lang/Class
    //   218: invokevirtual 49	java/lang/Class:getMethod	(Ljava/lang/String;[Ljava/lang/Class;)Ljava/lang/reflect/Method;
    //   221: astore 6
    //   223: aload 6
    //   225: aconst_null
    //   226: iconst_0
    //   227: anewarray 51	java/lang/Object
    //   230: invokevirtual 57	java/lang/reflect/Method:invoke	(Ljava/lang/Object;[Ljava/lang/Object;)Ljava/lang/Object;
    //   233: astore 6
    //   235: aload 6
    //   237: checkcast 59	java/lang/Integer
    //   240: invokevirtual 63	java/lang/Integer:intValue	()I
    //   243: putstatic 37	uuuuuu/qqllql:b00700070p00700070p0070p0070	I
    //   246: getstatic 31	uuuuuu/qqllql:bp0070p00700070p0070p0070	I
    //   249: istore_3
    //   250: ldc 2
    //   252: ldc -110
    //   254: bipush 57
    //   256: iconst_5
    //   257: invokestatic 45	xxxxxx/uxxxxx:bb00620062bb0062b0062b0062	(Ljava/lang/String;CC)Ljava/lang/String;
    //   260: iconst_0
    //   261: anewarray 25	java/lang/Class
    //   264: invokevirtual 49	java/lang/Class:getMethod	(Ljava/lang/String;[Ljava/lang/Class;)Ljava/lang/reflect/Method;
    //   267: astore 6
    //   269: aload 6
    //   271: aconst_null
    //   272: iconst_0
    //   273: anewarray 51	java/lang/Object
    //   276: invokevirtual 57	java/lang/reflect/Method:invoke	(Ljava/lang/Object;[Ljava/lang/Object;)Ljava/lang/Object;
    //   279: astore 6
    //   281: iload_2
    //   282: iload_1
    //   283: iadd
    //   284: iload_3
    //   285: imul
    //   286: aload 6
    //   288: checkcast 59	java/lang/Integer
    //   291: invokevirtual 63	java/lang/Integer:intValue	()I
    //   294: irem
    //   295: getstatic 37	uuuuuu/qqllql:b00700070p00700070p0070p0070	I
    //   298: if_icmpeq +92 -> 390
    //   301: ldc 2
    //   303: ldc -108
    //   305: sipush 203
    //   308: sipush 163
    //   311: iconst_2
    //   312: invokestatic 77	xxxxxx/uxxxxx:bbbb0062b0062b0062b0062	(Ljava/lang/String;CCC)Ljava/lang/String;
    //   315: iconst_0
    //   316: anewarray 25	java/lang/Class
    //   319: invokevirtual 49	java/lang/Class:getMethod	(Ljava/lang/String;[Ljava/lang/Class;)Ljava/lang/reflect/Method;
    //   322: astore 6
    //   324: aload 6
    //   326: aconst_null
    //   327: iconst_0
    //   328: anewarray 51	java/lang/Object
    //   331: invokevirtual 57	java/lang/reflect/Method:invoke	(Ljava/lang/Object;[Ljava/lang/Object;)Ljava/lang/Object;
    //   334: astore 6
    //   336: aload 6
    //   338: checkcast 59	java/lang/Integer
    //   341: invokevirtual 63	java/lang/Integer:intValue	()I
    //   344: putstatic 31	uuuuuu/qqllql:bp0070p00700070p0070p0070	I
    //   347: ldc 2
    //   349: ldc -106
    //   351: bipush 56
    //   353: iconst_1
    //   354: iconst_1
    //   355: invokestatic 77	xxxxxx/uxxxxx:bbbb0062b0062b0062b0062	(Ljava/lang/String;CCC)Ljava/lang/String;
    //   358: iconst_0
    //   359: anewarray 25	java/lang/Class
    //   362: invokevirtual 49	java/lang/Class:getMethod	(Ljava/lang/String;[Ljava/lang/Class;)Ljava/lang/reflect/Method;
    //   365: astore 6
    //   367: aload 6
    //   369: aconst_null
    //   370: iconst_0
    //   371: anewarray 51	java/lang/Object
    //   374: invokevirtual 57	java/lang/reflect/Method:invoke	(Ljava/lang/Object;[Ljava/lang/Object;)Ljava/lang/Object;
    //   377: astore 6
    //   379: aload 6
    //   381: checkcast 59	java/lang/Integer
    //   384: invokevirtual 63	java/lang/Integer:intValue	()I
    //   387: putstatic 37	uuuuuu/qqllql:b00700070p00700070p0070p0070	I
    //   390: aload 4
    //   392: aload_0
    //   393: aload 5
    //   395: aload_0
    //   396: getfield 153	uuuuuu/qqllql:bp0070p007000700070pp0070	Ljava/lang/String;
    //   399: invokevirtual 157	uuuuuu/alalaa:buu0075uu00750075007500750075	(Luuuuuu/aallll$llalll;Ljava/lang/String;Ljava/lang/String;)V
    //   402: return
    //   403: astore 4
    //   405: aload 4
    //   407: invokevirtual 81	java/lang/reflect/InvocationTargetException:getCause	()Ljava/lang/Throwable;
    //   410: athrow
    //   411: astore 4
    //   413: aload 4
    //   415: invokevirtual 81	java/lang/reflect/InvocationTargetException:getCause	()Ljava/lang/Throwable;
    //   418: athrow
    //   419: astore 4
    //   421: aload 4
    //   423: invokevirtual 81	java/lang/reflect/InvocationTargetException:getCause	()Ljava/lang/Throwable;
    //   426: athrow
    //   427: astore 4
    //   429: aload 4
    //   431: invokevirtual 81	java/lang/reflect/InvocationTargetException:getCause	()Ljava/lang/Throwable;
    //   434: athrow
    //   435: astore 4
    //   437: aload 4
    //   439: invokevirtual 81	java/lang/reflect/InvocationTargetException:getCause	()Ljava/lang/Throwable;
    //   442: athrow
    //   443: astore 4
    //   445: aload 4
    //   447: invokevirtual 81	java/lang/reflect/InvocationTargetException:getCause	()Ljava/lang/Throwable;
    //   450: athrow
    //   451: astore 4
    //   453: aload 4
    //   455: invokevirtual 81	java/lang/reflect/InvocationTargetException:getCause	()Ljava/lang/Throwable;
    //   458: athrow
    // Local variable table:
    //   start	length	slot	name	signature
    //   0	459	0	this	qqllql
    //   87	197	1	i	int
    //   91	193	2	j	int
    //   131	155	3	k	int
    //   39	352	4	localObject1	Object
    //   403	3	4	localInvocationTargetException1	java.lang.reflect.InvocationTargetException
    //   411	3	4	localInvocationTargetException2	java.lang.reflect.InvocationTargetException
    //   419	3	4	localInvocationTargetException3	java.lang.reflect.InvocationTargetException
    //   427	3	4	localInvocationTargetException4	java.lang.reflect.InvocationTargetException
    //   435	3	4	localInvocationTargetException5	java.lang.reflect.InvocationTargetException
    //   443	3	4	localInvocationTargetException6	java.lang.reflect.InvocationTargetException
    //   451	3	4	localInvocationTargetException7	java.lang.reflect.InvocationTargetException
    //   82	312	5	str	String
    //   109	271	6	localObject2	Object
    // Exception table:
    //   from	to	target	type
    //   269	281	403	java/lang/reflect/InvocationTargetException
    //   111	123	411	java/lang/reflect/InvocationTargetException
    //   41	53	419	java/lang/reflect/InvocationTargetException
    //   324	336	427	java/lang/reflect/InvocationTargetException
    //   367	379	435	java/lang/reflect/InvocationTargetException
    //   180	192	443	java/lang/reflect/InvocationTargetException
    //   223	235	451	java/lang/reflect/InvocationTargetException
  }
  
  /* Error */
  public boolean b006Fo006Foo006Fo006Foo()
  {
    // Byte code:
    //   0: getstatic 31	uuuuuu/qqllql:bp0070p00700070p0070p0070	I
    //   3: getstatic 33	uuuuuu/qqllql:bpp007000700070p0070p0070	I
    //   6: iadd
    //   7: getstatic 31	uuuuuu/qqllql:bp0070p00700070p0070p0070	I
    //   10: imul
    //   11: getstatic 35	uuuuuu/qqllql:b0070p007000700070p0070p0070	I
    //   14: irem
    //   15: getstatic 37	uuuuuu/qqllql:b00700070p00700070p0070p0070	I
    //   18: if_icmpeq +47 -> 65
    //   21: ldc 2
    //   23: ldc -96
    //   25: sipush 146
    //   28: iconst_5
    //   29: invokestatic 45	xxxxxx/uxxxxx:bb00620062bb0062b0062b0062	(Ljava/lang/String;CC)Ljava/lang/String;
    //   32: iconst_0
    //   33: anewarray 25	java/lang/Class
    //   36: invokevirtual 49	java/lang/Class:getMethod	(Ljava/lang/String;[Ljava/lang/Class;)Ljava/lang/reflect/Method;
    //   39: astore_1
    //   40: aload_1
    //   41: aconst_null
    //   42: iconst_0
    //   43: anewarray 51	java/lang/Object
    //   46: invokevirtual 57	java/lang/reflect/Method:invoke	(Ljava/lang/Object;[Ljava/lang/Object;)Ljava/lang/Object;
    //   49: astore_1
    //   50: aload_1
    //   51: checkcast 59	java/lang/Integer
    //   54: invokevirtual 63	java/lang/Integer:intValue	()I
    //   57: putstatic 31	uuuuuu/qqllql:bp0070p00700070p0070p0070	I
    //   60: bipush 65
    //   62: putstatic 37	uuuuuu/qqllql:b00700070p00700070p0070p0070	I
    //   65: getstatic 31	uuuuuu/qqllql:bp0070p00700070p0070p0070	I
    //   68: getstatic 33	uuuuuu/qqllql:bpp007000700070p0070p0070	I
    //   71: iadd
    //   72: getstatic 31	uuuuuu/qqllql:bp0070p00700070p0070p0070	I
    //   75: imul
    //   76: getstatic 35	uuuuuu/qqllql:b0070p007000700070p0070p0070	I
    //   79: irem
    //   80: getstatic 37	uuuuuu/qqllql:b00700070p00700070p0070p0070	I
    //   83: if_icmpeq +111 -> 194
    //   86: ldc 2
    //   88: ldc -94
    //   90: bipush 124
    //   92: iconst_1
    //   93: invokestatic 45	xxxxxx/uxxxxx:bb00620062bb0062b0062b0062	(Ljava/lang/String;CC)Ljava/lang/String;
    //   96: iconst_0
    //   97: anewarray 25	java/lang/Class
    //   100: invokevirtual 49	java/lang/Class:getMethod	(Ljava/lang/String;[Ljava/lang/Class;)Ljava/lang/reflect/Method;
    //   103: astore_1
    //   104: aload_1
    //   105: aconst_null
    //   106: iconst_0
    //   107: anewarray 51	java/lang/Object
    //   110: invokevirtual 57	java/lang/reflect/Method:invoke	(Ljava/lang/Object;[Ljava/lang/Object;)Ljava/lang/Object;
    //   113: astore_1
    //   114: aload_1
    //   115: checkcast 59	java/lang/Integer
    //   118: invokevirtual 63	java/lang/Integer:intValue	()I
    //   121: putstatic 31	uuuuuu/qqllql:bp0070p00700070p0070p0070	I
    //   124: bipush 11
    //   126: putstatic 37	uuuuuu/qqllql:b00700070p00700070p0070p0070	I
    //   129: getstatic 31	uuuuuu/qqllql:bp0070p00700070p0070p0070	I
    //   132: getstatic 33	uuuuuu/qqllql:bpp007000700070p0070p0070	I
    //   135: iadd
    //   136: getstatic 31	uuuuuu/qqllql:bp0070p00700070p0070p0070	I
    //   139: imul
    //   140: getstatic 35	uuuuuu/qqllql:b0070p007000700070p0070p0070	I
    //   143: irem
    //   144: getstatic 37	uuuuuu/qqllql:b00700070p00700070p0070p0070	I
    //   147: if_icmpeq +47 -> 194
    //   150: ldc 2
    //   152: ldc -92
    //   154: sipush 170
    //   157: iconst_4
    //   158: invokestatic 45	xxxxxx/uxxxxx:bb00620062bb0062b0062b0062	(Ljava/lang/String;CC)Ljava/lang/String;
    //   161: iconst_0
    //   162: anewarray 25	java/lang/Class
    //   165: invokevirtual 49	java/lang/Class:getMethod	(Ljava/lang/String;[Ljava/lang/Class;)Ljava/lang/reflect/Method;
    //   168: astore_1
    //   169: aload_1
    //   170: aconst_null
    //   171: iconst_0
    //   172: anewarray 51	java/lang/Object
    //   175: invokevirtual 57	java/lang/reflect/Method:invoke	(Ljava/lang/Object;[Ljava/lang/Object;)Ljava/lang/Object;
    //   178: astore_1
    //   179: aload_1
    //   180: checkcast 59	java/lang/Integer
    //   183: invokevirtual 63	java/lang/Integer:intValue	()I
    //   186: putstatic 31	uuuuuu/qqllql:bp0070p00700070p0070p0070	I
    //   189: bipush 34
    //   191: putstatic 37	uuuuuu/qqllql:b00700070p00700070p0070p0070	I
    //   194: iconst_0
    //   195: ireturn
    //   196: astore_1
    //   197: aload_1
    //   198: invokevirtual 81	java/lang/reflect/InvocationTargetException:getCause	()Ljava/lang/Throwable;
    //   201: athrow
    //   202: astore_1
    //   203: aload_1
    //   204: invokevirtual 81	java/lang/reflect/InvocationTargetException:getCause	()Ljava/lang/Throwable;
    //   207: athrow
    //   208: astore_1
    //   209: aload_1
    //   210: invokevirtual 81	java/lang/reflect/InvocationTargetException:getCause	()Ljava/lang/Throwable;
    //   213: athrow
    // Local variable table:
    //   start	length	slot	name	signature
    //   0	214	0	this	qqllql
    //   39	141	1	localObject	Object
    //   196	2	1	localInvocationTargetException1	java.lang.reflect.InvocationTargetException
    //   202	2	1	localInvocationTargetException2	java.lang.reflect.InvocationTargetException
    //   208	2	1	localInvocationTargetException3	java.lang.reflect.InvocationTargetException
    // Exception table:
    //   from	to	target	type
    //   104	114	196	java/lang/reflect/InvocationTargetException
    //   40	50	202	java/lang/reflect/InvocationTargetException
    //   169	179	208	java/lang/reflect/InvocationTargetException
  }
  
  /* Error */
  public void boooooo006F006Foo(com.db.pwcc.dbmobile.multi_bank_aggregator.model.MbaTransactionData paramMbaTransactionData)
  {
    // Byte code:
    //   0: aload_0
    //   1: invokevirtual 103	uuuuuu/qqllql:bkk006Bk006Bk006Bk006Bk	()Z
    //   4: ifne +4 -> 8
    //   7: return
    //   8: aload_0
    //   9: getfield 170	uuuuuu/qqllql:b00700070p007000700070pp0070	Lcom/db/pwcc/dbmobile/model/banking/Account;
    //   12: astore 4
    //   14: getstatic 31	uuuuuu/qqllql:bp0070p00700070p0070p0070	I
    //   17: istore_2
    //   18: iload_2
    //   19: getstatic 33	uuuuuu/qqllql:bpp007000700070p0070p0070	I
    //   22: iload_2
    //   23: iadd
    //   24: imul
    //   25: getstatic 35	uuuuuu/qqllql:b0070p007000700070p0070p0070	I
    //   28: irem
    //   29: tableswitch	default:+19->48, 0:+29->58
    //   48: bipush 13
    //   50: putstatic 31	uuuuuu/qqllql:bp0070p00700070p0070p0070	I
    //   53: bipush 30
    //   55: putstatic 37	uuuuuu/qqllql:b00700070p00700070p0070p0070	I
    //   58: aload_1
    //   59: aload 4
    //   61: invokevirtual 175	com/db/pwcc/dbmobile/model/banking/Account:getBaseCurrency	()Ljava/lang/String;
    //   64: invokevirtual 180	com/db/pwcc/dbmobile/multi_bank_aggregator/model/MbaTransactionData:setBaseCurrency	(Ljava/lang/String;)V
    //   67: aload_0
    //   68: getfield 184	uuuuuu/qqllql:bpp0070007000700070pp0070	Luuuuuu/heeeeh;
    //   71: aload_1
    //   72: invokestatic 190	uuuuuu/osssoo:bi0069i0069i00690069iii	(Lcom/db/pwcc/dbmobile/multi_bank_aggregator/model/MbaTransactionData;)Lcom/db/pwcc/dbmobile/model/banking/TransactionsData;
    //   75: invokevirtual 196	uuuuuu/heeeeh:b006F006F006Foooooo006F	(Lcom/db/pwcc/dbmobile/model/banking/TransactionsData;)V
    //   78: aload_0
    //   79: getfield 184	uuuuuu/qqllql:bpp0070007000700070pp0070	Luuuuuu/heeeeh;
    //   82: invokevirtual 200	uuuuuu/heeeeh:boo006Foooooo006F	()Lcom/db/pwcc/dbmobile/model/banking/TransactionsData;
    //   85: aload_0
    //   86: getfield 170	uuuuuu/qqllql:b00700070p007000700070pp0070	Lcom/db/pwcc/dbmobile/model/banking/Account;
    //   89: invokevirtual 206	com/db/pwcc/dbmobile/model/banking/TransactionsData:setAccount	(Lcom/db/pwcc/dbmobile/model/banking/Account;)V
    //   92: aload_0
    //   93: getfield 115	uuuuuu/qqllql:bnnnnn006E006E006En	Luuuuuu/ttssst$tsssst;
    //   96: checkcast 117	uuuuuu/llqqll$lqqqll
    //   99: aload_0
    //   100: getfield 170	uuuuuu/qqllql:b00700070p007000700070pp0070	Lcom/db/pwcc/dbmobile/model/banking/Account;
    //   103: invokeinterface 209 2 0
    //   108: aload_0
    //   109: getfield 115	uuuuuu/qqllql:bnnnnn006E006E006En	Luuuuuu/ttssst$tsssst;
    //   112: checkcast 117	uuuuuu/llqqll$lqqqll
    //   115: invokeinterface 212 1 0
    //   120: aload_0
    //   121: invokevirtual 215	uuuuuu/qqllql:bo006F006F006Fo006Fo006Foo	()Z
    //   124: ifeq +19 -> 143
    //   127: aload_0
    //   128: getfield 115	uuuuuu/qqllql:bnnnnn006E006E006En	Luuuuuu/ttssst$tsssst;
    //   131: checkcast 117	uuuuuu/llqqll$lqqqll
    //   134: getstatic 220	com/db/pwcc/dbmobile/financial_overview/R$string:no_transactions_available	I
    //   137: invokeinterface 224 2 0
    //   142: return
    //   143: aload_0
    //   144: getfield 115	uuuuuu/qqllql:bnnnnn006E006E006En	Luuuuuu/ttssst$tsssst;
    //   147: checkcast 117	uuuuuu/llqqll$lqqqll
    //   150: astore_1
    //   151: aload_0
    //   152: getfield 184	uuuuuu/qqllql:bpp0070007000700070pp0070	Luuuuuu/heeeeh;
    //   155: invokevirtual 200	uuuuuu/heeeeh:boo006Foooooo006F	()Lcom/db/pwcc/dbmobile/model/banking/TransactionsData;
    //   158: astore 4
    //   160: getstatic 31	uuuuuu/qqllql:bp0070p00700070p0070p0070	I
    //   163: istore_2
    //   164: iload_2
    //   165: getstatic 33	uuuuuu/qqllql:bpp007000700070p0070p0070	I
    //   168: iload_2
    //   169: iadd
    //   170: imul
    //   171: getstatic 35	uuuuuu/qqllql:b0070p007000700070p0070p0070	I
    //   174: irem
    //   175: tableswitch	default:+17->192, 0:+68->243
    //   192: bipush 94
    //   194: putstatic 31	uuuuuu/qqllql:bp0070p00700070p0070p0070	I
    //   197: ldc 2
    //   199: ldc -30
    //   201: sipush 254
    //   204: sipush 193
    //   207: iconst_0
    //   208: invokestatic 77	xxxxxx/uxxxxx:bbbb0062b0062b0062b0062	(Ljava/lang/String;CCC)Ljava/lang/String;
    //   211: iconst_0
    //   212: anewarray 25	java/lang/Class
    //   215: invokevirtual 49	java/lang/Class:getMethod	(Ljava/lang/String;[Ljava/lang/Class;)Ljava/lang/reflect/Method;
    //   218: astore 5
    //   220: aload 5
    //   222: aconst_null
    //   223: iconst_0
    //   224: anewarray 51	java/lang/Object
    //   227: invokevirtual 57	java/lang/reflect/Method:invoke	(Ljava/lang/Object;[Ljava/lang/Object;)Ljava/lang/Object;
    //   230: astore 5
    //   232: aload 5
    //   234: checkcast 59	java/lang/Integer
    //   237: invokevirtual 63	java/lang/Integer:intValue	()I
    //   240: putstatic 37	uuuuuu/qqllql:b00700070p00700070p0070p0070	I
    //   243: aload_1
    //   244: aload 4
    //   246: aload_0
    //   247: getfield 184	uuuuuu/qqllql:bpp0070007000700070pp0070	Luuuuuu/heeeeh;
    //   250: invokevirtual 230	uuuuuu/heeeeh:b006F006Fooooooo006F	()Lcom/db/pwcc/dbmobile/model/banking/FinancialOverviewData;
    //   253: aload_0
    //   254: getfield 153	uuuuuu/qqllql:bp0070p007000700070pp0070	Ljava/lang/String;
    //   257: invokevirtual 236	com/db/pwcc/dbmobile/model/banking/FinancialOverviewData:getAccountByID	(Ljava/lang/String;)Lcom/db/pwcc/dbmobile/model/banking/Account;
    //   260: invokeinterface 240 3 0
    //   265: aload_0
    //   266: getfield 115	uuuuuu/qqllql:bnnnnn006E006E006En	Luuuuuu/ttssst$tsssst;
    //   269: checkcast 117	uuuuuu/llqqll$lqqqll
    //   272: astore_1
    //   273: aload_0
    //   274: invokevirtual 215	uuuuuu/qqllql:bo006F006F006Fo006Fo006Foo	()Z
    //   277: ifne +123 -> 400
    //   280: iconst_1
    //   281: istore_3
    //   282: aload_1
    //   283: iload_3
    //   284: aconst_null
    //   285: invokeinterface 244 3 0
    //   290: ldc 2
    //   292: ldc -10
    //   294: bipush 62
    //   296: iconst_4
    //   297: invokestatic 45	xxxxxx/uxxxxx:bb00620062bb0062b0062b0062	(Ljava/lang/String;CC)Ljava/lang/String;
    //   300: iconst_0
    //   301: anewarray 25	java/lang/Class
    //   304: invokevirtual 49	java/lang/Class:getMethod	(Ljava/lang/String;[Ljava/lang/Class;)Ljava/lang/reflect/Method;
    //   307: astore_1
    //   308: aload_1
    //   309: aconst_null
    //   310: iconst_0
    //   311: anewarray 51	java/lang/Object
    //   314: invokevirtual 57	java/lang/reflect/Method:invoke	(Ljava/lang/Object;[Ljava/lang/Object;)Ljava/lang/Object;
    //   317: astore_1
    //   318: aload_1
    //   319: checkcast 59	java/lang/Integer
    //   322: invokevirtual 63	java/lang/Integer:intValue	()I
    //   325: istore_2
    //   326: iload_2
    //   327: getstatic 33	uuuuuu/qqllql:bpp007000700070p0070p0070	I
    //   330: iload_2
    //   331: iadd
    //   332: imul
    //   333: getstatic 35	uuuuuu/qqllql:b0070p007000700070p0070p0070	I
    //   336: irem
    //   337: tableswitch	default:+19->356, 0:+-330->7
    //   356: bipush 43
    //   358: putstatic 31	uuuuuu/qqllql:bp0070p00700070p0070p0070	I
    //   361: ldc 2
    //   363: ldc -8
    //   365: bipush 70
    //   367: iconst_1
    //   368: invokestatic 45	xxxxxx/uxxxxx:bb00620062bb0062b0062b0062	(Ljava/lang/String;CC)Ljava/lang/String;
    //   371: iconst_0
    //   372: anewarray 25	java/lang/Class
    //   375: invokevirtual 49	java/lang/Class:getMethod	(Ljava/lang/String;[Ljava/lang/Class;)Ljava/lang/reflect/Method;
    //   378: astore_1
    //   379: aload_1
    //   380: aconst_null
    //   381: iconst_0
    //   382: anewarray 51	java/lang/Object
    //   385: invokevirtual 57	java/lang/reflect/Method:invoke	(Ljava/lang/Object;[Ljava/lang/Object;)Ljava/lang/Object;
    //   388: astore_1
    //   389: aload_1
    //   390: checkcast 59	java/lang/Integer
    //   393: invokevirtual 63	java/lang/Integer:intValue	()I
    //   396: putstatic 37	uuuuuu/qqllql:b00700070p00700070p0070p0070	I
    //   399: return
    //   400: getstatic 31	uuuuuu/qqllql:bp0070p00700070p0070p0070	I
    //   403: getstatic 33	uuuuuu/qqllql:bpp007000700070p0070p0070	I
    //   406: iadd
    //   407: getstatic 31	uuuuuu/qqllql:bp0070p00700070p0070p0070	I
    //   410: imul
    //   411: getstatic 35	uuuuuu/qqllql:b0070p007000700070p0070p0070	I
    //   414: irem
    //   415: getstatic 37	uuuuuu/qqllql:b00700070p00700070p0070p0070	I
    //   418: if_icmpeq +51 -> 469
    //   421: bipush 59
    //   423: putstatic 31	uuuuuu/qqllql:bp0070p00700070p0070p0070	I
    //   426: ldc 2
    //   428: ldc -6
    //   430: sipush 198
    //   433: iconst_1
    //   434: invokestatic 45	xxxxxx/uxxxxx:bb00620062bb0062b0062b0062	(Ljava/lang/String;CC)Ljava/lang/String;
    //   437: iconst_0
    //   438: anewarray 25	java/lang/Class
    //   441: invokevirtual 49	java/lang/Class:getMethod	(Ljava/lang/String;[Ljava/lang/Class;)Ljava/lang/reflect/Method;
    //   444: astore 4
    //   446: aload 4
    //   448: aconst_null
    //   449: iconst_0
    //   450: anewarray 51	java/lang/Object
    //   453: invokevirtual 57	java/lang/reflect/Method:invoke	(Ljava/lang/Object;[Ljava/lang/Object;)Ljava/lang/Object;
    //   456: astore 4
    //   458: aload 4
    //   460: checkcast 59	java/lang/Integer
    //   463: invokevirtual 63	java/lang/Integer:intValue	()I
    //   466: putstatic 37	uuuuuu/qqllql:b00700070p00700070p0070p0070	I
    //   469: iconst_0
    //   470: istore_3
    //   471: goto -189 -> 282
    //   474: astore_1
    //   475: aload_1
    //   476: invokevirtual 81	java/lang/reflect/InvocationTargetException:getCause	()Ljava/lang/Throwable;
    //   479: athrow
    //   480: astore_1
    //   481: aload_1
    //   482: invokevirtual 81	java/lang/reflect/InvocationTargetException:getCause	()Ljava/lang/Throwable;
    //   485: athrow
    //   486: astore_1
    //   487: aload_1
    //   488: invokevirtual 81	java/lang/reflect/InvocationTargetException:getCause	()Ljava/lang/Throwable;
    //   491: athrow
    //   492: astore_1
    //   493: aload_1
    //   494: invokevirtual 81	java/lang/reflect/InvocationTargetException:getCause	()Ljava/lang/Throwable;
    //   497: athrow
    // Local variable table:
    //   start	length	slot	name	signature
    //   0	498	0	this	qqllql
    //   0	498	1	paramMbaTransactionData	com.db.pwcc.dbmobile.multi_bank_aggregator.model.MbaTransactionData
    //   17	316	2	i	int
    //   281	190	3	bool	boolean
    //   12	447	4	localObject1	Object
    //   218	15	5	localObject2	Object
    // Exception table:
    //   from	to	target	type
    //   379	389	474	java/lang/reflect/InvocationTargetException
    //   308	318	480	java/lang/reflect/InvocationTargetException
    //   446	458	486	java/lang/reflect/InvocationTargetException
    //   220	232	492	java/lang/reflect/InvocationTargetException
  }
}
