package uuuuuu;

import com.db.pwcc.dbmobile.model.error.DbError;
import com.db.pwcc.dbmobile.model.error.DbErrorCode;
import com.db.pwcc.dbmobile.multi_bank_aggregator.R.string;
import java.lang.reflect.InvocationTargetException;
import java.lang.reflect.Method;
import xxxxxx.uxxxxx;

public class qqqmmm
  extends qppppp<mqmqmm.mmmqmm>
  implements mqmqmm.qmmqmm, allaal.lalaal, aalaal.llaaal, aaalal.lllaal
{
  public static int b00760076007600760076v00760076v = 86;
  public static int b0076vvvv007600760076v = 2;
  public static int bv0076vvv007600760076v = 1;
  public static int bvvvvv007600760076v;
  
  public qqqmmm() {}
  
  public static int b00750075uu0075uu0075u0075()
  {
    return 2;
  }
  
  private void bu0075007500750075uu0075u0075(DbError paramDbError)
  {
    int i;
    Object localObject;
    if (DbErrorCode.NO_INTERNET_ERROR == paramDbError.getDbCode())
    {
      paramDbError = (mqmqmm.mmmqmm)this.bnnnnn006E006E006En;
      i = b00760076007600760076v00760076v;
      localObject = qqqmmm.class.getMethod(uxxxxx.bb00620062bb0062b0062b0062("Qe!\"*)jk'(0/pq-.65v23;:", '7', '\001'), new Class[0]);
    }
    for (;;)
    {
      try
      {
        localObject = ((Method)localObject).invoke(null, new Object[0]);
        if ((((Integer)localObject).intValue() + i) * b00760076007600760076v00760076v % b0076vvvv007600760076v != bvvvvv007600760076v)
        {
          i = b00760076007600760076v00760076v;
          switch (i * (bv0076vvv007600760076v + i) % b0076vvvv007600760076v)
          {
          default: 
            if ((b00760076007600760076v00760076v + bv0076vvv007600760076v) * b00760076007600760076v00760076v % b0076vvvv007600760076v != bvvvvv007600760076v) {
              localObject = qqqmmm.class.getMethod(uxxxxx.bbbb0062b0062b0062b0062("\013\037 [\\dc%`aih*+fgon0klts", 'f', '½', '\002'), new Class[0]);
            }
            break;
          }
        }
      }
      catch (InvocationTargetException paramDbError)
      {
        throw paramDbError.getCause();
      }
      try
      {
        localObject = ((Method)localObject).invoke(null, new Object[0]);
        b00760076007600760076v00760076v = ((Integer)localObject).intValue();
        localObject = qqqmmm.class.getMethod(uxxxxx.bbbb0062b0062b0062b0062("w\n\tBAGD\004=<B?~}76<9x2174", '\n', '`', '\000'), new Class[0]);
        try
        {
          localObject = ((Method)localObject).invoke(null, new Object[0]);
          bvvvvv007600760076v = ((Integer)localObject).intValue();
          b00760076007600760076v00760076v = 3;
          localObject = qqqmmm.class.getMethod(uxxxxx.bbbb0062b0062b0062b0062("o\004\005@AIH\nEFNM\017\020KLTS\025PQYX", '.', 'Ý', '\003'), new Class[0]);
        }
        catch (InvocationTargetException paramDbError)
        {
          throw paramDbError.getCause();
        }
        try
        {
          localObject = ((Method)localObject).invoke(null, new Object[0]);
          bvvvvv007600760076v = ((Integer)localObject).intValue();
          localObject = qqqmmm.class.getMethod(uxxxxx.bbbb0062b0062b0062b0062("Thi%&.-n*+32st0198y56>=", 'K', '&', '\003'), new Class[0]);
          try
          {
            localObject = ((Method)localObject).invoke(null, new Object[0]);
            b00760076007600760076v00760076v = ((Integer)localObject).intValue();
            bvvvvv007600760076v = 88;
            localObject = qqqmmm.class.getMethod(uxxxxx.bbbb0062b0062b0062b0062("^po)(.+j$#)&ed\036\035# _\031\030\036\033", '^', '¤', '\000'), new Class[0]);
            try
            {
              localObject = ((Method)localObject).invoke(null, new Object[0]);
              i = ((Integer)localObject).intValue();
              j = bv0076vvv007600760076v;
              localObject = qqqmmm.class.getMethod(uxxxxx.bbbb0062b0062b0062b0062("!56qrzy;vw~@A|}\006\005F\002\003\013\n", 'V', '', '\002'), new Class[0]);
            }
            catch (InvocationTargetException paramDbError)
            {
              int j;
              throw paramDbError.getCause();
            }
            try
            {
              localObject = ((Method)localObject).invoke(null, new Object[0]);
              if (((Integer)localObject).intValue() * (j + i) % b0076vvvv007600760076v != bvvvvv007600760076v) {
                localObject = qqqmmm.class.getMethod(uxxxxx.bb00620062bb0062b0062b0062("3ED}|\003?xw}z:9rqwt4mlro", '/', '\003'), new Class[0]);
              }
            }
            catch (InvocationTargetException paramDbError)
            {
              throw paramDbError.getCause();
            }
          }
          catch (InvocationTargetException paramDbError)
          {
            throw paramDbError.getCause();
          }
        }
        catch (InvocationTargetException paramDbError)
        {
          throw paramDbError.getCause();
        }
      }
      catch (InvocationTargetException paramDbError)
      {
        throw paramDbError.getCause();
      }
    }
    try
    {
      localObject = ((Method)localObject).invoke(null, new Object[0]);
      b00760076007600760076v00760076v = ((Integer)localObject).intValue();
      bvvvvv007600760076v = 83;
      paramDbError.showNoInternetError(false, null);
      return;
    }
    catch (InvocationTargetException paramDbError)
    {
      throw paramDbError.getCause();
    }
    ((mqmqmm.mmmqmm)this.bnnnnn006E006E006En).showError(R.string.technical_error_retry);
  }
  
  public static int bu00750075u0075uu0075u0075()
  {
    return 0;
  }
  
  public static int bu0075uu0075uu0075u0075()
  {
    return 1;
  }
  
  public static int buu0075u0075uu0075u0075()
  {
    return 71;
  }
  
  /* Error */
  public void b007500750075u0075uu0075u0075()
  {
    // Byte code:
    //   0: aload_0
    //   1: getfield 48	uuuuuu/qqqmmm:bnnnnn006E006E006En	Luuuuuu/ttssst$tsssst;
    //   4: checkcast 50	uuuuuu/mqmqmm$mmmqmm
    //   7: invokeinterface 127 1 0
    //   12: aload_0
    //   13: getfield 131	uuuuuu/qqqmmm:b006E006E006E006E006En006E006En	Luuuuuu/hyhyhh;
    //   16: invokevirtual 137	uuuuuu/hyhyhh:bp0070p007000700070p007000700070	()Luuuuuu/yhhyhh;
    //   19: invokevirtual 143	uuuuuu/yhhyhh:bp0070p0070p0070p007000700070	()Z
    //   22: ifeq +336 -> 358
    //   25: new 145	uuuuuu/aaaaal
    //   28: dup
    //   29: invokespecial 146	uuuuuu/aaaaal:<init>	()V
    //   32: aload_0
    //   33: aload_0
    //   34: getfield 131	uuuuuu/qqqmmm:b006E006E006E006E006En006E006En	Luuuuuu/hyhyhh;
    //   37: invokevirtual 150	uuuuuu/hyhyhh:bpp0070007000700070p007000700070	()Ljava/lang/String;
    //   40: aload_0
    //   41: getfield 131	uuuuuu/qqqmmm:b006E006E006E006E006En006E006En	Luuuuuu/hyhyhh;
    //   44: invokevirtual 137	uuuuuu/hyhyhh:bp0070p007000700070p007000700070	()Luuuuuu/yhhyhh;
    //   47: invokevirtual 153	uuuuuu/yhhyhh:b0070pp0070p0070p007000700070	()I
    //   50: invokestatic 159	java/lang/String:valueOf	(I)Ljava/lang/String;
    //   53: getstatic 165	com/db/pwcc/dbmobile/multi_bank_aggregator/model/consents/Status:INACTIVE	Lcom/db/pwcc/dbmobile/multi_bank_aggregator/model/consents/Status;
    //   56: invokevirtual 169	uuuuuu/aaaaal:buuuu007500750075007500750075	(Luuuuuu/allaal$lalaal;Ljava/lang/String;Ljava/lang/String;Lcom/db/pwcc/dbmobile/multi_bank_aggregator/model/consents/Status;)V
    //   59: getstatic 52	uuuuuu/qqqmmm:b00760076007600760076v00760076v	I
    //   62: getstatic 85	uuuuuu/qqqmmm:bv0076vvv007600760076v	I
    //   65: iadd
    //   66: getstatic 52	uuuuuu/qqqmmm:b00760076007600760076v00760076v	I
    //   69: imul
    //   70: getstatic 81	uuuuuu/qqqmmm:b0076vvvv007600760076v	I
    //   73: irem
    //   74: getstatic 83	uuuuuu/qqqmmm:bvvvvv007600760076v	I
    //   77: if_icmpeq +50 -> 127
    //   80: ldc 2
    //   82: ldc -85
    //   84: bipush 44
    //   86: iconst_3
    //   87: invokestatic 60	xxxxxx/uxxxxx:bb00620062bb0062b0062b0062	(Ljava/lang/String;CC)Ljava/lang/String;
    //   90: iconst_0
    //   91: anewarray 62	java/lang/Class
    //   94: invokevirtual 66	java/lang/Class:getMethod	(Ljava/lang/String;[Ljava/lang/Class;)Ljava/lang/reflect/Method;
    //   97: astore 6
    //   99: aload 6
    //   101: aconst_null
    //   102: iconst_0
    //   103: anewarray 68	java/lang/Object
    //   106: invokevirtual 74	java/lang/reflect/Method:invoke	(Ljava/lang/Object;[Ljava/lang/Object;)Ljava/lang/Object;
    //   109: astore 6
    //   111: aload 6
    //   113: checkcast 76	java/lang/Integer
    //   116: invokevirtual 79	java/lang/Integer:intValue	()I
    //   119: putstatic 52	uuuuuu/qqqmmm:b00760076007600760076v00760076v	I
    //   122: bipush 99
    //   124: putstatic 83	uuuuuu/qqqmmm:bvvvvv007600760076v	I
    //   127: getstatic 52	uuuuuu/qqqmmm:b00760076007600760076v00760076v	I
    //   130: istore_1
    //   131: iload_1
    //   132: getstatic 85	uuuuuu/qqqmmm:bv0076vvv007600760076v	I
    //   135: iload_1
    //   136: iadd
    //   137: imul
    //   138: getstatic 81	uuuuuu/qqqmmm:b0076vvvv007600760076v	I
    //   141: irem
    //   142: tableswitch	default:+18->160, 0:+216->358
    //   160: bipush 16
    //   162: putstatic 52	uuuuuu/qqqmmm:b00760076007600760076v00760076v	I
    //   165: ldc 2
    //   167: ldc -83
    //   169: bipush 39
    //   171: iconst_0
    //   172: invokestatic 60	xxxxxx/uxxxxx:bb00620062bb0062b0062b0062	(Ljava/lang/String;CC)Ljava/lang/String;
    //   175: iconst_0
    //   176: anewarray 62	java/lang/Class
    //   179: invokevirtual 66	java/lang/Class:getMethod	(Ljava/lang/String;[Ljava/lang/Class;)Ljava/lang/reflect/Method;
    //   182: astore 6
    //   184: aload 6
    //   186: aconst_null
    //   187: iconst_0
    //   188: anewarray 68	java/lang/Object
    //   191: invokevirtual 74	java/lang/reflect/Method:invoke	(Ljava/lang/Object;[Ljava/lang/Object;)Ljava/lang/Object;
    //   194: astore 6
    //   196: aload 6
    //   198: checkcast 76	java/lang/Integer
    //   201: invokevirtual 79	java/lang/Integer:intValue	()I
    //   204: putstatic 83	uuuuuu/qqqmmm:bvvvvv007600760076v	I
    //   207: getstatic 52	uuuuuu/qqqmmm:b00760076007600760076v00760076v	I
    //   210: istore_1
    //   211: getstatic 85	uuuuuu/qqqmmm:bv0076vvv007600760076v	I
    //   214: istore_2
    //   215: getstatic 52	uuuuuu/qqqmmm:b00760076007600760076v00760076v	I
    //   218: istore_3
    //   219: ldc 2
    //   221: ldc -81
    //   223: sipush 147
    //   226: iconst_3
    //   227: invokestatic 60	xxxxxx/uxxxxx:bb00620062bb0062b0062b0062	(Ljava/lang/String;CC)Ljava/lang/String;
    //   230: iconst_0
    //   231: anewarray 62	java/lang/Class
    //   234: invokevirtual 66	java/lang/Class:getMethod	(Ljava/lang/String;[Ljava/lang/Class;)Ljava/lang/reflect/Method;
    //   237: astore 6
    //   239: aload 6
    //   241: aconst_null
    //   242: iconst_0
    //   243: anewarray 68	java/lang/Object
    //   246: invokevirtual 74	java/lang/reflect/Method:invoke	(Ljava/lang/Object;[Ljava/lang/Object;)Ljava/lang/Object;
    //   249: astore 6
    //   251: aload 6
    //   253: checkcast 76	java/lang/Integer
    //   256: invokevirtual 79	java/lang/Integer:intValue	()I
    //   259: istore 4
    //   261: getstatic 83	uuuuuu/qqqmmm:bvvvvv007600760076v	I
    //   264: istore 5
    //   266: getstatic 52	uuuuuu/qqqmmm:b00760076007600760076v00760076v	I
    //   269: getstatic 85	uuuuuu/qqqmmm:bv0076vvv007600760076v	I
    //   272: iadd
    //   273: getstatic 52	uuuuuu/qqqmmm:b00760076007600760076v00760076v	I
    //   276: imul
    //   277: getstatic 81	uuuuuu/qqqmmm:b0076vvvv007600760076v	I
    //   280: irem
    //   281: getstatic 83	uuuuuu/qqqmmm:bvvvvv007600760076v	I
    //   284: if_icmpeq +51 -> 335
    //   287: bipush 47
    //   289: putstatic 52	uuuuuu/qqqmmm:b00760076007600760076v00760076v	I
    //   292: ldc 2
    //   294: ldc -79
    //   296: sipush 148
    //   299: iconst_4
    //   300: invokestatic 60	xxxxxx/uxxxxx:bb00620062bb0062b0062b0062	(Ljava/lang/String;CC)Ljava/lang/String;
    //   303: iconst_0
    //   304: anewarray 62	java/lang/Class
    //   307: invokevirtual 66	java/lang/Class:getMethod	(Ljava/lang/String;[Ljava/lang/Class;)Ljava/lang/reflect/Method;
    //   310: astore 6
    //   312: aload 6
    //   314: aconst_null
    //   315: iconst_0
    //   316: anewarray 68	java/lang/Object
    //   319: invokevirtual 74	java/lang/reflect/Method:invoke	(Ljava/lang/Object;[Ljava/lang/Object;)Ljava/lang/Object;
    //   322: astore 6
    //   324: aload 6
    //   326: checkcast 76	java/lang/Integer
    //   329: invokevirtual 79	java/lang/Integer:intValue	()I
    //   332: putstatic 83	uuuuuu/qqqmmm:bvvvvv007600760076v	I
    //   335: iload_3
    //   336: iload_1
    //   337: iload_2
    //   338: iadd
    //   339: imul
    //   340: iload 4
    //   342: irem
    //   343: iload 5
    //   345: if_icmpeq +13 -> 358
    //   348: bipush 27
    //   350: putstatic 52	uuuuuu/qqqmmm:b00760076007600760076v00760076v	I
    //   353: bipush 64
    //   355: putstatic 83	uuuuuu/qqqmmm:bvvvvv007600760076v	I
    //   358: return
    //   359: astore 6
    //   361: aload 6
    //   363: invokevirtual 120	java/lang/reflect/InvocationTargetException:getCause	()Ljava/lang/Throwable;
    //   366: athrow
    //   367: astore 6
    //   369: aload 6
    //   371: invokevirtual 120	java/lang/reflect/InvocationTargetException:getCause	()Ljava/lang/Throwable;
    //   374: athrow
    //   375: astore 6
    //   377: aload 6
    //   379: invokevirtual 120	java/lang/reflect/InvocationTargetException:getCause	()Ljava/lang/Throwable;
    //   382: athrow
    //   383: astore 6
    //   385: aload 6
    //   387: invokevirtual 120	java/lang/reflect/InvocationTargetException:getCause	()Ljava/lang/Throwable;
    //   390: athrow
    // Local variable table:
    //   start	length	slot	name	signature
    //   0	391	0	this	qqqmmm
    //   130	209	1	i	int
    //   214	125	2	j	int
    //   218	122	3	k	int
    //   259	84	4	m	int
    //   264	82	5	n	int
    //   97	228	6	localObject	Object
    //   359	3	6	localInvocationTargetException1	InvocationTargetException
    //   367	3	6	localInvocationTargetException2	InvocationTargetException
    //   375	3	6	localInvocationTargetException3	InvocationTargetException
    //   383	3	6	localInvocationTargetException4	InvocationTargetException
    // Exception table:
    //   from	to	target	type
    //   184	196	359	java/lang/reflect/InvocationTargetException
    //   99	111	367	java/lang/reflect/InvocationTargetException
    //   239	251	375	java/lang/reflect/InvocationTargetException
    //   312	324	383	java/lang/reflect/InvocationTargetException
  }
  
  /* Error */
  public void b00750075u00750075uu0075u0075(com.db.pwcc.dbmobile.multi_bank_aggregator.model.consents.PostConsentResponse paramPostConsentResponse)
  {
    // Byte code:
    //   0: aload_0
    //   1: getfield 131	uuuuuu/qqqmmm:b006E006E006E006E006En006E006En	Luuuuuu/hyhyhh;
    //   4: invokevirtual 137	uuuuuu/hyhyhh:bp0070p007000700070p007000700070	()Luuuuuu/yhhyhh;
    //   7: invokevirtual 182	uuuuuu/yhhyhh:bp007000700070p0070p007000700070	()V
    //   10: aload_0
    //   11: invokevirtual 185	uuuuuu/qqqmmm:bkk006Bk006Bk006Bk006Bk	()Z
    //   14: ifne +4 -> 18
    //   17: return
    //   18: new 187	uuuuuu/alaaal
    //   21: dup
    //   22: invokespecial 188	uuuuuu/alaaal:<init>	()V
    //   25: aload_0
    //   26: aload_0
    //   27: getfield 131	uuuuuu/qqqmmm:b006E006E006E006E006En006E006En	Luuuuuu/hyhyhh;
    //   30: invokevirtual 150	uuuuuu/hyhyhh:bpp0070007000700070p007000700070	()Ljava/lang/String;
    //   33: invokevirtual 192	uuuuuu/alaaal:b0075007500750075u00750075007500750075	(Luuuuuu/aaalal$lllaal;Ljava/lang/String;)V
    //   36: getstatic 52	uuuuuu/qqqmmm:b00760076007600760076v00760076v	I
    //   39: istore_2
    //   40: getstatic 85	uuuuuu/qqqmmm:bv0076vvv007600760076v	I
    //   43: istore_3
    //   44: getstatic 52	uuuuuu/qqqmmm:b00760076007600760076v00760076v	I
    //   47: istore 4
    //   49: getstatic 85	uuuuuu/qqqmmm:bv0076vvv007600760076v	I
    //   52: istore 5
    //   54: ldc 2
    //   56: ldc -62
    //   58: bipush 73
    //   60: bipush 115
    //   62: iconst_0
    //   63: invokestatic 91	xxxxxx/uxxxxx:bbbb0062b0062b0062b0062	(Ljava/lang/String;CCC)Ljava/lang/String;
    //   66: iconst_0
    //   67: anewarray 62	java/lang/Class
    //   70: invokevirtual 66	java/lang/Class:getMethod	(Ljava/lang/String;[Ljava/lang/Class;)Ljava/lang/reflect/Method;
    //   73: astore_1
    //   74: aload_1
    //   75: aconst_null
    //   76: iconst_0
    //   77: anewarray 68	java/lang/Object
    //   80: invokevirtual 74	java/lang/reflect/Method:invoke	(Ljava/lang/Object;[Ljava/lang/Object;)Ljava/lang/Object;
    //   83: astore_1
    //   84: aload_1
    //   85: checkcast 76	java/lang/Integer
    //   88: invokevirtual 79	java/lang/Integer:intValue	()I
    //   91: istore 6
    //   93: getstatic 52	uuuuuu/qqqmmm:b00760076007600760076v00760076v	I
    //   96: istore 7
    //   98: ldc 2
    //   100: ldc -60
    //   102: bipush 115
    //   104: iconst_5
    //   105: invokestatic 60	xxxxxx/uxxxxx:bb00620062bb0062b0062b0062	(Ljava/lang/String;CC)Ljava/lang/String;
    //   108: iconst_0
    //   109: anewarray 62	java/lang/Class
    //   112: invokevirtual 66	java/lang/Class:getMethod	(Ljava/lang/String;[Ljava/lang/Class;)Ljava/lang/reflect/Method;
    //   115: astore_1
    //   116: aload_1
    //   117: aconst_null
    //   118: iconst_0
    //   119: anewarray 68	java/lang/Object
    //   122: invokevirtual 74	java/lang/reflect/Method:invoke	(Ljava/lang/Object;[Ljava/lang/Object;)Ljava/lang/Object;
    //   125: astore_1
    //   126: aload_1
    //   127: checkcast 76	java/lang/Integer
    //   130: invokevirtual 79	java/lang/Integer:intValue	()I
    //   133: iload 7
    //   135: iadd
    //   136: iload 7
    //   138: imul
    //   139: getstatic 81	uuuuuu/qqqmmm:b0076vvvv007600760076v	I
    //   142: irem
    //   143: tableswitch	default:+17->160, 0:+27->170
    //   160: bipush 78
    //   162: putstatic 52	uuuuuu/qqqmmm:b00760076007600760076v00760076v	I
    //   165: bipush 54
    //   167: putstatic 83	uuuuuu/qqqmmm:bvvvvv007600760076v	I
    //   170: iload 5
    //   172: iload 4
    //   174: iadd
    //   175: iload 4
    //   177: imul
    //   178: iload 6
    //   180: irem
    //   181: tableswitch	default:+19->200, 0:+145->326
    //   200: bipush 45
    //   202: putstatic 52	uuuuuu/qqqmmm:b00760076007600760076v00760076v	I
    //   205: ldc 2
    //   207: ldc -58
    //   209: bipush 16
    //   211: iconst_0
    //   212: invokestatic 60	xxxxxx/uxxxxx:bb00620062bb0062b0062b0062	(Ljava/lang/String;CC)Ljava/lang/String;
    //   215: iconst_0
    //   216: anewarray 62	java/lang/Class
    //   219: invokevirtual 66	java/lang/Class:getMethod	(Ljava/lang/String;[Ljava/lang/Class;)Ljava/lang/reflect/Method;
    //   222: astore_1
    //   223: aload_1
    //   224: aconst_null
    //   225: iconst_0
    //   226: anewarray 68	java/lang/Object
    //   229: invokevirtual 74	java/lang/reflect/Method:invoke	(Ljava/lang/Object;[Ljava/lang/Object;)Ljava/lang/Object;
    //   232: astore_1
    //   233: aload_1
    //   234: checkcast 76	java/lang/Integer
    //   237: invokevirtual 79	java/lang/Integer:intValue	()I
    //   240: putstatic 83	uuuuuu/qqqmmm:bvvvvv007600760076v	I
    //   243: getstatic 52	uuuuuu/qqqmmm:b00760076007600760076v00760076v	I
    //   246: istore 4
    //   248: iload 4
    //   250: getstatic 85	uuuuuu/qqqmmm:bv0076vvv007600760076v	I
    //   253: iload 4
    //   255: iadd
    //   256: imul
    //   257: getstatic 81	uuuuuu/qqqmmm:b0076vvvv007600760076v	I
    //   260: irem
    //   261: tableswitch	default:+19->280, 0:+65->326
    //   280: ldc 2
    //   282: ldc -56
    //   284: sipush 154
    //   287: bipush 51
    //   289: iconst_3
    //   290: invokestatic 91	xxxxxx/uxxxxx:bbbb0062b0062b0062b0062	(Ljava/lang/String;CCC)Ljava/lang/String;
    //   293: iconst_0
    //   294: anewarray 62	java/lang/Class
    //   297: invokevirtual 66	java/lang/Class:getMethod	(Ljava/lang/String;[Ljava/lang/Class;)Ljava/lang/reflect/Method;
    //   300: astore_1
    //   301: aload_1
    //   302: aconst_null
    //   303: iconst_0
    //   304: anewarray 68	java/lang/Object
    //   307: invokevirtual 74	java/lang/reflect/Method:invoke	(Ljava/lang/Object;[Ljava/lang/Object;)Ljava/lang/Object;
    //   310: astore_1
    //   311: aload_1
    //   312: checkcast 76	java/lang/Integer
    //   315: invokevirtual 79	java/lang/Integer:intValue	()I
    //   318: putstatic 52	uuuuuu/qqqmmm:b00760076007600760076v00760076v	I
    //   321: bipush 20
    //   323: putstatic 83	uuuuuu/qqqmmm:bvvvvv007600760076v	I
    //   326: ldc 2
    //   328: ldc -54
    //   330: sipush 220
    //   333: bipush 91
    //   335: iconst_1
    //   336: invokestatic 91	xxxxxx/uxxxxx:bbbb0062b0062b0062b0062	(Ljava/lang/String;CCC)Ljava/lang/String;
    //   339: iconst_0
    //   340: anewarray 62	java/lang/Class
    //   343: invokevirtual 66	java/lang/Class:getMethod	(Ljava/lang/String;[Ljava/lang/Class;)Ljava/lang/reflect/Method;
    //   346: astore_1
    //   347: aload_1
    //   348: aconst_null
    //   349: iconst_0
    //   350: anewarray 68	java/lang/Object
    //   353: invokevirtual 74	java/lang/reflect/Method:invoke	(Ljava/lang/Object;[Ljava/lang/Object;)Ljava/lang/Object;
    //   356: astore_1
    //   357: iload_3
    //   358: iload_2
    //   359: iadd
    //   360: iload_2
    //   361: imul
    //   362: aload_1
    //   363: checkcast 76	java/lang/Integer
    //   366: invokevirtual 79	java/lang/Integer:intValue	()I
    //   369: irem
    //   370: tableswitch	default:+18->388, 0:+-353->17
    //   388: bipush 45
    //   390: putstatic 52	uuuuuu/qqqmmm:b00760076007600760076v00760076v	I
    //   393: ldc 2
    //   395: ldc -52
    //   397: bipush 127
    //   399: bipush 80
    //   401: iconst_3
    //   402: invokestatic 91	xxxxxx/uxxxxx:bbbb0062b0062b0062b0062	(Ljava/lang/String;CCC)Ljava/lang/String;
    //   405: iconst_0
    //   406: anewarray 62	java/lang/Class
    //   409: invokevirtual 66	java/lang/Class:getMethod	(Ljava/lang/String;[Ljava/lang/Class;)Ljava/lang/reflect/Method;
    //   412: astore_1
    //   413: aload_1
    //   414: aconst_null
    //   415: iconst_0
    //   416: anewarray 68	java/lang/Object
    //   419: invokevirtual 74	java/lang/reflect/Method:invoke	(Ljava/lang/Object;[Ljava/lang/Object;)Ljava/lang/Object;
    //   422: astore_1
    //   423: aload_1
    //   424: checkcast 76	java/lang/Integer
    //   427: invokevirtual 79	java/lang/Integer:intValue	()I
    //   430: putstatic 83	uuuuuu/qqqmmm:bvvvvv007600760076v	I
    //   433: return
    //   434: astore_1
    //   435: aload_1
    //   436: invokevirtual 120	java/lang/reflect/InvocationTargetException:getCause	()Ljava/lang/Throwable;
    //   439: athrow
    //   440: astore_1
    //   441: aload_1
    //   442: invokevirtual 120	java/lang/reflect/InvocationTargetException:getCause	()Ljava/lang/Throwable;
    //   445: athrow
    //   446: astore_1
    //   447: aload_1
    //   448: invokevirtual 120	java/lang/reflect/InvocationTargetException:getCause	()Ljava/lang/Throwable;
    //   451: athrow
    //   452: astore_1
    //   453: aload_1
    //   454: invokevirtual 120	java/lang/reflect/InvocationTargetException:getCause	()Ljava/lang/Throwable;
    //   457: athrow
    //   458: astore_1
    //   459: aload_1
    //   460: invokevirtual 120	java/lang/reflect/InvocationTargetException:getCause	()Ljava/lang/Throwable;
    //   463: athrow
    //   464: astore_1
    //   465: aload_1
    //   466: invokevirtual 120	java/lang/reflect/InvocationTargetException:getCause	()Ljava/lang/Throwable;
    //   469: athrow
    // Local variable table:
    //   start	length	slot	name	signature
    //   0	470	0	this	qqqmmm
    //   0	470	1	paramPostConsentResponse	com.db.pwcc.dbmobile.multi_bank_aggregator.model.consents.PostConsentResponse
    //   39	323	2	i	int
    //   43	317	3	j	int
    //   47	210	4	k	int
    //   52	123	5	m	int
    //   91	90	6	n	int
    //   96	43	7	i1	int
    // Exception table:
    //   from	to	target	type
    //   223	233	434	java/lang/reflect/InvocationTargetException
    //   74	84	440	java/lang/reflect/InvocationTargetException
    //   347	357	446	java/lang/reflect/InvocationTargetException
    //   413	423	452	java/lang/reflect/InvocationTargetException
    //   116	126	458	java/lang/reflect/InvocationTargetException
    //   301	311	464	java/lang/reflect/InvocationTargetException
  }
  
  /* Error */
  public void b0075u007500750075uu0075u0075(com.db.pwcc.dbmobile.multi_bank_aggregator.model.consents.ConsentsResponse paramConsentsResponse)
  {
    // Byte code:
    //   0: aload_0
    //   1: invokevirtual 185	uuuuuu/qqqmmm:bkk006Bk006Bk006Bk006Bk	()Z
    //   4: ifne +31 -> 35
    //   7: return
    //   8: aload_0
    //   9: getfield 131	uuuuuu/qqqmmm:b006E006E006E006E006En006E006En	Luuuuuu/hyhyhh;
    //   12: invokevirtual 137	uuuuuu/hyhyhh:bp0070p007000700070p007000700070	()Luuuuuu/yhhyhh;
    //   15: aload_1
    //   16: invokevirtual 212	com/db/pwcc/dbmobile/multi_bank_aggregator/model/consents/ConsentsResponse:getConsents	()Ljava/util/List;
    //   19: iconst_0
    //   20: invokeinterface 218 2 0
    //   25: checkcast 220	com/db/pwcc/dbmobile/multi_bank_aggregator/model/consents/Consent
    //   28: invokevirtual 223	com/db/pwcc/dbmobile/multi_bank_aggregator/model/consents/Consent:getId	()I
    //   31: invokevirtual 226	uuuuuu/yhhyhh:b0070007000700070p0070p007000700070	(I)V
    //   34: return
    //   35: aload_0
    //   36: getfield 48	uuuuuu/qqqmmm:bnnnnn006E006E006En	Luuuuuu/ttssst$tsssst;
    //   39: astore 4
    //   41: getstatic 52	uuuuuu/qqqmmm:b00760076007600760076v00760076v	I
    //   44: istore_2
    //   45: getstatic 85	uuuuuu/qqqmmm:bv0076vvv007600760076v	I
    //   48: istore_3
    //   49: getstatic 52	uuuuuu/qqqmmm:b00760076007600760076v00760076v	I
    //   52: getstatic 85	uuuuuu/qqqmmm:bv0076vvv007600760076v	I
    //   55: iadd
    //   56: getstatic 52	uuuuuu/qqqmmm:b00760076007600760076v00760076v	I
    //   59: imul
    //   60: getstatic 81	uuuuuu/qqqmmm:b0076vvvv007600760076v	I
    //   63: irem
    //   64: getstatic 83	uuuuuu/qqqmmm:bvvvvv007600760076v	I
    //   67: if_icmpeq +124 -> 191
    //   70: getstatic 52	uuuuuu/qqqmmm:b00760076007600760076v00760076v	I
    //   73: getstatic 85	uuuuuu/qqqmmm:bv0076vvv007600760076v	I
    //   76: iadd
    //   77: getstatic 52	uuuuuu/qqqmmm:b00760076007600760076v00760076v	I
    //   80: imul
    //   81: getstatic 81	uuuuuu/qqqmmm:b0076vvvv007600760076v	I
    //   84: irem
    //   85: getstatic 83	uuuuuu/qqqmmm:bvvvvv007600760076v	I
    //   88: if_icmpeq +53 -> 141
    //   91: bipush 88
    //   93: putstatic 52	uuuuuu/qqqmmm:b00760076007600760076v00760076v	I
    //   96: ldc 2
    //   98: ldc -28
    //   100: bipush 61
    //   102: sipush 164
    //   105: iconst_1
    //   106: invokestatic 91	xxxxxx/uxxxxx:bbbb0062b0062b0062b0062	(Ljava/lang/String;CCC)Ljava/lang/String;
    //   109: iconst_0
    //   110: anewarray 62	java/lang/Class
    //   113: invokevirtual 66	java/lang/Class:getMethod	(Ljava/lang/String;[Ljava/lang/Class;)Ljava/lang/reflect/Method;
    //   116: astore 5
    //   118: aload 5
    //   120: aconst_null
    //   121: iconst_0
    //   122: anewarray 68	java/lang/Object
    //   125: invokevirtual 74	java/lang/reflect/Method:invoke	(Ljava/lang/Object;[Ljava/lang/Object;)Ljava/lang/Object;
    //   128: astore 5
    //   130: aload 5
    //   132: checkcast 76	java/lang/Integer
    //   135: invokevirtual 79	java/lang/Integer:intValue	()I
    //   138: putstatic 83	uuuuuu/qqqmmm:bvvvvv007600760076v	I
    //   141: bipush 73
    //   143: putstatic 52	uuuuuu/qqqmmm:b00760076007600760076v00760076v	I
    //   146: ldc 2
    //   148: ldc -26
    //   150: bipush 102
    //   152: sipush 197
    //   155: iconst_2
    //   156: invokestatic 91	xxxxxx/uxxxxx:bbbb0062b0062b0062b0062	(Ljava/lang/String;CCC)Ljava/lang/String;
    //   159: iconst_0
    //   160: anewarray 62	java/lang/Class
    //   163: invokevirtual 66	java/lang/Class:getMethod	(Ljava/lang/String;[Ljava/lang/Class;)Ljava/lang/reflect/Method;
    //   166: astore 5
    //   168: aload 5
    //   170: aconst_null
    //   171: iconst_0
    //   172: anewarray 68	java/lang/Object
    //   175: invokevirtual 74	java/lang/reflect/Method:invoke	(Ljava/lang/Object;[Ljava/lang/Object;)Ljava/lang/Object;
    //   178: astore 5
    //   180: aload 5
    //   182: checkcast 76	java/lang/Integer
    //   185: invokevirtual 79	java/lang/Integer:intValue	()I
    //   188: putstatic 83	uuuuuu/qqqmmm:bvvvvv007600760076v	I
    //   191: getstatic 52	uuuuuu/qqqmmm:b00760076007600760076v00760076v	I
    //   194: iload_3
    //   195: iload_2
    //   196: iadd
    //   197: imul
    //   198: getstatic 81	uuuuuu/qqqmmm:b0076vvvv007600760076v	I
    //   201: irem
    //   202: getstatic 83	uuuuuu/qqqmmm:bvvvvv007600760076v	I
    //   205: if_icmpeq +50 -> 255
    //   208: ldc 2
    //   210: ldc 95
    //   212: bipush 70
    //   214: iconst_1
    //   215: invokestatic 60	xxxxxx/uxxxxx:bb00620062bb0062b0062b0062	(Ljava/lang/String;CC)Ljava/lang/String;
    //   218: iconst_0
    //   219: anewarray 62	java/lang/Class
    //   222: invokevirtual 66	java/lang/Class:getMethod	(Ljava/lang/String;[Ljava/lang/Class;)Ljava/lang/reflect/Method;
    //   225: astore 5
    //   227: aload 5
    //   229: aconst_null
    //   230: iconst_0
    //   231: anewarray 68	java/lang/Object
    //   234: invokevirtual 74	java/lang/reflect/Method:invoke	(Ljava/lang/Object;[Ljava/lang/Object;)Ljava/lang/Object;
    //   237: astore 5
    //   239: aload 5
    //   241: checkcast 76	java/lang/Integer
    //   244: invokevirtual 79	java/lang/Integer:intValue	()I
    //   247: putstatic 52	uuuuuu/qqqmmm:b00760076007600760076v00760076v	I
    //   250: bipush 32
    //   252: putstatic 83	uuuuuu/qqqmmm:bvvvvv007600760076v	I
    //   255: aload 4
    //   257: checkcast 50	uuuuuu/mqmqmm$mmmqmm
    //   260: invokeinterface 233 1 0
    //   265: aload_1
    //   266: invokevirtual 212	com/db/pwcc/dbmobile/multi_bank_aggregator/model/consents/ConsentsResponse:getConsents	()Ljava/util/List;
    //   269: invokeinterface 236 1 0
    //   274: ifeq -266 -> 8
    //   277: aload_0
    //   278: getfield 131	uuuuuu/qqqmmm:b006E006E006E006E006En006E006En	Luuuuuu/hyhyhh;
    //   281: astore_1
    //   282: getstatic 52	uuuuuu/qqqmmm:b00760076007600760076v00760076v	I
    //   285: getstatic 85	uuuuuu/qqqmmm:bv0076vvv007600760076v	I
    //   288: iadd
    //   289: getstatic 52	uuuuuu/qqqmmm:b00760076007600760076v00760076v	I
    //   292: imul
    //   293: getstatic 81	uuuuuu/qqqmmm:b0076vvvv007600760076v	I
    //   296: irem
    //   297: getstatic 83	uuuuuu/qqqmmm:bvvvvv007600760076v	I
    //   300: if_icmpeq +91 -> 391
    //   303: ldc 2
    //   305: ldc -18
    //   307: sipush 226
    //   310: sipush 138
    //   313: iconst_1
    //   314: invokestatic 91	xxxxxx/uxxxxx:bbbb0062b0062b0062b0062	(Ljava/lang/String;CCC)Ljava/lang/String;
    //   317: iconst_0
    //   318: anewarray 62	java/lang/Class
    //   321: invokevirtual 66	java/lang/Class:getMethod	(Ljava/lang/String;[Ljava/lang/Class;)Ljava/lang/reflect/Method;
    //   324: astore 4
    //   326: aload 4
    //   328: aconst_null
    //   329: iconst_0
    //   330: anewarray 68	java/lang/Object
    //   333: invokevirtual 74	java/lang/reflect/Method:invoke	(Ljava/lang/Object;[Ljava/lang/Object;)Ljava/lang/Object;
    //   336: astore 4
    //   338: aload 4
    //   340: checkcast 76	java/lang/Integer
    //   343: invokevirtual 79	java/lang/Integer:intValue	()I
    //   346: putstatic 52	uuuuuu/qqqmmm:b00760076007600760076v00760076v	I
    //   349: ldc 2
    //   351: ldc -16
    //   353: bipush 78
    //   355: iconst_0
    //   356: invokestatic 60	xxxxxx/uxxxxx:bb00620062bb0062b0062b0062	(Ljava/lang/String;CC)Ljava/lang/String;
    //   359: iconst_0
    //   360: anewarray 62	java/lang/Class
    //   363: invokevirtual 66	java/lang/Class:getMethod	(Ljava/lang/String;[Ljava/lang/Class;)Ljava/lang/reflect/Method;
    //   366: astore 4
    //   368: aload 4
    //   370: aconst_null
    //   371: iconst_0
    //   372: anewarray 68	java/lang/Object
    //   375: invokevirtual 74	java/lang/reflect/Method:invoke	(Ljava/lang/Object;[Ljava/lang/Object;)Ljava/lang/Object;
    //   378: astore 4
    //   380: aload 4
    //   382: checkcast 76	java/lang/Integer
    //   385: invokevirtual 79	java/lang/Integer:intValue	()I
    //   388: putstatic 83	uuuuuu/qqqmmm:bvvvvv007600760076v	I
    //   391: aload_1
    //   392: invokevirtual 137	uuuuuu/hyhyhh:bp0070p007000700070p007000700070	()Luuuuuu/yhhyhh;
    //   395: invokevirtual 182	uuuuuu/yhhyhh:bp007000700070p0070p007000700070	()V
    //   398: return
    //   399: astore_1
    //   400: aload_1
    //   401: invokevirtual 120	java/lang/reflect/InvocationTargetException:getCause	()Ljava/lang/Throwable;
    //   404: athrow
    //   405: astore_1
    //   406: aload_1
    //   407: invokevirtual 120	java/lang/reflect/InvocationTargetException:getCause	()Ljava/lang/Throwable;
    //   410: athrow
    //   411: astore_1
    //   412: aload_1
    //   413: invokevirtual 120	java/lang/reflect/InvocationTargetException:getCause	()Ljava/lang/Throwable;
    //   416: athrow
    //   417: astore_1
    //   418: aload_1
    //   419: invokevirtual 120	java/lang/reflect/InvocationTargetException:getCause	()Ljava/lang/Throwable;
    //   422: athrow
    //   423: astore_1
    //   424: aload_1
    //   425: invokevirtual 120	java/lang/reflect/InvocationTargetException:getCause	()Ljava/lang/Throwable;
    //   428: athrow
    // Local variable table:
    //   start	length	slot	name	signature
    //   0	429	0	this	qqqmmm
    //   0	429	1	paramConsentsResponse	com.db.pwcc.dbmobile.multi_bank_aggregator.model.consents.ConsentsResponse
    //   44	153	2	i	int
    //   48	149	3	j	int
    //   39	342	4	localObject1	Object
    //   116	124	5	localObject2	Object
    // Exception table:
    //   from	to	target	type
    //   168	180	399	java/lang/reflect/InvocationTargetException
    //   227	239	405	java/lang/reflect/InvocationTargetException
    //   118	130	411	java/lang/reflect/InvocationTargetException
    //   326	338	417	java/lang/reflect/InvocationTargetException
    //   368	380	423	java/lang/reflect/InvocationTargetException
  }
  
  /* Error */
  public void b0075u0075u0075uu0075u0075(mqmqmm.mmmqmm paramMmmqmm)
  {
    // Byte code:
    //   0: ldc 2
    //   2: ldc -12
    //   4: bipush 42
    //   6: iconst_4
    //   7: invokestatic 60	xxxxxx/uxxxxx:bb00620062bb0062b0062b0062	(Ljava/lang/String;CC)Ljava/lang/String;
    //   10: iconst_0
    //   11: anewarray 62	java/lang/Class
    //   14: invokevirtual 66	java/lang/Class:getMethod	(Ljava/lang/String;[Ljava/lang/Class;)Ljava/lang/reflect/Method;
    //   17: astore 7
    //   19: aload 7
    //   21: aconst_null
    //   22: iconst_0
    //   23: anewarray 68	java/lang/Object
    //   26: invokevirtual 74	java/lang/reflect/Method:invoke	(Ljava/lang/Object;[Ljava/lang/Object;)Ljava/lang/Object;
    //   29: astore 7
    //   31: aload 7
    //   33: checkcast 76	java/lang/Integer
    //   36: invokevirtual 79	java/lang/Integer:intValue	()I
    //   39: istore_2
    //   40: getstatic 85	uuuuuu/qqqmmm:bv0076vvv007600760076v	I
    //   43: istore_3
    //   44: ldc 2
    //   46: ldc -10
    //   48: sipush 128
    //   51: iconst_4
    //   52: invokestatic 60	xxxxxx/uxxxxx:bb00620062bb0062b0062b0062	(Ljava/lang/String;CC)Ljava/lang/String;
    //   55: iconst_0
    //   56: anewarray 62	java/lang/Class
    //   59: invokevirtual 66	java/lang/Class:getMethod	(Ljava/lang/String;[Ljava/lang/Class;)Ljava/lang/reflect/Method;
    //   62: astore 7
    //   64: aload 7
    //   66: aconst_null
    //   67: iconst_0
    //   68: anewarray 68	java/lang/Object
    //   71: invokevirtual 74	java/lang/reflect/Method:invoke	(Ljava/lang/Object;[Ljava/lang/Object;)Ljava/lang/Object;
    //   74: astore 7
    //   76: aload 7
    //   78: checkcast 76	java/lang/Integer
    //   81: invokevirtual 79	java/lang/Integer:intValue	()I
    //   84: iload_3
    //   85: iload_2
    //   86: iadd
    //   87: imul
    //   88: getstatic 81	uuuuuu/qqqmmm:b0076vvvv007600760076v	I
    //   91: irem
    //   92: getstatic 83	uuuuuu/qqqmmm:bvvvvv007600760076v	I
    //   95: if_icmpeq +133 -> 228
    //   98: getstatic 52	uuuuuu/qqqmmm:b00760076007600760076v00760076v	I
    //   101: istore_2
    //   102: iload_2
    //   103: getstatic 85	uuuuuu/qqqmmm:bv0076vvv007600760076v	I
    //   106: iload_2
    //   107: iadd
    //   108: imul
    //   109: getstatic 81	uuuuuu/qqqmmm:b0076vvvv007600760076v	I
    //   112: irem
    //   113: tableswitch	default:+19->132, 0:+67->180
    //   132: ldc 2
    //   134: ldc 87
    //   136: sipush 147
    //   139: iconst_1
    //   140: invokestatic 60	xxxxxx/uxxxxx:bb00620062bb0062b0062b0062	(Ljava/lang/String;CC)Ljava/lang/String;
    //   143: iconst_0
    //   144: anewarray 62	java/lang/Class
    //   147: invokevirtual 66	java/lang/Class:getMethod	(Ljava/lang/String;[Ljava/lang/Class;)Ljava/lang/reflect/Method;
    //   150: astore 7
    //   152: aload 7
    //   154: aconst_null
    //   155: iconst_0
    //   156: anewarray 68	java/lang/Object
    //   159: invokevirtual 74	java/lang/reflect/Method:invoke	(Ljava/lang/Object;[Ljava/lang/Object;)Ljava/lang/Object;
    //   162: astore 7
    //   164: aload 7
    //   166: checkcast 76	java/lang/Integer
    //   169: invokevirtual 79	java/lang/Integer:intValue	()I
    //   172: putstatic 52	uuuuuu/qqqmmm:b00760076007600760076v00760076v	I
    //   175: bipush 48
    //   177: putstatic 83	uuuuuu/qqqmmm:bvvvvv007600760076v	I
    //   180: ldc 2
    //   182: ldc 87
    //   184: sipush 225
    //   187: iconst_0
    //   188: invokestatic 60	xxxxxx/uxxxxx:bb00620062bb0062b0062b0062	(Ljava/lang/String;CC)Ljava/lang/String;
    //   191: iconst_0
    //   192: anewarray 62	java/lang/Class
    //   195: invokevirtual 66	java/lang/Class:getMethod	(Ljava/lang/String;[Ljava/lang/Class;)Ljava/lang/reflect/Method;
    //   198: astore 7
    //   200: aload 7
    //   202: aconst_null
    //   203: iconst_0
    //   204: anewarray 68	java/lang/Object
    //   207: invokevirtual 74	java/lang/reflect/Method:invoke	(Ljava/lang/Object;[Ljava/lang/Object;)Ljava/lang/Object;
    //   210: astore 7
    //   212: aload 7
    //   214: checkcast 76	java/lang/Integer
    //   217: invokevirtual 79	java/lang/Integer:intValue	()I
    //   220: putstatic 52	uuuuuu/qqqmmm:b00760076007600760076v00760076v	I
    //   223: bipush 80
    //   225: putstatic 83	uuuuuu/qqqmmm:bvvvvv007600760076v	I
    //   228: aload_0
    //   229: aload_1
    //   230: invokespecial 250	uuuuuu/qppppp:ba0061a0061a0061a0061aa	(Luuuuuu/ttssst$tsssst;)V
    //   233: aload_0
    //   234: getfield 131	uuuuuu/qqqmmm:b006E006E006E006E006En006E006En	Luuuuuu/hyhyhh;
    //   237: astore 7
    //   239: ldc 2
    //   241: ldc -4
    //   243: bipush 77
    //   245: iconst_4
    //   246: invokestatic 60	xxxxxx/uxxxxx:bb00620062bb0062b0062b0062	(Ljava/lang/String;CC)Ljava/lang/String;
    //   249: iconst_0
    //   250: anewarray 62	java/lang/Class
    //   253: invokevirtual 66	java/lang/Class:getMethod	(Ljava/lang/String;[Ljava/lang/Class;)Ljava/lang/reflect/Method;
    //   256: astore 8
    //   258: aload 8
    //   260: aconst_null
    //   261: iconst_0
    //   262: anewarray 68	java/lang/Object
    //   265: invokevirtual 74	java/lang/reflect/Method:invoke	(Ljava/lang/Object;[Ljava/lang/Object;)Ljava/lang/Object;
    //   268: astore 8
    //   270: aload 8
    //   272: checkcast 76	java/lang/Integer
    //   275: invokevirtual 79	java/lang/Integer:intValue	()I
    //   278: istore_2
    //   279: getstatic 85	uuuuuu/qqqmmm:bv0076vvv007600760076v	I
    //   282: istore_3
    //   283: ldc 2
    //   285: ldc -2
    //   287: sipush 240
    //   290: sipush 237
    //   293: iconst_3
    //   294: invokestatic 91	xxxxxx/uxxxxx:bbbb0062b0062b0062b0062	(Ljava/lang/String;CCC)Ljava/lang/String;
    //   297: iconst_0
    //   298: anewarray 62	java/lang/Class
    //   301: invokevirtual 66	java/lang/Class:getMethod	(Ljava/lang/String;[Ljava/lang/Class;)Ljava/lang/reflect/Method;
    //   304: astore 8
    //   306: aload 8
    //   308: aconst_null
    //   309: iconst_0
    //   310: anewarray 68	java/lang/Object
    //   313: invokevirtual 74	java/lang/reflect/Method:invoke	(Ljava/lang/Object;[Ljava/lang/Object;)Ljava/lang/Object;
    //   316: astore 8
    //   318: aload 8
    //   320: checkcast 76	java/lang/Integer
    //   323: invokevirtual 79	java/lang/Integer:intValue	()I
    //   326: istore 4
    //   328: getstatic 52	uuuuuu/qqqmmm:b00760076007600760076v00760076v	I
    //   331: istore 5
    //   333: getstatic 85	uuuuuu/qqqmmm:bv0076vvv007600760076v	I
    //   336: istore 6
    //   338: ldc 2
    //   340: ldc_w 256
    //   343: sipush 141
    //   346: bipush 69
    //   348: iconst_0
    //   349: invokestatic 91	xxxxxx/uxxxxx:bbbb0062b0062b0062b0062	(Ljava/lang/String;CCC)Ljava/lang/String;
    //   352: iconst_0
    //   353: anewarray 62	java/lang/Class
    //   356: invokevirtual 66	java/lang/Class:getMethod	(Ljava/lang/String;[Ljava/lang/Class;)Ljava/lang/reflect/Method;
    //   359: astore 8
    //   361: aload 8
    //   363: aconst_null
    //   364: iconst_0
    //   365: anewarray 68	java/lang/Object
    //   368: invokevirtual 74	java/lang/reflect/Method:invoke	(Ljava/lang/Object;[Ljava/lang/Object;)Ljava/lang/Object;
    //   371: astore 8
    //   373: iload 6
    //   375: iload 5
    //   377: iadd
    //   378: iload 5
    //   380: imul
    //   381: aload 8
    //   383: checkcast 76	java/lang/Integer
    //   386: invokevirtual 79	java/lang/Integer:intValue	()I
    //   389: irem
    //   390: tableswitch	default:+18->408, 0:+66->456
    //   408: ldc 2
    //   410: ldc_w 258
    //   413: bipush 71
    //   415: iconst_0
    //   416: invokestatic 60	xxxxxx/uxxxxx:bb00620062bb0062b0062b0062	(Ljava/lang/String;CC)Ljava/lang/String;
    //   419: iconst_0
    //   420: anewarray 62	java/lang/Class
    //   423: invokevirtual 66	java/lang/Class:getMethod	(Ljava/lang/String;[Ljava/lang/Class;)Ljava/lang/reflect/Method;
    //   426: astore 8
    //   428: aload 8
    //   430: aconst_null
    //   431: iconst_0
    //   432: anewarray 68	java/lang/Object
    //   435: invokevirtual 74	java/lang/reflect/Method:invoke	(Ljava/lang/Object;[Ljava/lang/Object;)Ljava/lang/Object;
    //   438: astore 8
    //   440: aload 8
    //   442: checkcast 76	java/lang/Integer
    //   445: invokevirtual 79	java/lang/Integer:intValue	()I
    //   448: putstatic 52	uuuuuu/qqqmmm:b00760076007600760076v00760076v	I
    //   451: bipush 16
    //   453: putstatic 83	uuuuuu/qqqmmm:bvvvvv007600760076v	I
    //   456: iload_3
    //   457: iload_2
    //   458: iadd
    //   459: iload_2
    //   460: imul
    //   461: iload 4
    //   463: irem
    //   464: tableswitch	default:+20->484, 0:+30->494
    //   484: bipush 93
    //   486: putstatic 52	uuuuuu/qqqmmm:b00760076007600760076v00760076v	I
    //   489: bipush 94
    //   491: putstatic 83	uuuuuu/qqqmmm:bvvvvv007600760076v	I
    //   494: aload_1
    //   495: aload 7
    //   497: invokevirtual 137	uuuuuu/hyhyhh:bp0070p007000700070p007000700070	()Luuuuuu/yhhyhh;
    //   500: invokevirtual 143	uuuuuu/yhhyhh:bp0070p0070p0070p007000700070	()Z
    //   503: invokeinterface 262 2 0
    //   508: return
    //   509: astore_1
    //   510: aload_1
    //   511: invokevirtual 120	java/lang/reflect/InvocationTargetException:getCause	()Ljava/lang/Throwable;
    //   514: athrow
    //   515: astore_1
    //   516: aload_1
    //   517: invokevirtual 120	java/lang/reflect/InvocationTargetException:getCause	()Ljava/lang/Throwable;
    //   520: athrow
    //   521: astore_1
    //   522: aload_1
    //   523: invokevirtual 120	java/lang/reflect/InvocationTargetException:getCause	()Ljava/lang/Throwable;
    //   526: athrow
    //   527: astore_1
    //   528: aload_1
    //   529: invokevirtual 120	java/lang/reflect/InvocationTargetException:getCause	()Ljava/lang/Throwable;
    //   532: athrow
    //   533: astore_1
    //   534: aload_1
    //   535: invokevirtual 120	java/lang/reflect/InvocationTargetException:getCause	()Ljava/lang/Throwable;
    //   538: athrow
    //   539: astore_1
    //   540: aload_1
    //   541: invokevirtual 120	java/lang/reflect/InvocationTargetException:getCause	()Ljava/lang/Throwable;
    //   544: athrow
    //   545: astore_1
    //   546: aload_1
    //   547: invokevirtual 120	java/lang/reflect/InvocationTargetException:getCause	()Ljava/lang/Throwable;
    //   550: athrow
    //   551: astore_1
    //   552: aload_1
    //   553: invokevirtual 120	java/lang/reflect/InvocationTargetException:getCause	()Ljava/lang/Throwable;
    //   556: athrow
    // Local variable table:
    //   start	length	slot	name	signature
    //   0	557	0	this	qqqmmm
    //   0	557	1	paramMmmqmm	mqmqmm.mmmqmm
    //   39	422	2	i	int
    //   43	416	3	j	int
    //   326	138	4	k	int
    //   331	50	5	m	int
    //   336	42	6	n	int
    //   17	479	7	localObject1	Object
    //   256	185	8	localObject2	Object
    // Exception table:
    //   from	to	target	type
    //   258	270	509	java/lang/reflect/InvocationTargetException
    //   19	31	515	java/lang/reflect/InvocationTargetException
    //   64	76	521	java/lang/reflect/InvocationTargetException
    //   200	212	527	java/lang/reflect/InvocationTargetException
    //   306	318	533	java/lang/reflect/InvocationTargetException
    //   361	373	539	java/lang/reflect/InvocationTargetException
    //   428	440	545	java/lang/reflect/InvocationTargetException
    //   152	164	551	java/lang/reflect/InvocationTargetException
  }
  
  /* Error */
  public void b0075uu00750075uu0075u0075()
  {
    // Byte code:
    //   0: aload_0
    //   1: getfield 131	uuuuuu/qqqmmm:b006E006E006E006E006En006E006En	Luuuuuu/hyhyhh;
    //   4: invokevirtual 137	uuuuuu/hyhyhh:bp0070p007000700070p007000700070	()Luuuuuu/yhhyhh;
    //   7: invokevirtual 182	uuuuuu/yhhyhh:bp007000700070p0070p007000700070	()V
    //   10: aload_0
    //   11: invokevirtual 185	uuuuuu/qqqmmm:bkk006Bk006Bk006Bk006Bk	()Z
    //   14: istore 6
    //   16: ldc 2
    //   18: ldc -58
    //   20: bipush 16
    //   22: iconst_0
    //   23: invokestatic 60	xxxxxx/uxxxxx:bb00620062bb0062b0062b0062	(Ljava/lang/String;CC)Ljava/lang/String;
    //   26: iconst_0
    //   27: anewarray 62	java/lang/Class
    //   30: invokevirtual 66	java/lang/Class:getMethod	(Ljava/lang/String;[Ljava/lang/Class;)Ljava/lang/reflect/Method;
    //   33: astore 7
    //   35: aload 7
    //   37: aconst_null
    //   38: iconst_0
    //   39: anewarray 68	java/lang/Object
    //   42: invokevirtual 74	java/lang/reflect/Method:invoke	(Ljava/lang/Object;[Ljava/lang/Object;)Ljava/lang/Object;
    //   45: astore 7
    //   47: aload 7
    //   49: checkcast 76	java/lang/Integer
    //   52: invokevirtual 79	java/lang/Integer:intValue	()I
    //   55: istore_1
    //   56: getstatic 85	uuuuuu/qqqmmm:bv0076vvv007600760076v	I
    //   59: istore_2
    //   60: ldc 2
    //   62: ldc_w 265
    //   65: bipush 120
    //   67: iconst_4
    //   68: invokestatic 60	xxxxxx/uxxxxx:bb00620062bb0062b0062b0062	(Ljava/lang/String;CC)Ljava/lang/String;
    //   71: iconst_0
    //   72: anewarray 62	java/lang/Class
    //   75: invokevirtual 66	java/lang/Class:getMethod	(Ljava/lang/String;[Ljava/lang/Class;)Ljava/lang/reflect/Method;
    //   78: astore 7
    //   80: aload 7
    //   82: aconst_null
    //   83: iconst_0
    //   84: anewarray 68	java/lang/Object
    //   87: invokevirtual 74	java/lang/reflect/Method:invoke	(Ljava/lang/Object;[Ljava/lang/Object;)Ljava/lang/Object;
    //   90: astore 7
    //   92: aload 7
    //   94: checkcast 76	java/lang/Integer
    //   97: invokevirtual 79	java/lang/Integer:intValue	()I
    //   100: istore_3
    //   101: ldc 2
    //   103: ldc_w 267
    //   106: iconst_1
    //   107: iconst_1
    //   108: invokestatic 60	xxxxxx/uxxxxx:bb00620062bb0062b0062b0062	(Ljava/lang/String;CC)Ljava/lang/String;
    //   111: iconst_0
    //   112: anewarray 62	java/lang/Class
    //   115: invokevirtual 66	java/lang/Class:getMethod	(Ljava/lang/String;[Ljava/lang/Class;)Ljava/lang/reflect/Method;
    //   118: astore 7
    //   120: aload 7
    //   122: aconst_null
    //   123: iconst_0
    //   124: anewarray 68	java/lang/Object
    //   127: invokevirtual 74	java/lang/reflect/Method:invoke	(Ljava/lang/Object;[Ljava/lang/Object;)Ljava/lang/Object;
    //   130: astore 7
    //   132: iload_2
    //   133: iload_1
    //   134: iadd
    //   135: iload_3
    //   136: imul
    //   137: aload 7
    //   139: checkcast 76	java/lang/Integer
    //   142: invokevirtual 79	java/lang/Integer:intValue	()I
    //   145: irem
    //   146: getstatic 83	uuuuuu/qqqmmm:bvvvvv007600760076v	I
    //   149: if_icmpeq +52 -> 201
    //   152: ldc 2
    //   154: ldc_w 269
    //   157: sipush 234
    //   160: iconst_5
    //   161: invokestatic 60	xxxxxx/uxxxxx:bb00620062bb0062b0062b0062	(Ljava/lang/String;CC)Ljava/lang/String;
    //   164: iconst_0
    //   165: anewarray 62	java/lang/Class
    //   168: invokevirtual 66	java/lang/Class:getMethod	(Ljava/lang/String;[Ljava/lang/Class;)Ljava/lang/reflect/Method;
    //   171: astore 7
    //   173: aload 7
    //   175: aconst_null
    //   176: iconst_0
    //   177: anewarray 68	java/lang/Object
    //   180: invokevirtual 74	java/lang/reflect/Method:invoke	(Ljava/lang/Object;[Ljava/lang/Object;)Ljava/lang/Object;
    //   183: astore 7
    //   185: aload 7
    //   187: checkcast 76	java/lang/Integer
    //   190: invokevirtual 79	java/lang/Integer:intValue	()I
    //   193: putstatic 52	uuuuuu/qqqmmm:b00760076007600760076v00760076v	I
    //   196: bipush 17
    //   198: putstatic 83	uuuuuu/qqqmmm:bvvvvv007600760076v	I
    //   201: iload 6
    //   203: ifne +4 -> 207
    //   206: return
    //   207: aload_0
    //   208: getfield 48	uuuuuu/qqqmmm:bnnnnn006E006E006En	Luuuuuu/ttssst$tsssst;
    //   211: checkcast 50	uuuuuu/mqmqmm$mmmqmm
    //   214: invokeinterface 233 1 0
    //   219: getstatic 52	uuuuuu/qqqmmm:b00760076007600760076v00760076v	I
    //   222: istore_1
    //   223: ldc 2
    //   225: ldc_w 271
    //   228: bipush 28
    //   230: bipush 48
    //   232: iconst_2
    //   233: invokestatic 91	xxxxxx/uxxxxx:bbbb0062b0062b0062b0062	(Ljava/lang/String;CCC)Ljava/lang/String;
    //   236: iconst_0
    //   237: anewarray 62	java/lang/Class
    //   240: invokevirtual 66	java/lang/Class:getMethod	(Ljava/lang/String;[Ljava/lang/Class;)Ljava/lang/reflect/Method;
    //   243: astore 7
    //   245: aload 7
    //   247: aconst_null
    //   248: iconst_0
    //   249: anewarray 68	java/lang/Object
    //   252: invokevirtual 74	java/lang/reflect/Method:invoke	(Ljava/lang/Object;[Ljava/lang/Object;)Ljava/lang/Object;
    //   255: astore 7
    //   257: aload 7
    //   259: checkcast 76	java/lang/Integer
    //   262: invokevirtual 79	java/lang/Integer:intValue	()I
    //   265: istore_2
    //   266: getstatic 52	uuuuuu/qqqmmm:b00760076007600760076v00760076v	I
    //   269: istore_3
    //   270: getstatic 52	uuuuuu/qqqmmm:b00760076007600760076v00760076v	I
    //   273: istore 4
    //   275: iload 4
    //   277: getstatic 85	uuuuuu/qqqmmm:bv0076vvv007600760076v	I
    //   280: iload 4
    //   282: iadd
    //   283: imul
    //   284: getstatic 81	uuuuuu/qqqmmm:b0076vvvv007600760076v	I
    //   287: irem
    //   288: tableswitch	default:+20->308, 0:+106->394
    //   308: ldc 2
    //   310: ldc_w 273
    //   313: bipush 116
    //   315: iconst_5
    //   316: invokestatic 60	xxxxxx/uxxxxx:bb00620062bb0062b0062b0062	(Ljava/lang/String;CC)Ljava/lang/String;
    //   319: iconst_0
    //   320: anewarray 62	java/lang/Class
    //   323: invokevirtual 66	java/lang/Class:getMethod	(Ljava/lang/String;[Ljava/lang/Class;)Ljava/lang/reflect/Method;
    //   326: astore 7
    //   328: aload 7
    //   330: aconst_null
    //   331: iconst_0
    //   332: anewarray 68	java/lang/Object
    //   335: invokevirtual 74	java/lang/reflect/Method:invoke	(Ljava/lang/Object;[Ljava/lang/Object;)Ljava/lang/Object;
    //   338: astore 7
    //   340: aload 7
    //   342: checkcast 76	java/lang/Integer
    //   345: invokevirtual 79	java/lang/Integer:intValue	()I
    //   348: putstatic 52	uuuuuu/qqqmmm:b00760076007600760076v00760076v	I
    //   351: ldc 2
    //   353: ldc -18
    //   355: sipush 215
    //   358: iconst_3
    //   359: invokestatic 60	xxxxxx/uxxxxx:bb00620062bb0062b0062b0062	(Ljava/lang/String;CC)Ljava/lang/String;
    //   362: iconst_0
    //   363: anewarray 62	java/lang/Class
    //   366: invokevirtual 66	java/lang/Class:getMethod	(Ljava/lang/String;[Ljava/lang/Class;)Ljava/lang/reflect/Method;
    //   369: astore 7
    //   371: aload 7
    //   373: aconst_null
    //   374: iconst_0
    //   375: anewarray 68	java/lang/Object
    //   378: invokevirtual 74	java/lang/reflect/Method:invoke	(Ljava/lang/Object;[Ljava/lang/Object;)Ljava/lang/Object;
    //   381: astore 7
    //   383: aload 7
    //   385: checkcast 76	java/lang/Integer
    //   388: invokevirtual 79	java/lang/Integer:intValue	()I
    //   391: putstatic 83	uuuuuu/qqqmmm:bvvvvv007600760076v	I
    //   394: getstatic 81	uuuuuu/qqqmmm:b0076vvvv007600760076v	I
    //   397: istore 4
    //   399: getstatic 52	uuuuuu/qqqmmm:b00760076007600760076v00760076v	I
    //   402: istore 5
    //   404: iload 5
    //   406: getstatic 85	uuuuuu/qqqmmm:bv0076vvv007600760076v	I
    //   409: iload 5
    //   411: iadd
    //   412: imul
    //   413: getstatic 81	uuuuuu/qqqmmm:b0076vvvv007600760076v	I
    //   416: irem
    //   417: tableswitch	default:+19->436, 0:+108->525
    //   436: ldc 2
    //   438: ldc_w 275
    //   441: bipush 108
    //   443: iconst_3
    //   444: invokestatic 60	xxxxxx/uxxxxx:bb00620062bb0062b0062b0062	(Ljava/lang/String;CC)Ljava/lang/String;
    //   447: iconst_0
    //   448: anewarray 62	java/lang/Class
    //   451: invokevirtual 66	java/lang/Class:getMethod	(Ljava/lang/String;[Ljava/lang/Class;)Ljava/lang/reflect/Method;
    //   454: astore 7
    //   456: aload 7
    //   458: aconst_null
    //   459: iconst_0
    //   460: anewarray 68	java/lang/Object
    //   463: invokevirtual 74	java/lang/reflect/Method:invoke	(Ljava/lang/Object;[Ljava/lang/Object;)Ljava/lang/Object;
    //   466: astore 7
    //   468: aload 7
    //   470: checkcast 76	java/lang/Integer
    //   473: invokevirtual 79	java/lang/Integer:intValue	()I
    //   476: putstatic 52	uuuuuu/qqqmmm:b00760076007600760076v00760076v	I
    //   479: ldc 2
    //   481: ldc_w 277
    //   484: sipush 159
    //   487: bipush 113
    //   489: iconst_3
    //   490: invokestatic 91	xxxxxx/uxxxxx:bbbb0062b0062b0062b0062	(Ljava/lang/String;CCC)Ljava/lang/String;
    //   493: iconst_0
    //   494: anewarray 62	java/lang/Class
    //   497: invokevirtual 66	java/lang/Class:getMethod	(Ljava/lang/String;[Ljava/lang/Class;)Ljava/lang/reflect/Method;
    //   500: astore 7
    //   502: aload 7
    //   504: aconst_null
    //   505: iconst_0
    //   506: anewarray 68	java/lang/Object
    //   509: invokevirtual 74	java/lang/reflect/Method:invoke	(Ljava/lang/Object;[Ljava/lang/Object;)Ljava/lang/Object;
    //   512: astore 7
    //   514: aload 7
    //   516: checkcast 76	java/lang/Integer
    //   519: invokevirtual 79	java/lang/Integer:intValue	()I
    //   522: putstatic 83	uuuuuu/qqqmmm:bvvvvv007600760076v	I
    //   525: ldc 2
    //   527: ldc_w 279
    //   530: bipush 109
    //   532: bipush 118
    //   534: iconst_3
    //   535: invokestatic 91	xxxxxx/uxxxxx:bbbb0062b0062b0062b0062	(Ljava/lang/String;CCC)Ljava/lang/String;
    //   538: iconst_0
    //   539: anewarray 62	java/lang/Class
    //   542: invokevirtual 66	java/lang/Class:getMethod	(Ljava/lang/String;[Ljava/lang/Class;)Ljava/lang/reflect/Method;
    //   545: astore 7
    //   547: aload 7
    //   549: aconst_null
    //   550: iconst_0
    //   551: anewarray 68	java/lang/Object
    //   554: invokevirtual 74	java/lang/reflect/Method:invoke	(Ljava/lang/Object;[Ljava/lang/Object;)Ljava/lang/Object;
    //   557: astore 7
    //   559: iload_1
    //   560: iload_2
    //   561: iadd
    //   562: iload_3
    //   563: imul
    //   564: iload 4
    //   566: irem
    //   567: aload 7
    //   569: checkcast 76	java/lang/Integer
    //   572: invokevirtual 79	java/lang/Integer:intValue	()I
    //   575: if_icmpeq -369 -> 206
    //   578: ldc 2
    //   580: ldc_w 281
    //   583: bipush 101
    //   585: bipush 50
    //   587: iconst_2
    //   588: invokestatic 91	xxxxxx/uxxxxx:bbbb0062b0062b0062b0062	(Ljava/lang/String;CCC)Ljava/lang/String;
    //   591: iconst_0
    //   592: anewarray 62	java/lang/Class
    //   595: invokevirtual 66	java/lang/Class:getMethod	(Ljava/lang/String;[Ljava/lang/Class;)Ljava/lang/reflect/Method;
    //   598: astore 7
    //   600: aload 7
    //   602: aconst_null
    //   603: iconst_0
    //   604: anewarray 68	java/lang/Object
    //   607: invokevirtual 74	java/lang/reflect/Method:invoke	(Ljava/lang/Object;[Ljava/lang/Object;)Ljava/lang/Object;
    //   610: astore 7
    //   612: aload 7
    //   614: checkcast 76	java/lang/Integer
    //   617: invokevirtual 79	java/lang/Integer:intValue	()I
    //   620: putstatic 52	uuuuuu/qqqmmm:b00760076007600760076v00760076v	I
    //   623: bipush 58
    //   625: putstatic 83	uuuuuu/qqqmmm:bvvvvv007600760076v	I
    //   628: return
    //   629: astore 7
    //   631: aload 7
    //   633: invokevirtual 120	java/lang/reflect/InvocationTargetException:getCause	()Ljava/lang/Throwable;
    //   636: athrow
    //   637: astore 7
    //   639: aload 7
    //   641: invokevirtual 120	java/lang/reflect/InvocationTargetException:getCause	()Ljava/lang/Throwable;
    //   644: athrow
    //   645: astore 7
    //   647: aload 7
    //   649: invokevirtual 120	java/lang/reflect/InvocationTargetException:getCause	()Ljava/lang/Throwable;
    //   652: athrow
    //   653: astore 7
    //   655: aload 7
    //   657: invokevirtual 120	java/lang/reflect/InvocationTargetException:getCause	()Ljava/lang/Throwable;
    //   660: athrow
    //   661: astore 7
    //   663: aload 7
    //   665: invokevirtual 120	java/lang/reflect/InvocationTargetException:getCause	()Ljava/lang/Throwable;
    //   668: athrow
    //   669: astore 7
    //   671: aload 7
    //   673: invokevirtual 120	java/lang/reflect/InvocationTargetException:getCause	()Ljava/lang/Throwable;
    //   676: athrow
    //   677: astore 7
    //   679: aload 7
    //   681: invokevirtual 120	java/lang/reflect/InvocationTargetException:getCause	()Ljava/lang/Throwable;
    //   684: athrow
    //   685: astore 7
    //   687: aload 7
    //   689: invokevirtual 120	java/lang/reflect/InvocationTargetException:getCause	()Ljava/lang/Throwable;
    //   692: athrow
    //   693: astore 7
    //   695: aload 7
    //   697: invokevirtual 120	java/lang/reflect/InvocationTargetException:getCause	()Ljava/lang/Throwable;
    //   700: athrow
    //   701: astore 7
    //   703: aload 7
    //   705: invokevirtual 120	java/lang/reflect/InvocationTargetException:getCause	()Ljava/lang/Throwable;
    //   708: athrow
    //   709: astore 7
    //   711: aload 7
    //   713: invokevirtual 120	java/lang/reflect/InvocationTargetException:getCause	()Ljava/lang/Throwable;
    //   716: athrow
    // Local variable table:
    //   start	length	slot	name	signature
    //   0	717	0	this	qqqmmm
    //   55	507	1	i	int
    //   59	503	2	j	int
    //   100	464	3	k	int
    //   273	294	4	m	int
    //   402	11	5	n	int
    //   14	188	6	bool	boolean
    //   33	580	7	localObject	Object
    //   629	3	7	localInvocationTargetException1	InvocationTargetException
    //   637	3	7	localInvocationTargetException2	InvocationTargetException
    //   645	3	7	localInvocationTargetException3	InvocationTargetException
    //   653	3	7	localInvocationTargetException4	InvocationTargetException
    //   661	3	7	localInvocationTargetException5	InvocationTargetException
    //   669	3	7	localInvocationTargetException6	InvocationTargetException
    //   677	3	7	localInvocationTargetException7	InvocationTargetException
    //   685	3	7	localInvocationTargetException8	InvocationTargetException
    //   693	3	7	localInvocationTargetException9	InvocationTargetException
    //   701	3	7	localInvocationTargetException10	InvocationTargetException
    //   709	3	7	localInvocationTargetException11	InvocationTargetException
    // Exception table:
    //   from	to	target	type
    //   547	559	629	java/lang/reflect/InvocationTargetException
    //   456	468	637	java/lang/reflect/InvocationTargetException
    //   502	514	645	java/lang/reflect/InvocationTargetException
    //   245	257	653	java/lang/reflect/InvocationTargetException
    //   173	185	661	java/lang/reflect/InvocationTargetException
    //   35	47	669	java/lang/reflect/InvocationTargetException
    //   80	92	677	java/lang/reflect/InvocationTargetException
    //   120	132	685	java/lang/reflect/InvocationTargetException
    //   600	612	693	java/lang/reflect/InvocationTargetException
    //   328	340	701	java/lang/reflect/InvocationTargetException
    //   371	383	709	java/lang/reflect/InvocationTargetException
  }
  
  /* Error */
  public void b0075uuu0075uu0075u0075()
  {
    // Byte code:
    //   0: aload_0
    //   1: getfield 48	uuuuuu/qqqmmm:bnnnnn006E006E006En	Luuuuuu/ttssst$tsssst;
    //   4: checkcast 50	uuuuuu/mqmqmm$mmmqmm
    //   7: invokeinterface 127 1 0
    //   12: new 284	uuuuuu/alllla
    //   15: dup
    //   16: invokespecial 285	uuuuuu/alllla:<init>	()V
    //   19: astore 4
    //   21: aload_0
    //   22: getfield 131	uuuuuu/qqqmmm:b006E006E006E006E006En006E006En	Luuuuuu/hyhyhh;
    //   25: astore 5
    //   27: getstatic 52	uuuuuu/qqqmmm:b00760076007600760076v00760076v	I
    //   30: istore_1
    //   31: getstatic 85	uuuuuu/qqqmmm:bv0076vvv007600760076v	I
    //   34: istore_2
    //   35: getstatic 52	uuuuuu/qqqmmm:b00760076007600760076v00760076v	I
    //   38: istore_3
    //   39: iload_3
    //   40: getstatic 85	uuuuuu/qqqmmm:bv0076vvv007600760076v	I
    //   43: iload_3
    //   44: iadd
    //   45: imul
    //   46: getstatic 81	uuuuuu/qqqmmm:b0076vvvv007600760076v	I
    //   49: irem
    //   50: tableswitch	default:+18->68, 0:+70->120
    //   68: bipush 24
    //   70: putstatic 52	uuuuuu/qqqmmm:b00760076007600760076v00760076v	I
    //   73: ldc 2
    //   75: ldc_w 287
    //   78: sipush 139
    //   81: sipush 209
    //   84: iconst_2
    //   85: invokestatic 91	xxxxxx/uxxxxx:bbbb0062b0062b0062b0062	(Ljava/lang/String;CCC)Ljava/lang/String;
    //   88: iconst_0
    //   89: anewarray 62	java/lang/Class
    //   92: invokevirtual 66	java/lang/Class:getMethod	(Ljava/lang/String;[Ljava/lang/Class;)Ljava/lang/reflect/Method;
    //   95: astore 6
    //   97: aload 6
    //   99: aconst_null
    //   100: iconst_0
    //   101: anewarray 68	java/lang/Object
    //   104: invokevirtual 74	java/lang/reflect/Method:invoke	(Ljava/lang/Object;[Ljava/lang/Object;)Ljava/lang/Object;
    //   107: astore 6
    //   109: aload 6
    //   111: checkcast 76	java/lang/Integer
    //   114: invokevirtual 79	java/lang/Integer:intValue	()I
    //   117: putstatic 83	uuuuuu/qqqmmm:bvvvvv007600760076v	I
    //   120: ldc 2
    //   122: ldc_w 289
    //   125: bipush 68
    //   127: iconst_1
    //   128: invokestatic 60	xxxxxx/uxxxxx:bb00620062bb0062b0062b0062	(Ljava/lang/String;CC)Ljava/lang/String;
    //   131: iconst_0
    //   132: anewarray 62	java/lang/Class
    //   135: invokevirtual 66	java/lang/Class:getMethod	(Ljava/lang/String;[Ljava/lang/Class;)Ljava/lang/reflect/Method;
    //   138: astore 6
    //   140: aload 6
    //   142: aconst_null
    //   143: iconst_0
    //   144: anewarray 68	java/lang/Object
    //   147: invokevirtual 74	java/lang/reflect/Method:invoke	(Ljava/lang/Object;[Ljava/lang/Object;)Ljava/lang/Object;
    //   150: astore 6
    //   152: iload_1
    //   153: iload_1
    //   154: iload_2
    //   155: iadd
    //   156: imul
    //   157: aload 6
    //   159: checkcast 76	java/lang/Integer
    //   162: invokevirtual 79	java/lang/Integer:intValue	()I
    //   165: irem
    //   166: tableswitch	default:+18->184, 0:+150->316
    //   184: getstatic 52	uuuuuu/qqqmmm:b00760076007600760076v00760076v	I
    //   187: istore_1
    //   188: iload_1
    //   189: getstatic 85	uuuuuu/qqqmmm:bv0076vvv007600760076v	I
    //   192: iload_1
    //   193: iadd
    //   194: imul
    //   195: getstatic 81	uuuuuu/qqqmmm:b0076vvvv007600760076v	I
    //   198: irem
    //   199: tableswitch	default:+17->216, 0:+68->267
    //   216: bipush 51
    //   218: putstatic 52	uuuuuu/qqqmmm:b00760076007600760076v00760076v	I
    //   221: ldc 2
    //   223: ldc_w 291
    //   226: bipush 48
    //   228: sipush 174
    //   231: iconst_0
    //   232: invokestatic 91	xxxxxx/uxxxxx:bbbb0062b0062b0062b0062	(Ljava/lang/String;CCC)Ljava/lang/String;
    //   235: iconst_0
    //   236: anewarray 62	java/lang/Class
    //   239: invokevirtual 66	java/lang/Class:getMethod	(Ljava/lang/String;[Ljava/lang/Class;)Ljava/lang/reflect/Method;
    //   242: astore 6
    //   244: aload 6
    //   246: aconst_null
    //   247: iconst_0
    //   248: anewarray 68	java/lang/Object
    //   251: invokevirtual 74	java/lang/reflect/Method:invoke	(Ljava/lang/Object;[Ljava/lang/Object;)Ljava/lang/Object;
    //   254: astore 6
    //   256: aload 6
    //   258: checkcast 76	java/lang/Integer
    //   261: invokevirtual 79	java/lang/Integer:intValue	()I
    //   264: putstatic 83	uuuuuu/qqqmmm:bvvvvv007600760076v	I
    //   267: ldc 2
    //   269: ldc_w 293
    //   272: sipush 132
    //   275: iconst_2
    //   276: invokestatic 60	xxxxxx/uxxxxx:bb00620062bb0062b0062b0062	(Ljava/lang/String;CC)Ljava/lang/String;
    //   279: iconst_0
    //   280: anewarray 62	java/lang/Class
    //   283: invokevirtual 66	java/lang/Class:getMethod	(Ljava/lang/String;[Ljava/lang/Class;)Ljava/lang/reflect/Method;
    //   286: astore 6
    //   288: aload 6
    //   290: aconst_null
    //   291: iconst_0
    //   292: anewarray 68	java/lang/Object
    //   295: invokevirtual 74	java/lang/reflect/Method:invoke	(Ljava/lang/Object;[Ljava/lang/Object;)Ljava/lang/Object;
    //   298: astore 6
    //   300: aload 6
    //   302: checkcast 76	java/lang/Integer
    //   305: invokevirtual 79	java/lang/Integer:intValue	()I
    //   308: putstatic 52	uuuuuu/qqqmmm:b00760076007600760076v00760076v	I
    //   311: bipush 99
    //   313: putstatic 83	uuuuuu/qqqmmm:bvvvvv007600760076v	I
    //   316: aload 4
    //   318: aload_0
    //   319: aload 5
    //   321: invokevirtual 150	uuuuuu/hyhyhh:bpp0070007000700070p007000700070	()Ljava/lang/String;
    //   324: invokevirtual 297	uuuuuu/alllla:b0075uuu007500750075007500750075	(Luuuuuu/aalaal$llaaal;Ljava/lang/String;)V
    //   327: getstatic 52	uuuuuu/qqqmmm:b00760076007600760076v00760076v	I
    //   330: istore_1
    //   331: ldc 2
    //   333: ldc_w 299
    //   336: bipush 95
    //   338: iconst_2
    //   339: invokestatic 60	xxxxxx/uxxxxx:bb00620062bb0062b0062b0062	(Ljava/lang/String;CC)Ljava/lang/String;
    //   342: iconst_0
    //   343: anewarray 62	java/lang/Class
    //   346: invokevirtual 66	java/lang/Class:getMethod	(Ljava/lang/String;[Ljava/lang/Class;)Ljava/lang/reflect/Method;
    //   349: astore 4
    //   351: aload 4
    //   353: aconst_null
    //   354: iconst_0
    //   355: anewarray 68	java/lang/Object
    //   358: invokevirtual 74	java/lang/reflect/Method:invoke	(Ljava/lang/Object;[Ljava/lang/Object;)Ljava/lang/Object;
    //   361: astore 4
    //   363: aload 4
    //   365: checkcast 76	java/lang/Integer
    //   368: invokevirtual 79	java/lang/Integer:intValue	()I
    //   371: iload_1
    //   372: iadd
    //   373: getstatic 52	uuuuuu/qqqmmm:b00760076007600760076v00760076v	I
    //   376: imul
    //   377: getstatic 81	uuuuuu/qqqmmm:b0076vvvv007600760076v	I
    //   380: irem
    //   381: getstatic 83	uuuuuu/qqqmmm:bvvvvv007600760076v	I
    //   384: if_icmpeq +52 -> 436
    //   387: ldc 2
    //   389: ldc_w 301
    //   392: sipush 226
    //   395: iconst_4
    //   396: invokestatic 60	xxxxxx/uxxxxx:bb00620062bb0062b0062b0062	(Ljava/lang/String;CC)Ljava/lang/String;
    //   399: iconst_0
    //   400: anewarray 62	java/lang/Class
    //   403: invokevirtual 66	java/lang/Class:getMethod	(Ljava/lang/String;[Ljava/lang/Class;)Ljava/lang/reflect/Method;
    //   406: astore 4
    //   408: aload 4
    //   410: aconst_null
    //   411: iconst_0
    //   412: anewarray 68	java/lang/Object
    //   415: invokevirtual 74	java/lang/reflect/Method:invoke	(Ljava/lang/Object;[Ljava/lang/Object;)Ljava/lang/Object;
    //   418: astore 4
    //   420: aload 4
    //   422: checkcast 76	java/lang/Integer
    //   425: invokevirtual 79	java/lang/Integer:intValue	()I
    //   428: putstatic 52	uuuuuu/qqqmmm:b00760076007600760076v00760076v	I
    //   431: bipush 25
    //   433: putstatic 83	uuuuuu/qqqmmm:bvvvvv007600760076v	I
    //   436: return
    //   437: astore 4
    //   439: aload 4
    //   441: invokevirtual 120	java/lang/reflect/InvocationTargetException:getCause	()Ljava/lang/Throwable;
    //   444: athrow
    //   445: astore 4
    //   447: aload 4
    //   449: invokevirtual 120	java/lang/reflect/InvocationTargetException:getCause	()Ljava/lang/Throwable;
    //   452: athrow
    //   453: astore 4
    //   455: aload 4
    //   457: invokevirtual 120	java/lang/reflect/InvocationTargetException:getCause	()Ljava/lang/Throwable;
    //   460: athrow
    //   461: astore 4
    //   463: aload 4
    //   465: invokevirtual 120	java/lang/reflect/InvocationTargetException:getCause	()Ljava/lang/Throwable;
    //   468: athrow
    //   469: astore 4
    //   471: aload 4
    //   473: invokevirtual 120	java/lang/reflect/InvocationTargetException:getCause	()Ljava/lang/Throwable;
    //   476: athrow
    //   477: astore 4
    //   479: aload 4
    //   481: invokevirtual 120	java/lang/reflect/InvocationTargetException:getCause	()Ljava/lang/Throwable;
    //   484: athrow
    // Local variable table:
    //   start	length	slot	name	signature
    //   0	485	0	this	qqqmmm
    //   30	343	1	i	int
    //   34	122	2	j	int
    //   38	8	3	k	int
    //   19	402	4	localObject1	Object
    //   437	3	4	localInvocationTargetException1	InvocationTargetException
    //   445	3	4	localInvocationTargetException2	InvocationTargetException
    //   453	3	4	localInvocationTargetException3	InvocationTargetException
    //   461	3	4	localInvocationTargetException4	InvocationTargetException
    //   469	3	4	localInvocationTargetException5	InvocationTargetException
    //   477	3	4	localInvocationTargetException6	InvocationTargetException
    //   25	295	5	localHyhyhh	hyhyhh
    //   95	206	6	localObject2	Object
    // Exception table:
    //   from	to	target	type
    //   244	256	437	java/lang/reflect/InvocationTargetException
    //   408	420	445	java/lang/reflect/InvocationTargetException
    //   288	300	453	java/lang/reflect/InvocationTargetException
    //   140	152	461	java/lang/reflect/InvocationTargetException
    //   351	363	469	java/lang/reflect/InvocationTargetException
    //   97	109	477	java/lang/reflect/InvocationTargetException
  }
  
  /* Error */
  public void bu0075u00750075uu0075u0075(DbError paramDbError)
  {
    // Byte code:
    //   0: aload_0
    //   1: invokevirtual 185	uuuuuu/qqqmmm:bkk006Bk006Bk006Bk006Bk	()Z
    //   4: ifne +4 -> 8
    //   7: return
    //   8: ldc 2
    //   10: ldc_w 312
    //   13: bipush 48
    //   15: iconst_0
    //   16: invokestatic 60	xxxxxx/uxxxxx:bb00620062bb0062b0062b0062	(Ljava/lang/String;CC)Ljava/lang/String;
    //   19: iconst_1
    //   20: anewarray 62	java/lang/Class
    //   23: dup
    //   24: iconst_0
    //   25: ldc 40
    //   27: aastore
    //   28: invokevirtual 315	java/lang/Class:getDeclaredMethod	(Ljava/lang/String;[Ljava/lang/Class;)Ljava/lang/reflect/Method;
    //   31: astore 8
    //   33: aload 8
    //   35: aload_0
    //   36: iconst_1
    //   37: anewarray 68	java/lang/Object
    //   40: dup
    //   41: iconst_0
    //   42: aload_1
    //   43: aastore
    //   44: invokevirtual 74	java/lang/reflect/Method:invoke	(Ljava/lang/Object;[Ljava/lang/Object;)Ljava/lang/Object;
    //   47: pop
    //   48: aload_0
    //   49: getfield 48	uuuuuu/qqqmmm:bnnnnn006E006E006En	Luuuuuu/ttssst$tsssst;
    //   52: checkcast 50	uuuuuu/mqmqmm$mmmqmm
    //   55: invokeinterface 318 1 0
    //   60: aload_0
    //   61: getfield 48	uuuuuu/qqqmmm:bnnnnn006E006E006En	Luuuuuu/ttssst$tsssst;
    //   64: checkcast 50	uuuuuu/mqmqmm$mmmqmm
    //   67: invokeinterface 233 1 0
    //   72: getstatic 52	uuuuuu/qqqmmm:b00760076007600760076v00760076v	I
    //   75: getstatic 85	uuuuuu/qqqmmm:bv0076vvv007600760076v	I
    //   78: iadd
    //   79: getstatic 52	uuuuuu/qqqmmm:b00760076007600760076v00760076v	I
    //   82: imul
    //   83: getstatic 81	uuuuuu/qqqmmm:b0076vvvv007600760076v	I
    //   86: irem
    //   87: getstatic 83	uuuuuu/qqqmmm:bvvvvv007600760076v	I
    //   90: if_icmpeq -83 -> 7
    //   93: ldc 2
    //   95: ldc_w 320
    //   98: bipush 86
    //   100: bipush 47
    //   102: iconst_3
    //   103: invokestatic 91	xxxxxx/uxxxxx:bbbb0062b0062b0062b0062	(Ljava/lang/String;CCC)Ljava/lang/String;
    //   106: iconst_0
    //   107: anewarray 62	java/lang/Class
    //   110: invokevirtual 66	java/lang/Class:getMethod	(Ljava/lang/String;[Ljava/lang/Class;)Ljava/lang/reflect/Method;
    //   113: astore_1
    //   114: aload_1
    //   115: aconst_null
    //   116: iconst_0
    //   117: anewarray 68	java/lang/Object
    //   120: invokevirtual 74	java/lang/reflect/Method:invoke	(Ljava/lang/Object;[Ljava/lang/Object;)Ljava/lang/Object;
    //   123: astore_1
    //   124: aload_1
    //   125: checkcast 76	java/lang/Integer
    //   128: invokevirtual 79	java/lang/Integer:intValue	()I
    //   131: putstatic 52	uuuuuu/qqqmmm:b00760076007600760076v00760076v	I
    //   134: iconst_3
    //   135: putstatic 83	uuuuuu/qqqmmm:bvvvvv007600760076v	I
    //   138: getstatic 52	uuuuuu/qqqmmm:b00760076007600760076v00760076v	I
    //   141: istore_2
    //   142: ldc 2
    //   144: ldc_w 322
    //   147: bipush 81
    //   149: sipush 174
    //   152: iconst_1
    //   153: invokestatic 91	xxxxxx/uxxxxx:bbbb0062b0062b0062b0062	(Ljava/lang/String;CCC)Ljava/lang/String;
    //   156: iconst_0
    //   157: anewarray 62	java/lang/Class
    //   160: invokevirtual 66	java/lang/Class:getMethod	(Ljava/lang/String;[Ljava/lang/Class;)Ljava/lang/reflect/Method;
    //   163: astore_1
    //   164: aload_1
    //   165: aconst_null
    //   166: iconst_0
    //   167: anewarray 68	java/lang/Object
    //   170: invokevirtual 74	java/lang/reflect/Method:invoke	(Ljava/lang/Object;[Ljava/lang/Object;)Ljava/lang/Object;
    //   173: astore_1
    //   174: aload_1
    //   175: checkcast 76	java/lang/Integer
    //   178: invokevirtual 79	java/lang/Integer:intValue	()I
    //   181: iload_2
    //   182: iadd
    //   183: iload_2
    //   184: imul
    //   185: getstatic 81	uuuuuu/qqqmmm:b0076vvvv007600760076v	I
    //   188: irem
    //   189: tableswitch	default:+19->208, 0:+-182->7
    //   208: bipush 41
    //   210: putstatic 52	uuuuuu/qqqmmm:b00760076007600760076v00760076v	I
    //   213: ldc 2
    //   215: ldc_w 324
    //   218: sipush 155
    //   221: iconst_3
    //   222: invokestatic 60	xxxxxx/uxxxxx:bb00620062bb0062b0062b0062	(Ljava/lang/String;CC)Ljava/lang/String;
    //   225: iconst_0
    //   226: anewarray 62	java/lang/Class
    //   229: invokevirtual 66	java/lang/Class:getMethod	(Ljava/lang/String;[Ljava/lang/Class;)Ljava/lang/reflect/Method;
    //   232: astore_1
    //   233: aload_1
    //   234: aconst_null
    //   235: iconst_0
    //   236: anewarray 68	java/lang/Object
    //   239: invokevirtual 74	java/lang/reflect/Method:invoke	(Ljava/lang/Object;[Ljava/lang/Object;)Ljava/lang/Object;
    //   242: astore_1
    //   243: aload_1
    //   244: checkcast 76	java/lang/Integer
    //   247: invokevirtual 79	java/lang/Integer:intValue	()I
    //   250: putstatic 83	uuuuuu/qqqmmm:bvvvvv007600760076v	I
    //   253: getstatic 52	uuuuuu/qqqmmm:b00760076007600760076v00760076v	I
    //   256: istore_2
    //   257: getstatic 85	uuuuuu/qqqmmm:bv0076vvv007600760076v	I
    //   260: istore_3
    //   261: ldc 2
    //   263: ldc_w 326
    //   266: sipush 232
    //   269: iconst_0
    //   270: invokestatic 60	xxxxxx/uxxxxx:bb00620062bb0062b0062b0062	(Ljava/lang/String;CC)Ljava/lang/String;
    //   273: iconst_0
    //   274: anewarray 62	java/lang/Class
    //   277: invokevirtual 66	java/lang/Class:getMethod	(Ljava/lang/String;[Ljava/lang/Class;)Ljava/lang/reflect/Method;
    //   280: astore_1
    //   281: aload_1
    //   282: aconst_null
    //   283: iconst_0
    //   284: anewarray 68	java/lang/Object
    //   287: invokevirtual 74	java/lang/reflect/Method:invoke	(Ljava/lang/Object;[Ljava/lang/Object;)Ljava/lang/Object;
    //   290: astore_1
    //   291: aload_1
    //   292: checkcast 76	java/lang/Integer
    //   295: invokevirtual 79	java/lang/Integer:intValue	()I
    //   298: istore 4
    //   300: getstatic 85	uuuuuu/qqqmmm:bv0076vvv007600760076v	I
    //   303: istore 5
    //   305: ldc 2
    //   307: ldc -85
    //   309: bipush 30
    //   311: bipush 113
    //   313: iconst_1
    //   314: invokestatic 91	xxxxxx/uxxxxx:bbbb0062b0062b0062b0062	(Ljava/lang/String;CCC)Ljava/lang/String;
    //   317: iconst_0
    //   318: anewarray 62	java/lang/Class
    //   321: invokevirtual 66	java/lang/Class:getMethod	(Ljava/lang/String;[Ljava/lang/Class;)Ljava/lang/reflect/Method;
    //   324: astore_1
    //   325: aload_1
    //   326: aconst_null
    //   327: iconst_0
    //   328: anewarray 68	java/lang/Object
    //   331: invokevirtual 74	java/lang/reflect/Method:invoke	(Ljava/lang/Object;[Ljava/lang/Object;)Ljava/lang/Object;
    //   334: astore_1
    //   335: aload_1
    //   336: checkcast 76	java/lang/Integer
    //   339: invokevirtual 79	java/lang/Integer:intValue	()I
    //   342: istore 6
    //   344: getstatic 81	uuuuuu/qqqmmm:b0076vvvv007600760076v	I
    //   347: istore 7
    //   349: ldc 2
    //   351: ldc_w 328
    //   354: bipush 67
    //   356: iconst_0
    //   357: invokestatic 60	xxxxxx/uxxxxx:bb00620062bb0062b0062b0062	(Ljava/lang/String;CC)Ljava/lang/String;
    //   360: iconst_0
    //   361: anewarray 62	java/lang/Class
    //   364: invokevirtual 66	java/lang/Class:getMethod	(Ljava/lang/String;[Ljava/lang/Class;)Ljava/lang/reflect/Method;
    //   367: astore_1
    //   368: aload_1
    //   369: aconst_null
    //   370: iconst_0
    //   371: anewarray 68	java/lang/Object
    //   374: invokevirtual 74	java/lang/reflect/Method:invoke	(Ljava/lang/Object;[Ljava/lang/Object;)Ljava/lang/Object;
    //   377: astore_1
    //   378: iload 6
    //   380: iload 5
    //   382: iload 4
    //   384: iadd
    //   385: imul
    //   386: iload 7
    //   388: irem
    //   389: aload_1
    //   390: checkcast 76	java/lang/Integer
    //   393: invokevirtual 79	java/lang/Integer:intValue	()I
    //   396: if_icmpeq +48 -> 444
    //   399: bipush 84
    //   401: putstatic 52	uuuuuu/qqqmmm:b00760076007600760076v00760076v	I
    //   404: ldc 2
    //   406: ldc_w 330
    //   409: sipush 253
    //   412: iconst_0
    //   413: invokestatic 60	xxxxxx/uxxxxx:bb00620062bb0062b0062b0062	(Ljava/lang/String;CC)Ljava/lang/String;
    //   416: iconst_0
    //   417: anewarray 62	java/lang/Class
    //   420: invokevirtual 66	java/lang/Class:getMethod	(Ljava/lang/String;[Ljava/lang/Class;)Ljava/lang/reflect/Method;
    //   423: astore_1
    //   424: aload_1
    //   425: aconst_null
    //   426: iconst_0
    //   427: anewarray 68	java/lang/Object
    //   430: invokevirtual 74	java/lang/reflect/Method:invoke	(Ljava/lang/Object;[Ljava/lang/Object;)Ljava/lang/Object;
    //   433: astore_1
    //   434: aload_1
    //   435: checkcast 76	java/lang/Integer
    //   438: invokevirtual 79	java/lang/Integer:intValue	()I
    //   441: putstatic 83	uuuuuu/qqqmmm:bvvvvv007600760076v	I
    //   444: iload_2
    //   445: iload_3
    //   446: iadd
    //   447: getstatic 52	uuuuuu/qqqmmm:b00760076007600760076v00760076v	I
    //   450: imul
    //   451: getstatic 81	uuuuuu/qqqmmm:b0076vvvv007600760076v	I
    //   454: irem
    //   455: getstatic 83	uuuuuu/qqqmmm:bvvvvv007600760076v	I
    //   458: if_icmpeq -451 -> 7
    //   461: ldc 2
    //   463: ldc_w 332
    //   466: bipush 97
    //   468: iconst_2
    //   469: invokestatic 60	xxxxxx/uxxxxx:bb00620062bb0062b0062b0062	(Ljava/lang/String;CC)Ljava/lang/String;
    //   472: iconst_0
    //   473: anewarray 62	java/lang/Class
    //   476: invokevirtual 66	java/lang/Class:getMethod	(Ljava/lang/String;[Ljava/lang/Class;)Ljava/lang/reflect/Method;
    //   479: astore_1
    //   480: aload_1
    //   481: aconst_null
    //   482: iconst_0
    //   483: anewarray 68	java/lang/Object
    //   486: invokevirtual 74	java/lang/reflect/Method:invoke	(Ljava/lang/Object;[Ljava/lang/Object;)Ljava/lang/Object;
    //   489: astore_1
    //   490: aload_1
    //   491: checkcast 76	java/lang/Integer
    //   494: invokevirtual 79	java/lang/Integer:intValue	()I
    //   497: putstatic 52	uuuuuu/qqqmmm:b00760076007600760076v00760076v	I
    //   500: ldc 2
    //   502: ldc_w 334
    //   505: sipush 132
    //   508: bipush 68
    //   510: iconst_3
    //   511: invokestatic 91	xxxxxx/uxxxxx:bbbb0062b0062b0062b0062	(Ljava/lang/String;CCC)Ljava/lang/String;
    //   514: iconst_0
    //   515: anewarray 62	java/lang/Class
    //   518: invokevirtual 66	java/lang/Class:getMethod	(Ljava/lang/String;[Ljava/lang/Class;)Ljava/lang/reflect/Method;
    //   521: astore_1
    //   522: aload_1
    //   523: aconst_null
    //   524: iconst_0
    //   525: anewarray 68	java/lang/Object
    //   528: invokevirtual 74	java/lang/reflect/Method:invoke	(Ljava/lang/Object;[Ljava/lang/Object;)Ljava/lang/Object;
    //   531: astore_1
    //   532: aload_1
    //   533: checkcast 76	java/lang/Integer
    //   536: invokevirtual 79	java/lang/Integer:intValue	()I
    //   539: putstatic 83	uuuuuu/qqqmmm:bvvvvv007600760076v	I
    //   542: return
    //   543: astore_1
    //   544: aload_1
    //   545: invokevirtual 120	java/lang/reflect/InvocationTargetException:getCause	()Ljava/lang/Throwable;
    //   548: athrow
    //   549: astore_1
    //   550: aload_1
    //   551: invokevirtual 120	java/lang/reflect/InvocationTargetException:getCause	()Ljava/lang/Throwable;
    //   554: athrow
    //   555: astore_1
    //   556: aload_1
    //   557: invokevirtual 120	java/lang/reflect/InvocationTargetException:getCause	()Ljava/lang/Throwable;
    //   560: athrow
    //   561: astore_1
    //   562: aload_1
    //   563: invokevirtual 120	java/lang/reflect/InvocationTargetException:getCause	()Ljava/lang/Throwable;
    //   566: athrow
    //   567: astore_1
    //   568: aload_1
    //   569: invokevirtual 120	java/lang/reflect/InvocationTargetException:getCause	()Ljava/lang/Throwable;
    //   572: athrow
    //   573: astore_1
    //   574: aload_1
    //   575: invokevirtual 120	java/lang/reflect/InvocationTargetException:getCause	()Ljava/lang/Throwable;
    //   578: athrow
    //   579: astore_1
    //   580: aload_1
    //   581: invokevirtual 120	java/lang/reflect/InvocationTargetException:getCause	()Ljava/lang/Throwable;
    //   584: athrow
    //   585: astore_1
    //   586: aload_1
    //   587: invokevirtual 120	java/lang/reflect/InvocationTargetException:getCause	()Ljava/lang/Throwable;
    //   590: athrow
    //   591: astore_1
    //   592: aload_1
    //   593: invokevirtual 120	java/lang/reflect/InvocationTargetException:getCause	()Ljava/lang/Throwable;
    //   596: athrow
    //   597: astore_1
    //   598: aload_1
    //   599: invokevirtual 120	java/lang/reflect/InvocationTargetException:getCause	()Ljava/lang/Throwable;
    //   602: athrow
    // Local variable table:
    //   start	length	slot	name	signature
    //   0	603	0	this	qqqmmm
    //   0	603	1	paramDbError	DbError
    //   141	306	2	i	int
    //   260	187	3	j	int
    //   298	87	4	k	int
    //   303	82	5	m	int
    //   342	44	6	n	int
    //   347	42	7	i1	int
    //   31	3	8	localMethod	Method
    // Exception table:
    //   from	to	target	type
    //   480	490	543	java/lang/reflect/InvocationTargetException
    //   522	532	549	java/lang/reflect/InvocationTargetException
    //   114	124	555	java/lang/reflect/InvocationTargetException
    //   164	174	561	java/lang/reflect/InvocationTargetException
    //   233	243	567	java/lang/reflect/InvocationTargetException
    //   281	291	573	java/lang/reflect/InvocationTargetException
    //   325	335	579	java/lang/reflect/InvocationTargetException
    //   368	378	585	java/lang/reflect/InvocationTargetException
    //   33	48	591	java/lang/reflect/InvocationTargetException
    //   424	434	597	java/lang/reflect/InvocationTargetException
  }
  
  public void buu007500750075uu0075u0075(int paramInt, DbError paramDbError)
  {
    throw new Runtime("d2j fail translate: java.lang.IndexOutOfBoundsException: fromIndex < 0: -1\n\tat java.util.BitSet.nextSetBit(BitSet.java:712)\n\tat com.googlecode.dex2jar.ir.ts.array.FillArrayTransformer.makeSureAllElementAreAssigned(FillArrayTransformer.java:505)\n\tat com.googlecode.dex2jar.ir.ts.array.FillArrayTransformer.transformReportChanged(FillArrayTransformer.java:123)\n\tat com.googlecode.dex2jar.ir.ts.StatedTransformer.transform(StatedTransformer.java:10)\n\tat com.googlecode.d2j.dex.Dex2jar$2.optimize(Dex2jar.java:149)\n\tat com.googlecode.d2j.dex.Dex2Asm.convertCode(Dex2Asm.java:414)\n\tat com.googlecode.d2j.dex.ExDex2Asm.convertCode(ExDex2Asm.java:42)\n\tat com.googlecode.d2j.dex.Dex2jar$2.convertCode(Dex2jar.java:128)\n\tat com.googlecode.d2j.dex.Dex2Asm.convertMethod(Dex2Asm.java:509)\n\tat com.googlecode.d2j.dex.Dex2Asm.convertClass(Dex2Asm.java:406)\n\tat com.googlecode.d2j.dex.Dex2Asm.convertDex(Dex2Asm.java:422)\n\tat com.googlecode.d2j.dex.Dex2jar.doTranslate(Dex2jar.java:172)\n\tat com.googlecode.d2j.dex.Dex2jar.to(Dex2jar.java:272)\n\tat com.googlecode.dex2jar.tools.Dex2jarCmd.doCommandLine(Dex2jarCmd.java:108)\n\tat com.googlecode.dex2jar.tools.BaseCmd.doMain(BaseCmd.java:288)\n\tat com.googlecode.dex2jar.tools.Dex2jarCmd.main(Dex2jarCmd.java:32)\n");
  }
  
  /* Error */
  public void buuu00750075uu0075u0075(DbError paramDbError)
  {
    // Byte code:
    //   0: getstatic 52	uuuuuu/qqqmmm:b00760076007600760076v00760076v	I
    //   3: istore_2
    //   4: iload_2
    //   5: getstatic 85	uuuuuu/qqqmmm:bv0076vvv007600760076v	I
    //   8: iload_2
    //   9: iadd
    //   10: imul
    //   11: getstatic 81	uuuuuu/qqqmmm:b0076vvvv007600760076v	I
    //   14: irem
    //   15: tableswitch	default:+17->32, 0:+27->42
    //   32: bipush 23
    //   34: putstatic 52	uuuuuu/qqqmmm:b00760076007600760076v00760076v	I
    //   37: bipush 25
    //   39: putstatic 83	uuuuuu/qqqmmm:bvvvvv007600760076v	I
    //   42: aload_0
    //   43: invokevirtual 185	uuuuuu/qqqmmm:bkk006Bk006Bk006Bk006Bk	()Z
    //   46: ifne +4 -> 50
    //   49: return
    //   50: ldc 2
    //   52: ldc_w 348
    //   55: sipush 195
    //   58: iconst_5
    //   59: iconst_1
    //   60: invokestatic 91	xxxxxx/uxxxxx:bbbb0062b0062b0062b0062	(Ljava/lang/String;CCC)Ljava/lang/String;
    //   63: iconst_1
    //   64: anewarray 62	java/lang/Class
    //   67: dup
    //   68: iconst_0
    //   69: ldc 40
    //   71: aastore
    //   72: invokevirtual 315	java/lang/Class:getDeclaredMethod	(Ljava/lang/String;[Ljava/lang/Class;)Ljava/lang/reflect/Method;
    //   75: astore_3
    //   76: aload_3
    //   77: aload_0
    //   78: iconst_1
    //   79: anewarray 68	java/lang/Object
    //   82: dup
    //   83: iconst_0
    //   84: aload_1
    //   85: aastore
    //   86: invokevirtual 74	java/lang/reflect/Method:invoke	(Ljava/lang/Object;[Ljava/lang/Object;)Ljava/lang/Object;
    //   89: pop
    //   90: aload_0
    //   91: getfield 48	uuuuuu/qqqmmm:bnnnnn006E006E006En	Luuuuuu/ttssst$tsssst;
    //   94: checkcast 50	uuuuuu/mqmqmm$mmmqmm
    //   97: invokeinterface 318 1 0
    //   102: aload_0
    //   103: getfield 48	uuuuuu/qqqmmm:bnnnnn006E006E006En	Luuuuuu/ttssst$tsssst;
    //   106: checkcast 50	uuuuuu/mqmqmm$mmmqmm
    //   109: astore_1
    //   110: getstatic 52	uuuuuu/qqqmmm:b00760076007600760076v00760076v	I
    //   113: getstatic 85	uuuuuu/qqqmmm:bv0076vvv007600760076v	I
    //   116: iadd
    //   117: getstatic 52	uuuuuu/qqqmmm:b00760076007600760076v00760076v	I
    //   120: imul
    //   121: getstatic 81	uuuuuu/qqqmmm:b0076vvvv007600760076v	I
    //   124: irem
    //   125: getstatic 83	uuuuuu/qqqmmm:bvvvvv007600760076v	I
    //   128: if_icmpeq +119 -> 247
    //   131: getstatic 52	uuuuuu/qqqmmm:b00760076007600760076v00760076v	I
    //   134: getstatic 85	uuuuuu/qqqmmm:bv0076vvv007600760076v	I
    //   137: iadd
    //   138: getstatic 52	uuuuuu/qqqmmm:b00760076007600760076v00760076v	I
    //   141: imul
    //   142: getstatic 81	uuuuuu/qqqmmm:b0076vvvv007600760076v	I
    //   145: irem
    //   146: getstatic 83	uuuuuu/qqqmmm:bvvvvv007600760076v	I
    //   149: if_icmpeq +50 -> 199
    //   152: ldc 2
    //   154: ldc_w 350
    //   157: bipush 19
    //   159: sipush 169
    //   162: iconst_2
    //   163: invokestatic 91	xxxxxx/uxxxxx:bbbb0062b0062b0062b0062	(Ljava/lang/String;CCC)Ljava/lang/String;
    //   166: iconst_0
    //   167: anewarray 62	java/lang/Class
    //   170: invokevirtual 66	java/lang/Class:getMethod	(Ljava/lang/String;[Ljava/lang/Class;)Ljava/lang/reflect/Method;
    //   173: astore_3
    //   174: aload_3
    //   175: aconst_null
    //   176: iconst_0
    //   177: anewarray 68	java/lang/Object
    //   180: invokevirtual 74	java/lang/reflect/Method:invoke	(Ljava/lang/Object;[Ljava/lang/Object;)Ljava/lang/Object;
    //   183: astore_3
    //   184: aload_3
    //   185: checkcast 76	java/lang/Integer
    //   188: invokevirtual 79	java/lang/Integer:intValue	()I
    //   191: putstatic 52	uuuuuu/qqqmmm:b00760076007600760076v00760076v	I
    //   194: bipush 8
    //   196: putstatic 83	uuuuuu/qqqmmm:bvvvvv007600760076v	I
    //   199: bipush 40
    //   201: putstatic 52	uuuuuu/qqqmmm:b00760076007600760076v00760076v	I
    //   204: ldc 2
    //   206: ldc_w 330
    //   209: sipush 237
    //   212: sipush 141
    //   215: iconst_3
    //   216: invokestatic 91	xxxxxx/uxxxxx:bbbb0062b0062b0062b0062	(Ljava/lang/String;CCC)Ljava/lang/String;
    //   219: iconst_0
    //   220: anewarray 62	java/lang/Class
    //   223: invokevirtual 66	java/lang/Class:getMethod	(Ljava/lang/String;[Ljava/lang/Class;)Ljava/lang/reflect/Method;
    //   226: astore_3
    //   227: aload_3
    //   228: aconst_null
    //   229: iconst_0
    //   230: anewarray 68	java/lang/Object
    //   233: invokevirtual 74	java/lang/reflect/Method:invoke	(Ljava/lang/Object;[Ljava/lang/Object;)Ljava/lang/Object;
    //   236: astore_3
    //   237: aload_3
    //   238: checkcast 76	java/lang/Integer
    //   241: invokevirtual 79	java/lang/Integer:intValue	()I
    //   244: putstatic 83	uuuuuu/qqqmmm:bvvvvv007600760076v	I
    //   247: aload_1
    //   248: invokeinterface 233 1 0
    //   253: getstatic 52	uuuuuu/qqqmmm:b00760076007600760076v00760076v	I
    //   256: istore_2
    //   257: iload_2
    //   258: getstatic 85	uuuuuu/qqqmmm:bv0076vvv007600760076v	I
    //   261: iload_2
    //   262: iadd
    //   263: imul
    //   264: getstatic 81	uuuuuu/qqqmmm:b0076vvvv007600760076v	I
    //   267: irem
    //   268: tableswitch	default:+20->288, 0:+-219->49
    //   288: bipush 99
    //   290: putstatic 52	uuuuuu/qqqmmm:b00760076007600760076v00760076v	I
    //   293: bipush 22
    //   295: putstatic 83	uuuuuu/qqqmmm:bvvvvv007600760076v	I
    //   298: return
    //   299: astore_1
    //   300: aload_1
    //   301: invokevirtual 120	java/lang/reflect/InvocationTargetException:getCause	()Ljava/lang/Throwable;
    //   304: athrow
    //   305: astore_1
    //   306: aload_1
    //   307: invokevirtual 120	java/lang/reflect/InvocationTargetException:getCause	()Ljava/lang/Throwable;
    //   310: athrow
    //   311: astore_1
    //   312: aload_1
    //   313: invokevirtual 120	java/lang/reflect/InvocationTargetException:getCause	()Ljava/lang/Throwable;
    //   316: athrow
    // Local variable table:
    //   start	length	slot	name	signature
    //   0	317	0	this	qqqmmm
    //   0	317	1	paramDbError	DbError
    //   3	261	2	i	int
    //   75	163	3	localObject	Object
    // Exception table:
    //   from	to	target	type
    //   227	237	299	java/lang/reflect/InvocationTargetException
    //   174	184	305	java/lang/reflect/InvocationTargetException
    //   76	90	311	java/lang/reflect/InvocationTargetException
  }
  
  /* Error */
  public void buuuu0075uu0075u0075(boolean paramBoolean)
  {
    // Byte code:
    //   0: iload_1
    //   1: ifeq +226 -> 227
    //   4: ldc 2
    //   6: ldc_w 353
    //   9: sipush 149
    //   12: iconst_4
    //   13: invokestatic 60	xxxxxx/uxxxxx:bb00620062bb0062b0062b0062	(Ljava/lang/String;CC)Ljava/lang/String;
    //   16: iconst_0
    //   17: anewarray 62	java/lang/Class
    //   20: invokevirtual 66	java/lang/Class:getMethod	(Ljava/lang/String;[Ljava/lang/Class;)Ljava/lang/reflect/Method;
    //   23: astore 4
    //   25: aload 4
    //   27: aload_0
    //   28: iconst_0
    //   29: anewarray 68	java/lang/Object
    //   32: invokevirtual 74	java/lang/reflect/Method:invoke	(Ljava/lang/Object;[Ljava/lang/Object;)Ljava/lang/Object;
    //   35: pop
    //   36: ldc 2
    //   38: ldc_w 355
    //   41: bipush 67
    //   43: iconst_0
    //   44: invokestatic 60	xxxxxx/uxxxxx:bb00620062bb0062b0062b0062	(Ljava/lang/String;CC)Ljava/lang/String;
    //   47: iconst_0
    //   48: anewarray 62	java/lang/Class
    //   51: invokevirtual 66	java/lang/Class:getMethod	(Ljava/lang/String;[Ljava/lang/Class;)Ljava/lang/reflect/Method;
    //   54: astore 4
    //   56: aload 4
    //   58: aconst_null
    //   59: iconst_0
    //   60: anewarray 68	java/lang/Object
    //   63: invokevirtual 74	java/lang/reflect/Method:invoke	(Ljava/lang/Object;[Ljava/lang/Object;)Ljava/lang/Object;
    //   66: astore 4
    //   68: aload 4
    //   70: checkcast 76	java/lang/Integer
    //   73: invokevirtual 79	java/lang/Integer:intValue	()I
    //   76: istore_2
    //   77: getstatic 85	uuuuuu/qqqmmm:bv0076vvv007600760076v	I
    //   80: istore_3
    //   81: ldc 2
    //   83: ldc_w 357
    //   86: sipush 188
    //   89: sipush 139
    //   92: iconst_1
    //   93: invokestatic 91	xxxxxx/uxxxxx:bbbb0062b0062b0062b0062	(Ljava/lang/String;CCC)Ljava/lang/String;
    //   96: iconst_0
    //   97: anewarray 62	java/lang/Class
    //   100: invokevirtual 66	java/lang/Class:getMethod	(Ljava/lang/String;[Ljava/lang/Class;)Ljava/lang/reflect/Method;
    //   103: astore 4
    //   105: aload 4
    //   107: aconst_null
    //   108: iconst_0
    //   109: anewarray 68	java/lang/Object
    //   112: invokevirtual 74	java/lang/reflect/Method:invoke	(Ljava/lang/Object;[Ljava/lang/Object;)Ljava/lang/Object;
    //   115: astore 4
    //   117: aload 4
    //   119: checkcast 76	java/lang/Integer
    //   122: invokevirtual 79	java/lang/Integer:intValue	()I
    //   125: iload_3
    //   126: iload_2
    //   127: iadd
    //   128: imul
    //   129: getstatic 81	uuuuuu/qqqmmm:b0076vvvv007600760076v	I
    //   132: irem
    //   133: getstatic 83	uuuuuu/qqqmmm:bvvvvv007600760076v	I
    //   136: if_icmpeq +90 -> 226
    //   139: ldc 2
    //   141: ldc_w 359
    //   144: bipush 103
    //   146: iconst_0
    //   147: invokestatic 60	xxxxxx/uxxxxx:bb00620062bb0062b0062b0062	(Ljava/lang/String;CC)Ljava/lang/String;
    //   150: iconst_0
    //   151: anewarray 62	java/lang/Class
    //   154: invokevirtual 66	java/lang/Class:getMethod	(Ljava/lang/String;[Ljava/lang/Class;)Ljava/lang/reflect/Method;
    //   157: astore 4
    //   159: aload 4
    //   161: aconst_null
    //   162: iconst_0
    //   163: anewarray 68	java/lang/Object
    //   166: invokevirtual 74	java/lang/reflect/Method:invoke	(Ljava/lang/Object;[Ljava/lang/Object;)Ljava/lang/Object;
    //   169: astore 4
    //   171: aload 4
    //   173: checkcast 76	java/lang/Integer
    //   176: invokevirtual 79	java/lang/Integer:intValue	()I
    //   179: putstatic 52	uuuuuu/qqqmmm:b00760076007600760076v00760076v	I
    //   182: ldc 2
    //   184: ldc_w 361
    //   187: sipush 242
    //   190: iconst_0
    //   191: invokestatic 60	xxxxxx/uxxxxx:bb00620062bb0062b0062b0062	(Ljava/lang/String;CC)Ljava/lang/String;
    //   194: iconst_0
    //   195: anewarray 62	java/lang/Class
    //   198: invokevirtual 66	java/lang/Class:getMethod	(Ljava/lang/String;[Ljava/lang/Class;)Ljava/lang/reflect/Method;
    //   201: astore 4
    //   203: aload 4
    //   205: aconst_null
    //   206: iconst_0
    //   207: anewarray 68	java/lang/Object
    //   210: invokevirtual 74	java/lang/reflect/Method:invoke	(Ljava/lang/Object;[Ljava/lang/Object;)Ljava/lang/Object;
    //   213: astore 4
    //   215: aload 4
    //   217: checkcast 76	java/lang/Integer
    //   220: invokevirtual 79	java/lang/Integer:intValue	()I
    //   223: putstatic 83	uuuuuu/qqqmmm:bvvvvv007600760076v	I
    //   226: return
    //   227: ldc 2
    //   229: ldc_w 363
    //   232: sipush 157
    //   235: iconst_5
    //   236: invokestatic 60	xxxxxx/uxxxxx:bb00620062bb0062b0062b0062	(Ljava/lang/String;CC)Ljava/lang/String;
    //   239: iconst_0
    //   240: anewarray 62	java/lang/Class
    //   243: invokevirtual 66	java/lang/Class:getMethod	(Ljava/lang/String;[Ljava/lang/Class;)Ljava/lang/reflect/Method;
    //   246: astore 4
    //   248: aload 4
    //   250: aload_0
    //   251: iconst_0
    //   252: anewarray 68	java/lang/Object
    //   255: invokevirtual 74	java/lang/reflect/Method:invoke	(Ljava/lang/Object;[Ljava/lang/Object;)Ljava/lang/Object;
    //   258: pop
    //   259: getstatic 52	uuuuuu/qqqmmm:b00760076007600760076v00760076v	I
    //   262: istore_2
    //   263: ldc 2
    //   265: ldc_w 365
    //   268: bipush 13
    //   270: iconst_3
    //   271: invokestatic 60	xxxxxx/uxxxxx:bb00620062bb0062b0062b0062	(Ljava/lang/String;CC)Ljava/lang/String;
    //   274: iconst_0
    //   275: anewarray 62	java/lang/Class
    //   278: invokevirtual 66	java/lang/Class:getMethod	(Ljava/lang/String;[Ljava/lang/Class;)Ljava/lang/reflect/Method;
    //   281: astore 4
    //   283: aload 4
    //   285: aconst_null
    //   286: iconst_0
    //   287: anewarray 68	java/lang/Object
    //   290: invokevirtual 74	java/lang/reflect/Method:invoke	(Ljava/lang/Object;[Ljava/lang/Object;)Ljava/lang/Object;
    //   293: astore 4
    //   295: aload 4
    //   297: checkcast 76	java/lang/Integer
    //   300: invokevirtual 79	java/lang/Integer:intValue	()I
    //   303: istore_3
    //   304: iload_3
    //   305: getstatic 85	uuuuuu/qqqmmm:bv0076vvv007600760076v	I
    //   308: iload_3
    //   309: iadd
    //   310: imul
    //   311: getstatic 81	uuuuuu/qqqmmm:b0076vvvv007600760076v	I
    //   314: irem
    //   315: tableswitch	default:+17->332, 0:+69->384
    //   332: bipush 75
    //   334: putstatic 52	uuuuuu/qqqmmm:b00760076007600760076v00760076v	I
    //   337: ldc 2
    //   339: ldc_w 367
    //   342: sipush 194
    //   345: sipush 128
    //   348: iconst_1
    //   349: invokestatic 91	xxxxxx/uxxxxx:bbbb0062b0062b0062b0062	(Ljava/lang/String;CCC)Ljava/lang/String;
    //   352: iconst_0
    //   353: anewarray 62	java/lang/Class
    //   356: invokevirtual 66	java/lang/Class:getMethod	(Ljava/lang/String;[Ljava/lang/Class;)Ljava/lang/reflect/Method;
    //   359: astore 4
    //   361: aload 4
    //   363: aconst_null
    //   364: iconst_0
    //   365: anewarray 68	java/lang/Object
    //   368: invokevirtual 74	java/lang/reflect/Method:invoke	(Ljava/lang/Object;[Ljava/lang/Object;)Ljava/lang/Object;
    //   371: astore 4
    //   373: aload 4
    //   375: checkcast 76	java/lang/Integer
    //   378: invokevirtual 79	java/lang/Integer:intValue	()I
    //   381: putstatic 83	uuuuuu/qqqmmm:bvvvvv007600760076v	I
    //   384: getstatic 52	uuuuuu/qqqmmm:b00760076007600760076v00760076v	I
    //   387: istore_3
    //   388: iload_3
    //   389: getstatic 85	uuuuuu/qqqmmm:bv0076vvv007600760076v	I
    //   392: iload_3
    //   393: iadd
    //   394: imul
    //   395: getstatic 81	uuuuuu/qqqmmm:b0076vvvv007600760076v	I
    //   398: irem
    //   399: tableswitch	default:+17->416, 0:+67->466
    //   416: bipush 22
    //   418: putstatic 52	uuuuuu/qqqmmm:b00760076007600760076v00760076v	I
    //   421: ldc 2
    //   423: ldc_w 369
    //   426: sipush 158
    //   429: iconst_3
    //   430: iconst_3
    //   431: invokestatic 91	xxxxxx/uxxxxx:bbbb0062b0062b0062b0062	(Ljava/lang/String;CCC)Ljava/lang/String;
    //   434: iconst_0
    //   435: anewarray 62	java/lang/Class
    //   438: invokevirtual 66	java/lang/Class:getMethod	(Ljava/lang/String;[Ljava/lang/Class;)Ljava/lang/reflect/Method;
    //   441: astore 4
    //   443: aload 4
    //   445: aconst_null
    //   446: iconst_0
    //   447: anewarray 68	java/lang/Object
    //   450: invokevirtual 74	java/lang/reflect/Method:invoke	(Ljava/lang/Object;[Ljava/lang/Object;)Ljava/lang/Object;
    //   453: astore 4
    //   455: aload 4
    //   457: checkcast 76	java/lang/Integer
    //   460: invokevirtual 79	java/lang/Integer:intValue	()I
    //   463: putstatic 83	uuuuuu/qqqmmm:bvvvvv007600760076v	I
    //   466: getstatic 85	uuuuuu/qqqmmm:bv0076vvv007600760076v	I
    //   469: iload_2
    //   470: iadd
    //   471: iload_2
    //   472: imul
    //   473: getstatic 81	uuuuuu/qqqmmm:b0076vvvv007600760076v	I
    //   476: irem
    //   477: tableswitch	default:+19->496, 0:+-251->226
    //   496: bipush 62
    //   498: putstatic 52	uuuuuu/qqqmmm:b00760076007600760076v00760076v	I
    //   501: ldc 2
    //   503: ldc_w 371
    //   506: bipush 124
    //   508: iconst_3
    //   509: invokestatic 60	xxxxxx/uxxxxx:bb00620062bb0062b0062b0062	(Ljava/lang/String;CC)Ljava/lang/String;
    //   512: iconst_0
    //   513: anewarray 62	java/lang/Class
    //   516: invokevirtual 66	java/lang/Class:getMethod	(Ljava/lang/String;[Ljava/lang/Class;)Ljava/lang/reflect/Method;
    //   519: astore 4
    //   521: aload 4
    //   523: aconst_null
    //   524: iconst_0
    //   525: anewarray 68	java/lang/Object
    //   528: invokevirtual 74	java/lang/reflect/Method:invoke	(Ljava/lang/Object;[Ljava/lang/Object;)Ljava/lang/Object;
    //   531: astore 4
    //   533: aload 4
    //   535: checkcast 76	java/lang/Integer
    //   538: invokevirtual 79	java/lang/Integer:intValue	()I
    //   541: putstatic 83	uuuuuu/qqqmmm:bvvvvv007600760076v	I
    //   544: return
    //   545: astore 4
    //   547: aload 4
    //   549: invokevirtual 120	java/lang/reflect/InvocationTargetException:getCause	()Ljava/lang/Throwable;
    //   552: athrow
    //   553: astore 4
    //   555: aload 4
    //   557: invokevirtual 120	java/lang/reflect/InvocationTargetException:getCause	()Ljava/lang/Throwable;
    //   560: athrow
    //   561: astore 4
    //   563: aload 4
    //   565: invokevirtual 120	java/lang/reflect/InvocationTargetException:getCause	()Ljava/lang/Throwable;
    //   568: athrow
    //   569: astore 4
    //   571: aload 4
    //   573: invokevirtual 120	java/lang/reflect/InvocationTargetException:getCause	()Ljava/lang/Throwable;
    //   576: athrow
    //   577: astore 4
    //   579: aload 4
    //   581: invokevirtual 120	java/lang/reflect/InvocationTargetException:getCause	()Ljava/lang/Throwable;
    //   584: athrow
    //   585: astore 4
    //   587: aload 4
    //   589: invokevirtual 120	java/lang/reflect/InvocationTargetException:getCause	()Ljava/lang/Throwable;
    //   592: athrow
    //   593: astore 4
    //   595: aload 4
    //   597: invokevirtual 120	java/lang/reflect/InvocationTargetException:getCause	()Ljava/lang/Throwable;
    //   600: athrow
    //   601: astore 4
    //   603: aload 4
    //   605: invokevirtual 120	java/lang/reflect/InvocationTargetException:getCause	()Ljava/lang/Throwable;
    //   608: athrow
    //   609: astore 4
    //   611: aload 4
    //   613: invokevirtual 120	java/lang/reflect/InvocationTargetException:getCause	()Ljava/lang/Throwable;
    //   616: athrow
    //   617: astore 4
    //   619: aload 4
    //   621: invokevirtual 120	java/lang/reflect/InvocationTargetException:getCause	()Ljava/lang/Throwable;
    //   624: athrow
    // Local variable table:
    //   start	length	slot	name	signature
    //   0	625	0	this	qqqmmm
    //   0	625	1	paramBoolean	boolean
    //   76	397	2	i	int
    //   80	315	3	j	int
    //   23	511	4	localObject	Object
    //   545	3	4	localInvocationTargetException1	InvocationTargetException
    //   553	3	4	localInvocationTargetException2	InvocationTargetException
    //   561	3	4	localInvocationTargetException3	InvocationTargetException
    //   569	3	4	localInvocationTargetException4	InvocationTargetException
    //   577	3	4	localInvocationTargetException5	InvocationTargetException
    //   585	3	4	localInvocationTargetException6	InvocationTargetException
    //   593	3	4	localInvocationTargetException7	InvocationTargetException
    //   601	3	4	localInvocationTargetException8	InvocationTargetException
    //   609	3	4	localInvocationTargetException9	InvocationTargetException
    //   617	3	4	localInvocationTargetException10	InvocationTargetException
    // Exception table:
    //   from	to	target	type
    //   521	533	545	java/lang/reflect/InvocationTargetException
    //   361	373	553	java/lang/reflect/InvocationTargetException
    //   25	36	561	java/lang/reflect/InvocationTargetException
    //   56	68	569	java/lang/reflect/InvocationTargetException
    //   105	117	577	java/lang/reflect/InvocationTargetException
    //   248	259	585	java/lang/reflect/InvocationTargetException
    //   443	455	593	java/lang/reflect/InvocationTargetException
    //   283	295	601	java/lang/reflect/InvocationTargetException
    //   159	171	609	java/lang/reflect/InvocationTargetException
    //   203	215	617	java/lang/reflect/InvocationTargetException
  }
}
