package uuuuuu;

import com.db.pwcc.dbmobile.model.banking.Account;

public abstract class qqqqll
  extends ssssst<llqqll.lqqqll>
  implements llqqll.qlqqll
{
  public static int b007000700070007000700070pp0070 = 1;
  public static int b0070p0070007000700070pp0070 = 48;
  public static int bp00700070007000700070pp0070 = 0;
  public static int bpppppp0070p0070 = 2;
  public Account b00700070p007000700070pp0070;
  public String bp0070p007000700070pp0070;
  public heeeeh bpp0070007000700070pp0070;
  
  public qqqqll(String paramString)
  {
    this.bp0070p007000700070pp0070 = paramString;
    this.bpp0070007000700070pp0070 = new heeeeh();
  }
  
  public static int b006F006Fo006Fo006Fo006Foo()
  {
    return 0;
  }
  
  public static int b006Foo006Fo006Fo006Foo()
  {
    return 2;
  }
  
  public static int bo006Fo006Fo006Fo006Foo()
  {
    return 74;
  }
  
  public static int booo006Fo006Fo006Foo()
  {
    return 1;
  }
  
  /* Error */
  public void b006F006F006Foo006Fo006Foo(com.db.pwcc.dbmobile.model.banking.FinancialOverviewData paramFinancialOverviewData)
  {
    // Byte code:
    //   0: aload_0
    //   1: getfield 48	uuuuuu/qqqqll:bnnnnn006E006E006En	Luuuuuu/ttssst$tsssst;
    //   4: checkcast 50	uuuuuu/llqqll$lqqqll
    //   7: invokeinterface 53 1 0
    //   12: aload_0
    //   13: getfield 34	uuuuuu/qqqqll:bpp0070007000700070pp0070	Luuuuuu/heeeeh;
    //   16: aload_1
    //   17: invokevirtual 56	uuuuuu/heeeeh:bo006F006Foooooo006F	(Lcom/db/pwcc/dbmobile/model/banking/FinancialOverviewData;)V
    //   20: aload_0
    //   21: aload_0
    //   22: getfield 34	uuuuuu/qqqqll:bpp0070007000700070pp0070	Luuuuuu/heeeeh;
    //   25: invokevirtual 60	uuuuuu/heeeeh:b006F006Fooooooo006F	()Lcom/db/pwcc/dbmobile/model/banking/FinancialOverviewData;
    //   28: aload_0
    //   29: getfield 29	uuuuuu/qqqqll:bp0070p007000700070pp0070	Ljava/lang/String;
    //   32: invokevirtual 66	com/db/pwcc/dbmobile/model/banking/FinancialOverviewData:getAccountByID	(Ljava/lang/String;)Lcom/db/pwcc/dbmobile/model/banking/Account;
    //   35: putfield 68	uuuuuu/qqqqll:b00700070p007000700070pp0070	Lcom/db/pwcc/dbmobile/model/banking/Account;
    //   38: getstatic 70	uuuuuu/qqqqll:b0070p0070007000700070pp0070	I
    //   41: istore_2
    //   42: ldc 2
    //   44: ldc 72
    //   46: bipush 90
    //   48: sipush 215
    //   51: iconst_1
    //   52: invokestatic 78	xxxxxx/uxxxxx:bbbb0062b0062b0062b0062	(Ljava/lang/String;CCC)Ljava/lang/String;
    //   55: iconst_0
    //   56: anewarray 80	java/lang/Class
    //   59: invokevirtual 84	java/lang/Class:getMethod	(Ljava/lang/String;[Ljava/lang/Class;)Ljava/lang/reflect/Method;
    //   62: astore_1
    //   63: aload_1
    //   64: aconst_null
    //   65: iconst_0
    //   66: anewarray 86	java/lang/Object
    //   69: invokevirtual 92	java/lang/reflect/Method:invoke	(Ljava/lang/Object;[Ljava/lang/Object;)Ljava/lang/Object;
    //   72: astore_1
    //   73: aload_1
    //   74: checkcast 94	java/lang/Integer
    //   77: invokevirtual 97	java/lang/Integer:intValue	()I
    //   80: iload_2
    //   81: iadd
    //   82: iload_2
    //   83: imul
    //   84: getstatic 99	uuuuuu/qqqqll:bpppppp0070p0070	I
    //   87: irem
    //   88: tableswitch	default:+20->108, 0:+135->223
    //   108: bipush 82
    //   110: putstatic 70	uuuuuu/qqqqll:b0070p0070007000700070pp0070	I
    //   113: getstatic 70	uuuuuu/qqqqll:b0070p0070007000700070pp0070	I
    //   116: getstatic 101	uuuuuu/qqqqll:b007000700070007000700070pp0070	I
    //   119: iadd
    //   120: getstatic 70	uuuuuu/qqqqll:b0070p0070007000700070pp0070	I
    //   123: imul
    //   124: getstatic 99	uuuuuu/qqqqll:bpppppp0070p0070	I
    //   127: irem
    //   128: getstatic 103	uuuuuu/qqqqll:bp00700070007000700070pp0070	I
    //   131: if_icmpeq +50 -> 181
    //   134: bipush 10
    //   136: putstatic 70	uuuuuu/qqqqll:b0070p0070007000700070pp0070	I
    //   139: ldc 2
    //   141: ldc 105
    //   143: sipush 250
    //   146: sipush 179
    //   149: iconst_3
    //   150: invokestatic 78	xxxxxx/uxxxxx:bbbb0062b0062b0062b0062	(Ljava/lang/String;CCC)Ljava/lang/String;
    //   153: iconst_0
    //   154: anewarray 80	java/lang/Class
    //   157: invokevirtual 84	java/lang/Class:getMethod	(Ljava/lang/String;[Ljava/lang/Class;)Ljava/lang/reflect/Method;
    //   160: astore_1
    //   161: aload_1
    //   162: aconst_null
    //   163: iconst_0
    //   164: anewarray 86	java/lang/Object
    //   167: invokevirtual 92	java/lang/reflect/Method:invoke	(Ljava/lang/Object;[Ljava/lang/Object;)Ljava/lang/Object;
    //   170: astore_1
    //   171: aload_1
    //   172: checkcast 94	java/lang/Integer
    //   175: invokevirtual 97	java/lang/Integer:intValue	()I
    //   178: putstatic 103	uuuuuu/qqqqll:bp00700070007000700070pp0070	I
    //   181: ldc 2
    //   183: ldc 107
    //   185: sipush 207
    //   188: sipush 134
    //   191: iconst_2
    //   192: invokestatic 78	xxxxxx/uxxxxx:bbbb0062b0062b0062b0062	(Ljava/lang/String;CCC)Ljava/lang/String;
    //   195: iconst_0
    //   196: anewarray 80	java/lang/Class
    //   199: invokevirtual 84	java/lang/Class:getMethod	(Ljava/lang/String;[Ljava/lang/Class;)Ljava/lang/reflect/Method;
    //   202: astore_1
    //   203: aload_1
    //   204: aconst_null
    //   205: iconst_0
    //   206: anewarray 86	java/lang/Object
    //   209: invokevirtual 92	java/lang/reflect/Method:invoke	(Ljava/lang/Object;[Ljava/lang/Object;)Ljava/lang/Object;
    //   212: astore_1
    //   213: aload_1
    //   214: checkcast 94	java/lang/Integer
    //   217: invokevirtual 97	java/lang/Integer:intValue	()I
    //   220: putstatic 103	uuuuuu/qqqqll:bp00700070007000700070pp0070	I
    //   223: aload_0
    //   224: getfield 68	uuuuuu/qqqqll:b00700070p007000700070pp0070	Lcom/db/pwcc/dbmobile/model/banking/Account;
    //   227: ifnull +39 -> 266
    //   230: ldc 2
    //   232: ldc 109
    //   234: sipush 181
    //   237: iconst_1
    //   238: invokestatic 113	xxxxxx/uxxxxx:bb00620062bb0062b0062b0062	(Ljava/lang/String;CC)Ljava/lang/String;
    //   241: iconst_0
    //   242: anewarray 80	java/lang/Class
    //   245: invokevirtual 84	java/lang/Class:getMethod	(Ljava/lang/String;[Ljava/lang/Class;)Ljava/lang/reflect/Method;
    //   248: astore_1
    //   249: aload_1
    //   250: aload_0
    //   251: iconst_0
    //   252: anewarray 86	java/lang/Object
    //   255: invokevirtual 92	java/lang/reflect/Method:invoke	(Ljava/lang/Object;[Ljava/lang/Object;)Ljava/lang/Object;
    //   258: pop
    //   259: return
    //   260: astore_1
    //   261: aload_1
    //   262: invokevirtual 117	java/lang/reflect/InvocationTargetException:getCause	()Ljava/lang/Throwable;
    //   265: athrow
    //   266: aload_0
    //   267: getfield 48	uuuuuu/qqqqll:bnnnnn006E006E006En	Luuuuuu/ttssst$tsssst;
    //   270: astore_1
    //   271: getstatic 70	uuuuuu/qqqqll:b0070p0070007000700070pp0070	I
    //   274: getstatic 101	uuuuuu/qqqqll:b007000700070007000700070pp0070	I
    //   277: iadd
    //   278: getstatic 70	uuuuuu/qqqqll:b0070p0070007000700070pp0070	I
    //   281: imul
    //   282: getstatic 99	uuuuuu/qqqqll:bpppppp0070p0070	I
    //   285: irem
    //   286: getstatic 103	uuuuuu/qqqqll:bp00700070007000700070pp0070	I
    //   289: if_icmpeq +13 -> 302
    //   292: bipush 6
    //   294: putstatic 70	uuuuuu/qqqqll:b0070p0070007000700070pp0070	I
    //   297: bipush 10
    //   299: putstatic 103	uuuuuu/qqqqll:bp00700070007000700070pp0070	I
    //   302: aload_1
    //   303: checkcast 50	uuuuuu/llqqll$lqqqll
    //   306: invokeinterface 120 1 0
    //   311: getstatic 70	uuuuuu/qqqqll:b0070p0070007000700070pp0070	I
    //   314: istore_2
    //   315: iload_2
    //   316: getstatic 101	uuuuuu/qqqqll:b007000700070007000700070pp0070	I
    //   319: iload_2
    //   320: iadd
    //   321: imul
    //   322: getstatic 99	uuuuuu/qqqqll:bpppppp0070p0070	I
    //   325: irem
    //   326: tableswitch	default:+18->344, 0:+28->354
    //   344: bipush 18
    //   346: putstatic 70	uuuuuu/qqqqll:b0070p0070007000700070pp0070	I
    //   349: bipush 24
    //   351: putstatic 103	uuuuuu/qqqqll:bp00700070007000700070pp0070	I
    //   354: aload_0
    //   355: getfield 48	uuuuuu/qqqqll:bnnnnn006E006E006En	Luuuuuu/ttssst$tsssst;
    //   358: checkcast 50	uuuuuu/llqqll$lqqqll
    //   361: getstatic 125	com/db/pwcc/dbmobile/financial_overview/R$string:technical_error_retry	I
    //   364: invokeinterface 129 2 0
    //   369: return
    //   370: astore_1
    //   371: aload_1
    //   372: invokevirtual 117	java/lang/reflect/InvocationTargetException:getCause	()Ljava/lang/Throwable;
    //   375: athrow
    //   376: astore_1
    //   377: aload_1
    //   378: invokevirtual 117	java/lang/reflect/InvocationTargetException:getCause	()Ljava/lang/Throwable;
    //   381: athrow
    //   382: astore_1
    //   383: aload_1
    //   384: invokevirtual 117	java/lang/reflect/InvocationTargetException:getCause	()Ljava/lang/Throwable;
    //   387: athrow
    // Local variable table:
    //   start	length	slot	name	signature
    //   0	388	0	this	qqqqll
    //   0	388	1	paramFinancialOverviewData	com.db.pwcc.dbmobile.model.banking.FinancialOverviewData
    //   41	281	2	i	int
    // Exception table:
    //   from	to	target	type
    //   63	73	260	java/lang/reflect/InvocationTargetException
    //   161	171	370	java/lang/reflect/InvocationTargetException
    //   249	259	376	java/lang/reflect/InvocationTargetException
    //   203	213	382	java/lang/reflect/InvocationTargetException
  }
  
  public abstract void b006Fo006F006Fo006Fo006Foo();
  
  /* Error */
  public boolean bo006F006F006Fo006Fo006Foo()
  {
    // Byte code:
    //   0: aload_0
    //   1: getfield 34	uuuuuu/qqqqll:bpp0070007000700070pp0070	Luuuuuu/heeeeh;
    //   4: astore 5
    //   6: getstatic 70	uuuuuu/qqqqll:b0070p0070007000700070pp0070	I
    //   9: istore_1
    //   10: getstatic 101	uuuuuu/qqqqll:b007000700070007000700070pp0070	I
    //   13: istore_2
    //   14: getstatic 70	uuuuuu/qqqqll:b0070p0070007000700070pp0070	I
    //   17: istore_3
    //   18: ldc 2
    //   20: ldc -110
    //   22: bipush 120
    //   24: iconst_5
    //   25: iconst_1
    //   26: invokestatic 78	xxxxxx/uxxxxx:bbbb0062b0062b0062b0062	(Ljava/lang/String;CCC)Ljava/lang/String;
    //   29: iconst_0
    //   30: anewarray 80	java/lang/Class
    //   33: invokevirtual 84	java/lang/Class:getMethod	(Ljava/lang/String;[Ljava/lang/Class;)Ljava/lang/reflect/Method;
    //   36: astore 6
    //   38: aload 6
    //   40: aconst_null
    //   41: iconst_0
    //   42: anewarray 86	java/lang/Object
    //   45: invokevirtual 92	java/lang/reflect/Method:invoke	(Ljava/lang/Object;[Ljava/lang/Object;)Ljava/lang/Object;
    //   48: astore 6
    //   50: iload_3
    //   51: iload_1
    //   52: iload_2
    //   53: iadd
    //   54: imul
    //   55: aload 6
    //   57: checkcast 94	java/lang/Integer
    //   60: invokevirtual 97	java/lang/Integer:intValue	()I
    //   63: irem
    //   64: getstatic 103	uuuuuu/qqqqll:bp00700070007000700070pp0070	I
    //   67: if_icmpeq +50 -> 117
    //   70: bipush 95
    //   72: putstatic 70	uuuuuu/qqqqll:b0070p0070007000700070pp0070	I
    //   75: ldc 2
    //   77: ldc -108
    //   79: bipush 33
    //   81: iconst_5
    //   82: invokestatic 113	xxxxxx/uxxxxx:bb00620062bb0062b0062b0062	(Ljava/lang/String;CC)Ljava/lang/String;
    //   85: iconst_0
    //   86: anewarray 80	java/lang/Class
    //   89: invokevirtual 84	java/lang/Class:getMethod	(Ljava/lang/String;[Ljava/lang/Class;)Ljava/lang/reflect/Method;
    //   92: astore 6
    //   94: aload 6
    //   96: aconst_null
    //   97: iconst_0
    //   98: anewarray 86	java/lang/Object
    //   101: invokevirtual 92	java/lang/reflect/Method:invoke	(Ljava/lang/Object;[Ljava/lang/Object;)Ljava/lang/Object;
    //   104: astore 6
    //   106: aload 6
    //   108: checkcast 94	java/lang/Integer
    //   111: invokevirtual 97	java/lang/Integer:intValue	()I
    //   114: putstatic 103	uuuuuu/qqqqll:bp00700070007000700070pp0070	I
    //   117: aload 5
    //   119: invokevirtual 152	uuuuuu/heeeeh:boo006Foooooo006F	()Lcom/db/pwcc/dbmobile/model/banking/TransactionsData;
    //   122: ifnull +106 -> 228
    //   125: aload_0
    //   126: getfield 34	uuuuuu/qqqqll:bpp0070007000700070pp0070	Luuuuuu/heeeeh;
    //   129: invokevirtual 152	uuuuuu/heeeeh:boo006Foooooo006F	()Lcom/db/pwcc/dbmobile/model/banking/TransactionsData;
    //   132: invokevirtual 158	com/db/pwcc/dbmobile/model/banking/TransactionsData:getAllTransactions	()Ljava/util/List;
    //   135: ifnull +93 -> 228
    //   138: aload_0
    //   139: getfield 34	uuuuuu/qqqqll:bpp0070007000700070pp0070	Luuuuuu/heeeeh;
    //   142: invokevirtual 152	uuuuuu/heeeeh:boo006Foooooo006F	()Lcom/db/pwcc/dbmobile/model/banking/TransactionsData;
    //   145: invokevirtual 158	com/db/pwcc/dbmobile/model/banking/TransactionsData:getAllTransactions	()Ljava/util/List;
    //   148: invokeinterface 163 1 0
    //   153: ifeq +317 -> 470
    //   156: getstatic 70	uuuuuu/qqqqll:b0070p0070007000700070pp0070	I
    //   159: getstatic 101	uuuuuu/qqqqll:b007000700070007000700070pp0070	I
    //   162: iadd
    //   163: getstatic 70	uuuuuu/qqqqll:b0070p0070007000700070pp0070	I
    //   166: imul
    //   167: getstatic 99	uuuuuu/qqqqll:bpppppp0070p0070	I
    //   170: irem
    //   171: getstatic 103	uuuuuu/qqqqll:bp00700070007000700070pp0070	I
    //   174: if_icmpeq +54 -> 228
    //   177: ldc 2
    //   179: ldc -91
    //   181: sipush 240
    //   184: sipush 201
    //   187: iconst_3
    //   188: invokestatic 78	xxxxxx/uxxxxx:bbbb0062b0062b0062b0062	(Ljava/lang/String;CCC)Ljava/lang/String;
    //   191: iconst_0
    //   192: anewarray 80	java/lang/Class
    //   195: invokevirtual 84	java/lang/Class:getMethod	(Ljava/lang/String;[Ljava/lang/Class;)Ljava/lang/reflect/Method;
    //   198: astore 5
    //   200: aload 5
    //   202: aconst_null
    //   203: iconst_0
    //   204: anewarray 86	java/lang/Object
    //   207: invokevirtual 92	java/lang/reflect/Method:invoke	(Ljava/lang/Object;[Ljava/lang/Object;)Ljava/lang/Object;
    //   210: astore 5
    //   212: aload 5
    //   214: checkcast 94	java/lang/Integer
    //   217: invokevirtual 97	java/lang/Integer:intValue	()I
    //   220: putstatic 70	uuuuuu/qqqqll:b0070p0070007000700070pp0070	I
    //   223: bipush 16
    //   225: putstatic 103	uuuuuu/qqqqll:bp00700070007000700070pp0070	I
    //   228: getstatic 70	uuuuuu/qqqqll:b0070p0070007000700070pp0070	I
    //   231: istore_1
    //   232: getstatic 101	uuuuuu/qqqqll:b007000700070007000700070pp0070	I
    //   235: istore_2
    //   236: getstatic 70	uuuuuu/qqqqll:b0070p0070007000700070pp0070	I
    //   239: istore_3
    //   240: getstatic 99	uuuuuu/qqqqll:bpppppp0070p0070	I
    //   243: istore 4
    //   245: ldc 2
    //   247: ldc -89
    //   249: bipush 8
    //   251: bipush 89
    //   253: iconst_0
    //   254: invokestatic 78	xxxxxx/uxxxxx:bbbb0062b0062b0062b0062	(Ljava/lang/String;CCC)Ljava/lang/String;
    //   257: iconst_0
    //   258: anewarray 80	java/lang/Class
    //   261: invokevirtual 84	java/lang/Class:getMethod	(Ljava/lang/String;[Ljava/lang/Class;)Ljava/lang/reflect/Method;
    //   264: astore 5
    //   266: aload 5
    //   268: aconst_null
    //   269: iconst_0
    //   270: anewarray 86	java/lang/Object
    //   273: invokevirtual 92	java/lang/reflect/Method:invoke	(Ljava/lang/Object;[Ljava/lang/Object;)Ljava/lang/Object;
    //   276: astore 5
    //   278: iload_1
    //   279: iload_2
    //   280: iadd
    //   281: iload_3
    //   282: imul
    //   283: iload 4
    //   285: irem
    //   286: aload 5
    //   288: checkcast 94	java/lang/Integer
    //   291: invokevirtual 97	java/lang/Integer:intValue	()I
    //   294: if_icmpeq +234 -> 528
    //   297: getstatic 70	uuuuuu/qqqqll:b0070p0070007000700070pp0070	I
    //   300: istore_1
    //   301: iload_1
    //   302: getstatic 101	uuuuuu/qqqqll:b007000700070007000700070pp0070	I
    //   305: iload_1
    //   306: iadd
    //   307: imul
    //   308: getstatic 99	uuuuuu/qqqqll:bpppppp0070p0070	I
    //   311: irem
    //   312: tableswitch	default:+20->332, 0:+70->382
    //   332: ldc 2
    //   334: ldc -87
    //   336: sipush 246
    //   339: sipush 129
    //   342: iconst_0
    //   343: invokestatic 78	xxxxxx/uxxxxx:bbbb0062b0062b0062b0062	(Ljava/lang/String;CCC)Ljava/lang/String;
    //   346: iconst_0
    //   347: anewarray 80	java/lang/Class
    //   350: invokevirtual 84	java/lang/Class:getMethod	(Ljava/lang/String;[Ljava/lang/Class;)Ljava/lang/reflect/Method;
    //   353: astore 5
    //   355: aload 5
    //   357: aconst_null
    //   358: iconst_0
    //   359: anewarray 86	java/lang/Object
    //   362: invokevirtual 92	java/lang/reflect/Method:invoke	(Ljava/lang/Object;[Ljava/lang/Object;)Ljava/lang/Object;
    //   365: astore 5
    //   367: aload 5
    //   369: checkcast 94	java/lang/Integer
    //   372: invokevirtual 97	java/lang/Integer:intValue	()I
    //   375: putstatic 70	uuuuuu/qqqqll:b0070p0070007000700070pp0070	I
    //   378: iconst_3
    //   379: putstatic 103	uuuuuu/qqqqll:bp00700070007000700070pp0070	I
    //   382: ldc 2
    //   384: ldc -85
    //   386: sipush 216
    //   389: iconst_1
    //   390: invokestatic 113	xxxxxx/uxxxxx:bb00620062bb0062b0062b0062	(Ljava/lang/String;CC)Ljava/lang/String;
    //   393: iconst_0
    //   394: anewarray 80	java/lang/Class
    //   397: invokevirtual 84	java/lang/Class:getMethod	(Ljava/lang/String;[Ljava/lang/Class;)Ljava/lang/reflect/Method;
    //   400: astore 5
    //   402: aload 5
    //   404: aconst_null
    //   405: iconst_0
    //   406: anewarray 86	java/lang/Object
    //   409: invokevirtual 92	java/lang/reflect/Method:invoke	(Ljava/lang/Object;[Ljava/lang/Object;)Ljava/lang/Object;
    //   412: astore 5
    //   414: aload 5
    //   416: checkcast 94	java/lang/Integer
    //   419: invokevirtual 97	java/lang/Integer:intValue	()I
    //   422: putstatic 70	uuuuuu/qqqqll:b0070p0070007000700070pp0070	I
    //   425: ldc 2
    //   427: ldc -83
    //   429: sipush 212
    //   432: iconst_1
    //   433: invokestatic 113	xxxxxx/uxxxxx:bb00620062bb0062b0062b0062	(Ljava/lang/String;CC)Ljava/lang/String;
    //   436: iconst_0
    //   437: anewarray 80	java/lang/Class
    //   440: invokevirtual 84	java/lang/Class:getMethod	(Ljava/lang/String;[Ljava/lang/Class;)Ljava/lang/reflect/Method;
    //   443: astore 5
    //   445: aload 5
    //   447: aconst_null
    //   448: iconst_0
    //   449: anewarray 86	java/lang/Object
    //   452: invokevirtual 92	java/lang/reflect/Method:invoke	(Ljava/lang/Object;[Ljava/lang/Object;)Ljava/lang/Object;
    //   455: astore 5
    //   457: aload 5
    //   459: checkcast 94	java/lang/Integer
    //   462: invokevirtual 97	java/lang/Integer:intValue	()I
    //   465: putstatic 103	uuuuuu/qqqqll:bp00700070007000700070pp0070	I
    //   468: iconst_1
    //   469: ireturn
    //   470: iconst_0
    //   471: ireturn
    //   472: astore 5
    //   474: aload 5
    //   476: invokevirtual 117	java/lang/reflect/InvocationTargetException:getCause	()Ljava/lang/Throwable;
    //   479: athrow
    //   480: astore 5
    //   482: aload 5
    //   484: invokevirtual 117	java/lang/reflect/InvocationTargetException:getCause	()Ljava/lang/Throwable;
    //   487: athrow
    //   488: astore 5
    //   490: aload 5
    //   492: invokevirtual 117	java/lang/reflect/InvocationTargetException:getCause	()Ljava/lang/Throwable;
    //   495: athrow
    //   496: astore 5
    //   498: aload 5
    //   500: invokevirtual 117	java/lang/reflect/InvocationTargetException:getCause	()Ljava/lang/Throwable;
    //   503: athrow
    //   504: astore 5
    //   506: aload 5
    //   508: invokevirtual 117	java/lang/reflect/InvocationTargetException:getCause	()Ljava/lang/Throwable;
    //   511: athrow
    //   512: astore 5
    //   514: aload 5
    //   516: invokevirtual 117	java/lang/reflect/InvocationTargetException:getCause	()Ljava/lang/Throwable;
    //   519: athrow
    //   520: astore 5
    //   522: aload 5
    //   524: invokevirtual 117	java/lang/reflect/InvocationTargetException:getCause	()Ljava/lang/Throwable;
    //   527: athrow
    //   528: iconst_1
    //   529: ireturn
    // Local variable table:
    //   start	length	slot	name	signature
    //   0	530	0	this	qqqqll
    //   9	299	1	i	int
    //   13	268	2	j	int
    //   17	266	3	k	int
    //   243	43	4	m	int
    //   4	454	5	localObject1	Object
    //   472	3	5	localInvocationTargetException1	java.lang.reflect.InvocationTargetException
    //   480	3	5	localInvocationTargetException2	java.lang.reflect.InvocationTargetException
    //   488	3	5	localInvocationTargetException3	java.lang.reflect.InvocationTargetException
    //   496	3	5	localInvocationTargetException4	java.lang.reflect.InvocationTargetException
    //   504	3	5	localInvocationTargetException5	java.lang.reflect.InvocationTargetException
    //   512	3	5	localInvocationTargetException6	java.lang.reflect.InvocationTargetException
    //   520	3	5	localInvocationTargetException7	java.lang.reflect.InvocationTargetException
    //   36	71	6	localObject2	Object
    // Exception table:
    //   from	to	target	type
    //   402	414	472	java/lang/reflect/InvocationTargetException
    //   445	457	480	java/lang/reflect/InvocationTargetException
    //   266	278	488	java/lang/reflect/InvocationTargetException
    //   355	367	496	java/lang/reflect/InvocationTargetException
    //   38	50	504	java/lang/reflect/InvocationTargetException
    //   94	106	512	java/lang/reflect/InvocationTargetException
    //   200	212	520	java/lang/reflect/InvocationTargetException
  }
  
  /* Error */
  public boolean bo006F006Foo006Fo006Foo()
  {
    // Byte code:
    //   0: getstatic 70	uuuuuu/qqqqll:b0070p0070007000700070pp0070	I
    //   3: getstatic 101	uuuuuu/qqqqll:b007000700070007000700070pp0070	I
    //   6: iadd
    //   7: getstatic 70	uuuuuu/qqqqll:b0070p0070007000700070pp0070	I
    //   10: imul
    //   11: getstatic 99	uuuuuu/qqqqll:bpppppp0070p0070	I
    //   14: irem
    //   15: getstatic 103	uuuuuu/qqqqll:bp00700070007000700070pp0070	I
    //   18: if_icmpeq +13 -> 31
    //   21: bipush 72
    //   23: putstatic 70	uuuuuu/qqqqll:b0070p0070007000700070pp0070	I
    //   26: bipush 98
    //   28: putstatic 103	uuuuuu/qqqqll:bp00700070007000700070pp0070	I
    //   31: aload_0
    //   32: getfield 34	uuuuuu/qqqqll:bpp0070007000700070pp0070	Luuuuuu/heeeeh;
    //   35: ifnull +50 -> 85
    //   38: ldc 2
    //   40: ldc -80
    //   42: sipush 185
    //   45: bipush 44
    //   47: iconst_2
    //   48: invokestatic 78	xxxxxx/uxxxxx:bbbb0062b0062b0062b0062	(Ljava/lang/String;CCC)Ljava/lang/String;
    //   51: iconst_0
    //   52: anewarray 80	java/lang/Class
    //   55: invokevirtual 84	java/lang/Class:getMethod	(Ljava/lang/String;[Ljava/lang/Class;)Ljava/lang/reflect/Method;
    //   58: astore 5
    //   60: aload 5
    //   62: aload_0
    //   63: iconst_0
    //   64: anewarray 86	java/lang/Object
    //   67: invokevirtual 92	java/lang/reflect/Method:invoke	(Ljava/lang/Object;[Ljava/lang/Object;)Ljava/lang/Object;
    //   70: astore 5
    //   72: aload 5
    //   74: checkcast 178	java/lang/Boolean
    //   77: invokevirtual 181	java/lang/Boolean:booleanValue	()Z
    //   80: ifne +5 -> 85
    //   83: iconst_1
    //   84: ireturn
    //   85: getstatic 70	uuuuuu/qqqqll:b0070p0070007000700070pp0070	I
    //   88: istore_1
    //   89: getstatic 101	uuuuuu/qqqqll:b007000700070007000700070pp0070	I
    //   92: istore_2
    //   93: getstatic 70	uuuuuu/qqqqll:b0070p0070007000700070pp0070	I
    //   96: istore_3
    //   97: ldc 2
    //   99: ldc -73
    //   101: sipush 142
    //   104: iconst_0
    //   105: invokestatic 113	xxxxxx/uxxxxx:bb00620062bb0062b0062b0062	(Ljava/lang/String;CC)Ljava/lang/String;
    //   108: iconst_0
    //   109: anewarray 80	java/lang/Class
    //   112: invokevirtual 84	java/lang/Class:getMethod	(Ljava/lang/String;[Ljava/lang/Class;)Ljava/lang/reflect/Method;
    //   115: astore 5
    //   117: aload 5
    //   119: aconst_null
    //   120: iconst_0
    //   121: anewarray 86	java/lang/Object
    //   124: invokevirtual 92	java/lang/reflect/Method:invoke	(Ljava/lang/Object;[Ljava/lang/Object;)Ljava/lang/Object;
    //   127: astore 5
    //   129: aload 5
    //   131: checkcast 94	java/lang/Integer
    //   134: invokevirtual 97	java/lang/Integer:intValue	()I
    //   137: istore 4
    //   139: ldc 2
    //   141: ldc -71
    //   143: sipush 241
    //   146: bipush 15
    //   148: iconst_3
    //   149: invokestatic 78	xxxxxx/uxxxxx:bbbb0062b0062b0062b0062	(Ljava/lang/String;CCC)Ljava/lang/String;
    //   152: iconst_0
    //   153: anewarray 80	java/lang/Class
    //   156: invokevirtual 84	java/lang/Class:getMethod	(Ljava/lang/String;[Ljava/lang/Class;)Ljava/lang/reflect/Method;
    //   159: astore 5
    //   161: aload 5
    //   163: aconst_null
    //   164: iconst_0
    //   165: anewarray 86	java/lang/Object
    //   168: invokevirtual 92	java/lang/reflect/Method:invoke	(Ljava/lang/Object;[Ljava/lang/Object;)Ljava/lang/Object;
    //   171: astore 5
    //   173: aload 5
    //   175: checkcast 94	java/lang/Integer
    //   178: invokevirtual 97	java/lang/Integer:intValue	()I
    //   181: iload 4
    //   183: iadd
    //   184: iload 4
    //   186: imul
    //   187: getstatic 99	uuuuuu/qqqqll:bpppppp0070p0070	I
    //   190: irem
    //   191: tableswitch	default:+17->208, 0:+109->300
    //   208: getstatic 70	uuuuuu/qqqqll:b0070p0070007000700070pp0070	I
    //   211: istore 4
    //   213: iload 4
    //   215: getstatic 101	uuuuuu/qqqqll:b007000700070007000700070pp0070	I
    //   218: iload 4
    //   220: iadd
    //   221: imul
    //   222: getstatic 99	uuuuuu/qqqqll:bpppppp0070p0070	I
    //   225: irem
    //   226: tableswitch	default:+18->244, 0:+65->291
    //   244: ldc 2
    //   246: ldc -69
    //   248: bipush 93
    //   250: iconst_3
    //   251: invokestatic 113	xxxxxx/uxxxxx:bb00620062bb0062b0062b0062	(Ljava/lang/String;CC)Ljava/lang/String;
    //   254: iconst_0
    //   255: anewarray 80	java/lang/Class
    //   258: invokevirtual 84	java/lang/Class:getMethod	(Ljava/lang/String;[Ljava/lang/Class;)Ljava/lang/reflect/Method;
    //   261: astore 5
    //   263: aload 5
    //   265: aconst_null
    //   266: iconst_0
    //   267: anewarray 86	java/lang/Object
    //   270: invokevirtual 92	java/lang/reflect/Method:invoke	(Ljava/lang/Object;[Ljava/lang/Object;)Ljava/lang/Object;
    //   273: astore 5
    //   275: aload 5
    //   277: checkcast 94	java/lang/Integer
    //   280: invokevirtual 97	java/lang/Integer:intValue	()I
    //   283: putstatic 70	uuuuuu/qqqqll:b0070p0070007000700070pp0070	I
    //   286: bipush 69
    //   288: putstatic 103	uuuuuu/qqqqll:bp00700070007000700070pp0070	I
    //   291: iconst_4
    //   292: putstatic 70	uuuuuu/qqqqll:b0070p0070007000700070pp0070	I
    //   295: bipush 45
    //   297: putstatic 103	uuuuuu/qqqqll:bp00700070007000700070pp0070	I
    //   300: iload_3
    //   301: iload_1
    //   302: iload_2
    //   303: iadd
    //   304: imul
    //   305: getstatic 99	uuuuuu/qqqqll:bpppppp0070p0070	I
    //   308: irem
    //   309: getstatic 103	uuuuuu/qqqqll:bp00700070007000700070pp0070	I
    //   312: if_icmpeq +92 -> 404
    //   315: bipush 19
    //   317: putstatic 70	uuuuuu/qqqqll:b0070p0070007000700070pp0070	I
    //   320: ldc 2
    //   322: ldc -67
    //   324: bipush 58
    //   326: iconst_4
    //   327: invokestatic 113	xxxxxx/uxxxxx:bb00620062bb0062b0062b0062	(Ljava/lang/String;CC)Ljava/lang/String;
    //   330: iconst_0
    //   331: anewarray 80	java/lang/Class
    //   334: invokevirtual 84	java/lang/Class:getMethod	(Ljava/lang/String;[Ljava/lang/Class;)Ljava/lang/reflect/Method;
    //   337: astore 5
    //   339: aload 5
    //   341: aconst_null
    //   342: iconst_0
    //   343: anewarray 86	java/lang/Object
    //   346: invokevirtual 92	java/lang/reflect/Method:invoke	(Ljava/lang/Object;[Ljava/lang/Object;)Ljava/lang/Object;
    //   349: astore 5
    //   351: aload 5
    //   353: checkcast 94	java/lang/Integer
    //   356: invokevirtual 97	java/lang/Integer:intValue	()I
    //   359: putstatic 103	uuuuuu/qqqqll:bp00700070007000700070pp0070	I
    //   362: iconst_0
    //   363: ireturn
    //   364: astore 5
    //   366: aload 5
    //   368: invokevirtual 117	java/lang/reflect/InvocationTargetException:getCause	()Ljava/lang/Throwable;
    //   371: athrow
    //   372: astore 5
    //   374: aload 5
    //   376: invokevirtual 117	java/lang/reflect/InvocationTargetException:getCause	()Ljava/lang/Throwable;
    //   379: athrow
    //   380: astore 5
    //   382: aload 5
    //   384: invokevirtual 117	java/lang/reflect/InvocationTargetException:getCause	()Ljava/lang/Throwable;
    //   387: athrow
    //   388: astore 5
    //   390: aload 5
    //   392: invokevirtual 117	java/lang/reflect/InvocationTargetException:getCause	()Ljava/lang/Throwable;
    //   395: athrow
    //   396: astore 5
    //   398: aload 5
    //   400: invokevirtual 117	java/lang/reflect/InvocationTargetException:getCause	()Ljava/lang/Throwable;
    //   403: athrow
    //   404: iconst_0
    //   405: ireturn
    // Local variable table:
    //   start	length	slot	name	signature
    //   0	406	0	this	qqqqll
    //   88	216	1	i	int
    //   92	212	2	j	int
    //   96	209	3	k	int
    //   137	85	4	m	int
    //   58	294	5	localObject	Object
    //   364	3	5	localInvocationTargetException1	java.lang.reflect.InvocationTargetException
    //   372	3	5	localInvocationTargetException2	java.lang.reflect.InvocationTargetException
    //   380	3	5	localInvocationTargetException3	java.lang.reflect.InvocationTargetException
    //   388	3	5	localInvocationTargetException4	java.lang.reflect.InvocationTargetException
    //   396	3	5	localInvocationTargetException5	java.lang.reflect.InvocationTargetException
    // Exception table:
    //   from	to	target	type
    //   339	351	364	java/lang/reflect/InvocationTargetException
    //   117	129	372	java/lang/reflect/InvocationTargetException
    //   60	72	380	java/lang/reflect/InvocationTargetException
    //   161	173	388	java/lang/reflect/InvocationTargetException
    //   263	275	396	java/lang/reflect/InvocationTargetException
  }
  
  /* Error */
  public heeeeh boo006F006Fo006Fo006Foo()
  {
    // Byte code:
    //   0: iconst_1
    //   1: istore_1
    //   2: iload_1
    //   3: iconst_0
    //   4: idiv
    //   5: istore_1
    //   6: goto -4 -> 2
    //   9: astore 5
    //   11: ldc 2
    //   13: ldc -61
    //   15: bipush 83
    //   17: sipush 237
    //   20: iconst_2
    //   21: invokestatic 78	xxxxxx/uxxxxx:bbbb0062b0062b0062b0062	(Ljava/lang/String;CCC)Ljava/lang/String;
    //   24: iconst_0
    //   25: anewarray 80	java/lang/Class
    //   28: invokevirtual 84	java/lang/Class:getMethod	(Ljava/lang/String;[Ljava/lang/Class;)Ljava/lang/reflect/Method;
    //   31: astore 5
    //   33: aload 5
    //   35: aconst_null
    //   36: iconst_0
    //   37: anewarray 86	java/lang/Object
    //   40: invokevirtual 92	java/lang/reflect/Method:invoke	(Ljava/lang/Object;[Ljava/lang/Object;)Ljava/lang/Object;
    //   43: astore 5
    //   45: aload 5
    //   47: checkcast 94	java/lang/Integer
    //   50: invokevirtual 97	java/lang/Integer:intValue	()I
    //   53: putstatic 70	uuuuuu/qqqqll:b0070p0070007000700070pp0070	I
    //   56: ldc 2
    //   58: ldc -59
    //   60: sipush 154
    //   63: iconst_2
    //   64: invokestatic 113	xxxxxx/uxxxxx:bb00620062bb0062b0062b0062	(Ljava/lang/String;CC)Ljava/lang/String;
    //   67: iconst_0
    //   68: anewarray 80	java/lang/Class
    //   71: invokevirtual 84	java/lang/Class:getMethod	(Ljava/lang/String;[Ljava/lang/Class;)Ljava/lang/reflect/Method;
    //   74: astore 5
    //   76: aload 5
    //   78: aconst_null
    //   79: iconst_0
    //   80: anewarray 86	java/lang/Object
    //   83: invokevirtual 92	java/lang/reflect/Method:invoke	(Ljava/lang/Object;[Ljava/lang/Object;)Ljava/lang/Object;
    //   86: astore 5
    //   88: aload 5
    //   90: checkcast 94	java/lang/Integer
    //   93: invokevirtual 97	java/lang/Integer:intValue	()I
    //   96: istore_1
    //   97: getstatic 101	uuuuuu/qqqqll:b007000700070007000700070pp0070	I
    //   100: istore_2
    //   101: ldc 2
    //   103: ldc -61
    //   105: bipush 100
    //   107: iconst_2
    //   108: invokestatic 113	xxxxxx/uxxxxx:bb00620062bb0062b0062b0062	(Ljava/lang/String;CC)Ljava/lang/String;
    //   111: iconst_0
    //   112: anewarray 80	java/lang/Class
    //   115: invokevirtual 84	java/lang/Class:getMethod	(Ljava/lang/String;[Ljava/lang/Class;)Ljava/lang/reflect/Method;
    //   118: astore 5
    //   120: aload 5
    //   122: aconst_null
    //   123: iconst_0
    //   124: anewarray 86	java/lang/Object
    //   127: invokevirtual 92	java/lang/reflect/Method:invoke	(Ljava/lang/Object;[Ljava/lang/Object;)Ljava/lang/Object;
    //   130: astore 5
    //   132: aload 5
    //   134: checkcast 94	java/lang/Integer
    //   137: invokevirtual 97	java/lang/Integer:intValue	()I
    //   140: istore_3
    //   141: ldc 2
    //   143: ldc -57
    //   145: bipush 11
    //   147: iconst_5
    //   148: invokestatic 113	xxxxxx/uxxxxx:bb00620062bb0062b0062b0062	(Ljava/lang/String;CC)Ljava/lang/String;
    //   151: iconst_0
    //   152: anewarray 80	java/lang/Class
    //   155: invokevirtual 84	java/lang/Class:getMethod	(Ljava/lang/String;[Ljava/lang/Class;)Ljava/lang/reflect/Method;
    //   158: astore 5
    //   160: aload 5
    //   162: aconst_null
    //   163: iconst_0
    //   164: anewarray 86	java/lang/Object
    //   167: invokevirtual 92	java/lang/reflect/Method:invoke	(Ljava/lang/Object;[Ljava/lang/Object;)Ljava/lang/Object;
    //   170: astore 5
    //   172: iload_2
    //   173: iload_1
    //   174: iadd
    //   175: iload_3
    //   176: imul
    //   177: aload 5
    //   179: checkcast 94	java/lang/Integer
    //   182: invokevirtual 97	java/lang/Integer:intValue	()I
    //   185: irem
    //   186: getstatic 103	uuuuuu/qqqqll:bp00700070007000700070pp0070	I
    //   189: if_icmpeq +271 -> 460
    //   192: getstatic 70	uuuuuu/qqqqll:b0070p0070007000700070pp0070	I
    //   195: getstatic 101	uuuuuu/qqqqll:b007000700070007000700070pp0070	I
    //   198: iadd
    //   199: getstatic 70	uuuuuu/qqqqll:b0070p0070007000700070pp0070	I
    //   202: imul
    //   203: getstatic 99	uuuuuu/qqqqll:bpppppp0070p0070	I
    //   206: irem
    //   207: getstatic 103	uuuuuu/qqqqll:bp00700070007000700070pp0070	I
    //   210: if_icmpeq +202 -> 412
    //   213: ldc 2
    //   215: ldc -55
    //   217: bipush 111
    //   219: iconst_5
    //   220: invokestatic 113	xxxxxx/uxxxxx:bb00620062bb0062b0062b0062	(Ljava/lang/String;CC)Ljava/lang/String;
    //   223: iconst_0
    //   224: anewarray 80	java/lang/Class
    //   227: invokevirtual 84	java/lang/Class:getMethod	(Ljava/lang/String;[Ljava/lang/Class;)Ljava/lang/reflect/Method;
    //   230: astore 5
    //   232: aload 5
    //   234: aconst_null
    //   235: iconst_0
    //   236: anewarray 86	java/lang/Object
    //   239: invokevirtual 92	java/lang/reflect/Method:invoke	(Ljava/lang/Object;[Ljava/lang/Object;)Ljava/lang/Object;
    //   242: astore 5
    //   244: aload 5
    //   246: checkcast 94	java/lang/Integer
    //   249: invokevirtual 97	java/lang/Integer:intValue	()I
    //   252: putstatic 70	uuuuuu/qqqqll:b0070p0070007000700070pp0070	I
    //   255: ldc 2
    //   257: ldc -53
    //   259: sipush 227
    //   262: iconst_5
    //   263: invokestatic 113	xxxxxx/uxxxxx:bb00620062bb0062b0062b0062	(Ljava/lang/String;CC)Ljava/lang/String;
    //   266: iconst_0
    //   267: anewarray 80	java/lang/Class
    //   270: invokevirtual 84	java/lang/Class:getMethod	(Ljava/lang/String;[Ljava/lang/Class;)Ljava/lang/reflect/Method;
    //   273: astore 5
    //   275: aload 5
    //   277: aconst_null
    //   278: iconst_0
    //   279: anewarray 86	java/lang/Object
    //   282: invokevirtual 92	java/lang/reflect/Method:invoke	(Ljava/lang/Object;[Ljava/lang/Object;)Ljava/lang/Object;
    //   285: astore 5
    //   287: aload 5
    //   289: checkcast 94	java/lang/Integer
    //   292: invokevirtual 97	java/lang/Integer:intValue	()I
    //   295: putstatic 103	uuuuuu/qqqqll:bp00700070007000700070pp0070	I
    //   298: getstatic 70	uuuuuu/qqqqll:b0070p0070007000700070pp0070	I
    //   301: istore_1
    //   302: getstatic 101	uuuuuu/qqqqll:b007000700070007000700070pp0070	I
    //   305: istore_2
    //   306: getstatic 70	uuuuuu/qqqqll:b0070p0070007000700070pp0070	I
    //   309: istore_3
    //   310: getstatic 99	uuuuuu/qqqqll:bpppppp0070p0070	I
    //   313: istore 4
    //   315: ldc 2
    //   317: ldc -51
    //   319: bipush 124
    //   321: iconst_5
    //   322: invokestatic 113	xxxxxx/uxxxxx:bb00620062bb0062b0062b0062	(Ljava/lang/String;CC)Ljava/lang/String;
    //   325: iconst_0
    //   326: anewarray 80	java/lang/Class
    //   329: invokevirtual 84	java/lang/Class:getMethod	(Ljava/lang/String;[Ljava/lang/Class;)Ljava/lang/reflect/Method;
    //   332: astore 5
    //   334: aload 5
    //   336: aconst_null
    //   337: iconst_0
    //   338: anewarray 86	java/lang/Object
    //   341: invokevirtual 92	java/lang/reflect/Method:invoke	(Ljava/lang/Object;[Ljava/lang/Object;)Ljava/lang/Object;
    //   344: astore 5
    //   346: iload_1
    //   347: iload_2
    //   348: iadd
    //   349: iload_3
    //   350: imul
    //   351: iload 4
    //   353: irem
    //   354: aload 5
    //   356: checkcast 94	java/lang/Integer
    //   359: invokevirtual 97	java/lang/Integer:intValue	()I
    //   362: if_icmpeq +50 -> 412
    //   365: bipush 38
    //   367: putstatic 70	uuuuuu/qqqqll:b0070p0070007000700070pp0070	I
    //   370: ldc 2
    //   372: ldc -49
    //   374: bipush 18
    //   376: iconst_3
    //   377: invokestatic 113	xxxxxx/uxxxxx:bb00620062bb0062b0062b0062	(Ljava/lang/String;CC)Ljava/lang/String;
    //   380: iconst_0
    //   381: anewarray 80	java/lang/Class
    //   384: invokevirtual 84	java/lang/Class:getMethod	(Ljava/lang/String;[Ljava/lang/Class;)Ljava/lang/reflect/Method;
    //   387: astore 5
    //   389: aload 5
    //   391: aconst_null
    //   392: iconst_0
    //   393: anewarray 86	java/lang/Object
    //   396: invokevirtual 92	java/lang/reflect/Method:invoke	(Ljava/lang/Object;[Ljava/lang/Object;)Ljava/lang/Object;
    //   399: astore 5
    //   401: aload 5
    //   403: checkcast 94	java/lang/Integer
    //   406: invokevirtual 97	java/lang/Integer:intValue	()I
    //   409: putstatic 103	uuuuuu/qqqqll:bp00700070007000700070pp0070	I
    //   412: bipush 37
    //   414: putstatic 70	uuuuuu/qqqqll:b0070p0070007000700070pp0070	I
    //   417: ldc 2
    //   419: ldc -47
    //   421: sipush 142
    //   424: iconst_5
    //   425: invokestatic 113	xxxxxx/uxxxxx:bb00620062bb0062b0062b0062	(Ljava/lang/String;CC)Ljava/lang/String;
    //   428: iconst_0
    //   429: anewarray 80	java/lang/Class
    //   432: invokevirtual 84	java/lang/Class:getMethod	(Ljava/lang/String;[Ljava/lang/Class;)Ljava/lang/reflect/Method;
    //   435: astore 5
    //   437: aload 5
    //   439: aconst_null
    //   440: iconst_0
    //   441: anewarray 86	java/lang/Object
    //   444: invokevirtual 92	java/lang/reflect/Method:invoke	(Ljava/lang/Object;[Ljava/lang/Object;)Ljava/lang/Object;
    //   447: astore 5
    //   449: aload 5
    //   451: checkcast 94	java/lang/Integer
    //   454: invokevirtual 97	java/lang/Integer:intValue	()I
    //   457: putstatic 103	uuuuuu/qqqqll:bp00700070007000700070pp0070	I
    //   460: aload_0
    //   461: getfield 34	uuuuuu/qqqqll:bpp0070007000700070pp0070	Luuuuuu/heeeeh;
    //   464: areturn
    //   465: astore 5
    //   467: aload 5
    //   469: invokevirtual 117	java/lang/reflect/InvocationTargetException:getCause	()Ljava/lang/Throwable;
    //   472: athrow
    //   473: astore 5
    //   475: aload 5
    //   477: invokevirtual 117	java/lang/reflect/InvocationTargetException:getCause	()Ljava/lang/Throwable;
    //   480: athrow
    //   481: astore 5
    //   483: aload 5
    //   485: invokevirtual 117	java/lang/reflect/InvocationTargetException:getCause	()Ljava/lang/Throwable;
    //   488: athrow
    //   489: astore 5
    //   491: aload 5
    //   493: invokevirtual 117	java/lang/reflect/InvocationTargetException:getCause	()Ljava/lang/Throwable;
    //   496: athrow
    //   497: astore 5
    //   499: aload 5
    //   501: invokevirtual 117	java/lang/reflect/InvocationTargetException:getCause	()Ljava/lang/Throwable;
    //   504: athrow
    //   505: astore 5
    //   507: aload 5
    //   509: invokevirtual 117	java/lang/reflect/InvocationTargetException:getCause	()Ljava/lang/Throwable;
    //   512: athrow
    //   513: astore 5
    //   515: aload 5
    //   517: invokevirtual 117	java/lang/reflect/InvocationTargetException:getCause	()Ljava/lang/Throwable;
    //   520: athrow
    //   521: astore 5
    //   523: aload 5
    //   525: invokevirtual 117	java/lang/reflect/InvocationTargetException:getCause	()Ljava/lang/Throwable;
    //   528: athrow
    //   529: astore 5
    //   531: aload 5
    //   533: invokevirtual 117	java/lang/reflect/InvocationTargetException:getCause	()Ljava/lang/Throwable;
    //   536: athrow
    // Local variable table:
    //   start	length	slot	name	signature
    //   0	537	0	this	qqqqll
    //   1	348	1	i	int
    //   100	249	2	j	int
    //   140	211	3	k	int
    //   313	41	4	m	int
    //   9	1	5	localException	Exception
    //   31	419	5	localObject	Object
    //   465	3	5	localInvocationTargetException1	java.lang.reflect.InvocationTargetException
    //   473	3	5	localInvocationTargetException2	java.lang.reflect.InvocationTargetException
    //   481	3	5	localInvocationTargetException3	java.lang.reflect.InvocationTargetException
    //   489	3	5	localInvocationTargetException4	java.lang.reflect.InvocationTargetException
    //   497	3	5	localInvocationTargetException5	java.lang.reflect.InvocationTargetException
    //   505	3	5	localInvocationTargetException6	java.lang.reflect.InvocationTargetException
    //   513	3	5	localInvocationTargetException7	java.lang.reflect.InvocationTargetException
    //   521	3	5	localInvocationTargetException8	java.lang.reflect.InvocationTargetException
    //   529	3	5	localInvocationTargetException9	java.lang.reflect.InvocationTargetException
    // Exception table:
    //   from	to	target	type
    //   2	6	9	java/lang/Exception
    //   33	45	465	java/lang/reflect/InvocationTargetException
    //   76	88	473	java/lang/reflect/InvocationTargetException
    //   120	132	481	java/lang/reflect/InvocationTargetException
    //   160	172	489	java/lang/reflect/InvocationTargetException
    //   437	449	497	java/lang/reflect/InvocationTargetException
    //   232	244	505	java/lang/reflect/InvocationTargetException
    //   275	287	513	java/lang/reflect/InvocationTargetException
    //   334	346	521	java/lang/reflect/InvocationTargetException
    //   389	401	529	java/lang/reflect/InvocationTargetException
  }
  
  /* Error */
  public com.db.pwcc.dbmobile.model.banking.TransactionsData boo006Foo006Fo006Foo()
  {
    // Byte code:
    //   0: aload_0
    //   1: getfield 34	uuuuuu/qqqqll:bpp0070007000700070pp0070	Luuuuuu/heeeeh;
    //   4: astore 8
    //   6: getstatic 70	uuuuuu/qqqqll:b0070p0070007000700070pp0070	I
    //   9: istore_1
    //   10: ldc 2
    //   12: ldc -44
    //   14: bipush 73
    //   16: iconst_1
    //   17: invokestatic 113	xxxxxx/uxxxxx:bb00620062bb0062b0062b0062	(Ljava/lang/String;CC)Ljava/lang/String;
    //   20: iconst_0
    //   21: anewarray 80	java/lang/Class
    //   24: invokevirtual 84	java/lang/Class:getMethod	(Ljava/lang/String;[Ljava/lang/Class;)Ljava/lang/reflect/Method;
    //   27: astore 9
    //   29: aload 9
    //   31: aconst_null
    //   32: iconst_0
    //   33: anewarray 86	java/lang/Object
    //   36: invokevirtual 92	java/lang/reflect/Method:invoke	(Ljava/lang/Object;[Ljava/lang/Object;)Ljava/lang/Object;
    //   39: astore 9
    //   41: aload 9
    //   43: checkcast 94	java/lang/Integer
    //   46: invokevirtual 97	java/lang/Integer:intValue	()I
    //   49: istore_2
    //   50: getstatic 101	uuuuuu/qqqqll:b007000700070007000700070pp0070	I
    //   53: istore_3
    //   54: ldc 2
    //   56: ldc -42
    //   58: bipush 33
    //   60: bipush 75
    //   62: iconst_2
    //   63: invokestatic 78	xxxxxx/uxxxxx:bbbb0062b0062b0062b0062	(Ljava/lang/String;CCC)Ljava/lang/String;
    //   66: iconst_0
    //   67: anewarray 80	java/lang/Class
    //   70: invokevirtual 84	java/lang/Class:getMethod	(Ljava/lang/String;[Ljava/lang/Class;)Ljava/lang/reflect/Method;
    //   73: astore 9
    //   75: aload 9
    //   77: aconst_null
    //   78: iconst_0
    //   79: anewarray 86	java/lang/Object
    //   82: invokevirtual 92	java/lang/reflect/Method:invoke	(Ljava/lang/Object;[Ljava/lang/Object;)Ljava/lang/Object;
    //   85: astore 9
    //   87: aload 9
    //   89: checkcast 94	java/lang/Integer
    //   92: invokevirtual 97	java/lang/Integer:intValue	()I
    //   95: istore 4
    //   97: getstatic 99	uuuuuu/qqqqll:bpppppp0070p0070	I
    //   100: istore 5
    //   102: getstatic 103	uuuuuu/qqqqll:bp00700070007000700070pp0070	I
    //   105: istore 6
    //   107: getstatic 70	uuuuuu/qqqqll:b0070p0070007000700070pp0070	I
    //   110: istore 7
    //   112: iload 7
    //   114: getstatic 101	uuuuuu/qqqqll:b007000700070007000700070pp0070	I
    //   117: iload 7
    //   119: iadd
    //   120: imul
    //   121: getstatic 99	uuuuuu/qqqqll:bpppppp0070p0070	I
    //   124: irem
    //   125: tableswitch	default:+19->144, 0:+106->231
    //   144: ldc 2
    //   146: ldc -40
    //   148: sipush 180
    //   151: bipush 96
    //   153: iconst_1
    //   154: invokestatic 78	xxxxxx/uxxxxx:bbbb0062b0062b0062b0062	(Ljava/lang/String;CCC)Ljava/lang/String;
    //   157: iconst_0
    //   158: anewarray 80	java/lang/Class
    //   161: invokevirtual 84	java/lang/Class:getMethod	(Ljava/lang/String;[Ljava/lang/Class;)Ljava/lang/reflect/Method;
    //   164: astore 9
    //   166: aload 9
    //   168: aconst_null
    //   169: iconst_0
    //   170: anewarray 86	java/lang/Object
    //   173: invokevirtual 92	java/lang/reflect/Method:invoke	(Ljava/lang/Object;[Ljava/lang/Object;)Ljava/lang/Object;
    //   176: astore 9
    //   178: aload 9
    //   180: checkcast 94	java/lang/Integer
    //   183: invokevirtual 97	java/lang/Integer:intValue	()I
    //   186: putstatic 70	uuuuuu/qqqqll:b0070p0070007000700070pp0070	I
    //   189: ldc 2
    //   191: ldc -38
    //   193: bipush 41
    //   195: iconst_0
    //   196: invokestatic 113	xxxxxx/uxxxxx:bb00620062bb0062b0062b0062	(Ljava/lang/String;CC)Ljava/lang/String;
    //   199: iconst_0
    //   200: anewarray 80	java/lang/Class
    //   203: invokevirtual 84	java/lang/Class:getMethod	(Ljava/lang/String;[Ljava/lang/Class;)Ljava/lang/reflect/Method;
    //   206: astore 9
    //   208: aload 9
    //   210: aconst_null
    //   211: iconst_0
    //   212: anewarray 86	java/lang/Object
    //   215: invokevirtual 92	java/lang/reflect/Method:invoke	(Ljava/lang/Object;[Ljava/lang/Object;)Ljava/lang/Object;
    //   218: astore 9
    //   220: aload 9
    //   222: checkcast 94	java/lang/Integer
    //   225: invokevirtual 97	java/lang/Integer:intValue	()I
    //   228: putstatic 103	uuuuuu/qqqqll:bp00700070007000700070pp0070	I
    //   231: iload 4
    //   233: iload_3
    //   234: iload_2
    //   235: iadd
    //   236: imul
    //   237: iload 5
    //   239: irem
    //   240: iload 6
    //   242: if_icmpeq +53 -> 295
    //   245: ldc 2
    //   247: ldc -36
    //   249: sipush 137
    //   252: bipush 47
    //   254: iconst_1
    //   255: invokestatic 78	xxxxxx/uxxxxx:bbbb0062b0062b0062b0062	(Ljava/lang/String;CCC)Ljava/lang/String;
    //   258: iconst_0
    //   259: anewarray 80	java/lang/Class
    //   262: invokevirtual 84	java/lang/Class:getMethod	(Ljava/lang/String;[Ljava/lang/Class;)Ljava/lang/reflect/Method;
    //   265: astore 9
    //   267: aload 9
    //   269: aconst_null
    //   270: iconst_0
    //   271: anewarray 86	java/lang/Object
    //   274: invokevirtual 92	java/lang/reflect/Method:invoke	(Ljava/lang/Object;[Ljava/lang/Object;)Ljava/lang/Object;
    //   277: astore 9
    //   279: aload 9
    //   281: checkcast 94	java/lang/Integer
    //   284: invokevirtual 97	java/lang/Integer:intValue	()I
    //   287: putstatic 70	uuuuuu/qqqqll:b0070p0070007000700070pp0070	I
    //   290: bipush 97
    //   292: putstatic 103	uuuuuu/qqqqll:bp00700070007000700070pp0070	I
    //   295: getstatic 101	uuuuuu/qqqqll:b007000700070007000700070pp0070	I
    //   298: iload_1
    //   299: iadd
    //   300: iload_1
    //   301: imul
    //   302: getstatic 99	uuuuuu/qqqqll:bpppppp0070p0070	I
    //   305: irem
    //   306: tableswitch	default:+18->324, 0:+145->451
    //   324: bipush 12
    //   326: putstatic 70	uuuuuu/qqqqll:b0070p0070007000700070pp0070	I
    //   329: ldc 2
    //   331: ldc -34
    //   333: sipush 255
    //   336: iconst_1
    //   337: invokestatic 113	xxxxxx/uxxxxx:bb00620062bb0062b0062b0062	(Ljava/lang/String;CC)Ljava/lang/String;
    //   340: iconst_0
    //   341: anewarray 80	java/lang/Class
    //   344: invokevirtual 84	java/lang/Class:getMethod	(Ljava/lang/String;[Ljava/lang/Class;)Ljava/lang/reflect/Method;
    //   347: astore 9
    //   349: aload 9
    //   351: aconst_null
    //   352: iconst_0
    //   353: anewarray 86	java/lang/Object
    //   356: invokevirtual 92	java/lang/reflect/Method:invoke	(Ljava/lang/Object;[Ljava/lang/Object;)Ljava/lang/Object;
    //   359: astore 9
    //   361: aload 9
    //   363: checkcast 94	java/lang/Integer
    //   366: invokevirtual 97	java/lang/Integer:intValue	()I
    //   369: putstatic 103	uuuuuu/qqqqll:bp00700070007000700070pp0070	I
    //   372: getstatic 70	uuuuuu/qqqqll:b0070p0070007000700070pp0070	I
    //   375: istore_1
    //   376: iload_1
    //   377: getstatic 101	uuuuuu/qqqqll:b007000700070007000700070pp0070	I
    //   380: iload_1
    //   381: iadd
    //   382: imul
    //   383: getstatic 99	uuuuuu/qqqqll:bpppppp0070p0070	I
    //   386: irem
    //   387: tableswitch	default:+17->404, 0:+64->451
    //   404: ldc 2
    //   406: ldc -32
    //   408: bipush 47
    //   410: iconst_4
    //   411: invokestatic 113	xxxxxx/uxxxxx:bb00620062bb0062b0062b0062	(Ljava/lang/String;CC)Ljava/lang/String;
    //   414: iconst_0
    //   415: anewarray 80	java/lang/Class
    //   418: invokevirtual 84	java/lang/Class:getMethod	(Ljava/lang/String;[Ljava/lang/Class;)Ljava/lang/reflect/Method;
    //   421: astore 9
    //   423: aload 9
    //   425: aconst_null
    //   426: iconst_0
    //   427: anewarray 86	java/lang/Object
    //   430: invokevirtual 92	java/lang/reflect/Method:invoke	(Ljava/lang/Object;[Ljava/lang/Object;)Ljava/lang/Object;
    //   433: astore 9
    //   435: aload 9
    //   437: checkcast 94	java/lang/Integer
    //   440: invokevirtual 97	java/lang/Integer:intValue	()I
    //   443: putstatic 70	uuuuuu/qqqqll:b0070p0070007000700070pp0070	I
    //   446: bipush 30
    //   448: putstatic 103	uuuuuu/qqqqll:bp00700070007000700070pp0070	I
    //   451: aload 8
    //   453: invokevirtual 152	uuuuuu/heeeeh:boo006Foooooo006F	()Lcom/db/pwcc/dbmobile/model/banking/TransactionsData;
    //   456: areturn
    //   457: astore 8
    //   459: aload 8
    //   461: invokevirtual 117	java/lang/reflect/InvocationTargetException:getCause	()Ljava/lang/Throwable;
    //   464: athrow
    //   465: astore 8
    //   467: aload 8
    //   469: invokevirtual 117	java/lang/reflect/InvocationTargetException:getCause	()Ljava/lang/Throwable;
    //   472: athrow
    //   473: astore 8
    //   475: aload 8
    //   477: invokevirtual 117	java/lang/reflect/InvocationTargetException:getCause	()Ljava/lang/Throwable;
    //   480: athrow
    //   481: astore 8
    //   483: aload 8
    //   485: invokevirtual 117	java/lang/reflect/InvocationTargetException:getCause	()Ljava/lang/Throwable;
    //   488: athrow
    //   489: astore 8
    //   491: aload 8
    //   493: invokevirtual 117	java/lang/reflect/InvocationTargetException:getCause	()Ljava/lang/Throwable;
    //   496: athrow
    //   497: astore 8
    //   499: aload 8
    //   501: invokevirtual 117	java/lang/reflect/InvocationTargetException:getCause	()Ljava/lang/Throwable;
    //   504: athrow
    //   505: astore 8
    //   507: aload 8
    //   509: invokevirtual 117	java/lang/reflect/InvocationTargetException:getCause	()Ljava/lang/Throwable;
    //   512: athrow
    // Local variable table:
    //   start	length	slot	name	signature
    //   0	513	0	this	qqqqll
    //   9	374	1	i	int
    //   49	187	2	j	int
    //   53	183	3	k	int
    //   95	142	4	m	int
    //   100	140	5	n	int
    //   105	138	6	i1	int
    //   110	11	7	i2	int
    //   4	448	8	localHeeeeh	heeeeh
    //   457	3	8	localInvocationTargetException1	java.lang.reflect.InvocationTargetException
    //   465	3	8	localInvocationTargetException2	java.lang.reflect.InvocationTargetException
    //   473	3	8	localInvocationTargetException3	java.lang.reflect.InvocationTargetException
    //   481	3	8	localInvocationTargetException4	java.lang.reflect.InvocationTargetException
    //   489	3	8	localInvocationTargetException5	java.lang.reflect.InvocationTargetException
    //   497	3	8	localInvocationTargetException6	java.lang.reflect.InvocationTargetException
    //   505	3	8	localInvocationTargetException7	java.lang.reflect.InvocationTargetException
    //   27	409	9	localObject	Object
    // Exception table:
    //   from	to	target	type
    //   29	41	457	java/lang/reflect/InvocationTargetException
    //   75	87	465	java/lang/reflect/InvocationTargetException
    //   267	279	473	java/lang/reflect/InvocationTargetException
    //   423	435	481	java/lang/reflect/InvocationTargetException
    //   349	361	489	java/lang/reflect/InvocationTargetException
    //   166	178	497	java/lang/reflect/InvocationTargetException
    //   208	220	505	java/lang/reflect/InvocationTargetException
  }
}
