package uuuuuu;

import com.db.pwcc.dbmobile.migration.MigrationKey;
import javax.inject.Inject;

public class rvrrvv
  implements vrvrvv
{
  public static int b007800780078xxx0078xx = 0;
  public static int b0078xx0078xx0078xx = 2;
  public static int bx00780078xxx0078xx = 31;
  private static final String bxx0078xxx0078xx;
  public static int bxxx0078xx0078xx = 1;
  @Inject
  public mbmmmb b0078x0078xxx0078xx;
  
  static
  {
    if ((bx00780078xxx0078xx + bxxx0078xx0078xx) * bx00780078xxx0078xx % b0078xx0078xx0078xx != b007800780078xxx0078xx)
    {
      bx00780078xxx0078xx = bqqq00710071q00710071q0071();
      b007800780078xxx0078xx = 83;
    }
    bxx0078xxx0078xx = rvrrvv.class.getSimpleName();
    int i = bx00780078xxx0078xx;
    switch (i * (bq00710071q0071q00710071q0071() + i) % b0078xx0078xx0078xx)
    {
    default: 
      bx00780078xxx0078xx = 85;
      b007800780078xxx0078xx = bqqq00710071q00710071q0071();
    }
  }
  
  public rvrrvv() {}
  
  public static int b007100710071q0071q00710071q0071()
  {
    return 0;
  }
  
  public static int b0071q0071q0071q00710071q0071()
  {
    return 2;
  }
  
  public static int bq00710071q0071q00710071q0071()
  {
    return 1;
  }
  
  public static int bqqq00710071q00710071q0071()
  {
    return 17;
  }
  
  public int b00710071q00710071q00710071q0071()
  {
    if ((bqqq00710071q00710071q0071() + bxxx0078xx0078xx) * bqqq00710071q00710071q0071() % b0071q0071q0071q00710071q0071() != b007800780078xxx0078xx)
    {
      bx00780078xxx0078xx = 94;
      b007800780078xxx0078xx = 72;
    }
    int i = bx00780078xxx0078xx;
    switch (i * (bq00710071q0071q00710071q0071() + i) % b0078xx0078xx0078xx)
    {
    default: 
      bx00780078xxx0078xx = bqqq00710071q00710071q0071();
      b007800780078xxx0078xx = 84;
    }
    return 0;
  }
  
  /* Error */
  @android.support.annotation.RequiresApi(api=23)
  public void b0071qq00710071q00710071q0071()
  {
    // Byte code:
    //   0: invokestatic 68	uuuuuu/ggyggg:ba0061aaa0061a006100610061	()Luuuuuu/ygyggg;
    //   3: astore_3
    //   4: getstatic 24	uuuuuu/rvrrvv:bx00780078xxx0078xx	I
    //   7: getstatic 26	uuuuuu/rvrrvv:bxxx0078xx0078xx	I
    //   10: iadd
    //   11: getstatic 24	uuuuuu/rvrrvv:bx00780078xxx0078xx	I
    //   14: imul
    //   15: getstatic 28	uuuuuu/rvrrvv:b0078xx0078xx0078xx	I
    //   18: irem
    //   19: invokestatic 70	uuuuuu/rvrrvv:b007100710071q0071q00710071q0071	()I
    //   22: if_icmpeq +14 -> 36
    //   25: bipush 12
    //   27: putstatic 24	uuuuuu/rvrrvv:bx00780078xxx0078xx	I
    //   30: invokestatic 34	uuuuuu/rvrrvv:bqqq00710071q00710071q0071	()I
    //   33: putstatic 30	uuuuuu/rvrrvv:b007800780078xxx0078xx	I
    //   36: aload_3
    //   37: aload_0
    //   38: invokeinterface 76 2 0
    //   43: new 78	com/db/pwcc/dbmobile/secure/preferences/encrypted/MigrationDecryptionManager
    //   46: dup
    //   47: invokespecial 79	com/db/pwcc/dbmobile/secure/preferences/encrypted/MigrationDecryptionManager:<init>	()V
    //   50: astore_3
    //   51: ldc 81
    //   53: ldc 83
    //   55: sipush 224
    //   58: bipush 60
    //   60: iconst_1
    //   61: invokestatic 89	xxxxxx/uxxxxx:bbbb0062b0062b0062b0062	(Ljava/lang/String;CCC)Ljava/lang/String;
    //   64: iconst_0
    //   65: anewarray 36	java/lang/Class
    //   68: invokevirtual 93	java/lang/Class:getMethod	(Ljava/lang/String;[Ljava/lang/Class;)Ljava/lang/reflect/Method;
    //   71: astore 4
    //   73: aload 4
    //   75: aload_3
    //   76: iconst_0
    //   77: anewarray 4	java/lang/Object
    //   80: invokevirtual 99	java/lang/reflect/Method:invoke	(Ljava/lang/Object;[Ljava/lang/Object;)Ljava/lang/Object;
    //   83: astore 4
    //   85: aload 4
    //   87: checkcast 101	java/lang/Boolean
    //   90: invokevirtual 105	java/lang/Boolean:booleanValue	()Z
    //   93: istore_2
    //   94: getstatic 24	uuuuuu/rvrrvv:bx00780078xxx0078xx	I
    //   97: istore_1
    //   98: iload_1
    //   99: invokestatic 45	uuuuuu/rvrrvv:bq00710071q0071q00710071q0071	()I
    //   102: iload_1
    //   103: iadd
    //   104: imul
    //   105: getstatic 28	uuuuuu/rvrrvv:b0078xx0078xx0078xx	I
    //   108: irem
    //   109: tableswitch	default:+19->128, 0:+30->139
    //   128: invokestatic 34	uuuuuu/rvrrvv:bqqq00710071q00710071q0071	()I
    //   131: putstatic 24	uuuuuu/rvrrvv:bx00780078xxx0078xx	I
    //   134: bipush 50
    //   136: putstatic 30	uuuuuu/rvrrvv:b007800780078xxx0078xx	I
    //   139: iload_2
    //   140: ifeq +212 -> 352
    //   143: aload_0
    //   144: getfield 107	uuuuuu/rvrrvv:b0078x0078xxx0078xx	Luuuuuu/mbmmmb;
    //   147: iconst_1
    //   148: invokevirtual 113	uuuuuu/mbmmmb:prepareEncryptionManagerForOperations	(I)V
    //   151: aload_0
    //   152: getfield 107	uuuuuu/rvrrvv:b0078x0078xxx0078xx	Luuuuuu/mbmmmb;
    //   155: invokevirtual 117	uuuuuu/mbmmmb:booo006Fo006F006Fo006F006F	()Landroid/support/v4/util/Pair;
    //   158: astore 4
    //   160: aload 4
    //   162: ifnull +151 -> 313
    //   165: aload 4
    //   167: getfield 123	android/support/v4/util/Pair:second	Ljava/lang/Object;
    //   170: checkcast 125	java/lang/String
    //   173: astore 5
    //   175: ldc 81
    //   177: ldc 127
    //   179: sipush 148
    //   182: iconst_2
    //   183: invokestatic 131	xxxxxx/uxxxxx:bb00620062bb0062b0062b0062	(Ljava/lang/String;CC)Ljava/lang/String;
    //   186: iconst_1
    //   187: anewarray 36	java/lang/Class
    //   190: dup
    //   191: iconst_0
    //   192: ldc 125
    //   194: aastore
    //   195: invokevirtual 93	java/lang/Class:getMethod	(Ljava/lang/String;[Ljava/lang/Class;)Ljava/lang/reflect/Method;
    //   198: astore 6
    //   200: aload 6
    //   202: aload_3
    //   203: iconst_1
    //   204: anewarray 4	java/lang/Object
    //   207: dup
    //   208: iconst_0
    //   209: aload 5
    //   211: aastore
    //   212: invokevirtual 99	java/lang/reflect/Method:invoke	(Ljava/lang/Object;[Ljava/lang/Object;)Ljava/lang/Object;
    //   215: astore 5
    //   217: aload 5
    //   219: checkcast 125	java/lang/String
    //   222: astore 5
    //   224: aload_0
    //   225: getfield 107	uuuuuu/rvrrvv:b0078x0078xxx0078xx	Luuuuuu/mbmmmb;
    //   228: invokevirtual 135	uuuuuu/mbmmmb:edit	()Lcom/db/pwcc/dbmobile/secure/preferences/encrypted/SecuredPreferenceStore$Editor;
    //   231: astore 6
    //   233: aload 4
    //   235: getfield 138	android/support/v4/util/Pair:first	Ljava/lang/Object;
    //   238: checkcast 125	java/lang/String
    //   241: astore 4
    //   243: ldc -116
    //   245: ldc -114
    //   247: sipush 132
    //   250: sipush 245
    //   253: iconst_2
    //   254: invokestatic 89	xxxxxx/uxxxxx:bbbb0062b0062b0062b0062	(Ljava/lang/String;CCC)Ljava/lang/String;
    //   257: iconst_2
    //   258: anewarray 36	java/lang/Class
    //   261: dup
    //   262: iconst_0
    //   263: ldc 125
    //   265: aastore
    //   266: dup
    //   267: iconst_1
    //   268: ldc 125
    //   270: aastore
    //   271: invokevirtual 93	java/lang/Class:getMethod	(Ljava/lang/String;[Ljava/lang/Class;)Ljava/lang/reflect/Method;
    //   274: astore 7
    //   276: aload 7
    //   278: aload 6
    //   280: iconst_2
    //   281: anewarray 4	java/lang/Object
    //   284: dup
    //   285: iconst_0
    //   286: aload 4
    //   288: aastore
    //   289: dup
    //   290: iconst_1
    //   291: aload 5
    //   293: aastore
    //   294: invokevirtual 99	java/lang/reflect/Method:invoke	(Ljava/lang/Object;[Ljava/lang/Object;)Ljava/lang/Object;
    //   297: astore 4
    //   299: aload 4
    //   301: checkcast 144	android/content/SharedPreferences$Editor
    //   304: astore 4
    //   306: aload 4
    //   308: invokeinterface 147 1 0
    //   313: ldc 81
    //   315: ldc -107
    //   317: bipush 36
    //   319: iconst_2
    //   320: iconst_3
    //   321: invokestatic 89	xxxxxx/uxxxxx:bbbb0062b0062b0062b0062	(Ljava/lang/String;CCC)Ljava/lang/String;
    //   324: iconst_0
    //   325: anewarray 36	java/lang/Class
    //   328: invokevirtual 93	java/lang/Class:getMethod	(Ljava/lang/String;[Ljava/lang/Class;)Ljava/lang/reflect/Method;
    //   331: astore 4
    //   333: aload 4
    //   335: aload_3
    //   336: iconst_0
    //   337: anewarray 4	java/lang/Object
    //   340: invokevirtual 99	java/lang/reflect/Method:invoke	(Ljava/lang/Object;[Ljava/lang/Object;)Ljava/lang/Object;
    //   343: astore_3
    //   344: aload_3
    //   345: checkcast 101	java/lang/Boolean
    //   348: invokevirtual 105	java/lang/Boolean:booleanValue	()Z
    //   351: pop
    //   352: return
    //   353: astore_3
    //   354: getstatic 42	uuuuuu/rvrrvv:bxx0078xxx0078xx	Ljava/lang/String;
    //   357: astore 4
    //   359: new 151	java/lang/StringBuilder
    //   362: dup
    //   363: invokespecial 152	java/lang/StringBuilder:<init>	()V
    //   366: astore 5
    //   368: ldc -102
    //   370: ldc -100
    //   372: bipush 111
    //   374: iconst_1
    //   375: invokestatic 131	xxxxxx/uxxxxx:bb00620062bb0062b0062b0062	(Ljava/lang/String;CC)Ljava/lang/String;
    //   378: iconst_4
    //   379: anewarray 36	java/lang/Class
    //   382: dup
    //   383: iconst_0
    //   384: ldc 125
    //   386: aastore
    //   387: dup
    //   388: iconst_1
    //   389: getstatic 162	java/lang/Character:TYPE	Ljava/lang/Class;
    //   392: aastore
    //   393: dup
    //   394: iconst_2
    //   395: getstatic 162	java/lang/Character:TYPE	Ljava/lang/Class;
    //   398: aastore
    //   399: dup
    //   400: iconst_3
    //   401: getstatic 162	java/lang/Character:TYPE	Ljava/lang/Class;
    //   404: aastore
    //   405: invokevirtual 93	java/lang/Class:getMethod	(Ljava/lang/String;[Ljava/lang/Class;)Ljava/lang/reflect/Method;
    //   408: astore 6
    //   410: aload 6
    //   412: aconst_null
    //   413: iconst_4
    //   414: anewarray 4	java/lang/Object
    //   417: dup
    //   418: iconst_0
    //   419: ldc -92
    //   421: aastore
    //   422: dup
    //   423: iconst_1
    //   424: bipush 100
    //   426: invokestatic 168	java/lang/Character:valueOf	(C)Ljava/lang/Character;
    //   429: aastore
    //   430: dup
    //   431: iconst_2
    //   432: sipush 162
    //   435: invokestatic 168	java/lang/Character:valueOf	(C)Ljava/lang/Character;
    //   438: aastore
    //   439: dup
    //   440: iconst_3
    //   441: iconst_1
    //   442: invokestatic 168	java/lang/Character:valueOf	(C)Ljava/lang/Character;
    //   445: aastore
    //   446: invokevirtual 99	java/lang/reflect/Method:invoke	(Ljava/lang/Object;[Ljava/lang/Object;)Ljava/lang/Object;
    //   449: astore 6
    //   451: aload 4
    //   453: aload 5
    //   455: aload 6
    //   457: checkcast 125	java/lang/String
    //   460: invokevirtual 172	java/lang/StringBuilder:append	(Ljava/lang/String;)Ljava/lang/StringBuilder;
    //   463: aload_3
    //   464: invokevirtual 175	java/lang/StringBuilder:append	(Ljava/lang/Object;)Ljava/lang/StringBuilder;
    //   467: invokevirtual 178	java/lang/StringBuilder:toString	()Ljava/lang/String;
    //   470: invokestatic 184	uuuuuu/rvvvrv:bqqqq00710071q0071q0071	(Ljava/lang/String;Ljava/lang/String;)V
    //   473: return
    //   474: astore_3
    //   475: aload_3
    //   476: invokevirtual 188	java/lang/reflect/InvocationTargetException:getCause	()Ljava/lang/Throwable;
    //   479: athrow
    //   480: astore_3
    //   481: aload_3
    //   482: invokevirtual 188	java/lang/reflect/InvocationTargetException:getCause	()Ljava/lang/Throwable;
    //   485: athrow
    //   486: astore_3
    //   487: aload_3
    //   488: invokevirtual 188	java/lang/reflect/InvocationTargetException:getCause	()Ljava/lang/Throwable;
    //   491: athrow
    //   492: astore_3
    //   493: aload_3
    //   494: invokevirtual 188	java/lang/reflect/InvocationTargetException:getCause	()Ljava/lang/Throwable;
    //   497: athrow
    //   498: astore_3
    //   499: aload_3
    //   500: invokevirtual 188	java/lang/reflect/InvocationTargetException:getCause	()Ljava/lang/Throwable;
    //   503: athrow
    // Local variable table:
    //   start	length	slot	name	signature
    //   0	504	0	this	rvrrvv
    //   97	8	1	i	int
    //   93	47	2	bool	boolean
    //   3	342	3	localObject1	Object
    //   353	111	3	localGeneralSecurityException	java.security.GeneralSecurityException
    //   474	2	3	localInvocationTargetException1	java.lang.reflect.InvocationTargetException
    //   480	2	3	localInvocationTargetException2	java.lang.reflect.InvocationTargetException
    //   486	2	3	localInvocationTargetException3	java.lang.reflect.InvocationTargetException
    //   492	2	3	localInvocationTargetException4	java.lang.reflect.InvocationTargetException
    //   498	2	3	localInvocationTargetException5	java.lang.reflect.InvocationTargetException
    //   71	381	4	localObject2	Object
    //   173	281	5	localObject3	Object
    //   198	258	6	localObject4	Object
    //   274	3	7	localMethod	java.lang.reflect.Method
    // Exception table:
    //   from	to	target	type
    //   73	85	353	java/security/GeneralSecurityException
    //   143	160	353	java/security/GeneralSecurityException
    //   165	175	353	java/security/GeneralSecurityException
    //   200	217	353	java/security/GeneralSecurityException
    //   224	243	353	java/security/GeneralSecurityException
    //   276	299	353	java/security/GeneralSecurityException
    //   306	313	353	java/security/GeneralSecurityException
    //   333	344	353	java/security/GeneralSecurityException
    //   475	480	353	java/security/GeneralSecurityException
    //   481	486	353	java/security/GeneralSecurityException
    //   487	492	353	java/security/GeneralSecurityException
    //   493	498	353	java/security/GeneralSecurityException
    //   200	217	474	java/lang/reflect/InvocationTargetException
    //   73	85	480	java/lang/reflect/InvocationTargetException
    //   276	299	486	java/lang/reflect/InvocationTargetException
    //   333	344	492	java/lang/reflect/InvocationTargetException
    //   410	451	498	java/lang/reflect/InvocationTargetException
  }
  
  public int bq0071q00710071q00710071q0071()
  {
    int i = bx00780078xxx0078xx;
    int j = bxxx0078xx0078xx;
    if ((bx00780078xxx0078xx + bxxx0078xx0078xx) * bx00780078xxx0078xx % b0078xx0078xx0078xx != b007800780078xxx0078xx)
    {
      bx00780078xxx0078xx = bqqq00710071q00710071q0071();
      b007800780078xxx0078xx = bqqq00710071q00710071q0071();
    }
    if ((i + j) * bx00780078xxx0078xx % b0078xx0078xx0078xx != b007800780078xxx0078xx)
    {
      bx00780078xxx0078xx = 25;
      b007800780078xxx0078xx = 17;
    }
    return Integer.MAX_VALUE;
  }
  
  public String bqq007100710071q00710071q0071()
  {
    MigrationKey localMigrationKey = MigrationKey.FINGERPRINT_KEY_MIGRATION;
    int i = bx00780078xxx0078xx;
    int j = bx00780078xxx0078xx;
    switch (j * (bxxx0078xx0078xx + j) % b0078xx0078xx0078xx)
    {
    default: 
      bx00780078xxx0078xx = 29;
      b007800780078xxx0078xx = 71;
    }
    switch (i * (bxxx0078xx0078xx + i) % b0078xx0078xx0078xx)
    {
    default: 
      bx00780078xxx0078xx = bqqq00710071q00710071q0071();
      b007800780078xxx0078xx = 57;
    }
    return localMigrationKey.name();
  }
}
