package uuuuuu;

import com.db.pwcc.dbmobile.secure.SecurityUtils;

public class sossso
  extends ssssst<ososso.oossso>
  implements ososso.ssosso
{
  public static int b006C006Clll006Cll006C = 2;
  public static int b006Cl006Cll006Cll006C = 0;
  public static int bl006Clll006Cll006C = 1;
  public static int bll006Cll006Cll006C = 79;
  private static final String blllll006Cll006C = sossso.class.getSimpleName();
  private final SecurityUtils b006Cllll006Cll006C = new SecurityUtils();
  
  /* Error */
  static
  {
    // Byte code:
    //   0: ldc 2
    //   2: invokevirtual 30	java/lang/Class:getSimpleName	()Ljava/lang/String;
    //   5: putstatic 32	uuuuuu/sossso:blllll006Cll006C	Ljava/lang/String;
    //   8: ldc 2
    //   10: ldc 34
    //   12: sipush 179
    //   15: bipush 6
    //   17: iconst_3
    //   18: invokestatic 40	xxxxxx/uxxxxx:bbbb0062b0062b0062b0062	(Ljava/lang/String;CCC)Ljava/lang/String;
    //   21: iconst_0
    //   22: anewarray 26	java/lang/Class
    //   25: invokevirtual 44	java/lang/Class:getMethod	(Ljava/lang/String;[Ljava/lang/Class;)Ljava/lang/reflect/Method;
    //   28: astore_1
    //   29: aload_1
    //   30: aconst_null
    //   31: iconst_0
    //   32: anewarray 46	java/lang/Object
    //   35: invokevirtual 52	java/lang/reflect/Method:invoke	(Ljava/lang/Object;[Ljava/lang/Object;)Ljava/lang/Object;
    //   38: astore_1
    //   39: aload_1
    //   40: checkcast 54	java/lang/Integer
    //   43: invokevirtual 58	java/lang/Integer:intValue	()I
    //   46: istore_0
    //   47: iload_0
    //   48: getstatic 60	uuuuuu/sossso:bl006Clll006Cll006C	I
    //   51: iload_0
    //   52: iadd
    //   53: imul
    //   54: getstatic 62	uuuuuu/sossso:b006C006Clll006Cll006C	I
    //   57: irem
    //   58: tableswitch	default:+18->76, 0:+276->334
    //   76: bipush 80
    //   78: putstatic 60	uuuuuu/sossso:bl006Clll006Cll006C	I
    //   81: getstatic 64	uuuuuu/sossso:bll006Cll006Cll006C	I
    //   84: istore_0
    //   85: iload_0
    //   86: getstatic 60	uuuuuu/sossso:bl006Clll006Cll006C	I
    //   89: iload_0
    //   90: iadd
    //   91: imul
    //   92: getstatic 62	uuuuuu/sossso:b006C006Clll006Cll006C	I
    //   95: irem
    //   96: tableswitch	default:+20->116, 0:+173->269
    //   116: getstatic 64	uuuuuu/sossso:bll006Cll006Cll006C	I
    //   119: istore_0
    //   120: iload_0
    //   121: getstatic 60	uuuuuu/sossso:bl006Clll006Cll006C	I
    //   124: iload_0
    //   125: iadd
    //   126: imul
    //   127: getstatic 62	uuuuuu/sossso:b006C006Clll006Cll006C	I
    //   130: irem
    //   131: tableswitch	default:+17->148, 0:+95->226
    //   148: ldc 2
    //   150: ldc 66
    //   152: bipush 26
    //   154: iconst_5
    //   155: invokestatic 70	xxxxxx/uxxxxx:bb00620062bb0062b0062b0062	(Ljava/lang/String;CC)Ljava/lang/String;
    //   158: iconst_0
    //   159: anewarray 26	java/lang/Class
    //   162: invokevirtual 44	java/lang/Class:getMethod	(Ljava/lang/String;[Ljava/lang/Class;)Ljava/lang/reflect/Method;
    //   165: astore_1
    //   166: aload_1
    //   167: aconst_null
    //   168: iconst_0
    //   169: anewarray 46	java/lang/Object
    //   172: invokevirtual 52	java/lang/reflect/Method:invoke	(Ljava/lang/Object;[Ljava/lang/Object;)Ljava/lang/Object;
    //   175: astore_1
    //   176: aload_1
    //   177: checkcast 54	java/lang/Integer
    //   180: invokevirtual 58	java/lang/Integer:intValue	()I
    //   183: putstatic 64	uuuuuu/sossso:bll006Cll006Cll006C	I
    //   186: ldc 2
    //   188: ldc 72
    //   190: bipush 95
    //   192: bipush 27
    //   194: iconst_1
    //   195: invokestatic 40	xxxxxx/uxxxxx:bbbb0062b0062b0062b0062	(Ljava/lang/String;CCC)Ljava/lang/String;
    //   198: iconst_0
    //   199: anewarray 26	java/lang/Class
    //   202: invokevirtual 44	java/lang/Class:getMethod	(Ljava/lang/String;[Ljava/lang/Class;)Ljava/lang/reflect/Method;
    //   205: astore_1
    //   206: aload_1
    //   207: aconst_null
    //   208: iconst_0
    //   209: anewarray 46	java/lang/Object
    //   212: invokevirtual 52	java/lang/reflect/Method:invoke	(Ljava/lang/Object;[Ljava/lang/Object;)Ljava/lang/Object;
    //   215: astore_1
    //   216: aload_1
    //   217: checkcast 54	java/lang/Integer
    //   220: invokevirtual 58	java/lang/Integer:intValue	()I
    //   223: putstatic 60	uuuuuu/sossso:bl006Clll006Cll006C	I
    //   226: ldc 2
    //   228: ldc 74
    //   230: sipush 196
    //   233: iconst_0
    //   234: invokestatic 70	xxxxxx/uxxxxx:bb00620062bb0062b0062b0062	(Ljava/lang/String;CC)Ljava/lang/String;
    //   237: iconst_0
    //   238: anewarray 26	java/lang/Class
    //   241: invokevirtual 44	java/lang/Class:getMethod	(Ljava/lang/String;[Ljava/lang/Class;)Ljava/lang/reflect/Method;
    //   244: astore_1
    //   245: aload_1
    //   246: aconst_null
    //   247: iconst_0
    //   248: anewarray 46	java/lang/Object
    //   251: invokevirtual 52	java/lang/reflect/Method:invoke	(Ljava/lang/Object;[Ljava/lang/Object;)Ljava/lang/Object;
    //   254: astore_1
    //   255: aload_1
    //   256: checkcast 54	java/lang/Integer
    //   259: invokevirtual 58	java/lang/Integer:intValue	()I
    //   262: putstatic 64	uuuuuu/sossso:bll006Cll006Cll006C	I
    //   265: iconst_3
    //   266: putstatic 60	uuuuuu/sossso:bl006Clll006Cll006C	I
    //   269: getstatic 64	uuuuuu/sossso:bll006Cll006Cll006C	I
    //   272: getstatic 60	uuuuuu/sossso:bl006Clll006Cll006C	I
    //   275: iadd
    //   276: getstatic 64	uuuuuu/sossso:bll006Cll006Cll006C	I
    //   279: imul
    //   280: getstatic 62	uuuuuu/sossso:b006C006Clll006Cll006C	I
    //   283: irem
    //   284: getstatic 76	uuuuuu/sossso:b006Cl006Cll006Cll006C	I
    //   287: if_icmpeq +47 -> 334
    //   290: bipush 63
    //   292: putstatic 64	uuuuuu/sossso:bll006Cll006Cll006C	I
    //   295: ldc 2
    //   297: ldc 78
    //   299: sipush 251
    //   302: iconst_0
    //   303: invokestatic 70	xxxxxx/uxxxxx:bb00620062bb0062b0062b0062	(Ljava/lang/String;CC)Ljava/lang/String;
    //   306: iconst_0
    //   307: anewarray 26	java/lang/Class
    //   310: invokevirtual 44	java/lang/Class:getMethod	(Ljava/lang/String;[Ljava/lang/Class;)Ljava/lang/reflect/Method;
    //   313: astore_1
    //   314: aload_1
    //   315: aconst_null
    //   316: iconst_0
    //   317: anewarray 46	java/lang/Object
    //   320: invokevirtual 52	java/lang/reflect/Method:invoke	(Ljava/lang/Object;[Ljava/lang/Object;)Ljava/lang/Object;
    //   323: astore_1
    //   324: aload_1
    //   325: checkcast 54	java/lang/Integer
    //   328: invokevirtual 58	java/lang/Integer:intValue	()I
    //   331: putstatic 76	uuuuuu/sossso:b006Cl006Cll006Cll006C	I
    //   334: return
    //   335: astore_1
    //   336: aload_1
    //   337: invokevirtual 82	java/lang/reflect/InvocationTargetException:getCause	()Ljava/lang/Throwable;
    //   340: athrow
    //   341: astore_1
    //   342: aload_1
    //   343: invokevirtual 82	java/lang/reflect/InvocationTargetException:getCause	()Ljava/lang/Throwable;
    //   346: athrow
    //   347: astore_1
    //   348: aload_1
    //   349: invokevirtual 82	java/lang/reflect/InvocationTargetException:getCause	()Ljava/lang/Throwable;
    //   352: athrow
    //   353: astore_1
    //   354: aload_1
    //   355: invokevirtual 82	java/lang/reflect/InvocationTargetException:getCause	()Ljava/lang/Throwable;
    //   358: athrow
    //   359: astore_1
    //   360: aload_1
    //   361: invokevirtual 82	java/lang/reflect/InvocationTargetException:getCause	()Ljava/lang/Throwable;
    //   364: athrow
    // Local variable table:
    //   start	length	slot	name	signature
    //   46	81	0	i	int
    //   28	297	1	localObject	Object
    //   335	2	1	localInvocationTargetException1	java.lang.reflect.InvocationTargetException
    //   341	2	1	localInvocationTargetException2	java.lang.reflect.InvocationTargetException
    //   347	2	1	localInvocationTargetException3	java.lang.reflect.InvocationTargetException
    //   353	2	1	localInvocationTargetException4	java.lang.reflect.InvocationTargetException
    //   359	2	1	localInvocationTargetException5	java.lang.reflect.InvocationTargetException
    // Exception table:
    //   from	to	target	type
    //   245	255	335	java/lang/reflect/InvocationTargetException
    //   29	39	341	java/lang/reflect/InvocationTargetException
    //   166	176	347	java/lang/reflect/InvocationTargetException
    //   206	216	353	java/lang/reflect/InvocationTargetException
    //   314	324	359	java/lang/reflect/InvocationTargetException
  }
  
  public sossso() {}
  
  public static int b00690069ii0069ii0069ii()
  {
    return 1;
  }
  
  public static int b0069iii0069ii0069ii()
  {
    return 2;
  }
  
  public static int bi0069ii0069ii0069ii()
  {
    return 42;
  }
  
  public static int biiii0069ii0069ii()
  {
    return 0;
  }
  
  /* Error */
  public void b0069i0069i0069ii0069ii()
  {
    // Byte code:
    //   0: ldc 2
    //   2: ldc 100
    //   4: sipush 254
    //   7: iconst_0
    //   8: invokestatic 70	xxxxxx/uxxxxx:bb00620062bb0062b0062b0062	(Ljava/lang/String;CC)Ljava/lang/String;
    //   11: iconst_0
    //   12: anewarray 26	java/lang/Class
    //   15: invokevirtual 44	java/lang/Class:getMethod	(Ljava/lang/String;[Ljava/lang/Class;)Ljava/lang/reflect/Method;
    //   18: astore 7
    //   20: aload 7
    //   22: aconst_null
    //   23: iconst_0
    //   24: anewarray 46	java/lang/Object
    //   27: invokevirtual 52	java/lang/reflect/Method:invoke	(Ljava/lang/Object;[Ljava/lang/Object;)Ljava/lang/Object;
    //   30: astore 7
    //   32: aload 7
    //   34: checkcast 54	java/lang/Integer
    //   37: invokevirtual 58	java/lang/Integer:intValue	()I
    //   40: istore_1
    //   41: getstatic 60	uuuuuu/sossso:bl006Clll006Cll006C	I
    //   44: istore_2
    //   45: getstatic 62	uuuuuu/sossso:b006C006Clll006Cll006C	I
    //   48: istore_3
    //   49: getstatic 64	uuuuuu/sossso:bll006Cll006Cll006C	I
    //   52: istore 6
    //   54: getstatic 60	uuuuuu/sossso:bl006Clll006Cll006C	I
    //   57: istore 5
    //   59: getstatic 64	uuuuuu/sossso:bll006Cll006Cll006C	I
    //   62: istore 4
    //   64: ldc 2
    //   66: ldc 102
    //   68: sipush 227
    //   71: iconst_0
    //   72: invokestatic 70	xxxxxx/uxxxxx:bb00620062bb0062b0062b0062	(Ljava/lang/String;CC)Ljava/lang/String;
    //   75: iconst_0
    //   76: anewarray 26	java/lang/Class
    //   79: invokevirtual 44	java/lang/Class:getMethod	(Ljava/lang/String;[Ljava/lang/Class;)Ljava/lang/reflect/Method;
    //   82: astore 7
    //   84: aload 7
    //   86: aconst_null
    //   87: iconst_0
    //   88: anewarray 46	java/lang/Object
    //   91: invokevirtual 52	java/lang/reflect/Method:invoke	(Ljava/lang/Object;[Ljava/lang/Object;)Ljava/lang/Object;
    //   94: astore 7
    //   96: iload 4
    //   98: iload 6
    //   100: iload 5
    //   102: iadd
    //   103: imul
    //   104: aload 7
    //   106: checkcast 54	java/lang/Integer
    //   109: invokevirtual 58	java/lang/Integer:intValue	()I
    //   112: irem
    //   113: getstatic 76	uuuuuu/sossso:b006Cl006Cll006Cll006C	I
    //   116: if_icmpeq +140 -> 256
    //   119: getstatic 64	uuuuuu/sossso:bll006Cll006Cll006C	I
    //   122: istore 4
    //   124: iload 4
    //   126: getstatic 60	uuuuuu/sossso:bl006Clll006Cll006C	I
    //   129: iload 4
    //   131: iadd
    //   132: imul
    //   133: getstatic 62	uuuuuu/sossso:b006C006Clll006Cll006C	I
    //   136: irem
    //   137: tableswitch	default:+19->156, 0:+69->206
    //   156: ldc 2
    //   158: ldc 104
    //   160: sipush 166
    //   163: bipush 113
    //   165: iconst_2
    //   166: invokestatic 40	xxxxxx/uxxxxx:bbbb0062b0062b0062b0062	(Ljava/lang/String;CCC)Ljava/lang/String;
    //   169: iconst_0
    //   170: anewarray 26	java/lang/Class
    //   173: invokevirtual 44	java/lang/Class:getMethod	(Ljava/lang/String;[Ljava/lang/Class;)Ljava/lang/reflect/Method;
    //   176: astore 7
    //   178: aload 7
    //   180: aconst_null
    //   181: iconst_0
    //   182: anewarray 46	java/lang/Object
    //   185: invokevirtual 52	java/lang/reflect/Method:invoke	(Ljava/lang/Object;[Ljava/lang/Object;)Ljava/lang/Object;
    //   188: astore 7
    //   190: aload 7
    //   192: checkcast 54	java/lang/Integer
    //   195: invokevirtual 58	java/lang/Integer:intValue	()I
    //   198: putstatic 64	uuuuuu/sossso:bll006Cll006Cll006C	I
    //   201: bipush 7
    //   203: putstatic 76	uuuuuu/sossso:b006Cl006Cll006Cll006C	I
    //   206: ldc 2
    //   208: ldc 106
    //   210: sipush 172
    //   213: bipush 63
    //   215: iconst_1
    //   216: invokestatic 40	xxxxxx/uxxxxx:bbbb0062b0062b0062b0062	(Ljava/lang/String;CCC)Ljava/lang/String;
    //   219: iconst_0
    //   220: anewarray 26	java/lang/Class
    //   223: invokevirtual 44	java/lang/Class:getMethod	(Ljava/lang/String;[Ljava/lang/Class;)Ljava/lang/reflect/Method;
    //   226: astore 7
    //   228: aload 7
    //   230: aconst_null
    //   231: iconst_0
    //   232: anewarray 46	java/lang/Object
    //   235: invokevirtual 52	java/lang/reflect/Method:invoke	(Ljava/lang/Object;[Ljava/lang/Object;)Ljava/lang/Object;
    //   238: astore 7
    //   240: aload 7
    //   242: checkcast 54	java/lang/Integer
    //   245: invokevirtual 58	java/lang/Integer:intValue	()I
    //   248: putstatic 64	uuuuuu/sossso:bll006Cll006Cll006C	I
    //   251: bipush 46
    //   253: putstatic 76	uuuuuu/sossso:b006Cl006Cll006Cll006C	I
    //   256: iload_1
    //   257: iload_2
    //   258: iload_1
    //   259: iadd
    //   260: imul
    //   261: iload_3
    //   262: irem
    //   263: tableswitch	default:+17->280, 0:+26->289
    //   280: iconst_5
    //   281: putstatic 64	uuuuuu/sossso:bll006Cll006Cll006C	I
    //   284: bipush 30
    //   286: putstatic 76	uuuuuu/sossso:b006Cl006Cll006Cll006C	I
    //   289: new 108	java/lang/NullPointerException
    //   292: dup
    //   293: invokespecial 109	java/lang/NullPointerException:<init>	()V
    //   296: athrow
    //   297: astore 7
    //   299: ldc 2
    //   301: ldc 104
    //   303: sipush 220
    //   306: bipush 87
    //   308: iconst_3
    //   309: invokestatic 40	xxxxxx/uxxxxx:bbbb0062b0062b0062b0062	(Ljava/lang/String;CCC)Ljava/lang/String;
    //   312: iconst_0
    //   313: anewarray 26	java/lang/Class
    //   316: invokevirtual 44	java/lang/Class:getMethod	(Ljava/lang/String;[Ljava/lang/Class;)Ljava/lang/reflect/Method;
    //   319: astore 7
    //   321: aload 7
    //   323: aconst_null
    //   324: iconst_0
    //   325: anewarray 46	java/lang/Object
    //   328: invokevirtual 52	java/lang/reflect/Method:invoke	(Ljava/lang/Object;[Ljava/lang/Object;)Ljava/lang/Object;
    //   331: astore 7
    //   333: aload 7
    //   335: checkcast 54	java/lang/Integer
    //   338: invokevirtual 58	java/lang/Integer:intValue	()I
    //   341: putstatic 64	uuuuuu/sossso:bll006Cll006Cll006C	I
    //   344: getstatic 115	uuuuuu/vvrvrv:b00680068hh0068h006800680068	Luuuuuu/vvrvrv;
    //   347: invokestatic 121	uuuuuu/rrvvrv:b0071q0071qq0071q0071q0071	(Luuuuuu/vvrvrv;)V
    //   350: return
    //   351: astore 7
    //   353: aload 7
    //   355: invokevirtual 82	java/lang/reflect/InvocationTargetException:getCause	()Ljava/lang/Throwable;
    //   358: athrow
    //   359: astore 7
    //   361: aload 7
    //   363: invokevirtual 82	java/lang/reflect/InvocationTargetException:getCause	()Ljava/lang/Throwable;
    //   366: athrow
    //   367: astore 7
    //   369: aload 7
    //   371: invokevirtual 82	java/lang/reflect/InvocationTargetException:getCause	()Ljava/lang/Throwable;
    //   374: athrow
    //   375: astore 7
    //   377: aload 7
    //   379: invokevirtual 82	java/lang/reflect/InvocationTargetException:getCause	()Ljava/lang/Throwable;
    //   382: athrow
    //   383: astore 7
    //   385: aload 7
    //   387: invokevirtual 82	java/lang/reflect/InvocationTargetException:getCause	()Ljava/lang/Throwable;
    //   390: athrow
    // Local variable table:
    //   start	length	slot	name	signature
    //   0	391	0	this	sossso
    //   40	221	1	i	int
    //   44	216	2	j	int
    //   48	215	3	k	int
    //   62	71	4	m	int
    //   57	46	5	n	int
    //   52	51	6	i1	int
    //   18	223	7	localObject1	Object
    //   297	1	7	localException	Exception
    //   319	15	7	localObject2	Object
    //   351	3	7	localInvocationTargetException1	java.lang.reflect.InvocationTargetException
    //   359	3	7	localInvocationTargetException2	java.lang.reflect.InvocationTargetException
    //   367	3	7	localInvocationTargetException3	java.lang.reflect.InvocationTargetException
    //   375	3	7	localInvocationTargetException4	java.lang.reflect.InvocationTargetException
    //   383	3	7	localInvocationTargetException5	java.lang.reflect.InvocationTargetException
    // Exception table:
    //   from	to	target	type
    //   289	297	297	java/lang/Exception
    //   84	96	351	java/lang/reflect/InvocationTargetException
    //   228	240	359	java/lang/reflect/InvocationTargetException
    //   20	32	367	java/lang/reflect/InvocationTargetException
    //   321	333	375	java/lang/reflect/InvocationTargetException
    //   178	190	383	java/lang/reflect/InvocationTargetException
  }
  
  /* Error */
  public void bi00690069i0069ii0069ii()
  {
    // Byte code:
    //   0: getstatic 32	uuuuuu/sossso:blllll006Cll006C	Ljava/lang/String;
    //   3: astore_3
    //   4: ldc -96
    //   6: ldc -94
    //   8: bipush 73
    //   10: sipush 154
    //   13: iconst_1
    //   14: invokestatic 40	xxxxxx/uxxxxx:bbbb0062b0062b0062b0062	(Ljava/lang/String;CCC)Ljava/lang/String;
    //   17: iconst_3
    //   18: anewarray 26	java/lang/Class
    //   21: dup
    //   22: iconst_0
    //   23: ldc -92
    //   25: aastore
    //   26: dup
    //   27: iconst_1
    //   28: getstatic 170	java/lang/Character:TYPE	Ljava/lang/Class;
    //   31: aastore
    //   32: dup
    //   33: iconst_2
    //   34: getstatic 170	java/lang/Character:TYPE	Ljava/lang/Class;
    //   37: aastore
    //   38: invokevirtual 44	java/lang/Class:getMethod	(Ljava/lang/String;[Ljava/lang/Class;)Ljava/lang/reflect/Method;
    //   41: astore 4
    //   43: aload 4
    //   45: aconst_null
    //   46: iconst_3
    //   47: anewarray 46	java/lang/Object
    //   50: dup
    //   51: iconst_0
    //   52: ldc -84
    //   54: aastore
    //   55: dup
    //   56: iconst_1
    //   57: bipush 34
    //   59: invokestatic 176	java/lang/Character:valueOf	(C)Ljava/lang/Character;
    //   62: aastore
    //   63: dup
    //   64: iconst_2
    //   65: iconst_1
    //   66: invokestatic 176	java/lang/Character:valueOf	(C)Ljava/lang/Character;
    //   69: aastore
    //   70: invokevirtual 52	java/lang/reflect/Method:invoke	(Ljava/lang/Object;[Ljava/lang/Object;)Ljava/lang/Object;
    //   73: astore 4
    //   75: aload_3
    //   76: aload 4
    //   78: checkcast 164	java/lang/String
    //   81: invokestatic 182	uuuuuu/rvvvrv:b007100710071q00710071q0071q0071	(Ljava/lang/String;Ljava/lang/String;)V
    //   84: ldc 2
    //   86: ldc -72
    //   88: sipush 223
    //   91: iconst_5
    //   92: invokestatic 70	xxxxxx/uxxxxx:bb00620062bb0062b0062b0062	(Ljava/lang/String;CC)Ljava/lang/String;
    //   95: iconst_0
    //   96: anewarray 26	java/lang/Class
    //   99: invokevirtual 44	java/lang/Class:getMethod	(Ljava/lang/String;[Ljava/lang/Class;)Ljava/lang/reflect/Method;
    //   102: astore_3
    //   103: aload_3
    //   104: aconst_null
    //   105: iconst_0
    //   106: anewarray 46	java/lang/Object
    //   109: invokevirtual 52	java/lang/reflect/Method:invoke	(Ljava/lang/Object;[Ljava/lang/Object;)Ljava/lang/Object;
    //   112: astore_3
    //   113: aload_3
    //   114: checkcast 54	java/lang/Integer
    //   117: invokevirtual 58	java/lang/Integer:intValue	()I
    //   120: istore_1
    //   121: getstatic 60	uuuuuu/sossso:bl006Clll006Cll006C	I
    //   124: istore_2
    //   125: ldc 2
    //   127: ldc -70
    //   129: bipush 121
    //   131: sipush 180
    //   134: iconst_1
    //   135: invokestatic 40	xxxxxx/uxxxxx:bbbb0062b0062b0062b0062	(Ljava/lang/String;CCC)Ljava/lang/String;
    //   138: iconst_0
    //   139: anewarray 26	java/lang/Class
    //   142: invokevirtual 44	java/lang/Class:getMethod	(Ljava/lang/String;[Ljava/lang/Class;)Ljava/lang/reflect/Method;
    //   145: astore_3
    //   146: aload_3
    //   147: aconst_null
    //   148: iconst_0
    //   149: anewarray 46	java/lang/Object
    //   152: invokevirtual 52	java/lang/reflect/Method:invoke	(Ljava/lang/Object;[Ljava/lang/Object;)Ljava/lang/Object;
    //   155: astore_3
    //   156: iload_2
    //   157: iload_1
    //   158: iadd
    //   159: iload_1
    //   160: imul
    //   161: aload_3
    //   162: checkcast 54	java/lang/Integer
    //   165: invokevirtual 58	java/lang/Integer:intValue	()I
    //   168: irem
    //   169: tableswitch	default:+19->188, 0:+63->232
    //   188: ldc 2
    //   190: ldc -68
    //   192: sipush 203
    //   195: iconst_5
    //   196: invokestatic 70	xxxxxx/uxxxxx:bb00620062bb0062b0062b0062	(Ljava/lang/String;CC)Ljava/lang/String;
    //   199: iconst_0
    //   200: anewarray 26	java/lang/Class
    //   203: invokevirtual 44	java/lang/Class:getMethod	(Ljava/lang/String;[Ljava/lang/Class;)Ljava/lang/reflect/Method;
    //   206: astore_3
    //   207: aload_3
    //   208: aconst_null
    //   209: iconst_0
    //   210: anewarray 46	java/lang/Object
    //   213: invokevirtual 52	java/lang/reflect/Method:invoke	(Ljava/lang/Object;[Ljava/lang/Object;)Ljava/lang/Object;
    //   216: astore_3
    //   217: aload_3
    //   218: checkcast 54	java/lang/Integer
    //   221: invokevirtual 58	java/lang/Integer:intValue	()I
    //   224: putstatic 64	uuuuuu/sossso:bll006Cll006Cll006C	I
    //   227: bipush 62
    //   229: putstatic 76	uuuuuu/sossso:b006Cl006Cll006Cll006C	I
    //   232: aload_0
    //   233: getfield 192	uuuuuu/sossso:b006E006E006E006E006En006E006En	Luuuuuu/hyhyhh;
    //   236: invokevirtual 197	uuuuuu/hyhyhh:b0070pp007000700070p007000700070	()Ljava/lang/String;
    //   239: astore_3
    //   240: getstatic 64	uuuuuu/sossso:bll006Cll006Cll006C	I
    //   243: istore_1
    //   244: iload_1
    //   245: getstatic 60	uuuuuu/sossso:bl006Clll006Cll006C	I
    //   248: iload_1
    //   249: iadd
    //   250: imul
    //   251: getstatic 62	uuuuuu/sossso:b006C006Clll006Cll006C	I
    //   254: irem
    //   255: tableswitch	default:+17->272, 0:+67->322
    //   272: bipush 94
    //   274: putstatic 64	uuuuuu/sossso:bll006Cll006Cll006C	I
    //   277: ldc 2
    //   279: ldc -57
    //   281: sipush 132
    //   284: bipush 19
    //   286: iconst_2
    //   287: invokestatic 40	xxxxxx/uxxxxx:bbbb0062b0062b0062b0062	(Ljava/lang/String;CCC)Ljava/lang/String;
    //   290: iconst_0
    //   291: anewarray 26	java/lang/Class
    //   294: invokevirtual 44	java/lang/Class:getMethod	(Ljava/lang/String;[Ljava/lang/Class;)Ljava/lang/reflect/Method;
    //   297: astore 4
    //   299: aload 4
    //   301: aconst_null
    //   302: iconst_0
    //   303: anewarray 46	java/lang/Object
    //   306: invokevirtual 52	java/lang/reflect/Method:invoke	(Ljava/lang/Object;[Ljava/lang/Object;)Ljava/lang/Object;
    //   309: astore 4
    //   311: aload 4
    //   313: checkcast 54	java/lang/Integer
    //   316: invokevirtual 58	java/lang/Integer:intValue	()I
    //   319: putstatic 76	uuuuuu/sossso:b006Cl006Cll006Cll006C	I
    //   322: aload_0
    //   323: getfield 91	uuuuuu/sossso:b006Cllll006Cll006C	Lcom/db/pwcc/dbmobile/secure/SecurityUtils;
    //   326: astore 4
    //   328: ldc 88
    //   330: ldc -55
    //   332: bipush 56
    //   334: iconst_4
    //   335: invokestatic 70	xxxxxx/uxxxxx:bb00620062bb0062b0062b0062	(Ljava/lang/String;CC)Ljava/lang/String;
    //   338: iconst_1
    //   339: anewarray 26	java/lang/Class
    //   342: dup
    //   343: iconst_0
    //   344: ldc -92
    //   346: aastore
    //   347: invokevirtual 44	java/lang/Class:getMethod	(Ljava/lang/String;[Ljava/lang/Class;)Ljava/lang/reflect/Method;
    //   350: astore 5
    //   352: aload 5
    //   354: aload 4
    //   356: iconst_1
    //   357: anewarray 46	java/lang/Object
    //   360: dup
    //   361: iconst_0
    //   362: aload_3
    //   363: aastore
    //   364: invokevirtual 52	java/lang/reflect/Method:invoke	(Ljava/lang/Object;[Ljava/lang/Object;)Ljava/lang/Object;
    //   367: astore_3
    //   368: aload_3
    //   369: checkcast 164	java/lang/String
    //   372: astore_3
    //   373: getstatic 64	uuuuuu/sossso:bll006Cll006Cll006C	I
    //   376: istore_1
    //   377: iload_1
    //   378: getstatic 60	uuuuuu/sossso:bl006Clll006Cll006C	I
    //   381: iload_1
    //   382: iadd
    //   383: imul
    //   384: getstatic 62	uuuuuu/sossso:b006C006Clll006Cll006C	I
    //   387: irem
    //   388: tableswitch	default:+20->408, 0:+108->496
    //   408: ldc 2
    //   410: ldc -53
    //   412: bipush 54
    //   414: iconst_2
    //   415: invokestatic 70	xxxxxx/uxxxxx:bb00620062bb0062b0062b0062	(Ljava/lang/String;CC)Ljava/lang/String;
    //   418: iconst_0
    //   419: anewarray 26	java/lang/Class
    //   422: invokevirtual 44	java/lang/Class:getMethod	(Ljava/lang/String;[Ljava/lang/Class;)Ljava/lang/reflect/Method;
    //   425: astore 4
    //   427: aload 4
    //   429: aconst_null
    //   430: iconst_0
    //   431: anewarray 46	java/lang/Object
    //   434: invokevirtual 52	java/lang/reflect/Method:invoke	(Ljava/lang/Object;[Ljava/lang/Object;)Ljava/lang/Object;
    //   437: astore 4
    //   439: aload 4
    //   441: checkcast 54	java/lang/Integer
    //   444: invokevirtual 58	java/lang/Integer:intValue	()I
    //   447: putstatic 64	uuuuuu/sossso:bll006Cll006Cll006C	I
    //   450: ldc 2
    //   452: ldc -51
    //   454: sipush 153
    //   457: sipush 246
    //   460: iconst_3
    //   461: invokestatic 40	xxxxxx/uxxxxx:bbbb0062b0062b0062b0062	(Ljava/lang/String;CCC)Ljava/lang/String;
    //   464: iconst_0
    //   465: anewarray 26	java/lang/Class
    //   468: invokevirtual 44	java/lang/Class:getMethod	(Ljava/lang/String;[Ljava/lang/Class;)Ljava/lang/reflect/Method;
    //   471: astore 4
    //   473: aload 4
    //   475: aconst_null
    //   476: iconst_0
    //   477: anewarray 46	java/lang/Object
    //   480: invokevirtual 52	java/lang/reflect/Method:invoke	(Ljava/lang/Object;[Ljava/lang/Object;)Ljava/lang/Object;
    //   483: astore 4
    //   485: aload 4
    //   487: checkcast 54	java/lang/Integer
    //   490: invokevirtual 58	java/lang/Integer:intValue	()I
    //   493: putstatic 76	uuuuuu/sossso:b006Cl006Cll006Cll006C	I
    //   496: getstatic 64	uuuuuu/sossso:bll006Cll006Cll006C	I
    //   499: istore_1
    //   500: iload_1
    //   501: getstatic 60	uuuuuu/sossso:bl006Clll006Cll006C	I
    //   504: iload_1
    //   505: iadd
    //   506: imul
    //   507: getstatic 62	uuuuuu/sossso:b006C006Clll006Cll006C	I
    //   510: irem
    //   511: tableswitch	default:+17->528, 0:+27->538
    //   528: bipush 99
    //   530: putstatic 64	uuuuuu/sossso:bll006Cll006Cll006C	I
    //   533: bipush 8
    //   535: putstatic 76	uuuuuu/sossso:b006Cl006Cll006Cll006C	I
    //   538: aload_3
    //   539: ifnull +49 -> 588
    //   542: aload_0
    //   543: getfield 91	uuuuuu/sossso:b006Cllll006Cll006C	Lcom/db/pwcc/dbmobile/secure/SecurityUtils;
    //   546: astore 4
    //   548: ldc 88
    //   550: ldc -49
    //   552: bipush 87
    //   554: iconst_5
    //   555: invokestatic 70	xxxxxx/uxxxxx:bb00620062bb0062b0062b0062	(Ljava/lang/String;CC)Ljava/lang/String;
    //   558: iconst_1
    //   559: anewarray 26	java/lang/Class
    //   562: dup
    //   563: iconst_0
    //   564: ldc -92
    //   566: aastore
    //   567: invokevirtual 44	java/lang/Class:getMethod	(Ljava/lang/String;[Ljava/lang/Class;)Ljava/lang/reflect/Method;
    //   570: astore 5
    //   572: aload 5
    //   574: aload 4
    //   576: iconst_1
    //   577: anewarray 46	java/lang/Object
    //   580: dup
    //   581: iconst_0
    //   582: aload_3
    //   583: aastore
    //   584: invokevirtual 52	java/lang/reflect/Method:invoke	(Ljava/lang/Object;[Ljava/lang/Object;)Ljava/lang/Object;
    //   587: pop
    //   588: return
    //   589: astore_3
    //   590: aload_3
    //   591: invokevirtual 82	java/lang/reflect/InvocationTargetException:getCause	()Ljava/lang/Throwable;
    //   594: athrow
    //   595: astore_3
    //   596: aload_3
    //   597: invokevirtual 82	java/lang/reflect/InvocationTargetException:getCause	()Ljava/lang/Throwable;
    //   600: athrow
    //   601: astore_3
    //   602: aload_3
    //   603: invokevirtual 82	java/lang/reflect/InvocationTargetException:getCause	()Ljava/lang/Throwable;
    //   606: athrow
    //   607: astore_3
    //   608: aload_3
    //   609: invokevirtual 82	java/lang/reflect/InvocationTargetException:getCause	()Ljava/lang/Throwable;
    //   612: athrow
    //   613: astore_3
    //   614: aload_3
    //   615: invokevirtual 82	java/lang/reflect/InvocationTargetException:getCause	()Ljava/lang/Throwable;
    //   618: athrow
    //   619: astore_3
    //   620: aload_3
    //   621: invokevirtual 82	java/lang/reflect/InvocationTargetException:getCause	()Ljava/lang/Throwable;
    //   624: athrow
    //   625: astore_3
    //   626: aload_3
    //   627: invokevirtual 82	java/lang/reflect/InvocationTargetException:getCause	()Ljava/lang/Throwable;
    //   630: athrow
    //   631: astore_3
    //   632: aload_3
    //   633: invokevirtual 82	java/lang/reflect/InvocationTargetException:getCause	()Ljava/lang/Throwable;
    //   636: athrow
    //   637: astore_3
    //   638: aload_3
    //   639: invokevirtual 82	java/lang/reflect/InvocationTargetException:getCause	()Ljava/lang/Throwable;
    //   642: athrow
    // Local variable table:
    //   start	length	slot	name	signature
    //   0	643	0	this	sossso
    //   120	387	1	i	int
    //   124	35	2	j	int
    //   3	580	3	localObject1	Object
    //   589	2	3	localInvocationTargetException1	java.lang.reflect.InvocationTargetException
    //   595	2	3	localInvocationTargetException2	java.lang.reflect.InvocationTargetException
    //   601	2	3	localInvocationTargetException3	java.lang.reflect.InvocationTargetException
    //   607	2	3	localInvocationTargetException4	java.lang.reflect.InvocationTargetException
    //   613	2	3	localInvocationTargetException5	java.lang.reflect.InvocationTargetException
    //   619	2	3	localInvocationTargetException6	java.lang.reflect.InvocationTargetException
    //   625	2	3	localInvocationTargetException7	java.lang.reflect.InvocationTargetException
    //   631	2	3	localInvocationTargetException8	java.lang.reflect.InvocationTargetException
    //   637	2	3	localInvocationTargetException9	java.lang.reflect.InvocationTargetException
    //   41	534	4	localObject2	Object
    //   350	223	5	localMethod	java.lang.reflect.Method
    // Exception table:
    //   from	to	target	type
    //   43	75	589	java/lang/reflect/InvocationTargetException
    //   103	113	595	java/lang/reflect/InvocationTargetException
    //   146	156	601	java/lang/reflect/InvocationTargetException
    //   572	588	607	java/lang/reflect/InvocationTargetException
    //   352	368	613	java/lang/reflect/InvocationTargetException
    //   299	311	619	java/lang/reflect/InvocationTargetException
    //   207	217	625	java/lang/reflect/InvocationTargetException
    //   427	439	631	java/lang/reflect/InvocationTargetException
    //   473	485	637	java/lang/reflect/InvocationTargetException
  }
  
  /* Error */
  public void bii0069i0069ii0069ii(ososso.oossso paramOossso)
  {
    // Byte code:
    //   0: getstatic 64	uuuuuu/sossso:bll006Cll006Cll006C	I
    //   3: istore_2
    //   4: getstatic 60	uuuuuu/sossso:bl006Clll006Cll006C	I
    //   7: istore_3
    //   8: getstatic 64	uuuuuu/sossso:bll006Cll006Cll006C	I
    //   11: istore 4
    //   13: getstatic 62	uuuuuu/sossso:b006C006Clll006Cll006C	I
    //   16: istore 5
    //   18: getstatic 76	uuuuuu/sossso:b006Cl006Cll006Cll006C	I
    //   21: istore 6
    //   23: getstatic 64	uuuuuu/sossso:bll006Cll006Cll006C	I
    //   26: istore 7
    //   28: iload 7
    //   30: getstatic 60	uuuuuu/sossso:bl006Clll006Cll006C	I
    //   33: iload 7
    //   35: iadd
    //   36: imul
    //   37: getstatic 62	uuuuuu/sossso:b006C006Clll006Cll006C	I
    //   40: irem
    //   41: tableswitch	default:+19->60, 0:+66->107
    //   60: ldc 2
    //   62: ldc -45
    //   64: bipush 52
    //   66: iconst_5
    //   67: invokestatic 70	xxxxxx/uxxxxx:bb00620062bb0062b0062b0062	(Ljava/lang/String;CC)Ljava/lang/String;
    //   70: iconst_0
    //   71: anewarray 26	java/lang/Class
    //   74: invokevirtual 44	java/lang/Class:getMethod	(Ljava/lang/String;[Ljava/lang/Class;)Ljava/lang/reflect/Method;
    //   77: astore 8
    //   79: aload 8
    //   81: aconst_null
    //   82: iconst_0
    //   83: anewarray 46	java/lang/Object
    //   86: invokevirtual 52	java/lang/reflect/Method:invoke	(Ljava/lang/Object;[Ljava/lang/Object;)Ljava/lang/Object;
    //   89: astore 8
    //   91: aload 8
    //   93: checkcast 54	java/lang/Integer
    //   96: invokevirtual 58	java/lang/Integer:intValue	()I
    //   99: putstatic 64	uuuuuu/sossso:bll006Cll006Cll006C	I
    //   102: bipush 30
    //   104: putstatic 76	uuuuuu/sossso:b006Cl006Cll006Cll006C	I
    //   107: iload_2
    //   108: iload_3
    //   109: iadd
    //   110: iload 4
    //   112: imul
    //   113: iload 5
    //   115: irem
    //   116: iload 6
    //   118: if_icmpeq +199 -> 317
    //   121: getstatic 64	uuuuuu/sossso:bll006Cll006Cll006C	I
    //   124: getstatic 60	uuuuuu/sossso:bl006Clll006Cll006C	I
    //   127: iadd
    //   128: getstatic 64	uuuuuu/sossso:bll006Cll006Cll006C	I
    //   131: imul
    //   132: getstatic 62	uuuuuu/sossso:b006C006Clll006Cll006C	I
    //   135: irem
    //   136: getstatic 76	uuuuuu/sossso:b006Cl006Cll006Cll006C	I
    //   139: if_icmpeq +13 -> 152
    //   142: bipush 75
    //   144: putstatic 64	uuuuuu/sossso:bll006Cll006Cll006C	I
    //   147: bipush 56
    //   149: putstatic 76	uuuuuu/sossso:b006Cl006Cll006Cll006C	I
    //   152: ldc 2
    //   154: ldc -43
    //   156: bipush 57
    //   158: iconst_3
    //   159: invokestatic 70	xxxxxx/uxxxxx:bb00620062bb0062b0062b0062	(Ljava/lang/String;CC)Ljava/lang/String;
    //   162: iconst_0
    //   163: anewarray 26	java/lang/Class
    //   166: invokevirtual 44	java/lang/Class:getMethod	(Ljava/lang/String;[Ljava/lang/Class;)Ljava/lang/reflect/Method;
    //   169: astore 8
    //   171: aload 8
    //   173: aconst_null
    //   174: iconst_0
    //   175: anewarray 46	java/lang/Object
    //   178: invokevirtual 52	java/lang/reflect/Method:invoke	(Ljava/lang/Object;[Ljava/lang/Object;)Ljava/lang/Object;
    //   181: astore 8
    //   183: aload 8
    //   185: checkcast 54	java/lang/Integer
    //   188: invokevirtual 58	java/lang/Integer:intValue	()I
    //   191: istore_2
    //   192: iload_2
    //   193: getstatic 60	uuuuuu/sossso:bl006Clll006Cll006C	I
    //   196: iload_2
    //   197: iadd
    //   198: imul
    //   199: getstatic 62	uuuuuu/sossso:b006C006Clll006Cll006C	I
    //   202: irem
    //   203: tableswitch	default:+17->220, 0:+66->269
    //   220: ldc 2
    //   222: ldc -41
    //   224: bipush 118
    //   226: bipush 6
    //   228: iconst_0
    //   229: invokestatic 40	xxxxxx/uxxxxx:bbbb0062b0062b0062b0062	(Ljava/lang/String;CCC)Ljava/lang/String;
    //   232: iconst_0
    //   233: anewarray 26	java/lang/Class
    //   236: invokevirtual 44	java/lang/Class:getMethod	(Ljava/lang/String;[Ljava/lang/Class;)Ljava/lang/reflect/Method;
    //   239: astore 8
    //   241: aload 8
    //   243: aconst_null
    //   244: iconst_0
    //   245: anewarray 46	java/lang/Object
    //   248: invokevirtual 52	java/lang/reflect/Method:invoke	(Ljava/lang/Object;[Ljava/lang/Object;)Ljava/lang/Object;
    //   251: astore 8
    //   253: aload 8
    //   255: checkcast 54	java/lang/Integer
    //   258: invokevirtual 58	java/lang/Integer:intValue	()I
    //   261: putstatic 64	uuuuuu/sossso:bll006Cll006Cll006C	I
    //   264: bipush 74
    //   266: putstatic 76	uuuuuu/sossso:b006Cl006Cll006Cll006C	I
    //   269: ldc 2
    //   271: ldc -39
    //   273: sipush 249
    //   276: iconst_0
    //   277: invokestatic 70	xxxxxx/uxxxxx:bb00620062bb0062b0062b0062	(Ljava/lang/String;CC)Ljava/lang/String;
    //   280: iconst_0
    //   281: anewarray 26	java/lang/Class
    //   284: invokevirtual 44	java/lang/Class:getMethod	(Ljava/lang/String;[Ljava/lang/Class;)Ljava/lang/reflect/Method;
    //   287: astore 8
    //   289: aload 8
    //   291: aconst_null
    //   292: iconst_0
    //   293: anewarray 46	java/lang/Object
    //   296: invokevirtual 52	java/lang/reflect/Method:invoke	(Ljava/lang/Object;[Ljava/lang/Object;)Ljava/lang/Object;
    //   299: astore 8
    //   301: aload 8
    //   303: checkcast 54	java/lang/Integer
    //   306: invokevirtual 58	java/lang/Integer:intValue	()I
    //   309: putstatic 64	uuuuuu/sossso:bll006Cll006Cll006C	I
    //   312: bipush 59
    //   314: putstatic 76	uuuuuu/sossso:b006Cl006Cll006Cll006C	I
    //   317: aload_0
    //   318: aload_1
    //   319: invokespecial 219	uuuuuu/ssssst:ba0061a0061a0061a0061aa	(Luuuuuu/ttssst$tsssst;)V
    //   322: ldc 2
    //   324: ldc -35
    //   326: bipush 17
    //   328: iconst_1
    //   329: invokestatic 70	xxxxxx/uxxxxx:bb00620062bb0062b0062b0062	(Ljava/lang/String;CC)Ljava/lang/String;
    //   332: iconst_0
    //   333: anewarray 26	java/lang/Class
    //   336: invokevirtual 44	java/lang/Class:getMethod	(Ljava/lang/String;[Ljava/lang/Class;)Ljava/lang/reflect/Method;
    //   339: astore_1
    //   340: aload_1
    //   341: aload_0
    //   342: iconst_0
    //   343: anewarray 46	java/lang/Object
    //   346: invokevirtual 52	java/lang/reflect/Method:invoke	(Ljava/lang/Object;[Ljava/lang/Object;)Ljava/lang/Object;
    //   349: pop
    //   350: return
    //   351: astore_1
    //   352: aload_1
    //   353: invokevirtual 82	java/lang/reflect/InvocationTargetException:getCause	()Ljava/lang/Throwable;
    //   356: athrow
    //   357: astore_1
    //   358: aload_1
    //   359: invokevirtual 82	java/lang/reflect/InvocationTargetException:getCause	()Ljava/lang/Throwable;
    //   362: athrow
    //   363: astore_1
    //   364: aload_1
    //   365: invokevirtual 82	java/lang/reflect/InvocationTargetException:getCause	()Ljava/lang/Throwable;
    //   368: athrow
    //   369: astore_1
    //   370: aload_1
    //   371: invokevirtual 82	java/lang/reflect/InvocationTargetException:getCause	()Ljava/lang/Throwable;
    //   374: athrow
    //   375: astore_1
    //   376: aload_1
    //   377: invokevirtual 82	java/lang/reflect/InvocationTargetException:getCause	()Ljava/lang/Throwable;
    //   380: athrow
    // Local variable table:
    //   start	length	slot	name	signature
    //   0	381	0	this	sossso
    //   0	381	1	paramOossso	ososso.oossso
    //   3	196	2	i	int
    //   7	103	3	j	int
    //   11	102	4	k	int
    //   16	100	5	m	int
    //   21	98	6	n	int
    //   26	11	7	i1	int
    //   77	225	8	localObject	Object
    // Exception table:
    //   from	to	target	type
    //   171	183	351	java/lang/reflect/InvocationTargetException
    //   340	350	357	java/lang/reflect/InvocationTargetException
    //   79	91	363	java/lang/reflect/InvocationTargetException
    //   241	253	369	java/lang/reflect/InvocationTargetException
    //   289	301	375	java/lang/reflect/InvocationTargetException
  }
}
