package uuuuuu;

import com.db.pwcc.dbmobile.model.error.DbError;
import com.db.pwcc.dbmobile.model.error.DbErrorsPayload;
import com.db.pwcc.dbmobile.postbox.model.PostboxMessages;
import java.util.Iterator;
import java.util.List;

public class ssooss
  extends mffmmm<PostboxMessages>
  implements ossoos
{
  public static int b006C006Cl006Cll006Cl006C = 1;
  public static int b006Cll006Cll006Cl006C = 48;
  public static int bl006Cl006Cll006Cl006C = 0;
  public static int bll006C006Cll006Cl006C = 2;
  
  public ssooss() {}
  
  public static int b0069ii006900690069i0069ii()
  {
    return 32;
  }
  
  /* Error */
  public void bi0069006900690069ii0069ii(@android.support.annotation.NonNull ossoos.sssoos paramSssoos, @android.support.annotation.NonNull String paramString)
  {
    // Byte code:
    //   0: ldc 33
    //   2: ldc 35
    //   4: sipush 161
    //   7: bipush 25
    //   9: iconst_3
    //   10: invokestatic 41	xxxxxx/uxxxxx:bbbb0062b0062b0062b0062	(Ljava/lang/String;CCC)Ljava/lang/String;
    //   13: iconst_3
    //   14: anewarray 43	java/lang/Class
    //   17: dup
    //   18: iconst_0
    //   19: ldc 45
    //   21: aastore
    //   22: dup
    //   23: iconst_1
    //   24: getstatic 51	java/lang/Character:TYPE	Ljava/lang/Class;
    //   27: aastore
    //   28: dup
    //   29: iconst_2
    //   30: getstatic 51	java/lang/Character:TYPE	Ljava/lang/Class;
    //   33: aastore
    //   34: invokevirtual 55	java/lang/Class:getMethod	(Ljava/lang/String;[Ljava/lang/Class;)Ljava/lang/reflect/Method;
    //   37: astore 4
    //   39: aload 4
    //   41: aconst_null
    //   42: iconst_3
    //   43: anewarray 57	java/lang/Object
    //   46: dup
    //   47: iconst_0
    //   48: ldc 59
    //   50: aastore
    //   51: dup
    //   52: iconst_1
    //   53: bipush 69
    //   55: invokestatic 63	java/lang/Character:valueOf	(C)Ljava/lang/Character;
    //   58: aastore
    //   59: dup
    //   60: iconst_2
    //   61: iconst_5
    //   62: invokestatic 63	java/lang/Character:valueOf	(C)Ljava/lang/Character;
    //   65: aastore
    //   66: invokevirtual 69	java/lang/reflect/Method:invoke	(Ljava/lang/Object;[Ljava/lang/Object;)Ljava/lang/Object;
    //   69: astore 4
    //   71: aload_2
    //   72: aload 4
    //   74: checkcast 45	java/lang/String
    //   77: invokestatic 75	java/util/Objects:requireNonNull	(Ljava/lang/Object;Ljava/lang/String;)Ljava/lang/Object;
    //   80: pop
    //   81: ldc 33
    //   83: ldc 77
    //   85: bipush 18
    //   87: bipush 69
    //   89: iconst_3
    //   90: invokestatic 41	xxxxxx/uxxxxx:bbbb0062b0062b0062b0062	(Ljava/lang/String;CCC)Ljava/lang/String;
    //   93: iconst_3
    //   94: anewarray 43	java/lang/Class
    //   97: dup
    //   98: iconst_0
    //   99: ldc 45
    //   101: aastore
    //   102: dup
    //   103: iconst_1
    //   104: getstatic 51	java/lang/Character:TYPE	Ljava/lang/Class;
    //   107: aastore
    //   108: dup
    //   109: iconst_2
    //   110: getstatic 51	java/lang/Character:TYPE	Ljava/lang/Class;
    //   113: aastore
    //   114: invokevirtual 55	java/lang/Class:getMethod	(Ljava/lang/String;[Ljava/lang/Class;)Ljava/lang/reflect/Method;
    //   117: astore 4
    //   119: aload 4
    //   121: aconst_null
    //   122: iconst_3
    //   123: anewarray 57	java/lang/Object
    //   126: dup
    //   127: iconst_0
    //   128: ldc 79
    //   130: aastore
    //   131: dup
    //   132: iconst_1
    //   133: bipush 16
    //   135: invokestatic 63	java/lang/Character:valueOf	(C)Ljava/lang/Character;
    //   138: aastore
    //   139: dup
    //   140: iconst_2
    //   141: iconst_5
    //   142: invokestatic 63	java/lang/Character:valueOf	(C)Ljava/lang/Character;
    //   145: aastore
    //   146: invokevirtual 69	java/lang/reflect/Method:invoke	(Ljava/lang/Object;[Ljava/lang/Object;)Ljava/lang/Object;
    //   149: astore 4
    //   151: aload 4
    //   153: checkcast 45	java/lang/String
    //   156: iconst_1
    //   157: invokestatic 85	java/lang/Boolean:toString	(Z)Ljava/lang/String;
    //   160: invokestatic 91	java/util/Collections:singletonMap	(Ljava/lang/Object;Ljava/lang/Object;)Ljava/util/Map;
    //   163: astore 4
    //   165: aload_0
    //   166: getfield 95	uuuuuu/ssooss:bkk006Bk006B006Bkk006B	Luuuuuu/yyyyhh;
    //   169: getstatic 101	uuuuuu/lolllo:bq00710071qqqqq0071	Luuuuuu/lolllo;
    //   172: aload 4
    //   174: aload_2
    //   175: invokestatic 105	java/util/Collections:singletonList	(Ljava/lang/Object;)Ljava/util/List;
    //   178: invokevirtual 111	uuuuuu/yyyyhh:bp007000700070p00700070007000700070	(Luuuuuu/lolllo;Ljava/util/Map;Ljava/util/List;)Ljava/lang/String;
    //   181: astore_2
    //   182: getstatic 113	uuuuuu/ssooss:b006Cll006Cll006Cl006C	I
    //   185: istore_3
    //   186: iload_3
    //   187: getstatic 115	uuuuuu/ssooss:b006C006Cl006Cll006Cl006C	I
    //   190: iload_3
    //   191: iadd
    //   192: imul
    //   193: getstatic 117	uuuuuu/ssooss:bll006C006Cll006Cl006C	I
    //   196: irem
    //   197: tableswitch	default:+19->216, 0:+31->228
    //   216: invokestatic 119	uuuuuu/ssooss:b0069ii006900690069i0069ii	()I
    //   219: putstatic 113	uuuuuu/ssooss:b006Cll006Cll006Cl006C	I
    //   222: invokestatic 119	uuuuuu/ssooss:b0069ii006900690069i0069ii	()I
    //   225: putstatic 121	uuuuuu/ssooss:bl006Cl006Cll006Cl006C	I
    //   228: aload_0
    //   229: new 123	uuuuuu/olllol
    //   232: dup
    //   233: aload_2
    //   234: new 9	uuuuuu/ssooss$oososs
    //   237: dup
    //   238: aload_1
    //   239: invokespecial 126	uuuuuu/ssooss$oososs:<init>	(Luuuuuu/ossoos$sssoos;)V
    //   242: invokespecial 129	uuuuuu/olllol:<init>	(Ljava/lang/String;Luuuuuu/loolol;)V
    //   245: putfield 133	uuuuuu/ssooss:b006B006Bkk006B006Bkk006B	Luuuuuu/ololol;
    //   248: aload_0
    //   249: getfield 133	uuuuuu/ssooss:b006B006Bkk006B006Bkk006B	Luuuuuu/ololol;
    //   252: getstatic 101	uuuuuu/lolllo:bq00710071qqqqq0071	Luuuuuu/lolllo;
    //   255: invokevirtual 137	uuuuuu/lolllo:name	()Ljava/lang/String;
    //   258: invokevirtual 143	uuuuuu/ololol:b0070p0070007000700070pp00700070	(Ljava/lang/Object;)V
    //   261: getstatic 113	uuuuuu/ssooss:b006Cll006Cll006Cl006C	I
    //   264: getstatic 115	uuuuuu/ssooss:b006C006Cl006Cll006Cl006C	I
    //   267: iadd
    //   268: getstatic 113	uuuuuu/ssooss:b006Cll006Cll006Cl006C	I
    //   271: imul
    //   272: getstatic 117	uuuuuu/ssooss:bll006C006Cll006Cl006C	I
    //   275: irem
    //   276: getstatic 121	uuuuuu/ssooss:bl006Cl006Cll006Cl006C	I
    //   279: if_icmpeq +14 -> 293
    //   282: invokestatic 119	uuuuuu/ssooss:b0069ii006900690069i0069ii	()I
    //   285: putstatic 113	uuuuuu/ssooss:b006Cll006Cll006Cl006C	I
    //   288: bipush 56
    //   290: putstatic 121	uuuuuu/ssooss:bl006Cl006Cll006Cl006C	I
    //   293: aload_0
    //   294: invokevirtual 146	uuuuuu/ssooss:bp0070pp00700070007000700070p	()V
    //   297: return
    //   298: astore_1
    //   299: aload_1
    //   300: invokevirtual 150	java/lang/reflect/InvocationTargetException:getCause	()Ljava/lang/Throwable;
    //   303: athrow
    //   304: astore_1
    //   305: aload_1
    //   306: invokevirtual 150	java/lang/reflect/InvocationTargetException:getCause	()Ljava/lang/Throwable;
    //   309: athrow
    // Local variable table:
    //   start	length	slot	name	signature
    //   0	310	0	this	ssooss
    //   0	310	1	paramSssoos	ossoos.sssoos
    //   0	310	2	paramString	String
    //   185	8	3	i	int
    //   37	136	4	localObject	Object
    // Exception table:
    //   from	to	target	type
    //   39	71	298	java/lang/reflect/InvocationTargetException
    //   119	151	304	java/lang/reflect/InvocationTargetException
  }
  
  public ololol<PostboxMessages> bi0069i006900690069i0069ii()
  {
    ololol localOlolol = this.b006B006Bkk006B006Bkk006B;
    int i = b006Cll006Cll006Cl006C;
    int j = b006C006Cl006Cll006Cl006C;
    if ((b0069ii006900690069i0069ii() + b006C006Cl006Cll006Cl006C) * b0069ii006900690069i0069ii() % bll006C006Cll006Cl006C != bl006Cl006Cll006Cl006C)
    {
      b006Cll006Cll006Cl006C = b0069ii006900690069i0069ii();
      bl006Cl006Cll006Cl006C = b0069ii006900690069i0069ii();
    }
    switch (i * (j + i) % bll006C006Cll006Cl006C)
    {
    default: 
      b006Cll006Cll006Cl006C = b0069ii006900690069i0069ii();
      bl006Cl006Cll006Cl006C = b0069ii006900690069i0069ii();
    }
    return localOlolol;
  }
  
  public static class oososs
    extends loolol<PostboxMessages>
  {
    public static int b006C006C006C006Cll006Cl006C = 0;
    public static int b006Clll006Cl006Cl006C = 2;
    public static int bl006C006C006Cll006Cl006C = 34;
    public static int bllll006Cl006Cl006C = 1;
    private final ossoos.sssoos b006Cl006C006Cll006Cl006C;
    
    public oososs(ossoos.sssoos paramSssoos)
    {
      this.b006Cl006C006Cll006Cl006C = paramSssoos;
    }
    
    public static int b006900690069i00690069i0069ii()
    {
      return 65;
    }
    
    public static int bi00690069i00690069i0069ii()
    {
      return 2;
    }
    
    public static int biii006900690069i0069ii()
    {
      return 0;
    }
    
    public void b006100610061aaa006100610061a(DbErrorsPayload paramDbErrorsPayload)
    {
      paramDbErrorsPayload = paramDbErrorsPayload.getErrors().iterator();
      for (;;)
      {
        boolean bool = paramDbErrorsPayload.hasNext();
        if ((bl006C006C006Cll006Cl006C + bllll006Cl006Cl006C) * bl006C006C006Cll006Cl006C % b006Clll006Cl006Cl006C != b006C006C006C006Cll006Cl006C)
        {
          bl006C006C006Cll006Cl006C = b006900690069i00690069i0069ii();
          b006C006C006C006Cll006Cl006C = 36;
        }
        if (!bool) {
          break;
        }
        DbError localDbError = (DbError)paramDbErrorsPayload.next();
        if ((bl006C006C006Cll006Cl006C + bllll006Cl006Cl006C) * bl006C006C006Cll006Cl006C % b006Clll006Cl006Cl006C != b006C006C006C006Cll006Cl006C)
        {
          bl006C006C006Cll006Cl006C = 29;
          b006C006C006C006Cll006Cl006C = 29;
        }
        this.b006Cl006C006Cll006Cl006C.ba00610061a0061aaa0061a(localDbError);
      }
    }
    
    public void baaa0061aa006100610061a(ooolol<PostboxMessages> paramOoolol)
    {
      this.b006Cl006C006Cll006Cl006C.b006100610061a0061aaa0061a((PostboxMessages)paramOoolol.bp007000700070pppp00700070());
      if ((b006900690069i00690069i0069ii() + bllll006Cl006Cl006C) * b006900690069i00690069i0069ii() % bi00690069i00690069i0069ii() != biii006900690069i0069ii())
      {
        bl006C006C006Cll006Cl006C = 39;
        b006C006C006C006Cll006Cl006C = 40;
      }
      if ((b006900690069i00690069i0069ii() + bllll006Cl006Cl006C) * b006900690069i00690069i0069ii() % b006Clll006Cl006Cl006C != b006C006C006C006Cll006Cl006C)
      {
        bl006C006C006Cll006Cl006C = 8;
        b006C006C006C006Cll006Cl006C = b006900690069i00690069i0069ii();
      }
    }
  }
}
