package uuuuuu;

public abstract class ssssst<V extends ttssst.tsssst>
  implements ttssst.stssst<V>
{
  public static int b006E006Ennn006E006E006En = 1;
  public static int b006Ennnn006E006E006En = 52;
  public static int bn006Ennn006E006E006En = 0;
  public static int bnn006Enn006E006E006En = 2;
  public final hyhyhh b006E006E006E006E006En006E006En;
  public ggyggy b006En006E006E006En006E006En;
  public yyyyhh bn006E006E006E006En006E006En;
  public V bnnnnn006E006E006En;
  
  public ssssst()
  {
    pppqpq localPppqpq = pqqppq.b006B006B006Bkkk006Bkkk();
    this.b006En006E006E006En006E006En = localPppqpq.bpppp00700070pppp();
    this.bn006E006E006E006En006E006En = localPppqpq.b0070ppp00700070pppp();
    this.b006E006E006E006E006En006E006En = localPppqpq.b00700070pp00700070pppp();
  }
  
  public static int b006B006B006B006Bkk006Bk006Bk()
  {
    return 2;
  }
  
  public static int b006Bkkk006Bk006Bk006Bk()
  {
    return 1;
  }
  
  public static int bk006Bkk006Bk006Bk006Bk()
  {
    return 79;
  }
  
  public static int bkkkk006Bk006Bk006Bk()
  {
    return 0;
  }
  
  /* Error */
  public V b006B006Bkk006Bk006Bk006Bk()
  {
    // Byte code:
    //   0: getstatic 67	uuuuuu/ssssst:b006Ennnn006E006E006En	I
    //   3: istore_1
    //   4: getstatic 69	uuuuuu/ssssst:b006E006Ennn006E006E006En	I
    //   7: istore_2
    //   8: ldc 2
    //   10: ldc 71
    //   12: sipush 200
    //   15: iconst_5
    //   16: invokestatic 77	xxxxxx/uxxxxx:bb00620062bb0062b0062b0062	(Ljava/lang/String;CC)Ljava/lang/String;
    //   19: iconst_0
    //   20: anewarray 79	java/lang/Class
    //   23: invokevirtual 83	java/lang/Class:getMethod	(Ljava/lang/String;[Ljava/lang/Class;)Ljava/lang/reflect/Method;
    //   26: astore_3
    //   27: aload_3
    //   28: aconst_null
    //   29: iconst_0
    //   30: anewarray 5	java/lang/Object
    //   33: invokevirtual 89	java/lang/reflect/Method:invoke	(Ljava/lang/Object;[Ljava/lang/Object;)Ljava/lang/Object;
    //   36: astore_3
    //   37: iload_2
    //   38: iload_1
    //   39: iadd
    //   40: iload_1
    //   41: imul
    //   42: aload_3
    //   43: checkcast 91	java/lang/Integer
    //   46: invokevirtual 94	java/lang/Integer:intValue	()I
    //   49: irem
    //   50: tableswitch	default:+18->68, 0:+27->77
    //   68: iconst_1
    //   69: putstatic 67	uuuuuu/ssssst:b006Ennnn006E006E006En	I
    //   72: bipush 96
    //   74: putstatic 96	uuuuuu/ssssst:bn006Ennn006E006E006En	I
    //   77: aload_0
    //   78: getfield 98	uuuuuu/ssssst:bnnnnn006E006E006En	Luuuuuu/ttssst$tsssst;
    //   81: astore_3
    //   82: getstatic 67	uuuuuu/ssssst:b006Ennnn006E006E006En	I
    //   85: istore_1
    //   86: ldc 2
    //   88: ldc 100
    //   90: sipush 195
    //   93: iconst_4
    //   94: invokestatic 77	xxxxxx/uxxxxx:bb00620062bb0062b0062b0062	(Ljava/lang/String;CC)Ljava/lang/String;
    //   97: iconst_0
    //   98: anewarray 79	java/lang/Class
    //   101: invokevirtual 83	java/lang/Class:getMethod	(Ljava/lang/String;[Ljava/lang/Class;)Ljava/lang/reflect/Method;
    //   104: astore 4
    //   106: aload 4
    //   108: aconst_null
    //   109: iconst_0
    //   110: anewarray 5	java/lang/Object
    //   113: invokevirtual 89	java/lang/reflect/Method:invoke	(Ljava/lang/Object;[Ljava/lang/Object;)Ljava/lang/Object;
    //   116: astore 4
    //   118: aload 4
    //   120: checkcast 91	java/lang/Integer
    //   123: invokevirtual 94	java/lang/Integer:intValue	()I
    //   126: iload_1
    //   127: iadd
    //   128: iload_1
    //   129: imul
    //   130: getstatic 102	uuuuuu/ssssst:bnn006Enn006E006E006En	I
    //   133: irem
    //   134: tableswitch	default:+18->152, 0:+264->398
    //   152: getstatic 67	uuuuuu/ssssst:b006Ennnn006E006E006En	I
    //   155: istore_1
    //   156: getstatic 69	uuuuuu/ssssst:b006E006Ennn006E006E006En	I
    //   159: istore_2
    //   160: ldc 2
    //   162: ldc 104
    //   164: bipush 96
    //   166: iconst_0
    //   167: invokestatic 77	xxxxxx/uxxxxx:bb00620062bb0062b0062b0062	(Ljava/lang/String;CC)Ljava/lang/String;
    //   170: iconst_0
    //   171: anewarray 79	java/lang/Class
    //   174: invokevirtual 83	java/lang/Class:getMethod	(Ljava/lang/String;[Ljava/lang/Class;)Ljava/lang/reflect/Method;
    //   177: astore 4
    //   179: aload 4
    //   181: aconst_null
    //   182: iconst_0
    //   183: anewarray 5	java/lang/Object
    //   186: invokevirtual 89	java/lang/reflect/Method:invoke	(Ljava/lang/Object;[Ljava/lang/Object;)Ljava/lang/Object;
    //   189: astore 4
    //   191: iload_2
    //   192: iload_1
    //   193: iadd
    //   194: iload_1
    //   195: imul
    //   196: aload 4
    //   198: checkcast 91	java/lang/Integer
    //   201: invokevirtual 94	java/lang/Integer:intValue	()I
    //   204: irem
    //   205: tableswitch	default:+19->224, 0:+146->351
    //   224: bipush 78
    //   226: putstatic 67	uuuuuu/ssssst:b006Ennnn006E006E006En	I
    //   229: ldc 2
    //   231: ldc 106
    //   233: bipush 124
    //   235: iconst_5
    //   236: invokestatic 77	xxxxxx/uxxxxx:bb00620062bb0062b0062b0062	(Ljava/lang/String;CC)Ljava/lang/String;
    //   239: iconst_0
    //   240: anewarray 79	java/lang/Class
    //   243: invokevirtual 83	java/lang/Class:getMethod	(Ljava/lang/String;[Ljava/lang/Class;)Ljava/lang/reflect/Method;
    //   246: astore 4
    //   248: aload 4
    //   250: aconst_null
    //   251: iconst_0
    //   252: anewarray 5	java/lang/Object
    //   255: invokevirtual 89	java/lang/reflect/Method:invoke	(Ljava/lang/Object;[Ljava/lang/Object;)Ljava/lang/Object;
    //   258: astore 4
    //   260: aload 4
    //   262: checkcast 91	java/lang/Integer
    //   265: invokevirtual 94	java/lang/Integer:intValue	()I
    //   268: putstatic 96	uuuuuu/ssssst:bn006Ennn006E006E006En	I
    //   271: getstatic 67	uuuuuu/ssssst:b006Ennnn006E006E006En	I
    //   274: istore_1
    //   275: iload_1
    //   276: getstatic 69	uuuuuu/ssssst:b006E006Ennn006E006E006En	I
    //   279: iload_1
    //   280: iadd
    //   281: imul
    //   282: getstatic 102	uuuuuu/ssssst:bnn006Enn006E006E006En	I
    //   285: irem
    //   286: tableswitch	default:+18->304, 0:+65->351
    //   304: bipush 94
    //   306: putstatic 67	uuuuuu/ssssst:b006Ennnn006E006E006En	I
    //   309: ldc 2
    //   311: ldc 108
    //   313: bipush 15
    //   315: iconst_5
    //   316: invokestatic 77	xxxxxx/uxxxxx:bb00620062bb0062b0062b0062	(Ljava/lang/String;CC)Ljava/lang/String;
    //   319: iconst_0
    //   320: anewarray 79	java/lang/Class
    //   323: invokevirtual 83	java/lang/Class:getMethod	(Ljava/lang/String;[Ljava/lang/Class;)Ljava/lang/reflect/Method;
    //   326: astore 4
    //   328: aload 4
    //   330: aconst_null
    //   331: iconst_0
    //   332: anewarray 5	java/lang/Object
    //   335: invokevirtual 89	java/lang/reflect/Method:invoke	(Ljava/lang/Object;[Ljava/lang/Object;)Ljava/lang/Object;
    //   338: astore 4
    //   340: aload 4
    //   342: checkcast 91	java/lang/Integer
    //   345: invokevirtual 94	java/lang/Integer:intValue	()I
    //   348: putstatic 96	uuuuuu/ssssst:bn006Ennn006E006E006En	I
    //   351: bipush 66
    //   353: putstatic 67	uuuuuu/ssssst:b006Ennnn006E006E006En	I
    //   356: ldc 2
    //   358: ldc 110
    //   360: bipush 57
    //   362: iconst_2
    //   363: invokestatic 77	xxxxxx/uxxxxx:bb00620062bb0062b0062b0062	(Ljava/lang/String;CC)Ljava/lang/String;
    //   366: iconst_0
    //   367: anewarray 79	java/lang/Class
    //   370: invokevirtual 83	java/lang/Class:getMethod	(Ljava/lang/String;[Ljava/lang/Class;)Ljava/lang/reflect/Method;
    //   373: astore 4
    //   375: aload 4
    //   377: aconst_null
    //   378: iconst_0
    //   379: anewarray 5	java/lang/Object
    //   382: invokevirtual 89	java/lang/reflect/Method:invoke	(Ljava/lang/Object;[Ljava/lang/Object;)Ljava/lang/Object;
    //   385: astore 4
    //   387: aload 4
    //   389: checkcast 91	java/lang/Integer
    //   392: invokevirtual 94	java/lang/Integer:intValue	()I
    //   395: putstatic 96	uuuuuu/ssssst:bn006Ennn006E006E006En	I
    //   398: aload_3
    //   399: areturn
    //   400: astore_3
    //   401: aload_3
    //   402: invokevirtual 114	java/lang/reflect/InvocationTargetException:getCause	()Ljava/lang/Throwable;
    //   405: athrow
    //   406: astore_3
    //   407: aload_3
    //   408: invokevirtual 114	java/lang/reflect/InvocationTargetException:getCause	()Ljava/lang/Throwable;
    //   411: athrow
    //   412: astore_3
    //   413: aload_3
    //   414: invokevirtual 114	java/lang/reflect/InvocationTargetException:getCause	()Ljava/lang/Throwable;
    //   417: athrow
    //   418: astore_3
    //   419: aload_3
    //   420: invokevirtual 114	java/lang/reflect/InvocationTargetException:getCause	()Ljava/lang/Throwable;
    //   423: athrow
    //   424: astore_3
    //   425: aload_3
    //   426: invokevirtual 114	java/lang/reflect/InvocationTargetException:getCause	()Ljava/lang/Throwable;
    //   429: athrow
    //   430: astore_3
    //   431: aload_3
    //   432: invokevirtual 114	java/lang/reflect/InvocationTargetException:getCause	()Ljava/lang/Throwable;
    //   435: athrow
    // Local variable table:
    //   start	length	slot	name	signature
    //   0	436	0	this	ssssst
    //   3	279	1	i	int
    //   7	187	2	j	int
    //   26	373	3	localObject1	Object
    //   400	2	3	localInvocationTargetException1	java.lang.reflect.InvocationTargetException
    //   406	2	3	localInvocationTargetException2	java.lang.reflect.InvocationTargetException
    //   412	2	3	localInvocationTargetException3	java.lang.reflect.InvocationTargetException
    //   418	2	3	localInvocationTargetException4	java.lang.reflect.InvocationTargetException
    //   424	2	3	localInvocationTargetException5	java.lang.reflect.InvocationTargetException
    //   430	2	3	localInvocationTargetException6	java.lang.reflect.InvocationTargetException
    //   104	284	4	localObject2	Object
    // Exception table:
    //   from	to	target	type
    //   106	118	400	java/lang/reflect/InvocationTargetException
    //   27	37	406	java/lang/reflect/InvocationTargetException
    //   375	387	412	java/lang/reflect/InvocationTargetException
    //   179	191	418	java/lang/reflect/InvocationTargetException
    //   248	260	424	java/lang/reflect/InvocationTargetException
    //   328	340	430	java/lang/reflect/InvocationTargetException
  }
  
  /* Error */
  public boolean b006Bk006B006Bkk006Bk006Bk()
  {
    // Byte code:
    //   0: aload_0
    //   1: getfield 43	uuuuuu/ssssst:b006En006E006E006En006E006En	Luuuuuu/ggyggy;
    //   4: astore_2
    //   5: getstatic 67	uuuuuu/ssssst:b006Ennnn006E006E006En	I
    //   8: getstatic 69	uuuuuu/ssssst:b006E006Ennn006E006E006En	I
    //   11: iadd
    //   12: getstatic 67	uuuuuu/ssssst:b006Ennnn006E006E006En	I
    //   15: imul
    //   16: getstatic 102	uuuuuu/ssssst:bnn006Enn006E006E006En	I
    //   19: irem
    //   20: getstatic 96	uuuuuu/ssssst:bn006Ennn006E006E006En	I
    //   23: if_icmpeq +208 -> 231
    //   26: getstatic 67	uuuuuu/ssssst:b006Ennnn006E006E006En	I
    //   29: istore_1
    //   30: ldc 2
    //   32: ldc 120
    //   34: sipush 157
    //   37: iconst_2
    //   38: invokestatic 77	xxxxxx/uxxxxx:bb00620062bb0062b0062b0062	(Ljava/lang/String;CC)Ljava/lang/String;
    //   41: iconst_0
    //   42: anewarray 79	java/lang/Class
    //   45: invokevirtual 83	java/lang/Class:getMethod	(Ljava/lang/String;[Ljava/lang/Class;)Ljava/lang/reflect/Method;
    //   48: astore_3
    //   49: aload_3
    //   50: aconst_null
    //   51: iconst_0
    //   52: anewarray 5	java/lang/Object
    //   55: invokevirtual 89	java/lang/reflect/Method:invoke	(Ljava/lang/Object;[Ljava/lang/Object;)Ljava/lang/Object;
    //   58: astore_3
    //   59: aload_3
    //   60: checkcast 91	java/lang/Integer
    //   63: invokevirtual 94	java/lang/Integer:intValue	()I
    //   66: iload_1
    //   67: iadd
    //   68: getstatic 67	uuuuuu/ssssst:b006Ennnn006E006E006En	I
    //   71: imul
    //   72: getstatic 102	uuuuuu/ssssst:bnn006Enn006E006E006En	I
    //   75: irem
    //   76: getstatic 96	uuuuuu/ssssst:bn006Ennn006E006E006En	I
    //   79: if_icmpeq +77 -> 156
    //   82: getstatic 67	uuuuuu/ssssst:b006Ennnn006E006E006En	I
    //   85: getstatic 69	uuuuuu/ssssst:b006E006Ennn006E006E006En	I
    //   88: iadd
    //   89: getstatic 67	uuuuuu/ssssst:b006Ennnn006E006E006En	I
    //   92: imul
    //   93: getstatic 102	uuuuuu/ssssst:bnn006Enn006E006E006En	I
    //   96: irem
    //   97: getstatic 96	uuuuuu/ssssst:bn006Ennn006E006E006En	I
    //   100: if_icmpeq +13 -> 113
    //   103: bipush 73
    //   105: putstatic 67	uuuuuu/ssssst:b006Ennnn006E006E006En	I
    //   108: bipush 12
    //   110: putstatic 96	uuuuuu/ssssst:bn006Ennn006E006E006En	I
    //   113: bipush 30
    //   115: putstatic 67	uuuuuu/ssssst:b006Ennnn006E006E006En	I
    //   118: ldc 2
    //   120: ldc 122
    //   122: bipush 73
    //   124: iconst_0
    //   125: invokestatic 77	xxxxxx/uxxxxx:bb00620062bb0062b0062b0062	(Ljava/lang/String;CC)Ljava/lang/String;
    //   128: iconst_0
    //   129: anewarray 79	java/lang/Class
    //   132: invokevirtual 83	java/lang/Class:getMethod	(Ljava/lang/String;[Ljava/lang/Class;)Ljava/lang/reflect/Method;
    //   135: astore_3
    //   136: aload_3
    //   137: aconst_null
    //   138: iconst_0
    //   139: anewarray 5	java/lang/Object
    //   142: invokevirtual 89	java/lang/reflect/Method:invoke	(Ljava/lang/Object;[Ljava/lang/Object;)Ljava/lang/Object;
    //   145: astore_3
    //   146: aload_3
    //   147: checkcast 91	java/lang/Integer
    //   150: invokevirtual 94	java/lang/Integer:intValue	()I
    //   153: putstatic 96	uuuuuu/ssssst:bn006Ennn006E006E006En	I
    //   156: bipush 82
    //   158: putstatic 67	uuuuuu/ssssst:b006Ennnn006E006E006En	I
    //   161: bipush 55
    //   163: putstatic 96	uuuuuu/ssssst:bn006Ennn006E006E006En	I
    //   166: getstatic 67	uuuuuu/ssssst:b006Ennnn006E006E006En	I
    //   169: getstatic 69	uuuuuu/ssssst:b006E006Ennn006E006E006En	I
    //   172: iadd
    //   173: getstatic 67	uuuuuu/ssssst:b006Ennnn006E006E006En	I
    //   176: imul
    //   177: getstatic 102	uuuuuu/ssssst:bnn006Enn006E006E006En	I
    //   180: irem
    //   181: getstatic 96	uuuuuu/ssssst:bn006Ennn006E006E006En	I
    //   184: if_icmpeq +47 -> 231
    //   187: bipush 40
    //   189: putstatic 67	uuuuuu/ssssst:b006Ennnn006E006E006En	I
    //   192: ldc 2
    //   194: ldc 124
    //   196: sipush 189
    //   199: iconst_3
    //   200: invokestatic 77	xxxxxx/uxxxxx:bb00620062bb0062b0062b0062	(Ljava/lang/String;CC)Ljava/lang/String;
    //   203: iconst_0
    //   204: anewarray 79	java/lang/Class
    //   207: invokevirtual 83	java/lang/Class:getMethod	(Ljava/lang/String;[Ljava/lang/Class;)Ljava/lang/reflect/Method;
    //   210: astore_3
    //   211: aload_3
    //   212: aconst_null
    //   213: iconst_0
    //   214: anewarray 5	java/lang/Object
    //   217: invokevirtual 89	java/lang/reflect/Method:invoke	(Ljava/lang/Object;[Ljava/lang/Object;)Ljava/lang/Object;
    //   220: astore_3
    //   221: aload_3
    //   222: checkcast 91	java/lang/Integer
    //   225: invokevirtual 94	java/lang/Integer:intValue	()I
    //   228: putstatic 96	uuuuuu/ssssst:bn006Ennn006E006E006En	I
    //   231: aload_2
    //   232: invokevirtual 129	uuuuuu/ggyggy:bpppp0070p00700070pp	()Z
    //   235: ireturn
    //   236: astore_2
    //   237: aload_2
    //   238: invokevirtual 114	java/lang/reflect/InvocationTargetException:getCause	()Ljava/lang/Throwable;
    //   241: athrow
    //   242: astore_2
    //   243: aload_2
    //   244: invokevirtual 114	java/lang/reflect/InvocationTargetException:getCause	()Ljava/lang/Throwable;
    //   247: athrow
    //   248: astore_2
    //   249: aload_2
    //   250: invokevirtual 114	java/lang/reflect/InvocationTargetException:getCause	()Ljava/lang/Throwable;
    //   253: athrow
    // Local variable table:
    //   start	length	slot	name	signature
    //   0	254	0	this	ssssst
    //   29	39	1	i	int
    //   4	228	2	localGgyggy	ggyggy
    //   236	2	2	localInvocationTargetException1	java.lang.reflect.InvocationTargetException
    //   242	2	2	localInvocationTargetException2	java.lang.reflect.InvocationTargetException
    //   248	2	2	localInvocationTargetException3	java.lang.reflect.InvocationTargetException
    //   48	174	3	localObject	Object
    // Exception table:
    //   from	to	target	type
    //   49	59	236	java/lang/reflect/InvocationTargetException
    //   211	221	242	java/lang/reflect/InvocationTargetException
    //   136	146	248	java/lang/reflect/InvocationTargetException
  }
  
  /* Error */
  @android.support.annotation.CallSuper
  public void ba006100610061a0061aa0061a()
  {
    // Byte code:
    //   0: ldc 2
    //   2: ldc -123
    //   4: sipush 206
    //   7: bipush 120
    //   9: iconst_2
    //   10: invokestatic 137	xxxxxx/uxxxxx:bbbb0062b0062b0062b0062	(Ljava/lang/String;CCC)Ljava/lang/String;
    //   13: iconst_0
    //   14: anewarray 79	java/lang/Class
    //   17: invokevirtual 83	java/lang/Class:getMethod	(Ljava/lang/String;[Ljava/lang/Class;)Ljava/lang/reflect/Method;
    //   20: astore_3
    //   21: aload_3
    //   22: aconst_null
    //   23: iconst_0
    //   24: anewarray 5	java/lang/Object
    //   27: invokevirtual 89	java/lang/reflect/Method:invoke	(Ljava/lang/Object;[Ljava/lang/Object;)Ljava/lang/Object;
    //   30: astore_3
    //   31: aload_3
    //   32: checkcast 91	java/lang/Integer
    //   35: invokevirtual 94	java/lang/Integer:intValue	()I
    //   38: istore_1
    //   39: ldc 2
    //   41: ldc -117
    //   43: sipush 216
    //   46: iconst_4
    //   47: invokestatic 77	xxxxxx/uxxxxx:bb00620062bb0062b0062b0062	(Ljava/lang/String;CC)Ljava/lang/String;
    //   50: iconst_0
    //   51: anewarray 79	java/lang/Class
    //   54: invokevirtual 83	java/lang/Class:getMethod	(Ljava/lang/String;[Ljava/lang/Class;)Ljava/lang/reflect/Method;
    //   57: astore_3
    //   58: aload_3
    //   59: aconst_null
    //   60: iconst_0
    //   61: anewarray 5	java/lang/Object
    //   64: invokevirtual 89	java/lang/reflect/Method:invoke	(Ljava/lang/Object;[Ljava/lang/Object;)Ljava/lang/Object;
    //   67: astore_3
    //   68: aload_3
    //   69: checkcast 91	java/lang/Integer
    //   72: invokevirtual 94	java/lang/Integer:intValue	()I
    //   75: iload_1
    //   76: iadd
    //   77: iload_1
    //   78: imul
    //   79: getstatic 102	uuuuuu/ssssst:bnn006Enn006E006E006En	I
    //   82: irem
    //   83: tableswitch	default:+17->100, 0:+448->531
    //   100: ldc 2
    //   102: ldc -115
    //   104: bipush 104
    //   106: iconst_2
    //   107: invokestatic 77	xxxxxx/uxxxxx:bb00620062bb0062b0062b0062	(Ljava/lang/String;CC)Ljava/lang/String;
    //   110: iconst_0
    //   111: anewarray 79	java/lang/Class
    //   114: invokevirtual 83	java/lang/Class:getMethod	(Ljava/lang/String;[Ljava/lang/Class;)Ljava/lang/reflect/Method;
    //   117: astore_3
    //   118: aload_3
    //   119: aconst_null
    //   120: iconst_0
    //   121: anewarray 5	java/lang/Object
    //   124: invokevirtual 89	java/lang/reflect/Method:invoke	(Ljava/lang/Object;[Ljava/lang/Object;)Ljava/lang/Object;
    //   127: astore_3
    //   128: aload_3
    //   129: checkcast 91	java/lang/Integer
    //   132: invokevirtual 94	java/lang/Integer:intValue	()I
    //   135: putstatic 67	uuuuuu/ssssst:b006Ennnn006E006E006En	I
    //   138: ldc 2
    //   140: ldc -113
    //   142: bipush 28
    //   144: iconst_5
    //   145: invokestatic 77	xxxxxx/uxxxxx:bb00620062bb0062b0062b0062	(Ljava/lang/String;CC)Ljava/lang/String;
    //   148: iconst_0
    //   149: anewarray 79	java/lang/Class
    //   152: invokevirtual 83	java/lang/Class:getMethod	(Ljava/lang/String;[Ljava/lang/Class;)Ljava/lang/reflect/Method;
    //   155: astore_3
    //   156: aload_3
    //   157: aconst_null
    //   158: iconst_0
    //   159: anewarray 5	java/lang/Object
    //   162: invokevirtual 89	java/lang/reflect/Method:invoke	(Ljava/lang/Object;[Ljava/lang/Object;)Ljava/lang/Object;
    //   165: astore_3
    //   166: aload_3
    //   167: checkcast 91	java/lang/Integer
    //   170: invokevirtual 94	java/lang/Integer:intValue	()I
    //   173: putstatic 96	uuuuuu/ssssst:bn006Ennn006E006E006En	I
    //   176: getstatic 67	uuuuuu/ssssst:b006Ennnn006E006E006En	I
    //   179: istore_1
    //   180: iload_1
    //   181: getstatic 69	uuuuuu/ssssst:b006E006Ennn006E006E006En	I
    //   184: iload_1
    //   185: iadd
    //   186: imul
    //   187: getstatic 102	uuuuuu/ssssst:bnn006Enn006E006E006En	I
    //   190: irem
    //   191: tableswitch	default:+17->208, 0:+340->531
    //   208: ldc 2
    //   210: ldc -111
    //   212: sipush 191
    //   215: iconst_3
    //   216: invokestatic 77	xxxxxx/uxxxxx:bb00620062bb0062b0062b0062	(Ljava/lang/String;CC)Ljava/lang/String;
    //   219: iconst_0
    //   220: anewarray 79	java/lang/Class
    //   223: invokevirtual 83	java/lang/Class:getMethod	(Ljava/lang/String;[Ljava/lang/Class;)Ljava/lang/reflect/Method;
    //   226: astore_3
    //   227: aload_3
    //   228: aconst_null
    //   229: iconst_0
    //   230: anewarray 5	java/lang/Object
    //   233: invokevirtual 89	java/lang/reflect/Method:invoke	(Ljava/lang/Object;[Ljava/lang/Object;)Ljava/lang/Object;
    //   236: astore_3
    //   237: aload_3
    //   238: checkcast 91	java/lang/Integer
    //   241: invokevirtual 94	java/lang/Integer:intValue	()I
    //   244: istore_1
    //   245: getstatic 67	uuuuuu/ssssst:b006Ennnn006E006E006En	I
    //   248: getstatic 69	uuuuuu/ssssst:b006E006Ennn006E006E006En	I
    //   251: iadd
    //   252: getstatic 67	uuuuuu/ssssst:b006Ennnn006E006E006En	I
    //   255: imul
    //   256: getstatic 102	uuuuuu/ssssst:bnn006Enn006E006E006En	I
    //   259: irem
    //   260: getstatic 96	uuuuuu/ssssst:bn006Ennn006E006E006En	I
    //   263: if_icmpeq +47 -> 310
    //   266: bipush 39
    //   268: putstatic 67	uuuuuu/ssssst:b006Ennnn006E006E006En	I
    //   271: ldc 2
    //   273: ldc -109
    //   275: sipush 183
    //   278: iconst_5
    //   279: invokestatic 77	xxxxxx/uxxxxx:bb00620062bb0062b0062b0062	(Ljava/lang/String;CC)Ljava/lang/String;
    //   282: iconst_0
    //   283: anewarray 79	java/lang/Class
    //   286: invokevirtual 83	java/lang/Class:getMethod	(Ljava/lang/String;[Ljava/lang/Class;)Ljava/lang/reflect/Method;
    //   289: astore_3
    //   290: aload_3
    //   291: aconst_null
    //   292: iconst_0
    //   293: anewarray 5	java/lang/Object
    //   296: invokevirtual 89	java/lang/reflect/Method:invoke	(Ljava/lang/Object;[Ljava/lang/Object;)Ljava/lang/Object;
    //   299: astore_3
    //   300: aload_3
    //   301: checkcast 91	java/lang/Integer
    //   304: invokevirtual 94	java/lang/Integer:intValue	()I
    //   307: putstatic 96	uuuuuu/ssssst:bn006Ennn006E006E006En	I
    //   310: iload_1
    //   311: putstatic 67	uuuuuu/ssssst:b006Ennnn006E006E006En	I
    //   314: ldc 2
    //   316: ldc -107
    //   318: bipush 12
    //   320: iconst_0
    //   321: invokestatic 77	xxxxxx/uxxxxx:bb00620062bb0062b0062b0062	(Ljava/lang/String;CC)Ljava/lang/String;
    //   324: iconst_0
    //   325: anewarray 79	java/lang/Class
    //   328: invokevirtual 83	java/lang/Class:getMethod	(Ljava/lang/String;[Ljava/lang/Class;)Ljava/lang/reflect/Method;
    //   331: astore_3
    //   332: aload_3
    //   333: aconst_null
    //   334: iconst_0
    //   335: anewarray 5	java/lang/Object
    //   338: invokevirtual 89	java/lang/reflect/Method:invoke	(Ljava/lang/Object;[Ljava/lang/Object;)Ljava/lang/Object;
    //   341: astore_3
    //   342: aload_3
    //   343: checkcast 91	java/lang/Integer
    //   346: invokevirtual 94	java/lang/Integer:intValue	()I
    //   349: putstatic 96	uuuuuu/ssssst:bn006Ennn006E006E006En	I
    //   352: getstatic 67	uuuuuu/ssssst:b006Ennnn006E006E006En	I
    //   355: istore_1
    //   356: ldc 2
    //   358: ldc -105
    //   360: sipush 142
    //   363: iconst_3
    //   364: invokestatic 77	xxxxxx/uxxxxx:bb00620062bb0062b0062b0062	(Ljava/lang/String;CC)Ljava/lang/String;
    //   367: iconst_0
    //   368: anewarray 79	java/lang/Class
    //   371: invokevirtual 83	java/lang/Class:getMethod	(Ljava/lang/String;[Ljava/lang/Class;)Ljava/lang/reflect/Method;
    //   374: astore_3
    //   375: aload_3
    //   376: aconst_null
    //   377: iconst_0
    //   378: anewarray 5	java/lang/Object
    //   381: invokevirtual 89	java/lang/reflect/Method:invoke	(Ljava/lang/Object;[Ljava/lang/Object;)Ljava/lang/Object;
    //   384: astore_3
    //   385: aload_3
    //   386: checkcast 91	java/lang/Integer
    //   389: invokevirtual 94	java/lang/Integer:intValue	()I
    //   392: istore_2
    //   393: ldc 2
    //   395: ldc -103
    //   397: bipush 8
    //   399: iconst_5
    //   400: invokestatic 77	xxxxxx/uxxxxx:bb00620062bb0062b0062b0062	(Ljava/lang/String;CC)Ljava/lang/String;
    //   403: iconst_0
    //   404: anewarray 79	java/lang/Class
    //   407: invokevirtual 83	java/lang/Class:getMethod	(Ljava/lang/String;[Ljava/lang/Class;)Ljava/lang/reflect/Method;
    //   410: astore_3
    //   411: aload_3
    //   412: aconst_null
    //   413: iconst_0
    //   414: anewarray 5	java/lang/Object
    //   417: invokevirtual 89	java/lang/reflect/Method:invoke	(Ljava/lang/Object;[Ljava/lang/Object;)Ljava/lang/Object;
    //   420: astore_3
    //   421: iload_1
    //   422: iload_2
    //   423: iload_1
    //   424: iadd
    //   425: imul
    //   426: aload_3
    //   427: checkcast 91	java/lang/Integer
    //   430: invokevirtual 94	java/lang/Integer:intValue	()I
    //   433: irem
    //   434: tableswitch	default:+18->452, 0:+97->531
    //   452: ldc 2
    //   454: ldc -101
    //   456: sipush 248
    //   459: iconst_3
    //   460: invokestatic 77	xxxxxx/uxxxxx:bb00620062bb0062b0062b0062	(Ljava/lang/String;CC)Ljava/lang/String;
    //   463: iconst_0
    //   464: anewarray 79	java/lang/Class
    //   467: invokevirtual 83	java/lang/Class:getMethod	(Ljava/lang/String;[Ljava/lang/Class;)Ljava/lang/reflect/Method;
    //   470: astore_3
    //   471: aload_3
    //   472: aconst_null
    //   473: iconst_0
    //   474: anewarray 5	java/lang/Object
    //   477: invokevirtual 89	java/lang/reflect/Method:invoke	(Ljava/lang/Object;[Ljava/lang/Object;)Ljava/lang/Object;
    //   480: astore_3
    //   481: aload_3
    //   482: checkcast 91	java/lang/Integer
    //   485: invokevirtual 94	java/lang/Integer:intValue	()I
    //   488: putstatic 67	uuuuuu/ssssst:b006Ennnn006E006E006En	I
    //   491: ldc 2
    //   493: ldc -99
    //   495: bipush 82
    //   497: bipush 55
    //   499: iconst_3
    //   500: invokestatic 137	xxxxxx/uxxxxx:bbbb0062b0062b0062b0062	(Ljava/lang/String;CCC)Ljava/lang/String;
    //   503: iconst_0
    //   504: anewarray 79	java/lang/Class
    //   507: invokevirtual 83	java/lang/Class:getMethod	(Ljava/lang/String;[Ljava/lang/Class;)Ljava/lang/reflect/Method;
    //   510: astore_3
    //   511: aload_3
    //   512: aconst_null
    //   513: iconst_0
    //   514: anewarray 5	java/lang/Object
    //   517: invokevirtual 89	java/lang/reflect/Method:invoke	(Ljava/lang/Object;[Ljava/lang/Object;)Ljava/lang/Object;
    //   520: astore_3
    //   521: aload_3
    //   522: checkcast 91	java/lang/Integer
    //   525: invokevirtual 94	java/lang/Integer:intValue	()I
    //   528: putstatic 96	uuuuuu/ssssst:bn006Ennn006E006E006En	I
    //   531: aload_0
    //   532: aconst_null
    //   533: putfield 98	uuuuuu/ssssst:bnnnnn006E006E006En	Luuuuuu/ttssst$tsssst;
    //   536: return
    //   537: astore_3
    //   538: aload_3
    //   539: invokevirtual 114	java/lang/reflect/InvocationTargetException:getCause	()Ljava/lang/Throwable;
    //   542: athrow
    //   543: astore_3
    //   544: aload_3
    //   545: invokevirtual 114	java/lang/reflect/InvocationTargetException:getCause	()Ljava/lang/Throwable;
    //   548: athrow
    //   549: astore_3
    //   550: aload_3
    //   551: invokevirtual 114	java/lang/reflect/InvocationTargetException:getCause	()Ljava/lang/Throwable;
    //   554: athrow
    //   555: astore_3
    //   556: aload_3
    //   557: invokevirtual 114	java/lang/reflect/InvocationTargetException:getCause	()Ljava/lang/Throwable;
    //   560: athrow
    //   561: astore_3
    //   562: aload_3
    //   563: invokevirtual 114	java/lang/reflect/InvocationTargetException:getCause	()Ljava/lang/Throwable;
    //   566: athrow
    //   567: astore_3
    //   568: aload_3
    //   569: invokevirtual 114	java/lang/reflect/InvocationTargetException:getCause	()Ljava/lang/Throwable;
    //   572: athrow
    //   573: astore_3
    //   574: aload_3
    //   575: invokevirtual 114	java/lang/reflect/InvocationTargetException:getCause	()Ljava/lang/Throwable;
    //   578: athrow
    //   579: astore_3
    //   580: aload_3
    //   581: invokevirtual 114	java/lang/reflect/InvocationTargetException:getCause	()Ljava/lang/Throwable;
    //   584: athrow
    //   585: astore_3
    //   586: aload_3
    //   587: invokevirtual 114	java/lang/reflect/InvocationTargetException:getCause	()Ljava/lang/Throwable;
    //   590: athrow
    //   591: astore_3
    //   592: aload_3
    //   593: invokevirtual 114	java/lang/reflect/InvocationTargetException:getCause	()Ljava/lang/Throwable;
    //   596: athrow
    //   597: astore_3
    //   598: aload_3
    //   599: invokevirtual 114	java/lang/reflect/InvocationTargetException:getCause	()Ljava/lang/Throwable;
    //   602: athrow
    // Local variable table:
    //   start	length	slot	name	signature
    //   0	603	0	this	ssssst
    //   38	388	1	i	int
    //   392	33	2	j	int
    //   20	502	3	localObject	Object
    //   537	2	3	localInvocationTargetException1	java.lang.reflect.InvocationTargetException
    //   543	2	3	localInvocationTargetException2	java.lang.reflect.InvocationTargetException
    //   549	2	3	localInvocationTargetException3	java.lang.reflect.InvocationTargetException
    //   555	2	3	localInvocationTargetException4	java.lang.reflect.InvocationTargetException
    //   561	2	3	localInvocationTargetException5	java.lang.reflect.InvocationTargetException
    //   567	2	3	localInvocationTargetException6	java.lang.reflect.InvocationTargetException
    //   573	2	3	localInvocationTargetException7	java.lang.reflect.InvocationTargetException
    //   579	2	3	localInvocationTargetException8	java.lang.reflect.InvocationTargetException
    //   585	2	3	localInvocationTargetException9	java.lang.reflect.InvocationTargetException
    //   591	2	3	localInvocationTargetException10	java.lang.reflect.InvocationTargetException
    //   597	2	3	localInvocationTargetException11	java.lang.reflect.InvocationTargetException
    // Exception table:
    //   from	to	target	type
    //   58	68	537	java/lang/reflect/InvocationTargetException
    //   118	128	543	java/lang/reflect/InvocationTargetException
    //   375	385	549	java/lang/reflect/InvocationTargetException
    //   411	421	555	java/lang/reflect/InvocationTargetException
    //   156	166	561	java/lang/reflect/InvocationTargetException
    //   227	237	567	java/lang/reflect/InvocationTargetException
    //   21	31	573	java/lang/reflect/InvocationTargetException
    //   332	342	579	java/lang/reflect/InvocationTargetException
    //   290	300	585	java/lang/reflect/InvocationTargetException
    //   471	481	591	java/lang/reflect/InvocationTargetException
    //   511	521	597	java/lang/reflect/InvocationTargetException
  }
  
  /* Error */
  @android.support.annotation.CallSuper
  public void ba0061a0061a0061a0061aa(V paramV)
  {
    // Byte code:
    //   0: getstatic 67	uuuuuu/ssssst:b006Ennnn006E006E006En	I
    //   3: getstatic 69	uuuuuu/ssssst:b006E006Ennn006E006E006En	I
    //   6: iadd
    //   7: getstatic 67	uuuuuu/ssssst:b006Ennnn006E006E006En	I
    //   10: imul
    //   11: getstatic 102	uuuuuu/ssssst:bnn006Enn006E006E006En	I
    //   14: irem
    //   15: getstatic 96	uuuuuu/ssssst:bn006Ennn006E006E006En	I
    //   18: if_icmpeq +323 -> 341
    //   21: getstatic 67	uuuuuu/ssssst:b006Ennnn006E006E006En	I
    //   24: istore_2
    //   25: getstatic 67	uuuuuu/ssssst:b006Ennnn006E006E006En	I
    //   28: istore_3
    //   29: getstatic 69	uuuuuu/ssssst:b006E006Ennn006E006E006En	I
    //   32: istore 4
    //   34: getstatic 67	uuuuuu/ssssst:b006Ennnn006E006E006En	I
    //   37: istore 5
    //   39: getstatic 102	uuuuuu/ssssst:bnn006Enn006E006E006En	I
    //   42: istore 6
    //   44: ldc 2
    //   46: ldc -94
    //   48: bipush 49
    //   50: sipush 212
    //   53: iconst_0
    //   54: invokestatic 137	xxxxxx/uxxxxx:bbbb0062b0062b0062b0062	(Ljava/lang/String;CCC)Ljava/lang/String;
    //   57: iconst_0
    //   58: anewarray 79	java/lang/Class
    //   61: invokevirtual 83	java/lang/Class:getMethod	(Ljava/lang/String;[Ljava/lang/Class;)Ljava/lang/reflect/Method;
    //   64: astore 7
    //   66: aload 7
    //   68: aconst_null
    //   69: iconst_0
    //   70: anewarray 5	java/lang/Object
    //   73: invokevirtual 89	java/lang/reflect/Method:invoke	(Ljava/lang/Object;[Ljava/lang/Object;)Ljava/lang/Object;
    //   76: astore 7
    //   78: iload_3
    //   79: iload 4
    //   81: iadd
    //   82: iload 5
    //   84: imul
    //   85: iload 6
    //   87: irem
    //   88: aload 7
    //   90: checkcast 91	java/lang/Integer
    //   93: invokevirtual 94	java/lang/Integer:intValue	()I
    //   96: if_icmpeq +51 -> 147
    //   99: ldc 2
    //   101: ldc -92
    //   103: sipush 195
    //   106: iconst_3
    //   107: invokestatic 77	xxxxxx/uxxxxx:bb00620062bb0062b0062b0062	(Ljava/lang/String;CC)Ljava/lang/String;
    //   110: iconst_0
    //   111: anewarray 79	java/lang/Class
    //   114: invokevirtual 83	java/lang/Class:getMethod	(Ljava/lang/String;[Ljava/lang/Class;)Ljava/lang/reflect/Method;
    //   117: astore 7
    //   119: aload 7
    //   121: aconst_null
    //   122: iconst_0
    //   123: anewarray 5	java/lang/Object
    //   126: invokevirtual 89	java/lang/reflect/Method:invoke	(Ljava/lang/Object;[Ljava/lang/Object;)Ljava/lang/Object;
    //   129: astore 7
    //   131: aload 7
    //   133: checkcast 91	java/lang/Integer
    //   136: invokevirtual 94	java/lang/Integer:intValue	()I
    //   139: putstatic 67	uuuuuu/ssssst:b006Ennnn006E006E006En	I
    //   142: bipush 57
    //   144: putstatic 96	uuuuuu/ssssst:bn006Ennn006E006E006En	I
    //   147: getstatic 69	uuuuuu/ssssst:b006E006Ennn006E006E006En	I
    //   150: istore_3
    //   151: ldc 2
    //   153: ldc -90
    //   155: bipush 118
    //   157: bipush 119
    //   159: iconst_3
    //   160: invokestatic 137	xxxxxx/uxxxxx:bbbb0062b0062b0062b0062	(Ljava/lang/String;CCC)Ljava/lang/String;
    //   163: iconst_0
    //   164: anewarray 79	java/lang/Class
    //   167: invokevirtual 83	java/lang/Class:getMethod	(Ljava/lang/String;[Ljava/lang/Class;)Ljava/lang/reflect/Method;
    //   170: astore 7
    //   172: aload 7
    //   174: aconst_null
    //   175: iconst_0
    //   176: anewarray 5	java/lang/Object
    //   179: invokevirtual 89	java/lang/reflect/Method:invoke	(Ljava/lang/Object;[Ljava/lang/Object;)Ljava/lang/Object;
    //   182: astore 7
    //   184: iload_2
    //   185: iload_3
    //   186: iload_2
    //   187: iadd
    //   188: imul
    //   189: aload 7
    //   191: checkcast 91	java/lang/Integer
    //   194: invokevirtual 94	java/lang/Integer:intValue	()I
    //   197: irem
    //   198: tableswitch	default:+18->216, 0:+134->332
    //   216: getstatic 67	uuuuuu/ssssst:b006Ennnn006E006E006En	I
    //   219: getstatic 69	uuuuuu/ssssst:b006E006Ennn006E006E006En	I
    //   222: iadd
    //   223: getstatic 67	uuuuuu/ssssst:b006Ennnn006E006E006En	I
    //   226: imul
    //   227: getstatic 102	uuuuuu/ssssst:bnn006Enn006E006E006En	I
    //   230: irem
    //   231: getstatic 96	uuuuuu/ssssst:bn006Ennn006E006E006En	I
    //   234: if_icmpeq +51 -> 285
    //   237: bipush 39
    //   239: putstatic 67	uuuuuu/ssssst:b006Ennnn006E006E006En	I
    //   242: ldc 2
    //   244: ldc -88
    //   246: sipush 139
    //   249: iconst_2
    //   250: invokestatic 77	xxxxxx/uxxxxx:bb00620062bb0062b0062b0062	(Ljava/lang/String;CC)Ljava/lang/String;
    //   253: iconst_0
    //   254: anewarray 79	java/lang/Class
    //   257: invokevirtual 83	java/lang/Class:getMethod	(Ljava/lang/String;[Ljava/lang/Class;)Ljava/lang/reflect/Method;
    //   260: astore 7
    //   262: aload 7
    //   264: aconst_null
    //   265: iconst_0
    //   266: anewarray 5	java/lang/Object
    //   269: invokevirtual 89	java/lang/reflect/Method:invoke	(Ljava/lang/Object;[Ljava/lang/Object;)Ljava/lang/Object;
    //   272: astore 7
    //   274: aload 7
    //   276: checkcast 91	java/lang/Integer
    //   279: invokevirtual 94	java/lang/Integer:intValue	()I
    //   282: putstatic 96	uuuuuu/ssssst:bn006Ennn006E006E006En	I
    //   285: iconst_0
    //   286: putstatic 67	uuuuuu/ssssst:b006Ennnn006E006E006En	I
    //   289: ldc 2
    //   291: ldc -86
    //   293: sipush 166
    //   296: iconst_3
    //   297: invokestatic 77	xxxxxx/uxxxxx:bb00620062bb0062b0062b0062	(Ljava/lang/String;CC)Ljava/lang/String;
    //   300: iconst_0
    //   301: anewarray 79	java/lang/Class
    //   304: invokevirtual 83	java/lang/Class:getMethod	(Ljava/lang/String;[Ljava/lang/Class;)Ljava/lang/reflect/Method;
    //   307: astore 7
    //   309: aload 7
    //   311: aconst_null
    //   312: iconst_0
    //   313: anewarray 5	java/lang/Object
    //   316: invokevirtual 89	java/lang/reflect/Method:invoke	(Ljava/lang/Object;[Ljava/lang/Object;)Ljava/lang/Object;
    //   319: astore 7
    //   321: aload 7
    //   323: checkcast 91	java/lang/Integer
    //   326: invokevirtual 94	java/lang/Integer:intValue	()I
    //   329: putstatic 96	uuuuuu/ssssst:bn006Ennn006E006E006En	I
    //   332: bipush 42
    //   334: putstatic 67	uuuuuu/ssssst:b006Ennnn006E006E006En	I
    //   337: iconst_2
    //   338: putstatic 96	uuuuuu/ssssst:bn006Ennn006E006E006En	I
    //   341: aload_0
    //   342: aload_1
    //   343: putfield 98	uuuuuu/ssssst:bnnnnn006E006E006En	Luuuuuu/ttssst$tsssst;
    //   346: return
    //   347: astore_1
    //   348: aload_1
    //   349: invokevirtual 114	java/lang/reflect/InvocationTargetException:getCause	()Ljava/lang/Throwable;
    //   352: athrow
    //   353: astore_1
    //   354: aload_1
    //   355: invokevirtual 114	java/lang/reflect/InvocationTargetException:getCause	()Ljava/lang/Throwable;
    //   358: athrow
    //   359: astore_1
    //   360: aload_1
    //   361: invokevirtual 114	java/lang/reflect/InvocationTargetException:getCause	()Ljava/lang/Throwable;
    //   364: athrow
    //   365: astore_1
    //   366: aload_1
    //   367: invokevirtual 114	java/lang/reflect/InvocationTargetException:getCause	()Ljava/lang/Throwable;
    //   370: athrow
    //   371: astore_1
    //   372: aload_1
    //   373: invokevirtual 114	java/lang/reflect/InvocationTargetException:getCause	()Ljava/lang/Throwable;
    //   376: athrow
    // Local variable table:
    //   start	length	slot	name	signature
    //   0	377	0	this	ssssst
    //   0	377	1	paramV	V
    //   24	165	2	i	int
    //   28	160	3	j	int
    //   32	50	4	k	int
    //   37	48	5	m	int
    //   42	46	6	n	int
    //   64	258	7	localObject	Object
    // Exception table:
    //   from	to	target	type
    //   172	184	347	java/lang/reflect/InvocationTargetException
    //   66	78	353	java/lang/reflect/InvocationTargetException
    //   309	321	359	java/lang/reflect/InvocationTargetException
    //   119	131	365	java/lang/reflect/InvocationTargetException
    //   262	274	371	java/lang/reflect/InvocationTargetException
  }
  
  /* Error */
  public boolean bk006B006B006Bkk006Bk006Bk()
  {
    // Byte code:
    //   0: aload_0
    //   1: getfield 43	uuuuuu/ssssst:b006En006E006E006En006E006En	Luuuuuu/ggyggy;
    //   4: astore 6
    //   6: getstatic 67	uuuuuu/ssssst:b006Ennnn006E006E006En	I
    //   9: getstatic 69	uuuuuu/ssssst:b006E006Ennn006E006E006En	I
    //   12: iadd
    //   13: getstatic 67	uuuuuu/ssssst:b006Ennnn006E006E006En	I
    //   16: imul
    //   17: getstatic 102	uuuuuu/ssssst:bnn006Enn006E006E006En	I
    //   20: irem
    //   21: getstatic 96	uuuuuu/ssssst:bn006Ennn006E006E006En	I
    //   24: if_icmpeq +124 -> 148
    //   27: getstatic 67	uuuuuu/ssssst:b006Ennnn006E006E006En	I
    //   30: istore_1
    //   31: getstatic 69	uuuuuu/ssssst:b006E006Ennn006E006E006En	I
    //   34: istore_2
    //   35: getstatic 67	uuuuuu/ssssst:b006Ennnn006E006E006En	I
    //   38: istore_3
    //   39: getstatic 102	uuuuuu/ssssst:bnn006Enn006E006E006En	I
    //   42: istore 4
    //   44: ldc 2
    //   46: ldc -82
    //   48: sipush 193
    //   51: bipush 98
    //   53: iconst_2
    //   54: invokestatic 137	xxxxxx/uxxxxx:bbbb0062b0062b0062b0062	(Ljava/lang/String;CCC)Ljava/lang/String;
    //   57: iconst_0
    //   58: anewarray 79	java/lang/Class
    //   61: invokevirtual 83	java/lang/Class:getMethod	(Ljava/lang/String;[Ljava/lang/Class;)Ljava/lang/reflect/Method;
    //   64: astore 7
    //   66: aload 7
    //   68: aconst_null
    //   69: iconst_0
    //   70: anewarray 5	java/lang/Object
    //   73: invokevirtual 89	java/lang/reflect/Method:invoke	(Ljava/lang/Object;[Ljava/lang/Object;)Ljava/lang/Object;
    //   76: astore 7
    //   78: iload_1
    //   79: iload_2
    //   80: iadd
    //   81: iload_3
    //   82: imul
    //   83: iload 4
    //   85: irem
    //   86: aload 7
    //   88: checkcast 91	java/lang/Integer
    //   91: invokevirtual 94	java/lang/Integer:intValue	()I
    //   94: if_icmpeq +13 -> 107
    //   97: bipush 57
    //   99: putstatic 67	uuuuuu/ssssst:b006Ennnn006E006E006En	I
    //   102: bipush 79
    //   104: putstatic 96	uuuuuu/ssssst:bn006Ennn006E006E006En	I
    //   107: bipush 86
    //   109: putstatic 67	uuuuuu/ssssst:b006Ennnn006E006E006En	I
    //   112: bipush 98
    //   114: putstatic 96	uuuuuu/ssssst:bn006Ennn006E006E006En	I
    //   117: getstatic 67	uuuuuu/ssssst:b006Ennnn006E006E006En	I
    //   120: getstatic 69	uuuuuu/ssssst:b006E006Ennn006E006E006En	I
    //   123: iadd
    //   124: getstatic 67	uuuuuu/ssssst:b006Ennnn006E006E006En	I
    //   127: imul
    //   128: getstatic 102	uuuuuu/ssssst:bnn006Enn006E006E006En	I
    //   131: irem
    //   132: getstatic 96	uuuuuu/ssssst:bn006Ennn006E006E006En	I
    //   135: if_icmpeq +13 -> 148
    //   138: bipush 75
    //   140: putstatic 67	uuuuuu/ssssst:b006Ennnn006E006E006En	I
    //   143: bipush 75
    //   145: putstatic 96	uuuuuu/ssssst:bn006Ennn006E006E006En	I
    //   148: aload 6
    //   150: invokevirtual 177	uuuuuu/ggyggy:b0070ppp0070p00700070pp	()Z
    //   153: istore 5
    //   155: ldc 2
    //   157: ldc -77
    //   159: sipush 197
    //   162: iconst_1
    //   163: invokestatic 77	xxxxxx/uxxxxx:bb00620062bb0062b0062b0062	(Ljava/lang/String;CC)Ljava/lang/String;
    //   166: iconst_0
    //   167: anewarray 79	java/lang/Class
    //   170: invokevirtual 83	java/lang/Class:getMethod	(Ljava/lang/String;[Ljava/lang/Class;)Ljava/lang/reflect/Method;
    //   173: astore 6
    //   175: aload 6
    //   177: aconst_null
    //   178: iconst_0
    //   179: anewarray 5	java/lang/Object
    //   182: invokevirtual 89	java/lang/reflect/Method:invoke	(Ljava/lang/Object;[Ljava/lang/Object;)Ljava/lang/Object;
    //   185: astore 6
    //   187: aload 6
    //   189: checkcast 91	java/lang/Integer
    //   192: invokevirtual 94	java/lang/Integer:intValue	()I
    //   195: istore_1
    //   196: getstatic 69	uuuuuu/ssssst:b006E006Ennn006E006E006En	I
    //   199: istore_2
    //   200: ldc 2
    //   202: ldc -75
    //   204: bipush 119
    //   206: iconst_2
    //   207: invokestatic 77	xxxxxx/uxxxxx:bb00620062bb0062b0062b0062	(Ljava/lang/String;CC)Ljava/lang/String;
    //   210: iconst_0
    //   211: anewarray 79	java/lang/Class
    //   214: invokevirtual 83	java/lang/Class:getMethod	(Ljava/lang/String;[Ljava/lang/Class;)Ljava/lang/reflect/Method;
    //   217: astore 6
    //   219: aload 6
    //   221: aconst_null
    //   222: iconst_0
    //   223: anewarray 5	java/lang/Object
    //   226: invokevirtual 89	java/lang/reflect/Method:invoke	(Ljava/lang/Object;[Ljava/lang/Object;)Ljava/lang/Object;
    //   229: astore 6
    //   231: aload 6
    //   233: checkcast 91	java/lang/Integer
    //   236: invokevirtual 94	java/lang/Integer:intValue	()I
    //   239: iload_2
    //   240: iload_1
    //   241: iadd
    //   242: imul
    //   243: getstatic 102	uuuuuu/ssssst:bnn006Enn006E006E006En	I
    //   246: irem
    //   247: getstatic 96	uuuuuu/ssssst:bn006Ennn006E006E006En	I
    //   250: if_icmpeq +53 -> 303
    //   253: ldc 2
    //   255: ldc -73
    //   257: sipush 233
    //   260: bipush 17
    //   262: iconst_2
    //   263: invokestatic 137	xxxxxx/uxxxxx:bbbb0062b0062b0062b0062	(Ljava/lang/String;CCC)Ljava/lang/String;
    //   266: iconst_0
    //   267: anewarray 79	java/lang/Class
    //   270: invokevirtual 83	java/lang/Class:getMethod	(Ljava/lang/String;[Ljava/lang/Class;)Ljava/lang/reflect/Method;
    //   273: astore 6
    //   275: aload 6
    //   277: aconst_null
    //   278: iconst_0
    //   279: anewarray 5	java/lang/Object
    //   282: invokevirtual 89	java/lang/reflect/Method:invoke	(Ljava/lang/Object;[Ljava/lang/Object;)Ljava/lang/Object;
    //   285: astore 6
    //   287: aload 6
    //   289: checkcast 91	java/lang/Integer
    //   292: invokevirtual 94	java/lang/Integer:intValue	()I
    //   295: putstatic 67	uuuuuu/ssssst:b006Ennnn006E006E006En	I
    //   298: bipush 40
    //   300: putstatic 96	uuuuuu/ssssst:bn006Ennn006E006E006En	I
    //   303: iload 5
    //   305: ireturn
    //   306: astore 6
    //   308: aload 6
    //   310: invokevirtual 114	java/lang/reflect/InvocationTargetException:getCause	()Ljava/lang/Throwable;
    //   313: athrow
    //   314: astore 6
    //   316: aload 6
    //   318: invokevirtual 114	java/lang/reflect/InvocationTargetException:getCause	()Ljava/lang/Throwable;
    //   321: athrow
    //   322: astore 6
    //   324: aload 6
    //   326: invokevirtual 114	java/lang/reflect/InvocationTargetException:getCause	()Ljava/lang/Throwable;
    //   329: athrow
    //   330: astore 6
    //   332: aload 6
    //   334: invokevirtual 114	java/lang/reflect/InvocationTargetException:getCause	()Ljava/lang/Throwable;
    //   337: athrow
    // Local variable table:
    //   start	length	slot	name	signature
    //   0	338	0	this	ssssst
    //   30	212	1	i	int
    //   34	208	2	j	int
    //   38	45	3	k	int
    //   42	44	4	m	int
    //   153	151	5	bool	boolean
    //   4	284	6	localObject1	Object
    //   306	3	6	localInvocationTargetException1	java.lang.reflect.InvocationTargetException
    //   314	3	6	localInvocationTargetException2	java.lang.reflect.InvocationTargetException
    //   322	3	6	localInvocationTargetException3	java.lang.reflect.InvocationTargetException
    //   330	3	6	localInvocationTargetException4	java.lang.reflect.InvocationTargetException
    //   64	23	7	localObject2	Object
    // Exception table:
    //   from	to	target	type
    //   175	187	306	java/lang/reflect/InvocationTargetException
    //   219	231	314	java/lang/reflect/InvocationTargetException
    //   275	287	322	java/lang/reflect/InvocationTargetException
    //   66	78	330	java/lang/reflect/InvocationTargetException
  }
  
  /* Error */
  public boolean bkk006Bk006Bk006Bk006Bk()
  {
    // Byte code:
    //   0: aload_0
    //   1: getfield 98	uuuuuu/ssssst:bnnnnn006E006E006En	Luuuuuu/ttssst$tsssst;
    //   4: ifnull +81 -> 85
    //   7: getstatic 67	uuuuuu/ssssst:b006Ennnn006E006E006En	I
    //   10: istore_1
    //   11: iload_1
    //   12: getstatic 69	uuuuuu/ssssst:b006E006Ennn006E006E006En	I
    //   15: iload_1
    //   16: iadd
    //   17: imul
    //   18: getstatic 102	uuuuuu/ssssst:bnn006Enn006E006E006En	I
    //   21: irem
    //   22: tableswitch	default:+18->40, 0:+61->83
    //   40: bipush 11
    //   42: putstatic 67	uuuuuu/ssssst:b006Ennnn006E006E006En	I
    //   45: ldc 2
    //   47: ldc -70
    //   49: bipush 78
    //   51: iconst_2
    //   52: invokestatic 77	xxxxxx/uxxxxx:bb00620062bb0062b0062b0062	(Ljava/lang/String;CC)Ljava/lang/String;
    //   55: iconst_0
    //   56: anewarray 79	java/lang/Class
    //   59: invokevirtual 83	java/lang/Class:getMethod	(Ljava/lang/String;[Ljava/lang/Class;)Ljava/lang/reflect/Method;
    //   62: astore_2
    //   63: aload_2
    //   64: aconst_null
    //   65: iconst_0
    //   66: anewarray 5	java/lang/Object
    //   69: invokevirtual 89	java/lang/reflect/Method:invoke	(Ljava/lang/Object;[Ljava/lang/Object;)Ljava/lang/Object;
    //   72: astore_2
    //   73: aload_2
    //   74: checkcast 91	java/lang/Integer
    //   77: invokevirtual 94	java/lang/Integer:intValue	()I
    //   80: putstatic 96	uuuuuu/ssssst:bn006Ennn006E006E006En	I
    //   83: iconst_1
    //   84: ireturn
    //   85: getstatic 67	uuuuuu/ssssst:b006Ennnn006E006E006En	I
    //   88: istore_1
    //   89: iload_1
    //   90: getstatic 69	uuuuuu/ssssst:b006E006Ennn006E006E006En	I
    //   93: iload_1
    //   94: iadd
    //   95: imul
    //   96: getstatic 102	uuuuuu/ssssst:bnn006Enn006E006E006En	I
    //   99: irem
    //   100: tableswitch	default:+20->120, 0:+30->130
    //   120: bipush 26
    //   122: putstatic 67	uuuuuu/ssssst:b006Ennnn006E006E006En	I
    //   125: bipush 15
    //   127: putstatic 96	uuuuuu/ssssst:bn006Ennn006E006E006En	I
    //   130: getstatic 67	uuuuuu/ssssst:b006Ennnn006E006E006En	I
    //   133: getstatic 69	uuuuuu/ssssst:b006E006Ennn006E006E006En	I
    //   136: iadd
    //   137: getstatic 67	uuuuuu/ssssst:b006Ennnn006E006E006En	I
    //   140: imul
    //   141: getstatic 102	uuuuuu/ssssst:bnn006Enn006E006E006En	I
    //   144: irem
    //   145: getstatic 96	uuuuuu/ssssst:bn006Ennn006E006E006En	I
    //   148: if_icmpeq +181 -> 329
    //   151: getstatic 67	uuuuuu/ssssst:b006Ennnn006E006E006En	I
    //   154: istore_1
    //   155: iload_1
    //   156: getstatic 69	uuuuuu/ssssst:b006E006Ennn006E006E006En	I
    //   159: iload_1
    //   160: iadd
    //   161: imul
    //   162: getstatic 102	uuuuuu/ssssst:bnn006Enn006E006E006En	I
    //   165: irem
    //   166: tableswitch	default:+18->184, 0:+62->228
    //   184: bipush 77
    //   186: putstatic 67	uuuuuu/ssssst:b006Ennnn006E006E006En	I
    //   189: ldc 2
    //   191: ldc -107
    //   193: sipush 139
    //   196: iconst_0
    //   197: invokestatic 77	xxxxxx/uxxxxx:bb00620062bb0062b0062b0062	(Ljava/lang/String;CC)Ljava/lang/String;
    //   200: iconst_0
    //   201: anewarray 79	java/lang/Class
    //   204: invokevirtual 83	java/lang/Class:getMethod	(Ljava/lang/String;[Ljava/lang/Class;)Ljava/lang/reflect/Method;
    //   207: astore_2
    //   208: aload_2
    //   209: aconst_null
    //   210: iconst_0
    //   211: anewarray 5	java/lang/Object
    //   214: invokevirtual 89	java/lang/reflect/Method:invoke	(Ljava/lang/Object;[Ljava/lang/Object;)Ljava/lang/Object;
    //   217: astore_2
    //   218: aload_2
    //   219: checkcast 91	java/lang/Integer
    //   222: invokevirtual 94	java/lang/Integer:intValue	()I
    //   225: putstatic 96	uuuuuu/ssssst:bn006Ennn006E006E006En	I
    //   228: ldc 2
    //   230: ldc -68
    //   232: bipush 16
    //   234: iconst_3
    //   235: invokestatic 77	xxxxxx/uxxxxx:bb00620062bb0062b0062b0062	(Ljava/lang/String;CC)Ljava/lang/String;
    //   238: iconst_0
    //   239: anewarray 79	java/lang/Class
    //   242: invokevirtual 83	java/lang/Class:getMethod	(Ljava/lang/String;[Ljava/lang/Class;)Ljava/lang/reflect/Method;
    //   245: astore_2
    //   246: aload_2
    //   247: aconst_null
    //   248: iconst_0
    //   249: anewarray 5	java/lang/Object
    //   252: invokevirtual 89	java/lang/reflect/Method:invoke	(Ljava/lang/Object;[Ljava/lang/Object;)Ljava/lang/Object;
    //   255: astore_2
    //   256: aload_2
    //   257: checkcast 91	java/lang/Integer
    //   260: invokevirtual 94	java/lang/Integer:intValue	()I
    //   263: putstatic 67	uuuuuu/ssssst:b006Ennnn006E006E006En	I
    //   266: ldc 2
    //   268: ldc -66
    //   270: iconst_5
    //   271: iconst_5
    //   272: invokestatic 77	xxxxxx/uxxxxx:bb00620062bb0062b0062b0062	(Ljava/lang/String;CC)Ljava/lang/String;
    //   275: iconst_0
    //   276: anewarray 79	java/lang/Class
    //   279: invokevirtual 83	java/lang/Class:getMethod	(Ljava/lang/String;[Ljava/lang/Class;)Ljava/lang/reflect/Method;
    //   282: astore_2
    //   283: aload_2
    //   284: aconst_null
    //   285: iconst_0
    //   286: anewarray 5	java/lang/Object
    //   289: invokevirtual 89	java/lang/reflect/Method:invoke	(Ljava/lang/Object;[Ljava/lang/Object;)Ljava/lang/Object;
    //   292: astore_2
    //   293: aload_2
    //   294: checkcast 91	java/lang/Integer
    //   297: invokevirtual 94	java/lang/Integer:intValue	()I
    //   300: putstatic 96	uuuuuu/ssssst:bn006Ennn006E006E006En	I
    //   303: iconst_0
    //   304: ireturn
    //   305: astore_2
    //   306: aload_2
    //   307: invokevirtual 114	java/lang/reflect/InvocationTargetException:getCause	()Ljava/lang/Throwable;
    //   310: athrow
    //   311: astore_2
    //   312: aload_2
    //   313: invokevirtual 114	java/lang/reflect/InvocationTargetException:getCause	()Ljava/lang/Throwable;
    //   316: athrow
    //   317: astore_2
    //   318: aload_2
    //   319: invokevirtual 114	java/lang/reflect/InvocationTargetException:getCause	()Ljava/lang/Throwable;
    //   322: athrow
    //   323: astore_2
    //   324: aload_2
    //   325: invokevirtual 114	java/lang/reflect/InvocationTargetException:getCause	()Ljava/lang/Throwable;
    //   328: athrow
    //   329: iconst_0
    //   330: ireturn
    // Local variable table:
    //   start	length	slot	name	signature
    //   0	331	0	this	ssssst
    //   10	152	1	i	int
    //   62	232	2	localObject	Object
    //   305	2	2	localInvocationTargetException1	java.lang.reflect.InvocationTargetException
    //   311	2	2	localInvocationTargetException2	java.lang.reflect.InvocationTargetException
    //   317	2	2	localInvocationTargetException3	java.lang.reflect.InvocationTargetException
    //   323	2	2	localInvocationTargetException4	java.lang.reflect.InvocationTargetException
    // Exception table:
    //   from	to	target	type
    //   246	256	305	java/lang/reflect/InvocationTargetException
    //   283	293	311	java/lang/reflect/InvocationTargetException
    //   208	218	317	java/lang/reflect/InvocationTargetException
    //   63	73	323	java/lang/reflect/InvocationTargetException
  }
}
