package uuuuuu;

import com.db.pwcc.dbmobile.secure.preferences.SharedPreferencesHelper;
import java.lang.reflect.InvocationTargetException;
import java.lang.reflect.Method;
import java.util.HashSet;
import java.util.Set;
import javax.inject.Inject;
import xxxxxx.uxxxxx;

public class sssxxx
{
  public static int b00660066f0066f0066f00660066 = 0;
  public static int b0066f00660066f0066f00660066 = 1;
  public static final int bf00660066ff0066f00660066 = -1;
  public static int bf0066f0066f0066f00660066 = 78;
  public static int bff00660066f0066f00660066 = 2;
  @Inject
  public bmmbbb b006600660066ff0066f00660066;
  private Set<String> b0066ff0066f0066f00660066;
  @Inject
  public SharedPreferencesHelper bfff0066f0066f00660066;
  
  public sssxxx()
  {
    pqqppq.b006B006B006Bkkk006Bkkk().b00700070pppppppp(this);
    this.b0066ff0066f0066f00660066 = new HashSet();
  }
  
  public static int b006B006Bk006Bk006B006B006B006B006B()
  {
    return 1;
  }
  
  public static int bk006Bk006Bk006B006B006B006B006B()
  {
    return 0;
  }
  
  /* Error */
  private void bk006Bkk006B006B006B006B006B006B(String paramString, int paramInt)
  {
    // Byte code:
    //   0: aload_0
    //   1: getfield 54	uuuuuu/sssxxx:bfff0066f0066f00660066	Lcom/db/pwcc/dbmobile/secure/preferences/SharedPreferencesHelper;
    //   4: astore 7
    //   6: ldc 56
    //   8: ldc 58
    //   10: bipush 119
    //   12: iconst_2
    //   13: invokestatic 64	xxxxxx/uxxxxx:bb00620062bb0062b0062b0062	(Ljava/lang/String;CC)Ljava/lang/String;
    //   16: iconst_2
    //   17: anewarray 66	java/lang/Class
    //   20: dup
    //   21: iconst_0
    //   22: ldc 68
    //   24: aastore
    //   25: dup
    //   26: iconst_1
    //   27: getstatic 74	java/lang/Integer:TYPE	Ljava/lang/Class;
    //   30: aastore
    //   31: invokevirtual 78	java/lang/Class:getMethod	(Ljava/lang/String;[Ljava/lang/Class;)Ljava/lang/reflect/Method;
    //   34: astore 8
    //   36: aload 8
    //   38: aload 7
    //   40: iconst_2
    //   41: anewarray 4	java/lang/Object
    //   44: dup
    //   45: iconst_0
    //   46: aload_1
    //   47: aastore
    //   48: dup
    //   49: iconst_1
    //   50: iconst_0
    //   51: invokestatic 82	java/lang/Integer:valueOf	(I)Ljava/lang/Integer;
    //   54: aastore
    //   55: invokevirtual 88	java/lang/reflect/Method:invoke	(Ljava/lang/Object;[Ljava/lang/Object;)Ljava/lang/Object;
    //   58: pop
    //   59: getstatic 90	uuuuuu/sssxxx:bf0066f0066f0066f00660066	I
    //   62: istore_3
    //   63: getstatic 92	uuuuuu/sssxxx:b0066f00660066f0066f00660066	I
    //   66: istore 4
    //   68: getstatic 94	uuuuuu/sssxxx:bff00660066f0066f00660066	I
    //   71: istore 5
    //   73: getstatic 90	uuuuuu/sssxxx:bf0066f0066f0066f00660066	I
    //   76: istore 6
    //   78: iload 6
    //   80: invokestatic 96	uuuuuu/sssxxx:b006B006Bk006Bk006B006B006B006B006B	()I
    //   83: iload 6
    //   85: iadd
    //   86: imul
    //   87: getstatic 94	uuuuuu/sssxxx:bff00660066f0066f00660066	I
    //   90: irem
    //   91: tableswitch	default:+17->108, 0:+28->119
    //   108: bipush 74
    //   110: putstatic 90	uuuuuu/sssxxx:bf0066f0066f0066f00660066	I
    //   113: invokestatic 99	uuuuuu/sssxxx:bkk006B006Bk006B006B006B006B006B	()I
    //   116: putstatic 101	uuuuuu/sssxxx:b00660066f0066f0066f00660066	I
    //   119: iload_3
    //   120: iload 4
    //   122: iload_3
    //   123: iadd
    //   124: imul
    //   125: iload 5
    //   127: irem
    //   128: tableswitch	default:+20->148, 0:+30->158
    //   148: bipush 75
    //   150: putstatic 90	uuuuuu/sssxxx:bf0066f0066f0066f00660066	I
    //   153: bipush 43
    //   155: putstatic 101	uuuuuu/sssxxx:b00660066f0066f0066f00660066	I
    //   158: aload_0
    //   159: getfield 54	uuuuuu/sssxxx:bfff0066f0066f00660066	Lcom/db/pwcc/dbmobile/secure/preferences/SharedPreferencesHelper;
    //   162: astore 7
    //   164: ldc 56
    //   166: ldc 103
    //   168: sipush 139
    //   171: iconst_4
    //   172: invokestatic 64	xxxxxx/uxxxxx:bb00620062bb0062b0062b0062	(Ljava/lang/String;CC)Ljava/lang/String;
    //   175: iconst_2
    //   176: anewarray 66	java/lang/Class
    //   179: dup
    //   180: iconst_0
    //   181: ldc 68
    //   183: aastore
    //   184: dup
    //   185: iconst_1
    //   186: getstatic 74	java/lang/Integer:TYPE	Ljava/lang/Class;
    //   189: aastore
    //   190: invokevirtual 78	java/lang/Class:getMethod	(Ljava/lang/String;[Ljava/lang/Class;)Ljava/lang/reflect/Method;
    //   193: astore 8
    //   195: aload 8
    //   197: aload 7
    //   199: iconst_2
    //   200: anewarray 4	java/lang/Object
    //   203: dup
    //   204: iconst_0
    //   205: aload_1
    //   206: aastore
    //   207: dup
    //   208: iconst_1
    //   209: iload_2
    //   210: invokestatic 82	java/lang/Integer:valueOf	(I)Ljava/lang/Integer;
    //   213: aastore
    //   214: invokevirtual 88	java/lang/reflect/Method:invoke	(Ljava/lang/Object;[Ljava/lang/Object;)Ljava/lang/Object;
    //   217: pop
    //   218: return
    //   219: astore_1
    //   220: aload_1
    //   221: invokevirtual 107	java/lang/reflect/InvocationTargetException:getCause	()Ljava/lang/Throwable;
    //   224: athrow
    //   225: astore_1
    //   226: aload_1
    //   227: invokevirtual 107	java/lang/reflect/InvocationTargetException:getCause	()Ljava/lang/Throwable;
    //   230: athrow
    // Local variable table:
    //   start	length	slot	name	signature
    //   0	231	0	this	sssxxx
    //   0	231	1	paramString	String
    //   0	231	2	paramInt	int
    //   62	63	3	i	int
    //   66	58	4	j	int
    //   71	57	5	k	int
    //   76	11	6	m	int
    //   4	194	7	localSharedPreferencesHelper	SharedPreferencesHelper
    //   34	162	8	localMethod	Method
    // Exception table:
    //   from	to	target	type
    //   195	218	219	java/lang/reflect/InvocationTargetException
    //   36	59	225	java/lang/reflect/InvocationTargetException
  }
  
  public static int bkk006B006Bk006B006B006B006B006B()
  {
    return 6;
  }
  
  private boolean bkkkk006B006B006B006B006B006B(String paramString)
  {
    int i = this.b006600660066ff0066f00660066.baa0061a006100610061aaa();
    if ((bf0066f0066f0066f00660066 + b006B006Bk006Bk006B006B006B006B006B()) * bf0066f0066f0066f00660066 % bff00660066f0066f00660066 != b00660066f0066f0066f00660066)
    {
      bf0066f0066f0066f00660066 = bkk006B006Bk006B006B006B006B006B();
      b00660066f0066f0066f00660066 = 34;
    }
    SharedPreferencesHelper localSharedPreferencesHelper = this.bfff0066f0066f00660066;
    Method localMethod = SharedPreferencesHelper.class.getMethod(uxxxxx.bbbb0062b0062b0062b0062("_\\jJgTYV3^c[`;Y\\\\WUSIG8FRRGLJ", 'å', '!', '\000'), new Class[] { String.class });
    try
    {
      paramString = localMethod.invoke(localSharedPreferencesHelper, new Object[] { paramString });
      int j = ((Integer)paramString).intValue();
      if (j != -1)
      {
        if (i > j) {
          break label163;
        }
        i = bf0066f0066f0066f00660066;
        switch (i * (b0066f00660066f0066f00660066 + i) % bff00660066f0066f00660066)
        {
        default: 
          bf0066f0066f0066f00660066 = 21;
          b00660066f0066f0066f00660066 = bkk006B006Bk006B006B006B006B006B();
        }
      }
      return true;
    }
    catch (InvocationTargetException paramString)
    {
      throw paramString.getCause();
    }
    label163:
    return false;
  }
  
  public int b006B006B006B006Bk006B006B006B006B006B(String paramString)
  {
    SharedPreferencesHelper localSharedPreferencesHelper = this.bfff0066f0066f00660066;
    if ((bf0066f0066f0066f00660066 + b0066f00660066f0066f00660066) * bf0066f0066f0066f00660066 % bff00660066f0066f00660066 != b00660066f0066f0066f00660066)
    {
      bf0066f0066f0066f00660066 = bkk006B006Bk006B006B006B006B006B();
      b00660066f0066f0066f00660066 = bkk006B006Bk006B006B006B006B006B();
      if ((bf0066f0066f0066f00660066 + b0066f00660066f0066f00660066) * bf0066f0066f0066f00660066 % bff00660066f0066f00660066 != b00660066f0066f0066f00660066)
      {
        bf0066f0066f0066f00660066 = bkk006B006Bk006B006B006B006B006B();
        b00660066f0066f0066f00660066 = 6;
      }
    }
    Method localMethod = SharedPreferencesHelper.class.getMethod(uxxxxx.bbbb0062b0062b0062b0062("\002\001\021r\022\001\b\007\026f\024\033\025\034", 'X', 'À', '\003'), new Class[] { String.class });
    try
    {
      paramString = localMethod.invoke(localSharedPreferencesHelper, new Object[] { paramString });
      return ((Integer)paramString).intValue();
    }
    catch (InvocationTargetException paramString)
    {
      throw paramString.getCause();
    }
  }
  
  public void b006B006Bkk006B006B006B006B006B006B(String paramString)
  {
    if ((bf0066f0066f0066f00660066 + b0066f00660066f0066f00660066) * bf0066f0066f0066f00660066 % bff00660066f0066f00660066 != b00660066f0066f0066f00660066)
    {
      if ((bf0066f0066f0066f00660066 + b0066f00660066f0066f00660066) * bf0066f0066f0066f00660066 % bff00660066f0066f00660066 != bk006Bk006Bk006B006B006B006B006B())
      {
        bf0066f0066f0066f00660066 = 27;
        b00660066f0066f0066f00660066 = bkk006B006Bk006B006B006B006B006B();
      }
      bf0066f0066f0066f00660066 = bkk006B006Bk006B006B006B006B006B();
      b00660066f0066f0066f00660066 = 58;
    }
    bk006Bkk006B006B006B006B006B006B(paramString, -1);
  }
  
  public boolean b006Bk006B006Bk006B006B006B006B006B(String paramString)
  {
    if ((bkkkk006B006B006B006B006B006B(paramString)) || (this.b0066ff0066f0066f00660066.contains(paramString))) {
      return false;
    }
    this.b0066ff0066f0066f00660066.add(paramString);
    int i = b006B006B006B006Bk006B006B006B006B006B(paramString);
    SharedPreferencesHelper localSharedPreferencesHelper = this.bfff0066f0066f00660066;
    Method localMethod = SharedPreferencesHelper.class.getMethod(uxxxxx.bb00620062bb0062b0062b0062("_P^>[HMJW&QVNS", '', '\003'), new Class[] { String.class, Integer.TYPE });
    try
    {
      localMethod.invoke(localSharedPreferencesHelper, new Object[] { paramString, Integer.valueOf(i + 1) });
      i = bf0066f0066f0066f00660066;
      switch (i * (b0066f00660066f0066f00660066 + i) % bff00660066f0066f00660066)
      {
      default: 
        if ((bf0066f0066f0066f00660066 + b006B006Bk006Bk006B006B006B006B006B()) * bf0066f0066f0066f00660066 % bff00660066f0066f00660066 != b00660066f0066f0066f00660066)
        {
          bf0066f0066f0066f00660066 = bkk006B006Bk006B006B006B006B006B();
          b00660066f0066f0066f00660066 = bkk006B006Bk006B006B006B006B006B();
        }
        bf0066f0066f0066f00660066 = bkk006B006Bk006B006B006B006B006B();
        b00660066f0066f0066f00660066 = bkk006B006Bk006B006B006B006B006B();
        return true;
      }
    }
    catch (InvocationTargetException paramString)
    {
      throw paramString.getCause();
    }
    return true;
  }
  
  public void b006Bkkk006B006B006B006B006B006B(String paramString)
  {
    int i = bf0066f0066f0066f00660066;
    switch (i * (b0066f00660066f0066f00660066 + i) % bff00660066f0066f00660066)
    {
    default: 
      i = bf0066f0066f0066f00660066;
      switch (i * (b0066f00660066f0066f00660066 + i) % bff00660066f0066f00660066)
      {
      default: 
        bf0066f0066f0066f00660066 = bkk006B006Bk006B006B006B006B006B();
        b00660066f0066f0066f00660066 = bkk006B006Bk006B006B006B006B006B();
      }
      bf0066f0066f0066f00660066 = bkk006B006Bk006B006B006B006B006B();
      b00660066f0066f0066f00660066 = 98;
    }
    bk006Bkk006B006B006B006B006B006B(paramString, this.b006600660066ff0066f00660066.baa0061a006100610061aaa());
  }
  
  public void bk006B006B006Bk006B006B006B006B006B()
  {
    Set localSet = this.b0066ff0066f0066f00660066;
    if ((bf0066f0066f0066f00660066 + b0066f00660066f0066f00660066) * bf0066f0066f0066f00660066 % bff00660066f0066f00660066 != b00660066f0066f0066f00660066)
    {
      bf0066f0066f0066f00660066 = bkk006B006Bk006B006B006B006B006B();
      b00660066f0066f0066f00660066 = 16;
      if ((bf0066f0066f0066f00660066 + b0066f00660066f0066f00660066) * bf0066f0066f0066f00660066 % bff00660066f0066f00660066 != b00660066f0066f0066f00660066)
      {
        bf0066f0066f0066f00660066 = bkk006B006Bk006B006B006B006B006B();
        b00660066f0066f0066f00660066 = 29;
      }
    }
    localSet.clear();
  }
}
