package uuuuuu;

import javax.inject.Inject;

public class sstsss
  extends ssssst<tttsss.tstsss>
  implements tttsss.sttsss
{
  public static int b006E006E006E006En006E006En006E = 2;
  public static int b006En006E006En006E006En006E = 21;
  public static int bn006E006E006En006E006En006E = 1;
  public static int bnnnn006E006E006En006E;
  @Inject
  public xsxsxs bnn006E006En006E006En006E;
  
  public sstsss()
  {
    pqqppq.b006B006B006Bkkk006Bkkk().ba00610061a006100610061006100610061(this);
  }
  
  public static int b006B006Bkk006B006Bk006B006Bk()
  {
    return 0;
  }
  
  public static int b006Bk006Bk006B006Bk006B006Bk()
  {
    return 2;
  }
  
  public static int b006Bkkk006B006Bk006B006Bk()
  {
    return 1;
  }
  
  public static int bk006Bkk006B006Bk006B006Bk()
  {
    return 87;
  }
  
  /* Error */
  public void b006B006B006B006Bk006Bk006B006Bk()
  {
    // Byte code:
    //   0: getstatic 49	uuuuuu/vvrvrv:bh00680068006800680068hh0068	Luuuuuu/vvrvrv;
    //   3: astore_3
    //   4: getstatic 51	uuuuuu/sstsss:b006En006E006En006E006En006E	I
    //   7: istore_1
    //   8: iload_1
    //   9: getstatic 53	uuuuuu/sstsss:bn006E006E006En006E006En006E	I
    //   12: iload_1
    //   13: iadd
    //   14: imul
    //   15: getstatic 55	uuuuuu/sstsss:b006E006E006E006En006E006En006E	I
    //   18: irem
    //   19: tableswitch	default:+17->36, 0:+267->286
    //   36: getstatic 51	uuuuuu/sstsss:b006En006E006En006E006En006E	I
    //   39: getstatic 53	uuuuuu/sstsss:bn006E006E006En006E006En006E	I
    //   42: iadd
    //   43: getstatic 51	uuuuuu/sstsss:b006En006E006En006E006En006E	I
    //   46: imul
    //   47: getstatic 55	uuuuuu/sstsss:b006E006E006E006En006E006En006E	I
    //   50: irem
    //   51: getstatic 57	uuuuuu/sstsss:bnnnn006E006E006En006E	I
    //   54: if_icmpeq +54 -> 108
    //   57: bipush 13
    //   59: putstatic 51	uuuuuu/sstsss:b006En006E006En006E006En006E	I
    //   62: ldc 2
    //   64: ldc 59
    //   66: sipush 171
    //   69: sipush 197
    //   72: iconst_0
    //   73: invokestatic 65	xxxxxx/uxxxxx:bbbb0062b0062b0062b0062	(Ljava/lang/String;CCC)Ljava/lang/String;
    //   76: iconst_0
    //   77: anewarray 67	java/lang/Class
    //   80: invokevirtual 71	java/lang/Class:getMethod	(Ljava/lang/String;[Ljava/lang/Class;)Ljava/lang/reflect/Method;
    //   83: astore 4
    //   85: aload 4
    //   87: aconst_null
    //   88: iconst_0
    //   89: anewarray 73	java/lang/Object
    //   92: invokevirtual 79	java/lang/reflect/Method:invoke	(Ljava/lang/Object;[Ljava/lang/Object;)Ljava/lang/Object;
    //   95: astore 4
    //   97: aload 4
    //   99: checkcast 81	java/lang/Integer
    //   102: invokevirtual 84	java/lang/Integer:intValue	()I
    //   105: putstatic 57	uuuuuu/sstsss:bnnnn006E006E006En006E	I
    //   108: bipush 80
    //   110: putstatic 51	uuuuuu/sstsss:b006En006E006En006E006En006E	I
    //   113: ldc 2
    //   115: ldc 86
    //   117: sipush 179
    //   120: sipush 234
    //   123: iconst_1
    //   124: invokestatic 65	xxxxxx/uxxxxx:bbbb0062b0062b0062b0062	(Ljava/lang/String;CCC)Ljava/lang/String;
    //   127: iconst_0
    //   128: anewarray 67	java/lang/Class
    //   131: invokevirtual 71	java/lang/Class:getMethod	(Ljava/lang/String;[Ljava/lang/Class;)Ljava/lang/reflect/Method;
    //   134: astore 4
    //   136: aload 4
    //   138: aconst_null
    //   139: iconst_0
    //   140: anewarray 73	java/lang/Object
    //   143: invokevirtual 79	java/lang/reflect/Method:invoke	(Ljava/lang/Object;[Ljava/lang/Object;)Ljava/lang/Object;
    //   146: astore 4
    //   148: aload 4
    //   150: checkcast 81	java/lang/Integer
    //   153: invokevirtual 84	java/lang/Integer:intValue	()I
    //   156: istore_1
    //   157: getstatic 51	uuuuuu/sstsss:b006En006E006En006E006En006E	I
    //   160: istore_2
    //   161: iload_2
    //   162: getstatic 53	uuuuuu/sstsss:bn006E006E006En006E006En006E	I
    //   165: iload_2
    //   166: iadd
    //   167: imul
    //   168: getstatic 55	uuuuuu/sstsss:b006E006E006E006En006E006En006E	I
    //   171: irem
    //   172: tableswitch	default:+20->192, 0:+68->240
    //   192: bipush 34
    //   194: putstatic 51	uuuuuu/sstsss:b006En006E006En006E006En006E	I
    //   197: ldc 2
    //   199: ldc 88
    //   201: sipush 195
    //   204: iconst_0
    //   205: invokestatic 92	xxxxxx/uxxxxx:bb00620062bb0062b0062b0062	(Ljava/lang/String;CC)Ljava/lang/String;
    //   208: iconst_0
    //   209: anewarray 67	java/lang/Class
    //   212: invokevirtual 71	java/lang/Class:getMethod	(Ljava/lang/String;[Ljava/lang/Class;)Ljava/lang/reflect/Method;
    //   215: astore 4
    //   217: aload 4
    //   219: aconst_null
    //   220: iconst_0
    //   221: anewarray 73	java/lang/Object
    //   224: invokevirtual 79	java/lang/reflect/Method:invoke	(Ljava/lang/Object;[Ljava/lang/Object;)Ljava/lang/Object;
    //   227: astore 4
    //   229: aload 4
    //   231: checkcast 81	java/lang/Integer
    //   234: invokevirtual 84	java/lang/Integer:intValue	()I
    //   237: putstatic 57	uuuuuu/sstsss:bnnnn006E006E006En006E	I
    //   240: iload_1
    //   241: putstatic 57	uuuuuu/sstsss:bnnnn006E006E006En006E	I
    //   244: getstatic 51	uuuuuu/sstsss:b006En006E006En006E006En006E	I
    //   247: istore_1
    //   248: iload_1
    //   249: getstatic 53	uuuuuu/sstsss:bn006E006E006En006E006En006E	I
    //   252: iload_1
    //   253: iadd
    //   254: imul
    //   255: getstatic 55	uuuuuu/sstsss:b006E006E006E006En006E006En006E	I
    //   258: irem
    //   259: tableswitch	default:+17->276, 0:+27->286
    //   276: bipush 64
    //   278: putstatic 51	uuuuuu/sstsss:b006En006E006En006E006En006E	I
    //   281: bipush 48
    //   283: putstatic 57	uuuuuu/sstsss:bnnnn006E006E006En006E	I
    //   286: aload_3
    //   287: invokestatic 98	uuuuuu/rrvvrv:b0071q0071qq0071q0071q0071	(Luuuuuu/vvrvrv;)V
    //   290: aload_0
    //   291: getfield 102	uuuuuu/sstsss:bnnnnn006E006E006En	Luuuuuu/ttssst$tsssst;
    //   294: checkcast 104	uuuuuu/tttsss$tstsss
    //   297: invokeinterface 107 1 0
    //   302: return
    //   303: astore_3
    //   304: aload_3
    //   305: invokevirtual 111	java/lang/reflect/InvocationTargetException:getCause	()Ljava/lang/Throwable;
    //   308: athrow
    //   309: astore_3
    //   310: aload_3
    //   311: invokevirtual 111	java/lang/reflect/InvocationTargetException:getCause	()Ljava/lang/Throwable;
    //   314: athrow
    //   315: astore_3
    //   316: aload_3
    //   317: invokevirtual 111	java/lang/reflect/InvocationTargetException:getCause	()Ljava/lang/Throwable;
    //   320: athrow
    // Local variable table:
    //   start	length	slot	name	signature
    //   0	321	0	this	sstsss
    //   7	248	1	i	int
    //   160	8	2	j	int
    //   3	284	3	localVvrvrv	vvrvrv
    //   303	2	3	localInvocationTargetException1	java.lang.reflect.InvocationTargetException
    //   309	2	3	localInvocationTargetException2	java.lang.reflect.InvocationTargetException
    //   315	2	3	localInvocationTargetException3	java.lang.reflect.InvocationTargetException
    //   83	147	4	localObject	Object
    // Exception table:
    //   from	to	target	type
    //   136	148	303	java/lang/reflect/InvocationTargetException
    //   217	229	309	java/lang/reflect/InvocationTargetException
    //   85	97	315	java/lang/reflect/InvocationTargetException
  }
  
  /* Error */
  public void bk006B006Bk006B006Bk006B006Bk()
  {
    // Byte code:
    //   0: aload_0
    //   1: invokevirtual 130	uuuuuu/sstsss:bkk006Bk006Bk006Bk006Bk	()Z
    //   4: ifeq +298 -> 302
    //   7: aload_0
    //   8: getfield 102	uuuuuu/sstsss:bnnnnn006E006E006En	Luuuuuu/ttssst$tsssst;
    //   11: checkcast 104	uuuuuu/tttsss$tstsss
    //   14: astore_2
    //   15: aload_0
    //   16: getfield 132	uuuuuu/sstsss:bnn006E006En006E006En006E	Luuuuuu/xsxsxs;
    //   19: astore_3
    //   20: getstatic 51	uuuuuu/sstsss:b006En006E006En006E006En006E	I
    //   23: getstatic 53	uuuuuu/sstsss:bn006E006E006En006E006En006E	I
    //   26: iadd
    //   27: getstatic 51	uuuuuu/sstsss:b006En006E006En006E006En006E	I
    //   30: imul
    //   31: getstatic 55	uuuuuu/sstsss:b006E006E006E006En006E006En006E	I
    //   34: irem
    //   35: getstatic 57	uuuuuu/sstsss:bnnnn006E006E006En006E	I
    //   38: if_icmpeq +254 -> 292
    //   41: getstatic 51	uuuuuu/sstsss:b006En006E006En006E006En006E	I
    //   44: istore_1
    //   45: ldc 2
    //   47: ldc -122
    //   49: bipush 38
    //   51: iconst_4
    //   52: invokestatic 92	xxxxxx/uxxxxx:bb00620062bb0062b0062b0062	(Ljava/lang/String;CC)Ljava/lang/String;
    //   55: iconst_0
    //   56: anewarray 67	java/lang/Class
    //   59: invokevirtual 71	java/lang/Class:getMethod	(Ljava/lang/String;[Ljava/lang/Class;)Ljava/lang/reflect/Method;
    //   62: astore 4
    //   64: aload 4
    //   66: aconst_null
    //   67: iconst_0
    //   68: anewarray 73	java/lang/Object
    //   71: invokevirtual 79	java/lang/reflect/Method:invoke	(Ljava/lang/Object;[Ljava/lang/Object;)Ljava/lang/Object;
    //   74: astore 4
    //   76: aload 4
    //   78: checkcast 81	java/lang/Integer
    //   81: invokevirtual 84	java/lang/Integer:intValue	()I
    //   84: iload_1
    //   85: iadd
    //   86: iload_1
    //   87: imul
    //   88: getstatic 55	uuuuuu/sstsss:b006E006E006E006En006E006En006E	I
    //   91: irem
    //   92: tableswitch	default:+20->112, 0:+72->164
    //   112: getstatic 51	uuuuuu/sstsss:b006En006E006En006E006En006E	I
    //   115: istore_1
    //   116: iload_1
    //   117: getstatic 53	uuuuuu/sstsss:bn006E006E006En006E006En006E	I
    //   120: iload_1
    //   121: iadd
    //   122: imul
    //   123: getstatic 55	uuuuuu/sstsss:b006E006E006E006En006E006En006E	I
    //   126: irem
    //   127: tableswitch	default:+17->144, 0:+27->154
    //   144: bipush 95
    //   146: putstatic 51	uuuuuu/sstsss:b006En006E006En006E006En006E	I
    //   149: bipush 9
    //   151: putstatic 57	uuuuuu/sstsss:bnnnn006E006E006En006E	I
    //   154: bipush 63
    //   156: putstatic 51	uuuuuu/sstsss:b006En006E006En006E006En006E	I
    //   159: bipush 33
    //   161: putstatic 57	uuuuuu/sstsss:bnnnn006E006E006En006E	I
    //   164: getstatic 51	uuuuuu/sstsss:b006En006E006En006E006En006E	I
    //   167: istore_1
    //   168: iload_1
    //   169: getstatic 53	uuuuuu/sstsss:bn006E006E006En006E006En006E	I
    //   172: iload_1
    //   173: iadd
    //   174: imul
    //   175: getstatic 55	uuuuuu/sstsss:b006E006E006E006En006E006En006E	I
    //   178: irem
    //   179: tableswitch	default:+17->196, 0:+27->206
    //   196: bipush 78
    //   198: putstatic 51	uuuuuu/sstsss:b006En006E006En006E006En006E	I
    //   201: bipush 40
    //   203: putstatic 57	uuuuuu/sstsss:bnnnn006E006E006En006E	I
    //   206: ldc 2
    //   208: ldc -120
    //   210: sipush 170
    //   213: iconst_1
    //   214: invokestatic 92	xxxxxx/uxxxxx:bb00620062bb0062b0062b0062	(Ljava/lang/String;CC)Ljava/lang/String;
    //   217: iconst_0
    //   218: anewarray 67	java/lang/Class
    //   221: invokevirtual 71	java/lang/Class:getMethod	(Ljava/lang/String;[Ljava/lang/Class;)Ljava/lang/reflect/Method;
    //   224: astore 4
    //   226: aload 4
    //   228: aconst_null
    //   229: iconst_0
    //   230: anewarray 73	java/lang/Object
    //   233: invokevirtual 79	java/lang/reflect/Method:invoke	(Ljava/lang/Object;[Ljava/lang/Object;)Ljava/lang/Object;
    //   236: astore 4
    //   238: aload 4
    //   240: checkcast 81	java/lang/Integer
    //   243: invokevirtual 84	java/lang/Integer:intValue	()I
    //   246: putstatic 51	uuuuuu/sstsss:b006En006E006En006E006En006E	I
    //   249: ldc 2
    //   251: ldc -118
    //   253: sipush 150
    //   256: iconst_1
    //   257: invokestatic 92	xxxxxx/uxxxxx:bb00620062bb0062b0062b0062	(Ljava/lang/String;CC)Ljava/lang/String;
    //   260: iconst_0
    //   261: anewarray 67	java/lang/Class
    //   264: invokevirtual 71	java/lang/Class:getMethod	(Ljava/lang/String;[Ljava/lang/Class;)Ljava/lang/reflect/Method;
    //   267: astore 4
    //   269: aload 4
    //   271: aconst_null
    //   272: iconst_0
    //   273: anewarray 73	java/lang/Object
    //   276: invokevirtual 79	java/lang/reflect/Method:invoke	(Ljava/lang/Object;[Ljava/lang/Object;)Ljava/lang/Object;
    //   279: astore 4
    //   281: aload 4
    //   283: checkcast 81	java/lang/Integer
    //   286: invokevirtual 84	java/lang/Integer:intValue	()I
    //   289: putstatic 57	uuuuuu/sstsss:bnnnn006E006E006En006E	I
    //   292: aload_2
    //   293: aload_3
    //   294: invokevirtual 143	uuuuuu/xsxsxs:bk006Bkk006B006Bkk006B006B	()I
    //   297: invokeinterface 147 2 0
    //   302: return
    //   303: astore_2
    //   304: aload_2
    //   305: invokevirtual 111	java/lang/reflect/InvocationTargetException:getCause	()Ljava/lang/Throwable;
    //   308: athrow
    //   309: astore_2
    //   310: aload_2
    //   311: invokevirtual 111	java/lang/reflect/InvocationTargetException:getCause	()Ljava/lang/Throwable;
    //   314: athrow
    //   315: astore_2
    //   316: aload_2
    //   317: invokevirtual 111	java/lang/reflect/InvocationTargetException:getCause	()Ljava/lang/Throwable;
    //   320: athrow
    // Local variable table:
    //   start	length	slot	name	signature
    //   0	321	0	this	sstsss
    //   44	131	1	i	int
    //   14	279	2	localTstsss	tttsss.tstsss
    //   303	2	2	localInvocationTargetException1	java.lang.reflect.InvocationTargetException
    //   309	2	2	localInvocationTargetException2	java.lang.reflect.InvocationTargetException
    //   315	2	2	localInvocationTargetException3	java.lang.reflect.InvocationTargetException
    //   19	275	3	localXsxsxs	xsxsxs
    //   62	220	4	localObject	Object
    // Exception table:
    //   from	to	target	type
    //   226	238	303	java/lang/reflect/InvocationTargetException
    //   269	281	309	java/lang/reflect/InvocationTargetException
    //   64	76	315	java/lang/reflect/InvocationTargetException
  }
  
  /* Error */
  public void bkk006Bk006B006Bk006B006Bk(tttsss.tstsss paramTstsss)
  {
    // Byte code:
    //   0: getstatic 51	uuuuuu/sstsss:b006En006E006En006E006En006E	I
    //   3: istore_2
    //   4: getstatic 53	uuuuuu/sstsss:bn006E006E006En006E006En006E	I
    //   7: istore_3
    //   8: ldc 2
    //   10: ldc -105
    //   12: sipush 238
    //   15: sipush 231
    //   18: iconst_0
    //   19: invokestatic 65	xxxxxx/uxxxxx:bbbb0062b0062b0062b0062	(Ljava/lang/String;CCC)Ljava/lang/String;
    //   22: iconst_0
    //   23: anewarray 67	java/lang/Class
    //   26: invokevirtual 71	java/lang/Class:getMethod	(Ljava/lang/String;[Ljava/lang/Class;)Ljava/lang/reflect/Method;
    //   29: astore 4
    //   31: aload 4
    //   33: aconst_null
    //   34: iconst_0
    //   35: anewarray 73	java/lang/Object
    //   38: invokevirtual 79	java/lang/reflect/Method:invoke	(Ljava/lang/Object;[Ljava/lang/Object;)Ljava/lang/Object;
    //   41: astore 4
    //   43: iload_3
    //   44: iload_2
    //   45: iadd
    //   46: iload_2
    //   47: imul
    //   48: aload 4
    //   50: checkcast 81	java/lang/Integer
    //   53: invokevirtual 84	java/lang/Integer:intValue	()I
    //   56: irem
    //   57: tableswitch	default:+19->76, 0:+135->192
    //   76: ldc 2
    //   78: ldc -103
    //   80: sipush 204
    //   83: iconst_3
    //   84: invokestatic 92	xxxxxx/uxxxxx:bb00620062bb0062b0062b0062	(Ljava/lang/String;CC)Ljava/lang/String;
    //   87: iconst_0
    //   88: anewarray 67	java/lang/Class
    //   91: invokevirtual 71	java/lang/Class:getMethod	(Ljava/lang/String;[Ljava/lang/Class;)Ljava/lang/reflect/Method;
    //   94: astore 4
    //   96: aload 4
    //   98: aconst_null
    //   99: iconst_0
    //   100: anewarray 73	java/lang/Object
    //   103: invokevirtual 79	java/lang/reflect/Method:invoke	(Ljava/lang/Object;[Ljava/lang/Object;)Ljava/lang/Object;
    //   106: astore 4
    //   108: aload 4
    //   110: checkcast 81	java/lang/Integer
    //   113: invokevirtual 84	java/lang/Integer:intValue	()I
    //   116: putstatic 51	uuuuuu/sstsss:b006En006E006En006E006En006E	I
    //   119: bipush 56
    //   121: putstatic 57	uuuuuu/sstsss:bnnnn006E006E006En006E	I
    //   124: getstatic 51	uuuuuu/sstsss:b006En006E006En006E006En006E	I
    //   127: getstatic 53	uuuuuu/sstsss:bn006E006E006En006E006En006E	I
    //   130: iadd
    //   131: getstatic 51	uuuuuu/sstsss:b006En006E006En006E006En006E	I
    //   134: imul
    //   135: getstatic 55	uuuuuu/sstsss:b006E006E006E006En006E006En006E	I
    //   138: irem
    //   139: getstatic 57	uuuuuu/sstsss:bnnnn006E006E006En006E	I
    //   142: if_icmpeq +50 -> 192
    //   145: bipush 93
    //   147: putstatic 51	uuuuuu/sstsss:b006En006E006En006E006En006E	I
    //   150: ldc 2
    //   152: ldc -101
    //   154: bipush 124
    //   156: iconst_4
    //   157: invokestatic 92	xxxxxx/uxxxxx:bb00620062bb0062b0062b0062	(Ljava/lang/String;CC)Ljava/lang/String;
    //   160: iconst_0
    //   161: anewarray 67	java/lang/Class
    //   164: invokevirtual 71	java/lang/Class:getMethod	(Ljava/lang/String;[Ljava/lang/Class;)Ljava/lang/reflect/Method;
    //   167: astore 4
    //   169: aload 4
    //   171: aconst_null
    //   172: iconst_0
    //   173: anewarray 73	java/lang/Object
    //   176: invokevirtual 79	java/lang/reflect/Method:invoke	(Ljava/lang/Object;[Ljava/lang/Object;)Ljava/lang/Object;
    //   179: astore 4
    //   181: aload 4
    //   183: checkcast 81	java/lang/Integer
    //   186: invokevirtual 84	java/lang/Integer:intValue	()I
    //   189: putstatic 57	uuuuuu/sstsss:bnnnn006E006E006En006E	I
    //   192: getstatic 51	uuuuuu/sstsss:b006En006E006En006E006En006E	I
    //   195: istore_2
    //   196: ldc 2
    //   198: ldc -99
    //   200: bipush 89
    //   202: iconst_3
    //   203: invokestatic 92	xxxxxx/uxxxxx:bb00620062bb0062b0062b0062	(Ljava/lang/String;CC)Ljava/lang/String;
    //   206: iconst_0
    //   207: anewarray 67	java/lang/Class
    //   210: invokevirtual 71	java/lang/Class:getMethod	(Ljava/lang/String;[Ljava/lang/Class;)Ljava/lang/reflect/Method;
    //   213: astore 4
    //   215: aload 4
    //   217: aconst_null
    //   218: iconst_0
    //   219: anewarray 73	java/lang/Object
    //   222: invokevirtual 79	java/lang/reflect/Method:invoke	(Ljava/lang/Object;[Ljava/lang/Object;)Ljava/lang/Object;
    //   225: astore 4
    //   227: aload 4
    //   229: checkcast 81	java/lang/Integer
    //   232: invokevirtual 84	java/lang/Integer:intValue	()I
    //   235: iload_2
    //   236: iadd
    //   237: iload_2
    //   238: imul
    //   239: getstatic 55	uuuuuu/sstsss:b006E006E006E006En006E006En006E	I
    //   242: irem
    //   243: tableswitch	default:+17->260, 0:+185->428
    //   260: getstatic 51	uuuuuu/sstsss:b006En006E006En006E006En006E	I
    //   263: istore_2
    //   264: iload_2
    //   265: getstatic 53	uuuuuu/sstsss:bn006E006E006En006E006En006E	I
    //   268: iload_2
    //   269: iadd
    //   270: imul
    //   271: getstatic 55	uuuuuu/sstsss:b006E006E006E006En006E006En006E	I
    //   274: irem
    //   275: tableswitch	default:+17->292, 0:+66->341
    //   292: bipush 86
    //   294: putstatic 51	uuuuuu/sstsss:b006En006E006En006E006En006E	I
    //   297: ldc 2
    //   299: ldc -97
    //   301: bipush 53
    //   303: bipush 26
    //   305: iconst_1
    //   306: invokestatic 65	xxxxxx/uxxxxx:bbbb0062b0062b0062b0062	(Ljava/lang/String;CCC)Ljava/lang/String;
    //   309: iconst_0
    //   310: anewarray 67	java/lang/Class
    //   313: invokevirtual 71	java/lang/Class:getMethod	(Ljava/lang/String;[Ljava/lang/Class;)Ljava/lang/reflect/Method;
    //   316: astore 4
    //   318: aload 4
    //   320: aconst_null
    //   321: iconst_0
    //   322: anewarray 73	java/lang/Object
    //   325: invokevirtual 79	java/lang/reflect/Method:invoke	(Ljava/lang/Object;[Ljava/lang/Object;)Ljava/lang/Object;
    //   328: astore 4
    //   330: aload 4
    //   332: checkcast 81	java/lang/Integer
    //   335: invokevirtual 84	java/lang/Integer:intValue	()I
    //   338: putstatic 57	uuuuuu/sstsss:bnnnn006E006E006En006E	I
    //   341: ldc 2
    //   343: ldc -95
    //   345: sipush 253
    //   348: bipush 86
    //   350: iconst_0
    //   351: invokestatic 65	xxxxxx/uxxxxx:bbbb0062b0062b0062b0062	(Ljava/lang/String;CCC)Ljava/lang/String;
    //   354: iconst_0
    //   355: anewarray 67	java/lang/Class
    //   358: invokevirtual 71	java/lang/Class:getMethod	(Ljava/lang/String;[Ljava/lang/Class;)Ljava/lang/reflect/Method;
    //   361: astore 4
    //   363: aload 4
    //   365: aconst_null
    //   366: iconst_0
    //   367: anewarray 73	java/lang/Object
    //   370: invokevirtual 79	java/lang/reflect/Method:invoke	(Ljava/lang/Object;[Ljava/lang/Object;)Ljava/lang/Object;
    //   373: astore 4
    //   375: aload 4
    //   377: checkcast 81	java/lang/Integer
    //   380: invokevirtual 84	java/lang/Integer:intValue	()I
    //   383: putstatic 51	uuuuuu/sstsss:b006En006E006En006E006En006E	I
    //   386: ldc 2
    //   388: ldc -93
    //   390: bipush 17
    //   392: iconst_1
    //   393: invokestatic 92	xxxxxx/uxxxxx:bb00620062bb0062b0062b0062	(Ljava/lang/String;CC)Ljava/lang/String;
    //   396: iconst_0
    //   397: anewarray 67	java/lang/Class
    //   400: invokevirtual 71	java/lang/Class:getMethod	(Ljava/lang/String;[Ljava/lang/Class;)Ljava/lang/reflect/Method;
    //   403: astore 4
    //   405: aload 4
    //   407: aconst_null
    //   408: iconst_0
    //   409: anewarray 73	java/lang/Object
    //   412: invokevirtual 79	java/lang/reflect/Method:invoke	(Ljava/lang/Object;[Ljava/lang/Object;)Ljava/lang/Object;
    //   415: astore 4
    //   417: aload 4
    //   419: checkcast 81	java/lang/Integer
    //   422: invokevirtual 84	java/lang/Integer:intValue	()I
    //   425: putstatic 57	uuuuuu/sstsss:bnnnn006E006E006En006E	I
    //   428: aload_0
    //   429: aload_1
    //   430: invokespecial 165	uuuuuu/ssssst:ba0061a0061a0061a0061aa	(Luuuuuu/ttssst$tsssst;)V
    //   433: ldc 2
    //   435: ldc -89
    //   437: sipush 193
    //   440: sipush 202
    //   443: iconst_2
    //   444: invokestatic 65	xxxxxx/uxxxxx:bbbb0062b0062b0062b0062	(Ljava/lang/String;CCC)Ljava/lang/String;
    //   447: iconst_0
    //   448: anewarray 67	java/lang/Class
    //   451: invokevirtual 71	java/lang/Class:getMethod	(Ljava/lang/String;[Ljava/lang/Class;)Ljava/lang/reflect/Method;
    //   454: astore_1
    //   455: aload_1
    //   456: aload_0
    //   457: iconst_0
    //   458: anewarray 73	java/lang/Object
    //   461: invokevirtual 79	java/lang/reflect/Method:invoke	(Ljava/lang/Object;[Ljava/lang/Object;)Ljava/lang/Object;
    //   464: pop
    //   465: return
    //   466: astore_1
    //   467: aload_1
    //   468: invokevirtual 111	java/lang/reflect/InvocationTargetException:getCause	()Ljava/lang/Throwable;
    //   471: athrow
    //   472: astore_1
    //   473: aload_1
    //   474: invokevirtual 111	java/lang/reflect/InvocationTargetException:getCause	()Ljava/lang/Throwable;
    //   477: athrow
    //   478: astore_1
    //   479: aload_1
    //   480: invokevirtual 111	java/lang/reflect/InvocationTargetException:getCause	()Ljava/lang/Throwable;
    //   483: athrow
    //   484: astore_1
    //   485: aload_1
    //   486: invokevirtual 111	java/lang/reflect/InvocationTargetException:getCause	()Ljava/lang/Throwable;
    //   489: athrow
    //   490: astore_1
    //   491: aload_1
    //   492: invokevirtual 111	java/lang/reflect/InvocationTargetException:getCause	()Ljava/lang/Throwable;
    //   495: athrow
    //   496: astore_1
    //   497: aload_1
    //   498: invokevirtual 111	java/lang/reflect/InvocationTargetException:getCause	()Ljava/lang/Throwable;
    //   501: athrow
    //   502: astore_1
    //   503: aload_1
    //   504: invokevirtual 111	java/lang/reflect/InvocationTargetException:getCause	()Ljava/lang/Throwable;
    //   507: athrow
    //   508: astore_1
    //   509: aload_1
    //   510: invokevirtual 111	java/lang/reflect/InvocationTargetException:getCause	()Ljava/lang/Throwable;
    //   513: athrow
    // Local variable table:
    //   start	length	slot	name	signature
    //   0	514	0	this	sstsss
    //   0	514	1	paramTstsss	tttsss.tstsss
    //   3	268	2	i	int
    //   7	39	3	j	int
    //   29	389	4	localObject	Object
    // Exception table:
    //   from	to	target	type
    //   455	465	466	java/lang/reflect/InvocationTargetException
    //   96	108	472	java/lang/reflect/InvocationTargetException
    //   363	375	478	java/lang/reflect/InvocationTargetException
    //   405	417	484	java/lang/reflect/InvocationTargetException
    //   31	43	490	java/lang/reflect/InvocationTargetException
    //   215	227	496	java/lang/reflect/InvocationTargetException
    //   169	181	502	java/lang/reflect/InvocationTargetException
    //   318	330	508	java/lang/reflect/InvocationTargetException
  }
  
  /* Error */
  public void bkkkk006B006Bk006B006Bk()
  {
    // Byte code:
    //   0: ldc 2
    //   2: ldc -86
    //   4: bipush 98
    //   6: bipush 77
    //   8: iconst_0
    //   9: invokestatic 65	xxxxxx/uxxxxx:bbbb0062b0062b0062b0062	(Ljava/lang/String;CCC)Ljava/lang/String;
    //   12: iconst_0
    //   13: anewarray 67	java/lang/Class
    //   16: invokevirtual 71	java/lang/Class:getMethod	(Ljava/lang/String;[Ljava/lang/Class;)Ljava/lang/reflect/Method;
    //   19: astore 5
    //   21: aload 5
    //   23: aload_0
    //   24: iconst_0
    //   25: anewarray 73	java/lang/Object
    //   28: invokevirtual 79	java/lang/reflect/Method:invoke	(Ljava/lang/Object;[Ljava/lang/Object;)Ljava/lang/Object;
    //   31: pop
    //   32: getstatic 51	uuuuuu/sstsss:b006En006E006En006E006En006E	I
    //   35: istore_1
    //   36: iload_1
    //   37: getstatic 53	uuuuuu/sstsss:bn006E006E006En006E006En006E	I
    //   40: iload_1
    //   41: iadd
    //   42: imul
    //   43: getstatic 55	uuuuuu/sstsss:b006E006E006E006En006E006En006E	I
    //   46: irem
    //   47: tableswitch	default:+17->64, 0:+327->374
    //   64: getstatic 51	uuuuuu/sstsss:b006En006E006En006E006En006E	I
    //   67: getstatic 53	uuuuuu/sstsss:bn006E006E006En006E006En006E	I
    //   70: iadd
    //   71: getstatic 51	uuuuuu/sstsss:b006En006E006En006E006En006E	I
    //   74: imul
    //   75: getstatic 55	uuuuuu/sstsss:b006E006E006E006En006E006En006E	I
    //   78: irem
    //   79: getstatic 57	uuuuuu/sstsss:bnnnn006E006E006En006E	I
    //   82: if_icmpeq +95 -> 177
    //   85: getstatic 51	uuuuuu/sstsss:b006En006E006En006E006En006E	I
    //   88: istore_1
    //   89: iload_1
    //   90: getstatic 53	uuuuuu/sstsss:bn006E006E006En006E006En006E	I
    //   93: iload_1
    //   94: iadd
    //   95: imul
    //   96: getstatic 55	uuuuuu/sstsss:b006E006E006E006En006E006En006E	I
    //   99: irem
    //   100: tableswitch	default:+20->120, 0:+67->167
    //   120: ldc 2
    //   122: ldc -84
    //   124: bipush 89
    //   126: iconst_3
    //   127: invokestatic 92	xxxxxx/uxxxxx:bb00620062bb0062b0062b0062	(Ljava/lang/String;CC)Ljava/lang/String;
    //   130: iconst_0
    //   131: anewarray 67	java/lang/Class
    //   134: invokevirtual 71	java/lang/Class:getMethod	(Ljava/lang/String;[Ljava/lang/Class;)Ljava/lang/reflect/Method;
    //   137: astore 5
    //   139: aload 5
    //   141: aconst_null
    //   142: iconst_0
    //   143: anewarray 73	java/lang/Object
    //   146: invokevirtual 79	java/lang/reflect/Method:invoke	(Ljava/lang/Object;[Ljava/lang/Object;)Ljava/lang/Object;
    //   149: astore 5
    //   151: aload 5
    //   153: checkcast 81	java/lang/Integer
    //   156: invokevirtual 84	java/lang/Integer:intValue	()I
    //   159: putstatic 51	uuuuuu/sstsss:b006En006E006En006E006En006E	I
    //   162: bipush 13
    //   164: putstatic 57	uuuuuu/sstsss:bnnnn006E006E006En006E	I
    //   167: bipush 91
    //   169: putstatic 51	uuuuuu/sstsss:b006En006E006En006E006En006E	I
    //   172: bipush 42
    //   174: putstatic 57	uuuuuu/sstsss:bnnnn006E006E006En006E	I
    //   177: ldc 2
    //   179: ldc -82
    //   181: sipush 154
    //   184: iconst_5
    //   185: invokestatic 92	xxxxxx/uxxxxx:bb00620062bb0062b0062b0062	(Ljava/lang/String;CC)Ljava/lang/String;
    //   188: iconst_0
    //   189: anewarray 67	java/lang/Class
    //   192: invokevirtual 71	java/lang/Class:getMethod	(Ljava/lang/String;[Ljava/lang/Class;)Ljava/lang/reflect/Method;
    //   195: astore 5
    //   197: aload 5
    //   199: aconst_null
    //   200: iconst_0
    //   201: anewarray 73	java/lang/Object
    //   204: invokevirtual 79	java/lang/reflect/Method:invoke	(Ljava/lang/Object;[Ljava/lang/Object;)Ljava/lang/Object;
    //   207: astore 5
    //   209: aload 5
    //   211: checkcast 81	java/lang/Integer
    //   214: invokevirtual 84	java/lang/Integer:intValue	()I
    //   217: istore_1
    //   218: getstatic 53	uuuuuu/sstsss:bn006E006E006En006E006En006E	I
    //   221: istore_2
    //   222: ldc 2
    //   224: ldc -80
    //   226: sipush 154
    //   229: iconst_0
    //   230: invokestatic 92	xxxxxx/uxxxxx:bb00620062bb0062b0062b0062	(Ljava/lang/String;CC)Ljava/lang/String;
    //   233: iconst_0
    //   234: anewarray 67	java/lang/Class
    //   237: invokevirtual 71	java/lang/Class:getMethod	(Ljava/lang/String;[Ljava/lang/Class;)Ljava/lang/reflect/Method;
    //   240: astore 5
    //   242: aload 5
    //   244: aconst_null
    //   245: iconst_0
    //   246: anewarray 73	java/lang/Object
    //   249: invokevirtual 79	java/lang/reflect/Method:invoke	(Ljava/lang/Object;[Ljava/lang/Object;)Ljava/lang/Object;
    //   252: astore 5
    //   254: aload 5
    //   256: checkcast 81	java/lang/Integer
    //   259: invokevirtual 84	java/lang/Integer:intValue	()I
    //   262: istore_3
    //   263: getstatic 55	uuuuuu/sstsss:b006E006E006E006En006E006En006E	I
    //   266: istore 4
    //   268: ldc 2
    //   270: ldc -78
    //   272: bipush 124
    //   274: iconst_5
    //   275: invokestatic 92	xxxxxx/uxxxxx:bb00620062bb0062b0062b0062	(Ljava/lang/String;CC)Ljava/lang/String;
    //   278: iconst_0
    //   279: anewarray 67	java/lang/Class
    //   282: invokevirtual 71	java/lang/Class:getMethod	(Ljava/lang/String;[Ljava/lang/Class;)Ljava/lang/reflect/Method;
    //   285: astore 5
    //   287: aload 5
    //   289: aconst_null
    //   290: iconst_0
    //   291: anewarray 73	java/lang/Object
    //   294: invokevirtual 79	java/lang/reflect/Method:invoke	(Ljava/lang/Object;[Ljava/lang/Object;)Ljava/lang/Object;
    //   297: astore 5
    //   299: iload_3
    //   300: iload_2
    //   301: iload_1
    //   302: iadd
    //   303: imul
    //   304: iload 4
    //   306: irem
    //   307: aload 5
    //   309: checkcast 81	java/lang/Integer
    //   312: invokevirtual 84	java/lang/Integer:intValue	()I
    //   315: if_icmpeq +50 -> 365
    //   318: ldc 2
    //   320: ldc -103
    //   322: bipush 68
    //   324: iconst_5
    //   325: invokestatic 92	xxxxxx/uxxxxx:bb00620062bb0062b0062b0062	(Ljava/lang/String;CC)Ljava/lang/String;
    //   328: iconst_0
    //   329: anewarray 67	java/lang/Class
    //   332: invokevirtual 71	java/lang/Class:getMethod	(Ljava/lang/String;[Ljava/lang/Class;)Ljava/lang/reflect/Method;
    //   335: astore 5
    //   337: aload 5
    //   339: aconst_null
    //   340: iconst_0
    //   341: anewarray 73	java/lang/Object
    //   344: invokevirtual 79	java/lang/reflect/Method:invoke	(Ljava/lang/Object;[Ljava/lang/Object;)Ljava/lang/Object;
    //   347: astore 5
    //   349: aload 5
    //   351: checkcast 81	java/lang/Integer
    //   354: invokevirtual 84	java/lang/Integer:intValue	()I
    //   357: putstatic 51	uuuuuu/sstsss:b006En006E006En006E006En006E	I
    //   360: bipush 81
    //   362: putstatic 57	uuuuuu/sstsss:bnnnn006E006E006En006E	I
    //   365: iconst_1
    //   366: putstatic 51	uuuuuu/sstsss:b006En006E006En006E006En006E	I
    //   369: bipush 84
    //   371: putstatic 57	uuuuuu/sstsss:bnnnn006E006E006En006E	I
    //   374: return
    //   375: astore 5
    //   377: aload 5
    //   379: invokevirtual 111	java/lang/reflect/InvocationTargetException:getCause	()Ljava/lang/Throwable;
    //   382: athrow
    //   383: astore 5
    //   385: aload 5
    //   387: invokevirtual 111	java/lang/reflect/InvocationTargetException:getCause	()Ljava/lang/Throwable;
    //   390: athrow
    //   391: astore 5
    //   393: aload 5
    //   395: invokevirtual 111	java/lang/reflect/InvocationTargetException:getCause	()Ljava/lang/Throwable;
    //   398: athrow
    //   399: astore 5
    //   401: aload 5
    //   403: invokevirtual 111	java/lang/reflect/InvocationTargetException:getCause	()Ljava/lang/Throwable;
    //   406: athrow
    //   407: astore 5
    //   409: aload 5
    //   411: invokevirtual 111	java/lang/reflect/InvocationTargetException:getCause	()Ljava/lang/Throwable;
    //   414: athrow
    //   415: astore 5
    //   417: aload 5
    //   419: invokevirtual 111	java/lang/reflect/InvocationTargetException:getCause	()Ljava/lang/Throwable;
    //   422: athrow
    // Local variable table:
    //   start	length	slot	name	signature
    //   0	423	0	this	sstsss
    //   35	268	1	i	int
    //   221	82	2	j	int
    //   262	42	3	k	int
    //   266	41	4	m	int
    //   19	331	5	localObject	Object
    //   375	3	5	localInvocationTargetException1	java.lang.reflect.InvocationTargetException
    //   383	3	5	localInvocationTargetException2	java.lang.reflect.InvocationTargetException
    //   391	3	5	localInvocationTargetException3	java.lang.reflect.InvocationTargetException
    //   399	3	5	localInvocationTargetException4	java.lang.reflect.InvocationTargetException
    //   407	3	5	localInvocationTargetException5	java.lang.reflect.InvocationTargetException
    //   415	3	5	localInvocationTargetException6	java.lang.reflect.InvocationTargetException
    // Exception table:
    //   from	to	target	type
    //   242	254	375	java/lang/reflect/InvocationTargetException
    //   287	299	383	java/lang/reflect/InvocationTargetException
    //   21	32	391	java/lang/reflect/InvocationTargetException
    //   197	209	399	java/lang/reflect/InvocationTargetException
    //   337	349	407	java/lang/reflect/InvocationTargetException
    //   139	151	415	java/lang/reflect/InvocationTargetException
  }
}
