package uuuuuu;

public enum sststt
{
  /* Error */
  static
  {
    // Byte code:
    //   0: ldc 20
    //   2: ldc 22
    //   4: bipush 41
    //   6: bipush 73
    //   8: iconst_2
    //   9: invokestatic 28	xxxxxx/uxxxxx:bbbb0062b0062b0062b0062	(Ljava/lang/String;CCC)Ljava/lang/String;
    //   12: iconst_3
    //   13: anewarray 30	java/lang/Class
    //   16: dup
    //   17: iconst_0
    //   18: ldc 32
    //   20: aastore
    //   21: dup
    //   22: iconst_1
    //   23: getstatic 38	java/lang/Character:TYPE	Ljava/lang/Class;
    //   26: aastore
    //   27: dup
    //   28: iconst_2
    //   29: getstatic 38	java/lang/Character:TYPE	Ljava/lang/Class;
    //   32: aastore
    //   33: invokevirtual 42	java/lang/Class:getMethod	(Ljava/lang/String;[Ljava/lang/Class;)Ljava/lang/reflect/Method;
    //   36: astore_0
    //   37: aload_0
    //   38: aconst_null
    //   39: iconst_3
    //   40: anewarray 44	java/lang/Object
    //   43: dup
    //   44: iconst_0
    //   45: ldc 46
    //   47: aastore
    //   48: dup
    //   49: iconst_1
    //   50: sipush 217
    //   53: invokestatic 50	java/lang/Character:valueOf	(C)Ljava/lang/Character;
    //   56: aastore
    //   57: dup
    //   58: iconst_2
    //   59: iconst_2
    //   60: invokestatic 50	java/lang/Character:valueOf	(C)Ljava/lang/Character;
    //   63: aastore
    //   64: invokevirtual 56	java/lang/reflect/Method:invoke	(Ljava/lang/Object;[Ljava/lang/Object;)Ljava/lang/Object;
    //   67: astore_0
    //   68: new 2	uuuuuu/sststt
    //   71: dup
    //   72: aload_0
    //   73: checkcast 32	java/lang/String
    //   76: iconst_0
    //   77: invokespecial 60	uuuuuu/sststt:<init>	(Ljava/lang/String;I)V
    //   80: putstatic 62	uuuuuu/sststt:b006En006En006Enn006En	Luuuuuu/sststt;
    //   83: ldc 20
    //   85: ldc 64
    //   87: bipush 91
    //   89: iconst_1
    //   90: invokestatic 68	xxxxxx/uxxxxx:bb00620062bb0062b0062b0062	(Ljava/lang/String;CC)Ljava/lang/String;
    //   93: iconst_3
    //   94: anewarray 30	java/lang/Class
    //   97: dup
    //   98: iconst_0
    //   99: ldc 32
    //   101: aastore
    //   102: dup
    //   103: iconst_1
    //   104: getstatic 38	java/lang/Character:TYPE	Ljava/lang/Class;
    //   107: aastore
    //   108: dup
    //   109: iconst_2
    //   110: getstatic 38	java/lang/Character:TYPE	Ljava/lang/Class;
    //   113: aastore
    //   114: invokevirtual 42	java/lang/Class:getMethod	(Ljava/lang/String;[Ljava/lang/Class;)Ljava/lang/reflect/Method;
    //   117: astore_0
    //   118: aload_0
    //   119: aconst_null
    //   120: iconst_3
    //   121: anewarray 44	java/lang/Object
    //   124: dup
    //   125: iconst_0
    //   126: ldc 70
    //   128: aastore
    //   129: dup
    //   130: iconst_1
    //   131: sipush 226
    //   134: invokestatic 50	java/lang/Character:valueOf	(C)Ljava/lang/Character;
    //   137: aastore
    //   138: dup
    //   139: iconst_2
    //   140: iconst_1
    //   141: invokestatic 50	java/lang/Character:valueOf	(C)Ljava/lang/Character;
    //   144: aastore
    //   145: invokevirtual 56	java/lang/reflect/Method:invoke	(Ljava/lang/Object;[Ljava/lang/Object;)Ljava/lang/Object;
    //   148: astore_0
    //   149: new 2	uuuuuu/sststt
    //   152: dup
    //   153: aload_0
    //   154: checkcast 32	java/lang/String
    //   157: iconst_1
    //   158: invokespecial 60	uuuuuu/sststt:<init>	(Ljava/lang/String;I)V
    //   161: putstatic 72	uuuuuu/sststt:bnnnn006Enn006En	Luuuuuu/sststt;
    //   164: ldc 20
    //   166: ldc 74
    //   168: bipush 81
    //   170: iconst_1
    //   171: invokestatic 68	xxxxxx/uxxxxx:bb00620062bb0062b0062b0062	(Ljava/lang/String;CC)Ljava/lang/String;
    //   174: iconst_4
    //   175: anewarray 30	java/lang/Class
    //   178: dup
    //   179: iconst_0
    //   180: ldc 32
    //   182: aastore
    //   183: dup
    //   184: iconst_1
    //   185: getstatic 38	java/lang/Character:TYPE	Ljava/lang/Class;
    //   188: aastore
    //   189: dup
    //   190: iconst_2
    //   191: getstatic 38	java/lang/Character:TYPE	Ljava/lang/Class;
    //   194: aastore
    //   195: dup
    //   196: iconst_3
    //   197: getstatic 38	java/lang/Character:TYPE	Ljava/lang/Class;
    //   200: aastore
    //   201: invokevirtual 42	java/lang/Class:getMethod	(Ljava/lang/String;[Ljava/lang/Class;)Ljava/lang/reflect/Method;
    //   204: astore_0
    //   205: aload_0
    //   206: aconst_null
    //   207: iconst_4
    //   208: anewarray 44	java/lang/Object
    //   211: dup
    //   212: iconst_0
    //   213: ldc 76
    //   215: aastore
    //   216: dup
    //   217: iconst_1
    //   218: bipush 44
    //   220: invokestatic 50	java/lang/Character:valueOf	(C)Ljava/lang/Character;
    //   223: aastore
    //   224: dup
    //   225: iconst_2
    //   226: sipush 198
    //   229: invokestatic 50	java/lang/Character:valueOf	(C)Ljava/lang/Character;
    //   232: aastore
    //   233: dup
    //   234: iconst_3
    //   235: iconst_3
    //   236: invokestatic 50	java/lang/Character:valueOf	(C)Ljava/lang/Character;
    //   239: aastore
    //   240: invokevirtual 56	java/lang/reflect/Method:invoke	(Ljava/lang/Object;[Ljava/lang/Object;)Ljava/lang/Object;
    //   243: astore_0
    //   244: new 2	uuuuuu/sststt
    //   247: dup
    //   248: aload_0
    //   249: checkcast 32	java/lang/String
    //   252: iconst_2
    //   253: invokespecial 60	uuuuuu/sststt:<init>	(Ljava/lang/String;I)V
    //   256: putstatic 78	uuuuuu/sststt:bn006Enn006Enn006En	Luuuuuu/sststt;
    //   259: ldc 20
    //   261: ldc 80
    //   263: sipush 206
    //   266: iconst_1
    //   267: invokestatic 68	xxxxxx/uxxxxx:bb00620062bb0062b0062b0062	(Ljava/lang/String;CC)Ljava/lang/String;
    //   270: iconst_4
    //   271: anewarray 30	java/lang/Class
    //   274: dup
    //   275: iconst_0
    //   276: ldc 32
    //   278: aastore
    //   279: dup
    //   280: iconst_1
    //   281: getstatic 38	java/lang/Character:TYPE	Ljava/lang/Class;
    //   284: aastore
    //   285: dup
    //   286: iconst_2
    //   287: getstatic 38	java/lang/Character:TYPE	Ljava/lang/Class;
    //   290: aastore
    //   291: dup
    //   292: iconst_3
    //   293: getstatic 38	java/lang/Character:TYPE	Ljava/lang/Class;
    //   296: aastore
    //   297: invokevirtual 42	java/lang/Class:getMethod	(Ljava/lang/String;[Ljava/lang/Class;)Ljava/lang/reflect/Method;
    //   300: astore_0
    //   301: aload_0
    //   302: aconst_null
    //   303: iconst_4
    //   304: anewarray 44	java/lang/Object
    //   307: dup
    //   308: iconst_0
    //   309: ldc 82
    //   311: aastore
    //   312: dup
    //   313: iconst_1
    //   314: bipush 76
    //   316: invokestatic 50	java/lang/Character:valueOf	(C)Ljava/lang/Character;
    //   319: aastore
    //   320: dup
    //   321: iconst_2
    //   322: sipush 212
    //   325: invokestatic 50	java/lang/Character:valueOf	(C)Ljava/lang/Character;
    //   328: aastore
    //   329: dup
    //   330: iconst_3
    //   331: iconst_3
    //   332: invokestatic 50	java/lang/Character:valueOf	(C)Ljava/lang/Character;
    //   335: aastore
    //   336: invokevirtual 56	java/lang/reflect/Method:invoke	(Ljava/lang/Object;[Ljava/lang/Object;)Ljava/lang/Object;
    //   339: astore_0
    //   340: new 2	uuuuuu/sststt
    //   343: dup
    //   344: aload_0
    //   345: checkcast 32	java/lang/String
    //   348: iconst_3
    //   349: invokespecial 60	uuuuuu/sststt:<init>	(Ljava/lang/String;I)V
    //   352: putstatic 84	uuuuuu/sststt:bnn006En006Enn006En	Luuuuuu/sststt;
    //   355: ldc 20
    //   357: ldc 86
    //   359: bipush 118
    //   361: sipush 151
    //   364: iconst_3
    //   365: invokestatic 28	xxxxxx/uxxxxx:bbbb0062b0062b0062b0062	(Ljava/lang/String;CCC)Ljava/lang/String;
    //   368: iconst_4
    //   369: anewarray 30	java/lang/Class
    //   372: dup
    //   373: iconst_0
    //   374: ldc 32
    //   376: aastore
    //   377: dup
    //   378: iconst_1
    //   379: getstatic 38	java/lang/Character:TYPE	Ljava/lang/Class;
    //   382: aastore
    //   383: dup
    //   384: iconst_2
    //   385: getstatic 38	java/lang/Character:TYPE	Ljava/lang/Class;
    //   388: aastore
    //   389: dup
    //   390: iconst_3
    //   391: getstatic 38	java/lang/Character:TYPE	Ljava/lang/Class;
    //   394: aastore
    //   395: invokevirtual 42	java/lang/Class:getMethod	(Ljava/lang/String;[Ljava/lang/Class;)Ljava/lang/reflect/Method;
    //   398: astore_0
    //   399: aload_0
    //   400: aconst_null
    //   401: iconst_4
    //   402: anewarray 44	java/lang/Object
    //   405: dup
    //   406: iconst_0
    //   407: ldc 88
    //   409: aastore
    //   410: dup
    //   411: iconst_1
    //   412: sipush 145
    //   415: invokestatic 50	java/lang/Character:valueOf	(C)Ljava/lang/Character;
    //   418: aastore
    //   419: dup
    //   420: iconst_2
    //   421: bipush 14
    //   423: invokestatic 50	java/lang/Character:valueOf	(C)Ljava/lang/Character;
    //   426: aastore
    //   427: dup
    //   428: iconst_3
    //   429: iconst_1
    //   430: invokestatic 50	java/lang/Character:valueOf	(C)Ljava/lang/Character;
    //   433: aastore
    //   434: invokevirtual 56	java/lang/reflect/Method:invoke	(Ljava/lang/Object;[Ljava/lang/Object;)Ljava/lang/Object;
    //   437: astore_0
    //   438: new 2	uuuuuu/sststt
    //   441: dup
    //   442: aload_0
    //   443: checkcast 32	java/lang/String
    //   446: iconst_4
    //   447: invokespecial 60	uuuuuu/sststt:<init>	(Ljava/lang/String;I)V
    //   450: putstatic 90	uuuuuu/sststt:b006E006Enn006Enn006En	Luuuuuu/sststt;
    //   453: invokestatic 94	uuuuuu/sststt:b006B006B006Bk006B006B006B006Bkk	()I
    //   456: invokestatic 97	uuuuuu/sststt:bkkk006B006B006B006B006Bkk	()I
    //   459: iadd
    //   460: invokestatic 94	uuuuuu/sststt:b006B006B006Bk006B006B006B006Bkk	()I
    //   463: imul
    //   464: invokestatic 100	uuuuuu/sststt:bk006B006Bk006B006B006B006Bkk	()I
    //   467: irem
    //   468: invokestatic 103	uuuuuu/sststt:b006Bk006Bk006B006B006B006Bkk	()I
    //   471: if_icmpeq +3 -> 474
    //   474: ldc 20
    //   476: ldc 105
    //   478: bipush 63
    //   480: iconst_2
    //   481: invokestatic 68	xxxxxx/uxxxxx:bb00620062bb0062b0062b0062	(Ljava/lang/String;CC)Ljava/lang/String;
    //   484: iconst_3
    //   485: anewarray 30	java/lang/Class
    //   488: dup
    //   489: iconst_0
    //   490: ldc 32
    //   492: aastore
    //   493: dup
    //   494: iconst_1
    //   495: getstatic 38	java/lang/Character:TYPE	Ljava/lang/Class;
    //   498: aastore
    //   499: dup
    //   500: iconst_2
    //   501: getstatic 38	java/lang/Character:TYPE	Ljava/lang/Class;
    //   504: aastore
    //   505: invokevirtual 42	java/lang/Class:getMethod	(Ljava/lang/String;[Ljava/lang/Class;)Ljava/lang/reflect/Method;
    //   508: astore_0
    //   509: aload_0
    //   510: aconst_null
    //   511: iconst_3
    //   512: anewarray 44	java/lang/Object
    //   515: dup
    //   516: iconst_0
    //   517: ldc 107
    //   519: aastore
    //   520: dup
    //   521: iconst_1
    //   522: sipush 217
    //   525: invokestatic 50	java/lang/Character:valueOf	(C)Ljava/lang/Character;
    //   528: aastore
    //   529: dup
    //   530: iconst_2
    //   531: iconst_0
    //   532: invokestatic 50	java/lang/Character:valueOf	(C)Ljava/lang/Character;
    //   535: aastore
    //   536: invokevirtual 56	java/lang/reflect/Method:invoke	(Ljava/lang/Object;[Ljava/lang/Object;)Ljava/lang/Object;
    //   539: astore_0
    //   540: new 2	uuuuuu/sststt
    //   543: dup
    //   544: aload_0
    //   545: checkcast 32	java/lang/String
    //   548: iconst_5
    //   549: invokespecial 60	uuuuuu/sststt:<init>	(Ljava/lang/String;I)V
    //   552: putstatic 109	uuuuuu/sststt:b006Ennn006Enn006En	Luuuuuu/sststt;
    //   555: getstatic 62	uuuuuu/sststt:b006En006En006Enn006En	Luuuuuu/sststt;
    //   558: astore_0
    //   559: getstatic 72	uuuuuu/sststt:bnnnn006Enn006En	Luuuuuu/sststt;
    //   562: astore_1
    //   563: getstatic 78	uuuuuu/sststt:bn006Enn006Enn006En	Luuuuuu/sststt;
    //   566: astore_2
    //   567: getstatic 84	uuuuuu/sststt:bnn006En006Enn006En	Luuuuuu/sststt;
    //   570: astore_3
    //   571: getstatic 90	uuuuuu/sststt:b006E006Enn006Enn006En	Luuuuuu/sststt;
    //   574: astore 4
    //   576: getstatic 109	uuuuuu/sststt:b006Ennn006Enn006En	Luuuuuu/sststt;
    //   579: astore 5
    //   581: invokestatic 94	uuuuuu/sststt:b006B006B006Bk006B006B006B006Bkk	()I
    //   584: invokestatic 97	uuuuuu/sststt:bkkk006B006B006B006B006Bkk	()I
    //   587: iadd
    //   588: invokestatic 94	uuuuuu/sststt:b006B006B006Bk006B006B006B006Bkk	()I
    //   591: imul
    //   592: invokestatic 100	uuuuuu/sststt:bk006B006Bk006B006B006B006Bkk	()I
    //   595: irem
    //   596: invokestatic 103	uuuuuu/sststt:b006Bk006Bk006B006B006B006Bkk	()I
    //   599: if_icmpeq +3 -> 602
    //   602: bipush 6
    //   604: anewarray 2	uuuuuu/sststt
    //   607: dup
    //   608: iconst_0
    //   609: aload_0
    //   610: aastore
    //   611: dup
    //   612: iconst_1
    //   613: aload_1
    //   614: aastore
    //   615: dup
    //   616: iconst_2
    //   617: aload_2
    //   618: aastore
    //   619: dup
    //   620: iconst_3
    //   621: aload_3
    //   622: aastore
    //   623: dup
    //   624: iconst_4
    //   625: aload 4
    //   627: aastore
    //   628: dup
    //   629: iconst_5
    //   630: aload 5
    //   632: aastore
    //   633: putstatic 111	uuuuuu/sststt:b006E006E006E006Ennn006En	[Luuuuuu/sststt;
    //   636: return
    //   637: astore_0
    //   638: aload_0
    //   639: invokevirtual 115	java/lang/reflect/InvocationTargetException:getCause	()Ljava/lang/Throwable;
    //   642: athrow
    //   643: astore_0
    //   644: aload_0
    //   645: invokevirtual 115	java/lang/reflect/InvocationTargetException:getCause	()Ljava/lang/Throwable;
    //   648: athrow
    //   649: astore_0
    //   650: aload_0
    //   651: invokevirtual 115	java/lang/reflect/InvocationTargetException:getCause	()Ljava/lang/Throwable;
    //   654: athrow
    //   655: astore_0
    //   656: aload_0
    //   657: invokevirtual 115	java/lang/reflect/InvocationTargetException:getCause	()Ljava/lang/Throwable;
    //   660: athrow
    //   661: astore_0
    //   662: aload_0
    //   663: invokevirtual 115	java/lang/reflect/InvocationTargetException:getCause	()Ljava/lang/Throwable;
    //   666: athrow
    //   667: astore_0
    //   668: aload_0
    //   669: invokevirtual 115	java/lang/reflect/InvocationTargetException:getCause	()Ljava/lang/Throwable;
    //   672: athrow
    // Local variable table:
    //   start	length	slot	name	signature
    //   36	574	0	localObject	Object
    //   637	2	0	localInvocationTargetException1	java.lang.reflect.InvocationTargetException
    //   643	2	0	localInvocationTargetException2	java.lang.reflect.InvocationTargetException
    //   649	2	0	localInvocationTargetException3	java.lang.reflect.InvocationTargetException
    //   655	2	0	localInvocationTargetException4	java.lang.reflect.InvocationTargetException
    //   661	2	0	localInvocationTargetException5	java.lang.reflect.InvocationTargetException
    //   667	2	0	localInvocationTargetException6	java.lang.reflect.InvocationTargetException
    //   562	52	1	localSststt1	sststt
    //   566	52	2	localSststt2	sststt
    //   570	52	3	localSststt3	sststt
    //   574	52	4	localSststt4	sststt
    //   579	52	5	localSststt5	sststt
    // Exception table:
    //   from	to	target	type
    //   37	68	637	java/lang/reflect/InvocationTargetException
    //   118	149	643	java/lang/reflect/InvocationTargetException
    //   509	540	649	java/lang/reflect/InvocationTargetException
    //   399	438	655	java/lang/reflect/InvocationTargetException
    //   205	244	661	java/lang/reflect/InvocationTargetException
    //   301	340	667	java/lang/reflect/InvocationTargetException
  }
  
  private sststt() {}
  
  public static int b006B006B006Bk006B006B006B006Bkk()
  {
    return 63;
  }
  
  public static int b006Bk006Bk006B006B006B006Bkk()
  {
    return 0;
  }
  
  public static sststt b006Bkk006B006B006B006B006Bkk(String paramString)
  {
    int i = b006B006B006Bk006B006B006B006Bkk();
    switch (i * (bkkk006B006B006B006B006Bkk() + i) % bk006B006Bk006B006B006B006Bkk())
    {
    default: 
      if ((b006B006B006Bk006B006B006B006Bkk() + bkkk006B006B006B006B006Bkk()) * b006B006B006Bk006B006B006B006Bkk() % bk006B006Bk006B006B006B006Bkk() == b006Bk006Bk006B006B006B006Bkk()) {
        break;
      }
    }
    return (sststt)Enum.valueOf(sststt.class, paramString);
  }
  
  public static int bk006B006Bk006B006B006B006Bkk()
  {
    return 2;
  }
  
  public static int bkkk006B006B006B006B006Bkk()
  {
    return 1;
  }
}
