package uuuuuu;

import android.support.annotation.Nullable;
import com.db.pwcc.dbmobile.model.banking.Account;
import com.db.pwcc.dbmobile.model.banking.FinancialOverviewData;
import com.db.pwcc.dbmobile.model.error.DbError;
import com.db.pwcc.dbmobile.model.profile.Profile;
import com.db.pwcc.dbmobile.model.profile.Profile.ProfileRole;
import com.db.pwcc.dbmobile.model.tan.Authorization;
import com.db.pwcc.dbmobile.model.tan.AuthorizationStatus;
import com.db.pwcc.dbmobile.model.tan.TanAuthorizationMethodsResponse;
import com.db.pwcc.dbmobile.secure.preferences.SharedPreferencesHelper;
import java.lang.reflect.InvocationTargetException;
import java.lang.reflect.Method;
import java.util.ArrayList;
import java.util.Iterator;
import java.util.List;
import javax.inject.Inject;
import xxxxxx.uxxxxx;

public class sxxxsx
{
  public static final int b0066006600660066f00660066f0066 = 4;
  public static int b00660066f0066006600660066f0066 = 1;
  public static final int b00660066f0066f00660066f0066 = 2;
  private static final int b0066f00660066f00660066f0066 = -1;
  public static int b0066ff0066006600660066f0066 = 90;
  private static final String b0066fff006600660066f0066 = sxxxsx.class.getSimpleName();
  public static final int bf006600660066f00660066f0066 = 0;
  public static int bf0066f0066006600660066f0066 = 0;
  public static int bff00660066006600660066f0066 = 2;
  public static final int bff00660066f00660066f0066 = 1;
  public static final int bffff006600660066f0066 = 3;
  @Inject
  public SharedPreferencesHelper b006600660066f006600660066f0066;
  private ArrayList<Integer> b00660066ff006600660066f0066;
  public mffffm b0066f0066f006600660066f0066;
  public mfffmf bf00660066f006600660066f0066;
  private xsxsxx bf0066ff006600660066f0066;
  public fmfmfm bff0066f006600660066f0066;
  @Inject
  public hyhyhh bfff0066006600660066f0066;
  
  static
  {
    if ((b0066ff0066006600660066f0066 + b00660066f0066006600660066f0066) * b0066ff0066006600660066f0066 % bff00660066006600660066f0066 != bf0066f0066006600660066f0066)
    {
      b0066ff0066006600660066f0066 = 79;
      bf0066f0066006600660066f0066 = bk006Bkk006Bk006B006B006B006B();
    }
    int i = b0066ff0066006600660066f0066;
    switch (i * (b00660066f0066006600660066f0066 + i) % bff00660066006600660066f0066)
    {
    default: 
      b0066ff0066006600660066f0066 = 44;
      bf0066f0066006600660066f0066 = 68;
    }
  }
  
  public sxxxsx()
  {
    pqqppq.b006B006B006Bkkk006Bkkk().bp0070pppppppp(this);
    this.bff0066f006600660066f0066 = new fmfmfm();
    this.bf00660066f006600660066f0066 = new mfffmf();
    this.b0066f0066f006600660066f0066 = new mffffm();
    this.b00660066ff006600660066f0066 = new ArrayList();
  }
  
  private void b006B006B006Bk006Bk006B006B006B006B()
  {
    fmfmfm localFmfmfm = this.bff0066f006600660066f0066;
    if ((b0066ff0066006600660066f0066 + b00660066f0066006600660066f0066) * b0066ff0066006600660066f0066 % bff00660066006600660066f0066 != bf0066f0066006600660066f0066)
    {
      b0066ff0066006600660066f0066 = bk006Bkk006Bk006B006B006B006B();
      bf0066f0066006600660066f0066 = 65;
    }
    if ((b0066ff0066006600660066f0066 + b00660066f0066006600660066f0066) * b0066ff0066006600660066f0066 % bff00660066006600660066f0066 != bf0066f0066006600660066f0066)
    {
      b0066ff0066006600660066f0066 = 64;
      bf0066f0066006600660066f0066 = bk006Bkk006Bk006B006B006B006B();
    }
    localFmfmfm.b0070p007000700070pp00700070p(new vpvpvp.pvvpvp()
    {
      public static int b0066006600660066fff00660066 = 0;
      public static int b0066f00660066fff00660066 = 2;
      public static int bf006600660066fff00660066 = 81;
      public static int bffff0066ff00660066 = 1;
      
      public static int b006B006Bkkkk006B006B006B006B()
      {
        return 1;
      }
      
      public static int b006Bk006Bkkk006B006B006B006B()
      {
        return 2;
      }
      
      public static int bk006B006Bkkk006B006B006B006B()
      {
        return 2;
      }
      
      public static int bkk006Bkkk006B006B006B006B()
      {
        return 0;
      }
      
      public void b006B006B006Bkkk006B006B006B006B(FinancialOverviewData paramAnonymousFinancialOverviewData) {}
      
      public void onGetFinancialOverviewError(DbError paramAnonymousDbError)
      {
        sxxxsx localSxxxsx = sxxxsx.this;
        int i = b006Bk006Bkkk006B006B006B006B();
        switch (i * (b006B006Bkkkk006B006B006B006B() + i) % b0066f00660066fff00660066)
        {
        default: 
          b0066f00660066fff00660066 = 83;
          if ((bf006600660066fff00660066 + bffff0066ff00660066) * bf006600660066fff00660066 % b0066f00660066fff00660066 != b0066006600660066fff00660066)
          {
            bf006600660066fff00660066 = b006Bk006Bkkk006B006B006B006B();
            b0066006600660066fff00660066 = 77;
          }
          break;
        }
        sxxxsx.bk006B006B006Bkk006B006B006B006B(localSxxxsx, 3, paramAnonymousDbError);
      }
      
      public void onGetFinancialOverviewSuccess(FinancialOverviewData paramAnonymousFinancialOverviewData)
      {
        if (sxxxsx.b006B006B006B006Bkk006B006B006B006B(sxxxsx.this, paramAnonymousFinancialOverviewData.getAccounts()))
        {
          sxxxsx.b006Bk006B006Bkk006B006B006B006B(sxxxsx.this);
          return;
        }
        sxxxsx.bk006B006B006Bkk006B006B006B006B(sxxxsx.this, 3, null);
        if ((bf006600660066fff00660066 + bffff0066ff00660066) * bf006600660066fff00660066 % bk006B006Bkkk006B006B006B006B() != b0066006600660066fff00660066)
        {
          bf006600660066fff00660066 = 69;
          b0066006600660066fff00660066 = b006Bk006Bkkk006B006B006B006B();
        }
        int i = bf006600660066fff00660066;
        switch (i * (bffff0066ff00660066 + i) % b0066f00660066fff00660066)
        {
        }
        bf006600660066fff00660066 = 6;
        b0066006600660066fff00660066 = b006Bk006Bkkk006B006B006B006B();
      }
    }, this.bfff0066006600660066f0066.b0070pp007000700070p007000700070());
  }
  
  public static int b006B006Bkk006Bk006B006B006B006B()
  {
    return 0;
  }
  
  private void b006Bk006B006B006Bk006B006B006B006B()
  {
    if (this.b00660066ff006600660066f0066.isEmpty())
    {
      this.bf0066ff006600660066f0066.boooo006Foo006Foo();
      return;
      bkk006Bk006Bk006B006B006B006B();
      return;
      b006Bk006Bk006Bk006B006B006B006B();
      return;
    }
    Object localObject1 = this.b00660066ff006600660066f0066.remove(0);
    if ((b0066ff0066006600660066f0066 + b006Bkkk006Bk006B006B006B006B()) * b0066ff0066006600660066f0066 % bff00660066006600660066f0066 != bf0066f0066006600660066f0066)
    {
      b0066ff0066006600660066f0066 = bk006Bkk006Bk006B006B006B006B();
      bf0066f0066006600660066f0066 = 50;
    }
    Object localObject2;
    switch (((Integer)localObject1).intValue())
    {
    case 0: 
    case 1: 
    default: 
      localObject1 = this.bf0066ff006600660066f0066;
      localObject2 = ppphhp.class.getMethod(uxxxxx.bb00620062bb0062b0062b0062("Zpqrs-.6712:;|67?@:;CD\006", 'ú', '\001'), new Class[] { String.class, Character.TYPE, Character.TYPE });
    case 2: 
      try
      {
        localObject2 = ((Method)localObject2).invoke(null, new Object[] { "2XaMYWS\020aWea^ijahh\033nbotetv", Character.valueOf('ç'), Character.valueOf('\002') });
        ((xsxsxx)localObject1).bo006Foo006Foo006Foo(-1, new DbError((String)localObject2));
        return;
      }
      catch (InvocationTargetException localInvocationTargetException)
      {
        throw localInvocationTargetException.getCause();
      }
      bkkk006B006Bk006B006B006B006B();
      return;
    case 3: 
      b006B006B006Bk006Bk006B006B006B006B();
      int i = b0066ff0066006600660066f0066;
      switch (i * (b00660066f0066006600660066f0066 + i) % bff00660066006600660066f0066)
      {
      }
      b0066ff0066006600660066f0066 = bk006Bkk006Bk006B006B006B006B();
      bf0066f0066006600660066f0066 = 24;
      return;
    }
    bk006B006Bk006Bk006B006B006B006B();
  }
  
  private void b006Bk006Bk006Bk006B006B006B006B()
  {
    mffffm localMffffm = this.b0066f0066f006600660066f0066;
    vvpvvp.ppvvvp local3 = new vvpvvp.ppvvvp()
    {
      public static int b00660066f0066fff00660066 = 2;
      public static int b0066ff0066fff00660066 = 0;
      public static int bf0066f0066fff00660066 = 1;
      public static int bfff0066fff00660066 = 53;
      
      public static int b006Bkkkkk006B006B006B006B()
      {
        return 0;
      }
      
      public static int bk006Bkkkk006B006B006B006B()
      {
        return 2;
      }
      
      public static int bkkkkkk006B006B006B006B()
      {
        return 65;
      }
      
      public void b0061aa00610061aaa0061a(Profile paramAnonymousProfile)
      {
        paramAnonymousProfile = paramAnonymousProfile.getRoles();
        if ((bkkkkkk006B006B006B006B() + bf0066f0066fff00660066) * bkkkkkk006B006B006B006B() % b00660066f0066fff00660066 != b006Bkkkkk006B006B006B006B())
        {
          bfff0066fff00660066 = bkkkkkk006B006B006B006B();
          b0066ff0066fff00660066 = bkkkkkk006B006B006B006B();
        }
        if (paramAnonymousProfile.isRightCreateMoneyTransfer())
        {
          paramAnonymousProfile = sxxxsx.this;
          int i = bfff0066fff00660066;
          switch (i * (bf0066f0066fff00660066 + i) % bk006Bkkkk006B006B006B006B())
          {
          default: 
            bfff0066fff00660066 = 40;
            b0066ff0066fff00660066 = bkkkkkk006B006B006B006B();
          }
          sxxxsx.b006Bk006B006Bkk006B006B006B006B(paramAnonymousProfile);
          return;
        }
        sxxxsx.bk006B006B006Bkk006B006B006B006B(sxxxsx.this, 1, null);
      }
      
      public void baaa00610061aaa0061a(DbError paramAnonymousDbError)
      {
        int i = bfff0066fff00660066;
        int j = bf0066f0066fff00660066;
        int k = bfff0066fff00660066;
        int m = b00660066f0066fff00660066;
        int n = b0066ff0066fff00660066;
        int i1 = bfff0066fff00660066;
        switch (i1 * (bf0066f0066fff00660066 + i1) % b00660066f0066fff00660066)
        {
        default: 
          bfff0066fff00660066 = 17;
          b0066ff0066fff00660066 = 9;
        }
        if ((i + j) * k % m != n)
        {
          bfff0066fff00660066 = 75;
          b0066ff0066fff00660066 = bkkkkkk006B006B006B006B();
        }
        sxxxsx.bk006B006B006Bkk006B006B006B006B(sxxxsx.this, 1, paramAnonymousDbError);
      }
    };
    int i = b0066ff0066006600660066f0066;
    int j = b00660066f0066006600660066f0066;
    int k = b0066ff0066006600660066f0066;
    int m = bff00660066006600660066f0066;
    if ((b0066ff0066006600660066f0066 + b00660066f0066006600660066f0066) * b0066ff0066006600660066f0066 % bff00660066006600660066f0066 != bf0066f0066006600660066f0066)
    {
      b0066ff0066006600660066f0066 = bk006Bkk006Bk006B006B006B006B();
      bf0066f0066006600660066f0066 = bk006Bkk006Bk006B006B006B006B();
    }
    if ((i + j) * k % m != bf0066f0066006600660066f0066)
    {
      b0066ff0066006600660066f0066 = bk006Bkk006Bk006B006B006B006B();
      bf0066f0066006600660066f0066 = bk006Bkk006Bk006B006B006B006B();
    }
    localMffffm.bpp0070pp0070p00700070p(local3);
  }
  
  private boolean b006Bkk006B006Bk006B006B006B006B(List<Account> paramList)
  {
    if (paramList != null)
    {
      paramList = paramList.iterator();
      while (paramList.hasNext())
      {
        int i = b0066ff0066006600660066f0066;
        switch (i * (b00660066f0066006600660066f0066 + i) % bff00660066006600660066f0066)
        {
        default: 
          b0066ff0066006600660066f0066 = 7;
          bf0066f0066006600660066f0066 = 88;
        }
        Account localAccount = (Account)paramList.next();
        if ((localAccount.getIban() != null) && (localAccount.isDomesticTransferCapabilities().booleanValue()))
        {
          if ((b0066ff0066006600660066f0066 + b00660066f0066006600660066f0066) * b0066ff0066006600660066f0066 % bff00660066006600660066f0066 != bf0066f0066006600660066f0066)
          {
            b0066ff0066006600660066f0066 = 54;
            bf0066f0066006600660066f0066 = 66;
          }
          return true;
        }
      }
    }
    return false;
  }
  
  public static int b006Bkkk006Bk006B006B006B006B()
  {
    return 1;
  }
  
  private void bk006B006Bk006Bk006B006B006B006B()
  {
    this.b0066f0066f006600660066f0066.bpp0070pp0070p00700070p(new vvpvvp.ppvvvp()
    {
      public static int b00660066ff0066ff00660066 = 0;
      public static int b0066f0066f0066ff00660066 = 2;
      public static int bf0066ff0066ff00660066 = 68;
      public static int bff0066f0066ff00660066 = 1;
      
      public static int bkkk006Bkk006B006B006B006B()
      {
        return 79;
      }
      
      public void b0061aa00610061aaa0061a(Profile paramAnonymousProfile)
      {
        if (paramAnonymousProfile.getRoles().isRightCreateStandingOrder())
        {
          sxxxsx.b006Bk006B006Bkk006B006B006B006B(sxxxsx.this);
          if ((bf0066ff0066ff00660066 + bff0066f0066ff00660066) * bf0066ff0066ff00660066 % b0066f0066f0066ff00660066 != b00660066ff0066ff00660066)
          {
            int i = bf0066ff0066ff00660066;
            switch (i * (bff0066f0066ff00660066 + i) % b0066f0066f0066ff00660066)
            {
            default: 
              bf0066ff0066ff00660066 = 75;
              b00660066ff0066ff00660066 = bkkk006Bkk006B006B006B006B();
            }
            bf0066ff0066ff00660066 = bkkk006Bkk006B006B006B006B();
            b00660066ff0066ff00660066 = 95;
          }
          return;
        }
        sxxxsx.bk006B006B006Bkk006B006B006B006B(sxxxsx.this, 4, null);
      }
      
      public void baaa00610061aaa0061a(DbError paramAnonymousDbError)
      {
        sxxxsx localSxxxsx = sxxxsx.this;
        int i = bf0066ff0066ff00660066;
        int j = bff0066f0066ff00660066;
        int k = bf0066ff0066ff00660066;
        int m = b0066f0066f0066ff00660066;
        int n = bf0066ff0066ff00660066;
        switch (n * (bff0066f0066ff00660066 + n) % b0066f0066f0066ff00660066)
        {
        default: 
          bf0066ff0066ff00660066 = 42;
          b00660066ff0066ff00660066 = 47;
        }
        if ((i + j) * k % m != b00660066ff0066ff00660066)
        {
          bf0066ff0066ff00660066 = 24;
          b00660066ff0066ff00660066 = 2;
        }
        sxxxsx.bk006B006B006Bkk006B006B006B006B(localSxxxsx, 4, paramAnonymousDbError);
      }
    });
    int i = b0066ff0066006600660066f0066;
    int j = b00660066f0066006600660066f0066;
    if ((b0066ff0066006600660066f0066 + b006Bkkk006Bk006B006B006B006B()) * b0066ff0066006600660066f0066 % bff00660066006600660066f0066 != bf0066f0066006600660066f0066)
    {
      b0066ff0066006600660066f0066 = bk006Bkk006Bk006B006B006B006B();
      bf0066f0066006600660066f0066 = bk006Bkk006Bk006B006B006B006B();
    }
    switch (i * (j + i) % bff00660066006600660066f0066)
    {
    default: 
      b0066ff0066006600660066f0066 = 50;
      bf0066f0066006600660066f0066 = 49;
    }
  }
  
  /* Error */
  private boolean bk006Bk006B006Bk006B006B006B006B(List<Account> paramList)
  {
    // Byte code:
    //   0: iconst_0
    //   1: istore 6
    //   3: aload_1
    //   4: ifnull +137 -> 141
    //   7: aload_1
    //   8: invokeinterface 242 1 0
    //   13: astore_1
    //   14: iconst_0
    //   15: istore 4
    //   17: iconst_0
    //   18: istore_2
    //   19: iconst_0
    //   20: istore 5
    //   22: iload 5
    //   24: istore 7
    //   26: iload_2
    //   27: istore_3
    //   28: iload 4
    //   30: istore 6
    //   32: aload_1
    //   33: invokeinterface 247 1 0
    //   38: ifeq +108 -> 146
    //   41: aload_1
    //   42: invokeinterface 251 1 0
    //   47: checkcast 253	com/db/pwcc/dbmobile/model/banking/Account
    //   50: astore 8
    //   52: aload 8
    //   54: invokevirtual 256	com/db/pwcc/dbmobile/model/banking/Account:getIban	()Ljava/lang/String;
    //   57: ifnull -35 -> 22
    //   60: iload 5
    //   62: istore 6
    //   64: aload 8
    //   66: invokevirtual 276	com/db/pwcc/dbmobile/model/banking/Account:isFromSubaccountCapable	()Ljava/lang/Boolean;
    //   69: invokevirtual 265	java/lang/Boolean:booleanValue	()Z
    //   72: ifeq +6 -> 78
    //   75: iconst_1
    //   76: istore 6
    //   78: iload 4
    //   80: istore 7
    //   82: aload 8
    //   84: invokevirtual 279	com/db/pwcc/dbmobile/model/banking/Account:isToSubaccountCapable	()Ljava/lang/Boolean;
    //   87: invokevirtual 265	java/lang/Boolean:booleanValue	()Z
    //   90: ifeq +6 -> 96
    //   93: iconst_1
    //   94: istore 7
    //   96: aload 8
    //   98: invokevirtual 276	com/db/pwcc/dbmobile/model/banking/Account:isFromSubaccountCapable	()Ljava/lang/Boolean;
    //   101: invokevirtual 265	java/lang/Boolean:booleanValue	()Z
    //   104: ifne +22 -> 126
    //   107: iload 6
    //   109: istore 5
    //   111: iload 7
    //   113: istore 4
    //   115: aload 8
    //   117: invokevirtual 279	com/db/pwcc/dbmobile/model/banking/Account:isToSubaccountCapable	()Ljava/lang/Boolean;
    //   120: invokevirtual 265	java/lang/Boolean:booleanValue	()Z
    //   123: ifeq -101 -> 22
    //   126: iload_2
    //   127: iconst_1
    //   128: iadd
    //   129: istore_2
    //   130: iload 6
    //   132: istore 5
    //   134: iload 7
    //   136: istore 4
    //   138: goto -116 -> 22
    //   141: iconst_0
    //   142: istore 7
    //   144: iconst_0
    //   145: istore_3
    //   146: getstatic 83	uuuuuu/sxxxsx:b0066fff006600660066f0066	Ljava/lang/String;
    //   149: astore_1
    //   150: new 281	java/lang/StringBuilder
    //   153: dup
    //   154: invokespecial 282	java/lang/StringBuilder:<init>	()V
    //   157: astore 8
    //   159: getstatic 65	uuuuuu/sxxxsx:b0066ff0066006600660066f0066	I
    //   162: getstatic 67	uuuuuu/sxxxsx:b00660066f0066006600660066f0066	I
    //   165: iadd
    //   166: getstatic 65	uuuuuu/sxxxsx:b0066ff0066006600660066f0066	I
    //   169: imul
    //   170: getstatic 69	uuuuuu/sxxxsx:bff00660066006600660066f0066	I
    //   173: irem
    //   174: getstatic 71	uuuuuu/sxxxsx:bf0066f0066006600660066f0066	I
    //   177: if_icmpeq +14 -> 191
    //   180: invokestatic 75	uuuuuu/sxxxsx:bk006Bkk006Bk006B006B006B006B	()I
    //   183: putstatic 65	uuuuuu/sxxxsx:b0066ff0066006600660066f0066	I
    //   186: bipush 7
    //   188: putstatic 71	uuuuuu/sxxxsx:bf0066f0066006600660066f0066	I
    //   191: aload 8
    //   193: iload 7
    //   195: invokevirtual 286	java/lang/StringBuilder:append	(Z)Ljava/lang/StringBuilder;
    //   198: astore 8
    //   200: ldc -82
    //   202: ldc_w 288
    //   205: sipush 177
    //   208: iconst_1
    //   209: invokestatic 182	xxxxxx/uxxxxx:bb00620062bb0062b0062b0062	(Ljava/lang/String;CC)Ljava/lang/String;
    //   212: iconst_4
    //   213: anewarray 77	java/lang/Class
    //   216: dup
    //   217: iconst_0
    //   218: ldc -72
    //   220: aastore
    //   221: dup
    //   222: iconst_1
    //   223: getstatic 190	java/lang/Character:TYPE	Ljava/lang/Class;
    //   226: aastore
    //   227: dup
    //   228: iconst_2
    //   229: getstatic 190	java/lang/Character:TYPE	Ljava/lang/Class;
    //   232: aastore
    //   233: dup
    //   234: iconst_3
    //   235: getstatic 190	java/lang/Character:TYPE	Ljava/lang/Class;
    //   238: aastore
    //   239: invokevirtual 194	java/lang/Class:getMethod	(Ljava/lang/String;[Ljava/lang/Class;)Ljava/lang/reflect/Method;
    //   242: astore 9
    //   244: aload 9
    //   246: aconst_null
    //   247: iconst_4
    //   248: anewarray 4	java/lang/Object
    //   251: dup
    //   252: iconst_0
    //   253: ldc_w 290
    //   256: aastore
    //   257: dup
    //   258: iconst_1
    //   259: sipush 168
    //   262: invokestatic 200	java/lang/Character:valueOf	(C)Ljava/lang/Character;
    //   265: aastore
    //   266: dup
    //   267: iconst_2
    //   268: bipush 98
    //   270: invokestatic 200	java/lang/Character:valueOf	(C)Ljava/lang/Character;
    //   273: aastore
    //   274: dup
    //   275: iconst_3
    //   276: iconst_1
    //   277: invokestatic 200	java/lang/Character:valueOf	(C)Ljava/lang/Character;
    //   280: aastore
    //   281: invokevirtual 206	java/lang/reflect/Method:invoke	(Ljava/lang/Object;[Ljava/lang/Object;)Ljava/lang/Object;
    //   284: astore 9
    //   286: aload 8
    //   288: aload 9
    //   290: checkcast 184	java/lang/String
    //   293: invokevirtual 293	java/lang/StringBuilder:append	(Ljava/lang/String;)Ljava/lang/StringBuilder;
    //   296: iload 6
    //   298: invokevirtual 286	java/lang/StringBuilder:append	(Z)Ljava/lang/StringBuilder;
    //   301: astore 8
    //   303: ldc -82
    //   305: ldc_w 295
    //   308: sipush 208
    //   311: iconst_2
    //   312: invokestatic 182	xxxxxx/uxxxxx:bb00620062bb0062b0062b0062	(Ljava/lang/String;CC)Ljava/lang/String;
    //   315: iconst_3
    //   316: anewarray 77	java/lang/Class
    //   319: dup
    //   320: iconst_0
    //   321: ldc -72
    //   323: aastore
    //   324: dup
    //   325: iconst_1
    //   326: getstatic 190	java/lang/Character:TYPE	Ljava/lang/Class;
    //   329: aastore
    //   330: dup
    //   331: iconst_2
    //   332: getstatic 190	java/lang/Character:TYPE	Ljava/lang/Class;
    //   335: aastore
    //   336: invokevirtual 194	java/lang/Class:getMethod	(Ljava/lang/String;[Ljava/lang/Class;)Ljava/lang/reflect/Method;
    //   339: astore 9
    //   341: aload 9
    //   343: aconst_null
    //   344: iconst_3
    //   345: anewarray 4	java/lang/Object
    //   348: dup
    //   349: iconst_0
    //   350: ldc_w 297
    //   353: aastore
    //   354: dup
    //   355: iconst_1
    //   356: sipush 229
    //   359: invokestatic 200	java/lang/Character:valueOf	(C)Ljava/lang/Character;
    //   362: aastore
    //   363: dup
    //   364: iconst_2
    //   365: iconst_3
    //   366: invokestatic 200	java/lang/Character:valueOf	(C)Ljava/lang/Character;
    //   369: aastore
    //   370: invokevirtual 206	java/lang/reflect/Method:invoke	(Ljava/lang/Object;[Ljava/lang/Object;)Ljava/lang/Object;
    //   373: astore 9
    //   375: aload 8
    //   377: aload 9
    //   379: checkcast 184	java/lang/String
    //   382: invokevirtual 293	java/lang/StringBuilder:append	(Ljava/lang/String;)Ljava/lang/StringBuilder;
    //   385: astore 8
    //   387: getstatic 65	uuuuuu/sxxxsx:b0066ff0066006600660066f0066	I
    //   390: istore_2
    //   391: iload_2
    //   392: getstatic 67	uuuuuu/sxxxsx:b00660066f0066006600660066f0066	I
    //   395: iload_2
    //   396: iadd
    //   397: imul
    //   398: getstatic 69	uuuuuu/sxxxsx:bff00660066006600660066f0066	I
    //   401: irem
    //   402: tableswitch	default:+18->420, 0:+30->432
    //   420: invokestatic 75	uuuuuu/sxxxsx:bk006Bkk006Bk006B006B006B006B	()I
    //   423: putstatic 65	uuuuuu/sxxxsx:b0066ff0066006600660066f0066	I
    //   426: invokestatic 75	uuuuuu/sxxxsx:bk006Bkk006Bk006B006B006B006B	()I
    //   429: putstatic 71	uuuuuu/sxxxsx:bf0066f0066006600660066f0066	I
    //   432: aload_1
    //   433: aload 8
    //   435: iload_3
    //   436: invokevirtual 300	java/lang/StringBuilder:append	(I)Ljava/lang/StringBuilder;
    //   439: invokevirtual 303	java/lang/StringBuilder:toString	()Ljava/lang/String;
    //   442: invokestatic 309	uuuuuu/rvvvrv:bq0071qq00710071q0071q0071	(Ljava/lang/String;Ljava/lang/String;)V
    //   445: iload 7
    //   447: ifeq +15 -> 462
    //   450: iload 6
    //   452: ifeq +10 -> 462
    //   455: iload_3
    //   456: iconst_1
    //   457: if_icmple +5 -> 462
    //   460: iconst_1
    //   461: ireturn
    //   462: iconst_0
    //   463: ireturn
    //   464: astore_1
    //   465: aload_1
    //   466: invokevirtual 222	java/lang/reflect/InvocationTargetException:getCause	()Ljava/lang/Throwable;
    //   469: athrow
    //   470: astore_1
    //   471: aload_1
    //   472: invokevirtual 222	java/lang/reflect/InvocationTargetException:getCause	()Ljava/lang/Throwable;
    //   475: athrow
    // Local variable table:
    //   start	length	slot	name	signature
    //   0	476	0	this	sxxxsx
    //   0	476	1	paramList	List<Account>
    //   18	380	2	i	int
    //   27	431	3	j	int
    //   15	122	4	bool1	boolean
    //   20	113	5	bool2	boolean
    //   1	450	6	bool3	boolean
    //   24	422	7	bool4	boolean
    //   50	384	8	localObject1	Object
    //   242	136	9	localObject2	Object
    // Exception table:
    //   from	to	target	type
    //   341	375	464	java/lang/reflect/InvocationTargetException
    //   244	286	470	java/lang/reflect/InvocationTargetException
  }
  
  public static int bk006Bkk006Bk006B006B006B006B()
  {
    return 95;
  }
  
  private void bkk006B006B006Bk006B006B006B006B(int paramInt, @Nullable DbError paramDbError)
  {
    if (paramDbError == null) {
      this.bf0066ff006600660066f0066.b006Fooo006Foo006Foo(paramInt);
    }
    for (;;)
    {
      this.b00660066ff006600660066f0066.clear();
      if ((b0066ff0066006600660066f0066 + b00660066f0066006600660066f0066) * b0066ff0066006600660066f0066 % bff00660066006600660066f0066 != bf0066f0066006600660066f0066)
      {
        b0066ff0066006600660066f0066 = bk006Bkk006Bk006B006B006B006B();
        bf0066f0066006600660066f0066 = bk006Bkk006Bk006B006B006B006B();
      }
      return;
      this.bf0066ff006600660066f0066.bo006Foo006Foo006Foo(paramInt, paramDbError);
      if ((b0066ff0066006600660066f0066 + b006Bkkk006Bk006B006B006B006B()) * b0066ff0066006600660066f0066 % bff00660066006600660066f0066 != bf0066f0066006600660066f0066)
      {
        b0066ff0066006600660066f0066 = 18;
        bf0066f0066006600660066f0066 = 35;
      }
    }
  }
  
  private void bkk006Bk006Bk006B006B006B006B()
  {
    this.bff0066f006600660066f0066.b0070p007000700070pp00700070p(new vpvpvp.pvvpvp()
    {
      public static int b006600660066f0066ff00660066 = 98;
      public static int b0066ff00660066ff00660066 = 1;
      public static int bf0066f00660066ff00660066 = 2;
      public static int bfff00660066ff00660066;
      
      public static int b006B006Bk006Bkk006B006B006B006B()
      {
        return 2;
      }
      
      public static int b006Bkk006Bkk006B006B006B006B()
      {
        return 50;
      }
      
      public static int bk006Bk006Bkk006B006B006B006B()
      {
        return 1;
      }
      
      public void bkk006B006Bkk006B006B006B006B(FinancialOverviewData paramAnonymousFinancialOverviewData) {}
      
      public void onGetFinancialOverviewError(DbError paramAnonymousDbError)
      {
        sxxxsx.bk006B006B006Bkk006B006B006B006B(sxxxsx.this, 0, paramAnonymousDbError);
        int i = b006600660066f0066ff00660066;
        int j = b0066ff00660066ff00660066;
        int k = b006Bkk006Bkk006B006B006B006B();
        switch (k * (b0066ff00660066ff00660066 + k) % b006B006Bk006Bkk006B006B006B006B())
        {
        default: 
          b006600660066f0066ff00660066 = 74;
          bfff00660066ff00660066 = b006Bkk006Bkk006B006B006B006B();
        }
        if ((i + j) * b006600660066f0066ff00660066 % bf0066f00660066ff00660066 != bfff00660066ff00660066)
        {
          b006600660066f0066ff00660066 = 59;
          bfff00660066ff00660066 = b006Bkk006Bkk006B006B006B006B();
        }
      }
      
      public void onGetFinancialOverviewSuccess(FinancialOverviewData paramAnonymousFinancialOverviewData)
      {
        if (sxxxsx.bkkkk006Bk006B006B006B006B(sxxxsx.this, paramAnonymousFinancialOverviewData.getAccounts()))
        {
          sxxxsx.b006Bk006B006Bkk006B006B006B006B(sxxxsx.this);
          return;
        }
        sxxxsx.bk006B006B006Bkk006B006B006B006B(sxxxsx.this, 0, null);
        int i = b006600660066f0066ff00660066;
        switch (i * (bk006Bk006Bkk006B006B006B006B() + i) % bf0066f00660066ff00660066)
        {
        }
        i = b006600660066f0066ff00660066;
        switch (i * (b0066ff00660066ff00660066 + i) % bf0066f00660066ff00660066)
        {
        default: 
          b006600660066f0066ff00660066 = b006Bkk006Bkk006B006B006B006B();
          bfff00660066ff00660066 = 76;
        }
        b006600660066f0066ff00660066 = b006Bkk006Bkk006B006B006B006B();
        bfff00660066ff00660066 = 35;
      }
    }, this.bfff0066006600660066f0066.b0070pp007000700070p007000700070());
    int i = b0066ff0066006600660066f0066;
    if ((b0066ff0066006600660066f0066 + b00660066f0066006600660066f0066) * b0066ff0066006600660066f0066 % bff00660066006600660066f0066 != bf0066f0066006600660066f0066)
    {
      b0066ff0066006600660066f0066 = bk006Bkk006Bk006B006B006B006B();
      bf0066f0066006600660066f0066 = 35;
    }
    if ((i + b00660066f0066006600660066f0066) * b0066ff0066006600660066f0066 % bff00660066006600660066f0066 != bf0066f0066006600660066f0066)
    {
      b0066ff0066006600660066f0066 = bk006Bkk006Bk006B006B006B006B();
      bf0066f0066006600660066f0066 = bk006Bkk006Bk006B006B006B006B();
    }
  }
  
  private void bkkk006B006Bk006B006B006B006B()
  {
    mfffmf localMfffmf = this.bf00660066f006600660066f0066;
    vvpppv.ppvppv local2 = new vvpppv.ppvppv()
    {
      public static int b00660066fffff00660066 = 19;
      public static int b0066f0066ffff00660066 = 2;
      public static int bf00660066ffff00660066 = 0;
      public static int bff0066ffff00660066 = 1;
      
      public static int b006B006B006B006B006B006Bk006B006B006B()
      {
        return 97;
      }
      
      public static int b006Bk006B006B006B006Bk006B006B006B()
      {
        return 0;
      }
      
      public static int bk006B006B006B006B006Bk006B006B006B()
      {
        return 1;
      }
      
      public static int bkk006B006B006B006Bk006B006B006B()
      {
        return 2;
      }
      
      public void b00610061a00610061aaa0061a(TanAuthorizationMethodsResponse paramAnonymousTanAuthorizationMethodsResponse)
      {
        AuthorizationStatus localAuthorizationStatus = xxsxsx.b006B006Bkk006B006Bk006B006B006B(Authorization.ITAN, paramAnonymousTanAuthorizationMethodsResponse);
        paramAnonymousTanAuthorizationMethodsResponse = xxsxsx.b006B006Bkk006B006Bk006B006B006B(Authorization.PHOTOTAN, paramAnonymousTanAuthorizationMethodsResponse);
        if ((b006B006B006B006B006B006Bk006B006B006B() + bff0066ffff00660066) * b006B006B006B006B006B006Bk006B006B006B() % b0066f0066ffff00660066 != b006Bk006B006B006B006Bk006B006B006B())
        {
          int i = b00660066fffff00660066;
          switch (i * (bk006B006B006B006B006Bk006B006B006B() + i) % b0066f0066ffff00660066)
          {
          default: 
            b00660066fffff00660066 = 57;
            bf00660066ffff00660066 = 98;
          }
          b00660066fffff00660066 = 42;
          bf00660066ffff00660066 = 56;
        }
        if ((localAuthorizationStatus == AuthorizationStatus.ACTIVE) || (paramAnonymousTanAuthorizationMethodsResponse == AuthorizationStatus.ACTIVE))
        {
          sxxxsx.b006Bk006B006Bkk006B006B006B006B(sxxxsx.this);
          return;
        }
        sxxxsx.bk006B006B006Bkk006B006B006B006B(sxxxsx.this, 2, null);
      }
      
      public void ba0061a00610061aaa0061a(DbError paramAnonymousDbError)
      {
        if ((b00660066fffff00660066 + bff0066ffff00660066) * b00660066fffff00660066 % bkk006B006B006B006Bk006B006B006B() != bf00660066ffff00660066)
        {
          b00660066fffff00660066 = b006B006B006B006B006B006Bk006B006B006B();
          bf00660066ffff00660066 = 51;
        }
        sxxxsx localSxxxsx = sxxxsx.this;
        int i = b00660066fffff00660066;
        switch (i * (bff0066ffff00660066 + i) % b0066f0066ffff00660066)
        {
        default: 
          b00660066fffff00660066 = 27;
          bff0066ffff00660066 = 45;
        }
        sxxxsx.bk006B006B006Bkk006B006B006B006B(localSxxxsx, 2, paramAnonymousDbError);
      }
    };
    int i = b0066ff0066006600660066f0066;
    int j = b00660066f0066006600660066f0066;
    int k = b0066ff0066006600660066f0066;
    int m = bff00660066006600660066f0066;
    if ((b0066ff0066006600660066f0066 + b00660066f0066006600660066f0066) * b0066ff0066006600660066f0066 % bff00660066006600660066f0066 != bf0066f0066006600660066f0066)
    {
      b0066ff0066006600660066f0066 = bk006Bkk006Bk006B006B006B006B();
      bf0066f0066006600660066f0066 = 56;
    }
    if ((i + j) * k % m != bf0066f0066006600660066f0066)
    {
      b0066ff0066006600660066f0066 = 59;
      bf0066f0066006600660066f0066 = 92;
    }
    localMfffmf.b0070ppp00700070p00700070p(local2);
  }
  
  public void b006B006Bk006B006Bk006B006B006B006B()
  {
    int i = b0066ff0066006600660066f0066;
    switch (i * (b00660066f0066006600660066f0066 + i) % bff00660066006600660066f0066)
    {
    default: 
      b0066ff0066006600660066f0066 = 12;
      bf0066f0066006600660066f0066 = 93;
    }
    this.bf00660066f006600660066f0066.b0070ppp00700070p00700070p(new vvpppv.ppvppv()
    {
      public static int b0066006600660066006600660066f0066 = 0;
      public static int b0066ffffff00660066 = 2;
      public static int bf006600660066006600660066f0066 = 11;
      public static int bfffffff00660066 = 1;
      
      public static int b006B006Bk006B006B006Bk006B006B006B()
      {
        return 2;
      }
      
      public static int bk006Bk006B006B006Bk006B006B006B()
      {
        return 74;
      }
      
      public void b00610061a00610061aaa0061a(TanAuthorizationMethodsResponse paramAnonymousTanAuthorizationMethodsResponse)
      {
        AuthorizationStatus localAuthorizationStatus = xxsxsx.b006B006Bkk006B006Bk006B006B006B(Authorization.ITAN, paramAnonymousTanAuthorizationMethodsResponse);
        paramAnonymousTanAuthorizationMethodsResponse = xxsxsx.b006B006Bkk006B006Bk006B006B006B(Authorization.PHOTOTAN, paramAnonymousTanAuthorizationMethodsResponse);
        SharedPreferencesHelper localSharedPreferencesHelper = sxxxsx.this.b006600660066f006600660066f0066;
        boolean bool;
        if (paramAnonymousTanAuthorizationMethodsResponse == AuthorizationStatus.INACTIVE) {
          bool = true;
        }
        for (;;)
        {
          Method localMethod = SharedPreferencesHelper.class.getMethod(uxxxxx.bb00620062bb0062b0062b0062("|o\\u}\004es\002]\004wz\r\003\021\001", 'Ã', '\001'), new Class[] { Boolean.TYPE });
          try
          {
            localMethod.invoke(localSharedPreferencesHelper, new Object[] { Boolean.valueOf(bool) });
            if (localAuthorizationStatus != AuthorizationStatus.ACTIVE)
            {
              int i = bf006600660066006600660066f0066;
              switch (i * (bfffffff00660066 + i) % b006B006Bk006B006B006Bk006B006B006B())
              {
              default: 
                bf006600660066006600660066f0066 = 67;
                b0066006600660066006600660066f0066 = 92;
              }
              if (paramAnonymousTanAuthorizationMethodsResponse != AuthorizationStatus.ACTIVE) {
                sxxxsx.this.bf00660066f006600660066f0066.bp0070pp00700070p00700070p();
              }
            }
            return;
          }
          catch (InvocationTargetException paramAnonymousTanAuthorizationMethodsResponse)
          {
            throw paramAnonymousTanAuthorizationMethodsResponse.getCause();
          }
          if ((bf006600660066006600660066f0066 + bfffffff00660066) * bf006600660066006600660066f0066 % b0066ffffff00660066 != b0066006600660066006600660066f0066)
          {
            bf006600660066006600660066f0066 = bk006Bk006B006B006Bk006B006B006B();
            b0066006600660066006600660066f0066 = bk006Bk006B006B006Bk006B006B006B();
            bool = false;
          }
          else
          {
            bool = false;
          }
        }
      }
      
      public void ba0061a00610061aaa0061a(DbError paramAnonymousDbError)
      {
        paramAnonymousDbError = sxxxsx.this;
        if ((bf006600660066006600660066f0066 + bfffffff00660066) * bf006600660066006600660066f0066 % b0066ffffff00660066 != b0066006600660066006600660066f0066)
        {
          bf006600660066006600660066f0066 = 74;
          int i = bk006Bk006B006B006Bk006B006B006B();
          if ((bf006600660066006600660066f0066 + bfffffff00660066) * bf006600660066006600660066f0066 % b0066ffffff00660066 != b0066006600660066006600660066f0066)
          {
            bf006600660066006600660066f0066 = 84;
            b0066006600660066006600660066f0066 = 44;
          }
          b0066006600660066006600660066f0066 = i;
        }
        paramAnonymousDbError = paramAnonymousDbError.b006600660066f006600660066f0066;
        Method localMethod = SharedPreferencesHelper.class.getMethod(uxxxxx.bbbb0062b0062b0062b0062("\002r\001[rx|vZfrLpbcsgsa", '8', 'Å', '\001'), new Class[] { Boolean.TYPE });
        try
        {
          localMethod.invoke(paramAnonymousDbError, new Object[] { Boolean.valueOf(false) });
          return;
        }
        catch (InvocationTargetException paramAnonymousDbError)
        {
          throw paramAnonymousDbError.getCause();
        }
      }
    });
    i = b0066ff0066006600660066f0066;
    switch (i * (b00660066f0066006600660066f0066 + i) % bff00660066006600660066f0066)
    {
    default: 
      b0066ff0066006600660066f0066 = 44;
      bf0066f0066006600660066f0066 = 34;
    }
  }
  
  public void bk006B006B006B006Bk006B006B006B006B(xsxsxx paramXsxsxx, int... paramVarArgs)
  {
    this.bf0066ff006600660066f0066 = paramXsxsxx;
    int j = paramVarArgs.length;
    int i = 0;
    while (i < j)
    {
      int k = paramVarArgs[i];
      paramXsxsxx = this.b00660066ff006600660066f0066;
      if ((b0066ff0066006600660066f0066 + b00660066f0066006600660066f0066) * b0066ff0066006600660066f0066 % bff00660066006600660066f0066 != bf0066f0066006600660066f0066)
      {
        if ((b0066ff0066006600660066f0066 + b00660066f0066006600660066f0066) * b0066ff0066006600660066f0066 % bff00660066006600660066f0066 != bf0066f0066006600660066f0066)
        {
          b0066ff0066006600660066f0066 = 79;
          bf0066f0066006600660066f0066 = bk006Bkk006Bk006B006B006B006B();
        }
        b0066ff0066006600660066f0066 = 39;
        bf0066f0066006600660066f0066 = bk006Bkk006Bk006B006B006B006B();
      }
      paramXsxsxx.add(Integer.valueOf(k));
      i += 1;
    }
    b006Bk006B006B006Bk006B006B006B006B();
  }
  
  public static abstract interface xsxsxx
  {
    public abstract void b006Fooo006Foo006Foo(int paramInt);
    
    public abstract void bo006Foo006Foo006Foo(int paramInt, DbError paramDbError);
    
    public abstract void boooo006Foo006Foo();
  }
}
