package uuuuuu;

import com.db.pwcc.dbmobile.model.tokenization.TokenizationPayload;
import com.db.pwcc.dbmobile.secure.preferences.SharedPreferencesHelper;
import java.util.HashMap;
import java.util.Map;
import javax.inject.Inject;

public class tytyty
  implements ytyyty.ttyyty, vppvvv.pvpvvv
{
  public static int b00780078xxx007800780078x = 1;
  public static int b0078x0078xx007800780078x = 40;
  public static int bx00780078xx007800780078x = 0;
  public static int bxx0078xx007800780078x = 2;
  private static final String bxxx00780078x00780078x;
  @Inject
  public hyhyhh b00780078007800780078x00780078x;
  public vpvppv b00780078x00780078x00780078x = null;
  private Map<String, Boolean> b0078x007800780078x00780078x = null;
  @Inject
  public ggyggy b0078xx00780078x00780078x;
  private TokenizationPayload b0078xxxx007800780078x = null;
  @Inject
  public qpqppq bx0078007800780078x00780078x;
  @Inject
  public yttttt bx0078x00780078x00780078x;
  private ytyyty.yytyty bx0078xxx007800780078x = null;
  @Inject
  public SharedPreferencesHelper bxx007800780078x00780078x;
  public vppvvv bxxxxx007800780078x = null;
  
  /* Error */
  static
  {
    // Byte code:
    //   0: ldc 2
    //   2: ldc 49
    //   4: bipush 77
    //   6: iconst_1
    //   7: invokestatic 55	xxxxxx/uxxxxx:bb00620062bb0062b0062b0062	(Ljava/lang/String;CC)Ljava/lang/String;
    //   10: iconst_0
    //   11: anewarray 57	java/lang/Class
    //   14: invokevirtual 61	java/lang/Class:getMethod	(Ljava/lang/String;[Ljava/lang/Class;)Ljava/lang/reflect/Method;
    //   17: astore_2
    //   18: aload_2
    //   19: aconst_null
    //   20: iconst_0
    //   21: anewarray 4	java/lang/Object
    //   24: invokevirtual 67	java/lang/reflect/Method:invoke	(Ljava/lang/Object;[Ljava/lang/Object;)Ljava/lang/Object;
    //   27: astore_2
    //   28: aload_2
    //   29: checkcast 69	java/lang/Integer
    //   32: invokevirtual 73	java/lang/Integer:intValue	()I
    //   35: istore_0
    //   36: getstatic 75	uuuuuu/tytyty:b0078x0078xx007800780078x	I
    //   39: istore_1
    //   40: iload_1
    //   41: getstatic 77	uuuuuu/tytyty:b00780078xxx007800780078x	I
    //   44: iload_1
    //   45: iadd
    //   46: imul
    //   47: getstatic 79	uuuuuu/tytyty:bxx0078xx007800780078x	I
    //   50: irem
    //   51: tableswitch	default:+17->68, 0:+61->112
    //   68: ldc 2
    //   70: ldc 81
    //   72: sipush 170
    //   75: iconst_0
    //   76: invokestatic 55	xxxxxx/uxxxxx:bb00620062bb0062b0062b0062	(Ljava/lang/String;CC)Ljava/lang/String;
    //   79: iconst_0
    //   80: anewarray 57	java/lang/Class
    //   83: invokevirtual 61	java/lang/Class:getMethod	(Ljava/lang/String;[Ljava/lang/Class;)Ljava/lang/reflect/Method;
    //   86: astore_2
    //   87: aload_2
    //   88: aconst_null
    //   89: iconst_0
    //   90: anewarray 4	java/lang/Object
    //   93: invokevirtual 67	java/lang/reflect/Method:invoke	(Ljava/lang/Object;[Ljava/lang/Object;)Ljava/lang/Object;
    //   96: astore_2
    //   97: aload_2
    //   98: checkcast 69	java/lang/Integer
    //   101: invokevirtual 73	java/lang/Integer:intValue	()I
    //   104: putstatic 75	uuuuuu/tytyty:b0078x0078xx007800780078x	I
    //   107: bipush 67
    //   109: putstatic 83	uuuuuu/tytyty:bx00780078xx007800780078x	I
    //   112: getstatic 77	uuuuuu/tytyty:b00780078xxx007800780078x	I
    //   115: iload_0
    //   116: iadd
    //   117: iload_0
    //   118: imul
    //   119: getstatic 79	uuuuuu/tytyty:bxx0078xx007800780078x	I
    //   122: irem
    //   123: tableswitch	default:+17->140, 0:+232->355
    //   140: getstatic 75	uuuuuu/tytyty:b0078x0078xx007800780078x	I
    //   143: getstatic 77	uuuuuu/tytyty:b00780078xxx007800780078x	I
    //   146: iadd
    //   147: getstatic 75	uuuuuu/tytyty:b0078x0078xx007800780078x	I
    //   150: imul
    //   151: getstatic 79	uuuuuu/tytyty:bxx0078xx007800780078x	I
    //   154: irem
    //   155: getstatic 83	uuuuuu/tytyty:bx00780078xx007800780078x	I
    //   158: if_icmpeq +192 -> 350
    //   161: ldc 2
    //   163: ldc 85
    //   165: sipush 204
    //   168: iconst_5
    //   169: invokestatic 55	xxxxxx/uxxxxx:bb00620062bb0062b0062b0062	(Ljava/lang/String;CC)Ljava/lang/String;
    //   172: iconst_0
    //   173: anewarray 57	java/lang/Class
    //   176: invokevirtual 61	java/lang/Class:getMethod	(Ljava/lang/String;[Ljava/lang/Class;)Ljava/lang/reflect/Method;
    //   179: astore_2
    //   180: aload_2
    //   181: aconst_null
    //   182: iconst_0
    //   183: anewarray 4	java/lang/Object
    //   186: invokevirtual 67	java/lang/reflect/Method:invoke	(Ljava/lang/Object;[Ljava/lang/Object;)Ljava/lang/Object;
    //   189: astore_2
    //   190: aload_2
    //   191: checkcast 69	java/lang/Integer
    //   194: invokevirtual 73	java/lang/Integer:intValue	()I
    //   197: istore_0
    //   198: iload_0
    //   199: getstatic 77	uuuuuu/tytyty:b00780078xxx007800780078x	I
    //   202: iload_0
    //   203: iadd
    //   204: imul
    //   205: getstatic 79	uuuuuu/tytyty:bxx0078xx007800780078x	I
    //   208: irem
    //   209: tableswitch	default:+19->228, 0:+95->304
    //   228: ldc 2
    //   230: ldc 85
    //   232: bipush 104
    //   234: iconst_3
    //   235: invokestatic 55	xxxxxx/uxxxxx:bb00620062bb0062b0062b0062	(Ljava/lang/String;CC)Ljava/lang/String;
    //   238: iconst_0
    //   239: anewarray 57	java/lang/Class
    //   242: invokevirtual 61	java/lang/Class:getMethod	(Ljava/lang/String;[Ljava/lang/Class;)Ljava/lang/reflect/Method;
    //   245: astore_2
    //   246: aload_2
    //   247: aconst_null
    //   248: iconst_0
    //   249: anewarray 4	java/lang/Object
    //   252: invokevirtual 67	java/lang/reflect/Method:invoke	(Ljava/lang/Object;[Ljava/lang/Object;)Ljava/lang/Object;
    //   255: astore_2
    //   256: aload_2
    //   257: checkcast 69	java/lang/Integer
    //   260: invokevirtual 73	java/lang/Integer:intValue	()I
    //   263: putstatic 75	uuuuuu/tytyty:b0078x0078xx007800780078x	I
    //   266: ldc 2
    //   268: ldc 87
    //   270: bipush 87
    //   272: iconst_4
    //   273: invokestatic 55	xxxxxx/uxxxxx:bb00620062bb0062b0062b0062	(Ljava/lang/String;CC)Ljava/lang/String;
    //   276: iconst_0
    //   277: anewarray 57	java/lang/Class
    //   280: invokevirtual 61	java/lang/Class:getMethod	(Ljava/lang/String;[Ljava/lang/Class;)Ljava/lang/reflect/Method;
    //   283: astore_2
    //   284: aload_2
    //   285: aconst_null
    //   286: iconst_0
    //   287: anewarray 4	java/lang/Object
    //   290: invokevirtual 67	java/lang/reflect/Method:invoke	(Ljava/lang/Object;[Ljava/lang/Object;)Ljava/lang/Object;
    //   293: astore_2
    //   294: aload_2
    //   295: checkcast 69	java/lang/Integer
    //   298: invokevirtual 73	java/lang/Integer:intValue	()I
    //   301: putstatic 83	uuuuuu/tytyty:bx00780078xx007800780078x	I
    //   304: ldc 2
    //   306: ldc 89
    //   308: sipush 145
    //   311: bipush 106
    //   313: iconst_1
    //   314: invokestatic 93	xxxxxx/uxxxxx:bbbb0062b0062b0062b0062	(Ljava/lang/String;CCC)Ljava/lang/String;
    //   317: iconst_0
    //   318: anewarray 57	java/lang/Class
    //   321: invokevirtual 61	java/lang/Class:getMethod	(Ljava/lang/String;[Ljava/lang/Class;)Ljava/lang/reflect/Method;
    //   324: astore_2
    //   325: aload_2
    //   326: aconst_null
    //   327: iconst_0
    //   328: anewarray 4	java/lang/Object
    //   331: invokevirtual 67	java/lang/reflect/Method:invoke	(Ljava/lang/Object;[Ljava/lang/Object;)Ljava/lang/Object;
    //   334: astore_2
    //   335: aload_2
    //   336: checkcast 69	java/lang/Integer
    //   339: invokevirtual 73	java/lang/Integer:intValue	()I
    //   342: putstatic 75	uuuuuu/tytyty:b0078x0078xx007800780078x	I
    //   345: bipush 45
    //   347: putstatic 83	uuuuuu/tytyty:bx00780078xx007800780078x	I
    //   350: bipush 50
    //   352: putstatic 77	uuuuuu/tytyty:b00780078xxx007800780078x	I
    //   355: ldc 2
    //   357: invokevirtual 97	java/lang/Class:getSimpleName	()Ljava/lang/String;
    //   360: putstatic 99	uuuuuu/tytyty:bxxx00780078x00780078x	Ljava/lang/String;
    //   363: return
    //   364: astore_2
    //   365: aload_2
    //   366: invokevirtual 103	java/lang/reflect/InvocationTargetException:getCause	()Ljava/lang/Throwable;
    //   369: athrow
    //   370: astore_2
    //   371: aload_2
    //   372: invokevirtual 103	java/lang/reflect/InvocationTargetException:getCause	()Ljava/lang/Throwable;
    //   375: athrow
    //   376: astore_2
    //   377: aload_2
    //   378: invokevirtual 103	java/lang/reflect/InvocationTargetException:getCause	()Ljava/lang/Throwable;
    //   381: athrow
    //   382: astore_2
    //   383: aload_2
    //   384: invokevirtual 103	java/lang/reflect/InvocationTargetException:getCause	()Ljava/lang/Throwable;
    //   387: athrow
    //   388: astore_2
    //   389: aload_2
    //   390: invokevirtual 103	java/lang/reflect/InvocationTargetException:getCause	()Ljava/lang/Throwable;
    //   393: athrow
    //   394: astore_2
    //   395: aload_2
    //   396: invokevirtual 103	java/lang/reflect/InvocationTargetException:getCause	()Ljava/lang/Throwable;
    //   399: athrow
    // Local variable table:
    //   start	length	slot	name	signature
    //   35	170	0	i	int
    //   39	8	1	j	int
    //   17	319	2	localObject	Object
    //   364	2	2	localInvocationTargetException1	java.lang.reflect.InvocationTargetException
    //   370	2	2	localInvocationTargetException2	java.lang.reflect.InvocationTargetException
    //   376	2	2	localInvocationTargetException3	java.lang.reflect.InvocationTargetException
    //   382	2	2	localInvocationTargetException4	java.lang.reflect.InvocationTargetException
    //   388	2	2	localInvocationTargetException5	java.lang.reflect.InvocationTargetException
    //   394	2	2	localInvocationTargetException6	java.lang.reflect.InvocationTargetException
    // Exception table:
    //   from	to	target	type
    //   180	190	364	java/lang/reflect/InvocationTargetException
    //   18	28	370	java/lang/reflect/InvocationTargetException
    //   246	256	376	java/lang/reflect/InvocationTargetException
    //   284	294	382	java/lang/reflect/InvocationTargetException
    //   325	335	388	java/lang/reflect/InvocationTargetException
    //   87	97	394	java/lang/reflect/InvocationTargetException
  }
  
  public tytyty(ytyyty.yytyty paramYytyty)
  {
    tttyyt.bq0071qqqqq007100710071().bpp00700070pppppp(this);
    this.bx0078xxx007800780078x = paramYytyty;
    this.bxxxxx007800780078x = new lloolo();
    this.b00780078x00780078x00780078x = new oooloo();
    this.b0078x007800780078x00780078x = new HashMap();
  }
  
  public static int b007100710071qqq0071q00710071()
  {
    return 1;
  }
  
  public static int b0071qq0071qq0071q00710071()
  {
    return 2;
  }
  
  /* Error */
  private void bq0071q0071qq0071q00710071(TokenizationPayload paramTokenizationPayload, String paramString)
  {
    // Byte code:
    //   0: aload_0
    //   1: aload_1
    //   2: putfield 116	uuuuuu/tytyty:b0078xxxx007800780078x	Lcom/db/pwcc/dbmobile/model/tokenization/TokenizationPayload;
    //   5: aload_1
    //   6: ifnonnull +648 -> 654
    //   9: new 175	com/db/pwcc/dbmobile/model/tokenization/TokenizationPayload$yvvvvy
    //   12: dup
    //   13: invokespecial 176	com/db/pwcc/dbmobile/model/tokenization/TokenizationPayload$yvvvvy:<init>	()V
    //   16: astore_1
    //   17: getstatic 75	uuuuuu/tytyty:b0078x0078xx007800780078x	I
    //   20: getstatic 77	uuuuuu/tytyty:b00780078xxx007800780078x	I
    //   23: iadd
    //   24: getstatic 75	uuuuuu/tytyty:b0078x0078xx007800780078x	I
    //   27: imul
    //   28: getstatic 79	uuuuuu/tytyty:bxx0078xx007800780078x	I
    //   31: irem
    //   32: getstatic 83	uuuuuu/tytyty:bx00780078xx007800780078x	I
    //   35: if_icmpeq +255 -> 290
    //   38: bipush 22
    //   40: putstatic 75	uuuuuu/tytyty:b0078x0078xx007800780078x	I
    //   43: ldc 2
    //   45: ldc -78
    //   47: sipush 233
    //   50: bipush 40
    //   52: iconst_0
    //   53: invokestatic 93	xxxxxx/uxxxxx:bbbb0062b0062b0062b0062	(Ljava/lang/String;CCC)Ljava/lang/String;
    //   56: iconst_0
    //   57: anewarray 57	java/lang/Class
    //   60: invokevirtual 61	java/lang/Class:getMethod	(Ljava/lang/String;[Ljava/lang/Class;)Ljava/lang/reflect/Method;
    //   63: astore 4
    //   65: aload 4
    //   67: aconst_null
    //   68: iconst_0
    //   69: anewarray 4	java/lang/Object
    //   72: invokevirtual 67	java/lang/reflect/Method:invoke	(Ljava/lang/Object;[Ljava/lang/Object;)Ljava/lang/Object;
    //   75: astore 4
    //   77: aload 4
    //   79: checkcast 69	java/lang/Integer
    //   82: invokevirtual 73	java/lang/Integer:intValue	()I
    //   85: putstatic 83	uuuuuu/tytyty:bx00780078xx007800780078x	I
    //   88: getstatic 75	uuuuuu/tytyty:b0078x0078xx007800780078x	I
    //   91: istore_3
    //   92: ldc 2
    //   94: ldc -76
    //   96: bipush 9
    //   98: bipush 40
    //   100: iconst_0
    //   101: invokestatic 93	xxxxxx/uxxxxx:bbbb0062b0062b0062b0062	(Ljava/lang/String;CCC)Ljava/lang/String;
    //   104: iconst_0
    //   105: anewarray 57	java/lang/Class
    //   108: invokevirtual 61	java/lang/Class:getMethod	(Ljava/lang/String;[Ljava/lang/Class;)Ljava/lang/reflect/Method;
    //   111: astore 4
    //   113: aload 4
    //   115: aconst_null
    //   116: iconst_0
    //   117: anewarray 4	java/lang/Object
    //   120: invokevirtual 67	java/lang/reflect/Method:invoke	(Ljava/lang/Object;[Ljava/lang/Object;)Ljava/lang/Object;
    //   123: astore 4
    //   125: aload 4
    //   127: checkcast 69	java/lang/Integer
    //   130: invokevirtual 73	java/lang/Integer:intValue	()I
    //   133: iload_3
    //   134: iadd
    //   135: iload_3
    //   136: imul
    //   137: getstatic 79	uuuuuu/tytyty:bxx0078xx007800780078x	I
    //   140: irem
    //   141: tableswitch	default:+19->160, 0:+149->290
    //   160: ldc 2
    //   162: ldc -74
    //   164: bipush 29
    //   166: iconst_4
    //   167: invokestatic 55	xxxxxx/uxxxxx:bb00620062bb0062b0062b0062	(Ljava/lang/String;CC)Ljava/lang/String;
    //   170: iconst_0
    //   171: anewarray 57	java/lang/Class
    //   174: invokevirtual 61	java/lang/Class:getMethod	(Ljava/lang/String;[Ljava/lang/Class;)Ljava/lang/reflect/Method;
    //   177: astore 4
    //   179: aload 4
    //   181: aconst_null
    //   182: iconst_0
    //   183: anewarray 4	java/lang/Object
    //   186: invokevirtual 67	java/lang/reflect/Method:invoke	(Ljava/lang/Object;[Ljava/lang/Object;)Ljava/lang/Object;
    //   189: astore 4
    //   191: aload 4
    //   193: checkcast 69	java/lang/Integer
    //   196: invokevirtual 73	java/lang/Integer:intValue	()I
    //   199: putstatic 75	uuuuuu/tytyty:b0078x0078xx007800780078x	I
    //   202: ldc 2
    //   204: ldc -72
    //   206: sipush 176
    //   209: sipush 198
    //   212: iconst_1
    //   213: invokestatic 93	xxxxxx/uxxxxx:bbbb0062b0062b0062b0062	(Ljava/lang/String;CCC)Ljava/lang/String;
    //   216: iconst_0
    //   217: anewarray 57	java/lang/Class
    //   220: invokevirtual 61	java/lang/Class:getMethod	(Ljava/lang/String;[Ljava/lang/Class;)Ljava/lang/reflect/Method;
    //   223: astore 4
    //   225: aload 4
    //   227: aconst_null
    //   228: iconst_0
    //   229: anewarray 4	java/lang/Object
    //   232: invokevirtual 67	java/lang/reflect/Method:invoke	(Ljava/lang/Object;[Ljava/lang/Object;)Ljava/lang/Object;
    //   235: astore 4
    //   237: aload 4
    //   239: checkcast 69	java/lang/Integer
    //   242: invokevirtual 73	java/lang/Integer:intValue	()I
    //   245: putstatic 83	uuuuuu/tytyty:bx00780078xx007800780078x	I
    //   248: getstatic 75	uuuuuu/tytyty:b0078x0078xx007800780078x	I
    //   251: istore_3
    //   252: iload_3
    //   253: getstatic 77	uuuuuu/tytyty:b00780078xxx007800780078x	I
    //   256: iload_3
    //   257: iadd
    //   258: imul
    //   259: getstatic 79	uuuuuu/tytyty:bxx0078xx007800780078x	I
    //   262: irem
    //   263: tableswitch	default:+17->280, 0:+27->290
    //   280: bipush 11
    //   282: putstatic 75	uuuuuu/tytyty:b0078x0078xx007800780078x	I
    //   285: bipush 62
    //   287: putstatic 83	uuuuuu/tytyty:bx00780078xx007800780078x	I
    //   290: aload_0
    //   291: getfield 186	uuuuuu/tytyty:bxx007800780078x00780078x	Lcom/db/pwcc/dbmobile/secure/preferences/SharedPreferencesHelper;
    //   294: astore 4
    //   296: ldc -68
    //   298: ldc -66
    //   300: bipush 110
    //   302: iconst_1
    //   303: invokestatic 55	xxxxxx/uxxxxx:bb00620062bb0062b0062b0062	(Ljava/lang/String;CC)Ljava/lang/String;
    //   306: iconst_0
    //   307: anewarray 57	java/lang/Class
    //   310: invokevirtual 61	java/lang/Class:getMethod	(Ljava/lang/String;[Ljava/lang/Class;)Ljava/lang/reflect/Method;
    //   313: astore 5
    //   315: aload 5
    //   317: aload 4
    //   319: iconst_0
    //   320: anewarray 4	java/lang/Object
    //   323: invokevirtual 67	java/lang/reflect/Method:invoke	(Ljava/lang/Object;[Ljava/lang/Object;)Ljava/lang/Object;
    //   326: astore 4
    //   328: aload_1
    //   329: aload 4
    //   331: checkcast 192	java/lang/String
    //   334: invokevirtual 196	com/db/pwcc/dbmobile/model/tokenization/TokenizationPayload$yvvvvy:b0075uu0075uuu00750075u	(Ljava/lang/String;)Lcom/db/pwcc/dbmobile/model/tokenization/TokenizationPayload$yvvvvy;
    //   337: aload_0
    //   338: getfield 198	uuuuuu/tytyty:bx0078x00780078x00780078x	Luuuuuu/yttttt;
    //   341: invokeinterface 203 1 0
    //   346: invokevirtual 206	com/db/pwcc/dbmobile/model/tokenization/TokenizationPayload$yvvvvy:b007500750075uuuu00750075u	(Ljava/lang/String;)Lcom/db/pwcc/dbmobile/model/tokenization/TokenizationPayload$yvvvvy;
    //   349: aload_0
    //   350: getfield 110	uuuuuu/tytyty:bx0078xxx007800780078x	Luuuuuu/ytyyty$yytyty;
    //   353: invokeinterface 211 1 0
    //   358: invokevirtual 214	com/db/pwcc/dbmobile/model/tokenization/TokenizationPayload$yvvvvy:bu00750075uuuu00750075u	(Ljava/lang/String;)Lcom/db/pwcc/dbmobile/model/tokenization/TokenizationPayload$yvvvvy;
    //   361: aload_0
    //   362: getfield 216	uuuuuu/tytyty:bx0078007800780078x00780078x	Luuuuuu/qpqppq;
    //   365: aload_2
    //   366: invokevirtual 222	uuuuuu/qpqppq:b006Bk006Bkkk006Bkkk	(Ljava/lang/String;)Ljava/lang/String;
    //   369: invokevirtual 225	com/db/pwcc/dbmobile/model/tokenization/TokenizationPayload$yvvvvy:buu00750075uuu00750075u	(Ljava/lang/String;)Lcom/db/pwcc/dbmobile/model/tokenization/TokenizationPayload$yvvvvy;
    //   372: aload_0
    //   373: getfield 216	uuuuuu/tytyty:bx0078007800780078x00780078x	Luuuuuu/qpqppq;
    //   376: aload_2
    //   377: invokevirtual 222	uuuuuu/qpqppq:b006Bk006Bkkk006Bkkk	(Ljava/lang/String;)Ljava/lang/String;
    //   380: invokevirtual 228	com/db/pwcc/dbmobile/model/tokenization/TokenizationPayload$yvvvvy:b00750075u0075uuu00750075u	(Ljava/lang/String;)Lcom/db/pwcc/dbmobile/model/tokenization/TokenizationPayload$yvvvvy;
    //   383: astore_1
    //   384: ldc -26
    //   386: ldc -24
    //   388: bipush 27
    //   390: iconst_0
    //   391: invokestatic 55	xxxxxx/uxxxxx:bb00620062bb0062b0062b0062	(Ljava/lang/String;CC)Ljava/lang/String;
    //   394: iconst_4
    //   395: anewarray 57	java/lang/Class
    //   398: dup
    //   399: iconst_0
    //   400: ldc -64
    //   402: aastore
    //   403: dup
    //   404: iconst_1
    //   405: getstatic 238	java/lang/Character:TYPE	Ljava/lang/Class;
    //   408: aastore
    //   409: dup
    //   410: iconst_2
    //   411: getstatic 238	java/lang/Character:TYPE	Ljava/lang/Class;
    //   414: aastore
    //   415: dup
    //   416: iconst_3
    //   417: getstatic 238	java/lang/Character:TYPE	Ljava/lang/Class;
    //   420: aastore
    //   421: invokevirtual 61	java/lang/Class:getMethod	(Ljava/lang/String;[Ljava/lang/Class;)Ljava/lang/reflect/Method;
    //   424: astore 4
    //   426: aload 4
    //   428: aconst_null
    //   429: iconst_4
    //   430: anewarray 4	java/lang/Object
    //   433: dup
    //   434: iconst_0
    //   435: ldc -16
    //   437: aastore
    //   438: dup
    //   439: iconst_1
    //   440: bipush 126
    //   442: invokestatic 244	java/lang/Character:valueOf	(C)Ljava/lang/Character;
    //   445: aastore
    //   446: dup
    //   447: iconst_2
    //   448: bipush 97
    //   450: invokestatic 244	java/lang/Character:valueOf	(C)Ljava/lang/Character;
    //   453: aastore
    //   454: dup
    //   455: iconst_3
    //   456: iconst_3
    //   457: invokestatic 244	java/lang/Character:valueOf	(C)Ljava/lang/Character;
    //   460: aastore
    //   461: invokevirtual 67	java/lang/reflect/Method:invoke	(Ljava/lang/Object;[Ljava/lang/Object;)Ljava/lang/Object;
    //   464: astore 4
    //   466: aload_1
    //   467: aload 4
    //   469: checkcast 192	java/lang/String
    //   472: invokevirtual 247	com/db/pwcc/dbmobile/model/tokenization/TokenizationPayload$yvvvvy:bu0075u0075uuu00750075u	(Ljava/lang/String;)Lcom/db/pwcc/dbmobile/model/tokenization/TokenizationPayload$yvvvvy;
    //   475: astore_1
    //   476: ldc -26
    //   478: ldc -7
    //   480: bipush 58
    //   482: iconst_2
    //   483: invokestatic 55	xxxxxx/uxxxxx:bb00620062bb0062b0062b0062	(Ljava/lang/String;CC)Ljava/lang/String;
    //   486: iconst_4
    //   487: anewarray 57	java/lang/Class
    //   490: dup
    //   491: iconst_0
    //   492: ldc -64
    //   494: aastore
    //   495: dup
    //   496: iconst_1
    //   497: getstatic 238	java/lang/Character:TYPE	Ljava/lang/Class;
    //   500: aastore
    //   501: dup
    //   502: iconst_2
    //   503: getstatic 238	java/lang/Character:TYPE	Ljava/lang/Class;
    //   506: aastore
    //   507: dup
    //   508: iconst_3
    //   509: getstatic 238	java/lang/Character:TYPE	Ljava/lang/Class;
    //   512: aastore
    //   513: invokevirtual 61	java/lang/Class:getMethod	(Ljava/lang/String;[Ljava/lang/Class;)Ljava/lang/reflect/Method;
    //   516: astore 4
    //   518: aload 4
    //   520: aconst_null
    //   521: iconst_4
    //   522: anewarray 4	java/lang/Object
    //   525: dup
    //   526: iconst_0
    //   527: ldc -5
    //   529: aastore
    //   530: dup
    //   531: iconst_1
    //   532: sipush 201
    //   535: invokestatic 244	java/lang/Character:valueOf	(C)Ljava/lang/Character;
    //   538: aastore
    //   539: dup
    //   540: iconst_2
    //   541: bipush 116
    //   543: invokestatic 244	java/lang/Character:valueOf	(C)Ljava/lang/Character;
    //   546: aastore
    //   547: dup
    //   548: iconst_3
    //   549: iconst_3
    //   550: invokestatic 244	java/lang/Character:valueOf	(C)Ljava/lang/Character;
    //   553: aastore
    //   554: invokevirtual 67	java/lang/reflect/Method:invoke	(Ljava/lang/Object;[Ljava/lang/Object;)Ljava/lang/Object;
    //   557: astore 4
    //   559: aload_1
    //   560: aload 4
    //   562: checkcast 192	java/lang/String
    //   565: invokevirtual 254	com/db/pwcc/dbmobile/model/tokenization/TokenizationPayload$yvvvvy:buuu0075uuu00750075u	(Ljava/lang/String;)Lcom/db/pwcc/dbmobile/model/tokenization/TokenizationPayload$yvvvvy;
    //   568: aload_2
    //   569: invokevirtual 257	com/db/pwcc/dbmobile/model/tokenization/TokenizationPayload$yvvvvy:b0075u0075uuuu00750075u	(Ljava/lang/String;)Lcom/db/pwcc/dbmobile/model/tokenization/TokenizationPayload$yvvvvy;
    //   572: invokevirtual 261	com/db/pwcc/dbmobile/model/tokenization/TokenizationPayload$yvvvvy:buu0075uuuu00750075u	()Lcom/db/pwcc/dbmobile/model/tokenization/TokenizationPayload;
    //   575: astore_1
    //   576: invokestatic 267	java/util/UUID:randomUUID	()Ljava/util/UUID;
    //   579: invokevirtual 270	java/util/UUID:toString	()Ljava/lang/String;
    //   582: astore_2
    //   583: new 272	com/db/pwcc/dbmobile/model/tan/ChallengeRequest
    //   586: dup
    //   587: getstatic 278	com/db/pwcc/dbmobile/model/sepa/TransactionState:CHALLENGE_REQUESTED	Lcom/db/pwcc/dbmobile/model/sepa/TransactionState;
    //   590: aload_2
    //   591: aload_0
    //   592: getfield 110	uuuuuu/tytyty:bx0078xxx007800780078x	Luuuuuu/ytyyty$yytyty;
    //   595: invokeinterface 282 1 0
    //   600: aload_1
    //   601: invokevirtual 288	com/db/pwcc/dbmobile/model/tokenization/TokenizationPayload:getTransaction	()Lcom/db/pwcc/dbmobile/model/tokenization/MoPayTransaction;
    //   604: invokespecial 291	com/db/pwcc/dbmobile/model/tan/ChallengeRequest:<init>	(Lcom/db/pwcc/dbmobile/model/sepa/TransactionState;Ljava/lang/String;Lcom/db/pwcc/dbmobile/model/tan/Authorization;Lcom/db/pwcc/dbmobile/model/common/Transaction;)V
    //   607: astore 4
    //   609: aload_0
    //   610: getfield 118	uuuuuu/tytyty:b0078x007800780078x00780078x	Ljava/util/Map;
    //   613: getstatic 297	uuuuuu/lolllo:bq0071007100710071qqq0071	Luuuuuu/lolllo;
    //   616: invokevirtual 300	uuuuuu/lolllo:name	()Ljava/lang/String;
    //   619: iconst_1
    //   620: invokestatic 305	java/lang/Boolean:valueOf	(Z)Ljava/lang/Boolean;
    //   623: invokeinterface 311 3 0
    //   628: pop
    //   629: aload_0
    //   630: getfield 114	uuuuuu/tytyty:b00780078x00780078x00780078x	Luuuuuu/vpvppv;
    //   633: new 10	uuuuuu/tytyty$yttyty
    //   636: dup
    //   637: aload_0
    //   638: aload_1
    //   639: invokevirtual 288	com/db/pwcc/dbmobile/model/tokenization/TokenizationPayload:getTransaction	()Lcom/db/pwcc/dbmobile/model/tokenization/MoPayTransaction;
    //   642: aload_2
    //   643: invokespecial 314	uuuuuu/tytyty$yttyty:<init>	(Luuuuuu/tytyty;Lcom/db/pwcc/dbmobile/model/tokenization/MoPayTransaction;Ljava/lang/String;)V
    //   646: aload 4
    //   648: invokeinterface 320 3 0
    //   653: return
    //   654: getstatic 75	uuuuuu/tytyty:b0078x0078xx007800780078x	I
    //   657: istore_3
    //   658: ldc 2
    //   660: ldc_w 322
    //   663: sipush 234
    //   666: iconst_2
    //   667: invokestatic 55	xxxxxx/uxxxxx:bb00620062bb0062b0062b0062	(Ljava/lang/String;CC)Ljava/lang/String;
    //   670: iconst_0
    //   671: anewarray 57	java/lang/Class
    //   674: invokevirtual 61	java/lang/Class:getMethod	(Ljava/lang/String;[Ljava/lang/Class;)Ljava/lang/reflect/Method;
    //   677: astore_2
    //   678: aload_2
    //   679: aconst_null
    //   680: iconst_0
    //   681: anewarray 4	java/lang/Object
    //   684: invokevirtual 67	java/lang/reflect/Method:invoke	(Ljava/lang/Object;[Ljava/lang/Object;)Ljava/lang/Object;
    //   687: astore_2
    //   688: aload_2
    //   689: checkcast 69	java/lang/Integer
    //   692: invokevirtual 73	java/lang/Integer:intValue	()I
    //   695: iload_3
    //   696: iadd
    //   697: iload_3
    //   698: imul
    //   699: getstatic 79	uuuuuu/tytyty:bxx0078xx007800780078x	I
    //   702: irem
    //   703: tableswitch	default:+17->720, 0:+99->802
    //   720: ldc 2
    //   722: ldc_w 324
    //   725: bipush 79
    //   727: iconst_5
    //   728: invokestatic 55	xxxxxx/uxxxxx:bb00620062bb0062b0062b0062	(Ljava/lang/String;CC)Ljava/lang/String;
    //   731: iconst_0
    //   732: anewarray 57	java/lang/Class
    //   735: invokevirtual 61	java/lang/Class:getMethod	(Ljava/lang/String;[Ljava/lang/Class;)Ljava/lang/reflect/Method;
    //   738: astore_2
    //   739: aload_2
    //   740: aconst_null
    //   741: iconst_0
    //   742: anewarray 4	java/lang/Object
    //   745: invokevirtual 67	java/lang/reflect/Method:invoke	(Ljava/lang/Object;[Ljava/lang/Object;)Ljava/lang/Object;
    //   748: astore_2
    //   749: aload_2
    //   750: checkcast 69	java/lang/Integer
    //   753: invokevirtual 73	java/lang/Integer:intValue	()I
    //   756: putstatic 75	uuuuuu/tytyty:b0078x0078xx007800780078x	I
    //   759: ldc 2
    //   761: ldc_w 326
    //   764: sipush 146
    //   767: sipush 187
    //   770: iconst_1
    //   771: invokestatic 93	xxxxxx/uxxxxx:bbbb0062b0062b0062b0062	(Ljava/lang/String;CCC)Ljava/lang/String;
    //   774: iconst_0
    //   775: anewarray 57	java/lang/Class
    //   778: invokevirtual 61	java/lang/Class:getMethod	(Ljava/lang/String;[Ljava/lang/Class;)Ljava/lang/reflect/Method;
    //   781: astore_2
    //   782: aload_2
    //   783: aconst_null
    //   784: iconst_0
    //   785: anewarray 4	java/lang/Object
    //   788: invokevirtual 67	java/lang/reflect/Method:invoke	(Ljava/lang/Object;[Ljava/lang/Object;)Ljava/lang/Object;
    //   791: astore_2
    //   792: aload_2
    //   793: checkcast 69	java/lang/Integer
    //   796: invokevirtual 73	java/lang/Integer:intValue	()I
    //   799: putstatic 83	uuuuuu/tytyty:bx00780078xx007800780078x	I
    //   802: aload_1
    //   803: invokevirtual 329	com/db/pwcc/dbmobile/model/tokenization/TokenizationPayload:getCorrelationId	()Ljava/lang/String;
    //   806: astore_2
    //   807: goto -224 -> 583
    //   810: astore_1
    //   811: aload_1
    //   812: invokevirtual 103	java/lang/reflect/InvocationTargetException:getCause	()Ljava/lang/Throwable;
    //   815: athrow
    //   816: astore_1
    //   817: aload_1
    //   818: invokevirtual 103	java/lang/reflect/InvocationTargetException:getCause	()Ljava/lang/Throwable;
    //   821: athrow
    //   822: astore_1
    //   823: aload_1
    //   824: invokevirtual 103	java/lang/reflect/InvocationTargetException:getCause	()Ljava/lang/Throwable;
    //   827: athrow
    //   828: astore_1
    //   829: aload_1
    //   830: invokevirtual 103	java/lang/reflect/InvocationTargetException:getCause	()Ljava/lang/Throwable;
    //   833: athrow
    //   834: astore_1
    //   835: aload_1
    //   836: invokevirtual 103	java/lang/reflect/InvocationTargetException:getCause	()Ljava/lang/Throwable;
    //   839: athrow
    //   840: astore_1
    //   841: aload_1
    //   842: invokevirtual 103	java/lang/reflect/InvocationTargetException:getCause	()Ljava/lang/Throwable;
    //   845: athrow
    //   846: astore_1
    //   847: aload_1
    //   848: invokevirtual 103	java/lang/reflect/InvocationTargetException:getCause	()Ljava/lang/Throwable;
    //   851: athrow
    //   852: astore_1
    //   853: aload_1
    //   854: invokevirtual 103	java/lang/reflect/InvocationTargetException:getCause	()Ljava/lang/Throwable;
    //   857: athrow
    //   858: astore_1
    //   859: aload_1
    //   860: invokevirtual 103	java/lang/reflect/InvocationTargetException:getCause	()Ljava/lang/Throwable;
    //   863: athrow
    //   864: astore_1
    //   865: aload_1
    //   866: invokevirtual 103	java/lang/reflect/InvocationTargetException:getCause	()Ljava/lang/Throwable;
    //   869: athrow
    // Local variable table:
    //   start	length	slot	name	signature
    //   0	870	0	this	tytyty
    //   0	870	1	paramTokenizationPayload	TokenizationPayload
    //   0	870	2	paramString	String
    //   91	608	3	i	int
    //   63	584	4	localObject	Object
    //   313	3	5	localMethod	java.lang.reflect.Method
    // Exception table:
    //   from	to	target	type
    //   179	191	810	java/lang/reflect/InvocationTargetException
    //   315	328	816	java/lang/reflect/InvocationTargetException
    //   65	77	822	java/lang/reflect/InvocationTargetException
    //   113	125	828	java/lang/reflect/InvocationTargetException
    //   678	688	834	java/lang/reflect/InvocationTargetException
    //   739	749	840	java/lang/reflect/InvocationTargetException
    //   782	792	846	java/lang/reflect/InvocationTargetException
    //   225	237	852	java/lang/reflect/InvocationTargetException
    //   426	466	858	java/lang/reflect/InvocationTargetException
    //   518	559	864	java/lang/reflect/InvocationTargetException
  }
  
  public static int bqqq0071qq0071q00710071()
  {
    return 18;
  }
  
  /* Error */
  public void b0070007000700070pp007000700070p(com.db.pwcc.dbmobile.model.error.DbError paramDbError)
  {
    // Byte code:
    //   0: getstatic 348	com/db/pwcc/dbmobile/model/error/DbErrorCode:NO_INTERNET_ERROR	Lcom/db/pwcc/dbmobile/model/error/DbErrorCode;
    //   3: aload_1
    //   4: invokevirtual 354	com/db/pwcc/dbmobile/model/error/DbError:getDbCode	()Lcom/db/pwcc/dbmobile/model/error/DbErrorCode;
    //   7: if_acmpne +28 -> 35
    //   10: aload_0
    //   11: getfield 110	uuuuuu/tytyty:bx0078xxx007800780078x	Luuuuuu/ytyyty$yytyty;
    //   14: getstatic 360	uuuuuu/kvkvvv:bf00660066f0066f006600660066	Luuuuuu/kvkvvv;
    //   17: invokeinterface 364 2 0
    //   22: aload_0
    //   23: getfield 110	uuuuuu/tytyty:bx0078xxx007800780078x	Luuuuuu/ytyyty$yytyty;
    //   26: getstatic 369	com/db/pwcc/dbmobile/mobile_payment/R$string:check_internet_connection	I
    //   29: invokeinterface 373 2 0
    //   34: return
    //   35: aload_0
    //   36: getfield 118	uuuuuu/tytyty:b0078x007800780078x00780078x	Ljava/util/Map;
    //   39: getstatic 297	uuuuuu/lolllo:bq0071007100710071qqq0071	Luuuuuu/lolllo;
    //   42: invokevirtual 300	uuuuuu/lolllo:name	()Ljava/lang/String;
    //   45: invokeinterface 377 2 0
    //   50: ifeq -16 -> 34
    //   53: aload_0
    //   54: getfield 118	uuuuuu/tytyty:b0078x007800780078x00780078x	Ljava/util/Map;
    //   57: getstatic 380	uuuuuu/lolllo:bqq0071qq0071qq0071	Luuuuuu/lolllo;
    //   60: invokevirtual 300	uuuuuu/lolllo:name	()Ljava/lang/String;
    //   63: invokeinterface 384 2 0
    //   68: checkcast 302	java/lang/Boolean
    //   71: invokevirtual 388	java/lang/Boolean:booleanValue	()Z
    //   74: ifeq -40 -> 34
    //   77: aload_0
    //   78: getfield 118	uuuuuu/tytyty:b0078x007800780078x00780078x	Ljava/util/Map;
    //   81: getstatic 297	uuuuuu/lolllo:bq0071007100710071qqq0071	Luuuuuu/lolllo;
    //   84: invokevirtual 300	uuuuuu/lolllo:name	()Ljava/lang/String;
    //   87: iconst_0
    //   88: invokestatic 305	java/lang/Boolean:valueOf	(Z)Ljava/lang/Boolean;
    //   91: invokeinterface 311 3 0
    //   96: pop
    //   97: getstatic 75	uuuuuu/tytyty:b0078x0078xx007800780078x	I
    //   100: getstatic 77	uuuuuu/tytyty:b00780078xxx007800780078x	I
    //   103: iadd
    //   104: getstatic 75	uuuuuu/tytyty:b0078x0078xx007800780078x	I
    //   107: imul
    //   108: getstatic 79	uuuuuu/tytyty:bxx0078xx007800780078x	I
    //   111: irem
    //   112: getstatic 83	uuuuuu/tytyty:bx00780078xx007800780078x	I
    //   115: if_icmpeq +13 -> 128
    //   118: bipush 14
    //   120: putstatic 75	uuuuuu/tytyty:b0078x0078xx007800780078x	I
    //   123: bipush 18
    //   125: putstatic 83	uuuuuu/tytyty:bx00780078xx007800780078x	I
    //   128: aload_0
    //   129: getfield 110	uuuuuu/tytyty:bx0078xxx007800780078x	Luuuuuu/ytyyty$yytyty;
    //   132: aload_1
    //   133: invokevirtual 391	com/db/pwcc/dbmobile/model/error/DbError:getMessage	()Ljava/lang/String;
    //   136: invokeinterface 394 2 0
    //   141: getstatic 75	uuuuuu/tytyty:b0078x0078xx007800780078x	I
    //   144: getstatic 77	uuuuuu/tytyty:b00780078xxx007800780078x	I
    //   147: iadd
    //   148: getstatic 75	uuuuuu/tytyty:b0078x0078xx007800780078x	I
    //   151: imul
    //   152: getstatic 79	uuuuuu/tytyty:bxx0078xx007800780078x	I
    //   155: irem
    //   156: getstatic 83	uuuuuu/tytyty:bx00780078xx007800780078x	I
    //   159: if_icmpeq +226 -> 385
    //   162: getstatic 75	uuuuuu/tytyty:b0078x0078xx007800780078x	I
    //   165: getstatic 77	uuuuuu/tytyty:b00780078xxx007800780078x	I
    //   168: iadd
    //   169: getstatic 75	uuuuuu/tytyty:b0078x0078xx007800780078x	I
    //   172: imul
    //   173: getstatic 79	uuuuuu/tytyty:bxx0078xx007800780078x	I
    //   176: irem
    //   177: getstatic 83	uuuuuu/tytyty:bx00780078xx007800780078x	I
    //   180: if_icmpeq +161 -> 341
    //   183: ldc 2
    //   185: ldc_w 396
    //   188: bipush 92
    //   190: iconst_2
    //   191: invokestatic 55	xxxxxx/uxxxxx:bb00620062bb0062b0062b0062	(Ljava/lang/String;CC)Ljava/lang/String;
    //   194: iconst_0
    //   195: anewarray 57	java/lang/Class
    //   198: invokevirtual 61	java/lang/Class:getMethod	(Ljava/lang/String;[Ljava/lang/Class;)Ljava/lang/reflect/Method;
    //   201: astore_1
    //   202: aload_1
    //   203: aconst_null
    //   204: iconst_0
    //   205: anewarray 4	java/lang/Object
    //   208: invokevirtual 67	java/lang/reflect/Method:invoke	(Ljava/lang/Object;[Ljava/lang/Object;)Ljava/lang/Object;
    //   211: astore_1
    //   212: aload_1
    //   213: checkcast 69	java/lang/Integer
    //   216: invokevirtual 73	java/lang/Integer:intValue	()I
    //   219: putstatic 75	uuuuuu/tytyty:b0078x0078xx007800780078x	I
    //   222: ldc 2
    //   224: ldc_w 398
    //   227: bipush 21
    //   229: bipush 97
    //   231: iconst_2
    //   232: invokestatic 93	xxxxxx/uxxxxx:bbbb0062b0062b0062b0062	(Ljava/lang/String;CCC)Ljava/lang/String;
    //   235: iconst_0
    //   236: anewarray 57	java/lang/Class
    //   239: invokevirtual 61	java/lang/Class:getMethod	(Ljava/lang/String;[Ljava/lang/Class;)Ljava/lang/reflect/Method;
    //   242: astore_1
    //   243: aload_1
    //   244: aconst_null
    //   245: iconst_0
    //   246: anewarray 4	java/lang/Object
    //   249: invokevirtual 67	java/lang/reflect/Method:invoke	(Ljava/lang/Object;[Ljava/lang/Object;)Ljava/lang/Object;
    //   252: astore_1
    //   253: aload_1
    //   254: checkcast 69	java/lang/Integer
    //   257: invokevirtual 73	java/lang/Integer:intValue	()I
    //   260: putstatic 83	uuuuuu/tytyty:bx00780078xx007800780078x	I
    //   263: getstatic 75	uuuuuu/tytyty:b0078x0078xx007800780078x	I
    //   266: istore_2
    //   267: iload_2
    //   268: getstatic 77	uuuuuu/tytyty:b00780078xxx007800780078x	I
    //   271: iload_2
    //   272: iadd
    //   273: imul
    //   274: getstatic 79	uuuuuu/tytyty:bxx0078xx007800780078x	I
    //   277: irem
    //   278: tableswitch	default:+18->296, 0:+63->341
    //   296: bipush 48
    //   298: putstatic 75	uuuuuu/tytyty:b0078x0078xx007800780078x	I
    //   301: ldc 2
    //   303: ldc_w 400
    //   306: sipush 205
    //   309: iconst_2
    //   310: invokestatic 55	xxxxxx/uxxxxx:bb00620062bb0062b0062b0062	(Ljava/lang/String;CC)Ljava/lang/String;
    //   313: iconst_0
    //   314: anewarray 57	java/lang/Class
    //   317: invokevirtual 61	java/lang/Class:getMethod	(Ljava/lang/String;[Ljava/lang/Class;)Ljava/lang/reflect/Method;
    //   320: astore_1
    //   321: aload_1
    //   322: aconst_null
    //   323: iconst_0
    //   324: anewarray 4	java/lang/Object
    //   327: invokevirtual 67	java/lang/reflect/Method:invoke	(Ljava/lang/Object;[Ljava/lang/Object;)Ljava/lang/Object;
    //   330: astore_1
    //   331: aload_1
    //   332: checkcast 69	java/lang/Integer
    //   335: invokevirtual 73	java/lang/Integer:intValue	()I
    //   338: putstatic 83	uuuuuu/tytyty:bx00780078xx007800780078x	I
    //   341: ldc 2
    //   343: ldc_w 402
    //   346: bipush 116
    //   348: iconst_1
    //   349: invokestatic 55	xxxxxx/uxxxxx:bb00620062bb0062b0062b0062	(Ljava/lang/String;CC)Ljava/lang/String;
    //   352: iconst_0
    //   353: anewarray 57	java/lang/Class
    //   356: invokevirtual 61	java/lang/Class:getMethod	(Ljava/lang/String;[Ljava/lang/Class;)Ljava/lang/reflect/Method;
    //   359: astore_1
    //   360: aload_1
    //   361: aconst_null
    //   362: iconst_0
    //   363: anewarray 4	java/lang/Object
    //   366: invokevirtual 67	java/lang/reflect/Method:invoke	(Ljava/lang/Object;[Ljava/lang/Object;)Ljava/lang/Object;
    //   369: astore_1
    //   370: aload_1
    //   371: checkcast 69	java/lang/Integer
    //   374: invokevirtual 73	java/lang/Integer:intValue	()I
    //   377: putstatic 75	uuuuuu/tytyty:b0078x0078xx007800780078x	I
    //   380: bipush 59
    //   382: putstatic 83	uuuuuu/tytyty:bx00780078xx007800780078x	I
    //   385: aload_0
    //   386: getfield 110	uuuuuu/tytyty:bx0078xxx007800780078x	Luuuuuu/ytyyty$yytyty;
    //   389: getstatic 360	uuuuuu/kvkvvv:bf00660066f0066f006600660066	Luuuuuu/kvkvvv;
    //   392: invokeinterface 364 2 0
    //   397: return
    //   398: astore_1
    //   399: aload_1
    //   400: invokevirtual 103	java/lang/reflect/InvocationTargetException:getCause	()Ljava/lang/Throwable;
    //   403: athrow
    //   404: astore_1
    //   405: aload_1
    //   406: invokevirtual 103	java/lang/reflect/InvocationTargetException:getCause	()Ljava/lang/Throwable;
    //   409: athrow
    //   410: astore_1
    //   411: aload_1
    //   412: invokevirtual 103	java/lang/reflect/InvocationTargetException:getCause	()Ljava/lang/Throwable;
    //   415: athrow
    //   416: astore_1
    //   417: aload_1
    //   418: invokevirtual 103	java/lang/reflect/InvocationTargetException:getCause	()Ljava/lang/Throwable;
    //   421: athrow
    // Local variable table:
    //   start	length	slot	name	signature
    //   0	422	0	this	tytyty
    //   0	422	1	paramDbError	com.db.pwcc.dbmobile.model.error.DbError
    //   266	8	2	i	int
    // Exception table:
    //   from	to	target	type
    //   360	370	398	java/lang/reflect/InvocationTargetException
    //   202	212	404	java/lang/reflect/InvocationTargetException
    //   243	253	410	java/lang/reflect/InvocationTargetException
    //   321	331	416	java/lang/reflect/InvocationTargetException
  }
  
  /* Error */
  public void b0071qqqqq0071q00710071(String paramString)
  {
    // Byte code:
    //   0: getstatic 75	uuuuuu/tytyty:b0078x0078xx007800780078x	I
    //   3: getstatic 77	uuuuuu/tytyty:b00780078xxx007800780078x	I
    //   6: iadd
    //   7: getstatic 75	uuuuuu/tytyty:b0078x0078xx007800780078x	I
    //   10: imul
    //   11: getstatic 79	uuuuuu/tytyty:bxx0078xx007800780078x	I
    //   14: irem
    //   15: getstatic 83	uuuuuu/tytyty:bx00780078xx007800780078x	I
    //   18: if_icmpeq +54 -> 72
    //   21: bipush 90
    //   23: putstatic 75	uuuuuu/tytyty:b0078x0078xx007800780078x	I
    //   26: ldc 2
    //   28: ldc_w 405
    //   31: sipush 142
    //   34: bipush 67
    //   36: iconst_0
    //   37: invokestatic 93	xxxxxx/uxxxxx:bbbb0062b0062b0062b0062	(Ljava/lang/String;CCC)Ljava/lang/String;
    //   40: iconst_0
    //   41: anewarray 57	java/lang/Class
    //   44: invokevirtual 61	java/lang/Class:getMethod	(Ljava/lang/String;[Ljava/lang/Class;)Ljava/lang/reflect/Method;
    //   47: astore 4
    //   49: aload 4
    //   51: aconst_null
    //   52: iconst_0
    //   53: anewarray 4	java/lang/Object
    //   56: invokevirtual 67	java/lang/reflect/Method:invoke	(Ljava/lang/Object;[Ljava/lang/Object;)Ljava/lang/Object;
    //   59: astore 4
    //   61: aload 4
    //   63: checkcast 69	java/lang/Integer
    //   66: invokevirtual 73	java/lang/Integer:intValue	()I
    //   69: putstatic 83	uuuuuu/tytyty:bx00780078xx007800780078x	I
    //   72: aload_0
    //   73: getfield 198	uuuuuu/tytyty:bx0078x00780078x00780078x	Luuuuuu/yttttt;
    //   76: aload_0
    //   77: getfield 216	uuuuuu/tytyty:bx0078007800780078x00780078x	Luuuuuu/qpqppq;
    //   80: aload_1
    //   81: invokevirtual 222	uuuuuu/qpqppq:b006Bk006Bkkk006Bkkk	(Ljava/lang/String;)Ljava/lang/String;
    //   84: invokeinterface 409 2 0
    //   89: astore 4
    //   91: aload 4
    //   93: ifnull +906 -> 999
    //   96: ldc_w 411
    //   99: ldc_w 413
    //   102: bipush 64
    //   104: sipush 154
    //   107: iconst_1
    //   108: invokestatic 93	xxxxxx/uxxxxx:bbbb0062b0062b0062b0062	(Ljava/lang/String;CCC)Ljava/lang/String;
    //   111: iconst_0
    //   112: anewarray 57	java/lang/Class
    //   115: invokevirtual 61	java/lang/Class:getMethod	(Ljava/lang/String;[Ljava/lang/Class;)Ljava/lang/reflect/Method;
    //   118: astore 5
    //   120: aload 5
    //   122: aload 4
    //   124: iconst_0
    //   125: anewarray 4	java/lang/Object
    //   128: invokevirtual 67	java/lang/reflect/Method:invoke	(Ljava/lang/Object;[Ljava/lang/Object;)Ljava/lang/Object;
    //   131: astore 4
    //   133: aload 4
    //   135: checkcast 302	java/lang/Boolean
    //   138: invokevirtual 388	java/lang/Boolean:booleanValue	()Z
    //   141: ifeq +924 -> 1065
    //   144: aload_0
    //   145: getfield 186	uuuuuu/tytyty:bxx007800780078x00780078x	Lcom/db/pwcc/dbmobile/secure/preferences/SharedPreferencesHelper;
    //   148: astore 4
    //   150: ldc -68
    //   152: ldc_w 415
    //   155: sipush 202
    //   158: iconst_3
    //   159: invokestatic 55	xxxxxx/uxxxxx:bb00620062bb0062b0062b0062	(Ljava/lang/String;CC)Ljava/lang/String;
    //   162: iconst_0
    //   163: anewarray 57	java/lang/Class
    //   166: invokevirtual 61	java/lang/Class:getMethod	(Ljava/lang/String;[Ljava/lang/Class;)Ljava/lang/reflect/Method;
    //   169: astore 5
    //   171: aload 5
    //   173: aload 4
    //   175: iconst_0
    //   176: anewarray 4	java/lang/Object
    //   179: invokevirtual 67	java/lang/reflect/Method:invoke	(Ljava/lang/Object;[Ljava/lang/Object;)Ljava/lang/Object;
    //   182: astore 4
    //   184: aload 4
    //   186: checkcast 192	java/lang/String
    //   189: invokevirtual 418	java/lang/String:isEmpty	()Z
    //   192: ifne +873 -> 1065
    //   195: aload_0
    //   196: getfield 110	uuuuuu/tytyty:bx0078xxx007800780078x	Luuuuuu/ytyyty$yytyty;
    //   199: getstatic 421	com/db/pwcc/dbmobile/mobile_payment/R$string:card_already_default	I
    //   202: invokeinterface 373 2 0
    //   207: aload_0
    //   208: getfield 110	uuuuuu/tytyty:bx0078xxx007800780078x	Luuuuuu/ytyyty$yytyty;
    //   211: invokeinterface 424 1 0
    //   216: getstatic 99	uuuuuu/tytyty:bxxx00780078x00780078x	Ljava/lang/String;
    //   219: astore_1
    //   220: ldc -26
    //   222: ldc_w 426
    //   225: bipush 77
    //   227: sipush 230
    //   230: iconst_2
    //   231: invokestatic 93	xxxxxx/uxxxxx:bbbb0062b0062b0062b0062	(Ljava/lang/String;CCC)Ljava/lang/String;
    //   234: iconst_3
    //   235: anewarray 57	java/lang/Class
    //   238: dup
    //   239: iconst_0
    //   240: ldc -64
    //   242: aastore
    //   243: dup
    //   244: iconst_1
    //   245: getstatic 238	java/lang/Character:TYPE	Ljava/lang/Class;
    //   248: aastore
    //   249: dup
    //   250: iconst_2
    //   251: getstatic 238	java/lang/Character:TYPE	Ljava/lang/Class;
    //   254: aastore
    //   255: invokevirtual 61	java/lang/Class:getMethod	(Ljava/lang/String;[Ljava/lang/Class;)Ljava/lang/reflect/Method;
    //   258: astore 4
    //   260: aload 4
    //   262: aconst_null
    //   263: iconst_3
    //   264: anewarray 4	java/lang/Object
    //   267: dup
    //   268: iconst_0
    //   269: ldc_w 428
    //   272: aastore
    //   273: dup
    //   274: iconst_1
    //   275: bipush 86
    //   277: invokestatic 244	java/lang/Character:valueOf	(C)Ljava/lang/Character;
    //   280: aastore
    //   281: dup
    //   282: iconst_2
    //   283: iconst_4
    //   284: invokestatic 244	java/lang/Character:valueOf	(C)Ljava/lang/Character;
    //   287: aastore
    //   288: invokevirtual 67	java/lang/reflect/Method:invoke	(Ljava/lang/Object;[Ljava/lang/Object;)Ljava/lang/Object;
    //   291: astore 4
    //   293: aload 4
    //   295: checkcast 192	java/lang/String
    //   298: astore 4
    //   300: getstatic 75	uuuuuu/tytyty:b0078x0078xx007800780078x	I
    //   303: istore_2
    //   304: iload_2
    //   305: getstatic 77	uuuuuu/tytyty:b00780078xxx007800780078x	I
    //   308: iload_2
    //   309: iadd
    //   310: imul
    //   311: getstatic 79	uuuuuu/tytyty:bxx0078xx007800780078x	I
    //   314: irem
    //   315: tableswitch	default:+17->332, 0:+26->341
    //   332: bipush 83
    //   334: putstatic 75	uuuuuu/tytyty:b0078x0078xx007800780078x	I
    //   337: iconst_4
    //   338: putstatic 83	uuuuuu/tytyty:bx00780078xx007800780078x	I
    //   341: aload_1
    //   342: aload 4
    //   344: invokestatic 434	uuuuuu/rvvvrv:bqqqq00710071q0071q0071	(Ljava/lang/String;Ljava/lang/String;)V
    //   347: return
    //   348: aload_0
    //   349: getfield 216	uuuuuu/tytyty:bx0078007800780078x00780078x	Luuuuuu/qpqppq;
    //   352: aload_1
    //   353: invokevirtual 222	uuuuuu/qpqppq:b006Bk006Bkkk006Bkkk	(Ljava/lang/String;)Ljava/lang/String;
    //   356: astore 4
    //   358: new 175	com/db/pwcc/dbmobile/model/tokenization/TokenizationPayload$yvvvvy
    //   361: dup
    //   362: invokespecial 176	com/db/pwcc/dbmobile/model/tokenization/TokenizationPayload$yvvvvy:<init>	()V
    //   365: astore 5
    //   367: aload_0
    //   368: getfield 186	uuuuuu/tytyty:bxx007800780078x00780078x	Lcom/db/pwcc/dbmobile/secure/preferences/SharedPreferencesHelper;
    //   371: astore 6
    //   373: ldc -68
    //   375: ldc_w 436
    //   378: bipush 16
    //   380: iconst_3
    //   381: invokestatic 55	xxxxxx/uxxxxx:bb00620062bb0062b0062b0062	(Ljava/lang/String;CC)Ljava/lang/String;
    //   384: iconst_0
    //   385: anewarray 57	java/lang/Class
    //   388: invokevirtual 61	java/lang/Class:getMethod	(Ljava/lang/String;[Ljava/lang/Class;)Ljava/lang/reflect/Method;
    //   391: astore 7
    //   393: aload 7
    //   395: aload 6
    //   397: iconst_0
    //   398: anewarray 4	java/lang/Object
    //   401: invokevirtual 67	java/lang/reflect/Method:invoke	(Ljava/lang/Object;[Ljava/lang/Object;)Ljava/lang/Object;
    //   404: astore 6
    //   406: aload 5
    //   408: aload 6
    //   410: checkcast 192	java/lang/String
    //   413: invokevirtual 196	com/db/pwcc/dbmobile/model/tokenization/TokenizationPayload$yvvvvy:b0075uu0075uuu00750075u	(Ljava/lang/String;)Lcom/db/pwcc/dbmobile/model/tokenization/TokenizationPayload$yvvvvy;
    //   416: aload_0
    //   417: getfield 198	uuuuuu/tytyty:bx0078x00780078x00780078x	Luuuuuu/yttttt;
    //   420: invokeinterface 203 1 0
    //   425: invokevirtual 206	com/db/pwcc/dbmobile/model/tokenization/TokenizationPayload$yvvvvy:b007500750075uuuu00750075u	(Ljava/lang/String;)Lcom/db/pwcc/dbmobile/model/tokenization/TokenizationPayload$yvvvvy;
    //   428: aload_0
    //   429: getfield 110	uuuuuu/tytyty:bx0078xxx007800780078x	Luuuuuu/ytyyty$yytyty;
    //   432: invokeinterface 211 1 0
    //   437: invokevirtual 214	com/db/pwcc/dbmobile/model/tokenization/TokenizationPayload$yvvvvy:bu00750075uuuu00750075u	(Ljava/lang/String;)Lcom/db/pwcc/dbmobile/model/tokenization/TokenizationPayload$yvvvvy;
    //   440: aload 4
    //   442: invokevirtual 225	com/db/pwcc/dbmobile/model/tokenization/TokenizationPayload$yvvvvy:buu00750075uuu00750075u	(Ljava/lang/String;)Lcom/db/pwcc/dbmobile/model/tokenization/TokenizationPayload$yvvvvy;
    //   445: aload 4
    //   447: invokevirtual 228	com/db/pwcc/dbmobile/model/tokenization/TokenizationPayload$yvvvvy:b00750075u0075uuu00750075u	(Ljava/lang/String;)Lcom/db/pwcc/dbmobile/model/tokenization/TokenizationPayload$yvvvvy;
    //   450: astore 4
    //   452: ldc -26
    //   454: ldc_w 438
    //   457: bipush 24
    //   459: sipush 219
    //   462: iconst_1
    //   463: invokestatic 93	xxxxxx/uxxxxx:bbbb0062b0062b0062b0062	(Ljava/lang/String;CCC)Ljava/lang/String;
    //   466: iconst_4
    //   467: anewarray 57	java/lang/Class
    //   470: dup
    //   471: iconst_0
    //   472: ldc -64
    //   474: aastore
    //   475: dup
    //   476: iconst_1
    //   477: getstatic 238	java/lang/Character:TYPE	Ljava/lang/Class;
    //   480: aastore
    //   481: dup
    //   482: iconst_2
    //   483: getstatic 238	java/lang/Character:TYPE	Ljava/lang/Class;
    //   486: aastore
    //   487: dup
    //   488: iconst_3
    //   489: getstatic 238	java/lang/Character:TYPE	Ljava/lang/Class;
    //   492: aastore
    //   493: invokevirtual 61	java/lang/Class:getMethod	(Ljava/lang/String;[Ljava/lang/Class;)Ljava/lang/reflect/Method;
    //   496: astore 5
    //   498: aload 5
    //   500: aconst_null
    //   501: iconst_4
    //   502: anewarray 4	java/lang/Object
    //   505: dup
    //   506: iconst_0
    //   507: ldc_w 440
    //   510: aastore
    //   511: dup
    //   512: iconst_1
    //   513: sipush 199
    //   516: invokestatic 244	java/lang/Character:valueOf	(C)Ljava/lang/Character;
    //   519: aastore
    //   520: dup
    //   521: iconst_2
    //   522: bipush 63
    //   524: invokestatic 244	java/lang/Character:valueOf	(C)Ljava/lang/Character;
    //   527: aastore
    //   528: dup
    //   529: iconst_3
    //   530: iconst_3
    //   531: invokestatic 244	java/lang/Character:valueOf	(C)Ljava/lang/Character;
    //   534: aastore
    //   535: invokevirtual 67	java/lang/reflect/Method:invoke	(Ljava/lang/Object;[Ljava/lang/Object;)Ljava/lang/Object;
    //   538: astore 5
    //   540: aload 4
    //   542: aload 5
    //   544: checkcast 192	java/lang/String
    //   547: invokevirtual 247	com/db/pwcc/dbmobile/model/tokenization/TokenizationPayload$yvvvvy:bu0075u0075uuu00750075u	(Ljava/lang/String;)Lcom/db/pwcc/dbmobile/model/tokenization/TokenizationPayload$yvvvvy;
    //   550: astore 4
    //   552: ldc -26
    //   554: ldc_w 442
    //   557: sipush 153
    //   560: iconst_0
    //   561: invokestatic 55	xxxxxx/uxxxxx:bb00620062bb0062b0062b0062	(Ljava/lang/String;CC)Ljava/lang/String;
    //   564: iconst_4
    //   565: anewarray 57	java/lang/Class
    //   568: dup
    //   569: iconst_0
    //   570: ldc -64
    //   572: aastore
    //   573: dup
    //   574: iconst_1
    //   575: getstatic 238	java/lang/Character:TYPE	Ljava/lang/Class;
    //   578: aastore
    //   579: dup
    //   580: iconst_2
    //   581: getstatic 238	java/lang/Character:TYPE	Ljava/lang/Class;
    //   584: aastore
    //   585: dup
    //   586: iconst_3
    //   587: getstatic 238	java/lang/Character:TYPE	Ljava/lang/Class;
    //   590: aastore
    //   591: invokevirtual 61	java/lang/Class:getMethod	(Ljava/lang/String;[Ljava/lang/Class;)Ljava/lang/reflect/Method;
    //   594: astore 5
    //   596: aload 5
    //   598: aconst_null
    //   599: iconst_4
    //   600: anewarray 4	java/lang/Object
    //   603: dup
    //   604: iconst_0
    //   605: ldc_w 444
    //   608: aastore
    //   609: dup
    //   610: iconst_1
    //   611: sipush 211
    //   614: invokestatic 244	java/lang/Character:valueOf	(C)Ljava/lang/Character;
    //   617: aastore
    //   618: dup
    //   619: iconst_2
    //   620: bipush 103
    //   622: invokestatic 244	java/lang/Character:valueOf	(C)Ljava/lang/Character;
    //   625: aastore
    //   626: dup
    //   627: iconst_3
    //   628: iconst_1
    //   629: invokestatic 244	java/lang/Character:valueOf	(C)Ljava/lang/Character;
    //   632: aastore
    //   633: invokevirtual 67	java/lang/reflect/Method:invoke	(Ljava/lang/Object;[Ljava/lang/Object;)Ljava/lang/Object;
    //   636: astore 5
    //   638: aload 4
    //   640: aload 5
    //   642: checkcast 192	java/lang/String
    //   645: invokevirtual 254	com/db/pwcc/dbmobile/model/tokenization/TokenizationPayload$yvvvvy:buuu0075uuu00750075u	(Ljava/lang/String;)Lcom/db/pwcc/dbmobile/model/tokenization/TokenizationPayload$yvvvvy;
    //   648: aload_1
    //   649: invokevirtual 257	com/db/pwcc/dbmobile/model/tokenization/TokenizationPayload$yvvvvy:b0075u0075uuuu00750075u	(Ljava/lang/String;)Lcom/db/pwcc/dbmobile/model/tokenization/TokenizationPayload$yvvvvy;
    //   652: astore 4
    //   654: aload_0
    //   655: getfield 118	uuuuuu/tytyty:b0078x007800780078x00780078x	Ljava/util/Map;
    //   658: astore 5
    //   660: getstatic 380	uuuuuu/lolllo:bqq0071qq0071qq0071	Luuuuuu/lolllo;
    //   663: invokevirtual 300	uuuuuu/lolllo:name	()Ljava/lang/String;
    //   666: astore 6
    //   668: ldc 2
    //   670: ldc_w 446
    //   673: bipush 49
    //   675: iconst_3
    //   676: invokestatic 55	xxxxxx/uxxxxx:bb00620062bb0062b0062b0062	(Ljava/lang/String;CC)Ljava/lang/String;
    //   679: iconst_0
    //   680: anewarray 57	java/lang/Class
    //   683: invokevirtual 61	java/lang/Class:getMethod	(Ljava/lang/String;[Ljava/lang/Class;)Ljava/lang/reflect/Method;
    //   686: astore 7
    //   688: aload 7
    //   690: aconst_null
    //   691: iconst_0
    //   692: anewarray 4	java/lang/Object
    //   695: invokevirtual 67	java/lang/reflect/Method:invoke	(Ljava/lang/Object;[Ljava/lang/Object;)Ljava/lang/Object;
    //   698: astore 7
    //   700: aload 7
    //   702: checkcast 69	java/lang/Integer
    //   705: invokevirtual 73	java/lang/Integer:intValue	()I
    //   708: istore_2
    //   709: getstatic 77	uuuuuu/tytyty:b00780078xxx007800780078x	I
    //   712: istore_3
    //   713: ldc 2
    //   715: ldc_w 448
    //   718: sipush 225
    //   721: bipush 83
    //   723: iconst_3
    //   724: invokestatic 93	xxxxxx/uxxxxx:bbbb0062b0062b0062b0062	(Ljava/lang/String;CCC)Ljava/lang/String;
    //   727: iconst_0
    //   728: anewarray 57	java/lang/Class
    //   731: invokevirtual 61	java/lang/Class:getMethod	(Ljava/lang/String;[Ljava/lang/Class;)Ljava/lang/reflect/Method;
    //   734: astore 7
    //   736: aload 7
    //   738: aconst_null
    //   739: iconst_0
    //   740: anewarray 4	java/lang/Object
    //   743: invokevirtual 67	java/lang/reflect/Method:invoke	(Ljava/lang/Object;[Ljava/lang/Object;)Ljava/lang/Object;
    //   746: astore 7
    //   748: aload 7
    //   750: checkcast 69	java/lang/Integer
    //   753: invokevirtual 73	java/lang/Integer:intValue	()I
    //   756: iload_3
    //   757: iload_2
    //   758: iadd
    //   759: imul
    //   760: getstatic 79	uuuuuu/tytyty:bxx0078xx007800780078x	I
    //   763: irem
    //   764: getstatic 83	uuuuuu/tytyty:bx00780078xx007800780078x	I
    //   767: if_icmpeq +89 -> 856
    //   770: ldc 2
    //   772: ldc_w 398
    //   775: bipush 51
    //   777: iconst_2
    //   778: invokestatic 55	xxxxxx/uxxxxx:bb00620062bb0062b0062b0062	(Ljava/lang/String;CC)Ljava/lang/String;
    //   781: iconst_0
    //   782: anewarray 57	java/lang/Class
    //   785: invokevirtual 61	java/lang/Class:getMethod	(Ljava/lang/String;[Ljava/lang/Class;)Ljava/lang/reflect/Method;
    //   788: astore 7
    //   790: aload 7
    //   792: aconst_null
    //   793: iconst_0
    //   794: anewarray 4	java/lang/Object
    //   797: invokevirtual 67	java/lang/reflect/Method:invoke	(Ljava/lang/Object;[Ljava/lang/Object;)Ljava/lang/Object;
    //   800: astore 7
    //   802: aload 7
    //   804: checkcast 69	java/lang/Integer
    //   807: invokevirtual 73	java/lang/Integer:intValue	()I
    //   810: putstatic 75	uuuuuu/tytyty:b0078x0078xx007800780078x	I
    //   813: ldc 2
    //   815: ldc_w 450
    //   818: bipush 23
    //   820: iconst_0
    //   821: invokestatic 55	xxxxxx/uxxxxx:bb00620062bb0062b0062b0062	(Ljava/lang/String;CC)Ljava/lang/String;
    //   824: iconst_0
    //   825: anewarray 57	java/lang/Class
    //   828: invokevirtual 61	java/lang/Class:getMethod	(Ljava/lang/String;[Ljava/lang/Class;)Ljava/lang/reflect/Method;
    //   831: astore 7
    //   833: aload 7
    //   835: aconst_null
    //   836: iconst_0
    //   837: anewarray 4	java/lang/Object
    //   840: invokevirtual 67	java/lang/reflect/Method:invoke	(Ljava/lang/Object;[Ljava/lang/Object;)Ljava/lang/Object;
    //   843: astore 7
    //   845: aload 7
    //   847: checkcast 69	java/lang/Integer
    //   850: invokevirtual 73	java/lang/Integer:intValue	()I
    //   853: putstatic 83	uuuuuu/tytyty:bx00780078xx007800780078x	I
    //   856: getstatic 75	uuuuuu/tytyty:b0078x0078xx007800780078x	I
    //   859: getstatic 77	uuuuuu/tytyty:b00780078xxx007800780078x	I
    //   862: iadd
    //   863: getstatic 75	uuuuuu/tytyty:b0078x0078xx007800780078x	I
    //   866: imul
    //   867: getstatic 79	uuuuuu/tytyty:bxx0078xx007800780078x	I
    //   870: irem
    //   871: getstatic 83	uuuuuu/tytyty:bx00780078xx007800780078x	I
    //   874: if_icmpeq +53 -> 927
    //   877: bipush 6
    //   879: putstatic 75	uuuuuu/tytyty:b0078x0078xx007800780078x	I
    //   882: ldc 2
    //   884: ldc_w 452
    //   887: bipush 25
    //   889: bipush 40
    //   891: iconst_2
    //   892: invokestatic 93	xxxxxx/uxxxxx:bbbb0062b0062b0062b0062	(Ljava/lang/String;CCC)Ljava/lang/String;
    //   895: iconst_0
    //   896: anewarray 57	java/lang/Class
    //   899: invokevirtual 61	java/lang/Class:getMethod	(Ljava/lang/String;[Ljava/lang/Class;)Ljava/lang/reflect/Method;
    //   902: astore 7
    //   904: aload 7
    //   906: aconst_null
    //   907: iconst_0
    //   908: anewarray 4	java/lang/Object
    //   911: invokevirtual 67	java/lang/reflect/Method:invoke	(Ljava/lang/Object;[Ljava/lang/Object;)Ljava/lang/Object;
    //   914: astore 7
    //   916: aload 7
    //   918: checkcast 69	java/lang/Integer
    //   921: invokevirtual 73	java/lang/Integer:intValue	()I
    //   924: putstatic 83	uuuuuu/tytyty:bx00780078xx007800780078x	I
    //   927: aload 5
    //   929: aload 6
    //   931: iconst_1
    //   932: invokestatic 305	java/lang/Boolean:valueOf	(Z)Ljava/lang/Boolean;
    //   935: invokeinterface 311 3 0
    //   940: pop
    //   941: aload_0
    //   942: getfield 112	uuuuuu/tytyty:bxxxxx007800780078x	Luuuuuu/vppvvv;
    //   945: aload_0
    //   946: aload_0
    //   947: getfield 454	uuuuuu/tytyty:b00780078007800780078x00780078x	Luuuuuu/hyhyhh;
    //   950: invokevirtual 459	uuuuuu/hyhyhh:bpp0070007000700070p007000700070	()Ljava/lang/String;
    //   953: aload_1
    //   954: aload 4
    //   956: invokevirtual 261	com/db/pwcc/dbmobile/model/tokenization/TokenizationPayload$yvvvvy:buu0075uuuu00750075u	()Lcom/db/pwcc/dbmobile/model/tokenization/TokenizationPayload;
    //   959: invokeinterface 465 5 0
    //   964: return
    //   965: astore_1
    //   966: aload_1
    //   967: invokevirtual 103	java/lang/reflect/InvocationTargetException:getCause	()Ljava/lang/Throwable;
    //   970: athrow
    //   971: aload_0
    //   972: getfield 198	uuuuuu/tytyty:bx0078x00780078x00780078x	Luuuuuu/yttttt;
    //   975: invokeinterface 203 1 0
    //   980: invokevirtual 418	java/lang/String:isEmpty	()Z
    //   983: ifeq -635 -> 348
    //   986: aload_0
    //   987: getfield 110	uuuuuu/tytyty:bx0078xxx007800780078x	Luuuuuu/ytyyty$yytyty;
    //   990: getstatic 468	com/db/pwcc/dbmobile/mobile_payment/R$string:technical_error_mopay	I
    //   993: invokeinterface 373 2 0
    //   998: return
    //   999: aload_0
    //   1000: getfield 186	uuuuuu/tytyty:bxx007800780078x00780078x	Lcom/db/pwcc/dbmobile/secure/preferences/SharedPreferencesHelper;
    //   1003: astore 4
    //   1005: ldc -68
    //   1007: ldc_w 470
    //   1010: bipush 13
    //   1012: iconst_2
    //   1013: invokestatic 55	xxxxxx/uxxxxx:bb00620062bb0062b0062b0062	(Ljava/lang/String;CC)Ljava/lang/String;
    //   1016: iconst_0
    //   1017: anewarray 57	java/lang/Class
    //   1020: invokevirtual 61	java/lang/Class:getMethod	(Ljava/lang/String;[Ljava/lang/Class;)Ljava/lang/reflect/Method;
    //   1023: astore 5
    //   1025: aload 5
    //   1027: aload 4
    //   1029: iconst_0
    //   1030: anewarray 4	java/lang/Object
    //   1033: invokevirtual 67	java/lang/reflect/Method:invoke	(Ljava/lang/Object;[Ljava/lang/Object;)Ljava/lang/Object;
    //   1036: astore 4
    //   1038: aload 4
    //   1040: checkcast 192	java/lang/String
    //   1043: invokevirtual 418	java/lang/String:isEmpty	()Z
    //   1046: ifeq -75 -> 971
    //   1049: aload_0
    //   1050: getfield 110	uuuuuu/tytyty:bx0078xxx007800780078x	Luuuuuu/ytyyty$yytyty;
    //   1053: invokeinterface 473 1 0
    //   1058: return
    //   1059: astore_1
    //   1060: aload_1
    //   1061: invokevirtual 103	java/lang/reflect/InvocationTargetException:getCause	()Ljava/lang/Throwable;
    //   1064: athrow
    //   1065: ldc 2
    //   1067: ldc_w 475
    //   1070: bipush 122
    //   1072: iconst_4
    //   1073: iconst_3
    //   1074: invokestatic 93	xxxxxx/uxxxxx:bbbb0062b0062b0062b0062	(Ljava/lang/String;CCC)Ljava/lang/String;
    //   1077: iconst_2
    //   1078: anewarray 57	java/lang/Class
    //   1081: dup
    //   1082: iconst_0
    //   1083: ldc_w 284
    //   1086: aastore
    //   1087: dup
    //   1088: iconst_1
    //   1089: ldc -64
    //   1091: aastore
    //   1092: invokevirtual 478	java/lang/Class:getDeclaredMethod	(Ljava/lang/String;[Ljava/lang/Class;)Ljava/lang/reflect/Method;
    //   1095: astore 4
    //   1097: aload 4
    //   1099: aload_0
    //   1100: iconst_2
    //   1101: anewarray 4	java/lang/Object
    //   1104: dup
    //   1105: iconst_0
    //   1106: aconst_null
    //   1107: aastore
    //   1108: dup
    //   1109: iconst_1
    //   1110: aload_1
    //   1111: aastore
    //   1112: invokevirtual 67	java/lang/reflect/Method:invoke	(Ljava/lang/Object;[Ljava/lang/Object;)Ljava/lang/Object;
    //   1115: pop
    //   1116: return
    //   1117: astore_1
    //   1118: aload_1
    //   1119: invokevirtual 103	java/lang/reflect/InvocationTargetException:getCause	()Ljava/lang/Throwable;
    //   1122: athrow
    //   1123: astore_1
    //   1124: aload_1
    //   1125: invokevirtual 103	java/lang/reflect/InvocationTargetException:getCause	()Ljava/lang/Throwable;
    //   1128: athrow
    //   1129: astore_1
    //   1130: aload_1
    //   1131: invokevirtual 103	java/lang/reflect/InvocationTargetException:getCause	()Ljava/lang/Throwable;
    //   1134: athrow
    //   1135: astore_1
    //   1136: aload_1
    //   1137: invokevirtual 103	java/lang/reflect/InvocationTargetException:getCause	()Ljava/lang/Throwable;
    //   1140: athrow
    //   1141: astore_1
    //   1142: aload_1
    //   1143: invokevirtual 103	java/lang/reflect/InvocationTargetException:getCause	()Ljava/lang/Throwable;
    //   1146: athrow
    //   1147: astore_1
    //   1148: aload_1
    //   1149: invokevirtual 103	java/lang/reflect/InvocationTargetException:getCause	()Ljava/lang/Throwable;
    //   1152: athrow
    //   1153: astore_1
    //   1154: aload_1
    //   1155: invokevirtual 103	java/lang/reflect/InvocationTargetException:getCause	()Ljava/lang/Throwable;
    //   1158: athrow
    //   1159: astore_1
    //   1160: aload_1
    //   1161: invokevirtual 103	java/lang/reflect/InvocationTargetException:getCause	()Ljava/lang/Throwable;
    //   1164: athrow
    //   1165: astore_1
    //   1166: aload_1
    //   1167: invokevirtual 103	java/lang/reflect/InvocationTargetException:getCause	()Ljava/lang/Throwable;
    //   1170: athrow
    //   1171: astore_1
    //   1172: aload_1
    //   1173: invokevirtual 103	java/lang/reflect/InvocationTargetException:getCause	()Ljava/lang/Throwable;
    //   1176: athrow
    //   1177: astore_1
    //   1178: aload_1
    //   1179: invokevirtual 103	java/lang/reflect/InvocationTargetException:getCause	()Ljava/lang/Throwable;
    //   1182: athrow
    //   1183: astore_1
    //   1184: aload_1
    //   1185: invokevirtual 103	java/lang/reflect/InvocationTargetException:getCause	()Ljava/lang/Throwable;
    //   1188: athrow
    // Local variable table:
    //   start	length	slot	name	signature
    //   0	1189	0	this	tytyty
    //   0	1189	1	paramString	String
    //   303	456	2	i	int
    //   712	47	3	j	int
    //   47	1051	4	localObject1	Object
    //   118	908	5	localObject2	Object
    //   371	559	6	localObject3	Object
    //   391	526	7	localObject4	Object
    // Exception table:
    //   from	to	target	type
    //   260	293	965	java/lang/reflect/InvocationTargetException
    //   1025	1038	1059	java/lang/reflect/InvocationTargetException
    //   1097	1116	1117	java/lang/reflect/InvocationTargetException
    //   393	406	1123	java/lang/reflect/InvocationTargetException
    //   498	540	1129	java/lang/reflect/InvocationTargetException
    //   120	133	1135	java/lang/reflect/InvocationTargetException
    //   596	638	1141	java/lang/reflect/InvocationTargetException
    //   688	700	1147	java/lang/reflect/InvocationTargetException
    //   736	748	1153	java/lang/reflect/InvocationTargetException
    //   171	184	1159	java/lang/reflect/InvocationTargetException
    //   790	802	1165	java/lang/reflect/InvocationTargetException
    //   833	845	1171	java/lang/reflect/InvocationTargetException
    //   904	916	1177	java/lang/reflect/InvocationTargetException
    //   49	61	1183	java/lang/reflect/InvocationTargetException
  }
  
  /* Error */
  public void bpppp0070p007000700070p(TokenizationPayload paramTokenizationPayload)
  {
    // Byte code:
    //   0: aload_0
    //   1: getfield 118	uuuuuu/tytyty:b0078x007800780078x00780078x	Ljava/util/Map;
    //   4: astore_3
    //   5: getstatic 380	uuuuuu/lolllo:bqq0071qq0071qq0071	Luuuuuu/lolllo;
    //   8: invokevirtual 300	uuuuuu/lolllo:name	()Ljava/lang/String;
    //   11: astore 4
    //   13: getstatic 75	uuuuuu/tytyty:b0078x0078xx007800780078x	I
    //   16: getstatic 77	uuuuuu/tytyty:b00780078xxx007800780078x	I
    //   19: iadd
    //   20: getstatic 75	uuuuuu/tytyty:b0078x0078xx007800780078x	I
    //   23: imul
    //   24: getstatic 79	uuuuuu/tytyty:bxx0078xx007800780078x	I
    //   27: irem
    //   28: getstatic 83	uuuuuu/tytyty:bx00780078xx007800780078x	I
    //   31: if_icmpeq +93 -> 124
    //   34: ldc 2
    //   36: ldc_w 482
    //   39: sipush 134
    //   42: iconst_2
    //   43: invokestatic 55	xxxxxx/uxxxxx:bb00620062bb0062b0062b0062	(Ljava/lang/String;CC)Ljava/lang/String;
    //   46: iconst_0
    //   47: anewarray 57	java/lang/Class
    //   50: invokevirtual 61	java/lang/Class:getMethod	(Ljava/lang/String;[Ljava/lang/Class;)Ljava/lang/reflect/Method;
    //   53: astore 5
    //   55: aload 5
    //   57: aconst_null
    //   58: iconst_0
    //   59: anewarray 4	java/lang/Object
    //   62: invokevirtual 67	java/lang/reflect/Method:invoke	(Ljava/lang/Object;[Ljava/lang/Object;)Ljava/lang/Object;
    //   65: astore 5
    //   67: aload 5
    //   69: checkcast 69	java/lang/Integer
    //   72: invokevirtual 73	java/lang/Integer:intValue	()I
    //   75: putstatic 75	uuuuuu/tytyty:b0078x0078xx007800780078x	I
    //   78: ldc 2
    //   80: ldc_w 484
    //   83: sipush 203
    //   86: bipush 49
    //   88: iconst_0
    //   89: invokestatic 93	xxxxxx/uxxxxx:bbbb0062b0062b0062b0062	(Ljava/lang/String;CCC)Ljava/lang/String;
    //   92: iconst_0
    //   93: anewarray 57	java/lang/Class
    //   96: invokevirtual 61	java/lang/Class:getMethod	(Ljava/lang/String;[Ljava/lang/Class;)Ljava/lang/reflect/Method;
    //   99: astore 5
    //   101: aload 5
    //   103: aconst_null
    //   104: iconst_0
    //   105: anewarray 4	java/lang/Object
    //   108: invokevirtual 67	java/lang/reflect/Method:invoke	(Ljava/lang/Object;[Ljava/lang/Object;)Ljava/lang/Object;
    //   111: astore 5
    //   113: aload 5
    //   115: checkcast 69	java/lang/Integer
    //   118: invokevirtual 73	java/lang/Integer:intValue	()I
    //   121: putstatic 83	uuuuuu/tytyty:bx00780078xx007800780078x	I
    //   124: aload_3
    //   125: aload 4
    //   127: invokeinterface 377 2 0
    //   132: ifeq +27 -> 159
    //   135: aload_0
    //   136: getfield 118	uuuuuu/tytyty:b0078x007800780078x00780078x	Ljava/util/Map;
    //   139: getstatic 380	uuuuuu/lolllo:bqq0071qq0071qq0071	Luuuuuu/lolllo;
    //   142: invokevirtual 300	uuuuuu/lolllo:name	()Ljava/lang/String;
    //   145: invokeinterface 384 2 0
    //   150: checkcast 302	java/lang/Boolean
    //   153: invokevirtual 388	java/lang/Boolean:booleanValue	()Z
    //   156: ifne +4 -> 160
    //   159: return
    //   160: aload_0
    //   161: getfield 118	uuuuuu/tytyty:b0078x007800780078x00780078x	Ljava/util/Map;
    //   164: getstatic 380	uuuuuu/lolllo:bqq0071qq0071qq0071	Luuuuuu/lolllo;
    //   167: invokevirtual 300	uuuuuu/lolllo:name	()Ljava/lang/String;
    //   170: iconst_0
    //   171: invokestatic 305	java/lang/Boolean:valueOf	(Z)Ljava/lang/Boolean;
    //   174: invokeinterface 311 3 0
    //   179: pop
    //   180: getstatic 75	uuuuuu/tytyty:b0078x0078xx007800780078x	I
    //   183: getstatic 77	uuuuuu/tytyty:b00780078xxx007800780078x	I
    //   186: iadd
    //   187: getstatic 75	uuuuuu/tytyty:b0078x0078xx007800780078x	I
    //   190: imul
    //   191: getstatic 79	uuuuuu/tytyty:bxx0078xx007800780078x	I
    //   194: irem
    //   195: getstatic 83	uuuuuu/tytyty:bx00780078xx007800780078x	I
    //   198: if_icmpeq +119 -> 317
    //   201: ldc 2
    //   203: ldc_w 486
    //   206: sipush 208
    //   209: sipush 154
    //   212: iconst_1
    //   213: invokestatic 93	xxxxxx/uxxxxx:bbbb0062b0062b0062b0062	(Ljava/lang/String;CCC)Ljava/lang/String;
    //   216: iconst_0
    //   217: anewarray 57	java/lang/Class
    //   220: invokevirtual 61	java/lang/Class:getMethod	(Ljava/lang/String;[Ljava/lang/Class;)Ljava/lang/reflect/Method;
    //   223: astore_3
    //   224: aload_3
    //   225: aconst_null
    //   226: iconst_0
    //   227: anewarray 4	java/lang/Object
    //   230: invokevirtual 67	java/lang/reflect/Method:invoke	(Ljava/lang/Object;[Ljava/lang/Object;)Ljava/lang/Object;
    //   233: astore_3
    //   234: aload_3
    //   235: checkcast 69	java/lang/Integer
    //   238: invokevirtual 73	java/lang/Integer:intValue	()I
    //   241: putstatic 75	uuuuuu/tytyty:b0078x0078xx007800780078x	I
    //   244: bipush 57
    //   246: putstatic 83	uuuuuu/tytyty:bx00780078xx007800780078x	I
    //   249: getstatic 75	uuuuuu/tytyty:b0078x0078xx007800780078x	I
    //   252: getstatic 77	uuuuuu/tytyty:b00780078xxx007800780078x	I
    //   255: iadd
    //   256: getstatic 75	uuuuuu/tytyty:b0078x0078xx007800780078x	I
    //   259: imul
    //   260: getstatic 79	uuuuuu/tytyty:bxx0078xx007800780078x	I
    //   263: irem
    //   264: getstatic 83	uuuuuu/tytyty:bx00780078xx007800780078x	I
    //   267: if_icmpeq +50 -> 317
    //   270: ldc 2
    //   272: ldc_w 488
    //   275: sipush 167
    //   278: bipush 114
    //   280: iconst_2
    //   281: invokestatic 93	xxxxxx/uxxxxx:bbbb0062b0062b0062b0062	(Ljava/lang/String;CCC)Ljava/lang/String;
    //   284: iconst_0
    //   285: anewarray 57	java/lang/Class
    //   288: invokevirtual 61	java/lang/Class:getMethod	(Ljava/lang/String;[Ljava/lang/Class;)Ljava/lang/reflect/Method;
    //   291: astore_3
    //   292: aload_3
    //   293: aconst_null
    //   294: iconst_0
    //   295: anewarray 4	java/lang/Object
    //   298: invokevirtual 67	java/lang/reflect/Method:invoke	(Ljava/lang/Object;[Ljava/lang/Object;)Ljava/lang/Object;
    //   301: astore_3
    //   302: aload_3
    //   303: checkcast 69	java/lang/Integer
    //   306: invokevirtual 73	java/lang/Integer:intValue	()I
    //   309: putstatic 75	uuuuuu/tytyty:b0078x0078xx007800780078x	I
    //   312: bipush 45
    //   314: putstatic 83	uuuuuu/tytyty:bx00780078xx007800780078x	I
    //   317: getstatic 75	uuuuuu/tytyty:b0078x0078xx007800780078x	I
    //   320: istore_2
    //   321: iload_2
    //   322: getstatic 77	uuuuuu/tytyty:b00780078xxx007800780078x	I
    //   325: iload_2
    //   326: iadd
    //   327: imul
    //   328: getstatic 79	uuuuuu/tytyty:bxx0078xx007800780078x	I
    //   331: irem
    //   332: tableswitch	default:+20->352, 0:+66->398
    //   352: bipush 38
    //   354: putstatic 75	uuuuuu/tytyty:b0078x0078xx007800780078x	I
    //   357: ldc 2
    //   359: ldc -78
    //   361: sipush 174
    //   364: bipush 99
    //   366: iconst_0
    //   367: invokestatic 93	xxxxxx/uxxxxx:bbbb0062b0062b0062b0062	(Ljava/lang/String;CCC)Ljava/lang/String;
    //   370: iconst_0
    //   371: anewarray 57	java/lang/Class
    //   374: invokevirtual 61	java/lang/Class:getMethod	(Ljava/lang/String;[Ljava/lang/Class;)Ljava/lang/reflect/Method;
    //   377: astore_3
    //   378: aload_3
    //   379: aconst_null
    //   380: iconst_0
    //   381: anewarray 4	java/lang/Object
    //   384: invokevirtual 67	java/lang/reflect/Method:invoke	(Ljava/lang/Object;[Ljava/lang/Object;)Ljava/lang/Object;
    //   387: astore_3
    //   388: aload_3
    //   389: checkcast 69	java/lang/Integer
    //   392: invokevirtual 73	java/lang/Integer:intValue	()I
    //   395: putstatic 83	uuuuuu/tytyty:bx00780078xx007800780078x	I
    //   398: aload_1
    //   399: invokevirtual 288	com/db/pwcc/dbmobile/model/tokenization/TokenizationPayload:getTransaction	()Lcom/db/pwcc/dbmobile/model/tokenization/MoPayTransaction;
    //   402: invokevirtual 493	com/db/pwcc/dbmobile/model/tokenization/MoPayTransaction:getBackendCardId	()Ljava/lang/String;
    //   405: astore_3
    //   406: ldc 2
    //   408: ldc_w 495
    //   411: bipush 43
    //   413: sipush 211
    //   416: iconst_2
    //   417: invokestatic 93	xxxxxx/uxxxxx:bbbb0062b0062b0062b0062	(Ljava/lang/String;CCC)Ljava/lang/String;
    //   420: iconst_2
    //   421: anewarray 57	java/lang/Class
    //   424: dup
    //   425: iconst_0
    //   426: ldc_w 284
    //   429: aastore
    //   430: dup
    //   431: iconst_1
    //   432: ldc -64
    //   434: aastore
    //   435: invokevirtual 478	java/lang/Class:getDeclaredMethod	(Ljava/lang/String;[Ljava/lang/Class;)Ljava/lang/reflect/Method;
    //   438: astore 4
    //   440: aload 4
    //   442: aload_0
    //   443: iconst_2
    //   444: anewarray 4	java/lang/Object
    //   447: dup
    //   448: iconst_0
    //   449: aload_1
    //   450: aastore
    //   451: dup
    //   452: iconst_1
    //   453: aload_3
    //   454: aastore
    //   455: invokevirtual 67	java/lang/reflect/Method:invoke	(Ljava/lang/Object;[Ljava/lang/Object;)Ljava/lang/Object;
    //   458: pop
    //   459: return
    //   460: astore_1
    //   461: aload_1
    //   462: invokevirtual 103	java/lang/reflect/InvocationTargetException:getCause	()Ljava/lang/Throwable;
    //   465: athrow
    //   466: astore_1
    //   467: aload_1
    //   468: invokevirtual 103	java/lang/reflect/InvocationTargetException:getCause	()Ljava/lang/Throwable;
    //   471: athrow
    //   472: astore_1
    //   473: aload_1
    //   474: invokevirtual 103	java/lang/reflect/InvocationTargetException:getCause	()Ljava/lang/Throwable;
    //   477: athrow
    //   478: astore_1
    //   479: aload_1
    //   480: invokevirtual 103	java/lang/reflect/InvocationTargetException:getCause	()Ljava/lang/Throwable;
    //   483: athrow
    //   484: astore_1
    //   485: aload_1
    //   486: invokevirtual 103	java/lang/reflect/InvocationTargetException:getCause	()Ljava/lang/Throwable;
    //   489: athrow
    //   490: astore_1
    //   491: aload_1
    //   492: invokevirtual 103	java/lang/reflect/InvocationTargetException:getCause	()Ljava/lang/Throwable;
    //   495: athrow
    // Local variable table:
    //   start	length	slot	name	signature
    //   0	496	0	this	tytyty
    //   0	496	1	paramTokenizationPayload	TokenizationPayload
    //   320	8	2	i	int
    //   4	450	3	localObject1	Object
    //   11	430	4	localObject2	Object
    //   53	61	5	localObject3	Object
    // Exception table:
    //   from	to	target	type
    //   440	459	460	java/lang/reflect/InvocationTargetException
    //   224	234	466	java/lang/reflect/InvocationTargetException
    //   378	388	472	java/lang/reflect/InvocationTargetException
    //   292	302	478	java/lang/reflect/InvocationTargetException
    //   55	67	484	java/lang/reflect/InvocationTargetException
    //   101	113	490	java/lang/reflect/InvocationTargetException
  }
  
  /* Error */
  public void bqqqqqq0071q00710071()
  {
    // Byte code:
    //   0: getstatic 75	uuuuuu/tytyty:b0078x0078xx007800780078x	I
    //   3: istore_1
    //   4: iload_1
    //   5: getstatic 77	uuuuuu/tytyty:b00780078xxx007800780078x	I
    //   8: iload_1
    //   9: iadd
    //   10: imul
    //   11: getstatic 79	uuuuuu/tytyty:bxx0078xx007800780078x	I
    //   14: irem
    //   15: tableswitch	default:+17->32, 0:+27->42
    //   32: bipush 38
    //   34: putstatic 75	uuuuuu/tytyty:b0078x0078xx007800780078x	I
    //   37: bipush 95
    //   39: putstatic 83	uuuuuu/tytyty:bx00780078xx007800780078x	I
    //   42: aload_0
    //   43: getfield 498	uuuuuu/tytyty:b0078xx00780078x00780078x	Luuuuuu/ggyggy;
    //   46: getstatic 504	uuuuuu/gyyygy$yyyygy:bkkk006Bk006Bk006Bk	Luuuuuu/gyyygy$yyyygy;
    //   49: invokevirtual 510	uuuuuu/ggyggy:b0070007000700070pp00700070pp	(Luuuuuu/gyyygy$yyyygy;)Luuuuuu/yyyggy;
    //   52: astore 4
    //   54: ldc 2
    //   56: ldc_w 512
    //   59: sipush 173
    //   62: iconst_0
    //   63: invokestatic 55	xxxxxx/uxxxxx:bb00620062bb0062b0062b0062	(Ljava/lang/String;CC)Ljava/lang/String;
    //   66: iconst_0
    //   67: anewarray 57	java/lang/Class
    //   70: invokevirtual 61	java/lang/Class:getMethod	(Ljava/lang/String;[Ljava/lang/Class;)Ljava/lang/reflect/Method;
    //   73: astore 5
    //   75: aload 5
    //   77: aconst_null
    //   78: iconst_0
    //   79: anewarray 4	java/lang/Object
    //   82: invokevirtual 67	java/lang/reflect/Method:invoke	(Ljava/lang/Object;[Ljava/lang/Object;)Ljava/lang/Object;
    //   85: astore 5
    //   87: aload 5
    //   89: checkcast 69	java/lang/Integer
    //   92: invokevirtual 73	java/lang/Integer:intValue	()I
    //   95: istore_1
    //   96: getstatic 77	uuuuuu/tytyty:b00780078xxx007800780078x	I
    //   99: istore_2
    //   100: ldc 2
    //   102: ldc_w 514
    //   105: sipush 156
    //   108: iconst_2
    //   109: invokestatic 55	xxxxxx/uxxxxx:bb00620062bb0062b0062b0062	(Ljava/lang/String;CC)Ljava/lang/String;
    //   112: iconst_0
    //   113: anewarray 57	java/lang/Class
    //   116: invokevirtual 61	java/lang/Class:getMethod	(Ljava/lang/String;[Ljava/lang/Class;)Ljava/lang/reflect/Method;
    //   119: astore 5
    //   121: aload 5
    //   123: aconst_null
    //   124: iconst_0
    //   125: anewarray 4	java/lang/Object
    //   128: invokevirtual 67	java/lang/reflect/Method:invoke	(Ljava/lang/Object;[Ljava/lang/Object;)Ljava/lang/Object;
    //   131: astore 5
    //   133: aload 5
    //   135: checkcast 69	java/lang/Integer
    //   138: invokevirtual 73	java/lang/Integer:intValue	()I
    //   141: iload_2
    //   142: iload_1
    //   143: iadd
    //   144: imul
    //   145: getstatic 79	uuuuuu/tytyty:bxx0078xx007800780078x	I
    //   148: irem
    //   149: getstatic 83	uuuuuu/tytyty:bx00780078xx007800780078x	I
    //   152: if_icmpeq +275 -> 427
    //   155: ldc 2
    //   157: ldc_w 516
    //   160: bipush 82
    //   162: iconst_0
    //   163: invokestatic 55	xxxxxx/uxxxxx:bb00620062bb0062b0062b0062	(Ljava/lang/String;CC)Ljava/lang/String;
    //   166: iconst_0
    //   167: anewarray 57	java/lang/Class
    //   170: invokevirtual 61	java/lang/Class:getMethod	(Ljava/lang/String;[Ljava/lang/Class;)Ljava/lang/reflect/Method;
    //   173: astore 5
    //   175: aload 5
    //   177: aconst_null
    //   178: iconst_0
    //   179: anewarray 4	java/lang/Object
    //   182: invokevirtual 67	java/lang/reflect/Method:invoke	(Ljava/lang/Object;[Ljava/lang/Object;)Ljava/lang/Object;
    //   185: astore 5
    //   187: aload 5
    //   189: checkcast 69	java/lang/Integer
    //   192: invokevirtual 73	java/lang/Integer:intValue	()I
    //   195: putstatic 75	uuuuuu/tytyty:b0078x0078xx007800780078x	I
    //   198: ldc 2
    //   200: ldc_w 518
    //   203: sipush 240
    //   206: iconst_4
    //   207: invokestatic 55	xxxxxx/uxxxxx:bb00620062bb0062b0062b0062	(Ljava/lang/String;CC)Ljava/lang/String;
    //   210: iconst_0
    //   211: anewarray 57	java/lang/Class
    //   214: invokevirtual 61	java/lang/Class:getMethod	(Ljava/lang/String;[Ljava/lang/Class;)Ljava/lang/reflect/Method;
    //   217: astore 5
    //   219: aload 5
    //   221: aconst_null
    //   222: iconst_0
    //   223: anewarray 4	java/lang/Object
    //   226: invokevirtual 67	java/lang/reflect/Method:invoke	(Ljava/lang/Object;[Ljava/lang/Object;)Ljava/lang/Object;
    //   229: astore 5
    //   231: aload 5
    //   233: checkcast 69	java/lang/Integer
    //   236: invokevirtual 73	java/lang/Integer:intValue	()I
    //   239: putstatic 83	uuuuuu/tytyty:bx00780078xx007800780078x	I
    //   242: getstatic 75	uuuuuu/tytyty:b0078x0078xx007800780078x	I
    //   245: istore_1
    //   246: getstatic 77	uuuuuu/tytyty:b00780078xxx007800780078x	I
    //   249: istore_2
    //   250: getstatic 75	uuuuuu/tytyty:b0078x0078xx007800780078x	I
    //   253: istore_3
    //   254: ldc 2
    //   256: ldc_w 520
    //   259: bipush 114
    //   261: sipush 201
    //   264: iconst_2
    //   265: invokestatic 93	xxxxxx/uxxxxx:bbbb0062b0062b0062b0062	(Ljava/lang/String;CCC)Ljava/lang/String;
    //   268: iconst_0
    //   269: anewarray 57	java/lang/Class
    //   272: invokevirtual 61	java/lang/Class:getMethod	(Ljava/lang/String;[Ljava/lang/Class;)Ljava/lang/reflect/Method;
    //   275: astore 5
    //   277: aload 5
    //   279: aconst_null
    //   280: iconst_0
    //   281: anewarray 4	java/lang/Object
    //   284: invokevirtual 67	java/lang/reflect/Method:invoke	(Ljava/lang/Object;[Ljava/lang/Object;)Ljava/lang/Object;
    //   287: astore 5
    //   289: iload_3
    //   290: iload_1
    //   291: iload_2
    //   292: iadd
    //   293: imul
    //   294: aload 5
    //   296: checkcast 69	java/lang/Integer
    //   299: invokevirtual 73	java/lang/Integer:intValue	()I
    //   302: irem
    //   303: getstatic 83	uuuuuu/tytyty:bx00780078xx007800780078x	I
    //   306: if_icmpeq +121 -> 427
    //   309: getstatic 75	uuuuuu/tytyty:b0078x0078xx007800780078x	I
    //   312: getstatic 77	uuuuuu/tytyty:b00780078xxx007800780078x	I
    //   315: iadd
    //   316: getstatic 75	uuuuuu/tytyty:b0078x0078xx007800780078x	I
    //   319: imul
    //   320: getstatic 79	uuuuuu/tytyty:bxx0078xx007800780078x	I
    //   323: irem
    //   324: getstatic 83	uuuuuu/tytyty:bx00780078xx007800780078x	I
    //   327: if_icmpeq +51 -> 378
    //   330: bipush 72
    //   332: putstatic 75	uuuuuu/tytyty:b0078x0078xx007800780078x	I
    //   335: ldc 2
    //   337: ldc_w 522
    //   340: bipush 97
    //   342: iconst_2
    //   343: invokestatic 55	xxxxxx/uxxxxx:bb00620062bb0062b0062b0062	(Ljava/lang/String;CC)Ljava/lang/String;
    //   346: iconst_0
    //   347: anewarray 57	java/lang/Class
    //   350: invokevirtual 61	java/lang/Class:getMethod	(Ljava/lang/String;[Ljava/lang/Class;)Ljava/lang/reflect/Method;
    //   353: astore 5
    //   355: aload 5
    //   357: aconst_null
    //   358: iconst_0
    //   359: anewarray 4	java/lang/Object
    //   362: invokevirtual 67	java/lang/reflect/Method:invoke	(Ljava/lang/Object;[Ljava/lang/Object;)Ljava/lang/Object;
    //   365: astore 5
    //   367: aload 5
    //   369: checkcast 69	java/lang/Integer
    //   372: invokevirtual 73	java/lang/Integer:intValue	()I
    //   375: putstatic 83	uuuuuu/tytyty:bx00780078xx007800780078x	I
    //   378: ldc 2
    //   380: ldc_w 524
    //   383: sipush 145
    //   386: iconst_2
    //   387: invokestatic 55	xxxxxx/uxxxxx:bb00620062bb0062b0062b0062	(Ljava/lang/String;CC)Ljava/lang/String;
    //   390: iconst_0
    //   391: anewarray 57	java/lang/Class
    //   394: invokevirtual 61	java/lang/Class:getMethod	(Ljava/lang/String;[Ljava/lang/Class;)Ljava/lang/reflect/Method;
    //   397: astore 5
    //   399: aload 5
    //   401: aconst_null
    //   402: iconst_0
    //   403: anewarray 4	java/lang/Object
    //   406: invokevirtual 67	java/lang/reflect/Method:invoke	(Ljava/lang/Object;[Ljava/lang/Object;)Ljava/lang/Object;
    //   409: astore 5
    //   411: aload 5
    //   413: checkcast 69	java/lang/Integer
    //   416: invokevirtual 73	java/lang/Integer:intValue	()I
    //   419: putstatic 75	uuuuuu/tytyty:b0078x0078xx007800780078x	I
    //   422: bipush 30
    //   424: putstatic 83	uuuuuu/tytyty:bx00780078xx007800780078x	I
    //   427: aload 4
    //   429: iconst_1
    //   430: anewarray 4	java/lang/Object
    //   433: dup
    //   434: iconst_0
    //   435: aload_0
    //   436: getfield 118	uuuuuu/tytyty:b0078x007800780078x00780078x	Ljava/util/Map;
    //   439: aastore
    //   440: invokeinterface 530 2 0
    //   445: aload_0
    //   446: getfield 110	uuuuuu/tytyty:bx0078xxx007800780078x	Luuuuuu/ytyyty$yytyty;
    //   449: getstatic 360	uuuuuu/kvkvvv:bf00660066f0066f006600660066	Luuuuuu/kvkvvv;
    //   452: invokeinterface 364 2 0
    //   457: aload_0
    //   458: getfield 118	uuuuuu/tytyty:b0078x007800780078x00780078x	Ljava/util/Map;
    //   461: invokeinterface 533 1 0
    //   466: return
    //   467: astore 4
    //   469: aload 4
    //   471: invokevirtual 103	java/lang/reflect/InvocationTargetException:getCause	()Ljava/lang/Throwable;
    //   474: athrow
    //   475: astore 4
    //   477: aload 4
    //   479: invokevirtual 103	java/lang/reflect/InvocationTargetException:getCause	()Ljava/lang/Throwable;
    //   482: athrow
    //   483: astore 4
    //   485: aload 4
    //   487: invokevirtual 103	java/lang/reflect/InvocationTargetException:getCause	()Ljava/lang/Throwable;
    //   490: athrow
    //   491: astore 4
    //   493: aload 4
    //   495: invokevirtual 103	java/lang/reflect/InvocationTargetException:getCause	()Ljava/lang/Throwable;
    //   498: athrow
    //   499: astore 4
    //   501: aload 4
    //   503: invokevirtual 103	java/lang/reflect/InvocationTargetException:getCause	()Ljava/lang/Throwable;
    //   506: athrow
    //   507: astore 4
    //   509: aload 4
    //   511: invokevirtual 103	java/lang/reflect/InvocationTargetException:getCause	()Ljava/lang/Throwable;
    //   514: athrow
    //   515: astore 4
    //   517: aload 4
    //   519: invokevirtual 103	java/lang/reflect/InvocationTargetException:getCause	()Ljava/lang/Throwable;
    //   522: athrow
    // Local variable table:
    //   start	length	slot	name	signature
    //   0	523	0	this	tytyty
    //   3	290	1	i	int
    //   99	194	2	j	int
    //   253	41	3	k	int
    //   52	376	4	localYyyggy	yyyggy
    //   467	3	4	localInvocationTargetException1	java.lang.reflect.InvocationTargetException
    //   475	3	4	localInvocationTargetException2	java.lang.reflect.InvocationTargetException
    //   483	3	4	localInvocationTargetException3	java.lang.reflect.InvocationTargetException
    //   491	3	4	localInvocationTargetException4	java.lang.reflect.InvocationTargetException
    //   499	3	4	localInvocationTargetException5	java.lang.reflect.InvocationTargetException
    //   507	3	4	localInvocationTargetException6	java.lang.reflect.InvocationTargetException
    //   515	3	4	localInvocationTargetException7	java.lang.reflect.InvocationTargetException
    //   73	339	5	localObject	Object
    // Exception table:
    //   from	to	target	type
    //   399	411	467	java/lang/reflect/InvocationTargetException
    //   175	187	475	java/lang/reflect/InvocationTargetException
    //   219	231	483	java/lang/reflect/InvocationTargetException
    //   277	289	491	java/lang/reflect/InvocationTargetException
    //   121	133	499	java/lang/reflect/InvocationTargetException
    //   75	87	507	java/lang/reflect/InvocationTargetException
    //   355	367	515	java/lang/reflect/InvocationTargetException
  }
}
