package uuuuuu;

import android.content.Context;
import android.content.Intent;
import android.os.Handler;
import com.db.pwcc.dbmobile.secure.preferences.SharedPreferencesHelper;
import javax.inject.Inject;

public class upupup
  extends ssssst<pppuup.puupup>
  implements pppuup.uuupup, yggggy.gygggy
{
  public static final String b007500750075007500750075u00750075 = ";hlmai_sippXYNJ";
  public static int b00750075u0075uu007500750075 = 52;
  public static int b0075u00750075uu007500750075 = 0;
  private static final int b0075uuuuu007500750075 = 500;
  public static int bu007500750075uu007500750075 = 1;
  private static final String bu0075uuuu007500750075;
  public static int buu00750075uu007500750075 = 2;
  public static final String buuuuuu007500750075 = "wksmj}p:\004s\002yw{vu\n\007\007";
  public upupup.ppupup b007500750075uuu007500750075;
  public yggggy b00750075uuuu007500750075;
  @Inject
  public sssttt b0075u0075uuu007500750075;
  private long b0075uu0075uu007500750075 = -1L;
  public Handler bu00750075uuu007500750075;
  @Inject
  public gaaaga bu0075u0075uu007500750075;
  @Inject
  public Context buu0075uuu007500750075;
  @Inject
  public SharedPreferencesHelper buuu0075uu007500750075;
  
  /* Error */
  static
  {
    // Byte code:
    //   0: getstatic 53	uuuuuu/upupup:b007500750075007500750075u00750075	Ljava/lang/String;
    //   3: astore 4
    //   5: getstatic 55	uuuuuu/upupup:b00750075u0075uu007500750075	I
    //   8: istore_0
    //   9: ldc 2
    //   11: ldc 57
    //   13: sipush 185
    //   16: iconst_4
    //   17: invokestatic 63	xxxxxx/uxxxxx:bb00620062bb0062b0062b0062	(Ljava/lang/String;CC)Ljava/lang/String;
    //   20: iconst_0
    //   21: anewarray 65	java/lang/Class
    //   24: invokevirtual 69	java/lang/Class:getMethod	(Ljava/lang/String;[Ljava/lang/Class;)Ljava/lang/reflect/Method;
    //   27: astore 5
    //   29: aload 5
    //   31: aconst_null
    //   32: iconst_0
    //   33: anewarray 71	java/lang/Object
    //   36: invokevirtual 77	java/lang/reflect/Method:invoke	(Ljava/lang/Object;[Ljava/lang/Object;)Ljava/lang/Object;
    //   39: astore 5
    //   41: aload 5
    //   43: checkcast 79	java/lang/Integer
    //   46: invokevirtual 83	java/lang/Integer:intValue	()I
    //   49: iload_0
    //   50: iadd
    //   51: iload_0
    //   52: imul
    //   53: getstatic 85	uuuuuu/upupup:buu00750075uu007500750075	I
    //   56: irem
    //   57: tableswitch	default:+19->76, 0:+246->303
    //   76: getstatic 55	uuuuuu/upupup:b00750075u0075uu007500750075	I
    //   79: istore_0
    //   80: ldc 2
    //   82: ldc 87
    //   84: bipush 83
    //   86: iconst_3
    //   87: invokestatic 63	xxxxxx/uxxxxx:bb00620062bb0062b0062b0062	(Ljava/lang/String;CC)Ljava/lang/String;
    //   90: iconst_0
    //   91: anewarray 65	java/lang/Class
    //   94: invokevirtual 69	java/lang/Class:getMethod	(Ljava/lang/String;[Ljava/lang/Class;)Ljava/lang/reflect/Method;
    //   97: astore 5
    //   99: aload 5
    //   101: aconst_null
    //   102: iconst_0
    //   103: anewarray 71	java/lang/Object
    //   106: invokevirtual 77	java/lang/reflect/Method:invoke	(Ljava/lang/Object;[Ljava/lang/Object;)Ljava/lang/Object;
    //   109: astore 5
    //   111: aload 5
    //   113: checkcast 79	java/lang/Integer
    //   116: invokevirtual 83	java/lang/Integer:intValue	()I
    //   119: istore_1
    //   120: getstatic 55	uuuuuu/upupup:b00750075u0075uu007500750075	I
    //   123: istore_2
    //   124: getstatic 85	uuuuuu/upupup:buu00750075uu007500750075	I
    //   127: istore_3
    //   128: getstatic 55	uuuuuu/upupup:b00750075u0075uu007500750075	I
    //   131: getstatic 89	uuuuuu/upupup:bu007500750075uu007500750075	I
    //   134: iadd
    //   135: getstatic 55	uuuuuu/upupup:b00750075u0075uu007500750075	I
    //   138: imul
    //   139: getstatic 85	uuuuuu/upupup:buu00750075uu007500750075	I
    //   142: irem
    //   143: getstatic 91	uuuuuu/upupup:b0075u00750075uu007500750075	I
    //   146: if_icmpeq +50 -> 196
    //   149: ldc 2
    //   151: ldc 93
    //   153: sipush 180
    //   156: iconst_0
    //   157: invokestatic 63	xxxxxx/uxxxxx:bb00620062bb0062b0062b0062	(Ljava/lang/String;CC)Ljava/lang/String;
    //   160: iconst_0
    //   161: anewarray 65	java/lang/Class
    //   164: invokevirtual 69	java/lang/Class:getMethod	(Ljava/lang/String;[Ljava/lang/Class;)Ljava/lang/reflect/Method;
    //   167: astore 5
    //   169: aload 5
    //   171: aconst_null
    //   172: iconst_0
    //   173: anewarray 71	java/lang/Object
    //   176: invokevirtual 77	java/lang/reflect/Method:invoke	(Ljava/lang/Object;[Ljava/lang/Object;)Ljava/lang/Object;
    //   179: astore 5
    //   181: aload 5
    //   183: checkcast 79	java/lang/Integer
    //   186: invokevirtual 83	java/lang/Integer:intValue	()I
    //   189: putstatic 55	uuuuuu/upupup:b00750075u0075uu007500750075	I
    //   192: iconst_1
    //   193: putstatic 91	uuuuuu/upupup:b0075u00750075uu007500750075	I
    //   196: ldc 2
    //   198: ldc 95
    //   200: sipush 186
    //   203: iconst_1
    //   204: invokestatic 63	xxxxxx/uxxxxx:bb00620062bb0062b0062b0062	(Ljava/lang/String;CC)Ljava/lang/String;
    //   207: iconst_0
    //   208: anewarray 65	java/lang/Class
    //   211: invokevirtual 69	java/lang/Class:getMethod	(Ljava/lang/String;[Ljava/lang/Class;)Ljava/lang/reflect/Method;
    //   214: astore 5
    //   216: aload 5
    //   218: aconst_null
    //   219: iconst_0
    //   220: anewarray 71	java/lang/Object
    //   223: invokevirtual 77	java/lang/reflect/Method:invoke	(Ljava/lang/Object;[Ljava/lang/Object;)Ljava/lang/Object;
    //   226: astore 5
    //   228: iload_2
    //   229: iload_1
    //   230: iload_0
    //   231: iadd
    //   232: imul
    //   233: iload_3
    //   234: irem
    //   235: aload 5
    //   237: checkcast 79	java/lang/Integer
    //   240: invokevirtual 83	java/lang/Integer:intValue	()I
    //   243: if_icmpeq +13 -> 256
    //   246: bipush 28
    //   248: putstatic 55	uuuuuu/upupup:b00750075u0075uu007500750075	I
    //   251: bipush 7
    //   253: putstatic 85	uuuuuu/upupup:buu00750075uu007500750075	I
    //   256: ldc 2
    //   258: ldc 97
    //   260: bipush 11
    //   262: iconst_4
    //   263: invokestatic 63	xxxxxx/uxxxxx:bb00620062bb0062b0062b0062	(Ljava/lang/String;CC)Ljava/lang/String;
    //   266: iconst_0
    //   267: anewarray 65	java/lang/Class
    //   270: invokevirtual 69	java/lang/Class:getMethod	(Ljava/lang/String;[Ljava/lang/Class;)Ljava/lang/reflect/Method;
    //   273: astore 5
    //   275: aload 5
    //   277: aconst_null
    //   278: iconst_0
    //   279: anewarray 71	java/lang/Object
    //   282: invokevirtual 77	java/lang/reflect/Method:invoke	(Ljava/lang/Object;[Ljava/lang/Object;)Ljava/lang/Object;
    //   285: astore 5
    //   287: aload 5
    //   289: checkcast 79	java/lang/Integer
    //   292: invokevirtual 83	java/lang/Integer:intValue	()I
    //   295: putstatic 55	uuuuuu/upupup:b00750075u0075uu007500750075	I
    //   298: bipush 28
    //   300: putstatic 85	uuuuuu/upupup:buu00750075uu007500750075	I
    //   303: ldc 99
    //   305: ldc 101
    //   307: sipush 194
    //   310: sipush 223
    //   313: iconst_0
    //   314: invokestatic 105	xxxxxx/uxxxxx:bbbb0062b0062b0062b0062	(Ljava/lang/String;CCC)Ljava/lang/String;
    //   317: iconst_3
    //   318: anewarray 65	java/lang/Class
    //   321: dup
    //   322: iconst_0
    //   323: ldc 107
    //   325: aastore
    //   326: dup
    //   327: iconst_1
    //   328: getstatic 113	java/lang/Character:TYPE	Ljava/lang/Class;
    //   331: aastore
    //   332: dup
    //   333: iconst_2
    //   334: getstatic 113	java/lang/Character:TYPE	Ljava/lang/Class;
    //   337: aastore
    //   338: invokevirtual 69	java/lang/Class:getMethod	(Ljava/lang/String;[Ljava/lang/Class;)Ljava/lang/reflect/Method;
    //   341: astore 5
    //   343: aload 5
    //   345: aconst_null
    //   346: iconst_3
    //   347: anewarray 71	java/lang/Object
    //   350: dup
    //   351: iconst_0
    //   352: aload 4
    //   354: aastore
    //   355: dup
    //   356: iconst_1
    //   357: sipush 209
    //   360: invokestatic 117	java/lang/Character:valueOf	(C)Ljava/lang/Character;
    //   363: aastore
    //   364: dup
    //   365: iconst_2
    //   366: iconst_0
    //   367: invokestatic 117	java/lang/Character:valueOf	(C)Ljava/lang/Character;
    //   370: aastore
    //   371: invokevirtual 77	java/lang/reflect/Method:invoke	(Ljava/lang/Object;[Ljava/lang/Object;)Ljava/lang/Object;
    //   374: astore 4
    //   376: aload 4
    //   378: checkcast 107	java/lang/String
    //   381: astore 4
    //   383: getstatic 55	uuuuuu/upupup:b00750075u0075uu007500750075	I
    //   386: istore_0
    //   387: iload_0
    //   388: getstatic 89	uuuuuu/upupup:bu007500750075uu007500750075	I
    //   391: iload_0
    //   392: iadd
    //   393: imul
    //   394: getstatic 85	uuuuuu/upupup:buu00750075uu007500750075	I
    //   397: irem
    //   398: tableswitch	default:+18->416, 0:+66->464
    //   416: bipush 90
    //   418: putstatic 55	uuuuuu/upupup:b00750075u0075uu007500750075	I
    //   421: ldc 2
    //   423: ldc 119
    //   425: sipush 197
    //   428: iconst_2
    //   429: invokestatic 63	xxxxxx/uxxxxx:bb00620062bb0062b0062b0062	(Ljava/lang/String;CC)Ljava/lang/String;
    //   432: iconst_0
    //   433: anewarray 65	java/lang/Class
    //   436: invokevirtual 69	java/lang/Class:getMethod	(Ljava/lang/String;[Ljava/lang/Class;)Ljava/lang/reflect/Method;
    //   439: astore 5
    //   441: aload 5
    //   443: aconst_null
    //   444: iconst_0
    //   445: anewarray 71	java/lang/Object
    //   448: invokevirtual 77	java/lang/reflect/Method:invoke	(Ljava/lang/Object;[Ljava/lang/Object;)Ljava/lang/Object;
    //   451: astore 5
    //   453: aload 5
    //   455: checkcast 79	java/lang/Integer
    //   458: invokevirtual 83	java/lang/Integer:intValue	()I
    //   461: putstatic 91	uuuuuu/upupup:b0075u00750075uu007500750075	I
    //   464: aload 4
    //   466: putstatic 53	uuuuuu/upupup:b007500750075007500750075u00750075	Ljava/lang/String;
    //   469: getstatic 121	uuuuuu/upupup:buuuuuu007500750075	Ljava/lang/String;
    //   472: astore 4
    //   474: ldc 99
    //   476: ldc 123
    //   478: bipush 59
    //   480: iconst_4
    //   481: invokestatic 63	xxxxxx/uxxxxx:bb00620062bb0062b0062b0062	(Ljava/lang/String;CC)Ljava/lang/String;
    //   484: iconst_3
    //   485: anewarray 65	java/lang/Class
    //   488: dup
    //   489: iconst_0
    //   490: ldc 107
    //   492: aastore
    //   493: dup
    //   494: iconst_1
    //   495: getstatic 113	java/lang/Character:TYPE	Ljava/lang/Class;
    //   498: aastore
    //   499: dup
    //   500: iconst_2
    //   501: getstatic 113	java/lang/Character:TYPE	Ljava/lang/Class;
    //   504: aastore
    //   505: invokevirtual 69	java/lang/Class:getMethod	(Ljava/lang/String;[Ljava/lang/Class;)Ljava/lang/reflect/Method;
    //   508: astore 5
    //   510: aload 5
    //   512: aconst_null
    //   513: iconst_3
    //   514: anewarray 71	java/lang/Object
    //   517: dup
    //   518: iconst_0
    //   519: aload 4
    //   521: aastore
    //   522: dup
    //   523: iconst_1
    //   524: iconst_5
    //   525: invokestatic 117	java/lang/Character:valueOf	(C)Ljava/lang/Character;
    //   528: aastore
    //   529: dup
    //   530: iconst_2
    //   531: iconst_2
    //   532: invokestatic 117	java/lang/Character:valueOf	(C)Ljava/lang/Character;
    //   535: aastore
    //   536: invokevirtual 77	java/lang/reflect/Method:invoke	(Ljava/lang/Object;[Ljava/lang/Object;)Ljava/lang/Object;
    //   539: astore 4
    //   541: aload 4
    //   543: checkcast 107	java/lang/String
    //   546: putstatic 121	uuuuuu/upupup:buuuuuu007500750075	Ljava/lang/String;
    //   549: ldc 2
    //   551: invokevirtual 127	java/lang/Class:getSimpleName	()Ljava/lang/String;
    //   554: putstatic 129	uuuuuu/upupup:bu0075uuuu007500750075	Ljava/lang/String;
    //   557: return
    //   558: astore 4
    //   560: aload 4
    //   562: invokevirtual 133	java/lang/reflect/InvocationTargetException:getCause	()Ljava/lang/Throwable;
    //   565: athrow
    //   566: astore 4
    //   568: aload 4
    //   570: invokevirtual 133	java/lang/reflect/InvocationTargetException:getCause	()Ljava/lang/Throwable;
    //   573: athrow
    //   574: astore 4
    //   576: aload 4
    //   578: invokevirtual 133	java/lang/reflect/InvocationTargetException:getCause	()Ljava/lang/Throwable;
    //   581: athrow
    //   582: astore 4
    //   584: aload 4
    //   586: invokevirtual 133	java/lang/reflect/InvocationTargetException:getCause	()Ljava/lang/Throwable;
    //   589: athrow
    //   590: astore 4
    //   592: aload 4
    //   594: invokevirtual 133	java/lang/reflect/InvocationTargetException:getCause	()Ljava/lang/Throwable;
    //   597: athrow
    //   598: astore 4
    //   600: aload 4
    //   602: invokevirtual 133	java/lang/reflect/InvocationTargetException:getCause	()Ljava/lang/Throwable;
    //   605: athrow
    //   606: astore 4
    //   608: aload 4
    //   610: invokevirtual 133	java/lang/reflect/InvocationTargetException:getCause	()Ljava/lang/Throwable;
    //   613: athrow
    //   614: astore 4
    //   616: aload 4
    //   618: invokevirtual 133	java/lang/reflect/InvocationTargetException:getCause	()Ljava/lang/Throwable;
    //   621: athrow
    // Local variable table:
    //   start	length	slot	name	signature
    //   8	386	0	i	int
    //   119	113	1	j	int
    //   123	110	2	k	int
    //   127	108	3	m	int
    //   3	539	4	localObject1	Object
    //   558	3	4	localInvocationTargetException1	java.lang.reflect.InvocationTargetException
    //   566	3	4	localInvocationTargetException2	java.lang.reflect.InvocationTargetException
    //   574	3	4	localInvocationTargetException3	java.lang.reflect.InvocationTargetException
    //   582	3	4	localInvocationTargetException4	java.lang.reflect.InvocationTargetException
    //   590	3	4	localInvocationTargetException5	java.lang.reflect.InvocationTargetException
    //   598	3	4	localInvocationTargetException6	java.lang.reflect.InvocationTargetException
    //   606	3	4	localInvocationTargetException7	java.lang.reflect.InvocationTargetException
    //   614	3	4	localInvocationTargetException8	java.lang.reflect.InvocationTargetException
    //   27	484	5	localObject2	Object
    // Exception table:
    //   from	to	target	type
    //   99	111	558	java/lang/reflect/InvocationTargetException
    //   510	541	566	java/lang/reflect/InvocationTargetException
    //   275	287	574	java/lang/reflect/InvocationTargetException
    //   343	376	582	java/lang/reflect/InvocationTargetException
    //   216	228	590	java/lang/reflect/InvocationTargetException
    //   169	181	598	java/lang/reflect/InvocationTargetException
    //   29	41	606	java/lang/reflect/InvocationTargetException
    //   441	453	614	java/lang/reflect/InvocationTargetException
  }
  
  public upupup() {}
  
  public static int b00610061a0061a0061a0061aa()
  {
    return 2;
  }
  
  public static int b0061a00610061a0061a0061aa()
  {
    return 1;
  }
  
  /* Error */
  private void b0061a0061a00610061a0061aa()
  {
    // Byte code:
    //   0: getstatic 55	uuuuuu/upupup:b00750075u0075uu007500750075	I
    //   3: istore_1
    //   4: iload_1
    //   5: getstatic 89	uuuuuu/upupup:bu007500750075uu007500750075	I
    //   8: iload_1
    //   9: iadd
    //   10: imul
    //   11: getstatic 85	uuuuuu/upupup:buu00750075uu007500750075	I
    //   14: irem
    //   15: tableswitch	default:+17->32, 0:+27->42
    //   32: bipush 26
    //   34: putstatic 55	uuuuuu/upupup:b00750075u0075uu007500750075	I
    //   37: bipush 50
    //   39: putstatic 91	uuuuuu/upupup:b0075u00750075uu007500750075	I
    //   42: invokestatic 162	java/lang/System:currentTimeMillis	()J
    //   45: aload_0
    //   46: getfield 141	uuuuuu/upupup:b0075uu0075uu007500750075	J
    //   49: lsub
    //   50: lstore_2
    //   51: lload_2
    //   52: ldc2_w 163
    //   55: lcmp
    //   56: iflt +16 -> 72
    //   59: aload_0
    //   60: getfield 166	uuuuuu/upupup:bu00750075uuu007500750075	Landroid/os/Handler;
    //   63: aload_0
    //   64: getfield 168	uuuuuu/upupup:b007500750075uuu007500750075	Luuuuuu/upupup$ppupup;
    //   67: invokevirtual 174	android/os/Handler:post	(Ljava/lang/Runnable;)Z
    //   70: pop
    //   71: return
    //   72: aload_0
    //   73: getfield 166	uuuuuu/upupup:bu00750075uuu007500750075	Landroid/os/Handler;
    //   76: astore 4
    //   78: aload_0
    //   79: getfield 168	uuuuuu/upupup:b007500750075uuu007500750075	Luuuuuu/upupup$ppupup;
    //   82: astore 5
    //   84: getstatic 55	uuuuuu/upupup:b00750075u0075uu007500750075	I
    //   87: getstatic 89	uuuuuu/upupup:bu007500750075uu007500750075	I
    //   90: iadd
    //   91: getstatic 55	uuuuuu/upupup:b00750075u0075uu007500750075	I
    //   94: imul
    //   95: getstatic 85	uuuuuu/upupup:buu00750075uu007500750075	I
    //   98: irem
    //   99: getstatic 91	uuuuuu/upupup:b0075u00750075uu007500750075	I
    //   102: if_icmpeq +96 -> 198
    //   105: ldc 2
    //   107: ldc -80
    //   109: bipush 99
    //   111: sipush 202
    //   114: iconst_3
    //   115: invokestatic 105	xxxxxx/uxxxxx:bbbb0062b0062b0062b0062	(Ljava/lang/String;CCC)Ljava/lang/String;
    //   118: iconst_0
    //   119: anewarray 65	java/lang/Class
    //   122: invokevirtual 69	java/lang/Class:getMethod	(Ljava/lang/String;[Ljava/lang/Class;)Ljava/lang/reflect/Method;
    //   125: astore 6
    //   127: aload 6
    //   129: aconst_null
    //   130: iconst_0
    //   131: anewarray 71	java/lang/Object
    //   134: invokevirtual 77	java/lang/reflect/Method:invoke	(Ljava/lang/Object;[Ljava/lang/Object;)Ljava/lang/Object;
    //   137: astore 6
    //   139: aload 6
    //   141: checkcast 79	java/lang/Integer
    //   144: invokevirtual 83	java/lang/Integer:intValue	()I
    //   147: putstatic 55	uuuuuu/upupup:b00750075u0075uu007500750075	I
    //   150: bipush 89
    //   152: putstatic 91	uuuuuu/upupup:b0075u00750075uu007500750075	I
    //   155: getstatic 55	uuuuuu/upupup:b00750075u0075uu007500750075	I
    //   158: istore_1
    //   159: iload_1
    //   160: getstatic 89	uuuuuu/upupup:bu007500750075uu007500750075	I
    //   163: iload_1
    //   164: iadd
    //   165: imul
    //   166: getstatic 85	uuuuuu/upupup:buu00750075uu007500750075	I
    //   169: irem
    //   170: tableswitch	default:+18->188, 0:+28->198
    //   188: bipush 61
    //   190: putstatic 55	uuuuuu/upupup:b00750075u0075uu007500750075	I
    //   193: bipush 95
    //   195: putstatic 91	uuuuuu/upupup:b0075u00750075uu007500750075	I
    //   198: getstatic 55	uuuuuu/upupup:b00750075u0075uu007500750075	I
    //   201: getstatic 89	uuuuuu/upupup:bu007500750075uu007500750075	I
    //   204: iadd
    //   205: getstatic 55	uuuuuu/upupup:b00750075u0075uu007500750075	I
    //   208: imul
    //   209: getstatic 85	uuuuuu/upupup:buu00750075uu007500750075	I
    //   212: irem
    //   213: getstatic 91	uuuuuu/upupup:b0075u00750075uu007500750075	I
    //   216: if_icmpeq +87 -> 303
    //   219: ldc 2
    //   221: ldc -78
    //   223: bipush 98
    //   225: iconst_4
    //   226: invokestatic 63	xxxxxx/uxxxxx:bb00620062bb0062b0062b0062	(Ljava/lang/String;CC)Ljava/lang/String;
    //   229: iconst_0
    //   230: anewarray 65	java/lang/Class
    //   233: invokevirtual 69	java/lang/Class:getMethod	(Ljava/lang/String;[Ljava/lang/Class;)Ljava/lang/reflect/Method;
    //   236: astore 6
    //   238: aload 6
    //   240: aconst_null
    //   241: iconst_0
    //   242: anewarray 71	java/lang/Object
    //   245: invokevirtual 77	java/lang/reflect/Method:invoke	(Ljava/lang/Object;[Ljava/lang/Object;)Ljava/lang/Object;
    //   248: astore 6
    //   250: aload 6
    //   252: checkcast 79	java/lang/Integer
    //   255: invokevirtual 83	java/lang/Integer:intValue	()I
    //   258: putstatic 55	uuuuuu/upupup:b00750075u0075uu007500750075	I
    //   261: ldc 2
    //   263: ldc 97
    //   265: bipush 92
    //   267: iconst_5
    //   268: invokestatic 63	xxxxxx/uxxxxx:bb00620062bb0062b0062b0062	(Ljava/lang/String;CC)Ljava/lang/String;
    //   271: iconst_0
    //   272: anewarray 65	java/lang/Class
    //   275: invokevirtual 69	java/lang/Class:getMethod	(Ljava/lang/String;[Ljava/lang/Class;)Ljava/lang/reflect/Method;
    //   278: astore 6
    //   280: aload 6
    //   282: aconst_null
    //   283: iconst_0
    //   284: anewarray 71	java/lang/Object
    //   287: invokevirtual 77	java/lang/reflect/Method:invoke	(Ljava/lang/Object;[Ljava/lang/Object;)Ljava/lang/Object;
    //   290: astore 6
    //   292: aload 6
    //   294: checkcast 79	java/lang/Integer
    //   297: invokevirtual 83	java/lang/Integer:intValue	()I
    //   300: putstatic 91	uuuuuu/upupup:b0075u00750075uu007500750075	I
    //   303: aload 4
    //   305: aload 5
    //   307: ldc2_w 163
    //   310: lload_2
    //   311: lsub
    //   312: invokevirtual 182	android/os/Handler:postDelayed	(Ljava/lang/Runnable;J)Z
    //   315: pop
    //   316: return
    //   317: astore 4
    //   319: aload 4
    //   321: invokevirtual 133	java/lang/reflect/InvocationTargetException:getCause	()Ljava/lang/Throwable;
    //   324: athrow
    //   325: astore 4
    //   327: aload 4
    //   329: invokevirtual 133	java/lang/reflect/InvocationTargetException:getCause	()Ljava/lang/Throwable;
    //   332: athrow
    //   333: astore 4
    //   335: aload 4
    //   337: invokevirtual 133	java/lang/reflect/InvocationTargetException:getCause	()Ljava/lang/Throwable;
    //   340: athrow
    // Local variable table:
    //   start	length	slot	name	signature
    //   0	341	0	this	upupup
    //   3	163	1	i	int
    //   50	261	2	l	long
    //   76	228	4	localHandler	Handler
    //   317	3	4	localInvocationTargetException1	java.lang.reflect.InvocationTargetException
    //   325	3	4	localInvocationTargetException2	java.lang.reflect.InvocationTargetException
    //   333	3	4	localInvocationTargetException3	java.lang.reflect.InvocationTargetException
    //   82	224	5	localPpupup	upupup.ppupup
    //   125	168	6	localObject	Object
    // Exception table:
    //   from	to	target	type
    //   127	139	317	java/lang/reflect/InvocationTargetException
    //   238	250	325	java/lang/reflect/InvocationTargetException
    //   280	292	333	java/lang/reflect/InvocationTargetException
  }
  
  /* Error */
  private void ba00610061a00610061a0061aa()
  {
    // Byte code:
    //   0: aload_0
    //   1: getfield 196	uuuuuu/upupup:b006En006E006E006En006E006En	Luuuuuu/ggyggy;
    //   4: invokevirtual 202	uuuuuu/ggyggy:bpppp0070p00700070pp	()Z
    //   7: ifeq +339 -> 346
    //   10: aload_0
    //   11: getfield 196	uuuuuu/upupup:b006En006E006E006En006E006En	Luuuuuu/ggyggy;
    //   14: invokevirtual 205	uuuuuu/ggyggy:b0070p00700070pp00700070pp	()V
    //   17: aload_0
    //   18: getfield 196	uuuuuu/upupup:b006En006E006E006En006E006En	Luuuuuu/ggyggy;
    //   21: getstatic 211	uuuuuu/gyyygy$ggggyy:b006B006Bk006Bk006Bk006Bk	Luuuuuu/gyyygy$ggggyy;
    //   24: invokevirtual 215	uuuuuu/ggyggy:bpp0070p0070p00700070pp	(Luuuuuu/gyyygy$ggggyy;)V
    //   27: getstatic 55	uuuuuu/upupup:b00750075u0075uu007500750075	I
    //   30: istore_1
    //   31: getstatic 89	uuuuuu/upupup:bu007500750075uu007500750075	I
    //   34: istore_2
    //   35: getstatic 85	uuuuuu/upupup:buu00750075uu007500750075	I
    //   38: istore_3
    //   39: getstatic 55	uuuuuu/upupup:b00750075u0075uu007500750075	I
    //   42: getstatic 89	uuuuuu/upupup:bu007500750075uu007500750075	I
    //   45: iadd
    //   46: getstatic 55	uuuuuu/upupup:b00750075u0075uu007500750075	I
    //   49: imul
    //   50: getstatic 85	uuuuuu/upupup:buu00750075uu007500750075	I
    //   53: irem
    //   54: getstatic 91	uuuuuu/upupup:b0075u00750075uu007500750075	I
    //   57: if_icmpeq +137 -> 194
    //   60: getstatic 55	uuuuuu/upupup:b00750075u0075uu007500750075	I
    //   63: istore 4
    //   65: iload 4
    //   67: getstatic 89	uuuuuu/upupup:bu007500750075uu007500750075	I
    //   70: iload 4
    //   72: iadd
    //   73: imul
    //   74: getstatic 85	uuuuuu/upupup:buu00750075uu007500750075	I
    //   77: irem
    //   78: tableswitch	default:+18->96, 0:+66->144
    //   96: bipush 28
    //   98: putstatic 55	uuuuuu/upupup:b00750075u0075uu007500750075	I
    //   101: ldc 2
    //   103: ldc -39
    //   105: sipush 189
    //   108: iconst_5
    //   109: invokestatic 63	xxxxxx/uxxxxx:bb00620062bb0062b0062b0062	(Ljava/lang/String;CC)Ljava/lang/String;
    //   112: iconst_0
    //   113: anewarray 65	java/lang/Class
    //   116: invokevirtual 69	java/lang/Class:getMethod	(Ljava/lang/String;[Ljava/lang/Class;)Ljava/lang/reflect/Method;
    //   119: astore 5
    //   121: aload 5
    //   123: aconst_null
    //   124: iconst_0
    //   125: anewarray 71	java/lang/Object
    //   128: invokevirtual 77	java/lang/reflect/Method:invoke	(Ljava/lang/Object;[Ljava/lang/Object;)Ljava/lang/Object;
    //   131: astore 5
    //   133: aload 5
    //   135: checkcast 79	java/lang/Integer
    //   138: invokevirtual 83	java/lang/Integer:intValue	()I
    //   141: putstatic 91	uuuuuu/upupup:b0075u00750075uu007500750075	I
    //   144: ldc 2
    //   146: ldc -37
    //   148: bipush 42
    //   150: sipush 196
    //   153: iconst_1
    //   154: invokestatic 105	xxxxxx/uxxxxx:bbbb0062b0062b0062b0062	(Ljava/lang/String;CCC)Ljava/lang/String;
    //   157: iconst_0
    //   158: anewarray 65	java/lang/Class
    //   161: invokevirtual 69	java/lang/Class:getMethod	(Ljava/lang/String;[Ljava/lang/Class;)Ljava/lang/reflect/Method;
    //   164: astore 5
    //   166: aload 5
    //   168: aconst_null
    //   169: iconst_0
    //   170: anewarray 71	java/lang/Object
    //   173: invokevirtual 77	java/lang/reflect/Method:invoke	(Ljava/lang/Object;[Ljava/lang/Object;)Ljava/lang/Object;
    //   176: astore 5
    //   178: aload 5
    //   180: checkcast 79	java/lang/Integer
    //   183: invokevirtual 83	java/lang/Integer:intValue	()I
    //   186: putstatic 55	uuuuuu/upupup:b00750075u0075uu007500750075	I
    //   189: bipush 52
    //   191: putstatic 91	uuuuuu/upupup:b0075u00750075uu007500750075	I
    //   194: iload_2
    //   195: iload_1
    //   196: iadd
    //   197: iload_1
    //   198: imul
    //   199: iload_3
    //   200: irem
    //   201: tableswitch	default:+19->220, 0:+145->346
    //   220: getstatic 55	uuuuuu/upupup:b00750075u0075uu007500750075	I
    //   223: istore_1
    //   224: iload_1
    //   225: getstatic 89	uuuuuu/upupup:bu007500750075uu007500750075	I
    //   228: iload_1
    //   229: iadd
    //   230: imul
    //   231: getstatic 85	uuuuuu/upupup:buu00750075uu007500750075	I
    //   234: irem
    //   235: tableswitch	default:+17->252, 0:+64->299
    //   252: bipush 82
    //   254: putstatic 55	uuuuuu/upupup:b00750075u0075uu007500750075	I
    //   257: ldc 2
    //   259: ldc -35
    //   261: bipush 28
    //   263: iconst_5
    //   264: invokestatic 63	xxxxxx/uxxxxx:bb00620062bb0062b0062b0062	(Ljava/lang/String;CC)Ljava/lang/String;
    //   267: iconst_0
    //   268: anewarray 65	java/lang/Class
    //   271: invokevirtual 69	java/lang/Class:getMethod	(Ljava/lang/String;[Ljava/lang/Class;)Ljava/lang/reflect/Method;
    //   274: astore 5
    //   276: aload 5
    //   278: aconst_null
    //   279: iconst_0
    //   280: anewarray 71	java/lang/Object
    //   283: invokevirtual 77	java/lang/reflect/Method:invoke	(Ljava/lang/Object;[Ljava/lang/Object;)Ljava/lang/Object;
    //   286: astore 5
    //   288: aload 5
    //   290: checkcast 79	java/lang/Integer
    //   293: invokevirtual 83	java/lang/Integer:intValue	()I
    //   296: putstatic 91	uuuuuu/upupup:b0075u00750075uu007500750075	I
    //   299: ldc 2
    //   301: ldc -33
    //   303: bipush 112
    //   305: iconst_2
    //   306: invokestatic 63	xxxxxx/uxxxxx:bb00620062bb0062b0062b0062	(Ljava/lang/String;CC)Ljava/lang/String;
    //   309: iconst_0
    //   310: anewarray 65	java/lang/Class
    //   313: invokevirtual 69	java/lang/Class:getMethod	(Ljava/lang/String;[Ljava/lang/Class;)Ljava/lang/reflect/Method;
    //   316: astore 5
    //   318: aload 5
    //   320: aconst_null
    //   321: iconst_0
    //   322: anewarray 71	java/lang/Object
    //   325: invokevirtual 77	java/lang/reflect/Method:invoke	(Ljava/lang/Object;[Ljava/lang/Object;)Ljava/lang/Object;
    //   328: astore 5
    //   330: aload 5
    //   332: checkcast 79	java/lang/Integer
    //   335: invokevirtual 83	java/lang/Integer:intValue	()I
    //   338: putstatic 55	uuuuuu/upupup:b00750075u0075uu007500750075	I
    //   341: bipush 64
    //   343: putstatic 91	uuuuuu/upupup:b0075u00750075uu007500750075	I
    //   346: return
    //   347: astore 5
    //   349: aload 5
    //   351: invokevirtual 133	java/lang/reflect/InvocationTargetException:getCause	()Ljava/lang/Throwable;
    //   354: athrow
    //   355: astore 5
    //   357: aload 5
    //   359: invokevirtual 133	java/lang/reflect/InvocationTargetException:getCause	()Ljava/lang/Throwable;
    //   362: athrow
    //   363: astore 5
    //   365: aload 5
    //   367: invokevirtual 133	java/lang/reflect/InvocationTargetException:getCause	()Ljava/lang/Throwable;
    //   370: athrow
    //   371: astore 5
    //   373: aload 5
    //   375: invokevirtual 133	java/lang/reflect/InvocationTargetException:getCause	()Ljava/lang/Throwable;
    //   378: athrow
    // Local variable table:
    //   start	length	slot	name	signature
    //   0	379	0	this	upupup
    //   30	201	1	i	int
    //   34	163	2	j	int
    //   38	163	3	k	int
    //   63	11	4	m	int
    //   119	212	5	localObject	Object
    //   347	3	5	localInvocationTargetException1	java.lang.reflect.InvocationTargetException
    //   355	3	5	localInvocationTargetException2	java.lang.reflect.InvocationTargetException
    //   363	3	5	localInvocationTargetException3	java.lang.reflect.InvocationTargetException
    //   371	3	5	localInvocationTargetException4	java.lang.reflect.InvocationTargetException
    // Exception table:
    //   from	to	target	type
    //   318	330	347	java/lang/reflect/InvocationTargetException
    //   166	178	355	java/lang/reflect/InvocationTargetException
    //   121	133	363	java/lang/reflect/InvocationTargetException
    //   276	288	371	java/lang/reflect/InvocationTargetException
  }
  
  public static int baa00610061a0061a0061aa()
  {
    return 69;
  }
  
  public static int baaa0061a0061a0061aa()
  {
    return 0;
  }
  
  /* Error */
  public void b00610061006100610061aa0061aa()
  {
    // Byte code:
    //   0: aload_0
    //   1: getfield 196	uuuuuu/upupup:b006En006E006E006En006E006En	Luuuuuu/ggyggy;
    //   4: getstatic 248	uuuuuu/gyyygy$yyyygy:bkkk006Bk006Bk006Bk	Luuuuuu/gyyygy$yyyygy;
    //   7: invokevirtual 252	uuuuuu/ggyggy:b0070007000700070pp00700070pp	(Luuuuuu/gyyygy$yyyygy;)Luuuuuu/yyyggy;
    //   10: astore_3
    //   11: getstatic 258	uuuuuu/lolllo:bq0071q0071qqqq0071	Luuuuuu/lolllo;
    //   14: astore 4
    //   16: getstatic 55	uuuuuu/upupup:b00750075u0075uu007500750075	I
    //   19: getstatic 89	uuuuuu/upupup:bu007500750075uu007500750075	I
    //   22: iadd
    //   23: getstatic 55	uuuuuu/upupup:b00750075u0075uu007500750075	I
    //   26: imul
    //   27: getstatic 85	uuuuuu/upupup:buu00750075uu007500750075	I
    //   30: irem
    //   31: getstatic 91	uuuuuu/upupup:b0075u00750075uu007500750075	I
    //   34: if_icmpeq +337 -> 371
    //   37: bipush 14
    //   39: putstatic 55	uuuuuu/upupup:b00750075u0075uu007500750075	I
    //   42: bipush 69
    //   44: putstatic 91	uuuuuu/upupup:b0075u00750075uu007500750075	I
    //   47: ldc 2
    //   49: ldc_w 260
    //   52: sipush 147
    //   55: iconst_1
    //   56: invokestatic 63	xxxxxx/uxxxxx:bb00620062bb0062b0062b0062	(Ljava/lang/String;CC)Ljava/lang/String;
    //   59: iconst_0
    //   60: anewarray 65	java/lang/Class
    //   63: invokevirtual 69	java/lang/Class:getMethod	(Ljava/lang/String;[Ljava/lang/Class;)Ljava/lang/reflect/Method;
    //   66: astore 5
    //   68: aload 5
    //   70: aconst_null
    //   71: iconst_0
    //   72: anewarray 71	java/lang/Object
    //   75: invokevirtual 77	java/lang/reflect/Method:invoke	(Ljava/lang/Object;[Ljava/lang/Object;)Ljava/lang/Object;
    //   78: astore 5
    //   80: aload 5
    //   82: checkcast 79	java/lang/Integer
    //   85: invokevirtual 83	java/lang/Integer:intValue	()I
    //   88: istore_1
    //   89: getstatic 55	uuuuuu/upupup:b00750075u0075uu007500750075	I
    //   92: istore_2
    //   93: iload_2
    //   94: getstatic 89	uuuuuu/upupup:bu007500750075uu007500750075	I
    //   97: iload_2
    //   98: iadd
    //   99: imul
    //   100: getstatic 85	uuuuuu/upupup:buu00750075uu007500750075	I
    //   103: irem
    //   104: tableswitch	default:+20->124, 0:+192->296
    //   124: getstatic 55	uuuuuu/upupup:b00750075u0075uu007500750075	I
    //   127: istore_2
    //   128: iload_2
    //   129: getstatic 89	uuuuuu/upupup:bu007500750075uu007500750075	I
    //   132: iload_2
    //   133: iadd
    //   134: imul
    //   135: getstatic 85	uuuuuu/upupup:buu00750075uu007500750075	I
    //   138: irem
    //   139: tableswitch	default:+17->156, 0:+109->248
    //   156: ldc 2
    //   158: ldc_w 262
    //   161: sipush 209
    //   164: bipush 37
    //   166: iconst_3
    //   167: invokestatic 105	xxxxxx/uxxxxx:bbbb0062b0062b0062b0062	(Ljava/lang/String;CCC)Ljava/lang/String;
    //   170: iconst_0
    //   171: anewarray 65	java/lang/Class
    //   174: invokevirtual 69	java/lang/Class:getMethod	(Ljava/lang/String;[Ljava/lang/Class;)Ljava/lang/reflect/Method;
    //   177: astore 5
    //   179: aload 5
    //   181: aconst_null
    //   182: iconst_0
    //   183: anewarray 71	java/lang/Object
    //   186: invokevirtual 77	java/lang/reflect/Method:invoke	(Ljava/lang/Object;[Ljava/lang/Object;)Ljava/lang/Object;
    //   189: astore 5
    //   191: aload 5
    //   193: checkcast 79	java/lang/Integer
    //   196: invokevirtual 83	java/lang/Integer:intValue	()I
    //   199: putstatic 55	uuuuuu/upupup:b00750075u0075uu007500750075	I
    //   202: ldc 2
    //   204: ldc -26
    //   206: sipush 162
    //   209: sipush 148
    //   212: iconst_2
    //   213: invokestatic 105	xxxxxx/uxxxxx:bbbb0062b0062b0062b0062	(Ljava/lang/String;CCC)Ljava/lang/String;
    //   216: iconst_0
    //   217: anewarray 65	java/lang/Class
    //   220: invokevirtual 69	java/lang/Class:getMethod	(Ljava/lang/String;[Ljava/lang/Class;)Ljava/lang/reflect/Method;
    //   223: astore 5
    //   225: aload 5
    //   227: aconst_null
    //   228: iconst_0
    //   229: anewarray 71	java/lang/Object
    //   232: invokevirtual 77	java/lang/reflect/Method:invoke	(Ljava/lang/Object;[Ljava/lang/Object;)Ljava/lang/Object;
    //   235: astore 5
    //   237: aload 5
    //   239: checkcast 79	java/lang/Integer
    //   242: invokevirtual 83	java/lang/Integer:intValue	()I
    //   245: putstatic 91	uuuuuu/upupup:b0075u00750075uu007500750075	I
    //   248: ldc 2
    //   250: ldc_w 264
    //   253: bipush 15
    //   255: iconst_4
    //   256: invokestatic 63	xxxxxx/uxxxxx:bb00620062bb0062b0062b0062	(Ljava/lang/String;CC)Ljava/lang/String;
    //   259: iconst_0
    //   260: anewarray 65	java/lang/Class
    //   263: invokevirtual 69	java/lang/Class:getMethod	(Ljava/lang/String;[Ljava/lang/Class;)Ljava/lang/reflect/Method;
    //   266: astore 5
    //   268: aload 5
    //   270: aconst_null
    //   271: iconst_0
    //   272: anewarray 71	java/lang/Object
    //   275: invokevirtual 77	java/lang/reflect/Method:invoke	(Ljava/lang/Object;[Ljava/lang/Object;)Ljava/lang/Object;
    //   278: astore 5
    //   280: aload 5
    //   282: checkcast 79	java/lang/Integer
    //   285: invokevirtual 83	java/lang/Integer:intValue	()I
    //   288: putstatic 55	uuuuuu/upupup:b00750075u0075uu007500750075	I
    //   291: bipush 16
    //   293: putstatic 91	uuuuuu/upupup:b0075u00750075uu007500750075	I
    //   296: getstatic 89	uuuuuu/upupup:bu007500750075uu007500750075	I
    //   299: iload_1
    //   300: iadd
    //   301: iload_1
    //   302: imul
    //   303: getstatic 85	uuuuuu/upupup:buu00750075uu007500750075	I
    //   306: irem
    //   307: tableswitch	default:+17->324, 0:+64->371
    //   324: iconst_5
    //   325: putstatic 55	uuuuuu/upupup:b00750075u0075uu007500750075	I
    //   328: ldc 2
    //   330: ldc_w 266
    //   333: bipush 92
    //   335: iconst_1
    //   336: invokestatic 63	xxxxxx/uxxxxx:bb00620062bb0062b0062b0062	(Ljava/lang/String;CC)Ljava/lang/String;
    //   339: iconst_0
    //   340: anewarray 65	java/lang/Class
    //   343: invokevirtual 69	java/lang/Class:getMethod	(Ljava/lang/String;[Ljava/lang/Class;)Ljava/lang/reflect/Method;
    //   346: astore 5
    //   348: aload 5
    //   350: aconst_null
    //   351: iconst_0
    //   352: anewarray 71	java/lang/Object
    //   355: invokevirtual 77	java/lang/reflect/Method:invoke	(Ljava/lang/Object;[Ljava/lang/Object;)Ljava/lang/Object;
    //   358: astore 5
    //   360: aload 5
    //   362: checkcast 79	java/lang/Integer
    //   365: invokevirtual 83	java/lang/Integer:intValue	()I
    //   368: putstatic 91	uuuuuu/upupup:b0075u00750075uu007500750075	I
    //   371: aload_3
    //   372: iconst_1
    //   373: anewarray 71	java/lang/Object
    //   376: dup
    //   377: iconst_0
    //   378: aload 4
    //   380: invokevirtual 269	uuuuuu/lolllo:name	()Ljava/lang/String;
    //   383: aastore
    //   384: invokeinterface 275 2 0
    //   389: aload_0
    //   390: getfield 277	uuuuuu/upupup:bu0075u0075uu007500750075	Luuuuuu/gaaaga;
    //   393: invokevirtual 282	uuuuuu/gaaaga:bww0077w0077ww0077ww	()V
    //   396: return
    //   397: astore_3
    //   398: aload_3
    //   399: invokevirtual 133	java/lang/reflect/InvocationTargetException:getCause	()Ljava/lang/Throwable;
    //   402: athrow
    //   403: astore_3
    //   404: aload_3
    //   405: invokevirtual 133	java/lang/reflect/InvocationTargetException:getCause	()Ljava/lang/Throwable;
    //   408: athrow
    //   409: astore_3
    //   410: aload_3
    //   411: invokevirtual 133	java/lang/reflect/InvocationTargetException:getCause	()Ljava/lang/Throwable;
    //   414: athrow
    //   415: astore_3
    //   416: aload_3
    //   417: invokevirtual 133	java/lang/reflect/InvocationTargetException:getCause	()Ljava/lang/Throwable;
    //   420: athrow
    //   421: astore_3
    //   422: aload_3
    //   423: invokevirtual 133	java/lang/reflect/InvocationTargetException:getCause	()Ljava/lang/Throwable;
    //   426: athrow
    // Local variable table:
    //   start	length	slot	name	signature
    //   0	427	0	this	upupup
    //   88	215	1	i	int
    //   92	43	2	j	int
    //   10	362	3	localYyyggy	yyyggy
    //   397	2	3	localInvocationTargetException1	java.lang.reflect.InvocationTargetException
    //   403	2	3	localInvocationTargetException2	java.lang.reflect.InvocationTargetException
    //   409	2	3	localInvocationTargetException3	java.lang.reflect.InvocationTargetException
    //   415	2	3	localInvocationTargetException4	java.lang.reflect.InvocationTargetException
    //   421	2	3	localInvocationTargetException5	java.lang.reflect.InvocationTargetException
    //   14	365	4	localLolllo	lolllo
    //   66	295	5	localObject	Object
    // Exception table:
    //   from	to	target	type
    //   348	360	397	java/lang/reflect/InvocationTargetException
    //   68	80	403	java/lang/reflect/InvocationTargetException
    //   268	280	409	java/lang/reflect/InvocationTargetException
    //   179	191	415	java/lang/reflect/InvocationTargetException
    //   225	237	421	java/lang/reflect/InvocationTargetException
  }
  
  /* Error */
  public void b0061006100610061a0061a0061aa()
  {
    // Byte code:
    //   0: aload_0
    //   1: invokestatic 162	java/lang/System:currentTimeMillis	()J
    //   4: putfield 141	uuuuuu/upupup:b0075uu0075uu007500750075	J
    //   7: aload_0
    //   8: getfield 285	uuuuuu/upupup:b00750075uuuu007500750075	Luuuuuu/yggggy;
    //   11: astore_2
    //   12: getstatic 55	uuuuuu/upupup:b00750075u0075uu007500750075	I
    //   15: istore_1
    //   16: ldc 2
    //   18: ldc_w 287
    //   21: sipush 240
    //   24: iconst_1
    //   25: invokestatic 63	xxxxxx/uxxxxx:bb00620062bb0062b0062b0062	(Ljava/lang/String;CC)Ljava/lang/String;
    //   28: iconst_0
    //   29: anewarray 65	java/lang/Class
    //   32: invokevirtual 69	java/lang/Class:getMethod	(Ljava/lang/String;[Ljava/lang/Class;)Ljava/lang/reflect/Method;
    //   35: astore_3
    //   36: aload_3
    //   37: aconst_null
    //   38: iconst_0
    //   39: anewarray 71	java/lang/Object
    //   42: invokevirtual 77	java/lang/reflect/Method:invoke	(Ljava/lang/Object;[Ljava/lang/Object;)Ljava/lang/Object;
    //   45: astore_3
    //   46: aload_3
    //   47: checkcast 79	java/lang/Integer
    //   50: invokevirtual 83	java/lang/Integer:intValue	()I
    //   53: iload_1
    //   54: iadd
    //   55: getstatic 55	uuuuuu/upupup:b00750075u0075uu007500750075	I
    //   58: imul
    //   59: getstatic 85	uuuuuu/upupup:buu00750075uu007500750075	I
    //   62: irem
    //   63: getstatic 91	uuuuuu/upupup:b0075u00750075uu007500750075	I
    //   66: if_icmpeq +182 -> 248
    //   69: getstatic 55	uuuuuu/upupup:b00750075u0075uu007500750075	I
    //   72: getstatic 89	uuuuuu/upupup:bu007500750075uu007500750075	I
    //   75: iadd
    //   76: getstatic 55	uuuuuu/upupup:b00750075u0075uu007500750075	I
    //   79: imul
    //   80: getstatic 85	uuuuuu/upupup:buu00750075uu007500750075	I
    //   83: irem
    //   84: getstatic 91	uuuuuu/upupup:b0075u00750075uu007500750075	I
    //   87: if_icmpeq +116 -> 203
    //   90: getstatic 55	uuuuuu/upupup:b00750075u0075uu007500750075	I
    //   93: getstatic 89	uuuuuu/upupup:bu007500750075uu007500750075	I
    //   96: iadd
    //   97: getstatic 55	uuuuuu/upupup:b00750075u0075uu007500750075	I
    //   100: imul
    //   101: getstatic 85	uuuuuu/upupup:buu00750075uu007500750075	I
    //   104: irem
    //   105: getstatic 91	uuuuuu/upupup:b0075u00750075uu007500750075	I
    //   108: if_icmpeq +85 -> 193
    //   111: ldc 2
    //   113: ldc_w 262
    //   116: bipush 76
    //   118: sipush 170
    //   121: iconst_3
    //   122: invokestatic 105	xxxxxx/uxxxxx:bbbb0062b0062b0062b0062	(Ljava/lang/String;CCC)Ljava/lang/String;
    //   125: iconst_0
    //   126: anewarray 65	java/lang/Class
    //   129: invokevirtual 69	java/lang/Class:getMethod	(Ljava/lang/String;[Ljava/lang/Class;)Ljava/lang/reflect/Method;
    //   132: astore_3
    //   133: aload_3
    //   134: aconst_null
    //   135: iconst_0
    //   136: anewarray 71	java/lang/Object
    //   139: invokevirtual 77	java/lang/reflect/Method:invoke	(Ljava/lang/Object;[Ljava/lang/Object;)Ljava/lang/Object;
    //   142: astore_3
    //   143: aload_3
    //   144: checkcast 79	java/lang/Integer
    //   147: invokevirtual 83	java/lang/Integer:intValue	()I
    //   150: putstatic 55	uuuuuu/upupup:b00750075u0075uu007500750075	I
    //   153: ldc 2
    //   155: ldc_w 289
    //   158: sipush 142
    //   161: iconst_3
    //   162: invokestatic 63	xxxxxx/uxxxxx:bb00620062bb0062b0062b0062	(Ljava/lang/String;CC)Ljava/lang/String;
    //   165: iconst_0
    //   166: anewarray 65	java/lang/Class
    //   169: invokevirtual 69	java/lang/Class:getMethod	(Ljava/lang/String;[Ljava/lang/Class;)Ljava/lang/reflect/Method;
    //   172: astore_3
    //   173: aload_3
    //   174: aconst_null
    //   175: iconst_0
    //   176: anewarray 71	java/lang/Object
    //   179: invokevirtual 77	java/lang/reflect/Method:invoke	(Ljava/lang/Object;[Ljava/lang/Object;)Ljava/lang/Object;
    //   182: astore_3
    //   183: aload_3
    //   184: checkcast 79	java/lang/Integer
    //   187: invokevirtual 83	java/lang/Integer:intValue	()I
    //   190: putstatic 91	uuuuuu/upupup:b0075u00750075uu007500750075	I
    //   193: bipush 82
    //   195: putstatic 55	uuuuuu/upupup:b00750075u0075uu007500750075	I
    //   198: bipush 19
    //   200: putstatic 91	uuuuuu/upupup:b0075u00750075uu007500750075	I
    //   203: ldc 2
    //   205: ldc_w 291
    //   208: sipush 196
    //   211: iconst_0
    //   212: invokestatic 63	xxxxxx/uxxxxx:bb00620062bb0062b0062b0062	(Ljava/lang/String;CC)Ljava/lang/String;
    //   215: iconst_0
    //   216: anewarray 65	java/lang/Class
    //   219: invokevirtual 69	java/lang/Class:getMethod	(Ljava/lang/String;[Ljava/lang/Class;)Ljava/lang/reflect/Method;
    //   222: astore_3
    //   223: aload_3
    //   224: aconst_null
    //   225: iconst_0
    //   226: anewarray 71	java/lang/Object
    //   229: invokevirtual 77	java/lang/reflect/Method:invoke	(Ljava/lang/Object;[Ljava/lang/Object;)Ljava/lang/Object;
    //   232: astore_3
    //   233: aload_3
    //   234: checkcast 79	java/lang/Integer
    //   237: invokevirtual 83	java/lang/Integer:intValue	()I
    //   240: putstatic 55	uuuuuu/upupup:b00750075u0075uu007500750075	I
    //   243: bipush 34
    //   245: putstatic 91	uuuuuu/upupup:b0075u00750075uu007500750075	I
    //   248: aload_2
    //   249: ifnonnull +14 -> 263
    //   252: aload_0
    //   253: new 293	uuuuuu/fffmmm
    //   256: dup
    //   257: invokespecial 294	uuuuuu/fffmmm:<init>	()V
    //   260: putfield 285	uuuuuu/upupup:b00750075uuuu007500750075	Luuuuuu/yggggy;
    //   263: aload_0
    //   264: getfield 285	uuuuuu/upupup:b00750075uuuu007500750075	Luuuuuu/yggggy;
    //   267: astore_2
    //   268: getstatic 55	uuuuuu/upupup:b00750075u0075uu007500750075	I
    //   271: istore_1
    //   272: iload_1
    //   273: getstatic 89	uuuuuu/upupup:bu007500750075uu007500750075	I
    //   276: iload_1
    //   277: iadd
    //   278: imul
    //   279: getstatic 85	uuuuuu/upupup:buu00750075uu007500750075	I
    //   282: irem
    //   283: tableswitch	default:+17->300, 0:+61->344
    //   300: ldc 2
    //   302: ldc_w 296
    //   305: bipush 96
    //   307: iconst_2
    //   308: invokestatic 63	xxxxxx/uxxxxx:bb00620062bb0062b0062b0062	(Ljava/lang/String;CC)Ljava/lang/String;
    //   311: iconst_0
    //   312: anewarray 65	java/lang/Class
    //   315: invokevirtual 69	java/lang/Class:getMethod	(Ljava/lang/String;[Ljava/lang/Class;)Ljava/lang/reflect/Method;
    //   318: astore_3
    //   319: aload_3
    //   320: aconst_null
    //   321: iconst_0
    //   322: anewarray 71	java/lang/Object
    //   325: invokevirtual 77	java/lang/reflect/Method:invoke	(Ljava/lang/Object;[Ljava/lang/Object;)Ljava/lang/Object;
    //   328: astore_3
    //   329: aload_3
    //   330: checkcast 79	java/lang/Integer
    //   333: invokevirtual 83	java/lang/Integer:intValue	()I
    //   336: putstatic 55	uuuuuu/upupup:b00750075u0075uu007500750075	I
    //   339: bipush 71
    //   341: putstatic 91	uuuuuu/upupup:b0075u00750075uu007500750075	I
    //   344: ldc 99
    //   346: ldc_w 298
    //   349: bipush 83
    //   351: sipush 253
    //   354: iconst_2
    //   355: invokestatic 105	xxxxxx/uxxxxx:bbbb0062b0062b0062b0062	(Ljava/lang/String;CCC)Ljava/lang/String;
    //   358: iconst_3
    //   359: anewarray 65	java/lang/Class
    //   362: dup
    //   363: iconst_0
    //   364: ldc 107
    //   366: aastore
    //   367: dup
    //   368: iconst_1
    //   369: getstatic 113	java/lang/Character:TYPE	Ljava/lang/Class;
    //   372: aastore
    //   373: dup
    //   374: iconst_2
    //   375: getstatic 113	java/lang/Character:TYPE	Ljava/lang/Class;
    //   378: aastore
    //   379: invokevirtual 69	java/lang/Class:getMethod	(Ljava/lang/String;[Ljava/lang/Class;)Ljava/lang/reflect/Method;
    //   382: astore_3
    //   383: aload_3
    //   384: aconst_null
    //   385: iconst_3
    //   386: anewarray 71	java/lang/Object
    //   389: dup
    //   390: iconst_0
    //   391: ldc_w 300
    //   394: aastore
    //   395: dup
    //   396: iconst_1
    //   397: sipush 159
    //   400: invokestatic 117	java/lang/Character:valueOf	(C)Ljava/lang/Character;
    //   403: aastore
    //   404: dup
    //   405: iconst_2
    //   406: iconst_0
    //   407: invokestatic 117	java/lang/Character:valueOf	(C)Ljava/lang/Character;
    //   410: aastore
    //   411: invokevirtual 77	java/lang/reflect/Method:invoke	(Ljava/lang/Object;[Ljava/lang/Object;)Ljava/lang/Object;
    //   414: astore_3
    //   415: aload_2
    //   416: aload_0
    //   417: aload_3
    //   418: checkcast 107	java/lang/String
    //   421: getstatic 305	android/os/Build$VERSION:RELEASE	Ljava/lang/String;
    //   424: invokeinterface 311 4 0
    //   429: return
    //   430: astore_2
    //   431: aload_2
    //   432: invokevirtual 133	java/lang/reflect/InvocationTargetException:getCause	()Ljava/lang/Throwable;
    //   435: athrow
    //   436: astore_2
    //   437: aload_2
    //   438: invokevirtual 133	java/lang/reflect/InvocationTargetException:getCause	()Ljava/lang/Throwable;
    //   441: athrow
    //   442: astore_2
    //   443: aload_2
    //   444: invokevirtual 133	java/lang/reflect/InvocationTargetException:getCause	()Ljava/lang/Throwable;
    //   447: athrow
    //   448: astore_2
    //   449: aload_2
    //   450: invokevirtual 133	java/lang/reflect/InvocationTargetException:getCause	()Ljava/lang/Throwable;
    //   453: athrow
    //   454: astore_2
    //   455: aload_2
    //   456: invokevirtual 133	java/lang/reflect/InvocationTargetException:getCause	()Ljava/lang/Throwable;
    //   459: athrow
    //   460: astore_2
    //   461: aload_2
    //   462: invokevirtual 133	java/lang/reflect/InvocationTargetException:getCause	()Ljava/lang/Throwable;
    //   465: athrow
    // Local variable table:
    //   start	length	slot	name	signature
    //   0	466	0	this	upupup
    //   15	264	1	i	int
    //   11	405	2	localYggggy	yggggy
    //   430	2	2	localInvocationTargetException1	java.lang.reflect.InvocationTargetException
    //   436	2	2	localInvocationTargetException2	java.lang.reflect.InvocationTargetException
    //   442	2	2	localInvocationTargetException3	java.lang.reflect.InvocationTargetException
    //   448	2	2	localInvocationTargetException4	java.lang.reflect.InvocationTargetException
    //   454	2	2	localInvocationTargetException5	java.lang.reflect.InvocationTargetException
    //   460	2	2	localInvocationTargetException6	java.lang.reflect.InvocationTargetException
    //   35	383	3	localObject	Object
    // Exception table:
    //   from	to	target	type
    //   383	415	430	java/lang/reflect/InvocationTargetException
    //   36	46	436	java/lang/reflect/InvocationTargetException
    //   223	233	442	java/lang/reflect/InvocationTargetException
    //   319	329	448	java/lang/reflect/InvocationTargetException
    //   133	143	454	java/lang/reflect/InvocationTargetException
    //   173	183	460	java/lang/reflect/InvocationTargetException
  }
  
  /* Error */
  public void b006100610061a00610061a0061aa()
  {
    // Byte code:
    //   0: getstatic 55	uuuuuu/upupup:b00750075u0075uu007500750075	I
    //   3: getstatic 89	uuuuuu/upupup:bu007500750075uu007500750075	I
    //   6: iadd
    //   7: getstatic 55	uuuuuu/upupup:b00750075u0075uu007500750075	I
    //   10: imul
    //   11: getstatic 85	uuuuuu/upupup:buu00750075uu007500750075	I
    //   14: irem
    //   15: getstatic 91	uuuuuu/upupup:b0075u00750075uu007500750075	I
    //   18: if_icmpeq +12 -> 30
    //   21: bipush 72
    //   23: putstatic 55	uuuuuu/upupup:b00750075u0075uu007500750075	I
    //   26: iconst_1
    //   27: putstatic 91	uuuuuu/upupup:b0075u00750075uu007500750075	I
    //   30: aload_0
    //   31: getfield 316	uuuuuu/upupup:buuu0075uu007500750075	Lcom/db/pwcc/dbmobile/secure/preferences/SharedPreferencesHelper;
    //   34: astore 4
    //   36: ldc_w 318
    //   39: ldc_w 320
    //   42: sipush 190
    //   45: iconst_2
    //   46: invokestatic 63	xxxxxx/uxxxxx:bb00620062bb0062b0062b0062	(Ljava/lang/String;CC)Ljava/lang/String;
    //   49: iconst_0
    //   50: anewarray 65	java/lang/Class
    //   53: invokevirtual 69	java/lang/Class:getMethod	(Ljava/lang/String;[Ljava/lang/Class;)Ljava/lang/reflect/Method;
    //   56: astore 5
    //   58: aload 5
    //   60: aload 4
    //   62: iconst_0
    //   63: anewarray 71	java/lang/Object
    //   66: invokevirtual 77	java/lang/reflect/Method:invoke	(Ljava/lang/Object;[Ljava/lang/Object;)Ljava/lang/Object;
    //   69: astore 4
    //   71: aload 4
    //   73: checkcast 107	java/lang/String
    //   76: invokestatic 326	android/text/TextUtils:isEmpty	(Ljava/lang/CharSequence;)Z
    //   79: ifeq +292 -> 371
    //   82: invokestatic 332	java/util/UUID:randomUUID	()Ljava/util/UUID;
    //   85: invokestatic 335	java/lang/String:valueOf	(Ljava/lang/Object;)Ljava/lang/String;
    //   88: astore 4
    //   90: new 337	java/lang/NullPointerException
    //   93: dup
    //   94: invokespecial 338	java/lang/NullPointerException:<init>	()V
    //   97: athrow
    //   98: astore 5
    //   100: ldc 2
    //   102: ldc_w 340
    //   105: sipush 246
    //   108: sipush 183
    //   111: iconst_3
    //   112: invokestatic 105	xxxxxx/uxxxxx:bbbb0062b0062b0062b0062	(Ljava/lang/String;CCC)Ljava/lang/String;
    //   115: iconst_0
    //   116: anewarray 65	java/lang/Class
    //   119: invokevirtual 69	java/lang/Class:getMethod	(Ljava/lang/String;[Ljava/lang/Class;)Ljava/lang/reflect/Method;
    //   122: astore 5
    //   124: aload 5
    //   126: aconst_null
    //   127: iconst_0
    //   128: anewarray 71	java/lang/Object
    //   131: invokevirtual 77	java/lang/reflect/Method:invoke	(Ljava/lang/Object;[Ljava/lang/Object;)Ljava/lang/Object;
    //   134: astore 5
    //   136: aload 5
    //   138: checkcast 79	java/lang/Integer
    //   141: invokevirtual 83	java/lang/Integer:intValue	()I
    //   144: putstatic 55	uuuuuu/upupup:b00750075u0075uu007500750075	I
    //   147: aload_0
    //   148: getfield 316	uuuuuu/upupup:buuu0075uu007500750075	Lcom/db/pwcc/dbmobile/secure/preferences/SharedPreferencesHelper;
    //   151: astore 6
    //   153: ldc_w 318
    //   156: ldc_w 342
    //   159: bipush 85
    //   161: iconst_1
    //   162: invokestatic 63	xxxxxx/uxxxxx:bb00620062bb0062b0062b0062	(Ljava/lang/String;CC)Ljava/lang/String;
    //   165: iconst_1
    //   166: anewarray 65	java/lang/Class
    //   169: dup
    //   170: iconst_0
    //   171: ldc 107
    //   173: aastore
    //   174: invokevirtual 69	java/lang/Class:getMethod	(Ljava/lang/String;[Ljava/lang/Class;)Ljava/lang/reflect/Method;
    //   177: astore 5
    //   179: aload 5
    //   181: aload 6
    //   183: iconst_1
    //   184: anewarray 71	java/lang/Object
    //   187: dup
    //   188: iconst_0
    //   189: aload 4
    //   191: aastore
    //   192: invokevirtual 77	java/lang/reflect/Method:invoke	(Ljava/lang/Object;[Ljava/lang/Object;)Ljava/lang/Object;
    //   195: pop
    //   196: getstatic 55	uuuuuu/upupup:b00750075u0075uu007500750075	I
    //   199: istore_1
    //   200: iload_1
    //   201: getstatic 89	uuuuuu/upupup:bu007500750075uu007500750075	I
    //   204: iload_1
    //   205: iadd
    //   206: imul
    //   207: getstatic 85	uuuuuu/upupup:buu00750075uu007500750075	I
    //   210: irem
    //   211: tableswitch	default:+17->228, 0:+65->276
    //   228: bipush 47
    //   230: putstatic 55	uuuuuu/upupup:b00750075u0075uu007500750075	I
    //   233: ldc 2
    //   235: ldc_w 344
    //   238: bipush 8
    //   240: iconst_2
    //   241: invokestatic 63	xxxxxx/uxxxxx:bb00620062bb0062b0062b0062	(Ljava/lang/String;CC)Ljava/lang/String;
    //   244: iconst_0
    //   245: anewarray 65	java/lang/Class
    //   248: invokevirtual 69	java/lang/Class:getMethod	(Ljava/lang/String;[Ljava/lang/Class;)Ljava/lang/reflect/Method;
    //   251: astore 5
    //   253: aload 5
    //   255: aconst_null
    //   256: iconst_0
    //   257: anewarray 71	java/lang/Object
    //   260: invokevirtual 77	java/lang/reflect/Method:invoke	(Ljava/lang/Object;[Ljava/lang/Object;)Ljava/lang/Object;
    //   263: astore 5
    //   265: aload 5
    //   267: checkcast 79	java/lang/Integer
    //   270: invokevirtual 83	java/lang/Integer:intValue	()I
    //   273: putstatic 91	uuuuuu/upupup:b0075u00750075uu007500750075	I
    //   276: ldc 99
    //   278: ldc_w 346
    //   281: sipush 147
    //   284: iconst_2
    //   285: invokestatic 63	xxxxxx/uxxxxx:bb00620062bb0062b0062b0062	(Ljava/lang/String;CC)Ljava/lang/String;
    //   288: iconst_4
    //   289: anewarray 65	java/lang/Class
    //   292: dup
    //   293: iconst_0
    //   294: ldc 107
    //   296: aastore
    //   297: dup
    //   298: iconst_1
    //   299: getstatic 113	java/lang/Character:TYPE	Ljava/lang/Class;
    //   302: aastore
    //   303: dup
    //   304: iconst_2
    //   305: getstatic 113	java/lang/Character:TYPE	Ljava/lang/Class;
    //   308: aastore
    //   309: dup
    //   310: iconst_3
    //   311: getstatic 113	java/lang/Character:TYPE	Ljava/lang/Class;
    //   314: aastore
    //   315: invokevirtual 69	java/lang/Class:getMethod	(Ljava/lang/String;[Ljava/lang/Class;)Ljava/lang/reflect/Method;
    //   318: astore 5
    //   320: aload 5
    //   322: aconst_null
    //   323: iconst_4
    //   324: anewarray 71	java/lang/Object
    //   327: dup
    //   328: iconst_0
    //   329: ldc_w 348
    //   332: aastore
    //   333: dup
    //   334: iconst_1
    //   335: bipush 77
    //   337: invokestatic 117	java/lang/Character:valueOf	(C)Ljava/lang/Character;
    //   340: aastore
    //   341: dup
    //   342: iconst_2
    //   343: bipush 95
    //   345: invokestatic 117	java/lang/Character:valueOf	(C)Ljava/lang/Character;
    //   348: aastore
    //   349: dup
    //   350: iconst_3
    //   351: iconst_2
    //   352: invokestatic 117	java/lang/Character:valueOf	(C)Ljava/lang/Character;
    //   355: aastore
    //   356: invokevirtual 77	java/lang/reflect/Method:invoke	(Ljava/lang/Object;[Ljava/lang/Object;)Ljava/lang/Object;
    //   359: astore 5
    //   361: aload 5
    //   363: checkcast 107	java/lang/String
    //   366: aload 4
    //   368: invokestatic 354	uuuuuu/rrvvrv:b0071qq0071q0071q0071q0071	(Ljava/lang/String;Ljava/lang/String;)V
    //   371: aload_0
    //   372: getfield 196	uuuuuu/upupup:b006En006E006E006En006E006En	Luuuuuu/ggyggy;
    //   375: astore 4
    //   377: aload_0
    //   378: getfield 316	uuuuuu/upupup:buuu0075uu007500750075	Lcom/db/pwcc/dbmobile/secure/preferences/SharedPreferencesHelper;
    //   381: astore 6
    //   383: ldc_w 318
    //   386: ldc_w 356
    //   389: sipush 171
    //   392: iconst_3
    //   393: invokestatic 63	xxxxxx/uxxxxx:bb00620062bb0062b0062b0062	(Ljava/lang/String;CC)Ljava/lang/String;
    //   396: iconst_0
    //   397: anewarray 65	java/lang/Class
    //   400: invokevirtual 69	java/lang/Class:getMethod	(Ljava/lang/String;[Ljava/lang/Class;)Ljava/lang/reflect/Method;
    //   403: astore 5
    //   405: aload 5
    //   407: aload 6
    //   409: iconst_0
    //   410: anewarray 71	java/lang/Object
    //   413: invokevirtual 77	java/lang/reflect/Method:invoke	(Ljava/lang/Object;[Ljava/lang/Object;)Ljava/lang/Object;
    //   416: astore 5
    //   418: aload 4
    //   420: aload 5
    //   422: checkcast 107	java/lang/String
    //   425: invokevirtual 360	uuuuuu/ggyggy:bp0070pp0070p00700070pp	(Ljava/lang/String;)V
    //   428: ldc 2
    //   430: ldc_w 362
    //   433: sipush 171
    //   436: iconst_2
    //   437: invokestatic 63	xxxxxx/uxxxxx:bb00620062bb0062b0062b0062	(Ljava/lang/String;CC)Ljava/lang/String;
    //   440: iconst_0
    //   441: anewarray 65	java/lang/Class
    //   444: invokevirtual 69	java/lang/Class:getMethod	(Ljava/lang/String;[Ljava/lang/Class;)Ljava/lang/reflect/Method;
    //   447: astore 4
    //   449: aload 4
    //   451: aconst_null
    //   452: iconst_0
    //   453: anewarray 71	java/lang/Object
    //   456: invokevirtual 77	java/lang/reflect/Method:invoke	(Ljava/lang/Object;[Ljava/lang/Object;)Ljava/lang/Object;
    //   459: astore 4
    //   461: aload 4
    //   463: checkcast 79	java/lang/Integer
    //   466: invokevirtual 83	java/lang/Integer:intValue	()I
    //   469: istore_3
    //   470: getstatic 89	uuuuuu/upupup:bu007500750075uu007500750075	I
    //   473: istore_1
    //   474: ldc 2
    //   476: ldc_w 364
    //   479: sipush 153
    //   482: bipush 102
    //   484: iconst_2
    //   485: invokestatic 105	xxxxxx/uxxxxx:bbbb0062b0062b0062b0062	(Ljava/lang/String;CCC)Ljava/lang/String;
    //   488: iconst_0
    //   489: anewarray 65	java/lang/Class
    //   492: invokevirtual 69	java/lang/Class:getMethod	(Ljava/lang/String;[Ljava/lang/Class;)Ljava/lang/reflect/Method;
    //   495: astore 4
    //   497: aload 4
    //   499: aconst_null
    //   500: iconst_0
    //   501: anewarray 71	java/lang/Object
    //   504: invokevirtual 77	java/lang/reflect/Method:invoke	(Ljava/lang/Object;[Ljava/lang/Object;)Ljava/lang/Object;
    //   507: astore 4
    //   509: aload 4
    //   511: checkcast 79	java/lang/Integer
    //   514: invokevirtual 83	java/lang/Integer:intValue	()I
    //   517: istore_2
    //   518: ldc 2
    //   520: ldc_w 366
    //   523: sipush 244
    //   526: iconst_4
    //   527: invokestatic 63	xxxxxx/uxxxxx:bb00620062bb0062b0062b0062	(Ljava/lang/String;CC)Ljava/lang/String;
    //   530: iconst_0
    //   531: anewarray 65	java/lang/Class
    //   534: invokevirtual 69	java/lang/Class:getMethod	(Ljava/lang/String;[Ljava/lang/Class;)Ljava/lang/reflect/Method;
    //   537: astore 4
    //   539: aload 4
    //   541: aconst_null
    //   542: iconst_0
    //   543: anewarray 71	java/lang/Object
    //   546: invokevirtual 77	java/lang/reflect/Method:invoke	(Ljava/lang/Object;[Ljava/lang/Object;)Ljava/lang/Object;
    //   549: astore 4
    //   551: iload_1
    //   552: iload_3
    //   553: iadd
    //   554: iload_2
    //   555: imul
    //   556: aload 4
    //   558: checkcast 79	java/lang/Integer
    //   561: invokevirtual 83	java/lang/Integer:intValue	()I
    //   564: irem
    //   565: getstatic 91	uuuuuu/upupup:b0075u00750075uu007500750075	I
    //   568: if_icmpeq +94 -> 662
    //   571: ldc 2
    //   573: ldc_w 368
    //   576: sipush 202
    //   579: bipush 105
    //   581: iconst_1
    //   582: invokestatic 105	xxxxxx/uxxxxx:bbbb0062b0062b0062b0062	(Ljava/lang/String;CCC)Ljava/lang/String;
    //   585: iconst_0
    //   586: anewarray 65	java/lang/Class
    //   589: invokevirtual 69	java/lang/Class:getMethod	(Ljava/lang/String;[Ljava/lang/Class;)Ljava/lang/reflect/Method;
    //   592: astore 4
    //   594: aload 4
    //   596: aconst_null
    //   597: iconst_0
    //   598: anewarray 71	java/lang/Object
    //   601: invokevirtual 77	java/lang/reflect/Method:invoke	(Ljava/lang/Object;[Ljava/lang/Object;)Ljava/lang/Object;
    //   604: astore 4
    //   606: aload 4
    //   608: checkcast 79	java/lang/Integer
    //   611: invokevirtual 83	java/lang/Integer:intValue	()I
    //   614: putstatic 55	uuuuuu/upupup:b00750075u0075uu007500750075	I
    //   617: ldc 2
    //   619: ldc_w 370
    //   622: bipush 125
    //   624: bipush 124
    //   626: iconst_1
    //   627: invokestatic 105	xxxxxx/uxxxxx:bbbb0062b0062b0062b0062	(Ljava/lang/String;CCC)Ljava/lang/String;
    //   630: iconst_0
    //   631: anewarray 65	java/lang/Class
    //   634: invokevirtual 69	java/lang/Class:getMethod	(Ljava/lang/String;[Ljava/lang/Class;)Ljava/lang/reflect/Method;
    //   637: astore 4
    //   639: aload 4
    //   641: aconst_null
    //   642: iconst_0
    //   643: anewarray 71	java/lang/Object
    //   646: invokevirtual 77	java/lang/reflect/Method:invoke	(Ljava/lang/Object;[Ljava/lang/Object;)Ljava/lang/Object;
    //   649: astore 4
    //   651: aload 4
    //   653: checkcast 79	java/lang/Integer
    //   656: invokevirtual 83	java/lang/Integer:intValue	()I
    //   659: putstatic 91	uuuuuu/upupup:b0075u00750075uu007500750075	I
    //   662: return
    //   663: astore 4
    //   665: aload 4
    //   667: invokevirtual 133	java/lang/reflect/InvocationTargetException:getCause	()Ljava/lang/Throwable;
    //   670: athrow
    //   671: astore 4
    //   673: aload 4
    //   675: invokevirtual 133	java/lang/reflect/InvocationTargetException:getCause	()Ljava/lang/Throwable;
    //   678: athrow
    //   679: astore 4
    //   681: aload 4
    //   683: invokevirtual 133	java/lang/reflect/InvocationTargetException:getCause	()Ljava/lang/Throwable;
    //   686: athrow
    //   687: astore 4
    //   689: aload 4
    //   691: invokevirtual 133	java/lang/reflect/InvocationTargetException:getCause	()Ljava/lang/Throwable;
    //   694: athrow
    //   695: astore 4
    //   697: aload 4
    //   699: invokevirtual 133	java/lang/reflect/InvocationTargetException:getCause	()Ljava/lang/Throwable;
    //   702: athrow
    //   703: astore 4
    //   705: aload 4
    //   707: invokevirtual 133	java/lang/reflect/InvocationTargetException:getCause	()Ljava/lang/Throwable;
    //   710: athrow
    //   711: astore 4
    //   713: aload 4
    //   715: invokevirtual 133	java/lang/reflect/InvocationTargetException:getCause	()Ljava/lang/Throwable;
    //   718: athrow
    //   719: astore 4
    //   721: aload 4
    //   723: invokevirtual 133	java/lang/reflect/InvocationTargetException:getCause	()Ljava/lang/Throwable;
    //   726: athrow
    //   727: astore 4
    //   729: aload 4
    //   731: invokevirtual 133	java/lang/reflect/InvocationTargetException:getCause	()Ljava/lang/Throwable;
    //   734: athrow
    //   735: astore 4
    //   737: aload 4
    //   739: invokevirtual 133	java/lang/reflect/InvocationTargetException:getCause	()Ljava/lang/Throwable;
    //   742: athrow
    //   743: astore 4
    //   745: aload 4
    //   747: invokevirtual 133	java/lang/reflect/InvocationTargetException:getCause	()Ljava/lang/Throwable;
    //   750: athrow
    // Local variable table:
    //   start	length	slot	name	signature
    //   0	751	0	this	upupup
    //   199	355	1	i	int
    //   517	39	2	j	int
    //   469	85	3	k	int
    //   34	618	4	localObject1	Object
    //   663	3	4	localInvocationTargetException1	java.lang.reflect.InvocationTargetException
    //   671	3	4	localInvocationTargetException2	java.lang.reflect.InvocationTargetException
    //   679	3	4	localInvocationTargetException3	java.lang.reflect.InvocationTargetException
    //   687	3	4	localInvocationTargetException4	java.lang.reflect.InvocationTargetException
    //   695	3	4	localInvocationTargetException5	java.lang.reflect.InvocationTargetException
    //   703	3	4	localInvocationTargetException6	java.lang.reflect.InvocationTargetException
    //   711	3	4	localInvocationTargetException7	java.lang.reflect.InvocationTargetException
    //   719	3	4	localInvocationTargetException8	java.lang.reflect.InvocationTargetException
    //   727	3	4	localInvocationTargetException9	java.lang.reflect.InvocationTargetException
    //   735	3	4	localInvocationTargetException10	java.lang.reflect.InvocationTargetException
    //   743	3	4	localInvocationTargetException11	java.lang.reflect.InvocationTargetException
    //   56	3	5	localMethod	java.lang.reflect.Method
    //   98	1	5	localException	Exception
    //   122	299	5	localObject2	Object
    //   151	257	6	localSharedPreferencesHelper	SharedPreferencesHelper
    // Exception table:
    //   from	to	target	type
    //   90	98	98	java/lang/Exception
    //   58	71	663	java/lang/reflect/InvocationTargetException
    //   124	136	671	java/lang/reflect/InvocationTargetException
    //   639	651	679	java/lang/reflect/InvocationTargetException
    //   594	606	687	java/lang/reflect/InvocationTargetException
    //   179	196	695	java/lang/reflect/InvocationTargetException
    //   320	361	703	java/lang/reflect/InvocationTargetException
    //   449	461	711	java/lang/reflect/InvocationTargetException
    //   497	509	719	java/lang/reflect/InvocationTargetException
    //   539	551	727	java/lang/reflect/InvocationTargetException
    //   405	418	735	java/lang/reflect/InvocationTargetException
    //   253	265	743	java/lang/reflect/InvocationTargetException
  }
  
  /* Error */
  public void b00610061aa00610061a0061aa(com.db.pwcc.dbmobile.model.support.ClientSupport paramClientSupport)
  {
    // Byte code:
    //   0: aload_1
    //   1: invokevirtual 378	com/db/pwcc/dbmobile/model/support/ClientSupport:getFeatures	()Ljava/util/List;
    //   4: invokeinterface 384 1 0
    //   9: astore_1
    //   10: getstatic 55	uuuuuu/upupup:b00750075u0075uu007500750075	I
    //   13: istore_2
    //   14: ldc 2
    //   16: ldc_w 386
    //   19: sipush 249
    //   22: bipush 61
    //   24: iconst_2
    //   25: invokestatic 105	xxxxxx/uxxxxx:bbbb0062b0062b0062b0062	(Ljava/lang/String;CCC)Ljava/lang/String;
    //   28: iconst_0
    //   29: anewarray 65	java/lang/Class
    //   32: invokevirtual 69	java/lang/Class:getMethod	(Ljava/lang/String;[Ljava/lang/Class;)Ljava/lang/reflect/Method;
    //   35: astore 6
    //   37: aload 6
    //   39: aconst_null
    //   40: iconst_0
    //   41: anewarray 71	java/lang/Object
    //   44: invokevirtual 77	java/lang/reflect/Method:invoke	(Ljava/lang/Object;[Ljava/lang/Object;)Ljava/lang/Object;
    //   47: astore 6
    //   49: aload 6
    //   51: checkcast 79	java/lang/Integer
    //   54: invokevirtual 83	java/lang/Integer:intValue	()I
    //   57: istore_3
    //   58: getstatic 85	uuuuuu/upupup:buu00750075uu007500750075	I
    //   61: istore 4
    //   63: getstatic 55	uuuuuu/upupup:b00750075u0075uu007500750075	I
    //   66: getstatic 89	uuuuuu/upupup:bu007500750075uu007500750075	I
    //   69: iadd
    //   70: getstatic 55	uuuuuu/upupup:b00750075u0075uu007500750075	I
    //   73: imul
    //   74: getstatic 85	uuuuuu/upupup:buu00750075uu007500750075	I
    //   77: irem
    //   78: getstatic 91	uuuuuu/upupup:b0075u00750075uu007500750075	I
    //   81: if_icmpeq +176 -> 257
    //   84: ldc 2
    //   86: ldc_w 388
    //   89: sipush 243
    //   92: iconst_2
    //   93: invokestatic 63	xxxxxx/uxxxxx:bb00620062bb0062b0062b0062	(Ljava/lang/String;CC)Ljava/lang/String;
    //   96: iconst_0
    //   97: anewarray 65	java/lang/Class
    //   100: invokevirtual 69	java/lang/Class:getMethod	(Ljava/lang/String;[Ljava/lang/Class;)Ljava/lang/reflect/Method;
    //   103: astore 6
    //   105: aload 6
    //   107: aconst_null
    //   108: iconst_0
    //   109: anewarray 71	java/lang/Object
    //   112: invokevirtual 77	java/lang/reflect/Method:invoke	(Ljava/lang/Object;[Ljava/lang/Object;)Ljava/lang/Object;
    //   115: astore 6
    //   117: aload 6
    //   119: checkcast 79	java/lang/Integer
    //   122: invokevirtual 83	java/lang/Integer:intValue	()I
    //   125: istore 5
    //   127: iload 5
    //   129: getstatic 89	uuuuuu/upupup:bu007500750075uu007500750075	I
    //   132: iload 5
    //   134: iadd
    //   135: imul
    //   136: getstatic 85	uuuuuu/upupup:buu00750075uu007500750075	I
    //   139: irem
    //   140: tableswitch	default:+20->160, 0:+69->209
    //   160: ldc 2
    //   162: ldc_w 390
    //   165: sipush 213
    //   168: iconst_3
    //   169: invokestatic 63	xxxxxx/uxxxxx:bb00620062bb0062b0062b0062	(Ljava/lang/String;CC)Ljava/lang/String;
    //   172: iconst_0
    //   173: anewarray 65	java/lang/Class
    //   176: invokevirtual 69	java/lang/Class:getMethod	(Ljava/lang/String;[Ljava/lang/Class;)Ljava/lang/reflect/Method;
    //   179: astore 6
    //   181: aload 6
    //   183: aconst_null
    //   184: iconst_0
    //   185: anewarray 71	java/lang/Object
    //   188: invokevirtual 77	java/lang/reflect/Method:invoke	(Ljava/lang/Object;[Ljava/lang/Object;)Ljava/lang/Object;
    //   191: astore 6
    //   193: aload 6
    //   195: checkcast 79	java/lang/Integer
    //   198: invokevirtual 83	java/lang/Integer:intValue	()I
    //   201: putstatic 55	uuuuuu/upupup:b00750075u0075uu007500750075	I
    //   204: bipush 25
    //   206: putstatic 91	uuuuuu/upupup:b0075u00750075uu007500750075	I
    //   209: bipush 95
    //   211: putstatic 55	uuuuuu/upupup:b00750075u0075uu007500750075	I
    //   214: ldc 2
    //   216: ldc 93
    //   218: sipush 180
    //   221: iconst_0
    //   222: invokestatic 63	xxxxxx/uxxxxx:bb00620062bb0062b0062b0062	(Ljava/lang/String;CC)Ljava/lang/String;
    //   225: iconst_0
    //   226: anewarray 65	java/lang/Class
    //   229: invokevirtual 69	java/lang/Class:getMethod	(Ljava/lang/String;[Ljava/lang/Class;)Ljava/lang/reflect/Method;
    //   232: astore 6
    //   234: aload 6
    //   236: aconst_null
    //   237: iconst_0
    //   238: anewarray 71	java/lang/Object
    //   241: invokevirtual 77	java/lang/reflect/Method:invoke	(Ljava/lang/Object;[Ljava/lang/Object;)Ljava/lang/Object;
    //   244: astore 6
    //   246: aload 6
    //   248: checkcast 79	java/lang/Integer
    //   251: invokevirtual 83	java/lang/Integer:intValue	()I
    //   254: putstatic 91	uuuuuu/upupup:b0075u00750075uu007500750075	I
    //   257: iload_2
    //   258: iload_3
    //   259: iload_2
    //   260: iadd
    //   261: imul
    //   262: iload 4
    //   264: irem
    //   265: tableswitch	default:+19->284, 0:+68->333
    //   284: ldc 2
    //   286: ldc_w 296
    //   289: sipush 159
    //   292: iconst_0
    //   293: invokestatic 63	xxxxxx/uxxxxx:bb00620062bb0062b0062b0062	(Ljava/lang/String;CC)Ljava/lang/String;
    //   296: iconst_0
    //   297: anewarray 65	java/lang/Class
    //   300: invokevirtual 69	java/lang/Class:getMethod	(Ljava/lang/String;[Ljava/lang/Class;)Ljava/lang/reflect/Method;
    //   303: astore 6
    //   305: aload 6
    //   307: aconst_null
    //   308: iconst_0
    //   309: anewarray 71	java/lang/Object
    //   312: invokevirtual 77	java/lang/reflect/Method:invoke	(Ljava/lang/Object;[Ljava/lang/Object;)Ljava/lang/Object;
    //   315: astore 6
    //   317: aload 6
    //   319: checkcast 79	java/lang/Integer
    //   322: invokevirtual 83	java/lang/Integer:intValue	()I
    //   325: putstatic 55	uuuuuu/upupup:b00750075u0075uu007500750075	I
    //   328: bipush 53
    //   330: putstatic 91	uuuuuu/upupup:b0075u00750075uu007500750075	I
    //   333: aload_1
    //   334: invokeinterface 395 1 0
    //   339: ifeq +128 -> 467
    //   342: getstatic 55	uuuuuu/upupup:b00750075u0075uu007500750075	I
    //   345: istore_2
    //   346: iload_2
    //   347: getstatic 89	uuuuuu/upupup:bu007500750075uu007500750075	I
    //   350: iload_2
    //   351: iadd
    //   352: imul
    //   353: getstatic 85	uuuuuu/upupup:buu00750075uu007500750075	I
    //   356: irem
    //   357: tableswitch	default:+19->376, 0:+69->426
    //   376: bipush 28
    //   378: putstatic 55	uuuuuu/upupup:b00750075u0075uu007500750075	I
    //   381: ldc 2
    //   383: ldc_w 397
    //   386: bipush 77
    //   388: bipush 95
    //   390: iconst_2
    //   391: invokestatic 105	xxxxxx/uxxxxx:bbbb0062b0062b0062b0062	(Ljava/lang/String;CCC)Ljava/lang/String;
    //   394: iconst_0
    //   395: anewarray 65	java/lang/Class
    //   398: invokevirtual 69	java/lang/Class:getMethod	(Ljava/lang/String;[Ljava/lang/Class;)Ljava/lang/reflect/Method;
    //   401: astore 6
    //   403: aload 6
    //   405: aconst_null
    //   406: iconst_0
    //   407: anewarray 71	java/lang/Object
    //   410: invokevirtual 77	java/lang/reflect/Method:invoke	(Ljava/lang/Object;[Ljava/lang/Object;)Ljava/lang/Object;
    //   413: astore 6
    //   415: aload 6
    //   417: checkcast 79	java/lang/Integer
    //   420: invokevirtual 83	java/lang/Integer:intValue	()I
    //   423: putstatic 91	uuuuuu/upupup:b0075u00750075uu007500750075	I
    //   426: aload_1
    //   427: invokeinterface 401 1 0
    //   432: checkcast 403	com/db/pwcc/dbmobile/model/support/ClientSupport$FeatureSupport
    //   435: astore 6
    //   437: aload_0
    //   438: getfield 405	uuuuuu/upupup:b0075u0075uuu007500750075	Luuuuuu/sssttt;
    //   441: aload 6
    //   443: invokevirtual 411	uuuuuu/sssttt:b006B006B006Bkk006B006B006Bkk	(Lcom/db/pwcc/dbmobile/model/support/ClientSupport$FeatureSupport;)V
    //   446: goto -113 -> 333
    //   449: astore_1
    //   450: aload_1
    //   451: invokevirtual 133	java/lang/reflect/InvocationTargetException:getCause	()Ljava/lang/Throwable;
    //   454: athrow
    //   455: astore_1
    //   456: aload_1
    //   457: invokevirtual 133	java/lang/reflect/InvocationTargetException:getCause	()Ljava/lang/Throwable;
    //   460: athrow
    //   461: astore_1
    //   462: aload_1
    //   463: invokevirtual 133	java/lang/reflect/InvocationTargetException:getCause	()Ljava/lang/Throwable;
    //   466: athrow
    //   467: ldc 2
    //   469: ldc_w 413
    //   472: iconst_3
    //   473: iconst_1
    //   474: invokestatic 63	xxxxxx/uxxxxx:bb00620062bb0062b0062b0062	(Ljava/lang/String;CC)Ljava/lang/String;
    //   477: iconst_0
    //   478: anewarray 65	java/lang/Class
    //   481: invokevirtual 416	java/lang/Class:getDeclaredMethod	(Ljava/lang/String;[Ljava/lang/Class;)Ljava/lang/reflect/Method;
    //   484: astore_1
    //   485: aload_1
    //   486: aload_0
    //   487: iconst_0
    //   488: anewarray 71	java/lang/Object
    //   491: invokevirtual 77	java/lang/reflect/Method:invoke	(Ljava/lang/Object;[Ljava/lang/Object;)Ljava/lang/Object;
    //   494: pop
    //   495: return
    //   496: astore_1
    //   497: aload_1
    //   498: invokevirtual 133	java/lang/reflect/InvocationTargetException:getCause	()Ljava/lang/Throwable;
    //   501: athrow
    //   502: astore_1
    //   503: aload_1
    //   504: invokevirtual 133	java/lang/reflect/InvocationTargetException:getCause	()Ljava/lang/Throwable;
    //   507: athrow
    //   508: astore_1
    //   509: aload_1
    //   510: invokevirtual 133	java/lang/reflect/InvocationTargetException:getCause	()Ljava/lang/Throwable;
    //   513: athrow
    //   514: astore_1
    //   515: aload_1
    //   516: invokevirtual 133	java/lang/reflect/InvocationTargetException:getCause	()Ljava/lang/Throwable;
    //   519: athrow
    // Local variable table:
    //   start	length	slot	name	signature
    //   0	520	0	this	upupup
    //   0	520	1	paramClientSupport	com.db.pwcc.dbmobile.model.support.ClientSupport
    //   13	340	2	i	int
    //   57	204	3	j	int
    //   61	204	4	k	int
    //   125	11	5	m	int
    //   35	407	6	localObject	Object
    // Exception table:
    //   from	to	target	type
    //   305	317	449	java/lang/reflect/InvocationTargetException
    //   234	246	455	java/lang/reflect/InvocationTargetException
    //   105	117	461	java/lang/reflect/InvocationTargetException
    //   485	495	496	java/lang/reflect/InvocationTargetException
    //   37	49	502	java/lang/reflect/InvocationTargetException
    //   403	415	508	java/lang/reflect/InvocationTargetException
    //   181	193	514	java/lang/reflect/InvocationTargetException
  }
  
  /* Error */
  public void b0061a006100610061aa0061aa()
  {
    // Byte code:
    //   0: getstatic 55	uuuuuu/upupup:b00750075u0075uu007500750075	I
    //   3: istore_1
    //   4: iload_1
    //   5: getstatic 89	uuuuuu/upupup:bu007500750075uu007500750075	I
    //   8: iload_1
    //   9: iadd
    //   10: imul
    //   11: getstatic 85	uuuuuu/upupup:buu00750075uu007500750075	I
    //   14: irem
    //   15: tableswitch	default:+17->32, 0:+64->79
    //   32: ldc 2
    //   34: ldc -69
    //   36: bipush 65
    //   38: iconst_2
    //   39: invokestatic 63	xxxxxx/uxxxxx:bb00620062bb0062b0062b0062	(Ljava/lang/String;CC)Ljava/lang/String;
    //   42: iconst_0
    //   43: anewarray 65	java/lang/Class
    //   46: invokevirtual 69	java/lang/Class:getMethod	(Ljava/lang/String;[Ljava/lang/Class;)Ljava/lang/reflect/Method;
    //   49: astore 4
    //   51: aload 4
    //   53: aconst_null
    //   54: iconst_0
    //   55: anewarray 71	java/lang/Object
    //   58: invokevirtual 77	java/lang/reflect/Method:invoke	(Ljava/lang/Object;[Ljava/lang/Object;)Ljava/lang/Object;
    //   61: astore 4
    //   63: aload 4
    //   65: checkcast 79	java/lang/Integer
    //   68: invokevirtual 83	java/lang/Integer:intValue	()I
    //   71: putstatic 55	uuuuuu/upupup:b00750075u0075uu007500750075	I
    //   74: bipush 66
    //   76: putstatic 91	uuuuuu/upupup:b0075u00750075uu007500750075	I
    //   79: aload_0
    //   80: getfield 405	uuuuuu/upupup:b0075u0075uuu007500750075	Luuuuuu/sssttt;
    //   83: getstatic 423	com/db/pwcc/dbmobile/foundation/features/Feature:TREATMENTS	Lcom/db/pwcc/dbmobile/foundation/features/Feature;
    //   86: invokevirtual 427	uuuuuu/sssttt:bk006Bkkk006B006B006Bkk	(Lcom/db/pwcc/dbmobile/foundation/features/Feature;)Luuuuuu/sststt;
    //   89: getstatic 433	uuuuuu/sststt:b006En006En006Enn006En	Luuuuuu/sststt;
    //   92: if_acmpne +215 -> 307
    //   95: aload_0
    //   96: getfield 277	uuuuuu/upupup:bu0075u0075uu007500750075	Luuuuuu/gaaaga;
    //   99: invokevirtual 436	uuuuuu/gaaaga:bww00770077www0077ww	()Z
    //   102: ifeq +205 -> 307
    //   105: getstatic 55	uuuuuu/upupup:b00750075u0075uu007500750075	I
    //   108: istore_1
    //   109: getstatic 89	uuuuuu/upupup:bu007500750075uu007500750075	I
    //   112: istore_2
    //   113: getstatic 55	uuuuuu/upupup:b00750075u0075uu007500750075	I
    //   116: istore_3
    //   117: iload_3
    //   118: getstatic 89	uuuuuu/upupup:bu007500750075uu007500750075	I
    //   121: iload_3
    //   122: iadd
    //   123: imul
    //   124: getstatic 85	uuuuuu/upupup:buu00750075uu007500750075	I
    //   127: irem
    //   128: tableswitch	default:+20->148, 0:+72->200
    //   148: bipush 61
    //   150: putstatic 55	uuuuuu/upupup:b00750075u0075uu007500750075	I
    //   153: ldc 2
    //   155: ldc_w 438
    //   158: sipush 243
    //   161: sipush 171
    //   164: iconst_1
    //   165: invokestatic 105	xxxxxx/uxxxxx:bbbb0062b0062b0062b0062	(Ljava/lang/String;CCC)Ljava/lang/String;
    //   168: iconst_0
    //   169: anewarray 65	java/lang/Class
    //   172: invokevirtual 69	java/lang/Class:getMethod	(Ljava/lang/String;[Ljava/lang/Class;)Ljava/lang/reflect/Method;
    //   175: astore 4
    //   177: aload 4
    //   179: aconst_null
    //   180: iconst_0
    //   181: anewarray 71	java/lang/Object
    //   184: invokevirtual 77	java/lang/reflect/Method:invoke	(Ljava/lang/Object;[Ljava/lang/Object;)Ljava/lang/Object;
    //   187: astore 4
    //   189: aload 4
    //   191: checkcast 79	java/lang/Integer
    //   194: invokevirtual 83	java/lang/Integer:intValue	()I
    //   197: putstatic 91	uuuuuu/upupup:b0075u00750075uu007500750075	I
    //   200: getstatic 55	uuuuuu/upupup:b00750075u0075uu007500750075	I
    //   203: iload_2
    //   204: iload_1
    //   205: iadd
    //   206: imul
    //   207: getstatic 85	uuuuuu/upupup:buu00750075uu007500750075	I
    //   210: irem
    //   211: getstatic 91	uuuuuu/upupup:b0075u00750075uu007500750075	I
    //   214: if_icmpeq +85 -> 299
    //   217: bipush 50
    //   219: putstatic 55	uuuuuu/upupup:b00750075u0075uu007500750075	I
    //   222: bipush 48
    //   224: putstatic 91	uuuuuu/upupup:b0075u00750075uu007500750075	I
    //   227: getstatic 55	uuuuuu/upupup:b00750075u0075uu007500750075	I
    //   230: getstatic 89	uuuuuu/upupup:bu007500750075uu007500750075	I
    //   233: iadd
    //   234: getstatic 55	uuuuuu/upupup:b00750075u0075uu007500750075	I
    //   237: imul
    //   238: getstatic 85	uuuuuu/upupup:buu00750075uu007500750075	I
    //   241: irem
    //   242: getstatic 91	uuuuuu/upupup:b0075u00750075uu007500750075	I
    //   245: if_icmpeq +54 -> 299
    //   248: ldc 2
    //   250: ldc_w 440
    //   253: sipush 140
    //   256: bipush 37
    //   258: iconst_3
    //   259: invokestatic 105	xxxxxx/uxxxxx:bbbb0062b0062b0062b0062	(Ljava/lang/String;CCC)Ljava/lang/String;
    //   262: iconst_0
    //   263: anewarray 65	java/lang/Class
    //   266: invokevirtual 69	java/lang/Class:getMethod	(Ljava/lang/String;[Ljava/lang/Class;)Ljava/lang/reflect/Method;
    //   269: astore 4
    //   271: aload 4
    //   273: aconst_null
    //   274: iconst_0
    //   275: anewarray 71	java/lang/Object
    //   278: invokevirtual 77	java/lang/reflect/Method:invoke	(Ljava/lang/Object;[Ljava/lang/Object;)Ljava/lang/Object;
    //   281: astore 4
    //   283: aload 4
    //   285: checkcast 79	java/lang/Integer
    //   288: invokevirtual 83	java/lang/Integer:intValue	()I
    //   291: putstatic 55	uuuuuu/upupup:b00750075u0075uu007500750075	I
    //   294: bipush 54
    //   296: putstatic 91	uuuuuu/upupup:b0075u00750075uu007500750075	I
    //   299: aload_0
    //   300: getfield 277	uuuuuu/upupup:bu0075u0075uu007500750075	Luuuuuu/gaaaga;
    //   303: aconst_null
    //   304: invokevirtual 444	uuuuuu/gaaaga:bw007700770077007700770077www	(Luuuuuu/gaaaga$aaggaa;)V
    //   307: return
    //   308: astore 4
    //   310: aload 4
    //   312: invokevirtual 133	java/lang/reflect/InvocationTargetException:getCause	()Ljava/lang/Throwable;
    //   315: athrow
    //   316: astore 4
    //   318: aload 4
    //   320: invokevirtual 133	java/lang/reflect/InvocationTargetException:getCause	()Ljava/lang/Throwable;
    //   323: athrow
    //   324: astore 4
    //   326: aload 4
    //   328: invokevirtual 133	java/lang/reflect/InvocationTargetException:getCause	()Ljava/lang/Throwable;
    //   331: athrow
    // Local variable table:
    //   start	length	slot	name	signature
    //   0	332	0	this	upupup
    //   3	203	1	i	int
    //   112	94	2	j	int
    //   116	8	3	k	int
    //   49	235	4	localObject	Object
    //   308	3	4	localInvocationTargetException1	java.lang.reflect.InvocationTargetException
    //   316	3	4	localInvocationTargetException2	java.lang.reflect.InvocationTargetException
    //   324	3	4	localInvocationTargetException3	java.lang.reflect.InvocationTargetException
    // Exception table:
    //   from	to	target	type
    //   177	189	308	java/lang/reflect/InvocationTargetException
    //   51	63	316	java/lang/reflect/InvocationTargetException
    //   271	283	324	java/lang/reflect/InvocationTargetException
  }
  
  public void b0061aa0061a0061a0061aa(pppuup.puupup paramPuupup)
  {
    throw new Runtime("d2j fail translate: java.lang.IndexOutOfBoundsException: fromIndex < 0: -1\n\tat java.util.BitSet.nextSetBit(BitSet.java:712)\n\tat com.googlecode.dex2jar.ir.ts.array.FillArrayTransformer.makeSureAllElementAreAssigned(FillArrayTransformer.java:505)\n\tat com.googlecode.dex2jar.ir.ts.array.FillArrayTransformer.transformReportChanged(FillArrayTransformer.java:123)\n\tat com.googlecode.dex2jar.ir.ts.StatedTransformer.transform(StatedTransformer.java:10)\n\tat com.googlecode.d2j.dex.Dex2jar$2.optimize(Dex2jar.java:149)\n\tat com.googlecode.d2j.dex.Dex2Asm.convertCode(Dex2Asm.java:414)\n\tat com.googlecode.d2j.dex.ExDex2Asm.convertCode(ExDex2Asm.java:42)\n\tat com.googlecode.d2j.dex.Dex2jar$2.convertCode(Dex2jar.java:128)\n\tat com.googlecode.d2j.dex.Dex2Asm.convertMethod(Dex2Asm.java:509)\n\tat com.googlecode.d2j.dex.Dex2Asm.convertClass(Dex2Asm.java:406)\n\tat com.googlecode.d2j.dex.Dex2Asm.convertDex(Dex2Asm.java:422)\n\tat com.googlecode.d2j.dex.Dex2jar.doTranslate(Dex2jar.java:172)\n\tat com.googlecode.d2j.dex.Dex2jar.to(Dex2jar.java:272)\n\tat com.googlecode.dex2jar.tools.Dex2jarCmd.doCommandLine(Dex2jarCmd.java:108)\n\tat com.googlecode.dex2jar.tools.BaseCmd.doMain(BaseCmd.java:288)\n\tat com.googlecode.dex2jar.tools.Dex2jarCmd.main(Dex2jarCmd.java:32)\n");
  }
  
  /* Error */
  public boolean b0061aaa00610061a0061aa(String paramString)
  {
    // Byte code:
    //   0: aload_0
    //   1: getfield 458	uuuuuu/upupup:buu0075uuu007500750075	Landroid/content/Context;
    //   4: astore 5
    //   6: getstatic 55	uuuuuu/upupup:b00750075u0075uu007500750075	I
    //   9: getstatic 89	uuuuuu/upupup:bu007500750075uu007500750075	I
    //   12: iadd
    //   13: getstatic 55	uuuuuu/upupup:b00750075u0075uu007500750075	I
    //   16: imul
    //   17: getstatic 85	uuuuuu/upupup:buu00750075uu007500750075	I
    //   20: irem
    //   21: getstatic 91	uuuuuu/upupup:b0075u00750075uu007500750075	I
    //   24: if_icmpeq +13 -> 37
    //   27: bipush 19
    //   29: putstatic 55	uuuuuu/upupup:b00750075u0075uu007500750075	I
    //   32: bipush 52
    //   34: putstatic 91	uuuuuu/upupup:b0075u00750075uu007500750075	I
    //   37: aload 5
    //   39: ldc_w 459
    //   42: invokevirtual 465	android/content/Context:getString	(I)Ljava/lang/String;
    //   45: astore 5
    //   47: getstatic 55	uuuuuu/upupup:b00750075u0075uu007500750075	I
    //   50: istore_2
    //   51: getstatic 89	uuuuuu/upupup:bu007500750075uu007500750075	I
    //   54: istore_3
    //   55: getstatic 55	uuuuuu/upupup:b00750075u0075uu007500750075	I
    //   58: istore 4
    //   60: ldc 2
    //   62: ldc_w 467
    //   65: bipush 97
    //   67: iconst_2
    //   68: invokestatic 63	xxxxxx/uxxxxx:bb00620062bb0062b0062b0062	(Ljava/lang/String;CC)Ljava/lang/String;
    //   71: iconst_0
    //   72: anewarray 65	java/lang/Class
    //   75: invokevirtual 69	java/lang/Class:getMethod	(Ljava/lang/String;[Ljava/lang/Class;)Ljava/lang/reflect/Method;
    //   78: astore 6
    //   80: aload 6
    //   82: aconst_null
    //   83: iconst_0
    //   84: anewarray 71	java/lang/Object
    //   87: invokevirtual 77	java/lang/reflect/Method:invoke	(Ljava/lang/Object;[Ljava/lang/Object;)Ljava/lang/Object;
    //   90: astore 6
    //   92: iload 4
    //   94: iload_2
    //   95: iload_3
    //   96: iadd
    //   97: imul
    //   98: aload 6
    //   100: checkcast 79	java/lang/Integer
    //   103: invokevirtual 83	java/lang/Integer:intValue	()I
    //   106: irem
    //   107: getstatic 91	uuuuuu/upupup:b0075u00750075uu007500750075	I
    //   110: if_icmpeq +152 -> 262
    //   113: bipush 22
    //   115: putstatic 55	uuuuuu/upupup:b00750075u0075uu007500750075	I
    //   118: bipush 96
    //   120: putstatic 91	uuuuuu/upupup:b0075u00750075uu007500750075	I
    //   123: getstatic 55	uuuuuu/upupup:b00750075u0075uu007500750075	I
    //   126: getstatic 89	uuuuuu/upupup:bu007500750075uu007500750075	I
    //   129: iadd
    //   130: getstatic 55	uuuuuu/upupup:b00750075u0075uu007500750075	I
    //   133: imul
    //   134: getstatic 85	uuuuuu/upupup:buu00750075uu007500750075	I
    //   137: irem
    //   138: getstatic 91	uuuuuu/upupup:b0075u00750075uu007500750075	I
    //   141: if_icmpeq +121 -> 262
    //   144: getstatic 55	uuuuuu/upupup:b00750075u0075uu007500750075	I
    //   147: getstatic 89	uuuuuu/upupup:bu007500750075uu007500750075	I
    //   150: iadd
    //   151: getstatic 55	uuuuuu/upupup:b00750075u0075uu007500750075	I
    //   154: imul
    //   155: getstatic 85	uuuuuu/upupup:buu00750075uu007500750075	I
    //   158: irem
    //   159: getstatic 91	uuuuuu/upupup:b0075u00750075uu007500750075	I
    //   162: if_icmpeq +13 -> 175
    //   165: bipush 9
    //   167: putstatic 55	uuuuuu/upupup:b00750075u0075uu007500750075	I
    //   170: bipush 80
    //   172: putstatic 91	uuuuuu/upupup:b0075u00750075uu007500750075	I
    //   175: ldc 2
    //   177: ldc_w 469
    //   180: bipush 86
    //   182: iconst_1
    //   183: invokestatic 63	xxxxxx/uxxxxx:bb00620062bb0062b0062b0062	(Ljava/lang/String;CC)Ljava/lang/String;
    //   186: iconst_0
    //   187: anewarray 65	java/lang/Class
    //   190: invokevirtual 69	java/lang/Class:getMethod	(Ljava/lang/String;[Ljava/lang/Class;)Ljava/lang/reflect/Method;
    //   193: astore 6
    //   195: aload 6
    //   197: aconst_null
    //   198: iconst_0
    //   199: anewarray 71	java/lang/Object
    //   202: invokevirtual 77	java/lang/reflect/Method:invoke	(Ljava/lang/Object;[Ljava/lang/Object;)Ljava/lang/Object;
    //   205: astore 6
    //   207: aload 6
    //   209: checkcast 79	java/lang/Integer
    //   212: invokevirtual 83	java/lang/Integer:intValue	()I
    //   215: putstatic 55	uuuuuu/upupup:b00750075u0075uu007500750075	I
    //   218: ldc 2
    //   220: ldc_w 471
    //   223: sipush 136
    //   226: iconst_3
    //   227: invokestatic 63	xxxxxx/uxxxxx:bb00620062bb0062b0062b0062	(Ljava/lang/String;CC)Ljava/lang/String;
    //   230: iconst_0
    //   231: anewarray 65	java/lang/Class
    //   234: invokevirtual 69	java/lang/Class:getMethod	(Ljava/lang/String;[Ljava/lang/Class;)Ljava/lang/reflect/Method;
    //   237: astore 6
    //   239: aload 6
    //   241: aconst_null
    //   242: iconst_0
    //   243: anewarray 71	java/lang/Object
    //   246: invokevirtual 77	java/lang/reflect/Method:invoke	(Ljava/lang/Object;[Ljava/lang/Object;)Ljava/lang/Object;
    //   249: astore 6
    //   251: aload 6
    //   253: checkcast 79	java/lang/Integer
    //   256: invokevirtual 83	java/lang/Integer:intValue	()I
    //   259: putstatic 91	uuuuuu/upupup:b0075u00750075uu007500750075	I
    //   262: aload 5
    //   264: aload_1
    //   265: invokevirtual 475	java/lang/String:equals	(Ljava/lang/Object;)Z
    //   268: ireturn
    //   269: astore_1
    //   270: aload_1
    //   271: invokevirtual 133	java/lang/reflect/InvocationTargetException:getCause	()Ljava/lang/Throwable;
    //   274: athrow
    //   275: astore_1
    //   276: aload_1
    //   277: invokevirtual 133	java/lang/reflect/InvocationTargetException:getCause	()Ljava/lang/Throwable;
    //   280: athrow
    //   281: astore_1
    //   282: aload_1
    //   283: invokevirtual 133	java/lang/reflect/InvocationTargetException:getCause	()Ljava/lang/Throwable;
    //   286: athrow
    // Local variable table:
    //   start	length	slot	name	signature
    //   0	287	0	this	upupup
    //   0	287	1	paramString	String
    //   50	47	2	i	int
    //   54	43	3	j	int
    //   58	40	4	k	int
    //   4	259	5	localObject1	Object
    //   78	174	6	localObject2	Object
    // Exception table:
    //   from	to	target	type
    //   80	92	269	java/lang/reflect/InvocationTargetException
    //   195	207	275	java/lang/reflect/InvocationTargetException
    //   239	251	281	java/lang/reflect/InvocationTargetException
  }
  
  /* Error */
  public void ba0061006100610061aa0061aa(Intent paramIntent)
  {
    // Byte code:
    //   0: getstatic 55	uuuuuu/upupup:b00750075u0075uu007500750075	I
    //   3: getstatic 89	uuuuuu/upupup:bu007500750075uu007500750075	I
    //   6: iadd
    //   7: getstatic 55	uuuuuu/upupup:b00750075u0075uu007500750075	I
    //   10: imul
    //   11: getstatic 85	uuuuuu/upupup:buu00750075uu007500750075	I
    //   14: irem
    //   15: getstatic 91	uuuuuu/upupup:b0075u00750075uu007500750075	I
    //   18: if_icmpeq +367 -> 385
    //   21: bipush 42
    //   23: putstatic 55	uuuuuu/upupup:b00750075u0075uu007500750075	I
    //   26: bipush 19
    //   28: putstatic 91	uuuuuu/upupup:b0075u00750075uu007500750075	I
    //   31: ldc 2
    //   33: ldc_w 364
    //   36: bipush 17
    //   38: iconst_0
    //   39: invokestatic 63	xxxxxx/uxxxxx:bb00620062bb0062b0062b0062	(Ljava/lang/String;CC)Ljava/lang/String;
    //   42: iconst_0
    //   43: anewarray 65	java/lang/Class
    //   46: invokevirtual 69	java/lang/Class:getMethod	(Ljava/lang/String;[Ljava/lang/Class;)Ljava/lang/reflect/Method;
    //   49: astore 4
    //   51: aload 4
    //   53: aconst_null
    //   54: iconst_0
    //   55: anewarray 71	java/lang/Object
    //   58: invokevirtual 77	java/lang/reflect/Method:invoke	(Ljava/lang/Object;[Ljava/lang/Object;)Ljava/lang/Object;
    //   61: astore 4
    //   63: aload 4
    //   65: checkcast 79	java/lang/Integer
    //   68: invokevirtual 83	java/lang/Integer:intValue	()I
    //   71: istore_2
    //   72: getstatic 89	uuuuuu/upupup:bu007500750075uu007500750075	I
    //   75: istore_3
    //   76: ldc 2
    //   78: ldc_w 479
    //   81: bipush 89
    //   83: iconst_5
    //   84: invokestatic 63	xxxxxx/uxxxxx:bb00620062bb0062b0062b0062	(Ljava/lang/String;CC)Ljava/lang/String;
    //   87: iconst_0
    //   88: anewarray 65	java/lang/Class
    //   91: invokevirtual 69	java/lang/Class:getMethod	(Ljava/lang/String;[Ljava/lang/Class;)Ljava/lang/reflect/Method;
    //   94: astore 4
    //   96: aload 4
    //   98: aconst_null
    //   99: iconst_0
    //   100: anewarray 71	java/lang/Object
    //   103: invokevirtual 77	java/lang/reflect/Method:invoke	(Ljava/lang/Object;[Ljava/lang/Object;)Ljava/lang/Object;
    //   106: astore 4
    //   108: aload 4
    //   110: checkcast 79	java/lang/Integer
    //   113: invokevirtual 83	java/lang/Integer:intValue	()I
    //   116: iload_3
    //   117: iload_2
    //   118: iadd
    //   119: imul
    //   120: getstatic 85	uuuuuu/upupup:buu00750075uu007500750075	I
    //   123: irem
    //   124: getstatic 91	uuuuuu/upupup:b0075u00750075uu007500750075	I
    //   127: if_icmpeq +258 -> 385
    //   130: ldc 2
    //   132: ldc_w 481
    //   135: sipush 146
    //   138: sipush 185
    //   141: iconst_0
    //   142: invokestatic 105	xxxxxx/uxxxxx:bbbb0062b0062b0062b0062	(Ljava/lang/String;CCC)Ljava/lang/String;
    //   145: iconst_0
    //   146: anewarray 65	java/lang/Class
    //   149: invokevirtual 69	java/lang/Class:getMethod	(Ljava/lang/String;[Ljava/lang/Class;)Ljava/lang/reflect/Method;
    //   152: astore 4
    //   154: aload 4
    //   156: aconst_null
    //   157: iconst_0
    //   158: anewarray 71	java/lang/Object
    //   161: invokevirtual 77	java/lang/reflect/Method:invoke	(Ljava/lang/Object;[Ljava/lang/Object;)Ljava/lang/Object;
    //   164: astore 4
    //   166: aload 4
    //   168: checkcast 79	java/lang/Integer
    //   171: invokevirtual 83	java/lang/Integer:intValue	()I
    //   174: putstatic 55	uuuuuu/upupup:b00750075u0075uu007500750075	I
    //   177: getstatic 55	uuuuuu/upupup:b00750075u0075uu007500750075	I
    //   180: istore_2
    //   181: iload_2
    //   182: getstatic 89	uuuuuu/upupup:bu007500750075uu007500750075	I
    //   185: iload_2
    //   186: iadd
    //   187: imul
    //   188: getstatic 85	uuuuuu/upupup:buu00750075uu007500750075	I
    //   191: irem
    //   192: tableswitch	default:+20->212, 0:+188->380
    //   212: getstatic 55	uuuuuu/upupup:b00750075u0075uu007500750075	I
    //   215: istore_2
    //   216: iload_2
    //   217: getstatic 89	uuuuuu/upupup:bu007500750075uu007500750075	I
    //   220: iload_2
    //   221: iadd
    //   222: imul
    //   223: getstatic 85	uuuuuu/upupup:buu00750075uu007500750075	I
    //   226: irem
    //   227: tableswitch	default:+17->244, 0:+105->332
    //   244: ldc 2
    //   246: ldc_w 483
    //   249: sipush 244
    //   252: iconst_4
    //   253: invokestatic 63	xxxxxx/uxxxxx:bb00620062bb0062b0062b0062	(Ljava/lang/String;CC)Ljava/lang/String;
    //   256: iconst_0
    //   257: anewarray 65	java/lang/Class
    //   260: invokevirtual 69	java/lang/Class:getMethod	(Ljava/lang/String;[Ljava/lang/Class;)Ljava/lang/reflect/Method;
    //   263: astore 4
    //   265: aload 4
    //   267: aconst_null
    //   268: iconst_0
    //   269: anewarray 71	java/lang/Object
    //   272: invokevirtual 77	java/lang/reflect/Method:invoke	(Ljava/lang/Object;[Ljava/lang/Object;)Ljava/lang/Object;
    //   275: astore 4
    //   277: aload 4
    //   279: checkcast 79	java/lang/Integer
    //   282: invokevirtual 83	java/lang/Integer:intValue	()I
    //   285: putstatic 55	uuuuuu/upupup:b00750075u0075uu007500750075	I
    //   288: ldc 2
    //   290: ldc -37
    //   292: bipush 19
    //   294: bipush 46
    //   296: iconst_1
    //   297: invokestatic 105	xxxxxx/uxxxxx:bbbb0062b0062b0062b0062	(Ljava/lang/String;CCC)Ljava/lang/String;
    //   300: iconst_0
    //   301: anewarray 65	java/lang/Class
    //   304: invokevirtual 69	java/lang/Class:getMethod	(Ljava/lang/String;[Ljava/lang/Class;)Ljava/lang/reflect/Method;
    //   307: astore 4
    //   309: aload 4
    //   311: aconst_null
    //   312: iconst_0
    //   313: anewarray 71	java/lang/Object
    //   316: invokevirtual 77	java/lang/reflect/Method:invoke	(Ljava/lang/Object;[Ljava/lang/Object;)Ljava/lang/Object;
    //   319: astore 4
    //   321: aload 4
    //   323: checkcast 79	java/lang/Integer
    //   326: invokevirtual 83	java/lang/Integer:intValue	()I
    //   329: putstatic 91	uuuuuu/upupup:b0075u00750075uu007500750075	I
    //   332: ldc 2
    //   334: ldc_w 485
    //   337: bipush 124
    //   339: iconst_4
    //   340: invokestatic 63	xxxxxx/uxxxxx:bb00620062bb0062b0062b0062	(Ljava/lang/String;CC)Ljava/lang/String;
    //   343: iconst_0
    //   344: anewarray 65	java/lang/Class
    //   347: invokevirtual 69	java/lang/Class:getMethod	(Ljava/lang/String;[Ljava/lang/Class;)Ljava/lang/reflect/Method;
    //   350: astore 4
    //   352: aload 4
    //   354: aconst_null
    //   355: iconst_0
    //   356: anewarray 71	java/lang/Object
    //   359: invokevirtual 77	java/lang/reflect/Method:invoke	(Ljava/lang/Object;[Ljava/lang/Object;)Ljava/lang/Object;
    //   362: astore 4
    //   364: aload 4
    //   366: checkcast 79	java/lang/Integer
    //   369: invokevirtual 83	java/lang/Integer:intValue	()I
    //   372: putstatic 55	uuuuuu/upupup:b00750075u0075uu007500750075	I
    //   375: bipush 7
    //   377: putstatic 91	uuuuuu/upupup:b0075u00750075uu007500750075	I
    //   380: bipush 93
    //   382: putstatic 91	uuuuuu/upupup:b0075u00750075uu007500750075	I
    //   385: ldc 2
    //   387: ldc_w 487
    //   390: sipush 191
    //   393: bipush 22
    //   395: iconst_3
    //   396: invokestatic 105	xxxxxx/uxxxxx:bbbb0062b0062b0062b0062	(Ljava/lang/String;CCC)Ljava/lang/String;
    //   399: iconst_1
    //   400: anewarray 65	java/lang/Class
    //   403: dup
    //   404: iconst_0
    //   405: ldc_w 489
    //   408: aastore
    //   409: invokevirtual 69	java/lang/Class:getMethod	(Ljava/lang/String;[Ljava/lang/Class;)Ljava/lang/reflect/Method;
    //   412: astore 4
    //   414: aload 4
    //   416: aload_0
    //   417: iconst_1
    //   418: anewarray 71	java/lang/Object
    //   421: dup
    //   422: iconst_0
    //   423: aload_1
    //   424: aastore
    //   425: invokevirtual 77	java/lang/reflect/Method:invoke	(Ljava/lang/Object;[Ljava/lang/Object;)Ljava/lang/Object;
    //   428: pop
    //   429: return
    //   430: astore_1
    //   431: aload_1
    //   432: invokevirtual 133	java/lang/reflect/InvocationTargetException:getCause	()Ljava/lang/Throwable;
    //   435: athrow
    //   436: astore_1
    //   437: aload_1
    //   438: invokevirtual 133	java/lang/reflect/InvocationTargetException:getCause	()Ljava/lang/Throwable;
    //   441: athrow
    //   442: astore_1
    //   443: aload_1
    //   444: invokevirtual 133	java/lang/reflect/InvocationTargetException:getCause	()Ljava/lang/Throwable;
    //   447: athrow
    //   448: astore_1
    //   449: aload_1
    //   450: invokevirtual 133	java/lang/reflect/InvocationTargetException:getCause	()Ljava/lang/Throwable;
    //   453: athrow
    //   454: astore_1
    //   455: aload_1
    //   456: invokevirtual 133	java/lang/reflect/InvocationTargetException:getCause	()Ljava/lang/Throwable;
    //   459: athrow
    //   460: astore_1
    //   461: aload_1
    //   462: invokevirtual 133	java/lang/reflect/InvocationTargetException:getCause	()Ljava/lang/Throwable;
    //   465: athrow
    //   466: astore_1
    //   467: aload_1
    //   468: invokevirtual 133	java/lang/reflect/InvocationTargetException:getCause	()Ljava/lang/Throwable;
    //   471: athrow
    // Local variable table:
    //   start	length	slot	name	signature
    //   0	472	0	this	upupup
    //   0	472	1	paramIntent	Intent
    //   71	152	2	i	int
    //   75	44	3	j	int
    //   49	366	4	localObject	Object
    // Exception table:
    //   from	to	target	type
    //   414	429	430	java/lang/reflect/InvocationTargetException
    //   51	63	436	java/lang/reflect/InvocationTargetException
    //   96	108	442	java/lang/reflect/InvocationTargetException
    //   154	166	448	java/lang/reflect/InvocationTargetException
    //   352	364	454	java/lang/reflect/InvocationTargetException
    //   265	277	460	java/lang/reflect/InvocationTargetException
    //   309	321	466	java/lang/reflect/InvocationTargetException
  }
  
  /* Error */
  public void ba006100610061a0061a0061aa()
  {
    // Byte code:
    //   0: getstatic 55	uuuuuu/upupup:b00750075u0075uu007500750075	I
    //   3: getstatic 89	uuuuuu/upupup:bu007500750075uu007500750075	I
    //   6: iadd
    //   7: getstatic 55	uuuuuu/upupup:b00750075u0075uu007500750075	I
    //   10: imul
    //   11: getstatic 85	uuuuuu/upupup:buu00750075uu007500750075	I
    //   14: irem
    //   15: getstatic 91	uuuuuu/upupup:b0075u00750075uu007500750075	I
    //   18: if_icmpeq +456 -> 474
    //   21: getstatic 55	uuuuuu/upupup:b00750075u0075uu007500750075	I
    //   24: istore_1
    //   25: getstatic 89	uuuuuu/upupup:bu007500750075uu007500750075	I
    //   28: istore_2
    //   29: ldc 2
    //   31: ldc_w 492
    //   34: bipush 116
    //   36: iconst_2
    //   37: invokestatic 63	xxxxxx/uxxxxx:bb00620062bb0062b0062b0062	(Ljava/lang/String;CC)Ljava/lang/String;
    //   40: iconst_0
    //   41: anewarray 65	java/lang/Class
    //   44: invokevirtual 69	java/lang/Class:getMethod	(Ljava/lang/String;[Ljava/lang/Class;)Ljava/lang/reflect/Method;
    //   47: astore_3
    //   48: aload_3
    //   49: aconst_null
    //   50: iconst_0
    //   51: anewarray 71	java/lang/Object
    //   54: invokevirtual 77	java/lang/reflect/Method:invoke	(Ljava/lang/Object;[Ljava/lang/Object;)Ljava/lang/Object;
    //   57: astore_3
    //   58: iload_2
    //   59: iload_1
    //   60: iadd
    //   61: iload_1
    //   62: imul
    //   63: aload_3
    //   64: checkcast 79	java/lang/Integer
    //   67: invokevirtual 83	java/lang/Integer:intValue	()I
    //   70: irem
    //   71: tableswitch	default:+17->88, 0:+98->169
    //   88: ldc 2
    //   90: ldc_w 494
    //   93: sipush 141
    //   96: iconst_0
    //   97: invokestatic 63	xxxxxx/uxxxxx:bb00620062bb0062b0062b0062	(Ljava/lang/String;CC)Ljava/lang/String;
    //   100: iconst_0
    //   101: anewarray 65	java/lang/Class
    //   104: invokevirtual 69	java/lang/Class:getMethod	(Ljava/lang/String;[Ljava/lang/Class;)Ljava/lang/reflect/Method;
    //   107: astore_3
    //   108: aload_3
    //   109: aconst_null
    //   110: iconst_0
    //   111: anewarray 71	java/lang/Object
    //   114: invokevirtual 77	java/lang/reflect/Method:invoke	(Ljava/lang/Object;[Ljava/lang/Object;)Ljava/lang/Object;
    //   117: astore_3
    //   118: aload_3
    //   119: checkcast 79	java/lang/Integer
    //   122: invokevirtual 83	java/lang/Integer:intValue	()I
    //   125: putstatic 55	uuuuuu/upupup:b00750075u0075uu007500750075	I
    //   128: ldc 2
    //   130: ldc_w 496
    //   133: bipush 93
    //   135: bipush 71
    //   137: iconst_0
    //   138: invokestatic 105	xxxxxx/uxxxxx:bbbb0062b0062b0062b0062	(Ljava/lang/String;CCC)Ljava/lang/String;
    //   141: iconst_0
    //   142: anewarray 65	java/lang/Class
    //   145: invokevirtual 69	java/lang/Class:getMethod	(Ljava/lang/String;[Ljava/lang/Class;)Ljava/lang/reflect/Method;
    //   148: astore_3
    //   149: aload_3
    //   150: aconst_null
    //   151: iconst_0
    //   152: anewarray 71	java/lang/Object
    //   155: invokevirtual 77	java/lang/reflect/Method:invoke	(Ljava/lang/Object;[Ljava/lang/Object;)Ljava/lang/Object;
    //   158: astore_3
    //   159: aload_3
    //   160: checkcast 79	java/lang/Integer
    //   163: invokevirtual 83	java/lang/Integer:intValue	()I
    //   166: putstatic 91	uuuuuu/upupup:b0075u00750075uu007500750075	I
    //   169: bipush 73
    //   171: putstatic 55	uuuuuu/upupup:b00750075u0075uu007500750075	I
    //   174: ldc 2
    //   176: ldc_w 498
    //   179: bipush 38
    //   181: iconst_5
    //   182: invokestatic 63	xxxxxx/uxxxxx:bb00620062bb0062b0062b0062	(Ljava/lang/String;CC)Ljava/lang/String;
    //   185: iconst_0
    //   186: anewarray 65	java/lang/Class
    //   189: invokevirtual 69	java/lang/Class:getMethod	(Ljava/lang/String;[Ljava/lang/Class;)Ljava/lang/reflect/Method;
    //   192: astore_3
    //   193: aload_3
    //   194: aconst_null
    //   195: iconst_0
    //   196: anewarray 71	java/lang/Object
    //   199: invokevirtual 77	java/lang/reflect/Method:invoke	(Ljava/lang/Object;[Ljava/lang/Object;)Ljava/lang/Object;
    //   202: astore_3
    //   203: aload_3
    //   204: checkcast 79	java/lang/Integer
    //   207: invokevirtual 83	java/lang/Integer:intValue	()I
    //   210: putstatic 91	uuuuuu/upupup:b0075u00750075uu007500750075	I
    //   213: getstatic 55	uuuuuu/upupup:b00750075u0075uu007500750075	I
    //   216: istore_1
    //   217: iload_1
    //   218: getstatic 89	uuuuuu/upupup:bu007500750075uu007500750075	I
    //   221: iload_1
    //   222: iadd
    //   223: imul
    //   224: getstatic 85	uuuuuu/upupup:buu00750075uu007500750075	I
    //   227: irem
    //   228: tableswitch	default:+20->248, 0:+246->474
    //   248: ldc 2
    //   250: ldc_w 500
    //   253: bipush 91
    //   255: iconst_3
    //   256: invokestatic 63	xxxxxx/uxxxxx:bb00620062bb0062b0062b0062	(Ljava/lang/String;CC)Ljava/lang/String;
    //   259: iconst_0
    //   260: anewarray 65	java/lang/Class
    //   263: invokevirtual 69	java/lang/Class:getMethod	(Ljava/lang/String;[Ljava/lang/Class;)Ljava/lang/reflect/Method;
    //   266: astore_3
    //   267: aload_3
    //   268: aconst_null
    //   269: iconst_0
    //   270: anewarray 71	java/lang/Object
    //   273: invokevirtual 77	java/lang/reflect/Method:invoke	(Ljava/lang/Object;[Ljava/lang/Object;)Ljava/lang/Object;
    //   276: astore_3
    //   277: aload_3
    //   278: checkcast 79	java/lang/Integer
    //   281: invokevirtual 83	java/lang/Integer:intValue	()I
    //   284: putstatic 55	uuuuuu/upupup:b00750075u0075uu007500750075	I
    //   287: ldc 2
    //   289: ldc_w 502
    //   292: bipush 12
    //   294: iconst_0
    //   295: invokestatic 63	xxxxxx/uxxxxx:bb00620062bb0062b0062b0062	(Ljava/lang/String;CC)Ljava/lang/String;
    //   298: iconst_0
    //   299: anewarray 65	java/lang/Class
    //   302: invokevirtual 69	java/lang/Class:getMethod	(Ljava/lang/String;[Ljava/lang/Class;)Ljava/lang/reflect/Method;
    //   305: astore_3
    //   306: aload_3
    //   307: aconst_null
    //   308: iconst_0
    //   309: anewarray 71	java/lang/Object
    //   312: invokevirtual 77	java/lang/reflect/Method:invoke	(Ljava/lang/Object;[Ljava/lang/Object;)Ljava/lang/Object;
    //   315: astore_3
    //   316: aload_3
    //   317: checkcast 79	java/lang/Integer
    //   320: invokevirtual 83	java/lang/Integer:intValue	()I
    //   323: putstatic 91	uuuuuu/upupup:b0075u00750075uu007500750075	I
    //   326: getstatic 55	uuuuuu/upupup:b00750075u0075uu007500750075	I
    //   329: istore_1
    //   330: ldc 2
    //   332: ldc_w 504
    //   335: sipush 165
    //   338: iconst_3
    //   339: invokestatic 63	xxxxxx/uxxxxx:bb00620062bb0062b0062b0062	(Ljava/lang/String;CC)Ljava/lang/String;
    //   342: iconst_0
    //   343: anewarray 65	java/lang/Class
    //   346: invokevirtual 69	java/lang/Class:getMethod	(Ljava/lang/String;[Ljava/lang/Class;)Ljava/lang/reflect/Method;
    //   349: astore_3
    //   350: aload_3
    //   351: aconst_null
    //   352: iconst_0
    //   353: anewarray 71	java/lang/Object
    //   356: invokevirtual 77	java/lang/reflect/Method:invoke	(Ljava/lang/Object;[Ljava/lang/Object;)Ljava/lang/Object;
    //   359: astore_3
    //   360: aload_3
    //   361: checkcast 79	java/lang/Integer
    //   364: invokevirtual 83	java/lang/Integer:intValue	()I
    //   367: iload_1
    //   368: iadd
    //   369: iload_1
    //   370: imul
    //   371: getstatic 85	uuuuuu/upupup:buu00750075uu007500750075	I
    //   374: irem
    //   375: tableswitch	default:+17->392, 0:+99->474
    //   392: ldc 2
    //   394: ldc_w 506
    //   397: sipush 206
    //   400: iconst_5
    //   401: invokestatic 63	xxxxxx/uxxxxx:bb00620062bb0062b0062b0062	(Ljava/lang/String;CC)Ljava/lang/String;
    //   404: iconst_0
    //   405: anewarray 65	java/lang/Class
    //   408: invokevirtual 69	java/lang/Class:getMethod	(Ljava/lang/String;[Ljava/lang/Class;)Ljava/lang/reflect/Method;
    //   411: astore_3
    //   412: aload_3
    //   413: aconst_null
    //   414: iconst_0
    //   415: anewarray 71	java/lang/Object
    //   418: invokevirtual 77	java/lang/reflect/Method:invoke	(Ljava/lang/Object;[Ljava/lang/Object;)Ljava/lang/Object;
    //   421: astore_3
    //   422: aload_3
    //   423: checkcast 79	java/lang/Integer
    //   426: invokevirtual 83	java/lang/Integer:intValue	()I
    //   429: putstatic 55	uuuuuu/upupup:b00750075u0075uu007500750075	I
    //   432: ldc 2
    //   434: ldc_w 508
    //   437: sipush 189
    //   440: bipush 64
    //   442: iconst_2
    //   443: invokestatic 105	xxxxxx/uxxxxx:bbbb0062b0062b0062b0062	(Ljava/lang/String;CCC)Ljava/lang/String;
    //   446: iconst_0
    //   447: anewarray 65	java/lang/Class
    //   450: invokevirtual 69	java/lang/Class:getMethod	(Ljava/lang/String;[Ljava/lang/Class;)Ljava/lang/reflect/Method;
    //   453: astore_3
    //   454: aload_3
    //   455: aconst_null
    //   456: iconst_0
    //   457: anewarray 71	java/lang/Object
    //   460: invokevirtual 77	java/lang/reflect/Method:invoke	(Ljava/lang/Object;[Ljava/lang/Object;)Ljava/lang/Object;
    //   463: astore_3
    //   464: aload_3
    //   465: checkcast 79	java/lang/Integer
    //   468: invokevirtual 83	java/lang/Integer:intValue	()I
    //   471: putstatic 91	uuuuuu/upupup:b0075u00750075uu007500750075	I
    //   474: aload_0
    //   475: getfield 168	uuuuuu/upupup:b007500750075uuu007500750075	Luuuuuu/upupup$ppupup;
    //   478: invokevirtual 511	uuuuuu/upupup$ppupup:b00610061aaa0061a0061aa	()V
    //   481: aload_0
    //   482: getfield 166	uuuuuu/upupup:bu00750075uuu007500750075	Landroid/os/Handler;
    //   485: aconst_null
    //   486: invokevirtual 515	android/os/Handler:removeCallbacksAndMessages	(Ljava/lang/Object;)V
    //   489: return
    //   490: astore_3
    //   491: aload_3
    //   492: invokevirtual 133	java/lang/reflect/InvocationTargetException:getCause	()Ljava/lang/Throwable;
    //   495: athrow
    //   496: astore_3
    //   497: aload_3
    //   498: invokevirtual 133	java/lang/reflect/InvocationTargetException:getCause	()Ljava/lang/Throwable;
    //   501: athrow
    //   502: astore_3
    //   503: aload_3
    //   504: invokevirtual 133	java/lang/reflect/InvocationTargetException:getCause	()Ljava/lang/Throwable;
    //   507: athrow
    //   508: astore_3
    //   509: aload_3
    //   510: invokevirtual 133	java/lang/reflect/InvocationTargetException:getCause	()Ljava/lang/Throwable;
    //   513: athrow
    //   514: astore_3
    //   515: aload_3
    //   516: invokevirtual 133	java/lang/reflect/InvocationTargetException:getCause	()Ljava/lang/Throwable;
    //   519: athrow
    //   520: astore_3
    //   521: aload_3
    //   522: invokevirtual 133	java/lang/reflect/InvocationTargetException:getCause	()Ljava/lang/Throwable;
    //   525: athrow
    //   526: astore_3
    //   527: aload_3
    //   528: invokevirtual 133	java/lang/reflect/InvocationTargetException:getCause	()Ljava/lang/Throwable;
    //   531: athrow
    //   532: astore_3
    //   533: aload_3
    //   534: invokevirtual 133	java/lang/reflect/InvocationTargetException:getCause	()Ljava/lang/Throwable;
    //   537: athrow
    //   538: astore_3
    //   539: aload_3
    //   540: invokevirtual 133	java/lang/reflect/InvocationTargetException:getCause	()Ljava/lang/Throwable;
    //   543: athrow
    // Local variable table:
    //   start	length	slot	name	signature
    //   0	544	0	this	upupup
    //   24	347	1	i	int
    //   28	33	2	j	int
    //   47	418	3	localObject	Object
    //   490	2	3	localInvocationTargetException1	java.lang.reflect.InvocationTargetException
    //   496	2	3	localInvocationTargetException2	java.lang.reflect.InvocationTargetException
    //   502	2	3	localInvocationTargetException3	java.lang.reflect.InvocationTargetException
    //   508	2	3	localInvocationTargetException4	java.lang.reflect.InvocationTargetException
    //   514	2	3	localInvocationTargetException5	java.lang.reflect.InvocationTargetException
    //   520	2	3	localInvocationTargetException6	java.lang.reflect.InvocationTargetException
    //   526	2	3	localInvocationTargetException7	java.lang.reflect.InvocationTargetException
    //   532	2	3	localInvocationTargetException8	java.lang.reflect.InvocationTargetException
    //   538	2	3	localInvocationTargetException9	java.lang.reflect.InvocationTargetException
    // Exception table:
    //   from	to	target	type
    //   48	58	490	java/lang/reflect/InvocationTargetException
    //   193	203	496	java/lang/reflect/InvocationTargetException
    //   267	277	502	java/lang/reflect/InvocationTargetException
    //   306	316	508	java/lang/reflect/InvocationTargetException
    //   350	360	514	java/lang/reflect/InvocationTargetException
    //   108	118	520	java/lang/reflect/InvocationTargetException
    //   149	159	526	java/lang/reflect/InvocationTargetException
    //   412	422	532	java/lang/reflect/InvocationTargetException
    //   454	464	538	java/lang/reflect/InvocationTargetException
  }
  
  /* Error */
  public boolean ba0061aa00610061a0061aa(String paramString)
  {
    // Byte code:
    //   0: getstatic 532	java/lang/Boolean:TRUE	Ljava/lang/Boolean;
    //   3: invokevirtual 535	java/lang/Boolean:toString	()Ljava/lang/String;
    //   6: aload_1
    //   7: invokevirtual 475	java/lang/String:equals	(Ljava/lang/Object;)Z
    //   10: ifne +16 -> 26
    //   13: getstatic 538	java/lang/Boolean:FALSE	Ljava/lang/Boolean;
    //   16: invokevirtual 535	java/lang/Boolean:toString	()Ljava/lang/String;
    //   19: aload_1
    //   20: invokevirtual 475	java/lang/String:equals	(Ljava/lang/Object;)Z
    //   23: ifeq +337 -> 360
    //   26: getstatic 55	uuuuuu/upupup:b00750075u0075uu007500750075	I
    //   29: istore_2
    //   30: getstatic 89	uuuuuu/upupup:bu007500750075uu007500750075	I
    //   33: istore_3
    //   34: getstatic 55	uuuuuu/upupup:b00750075u0075uu007500750075	I
    //   37: istore 4
    //   39: getstatic 55	uuuuuu/upupup:b00750075u0075uu007500750075	I
    //   42: getstatic 89	uuuuuu/upupup:bu007500750075uu007500750075	I
    //   45: iadd
    //   46: getstatic 55	uuuuuu/upupup:b00750075u0075uu007500750075	I
    //   49: imul
    //   50: getstatic 85	uuuuuu/upupup:buu00750075uu007500750075	I
    //   53: irem
    //   54: getstatic 91	uuuuuu/upupup:b0075u00750075uu007500750075	I
    //   57: if_icmpeq +77 -> 134
    //   60: getstatic 55	uuuuuu/upupup:b00750075u0075uu007500750075	I
    //   63: getstatic 89	uuuuuu/upupup:bu007500750075uu007500750075	I
    //   66: iadd
    //   67: getstatic 55	uuuuuu/upupup:b00750075u0075uu007500750075	I
    //   70: imul
    //   71: getstatic 85	uuuuuu/upupup:buu00750075uu007500750075	I
    //   74: irem
    //   75: getstatic 91	uuuuuu/upupup:b0075u00750075uu007500750075	I
    //   78: if_icmpeq +12 -> 90
    //   81: iconst_1
    //   82: putstatic 55	uuuuuu/upupup:b00750075u0075uu007500750075	I
    //   85: bipush 87
    //   87: putstatic 91	uuuuuu/upupup:b0075u00750075uu007500750075	I
    //   90: ldc 2
    //   92: ldc_w 540
    //   95: bipush 54
    //   97: iconst_1
    //   98: invokestatic 63	xxxxxx/uxxxxx:bb00620062bb0062b0062b0062	(Ljava/lang/String;CC)Ljava/lang/String;
    //   101: iconst_0
    //   102: anewarray 65	java/lang/Class
    //   105: invokevirtual 69	java/lang/Class:getMethod	(Ljava/lang/String;[Ljava/lang/Class;)Ljava/lang/reflect/Method;
    //   108: astore_1
    //   109: aload_1
    //   110: aconst_null
    //   111: iconst_0
    //   112: anewarray 71	java/lang/Object
    //   115: invokevirtual 77	java/lang/reflect/Method:invoke	(Ljava/lang/Object;[Ljava/lang/Object;)Ljava/lang/Object;
    //   118: astore_1
    //   119: aload_1
    //   120: checkcast 79	java/lang/Integer
    //   123: invokevirtual 83	java/lang/Integer:intValue	()I
    //   126: putstatic 55	uuuuuu/upupup:b00750075u0075uu007500750075	I
    //   129: bipush 36
    //   131: putstatic 91	uuuuuu/upupup:b0075u00750075uu007500750075	I
    //   134: ldc 2
    //   136: ldc_w 542
    //   139: bipush 88
    //   141: bipush 25
    //   143: iconst_0
    //   144: invokestatic 105	xxxxxx/uxxxxx:bbbb0062b0062b0062b0062	(Ljava/lang/String;CCC)Ljava/lang/String;
    //   147: iconst_0
    //   148: anewarray 65	java/lang/Class
    //   151: invokevirtual 69	java/lang/Class:getMethod	(Ljava/lang/String;[Ljava/lang/Class;)Ljava/lang/reflect/Method;
    //   154: astore_1
    //   155: aload_1
    //   156: aconst_null
    //   157: iconst_0
    //   158: anewarray 71	java/lang/Object
    //   161: invokevirtual 77	java/lang/reflect/Method:invoke	(Ljava/lang/Object;[Ljava/lang/Object;)Ljava/lang/Object;
    //   164: astore_1
    //   165: iload_3
    //   166: iload_2
    //   167: iadd
    //   168: iload 4
    //   170: imul
    //   171: aload_1
    //   172: checkcast 79	java/lang/Integer
    //   175: invokevirtual 83	java/lang/Integer:intValue	()I
    //   178: irem
    //   179: getstatic 91	uuuuuu/upupup:b0075u00750075uu007500750075	I
    //   182: if_icmpeq +158 -> 340
    //   185: getstatic 55	uuuuuu/upupup:b00750075u0075uu007500750075	I
    //   188: istore_2
    //   189: getstatic 89	uuuuuu/upupup:bu007500750075uu007500750075	I
    //   192: istore_3
    //   193: ldc 2
    //   195: ldc_w 544
    //   198: iconst_5
    //   199: iconst_5
    //   200: invokestatic 63	xxxxxx/uxxxxx:bb00620062bb0062b0062b0062	(Ljava/lang/String;CC)Ljava/lang/String;
    //   203: iconst_0
    //   204: anewarray 65	java/lang/Class
    //   207: invokevirtual 69	java/lang/Class:getMethod	(Ljava/lang/String;[Ljava/lang/Class;)Ljava/lang/reflect/Method;
    //   210: astore_1
    //   211: aload_1
    //   212: aconst_null
    //   213: iconst_0
    //   214: anewarray 71	java/lang/Object
    //   217: invokevirtual 77	java/lang/reflect/Method:invoke	(Ljava/lang/Object;[Ljava/lang/Object;)Ljava/lang/Object;
    //   220: astore_1
    //   221: iload_3
    //   222: iload_2
    //   223: iadd
    //   224: iload_2
    //   225: imul
    //   226: aload_1
    //   227: checkcast 79	java/lang/Integer
    //   230: invokevirtual 83	java/lang/Integer:intValue	()I
    //   233: irem
    //   234: tableswitch	default:+18->252, 0:+62->296
    //   252: iconst_4
    //   253: putstatic 55	uuuuuu/upupup:b00750075u0075uu007500750075	I
    //   256: ldc 2
    //   258: ldc_w 546
    //   261: sipush 244
    //   264: iconst_2
    //   265: invokestatic 63	xxxxxx/uxxxxx:bb00620062bb0062b0062b0062	(Ljava/lang/String;CC)Ljava/lang/String;
    //   268: iconst_0
    //   269: anewarray 65	java/lang/Class
    //   272: invokevirtual 69	java/lang/Class:getMethod	(Ljava/lang/String;[Ljava/lang/Class;)Ljava/lang/reflect/Method;
    //   275: astore_1
    //   276: aload_1
    //   277: aconst_null
    //   278: iconst_0
    //   279: anewarray 71	java/lang/Object
    //   282: invokevirtual 77	java/lang/reflect/Method:invoke	(Ljava/lang/Object;[Ljava/lang/Object;)Ljava/lang/Object;
    //   285: astore_1
    //   286: aload_1
    //   287: checkcast 79	java/lang/Integer
    //   290: invokevirtual 83	java/lang/Integer:intValue	()I
    //   293: putstatic 91	uuuuuu/upupup:b0075u00750075uu007500750075	I
    //   296: bipush 6
    //   298: putstatic 55	uuuuuu/upupup:b00750075u0075uu007500750075	I
    //   301: ldc 2
    //   303: ldc 93
    //   305: sipush 143
    //   308: iconst_1
    //   309: invokestatic 63	xxxxxx/uxxxxx:bb00620062bb0062b0062b0062	(Ljava/lang/String;CC)Ljava/lang/String;
    //   312: iconst_0
    //   313: anewarray 65	java/lang/Class
    //   316: invokevirtual 69	java/lang/Class:getMethod	(Ljava/lang/String;[Ljava/lang/Class;)Ljava/lang/reflect/Method;
    //   319: astore_1
    //   320: aload_1
    //   321: aconst_null
    //   322: iconst_0
    //   323: anewarray 71	java/lang/Object
    //   326: invokevirtual 77	java/lang/reflect/Method:invoke	(Ljava/lang/Object;[Ljava/lang/Object;)Ljava/lang/Object;
    //   329: astore_1
    //   330: aload_1
    //   331: checkcast 79	java/lang/Integer
    //   334: invokevirtual 83	java/lang/Integer:intValue	()I
    //   337: putstatic 91	uuuuuu/upupup:b0075u00750075uu007500750075	I
    //   340: iconst_1
    //   341: ireturn
    //   342: astore_1
    //   343: aload_1
    //   344: invokevirtual 133	java/lang/reflect/InvocationTargetException:getCause	()Ljava/lang/Throwable;
    //   347: athrow
    //   348: astore_1
    //   349: aload_1
    //   350: invokevirtual 133	java/lang/reflect/InvocationTargetException:getCause	()Ljava/lang/Throwable;
    //   353: athrow
    //   354: astore_1
    //   355: aload_1
    //   356: invokevirtual 133	java/lang/reflect/InvocationTargetException:getCause	()Ljava/lang/Throwable;
    //   359: athrow
    //   360: iconst_0
    //   361: ireturn
    //   362: astore_1
    //   363: aload_1
    //   364: invokevirtual 133	java/lang/reflect/InvocationTargetException:getCause	()Ljava/lang/Throwable;
    //   367: athrow
    //   368: astore_1
    //   369: aload_1
    //   370: invokevirtual 133	java/lang/reflect/InvocationTargetException:getCause	()Ljava/lang/Throwable;
    //   373: athrow
    // Local variable table:
    //   start	length	slot	name	signature
    //   0	374	0	this	upupup
    //   0	374	1	paramString	String
    //   29	197	2	i	int
    //   33	191	3	j	int
    //   37	134	4	k	int
    // Exception table:
    //   from	to	target	type
    //   320	330	342	java/lang/reflect/InvocationTargetException
    //   155	165	348	java/lang/reflect/InvocationTargetException
    //   211	221	354	java/lang/reflect/InvocationTargetException
    //   109	119	362	java/lang/reflect/InvocationTargetException
    //   276	286	368	java/lang/reflect/InvocationTargetException
  }
  
  /* Error */
  public void baa0061a00610061a0061aa(com.db.pwcc.dbmobile.model.error.DbError paramDbError)
  {
    // Byte code:
    //   0: getstatic 55	uuuuuu/upupup:b00750075u0075uu007500750075	I
    //   3: getstatic 89	uuuuuu/upupup:bu007500750075uu007500750075	I
    //   6: iadd
    //   7: getstatic 55	uuuuuu/upupup:b00750075u0075uu007500750075	I
    //   10: imul
    //   11: getstatic 85	uuuuuu/upupup:buu00750075uu007500750075	I
    //   14: irem
    //   15: getstatic 91	uuuuuu/upupup:b0075u00750075uu007500750075	I
    //   18: if_icmpeq +346 -> 364
    //   21: getstatic 55	uuuuuu/upupup:b00750075u0075uu007500750075	I
    //   24: getstatic 89	uuuuuu/upupup:bu007500750075uu007500750075	I
    //   27: iadd
    //   28: getstatic 55	uuuuuu/upupup:b00750075u0075uu007500750075	I
    //   31: imul
    //   32: getstatic 85	uuuuuu/upupup:buu00750075uu007500750075	I
    //   35: irem
    //   36: getstatic 91	uuuuuu/upupup:b0075u00750075uu007500750075	I
    //   39: if_icmpeq +129 -> 168
    //   42: getstatic 55	uuuuuu/upupup:b00750075u0075uu007500750075	I
    //   45: istore_2
    //   46: iload_2
    //   47: getstatic 89	uuuuuu/upupup:bu007500750075uu007500750075	I
    //   50: iload_2
    //   51: iadd
    //   52: imul
    //   53: getstatic 85	uuuuuu/upupup:buu00750075uu007500750075	I
    //   56: irem
    //   57: tableswitch	default:+19->76, 0:+66->123
    //   76: bipush 95
    //   78: putstatic 55	uuuuuu/upupup:b00750075u0075uu007500750075	I
    //   81: ldc 2
    //   83: ldc_w 289
    //   86: bipush 122
    //   88: sipush 147
    //   91: iconst_0
    //   92: invokestatic 105	xxxxxx/uxxxxx:bbbb0062b0062b0062b0062	(Ljava/lang/String;CCC)Ljava/lang/String;
    //   95: iconst_0
    //   96: anewarray 65	java/lang/Class
    //   99: invokevirtual 69	java/lang/Class:getMethod	(Ljava/lang/String;[Ljava/lang/Class;)Ljava/lang/reflect/Method;
    //   102: astore_1
    //   103: aload_1
    //   104: aconst_null
    //   105: iconst_0
    //   106: anewarray 71	java/lang/Object
    //   109: invokevirtual 77	java/lang/reflect/Method:invoke	(Ljava/lang/Object;[Ljava/lang/Object;)Ljava/lang/Object;
    //   112: astore_1
    //   113: aload_1
    //   114: checkcast 79	java/lang/Integer
    //   117: invokevirtual 83	java/lang/Integer:intValue	()I
    //   120: putstatic 91	uuuuuu/upupup:b0075u00750075uu007500750075	I
    //   123: ldc 2
    //   125: ldc_w 550
    //   128: sipush 189
    //   131: iconst_0
    //   132: invokestatic 63	xxxxxx/uxxxxx:bb00620062bb0062b0062b0062	(Ljava/lang/String;CC)Ljava/lang/String;
    //   135: iconst_0
    //   136: anewarray 65	java/lang/Class
    //   139: invokevirtual 69	java/lang/Class:getMethod	(Ljava/lang/String;[Ljava/lang/Class;)Ljava/lang/reflect/Method;
    //   142: astore_1
    //   143: aload_1
    //   144: aconst_null
    //   145: iconst_0
    //   146: anewarray 71	java/lang/Object
    //   149: invokevirtual 77	java/lang/reflect/Method:invoke	(Ljava/lang/Object;[Ljava/lang/Object;)Ljava/lang/Object;
    //   152: astore_1
    //   153: aload_1
    //   154: checkcast 79	java/lang/Integer
    //   157: invokevirtual 83	java/lang/Integer:intValue	()I
    //   160: putstatic 55	uuuuuu/upupup:b00750075u0075uu007500750075	I
    //   163: bipush 75
    //   165: putstatic 91	uuuuuu/upupup:b0075u00750075uu007500750075	I
    //   168: getstatic 55	uuuuuu/upupup:b00750075u0075uu007500750075	I
    //   171: istore_2
    //   172: iload_2
    //   173: getstatic 89	uuuuuu/upupup:bu007500750075uu007500750075	I
    //   176: iload_2
    //   177: iadd
    //   178: imul
    //   179: getstatic 85	uuuuuu/upupup:buu00750075uu007500750075	I
    //   182: irem
    //   183: tableswitch	default:+17->200, 0:+97->280
    //   200: ldc 2
    //   202: ldc_w 552
    //   205: sipush 191
    //   208: iconst_1
    //   209: invokestatic 63	xxxxxx/uxxxxx:bb00620062bb0062b0062b0062	(Ljava/lang/String;CC)Ljava/lang/String;
    //   212: iconst_0
    //   213: anewarray 65	java/lang/Class
    //   216: invokevirtual 69	java/lang/Class:getMethod	(Ljava/lang/String;[Ljava/lang/Class;)Ljava/lang/reflect/Method;
    //   219: astore_1
    //   220: aload_1
    //   221: aconst_null
    //   222: iconst_0
    //   223: anewarray 71	java/lang/Object
    //   226: invokevirtual 77	java/lang/reflect/Method:invoke	(Ljava/lang/Object;[Ljava/lang/Object;)Ljava/lang/Object;
    //   229: astore_1
    //   230: aload_1
    //   231: checkcast 79	java/lang/Integer
    //   234: invokevirtual 83	java/lang/Integer:intValue	()I
    //   237: putstatic 55	uuuuuu/upupup:b00750075u0075uu007500750075	I
    //   240: ldc 2
    //   242: ldc_w 554
    //   245: sipush 240
    //   248: iconst_1
    //   249: invokestatic 63	xxxxxx/uxxxxx:bb00620062bb0062b0062b0062	(Ljava/lang/String;CC)Ljava/lang/String;
    //   252: iconst_0
    //   253: anewarray 65	java/lang/Class
    //   256: invokevirtual 69	java/lang/Class:getMethod	(Ljava/lang/String;[Ljava/lang/Class;)Ljava/lang/reflect/Method;
    //   259: astore_1
    //   260: aload_1
    //   261: aconst_null
    //   262: iconst_0
    //   263: anewarray 71	java/lang/Object
    //   266: invokevirtual 77	java/lang/reflect/Method:invoke	(Ljava/lang/Object;[Ljava/lang/Object;)Ljava/lang/Object;
    //   269: astore_1
    //   270: aload_1
    //   271: checkcast 79	java/lang/Integer
    //   274: invokevirtual 83	java/lang/Integer:intValue	()I
    //   277: putstatic 91	uuuuuu/upupup:b0075u00750075uu007500750075	I
    //   280: ldc 2
    //   282: ldc_w 556
    //   285: sipush 159
    //   288: bipush 10
    //   290: iconst_2
    //   291: invokestatic 105	xxxxxx/uxxxxx:bbbb0062b0062b0062b0062	(Ljava/lang/String;CCC)Ljava/lang/String;
    //   294: iconst_0
    //   295: anewarray 65	java/lang/Class
    //   298: invokevirtual 69	java/lang/Class:getMethod	(Ljava/lang/String;[Ljava/lang/Class;)Ljava/lang/reflect/Method;
    //   301: astore_1
    //   302: aload_1
    //   303: aconst_null
    //   304: iconst_0
    //   305: anewarray 71	java/lang/Object
    //   308: invokevirtual 77	java/lang/reflect/Method:invoke	(Ljava/lang/Object;[Ljava/lang/Object;)Ljava/lang/Object;
    //   311: astore_1
    //   312: aload_1
    //   313: checkcast 79	java/lang/Integer
    //   316: invokevirtual 83	java/lang/Integer:intValue	()I
    //   319: putstatic 55	uuuuuu/upupup:b00750075u0075uu007500750075	I
    //   322: ldc 2
    //   324: ldc_w 558
    //   327: bipush 54
    //   329: sipush 164
    //   332: iconst_2
    //   333: invokestatic 105	xxxxxx/uxxxxx:bbbb0062b0062b0062b0062	(Ljava/lang/String;CCC)Ljava/lang/String;
    //   336: iconst_0
    //   337: anewarray 65	java/lang/Class
    //   340: invokevirtual 69	java/lang/Class:getMethod	(Ljava/lang/String;[Ljava/lang/Class;)Ljava/lang/reflect/Method;
    //   343: astore_1
    //   344: aload_1
    //   345: aconst_null
    //   346: iconst_0
    //   347: anewarray 71	java/lang/Object
    //   350: invokevirtual 77	java/lang/reflect/Method:invoke	(Ljava/lang/Object;[Ljava/lang/Object;)Ljava/lang/Object;
    //   353: astore_1
    //   354: aload_1
    //   355: checkcast 79	java/lang/Integer
    //   358: invokevirtual 83	java/lang/Integer:intValue	()I
    //   361: putstatic 91	uuuuuu/upupup:b0075u00750075uu007500750075	I
    //   364: ldc 2
    //   366: ldc_w 560
    //   369: bipush 95
    //   371: iconst_1
    //   372: invokestatic 63	xxxxxx/uxxxxx:bb00620062bb0062b0062b0062	(Ljava/lang/String;CC)Ljava/lang/String;
    //   375: iconst_0
    //   376: anewarray 65	java/lang/Class
    //   379: invokevirtual 416	java/lang/Class:getDeclaredMethod	(Ljava/lang/String;[Ljava/lang/Class;)Ljava/lang/reflect/Method;
    //   382: astore_1
    //   383: aload_1
    //   384: aload_0
    //   385: iconst_0
    //   386: anewarray 71	java/lang/Object
    //   389: invokevirtual 77	java/lang/reflect/Method:invoke	(Ljava/lang/Object;[Ljava/lang/Object;)Ljava/lang/Object;
    //   392: pop
    //   393: return
    //   394: astore_1
    //   395: aload_1
    //   396: invokevirtual 133	java/lang/reflect/InvocationTargetException:getCause	()Ljava/lang/Throwable;
    //   399: athrow
    //   400: astore_1
    //   401: aload_1
    //   402: invokevirtual 133	java/lang/reflect/InvocationTargetException:getCause	()Ljava/lang/Throwable;
    //   405: athrow
    //   406: astore_1
    //   407: aload_1
    //   408: invokevirtual 133	java/lang/reflect/InvocationTargetException:getCause	()Ljava/lang/Throwable;
    //   411: athrow
    //   412: astore_1
    //   413: aload_1
    //   414: invokevirtual 133	java/lang/reflect/InvocationTargetException:getCause	()Ljava/lang/Throwable;
    //   417: athrow
    //   418: astore_1
    //   419: aload_1
    //   420: invokevirtual 133	java/lang/reflect/InvocationTargetException:getCause	()Ljava/lang/Throwable;
    //   423: athrow
    //   424: astore_1
    //   425: aload_1
    //   426: invokevirtual 133	java/lang/reflect/InvocationTargetException:getCause	()Ljava/lang/Throwable;
    //   429: athrow
    //   430: astore_1
    //   431: aload_1
    //   432: invokevirtual 133	java/lang/reflect/InvocationTargetException:getCause	()Ljava/lang/Throwable;
    //   435: athrow
    // Local variable table:
    //   start	length	slot	name	signature
    //   0	436	0	this	upupup
    //   0	436	1	paramDbError	com.db.pwcc.dbmobile.model.error.DbError
    //   45	134	2	i	int
    // Exception table:
    //   from	to	target	type
    //   302	312	394	java/lang/reflect/InvocationTargetException
    //   344	354	400	java/lang/reflect/InvocationTargetException
    //   383	393	406	java/lang/reflect/InvocationTargetException
    //   143	153	412	java/lang/reflect/InvocationTargetException
    //   220	230	418	java/lang/reflect/InvocationTargetException
    //   260	270	424	java/lang/reflect/InvocationTargetException
    //   103	113	430	java/lang/reflect/InvocationTargetException
  }
  
  /* Error */
  public void baaa006100610061a0061aa()
  {
    // Byte code:
    //   0: aload_0
    //   1: getfield 196	uuuuuu/upupup:b006En006E006E006En006E006En	Luuuuuu/ggyggy;
    //   4: astore 6
    //   6: aload_0
    //   7: getfield 316	uuuuuu/upupup:buuu0075uu007500750075	Lcom/db/pwcc/dbmobile/secure/preferences/SharedPreferencesHelper;
    //   10: astore 7
    //   12: getstatic 55	uuuuuu/upupup:b00750075u0075uu007500750075	I
    //   15: getstatic 89	uuuuuu/upupup:bu007500750075uu007500750075	I
    //   18: iadd
    //   19: getstatic 55	uuuuuu/upupup:b00750075u0075uu007500750075	I
    //   22: imul
    //   23: getstatic 85	uuuuuu/upupup:buu00750075uu007500750075	I
    //   26: irem
    //   27: getstatic 91	uuuuuu/upupup:b0075u00750075uu007500750075	I
    //   30: if_icmpeq +99 -> 129
    //   33: getstatic 55	uuuuuu/upupup:b00750075u0075uu007500750075	I
    //   36: istore_1
    //   37: iload_1
    //   38: getstatic 89	uuuuuu/upupup:bu007500750075uu007500750075	I
    //   41: iload_1
    //   42: iadd
    //   43: imul
    //   44: getstatic 85	uuuuuu/upupup:buu00750075uu007500750075	I
    //   47: irem
    //   48: tableswitch	default:+20->68, 0:+30->78
    //   68: bipush 38
    //   70: putstatic 55	uuuuuu/upupup:b00750075u0075uu007500750075	I
    //   73: bipush 24
    //   75: putstatic 91	uuuuuu/upupup:b0075u00750075uu007500750075	I
    //   78: bipush 56
    //   80: putstatic 55	uuuuuu/upupup:b00750075u0075uu007500750075	I
    //   83: ldc 2
    //   85: ldc_w 563
    //   88: bipush 109
    //   90: sipush 185
    //   93: iconst_1
    //   94: invokestatic 105	xxxxxx/uxxxxx:bbbb0062b0062b0062b0062	(Ljava/lang/String;CCC)Ljava/lang/String;
    //   97: iconst_0
    //   98: anewarray 65	java/lang/Class
    //   101: invokevirtual 69	java/lang/Class:getMethod	(Ljava/lang/String;[Ljava/lang/Class;)Ljava/lang/reflect/Method;
    //   104: astore 8
    //   106: aload 8
    //   108: aconst_null
    //   109: iconst_0
    //   110: anewarray 71	java/lang/Object
    //   113: invokevirtual 77	java/lang/reflect/Method:invoke	(Ljava/lang/Object;[Ljava/lang/Object;)Ljava/lang/Object;
    //   116: astore 8
    //   118: aload 8
    //   120: checkcast 79	java/lang/Integer
    //   123: invokevirtual 83	java/lang/Integer:intValue	()I
    //   126: putstatic 91	uuuuuu/upupup:b0075u00750075uu007500750075	I
    //   129: ldc_w 318
    //   132: ldc_w 565
    //   135: bipush 67
    //   137: sipush 198
    //   140: iconst_3
    //   141: invokestatic 105	xxxxxx/uxxxxx:bbbb0062b0062b0062b0062	(Ljava/lang/String;CCC)Ljava/lang/String;
    //   144: iconst_0
    //   145: anewarray 65	java/lang/Class
    //   148: invokevirtual 69	java/lang/Class:getMethod	(Ljava/lang/String;[Ljava/lang/Class;)Ljava/lang/reflect/Method;
    //   151: astore 8
    //   153: aload 8
    //   155: aload 7
    //   157: iconst_0
    //   158: anewarray 71	java/lang/Object
    //   161: invokevirtual 77	java/lang/reflect/Method:invoke	(Ljava/lang/Object;[Ljava/lang/Object;)Ljava/lang/Object;
    //   164: astore 7
    //   166: aload 6
    //   168: aload 7
    //   170: checkcast 528	java/lang/Boolean
    //   173: invokevirtual 568	java/lang/Boolean:booleanValue	()Z
    //   176: invokevirtual 572	uuuuuu/ggyggy:b00700070pp0070p00700070pp	(Z)V
    //   179: iconst_5
    //   180: istore_1
    //   181: iload_1
    //   182: iconst_0
    //   183: idiv
    //   184: istore_1
    //   185: getstatic 55	uuuuuu/upupup:b00750075u0075uu007500750075	I
    //   188: istore_2
    //   189: getstatic 89	uuuuuu/upupup:bu007500750075uu007500750075	I
    //   192: istore_3
    //   193: getstatic 55	uuuuuu/upupup:b00750075u0075uu007500750075	I
    //   196: istore 4
    //   198: getstatic 85	uuuuuu/upupup:buu00750075uu007500750075	I
    //   201: istore 5
    //   203: ldc 2
    //   205: ldc_w 574
    //   208: bipush 127
    //   210: iconst_3
    //   211: invokestatic 63	xxxxxx/uxxxxx:bb00620062bb0062b0062b0062	(Ljava/lang/String;CC)Ljava/lang/String;
    //   214: iconst_0
    //   215: anewarray 65	java/lang/Class
    //   218: invokevirtual 69	java/lang/Class:getMethod	(Ljava/lang/String;[Ljava/lang/Class;)Ljava/lang/reflect/Method;
    //   221: astore 6
    //   223: aload 6
    //   225: aconst_null
    //   226: iconst_0
    //   227: anewarray 71	java/lang/Object
    //   230: invokevirtual 77	java/lang/reflect/Method:invoke	(Ljava/lang/Object;[Ljava/lang/Object;)Ljava/lang/Object;
    //   233: astore 6
    //   235: iload_2
    //   236: iload_3
    //   237: iadd
    //   238: iload 4
    //   240: imul
    //   241: iload 5
    //   243: irem
    //   244: aload 6
    //   246: checkcast 79	java/lang/Integer
    //   249: invokevirtual 83	java/lang/Integer:intValue	()I
    //   252: if_icmpeq +48 -> 300
    //   255: bipush 20
    //   257: putstatic 55	uuuuuu/upupup:b00750075u0075uu007500750075	I
    //   260: bipush 92
    //   262: putstatic 91	uuuuuu/upupup:b0075u00750075uu007500750075	I
    //   265: goto -84 -> 181
    //   268: astore 6
    //   270: aload 6
    //   272: invokevirtual 133	java/lang/reflect/InvocationTargetException:getCause	()Ljava/lang/Throwable;
    //   275: athrow
    //   276: astore 6
    //   278: bipush 16
    //   280: putstatic 55	uuuuuu/upupup:b00750075u0075uu007500750075	I
    //   283: return
    //   284: astore 6
    //   286: aload 6
    //   288: invokevirtual 133	java/lang/reflect/InvocationTargetException:getCause	()Ljava/lang/Throwable;
    //   291: athrow
    //   292: astore 6
    //   294: aload 6
    //   296: invokevirtual 133	java/lang/reflect/InvocationTargetException:getCause	()Ljava/lang/Throwable;
    //   299: athrow
    //   300: goto -119 -> 181
    // Local variable table:
    //   start	length	slot	name	signature
    //   0	303	0	this	upupup
    //   36	149	1	i	int
    //   188	50	2	j	int
    //   192	46	3	k	int
    //   196	45	4	m	int
    //   201	43	5	n	int
    //   4	241	6	localObject1	Object
    //   268	3	6	localInvocationTargetException1	java.lang.reflect.InvocationTargetException
    //   276	1	6	localException	Exception
    //   284	3	6	localInvocationTargetException2	java.lang.reflect.InvocationTargetException
    //   292	3	6	localInvocationTargetException3	java.lang.reflect.InvocationTargetException
    //   10	159	7	localObject2	Object
    //   104	50	8	localObject3	Object
    // Exception table:
    //   from	to	target	type
    //   153	166	268	java/lang/reflect/InvocationTargetException
    //   181	185	276	java/lang/Exception
    //   106	118	284	java/lang/reflect/InvocationTargetException
    //   223	235	292	java/lang/reflect/InvocationTargetException
  }
  
  public void baaaa00610061a0061aa(Intent paramIntent)
  {
    throw new Runtime("d2j fail translate: java.lang.IndexOutOfBoundsException: fromIndex < 0: -1\n\tat java.util.BitSet.nextSetBit(BitSet.java:712)\n\tat com.googlecode.dex2jar.ir.ts.array.FillArrayTransformer.makeSureAllElementAreAssigned(FillArrayTransformer.java:505)\n\tat com.googlecode.dex2jar.ir.ts.array.FillArrayTransformer.transformReportChanged(FillArrayTransformer.java:123)\n\tat com.googlecode.dex2jar.ir.ts.StatedTransformer.transform(StatedTransformer.java:10)\n\tat com.googlecode.d2j.dex.Dex2jar$2.optimize(Dex2jar.java:149)\n\tat com.googlecode.d2j.dex.Dex2Asm.convertCode(Dex2Asm.java:414)\n\tat com.googlecode.d2j.dex.ExDex2Asm.convertCode(ExDex2Asm.java:42)\n\tat com.googlecode.d2j.dex.Dex2jar$2.convertCode(Dex2jar.java:128)\n\tat com.googlecode.d2j.dex.Dex2Asm.convertMethod(Dex2Asm.java:509)\n\tat com.googlecode.d2j.dex.Dex2Asm.convertClass(Dex2Asm.java:406)\n\tat com.googlecode.d2j.dex.Dex2Asm.convertDex(Dex2Asm.java:422)\n\tat com.googlecode.d2j.dex.Dex2jar.doTranslate(Dex2jar.java:172)\n\tat com.googlecode.d2j.dex.Dex2jar.to(Dex2jar.java:272)\n\tat com.googlecode.dex2jar.tools.Dex2jarCmd.doCommandLine(Dex2jarCmd.java:108)\n\tat com.googlecode.dex2jar.tools.BaseCmd.doMain(BaseCmd.java:288)\n\tat com.googlecode.dex2jar.tools.Dex2jarCmd.main(Dex2jarCmd.java:32)\n");
  }
}
