package uuuuuu;

import android.os.Bundle;

public class vdvvdd
  implements dvdvdd.vvdvdd
{
  public static int b00680068hhhhhhh = 2;
  public static int b0068hhhhhhhh = 0;
  public static int bc00630063006300630063006300630063 = 87;
  public static int bh0068hhhhhhh = 1;
  private boolean b00630063c006300630063006300630063;
  public dvdvdd.ddvvdd b0063c0063006300630063006300630063;
  private Bundle b0063cc006300630063006300630063;
  private boolean bc0063c006300630063006300630063;
  private String bcc0063006300630063006300630063;
  
  public vdvvdd(dvdvdd.ddvvdd paramDdvvdd)
  {
    this.b0063c0063006300630063006300630063 = paramDdvvdd;
  }
  
  public static int b00710071qq00710071q00710071q()
  {
    return 0;
  }
  
  public static int b0071qqq00710071q00710071q()
  {
    return 1;
  }
  
  public static int bq0071qq00710071q00710071q()
  {
    return 81;
  }
  
  public static int bqqqq00710071q00710071q()
  {
    return 2;
  }
  
  /* Error */
  public void b0071007100710071q0071q00710071q(Bundle paramBundle)
  {
    // Byte code:
    //   0: ldc 43
    //   2: ldc 45
    //   4: sipush 204
    //   7: bipush 62
    //   9: iconst_0
    //   10: invokestatic 51	xxxxxx/uxxxxx:bbbb0062b0062b0062b0062	(Ljava/lang/String;CCC)Ljava/lang/String;
    //   13: iconst_3
    //   14: anewarray 53	java/lang/Class
    //   17: dup
    //   18: iconst_0
    //   19: ldc 55
    //   21: aastore
    //   22: dup
    //   23: iconst_1
    //   24: getstatic 61	java/lang/Character:TYPE	Ljava/lang/Class;
    //   27: aastore
    //   28: dup
    //   29: iconst_2
    //   30: getstatic 61	java/lang/Character:TYPE	Ljava/lang/Class;
    //   33: aastore
    //   34: invokevirtual 65	java/lang/Class:getMethod	(Ljava/lang/String;[Ljava/lang/Class;)Ljava/lang/reflect/Method;
    //   37: astore 6
    //   39: aload 6
    //   41: aconst_null
    //   42: iconst_3
    //   43: anewarray 4	java/lang/Object
    //   46: dup
    //   47: iconst_0
    //   48: ldc 67
    //   50: aastore
    //   51: dup
    //   52: iconst_1
    //   53: sipush 144
    //   56: invokestatic 71	java/lang/Character:valueOf	(C)Ljava/lang/Character;
    //   59: aastore
    //   60: dup
    //   61: iconst_2
    //   62: iconst_4
    //   63: invokestatic 71	java/lang/Character:valueOf	(C)Ljava/lang/Character;
    //   66: aastore
    //   67: invokevirtual 77	java/lang/reflect/Method:invoke	(Ljava/lang/Object;[Ljava/lang/Object;)Ljava/lang/Object;
    //   70: astore 6
    //   72: aload_0
    //   73: aload_1
    //   74: aload 6
    //   76: checkcast 55	java/lang/String
    //   79: invokevirtual 83	android/os/Bundle:getBoolean	(Ljava/lang/String;)Z
    //   82: putfield 85	uuuuuu/vdvvdd:bc0063c006300630063006300630063	Z
    //   85: ldc 43
    //   87: ldc 87
    //   89: bipush 37
    //   91: bipush 59
    //   93: iconst_3
    //   94: invokestatic 51	xxxxxx/uxxxxx:bbbb0062b0062b0062b0062	(Ljava/lang/String;CCC)Ljava/lang/String;
    //   97: iconst_4
    //   98: anewarray 53	java/lang/Class
    //   101: dup
    //   102: iconst_0
    //   103: ldc 55
    //   105: aastore
    //   106: dup
    //   107: iconst_1
    //   108: getstatic 61	java/lang/Character:TYPE	Ljava/lang/Class;
    //   111: aastore
    //   112: dup
    //   113: iconst_2
    //   114: getstatic 61	java/lang/Character:TYPE	Ljava/lang/Class;
    //   117: aastore
    //   118: dup
    //   119: iconst_3
    //   120: getstatic 61	java/lang/Character:TYPE	Ljava/lang/Class;
    //   123: aastore
    //   124: invokevirtual 65	java/lang/Class:getMethod	(Ljava/lang/String;[Ljava/lang/Class;)Ljava/lang/reflect/Method;
    //   127: astore 6
    //   129: aload 6
    //   131: aconst_null
    //   132: iconst_4
    //   133: anewarray 4	java/lang/Object
    //   136: dup
    //   137: iconst_0
    //   138: ldc 89
    //   140: aastore
    //   141: dup
    //   142: iconst_1
    //   143: sipush 150
    //   146: invokestatic 71	java/lang/Character:valueOf	(C)Ljava/lang/Character;
    //   149: aastore
    //   150: dup
    //   151: iconst_2
    //   152: bipush 37
    //   154: invokestatic 71	java/lang/Character:valueOf	(C)Ljava/lang/Character;
    //   157: aastore
    //   158: dup
    //   159: iconst_3
    //   160: iconst_2
    //   161: invokestatic 71	java/lang/Character:valueOf	(C)Ljava/lang/Character;
    //   164: aastore
    //   165: invokevirtual 77	java/lang/reflect/Method:invoke	(Ljava/lang/Object;[Ljava/lang/Object;)Ljava/lang/Object;
    //   168: astore 6
    //   170: aload_0
    //   171: aload_1
    //   172: aload 6
    //   174: checkcast 55	java/lang/String
    //   177: invokevirtual 83	android/os/Bundle:getBoolean	(Ljava/lang/String;)Z
    //   180: putfield 91	uuuuuu/vdvvdd:b00630063c006300630063006300630063	Z
    //   183: ldc 43
    //   185: ldc 93
    //   187: bipush 12
    //   189: bipush 80
    //   191: iconst_3
    //   192: invokestatic 51	xxxxxx/uxxxxx:bbbb0062b0062b0062b0062	(Ljava/lang/String;CCC)Ljava/lang/String;
    //   195: iconst_4
    //   196: anewarray 53	java/lang/Class
    //   199: dup
    //   200: iconst_0
    //   201: ldc 55
    //   203: aastore
    //   204: dup
    //   205: iconst_1
    //   206: getstatic 61	java/lang/Character:TYPE	Ljava/lang/Class;
    //   209: aastore
    //   210: dup
    //   211: iconst_2
    //   212: getstatic 61	java/lang/Character:TYPE	Ljava/lang/Class;
    //   215: aastore
    //   216: dup
    //   217: iconst_3
    //   218: getstatic 61	java/lang/Character:TYPE	Ljava/lang/Class;
    //   221: aastore
    //   222: invokevirtual 65	java/lang/Class:getMethod	(Ljava/lang/String;[Ljava/lang/Class;)Ljava/lang/reflect/Method;
    //   225: astore 6
    //   227: aload 6
    //   229: aconst_null
    //   230: iconst_4
    //   231: anewarray 4	java/lang/Object
    //   234: dup
    //   235: iconst_0
    //   236: ldc 95
    //   238: aastore
    //   239: dup
    //   240: iconst_1
    //   241: bipush 110
    //   243: invokestatic 71	java/lang/Character:valueOf	(C)Ljava/lang/Character;
    //   246: aastore
    //   247: dup
    //   248: iconst_2
    //   249: sipush 223
    //   252: invokestatic 71	java/lang/Character:valueOf	(C)Ljava/lang/Character;
    //   255: aastore
    //   256: dup
    //   257: iconst_3
    //   258: iconst_3
    //   259: invokestatic 71	java/lang/Character:valueOf	(C)Ljava/lang/Character;
    //   262: aastore
    //   263: invokevirtual 77	java/lang/reflect/Method:invoke	(Ljava/lang/Object;[Ljava/lang/Object;)Ljava/lang/Object;
    //   266: astore 6
    //   268: aload_0
    //   269: aload_1
    //   270: aload 6
    //   272: checkcast 55	java/lang/String
    //   275: invokevirtual 99	android/os/Bundle:getString	(Ljava/lang/String;)Ljava/lang/String;
    //   278: putfield 101	uuuuuu/vdvvdd:bcc0063006300630063006300630063	Ljava/lang/String;
    //   281: ldc 2
    //   283: ldc 103
    //   285: sipush 162
    //   288: sipush 158
    //   291: iconst_1
    //   292: invokestatic 51	xxxxxx/uxxxxx:bbbb0062b0062b0062b0062	(Ljava/lang/String;CCC)Ljava/lang/String;
    //   295: iconst_0
    //   296: anewarray 53	java/lang/Class
    //   299: invokevirtual 65	java/lang/Class:getMethod	(Ljava/lang/String;[Ljava/lang/Class;)Ljava/lang/reflect/Method;
    //   302: astore 6
    //   304: aload 6
    //   306: aconst_null
    //   307: iconst_0
    //   308: anewarray 4	java/lang/Object
    //   311: invokevirtual 77	java/lang/reflect/Method:invoke	(Ljava/lang/Object;[Ljava/lang/Object;)Ljava/lang/Object;
    //   314: astore 6
    //   316: aload 6
    //   318: checkcast 105	java/lang/Integer
    //   321: invokevirtual 108	java/lang/Integer:intValue	()I
    //   324: istore_2
    //   325: iload_2
    //   326: getstatic 110	uuuuuu/vdvvdd:bh0068hhhhhhh	I
    //   329: iload_2
    //   330: iadd
    //   331: imul
    //   332: getstatic 112	uuuuuu/vdvvdd:b00680068hhhhhhh	I
    //   335: irem
    //   336: tableswitch	default:+20->356, 0:+106->442
    //   356: ldc 2
    //   358: ldc 114
    //   360: sipush 148
    //   363: iconst_1
    //   364: invokestatic 118	xxxxxx/uxxxxx:bb00620062bb0062b0062b0062	(Ljava/lang/String;CC)Ljava/lang/String;
    //   367: iconst_0
    //   368: anewarray 53	java/lang/Class
    //   371: invokevirtual 65	java/lang/Class:getMethod	(Ljava/lang/String;[Ljava/lang/Class;)Ljava/lang/reflect/Method;
    //   374: astore 6
    //   376: aload 6
    //   378: aconst_null
    //   379: iconst_0
    //   380: anewarray 4	java/lang/Object
    //   383: invokevirtual 77	java/lang/reflect/Method:invoke	(Ljava/lang/Object;[Ljava/lang/Object;)Ljava/lang/Object;
    //   386: astore 6
    //   388: aload 6
    //   390: checkcast 105	java/lang/Integer
    //   393: invokevirtual 108	java/lang/Integer:intValue	()I
    //   396: putstatic 120	uuuuuu/vdvvdd:bc00630063006300630063006300630063	I
    //   399: ldc 2
    //   401: ldc 122
    //   403: sipush 223
    //   406: iconst_3
    //   407: invokestatic 118	xxxxxx/uxxxxx:bb00620062bb0062b0062b0062	(Ljava/lang/String;CC)Ljava/lang/String;
    //   410: iconst_0
    //   411: anewarray 53	java/lang/Class
    //   414: invokevirtual 65	java/lang/Class:getMethod	(Ljava/lang/String;[Ljava/lang/Class;)Ljava/lang/reflect/Method;
    //   417: astore 6
    //   419: aload 6
    //   421: aconst_null
    //   422: iconst_0
    //   423: anewarray 4	java/lang/Object
    //   426: invokevirtual 77	java/lang/reflect/Method:invoke	(Ljava/lang/Object;[Ljava/lang/Object;)Ljava/lang/Object;
    //   429: astore 6
    //   431: aload 6
    //   433: checkcast 105	java/lang/Integer
    //   436: invokevirtual 108	java/lang/Integer:intValue	()I
    //   439: putstatic 124	uuuuuu/vdvvdd:b0068hhhhhhhh	I
    //   442: aload_0
    //   443: aload_1
    //   444: putfield 126	uuuuuu/vdvvdd:b0063cc006300630063006300630063	Landroid/os/Bundle;
    //   447: getstatic 120	uuuuuu/vdvvdd:bc00630063006300630063006300630063	I
    //   450: istore_2
    //   451: getstatic 110	uuuuuu/vdvvdd:bh0068hhhhhhh	I
    //   454: istore_3
    //   455: getstatic 120	uuuuuu/vdvvdd:bc00630063006300630063006300630063	I
    //   458: istore 4
    //   460: getstatic 120	uuuuuu/vdvvdd:bc00630063006300630063006300630063	I
    //   463: istore 5
    //   465: iload 5
    //   467: getstatic 110	uuuuuu/vdvvdd:bh0068hhhhhhh	I
    //   470: iload 5
    //   472: iadd
    //   473: imul
    //   474: getstatic 112	uuuuuu/vdvvdd:b00680068hhhhhhh	I
    //   477: irem
    //   478: tableswitch	default:+18->496, 0:+28->506
    //   496: bipush 51
    //   498: putstatic 120	uuuuuu/vdvvdd:bc00630063006300630063006300630063	I
    //   501: bipush 72
    //   503: putstatic 124	uuuuuu/vdvvdd:b0068hhhhhhhh	I
    //   506: iload_2
    //   507: iload_3
    //   508: iadd
    //   509: iload 4
    //   511: imul
    //   512: getstatic 112	uuuuuu/vdvvdd:b00680068hhhhhhh	I
    //   515: irem
    //   516: getstatic 124	uuuuuu/vdvvdd:b0068hhhhhhhh	I
    //   519: if_icmpeq +89 -> 608
    //   522: bipush 77
    //   524: putstatic 120	uuuuuu/vdvvdd:bc00630063006300630063006300630063	I
    //   527: bipush 92
    //   529: putstatic 124	uuuuuu/vdvvdd:b0068hhhhhhhh	I
    //   532: getstatic 120	uuuuuu/vdvvdd:bc00630063006300630063006300630063	I
    //   535: istore_2
    //   536: iload_2
    //   537: getstatic 110	uuuuuu/vdvvdd:bh0068hhhhhhh	I
    //   540: iload_2
    //   541: iadd
    //   542: imul
    //   543: getstatic 112	uuuuuu/vdvvdd:b00680068hhhhhhh	I
    //   546: irem
    //   547: tableswitch	default:+17->564, 0:+61->608
    //   564: ldc 2
    //   566: ldc -128
    //   568: sipush 197
    //   571: iconst_3
    //   572: invokestatic 118	xxxxxx/uxxxxx:bb00620062bb0062b0062b0062	(Ljava/lang/String;CC)Ljava/lang/String;
    //   575: iconst_0
    //   576: anewarray 53	java/lang/Class
    //   579: invokevirtual 65	java/lang/Class:getMethod	(Ljava/lang/String;[Ljava/lang/Class;)Ljava/lang/reflect/Method;
    //   582: astore_1
    //   583: aload_1
    //   584: aconst_null
    //   585: iconst_0
    //   586: anewarray 4	java/lang/Object
    //   589: invokevirtual 77	java/lang/reflect/Method:invoke	(Ljava/lang/Object;[Ljava/lang/Object;)Ljava/lang/Object;
    //   592: astore_1
    //   593: aload_1
    //   594: checkcast 105	java/lang/Integer
    //   597: invokevirtual 108	java/lang/Integer:intValue	()I
    //   600: putstatic 120	uuuuuu/vdvvdd:bc00630063006300630063006300630063	I
    //   603: bipush 60
    //   605: putstatic 124	uuuuuu/vdvvdd:b0068hhhhhhhh	I
    //   608: return
    //   609: astore_1
    //   610: aload_1
    //   611: invokevirtual 132	java/lang/reflect/InvocationTargetException:getCause	()Ljava/lang/Throwable;
    //   614: athrow
    //   615: astore_1
    //   616: aload_1
    //   617: invokevirtual 132	java/lang/reflect/InvocationTargetException:getCause	()Ljava/lang/Throwable;
    //   620: athrow
    //   621: astore_1
    //   622: aload_1
    //   623: invokevirtual 132	java/lang/reflect/InvocationTargetException:getCause	()Ljava/lang/Throwable;
    //   626: athrow
    //   627: astore_1
    //   628: aload_1
    //   629: invokevirtual 132	java/lang/reflect/InvocationTargetException:getCause	()Ljava/lang/Throwable;
    //   632: athrow
    //   633: astore_1
    //   634: aload_1
    //   635: invokevirtual 132	java/lang/reflect/InvocationTargetException:getCause	()Ljava/lang/Throwable;
    //   638: athrow
    //   639: astore_1
    //   640: aload_1
    //   641: invokevirtual 132	java/lang/reflect/InvocationTargetException:getCause	()Ljava/lang/Throwable;
    //   644: athrow
    //   645: astore_1
    //   646: aload_1
    //   647: invokevirtual 132	java/lang/reflect/InvocationTargetException:getCause	()Ljava/lang/Throwable;
    //   650: athrow
    // Local variable table:
    //   start	length	slot	name	signature
    //   0	651	0	this	vdvvdd
    //   0	651	1	paramBundle	Bundle
    //   324	219	2	i	int
    //   454	55	3	j	int
    //   458	54	4	k	int
    //   463	11	5	m	int
    //   37	395	6	localObject	Object
    // Exception table:
    //   from	to	target	type
    //   304	316	609	java/lang/reflect/InvocationTargetException
    //   39	72	615	java/lang/reflect/InvocationTargetException
    //   129	170	621	java/lang/reflect/InvocationTargetException
    //   583	593	627	java/lang/reflect/InvocationTargetException
    //   227	268	633	java/lang/reflect/InvocationTargetException
    //   376	388	639	java/lang/reflect/InvocationTargetException
    //   419	431	645	java/lang/reflect/InvocationTargetException
  }
  
  /* Error */
  public void b00710071q0071q0071q00710071q()
  {
    // Byte code:
    //   0: getstatic 120	uuuuuu/vdvvdd:bc00630063006300630063006300630063	I
    //   3: istore_1
    //   4: getstatic 110	uuuuuu/vdvvdd:bh0068hhhhhhh	I
    //   7: istore_2
    //   8: getstatic 120	uuuuuu/vdvvdd:bc00630063006300630063006300630063	I
    //   11: istore_3
    //   12: getstatic 120	uuuuuu/vdvvdd:bc00630063006300630063006300630063	I
    //   15: istore 4
    //   17: getstatic 110	uuuuuu/vdvvdd:bh0068hhhhhhh	I
    //   20: istore 5
    //   22: ldc 2
    //   24: ldc -121
    //   26: bipush 8
    //   28: iconst_3
    //   29: invokestatic 118	xxxxxx/uxxxxx:bb00620062bb0062b0062b0062	(Ljava/lang/String;CC)Ljava/lang/String;
    //   32: iconst_0
    //   33: anewarray 53	java/lang/Class
    //   36: invokevirtual 65	java/lang/Class:getMethod	(Ljava/lang/String;[Ljava/lang/Class;)Ljava/lang/reflect/Method;
    //   39: astore 6
    //   41: aload 6
    //   43: aconst_null
    //   44: iconst_0
    //   45: anewarray 4	java/lang/Object
    //   48: invokevirtual 77	java/lang/reflect/Method:invoke	(Ljava/lang/Object;[Ljava/lang/Object;)Ljava/lang/Object;
    //   51: astore 6
    //   53: iload 5
    //   55: iload 4
    //   57: iadd
    //   58: iload 4
    //   60: imul
    //   61: aload 6
    //   63: checkcast 105	java/lang/Integer
    //   66: invokevirtual 108	java/lang/Integer:intValue	()I
    //   69: irem
    //   70: tableswitch	default:+18->88, 0:+106->176
    //   88: ldc 2
    //   90: ldc -119
    //   92: bipush 80
    //   94: sipush 200
    //   97: iconst_3
    //   98: invokestatic 51	xxxxxx/uxxxxx:bbbb0062b0062b0062b0062	(Ljava/lang/String;CCC)Ljava/lang/String;
    //   101: iconst_0
    //   102: anewarray 53	java/lang/Class
    //   105: invokevirtual 65	java/lang/Class:getMethod	(Ljava/lang/String;[Ljava/lang/Class;)Ljava/lang/reflect/Method;
    //   108: astore 6
    //   110: aload 6
    //   112: aconst_null
    //   113: iconst_0
    //   114: anewarray 4	java/lang/Object
    //   117: invokevirtual 77	java/lang/reflect/Method:invoke	(Ljava/lang/Object;[Ljava/lang/Object;)Ljava/lang/Object;
    //   120: astore 6
    //   122: aload 6
    //   124: checkcast 105	java/lang/Integer
    //   127: invokevirtual 108	java/lang/Integer:intValue	()I
    //   130: putstatic 120	uuuuuu/vdvvdd:bc00630063006300630063006300630063	I
    //   133: ldc 2
    //   135: ldc -117
    //   137: sipush 207
    //   140: iconst_1
    //   141: invokestatic 118	xxxxxx/uxxxxx:bb00620062bb0062b0062b0062	(Ljava/lang/String;CC)Ljava/lang/String;
    //   144: iconst_0
    //   145: anewarray 53	java/lang/Class
    //   148: invokevirtual 65	java/lang/Class:getMethod	(Ljava/lang/String;[Ljava/lang/Class;)Ljava/lang/reflect/Method;
    //   151: astore 6
    //   153: aload 6
    //   155: aconst_null
    //   156: iconst_0
    //   157: anewarray 4	java/lang/Object
    //   160: invokevirtual 77	java/lang/reflect/Method:invoke	(Ljava/lang/Object;[Ljava/lang/Object;)Ljava/lang/Object;
    //   163: astore 6
    //   165: aload 6
    //   167: checkcast 105	java/lang/Integer
    //   170: invokevirtual 108	java/lang/Integer:intValue	()I
    //   173: putstatic 124	uuuuuu/vdvvdd:b0068hhhhhhhh	I
    //   176: iload_3
    //   177: iload_1
    //   178: iload_2
    //   179: iadd
    //   180: imul
    //   181: getstatic 112	uuuuuu/vdvvdd:b00680068hhhhhhh	I
    //   184: irem
    //   185: getstatic 124	uuuuuu/vdvvdd:b0068hhhhhhhh	I
    //   188: if_icmpeq +13 -> 201
    //   191: bipush 79
    //   193: putstatic 120	uuuuuu/vdvvdd:bc00630063006300630063006300630063	I
    //   196: bipush 91
    //   198: putstatic 124	uuuuuu/vdvvdd:b0068hhhhhhhh	I
    //   201: new 141	uuuuuu/lloooo
    //   204: dup
    //   205: invokespecial 142	uuuuuu/lloooo:<init>	()V
    //   208: astore 6
    //   210: getstatic 120	uuuuuu/vdvvdd:bc00630063006300630063006300630063	I
    //   213: istore_1
    //   214: iload_1
    //   215: getstatic 110	uuuuuu/vdvvdd:bh0068hhhhhhh	I
    //   218: iload_1
    //   219: iadd
    //   220: imul
    //   221: getstatic 112	uuuuuu/vdvvdd:b00680068hhhhhhh	I
    //   224: irem
    //   225: tableswitch	default:+19->244, 0:+104->329
    //   244: ldc 2
    //   246: ldc -112
    //   248: bipush 65
    //   250: iconst_3
    //   251: invokestatic 118	xxxxxx/uxxxxx:bb00620062bb0062b0062b0062	(Ljava/lang/String;CC)Ljava/lang/String;
    //   254: iconst_0
    //   255: anewarray 53	java/lang/Class
    //   258: invokevirtual 65	java/lang/Class:getMethod	(Ljava/lang/String;[Ljava/lang/Class;)Ljava/lang/reflect/Method;
    //   261: astore 7
    //   263: aload 7
    //   265: aconst_null
    //   266: iconst_0
    //   267: anewarray 4	java/lang/Object
    //   270: invokevirtual 77	java/lang/reflect/Method:invoke	(Ljava/lang/Object;[Ljava/lang/Object;)Ljava/lang/Object;
    //   273: astore 7
    //   275: aload 7
    //   277: checkcast 105	java/lang/Integer
    //   280: invokevirtual 108	java/lang/Integer:intValue	()I
    //   283: putstatic 120	uuuuuu/vdvvdd:bc00630063006300630063006300630063	I
    //   286: ldc 2
    //   288: ldc -110
    //   290: sipush 184
    //   293: iconst_0
    //   294: invokestatic 118	xxxxxx/uxxxxx:bb00620062bb0062b0062b0062	(Ljava/lang/String;CC)Ljava/lang/String;
    //   297: iconst_0
    //   298: anewarray 53	java/lang/Class
    //   301: invokevirtual 65	java/lang/Class:getMethod	(Ljava/lang/String;[Ljava/lang/Class;)Ljava/lang/reflect/Method;
    //   304: astore 7
    //   306: aload 7
    //   308: aconst_null
    //   309: iconst_0
    //   310: anewarray 4	java/lang/Object
    //   313: invokevirtual 77	java/lang/reflect/Method:invoke	(Ljava/lang/Object;[Ljava/lang/Object;)Ljava/lang/Object;
    //   316: astore 7
    //   318: aload 7
    //   320: checkcast 105	java/lang/Integer
    //   323: invokevirtual 108	java/lang/Integer:intValue	()I
    //   326: putstatic 124	uuuuuu/vdvvdd:b0068hhhhhhhh	I
    //   329: aload_0
    //   330: getfield 101	uuuuuu/vdvvdd:bcc0063006300630063006300630063	Ljava/lang/String;
    //   333: iconst_0
    //   334: bipush 10
    //   336: invokevirtual 150	java/lang/String:substring	(II)Ljava/lang/String;
    //   339: astore 7
    //   341: new 152	java/lang/StringBuilder
    //   344: dup
    //   345: invokespecial 153	java/lang/StringBuilder:<init>	()V
    //   348: aload 7
    //   350: invokevirtual 157	java/lang/StringBuilder:append	(Ljava/lang/String;)Ljava/lang/StringBuilder;
    //   353: astore 7
    //   355: ldc 43
    //   357: ldc -97
    //   359: sipush 153
    //   362: iconst_1
    //   363: invokestatic 118	xxxxxx/uxxxxx:bb00620062bb0062b0062b0062	(Ljava/lang/String;CC)Ljava/lang/String;
    //   366: iconst_3
    //   367: anewarray 53	java/lang/Class
    //   370: dup
    //   371: iconst_0
    //   372: ldc 55
    //   374: aastore
    //   375: dup
    //   376: iconst_1
    //   377: getstatic 61	java/lang/Character:TYPE	Ljava/lang/Class;
    //   380: aastore
    //   381: dup
    //   382: iconst_2
    //   383: getstatic 61	java/lang/Character:TYPE	Ljava/lang/Class;
    //   386: aastore
    //   387: invokevirtual 65	java/lang/Class:getMethod	(Ljava/lang/String;[Ljava/lang/Class;)Ljava/lang/reflect/Method;
    //   390: astore 8
    //   392: aload 8
    //   394: aconst_null
    //   395: iconst_3
    //   396: anewarray 4	java/lang/Object
    //   399: dup
    //   400: iconst_0
    //   401: ldc -95
    //   403: aastore
    //   404: dup
    //   405: iconst_1
    //   406: sipush 251
    //   409: invokestatic 71	java/lang/Character:valueOf	(C)Ljava/lang/Character;
    //   412: aastore
    //   413: dup
    //   414: iconst_2
    //   415: iconst_4
    //   416: invokestatic 71	java/lang/Character:valueOf	(C)Ljava/lang/Character;
    //   419: aastore
    //   420: invokevirtual 77	java/lang/reflect/Method:invoke	(Ljava/lang/Object;[Ljava/lang/Object;)Ljava/lang/Object;
    //   423: astore 8
    //   425: aload 7
    //   427: aload 8
    //   429: checkcast 55	java/lang/String
    //   432: invokevirtual 157	java/lang/StringBuilder:append	(Ljava/lang/String;)Ljava/lang/StringBuilder;
    //   435: astore 7
    //   437: getstatic 120	uuuuuu/vdvvdd:bc00630063006300630063006300630063	I
    //   440: istore_1
    //   441: getstatic 110	uuuuuu/vdvvdd:bh0068hhhhhhh	I
    //   444: istore_2
    //   445: getstatic 120	uuuuuu/vdvvdd:bc00630063006300630063006300630063	I
    //   448: istore_3
    //   449: getstatic 112	uuuuuu/vdvvdd:b00680068hhhhhhh	I
    //   452: istore 4
    //   454: ldc 2
    //   456: ldc -93
    //   458: bipush 62
    //   460: iconst_1
    //   461: invokestatic 118	xxxxxx/uxxxxx:bb00620062bb0062b0062b0062	(Ljava/lang/String;CC)Ljava/lang/String;
    //   464: iconst_0
    //   465: anewarray 53	java/lang/Class
    //   468: invokevirtual 65	java/lang/Class:getMethod	(Ljava/lang/String;[Ljava/lang/Class;)Ljava/lang/reflect/Method;
    //   471: astore 8
    //   473: aload 8
    //   475: aconst_null
    //   476: iconst_0
    //   477: anewarray 4	java/lang/Object
    //   480: invokevirtual 77	java/lang/reflect/Method:invoke	(Ljava/lang/Object;[Ljava/lang/Object;)Ljava/lang/Object;
    //   483: astore 8
    //   485: iload_1
    //   486: iload_2
    //   487: iadd
    //   488: iload_3
    //   489: imul
    //   490: iload 4
    //   492: irem
    //   493: aload 8
    //   495: checkcast 105	java/lang/Integer
    //   498: invokevirtual 108	java/lang/Integer:intValue	()I
    //   501: if_icmpeq +13 -> 514
    //   504: bipush 57
    //   506: putstatic 120	uuuuuu/vdvvdd:bc00630063006300630063006300630063	I
    //   509: bipush 35
    //   511: putstatic 124	uuuuuu/vdvvdd:b0068hhhhhhhh	I
    //   514: aload 6
    //   516: aload 7
    //   518: invokevirtual 167	java/lang/StringBuilder:toString	()Ljava/lang/String;
    //   521: invokevirtual 171	uuuuuu/lloooo:bppp0070pp007000700070p	(Ljava/lang/String;)V
    //   524: return
    //   525: astore 6
    //   527: aload 6
    //   529: invokevirtual 132	java/lang/reflect/InvocationTargetException:getCause	()Ljava/lang/Throwable;
    //   532: athrow
    //   533: astore 6
    //   535: aload 6
    //   537: invokevirtual 132	java/lang/reflect/InvocationTargetException:getCause	()Ljava/lang/Throwable;
    //   540: athrow
    //   541: astore 6
    //   543: aload 6
    //   545: invokevirtual 132	java/lang/reflect/InvocationTargetException:getCause	()Ljava/lang/Throwable;
    //   548: athrow
    //   549: astore 6
    //   551: aload 6
    //   553: invokevirtual 132	java/lang/reflect/InvocationTargetException:getCause	()Ljava/lang/Throwable;
    //   556: athrow
    //   557: astore 6
    //   559: aload 6
    //   561: invokevirtual 132	java/lang/reflect/InvocationTargetException:getCause	()Ljava/lang/Throwable;
    //   564: athrow
    //   565: astore 6
    //   567: aload 6
    //   569: invokevirtual 132	java/lang/reflect/InvocationTargetException:getCause	()Ljava/lang/Throwable;
    //   572: athrow
    //   573: astore 6
    //   575: aload 6
    //   577: invokevirtual 132	java/lang/reflect/InvocationTargetException:getCause	()Ljava/lang/Throwable;
    //   580: athrow
    // Local variable table:
    //   start	length	slot	name	signature
    //   0	581	0	this	vdvvdd
    //   3	485	1	i	int
    //   7	481	2	j	int
    //   11	479	3	k	int
    //   15	478	4	m	int
    //   20	38	5	n	int
    //   39	476	6	localObject1	Object
    //   525	3	6	localInvocationTargetException1	java.lang.reflect.InvocationTargetException
    //   533	3	6	localInvocationTargetException2	java.lang.reflect.InvocationTargetException
    //   541	3	6	localInvocationTargetException3	java.lang.reflect.InvocationTargetException
    //   549	3	6	localInvocationTargetException4	java.lang.reflect.InvocationTargetException
    //   557	3	6	localInvocationTargetException5	java.lang.reflect.InvocationTargetException
    //   565	3	6	localInvocationTargetException6	java.lang.reflect.InvocationTargetException
    //   573	3	6	localInvocationTargetException7	java.lang.reflect.InvocationTargetException
    //   261	256	7	localObject2	Object
    //   390	104	8	localObject3	Object
    // Exception table:
    //   from	to	target	type
    //   41	53	525	java/lang/reflect/InvocationTargetException
    //   392	425	533	java/lang/reflect/InvocationTargetException
    //   473	485	541	java/lang/reflect/InvocationTargetException
    //   263	275	549	java/lang/reflect/InvocationTargetException
    //   153	165	557	java/lang/reflect/InvocationTargetException
    //   110	122	565	java/lang/reflect/InvocationTargetException
    //   306	318	573	java/lang/reflect/InvocationTargetException
  }
  
  /* Error */
  public boolean b0071q00710071q0071q00710071q()
  {
    // Byte code:
    //   0: aload_0
    //   1: getfield 85	uuuuuu/vdvvdd:bc0063c006300630063006300630063	Z
    //   4: istore 9
    //   6: ldc 2
    //   8: ldc -81
    //   10: sipush 240
    //   13: sipush 210
    //   16: iconst_2
    //   17: invokestatic 51	xxxxxx/uxxxxx:bbbb0062b0062b0062b0062	(Ljava/lang/String;CCC)Ljava/lang/String;
    //   20: iconst_0
    //   21: anewarray 53	java/lang/Class
    //   24: invokevirtual 65	java/lang/Class:getMethod	(Ljava/lang/String;[Ljava/lang/Class;)Ljava/lang/reflect/Method;
    //   27: astore 10
    //   29: aload 10
    //   31: aconst_null
    //   32: iconst_0
    //   33: anewarray 4	java/lang/Object
    //   36: invokevirtual 77	java/lang/reflect/Method:invoke	(Ljava/lang/Object;[Ljava/lang/Object;)Ljava/lang/Object;
    //   39: astore 10
    //   41: aload 10
    //   43: checkcast 105	java/lang/Integer
    //   46: invokevirtual 108	java/lang/Integer:intValue	()I
    //   49: istore_1
    //   50: getstatic 110	uuuuuu/vdvvdd:bh0068hhhhhhh	I
    //   53: istore_2
    //   54: ldc 2
    //   56: ldc -79
    //   58: sipush 200
    //   61: iconst_0
    //   62: invokestatic 118	xxxxxx/uxxxxx:bb00620062bb0062b0062b0062	(Ljava/lang/String;CC)Ljava/lang/String;
    //   65: iconst_0
    //   66: anewarray 53	java/lang/Class
    //   69: invokevirtual 65	java/lang/Class:getMethod	(Ljava/lang/String;[Ljava/lang/Class;)Ljava/lang/reflect/Method;
    //   72: astore 10
    //   74: aload 10
    //   76: aconst_null
    //   77: iconst_0
    //   78: anewarray 4	java/lang/Object
    //   81: invokevirtual 77	java/lang/reflect/Method:invoke	(Ljava/lang/Object;[Ljava/lang/Object;)Ljava/lang/Object;
    //   84: astore 10
    //   86: aload 10
    //   88: checkcast 105	java/lang/Integer
    //   91: invokevirtual 108	java/lang/Integer:intValue	()I
    //   94: istore_3
    //   95: getstatic 112	uuuuuu/vdvvdd:b00680068hhhhhhh	I
    //   98: istore 4
    //   100: getstatic 120	uuuuuu/vdvvdd:bc00630063006300630063006300630063	I
    //   103: istore 5
    //   105: getstatic 110	uuuuuu/vdvvdd:bh0068hhhhhhh	I
    //   108: istore 6
    //   110: getstatic 120	uuuuuu/vdvvdd:bc00630063006300630063006300630063	I
    //   113: istore 7
    //   115: getstatic 120	uuuuuu/vdvvdd:bc00630063006300630063006300630063	I
    //   118: istore 8
    //   120: iload 8
    //   122: getstatic 110	uuuuuu/vdvvdd:bh0068hhhhhhh	I
    //   125: iload 8
    //   127: iadd
    //   128: imul
    //   129: getstatic 112	uuuuuu/vdvvdd:b00680068hhhhhhh	I
    //   132: irem
    //   133: tableswitch	default:+19->152, 0:+66->199
    //   152: ldc 2
    //   154: ldc -77
    //   156: bipush 117
    //   158: iconst_0
    //   159: invokestatic 118	xxxxxx/uxxxxx:bb00620062bb0062b0062b0062	(Ljava/lang/String;CC)Ljava/lang/String;
    //   162: iconst_0
    //   163: anewarray 53	java/lang/Class
    //   166: invokevirtual 65	java/lang/Class:getMethod	(Ljava/lang/String;[Ljava/lang/Class;)Ljava/lang/reflect/Method;
    //   169: astore 10
    //   171: aload 10
    //   173: aconst_null
    //   174: iconst_0
    //   175: anewarray 4	java/lang/Object
    //   178: invokevirtual 77	java/lang/reflect/Method:invoke	(Ljava/lang/Object;[Ljava/lang/Object;)Ljava/lang/Object;
    //   181: astore 10
    //   183: aload 10
    //   185: checkcast 105	java/lang/Integer
    //   188: invokevirtual 108	java/lang/Integer:intValue	()I
    //   191: putstatic 120	uuuuuu/vdvvdd:bc00630063006300630063006300630063	I
    //   194: bipush 72
    //   196: putstatic 124	uuuuuu/vdvvdd:b0068hhhhhhhh	I
    //   199: iload 7
    //   201: iload 5
    //   203: iload 6
    //   205: iadd
    //   206: imul
    //   207: getstatic 112	uuuuuu/vdvvdd:b00680068hhhhhhh	I
    //   210: irem
    //   211: getstatic 124	uuuuuu/vdvvdd:b0068hhhhhhhh	I
    //   214: if_icmpeq +12 -> 226
    //   217: bipush 71
    //   219: putstatic 120	uuuuuu/vdvvdd:bc00630063006300630063006300630063	I
    //   222: iconst_2
    //   223: putstatic 124	uuuuuu/vdvvdd:b0068hhhhhhhh	I
    //   226: iload_3
    //   227: iload_2
    //   228: iload_1
    //   229: iadd
    //   230: imul
    //   231: iload 4
    //   233: irem
    //   234: getstatic 124	uuuuuu/vdvvdd:b0068hhhhhhhh	I
    //   237: if_icmpeq +13 -> 250
    //   240: bipush 80
    //   242: putstatic 120	uuuuuu/vdvvdd:bc00630063006300630063006300630063	I
    //   245: bipush 86
    //   247: putstatic 124	uuuuuu/vdvvdd:b0068hhhhhhhh	I
    //   250: getstatic 120	uuuuuu/vdvvdd:bc00630063006300630063006300630063	I
    //   253: istore_1
    //   254: iload_1
    //   255: getstatic 110	uuuuuu/vdvvdd:bh0068hhhhhhh	I
    //   258: iload_1
    //   259: iadd
    //   260: imul
    //   261: getstatic 112	uuuuuu/vdvvdd:b00680068hhhhhhh	I
    //   264: irem
    //   265: tableswitch	default:+19->284, 0:+70->335
    //   284: ldc 2
    //   286: ldc -75
    //   288: sipush 161
    //   291: sipush 141
    //   294: iconst_2
    //   295: invokestatic 51	xxxxxx/uxxxxx:bbbb0062b0062b0062b0062	(Ljava/lang/String;CCC)Ljava/lang/String;
    //   298: iconst_0
    //   299: anewarray 53	java/lang/Class
    //   302: invokevirtual 65	java/lang/Class:getMethod	(Ljava/lang/String;[Ljava/lang/Class;)Ljava/lang/reflect/Method;
    //   305: astore 10
    //   307: aload 10
    //   309: aconst_null
    //   310: iconst_0
    //   311: anewarray 4	java/lang/Object
    //   314: invokevirtual 77	java/lang/reflect/Method:invoke	(Ljava/lang/Object;[Ljava/lang/Object;)Ljava/lang/Object;
    //   317: astore 10
    //   319: aload 10
    //   321: checkcast 105	java/lang/Integer
    //   324: invokevirtual 108	java/lang/Integer:intValue	()I
    //   327: putstatic 120	uuuuuu/vdvvdd:bc00630063006300630063006300630063	I
    //   330: bipush 9
    //   332: putstatic 124	uuuuuu/vdvvdd:b0068hhhhhhhh	I
    //   335: iload 9
    //   337: ireturn
    //   338: astore 10
    //   340: aload 10
    //   342: invokevirtual 132	java/lang/reflect/InvocationTargetException:getCause	()Ljava/lang/Throwable;
    //   345: athrow
    //   346: astore 10
    //   348: aload 10
    //   350: invokevirtual 132	java/lang/reflect/InvocationTargetException:getCause	()Ljava/lang/Throwable;
    //   353: athrow
    //   354: astore 10
    //   356: aload 10
    //   358: invokevirtual 132	java/lang/reflect/InvocationTargetException:getCause	()Ljava/lang/Throwable;
    //   361: athrow
    //   362: astore 10
    //   364: aload 10
    //   366: invokevirtual 132	java/lang/reflect/InvocationTargetException:getCause	()Ljava/lang/Throwable;
    //   369: athrow
    // Local variable table:
    //   start	length	slot	name	signature
    //   0	370	0	this	vdvvdd
    //   49	212	1	i	int
    //   53	177	2	j	int
    //   94	137	3	k	int
    //   98	136	4	m	int
    //   103	103	5	n	int
    //   108	98	6	i1	int
    //   113	94	7	i2	int
    //   118	11	8	i3	int
    //   4	332	9	bool	boolean
    //   27	293	10	localObject	Object
    //   338	3	10	localInvocationTargetException1	java.lang.reflect.InvocationTargetException
    //   346	3	10	localInvocationTargetException2	java.lang.reflect.InvocationTargetException
    //   354	3	10	localInvocationTargetException3	java.lang.reflect.InvocationTargetException
    //   362	3	10	localInvocationTargetException4	java.lang.reflect.InvocationTargetException
    // Exception table:
    //   from	to	target	type
    //   307	319	338	java/lang/reflect/InvocationTargetException
    //   29	41	346	java/lang/reflect/InvocationTargetException
    //   74	86	354	java/lang/reflect/InvocationTargetException
    //   171	183	362	java/lang/reflect/InvocationTargetException
  }
  
  /* Error */
  public boolean bq007100710071q0071q00710071q()
  {
    // Byte code:
    //   0: getstatic 120	uuuuuu/vdvvdd:bc00630063006300630063006300630063	I
    //   3: istore_1
    //   4: getstatic 110	uuuuuu/vdvvdd:bh0068hhhhhhh	I
    //   7: istore_2
    //   8: getstatic 120	uuuuuu/vdvvdd:bc00630063006300630063006300630063	I
    //   11: istore_3
    //   12: ldc 2
    //   14: ldc -72
    //   16: sipush 186
    //   19: iconst_0
    //   20: invokestatic 118	xxxxxx/uxxxxx:bb00620062bb0062b0062b0062	(Ljava/lang/String;CC)Ljava/lang/String;
    //   23: iconst_0
    //   24: anewarray 53	java/lang/Class
    //   27: invokevirtual 65	java/lang/Class:getMethod	(Ljava/lang/String;[Ljava/lang/Class;)Ljava/lang/reflect/Method;
    //   30: astore 4
    //   32: aload 4
    //   34: aconst_null
    //   35: iconst_0
    //   36: anewarray 4	java/lang/Object
    //   39: invokevirtual 77	java/lang/reflect/Method:invoke	(Ljava/lang/Object;[Ljava/lang/Object;)Ljava/lang/Object;
    //   42: astore 4
    //   44: iload_3
    //   45: iload_1
    //   46: iload_2
    //   47: iadd
    //   48: imul
    //   49: aload 4
    //   51: checkcast 105	java/lang/Integer
    //   54: invokevirtual 108	java/lang/Integer:intValue	()I
    //   57: irem
    //   58: getstatic 124	uuuuuu/vdvvdd:b0068hhhhhhhh	I
    //   61: if_icmpeq +387 -> 448
    //   64: getstatic 120	uuuuuu/vdvvdd:bc00630063006300630063006300630063	I
    //   67: istore_1
    //   68: ldc 2
    //   70: ldc -70
    //   72: bipush 117
    //   74: iconst_5
    //   75: invokestatic 118	xxxxxx/uxxxxx:bb00620062bb0062b0062b0062	(Ljava/lang/String;CC)Ljava/lang/String;
    //   78: iconst_0
    //   79: anewarray 53	java/lang/Class
    //   82: invokevirtual 65	java/lang/Class:getMethod	(Ljava/lang/String;[Ljava/lang/Class;)Ljava/lang/reflect/Method;
    //   85: astore 4
    //   87: aload 4
    //   89: aconst_null
    //   90: iconst_0
    //   91: anewarray 4	java/lang/Object
    //   94: invokevirtual 77	java/lang/reflect/Method:invoke	(Ljava/lang/Object;[Ljava/lang/Object;)Ljava/lang/Object;
    //   97: astore 4
    //   99: aload 4
    //   101: checkcast 105	java/lang/Integer
    //   104: invokevirtual 108	java/lang/Integer:intValue	()I
    //   107: iload_1
    //   108: iadd
    //   109: getstatic 120	uuuuuu/vdvvdd:bc00630063006300630063006300630063	I
    //   112: imul
    //   113: getstatic 112	uuuuuu/vdvvdd:b00680068hhhhhhh	I
    //   116: irem
    //   117: getstatic 124	uuuuuu/vdvvdd:b0068hhhhhhhh	I
    //   120: if_icmpeq +169 -> 289
    //   123: ldc 2
    //   125: ldc -112
    //   127: sipush 223
    //   130: iconst_4
    //   131: invokestatic 118	xxxxxx/uxxxxx:bb00620062bb0062b0062b0062	(Ljava/lang/String;CC)Ljava/lang/String;
    //   134: iconst_0
    //   135: anewarray 53	java/lang/Class
    //   138: invokevirtual 65	java/lang/Class:getMethod	(Ljava/lang/String;[Ljava/lang/Class;)Ljava/lang/reflect/Method;
    //   141: astore 4
    //   143: aload 4
    //   145: aconst_null
    //   146: iconst_0
    //   147: anewarray 4	java/lang/Object
    //   150: invokevirtual 77	java/lang/reflect/Method:invoke	(Ljava/lang/Object;[Ljava/lang/Object;)Ljava/lang/Object;
    //   153: astore 4
    //   155: aload 4
    //   157: checkcast 105	java/lang/Integer
    //   160: invokevirtual 108	java/lang/Integer:intValue	()I
    //   163: istore_1
    //   164: iload_1
    //   165: getstatic 110	uuuuuu/vdvvdd:bh0068hhhhhhh	I
    //   168: iload_1
    //   169: iadd
    //   170: imul
    //   171: getstatic 112	uuuuuu/vdvvdd:b00680068hhhhhhh	I
    //   174: irem
    //   175: tableswitch	default:+17->192, 0:+104->279
    //   192: ldc 2
    //   194: ldc -79
    //   196: sipush 227
    //   199: bipush 119
    //   201: iconst_3
    //   202: invokestatic 51	xxxxxx/uxxxxx:bbbb0062b0062b0062b0062	(Ljava/lang/String;CCC)Ljava/lang/String;
    //   205: iconst_0
    //   206: anewarray 53	java/lang/Class
    //   209: invokevirtual 65	java/lang/Class:getMethod	(Ljava/lang/String;[Ljava/lang/Class;)Ljava/lang/reflect/Method;
    //   212: astore 4
    //   214: aload 4
    //   216: aconst_null
    //   217: iconst_0
    //   218: anewarray 4	java/lang/Object
    //   221: invokevirtual 77	java/lang/reflect/Method:invoke	(Ljava/lang/Object;[Ljava/lang/Object;)Ljava/lang/Object;
    //   224: astore 4
    //   226: aload 4
    //   228: checkcast 105	java/lang/Integer
    //   231: invokevirtual 108	java/lang/Integer:intValue	()I
    //   234: putstatic 120	uuuuuu/vdvvdd:bc00630063006300630063006300630063	I
    //   237: ldc 2
    //   239: ldc -68
    //   241: bipush 98
    //   243: iconst_1
    //   244: invokestatic 118	xxxxxx/uxxxxx:bb00620062bb0062b0062b0062	(Ljava/lang/String;CC)Ljava/lang/String;
    //   247: iconst_0
    //   248: anewarray 53	java/lang/Class
    //   251: invokevirtual 65	java/lang/Class:getMethod	(Ljava/lang/String;[Ljava/lang/Class;)Ljava/lang/reflect/Method;
    //   254: astore 4
    //   256: aload 4
    //   258: aconst_null
    //   259: iconst_0
    //   260: anewarray 4	java/lang/Object
    //   263: invokevirtual 77	java/lang/reflect/Method:invoke	(Ljava/lang/Object;[Ljava/lang/Object;)Ljava/lang/Object;
    //   266: astore 4
    //   268: aload 4
    //   270: checkcast 105	java/lang/Integer
    //   273: invokevirtual 108	java/lang/Integer:intValue	()I
    //   276: putstatic 124	uuuuuu/vdvvdd:b0068hhhhhhhh	I
    //   279: bipush 8
    //   281: putstatic 120	uuuuuu/vdvvdd:bc00630063006300630063006300630063	I
    //   284: bipush 62
    //   286: putstatic 124	uuuuuu/vdvvdd:b0068hhhhhhhh	I
    //   289: bipush 90
    //   291: putstatic 120	uuuuuu/vdvvdd:bc00630063006300630063006300630063	I
    //   294: ldc 2
    //   296: ldc -66
    //   298: bipush 110
    //   300: sipush 218
    //   303: iconst_0
    //   304: invokestatic 51	xxxxxx/uxxxxx:bbbb0062b0062b0062b0062	(Ljava/lang/String;CCC)Ljava/lang/String;
    //   307: iconst_0
    //   308: anewarray 53	java/lang/Class
    //   311: invokevirtual 65	java/lang/Class:getMethod	(Ljava/lang/String;[Ljava/lang/Class;)Ljava/lang/reflect/Method;
    //   314: astore 4
    //   316: aload 4
    //   318: aconst_null
    //   319: iconst_0
    //   320: anewarray 4	java/lang/Object
    //   323: invokevirtual 77	java/lang/reflect/Method:invoke	(Ljava/lang/Object;[Ljava/lang/Object;)Ljava/lang/Object;
    //   326: astore 4
    //   328: aload 4
    //   330: checkcast 105	java/lang/Integer
    //   333: invokevirtual 108	java/lang/Integer:intValue	()I
    //   336: putstatic 124	uuuuuu/vdvvdd:b0068hhhhhhhh	I
    //   339: getstatic 120	uuuuuu/vdvvdd:bc00630063006300630063006300630063	I
    //   342: istore_1
    //   343: ldc 2
    //   345: ldc -64
    //   347: sipush 192
    //   350: iconst_5
    //   351: invokestatic 118	xxxxxx/uxxxxx:bb00620062bb0062b0062b0062	(Ljava/lang/String;CC)Ljava/lang/String;
    //   354: iconst_0
    //   355: anewarray 53	java/lang/Class
    //   358: invokevirtual 65	java/lang/Class:getMethod	(Ljava/lang/String;[Ljava/lang/Class;)Ljava/lang/reflect/Method;
    //   361: astore 4
    //   363: aload 4
    //   365: aconst_null
    //   366: iconst_0
    //   367: anewarray 4	java/lang/Object
    //   370: invokevirtual 77	java/lang/reflect/Method:invoke	(Ljava/lang/Object;[Ljava/lang/Object;)Ljava/lang/Object;
    //   373: astore 4
    //   375: aload 4
    //   377: checkcast 105	java/lang/Integer
    //   380: invokevirtual 108	java/lang/Integer:intValue	()I
    //   383: iload_1
    //   384: iadd
    //   385: getstatic 120	uuuuuu/vdvvdd:bc00630063006300630063006300630063	I
    //   388: imul
    //   389: getstatic 112	uuuuuu/vdvvdd:b00680068hhhhhhh	I
    //   392: irem
    //   393: getstatic 124	uuuuuu/vdvvdd:b0068hhhhhhhh	I
    //   396: if_icmpeq +52 -> 448
    //   399: bipush 53
    //   401: putstatic 120	uuuuuu/vdvvdd:bc00630063006300630063006300630063	I
    //   404: ldc 2
    //   406: ldc -62
    //   408: bipush 125
    //   410: bipush 111
    //   412: iconst_0
    //   413: invokestatic 51	xxxxxx/uxxxxx:bbbb0062b0062b0062b0062	(Ljava/lang/String;CCC)Ljava/lang/String;
    //   416: iconst_0
    //   417: anewarray 53	java/lang/Class
    //   420: invokevirtual 65	java/lang/Class:getMethod	(Ljava/lang/String;[Ljava/lang/Class;)Ljava/lang/reflect/Method;
    //   423: astore 4
    //   425: aload 4
    //   427: aconst_null
    //   428: iconst_0
    //   429: anewarray 4	java/lang/Object
    //   432: invokevirtual 77	java/lang/reflect/Method:invoke	(Ljava/lang/Object;[Ljava/lang/Object;)Ljava/lang/Object;
    //   435: astore 4
    //   437: aload 4
    //   439: checkcast 105	java/lang/Integer
    //   442: invokevirtual 108	java/lang/Integer:intValue	()I
    //   445: putstatic 124	uuuuuu/vdvvdd:b0068hhhhhhhh	I
    //   448: aload_0
    //   449: getfield 91	uuuuuu/vdvvdd:b00630063c006300630063006300630063	Z
    //   452: ireturn
    //   453: astore 4
    //   455: aload 4
    //   457: invokevirtual 132	java/lang/reflect/InvocationTargetException:getCause	()Ljava/lang/Throwable;
    //   460: athrow
    //   461: astore 4
    //   463: aload 4
    //   465: invokevirtual 132	java/lang/reflect/InvocationTargetException:getCause	()Ljava/lang/Throwable;
    //   468: athrow
    //   469: astore 4
    //   471: aload 4
    //   473: invokevirtual 132	java/lang/reflect/InvocationTargetException:getCause	()Ljava/lang/Throwable;
    //   476: athrow
    //   477: astore 4
    //   479: aload 4
    //   481: invokevirtual 132	java/lang/reflect/InvocationTargetException:getCause	()Ljava/lang/Throwable;
    //   484: athrow
    //   485: astore 4
    //   487: aload 4
    //   489: invokevirtual 132	java/lang/reflect/InvocationTargetException:getCause	()Ljava/lang/Throwable;
    //   492: athrow
    //   493: astore 4
    //   495: aload 4
    //   497: invokevirtual 132	java/lang/reflect/InvocationTargetException:getCause	()Ljava/lang/Throwable;
    //   500: athrow
    //   501: astore 4
    //   503: aload 4
    //   505: invokevirtual 132	java/lang/reflect/InvocationTargetException:getCause	()Ljava/lang/Throwable;
    //   508: athrow
    //   509: astore 4
    //   511: aload 4
    //   513: invokevirtual 132	java/lang/reflect/InvocationTargetException:getCause	()Ljava/lang/Throwable;
    //   516: athrow
    // Local variable table:
    //   start	length	slot	name	signature
    //   0	517	0	this	vdvvdd
    //   3	382	1	i	int
    //   7	41	2	j	int
    //   11	38	3	k	int
    //   30	408	4	localObject	Object
    //   453	3	4	localInvocationTargetException1	java.lang.reflect.InvocationTargetException
    //   461	3	4	localInvocationTargetException2	java.lang.reflect.InvocationTargetException
    //   469	3	4	localInvocationTargetException3	java.lang.reflect.InvocationTargetException
    //   477	3	4	localInvocationTargetException4	java.lang.reflect.InvocationTargetException
    //   485	3	4	localInvocationTargetException5	java.lang.reflect.InvocationTargetException
    //   493	3	4	localInvocationTargetException6	java.lang.reflect.InvocationTargetException
    //   501	3	4	localInvocationTargetException7	java.lang.reflect.InvocationTargetException
    //   509	3	4	localInvocationTargetException8	java.lang.reflect.InvocationTargetException
    // Exception table:
    //   from	to	target	type
    //   32	44	453	java/lang/reflect/InvocationTargetException
    //   425	437	461	java/lang/reflect/InvocationTargetException
    //   87	99	469	java/lang/reflect/InvocationTargetException
    //   143	155	477	java/lang/reflect/InvocationTargetException
    //   316	328	485	java/lang/reflect/InvocationTargetException
    //   363	375	493	java/lang/reflect/InvocationTargetException
    //   214	226	501	java/lang/reflect/InvocationTargetException
    //   256	268	509	java/lang/reflect/InvocationTargetException
  }
  
  /* Error */
  public Bundle bqq00710071q0071q00710071q()
  {
    // Byte code:
    //   0: aload_0
    //   1: getfield 126	uuuuuu/vdvvdd:b0063cc006300630063006300630063	Landroid/os/Bundle;
    //   4: astore_3
    //   5: ldc 2
    //   7: ldc -58
    //   9: sipush 154
    //   12: iconst_2
    //   13: invokestatic 118	xxxxxx/uxxxxx:bb00620062bb0062b0062b0062	(Ljava/lang/String;CC)Ljava/lang/String;
    //   16: iconst_0
    //   17: anewarray 53	java/lang/Class
    //   20: invokevirtual 65	java/lang/Class:getMethod	(Ljava/lang/String;[Ljava/lang/Class;)Ljava/lang/reflect/Method;
    //   23: astore 4
    //   25: aload 4
    //   27: aconst_null
    //   28: iconst_0
    //   29: anewarray 4	java/lang/Object
    //   32: invokevirtual 77	java/lang/reflect/Method:invoke	(Ljava/lang/Object;[Ljava/lang/Object;)Ljava/lang/Object;
    //   35: astore 4
    //   37: aload 4
    //   39: checkcast 105	java/lang/Integer
    //   42: invokevirtual 108	java/lang/Integer:intValue	()I
    //   45: istore_1
    //   46: iload_1
    //   47: getstatic 110	uuuuuu/vdvvdd:bh0068hhhhhhh	I
    //   50: iload_1
    //   51: iadd
    //   52: imul
    //   53: getstatic 112	uuuuuu/vdvvdd:b00680068hhhhhhh	I
    //   56: irem
    //   57: tableswitch	default:+19->76, 0:+498->555
    //   76: getstatic 120	uuuuuu/vdvvdd:bc00630063006300630063006300630063	I
    //   79: istore_1
    //   80: ldc 2
    //   82: ldc -56
    //   84: bipush 94
    //   86: bipush 73
    //   88: iconst_0
    //   89: invokestatic 51	xxxxxx/uxxxxx:bbbb0062b0062b0062b0062	(Ljava/lang/String;CCC)Ljava/lang/String;
    //   92: iconst_0
    //   93: anewarray 53	java/lang/Class
    //   96: invokevirtual 65	java/lang/Class:getMethod	(Ljava/lang/String;[Ljava/lang/Class;)Ljava/lang/reflect/Method;
    //   99: astore 4
    //   101: aload 4
    //   103: aconst_null
    //   104: iconst_0
    //   105: anewarray 4	java/lang/Object
    //   108: invokevirtual 77	java/lang/reflect/Method:invoke	(Ljava/lang/Object;[Ljava/lang/Object;)Ljava/lang/Object;
    //   111: astore 4
    //   113: aload 4
    //   115: checkcast 105	java/lang/Integer
    //   118: invokevirtual 108	java/lang/Integer:intValue	()I
    //   121: iload_1
    //   122: iadd
    //   123: getstatic 120	uuuuuu/vdvvdd:bc00630063006300630063006300630063	I
    //   126: imul
    //   127: getstatic 112	uuuuuu/vdvvdd:b00680068hhhhhhh	I
    //   130: irem
    //   131: getstatic 124	uuuuuu/vdvvdd:b0068hhhhhhhh	I
    //   134: if_icmpeq +373 -> 507
    //   137: getstatic 120	uuuuuu/vdvvdd:bc00630063006300630063006300630063	I
    //   140: istore_1
    //   141: getstatic 110	uuuuuu/vdvvdd:bh0068hhhhhhh	I
    //   144: istore_2
    //   145: ldc 2
    //   147: ldc -54
    //   149: sipush 148
    //   152: bipush 16
    //   154: iconst_0
    //   155: invokestatic 51	xxxxxx/uxxxxx:bbbb0062b0062b0062b0062	(Ljava/lang/String;CCC)Ljava/lang/String;
    //   158: iconst_0
    //   159: anewarray 53	java/lang/Class
    //   162: invokevirtual 65	java/lang/Class:getMethod	(Ljava/lang/String;[Ljava/lang/Class;)Ljava/lang/reflect/Method;
    //   165: astore 4
    //   167: aload 4
    //   169: aconst_null
    //   170: iconst_0
    //   171: anewarray 4	java/lang/Object
    //   174: invokevirtual 77	java/lang/reflect/Method:invoke	(Ljava/lang/Object;[Ljava/lang/Object;)Ljava/lang/Object;
    //   177: astore 4
    //   179: iload_2
    //   180: iload_1
    //   181: iadd
    //   182: iload_1
    //   183: imul
    //   184: aload 4
    //   186: checkcast 105	java/lang/Integer
    //   189: invokevirtual 108	java/lang/Integer:intValue	()I
    //   192: irem
    //   193: tableswitch	default:+19->212, 0:+103->296
    //   212: ldc 2
    //   214: ldc -52
    //   216: bipush 91
    //   218: iconst_1
    //   219: invokestatic 118	xxxxxx/uxxxxx:bb00620062bb0062b0062b0062	(Ljava/lang/String;CC)Ljava/lang/String;
    //   222: iconst_0
    //   223: anewarray 53	java/lang/Class
    //   226: invokevirtual 65	java/lang/Class:getMethod	(Ljava/lang/String;[Ljava/lang/Class;)Ljava/lang/reflect/Method;
    //   229: astore 4
    //   231: aload 4
    //   233: aconst_null
    //   234: iconst_0
    //   235: anewarray 4	java/lang/Object
    //   238: invokevirtual 77	java/lang/reflect/Method:invoke	(Ljava/lang/Object;[Ljava/lang/Object;)Ljava/lang/Object;
    //   241: astore 4
    //   243: aload 4
    //   245: checkcast 105	java/lang/Integer
    //   248: invokevirtual 108	java/lang/Integer:intValue	()I
    //   251: putstatic 120	uuuuuu/vdvvdd:bc00630063006300630063006300630063	I
    //   254: ldc 2
    //   256: ldc -50
    //   258: bipush 94
    //   260: iconst_4
    //   261: invokestatic 118	xxxxxx/uxxxxx:bb00620062bb0062b0062b0062	(Ljava/lang/String;CC)Ljava/lang/String;
    //   264: iconst_0
    //   265: anewarray 53	java/lang/Class
    //   268: invokevirtual 65	java/lang/Class:getMethod	(Ljava/lang/String;[Ljava/lang/Class;)Ljava/lang/reflect/Method;
    //   271: astore 4
    //   273: aload 4
    //   275: aconst_null
    //   276: iconst_0
    //   277: anewarray 4	java/lang/Object
    //   280: invokevirtual 77	java/lang/reflect/Method:invoke	(Ljava/lang/Object;[Ljava/lang/Object;)Ljava/lang/Object;
    //   283: astore 4
    //   285: aload 4
    //   287: checkcast 105	java/lang/Integer
    //   290: invokevirtual 108	java/lang/Integer:intValue	()I
    //   293: putstatic 124	uuuuuu/vdvvdd:b0068hhhhhhhh	I
    //   296: ldc 2
    //   298: ldc -48
    //   300: sipush 186
    //   303: sipush 140
    //   306: iconst_3
    //   307: invokestatic 51	xxxxxx/uxxxxx:bbbb0062b0062b0062b0062	(Ljava/lang/String;CCC)Ljava/lang/String;
    //   310: iconst_0
    //   311: anewarray 53	java/lang/Class
    //   314: invokevirtual 65	java/lang/Class:getMethod	(Ljava/lang/String;[Ljava/lang/Class;)Ljava/lang/reflect/Method;
    //   317: astore 4
    //   319: aload 4
    //   321: aconst_null
    //   322: iconst_0
    //   323: anewarray 4	java/lang/Object
    //   326: invokevirtual 77	java/lang/reflect/Method:invoke	(Ljava/lang/Object;[Ljava/lang/Object;)Ljava/lang/Object;
    //   329: astore 4
    //   331: aload 4
    //   333: checkcast 105	java/lang/Integer
    //   336: invokevirtual 108	java/lang/Integer:intValue	()I
    //   339: putstatic 120	uuuuuu/vdvvdd:bc00630063006300630063006300630063	I
    //   342: bipush 65
    //   344: putstatic 124	uuuuuu/vdvvdd:b0068hhhhhhhh	I
    //   347: ldc 2
    //   349: ldc -46
    //   351: bipush 74
    //   353: sipush 182
    //   356: iconst_1
    //   357: invokestatic 51	xxxxxx/uxxxxx:bbbb0062b0062b0062b0062	(Ljava/lang/String;CCC)Ljava/lang/String;
    //   360: iconst_0
    //   361: anewarray 53	java/lang/Class
    //   364: invokevirtual 65	java/lang/Class:getMethod	(Ljava/lang/String;[Ljava/lang/Class;)Ljava/lang/reflect/Method;
    //   367: astore 4
    //   369: aload 4
    //   371: aconst_null
    //   372: iconst_0
    //   373: anewarray 4	java/lang/Object
    //   376: invokevirtual 77	java/lang/reflect/Method:invoke	(Ljava/lang/Object;[Ljava/lang/Object;)Ljava/lang/Object;
    //   379: astore 4
    //   381: aload 4
    //   383: checkcast 105	java/lang/Integer
    //   386: invokevirtual 108	java/lang/Integer:intValue	()I
    //   389: istore_1
    //   390: iload_1
    //   391: getstatic 110	uuuuuu/vdvvdd:bh0068hhhhhhh	I
    //   394: iload_1
    //   395: iadd
    //   396: imul
    //   397: getstatic 112	uuuuuu/vdvvdd:b00680068hhhhhhh	I
    //   400: irem
    //   401: tableswitch	default:+19->420, 0:+106->507
    //   420: ldc 2
    //   422: ldc -44
    //   424: sipush 167
    //   427: iconst_0
    //   428: invokestatic 118	xxxxxx/uxxxxx:bb00620062bb0062b0062b0062	(Ljava/lang/String;CC)Ljava/lang/String;
    //   431: iconst_0
    //   432: anewarray 53	java/lang/Class
    //   435: invokevirtual 65	java/lang/Class:getMethod	(Ljava/lang/String;[Ljava/lang/Class;)Ljava/lang/reflect/Method;
    //   438: astore 4
    //   440: aload 4
    //   442: aconst_null
    //   443: iconst_0
    //   444: anewarray 4	java/lang/Object
    //   447: invokevirtual 77	java/lang/reflect/Method:invoke	(Ljava/lang/Object;[Ljava/lang/Object;)Ljava/lang/Object;
    //   450: astore 4
    //   452: aload 4
    //   454: checkcast 105	java/lang/Integer
    //   457: invokevirtual 108	java/lang/Integer:intValue	()I
    //   460: putstatic 120	uuuuuu/vdvvdd:bc00630063006300630063006300630063	I
    //   463: ldc 2
    //   465: ldc -42
    //   467: bipush 18
    //   469: bipush 117
    //   471: iconst_3
    //   472: invokestatic 51	xxxxxx/uxxxxx:bbbb0062b0062b0062b0062	(Ljava/lang/String;CCC)Ljava/lang/String;
    //   475: iconst_0
    //   476: anewarray 53	java/lang/Class
    //   479: invokevirtual 65	java/lang/Class:getMethod	(Ljava/lang/String;[Ljava/lang/Class;)Ljava/lang/reflect/Method;
    //   482: astore 4
    //   484: aload 4
    //   486: aconst_null
    //   487: iconst_0
    //   488: anewarray 4	java/lang/Object
    //   491: invokevirtual 77	java/lang/reflect/Method:invoke	(Ljava/lang/Object;[Ljava/lang/Object;)Ljava/lang/Object;
    //   494: astore 4
    //   496: aload 4
    //   498: checkcast 105	java/lang/Integer
    //   501: invokevirtual 108	java/lang/Integer:intValue	()I
    //   504: putstatic 124	uuuuuu/vdvvdd:b0068hhhhhhhh	I
    //   507: bipush 96
    //   509: putstatic 120	uuuuuu/vdvvdd:bc00630063006300630063006300630063	I
    //   512: ldc 2
    //   514: ldc -40
    //   516: sipush 243
    //   519: iconst_2
    //   520: invokestatic 118	xxxxxx/uxxxxx:bb00620062bb0062b0062b0062	(Ljava/lang/String;CC)Ljava/lang/String;
    //   523: iconst_0
    //   524: anewarray 53	java/lang/Class
    //   527: invokevirtual 65	java/lang/Class:getMethod	(Ljava/lang/String;[Ljava/lang/Class;)Ljava/lang/reflect/Method;
    //   530: astore 4
    //   532: aload 4
    //   534: aconst_null
    //   535: iconst_0
    //   536: anewarray 4	java/lang/Object
    //   539: invokevirtual 77	java/lang/reflect/Method:invoke	(Ljava/lang/Object;[Ljava/lang/Object;)Ljava/lang/Object;
    //   542: astore 4
    //   544: aload 4
    //   546: checkcast 105	java/lang/Integer
    //   549: invokevirtual 108	java/lang/Integer:intValue	()I
    //   552: putstatic 124	uuuuuu/vdvvdd:b0068hhhhhhhh	I
    //   555: aload_3
    //   556: areturn
    //   557: astore_3
    //   558: aload_3
    //   559: invokevirtual 132	java/lang/reflect/InvocationTargetException:getCause	()Ljava/lang/Throwable;
    //   562: athrow
    //   563: astore_3
    //   564: aload_3
    //   565: invokevirtual 132	java/lang/reflect/InvocationTargetException:getCause	()Ljava/lang/Throwable;
    //   568: athrow
    //   569: astore_3
    //   570: aload_3
    //   571: invokevirtual 132	java/lang/reflect/InvocationTargetException:getCause	()Ljava/lang/Throwable;
    //   574: athrow
    //   575: astore_3
    //   576: aload_3
    //   577: invokevirtual 132	java/lang/reflect/InvocationTargetException:getCause	()Ljava/lang/Throwable;
    //   580: athrow
    //   581: astore_3
    //   582: aload_3
    //   583: invokevirtual 132	java/lang/reflect/InvocationTargetException:getCause	()Ljava/lang/Throwable;
    //   586: athrow
    //   587: astore_3
    //   588: aload_3
    //   589: invokevirtual 132	java/lang/reflect/InvocationTargetException:getCause	()Ljava/lang/Throwable;
    //   592: athrow
    //   593: astore_3
    //   594: aload_3
    //   595: invokevirtual 132	java/lang/reflect/InvocationTargetException:getCause	()Ljava/lang/Throwable;
    //   598: athrow
    //   599: astore_3
    //   600: aload_3
    //   601: invokevirtual 132	java/lang/reflect/InvocationTargetException:getCause	()Ljava/lang/Throwable;
    //   604: athrow
    //   605: astore_3
    //   606: aload_3
    //   607: invokevirtual 132	java/lang/reflect/InvocationTargetException:getCause	()Ljava/lang/Throwable;
    //   610: athrow
    //   611: astore_3
    //   612: aload_3
    //   613: invokevirtual 132	java/lang/reflect/InvocationTargetException:getCause	()Ljava/lang/Throwable;
    //   616: athrow
    // Local variable table:
    //   start	length	slot	name	signature
    //   0	617	0	this	vdvvdd
    //   45	352	1	i	int
    //   144	38	2	j	int
    //   4	552	3	localBundle	Bundle
    //   557	2	3	localInvocationTargetException1	java.lang.reflect.InvocationTargetException
    //   563	2	3	localInvocationTargetException2	java.lang.reflect.InvocationTargetException
    //   569	2	3	localInvocationTargetException3	java.lang.reflect.InvocationTargetException
    //   575	2	3	localInvocationTargetException4	java.lang.reflect.InvocationTargetException
    //   581	2	3	localInvocationTargetException5	java.lang.reflect.InvocationTargetException
    //   587	2	3	localInvocationTargetException6	java.lang.reflect.InvocationTargetException
    //   593	2	3	localInvocationTargetException7	java.lang.reflect.InvocationTargetException
    //   599	2	3	localInvocationTargetException8	java.lang.reflect.InvocationTargetException
    //   605	2	3	localInvocationTargetException9	java.lang.reflect.InvocationTargetException
    //   611	2	3	localInvocationTargetException10	java.lang.reflect.InvocationTargetException
    //   23	522	4	localObject	Object
    // Exception table:
    //   from	to	target	type
    //   369	381	557	java/lang/reflect/InvocationTargetException
    //   167	179	563	java/lang/reflect/InvocationTargetException
    //   532	544	569	java/lang/reflect/InvocationTargetException
    //   25	37	575	java/lang/reflect/InvocationTargetException
    //   319	331	581	java/lang/reflect/InvocationTargetException
    //   101	113	587	java/lang/reflect/InvocationTargetException
    //   440	452	593	java/lang/reflect/InvocationTargetException
    //   484	496	599	java/lang/reflect/InvocationTargetException
    //   231	243	605	java/lang/reflect/InvocationTargetException
    //   273	285	611	java/lang/reflect/InvocationTargetException
  }
}
