package uuuuuu;

import android.support.annotation.NonNull;
import com.db.pwcc.dbmobile.model.friend.Friend;
import java.util.Collection;

public class vkkkvk
{
  public static int b00630063c0063cc0063cc = 1;
  public static int b0063c00630063cc0063cc = 0;
  public static int bc0063c0063cc0063cc = 32;
  public static int bcc00630063cc0063cc = 2;
  private kkkkvk b006300630063ccc0063cc;
  private String b0063cc0063cc0063cc;
  private vvvvkk bccc0063cc0063cc;
  
  private vkkkvk()
  {
    this.b006300630063ccc0063cc = kkkkvk.b00630063cc0063c0063cc;
  }
  
  public vkkkvk(kkkkvk paramKkkkvk, @NonNull vvvvkk paramVvvvkk)
  {
    this.b006300630063ccc0063cc = paramKkkkvk;
    this.bccc0063cc0063cc = paramVvvvkk;
  }
  
  public static vkkkvk b007100710071qq00710071qqq(@NonNull String paramString)
  {
    int i = bc0063c0063cc0063cc;
    switch (i * (b00630063c0063cc0063cc + i) % bcc00630063cc0063cc)
    {
    default: 
      bc0063c0063cc0063cc = bqq0071qq00710071qqq();
      b00630063c0063cc0063cc = bqq0071qq00710071qqq();
    }
    vkkkvk localVkkkvk = new vkkkvk();
    localVkkkvk.b0071q00710071q00710071qqq(kkkkvk.b0063006300630063cc0063cc);
    localVkkkvk.b0071007100710071q00710071qqq(paramString);
    i = bqq0071qq00710071qqq();
    switch (i * (b00630063c0063cc0063cc + i) % bcc00630063cc0063cc)
    {
    default: 
      bc0063c0063cc0063cc = 30;
      b00630063c0063cc0063cc = bqq0071qq00710071qqq();
    }
    return localVkkkvk;
  }
  
  public static int b00710071qqq00710071qqq()
  {
    return 2;
  }
  
  public static int b0071q0071qq00710071qqq()
  {
    return 0;
  }
  
  public static int bq00710071qq00710071qqq()
  {
    return 1;
  }
  
  public static vkkkvk bqq00710071q00710071qqq(@NonNull String paramString, @NonNull vvvvkk paramVvvvkk)
  {
    vkkkvk localVkkkvk = new vkkkvk();
    localVkkkvk.b0071q00710071q00710071qqq(kkkkvk.bc0063cc0063c0063cc);
    if ((bc0063c0063cc0063cc + b00630063c0063cc0063cc) * bc0063c0063cc0063cc % b00710071qqq00710071qqq() != b0063c00630063cc0063cc)
    {
      if ((bc0063c0063cc0063cc + b00630063c0063cc0063cc) * bc0063c0063cc0063cc % bcc00630063cc0063cc != b0063c00630063cc0063cc)
      {
        bc0063c0063cc0063cc = bqq0071qq00710071qqq();
        b0063c00630063cc0063cc = bqq0071qq00710071qqq();
      }
      bc0063c0063cc0063cc = 93;
      b0063c00630063cc0063cc = bqq0071qq00710071qqq();
    }
    localVkkkvk.b0071007100710071q00710071qqq(paramString);
    localVkkkvk.bq007100710071q00710071qqq(paramVvvvkk);
    return localVkkkvk;
  }
  
  public static int bqq0071qq00710071qqq()
  {
    return 38;
  }
  
  public static vkkkvk bqqq0071q00710071qqq(@NonNull vvvvkk paramVvvvkk)
  {
    vkkkvk localVkkkvk = new vkkkvk();
    if ((bc0063c0063cc0063cc + b00630063c0063cc0063cc) * bc0063c0063cc0063cc % bcc00630063cc0063cc != b0063c00630063cc0063cc)
    {
      bc0063c0063cc0063cc = 7;
      b0063c00630063cc0063cc = 76;
    }
    kkkkvk localKkkkvk = kkkkvk.bcccc0063c0063cc;
    if ((bc0063c0063cc0063cc + b00630063c0063cc0063cc) * bc0063c0063cc0063cc % bcc00630063cc0063cc != b0063c00630063cc0063cc)
    {
      bc0063c0063cc0063cc = bqq0071qq00710071qqq();
      b0063c00630063cc0063cc = bqq0071qq00710071qqq();
    }
    localVkkkvk.b0071q00710071q00710071qqq(localKkkkvk);
    localVkkkvk.bq007100710071q00710071qqq(paramVvvvkk);
    return localVkkkvk;
  }
  
  public static vkkkvk bqqqq007100710071qqq()
  {
    vkkkvk localVkkkvk = new vkkkvk();
    if ((bqq0071qq00710071qqq() + b00630063c0063cc0063cc) * bqq0071qq00710071qqq() % bcc00630063cc0063cc != b0063c00630063cc0063cc)
    {
      int i = bc0063c0063cc0063cc;
      switch (i * (b00630063c0063cc0063cc + i) % bcc00630063cc0063cc)
      {
      default: 
        bc0063c0063cc0063cc = 60;
        b0063c00630063cc0063cc = 57;
      }
      bc0063c0063cc0063cc = 58;
      b0063c00630063cc0063cc = bqq0071qq00710071qqq();
    }
    return localVkkkvk;
  }
  
  public void b0071007100710071q00710071qqq(String paramString)
  {
    if ((bc0063c0063cc0063cc + b00630063c0063cc0063cc) * bc0063c0063cc0063cc % bcc00630063cc0063cc != b0071q0071qq00710071qqq())
    {
      bc0063c0063cc0063cc = 86;
      b0063c00630063cc0063cc = bqq0071qq00710071qqq();
    }
    this.b0063cc0063cc0063cc = paramString;
    if ((bc0063c0063cc0063cc + b00630063c0063cc0063cc) * bc0063c0063cc0063cc % bcc00630063cc0063cc != b0063c00630063cc0063cc)
    {
      bc0063c0063cc0063cc = bqq0071qq00710071qqq();
      b0063c00630063cc0063cc = bqq0071qq00710071qqq();
    }
  }
  
  public String b00710071q0071q00710071qqq()
  {
    if ((bc0063c0063cc0063cc + b00630063c0063cc0063cc) * bc0063c0063cc0063cc % bcc00630063cc0063cc != b0063c00630063cc0063cc)
    {
      int i = bc0063c0063cc0063cc;
      switch (i * (b00630063c0063cc0063cc + i) % bcc00630063cc0063cc)
      {
      default: 
        bc0063c0063cc0063cc = bqq0071qq00710071qqq();
        b0063c00630063cc0063cc = 16;
      }
      bc0063c0063cc0063cc = 36;
      b0063c00630063cc0063cc = 45;
    }
    return this.b0063cc0063cc0063cc;
  }
  
  public void b0071q00710071q00710071qqq(@NonNull kkkkvk paramKkkkvk)
  {
    if ((bc0063c0063cc0063cc + b00630063c0063cc0063cc) * bc0063c0063cc0063cc % bcc00630063cc0063cc != b0063c00630063cc0063cc)
    {
      bc0063c0063cc0063cc = bqq0071qq00710071qqq();
      b0063c00630063cc0063cc = bqq0071qq00710071qqq();
      int i = bc0063c0063cc0063cc;
      switch (i * (bq00710071qq00710071qqq() + i) % bcc00630063cc0063cc)
      {
      default: 
        bc0063c0063cc0063cc = 29;
        b0063c00630063cc0063cc = bqq0071qq00710071qqq();
      }
    }
    this.b006300630063ccc0063cc = paramKkkkvk;
  }
  
  public kkkkvk b0071qq0071q00710071qqq()
  {
    if ((bc0063c0063cc0063cc + bq00710071qq00710071qqq()) * bc0063c0063cc0063cc % bcc00630063cc0063cc != b0063c00630063cc0063cc)
    {
      bc0063c0063cc0063cc = 75;
      b0063c00630063cc0063cc = 36;
      if ((bc0063c0063cc0063cc + b00630063c0063cc0063cc) * bc0063c0063cc0063cc % bcc00630063cc0063cc != b0063c00630063cc0063cc)
      {
        bc0063c0063cc0063cc = 59;
        b0063c00630063cc0063cc = bqq0071qq00710071qqq();
      }
    }
    return this.b006300630063ccc0063cc;
  }
  
  public void bq007100710071q00710071qqq(@NonNull vvvvkk paramVvvvkk)
  {
    this.bccc0063cc0063cc = paramVvvvkk;
    int i = bc0063c0063cc0063cc;
    int j = b00630063c0063cc0063cc;
    int k = bc0063c0063cc0063cc;
    int m = bcc00630063cc0063cc;
    int n = b0071q0071qq00710071qqq();
    if ((bc0063c0063cc0063cc + bq00710071qq00710071qqq()) * bc0063c0063cc0063cc % bcc00630063cc0063cc != b0063c00630063cc0063cc)
    {
      bc0063c0063cc0063cc = bqq0071qq00710071qqq();
      b0063c00630063cc0063cc = 57;
    }
    if ((i + j) * k % m != n)
    {
      bc0063c0063cc0063cc = bqq0071qq00710071qqq();
      b0063c00630063cc0063cc = bqq0071qq00710071qqq();
    }
  }
  
  public vvvvkk bq0071q0071q00710071qqq()
  {
    if ((bc0063c0063cc0063cc + b00630063c0063cc0063cc) * bc0063c0063cc0063cc % bcc00630063cc0063cc != b0063c00630063cc0063cc)
    {
      bc0063c0063cc0063cc = bqq0071qq00710071qqq();
      b0063c00630063cc0063cc = 9;
    }
    vvvvkk localVvvvkk = this.bccc0063cc0063cc;
    if ((bc0063c0063cc0063cc + b00630063c0063cc0063cc) * bc0063c0063cc0063cc % bcc00630063cc0063cc != b0063c00630063cc0063cc)
    {
      bc0063c0063cc0063cc = bqq0071qq00710071qqq();
      b0063c00630063cc0063cc = bqq0071qq00710071qqq();
    }
    return localVvvvkk;
  }
  
  public static enum kkkkvk
  {
    /* Error */
    static
    {
      // Byte code:
      //   0: invokestatic 24	uuuuuu/vkkkvk$kkkkvk:bqqqqq00710071qqq	()I
      //   3: invokestatic 27	uuuuuu/vkkkvk$kkkkvk:b0071qqqq00710071qqq	()I
      //   6: iadd
      //   7: invokestatic 24	uuuuuu/vkkkvk$kkkkvk:bqqqqq00710071qqq	()I
      //   10: imul
      //   11: invokestatic 30	uuuuuu/vkkkvk$kkkkvk:b00710071007100710071q0071qqq	()I
      //   14: irem
      //   15: invokestatic 33	uuuuuu/vkkkvk$kkkkvk:bq0071007100710071q0071qqq	()I
      //   18: if_icmpeq +3 -> 21
      //   21: ldc 35
      //   23: ldc 37
      //   25: sipush 130
      //   28: iconst_2
      //   29: invokestatic 43	xxxxxx/uxxxxx:bb00620062bb0062b0062b0062	(Ljava/lang/String;CC)Ljava/lang/String;
      //   32: iconst_4
      //   33: anewarray 45	java/lang/Class
      //   36: dup
      //   37: iconst_0
      //   38: ldc 47
      //   40: aastore
      //   41: dup
      //   42: iconst_1
      //   43: getstatic 53	java/lang/Character:TYPE	Ljava/lang/Class;
      //   46: aastore
      //   47: dup
      //   48: iconst_2
      //   49: getstatic 53	java/lang/Character:TYPE	Ljava/lang/Class;
      //   52: aastore
      //   53: dup
      //   54: iconst_3
      //   55: getstatic 53	java/lang/Character:TYPE	Ljava/lang/Class;
      //   58: aastore
      //   59: invokevirtual 57	java/lang/Class:getMethod	(Ljava/lang/String;[Ljava/lang/Class;)Ljava/lang/reflect/Method;
      //   62: astore_0
      //   63: aload_0
      //   64: aconst_null
      //   65: iconst_4
      //   66: anewarray 59	java/lang/Object
      //   69: dup
      //   70: iconst_0
      //   71: ldc 61
      //   73: aastore
      //   74: dup
      //   75: iconst_1
      //   76: sipush 167
      //   79: invokestatic 65	java/lang/Character:valueOf	(C)Ljava/lang/Character;
      //   82: aastore
      //   83: dup
      //   84: iconst_2
      //   85: bipush 78
      //   87: invokestatic 65	java/lang/Character:valueOf	(C)Ljava/lang/Character;
      //   90: aastore
      //   91: dup
      //   92: iconst_3
      //   93: iconst_0
      //   94: invokestatic 65	java/lang/Character:valueOf	(C)Ljava/lang/Character;
      //   97: aastore
      //   98: invokevirtual 71	java/lang/reflect/Method:invoke	(Ljava/lang/Object;[Ljava/lang/Object;)Ljava/lang/Object;
      //   101: astore_0
      //   102: new 2	uuuuuu/vkkkvk$kkkkvk
      //   105: dup
      //   106: aload_0
      //   107: checkcast 47	java/lang/String
      //   110: iconst_0
      //   111: invokespecial 75	uuuuuu/vkkkvk$kkkkvk:<init>	(Ljava/lang/String;I)V
      //   114: putstatic 77	uuuuuu/vkkkvk$kkkkvk:bcccc0063c0063cc	Luuuuuu/vkkkvk$kkkkvk;
      //   117: ldc 35
      //   119: ldc 79
      //   121: bipush 124
      //   123: iconst_1
      //   124: invokestatic 43	xxxxxx/uxxxxx:bb00620062bb0062b0062b0062	(Ljava/lang/String;CC)Ljava/lang/String;
      //   127: iconst_3
      //   128: anewarray 45	java/lang/Class
      //   131: dup
      //   132: iconst_0
      //   133: ldc 47
      //   135: aastore
      //   136: dup
      //   137: iconst_1
      //   138: getstatic 53	java/lang/Character:TYPE	Ljava/lang/Class;
      //   141: aastore
      //   142: dup
      //   143: iconst_2
      //   144: getstatic 53	java/lang/Character:TYPE	Ljava/lang/Class;
      //   147: aastore
      //   148: invokevirtual 57	java/lang/Class:getMethod	(Ljava/lang/String;[Ljava/lang/Class;)Ljava/lang/reflect/Method;
      //   151: astore_0
      //   152: aload_0
      //   153: aconst_null
      //   154: iconst_3
      //   155: anewarray 59	java/lang/Object
      //   158: dup
      //   159: iconst_0
      //   160: ldc 81
      //   162: aastore
      //   163: dup
      //   164: iconst_1
      //   165: sipush 239
      //   168: invokestatic 65	java/lang/Character:valueOf	(C)Ljava/lang/Character;
      //   171: aastore
      //   172: dup
      //   173: iconst_2
      //   174: iconst_4
      //   175: invokestatic 65	java/lang/Character:valueOf	(C)Ljava/lang/Character;
      //   178: aastore
      //   179: invokevirtual 71	java/lang/reflect/Method:invoke	(Ljava/lang/Object;[Ljava/lang/Object;)Ljava/lang/Object;
      //   182: astore_0
      //   183: new 2	uuuuuu/vkkkvk$kkkkvk
      //   186: dup
      //   187: aload_0
      //   188: checkcast 47	java/lang/String
      //   191: iconst_1
      //   192: invokespecial 75	uuuuuu/vkkkvk$kkkkvk:<init>	(Ljava/lang/String;I)V
      //   195: putstatic 83	uuuuuu/vkkkvk$kkkkvk:b00630063cc0063c0063cc	Luuuuuu/vkkkvk$kkkkvk;
      //   198: invokestatic 24	uuuuuu/vkkkvk$kkkkvk:bqqqqq00710071qqq	()I
      //   201: invokestatic 27	uuuuuu/vkkkvk$kkkkvk:b0071qqqq00710071qqq	()I
      //   204: iadd
      //   205: invokestatic 24	uuuuuu/vkkkvk$kkkkvk:bqqqqq00710071qqq	()I
      //   208: imul
      //   209: invokestatic 30	uuuuuu/vkkkvk$kkkkvk:b00710071007100710071q0071qqq	()I
      //   212: irem
      //   213: invokestatic 33	uuuuuu/vkkkvk$kkkkvk:bq0071007100710071q0071qqq	()I
      //   216: if_icmpeq +3 -> 219
      //   219: ldc 35
      //   221: ldc 85
      //   223: sipush 142
      //   226: iconst_3
      //   227: invokestatic 43	xxxxxx/uxxxxx:bb00620062bb0062b0062b0062	(Ljava/lang/String;CC)Ljava/lang/String;
      //   230: iconst_4
      //   231: anewarray 45	java/lang/Class
      //   234: dup
      //   235: iconst_0
      //   236: ldc 47
      //   238: aastore
      //   239: dup
      //   240: iconst_1
      //   241: getstatic 53	java/lang/Character:TYPE	Ljava/lang/Class;
      //   244: aastore
      //   245: dup
      //   246: iconst_2
      //   247: getstatic 53	java/lang/Character:TYPE	Ljava/lang/Class;
      //   250: aastore
      //   251: dup
      //   252: iconst_3
      //   253: getstatic 53	java/lang/Character:TYPE	Ljava/lang/Class;
      //   256: aastore
      //   257: invokevirtual 57	java/lang/Class:getMethod	(Ljava/lang/String;[Ljava/lang/Class;)Ljava/lang/reflect/Method;
      //   260: astore_0
      //   261: aload_0
      //   262: aconst_null
      //   263: iconst_4
      //   264: anewarray 59	java/lang/Object
      //   267: dup
      //   268: iconst_0
      //   269: ldc 87
      //   271: aastore
      //   272: dup
      //   273: iconst_1
      //   274: bipush 123
      //   276: invokestatic 65	java/lang/Character:valueOf	(C)Ljava/lang/Character;
      //   279: aastore
      //   280: dup
      //   281: iconst_2
      //   282: sipush 135
      //   285: invokestatic 65	java/lang/Character:valueOf	(C)Ljava/lang/Character;
      //   288: aastore
      //   289: dup
      //   290: iconst_3
      //   291: iconst_2
      //   292: invokestatic 65	java/lang/Character:valueOf	(C)Ljava/lang/Character;
      //   295: aastore
      //   296: invokevirtual 71	java/lang/reflect/Method:invoke	(Ljava/lang/Object;[Ljava/lang/Object;)Ljava/lang/Object;
      //   299: astore_0
      //   300: new 2	uuuuuu/vkkkvk$kkkkvk
      //   303: dup
      //   304: aload_0
      //   305: checkcast 47	java/lang/String
      //   308: iconst_2
      //   309: invokespecial 75	uuuuuu/vkkkvk$kkkkvk:<init>	(Ljava/lang/String;I)V
      //   312: putstatic 89	uuuuuu/vkkkvk$kkkkvk:bc0063cc0063c0063cc	Luuuuuu/vkkkvk$kkkkvk;
      //   315: ldc 35
      //   317: ldc 91
      //   319: sipush 157
      //   322: iconst_4
      //   323: invokestatic 43	xxxxxx/uxxxxx:bb00620062bb0062b0062b0062	(Ljava/lang/String;CC)Ljava/lang/String;
      //   326: iconst_4
      //   327: anewarray 45	java/lang/Class
      //   330: dup
      //   331: iconst_0
      //   332: ldc 47
      //   334: aastore
      //   335: dup
      //   336: iconst_1
      //   337: getstatic 53	java/lang/Character:TYPE	Ljava/lang/Class;
      //   340: aastore
      //   341: dup
      //   342: iconst_2
      //   343: getstatic 53	java/lang/Character:TYPE	Ljava/lang/Class;
      //   346: aastore
      //   347: dup
      //   348: iconst_3
      //   349: getstatic 53	java/lang/Character:TYPE	Ljava/lang/Class;
      //   352: aastore
      //   353: invokevirtual 57	java/lang/Class:getMethod	(Ljava/lang/String;[Ljava/lang/Class;)Ljava/lang/reflect/Method;
      //   356: astore_0
      //   357: aload_0
      //   358: aconst_null
      //   359: iconst_4
      //   360: anewarray 59	java/lang/Object
      //   363: dup
      //   364: iconst_0
      //   365: ldc 93
      //   367: aastore
      //   368: dup
      //   369: iconst_1
      //   370: bipush 33
      //   372: invokestatic 65	java/lang/Character:valueOf	(C)Ljava/lang/Character;
      //   375: aastore
      //   376: dup
      //   377: iconst_2
      //   378: sipush 149
      //   381: invokestatic 65	java/lang/Character:valueOf	(C)Ljava/lang/Character;
      //   384: aastore
      //   385: dup
      //   386: iconst_3
      //   387: iconst_0
      //   388: invokestatic 65	java/lang/Character:valueOf	(C)Ljava/lang/Character;
      //   391: aastore
      //   392: invokevirtual 71	java/lang/reflect/Method:invoke	(Ljava/lang/Object;[Ljava/lang/Object;)Ljava/lang/Object;
      //   395: astore_0
      //   396: new 2	uuuuuu/vkkkvk$kkkkvk
      //   399: dup
      //   400: aload_0
      //   401: checkcast 47	java/lang/String
      //   404: iconst_3
      //   405: invokespecial 75	uuuuuu/vkkkvk$kkkkvk:<init>	(Ljava/lang/String;I)V
      //   408: putstatic 95	uuuuuu/vkkkvk$kkkkvk:b0063ccc0063c0063cc	Luuuuuu/vkkkvk$kkkkvk;
      //   411: ldc 35
      //   413: ldc 97
      //   415: iconst_3
      //   416: iconst_1
      //   417: invokestatic 43	xxxxxx/uxxxxx:bb00620062bb0062b0062b0062	(Ljava/lang/String;CC)Ljava/lang/String;
      //   420: iconst_4
      //   421: anewarray 45	java/lang/Class
      //   424: dup
      //   425: iconst_0
      //   426: ldc 47
      //   428: aastore
      //   429: dup
      //   430: iconst_1
      //   431: getstatic 53	java/lang/Character:TYPE	Ljava/lang/Class;
      //   434: aastore
      //   435: dup
      //   436: iconst_2
      //   437: getstatic 53	java/lang/Character:TYPE	Ljava/lang/Class;
      //   440: aastore
      //   441: dup
      //   442: iconst_3
      //   443: getstatic 53	java/lang/Character:TYPE	Ljava/lang/Class;
      //   446: aastore
      //   447: invokevirtual 57	java/lang/Class:getMethod	(Ljava/lang/String;[Ljava/lang/Class;)Ljava/lang/reflect/Method;
      //   450: astore_0
      //   451: aload_0
      //   452: aconst_null
      //   453: iconst_4
      //   454: anewarray 59	java/lang/Object
      //   457: dup
      //   458: iconst_0
      //   459: ldc 99
      //   461: aastore
      //   462: dup
      //   463: iconst_1
      //   464: bipush 46
      //   466: invokestatic 65	java/lang/Character:valueOf	(C)Ljava/lang/Character;
      //   469: aastore
      //   470: dup
      //   471: iconst_2
      //   472: sipush 234
      //   475: invokestatic 65	java/lang/Character:valueOf	(C)Ljava/lang/Character;
      //   478: aastore
      //   479: dup
      //   480: iconst_3
      //   481: iconst_1
      //   482: invokestatic 65	java/lang/Character:valueOf	(C)Ljava/lang/Character;
      //   485: aastore
      //   486: invokevirtual 71	java/lang/reflect/Method:invoke	(Ljava/lang/Object;[Ljava/lang/Object;)Ljava/lang/Object;
      //   489: astore_0
      //   490: new 2	uuuuuu/vkkkvk$kkkkvk
      //   493: dup
      //   494: aload_0
      //   495: checkcast 47	java/lang/String
      //   498: iconst_4
      //   499: invokespecial 75	uuuuuu/vkkkvk$kkkkvk:<init>	(Ljava/lang/String;I)V
      //   502: putstatic 101	uuuuuu/vkkkvk$kkkkvk:b0063006300630063cc0063cc	Luuuuuu/vkkkvk$kkkkvk;
      //   505: iconst_5
      //   506: anewarray 2	uuuuuu/vkkkvk$kkkkvk
      //   509: dup
      //   510: iconst_0
      //   511: getstatic 77	uuuuuu/vkkkvk$kkkkvk:bcccc0063c0063cc	Luuuuuu/vkkkvk$kkkkvk;
      //   514: aastore
      //   515: dup
      //   516: iconst_1
      //   517: getstatic 83	uuuuuu/vkkkvk$kkkkvk:b00630063cc0063c0063cc	Luuuuuu/vkkkvk$kkkkvk;
      //   520: aastore
      //   521: dup
      //   522: iconst_2
      //   523: getstatic 89	uuuuuu/vkkkvk$kkkkvk:bc0063cc0063c0063cc	Luuuuuu/vkkkvk$kkkkvk;
      //   526: aastore
      //   527: dup
      //   528: iconst_3
      //   529: getstatic 95	uuuuuu/vkkkvk$kkkkvk:b0063ccc0063c0063cc	Luuuuuu/vkkkvk$kkkkvk;
      //   532: aastore
      //   533: dup
      //   534: iconst_4
      //   535: getstatic 101	uuuuuu/vkkkvk$kkkkvk:b0063006300630063cc0063cc	Luuuuuu/vkkkvk$kkkkvk;
      //   538: aastore
      //   539: putstatic 103	uuuuuu/vkkkvk$kkkkvk:bc006300630063cc0063cc	[Luuuuuu/vkkkvk$kkkkvk;
      //   542: return
      //   543: astore_0
      //   544: aload_0
      //   545: invokevirtual 107	java/lang/reflect/InvocationTargetException:getCause	()Ljava/lang/Throwable;
      //   548: athrow
      //   549: astore_0
      //   550: aload_0
      //   551: invokevirtual 107	java/lang/reflect/InvocationTargetException:getCause	()Ljava/lang/Throwable;
      //   554: athrow
      //   555: astore_0
      //   556: aload_0
      //   557: invokevirtual 107	java/lang/reflect/InvocationTargetException:getCause	()Ljava/lang/Throwable;
      //   560: athrow
      //   561: astore_0
      //   562: aload_0
      //   563: invokevirtual 107	java/lang/reflect/InvocationTargetException:getCause	()Ljava/lang/Throwable;
      //   566: athrow
      //   567: astore_0
      //   568: aload_0
      //   569: invokevirtual 107	java/lang/reflect/InvocationTargetException:getCause	()Ljava/lang/Throwable;
      //   572: athrow
      // Local variable table:
      //   start	length	slot	name	signature
      //   62	433	0	localObject	Object
      //   543	2	0	localInvocationTargetException1	java.lang.reflect.InvocationTargetException
      //   549	2	0	localInvocationTargetException2	java.lang.reflect.InvocationTargetException
      //   555	2	0	localInvocationTargetException3	java.lang.reflect.InvocationTargetException
      //   561	2	0	localInvocationTargetException4	java.lang.reflect.InvocationTargetException
      //   567	2	0	localInvocationTargetException5	java.lang.reflect.InvocationTargetException
      // Exception table:
      //   from	to	target	type
      //   63	102	543	java/lang/reflect/InvocationTargetException
      //   357	396	549	java/lang/reflect/InvocationTargetException
      //   261	300	555	java/lang/reflect/InvocationTargetException
      //   451	490	561	java/lang/reflect/InvocationTargetException
      //   152	183	567	java/lang/reflect/InvocationTargetException
    }
    
    private kkkkvk() {}
    
    public static int b00710071007100710071q0071qqq()
    {
      return 2;
    }
    
    public static int b0071qqqq00710071qqq()
    {
      return 1;
    }
    
    public static int bq0071007100710071q0071qqq()
    {
      return 0;
    }
    
    public static kkkkvk bq0071qqq00710071qqq(String paramString)
    {
      int i = bqqqqq00710071qqq();
      switch (i * (b0071qqqq00710071qqq() + i) % b00710071007100710071q0071qqq())
      {
      }
      paramString = Enum.valueOf(kkkkvk.class, paramString);
      i = bqqqqq00710071qqq();
      switch (i * (b0071qqqq00710071qqq() + i) % b00710071007100710071q0071qqq())
      {
      }
      return (kkkkvk)paramString;
    }
    
    public static int bqqqqq00710071qqq()
    {
      return 67;
    }
  }
  
  public static abstract interface vvvvkk
  {
    public abstract void b00610061aa0061006100610061aa(String paramString);
    
    public abstract void b0061a0061a0061006100610061aa(boolean paramBoolean);
    
    public abstract void baa0061a0061006100610061aa(Collection<Friend> paramCollection);
  }
}
