package uuuuuu;

public enum vkkvvv
{
  /* Error */
  static
  {
    // Byte code:
    //   0: ldc 16
    //   2: ldc 18
    //   4: sipush 247
    //   7: iconst_1
    //   8: invokestatic 24	xxxxxx/uxxxxx:bb00620062bb0062b0062b0062	(Ljava/lang/String;CC)Ljava/lang/String;
    //   11: iconst_3
    //   12: anewarray 26	java/lang/Class
    //   15: dup
    //   16: iconst_0
    //   17: ldc 28
    //   19: aastore
    //   20: dup
    //   21: iconst_1
    //   22: getstatic 34	java/lang/Character:TYPE	Ljava/lang/Class;
    //   25: aastore
    //   26: dup
    //   27: iconst_2
    //   28: getstatic 34	java/lang/Character:TYPE	Ljava/lang/Class;
    //   31: aastore
    //   32: invokevirtual 38	java/lang/Class:getMethod	(Ljava/lang/String;[Ljava/lang/Class;)Ljava/lang/reflect/Method;
    //   35: astore_3
    //   36: aload_3
    //   37: aconst_null
    //   38: iconst_3
    //   39: anewarray 40	java/lang/Object
    //   42: dup
    //   43: iconst_0
    //   44: ldc 42
    //   46: aastore
    //   47: dup
    //   48: iconst_1
    //   49: bipush 65
    //   51: invokestatic 46	java/lang/Character:valueOf	(C)Ljava/lang/Character;
    //   54: aastore
    //   55: dup
    //   56: iconst_2
    //   57: iconst_5
    //   58: invokestatic 46	java/lang/Character:valueOf	(C)Ljava/lang/Character;
    //   61: aastore
    //   62: invokevirtual 52	java/lang/reflect/Method:invoke	(Ljava/lang/Object;[Ljava/lang/Object;)Ljava/lang/Object;
    //   65: astore_3
    //   66: new 2	uuuuuu/vkkvvv
    //   69: dup
    //   70: aload_3
    //   71: checkcast 28	java/lang/String
    //   74: iconst_0
    //   75: invokespecial 56	uuuuuu/vkkvvv:<init>	(Ljava/lang/String;I)V
    //   78: astore_3
    //   79: invokestatic 60	uuuuuu/vkkvvv:b0071q007100710071qqqqq	()I
    //   82: istore_0
    //   83: invokestatic 63	uuuuuu/vkkvvv:bq0071007100710071qqqqq	()I
    //   86: istore_1
    //   87: invokestatic 60	uuuuuu/vkkvvv:b0071q007100710071qqqqq	()I
    //   90: istore_2
    //   91: iload_2
    //   92: invokestatic 63	uuuuuu/vkkvvv:bq0071007100710071qqqqq	()I
    //   95: iload_2
    //   96: iadd
    //   97: imul
    //   98: invokestatic 66	uuuuuu/vkkvvv:bqq007100710071qqqqq	()I
    //   101: irem
    //   102: tableswitch	default:+18->120, 0:+18->120
    //   120: iload_0
    //   121: iload_1
    //   122: iadd
    //   123: invokestatic 60	uuuuuu/vkkvvv:b0071q007100710071qqqqq	()I
    //   126: imul
    //   127: invokestatic 66	uuuuuu/vkkvvv:bqq007100710071qqqqq	()I
    //   130: irem
    //   131: invokestatic 69	uuuuuu/vkkvvv:b00710071q00710071qqqqq	()I
    //   134: if_icmpeq +3 -> 137
    //   137: aload_3
    //   138: putstatic 71	uuuuuu/vkkvvv:b00660066f00660066f006600660066	Luuuuuu/vkkvvv;
    //   141: ldc 16
    //   143: ldc 73
    //   145: sipush 180
    //   148: iconst_2
    //   149: invokestatic 24	xxxxxx/uxxxxx:bb00620062bb0062b0062b0062	(Ljava/lang/String;CC)Ljava/lang/String;
    //   152: iconst_3
    //   153: anewarray 26	java/lang/Class
    //   156: dup
    //   157: iconst_0
    //   158: ldc 28
    //   160: aastore
    //   161: dup
    //   162: iconst_1
    //   163: getstatic 34	java/lang/Character:TYPE	Ljava/lang/Class;
    //   166: aastore
    //   167: dup
    //   168: iconst_2
    //   169: getstatic 34	java/lang/Character:TYPE	Ljava/lang/Class;
    //   172: aastore
    //   173: invokevirtual 38	java/lang/Class:getMethod	(Ljava/lang/String;[Ljava/lang/Class;)Ljava/lang/reflect/Method;
    //   176: astore_3
    //   177: aload_3
    //   178: aconst_null
    //   179: iconst_3
    //   180: anewarray 40	java/lang/Object
    //   183: dup
    //   184: iconst_0
    //   185: ldc 75
    //   187: aastore
    //   188: dup
    //   189: iconst_1
    //   190: bipush 52
    //   192: invokestatic 46	java/lang/Character:valueOf	(C)Ljava/lang/Character;
    //   195: aastore
    //   196: dup
    //   197: iconst_2
    //   198: iconst_2
    //   199: invokestatic 46	java/lang/Character:valueOf	(C)Ljava/lang/Character;
    //   202: aastore
    //   203: invokevirtual 52	java/lang/reflect/Method:invoke	(Ljava/lang/Object;[Ljava/lang/Object;)Ljava/lang/Object;
    //   206: astore_3
    //   207: new 2	uuuuuu/vkkvvv
    //   210: dup
    //   211: aload_3
    //   212: checkcast 28	java/lang/String
    //   215: iconst_1
    //   216: invokespecial 56	uuuuuu/vkkvvv:<init>	(Ljava/lang/String;I)V
    //   219: putstatic 77	uuuuuu/vkkvvv:bf0066f00660066f006600660066	Luuuuuu/vkkvvv;
    //   222: iconst_2
    //   223: anewarray 2	uuuuuu/vkkvvv
    //   226: dup
    //   227: iconst_0
    //   228: getstatic 71	uuuuuu/vkkvvv:b00660066f00660066f006600660066	Luuuuuu/vkkvvv;
    //   231: aastore
    //   232: dup
    //   233: iconst_1
    //   234: getstatic 77	uuuuuu/vkkvvv:bf0066f00660066f006600660066	Luuuuuu/vkkvvv;
    //   237: aastore
    //   238: putstatic 79	uuuuuu/vkkvvv:b0066ff00660066f006600660066	[Luuuuuu/vkkvvv;
    //   241: return
    //   242: astore_3
    //   243: aload_3
    //   244: invokevirtual 83	java/lang/reflect/InvocationTargetException:getCause	()Ljava/lang/Throwable;
    //   247: athrow
    //   248: astore_3
    //   249: aload_3
    //   250: invokevirtual 83	java/lang/reflect/InvocationTargetException:getCause	()Ljava/lang/Throwable;
    //   253: athrow
    // Local variable table:
    //   start	length	slot	name	signature
    //   82	41	0	i	int
    //   86	37	1	j	int
    //   90	8	2	k	int
    //   35	177	3	localObject	Object
    //   242	2	3	localInvocationTargetException1	java.lang.reflect.InvocationTargetException
    //   248	2	3	localInvocationTargetException2	java.lang.reflect.InvocationTargetException
    // Exception table:
    //   from	to	target	type
    //   36	66	242	java/lang/reflect/InvocationTargetException
    //   177	207	248	java/lang/reflect/InvocationTargetException
  }
  
  private vkkvvv() {}
  
  public static vkkvvv b00710071007100710071qqqqq(String paramString)
  {
    int i = b0071q007100710071qqqqq();
    int j = bq0071007100710071qqqqq();
    int k = b0071q007100710071qqqqq();
    int m = bqq007100710071qqqqq();
    if (((b0071q007100710071qqqqq() + bq0071007100710071qqqqq()) * b0071q007100710071qqqqq() % bqq007100710071qqqqq() == b00710071q00710071qqqqq()) || ((i + j) * k % m != b00710071q00710071qqqqq())) {}
    return (vkkvvv)Enum.valueOf(vkkvvv.class, paramString);
  }
  
  public static int b00710071q00710071qqqqq()
  {
    return 0;
  }
  
  public static int b0071q007100710071qqqqq()
  {
    return 82;
  }
  
  public static int bq0071007100710071qqqqq()
  {
    return 1;
  }
  
  public static int bqq007100710071qqqqq()
  {
    return 2;
  }
}
