package uuuuuu;

import android.view.ViewGroup;
import com.db.pwcc.dbmobile.transfer.R.string;
import com.db.pwcc.dbmobile.transfer.widgets.inputFields.iban.IbanGroup;

public class vlllvv
{
  public static int b006F006Foo006Foo006F006F = 1;
  public static int b006Fo006Fo006Foo006F006F = 0;
  public static int bo006F006Fo006Foo006F006F = 60;
  public static int boo006Fo006Foo006F006F = 2;
  
  public vlllvv() {}
  
  /* Error */
  public static int b00690069i00690069ii006900690069(com.db.pwcc.dbmobile.model.sepa.OnlineCheckStatus paramOnlineCheckStatus)
  {
    // Byte code:
    //   0: aload_0
    //   1: getstatic 28	com/db/pwcc/dbmobile/model/sepa/OnlineCheckStatus:NOT_SEPA	Lcom/db/pwcc/dbmobile/model/sepa/OnlineCheckStatus;
    //   4: if_acmpne +124 -> 128
    //   7: getstatic 33	com/db/pwcc/dbmobile/transfer/R$string:sepatransfer_iban_not_sepa	I
    //   10: istore_1
    //   11: getstatic 35	uuuuuu/vlllvv:bo006F006Fo006Foo006F006F	I
    //   14: getstatic 37	uuuuuu/vlllvv:b006F006Foo006Foo006F006F	I
    //   17: iadd
    //   18: getstatic 35	uuuuuu/vlllvv:bo006F006Fo006Foo006F006F	I
    //   21: imul
    //   22: getstatic 39	uuuuuu/vlllvv:boo006Fo006Foo006F006F	I
    //   25: irem
    //   26: getstatic 41	uuuuuu/vlllvv:b006Fo006Fo006Foo006F006F	I
    //   29: if_icmpeq +14 -> 43
    //   32: invokestatic 45	uuuuuu/vlllvv:b0069ii00690069ii006900690069	()I
    //   35: putstatic 35	uuuuuu/vlllvv:bo006F006Fo006Foo006F006F	I
    //   38: bipush 23
    //   40: putstatic 41	uuuuuu/vlllvv:b006Fo006Fo006Foo006F006F	I
    //   43: iload_1
    //   44: ireturn
    //   45: astore_0
    //   46: getstatic 35	uuuuuu/vlllvv:bo006F006Fo006Foo006F006F	I
    //   49: istore_2
    //   50: iload_2
    //   51: getstatic 37	uuuuuu/vlllvv:b006F006Foo006Foo006F006F	I
    //   54: iload_2
    //   55: iadd
    //   56: imul
    //   57: getstatic 39	uuuuuu/vlllvv:boo006Fo006Foo006F006F	I
    //   60: irem
    //   61: tableswitch	default:+19->80, 0:+60->121
    //   80: getstatic 35	uuuuuu/vlllvv:bo006F006Fo006Foo006F006F	I
    //   83: getstatic 37	uuuuuu/vlllvv:b006F006Foo006Foo006F006F	I
    //   86: iadd
    //   87: getstatic 35	uuuuuu/vlllvv:bo006F006Fo006Foo006F006F	I
    //   90: imul
    //   91: getstatic 39	uuuuuu/vlllvv:boo006Fo006Foo006F006F	I
    //   94: irem
    //   95: getstatic 41	uuuuuu/vlllvv:b006Fo006Fo006Foo006F006F	I
    //   98: if_icmpeq +14 -> 112
    //   101: bipush 64
    //   103: putstatic 35	uuuuuu/vlllvv:bo006F006Fo006Foo006F006F	I
    //   106: invokestatic 45	uuuuuu/vlllvv:b0069ii00690069ii006900690069	()I
    //   109: putstatic 41	uuuuuu/vlllvv:b006Fo006Fo006Foo006F006F	I
    //   112: iconst_5
    //   113: putstatic 35	uuuuuu/vlllvv:bo006F006Fo006Foo006F006F	I
    //   116: bipush 41
    //   118: putstatic 41	uuuuuu/vlllvv:b006Fo006Fo006Foo006F006F	I
    //   121: bipush 59
    //   123: putstatic 35	uuuuuu/vlllvv:bo006F006Fo006Foo006F006F	I
    //   126: iload_1
    //   127: ireturn
    //   128: getstatic 48	com/db/pwcc/dbmobile/transfer/R$string:sepatransfer_iban_invalid_label	I
    //   131: istore_1
    //   132: new 50	java/lang/NullPointerException
    //   135: dup
    //   136: invokespecial 51	java/lang/NullPointerException:<init>	()V
    //   139: athrow
    // Local variable table:
    //   start	length	slot	name	signature
    //   0	140	0	paramOnlineCheckStatus	com.db.pwcc.dbmobile.model.sepa.OnlineCheckStatus
    //   10	122	1	i	int
    //   49	8	2	j	int
    // Exception table:
    //   from	to	target	type
    //   132	140	45	java/lang/Exception
  }
  
  public static int b0069ii00690069ii006900690069()
  {
    return 22;
  }
  
  public static void bi0069i00690069ii006900690069(IbanGroup paramIbanGroup, ViewGroup paramViewGroup, String paramString)
  {
    boolean bool = paramIbanGroup.isTheIbanDifferent();
    paramIbanGroup.setPrincipalIban(paramString);
    if (!paramIbanGroup.isTheIbanDifferent()) {
      paramIbanGroup.updateHintError(R.string.sepatransfer_error_iban_same_as_principal);
    }
    for (;;)
    {
      paramIbanGroup.requestFocus();
      int i = bo006F006Fo006Foo006F006F;
      switch (i * (b006F006Foo006Foo006F006F + i) % biii00690069ii006900690069())
      {
      default: 
        bo006F006Fo006Foo006F006F = b0069ii00690069ii006900690069();
        b006Fo006Fo006Foo006F006F = b0069ii00690069ii006900690069();
      }
      paramViewGroup.requestFocus();
      return;
      if (!bool)
      {
        paramIbanGroup.checkIbanOfflineOnline();
        i = bo006F006Fo006Foo006F006F;
        switch (i * (b006F006Foo006Foo006F006F + i) % boo006Fo006Foo006F006F)
        {
        default: 
          bo006F006Fo006Foo006F006F = 29;
          b006Fo006Fo006Foo006F006F = 94;
        }
        i = b0069ii00690069ii006900690069();
        int j = b006F006Foo006Foo006F006F;
        if ((b0069ii00690069ii006900690069() + b006F006Foo006Foo006F006F) * b0069ii00690069ii006900690069() % boo006Fo006Foo006F006F != b006Fo006Fo006Foo006F006F) {
          b006Fo006Fo006Foo006F006F = b0069ii00690069ii006900690069();
        }
        switch (i * (j + i) % boo006Fo006Foo006F006F)
        {
        }
        b006F006Foo006Foo006F006F = b0069ii00690069ii006900690069();
      }
    }
  }
  
  /* Error */
  public static void bii006900690069ii006900690069(android.content.Context paramContext, android.widget.EditText paramEditText)
  {
    // Byte code:
    //   0: new 88	uuuuuu/sxssss
    //   3: dup
    //   4: invokespecial 89	uuuuuu/sxssss:<init>	()V
    //   7: astore_3
    //   8: new 91	java/util/ArrayList
    //   11: dup
    //   12: invokespecial 92	java/util/ArrayList:<init>	()V
    //   15: astore 4
    //   17: ldc 94
    //   19: ldc 96
    //   21: bipush 49
    //   23: iconst_3
    //   24: invokestatic 102	xxxxxx/uxxxxx:bb00620062bb0062b0062b0062	(Ljava/lang/String;CC)Ljava/lang/String;
    //   27: iconst_3
    //   28: anewarray 104	java/lang/Class
    //   31: dup
    //   32: iconst_0
    //   33: ldc 106
    //   35: aastore
    //   36: dup
    //   37: iconst_1
    //   38: getstatic 112	java/lang/Character:TYPE	Ljava/lang/Class;
    //   41: aastore
    //   42: dup
    //   43: iconst_2
    //   44: getstatic 112	java/lang/Character:TYPE	Ljava/lang/Class;
    //   47: aastore
    //   48: invokevirtual 116	java/lang/Class:getMethod	(Ljava/lang/String;[Ljava/lang/Class;)Ljava/lang/reflect/Method;
    //   51: astore 5
    //   53: aload 5
    //   55: aconst_null
    //   56: iconst_3
    //   57: anewarray 4	java/lang/Object
    //   60: dup
    //   61: iconst_0
    //   62: ldc 118
    //   64: aastore
    //   65: dup
    //   66: iconst_1
    //   67: bipush 78
    //   69: invokestatic 122	java/lang/Character:valueOf	(C)Ljava/lang/Character;
    //   72: aastore
    //   73: dup
    //   74: iconst_2
    //   75: iconst_2
    //   76: invokestatic 122	java/lang/Character:valueOf	(C)Ljava/lang/Character;
    //   79: aastore
    //   80: invokevirtual 128	java/lang/reflect/Method:invoke	(Ljava/lang/Object;[Ljava/lang/Object;)Ljava/lang/Object;
    //   83: astore 5
    //   85: aload 4
    //   87: aload 5
    //   89: checkcast 106	java/lang/String
    //   92: invokevirtual 132	java/util/ArrayList:add	(Ljava/lang/Object;)Z
    //   95: pop
    //   96: ldc 94
    //   98: ldc -122
    //   100: bipush 71
    //   102: iconst_3
    //   103: invokestatic 102	xxxxxx/uxxxxx:bb00620062bb0062b0062b0062	(Ljava/lang/String;CC)Ljava/lang/String;
    //   106: iconst_3
    //   107: anewarray 104	java/lang/Class
    //   110: dup
    //   111: iconst_0
    //   112: ldc 106
    //   114: aastore
    //   115: dup
    //   116: iconst_1
    //   117: getstatic 112	java/lang/Character:TYPE	Ljava/lang/Class;
    //   120: aastore
    //   121: dup
    //   122: iconst_2
    //   123: getstatic 112	java/lang/Character:TYPE	Ljava/lang/Class;
    //   126: aastore
    //   127: invokevirtual 116	java/lang/Class:getMethod	(Ljava/lang/String;[Ljava/lang/Class;)Ljava/lang/reflect/Method;
    //   130: astore 5
    //   132: aload 5
    //   134: aconst_null
    //   135: iconst_3
    //   136: anewarray 4	java/lang/Object
    //   139: dup
    //   140: iconst_0
    //   141: ldc -120
    //   143: aastore
    //   144: dup
    //   145: iconst_1
    //   146: sipush 157
    //   149: invokestatic 122	java/lang/Character:valueOf	(C)Ljava/lang/Character;
    //   152: aastore
    //   153: dup
    //   154: iconst_2
    //   155: iconst_2
    //   156: invokestatic 122	java/lang/Character:valueOf	(C)Ljava/lang/Character;
    //   159: aastore
    //   160: invokevirtual 128	java/lang/reflect/Method:invoke	(Ljava/lang/Object;[Ljava/lang/Object;)Ljava/lang/Object;
    //   163: astore 5
    //   165: aload 4
    //   167: aload 5
    //   169: checkcast 106	java/lang/String
    //   172: invokevirtual 132	java/util/ArrayList:add	(Ljava/lang/Object;)Z
    //   175: pop
    //   176: ldc 94
    //   178: ldc -118
    //   180: sipush 240
    //   183: iconst_2
    //   184: invokestatic 102	xxxxxx/uxxxxx:bb00620062bb0062b0062b0062	(Ljava/lang/String;CC)Ljava/lang/String;
    //   187: iconst_3
    //   188: anewarray 104	java/lang/Class
    //   191: dup
    //   192: iconst_0
    //   193: ldc 106
    //   195: aastore
    //   196: dup
    //   197: iconst_1
    //   198: getstatic 112	java/lang/Character:TYPE	Ljava/lang/Class;
    //   201: aastore
    //   202: dup
    //   203: iconst_2
    //   204: getstatic 112	java/lang/Character:TYPE	Ljava/lang/Class;
    //   207: aastore
    //   208: invokevirtual 116	java/lang/Class:getMethod	(Ljava/lang/String;[Ljava/lang/Class;)Ljava/lang/reflect/Method;
    //   211: astore 5
    //   213: aload 5
    //   215: aconst_null
    //   216: iconst_3
    //   217: anewarray 4	java/lang/Object
    //   220: dup
    //   221: iconst_0
    //   222: ldc -116
    //   224: aastore
    //   225: dup
    //   226: iconst_1
    //   227: sipush 189
    //   230: invokestatic 122	java/lang/Character:valueOf	(C)Ljava/lang/Character;
    //   233: aastore
    //   234: dup
    //   235: iconst_2
    //   236: iconst_3
    //   237: invokestatic 122	java/lang/Character:valueOf	(C)Ljava/lang/Character;
    //   240: aastore
    //   241: invokevirtual 128	java/lang/reflect/Method:invoke	(Ljava/lang/Object;[Ljava/lang/Object;)Ljava/lang/Object;
    //   244: astore 5
    //   246: aload 4
    //   248: aload 5
    //   250: checkcast 106	java/lang/String
    //   253: invokevirtual 132	java/util/ArrayList:add	(Ljava/lang/Object;)Z
    //   256: pop
    //   257: ldc 94
    //   259: ldc -114
    //   261: bipush 126
    //   263: iconst_0
    //   264: invokestatic 102	xxxxxx/uxxxxx:bb00620062bb0062b0062b0062	(Ljava/lang/String;CC)Ljava/lang/String;
    //   267: iconst_3
    //   268: anewarray 104	java/lang/Class
    //   271: dup
    //   272: iconst_0
    //   273: ldc 106
    //   275: aastore
    //   276: dup
    //   277: iconst_1
    //   278: getstatic 112	java/lang/Character:TYPE	Ljava/lang/Class;
    //   281: aastore
    //   282: dup
    //   283: iconst_2
    //   284: getstatic 112	java/lang/Character:TYPE	Ljava/lang/Class;
    //   287: aastore
    //   288: invokevirtual 116	java/lang/Class:getMethod	(Ljava/lang/String;[Ljava/lang/Class;)Ljava/lang/reflect/Method;
    //   291: astore 5
    //   293: aload 5
    //   295: aconst_null
    //   296: iconst_3
    //   297: anewarray 4	java/lang/Object
    //   300: dup
    //   301: iconst_0
    //   302: ldc -112
    //   304: aastore
    //   305: dup
    //   306: iconst_1
    //   307: bipush 73
    //   309: invokestatic 122	java/lang/Character:valueOf	(C)Ljava/lang/Character;
    //   312: aastore
    //   313: dup
    //   314: iconst_2
    //   315: iconst_0
    //   316: invokestatic 122	java/lang/Character:valueOf	(C)Ljava/lang/Character;
    //   319: aastore
    //   320: invokevirtual 128	java/lang/reflect/Method:invoke	(Ljava/lang/Object;[Ljava/lang/Object;)Ljava/lang/Object;
    //   323: astore 5
    //   325: aload 4
    //   327: aload 5
    //   329: checkcast 106	java/lang/String
    //   332: invokevirtual 132	java/util/ArrayList:add	(Ljava/lang/Object;)Z
    //   335: pop
    //   336: ldc 94
    //   338: ldc -110
    //   340: bipush 27
    //   342: iconst_5
    //   343: invokestatic 102	xxxxxx/uxxxxx:bb00620062bb0062b0062b0062	(Ljava/lang/String;CC)Ljava/lang/String;
    //   346: iconst_3
    //   347: anewarray 104	java/lang/Class
    //   350: dup
    //   351: iconst_0
    //   352: ldc 106
    //   354: aastore
    //   355: dup
    //   356: iconst_1
    //   357: getstatic 112	java/lang/Character:TYPE	Ljava/lang/Class;
    //   360: aastore
    //   361: dup
    //   362: iconst_2
    //   363: getstatic 112	java/lang/Character:TYPE	Ljava/lang/Class;
    //   366: aastore
    //   367: invokevirtual 116	java/lang/Class:getMethod	(Ljava/lang/String;[Ljava/lang/Class;)Ljava/lang/reflect/Method;
    //   370: astore 5
    //   372: aload 5
    //   374: aconst_null
    //   375: iconst_3
    //   376: anewarray 4	java/lang/Object
    //   379: dup
    //   380: iconst_0
    //   381: ldc -108
    //   383: aastore
    //   384: dup
    //   385: iconst_1
    //   386: sipush 197
    //   389: invokestatic 122	java/lang/Character:valueOf	(C)Ljava/lang/Character;
    //   392: aastore
    //   393: dup
    //   394: iconst_2
    //   395: iconst_1
    //   396: invokestatic 122	java/lang/Character:valueOf	(C)Ljava/lang/Character;
    //   399: aastore
    //   400: invokevirtual 128	java/lang/reflect/Method:invoke	(Ljava/lang/Object;[Ljava/lang/Object;)Ljava/lang/Object;
    //   403: astore 5
    //   405: aload 4
    //   407: aload 5
    //   409: checkcast 106	java/lang/String
    //   412: invokevirtual 132	java/util/ArrayList:add	(Ljava/lang/Object;)Z
    //   415: pop
    //   416: ldc 94
    //   418: ldc -106
    //   420: sipush 195
    //   423: iconst_1
    //   424: invokestatic 102	xxxxxx/uxxxxx:bb00620062bb0062b0062b0062	(Ljava/lang/String;CC)Ljava/lang/String;
    //   427: iconst_3
    //   428: anewarray 104	java/lang/Class
    //   431: dup
    //   432: iconst_0
    //   433: ldc 106
    //   435: aastore
    //   436: dup
    //   437: iconst_1
    //   438: getstatic 112	java/lang/Character:TYPE	Ljava/lang/Class;
    //   441: aastore
    //   442: dup
    //   443: iconst_2
    //   444: getstatic 112	java/lang/Character:TYPE	Ljava/lang/Class;
    //   447: aastore
    //   448: invokevirtual 116	java/lang/Class:getMethod	(Ljava/lang/String;[Ljava/lang/Class;)Ljava/lang/reflect/Method;
    //   451: astore 5
    //   453: aload 5
    //   455: aconst_null
    //   456: iconst_3
    //   457: anewarray 4	java/lang/Object
    //   460: dup
    //   461: iconst_0
    //   462: ldc -104
    //   464: aastore
    //   465: dup
    //   466: iconst_1
    //   467: bipush 119
    //   469: invokestatic 122	java/lang/Character:valueOf	(C)Ljava/lang/Character;
    //   472: aastore
    //   473: dup
    //   474: iconst_2
    //   475: iconst_2
    //   476: invokestatic 122	java/lang/Character:valueOf	(C)Ljava/lang/Character;
    //   479: aastore
    //   480: invokevirtual 128	java/lang/reflect/Method:invoke	(Ljava/lang/Object;[Ljava/lang/Object;)Ljava/lang/Object;
    //   483: astore 5
    //   485: aload 4
    //   487: aload 5
    //   489: checkcast 106	java/lang/String
    //   492: invokevirtual 132	java/util/ArrayList:add	(Ljava/lang/Object;)Z
    //   495: pop
    //   496: new 91	java/util/ArrayList
    //   499: dup
    //   500: invokespecial 92	java/util/ArrayList:<init>	()V
    //   503: astore 5
    //   505: getstatic 35	uuuuuu/vlllvv:bo006F006Fo006Foo006F006F	I
    //   508: istore_2
    //   509: iload_2
    //   510: getstatic 37	uuuuuu/vlllvv:b006F006Foo006Foo006F006F	I
    //   513: iload_2
    //   514: iadd
    //   515: imul
    //   516: getstatic 39	uuuuuu/vlllvv:boo006Fo006Foo006F006F	I
    //   519: irem
    //   520: tableswitch	default:+20->540, 0:+31->551
    //   540: invokestatic 45	uuuuuu/vlllvv:b0069ii00690069ii006900690069	()I
    //   543: putstatic 35	uuuuuu/vlllvv:bo006F006Fo006Foo006F006F	I
    //   546: bipush 60
    //   548: putstatic 41	uuuuuu/vlllvv:b006Fo006Fo006Foo006F006F	I
    //   551: ldc 94
    //   553: ldc -102
    //   555: bipush 62
    //   557: sipush 212
    //   560: iconst_2
    //   561: invokestatic 158	xxxxxx/uxxxxx:bbbb0062b0062b0062b0062	(Ljava/lang/String;CCC)Ljava/lang/String;
    //   564: iconst_4
    //   565: anewarray 104	java/lang/Class
    //   568: dup
    //   569: iconst_0
    //   570: ldc 106
    //   572: aastore
    //   573: dup
    //   574: iconst_1
    //   575: getstatic 112	java/lang/Character:TYPE	Ljava/lang/Class;
    //   578: aastore
    //   579: dup
    //   580: iconst_2
    //   581: getstatic 112	java/lang/Character:TYPE	Ljava/lang/Class;
    //   584: aastore
    //   585: dup
    //   586: iconst_3
    //   587: getstatic 112	java/lang/Character:TYPE	Ljava/lang/Class;
    //   590: aastore
    //   591: invokevirtual 116	java/lang/Class:getMethod	(Ljava/lang/String;[Ljava/lang/Class;)Ljava/lang/reflect/Method;
    //   594: astore 6
    //   596: aload 6
    //   598: aconst_null
    //   599: iconst_4
    //   600: anewarray 4	java/lang/Object
    //   603: dup
    //   604: iconst_0
    //   605: ldc -96
    //   607: aastore
    //   608: dup
    //   609: iconst_1
    //   610: sipush 233
    //   613: invokestatic 122	java/lang/Character:valueOf	(C)Ljava/lang/Character;
    //   616: aastore
    //   617: dup
    //   618: iconst_2
    //   619: bipush 17
    //   621: invokestatic 122	java/lang/Character:valueOf	(C)Ljava/lang/Character;
    //   624: aastore
    //   625: dup
    //   626: iconst_3
    //   627: iconst_2
    //   628: invokestatic 122	java/lang/Character:valueOf	(C)Ljava/lang/Character;
    //   631: aastore
    //   632: invokevirtual 128	java/lang/reflect/Method:invoke	(Ljava/lang/Object;[Ljava/lang/Object;)Ljava/lang/Object;
    //   635: astore 6
    //   637: aload 5
    //   639: aload 6
    //   641: checkcast 106	java/lang/String
    //   644: invokevirtual 132	java/util/ArrayList:add	(Ljava/lang/Object;)Z
    //   647: pop
    //   648: ldc 94
    //   650: ldc -94
    //   652: bipush 97
    //   654: iconst_4
    //   655: invokestatic 102	xxxxxx/uxxxxx:bb00620062bb0062b0062b0062	(Ljava/lang/String;CC)Ljava/lang/String;
    //   658: iconst_4
    //   659: anewarray 104	java/lang/Class
    //   662: dup
    //   663: iconst_0
    //   664: ldc 106
    //   666: aastore
    //   667: dup
    //   668: iconst_1
    //   669: getstatic 112	java/lang/Character:TYPE	Ljava/lang/Class;
    //   672: aastore
    //   673: dup
    //   674: iconst_2
    //   675: getstatic 112	java/lang/Character:TYPE	Ljava/lang/Class;
    //   678: aastore
    //   679: dup
    //   680: iconst_3
    //   681: getstatic 112	java/lang/Character:TYPE	Ljava/lang/Class;
    //   684: aastore
    //   685: invokevirtual 116	java/lang/Class:getMethod	(Ljava/lang/String;[Ljava/lang/Class;)Ljava/lang/reflect/Method;
    //   688: astore 6
    //   690: aload 6
    //   692: aconst_null
    //   693: iconst_4
    //   694: anewarray 4	java/lang/Object
    //   697: dup
    //   698: iconst_0
    //   699: ldc -92
    //   701: aastore
    //   702: dup
    //   703: iconst_1
    //   704: sipush 193
    //   707: invokestatic 122	java/lang/Character:valueOf	(C)Ljava/lang/Character;
    //   710: aastore
    //   711: dup
    //   712: iconst_2
    //   713: bipush 98
    //   715: invokestatic 122	java/lang/Character:valueOf	(C)Ljava/lang/Character;
    //   718: aastore
    //   719: dup
    //   720: iconst_3
    //   721: iconst_2
    //   722: invokestatic 122	java/lang/Character:valueOf	(C)Ljava/lang/Character;
    //   725: aastore
    //   726: invokevirtual 128	java/lang/reflect/Method:invoke	(Ljava/lang/Object;[Ljava/lang/Object;)Ljava/lang/Object;
    //   729: astore 6
    //   731: aload 5
    //   733: aload 6
    //   735: checkcast 106	java/lang/String
    //   738: invokevirtual 132	java/util/ArrayList:add	(Ljava/lang/Object;)Z
    //   741: pop
    //   742: ldc 94
    //   744: ldc -90
    //   746: bipush 62
    //   748: iconst_0
    //   749: invokestatic 102	xxxxxx/uxxxxx:bb00620062bb0062b0062b0062	(Ljava/lang/String;CC)Ljava/lang/String;
    //   752: iconst_3
    //   753: anewarray 104	java/lang/Class
    //   756: dup
    //   757: iconst_0
    //   758: ldc 106
    //   760: aastore
    //   761: dup
    //   762: iconst_1
    //   763: getstatic 112	java/lang/Character:TYPE	Ljava/lang/Class;
    //   766: aastore
    //   767: dup
    //   768: iconst_2
    //   769: getstatic 112	java/lang/Character:TYPE	Ljava/lang/Class;
    //   772: aastore
    //   773: invokevirtual 116	java/lang/Class:getMethod	(Ljava/lang/String;[Ljava/lang/Class;)Ljava/lang/reflect/Method;
    //   776: astore 6
    //   778: aload 6
    //   780: aconst_null
    //   781: iconst_3
    //   782: anewarray 4	java/lang/Object
    //   785: dup
    //   786: iconst_0
    //   787: ldc -88
    //   789: aastore
    //   790: dup
    //   791: iconst_1
    //   792: sipush 216
    //   795: invokestatic 122	java/lang/Character:valueOf	(C)Ljava/lang/Character;
    //   798: aastore
    //   799: dup
    //   800: iconst_2
    //   801: iconst_4
    //   802: invokestatic 122	java/lang/Character:valueOf	(C)Ljava/lang/Character;
    //   805: aastore
    //   806: invokevirtual 128	java/lang/reflect/Method:invoke	(Ljava/lang/Object;[Ljava/lang/Object;)Ljava/lang/Object;
    //   809: astore 6
    //   811: aload 6
    //   813: checkcast 106	java/lang/String
    //   816: astore 6
    //   818: getstatic 35	uuuuuu/vlllvv:bo006F006Fo006Foo006F006F	I
    //   821: istore_2
    //   822: iload_2
    //   823: getstatic 37	uuuuuu/vlllvv:b006F006Foo006Foo006F006F	I
    //   826: iload_2
    //   827: iadd
    //   828: imul
    //   829: getstatic 39	uuuuuu/vlllvv:boo006Fo006Foo006F006F	I
    //   832: irem
    //   833: tableswitch	default:+19->852, 0:+30->863
    //   852: bipush 45
    //   854: putstatic 35	uuuuuu/vlllvv:bo006F006Fo006Foo006F006F	I
    //   857: invokestatic 45	uuuuuu/vlllvv:b0069ii00690069ii006900690069	()I
    //   860: putstatic 41	uuuuuu/vlllvv:b006Fo006Fo006Foo006F006F	I
    //   863: aload 5
    //   865: aload 6
    //   867: invokevirtual 132	java/util/ArrayList:add	(Ljava/lang/Object;)Z
    //   870: pop
    //   871: ldc 94
    //   873: ldc -86
    //   875: sipush 136
    //   878: sipush 171
    //   881: iconst_0
    //   882: invokestatic 158	xxxxxx/uxxxxx:bbbb0062b0062b0062b0062	(Ljava/lang/String;CCC)Ljava/lang/String;
    //   885: iconst_3
    //   886: anewarray 104	java/lang/Class
    //   889: dup
    //   890: iconst_0
    //   891: ldc 106
    //   893: aastore
    //   894: dup
    //   895: iconst_1
    //   896: getstatic 112	java/lang/Character:TYPE	Ljava/lang/Class;
    //   899: aastore
    //   900: dup
    //   901: iconst_2
    //   902: getstatic 112	java/lang/Character:TYPE	Ljava/lang/Class;
    //   905: aastore
    //   906: invokevirtual 116	java/lang/Class:getMethod	(Ljava/lang/String;[Ljava/lang/Class;)Ljava/lang/reflect/Method;
    //   909: astore 6
    //   911: aload 6
    //   913: aconst_null
    //   914: iconst_3
    //   915: anewarray 4	java/lang/Object
    //   918: dup
    //   919: iconst_0
    //   920: ldc -84
    //   922: aastore
    //   923: dup
    //   924: iconst_1
    //   925: bipush 104
    //   927: invokestatic 122	java/lang/Character:valueOf	(C)Ljava/lang/Character;
    //   930: aastore
    //   931: dup
    //   932: iconst_2
    //   933: iconst_2
    //   934: invokestatic 122	java/lang/Character:valueOf	(C)Ljava/lang/Character;
    //   937: aastore
    //   938: invokevirtual 128	java/lang/reflect/Method:invoke	(Ljava/lang/Object;[Ljava/lang/Object;)Ljava/lang/Object;
    //   941: astore 6
    //   943: aload 5
    //   945: aload 6
    //   947: checkcast 106	java/lang/String
    //   950: invokevirtual 132	java/util/ArrayList:add	(Ljava/lang/Object;)Z
    //   953: pop
    //   954: getstatic 35	uuuuuu/vlllvv:bo006F006Fo006Foo006F006F	I
    //   957: istore_2
    //   958: iload_2
    //   959: getstatic 37	uuuuuu/vlllvv:b006F006Foo006Foo006F006F	I
    //   962: iload_2
    //   963: iadd
    //   964: imul
    //   965: getstatic 39	uuuuuu/vlllvv:boo006Fo006Foo006F006F	I
    //   968: irem
    //   969: tableswitch	default:+19->988, 0:+29->998
    //   988: bipush 92
    //   990: putstatic 35	uuuuuu/vlllvv:bo006F006Fo006Foo006F006F	I
    //   993: bipush 14
    //   995: putstatic 41	uuuuuu/vlllvv:b006Fo006Fo006Foo006F006F	I
    //   998: ldc 94
    //   1000: ldc -82
    //   1002: bipush 70
    //   1004: iconst_5
    //   1005: invokestatic 102	xxxxxx/uxxxxx:bb00620062bb0062b0062b0062	(Ljava/lang/String;CC)Ljava/lang/String;
    //   1008: iconst_3
    //   1009: anewarray 104	java/lang/Class
    //   1012: dup
    //   1013: iconst_0
    //   1014: ldc 106
    //   1016: aastore
    //   1017: dup
    //   1018: iconst_1
    //   1019: getstatic 112	java/lang/Character:TYPE	Ljava/lang/Class;
    //   1022: aastore
    //   1023: dup
    //   1024: iconst_2
    //   1025: getstatic 112	java/lang/Character:TYPE	Ljava/lang/Class;
    //   1028: aastore
    //   1029: invokevirtual 116	java/lang/Class:getMethod	(Ljava/lang/String;[Ljava/lang/Class;)Ljava/lang/reflect/Method;
    //   1032: astore 6
    //   1034: aload 6
    //   1036: aconst_null
    //   1037: iconst_3
    //   1038: anewarray 4	java/lang/Object
    //   1041: dup
    //   1042: iconst_0
    //   1043: ldc -80
    //   1045: aastore
    //   1046: dup
    //   1047: iconst_1
    //   1048: sipush 142
    //   1051: invokestatic 122	java/lang/Character:valueOf	(C)Ljava/lang/Character;
    //   1054: aastore
    //   1055: dup
    //   1056: iconst_2
    //   1057: iconst_3
    //   1058: invokestatic 122	java/lang/Character:valueOf	(C)Ljava/lang/Character;
    //   1061: aastore
    //   1062: invokevirtual 128	java/lang/reflect/Method:invoke	(Ljava/lang/Object;[Ljava/lang/Object;)Ljava/lang/Object;
    //   1065: astore 6
    //   1067: aload 5
    //   1069: aload 6
    //   1071: checkcast 106	java/lang/String
    //   1074: invokevirtual 132	java/util/ArrayList:add	(Ljava/lang/Object;)Z
    //   1077: pop
    //   1078: getstatic 181	com/db/pwcc/dbmobile/transfer/R$layout:dialog_textview_black	I
    //   1081: istore_2
    //   1082: getstatic 35	uuuuuu/vlllvv:bo006F006Fo006Foo006F006F	I
    //   1085: getstatic 37	uuuuuu/vlllvv:b006F006Foo006Foo006F006F	I
    //   1088: iadd
    //   1089: getstatic 35	uuuuuu/vlllvv:bo006F006Fo006Foo006F006F	I
    //   1092: imul
    //   1093: getstatic 39	uuuuuu/vlllvv:boo006Fo006Foo006F006F	I
    //   1096: irem
    //   1097: getstatic 41	uuuuuu/vlllvv:b006Fo006Fo006Foo006F006F	I
    //   1100: if_icmpeq +13 -> 1113
    //   1103: bipush 99
    //   1105: putstatic 35	uuuuuu/vlllvv:bo006F006Fo006Foo006F006F	I
    //   1108: bipush 28
    //   1110: putstatic 41	uuuuuu/vlllvv:b006Fo006Fo006Foo006F006F	I
    //   1113: aload_1
    //   1114: new 183	uuuuuu/vlllvv$2
    //   1117: dup
    //   1118: aload_3
    //   1119: aload_0
    //   1120: new 185	android/widget/ArrayAdapter
    //   1123: dup
    //   1124: aload_0
    //   1125: iload_2
    //   1126: aload 4
    //   1128: invokespecial 188	android/widget/ArrayAdapter:<init>	(Landroid/content/Context;ILjava/util/List;)V
    //   1131: new 190	uuuuuu/vlllvv$1
    //   1134: dup
    //   1135: aload_0
    //   1136: aload_1
    //   1137: aload_3
    //   1138: aload 5
    //   1140: invokespecial 193	uuuuuu/vlllvv$1:<init>	(Landroid/content/Context;Landroid/widget/EditText;Luuuuuu/sxssss;Ljava/util/ArrayList;)V
    //   1143: aload_1
    //   1144: invokespecial 196	uuuuuu/vlllvv$2:<init>	(Luuuuuu/sxssss;Landroid/content/Context;Landroid/widget/ArrayAdapter;Landroid/widget/AdapterView$OnItemClickListener;Landroid/widget/EditText;)V
    //   1147: invokevirtual 202	android/widget/EditText:setOnLongClickListener	(Landroid/view/View$OnLongClickListener;)V
    //   1150: return
    //   1151: astore_0
    //   1152: aload_0
    //   1153: invokevirtual 206	java/lang/reflect/InvocationTargetException:getCause	()Ljava/lang/Throwable;
    //   1156: athrow
    //   1157: astore_0
    //   1158: aload_0
    //   1159: invokevirtual 206	java/lang/reflect/InvocationTargetException:getCause	()Ljava/lang/Throwable;
    //   1162: athrow
    //   1163: astore_0
    //   1164: aload_0
    //   1165: invokevirtual 206	java/lang/reflect/InvocationTargetException:getCause	()Ljava/lang/Throwable;
    //   1168: athrow
    //   1169: astore_0
    //   1170: aload_0
    //   1171: invokevirtual 206	java/lang/reflect/InvocationTargetException:getCause	()Ljava/lang/Throwable;
    //   1174: athrow
    //   1175: astore_0
    //   1176: aload_0
    //   1177: invokevirtual 206	java/lang/reflect/InvocationTargetException:getCause	()Ljava/lang/Throwable;
    //   1180: athrow
    //   1181: astore_0
    //   1182: aload_0
    //   1183: invokevirtual 206	java/lang/reflect/InvocationTargetException:getCause	()Ljava/lang/Throwable;
    //   1186: athrow
    //   1187: astore_0
    //   1188: aload_0
    //   1189: invokevirtual 206	java/lang/reflect/InvocationTargetException:getCause	()Ljava/lang/Throwable;
    //   1192: athrow
    //   1193: astore_0
    //   1194: aload_0
    //   1195: invokevirtual 206	java/lang/reflect/InvocationTargetException:getCause	()Ljava/lang/Throwable;
    //   1198: athrow
    //   1199: astore_0
    //   1200: aload_0
    //   1201: invokevirtual 206	java/lang/reflect/InvocationTargetException:getCause	()Ljava/lang/Throwable;
    //   1204: athrow
    //   1205: astore_0
    //   1206: aload_0
    //   1207: invokevirtual 206	java/lang/reflect/InvocationTargetException:getCause	()Ljava/lang/Throwable;
    //   1210: athrow
    //   1211: astore_0
    //   1212: aload_0
    //   1213: invokevirtual 206	java/lang/reflect/InvocationTargetException:getCause	()Ljava/lang/Throwable;
    //   1216: athrow
    // Local variable table:
    //   start	length	slot	name	signature
    //   0	1217	0	paramContext	android.content.Context
    //   0	1217	1	paramEditText	android.widget.EditText
    //   508	618	2	i	int
    //   7	1131	3	localSxssss	sxssss
    //   15	1112	4	localArrayList	java.util.ArrayList
    //   51	1088	5	localObject1	Object
    //   594	476	6	localObject2	Object
    // Exception table:
    //   from	to	target	type
    //   778	811	1151	java/lang/reflect/InvocationTargetException
    //   293	325	1157	java/lang/reflect/InvocationTargetException
    //   453	485	1163	java/lang/reflect/InvocationTargetException
    //   911	943	1169	java/lang/reflect/InvocationTargetException
    //   372	405	1175	java/lang/reflect/InvocationTargetException
    //   132	165	1181	java/lang/reflect/InvocationTargetException
    //   1034	1067	1187	java/lang/reflect/InvocationTargetException
    //   53	85	1193	java/lang/reflect/InvocationTargetException
    //   596	637	1199	java/lang/reflect/InvocationTargetException
    //   690	731	1205	java/lang/reflect/InvocationTargetException
    //   213	246	1211	java/lang/reflect/InvocationTargetException
  }
  
  public static int biii00690069ii006900690069()
  {
    return 2;
  }
}
