package uuuuuu;

import android.content.Context;
import android.os.Bundle;
import com.db.pwcc.dbmobile.foundation.data.manager.broadcasting.ModelUpdatedBroadcastReceiver;
import com.db.pwcc.dbmobile.investment.tiles.InvestmentsTile;
import com.db.pwcc.dbmobile.model.error.DbError;
import com.db.pwcc.dbmobile.treatments.views.TreatmentTile;
import com.db.pwcc.dbmobile.user_review.tiles.UserReviewTile;
import com.db.pwcc.dbmobile.user_review.tiles.UserReviewTile.pppphh;
import java.lang.reflect.InvocationTargetException;
import java.lang.reflect.Method;
import java.util.Iterator;
import java.util.List;
import javax.inject.Inject;
import xxxxxx.uxxxxx;

public class vuuvuv
  extends qppppp<uuvvuv.uvuvuv>
  implements uuvvuv.vvuvuv
{
  public static int b00690069i006900690069i0069i = 1;
  public static int b0069i0069006900690069i0069i = 0;
  public static final String b0069iii00690069i0069i = "O@PNLMaLRKUYUJ^T[[mdcRYXsXelfm";
  public static int bi0069i006900690069i0069i = 52;
  public static int bii0069006900690069i0069i = 2;
  public static final int biiii00690069i0069i = 4;
  @Inject
  public gaaaga b006900690069i00690069i0069i;
  @Inject
  public qpqqqq b00690069ii00690069i0069i;
  public uuvuuv b0069i0069i00690069i0069i;
  @Inject
  public phphph b0069ii006900690069i0069i;
  public ooooon bi00690069i00690069i0069i;
  @Inject
  public sssttt bi0069ii00690069i0069i;
  public ModelUpdatedBroadcastReceiver bii0069i00690069i0069i;
  @Inject
  public sssxxx biii006900690069i0069i;
  
  public vuuvuv() {}
  
  public static int b00610061aaaaa00610061a()
  {
    return 2;
  }
  
  public static int b0061a0061aaaa00610061a()
  {
    return 95;
  }
  
  /* Error */
  private boolean b0061aaa0061aa00610061a()
  {
    // Byte code:
    //   0: getstatic 59	uuuuuu/vuuvuv:bi0069i006900690069i0069i	I
    //   3: istore_1
    //   4: iload_1
    //   5: getstatic 103	uuuuuu/vuuvuv:b00690069i006900690069i0069i	I
    //   8: iload_1
    //   9: iadd
    //   10: imul
    //   11: getstatic 89	uuuuuu/vuuvuv:bii0069006900690069i0069i	I
    //   14: irem
    //   15: tableswitch	default:+17->32, 0:+61->76
    //   32: bipush 13
    //   34: putstatic 59	uuuuuu/vuuvuv:bi0069i006900690069i0069i	I
    //   37: ldc 2
    //   39: ldc 123
    //   41: sipush 169
    //   44: iconst_0
    //   45: invokestatic 101	xxxxxx/uxxxxx:bb00620062bb0062b0062b0062	(Ljava/lang/String;CC)Ljava/lang/String;
    //   48: iconst_0
    //   49: anewarray 69	java/lang/Class
    //   52: invokevirtual 73	java/lang/Class:getMethod	(Ljava/lang/String;[Ljava/lang/Class;)Ljava/lang/reflect/Method;
    //   55: astore_3
    //   56: aload_3
    //   57: aconst_null
    //   58: iconst_0
    //   59: anewarray 75	java/lang/Object
    //   62: invokevirtual 81	java/lang/reflect/Method:invoke	(Ljava/lang/Object;[Ljava/lang/Object;)Ljava/lang/Object;
    //   65: astore_3
    //   66: aload_3
    //   67: checkcast 83	java/lang/Integer
    //   70: invokevirtual 87	java/lang/Integer:intValue	()I
    //   73: putstatic 91	uuuuuu/vuuvuv:b0069i0069006900690069i0069i	I
    //   76: ldc 125
    //   78: ldc 127
    //   80: sipush 228
    //   83: iconst_4
    //   84: invokestatic 101	xxxxxx/uxxxxx:bb00620062bb0062b0062b0062	(Ljava/lang/String;CC)Ljava/lang/String;
    //   87: iconst_0
    //   88: anewarray 69	java/lang/Class
    //   91: invokevirtual 73	java/lang/Class:getMethod	(Ljava/lang/String;[Ljava/lang/Class;)Ljava/lang/reflect/Method;
    //   94: astore_3
    //   95: aload_3
    //   96: aconst_null
    //   97: iconst_0
    //   98: anewarray 75	java/lang/Object
    //   101: invokevirtual 81	java/lang/reflect/Method:invoke	(Ljava/lang/Object;[Ljava/lang/Object;)Ljava/lang/Object;
    //   104: astore_3
    //   105: aload_3
    //   106: checkcast 125	com/db/pwcc/dbmobile/secure/preferences/SharedPreferencesHelper
    //   109: astore_3
    //   110: ldc 125
    //   112: ldc -127
    //   114: bipush 117
    //   116: iconst_3
    //   117: invokestatic 101	xxxxxx/uxxxxx:bb00620062bb0062b0062b0062	(Ljava/lang/String;CC)Ljava/lang/String;
    //   120: iconst_0
    //   121: anewarray 69	java/lang/Class
    //   124: invokevirtual 73	java/lang/Class:getMethod	(Ljava/lang/String;[Ljava/lang/Class;)Ljava/lang/reflect/Method;
    //   127: astore 4
    //   129: aload 4
    //   131: aload_3
    //   132: iconst_0
    //   133: anewarray 75	java/lang/Object
    //   136: invokevirtual 81	java/lang/reflect/Method:invoke	(Ljava/lang/Object;[Ljava/lang/Object;)Ljava/lang/Object;
    //   139: astore_3
    //   140: aload_3
    //   141: checkcast 131	java/lang/Boolean
    //   144: invokevirtual 134	java/lang/Boolean:booleanValue	()Z
    //   147: ifeq +12 -> 159
    //   150: aload_0
    //   151: invokevirtual 137	uuuuuu/vuuvuv:b006Bk006B006Bkk006Bk006Bk	()Z
    //   154: ifne +5 -> 159
    //   157: iconst_1
    //   158: ireturn
    //   159: getstatic 59	uuuuuu/vuuvuv:bi0069i006900690069i0069i	I
    //   162: istore_1
    //   163: iload_1
    //   164: getstatic 103	uuuuuu/vuuvuv:b00690069i006900690069i0069i	I
    //   167: iload_1
    //   168: iadd
    //   169: imul
    //   170: getstatic 89	uuuuuu/vuuvuv:bii0069006900690069i0069i	I
    //   173: irem
    //   174: tableswitch	default:+18->192, 0:+252->426
    //   192: ldc 2
    //   194: ldc -117
    //   196: sipush 179
    //   199: iconst_5
    //   200: invokestatic 101	xxxxxx/uxxxxx:bb00620062bb0062b0062b0062	(Ljava/lang/String;CC)Ljava/lang/String;
    //   203: iconst_0
    //   204: anewarray 69	java/lang/Class
    //   207: invokevirtual 73	java/lang/Class:getMethod	(Ljava/lang/String;[Ljava/lang/Class;)Ljava/lang/reflect/Method;
    //   210: astore_3
    //   211: aload_3
    //   212: aconst_null
    //   213: iconst_0
    //   214: anewarray 75	java/lang/Object
    //   217: invokevirtual 81	java/lang/reflect/Method:invoke	(Ljava/lang/Object;[Ljava/lang/Object;)Ljava/lang/Object;
    //   220: astore_3
    //   221: aload_3
    //   222: checkcast 83	java/lang/Integer
    //   225: invokevirtual 87	java/lang/Integer:intValue	()I
    //   228: putstatic 59	uuuuuu/vuuvuv:bi0069i006900690069i0069i	I
    //   231: getstatic 59	uuuuuu/vuuvuv:bi0069i006900690069i0069i	I
    //   234: istore_1
    //   235: getstatic 103	uuuuuu/vuuvuv:b00690069i006900690069i0069i	I
    //   238: istore_2
    //   239: ldc 2
    //   241: ldc -115
    //   243: sipush 145
    //   246: iconst_4
    //   247: invokestatic 101	xxxxxx/uxxxxx:bb00620062bb0062b0062b0062	(Ljava/lang/String;CC)Ljava/lang/String;
    //   250: iconst_0
    //   251: anewarray 69	java/lang/Class
    //   254: invokevirtual 73	java/lang/Class:getMethod	(Ljava/lang/String;[Ljava/lang/Class;)Ljava/lang/reflect/Method;
    //   257: astore_3
    //   258: aload_3
    //   259: aconst_null
    //   260: iconst_0
    //   261: anewarray 75	java/lang/Object
    //   264: invokevirtual 81	java/lang/reflect/Method:invoke	(Ljava/lang/Object;[Ljava/lang/Object;)Ljava/lang/Object;
    //   267: astore_3
    //   268: iload_2
    //   269: iload_1
    //   270: iadd
    //   271: iload_1
    //   272: imul
    //   273: aload_3
    //   274: checkcast 83	java/lang/Integer
    //   277: invokevirtual 87	java/lang/Integer:intValue	()I
    //   280: irem
    //   281: tableswitch	default:+19->300, 0:+98->379
    //   300: ldc 2
    //   302: ldc -113
    //   304: bipush 71
    //   306: sipush 172
    //   309: iconst_0
    //   310: invokestatic 67	xxxxxx/uxxxxx:bbbb0062b0062b0062b0062	(Ljava/lang/String;CCC)Ljava/lang/String;
    //   313: iconst_0
    //   314: anewarray 69	java/lang/Class
    //   317: invokevirtual 73	java/lang/Class:getMethod	(Ljava/lang/String;[Ljava/lang/Class;)Ljava/lang/reflect/Method;
    //   320: astore_3
    //   321: aload_3
    //   322: aconst_null
    //   323: iconst_0
    //   324: anewarray 75	java/lang/Object
    //   327: invokevirtual 81	java/lang/reflect/Method:invoke	(Ljava/lang/Object;[Ljava/lang/Object;)Ljava/lang/Object;
    //   330: astore_3
    //   331: aload_3
    //   332: checkcast 83	java/lang/Integer
    //   335: invokevirtual 87	java/lang/Integer:intValue	()I
    //   338: putstatic 59	uuuuuu/vuuvuv:bi0069i006900690069i0069i	I
    //   341: ldc 2
    //   343: ldc -111
    //   345: bipush 61
    //   347: iconst_4
    //   348: invokestatic 101	xxxxxx/uxxxxx:bb00620062bb0062b0062b0062	(Ljava/lang/String;CC)Ljava/lang/String;
    //   351: iconst_0
    //   352: anewarray 69	java/lang/Class
    //   355: invokevirtual 73	java/lang/Class:getMethod	(Ljava/lang/String;[Ljava/lang/Class;)Ljava/lang/reflect/Method;
    //   358: astore_3
    //   359: aload_3
    //   360: aconst_null
    //   361: iconst_0
    //   362: anewarray 75	java/lang/Object
    //   365: invokevirtual 81	java/lang/reflect/Method:invoke	(Ljava/lang/Object;[Ljava/lang/Object;)Ljava/lang/Object;
    //   368: astore_3
    //   369: aload_3
    //   370: checkcast 83	java/lang/Integer
    //   373: invokevirtual 87	java/lang/Integer:intValue	()I
    //   376: putstatic 91	uuuuuu/vuuvuv:b0069i0069006900690069i0069i	I
    //   379: bipush 87
    //   381: putstatic 91	uuuuuu/vuuvuv:b0069i0069006900690069i0069i	I
    //   384: getstatic 59	uuuuuu/vuuvuv:bi0069i006900690069i0069i	I
    //   387: istore_1
    //   388: iload_1
    //   389: getstatic 103	uuuuuu/vuuvuv:b00690069i006900690069i0069i	I
    //   392: iload_1
    //   393: iadd
    //   394: imul
    //   395: getstatic 89	uuuuuu/vuuvuv:bii0069006900690069i0069i	I
    //   398: irem
    //   399: tableswitch	default:+17->416, 0:+27->426
    //   416: bipush 7
    //   418: putstatic 59	uuuuuu/vuuvuv:bi0069i006900690069i0069i	I
    //   421: bipush 27
    //   423: putstatic 91	uuuuuu/vuuvuv:b0069i0069006900690069i0069i	I
    //   426: iconst_0
    //   427: ireturn
    //   428: astore_3
    //   429: aload_3
    //   430: invokevirtual 117	java/lang/reflect/InvocationTargetException:getCause	()Ljava/lang/Throwable;
    //   433: athrow
    //   434: astore_3
    //   435: aload_3
    //   436: invokevirtual 117	java/lang/reflect/InvocationTargetException:getCause	()Ljava/lang/Throwable;
    //   439: athrow
    //   440: astore_3
    //   441: aload_3
    //   442: invokevirtual 117	java/lang/reflect/InvocationTargetException:getCause	()Ljava/lang/Throwable;
    //   445: athrow
    //   446: astore_3
    //   447: aload_3
    //   448: invokevirtual 117	java/lang/reflect/InvocationTargetException:getCause	()Ljava/lang/Throwable;
    //   451: athrow
    //   452: astore_3
    //   453: aload_3
    //   454: invokevirtual 117	java/lang/reflect/InvocationTargetException:getCause	()Ljava/lang/Throwable;
    //   457: athrow
    //   458: astore_3
    //   459: aload_3
    //   460: invokevirtual 117	java/lang/reflect/InvocationTargetException:getCause	()Ljava/lang/Throwable;
    //   463: athrow
    //   464: astore_3
    //   465: aload_3
    //   466: invokevirtual 117	java/lang/reflect/InvocationTargetException:getCause	()Ljava/lang/Throwable;
    //   469: athrow
    // Local variable table:
    //   start	length	slot	name	signature
    //   0	470	0	this	vuuvuv
    //   3	392	1	i	int
    //   238	33	2	j	int
    //   55	315	3	localObject	Object
    //   428	2	3	localInvocationTargetException1	InvocationTargetException
    //   434	2	3	localInvocationTargetException2	InvocationTargetException
    //   440	2	3	localInvocationTargetException3	InvocationTargetException
    //   446	2	3	localInvocationTargetException4	InvocationTargetException
    //   452	2	3	localInvocationTargetException5	InvocationTargetException
    //   458	2	3	localInvocationTargetException6	InvocationTargetException
    //   464	2	3	localInvocationTargetException7	InvocationTargetException
    //   127	3	4	localMethod	Method
    // Exception table:
    //   from	to	target	type
    //   56	66	428	java/lang/reflect/InvocationTargetException
    //   95	105	434	java/lang/reflect/InvocationTargetException
    //   129	140	440	java/lang/reflect/InvocationTargetException
    //   211	221	446	java/lang/reflect/InvocationTargetException
    //   258	268	452	java/lang/reflect/InvocationTargetException
    //   321	331	458	java/lang/reflect/InvocationTargetException
    //   359	369	464	java/lang/reflect/InvocationTargetException
  }
  
  public static int ba00610061aaaa00610061a()
  {
    return 1;
  }
  
  public static int baa0061aaaa00610061a()
  {
    return 0;
  }
  
  /* Error */
  public void b0061006100610061aaa00610061a()
  {
    // Byte code:
    //   0: aload_0
    //   1: getfield 159	uuuuuu/vuuvuv:bi0069ii00690069i0069i	Luuuuuu/sssttt;
    //   4: getstatic 165	com/db/pwcc/dbmobile/foundation/features/Feature:TREATMENTS	Lcom/db/pwcc/dbmobile/foundation/features/Feature;
    //   7: invokevirtual 171	uuuuuu/sssttt:bk006Bkkk006B006B006Bkk	(Lcom/db/pwcc/dbmobile/foundation/features/Feature;)Luuuuuu/sststt;
    //   10: getstatic 177	uuuuuu/sststt:b006En006En006Enn006En	Luuuuuu/sststt;
    //   13: if_acmpeq +4 -> 17
    //   16: return
    //   17: aload_0
    //   18: getfield 179	uuuuuu/vuuvuv:b006900690069i00690069i0069i	Luuuuuu/gaaaga;
    //   21: iconst_1
    //   22: invokevirtual 185	uuuuuu/gaaaga:b0077w0077wwww0077ww	(I)Lcom/db/pwcc/dbmobile/treatments/model/TreatmentCache;
    //   25: invokevirtual 191	com/db/pwcc/dbmobile/treatments/model/TreatmentCache:getCategory	()Lcom/db/pwcc/dbmobile/treatments/model/TreatmentCategory;
    //   28: astore_2
    //   29: ldc 2
    //   31: ldc -63
    //   33: sipush 231
    //   36: iconst_0
    //   37: invokestatic 101	xxxxxx/uxxxxx:bb00620062bb0062b0062b0062	(Ljava/lang/String;CC)Ljava/lang/String;
    //   40: iconst_0
    //   41: anewarray 69	java/lang/Class
    //   44: invokevirtual 73	java/lang/Class:getMethod	(Ljava/lang/String;[Ljava/lang/Class;)Ljava/lang/reflect/Method;
    //   47: astore_3
    //   48: aload_3
    //   49: aconst_null
    //   50: iconst_0
    //   51: anewarray 75	java/lang/Object
    //   54: invokevirtual 81	java/lang/reflect/Method:invoke	(Ljava/lang/Object;[Ljava/lang/Object;)Ljava/lang/Object;
    //   57: astore_3
    //   58: aload_3
    //   59: checkcast 83	java/lang/Integer
    //   62: invokevirtual 87	java/lang/Integer:intValue	()I
    //   65: istore_1
    //   66: ldc 2
    //   68: ldc -61
    //   70: bipush 30
    //   72: iconst_1
    //   73: invokestatic 101	xxxxxx/uxxxxx:bb00620062bb0062b0062b0062	(Ljava/lang/String;CC)Ljava/lang/String;
    //   76: iconst_0
    //   77: anewarray 69	java/lang/Class
    //   80: invokevirtual 73	java/lang/Class:getMethod	(Ljava/lang/String;[Ljava/lang/Class;)Ljava/lang/reflect/Method;
    //   83: astore_3
    //   84: aload_3
    //   85: aconst_null
    //   86: iconst_0
    //   87: anewarray 75	java/lang/Object
    //   90: invokevirtual 81	java/lang/reflect/Method:invoke	(Ljava/lang/Object;[Ljava/lang/Object;)Ljava/lang/Object;
    //   93: astore_3
    //   94: aload_3
    //   95: checkcast 83	java/lang/Integer
    //   98: invokevirtual 87	java/lang/Integer:intValue	()I
    //   101: iload_1
    //   102: iadd
    //   103: iload_1
    //   104: imul
    //   105: getstatic 89	uuuuuu/vuuvuv:bii0069006900690069i0069i	I
    //   108: irem
    //   109: tableswitch	default:+19->128, 0:+100->209
    //   128: ldc 2
    //   130: ldc -59
    //   132: sipush 236
    //   135: iconst_3
    //   136: invokestatic 101	xxxxxx/uxxxxx:bb00620062bb0062b0062b0062	(Ljava/lang/String;CC)Ljava/lang/String;
    //   139: iconst_0
    //   140: anewarray 69	java/lang/Class
    //   143: invokevirtual 73	java/lang/Class:getMethod	(Ljava/lang/String;[Ljava/lang/Class;)Ljava/lang/reflect/Method;
    //   146: astore_3
    //   147: aload_3
    //   148: aconst_null
    //   149: iconst_0
    //   150: anewarray 75	java/lang/Object
    //   153: invokevirtual 81	java/lang/reflect/Method:invoke	(Ljava/lang/Object;[Ljava/lang/Object;)Ljava/lang/Object;
    //   156: astore_3
    //   157: aload_3
    //   158: checkcast 83	java/lang/Integer
    //   161: invokevirtual 87	java/lang/Integer:intValue	()I
    //   164: putstatic 59	uuuuuu/vuuvuv:bi0069i006900690069i0069i	I
    //   167: ldc 2
    //   169: ldc -57
    //   171: sipush 227
    //   174: sipush 205
    //   177: iconst_2
    //   178: invokestatic 67	xxxxxx/uxxxxx:bbbb0062b0062b0062b0062	(Ljava/lang/String;CCC)Ljava/lang/String;
    //   181: iconst_0
    //   182: anewarray 69	java/lang/Class
    //   185: invokevirtual 73	java/lang/Class:getMethod	(Ljava/lang/String;[Ljava/lang/Class;)Ljava/lang/reflect/Method;
    //   188: astore_3
    //   189: aload_3
    //   190: aconst_null
    //   191: iconst_0
    //   192: anewarray 75	java/lang/Object
    //   195: invokevirtual 81	java/lang/reflect/Method:invoke	(Ljava/lang/Object;[Ljava/lang/Object;)Ljava/lang/Object;
    //   198: astore_3
    //   199: aload_3
    //   200: checkcast 83	java/lang/Integer
    //   203: invokevirtual 87	java/lang/Integer:intValue	()I
    //   206: putstatic 91	uuuuuu/vuuvuv:b0069i0069006900690069i0069i	I
    //   209: aload_2
    //   210: getstatic 205	com/db/pwcc/dbmobile/treatments/model/TreatmentCategory:INFORMATION	Lcom/db/pwcc/dbmobile/treatments/model/TreatmentCategory;
    //   213: if_acmpne -197 -> 16
    //   216: aload_0
    //   217: getfield 179	uuuuuu/vuuvuv:b006900690069i00690069i0069i	Luuuuuu/gaaaga;
    //   220: invokevirtual 208	uuuuuu/gaaaga:bww007700770077ww0077ww	()Z
    //   223: ifne -207 -> 16
    //   226: getstatic 59	uuuuuu/vuuvuv:bi0069i006900690069i0069i	I
    //   229: getstatic 103	uuuuuu/vuuvuv:b00690069i006900690069i0069i	I
    //   232: iadd
    //   233: getstatic 59	uuuuuu/vuuvuv:bi0069i006900690069i0069i	I
    //   236: imul
    //   237: getstatic 89	uuuuuu/vuuvuv:bii0069006900690069i0069i	I
    //   240: irem
    //   241: getstatic 91	uuuuuu/vuuvuv:b0069i0069006900690069i0069i	I
    //   244: if_icmpeq +205 -> 449
    //   247: getstatic 59	uuuuuu/vuuvuv:bi0069i006900690069i0069i	I
    //   250: istore_1
    //   251: ldc 2
    //   253: ldc -46
    //   255: bipush 122
    //   257: sipush 201
    //   260: iconst_0
    //   261: invokestatic 67	xxxxxx/uxxxxx:bbbb0062b0062b0062b0062	(Ljava/lang/String;CCC)Ljava/lang/String;
    //   264: iconst_0
    //   265: anewarray 69	java/lang/Class
    //   268: invokevirtual 73	java/lang/Class:getMethod	(Ljava/lang/String;[Ljava/lang/Class;)Ljava/lang/reflect/Method;
    //   271: astore_2
    //   272: aload_2
    //   273: aconst_null
    //   274: iconst_0
    //   275: anewarray 75	java/lang/Object
    //   278: invokevirtual 81	java/lang/reflect/Method:invoke	(Ljava/lang/Object;[Ljava/lang/Object;)Ljava/lang/Object;
    //   281: astore_2
    //   282: aload_2
    //   283: checkcast 83	java/lang/Integer
    //   286: invokevirtual 87	java/lang/Integer:intValue	()I
    //   289: iload_1
    //   290: iadd
    //   291: iload_1
    //   292: imul
    //   293: getstatic 89	uuuuuu/vuuvuv:bii0069006900690069i0069i	I
    //   296: irem
    //   297: tableswitch	default:+19->316, 0:+29->326
    //   316: bipush 7
    //   318: putstatic 59	uuuuuu/vuuvuv:bi0069i006900690069i0069i	I
    //   321: bipush 40
    //   323: putstatic 91	uuuuuu/vuuvuv:b0069i0069006900690069i0069i	I
    //   326: iconst_0
    //   327: putstatic 59	uuuuuu/vuuvuv:bi0069i006900690069i0069i	I
    //   330: bipush 83
    //   332: putstatic 91	uuuuuu/vuuvuv:b0069i0069006900690069i0069i	I
    //   335: getstatic 59	uuuuuu/vuuvuv:bi0069i006900690069i0069i	I
    //   338: istore_1
    //   339: iload_1
    //   340: getstatic 103	uuuuuu/vuuvuv:b00690069i006900690069i0069i	I
    //   343: iload_1
    //   344: iadd
    //   345: imul
    //   346: getstatic 89	uuuuuu/vuuvuv:bii0069006900690069i0069i	I
    //   349: irem
    //   350: tableswitch	default:+18->368, 0:+99->449
    //   368: ldc 2
    //   370: ldc -44
    //   372: sipush 154
    //   375: sipush 165
    //   378: iconst_3
    //   379: invokestatic 67	xxxxxx/uxxxxx:bbbb0062b0062b0062b0062	(Ljava/lang/String;CCC)Ljava/lang/String;
    //   382: iconst_0
    //   383: anewarray 69	java/lang/Class
    //   386: invokevirtual 73	java/lang/Class:getMethod	(Ljava/lang/String;[Ljava/lang/Class;)Ljava/lang/reflect/Method;
    //   389: astore_2
    //   390: aload_2
    //   391: aconst_null
    //   392: iconst_0
    //   393: anewarray 75	java/lang/Object
    //   396: invokevirtual 81	java/lang/reflect/Method:invoke	(Ljava/lang/Object;[Ljava/lang/Object;)Ljava/lang/Object;
    //   399: astore_2
    //   400: aload_2
    //   401: checkcast 83	java/lang/Integer
    //   404: invokevirtual 87	java/lang/Integer:intValue	()I
    //   407: putstatic 59	uuuuuu/vuuvuv:bi0069i006900690069i0069i	I
    //   410: ldc 2
    //   412: ldc -42
    //   414: sipush 182
    //   417: iconst_3
    //   418: invokestatic 101	xxxxxx/uxxxxx:bb00620062bb0062b0062b0062	(Ljava/lang/String;CC)Ljava/lang/String;
    //   421: iconst_0
    //   422: anewarray 69	java/lang/Class
    //   425: invokevirtual 73	java/lang/Class:getMethod	(Ljava/lang/String;[Ljava/lang/Class;)Ljava/lang/reflect/Method;
    //   428: astore_2
    //   429: aload_2
    //   430: aconst_null
    //   431: iconst_0
    //   432: anewarray 75	java/lang/Object
    //   435: invokevirtual 81	java/lang/reflect/Method:invoke	(Ljava/lang/Object;[Ljava/lang/Object;)Ljava/lang/Object;
    //   438: astore_2
    //   439: aload_2
    //   440: checkcast 83	java/lang/Integer
    //   443: invokevirtual 87	java/lang/Integer:intValue	()I
    //   446: putstatic 91	uuuuuu/vuuvuv:b0069i0069006900690069i0069i	I
    //   449: aload_0
    //   450: getfield 95	uuuuuu/vuuvuv:bnnnnn006E006E006En	Luuuuuu/ttssst$tsssst;
    //   453: checkcast 216	uuuuuu/uuvvuv$uvuvuv
    //   456: invokeinterface 219 1 0
    //   461: return
    //   462: astore_2
    //   463: aload_2
    //   464: invokevirtual 117	java/lang/reflect/InvocationTargetException:getCause	()Ljava/lang/Throwable;
    //   467: athrow
    //   468: astore_2
    //   469: aload_2
    //   470: invokevirtual 117	java/lang/reflect/InvocationTargetException:getCause	()Ljava/lang/Throwable;
    //   473: athrow
    //   474: astore_2
    //   475: aload_2
    //   476: invokevirtual 117	java/lang/reflect/InvocationTargetException:getCause	()Ljava/lang/Throwable;
    //   479: athrow
    //   480: astore_2
    //   481: aload_2
    //   482: invokevirtual 117	java/lang/reflect/InvocationTargetException:getCause	()Ljava/lang/Throwable;
    //   485: athrow
    //   486: astore_2
    //   487: aload_2
    //   488: invokevirtual 117	java/lang/reflect/InvocationTargetException:getCause	()Ljava/lang/Throwable;
    //   491: athrow
    //   492: astore_2
    //   493: aload_2
    //   494: invokevirtual 117	java/lang/reflect/InvocationTargetException:getCause	()Ljava/lang/Throwable;
    //   497: athrow
    //   498: astore_2
    //   499: aload_2
    //   500: invokevirtual 117	java/lang/reflect/InvocationTargetException:getCause	()Ljava/lang/Throwable;
    //   503: athrow
    // Local variable table:
    //   start	length	slot	name	signature
    //   0	504	0	this	vuuvuv
    //   65	281	1	i	int
    //   28	412	2	localObject1	Object
    //   462	2	2	localInvocationTargetException1	InvocationTargetException
    //   468	2	2	localInvocationTargetException2	InvocationTargetException
    //   474	2	2	localInvocationTargetException3	InvocationTargetException
    //   480	2	2	localInvocationTargetException4	InvocationTargetException
    //   486	2	2	localInvocationTargetException5	InvocationTargetException
    //   492	2	2	localInvocationTargetException6	InvocationTargetException
    //   498	2	2	localInvocationTargetException7	InvocationTargetException
    //   47	153	3	localObject2	Object
    // Exception table:
    //   from	to	target	type
    //   48	58	462	java/lang/reflect/InvocationTargetException
    //   84	94	468	java/lang/reflect/InvocationTargetException
    //   272	282	474	java/lang/reflect/InvocationTargetException
    //   147	157	480	java/lang/reflect/InvocationTargetException
    //   189	199	486	java/lang/reflect/InvocationTargetException
    //   390	400	492	java/lang/reflect/InvocationTargetException
    //   429	439	498	java/lang/reflect/InvocationTargetException
  }
  
  /* Error */
  public boolean b006100610061aaaa00610061a(com.db.pwcc.dbmobile.model.banking.FinancialOverviewData paramFinancialOverviewData)
  {
    // Byte code:
    //   0: aload_1
    //   1: invokevirtual 227	com/db/pwcc/dbmobile/model/banking/FinancialOverviewData:getAccounts	()Ljava/util/List;
    //   4: invokeinterface 233 1 0
    //   9: astore_1
    //   10: getstatic 59	uuuuuu/vuuvuv:bi0069i006900690069i0069i	I
    //   13: istore_2
    //   14: ldc 2
    //   16: ldc -21
    //   18: bipush 8
    //   20: sipush 132
    //   23: iconst_3
    //   24: invokestatic 67	xxxxxx/uxxxxx:bbbb0062b0062b0062b0062	(Ljava/lang/String;CCC)Ljava/lang/String;
    //   27: iconst_0
    //   28: anewarray 69	java/lang/Class
    //   31: invokevirtual 73	java/lang/Class:getMethod	(Ljava/lang/String;[Ljava/lang/Class;)Ljava/lang/reflect/Method;
    //   34: astore 5
    //   36: aload 5
    //   38: aconst_null
    //   39: iconst_0
    //   40: anewarray 75	java/lang/Object
    //   43: invokevirtual 81	java/lang/reflect/Method:invoke	(Ljava/lang/Object;[Ljava/lang/Object;)Ljava/lang/Object;
    //   46: astore 5
    //   48: aload 5
    //   50: checkcast 83	java/lang/Integer
    //   53: invokevirtual 87	java/lang/Integer:intValue	()I
    //   56: iload_2
    //   57: iadd
    //   58: getstatic 59	uuuuuu/vuuvuv:bi0069i006900690069i0069i	I
    //   61: imul
    //   62: getstatic 89	uuuuuu/vuuvuv:bii0069006900690069i0069i	I
    //   65: irem
    //   66: getstatic 91	uuuuuu/vuuvuv:b0069i0069006900690069i0069i	I
    //   69: if_icmpeq +13 -> 82
    //   72: bipush 54
    //   74: putstatic 59	uuuuuu/vuuvuv:bi0069i006900690069i0069i	I
    //   77: bipush 17
    //   79: putstatic 91	uuuuuu/vuuvuv:b0069i0069006900690069i0069i	I
    //   82: aload_1
    //   83: invokeinterface 240 1 0
    //   88: ifeq +459 -> 547
    //   91: aload_1
    //   92: invokeinterface 244 1 0
    //   97: checkcast 246	com/db/pwcc/dbmobile/model/banking/Account
    //   100: astore 5
    //   102: getstatic 59	uuuuuu/vuuvuv:bi0069i006900690069i0069i	I
    //   105: istore_2
    //   106: ldc 2
    //   108: ldc -8
    //   110: sipush 195
    //   113: iconst_3
    //   114: invokestatic 101	xxxxxx/uxxxxx:bb00620062bb0062b0062b0062	(Ljava/lang/String;CC)Ljava/lang/String;
    //   117: iconst_0
    //   118: anewarray 69	java/lang/Class
    //   121: invokevirtual 73	java/lang/Class:getMethod	(Ljava/lang/String;[Ljava/lang/Class;)Ljava/lang/reflect/Method;
    //   124: astore 6
    //   126: aload 6
    //   128: aconst_null
    //   129: iconst_0
    //   130: anewarray 75	java/lang/Object
    //   133: invokevirtual 81	java/lang/reflect/Method:invoke	(Ljava/lang/Object;[Ljava/lang/Object;)Ljava/lang/Object;
    //   136: astore 6
    //   138: aload 6
    //   140: checkcast 83	java/lang/Integer
    //   143: invokevirtual 87	java/lang/Integer:intValue	()I
    //   146: iload_2
    //   147: iadd
    //   148: getstatic 59	uuuuuu/vuuvuv:bi0069i006900690069i0069i	I
    //   151: imul
    //   152: getstatic 89	uuuuuu/vuuvuv:bii0069006900690069i0069i	I
    //   155: irem
    //   156: getstatic 91	uuuuuu/vuuvuv:b0069i0069006900690069i0069i	I
    //   159: if_icmpeq +316 -> 475
    //   162: getstatic 59	uuuuuu/vuuvuv:bi0069i006900690069i0069i	I
    //   165: getstatic 103	uuuuuu/vuuvuv:b00690069i006900690069i0069i	I
    //   168: iadd
    //   169: getstatic 59	uuuuuu/vuuvuv:bi0069i006900690069i0069i	I
    //   172: imul
    //   173: getstatic 89	uuuuuu/vuuvuv:bii0069006900690069i0069i	I
    //   176: irem
    //   177: getstatic 91	uuuuuu/vuuvuv:b0069i0069006900690069i0069i	I
    //   180: if_icmpeq +205 -> 385
    //   183: bipush 39
    //   185: putstatic 59	uuuuuu/vuuvuv:bi0069i006900690069i0069i	I
    //   188: ldc 2
    //   190: ldc -6
    //   192: bipush 116
    //   194: sipush 230
    //   197: iconst_3
    //   198: invokestatic 67	xxxxxx/uxxxxx:bbbb0062b0062b0062b0062	(Ljava/lang/String;CCC)Ljava/lang/String;
    //   201: iconst_0
    //   202: anewarray 69	java/lang/Class
    //   205: invokevirtual 73	java/lang/Class:getMethod	(Ljava/lang/String;[Ljava/lang/Class;)Ljava/lang/reflect/Method;
    //   208: astore 6
    //   210: aload 6
    //   212: aconst_null
    //   213: iconst_0
    //   214: anewarray 75	java/lang/Object
    //   217: invokevirtual 81	java/lang/reflect/Method:invoke	(Ljava/lang/Object;[Ljava/lang/Object;)Ljava/lang/Object;
    //   220: astore 6
    //   222: aload 6
    //   224: checkcast 83	java/lang/Integer
    //   227: invokevirtual 87	java/lang/Integer:intValue	()I
    //   230: putstatic 91	uuuuuu/vuuvuv:b0069i0069006900690069i0069i	I
    //   233: getstatic 59	uuuuuu/vuuvuv:bi0069i006900690069i0069i	I
    //   236: istore_2
    //   237: getstatic 103	uuuuuu/vuuvuv:b00690069i006900690069i0069i	I
    //   240: istore_3
    //   241: getstatic 59	uuuuuu/vuuvuv:bi0069i006900690069i0069i	I
    //   244: istore 4
    //   246: ldc 2
    //   248: ldc -4
    //   250: bipush 77
    //   252: iconst_3
    //   253: invokestatic 101	xxxxxx/uxxxxx:bb00620062bb0062b0062b0062	(Ljava/lang/String;CC)Ljava/lang/String;
    //   256: iconst_0
    //   257: anewarray 69	java/lang/Class
    //   260: invokevirtual 73	java/lang/Class:getMethod	(Ljava/lang/String;[Ljava/lang/Class;)Ljava/lang/reflect/Method;
    //   263: astore 6
    //   265: aload 6
    //   267: aconst_null
    //   268: iconst_0
    //   269: anewarray 75	java/lang/Object
    //   272: invokevirtual 81	java/lang/reflect/Method:invoke	(Ljava/lang/Object;[Ljava/lang/Object;)Ljava/lang/Object;
    //   275: astore 6
    //   277: iload 4
    //   279: iload_2
    //   280: iload_3
    //   281: iadd
    //   282: imul
    //   283: aload 6
    //   285: checkcast 83	java/lang/Integer
    //   288: invokevirtual 87	java/lang/Integer:intValue	()I
    //   291: irem
    //   292: getstatic 91	uuuuuu/vuuvuv:b0069i0069006900690069i0069i	I
    //   295: if_icmpeq +90 -> 385
    //   298: ldc 2
    //   300: ldc -2
    //   302: sipush 165
    //   305: iconst_5
    //   306: invokestatic 101	xxxxxx/uxxxxx:bb00620062bb0062b0062b0062	(Ljava/lang/String;CC)Ljava/lang/String;
    //   309: iconst_0
    //   310: anewarray 69	java/lang/Class
    //   313: invokevirtual 73	java/lang/Class:getMethod	(Ljava/lang/String;[Ljava/lang/Class;)Ljava/lang/reflect/Method;
    //   316: astore 6
    //   318: aload 6
    //   320: aconst_null
    //   321: iconst_0
    //   322: anewarray 75	java/lang/Object
    //   325: invokevirtual 81	java/lang/reflect/Method:invoke	(Ljava/lang/Object;[Ljava/lang/Object;)Ljava/lang/Object;
    //   328: astore 6
    //   330: aload 6
    //   332: checkcast 83	java/lang/Integer
    //   335: invokevirtual 87	java/lang/Integer:intValue	()I
    //   338: putstatic 59	uuuuuu/vuuvuv:bi0069i006900690069i0069i	I
    //   341: ldc 2
    //   343: ldc_w 256
    //   346: sipush 183
    //   349: iconst_0
    //   350: invokestatic 101	xxxxxx/uxxxxx:bb00620062bb0062b0062b0062	(Ljava/lang/String;CC)Ljava/lang/String;
    //   353: iconst_0
    //   354: anewarray 69	java/lang/Class
    //   357: invokevirtual 73	java/lang/Class:getMethod	(Ljava/lang/String;[Ljava/lang/Class;)Ljava/lang/reflect/Method;
    //   360: astore 6
    //   362: aload 6
    //   364: aconst_null
    //   365: iconst_0
    //   366: anewarray 75	java/lang/Object
    //   369: invokevirtual 81	java/lang/reflect/Method:invoke	(Ljava/lang/Object;[Ljava/lang/Object;)Ljava/lang/Object;
    //   372: astore 6
    //   374: aload 6
    //   376: checkcast 83	java/lang/Integer
    //   379: invokevirtual 87	java/lang/Integer:intValue	()I
    //   382: putstatic 91	uuuuuu/vuuvuv:b0069i0069006900690069i0069i	I
    //   385: ldc 2
    //   387: ldc_w 258
    //   390: bipush 76
    //   392: iconst_2
    //   393: invokestatic 101	xxxxxx/uxxxxx:bb00620062bb0062b0062b0062	(Ljava/lang/String;CC)Ljava/lang/String;
    //   396: iconst_0
    //   397: anewarray 69	java/lang/Class
    //   400: invokevirtual 73	java/lang/Class:getMethod	(Ljava/lang/String;[Ljava/lang/Class;)Ljava/lang/reflect/Method;
    //   403: astore 6
    //   405: aload 6
    //   407: aconst_null
    //   408: iconst_0
    //   409: anewarray 75	java/lang/Object
    //   412: invokevirtual 81	java/lang/reflect/Method:invoke	(Ljava/lang/Object;[Ljava/lang/Object;)Ljava/lang/Object;
    //   415: astore 6
    //   417: aload 6
    //   419: checkcast 83	java/lang/Integer
    //   422: invokevirtual 87	java/lang/Integer:intValue	()I
    //   425: putstatic 59	uuuuuu/vuuvuv:bi0069i006900690069i0069i	I
    //   428: ldc 2
    //   430: ldc_w 260
    //   433: sipush 137
    //   436: sipush 240
    //   439: iconst_1
    //   440: invokestatic 67	xxxxxx/uxxxxx:bbbb0062b0062b0062b0062	(Ljava/lang/String;CCC)Ljava/lang/String;
    //   443: iconst_0
    //   444: anewarray 69	java/lang/Class
    //   447: invokevirtual 73	java/lang/Class:getMethod	(Ljava/lang/String;[Ljava/lang/Class;)Ljava/lang/reflect/Method;
    //   450: astore 6
    //   452: aload 6
    //   454: aconst_null
    //   455: iconst_0
    //   456: anewarray 75	java/lang/Object
    //   459: invokevirtual 81	java/lang/reflect/Method:invoke	(Ljava/lang/Object;[Ljava/lang/Object;)Ljava/lang/Object;
    //   462: astore 6
    //   464: aload 6
    //   466: checkcast 83	java/lang/Integer
    //   469: invokevirtual 87	java/lang/Integer:intValue	()I
    //   472: putstatic 91	uuuuuu/vuuvuv:b0069i0069006900690069i0069i	I
    //   475: getstatic 266	com/db/pwcc/dbmobile/model/banking/Account$ProductType:DEPOSIT_ACCOUNT	Lcom/db/pwcc/dbmobile/model/banking/Account$ProductType;
    //   478: aload 5
    //   480: invokevirtual 270	com/db/pwcc/dbmobile/model/banking/Account:getProductType	()Lcom/db/pwcc/dbmobile/model/banking/Account$ProductType;
    //   483: if_acmpne -473 -> 10
    //   486: aload 5
    //   488: invokevirtual 274	com/db/pwcc/dbmobile/model/banking/Account:isAuthorized	()Ljava/lang/Boolean;
    //   491: invokevirtual 134	java/lang/Boolean:booleanValue	()Z
    //   494: ifeq -484 -> 10
    //   497: iconst_1
    //   498: ireturn
    //   499: astore_1
    //   500: aload_1
    //   501: invokevirtual 117	java/lang/reflect/InvocationTargetException:getCause	()Ljava/lang/Throwable;
    //   504: athrow
    //   505: astore_1
    //   506: aload_1
    //   507: invokevirtual 117	java/lang/reflect/InvocationTargetException:getCause	()Ljava/lang/Throwable;
    //   510: athrow
    //   511: astore_1
    //   512: aload_1
    //   513: invokevirtual 117	java/lang/reflect/InvocationTargetException:getCause	()Ljava/lang/Throwable;
    //   516: athrow
    //   517: astore_1
    //   518: aload_1
    //   519: invokevirtual 117	java/lang/reflect/InvocationTargetException:getCause	()Ljava/lang/Throwable;
    //   522: athrow
    //   523: astore_1
    //   524: aload_1
    //   525: invokevirtual 117	java/lang/reflect/InvocationTargetException:getCause	()Ljava/lang/Throwable;
    //   528: athrow
    //   529: astore_1
    //   530: aload_1
    //   531: invokevirtual 117	java/lang/reflect/InvocationTargetException:getCause	()Ljava/lang/Throwable;
    //   534: athrow
    //   535: astore_1
    //   536: aload_1
    //   537: invokevirtual 117	java/lang/reflect/InvocationTargetException:getCause	()Ljava/lang/Throwable;
    //   540: athrow
    //   541: astore_1
    //   542: aload_1
    //   543: invokevirtual 117	java/lang/reflect/InvocationTargetException:getCause	()Ljava/lang/Throwable;
    //   546: athrow
    //   547: iconst_0
    //   548: ireturn
    // Local variable table:
    //   start	length	slot	name	signature
    //   0	549	0	this	vuuvuv
    //   0	549	1	paramFinancialOverviewData	com.db.pwcc.dbmobile.model.banking.FinancialOverviewData
    //   13	269	2	i	int
    //   240	42	3	j	int
    //   244	39	4	k	int
    //   34	453	5	localObject1	Object
    //   124	341	6	localObject2	Object
    // Exception table:
    //   from	to	target	type
    //   126	138	499	java/lang/reflect/InvocationTargetException
    //   36	48	505	java/lang/reflect/InvocationTargetException
    //   405	417	511	java/lang/reflect/InvocationTargetException
    //   452	464	517	java/lang/reflect/InvocationTargetException
    //   265	277	523	java/lang/reflect/InvocationTargetException
    //   210	222	529	java/lang/reflect/InvocationTargetException
    //   318	330	535	java/lang/reflect/InvocationTargetException
    //   362	374	541	java/lang/reflect/InvocationTargetException
  }
  
  /* Error */
  public void b00610061a0061aaa00610061a(@android.support.annotation.NonNull Context paramContext, com.db.pwcc.dbmobile.model.banking.FinancialOverviewData paramFinancialOverviewData)
  {
    // Byte code:
    //   0: aload_0
    //   1: getfield 159	uuuuuu/vuuvuv:bi0069ii00690069i0069i	Luuuuuu/sssttt;
    //   4: getstatic 280	com/db/pwcc/dbmobile/foundation/features/Feature:MORTGAGES	Lcom/db/pwcc/dbmobile/foundation/features/Feature;
    //   7: invokevirtual 171	uuuuuu/sssttt:bk006Bkkk006B006B006Bkk	(Lcom/db/pwcc/dbmobile/foundation/features/Feature;)Luuuuuu/sststt;
    //   10: getstatic 177	uuuuuu/sststt:b006En006En006Enn006En	Luuuuuu/sststt;
    //   13: if_acmpne +72 -> 85
    //   16: aload_2
    //   17: invokevirtual 283	com/db/pwcc/dbmobile/model/banking/FinancialOverviewData:hasMortgages	()Z
    //   20: ifeq +65 -> 85
    //   23: ldc 2
    //   25: ldc_w 285
    //   28: sipush 237
    //   31: iconst_1
    //   32: invokestatic 101	xxxxxx/uxxxxx:bb00620062bb0062b0062b0062	(Ljava/lang/String;CC)Ljava/lang/String;
    //   35: iconst_0
    //   36: anewarray 69	java/lang/Class
    //   39: invokevirtual 73	java/lang/Class:getMethod	(Ljava/lang/String;[Ljava/lang/Class;)Ljava/lang/reflect/Method;
    //   42: astore 10
    //   44: aload 10
    //   46: aload_0
    //   47: iconst_0
    //   48: anewarray 75	java/lang/Object
    //   51: invokevirtual 81	java/lang/reflect/Method:invoke	(Ljava/lang/Object;[Ljava/lang/Object;)Ljava/lang/Object;
    //   54: astore 10
    //   56: aload 10
    //   58: checkcast 131	java/lang/Boolean
    //   61: invokevirtual 134	java/lang/Boolean:booleanValue	()Z
    //   64: ifne +21 -> 85
    //   67: aload_0
    //   68: getfield 287	uuuuuu/vuuvuv:b0069i0069i00690069i0069i	Luuuuuu/uuvuuv;
    //   71: aload_1
    //   72: aload_2
    //   73: invokevirtual 290	com/db/pwcc/dbmobile/model/banking/FinancialOverviewData:getMortgagesIdsWithAuthorizations	()Ljava/util/List;
    //   76: invokevirtual 296	uuuuuu/uuvuuv:baa0061aa00610061a0061a	(Landroid/content/Context;Ljava/util/List;)V
    //   79: getstatic 302	uuuuuu/vvrvrv:bh006800680068hh006800680068	Luuuuuu/vvrvrv;
    //   82: invokestatic 308	uuuuuu/rrvvrv:b0071q0071qq0071q0071q0071	(Luuuuuu/vvrvrv;)V
    //   85: ldc 2
    //   87: ldc_w 310
    //   90: sipush 197
    //   93: sipush 159
    //   96: iconst_3
    //   97: invokestatic 67	xxxxxx/uxxxxx:bbbb0062b0062b0062b0062	(Ljava/lang/String;CCC)Ljava/lang/String;
    //   100: iconst_1
    //   101: anewarray 69	java/lang/Class
    //   104: dup
    //   105: iconst_0
    //   106: ldc -33
    //   108: aastore
    //   109: invokevirtual 73	java/lang/Class:getMethod	(Ljava/lang/String;[Ljava/lang/Class;)Ljava/lang/reflect/Method;
    //   112: astore 10
    //   114: aload 10
    //   116: aload_0
    //   117: iconst_1
    //   118: anewarray 75	java/lang/Object
    //   121: dup
    //   122: iconst_0
    //   123: aload_2
    //   124: aastore
    //   125: invokevirtual 81	java/lang/reflect/Method:invoke	(Ljava/lang/Object;[Ljava/lang/Object;)Ljava/lang/Object;
    //   128: astore_2
    //   129: aload_2
    //   130: checkcast 131	java/lang/Boolean
    //   133: invokevirtual 134	java/lang/Boolean:booleanValue	()Z
    //   136: istore 9
    //   138: aload_0
    //   139: getfield 159	uuuuuu/vuuvuv:bi0069ii00690069i0069i	Luuuuuu/sssttt;
    //   142: getstatic 313	com/db/pwcc/dbmobile/foundation/features/Feature:INVESTMENTS	Lcom/db/pwcc/dbmobile/foundation/features/Feature;
    //   145: invokevirtual 171	uuuuuu/sssttt:bk006Bkkk006B006B006Bkk	(Lcom/db/pwcc/dbmobile/foundation/features/Feature;)Luuuuuu/sststt;
    //   148: astore_2
    //   149: getstatic 177	uuuuuu/sststt:b006En006En006Enn006En	Luuuuuu/sststt;
    //   152: astore 10
    //   154: getstatic 59	uuuuuu/vuuvuv:bi0069i006900690069i0069i	I
    //   157: istore_3
    //   158: ldc 2
    //   160: ldc_w 315
    //   163: sipush 207
    //   166: iconst_1
    //   167: invokestatic 101	xxxxxx/uxxxxx:bb00620062bb0062b0062b0062	(Ljava/lang/String;CC)Ljava/lang/String;
    //   170: iconst_0
    //   171: anewarray 69	java/lang/Class
    //   174: invokevirtual 73	java/lang/Class:getMethod	(Ljava/lang/String;[Ljava/lang/Class;)Ljava/lang/reflect/Method;
    //   177: astore 11
    //   179: aload 11
    //   181: aconst_null
    //   182: iconst_0
    //   183: anewarray 75	java/lang/Object
    //   186: invokevirtual 81	java/lang/reflect/Method:invoke	(Ljava/lang/Object;[Ljava/lang/Object;)Ljava/lang/Object;
    //   189: astore 11
    //   191: aload 11
    //   193: checkcast 83	java/lang/Integer
    //   196: invokevirtual 87	java/lang/Integer:intValue	()I
    //   199: iload_3
    //   200: iadd
    //   201: iload_3
    //   202: imul
    //   203: getstatic 89	uuuuuu/vuuvuv:bii0069006900690069i0069i	I
    //   206: irem
    //   207: tableswitch	default:+17->224, 0:+65->272
    //   224: ldc 2
    //   226: ldc_w 317
    //   229: bipush 93
    //   231: iconst_0
    //   232: invokestatic 101	xxxxxx/uxxxxx:bb00620062bb0062b0062b0062	(Ljava/lang/String;CC)Ljava/lang/String;
    //   235: iconst_0
    //   236: anewarray 69	java/lang/Class
    //   239: invokevirtual 73	java/lang/Class:getMethod	(Ljava/lang/String;[Ljava/lang/Class;)Ljava/lang/reflect/Method;
    //   242: astore 11
    //   244: aload 11
    //   246: aconst_null
    //   247: iconst_0
    //   248: anewarray 75	java/lang/Object
    //   251: invokevirtual 81	java/lang/reflect/Method:invoke	(Ljava/lang/Object;[Ljava/lang/Object;)Ljava/lang/Object;
    //   254: astore 11
    //   256: aload 11
    //   258: checkcast 83	java/lang/Integer
    //   261: invokevirtual 87	java/lang/Integer:intValue	()I
    //   264: putstatic 59	uuuuuu/vuuvuv:bi0069i006900690069i0069i	I
    //   267: bipush 12
    //   269: putstatic 91	uuuuuu/vuuvuv:b0069i0069006900690069i0069i	I
    //   272: aload_2
    //   273: aload 10
    //   275: if_acmpne +346 -> 621
    //   278: iload 9
    //   280: ifeq +341 -> 621
    //   283: ldc 2
    //   285: ldc_w 319
    //   288: bipush 19
    //   290: iconst_0
    //   291: invokestatic 101	xxxxxx/uxxxxx:bb00620062bb0062b0062b0062	(Ljava/lang/String;CC)Ljava/lang/String;
    //   294: iconst_0
    //   295: anewarray 69	java/lang/Class
    //   298: invokevirtual 73	java/lang/Class:getMethod	(Ljava/lang/String;[Ljava/lang/Class;)Ljava/lang/reflect/Method;
    //   301: astore_2
    //   302: aload_2
    //   303: aload_0
    //   304: iconst_0
    //   305: anewarray 75	java/lang/Object
    //   308: invokevirtual 81	java/lang/reflect/Method:invoke	(Ljava/lang/Object;[Ljava/lang/Object;)Ljava/lang/Object;
    //   311: astore_2
    //   312: aload_2
    //   313: checkcast 131	java/lang/Boolean
    //   316: invokevirtual 134	java/lang/Boolean:booleanValue	()Z
    //   319: ifne +302 -> 621
    //   322: aload_0
    //   323: getfield 287	uuuuuu/vuuvuv:b0069i0069i00690069i0069i	Luuuuuu/uuvuuv;
    //   326: astore_2
    //   327: getstatic 59	uuuuuu/vuuvuv:bi0069i006900690069i0069i	I
    //   330: istore_3
    //   331: ldc 2
    //   333: ldc_w 321
    //   336: bipush 9
    //   338: sipush 151
    //   341: iconst_2
    //   342: invokestatic 67	xxxxxx/uxxxxx:bbbb0062b0062b0062b0062	(Ljava/lang/String;CCC)Ljava/lang/String;
    //   345: iconst_0
    //   346: anewarray 69	java/lang/Class
    //   349: invokevirtual 73	java/lang/Class:getMethod	(Ljava/lang/String;[Ljava/lang/Class;)Ljava/lang/reflect/Method;
    //   352: astore 10
    //   354: aload 10
    //   356: aconst_null
    //   357: iconst_0
    //   358: anewarray 75	java/lang/Object
    //   361: invokevirtual 81	java/lang/reflect/Method:invoke	(Ljava/lang/Object;[Ljava/lang/Object;)Ljava/lang/Object;
    //   364: astore 10
    //   366: aload 10
    //   368: checkcast 83	java/lang/Integer
    //   371: invokevirtual 87	java/lang/Integer:intValue	()I
    //   374: iload_3
    //   375: iadd
    //   376: getstatic 59	uuuuuu/vuuvuv:bi0069i006900690069i0069i	I
    //   379: imul
    //   380: getstatic 89	uuuuuu/vuuvuv:bii0069006900690069i0069i	I
    //   383: irem
    //   384: getstatic 91	uuuuuu/vuuvuv:b0069i0069006900690069i0069i	I
    //   387: if_icmpeq +223 -> 610
    //   390: bipush 90
    //   392: putstatic 59	uuuuuu/vuuvuv:bi0069i006900690069i0069i	I
    //   395: bipush 54
    //   397: putstatic 91	uuuuuu/vuuvuv:b0069i0069006900690069i0069i	I
    //   400: getstatic 59	uuuuuu/vuuvuv:bi0069i006900690069i0069i	I
    //   403: istore_3
    //   404: getstatic 103	uuuuuu/vuuvuv:b00690069i006900690069i0069i	I
    //   407: istore 4
    //   409: getstatic 89	uuuuuu/vuuvuv:bii0069006900690069i0069i	I
    //   412: istore 5
    //   414: getstatic 59	uuuuuu/vuuvuv:bi0069i006900690069i0069i	I
    //   417: istore 6
    //   419: getstatic 103	uuuuuu/vuuvuv:b00690069i006900690069i0069i	I
    //   422: istore 7
    //   424: getstatic 59	uuuuuu/vuuvuv:bi0069i006900690069i0069i	I
    //   427: istore 8
    //   429: ldc 2
    //   431: ldc_w 323
    //   434: bipush 112
    //   436: iconst_0
    //   437: invokestatic 101	xxxxxx/uxxxxx:bb00620062bb0062b0062b0062	(Ljava/lang/String;CC)Ljava/lang/String;
    //   440: iconst_0
    //   441: anewarray 69	java/lang/Class
    //   444: invokevirtual 73	java/lang/Class:getMethod	(Ljava/lang/String;[Ljava/lang/Class;)Ljava/lang/reflect/Method;
    //   447: astore 10
    //   449: aload 10
    //   451: aconst_null
    //   452: iconst_0
    //   453: anewarray 75	java/lang/Object
    //   456: invokevirtual 81	java/lang/reflect/Method:invoke	(Ljava/lang/Object;[Ljava/lang/Object;)Ljava/lang/Object;
    //   459: astore 10
    //   461: iload 8
    //   463: iload 6
    //   465: iload 7
    //   467: iadd
    //   468: imul
    //   469: aload 10
    //   471: checkcast 83	java/lang/Integer
    //   474: invokevirtual 87	java/lang/Integer:intValue	()I
    //   477: irem
    //   478: getstatic 91	uuuuuu/vuuvuv:b0069i0069006900690069i0069i	I
    //   481: if_icmpeq +93 -> 574
    //   484: ldc 2
    //   486: ldc_w 325
    //   489: bipush 74
    //   491: sipush 132
    //   494: iconst_1
    //   495: invokestatic 67	xxxxxx/uxxxxx:bbbb0062b0062b0062b0062	(Ljava/lang/String;CCC)Ljava/lang/String;
    //   498: iconst_0
    //   499: anewarray 69	java/lang/Class
    //   502: invokevirtual 73	java/lang/Class:getMethod	(Ljava/lang/String;[Ljava/lang/Class;)Ljava/lang/reflect/Method;
    //   505: astore 10
    //   507: aload 10
    //   509: aconst_null
    //   510: iconst_0
    //   511: anewarray 75	java/lang/Object
    //   514: invokevirtual 81	java/lang/reflect/Method:invoke	(Ljava/lang/Object;[Ljava/lang/Object;)Ljava/lang/Object;
    //   517: astore 10
    //   519: aload 10
    //   521: checkcast 83	java/lang/Integer
    //   524: invokevirtual 87	java/lang/Integer:intValue	()I
    //   527: putstatic 59	uuuuuu/vuuvuv:bi0069i006900690069i0069i	I
    //   530: ldc 2
    //   532: ldc_w 327
    //   535: sipush 176
    //   538: iconst_4
    //   539: invokestatic 101	xxxxxx/uxxxxx:bb00620062bb0062b0062b0062	(Ljava/lang/String;CC)Ljava/lang/String;
    //   542: iconst_0
    //   543: anewarray 69	java/lang/Class
    //   546: invokevirtual 73	java/lang/Class:getMethod	(Ljava/lang/String;[Ljava/lang/Class;)Ljava/lang/reflect/Method;
    //   549: astore 10
    //   551: aload 10
    //   553: aconst_null
    //   554: iconst_0
    //   555: anewarray 75	java/lang/Object
    //   558: invokevirtual 81	java/lang/reflect/Method:invoke	(Ljava/lang/Object;[Ljava/lang/Object;)Ljava/lang/Object;
    //   561: astore 10
    //   563: aload 10
    //   565: checkcast 83	java/lang/Integer
    //   568: invokevirtual 87	java/lang/Integer:intValue	()I
    //   571: putstatic 91	uuuuuu/vuuvuv:b0069i0069006900690069i0069i	I
    //   574: iload 4
    //   576: iload_3
    //   577: iadd
    //   578: iload_3
    //   579: imul
    //   580: iload 5
    //   582: irem
    //   583: tableswitch	default:+17->600, 0:+27->610
    //   600: bipush 67
    //   602: putstatic 59	uuuuuu/vuuvuv:bi0069i006900690069i0069i	I
    //   605: bipush 75
    //   607: putstatic 91	uuuuuu/vuuvuv:b0069i0069006900690069i0069i	I
    //   610: aload_2
    //   611: aload_1
    //   612: invokevirtual 331	uuuuuu/uuvuuv:b00610061aaa00610061a0061a	(Landroid/content/Context;)V
    //   615: getstatic 334	uuuuuu/vvrvrv:bhh00680068hhh00680068	Luuuuuu/vvrvrv;
    //   618: invokestatic 308	uuuuuu/rrvvrv:b0071q0071qq0071q0071q0071	(Luuuuuu/vvrvrv;)V
    //   621: return
    //   622: astore_1
    //   623: aload_1
    //   624: invokevirtual 117	java/lang/reflect/InvocationTargetException:getCause	()Ljava/lang/Throwable;
    //   627: athrow
    //   628: astore_1
    //   629: aload_1
    //   630: invokevirtual 117	java/lang/reflect/InvocationTargetException:getCause	()Ljava/lang/Throwable;
    //   633: athrow
    //   634: astore_1
    //   635: aload_1
    //   636: invokevirtual 117	java/lang/reflect/InvocationTargetException:getCause	()Ljava/lang/Throwable;
    //   639: athrow
    //   640: astore_1
    //   641: aload_1
    //   642: invokevirtual 117	java/lang/reflect/InvocationTargetException:getCause	()Ljava/lang/Throwable;
    //   645: athrow
    //   646: astore_1
    //   647: aload_1
    //   648: invokevirtual 117	java/lang/reflect/InvocationTargetException:getCause	()Ljava/lang/Throwable;
    //   651: athrow
    //   652: astore_1
    //   653: aload_1
    //   654: invokevirtual 117	java/lang/reflect/InvocationTargetException:getCause	()Ljava/lang/Throwable;
    //   657: athrow
    //   658: astore_1
    //   659: aload_1
    //   660: invokevirtual 117	java/lang/reflect/InvocationTargetException:getCause	()Ljava/lang/Throwable;
    //   663: athrow
    //   664: astore_1
    //   665: aload_1
    //   666: invokevirtual 117	java/lang/reflect/InvocationTargetException:getCause	()Ljava/lang/Throwable;
    //   669: athrow
    //   670: astore_1
    //   671: aload_1
    //   672: invokevirtual 117	java/lang/reflect/InvocationTargetException:getCause	()Ljava/lang/Throwable;
    //   675: athrow
    // Local variable table:
    //   start	length	slot	name	signature
    //   0	676	0	this	vuuvuv
    //   0	676	1	paramContext	Context
    //   0	676	2	paramFinancialOverviewData	com.db.pwcc.dbmobile.model.banking.FinancialOverviewData
    //   157	423	3	i	int
    //   407	171	4	j	int
    //   412	171	5	k	int
    //   417	51	6	m	int
    //   422	46	7	n	int
    //   427	42	8	i1	int
    //   136	143	9	bool	boolean
    //   42	522	10	localObject1	Object
    //   177	80	11	localObject2	Object
    // Exception table:
    //   from	to	target	type
    //   44	56	622	java/lang/reflect/InvocationTargetException
    //   179	191	628	java/lang/reflect/InvocationTargetException
    //   114	129	634	java/lang/reflect/InvocationTargetException
    //   449	461	640	java/lang/reflect/InvocationTargetException
    //   244	256	646	java/lang/reflect/InvocationTargetException
    //   302	312	652	java/lang/reflect/InvocationTargetException
    //   354	366	658	java/lang/reflect/InvocationTargetException
    //   507	519	664	java/lang/reflect/InvocationTargetException
    //   551	563	670	java/lang/reflect/InvocationTargetException
  }
  
  public void b00610061aa006100610061a0061a()
  {
    throw new Runtime("d2j fail translate: java.lang.IndexOutOfBoundsException: fromIndex < 0: -1\n\tat java.util.BitSet.nextSetBit(BitSet.java:712)\n\tat com.googlecode.dex2jar.ir.ts.array.FillArrayTransformer.makeSureAllElementAreAssigned(FillArrayTransformer.java:505)\n\tat com.googlecode.dex2jar.ir.ts.array.FillArrayTransformer.transformReportChanged(FillArrayTransformer.java:123)\n\tat com.googlecode.dex2jar.ir.ts.StatedTransformer.transform(StatedTransformer.java:10)\n\tat com.googlecode.d2j.dex.Dex2jar$2.optimize(Dex2jar.java:149)\n\tat com.googlecode.d2j.dex.Dex2Asm.convertCode(Dex2Asm.java:414)\n\tat com.googlecode.d2j.dex.ExDex2Asm.convertCode(ExDex2Asm.java:42)\n\tat com.googlecode.d2j.dex.Dex2jar$2.convertCode(Dex2jar.java:128)\n\tat com.googlecode.d2j.dex.Dex2Asm.convertMethod(Dex2Asm.java:509)\n\tat com.googlecode.d2j.dex.Dex2Asm.convertClass(Dex2Asm.java:406)\n\tat com.googlecode.d2j.dex.Dex2Asm.convertDex(Dex2Asm.java:422)\n\tat com.googlecode.d2j.dex.Dex2jar.doTranslate(Dex2jar.java:172)\n\tat com.googlecode.d2j.dex.Dex2jar.to(Dex2jar.java:272)\n\tat com.googlecode.dex2jar.tools.Dex2jarCmd.doCommandLine(Dex2jarCmd.java:108)\n\tat com.googlecode.dex2jar.tools.BaseCmd.doMain(BaseCmd.java:288)\n\tat com.googlecode.dex2jar.tools.Dex2jarCmd.main(Dex2jarCmd.java:32)\n");
  }
  
  /* Error */
  public boolean b0061a00610061aaa00610061a()
  {
    // Byte code:
    //   0: aload_0
    //   1: getfield 348	uuuuuu/vuuvuv:bi00690069i00690069i0069i	Luuuuuu/ooooon;
    //   4: invokevirtual 353	uuuuuu/ooooon:b006B006Bkkkk006Bkk006B	()Ljava/util/List;
    //   7: invokeinterface 357 1 0
    //   12: astore 7
    //   14: getstatic 59	uuuuuu/vuuvuv:bi0069i006900690069i0069i	I
    //   17: istore_1
    //   18: getstatic 103	uuuuuu/vuuvuv:b00690069i006900690069i0069i	I
    //   21: istore_2
    //   22: getstatic 59	uuuuuu/vuuvuv:bi0069i006900690069i0069i	I
    //   25: istore_3
    //   26: ldc 2
    //   28: ldc_w 359
    //   31: sipush 188
    //   34: iconst_1
    //   35: invokestatic 101	xxxxxx/uxxxxx:bb00620062bb0062b0062b0062	(Ljava/lang/String;CC)Ljava/lang/String;
    //   38: iconst_0
    //   39: anewarray 69	java/lang/Class
    //   42: invokevirtual 73	java/lang/Class:getMethod	(Ljava/lang/String;[Ljava/lang/Class;)Ljava/lang/reflect/Method;
    //   45: astore 8
    //   47: aload 8
    //   49: aconst_null
    //   50: iconst_0
    //   51: anewarray 75	java/lang/Object
    //   54: invokevirtual 81	java/lang/reflect/Method:invoke	(Ljava/lang/Object;[Ljava/lang/Object;)Ljava/lang/Object;
    //   57: astore 8
    //   59: aload 8
    //   61: checkcast 83	java/lang/Integer
    //   64: invokevirtual 87	java/lang/Integer:intValue	()I
    //   67: istore 4
    //   69: getstatic 59	uuuuuu/vuuvuv:bi0069i006900690069i0069i	I
    //   72: getstatic 103	uuuuuu/vuuvuv:b00690069i006900690069i0069i	I
    //   75: iadd
    //   76: getstatic 59	uuuuuu/vuuvuv:bi0069i006900690069i0069i	I
    //   79: imul
    //   80: getstatic 89	uuuuuu/vuuvuv:bii0069006900690069i0069i	I
    //   83: irem
    //   84: getstatic 91	uuuuuu/vuuvuv:b0069i0069006900690069i0069i	I
    //   87: if_icmpeq +221 -> 308
    //   90: ldc 2
    //   92: ldc_w 361
    //   95: sipush 229
    //   98: iconst_0
    //   99: invokestatic 101	xxxxxx/uxxxxx:bb00620062bb0062b0062b0062	(Ljava/lang/String;CC)Ljava/lang/String;
    //   102: iconst_0
    //   103: anewarray 69	java/lang/Class
    //   106: invokevirtual 73	java/lang/Class:getMethod	(Ljava/lang/String;[Ljava/lang/Class;)Ljava/lang/reflect/Method;
    //   109: astore 8
    //   111: aload 8
    //   113: aconst_null
    //   114: iconst_0
    //   115: anewarray 75	java/lang/Object
    //   118: invokevirtual 81	java/lang/reflect/Method:invoke	(Ljava/lang/Object;[Ljava/lang/Object;)Ljava/lang/Object;
    //   121: astore 8
    //   123: aload 8
    //   125: checkcast 83	java/lang/Integer
    //   128: invokevirtual 87	java/lang/Integer:intValue	()I
    //   131: istore 5
    //   133: getstatic 103	uuuuuu/vuuvuv:b00690069i006900690069i0069i	I
    //   136: istore 6
    //   138: ldc 2
    //   140: ldc_w 363
    //   143: sipush 148
    //   146: bipush 125
    //   148: iconst_1
    //   149: invokestatic 67	xxxxxx/uxxxxx:bbbb0062b0062b0062b0062	(Ljava/lang/String;CCC)Ljava/lang/String;
    //   152: iconst_0
    //   153: anewarray 69	java/lang/Class
    //   156: invokevirtual 73	java/lang/Class:getMethod	(Ljava/lang/String;[Ljava/lang/Class;)Ljava/lang/reflect/Method;
    //   159: astore 8
    //   161: aload 8
    //   163: aconst_null
    //   164: iconst_0
    //   165: anewarray 75	java/lang/Object
    //   168: invokevirtual 81	java/lang/reflect/Method:invoke	(Ljava/lang/Object;[Ljava/lang/Object;)Ljava/lang/Object;
    //   171: astore 8
    //   173: aload 8
    //   175: checkcast 83	java/lang/Integer
    //   178: invokevirtual 87	java/lang/Integer:intValue	()I
    //   181: iload 6
    //   183: iload 5
    //   185: iadd
    //   186: imul
    //   187: getstatic 89	uuuuuu/vuuvuv:bii0069006900690069i0069i	I
    //   190: irem
    //   191: getstatic 91	uuuuuu/vuuvuv:b0069i0069006900690069i0069i	I
    //   194: if_icmpeq +13 -> 207
    //   197: bipush 54
    //   199: putstatic 59	uuuuuu/vuuvuv:bi0069i006900690069i0069i	I
    //   202: bipush 46
    //   204: putstatic 91	uuuuuu/vuuvuv:b0069i0069006900690069i0069i	I
    //   207: ldc 2
    //   209: ldc_w 365
    //   212: bipush 7
    //   214: bipush 6
    //   216: iconst_1
    //   217: invokestatic 67	xxxxxx/uxxxxx:bbbb0062b0062b0062b0062	(Ljava/lang/String;CCC)Ljava/lang/String;
    //   220: iconst_0
    //   221: anewarray 69	java/lang/Class
    //   224: invokevirtual 73	java/lang/Class:getMethod	(Ljava/lang/String;[Ljava/lang/Class;)Ljava/lang/reflect/Method;
    //   227: astore 8
    //   229: aload 8
    //   231: aconst_null
    //   232: iconst_0
    //   233: anewarray 75	java/lang/Object
    //   236: invokevirtual 81	java/lang/reflect/Method:invoke	(Ljava/lang/Object;[Ljava/lang/Object;)Ljava/lang/Object;
    //   239: astore 8
    //   241: aload 8
    //   243: checkcast 83	java/lang/Integer
    //   246: invokevirtual 87	java/lang/Integer:intValue	()I
    //   249: istore 5
    //   251: getstatic 59	uuuuuu/vuuvuv:bi0069i006900690069i0069i	I
    //   254: istore 6
    //   256: iload 6
    //   258: getstatic 103	uuuuuu/vuuvuv:b00690069i006900690069i0069i	I
    //   261: iload 6
    //   263: iadd
    //   264: imul
    //   265: getstatic 89	uuuuuu/vuuvuv:bii0069006900690069i0069i	I
    //   268: irem
    //   269: tableswitch	default:+19->288, 0:+29->298
    //   288: bipush 58
    //   290: putstatic 59	uuuuuu/vuuvuv:bi0069i006900690069i0069i	I
    //   293: bipush 38
    //   295: putstatic 91	uuuuuu/vuuvuv:b0069i0069006900690069i0069i	I
    //   298: iload 5
    //   300: putstatic 59	uuuuuu/vuuvuv:bi0069i006900690069i0069i	I
    //   303: bipush 64
    //   305: putstatic 91	uuuuuu/vuuvuv:b0069i0069006900690069i0069i	I
    //   308: iload_3
    //   309: iload_1
    //   310: iload_2
    //   311: iadd
    //   312: imul
    //   313: iload 4
    //   315: irem
    //   316: getstatic 91	uuuuuu/vuuvuv:b0069i0069006900690069i0069i	I
    //   319: if_icmpeq +53 -> 372
    //   322: iconst_0
    //   323: putstatic 59	uuuuuu/vuuvuv:bi0069i006900690069i0069i	I
    //   326: ldc 2
    //   328: ldc_w 367
    //   331: sipush 239
    //   334: bipush 92
    //   336: iconst_3
    //   337: invokestatic 67	xxxxxx/uxxxxx:bbbb0062b0062b0062b0062	(Ljava/lang/String;CCC)Ljava/lang/String;
    //   340: iconst_0
    //   341: anewarray 69	java/lang/Class
    //   344: invokevirtual 73	java/lang/Class:getMethod	(Ljava/lang/String;[Ljava/lang/Class;)Ljava/lang/reflect/Method;
    //   347: astore 8
    //   349: aload 8
    //   351: aconst_null
    //   352: iconst_0
    //   353: anewarray 75	java/lang/Object
    //   356: invokevirtual 81	java/lang/reflect/Method:invoke	(Ljava/lang/Object;[Ljava/lang/Object;)Ljava/lang/Object;
    //   359: astore 8
    //   361: aload 8
    //   363: checkcast 83	java/lang/Integer
    //   366: invokevirtual 87	java/lang/Integer:intValue	()I
    //   369: putstatic 91	uuuuuu/vuuvuv:b0069i0069006900690069i0069i	I
    //   372: aload 7
    //   374: invokeinterface 370 1 0
    //   379: ifeq +29 -> 408
    //   382: aload 7
    //   384: invokeinterface 371 1 0
    //   389: checkcast 373	uuuuuu/onnnno
    //   392: instanceof 375
    //   395: ifeq -23 -> 372
    //   398: iconst_1
    //   399: ireturn
    //   400: astore 7
    //   402: aload 7
    //   404: invokevirtual 117	java/lang/reflect/InvocationTargetException:getCause	()Ljava/lang/Throwable;
    //   407: athrow
    //   408: iconst_0
    //   409: ireturn
    //   410: astore 7
    //   412: aload 7
    //   414: invokevirtual 117	java/lang/reflect/InvocationTargetException:getCause	()Ljava/lang/Throwable;
    //   417: athrow
    //   418: astore 7
    //   420: aload 7
    //   422: invokevirtual 117	java/lang/reflect/InvocationTargetException:getCause	()Ljava/lang/Throwable;
    //   425: athrow
    //   426: astore 7
    //   428: aload 7
    //   430: invokevirtual 117	java/lang/reflect/InvocationTargetException:getCause	()Ljava/lang/Throwable;
    //   433: athrow
    //   434: astore 7
    //   436: aload 7
    //   438: invokevirtual 117	java/lang/reflect/InvocationTargetException:getCause	()Ljava/lang/Throwable;
    //   441: athrow
    // Local variable table:
    //   start	length	slot	name	signature
    //   0	442	0	this	vuuvuv
    //   17	295	1	i	int
    //   21	291	2	j	int
    //   25	288	3	k	int
    //   67	249	4	m	int
    //   131	168	5	n	int
    //   136	129	6	i1	int
    //   12	371	7	localIterator	Iterator
    //   400	3	7	localInvocationTargetException1	InvocationTargetException
    //   410	3	7	localInvocationTargetException2	InvocationTargetException
    //   418	3	7	localInvocationTargetException3	InvocationTargetException
    //   426	3	7	localInvocationTargetException4	InvocationTargetException
    //   434	3	7	localInvocationTargetException5	InvocationTargetException
    //   45	317	8	localObject	Object
    // Exception table:
    //   from	to	target	type
    //   47	59	400	java/lang/reflect/InvocationTargetException
    //   229	241	410	java/lang/reflect/InvocationTargetException
    //   111	123	418	java/lang/reflect/InvocationTargetException
    //   161	173	426	java/lang/reflect/InvocationTargetException
    //   349	361	434	java/lang/reflect/InvocationTargetException
  }
  
  /* Error */
  public void b0061a0061a006100610061a0061a(TreatmentTile paramTreatmentTile, int paramInt)
  {
    // Byte code:
    //   0: getstatic 59	uuuuuu/vuuvuv:bi0069i006900690069i0069i	I
    //   3: istore_3
    //   4: iload_3
    //   5: getstatic 103	uuuuuu/vuuvuv:b00690069i006900690069i0069i	I
    //   8: iload_3
    //   9: iadd
    //   10: imul
    //   11: getstatic 89	uuuuuu/vuuvuv:bii0069006900690069i0069i	I
    //   14: irem
    //   15: tableswitch	default:+17->32, 0:+466->481
    //   32: getstatic 59	uuuuuu/vuuvuv:bi0069i006900690069i0069i	I
    //   35: istore_3
    //   36: iload_3
    //   37: getstatic 103	uuuuuu/vuuvuv:b00690069i006900690069i0069i	I
    //   40: iload_3
    //   41: iadd
    //   42: imul
    //   43: getstatic 89	uuuuuu/vuuvuv:bii0069006900690069i0069i	I
    //   46: irem
    //   47: tableswitch	default:+17->64, 0:+345->392
    //   64: bipush 98
    //   66: putstatic 59	uuuuuu/vuuvuv:bi0069i006900690069i0069i	I
    //   69: ldc 2
    //   71: ldc_w 379
    //   74: bipush 28
    //   76: iconst_4
    //   77: invokestatic 101	xxxxxx/uxxxxx:bb00620062bb0062b0062b0062	(Ljava/lang/String;CC)Ljava/lang/String;
    //   80: iconst_0
    //   81: anewarray 69	java/lang/Class
    //   84: invokevirtual 73	java/lang/Class:getMethod	(Ljava/lang/String;[Ljava/lang/Class;)Ljava/lang/reflect/Method;
    //   87: astore 4
    //   89: aload 4
    //   91: aconst_null
    //   92: iconst_0
    //   93: anewarray 75	java/lang/Object
    //   96: invokevirtual 81	java/lang/reflect/Method:invoke	(Ljava/lang/Object;[Ljava/lang/Object;)Ljava/lang/Object;
    //   99: astore 4
    //   101: aload 4
    //   103: checkcast 83	java/lang/Integer
    //   106: invokevirtual 87	java/lang/Integer:intValue	()I
    //   109: putstatic 91	uuuuuu/vuuvuv:b0069i0069006900690069i0069i	I
    //   112: getstatic 59	uuuuuu/vuuvuv:bi0069i006900690069i0069i	I
    //   115: istore_3
    //   116: ldc 2
    //   118: ldc_w 381
    //   121: bipush 71
    //   123: iconst_4
    //   124: invokestatic 101	xxxxxx/uxxxxx:bb00620062bb0062b0062b0062	(Ljava/lang/String;CC)Ljava/lang/String;
    //   127: iconst_0
    //   128: anewarray 69	java/lang/Class
    //   131: invokevirtual 73	java/lang/Class:getMethod	(Ljava/lang/String;[Ljava/lang/Class;)Ljava/lang/reflect/Method;
    //   134: astore 4
    //   136: aload 4
    //   138: aconst_null
    //   139: iconst_0
    //   140: anewarray 75	java/lang/Object
    //   143: invokevirtual 81	java/lang/reflect/Method:invoke	(Ljava/lang/Object;[Ljava/lang/Object;)Ljava/lang/Object;
    //   146: astore 4
    //   148: aload 4
    //   150: checkcast 83	java/lang/Integer
    //   153: invokevirtual 87	java/lang/Integer:intValue	()I
    //   156: iload_3
    //   157: iadd
    //   158: iload_3
    //   159: imul
    //   160: getstatic 89	uuuuuu/vuuvuv:bii0069006900690069i0069i	I
    //   163: irem
    //   164: tableswitch	default:+20->184, 0:+228->392
    //   184: bipush 72
    //   186: putstatic 59	uuuuuu/vuuvuv:bi0069i006900690069i0069i	I
    //   189: ldc 2
    //   191: ldc_w 383
    //   194: sipush 193
    //   197: iconst_4
    //   198: invokestatic 101	xxxxxx/uxxxxx:bb00620062bb0062b0062b0062	(Ljava/lang/String;CC)Ljava/lang/String;
    //   201: iconst_0
    //   202: anewarray 69	java/lang/Class
    //   205: invokevirtual 73	java/lang/Class:getMethod	(Ljava/lang/String;[Ljava/lang/Class;)Ljava/lang/reflect/Method;
    //   208: astore 4
    //   210: aload 4
    //   212: aconst_null
    //   213: iconst_0
    //   214: anewarray 75	java/lang/Object
    //   217: invokevirtual 81	java/lang/reflect/Method:invoke	(Ljava/lang/Object;[Ljava/lang/Object;)Ljava/lang/Object;
    //   220: astore 4
    //   222: aload 4
    //   224: checkcast 83	java/lang/Integer
    //   227: invokevirtual 87	java/lang/Integer:intValue	()I
    //   230: putstatic 91	uuuuuu/vuuvuv:b0069i0069006900690069i0069i	I
    //   233: ldc 2
    //   235: ldc_w 385
    //   238: bipush 126
    //   240: iconst_5
    //   241: invokestatic 101	xxxxxx/uxxxxx:bb00620062bb0062b0062b0062	(Ljava/lang/String;CC)Ljava/lang/String;
    //   244: iconst_0
    //   245: anewarray 69	java/lang/Class
    //   248: invokevirtual 73	java/lang/Class:getMethod	(Ljava/lang/String;[Ljava/lang/Class;)Ljava/lang/reflect/Method;
    //   251: astore 4
    //   253: aload 4
    //   255: aconst_null
    //   256: iconst_0
    //   257: anewarray 75	java/lang/Object
    //   260: invokevirtual 81	java/lang/reflect/Method:invoke	(Ljava/lang/Object;[Ljava/lang/Object;)Ljava/lang/Object;
    //   263: astore 4
    //   265: aload 4
    //   267: checkcast 83	java/lang/Integer
    //   270: invokevirtual 87	java/lang/Integer:intValue	()I
    //   273: istore_3
    //   274: ldc 2
    //   276: ldc_w 387
    //   279: bipush 17
    //   281: sipush 178
    //   284: iconst_3
    //   285: invokestatic 67	xxxxxx/uxxxxx:bbbb0062b0062b0062b0062	(Ljava/lang/String;CCC)Ljava/lang/String;
    //   288: iconst_0
    //   289: anewarray 69	java/lang/Class
    //   292: invokevirtual 73	java/lang/Class:getMethod	(Ljava/lang/String;[Ljava/lang/Class;)Ljava/lang/reflect/Method;
    //   295: astore 4
    //   297: aload 4
    //   299: aconst_null
    //   300: iconst_0
    //   301: anewarray 75	java/lang/Object
    //   304: invokevirtual 81	java/lang/reflect/Method:invoke	(Ljava/lang/Object;[Ljava/lang/Object;)Ljava/lang/Object;
    //   307: astore 4
    //   309: aload 4
    //   311: checkcast 83	java/lang/Integer
    //   314: invokevirtual 87	java/lang/Integer:intValue	()I
    //   317: iload_3
    //   318: iadd
    //   319: iload_3
    //   320: imul
    //   321: getstatic 89	uuuuuu/vuuvuv:bii0069006900690069i0069i	I
    //   324: irem
    //   325: tableswitch	default:+19->344, 0:+67->392
    //   344: bipush 88
    //   346: putstatic 59	uuuuuu/vuuvuv:bi0069i006900690069i0069i	I
    //   349: ldc 2
    //   351: ldc 109
    //   353: sipush 233
    //   356: iconst_5
    //   357: invokestatic 101	xxxxxx/uxxxxx:bb00620062bb0062b0062b0062	(Ljava/lang/String;CC)Ljava/lang/String;
    //   360: iconst_0
    //   361: anewarray 69	java/lang/Class
    //   364: invokevirtual 73	java/lang/Class:getMethod	(Ljava/lang/String;[Ljava/lang/Class;)Ljava/lang/reflect/Method;
    //   367: astore 4
    //   369: aload 4
    //   371: aconst_null
    //   372: iconst_0
    //   373: anewarray 75	java/lang/Object
    //   376: invokevirtual 81	java/lang/reflect/Method:invoke	(Ljava/lang/Object;[Ljava/lang/Object;)Ljava/lang/Object;
    //   379: astore 4
    //   381: aload 4
    //   383: checkcast 83	java/lang/Integer
    //   386: invokevirtual 87	java/lang/Integer:intValue	()I
    //   389: putstatic 91	uuuuuu/vuuvuv:b0069i0069006900690069i0069i	I
    //   392: ldc 2
    //   394: ldc_w 389
    //   397: bipush 105
    //   399: iconst_1
    //   400: invokestatic 101	xxxxxx/uxxxxx:bb00620062bb0062b0062b0062	(Ljava/lang/String;CC)Ljava/lang/String;
    //   403: iconst_0
    //   404: anewarray 69	java/lang/Class
    //   407: invokevirtual 73	java/lang/Class:getMethod	(Ljava/lang/String;[Ljava/lang/Class;)Ljava/lang/reflect/Method;
    //   410: astore 4
    //   412: aload 4
    //   414: aconst_null
    //   415: iconst_0
    //   416: anewarray 75	java/lang/Object
    //   419: invokevirtual 81	java/lang/reflect/Method:invoke	(Ljava/lang/Object;[Ljava/lang/Object;)Ljava/lang/Object;
    //   422: astore 4
    //   424: aload 4
    //   426: checkcast 83	java/lang/Integer
    //   429: invokevirtual 87	java/lang/Integer:intValue	()I
    //   432: putstatic 59	uuuuuu/vuuvuv:bi0069i006900690069i0069i	I
    //   435: ldc 2
    //   437: ldc_w 391
    //   440: sipush 176
    //   443: bipush 94
    //   445: iconst_1
    //   446: invokestatic 67	xxxxxx/uxxxxx:bbbb0062b0062b0062b0062	(Ljava/lang/String;CCC)Ljava/lang/String;
    //   449: iconst_0
    //   450: anewarray 69	java/lang/Class
    //   453: invokevirtual 73	java/lang/Class:getMethod	(Ljava/lang/String;[Ljava/lang/Class;)Ljava/lang/reflect/Method;
    //   456: astore 4
    //   458: aload 4
    //   460: aconst_null
    //   461: iconst_0
    //   462: anewarray 75	java/lang/Object
    //   465: invokevirtual 81	java/lang/reflect/Method:invoke	(Ljava/lang/Object;[Ljava/lang/Object;)Ljava/lang/Object;
    //   468: astore 4
    //   470: aload 4
    //   472: checkcast 83	java/lang/Integer
    //   475: invokevirtual 87	java/lang/Integer:intValue	()I
    //   478: putstatic 91	uuuuuu/vuuvuv:b0069i0069006900690069i0069i	I
    //   481: ldc 2
    //   483: ldc_w 393
    //   486: sipush 162
    //   489: iconst_3
    //   490: invokestatic 101	xxxxxx/uxxxxx:bb00620062bb0062b0062b0062	(Ljava/lang/String;CC)Ljava/lang/String;
    //   493: iconst_1
    //   494: anewarray 69	java/lang/Class
    //   497: dup
    //   498: iconst_0
    //   499: ldc_w 373
    //   502: aastore
    //   503: invokevirtual 73	java/lang/Class:getMethod	(Ljava/lang/String;[Ljava/lang/Class;)Ljava/lang/reflect/Method;
    //   506: astore 4
    //   508: aload 4
    //   510: aload_0
    //   511: iconst_1
    //   512: anewarray 75	java/lang/Object
    //   515: dup
    //   516: iconst_0
    //   517: aload_1
    //   518: aastore
    //   519: invokevirtual 81	java/lang/reflect/Method:invoke	(Ljava/lang/Object;[Ljava/lang/Object;)Ljava/lang/Object;
    //   522: pop
    //   523: aload_0
    //   524: getfield 179	uuuuuu/vuuvuv:b006900690069i00690069i0069i	Luuuuuu/gaaaga;
    //   527: iload_2
    //   528: invokevirtual 397	uuuuuu/gaaaga:b0077ww00770077ww0077ww	(I)V
    //   531: return
    //   532: astore_1
    //   533: aload_1
    //   534: invokevirtual 117	java/lang/reflect/InvocationTargetException:getCause	()Ljava/lang/Throwable;
    //   537: athrow
    //   538: astore_1
    //   539: aload_1
    //   540: invokevirtual 117	java/lang/reflect/InvocationTargetException:getCause	()Ljava/lang/Throwable;
    //   543: athrow
    //   544: astore_1
    //   545: aload_1
    //   546: invokevirtual 117	java/lang/reflect/InvocationTargetException:getCause	()Ljava/lang/Throwable;
    //   549: athrow
    //   550: astore_1
    //   551: aload_1
    //   552: invokevirtual 117	java/lang/reflect/InvocationTargetException:getCause	()Ljava/lang/Throwable;
    //   555: athrow
    //   556: astore_1
    //   557: aload_1
    //   558: invokevirtual 117	java/lang/reflect/InvocationTargetException:getCause	()Ljava/lang/Throwable;
    //   561: athrow
    //   562: astore_1
    //   563: aload_1
    //   564: invokevirtual 117	java/lang/reflect/InvocationTargetException:getCause	()Ljava/lang/Throwable;
    //   567: athrow
    //   568: astore_1
    //   569: aload_1
    //   570: invokevirtual 117	java/lang/reflect/InvocationTargetException:getCause	()Ljava/lang/Throwable;
    //   573: athrow
    //   574: astore_1
    //   575: aload_1
    //   576: invokevirtual 117	java/lang/reflect/InvocationTargetException:getCause	()Ljava/lang/Throwable;
    //   579: athrow
    //   580: astore_1
    //   581: aload_1
    //   582: invokevirtual 117	java/lang/reflect/InvocationTargetException:getCause	()Ljava/lang/Throwable;
    //   585: athrow
    // Local variable table:
    //   start	length	slot	name	signature
    //   0	586	0	this	vuuvuv
    //   0	586	1	paramTreatmentTile	TreatmentTile
    //   0	586	2	paramInt	int
    //   3	318	3	i	int
    //   87	422	4	localObject	Object
    // Exception table:
    //   from	to	target	type
    //   458	470	532	java/lang/reflect/InvocationTargetException
    //   136	148	538	java/lang/reflect/InvocationTargetException
    //   89	101	544	java/lang/reflect/InvocationTargetException
    //   508	523	550	java/lang/reflect/InvocationTargetException
    //   412	424	556	java/lang/reflect/InvocationTargetException
    //   210	222	562	java/lang/reflect/InvocationTargetException
    //   253	265	568	java/lang/reflect/InvocationTargetException
    //   297	309	574	java/lang/reflect/InvocationTargetException
    //   369	381	580	java/lang/reflect/InvocationTargetException
  }
  
  /* Error */
  public TreatmentTile b0061aa0061aaa00610061a(final com.db.pwcc.dbmobile.treatments.model.TreatmentCache paramTreatmentCache, int paramInt)
  {
    // Byte code:
    //   0: getstatic 59	uuuuuu/vuuvuv:bi0069i006900690069i0069i	I
    //   3: istore_3
    //   4: iload_3
    //   5: getstatic 103	uuuuuu/vuuvuv:b00690069i006900690069i0069i	I
    //   8: iload_3
    //   9: iadd
    //   10: imul
    //   11: getstatic 89	uuuuuu/vuuvuv:bii0069006900690069i0069i	I
    //   14: irem
    //   15: tableswitch	default:+17->32, 0:+65->80
    //   32: ldc 2
    //   34: ldc_w 401
    //   37: bipush 14
    //   39: iconst_5
    //   40: invokestatic 101	xxxxxx/uxxxxx:bb00620062bb0062b0062b0062	(Ljava/lang/String;CC)Ljava/lang/String;
    //   43: iconst_0
    //   44: anewarray 69	java/lang/Class
    //   47: invokevirtual 73	java/lang/Class:getMethod	(Ljava/lang/String;[Ljava/lang/Class;)Ljava/lang/reflect/Method;
    //   50: astore 4
    //   52: aload 4
    //   54: aconst_null
    //   55: iconst_0
    //   56: anewarray 75	java/lang/Object
    //   59: invokevirtual 81	java/lang/reflect/Method:invoke	(Ljava/lang/Object;[Ljava/lang/Object;)Ljava/lang/Object;
    //   62: astore 4
    //   64: aload 4
    //   66: checkcast 83	java/lang/Integer
    //   69: invokevirtual 87	java/lang/Integer:intValue	()I
    //   72: putstatic 59	uuuuuu/vuuvuv:bi0069i006900690069i0069i	I
    //   75: bipush 42
    //   77: putstatic 91	uuuuuu/vuuvuv:b0069i0069006900690069i0069i	I
    //   80: new 403	com/db/pwcc/dbmobile/treatments/views/TreatmentTile
    //   83: dup
    //   84: aload_1
    //   85: iload_2
    //   86: invokespecial 406	com/db/pwcc/dbmobile/treatments/views/TreatmentTile:<init>	(Lcom/db/pwcc/dbmobile/treatments/model/TreatmentCache;I)V
    //   89: astore_1
    //   90: getstatic 59	uuuuuu/vuuvuv:bi0069i006900690069i0069i	I
    //   93: istore_2
    //   94: iload_2
    //   95: getstatic 103	uuuuuu/vuuvuv:b00690069i006900690069i0069i	I
    //   98: iload_2
    //   99: iadd
    //   100: imul
    //   101: getstatic 89	uuuuuu/vuuvuv:bii0069006900690069i0069i	I
    //   104: irem
    //   105: tableswitch	default:+19->124, 0:+67->172
    //   124: ldc 2
    //   126: ldc -113
    //   128: sipush 208
    //   131: iconst_5
    //   132: invokestatic 101	xxxxxx/uxxxxx:bb00620062bb0062b0062b0062	(Ljava/lang/String;CC)Ljava/lang/String;
    //   135: iconst_0
    //   136: anewarray 69	java/lang/Class
    //   139: invokevirtual 73	java/lang/Class:getMethod	(Ljava/lang/String;[Ljava/lang/Class;)Ljava/lang/reflect/Method;
    //   142: astore 4
    //   144: aload 4
    //   146: aconst_null
    //   147: iconst_0
    //   148: anewarray 75	java/lang/Object
    //   151: invokevirtual 81	java/lang/reflect/Method:invoke	(Ljava/lang/Object;[Ljava/lang/Object;)Ljava/lang/Object;
    //   154: astore 4
    //   156: aload 4
    //   158: checkcast 83	java/lang/Integer
    //   161: invokevirtual 87	java/lang/Integer:intValue	()I
    //   164: putstatic 59	uuuuuu/vuuvuv:bi0069i006900690069i0069i	I
    //   167: bipush 57
    //   169: putstatic 91	uuuuuu/vuuvuv:b0069i0069006900690069i0069i	I
    //   172: getstatic 59	uuuuuu/vuuvuv:bi0069i006900690069i0069i	I
    //   175: istore_2
    //   176: iload_2
    //   177: getstatic 103	uuuuuu/vuuvuv:b00690069i006900690069i0069i	I
    //   180: iload_2
    //   181: iadd
    //   182: imul
    //   183: getstatic 89	uuuuuu/vuuvuv:bii0069006900690069i0069i	I
    //   186: irem
    //   187: tableswitch	default:+17->204, 0:+111->298
    //   204: ldc 2
    //   206: ldc_w 408
    //   209: sipush 212
    //   212: sipush 180
    //   215: iconst_1
    //   216: invokestatic 67	xxxxxx/uxxxxx:bbbb0062b0062b0062b0062	(Ljava/lang/String;CCC)Ljava/lang/String;
    //   219: iconst_0
    //   220: anewarray 69	java/lang/Class
    //   223: invokevirtual 73	java/lang/Class:getMethod	(Ljava/lang/String;[Ljava/lang/Class;)Ljava/lang/reflect/Method;
    //   226: astore 4
    //   228: aload 4
    //   230: aconst_null
    //   231: iconst_0
    //   232: anewarray 75	java/lang/Object
    //   235: invokevirtual 81	java/lang/reflect/Method:invoke	(Ljava/lang/Object;[Ljava/lang/Object;)Ljava/lang/Object;
    //   238: astore 4
    //   240: aload 4
    //   242: checkcast 83	java/lang/Integer
    //   245: invokevirtual 87	java/lang/Integer:intValue	()I
    //   248: putstatic 59	uuuuuu/vuuvuv:bi0069i006900690069i0069i	I
    //   251: ldc 2
    //   253: ldc_w 410
    //   256: sipush 254
    //   259: sipush 218
    //   262: iconst_3
    //   263: invokestatic 67	xxxxxx/uxxxxx:bbbb0062b0062b0062b0062	(Ljava/lang/String;CCC)Ljava/lang/String;
    //   266: iconst_0
    //   267: anewarray 69	java/lang/Class
    //   270: invokevirtual 73	java/lang/Class:getMethod	(Ljava/lang/String;[Ljava/lang/Class;)Ljava/lang/reflect/Method;
    //   273: astore 4
    //   275: aload 4
    //   277: aconst_null
    //   278: iconst_0
    //   279: anewarray 75	java/lang/Object
    //   282: invokevirtual 81	java/lang/reflect/Method:invoke	(Ljava/lang/Object;[Ljava/lang/Object;)Ljava/lang/Object;
    //   285: astore 4
    //   287: aload 4
    //   289: checkcast 83	java/lang/Integer
    //   292: invokevirtual 87	java/lang/Integer:intValue	()I
    //   295: putstatic 91	uuuuuu/vuuvuv:b0069i0069006900690069i0069i	I
    //   298: getstatic 59	uuuuuu/vuuvuv:bi0069i006900690069i0069i	I
    //   301: getstatic 103	uuuuuu/vuuvuv:b00690069i006900690069i0069i	I
    //   304: iadd
    //   305: getstatic 59	uuuuuu/vuuvuv:bi0069i006900690069i0069i	I
    //   308: imul
    //   309: getstatic 89	uuuuuu/vuuvuv:bii0069006900690069i0069i	I
    //   312: irem
    //   313: getstatic 91	uuuuuu/vuuvuv:b0069i0069006900690069i0069i	I
    //   316: if_icmpeq +90 -> 406
    //   319: ldc 2
    //   321: ldc_w 412
    //   324: sipush 239
    //   327: iconst_3
    //   328: invokestatic 101	xxxxxx/uxxxxx:bb00620062bb0062b0062b0062	(Ljava/lang/String;CC)Ljava/lang/String;
    //   331: iconst_0
    //   332: anewarray 69	java/lang/Class
    //   335: invokevirtual 73	java/lang/Class:getMethod	(Ljava/lang/String;[Ljava/lang/Class;)Ljava/lang/reflect/Method;
    //   338: astore 4
    //   340: aload 4
    //   342: aconst_null
    //   343: iconst_0
    //   344: anewarray 75	java/lang/Object
    //   347: invokevirtual 81	java/lang/reflect/Method:invoke	(Ljava/lang/Object;[Ljava/lang/Object;)Ljava/lang/Object;
    //   350: astore 4
    //   352: aload 4
    //   354: checkcast 83	java/lang/Integer
    //   357: invokevirtual 87	java/lang/Integer:intValue	()I
    //   360: putstatic 59	uuuuuu/vuuvuv:bi0069i006900690069i0069i	I
    //   363: ldc 2
    //   365: ldc_w 414
    //   368: bipush 63
    //   370: iconst_5
    //   371: invokestatic 101	xxxxxx/uxxxxx:bb00620062bb0062b0062b0062	(Ljava/lang/String;CC)Ljava/lang/String;
    //   374: iconst_0
    //   375: anewarray 69	java/lang/Class
    //   378: invokevirtual 73	java/lang/Class:getMethod	(Ljava/lang/String;[Ljava/lang/Class;)Ljava/lang/reflect/Method;
    //   381: astore 4
    //   383: aload 4
    //   385: aconst_null
    //   386: iconst_0
    //   387: anewarray 75	java/lang/Object
    //   390: invokevirtual 81	java/lang/reflect/Method:invoke	(Ljava/lang/Object;[Ljava/lang/Object;)Ljava/lang/Object;
    //   393: astore 4
    //   395: aload 4
    //   397: checkcast 83	java/lang/Integer
    //   400: invokevirtual 87	java/lang/Integer:intValue	()I
    //   403: putstatic 91	uuuuuu/vuuvuv:b0069i0069006900690069i0069i	I
    //   406: aload_1
    //   407: new 12	uuuuuu/vuuvuv$2
    //   410: dup
    //   411: aload_0
    //   412: aload_1
    //   413: aload_1
    //   414: invokevirtual 417	com/db/pwcc/dbmobile/treatments/views/TreatmentTile:getPosition	()I
    //   417: invokespecial 420	uuuuuu/vuuvuv$2:<init>	(Luuuuuu/vuuvuv;Lcom/db/pwcc/dbmobile/treatments/views/TreatmentTile;I)V
    //   420: invokevirtual 424	com/db/pwcc/dbmobile/treatments/views/TreatmentTile:setTreatmentTileDismissedListener	(Luuuuuu/hhphhh;)V
    //   423: aload_1
    //   424: areturn
    //   425: astore_1
    //   426: aload_1
    //   427: invokevirtual 117	java/lang/reflect/InvocationTargetException:getCause	()Ljava/lang/Throwable;
    //   430: athrow
    //   431: astore_1
    //   432: aload_1
    //   433: invokevirtual 117	java/lang/reflect/InvocationTargetException:getCause	()Ljava/lang/Throwable;
    //   436: athrow
    //   437: astore_1
    //   438: aload_1
    //   439: invokevirtual 117	java/lang/reflect/InvocationTargetException:getCause	()Ljava/lang/Throwable;
    //   442: athrow
    //   443: astore_1
    //   444: aload_1
    //   445: invokevirtual 117	java/lang/reflect/InvocationTargetException:getCause	()Ljava/lang/Throwable;
    //   448: athrow
    //   449: astore_1
    //   450: aload_1
    //   451: invokevirtual 117	java/lang/reflect/InvocationTargetException:getCause	()Ljava/lang/Throwable;
    //   454: athrow
    //   455: astore_1
    //   456: aload_1
    //   457: invokevirtual 117	java/lang/reflect/InvocationTargetException:getCause	()Ljava/lang/Throwable;
    //   460: athrow
    // Local variable table:
    //   start	length	slot	name	signature
    //   0	461	0	this	vuuvuv
    //   0	461	1	paramTreatmentCache	com.db.pwcc.dbmobile.treatments.model.TreatmentCache
    //   0	461	2	paramInt	int
    //   3	8	3	i	int
    //   50	346	4	localObject	Object
    // Exception table:
    //   from	to	target	type
    //   52	64	425	java/lang/reflect/InvocationTargetException
    //   340	352	431	java/lang/reflect/InvocationTargetException
    //   383	395	437	java/lang/reflect/InvocationTargetException
    //   228	240	443	java/lang/reflect/InvocationTargetException
    //   275	287	449	java/lang/reflect/InvocationTargetException
    //   144	156	455	java/lang/reflect/InvocationTargetException
  }
  
  /* Error */
  public void b0061aaa006100610061a0061a(uuvvuv.uvuvuv paramUvuvuv, Context paramContext)
  {
    // Byte code:
    //   0: aload_0
    //   1: aload_1
    //   2: invokespecial 430	uuuuuu/qppppp:ba0061a0061a0061a0061aa	(Luuuuuu/ttssst$tsssst;)V
    //   5: aload_0
    //   6: getfield 432	uuuuuu/vuuvuv:b00690069ii00690069i0069i	Luuuuuu/qpqqqq;
    //   9: astore_1
    //   10: ldc 2
    //   12: ldc_w 434
    //   15: sipush 246
    //   18: bipush 98
    //   20: iconst_0
    //   21: invokestatic 67	xxxxxx/uxxxxx:bbbb0062b0062b0062b0062	(Ljava/lang/String;CCC)Ljava/lang/String;
    //   24: iconst_0
    //   25: anewarray 69	java/lang/Class
    //   28: invokevirtual 73	java/lang/Class:getMethod	(Ljava/lang/String;[Ljava/lang/Class;)Ljava/lang/reflect/Method;
    //   31: astore 5
    //   33: aload 5
    //   35: aconst_null
    //   36: iconst_0
    //   37: anewarray 75	java/lang/Object
    //   40: invokevirtual 81	java/lang/reflect/Method:invoke	(Ljava/lang/Object;[Ljava/lang/Object;)Ljava/lang/Object;
    //   43: astore 5
    //   45: aload 5
    //   47: checkcast 83	java/lang/Integer
    //   50: invokevirtual 87	java/lang/Integer:intValue	()I
    //   53: istore_3
    //   54: getstatic 103	uuuuuu/vuuvuv:b00690069i006900690069i0069i	I
    //   57: istore 4
    //   59: ldc 2
    //   61: ldc_w 436
    //   64: sipush 148
    //   67: iconst_5
    //   68: invokestatic 101	xxxxxx/uxxxxx:bb00620062bb0062b0062b0062	(Ljava/lang/String;CC)Ljava/lang/String;
    //   71: iconst_0
    //   72: anewarray 69	java/lang/Class
    //   75: invokevirtual 73	java/lang/Class:getMethod	(Ljava/lang/String;[Ljava/lang/Class;)Ljava/lang/reflect/Method;
    //   78: astore 5
    //   80: aload 5
    //   82: aconst_null
    //   83: iconst_0
    //   84: anewarray 75	java/lang/Object
    //   87: invokevirtual 81	java/lang/reflect/Method:invoke	(Ljava/lang/Object;[Ljava/lang/Object;)Ljava/lang/Object;
    //   90: astore 5
    //   92: aload 5
    //   94: checkcast 83	java/lang/Integer
    //   97: invokevirtual 87	java/lang/Integer:intValue	()I
    //   100: iload 4
    //   102: iload_3
    //   103: iadd
    //   104: imul
    //   105: getstatic 89	uuuuuu/vuuvuv:bii0069006900690069i0069i	I
    //   108: irem
    //   109: getstatic 91	uuuuuu/vuuvuv:b0069i0069006900690069i0069i	I
    //   112: if_icmpeq +13 -> 125
    //   115: bipush 61
    //   117: putstatic 59	uuuuuu/vuuvuv:bi0069i006900690069i0069i	I
    //   120: bipush 32
    //   122: putstatic 91	uuuuuu/vuuvuv:b0069i0069006900690069i0069i	I
    //   125: aload_1
    //   126: ifnull +297 -> 423
    //   129: aload_0
    //   130: getfield 432	uuuuuu/vuuvuv:b00690069ii00690069i0069i	Luuuuuu/qpqqqq;
    //   133: invokeinterface 442 1 0
    //   138: ifnull +285 -> 423
    //   141: getstatic 59	uuuuuu/vuuvuv:bi0069i006900690069i0069i	I
    //   144: istore_3
    //   145: iload_3
    //   146: getstatic 103	uuuuuu/vuuvuv:b00690069i006900690069i0069i	I
    //   149: iload_3
    //   150: iadd
    //   151: imul
    //   152: getstatic 89	uuuuuu/vuuvuv:bii0069006900690069i0069i	I
    //   155: irem
    //   156: tableswitch	default:+20->176, 0:+30->186
    //   176: bipush 88
    //   178: putstatic 59	uuuuuu/vuuvuv:bi0069i006900690069i0069i	I
    //   181: bipush 52
    //   183: putstatic 91	uuuuuu/vuuvuv:b0069i0069006900690069i0069i	I
    //   186: aload_0
    //   187: getfield 432	uuuuuu/vuuvuv:b00690069ii00690069i0069i	Luuuuuu/qpqqqq;
    //   190: invokeinterface 442 1 0
    //   195: astore_1
    //   196: getstatic 59	uuuuuu/vuuvuv:bi0069i006900690069i0069i	I
    //   199: getstatic 103	uuuuuu/vuuvuv:b00690069i006900690069i0069i	I
    //   202: iadd
    //   203: getstatic 59	uuuuuu/vuuvuv:bi0069i006900690069i0069i	I
    //   206: imul
    //   207: getstatic 89	uuuuuu/vuuvuv:bii0069006900690069i0069i	I
    //   210: irem
    //   211: getstatic 91	uuuuuu/vuuvuv:b0069i0069006900690069i0069i	I
    //   214: if_icmpeq +158 -> 372
    //   217: ldc 2
    //   219: ldc_w 444
    //   222: bipush 21
    //   224: iconst_2
    //   225: invokestatic 101	xxxxxx/uxxxxx:bb00620062bb0062b0062b0062	(Ljava/lang/String;CC)Ljava/lang/String;
    //   228: iconst_0
    //   229: anewarray 69	java/lang/Class
    //   232: invokevirtual 73	java/lang/Class:getMethod	(Ljava/lang/String;[Ljava/lang/Class;)Ljava/lang/reflect/Method;
    //   235: astore 5
    //   237: aload 5
    //   239: aconst_null
    //   240: iconst_0
    //   241: anewarray 75	java/lang/Object
    //   244: invokevirtual 81	java/lang/reflect/Method:invoke	(Ljava/lang/Object;[Ljava/lang/Object;)Ljava/lang/Object;
    //   247: astore 5
    //   249: aload 5
    //   251: checkcast 83	java/lang/Integer
    //   254: invokevirtual 87	java/lang/Integer:intValue	()I
    //   257: putstatic 59	uuuuuu/vuuvuv:bi0069i006900690069i0069i	I
    //   260: ldc 2
    //   262: ldc_w 446
    //   265: bipush 118
    //   267: iconst_5
    //   268: invokestatic 101	xxxxxx/uxxxxx:bb00620062bb0062b0062b0062	(Ljava/lang/String;CC)Ljava/lang/String;
    //   271: iconst_0
    //   272: anewarray 69	java/lang/Class
    //   275: invokevirtual 73	java/lang/Class:getMethod	(Ljava/lang/String;[Ljava/lang/Class;)Ljava/lang/reflect/Method;
    //   278: astore 5
    //   280: aload 5
    //   282: aconst_null
    //   283: iconst_0
    //   284: anewarray 75	java/lang/Object
    //   287: invokevirtual 81	java/lang/reflect/Method:invoke	(Ljava/lang/Object;[Ljava/lang/Object;)Ljava/lang/Object;
    //   290: astore 5
    //   292: aload 5
    //   294: checkcast 83	java/lang/Integer
    //   297: invokevirtual 87	java/lang/Integer:intValue	()I
    //   300: putstatic 91	uuuuuu/vuuvuv:b0069i0069006900690069i0069i	I
    //   303: getstatic 59	uuuuuu/vuuvuv:bi0069i006900690069i0069i	I
    //   306: getstatic 103	uuuuuu/vuuvuv:b00690069i006900690069i0069i	I
    //   309: iadd
    //   310: getstatic 59	uuuuuu/vuuvuv:bi0069i006900690069i0069i	I
    //   313: imul
    //   314: getstatic 89	uuuuuu/vuuvuv:bii0069006900690069i0069i	I
    //   317: irem
    //   318: getstatic 91	uuuuuu/vuuvuv:b0069i0069006900690069i0069i	I
    //   321: if_icmpeq +51 -> 372
    //   324: bipush 99
    //   326: putstatic 59	uuuuuu/vuuvuv:bi0069i006900690069i0069i	I
    //   329: ldc 2
    //   331: ldc_w 448
    //   334: bipush 34
    //   336: iconst_4
    //   337: invokestatic 101	xxxxxx/uxxxxx:bb00620062bb0062b0062b0062	(Ljava/lang/String;CC)Ljava/lang/String;
    //   340: iconst_0
    //   341: anewarray 69	java/lang/Class
    //   344: invokevirtual 73	java/lang/Class:getMethod	(Ljava/lang/String;[Ljava/lang/Class;)Ljava/lang/reflect/Method;
    //   347: astore 5
    //   349: aload 5
    //   351: aconst_null
    //   352: iconst_0
    //   353: anewarray 75	java/lang/Object
    //   356: invokevirtual 81	java/lang/reflect/Method:invoke	(Ljava/lang/Object;[Ljava/lang/Object;)Ljava/lang/Object;
    //   359: astore 5
    //   361: aload 5
    //   363: checkcast 83	java/lang/Integer
    //   366: invokevirtual 87	java/lang/Integer:intValue	()I
    //   369: putstatic 91	uuuuuu/vuuvuv:b0069i0069006900690069i0069i	I
    //   372: ldc 2
    //   374: ldc_w 450
    //   377: sipush 207
    //   380: iconst_3
    //   381: invokestatic 101	xxxxxx/uxxxxx:bb00620062bb0062b0062b0062	(Ljava/lang/String;CC)Ljava/lang/String;
    //   384: iconst_2
    //   385: anewarray 69	java/lang/Class
    //   388: dup
    //   389: iconst_0
    //   390: ldc_w 452
    //   393: aastore
    //   394: dup
    //   395: iconst_1
    //   396: ldc -33
    //   398: aastore
    //   399: invokevirtual 73	java/lang/Class:getMethod	(Ljava/lang/String;[Ljava/lang/Class;)Ljava/lang/reflect/Method;
    //   402: astore 5
    //   404: aload 5
    //   406: aload_0
    //   407: iconst_2
    //   408: anewarray 75	java/lang/Object
    //   411: dup
    //   412: iconst_0
    //   413: aload_2
    //   414: aastore
    //   415: dup
    //   416: iconst_1
    //   417: aload_1
    //   418: aastore
    //   419: invokevirtual 81	java/lang/reflect/Method:invoke	(Ljava/lang/Object;[Ljava/lang/Object;)Ljava/lang/Object;
    //   422: pop
    //   423: ldc 2
    //   425: ldc_w 454
    //   428: sipush 172
    //   431: iconst_4
    //   432: invokestatic 101	xxxxxx/uxxxxx:bb00620062bb0062b0062b0062	(Ljava/lang/String;CC)Ljava/lang/String;
    //   435: iconst_1
    //   436: anewarray 69	java/lang/Class
    //   439: dup
    //   440: iconst_0
    //   441: ldc_w 452
    //   444: aastore
    //   445: invokevirtual 73	java/lang/Class:getMethod	(Ljava/lang/String;[Ljava/lang/Class;)Ljava/lang/reflect/Method;
    //   448: astore_1
    //   449: aload_1
    //   450: aload_0
    //   451: iconst_1
    //   452: anewarray 75	java/lang/Object
    //   455: dup
    //   456: iconst_0
    //   457: aload_2
    //   458: aastore
    //   459: invokevirtual 81	java/lang/reflect/Method:invoke	(Ljava/lang/Object;[Ljava/lang/Object;)Ljava/lang/Object;
    //   462: pop
    //   463: return
    //   464: astore_1
    //   465: aload_1
    //   466: invokevirtual 117	java/lang/reflect/InvocationTargetException:getCause	()Ljava/lang/Throwable;
    //   469: athrow
    //   470: astore_1
    //   471: aload_1
    //   472: invokevirtual 117	java/lang/reflect/InvocationTargetException:getCause	()Ljava/lang/Throwable;
    //   475: athrow
    //   476: astore_1
    //   477: aload_1
    //   478: invokevirtual 117	java/lang/reflect/InvocationTargetException:getCause	()Ljava/lang/Throwable;
    //   481: athrow
    //   482: astore_1
    //   483: aload_1
    //   484: invokevirtual 117	java/lang/reflect/InvocationTargetException:getCause	()Ljava/lang/Throwable;
    //   487: athrow
    //   488: astore_1
    //   489: aload_1
    //   490: invokevirtual 117	java/lang/reflect/InvocationTargetException:getCause	()Ljava/lang/Throwable;
    //   493: athrow
    //   494: astore_1
    //   495: aload_1
    //   496: invokevirtual 117	java/lang/reflect/InvocationTargetException:getCause	()Ljava/lang/Throwable;
    //   499: athrow
    //   500: astore_1
    //   501: aload_1
    //   502: invokevirtual 117	java/lang/reflect/InvocationTargetException:getCause	()Ljava/lang/Throwable;
    //   505: athrow
    // Local variable table:
    //   start	length	slot	name	signature
    //   0	506	0	this	vuuvuv
    //   0	506	1	paramUvuvuv	uuvvuv.uvuvuv
    //   0	506	2	paramContext	Context
    //   53	99	3	i	int
    //   57	47	4	j	int
    //   31	374	5	localObject	Object
    // Exception table:
    //   from	to	target	type
    //   33	45	464	java/lang/reflect/InvocationTargetException
    //   80	92	470	java/lang/reflect/InvocationTargetException
    //   237	249	476	java/lang/reflect/InvocationTargetException
    //   280	292	482	java/lang/reflect/InvocationTargetException
    //   404	423	488	java/lang/reflect/InvocationTargetException
    //   449	463	494	java/lang/reflect/InvocationTargetException
    //   349	361	500	java/lang/reflect/InvocationTargetException
  }
  
  /* Error */
  public void b0061aaaaaa00610061a()
  {
    // Byte code:
    //   0: aload_0
    //   1: getfield 159	uuuuuu/vuuvuv:bi0069ii00690069i0069i	Luuuuuu/sssttt;
    //   4: getstatic 165	com/db/pwcc/dbmobile/foundation/features/Feature:TREATMENTS	Lcom/db/pwcc/dbmobile/foundation/features/Feature;
    //   7: invokevirtual 171	uuuuuu/sssttt:bk006Bkkk006B006B006Bkk	(Lcom/db/pwcc/dbmobile/foundation/features/Feature;)Luuuuuu/sststt;
    //   10: getstatic 177	uuuuuu/sststt:b006En006En006Enn006En	Luuuuuu/sststt;
    //   13: if_acmpne +13 -> 26
    //   16: aload_0
    //   17: getfield 179	uuuuuu/vuuvuv:b006900690069i00690069i0069i	Luuuuuu/gaaaga;
    //   20: invokevirtual 458	uuuuuu/gaaaga:bw007700770077www0077ww	()Z
    //   23: ifne +4 -> 27
    //   26: return
    //   27: aload_0
    //   28: getfield 179	uuuuuu/vuuvuv:b006900690069i00690069i0069i	Luuuuuu/gaaaga;
    //   31: iconst_2
    //   32: invokevirtual 462	uuuuuu/gaaaga:b0077ww0077www0077ww	(I)Z
    //   35: ifeq +74 -> 109
    //   38: aload_0
    //   39: getfield 179	uuuuuu/vuuvuv:b006900690069i00690069i0069i	Luuuuuu/gaaaga;
    //   42: iconst_2
    //   43: invokevirtual 465	uuuuuu/gaaaga:bwww0077www0077ww	(I)V
    //   46: aload_0
    //   47: getfield 179	uuuuuu/vuuvuv:b006900690069i00690069i0069i	Luuuuuu/gaaaga;
    //   50: iconst_2
    //   51: invokevirtual 185	uuuuuu/gaaaga:b0077w0077wwww0077ww	(I)Lcom/db/pwcc/dbmobile/treatments/model/TreatmentCache;
    //   54: astore 5
    //   56: aload 5
    //   58: ifnull +529 -> 587
    //   61: ldc 2
    //   63: ldc_w 467
    //   66: sipush 157
    //   69: iconst_3
    //   70: invokestatic 101	xxxxxx/uxxxxx:bb00620062bb0062b0062b0062	(Ljava/lang/String;CC)Ljava/lang/String;
    //   73: iconst_1
    //   74: anewarray 69	java/lang/Class
    //   77: dup
    //   78: iconst_0
    //   79: ldc -69
    //   81: aastore
    //   82: invokevirtual 73	java/lang/Class:getMethod	(Ljava/lang/String;[Ljava/lang/Class;)Ljava/lang/reflect/Method;
    //   85: astore 6
    //   87: aload 6
    //   89: aload_0
    //   90: iconst_1
    //   91: anewarray 75	java/lang/Object
    //   94: dup
    //   95: iconst_0
    //   96: aload 5
    //   98: aastore
    //   99: invokevirtual 81	java/lang/reflect/Method:invoke	(Ljava/lang/Object;[Ljava/lang/Object;)Ljava/lang/Object;
    //   102: pop
    //   103: getstatic 470	uuuuuu/vvrvrv:b00780078007800780078xxxx	Luuuuuu/vvrvrv;
    //   106: invokestatic 308	uuuuuu/rrvvrv:b0071q0071qq0071q0071q0071	(Luuuuuu/vvrvrv;)V
    //   109: aload_0
    //   110: getfield 179	uuuuuu/vuuvuv:b006900690069i00690069i0069i	Luuuuuu/gaaaga;
    //   113: iconst_3
    //   114: invokevirtual 462	uuuuuu/gaaaga:b0077ww0077www0077ww	(I)Z
    //   117: ifeq -91 -> 26
    //   120: getstatic 59	uuuuuu/vuuvuv:bi0069i006900690069i0069i	I
    //   123: istore_1
    //   124: ldc 2
    //   126: ldc_w 472
    //   129: sipush 189
    //   132: sipush 144
    //   135: iconst_1
    //   136: invokestatic 67	xxxxxx/uxxxxx:bbbb0062b0062b0062b0062	(Ljava/lang/String;CCC)Ljava/lang/String;
    //   139: iconst_0
    //   140: anewarray 69	java/lang/Class
    //   143: invokevirtual 73	java/lang/Class:getMethod	(Ljava/lang/String;[Ljava/lang/Class;)Ljava/lang/reflect/Method;
    //   146: astore 5
    //   148: aload 5
    //   150: aconst_null
    //   151: iconst_0
    //   152: anewarray 75	java/lang/Object
    //   155: invokevirtual 81	java/lang/reflect/Method:invoke	(Ljava/lang/Object;[Ljava/lang/Object;)Ljava/lang/Object;
    //   158: astore 5
    //   160: aload 5
    //   162: checkcast 83	java/lang/Integer
    //   165: invokevirtual 87	java/lang/Integer:intValue	()I
    //   168: iload_1
    //   169: iadd
    //   170: getstatic 59	uuuuuu/vuuvuv:bi0069i006900690069i0069i	I
    //   173: imul
    //   174: getstatic 89	uuuuuu/vuuvuv:bii0069006900690069i0069i	I
    //   177: irem
    //   178: getstatic 91	uuuuuu/vuuvuv:b0069i0069006900690069i0069i	I
    //   181: if_icmpeq +13 -> 194
    //   184: bipush 76
    //   186: putstatic 59	uuuuuu/vuuvuv:bi0069i006900690069i0069i	I
    //   189: bipush 68
    //   191: putstatic 91	uuuuuu/vuuvuv:b0069i0069006900690069i0069i	I
    //   194: aload_0
    //   195: getfield 179	uuuuuu/vuuvuv:b006900690069i00690069i0069i	Luuuuuu/gaaaga;
    //   198: iconst_3
    //   199: invokevirtual 465	uuuuuu/gaaaga:bwww0077www0077ww	(I)V
    //   202: aload_0
    //   203: getfield 179	uuuuuu/vuuvuv:b006900690069i00690069i0069i	Luuuuuu/gaaaga;
    //   206: iconst_3
    //   207: invokevirtual 185	uuuuuu/gaaaga:b0077w0077wwww0077ww	(I)Lcom/db/pwcc/dbmobile/treatments/model/TreatmentCache;
    //   210: astore 5
    //   212: aload 5
    //   214: ifnull +390 -> 604
    //   217: ldc 2
    //   219: ldc_w 474
    //   222: sipush 131
    //   225: bipush 115
    //   227: iconst_1
    //   228: invokestatic 67	xxxxxx/uxxxxx:bbbb0062b0062b0062b0062	(Ljava/lang/String;CCC)Ljava/lang/String;
    //   231: iconst_1
    //   232: anewarray 69	java/lang/Class
    //   235: dup
    //   236: iconst_0
    //   237: ldc -69
    //   239: aastore
    //   240: invokevirtual 73	java/lang/Class:getMethod	(Ljava/lang/String;[Ljava/lang/Class;)Ljava/lang/reflect/Method;
    //   243: astore 6
    //   245: aload 6
    //   247: aload_0
    //   248: iconst_1
    //   249: anewarray 75	java/lang/Object
    //   252: dup
    //   253: iconst_0
    //   254: aload 5
    //   256: aastore
    //   257: invokevirtual 81	java/lang/reflect/Method:invoke	(Ljava/lang/Object;[Ljava/lang/Object;)Ljava/lang/Object;
    //   260: pop
    //   261: getstatic 477	uuuuuu/vvrvrv:bx0078x00780078xxxx	Luuuuuu/vvrvrv;
    //   264: invokestatic 308	uuuuuu/rrvvrv:b0071q0071qq0071q0071q0071	(Luuuuuu/vvrvrv;)V
    //   267: getstatic 59	uuuuuu/vuuvuv:bi0069i006900690069i0069i	I
    //   270: istore_1
    //   271: getstatic 103	uuuuuu/vuuvuv:b00690069i006900690069i0069i	I
    //   274: istore_2
    //   275: getstatic 59	uuuuuu/vuuvuv:bi0069i006900690069i0069i	I
    //   278: istore_3
    //   279: getstatic 89	uuuuuu/vuuvuv:bii0069006900690069i0069i	I
    //   282: istore 4
    //   284: ldc 2
    //   286: ldc_w 479
    //   289: sipush 179
    //   292: iconst_5
    //   293: invokestatic 101	xxxxxx/uxxxxx:bb00620062bb0062b0062b0062	(Ljava/lang/String;CC)Ljava/lang/String;
    //   296: iconst_0
    //   297: anewarray 69	java/lang/Class
    //   300: invokevirtual 73	java/lang/Class:getMethod	(Ljava/lang/String;[Ljava/lang/Class;)Ljava/lang/reflect/Method;
    //   303: astore 5
    //   305: aload 5
    //   307: aconst_null
    //   308: iconst_0
    //   309: anewarray 75	java/lang/Object
    //   312: invokevirtual 81	java/lang/reflect/Method:invoke	(Ljava/lang/Object;[Ljava/lang/Object;)Ljava/lang/Object;
    //   315: astore 5
    //   317: iload_1
    //   318: iload_2
    //   319: iadd
    //   320: iload_3
    //   321: imul
    //   322: iload 4
    //   324: irem
    //   325: aload 5
    //   327: checkcast 83	java/lang/Integer
    //   330: invokevirtual 87	java/lang/Integer:intValue	()I
    //   333: if_icmpeq -307 -> 26
    //   336: getstatic 59	uuuuuu/vuuvuv:bi0069i006900690069i0069i	I
    //   339: istore_1
    //   340: ldc 2
    //   342: ldc_w 481
    //   345: sipush 136
    //   348: bipush 82
    //   350: iconst_2
    //   351: invokestatic 67	xxxxxx/uxxxxx:bbbb0062b0062b0062b0062	(Ljava/lang/String;CCC)Ljava/lang/String;
    //   354: iconst_0
    //   355: anewarray 69	java/lang/Class
    //   358: invokevirtual 73	java/lang/Class:getMethod	(Ljava/lang/String;[Ljava/lang/Class;)Ljava/lang/reflect/Method;
    //   361: astore 5
    //   363: aload 5
    //   365: aconst_null
    //   366: iconst_0
    //   367: anewarray 75	java/lang/Object
    //   370: invokevirtual 81	java/lang/reflect/Method:invoke	(Ljava/lang/Object;[Ljava/lang/Object;)Ljava/lang/Object;
    //   373: astore 5
    //   375: aload 5
    //   377: checkcast 83	java/lang/Integer
    //   380: invokevirtual 87	java/lang/Integer:intValue	()I
    //   383: iload_1
    //   384: iadd
    //   385: getstatic 59	uuuuuu/vuuvuv:bi0069i006900690069i0069i	I
    //   388: imul
    //   389: getstatic 89	uuuuuu/vuuvuv:bii0069006900690069i0069i	I
    //   392: irem
    //   393: getstatic 91	uuuuuu/vuuvuv:b0069i0069006900690069i0069i	I
    //   396: if_icmpeq +54 -> 450
    //   399: ldc 2
    //   401: ldc_w 483
    //   404: sipush 179
    //   407: bipush 20
    //   409: iconst_3
    //   410: invokestatic 67	xxxxxx/uxxxxx:bbbb0062b0062b0062b0062	(Ljava/lang/String;CCC)Ljava/lang/String;
    //   413: iconst_0
    //   414: anewarray 69	java/lang/Class
    //   417: invokevirtual 73	java/lang/Class:getMethod	(Ljava/lang/String;[Ljava/lang/Class;)Ljava/lang/reflect/Method;
    //   420: astore 5
    //   422: aload 5
    //   424: aconst_null
    //   425: iconst_0
    //   426: anewarray 75	java/lang/Object
    //   429: invokevirtual 81	java/lang/reflect/Method:invoke	(Ljava/lang/Object;[Ljava/lang/Object;)Ljava/lang/Object;
    //   432: astore 5
    //   434: aload 5
    //   436: checkcast 83	java/lang/Integer
    //   439: invokevirtual 87	java/lang/Integer:intValue	()I
    //   442: putstatic 59	uuuuuu/vuuvuv:bi0069i006900690069i0069i	I
    //   445: bipush 15
    //   447: putstatic 91	uuuuuu/vuuvuv:b0069i0069006900690069i0069i	I
    //   450: bipush 35
    //   452: putstatic 59	uuuuuu/vuuvuv:bi0069i006900690069i0069i	I
    //   455: bipush 26
    //   457: putstatic 91	uuuuuu/vuuvuv:b0069i0069006900690069i0069i	I
    //   460: getstatic 59	uuuuuu/vuuvuv:bi0069i006900690069i0069i	I
    //   463: istore_1
    //   464: ldc 2
    //   466: ldc_w 485
    //   469: sipush 130
    //   472: iconst_0
    //   473: invokestatic 101	xxxxxx/uxxxxx:bb00620062bb0062b0062b0062	(Ljava/lang/String;CC)Ljava/lang/String;
    //   476: iconst_0
    //   477: anewarray 69	java/lang/Class
    //   480: invokevirtual 73	java/lang/Class:getMethod	(Ljava/lang/String;[Ljava/lang/Class;)Ljava/lang/reflect/Method;
    //   483: astore 5
    //   485: aload 5
    //   487: aconst_null
    //   488: iconst_0
    //   489: anewarray 75	java/lang/Object
    //   492: invokevirtual 81	java/lang/reflect/Method:invoke	(Ljava/lang/Object;[Ljava/lang/Object;)Ljava/lang/Object;
    //   495: astore 5
    //   497: aload 5
    //   499: checkcast 83	java/lang/Integer
    //   502: invokevirtual 87	java/lang/Integer:intValue	()I
    //   505: iload_1
    //   506: iadd
    //   507: getstatic 59	uuuuuu/vuuvuv:bi0069i006900690069i0069i	I
    //   510: imul
    //   511: getstatic 89	uuuuuu/vuuvuv:bii0069006900690069i0069i	I
    //   514: irem
    //   515: getstatic 91	uuuuuu/vuuvuv:b0069i0069006900690069i0069i	I
    //   518: if_icmpeq -492 -> 26
    //   521: bipush 57
    //   523: putstatic 59	uuuuuu/vuuvuv:bi0069i006900690069i0069i	I
    //   526: ldc 2
    //   528: ldc_w 487
    //   531: sipush 178
    //   534: iconst_4
    //   535: invokestatic 101	xxxxxx/uxxxxx:bb00620062bb0062b0062b0062	(Ljava/lang/String;CC)Ljava/lang/String;
    //   538: iconst_0
    //   539: anewarray 69	java/lang/Class
    //   542: invokevirtual 73	java/lang/Class:getMethod	(Ljava/lang/String;[Ljava/lang/Class;)Ljava/lang/reflect/Method;
    //   545: astore 5
    //   547: aload 5
    //   549: aconst_null
    //   550: iconst_0
    //   551: anewarray 75	java/lang/Object
    //   554: invokevirtual 81	java/lang/reflect/Method:invoke	(Ljava/lang/Object;[Ljava/lang/Object;)Ljava/lang/Object;
    //   557: astore 5
    //   559: aload 5
    //   561: checkcast 83	java/lang/Integer
    //   564: invokevirtual 87	java/lang/Integer:intValue	()I
    //   567: putstatic 91	uuuuuu/vuuvuv:b0069i0069006900690069i0069i	I
    //   570: return
    //   571: astore 5
    //   573: aload 5
    //   575: invokevirtual 117	java/lang/reflect/InvocationTargetException:getCause	()Ljava/lang/Throwable;
    //   578: athrow
    //   579: astore 5
    //   581: aload 5
    //   583: invokevirtual 117	java/lang/reflect/InvocationTargetException:getCause	()Ljava/lang/Throwable;
    //   586: athrow
    //   587: getstatic 490	uuuuuu/vvrvrv:b00780078x00780078xxxx	Luuuuuu/vvrvrv;
    //   590: invokestatic 308	uuuuuu/rrvvrv:b0071q0071qq0071q0071q0071	(Luuuuuu/vvrvrv;)V
    //   593: goto -484 -> 109
    //   596: astore 5
    //   598: aload 5
    //   600: invokevirtual 117	java/lang/reflect/InvocationTargetException:getCause	()Ljava/lang/Throwable;
    //   603: athrow
    //   604: getstatic 493	uuuuuu/vvrvrv:bx00780078x0078xxxx	Luuuuuu/vvrvrv;
    //   607: invokestatic 308	uuuuuu/rrvvrv:b0071q0071qq0071q0071q0071	(Luuuuuu/vvrvrv;)V
    //   610: return
    //   611: astore 5
    //   613: aload 5
    //   615: invokevirtual 117	java/lang/reflect/InvocationTargetException:getCause	()Ljava/lang/Throwable;
    //   618: athrow
    //   619: astore 5
    //   621: aload 5
    //   623: invokevirtual 117	java/lang/reflect/InvocationTargetException:getCause	()Ljava/lang/Throwable;
    //   626: athrow
    //   627: astore 5
    //   629: aload 5
    //   631: invokevirtual 117	java/lang/reflect/InvocationTargetException:getCause	()Ljava/lang/Throwable;
    //   634: athrow
    //   635: astore 5
    //   637: aload 5
    //   639: invokevirtual 117	java/lang/reflect/InvocationTargetException:getCause	()Ljava/lang/Throwable;
    //   642: athrow
    //   643: astore 5
    //   645: aload 5
    //   647: invokevirtual 117	java/lang/reflect/InvocationTargetException:getCause	()Ljava/lang/Throwable;
    //   650: athrow
    // Local variable table:
    //   start	length	slot	name	signature
    //   0	651	0	this	vuuvuv
    //   123	384	1	i	int
    //   274	46	2	j	int
    //   278	44	3	k	int
    //   282	43	4	m	int
    //   54	506	5	localObject	Object
    //   571	3	5	localInvocationTargetException1	InvocationTargetException
    //   579	3	5	localInvocationTargetException2	InvocationTargetException
    //   596	3	5	localInvocationTargetException3	InvocationTargetException
    //   611	3	5	localInvocationTargetException4	InvocationTargetException
    //   619	3	5	localInvocationTargetException5	InvocationTargetException
    //   627	3	5	localInvocationTargetException6	InvocationTargetException
    //   635	3	5	localInvocationTargetException7	InvocationTargetException
    //   643	3	5	localInvocationTargetException8	InvocationTargetException
    //   85	161	6	localMethod	Method
    // Exception table:
    //   from	to	target	type
    //   87	103	571	java/lang/reflect/InvocationTargetException
    //   363	375	579	java/lang/reflect/InvocationTargetException
    //   245	261	596	java/lang/reflect/InvocationTargetException
    //   148	160	611	java/lang/reflect/InvocationTargetException
    //   547	559	619	java/lang/reflect/InvocationTargetException
    //   305	317	627	java/lang/reflect/InvocationTargetException
    //   485	497	635	java/lang/reflect/InvocationTargetException
    //   422	434	643	java/lang/reflect/InvocationTargetException
  }
  
  /* Error */
  public void ba006100610061aaa00610061a(onnnno paramOnnnno)
  {
    // Byte code:
    //   0: getstatic 59	uuuuuu/vuuvuv:bi0069i006900690069i0069i	I
    //   3: istore_2
    //   4: getstatic 103	uuuuuu/vuuvuv:b00690069i006900690069i0069i	I
    //   7: istore_3
    //   8: getstatic 59	uuuuuu/vuuvuv:bi0069i006900690069i0069i	I
    //   11: istore 4
    //   13: getstatic 89	uuuuuu/vuuvuv:bii0069006900690069i0069i	I
    //   16: istore 5
    //   18: getstatic 59	uuuuuu/vuuvuv:bi0069i006900690069i0069i	I
    //   21: istore 6
    //   23: getstatic 103	uuuuuu/vuuvuv:b00690069i006900690069i0069i	I
    //   26: istore 7
    //   28: getstatic 59	uuuuuu/vuuvuv:bi0069i006900690069i0069i	I
    //   31: istore 8
    //   33: ldc 2
    //   35: ldc_w 497
    //   38: bipush 125
    //   40: iconst_0
    //   41: invokestatic 101	xxxxxx/uxxxxx:bb00620062bb0062b0062b0062	(Ljava/lang/String;CC)Ljava/lang/String;
    //   44: iconst_0
    //   45: anewarray 69	java/lang/Class
    //   48: invokevirtual 73	java/lang/Class:getMethod	(Ljava/lang/String;[Ljava/lang/Class;)Ljava/lang/reflect/Method;
    //   51: astore 9
    //   53: aload 9
    //   55: aconst_null
    //   56: iconst_0
    //   57: anewarray 75	java/lang/Object
    //   60: invokevirtual 81	java/lang/reflect/Method:invoke	(Ljava/lang/Object;[Ljava/lang/Object;)Ljava/lang/Object;
    //   63: astore 9
    //   65: iload 8
    //   67: iload 6
    //   69: iload 7
    //   71: iadd
    //   72: imul
    //   73: aload 9
    //   75: checkcast 83	java/lang/Integer
    //   78: invokevirtual 87	java/lang/Integer:intValue	()I
    //   81: irem
    //   82: getstatic 91	uuuuuu/vuuvuv:b0069i0069006900690069i0069i	I
    //   85: if_icmpeq +136 -> 221
    //   88: ldc 2
    //   90: ldc_w 499
    //   93: bipush 68
    //   95: iconst_4
    //   96: invokestatic 101	xxxxxx/uxxxxx:bb00620062bb0062b0062b0062	(Ljava/lang/String;CC)Ljava/lang/String;
    //   99: iconst_0
    //   100: anewarray 69	java/lang/Class
    //   103: invokevirtual 73	java/lang/Class:getMethod	(Ljava/lang/String;[Ljava/lang/Class;)Ljava/lang/reflect/Method;
    //   106: astore 9
    //   108: aload 9
    //   110: aconst_null
    //   111: iconst_0
    //   112: anewarray 75	java/lang/Object
    //   115: invokevirtual 81	java/lang/reflect/Method:invoke	(Ljava/lang/Object;[Ljava/lang/Object;)Ljava/lang/Object;
    //   118: astore 9
    //   120: aload 9
    //   122: checkcast 83	java/lang/Integer
    //   125: invokevirtual 87	java/lang/Integer:intValue	()I
    //   128: putstatic 59	uuuuuu/vuuvuv:bi0069i006900690069i0069i	I
    //   131: getstatic 59	uuuuuu/vuuvuv:bi0069i006900690069i0069i	I
    //   134: istore 6
    //   136: iload 6
    //   138: getstatic 103	uuuuuu/vuuvuv:b00690069i006900690069i0069i	I
    //   141: iload 6
    //   143: iadd
    //   144: imul
    //   145: getstatic 89	uuuuuu/vuuvuv:bii0069006900690069i0069i	I
    //   148: irem
    //   149: tableswitch	default:+19->168, 0:+67->216
    //   168: bipush 83
    //   170: putstatic 59	uuuuuu/vuuvuv:bi0069i006900690069i0069i	I
    //   173: ldc 2
    //   175: ldc_w 501
    //   178: bipush 30
    //   180: iconst_0
    //   181: invokestatic 101	xxxxxx/uxxxxx:bb00620062bb0062b0062b0062	(Ljava/lang/String;CC)Ljava/lang/String;
    //   184: iconst_0
    //   185: anewarray 69	java/lang/Class
    //   188: invokevirtual 73	java/lang/Class:getMethod	(Ljava/lang/String;[Ljava/lang/Class;)Ljava/lang/reflect/Method;
    //   191: astore 9
    //   193: aload 9
    //   195: aconst_null
    //   196: iconst_0
    //   197: anewarray 75	java/lang/Object
    //   200: invokevirtual 81	java/lang/reflect/Method:invoke	(Ljava/lang/Object;[Ljava/lang/Object;)Ljava/lang/Object;
    //   203: astore 9
    //   205: aload 9
    //   207: checkcast 83	java/lang/Integer
    //   210: invokevirtual 87	java/lang/Integer:intValue	()I
    //   213: putstatic 91	uuuuuu/vuuvuv:b0069i0069006900690069i0069i	I
    //   216: bipush 90
    //   218: putstatic 91	uuuuuu/vuuvuv:b0069i0069006900690069i0069i	I
    //   221: iload 4
    //   223: iload_2
    //   224: iload_3
    //   225: iadd
    //   226: imul
    //   227: iload 5
    //   229: irem
    //   230: getstatic 91	uuuuuu/vuuvuv:b0069i0069006900690069i0069i	I
    //   233: if_icmpeq +161 -> 394
    //   236: bipush 52
    //   238: putstatic 59	uuuuuu/vuuvuv:bi0069i006900690069i0069i	I
    //   241: ldc 2
    //   243: ldc_w 503
    //   246: sipush 244
    //   249: iconst_1
    //   250: invokestatic 101	xxxxxx/uxxxxx:bb00620062bb0062b0062b0062	(Ljava/lang/String;CC)Ljava/lang/String;
    //   253: iconst_0
    //   254: anewarray 69	java/lang/Class
    //   257: invokevirtual 73	java/lang/Class:getMethod	(Ljava/lang/String;[Ljava/lang/Class;)Ljava/lang/reflect/Method;
    //   260: astore 9
    //   262: aload 9
    //   264: aconst_null
    //   265: iconst_0
    //   266: anewarray 75	java/lang/Object
    //   269: invokevirtual 81	java/lang/reflect/Method:invoke	(Ljava/lang/Object;[Ljava/lang/Object;)Ljava/lang/Object;
    //   272: astore 9
    //   274: aload 9
    //   276: checkcast 83	java/lang/Integer
    //   279: invokevirtual 87	java/lang/Integer:intValue	()I
    //   282: putstatic 91	uuuuuu/vuuvuv:b0069i0069006900690069i0069i	I
    //   285: getstatic 59	uuuuuu/vuuvuv:bi0069i006900690069i0069i	I
    //   288: getstatic 103	uuuuuu/vuuvuv:b00690069i006900690069i0069i	I
    //   291: iadd
    //   292: getstatic 59	uuuuuu/vuuvuv:bi0069i006900690069i0069i	I
    //   295: imul
    //   296: getstatic 89	uuuuuu/vuuvuv:bii0069006900690069i0069i	I
    //   299: irem
    //   300: getstatic 91	uuuuuu/vuuvuv:b0069i0069006900690069i0069i	I
    //   303: if_icmpeq +91 -> 394
    //   306: ldc 2
    //   308: ldc_w 505
    //   311: bipush 92
    //   313: bipush 7
    //   315: iconst_1
    //   316: invokestatic 67	xxxxxx/uxxxxx:bbbb0062b0062b0062b0062	(Ljava/lang/String;CCC)Ljava/lang/String;
    //   319: iconst_0
    //   320: anewarray 69	java/lang/Class
    //   323: invokevirtual 73	java/lang/Class:getMethod	(Ljava/lang/String;[Ljava/lang/Class;)Ljava/lang/reflect/Method;
    //   326: astore 9
    //   328: aload 9
    //   330: aconst_null
    //   331: iconst_0
    //   332: anewarray 75	java/lang/Object
    //   335: invokevirtual 81	java/lang/reflect/Method:invoke	(Ljava/lang/Object;[Ljava/lang/Object;)Ljava/lang/Object;
    //   338: astore 9
    //   340: aload 9
    //   342: checkcast 83	java/lang/Integer
    //   345: invokevirtual 87	java/lang/Integer:intValue	()I
    //   348: putstatic 59	uuuuuu/vuuvuv:bi0069i006900690069i0069i	I
    //   351: ldc 2
    //   353: ldc_w 505
    //   356: bipush 113
    //   358: iconst_5
    //   359: invokestatic 101	xxxxxx/uxxxxx:bb00620062bb0062b0062b0062	(Ljava/lang/String;CC)Ljava/lang/String;
    //   362: iconst_0
    //   363: anewarray 69	java/lang/Class
    //   366: invokevirtual 73	java/lang/Class:getMethod	(Ljava/lang/String;[Ljava/lang/Class;)Ljava/lang/reflect/Method;
    //   369: astore 9
    //   371: aload 9
    //   373: aconst_null
    //   374: iconst_0
    //   375: anewarray 75	java/lang/Object
    //   378: invokevirtual 81	java/lang/reflect/Method:invoke	(Ljava/lang/Object;[Ljava/lang/Object;)Ljava/lang/Object;
    //   381: astore 9
    //   383: aload 9
    //   385: checkcast 83	java/lang/Integer
    //   388: invokevirtual 87	java/lang/Integer:intValue	()I
    //   391: putstatic 91	uuuuuu/vuuvuv:b0069i0069006900690069i0069i	I
    //   394: aload_0
    //   395: getfield 348	uuuuuu/vuuvuv:bi00690069i00690069i0069i	Luuuuuu/ooooon;
    //   398: aload_1
    //   399: invokevirtual 509	uuuuuu/ooooon:b006B006B006Bkkk006Bkk006B	(Luuuuuu/onnnno;)I
    //   402: pop
    //   403: aload_0
    //   404: getfield 95	uuuuuu/vuuvuv:bnnnnn006E006E006En	Luuuuuu/ttssst$tsssst;
    //   407: checkcast 216	uuuuuu/uuvvuv$uvuvuv
    //   410: invokeinterface 512 1 0
    //   415: return
    //   416: astore_1
    //   417: aload_1
    //   418: invokevirtual 117	java/lang/reflect/InvocationTargetException:getCause	()Ljava/lang/Throwable;
    //   421: athrow
    //   422: astore_1
    //   423: aload_1
    //   424: invokevirtual 117	java/lang/reflect/InvocationTargetException:getCause	()Ljava/lang/Throwable;
    //   427: athrow
    //   428: astore_1
    //   429: aload_1
    //   430: invokevirtual 117	java/lang/reflect/InvocationTargetException:getCause	()Ljava/lang/Throwable;
    //   433: athrow
    //   434: astore_1
    //   435: aload_1
    //   436: invokevirtual 117	java/lang/reflect/InvocationTargetException:getCause	()Ljava/lang/Throwable;
    //   439: athrow
    //   440: astore_1
    //   441: aload_1
    //   442: invokevirtual 117	java/lang/reflect/InvocationTargetException:getCause	()Ljava/lang/Throwable;
    //   445: athrow
    //   446: astore_1
    //   447: aload_1
    //   448: invokevirtual 117	java/lang/reflect/InvocationTargetException:getCause	()Ljava/lang/Throwable;
    //   451: athrow
    // Local variable table:
    //   start	length	slot	name	signature
    //   0	452	0	this	vuuvuv
    //   0	452	1	paramOnnnno	onnnno
    //   3	223	2	i	int
    //   7	219	3	j	int
    //   11	216	4	k	int
    //   16	214	5	m	int
    //   21	124	6	n	int
    //   26	46	7	i1	int
    //   31	42	8	i2	int
    //   51	333	9	localObject	Object
    // Exception table:
    //   from	to	target	type
    //   328	340	416	java/lang/reflect/InvocationTargetException
    //   371	383	422	java/lang/reflect/InvocationTargetException
    //   262	274	428	java/lang/reflect/InvocationTargetException
    //   53	65	434	java/lang/reflect/InvocationTargetException
    //   108	120	440	java/lang/reflect/InvocationTargetException
    //   193	205	446	java/lang/reflect/InvocationTargetException
  }
  
  /* Error */
  public void ba00610061a006100610061a0061a(Context paramContext)
  {
    // Byte code:
    //   0: ldc 2
    //   2: ldc_w 515
    //   5: bipush 46
    //   7: bipush 111
    //   9: iconst_2
    //   10: invokestatic 67	xxxxxx/uxxxxx:bbbb0062b0062b0062b0062	(Ljava/lang/String;CCC)Ljava/lang/String;
    //   13: iconst_1
    //   14: anewarray 69	java/lang/Class
    //   17: dup
    //   18: iconst_0
    //   19: ldc_w 452
    //   22: aastore
    //   23: invokevirtual 73	java/lang/Class:getMethod	(Ljava/lang/String;[Ljava/lang/Class;)Ljava/lang/reflect/Method;
    //   26: astore 5
    //   28: aload 5
    //   30: aload_0
    //   31: iconst_1
    //   32: anewarray 75	java/lang/Object
    //   35: dup
    //   36: iconst_0
    //   37: aload_1
    //   38: aastore
    //   39: invokevirtual 81	java/lang/reflect/Method:invoke	(Ljava/lang/Object;[Ljava/lang/Object;)Ljava/lang/Object;
    //   42: pop
    //   43: aload_0
    //   44: invokespecial 518	uuuuuu/qppppp:ba006100610061a0061aa0061a	()V
    //   47: getstatic 59	uuuuuu/vuuvuv:bi0069i006900690069i0069i	I
    //   50: istore_2
    //   51: getstatic 59	uuuuuu/vuuvuv:bi0069i006900690069i0069i	I
    //   54: getstatic 103	uuuuuu/vuuvuv:b00690069i006900690069i0069i	I
    //   57: iadd
    //   58: getstatic 59	uuuuuu/vuuvuv:bi0069i006900690069i0069i	I
    //   61: imul
    //   62: getstatic 89	uuuuuu/vuuvuv:bii0069006900690069i0069i	I
    //   65: irem
    //   66: getstatic 91	uuuuuu/vuuvuv:b0069i0069006900690069i0069i	I
    //   69: if_icmpeq +239 -> 308
    //   72: bipush 81
    //   74: putstatic 59	uuuuuu/vuuvuv:bi0069i006900690069i0069i	I
    //   77: ldc 2
    //   79: ldc_w 520
    //   82: sipush 155
    //   85: bipush 83
    //   87: iconst_0
    //   88: invokestatic 67	xxxxxx/uxxxxx:bbbb0062b0062b0062b0062	(Ljava/lang/String;CCC)Ljava/lang/String;
    //   91: iconst_0
    //   92: anewarray 69	java/lang/Class
    //   95: invokevirtual 73	java/lang/Class:getMethod	(Ljava/lang/String;[Ljava/lang/Class;)Ljava/lang/reflect/Method;
    //   98: astore_1
    //   99: aload_1
    //   100: aconst_null
    //   101: iconst_0
    //   102: anewarray 75	java/lang/Object
    //   105: invokevirtual 81	java/lang/reflect/Method:invoke	(Ljava/lang/Object;[Ljava/lang/Object;)Ljava/lang/Object;
    //   108: astore_1
    //   109: aload_1
    //   110: checkcast 83	java/lang/Integer
    //   113: invokevirtual 87	java/lang/Integer:intValue	()I
    //   116: putstatic 91	uuuuuu/vuuvuv:b0069i0069006900690069i0069i	I
    //   119: ldc 2
    //   121: ldc_w 522
    //   124: sipush 132
    //   127: iconst_5
    //   128: invokestatic 101	xxxxxx/uxxxxx:bb00620062bb0062b0062b0062	(Ljava/lang/String;CC)Ljava/lang/String;
    //   131: iconst_0
    //   132: anewarray 69	java/lang/Class
    //   135: invokevirtual 73	java/lang/Class:getMethod	(Ljava/lang/String;[Ljava/lang/Class;)Ljava/lang/reflect/Method;
    //   138: astore_1
    //   139: aload_1
    //   140: aconst_null
    //   141: iconst_0
    //   142: anewarray 75	java/lang/Object
    //   145: invokevirtual 81	java/lang/reflect/Method:invoke	(Ljava/lang/Object;[Ljava/lang/Object;)Ljava/lang/Object;
    //   148: astore_1
    //   149: aload_1
    //   150: checkcast 83	java/lang/Integer
    //   153: invokevirtual 87	java/lang/Integer:intValue	()I
    //   156: istore_3
    //   157: getstatic 59	uuuuuu/vuuvuv:bi0069i006900690069i0069i	I
    //   160: istore 4
    //   162: iload 4
    //   164: getstatic 103	uuuuuu/vuuvuv:b00690069i006900690069i0069i	I
    //   167: iload 4
    //   169: iadd
    //   170: imul
    //   171: getstatic 89	uuuuuu/vuuvuv:bii0069006900690069i0069i	I
    //   174: irem
    //   175: tableswitch	default:+17->192, 0:+61->236
    //   192: ldc 2
    //   194: ldc_w 524
    //   197: bipush 59
    //   199: iconst_4
    //   200: invokestatic 101	xxxxxx/uxxxxx:bb00620062bb0062b0062b0062	(Ljava/lang/String;CC)Ljava/lang/String;
    //   203: iconst_0
    //   204: anewarray 69	java/lang/Class
    //   207: invokevirtual 73	java/lang/Class:getMethod	(Ljava/lang/String;[Ljava/lang/Class;)Ljava/lang/reflect/Method;
    //   210: astore_1
    //   211: aload_1
    //   212: aconst_null
    //   213: iconst_0
    //   214: anewarray 75	java/lang/Object
    //   217: invokevirtual 81	java/lang/reflect/Method:invoke	(Ljava/lang/Object;[Ljava/lang/Object;)Ljava/lang/Object;
    //   220: astore_1
    //   221: aload_1
    //   222: checkcast 83	java/lang/Integer
    //   225: invokevirtual 87	java/lang/Integer:intValue	()I
    //   228: putstatic 59	uuuuuu/vuuvuv:bi0069i006900690069i0069i	I
    //   231: bipush 80
    //   233: putstatic 91	uuuuuu/vuuvuv:b0069i0069006900690069i0069i	I
    //   236: getstatic 103	uuuuuu/vuuvuv:b00690069i006900690069i0069i	I
    //   239: iload_3
    //   240: iadd
    //   241: iload_3
    //   242: imul
    //   243: getstatic 89	uuuuuu/vuuvuv:bii0069006900690069i0069i	I
    //   246: irem
    //   247: tableswitch	default:+17->264, 0:+61->308
    //   264: ldc 2
    //   266: ldc_w 526
    //   269: bipush 11
    //   271: iconst_5
    //   272: invokestatic 101	xxxxxx/uxxxxx:bb00620062bb0062b0062b0062	(Ljava/lang/String;CC)Ljava/lang/String;
    //   275: iconst_0
    //   276: anewarray 69	java/lang/Class
    //   279: invokevirtual 73	java/lang/Class:getMethod	(Ljava/lang/String;[Ljava/lang/Class;)Ljava/lang/reflect/Method;
    //   282: astore_1
    //   283: aload_1
    //   284: aconst_null
    //   285: iconst_0
    //   286: anewarray 75	java/lang/Object
    //   289: invokevirtual 81	java/lang/reflect/Method:invoke	(Ljava/lang/Object;[Ljava/lang/Object;)Ljava/lang/Object;
    //   292: astore_1
    //   293: aload_1
    //   294: checkcast 83	java/lang/Integer
    //   297: invokevirtual 87	java/lang/Integer:intValue	()I
    //   300: putstatic 59	uuuuuu/vuuvuv:bi0069i006900690069i0069i	I
    //   303: bipush 87
    //   305: putstatic 91	uuuuuu/vuuvuv:b0069i0069006900690069i0069i	I
    //   308: getstatic 103	uuuuuu/vuuvuv:b00690069i006900690069i0069i	I
    //   311: iload_2
    //   312: iadd
    //   313: getstatic 59	uuuuuu/vuuvuv:bi0069i006900690069i0069i	I
    //   316: imul
    //   317: getstatic 89	uuuuuu/vuuvuv:bii0069006900690069i0069i	I
    //   320: irem
    //   321: getstatic 91	uuuuuu/vuuvuv:b0069i0069006900690069i0069i	I
    //   324: if_icmpeq +12 -> 336
    //   327: bipush 82
    //   329: putstatic 59	uuuuuu/vuuvuv:bi0069i006900690069i0069i	I
    //   332: iconst_2
    //   333: putstatic 91	uuuuuu/vuuvuv:b0069i0069006900690069i0069i	I
    //   336: return
    //   337: astore_1
    //   338: aload_1
    //   339: invokevirtual 117	java/lang/reflect/InvocationTargetException:getCause	()Ljava/lang/Throwable;
    //   342: athrow
    //   343: astore_1
    //   344: aload_1
    //   345: invokevirtual 117	java/lang/reflect/InvocationTargetException:getCause	()Ljava/lang/Throwable;
    //   348: athrow
    //   349: astore_1
    //   350: aload_1
    //   351: invokevirtual 117	java/lang/reflect/InvocationTargetException:getCause	()Ljava/lang/Throwable;
    //   354: athrow
    //   355: astore_1
    //   356: aload_1
    //   357: invokevirtual 117	java/lang/reflect/InvocationTargetException:getCause	()Ljava/lang/Throwable;
    //   360: athrow
    //   361: astore_1
    //   362: aload_1
    //   363: invokevirtual 117	java/lang/reflect/InvocationTargetException:getCause	()Ljava/lang/Throwable;
    //   366: athrow
    // Local variable table:
    //   start	length	slot	name	signature
    //   0	367	0	this	vuuvuv
    //   0	367	1	paramContext	Context
    //   50	263	2	i	int
    //   156	87	3	j	int
    //   160	11	4	k	int
    //   26	3	5	localMethod	Method
    // Exception table:
    //   from	to	target	type
    //   28	43	337	java/lang/reflect/InvocationTargetException
    //   283	293	343	java/lang/reflect/InvocationTargetException
    //   99	109	349	java/lang/reflect/InvocationTargetException
    //   139	149	355	java/lang/reflect/InvocationTargetException
    //   211	221	361	java/lang/reflect/InvocationTargetException
  }
  
  /* Error */
  public UserReviewTile ba0061a0061aaa00610061a()
  {
    // Byte code:
    //   0: new 530	com/db/pwcc/dbmobile/user_review/tiles/UserReviewTile
    //   3: dup
    //   4: bipush 50
    //   6: invokespecial 532	com/db/pwcc/dbmobile/user_review/tiles/UserReviewTile:<init>	(I)V
    //   9: astore 5
    //   11: getstatic 59	uuuuuu/vuuvuv:bi0069i006900690069i0069i	I
    //   14: istore_1
    //   15: iload_1
    //   16: getstatic 103	uuuuuu/vuuvuv:b00690069i006900690069i0069i	I
    //   19: iload_1
    //   20: iadd
    //   21: imul
    //   22: getstatic 89	uuuuuu/vuuvuv:bii0069006900690069i0069i	I
    //   25: irem
    //   26: tableswitch	default:+18->44, 0:+108->134
    //   44: ldc 2
    //   46: ldc_w 534
    //   49: sipush 175
    //   52: bipush 114
    //   54: iconst_1
    //   55: invokestatic 67	xxxxxx/uxxxxx:bbbb0062b0062b0062b0062	(Ljava/lang/String;CCC)Ljava/lang/String;
    //   58: iconst_0
    //   59: anewarray 69	java/lang/Class
    //   62: invokevirtual 73	java/lang/Class:getMethod	(Ljava/lang/String;[Ljava/lang/Class;)Ljava/lang/reflect/Method;
    //   65: astore 6
    //   67: aload 6
    //   69: aconst_null
    //   70: iconst_0
    //   71: anewarray 75	java/lang/Object
    //   74: invokevirtual 81	java/lang/reflect/Method:invoke	(Ljava/lang/Object;[Ljava/lang/Object;)Ljava/lang/Object;
    //   77: astore 6
    //   79: aload 6
    //   81: checkcast 83	java/lang/Integer
    //   84: invokevirtual 87	java/lang/Integer:intValue	()I
    //   87: putstatic 59	uuuuuu/vuuvuv:bi0069i006900690069i0069i	I
    //   90: ldc 2
    //   92: ldc_w 389
    //   95: sipush 210
    //   98: iconst_2
    //   99: invokestatic 101	xxxxxx/uxxxxx:bb00620062bb0062b0062b0062	(Ljava/lang/String;CC)Ljava/lang/String;
    //   102: iconst_0
    //   103: anewarray 69	java/lang/Class
    //   106: invokevirtual 73	java/lang/Class:getMethod	(Ljava/lang/String;[Ljava/lang/Class;)Ljava/lang/reflect/Method;
    //   109: astore 6
    //   111: aload 6
    //   113: aconst_null
    //   114: iconst_0
    //   115: anewarray 75	java/lang/Object
    //   118: invokevirtual 81	java/lang/reflect/Method:invoke	(Ljava/lang/Object;[Ljava/lang/Object;)Ljava/lang/Object;
    //   121: astore 6
    //   123: aload 6
    //   125: checkcast 83	java/lang/Integer
    //   128: invokevirtual 87	java/lang/Integer:intValue	()I
    //   131: putstatic 91	uuuuuu/vuuvuv:b0069i0069006900690069i0069i	I
    //   134: getstatic 59	uuuuuu/vuuvuv:bi0069i006900690069i0069i	I
    //   137: getstatic 103	uuuuuu/vuuvuv:b00690069i006900690069i0069i	I
    //   140: iadd
    //   141: getstatic 59	uuuuuu/vuuvuv:bi0069i006900690069i0069i	I
    //   144: imul
    //   145: getstatic 89	uuuuuu/vuuvuv:bii0069006900690069i0069i	I
    //   148: irem
    //   149: getstatic 91	uuuuuu/vuuvuv:b0069i0069006900690069i0069i	I
    //   152: if_icmpeq +214 -> 366
    //   155: getstatic 59	uuuuuu/vuuvuv:bi0069i006900690069i0069i	I
    //   158: istore_1
    //   159: getstatic 103	uuuuuu/vuuvuv:b00690069i006900690069i0069i	I
    //   162: istore_2
    //   163: getstatic 59	uuuuuu/vuuvuv:bi0069i006900690069i0069i	I
    //   166: istore_3
    //   167: getstatic 89	uuuuuu/vuuvuv:bii0069006900690069i0069i	I
    //   170: istore 4
    //   172: ldc 2
    //   174: ldc_w 536
    //   177: sipush 134
    //   180: iconst_0
    //   181: invokestatic 101	xxxxxx/uxxxxx:bb00620062bb0062b0062b0062	(Ljava/lang/String;CC)Ljava/lang/String;
    //   184: iconst_0
    //   185: anewarray 69	java/lang/Class
    //   188: invokevirtual 73	java/lang/Class:getMethod	(Ljava/lang/String;[Ljava/lang/Class;)Ljava/lang/reflect/Method;
    //   191: astore 6
    //   193: aload 6
    //   195: aconst_null
    //   196: iconst_0
    //   197: anewarray 75	java/lang/Object
    //   200: invokevirtual 81	java/lang/reflect/Method:invoke	(Ljava/lang/Object;[Ljava/lang/Object;)Ljava/lang/Object;
    //   203: astore 6
    //   205: iload_1
    //   206: iload_2
    //   207: iadd
    //   208: iload_3
    //   209: imul
    //   210: iload 4
    //   212: irem
    //   213: aload 6
    //   215: checkcast 83	java/lang/Integer
    //   218: invokevirtual 87	java/lang/Integer:intValue	()I
    //   221: if_icmpeq +52 -> 273
    //   224: bipush 86
    //   226: putstatic 59	uuuuuu/vuuvuv:bi0069i006900690069i0069i	I
    //   229: ldc 2
    //   231: ldc_w 538
    //   234: sipush 237
    //   237: iconst_3
    //   238: invokestatic 101	xxxxxx/uxxxxx:bb00620062bb0062b0062b0062	(Ljava/lang/String;CC)Ljava/lang/String;
    //   241: iconst_0
    //   242: anewarray 69	java/lang/Class
    //   245: invokevirtual 73	java/lang/Class:getMethod	(Ljava/lang/String;[Ljava/lang/Class;)Ljava/lang/reflect/Method;
    //   248: astore 6
    //   250: aload 6
    //   252: aconst_null
    //   253: iconst_0
    //   254: anewarray 75	java/lang/Object
    //   257: invokevirtual 81	java/lang/reflect/Method:invoke	(Ljava/lang/Object;[Ljava/lang/Object;)Ljava/lang/Object;
    //   260: astore 6
    //   262: aload 6
    //   264: checkcast 83	java/lang/Integer
    //   267: invokevirtual 87	java/lang/Integer:intValue	()I
    //   270: putstatic 91	uuuuuu/vuuvuv:b0069i0069006900690069i0069i	I
    //   273: bipush 94
    //   275: putstatic 59	uuuuuu/vuuvuv:bi0069i006900690069i0069i	I
    //   278: bipush 39
    //   280: putstatic 91	uuuuuu/vuuvuv:b0069i0069006900690069i0069i	I
    //   283: getstatic 59	uuuuuu/vuuvuv:bi0069i006900690069i0069i	I
    //   286: istore_1
    //   287: iload_1
    //   288: getstatic 103	uuuuuu/vuuvuv:b00690069i006900690069i0069i	I
    //   291: iload_1
    //   292: iadd
    //   293: imul
    //   294: getstatic 89	uuuuuu/vuuvuv:bii0069006900690069i0069i	I
    //   297: irem
    //   298: tableswitch	default:+18->316, 0:+68->366
    //   316: ldc 2
    //   318: ldc_w 540
    //   321: bipush 116
    //   323: bipush 48
    //   325: iconst_0
    //   326: invokestatic 67	xxxxxx/uxxxxx:bbbb0062b0062b0062b0062	(Ljava/lang/String;CCC)Ljava/lang/String;
    //   329: iconst_0
    //   330: anewarray 69	java/lang/Class
    //   333: invokevirtual 73	java/lang/Class:getMethod	(Ljava/lang/String;[Ljava/lang/Class;)Ljava/lang/reflect/Method;
    //   336: astore 6
    //   338: aload 6
    //   340: aconst_null
    //   341: iconst_0
    //   342: anewarray 75	java/lang/Object
    //   345: invokevirtual 81	java/lang/reflect/Method:invoke	(Ljava/lang/Object;[Ljava/lang/Object;)Ljava/lang/Object;
    //   348: astore 6
    //   350: aload 6
    //   352: checkcast 83	java/lang/Integer
    //   355: invokevirtual 87	java/lang/Integer:intValue	()I
    //   358: putstatic 59	uuuuuu/vuuvuv:bi0069i006900690069i0069i	I
    //   361: bipush 61
    //   363: putstatic 91	uuuuuu/vuuvuv:b0069i0069006900690069i0069i	I
    //   366: aload 5
    //   368: new 9	uuuuuu/vuuvuv$1
    //   371: dup
    //   372: aload_0
    //   373: aload 5
    //   375: invokespecial 543	uuuuuu/vuuvuv$1:<init>	(Luuuuuu/vuuvuv;Lcom/db/pwcc/dbmobile/user_review/tiles/UserReviewTile;)V
    //   378: invokevirtual 547	com/db/pwcc/dbmobile/user_review/tiles/UserReviewTile:setTileListener	(Lcom/db/pwcc/dbmobile/user_review/tiles/UserReviewTile$pppphh;)V
    //   381: aload 5
    //   383: areturn
    //   384: astore 5
    //   386: aload 5
    //   388: invokevirtual 117	java/lang/reflect/InvocationTargetException:getCause	()Ljava/lang/Throwable;
    //   391: athrow
    //   392: astore 5
    //   394: aload 5
    //   396: invokevirtual 117	java/lang/reflect/InvocationTargetException:getCause	()Ljava/lang/Throwable;
    //   399: athrow
    //   400: astore 5
    //   402: aload 5
    //   404: invokevirtual 117	java/lang/reflect/InvocationTargetException:getCause	()Ljava/lang/Throwable;
    //   407: athrow
    //   408: astore 5
    //   410: aload 5
    //   412: invokevirtual 117	java/lang/reflect/InvocationTargetException:getCause	()Ljava/lang/Throwable;
    //   415: athrow
    //   416: astore 5
    //   418: aload 5
    //   420: invokevirtual 117	java/lang/reflect/InvocationTargetException:getCause	()Ljava/lang/Throwable;
    //   423: athrow
    // Local variable table:
    //   start	length	slot	name	signature
    //   0	424	0	this	vuuvuv
    //   14	280	1	i	int
    //   162	46	2	j	int
    //   166	44	3	k	int
    //   170	43	4	m	int
    //   9	373	5	localUserReviewTile	UserReviewTile
    //   384	3	5	localInvocationTargetException1	InvocationTargetException
    //   392	3	5	localInvocationTargetException2	InvocationTargetException
    //   400	3	5	localInvocationTargetException3	InvocationTargetException
    //   408	3	5	localInvocationTargetException4	InvocationTargetException
    //   416	3	5	localInvocationTargetException5	InvocationTargetException
    //   65	286	6	localObject	Object
    // Exception table:
    //   from	to	target	type
    //   67	79	384	java/lang/reflect/InvocationTargetException
    //   111	123	392	java/lang/reflect/InvocationTargetException
    //   193	205	400	java/lang/reflect/InvocationTargetException
    //   338	350	408	java/lang/reflect/InvocationTargetException
    //   250	262	416	java/lang/reflect/InvocationTargetException
  }
  
  /* Error */
  public void ba0061aa006100610061a0061a(Context paramContext)
  {
    // Byte code:
    //   0: aload_1
    //   1: invokestatic 554	uuuuuu/ggyggg:b00610061aaa0061a006100610061	(Landroid/content/Context;)Luuuuuu/ygyggg;
    //   4: aload_0
    //   5: invokeinterface 560 2 0
    //   10: getstatic 59	uuuuuu/vuuvuv:bi0069i006900690069i0069i	I
    //   13: getstatic 103	uuuuuu/vuuvuv:b00690069i006900690069i0069i	I
    //   16: iadd
    //   17: getstatic 59	uuuuuu/vuuvuv:bi0069i006900690069i0069i	I
    //   20: imul
    //   21: getstatic 89	uuuuuu/vuuvuv:bii0069006900690069i0069i	I
    //   24: irem
    //   25: getstatic 91	uuuuuu/vuuvuv:b0069i0069006900690069i0069i	I
    //   28: if_icmpeq +252 -> 280
    //   31: getstatic 59	uuuuuu/vuuvuv:bi0069i006900690069i0069i	I
    //   34: istore_2
    //   35: getstatic 103	uuuuuu/vuuvuv:b00690069i006900690069i0069i	I
    //   38: istore_3
    //   39: getstatic 59	uuuuuu/vuuvuv:bi0069i006900690069i0069i	I
    //   42: istore 4
    //   44: ldc 2
    //   46: ldc_w 562
    //   49: iconst_5
    //   50: sipush 130
    //   53: iconst_2
    //   54: invokestatic 67	xxxxxx/uxxxxx:bbbb0062b0062b0062b0062	(Ljava/lang/String;CCC)Ljava/lang/String;
    //   57: iconst_0
    //   58: anewarray 69	java/lang/Class
    //   61: invokevirtual 73	java/lang/Class:getMethod	(Ljava/lang/String;[Ljava/lang/Class;)Ljava/lang/reflect/Method;
    //   64: astore 5
    //   66: aload 5
    //   68: aconst_null
    //   69: iconst_0
    //   70: anewarray 75	java/lang/Object
    //   73: invokevirtual 81	java/lang/reflect/Method:invoke	(Ljava/lang/Object;[Ljava/lang/Object;)Ljava/lang/Object;
    //   76: astore 5
    //   78: aload 5
    //   80: checkcast 83	java/lang/Integer
    //   83: invokevirtual 87	java/lang/Integer:intValue	()I
    //   86: iload 4
    //   88: iadd
    //   89: getstatic 59	uuuuuu/vuuvuv:bi0069i006900690069i0069i	I
    //   92: imul
    //   93: getstatic 89	uuuuuu/vuuvuv:bii0069006900690069i0069i	I
    //   96: irem
    //   97: getstatic 91	uuuuuu/vuuvuv:b0069i0069006900690069i0069i	I
    //   100: if_icmpeq +53 -> 153
    //   103: ldc 2
    //   105: ldc_w 564
    //   108: bipush 54
    //   110: bipush 103
    //   112: iconst_1
    //   113: invokestatic 67	xxxxxx/uxxxxx:bbbb0062b0062b0062b0062	(Ljava/lang/String;CCC)Ljava/lang/String;
    //   116: iconst_0
    //   117: anewarray 69	java/lang/Class
    //   120: invokevirtual 73	java/lang/Class:getMethod	(Ljava/lang/String;[Ljava/lang/Class;)Ljava/lang/reflect/Method;
    //   123: astore 5
    //   125: aload 5
    //   127: aconst_null
    //   128: iconst_0
    //   129: anewarray 75	java/lang/Object
    //   132: invokevirtual 81	java/lang/reflect/Method:invoke	(Ljava/lang/Object;[Ljava/lang/Object;)Ljava/lang/Object;
    //   135: astore 5
    //   137: aload 5
    //   139: checkcast 83	java/lang/Integer
    //   142: invokevirtual 87	java/lang/Integer:intValue	()I
    //   145: putstatic 59	uuuuuu/vuuvuv:bi0069i006900690069i0069i	I
    //   148: bipush 47
    //   150: putstatic 91	uuuuuu/vuuvuv:b0069i0069006900690069i0069i	I
    //   153: iload_2
    //   154: iload_2
    //   155: iload_3
    //   156: iadd
    //   157: imul
    //   158: getstatic 89	uuuuuu/vuuvuv:bii0069006900690069i0069i	I
    //   161: irem
    //   162: tableswitch	default:+18->180, 0:+66->228
    //   180: ldc 2
    //   182: ldc_w 566
    //   185: sipush 168
    //   188: iconst_5
    //   189: invokestatic 101	xxxxxx/uxxxxx:bb00620062bb0062b0062b0062	(Ljava/lang/String;CC)Ljava/lang/String;
    //   192: iconst_0
    //   193: anewarray 69	java/lang/Class
    //   196: invokevirtual 73	java/lang/Class:getMethod	(Ljava/lang/String;[Ljava/lang/Class;)Ljava/lang/reflect/Method;
    //   199: astore 5
    //   201: aload 5
    //   203: aconst_null
    //   204: iconst_0
    //   205: anewarray 75	java/lang/Object
    //   208: invokevirtual 81	java/lang/reflect/Method:invoke	(Ljava/lang/Object;[Ljava/lang/Object;)Ljava/lang/Object;
    //   211: astore 5
    //   213: aload 5
    //   215: checkcast 83	java/lang/Integer
    //   218: invokevirtual 87	java/lang/Integer:intValue	()I
    //   221: putstatic 59	uuuuuu/vuuvuv:bi0069i006900690069i0069i	I
    //   224: iconst_1
    //   225: putstatic 91	uuuuuu/vuuvuv:b0069i0069006900690069i0069i	I
    //   228: ldc 2
    //   230: ldc_w 568
    //   233: sipush 194
    //   236: sipush 201
    //   239: iconst_1
    //   240: invokestatic 67	xxxxxx/uxxxxx:bbbb0062b0062b0062b0062	(Ljava/lang/String;CCC)Ljava/lang/String;
    //   243: iconst_0
    //   244: anewarray 69	java/lang/Class
    //   247: invokevirtual 73	java/lang/Class:getMethod	(Ljava/lang/String;[Ljava/lang/Class;)Ljava/lang/reflect/Method;
    //   250: astore 5
    //   252: aload 5
    //   254: aconst_null
    //   255: iconst_0
    //   256: anewarray 75	java/lang/Object
    //   259: invokevirtual 81	java/lang/reflect/Method:invoke	(Ljava/lang/Object;[Ljava/lang/Object;)Ljava/lang/Object;
    //   262: astore 5
    //   264: aload 5
    //   266: checkcast 83	java/lang/Integer
    //   269: invokevirtual 87	java/lang/Integer:intValue	()I
    //   272: putstatic 59	uuuuuu/vuuvuv:bi0069i006900690069i0069i	I
    //   275: bipush 50
    //   277: putstatic 91	uuuuuu/vuuvuv:b0069i0069006900690069i0069i	I
    //   280: aload_0
    //   281: invokestatic 572	uuuuuu/ooooon:bk006Bkkkk006Bkk006B	()Luuuuuu/ooooon;
    //   284: putfield 348	uuuuuu/vuuvuv:bi00690069i00690069i0069i	Luuuuuu/ooooon;
    //   287: aload_0
    //   288: getfield 348	uuuuuu/vuuvuv:bi00690069i00690069i0069i	Luuuuuu/ooooon;
    //   291: invokevirtual 575	uuuuuu/ooooon:bkkkkkk006Bkk006B	()V
    //   294: aload_0
    //   295: new 292	uuuuuu/uuvuuv
    //   298: dup
    //   299: aload_0
    //   300: getfield 348	uuuuuu/vuuvuv:bi00690069i00690069i0069i	Luuuuuu/ooooon;
    //   303: invokespecial 578	uuuuuu/uuvuuv:<init>	(Luuuuuu/ooooon;)V
    //   306: putfield 287	uuuuuu/vuuvuv:b0069i0069i00690069i0069i	Luuuuuu/uuvuuv;
    //   309: aload_0
    //   310: getfield 287	uuuuuu/vuuvuv:b0069i0069i00690069i0069i	Luuuuuu/uuvuuv;
    //   313: astore 5
    //   315: getstatic 59	uuuuuu/vuuvuv:bi0069i006900690069i0069i	I
    //   318: getstatic 103	uuuuuu/vuuvuv:b00690069i006900690069i0069i	I
    //   321: iadd
    //   322: getstatic 59	uuuuuu/vuuvuv:bi0069i006900690069i0069i	I
    //   325: imul
    //   326: getstatic 89	uuuuuu/vuuvuv:bii0069006900690069i0069i	I
    //   329: irem
    //   330: getstatic 91	uuuuuu/vuuvuv:b0069i0069006900690069i0069i	I
    //   333: if_icmpeq +54 -> 387
    //   336: bipush 11
    //   338: putstatic 59	uuuuuu/vuuvuv:bi0069i006900690069i0069i	I
    //   341: ldc 2
    //   343: ldc_w 580
    //   346: sipush 200
    //   349: bipush 86
    //   351: iconst_3
    //   352: invokestatic 67	xxxxxx/uxxxxx:bbbb0062b0062b0062b0062	(Ljava/lang/String;CCC)Ljava/lang/String;
    //   355: iconst_0
    //   356: anewarray 69	java/lang/Class
    //   359: invokevirtual 73	java/lang/Class:getMethod	(Ljava/lang/String;[Ljava/lang/Class;)Ljava/lang/reflect/Method;
    //   362: astore 6
    //   364: aload 6
    //   366: aconst_null
    //   367: iconst_0
    //   368: anewarray 75	java/lang/Object
    //   371: invokevirtual 81	java/lang/reflect/Method:invoke	(Ljava/lang/Object;[Ljava/lang/Object;)Ljava/lang/Object;
    //   374: astore 6
    //   376: aload 6
    //   378: checkcast 83	java/lang/Integer
    //   381: invokevirtual 87	java/lang/Integer:intValue	()I
    //   384: putstatic 91	uuuuuu/vuuvuv:b0069i0069006900690069i0069i	I
    //   387: aload 5
    //   389: invokevirtual 583	uuuuuu/uuvuuv:b0061a0061aa00610061a0061a	()V
    //   392: ldc 2
    //   394: ldc_w 585
    //   397: bipush 10
    //   399: iconst_1
    //   400: invokestatic 101	xxxxxx/uxxxxx:bb00620062bb0062b0062b0062	(Ljava/lang/String;CC)Ljava/lang/String;
    //   403: iconst_0
    //   404: anewarray 69	java/lang/Class
    //   407: invokevirtual 73	java/lang/Class:getMethod	(Ljava/lang/String;[Ljava/lang/Class;)Ljava/lang/reflect/Method;
    //   410: astore 5
    //   412: aload 5
    //   414: aload_0
    //   415: iconst_0
    //   416: anewarray 75	java/lang/Object
    //   419: invokevirtual 81	java/lang/reflect/Method:invoke	(Ljava/lang/Object;[Ljava/lang/Object;)Ljava/lang/Object;
    //   422: pop
    //   423: ldc 2
    //   425: ldc_w 587
    //   428: bipush 63
    //   430: iconst_0
    //   431: invokestatic 101	xxxxxx/uxxxxx:bb00620062bb0062b0062b0062	(Ljava/lang/String;CC)Ljava/lang/String;
    //   434: iconst_0
    //   435: anewarray 69	java/lang/Class
    //   438: invokevirtual 73	java/lang/Class:getMethod	(Ljava/lang/String;[Ljava/lang/Class;)Ljava/lang/reflect/Method;
    //   441: astore 5
    //   443: aload 5
    //   445: aload_0
    //   446: iconst_0
    //   447: anewarray 75	java/lang/Object
    //   450: invokevirtual 81	java/lang/reflect/Method:invoke	(Ljava/lang/Object;[Ljava/lang/Object;)Ljava/lang/Object;
    //   453: pop
    //   454: aload_0
    //   455: getfield 348	uuuuuu/vuuvuv:bi00690069i00690069i0069i	Luuuuuu/ooooon;
    //   458: aload_1
    //   459: invokevirtual 590	uuuuuu/ooooon:b006Bk006Bkkk006Bkk006B	(Landroid/content/Context;)V
    //   462: aload_0
    //   463: getfield 348	uuuuuu/vuuvuv:bi00690069i00690069i0069i	Luuuuuu/ooooon;
    //   466: aload_1
    //   467: invokevirtual 593	uuuuuu/ooooon:bkk006Bkkk006Bkk006B	(Landroid/content/Context;)V
    //   470: return
    //   471: astore_1
    //   472: aload_1
    //   473: invokevirtual 117	java/lang/reflect/InvocationTargetException:getCause	()Ljava/lang/Throwable;
    //   476: athrow
    //   477: astore_1
    //   478: aload_1
    //   479: invokevirtual 117	java/lang/reflect/InvocationTargetException:getCause	()Ljava/lang/Throwable;
    //   482: athrow
    //   483: astore_1
    //   484: aload_1
    //   485: invokevirtual 117	java/lang/reflect/InvocationTargetException:getCause	()Ljava/lang/Throwable;
    //   488: athrow
    //   489: astore_1
    //   490: aload_1
    //   491: invokevirtual 117	java/lang/reflect/InvocationTargetException:getCause	()Ljava/lang/Throwable;
    //   494: athrow
    //   495: astore_1
    //   496: aload_1
    //   497: invokevirtual 117	java/lang/reflect/InvocationTargetException:getCause	()Ljava/lang/Throwable;
    //   500: athrow
    //   501: astore_1
    //   502: aload_1
    //   503: invokevirtual 117	java/lang/reflect/InvocationTargetException:getCause	()Ljava/lang/Throwable;
    //   506: athrow
    //   507: astore_1
    //   508: aload_1
    //   509: invokevirtual 117	java/lang/reflect/InvocationTargetException:getCause	()Ljava/lang/Throwable;
    //   512: athrow
    // Local variable table:
    //   start	length	slot	name	signature
    //   0	513	0	this	vuuvuv
    //   0	513	1	paramContext	Context
    //   34	124	2	i	int
    //   38	119	3	j	int
    //   42	47	4	k	int
    //   64	380	5	localObject1	Object
    //   362	15	6	localObject2	Object
    // Exception table:
    //   from	to	target	type
    //   412	423	471	java/lang/reflect/InvocationTargetException
    //   443	454	477	java/lang/reflect/InvocationTargetException
    //   66	78	483	java/lang/reflect/InvocationTargetException
    //   252	264	489	java/lang/reflect/InvocationTargetException
    //   364	376	495	java/lang/reflect/InvocationTargetException
    //   201	213	501	java/lang/reflect/InvocationTargetException
    //   125	137	507	java/lang/reflect/InvocationTargetException
  }
  
  /* Error */
  public void ba0061aa0061aa00610061a(Context paramContext)
  {
    // Byte code:
    //   0: aload_0
    //   1: getfield 596	uuuuuu/vuuvuv:bii0069i00690069i0069i	Lcom/db/pwcc/dbmobile/foundation/data/manager/broadcasting/ModelUpdatedBroadcastReceiver;
    //   4: ifnull +419 -> 423
    //   7: ldc 2
    //   9: ldc_w 598
    //   12: bipush 17
    //   14: iconst_4
    //   15: invokestatic 101	xxxxxx/uxxxxx:bb00620062bb0062b0062b0062	(Ljava/lang/String;CC)Ljava/lang/String;
    //   18: iconst_0
    //   19: anewarray 69	java/lang/Class
    //   22: invokevirtual 73	java/lang/Class:getMethod	(Ljava/lang/String;[Ljava/lang/Class;)Ljava/lang/reflect/Method;
    //   25: astore_3
    //   26: aload_3
    //   27: aconst_null
    //   28: iconst_0
    //   29: anewarray 75	java/lang/Object
    //   32: invokevirtual 81	java/lang/reflect/Method:invoke	(Ljava/lang/Object;[Ljava/lang/Object;)Ljava/lang/Object;
    //   35: astore_3
    //   36: aload_3
    //   37: checkcast 83	java/lang/Integer
    //   40: invokevirtual 87	java/lang/Integer:intValue	()I
    //   43: istore_2
    //   44: iload_2
    //   45: getstatic 103	uuuuuu/vuuvuv:b00690069i006900690069i0069i	I
    //   48: iload_2
    //   49: iadd
    //   50: imul
    //   51: getstatic 89	uuuuuu/vuuvuv:bii0069006900690069i0069i	I
    //   54: irem
    //   55: tableswitch	default:+17->72, 0:+215->270
    //   72: ldc 2
    //   74: ldc_w 410
    //   77: sipush 233
    //   80: bipush 15
    //   82: iconst_2
    //   83: invokestatic 67	xxxxxx/uxxxxx:bbbb0062b0062b0062b0062	(Ljava/lang/String;CCC)Ljava/lang/String;
    //   86: iconst_0
    //   87: anewarray 69	java/lang/Class
    //   90: invokevirtual 73	java/lang/Class:getMethod	(Ljava/lang/String;[Ljava/lang/Class;)Ljava/lang/reflect/Method;
    //   93: astore_3
    //   94: aload_3
    //   95: aconst_null
    //   96: iconst_0
    //   97: anewarray 75	java/lang/Object
    //   100: invokevirtual 81	java/lang/reflect/Method:invoke	(Ljava/lang/Object;[Ljava/lang/Object;)Ljava/lang/Object;
    //   103: astore_3
    //   104: aload_3
    //   105: checkcast 83	java/lang/Integer
    //   108: invokevirtual 87	java/lang/Integer:intValue	()I
    //   111: istore_2
    //   112: ldc 2
    //   114: ldc_w 600
    //   117: sipush 184
    //   120: sipush 253
    //   123: iconst_1
    //   124: invokestatic 67	xxxxxx/uxxxxx:bbbb0062b0062b0062b0062	(Ljava/lang/String;CCC)Ljava/lang/String;
    //   127: iconst_0
    //   128: anewarray 69	java/lang/Class
    //   131: invokevirtual 73	java/lang/Class:getMethod	(Ljava/lang/String;[Ljava/lang/Class;)Ljava/lang/reflect/Method;
    //   134: astore_3
    //   135: aload_3
    //   136: aconst_null
    //   137: iconst_0
    //   138: anewarray 75	java/lang/Object
    //   141: invokevirtual 81	java/lang/reflect/Method:invoke	(Ljava/lang/Object;[Ljava/lang/Object;)Ljava/lang/Object;
    //   144: astore_3
    //   145: aload_3
    //   146: checkcast 83	java/lang/Integer
    //   149: invokevirtual 87	java/lang/Integer:intValue	()I
    //   152: iload_2
    //   153: iadd
    //   154: iload_2
    //   155: imul
    //   156: getstatic 89	uuuuuu/vuuvuv:bii0069006900690069i0069i	I
    //   159: irem
    //   160: tableswitch	default:+20->180, 0:+64->224
    //   180: ldc 2
    //   182: ldc_w 602
    //   185: bipush 104
    //   187: iconst_2
    //   188: invokestatic 101	xxxxxx/uxxxxx:bb00620062bb0062b0062b0062	(Ljava/lang/String;CC)Ljava/lang/String;
    //   191: iconst_0
    //   192: anewarray 69	java/lang/Class
    //   195: invokevirtual 73	java/lang/Class:getMethod	(Ljava/lang/String;[Ljava/lang/Class;)Ljava/lang/reflect/Method;
    //   198: astore_3
    //   199: aload_3
    //   200: aconst_null
    //   201: iconst_0
    //   202: anewarray 75	java/lang/Object
    //   205: invokevirtual 81	java/lang/reflect/Method:invoke	(Ljava/lang/Object;[Ljava/lang/Object;)Ljava/lang/Object;
    //   208: astore_3
    //   209: aload_3
    //   210: checkcast 83	java/lang/Integer
    //   213: invokevirtual 87	java/lang/Integer:intValue	()I
    //   216: putstatic 59	uuuuuu/vuuvuv:bi0069i006900690069i0069i	I
    //   219: bipush 87
    //   221: putstatic 91	uuuuuu/vuuvuv:b0069i0069006900690069i0069i	I
    //   224: bipush 70
    //   226: putstatic 59	uuuuuu/vuuvuv:bi0069i006900690069i0069i	I
    //   229: ldc 2
    //   231: ldc -44
    //   233: bipush 80
    //   235: sipush 239
    //   238: iconst_3
    //   239: invokestatic 67	xxxxxx/uxxxxx:bbbb0062b0062b0062b0062	(Ljava/lang/String;CCC)Ljava/lang/String;
    //   242: iconst_0
    //   243: anewarray 69	java/lang/Class
    //   246: invokevirtual 73	java/lang/Class:getMethod	(Ljava/lang/String;[Ljava/lang/Class;)Ljava/lang/reflect/Method;
    //   249: astore_3
    //   250: aload_3
    //   251: aconst_null
    //   252: iconst_0
    //   253: anewarray 75	java/lang/Object
    //   256: invokevirtual 81	java/lang/reflect/Method:invoke	(Ljava/lang/Object;[Ljava/lang/Object;)Ljava/lang/Object;
    //   259: astore_3
    //   260: aload_3
    //   261: checkcast 83	java/lang/Integer
    //   264: invokevirtual 87	java/lang/Integer:intValue	()I
    //   267: putstatic 91	uuuuuu/vuuvuv:b0069i0069006900690069i0069i	I
    //   270: aload_1
    //   271: invokestatic 608	android/support/v4/content/LocalBroadcastManager:getInstance	(Landroid/content/Context;)Landroid/support/v4/content/LocalBroadcastManager;
    //   274: astore_1
    //   275: getstatic 59	uuuuuu/vuuvuv:bi0069i006900690069i0069i	I
    //   278: istore_2
    //   279: ldc 2
    //   281: ldc_w 610
    //   284: bipush 126
    //   286: sipush 180
    //   289: iconst_1
    //   290: invokestatic 67	xxxxxx/uxxxxx:bbbb0062b0062b0062b0062	(Ljava/lang/String;CCC)Ljava/lang/String;
    //   293: iconst_0
    //   294: anewarray 69	java/lang/Class
    //   297: invokevirtual 73	java/lang/Class:getMethod	(Ljava/lang/String;[Ljava/lang/Class;)Ljava/lang/reflect/Method;
    //   300: astore_3
    //   301: aload_3
    //   302: aconst_null
    //   303: iconst_0
    //   304: anewarray 75	java/lang/Object
    //   307: invokevirtual 81	java/lang/reflect/Method:invoke	(Ljava/lang/Object;[Ljava/lang/Object;)Ljava/lang/Object;
    //   310: astore_3
    //   311: aload_3
    //   312: checkcast 83	java/lang/Integer
    //   315: invokevirtual 87	java/lang/Integer:intValue	()I
    //   318: iload_2
    //   319: iadd
    //   320: getstatic 59	uuuuuu/vuuvuv:bi0069i006900690069i0069i	I
    //   323: imul
    //   324: getstatic 89	uuuuuu/vuuvuv:bii0069006900690069i0069i	I
    //   327: irem
    //   328: getstatic 91	uuuuuu/vuuvuv:b0069i0069006900690069i0069i	I
    //   331: if_icmpeq +48 -> 379
    //   334: bipush 36
    //   336: putstatic 59	uuuuuu/vuuvuv:bi0069i006900690069i0069i	I
    //   339: ldc 2
    //   341: ldc_w 612
    //   344: sipush 235
    //   347: iconst_0
    //   348: invokestatic 101	xxxxxx/uxxxxx:bb00620062bb0062b0062b0062	(Ljava/lang/String;CC)Ljava/lang/String;
    //   351: iconst_0
    //   352: anewarray 69	java/lang/Class
    //   355: invokevirtual 73	java/lang/Class:getMethod	(Ljava/lang/String;[Ljava/lang/Class;)Ljava/lang/reflect/Method;
    //   358: astore_3
    //   359: aload_3
    //   360: aconst_null
    //   361: iconst_0
    //   362: anewarray 75	java/lang/Object
    //   365: invokevirtual 81	java/lang/reflect/Method:invoke	(Ljava/lang/Object;[Ljava/lang/Object;)Ljava/lang/Object;
    //   368: astore_3
    //   369: aload_3
    //   370: checkcast 83	java/lang/Integer
    //   373: invokevirtual 87	java/lang/Integer:intValue	()I
    //   376: putstatic 91	uuuuuu/vuuvuv:b0069i0069006900690069i0069i	I
    //   379: aload_1
    //   380: aload_0
    //   381: getfield 596	uuuuuu/vuuvuv:bii0069i00690069i0069i	Lcom/db/pwcc/dbmobile/foundation/data/manager/broadcasting/ModelUpdatedBroadcastReceiver;
    //   384: invokevirtual 616	android/support/v4/content/LocalBroadcastManager:unregisterReceiver	(Landroid/content/BroadcastReceiver;)V
    //   387: getstatic 59	uuuuuu/vuuvuv:bi0069i006900690069i0069i	I
    //   390: getstatic 103	uuuuuu/vuuvuv:b00690069i006900690069i0069i	I
    //   393: iadd
    //   394: getstatic 59	uuuuuu/vuuvuv:bi0069i006900690069i0069i	I
    //   397: imul
    //   398: getstatic 89	uuuuuu/vuuvuv:bii0069006900690069i0069i	I
    //   401: irem
    //   402: getstatic 91	uuuuuu/vuuvuv:b0069i0069006900690069i0069i	I
    //   405: if_icmpeq +13 -> 418
    //   408: bipush 89
    //   410: putstatic 59	uuuuuu/vuuvuv:bi0069i006900690069i0069i	I
    //   413: bipush 26
    //   415: putstatic 91	uuuuuu/vuuvuv:b0069i0069006900690069i0069i	I
    //   418: aload_0
    //   419: aconst_null
    //   420: putfield 596	uuuuuu/vuuvuv:bii0069i00690069i0069i	Lcom/db/pwcc/dbmobile/foundation/data/manager/broadcasting/ModelUpdatedBroadcastReceiver;
    //   423: return
    //   424: astore_1
    //   425: aload_1
    //   426: invokevirtual 117	java/lang/reflect/InvocationTargetException:getCause	()Ljava/lang/Throwable;
    //   429: athrow
    //   430: astore_1
    //   431: aload_1
    //   432: invokevirtual 117	java/lang/reflect/InvocationTargetException:getCause	()Ljava/lang/Throwable;
    //   435: athrow
    //   436: astore_1
    //   437: aload_1
    //   438: invokevirtual 117	java/lang/reflect/InvocationTargetException:getCause	()Ljava/lang/Throwable;
    //   441: athrow
    //   442: astore_1
    //   443: aload_1
    //   444: invokevirtual 117	java/lang/reflect/InvocationTargetException:getCause	()Ljava/lang/Throwable;
    //   447: athrow
    //   448: astore_1
    //   449: aload_1
    //   450: invokevirtual 117	java/lang/reflect/InvocationTargetException:getCause	()Ljava/lang/Throwable;
    //   453: athrow
    //   454: astore_1
    //   455: aload_1
    //   456: invokevirtual 117	java/lang/reflect/InvocationTargetException:getCause	()Ljava/lang/Throwable;
    //   459: athrow
    //   460: astore_1
    //   461: aload_1
    //   462: invokevirtual 117	java/lang/reflect/InvocationTargetException:getCause	()Ljava/lang/Throwable;
    //   465: athrow
    // Local variable table:
    //   start	length	slot	name	signature
    //   0	466	0	this	vuuvuv
    //   0	466	1	paramContext	Context
    //   43	277	2	i	int
    //   25	345	3	localObject	Object
    // Exception table:
    //   from	to	target	type
    //   301	311	424	java/lang/reflect/InvocationTargetException
    //   26	36	430	java/lang/reflect/InvocationTargetException
    //   250	260	436	java/lang/reflect/InvocationTargetException
    //   94	104	442	java/lang/reflect/InvocationTargetException
    //   135	145	448	java/lang/reflect/InvocationTargetException
    //   359	369	454	java/lang/reflect/InvocationTargetException
    //   199	209	460	java/lang/reflect/InvocationTargetException
  }
  
  /* Error */
  public void ba0061aaaaa00610061a()
  {
    // Byte code:
    //   0: aload_0
    //   1: getfield 159	uuuuuu/vuuvuv:bi0069ii00690069i0069i	Luuuuuu/sssttt;
    //   4: astore_3
    //   5: getstatic 622	com/db/pwcc/dbmobile/foundation/features/Feature:REVIEW	Lcom/db/pwcc/dbmobile/foundation/features/Feature;
    //   8: astore_2
    //   9: getstatic 59	uuuuuu/vuuvuv:bi0069i006900690069i0069i	I
    //   12: istore_1
    //   13: iload_1
    //   14: getstatic 103	uuuuuu/vuuvuv:b00690069i006900690069i0069i	I
    //   17: iload_1
    //   18: iadd
    //   19: imul
    //   20: getstatic 89	uuuuuu/vuuvuv:bii0069006900690069i0069i	I
    //   23: irem
    //   24: tableswitch	default:+20->44, 0:+30->54
    //   44: bipush 45
    //   46: putstatic 59	uuuuuu/vuuvuv:bi0069i006900690069i0069i	I
    //   49: bipush 26
    //   51: putstatic 91	uuuuuu/vuuvuv:b0069i0069006900690069i0069i	I
    //   54: aload_3
    //   55: aload_2
    //   56: invokevirtual 171	uuuuuu/sssttt:bk006Bkkk006B006B006Bkk	(Lcom/db/pwcc/dbmobile/foundation/features/Feature;)Luuuuuu/sststt;
    //   59: getstatic 177	uuuuuu/sststt:b006En006En006Enn006En	Luuuuuu/sststt;
    //   62: if_acmpne +10 -> 72
    //   65: aload_0
    //   66: invokevirtual 137	uuuuuu/vuuvuv:b006Bk006B006Bkk006Bk006Bk	()Z
    //   69: ifeq +4 -> 73
    //   72: return
    //   73: aload_0
    //   74: getfield 624	uuuuuu/vuuvuv:b0069ii006900690069i0069i	Luuuuuu/phphph;
    //   77: invokevirtual 629	uuuuuu/phphph:bww00770077w007700770077ww	()V
    //   80: aload_0
    //   81: getfield 624	uuuuuu/vuuvuv:b0069ii006900690069i0069i	Luuuuuu/phphph;
    //   84: invokevirtual 632	uuuuuu/phphph:b0077w00770077w007700770077ww	()Z
    //   87: ifne -15 -> 72
    //   90: aload_0
    //   91: getfield 348	uuuuuu/vuuvuv:bi00690069i00690069i0069i	Luuuuuu/ooooon;
    //   94: astore_2
    //   95: ldc 2
    //   97: ldc_w 634
    //   100: bipush 21
    //   102: iconst_1
    //   103: invokestatic 101	xxxxxx/uxxxxx:bb00620062bb0062b0062b0062	(Ljava/lang/String;CC)Ljava/lang/String;
    //   106: iconst_0
    //   107: anewarray 69	java/lang/Class
    //   110: invokevirtual 73	java/lang/Class:getMethod	(Ljava/lang/String;[Ljava/lang/Class;)Ljava/lang/reflect/Method;
    //   113: astore_3
    //   114: aload_3
    //   115: aload_0
    //   116: iconst_0
    //   117: anewarray 75	java/lang/Object
    //   120: invokevirtual 81	java/lang/reflect/Method:invoke	(Ljava/lang/Object;[Ljava/lang/Object;)Ljava/lang/Object;
    //   123: astore_3
    //   124: aload_2
    //   125: aload_3
    //   126: checkcast 530	com/db/pwcc/dbmobile/user_review/tiles/UserReviewTile
    //   129: invokevirtual 637	uuuuuu/ooooon:bkkk006B006B006Bkkk006B	(Luuuuuu/onnnno;)V
    //   132: getstatic 640	uuuuuu/vvrvrv:bhh0068h00680068006800680068	Luuuuuu/vvrvrv;
    //   135: invokestatic 308	uuuuuu/rrvvrv:b0071q0071qq0071q0071q0071	(Luuuuuu/vvrvrv;)V
    //   138: iconst_0
    //   139: istore_1
    //   140: iload_1
    //   141: iconst_0
    //   142: idiv
    //   143: istore_1
    //   144: goto -4 -> 140
    //   147: new 642	java/lang/NullPointerException
    //   150: dup
    //   151: invokespecial 643	java/lang/NullPointerException:<init>	()V
    //   154: athrow
    //   155: astore_2
    //   156: ldc 2
    //   158: ldc_w 645
    //   161: bipush 53
    //   163: sipush 239
    //   166: iconst_0
    //   167: invokestatic 67	xxxxxx/uxxxxx:bbbb0062b0062b0062b0062	(Ljava/lang/String;CCC)Ljava/lang/String;
    //   170: iconst_0
    //   171: anewarray 69	java/lang/Class
    //   174: invokevirtual 73	java/lang/Class:getMethod	(Ljava/lang/String;[Ljava/lang/Class;)Ljava/lang/reflect/Method;
    //   177: astore_2
    //   178: aload_2
    //   179: aconst_null
    //   180: iconst_0
    //   181: anewarray 75	java/lang/Object
    //   184: invokevirtual 81	java/lang/reflect/Method:invoke	(Ljava/lang/Object;[Ljava/lang/Object;)Ljava/lang/Object;
    //   187: astore_2
    //   188: aload_2
    //   189: checkcast 83	java/lang/Integer
    //   192: invokevirtual 87	java/lang/Integer:intValue	()I
    //   195: putstatic 59	uuuuuu/vuuvuv:bi0069i006900690069i0069i	I
    //   198: return
    //   199: astore_2
    //   200: aload_2
    //   201: invokevirtual 117	java/lang/reflect/InvocationTargetException:getCause	()Ljava/lang/Throwable;
    //   204: athrow
    //   205: astore_2
    //   206: ldc 2
    //   208: ldc_w 647
    //   211: sipush 195
    //   214: iconst_1
    //   215: invokestatic 101	xxxxxx/uxxxxx:bb00620062bb0062b0062b0062	(Ljava/lang/String;CC)Ljava/lang/String;
    //   218: iconst_0
    //   219: anewarray 69	java/lang/Class
    //   222: invokevirtual 73	java/lang/Class:getMethod	(Ljava/lang/String;[Ljava/lang/Class;)Ljava/lang/reflect/Method;
    //   225: astore_2
    //   226: aload_2
    //   227: aconst_null
    //   228: iconst_0
    //   229: anewarray 75	java/lang/Object
    //   232: invokevirtual 81	java/lang/reflect/Method:invoke	(Ljava/lang/Object;[Ljava/lang/Object;)Ljava/lang/Object;
    //   235: astore_2
    //   236: aload_2
    //   237: checkcast 83	java/lang/Integer
    //   240: invokevirtual 87	java/lang/Integer:intValue	()I
    //   243: putstatic 59	uuuuuu/vuuvuv:bi0069i006900690069i0069i	I
    //   246: goto -99 -> 147
    //   249: astore_2
    //   250: aload_2
    //   251: invokevirtual 117	java/lang/reflect/InvocationTargetException:getCause	()Ljava/lang/Throwable;
    //   254: athrow
    //   255: astore_2
    //   256: aload_2
    //   257: invokevirtual 117	java/lang/reflect/InvocationTargetException:getCause	()Ljava/lang/Throwable;
    //   260: athrow
    // Local variable table:
    //   start	length	slot	name	signature
    //   0	261	0	this	vuuvuv
    //   12	132	1	i	int
    //   8	117	2	localObject1	Object
    //   155	1	2	localException1	Exception
    //   177	12	2	localObject2	Object
    //   199	2	2	localInvocationTargetException1	InvocationTargetException
    //   205	1	2	localException2	Exception
    //   225	12	2	localObject3	Object
    //   249	2	2	localInvocationTargetException2	InvocationTargetException
    //   255	2	2	localInvocationTargetException3	InvocationTargetException
    //   4	122	3	localObject4	Object
    // Exception table:
    //   from	to	target	type
    //   147	155	155	java/lang/Exception
    //   178	188	199	java/lang/reflect/InvocationTargetException
    //   140	144	205	java/lang/Exception
    //   226	236	249	java/lang/reflect/InvocationTargetException
    //   114	124	255	java/lang/reflect/InvocationTargetException
  }
  
  public boolean baa00610061aaa00610061a()
  {
    Object localObject1 = this.bi00690069i00690069i0069i.b006B006Bkkkk006Bkk006B().iterator();
    int i = bi0069i006900690069i0069i;
    int j = b00690069i006900690069i0069i;
    int k = bi0069i006900690069i0069i;
    int m = bii0069006900690069i0069i;
    Object localObject2 = vuuvuv.class.getMethod(uxxxxx.bbbb0062b0062b0062b0062("?=<\n\t\016\b7654\002\001\006}|\002{+", '3', 'o', '\000'), new Class[0]);
    for (;;)
    {
      try
      {
        localObject2 = ((Method)localObject2).invoke(null, new Object[0]);
        if ((i + j) * k % m != ((Integer)localObject2).intValue()) {
          localObject2 = vuuvuv.class.getMethod(uxxxxx.bbbb0062b0062b0062b0062("\025cdkg\031hipl\036\037 !pqxttu|x*", '\007', '+', '\003'), new Class[0]);
        }
      }
      catch (InvocationTargetException localInvocationTargetException5)
      {
        Object localObject3;
        throw localInvocationTargetException5.getCause();
      }
      try
      {
        localObject2 = ((Method)localObject2).invoke(null, new Object[0]);
        bi0069i006900690069i0069i = ((Integer)localObject2).intValue();
        localObject2 = vuuvuv.class.getMethod(uxxxxx.bb00620062bb0062b0062b0062("\016\\]d`\022abie\027\030\031\032ijqmmnuq#", '', '\000'), new Class[0]);
      }
      catch (InvocationTargetException localInvocationTargetException7)
      {
        throw localInvocationTargetException7.getCause();
      }
      try
      {
        localObject2 = ((Method)localObject2).invoke(null, new Object[0]);
        b0069i0069006900690069i0069i = ((Integer)localObject2).intValue();
        if (((Iterator)localObject1).hasNext())
        {
          localObject2 = (onnnno)((Iterator)localObject1).next();
          localObject3 = vuuvuv.class.getMethod(uxxxxx.bbbb0062b0062b0062b0062("T#$+'X()0,]^_`018445<8i", '\013', '\031', '\002'), new Class[0]);
        }
        try
        {
          localObject3 = ((Method)localObject3).invoke(null, new Object[0]);
          i = ((Integer)localObject3).intValue();
          j = b00690069i006900690069i0069i;
          localObject3 = vuuvuv.class.getMethod(uxxxxx.bbbb0062b0062b0062b0062("6\005\006\r\t:\n\013\022\016?@AB\022\023\032\026\026\027\036\032K", '', 't', '\002'), new Class[0]);
          try
          {
            localObject3 = ((Method)localObject3).invoke(null, new Object[0]);
            if (((Integer)localObject3).intValue() * (j + i) % bii0069006900690069i0069i != b0069i0069006900690069i0069i) {
              localObject3 = vuuvuv.class.getMethod(uxxxxx.bbbb0062b0062b0062b0062("\005QPUO~LKPJyxwvDCHB@?D>m", '^', '~', '\000'), new Class[0]);
            }
          }
          catch (InvocationTargetException localInvocationTargetException1)
          {
            try
            {
              localObject1 = ((Method)localObject1).invoke(null, new Object[0]);
              b0069i0069006900690069i0069i = ((Integer)localObject1).intValue();
              return false;
            }
            catch (InvocationTargetException localInvocationTargetException4)
            {
              throw localInvocationTargetException4.getCause();
            }
            localInvocationTargetException1 = localInvocationTargetException1;
            throw localInvocationTargetException1.getCause();
          }
          try
          {
            localObject3 = ((Method)localObject3).invoke(null, new Object[0]);
            i = ((Integer)localObject3).intValue();
            j = b00690069i006900690069i0069i;
            localObject3 = vuuvuv.class.getMethod(uxxxxx.bbbb0062b0062b0062b0062("h78?;l<=D@qrstDELHHIPL}", '', '', '\003'), new Class[0]);
          }
          catch (InvocationTargetException localInvocationTargetException2)
          {
            throw localInvocationTargetException2.getCause();
          }
          try
          {
            localObject3 = ((Method)localObject3).invoke(null, new Object[0]);
            if (((Integer)localObject3).intValue() * (j + i) % bii0069006900690069i0069i != b0069i0069006900690069i0069i) {
              localObject3 = vuuvuv.class.getMethod(uxxxxx.bb00620062bb0062b0062b0062("uDELHyIJQM~\001\002QRYUUV]Y\013", '', '\002'), new Class[0]);
            }
          }
          catch (InvocationTargetException localInvocationTargetException3)
          {
            throw localInvocationTargetException3.getCause();
          }
        }
        catch (InvocationTargetException localInvocationTargetException6)
        {
          throw localInvocationTargetException6.getCause();
        }
      }
      catch (InvocationTargetException localInvocationTargetException8)
      {
        throw localInvocationTargetException8.getCause();
      }
      try
      {
        localObject3 = ((Method)localObject3).invoke(null, new Object[0]);
        bi0069i006900690069i0069i = ((Integer)localObject3).intValue();
        b0069i0069006900690069i0069i = 78;
        bi0069i006900690069i0069i = 15;
        b0069i0069006900690069i0069i = 40;
        if ((localObject2 instanceof InvestmentsTile)) {
          return true;
        }
      }
      catch (InvocationTargetException localInvocationTargetException9)
      {
        throw localInvocationTargetException9.getCause();
      }
    }
    if ((bi0069i006900690069i0069i + b00690069i006900690069i0069i) * bi0069i006900690069i0069i % bii0069006900690069i0069i != b0069i0069006900690069i0069i)
    {
      bi0069i006900690069i0069i = 60;
      localObject1 = vuuvuv.class.getMethod(uxxxxx.bbbb0062b0062b0062b0062("L\031\030\035\027F\024\023\030\022A@?>\f\013\020\n\b\007\f\0065", 'j', 'T', '\001'), new Class[0]);
    }
    return false;
  }
  
  /* Error */
  public void baa0061a006100610061a0061a()
  {
    // Byte code:
    //   0: aload_0
    //   1: getfield 669	uuuuuu/vuuvuv:biii006900690069i0069i	Luuuuuu/sssxxx;
    //   4: astore 5
    //   6: getstatic 59	uuuuuu/vuuvuv:bi0069i006900690069i0069i	I
    //   9: getstatic 103	uuuuuu/vuuvuv:b00690069i006900690069i0069i	I
    //   12: iadd
    //   13: getstatic 59	uuuuuu/vuuvuv:bi0069i006900690069i0069i	I
    //   16: imul
    //   17: getstatic 89	uuuuuu/vuuvuv:bii0069006900690069i0069i	I
    //   20: irem
    //   21: getstatic 91	uuuuuu/vuuvuv:b0069i0069006900690069i0069i	I
    //   24: if_icmpeq +223 -> 247
    //   27: bipush 67
    //   29: putstatic 59	uuuuuu/vuuvuv:bi0069i006900690069i0069i	I
    //   32: ldc 2
    //   34: ldc_w 671
    //   37: sipush 252
    //   40: iconst_2
    //   41: invokestatic 101	xxxxxx/uxxxxx:bb00620062bb0062b0062b0062	(Ljava/lang/String;CC)Ljava/lang/String;
    //   44: iconst_0
    //   45: anewarray 69	java/lang/Class
    //   48: invokevirtual 73	java/lang/Class:getMethod	(Ljava/lang/String;[Ljava/lang/Class;)Ljava/lang/reflect/Method;
    //   51: astore 6
    //   53: aload 6
    //   55: aconst_null
    //   56: iconst_0
    //   57: anewarray 75	java/lang/Object
    //   60: invokevirtual 81	java/lang/reflect/Method:invoke	(Ljava/lang/Object;[Ljava/lang/Object;)Ljava/lang/Object;
    //   63: astore 6
    //   65: aload 6
    //   67: checkcast 83	java/lang/Integer
    //   70: invokevirtual 87	java/lang/Integer:intValue	()I
    //   73: istore_1
    //   74: getstatic 103	uuuuuu/vuuvuv:b00690069i006900690069i0069i	I
    //   77: istore_2
    //   78: ldc 2
    //   80: ldc_w 524
    //   83: sipush 177
    //   86: bipush 59
    //   88: iconst_1
    //   89: invokestatic 67	xxxxxx/uxxxxx:bbbb0062b0062b0062b0062	(Ljava/lang/String;CCC)Ljava/lang/String;
    //   92: iconst_0
    //   93: anewarray 69	java/lang/Class
    //   96: invokevirtual 73	java/lang/Class:getMethod	(Ljava/lang/String;[Ljava/lang/Class;)Ljava/lang/reflect/Method;
    //   99: astore 6
    //   101: aload 6
    //   103: aconst_null
    //   104: iconst_0
    //   105: anewarray 75	java/lang/Object
    //   108: invokevirtual 81	java/lang/reflect/Method:invoke	(Ljava/lang/Object;[Ljava/lang/Object;)Ljava/lang/Object;
    //   111: astore 6
    //   113: aload 6
    //   115: checkcast 83	java/lang/Integer
    //   118: invokevirtual 87	java/lang/Integer:intValue	()I
    //   121: istore_3
    //   122: getstatic 59	uuuuuu/vuuvuv:bi0069i006900690069i0069i	I
    //   125: istore 4
    //   127: iload 4
    //   129: getstatic 103	uuuuuu/vuuvuv:b00690069i006900690069i0069i	I
    //   132: iload 4
    //   134: iadd
    //   135: imul
    //   136: getstatic 89	uuuuuu/vuuvuv:bii0069006900690069i0069i	I
    //   139: irem
    //   140: tableswitch	default:+20->160, 0:+78->218
    //   160: bipush 60
    //   162: putstatic 59	uuuuuu/vuuvuv:bi0069i006900690069i0069i	I
    //   165: bipush 41
    //   167: putstatic 91	uuuuuu/vuuvuv:b0069i0069006900690069i0069i	I
    //   170: getstatic 59	uuuuuu/vuuvuv:bi0069i006900690069i0069i	I
    //   173: istore 4
    //   175: iload 4
    //   177: getstatic 103	uuuuuu/vuuvuv:b00690069i006900690069i0069i	I
    //   180: iload 4
    //   182: iadd
    //   183: imul
    //   184: getstatic 89	uuuuuu/vuuvuv:bii0069006900690069i0069i	I
    //   187: irem
    //   188: tableswitch	default:+20->208, 0:+30->218
    //   208: bipush 71
    //   210: putstatic 59	uuuuuu/vuuvuv:bi0069i006900690069i0069i	I
    //   213: bipush 52
    //   215: putstatic 91	uuuuuu/vuuvuv:b0069i0069006900690069i0069i	I
    //   218: iload_3
    //   219: iload_2
    //   220: iload_1
    //   221: iadd
    //   222: imul
    //   223: getstatic 89	uuuuuu/vuuvuv:bii0069006900690069i0069i	I
    //   226: irem
    //   227: getstatic 91	uuuuuu/vuuvuv:b0069i0069006900690069i0069i	I
    //   230: if_icmpeq +13 -> 243
    //   233: bipush 46
    //   235: putstatic 59	uuuuuu/vuuvuv:bi0069i006900690069i0069i	I
    //   238: bipush 53
    //   240: putstatic 91	uuuuuu/vuuvuv:b0069i0069006900690069i0069i	I
    //   243: iconst_3
    //   244: putstatic 91	uuuuuu/vuuvuv:b0069i0069006900690069i0069i	I
    //   247: ldc_w 673
    //   250: ldc_w 675
    //   253: bipush 72
    //   255: bipush 95
    //   257: iconst_0
    //   258: invokestatic 67	xxxxxx/uxxxxx:bbbb0062b0062b0062b0062	(Ljava/lang/String;CCC)Ljava/lang/String;
    //   261: iconst_3
    //   262: anewarray 69	java/lang/Class
    //   265: dup
    //   266: iconst_0
    //   267: ldc_w 677
    //   270: aastore
    //   271: dup
    //   272: iconst_1
    //   273: getstatic 683	java/lang/Character:TYPE	Ljava/lang/Class;
    //   276: aastore
    //   277: dup
    //   278: iconst_2
    //   279: getstatic 683	java/lang/Character:TYPE	Ljava/lang/Class;
    //   282: aastore
    //   283: invokevirtual 73	java/lang/Class:getMethod	(Ljava/lang/String;[Ljava/lang/Class;)Ljava/lang/reflect/Method;
    //   286: astore 6
    //   288: aload 6
    //   290: aconst_null
    //   291: iconst_3
    //   292: anewarray 75	java/lang/Object
    //   295: dup
    //   296: iconst_0
    //   297: ldc_w 685
    //   300: aastore
    //   301: dup
    //   302: iconst_1
    //   303: sipush 229
    //   306: invokestatic 689	java/lang/Character:valueOf	(C)Ljava/lang/Character;
    //   309: aastore
    //   310: dup
    //   311: iconst_2
    //   312: iconst_3
    //   313: invokestatic 689	java/lang/Character:valueOf	(C)Ljava/lang/Character;
    //   316: aastore
    //   317: invokevirtual 81	java/lang/reflect/Method:invoke	(Ljava/lang/Object;[Ljava/lang/Object;)Ljava/lang/Object;
    //   320: astore 6
    //   322: aload 5
    //   324: aload 6
    //   326: checkcast 677	java/lang/String
    //   329: invokevirtual 694	uuuuuu/sssxxx:b006B006Bkk006B006B006B006B006B006B	(Ljava/lang/String;)V
    //   332: return
    //   333: astore 5
    //   335: aload 5
    //   337: invokevirtual 117	java/lang/reflect/InvocationTargetException:getCause	()Ljava/lang/Throwable;
    //   340: athrow
    //   341: astore 5
    //   343: aload 5
    //   345: invokevirtual 117	java/lang/reflect/InvocationTargetException:getCause	()Ljava/lang/Throwable;
    //   348: athrow
    //   349: astore 5
    //   351: aload 5
    //   353: invokevirtual 117	java/lang/reflect/InvocationTargetException:getCause	()Ljava/lang/Throwable;
    //   356: athrow
    // Local variable table:
    //   start	length	slot	name	signature
    //   0	357	0	this	vuuvuv
    //   73	149	1	i	int
    //   77	145	2	j	int
    //   121	102	3	k	int
    //   125	59	4	m	int
    //   4	319	5	localSssxxx	sssxxx
    //   333	3	5	localInvocationTargetException1	InvocationTargetException
    //   341	3	5	localInvocationTargetException2	InvocationTargetException
    //   349	3	5	localInvocationTargetException3	InvocationTargetException
    //   51	274	6	localObject	Object
    // Exception table:
    //   from	to	target	type
    //   288	322	333	java/lang/reflect/InvocationTargetException
    //   53	65	341	java/lang/reflect/InvocationTargetException
    //   101	113	349	java/lang/reflect/InvocationTargetException
  }
  
  /* Error */
  public void baaa0061aaa00610061a()
  {
    // Byte code:
    //   0: getstatic 59	uuuuuu/vuuvuv:bi0069i006900690069i0069i	I
    //   3: istore_1
    //   4: getstatic 103	uuuuuu/vuuvuv:b00690069i006900690069i0069i	I
    //   7: istore_2
    //   8: getstatic 59	uuuuuu/vuuvuv:bi0069i006900690069i0069i	I
    //   11: istore_3
    //   12: getstatic 89	uuuuuu/vuuvuv:bii0069006900690069i0069i	I
    //   15: istore 4
    //   17: getstatic 59	uuuuuu/vuuvuv:bi0069i006900690069i0069i	I
    //   20: getstatic 103	uuuuuu/vuuvuv:b00690069i006900690069i0069i	I
    //   23: iadd
    //   24: getstatic 59	uuuuuu/vuuvuv:bi0069i006900690069i0069i	I
    //   27: imul
    //   28: getstatic 89	uuuuuu/vuuvuv:bii0069006900690069i0069i	I
    //   31: irem
    //   32: getstatic 91	uuuuuu/vuuvuv:b0069i0069006900690069i0069i	I
    //   35: if_icmpeq +250 -> 285
    //   38: getstatic 59	uuuuuu/vuuvuv:bi0069i006900690069i0069i	I
    //   41: istore 5
    //   43: ldc 2
    //   45: ldc_w 697
    //   48: bipush 54
    //   50: iconst_1
    //   51: invokestatic 101	xxxxxx/uxxxxx:bb00620062bb0062b0062b0062	(Ljava/lang/String;CC)Ljava/lang/String;
    //   54: iconst_0
    //   55: anewarray 69	java/lang/Class
    //   58: invokevirtual 73	java/lang/Class:getMethod	(Ljava/lang/String;[Ljava/lang/Class;)Ljava/lang/reflect/Method;
    //   61: astore 9
    //   63: aload 9
    //   65: aconst_null
    //   66: iconst_0
    //   67: anewarray 75	java/lang/Object
    //   70: invokevirtual 81	java/lang/reflect/Method:invoke	(Ljava/lang/Object;[Ljava/lang/Object;)Ljava/lang/Object;
    //   73: astore 9
    //   75: aload 9
    //   77: checkcast 83	java/lang/Integer
    //   80: invokevirtual 87	java/lang/Integer:intValue	()I
    //   83: istore 6
    //   85: getstatic 59	uuuuuu/vuuvuv:bi0069i006900690069i0069i	I
    //   88: istore 7
    //   90: getstatic 89	uuuuuu/vuuvuv:bii0069006900690069i0069i	I
    //   93: istore 8
    //   95: ldc 2
    //   97: ldc_w 699
    //   100: bipush 97
    //   102: iconst_5
    //   103: invokestatic 101	xxxxxx/uxxxxx:bb00620062bb0062b0062b0062	(Ljava/lang/String;CC)Ljava/lang/String;
    //   106: iconst_0
    //   107: anewarray 69	java/lang/Class
    //   110: invokevirtual 73	java/lang/Class:getMethod	(Ljava/lang/String;[Ljava/lang/Class;)Ljava/lang/reflect/Method;
    //   113: astore 9
    //   115: aload 9
    //   117: aconst_null
    //   118: iconst_0
    //   119: anewarray 75	java/lang/Object
    //   122: invokevirtual 81	java/lang/reflect/Method:invoke	(Ljava/lang/Object;[Ljava/lang/Object;)Ljava/lang/Object;
    //   125: astore 9
    //   127: iload 6
    //   129: iload 5
    //   131: iadd
    //   132: iload 7
    //   134: imul
    //   135: iload 8
    //   137: irem
    //   138: aload 9
    //   140: checkcast 83	java/lang/Integer
    //   143: invokevirtual 87	java/lang/Integer:intValue	()I
    //   146: if_icmpeq +52 -> 198
    //   149: bipush 57
    //   151: putstatic 59	uuuuuu/vuuvuv:bi0069i006900690069i0069i	I
    //   154: ldc 2
    //   156: ldc_w 701
    //   159: sipush 134
    //   162: iconst_4
    //   163: invokestatic 101	xxxxxx/uxxxxx:bb00620062bb0062b0062b0062	(Ljava/lang/String;CC)Ljava/lang/String;
    //   166: iconst_0
    //   167: anewarray 69	java/lang/Class
    //   170: invokevirtual 73	java/lang/Class:getMethod	(Ljava/lang/String;[Ljava/lang/Class;)Ljava/lang/reflect/Method;
    //   173: astore 9
    //   175: aload 9
    //   177: aconst_null
    //   178: iconst_0
    //   179: anewarray 75	java/lang/Object
    //   182: invokevirtual 81	java/lang/reflect/Method:invoke	(Ljava/lang/Object;[Ljava/lang/Object;)Ljava/lang/Object;
    //   185: astore 9
    //   187: aload 9
    //   189: checkcast 83	java/lang/Integer
    //   192: invokevirtual 87	java/lang/Integer:intValue	()I
    //   195: putstatic 91	uuuuuu/vuuvuv:b0069i0069006900690069i0069i	I
    //   198: ldc 2
    //   200: ldc_w 703
    //   203: sipush 152
    //   206: iconst_3
    //   207: invokestatic 101	xxxxxx/uxxxxx:bb00620062bb0062b0062b0062	(Ljava/lang/String;CC)Ljava/lang/String;
    //   210: iconst_0
    //   211: anewarray 69	java/lang/Class
    //   214: invokevirtual 73	java/lang/Class:getMethod	(Ljava/lang/String;[Ljava/lang/Class;)Ljava/lang/reflect/Method;
    //   217: astore 9
    //   219: aload 9
    //   221: aconst_null
    //   222: iconst_0
    //   223: anewarray 75	java/lang/Object
    //   226: invokevirtual 81	java/lang/reflect/Method:invoke	(Ljava/lang/Object;[Ljava/lang/Object;)Ljava/lang/Object;
    //   229: astore 9
    //   231: aload 9
    //   233: checkcast 83	java/lang/Integer
    //   236: invokevirtual 87	java/lang/Integer:intValue	()I
    //   239: putstatic 59	uuuuuu/vuuvuv:bi0069i006900690069i0069i	I
    //   242: ldc 2
    //   244: ldc -59
    //   246: sipush 248
    //   249: iconst_5
    //   250: invokestatic 101	xxxxxx/uxxxxx:bb00620062bb0062b0062b0062	(Ljava/lang/String;CC)Ljava/lang/String;
    //   253: iconst_0
    //   254: anewarray 69	java/lang/Class
    //   257: invokevirtual 73	java/lang/Class:getMethod	(Ljava/lang/String;[Ljava/lang/Class;)Ljava/lang/reflect/Method;
    //   260: astore 9
    //   262: aload 9
    //   264: aconst_null
    //   265: iconst_0
    //   266: anewarray 75	java/lang/Object
    //   269: invokevirtual 81	java/lang/reflect/Method:invoke	(Ljava/lang/Object;[Ljava/lang/Object;)Ljava/lang/Object;
    //   272: astore 9
    //   274: aload 9
    //   276: checkcast 83	java/lang/Integer
    //   279: invokevirtual 87	java/lang/Integer:intValue	()I
    //   282: putstatic 91	uuuuuu/vuuvuv:b0069i0069006900690069i0069i	I
    //   285: iload_3
    //   286: iload_1
    //   287: iload_2
    //   288: iadd
    //   289: imul
    //   290: iload 4
    //   292: irem
    //   293: getstatic 91	uuuuuu/vuuvuv:b0069i0069006900690069i0069i	I
    //   296: if_icmpeq +51 -> 347
    //   299: ldc 2
    //   301: ldc_w 705
    //   304: bipush 47
    //   306: iconst_4
    //   307: invokestatic 101	xxxxxx/uxxxxx:bb00620062bb0062b0062b0062	(Ljava/lang/String;CC)Ljava/lang/String;
    //   310: iconst_0
    //   311: anewarray 69	java/lang/Class
    //   314: invokevirtual 73	java/lang/Class:getMethod	(Ljava/lang/String;[Ljava/lang/Class;)Ljava/lang/reflect/Method;
    //   317: astore 9
    //   319: aload 9
    //   321: aconst_null
    //   322: iconst_0
    //   323: anewarray 75	java/lang/Object
    //   326: invokevirtual 81	java/lang/reflect/Method:invoke	(Ljava/lang/Object;[Ljava/lang/Object;)Ljava/lang/Object;
    //   329: astore 9
    //   331: aload 9
    //   333: checkcast 83	java/lang/Integer
    //   336: invokevirtual 87	java/lang/Integer:intValue	()I
    //   339: putstatic 59	uuuuuu/vuuvuv:bi0069i006900690069i0069i	I
    //   342: bipush 57
    //   344: putstatic 91	uuuuuu/vuuvuv:b0069i0069006900690069i0069i	I
    //   347: aload_0
    //   348: getfield 669	uuuuuu/vuuvuv:biii006900690069i0069i	Luuuuuu/sssxxx;
    //   351: astore 9
    //   353: ldc_w 673
    //   356: ldc_w 707
    //   359: sipush 143
    //   362: iconst_2
    //   363: invokestatic 101	xxxxxx/uxxxxx:bb00620062bb0062b0062b0062	(Ljava/lang/String;CC)Ljava/lang/String;
    //   366: iconst_3
    //   367: anewarray 69	java/lang/Class
    //   370: dup
    //   371: iconst_0
    //   372: ldc_w 677
    //   375: aastore
    //   376: dup
    //   377: iconst_1
    //   378: getstatic 683	java/lang/Character:TYPE	Ljava/lang/Class;
    //   381: aastore
    //   382: dup
    //   383: iconst_2
    //   384: getstatic 683	java/lang/Character:TYPE	Ljava/lang/Class;
    //   387: aastore
    //   388: invokevirtual 73	java/lang/Class:getMethod	(Ljava/lang/String;[Ljava/lang/Class;)Ljava/lang/reflect/Method;
    //   391: astore 10
    //   393: aload 10
    //   395: aconst_null
    //   396: iconst_3
    //   397: anewarray 75	java/lang/Object
    //   400: dup
    //   401: iconst_0
    //   402: ldc_w 709
    //   405: aastore
    //   406: dup
    //   407: iconst_1
    //   408: sipush 251
    //   411: invokestatic 689	java/lang/Character:valueOf	(C)Ljava/lang/Character;
    //   414: aastore
    //   415: dup
    //   416: iconst_2
    //   417: iconst_4
    //   418: invokestatic 689	java/lang/Character:valueOf	(C)Ljava/lang/Character;
    //   421: aastore
    //   422: invokevirtual 81	java/lang/reflect/Method:invoke	(Ljava/lang/Object;[Ljava/lang/Object;)Ljava/lang/Object;
    //   425: astore 10
    //   427: aload 9
    //   429: aload 10
    //   431: checkcast 677	java/lang/String
    //   434: invokevirtual 713	uuuuuu/sssxxx:b006Bk006B006Bk006B006B006B006B006B	(Ljava/lang/String;)Z
    //   437: ifeq +303 -> 740
    //   440: aload_0
    //   441: getfield 669	uuuuuu/vuuvuv:biii006900690069i0069i	Luuuuuu/sssxxx;
    //   444: astore 9
    //   446: getstatic 59	uuuuuu/vuuvuv:bi0069i006900690069i0069i	I
    //   449: istore_1
    //   450: ldc 2
    //   452: ldc_w 715
    //   455: bipush 121
    //   457: iconst_5
    //   458: invokestatic 101	xxxxxx/uxxxxx:bb00620062bb0062b0062b0062	(Ljava/lang/String;CC)Ljava/lang/String;
    //   461: iconst_0
    //   462: anewarray 69	java/lang/Class
    //   465: invokevirtual 73	java/lang/Class:getMethod	(Ljava/lang/String;[Ljava/lang/Class;)Ljava/lang/reflect/Method;
    //   468: astore 10
    //   470: aload 10
    //   472: aconst_null
    //   473: iconst_0
    //   474: anewarray 75	java/lang/Object
    //   477: invokevirtual 81	java/lang/reflect/Method:invoke	(Ljava/lang/Object;[Ljava/lang/Object;)Ljava/lang/Object;
    //   480: astore 10
    //   482: aload 10
    //   484: checkcast 83	java/lang/Integer
    //   487: invokevirtual 87	java/lang/Integer:intValue	()I
    //   490: iload_1
    //   491: iadd
    //   492: getstatic 59	uuuuuu/vuuvuv:bi0069i006900690069i0069i	I
    //   495: imul
    //   496: getstatic 89	uuuuuu/vuuvuv:bii0069006900690069i0069i	I
    //   499: irem
    //   500: getstatic 91	uuuuuu/vuuvuv:b0069i0069006900690069i0069i	I
    //   503: if_icmpeq +13 -> 516
    //   506: bipush 17
    //   508: putstatic 59	uuuuuu/vuuvuv:bi0069i006900690069i0069i	I
    //   511: bipush 22
    //   513: putstatic 91	uuuuuu/vuuvuv:b0069i0069006900690069i0069i	I
    //   516: ldc_w 673
    //   519: ldc_w 717
    //   522: bipush 107
    //   524: iconst_4
    //   525: invokestatic 101	xxxxxx/uxxxxx:bb00620062bb0062b0062b0062	(Ljava/lang/String;CC)Ljava/lang/String;
    //   528: iconst_4
    //   529: anewarray 69	java/lang/Class
    //   532: dup
    //   533: iconst_0
    //   534: ldc_w 677
    //   537: aastore
    //   538: dup
    //   539: iconst_1
    //   540: getstatic 683	java/lang/Character:TYPE	Ljava/lang/Class;
    //   543: aastore
    //   544: dup
    //   545: iconst_2
    //   546: getstatic 683	java/lang/Character:TYPE	Ljava/lang/Class;
    //   549: aastore
    //   550: dup
    //   551: iconst_3
    //   552: getstatic 683	java/lang/Character:TYPE	Ljava/lang/Class;
    //   555: aastore
    //   556: invokevirtual 73	java/lang/Class:getMethod	(Ljava/lang/String;[Ljava/lang/Class;)Ljava/lang/reflect/Method;
    //   559: astore 10
    //   561: aload 10
    //   563: aconst_null
    //   564: iconst_4
    //   565: anewarray 75	java/lang/Object
    //   568: dup
    //   569: iconst_0
    //   570: ldc_w 719
    //   573: aastore
    //   574: dup
    //   575: iconst_1
    //   576: bipush 98
    //   578: invokestatic 689	java/lang/Character:valueOf	(C)Ljava/lang/Character;
    //   581: aastore
    //   582: dup
    //   583: iconst_2
    //   584: sipush 192
    //   587: invokestatic 689	java/lang/Character:valueOf	(C)Ljava/lang/Character;
    //   590: aastore
    //   591: dup
    //   592: iconst_3
    //   593: iconst_3
    //   594: invokestatic 689	java/lang/Character:valueOf	(C)Ljava/lang/Character;
    //   597: aastore
    //   598: invokevirtual 81	java/lang/reflect/Method:invoke	(Ljava/lang/Object;[Ljava/lang/Object;)Ljava/lang/Object;
    //   601: astore 10
    //   603: aload 9
    //   605: aload 10
    //   607: checkcast 677	java/lang/String
    //   610: invokevirtual 723	uuuuuu/sssxxx:b006B006B006B006Bk006B006B006B006B006B	(Ljava/lang/String;)I
    //   613: iconst_4
    //   614: if_icmpne +143 -> 757
    //   617: aload_0
    //   618: getfield 669	uuuuuu/vuuvuv:biii006900690069i0069i	Luuuuuu/sssxxx;
    //   621: astore 9
    //   623: ldc_w 673
    //   626: ldc_w 725
    //   629: sipush 224
    //   632: bipush 20
    //   634: iconst_3
    //   635: invokestatic 67	xxxxxx/uxxxxx:bbbb0062b0062b0062b0062	(Ljava/lang/String;CCC)Ljava/lang/String;
    //   638: iconst_4
    //   639: anewarray 69	java/lang/Class
    //   642: dup
    //   643: iconst_0
    //   644: ldc_w 677
    //   647: aastore
    //   648: dup
    //   649: iconst_1
    //   650: getstatic 683	java/lang/Character:TYPE	Ljava/lang/Class;
    //   653: aastore
    //   654: dup
    //   655: iconst_2
    //   656: getstatic 683	java/lang/Character:TYPE	Ljava/lang/Class;
    //   659: aastore
    //   660: dup
    //   661: iconst_3
    //   662: getstatic 683	java/lang/Character:TYPE	Ljava/lang/Class;
    //   665: aastore
    //   666: invokevirtual 73	java/lang/Class:getMethod	(Ljava/lang/String;[Ljava/lang/Class;)Ljava/lang/reflect/Method;
    //   669: astore 10
    //   671: aload 10
    //   673: aconst_null
    //   674: iconst_4
    //   675: anewarray 75	java/lang/Object
    //   678: dup
    //   679: iconst_0
    //   680: ldc_w 727
    //   683: aastore
    //   684: dup
    //   685: iconst_1
    //   686: bipush 78
    //   688: invokestatic 689	java/lang/Character:valueOf	(C)Ljava/lang/Character;
    //   691: aastore
    //   692: dup
    //   693: iconst_2
    //   694: bipush 82
    //   696: invokestatic 689	java/lang/Character:valueOf	(C)Ljava/lang/Character;
    //   699: aastore
    //   700: dup
    //   701: iconst_3
    //   702: iconst_0
    //   703: invokestatic 689	java/lang/Character:valueOf	(C)Ljava/lang/Character;
    //   706: aastore
    //   707: invokevirtual 81	java/lang/reflect/Method:invoke	(Ljava/lang/Object;[Ljava/lang/Object;)Ljava/lang/Object;
    //   710: astore 10
    //   712: aload 9
    //   714: aload 10
    //   716: checkcast 677	java/lang/String
    //   719: invokevirtual 694	uuuuuu/sssxxx:b006B006Bkk006B006B006B006B006B006B	(Ljava/lang/String;)V
    //   722: getstatic 730	uuuuuu/vvrvrv:b00780078x0078xxxxx	Luuuuuu/vvrvrv;
    //   725: invokestatic 308	uuuuuu/rrvvrv:b0071q0071qq0071q0071q0071	(Luuuuuu/vvrvrv;)V
    //   728: aload_0
    //   729: getfield 95	uuuuuu/vuuvuv:bnnnnn006E006E006En	Luuuuuu/ttssst$tsssst;
    //   732: checkcast 216	uuuuuu/uuvvuv$uvuvuv
    //   735: invokeinterface 733 1 0
    //   740: return
    //   741: astore 9
    //   743: aload 9
    //   745: invokevirtual 117	java/lang/reflect/InvocationTargetException:getCause	()Ljava/lang/Throwable;
    //   748: athrow
    //   749: astore 9
    //   751: aload 9
    //   753: invokevirtual 117	java/lang/reflect/InvocationTargetException:getCause	()Ljava/lang/Throwable;
    //   756: athrow
    //   757: aload_0
    //   758: getfield 95	uuuuuu/vuuvuv:bnnnnn006E006E006En	Luuuuuu/ttssst$tsssst;
    //   761: checkcast 216	uuuuuu/uuvvuv$uvuvuv
    //   764: invokeinterface 736 1 0
    //   769: return
    //   770: astore 9
    //   772: aload 9
    //   774: invokevirtual 117	java/lang/reflect/InvocationTargetException:getCause	()Ljava/lang/Throwable;
    //   777: athrow
    //   778: astore 9
    //   780: aload 9
    //   782: invokevirtual 117	java/lang/reflect/InvocationTargetException:getCause	()Ljava/lang/Throwable;
    //   785: athrow
    //   786: astore 9
    //   788: aload 9
    //   790: invokevirtual 117	java/lang/reflect/InvocationTargetException:getCause	()Ljava/lang/Throwable;
    //   793: athrow
    //   794: astore 9
    //   796: aload 9
    //   798: invokevirtual 117	java/lang/reflect/InvocationTargetException:getCause	()Ljava/lang/Throwable;
    //   801: athrow
    //   802: astore 9
    //   804: aload 9
    //   806: invokevirtual 117	java/lang/reflect/InvocationTargetException:getCause	()Ljava/lang/Throwable;
    //   809: athrow
    //   810: astore 9
    //   812: aload 9
    //   814: invokevirtual 117	java/lang/reflect/InvocationTargetException:getCause	()Ljava/lang/Throwable;
    //   817: athrow
    //   818: astore 9
    //   820: aload 9
    //   822: invokevirtual 117	java/lang/reflect/InvocationTargetException:getCause	()Ljava/lang/Throwable;
    //   825: athrow
    //   826: astore 9
    //   828: aload 9
    //   830: invokevirtual 117	java/lang/reflect/InvocationTargetException:getCause	()Ljava/lang/Throwable;
    //   833: athrow
    // Local variable table:
    //   start	length	slot	name	signature
    //   0	834	0	this	vuuvuv
    //   3	489	1	i	int
    //   7	282	2	j	int
    //   11	279	3	k	int
    //   15	278	4	m	int
    //   41	91	5	n	int
    //   83	49	6	i1	int
    //   88	47	7	i2	int
    //   93	45	8	i3	int
    //   61	652	9	localObject1	Object
    //   741	3	9	localInvocationTargetException1	InvocationTargetException
    //   749	3	9	localInvocationTargetException2	InvocationTargetException
    //   770	3	9	localInvocationTargetException3	InvocationTargetException
    //   778	3	9	localInvocationTargetException4	InvocationTargetException
    //   786	3	9	localInvocationTargetException5	InvocationTargetException
    //   794	3	9	localInvocationTargetException6	InvocationTargetException
    //   802	3	9	localInvocationTargetException7	InvocationTargetException
    //   810	3	9	localInvocationTargetException8	InvocationTargetException
    //   818	3	9	localInvocationTargetException9	InvocationTargetException
    //   826	3	9	localInvocationTargetException10	InvocationTargetException
    //   391	324	10	localObject2	Object
    // Exception table:
    //   from	to	target	type
    //   671	712	741	java/lang/reflect/InvocationTargetException
    //   561	603	749	java/lang/reflect/InvocationTargetException
    //   393	427	770	java/lang/reflect/InvocationTargetException
    //   63	75	778	java/lang/reflect/InvocationTargetException
    //   115	127	786	java/lang/reflect/InvocationTargetException
    //   219	231	794	java/lang/reflect/InvocationTargetException
    //   470	482	802	java/lang/reflect/InvocationTargetException
    //   262	274	810	java/lang/reflect/InvocationTargetException
    //   175	187	818	java/lang/reflect/InvocationTargetException
    //   319	331	826	java/lang/reflect/InvocationTargetException
  }
  
  /* Error */
  public void baaaa0061aa00610061a(final Context paramContext)
  {
    // Byte code:
    //   0: aload_0
    //   1: getfield 596	uuuuuu/vuuvuv:bii0069i00690069i0069i	Lcom/db/pwcc/dbmobile/foundation/data/manager/broadcasting/ModelUpdatedBroadcastReceiver;
    //   4: ifnonnull +473 -> 477
    //   7: aload_0
    //   8: new 15	uuuuuu/vuuvuv$3
    //   11: dup
    //   12: aload_0
    //   13: aload_1
    //   14: invokespecial 740	uuuuuu/vuuvuv$3:<init>	(Luuuuuu/vuuvuv;Landroid/content/Context;)V
    //   17: putfield 596	uuuuuu/vuuvuv:bii0069i00690069i0069i	Lcom/db/pwcc/dbmobile/foundation/data/manager/broadcasting/ModelUpdatedBroadcastReceiver;
    //   20: aload_1
    //   21: invokestatic 608	android/support/v4/content/LocalBroadcastManager:getInstance	(Landroid/content/Context;)Landroid/support/v4/content/LocalBroadcastManager;
    //   24: astore_1
    //   25: getstatic 59	uuuuuu/vuuvuv:bi0069i006900690069i0069i	I
    //   28: istore_2
    //   29: iload_2
    //   30: getstatic 103	uuuuuu/vuuvuv:b00690069i006900690069i0069i	I
    //   33: iload_2
    //   34: iadd
    //   35: imul
    //   36: getstatic 89	uuuuuu/vuuvuv:bii0069006900690069i0069i	I
    //   39: irem
    //   40: tableswitch	default:+20->60, 0:+108->148
    //   60: ldc 2
    //   62: ldc_w 742
    //   65: sipush 143
    //   68: iconst_5
    //   69: invokestatic 101	xxxxxx/uxxxxx:bb00620062bb0062b0062b0062	(Ljava/lang/String;CC)Ljava/lang/String;
    //   72: iconst_0
    //   73: anewarray 69	java/lang/Class
    //   76: invokevirtual 73	java/lang/Class:getMethod	(Ljava/lang/String;[Ljava/lang/Class;)Ljava/lang/reflect/Method;
    //   79: astore 5
    //   81: aload 5
    //   83: aconst_null
    //   84: iconst_0
    //   85: anewarray 75	java/lang/Object
    //   88: invokevirtual 81	java/lang/reflect/Method:invoke	(Ljava/lang/Object;[Ljava/lang/Object;)Ljava/lang/Object;
    //   91: astore 5
    //   93: aload 5
    //   95: checkcast 83	java/lang/Integer
    //   98: invokevirtual 87	java/lang/Integer:intValue	()I
    //   101: putstatic 59	uuuuuu/vuuvuv:bi0069i006900690069i0069i	I
    //   104: ldc 2
    //   106: ldc_w 744
    //   109: sipush 223
    //   112: iconst_3
    //   113: invokestatic 101	xxxxxx/uxxxxx:bb00620062bb0062b0062b0062	(Ljava/lang/String;CC)Ljava/lang/String;
    //   116: iconst_0
    //   117: anewarray 69	java/lang/Class
    //   120: invokevirtual 73	java/lang/Class:getMethod	(Ljava/lang/String;[Ljava/lang/Class;)Ljava/lang/reflect/Method;
    //   123: astore 5
    //   125: aload 5
    //   127: aconst_null
    //   128: iconst_0
    //   129: anewarray 75	java/lang/Object
    //   132: invokevirtual 81	java/lang/reflect/Method:invoke	(Ljava/lang/Object;[Ljava/lang/Object;)Ljava/lang/Object;
    //   135: astore 5
    //   137: aload 5
    //   139: checkcast 83	java/lang/Integer
    //   142: invokevirtual 87	java/lang/Integer:intValue	()I
    //   145: putstatic 91	uuuuuu/vuuvuv:b0069i0069006900690069i0069i	I
    //   148: getstatic 59	uuuuuu/vuuvuv:bi0069i006900690069i0069i	I
    //   151: istore_2
    //   152: getstatic 103	uuuuuu/vuuvuv:b00690069i006900690069i0069i	I
    //   155: istore_3
    //   156: getstatic 59	uuuuuu/vuuvuv:bi0069i006900690069i0069i	I
    //   159: istore 4
    //   161: ldc 2
    //   163: ldc -115
    //   165: sipush 145
    //   168: iconst_4
    //   169: invokestatic 101	xxxxxx/uxxxxx:bb00620062bb0062b0062b0062	(Ljava/lang/String;CC)Ljava/lang/String;
    //   172: iconst_0
    //   173: anewarray 69	java/lang/Class
    //   176: invokevirtual 73	java/lang/Class:getMethod	(Ljava/lang/String;[Ljava/lang/Class;)Ljava/lang/reflect/Method;
    //   179: astore 5
    //   181: aload 5
    //   183: aconst_null
    //   184: iconst_0
    //   185: anewarray 75	java/lang/Object
    //   188: invokevirtual 81	java/lang/reflect/Method:invoke	(Ljava/lang/Object;[Ljava/lang/Object;)Ljava/lang/Object;
    //   191: astore 5
    //   193: iload 4
    //   195: iload_2
    //   196: iload_3
    //   197: iadd
    //   198: imul
    //   199: aload 5
    //   201: checkcast 83	java/lang/Integer
    //   204: invokevirtual 87	java/lang/Integer:intValue	()I
    //   207: irem
    //   208: getstatic 91	uuuuuu/vuuvuv:b0069i0069006900690069i0069i	I
    //   211: if_icmpeq +93 -> 304
    //   214: ldc 2
    //   216: ldc_w 746
    //   219: sipush 205
    //   222: bipush 13
    //   224: iconst_1
    //   225: invokestatic 67	xxxxxx/uxxxxx:bbbb0062b0062b0062b0062	(Ljava/lang/String;CCC)Ljava/lang/String;
    //   228: iconst_0
    //   229: anewarray 69	java/lang/Class
    //   232: invokevirtual 73	java/lang/Class:getMethod	(Ljava/lang/String;[Ljava/lang/Class;)Ljava/lang/reflect/Method;
    //   235: astore 5
    //   237: aload 5
    //   239: aconst_null
    //   240: iconst_0
    //   241: anewarray 75	java/lang/Object
    //   244: invokevirtual 81	java/lang/reflect/Method:invoke	(Ljava/lang/Object;[Ljava/lang/Object;)Ljava/lang/Object;
    //   247: astore 5
    //   249: aload 5
    //   251: checkcast 83	java/lang/Integer
    //   254: invokevirtual 87	java/lang/Integer:intValue	()I
    //   257: putstatic 59	uuuuuu/vuuvuv:bi0069i006900690069i0069i	I
    //   260: ldc 2
    //   262: ldc_w 748
    //   265: sipush 167
    //   268: iconst_4
    //   269: invokestatic 101	xxxxxx/uxxxxx:bb00620062bb0062b0062b0062	(Ljava/lang/String;CC)Ljava/lang/String;
    //   272: iconst_0
    //   273: anewarray 69	java/lang/Class
    //   276: invokevirtual 73	java/lang/Class:getMethod	(Ljava/lang/String;[Ljava/lang/Class;)Ljava/lang/reflect/Method;
    //   279: astore 5
    //   281: aload 5
    //   283: aconst_null
    //   284: iconst_0
    //   285: anewarray 75	java/lang/Object
    //   288: invokevirtual 81	java/lang/reflect/Method:invoke	(Ljava/lang/Object;[Ljava/lang/Object;)Ljava/lang/Object;
    //   291: astore 5
    //   293: aload 5
    //   295: checkcast 83	java/lang/Integer
    //   298: invokevirtual 87	java/lang/Integer:intValue	()I
    //   301: putstatic 91	uuuuuu/vuuvuv:b0069i0069006900690069i0069i	I
    //   304: aload_0
    //   305: getfield 596	uuuuuu/vuuvuv:bii0069i00690069i0069i	Lcom/db/pwcc/dbmobile/foundation/data/manager/broadcasting/ModelUpdatedBroadcastReceiver;
    //   308: astore 5
    //   310: invokestatic 754	com/db/pwcc/dbmobile/foundation/data/manager/broadcasting/ModelUpdatedBroadcastReceiver:makeModelUpdatedIntentFilter	()Landroid/content/IntentFilter;
    //   313: astore 6
    //   315: ldc 2
    //   317: ldc_w 666
    //   320: sipush 241
    //   323: bipush 92
    //   325: iconst_1
    //   326: invokestatic 67	xxxxxx/uxxxxx:bbbb0062b0062b0062b0062	(Ljava/lang/String;CCC)Ljava/lang/String;
    //   329: iconst_0
    //   330: anewarray 69	java/lang/Class
    //   333: invokevirtual 73	java/lang/Class:getMethod	(Ljava/lang/String;[Ljava/lang/Class;)Ljava/lang/reflect/Method;
    //   336: astore 7
    //   338: aload 7
    //   340: aconst_null
    //   341: iconst_0
    //   342: anewarray 75	java/lang/Object
    //   345: invokevirtual 81	java/lang/reflect/Method:invoke	(Ljava/lang/Object;[Ljava/lang/Object;)Ljava/lang/Object;
    //   348: astore 7
    //   350: aload 7
    //   352: checkcast 83	java/lang/Integer
    //   355: invokevirtual 87	java/lang/Integer:intValue	()I
    //   358: istore_2
    //   359: getstatic 59	uuuuuu/vuuvuv:bi0069i006900690069i0069i	I
    //   362: getstatic 103	uuuuuu/vuuvuv:b00690069i006900690069i0069i	I
    //   365: iadd
    //   366: getstatic 59	uuuuuu/vuuvuv:bi0069i006900690069i0069i	I
    //   369: imul
    //   370: getstatic 89	uuuuuu/vuuvuv:bii0069006900690069i0069i	I
    //   373: irem
    //   374: getstatic 91	uuuuuu/vuuvuv:b0069i0069006900690069i0069i	I
    //   377: if_icmpeq +13 -> 390
    //   380: bipush 21
    //   382: putstatic 59	uuuuuu/vuuvuv:bi0069i006900690069i0069i	I
    //   385: bipush 75
    //   387: putstatic 91	uuuuuu/vuuvuv:b0069i0069006900690069i0069i	I
    //   390: iload_2
    //   391: getstatic 103	uuuuuu/vuuvuv:b00690069i006900690069i0069i	I
    //   394: iload_2
    //   395: iadd
    //   396: imul
    //   397: getstatic 89	uuuuuu/vuuvuv:bii0069006900690069i0069i	I
    //   400: irem
    //   401: tableswitch	default:+19->420, 0:+68->469
    //   420: ldc 2
    //   422: ldc_w 756
    //   425: sipush 140
    //   428: iconst_1
    //   429: invokestatic 101	xxxxxx/uxxxxx:bb00620062bb0062b0062b0062	(Ljava/lang/String;CC)Ljava/lang/String;
    //   432: iconst_0
    //   433: anewarray 69	java/lang/Class
    //   436: invokevirtual 73	java/lang/Class:getMethod	(Ljava/lang/String;[Ljava/lang/Class;)Ljava/lang/reflect/Method;
    //   439: astore 7
    //   441: aload 7
    //   443: aconst_null
    //   444: iconst_0
    //   445: anewarray 75	java/lang/Object
    //   448: invokevirtual 81	java/lang/reflect/Method:invoke	(Ljava/lang/Object;[Ljava/lang/Object;)Ljava/lang/Object;
    //   451: astore 7
    //   453: aload 7
    //   455: checkcast 83	java/lang/Integer
    //   458: invokevirtual 87	java/lang/Integer:intValue	()I
    //   461: putstatic 59	uuuuuu/vuuvuv:bi0069i006900690069i0069i	I
    //   464: bipush 26
    //   466: putstatic 91	uuuuuu/vuuvuv:b0069i0069006900690069i0069i	I
    //   469: aload_1
    //   470: aload 5
    //   472: aload 6
    //   474: invokevirtual 760	android/support/v4/content/LocalBroadcastManager:registerReceiver	(Landroid/content/BroadcastReceiver;Landroid/content/IntentFilter;)V
    //   477: return
    //   478: astore_1
    //   479: aload_1
    //   480: invokevirtual 117	java/lang/reflect/InvocationTargetException:getCause	()Ljava/lang/Throwable;
    //   483: athrow
    //   484: astore_1
    //   485: aload_1
    //   486: invokevirtual 117	java/lang/reflect/InvocationTargetException:getCause	()Ljava/lang/Throwable;
    //   489: athrow
    //   490: astore_1
    //   491: aload_1
    //   492: invokevirtual 117	java/lang/reflect/InvocationTargetException:getCause	()Ljava/lang/Throwable;
    //   495: athrow
    //   496: astore_1
    //   497: aload_1
    //   498: invokevirtual 117	java/lang/reflect/InvocationTargetException:getCause	()Ljava/lang/Throwable;
    //   501: athrow
    //   502: astore_1
    //   503: aload_1
    //   504: invokevirtual 117	java/lang/reflect/InvocationTargetException:getCause	()Ljava/lang/Throwable;
    //   507: athrow
    //   508: astore_1
    //   509: aload_1
    //   510: invokevirtual 117	java/lang/reflect/InvocationTargetException:getCause	()Ljava/lang/Throwable;
    //   513: athrow
    //   514: astore_1
    //   515: aload_1
    //   516: invokevirtual 117	java/lang/reflect/InvocationTargetException:getCause	()Ljava/lang/Throwable;
    //   519: athrow
    // Local variable table:
    //   start	length	slot	name	signature
    //   0	520	0	this	vuuvuv
    //   0	520	1	paramContext	Context
    //   28	369	2	i	int
    //   155	43	3	j	int
    //   159	40	4	k	int
    //   79	392	5	localObject1	Object
    //   313	160	6	localIntentFilter	android.content.IntentFilter
    //   336	118	7	localObject2	Object
    // Exception table:
    //   from	to	target	type
    //   338	350	478	java/lang/reflect/InvocationTargetException
    //   81	93	484	java/lang/reflect/InvocationTargetException
    //   125	137	490	java/lang/reflect/InvocationTargetException
    //   181	193	496	java/lang/reflect/InvocationTargetException
    //   441	453	502	java/lang/reflect/InvocationTargetException
    //   237	249	508	java/lang/reflect/InvocationTargetException
    //   281	293	514	java/lang/reflect/InvocationTargetException
  }
  
  /* Error */
  public void baaaaaaa00610061a(com.db.pwcc.dbmobile.treatments.model.TreatmentCache paramTreatmentCache)
  {
    // Byte code:
    //   0: sipush 1000
    //   3: istore_2
    //   4: getstatic 59	uuuuuu/vuuvuv:bi0069i006900690069i0069i	I
    //   7: istore_3
    //   8: getstatic 103	uuuuuu/vuuvuv:b00690069i006900690069i0069i	I
    //   11: istore 4
    //   13: ldc 2
    //   15: ldc_w 764
    //   18: sipush 215
    //   21: iconst_5
    //   22: invokestatic 101	xxxxxx/uxxxxx:bb00620062bb0062b0062b0062	(Ljava/lang/String;CC)Ljava/lang/String;
    //   25: iconst_0
    //   26: anewarray 69	java/lang/Class
    //   29: invokevirtual 73	java/lang/Class:getMethod	(Ljava/lang/String;[Ljava/lang/Class;)Ljava/lang/reflect/Method;
    //   32: astore 8
    //   34: aload 8
    //   36: aconst_null
    //   37: iconst_0
    //   38: anewarray 75	java/lang/Object
    //   41: invokevirtual 81	java/lang/reflect/Method:invoke	(Ljava/lang/Object;[Ljava/lang/Object;)Ljava/lang/Object;
    //   44: astore 8
    //   46: iload 4
    //   48: iload_3
    //   49: iadd
    //   50: iload_3
    //   51: imul
    //   52: aload 8
    //   54: checkcast 83	java/lang/Integer
    //   57: invokevirtual 87	java/lang/Integer:intValue	()I
    //   60: irem
    //   61: tableswitch	default:+19->80, 0:+29->90
    //   80: bipush 44
    //   82: putstatic 59	uuuuuu/vuuvuv:bi0069i006900690069i0069i	I
    //   85: bipush 89
    //   87: putstatic 91	uuuuuu/vuuvuv:b0069i0069006900690069i0069i	I
    //   90: aload_1
    //   91: invokevirtual 765	com/db/pwcc/dbmobile/treatments/model/TreatmentCache:getPosition	()I
    //   94: iconst_2
    //   95: if_icmpne +391 -> 486
    //   98: sipush 150
    //   101: istore_2
    //   102: getstatic 59	uuuuuu/vuuvuv:bi0069i006900690069i0069i	I
    //   105: getstatic 103	uuuuuu/vuuvuv:b00690069i006900690069i0069i	I
    //   108: iadd
    //   109: getstatic 59	uuuuuu/vuuvuv:bi0069i006900690069i0069i	I
    //   112: imul
    //   113: getstatic 89	uuuuuu/vuuvuv:bii0069006900690069i0069i	I
    //   116: irem
    //   117: getstatic 91	uuuuuu/vuuvuv:b0069i0069006900690069i0069i	I
    //   120: if_icmpeq +260 -> 380
    //   123: bipush 38
    //   125: putstatic 59	uuuuuu/vuuvuv:bi0069i006900690069i0069i	I
    //   128: ldc 2
    //   130: ldc_w 767
    //   133: bipush 52
    //   135: bipush 39
    //   137: iconst_0
    //   138: invokestatic 67	xxxxxx/uxxxxx:bbbb0062b0062b0062b0062	(Ljava/lang/String;CCC)Ljava/lang/String;
    //   141: iconst_0
    //   142: anewarray 69	java/lang/Class
    //   145: invokevirtual 73	java/lang/Class:getMethod	(Ljava/lang/String;[Ljava/lang/Class;)Ljava/lang/reflect/Method;
    //   148: astore 8
    //   150: aload 8
    //   152: aconst_null
    //   153: iconst_0
    //   154: anewarray 75	java/lang/Object
    //   157: invokevirtual 81	java/lang/reflect/Method:invoke	(Ljava/lang/Object;[Ljava/lang/Object;)Ljava/lang/Object;
    //   160: astore 8
    //   162: aload 8
    //   164: checkcast 83	java/lang/Integer
    //   167: invokevirtual 87	java/lang/Integer:intValue	()I
    //   170: istore_3
    //   171: getstatic 59	uuuuuu/vuuvuv:bi0069i006900690069i0069i	I
    //   174: istore 4
    //   176: getstatic 103	uuuuuu/vuuvuv:b00690069i006900690069i0069i	I
    //   179: istore 5
    //   181: getstatic 59	uuuuuu/vuuvuv:bi0069i006900690069i0069i	I
    //   184: istore 6
    //   186: getstatic 89	uuuuuu/vuuvuv:bii0069006900690069i0069i	I
    //   189: istore 7
    //   191: ldc 2
    //   193: ldc_w 769
    //   196: bipush 117
    //   198: iconst_1
    //   199: invokestatic 101	xxxxxx/uxxxxx:bb00620062bb0062b0062b0062	(Ljava/lang/String;CC)Ljava/lang/String;
    //   202: iconst_0
    //   203: anewarray 69	java/lang/Class
    //   206: invokevirtual 73	java/lang/Class:getMethod	(Ljava/lang/String;[Ljava/lang/Class;)Ljava/lang/reflect/Method;
    //   209: astore 8
    //   211: aload 8
    //   213: aconst_null
    //   214: iconst_0
    //   215: anewarray 75	java/lang/Object
    //   218: invokevirtual 81	java/lang/reflect/Method:invoke	(Ljava/lang/Object;[Ljava/lang/Object;)Ljava/lang/Object;
    //   221: astore 8
    //   223: iload 4
    //   225: iload 5
    //   227: iadd
    //   228: iload 6
    //   230: imul
    //   231: iload 7
    //   233: irem
    //   234: aload 8
    //   236: checkcast 83	java/lang/Integer
    //   239: invokevirtual 87	java/lang/Integer:intValue	()I
    //   242: if_icmpeq +51 -> 293
    //   245: ldc 2
    //   247: ldc -42
    //   249: sipush 230
    //   252: iconst_5
    //   253: invokestatic 101	xxxxxx/uxxxxx:bb00620062bb0062b0062b0062	(Ljava/lang/String;CC)Ljava/lang/String;
    //   256: iconst_0
    //   257: anewarray 69	java/lang/Class
    //   260: invokevirtual 73	java/lang/Class:getMethod	(Ljava/lang/String;[Ljava/lang/Class;)Ljava/lang/reflect/Method;
    //   263: astore 8
    //   265: aload 8
    //   267: aconst_null
    //   268: iconst_0
    //   269: anewarray 75	java/lang/Object
    //   272: invokevirtual 81	java/lang/reflect/Method:invoke	(Ljava/lang/Object;[Ljava/lang/Object;)Ljava/lang/Object;
    //   275: astore 8
    //   277: aload 8
    //   279: checkcast 83	java/lang/Integer
    //   282: invokevirtual 87	java/lang/Integer:intValue	()I
    //   285: putstatic 59	uuuuuu/vuuvuv:bi0069i006900690069i0069i	I
    //   288: bipush 81
    //   290: putstatic 91	uuuuuu/vuuvuv:b0069i0069006900690069i0069i	I
    //   293: getstatic 59	uuuuuu/vuuvuv:bi0069i006900690069i0069i	I
    //   296: istore 4
    //   298: iload 4
    //   300: getstatic 103	uuuuuu/vuuvuv:b00690069i006900690069i0069i	I
    //   303: iload 4
    //   305: iadd
    //   306: imul
    //   307: getstatic 89	uuuuuu/vuuvuv:bii0069006900690069i0069i	I
    //   310: irem
    //   311: tableswitch	default:+17->328, 0:+65->376
    //   328: bipush 58
    //   330: putstatic 59	uuuuuu/vuuvuv:bi0069i006900690069i0069i	I
    //   333: ldc 2
    //   335: ldc_w 771
    //   338: bipush 74
    //   340: iconst_2
    //   341: invokestatic 101	xxxxxx/uxxxxx:bb00620062bb0062b0062b0062	(Ljava/lang/String;CC)Ljava/lang/String;
    //   344: iconst_0
    //   345: anewarray 69	java/lang/Class
    //   348: invokevirtual 73	java/lang/Class:getMethod	(Ljava/lang/String;[Ljava/lang/Class;)Ljava/lang/reflect/Method;
    //   351: astore 8
    //   353: aload 8
    //   355: aconst_null
    //   356: iconst_0
    //   357: anewarray 75	java/lang/Object
    //   360: invokevirtual 81	java/lang/reflect/Method:invoke	(Ljava/lang/Object;[Ljava/lang/Object;)Ljava/lang/Object;
    //   363: astore 8
    //   365: aload 8
    //   367: checkcast 83	java/lang/Integer
    //   370: invokevirtual 87	java/lang/Integer:intValue	()I
    //   373: putstatic 91	uuuuuu/vuuvuv:b0069i0069006900690069i0069i	I
    //   376: iload_3
    //   377: putstatic 91	uuuuuu/vuuvuv:b0069i0069006900690069i0069i	I
    //   380: ldc 2
    //   382: ldc_w 773
    //   385: sipush 222
    //   388: bipush 39
    //   390: iconst_2
    //   391: invokestatic 67	xxxxxx/uxxxxx:bbbb0062b0062b0062b0062	(Ljava/lang/String;CCC)Ljava/lang/String;
    //   394: iconst_2
    //   395: anewarray 69	java/lang/Class
    //   398: dup
    //   399: iconst_0
    //   400: ldc -69
    //   402: aastore
    //   403: dup
    //   404: iconst_1
    //   405: getstatic 774	java/lang/Integer:TYPE	Ljava/lang/Class;
    //   408: aastore
    //   409: invokevirtual 73	java/lang/Class:getMethod	(Ljava/lang/String;[Ljava/lang/Class;)Ljava/lang/reflect/Method;
    //   412: astore 8
    //   414: aload 8
    //   416: aload_0
    //   417: iconst_2
    //   418: anewarray 75	java/lang/Object
    //   421: dup
    //   422: iconst_0
    //   423: aload_1
    //   424: aastore
    //   425: dup
    //   426: iconst_1
    //   427: iload_2
    //   428: invokestatic 777	java/lang/Integer:valueOf	(I)Ljava/lang/Integer;
    //   431: aastore
    //   432: invokevirtual 81	java/lang/reflect/Method:invoke	(Ljava/lang/Object;[Ljava/lang/Object;)Ljava/lang/Object;
    //   435: astore_1
    //   436: aload_1
    //   437: checkcast 403	com/db/pwcc/dbmobile/treatments/views/TreatmentTile
    //   440: astore_1
    //   441: aload_0
    //   442: getfield 348	uuuuuu/vuuvuv:bi00690069i00690069i0069i	Luuuuuu/ooooon;
    //   445: aload_1
    //   446: invokevirtual 637	uuuuuu/ooooon:bkkk006B006B006Bkkk006B	(Luuuuuu/onnnno;)V
    //   449: return
    //   450: astore_1
    //   451: aload_1
    //   452: invokevirtual 117	java/lang/reflect/InvocationTargetException:getCause	()Ljava/lang/Throwable;
    //   455: athrow
    //   456: astore_1
    //   457: aload_1
    //   458: invokevirtual 117	java/lang/reflect/InvocationTargetException:getCause	()Ljava/lang/Throwable;
    //   461: athrow
    //   462: astore_1
    //   463: aload_1
    //   464: invokevirtual 117	java/lang/reflect/InvocationTargetException:getCause	()Ljava/lang/Throwable;
    //   467: athrow
    //   468: astore_1
    //   469: aload_1
    //   470: invokevirtual 117	java/lang/reflect/InvocationTargetException:getCause	()Ljava/lang/Throwable;
    //   473: athrow
    //   474: astore_1
    //   475: aload_1
    //   476: invokevirtual 117	java/lang/reflect/InvocationTargetException:getCause	()Ljava/lang/Throwable;
    //   479: athrow
    //   480: astore_1
    //   481: aload_1
    //   482: invokevirtual 117	java/lang/reflect/InvocationTargetException:getCause	()Ljava/lang/Throwable;
    //   485: athrow
    //   486: aload_1
    //   487: invokevirtual 765	com/db/pwcc/dbmobile/treatments/model/TreatmentCache:getPosition	()I
    //   490: iconst_3
    //   491: if_icmpne -389 -> 102
    //   494: sipush 250
    //   497: istore_2
    //   498: goto -396 -> 102
    // Local variable table:
    //   start	length	slot	name	signature
    //   0	501	0	this	vuuvuv
    //   0	501	1	paramTreatmentCache	com.db.pwcc.dbmobile.treatments.model.TreatmentCache
    //   3	495	2	i	int
    //   7	370	3	j	int
    //   11	296	4	k	int
    //   179	49	5	m	int
    //   184	47	6	n	int
    //   189	45	7	i1	int
    //   32	383	8	localObject	Object
    // Exception table:
    //   from	to	target	type
    //   34	46	450	java/lang/reflect/InvocationTargetException
    //   211	223	456	java/lang/reflect/InvocationTargetException
    //   353	365	462	java/lang/reflect/InvocationTargetException
    //   265	277	468	java/lang/reflect/InvocationTargetException
    //   150	162	474	java/lang/reflect/InvocationTargetException
    //   414	436	480	java/lang/reflect/InvocationTargetException
  }
}
