package uuuuuu;

import java.lang.reflect.InvocationTargetException;
import java.lang.reflect.Method;
import java.math.BigDecimal;
import java.util.Locale;
import java.util.regex.Pattern;
import xxxxxx.uxxxxx;

public final class vvllvv
{
  private static final String b006F006F006F006F006Foo006F006F = "403.8p'9#$#!!\037";
  public static int b006F006F006Foo006Fo006F006F = 0;
  public static final Pattern b006F006Fooo006Fo006F006F;
  public static final Pattern b006Fo006Foo006Fo006F006F;
  public static int b006Foo006Fo006Fo006F006F = 2;
  private static final String b006Foooo006Fo006F006F;
  public static final Pattern bo006F006Foo006Fo006F006F;
  public static int bo006Fo006Fo006Fo006F006F = 99;
  public static final Pattern bo006Fooo006Fo006F006F;
  public static final Pattern boo006Foo006Fo006F006F;
  public static int booo006Fo006Fo006F006F = 1;
  private static final String booooo006Fo006F006F = "wjvh6usxu\002<t\ttwxxzz";
  
  /* Error */
  static
  {
    // Byte code:
    //   0: getstatic 33	uuuuuu/vvllvv:b006F006F006F006F006Foo006F006F	Ljava/lang/String;
    //   3: astore_0
    //   4: ldc 35
    //   6: ldc 37
    //   8: sipush 134
    //   11: iconst_5
    //   12: invokestatic 43	xxxxxx/uxxxxx:bb00620062bb0062b0062b0062	(Ljava/lang/String;CC)Ljava/lang/String;
    //   15: iconst_3
    //   16: anewarray 45	java/lang/Class
    //   19: dup
    //   20: iconst_0
    //   21: ldc 47
    //   23: aastore
    //   24: dup
    //   25: iconst_1
    //   26: getstatic 53	java/lang/Character:TYPE	Ljava/lang/Class;
    //   29: aastore
    //   30: dup
    //   31: iconst_2
    //   32: getstatic 53	java/lang/Character:TYPE	Ljava/lang/Class;
    //   35: aastore
    //   36: invokevirtual 57	java/lang/Class:getMethod	(Ljava/lang/String;[Ljava/lang/Class;)Ljava/lang/reflect/Method;
    //   39: astore_1
    //   40: aload_1
    //   41: aconst_null
    //   42: iconst_3
    //   43: anewarray 4	java/lang/Object
    //   46: dup
    //   47: iconst_0
    //   48: aload_0
    //   49: aastore
    //   50: dup
    //   51: iconst_1
    //   52: bipush 28
    //   54: invokestatic 61	java/lang/Character:valueOf	(C)Ljava/lang/Character;
    //   57: aastore
    //   58: dup
    //   59: iconst_2
    //   60: iconst_4
    //   61: invokestatic 61	java/lang/Character:valueOf	(C)Ljava/lang/Character;
    //   64: aastore
    //   65: invokevirtual 67	java/lang/reflect/Method:invoke	(Ljava/lang/Object;[Ljava/lang/Object;)Ljava/lang/Object;
    //   68: astore_0
    //   69: aload_0
    //   70: checkcast 47	java/lang/String
    //   73: putstatic 33	uuuuuu/vvllvv:b006F006F006F006F006Foo006F006F	Ljava/lang/String;
    //   76: getstatic 69	uuuuuu/vvllvv:booooo006Fo006F006F	Ljava/lang/String;
    //   79: astore_0
    //   80: ldc 35
    //   82: ldc 71
    //   84: sipush 180
    //   87: iconst_2
    //   88: invokestatic 43	xxxxxx/uxxxxx:bb00620062bb0062b0062b0062	(Ljava/lang/String;CC)Ljava/lang/String;
    //   91: iconst_3
    //   92: anewarray 45	java/lang/Class
    //   95: dup
    //   96: iconst_0
    //   97: ldc 47
    //   99: aastore
    //   100: dup
    //   101: iconst_1
    //   102: getstatic 53	java/lang/Character:TYPE	Ljava/lang/Class;
    //   105: aastore
    //   106: dup
    //   107: iconst_2
    //   108: getstatic 53	java/lang/Character:TYPE	Ljava/lang/Class;
    //   111: aastore
    //   112: invokevirtual 57	java/lang/Class:getMethod	(Ljava/lang/String;[Ljava/lang/Class;)Ljava/lang/reflect/Method;
    //   115: astore_1
    //   116: aload_1
    //   117: aconst_null
    //   118: iconst_3
    //   119: anewarray 4	java/lang/Object
    //   122: dup
    //   123: iconst_0
    //   124: aload_0
    //   125: aastore
    //   126: dup
    //   127: iconst_1
    //   128: iconst_2
    //   129: invokestatic 61	java/lang/Character:valueOf	(C)Ljava/lang/Character;
    //   132: aastore
    //   133: dup
    //   134: iconst_2
    //   135: iconst_1
    //   136: invokestatic 61	java/lang/Character:valueOf	(C)Ljava/lang/Character;
    //   139: aastore
    //   140: invokevirtual 67	java/lang/reflect/Method:invoke	(Ljava/lang/Object;[Ljava/lang/Object;)Ljava/lang/Object;
    //   143: astore_0
    //   144: aload_0
    //   145: checkcast 47	java/lang/String
    //   148: putstatic 69	uuuuuu/vvllvv:booooo006Fo006F006F	Ljava/lang/String;
    //   151: ldc 2
    //   153: invokevirtual 75	java/lang/Class:getSimpleName	()Ljava/lang/String;
    //   156: putstatic 77	uuuuuu/vvllvv:b006Foooo006Fo006F006F	Ljava/lang/String;
    //   159: getstatic 79	uuuuuu/vvllvv:bo006Fo006Fo006Fo006F006F	I
    //   162: getstatic 81	uuuuuu/vvllvv:booo006Fo006Fo006F006F	I
    //   165: iadd
    //   166: getstatic 79	uuuuuu/vvllvv:bo006Fo006Fo006Fo006F006F	I
    //   169: imul
    //   170: getstatic 83	uuuuuu/vvllvv:b006Foo006Fo006Fo006F006F	I
    //   173: irem
    //   174: getstatic 85	uuuuuu/vvllvv:b006F006F006Foo006Fo006F006F	I
    //   177: if_icmpeq +15 -> 192
    //   180: invokestatic 89	uuuuuu/vvllvv:b0069i006900690069ii006900690069	()I
    //   183: putstatic 79	uuuuuu/vvllvv:bo006Fo006Fo006Fo006F006F	I
    //   186: invokestatic 89	uuuuuu/vvllvv:b0069i006900690069ii006900690069	()I
    //   189: putstatic 85	uuuuuu/vvllvv:b006F006F006Foo006Fo006F006F	I
    //   192: invokestatic 89	uuuuuu/vvllvv:b0069i006900690069ii006900690069	()I
    //   195: getstatic 81	uuuuuu/vvllvv:booo006Fo006Fo006F006F	I
    //   198: iadd
    //   199: invokestatic 89	uuuuuu/vvllvv:b0069i006900690069ii006900690069	()I
    //   202: imul
    //   203: getstatic 83	uuuuuu/vvllvv:b006Foo006Fo006Fo006F006F	I
    //   206: irem
    //   207: getstatic 85	uuuuuu/vvllvv:b006F006F006Foo006Fo006F006F	I
    //   210: if_icmpeq +9 -> 219
    //   213: invokestatic 89	uuuuuu/vvllvv:b0069i006900690069ii006900690069	()I
    //   216: putstatic 85	uuuuuu/vvllvv:b006F006F006Foo006Fo006F006F	I
    //   219: ldc 35
    //   221: ldc 91
    //   223: bipush 120
    //   225: iconst_2
    //   226: invokestatic 43	xxxxxx/uxxxxx:bb00620062bb0062b0062b0062	(Ljava/lang/String;CC)Ljava/lang/String;
    //   229: iconst_3
    //   230: anewarray 45	java/lang/Class
    //   233: dup
    //   234: iconst_0
    //   235: ldc 47
    //   237: aastore
    //   238: dup
    //   239: iconst_1
    //   240: getstatic 53	java/lang/Character:TYPE	Ljava/lang/Class;
    //   243: aastore
    //   244: dup
    //   245: iconst_2
    //   246: getstatic 53	java/lang/Character:TYPE	Ljava/lang/Class;
    //   249: aastore
    //   250: invokevirtual 57	java/lang/Class:getMethod	(Ljava/lang/String;[Ljava/lang/Class;)Ljava/lang/reflect/Method;
    //   253: astore_0
    //   254: aload_0
    //   255: aconst_null
    //   256: iconst_3
    //   257: anewarray 4	java/lang/Object
    //   260: dup
    //   261: iconst_0
    //   262: ldc 93
    //   264: aastore
    //   265: dup
    //   266: iconst_1
    //   267: bipush 120
    //   269: invokestatic 61	java/lang/Character:valueOf	(C)Ljava/lang/Character;
    //   272: aastore
    //   273: dup
    //   274: iconst_2
    //   275: iconst_5
    //   276: invokestatic 61	java/lang/Character:valueOf	(C)Ljava/lang/Character;
    //   279: aastore
    //   280: invokevirtual 67	java/lang/reflect/Method:invoke	(Ljava/lang/Object;[Ljava/lang/Object;)Ljava/lang/Object;
    //   283: astore_0
    //   284: aload_0
    //   285: checkcast 47	java/lang/String
    //   288: invokestatic 99	java/util/regex/Pattern:compile	(Ljava/lang/String;)Ljava/util/regex/Pattern;
    //   291: astore_0
    //   292: getstatic 79	uuuuuu/vvllvv:bo006Fo006Fo006Fo006F006F	I
    //   295: getstatic 81	uuuuuu/vvllvv:booo006Fo006Fo006F006F	I
    //   298: iadd
    //   299: getstatic 79	uuuuuu/vvllvv:bo006Fo006Fo006Fo006F006F	I
    //   302: imul
    //   303: getstatic 83	uuuuuu/vvllvv:b006Foo006Fo006Fo006F006F	I
    //   306: irem
    //   307: getstatic 85	uuuuuu/vvllvv:b006F006F006Foo006Fo006F006F	I
    //   310: if_icmpeq +13 -> 323
    //   313: bipush 65
    //   315: putstatic 79	uuuuuu/vvllvv:bo006Fo006Fo006Fo006F006F	I
    //   318: bipush 42
    //   320: putstatic 85	uuuuuu/vvllvv:b006F006F006Foo006Fo006F006F	I
    //   323: aload_0
    //   324: putstatic 101	uuuuuu/vvllvv:bo006Fooo006Fo006F006F	Ljava/util/regex/Pattern;
    //   327: invokestatic 89	uuuuuu/vvllvv:b0069i006900690069ii006900690069	()I
    //   330: getstatic 81	uuuuuu/vvllvv:booo006Fo006Fo006F006F	I
    //   333: iadd
    //   334: invokestatic 89	uuuuuu/vvllvv:b0069i006900690069ii006900690069	()I
    //   337: imul
    //   338: invokestatic 104	uuuuuu/vvllvv:bi0069006900690069ii006900690069	()I
    //   341: irem
    //   342: invokestatic 107	uuuuuu/vvllvv:biiiii0069i006900690069	()I
    //   345: if_icmpeq +14 -> 359
    //   348: invokestatic 89	uuuuuu/vvllvv:b0069i006900690069ii006900690069	()I
    //   351: putstatic 79	uuuuuu/vvllvv:bo006Fo006Fo006Fo006F006F	I
    //   354: bipush 15
    //   356: putstatic 85	uuuuuu/vvllvv:b006F006F006Foo006Fo006F006F	I
    //   359: ldc 35
    //   361: ldc 109
    //   363: sipush 176
    //   366: iconst_3
    //   367: invokestatic 43	xxxxxx/uxxxxx:bb00620062bb0062b0062b0062	(Ljava/lang/String;CC)Ljava/lang/String;
    //   370: iconst_3
    //   371: anewarray 45	java/lang/Class
    //   374: dup
    //   375: iconst_0
    //   376: ldc 47
    //   378: aastore
    //   379: dup
    //   380: iconst_1
    //   381: getstatic 53	java/lang/Character:TYPE	Ljava/lang/Class;
    //   384: aastore
    //   385: dup
    //   386: iconst_2
    //   387: getstatic 53	java/lang/Character:TYPE	Ljava/lang/Class;
    //   390: aastore
    //   391: invokevirtual 57	java/lang/Class:getMethod	(Ljava/lang/String;[Ljava/lang/Class;)Ljava/lang/reflect/Method;
    //   394: astore_0
    //   395: aload_0
    //   396: aconst_null
    //   397: iconst_3
    //   398: anewarray 4	java/lang/Object
    //   401: dup
    //   402: iconst_0
    //   403: ldc 111
    //   405: aastore
    //   406: dup
    //   407: iconst_1
    //   408: sipush 168
    //   411: invokestatic 61	java/lang/Character:valueOf	(C)Ljava/lang/Character;
    //   414: aastore
    //   415: dup
    //   416: iconst_2
    //   417: iconst_2
    //   418: invokestatic 61	java/lang/Character:valueOf	(C)Ljava/lang/Character;
    //   421: aastore
    //   422: invokevirtual 67	java/lang/reflect/Method:invoke	(Ljava/lang/Object;[Ljava/lang/Object;)Ljava/lang/Object;
    //   425: astore_0
    //   426: aload_0
    //   427: checkcast 47	java/lang/String
    //   430: invokestatic 99	java/util/regex/Pattern:compile	(Ljava/lang/String;)Ljava/util/regex/Pattern;
    //   433: putstatic 113	uuuuuu/vvllvv:b006F006Fooo006Fo006F006F	Ljava/util/regex/Pattern;
    //   436: ldc 35
    //   438: ldc 115
    //   440: sipush 220
    //   443: sipush 155
    //   446: iconst_2
    //   447: invokestatic 119	xxxxxx/uxxxxx:bbbb0062b0062b0062b0062	(Ljava/lang/String;CCC)Ljava/lang/String;
    //   450: iconst_4
    //   451: anewarray 45	java/lang/Class
    //   454: dup
    //   455: iconst_0
    //   456: ldc 47
    //   458: aastore
    //   459: dup
    //   460: iconst_1
    //   461: getstatic 53	java/lang/Character:TYPE	Ljava/lang/Class;
    //   464: aastore
    //   465: dup
    //   466: iconst_2
    //   467: getstatic 53	java/lang/Character:TYPE	Ljava/lang/Class;
    //   470: aastore
    //   471: dup
    //   472: iconst_3
    //   473: getstatic 53	java/lang/Character:TYPE	Ljava/lang/Class;
    //   476: aastore
    //   477: invokevirtual 57	java/lang/Class:getMethod	(Ljava/lang/String;[Ljava/lang/Class;)Ljava/lang/reflect/Method;
    //   480: astore_0
    //   481: aload_0
    //   482: aconst_null
    //   483: iconst_4
    //   484: anewarray 4	java/lang/Object
    //   487: dup
    //   488: iconst_0
    //   489: ldc 121
    //   491: aastore
    //   492: dup
    //   493: iconst_1
    //   494: sipush 206
    //   497: invokestatic 61	java/lang/Character:valueOf	(C)Ljava/lang/Character;
    //   500: aastore
    //   501: dup
    //   502: iconst_2
    //   503: sipush 248
    //   506: invokestatic 61	java/lang/Character:valueOf	(C)Ljava/lang/Character;
    //   509: aastore
    //   510: dup
    //   511: iconst_3
    //   512: iconst_3
    //   513: invokestatic 61	java/lang/Character:valueOf	(C)Ljava/lang/Character;
    //   516: aastore
    //   517: invokevirtual 67	java/lang/reflect/Method:invoke	(Ljava/lang/Object;[Ljava/lang/Object;)Ljava/lang/Object;
    //   520: astore_0
    //   521: aload_0
    //   522: checkcast 47	java/lang/String
    //   525: invokestatic 99	java/util/regex/Pattern:compile	(Ljava/lang/String;)Ljava/util/regex/Pattern;
    //   528: putstatic 123	uuuuuu/vvllvv:boo006Foo006Fo006F006F	Ljava/util/regex/Pattern;
    //   531: ldc 35
    //   533: ldc 125
    //   535: sipush 195
    //   538: iconst_2
    //   539: invokestatic 43	xxxxxx/uxxxxx:bb00620062bb0062b0062b0062	(Ljava/lang/String;CC)Ljava/lang/String;
    //   542: iconst_3
    //   543: anewarray 45	java/lang/Class
    //   546: dup
    //   547: iconst_0
    //   548: ldc 47
    //   550: aastore
    //   551: dup
    //   552: iconst_1
    //   553: getstatic 53	java/lang/Character:TYPE	Ljava/lang/Class;
    //   556: aastore
    //   557: dup
    //   558: iconst_2
    //   559: getstatic 53	java/lang/Character:TYPE	Ljava/lang/Class;
    //   562: aastore
    //   563: invokevirtual 57	java/lang/Class:getMethod	(Ljava/lang/String;[Ljava/lang/Class;)Ljava/lang/reflect/Method;
    //   566: astore_0
    //   567: aload_0
    //   568: aconst_null
    //   569: iconst_3
    //   570: anewarray 4	java/lang/Object
    //   573: dup
    //   574: iconst_0
    //   575: ldc 127
    //   577: aastore
    //   578: dup
    //   579: iconst_1
    //   580: bipush 76
    //   582: invokestatic 61	java/lang/Character:valueOf	(C)Ljava/lang/Character;
    //   585: aastore
    //   586: dup
    //   587: iconst_2
    //   588: iconst_2
    //   589: invokestatic 61	java/lang/Character:valueOf	(C)Ljava/lang/Character;
    //   592: aastore
    //   593: invokevirtual 67	java/lang/reflect/Method:invoke	(Ljava/lang/Object;[Ljava/lang/Object;)Ljava/lang/Object;
    //   596: astore_0
    //   597: aload_0
    //   598: checkcast 47	java/lang/String
    //   601: invokestatic 99	java/util/regex/Pattern:compile	(Ljava/lang/String;)Ljava/util/regex/Pattern;
    //   604: putstatic 129	uuuuuu/vvllvv:bo006F006Foo006Fo006F006F	Ljava/util/regex/Pattern;
    //   607: ldc 35
    //   609: ldc -125
    //   611: bipush 72
    //   613: iconst_0
    //   614: invokestatic 43	xxxxxx/uxxxxx:bb00620062bb0062b0062b0062	(Ljava/lang/String;CC)Ljava/lang/String;
    //   617: iconst_3
    //   618: anewarray 45	java/lang/Class
    //   621: dup
    //   622: iconst_0
    //   623: ldc 47
    //   625: aastore
    //   626: dup
    //   627: iconst_1
    //   628: getstatic 53	java/lang/Character:TYPE	Ljava/lang/Class;
    //   631: aastore
    //   632: dup
    //   633: iconst_2
    //   634: getstatic 53	java/lang/Character:TYPE	Ljava/lang/Class;
    //   637: aastore
    //   638: invokevirtual 57	java/lang/Class:getMethod	(Ljava/lang/String;[Ljava/lang/Class;)Ljava/lang/reflect/Method;
    //   641: astore_0
    //   642: aload_0
    //   643: aconst_null
    //   644: iconst_3
    //   645: anewarray 4	java/lang/Object
    //   648: dup
    //   649: iconst_0
    //   650: ldc -123
    //   652: aastore
    //   653: dup
    //   654: iconst_1
    //   655: bipush 55
    //   657: invokestatic 61	java/lang/Character:valueOf	(C)Ljava/lang/Character;
    //   660: aastore
    //   661: dup
    //   662: iconst_2
    //   663: iconst_1
    //   664: invokestatic 61	java/lang/Character:valueOf	(C)Ljava/lang/Character;
    //   667: aastore
    //   668: invokevirtual 67	java/lang/reflect/Method:invoke	(Ljava/lang/Object;[Ljava/lang/Object;)Ljava/lang/Object;
    //   671: astore_0
    //   672: aload_0
    //   673: checkcast 47	java/lang/String
    //   676: invokestatic 99	java/util/regex/Pattern:compile	(Ljava/lang/String;)Ljava/util/regex/Pattern;
    //   679: putstatic 135	uuuuuu/vvllvv:b006Fo006Foo006Fo006F006F	Ljava/util/regex/Pattern;
    //   682: return
    //   683: astore_0
    //   684: aload_0
    //   685: invokevirtual 139	java/lang/reflect/InvocationTargetException:getCause	()Ljava/lang/Throwable;
    //   688: athrow
    //   689: astore_0
    //   690: aload_0
    //   691: invokevirtual 139	java/lang/reflect/InvocationTargetException:getCause	()Ljava/lang/Throwable;
    //   694: athrow
    //   695: astore_0
    //   696: aload_0
    //   697: invokevirtual 139	java/lang/reflect/InvocationTargetException:getCause	()Ljava/lang/Throwable;
    //   700: athrow
    //   701: astore_0
    //   702: aload_0
    //   703: invokevirtual 139	java/lang/reflect/InvocationTargetException:getCause	()Ljava/lang/Throwable;
    //   706: athrow
    //   707: astore_0
    //   708: aload_0
    //   709: invokevirtual 139	java/lang/reflect/InvocationTargetException:getCause	()Ljava/lang/Throwable;
    //   712: athrow
    //   713: astore_0
    //   714: aload_0
    //   715: invokevirtual 139	java/lang/reflect/InvocationTargetException:getCause	()Ljava/lang/Throwable;
    //   718: athrow
    //   719: astore_0
    //   720: aload_0
    //   721: invokevirtual 139	java/lang/reflect/InvocationTargetException:getCause	()Ljava/lang/Throwable;
    //   724: athrow
    // Local variable table:
    //   start	length	slot	name	signature
    //   3	670	0	localObject	Object
    //   683	2	0	localInvocationTargetException1	InvocationTargetException
    //   689	2	0	localInvocationTargetException2	InvocationTargetException
    //   695	2	0	localInvocationTargetException3	InvocationTargetException
    //   701	2	0	localInvocationTargetException4	InvocationTargetException
    //   707	2	0	localInvocationTargetException5	InvocationTargetException
    //   713	2	0	localInvocationTargetException6	InvocationTargetException
    //   719	2	0	localInvocationTargetException7	InvocationTargetException
    //   39	78	1	localMethod	Method
    // Exception table:
    //   from	to	target	type
    //   40	69	683	java/lang/reflect/InvocationTargetException
    //   254	284	689	java/lang/reflect/InvocationTargetException
    //   481	521	695	java/lang/reflect/InvocationTargetException
    //   642	672	701	java/lang/reflect/InvocationTargetException
    //   116	144	707	java/lang/reflect/InvocationTargetException
    //   567	597	713	java/lang/reflect/InvocationTargetException
    //   395	426	719	java/lang/reflect/InvocationTargetException
  }
  
  private vvllvv()
  {
    Object localObject = ppphhp.class.getMethod(uxxxxx.bbbb0062b0062b0062b0062("CY\023\024\034\035^_\031\032\"#\035\036&'h\"#+,&'/0q", '®', 'Í', '\002'), new Class[] { String.class, Character.TYPE, Character.TYPE, Character.TYPE });
    try
    {
      localObject = ((Method)localObject).invoke(null, new Object[] { "]{oqmw{!ck_po", Character.valueOf('w'), Character.valueOf('þ'), Character.valueOf('\000') });
      throw new IllegalStateException((String)localObject);
    }
    catch (InvocationTargetException localInvocationTargetException)
    {
      throw localInvocationTargetException.getCause();
    }
  }
  
  public static int b00690069006900690069ii006900690069()
  {
    return 1;
  }
  
  public static boolean b00690069iii0069i006900690069(String paramString)
  {
    Object localObject = ppphhp.class.getMethod(uxxxxx.bb00620062bb0062b0062b0062("AWXYZ\024\025\035\036\030\031!\"c\035\036&'!\"*+l", '^', '\002'), new Class[] { String.class, Character.TYPE, Character.TYPE });
    try
    {
      localObject = ((Method)localObject).invoke(null, new Object[] { "\007w\002q=zvyt~7mijigge", Character.valueOf('l'), Character.valueOf('\003') });
      if (!((String)localObject).equals(paramString)) {
        localObject = ppphhp.class.getMethod(uxxxxx.bbbb0062b0062b0062b0062("Yo)*23tu/08934<=~89AB<=EF\b", 'H', '­', '\003'), new Class[] { String.class, Character.TYPE, Character.TYPE, Character.TYPE });
      }
      try
      {
        localObject = ((Method)localObject).invoke(null, new Object[] { "IEHCM\006<N898664", Character.valueOf(''), Character.valueOf('\037'), Character.valueOf('\000') });
        localObject = (String)localObject;
        if ((bo006Fo006Fo006Fo006F006F + booo006Fo006Fo006F006F) * bo006Fo006Fo006Fo006F006F % b006Foo006Fo006Fo006F006F != b006F006F006Foo006Fo006F006F)
        {
          bo006Fo006Fo006Fo006F006F = 22;
          b006F006F006Foo006Fo006F006F = 5;
        }
        if (((String)localObject).equals(paramString))
        {
          if ((bo006Fo006Fo006Fo006F006F + booo006Fo006Fo006F006F) * bo006Fo006Fo006Fo006F006F % b006Foo006Fo006Fo006F006F != b006F006F006Foo006Fo006F006F)
          {
            bo006Fo006Fo006Fo006F006F = b0069i006900690069ii006900690069();
            int i = b0069i006900690069ii006900690069();
            switch (i * (booo006Fo006Fo006F006F + i) % b006Foo006Fo006Fo006F006F)
            {
            default: 
              bo006Fo006Fo006Fo006F006F = 69;
              b006F006F006Foo006Fo006F006F = 2;
            }
            b006F006F006Foo006Fo006F006F = b0069i006900690069ii006900690069();
            return true;
          }
        }
        else
        {
          if ((bo006Fo006Fo006Fo006F006F + b00690069006900690069ii006900690069()) * bo006Fo006Fo006Fo006F006F % b006Foo006Fo006Fo006F006F != b006F006F006Foo006Fo006F006F)
          {
            bo006Fo006Fo006Fo006F006F = b0069i006900690069ii006900690069();
            b006F006F006Foo006Fo006F006F = 42;
          }
          return false;
        }
      }
      catch (InvocationTargetException paramString)
      {
        throw paramString.getCause();
      }
      return true;
    }
    catch (InvocationTargetException paramString)
    {
      throw paramString.getCause();
    }
  }
  
  public static int b0069i006900690069ii006900690069()
  {
    return 76;
  }
  
  public static String b0069iiii0069i006900690069(String paramString)
  {
    Object localObject1;
    if ((paramString != null) && (!paramString.isEmpty())) {
      localObject1 = ppphhp.class.getMethod(uxxxxx.bbbb0062b0062b0062b0062("FZYXW\017\016\024\023\013\n\020\017N\006\005\013\n\002\001\007\006E", 'à', 'Ä', '\001'), new Class[] { String.class, Character.TYPE, Character.TYPE });
    }
    try
    {
      localObject1 = ((Method)localObject1).invoke(null, new Object[] { "\024\017?D\017[!\f8:\007\t\004", Character.valueOf('\032'), Character.valueOf('\003') });
      if (!paramString.matches((String)localObject1))
      {
        localObject1 = ppphhp.class.getMethod(uxxxxx.bb00620062bb0062b0062b0062("@V\020\021\031\032[\\\026\027\037 \032\033#$e\037 ()#$,-n", 'n', '\001'), new Class[] { String.class, Character.TYPE, Character.TYPE, Character.TYPE });
        for (;;)
        {
          try
          {
            localObject1 = ((Method)localObject1).invoke(null, new Object[] { "7", Character.valueOf(''), Character.valueOf(''), Character.valueOf('\003') });
            if (!paramString.equals((String)localObject1)) {
              localObject1 = ppphhp.class.getMethod(uxxxxx.bbbb0062b0062b0062b0062("1EDCByx~}utzy9poutlkqp0", 'v', '¹', '\000'), new Class[] { String.class, Character.TYPE, Character.TYPE });
            }
          }
          catch (InvocationTargetException paramString)
          {
            try
            {
              int i;
              localObject1 = ((Method)localObject1).invoke(null, new Object[] { ">", Character.valueOf('\022'), Character.valueOf('\002') });
              localObject1 = (String)localObject1;
              localObject2 = ppphhp.class.getMethod(uxxxxx.bb00620062bb0062b0062b0062("+?vu{z:9poutlkqp0gflkcbhg'", 'Ú', '\004'), new Class[] { String.class, Character.TYPE, Character.TYPE, Character.TYPE });
            }
            catch (InvocationTargetException paramString)
            {
              Object localObject2;
              throw paramString.getCause();
            }
            try
            {
              localObject2 = ((Method)localObject2).invoke(null, new Object[] { "\027", Character.valueOf('\t'), Character.valueOf('q'), Character.valueOf('\001') });
              paramString = paramString.replace((CharSequence)localObject1, (String)localObject2);
            }
            catch (InvocationTargetException paramString)
            {
              throw paramString.getCause();
            }
            paramString = paramString;
            throw paramString.getCause();
          }
          try
          {
            localObject1 = ((Method)localObject1).invoke(null, new Object[] { "$", Character.valueOf('¦'), Character.valueOf('\000') });
            if (paramString.equals((String)localObject1)) {
              paramString = ppphhp.class.getMethod(uxxxxx.bb00620062bb0062b0062b0062("?SRQP\b\007\r\f\004\003\t\bG~}\004\003zy~>", '6', '\005'), new Class[] { String.class, Character.TYPE, Character.TYPE });
            }
          }
          catch (InvocationTargetException paramString)
          {
            try
            {
              paramString = paramString.invoke(null, new Object[] { "\f\013", Character.valueOf('m'), Character.valueOf('\001') });
              paramString = (String)paramString;
              if ((bo006Fo006Fo006Fo006F006F + booo006Fo006Fo006F006F) * bo006Fo006Fo006Fo006F006F % b006Foo006Fo006Fo006F006F != b006F006F006Foo006Fo006F006F)
              {
                bo006Fo006Fo006Fo006F006F = 42;
                b006F006F006Foo006Fo006F006F = b0069i006900690069ii006900690069();
              }
              if ((bo006Fo006Fo006Fo006F006F + booo006Fo006Fo006F006F) * bo006Fo006Fo006Fo006F006F % b006Foo006Fo006Fo006F006F != b006F006F006Foo006Fo006F006F)
              {
                bo006Fo006Fo006Fo006F006F = 77;
                b006F006F006Foo006Fo006F006F = 35;
              }
              paramString = new BigDecimal(paramString);
              if (paramString.compareTo(BigDecimal.valueOf(0.01D)) < 0) {
                break label716;
              }
              i = bo006Fo006Fo006Fo006F006F;
              switch (i * (b00690069006900690069ii006900690069() + i) % b006Foo006Fo006Fo006F006F)
              {
              default: 
                bo006Fo006Fo006Fo006F006F = b0069i006900690069ii006900690069();
                b006F006F006Foo006Fo006F006F = b0069i006900690069ii006900690069();
              }
              paramString = hhhpph.bw00770077wwwww0077w(paramString, 2, Locale.getDefault(), false);
              i = bo006Fo006Fo006Fo006F006F;
              switch (i * (booo006Fo006Fo006F006F + i) % b006Foo006Fo006Fo006F006F)
              {
              default: 
                bo006Fo006Fo006Fo006F006F = b0069i006900690069ii006900690069();
                b006F006F006Foo006Fo006F006F = b0069i006900690069ii006900690069();
              }
              return paramString;
            }
            catch (InvocationTargetException paramString)
            {
              throw paramString.getCause();
            }
            paramString = paramString;
            throw paramString.getCause();
          }
        }
        tmp543_540[0] = String.class;
        Class[] tmp548_543 = tmp543_540;
        tmp548_543[1] = Character.TYPE;
        Class[] tmp554_548 = tmp548_543;
        tmp554_548[2] = Character.TYPE;
        localObject1 = ppphhp.class.getMethod(uxxxxx.bb00620062bb0062b0062b0062("@VWXY\023\024\034\035\027\030 !b\034\035%& !)*k", 'Ü', '\002'), tmp554_548);
      }
      label716:
      return "";
    }
    catch (InvocationTargetException paramString)
    {
      throw paramString.getCause();
    }
  }
  
  public static int bi0069006900690069ii006900690069()
  {
    return 2;
  }
  
  public static BigDecimal bi0069iii0069i006900690069(String paramString)
  {
    if ((paramString == null) || (paramString.isEmpty())) {
      paramString = BigDecimal.ZERO;
    }
    for (;;)
    {
      int i = bo006Fo006Fo006Fo006F006F;
      switch (i * (booo006Fo006Fo006F006F + i) % b006Foo006Fo006Fo006F006F)
      {
      default: 
        bo006Fo006Fo006Fo006F006F = 63;
        b006F006F006Foo006Fo006F006F = b0069i006900690069ii006900690069();
      }
      return paramString;
      paramString = b0069iiii0069i006900690069(paramString);
      i = bo006Fo006Fo006Fo006F006F;
      switch (i * (booo006Fo006Fo006F006F + i) % b006Foo006Fo006Fo006F006F)
      {
      default: 
        bo006Fo006Fo006Fo006F006F = 23;
        b006F006F006Foo006Fo006F006F = 19;
      }
      if ((bo006Fo006Fo006Fo006F006F + b00690069006900690069ii006900690069()) * bo006Fo006Fo006Fo006F006F % b006Foo006Fo006Fo006F006F != b006F006F006Foo006Fo006F006F)
      {
        i = bo006Fo006Fo006Fo006F006F;
        switch (i * (booo006Fo006Fo006F006F + i) % b006Foo006Fo006Fo006F006F)
        {
        default: 
          bo006Fo006Fo006Fo006F006F = b0069i006900690069ii006900690069();
          b006F006F006Foo006Fo006F006F = b0069i006900690069ii006900690069();
        }
        bo006Fo006Fo006Fo006F006F = 76;
        b006F006F006Foo006Fo006F006F = 53;
      }
      try
      {
        paramString = new BigDecimal(paramString.replace(',', '.'));
      }
      catch (NumberFormatException paramString)
      {
        rvvvrv.bq0071qq00710071q0071q0071(b006Foooo006Fo006F006F, paramString.getMessage());
        paramString = BigDecimal.ZERO;
      }
    }
  }
  
  public static int biiiii0069i006900690069()
  {
    return 0;
  }
}
