package uuuuuu;

import com.db.pwcc.dbmobile.click4credit.model.OverdraftData;

public class vvmvvv
  extends qppppp<mmmvvv.mvmvvv>
  implements mmmvvv.vmmvvv
{
  public static int b006A006Ajjjjjj006A = 91;
  public static int b006Aj006Ajjjjj006A = 1;
  public static int bj006A006Ajjjjj006A = 2;
  public static int bjj006Ajjjjj006A;
  private OverdraftData bj006Ajjjjjj006A;
  
  public vvmvvv() {}
  
  public static int b006100610061aaaa006100610061()
  {
    return 2;
  }
  
  public static int b0061aa0061aaa006100610061()
  {
    return 1;
  }
  
  public static int ba00610061aaaa006100610061()
  {
    return 89;
  }
  
  public static int baaa0061aaa006100610061()
  {
    return 0;
  }
  
  /* Error */
  public OverdraftData b00610061aaaaa006100610061()
  {
    // Byte code:
    //   0: aload_0
    //   1: getfield 33	uuuuuu/vvmvvv:bj006Ajjjjjj006A	Lcom/db/pwcc/dbmobile/click4credit/model/OverdraftData;
    //   4: astore_2
    //   5: getstatic 35	uuuuuu/vvmvvv:b006A006Ajjjjjj006A	I
    //   8: getstatic 37	uuuuuu/vvmvvv:b006Aj006Ajjjjj006A	I
    //   11: iadd
    //   12: getstatic 35	uuuuuu/vvmvvv:b006A006Ajjjjjj006A	I
    //   15: imul
    //   16: getstatic 39	uuuuuu/vvmvvv:bj006A006Ajjjjj006A	I
    //   19: irem
    //   20: getstatic 41	uuuuuu/vvmvvv:bjj006Ajjjjj006A	I
    //   23: if_icmpeq +49 -> 72
    //   26: bipush 74
    //   28: putstatic 35	uuuuuu/vvmvvv:b006A006Ajjjjjj006A	I
    //   31: ldc 2
    //   33: ldc 43
    //   35: bipush 48
    //   37: sipush 151
    //   40: iconst_1
    //   41: invokestatic 49	xxxxxx/uxxxxx:bbbb0062b0062b0062b0062	(Ljava/lang/String;CCC)Ljava/lang/String;
    //   44: iconst_0
    //   45: anewarray 51	java/lang/Class
    //   48: invokevirtual 55	java/lang/Class:getMethod	(Ljava/lang/String;[Ljava/lang/Class;)Ljava/lang/reflect/Method;
    //   51: astore_3
    //   52: aload_3
    //   53: aconst_null
    //   54: iconst_0
    //   55: anewarray 57	java/lang/Object
    //   58: invokevirtual 63	java/lang/reflect/Method:invoke	(Ljava/lang/Object;[Ljava/lang/Object;)Ljava/lang/Object;
    //   61: astore_3
    //   62: aload_3
    //   63: checkcast 65	java/lang/Integer
    //   66: invokevirtual 68	java/lang/Integer:intValue	()I
    //   69: putstatic 41	uuuuuu/vvmvvv:bjj006Ajjjjj006A	I
    //   72: getstatic 35	uuuuuu/vvmvvv:b006A006Ajjjjjj006A	I
    //   75: getstatic 37	uuuuuu/vvmvvv:b006Aj006Ajjjjj006A	I
    //   78: iadd
    //   79: getstatic 35	uuuuuu/vvmvvv:b006A006Ajjjjjj006A	I
    //   82: imul
    //   83: getstatic 39	uuuuuu/vvmvvv:bj006A006Ajjjjj006A	I
    //   86: irem
    //   87: getstatic 41	uuuuuu/vvmvvv:bjj006Ajjjjj006A	I
    //   90: if_icmpeq +227 -> 317
    //   93: ldc 2
    //   95: ldc 70
    //   97: sipush 215
    //   100: sipush 231
    //   103: iconst_0
    //   104: invokestatic 49	xxxxxx/uxxxxx:bbbb0062b0062b0062b0062	(Ljava/lang/String;CCC)Ljava/lang/String;
    //   107: iconst_0
    //   108: anewarray 51	java/lang/Class
    //   111: invokevirtual 55	java/lang/Class:getMethod	(Ljava/lang/String;[Ljava/lang/Class;)Ljava/lang/reflect/Method;
    //   114: astore_3
    //   115: aload_3
    //   116: aconst_null
    //   117: iconst_0
    //   118: anewarray 57	java/lang/Object
    //   121: invokevirtual 63	java/lang/reflect/Method:invoke	(Ljava/lang/Object;[Ljava/lang/Object;)Ljava/lang/Object;
    //   124: astore_3
    //   125: aload_3
    //   126: checkcast 65	java/lang/Integer
    //   129: invokevirtual 68	java/lang/Integer:intValue	()I
    //   132: putstatic 35	uuuuuu/vvmvvv:b006A006Ajjjjjj006A	I
    //   135: getstatic 35	uuuuuu/vvmvvv:b006A006Ajjjjjj006A	I
    //   138: istore_1
    //   139: iload_1
    //   140: getstatic 37	uuuuuu/vvmvvv:b006Aj006Ajjjjj006A	I
    //   143: iload_1
    //   144: iadd
    //   145: imul
    //   146: getstatic 39	uuuuuu/vvmvvv:bj006A006Ajjjjj006A	I
    //   149: irem
    //   150: tableswitch	default:+18->168, 0:+61->211
    //   168: bipush 37
    //   170: putstatic 35	uuuuuu/vvmvvv:b006A006Ajjjjjj006A	I
    //   173: ldc 2
    //   175: ldc 72
    //   177: bipush 121
    //   179: iconst_1
    //   180: invokestatic 76	xxxxxx/uxxxxx:bb00620062bb0062b0062b0062	(Ljava/lang/String;CC)Ljava/lang/String;
    //   183: iconst_0
    //   184: anewarray 51	java/lang/Class
    //   187: invokevirtual 55	java/lang/Class:getMethod	(Ljava/lang/String;[Ljava/lang/Class;)Ljava/lang/reflect/Method;
    //   190: astore_3
    //   191: aload_3
    //   192: aconst_null
    //   193: iconst_0
    //   194: anewarray 57	java/lang/Object
    //   197: invokevirtual 63	java/lang/reflect/Method:invoke	(Ljava/lang/Object;[Ljava/lang/Object;)Ljava/lang/Object;
    //   200: astore_3
    //   201: aload_3
    //   202: checkcast 65	java/lang/Integer
    //   205: invokevirtual 68	java/lang/Integer:intValue	()I
    //   208: putstatic 41	uuuuuu/vvmvvv:bjj006Ajjjjj006A	I
    //   211: ldc 2
    //   213: ldc 78
    //   215: bipush 34
    //   217: bipush 32
    //   219: iconst_3
    //   220: invokestatic 49	xxxxxx/uxxxxx:bbbb0062b0062b0062b0062	(Ljava/lang/String;CCC)Ljava/lang/String;
    //   223: iconst_0
    //   224: anewarray 51	java/lang/Class
    //   227: invokevirtual 55	java/lang/Class:getMethod	(Ljava/lang/String;[Ljava/lang/Class;)Ljava/lang/reflect/Method;
    //   230: astore_3
    //   231: aload_3
    //   232: aconst_null
    //   233: iconst_0
    //   234: anewarray 57	java/lang/Object
    //   237: invokevirtual 63	java/lang/reflect/Method:invoke	(Ljava/lang/Object;[Ljava/lang/Object;)Ljava/lang/Object;
    //   240: astore_3
    //   241: aload_3
    //   242: checkcast 65	java/lang/Integer
    //   245: invokevirtual 68	java/lang/Integer:intValue	()I
    //   248: putstatic 41	uuuuuu/vvmvvv:bjj006Ajjjjj006A	I
    //   251: getstatic 35	uuuuuu/vvmvvv:b006A006Ajjjjjj006A	I
    //   254: getstatic 37	uuuuuu/vvmvvv:b006Aj006Ajjjjj006A	I
    //   257: iadd
    //   258: getstatic 35	uuuuuu/vvmvvv:b006A006Ajjjjjj006A	I
    //   261: imul
    //   262: getstatic 39	uuuuuu/vvmvvv:bj006A006Ajjjjj006A	I
    //   265: irem
    //   266: getstatic 41	uuuuuu/vvmvvv:bjj006Ajjjjj006A	I
    //   269: if_icmpeq +48 -> 317
    //   272: bipush 78
    //   274: putstatic 35	uuuuuu/vvmvvv:b006A006Ajjjjjj006A	I
    //   277: ldc 2
    //   279: ldc 80
    //   281: bipush 82
    //   283: bipush 37
    //   285: iconst_2
    //   286: invokestatic 49	xxxxxx/uxxxxx:bbbb0062b0062b0062b0062	(Ljava/lang/String;CCC)Ljava/lang/String;
    //   289: iconst_0
    //   290: anewarray 51	java/lang/Class
    //   293: invokevirtual 55	java/lang/Class:getMethod	(Ljava/lang/String;[Ljava/lang/Class;)Ljava/lang/reflect/Method;
    //   296: astore_3
    //   297: aload_3
    //   298: aconst_null
    //   299: iconst_0
    //   300: anewarray 57	java/lang/Object
    //   303: invokevirtual 63	java/lang/reflect/Method:invoke	(Ljava/lang/Object;[Ljava/lang/Object;)Ljava/lang/Object;
    //   306: astore_3
    //   307: aload_3
    //   308: checkcast 65	java/lang/Integer
    //   311: invokevirtual 68	java/lang/Integer:intValue	()I
    //   314: putstatic 41	uuuuuu/vvmvvv:bjj006Ajjjjj006A	I
    //   317: aload_2
    //   318: areturn
    //   319: astore_2
    //   320: aload_2
    //   321: invokevirtual 84	java/lang/reflect/InvocationTargetException:getCause	()Ljava/lang/Throwable;
    //   324: athrow
    //   325: astore_2
    //   326: aload_2
    //   327: invokevirtual 84	java/lang/reflect/InvocationTargetException:getCause	()Ljava/lang/Throwable;
    //   330: athrow
    //   331: astore_2
    //   332: aload_2
    //   333: invokevirtual 84	java/lang/reflect/InvocationTargetException:getCause	()Ljava/lang/Throwable;
    //   336: athrow
    //   337: astore_2
    //   338: aload_2
    //   339: invokevirtual 84	java/lang/reflect/InvocationTargetException:getCause	()Ljava/lang/Throwable;
    //   342: athrow
    //   343: astore_2
    //   344: aload_2
    //   345: invokevirtual 84	java/lang/reflect/InvocationTargetException:getCause	()Ljava/lang/Throwable;
    //   348: athrow
    // Local variable table:
    //   start	length	slot	name	signature
    //   0	349	0	this	vvmvvv
    //   138	8	1	i	int
    //   4	314	2	localOverdraftData	OverdraftData
    //   319	2	2	localInvocationTargetException1	java.lang.reflect.InvocationTargetException
    //   325	2	2	localInvocationTargetException2	java.lang.reflect.InvocationTargetException
    //   331	2	2	localInvocationTargetException3	java.lang.reflect.InvocationTargetException
    //   337	2	2	localInvocationTargetException4	java.lang.reflect.InvocationTargetException
    //   343	2	2	localInvocationTargetException5	java.lang.reflect.InvocationTargetException
    //   51	257	3	localObject	Object
    // Exception table:
    //   from	to	target	type
    //   52	62	319	java/lang/reflect/InvocationTargetException
    //   115	125	325	java/lang/reflect/InvocationTargetException
    //   231	241	331	java/lang/reflect/InvocationTargetException
    //   297	307	337	java/lang/reflect/InvocationTargetException
    //   191	201	343	java/lang/reflect/InvocationTargetException
  }
  
  /* Error */
  public void b0061a0061aaaa006100610061(OverdraftData paramOverdraftData)
  {
    // Byte code:
    //   0: aload_0
    //   1: aload_1
    //   2: putfield 33	uuuuuu/vvmvvv:bj006Ajjjjjj006A	Lcom/db/pwcc/dbmobile/click4credit/model/OverdraftData;
    //   5: getstatic 35	uuuuuu/vvmvvv:b006A006Ajjjjjj006A	I
    //   8: istore_2
    //   9: getstatic 37	uuuuuu/vvmvvv:b006Aj006Ajjjjj006A	I
    //   12: istore_3
    //   13: getstatic 39	uuuuuu/vvmvvv:bj006A006Ajjjjj006A	I
    //   16: istore 4
    //   18: getstatic 35	uuuuuu/vvmvvv:b006A006Ajjjjjj006A	I
    //   21: istore 5
    //   23: ldc 2
    //   25: ldc 88
    //   27: bipush 72
    //   29: iconst_1
    //   30: invokestatic 76	xxxxxx/uxxxxx:bb00620062bb0062b0062b0062	(Ljava/lang/String;CC)Ljava/lang/String;
    //   33: iconst_0
    //   34: anewarray 51	java/lang/Class
    //   37: invokevirtual 55	java/lang/Class:getMethod	(Ljava/lang/String;[Ljava/lang/Class;)Ljava/lang/reflect/Method;
    //   40: astore_1
    //   41: aload_1
    //   42: aconst_null
    //   43: iconst_0
    //   44: anewarray 57	java/lang/Object
    //   47: invokevirtual 63	java/lang/reflect/Method:invoke	(Ljava/lang/Object;[Ljava/lang/Object;)Ljava/lang/Object;
    //   50: astore_1
    //   51: aload_1
    //   52: checkcast 65	java/lang/Integer
    //   55: invokevirtual 68	java/lang/Integer:intValue	()I
    //   58: istore 6
    //   60: getstatic 35	uuuuuu/vvmvvv:b006A006Ajjjjjj006A	I
    //   63: istore 7
    //   65: getstatic 35	uuuuuu/vvmvvv:b006A006Ajjjjjj006A	I
    //   68: istore 8
    //   70: getstatic 37	uuuuuu/vvmvvv:b006Aj006Ajjjjj006A	I
    //   73: istore 9
    //   75: getstatic 35	uuuuuu/vvmvvv:b006A006Ajjjjjj006A	I
    //   78: istore 10
    //   80: getstatic 39	uuuuuu/vvmvvv:bj006A006Ajjjjj006A	I
    //   83: istore 11
    //   85: ldc 2
    //   87: ldc 90
    //   89: sipush 143
    //   92: iconst_5
    //   93: invokestatic 76	xxxxxx/uxxxxx:bb00620062bb0062b0062b0062	(Ljava/lang/String;CC)Ljava/lang/String;
    //   96: iconst_0
    //   97: anewarray 51	java/lang/Class
    //   100: invokevirtual 55	java/lang/Class:getMethod	(Ljava/lang/String;[Ljava/lang/Class;)Ljava/lang/reflect/Method;
    //   103: astore_1
    //   104: aload_1
    //   105: aconst_null
    //   106: iconst_0
    //   107: anewarray 57	java/lang/Object
    //   110: invokevirtual 63	java/lang/reflect/Method:invoke	(Ljava/lang/Object;[Ljava/lang/Object;)Ljava/lang/Object;
    //   113: astore_1
    //   114: iload 8
    //   116: iload 9
    //   118: iadd
    //   119: iload 10
    //   121: imul
    //   122: iload 11
    //   124: irem
    //   125: aload_1
    //   126: checkcast 65	java/lang/Integer
    //   129: invokevirtual 68	java/lang/Integer:intValue	()I
    //   132: if_icmpeq +81 -> 213
    //   135: ldc 2
    //   137: ldc 92
    //   139: sipush 142
    //   142: iconst_2
    //   143: invokestatic 76	xxxxxx/uxxxxx:bb00620062bb0062b0062b0062	(Ljava/lang/String;CC)Ljava/lang/String;
    //   146: iconst_0
    //   147: anewarray 51	java/lang/Class
    //   150: invokevirtual 55	java/lang/Class:getMethod	(Ljava/lang/String;[Ljava/lang/Class;)Ljava/lang/reflect/Method;
    //   153: astore_1
    //   154: aload_1
    //   155: aconst_null
    //   156: iconst_0
    //   157: anewarray 57	java/lang/Object
    //   160: invokevirtual 63	java/lang/reflect/Method:invoke	(Ljava/lang/Object;[Ljava/lang/Object;)Ljava/lang/Object;
    //   163: astore_1
    //   164: aload_1
    //   165: checkcast 65	java/lang/Integer
    //   168: invokevirtual 68	java/lang/Integer:intValue	()I
    //   171: putstatic 35	uuuuuu/vvmvvv:b006A006Ajjjjjj006A	I
    //   174: ldc 2
    //   176: ldc 94
    //   178: sipush 191
    //   181: iconst_3
    //   182: invokestatic 76	xxxxxx/uxxxxx:bb00620062bb0062b0062b0062	(Ljava/lang/String;CC)Ljava/lang/String;
    //   185: iconst_0
    //   186: anewarray 51	java/lang/Class
    //   189: invokevirtual 55	java/lang/Class:getMethod	(Ljava/lang/String;[Ljava/lang/Class;)Ljava/lang/reflect/Method;
    //   192: astore_1
    //   193: aload_1
    //   194: aconst_null
    //   195: iconst_0
    //   196: anewarray 57	java/lang/Object
    //   199: invokevirtual 63	java/lang/reflect/Method:invoke	(Ljava/lang/Object;[Ljava/lang/Object;)Ljava/lang/Object;
    //   202: astore_1
    //   203: aload_1
    //   204: checkcast 65	java/lang/Integer
    //   207: invokevirtual 68	java/lang/Integer:intValue	()I
    //   210: putstatic 41	uuuuuu/vvmvvv:bjj006Ajjjjj006A	I
    //   213: iload 7
    //   215: iload 6
    //   217: iload 5
    //   219: iadd
    //   220: imul
    //   221: getstatic 39	uuuuuu/vvmvvv:bj006A006Ajjjjj006A	I
    //   224: irem
    //   225: getstatic 41	uuuuuu/vvmvvv:bjj006Ajjjjj006A	I
    //   228: if_icmpeq +13 -> 241
    //   231: bipush 51
    //   233: putstatic 35	uuuuuu/vvmvvv:b006A006Ajjjjjj006A	I
    //   236: bipush 41
    //   238: putstatic 41	uuuuuu/vvmvvv:bjj006Ajjjjj006A	I
    //   241: iload_3
    //   242: iload_2
    //   243: iadd
    //   244: iload_2
    //   245: imul
    //   246: iload 4
    //   248: irem
    //   249: tableswitch	default:+19->268, 0:+166->415
    //   268: bipush 79
    //   270: putstatic 35	uuuuuu/vvmvvv:b006A006Ajjjjjj006A	I
    //   273: bipush 44
    //   275: putstatic 41	uuuuuu/vvmvvv:bjj006Ajjjjj006A	I
    //   278: ldc 2
    //   280: ldc 96
    //   282: sipush 160
    //   285: sipush 141
    //   288: iconst_2
    //   289: invokestatic 49	xxxxxx/uxxxxx:bbbb0062b0062b0062b0062	(Ljava/lang/String;CCC)Ljava/lang/String;
    //   292: iconst_0
    //   293: anewarray 51	java/lang/Class
    //   296: invokevirtual 55	java/lang/Class:getMethod	(Ljava/lang/String;[Ljava/lang/Class;)Ljava/lang/reflect/Method;
    //   299: astore_1
    //   300: aload_1
    //   301: aconst_null
    //   302: iconst_0
    //   303: anewarray 57	java/lang/Object
    //   306: invokevirtual 63	java/lang/reflect/Method:invoke	(Ljava/lang/Object;[Ljava/lang/Object;)Ljava/lang/Object;
    //   309: astore_1
    //   310: aload_1
    //   311: checkcast 65	java/lang/Integer
    //   314: invokevirtual 68	java/lang/Integer:intValue	()I
    //   317: istore_2
    //   318: getstatic 37	uuuuuu/vvmvvv:b006Aj006Ajjjjj006A	I
    //   321: istore_3
    //   322: ldc 2
    //   324: ldc 98
    //   326: bipush 81
    //   328: iconst_5
    //   329: invokestatic 76	xxxxxx/uxxxxx:bb00620062bb0062b0062b0062	(Ljava/lang/String;CC)Ljava/lang/String;
    //   332: iconst_0
    //   333: anewarray 51	java/lang/Class
    //   336: invokevirtual 55	java/lang/Class:getMethod	(Ljava/lang/String;[Ljava/lang/Class;)Ljava/lang/reflect/Method;
    //   339: astore_1
    //   340: aload_1
    //   341: aconst_null
    //   342: iconst_0
    //   343: anewarray 57	java/lang/Object
    //   346: invokevirtual 63	java/lang/reflect/Method:invoke	(Ljava/lang/Object;[Ljava/lang/Object;)Ljava/lang/Object;
    //   349: astore_1
    //   350: aload_1
    //   351: checkcast 65	java/lang/Integer
    //   354: invokevirtual 68	java/lang/Integer:intValue	()I
    //   357: iload_3
    //   358: iload_2
    //   359: iadd
    //   360: imul
    //   361: getstatic 39	uuuuuu/vvmvvv:bj006A006Ajjjjj006A	I
    //   364: irem
    //   365: getstatic 41	uuuuuu/vvmvvv:bjj006Ajjjjj006A	I
    //   368: if_icmpeq +47 -> 415
    //   371: ldc 2
    //   373: ldc 100
    //   375: sipush 177
    //   378: iconst_4
    //   379: invokestatic 76	xxxxxx/uxxxxx:bb00620062bb0062b0062b0062	(Ljava/lang/String;CC)Ljava/lang/String;
    //   382: iconst_0
    //   383: anewarray 51	java/lang/Class
    //   386: invokevirtual 55	java/lang/Class:getMethod	(Ljava/lang/String;[Ljava/lang/Class;)Ljava/lang/reflect/Method;
    //   389: astore_1
    //   390: aload_1
    //   391: aconst_null
    //   392: iconst_0
    //   393: anewarray 57	java/lang/Object
    //   396: invokevirtual 63	java/lang/reflect/Method:invoke	(Ljava/lang/Object;[Ljava/lang/Object;)Ljava/lang/Object;
    //   399: astore_1
    //   400: aload_1
    //   401: checkcast 65	java/lang/Integer
    //   404: invokevirtual 68	java/lang/Integer:intValue	()I
    //   407: putstatic 35	uuuuuu/vvmvvv:b006A006Ajjjjjj006A	I
    //   410: bipush 85
    //   412: putstatic 41	uuuuuu/vvmvvv:bjj006Ajjjjj006A	I
    //   415: return
    //   416: astore_1
    //   417: aload_1
    //   418: invokevirtual 84	java/lang/reflect/InvocationTargetException:getCause	()Ljava/lang/Throwable;
    //   421: athrow
    //   422: astore_1
    //   423: aload_1
    //   424: invokevirtual 84	java/lang/reflect/InvocationTargetException:getCause	()Ljava/lang/Throwable;
    //   427: athrow
    //   428: astore_1
    //   429: aload_1
    //   430: invokevirtual 84	java/lang/reflect/InvocationTargetException:getCause	()Ljava/lang/Throwable;
    //   433: athrow
    //   434: astore_1
    //   435: aload_1
    //   436: invokevirtual 84	java/lang/reflect/InvocationTargetException:getCause	()Ljava/lang/Throwable;
    //   439: athrow
    //   440: astore_1
    //   441: aload_1
    //   442: invokevirtual 84	java/lang/reflect/InvocationTargetException:getCause	()Ljava/lang/Throwable;
    //   445: athrow
    //   446: astore_1
    //   447: aload_1
    //   448: invokevirtual 84	java/lang/reflect/InvocationTargetException:getCause	()Ljava/lang/Throwable;
    //   451: athrow
    //   452: astore_1
    //   453: aload_1
    //   454: invokevirtual 84	java/lang/reflect/InvocationTargetException:getCause	()Ljava/lang/Throwable;
    //   457: athrow
    // Local variable table:
    //   start	length	slot	name	signature
    //   0	458	0	this	vvmvvv
    //   0	458	1	paramOverdraftData	OverdraftData
    //   8	352	2	i	int
    //   12	348	3	j	int
    //   16	233	4	k	int
    //   21	199	5	m	int
    //   58	162	6	n	int
    //   63	158	7	i1	int
    //   68	51	8	i2	int
    //   73	46	9	i3	int
    //   78	44	10	i4	int
    //   83	42	11	i5	int
    // Exception table:
    //   from	to	target	type
    //   390	400	416	java/lang/reflect/InvocationTargetException
    //   41	51	422	java/lang/reflect/InvocationTargetException
    //   104	114	428	java/lang/reflect/InvocationTargetException
    //   300	310	434	java/lang/reflect/InvocationTargetException
    //   340	350	440	java/lang/reflect/InvocationTargetException
    //   154	164	446	java/lang/reflect/InvocationTargetException
    //   193	203	452	java/lang/reflect/InvocationTargetException
  }
  
  /* Error */
  public void baa0061aaaa006100610061(int paramInt)
  {
    // Byte code:
    //   0: iload_1
    //   1: ifne +377 -> 378
    //   4: getstatic 35	uuuuuu/vvmvvv:b006A006Ajjjjjj006A	I
    //   7: istore_1
    //   8: ldc 2
    //   10: ldc 104
    //   12: bipush 26
    //   14: bipush 74
    //   16: iconst_2
    //   17: invokestatic 49	xxxxxx/uxxxxx:bbbb0062b0062b0062b0062	(Ljava/lang/String;CCC)Ljava/lang/String;
    //   20: iconst_0
    //   21: anewarray 51	java/lang/Class
    //   24: invokevirtual 55	java/lang/Class:getMethod	(Ljava/lang/String;[Ljava/lang/Class;)Ljava/lang/reflect/Method;
    //   27: astore_3
    //   28: aload_3
    //   29: aconst_null
    //   30: iconst_0
    //   31: anewarray 57	java/lang/Object
    //   34: invokevirtual 63	java/lang/reflect/Method:invoke	(Ljava/lang/Object;[Ljava/lang/Object;)Ljava/lang/Object;
    //   37: astore_3
    //   38: aload_3
    //   39: checkcast 65	java/lang/Integer
    //   42: invokevirtual 68	java/lang/Integer:intValue	()I
    //   45: istore_2
    //   46: ldc 2
    //   48: ldc 106
    //   50: bipush 64
    //   52: bipush 25
    //   54: iconst_2
    //   55: invokestatic 49	xxxxxx/uxxxxx:bbbb0062b0062b0062b0062	(Ljava/lang/String;CCC)Ljava/lang/String;
    //   58: iconst_0
    //   59: anewarray 51	java/lang/Class
    //   62: invokevirtual 55	java/lang/Class:getMethod	(Ljava/lang/String;[Ljava/lang/Class;)Ljava/lang/reflect/Method;
    //   65: astore_3
    //   66: aload_3
    //   67: aconst_null
    //   68: iconst_0
    //   69: anewarray 57	java/lang/Object
    //   72: invokevirtual 63	java/lang/reflect/Method:invoke	(Ljava/lang/Object;[Ljava/lang/Object;)Ljava/lang/Object;
    //   75: astore_3
    //   76: iload_1
    //   77: iload_2
    //   78: iload_1
    //   79: iadd
    //   80: imul
    //   81: aload_3
    //   82: checkcast 65	java/lang/Integer
    //   85: invokevirtual 68	java/lang/Integer:intValue	()I
    //   88: irem
    //   89: tableswitch	default:+19->108, 0:+270->359
    //   108: bipush 32
    //   110: putstatic 35	uuuuuu/vvmvvv:b006A006Ajjjjjj006A	I
    //   113: bipush 59
    //   115: putstatic 41	uuuuuu/vvmvvv:bjj006Ajjjjj006A	I
    //   118: getstatic 35	uuuuuu/vvmvvv:b006A006Ajjjjjj006A	I
    //   121: getstatic 37	uuuuuu/vvmvvv:b006Aj006Ajjjjj006A	I
    //   124: iadd
    //   125: getstatic 35	uuuuuu/vvmvvv:b006A006Ajjjjjj006A	I
    //   128: imul
    //   129: getstatic 39	uuuuuu/vvmvvv:bj006A006Ajjjjj006A	I
    //   132: irem
    //   133: getstatic 41	uuuuuu/vvmvvv:bjj006Ajjjjj006A	I
    //   136: if_icmpeq +223 -> 359
    //   139: getstatic 35	uuuuuu/vvmvvv:b006A006Ajjjjjj006A	I
    //   142: istore_1
    //   143: ldc 2
    //   145: ldc 108
    //   147: sipush 147
    //   150: iconst_4
    //   151: invokestatic 76	xxxxxx/uxxxxx:bb00620062bb0062b0062b0062	(Ljava/lang/String;CC)Ljava/lang/String;
    //   154: iconst_0
    //   155: anewarray 51	java/lang/Class
    //   158: invokevirtual 55	java/lang/Class:getMethod	(Ljava/lang/String;[Ljava/lang/Class;)Ljava/lang/reflect/Method;
    //   161: astore_3
    //   162: aload_3
    //   163: aconst_null
    //   164: iconst_0
    //   165: anewarray 57	java/lang/Object
    //   168: invokevirtual 63	java/lang/reflect/Method:invoke	(Ljava/lang/Object;[Ljava/lang/Object;)Ljava/lang/Object;
    //   171: astore_3
    //   172: aload_3
    //   173: checkcast 65	java/lang/Integer
    //   176: invokevirtual 68	java/lang/Integer:intValue	()I
    //   179: iload_1
    //   180: iadd
    //   181: iload_1
    //   182: imul
    //   183: getstatic 39	uuuuuu/vvmvvv:bj006A006Ajjjjj006A	I
    //   186: irem
    //   187: tableswitch	default:+17->204, 0:+63->250
    //   204: ldc 2
    //   206: ldc 110
    //   208: sipush 139
    //   211: bipush 76
    //   213: iconst_0
    //   214: invokestatic 49	xxxxxx/uxxxxx:bbbb0062b0062b0062b0062	(Ljava/lang/String;CCC)Ljava/lang/String;
    //   217: iconst_0
    //   218: anewarray 51	java/lang/Class
    //   221: invokevirtual 55	java/lang/Class:getMethod	(Ljava/lang/String;[Ljava/lang/Class;)Ljava/lang/reflect/Method;
    //   224: astore_3
    //   225: aload_3
    //   226: aconst_null
    //   227: iconst_0
    //   228: anewarray 57	java/lang/Object
    //   231: invokevirtual 63	java/lang/reflect/Method:invoke	(Ljava/lang/Object;[Ljava/lang/Object;)Ljava/lang/Object;
    //   234: astore_3
    //   235: aload_3
    //   236: checkcast 65	java/lang/Integer
    //   239: invokevirtual 68	java/lang/Integer:intValue	()I
    //   242: putstatic 35	uuuuuu/vvmvvv:b006A006Ajjjjjj006A	I
    //   245: bipush 41
    //   247: putstatic 41	uuuuuu/vvmvvv:bjj006Ajjjjj006A	I
    //   250: ldc 2
    //   252: ldc 112
    //   254: bipush 38
    //   256: sipush 162
    //   259: iconst_3
    //   260: invokestatic 49	xxxxxx/uxxxxx:bbbb0062b0062b0062b0062	(Ljava/lang/String;CCC)Ljava/lang/String;
    //   263: iconst_0
    //   264: anewarray 51	java/lang/Class
    //   267: invokevirtual 55	java/lang/Class:getMethod	(Ljava/lang/String;[Ljava/lang/Class;)Ljava/lang/reflect/Method;
    //   270: astore_3
    //   271: aload_3
    //   272: aconst_null
    //   273: iconst_0
    //   274: anewarray 57	java/lang/Object
    //   277: invokevirtual 63	java/lang/reflect/Method:invoke	(Ljava/lang/Object;[Ljava/lang/Object;)Ljava/lang/Object;
    //   280: astore_3
    //   281: aload_3
    //   282: checkcast 65	java/lang/Integer
    //   285: invokevirtual 68	java/lang/Integer:intValue	()I
    //   288: putstatic 35	uuuuuu/vvmvvv:b006A006Ajjjjjj006A	I
    //   291: iconst_2
    //   292: putstatic 41	uuuuuu/vvmvvv:bjj006Ajjjjj006A	I
    //   295: getstatic 35	uuuuuu/vvmvvv:b006A006Ajjjjjj006A	I
    //   298: getstatic 37	uuuuuu/vvmvvv:b006Aj006Ajjjjj006A	I
    //   301: iadd
    //   302: getstatic 35	uuuuuu/vvmvvv:b006A006Ajjjjjj006A	I
    //   305: imul
    //   306: getstatic 39	uuuuuu/vvmvvv:bj006A006Ajjjjj006A	I
    //   309: irem
    //   310: getstatic 41	uuuuuu/vvmvvv:bjj006Ajjjjj006A	I
    //   313: if_icmpeq +46 -> 359
    //   316: bipush 90
    //   318: putstatic 35	uuuuuu/vvmvvv:b006A006Ajjjjjj006A	I
    //   321: ldc 2
    //   323: ldc 114
    //   325: bipush 117
    //   327: iconst_5
    //   328: invokestatic 76	xxxxxx/uxxxxx:bb00620062bb0062b0062b0062	(Ljava/lang/String;CC)Ljava/lang/String;
    //   331: iconst_0
    //   332: anewarray 51	java/lang/Class
    //   335: invokevirtual 55	java/lang/Class:getMethod	(Ljava/lang/String;[Ljava/lang/Class;)Ljava/lang/reflect/Method;
    //   338: astore_3
    //   339: aload_3
    //   340: aconst_null
    //   341: iconst_0
    //   342: anewarray 57	java/lang/Object
    //   345: invokevirtual 63	java/lang/reflect/Method:invoke	(Ljava/lang/Object;[Ljava/lang/Object;)Ljava/lang/Object;
    //   348: astore_3
    //   349: aload_3
    //   350: checkcast 65	java/lang/Integer
    //   353: invokevirtual 68	java/lang/Integer:intValue	()I
    //   356: putstatic 41	uuuuuu/vvmvvv:bjj006Ajjjjj006A	I
    //   359: aload_0
    //   360: getfield 118	uuuuuu/vvmvvv:bnnnnn006E006E006En	Luuuuuu/ttssst$tsssst;
    //   363: checkcast 120	uuuuuu/mmmvvv$mvmvvv
    //   366: invokeinterface 123 1 0
    //   371: return
    //   372: astore_3
    //   373: aload_3
    //   374: invokevirtual 84	java/lang/reflect/InvocationTargetException:getCause	()Ljava/lang/Throwable;
    //   377: athrow
    //   378: aload_0
    //   379: getfield 118	uuuuuu/vvmvvv:bnnnnn006E006E006En	Luuuuuu/ttssst$tsssst;
    //   382: checkcast 120	uuuuuu/mmmvvv$mvmvvv
    //   385: invokeinterface 126 1 0
    //   390: return
    //   391: astore_3
    //   392: aload_3
    //   393: invokevirtual 84	java/lang/reflect/InvocationTargetException:getCause	()Ljava/lang/Throwable;
    //   396: athrow
    //   397: astore_3
    //   398: aload_3
    //   399: invokevirtual 84	java/lang/reflect/InvocationTargetException:getCause	()Ljava/lang/Throwable;
    //   402: athrow
    //   403: astore_3
    //   404: aload_3
    //   405: invokevirtual 84	java/lang/reflect/InvocationTargetException:getCause	()Ljava/lang/Throwable;
    //   408: athrow
    //   409: astore_3
    //   410: aload_3
    //   411: invokevirtual 84	java/lang/reflect/InvocationTargetException:getCause	()Ljava/lang/Throwable;
    //   414: athrow
    //   415: astore_3
    //   416: aload_3
    //   417: invokevirtual 84	java/lang/reflect/InvocationTargetException:getCause	()Ljava/lang/Throwable;
    //   420: athrow
    // Local variable table:
    //   start	length	slot	name	signature
    //   0	421	0	this	vvmvvv
    //   0	421	1	paramInt	int
    //   45	35	2	i	int
    //   27	323	3	localObject	Object
    //   372	2	3	localInvocationTargetException1	java.lang.reflect.InvocationTargetException
    //   391	2	3	localInvocationTargetException2	java.lang.reflect.InvocationTargetException
    //   397	2	3	localInvocationTargetException3	java.lang.reflect.InvocationTargetException
    //   403	2	3	localInvocationTargetException4	java.lang.reflect.InvocationTargetException
    //   409	2	3	localInvocationTargetException5	java.lang.reflect.InvocationTargetException
    //   415	2	3	localInvocationTargetException6	java.lang.reflect.InvocationTargetException
    // Exception table:
    //   from	to	target	type
    //   28	38	372	java/lang/reflect/InvocationTargetException
    //   66	76	391	java/lang/reflect/InvocationTargetException
    //   162	172	397	java/lang/reflect/InvocationTargetException
    //   271	281	403	java/lang/reflect/InvocationTargetException
    //   339	349	409	java/lang/reflect/InvocationTargetException
    //   225	235	415	java/lang/reflect/InvocationTargetException
  }
}
