package uuuuuu;

public enum vvvkkk
{
  private String b006300630063c0063cc0063c;
  private String bccc00630063cc0063c;
  
  /* Error */
  static
  {
    // Byte code:
    //   0: ldc 23
    //   2: ldc 25
    //   4: bipush 88
    //   6: iconst_5
    //   7: invokestatic 31	xxxxxx/uxxxxx:bb00620062bb0062b0062b0062	(Ljava/lang/String;CC)Ljava/lang/String;
    //   10: iconst_4
    //   11: anewarray 33	java/lang/Class
    //   14: dup
    //   15: iconst_0
    //   16: ldc 35
    //   18: aastore
    //   19: dup
    //   20: iconst_1
    //   21: getstatic 41	java/lang/Character:TYPE	Ljava/lang/Class;
    //   24: aastore
    //   25: dup
    //   26: iconst_2
    //   27: getstatic 41	java/lang/Character:TYPE	Ljava/lang/Class;
    //   30: aastore
    //   31: dup
    //   32: iconst_3
    //   33: getstatic 41	java/lang/Character:TYPE	Ljava/lang/Class;
    //   36: aastore
    //   37: invokevirtual 45	java/lang/Class:getMethod	(Ljava/lang/String;[Ljava/lang/Class;)Ljava/lang/reflect/Method;
    //   40: astore_1
    //   41: aload_1
    //   42: aconst_null
    //   43: iconst_4
    //   44: anewarray 47	java/lang/Object
    //   47: dup
    //   48: iconst_0
    //   49: ldc 49
    //   51: aastore
    //   52: dup
    //   53: iconst_1
    //   54: sipush 154
    //   57: invokestatic 53	java/lang/Character:valueOf	(C)Ljava/lang/Character;
    //   60: aastore
    //   61: dup
    //   62: iconst_2
    //   63: bipush 100
    //   65: invokestatic 53	java/lang/Character:valueOf	(C)Ljava/lang/Character;
    //   68: aastore
    //   69: dup
    //   70: iconst_3
    //   71: iconst_1
    //   72: invokestatic 53	java/lang/Character:valueOf	(C)Ljava/lang/Character;
    //   75: aastore
    //   76: invokevirtual 59	java/lang/reflect/Method:invoke	(Ljava/lang/Object;[Ljava/lang/Object;)Ljava/lang/Object;
    //   79: astore_1
    //   80: aload_1
    //   81: checkcast 35	java/lang/String
    //   84: astore_1
    //   85: ldc 23
    //   87: ldc 61
    //   89: bipush 15
    //   91: iconst_4
    //   92: invokestatic 31	xxxxxx/uxxxxx:bb00620062bb0062b0062b0062	(Ljava/lang/String;CC)Ljava/lang/String;
    //   95: iconst_3
    //   96: anewarray 33	java/lang/Class
    //   99: dup
    //   100: iconst_0
    //   101: ldc 35
    //   103: aastore
    //   104: dup
    //   105: iconst_1
    //   106: getstatic 41	java/lang/Character:TYPE	Ljava/lang/Class;
    //   109: aastore
    //   110: dup
    //   111: iconst_2
    //   112: getstatic 41	java/lang/Character:TYPE	Ljava/lang/Class;
    //   115: aastore
    //   116: invokevirtual 45	java/lang/Class:getMethod	(Ljava/lang/String;[Ljava/lang/Class;)Ljava/lang/reflect/Method;
    //   119: astore_2
    //   120: aload_2
    //   121: aconst_null
    //   122: iconst_3
    //   123: anewarray 47	java/lang/Object
    //   126: dup
    //   127: iconst_0
    //   128: ldc 63
    //   130: aastore
    //   131: dup
    //   132: iconst_1
    //   133: sipush 214
    //   136: invokestatic 53	java/lang/Character:valueOf	(C)Ljava/lang/Character;
    //   139: aastore
    //   140: dup
    //   141: iconst_2
    //   142: iconst_5
    //   143: invokestatic 53	java/lang/Character:valueOf	(C)Ljava/lang/Character;
    //   146: aastore
    //   147: invokevirtual 59	java/lang/reflect/Method:invoke	(Ljava/lang/Object;[Ljava/lang/Object;)Ljava/lang/Object;
    //   150: astore_2
    //   151: aload_2
    //   152: checkcast 35	java/lang/String
    //   155: astore_2
    //   156: ldc 23
    //   158: ldc 65
    //   160: bipush 56
    //   162: iconst_1
    //   163: invokestatic 31	xxxxxx/uxxxxx:bb00620062bb0062b0062b0062	(Ljava/lang/String;CC)Ljava/lang/String;
    //   166: iconst_4
    //   167: anewarray 33	java/lang/Class
    //   170: dup
    //   171: iconst_0
    //   172: ldc 35
    //   174: aastore
    //   175: dup
    //   176: iconst_1
    //   177: getstatic 41	java/lang/Character:TYPE	Ljava/lang/Class;
    //   180: aastore
    //   181: dup
    //   182: iconst_2
    //   183: getstatic 41	java/lang/Character:TYPE	Ljava/lang/Class;
    //   186: aastore
    //   187: dup
    //   188: iconst_3
    //   189: getstatic 41	java/lang/Character:TYPE	Ljava/lang/Class;
    //   192: aastore
    //   193: invokevirtual 45	java/lang/Class:getMethod	(Ljava/lang/String;[Ljava/lang/Class;)Ljava/lang/reflect/Method;
    //   196: astore_3
    //   197: aload_3
    //   198: aconst_null
    //   199: iconst_4
    //   200: anewarray 47	java/lang/Object
    //   203: dup
    //   204: iconst_0
    //   205: ldc 67
    //   207: aastore
    //   208: dup
    //   209: iconst_1
    //   210: bipush 126
    //   212: invokestatic 53	java/lang/Character:valueOf	(C)Ljava/lang/Character;
    //   215: aastore
    //   216: dup
    //   217: iconst_2
    //   218: sipush 204
    //   221: invokestatic 53	java/lang/Character:valueOf	(C)Ljava/lang/Character;
    //   224: aastore
    //   225: dup
    //   226: iconst_3
    //   227: iconst_1
    //   228: invokestatic 53	java/lang/Character:valueOf	(C)Ljava/lang/Character;
    //   231: aastore
    //   232: invokevirtual 59	java/lang/reflect/Method:invoke	(Ljava/lang/Object;[Ljava/lang/Object;)Ljava/lang/Object;
    //   235: astore_3
    //   236: new 2	uuuuuu/vvvkkk
    //   239: dup
    //   240: aload_1
    //   241: iconst_0
    //   242: aload_2
    //   243: aload_3
    //   244: checkcast 35	java/lang/String
    //   247: invokespecial 71	uuuuuu/vvvkkk:<init>	(Ljava/lang/String;ILjava/lang/String;Ljava/lang/String;)V
    //   250: putstatic 73	uuuuuu/vvvkkk:b0063ccc0063cc0063c	Luuuuuu/vvvkkk;
    //   253: ldc 23
    //   255: ldc 75
    //   257: sipush 210
    //   260: iconst_5
    //   261: invokestatic 31	xxxxxx/uxxxxx:bb00620062bb0062b0062b0062	(Ljava/lang/String;CC)Ljava/lang/String;
    //   264: iconst_3
    //   265: anewarray 33	java/lang/Class
    //   268: dup
    //   269: iconst_0
    //   270: ldc 35
    //   272: aastore
    //   273: dup
    //   274: iconst_1
    //   275: getstatic 41	java/lang/Character:TYPE	Ljava/lang/Class;
    //   278: aastore
    //   279: dup
    //   280: iconst_2
    //   281: getstatic 41	java/lang/Character:TYPE	Ljava/lang/Class;
    //   284: aastore
    //   285: invokevirtual 45	java/lang/Class:getMethod	(Ljava/lang/String;[Ljava/lang/Class;)Ljava/lang/reflect/Method;
    //   288: astore_1
    //   289: aload_1
    //   290: aconst_null
    //   291: iconst_3
    //   292: anewarray 47	java/lang/Object
    //   295: dup
    //   296: iconst_0
    //   297: ldc 77
    //   299: aastore
    //   300: dup
    //   301: iconst_1
    //   302: sipush 196
    //   305: invokestatic 53	java/lang/Character:valueOf	(C)Ljava/lang/Character;
    //   308: aastore
    //   309: dup
    //   310: iconst_2
    //   311: iconst_2
    //   312: invokestatic 53	java/lang/Character:valueOf	(C)Ljava/lang/Character;
    //   315: aastore
    //   316: invokevirtual 59	java/lang/reflect/Method:invoke	(Ljava/lang/Object;[Ljava/lang/Object;)Ljava/lang/Object;
    //   319: astore_1
    //   320: aload_1
    //   321: checkcast 35	java/lang/String
    //   324: astore_1
    //   325: ldc 23
    //   327: ldc 79
    //   329: bipush 56
    //   331: iconst_1
    //   332: invokestatic 31	xxxxxx/uxxxxx:bb00620062bb0062b0062b0062	(Ljava/lang/String;CC)Ljava/lang/String;
    //   335: iconst_3
    //   336: anewarray 33	java/lang/Class
    //   339: dup
    //   340: iconst_0
    //   341: ldc 35
    //   343: aastore
    //   344: dup
    //   345: iconst_1
    //   346: getstatic 41	java/lang/Character:TYPE	Ljava/lang/Class;
    //   349: aastore
    //   350: dup
    //   351: iconst_2
    //   352: getstatic 41	java/lang/Character:TYPE	Ljava/lang/Class;
    //   355: aastore
    //   356: invokevirtual 45	java/lang/Class:getMethod	(Ljava/lang/String;[Ljava/lang/Class;)Ljava/lang/reflect/Method;
    //   359: astore_2
    //   360: aload_2
    //   361: aconst_null
    //   362: iconst_3
    //   363: anewarray 47	java/lang/Object
    //   366: dup
    //   367: iconst_0
    //   368: ldc 81
    //   370: aastore
    //   371: dup
    //   372: iconst_1
    //   373: sipush 235
    //   376: invokestatic 53	java/lang/Character:valueOf	(C)Ljava/lang/Character;
    //   379: aastore
    //   380: dup
    //   381: iconst_2
    //   382: iconst_5
    //   383: invokestatic 53	java/lang/Character:valueOf	(C)Ljava/lang/Character;
    //   386: aastore
    //   387: invokevirtual 59	java/lang/reflect/Method:invoke	(Ljava/lang/Object;[Ljava/lang/Object;)Ljava/lang/Object;
    //   390: astore_2
    //   391: aload_2
    //   392: checkcast 35	java/lang/String
    //   395: astore_2
    //   396: ldc 23
    //   398: ldc 83
    //   400: sipush 192
    //   403: iconst_4
    //   404: invokestatic 31	xxxxxx/uxxxxx:bb00620062bb0062b0062b0062	(Ljava/lang/String;CC)Ljava/lang/String;
    //   407: iconst_3
    //   408: anewarray 33	java/lang/Class
    //   411: dup
    //   412: iconst_0
    //   413: ldc 35
    //   415: aastore
    //   416: dup
    //   417: iconst_1
    //   418: getstatic 41	java/lang/Character:TYPE	Ljava/lang/Class;
    //   421: aastore
    //   422: dup
    //   423: iconst_2
    //   424: getstatic 41	java/lang/Character:TYPE	Ljava/lang/Class;
    //   427: aastore
    //   428: invokevirtual 45	java/lang/Class:getMethod	(Ljava/lang/String;[Ljava/lang/Class;)Ljava/lang/reflect/Method;
    //   431: astore_3
    //   432: aload_3
    //   433: aconst_null
    //   434: iconst_3
    //   435: anewarray 47	java/lang/Object
    //   438: dup
    //   439: iconst_0
    //   440: ldc 85
    //   442: aastore
    //   443: dup
    //   444: iconst_1
    //   445: sipush 253
    //   448: invokestatic 53	java/lang/Character:valueOf	(C)Ljava/lang/Character;
    //   451: aastore
    //   452: dup
    //   453: iconst_2
    //   454: iconst_0
    //   455: invokestatic 53	java/lang/Character:valueOf	(C)Ljava/lang/Character;
    //   458: aastore
    //   459: invokevirtual 59	java/lang/reflect/Method:invoke	(Ljava/lang/Object;[Ljava/lang/Object;)Ljava/lang/Object;
    //   462: astore_3
    //   463: new 2	uuuuuu/vvvkkk
    //   466: dup
    //   467: aload_1
    //   468: iconst_1
    //   469: aload_2
    //   470: aload_3
    //   471: checkcast 35	java/lang/String
    //   474: invokespecial 71	uuuuuu/vvvkkk:<init>	(Ljava/lang/String;ILjava/lang/String;Ljava/lang/String;)V
    //   477: putstatic 87	uuuuuu/vvvkkk:bc0063cc0063cc0063c	Luuuuuu/vvvkkk;
    //   480: ldc 23
    //   482: ldc 89
    //   484: bipush 124
    //   486: iconst_1
    //   487: invokestatic 31	xxxxxx/uxxxxx:bb00620062bb0062b0062b0062	(Ljava/lang/String;CC)Ljava/lang/String;
    //   490: iconst_4
    //   491: anewarray 33	java/lang/Class
    //   494: dup
    //   495: iconst_0
    //   496: ldc 35
    //   498: aastore
    //   499: dup
    //   500: iconst_1
    //   501: getstatic 41	java/lang/Character:TYPE	Ljava/lang/Class;
    //   504: aastore
    //   505: dup
    //   506: iconst_2
    //   507: getstatic 41	java/lang/Character:TYPE	Ljava/lang/Class;
    //   510: aastore
    //   511: dup
    //   512: iconst_3
    //   513: getstatic 41	java/lang/Character:TYPE	Ljava/lang/Class;
    //   516: aastore
    //   517: invokevirtual 45	java/lang/Class:getMethod	(Ljava/lang/String;[Ljava/lang/Class;)Ljava/lang/reflect/Method;
    //   520: astore_1
    //   521: aload_1
    //   522: aconst_null
    //   523: iconst_4
    //   524: anewarray 47	java/lang/Object
    //   527: dup
    //   528: iconst_0
    //   529: ldc 91
    //   531: aastore
    //   532: dup
    //   533: iconst_1
    //   534: sipush 251
    //   537: invokestatic 53	java/lang/Character:valueOf	(C)Ljava/lang/Character;
    //   540: aastore
    //   541: dup
    //   542: iconst_2
    //   543: bipush 110
    //   545: invokestatic 53	java/lang/Character:valueOf	(C)Ljava/lang/Character;
    //   548: aastore
    //   549: dup
    //   550: iconst_3
    //   551: iconst_3
    //   552: invokestatic 53	java/lang/Character:valueOf	(C)Ljava/lang/Character;
    //   555: aastore
    //   556: invokevirtual 59	java/lang/reflect/Method:invoke	(Ljava/lang/Object;[Ljava/lang/Object;)Ljava/lang/Object;
    //   559: astore_1
    //   560: aload_1
    //   561: checkcast 35	java/lang/String
    //   564: astore_1
    //   565: invokestatic 95	uuuuuu/vvvkkk:b0071q00710071q0071q0071qq	()I
    //   568: istore_0
    //   569: iload_0
    //   570: invokestatic 98	uuuuuu/vvvkkk:b00710071q0071q0071q0071qq	()I
    //   573: iload_0
    //   574: iadd
    //   575: imul
    //   576: invokestatic 101	uuuuuu/vvvkkk:bqq00710071q0071q0071qq	()I
    //   579: irem
    //   580: tableswitch	default:+20->600, 0:+20->600
    //   600: ldc 23
    //   602: ldc 103
    //   604: sipush 243
    //   607: iconst_0
    //   608: invokestatic 31	xxxxxx/uxxxxx:bb00620062bb0062b0062b0062	(Ljava/lang/String;CC)Ljava/lang/String;
    //   611: iconst_4
    //   612: anewarray 33	java/lang/Class
    //   615: dup
    //   616: iconst_0
    //   617: ldc 35
    //   619: aastore
    //   620: dup
    //   621: iconst_1
    //   622: getstatic 41	java/lang/Character:TYPE	Ljava/lang/Class;
    //   625: aastore
    //   626: dup
    //   627: iconst_2
    //   628: getstatic 41	java/lang/Character:TYPE	Ljava/lang/Class;
    //   631: aastore
    //   632: dup
    //   633: iconst_3
    //   634: getstatic 41	java/lang/Character:TYPE	Ljava/lang/Class;
    //   637: aastore
    //   638: invokevirtual 45	java/lang/Class:getMethod	(Ljava/lang/String;[Ljava/lang/Class;)Ljava/lang/reflect/Method;
    //   641: astore_2
    //   642: aload_2
    //   643: aconst_null
    //   644: iconst_4
    //   645: anewarray 47	java/lang/Object
    //   648: dup
    //   649: iconst_0
    //   650: ldc 105
    //   652: aastore
    //   653: dup
    //   654: iconst_1
    //   655: sipush 162
    //   658: invokestatic 53	java/lang/Character:valueOf	(C)Ljava/lang/Character;
    //   661: aastore
    //   662: dup
    //   663: iconst_2
    //   664: sipush 179
    //   667: invokestatic 53	java/lang/Character:valueOf	(C)Ljava/lang/Character;
    //   670: aastore
    //   671: dup
    //   672: iconst_3
    //   673: iconst_2
    //   674: invokestatic 53	java/lang/Character:valueOf	(C)Ljava/lang/Character;
    //   677: aastore
    //   678: invokevirtual 59	java/lang/reflect/Method:invoke	(Ljava/lang/Object;[Ljava/lang/Object;)Ljava/lang/Object;
    //   681: astore_2
    //   682: aload_2
    //   683: checkcast 35	java/lang/String
    //   686: astore_2
    //   687: ldc 23
    //   689: ldc 107
    //   691: sipush 143
    //   694: iconst_5
    //   695: invokestatic 31	xxxxxx/uxxxxx:bb00620062bb0062b0062b0062	(Ljava/lang/String;CC)Ljava/lang/String;
    //   698: iconst_3
    //   699: anewarray 33	java/lang/Class
    //   702: dup
    //   703: iconst_0
    //   704: ldc 35
    //   706: aastore
    //   707: dup
    //   708: iconst_1
    //   709: getstatic 41	java/lang/Character:TYPE	Ljava/lang/Class;
    //   712: aastore
    //   713: dup
    //   714: iconst_2
    //   715: getstatic 41	java/lang/Character:TYPE	Ljava/lang/Class;
    //   718: aastore
    //   719: invokevirtual 45	java/lang/Class:getMethod	(Ljava/lang/String;[Ljava/lang/Class;)Ljava/lang/reflect/Method;
    //   722: astore_3
    //   723: aload_3
    //   724: aconst_null
    //   725: iconst_3
    //   726: anewarray 47	java/lang/Object
    //   729: dup
    //   730: iconst_0
    //   731: ldc 109
    //   733: aastore
    //   734: dup
    //   735: iconst_1
    //   736: bipush 17
    //   738: invokestatic 53	java/lang/Character:valueOf	(C)Ljava/lang/Character;
    //   741: aastore
    //   742: dup
    //   743: iconst_2
    //   744: iconst_3
    //   745: invokestatic 53	java/lang/Character:valueOf	(C)Ljava/lang/Character;
    //   748: aastore
    //   749: invokevirtual 59	java/lang/reflect/Method:invoke	(Ljava/lang/Object;[Ljava/lang/Object;)Ljava/lang/Object;
    //   752: astore_3
    //   753: new 2	uuuuuu/vvvkkk
    //   756: dup
    //   757: aload_1
    //   758: iconst_2
    //   759: aload_2
    //   760: aload_3
    //   761: checkcast 35	java/lang/String
    //   764: invokespecial 71	uuuuuu/vvvkkk:<init>	(Ljava/lang/String;ILjava/lang/String;Ljava/lang/String;)V
    //   767: putstatic 111	uuuuuu/vvvkkk:bcc0063c0063cc0063c	Luuuuuu/vvvkkk;
    //   770: ldc 23
    //   772: ldc 113
    //   774: bipush 124
    //   776: bipush 70
    //   778: iconst_1
    //   779: invokestatic 117	xxxxxx/uxxxxx:bbbb0062b0062b0062b0062	(Ljava/lang/String;CCC)Ljava/lang/String;
    //   782: iconst_3
    //   783: anewarray 33	java/lang/Class
    //   786: dup
    //   787: iconst_0
    //   788: ldc 35
    //   790: aastore
    //   791: dup
    //   792: iconst_1
    //   793: getstatic 41	java/lang/Character:TYPE	Ljava/lang/Class;
    //   796: aastore
    //   797: dup
    //   798: iconst_2
    //   799: getstatic 41	java/lang/Character:TYPE	Ljava/lang/Class;
    //   802: aastore
    //   803: invokevirtual 45	java/lang/Class:getMethod	(Ljava/lang/String;[Ljava/lang/Class;)Ljava/lang/reflect/Method;
    //   806: astore_1
    //   807: aload_1
    //   808: aconst_null
    //   809: iconst_3
    //   810: anewarray 47	java/lang/Object
    //   813: dup
    //   814: iconst_0
    //   815: ldc 119
    //   817: aastore
    //   818: dup
    //   819: iconst_1
    //   820: sipush 197
    //   823: invokestatic 53	java/lang/Character:valueOf	(C)Ljava/lang/Character;
    //   826: aastore
    //   827: dup
    //   828: iconst_2
    //   829: iconst_1
    //   830: invokestatic 53	java/lang/Character:valueOf	(C)Ljava/lang/Character;
    //   833: aastore
    //   834: invokevirtual 59	java/lang/reflect/Method:invoke	(Ljava/lang/Object;[Ljava/lang/Object;)Ljava/lang/Object;
    //   837: astore_1
    //   838: aload_1
    //   839: checkcast 35	java/lang/String
    //   842: astore_1
    //   843: ldc 23
    //   845: ldc 121
    //   847: sipush 214
    //   850: sipush 186
    //   853: iconst_3
    //   854: invokestatic 117	xxxxxx/uxxxxx:bbbb0062b0062b0062b0062	(Ljava/lang/String;CCC)Ljava/lang/String;
    //   857: iconst_3
    //   858: anewarray 33	java/lang/Class
    //   861: dup
    //   862: iconst_0
    //   863: ldc 35
    //   865: aastore
    //   866: dup
    //   867: iconst_1
    //   868: getstatic 41	java/lang/Character:TYPE	Ljava/lang/Class;
    //   871: aastore
    //   872: dup
    //   873: iconst_2
    //   874: getstatic 41	java/lang/Character:TYPE	Ljava/lang/Class;
    //   877: aastore
    //   878: invokevirtual 45	java/lang/Class:getMethod	(Ljava/lang/String;[Ljava/lang/Class;)Ljava/lang/reflect/Method;
    //   881: astore_2
    //   882: aload_2
    //   883: aconst_null
    //   884: iconst_3
    //   885: anewarray 47	java/lang/Object
    //   888: dup
    //   889: iconst_0
    //   890: ldc 123
    //   892: aastore
    //   893: dup
    //   894: iconst_1
    //   895: sipush 233
    //   898: invokestatic 53	java/lang/Character:valueOf	(C)Ljava/lang/Character;
    //   901: aastore
    //   902: dup
    //   903: iconst_2
    //   904: iconst_1
    //   905: invokestatic 53	java/lang/Character:valueOf	(C)Ljava/lang/Character;
    //   908: aastore
    //   909: invokevirtual 59	java/lang/reflect/Method:invoke	(Ljava/lang/Object;[Ljava/lang/Object;)Ljava/lang/Object;
    //   912: astore_2
    //   913: aload_2
    //   914: checkcast 35	java/lang/String
    //   917: astore_2
    //   918: ldc 23
    //   920: ldc 125
    //   922: bipush 94
    //   924: iconst_0
    //   925: invokestatic 31	xxxxxx/uxxxxx:bb00620062bb0062b0062b0062	(Ljava/lang/String;CC)Ljava/lang/String;
    //   928: iconst_4
    //   929: anewarray 33	java/lang/Class
    //   932: dup
    //   933: iconst_0
    //   934: ldc 35
    //   936: aastore
    //   937: dup
    //   938: iconst_1
    //   939: getstatic 41	java/lang/Character:TYPE	Ljava/lang/Class;
    //   942: aastore
    //   943: dup
    //   944: iconst_2
    //   945: getstatic 41	java/lang/Character:TYPE	Ljava/lang/Class;
    //   948: aastore
    //   949: dup
    //   950: iconst_3
    //   951: getstatic 41	java/lang/Character:TYPE	Ljava/lang/Class;
    //   954: aastore
    //   955: invokevirtual 45	java/lang/Class:getMethod	(Ljava/lang/String;[Ljava/lang/Class;)Ljava/lang/reflect/Method;
    //   958: astore_3
    //   959: aload_3
    //   960: aconst_null
    //   961: iconst_4
    //   962: anewarray 47	java/lang/Object
    //   965: dup
    //   966: iconst_0
    //   967: ldc 127
    //   969: aastore
    //   970: dup
    //   971: iconst_1
    //   972: bipush 48
    //   974: invokestatic 53	java/lang/Character:valueOf	(C)Ljava/lang/Character;
    //   977: aastore
    //   978: dup
    //   979: iconst_2
    //   980: sipush 199
    //   983: invokestatic 53	java/lang/Character:valueOf	(C)Ljava/lang/Character;
    //   986: aastore
    //   987: dup
    //   988: iconst_3
    //   989: iconst_2
    //   990: invokestatic 53	java/lang/Character:valueOf	(C)Ljava/lang/Character;
    //   993: aastore
    //   994: invokevirtual 59	java/lang/reflect/Method:invoke	(Ljava/lang/Object;[Ljava/lang/Object;)Ljava/lang/Object;
    //   997: astore_3
    //   998: new 2	uuuuuu/vvvkkk
    //   1001: dup
    //   1002: aload_1
    //   1003: iconst_3
    //   1004: aload_2
    //   1005: aload_3
    //   1006: checkcast 35	java/lang/String
    //   1009: invokespecial 71	uuuuuu/vvvkkk:<init>	(Ljava/lang/String;ILjava/lang/String;Ljava/lang/String;)V
    //   1012: putstatic 129	uuuuuu/vvvkkk:b00630063cc0063cc0063c	Luuuuuu/vvvkkk;
    //   1015: ldc 23
    //   1017: ldc -125
    //   1019: sipush 244
    //   1022: iconst_2
    //   1023: invokestatic 31	xxxxxx/uxxxxx:bb00620062bb0062b0062b0062	(Ljava/lang/String;CC)Ljava/lang/String;
    //   1026: iconst_4
    //   1027: anewarray 33	java/lang/Class
    //   1030: dup
    //   1031: iconst_0
    //   1032: ldc 35
    //   1034: aastore
    //   1035: dup
    //   1036: iconst_1
    //   1037: getstatic 41	java/lang/Character:TYPE	Ljava/lang/Class;
    //   1040: aastore
    //   1041: dup
    //   1042: iconst_2
    //   1043: getstatic 41	java/lang/Character:TYPE	Ljava/lang/Class;
    //   1046: aastore
    //   1047: dup
    //   1048: iconst_3
    //   1049: getstatic 41	java/lang/Character:TYPE	Ljava/lang/Class;
    //   1052: aastore
    //   1053: invokevirtual 45	java/lang/Class:getMethod	(Ljava/lang/String;[Ljava/lang/Class;)Ljava/lang/reflect/Method;
    //   1056: astore_1
    //   1057: aload_1
    //   1058: aconst_null
    //   1059: iconst_4
    //   1060: anewarray 47	java/lang/Object
    //   1063: dup
    //   1064: iconst_0
    //   1065: ldc -123
    //   1067: aastore
    //   1068: dup
    //   1069: iconst_1
    //   1070: bipush 35
    //   1072: invokestatic 53	java/lang/Character:valueOf	(C)Ljava/lang/Character;
    //   1075: aastore
    //   1076: dup
    //   1077: iconst_2
    //   1078: bipush 6
    //   1080: invokestatic 53	java/lang/Character:valueOf	(C)Ljava/lang/Character;
    //   1083: aastore
    //   1084: dup
    //   1085: iconst_3
    //   1086: iconst_2
    //   1087: invokestatic 53	java/lang/Character:valueOf	(C)Ljava/lang/Character;
    //   1090: aastore
    //   1091: invokevirtual 59	java/lang/reflect/Method:invoke	(Ljava/lang/Object;[Ljava/lang/Object;)Ljava/lang/Object;
    //   1094: astore_1
    //   1095: aload_1
    //   1096: checkcast 35	java/lang/String
    //   1099: astore_1
    //   1100: ldc 23
    //   1102: ldc -121
    //   1104: bipush 107
    //   1106: iconst_0
    //   1107: invokestatic 31	xxxxxx/uxxxxx:bb00620062bb0062b0062b0062	(Ljava/lang/String;CC)Ljava/lang/String;
    //   1110: iconst_3
    //   1111: anewarray 33	java/lang/Class
    //   1114: dup
    //   1115: iconst_0
    //   1116: ldc 35
    //   1118: aastore
    //   1119: dup
    //   1120: iconst_1
    //   1121: getstatic 41	java/lang/Character:TYPE	Ljava/lang/Class;
    //   1124: aastore
    //   1125: dup
    //   1126: iconst_2
    //   1127: getstatic 41	java/lang/Character:TYPE	Ljava/lang/Class;
    //   1130: aastore
    //   1131: invokevirtual 45	java/lang/Class:getMethod	(Ljava/lang/String;[Ljava/lang/Class;)Ljava/lang/reflect/Method;
    //   1134: astore_2
    //   1135: aload_2
    //   1136: aconst_null
    //   1137: iconst_3
    //   1138: anewarray 47	java/lang/Object
    //   1141: dup
    //   1142: iconst_0
    //   1143: ldc -119
    //   1145: aastore
    //   1146: dup
    //   1147: iconst_1
    //   1148: bipush 70
    //   1150: invokestatic 53	java/lang/Character:valueOf	(C)Ljava/lang/Character;
    //   1153: aastore
    //   1154: dup
    //   1155: iconst_2
    //   1156: iconst_3
    //   1157: invokestatic 53	java/lang/Character:valueOf	(C)Ljava/lang/Character;
    //   1160: aastore
    //   1161: invokevirtual 59	java/lang/reflect/Method:invoke	(Ljava/lang/Object;[Ljava/lang/Object;)Ljava/lang/Object;
    //   1164: astore_2
    //   1165: aload_2
    //   1166: checkcast 35	java/lang/String
    //   1169: astore_2
    //   1170: ldc 23
    //   1172: ldc -117
    //   1174: bipush 100
    //   1176: iconst_3
    //   1177: invokestatic 31	xxxxxx/uxxxxx:bb00620062bb0062b0062b0062	(Ljava/lang/String;CC)Ljava/lang/String;
    //   1180: iconst_4
    //   1181: anewarray 33	java/lang/Class
    //   1184: dup
    //   1185: iconst_0
    //   1186: ldc 35
    //   1188: aastore
    //   1189: dup
    //   1190: iconst_1
    //   1191: getstatic 41	java/lang/Character:TYPE	Ljava/lang/Class;
    //   1194: aastore
    //   1195: dup
    //   1196: iconst_2
    //   1197: getstatic 41	java/lang/Character:TYPE	Ljava/lang/Class;
    //   1200: aastore
    //   1201: dup
    //   1202: iconst_3
    //   1203: getstatic 41	java/lang/Character:TYPE	Ljava/lang/Class;
    //   1206: aastore
    //   1207: invokevirtual 45	java/lang/Class:getMethod	(Ljava/lang/String;[Ljava/lang/Class;)Ljava/lang/reflect/Method;
    //   1210: astore_3
    //   1211: aload_3
    //   1212: aconst_null
    //   1213: iconst_4
    //   1214: anewarray 47	java/lang/Object
    //   1217: dup
    //   1218: iconst_0
    //   1219: ldc -115
    //   1221: aastore
    //   1222: dup
    //   1223: iconst_1
    //   1224: sipush 239
    //   1227: invokestatic 53	java/lang/Character:valueOf	(C)Ljava/lang/Character;
    //   1230: aastore
    //   1231: dup
    //   1232: iconst_2
    //   1233: bipush 55
    //   1235: invokestatic 53	java/lang/Character:valueOf	(C)Ljava/lang/Character;
    //   1238: aastore
    //   1239: dup
    //   1240: iconst_3
    //   1241: iconst_3
    //   1242: invokestatic 53	java/lang/Character:valueOf	(C)Ljava/lang/Character;
    //   1245: aastore
    //   1246: invokevirtual 59	java/lang/reflect/Method:invoke	(Ljava/lang/Object;[Ljava/lang/Object;)Ljava/lang/Object;
    //   1249: astore_3
    //   1250: new 2	uuuuuu/vvvkkk
    //   1253: dup
    //   1254: aload_1
    //   1255: iconst_4
    //   1256: aload_2
    //   1257: aload_3
    //   1258: checkcast 35	java/lang/String
    //   1261: invokespecial 71	uuuuuu/vvvkkk:<init>	(Ljava/lang/String;ILjava/lang/String;Ljava/lang/String;)V
    //   1264: putstatic 143	uuuuuu/vvvkkk:b0063c0063c0063cc0063c	Luuuuuu/vvvkkk;
    //   1267: ldc 23
    //   1269: ldc -111
    //   1271: sipush 172
    //   1274: iconst_1
    //   1275: invokestatic 31	xxxxxx/uxxxxx:bb00620062bb0062b0062b0062	(Ljava/lang/String;CC)Ljava/lang/String;
    //   1278: iconst_3
    //   1279: anewarray 33	java/lang/Class
    //   1282: dup
    //   1283: iconst_0
    //   1284: ldc 35
    //   1286: aastore
    //   1287: dup
    //   1288: iconst_1
    //   1289: getstatic 41	java/lang/Character:TYPE	Ljava/lang/Class;
    //   1292: aastore
    //   1293: dup
    //   1294: iconst_2
    //   1295: getstatic 41	java/lang/Character:TYPE	Ljava/lang/Class;
    //   1298: aastore
    //   1299: invokevirtual 45	java/lang/Class:getMethod	(Ljava/lang/String;[Ljava/lang/Class;)Ljava/lang/reflect/Method;
    //   1302: astore_1
    //   1303: aload_1
    //   1304: aconst_null
    //   1305: iconst_3
    //   1306: anewarray 47	java/lang/Object
    //   1309: dup
    //   1310: iconst_0
    //   1311: ldc -109
    //   1313: aastore
    //   1314: dup
    //   1315: iconst_1
    //   1316: bipush 47
    //   1318: invokestatic 53	java/lang/Character:valueOf	(C)Ljava/lang/Character;
    //   1321: aastore
    //   1322: dup
    //   1323: iconst_2
    //   1324: iconst_5
    //   1325: invokestatic 53	java/lang/Character:valueOf	(C)Ljava/lang/Character;
    //   1328: aastore
    //   1329: invokevirtual 59	java/lang/reflect/Method:invoke	(Ljava/lang/Object;[Ljava/lang/Object;)Ljava/lang/Object;
    //   1332: astore_1
    //   1333: aload_1
    //   1334: checkcast 35	java/lang/String
    //   1337: astore_1
    //   1338: ldc 23
    //   1340: ldc -107
    //   1342: bipush 35
    //   1344: iconst_4
    //   1345: invokestatic 31	xxxxxx/uxxxxx:bb00620062bb0062b0062b0062	(Ljava/lang/String;CC)Ljava/lang/String;
    //   1348: iconst_4
    //   1349: anewarray 33	java/lang/Class
    //   1352: dup
    //   1353: iconst_0
    //   1354: ldc 35
    //   1356: aastore
    //   1357: dup
    //   1358: iconst_1
    //   1359: getstatic 41	java/lang/Character:TYPE	Ljava/lang/Class;
    //   1362: aastore
    //   1363: dup
    //   1364: iconst_2
    //   1365: getstatic 41	java/lang/Character:TYPE	Ljava/lang/Class;
    //   1368: aastore
    //   1369: dup
    //   1370: iconst_3
    //   1371: getstatic 41	java/lang/Character:TYPE	Ljava/lang/Class;
    //   1374: aastore
    //   1375: invokevirtual 45	java/lang/Class:getMethod	(Ljava/lang/String;[Ljava/lang/Class;)Ljava/lang/reflect/Method;
    //   1378: astore_2
    //   1379: aload_2
    //   1380: aconst_null
    //   1381: iconst_4
    //   1382: anewarray 47	java/lang/Object
    //   1385: dup
    //   1386: iconst_0
    //   1387: ldc -105
    //   1389: aastore
    //   1390: dup
    //   1391: iconst_1
    //   1392: sipush 228
    //   1395: invokestatic 53	java/lang/Character:valueOf	(C)Ljava/lang/Character;
    //   1398: aastore
    //   1399: dup
    //   1400: iconst_2
    //   1401: bipush 30
    //   1403: invokestatic 53	java/lang/Character:valueOf	(C)Ljava/lang/Character;
    //   1406: aastore
    //   1407: dup
    //   1408: iconst_3
    //   1409: iconst_0
    //   1410: invokestatic 53	java/lang/Character:valueOf	(C)Ljava/lang/Character;
    //   1413: aastore
    //   1414: invokevirtual 59	java/lang/reflect/Method:invoke	(Ljava/lang/Object;[Ljava/lang/Object;)Ljava/lang/Object;
    //   1417: astore_2
    //   1418: new 2	uuuuuu/vvvkkk
    //   1421: dup
    //   1422: aload_1
    //   1423: iconst_5
    //   1424: aload_2
    //   1425: checkcast 35	java/lang/String
    //   1428: ldc -103
    //   1430: invokespecial 71	uuuuuu/vvvkkk:<init>	(Ljava/lang/String;ILjava/lang/String;Ljava/lang/String;)V
    //   1433: putstatic 155	uuuuuu/vvvkkk:bc00630063c0063cc0063c	Luuuuuu/vvvkkk;
    //   1436: getstatic 73	uuuuuu/vvvkkk:b0063ccc0063cc0063c	Luuuuuu/vvvkkk;
    //   1439: astore_1
    //   1440: getstatic 87	uuuuuu/vvvkkk:bc0063cc0063cc0063c	Luuuuuu/vvvkkk;
    //   1443: astore_2
    //   1444: getstatic 111	uuuuuu/vvvkkk:bcc0063c0063cc0063c	Luuuuuu/vvvkkk;
    //   1447: astore_3
    //   1448: getstatic 129	uuuuuu/vvvkkk:b00630063cc0063cc0063c	Luuuuuu/vvvkkk;
    //   1451: astore 4
    //   1453: getstatic 143	uuuuuu/vvvkkk:b0063c0063c0063cc0063c	Luuuuuu/vvvkkk;
    //   1456: astore 5
    //   1458: getstatic 155	uuuuuu/vvvkkk:bc00630063c0063cc0063c	Luuuuuu/vvvkkk;
    //   1461: astore 6
    //   1463: invokestatic 95	uuuuuu/vvvkkk:b0071q00710071q0071q0071qq	()I
    //   1466: istore_0
    //   1467: iload_0
    //   1468: invokestatic 98	uuuuuu/vvvkkk:b00710071q0071q0071q0071qq	()I
    //   1471: iload_0
    //   1472: iadd
    //   1473: imul
    //   1474: invokestatic 101	uuuuuu/vvvkkk:bqq00710071q0071q0071qq	()I
    //   1477: irem
    //   1478: tableswitch	default:+18->1496, 0:+18->1496
    //   1496: bipush 6
    //   1498: anewarray 2	uuuuuu/vvvkkk
    //   1501: dup
    //   1502: iconst_0
    //   1503: aload_1
    //   1504: aastore
    //   1505: dup
    //   1506: iconst_1
    //   1507: aload_2
    //   1508: aastore
    //   1509: dup
    //   1510: iconst_2
    //   1511: aload_3
    //   1512: aastore
    //   1513: dup
    //   1514: iconst_3
    //   1515: aload 4
    //   1517: aastore
    //   1518: dup
    //   1519: iconst_4
    //   1520: aload 5
    //   1522: aastore
    //   1523: dup
    //   1524: iconst_5
    //   1525: aload 6
    //   1527: aastore
    //   1528: putstatic 157	uuuuuu/vvvkkk:bcccc0063cc0063c	[Luuuuuu/vvvkkk;
    //   1531: return
    //   1532: astore_1
    //   1533: aload_1
    //   1534: invokevirtual 161	java/lang/reflect/InvocationTargetException:getCause	()Ljava/lang/Throwable;
    //   1537: athrow
    //   1538: astore_1
    //   1539: aload_1
    //   1540: invokevirtual 161	java/lang/reflect/InvocationTargetException:getCause	()Ljava/lang/Throwable;
    //   1543: athrow
    //   1544: astore_1
    //   1545: aload_1
    //   1546: invokevirtual 161	java/lang/reflect/InvocationTargetException:getCause	()Ljava/lang/Throwable;
    //   1549: athrow
    //   1550: astore_1
    //   1551: aload_1
    //   1552: invokevirtual 161	java/lang/reflect/InvocationTargetException:getCause	()Ljava/lang/Throwable;
    //   1555: athrow
    //   1556: astore_1
    //   1557: aload_1
    //   1558: invokevirtual 161	java/lang/reflect/InvocationTargetException:getCause	()Ljava/lang/Throwable;
    //   1561: athrow
    //   1562: astore_1
    //   1563: aload_1
    //   1564: invokevirtual 161	java/lang/reflect/InvocationTargetException:getCause	()Ljava/lang/Throwable;
    //   1567: athrow
    //   1568: astore_1
    //   1569: aload_1
    //   1570: invokevirtual 161	java/lang/reflect/InvocationTargetException:getCause	()Ljava/lang/Throwable;
    //   1573: athrow
    //   1574: astore_1
    //   1575: aload_1
    //   1576: invokevirtual 161	java/lang/reflect/InvocationTargetException:getCause	()Ljava/lang/Throwable;
    //   1579: athrow
    //   1580: astore_1
    //   1581: aload_1
    //   1582: invokevirtual 161	java/lang/reflect/InvocationTargetException:getCause	()Ljava/lang/Throwable;
    //   1585: athrow
    //   1586: astore_1
    //   1587: aload_1
    //   1588: invokevirtual 161	java/lang/reflect/InvocationTargetException:getCause	()Ljava/lang/Throwable;
    //   1591: athrow
    //   1592: astore_1
    //   1593: aload_1
    //   1594: invokevirtual 161	java/lang/reflect/InvocationTargetException:getCause	()Ljava/lang/Throwable;
    //   1597: athrow
    //   1598: astore_1
    //   1599: aload_1
    //   1600: invokevirtual 161	java/lang/reflect/InvocationTargetException:getCause	()Ljava/lang/Throwable;
    //   1603: athrow
    //   1604: astore_1
    //   1605: aload_1
    //   1606: invokevirtual 161	java/lang/reflect/InvocationTargetException:getCause	()Ljava/lang/Throwable;
    //   1609: athrow
    //   1610: astore_1
    //   1611: aload_1
    //   1612: invokevirtual 161	java/lang/reflect/InvocationTargetException:getCause	()Ljava/lang/Throwable;
    //   1615: athrow
    //   1616: astore_1
    //   1617: aload_1
    //   1618: invokevirtual 161	java/lang/reflect/InvocationTargetException:getCause	()Ljava/lang/Throwable;
    //   1621: athrow
    //   1622: astore_1
    //   1623: aload_1
    //   1624: invokevirtual 161	java/lang/reflect/InvocationTargetException:getCause	()Ljava/lang/Throwable;
    //   1627: athrow
    //   1628: astore_1
    //   1629: aload_1
    //   1630: invokevirtual 161	java/lang/reflect/InvocationTargetException:getCause	()Ljava/lang/Throwable;
    //   1633: athrow
    // Local variable table:
    //   start	length	slot	name	signature
    //   568	906	0	i	int
    //   40	1464	1	localObject1	Object
    //   1532	2	1	localInvocationTargetException1	java.lang.reflect.InvocationTargetException
    //   1538	2	1	localInvocationTargetException2	java.lang.reflect.InvocationTargetException
    //   1544	2	1	localInvocationTargetException3	java.lang.reflect.InvocationTargetException
    //   1550	2	1	localInvocationTargetException4	java.lang.reflect.InvocationTargetException
    //   1556	2	1	localInvocationTargetException5	java.lang.reflect.InvocationTargetException
    //   1562	2	1	localInvocationTargetException6	java.lang.reflect.InvocationTargetException
    //   1568	2	1	localInvocationTargetException7	java.lang.reflect.InvocationTargetException
    //   1574	2	1	localInvocationTargetException8	java.lang.reflect.InvocationTargetException
    //   1580	2	1	localInvocationTargetException9	java.lang.reflect.InvocationTargetException
    //   1586	2	1	localInvocationTargetException10	java.lang.reflect.InvocationTargetException
    //   1592	2	1	localInvocationTargetException11	java.lang.reflect.InvocationTargetException
    //   1598	2	1	localInvocationTargetException12	java.lang.reflect.InvocationTargetException
    //   1604	2	1	localInvocationTargetException13	java.lang.reflect.InvocationTargetException
    //   1610	2	1	localInvocationTargetException14	java.lang.reflect.InvocationTargetException
    //   1616	2	1	localInvocationTargetException15	java.lang.reflect.InvocationTargetException
    //   1622	2	1	localInvocationTargetException16	java.lang.reflect.InvocationTargetException
    //   1628	2	1	localInvocationTargetException17	java.lang.reflect.InvocationTargetException
    //   119	1389	2	localObject2	Object
    //   196	1316	3	localObject3	Object
    //   1451	65	4	localVvvkkk1	vvvkkk
    //   1456	65	5	localVvvkkk2	vvvkkk
    //   1461	65	6	localVvvkkk3	vvvkkk
    // Exception table:
    //   from	to	target	type
    //   41	80	1532	java/lang/reflect/InvocationTargetException
    //   1379	1418	1538	java/lang/reflect/InvocationTargetException
    //   120	151	1544	java/lang/reflect/InvocationTargetException
    //   197	236	1550	java/lang/reflect/InvocationTargetException
    //   289	320	1556	java/lang/reflect/InvocationTargetException
    //   360	391	1562	java/lang/reflect/InvocationTargetException
    //   807	838	1568	java/lang/reflect/InvocationTargetException
    //   882	913	1574	java/lang/reflect/InvocationTargetException
    //   432	463	1580	java/lang/reflect/InvocationTargetException
    //   1057	1095	1586	java/lang/reflect/InvocationTargetException
    //   959	998	1592	java/lang/reflect/InvocationTargetException
    //   521	560	1598	java/lang/reflect/InvocationTargetException
    //   642	682	1604	java/lang/reflect/InvocationTargetException
    //   723	753	1610	java/lang/reflect/InvocationTargetException
    //   1135	1165	1616	java/lang/reflect/InvocationTargetException
    //   1211	1250	1622	java/lang/reflect/InvocationTargetException
    //   1303	1333	1628	java/lang/reflect/InvocationTargetException
  }
  
  private vvvkkk(String paramString1, String paramString2)
  {
    this.bccc00630063cc0063c = paramString1;
    this.b006300630063c0063cc0063c = paramString2;
  }
  
  public static int b00710071q0071q0071q0071qq()
  {
    return 1;
  }
  
  public static int b0071q00710071q0071q0071qq()
  {
    return 21;
  }
  
  public static int bq0071q0071q0071q0071qq()
  {
    return 0;
  }
  
  public static int bqq00710071q0071q0071qq()
  {
    return 2;
  }
  
  public static vvvkkk bqqqq00710071q0071qq(String paramString)
  {
    int i = b0071q00710071q0071q0071qq();
    switch (i * (b00710071q0071q0071q0071qq() + i) % bqq00710071q0071q0071qq())
    {
    default: 
      if ((b0071q00710071q0071q0071qq() + b00710071q0071q0071q0071qq()) * b0071q00710071q0071q0071qq() % bqq00710071q0071q0071qq() == bq0071q0071q0071q0071qq()) {
        break;
      }
    }
    return (vvvkkk)Enum.valueOf(vvvkkk.class, paramString);
  }
  
  public String b0071007100710071q0071q0071qq()
  {
    String str = this.bccc00630063cc0063c;
    int i = b0071q00710071q0071q0071qq();
    switch (i * (b00710071q0071q0071q0071qq() + i) % bqq00710071q0071q0071qq())
    {
    default: 
      i = b0071q00710071q0071q0071qq();
      switch (i * (b00710071q0071q0071q0071qq() + i) % bqq00710071q0071q0071qq())
      {
      }
      break;
    }
    return str;
  }
  
  public String bq007100710071q0071q0071qq()
  {
    int i = b0071q00710071q0071q0071qq();
    switch (i * (b00710071q0071q0071q0071qq() + i) % bqq00710071q0071q0071qq())
    {
    }
    String str = this.b006300630063c0063cc0063c;
    if ((b0071q00710071q0071q0071qq() + b00710071q0071q0071q0071qq()) * b0071q00710071q0071q0071qq() % bqq00710071q0071q0071qq() != bq0071q0071q0071q0071qq()) {}
    return str;
  }
}
