package uuuuuu;

import android.os.Build.VERSION;
import com.db.pwcc.dbmobile.migration.MigrationKey;
import com.db.pwcc.dbmobile.secure.preferences.SharedPreferencesHelper;

public class vvvrvv
  implements vrvrvv
{
  public static int b007800780078x0078x0078xx = 84;
  public static int b0078xx00780078x0078xx = 0;
  public static int bx0078x00780078x0078xx = 2;
  public static int bxxx00780078x0078xx = 1;
  private yttttt b0078x0078x0078x0078xx;
  private SharedPreferencesHelper bx00780078x0078x0078xx;
  
  public vvvrvv(SharedPreferencesHelper paramSharedPreferencesHelper, yttttt paramYttttt)
  {
    this.bx00780078x0078x0078xx = paramSharedPreferencesHelper;
    this.b0078x0078x0078x0078xx = paramYttttt;
  }
  
  public static int b00710071q0071q007100710071q0071()
  {
    return 3;
  }
  
  public static int b0071q00710071q007100710071q0071()
  {
    return 2;
  }
  
  private boolean bq007100710071q007100710071q0071()
  {
    if (Build.VERSION.SDK_INT >= 26)
    {
      if ((b007800780078x0078x0078xx + bxxx00780078x0078xx) * b007800780078x0078x0078xx % bx0078x00780078x0078xx != b0078xx00780078x0078xx)
      {
        if ((b007800780078x0078x0078xx + bxxx00780078x0078xx) * b007800780078x0078x0078xx % bx0078x00780078x0078xx != b0078xx00780078x0078xx)
        {
          b007800780078x0078x0078xx = 2;
          b0078xx00780078x0078xx = b00710071q0071q007100710071q0071();
        }
        b007800780078x0078x0078xx = b00710071q0071q007100710071q0071();
        b0078xx00780078x0078xx = b00710071q0071q007100710071q0071();
      }
      return true;
    }
    return false;
  }
  
  public static int bqq00710071q007100710071q0071()
  {
    return 1;
  }
  
  public int b00710071q00710071q00710071q0071()
  {
    if ((b007800780078x0078x0078xx + bqq00710071q007100710071q0071()) * b007800780078x0078x0078xx % bx0078x00780078x0078xx != b0078xx00780078x0078xx)
    {
      b007800780078x0078x0078xx = b00710071q0071q007100710071q0071();
      b0078xx00780078x0078xx = b00710071q0071q007100710071q0071();
    }
    if ((b007800780078x0078x0078xx + bxxx00780078x0078xx) * b007800780078x0078x0078xx % bx0078x00780078x0078xx != b0078xx00780078x0078xx)
    {
      b007800780078x0078x0078xx = b00710071q0071q007100710071q0071();
      b0078xx00780078x0078xx = 28;
    }
    return 0;
  }
  
  /* Error */
  public void b0071qq00710071q00710071q0071()
  {
    // Byte code:
    //   0: aload_0
    //   1: getfield 26	uuuuuu/vvvrvv:bx00780078x0078x0078xx	Lcom/db/pwcc/dbmobile/secure/preferences/SharedPreferencesHelper;
    //   4: astore_2
    //   5: getstatic 68	com/db/pwcc/dbmobile/migration/MigrationKey:MOPAY_HOUSEKEEPING	Lcom/db/pwcc/dbmobile/migration/MigrationKey;
    //   8: invokevirtual 72	com/db/pwcc/dbmobile/migration/MigrationKey:name	()Ljava/lang/String;
    //   11: astore_3
    //   12: ldc 74
    //   14: ldc 76
    //   16: bipush 10
    //   18: iconst_3
    //   19: invokestatic 82	xxxxxx/uxxxxx:bb00620062bb0062b0062b0062	(Ljava/lang/String;CC)Ljava/lang/String;
    //   22: iconst_1
    //   23: anewarray 84	java/lang/Class
    //   26: dup
    //   27: iconst_0
    //   28: ldc 86
    //   30: aastore
    //   31: invokevirtual 90	java/lang/Class:getMethod	(Ljava/lang/String;[Ljava/lang/Class;)Ljava/lang/reflect/Method;
    //   34: astore 4
    //   36: aload 4
    //   38: aload_2
    //   39: iconst_1
    //   40: anewarray 4	java/lang/Object
    //   43: dup
    //   44: iconst_0
    //   45: aload_3
    //   46: aastore
    //   47: invokevirtual 96	java/lang/reflect/Method:invoke	(Ljava/lang/Object;[Ljava/lang/Object;)Ljava/lang/Object;
    //   50: astore_2
    //   51: aload_2
    //   52: checkcast 98	java/lang/Boolean
    //   55: invokevirtual 101	java/lang/Boolean:booleanValue	()Z
    //   58: ifne +113 -> 171
    //   61: aload_0
    //   62: invokespecial 103	uuuuuu/vvvrvv:bq007100710071q007100710071q0071	()Z
    //   65: ifeq +106 -> 171
    //   68: new 105	uuuuuu/tytytt
    //   71: dup
    //   72: invokespecial 106	uuuuuu/tytytt:<init>	()V
    //   75: astore_2
    //   76: aload_2
    //   77: new 108	uuuuuu/vvvrvv$1
    //   80: dup
    //   81: aload_0
    //   82: invokespecial 111	uuuuuu/vvvrvv$1:<init>	(Luuuuuu/vvvrvv;)V
    //   85: invokevirtual 115	uuuuuu/tytytt:b00710071q00710071q0071007100710071	(Luuuuuu/tytytt$yyyttt;)V
    //   88: aload_2
    //   89: invokevirtual 118	uuuuuu/tytytt:run	()V
    //   92: getstatic 36	uuuuuu/vvvrvv:b007800780078x0078x0078xx	I
    //   95: getstatic 38	uuuuuu/vvvrvv:bxxx00780078x0078xx	I
    //   98: iadd
    //   99: getstatic 36	uuuuuu/vvvrvv:b007800780078x0078x0078xx	I
    //   102: imul
    //   103: getstatic 44	uuuuuu/vvvrvv:bx0078x00780078x0078xx	I
    //   106: irem
    //   107: getstatic 46	uuuuuu/vvvrvv:b0078xx00780078x0078xx	I
    //   110: if_icmpeq +61 -> 171
    //   113: invokestatic 42	uuuuuu/vvvrvv:b00710071q0071q007100710071q0071	()I
    //   116: putstatic 36	uuuuuu/vvvrvv:b007800780078x0078x0078xx	I
    //   119: invokestatic 42	uuuuuu/vvvrvv:b00710071q0071q007100710071q0071	()I
    //   122: putstatic 46	uuuuuu/vvvrvv:b0078xx00780078x0078xx	I
    //   125: invokestatic 42	uuuuuu/vvvrvv:b00710071q0071q007100710071q0071	()I
    //   128: istore_1
    //   129: iload_1
    //   130: getstatic 38	uuuuuu/vvvrvv:bxxx00780078x0078xx	I
    //   133: iload_1
    //   134: iadd
    //   135: imul
    //   136: getstatic 44	uuuuuu/vvvrvv:bx0078x00780078x0078xx	I
    //   139: irem
    //   140: tableswitch	default:+20->160, 0:+31->171
    //   160: invokestatic 42	uuuuuu/vvvrvv:b00710071q0071q007100710071q0071	()I
    //   163: putstatic 36	uuuuuu/vvvrvv:b007800780078x0078x0078xx	I
    //   166: bipush 8
    //   168: putstatic 46	uuuuuu/vvvrvv:b0078xx00780078x0078xx	I
    //   171: aload_0
    //   172: invokespecial 103	uuuuuu/vvvrvv:bq007100710071q007100710071q0071	()Z
    //   175: ifne +71 -> 246
    //   178: aload_0
    //   179: getfield 26	uuuuuu/vvvrvv:bx00780078x0078x0078xx	Lcom/db/pwcc/dbmobile/secure/preferences/SharedPreferencesHelper;
    //   182: astore_2
    //   183: getstatic 68	com/db/pwcc/dbmobile/migration/MigrationKey:MOPAY_HOUSEKEEPING	Lcom/db/pwcc/dbmobile/migration/MigrationKey;
    //   186: invokevirtual 72	com/db/pwcc/dbmobile/migration/MigrationKey:name	()Ljava/lang/String;
    //   189: astore_3
    //   190: ldc 74
    //   192: ldc 120
    //   194: sipush 181
    //   197: sipush 135
    //   200: iconst_0
    //   201: invokestatic 124	xxxxxx/uxxxxx:bbbb0062b0062b0062b0062	(Ljava/lang/String;CCC)Ljava/lang/String;
    //   204: iconst_2
    //   205: anewarray 84	java/lang/Class
    //   208: dup
    //   209: iconst_0
    //   210: ldc 86
    //   212: aastore
    //   213: dup
    //   214: iconst_1
    //   215: getstatic 128	java/lang/Boolean:TYPE	Ljava/lang/Class;
    //   218: aastore
    //   219: invokevirtual 90	java/lang/Class:getMethod	(Ljava/lang/String;[Ljava/lang/Class;)Ljava/lang/reflect/Method;
    //   222: astore 4
    //   224: aload 4
    //   226: aload_2
    //   227: iconst_2
    //   228: anewarray 4	java/lang/Object
    //   231: dup
    //   232: iconst_0
    //   233: aload_3
    //   234: aastore
    //   235: dup
    //   236: iconst_1
    //   237: iconst_1
    //   238: invokestatic 132	java/lang/Boolean:valueOf	(Z)Ljava/lang/Boolean;
    //   241: aastore
    //   242: invokevirtual 96	java/lang/reflect/Method:invoke	(Ljava/lang/Object;[Ljava/lang/Object;)Ljava/lang/Object;
    //   245: pop
    //   246: return
    //   247: astore_2
    //   248: aload_2
    //   249: invokevirtual 136	java/lang/reflect/InvocationTargetException:getCause	()Ljava/lang/Throwable;
    //   252: athrow
    //   253: astore_2
    //   254: aload_2
    //   255: invokevirtual 136	java/lang/reflect/InvocationTargetException:getCause	()Ljava/lang/Throwable;
    //   258: athrow
    // Local variable table:
    //   start	length	slot	name	signature
    //   0	259	0	this	vvvrvv
    //   128	8	1	i	int
    //   4	223	2	localObject	Object
    //   247	2	2	localInvocationTargetException1	java.lang.reflect.InvocationTargetException
    //   253	2	2	localInvocationTargetException2	java.lang.reflect.InvocationTargetException
    //   11	223	3	str	String
    //   34	191	4	localMethod	java.lang.reflect.Method
    // Exception table:
    //   from	to	target	type
    //   36	51	247	java/lang/reflect/InvocationTargetException
    //   224	246	253	java/lang/reflect/InvocationTargetException
  }
  
  public int bq0071q00710071q00710071q0071()
  {
    if ((b007800780078x0078x0078xx + bxxx00780078x0078xx) * b007800780078x0078x0078xx % bx0078x00780078x0078xx != b0078xx00780078x0078xx)
    {
      if ((b007800780078x0078x0078xx + bxxx00780078x0078xx) * b007800780078x0078x0078xx % b0071q00710071q007100710071q0071() != b0078xx00780078x0078xx)
      {
        b007800780078x0078x0078xx = b00710071q0071q007100710071q0071();
        b0078xx00780078x0078xx = 26;
      }
      b007800780078x0078x0078xx = b00710071q0071q007100710071q0071();
      b0078xx00780078x0078xx = 27;
    }
    return Integer.MAX_VALUE;
  }
  
  public String bqq007100710071q00710071q0071()
  {
    String str = MigrationKey.MOPAY_HOUSEKEEPING.name();
    int i = b007800780078x0078x0078xx;
    int j = bxxx00780078x0078xx;
    int k = b007800780078x0078x0078xx;
    int m = bx0078x00780078x0078xx;
    int n = b007800780078x0078x0078xx;
    switch (n * (bqq00710071q007100710071q0071() + n) % bx0078x00780078x0078xx)
    {
    default: 
      b007800780078x0078x0078xx = b00710071q0071q007100710071q0071();
      b0078xx00780078x0078xx = 49;
    }
    if ((i + j) * k % m != b0078xx00780078x0078xx)
    {
      b007800780078x0078x0078xx = 64;
      b0078xx00780078x0078xx = b00710071q0071q007100710071q0071();
    }
    return str;
  }
}
