package uuuuuu;

import android.content.Context;
import android.support.annotation.NonNull;
import com.db.pwcc.dbmobile.secure.preferences.SharedPreferencesHelper;
import java.util.ArrayList;
import java.util.List;

public class vvvvrv
{
  public static int b007800780078x00780078xxx = 1;
  public static int b0078x0078x00780078xxx = 30;
  private static final String b0078xxx00780078xxx = vvvvrv.class.getSimpleName();
  public static int bx00780078x00780078xxx = 0;
  public static int bxxx007800780078xxx = 2;
  public List<vrvrvv> b00780078xx00780078xxx;
  public Context bx0078xx00780078xxx;
  public SharedPreferencesHelper bxx0078x00780078xxx;
  
  static
  {
    if ((b0078x0078x00780078xxx + b007800780078x00780078xxx) * b0078x0078x00780078xxx % b0071q0071007100710071q0071q0071() != bx00780078x00780078xxx)
    {
      b0078x0078x00780078xxx = bq00710071007100710071q0071q0071();
      bx00780078x00780078xxx = 55;
    }
    if ((bq00710071007100710071q0071q0071() + b007800780078x00780078xxx) * bq00710071007100710071q0071q0071() % bxxx007800780078xxx != bx00780078x00780078xxx)
    {
      b0078x0078x00780078xxx = bq00710071007100710071q0071q0071();
      bx00780078x00780078xxx = bq00710071007100710071q0071q0071();
    }
  }
  
  public vvvvrv(Context paramContext, SharedPreferencesHelper paramSharedPreferencesHelper)
  {
    this.bx0078xx00780078xxx = paramContext;
    this.bxx0078x00780078xxx = paramSharedPreferencesHelper;
    this.b00780078xx00780078xxx = new ArrayList();
    bq0071qqqq00710071q0071();
  }
  
  public static int b007100710071007100710071q0071q0071()
  {
    return 1;
  }
  
  public static int b0071q0071007100710071q0071q0071()
  {
    return 2;
  }
  
  public static int bq00710071007100710071q0071q0071()
  {
    return 53;
  }
  
  private void bq0071qqqq00710071q0071()
  {
    List localList = this.b00780078xx00780078xxx;
    int i = b0078x0078x00780078xxx;
    switch (i * (b007100710071007100710071q0071q0071() + i) % b0071q0071007100710071q0071q0071())
    {
    default: 
      b0078x0078x00780078xxx = 92;
      bx00780078x00780078xxx = 26;
    }
    Context localContext = this.bx0078xx00780078xxx;
    i = b0078x0078x00780078xxx;
    switch (i * (b007800780078x00780078xxx + i) % bxxx007800780078xxx)
    {
    default: 
      b0078x0078x00780078xxx = 91;
      bx00780078x00780078xxx = 90;
    }
    localList.add(new vrrvvv(localContext, this.bxx0078x00780078xxx));
    this.b00780078xx00780078xxx.add(new rvrrvv());
    this.b00780078xx00780078xxx.add(new rrvrvv(this.bxx0078x00780078xxx));
  }
  
  public static int bqq0071007100710071q0071q0071()
  {
    return 0;
  }
  
  public void b00710071qqqq00710071q0071(@NonNull vvrvrv paramVvrvrv, @NonNull String... paramVarArgs)
  {
    if ((b0078x0078x00780078xxx + b007800780078x00780078xxx) * b0078x0078x00780078xxx % bxxx007800780078xxx != bqq0071007100710071q0071q0071())
    {
      b0078x0078x00780078xxx = 58;
      bx00780078x00780078xxx = bq00710071007100710071q0071q0071();
    }
    paramVvrvrv = new StringBuilder(paramVvrvrv.toString());
    int k = paramVarArgs.length;
    int j = 0;
    int m = bq00710071007100710071q0071q0071();
    int i = j;
    switch (m * (b007800780078x00780078xxx + m) % bxxx007800780078xxx)
    {
    default: 
      b0078x0078x00780078xxx = bq00710071007100710071q0071q0071();
      bx00780078x00780078xxx = 34;
      i = j;
    }
    while (i < k)
    {
      String str = paramVarArgs[i];
      paramVvrvrv.append('_').append(str);
      i += 1;
    }
    rrvvrv.bqq0071qq0071q0071q0071(paramVvrvrv.toString());
  }
  
  public int b0071qqqqq00710071q0071()
  {
    if ((b0078x0078x00780078xxx + b007800780078x00780078xxx) * b0078x0078x00780078xxx % bxxx007800780078xxx != bx00780078x00780078xxx)
    {
      if ((b0078x0078x00780078xxx + b007100710071007100710071q0071q0071()) * b0078x0078x00780078xxx % b0071q0071007100710071q0071q0071() != bqq0071007100710071q0071q0071())
      {
        b0078x0078x00780078xxx = bq00710071007100710071q0071q0071();
        bx00780078x00780078xxx = 47;
      }
      b0078x0078x00780078xxx = 58;
      bx00780078x00780078xxx = bq00710071007100710071q0071q0071();
    }
    return 11268;
  }
  
  /* Error */
  public void bqqqqqq00710071q0071()
  {
    // Byte code:
    //   0: aload_0
    //   1: invokevirtual 123	uuuuuu/vvvvrv:b0071qqqqq00710071q0071	()I
    //   4: istore_1
    //   5: aload_0
    //   6: getfield 56	uuuuuu/vvvvrv:bxx0078x00780078xxx	Lcom/db/pwcc/dbmobile/secure/preferences/SharedPreferencesHelper;
    //   9: astore 4
    //   11: ldc 125
    //   13: ldc 127
    //   15: bipush 43
    //   17: iconst_0
    //   18: invokestatic 133	xxxxxx/uxxxxx:bb00620062bb0062b0062b0062	(Ljava/lang/String;CC)Ljava/lang/String;
    //   21: iconst_0
    //   22: anewarray 41	java/lang/Class
    //   25: invokevirtual 137	java/lang/Class:getMethod	(Ljava/lang/String;[Ljava/lang/Class;)Ljava/lang/reflect/Method;
    //   28: astore 5
    //   30: aload 5
    //   32: aload 4
    //   34: iconst_0
    //   35: anewarray 4	java/lang/Object
    //   38: invokevirtual 143	java/lang/reflect/Method:invoke	(Ljava/lang/Object;[Ljava/lang/Object;)Ljava/lang/Object;
    //   41: astore 4
    //   43: aload 4
    //   45: checkcast 145	java/lang/Integer
    //   48: invokevirtual 148	java/lang/Integer:intValue	()I
    //   51: istore_2
    //   52: getstatic 47	uuuuuu/vvvvrv:b0078xxx00780078xxx	Ljava/lang/String;
    //   55: astore 4
    //   57: new 93	java/lang/StringBuilder
    //   60: dup
    //   61: invokespecial 149	java/lang/StringBuilder:<init>	()V
    //   64: astore 5
    //   66: ldc -105
    //   68: ldc -103
    //   70: bipush 25
    //   72: iconst_2
    //   73: invokestatic 133	xxxxxx/uxxxxx:bb00620062bb0062b0062b0062	(Ljava/lang/String;CC)Ljava/lang/String;
    //   76: iconst_4
    //   77: anewarray 41	java/lang/Class
    //   80: dup
    //   81: iconst_0
    //   82: ldc -101
    //   84: aastore
    //   85: dup
    //   86: iconst_1
    //   87: getstatic 161	java/lang/Character:TYPE	Ljava/lang/Class;
    //   90: aastore
    //   91: dup
    //   92: iconst_2
    //   93: getstatic 161	java/lang/Character:TYPE	Ljava/lang/Class;
    //   96: aastore
    //   97: dup
    //   98: iconst_3
    //   99: getstatic 161	java/lang/Character:TYPE	Ljava/lang/Class;
    //   102: aastore
    //   103: invokevirtual 137	java/lang/Class:getMethod	(Ljava/lang/String;[Ljava/lang/Class;)Ljava/lang/reflect/Method;
    //   106: astore 6
    //   108: aload 6
    //   110: aconst_null
    //   111: iconst_4
    //   112: anewarray 4	java/lang/Object
    //   115: dup
    //   116: iconst_0
    //   117: ldc -93
    //   119: aastore
    //   120: dup
    //   121: iconst_1
    //   122: bipush 75
    //   124: invokestatic 167	java/lang/Character:valueOf	(C)Ljava/lang/Character;
    //   127: aastore
    //   128: dup
    //   129: iconst_2
    //   130: sipush 206
    //   133: invokestatic 167	java/lang/Character:valueOf	(C)Ljava/lang/Character;
    //   136: aastore
    //   137: dup
    //   138: iconst_3
    //   139: iconst_2
    //   140: invokestatic 167	java/lang/Character:valueOf	(C)Ljava/lang/Character;
    //   143: aastore
    //   144: invokevirtual 143	java/lang/reflect/Method:invoke	(Ljava/lang/Object;[Ljava/lang/Object;)Ljava/lang/Object;
    //   147: astore 6
    //   149: aload 5
    //   151: aload 6
    //   153: checkcast 155	java/lang/String
    //   156: invokevirtual 108	java/lang/StringBuilder:append	(Ljava/lang/String;)Ljava/lang/StringBuilder;
    //   159: iload_1
    //   160: invokevirtual 170	java/lang/StringBuilder:append	(I)Ljava/lang/StringBuilder;
    //   163: astore 5
    //   165: ldc -105
    //   167: ldc -84
    //   169: sipush 157
    //   172: iconst_0
    //   173: invokestatic 133	xxxxxx/uxxxxx:bb00620062bb0062b0062b0062	(Ljava/lang/String;CC)Ljava/lang/String;
    //   176: iconst_3
    //   177: anewarray 41	java/lang/Class
    //   180: dup
    //   181: iconst_0
    //   182: ldc -101
    //   184: aastore
    //   185: dup
    //   186: iconst_1
    //   187: getstatic 161	java/lang/Character:TYPE	Ljava/lang/Class;
    //   190: aastore
    //   191: dup
    //   192: iconst_2
    //   193: getstatic 161	java/lang/Character:TYPE	Ljava/lang/Class;
    //   196: aastore
    //   197: invokevirtual 137	java/lang/Class:getMethod	(Ljava/lang/String;[Ljava/lang/Class;)Ljava/lang/reflect/Method;
    //   200: astore 6
    //   202: aload 6
    //   204: aconst_null
    //   205: iconst_3
    //   206: anewarray 4	java/lang/Object
    //   209: dup
    //   210: iconst_0
    //   211: ldc -82
    //   213: aastore
    //   214: dup
    //   215: iconst_1
    //   216: sipush 207
    //   219: invokestatic 167	java/lang/Character:valueOf	(C)Ljava/lang/Character;
    //   222: aastore
    //   223: dup
    //   224: iconst_2
    //   225: iconst_5
    //   226: invokestatic 167	java/lang/Character:valueOf	(C)Ljava/lang/Character;
    //   229: aastore
    //   230: invokevirtual 143	java/lang/reflect/Method:invoke	(Ljava/lang/Object;[Ljava/lang/Object;)Ljava/lang/Object;
    //   233: astore 6
    //   235: aload 4
    //   237: aload 5
    //   239: aload 6
    //   241: checkcast 155	java/lang/String
    //   244: invokevirtual 108	java/lang/StringBuilder:append	(Ljava/lang/String;)Ljava/lang/StringBuilder;
    //   247: iload_2
    //   248: invokevirtual 170	java/lang/StringBuilder:append	(I)Ljava/lang/StringBuilder;
    //   251: invokevirtual 109	java/lang/StringBuilder:toString	()Ljava/lang/String;
    //   254: invokestatic 180	uuuuuu/rvvvrv:bqqqq00710071q0071q0071	(Ljava/lang/String;Ljava/lang/String;)V
    //   257: iload_1
    //   258: iload_2
    //   259: if_icmple +15 -> 274
    //   262: aload_0
    //   263: getfield 61	uuuuuu/vvvvrv:b00780078xx00780078xxx	Ljava/util/List;
    //   266: invokeinterface 184 1 0
    //   271: ifeq +1569 -> 1840
    //   274: getstatic 47	uuuuuu/vvvvrv:b0078xxx00780078xxx	Ljava/lang/String;
    //   277: astore 4
    //   279: ldc -105
    //   281: ldc -70
    //   283: bipush 28
    //   285: iconst_5
    //   286: invokestatic 133	xxxxxx/uxxxxx:bb00620062bb0062b0062b0062	(Ljava/lang/String;CC)Ljava/lang/String;
    //   289: iconst_4
    //   290: anewarray 41	java/lang/Class
    //   293: dup
    //   294: iconst_0
    //   295: ldc -101
    //   297: aastore
    //   298: dup
    //   299: iconst_1
    //   300: getstatic 161	java/lang/Character:TYPE	Ljava/lang/Class;
    //   303: aastore
    //   304: dup
    //   305: iconst_2
    //   306: getstatic 161	java/lang/Character:TYPE	Ljava/lang/Class;
    //   309: aastore
    //   310: dup
    //   311: iconst_3
    //   312: getstatic 161	java/lang/Character:TYPE	Ljava/lang/Class;
    //   315: aastore
    //   316: invokevirtual 137	java/lang/Class:getMethod	(Ljava/lang/String;[Ljava/lang/Class;)Ljava/lang/reflect/Method;
    //   319: astore 5
    //   321: aload 5
    //   323: aconst_null
    //   324: iconst_4
    //   325: anewarray 4	java/lang/Object
    //   328: dup
    //   329: iconst_0
    //   330: ldc -68
    //   332: aastore
    //   333: dup
    //   334: iconst_1
    //   335: bipush 74
    //   337: invokestatic 167	java/lang/Character:valueOf	(C)Ljava/lang/Character;
    //   340: aastore
    //   341: dup
    //   342: iconst_2
    //   343: sipush 129
    //   346: invokestatic 167	java/lang/Character:valueOf	(C)Ljava/lang/Character;
    //   349: aastore
    //   350: dup
    //   351: iconst_3
    //   352: iconst_1
    //   353: invokestatic 167	java/lang/Character:valueOf	(C)Ljava/lang/Character;
    //   356: aastore
    //   357: invokevirtual 143	java/lang/reflect/Method:invoke	(Ljava/lang/Object;[Ljava/lang/Object;)Ljava/lang/Object;
    //   360: astore 5
    //   362: aload 4
    //   364: aload 5
    //   366: checkcast 155	java/lang/String
    //   369: invokestatic 191	uuuuuu/rvvvrv:b007100710071q00710071q0071q0071	(Ljava/lang/String;Ljava/lang/String;)V
    //   372: return
    //   373: aload 7
    //   375: aload 8
    //   377: invokestatic 180	uuuuuu/rvvvrv:bqqqq00710071q0071q0071	(Ljava/lang/String;Ljava/lang/String;)V
    //   380: aload 5
    //   382: invokeinterface 196 1 0
    //   387: aload 4
    //   389: invokeinterface 201 1 0
    //   394: aload 4
    //   396: invokeinterface 204 1 0
    //   401: ifeq +598 -> 999
    //   404: aload 4
    //   406: invokeinterface 208 1 0
    //   411: checkcast 193	uuuuuu/vrvrvv
    //   414: astore 5
    //   416: aload 5
    //   418: invokeinterface 211 1 0
    //   423: astore 6
    //   425: getstatic 215	uuuuuu/vvrvrv:bhhhhh0068h00680068	Luuuuuu/vvrvrv;
    //   428: astore 7
    //   430: getstatic 26	uuuuuu/vvvvrv:b0078x0078x00780078xxx	I
    //   433: getstatic 28	uuuuuu/vvvvrv:b007800780078x00780078xxx	I
    //   436: iadd
    //   437: getstatic 26	uuuuuu/vvvvrv:b0078x0078x00780078xxx	I
    //   440: imul
    //   441: invokestatic 32	uuuuuu/vvvvrv:b0071q0071007100710071q0071q0071	()I
    //   444: irem
    //   445: invokestatic 91	uuuuuu/vvvvrv:bqq0071007100710071q0071q0071	()I
    //   448: if_icmpeq +14 -> 462
    //   451: invokestatic 37	uuuuuu/vvvvrv:bq00710071007100710071q0071q0071	()I
    //   454: putstatic 26	uuuuuu/vvvvrv:b0078x0078x00780078xxx	I
    //   457: bipush 47
    //   459: putstatic 34	uuuuuu/vvvvrv:bx00780078x00780078xxx	I
    //   462: ldc -105
    //   464: ldc -39
    //   466: sipush 154
    //   469: iconst_3
    //   470: invokestatic 133	xxxxxx/uxxxxx:bb00620062bb0062b0062b0062	(Ljava/lang/String;CC)Ljava/lang/String;
    //   473: iconst_4
    //   474: anewarray 41	java/lang/Class
    //   477: dup
    //   478: iconst_0
    //   479: ldc -101
    //   481: aastore
    //   482: dup
    //   483: iconst_1
    //   484: getstatic 161	java/lang/Character:TYPE	Ljava/lang/Class;
    //   487: aastore
    //   488: dup
    //   489: iconst_2
    //   490: getstatic 161	java/lang/Character:TYPE	Ljava/lang/Class;
    //   493: aastore
    //   494: dup
    //   495: iconst_3
    //   496: getstatic 161	java/lang/Character:TYPE	Ljava/lang/Class;
    //   499: aastore
    //   500: invokevirtual 137	java/lang/Class:getMethod	(Ljava/lang/String;[Ljava/lang/Class;)Ljava/lang/reflect/Method;
    //   503: astore 8
    //   505: aload 8
    //   507: aconst_null
    //   508: iconst_4
    //   509: anewarray 4	java/lang/Object
    //   512: dup
    //   513: iconst_0
    //   514: ldc -37
    //   516: aastore
    //   517: dup
    //   518: iconst_1
    //   519: bipush 88
    //   521: invokestatic 167	java/lang/Character:valueOf	(C)Ljava/lang/Character;
    //   524: aastore
    //   525: dup
    //   526: iconst_2
    //   527: iconst_4
    //   528: invokestatic 167	java/lang/Character:valueOf	(C)Ljava/lang/Character;
    //   531: aastore
    //   532: dup
    //   533: iconst_3
    //   534: iconst_2
    //   535: invokestatic 167	java/lang/Character:valueOf	(C)Ljava/lang/Character;
    //   538: aastore
    //   539: invokevirtual 143	java/lang/reflect/Method:invoke	(Ljava/lang/Object;[Ljava/lang/Object;)Ljava/lang/Object;
    //   542: astore 8
    //   544: aload 8
    //   546: checkcast 155	java/lang/String
    //   549: astore 8
    //   551: ldc -105
    //   553: ldc -35
    //   555: sipush 169
    //   558: iconst_0
    //   559: invokestatic 133	xxxxxx/uxxxxx:bb00620062bb0062b0062b0062	(Ljava/lang/String;CC)Ljava/lang/String;
    //   562: iconst_3
    //   563: anewarray 41	java/lang/Class
    //   566: dup
    //   567: iconst_0
    //   568: ldc -101
    //   570: aastore
    //   571: dup
    //   572: iconst_1
    //   573: getstatic 161	java/lang/Character:TYPE	Ljava/lang/Class;
    //   576: aastore
    //   577: dup
    //   578: iconst_2
    //   579: getstatic 161	java/lang/Character:TYPE	Ljava/lang/Class;
    //   582: aastore
    //   583: invokevirtual 137	java/lang/Class:getMethod	(Ljava/lang/String;[Ljava/lang/Class;)Ljava/lang/reflect/Method;
    //   586: astore 9
    //   588: aload 9
    //   590: aconst_null
    //   591: iconst_3
    //   592: anewarray 4	java/lang/Object
    //   595: dup
    //   596: iconst_0
    //   597: ldc -33
    //   599: aastore
    //   600: dup
    //   601: iconst_1
    //   602: iconst_3
    //   603: invokestatic 167	java/lang/Character:valueOf	(C)Ljava/lang/Character;
    //   606: aastore
    //   607: dup
    //   608: iconst_2
    //   609: iconst_4
    //   610: invokestatic 167	java/lang/Character:valueOf	(C)Ljava/lang/Character;
    //   613: aastore
    //   614: invokevirtual 143	java/lang/reflect/Method:invoke	(Ljava/lang/Object;[Ljava/lang/Object;)Ljava/lang/Object;
    //   617: astore 9
    //   619: aload 9
    //   621: checkcast 155	java/lang/String
    //   624: astore 9
    //   626: ldc -105
    //   628: ldc -31
    //   630: sipush 249
    //   633: iconst_5
    //   634: invokestatic 133	xxxxxx/uxxxxx:bb00620062bb0062b0062b0062	(Ljava/lang/String;CC)Ljava/lang/String;
    //   637: iconst_3
    //   638: anewarray 41	java/lang/Class
    //   641: dup
    //   642: iconst_0
    //   643: ldc -101
    //   645: aastore
    //   646: dup
    //   647: iconst_1
    //   648: getstatic 161	java/lang/Character:TYPE	Ljava/lang/Class;
    //   651: aastore
    //   652: dup
    //   653: iconst_2
    //   654: getstatic 161	java/lang/Character:TYPE	Ljava/lang/Class;
    //   657: aastore
    //   658: invokevirtual 137	java/lang/Class:getMethod	(Ljava/lang/String;[Ljava/lang/Class;)Ljava/lang/reflect/Method;
    //   661: astore 10
    //   663: aload 10
    //   665: aconst_null
    //   666: iconst_3
    //   667: anewarray 4	java/lang/Object
    //   670: dup
    //   671: iconst_0
    //   672: ldc -29
    //   674: aastore
    //   675: dup
    //   676: iconst_1
    //   677: sipush 228
    //   680: invokestatic 167	java/lang/Character:valueOf	(C)Ljava/lang/Character;
    //   683: aastore
    //   684: dup
    //   685: iconst_2
    //   686: iconst_4
    //   687: invokestatic 167	java/lang/Character:valueOf	(C)Ljava/lang/Character;
    //   690: aastore
    //   691: invokevirtual 143	java/lang/reflect/Method:invoke	(Ljava/lang/Object;[Ljava/lang/Object;)Ljava/lang/Object;
    //   694: astore 10
    //   696: aload 10
    //   698: checkcast 155	java/lang/String
    //   701: astore 10
    //   703: aload 5
    //   705: invokeinterface 230 1 0
    //   710: istore_3
    //   711: ldc -105
    //   713: ldc -24
    //   715: bipush 97
    //   717: iconst_4
    //   718: invokestatic 133	xxxxxx/uxxxxx:bb00620062bb0062b0062b0062	(Ljava/lang/String;CC)Ljava/lang/String;
    //   721: iconst_3
    //   722: anewarray 41	java/lang/Class
    //   725: dup
    //   726: iconst_0
    //   727: ldc -101
    //   729: aastore
    //   730: dup
    //   731: iconst_1
    //   732: getstatic 161	java/lang/Character:TYPE	Ljava/lang/Class;
    //   735: aastore
    //   736: dup
    //   737: iconst_2
    //   738: getstatic 161	java/lang/Character:TYPE	Ljava/lang/Class;
    //   741: aastore
    //   742: invokevirtual 137	java/lang/Class:getMethod	(Ljava/lang/String;[Ljava/lang/Class;)Ljava/lang/reflect/Method;
    //   745: astore 11
    //   747: aload 11
    //   749: aconst_null
    //   750: iconst_3
    //   751: anewarray 4	java/lang/Object
    //   754: dup
    //   755: iconst_0
    //   756: ldc -22
    //   758: aastore
    //   759: dup
    //   760: iconst_1
    //   761: bipush 40
    //   763: invokestatic 167	java/lang/Character:valueOf	(C)Ljava/lang/Character;
    //   766: aastore
    //   767: dup
    //   768: iconst_2
    //   769: iconst_3
    //   770: invokestatic 167	java/lang/Character:valueOf	(C)Ljava/lang/Character;
    //   773: aastore
    //   774: invokevirtual 143	java/lang/reflect/Method:invoke	(Ljava/lang/Object;[Ljava/lang/Object;)Ljava/lang/Object;
    //   777: astore 11
    //   779: aload_0
    //   780: aload 7
    //   782: bipush 9
    //   784: anewarray 155	java/lang/String
    //   787: dup
    //   788: iconst_0
    //   789: aload 6
    //   791: aastore
    //   792: dup
    //   793: iconst_1
    //   794: aload 8
    //   796: aastore
    //   797: dup
    //   798: iconst_2
    //   799: iload_1
    //   800: invokestatic 237	java/lang/String:valueOf	(I)Ljava/lang/String;
    //   803: aastore
    //   804: dup
    //   805: iconst_3
    //   806: aload 9
    //   808: aastore
    //   809: dup
    //   810: iconst_4
    //   811: iload_2
    //   812: invokestatic 237	java/lang/String:valueOf	(I)Ljava/lang/String;
    //   815: aastore
    //   816: dup
    //   817: iconst_5
    //   818: aload 10
    //   820: aastore
    //   821: dup
    //   822: bipush 6
    //   824: iload_3
    //   825: invokestatic 237	java/lang/String:valueOf	(I)Ljava/lang/String;
    //   828: aastore
    //   829: dup
    //   830: bipush 7
    //   832: aload 11
    //   834: checkcast 155	java/lang/String
    //   837: aastore
    //   838: dup
    //   839: bipush 8
    //   841: aload 5
    //   843: invokeinterface 240 1 0
    //   848: invokestatic 237	java/lang/String:valueOf	(I)Ljava/lang/String;
    //   851: aastore
    //   852: invokevirtual 242	uuuuuu/vvvvrv:b00710071qqqq00710071q0071	(Luuuuuu/vvrvrv;[Ljava/lang/String;)V
    //   855: iload_1
    //   856: aload 5
    //   858: invokeinterface 230 1 0
    //   863: if_icmplt +343 -> 1206
    //   866: iload_1
    //   867: aload 5
    //   869: invokeinterface 240 1 0
    //   874: if_icmpgt +332 -> 1206
    //   877: aload_0
    //   878: getstatic 245	uuuuuu/vvrvrv:bh0068hhh0068h00680068	Luuuuuu/vvrvrv;
    //   881: iconst_1
    //   882: anewarray 155	java/lang/String
    //   885: dup
    //   886: iconst_0
    //   887: aload 6
    //   889: aastore
    //   890: invokevirtual 242	uuuuuu/vvvvrv:b00710071qqqq00710071q0071	(Luuuuuu/vvrvrv;[Ljava/lang/String;)V
    //   893: getstatic 47	uuuuuu/vvvvrv:b0078xxx00780078xxx	Ljava/lang/String;
    //   896: astore 7
    //   898: new 93	java/lang/StringBuilder
    //   901: dup
    //   902: invokespecial 149	java/lang/StringBuilder:<init>	()V
    //   905: astore 8
    //   907: ldc -105
    //   909: ldc -9
    //   911: bipush 7
    //   913: iconst_1
    //   914: invokestatic 133	xxxxxx/uxxxxx:bb00620062bb0062b0062b0062	(Ljava/lang/String;CC)Ljava/lang/String;
    //   917: iconst_3
    //   918: anewarray 41	java/lang/Class
    //   921: dup
    //   922: iconst_0
    //   923: ldc -101
    //   925: aastore
    //   926: dup
    //   927: iconst_1
    //   928: getstatic 161	java/lang/Character:TYPE	Ljava/lang/Class;
    //   931: aastore
    //   932: dup
    //   933: iconst_2
    //   934: getstatic 161	java/lang/Character:TYPE	Ljava/lang/Class;
    //   937: aastore
    //   938: invokevirtual 137	java/lang/Class:getMethod	(Ljava/lang/String;[Ljava/lang/Class;)Ljava/lang/reflect/Method;
    //   941: astore 9
    //   943: aload 9
    //   945: aconst_null
    //   946: iconst_3
    //   947: anewarray 4	java/lang/Object
    //   950: dup
    //   951: iconst_0
    //   952: ldc -7
    //   954: aastore
    //   955: dup
    //   956: iconst_1
    //   957: sipush 162
    //   960: invokestatic 167	java/lang/Character:valueOf	(C)Ljava/lang/Character;
    //   963: aastore
    //   964: dup
    //   965: iconst_2
    //   966: iconst_3
    //   967: invokestatic 167	java/lang/Character:valueOf	(C)Ljava/lang/Character;
    //   970: aastore
    //   971: invokevirtual 143	java/lang/reflect/Method:invoke	(Ljava/lang/Object;[Ljava/lang/Object;)Ljava/lang/Object;
    //   974: astore 9
    //   976: aload 8
    //   978: aload 9
    //   980: checkcast 155	java/lang/String
    //   983: invokevirtual 108	java/lang/StringBuilder:append	(Ljava/lang/String;)Ljava/lang/StringBuilder;
    //   986: aload 6
    //   988: invokevirtual 108	java/lang/StringBuilder:append	(Ljava/lang/String;)Ljava/lang/StringBuilder;
    //   991: invokevirtual 109	java/lang/StringBuilder:toString	()Ljava/lang/String;
    //   994: astore 8
    //   996: goto -623 -> 373
    //   999: getstatic 47	uuuuuu/vvvvrv:b0078xxx00780078xxx	Ljava/lang/String;
    //   1002: astore 4
    //   1004: ldc -105
    //   1006: ldc -5
    //   1008: bipush 22
    //   1010: bipush 119
    //   1012: iconst_1
    //   1013: invokestatic 255	xxxxxx/uxxxxx:bbbb0062b0062b0062b0062	(Ljava/lang/String;CCC)Ljava/lang/String;
    //   1016: iconst_3
    //   1017: anewarray 41	java/lang/Class
    //   1020: dup
    //   1021: iconst_0
    //   1022: ldc -101
    //   1024: aastore
    //   1025: dup
    //   1026: iconst_1
    //   1027: getstatic 161	java/lang/Character:TYPE	Ljava/lang/Class;
    //   1030: aastore
    //   1031: dup
    //   1032: iconst_2
    //   1033: getstatic 161	java/lang/Character:TYPE	Ljava/lang/Class;
    //   1036: aastore
    //   1037: invokevirtual 137	java/lang/Class:getMethod	(Ljava/lang/String;[Ljava/lang/Class;)Ljava/lang/reflect/Method;
    //   1040: astore 5
    //   1042: aload 5
    //   1044: aconst_null
    //   1045: iconst_3
    //   1046: anewarray 4	java/lang/Object
    //   1049: dup
    //   1050: iconst_0
    //   1051: ldc_w 257
    //   1054: aastore
    //   1055: dup
    //   1056: iconst_1
    //   1057: sipush 159
    //   1060: invokestatic 167	java/lang/Character:valueOf	(C)Ljava/lang/Character;
    //   1063: aastore
    //   1064: dup
    //   1065: iconst_2
    //   1066: iconst_5
    //   1067: invokestatic 167	java/lang/Character:valueOf	(C)Ljava/lang/Character;
    //   1070: aastore
    //   1071: invokevirtual 143	java/lang/reflect/Method:invoke	(Ljava/lang/Object;[Ljava/lang/Object;)Ljava/lang/Object;
    //   1074: astore 5
    //   1076: aload 5
    //   1078: checkcast 155	java/lang/String
    //   1081: astore 5
    //   1083: getstatic 26	uuuuuu/vvvvrv:b0078x0078x00780078xxx	I
    //   1086: istore_2
    //   1087: iload_2
    //   1088: getstatic 28	uuuuuu/vvvvrv:b007800780078x00780078xxx	I
    //   1091: iload_2
    //   1092: iadd
    //   1093: imul
    //   1094: getstatic 39	uuuuuu/vvvvrv:bxxx007800780078xxx	I
    //   1097: irem
    //   1098: tableswitch	default:+18->1116, 0:+28->1126
    //   1116: iconst_2
    //   1117: putstatic 26	uuuuuu/vvvvrv:b0078x0078x00780078xxx	I
    //   1120: invokestatic 37	uuuuuu/vvvvrv:bq00710071007100710071q0071q0071	()I
    //   1123: putstatic 34	uuuuuu/vvvvrv:bx00780078x00780078xxx	I
    //   1126: aload 4
    //   1128: aload 5
    //   1130: invokestatic 191	uuuuuu/rvvvrv:b007100710071q00710071q0071q0071	(Ljava/lang/String;Ljava/lang/String;)V
    //   1133: aload_0
    //   1134: getfield 61	uuuuuu/vvvvrv:b00780078xx00780078xxx	Ljava/util/List;
    //   1137: invokeinterface 184 1 0
    //   1142: ifeq -770 -> 372
    //   1145: aload_0
    //   1146: getfield 56	uuuuuu/vvvvrv:bxx0078x00780078xxx	Lcom/db/pwcc/dbmobile/secure/preferences/SharedPreferencesHelper;
    //   1149: astore 4
    //   1151: ldc 125
    //   1153: ldc_w 259
    //   1156: sipush 137
    //   1159: iconst_4
    //   1160: invokestatic 133	xxxxxx/uxxxxx:bb00620062bb0062b0062b0062	(Ljava/lang/String;CC)Ljava/lang/String;
    //   1163: iconst_1
    //   1164: anewarray 41	java/lang/Class
    //   1167: dup
    //   1168: iconst_0
    //   1169: getstatic 260	java/lang/Integer:TYPE	Ljava/lang/Class;
    //   1172: aastore
    //   1173: invokevirtual 137	java/lang/Class:getMethod	(Ljava/lang/String;[Ljava/lang/Class;)Ljava/lang/reflect/Method;
    //   1176: astore 5
    //   1178: aload 5
    //   1180: aload 4
    //   1182: iconst_1
    //   1183: anewarray 4	java/lang/Object
    //   1186: dup
    //   1187: iconst_0
    //   1188: iload_1
    //   1189: invokestatic 263	java/lang/Integer:valueOf	(I)Ljava/lang/Integer;
    //   1192: aastore
    //   1193: invokevirtual 143	java/lang/reflect/Method:invoke	(Ljava/lang/Object;[Ljava/lang/Object;)Ljava/lang/Object;
    //   1196: pop
    //   1197: return
    //   1198: astore 4
    //   1200: aload 4
    //   1202: invokevirtual 267	java/lang/reflect/InvocationTargetException:getCause	()Ljava/lang/Throwable;
    //   1205: athrow
    //   1206: aload_0
    //   1207: getstatic 270	uuuuuu/vvrvrv:b00680068hhh0068h00680068	Luuuuuu/vvrvrv;
    //   1210: iconst_1
    //   1211: anewarray 155	java/lang/String
    //   1214: dup
    //   1215: iconst_0
    //   1216: aload 6
    //   1218: aastore
    //   1219: invokevirtual 242	uuuuuu/vvvvrv:b00710071qqqq00710071q0071	(Luuuuuu/vvrvrv;[Ljava/lang/String;)V
    //   1222: getstatic 47	uuuuuu/vvvvrv:b0078xxx00780078xxx	Ljava/lang/String;
    //   1225: astore 7
    //   1227: new 93	java/lang/StringBuilder
    //   1230: dup
    //   1231: invokespecial 149	java/lang/StringBuilder:<init>	()V
    //   1234: astore 8
    //   1236: ldc -105
    //   1238: ldc_w 272
    //   1241: sipush 171
    //   1244: iconst_1
    //   1245: invokestatic 133	xxxxxx/uxxxxx:bb00620062bb0062b0062b0062	(Ljava/lang/String;CC)Ljava/lang/String;
    //   1248: iconst_3
    //   1249: anewarray 41	java/lang/Class
    //   1252: dup
    //   1253: iconst_0
    //   1254: ldc -101
    //   1256: aastore
    //   1257: dup
    //   1258: iconst_1
    //   1259: getstatic 161	java/lang/Character:TYPE	Ljava/lang/Class;
    //   1262: aastore
    //   1263: dup
    //   1264: iconst_2
    //   1265: getstatic 161	java/lang/Character:TYPE	Ljava/lang/Class;
    //   1268: aastore
    //   1269: invokevirtual 137	java/lang/Class:getMethod	(Ljava/lang/String;[Ljava/lang/Class;)Ljava/lang/reflect/Method;
    //   1272: astore 9
    //   1274: aload 9
    //   1276: aconst_null
    //   1277: iconst_3
    //   1278: anewarray 4	java/lang/Object
    //   1281: dup
    //   1282: iconst_0
    //   1283: ldc_w 274
    //   1286: aastore
    //   1287: dup
    //   1288: iconst_1
    //   1289: sipush 162
    //   1292: invokestatic 167	java/lang/Character:valueOf	(C)Ljava/lang/Character;
    //   1295: aastore
    //   1296: dup
    //   1297: iconst_2
    //   1298: iconst_5
    //   1299: invokestatic 167	java/lang/Character:valueOf	(C)Ljava/lang/Character;
    //   1302: aastore
    //   1303: invokevirtual 143	java/lang/reflect/Method:invoke	(Ljava/lang/Object;[Ljava/lang/Object;)Ljava/lang/Object;
    //   1306: astore 9
    //   1308: aload 8
    //   1310: aload 9
    //   1312: checkcast 155	java/lang/String
    //   1315: invokevirtual 108	java/lang/StringBuilder:append	(Ljava/lang/String;)Ljava/lang/StringBuilder;
    //   1318: aload 6
    //   1320: invokevirtual 108	java/lang/StringBuilder:append	(Ljava/lang/String;)Ljava/lang/StringBuilder;
    //   1323: astore 6
    //   1325: ldc -105
    //   1327: ldc_w 276
    //   1330: bipush 107
    //   1332: iconst_2
    //   1333: invokestatic 133	xxxxxx/uxxxxx:bb00620062bb0062b0062b0062	(Ljava/lang/String;CC)Ljava/lang/String;
    //   1336: iconst_4
    //   1337: anewarray 41	java/lang/Class
    //   1340: dup
    //   1341: iconst_0
    //   1342: ldc -101
    //   1344: aastore
    //   1345: dup
    //   1346: iconst_1
    //   1347: getstatic 161	java/lang/Character:TYPE	Ljava/lang/Class;
    //   1350: aastore
    //   1351: dup
    //   1352: iconst_2
    //   1353: getstatic 161	java/lang/Character:TYPE	Ljava/lang/Class;
    //   1356: aastore
    //   1357: dup
    //   1358: iconst_3
    //   1359: getstatic 161	java/lang/Character:TYPE	Ljava/lang/Class;
    //   1362: aastore
    //   1363: invokevirtual 137	java/lang/Class:getMethod	(Ljava/lang/String;[Ljava/lang/Class;)Ljava/lang/reflect/Method;
    //   1366: astore 8
    //   1368: aload 8
    //   1370: aconst_null
    //   1371: iconst_4
    //   1372: anewarray 4	java/lang/Object
    //   1375: dup
    //   1376: iconst_0
    //   1377: ldc_w 278
    //   1380: aastore
    //   1381: dup
    //   1382: iconst_1
    //   1383: sipush 206
    //   1386: invokestatic 167	java/lang/Character:valueOf	(C)Ljava/lang/Character;
    //   1389: aastore
    //   1390: dup
    //   1391: iconst_2
    //   1392: bipush 42
    //   1394: invokestatic 167	java/lang/Character:valueOf	(C)Ljava/lang/Character;
    //   1397: aastore
    //   1398: dup
    //   1399: iconst_3
    //   1400: iconst_3
    //   1401: invokestatic 167	java/lang/Character:valueOf	(C)Ljava/lang/Character;
    //   1404: aastore
    //   1405: invokevirtual 143	java/lang/reflect/Method:invoke	(Ljava/lang/Object;[Ljava/lang/Object;)Ljava/lang/Object;
    //   1408: astore 8
    //   1410: aload 6
    //   1412: aload 8
    //   1414: checkcast 155	java/lang/String
    //   1417: invokevirtual 108	java/lang/StringBuilder:append	(Ljava/lang/String;)Ljava/lang/StringBuilder;
    //   1420: aload 5
    //   1422: invokeinterface 230 1 0
    //   1427: invokevirtual 170	java/lang/StringBuilder:append	(I)Ljava/lang/StringBuilder;
    //   1430: astore 6
    //   1432: ldc -105
    //   1434: ldc_w 280
    //   1437: sipush 215
    //   1440: bipush 48
    //   1442: iconst_1
    //   1443: invokestatic 255	xxxxxx/uxxxxx:bbbb0062b0062b0062b0062	(Ljava/lang/String;CCC)Ljava/lang/String;
    //   1446: iconst_4
    //   1447: anewarray 41	java/lang/Class
    //   1450: dup
    //   1451: iconst_0
    //   1452: ldc -101
    //   1454: aastore
    //   1455: dup
    //   1456: iconst_1
    //   1457: getstatic 161	java/lang/Character:TYPE	Ljava/lang/Class;
    //   1460: aastore
    //   1461: dup
    //   1462: iconst_2
    //   1463: getstatic 161	java/lang/Character:TYPE	Ljava/lang/Class;
    //   1466: aastore
    //   1467: dup
    //   1468: iconst_3
    //   1469: getstatic 161	java/lang/Character:TYPE	Ljava/lang/Class;
    //   1472: aastore
    //   1473: invokevirtual 137	java/lang/Class:getMethod	(Ljava/lang/String;[Ljava/lang/Class;)Ljava/lang/reflect/Method;
    //   1476: astore 8
    //   1478: aload 8
    //   1480: aconst_null
    //   1481: iconst_4
    //   1482: anewarray 4	java/lang/Object
    //   1485: dup
    //   1486: iconst_0
    //   1487: ldc_w 282
    //   1490: aastore
    //   1491: dup
    //   1492: iconst_1
    //   1493: sipush 198
    //   1496: invokestatic 167	java/lang/Character:valueOf	(C)Ljava/lang/Character;
    //   1499: aastore
    //   1500: dup
    //   1501: iconst_2
    //   1502: sipush 211
    //   1505: invokestatic 167	java/lang/Character:valueOf	(C)Ljava/lang/Character;
    //   1508: aastore
    //   1509: dup
    //   1510: iconst_3
    //   1511: iconst_1
    //   1512: invokestatic 167	java/lang/Character:valueOf	(C)Ljava/lang/Character;
    //   1515: aastore
    //   1516: invokevirtual 143	java/lang/reflect/Method:invoke	(Ljava/lang/Object;[Ljava/lang/Object;)Ljava/lang/Object;
    //   1519: astore 8
    //   1521: aload 6
    //   1523: aload 8
    //   1525: checkcast 155	java/lang/String
    //   1528: invokevirtual 108	java/lang/StringBuilder:append	(Ljava/lang/String;)Ljava/lang/StringBuilder;
    //   1531: aload 5
    //   1533: invokeinterface 240 1 0
    //   1538: invokevirtual 170	java/lang/StringBuilder:append	(I)Ljava/lang/StringBuilder;
    //   1541: astore 5
    //   1543: ldc -105
    //   1545: ldc_w 284
    //   1548: bipush 34
    //   1550: iconst_0
    //   1551: invokestatic 133	xxxxxx/uxxxxx:bb00620062bb0062b0062b0062	(Ljava/lang/String;CC)Ljava/lang/String;
    //   1554: iconst_3
    //   1555: anewarray 41	java/lang/Class
    //   1558: dup
    //   1559: iconst_0
    //   1560: ldc -101
    //   1562: aastore
    //   1563: dup
    //   1564: iconst_1
    //   1565: getstatic 161	java/lang/Character:TYPE	Ljava/lang/Class;
    //   1568: aastore
    //   1569: dup
    //   1570: iconst_2
    //   1571: getstatic 161	java/lang/Character:TYPE	Ljava/lang/Class;
    //   1574: aastore
    //   1575: invokevirtual 137	java/lang/Class:getMethod	(Ljava/lang/String;[Ljava/lang/Class;)Ljava/lang/reflect/Method;
    //   1578: astore 6
    //   1580: aload 6
    //   1582: aconst_null
    //   1583: iconst_3
    //   1584: anewarray 4	java/lang/Object
    //   1587: dup
    //   1588: iconst_0
    //   1589: ldc_w 286
    //   1592: aastore
    //   1593: dup
    //   1594: iconst_1
    //   1595: bipush 37
    //   1597: invokestatic 167	java/lang/Character:valueOf	(C)Ljava/lang/Character;
    //   1600: aastore
    //   1601: dup
    //   1602: iconst_2
    //   1603: iconst_0
    //   1604: invokestatic 167	java/lang/Character:valueOf	(C)Ljava/lang/Character;
    //   1607: aastore
    //   1608: invokevirtual 143	java/lang/reflect/Method:invoke	(Ljava/lang/Object;[Ljava/lang/Object;)Ljava/lang/Object;
    //   1611: astore 6
    //   1613: aload 7
    //   1615: aload 5
    //   1617: aload 6
    //   1619: checkcast 155	java/lang/String
    //   1622: invokevirtual 108	java/lang/StringBuilder:append	(Ljava/lang/String;)Ljava/lang/StringBuilder;
    //   1625: invokevirtual 109	java/lang/StringBuilder:toString	()Ljava/lang/String;
    //   1628: invokestatic 180	uuuuuu/rvvvrv:bqqqq00710071q0071q0071	(Ljava/lang/String;Ljava/lang/String;)V
    //   1631: goto -1244 -> 387
    //   1634: astore 4
    //   1636: aload 4
    //   1638: invokevirtual 267	java/lang/reflect/InvocationTargetException:getCause	()Ljava/lang/Throwable;
    //   1641: athrow
    //   1642: astore 4
    //   1644: aload 4
    //   1646: invokevirtual 267	java/lang/reflect/InvocationTargetException:getCause	()Ljava/lang/Throwable;
    //   1649: athrow
    //   1650: astore 5
    //   1652: aload_0
    //   1653: getstatic 289	uuuuuu/vvrvrv:b0068hhhh0068h00680068	Luuuuuu/vvrvrv;
    //   1656: iconst_1
    //   1657: anewarray 155	java/lang/String
    //   1660: dup
    //   1661: iconst_0
    //   1662: aload 6
    //   1664: aastore
    //   1665: invokevirtual 242	uuuuuu/vvvvrv:b00710071qqqq00710071q0071	(Luuuuuu/vvrvrv;[Ljava/lang/String;)V
    //   1668: getstatic 47	uuuuuu/vvvvrv:b0078xxx00780078xxx	Ljava/lang/String;
    //   1671: astore 5
    //   1673: new 93	java/lang/StringBuilder
    //   1676: dup
    //   1677: invokespecial 149	java/lang/StringBuilder:<init>	()V
    //   1680: astore 7
    //   1682: ldc -105
    //   1684: ldc_w 291
    //   1687: bipush 118
    //   1689: iconst_3
    //   1690: invokestatic 133	xxxxxx/uxxxxx:bb00620062bb0062b0062b0062	(Ljava/lang/String;CC)Ljava/lang/String;
    //   1693: iconst_4
    //   1694: anewarray 41	java/lang/Class
    //   1697: dup
    //   1698: iconst_0
    //   1699: ldc -101
    //   1701: aastore
    //   1702: dup
    //   1703: iconst_1
    //   1704: getstatic 161	java/lang/Character:TYPE	Ljava/lang/Class;
    //   1707: aastore
    //   1708: dup
    //   1709: iconst_2
    //   1710: getstatic 161	java/lang/Character:TYPE	Ljava/lang/Class;
    //   1713: aastore
    //   1714: dup
    //   1715: iconst_3
    //   1716: getstatic 161	java/lang/Character:TYPE	Ljava/lang/Class;
    //   1719: aastore
    //   1720: invokevirtual 137	java/lang/Class:getMethod	(Ljava/lang/String;[Ljava/lang/Class;)Ljava/lang/reflect/Method;
    //   1723: astore 8
    //   1725: aload 8
    //   1727: aconst_null
    //   1728: iconst_4
    //   1729: anewarray 4	java/lang/Object
    //   1732: dup
    //   1733: iconst_0
    //   1734: ldc_w 293
    //   1737: aastore
    //   1738: dup
    //   1739: iconst_1
    //   1740: bipush 126
    //   1742: invokestatic 167	java/lang/Character:valueOf	(C)Ljava/lang/Character;
    //   1745: aastore
    //   1746: dup
    //   1747: iconst_2
    //   1748: bipush 64
    //   1750: invokestatic 167	java/lang/Character:valueOf	(C)Ljava/lang/Character;
    //   1753: aastore
    //   1754: dup
    //   1755: iconst_3
    //   1756: iconst_1
    //   1757: invokestatic 167	java/lang/Character:valueOf	(C)Ljava/lang/Character;
    //   1760: aastore
    //   1761: invokevirtual 143	java/lang/reflect/Method:invoke	(Ljava/lang/Object;[Ljava/lang/Object;)Ljava/lang/Object;
    //   1764: astore 8
    //   1766: aload 5
    //   1768: aload 7
    //   1770: aload 8
    //   1772: checkcast 155	java/lang/String
    //   1775: invokevirtual 108	java/lang/StringBuilder:append	(Ljava/lang/String;)Ljava/lang/StringBuilder;
    //   1778: aload 6
    //   1780: invokevirtual 108	java/lang/StringBuilder:append	(Ljava/lang/String;)Ljava/lang/StringBuilder;
    //   1783: invokevirtual 109	java/lang/StringBuilder:toString	()Ljava/lang/String;
    //   1786: invokestatic 296	uuuuuu/rvvvrv:bq0071qq00710071q0071q0071	(Ljava/lang/String;Ljava/lang/String;)V
    //   1789: goto -1402 -> 387
    //   1792: astore 4
    //   1794: aload 4
    //   1796: invokevirtual 267	java/lang/reflect/InvocationTargetException:getCause	()Ljava/lang/Throwable;
    //   1799: athrow
    //   1800: astore 4
    //   1802: aload 4
    //   1804: invokevirtual 267	java/lang/reflect/InvocationTargetException:getCause	()Ljava/lang/Throwable;
    //   1807: athrow
    //   1808: astore 4
    //   1810: aload 4
    //   1812: invokevirtual 267	java/lang/reflect/InvocationTargetException:getCause	()Ljava/lang/Throwable;
    //   1815: athrow
    //   1816: astore 4
    //   1818: aload 4
    //   1820: invokevirtual 267	java/lang/reflect/InvocationTargetException:getCause	()Ljava/lang/Throwable;
    //   1823: athrow
    //   1824: astore 4
    //   1826: aload 4
    //   1828: invokevirtual 267	java/lang/reflect/InvocationTargetException:getCause	()Ljava/lang/Throwable;
    //   1831: athrow
    //   1832: astore 4
    //   1834: aload 4
    //   1836: invokevirtual 267	java/lang/reflect/InvocationTargetException:getCause	()Ljava/lang/Throwable;
    //   1839: athrow
    //   1840: aload_0
    //   1841: getfield 61	uuuuuu/vvvvrv:b00780078xx00780078xxx	Ljava/util/List;
    //   1844: invokeinterface 300 1 0
    //   1849: astore 4
    //   1851: goto -1457 -> 394
    //   1854: astore 4
    //   1856: aload 4
    //   1858: invokevirtual 267	java/lang/reflect/InvocationTargetException:getCause	()Ljava/lang/Throwable;
    //   1861: athrow
    //   1862: astore 4
    //   1864: aload 4
    //   1866: invokevirtual 267	java/lang/reflect/InvocationTargetException:getCause	()Ljava/lang/Throwable;
    //   1869: athrow
    //   1870: astore 4
    //   1872: aload 4
    //   1874: invokevirtual 267	java/lang/reflect/InvocationTargetException:getCause	()Ljava/lang/Throwable;
    //   1877: athrow
    //   1878: astore 4
    //   1880: aload 4
    //   1882: invokevirtual 267	java/lang/reflect/InvocationTargetException:getCause	()Ljava/lang/Throwable;
    //   1885: athrow
    //   1886: astore 4
    //   1888: aload 4
    //   1890: invokevirtual 267	java/lang/reflect/InvocationTargetException:getCause	()Ljava/lang/Throwable;
    //   1893: athrow
    //   1894: astore 4
    //   1896: aload 4
    //   1898: invokevirtual 267	java/lang/reflect/InvocationTargetException:getCause	()Ljava/lang/Throwable;
    //   1901: athrow
    //   1902: astore 4
    //   1904: aload 4
    //   1906: invokevirtual 267	java/lang/reflect/InvocationTargetException:getCause	()Ljava/lang/Throwable;
    //   1909: athrow
    // Local variable table:
    //   start	length	slot	name	signature
    //   0	1910	0	this	vvvvrv
    //   4	1185	1	i	int
    //   51	1043	2	j	int
    //   710	115	3	k	int
    //   9	1172	4	localObject1	Object
    //   1198	3	4	localInvocationTargetException1	java.lang.reflect.InvocationTargetException
    //   1634	3	4	localInvocationTargetException2	java.lang.reflect.InvocationTargetException
    //   1642	3	4	localInvocationTargetException3	java.lang.reflect.InvocationTargetException
    //   1792	3	4	localInvocationTargetException4	java.lang.reflect.InvocationTargetException
    //   1800	3	4	localInvocationTargetException5	java.lang.reflect.InvocationTargetException
    //   1808	3	4	localInvocationTargetException6	java.lang.reflect.InvocationTargetException
    //   1816	3	4	localInvocationTargetException7	java.lang.reflect.InvocationTargetException
    //   1824	3	4	localInvocationTargetException8	java.lang.reflect.InvocationTargetException
    //   1832	3	4	localInvocationTargetException9	java.lang.reflect.InvocationTargetException
    //   1849	1	4	localIterator	java.util.Iterator
    //   1854	3	4	localInvocationTargetException10	java.lang.reflect.InvocationTargetException
    //   1862	3	4	localInvocationTargetException11	java.lang.reflect.InvocationTargetException
    //   1870	3	4	localInvocationTargetException12	java.lang.reflect.InvocationTargetException
    //   1878	3	4	localInvocationTargetException13	java.lang.reflect.InvocationTargetException
    //   1886	3	4	localInvocationTargetException14	java.lang.reflect.InvocationTargetException
    //   1894	3	4	localInvocationTargetException15	java.lang.reflect.InvocationTargetException
    //   1902	3	4	localInvocationTargetException16	java.lang.reflect.InvocationTargetException
    //   28	1588	5	localObject2	Object
    //   1650	1	5	localRuntimeException	RuntimeException
    //   1671	96	5	str	String
    //   106	1673	6	localObject3	Object
    //   373	1396	7	localObject4	Object
    //   375	1396	8	localObject5	Object
    //   586	725	9	localObject6	Object
    //   661	158	10	localObject7	Object
    //   745	88	11	localObject8	Object
    // Exception table:
    //   from	to	target	type
    //   1178	1197	1198	java/lang/reflect/InvocationTargetException
    //   321	362	1634	java/lang/reflect/InvocationTargetException
    //   1478	1521	1642	java/lang/reflect/InvocationTargetException
    //   380	387	1650	java/lang/RuntimeException
    //   30	43	1792	java/lang/reflect/InvocationTargetException
    //   1580	1613	1800	java/lang/reflect/InvocationTargetException
    //   202	235	1808	java/lang/reflect/InvocationTargetException
    //   108	149	1816	java/lang/reflect/InvocationTargetException
    //   1368	1410	1824	java/lang/reflect/InvocationTargetException
    //   588	619	1832	java/lang/reflect/InvocationTargetException
    //   747	779	1854	java/lang/reflect/InvocationTargetException
    //   1042	1076	1862	java/lang/reflect/InvocationTargetException
    //   505	544	1870	java/lang/reflect/InvocationTargetException
    //   943	976	1878	java/lang/reflect/InvocationTargetException
    //   1274	1308	1886	java/lang/reflect/InvocationTargetException
    //   663	696	1894	java/lang/reflect/InvocationTargetException
    //   1725	1766	1902	java/lang/reflect/InvocationTargetException
  }
}
