package uuuuuu;

import android.net.Uri;
import android.provider.BaseColumns;

public abstract interface vvxvvx
  extends BaseColumns
{
  public static final String b007600760076v007600760076v0076 = "\037\023 \031";
  public static final int b00760076v0076007600760076v0076;
  public static final String b00760076vv007600760076v0076 = "[[ig";
  public static final int b0076v00760076007600760076v0076 = 2;
  public static final String b0076v0076v007600760076v0076 = "s~\016";
  public static final Uri b0076vv0076007600760076v0076;
  public static final String bv00760076v007600760076v0076 = "}w";
  public static final int bv0076v0076007600760076v0076 = 62;
  public static final String bv0076vv007600760076v0076 = ",,.";
  public static final int bvv00760076007600760076v0076 = 1;
  public static final String bvv0076v007600760076v0076 = "[aZ";
  public static final String bvvv0076007600760076v0076 = "@90z/=4CA<8\0039LJLIM\nAGQ\017WPG\022IH\025MOS^";
  
  /* Error */
  static
  {
    // Byte code:
    //   0: getstatic 44	uuuuuu/vvxvvx:bv0076vv007600760076v0076	Ljava/lang/String;
    //   3: astore_0
    //   4: ldc 46
    //   6: ldc 48
    //   8: sipush 224
    //   11: iconst_0
    //   12: invokestatic 54	xxxxxx/uxxxxx:bb00620062bb0062b0062b0062	(Ljava/lang/String;CC)Ljava/lang/String;
    //   15: iconst_4
    //   16: anewarray 56	java/lang/Class
    //   19: dup
    //   20: iconst_0
    //   21: ldc 58
    //   23: aastore
    //   24: dup
    //   25: iconst_1
    //   26: getstatic 64	java/lang/Character:TYPE	Ljava/lang/Class;
    //   29: aastore
    //   30: dup
    //   31: iconst_2
    //   32: getstatic 64	java/lang/Character:TYPE	Ljava/lang/Class;
    //   35: aastore
    //   36: dup
    //   37: iconst_3
    //   38: getstatic 64	java/lang/Character:TYPE	Ljava/lang/Class;
    //   41: aastore
    //   42: invokevirtual 68	java/lang/Class:getMethod	(Ljava/lang/String;[Ljava/lang/Class;)Ljava/lang/reflect/Method;
    //   45: astore_1
    //   46: aload_1
    //   47: aconst_null
    //   48: iconst_4
    //   49: anewarray 4	java/lang/Object
    //   52: dup
    //   53: iconst_0
    //   54: aload_0
    //   55: aastore
    //   56: dup
    //   57: iconst_1
    //   58: bipush 12
    //   60: invokestatic 72	java/lang/Character:valueOf	(C)Ljava/lang/Character;
    //   63: aastore
    //   64: dup
    //   65: iconst_2
    //   66: sipush 209
    //   69: invokestatic 72	java/lang/Character:valueOf	(C)Ljava/lang/Character;
    //   72: aastore
    //   73: dup
    //   74: iconst_3
    //   75: iconst_1
    //   76: invokestatic 72	java/lang/Character:valueOf	(C)Ljava/lang/Character;
    //   79: aastore
    //   80: invokevirtual 78	java/lang/reflect/Method:invoke	(Ljava/lang/Object;[Ljava/lang/Object;)Ljava/lang/Object;
    //   83: astore_0
    //   84: aload_0
    //   85: checkcast 58	java/lang/String
    //   88: putstatic 44	uuuuuu/vvxvvx:bv0076vv007600760076v0076	Ljava/lang/String;
    //   91: getstatic 80	uuuuuu/vvxvvx:b00760076vv007600760076v0076	Ljava/lang/String;
    //   94: astore_0
    //   95: ldc 46
    //   97: ldc 82
    //   99: sipush 174
    //   102: bipush 80
    //   104: iconst_0
    //   105: invokestatic 86	xxxxxx/uxxxxx:bbbb0062b0062b0062b0062	(Ljava/lang/String;CCC)Ljava/lang/String;
    //   108: iconst_4
    //   109: anewarray 56	java/lang/Class
    //   112: dup
    //   113: iconst_0
    //   114: ldc 58
    //   116: aastore
    //   117: dup
    //   118: iconst_1
    //   119: getstatic 64	java/lang/Character:TYPE	Ljava/lang/Class;
    //   122: aastore
    //   123: dup
    //   124: iconst_2
    //   125: getstatic 64	java/lang/Character:TYPE	Ljava/lang/Class;
    //   128: aastore
    //   129: dup
    //   130: iconst_3
    //   131: getstatic 64	java/lang/Character:TYPE	Ljava/lang/Class;
    //   134: aastore
    //   135: invokevirtual 68	java/lang/Class:getMethod	(Ljava/lang/String;[Ljava/lang/Class;)Ljava/lang/reflect/Method;
    //   138: astore_1
    //   139: aload_1
    //   140: aconst_null
    //   141: iconst_4
    //   142: anewarray 4	java/lang/Object
    //   145: dup
    //   146: iconst_0
    //   147: aload_0
    //   148: aastore
    //   149: dup
    //   150: iconst_1
    //   151: bipush 113
    //   153: invokestatic 72	java/lang/Character:valueOf	(C)Ljava/lang/Character;
    //   156: aastore
    //   157: dup
    //   158: iconst_2
    //   159: bipush 7
    //   161: invokestatic 72	java/lang/Character:valueOf	(C)Ljava/lang/Character;
    //   164: aastore
    //   165: dup
    //   166: iconst_3
    //   167: iconst_3
    //   168: invokestatic 72	java/lang/Character:valueOf	(C)Ljava/lang/Character;
    //   171: aastore
    //   172: invokevirtual 78	java/lang/reflect/Method:invoke	(Ljava/lang/Object;[Ljava/lang/Object;)Ljava/lang/Object;
    //   175: astore_0
    //   176: aload_0
    //   177: checkcast 58	java/lang/String
    //   180: putstatic 80	uuuuuu/vvxvvx:b00760076vv007600760076v0076	Ljava/lang/String;
    //   183: getstatic 88	uuuuuu/vvxvvx:bvv0076v007600760076v0076	Ljava/lang/String;
    //   186: astore_0
    //   187: ldc 46
    //   189: ldc 90
    //   191: bipush 91
    //   193: iconst_1
    //   194: invokestatic 54	xxxxxx/uxxxxx:bb00620062bb0062b0062b0062	(Ljava/lang/String;CC)Ljava/lang/String;
    //   197: iconst_3
    //   198: anewarray 56	java/lang/Class
    //   201: dup
    //   202: iconst_0
    //   203: ldc 58
    //   205: aastore
    //   206: dup
    //   207: iconst_1
    //   208: getstatic 64	java/lang/Character:TYPE	Ljava/lang/Class;
    //   211: aastore
    //   212: dup
    //   213: iconst_2
    //   214: getstatic 64	java/lang/Character:TYPE	Ljava/lang/Class;
    //   217: aastore
    //   218: invokevirtual 68	java/lang/Class:getMethod	(Ljava/lang/String;[Ljava/lang/Class;)Ljava/lang/reflect/Method;
    //   221: astore_1
    //   222: aload_1
    //   223: aconst_null
    //   224: iconst_3
    //   225: anewarray 4	java/lang/Object
    //   228: dup
    //   229: iconst_0
    //   230: aload_0
    //   231: aastore
    //   232: dup
    //   233: iconst_1
    //   234: sipush 214
    //   237: invokestatic 72	java/lang/Character:valueOf	(C)Ljava/lang/Character;
    //   240: aastore
    //   241: dup
    //   242: iconst_2
    //   243: iconst_5
    //   244: invokestatic 72	java/lang/Character:valueOf	(C)Ljava/lang/Character;
    //   247: aastore
    //   248: invokevirtual 78	java/lang/reflect/Method:invoke	(Ljava/lang/Object;[Ljava/lang/Object;)Ljava/lang/Object;
    //   251: astore_0
    //   252: aload_0
    //   253: checkcast 58	java/lang/String
    //   256: putstatic 88	uuuuuu/vvxvvx:bvv0076v007600760076v0076	Ljava/lang/String;
    //   259: getstatic 92	uuuuuu/vvxvvx:b0076v0076v007600760076v0076	Ljava/lang/String;
    //   262: astore_0
    //   263: ldc 46
    //   265: ldc 94
    //   267: bipush 102
    //   269: iconst_3
    //   270: invokestatic 54	xxxxxx/uxxxxx:bb00620062bb0062b0062b0062	(Ljava/lang/String;CC)Ljava/lang/String;
    //   273: iconst_4
    //   274: anewarray 56	java/lang/Class
    //   277: dup
    //   278: iconst_0
    //   279: ldc 58
    //   281: aastore
    //   282: dup
    //   283: iconst_1
    //   284: getstatic 64	java/lang/Character:TYPE	Ljava/lang/Class;
    //   287: aastore
    //   288: dup
    //   289: iconst_2
    //   290: getstatic 64	java/lang/Character:TYPE	Ljava/lang/Class;
    //   293: aastore
    //   294: dup
    //   295: iconst_3
    //   296: getstatic 64	java/lang/Character:TYPE	Ljava/lang/Class;
    //   299: aastore
    //   300: invokevirtual 68	java/lang/Class:getMethod	(Ljava/lang/String;[Ljava/lang/Class;)Ljava/lang/reflect/Method;
    //   303: astore_1
    //   304: aload_1
    //   305: aconst_null
    //   306: iconst_4
    //   307: anewarray 4	java/lang/Object
    //   310: dup
    //   311: iconst_0
    //   312: aload_0
    //   313: aastore
    //   314: dup
    //   315: iconst_1
    //   316: bipush 13
    //   318: invokestatic 72	java/lang/Character:valueOf	(C)Ljava/lang/Character;
    //   321: aastore
    //   322: dup
    //   323: iconst_2
    //   324: sipush 131
    //   327: invokestatic 72	java/lang/Character:valueOf	(C)Ljava/lang/Character;
    //   330: aastore
    //   331: dup
    //   332: iconst_3
    //   333: iconst_3
    //   334: invokestatic 72	java/lang/Character:valueOf	(C)Ljava/lang/Character;
    //   337: aastore
    //   338: invokevirtual 78	java/lang/reflect/Method:invoke	(Ljava/lang/Object;[Ljava/lang/Object;)Ljava/lang/Object;
    //   341: astore_0
    //   342: aload_0
    //   343: checkcast 58	java/lang/String
    //   346: putstatic 92	uuuuuu/vvxvvx:b0076v0076v007600760076v0076	Ljava/lang/String;
    //   349: getstatic 96	uuuuuu/vvxvvx:bv00760076v007600760076v0076	Ljava/lang/String;
    //   352: astore_0
    //   353: getstatic 98	uuuuuu/vvxvvx:bv0076v0076007600760076v0076	I
    //   356: getstatic 100	uuuuuu/vvxvvx:bvv00760076007600760076v0076	I
    //   359: iadd
    //   360: getstatic 98	uuuuuu/vvxvvx:bv0076v0076007600760076v0076	I
    //   363: imul
    //   364: getstatic 102	uuuuuu/vvxvvx:b0076v00760076007600760076v0076	I
    //   367: irem
    //   368: getstatic 104	uuuuuu/vvxvvx:b00760076v0076007600760076v0076	I
    //   371: if_icmpeq +8 -> 379
    //   374: bipush 50
    //   376: putstatic 104	uuuuuu/vvxvvx:b00760076v0076007600760076v0076	I
    //   379: getstatic 98	uuuuuu/vvxvvx:bv0076v0076007600760076v0076	I
    //   382: getstatic 100	uuuuuu/vvxvvx:bvv00760076007600760076v0076	I
    //   385: iadd
    //   386: getstatic 98	uuuuuu/vvxvvx:bv0076v0076007600760076v0076	I
    //   389: imul
    //   390: getstatic 102	uuuuuu/vvxvvx:b0076v00760076007600760076v0076	I
    //   393: irem
    //   394: getstatic 104	uuuuuu/vvxvvx:b00760076v0076007600760076v0076	I
    //   397: if_icmpeq +8 -> 405
    //   400: bipush 75
    //   402: putstatic 104	uuuuuu/vvxvvx:b00760076v0076007600760076v0076	I
    //   405: ldc 46
    //   407: ldc 106
    //   409: bipush 37
    //   411: iconst_2
    //   412: invokestatic 54	xxxxxx/uxxxxx:bb00620062bb0062b0062b0062	(Ljava/lang/String;CC)Ljava/lang/String;
    //   415: iconst_3
    //   416: anewarray 56	java/lang/Class
    //   419: dup
    //   420: iconst_0
    //   421: ldc 58
    //   423: aastore
    //   424: dup
    //   425: iconst_1
    //   426: getstatic 64	java/lang/Character:TYPE	Ljava/lang/Class;
    //   429: aastore
    //   430: dup
    //   431: iconst_2
    //   432: getstatic 64	java/lang/Character:TYPE	Ljava/lang/Class;
    //   435: aastore
    //   436: invokevirtual 68	java/lang/Class:getMethod	(Ljava/lang/String;[Ljava/lang/Class;)Ljava/lang/reflect/Method;
    //   439: astore_1
    //   440: aload_1
    //   441: aconst_null
    //   442: iconst_3
    //   443: anewarray 4	java/lang/Object
    //   446: dup
    //   447: iconst_0
    //   448: aload_0
    //   449: aastore
    //   450: dup
    //   451: iconst_1
    //   452: bipush 107
    //   454: invokestatic 72	java/lang/Character:valueOf	(C)Ljava/lang/Character;
    //   457: aastore
    //   458: dup
    //   459: iconst_2
    //   460: iconst_3
    //   461: invokestatic 72	java/lang/Character:valueOf	(C)Ljava/lang/Character;
    //   464: aastore
    //   465: invokevirtual 78	java/lang/reflect/Method:invoke	(Ljava/lang/Object;[Ljava/lang/Object;)Ljava/lang/Object;
    //   468: astore_0
    //   469: aload_0
    //   470: checkcast 58	java/lang/String
    //   473: putstatic 96	uuuuuu/vvxvvx:bv00760076v007600760076v0076	Ljava/lang/String;
    //   476: getstatic 108	uuuuuu/vvxvvx:b007600760076v007600760076v0076	Ljava/lang/String;
    //   479: astore_0
    //   480: ldc 46
    //   482: ldc 110
    //   484: sipush 133
    //   487: iconst_4
    //   488: invokestatic 54	xxxxxx/uxxxxx:bb00620062bb0062b0062b0062	(Ljava/lang/String;CC)Ljava/lang/String;
    //   491: iconst_3
    //   492: anewarray 56	java/lang/Class
    //   495: dup
    //   496: iconst_0
    //   497: ldc 58
    //   499: aastore
    //   500: dup
    //   501: iconst_1
    //   502: getstatic 64	java/lang/Character:TYPE	Ljava/lang/Class;
    //   505: aastore
    //   506: dup
    //   507: iconst_2
    //   508: getstatic 64	java/lang/Character:TYPE	Ljava/lang/Class;
    //   511: aastore
    //   512: invokevirtual 68	java/lang/Class:getMethod	(Ljava/lang/String;[Ljava/lang/Class;)Ljava/lang/reflect/Method;
    //   515: astore_1
    //   516: aload_1
    //   517: aconst_null
    //   518: iconst_3
    //   519: anewarray 4	java/lang/Object
    //   522: dup
    //   523: iconst_0
    //   524: aload_0
    //   525: aastore
    //   526: dup
    //   527: iconst_1
    //   528: bipush 48
    //   530: invokestatic 72	java/lang/Character:valueOf	(C)Ljava/lang/Character;
    //   533: aastore
    //   534: dup
    //   535: iconst_2
    //   536: iconst_2
    //   537: invokestatic 72	java/lang/Character:valueOf	(C)Ljava/lang/Character;
    //   540: aastore
    //   541: invokevirtual 78	java/lang/reflect/Method:invoke	(Ljava/lang/Object;[Ljava/lang/Object;)Ljava/lang/Object;
    //   544: astore_0
    //   545: aload_0
    //   546: checkcast 58	java/lang/String
    //   549: putstatic 108	uuuuuu/vvxvvx:b007600760076v007600760076v0076	Ljava/lang/String;
    //   552: getstatic 112	uuuuuu/vvxvvx:bvvv0076007600760076v0076	Ljava/lang/String;
    //   555: astore_0
    //   556: ldc 46
    //   558: ldc 114
    //   560: sipush 189
    //   563: iconst_4
    //   564: invokestatic 54	xxxxxx/uxxxxx:bb00620062bb0062b0062b0062	(Ljava/lang/String;CC)Ljava/lang/String;
    //   567: iconst_4
    //   568: anewarray 56	java/lang/Class
    //   571: dup
    //   572: iconst_0
    //   573: ldc 58
    //   575: aastore
    //   576: dup
    //   577: iconst_1
    //   578: getstatic 64	java/lang/Character:TYPE	Ljava/lang/Class;
    //   581: aastore
    //   582: dup
    //   583: iconst_2
    //   584: getstatic 64	java/lang/Character:TYPE	Ljava/lang/Class;
    //   587: aastore
    //   588: dup
    //   589: iconst_3
    //   590: getstatic 64	java/lang/Character:TYPE	Ljava/lang/Class;
    //   593: aastore
    //   594: invokevirtual 68	java/lang/Class:getMethod	(Ljava/lang/String;[Ljava/lang/Class;)Ljava/lang/reflect/Method;
    //   597: astore_1
    //   598: aload_1
    //   599: aconst_null
    //   600: iconst_4
    //   601: anewarray 4	java/lang/Object
    //   604: dup
    //   605: iconst_0
    //   606: aload_0
    //   607: aastore
    //   608: dup
    //   609: iconst_1
    //   610: sipush 155
    //   613: invokestatic 72	java/lang/Character:valueOf	(C)Ljava/lang/Character;
    //   616: aastore
    //   617: dup
    //   618: iconst_2
    //   619: bipush 82
    //   621: invokestatic 72	java/lang/Character:valueOf	(C)Ljava/lang/Character;
    //   624: aastore
    //   625: dup
    //   626: iconst_3
    //   627: iconst_2
    //   628: invokestatic 72	java/lang/Character:valueOf	(C)Ljava/lang/Character;
    //   631: aastore
    //   632: invokevirtual 78	java/lang/reflect/Method:invoke	(Ljava/lang/Object;[Ljava/lang/Object;)Ljava/lang/Object;
    //   635: astore_0
    //   636: aload_0
    //   637: checkcast 58	java/lang/String
    //   640: putstatic 112	uuuuuu/vvxvvx:bvvv0076007600760076v0076	Ljava/lang/String;
    //   643: new 116	java/lang/StringBuilder
    //   646: dup
    //   647: invokespecial 119	java/lang/StringBuilder:<init>	()V
    //   650: astore_0
    //   651: ldc 46
    //   653: ldc 121
    //   655: sipush 229
    //   658: iconst_5
    //   659: invokestatic 54	xxxxxx/uxxxxx:bb00620062bb0062b0062b0062	(Ljava/lang/String;CC)Ljava/lang/String;
    //   662: iconst_3
    //   663: anewarray 56	java/lang/Class
    //   666: dup
    //   667: iconst_0
    //   668: ldc 58
    //   670: aastore
    //   671: dup
    //   672: iconst_1
    //   673: getstatic 64	java/lang/Character:TYPE	Ljava/lang/Class;
    //   676: aastore
    //   677: dup
    //   678: iconst_2
    //   679: getstatic 64	java/lang/Character:TYPE	Ljava/lang/Class;
    //   682: aastore
    //   683: invokevirtual 68	java/lang/Class:getMethod	(Ljava/lang/String;[Ljava/lang/Class;)Ljava/lang/reflect/Method;
    //   686: astore_1
    //   687: aload_1
    //   688: aconst_null
    //   689: iconst_3
    //   690: anewarray 4	java/lang/Object
    //   693: dup
    //   694: iconst_0
    //   695: ldc 123
    //   697: aastore
    //   698: dup
    //   699: iconst_1
    //   700: bipush 16
    //   702: invokestatic 72	java/lang/Character:valueOf	(C)Ljava/lang/Character;
    //   705: aastore
    //   706: dup
    //   707: iconst_2
    //   708: iconst_5
    //   709: invokestatic 72	java/lang/Character:valueOf	(C)Ljava/lang/Character;
    //   712: aastore
    //   713: invokevirtual 78	java/lang/reflect/Method:invoke	(Ljava/lang/Object;[Ljava/lang/Object;)Ljava/lang/Object;
    //   716: astore_1
    //   717: aload_0
    //   718: aload_1
    //   719: checkcast 58	java/lang/String
    //   722: invokestatic 129	uuuuuu/stttts:b006Bk006B006B006Bk006Bk006Bk	(Ljava/lang/String;)Ljava/lang/String;
    //   725: invokevirtual 133	java/lang/StringBuilder:append	(Ljava/lang/String;)Ljava/lang/StringBuilder;
    //   728: astore_0
    //   729: ldc 46
    //   731: ldc -121
    //   733: sipush 140
    //   736: iconst_0
    //   737: invokestatic 54	xxxxxx/uxxxxx:bb00620062bb0062b0062b0062	(Ljava/lang/String;CC)Ljava/lang/String;
    //   740: iconst_3
    //   741: anewarray 56	java/lang/Class
    //   744: dup
    //   745: iconst_0
    //   746: ldc 58
    //   748: aastore
    //   749: dup
    //   750: iconst_1
    //   751: getstatic 64	java/lang/Character:TYPE	Ljava/lang/Class;
    //   754: aastore
    //   755: dup
    //   756: iconst_2
    //   757: getstatic 64	java/lang/Character:TYPE	Ljava/lang/Class;
    //   760: aastore
    //   761: invokevirtual 68	java/lang/Class:getMethod	(Ljava/lang/String;[Ljava/lang/Class;)Ljava/lang/reflect/Method;
    //   764: astore_1
    //   765: aload_1
    //   766: aconst_null
    //   767: iconst_3
    //   768: anewarray 4	java/lang/Object
    //   771: dup
    //   772: iconst_0
    //   773: ldc -119
    //   775: aastore
    //   776: dup
    //   777: iconst_1
    //   778: bipush 91
    //   780: invokestatic 72	java/lang/Character:valueOf	(C)Ljava/lang/Character;
    //   783: aastore
    //   784: dup
    //   785: iconst_2
    //   786: iconst_3
    //   787: invokestatic 72	java/lang/Character:valueOf	(C)Ljava/lang/Character;
    //   790: aastore
    //   791: invokevirtual 78	java/lang/reflect/Method:invoke	(Ljava/lang/Object;[Ljava/lang/Object;)Ljava/lang/Object;
    //   794: astore_1
    //   795: aload_0
    //   796: aload_1
    //   797: checkcast 58	java/lang/String
    //   800: invokevirtual 133	java/lang/StringBuilder:append	(Ljava/lang/String;)Ljava/lang/StringBuilder;
    //   803: astore_0
    //   804: ldc 46
    //   806: ldc -117
    //   808: bipush 50
    //   810: sipush 190
    //   813: iconst_3
    //   814: invokestatic 86	xxxxxx/uxxxxx:bbbb0062b0062b0062b0062	(Ljava/lang/String;CCC)Ljava/lang/String;
    //   817: iconst_4
    //   818: anewarray 56	java/lang/Class
    //   821: dup
    //   822: iconst_0
    //   823: ldc 58
    //   825: aastore
    //   826: dup
    //   827: iconst_1
    //   828: getstatic 64	java/lang/Character:TYPE	Ljava/lang/Class;
    //   831: aastore
    //   832: dup
    //   833: iconst_2
    //   834: getstatic 64	java/lang/Character:TYPE	Ljava/lang/Class;
    //   837: aastore
    //   838: dup
    //   839: iconst_3
    //   840: getstatic 64	java/lang/Character:TYPE	Ljava/lang/Class;
    //   843: aastore
    //   844: invokevirtual 68	java/lang/Class:getMethod	(Ljava/lang/String;[Ljava/lang/Class;)Ljava/lang/reflect/Method;
    //   847: astore_1
    //   848: aload_1
    //   849: aconst_null
    //   850: iconst_4
    //   851: anewarray 4	java/lang/Object
    //   854: dup
    //   855: iconst_0
    //   856: ldc -115
    //   858: aastore
    //   859: dup
    //   860: iconst_1
    //   861: sipush 131
    //   864: invokestatic 72	java/lang/Character:valueOf	(C)Ljava/lang/Character;
    //   867: aastore
    //   868: dup
    //   869: iconst_2
    //   870: bipush 98
    //   872: invokestatic 72	java/lang/Character:valueOf	(C)Ljava/lang/Character;
    //   875: aastore
    //   876: dup
    //   877: iconst_3
    //   878: iconst_2
    //   879: invokestatic 72	java/lang/Character:valueOf	(C)Ljava/lang/Character;
    //   882: aastore
    //   883: invokevirtual 78	java/lang/reflect/Method:invoke	(Ljava/lang/Object;[Ljava/lang/Object;)Ljava/lang/Object;
    //   886: astore_1
    //   887: aload_0
    //   888: aload_1
    //   889: checkcast 58	java/lang/String
    //   892: invokevirtual 133	java/lang/StringBuilder:append	(Ljava/lang/String;)Ljava/lang/StringBuilder;
    //   895: invokevirtual 145	java/lang/StringBuilder:toString	()Ljava/lang/String;
    //   898: invokestatic 151	android/net/Uri:parse	(Ljava/lang/String;)Landroid/net/Uri;
    //   901: putstatic 153	uuuuuu/vvxvvx:b0076vv0076007600760076v0076	Landroid/net/Uri;
    //   904: return
    //   905: astore_0
    //   906: aload_0
    //   907: invokevirtual 157	java/lang/reflect/InvocationTargetException:getCause	()Ljava/lang/Throwable;
    //   910: athrow
    //   911: astore_0
    //   912: aload_0
    //   913: invokevirtual 157	java/lang/reflect/InvocationTargetException:getCause	()Ljava/lang/Throwable;
    //   916: athrow
    //   917: astore_0
    //   918: aload_0
    //   919: invokevirtual 157	java/lang/reflect/InvocationTargetException:getCause	()Ljava/lang/Throwable;
    //   922: athrow
    //   923: astore_0
    //   924: aload_0
    //   925: invokevirtual 157	java/lang/reflect/InvocationTargetException:getCause	()Ljava/lang/Throwable;
    //   928: athrow
    //   929: astore_0
    //   930: aload_0
    //   931: invokevirtual 157	java/lang/reflect/InvocationTargetException:getCause	()Ljava/lang/Throwable;
    //   934: athrow
    //   935: astore_0
    //   936: aload_0
    //   937: invokevirtual 157	java/lang/reflect/InvocationTargetException:getCause	()Ljava/lang/Throwable;
    //   940: athrow
    //   941: astore_0
    //   942: aload_0
    //   943: invokevirtual 157	java/lang/reflect/InvocationTargetException:getCause	()Ljava/lang/Throwable;
    //   946: athrow
    //   947: astore_0
    //   948: aload_0
    //   949: invokevirtual 157	java/lang/reflect/InvocationTargetException:getCause	()Ljava/lang/Throwable;
    //   952: athrow
    //   953: astore_0
    //   954: aload_0
    //   955: invokevirtual 157	java/lang/reflect/InvocationTargetException:getCause	()Ljava/lang/Throwable;
    //   958: athrow
    //   959: astore_0
    //   960: aload_0
    //   961: invokevirtual 157	java/lang/reflect/InvocationTargetException:getCause	()Ljava/lang/Throwable;
    //   964: athrow
    // Local variable table:
    //   start	length	slot	name	signature
    //   3	885	0	localObject1	Object
    //   905	2	0	localInvocationTargetException1	java.lang.reflect.InvocationTargetException
    //   911	2	0	localInvocationTargetException2	java.lang.reflect.InvocationTargetException
    //   917	2	0	localInvocationTargetException3	java.lang.reflect.InvocationTargetException
    //   923	2	0	localInvocationTargetException4	java.lang.reflect.InvocationTargetException
    //   929	2	0	localInvocationTargetException5	java.lang.reflect.InvocationTargetException
    //   935	2	0	localInvocationTargetException6	java.lang.reflect.InvocationTargetException
    //   941	2	0	localInvocationTargetException7	java.lang.reflect.InvocationTargetException
    //   947	2	0	localInvocationTargetException8	java.lang.reflect.InvocationTargetException
    //   953	2	0	localInvocationTargetException9	java.lang.reflect.InvocationTargetException
    //   959	2	0	localInvocationTargetException10	java.lang.reflect.InvocationTargetException
    //   45	844	1	localObject2	Object
    // Exception table:
    //   from	to	target	type
    //   222	252	905	java/lang/reflect/InvocationTargetException
    //   304	342	911	java/lang/reflect/InvocationTargetException
    //   516	545	917	java/lang/reflect/InvocationTargetException
    //   598	636	923	java/lang/reflect/InvocationTargetException
    //   687	717	929	java/lang/reflect/InvocationTargetException
    //   765	795	935	java/lang/reflect/InvocationTargetException
    //   46	84	941	java/lang/reflect/InvocationTargetException
    //   848	887	947	java/lang/reflect/InvocationTargetException
    //   139	176	953	java/lang/reflect/InvocationTargetException
    //   440	469	959	java/lang/reflect/InvocationTargetException
  }
}
