package uuuuuu;

import android.content.Context;
import com.db.pwcc.dbmobile.multi_bank_aggregator.R.drawable;
import com.google.gson.Gson;
import com.google.gson.internal.LinkedTreeMap;
import java.io.IOException;
import java.lang.reflect.InvocationTargetException;
import java.lang.reflect.Method;
import java.util.Map;
import xxxxxx.uxxxxx;

public class vxvxvx
{
  public static int b007600760076v0076v0076v0076 = 1;
  public static int b0076v0076v0076v0076v0076 = 82;
  private static final String b0076vvv0076v0076v0076 = "ooqfithhahrnsm[h[ih`d\\g!\\d_]";
  public static int bv00760076v0076v0076v0076 = 0;
  private static final String bv0076vv0076v0076v0076;
  public static int bvvv00760076v0076v0076 = 2;
  private Map<String, String> b00760076vv0076v0076v0076;
  private final Map<String, Integer> bvv0076v0076v0076v0076;
  
  static
  {
    Object localObject = b0076vvv0076v0076v0076;
    Method localMethod = ppphhp.class.getMethod(uxxxxx.bb00620062bb0062b0062b0062("=S\r\016\026\027XY\023\024\034\035\027\030 !b\034\035%& !)*k", 'Z', '\002'), new Class[] { String.class, Character.TYPE, Character.TYPE, Character.TYPE });
    try
    {
      localObject = localMethod.invoke(null, new Object[] { localObject, Character.valueOf('\030'), Character.valueOf('"'), Character.valueOf('\001') });
      b0076vvv0076v0076v0076 = (String)localObject;
      if ((b0076v0076v0076v0076v0076 + b007600760076v0076v0076v0076) * b0076v0076v0076v0076v0076 % bvvv00760076v0076v0076 != bv00760076v0076v0076v0076)
      {
        b0076v0076v0076v0076v0076 = buuuu0075uuu00750075();
        bv00760076v0076v0076v0076 = buuuu0075uuu00750075();
      }
      if ((b0076v0076v0076v0076v0076 + b007600760076v0076v0076v0076) * b0076v0076v0076v0076v0076 % bvvv00760076v0076v0076 != b0075uuu0075uuu00750075())
      {
        b0076v0076v0076v0076v0076 = 66;
        bv00760076v0076v0076v0076 = buuuu0075uuu00750075();
      }
      bv0076vv0076v0076v0076 = vxvxvx.class.getSimpleName();
      return;
    }
    catch (InvocationTargetException localInvocationTargetException)
    {
      throw localInvocationTargetException.getCause();
    }
  }
  
  /* Error */
  public vxvxvx(Context paramContext)
  {
    // Byte code:
    //   0: aload_0
    //   1: invokespecial 95	java/lang/Object:<init>	()V
    //   4: aload_0
    //   5: new 97	java/util/HashMap
    //   8: dup
    //   9: invokespecial 98	java/util/HashMap:<init>	()V
    //   12: putfield 100	uuuuuu/vxvxvx:bvv0076v0076v0076v0076	Ljava/util/Map;
    //   15: aload_0
    //   16: getfield 100	uuuuuu/vxvxvx:bvv0076v0076v0076v0076	Ljava/util/Map;
    //   19: astore_2
    //   20: ldc 31
    //   22: ldc 102
    //   24: bipush 51
    //   26: iconst_3
    //   27: invokestatic 39	xxxxxx/uxxxxx:bb00620062bb0062b0062b0062	(Ljava/lang/String;CC)Ljava/lang/String;
    //   30: iconst_3
    //   31: anewarray 41	java/lang/Class
    //   34: dup
    //   35: iconst_0
    //   36: ldc 43
    //   38: aastore
    //   39: dup
    //   40: iconst_1
    //   41: getstatic 49	java/lang/Character:TYPE	Ljava/lang/Class;
    //   44: aastore
    //   45: dup
    //   46: iconst_2
    //   47: getstatic 49	java/lang/Character:TYPE	Ljava/lang/Class;
    //   50: aastore
    //   51: invokevirtual 53	java/lang/Class:getMethod	(Ljava/lang/String;[Ljava/lang/Class;)Ljava/lang/reflect/Method;
    //   54: astore_3
    //   55: aload_3
    //   56: aconst_null
    //   57: iconst_3
    //   58: anewarray 4	java/lang/Object
    //   61: dup
    //   62: iconst_0
    //   63: ldc 104
    //   65: aastore
    //   66: dup
    //   67: iconst_1
    //   68: sipush 235
    //   71: invokestatic 57	java/lang/Character:valueOf	(C)Ljava/lang/Character;
    //   74: aastore
    //   75: dup
    //   76: iconst_2
    //   77: iconst_2
    //   78: invokestatic 57	java/lang/Character:valueOf	(C)Ljava/lang/Character;
    //   81: aastore
    //   82: invokevirtual 63	java/lang/reflect/Method:invoke	(Ljava/lang/Object;[Ljava/lang/Object;)Ljava/lang/Object;
    //   85: astore_3
    //   86: aload_2
    //   87: aload_3
    //   88: checkcast 43	java/lang/String
    //   91: getstatic 109	com/db/pwcc/dbmobile/multi_bank_aggregator/R$drawable:ic_american_express	I
    //   94: invokestatic 114	java/lang/Integer:valueOf	(I)Ljava/lang/Integer;
    //   97: invokeinterface 120 3 0
    //   102: pop
    //   103: aload_0
    //   104: getfield 100	uuuuuu/vxvxvx:bvv0076v0076v0076v0076	Ljava/util/Map;
    //   107: astore_2
    //   108: ldc 31
    //   110: ldc 122
    //   112: sipush 134
    //   115: iconst_4
    //   116: invokestatic 39	xxxxxx/uxxxxx:bb00620062bb0062b0062b0062	(Ljava/lang/String;CC)Ljava/lang/String;
    //   119: iconst_4
    //   120: anewarray 41	java/lang/Class
    //   123: dup
    //   124: iconst_0
    //   125: ldc 43
    //   127: aastore
    //   128: dup
    //   129: iconst_1
    //   130: getstatic 49	java/lang/Character:TYPE	Ljava/lang/Class;
    //   133: aastore
    //   134: dup
    //   135: iconst_2
    //   136: getstatic 49	java/lang/Character:TYPE	Ljava/lang/Class;
    //   139: aastore
    //   140: dup
    //   141: iconst_3
    //   142: getstatic 49	java/lang/Character:TYPE	Ljava/lang/Class;
    //   145: aastore
    //   146: invokevirtual 53	java/lang/Class:getMethod	(Ljava/lang/String;[Ljava/lang/Class;)Ljava/lang/reflect/Method;
    //   149: astore_3
    //   150: aload_3
    //   151: aconst_null
    //   152: iconst_4
    //   153: anewarray 4	java/lang/Object
    //   156: dup
    //   157: iconst_0
    //   158: ldc 124
    //   160: aastore
    //   161: dup
    //   162: iconst_1
    //   163: sipush 226
    //   166: invokestatic 57	java/lang/Character:valueOf	(C)Ljava/lang/Character;
    //   169: aastore
    //   170: dup
    //   171: iconst_2
    //   172: bipush 55
    //   174: invokestatic 57	java/lang/Character:valueOf	(C)Ljava/lang/Character;
    //   177: aastore
    //   178: dup
    //   179: iconst_3
    //   180: iconst_0
    //   181: invokestatic 57	java/lang/Character:valueOf	(C)Ljava/lang/Character;
    //   184: aastore
    //   185: invokevirtual 63	java/lang/reflect/Method:invoke	(Ljava/lang/Object;[Ljava/lang/Object;)Ljava/lang/Object;
    //   188: astore_3
    //   189: aload_2
    //   190: aload_3
    //   191: checkcast 43	java/lang/String
    //   194: getstatic 127	com/db/pwcc/dbmobile/multi_bank_aggregator/R$drawable:ic_flatex	I
    //   197: invokestatic 114	java/lang/Integer:valueOf	(I)Ljava/lang/Integer;
    //   200: invokeinterface 120 3 0
    //   205: pop
    //   206: aload_0
    //   207: getfield 100	uuuuuu/vxvxvx:bvv0076v0076v0076v0076	Ljava/util/Map;
    //   210: astore_2
    //   211: ldc 31
    //   213: ldc -127
    //   215: bipush 116
    //   217: iconst_5
    //   218: invokestatic 39	xxxxxx/uxxxxx:bb00620062bb0062b0062b0062	(Ljava/lang/String;CC)Ljava/lang/String;
    //   221: iconst_4
    //   222: anewarray 41	java/lang/Class
    //   225: dup
    //   226: iconst_0
    //   227: ldc 43
    //   229: aastore
    //   230: dup
    //   231: iconst_1
    //   232: getstatic 49	java/lang/Character:TYPE	Ljava/lang/Class;
    //   235: aastore
    //   236: dup
    //   237: iconst_2
    //   238: getstatic 49	java/lang/Character:TYPE	Ljava/lang/Class;
    //   241: aastore
    //   242: dup
    //   243: iconst_3
    //   244: getstatic 49	java/lang/Character:TYPE	Ljava/lang/Class;
    //   247: aastore
    //   248: invokevirtual 53	java/lang/Class:getMethod	(Ljava/lang/String;[Ljava/lang/Class;)Ljava/lang/reflect/Method;
    //   251: astore_3
    //   252: aload_3
    //   253: aconst_null
    //   254: iconst_4
    //   255: anewarray 4	java/lang/Object
    //   258: dup
    //   259: iconst_0
    //   260: ldc -125
    //   262: aastore
    //   263: dup
    //   264: iconst_1
    //   265: bipush 124
    //   267: invokestatic 57	java/lang/Character:valueOf	(C)Ljava/lang/Character;
    //   270: aastore
    //   271: dup
    //   272: iconst_2
    //   273: sipush 161
    //   276: invokestatic 57	java/lang/Character:valueOf	(C)Ljava/lang/Character;
    //   279: aastore
    //   280: dup
    //   281: iconst_3
    //   282: iconst_1
    //   283: invokestatic 57	java/lang/Character:valueOf	(C)Ljava/lang/Character;
    //   286: aastore
    //   287: invokevirtual 63	java/lang/reflect/Method:invoke	(Ljava/lang/Object;[Ljava/lang/Object;)Ljava/lang/Object;
    //   290: astore_3
    //   291: aload_2
    //   292: aload_3
    //   293: checkcast 43	java/lang/String
    //   296: getstatic 134	com/db/pwcc/dbmobile/multi_bank_aggregator/R$drawable:ic_bnp_paribas	I
    //   299: invokestatic 114	java/lang/Integer:valueOf	(I)Ljava/lang/Integer;
    //   302: invokeinterface 120 3 0
    //   307: pop
    //   308: aload_0
    //   309: getfield 100	uuuuuu/vxvxvx:bvv0076v0076v0076v0076	Ljava/util/Map;
    //   312: astore_2
    //   313: ldc 31
    //   315: ldc -120
    //   317: sipush 150
    //   320: sipush 241
    //   323: iconst_0
    //   324: invokestatic 140	xxxxxx/uxxxxx:bbbb0062b0062b0062b0062	(Ljava/lang/String;CCC)Ljava/lang/String;
    //   327: iconst_4
    //   328: anewarray 41	java/lang/Class
    //   331: dup
    //   332: iconst_0
    //   333: ldc 43
    //   335: aastore
    //   336: dup
    //   337: iconst_1
    //   338: getstatic 49	java/lang/Character:TYPE	Ljava/lang/Class;
    //   341: aastore
    //   342: dup
    //   343: iconst_2
    //   344: getstatic 49	java/lang/Character:TYPE	Ljava/lang/Class;
    //   347: aastore
    //   348: dup
    //   349: iconst_3
    //   350: getstatic 49	java/lang/Character:TYPE	Ljava/lang/Class;
    //   353: aastore
    //   354: invokevirtual 53	java/lang/Class:getMethod	(Ljava/lang/String;[Ljava/lang/Class;)Ljava/lang/reflect/Method;
    //   357: astore_3
    //   358: aload_3
    //   359: aconst_null
    //   360: iconst_4
    //   361: anewarray 4	java/lang/Object
    //   364: dup
    //   365: iconst_0
    //   366: ldc -114
    //   368: aastore
    //   369: dup
    //   370: iconst_1
    //   371: bipush 115
    //   373: invokestatic 57	java/lang/Character:valueOf	(C)Ljava/lang/Character;
    //   376: aastore
    //   377: dup
    //   378: iconst_2
    //   379: bipush 15
    //   381: invokestatic 57	java/lang/Character:valueOf	(C)Ljava/lang/Character;
    //   384: aastore
    //   385: dup
    //   386: iconst_3
    //   387: iconst_0
    //   388: invokestatic 57	java/lang/Character:valueOf	(C)Ljava/lang/Character;
    //   391: aastore
    //   392: invokevirtual 63	java/lang/reflect/Method:invoke	(Ljava/lang/Object;[Ljava/lang/Object;)Ljava/lang/Object;
    //   395: astore_3
    //   396: aload_2
    //   397: aload_3
    //   398: checkcast 43	java/lang/String
    //   401: getstatic 145	com/db/pwcc/dbmobile/multi_bank_aggregator/R$drawable:ic_comdirect	I
    //   404: invokestatic 114	java/lang/Integer:valueOf	(I)Ljava/lang/Integer;
    //   407: invokeinterface 120 3 0
    //   412: pop
    //   413: aload_0
    //   414: getfield 100	uuuuuu/vxvxvx:bvv0076v0076v0076v0076	Ljava/util/Map;
    //   417: astore_2
    //   418: ldc 31
    //   420: ldc -109
    //   422: bipush 58
    //   424: iconst_4
    //   425: invokestatic 39	xxxxxx/uxxxxx:bb00620062bb0062b0062b0062	(Ljava/lang/String;CC)Ljava/lang/String;
    //   428: iconst_3
    //   429: anewarray 41	java/lang/Class
    //   432: dup
    //   433: iconst_0
    //   434: ldc 43
    //   436: aastore
    //   437: dup
    //   438: iconst_1
    //   439: getstatic 49	java/lang/Character:TYPE	Ljava/lang/Class;
    //   442: aastore
    //   443: dup
    //   444: iconst_2
    //   445: getstatic 49	java/lang/Character:TYPE	Ljava/lang/Class;
    //   448: aastore
    //   449: invokevirtual 53	java/lang/Class:getMethod	(Ljava/lang/String;[Ljava/lang/Class;)Ljava/lang/reflect/Method;
    //   452: astore_3
    //   453: aload_3
    //   454: aconst_null
    //   455: iconst_3
    //   456: anewarray 4	java/lang/Object
    //   459: dup
    //   460: iconst_0
    //   461: ldc -107
    //   463: aastore
    //   464: dup
    //   465: iconst_1
    //   466: bipush 57
    //   468: invokestatic 57	java/lang/Character:valueOf	(C)Ljava/lang/Character;
    //   471: aastore
    //   472: dup
    //   473: iconst_2
    //   474: iconst_0
    //   475: invokestatic 57	java/lang/Character:valueOf	(C)Ljava/lang/Character;
    //   478: aastore
    //   479: invokevirtual 63	java/lang/reflect/Method:invoke	(Ljava/lang/Object;[Ljava/lang/Object;)Ljava/lang/Object;
    //   482: astore_3
    //   483: aload_2
    //   484: aload_3
    //   485: checkcast 43	java/lang/String
    //   488: getstatic 152	com/db/pwcc/dbmobile/multi_bank_aggregator/R$drawable:ic_commerzbank	I
    //   491: invokestatic 114	java/lang/Integer:valueOf	(I)Ljava/lang/Integer;
    //   494: invokeinterface 120 3 0
    //   499: pop
    //   500: aload_0
    //   501: getfield 100	uuuuuu/vxvxvx:bvv0076v0076v0076v0076	Ljava/util/Map;
    //   504: astore_2
    //   505: ldc 31
    //   507: ldc -102
    //   509: sipush 154
    //   512: bipush 73
    //   514: iconst_1
    //   515: invokestatic 140	xxxxxx/uxxxxx:bbbb0062b0062b0062b0062	(Ljava/lang/String;CCC)Ljava/lang/String;
    //   518: iconst_3
    //   519: anewarray 41	java/lang/Class
    //   522: dup
    //   523: iconst_0
    //   524: ldc 43
    //   526: aastore
    //   527: dup
    //   528: iconst_1
    //   529: getstatic 49	java/lang/Character:TYPE	Ljava/lang/Class;
    //   532: aastore
    //   533: dup
    //   534: iconst_2
    //   535: getstatic 49	java/lang/Character:TYPE	Ljava/lang/Class;
    //   538: aastore
    //   539: invokevirtual 53	java/lang/Class:getMethod	(Ljava/lang/String;[Ljava/lang/Class;)Ljava/lang/reflect/Method;
    //   542: astore_3
    //   543: aload_3
    //   544: aconst_null
    //   545: iconst_3
    //   546: anewarray 4	java/lang/Object
    //   549: dup
    //   550: iconst_0
    //   551: ldc -100
    //   553: aastore
    //   554: dup
    //   555: iconst_1
    //   556: sipush 202
    //   559: invokestatic 57	java/lang/Character:valueOf	(C)Ljava/lang/Character;
    //   562: aastore
    //   563: dup
    //   564: iconst_2
    //   565: iconst_2
    //   566: invokestatic 57	java/lang/Character:valueOf	(C)Ljava/lang/Character;
    //   569: aastore
    //   570: invokevirtual 63	java/lang/reflect/Method:invoke	(Ljava/lang/Object;[Ljava/lang/Object;)Ljava/lang/Object;
    //   573: astore_3
    //   574: aload_2
    //   575: aload_3
    //   576: checkcast 43	java/lang/String
    //   579: getstatic 159	com/db/pwcc/dbmobile/multi_bank_aggregator/R$drawable:ic_consors_bank	I
    //   582: invokestatic 114	java/lang/Integer:valueOf	(I)Ljava/lang/Integer;
    //   585: invokeinterface 120 3 0
    //   590: pop
    //   591: aload_0
    //   592: getfield 100	uuuuuu/vxvxvx:bvv0076v0076v0076v0076	Ljava/util/Map;
    //   595: astore_2
    //   596: ldc 31
    //   598: ldc -95
    //   600: sipush 150
    //   603: sipush 208
    //   606: iconst_1
    //   607: invokestatic 140	xxxxxx/uxxxxx:bbbb0062b0062b0062b0062	(Ljava/lang/String;CCC)Ljava/lang/String;
    //   610: iconst_4
    //   611: anewarray 41	java/lang/Class
    //   614: dup
    //   615: iconst_0
    //   616: ldc 43
    //   618: aastore
    //   619: dup
    //   620: iconst_1
    //   621: getstatic 49	java/lang/Character:TYPE	Ljava/lang/Class;
    //   624: aastore
    //   625: dup
    //   626: iconst_2
    //   627: getstatic 49	java/lang/Character:TYPE	Ljava/lang/Class;
    //   630: aastore
    //   631: dup
    //   632: iconst_3
    //   633: getstatic 49	java/lang/Character:TYPE	Ljava/lang/Class;
    //   636: aastore
    //   637: invokevirtual 53	java/lang/Class:getMethod	(Ljava/lang/String;[Ljava/lang/Class;)Ljava/lang/reflect/Method;
    //   640: astore_3
    //   641: aload_3
    //   642: aconst_null
    //   643: iconst_4
    //   644: anewarray 4	java/lang/Object
    //   647: dup
    //   648: iconst_0
    //   649: ldc -93
    //   651: aastore
    //   652: dup
    //   653: iconst_1
    //   654: bipush 123
    //   656: invokestatic 57	java/lang/Character:valueOf	(C)Ljava/lang/Character;
    //   659: aastore
    //   660: dup
    //   661: iconst_2
    //   662: bipush 102
    //   664: invokestatic 57	java/lang/Character:valueOf	(C)Ljava/lang/Character;
    //   667: aastore
    //   668: dup
    //   669: iconst_3
    //   670: iconst_2
    //   671: invokestatic 57	java/lang/Character:valueOf	(C)Ljava/lang/Character;
    //   674: aastore
    //   675: invokevirtual 63	java/lang/reflect/Method:invoke	(Ljava/lang/Object;[Ljava/lang/Object;)Ljava/lang/Object;
    //   678: astore_3
    //   679: aload_2
    //   680: aload_3
    //   681: checkcast 43	java/lang/String
    //   684: getstatic 166	com/db/pwcc/dbmobile/multi_bank_aggregator/R$drawable:ic_figo_testaccount	I
    //   687: invokestatic 114	java/lang/Integer:valueOf	(I)Ljava/lang/Integer;
    //   690: invokeinterface 120 3 0
    //   695: pop
    //   696: aload_0
    //   697: getfield 100	uuuuuu/vxvxvx:bvv0076v0076v0076v0076	Ljava/util/Map;
    //   700: astore_2
    //   701: ldc 31
    //   703: ldc -88
    //   705: iconst_4
    //   706: iconst_0
    //   707: invokestatic 39	xxxxxx/uxxxxx:bb00620062bb0062b0062b0062	(Ljava/lang/String;CC)Ljava/lang/String;
    //   710: iconst_4
    //   711: anewarray 41	java/lang/Class
    //   714: dup
    //   715: iconst_0
    //   716: ldc 43
    //   718: aastore
    //   719: dup
    //   720: iconst_1
    //   721: getstatic 49	java/lang/Character:TYPE	Ljava/lang/Class;
    //   724: aastore
    //   725: dup
    //   726: iconst_2
    //   727: getstatic 49	java/lang/Character:TYPE	Ljava/lang/Class;
    //   730: aastore
    //   731: dup
    //   732: iconst_3
    //   733: getstatic 49	java/lang/Character:TYPE	Ljava/lang/Class;
    //   736: aastore
    //   737: invokevirtual 53	java/lang/Class:getMethod	(Ljava/lang/String;[Ljava/lang/Class;)Ljava/lang/reflect/Method;
    //   740: astore_3
    //   741: aload_3
    //   742: aconst_null
    //   743: iconst_4
    //   744: anewarray 4	java/lang/Object
    //   747: dup
    //   748: iconst_0
    //   749: ldc -86
    //   751: aastore
    //   752: dup
    //   753: iconst_1
    //   754: bipush 67
    //   756: invokestatic 57	java/lang/Character:valueOf	(C)Ljava/lang/Character;
    //   759: aastore
    //   760: dup
    //   761: iconst_2
    //   762: bipush 94
    //   764: invokestatic 57	java/lang/Character:valueOf	(C)Ljava/lang/Character;
    //   767: aastore
    //   768: dup
    //   769: iconst_3
    //   770: iconst_1
    //   771: invokestatic 57	java/lang/Character:valueOf	(C)Ljava/lang/Character;
    //   774: aastore
    //   775: invokevirtual 63	java/lang/reflect/Method:invoke	(Ljava/lang/Object;[Ljava/lang/Object;)Ljava/lang/Object;
    //   778: astore_3
    //   779: aload_2
    //   780: aload_3
    //   781: checkcast 43	java/lang/String
    //   784: getstatic 173	com/db/pwcc/dbmobile/multi_bank_aggregator/R$drawable:ic_db_bank	I
    //   787: invokestatic 114	java/lang/Integer:valueOf	(I)Ljava/lang/Integer;
    //   790: invokeinterface 120 3 0
    //   795: pop
    //   796: aload_0
    //   797: getfield 100	uuuuuu/vxvxvx:bvv0076v0076v0076v0076	Ljava/util/Map;
    //   800: astore_2
    //   801: ldc 31
    //   803: ldc -81
    //   805: bipush 100
    //   807: iconst_3
    //   808: invokestatic 39	xxxxxx/uxxxxx:bb00620062bb0062b0062b0062	(Ljava/lang/String;CC)Ljava/lang/String;
    //   811: iconst_3
    //   812: anewarray 41	java/lang/Class
    //   815: dup
    //   816: iconst_0
    //   817: ldc 43
    //   819: aastore
    //   820: dup
    //   821: iconst_1
    //   822: getstatic 49	java/lang/Character:TYPE	Ljava/lang/Class;
    //   825: aastore
    //   826: dup
    //   827: iconst_2
    //   828: getstatic 49	java/lang/Character:TYPE	Ljava/lang/Class;
    //   831: aastore
    //   832: invokevirtual 53	java/lang/Class:getMethod	(Ljava/lang/String;[Ljava/lang/Class;)Ljava/lang/reflect/Method;
    //   835: astore_3
    //   836: aload_3
    //   837: aconst_null
    //   838: iconst_3
    //   839: anewarray 4	java/lang/Object
    //   842: dup
    //   843: iconst_0
    //   844: ldc -79
    //   846: aastore
    //   847: dup
    //   848: iconst_1
    //   849: bipush 91
    //   851: invokestatic 57	java/lang/Character:valueOf	(C)Ljava/lang/Character;
    //   854: aastore
    //   855: dup
    //   856: iconst_2
    //   857: iconst_0
    //   858: invokestatic 57	java/lang/Character:valueOf	(C)Ljava/lang/Character;
    //   861: aastore
    //   862: invokevirtual 63	java/lang/reflect/Method:invoke	(Ljava/lang/Object;[Ljava/lang/Object;)Ljava/lang/Object;
    //   865: astore_3
    //   866: aload_2
    //   867: aload_3
    //   868: checkcast 43	java/lang/String
    //   871: getstatic 180	com/db/pwcc/dbmobile/multi_bank_aggregator/R$drawable:ic_dkb_bank	I
    //   874: invokestatic 114	java/lang/Integer:valueOf	(I)Ljava/lang/Integer;
    //   877: invokeinterface 120 3 0
    //   882: pop
    //   883: aload_0
    //   884: getfield 100	uuuuuu/vxvxvx:bvv0076v0076v0076v0076	Ljava/util/Map;
    //   887: astore_2
    //   888: ldc 31
    //   890: ldc -74
    //   892: sipush 217
    //   895: bipush 73
    //   897: iconst_1
    //   898: invokestatic 140	xxxxxx/uxxxxx:bbbb0062b0062b0062b0062	(Ljava/lang/String;CCC)Ljava/lang/String;
    //   901: iconst_3
    //   902: anewarray 41	java/lang/Class
    //   905: dup
    //   906: iconst_0
    //   907: ldc 43
    //   909: aastore
    //   910: dup
    //   911: iconst_1
    //   912: getstatic 49	java/lang/Character:TYPE	Ljava/lang/Class;
    //   915: aastore
    //   916: dup
    //   917: iconst_2
    //   918: getstatic 49	java/lang/Character:TYPE	Ljava/lang/Class;
    //   921: aastore
    //   922: invokevirtual 53	java/lang/Class:getMethod	(Ljava/lang/String;[Ljava/lang/Class;)Ljava/lang/reflect/Method;
    //   925: astore_3
    //   926: aload_3
    //   927: aconst_null
    //   928: iconst_3
    //   929: anewarray 4	java/lang/Object
    //   932: dup
    //   933: iconst_0
    //   934: ldc -72
    //   936: aastore
    //   937: dup
    //   938: iconst_1
    //   939: sipush 216
    //   942: invokestatic 57	java/lang/Character:valueOf	(C)Ljava/lang/Character;
    //   945: aastore
    //   946: dup
    //   947: iconst_2
    //   948: iconst_2
    //   949: invokestatic 57	java/lang/Character:valueOf	(C)Ljava/lang/Character;
    //   952: aastore
    //   953: invokevirtual 63	java/lang/reflect/Method:invoke	(Ljava/lang/Object;[Ljava/lang/Object;)Ljava/lang/Object;
    //   956: astore_3
    //   957: aload_2
    //   958: aload_3
    //   959: checkcast 43	java/lang/String
    //   962: getstatic 187	com/db/pwcc/dbmobile/multi_bank_aggregator/R$drawable:ic_dws_bank	I
    //   965: invokestatic 114	java/lang/Integer:valueOf	(I)Ljava/lang/Integer;
    //   968: invokeinterface 120 3 0
    //   973: pop
    //   974: aload_0
    //   975: getfield 100	uuuuuu/vxvxvx:bvv0076v0076v0076v0076	Ljava/util/Map;
    //   978: astore_2
    //   979: ldc 31
    //   981: ldc -67
    //   983: sipush 147
    //   986: iconst_3
    //   987: invokestatic 39	xxxxxx/uxxxxx:bb00620062bb0062b0062b0062	(Ljava/lang/String;CC)Ljava/lang/String;
    //   990: iconst_3
    //   991: anewarray 41	java/lang/Class
    //   994: dup
    //   995: iconst_0
    //   996: ldc 43
    //   998: aastore
    //   999: dup
    //   1000: iconst_1
    //   1001: getstatic 49	java/lang/Character:TYPE	Ljava/lang/Class;
    //   1004: aastore
    //   1005: dup
    //   1006: iconst_2
    //   1007: getstatic 49	java/lang/Character:TYPE	Ljava/lang/Class;
    //   1010: aastore
    //   1011: invokevirtual 53	java/lang/Class:getMethod	(Ljava/lang/String;[Ljava/lang/Class;)Ljava/lang/reflect/Method;
    //   1014: astore_3
    //   1015: aload_3
    //   1016: aconst_null
    //   1017: iconst_3
    //   1018: anewarray 4	java/lang/Object
    //   1021: dup
    //   1022: iconst_0
    //   1023: ldc -65
    //   1025: aastore
    //   1026: dup
    //   1027: iconst_1
    //   1028: bipush 34
    //   1030: invokestatic 57	java/lang/Character:valueOf	(C)Ljava/lang/Character;
    //   1033: aastore
    //   1034: dup
    //   1035: iconst_2
    //   1036: iconst_0
    //   1037: invokestatic 57	java/lang/Character:valueOf	(C)Ljava/lang/Character;
    //   1040: aastore
    //   1041: invokevirtual 63	java/lang/reflect/Method:invoke	(Ljava/lang/Object;[Ljava/lang/Object;)Ljava/lang/Object;
    //   1044: astore_3
    //   1045: aload_2
    //   1046: aload_3
    //   1047: checkcast 43	java/lang/String
    //   1050: getstatic 194	com/db/pwcc/dbmobile/multi_bank_aggregator/R$drawable:ic_fidor_bank	I
    //   1053: invokestatic 114	java/lang/Integer:valueOf	(I)Ljava/lang/Integer;
    //   1056: invokeinterface 120 3 0
    //   1061: pop
    //   1062: aload_0
    //   1063: getfield 100	uuuuuu/vxvxvx:bvv0076v0076v0076v0076	Ljava/util/Map;
    //   1066: astore_2
    //   1067: ldc 31
    //   1069: ldc -60
    //   1071: sipush 165
    //   1074: iconst_3
    //   1075: invokestatic 39	xxxxxx/uxxxxx:bb00620062bb0062b0062b0062	(Ljava/lang/String;CC)Ljava/lang/String;
    //   1078: iconst_4
    //   1079: anewarray 41	java/lang/Class
    //   1082: dup
    //   1083: iconst_0
    //   1084: ldc 43
    //   1086: aastore
    //   1087: dup
    //   1088: iconst_1
    //   1089: getstatic 49	java/lang/Character:TYPE	Ljava/lang/Class;
    //   1092: aastore
    //   1093: dup
    //   1094: iconst_2
    //   1095: getstatic 49	java/lang/Character:TYPE	Ljava/lang/Class;
    //   1098: aastore
    //   1099: dup
    //   1100: iconst_3
    //   1101: getstatic 49	java/lang/Character:TYPE	Ljava/lang/Class;
    //   1104: aastore
    //   1105: invokevirtual 53	java/lang/Class:getMethod	(Ljava/lang/String;[Ljava/lang/Class;)Ljava/lang/reflect/Method;
    //   1108: astore_3
    //   1109: aload_3
    //   1110: aconst_null
    //   1111: iconst_4
    //   1112: anewarray 4	java/lang/Object
    //   1115: dup
    //   1116: iconst_0
    //   1117: ldc -58
    //   1119: aastore
    //   1120: dup
    //   1121: iconst_1
    //   1122: bipush 90
    //   1124: invokestatic 57	java/lang/Character:valueOf	(C)Ljava/lang/Character;
    //   1127: aastore
    //   1128: dup
    //   1129: iconst_2
    //   1130: sipush 129
    //   1133: invokestatic 57	java/lang/Character:valueOf	(C)Ljava/lang/Character;
    //   1136: aastore
    //   1137: dup
    //   1138: iconst_3
    //   1139: iconst_3
    //   1140: invokestatic 57	java/lang/Character:valueOf	(C)Ljava/lang/Character;
    //   1143: aastore
    //   1144: invokevirtual 63	java/lang/reflect/Method:invoke	(Ljava/lang/Object;[Ljava/lang/Object;)Ljava/lang/Object;
    //   1147: astore_3
    //   1148: aload_2
    //   1149: aload_3
    //   1150: checkcast 43	java/lang/String
    //   1153: getstatic 201	com/db/pwcc/dbmobile/multi_bank_aggregator/R$drawable:ic_haspa_bank	I
    //   1156: invokestatic 114	java/lang/Integer:valueOf	(I)Ljava/lang/Integer;
    //   1159: invokeinterface 120 3 0
    //   1164: pop
    //   1165: aload_0
    //   1166: getfield 100	uuuuuu/vxvxvx:bvv0076v0076v0076v0076	Ljava/util/Map;
    //   1169: astore_2
    //   1170: ldc 31
    //   1172: ldc -53
    //   1174: bipush 84
    //   1176: sipush 197
    //   1179: iconst_1
    //   1180: invokestatic 140	xxxxxx/uxxxxx:bbbb0062b0062b0062b0062	(Ljava/lang/String;CCC)Ljava/lang/String;
    //   1183: iconst_3
    //   1184: anewarray 41	java/lang/Class
    //   1187: dup
    //   1188: iconst_0
    //   1189: ldc 43
    //   1191: aastore
    //   1192: dup
    //   1193: iconst_1
    //   1194: getstatic 49	java/lang/Character:TYPE	Ljava/lang/Class;
    //   1197: aastore
    //   1198: dup
    //   1199: iconst_2
    //   1200: getstatic 49	java/lang/Character:TYPE	Ljava/lang/Class;
    //   1203: aastore
    //   1204: invokevirtual 53	java/lang/Class:getMethod	(Ljava/lang/String;[Ljava/lang/Class;)Ljava/lang/reflect/Method;
    //   1207: astore_3
    //   1208: aload_3
    //   1209: aconst_null
    //   1210: iconst_3
    //   1211: anewarray 4	java/lang/Object
    //   1214: dup
    //   1215: iconst_0
    //   1216: ldc -51
    //   1218: aastore
    //   1219: dup
    //   1220: iconst_1
    //   1221: bipush 88
    //   1223: invokestatic 57	java/lang/Character:valueOf	(C)Ljava/lang/Character;
    //   1226: aastore
    //   1227: dup
    //   1228: iconst_2
    //   1229: iconst_0
    //   1230: invokestatic 57	java/lang/Character:valueOf	(C)Ljava/lang/Character;
    //   1233: aastore
    //   1234: invokevirtual 63	java/lang/reflect/Method:invoke	(Ljava/lang/Object;[Ljava/lang/Object;)Ljava/lang/Object;
    //   1237: astore_3
    //   1238: aload_2
    //   1239: aload_3
    //   1240: checkcast 43	java/lang/String
    //   1243: getstatic 208	com/db/pwcc/dbmobile/multi_bank_aggregator/R$drawable:ic_ing_diba	I
    //   1246: invokestatic 114	java/lang/Integer:valueOf	(I)Ljava/lang/Integer;
    //   1249: invokeinterface 120 3 0
    //   1254: pop
    //   1255: aload_0
    //   1256: getfield 100	uuuuuu/vxvxvx:bvv0076v0076v0076v0076	Ljava/util/Map;
    //   1259: astore_2
    //   1260: ldc 31
    //   1262: ldc -46
    //   1264: bipush 74
    //   1266: iconst_0
    //   1267: invokestatic 39	xxxxxx/uxxxxx:bb00620062bb0062b0062b0062	(Ljava/lang/String;CC)Ljava/lang/String;
    //   1270: iconst_3
    //   1271: anewarray 41	java/lang/Class
    //   1274: dup
    //   1275: iconst_0
    //   1276: ldc 43
    //   1278: aastore
    //   1279: dup
    //   1280: iconst_1
    //   1281: getstatic 49	java/lang/Character:TYPE	Ljava/lang/Class;
    //   1284: aastore
    //   1285: dup
    //   1286: iconst_2
    //   1287: getstatic 49	java/lang/Character:TYPE	Ljava/lang/Class;
    //   1290: aastore
    //   1291: invokevirtual 53	java/lang/Class:getMethod	(Ljava/lang/String;[Ljava/lang/Class;)Ljava/lang/reflect/Method;
    //   1294: astore_3
    //   1295: aload_3
    //   1296: aconst_null
    //   1297: iconst_3
    //   1298: anewarray 4	java/lang/Object
    //   1301: dup
    //   1302: iconst_0
    //   1303: ldc -44
    //   1305: aastore
    //   1306: dup
    //   1307: iconst_1
    //   1308: sipush 187
    //   1311: invokestatic 57	java/lang/Character:valueOf	(C)Ljava/lang/Character;
    //   1314: aastore
    //   1315: dup
    //   1316: iconst_2
    //   1317: iconst_3
    //   1318: invokestatic 57	java/lang/Character:valueOf	(C)Ljava/lang/Character;
    //   1321: aastore
    //   1322: invokevirtual 63	java/lang/reflect/Method:invoke	(Ljava/lang/Object;[Ljava/lang/Object;)Ljava/lang/Object;
    //   1325: astore_3
    //   1326: aload_2
    //   1327: aload_3
    //   1328: checkcast 43	java/lang/String
    //   1331: getstatic 215	com/db/pwcc/dbmobile/multi_bank_aggregator/R$drawable:ic_lbb_bank	I
    //   1334: invokestatic 114	java/lang/Integer:valueOf	(I)Ljava/lang/Integer;
    //   1337: invokeinterface 120 3 0
    //   1342: pop
    //   1343: aload_0
    //   1344: getfield 100	uuuuuu/vxvxvx:bvv0076v0076v0076v0076	Ljava/util/Map;
    //   1347: astore_2
    //   1348: ldc 31
    //   1350: ldc -39
    //   1352: bipush 73
    //   1354: iconst_5
    //   1355: invokestatic 39	xxxxxx/uxxxxx:bb00620062bb0062b0062b0062	(Ljava/lang/String;CC)Ljava/lang/String;
    //   1358: iconst_4
    //   1359: anewarray 41	java/lang/Class
    //   1362: dup
    //   1363: iconst_0
    //   1364: ldc 43
    //   1366: aastore
    //   1367: dup
    //   1368: iconst_1
    //   1369: getstatic 49	java/lang/Character:TYPE	Ljava/lang/Class;
    //   1372: aastore
    //   1373: dup
    //   1374: iconst_2
    //   1375: getstatic 49	java/lang/Character:TYPE	Ljava/lang/Class;
    //   1378: aastore
    //   1379: dup
    //   1380: iconst_3
    //   1381: getstatic 49	java/lang/Character:TYPE	Ljava/lang/Class;
    //   1384: aastore
    //   1385: invokevirtual 53	java/lang/Class:getMethod	(Ljava/lang/String;[Ljava/lang/Class;)Ljava/lang/reflect/Method;
    //   1388: astore_3
    //   1389: aload_3
    //   1390: aconst_null
    //   1391: iconst_4
    //   1392: anewarray 4	java/lang/Object
    //   1395: dup
    //   1396: iconst_0
    //   1397: ldc -37
    //   1399: aastore
    //   1400: dup
    //   1401: iconst_1
    //   1402: sipush 253
    //   1405: invokestatic 57	java/lang/Character:valueOf	(C)Ljava/lang/Character;
    //   1408: aastore
    //   1409: dup
    //   1410: iconst_2
    //   1411: bipush 103
    //   1413: invokestatic 57	java/lang/Character:valueOf	(C)Ljava/lang/Character;
    //   1416: aastore
    //   1417: dup
    //   1418: iconst_3
    //   1419: iconst_0
    //   1420: invokestatic 57	java/lang/Character:valueOf	(C)Ljava/lang/Character;
    //   1423: aastore
    //   1424: invokevirtual 63	java/lang/reflect/Method:invoke	(Ljava/lang/Object;[Ljava/lang/Object;)Ljava/lang/Object;
    //   1427: astore_3
    //   1428: aload_2
    //   1429: aload_3
    //   1430: checkcast 43	java/lang/String
    //   1433: getstatic 222	com/db/pwcc/dbmobile/multi_bank_aggregator/R$drawable:ic_miles_and_more	I
    //   1436: invokestatic 114	java/lang/Integer:valueOf	(I)Ljava/lang/Integer;
    //   1439: invokeinterface 120 3 0
    //   1444: pop
    //   1445: aload_0
    //   1446: getfield 100	uuuuuu/vxvxvx:bvv0076v0076v0076v0076	Ljava/util/Map;
    //   1449: astore_2
    //   1450: ldc 31
    //   1452: ldc -32
    //   1454: iconst_4
    //   1455: iconst_4
    //   1456: invokestatic 39	xxxxxx/uxxxxx:bb00620062bb0062b0062b0062	(Ljava/lang/String;CC)Ljava/lang/String;
    //   1459: iconst_3
    //   1460: anewarray 41	java/lang/Class
    //   1463: dup
    //   1464: iconst_0
    //   1465: ldc 43
    //   1467: aastore
    //   1468: dup
    //   1469: iconst_1
    //   1470: getstatic 49	java/lang/Character:TYPE	Ljava/lang/Class;
    //   1473: aastore
    //   1474: dup
    //   1475: iconst_2
    //   1476: getstatic 49	java/lang/Character:TYPE	Ljava/lang/Class;
    //   1479: aastore
    //   1480: invokevirtual 53	java/lang/Class:getMethod	(Ljava/lang/String;[Ljava/lang/Class;)Ljava/lang/reflect/Method;
    //   1483: astore_3
    //   1484: aload_3
    //   1485: aconst_null
    //   1486: iconst_3
    //   1487: anewarray 4	java/lang/Object
    //   1490: dup
    //   1491: iconst_0
    //   1492: ldc -30
    //   1494: aastore
    //   1495: dup
    //   1496: iconst_1
    //   1497: sipush 220
    //   1500: invokestatic 57	java/lang/Character:valueOf	(C)Ljava/lang/Character;
    //   1503: aastore
    //   1504: dup
    //   1505: iconst_2
    //   1506: iconst_1
    //   1507: invokestatic 57	java/lang/Character:valueOf	(C)Ljava/lang/Character;
    //   1510: aastore
    //   1511: invokevirtual 63	java/lang/reflect/Method:invoke	(Ljava/lang/Object;[Ljava/lang/Object;)Ljava/lang/Object;
    //   1514: astore_3
    //   1515: aload_2
    //   1516: aload_3
    //   1517: checkcast 43	java/lang/String
    //   1520: getstatic 229	com/db/pwcc/dbmobile/multi_bank_aggregator/R$drawable:ic_norisbank	I
    //   1523: invokestatic 114	java/lang/Integer:valueOf	(I)Ljava/lang/Integer;
    //   1526: invokeinterface 120 3 0
    //   1531: pop
    //   1532: aload_0
    //   1533: getfield 100	uuuuuu/vxvxvx:bvv0076v0076v0076v0076	Ljava/util/Map;
    //   1536: astore_2
    //   1537: ldc 31
    //   1539: ldc -25
    //   1541: sipush 248
    //   1544: sipush 214
    //   1547: iconst_1
    //   1548: invokestatic 140	xxxxxx/uxxxxx:bbbb0062b0062b0062b0062	(Ljava/lang/String;CCC)Ljava/lang/String;
    //   1551: iconst_4
    //   1552: anewarray 41	java/lang/Class
    //   1555: dup
    //   1556: iconst_0
    //   1557: ldc 43
    //   1559: aastore
    //   1560: dup
    //   1561: iconst_1
    //   1562: getstatic 49	java/lang/Character:TYPE	Ljava/lang/Class;
    //   1565: aastore
    //   1566: dup
    //   1567: iconst_2
    //   1568: getstatic 49	java/lang/Character:TYPE	Ljava/lang/Class;
    //   1571: aastore
    //   1572: dup
    //   1573: iconst_3
    //   1574: getstatic 49	java/lang/Character:TYPE	Ljava/lang/Class;
    //   1577: aastore
    //   1578: invokevirtual 53	java/lang/Class:getMethod	(Ljava/lang/String;[Ljava/lang/Class;)Ljava/lang/reflect/Method;
    //   1581: astore_3
    //   1582: aload_3
    //   1583: aconst_null
    //   1584: iconst_4
    //   1585: anewarray 4	java/lang/Object
    //   1588: dup
    //   1589: iconst_0
    //   1590: ldc -23
    //   1592: aastore
    //   1593: dup
    //   1594: iconst_1
    //   1595: sipush 246
    //   1598: invokestatic 57	java/lang/Character:valueOf	(C)Ljava/lang/Character;
    //   1601: aastore
    //   1602: dup
    //   1603: iconst_2
    //   1604: sipush 187
    //   1607: invokestatic 57	java/lang/Character:valueOf	(C)Ljava/lang/Character;
    //   1610: aastore
    //   1611: dup
    //   1612: iconst_3
    //   1613: iconst_1
    //   1614: invokestatic 57	java/lang/Character:valueOf	(C)Ljava/lang/Character;
    //   1617: aastore
    //   1618: invokevirtual 63	java/lang/reflect/Method:invoke	(Ljava/lang/Object;[Ljava/lang/Object;)Ljava/lang/Object;
    //   1621: astore_3
    //   1622: aload_2
    //   1623: aload_3
    //   1624: checkcast 43	java/lang/String
    //   1627: getstatic 236	com/db/pwcc/dbmobile/multi_bank_aggregator/R$drawable:ic_paypal	I
    //   1630: invokestatic 114	java/lang/Integer:valueOf	(I)Ljava/lang/Integer;
    //   1633: invokeinterface 120 3 0
    //   1638: pop
    //   1639: aload_0
    //   1640: getfield 100	uuuuuu/vxvxvx:bvv0076v0076v0076v0076	Ljava/util/Map;
    //   1643: astore_2
    //   1644: ldc 31
    //   1646: ldc -18
    //   1648: bipush 59
    //   1650: iconst_1
    //   1651: invokestatic 39	xxxxxx/uxxxxx:bb00620062bb0062b0062b0062	(Ljava/lang/String;CC)Ljava/lang/String;
    //   1654: iconst_4
    //   1655: anewarray 41	java/lang/Class
    //   1658: dup
    //   1659: iconst_0
    //   1660: ldc 43
    //   1662: aastore
    //   1663: dup
    //   1664: iconst_1
    //   1665: getstatic 49	java/lang/Character:TYPE	Ljava/lang/Class;
    //   1668: aastore
    //   1669: dup
    //   1670: iconst_2
    //   1671: getstatic 49	java/lang/Character:TYPE	Ljava/lang/Class;
    //   1674: aastore
    //   1675: dup
    //   1676: iconst_3
    //   1677: getstatic 49	java/lang/Character:TYPE	Ljava/lang/Class;
    //   1680: aastore
    //   1681: invokevirtual 53	java/lang/Class:getMethod	(Ljava/lang/String;[Ljava/lang/Class;)Ljava/lang/reflect/Method;
    //   1684: astore_3
    //   1685: aload_3
    //   1686: aconst_null
    //   1687: iconst_4
    //   1688: anewarray 4	java/lang/Object
    //   1691: dup
    //   1692: iconst_0
    //   1693: ldc -16
    //   1695: aastore
    //   1696: dup
    //   1697: iconst_1
    //   1698: sipush 239
    //   1701: invokestatic 57	java/lang/Character:valueOf	(C)Ljava/lang/Character;
    //   1704: aastore
    //   1705: dup
    //   1706: iconst_2
    //   1707: bipush 127
    //   1709: invokestatic 57	java/lang/Character:valueOf	(C)Ljava/lang/Character;
    //   1712: aastore
    //   1713: dup
    //   1714: iconst_3
    //   1715: iconst_3
    //   1716: invokestatic 57	java/lang/Character:valueOf	(C)Ljava/lang/Character;
    //   1719: aastore
    //   1720: invokevirtual 63	java/lang/reflect/Method:invoke	(Ljava/lang/Object;[Ljava/lang/Object;)Ljava/lang/Object;
    //   1723: astore_3
    //   1724: aload_2
    //   1725: aload_3
    //   1726: checkcast 43	java/lang/String
    //   1729: getstatic 243	com/db/pwcc/dbmobile/multi_bank_aggregator/R$drawable:ic_postbank	I
    //   1732: invokestatic 114	java/lang/Integer:valueOf	(I)Ljava/lang/Integer;
    //   1735: invokeinterface 120 3 0
    //   1740: pop
    //   1741: aload_0
    //   1742: getfield 100	uuuuuu/vxvxvx:bvv0076v0076v0076v0076	Ljava/util/Map;
    //   1745: astore_2
    //   1746: ldc 31
    //   1748: ldc -11
    //   1750: sipush 157
    //   1753: iconst_4
    //   1754: invokestatic 39	xxxxxx/uxxxxx:bb00620062bb0062b0062b0062	(Ljava/lang/String;CC)Ljava/lang/String;
    //   1757: iconst_4
    //   1758: anewarray 41	java/lang/Class
    //   1761: dup
    //   1762: iconst_0
    //   1763: ldc 43
    //   1765: aastore
    //   1766: dup
    //   1767: iconst_1
    //   1768: getstatic 49	java/lang/Character:TYPE	Ljava/lang/Class;
    //   1771: aastore
    //   1772: dup
    //   1773: iconst_2
    //   1774: getstatic 49	java/lang/Character:TYPE	Ljava/lang/Class;
    //   1777: aastore
    //   1778: dup
    //   1779: iconst_3
    //   1780: getstatic 49	java/lang/Character:TYPE	Ljava/lang/Class;
    //   1783: aastore
    //   1784: invokevirtual 53	java/lang/Class:getMethod	(Ljava/lang/String;[Ljava/lang/Class;)Ljava/lang/reflect/Method;
    //   1787: astore_3
    //   1788: aload_3
    //   1789: aconst_null
    //   1790: iconst_4
    //   1791: anewarray 4	java/lang/Object
    //   1794: dup
    //   1795: iconst_0
    //   1796: ldc -9
    //   1798: aastore
    //   1799: dup
    //   1800: iconst_1
    //   1801: sipush 208
    //   1804: invokestatic 57	java/lang/Character:valueOf	(C)Ljava/lang/Character;
    //   1807: aastore
    //   1808: dup
    //   1809: iconst_2
    //   1810: bipush 88
    //   1812: invokestatic 57	java/lang/Character:valueOf	(C)Ljava/lang/Character;
    //   1815: aastore
    //   1816: dup
    //   1817: iconst_3
    //   1818: iconst_0
    //   1819: invokestatic 57	java/lang/Character:valueOf	(C)Ljava/lang/Character;
    //   1822: aastore
    //   1823: invokevirtual 63	java/lang/reflect/Method:invoke	(Ljava/lang/Object;[Ljava/lang/Object;)Ljava/lang/Object;
    //   1826: astore_3
    //   1827: aload_2
    //   1828: aload_3
    //   1829: checkcast 43	java/lang/String
    //   1832: getstatic 250	com/db/pwcc/dbmobile/multi_bank_aggregator/R$drawable:ic_santander_bank	I
    //   1835: invokestatic 114	java/lang/Integer:valueOf	(I)Ljava/lang/Integer;
    //   1838: invokeinterface 120 3 0
    //   1843: pop
    //   1844: aload_0
    //   1845: getfield 100	uuuuuu/vxvxvx:bvv0076v0076v0076v0076	Ljava/util/Map;
    //   1848: astore_2
    //   1849: ldc 31
    //   1851: ldc -4
    //   1853: sipush 200
    //   1856: sipush 222
    //   1859: iconst_2
    //   1860: invokestatic 140	xxxxxx/uxxxxx:bbbb0062b0062b0062b0062	(Ljava/lang/String;CCC)Ljava/lang/String;
    //   1863: iconst_4
    //   1864: anewarray 41	java/lang/Class
    //   1867: dup
    //   1868: iconst_0
    //   1869: ldc 43
    //   1871: aastore
    //   1872: dup
    //   1873: iconst_1
    //   1874: getstatic 49	java/lang/Character:TYPE	Ljava/lang/Class;
    //   1877: aastore
    //   1878: dup
    //   1879: iconst_2
    //   1880: getstatic 49	java/lang/Character:TYPE	Ljava/lang/Class;
    //   1883: aastore
    //   1884: dup
    //   1885: iconst_3
    //   1886: getstatic 49	java/lang/Character:TYPE	Ljava/lang/Class;
    //   1889: aastore
    //   1890: invokevirtual 53	java/lang/Class:getMethod	(Ljava/lang/String;[Ljava/lang/Class;)Ljava/lang/reflect/Method;
    //   1893: astore_3
    //   1894: aload_3
    //   1895: aconst_null
    //   1896: iconst_4
    //   1897: anewarray 4	java/lang/Object
    //   1900: dup
    //   1901: iconst_0
    //   1902: ldc -2
    //   1904: aastore
    //   1905: dup
    //   1906: iconst_1
    //   1907: sipush 144
    //   1910: invokestatic 57	java/lang/Character:valueOf	(C)Ljava/lang/Character;
    //   1913: aastore
    //   1914: dup
    //   1915: iconst_2
    //   1916: sipush 148
    //   1919: invokestatic 57	java/lang/Character:valueOf	(C)Ljava/lang/Character;
    //   1922: aastore
    //   1923: dup
    //   1924: iconst_3
    //   1925: iconst_1
    //   1926: invokestatic 57	java/lang/Character:valueOf	(C)Ljava/lang/Character;
    //   1929: aastore
    //   1930: invokevirtual 63	java/lang/reflect/Method:invoke	(Ljava/lang/Object;[Ljava/lang/Object;)Ljava/lang/Object;
    //   1933: astore_3
    //   1934: aload_2
    //   1935: aload_3
    //   1936: checkcast 43	java/lang/String
    //   1939: getstatic 257	com/db/pwcc/dbmobile/multi_bank_aggregator/R$drawable:ic_sparda_bank	I
    //   1942: invokestatic 114	java/lang/Integer:valueOf	(I)Ljava/lang/Integer;
    //   1945: invokeinterface 120 3 0
    //   1950: pop
    //   1951: aload_0
    //   1952: getfield 100	uuuuuu/vxvxvx:bvv0076v0076v0076v0076	Ljava/util/Map;
    //   1955: astore_2
    //   1956: ldc 31
    //   1958: ldc_w 259
    //   1961: iconst_5
    //   1962: iconst_0
    //   1963: invokestatic 39	xxxxxx/uxxxxx:bb00620062bb0062b0062b0062	(Ljava/lang/String;CC)Ljava/lang/String;
    //   1966: iconst_4
    //   1967: anewarray 41	java/lang/Class
    //   1970: dup
    //   1971: iconst_0
    //   1972: ldc 43
    //   1974: aastore
    //   1975: dup
    //   1976: iconst_1
    //   1977: getstatic 49	java/lang/Character:TYPE	Ljava/lang/Class;
    //   1980: aastore
    //   1981: dup
    //   1982: iconst_2
    //   1983: getstatic 49	java/lang/Character:TYPE	Ljava/lang/Class;
    //   1986: aastore
    //   1987: dup
    //   1988: iconst_3
    //   1989: getstatic 49	java/lang/Character:TYPE	Ljava/lang/Class;
    //   1992: aastore
    //   1993: invokevirtual 53	java/lang/Class:getMethod	(Ljava/lang/String;[Ljava/lang/Class;)Ljava/lang/reflect/Method;
    //   1996: astore_3
    //   1997: aload_3
    //   1998: aconst_null
    //   1999: iconst_4
    //   2000: anewarray 4	java/lang/Object
    //   2003: dup
    //   2004: iconst_0
    //   2005: ldc_w 261
    //   2008: aastore
    //   2009: dup
    //   2010: iconst_1
    //   2011: iconst_5
    //   2012: invokestatic 57	java/lang/Character:valueOf	(C)Ljava/lang/Character;
    //   2015: aastore
    //   2016: dup
    //   2017: iconst_2
    //   2018: sipush 136
    //   2021: invokestatic 57	java/lang/Character:valueOf	(C)Ljava/lang/Character;
    //   2024: aastore
    //   2025: dup
    //   2026: iconst_3
    //   2027: iconst_2
    //   2028: invokestatic 57	java/lang/Character:valueOf	(C)Ljava/lang/Character;
    //   2031: aastore
    //   2032: invokevirtual 63	java/lang/reflect/Method:invoke	(Ljava/lang/Object;[Ljava/lang/Object;)Ljava/lang/Object;
    //   2035: astore_3
    //   2036: aload_2
    //   2037: aload_3
    //   2038: checkcast 43	java/lang/String
    //   2041: getstatic 264	com/db/pwcc/dbmobile/multi_bank_aggregator/R$drawable:ic_sparkasse	I
    //   2044: invokestatic 114	java/lang/Integer:valueOf	(I)Ljava/lang/Integer;
    //   2047: invokeinterface 120 3 0
    //   2052: pop
    //   2053: aload_0
    //   2054: getfield 100	uuuuuu/vxvxvx:bvv0076v0076v0076v0076	Ljava/util/Map;
    //   2057: astore_2
    //   2058: ldc 31
    //   2060: ldc_w 266
    //   2063: sipush 212
    //   2066: bipush 88
    //   2068: iconst_1
    //   2069: invokestatic 140	xxxxxx/uxxxxx:bbbb0062b0062b0062b0062	(Ljava/lang/String;CCC)Ljava/lang/String;
    //   2072: iconst_3
    //   2073: anewarray 41	java/lang/Class
    //   2076: dup
    //   2077: iconst_0
    //   2078: ldc 43
    //   2080: aastore
    //   2081: dup
    //   2082: iconst_1
    //   2083: getstatic 49	java/lang/Character:TYPE	Ljava/lang/Class;
    //   2086: aastore
    //   2087: dup
    //   2088: iconst_2
    //   2089: getstatic 49	java/lang/Character:TYPE	Ljava/lang/Class;
    //   2092: aastore
    //   2093: invokevirtual 53	java/lang/Class:getMethod	(Ljava/lang/String;[Ljava/lang/Class;)Ljava/lang/reflect/Method;
    //   2096: astore_3
    //   2097: aload_3
    //   2098: aconst_null
    //   2099: iconst_3
    //   2100: anewarray 4	java/lang/Object
    //   2103: dup
    //   2104: iconst_0
    //   2105: ldc_w 268
    //   2108: aastore
    //   2109: dup
    //   2110: iconst_1
    //   2111: bipush 113
    //   2113: invokestatic 57	java/lang/Character:valueOf	(C)Ljava/lang/Character;
    //   2116: aastore
    //   2117: dup
    //   2118: iconst_2
    //   2119: iconst_2
    //   2120: invokestatic 57	java/lang/Character:valueOf	(C)Ljava/lang/Character;
    //   2123: aastore
    //   2124: invokevirtual 63	java/lang/reflect/Method:invoke	(Ljava/lang/Object;[Ljava/lang/Object;)Ljava/lang/Object;
    //   2127: astore_3
    //   2128: aload_2
    //   2129: aload_3
    //   2130: checkcast 43	java/lang/String
    //   2133: getstatic 271	com/db/pwcc/dbmobile/multi_bank_aggregator/R$drawable:ic_targo_bank	I
    //   2136: invokestatic 114	java/lang/Integer:valueOf	(I)Ljava/lang/Integer;
    //   2139: invokeinterface 120 3 0
    //   2144: pop
    //   2145: aload_0
    //   2146: getfield 100	uuuuuu/vxvxvx:bvv0076v0076v0076v0076	Ljava/util/Map;
    //   2149: astore_2
    //   2150: ldc 31
    //   2152: ldc_w 273
    //   2155: sipush 239
    //   2158: iconst_5
    //   2159: invokestatic 39	xxxxxx/uxxxxx:bb00620062bb0062b0062b0062	(Ljava/lang/String;CC)Ljava/lang/String;
    //   2162: iconst_3
    //   2163: anewarray 41	java/lang/Class
    //   2166: dup
    //   2167: iconst_0
    //   2168: ldc 43
    //   2170: aastore
    //   2171: dup
    //   2172: iconst_1
    //   2173: getstatic 49	java/lang/Character:TYPE	Ljava/lang/Class;
    //   2176: aastore
    //   2177: dup
    //   2178: iconst_2
    //   2179: getstatic 49	java/lang/Character:TYPE	Ljava/lang/Class;
    //   2182: aastore
    //   2183: invokevirtual 53	java/lang/Class:getMethod	(Ljava/lang/String;[Ljava/lang/Class;)Ljava/lang/reflect/Method;
    //   2186: astore_3
    //   2187: aload_3
    //   2188: aconst_null
    //   2189: iconst_3
    //   2190: anewarray 4	java/lang/Object
    //   2193: dup
    //   2194: iconst_0
    //   2195: ldc_w 275
    //   2198: aastore
    //   2199: dup
    //   2200: iconst_1
    //   2201: sipush 190
    //   2204: invokestatic 57	java/lang/Character:valueOf	(C)Ljava/lang/Character;
    //   2207: aastore
    //   2208: dup
    //   2209: iconst_2
    //   2210: iconst_2
    //   2211: invokestatic 57	java/lang/Character:valueOf	(C)Ljava/lang/Character;
    //   2214: aastore
    //   2215: invokevirtual 63	java/lang/reflect/Method:invoke	(Ljava/lang/Object;[Ljava/lang/Object;)Ljava/lang/Object;
    //   2218: astore_3
    //   2219: aload_2
    //   2220: aload_3
    //   2221: checkcast 43	java/lang/String
    //   2224: getstatic 278	com/db/pwcc/dbmobile/multi_bank_aggregator/R$drawable:ic_hypovereinsbank	I
    //   2227: invokestatic 114	java/lang/Integer:valueOf	(I)Ljava/lang/Integer;
    //   2230: invokeinterface 120 3 0
    //   2235: pop
    //   2236: aload_0
    //   2237: getfield 100	uuuuuu/vxvxvx:bvv0076v0076v0076v0076	Ljava/util/Map;
    //   2240: astore_2
    //   2241: ldc 31
    //   2243: ldc_w 280
    //   2246: sipush 205
    //   2249: iconst_3
    //   2250: invokestatic 39	xxxxxx/uxxxxx:bb00620062bb0062b0062b0062	(Ljava/lang/String;CC)Ljava/lang/String;
    //   2253: iconst_4
    //   2254: anewarray 41	java/lang/Class
    //   2257: dup
    //   2258: iconst_0
    //   2259: ldc 43
    //   2261: aastore
    //   2262: dup
    //   2263: iconst_1
    //   2264: getstatic 49	java/lang/Character:TYPE	Ljava/lang/Class;
    //   2267: aastore
    //   2268: dup
    //   2269: iconst_2
    //   2270: getstatic 49	java/lang/Character:TYPE	Ljava/lang/Class;
    //   2273: aastore
    //   2274: dup
    //   2275: iconst_3
    //   2276: getstatic 49	java/lang/Character:TYPE	Ljava/lang/Class;
    //   2279: aastore
    //   2280: invokevirtual 53	java/lang/Class:getMethod	(Ljava/lang/String;[Ljava/lang/Class;)Ljava/lang/reflect/Method;
    //   2283: astore_3
    //   2284: aload_3
    //   2285: aconst_null
    //   2286: iconst_4
    //   2287: anewarray 4	java/lang/Object
    //   2290: dup
    //   2291: iconst_0
    //   2292: ldc_w 282
    //   2295: aastore
    //   2296: dup
    //   2297: iconst_1
    //   2298: bipush 37
    //   2300: invokestatic 57	java/lang/Character:valueOf	(C)Ljava/lang/Character;
    //   2303: aastore
    //   2304: dup
    //   2305: iconst_2
    //   2306: sipush 206
    //   2309: invokestatic 57	java/lang/Character:valueOf	(C)Ljava/lang/Character;
    //   2312: aastore
    //   2313: dup
    //   2314: iconst_3
    //   2315: iconst_3
    //   2316: invokestatic 57	java/lang/Character:valueOf	(C)Ljava/lang/Character;
    //   2319: aastore
    //   2320: invokevirtual 63	java/lang/reflect/Method:invoke	(Ljava/lang/Object;[Ljava/lang/Object;)Ljava/lang/Object;
    //   2323: astore_3
    //   2324: aload_2
    //   2325: aload_3
    //   2326: checkcast 43	java/lang/String
    //   2329: getstatic 285	com/db/pwcc/dbmobile/multi_bank_aggregator/R$drawable:ic_volksbank	I
    //   2332: invokestatic 114	java/lang/Integer:valueOf	(I)Ljava/lang/Integer;
    //   2335: invokeinterface 120 3 0
    //   2340: pop
    //   2341: aload_0
    //   2342: aload_0
    //   2343: aload_1
    //   2344: invokespecial 289	uuuuuu/vxvxvx:bu0075uu0075uuu00750075	(Landroid/content/Context;)Lcom/google/gson/internal/LinkedTreeMap;
    //   2347: putfield 291	uuuuuu/vxvxvx:b00760076vv0076v0076v0076	Ljava/util/Map;
    //   2350: return
    //   2351: astore_1
    //   2352: aload_1
    //   2353: invokevirtual 88	java/lang/reflect/InvocationTargetException:getCause	()Ljava/lang/Throwable;
    //   2356: athrow
    //   2357: astore_1
    //   2358: aload_1
    //   2359: invokevirtual 88	java/lang/reflect/InvocationTargetException:getCause	()Ljava/lang/Throwable;
    //   2362: athrow
    //   2363: astore_1
    //   2364: aload_1
    //   2365: invokevirtual 88	java/lang/reflect/InvocationTargetException:getCause	()Ljava/lang/Throwable;
    //   2368: athrow
    //   2369: astore_1
    //   2370: aload_1
    //   2371: invokevirtual 88	java/lang/reflect/InvocationTargetException:getCause	()Ljava/lang/Throwable;
    //   2374: athrow
    //   2375: astore_1
    //   2376: aload_1
    //   2377: invokevirtual 88	java/lang/reflect/InvocationTargetException:getCause	()Ljava/lang/Throwable;
    //   2380: athrow
    //   2381: astore_1
    //   2382: aload_1
    //   2383: invokevirtual 88	java/lang/reflect/InvocationTargetException:getCause	()Ljava/lang/Throwable;
    //   2386: athrow
    //   2387: astore_1
    //   2388: aload_1
    //   2389: invokevirtual 88	java/lang/reflect/InvocationTargetException:getCause	()Ljava/lang/Throwable;
    //   2392: athrow
    //   2393: astore_1
    //   2394: aload_1
    //   2395: invokevirtual 88	java/lang/reflect/InvocationTargetException:getCause	()Ljava/lang/Throwable;
    //   2398: athrow
    //   2399: astore_1
    //   2400: aload_1
    //   2401: invokevirtual 88	java/lang/reflect/InvocationTargetException:getCause	()Ljava/lang/Throwable;
    //   2404: athrow
    //   2405: astore_1
    //   2406: aload_1
    //   2407: invokevirtual 88	java/lang/reflect/InvocationTargetException:getCause	()Ljava/lang/Throwable;
    //   2410: athrow
    //   2411: astore_1
    //   2412: aload_1
    //   2413: invokevirtual 88	java/lang/reflect/InvocationTargetException:getCause	()Ljava/lang/Throwable;
    //   2416: athrow
    //   2417: astore_1
    //   2418: aload_1
    //   2419: invokevirtual 88	java/lang/reflect/InvocationTargetException:getCause	()Ljava/lang/Throwable;
    //   2422: athrow
    //   2423: astore_1
    //   2424: aload_1
    //   2425: invokevirtual 88	java/lang/reflect/InvocationTargetException:getCause	()Ljava/lang/Throwable;
    //   2428: athrow
    //   2429: astore_1
    //   2430: aload_1
    //   2431: invokevirtual 88	java/lang/reflect/InvocationTargetException:getCause	()Ljava/lang/Throwable;
    //   2434: athrow
    //   2435: astore_1
    //   2436: aload_1
    //   2437: invokevirtual 88	java/lang/reflect/InvocationTargetException:getCause	()Ljava/lang/Throwable;
    //   2440: athrow
    //   2441: astore_1
    //   2442: aload_1
    //   2443: invokevirtual 88	java/lang/reflect/InvocationTargetException:getCause	()Ljava/lang/Throwable;
    //   2446: athrow
    //   2447: astore_1
    //   2448: aload_1
    //   2449: invokevirtual 88	java/lang/reflect/InvocationTargetException:getCause	()Ljava/lang/Throwable;
    //   2452: athrow
    //   2453: astore_1
    //   2454: aload_1
    //   2455: invokevirtual 88	java/lang/reflect/InvocationTargetException:getCause	()Ljava/lang/Throwable;
    //   2458: athrow
    //   2459: astore_1
    //   2460: aload_1
    //   2461: invokevirtual 88	java/lang/reflect/InvocationTargetException:getCause	()Ljava/lang/Throwable;
    //   2464: athrow
    //   2465: astore_1
    //   2466: aload_1
    //   2467: invokevirtual 88	java/lang/reflect/InvocationTargetException:getCause	()Ljava/lang/Throwable;
    //   2470: athrow
    //   2471: astore_1
    //   2472: aload_1
    //   2473: invokevirtual 88	java/lang/reflect/InvocationTargetException:getCause	()Ljava/lang/Throwable;
    //   2476: athrow
    //   2477: astore_1
    //   2478: aload_1
    //   2479: invokevirtual 88	java/lang/reflect/InvocationTargetException:getCause	()Ljava/lang/Throwable;
    //   2482: athrow
    //   2483: astore_1
    //   2484: aload_1
    //   2485: invokevirtual 88	java/lang/reflect/InvocationTargetException:getCause	()Ljava/lang/Throwable;
    //   2488: athrow
    //   2489: astore_1
    //   2490: aload_1
    //   2491: invokevirtual 88	java/lang/reflect/InvocationTargetException:getCause	()Ljava/lang/Throwable;
    //   2494: athrow
    //   2495: astore_1
    //   2496: getstatic 84	uuuuuu/vxvxvx:bv0076vv0076v0076v0076	Ljava/lang/String;
    //   2499: astore_2
    //   2500: ldc 31
    //   2502: ldc_w 293
    //   2505: sipush 233
    //   2508: bipush 123
    //   2510: iconst_1
    //   2511: invokestatic 140	xxxxxx/uxxxxx:bbbb0062b0062b0062b0062	(Ljava/lang/String;CCC)Ljava/lang/String;
    //   2514: iconst_4
    //   2515: anewarray 41	java/lang/Class
    //   2518: dup
    //   2519: iconst_0
    //   2520: ldc 43
    //   2522: aastore
    //   2523: dup
    //   2524: iconst_1
    //   2525: getstatic 49	java/lang/Character:TYPE	Ljava/lang/Class;
    //   2528: aastore
    //   2529: dup
    //   2530: iconst_2
    //   2531: getstatic 49	java/lang/Character:TYPE	Ljava/lang/Class;
    //   2534: aastore
    //   2535: dup
    //   2536: iconst_3
    //   2537: getstatic 49	java/lang/Character:TYPE	Ljava/lang/Class;
    //   2540: aastore
    //   2541: invokevirtual 53	java/lang/Class:getMethod	(Ljava/lang/String;[Ljava/lang/Class;)Ljava/lang/reflect/Method;
    //   2544: astore_3
    //   2545: aload_3
    //   2546: aconst_null
    //   2547: iconst_4
    //   2548: anewarray 4	java/lang/Object
    //   2551: dup
    //   2552: iconst_0
    //   2553: ldc_w 295
    //   2556: aastore
    //   2557: dup
    //   2558: iconst_1
    //   2559: sipush 220
    //   2562: invokestatic 57	java/lang/Character:valueOf	(C)Ljava/lang/Character;
    //   2565: aastore
    //   2566: dup
    //   2567: iconst_2
    //   2568: sipush 131
    //   2571: invokestatic 57	java/lang/Character:valueOf	(C)Ljava/lang/Character;
    //   2574: aastore
    //   2575: dup
    //   2576: iconst_3
    //   2577: iconst_2
    //   2578: invokestatic 57	java/lang/Character:valueOf	(C)Ljava/lang/Character;
    //   2581: aastore
    //   2582: invokevirtual 63	java/lang/reflect/Method:invoke	(Ljava/lang/Object;[Ljava/lang/Object;)Ljava/lang/Object;
    //   2585: astore_3
    //   2586: aload_2
    //   2587: aload_3
    //   2588: checkcast 43	java/lang/String
    //   2591: aload_1
    //   2592: invokestatic 301	uuuuuu/rvvvrv:b00710071qq00710071q0071q0071	(Ljava/lang/String;Ljava/lang/String;Ljava/lang/Throwable;)V
    //   2595: aload_0
    //   2596: aconst_null
    //   2597: putfield 291	uuuuuu/vxvxvx:b00760076vv0076v0076v0076	Ljava/util/Map;
    //   2600: return
    //   2601: astore_1
    //   2602: aload_1
    //   2603: invokevirtual 88	java/lang/reflect/InvocationTargetException:getCause	()Ljava/lang/Throwable;
    //   2606: athrow
    // Local variable table:
    //   start	length	slot	name	signature
    //   0	2607	0	this	vxvxvx
    //   0	2607	1	paramContext	Context
    //   19	2568	2	localObject1	Object
    //   54	2534	3	localObject2	Object
    // Exception table:
    //   from	to	target	type
    //   55	86	2351	java/lang/reflect/InvocationTargetException
    //   150	189	2357	java/lang/reflect/InvocationTargetException
    //   252	291	2363	java/lang/reflect/InvocationTargetException
    //   358	396	2369	java/lang/reflect/InvocationTargetException
    //   453	483	2375	java/lang/reflect/InvocationTargetException
    //   543	574	2381	java/lang/reflect/InvocationTargetException
    //   641	679	2387	java/lang/reflect/InvocationTargetException
    //   741	779	2393	java/lang/reflect/InvocationTargetException
    //   836	866	2399	java/lang/reflect/InvocationTargetException
    //   926	957	2405	java/lang/reflect/InvocationTargetException
    //   1015	1045	2411	java/lang/reflect/InvocationTargetException
    //   1109	1148	2417	java/lang/reflect/InvocationTargetException
    //   1208	1238	2423	java/lang/reflect/InvocationTargetException
    //   1295	1326	2429	java/lang/reflect/InvocationTargetException
    //   1389	1428	2435	java/lang/reflect/InvocationTargetException
    //   1484	1515	2441	java/lang/reflect/InvocationTargetException
    //   1582	1622	2447	java/lang/reflect/InvocationTargetException
    //   1685	1724	2453	java/lang/reflect/InvocationTargetException
    //   1788	1827	2459	java/lang/reflect/InvocationTargetException
    //   1894	1934	2465	java/lang/reflect/InvocationTargetException
    //   1997	2036	2471	java/lang/reflect/InvocationTargetException
    //   2097	2128	2477	java/lang/reflect/InvocationTargetException
    //   2187	2219	2483	java/lang/reflect/InvocationTargetException
    //   2284	2324	2489	java/lang/reflect/InvocationTargetException
    //   2341	2350	2495	java/io/IOException
    //   2545	2586	2601	java/lang/reflect/InvocationTargetException
  }
  
  public static int b0075uuu0075uuu00750075()
  {
    return 0;
  }
  
  private LinkedTreeMap<String, String> bu0075uu0075uuu00750075(Context paramContext)
    throws IOException
  {
    if ((b0076v0076v0076v0076v0076 + b007600760076v0076v0076v0076) * b0076v0076v0076v0076v0076 % bvvv00760076v0076v0076 != bv00760076v0076v0076v0076)
    {
      b0076v0076v0076v0076v0076 = buuuu0075uuu00750075();
      bv00760076v0076v0076v0076 = 73;
    }
    Object localObject = ppphhp.class.getMethod(uxxxxx.bb00620062bb0062b0062b0062("v\013BAGF\006\005<;A@87=<{3287/.43r", '', '\004'), new Class[] { String.class, Character.TYPE, Character.TYPE, Character.TYPE });
    try
    {
      localObject = ((Method)localObject).invoke(null, new Object[] { "HJNEJWMOJS_]d`P_Tde_e_l(eoll", Character.valueOf('\007'), Character.valueOf(''), Character.valueOf('\003') });
      localObject = (String)localObject;
      if ((b0076v0076v0076v0076v0076 + b007600760076v0076v0076v0076) * b0076v0076v0076v0076v0076 % bvvv00760076v0076v0076 != bv00760076v0076v0076v0076)
      {
        b0076v0076v0076v0076v0076 = 3;
        bv00760076v0076v0076v0076 = 35;
      }
      paramContext = ssxxxs.bk006Bk006B006Bk006Bk006B006B(paramContext, (String)localObject);
      return (LinkedTreeMap)new Gson().fromJson(paramContext, Map.class);
    }
    catch (InvocationTargetException paramContext)
    {
      throw paramContext.getCause();
    }
  }
  
  public static int buuuu0075uuu00750075()
  {
    return 78;
  }
  
  public int b00750075uu0075uuu00750075(String paramString)
  {
    int i;
    if (this.b00760076vv0076v0076v0076 == null) {
      i = R.drawable.ic_standard_bank;
    }
    int j;
    do
    {
      return i;
      paramString = (String)this.b00760076vv0076v0076v0076.get(paramString);
      if (paramString == null) {
        return R.drawable.ic_standard_bank;
      }
      paramString = (Integer)this.bvv0076v0076v0076v0076.get(paramString);
      if (paramString == null)
      {
        j = R.drawable.ic_standard_bank;
        int k = b0076v0076v0076v0076v0076;
        i = j;
        switch (k * (b007600760076v0076v0076v0076 + k) % bvvv00760076v0076v0076)
        {
        }
        b0076v0076v0076v0076v0076 = 14;
        bv00760076v0076v0076v0076 = 22;
        return j;
      }
      j = paramString.intValue();
      i = j;
    } while ((buuuu0075uuu00750075() + b007600760076v0076v0076v0076) * buuuu0075uuu00750075() % bvvv00760076v0076v0076 == bv00760076v0076v0076v0076);
    b0076v0076v0076v0076v0076 = 88;
    bv00760076v0076v0076v0076 = buuuu0075uuu00750075();
    return j;
  }
  
  public int buu0075u0075uuu00750075(String paramString)
  {
    paramString = (Integer)this.bvv0076v0076v0076v0076.get(paramString);
    if (paramString == null)
    {
      int i = R.drawable.ic_standard_bank;
      if ((b0076v0076v0076v0076v0076 + b007600760076v0076v0076v0076) * b0076v0076v0076v0076v0076 % bvvv00760076v0076v0076 != bv00760076v0076v0076v0076)
      {
        b0076v0076v0076v0076v0076 = 83;
        bv00760076v0076v0076v0076 = buuuu0075uuu00750075();
        int j = b0076v0076v0076v0076v0076;
        switch (j * (b007600760076v0076v0076v0076 + j) % bvvv00760076v0076v0076)
        {
        default: 
          b0076v0076v0076v0076v0076 = 77;
          bv00760076v0076v0076v0076 = 18;
        }
      }
      return i;
    }
    return paramString.intValue();
  }
}
