package uuuuuu;

import java.util.ArrayList;
import net.gini.android.vision.onboarding.OnboardingPage;

public enum wnnwwn
{
  private final OnboardingPage bc00630063c00630063cc0063;
  
  /* Error */
  static
  {
    // Byte code:
    //   0: ldc 19
    //   2: ldc 21
    //   4: bipush 69
    //   6: iconst_5
    //   7: invokestatic 27	xxxxxx/uxxxxx:bb00620062bb0062b0062b0062	(Ljava/lang/String;CC)Ljava/lang/String;
    //   10: iconst_4
    //   11: anewarray 29	java/lang/Class
    //   14: dup
    //   15: iconst_0
    //   16: ldc 31
    //   18: aastore
    //   19: dup
    //   20: iconst_1
    //   21: getstatic 37	java/lang/Character:TYPE	Ljava/lang/Class;
    //   24: aastore
    //   25: dup
    //   26: iconst_2
    //   27: getstatic 37	java/lang/Character:TYPE	Ljava/lang/Class;
    //   30: aastore
    //   31: dup
    //   32: iconst_3
    //   33: getstatic 37	java/lang/Character:TYPE	Ljava/lang/Class;
    //   36: aastore
    //   37: invokevirtual 41	java/lang/Class:getMethod	(Ljava/lang/String;[Ljava/lang/Class;)Ljava/lang/reflect/Method;
    //   40: astore 5
    //   42: aload 5
    //   44: aconst_null
    //   45: iconst_4
    //   46: anewarray 43	java/lang/Object
    //   49: dup
    //   50: iconst_0
    //   51: ldc 45
    //   53: aastore
    //   54: dup
    //   55: iconst_1
    //   56: bipush 121
    //   58: invokestatic 49	java/lang/Character:valueOf	(C)Ljava/lang/Character;
    //   61: aastore
    //   62: dup
    //   63: iconst_2
    //   64: bipush 55
    //   66: invokestatic 49	java/lang/Character:valueOf	(C)Ljava/lang/Character;
    //   69: aastore
    //   70: dup
    //   71: iconst_3
    //   72: iconst_3
    //   73: invokestatic 49	java/lang/Character:valueOf	(C)Ljava/lang/Character;
    //   76: aastore
    //   77: invokevirtual 55	java/lang/reflect/Method:invoke	(Ljava/lang/Object;[Ljava/lang/Object;)Ljava/lang/Object;
    //   80: astore 5
    //   82: new 2	uuuuuu/wnnwwn
    //   85: dup
    //   86: aload 5
    //   88: checkcast 31	java/lang/String
    //   91: iconst_0
    //   92: new 57	net/gini/android/vision/onboarding/OnboardingPage
    //   95: dup
    //   96: getstatic 63	com/db/pwcc/dbmobile/gini/R$string:gv_onboarding_flat	I
    //   99: getstatic 68	com/db/pwcc/dbmobile/gini/R$drawable:img_gini_tut_01	I
    //   102: invokespecial 72	net/gini/android/vision/onboarding/OnboardingPage:<init>	(II)V
    //   105: invokespecial 75	uuuuuu/wnnwwn:<init>	(Ljava/lang/String;ILnet/gini/android/vision/onboarding/OnboardingPage;)V
    //   108: putstatic 77	uuuuuu/wnnwwn:bcc0063c00630063cc0063	Luuuuuu/wnnwwn;
    //   111: ldc 19
    //   113: ldc 79
    //   115: bipush 11
    //   117: iconst_3
    //   118: invokestatic 27	xxxxxx/uxxxxx:bb00620062bb0062b0062b0062	(Ljava/lang/String;CC)Ljava/lang/String;
    //   121: iconst_3
    //   122: anewarray 29	java/lang/Class
    //   125: dup
    //   126: iconst_0
    //   127: ldc 31
    //   129: aastore
    //   130: dup
    //   131: iconst_1
    //   132: getstatic 37	java/lang/Character:TYPE	Ljava/lang/Class;
    //   135: aastore
    //   136: dup
    //   137: iconst_2
    //   138: getstatic 37	java/lang/Character:TYPE	Ljava/lang/Class;
    //   141: aastore
    //   142: invokevirtual 41	java/lang/Class:getMethod	(Ljava/lang/String;[Ljava/lang/Class;)Ljava/lang/reflect/Method;
    //   145: astore 5
    //   147: aload 5
    //   149: aconst_null
    //   150: iconst_3
    //   151: anewarray 43	java/lang/Object
    //   154: dup
    //   155: iconst_0
    //   156: ldc 81
    //   158: aastore
    //   159: dup
    //   160: iconst_1
    //   161: sipush 187
    //   164: invokestatic 49	java/lang/Character:valueOf	(C)Ljava/lang/Character;
    //   167: aastore
    //   168: dup
    //   169: iconst_2
    //   170: iconst_5
    //   171: invokestatic 49	java/lang/Character:valueOf	(C)Ljava/lang/Character;
    //   174: aastore
    //   175: invokevirtual 55	java/lang/reflect/Method:invoke	(Ljava/lang/Object;[Ljava/lang/Object;)Ljava/lang/Object;
    //   178: astore 5
    //   180: new 2	uuuuuu/wnnwwn
    //   183: dup
    //   184: aload 5
    //   186: checkcast 31	java/lang/String
    //   189: iconst_1
    //   190: new 57	net/gini/android/vision/onboarding/OnboardingPage
    //   193: dup
    //   194: getstatic 84	com/db/pwcc/dbmobile/gini/R$string:gv_onboarding_parallel	I
    //   197: getstatic 87	com/db/pwcc/dbmobile/gini/R$drawable:img_gini_tut_02	I
    //   200: invokespecial 72	net/gini/android/vision/onboarding/OnboardingPage:<init>	(II)V
    //   203: invokespecial 75	uuuuuu/wnnwwn:<init>	(Ljava/lang/String;ILnet/gini/android/vision/onboarding/OnboardingPage;)V
    //   206: putstatic 89	uuuuuu/wnnwwn:b0063c0063c00630063cc0063	Luuuuuu/wnnwwn;
    //   209: ldc 19
    //   211: ldc 91
    //   213: bipush 64
    //   215: sipush 154
    //   218: iconst_0
    //   219: invokestatic 95	xxxxxx/uxxxxx:bbbb0062b0062b0062b0062	(Ljava/lang/String;CCC)Ljava/lang/String;
    //   222: iconst_3
    //   223: anewarray 29	java/lang/Class
    //   226: dup
    //   227: iconst_0
    //   228: ldc 31
    //   230: aastore
    //   231: dup
    //   232: iconst_1
    //   233: getstatic 37	java/lang/Character:TYPE	Ljava/lang/Class;
    //   236: aastore
    //   237: dup
    //   238: iconst_2
    //   239: getstatic 37	java/lang/Character:TYPE	Ljava/lang/Class;
    //   242: aastore
    //   243: invokevirtual 41	java/lang/Class:getMethod	(Ljava/lang/String;[Ljava/lang/Class;)Ljava/lang/reflect/Method;
    //   246: astore 5
    //   248: aload 5
    //   250: aconst_null
    //   251: iconst_3
    //   252: anewarray 43	java/lang/Object
    //   255: dup
    //   256: iconst_0
    //   257: ldc 97
    //   259: aastore
    //   260: dup
    //   261: iconst_1
    //   262: bipush 16
    //   264: invokestatic 49	java/lang/Character:valueOf	(C)Ljava/lang/Character;
    //   267: aastore
    //   268: dup
    //   269: iconst_2
    //   270: iconst_3
    //   271: invokestatic 49	java/lang/Character:valueOf	(C)Ljava/lang/Character;
    //   274: aastore
    //   275: invokevirtual 55	java/lang/reflect/Method:invoke	(Ljava/lang/Object;[Ljava/lang/Object;)Ljava/lang/Object;
    //   278: astore 5
    //   280: new 2	uuuuuu/wnnwwn
    //   283: dup
    //   284: aload 5
    //   286: checkcast 31	java/lang/String
    //   289: iconst_2
    //   290: new 57	net/gini/android/vision/onboarding/OnboardingPage
    //   293: dup
    //   294: getstatic 100	com/db/pwcc/dbmobile/gini/R$string:gv_onboarding_align	I
    //   297: getstatic 103	com/db/pwcc/dbmobile/gini/R$drawable:img_gini_tut_03	I
    //   300: invokespecial 72	net/gini/android/vision/onboarding/OnboardingPage:<init>	(II)V
    //   303: invokespecial 75	uuuuuu/wnnwwn:<init>	(Ljava/lang/String;ILnet/gini/android/vision/onboarding/OnboardingPage;)V
    //   306: putstatic 105	uuuuuu/wnnwwn:b00630063cc00630063cc0063	Luuuuuu/wnnwwn;
    //   309: getstatic 77	uuuuuu/wnnwwn:bcc0063c00630063cc0063	Luuuuuu/wnnwwn;
    //   312: astore 5
    //   314: getstatic 89	uuuuuu/wnnwwn:b0063c0063c00630063cc0063	Luuuuuu/wnnwwn;
    //   317: astore 6
    //   319: getstatic 105	uuuuuu/wnnwwn:b00630063cc00630063cc0063	Luuuuuu/wnnwwn;
    //   322: astore 7
    //   324: invokestatic 109	uuuuuu/wnnwwn:b0071qq0071q0071qq0071q	()I
    //   327: istore_0
    //   328: invokestatic 112	uuuuuu/wnnwwn:bq0071q0071q0071qq0071q	()I
    //   331: istore_1
    //   332: invokestatic 109	uuuuuu/wnnwwn:b0071qq0071q0071qq0071q	()I
    //   335: istore_2
    //   336: invokestatic 115	uuuuuu/wnnwwn:b00710071q0071q0071qq0071q	()I
    //   339: istore_3
    //   340: invokestatic 118	uuuuuu/wnnwwn:bqq00710071q0071qq0071q	()I
    //   343: istore 4
    //   345: invokestatic 109	uuuuuu/wnnwwn:b0071qq0071q0071qq0071q	()I
    //   348: invokestatic 112	uuuuuu/wnnwwn:bq0071q0071q0071qq0071q	()I
    //   351: iadd
    //   352: invokestatic 109	uuuuuu/wnnwwn:b0071qq0071q0071qq0071q	()I
    //   355: imul
    //   356: invokestatic 115	uuuuuu/wnnwwn:b00710071q0071q0071qq0071q	()I
    //   359: irem
    //   360: invokestatic 118	uuuuuu/wnnwwn:bqq00710071q0071qq0071q	()I
    //   363: if_icmpeq +3 -> 366
    //   366: iload_0
    //   367: iload_1
    //   368: iadd
    //   369: iload_2
    //   370: imul
    //   371: iload_3
    //   372: irem
    //   373: iload 4
    //   375: if_icmpeq +3 -> 378
    //   378: iconst_3
    //   379: anewarray 2	uuuuuu/wnnwwn
    //   382: dup
    //   383: iconst_0
    //   384: aload 5
    //   386: aastore
    //   387: dup
    //   388: iconst_1
    //   389: aload 6
    //   391: aastore
    //   392: dup
    //   393: iconst_2
    //   394: aload 7
    //   396: aastore
    //   397: putstatic 120	uuuuuu/wnnwwn:bc0063cc00630063cc0063	[Luuuuuu/wnnwwn;
    //   400: return
    //   401: astore 5
    //   403: aload 5
    //   405: invokevirtual 124	java/lang/reflect/InvocationTargetException:getCause	()Ljava/lang/Throwable;
    //   408: athrow
    //   409: astore 5
    //   411: aload 5
    //   413: invokevirtual 124	java/lang/reflect/InvocationTargetException:getCause	()Ljava/lang/Throwable;
    //   416: athrow
    //   417: astore 5
    //   419: aload 5
    //   421: invokevirtual 124	java/lang/reflect/InvocationTargetException:getCause	()Ljava/lang/Throwable;
    //   424: athrow
    // Local variable table:
    //   start	length	slot	name	signature
    //   327	42	0	i	int
    //   331	38	1	j	int
    //   335	36	2	k	int
    //   339	34	3	m	int
    //   343	33	4	n	int
    //   40	345	5	localObject	Object
    //   401	3	5	localInvocationTargetException1	java.lang.reflect.InvocationTargetException
    //   409	3	5	localInvocationTargetException2	java.lang.reflect.InvocationTargetException
    //   417	3	5	localInvocationTargetException3	java.lang.reflect.InvocationTargetException
    //   317	73	6	localWnnwwn1	wnnwwn
    //   322	73	7	localWnnwwn2	wnnwwn
    // Exception table:
    //   from	to	target	type
    //   42	82	401	java/lang/reflect/InvocationTargetException
    //   248	280	409	java/lang/reflect/InvocationTargetException
    //   147	180	417	java/lang/reflect/InvocationTargetException
  }
  
  private wnnwwn(OnboardingPage paramOnboardingPage)
  {
    this.bc00630063c00630063cc0063 = paramOnboardingPage;
  }
  
  public static int b00710071q0071q0071qq0071q()
  {
    return 2;
  }
  
  public static int b0071qq0071q0071qq0071q()
  {
    return 24;
  }
  
  public static wnnwwn bq007100710071q0071qq0071q(String paramString)
  {
    int i = b0071qq0071q0071qq0071q();
    switch (i * (bq0071q0071q0071qq0071q() + i) % b00710071q0071q0071qq0071q())
    {
    default: 
      i = b0071qq0071q0071qq0071q();
      switch (i * (bq0071q0071q0071qq0071q() + i) % b00710071q0071q0071qq0071q())
      {
      }
      break;
    }
    return (wnnwwn)Enum.valueOf(wnnwwn.class, paramString);
  }
  
  public static int bq0071q0071q0071qq0071q()
  {
    return 1;
  }
  
  public static int bqq00710071q0071qq0071q()
  {
    return 0;
  }
  
  public static ArrayList<OnboardingPage> bqqq0071q0071qq0071q()
  {
    if ((b0071qq0071q0071qq0071q() + bq0071q0071q0071qq0071q()) * b0071qq0071q0071qq0071q() % b00710071q0071q0071qq0071q() != bqq00710071q0071qq0071q()) {}
    ArrayList localArrayList = new ArrayList(values().length);
    wnnwwn[] arrayOfWnnwwn = values();
    int j = arrayOfWnnwwn.length;
    int i = 0;
    while (i < j)
    {
      if ((b0071qq0071q0071qq0071q() + bq0071q0071q0071qq0071q()) * b0071qq0071q0071qq0071q() % b00710071q0071q0071qq0071q() != bqq00710071q0071qq0071q()) {}
      localArrayList.add(arrayOfWnnwwn[i].b0071q00710071q0071qq0071q());
      i += 1;
    }
    return localArrayList;
  }
  
  public OnboardingPage b0071q00710071q0071qq0071q()
  {
    int i = b0071qq0071q0071qq0071q();
    int j = bq0071q0071q0071qq0071q();
    int k = b0071qq0071q0071qq0071q();
    int m = b00710071q0071q0071qq0071q();
    int n = b0071qq0071q0071qq0071q();
    switch (n * (bq0071q0071q0071qq0071q() + n) % b00710071q0071q0071qq0071q())
    {
    }
    if ((i + j) * k % m != bqq00710071q0071qq0071q()) {}
    return this.bc00630063c00630063cc0063;
  }
}
