package uuuuuu;

import android.content.Context;
import android.graphics.BitmapFactory;
import android.graphics.drawable.Drawable;
import android.graphics.drawable.TransitionDrawable;
import android.support.v4.content.ContextCompat;
import android.support.v7.app.AppCompatActivity;
import android.view.Window;
import com.db.pwcc.dbmobile.foundation.R.string;
import com.db.pwcc.dbmobile.foundation.utils.BackgroundChangeEnum;
import com.db.pwcc.dbmobile.secure.preferences.SharedPreferencesHelper;
import java.io.File;
import java.lang.reflect.InvocationTargetException;
import java.lang.reflect.Method;
import javax.inject.Inject;
import xxxxxx.uxxxxx;

public class xsxsxs
{
  private static final String b00660066f0066f006600660066f;
  public static int b00660066ff0066006600660066f = 2;
  private static final String b0066ff0066f006600660066f = "6IHJFE\035<\035=@IFRPWQH\023PWO";
  public static int b0066fff0066006600660066f = 0;
  private static final String bf0066f0066f006600660066f = "dg[ma^q>qprnmEdEehqnzxyp;xw";
  public static int bf0066ff0066006600660066f = 1;
  public static int bffff0066006600660066f = 16;
  @Inject
  public SharedPreferencesHelper b0066006600660066f006600660066f;
  private String b0066f00660066f006600660066f;
  private Drawable bf006600660066f006600660066f;
  private String bff00660066f006600660066f;
  
  /* Error */
  static
  {
    // Byte code:
    //   0: getstatic 34	uuuuuu/xsxsxs:b0066ff0066f006600660066f	Ljava/lang/String;
    //   3: astore_2
    //   4: ldc 36
    //   6: ldc 38
    //   8: iconst_5
    //   9: iconst_2
    //   10: invokestatic 44	xxxxxx/uxxxxx:bb00620062bb0062b0062b0062	(Ljava/lang/String;CC)Ljava/lang/String;
    //   13: iconst_3
    //   14: anewarray 46	java/lang/Class
    //   17: dup
    //   18: iconst_0
    //   19: ldc 48
    //   21: aastore
    //   22: dup
    //   23: iconst_1
    //   24: getstatic 54	java/lang/Character:TYPE	Ljava/lang/Class;
    //   27: aastore
    //   28: dup
    //   29: iconst_2
    //   30: getstatic 54	java/lang/Character:TYPE	Ljava/lang/Class;
    //   33: aastore
    //   34: invokevirtual 58	java/lang/Class:getMethod	(Ljava/lang/String;[Ljava/lang/Class;)Ljava/lang/reflect/Method;
    //   37: astore_3
    //   38: aload_3
    //   39: aconst_null
    //   40: iconst_3
    //   41: anewarray 4	java/lang/Object
    //   44: dup
    //   45: iconst_0
    //   46: aload_2
    //   47: aastore
    //   48: dup
    //   49: iconst_1
    //   50: bipush 82
    //   52: invokestatic 62	java/lang/Character:valueOf	(C)Ljava/lang/Character;
    //   55: aastore
    //   56: dup
    //   57: iconst_2
    //   58: iconst_2
    //   59: invokestatic 62	java/lang/Character:valueOf	(C)Ljava/lang/Character;
    //   62: aastore
    //   63: invokevirtual 68	java/lang/reflect/Method:invoke	(Ljava/lang/Object;[Ljava/lang/Object;)Ljava/lang/Object;
    //   66: astore_2
    //   67: aload_2
    //   68: checkcast 48	java/lang/String
    //   71: astore_2
    //   72: getstatic 70	uuuuuu/xsxsxs:bffff0066006600660066f	I
    //   75: istore_0
    //   76: getstatic 72	uuuuuu/xsxsxs:bf0066ff0066006600660066f	I
    //   79: istore_1
    //   80: getstatic 70	uuuuuu/xsxsxs:bffff0066006600660066f	I
    //   83: getstatic 72	uuuuuu/xsxsxs:bf0066ff0066006600660066f	I
    //   86: iadd
    //   87: getstatic 70	uuuuuu/xsxsxs:bffff0066006600660066f	I
    //   90: imul
    //   91: getstatic 74	uuuuuu/xsxsxs:b00660066ff0066006600660066f	I
    //   94: irem
    //   95: getstatic 76	uuuuuu/xsxsxs:b0066fff0066006600660066f	I
    //   98: if_icmpeq +12 -> 110
    //   101: bipush 65
    //   103: putstatic 70	uuuuuu/xsxsxs:bffff0066006600660066f	I
    //   106: iconst_5
    //   107: putstatic 76	uuuuuu/xsxsxs:b0066fff0066006600660066f	I
    //   110: iload_0
    //   111: iload_1
    //   112: iadd
    //   113: getstatic 70	uuuuuu/xsxsxs:bffff0066006600660066f	I
    //   116: imul
    //   117: getstatic 74	uuuuuu/xsxsxs:b00660066ff0066006600660066f	I
    //   120: irem
    //   121: getstatic 76	uuuuuu/xsxsxs:b0066fff0066006600660066f	I
    //   124: if_icmpeq +14 -> 138
    //   127: invokestatic 80	uuuuuu/xsxsxs:bk006B006B006Bk006Bkk006B006B	()I
    //   130: putstatic 70	uuuuuu/xsxsxs:bffff0066006600660066f	I
    //   133: bipush 81
    //   135: putstatic 76	uuuuuu/xsxsxs:b0066fff0066006600660066f	I
    //   138: aload_2
    //   139: putstatic 34	uuuuuu/xsxsxs:b0066ff0066f006600660066f	Ljava/lang/String;
    //   142: getstatic 82	uuuuuu/xsxsxs:bf0066f0066f006600660066f	Ljava/lang/String;
    //   145: astore_2
    //   146: ldc 36
    //   148: ldc 84
    //   150: bipush 120
    //   152: sipush 180
    //   155: iconst_2
    //   156: invokestatic 88	xxxxxx/uxxxxx:bbbb0062b0062b0062b0062	(Ljava/lang/String;CCC)Ljava/lang/String;
    //   159: iconst_3
    //   160: anewarray 46	java/lang/Class
    //   163: dup
    //   164: iconst_0
    //   165: ldc 48
    //   167: aastore
    //   168: dup
    //   169: iconst_1
    //   170: getstatic 54	java/lang/Character:TYPE	Ljava/lang/Class;
    //   173: aastore
    //   174: dup
    //   175: iconst_2
    //   176: getstatic 54	java/lang/Character:TYPE	Ljava/lang/Class;
    //   179: aastore
    //   180: invokevirtual 58	java/lang/Class:getMethod	(Ljava/lang/String;[Ljava/lang/Class;)Ljava/lang/reflect/Method;
    //   183: astore_3
    //   184: aload_3
    //   185: aconst_null
    //   186: iconst_3
    //   187: anewarray 4	java/lang/Object
    //   190: dup
    //   191: iconst_0
    //   192: aload_2
    //   193: aastore
    //   194: dup
    //   195: iconst_1
    //   196: bipush 121
    //   198: invokestatic 62	java/lang/Character:valueOf	(C)Ljava/lang/Character;
    //   201: aastore
    //   202: dup
    //   203: iconst_2
    //   204: iconst_1
    //   205: invokestatic 62	java/lang/Character:valueOf	(C)Ljava/lang/Character;
    //   208: aastore
    //   209: invokevirtual 68	java/lang/reflect/Method:invoke	(Ljava/lang/Object;[Ljava/lang/Object;)Ljava/lang/Object;
    //   212: astore_2
    //   213: aload_2
    //   214: checkcast 48	java/lang/String
    //   217: putstatic 82	uuuuuu/xsxsxs:bf0066f0066f006600660066f	Ljava/lang/String;
    //   220: ldc 2
    //   222: invokevirtual 92	java/lang/Class:getSimpleName	()Ljava/lang/String;
    //   225: putstatic 94	uuuuuu/xsxsxs:b00660066f0066f006600660066f	Ljava/lang/String;
    //   228: return
    //   229: astore_2
    //   230: aload_2
    //   231: invokevirtual 98	java/lang/reflect/InvocationTargetException:getCause	()Ljava/lang/Throwable;
    //   234: athrow
    //   235: astore_2
    //   236: aload_2
    //   237: invokevirtual 98	java/lang/reflect/InvocationTargetException:getCause	()Ljava/lang/Throwable;
    //   240: athrow
    // Local variable table:
    //   start	length	slot	name	signature
    //   75	38	0	i	int
    //   79	34	1	j	int
    //   3	211	2	localObject	Object
    //   229	2	2	localInvocationTargetException1	InvocationTargetException
    //   235	2	2	localInvocationTargetException2	InvocationTargetException
    //   37	148	3	localMethod	Method
    // Exception table:
    //   from	to	target	type
    //   184	213	229	java/lang/reflect/InvocationTargetException
    //   38	67	235	java/lang/reflect/InvocationTargetException
  }
  
  public xsxsxs()
  {
    pqqppq.b006B006B006Bkkk006Bkkk().b0070ppppppppp(this);
  }
  
  public static int b006B006B006B006Bk006Bkk006B006B()
  {
    return 1;
  }
  
  private void b006B006Bk006Bk006Bkk006B006B(Drawable[] paramArrayOfDrawable, AppCompatActivity paramAppCompatActivity)
  {
    paramArrayOfDrawable = new TransitionDrawable(paramArrayOfDrawable);
    paramAppCompatActivity.getWindow().setBackgroundDrawable(paramArrayOfDrawable);
    if ((bffff0066006600660066f + bf0066ff0066006600660066f) * bffff0066006600660066f % b00660066ff0066006600660066f != bkk006B006Bk006Bkk006B006B())
    {
      int i = bffff0066006600660066f;
      switch (i * (bf0066ff0066006600660066f + i) % b00660066ff0066006600660066f)
      {
      default: 
        bffff0066006600660066f = bk006B006B006Bk006Bkk006B006B();
        b0066fff0066006600660066f = bk006B006B006Bk006Bkk006B006B();
      }
      bffff0066006600660066f = 63;
      b0066fff0066006600660066f = bk006B006B006Bk006Bkk006B006B();
    }
    paramArrayOfDrawable.startTransition(500);
  }
  
  public static int b006Bk006B006Bk006Bkk006B006B()
  {
    return 2;
  }
  
  private void b006Bkkk006B006Bkk006B006B(int paramInt)
  {
    int i = bffff0066006600660066f;
    switch (i * (b006B006B006B006Bk006Bkk006B006B() + i) % b00660066ff0066006600660066f)
    {
    default: 
      bffff0066006600660066f = bk006B006B006Bk006Bkk006B006B();
      b0066fff0066006600660066f = 8;
    }
    switch (paramInt)
    {
    default: 
    case 1: 
    case 2: 
    case 3: 
      do
      {
        return;
        rrvvrv.b0071q0071qq0071q0071q0071(vvrvrv.bh00680068hh0068006800680068);
        return;
        rrvvrv.b0071q0071qq0071q0071q0071(vvrvrv.bhh0068hh0068006800680068);
        return;
        rrvvrv.b0071q0071qq0071q0071q0071(vvrvrv.bhhhhh0068006800680068);
      } while ((bffff0066006600660066f + bf0066ff0066006600660066f) * bffff0066006600660066f % b00660066ff0066006600660066f == b0066fff0066006600660066f);
      bffff0066006600660066f = 81;
      b0066fff0066006600660066f = bk006B006B006Bk006Bkk006B006B();
      return;
    }
    rrvvrv.b0071q0071qq0071q0071q0071(vvrvrv.bh0068hhh0068006800680068);
  }
  
  public static int bk006B006B006Bk006Bkk006B006B()
  {
    return 10;
  }
  
  public static int bkk006B006Bk006Bkk006B006B()
  {
    return 0;
  }
  
  public void b006B006B006Bk006B006Bkk006B006B(int paramInt)
  {
    if (paramInt == BackgroundChangeEnum.values().length)
    {
      rrvvrv.b0071q0071qq0071q0071q0071(vvrvrv.b00680068006800680068h006800680068);
      paramInt = bffff0066006600660066f;
      switch (paramInt * (bf0066ff0066006600660066f + paramInt) % b00660066ff0066006600660066f)
      {
      default: 
        bffff0066006600660066f = bk006B006B006Bk006Bkk006B006B();
        b0066fff0066006600660066f = 74;
        if ((bffff0066006600660066f + bf0066ff0066006600660066f) * bffff0066006600660066f % b006Bk006B006Bk006Bkk006B006B() != b0066fff0066006600660066f)
        {
          bffff0066006600660066f = 53;
          b0066fff0066006600660066f = bk006B006B006Bk006Bkk006B006B();
        }
        break;
      }
    }
  }
  
  public Drawable b006B006Bkk006B006Bkk006B006B(Context paramContext)
  {
    Object localObject = this.b0066006600660066f006600660066f;
    Method localMethod = SharedPreferencesHelper.class.getMethod(uxxxxx.bbbb0062b0062b0062b0062("xu\004Q\003yvJhipkuqvncGj]b_IYk^", '', 'e', '\000'), new Class[0]);
    try
    {
      localObject = localMethod.invoke(localObject, new Object[0]);
      localObject = (String)localObject;
      if ((bffff0066006600660066f + bf0066ff0066006600660066f) * bffff0066006600660066f % b006Bk006B006Bk006Bkk006B006B() != b0066fff0066006600660066f)
      {
        bffff0066006600660066f = bk006B006B006Bk006Bkk006B006B();
        b0066fff0066006600660066f = bk006B006B006Bk006Bkk006B006B();
      }
      if (((String)localObject).isEmpty())
      {
        localObject = BackgroundChangeEnum.values()[bkkkk006B006Bkk006B006B()];
        if ((bffff0066006600660066f + b006B006B006B006Bk006Bkk006B006B()) * bffff0066006600660066f % b00660066ff0066006600660066f != b0066fff0066006600660066f)
        {
          bffff0066006600660066f = bk006B006B006Bk006Bkk006B006B();
          b0066fff0066006600660066f = 83;
        }
        return ContextCompat.getDrawable(paramContext, ((BackgroundChangeEnum)localObject).getDrawableResId());
      }
    }
    catch (InvocationTargetException paramContext)
    {
      throw paramContext.getCause();
    }
    return Drawable.createFromPath((String)localObject);
  }
  
  public void b006Bk006Bk006B006Bkk006B006B(Context paramContext)
  {
    paramContext = paramContext.getFilesDir();
    paramContext = new StringBuilder().append(paramContext).append(File.separator);
    Object localObject = ppphhp.class.getMethod(uxxxxx.bb00620062bb0062b0062b0062("au-,21po'&,+#\"('f\036\035#\"\032\031\037\036]", 'Ô', '\005'), new Class[] { String.class, Character.TYPE, Character.TYPE, Character.TYPE });
    try
    {
      localObject = ((Method)localObject).invoke(null, new Object[] { "6GDD>;\021.\r+,3.8491&n*/%", Character.valueOf(''), Character.valueOf('\021'), Character.valueOf('\000') });
      this.bff00660066f006600660066f = ((String)localObject);
      int i = bk006B006B006Bk006Bkk006B006B();
      switch (i * (bf0066ff0066006600660066f + i) % b00660066ff0066006600660066f)
      {
      default: 
        bffff0066006600660066f = 2;
        b0066fff0066006600660066f = bk006B006B006Bk006Bkk006B006B();
      }
      paramContext = new File(this.bff00660066f006600660066f);
      localObject = this.b0066f00660066f006600660066f;
      i = bffff0066006600660066f;
      switch (i * (bf0066ff0066006600660066f + i) % b00660066ff0066006600660066f)
      {
      default: 
        bffff0066006600660066f = bk006B006B006Bk006Bkk006B006B();
        b0066fff0066006600660066f = 89;
      }
      bk006B006Bk006B006Bkk006B006B(BitmapFactory.decodeFile((String)localObject), paramContext);
      return;
    }
    catch (InvocationTargetException paramContext)
    {
      throw paramContext.getCause();
    }
  }
  
  public void b006Bkk006B006B006Bkk006B006B(Context paramContext, boolean paramBoolean, int paramInt)
  {
    int i = bffff0066006600660066f;
    switch (i * (bf0066ff0066006600660066f + i) % b00660066ff0066006600660066f)
    {
    default: 
      bffff0066006600660066f = bk006B006B006Bk006Bkk006B006B();
      b0066fff0066006600660066f = bk006B006B006Bk006Bkk006B006B();
    }
    Object localObject;
    Method localMethod;
    if (paramBoolean)
    {
      b006Bk006Bk006B006Bkk006B006B(paramContext);
      if ((this.bff00660066f006600660066f != null) && (!this.bff00660066f006600660066f.isEmpty()))
      {
        paramContext = this.b0066006600660066f006600660066f;
        localObject = this.bff00660066f006600660066f;
        if ((bk006B006B006Bk006Bkk006B006B() + b006B006B006B006Bk006Bkk006B006B()) * bk006B006B006Bk006Bkk006B006B() % b00660066ff0066006600660066f != b0066fff0066006600660066f)
        {
          bffff0066006600660066f = 82;
          b0066fff0066006600660066f = 71;
        }
        localMethod = SharedPreferencesHelper.class.getMethod(uxxxxx.bb00620062bb0062b0062b0062("UFT\"SPPJG\0339:A<FBG?4\030;.30\032*</", '', '\005'), new Class[] { String.class });
      }
    }
    for (;;)
    {
      try
      {
        paramContext = localMethod.invoke(paramContext, new Object[] { localObject });
        ((Boolean)paramContext).booleanValue();
        b006Bkkk006B006Bkk006B006B(paramInt);
        return;
      }
      catch (InvocationTargetException paramContext)
      {
        throw paramContext.getCause();
      }
      paramContext = this.b0066006600660066f006600660066f;
      localObject = SharedPreferencesHelper.class.getMethod(uxxxxx.bb00620062bb0062b0062b0062("\031\n\030f\007\007\001\024\n\021]{|\004~\t\005\n\002vZ}purUynn\001", '', '\005'), new Class[] { Integer.TYPE });
      try
      {
        paramContext = ((Method)localObject).invoke(paramContext, new Object[] { Integer.valueOf(paramInt) });
        ((Boolean)paramContext).booleanValue();
      }
      catch (InvocationTargetException paramContext)
      {
        throw paramContext.getCause();
      }
    }
  }
  
  /* Error */
  public void bk006B006Bk006B006Bkk006B006B(android.graphics.Bitmap paramBitmap, File paramFile)
  {
    // Byte code:
    //   0: aconst_null
    //   1: astore_3
    //   2: new 282	java/io/FileOutputStream
    //   5: dup
    //   6: aload_2
    //   7: invokespecial 285	java/io/FileOutputStream:<init>	(Ljava/io/File;)V
    //   10: astore 5
    //   12: aload_1
    //   13: getstatic 291	android/graphics/Bitmap$CompressFormat:JPEG	Landroid/graphics/Bitmap$CompressFormat;
    //   16: bipush 100
    //   18: aload 5
    //   20: invokevirtual 297	android/graphics/Bitmap:compress	(Landroid/graphics/Bitmap$CompressFormat;ILjava/io/OutputStream;)Z
    //   23: pop
    //   24: aload 5
    //   26: ifnull +8 -> 34
    //   29: aload 5
    //   31: invokevirtual 300	java/io/FileOutputStream:close	()V
    //   34: getstatic 94	uuuuuu/xsxsxs:b00660066f0066f006600660066f	Ljava/lang/String;
    //   37: astore_1
    //   38: ldc 36
    //   40: ldc_w 302
    //   43: bipush 26
    //   45: sipush 198
    //   48: iconst_2
    //   49: invokestatic 88	xxxxxx/uxxxxx:bbbb0062b0062b0062b0062	(Ljava/lang/String;CCC)Ljava/lang/String;
    //   52: iconst_3
    //   53: anewarray 46	java/lang/Class
    //   56: dup
    //   57: iconst_0
    //   58: ldc 48
    //   60: aastore
    //   61: dup
    //   62: iconst_1
    //   63: getstatic 54	java/lang/Character:TYPE	Ljava/lang/Class;
    //   66: aastore
    //   67: dup
    //   68: iconst_2
    //   69: getstatic 54	java/lang/Character:TYPE	Ljava/lang/Class;
    //   72: aastore
    //   73: invokevirtual 58	java/lang/Class:getMethod	(Ljava/lang/String;[Ljava/lang/Class;)Ljava/lang/reflect/Method;
    //   76: astore_2
    //   77: aload_2
    //   78: aconst_null
    //   79: iconst_3
    //   80: anewarray 4	java/lang/Object
    //   83: dup
    //   84: iconst_0
    //   85: ldc_w 304
    //   88: aastore
    //   89: dup
    //   90: iconst_1
    //   91: sipush 144
    //   94: invokestatic 62	java/lang/Character:valueOf	(C)Ljava/lang/Character;
    //   97: aastore
    //   98: dup
    //   99: iconst_2
    //   100: iconst_0
    //   101: invokestatic 62	java/lang/Character:valueOf	(C)Ljava/lang/Character;
    //   104: aastore
    //   105: invokevirtual 68	java/lang/reflect/Method:invoke	(Ljava/lang/Object;[Ljava/lang/Object;)Ljava/lang/Object;
    //   108: astore_2
    //   109: aload_1
    //   110: aload_2
    //   111: checkcast 48	java/lang/String
    //   114: invokestatic 310	uuuuuu/rvvvrv:bqq0071q00710071q0071q0071	(Ljava/lang/String;Ljava/lang/String;)V
    //   117: return
    //   118: astore_2
    //   119: aload 5
    //   121: ifnull +12 -> 133
    //   124: aload_1
    //   125: ifnull +105 -> 230
    //   128: aload 5
    //   130: invokevirtual 300	java/io/FileOutputStream:close	()V
    //   133: aload_2
    //   134: athrow
    //   135: astore_1
    //   136: getstatic 94	uuuuuu/xsxsxs:b00660066f0066f006600660066f	Ljava/lang/String;
    //   139: astore_2
    //   140: ldc 36
    //   142: ldc_w 312
    //   145: sipush 170
    //   148: iconst_4
    //   149: iconst_3
    //   150: invokestatic 88	xxxxxx/uxxxxx:bbbb0062b0062b0062b0062	(Ljava/lang/String;CCC)Ljava/lang/String;
    //   153: iconst_3
    //   154: anewarray 46	java/lang/Class
    //   157: dup
    //   158: iconst_0
    //   159: ldc 48
    //   161: aastore
    //   162: dup
    //   163: iconst_1
    //   164: getstatic 54	java/lang/Character:TYPE	Ljava/lang/Class;
    //   167: aastore
    //   168: dup
    //   169: iconst_2
    //   170: getstatic 54	java/lang/Character:TYPE	Ljava/lang/Class;
    //   173: aastore
    //   174: invokevirtual 58	java/lang/Class:getMethod	(Ljava/lang/String;[Ljava/lang/Class;)Ljava/lang/reflect/Method;
    //   177: astore_3
    //   178: aload_3
    //   179: aconst_null
    //   180: iconst_3
    //   181: anewarray 4	java/lang/Object
    //   184: dup
    //   185: iconst_0
    //   186: ldc_w 314
    //   189: aastore
    //   190: dup
    //   191: iconst_1
    //   192: bipush 59
    //   194: invokestatic 62	java/lang/Character:valueOf	(C)Ljava/lang/Character;
    //   197: aastore
    //   198: dup
    //   199: iconst_2
    //   200: iconst_1
    //   201: invokestatic 62	java/lang/Character:valueOf	(C)Ljava/lang/Character;
    //   204: aastore
    //   205: invokevirtual 68	java/lang/reflect/Method:invoke	(Ljava/lang/Object;[Ljava/lang/Object;)Ljava/lang/Object;
    //   208: astore_3
    //   209: aload_2
    //   210: aload_3
    //   211: checkcast 48	java/lang/String
    //   214: aload_1
    //   215: invokestatic 318	uuuuuu/rvvvrv:b00710071qq00710071q0071q0071	(Ljava/lang/String;Ljava/lang/String;Ljava/lang/Throwable;)V
    //   218: goto -184 -> 34
    //   221: astore_3
    //   222: aload_1
    //   223: aload_3
    //   224: invokevirtual 322	java/lang/Throwable:addSuppressed	(Ljava/lang/Throwable;)V
    //   227: goto -94 -> 133
    //   230: aload 5
    //   232: invokevirtual 300	java/io/FileOutputStream:close	()V
    //   235: goto -102 -> 133
    //   238: astore_1
    //   239: aload_1
    //   240: invokevirtual 98	java/lang/reflect/InvocationTargetException:getCause	()Ljava/lang/Throwable;
    //   243: athrow
    //   244: astore_1
    //   245: aload_1
    //   246: invokevirtual 98	java/lang/reflect/InvocationTargetException:getCause	()Ljava/lang/Throwable;
    //   249: athrow
    //   250: astore_1
    //   251: aload_1
    //   252: athrow
    //   253: astore 4
    //   255: aload 4
    //   257: astore_2
    //   258: aload_3
    //   259: astore_1
    //   260: getstatic 70	uuuuuu/xsxsxs:bffff0066006600660066f	I
    //   263: getstatic 72	uuuuuu/xsxsxs:bf0066ff0066006600660066f	I
    //   266: iadd
    //   267: getstatic 70	uuuuuu/xsxsxs:bffff0066006600660066f	I
    //   270: imul
    //   271: getstatic 74	uuuuuu/xsxsxs:b00660066ff0066006600660066f	I
    //   274: irem
    //   275: getstatic 76	uuuuuu/xsxsxs:b0066fff0066006600660066f	I
    //   278: if_icmpeq -159 -> 119
    //   281: invokestatic 80	uuuuuu/xsxsxs:bk006B006B006Bk006Bkk006B006B	()I
    //   284: putstatic 70	uuuuuu/xsxsxs:bffff0066006600660066f	I
    //   287: invokestatic 80	uuuuuu/xsxsxs:bk006B006B006Bk006Bkk006B006B	()I
    //   290: putstatic 76	uuuuuu/xsxsxs:b0066fff0066006600660066f	I
    //   293: aload 4
    //   295: astore_2
    //   296: aload_3
    //   297: astore_1
    //   298: goto -179 -> 119
    // Local variable table:
    //   start	length	slot	name	signature
    //   0	301	0	this	xsxsxs
    //   0	301	1	paramBitmap	android.graphics.Bitmap
    //   0	301	2	paramFile	File
    //   1	210	3	localObject1	Object
    //   221	76	3	localThrowable	Throwable
    //   253	41	4	localObject2	Object
    //   10	221	5	localFileOutputStream	java.io.FileOutputStream
    // Exception table:
    //   from	to	target	type
    //   251	253	118	finally
    //   2	12	135	java/io/IOException
    //   29	34	135	java/io/IOException
    //   128	133	135	java/io/IOException
    //   133	135	135	java/io/IOException
    //   222	227	135	java/io/IOException
    //   230	235	135	java/io/IOException
    //   128	133	221	java/lang/Throwable
    //   77	109	238	java/lang/reflect/InvocationTargetException
    //   178	209	244	java/lang/reflect/InvocationTargetException
    //   12	24	250	java/lang/Throwable
    //   12	24	253	finally
  }
  
  public void bk006Bk006B006B006Bkk006B006B(Drawable paramDrawable, AppCompatActivity paramAppCompatActivity)
  {
    if (this.bf006600660066f006600660066f == null) {
      this.bf006600660066f006600660066f = b006B006Bkk006B006Bkk006B006B(paramAppCompatActivity);
    }
    Drawable localDrawable = this.bf006600660066f006600660066f;
    if ((bffff0066006600660066f + bf0066ff0066006600660066f) * bffff0066006600660066f % b00660066ff0066006600660066f != b0066fff0066006600660066f)
    {
      bffff0066006600660066f = 90;
      b0066fff0066006600660066f = bk006B006B006Bk006Bkk006B006B();
    }
    if ((bffff0066006600660066f + bf0066ff0066006600660066f) * bffff0066006600660066f % b00660066ff0066006600660066f != b0066fff0066006600660066f)
    {
      bffff0066006600660066f = bk006B006B006Bk006Bkk006B006B();
      b0066fff0066006600660066f = bk006B006B006Bk006Bkk006B006B();
    }
    b006B006Bk006Bk006Bkk006B006B(new Drawable[] { localDrawable, paramDrawable }, paramAppCompatActivity);
    this.bf006600660066f006600660066f = paramDrawable;
  }
  
  public int bk006Bkk006B006Bkk006B006B()
  {
    Object localObject = this.b0066006600660066f006600660066f;
    Method localMethod = SharedPreferencesHelper.class.getMethod(uxxxxx.bbbb0062b0062b0062b0062("\037\034*w)&& \035p\017\020\027\022\034\030\035\025\nm\021\004\t\006o\022\005", '×', 'o', '\000'), new Class[0]);
    try
    {
      localObject = localMethod.invoke(localObject, new Object[0]);
      if (!((String)localObject).isEmpty())
      {
        int i = R.string.background_image_custom;
        int j = bffff0066006600660066f;
        int k = bf0066ff0066006600660066f;
        int m = bffff0066006600660066f;
        int n = bffff0066006600660066f;
        switch (n * (bf0066ff0066006600660066f + n) % b00660066ff0066006600660066f)
        {
        default: 
          bffff0066006600660066f = bk006B006B006Bk006Bkk006B006B();
          b0066fff0066006600660066f = 53;
        }
        if ((j + k) * m % b00660066ff0066006600660066f != b0066fff0066006600660066f)
        {
          bffff0066006600660066f = bk006B006B006Bk006Bkk006B006B();
          b0066fff0066006600660066f = 28;
        }
        return i;
      }
    }
    catch (InvocationTargetException localInvocationTargetException)
    {
      throw localInvocationTargetException.getCause();
    }
    return BackgroundChangeEnum.values()[bkkkk006B006Bkk006B006B()].getStringResId();
  }
  
  /* Error */
  public android.graphics.Bitmap bkk006Bk006B006Bkk006B006B(Context paramContext, android.net.Uri paramUri, int paramInt1, int paramInt2)
  {
    // Byte code:
    //   0: getstatic 94	uuuuuu/xsxsxs:b00660066f0066f006600660066f	Ljava/lang/String;
    //   3: astore 7
    //   5: ldc 36
    //   7: ldc_w 345
    //   10: bipush 63
    //   12: iconst_0
    //   13: invokestatic 44	xxxxxx/uxxxxx:bb00620062bb0062b0062b0062	(Ljava/lang/String;CC)Ljava/lang/String;
    //   16: iconst_4
    //   17: anewarray 46	java/lang/Class
    //   20: dup
    //   21: iconst_0
    //   22: ldc 48
    //   24: aastore
    //   25: dup
    //   26: iconst_1
    //   27: getstatic 54	java/lang/Character:TYPE	Ljava/lang/Class;
    //   30: aastore
    //   31: dup
    //   32: iconst_2
    //   33: getstatic 54	java/lang/Character:TYPE	Ljava/lang/Class;
    //   36: aastore
    //   37: dup
    //   38: iconst_3
    //   39: getstatic 54	java/lang/Character:TYPE	Ljava/lang/Class;
    //   42: aastore
    //   43: invokevirtual 58	java/lang/Class:getMethod	(Ljava/lang/String;[Ljava/lang/Class;)Ljava/lang/reflect/Method;
    //   46: astore 8
    //   48: aload 8
    //   50: aconst_null
    //   51: iconst_4
    //   52: anewarray 4	java/lang/Object
    //   55: dup
    //   56: iconst_0
    //   57: ldc_w 347
    //   60: aastore
    //   61: dup
    //   62: iconst_1
    //   63: bipush 14
    //   65: invokestatic 62	java/lang/Character:valueOf	(C)Ljava/lang/Character;
    //   68: aastore
    //   69: dup
    //   70: iconst_2
    //   71: bipush 19
    //   73: invokestatic 62	java/lang/Character:valueOf	(C)Ljava/lang/Character;
    //   76: aastore
    //   77: dup
    //   78: iconst_3
    //   79: iconst_1
    //   80: invokestatic 62	java/lang/Character:valueOf	(C)Ljava/lang/Character;
    //   83: aastore
    //   84: invokevirtual 68	java/lang/reflect/Method:invoke	(Ljava/lang/Object;[Ljava/lang/Object;)Ljava/lang/Object;
    //   87: astore 8
    //   89: aload 7
    //   91: aload 8
    //   93: checkcast 48	java/lang/String
    //   96: invokestatic 310	uuuuuu/rvvvrv:bqq0071q00710071q0071q0071	(Ljava/lang/String;Ljava/lang/String;)V
    //   99: iload_3
    //   100: i2f
    //   101: fstore 5
    //   103: iload 4
    //   105: i2f
    //   106: fstore 6
    //   108: getstatic 70	uuuuuu/xsxsxs:bffff0066006600660066f	I
    //   111: getstatic 72	uuuuuu/xsxsxs:bf0066ff0066006600660066f	I
    //   114: iadd
    //   115: getstatic 70	uuuuuu/xsxsxs:bffff0066006600660066f	I
    //   118: imul
    //   119: getstatic 74	uuuuuu/xsxsxs:b00660066ff0066006600660066f	I
    //   122: irem
    //   123: getstatic 76	uuuuuu/xsxsxs:b0066fff0066006600660066f	I
    //   126: if_icmpeq +14 -> 140
    //   129: invokestatic 80	uuuuuu/xsxsxs:bk006B006B006Bk006Bkk006B006B	()I
    //   132: putstatic 70	uuuuuu/xsxsxs:bffff0066006600660066f	I
    //   135: bipush 43
    //   137: putstatic 76	uuuuuu/xsxsxs:b0066fff0066006600660066f	I
    //   140: aload_1
    //   141: aload_2
    //   142: fload 5
    //   144: fload 6
    //   146: iconst_1
    //   147: invokestatic 353	uuuuuu/hpppph:bww00770077ww0077w0077w	(Landroid/content/Context;Landroid/net/Uri;FFZ)Landroid/graphics/Bitmap;
    //   150: astore_2
    //   151: aload_1
    //   152: invokevirtual 216	android/content/Context:getFilesDir	()Ljava/io/File;
    //   155: astore 7
    //   157: new 218	java/lang/StringBuilder
    //   160: dup
    //   161: invokespecial 219	java/lang/StringBuilder:<init>	()V
    //   164: astore 8
    //   166: getstatic 70	uuuuuu/xsxsxs:bffff0066006600660066f	I
    //   169: getstatic 72	uuuuuu/xsxsxs:bf0066ff0066006600660066f	I
    //   172: iadd
    //   173: getstatic 70	uuuuuu/xsxsxs:bffff0066006600660066f	I
    //   176: imul
    //   177: getstatic 74	uuuuuu/xsxsxs:b00660066ff0066006600660066f	I
    //   180: irem
    //   181: getstatic 76	uuuuuu/xsxsxs:b0066fff0066006600660066f	I
    //   184: if_icmpeq +14 -> 198
    //   187: bipush 97
    //   189: putstatic 70	uuuuuu/xsxsxs:bffff0066006600660066f	I
    //   192: invokestatic 80	uuuuuu/xsxsxs:bk006B006B006Bk006Bkk006B006B	()I
    //   195: putstatic 76	uuuuuu/xsxsxs:b0066fff0066006600660066f	I
    //   198: aload 8
    //   200: aload 7
    //   202: invokevirtual 223	java/lang/StringBuilder:append	(Ljava/lang/Object;)Ljava/lang/StringBuilder;
    //   205: getstatic 228	java/io/File:separator	Ljava/lang/String;
    //   208: invokevirtual 231	java/lang/StringBuilder:append	(Ljava/lang/String;)Ljava/lang/StringBuilder;
    //   211: astore 7
    //   213: ldc 36
    //   215: ldc_w 355
    //   218: sipush 147
    //   221: bipush 26
    //   223: iconst_0
    //   224: invokestatic 88	xxxxxx/uxxxxx:bbbb0062b0062b0062b0062	(Ljava/lang/String;CCC)Ljava/lang/String;
    //   227: iconst_4
    //   228: anewarray 46	java/lang/Class
    //   231: dup
    //   232: iconst_0
    //   233: ldc 48
    //   235: aastore
    //   236: dup
    //   237: iconst_1
    //   238: getstatic 54	java/lang/Character:TYPE	Ljava/lang/Class;
    //   241: aastore
    //   242: dup
    //   243: iconst_2
    //   244: getstatic 54	java/lang/Character:TYPE	Ljava/lang/Class;
    //   247: aastore
    //   248: dup
    //   249: iconst_3
    //   250: getstatic 54	java/lang/Character:TYPE	Ljava/lang/Class;
    //   253: aastore
    //   254: invokevirtual 58	java/lang/Class:getMethod	(Ljava/lang/String;[Ljava/lang/Class;)Ljava/lang/reflect/Method;
    //   257: astore 8
    //   259: aload 8
    //   261: aconst_null
    //   262: iconst_4
    //   263: anewarray 4	java/lang/Object
    //   266: dup
    //   267: iconst_0
    //   268: ldc_w 357
    //   271: aastore
    //   272: dup
    //   273: iconst_1
    //   274: bipush 123
    //   276: invokestatic 62	java/lang/Character:valueOf	(C)Ljava/lang/Character;
    //   279: aastore
    //   280: dup
    //   281: iconst_2
    //   282: bipush 77
    //   284: invokestatic 62	java/lang/Character:valueOf	(C)Ljava/lang/Character;
    //   287: aastore
    //   288: dup
    //   289: iconst_3
    //   290: iconst_2
    //   291: invokestatic 62	java/lang/Character:valueOf	(C)Ljava/lang/Character;
    //   294: aastore
    //   295: invokevirtual 68	java/lang/reflect/Method:invoke	(Ljava/lang/Object;[Ljava/lang/Object;)Ljava/lang/Object;
    //   298: astore 8
    //   300: aload 8
    //   302: checkcast 48	java/lang/String
    //   305: astore 8
    //   307: aload_0
    //   308: aload 7
    //   310: aload 8
    //   312: invokevirtual 231	java/lang/StringBuilder:append	(Ljava/lang/String;)Ljava/lang/StringBuilder;
    //   315: invokevirtual 238	java/lang/StringBuilder:toString	()Ljava/lang/String;
    //   318: putfield 245	uuuuuu/xsxsxs:b0066f00660066f006600660066f	Ljava/lang/String;
    //   321: new 225	java/io/File
    //   324: dup
    //   325: aload_0
    //   326: getfield 245	uuuuuu/xsxsxs:b0066f00660066f006600660066f	Ljava/lang/String;
    //   329: invokespecial 243	java/io/File:<init>	(Ljava/lang/String;)V
    //   332: astore 8
    //   334: aload_2
    //   335: iload_3
    //   336: iload 4
    //   338: invokestatic 361	uuuuuu/hpppph:bw0077w0077ww0077w0077w	(Landroid/graphics/Bitmap;II)Landroid/graphics/Bitmap;
    //   341: iload 4
    //   343: invokestatic 365	uuuuuu/hpppph:b00770077ww0077w0077w0077w	(Landroid/graphics/Bitmap;I)Landroid/graphics/Bitmap;
    //   346: astore 7
    //   348: aload_0
    //   349: aload 7
    //   351: aload 8
    //   353: invokevirtual 255	uuuuuu/xsxsxs:bk006B006Bk006B006Bkk006B006B	(Landroid/graphics/Bitmap;Ljava/io/File;)V
    //   356: aload_0
    //   357: getfield 245	uuuuuu/xsxsxs:b0066f00660066f006600660066f	Ljava/lang/String;
    //   360: invokestatic 251	android/graphics/BitmapFactory:decodeFile	(Ljava/lang/String;)Landroid/graphics/Bitmap;
    //   363: astore 8
    //   365: new 367	android/graphics/drawable/BitmapDrawable
    //   368: dup
    //   369: aload_1
    //   370: invokevirtual 371	android/content/Context:getResources	()Landroid/content/res/Resources;
    //   373: aload 8
    //   375: invokespecial 374	android/graphics/drawable/BitmapDrawable:<init>	(Landroid/content/res/Resources;Landroid/graphics/Bitmap;)V
    //   378: bipush 17
    //   380: invokevirtual 377	android/graphics/drawable/BitmapDrawable:setGravity	(I)V
    //   383: aload_2
    //   384: invokevirtual 380	android/graphics/Bitmap:recycle	()V
    //   387: aload 7
    //   389: invokevirtual 380	android/graphics/Bitmap:recycle	()V
    //   392: aload 8
    //   394: areturn
    //   395: astore_1
    //   396: aload_1
    //   397: invokevirtual 98	java/lang/reflect/InvocationTargetException:getCause	()Ljava/lang/Throwable;
    //   400: athrow
    //   401: astore_1
    //   402: aload_1
    //   403: invokevirtual 98	java/lang/reflect/InvocationTargetException:getCause	()Ljava/lang/Throwable;
    //   406: athrow
    //   407: astore_1
    //   408: getstatic 94	uuuuuu/xsxsxs:b00660066f0066f006600660066f	Ljava/lang/String;
    //   411: astore_2
    //   412: ldc 36
    //   414: ldc_w 382
    //   417: sipush 141
    //   420: iconst_1
    //   421: invokestatic 44	xxxxxx/uxxxxx:bb00620062bb0062b0062b0062	(Ljava/lang/String;CC)Ljava/lang/String;
    //   424: iconst_3
    //   425: anewarray 46	java/lang/Class
    //   428: dup
    //   429: iconst_0
    //   430: ldc 48
    //   432: aastore
    //   433: dup
    //   434: iconst_1
    //   435: getstatic 54	java/lang/Character:TYPE	Ljava/lang/Class;
    //   438: aastore
    //   439: dup
    //   440: iconst_2
    //   441: getstatic 54	java/lang/Character:TYPE	Ljava/lang/Class;
    //   444: aastore
    //   445: invokevirtual 58	java/lang/Class:getMethod	(Ljava/lang/String;[Ljava/lang/Class;)Ljava/lang/reflect/Method;
    //   448: astore 7
    //   450: aload 7
    //   452: aconst_null
    //   453: iconst_3
    //   454: anewarray 4	java/lang/Object
    //   457: dup
    //   458: iconst_0
    //   459: ldc_w 384
    //   462: aastore
    //   463: dup
    //   464: iconst_1
    //   465: sipush 232
    //   468: invokestatic 62	java/lang/Character:valueOf	(C)Ljava/lang/Character;
    //   471: aastore
    //   472: dup
    //   473: iconst_2
    //   474: iconst_4
    //   475: invokestatic 62	java/lang/Character:valueOf	(C)Ljava/lang/Character;
    //   478: aastore
    //   479: invokevirtual 68	java/lang/reflect/Method:invoke	(Ljava/lang/Object;[Ljava/lang/Object;)Ljava/lang/Object;
    //   482: astore 7
    //   484: aload_2
    //   485: aload 7
    //   487: checkcast 48	java/lang/String
    //   490: aload_1
    //   491: invokestatic 318	uuuuuu/rvvvrv:b00710071qq00710071q0071q0071	(Ljava/lang/String;Ljava/lang/String;Ljava/lang/Throwable;)V
    //   494: aconst_null
    //   495: areturn
    //   496: astore_1
    //   497: aload_1
    //   498: invokevirtual 98	java/lang/reflect/InvocationTargetException:getCause	()Ljava/lang/Throwable;
    //   501: athrow
    // Local variable table:
    //   start	length	slot	name	signature
    //   0	502	0	this	xsxsxs
    //   0	502	1	paramContext	Context
    //   0	502	2	paramUri	android.net.Uri
    //   0	502	3	paramInt1	int
    //   0	502	4	paramInt2	int
    //   101	42	5	f1	float
    //   106	39	6	f2	float
    //   3	483	7	localObject1	Object
    //   46	347	8	localObject2	Object
    // Exception table:
    //   from	to	target	type
    //   48	89	395	java/lang/reflect/InvocationTargetException
    //   259	300	401	java/lang/reflect/InvocationTargetException
    //   140	166	407	java/io/IOException
    //   198	213	407	java/io/IOException
    //   259	300	407	java/io/IOException
    //   307	392	407	java/io/IOException
    //   402	407	407	java/io/IOException
    //   450	484	496	java/lang/reflect/InvocationTargetException
  }
  
  /* Error */
  public void bkkk006B006B006Bkk006B006B(Window paramWindow, android.content.res.Resources paramResources)
  {
    // Byte code:
    //   0: aload_0
    //   1: getfield 182	uuuuuu/xsxsxs:b0066006600660066f006600660066f	Lcom/db/pwcc/dbmobile/secure/preferences/SharedPreferencesHelper;
    //   4: astore 5
    //   6: ldc -72
    //   8: ldc_w 388
    //   11: sipush 232
    //   14: iconst_1
    //   15: invokestatic 44	xxxxxx/uxxxxx:bb00620062bb0062b0062b0062	(Ljava/lang/String;CC)Ljava/lang/String;
    //   18: iconst_0
    //   19: anewarray 46	java/lang/Class
    //   22: invokevirtual 58	java/lang/Class:getMethod	(Ljava/lang/String;[Ljava/lang/Class;)Ljava/lang/reflect/Method;
    //   25: astore 6
    //   27: aload 6
    //   29: aload 5
    //   31: iconst_0
    //   32: anewarray 4	java/lang/Object
    //   35: invokevirtual 68	java/lang/reflect/Method:invoke	(Ljava/lang/Object;[Ljava/lang/Object;)Ljava/lang/Object;
    //   38: astore 5
    //   40: aload 5
    //   42: checkcast 48	java/lang/String
    //   45: invokevirtual 190	java/lang/String:isEmpty	()Z
    //   48: ifeq +101 -> 149
    //   51: invokestatic 173	com/db/pwcc/dbmobile/foundation/utils/BackgroundChangeEnum:values	()[Lcom/db/pwcc/dbmobile/foundation/utils/BackgroundChangeEnum;
    //   54: astore_2
    //   55: aload_0
    //   56: invokevirtual 193	uuuuuu/xsxsxs:bkkkk006B006Bkk006B006B	()I
    //   59: istore_3
    //   60: getstatic 70	uuuuuu/xsxsxs:bffff0066006600660066f	I
    //   63: invokestatic 145	uuuuuu/xsxsxs:b006B006B006B006Bk006Bkk006B006B	()I
    //   66: iadd
    //   67: getstatic 70	uuuuuu/xsxsxs:bffff0066006600660066f	I
    //   70: imul
    //   71: getstatic 74	uuuuuu/xsxsxs:b00660066ff0066006600660066f	I
    //   74: irem
    //   75: getstatic 76	uuuuuu/xsxsxs:b0066fff0066006600660066f	I
    //   78: if_icmpeq +60 -> 138
    //   81: invokestatic 80	uuuuuu/xsxsxs:bk006B006B006Bk006Bkk006B006B	()I
    //   84: putstatic 70	uuuuuu/xsxsxs:bffff0066006600660066f	I
    //   87: invokestatic 80	uuuuuu/xsxsxs:bk006B006B006Bk006Bkk006B006B	()I
    //   90: putstatic 76	uuuuuu/xsxsxs:b0066fff0066006600660066f	I
    //   93: getstatic 70	uuuuuu/xsxsxs:bffff0066006600660066f	I
    //   96: istore 4
    //   98: iload 4
    //   100: getstatic 72	uuuuuu/xsxsxs:bf0066ff0066006600660066f	I
    //   103: iload 4
    //   105: iadd
    //   106: imul
    //   107: getstatic 74	uuuuuu/xsxsxs:b00660066ff0066006600660066f	I
    //   110: irem
    //   111: tableswitch	default:+17->128, 0:+27->138
    //   128: bipush 18
    //   130: putstatic 70	uuuuuu/xsxsxs:bffff0066006600660066f	I
    //   133: bipush 74
    //   135: putstatic 76	uuuuuu/xsxsxs:b0066fff0066006600660066f	I
    //   138: aload_1
    //   139: aload_2
    //   140: iload_3
    //   141: aaload
    //   142: invokevirtual 196	com/db/pwcc/dbmobile/foundation/utils/BackgroundChangeEnum:getDrawableResId	()I
    //   145: invokevirtual 391	android/view/Window:setBackgroundDrawableResource	(I)V
    //   148: return
    //   149: aload_0
    //   150: getfield 182	uuuuuu/xsxsxs:b0066006600660066f006600660066f	Lcom/db/pwcc/dbmobile/secure/preferences/SharedPreferencesHelper;
    //   153: astore 5
    //   155: ldc -72
    //   157: ldc_w 393
    //   160: bipush 117
    //   162: iconst_4
    //   163: invokestatic 44	xxxxxx/uxxxxx:bb00620062bb0062b0062b0062	(Ljava/lang/String;CC)Ljava/lang/String;
    //   166: iconst_0
    //   167: anewarray 46	java/lang/Class
    //   170: invokevirtual 58	java/lang/Class:getMethod	(Ljava/lang/String;[Ljava/lang/Class;)Ljava/lang/reflect/Method;
    //   173: astore 6
    //   175: aload 6
    //   177: aload 5
    //   179: iconst_0
    //   180: anewarray 4	java/lang/Object
    //   183: invokevirtual 68	java/lang/reflect/Method:invoke	(Ljava/lang/Object;[Ljava/lang/Object;)Ljava/lang/Object;
    //   186: astore 5
    //   188: new 367	android/graphics/drawable/BitmapDrawable
    //   191: dup
    //   192: aload_2
    //   193: aload 5
    //   195: checkcast 48	java/lang/String
    //   198: invokestatic 251	android/graphics/BitmapFactory:decodeFile	(Ljava/lang/String;)Landroid/graphics/Bitmap;
    //   201: invokespecial 374	android/graphics/drawable/BitmapDrawable:<init>	(Landroid/content/res/Resources;Landroid/graphics/Bitmap;)V
    //   204: astore_2
    //   205: aload_2
    //   206: bipush 17
    //   208: invokevirtual 377	android/graphics/drawable/BitmapDrawable:setGravity	(I)V
    //   211: aload_1
    //   212: aload_2
    //   213: invokevirtual 134	android/view/Window:setBackgroundDrawable	(Landroid/graphics/drawable/Drawable;)V
    //   216: return
    //   217: astore_1
    //   218: aload_1
    //   219: invokevirtual 98	java/lang/reflect/InvocationTargetException:getCause	()Ljava/lang/Throwable;
    //   222: athrow
    //   223: astore_1
    //   224: aload_1
    //   225: invokevirtual 98	java/lang/reflect/InvocationTargetException:getCause	()Ljava/lang/Throwable;
    //   228: athrow
    // Local variable table:
    //   start	length	slot	name	signature
    //   0	229	0	this	xsxsxs
    //   0	229	1	paramWindow	Window
    //   0	229	2	paramResources	android.content.res.Resources
    //   59	82	3	i	int
    //   96	11	4	j	int
    //   4	190	5	localObject	Object
    //   25	151	6	localMethod	Method
    // Exception table:
    //   from	to	target	type
    //   175	188	217	java/lang/reflect/InvocationTargetException
    //   27	40	223	java/lang/reflect/InvocationTargetException
  }
  
  public int bkkkk006B006Bkk006B006B()
  {
    Object localObject = this.b0066006600660066f006600660066f;
    Method localMethod = SharedPreferencesHelper.class.getMethod(uxxxxx.bb00620062bb0062b0062b0062(">;I\030882E;B\017-.50:6;3(\f/\"'$\007+  2", 'Ó', '\004'), new Class[0]);
    try
    {
      localObject = localMethod.invoke(localObject, new Object[0]);
      if (((Integer)localObject).intValue() >= 0)
      {
        localObject = this.b0066006600660066f006600660066f;
        localMethod = SharedPreferencesHelper.class.getMethod(uxxxxx.bbbb0062b0062b0062b0062("tqNnnh{qxEcdkfplqi^BeX]Z=aVVh", 'Ú', '\027', '\000'), new Class[0]);
      }
      int i;
      int j;
      return 0;
    }
    catch (InvocationTargetException localInvocationTargetException1)
    {
      for (;;)
      {
        try
        {
          localObject = localMethod.invoke(localObject, new Object[0]);
          if (((Integer)localObject).intValue() >= BackgroundChangeEnum.values().length) {
            break;
          }
          localObject = this.b0066006600660066f006600660066f;
          localMethod = SharedPreferencesHelper.class.getMethod(uxxxxx.bb00620062bb0062b0062b0062(")&4\003##\0350&-y\030\031 \033%!&\036\023v\032\r\022\017q\026\013\013\035", '', '\004'), new Class[0]);
        }
        catch (InvocationTargetException localInvocationTargetException2)
        {
          throw localInvocationTargetException2.getCause();
        }
        try
        {
          localObject = localMethod.invoke(localObject, new Object[0]);
          i = ((Integer)localObject).intValue();
          if ((bffff0066006600660066f + b006B006B006B006Bk006Bkk006B006B()) * bffff0066006600660066f % b00660066ff0066006600660066f != b0066fff0066006600660066f)
          {
            bffff0066006600660066f = 91;
            b0066fff0066006600660066f = 74;
            j = bk006B006B006Bk006Bkk006B006B();
            switch (j * (bf0066ff0066006600660066f + j) % b00660066ff0066006600660066f)
            {
            default: 
              bffff0066006600660066f = 62;
              b0066fff0066006600660066f = bk006B006B006Bk006Bkk006B006B();
            }
          }
          return i;
        }
        catch (InvocationTargetException localInvocationTargetException3)
        {
          throw localInvocationTargetException3.getCause();
        }
      }
      localInvocationTargetException1 = localInvocationTargetException1;
      throw localInvocationTargetException1.getCause();
    }
  }
}
