package uuuuuu;

import android.content.Context;
import android.content.res.Resources;
import android.util.DisplayMetrics;

public final class xsxxss
{
  private static final String b006600660066f00660066f0066f = xsxxss.class.getSimpleName();
  public static int b00660066f006600660066f0066f = 1;
  public static int b0066ff006600660066f0066f = 97;
  public static int bf0066f006600660066f0066f = 0;
  public static int bff0066006600660066f0066f = 2;
  private static float bfff006600660066f0066f = -1.0F;
  
  static
  {
    if ((b0066ff006600660066f0066f + b00660066f006600660066f0066f) * b0066ff006600660066f0066f % bff0066006600660066f0066f != bf0066f006600660066f0066f)
    {
      b0066ff006600660066f0066f = b006B006B006Bk006Bkkk006B006B();
      bf0066f006600660066f0066f = b006B006B006Bk006Bkkk006B006B();
      int i = b0066ff006600660066f0066f;
      switch (i * (b00660066f006600660066f0066f + i) % bff0066006600660066f0066f)
      {
      default: 
        b0066ff006600660066f0066f = b006B006B006Bk006Bkkk006B006B();
        bf0066f006600660066f0066f = 50;
      }
    }
  }
  
  private xsxxss() {}
  
  public static int b006B006B006Bk006Bkkk006B006B()
  {
    return 1;
  }
  
  public static int b006B006Bk006B006Bkkk006B006B(float paramFloat)
  {
    if ((b0066ff006600660066f0066f + b00660066f006600660066f0066f) * b0066ff006600660066f0066f % bff0066006600660066f0066f != bkkk006B006Bkkk006B006B())
    {
      b0066ff006600660066f0066f = b006B006B006Bk006Bkkk006B006B();
      bf0066f006600660066f0066f = 40;
    }
    if (bfff006600660066f0066f == -1.0F) {
      bk006Bk006B006Bkkk006B006B(yyyyyg.bpp0070ppp00700070pp());
    }
    float f = bfff006600660066f0066f;
    int i = b0066ff006600660066f0066f;
    switch (i * (b00660066f006600660066f0066f + i) % bff0066006600660066f0066f)
    {
    default: 
      b0066ff006600660066f0066f = b006B006B006Bk006Bkkk006B006B();
      bf0066f006600660066f0066f = b006B006B006Bk006Bkkk006B006B();
    }
    return (int)(f * paramFloat + 0.5F);
  }
  
  /* Error */
  public static float b006Bkk006B006Bkkk006B006B(Context paramContext, float paramFloat)
  {
    // Byte code:
    //   0: getstatic 30	uuuuuu/xsxxss:bfff006600660066f0066f	F
    //   3: fstore_2
    //   4: getstatic 32	uuuuuu/xsxxss:b0066ff006600660066f0066f	I
    //   7: getstatic 34	uuuuuu/xsxxss:b00660066f006600660066f0066f	I
    //   10: iadd
    //   11: getstatic 32	uuuuuu/xsxxss:b0066ff006600660066f0066f	I
    //   14: imul
    //   15: getstatic 36	uuuuuu/xsxxss:bff0066006600660066f0066f	I
    //   18: irem
    //   19: getstatic 38	uuuuuu/xsxxss:bf0066f006600660066f0066f	I
    //   22: if_icmpeq +13 -> 35
    //   25: iconst_2
    //   26: putstatic 32	uuuuuu/xsxxss:b0066ff006600660066f0066f	I
    //   29: invokestatic 42	uuuuuu/xsxxss:b006B006B006Bk006Bkkk006B006B	()I
    //   32: putstatic 38	uuuuuu/xsxxss:bf0066f006600660066f0066f	I
    //   35: fload_2
    //   36: ldc 28
    //   38: fcmpl
    //   39: ifne +7 -> 46
    //   42: aload_0
    //   43: invokestatic 61	uuuuuu/xsxxss:bk006Bk006B006Bkkk006B006B	(Landroid/content/Context;)V
    //   46: getstatic 27	uuuuuu/xsxxss:b006600660066f00660066f0066f	Ljava/lang/String;
    //   49: astore_0
    //   50: new 68	java/lang/StringBuilder
    //   53: dup
    //   54: invokespecial 69	java/lang/StringBuilder:<init>	()V
    //   57: astore_3
    //   58: ldc 71
    //   60: ldc 73
    //   62: sipush 146
    //   65: iconst_3
    //   66: invokestatic 79	xxxxxx/uxxxxx:bb00620062bb0062b0062b0062	(Ljava/lang/String;CC)Ljava/lang/String;
    //   69: iconst_3
    //   70: anewarray 21	java/lang/Class
    //   73: dup
    //   74: iconst_0
    //   75: ldc 81
    //   77: aastore
    //   78: dup
    //   79: iconst_1
    //   80: getstatic 87	java/lang/Character:TYPE	Ljava/lang/Class;
    //   83: aastore
    //   84: dup
    //   85: iconst_2
    //   86: getstatic 87	java/lang/Character:TYPE	Ljava/lang/Class;
    //   89: aastore
    //   90: invokevirtual 91	java/lang/Class:getMethod	(Ljava/lang/String;[Ljava/lang/Class;)Ljava/lang/reflect/Method;
    //   93: astore 4
    //   95: aload 4
    //   97: aconst_null
    //   98: iconst_3
    //   99: anewarray 4	java/lang/Object
    //   102: dup
    //   103: iconst_0
    //   104: ldc 93
    //   106: aastore
    //   107: dup
    //   108: iconst_1
    //   109: bipush 106
    //   111: invokestatic 97	java/lang/Character:valueOf	(C)Ljava/lang/Character;
    //   114: aastore
    //   115: dup
    //   116: iconst_2
    //   117: iconst_3
    //   118: invokestatic 97	java/lang/Character:valueOf	(C)Ljava/lang/Character;
    //   121: aastore
    //   122: invokevirtual 103	java/lang/reflect/Method:invoke	(Ljava/lang/Object;[Ljava/lang/Object;)Ljava/lang/Object;
    //   125: astore 4
    //   127: aload 4
    //   129: checkcast 81	java/lang/String
    //   132: astore 4
    //   134: getstatic 32	uuuuuu/xsxxss:b0066ff006600660066f0066f	I
    //   137: getstatic 34	uuuuuu/xsxxss:b00660066f006600660066f0066f	I
    //   140: iadd
    //   141: getstatic 32	uuuuuu/xsxxss:b0066ff006600660066f0066f	I
    //   144: imul
    //   145: getstatic 36	uuuuuu/xsxxss:bff0066006600660066f0066f	I
    //   148: irem
    //   149: getstatic 38	uuuuuu/xsxxss:bf0066f006600660066f0066f	I
    //   152: if_icmpeq +14 -> 166
    //   155: invokestatic 42	uuuuuu/xsxxss:b006B006B006Bk006Bkkk006B006B	()I
    //   158: putstatic 32	uuuuuu/xsxxss:b0066ff006600660066f0066f	I
    //   161: bipush 39
    //   163: putstatic 38	uuuuuu/xsxxss:bf0066f006600660066f0066f	I
    //   166: aload_3
    //   167: aload 4
    //   169: invokevirtual 107	java/lang/StringBuilder:append	(Ljava/lang/String;)Ljava/lang/StringBuilder;
    //   172: getstatic 30	uuuuuu/xsxxss:bfff006600660066f0066f	F
    //   175: invokevirtual 110	java/lang/StringBuilder:append	(F)Ljava/lang/StringBuilder;
    //   178: astore_3
    //   179: ldc 71
    //   181: ldc 112
    //   183: bipush 87
    //   185: iconst_2
    //   186: invokestatic 79	xxxxxx/uxxxxx:bb00620062bb0062b0062b0062	(Ljava/lang/String;CC)Ljava/lang/String;
    //   189: iconst_4
    //   190: anewarray 21	java/lang/Class
    //   193: dup
    //   194: iconst_0
    //   195: ldc 81
    //   197: aastore
    //   198: dup
    //   199: iconst_1
    //   200: getstatic 87	java/lang/Character:TYPE	Ljava/lang/Class;
    //   203: aastore
    //   204: dup
    //   205: iconst_2
    //   206: getstatic 87	java/lang/Character:TYPE	Ljava/lang/Class;
    //   209: aastore
    //   210: dup
    //   211: iconst_3
    //   212: getstatic 87	java/lang/Character:TYPE	Ljava/lang/Class;
    //   215: aastore
    //   216: invokevirtual 91	java/lang/Class:getMethod	(Ljava/lang/String;[Ljava/lang/Class;)Ljava/lang/reflect/Method;
    //   219: astore 4
    //   221: aload 4
    //   223: aconst_null
    //   224: iconst_4
    //   225: anewarray 4	java/lang/Object
    //   228: dup
    //   229: iconst_0
    //   230: ldc 114
    //   232: aastore
    //   233: dup
    //   234: iconst_1
    //   235: bipush 23
    //   237: invokestatic 97	java/lang/Character:valueOf	(C)Ljava/lang/Character;
    //   240: aastore
    //   241: dup
    //   242: iconst_2
    //   243: bipush 26
    //   245: invokestatic 97	java/lang/Character:valueOf	(C)Ljava/lang/Character;
    //   248: aastore
    //   249: dup
    //   250: iconst_3
    //   251: iconst_3
    //   252: invokestatic 97	java/lang/Character:valueOf	(C)Ljava/lang/Character;
    //   255: aastore
    //   256: invokevirtual 103	java/lang/reflect/Method:invoke	(Ljava/lang/Object;[Ljava/lang/Object;)Ljava/lang/Object;
    //   259: astore 4
    //   261: aload_3
    //   262: aload 4
    //   264: checkcast 81	java/lang/String
    //   267: invokevirtual 107	java/lang/StringBuilder:append	(Ljava/lang/String;)Ljava/lang/StringBuilder;
    //   270: fload_1
    //   271: invokevirtual 110	java/lang/StringBuilder:append	(F)Ljava/lang/StringBuilder;
    //   274: astore_3
    //   275: ldc 71
    //   277: ldc 116
    //   279: sipush 164
    //   282: sipush 239
    //   285: iconst_0
    //   286: invokestatic 120	xxxxxx/uxxxxx:bbbb0062b0062b0062b0062	(Ljava/lang/String;CCC)Ljava/lang/String;
    //   289: iconst_3
    //   290: anewarray 21	java/lang/Class
    //   293: dup
    //   294: iconst_0
    //   295: ldc 81
    //   297: aastore
    //   298: dup
    //   299: iconst_1
    //   300: getstatic 87	java/lang/Character:TYPE	Ljava/lang/Class;
    //   303: aastore
    //   304: dup
    //   305: iconst_2
    //   306: getstatic 87	java/lang/Character:TYPE	Ljava/lang/Class;
    //   309: aastore
    //   310: invokevirtual 91	java/lang/Class:getMethod	(Ljava/lang/String;[Ljava/lang/Class;)Ljava/lang/reflect/Method;
    //   313: astore 4
    //   315: aload 4
    //   317: aconst_null
    //   318: iconst_3
    //   319: anewarray 4	java/lang/Object
    //   322: dup
    //   323: iconst_0
    //   324: ldc 122
    //   326: aastore
    //   327: dup
    //   328: iconst_1
    //   329: bipush 60
    //   331: invokestatic 97	java/lang/Character:valueOf	(C)Ljava/lang/Character;
    //   334: aastore
    //   335: dup
    //   336: iconst_2
    //   337: iconst_3
    //   338: invokestatic 97	java/lang/Character:valueOf	(C)Ljava/lang/Character;
    //   341: aastore
    //   342: invokevirtual 103	java/lang/reflect/Method:invoke	(Ljava/lang/Object;[Ljava/lang/Object;)Ljava/lang/Object;
    //   345: astore 4
    //   347: aload_0
    //   348: aload_3
    //   349: aload 4
    //   351: checkcast 81	java/lang/String
    //   354: invokevirtual 107	java/lang/StringBuilder:append	(Ljava/lang/String;)Ljava/lang/StringBuilder;
    //   357: getstatic 30	uuuuuu/xsxxss:bfff006600660066f0066f	F
    //   360: fload_1
    //   361: fmul
    //   362: ldc 62
    //   364: fadd
    //   365: invokevirtual 110	java/lang/StringBuilder:append	(F)Ljava/lang/StringBuilder;
    //   368: invokevirtual 125	java/lang/StringBuilder:toString	()Ljava/lang/String;
    //   371: invokestatic 131	uuuuuu/rvvvrv:bqq0071q00710071q0071q0071	(Ljava/lang/String;Ljava/lang/String;)V
    //   374: getstatic 30	uuuuuu/xsxxss:bfff006600660066f0066f	F
    //   377: fload_1
    //   378: fmul
    //   379: ldc 62
    //   381: fadd
    //   382: freturn
    //   383: astore_0
    //   384: aload_0
    //   385: invokevirtual 135	java/lang/reflect/InvocationTargetException:getCause	()Ljava/lang/Throwable;
    //   388: athrow
    //   389: astore_0
    //   390: aload_0
    //   391: invokevirtual 135	java/lang/reflect/InvocationTargetException:getCause	()Ljava/lang/Throwable;
    //   394: athrow
    //   395: astore_0
    //   396: aload_0
    //   397: invokevirtual 135	java/lang/reflect/InvocationTargetException:getCause	()Ljava/lang/Throwable;
    //   400: athrow
    // Local variable table:
    //   start	length	slot	name	signature
    //   0	401	0	paramContext	Context
    //   0	401	1	paramFloat	float
    //   3	33	2	f	float
    //   57	292	3	localStringBuilder	StringBuilder
    //   93	257	4	localObject	Object
    // Exception table:
    //   from	to	target	type
    //   95	127	383	java/lang/reflect/InvocationTargetException
    //   221	261	389	java/lang/reflect/InvocationTargetException
    //   315	347	395	java/lang/reflect/InvocationTargetException
  }
  
  public static void bk006Bk006B006Bkkk006B006B(Context paramContext)
  {
    if (paramContext != null)
    {
      paramContext = paramContext.getResources().getDisplayMetrics();
      int i = b0066ff006600660066f0066f;
      switch (i * (b00660066f006600660066f0066f + i) % bff0066006600660066f0066f)
      {
      default: 
        b0066ff006600660066f0066f = 19;
        bf0066f006600660066f0066f = 43;
      }
      bfff006600660066f0066f = paramContext.density;
      i = b0066ff006600660066f0066f;
      switch (i * (b00660066f006600660066f0066f + i) % bff0066006600660066f0066f)
      {
      default: 
        b0066ff006600660066f0066f = b006B006B006Bk006Bkkk006B006B();
        bf0066f006600660066f0066f = b006B006B006Bk006Bkkk006B006B();
      }
      return;
    }
    bfff006600660066f0066f = 1.0F;
  }
  
  public static int bkkk006B006Bkkk006B006B()
  {
    return 0;
  }
}
