package uuuuuu;

public class xsxxxx
{
  public static int b00660066f006600660066f00660066 = 0;
  public static int b0066ff006600660066f00660066 = 29;
  public static int bf0066f006600660066f00660066 = 2;
  public static int bff0066006600660066f00660066 = 1;
  private final String bfff006600660066f00660066 = xsxxxx.class.getName();
  
  public xsxxxx() {}
  
  public static int b007100710071qqqqqqq()
  {
    return 1;
  }
  
  public static int bq00710071qqqqqqq()
  {
    return 86;
  }
  
  /* Error */
  public java.util.List<String> bqqq0071qqqqqq(java.util.List<String> paramList, onooon.nnooon paramNnooon)
  {
    // Byte code:
    //   0: invokestatic 43	java/util/Calendar:getInstance	()Ljava/util/Calendar;
    //   3: astore 5
    //   5: aload_2
    //   6: invokevirtual 48	uuuuuu/onooon$nnooon:bkk006Bk006Bk006Bkk006B	()I
    //   9: istore_3
    //   10: getstatic 50	uuuuuu/xsxxxx:b0066ff006600660066f00660066	I
    //   13: istore 4
    //   15: iload 4
    //   17: invokestatic 52	uuuuuu/xsxxxx:b007100710071qqqqqqq	()I
    //   20: iload 4
    //   22: iadd
    //   23: imul
    //   24: getstatic 54	uuuuuu/xsxxxx:bf0066f006600660066f00660066	I
    //   27: irem
    //   28: tableswitch	default:+20->48, 0:+31->59
    //   48: bipush 98
    //   50: putstatic 50	uuuuuu/xsxxxx:b0066ff006600660066f00660066	I
    //   53: invokestatic 56	uuuuuu/xsxxxx:bq00710071qqqqqqq	()I
    //   56: putstatic 54	uuuuuu/xsxxxx:bf0066f006600660066f00660066	I
    //   59: aload 5
    //   61: bipush 6
    //   63: iload_3
    //   64: ineg
    //   65: iconst_1
    //   66: isub
    //   67: invokevirtual 60	java/util/Calendar:add	(II)V
    //   70: invokestatic 43	java/util/Calendar:getInstance	()Ljava/util/Calendar;
    //   73: astore_2
    //   74: ldc 62
    //   76: ldc 64
    //   78: sipush 249
    //   81: iconst_2
    //   82: invokestatic 70	xxxxxx/uxxxxx:bb00620062bb0062b0062b0062	(Ljava/lang/String;CC)Ljava/lang/String;
    //   85: iconst_3
    //   86: anewarray 21	java/lang/Class
    //   89: dup
    //   90: iconst_0
    //   91: ldc 72
    //   93: aastore
    //   94: dup
    //   95: iconst_1
    //   96: getstatic 78	java/lang/Character:TYPE	Ljava/lang/Class;
    //   99: aastore
    //   100: dup
    //   101: iconst_2
    //   102: getstatic 78	java/lang/Character:TYPE	Ljava/lang/Class;
    //   105: aastore
    //   106: invokevirtual 82	java/lang/Class:getMethod	(Ljava/lang/String;[Ljava/lang/Class;)Ljava/lang/reflect/Method;
    //   109: astore 6
    //   111: aload 6
    //   113: aconst_null
    //   114: iconst_3
    //   115: anewarray 4	java/lang/Object
    //   118: dup
    //   119: iconst_0
    //   120: ldc 84
    //   122: aastore
    //   123: dup
    //   124: iconst_1
    //   125: sipush 206
    //   128: invokestatic 88	java/lang/Character:valueOf	(C)Ljava/lang/Character;
    //   131: aastore
    //   132: dup
    //   133: iconst_2
    //   134: iconst_3
    //   135: invokestatic 88	java/lang/Character:valueOf	(C)Ljava/lang/Character;
    //   138: aastore
    //   139: invokevirtual 94	java/lang/reflect/Method:invoke	(Ljava/lang/Object;[Ljava/lang/Object;)Ljava/lang/Object;
    //   142: astore 6
    //   144: aload_2
    //   145: aload 6
    //   147: checkcast 72	java/lang/String
    //   150: invokestatic 100	java/util/TimeZone:getTimeZone	(Ljava/lang/String;)Ljava/util/TimeZone;
    //   153: invokevirtual 104	java/util/Calendar:setTimeZone	(Ljava/util/TimeZone;)V
    //   156: aload_2
    //   157: bipush 11
    //   159: iconst_0
    //   160: invokevirtual 107	java/util/Calendar:set	(II)V
    //   163: aload_2
    //   164: bipush 12
    //   166: iconst_0
    //   167: invokevirtual 107	java/util/Calendar:set	(II)V
    //   170: aload_2
    //   171: bipush 13
    //   173: iconst_0
    //   174: invokevirtual 107	java/util/Calendar:set	(II)V
    //   177: new 109	java/util/LinkedList
    //   180: dup
    //   181: invokespecial 110	java/util/LinkedList:<init>	()V
    //   184: astore 6
    //   186: ldc 62
    //   188: ldc 112
    //   190: sipush 160
    //   193: sipush 161
    //   196: iconst_1
    //   197: invokestatic 116	xxxxxx/uxxxxx:bbbb0062b0062b0062b0062	(Ljava/lang/String;CCC)Ljava/lang/String;
    //   200: iconst_3
    //   201: anewarray 21	java/lang/Class
    //   204: dup
    //   205: iconst_0
    //   206: ldc 72
    //   208: aastore
    //   209: dup
    //   210: iconst_1
    //   211: getstatic 78	java/lang/Character:TYPE	Ljava/lang/Class;
    //   214: aastore
    //   215: dup
    //   216: iconst_2
    //   217: getstatic 78	java/lang/Character:TYPE	Ljava/lang/Class;
    //   220: aastore
    //   221: invokevirtual 82	java/lang/Class:getMethod	(Ljava/lang/String;[Ljava/lang/Class;)Ljava/lang/reflect/Method;
    //   224: astore 7
    //   226: aload 7
    //   228: aconst_null
    //   229: iconst_3
    //   230: anewarray 4	java/lang/Object
    //   233: dup
    //   234: iconst_0
    //   235: ldc 118
    //   237: aastore
    //   238: dup
    //   239: iconst_1
    //   240: bipush 101
    //   242: invokestatic 88	java/lang/Character:valueOf	(C)Ljava/lang/Character;
    //   245: aastore
    //   246: dup
    //   247: iconst_2
    //   248: iconst_4
    //   249: invokestatic 88	java/lang/Character:valueOf	(C)Ljava/lang/Character;
    //   252: aastore
    //   253: invokevirtual 94	java/lang/reflect/Method:invoke	(Ljava/lang/Object;[Ljava/lang/Object;)Ljava/lang/Object;
    //   256: astore 7
    //   258: aload 7
    //   260: checkcast 72	java/lang/String
    //   263: astore 7
    //   265: getstatic 124	java/util/Locale:GERMANY	Ljava/util/Locale;
    //   268: astore 8
    //   270: getstatic 50	uuuuuu/xsxxxx:b0066ff006600660066f00660066	I
    //   273: getstatic 126	uuuuuu/xsxxxx:bff0066006600660066f00660066	I
    //   276: iadd
    //   277: getstatic 50	uuuuuu/xsxxxx:b0066ff006600660066f00660066	I
    //   280: imul
    //   281: getstatic 54	uuuuuu/xsxxxx:bf0066f006600660066f00660066	I
    //   284: irem
    //   285: getstatic 128	uuuuuu/xsxxxx:b00660066f006600660066f00660066	I
    //   288: if_icmpeq +14 -> 302
    //   291: invokestatic 56	uuuuuu/xsxxxx:bq00710071qqqqqqq	()I
    //   294: putstatic 50	uuuuuu/xsxxxx:b0066ff006600660066f00660066	I
    //   297: bipush 78
    //   299: putstatic 128	uuuuuu/xsxxxx:b00660066f006600660066f00660066	I
    //   302: new 130	java/text/SimpleDateFormat
    //   305: dup
    //   306: aload 7
    //   308: aload 8
    //   310: invokespecial 133	java/text/SimpleDateFormat:<init>	(Ljava/lang/String;Ljava/util/Locale;)V
    //   313: astore 7
    //   315: aload_1
    //   316: invokeinterface 139 1 0
    //   321: astore_1
    //   322: aload_1
    //   323: invokeinterface 145 1 0
    //   328: ifeq +178 -> 506
    //   331: aload_1
    //   332: invokeinterface 149 1 0
    //   337: checkcast 72	java/lang/String
    //   340: astore 8
    //   342: aload_2
    //   343: aload 7
    //   345: aload 8
    //   347: invokevirtual 153	java/text/SimpleDateFormat:parse	(Ljava/lang/String;)Ljava/util/Date;
    //   350: invokevirtual 157	java/util/Calendar:setTime	(Ljava/util/Date;)V
    //   353: aload 5
    //   355: aload_2
    //   356: invokevirtual 161	java/util/Calendar:before	(Ljava/lang/Object;)Z
    //   359: ifeq -37 -> 322
    //   362: aload 6
    //   364: aload 8
    //   366: invokevirtual 163	java/util/LinkedList:add	(Ljava/lang/Object;)Z
    //   369: pop
    //   370: goto -48 -> 322
    //   373: astore 8
    //   375: aload_0
    //   376: getfield 27	uuuuuu/xsxxxx:bfff006600660066f00660066	Ljava/lang/String;
    //   379: astore 9
    //   381: new 165	java/lang/StringBuilder
    //   384: dup
    //   385: invokespecial 166	java/lang/StringBuilder:<init>	()V
    //   388: astore 10
    //   390: ldc 62
    //   392: ldc -88
    //   394: sipush 250
    //   397: iconst_2
    //   398: invokestatic 70	xxxxxx/uxxxxx:bb00620062bb0062b0062b0062	(Ljava/lang/String;CC)Ljava/lang/String;
    //   401: iconst_3
    //   402: anewarray 21	java/lang/Class
    //   405: dup
    //   406: iconst_0
    //   407: ldc 72
    //   409: aastore
    //   410: dup
    //   411: iconst_1
    //   412: getstatic 78	java/lang/Character:TYPE	Ljava/lang/Class;
    //   415: aastore
    //   416: dup
    //   417: iconst_2
    //   418: getstatic 78	java/lang/Character:TYPE	Ljava/lang/Class;
    //   421: aastore
    //   422: invokevirtual 82	java/lang/Class:getMethod	(Ljava/lang/String;[Ljava/lang/Class;)Ljava/lang/reflect/Method;
    //   425: astore 11
    //   427: aload 11
    //   429: aconst_null
    //   430: iconst_3
    //   431: anewarray 4	java/lang/Object
    //   434: dup
    //   435: iconst_0
    //   436: ldc -86
    //   438: aastore
    //   439: dup
    //   440: iconst_1
    //   441: bipush 72
    //   443: invokestatic 88	java/lang/Character:valueOf	(C)Ljava/lang/Character;
    //   446: aastore
    //   447: dup
    //   448: iconst_2
    //   449: iconst_0
    //   450: invokestatic 88	java/lang/Character:valueOf	(C)Ljava/lang/Character;
    //   453: aastore
    //   454: invokevirtual 94	java/lang/reflect/Method:invoke	(Ljava/lang/Object;[Ljava/lang/Object;)Ljava/lang/Object;
    //   457: astore 11
    //   459: aload 9
    //   461: aload 10
    //   463: aload 11
    //   465: checkcast 72	java/lang/String
    //   468: invokevirtual 174	java/lang/StringBuilder:append	(Ljava/lang/String;)Ljava/lang/StringBuilder;
    //   471: aload 8
    //   473: invokevirtual 177	java/text/ParseException:getMessage	()Ljava/lang/String;
    //   476: invokevirtual 174	java/lang/StringBuilder:append	(Ljava/lang/String;)Ljava/lang/StringBuilder;
    //   479: invokevirtual 180	java/lang/StringBuilder:toString	()Ljava/lang/String;
    //   482: invokestatic 186	uuuuuu/rvvvrv:b0071qq007100710071q0071q0071	(Ljava/lang/String;Ljava/lang/String;)V
    //   485: goto -163 -> 322
    //   488: astore_1
    //   489: aload_1
    //   490: invokevirtual 190	java/lang/reflect/InvocationTargetException:getCause	()Ljava/lang/Throwable;
    //   493: athrow
    //   494: astore_1
    //   495: aload_1
    //   496: invokevirtual 190	java/lang/reflect/InvocationTargetException:getCause	()Ljava/lang/Throwable;
    //   499: athrow
    //   500: astore_1
    //   501: aload_1
    //   502: invokevirtual 190	java/lang/reflect/InvocationTargetException:getCause	()Ljava/lang/Throwable;
    //   505: athrow
    //   506: aload 6
    //   508: areturn
    // Local variable table:
    //   start	length	slot	name	signature
    //   0	509	0	this	xsxxxx
    //   0	509	1	paramList	java.util.List<String>
    //   0	509	2	paramNnooon	onooon.nnooon
    //   9	55	3	i	int
    //   13	11	4	j	int
    //   3	351	5	localCalendar	java.util.Calendar
    //   109	398	6	localObject1	Object
    //   224	120	7	localObject2	Object
    //   268	97	8	localObject3	Object
    //   373	99	8	localParseException	java.text.ParseException
    //   379	81	9	str	String
    //   388	74	10	localStringBuilder	StringBuilder
    //   425	39	11	localObject4	Object
    // Exception table:
    //   from	to	target	type
    //   342	370	373	java/text/ParseException
    //   427	459	488	java/lang/reflect/InvocationTargetException
    //   226	258	494	java/lang/reflect/InvocationTargetException
    //   111	144	500	java/lang/reflect/InvocationTargetException
  }
}
