package uuuuuu;

public class xsxxsx
{
  public static int b006600660066ff00660066f0066 = 26;
  public static int b0066ff0066f00660066f0066 = 2;
  private static final String bf00660066ff00660066f0066 = xsxxsx.class.getSimpleName();
  public static int bf0066f0066f00660066f0066 = 0;
  public static int bfff0066f00660066f0066 = 1;
  
  static
  {
    int i = b006600660066ff00660066f0066;
    switch (i * (bfff0066f00660066f0066 + i) % b0066ff0066f00660066f0066)
    {
    default: 
      b006600660066ff00660066f0066 = b006B006B006Bk006B006Bk006B006B006B();
      bfff0066f00660066f0066 = b006B006B006Bk006B006Bk006B006B006B();
      if ((b006600660066ff00660066f0066 + bkkk006B006B006Bk006B006B006B()) * b006600660066ff00660066f0066 % b0066ff0066f00660066f0066 != bf0066f0066f00660066f0066)
      {
        b006600660066ff00660066f0066 = 34;
        bf0066f0066f00660066f0066 = 66;
      }
      break;
    }
  }
  
  public xsxxsx() {}
  
  public static int b006B006B006Bk006B006Bk006B006B006B()
  {
    return 78;
  }
  
  /* Error */
  public static java.util.List<com.db.pwcc.dbmobile.model.banking.CashAccountTransaction> b006Bkk006B006B006Bk006B006B006B(java.util.List<com.db.pwcc.dbmobile.model.banking.CashAccountTransaction> paramList, onooon.nnooon paramNnooon, java.util.Date paramDate)
  {
    // Byte code:
    //   0: invokestatic 56	java/util/Calendar:getInstance	()Ljava/util/Calendar;
    //   3: astore_3
    //   4: aload_3
    //   5: aload_2
    //   6: invokevirtual 60	java/util/Calendar:setTime	(Ljava/util/Date;)V
    //   9: aload_3
    //   10: bipush 6
    //   12: aload_1
    //   13: invokevirtual 65	uuuuuu/onooon$nnooon:bkk006Bk006Bk006Bkk006B	()I
    //   16: ineg
    //   17: iconst_1
    //   18: isub
    //   19: invokevirtual 69	java/util/Calendar:add	(II)V
    //   22: new 71	java/lang/StringBuilder
    //   25: dup
    //   26: invokespecial 72	java/lang/StringBuilder:<init>	()V
    //   29: aload_3
    //   30: invokevirtual 76	java/util/Calendar:getTime	()Ljava/util/Date;
    //   33: invokevirtual 80	java/lang/StringBuilder:append	(Ljava/lang/Object;)Ljava/lang/StringBuilder;
    //   36: ldc 82
    //   38: invokevirtual 85	java/lang/StringBuilder:append	(Ljava/lang/String;)Ljava/lang/StringBuilder;
    //   41: invokevirtual 88	java/lang/StringBuilder:toString	()Ljava/lang/String;
    //   44: astore_1
    //   45: getstatic 40	uuuuuu/xsxxsx:bf00660066ff00660066f0066	Ljava/lang/String;
    //   48: astore_2
    //   49: new 71	java/lang/StringBuilder
    //   52: dup
    //   53: invokespecial 72	java/lang/StringBuilder:<init>	()V
    //   56: astore 4
    //   58: ldc 90
    //   60: ldc 92
    //   62: sipush 189
    //   65: iconst_4
    //   66: invokestatic 98	xxxxxx/uxxxxx:bb00620062bb0062b0062b0062	(Ljava/lang/String;CC)Ljava/lang/String;
    //   69: iconst_3
    //   70: anewarray 34	java/lang/Class
    //   73: dup
    //   74: iconst_0
    //   75: ldc 100
    //   77: aastore
    //   78: dup
    //   79: iconst_1
    //   80: getstatic 106	java/lang/Character:TYPE	Ljava/lang/Class;
    //   83: aastore
    //   84: dup
    //   85: iconst_2
    //   86: getstatic 106	java/lang/Character:TYPE	Ljava/lang/Class;
    //   89: aastore
    //   90: invokevirtual 110	java/lang/Class:getMethod	(Ljava/lang/String;[Ljava/lang/Class;)Ljava/lang/reflect/Method;
    //   93: astore 5
    //   95: aload 5
    //   97: aconst_null
    //   98: iconst_3
    //   99: anewarray 4	java/lang/Object
    //   102: dup
    //   103: iconst_0
    //   104: ldc 112
    //   106: aastore
    //   107: dup
    //   108: iconst_1
    //   109: sipush 224
    //   112: invokestatic 116	java/lang/Character:valueOf	(C)Ljava/lang/Character;
    //   115: aastore
    //   116: dup
    //   117: iconst_2
    //   118: iconst_2
    //   119: invokestatic 116	java/lang/Character:valueOf	(C)Ljava/lang/Character;
    //   122: aastore
    //   123: invokevirtual 122	java/lang/reflect/Method:invoke	(Ljava/lang/Object;[Ljava/lang/Object;)Ljava/lang/Object;
    //   126: astore 5
    //   128: aload 4
    //   130: aload 5
    //   132: checkcast 100	java/lang/String
    //   135: invokevirtual 85	java/lang/StringBuilder:append	(Ljava/lang/String;)Ljava/lang/StringBuilder;
    //   138: astore 4
    //   140: getstatic 19	uuuuuu/xsxxsx:b006600660066ff00660066f0066	I
    //   143: getstatic 21	uuuuuu/xsxxsx:bfff0066f00660066f0066	I
    //   146: iadd
    //   147: getstatic 19	uuuuuu/xsxxsx:b006600660066ff00660066f0066	I
    //   150: imul
    //   151: getstatic 23	uuuuuu/xsxxsx:b0066ff0066f00660066f0066	I
    //   154: irem
    //   155: invokestatic 125	uuuuuu/xsxxsx:bk006B006Bk006B006Bk006B006B006B	()I
    //   158: if_icmpeq +13 -> 171
    //   161: bipush 98
    //   163: putstatic 19	uuuuuu/xsxxsx:b006600660066ff00660066f0066	I
    //   166: bipush 8
    //   168: putstatic 32	uuuuuu/xsxxsx:bf0066f0066f00660066f0066	I
    //   171: aload_2
    //   172: aload 4
    //   174: aload_1
    //   175: invokevirtual 85	java/lang/StringBuilder:append	(Ljava/lang/String;)Ljava/lang/StringBuilder;
    //   178: invokevirtual 88	java/lang/StringBuilder:toString	()Ljava/lang/String;
    //   181: invokestatic 131	uuuuuu/rvvvrv:bqqqq00710071q0071q0071	(Ljava/lang/String;Ljava/lang/String;)V
    //   184: invokestatic 56	java/util/Calendar:getInstance	()Ljava/util/Calendar;
    //   187: astore_1
    //   188: ldc 90
    //   190: ldc -123
    //   192: bipush 19
    //   194: iconst_5
    //   195: invokestatic 98	xxxxxx/uxxxxx:bb00620062bb0062b0062b0062	(Ljava/lang/String;CC)Ljava/lang/String;
    //   198: iconst_4
    //   199: anewarray 34	java/lang/Class
    //   202: dup
    //   203: iconst_0
    //   204: ldc 100
    //   206: aastore
    //   207: dup
    //   208: iconst_1
    //   209: getstatic 106	java/lang/Character:TYPE	Ljava/lang/Class;
    //   212: aastore
    //   213: dup
    //   214: iconst_2
    //   215: getstatic 106	java/lang/Character:TYPE	Ljava/lang/Class;
    //   218: aastore
    //   219: dup
    //   220: iconst_3
    //   221: getstatic 106	java/lang/Character:TYPE	Ljava/lang/Class;
    //   224: aastore
    //   225: invokevirtual 110	java/lang/Class:getMethod	(Ljava/lang/String;[Ljava/lang/Class;)Ljava/lang/reflect/Method;
    //   228: astore_2
    //   229: aload_2
    //   230: aconst_null
    //   231: iconst_4
    //   232: anewarray 4	java/lang/Object
    //   235: dup
    //   236: iconst_0
    //   237: ldc -121
    //   239: aastore
    //   240: dup
    //   241: iconst_1
    //   242: bipush 103
    //   244: invokestatic 116	java/lang/Character:valueOf	(C)Ljava/lang/Character;
    //   247: aastore
    //   248: dup
    //   249: iconst_2
    //   250: bipush 117
    //   252: invokestatic 116	java/lang/Character:valueOf	(C)Ljava/lang/Character;
    //   255: aastore
    //   256: dup
    //   257: iconst_3
    //   258: iconst_3
    //   259: invokestatic 116	java/lang/Character:valueOf	(C)Ljava/lang/Character;
    //   262: aastore
    //   263: invokevirtual 122	java/lang/reflect/Method:invoke	(Ljava/lang/Object;[Ljava/lang/Object;)Ljava/lang/Object;
    //   266: astore_2
    //   267: aload_1
    //   268: aload_2
    //   269: checkcast 100	java/lang/String
    //   272: invokestatic 141	java/util/TimeZone:getTimeZone	(Ljava/lang/String;)Ljava/util/TimeZone;
    //   275: invokevirtual 145	java/util/Calendar:setTimeZone	(Ljava/util/TimeZone;)V
    //   278: aload_1
    //   279: bipush 11
    //   281: iconst_0
    //   282: invokevirtual 148	java/util/Calendar:set	(II)V
    //   285: aload_1
    //   286: bipush 12
    //   288: iconst_0
    //   289: invokevirtual 148	java/util/Calendar:set	(II)V
    //   292: aload_1
    //   293: bipush 13
    //   295: iconst_0
    //   296: invokevirtual 148	java/util/Calendar:set	(II)V
    //   299: new 150	java/util/LinkedList
    //   302: dup
    //   303: invokespecial 151	java/util/LinkedList:<init>	()V
    //   306: astore_2
    //   307: ldc 90
    //   309: ldc -103
    //   311: sipush 159
    //   314: iconst_4
    //   315: invokestatic 98	xxxxxx/uxxxxx:bb00620062bb0062b0062b0062	(Ljava/lang/String;CC)Ljava/lang/String;
    //   318: iconst_3
    //   319: anewarray 34	java/lang/Class
    //   322: dup
    //   323: iconst_0
    //   324: ldc 100
    //   326: aastore
    //   327: dup
    //   328: iconst_1
    //   329: getstatic 106	java/lang/Character:TYPE	Ljava/lang/Class;
    //   332: aastore
    //   333: dup
    //   334: iconst_2
    //   335: getstatic 106	java/lang/Character:TYPE	Ljava/lang/Class;
    //   338: aastore
    //   339: invokevirtual 110	java/lang/Class:getMethod	(Ljava/lang/String;[Ljava/lang/Class;)Ljava/lang/reflect/Method;
    //   342: astore 4
    //   344: aload 4
    //   346: aconst_null
    //   347: iconst_3
    //   348: anewarray 4	java/lang/Object
    //   351: dup
    //   352: iconst_0
    //   353: ldc -101
    //   355: aastore
    //   356: dup
    //   357: iconst_1
    //   358: bipush 113
    //   360: invokestatic 116	java/lang/Character:valueOf	(C)Ljava/lang/Character;
    //   363: aastore
    //   364: dup
    //   365: iconst_2
    //   366: iconst_2
    //   367: invokestatic 116	java/lang/Character:valueOf	(C)Ljava/lang/Character;
    //   370: aastore
    //   371: invokevirtual 122	java/lang/reflect/Method:invoke	(Ljava/lang/Object;[Ljava/lang/Object;)Ljava/lang/Object;
    //   374: astore 4
    //   376: new 157	java/text/SimpleDateFormat
    //   379: dup
    //   380: aload 4
    //   382: checkcast 100	java/lang/String
    //   385: getstatic 163	java/util/Locale:GERMANY	Ljava/util/Locale;
    //   388: invokespecial 166	java/text/SimpleDateFormat:<init>	(Ljava/lang/String;Ljava/util/Locale;)V
    //   391: astore 4
    //   393: aload_0
    //   394: invokeinterface 172 1 0
    //   399: astore_0
    //   400: aload_0
    //   401: invokeinterface 178 1 0
    //   406: ifeq +328 -> 734
    //   409: aload_0
    //   410: invokeinterface 182 1 0
    //   415: checkcast 184	com/db/pwcc/dbmobile/model/banking/CashAccountTransaction
    //   418: astore 5
    //   420: aload 5
    //   422: invokevirtual 187	com/db/pwcc/dbmobile/model/banking/CashAccountTransaction:getBookDate	()Ljava/lang/String;
    //   425: astore 7
    //   427: aload 7
    //   429: ifnull -29 -> 400
    //   432: aload 7
    //   434: invokevirtual 190	java/lang/String:length	()I
    //   437: iconst_1
    //   438: if_icmplt -38 -> 400
    //   441: aload_1
    //   442: aload 4
    //   444: aload 7
    //   446: invokevirtual 194	java/text/SimpleDateFormat:parse	(Ljava/lang/String;)Ljava/util/Date;
    //   449: invokevirtual 60	java/util/Calendar:setTime	(Ljava/util/Date;)V
    //   452: aload_3
    //   453: aload_1
    //   454: invokevirtual 198	java/util/Calendar:before	(Ljava/lang/Object;)Z
    //   457: ifeq -57 -> 400
    //   460: aload_2
    //   461: aload 5
    //   463: invokevirtual 200	java/util/LinkedList:add	(Ljava/lang/Object;)Z
    //   466: pop
    //   467: goto -67 -> 400
    //   470: astore 5
    //   472: getstatic 40	uuuuuu/xsxxsx:bf00660066ff00660066f0066	Ljava/lang/String;
    //   475: astore 6
    //   477: new 71	java/lang/StringBuilder
    //   480: dup
    //   481: invokespecial 72	java/lang/StringBuilder:<init>	()V
    //   484: astore 8
    //   486: getstatic 19	uuuuuu/xsxxsx:b006600660066ff00660066f0066	I
    //   489: getstatic 21	uuuuuu/xsxxsx:bfff0066f00660066f0066	I
    //   492: iadd
    //   493: getstatic 19	uuuuuu/xsxxsx:b006600660066ff00660066f0066	I
    //   496: imul
    //   497: getstatic 23	uuuuuu/xsxxsx:b0066ff0066f00660066f0066	I
    //   500: irem
    //   501: getstatic 32	uuuuuu/xsxxsx:bf0066f0066f00660066f0066	I
    //   504: if_icmpeq +14 -> 518
    //   507: invokestatic 27	uuuuuu/xsxxsx:b006B006B006Bk006B006Bk006B006B006B	()I
    //   510: putstatic 19	uuuuuu/xsxxsx:b006600660066ff00660066f0066	I
    //   513: bipush 91
    //   515: putstatic 32	uuuuuu/xsxxsx:bf0066f0066f00660066f0066	I
    //   518: ldc 90
    //   520: ldc -54
    //   522: bipush 62
    //   524: bipush 48
    //   526: iconst_2
    //   527: invokestatic 206	xxxxxx/uxxxxx:bbbb0062b0062b0062b0062	(Ljava/lang/String;CCC)Ljava/lang/String;
    //   530: iconst_3
    //   531: anewarray 34	java/lang/Class
    //   534: dup
    //   535: iconst_0
    //   536: ldc 100
    //   538: aastore
    //   539: dup
    //   540: iconst_1
    //   541: getstatic 106	java/lang/Character:TYPE	Ljava/lang/Class;
    //   544: aastore
    //   545: dup
    //   546: iconst_2
    //   547: getstatic 106	java/lang/Character:TYPE	Ljava/lang/Class;
    //   550: aastore
    //   551: invokevirtual 110	java/lang/Class:getMethod	(Ljava/lang/String;[Ljava/lang/Class;)Ljava/lang/reflect/Method;
    //   554: astore 9
    //   556: aload 9
    //   558: aconst_null
    //   559: iconst_3
    //   560: anewarray 4	java/lang/Object
    //   563: dup
    //   564: iconst_0
    //   565: ldc -48
    //   567: aastore
    //   568: dup
    //   569: iconst_1
    //   570: bipush 87
    //   572: invokestatic 116	java/lang/Character:valueOf	(C)Ljava/lang/Character;
    //   575: aastore
    //   576: dup
    //   577: iconst_2
    //   578: iconst_4
    //   579: invokestatic 116	java/lang/Character:valueOf	(C)Ljava/lang/Character;
    //   582: aastore
    //   583: invokevirtual 122	java/lang/reflect/Method:invoke	(Ljava/lang/Object;[Ljava/lang/Object;)Ljava/lang/Object;
    //   586: astore 9
    //   588: aload 8
    //   590: aload 9
    //   592: checkcast 100	java/lang/String
    //   595: invokevirtual 85	java/lang/StringBuilder:append	(Ljava/lang/String;)Ljava/lang/StringBuilder;
    //   598: aload 7
    //   600: invokevirtual 85	java/lang/StringBuilder:append	(Ljava/lang/String;)Ljava/lang/StringBuilder;
    //   603: astore 7
    //   605: ldc 90
    //   607: ldc -46
    //   609: sipush 164
    //   612: iconst_0
    //   613: invokestatic 98	xxxxxx/uxxxxx:bb00620062bb0062b0062b0062	(Ljava/lang/String;CC)Ljava/lang/String;
    //   616: iconst_3
    //   617: anewarray 34	java/lang/Class
    //   620: dup
    //   621: iconst_0
    //   622: ldc 100
    //   624: aastore
    //   625: dup
    //   626: iconst_1
    //   627: getstatic 106	java/lang/Character:TYPE	Ljava/lang/Class;
    //   630: aastore
    //   631: dup
    //   632: iconst_2
    //   633: getstatic 106	java/lang/Character:TYPE	Ljava/lang/Class;
    //   636: aastore
    //   637: invokevirtual 110	java/lang/Class:getMethod	(Ljava/lang/String;[Ljava/lang/Class;)Ljava/lang/reflect/Method;
    //   640: astore 8
    //   642: aload 8
    //   644: aconst_null
    //   645: iconst_3
    //   646: anewarray 4	java/lang/Object
    //   649: dup
    //   650: iconst_0
    //   651: ldc -44
    //   653: aastore
    //   654: dup
    //   655: iconst_1
    //   656: sipush 193
    //   659: invokestatic 116	java/lang/Character:valueOf	(C)Ljava/lang/Character;
    //   662: aastore
    //   663: dup
    //   664: iconst_2
    //   665: iconst_2
    //   666: invokestatic 116	java/lang/Character:valueOf	(C)Ljava/lang/Character;
    //   669: aastore
    //   670: invokevirtual 122	java/lang/reflect/Method:invoke	(Ljava/lang/Object;[Ljava/lang/Object;)Ljava/lang/Object;
    //   673: astore 8
    //   675: aload 6
    //   677: aload 7
    //   679: aload 8
    //   681: checkcast 100	java/lang/String
    //   684: invokevirtual 85	java/lang/StringBuilder:append	(Ljava/lang/String;)Ljava/lang/StringBuilder;
    //   687: aload 5
    //   689: invokevirtual 215	java/text/ParseException:getMessage	()Ljava/lang/String;
    //   692: invokevirtual 85	java/lang/StringBuilder:append	(Ljava/lang/String;)Ljava/lang/StringBuilder;
    //   695: invokevirtual 88	java/lang/StringBuilder:toString	()Ljava/lang/String;
    //   698: invokestatic 218	uuuuuu/rvvvrv:b0071qq007100710071q0071q0071	(Ljava/lang/String;Ljava/lang/String;)V
    //   701: goto -301 -> 400
    //   704: astore_0
    //   705: aload_0
    //   706: invokevirtual 222	java/lang/reflect/InvocationTargetException:getCause	()Ljava/lang/Throwable;
    //   709: athrow
    //   710: astore_0
    //   711: aload_0
    //   712: invokevirtual 222	java/lang/reflect/InvocationTargetException:getCause	()Ljava/lang/Throwable;
    //   715: athrow
    //   716: astore_0
    //   717: aload_0
    //   718: invokevirtual 222	java/lang/reflect/InvocationTargetException:getCause	()Ljava/lang/Throwable;
    //   721: athrow
    //   722: astore_0
    //   723: aload_0
    //   724: invokevirtual 222	java/lang/reflect/InvocationTargetException:getCause	()Ljava/lang/Throwable;
    //   727: athrow
    //   728: astore_0
    //   729: aload_0
    //   730: invokevirtual 222	java/lang/reflect/InvocationTargetException:getCause	()Ljava/lang/Throwable;
    //   733: athrow
    //   734: aload_2
    //   735: areturn
    // Local variable table:
    //   start	length	slot	name	signature
    //   0	736	0	paramList	java.util.List<com.db.pwcc.dbmobile.model.banking.CashAccountTransaction>
    //   0	736	1	paramNnooon	onooon.nnooon
    //   0	736	2	paramDate	java.util.Date
    //   3	450	3	localCalendar	java.util.Calendar
    //   56	387	4	localObject1	Object
    //   93	369	5	localObject2	Object
    //   470	218	5	localParseException	java.text.ParseException
    //   475	201	6	str	String
    //   425	253	7	localObject3	Object
    //   484	196	8	localObject4	Object
    //   554	37	9	localObject5	Object
    // Exception table:
    //   from	to	target	type
    //   441	467	470	java/text/ParseException
    //   556	588	704	java/lang/reflect/InvocationTargetException
    //   642	675	710	java/lang/reflect/InvocationTargetException
    //   229	267	716	java/lang/reflect/InvocationTargetException
    //   344	376	722	java/lang/reflect/InvocationTargetException
    //   95	128	728	java/lang/reflect/InvocationTargetException
  }
  
  public static int bk006B006Bk006B006Bk006B006B006B()
  {
    return 0;
  }
  
  public static int bkkk006B006B006Bk006B006B006B()
  {
    return 1;
  }
}
