package uuuuuu;

import android.content.Context;
import android.graphics.Paint;
import android.graphics.Typeface;
import android.support.annotation.NonNull;
import android.support.design.widget.TextInputLayout;
import android.view.View;
import android.widget.TextView;
import java.lang.reflect.InvocationTargetException;
import java.lang.reflect.Method;
import java.util.Map;
import xxxxxx.uxxxxx;

public final class xsxxxs
{
  public static int b00660066006600660066fff0066 = 1;
  public static final String b006600660066f0066fff0066 = "\033%%,,h\007\020\034ooptup89,";
  public static Map<String, Typeface> b00660066f00660066fff0066;
  public static int b0066f006600660066fff0066 = 0;
  public static final String b0066ff00660066fff0066 = "\032$$++g\006\017\033nnospo78+";
  public static int bf0066006600660066fff0066 = 2;
  private static final String bf0066f00660066fff0066;
  public static int bff006600660066fff0066 = 41;
  public static final String bfff00660066fff0066 = "&.,1/i\t{\nwc)(\031";
  
  /* Error */
  static
  {
    // Byte code:
    //   0: getstatic 33	uuuuuu/xsxxxs:b006600660066f0066fff0066	Ljava/lang/String;
    //   3: astore_1
    //   4: ldc 35
    //   6: ldc 37
    //   8: sipush 170
    //   11: iconst_0
    //   12: invokestatic 43	xxxxxx/uxxxxx:bb00620062bb0062b0062b0062	(Ljava/lang/String;CC)Ljava/lang/String;
    //   15: iconst_4
    //   16: anewarray 45	java/lang/Class
    //   19: dup
    //   20: iconst_0
    //   21: ldc 47
    //   23: aastore
    //   24: dup
    //   25: iconst_1
    //   26: getstatic 53	java/lang/Character:TYPE	Ljava/lang/Class;
    //   29: aastore
    //   30: dup
    //   31: iconst_2
    //   32: getstatic 53	java/lang/Character:TYPE	Ljava/lang/Class;
    //   35: aastore
    //   36: dup
    //   37: iconst_3
    //   38: getstatic 53	java/lang/Character:TYPE	Ljava/lang/Class;
    //   41: aastore
    //   42: invokevirtual 57	java/lang/Class:getMethod	(Ljava/lang/String;[Ljava/lang/Class;)Ljava/lang/reflect/Method;
    //   45: astore_2
    //   46: aload_2
    //   47: aconst_null
    //   48: iconst_4
    //   49: anewarray 4	java/lang/Object
    //   52: dup
    //   53: iconst_0
    //   54: aload_1
    //   55: aastore
    //   56: dup
    //   57: iconst_1
    //   58: sipush 246
    //   61: invokestatic 61	java/lang/Character:valueOf	(C)Ljava/lang/Character;
    //   64: aastore
    //   65: dup
    //   66: iconst_2
    //   67: bipush 67
    //   69: invokestatic 61	java/lang/Character:valueOf	(C)Ljava/lang/Character;
    //   72: aastore
    //   73: dup
    //   74: iconst_3
    //   75: iconst_2
    //   76: invokestatic 61	java/lang/Character:valueOf	(C)Ljava/lang/Character;
    //   79: aastore
    //   80: invokevirtual 67	java/lang/reflect/Method:invoke	(Ljava/lang/Object;[Ljava/lang/Object;)Ljava/lang/Object;
    //   83: astore_1
    //   84: aload_1
    //   85: checkcast 47	java/lang/String
    //   88: putstatic 33	uuuuuu/xsxxxs:b006600660066f0066fff0066	Ljava/lang/String;
    //   91: getstatic 69	uuuuuu/xsxxxs:bfff00660066fff0066	Ljava/lang/String;
    //   94: astore_1
    //   95: ldc 35
    //   97: ldc 71
    //   99: bipush 125
    //   101: iconst_3
    //   102: invokestatic 43	xxxxxx/uxxxxx:bb00620062bb0062b0062b0062	(Ljava/lang/String;CC)Ljava/lang/String;
    //   105: iconst_4
    //   106: anewarray 45	java/lang/Class
    //   109: dup
    //   110: iconst_0
    //   111: ldc 47
    //   113: aastore
    //   114: dup
    //   115: iconst_1
    //   116: getstatic 53	java/lang/Character:TYPE	Ljava/lang/Class;
    //   119: aastore
    //   120: dup
    //   121: iconst_2
    //   122: getstatic 53	java/lang/Character:TYPE	Ljava/lang/Class;
    //   125: aastore
    //   126: dup
    //   127: iconst_3
    //   128: getstatic 53	java/lang/Character:TYPE	Ljava/lang/Class;
    //   131: aastore
    //   132: invokevirtual 57	java/lang/Class:getMethod	(Ljava/lang/String;[Ljava/lang/Class;)Ljava/lang/reflect/Method;
    //   135: astore_2
    //   136: aload_2
    //   137: aconst_null
    //   138: iconst_4
    //   139: anewarray 4	java/lang/Object
    //   142: dup
    //   143: iconst_0
    //   144: aload_1
    //   145: aastore
    //   146: dup
    //   147: iconst_1
    //   148: sipush 197
    //   151: invokestatic 61	java/lang/Character:valueOf	(C)Ljava/lang/Character;
    //   154: aastore
    //   155: dup
    //   156: iconst_2
    //   157: bipush 121
    //   159: invokestatic 61	java/lang/Character:valueOf	(C)Ljava/lang/Character;
    //   162: aastore
    //   163: dup
    //   164: iconst_3
    //   165: iconst_0
    //   166: invokestatic 61	java/lang/Character:valueOf	(C)Ljava/lang/Character;
    //   169: aastore
    //   170: invokevirtual 67	java/lang/reflect/Method:invoke	(Ljava/lang/Object;[Ljava/lang/Object;)Ljava/lang/Object;
    //   173: astore_1
    //   174: aload_1
    //   175: checkcast 47	java/lang/String
    //   178: putstatic 69	uuuuuu/xsxxxs:bfff00660066fff0066	Ljava/lang/String;
    //   181: getstatic 73	uuuuuu/xsxxxs:bff006600660066fff0066	I
    //   184: istore_0
    //   185: iload_0
    //   186: getstatic 75	uuuuuu/xsxxxs:b00660066006600660066fff0066	I
    //   189: iload_0
    //   190: iadd
    //   191: imul
    //   192: getstatic 77	uuuuuu/xsxxxs:bf0066006600660066fff0066	I
    //   195: irem
    //   196: tableswitch	default:+20->216, 0:+32->228
    //   216: invokestatic 81	uuuuuu/xsxxxs:bk006Bkkk006B006Bk006B006B	()I
    //   219: putstatic 73	uuuuuu/xsxxxs:bff006600660066fff0066	I
    //   222: invokestatic 81	uuuuuu/xsxxxs:bk006Bkkk006B006Bk006B006B	()I
    //   225: putstatic 83	uuuuuu/xsxxxs:b0066f006600660066fff0066	I
    //   228: getstatic 85	uuuuuu/xsxxxs:b0066ff00660066fff0066	Ljava/lang/String;
    //   231: astore_1
    //   232: ldc 35
    //   234: ldc 87
    //   236: bipush 10
    //   238: iconst_1
    //   239: invokestatic 43	xxxxxx/uxxxxx:bb00620062bb0062b0062b0062	(Ljava/lang/String;CC)Ljava/lang/String;
    //   242: iconst_3
    //   243: anewarray 45	java/lang/Class
    //   246: dup
    //   247: iconst_0
    //   248: ldc 47
    //   250: aastore
    //   251: dup
    //   252: iconst_1
    //   253: getstatic 53	java/lang/Character:TYPE	Ljava/lang/Class;
    //   256: aastore
    //   257: dup
    //   258: iconst_2
    //   259: getstatic 53	java/lang/Character:TYPE	Ljava/lang/Class;
    //   262: aastore
    //   263: invokevirtual 57	java/lang/Class:getMethod	(Ljava/lang/String;[Ljava/lang/Class;)Ljava/lang/reflect/Method;
    //   266: astore_2
    //   267: aload_2
    //   268: aconst_null
    //   269: iconst_3
    //   270: anewarray 4	java/lang/Object
    //   273: dup
    //   274: iconst_0
    //   275: aload_1
    //   276: aastore
    //   277: dup
    //   278: iconst_1
    //   279: sipush 178
    //   282: invokestatic 61	java/lang/Character:valueOf	(C)Ljava/lang/Character;
    //   285: aastore
    //   286: dup
    //   287: iconst_2
    //   288: iconst_2
    //   289: invokestatic 61	java/lang/Character:valueOf	(C)Ljava/lang/Character;
    //   292: aastore
    //   293: invokevirtual 67	java/lang/reflect/Method:invoke	(Ljava/lang/Object;[Ljava/lang/Object;)Ljava/lang/Object;
    //   296: astore_1
    //   297: aload_1
    //   298: checkcast 47	java/lang/String
    //   301: putstatic 85	uuuuuu/xsxxxs:b0066ff00660066fff0066	Ljava/lang/String;
    //   304: ldc 2
    //   306: invokevirtual 91	java/lang/Class:getSimpleName	()Ljava/lang/String;
    //   309: putstatic 93	uuuuuu/xsxxxs:bf0066f00660066fff0066	Ljava/lang/String;
    //   312: getstatic 73	uuuuuu/xsxxxs:bff006600660066fff0066	I
    //   315: invokestatic 96	uuuuuu/xsxxxs:b006Bkkkk006B006Bk006B006B	()I
    //   318: iadd
    //   319: getstatic 73	uuuuuu/xsxxxs:bff006600660066fff0066	I
    //   322: imul
    //   323: getstatic 77	uuuuuu/xsxxxs:bf0066006600660066fff0066	I
    //   326: irem
    //   327: getstatic 83	uuuuuu/xsxxxs:b0066f006600660066fff0066	I
    //   330: if_icmpeq +14 -> 344
    //   333: bipush 13
    //   335: putstatic 73	uuuuuu/xsxxxs:bff006600660066fff0066	I
    //   338: invokestatic 81	uuuuuu/xsxxxs:bk006Bkkk006B006Bk006B006B	()I
    //   341: putstatic 83	uuuuuu/xsxxxs:b0066f006600660066fff0066	I
    //   344: new 98	java/util/HashMap
    //   347: dup
    //   348: invokespecial 101	java/util/HashMap:<init>	()V
    //   351: putstatic 103	uuuuuu/xsxxxs:b00660066f00660066fff0066	Ljava/util/Map;
    //   354: return
    //   355: astore_1
    //   356: aload_1
    //   357: invokevirtual 107	java/lang/reflect/InvocationTargetException:getCause	()Ljava/lang/Throwable;
    //   360: athrow
    //   361: astore_1
    //   362: aload_1
    //   363: invokevirtual 107	java/lang/reflect/InvocationTargetException:getCause	()Ljava/lang/Throwable;
    //   366: athrow
    //   367: astore_1
    //   368: aload_1
    //   369: invokevirtual 107	java/lang/reflect/InvocationTargetException:getCause	()Ljava/lang/Throwable;
    //   372: athrow
    // Local variable table:
    //   start	length	slot	name	signature
    //   184	8	0	i	int
    //   3	295	1	localObject	Object
    //   355	2	1	localInvocationTargetException1	InvocationTargetException
    //   361	2	1	localInvocationTargetException2	InvocationTargetException
    //   367	2	1	localInvocationTargetException3	InvocationTargetException
    //   45	223	2	localMethod	Method
    // Exception table:
    //   from	to	target	type
    //   267	297	355	java/lang/reflect/InvocationTargetException
    //   46	84	361	java/lang/reflect/InvocationTargetException
    //   136	174	367	java/lang/reflect/InvocationTargetException
  }
  
  private xsxxxs() {}
  
  private static void b006B006B006B006B006Bk006Bk006B006B(@NonNull View paramView, String paramString)
  {
    paramString = b006B006Bkkk006B006Bk006B006B(paramView.getContext(), paramString);
    if ((paramView instanceof TextView))
    {
      paramView = (TextView)paramView;
      int i = bff006600660066fff0066;
      switch (i * (b006Bkkkk006B006Bk006B006B() + i) % bf0066006600660066fff0066)
      {
      default: 
        bff006600660066fff0066 = 47;
        b0066f006600660066fff0066 = bk006Bkkk006B006Bk006B006B();
      }
      paramView.setTypeface(paramString);
    }
    for (;;)
    {
      return;
      if ((paramView instanceof TextInputLayout))
      {
        ((TextInputLayout)paramView).setTypeface(paramString);
        return;
      }
      paramString = bf0066f00660066fff0066;
      StringBuilder localStringBuilder = new StringBuilder();
      Object localObject = ppphhp.class.getMethod(uxxxxx.bbbb0062b0062b0062b0062("\r! \037\036UTZYQPVU\025LKQPHGML\f", '±', '#', '\000'), new Class[] { String.class, Character.TYPE, Character.TYPE });
      try
      {
        localObject = ((Method)localObject).invoke(null, new Object[] { "m\024\f\002\004\003\006A\021\023\031E\032\r\035I\032\032L$\030\025(Q", Character.valueOf('\031'), Character.valueOf('\002') });
        rvvvrv.b0071qq007100710071q0071q0071(paramString, (String)localObject + paramView.getClass().getSimpleName());
        if ((bff006600660066fff0066 + b00660066006600660066fff0066) * bff006600660066fff0066 % bf0066006600660066fff0066 == b0066f006600660066fff0066) {
          continue;
        }
        bff006600660066fff0066 = 99;
        b0066f006600660066fff0066 = bk006Bkkk006B006Bk006B006B();
        return;
      }
      catch (InvocationTargetException paramView)
      {
        throw paramView.getCause();
      }
    }
  }
  
  private static Typeface b006B006Bkkk006B006Bk006B006B(Context paramContext, String paramString)
  {
    if (b00660066f00660066fff0066.containsKey(paramString))
    {
      paramContext = (Typeface)b00660066f00660066fff0066.get(paramString);
      return paramContext;
    }
    Typeface localTypeface = Typeface.createFromAsset(paramContext.getAssets(), paramString);
    b00660066f00660066fff0066.put(paramString, localTypeface);
    int i = bff006600660066fff0066;
    int j = b00660066006600660066fff0066;
    int k = bf0066006600660066fff0066;
    if ((bff006600660066fff0066 + b00660066006600660066fff0066) * bff006600660066fff0066 % bkkkkk006B006Bk006B006B() != b0066f006600660066fff0066)
    {
      bff006600660066fff0066 = bk006Bkkk006B006Bk006B006B();
      b0066f006600660066fff0066 = 1;
    }
    paramContext = localTypeface;
    switch (i * (j + i) % k)
    {
    }
    bff006600660066fff0066 = 16;
    b0066f006600660066fff0066 = bk006Bkkk006B006Bk006B006B();
    return localTypeface;
  }
  
  public static void b006Bk006Bkk006B006Bk006B006B(@NonNull Context paramContext, @NonNull Paint paramPaint)
  {
    if ((bff006600660066fff0066 + b00660066006600660066fff0066) * bff006600660066fff0066 % bf0066006600660066fff0066 != b0066f006600660066fff0066)
    {
      bff006600660066fff0066 = 72;
      b0066f006600660066fff0066 = 74;
      if ((bff006600660066fff0066 + b00660066006600660066fff0066) * bff006600660066fff0066 % bf0066006600660066fff0066 != b0066f006600660066fff0066)
      {
        bff006600660066fff0066 = bk006Bkkk006B006Bk006B006B();
        b0066f006600660066fff0066 = 43;
      }
    }
    Object localObject = ppphhp.class.getMethod(uxxxxx.bb00620062bb0062b0062b0062("?UVWX\022\023\033\034\026\027\037 a\033\034$%\037 ()j", 'I', '\000'), new Class[] { String.class, Character.TYPE, Character.TYPE });
    try
    {
      localObject = ((Method)localObject).invoke(null, new Object[] { "\r\027\027\036\036Z{p\001p^&'\032", Character.valueOf('\023'), Character.valueOf('\001') });
      paramPaint.setTypeface(b006B006Bkkk006B006Bk006B006B(paramContext, (String)localObject));
      return;
    }
    catch (InvocationTargetException paramContext)
    {
      throw paramContext.getCause();
    }
  }
  
  public static int b006Bkkkk006B006Bk006B006B()
  {
    return 1;
  }
  
  public static void bk006B006Bkk006B006Bk006B006B(@NonNull View paramView)
  {
    Object localObject = ppphhp.class.getMethod(uxxxxx.bb00620062bb0062b0062b0062("G[ZYX\020\017\025\024\f\013\021\020O\007\006\f\013\003\002\b\007F", '\t', '\005'), new Class[] { String.class, Character.TYPE, Character.TYPE });
    try
    {
      localObject = ((Method)localObject).invoke(null, new Object[] { "IQOTR\r)0:\f\n\t\013\006\003HG8", Character.valueOf('N'), Character.valueOf('\004') });
      localObject = (String)localObject;
      if ((bff006600660066fff0066 + b00660066006600660066fff0066) * bff006600660066fff0066 % bf0066006600660066fff0066 != b0066f006600660066fff0066)
      {
        int i = bff006600660066fff0066;
        switch (i * (b00660066006600660066fff0066 + i) % bf0066006600660066fff0066)
        {
        default: 
          bff006600660066fff0066 = bk006Bkkk006B006Bk006B006B();
          b0066f006600660066fff0066 = bk006Bkkk006B006Bk006B006B();
        }
        bff006600660066fff0066 = 91;
        b0066f006600660066fff0066 = 39;
      }
      b006B006B006B006B006Bk006Bk006B006B(paramView, (String)localObject);
      return;
    }
    catch (InvocationTargetException paramView)
    {
      throw paramView.getCause();
    }
  }
  
  public static int bk006Bkkk006B006Bk006B006B()
  {
    return 20;
  }
  
  public static void bkk006Bkk006B006Bk006B006B(@NonNull View paramView)
  {
    int i = bff006600660066fff0066;
    switch (i * (b00660066006600660066fff0066 + i) % bf0066006600660066fff0066)
    {
    default: 
      bff006600660066fff0066 = 41;
      i = bk006Bkkk006B006Bk006B006B();
      if ((bff006600660066fff0066 + b006Bkkkk006B006Bk006B006B()) * bff006600660066fff0066 % bf0066006600660066fff0066 != b0066f006600660066fff0066)
      {
        bff006600660066fff0066 = bk006Bkkk006B006Bk006B006B();
        b0066f006600660066fff0066 = bk006Bkkk006B006Bk006B006B();
      }
      b0066f006600660066fff0066 = i;
    }
    Object localObject = ppphhp.class.getMethod(uxxxxx.bbbb0062b0062b0062b0062("I]\025\024\032\031XW\017\016\024\023\013\n\020\017N\006\005\013\n\002\001\007\006E", 'X', '¿', '\000'), new Class[] { String.class, Character.TYPE, Character.TYPE, Character.TYPE });
    try
    {
      localObject = ((Method)localObject).invoke(null, new Object[] { "\b\022\022\031\031Us|\t\\\\]ab]%&\031", Character.valueOf('â'), Character.valueOf('¼'), Character.valueOf('\003') });
      b006B006B006B006B006Bk006Bk006B006B(paramView, (String)localObject);
      return;
    }
    catch (InvocationTargetException paramView)
    {
      throw paramView.getCause();
    }
  }
  
  public static int bkkkkk006B006Bk006B006B()
  {
    return 2;
  }
}
