package uuuuuu;

import android.content.Context;
import android.net.Uri;
import com.db.pwcc.dbmobile.model.env_selector.UserInfo;
import java.lang.reflect.InvocationTargetException;
import java.lang.reflect.Method;
import xxxxxx.uxxxxx;

public class ygggyy
  extends gyggyy
{
  public static int b006B006B006B006Bk006Bk006Bk = 0;
  public static int b006Bkkk006B006Bk006Bk = 2;
  public static int bk006Bkk006B006Bk006Bk = 34;
  public static int bkkkk006B006Bk006Bk = 1;
  public UserInfo bk006B006B006Bk006Bk006Bk = b0070pp0070p0070pp0070p(paramContext);
  
  public ygggyy(Context paramContext, ygyygy paramYgyygy)
  {
    super(paramYgyygy);
  }
  
  public static int b0070p0070pp0070pp0070p()
  {
    return 1;
  }
  
  /* Error */
  private UserInfo b0070pp0070p0070pp0070p(Context paramContext)
  {
    // Byte code:
    //   0: invokestatic 39	uuuuuu/yyhyhh:bp0070pp0070p0070007000700070	()Luuuuuu/yyhyhh;
    //   3: astore 7
    //   5: invokestatic 42	uuuuuu/ygggyy:bp00700070pp0070pp0070p	()I
    //   8: istore_2
    //   9: getstatic 44	uuuuuu/ygggyy:bkkkk006B006Bk006Bk	I
    //   12: istore_3
    //   13: invokestatic 42	uuuuuu/ygggyy:bp00700070pp0070pp0070p	()I
    //   16: istore 4
    //   18: getstatic 46	uuuuuu/ygggyy:b006Bkkk006B006Bk006Bk	I
    //   21: istore 5
    //   23: getstatic 48	uuuuuu/ygggyy:bk006Bkk006B006Bk006Bk	I
    //   26: istore 6
    //   28: iload 6
    //   30: invokestatic 50	uuuuuu/ygggyy:b0070p0070pp0070pp0070p	()I
    //   33: iload 6
    //   35: iadd
    //   36: imul
    //   37: getstatic 46	uuuuuu/ygggyy:b006Bkkk006B006Bk006Bk	I
    //   40: irem
    //   41: tableswitch	default:+19->60, 0:+28->69
    //   60: bipush 89
    //   62: putstatic 48	uuuuuu/ygggyy:bk006Bkk006B006Bk006Bk	I
    //   65: iconst_2
    //   66: putstatic 52	uuuuuu/ygggyy:b006B006B006B006Bk006Bk006Bk	I
    //   69: iload_2
    //   70: iload_3
    //   71: iadd
    //   72: iload 4
    //   74: imul
    //   75: iload 5
    //   77: irem
    //   78: getstatic 52	uuuuuu/ygggyy:b006B006B006B006Bk006Bk006Bk	I
    //   81: if_icmpeq +9 -> 90
    //   84: invokestatic 42	uuuuuu/ygggyy:bp00700070pp0070pp0070p	()I
    //   87: putstatic 52	uuuuuu/ygggyy:b006B006B006B006Bk006Bk006Bk	I
    //   90: ldc 54
    //   92: ldc 56
    //   94: bipush 36
    //   96: bipush 44
    //   98: iconst_2
    //   99: invokestatic 62	xxxxxx/uxxxxx:bbbb0062b0062b0062b0062	(Ljava/lang/String;CCC)Ljava/lang/String;
    //   102: iconst_4
    //   103: anewarray 64	java/lang/Class
    //   106: dup
    //   107: iconst_0
    //   108: ldc 66
    //   110: aastore
    //   111: dup
    //   112: iconst_1
    //   113: getstatic 72	java/lang/Character:TYPE	Ljava/lang/Class;
    //   116: aastore
    //   117: dup
    //   118: iconst_2
    //   119: getstatic 72	java/lang/Character:TYPE	Ljava/lang/Class;
    //   122: aastore
    //   123: dup
    //   124: iconst_3
    //   125: getstatic 72	java/lang/Character:TYPE	Ljava/lang/Class;
    //   128: aastore
    //   129: invokevirtual 76	java/lang/Class:getMethod	(Ljava/lang/String;[Ljava/lang/Class;)Ljava/lang/reflect/Method;
    //   132: astore 8
    //   134: aload 8
    //   136: aconst_null
    //   137: iconst_4
    //   138: anewarray 78	java/lang/Object
    //   141: dup
    //   142: iconst_0
    //   143: ldc 80
    //   145: aastore
    //   146: dup
    //   147: iconst_1
    //   148: sipush 244
    //   151: invokestatic 84	java/lang/Character:valueOf	(C)Ljava/lang/Character;
    //   154: aastore
    //   155: dup
    //   156: iconst_2
    //   157: bipush 55
    //   159: invokestatic 84	java/lang/Character:valueOf	(C)Ljava/lang/Character;
    //   162: aastore
    //   163: dup
    //   164: iconst_3
    //   165: iconst_3
    //   166: invokestatic 84	java/lang/Character:valueOf	(C)Ljava/lang/Character;
    //   169: aastore
    //   170: invokevirtual 90	java/lang/reflect/Method:invoke	(Ljava/lang/Object;[Ljava/lang/Object;)Ljava/lang/Object;
    //   173: astore 8
    //   175: aload 8
    //   177: checkcast 66	java/lang/String
    //   180: astore 8
    //   182: new 92	com/db/pwcc/dbmobile/model/env_selector/UserInfo
    //   185: dup
    //   186: new 94	org/json/JSONObject
    //   189: dup
    //   190: aload 7
    //   192: aload_1
    //   193: aload 8
    //   195: invokevirtual 98	uuuuuu/yyhyhh:bpp0070p0070p0070007000700070	(Landroid/content/Context;Ljava/lang/String;)Ljava/lang/String;
    //   198: invokespecial 101	org/json/JSONObject:<init>	(Ljava/lang/String;)V
    //   201: invokespecial 104	com/db/pwcc/dbmobile/model/env_selector/UserInfo:<init>	(Lorg/json/JSONObject;)V
    //   204: astore_1
    //   205: aload_1
    //   206: areturn
    //   207: astore_1
    //   208: ldc 54
    //   210: ldc 106
    //   212: bipush 21
    //   214: bipush 61
    //   216: iconst_1
    //   217: invokestatic 62	xxxxxx/uxxxxx:bbbb0062b0062b0062b0062	(Ljava/lang/String;CCC)Ljava/lang/String;
    //   220: iconst_3
    //   221: anewarray 64	java/lang/Class
    //   224: dup
    //   225: iconst_0
    //   226: ldc 66
    //   228: aastore
    //   229: dup
    //   230: iconst_1
    //   231: getstatic 72	java/lang/Character:TYPE	Ljava/lang/Class;
    //   234: aastore
    //   235: dup
    //   236: iconst_2
    //   237: getstatic 72	java/lang/Character:TYPE	Ljava/lang/Class;
    //   240: aastore
    //   241: invokevirtual 76	java/lang/Class:getMethod	(Ljava/lang/String;[Ljava/lang/Class;)Ljava/lang/reflect/Method;
    //   244: astore 7
    //   246: aload 7
    //   248: aconst_null
    //   249: iconst_3
    //   250: anewarray 78	java/lang/Object
    //   253: dup
    //   254: iconst_0
    //   255: ldc 108
    //   257: aastore
    //   258: dup
    //   259: iconst_1
    //   260: bipush 112
    //   262: invokestatic 84	java/lang/Character:valueOf	(C)Ljava/lang/Character;
    //   265: aastore
    //   266: dup
    //   267: iconst_2
    //   268: iconst_2
    //   269: invokestatic 84	java/lang/Character:valueOf	(C)Ljava/lang/Character;
    //   272: aastore
    //   273: invokevirtual 90	java/lang/reflect/Method:invoke	(Ljava/lang/Object;[Ljava/lang/Object;)Ljava/lang/Object;
    //   276: astore 7
    //   278: new 110	java/lang/IllegalStateException
    //   281: dup
    //   282: aload 7
    //   284: checkcast 66	java/lang/String
    //   287: aload_1
    //   288: invokespecial 113	java/lang/IllegalStateException:<init>	(Ljava/lang/String;Ljava/lang/Throwable;)V
    //   291: athrow
    //   292: astore_1
    //   293: aload_1
    //   294: invokevirtual 117	java/lang/reflect/InvocationTargetException:getCause	()Ljava/lang/Throwable;
    //   297: athrow
    //   298: astore_1
    //   299: aload_1
    //   300: invokevirtual 117	java/lang/reflect/InvocationTargetException:getCause	()Ljava/lang/Throwable;
    //   303: athrow
    // Local variable table:
    //   start	length	slot	name	signature
    //   0	304	0	this	ygggyy
    //   0	304	1	paramContext	Context
    //   8	64	2	i	int
    //   12	60	3	j	int
    //   16	59	4	k	int
    //   21	57	5	m	int
    //   26	11	6	n	int
    //   3	280	7	localObject1	Object
    //   132	62	8	localObject2	Object
    // Exception table:
    //   from	to	target	type
    //   0	5	207	org/json/JSONException
    //   134	175	207	org/json/JSONException
    //   182	205	207	org/json/JSONException
    //   299	304	207	org/json/JSONException
    //   246	278	292	java/lang/reflect/InvocationTargetException
    //   134	175	298	java/lang/reflect/InvocationTargetException
  }
  
  public static int bp00700070pp0070pp0070p()
  {
    return 64;
  }
  
  public UserInfo b007000700070pp0070pp0070p()
  {
    UserInfo localUserInfo = this.bk006B006B006Bk006Bk006Bk;
    int i = bp00700070pp0070pp0070p();
    int j = bkkkk006B006Bk006Bk;
    int k = bp00700070pp0070pp0070p();
    int m = b006Bkkk006B006Bk006Bk;
    int n = b006B006B006B006Bk006Bk006Bk;
    int i1 = bp00700070pp0070pp0070p();
    switch (i1 * (bkkkk006B006Bk006Bk + i1) % b006Bkkk006B006Bk006Bk)
    {
    default: 
      bk006Bkk006B006Bk006Bk = bp00700070pp0070pp0070p();
      b006B006B006B006Bk006Bk006Bk = 40;
    }
    if ((i + j) * k % m != n)
    {
      bk006Bkk006B006Bk006Bk = bp00700070pp0070pp0070p();
      b006B006B006B006Bk006Bk006Bk = bp00700070pp0070pp0070p();
    }
    return localUserInfo;
  }
  
  public String b0070p0070pp007000700070pp(String paramString)
  {
    if ((bk006Bkk006B006Bk006Bk + bkkkk006B006Bk006Bk) * bk006Bkk006B006Bk006Bk % b006Bkkk006B006Bk006Bk != b006B006B006B006Bk006Bk006Bk)
    {
      bk006Bkk006B006Bk006Bk = 11;
      b006B006B006B006Bk006Bk006Bk = bp00700070pp0070pp0070p();
    }
    int i = bp00700070pp0070pp0070p();
    switch (i * (bkkkk006B006Bk006Bk + i) % b006Bkkk006B006Bk006Bk)
    {
    default: 
      bk006Bkk006B006Bk006Bk = bp00700070pp0070pp0070p();
      b006B006B006B006Bk006Bk006Bk = 60;
    }
    Object localObject = ppphhp.class.getMethod(uxxxxx.bb00620062bb0062b0062b0062("6L\006\007\017\020QR\f\r\025\026\020\021\031\032[\025\026\036\037\031\032\"#d", 'Ò', '\002'), new Class[] { String.class, Character.TYPE, Character.TYPE, Character.TYPE });
    try
    {
      localObject = ((Method)localObject).invoke(null, new Object[] { "\013\ty_i", Character.valueOf('.'), Character.valueOf('\034'), Character.valueOf('\000') });
      return Uri.encode(paramString, (String)localObject);
    }
    catch (InvocationTargetException paramString)
    {
      throw paramString.getCause();
    }
  }
  
  public String bppp0070p0070pp0070p(String paramString)
  {
    int i = bk006Bkk006B006Bk006Bk;
    switch (i * (bkkkk006B006Bk006Bk + i) % b006Bkkk006B006Bk006Bk)
    {
    default: 
      bk006Bkk006B006Bk006Bk = 11;
      b006B006B006B006Bk006Bk006Bk = bp00700070pp0070pp0070p();
    }
    i = bk006Bkk006B006Bk006Bk;
    switch (i * (bkkkk006B006Bk006Bk + i) % b006Bkkk006B006Bk006Bk)
    {
    default: 
      bk006Bkk006B006Bk006Bk = bp00700070pp0070pp0070p();
      b006B006B006B006Bk006Bk006Bk = 94;
    }
    paramString = ppphhp.class.getMethod(uxxxxx.bb00620062bb0062b0062b0062("dz45=>\001:;CD>?GH\nCDLMGHPQ\023", 'ª', '\000'), new Class[] { String.class, Character.TYPE, Character.TYPE, Character.TYPE });
    try
    {
      paramString = paramString.invoke(null, new Object[] { "\004\004\013\f{\016y", Character.valueOf('¨'), Character.valueOf('Ç'), Character.valueOf('\001') });
      return (String)paramString;
    }
    catch (InvocationTargetException paramString)
    {
      throw paramString.getCause();
    }
  }
}
