package uuuuuu;

import java.net.MalformedURLException;
import java.net.URL;
import java.util.Map;

public class ygyygy
{
  public static int b006B006B006B006B006Bkk006Bk = 1;
  public static int b006Bk006B006B006Bkk006Bk = 93;
  public static int bk006B006B006B006Bkk006Bk = 0;
  public static int bkkkkk006Bk006Bk = 2;
  private String b006B006Bk006B006Bkk006Bk;
  private Map<String, String> bk006Bk006B006Bkk006Bk;
  private String bkk006B006B006Bkk006Bk;
  
  public ygyygy() {}
  
  public static int b00700070p0070pppp0070p()
  {
    return 0;
  }
  
  public static int b0070p00700070pppp0070p()
  {
    return 2;
  }
  
  public static int bp0070p0070pppp0070p()
  {
    return 1;
  }
  
  public static int bpp00700070pppp0070p()
  {
    return 82;
  }
  
  /* Error */
  public String b0070007000700070pppp0070p(String paramString, int paramInt)
  {
    // Byte code:
    //   0: aload_0
    //   1: getfield 35	uuuuuu/ygyygy:bkk006B006B006Bkk006Bk	Ljava/lang/String;
    //   4: ifnull +106 -> 110
    //   7: aload_0
    //   8: getfield 35	uuuuuu/ygyygy:bkk006B006B006Bkk006Bk	Ljava/lang/String;
    //   11: astore 4
    //   13: ldc 37
    //   15: ldc 39
    //   17: bipush 103
    //   19: iconst_3
    //   20: invokestatic 45	xxxxxx/uxxxxx:bb00620062bb0062b0062b0062	(Ljava/lang/String;CC)Ljava/lang/String;
    //   23: iconst_4
    //   24: anewarray 47	java/lang/Class
    //   27: dup
    //   28: iconst_0
    //   29: ldc 49
    //   31: aastore
    //   32: dup
    //   33: iconst_1
    //   34: getstatic 55	java/lang/Character:TYPE	Ljava/lang/Class;
    //   37: aastore
    //   38: dup
    //   39: iconst_2
    //   40: getstatic 55	java/lang/Character:TYPE	Ljava/lang/Class;
    //   43: aastore
    //   44: dup
    //   45: iconst_3
    //   46: getstatic 55	java/lang/Character:TYPE	Ljava/lang/Class;
    //   49: aastore
    //   50: invokevirtual 59	java/lang/Class:getMethod	(Ljava/lang/String;[Ljava/lang/Class;)Ljava/lang/reflect/Method;
    //   53: astore 5
    //   55: aload 5
    //   57: aconst_null
    //   58: iconst_4
    //   59: anewarray 4	java/lang/Object
    //   62: dup
    //   63: iconst_0
    //   64: ldc 61
    //   66: aastore
    //   67: dup
    //   68: iconst_1
    //   69: sipush 134
    //   72: invokestatic 65	java/lang/Character:valueOf	(C)Ljava/lang/Character;
    //   75: aastore
    //   76: dup
    //   77: iconst_2
    //   78: sipush 170
    //   81: invokestatic 65	java/lang/Character:valueOf	(C)Ljava/lang/Character;
    //   84: aastore
    //   85: dup
    //   86: iconst_3
    //   87: iconst_2
    //   88: invokestatic 65	java/lang/Character:valueOf	(C)Ljava/lang/Character;
    //   91: aastore
    //   92: invokevirtual 71	java/lang/reflect/Method:invoke	(Ljava/lang/Object;[Ljava/lang/Object;)Ljava/lang/Object;
    //   95: astore 5
    //   97: aload 4
    //   99: aload 5
    //   101: checkcast 49	java/lang/String
    //   104: invokevirtual 75	java/lang/String:contains	(Ljava/lang/CharSequence;)Z
    //   107: ifne +25 -> 132
    //   110: new 77	java/lang/StringBuilder
    //   113: dup
    //   114: invokespecial 78	java/lang/StringBuilder:<init>	()V
    //   117: aload_0
    //   118: getfield 35	uuuuuu/ygyygy:bkk006B006B006Bkk006Bk	Ljava/lang/String;
    //   121: invokevirtual 82	java/lang/StringBuilder:append	(Ljava/lang/String;)Ljava/lang/StringBuilder;
    //   124: aload_1
    //   125: invokevirtual 82	java/lang/StringBuilder:append	(Ljava/lang/String;)Ljava/lang/StringBuilder;
    //   128: invokevirtual 86	java/lang/StringBuilder:toString	()Ljava/lang/String;
    //   131: areturn
    //   132: new 77	java/lang/StringBuilder
    //   135: dup
    //   136: invokespecial 78	java/lang/StringBuilder:<init>	()V
    //   139: astore 4
    //   141: aload_0
    //   142: getfield 35	uuuuuu/ygyygy:bkk006B006B006Bkk006Bk	Ljava/lang/String;
    //   145: astore 5
    //   147: getstatic 88	uuuuuu/ygyygy:b006Bk006B006B006Bkk006Bk	I
    //   150: getstatic 90	uuuuuu/ygyygy:b006B006B006B006B006Bkk006Bk	I
    //   153: iadd
    //   154: getstatic 88	uuuuuu/ygyygy:b006Bk006B006B006Bkk006Bk	I
    //   157: imul
    //   158: invokestatic 92	uuuuuu/ygyygy:b0070p00700070pppp0070p	()I
    //   161: irem
    //   162: getstatic 94	uuuuuu/ygyygy:bk006B006B006B006Bkk006Bk	I
    //   165: if_icmpeq +14 -> 179
    //   168: invokestatic 96	uuuuuu/ygyygy:bpp00700070pppp0070p	()I
    //   171: putstatic 88	uuuuuu/ygyygy:b006Bk006B006B006Bkk006Bk	I
    //   174: bipush 90
    //   176: putstatic 94	uuuuuu/ygyygy:bk006B006B006B006Bkk006Bk	I
    //   179: ldc 37
    //   181: ldc 98
    //   183: sipush 221
    //   186: iconst_5
    //   187: invokestatic 45	xxxxxx/uxxxxx:bb00620062bb0062b0062b0062	(Ljava/lang/String;CC)Ljava/lang/String;
    //   190: iconst_3
    //   191: anewarray 47	java/lang/Class
    //   194: dup
    //   195: iconst_0
    //   196: ldc 49
    //   198: aastore
    //   199: dup
    //   200: iconst_1
    //   201: getstatic 55	java/lang/Character:TYPE	Ljava/lang/Class;
    //   204: aastore
    //   205: dup
    //   206: iconst_2
    //   207: getstatic 55	java/lang/Character:TYPE	Ljava/lang/Class;
    //   210: aastore
    //   211: invokevirtual 59	java/lang/Class:getMethod	(Ljava/lang/String;[Ljava/lang/Class;)Ljava/lang/reflect/Method;
    //   214: astore 6
    //   216: aload 6
    //   218: aconst_null
    //   219: iconst_3
    //   220: anewarray 4	java/lang/Object
    //   223: dup
    //   224: iconst_0
    //   225: ldc 100
    //   227: aastore
    //   228: dup
    //   229: iconst_1
    //   230: sipush 214
    //   233: invokestatic 65	java/lang/Character:valueOf	(C)Ljava/lang/Character;
    //   236: aastore
    //   237: dup
    //   238: iconst_2
    //   239: iconst_1
    //   240: invokestatic 65	java/lang/Character:valueOf	(C)Ljava/lang/Character;
    //   243: aastore
    //   244: invokevirtual 71	java/lang/reflect/Method:invoke	(Ljava/lang/Object;[Ljava/lang/Object;)Ljava/lang/Object;
    //   247: astore 6
    //   249: aload 6
    //   251: checkcast 49	java/lang/String
    //   254: astore 6
    //   256: new 77	java/lang/StringBuilder
    //   259: dup
    //   260: invokespecial 78	java/lang/StringBuilder:<init>	()V
    //   263: astore 7
    //   265: getstatic 88	uuuuuu/ygyygy:b006Bk006B006B006Bkk006Bk	I
    //   268: istore_3
    //   269: iload_3
    //   270: getstatic 90	uuuuuu/ygyygy:b006B006B006B006B006Bkk006Bk	I
    //   273: iload_3
    //   274: iadd
    //   275: imul
    //   276: getstatic 102	uuuuuu/ygyygy:bkkkkk006Bk006Bk	I
    //   279: irem
    //   280: tableswitch	default:+20->300, 0:+30->310
    //   300: bipush 80
    //   302: putstatic 88	uuuuuu/ygyygy:b006Bk006B006B006Bkk006Bk	I
    //   305: bipush 43
    //   307: putstatic 94	uuuuuu/ygyygy:bk006B006B006B006Bkk006Bk	I
    //   310: ldc 37
    //   312: ldc 104
    //   314: bipush 121
    //   316: iconst_1
    //   317: invokestatic 45	xxxxxx/uxxxxx:bb00620062bb0062b0062b0062	(Ljava/lang/String;CC)Ljava/lang/String;
    //   320: iconst_3
    //   321: anewarray 47	java/lang/Class
    //   324: dup
    //   325: iconst_0
    //   326: ldc 49
    //   328: aastore
    //   329: dup
    //   330: iconst_1
    //   331: getstatic 55	java/lang/Character:TYPE	Ljava/lang/Class;
    //   334: aastore
    //   335: dup
    //   336: iconst_2
    //   337: getstatic 55	java/lang/Character:TYPE	Ljava/lang/Class;
    //   340: aastore
    //   341: invokevirtual 59	java/lang/Class:getMethod	(Ljava/lang/String;[Ljava/lang/Class;)Ljava/lang/reflect/Method;
    //   344: astore 8
    //   346: aload 8
    //   348: aconst_null
    //   349: iconst_3
    //   350: anewarray 4	java/lang/Object
    //   353: dup
    //   354: iconst_0
    //   355: ldc 106
    //   357: aastore
    //   358: dup
    //   359: iconst_1
    //   360: bipush 65
    //   362: invokestatic 65	java/lang/Character:valueOf	(C)Ljava/lang/Character;
    //   365: aastore
    //   366: dup
    //   367: iconst_2
    //   368: iconst_1
    //   369: invokestatic 65	java/lang/Character:valueOf	(C)Ljava/lang/Character;
    //   372: aastore
    //   373: invokevirtual 71	java/lang/reflect/Method:invoke	(Ljava/lang/Object;[Ljava/lang/Object;)Ljava/lang/Object;
    //   376: astore 8
    //   378: aload 4
    //   380: aload 5
    //   382: aload 6
    //   384: aload 7
    //   386: aload 8
    //   388: checkcast 49	java/lang/String
    //   391: invokevirtual 82	java/lang/StringBuilder:append	(Ljava/lang/String;)Ljava/lang/StringBuilder;
    //   394: iload_2
    //   395: invokevirtual 109	java/lang/StringBuilder:append	(I)Ljava/lang/StringBuilder;
    //   398: invokevirtual 86	java/lang/StringBuilder:toString	()Ljava/lang/String;
    //   401: invokevirtual 113	java/lang/String:replace	(Ljava/lang/CharSequence;Ljava/lang/CharSequence;)Ljava/lang/String;
    //   404: invokevirtual 82	java/lang/StringBuilder:append	(Ljava/lang/String;)Ljava/lang/StringBuilder;
    //   407: aload_1
    //   408: invokevirtual 82	java/lang/StringBuilder:append	(Ljava/lang/String;)Ljava/lang/StringBuilder;
    //   411: invokevirtual 86	java/lang/StringBuilder:toString	()Ljava/lang/String;
    //   414: areturn
    //   415: astore_1
    //   416: aload_1
    //   417: invokevirtual 117	java/lang/reflect/InvocationTargetException:getCause	()Ljava/lang/Throwable;
    //   420: athrow
    //   421: astore_1
    //   422: aload_1
    //   423: invokevirtual 117	java/lang/reflect/InvocationTargetException:getCause	()Ljava/lang/Throwable;
    //   426: athrow
    //   427: astore_1
    //   428: aload_1
    //   429: invokevirtual 117	java/lang/reflect/InvocationTargetException:getCause	()Ljava/lang/Throwable;
    //   432: athrow
    // Local variable table:
    //   start	length	slot	name	signature
    //   0	433	0	this	ygyygy
    //   0	433	1	paramString	String
    //   0	433	2	paramInt	int
    //   268	8	3	i	int
    //   11	368	4	localObject1	Object
    //   53	328	5	localObject2	Object
    //   214	169	6	localObject3	Object
    //   263	122	7	localStringBuilder	StringBuilder
    //   344	43	8	localObject4	Object
    // Exception table:
    //   from	to	target	type
    //   216	249	415	java/lang/reflect/InvocationTargetException
    //   55	97	421	java/lang/reflect/InvocationTargetException
    //   346	378	427	java/lang/reflect/InvocationTargetException
  }
  
  public String b00700070pp0070ppp0070p()
  {
    String str = this.bkk006B006B006Bkk006Bk;
    if ((b006Bk006B006B006Bkk006Bk + b006B006B006B006B006Bkk006Bk) * b006Bk006B006B006Bkk006Bk % bkkkkk006Bk006Bk != bk006B006B006B006Bkk006Bk)
    {
      b006Bk006B006B006Bkk006Bk = bpp00700070pppp0070p();
      bk006B006B006B006Bkk006Bk = bpp00700070pppp0070p();
      if ((bpp00700070pppp0070p() + b006B006B006B006B006Bkk006Bk) * bpp00700070pppp0070p() % bkkkkk006Bk006Bk != bk006B006B006B006Bkk006Bk)
      {
        b006Bk006B006B006Bkk006Bk = 77;
        bk006B006B006B006Bkk006Bk = 73;
      }
    }
    return str;
  }
  
  public ygyygy b0070p0070p0070ppp0070p(String paramString)
  {
    if ((b006Bk006B006B006Bkk006Bk + b006B006B006B006B006Bkk006Bk) * b006Bk006B006B006Bkk006Bk % bkkkkk006Bk006Bk != bk006B006B006B006Bkk006Bk)
    {
      if ((b006Bk006B006B006Bkk006Bk + b006B006B006B006B006Bkk006Bk) * b006Bk006B006B006Bkk006Bk % bkkkkk006Bk006Bk != bk006B006B006B006Bkk006Bk)
      {
        b006Bk006B006B006Bkk006Bk = bpp00700070pppp0070p();
        bk006B006B006B006Bkk006Bk = bpp00700070pppp0070p();
      }
      b006Bk006B006B006Bkk006Bk = 37;
      bk006B006B006B006Bkk006Bk = bpp00700070pppp0070p();
    }
    this.b006B006Bk006B006Bkk006Bk = paramString;
    return this;
  }
  
  public String b0070ppp0070ppp0070p()
  {
    String str = this.b006B006Bk006B006Bkk006Bk;
    if ((b006Bk006B006B006Bkk006Bk + b006B006B006B006B006Bkk006Bk) * b006Bk006B006B006Bkk006Bk % bkkkkk006Bk006Bk != bk006B006B006B006Bkk006Bk)
    {
      b006Bk006B006B006Bkk006Bk = 66;
      int i = b006Bk006B006B006Bkk006Bk;
      switch (i * (b006B006B006B006B006Bkk006Bk + i) % bkkkkk006Bk006Bk)
      {
      default: 
        b006Bk006B006B006Bkk006Bk = 92;
        bk006B006B006B006Bkk006Bk = bpp00700070pppp0070p();
      }
      bk006B006B006B006Bkk006Bk = 63;
    }
    return str;
  }
  
  public Map<String, String> bp007000700070pppp0070p()
  {
    Map localMap = this.bk006Bk006B006Bkk006Bk;
    int i = b006Bk006B006B006Bkk006Bk;
    switch (i * (bp0070p0070pppp0070p() + i) % bkkkkk006Bk006Bk)
    {
    default: 
      b006Bk006B006B006Bkk006Bk = 35;
      bk006B006B006B006Bkk006Bk = bpp00700070pppp0070p();
      i = b006Bk006B006B006Bkk006Bk;
      switch (i * (b006B006B006B006B006Bkk006Bk + i) % bkkkkk006Bk006Bk)
      {
      default: 
        b006Bk006B006B006Bkk006Bk = 24;
        bk006B006B006B006Bkk006Bk = 63;
      }
      break;
    }
    return localMap;
  }
  
  public ygyygy bp00700070p0070ppp0070p(String paramString)
  {
    int i = b006Bk006B006B006Bkk006Bk;
    switch (i * (b006B006B006B006B006Bkk006Bk + i) % bkkkkk006Bk006Bk)
    {
    default: 
      if ((b006Bk006B006B006Bkk006Bk + b006B006B006B006B006Bkk006Bk) * b006Bk006B006B006Bkk006Bk % bkkkkk006Bk006Bk != b00700070p0070pppp0070p())
      {
        b006Bk006B006B006Bkk006Bk = 30;
        bk006B006B006B006Bkk006Bk = bpp00700070pppp0070p();
      }
      b006Bk006B006B006Bkk006Bk = bpp00700070pppp0070p();
      bk006B006B006B006Bkk006Bk = bpp00700070pppp0070p();
    }
    this.bkk006B006B006Bkk006Bk = paramString;
    return this;
  }
  
  public String bp0070pp0070ppp0070p()
  {
    int i = b006Bk006B006B006Bkk006Bk;
    switch (i * (bp0070p0070pppp0070p() + i) % bkkkkk006Bk006Bk)
    {
    default: 
      b006Bk006B006B006Bkk006Bk = bpp00700070pppp0070p();
      bk006B006B006B006Bkk006Bk = bpp00700070pppp0070p();
    }
    try
    {
      String str1 = new URL(this.bkk006B006B006Bkk006Bk).getProtocol();
      i = b006Bk006B006B006Bkk006Bk;
      switch (i * (b006B006B006B006B006Bkk006Bk + i) % bkkkkk006Bk006Bk)
      {
      default: 
        b006Bk006B006B006Bkk006Bk = bpp00700070pppp0070p();
        bk006B006B006B006Bkk006Bk = 42;
      }
      return str1;
    }
    catch (MalformedURLException localMalformedURLException)
    {
      for (;;)
      {
        String str2 = "";
      }
    }
  }
  
  public ygyygy bpp0070p0070ppp0070p(Map<String, String> paramMap)
  {
    this.bk006Bk006B006Bkk006Bk = paramMap;
    if ((b006Bk006B006B006Bkk006Bk + b006B006B006B006B006Bkk006Bk) * b006Bk006B006B006Bkk006Bk % bkkkkk006Bk006Bk != bk006B006B006B006Bkk006Bk)
    {
      b006Bk006B006B006Bkk006Bk = 11;
      bk006B006B006B006Bkk006Bk = 92;
    }
    return this;
  }
  
  public String bpppp0070ppp0070p()
  {
    try
    {
      String str1 = new URL(this.bkk006B006B006Bkk006Bk).getHost();
      return str1;
    }
    catch (MalformedURLException localMalformedURLException)
    {
      String str2 = "";
      int i = bpp00700070pppp0070p();
      int j = bp0070p0070pppp0070p();
      if ((b006Bk006B006B006Bkk006Bk + b006B006B006B006B006Bkk006Bk) * b006Bk006B006B006Bkk006Bk % bkkkkk006Bk006Bk != bk006B006B006B006Bkk006Bk)
      {
        b006Bk006B006B006Bkk006Bk = bpp00700070pppp0070p();
        bk006B006B006B006Bkk006Bk = bpp00700070pppp0070p();
      }
      switch (i * (j + i) % b0070p00700070pppp0070p())
      {
      }
      b006Bk006B006B006Bkk006Bk = bpp00700070pppp0070p();
      bk006B006B006B006Bkk006Bk = bpp00700070pppp0070p();
    }
    return "";
  }
  
  public boolean equals(Object paramObject)
  {
    if (this == paramObject) {}
    do
    {
      return true;
      if ((paramObject == null) || (getClass() != paramObject.getClass())) {
        break;
      }
      paramObject = (ygyygy)paramObject;
      if ((b006Bk006B006B006Bkk006Bk + b006B006B006B006B006Bkk006Bk) * b006Bk006B006B006Bkk006Bk % bkkkkk006Bk006Bk != bk006B006B006B006Bkk006Bk)
      {
        b006Bk006B006B006Bkk006Bk = bpp00700070pppp0070p();
        bk006B006B006B006Bkk006Bk = bpp00700070pppp0070p();
      }
      if (this.bkk006B006B006Bkk006Bk != null) {
        if (!this.bkk006B006B006Bkk006Bk.equals(paramObject.bkk006B006B006Bkk006Bk)) {
          break;
        }
      }
      while (paramObject.bkk006B006B006Bkk006Bk == null)
      {
        if (this.b006B006Bk006B006Bkk006Bk != null) {
          if (!this.b006B006Bk006B006Bkk006Bk.equals(paramObject.b006B006Bk006B006Bkk006Bk)) {
            break label182;
          }
        }
        while (paramObject.b006B006Bk006B006Bkk006Bk == null)
        {
          if (this.bk006Bk006B006Bkk006Bk == null) {
            break;
          }
          return this.bk006Bk006B006Bkk006Bk.equals(paramObject.bk006Bk006B006Bkk006Bk);
        }
        return false;
      }
      if ((b006Bk006B006B006Bkk006Bk + b006B006B006B006B006Bkk006Bk) * b006Bk006B006B006Bkk006Bk % bkkkkk006Bk006Bk == bk006B006B006B006Bkk006Bk) {
        break;
      }
      b006Bk006B006B006Bkk006Bk = 45;
      bk006B006B006B006Bkk006Bk = bpp00700070pppp0070p();
      return false;
    } while (paramObject.bk006Bk006B006Bkk006Bk == null);
    return false;
    label182:
    return false;
  }
  
  public int hashCode()
  {
    int k = 0;
    int i;
    if (this.bkk006B006B006Bkk006Bk != null)
    {
      i = this.bkk006B006B006Bkk006Bk.hashCode();
      if (this.b006B006Bk006B006Bkk006Bk == null) {
        break label143;
      }
    }
    label143:
    for (int j = this.b006B006Bk006B006Bkk006Bk.hashCode();; j = 0)
    {
      if (this.bk006Bk006B006Bkk006Bk != null) {
        k = this.bk006Bk006B006Bkk006Bk.hashCode();
      }
      return (i * 31 + j) * 31 + k;
      if ((b006Bk006B006B006Bkk006Bk + bp0070p0070pppp0070p()) * b006Bk006B006B006Bkk006Bk % bkkkkk006Bk006Bk != b00700070p0070pppp0070p())
      {
        i = b006Bk006B006B006Bkk006Bk;
        switch (i * (b006B006B006B006B006Bkk006Bk + i) % bkkkkk006Bk006Bk)
        {
        default: 
          b006Bk006B006B006Bkk006Bk = 75;
          bk006B006B006B006Bkk006Bk = bpp00700070pppp0070p();
        }
        b006Bk006B006B006Bkk006Bk = 84;
        bk006B006B006B006Bkk006Bk = bpp00700070pppp0070p();
      }
      i = 0;
      break;
    }
  }
}
