package uuuuuu;

import android.content.BroadcastReceiver;
import android.content.IntentFilter;
import android.os.Bundle;
import android.support.annotation.NonNull;
import com.db.pwcc.dbmobile.foundation.data.manager.broadcasting.ModelUpdatedBroadcastReceiver;
import com.db.pwcc.dbmobile.model.error.DbError;

public class yyhyyh
{
  public static int b00700070p0070p00700070pp = 1;
  public static int b0070pp0070p00700070pp = 2;
  public static int bp0070p0070p00700070pp = 0;
  public static int bppp0070p00700070pp = 76;
  private boolean b007000700070pp00700070pp;
  private final hhyyyh b0070p0070pp00700070pp;
  public ModelUpdatedBroadcastReceiver bp00700070pp00700070pp;
  private final String bpp0070pp00700070pp;
  
  public yyhyyh(@NonNull hhyyyh paramHhyyyh, @NonNull String paramString)
  {
    this.b0070p0070pp00700070pp = paramHhyyyh;
    this.bpp0070pp00700070pp = paramString;
    boooo006Fooooo();
  }
  
  public static int b006F006F006F006Foooooo()
  {
    return 2;
  }
  
  public static int b006Fo006F006Foooooo()
  {
    return 34;
  }
  
  public static int bo006F006F006Foooooo()
  {
    return 1;
  }
  
  private void boooo006Fooooo()
  {
    int i = bppp0070p00700070pp;
    switch (i * (bo006F006F006Foooooo() + i) % b0070pp0070p00700070pp)
    {
    default: 
      if ((bppp0070p00700070pp + b00700070p0070p00700070pp) * bppp0070p00700070pp % b0070pp0070p00700070pp != bp0070p0070p00700070pp)
      {
        bppp0070p00700070pp = 53;
        bp0070p0070p00700070pp = 48;
      }
      bppp0070p00700070pp = b006Fo006F006Foooooo();
      b0070pp0070p00700070pp = 53;
    }
    this.bp00700070pp00700070pp = new ModelUpdatedBroadcastReceiver()
    {
      public static int b00620062006200620062bb = 21;
      public static int b00620062bbb0062b = 1;
      public static int bb0062bbb0062b = 2;
      public static int bbbbbb0062b;
      
      public static int b0062b0062bb0062b()
      {
        return 0;
      }
      
      public static int b0062bbbb0062b()
      {
        return 1;
      }
      
      public static int bbb0062bb0062b()
      {
        return 9;
      }
      
      public void onDataModelUpdateFailed(String paramAnonymousString, DbError paramAnonymousDbError, Bundle paramAnonymousBundle)
      {
        yyhyyh.this.b006Fooo006Fooooo(paramAnonymousString, paramAnonymousBundle);
        if ((b00620062006200620062bb + b0062bbbb0062b()) * b00620062006200620062bb % bb0062bbb0062b != bbbbbb0062b)
        {
          b00620062006200620062bb = 25;
          if ((b00620062006200620062bb + b00620062bbb0062b) * b00620062006200620062bb % bb0062bbb0062b != bbbbbb0062b)
          {
            b00620062006200620062bb = 49;
            bbbbbb0062b = bbb0062bb0062b();
          }
          bbbbbb0062b = 49;
        }
      }
      
      public void onDataModelUpdated(String paramAnonymousString, Bundle paramAnonymousBundle)
      {
        yyhyyh localYyhyyh = yyhyyh.this;
        int i = b00620062006200620062bb;
        switch (i * (b0062bbbb0062b() + i) % bb0062bbb0062b)
        {
        default: 
          b00620062006200620062bb = 25;
          bbbbbb0062b = 47;
        }
        if ((b00620062006200620062bb + b00620062bbb0062b) * b00620062006200620062bb % bb0062bbb0062b != bbbbbb0062b)
        {
          b00620062006200620062bb = 82;
          bbbbbb0062b = 6;
        }
        localYyhyyh.b006Fooo006Fooooo(paramAnonymousString, paramAnonymousBundle);
      }
      
      /* Error */
      public void onReceive(android.content.Context paramAnonymousContext, android.content.Intent paramAnonymousIntent)
      {
        // Byte code:
        //   0: getstatic 37	uuuuuu/yyhyyh$1:b00620062006200620062bb	I
        //   3: getstatic 45	uuuuuu/yyhyyh$1:b00620062bbb0062b	I
        //   6: iadd
        //   7: getstatic 37	uuuuuu/yyhyyh$1:b00620062006200620062bb	I
        //   10: imul
        //   11: getstatic 41	uuuuuu/yyhyyh$1:bb0062bbb0062b	I
        //   14: irem
        //   15: invokestatic 54	uuuuuu/yyhyyh$1:b0062b0062bb0062b	()I
        //   18: if_icmpeq +48 -> 66
        //   21: invokestatic 47	uuuuuu/yyhyyh$1:bbb0062bb0062b	()I
        //   24: putstatic 37	uuuuuu/yyhyyh$1:b00620062006200620062bb	I
        //   27: invokestatic 47	uuuuuu/yyhyyh$1:bbb0062bb0062b	()I
        //   30: putstatic 43	uuuuuu/yyhyyh$1:bbbbbb0062b	I
        //   33: getstatic 37	uuuuuu/yyhyyh$1:b00620062006200620062bb	I
        //   36: getstatic 45	uuuuuu/yyhyyh$1:b00620062bbb0062b	I
        //   39: iadd
        //   40: getstatic 37	uuuuuu/yyhyyh$1:b00620062006200620062bb	I
        //   43: imul
        //   44: getstatic 41	uuuuuu/yyhyyh$1:bb0062bbb0062b	I
        //   47: irem
        //   48: invokestatic 54	uuuuuu/yyhyyh$1:b0062b0062bb0062b	()I
        //   51: if_icmpeq +15 -> 66
        //   54: invokestatic 47	uuuuuu/yyhyyh$1:bbb0062bb0062b	()I
        //   57: putstatic 37	uuuuuu/yyhyyh$1:b00620062006200620062bb	I
        //   60: invokestatic 47	uuuuuu/yyhyyh$1:bbb0062bb0062b	()I
        //   63: putstatic 43	uuuuuu/yyhyyh$1:bbbbbb0062b	I
        //   66: ldc 56
        //   68: ldc 58
        //   70: sipush 211
        //   73: iconst_2
        //   74: iconst_1
        //   75: invokestatic 64	xxxxxx/uxxxxx:bbbb0062b0062b0062b0062	(Ljava/lang/String;CCC)Ljava/lang/String;
        //   78: iconst_1
        //   79: anewarray 66	java/lang/Class
        //   82: dup
        //   83: iconst_0
        //   84: ldc 68
        //   86: aastore
        //   87: invokevirtual 72	java/lang/Class:getMethod	(Ljava/lang/String;[Ljava/lang/Class;)Ljava/lang/reflect/Method;
        //   90: astore_3
        //   91: aload_3
        //   92: aconst_null
        //   93: iconst_1
        //   94: anewarray 74	java/lang/Object
        //   97: dup
        //   98: iconst_0
        //   99: aload_1
        //   100: aastore
        //   101: invokevirtual 80	java/lang/reflect/Method:invoke	(Ljava/lang/Object;[Ljava/lang/Object;)Ljava/lang/Object;
        //   104: pop
        //   105: ldc 82
        //   107: ldc 84
        //   109: sipush 247
        //   112: iconst_2
        //   113: invokestatic 88	xxxxxx/uxxxxx:bb00620062bb0062b0062b0062	(Ljava/lang/String;CC)Ljava/lang/String;
        //   116: iconst_1
        //   117: anewarray 66	java/lang/Class
        //   120: dup
        //   121: iconst_0
        //   122: ldc 68
        //   124: aastore
        //   125: invokevirtual 72	java/lang/Class:getMethod	(Ljava/lang/String;[Ljava/lang/Class;)Ljava/lang/reflect/Method;
        //   128: astore_3
        //   129: aload_3
        //   130: aconst_null
        //   131: iconst_1
        //   132: anewarray 74	java/lang/Object
        //   135: dup
        //   136: iconst_0
        //   137: aload_1
        //   138: aastore
        //   139: invokevirtual 80	java/lang/reflect/Method:invoke	(Ljava/lang/Object;[Ljava/lang/Object;)Ljava/lang/Object;
        //   142: pop
        //   143: aload_1
        //   144: invokestatic 94	uuuuuu/uppupu:b0072r0072r00720072rr0072	(Landroid/content/Context;)V
        //   147: aload_0
        //   148: aload_1
        //   149: aload_2
        //   150: invokespecial 96	com/db/pwcc/dbmobile/foundation/data/manager/broadcasting/ModelUpdatedBroadcastReceiver:onReceive	(Landroid/content/Context;Landroid/content/Intent;)V
        //   153: return
        //   154: astore_1
        //   155: aload_1
        //   156: invokevirtual 100	java/lang/reflect/InvocationTargetException:getCause	()Ljava/lang/Throwable;
        //   159: athrow
        //   160: astore_1
        //   161: aload_1
        //   162: invokevirtual 100	java/lang/reflect/InvocationTargetException:getCause	()Ljava/lang/Throwable;
        //   165: athrow
        // Local variable table:
        //   start	length	slot	name	signature
        //   0	166	0	this	1
        //   0	166	1	paramAnonymousContext	android.content.Context
        //   0	166	2	paramAnonymousIntent	android.content.Intent
        //   90	40	3	localMethod	java.lang.reflect.Method
        // Exception table:
        //   from	to	target	type
        //   91	105	154	java/lang/reflect/InvocationTargetException
        //   129	143	160	java/lang/reflect/InvocationTargetException
      }
    };
  }
  
  public void b006F006Foo006Fooooo()
  {
    boolean bool1;
    if ((this.bp00700070pp00700070pp != null) && (this.b0070p0070pp00700070pp != null))
    {
      bool1 = this.b0070p0070pp00700070pp.unregisterBroadcastReceiver(this.bp00700070pp00700070pp);
      int i = bppp0070p00700070pp;
      switch (i * (b00700070p0070p00700070pp + i) % b0070pp0070p00700070pp)
      {
      default: 
        bppp0070p00700070pp = 24;
        bp0070p0070p00700070pp = 14;
      }
      if (!bool1) {
        bool1 = true;
      }
    }
    for (;;)
    {
      this.b007000700070pp00700070pp = bool1;
      return;
      boolean bool2 = false;
      bool1 = bool2;
      if ((bppp0070p00700070pp + b00700070p0070p00700070pp) * bppp0070p00700070pp % b0070pp0070p00700070pp != bp0070p0070p00700070pp)
      {
        bppp0070p00700070pp = 59;
        bp0070p0070p00700070pp = b006Fo006F006Foooooo();
        bool1 = bool2;
      }
    }
  }
  
  /* Error */
  public void b006Fooo006Fooooo(String paramString, Bundle paramBundle)
  {
    // Byte code:
    //   0: aload_0
    //   1: getfield 35	uuuuuu/yyhyyh:b0070p0070pp00700070pp	Luuuuuu/yyhyyh$hhyyyh;
    //   4: invokeinterface 77 1 0
    //   9: getstatic 48	uuuuuu/yyhyyh:bppp0070p00700070pp	I
    //   12: istore_3
    //   13: iload_3
    //   14: invokestatic 50	uuuuuu/yyhyyh:bo006F006F006Foooooo	()I
    //   17: iload_3
    //   18: iadd
    //   19: imul
    //   20: invokestatic 79	uuuuuu/yyhyyh:b006F006F006F006Foooooo	()I
    //   23: irem
    //   24: tableswitch	default:+20->44, 0:+31->55
    //   44: bipush 92
    //   46: putstatic 48	uuuuuu/yyhyyh:bppp0070p00700070pp	I
    //   49: invokestatic 58	uuuuuu/yyhyyh:b006Fo006F006Foooooo	()I
    //   52: putstatic 56	uuuuuu/yyhyyh:bp0070p0070p00700070pp	I
    //   55: ldc 81
    //   57: ldc 83
    //   59: bipush 56
    //   61: sipush 233
    //   64: iconst_2
    //   65: invokestatic 89	xxxxxx/uxxxxx:bbbb0062b0062b0062b0062	(Ljava/lang/String;CCC)Ljava/lang/String;
    //   68: iconst_3
    //   69: anewarray 91	java/lang/Class
    //   72: dup
    //   73: iconst_0
    //   74: ldc 93
    //   76: aastore
    //   77: dup
    //   78: iconst_1
    //   79: getstatic 99	java/lang/Character:TYPE	Ljava/lang/Class;
    //   82: aastore
    //   83: dup
    //   84: iconst_2
    //   85: getstatic 99	java/lang/Character:TYPE	Ljava/lang/Class;
    //   88: aastore
    //   89: invokevirtual 103	java/lang/Class:getMethod	(Ljava/lang/String;[Ljava/lang/Class;)Ljava/lang/reflect/Method;
    //   92: astore 4
    //   94: aload 4
    //   96: aconst_null
    //   97: iconst_3
    //   98: anewarray 4	java/lang/Object
    //   101: dup
    //   102: iconst_0
    //   103: ldc 105
    //   105: aastore
    //   106: dup
    //   107: iconst_1
    //   108: sipush 152
    //   111: invokestatic 109	java/lang/Character:valueOf	(C)Ljava/lang/Character;
    //   114: aastore
    //   115: dup
    //   116: iconst_2
    //   117: iconst_3
    //   118: invokestatic 109	java/lang/Character:valueOf	(C)Ljava/lang/Character;
    //   121: aastore
    //   122: invokevirtual 115	java/lang/reflect/Method:invoke	(Ljava/lang/Object;[Ljava/lang/Object;)Ljava/lang/Object;
    //   125: astore 4
    //   127: aload 4
    //   129: checkcast 93	java/lang/String
    //   132: aload_1
    //   133: invokevirtual 119	java/lang/String:equals	(Ljava/lang/Object;)Z
    //   136: ifeq +224 -> 360
    //   139: aload_0
    //   140: getfield 37	uuuuuu/yyhyyh:bpp0070pp00700070pp	Ljava/lang/String;
    //   143: astore_1
    //   144: getstatic 48	uuuuuu/yyhyyh:bppp0070p00700070pp	I
    //   147: istore_3
    //   148: iload_3
    //   149: getstatic 54	uuuuuu/yyhyyh:b00700070p0070p00700070pp	I
    //   152: iload_3
    //   153: iadd
    //   154: imul
    //   155: getstatic 52	uuuuuu/yyhyyh:b0070pp0070p00700070pp	I
    //   158: irem
    //   159: tableswitch	default:+17->176, 0:+28->187
    //   176: invokestatic 58	uuuuuu/yyhyyh:b006Fo006F006Foooooo	()I
    //   179: putstatic 48	uuuuuu/yyhyyh:bppp0070p00700070pp	I
    //   182: bipush 18
    //   184: putstatic 56	uuuuuu/yyhyyh:bp0070p0070p00700070pp	I
    //   187: ldc 81
    //   189: ldc 121
    //   191: bipush 105
    //   193: bipush 56
    //   195: iconst_3
    //   196: invokestatic 89	xxxxxx/uxxxxx:bbbb0062b0062b0062b0062	(Ljava/lang/String;CCC)Ljava/lang/String;
    //   199: iconst_3
    //   200: anewarray 91	java/lang/Class
    //   203: dup
    //   204: iconst_0
    //   205: ldc 93
    //   207: aastore
    //   208: dup
    //   209: iconst_1
    //   210: getstatic 99	java/lang/Character:TYPE	Ljava/lang/Class;
    //   213: aastore
    //   214: dup
    //   215: iconst_2
    //   216: getstatic 99	java/lang/Character:TYPE	Ljava/lang/Class;
    //   219: aastore
    //   220: invokevirtual 103	java/lang/Class:getMethod	(Ljava/lang/String;[Ljava/lang/Class;)Ljava/lang/reflect/Method;
    //   223: astore 4
    //   225: aload 4
    //   227: aconst_null
    //   228: iconst_3
    //   229: anewarray 4	java/lang/Object
    //   232: dup
    //   233: iconst_0
    //   234: ldc 123
    //   236: aastore
    //   237: dup
    //   238: iconst_1
    //   239: bipush 121
    //   241: invokestatic 109	java/lang/Character:valueOf	(C)Ljava/lang/Character;
    //   244: aastore
    //   245: dup
    //   246: iconst_2
    //   247: iconst_5
    //   248: invokestatic 109	java/lang/Character:valueOf	(C)Ljava/lang/Character;
    //   251: aastore
    //   252: invokevirtual 115	java/lang/reflect/Method:invoke	(Ljava/lang/Object;[Ljava/lang/Object;)Ljava/lang/Object;
    //   255: astore 4
    //   257: aload_1
    //   258: aload_2
    //   259: aload 4
    //   261: checkcast 93	java/lang/String
    //   264: invokevirtual 129	android/os/Bundle:getString	(Ljava/lang/String;)Ljava/lang/String;
    //   267: invokevirtual 119	java/lang/String:equals	(Ljava/lang/Object;)Z
    //   270: ifeq +90 -> 360
    //   273: ldc 81
    //   275: ldc -125
    //   277: sipush 162
    //   280: iconst_4
    //   281: invokestatic 135	xxxxxx/uxxxxx:bb00620062bb0062b0062b0062	(Ljava/lang/String;CC)Ljava/lang/String;
    //   284: iconst_3
    //   285: anewarray 91	java/lang/Class
    //   288: dup
    //   289: iconst_0
    //   290: ldc 93
    //   292: aastore
    //   293: dup
    //   294: iconst_1
    //   295: getstatic 99	java/lang/Character:TYPE	Ljava/lang/Class;
    //   298: aastore
    //   299: dup
    //   300: iconst_2
    //   301: getstatic 99	java/lang/Character:TYPE	Ljava/lang/Class;
    //   304: aastore
    //   305: invokevirtual 103	java/lang/Class:getMethod	(Ljava/lang/String;[Ljava/lang/Class;)Ljava/lang/reflect/Method;
    //   308: astore_1
    //   309: aload_1
    //   310: aconst_null
    //   311: iconst_3
    //   312: anewarray 4	java/lang/Object
    //   315: dup
    //   316: iconst_0
    //   317: ldc -119
    //   319: aastore
    //   320: dup
    //   321: iconst_1
    //   322: sipush 248
    //   325: invokestatic 109	java/lang/Character:valueOf	(C)Ljava/lang/Character;
    //   328: aastore
    //   329: dup
    //   330: iconst_2
    //   331: iconst_5
    //   332: invokestatic 109	java/lang/Character:valueOf	(C)Ljava/lang/Character;
    //   335: aastore
    //   336: invokevirtual 115	java/lang/reflect/Method:invoke	(Ljava/lang/Object;[Ljava/lang/Object;)Ljava/lang/Object;
    //   339: astore_1
    //   340: aload_2
    //   341: aload_1
    //   342: checkcast 93	java/lang/String
    //   345: invokevirtual 141	android/os/Bundle:containsKey	(Ljava/lang/String;)Z
    //   348: ifeq +12 -> 360
    //   351: aload_0
    //   352: getfield 35	uuuuuu/yyhyyh:b0070p0070pp00700070pp	Luuuuuu/yyhyyh$hhyyyh;
    //   355: invokeinterface 144 1 0
    //   360: return
    //   361: astore_1
    //   362: aload_1
    //   363: invokevirtual 148	java/lang/reflect/InvocationTargetException:getCause	()Ljava/lang/Throwable;
    //   366: athrow
    //   367: astore_1
    //   368: aload_1
    //   369: invokevirtual 148	java/lang/reflect/InvocationTargetException:getCause	()Ljava/lang/Throwable;
    //   372: athrow
    //   373: astore_1
    //   374: aload_1
    //   375: invokevirtual 148	java/lang/reflect/InvocationTargetException:getCause	()Ljava/lang/Throwable;
    //   378: athrow
    // Local variable table:
    //   start	length	slot	name	signature
    //   0	379	0	this	yyhyyh
    //   0	379	1	paramString	String
    //   0	379	2	paramBundle	Bundle
    //   12	143	3	i	int
    //   92	168	4	localObject	Object
    // Exception table:
    //   from	to	target	type
    //   309	340	361	java/lang/reflect/InvocationTargetException
    //   225	257	367	java/lang/reflect/InvocationTargetException
    //   94	127	373	java/lang/reflect/InvocationTargetException
  }
  
  public void bo006Foo006Fooooo()
  {
    if (!this.b007000700070pp00700070pp)
    {
      int i = bppp0070p00700070pp;
      switch (i * (b00700070p0070p00700070pp + i) % b0070pp0070p00700070pp)
      {
      default: 
        bppp0070p00700070pp = b006Fo006F006Foooooo();
        bp0070p0070p00700070pp = 88;
      }
      this.b007000700070pp00700070pp = this.b0070p0070pp00700070pp.registerBroadcastReceiver(this.bp00700070pp00700070pp, ModelUpdatedBroadcastReceiver.makeModelUpdatedIntentFilter());
    }
  }
  
  public static abstract interface hhyyyh
  {
    public abstract void onDataReceived();
    
    public abstract void onMbaProductDeleteFinished();
    
    public abstract boolean registerBroadcastReceiver(BroadcastReceiver paramBroadcastReceiver, IntentFilter paramIntentFilter);
    
    public abstract boolean unregisterBroadcastReceiver(BroadcastReceiver paramBroadcastReceiver);
  }
}
