package uuuuuu;

import com.db.pwcc.dbmobile.secure.preferences.SharedPreferencesHelper;
import javax.inject.Inject;

public class yyttty
  implements vvvpvv.pppvvv
{
  public static int b00780078xx0078xxx0078 = 1;
  public static int b0078xxx0078xxx0078 = 68;
  public static int bx0078xx0078xxx0078 = 0;
  public static int bxx0078x0078xxx0078 = 2;
  @Inject
  public SharedPreferencesHelper b0078007800780078xxxx0078;
  public vvvpvv bxxxx0078xxx0078;
  
  public yyttty()
  {
    tttyyt.bq0071qqqqq007100710071().bp007000700070pppppp(this);
    this.bxxxx0078xxx0078 = new lolloo();
  }
  
  public static int b00710071qqq00710071q00710071()
  {
    return 90;
  }
  
  public static int b0071qqqq00710071q00710071()
  {
    return 2;
  }
  
  public static int bq0071qqq00710071q00710071()
  {
    return 1;
  }
  
  public static int bqq0071qq00710071q00710071()
  {
    return 0;
  }
  
  /* Error */
  public void b0070p00700070pp007000700070p()
  {
    // Byte code:
    //   0: aload_0
    //   1: getfield 52	uuuuuu/yyttty:b0078007800780078xxxx0078	Lcom/db/pwcc/dbmobile/secure/preferences/SharedPreferencesHelper;
    //   4: astore_3
    //   5: getstatic 54	uuuuuu/yyttty:b0078xxx0078xxx0078	I
    //   8: istore_1
    //   9: iload_1
    //   10: getstatic 56	uuuuuu/yyttty:b00780078xx0078xxx0078	I
    //   13: iload_1
    //   14: iadd
    //   15: imul
    //   16: getstatic 58	uuuuuu/yyttty:bxx0078x0078xxx0078	I
    //   19: irem
    //   20: tableswitch	default:+20->40, 0:+287->307
    //   40: ldc 2
    //   42: ldc 60
    //   44: sipush 214
    //   47: iconst_1
    //   48: invokestatic 66	xxxxxx/uxxxxx:bb00620062bb0062b0062b0062	(Ljava/lang/String;CC)Ljava/lang/String;
    //   51: iconst_0
    //   52: anewarray 68	java/lang/Class
    //   55: invokevirtual 72	java/lang/Class:getMethod	(Ljava/lang/String;[Ljava/lang/Class;)Ljava/lang/reflect/Method;
    //   58: astore 4
    //   60: aload 4
    //   62: aconst_null
    //   63: iconst_0
    //   64: anewarray 4	java/lang/Object
    //   67: invokevirtual 78	java/lang/reflect/Method:invoke	(Ljava/lang/Object;[Ljava/lang/Object;)Ljava/lang/Object;
    //   70: astore 4
    //   72: aload 4
    //   74: checkcast 80	java/lang/Integer
    //   77: invokevirtual 83	java/lang/Integer:intValue	()I
    //   80: putstatic 54	uuuuuu/yyttty:b0078xxx0078xxx0078	I
    //   83: ldc 2
    //   85: ldc 85
    //   87: bipush 22
    //   89: iconst_4
    //   90: invokestatic 66	xxxxxx/uxxxxx:bb00620062bb0062b0062b0062	(Ljava/lang/String;CC)Ljava/lang/String;
    //   93: iconst_0
    //   94: anewarray 68	java/lang/Class
    //   97: invokevirtual 72	java/lang/Class:getMethod	(Ljava/lang/String;[Ljava/lang/Class;)Ljava/lang/reflect/Method;
    //   100: astore 4
    //   102: aload 4
    //   104: aconst_null
    //   105: iconst_0
    //   106: anewarray 4	java/lang/Object
    //   109: invokevirtual 78	java/lang/reflect/Method:invoke	(Ljava/lang/Object;[Ljava/lang/Object;)Ljava/lang/Object;
    //   112: astore 4
    //   114: aload 4
    //   116: checkcast 80	java/lang/Integer
    //   119: invokevirtual 83	java/lang/Integer:intValue	()I
    //   122: istore_1
    //   123: ldc 2
    //   125: ldc 87
    //   127: bipush 33
    //   129: iconst_3
    //   130: invokestatic 66	xxxxxx/uxxxxx:bb00620062bb0062b0062b0062	(Ljava/lang/String;CC)Ljava/lang/String;
    //   133: iconst_0
    //   134: anewarray 68	java/lang/Class
    //   137: invokevirtual 72	java/lang/Class:getMethod	(Ljava/lang/String;[Ljava/lang/Class;)Ljava/lang/reflect/Method;
    //   140: astore 4
    //   142: aload 4
    //   144: aconst_null
    //   145: iconst_0
    //   146: anewarray 4	java/lang/Object
    //   149: invokevirtual 78	java/lang/reflect/Method:invoke	(Ljava/lang/Object;[Ljava/lang/Object;)Ljava/lang/Object;
    //   152: astore 4
    //   154: aload 4
    //   156: checkcast 80	java/lang/Integer
    //   159: invokevirtual 83	java/lang/Integer:intValue	()I
    //   162: istore_2
    //   163: ldc 2
    //   165: ldc 89
    //   167: sipush 168
    //   170: iconst_4
    //   171: invokestatic 66	xxxxxx/uxxxxx:bb00620062bb0062b0062b0062	(Ljava/lang/String;CC)Ljava/lang/String;
    //   174: iconst_0
    //   175: anewarray 68	java/lang/Class
    //   178: invokevirtual 72	java/lang/Class:getMethod	(Ljava/lang/String;[Ljava/lang/Class;)Ljava/lang/reflect/Method;
    //   181: astore 4
    //   183: aload 4
    //   185: aconst_null
    //   186: iconst_0
    //   187: anewarray 4	java/lang/Object
    //   190: invokevirtual 78	java/lang/reflect/Method:invoke	(Ljava/lang/Object;[Ljava/lang/Object;)Ljava/lang/Object;
    //   193: astore 4
    //   195: aload 4
    //   197: checkcast 80	java/lang/Integer
    //   200: invokevirtual 83	java/lang/Integer:intValue	()I
    //   203: iload_1
    //   204: iload_2
    //   205: iadd
    //   206: imul
    //   207: getstatic 58	uuuuuu/yyttty:bxx0078x0078xxx0078	I
    //   210: irem
    //   211: getstatic 91	uuuuuu/yyttty:bx0078xx0078xxx0078	I
    //   214: if_icmpeq +88 -> 302
    //   217: ldc 2
    //   219: ldc 93
    //   221: sipush 240
    //   224: iconst_2
    //   225: invokestatic 66	xxxxxx/uxxxxx:bb00620062bb0062b0062b0062	(Ljava/lang/String;CC)Ljava/lang/String;
    //   228: iconst_0
    //   229: anewarray 68	java/lang/Class
    //   232: invokevirtual 72	java/lang/Class:getMethod	(Ljava/lang/String;[Ljava/lang/Class;)Ljava/lang/reflect/Method;
    //   235: astore 4
    //   237: aload 4
    //   239: aconst_null
    //   240: iconst_0
    //   241: anewarray 4	java/lang/Object
    //   244: invokevirtual 78	java/lang/reflect/Method:invoke	(Ljava/lang/Object;[Ljava/lang/Object;)Ljava/lang/Object;
    //   247: astore 4
    //   249: aload 4
    //   251: checkcast 80	java/lang/Integer
    //   254: invokevirtual 83	java/lang/Integer:intValue	()I
    //   257: putstatic 54	uuuuuu/yyttty:b0078xxx0078xxx0078	I
    //   260: ldc 2
    //   262: ldc 95
    //   264: bipush 74
    //   266: iconst_5
    //   267: invokestatic 66	xxxxxx/uxxxxx:bb00620062bb0062b0062b0062	(Ljava/lang/String;CC)Ljava/lang/String;
    //   270: iconst_0
    //   271: anewarray 68	java/lang/Class
    //   274: invokevirtual 72	java/lang/Class:getMethod	(Ljava/lang/String;[Ljava/lang/Class;)Ljava/lang/reflect/Method;
    //   277: astore 4
    //   279: aload 4
    //   281: aconst_null
    //   282: iconst_0
    //   283: anewarray 4	java/lang/Object
    //   286: invokevirtual 78	java/lang/reflect/Method:invoke	(Ljava/lang/Object;[Ljava/lang/Object;)Ljava/lang/Object;
    //   289: astore 4
    //   291: aload 4
    //   293: checkcast 80	java/lang/Integer
    //   296: invokevirtual 83	java/lang/Integer:intValue	()I
    //   299: putstatic 91	uuuuuu/yyttty:bx0078xx0078xxx0078	I
    //   302: bipush 23
    //   304: putstatic 91	uuuuuu/yyttty:bx0078xx0078xxx0078	I
    //   307: ldc 97
    //   309: ldc 99
    //   311: bipush 80
    //   313: iconst_2
    //   314: invokestatic 66	xxxxxx/uxxxxx:bb00620062bb0062b0062b0062	(Ljava/lang/String;CC)Ljava/lang/String;
    //   317: iconst_4
    //   318: anewarray 68	java/lang/Class
    //   321: dup
    //   322: iconst_0
    //   323: ldc 101
    //   325: aastore
    //   326: dup
    //   327: iconst_1
    //   328: getstatic 107	java/lang/Character:TYPE	Ljava/lang/Class;
    //   331: aastore
    //   332: dup
    //   333: iconst_2
    //   334: getstatic 107	java/lang/Character:TYPE	Ljava/lang/Class;
    //   337: aastore
    //   338: dup
    //   339: iconst_3
    //   340: getstatic 107	java/lang/Character:TYPE	Ljava/lang/Class;
    //   343: aastore
    //   344: invokevirtual 72	java/lang/Class:getMethod	(Ljava/lang/String;[Ljava/lang/Class;)Ljava/lang/reflect/Method;
    //   347: astore 4
    //   349: aload 4
    //   351: aconst_null
    //   352: iconst_4
    //   353: anewarray 4	java/lang/Object
    //   356: dup
    //   357: iconst_0
    //   358: ldc 109
    //   360: aastore
    //   361: dup
    //   362: iconst_1
    //   363: bipush 83
    //   365: invokestatic 113	java/lang/Character:valueOf	(C)Ljava/lang/Character;
    //   368: aastore
    //   369: dup
    //   370: iconst_2
    //   371: sipush 237
    //   374: invokestatic 113	java/lang/Character:valueOf	(C)Ljava/lang/Character;
    //   377: aastore
    //   378: dup
    //   379: iconst_3
    //   380: iconst_2
    //   381: invokestatic 113	java/lang/Character:valueOf	(C)Ljava/lang/Character;
    //   384: aastore
    //   385: invokevirtual 78	java/lang/reflect/Method:invoke	(Ljava/lang/Object;[Ljava/lang/Object;)Ljava/lang/Object;
    //   388: astore 4
    //   390: aload 4
    //   392: checkcast 101	java/lang/String
    //   395: astore 4
    //   397: getstatic 54	uuuuuu/yyttty:b0078xxx0078xxx0078	I
    //   400: istore_1
    //   401: getstatic 54	uuuuuu/yyttty:b0078xxx0078xxx0078	I
    //   404: istore_2
    //   405: iload_2
    //   406: getstatic 56	uuuuuu/yyttty:b00780078xx0078xxx0078	I
    //   409: iload_2
    //   410: iadd
    //   411: imul
    //   412: getstatic 58	uuuuuu/yyttty:bxx0078x0078xxx0078	I
    //   415: irem
    //   416: tableswitch	default:+20->436, 0:+68->484
    //   436: ldc 2
    //   438: ldc 115
    //   440: sipush 203
    //   443: iconst_2
    //   444: invokestatic 66	xxxxxx/uxxxxx:bb00620062bb0062b0062b0062	(Ljava/lang/String;CC)Ljava/lang/String;
    //   447: iconst_0
    //   448: anewarray 68	java/lang/Class
    //   451: invokevirtual 72	java/lang/Class:getMethod	(Ljava/lang/String;[Ljava/lang/Class;)Ljava/lang/reflect/Method;
    //   454: astore 5
    //   456: aload 5
    //   458: aconst_null
    //   459: iconst_0
    //   460: anewarray 4	java/lang/Object
    //   463: invokevirtual 78	java/lang/reflect/Method:invoke	(Ljava/lang/Object;[Ljava/lang/Object;)Ljava/lang/Object;
    //   466: astore 5
    //   468: aload 5
    //   470: checkcast 80	java/lang/Integer
    //   473: invokevirtual 83	java/lang/Integer:intValue	()I
    //   476: putstatic 54	uuuuuu/yyttty:b0078xxx0078xxx0078	I
    //   479: bipush 16
    //   481: putstatic 91	uuuuuu/yyttty:bx0078xx0078xxx0078	I
    //   484: getstatic 56	uuuuuu/yyttty:b00780078xx0078xxx0078	I
    //   487: istore_2
    //   488: ldc 2
    //   490: ldc 117
    //   492: bipush 22
    //   494: iconst_0
    //   495: invokestatic 66	xxxxxx/uxxxxx:bb00620062bb0062b0062b0062	(Ljava/lang/String;CC)Ljava/lang/String;
    //   498: iconst_0
    //   499: anewarray 68	java/lang/Class
    //   502: invokevirtual 72	java/lang/Class:getMethod	(Ljava/lang/String;[Ljava/lang/Class;)Ljava/lang/reflect/Method;
    //   505: astore 5
    //   507: aload 5
    //   509: aconst_null
    //   510: iconst_0
    //   511: anewarray 4	java/lang/Object
    //   514: invokevirtual 78	java/lang/reflect/Method:invoke	(Ljava/lang/Object;[Ljava/lang/Object;)Ljava/lang/Object;
    //   517: astore 5
    //   519: iload_1
    //   520: iload_2
    //   521: iload_1
    //   522: iadd
    //   523: imul
    //   524: aload 5
    //   526: checkcast 80	java/lang/Integer
    //   529: invokevirtual 83	java/lang/Integer:intValue	()I
    //   532: irem
    //   533: tableswitch	default:+19->552, 0:+107->640
    //   552: ldc 2
    //   554: ldc 119
    //   556: bipush 91
    //   558: sipush 181
    //   561: iconst_2
    //   562: invokestatic 123	xxxxxx/uxxxxx:bbbb0062b0062b0062b0062	(Ljava/lang/String;CCC)Ljava/lang/String;
    //   565: iconst_0
    //   566: anewarray 68	java/lang/Class
    //   569: invokevirtual 72	java/lang/Class:getMethod	(Ljava/lang/String;[Ljava/lang/Class;)Ljava/lang/reflect/Method;
    //   572: astore 5
    //   574: aload 5
    //   576: aconst_null
    //   577: iconst_0
    //   578: anewarray 4	java/lang/Object
    //   581: invokevirtual 78	java/lang/reflect/Method:invoke	(Ljava/lang/Object;[Ljava/lang/Object;)Ljava/lang/Object;
    //   584: astore 5
    //   586: aload 5
    //   588: checkcast 80	java/lang/Integer
    //   591: invokevirtual 83	java/lang/Integer:intValue	()I
    //   594: putstatic 54	uuuuuu/yyttty:b0078xxx0078xxx0078	I
    //   597: ldc 2
    //   599: ldc 125
    //   601: sipush 142
    //   604: iconst_4
    //   605: invokestatic 66	xxxxxx/uxxxxx:bb00620062bb0062b0062b0062	(Ljava/lang/String;CC)Ljava/lang/String;
    //   608: iconst_0
    //   609: anewarray 68	java/lang/Class
    //   612: invokevirtual 72	java/lang/Class:getMethod	(Ljava/lang/String;[Ljava/lang/Class;)Ljava/lang/reflect/Method;
    //   615: astore 5
    //   617: aload 5
    //   619: aconst_null
    //   620: iconst_0
    //   621: anewarray 4	java/lang/Object
    //   624: invokevirtual 78	java/lang/reflect/Method:invoke	(Ljava/lang/Object;[Ljava/lang/Object;)Ljava/lang/Object;
    //   627: astore 5
    //   629: aload 5
    //   631: checkcast 80	java/lang/Integer
    //   634: invokevirtual 83	java/lang/Integer:intValue	()I
    //   637: putstatic 91	uuuuuu/yyttty:bx0078xx0078xxx0078	I
    //   640: ldc 97
    //   642: ldc 127
    //   644: bipush 23
    //   646: sipush 242
    //   649: iconst_0
    //   650: invokestatic 123	xxxxxx/uxxxxx:bbbb0062b0062b0062b0062	(Ljava/lang/String;CCC)Ljava/lang/String;
    //   653: iconst_3
    //   654: anewarray 68	java/lang/Class
    //   657: dup
    //   658: iconst_0
    //   659: ldc 101
    //   661: aastore
    //   662: dup
    //   663: iconst_1
    //   664: getstatic 107	java/lang/Character:TYPE	Ljava/lang/Class;
    //   667: aastore
    //   668: dup
    //   669: iconst_2
    //   670: getstatic 107	java/lang/Character:TYPE	Ljava/lang/Class;
    //   673: aastore
    //   674: invokevirtual 72	java/lang/Class:getMethod	(Ljava/lang/String;[Ljava/lang/Class;)Ljava/lang/reflect/Method;
    //   677: astore 5
    //   679: aload 5
    //   681: aconst_null
    //   682: iconst_3
    //   683: anewarray 4	java/lang/Object
    //   686: dup
    //   687: iconst_0
    //   688: ldc -127
    //   690: aastore
    //   691: dup
    //   692: iconst_1
    //   693: sipush 154
    //   696: invokestatic 113	java/lang/Character:valueOf	(C)Ljava/lang/Character;
    //   699: aastore
    //   700: dup
    //   701: iconst_2
    //   702: iconst_2
    //   703: invokestatic 113	java/lang/Character:valueOf	(C)Ljava/lang/Character;
    //   706: aastore
    //   707: invokevirtual 78	java/lang/reflect/Method:invoke	(Ljava/lang/Object;[Ljava/lang/Object;)Ljava/lang/Object;
    //   710: astore 5
    //   712: aload 5
    //   714: checkcast 101	java/lang/String
    //   717: astore 5
    //   719: ldc -125
    //   721: ldc -123
    //   723: bipush 7
    //   725: iconst_1
    //   726: invokestatic 66	xxxxxx/uxxxxx:bb00620062bb0062b0062b0062	(Ljava/lang/String;CC)Ljava/lang/String;
    //   729: iconst_2
    //   730: anewarray 68	java/lang/Class
    //   733: dup
    //   734: iconst_0
    //   735: ldc 101
    //   737: aastore
    //   738: dup
    //   739: iconst_1
    //   740: ldc 101
    //   742: aastore
    //   743: invokevirtual 72	java/lang/Class:getMethod	(Ljava/lang/String;[Ljava/lang/Class;)Ljava/lang/reflect/Method;
    //   746: astore 6
    //   748: aload 6
    //   750: aload_3
    //   751: iconst_2
    //   752: anewarray 4	java/lang/Object
    //   755: dup
    //   756: iconst_0
    //   757: aload 4
    //   759: aastore
    //   760: dup
    //   761: iconst_1
    //   762: aload 5
    //   764: aastore
    //   765: invokevirtual 78	java/lang/reflect/Method:invoke	(Ljava/lang/Object;[Ljava/lang/Object;)Ljava/lang/Object;
    //   768: astore_3
    //   769: aload_3
    //   770: checkcast 135	java/lang/Boolean
    //   773: invokevirtual 139	java/lang/Boolean:booleanValue	()Z
    //   776: pop
    //   777: return
    //   778: astore_3
    //   779: aload_3
    //   780: invokevirtual 143	java/lang/reflect/InvocationTargetException:getCause	()Ljava/lang/Throwable;
    //   783: athrow
    //   784: astore_3
    //   785: aload_3
    //   786: invokevirtual 143	java/lang/reflect/InvocationTargetException:getCause	()Ljava/lang/Throwable;
    //   789: athrow
    //   790: astore_3
    //   791: aload_3
    //   792: invokevirtual 143	java/lang/reflect/InvocationTargetException:getCause	()Ljava/lang/Throwable;
    //   795: athrow
    //   796: astore_3
    //   797: aload_3
    //   798: invokevirtual 143	java/lang/reflect/InvocationTargetException:getCause	()Ljava/lang/Throwable;
    //   801: athrow
    //   802: astore_3
    //   803: aload_3
    //   804: invokevirtual 143	java/lang/reflect/InvocationTargetException:getCause	()Ljava/lang/Throwable;
    //   807: athrow
    //   808: astore_3
    //   809: aload_3
    //   810: invokevirtual 143	java/lang/reflect/InvocationTargetException:getCause	()Ljava/lang/Throwable;
    //   813: athrow
    //   814: astore_3
    //   815: aload_3
    //   816: invokevirtual 143	java/lang/reflect/InvocationTargetException:getCause	()Ljava/lang/Throwable;
    //   819: athrow
    //   820: astore_3
    //   821: aload_3
    //   822: invokevirtual 143	java/lang/reflect/InvocationTargetException:getCause	()Ljava/lang/Throwable;
    //   825: athrow
    //   826: astore_3
    //   827: aload_3
    //   828: invokevirtual 143	java/lang/reflect/InvocationTargetException:getCause	()Ljava/lang/Throwable;
    //   831: athrow
    //   832: astore_3
    //   833: aload_3
    //   834: invokevirtual 143	java/lang/reflect/InvocationTargetException:getCause	()Ljava/lang/Throwable;
    //   837: athrow
    //   838: astore_3
    //   839: aload_3
    //   840: invokevirtual 143	java/lang/reflect/InvocationTargetException:getCause	()Ljava/lang/Throwable;
    //   843: athrow
    //   844: astore_3
    //   845: aload_3
    //   846: invokevirtual 143	java/lang/reflect/InvocationTargetException:getCause	()Ljava/lang/Throwable;
    //   849: athrow
    //   850: astore_3
    //   851: aload_3
    //   852: invokevirtual 143	java/lang/reflect/InvocationTargetException:getCause	()Ljava/lang/Throwable;
    //   855: athrow
    // Local variable table:
    //   start	length	slot	name	signature
    //   0	856	0	this	yyttty
    //   8	516	1	i	int
    //   162	361	2	j	int
    //   4	766	3	localObject1	Object
    //   778	2	3	localInvocationTargetException1	java.lang.reflect.InvocationTargetException
    //   784	2	3	localInvocationTargetException2	java.lang.reflect.InvocationTargetException
    //   790	2	3	localInvocationTargetException3	java.lang.reflect.InvocationTargetException
    //   796	2	3	localInvocationTargetException4	java.lang.reflect.InvocationTargetException
    //   802	2	3	localInvocationTargetException5	java.lang.reflect.InvocationTargetException
    //   808	2	3	localInvocationTargetException6	java.lang.reflect.InvocationTargetException
    //   814	2	3	localInvocationTargetException7	java.lang.reflect.InvocationTargetException
    //   820	2	3	localInvocationTargetException8	java.lang.reflect.InvocationTargetException
    //   826	2	3	localInvocationTargetException9	java.lang.reflect.InvocationTargetException
    //   832	2	3	localInvocationTargetException10	java.lang.reflect.InvocationTargetException
    //   838	2	3	localInvocationTargetException11	java.lang.reflect.InvocationTargetException
    //   844	2	3	localInvocationTargetException12	java.lang.reflect.InvocationTargetException
    //   850	2	3	localInvocationTargetException13	java.lang.reflect.InvocationTargetException
    //   58	700	4	localObject2	Object
    //   454	309	5	localObject3	Object
    //   746	3	6	localMethod	java.lang.reflect.Method
    // Exception table:
    //   from	to	target	type
    //   507	519	778	java/lang/reflect/InvocationTargetException
    //   349	390	784	java/lang/reflect/InvocationTargetException
    //   574	586	790	java/lang/reflect/InvocationTargetException
    //   617	629	796	java/lang/reflect/InvocationTargetException
    //   679	712	802	java/lang/reflect/InvocationTargetException
    //   748	769	808	java/lang/reflect/InvocationTargetException
    //   237	249	814	java/lang/reflect/InvocationTargetException
    //   279	291	820	java/lang/reflect/InvocationTargetException
    //   60	72	826	java/lang/reflect/InvocationTargetException
    //   102	114	832	java/lang/reflect/InvocationTargetException
    //   142	154	838	java/lang/reflect/InvocationTargetException
    //   183	195	844	java/lang/reflect/InvocationTargetException
    //   456	468	850	java/lang/reflect/InvocationTargetException
  }
  
  /* Error */
  public void b0071q0071qq00710071q00710071()
  {
    // Byte code:
    //   0: getstatic 54	uuuuuu/yyttty:b0078xxx0078xxx0078	I
    //   3: istore_1
    //   4: getstatic 56	uuuuuu/yyttty:b00780078xx0078xxx0078	I
    //   7: istore_2
    //   8: ldc 2
    //   10: ldc -110
    //   12: sipush 152
    //   15: iconst_1
    //   16: invokestatic 66	xxxxxx/uxxxxx:bb00620062bb0062b0062b0062	(Ljava/lang/String;CC)Ljava/lang/String;
    //   19: iconst_0
    //   20: anewarray 68	java/lang/Class
    //   23: invokevirtual 72	java/lang/Class:getMethod	(Ljava/lang/String;[Ljava/lang/Class;)Ljava/lang/reflect/Method;
    //   26: astore 5
    //   28: aload 5
    //   30: aconst_null
    //   31: iconst_0
    //   32: anewarray 4	java/lang/Object
    //   35: invokevirtual 78	java/lang/reflect/Method:invoke	(Ljava/lang/Object;[Ljava/lang/Object;)Ljava/lang/Object;
    //   38: astore 5
    //   40: iload_2
    //   41: iload_1
    //   42: iadd
    //   43: iload_1
    //   44: imul
    //   45: aload 5
    //   47: checkcast 80	java/lang/Integer
    //   50: invokevirtual 83	java/lang/Integer:intValue	()I
    //   53: irem
    //   54: tableswitch	default:+18->72, 0:+66->120
    //   72: bipush 94
    //   74: putstatic 54	uuuuuu/yyttty:b0078xxx0078xxx0078	I
    //   77: ldc 2
    //   79: ldc -108
    //   81: sipush 227
    //   84: iconst_4
    //   85: invokestatic 66	xxxxxx/uxxxxx:bb00620062bb0062b0062b0062	(Ljava/lang/String;CC)Ljava/lang/String;
    //   88: iconst_0
    //   89: anewarray 68	java/lang/Class
    //   92: invokevirtual 72	java/lang/Class:getMethod	(Ljava/lang/String;[Ljava/lang/Class;)Ljava/lang/reflect/Method;
    //   95: astore 5
    //   97: aload 5
    //   99: aconst_null
    //   100: iconst_0
    //   101: anewarray 4	java/lang/Object
    //   104: invokevirtual 78	java/lang/reflect/Method:invoke	(Ljava/lang/Object;[Ljava/lang/Object;)Ljava/lang/Object;
    //   107: astore 5
    //   109: aload 5
    //   111: checkcast 80	java/lang/Integer
    //   114: invokevirtual 83	java/lang/Integer:intValue	()I
    //   117: putstatic 91	uuuuuu/yyttty:bx0078xx0078xxx0078	I
    //   120: new 150	com/db/pwcc/dbmobile/model/terms_and_conditions/TermsRequest$vvyvvy
    //   123: dup
    //   124: invokespecial 151	com/db/pwcc/dbmobile/model/terms_and_conditions/TermsRequest$vvyvvy:<init>	()V
    //   127: invokevirtual 155	com/db/pwcc/dbmobile/model/terms_and_conditions/TermsRequest$vvyvvy:b0075uuu007500750075u0075u	()Lcom/db/pwcc/dbmobile/model/terms_and_conditions/TermsRequest$vvyvvy;
    //   130: invokevirtual 158	com/db/pwcc/dbmobile/model/terms_and_conditions/TermsRequest$vvyvvy:b0075uu0075u00750075u0075u	()Lcom/db/pwcc/dbmobile/model/terms_and_conditions/TermsRequest$vvyvvy;
    //   133: invokevirtual 162	com/db/pwcc/dbmobile/model/terms_and_conditions/TermsRequest$vvyvvy:bu007500750075u00750075u0075u	()Lcom/db/pwcc/dbmobile/model/terms_and_conditions/TermsRequest;
    //   136: astore 5
    //   138: aload_0
    //   139: getfield 41	uuuuuu/yyttty:bxxxx0078xxx0078	Luuuuuu/vvvpvv;
    //   142: astore 6
    //   144: getstatic 54	uuuuuu/yyttty:b0078xxx0078xxx0078	I
    //   147: istore_1
    //   148: ldc 2
    //   150: ldc -92
    //   152: sipush 244
    //   155: sipush 226
    //   158: iconst_1
    //   159: invokestatic 123	xxxxxx/uxxxxx:bbbb0062b0062b0062b0062	(Ljava/lang/String;CCC)Ljava/lang/String;
    //   162: iconst_0
    //   163: anewarray 68	java/lang/Class
    //   166: invokevirtual 72	java/lang/Class:getMethod	(Ljava/lang/String;[Ljava/lang/Class;)Ljava/lang/reflect/Method;
    //   169: astore 7
    //   171: aload 7
    //   173: aconst_null
    //   174: iconst_0
    //   175: anewarray 4	java/lang/Object
    //   178: invokevirtual 78	java/lang/reflect/Method:invoke	(Ljava/lang/Object;[Ljava/lang/Object;)Ljava/lang/Object;
    //   181: astore 7
    //   183: aload 7
    //   185: checkcast 80	java/lang/Integer
    //   188: invokevirtual 83	java/lang/Integer:intValue	()I
    //   191: istore_2
    //   192: getstatic 54	uuuuuu/yyttty:b0078xxx0078xxx0078	I
    //   195: istore_3
    //   196: getstatic 58	uuuuuu/yyttty:bxx0078x0078xxx0078	I
    //   199: istore 4
    //   201: ldc 2
    //   203: ldc -90
    //   205: sipush 218
    //   208: iconst_2
    //   209: invokestatic 66	xxxxxx/uxxxxx:bb00620062bb0062b0062b0062	(Ljava/lang/String;CC)Ljava/lang/String;
    //   212: iconst_0
    //   213: anewarray 68	java/lang/Class
    //   216: invokevirtual 72	java/lang/Class:getMethod	(Ljava/lang/String;[Ljava/lang/Class;)Ljava/lang/reflect/Method;
    //   219: astore 7
    //   221: aload 7
    //   223: aconst_null
    //   224: iconst_0
    //   225: anewarray 4	java/lang/Object
    //   228: invokevirtual 78	java/lang/reflect/Method:invoke	(Ljava/lang/Object;[Ljava/lang/Object;)Ljava/lang/Object;
    //   231: astore 7
    //   233: iload_2
    //   234: iload_1
    //   235: iadd
    //   236: iload_3
    //   237: imul
    //   238: iload 4
    //   240: irem
    //   241: aload 7
    //   243: checkcast 80	java/lang/Integer
    //   246: invokevirtual 83	java/lang/Integer:intValue	()I
    //   249: if_icmpeq +312 -> 561
    //   252: getstatic 54	uuuuuu/yyttty:b0078xxx0078xxx0078	I
    //   255: getstatic 56	uuuuuu/yyttty:b00780078xx0078xxx0078	I
    //   258: iadd
    //   259: getstatic 54	uuuuuu/yyttty:b0078xxx0078xxx0078	I
    //   262: imul
    //   263: getstatic 58	uuuuuu/yyttty:bxx0078x0078xxx0078	I
    //   266: irem
    //   267: getstatic 91	uuuuuu/yyttty:bx0078xx0078xxx0078	I
    //   270: if_icmpeq +242 -> 512
    //   273: ldc 2
    //   275: ldc -88
    //   277: sipush 183
    //   280: iconst_5
    //   281: invokestatic 66	xxxxxx/uxxxxx:bb00620062bb0062b0062b0062	(Ljava/lang/String;CC)Ljava/lang/String;
    //   284: iconst_0
    //   285: anewarray 68	java/lang/Class
    //   288: invokevirtual 72	java/lang/Class:getMethod	(Ljava/lang/String;[Ljava/lang/Class;)Ljava/lang/reflect/Method;
    //   291: astore 7
    //   293: aload 7
    //   295: aconst_null
    //   296: iconst_0
    //   297: anewarray 4	java/lang/Object
    //   300: invokevirtual 78	java/lang/reflect/Method:invoke	(Ljava/lang/Object;[Ljava/lang/Object;)Ljava/lang/Object;
    //   303: astore 7
    //   305: aload 7
    //   307: checkcast 80	java/lang/Integer
    //   310: invokevirtual 83	java/lang/Integer:intValue	()I
    //   313: istore_1
    //   314: ldc 2
    //   316: ldc -86
    //   318: sipush 144
    //   321: iconst_4
    //   322: invokestatic 66	xxxxxx/uxxxxx:bb00620062bb0062b0062b0062	(Ljava/lang/String;CC)Ljava/lang/String;
    //   325: iconst_0
    //   326: anewarray 68	java/lang/Class
    //   329: invokevirtual 72	java/lang/Class:getMethod	(Ljava/lang/String;[Ljava/lang/Class;)Ljava/lang/reflect/Method;
    //   332: astore 7
    //   334: aload 7
    //   336: aconst_null
    //   337: iconst_0
    //   338: anewarray 4	java/lang/Object
    //   341: invokevirtual 78	java/lang/reflect/Method:invoke	(Ljava/lang/Object;[Ljava/lang/Object;)Ljava/lang/Object;
    //   344: astore 7
    //   346: aload 7
    //   348: checkcast 80	java/lang/Integer
    //   351: invokevirtual 83	java/lang/Integer:intValue	()I
    //   354: istore_2
    //   355: ldc 2
    //   357: ldc -84
    //   359: sipush 245
    //   362: sipush 181
    //   365: iconst_3
    //   366: invokestatic 123	xxxxxx/uxxxxx:bbbb0062b0062b0062b0062	(Ljava/lang/String;CCC)Ljava/lang/String;
    //   369: iconst_0
    //   370: anewarray 68	java/lang/Class
    //   373: invokevirtual 72	java/lang/Class:getMethod	(Ljava/lang/String;[Ljava/lang/Class;)Ljava/lang/reflect/Method;
    //   376: astore 7
    //   378: aload 7
    //   380: aconst_null
    //   381: iconst_0
    //   382: anewarray 4	java/lang/Object
    //   385: invokevirtual 78	java/lang/reflect/Method:invoke	(Ljava/lang/Object;[Ljava/lang/Object;)Ljava/lang/Object;
    //   388: astore 7
    //   390: aload 7
    //   392: checkcast 80	java/lang/Integer
    //   395: invokevirtual 83	java/lang/Integer:intValue	()I
    //   398: istore_3
    //   399: getstatic 58	uuuuuu/yyttty:bxx0078x0078xxx0078	I
    //   402: istore 4
    //   404: ldc 2
    //   406: ldc -82
    //   408: bipush 12
    //   410: iconst_2
    //   411: invokestatic 66	xxxxxx/uxxxxx:bb00620062bb0062b0062b0062	(Ljava/lang/String;CC)Ljava/lang/String;
    //   414: iconst_0
    //   415: anewarray 68	java/lang/Class
    //   418: invokevirtual 72	java/lang/Class:getMethod	(Ljava/lang/String;[Ljava/lang/Class;)Ljava/lang/reflect/Method;
    //   421: astore 7
    //   423: aload 7
    //   425: aconst_null
    //   426: iconst_0
    //   427: anewarray 4	java/lang/Object
    //   430: invokevirtual 78	java/lang/reflect/Method:invoke	(Ljava/lang/Object;[Ljava/lang/Object;)Ljava/lang/Object;
    //   433: astore 7
    //   435: iload_3
    //   436: iload_1
    //   437: iload_2
    //   438: iadd
    //   439: imul
    //   440: iload 4
    //   442: irem
    //   443: aload 7
    //   445: checkcast 80	java/lang/Integer
    //   448: invokevirtual 83	java/lang/Integer:intValue	()I
    //   451: if_icmpeq +51 -> 502
    //   454: bipush 76
    //   456: putstatic 54	uuuuuu/yyttty:b0078xxx0078xxx0078	I
    //   459: ldc 2
    //   461: ldc -80
    //   463: bipush 112
    //   465: iconst_5
    //   466: iconst_2
    //   467: invokestatic 123	xxxxxx/uxxxxx:bbbb0062b0062b0062b0062	(Ljava/lang/String;CCC)Ljava/lang/String;
    //   470: iconst_0
    //   471: anewarray 68	java/lang/Class
    //   474: invokevirtual 72	java/lang/Class:getMethod	(Ljava/lang/String;[Ljava/lang/Class;)Ljava/lang/reflect/Method;
    //   477: astore 7
    //   479: aload 7
    //   481: aconst_null
    //   482: iconst_0
    //   483: anewarray 4	java/lang/Object
    //   486: invokevirtual 78	java/lang/reflect/Method:invoke	(Ljava/lang/Object;[Ljava/lang/Object;)Ljava/lang/Object;
    //   489: astore 7
    //   491: aload 7
    //   493: checkcast 80	java/lang/Integer
    //   496: invokevirtual 83	java/lang/Integer:intValue	()I
    //   499: putstatic 91	uuuuuu/yyttty:bx0078xx0078xxx0078	I
    //   502: bipush 88
    //   504: putstatic 54	uuuuuu/yyttty:b0078xxx0078xxx0078	I
    //   507: bipush 85
    //   509: putstatic 91	uuuuuu/yyttty:bx0078xx0078xxx0078	I
    //   512: ldc 2
    //   514: ldc -78
    //   516: bipush 114
    //   518: bipush 36
    //   520: iconst_2
    //   521: invokestatic 123	xxxxxx/uxxxxx:bbbb0062b0062b0062b0062	(Ljava/lang/String;CCC)Ljava/lang/String;
    //   524: iconst_0
    //   525: anewarray 68	java/lang/Class
    //   528: invokevirtual 72	java/lang/Class:getMethod	(Ljava/lang/String;[Ljava/lang/Class;)Ljava/lang/reflect/Method;
    //   531: astore 7
    //   533: aload 7
    //   535: aconst_null
    //   536: iconst_0
    //   537: anewarray 4	java/lang/Object
    //   540: invokevirtual 78	java/lang/reflect/Method:invoke	(Ljava/lang/Object;[Ljava/lang/Object;)Ljava/lang/Object;
    //   543: astore 7
    //   545: aload 7
    //   547: checkcast 80	java/lang/Integer
    //   550: invokevirtual 83	java/lang/Integer:intValue	()I
    //   553: putstatic 54	uuuuuu/yyttty:b0078xxx0078xxx0078	I
    //   556: bipush 23
    //   558: putstatic 91	uuuuuu/yyttty:bx0078xx0078xxx0078	I
    //   561: aload 6
    //   563: aload_0
    //   564: aload 5
    //   566: invokeinterface 184 3 0
    //   571: return
    //   572: astore 5
    //   574: aload 5
    //   576: invokevirtual 143	java/lang/reflect/InvocationTargetException:getCause	()Ljava/lang/Throwable;
    //   579: athrow
    //   580: astore 5
    //   582: aload 5
    //   584: invokevirtual 143	java/lang/reflect/InvocationTargetException:getCause	()Ljava/lang/Throwable;
    //   587: athrow
    //   588: astore 5
    //   590: aload 5
    //   592: invokevirtual 143	java/lang/reflect/InvocationTargetException:getCause	()Ljava/lang/Throwable;
    //   595: athrow
    //   596: astore 5
    //   598: aload 5
    //   600: invokevirtual 143	java/lang/reflect/InvocationTargetException:getCause	()Ljava/lang/Throwable;
    //   603: athrow
    //   604: astore 5
    //   606: aload 5
    //   608: invokevirtual 143	java/lang/reflect/InvocationTargetException:getCause	()Ljava/lang/Throwable;
    //   611: athrow
    //   612: astore 5
    //   614: aload 5
    //   616: invokevirtual 143	java/lang/reflect/InvocationTargetException:getCause	()Ljava/lang/Throwable;
    //   619: athrow
    //   620: astore 5
    //   622: aload 5
    //   624: invokevirtual 143	java/lang/reflect/InvocationTargetException:getCause	()Ljava/lang/Throwable;
    //   627: athrow
    //   628: astore 5
    //   630: aload 5
    //   632: invokevirtual 143	java/lang/reflect/InvocationTargetException:getCause	()Ljava/lang/Throwable;
    //   635: athrow
    //   636: astore 5
    //   638: aload 5
    //   640: invokevirtual 143	java/lang/reflect/InvocationTargetException:getCause	()Ljava/lang/Throwable;
    //   643: athrow
    //   644: astore 5
    //   646: aload 5
    //   648: invokevirtual 143	java/lang/reflect/InvocationTargetException:getCause	()Ljava/lang/Throwable;
    //   651: athrow
    // Local variable table:
    //   start	length	slot	name	signature
    //   0	652	0	this	yyttty
    //   3	436	1	i	int
    //   7	432	2	j	int
    //   195	245	3	k	int
    //   199	244	4	m	int
    //   26	539	5	localObject1	Object
    //   572	3	5	localInvocationTargetException1	java.lang.reflect.InvocationTargetException
    //   580	3	5	localInvocationTargetException2	java.lang.reflect.InvocationTargetException
    //   588	3	5	localInvocationTargetException3	java.lang.reflect.InvocationTargetException
    //   596	3	5	localInvocationTargetException4	java.lang.reflect.InvocationTargetException
    //   604	3	5	localInvocationTargetException5	java.lang.reflect.InvocationTargetException
    //   612	3	5	localInvocationTargetException6	java.lang.reflect.InvocationTargetException
    //   620	3	5	localInvocationTargetException7	java.lang.reflect.InvocationTargetException
    //   628	3	5	localInvocationTargetException8	java.lang.reflect.InvocationTargetException
    //   636	3	5	localInvocationTargetException9	java.lang.reflect.InvocationTargetException
    //   644	3	5	localInvocationTargetException10	java.lang.reflect.InvocationTargetException
    //   142	420	6	localVvvpvv	vvvpvv
    //   169	377	7	localObject2	Object
    // Exception table:
    //   from	to	target	type
    //   171	183	572	java/lang/reflect/InvocationTargetException
    //   28	40	580	java/lang/reflect/InvocationTargetException
    //   221	233	588	java/lang/reflect/InvocationTargetException
    //   293	305	596	java/lang/reflect/InvocationTargetException
    //   334	346	604	java/lang/reflect/InvocationTargetException
    //   378	390	612	java/lang/reflect/InvocationTargetException
    //   423	435	620	java/lang/reflect/InvocationTargetException
    //   533	545	628	java/lang/reflect/InvocationTargetException
    //   97	109	636	java/lang/reflect/InvocationTargetException
    //   479	491	644	java/lang/reflect/InvocationTargetException
  }
  
  /* Error */
  public void bpp00700070pp007000700070p(com.db.pwcc.dbmobile.model.error.DbError paramDbError)
  {
    // Byte code:
    //   0: ldc 2
    //   2: invokevirtual 190	java/lang/Class:getSimpleName	()Ljava/lang/String;
    //   5: astore 8
    //   7: ldc 97
    //   9: ldc -64
    //   11: sipush 185
    //   14: iconst_0
    //   15: invokestatic 66	xxxxxx/uxxxxx:bb00620062bb0062b0062b0062	(Ljava/lang/String;CC)Ljava/lang/String;
    //   18: iconst_4
    //   19: anewarray 68	java/lang/Class
    //   22: dup
    //   23: iconst_0
    //   24: ldc 101
    //   26: aastore
    //   27: dup
    //   28: iconst_1
    //   29: getstatic 107	java/lang/Character:TYPE	Ljava/lang/Class;
    //   32: aastore
    //   33: dup
    //   34: iconst_2
    //   35: getstatic 107	java/lang/Character:TYPE	Ljava/lang/Class;
    //   38: aastore
    //   39: dup
    //   40: iconst_3
    //   41: getstatic 107	java/lang/Character:TYPE	Ljava/lang/Class;
    //   44: aastore
    //   45: invokevirtual 72	java/lang/Class:getMethod	(Ljava/lang/String;[Ljava/lang/Class;)Ljava/lang/reflect/Method;
    //   48: astore 9
    //   50: aload 9
    //   52: aconst_null
    //   53: iconst_4
    //   54: anewarray 4	java/lang/Object
    //   57: dup
    //   58: iconst_0
    //   59: ldc -62
    //   61: aastore
    //   62: dup
    //   63: iconst_1
    //   64: sipush 164
    //   67: invokestatic 113	java/lang/Character:valueOf	(C)Ljava/lang/Character;
    //   70: aastore
    //   71: dup
    //   72: iconst_2
    //   73: bipush 45
    //   75: invokestatic 113	java/lang/Character:valueOf	(C)Ljava/lang/Character;
    //   78: aastore
    //   79: dup
    //   80: iconst_3
    //   81: iconst_0
    //   82: invokestatic 113	java/lang/Character:valueOf	(C)Ljava/lang/Character;
    //   85: aastore
    //   86: invokevirtual 78	java/lang/reflect/Method:invoke	(Ljava/lang/Object;[Ljava/lang/Object;)Ljava/lang/Object;
    //   89: astore 9
    //   91: aload 8
    //   93: aload 9
    //   95: checkcast 101	java/lang/String
    //   98: aload_1
    //   99: invokestatic 200	uuuuuu/rvvvrv:b00710071qq00710071q0071q0071	(Ljava/lang/String;Ljava/lang/String;Ljava/lang/Throwable;)V
    //   102: getstatic 54	uuuuuu/yyttty:b0078xxx0078xxx0078	I
    //   105: istore_2
    //   106: getstatic 56	uuuuuu/yyttty:b00780078xx0078xxx0078	I
    //   109: istore_3
    //   110: getstatic 54	uuuuuu/yyttty:b0078xxx0078xxx0078	I
    //   113: istore 4
    //   115: getstatic 58	uuuuuu/yyttty:bxx0078x0078xxx0078	I
    //   118: istore 5
    //   120: getstatic 54	uuuuuu/yyttty:b0078xxx0078xxx0078	I
    //   123: getstatic 56	uuuuuu/yyttty:b00780078xx0078xxx0078	I
    //   126: iadd
    //   127: getstatic 54	uuuuuu/yyttty:b0078xxx0078xxx0078	I
    //   130: imul
    //   131: getstatic 58	uuuuuu/yyttty:bxx0078x0078xxx0078	I
    //   134: irem
    //   135: getstatic 91	uuuuuu/yyttty:bx0078xx0078xxx0078	I
    //   138: if_icmpeq +162 -> 300
    //   141: ldc 2
    //   143: ldc -54
    //   145: sipush 201
    //   148: iconst_4
    //   149: invokestatic 66	xxxxxx/uxxxxx:bb00620062bb0062b0062b0062	(Ljava/lang/String;CC)Ljava/lang/String;
    //   152: iconst_0
    //   153: anewarray 68	java/lang/Class
    //   156: invokevirtual 72	java/lang/Class:getMethod	(Ljava/lang/String;[Ljava/lang/Class;)Ljava/lang/reflect/Method;
    //   159: astore_1
    //   160: aload_1
    //   161: aconst_null
    //   162: iconst_0
    //   163: anewarray 4	java/lang/Object
    //   166: invokevirtual 78	java/lang/reflect/Method:invoke	(Ljava/lang/Object;[Ljava/lang/Object;)Ljava/lang/Object;
    //   169: astore_1
    //   170: aload_1
    //   171: checkcast 80	java/lang/Integer
    //   174: invokevirtual 83	java/lang/Integer:intValue	()I
    //   177: putstatic 54	uuuuuu/yyttty:b0078xxx0078xxx0078	I
    //   180: bipush 56
    //   182: putstatic 91	uuuuuu/yyttty:bx0078xx0078xxx0078	I
    //   185: getstatic 54	uuuuuu/yyttty:b0078xxx0078xxx0078	I
    //   188: istore 6
    //   190: getstatic 56	uuuuuu/yyttty:b00780078xx0078xxx0078	I
    //   193: istore 7
    //   195: ldc 2
    //   197: ldc -52
    //   199: bipush 44
    //   201: iconst_0
    //   202: invokestatic 66	xxxxxx/uxxxxx:bb00620062bb0062b0062b0062	(Ljava/lang/String;CC)Ljava/lang/String;
    //   205: iconst_0
    //   206: anewarray 68	java/lang/Class
    //   209: invokevirtual 72	java/lang/Class:getMethod	(Ljava/lang/String;[Ljava/lang/Class;)Ljava/lang/reflect/Method;
    //   212: astore_1
    //   213: aload_1
    //   214: aconst_null
    //   215: iconst_0
    //   216: anewarray 4	java/lang/Object
    //   219: invokevirtual 78	java/lang/reflect/Method:invoke	(Ljava/lang/Object;[Ljava/lang/Object;)Ljava/lang/Object;
    //   222: astore_1
    //   223: iload 7
    //   225: iload 6
    //   227: iadd
    //   228: iload 6
    //   230: imul
    //   231: aload_1
    //   232: checkcast 80	java/lang/Integer
    //   235: invokevirtual 83	java/lang/Integer:intValue	()I
    //   238: irem
    //   239: tableswitch	default:+17->256, 0:+61->300
    //   256: ldc 2
    //   258: ldc -50
    //   260: sipush 169
    //   263: iconst_2
    //   264: invokestatic 66	xxxxxx/uxxxxx:bb00620062bb0062b0062b0062	(Ljava/lang/String;CC)Ljava/lang/String;
    //   267: iconst_0
    //   268: anewarray 68	java/lang/Class
    //   271: invokevirtual 72	java/lang/Class:getMethod	(Ljava/lang/String;[Ljava/lang/Class;)Ljava/lang/reflect/Method;
    //   274: astore_1
    //   275: aload_1
    //   276: aconst_null
    //   277: iconst_0
    //   278: anewarray 4	java/lang/Object
    //   281: invokevirtual 78	java/lang/reflect/Method:invoke	(Ljava/lang/Object;[Ljava/lang/Object;)Ljava/lang/Object;
    //   284: astore_1
    //   285: aload_1
    //   286: checkcast 80	java/lang/Integer
    //   289: invokevirtual 83	java/lang/Integer:intValue	()I
    //   292: putstatic 54	uuuuuu/yyttty:b0078xxx0078xxx0078	I
    //   295: bipush 57
    //   297: putstatic 91	uuuuuu/yyttty:bx0078xx0078xxx0078	I
    //   300: iload_2
    //   301: iload_3
    //   302: iadd
    //   303: iload 4
    //   305: imul
    //   306: iload 5
    //   308: irem
    //   309: getstatic 91	uuuuuu/yyttty:bx0078xx0078xxx0078	I
    //   312: if_icmpeq +154 -> 466
    //   315: bipush 96
    //   317: putstatic 54	uuuuuu/yyttty:b0078xxx0078xxx0078	I
    //   320: ldc 2
    //   322: ldc -78
    //   324: bipush 39
    //   326: iconst_1
    //   327: invokestatic 66	xxxxxx/uxxxxx:bb00620062bb0062b0062b0062	(Ljava/lang/String;CC)Ljava/lang/String;
    //   330: iconst_0
    //   331: anewarray 68	java/lang/Class
    //   334: invokevirtual 72	java/lang/Class:getMethod	(Ljava/lang/String;[Ljava/lang/Class;)Ljava/lang/reflect/Method;
    //   337: astore_1
    //   338: aload_1
    //   339: aconst_null
    //   340: iconst_0
    //   341: anewarray 4	java/lang/Object
    //   344: invokevirtual 78	java/lang/reflect/Method:invoke	(Ljava/lang/Object;[Ljava/lang/Object;)Ljava/lang/Object;
    //   347: astore_1
    //   348: aload_1
    //   349: checkcast 80	java/lang/Integer
    //   352: invokevirtual 83	java/lang/Integer:intValue	()I
    //   355: putstatic 91	uuuuuu/yyttty:bx0078xx0078xxx0078	I
    //   358: getstatic 54	uuuuuu/yyttty:b0078xxx0078xxx0078	I
    //   361: istore_2
    //   362: getstatic 56	uuuuuu/yyttty:b00780078xx0078xxx0078	I
    //   365: istore_3
    //   366: getstatic 54	uuuuuu/yyttty:b0078xxx0078xxx0078	I
    //   369: istore 4
    //   371: ldc 2
    //   373: ldc -48
    //   375: sipush 198
    //   378: iconst_2
    //   379: invokestatic 66	xxxxxx/uxxxxx:bb00620062bb0062b0062b0062	(Ljava/lang/String;CC)Ljava/lang/String;
    //   382: iconst_0
    //   383: anewarray 68	java/lang/Class
    //   386: invokevirtual 72	java/lang/Class:getMethod	(Ljava/lang/String;[Ljava/lang/Class;)Ljava/lang/reflect/Method;
    //   389: astore_1
    //   390: aload_1
    //   391: aconst_null
    //   392: iconst_0
    //   393: anewarray 4	java/lang/Object
    //   396: invokevirtual 78	java/lang/reflect/Method:invoke	(Ljava/lang/Object;[Ljava/lang/Object;)Ljava/lang/Object;
    //   399: astore_1
    //   400: aload_1
    //   401: checkcast 80	java/lang/Integer
    //   404: invokevirtual 83	java/lang/Integer:intValue	()I
    //   407: istore 5
    //   409: ldc 2
    //   411: ldc -46
    //   413: bipush 39
    //   415: iconst_3
    //   416: invokestatic 66	xxxxxx/uxxxxx:bb00620062bb0062b0062b0062	(Ljava/lang/String;CC)Ljava/lang/String;
    //   419: iconst_0
    //   420: anewarray 68	java/lang/Class
    //   423: invokevirtual 72	java/lang/Class:getMethod	(Ljava/lang/String;[Ljava/lang/Class;)Ljava/lang/reflect/Method;
    //   426: astore_1
    //   427: aload_1
    //   428: aconst_null
    //   429: iconst_0
    //   430: anewarray 4	java/lang/Object
    //   433: invokevirtual 78	java/lang/reflect/Method:invoke	(Ljava/lang/Object;[Ljava/lang/Object;)Ljava/lang/Object;
    //   436: astore_1
    //   437: iload 4
    //   439: iload_2
    //   440: iload_3
    //   441: iadd
    //   442: imul
    //   443: iload 5
    //   445: irem
    //   446: aload_1
    //   447: checkcast 80	java/lang/Integer
    //   450: invokevirtual 83	java/lang/Integer:intValue	()I
    //   453: if_icmpeq +13 -> 466
    //   456: bipush 9
    //   458: putstatic 54	uuuuuu/yyttty:b0078xxx0078xxx0078	I
    //   461: bipush 56
    //   463: putstatic 91	uuuuuu/yyttty:bx0078xx0078xxx0078	I
    //   466: return
    //   467: astore_1
    //   468: aload_1
    //   469: invokevirtual 143	java/lang/reflect/InvocationTargetException:getCause	()Ljava/lang/Throwable;
    //   472: athrow
    //   473: astore_1
    //   474: aload_1
    //   475: invokevirtual 143	java/lang/reflect/InvocationTargetException:getCause	()Ljava/lang/Throwable;
    //   478: athrow
    //   479: astore_1
    //   480: aload_1
    //   481: invokevirtual 143	java/lang/reflect/InvocationTargetException:getCause	()Ljava/lang/Throwable;
    //   484: athrow
    //   485: astore_1
    //   486: aload_1
    //   487: invokevirtual 143	java/lang/reflect/InvocationTargetException:getCause	()Ljava/lang/Throwable;
    //   490: athrow
    //   491: astore_1
    //   492: aload_1
    //   493: invokevirtual 143	java/lang/reflect/InvocationTargetException:getCause	()Ljava/lang/Throwable;
    //   496: athrow
    //   497: astore_1
    //   498: aload_1
    //   499: invokevirtual 143	java/lang/reflect/InvocationTargetException:getCause	()Ljava/lang/Throwable;
    //   502: athrow
    //   503: astore_1
    //   504: aload_1
    //   505: invokevirtual 143	java/lang/reflect/InvocationTargetException:getCause	()Ljava/lang/Throwable;
    //   508: athrow
    // Local variable table:
    //   start	length	slot	name	signature
    //   0	509	0	this	yyttty
    //   0	509	1	paramDbError	com.db.pwcc.dbmobile.model.error.DbError
    //   105	337	2	i	int
    //   109	333	3	j	int
    //   113	330	4	k	int
    //   118	328	5	m	int
    //   188	43	6	n	int
    //   193	35	7	i1	int
    //   5	87	8	str	String
    //   48	46	9	localObject	Object
    // Exception table:
    //   from	to	target	type
    //   338	348	467	java/lang/reflect/InvocationTargetException
    //   390	400	473	java/lang/reflect/InvocationTargetException
    //   427	437	479	java/lang/reflect/InvocationTargetException
    //   50	91	485	java/lang/reflect/InvocationTargetException
    //   160	170	491	java/lang/reflect/InvocationTargetException
    //   213	223	497	java/lang/reflect/InvocationTargetException
    //   275	285	503	java/lang/reflect/InvocationTargetException
  }
}
