package uuuuuu;

import com.db.pwcc.dbmobile.model.error.DbError;
import com.db.pwcc.dbmobile.mortgages.model.details.MortgageDetails;

public class yyvvyv
  extends qppppp<vyyvyv.vvyvyv>
  implements vyyvyv.yvyvyv, vvvvyv.yyyyvv
{
  public static int b00670067gggg006700670067 = 2;
  public static int b0067ggggg006700670067 = 0;
  public static int bg0067gggg006700670067 = 1;
  public static int bgggggg006700670067 = 41;
  private final vvvvyv b006700670067006700670067g00670067 = new vvyyvv();
  private DbError b0067g0067006700670067g00670067;
  private MortgageDetails bg00670067006700670067g00670067;
  
  public yyvvyv() {}
  
  public static int b007500750075uu0075u00750075u()
  {
    return 2;
  }
  
  public static int b00750075u0075u0075u00750075u()
  {
    return 4;
  }
  
  public static int bu0075u0075u0075u00750075u()
  {
    return 0;
  }
  
  /* Error */
  private int buu00750075u0075u00750075u(String paramString1, String paramString2)
  {
    // Byte code:
    //   0: new 44	uuuuuu/mmmqqq
    //   3: dup
    //   4: invokespecial 45	uuuuuu/mmmqqq:<init>	()V
    //   7: aload_1
    //   8: aload_2
    //   9: invokevirtual 49	uuuuuu/mmmqqq:bu00750075007500750075007500750075u	(Ljava/lang/String;Ljava/lang/String;)Ljava/math/BigDecimal;
    //   12: invokevirtual 54	java/math/BigDecimal:intValue	()I
    //   15: istore_3
    //   16: getstatic 56	uuuuuu/yyvvyv:bgggggg006700670067	I
    //   19: istore 4
    //   21: getstatic 58	uuuuuu/yyvvyv:bg0067gggg006700670067	I
    //   24: istore 5
    //   26: getstatic 56	uuuuuu/yyvvyv:bgggggg006700670067	I
    //   29: istore 6
    //   31: getstatic 60	uuuuuu/yyvvyv:b00670067gggg006700670067	I
    //   34: istore 7
    //   36: getstatic 56	uuuuuu/yyvvyv:bgggggg006700670067	I
    //   39: getstatic 58	uuuuuu/yyvvyv:bg0067gggg006700670067	I
    //   42: iadd
    //   43: getstatic 56	uuuuuu/yyvvyv:bgggggg006700670067	I
    //   46: imul
    //   47: getstatic 60	uuuuuu/yyvvyv:b00670067gggg006700670067	I
    //   50: irem
    //   51: getstatic 62	uuuuuu/yyvvyv:b0067ggggg006700670067	I
    //   54: if_icmpeq +50 -> 104
    //   57: ldc 2
    //   59: ldc 64
    //   61: sipush 146
    //   64: sipush 181
    //   67: iconst_1
    //   68: invokestatic 70	xxxxxx/uxxxxx:bbbb0062b0062b0062b0062	(Ljava/lang/String;CCC)Ljava/lang/String;
    //   71: iconst_0
    //   72: anewarray 72	java/lang/Class
    //   75: invokevirtual 76	java/lang/Class:getMethod	(Ljava/lang/String;[Ljava/lang/Class;)Ljava/lang/reflect/Method;
    //   78: astore_1
    //   79: aload_1
    //   80: aconst_null
    //   81: iconst_0
    //   82: anewarray 78	java/lang/Object
    //   85: invokevirtual 84	java/lang/reflect/Method:invoke	(Ljava/lang/Object;[Ljava/lang/Object;)Ljava/lang/Object;
    //   88: astore_1
    //   89: aload_1
    //   90: checkcast 86	java/lang/Integer
    //   93: invokevirtual 87	java/lang/Integer:intValue	()I
    //   96: putstatic 56	uuuuuu/yyvvyv:bgggggg006700670067	I
    //   99: bipush 20
    //   101: putstatic 62	uuuuuu/yyvvyv:b0067ggggg006700670067	I
    //   104: getstatic 62	uuuuuu/yyvvyv:b0067ggggg006700670067	I
    //   107: istore 8
    //   109: getstatic 56	uuuuuu/yyvvyv:bgggggg006700670067	I
    //   112: getstatic 58	uuuuuu/yyvvyv:bg0067gggg006700670067	I
    //   115: iadd
    //   116: getstatic 56	uuuuuu/yyvvyv:bgggggg006700670067	I
    //   119: imul
    //   120: getstatic 60	uuuuuu/yyvvyv:b00670067gggg006700670067	I
    //   123: irem
    //   124: getstatic 62	uuuuuu/yyvvyv:b0067ggggg006700670067	I
    //   127: if_icmpeq +45 -> 172
    //   130: iconst_1
    //   131: putstatic 56	uuuuuu/yyvvyv:bgggggg006700670067	I
    //   134: ldc 2
    //   136: ldc 89
    //   138: bipush 40
    //   140: iconst_1
    //   141: invokestatic 93	xxxxxx/uxxxxx:bb00620062bb0062b0062b0062	(Ljava/lang/String;CC)Ljava/lang/String;
    //   144: iconst_0
    //   145: anewarray 72	java/lang/Class
    //   148: invokevirtual 76	java/lang/Class:getMethod	(Ljava/lang/String;[Ljava/lang/Class;)Ljava/lang/reflect/Method;
    //   151: astore_1
    //   152: aload_1
    //   153: aconst_null
    //   154: iconst_0
    //   155: anewarray 78	java/lang/Object
    //   158: invokevirtual 84	java/lang/reflect/Method:invoke	(Ljava/lang/Object;[Ljava/lang/Object;)Ljava/lang/Object;
    //   161: astore_1
    //   162: aload_1
    //   163: checkcast 86	java/lang/Integer
    //   166: invokevirtual 87	java/lang/Integer:intValue	()I
    //   169: putstatic 62	uuuuuu/yyvvyv:b0067ggggg006700670067	I
    //   172: iload 6
    //   174: iload 4
    //   176: iload 5
    //   178: iadd
    //   179: imul
    //   180: iload 7
    //   182: irem
    //   183: iload 8
    //   185: if_icmpeq +146 -> 331
    //   188: getstatic 56	uuuuuu/yyvvyv:bgggggg006700670067	I
    //   191: getstatic 58	uuuuuu/yyvvyv:bg0067gggg006700670067	I
    //   194: iadd
    //   195: getstatic 56	uuuuuu/yyvvyv:bgggggg006700670067	I
    //   198: imul
    //   199: getstatic 60	uuuuuu/yyvvyv:b00670067gggg006700670067	I
    //   202: irem
    //   203: getstatic 62	uuuuuu/yyvvyv:b0067ggggg006700670067	I
    //   206: if_icmpeq +48 -> 254
    //   209: ldc 2
    //   211: ldc 95
    //   213: sipush 179
    //   216: bipush 121
    //   218: iconst_1
    //   219: invokestatic 70	xxxxxx/uxxxxx:bbbb0062b0062b0062b0062	(Ljava/lang/String;CCC)Ljava/lang/String;
    //   222: iconst_0
    //   223: anewarray 72	java/lang/Class
    //   226: invokevirtual 76	java/lang/Class:getMethod	(Ljava/lang/String;[Ljava/lang/Class;)Ljava/lang/reflect/Method;
    //   229: astore_1
    //   230: aload_1
    //   231: aconst_null
    //   232: iconst_0
    //   233: anewarray 78	java/lang/Object
    //   236: invokevirtual 84	java/lang/reflect/Method:invoke	(Ljava/lang/Object;[Ljava/lang/Object;)Ljava/lang/Object;
    //   239: astore_1
    //   240: aload_1
    //   241: checkcast 86	java/lang/Integer
    //   244: invokevirtual 87	java/lang/Integer:intValue	()I
    //   247: putstatic 56	uuuuuu/yyvvyv:bgggggg006700670067	I
    //   250: iconst_3
    //   251: putstatic 62	uuuuuu/yyvvyv:b0067ggggg006700670067	I
    //   254: ldc 2
    //   256: ldc 97
    //   258: bipush 107
    //   260: iconst_5
    //   261: invokestatic 93	xxxxxx/uxxxxx:bb00620062bb0062b0062b0062	(Ljava/lang/String;CC)Ljava/lang/String;
    //   264: iconst_0
    //   265: anewarray 72	java/lang/Class
    //   268: invokevirtual 76	java/lang/Class:getMethod	(Ljava/lang/String;[Ljava/lang/Class;)Ljava/lang/reflect/Method;
    //   271: astore_1
    //   272: aload_1
    //   273: aconst_null
    //   274: iconst_0
    //   275: anewarray 78	java/lang/Object
    //   278: invokevirtual 84	java/lang/reflect/Method:invoke	(Ljava/lang/Object;[Ljava/lang/Object;)Ljava/lang/Object;
    //   281: astore_1
    //   282: aload_1
    //   283: checkcast 86	java/lang/Integer
    //   286: invokevirtual 87	java/lang/Integer:intValue	()I
    //   289: putstatic 56	uuuuuu/yyvvyv:bgggggg006700670067	I
    //   292: ldc 2
    //   294: ldc 99
    //   296: sipush 153
    //   299: iconst_4
    //   300: invokestatic 93	xxxxxx/uxxxxx:bb00620062bb0062b0062b0062	(Ljava/lang/String;CC)Ljava/lang/String;
    //   303: iconst_0
    //   304: anewarray 72	java/lang/Class
    //   307: invokevirtual 76	java/lang/Class:getMethod	(Ljava/lang/String;[Ljava/lang/Class;)Ljava/lang/reflect/Method;
    //   310: astore_1
    //   311: aload_1
    //   312: aconst_null
    //   313: iconst_0
    //   314: anewarray 78	java/lang/Object
    //   317: invokevirtual 84	java/lang/reflect/Method:invoke	(Ljava/lang/Object;[Ljava/lang/Object;)Ljava/lang/Object;
    //   320: astore_1
    //   321: aload_1
    //   322: checkcast 86	java/lang/Integer
    //   325: invokevirtual 87	java/lang/Integer:intValue	()I
    //   328: putstatic 62	uuuuuu/yyvvyv:b0067ggggg006700670067	I
    //   331: iload_3
    //   332: ireturn
    //   333: astore_1
    //   334: aload_1
    //   335: invokevirtual 103	java/lang/reflect/InvocationTargetException:getCause	()Ljava/lang/Throwable;
    //   338: athrow
    //   339: astore_1
    //   340: aload_1
    //   341: invokevirtual 103	java/lang/reflect/InvocationTargetException:getCause	()Ljava/lang/Throwable;
    //   344: athrow
    //   345: astore_1
    //   346: aload_1
    //   347: invokevirtual 103	java/lang/reflect/InvocationTargetException:getCause	()Ljava/lang/Throwable;
    //   350: athrow
    //   351: astore_1
    //   352: aload_1
    //   353: invokevirtual 103	java/lang/reflect/InvocationTargetException:getCause	()Ljava/lang/Throwable;
    //   356: athrow
    //   357: astore_1
    //   358: aload_1
    //   359: invokevirtual 103	java/lang/reflect/InvocationTargetException:getCause	()Ljava/lang/Throwable;
    //   362: athrow
    // Local variable table:
    //   start	length	slot	name	signature
    //   0	363	0	this	yyvvyv
    //   0	363	1	paramString1	String
    //   0	363	2	paramString2	String
    //   15	317	3	i	int
    //   19	160	4	j	int
    //   24	155	5	k	int
    //   29	151	6	m	int
    //   34	149	7	n	int
    //   107	79	8	i1	int
    // Exception table:
    //   from	to	target	type
    //   79	89	333	java/lang/reflect/InvocationTargetException
    //   311	321	339	java/lang/reflect/InvocationTargetException
    //   152	162	345	java/lang/reflect/InvocationTargetException
    //   272	282	351	java/lang/reflect/InvocationTargetException
    //   230	240	357	java/lang/reflect/InvocationTargetException
  }
  
  public static int buuu0075u0075u00750075u()
  {
    return 1;
  }
  
  /* Error */
  public int b00750075uuu0075u00750075u(MortgageDetails paramMortgageDetails)
  {
    // Byte code:
    //   0: getstatic 56	uuuuuu/yyvvyv:bgggggg006700670067	I
    //   3: getstatic 58	uuuuuu/yyvvyv:bg0067gggg006700670067	I
    //   6: iadd
    //   7: getstatic 56	uuuuuu/yyvvyv:bgggggg006700670067	I
    //   10: imul
    //   11: getstatic 60	uuuuuu/yyvvyv:b00670067gggg006700670067	I
    //   14: irem
    //   15: getstatic 62	uuuuuu/yyvvyv:b0067ggggg006700670067	I
    //   18: if_icmpeq +208 -> 226
    //   21: getstatic 56	uuuuuu/yyvvyv:bgggggg006700670067	I
    //   24: getstatic 58	uuuuuu/yyvvyv:bg0067gggg006700670067	I
    //   27: iadd
    //   28: getstatic 56	uuuuuu/yyvvyv:bgggggg006700670067	I
    //   31: imul
    //   32: getstatic 60	uuuuuu/yyvvyv:b00670067gggg006700670067	I
    //   35: irem
    //   36: getstatic 62	uuuuuu/yyvvyv:b0067ggggg006700670067	I
    //   39: if_icmpeq +108 -> 147
    //   42: getstatic 56	uuuuuu/yyvvyv:bgggggg006700670067	I
    //   45: getstatic 58	uuuuuu/yyvvyv:bg0067gggg006700670067	I
    //   48: iadd
    //   49: getstatic 56	uuuuuu/yyvvyv:bgggggg006700670067	I
    //   52: imul
    //   53: getstatic 60	uuuuuu/yyvvyv:b00670067gggg006700670067	I
    //   56: irem
    //   57: getstatic 62	uuuuuu/yyvvyv:b0067ggggg006700670067	I
    //   60: if_icmpeq +77 -> 137
    //   63: bipush 99
    //   65: putstatic 56	uuuuuu/yyvvyv:bgggggg006700670067	I
    //   68: bipush 34
    //   70: putstatic 62	uuuuuu/yyvvyv:b0067ggggg006700670067	I
    //   73: getstatic 56	uuuuuu/yyvvyv:bgggggg006700670067	I
    //   76: getstatic 58	uuuuuu/yyvvyv:bg0067gggg006700670067	I
    //   79: iadd
    //   80: getstatic 56	uuuuuu/yyvvyv:bgggggg006700670067	I
    //   83: imul
    //   84: getstatic 60	uuuuuu/yyvvyv:b00670067gggg006700670067	I
    //   87: irem
    //   88: getstatic 62	uuuuuu/yyvvyv:b0067ggggg006700670067	I
    //   91: if_icmpeq +46 -> 137
    //   94: iconst_1
    //   95: putstatic 56	uuuuuu/yyvvyv:bgggggg006700670067	I
    //   98: ldc 2
    //   100: ldc 108
    //   102: sipush 181
    //   105: iconst_1
    //   106: invokestatic 93	xxxxxx/uxxxxx:bb00620062bb0062b0062b0062	(Ljava/lang/String;CC)Ljava/lang/String;
    //   109: iconst_0
    //   110: anewarray 72	java/lang/Class
    //   113: invokevirtual 76	java/lang/Class:getMethod	(Ljava/lang/String;[Ljava/lang/Class;)Ljava/lang/reflect/Method;
    //   116: astore_2
    //   117: aload_2
    //   118: aconst_null
    //   119: iconst_0
    //   120: anewarray 78	java/lang/Object
    //   123: invokevirtual 84	java/lang/reflect/Method:invoke	(Ljava/lang/Object;[Ljava/lang/Object;)Ljava/lang/Object;
    //   126: astore_2
    //   127: aload_2
    //   128: checkcast 86	java/lang/Integer
    //   131: invokevirtual 87	java/lang/Integer:intValue	()I
    //   134: putstatic 62	uuuuuu/yyvvyv:b0067ggggg006700670067	I
    //   137: bipush 71
    //   139: putstatic 56	uuuuuu/yyvvyv:bgggggg006700670067	I
    //   142: bipush 46
    //   144: putstatic 62	uuuuuu/yyvvyv:b0067ggggg006700670067	I
    //   147: ldc 2
    //   149: ldc 110
    //   151: sipush 211
    //   154: bipush 104
    //   156: iconst_2
    //   157: invokestatic 70	xxxxxx/uxxxxx:bbbb0062b0062b0062b0062	(Ljava/lang/String;CCC)Ljava/lang/String;
    //   160: iconst_0
    //   161: anewarray 72	java/lang/Class
    //   164: invokevirtual 76	java/lang/Class:getMethod	(Ljava/lang/String;[Ljava/lang/Class;)Ljava/lang/reflect/Method;
    //   167: astore_2
    //   168: aload_2
    //   169: aconst_null
    //   170: iconst_0
    //   171: anewarray 78	java/lang/Object
    //   174: invokevirtual 84	java/lang/reflect/Method:invoke	(Ljava/lang/Object;[Ljava/lang/Object;)Ljava/lang/Object;
    //   177: astore_2
    //   178: aload_2
    //   179: checkcast 86	java/lang/Integer
    //   182: invokevirtual 87	java/lang/Integer:intValue	()I
    //   185: putstatic 56	uuuuuu/yyvvyv:bgggggg006700670067	I
    //   188: ldc 2
    //   190: ldc 112
    //   192: bipush 33
    //   194: iconst_5
    //   195: invokestatic 93	xxxxxx/uxxxxx:bb00620062bb0062b0062b0062	(Ljava/lang/String;CC)Ljava/lang/String;
    //   198: iconst_0
    //   199: anewarray 72	java/lang/Class
    //   202: invokevirtual 76	java/lang/Class:getMethod	(Ljava/lang/String;[Ljava/lang/Class;)Ljava/lang/reflect/Method;
    //   205: astore_2
    //   206: aload_2
    //   207: aconst_null
    //   208: iconst_0
    //   209: anewarray 78	java/lang/Object
    //   212: invokevirtual 84	java/lang/reflect/Method:invoke	(Ljava/lang/Object;[Ljava/lang/Object;)Ljava/lang/Object;
    //   215: astore_2
    //   216: aload_2
    //   217: checkcast 86	java/lang/Integer
    //   220: invokevirtual 87	java/lang/Integer:intValue	()I
    //   223: putstatic 62	uuuuuu/yyvvyv:b0067ggggg006700670067	I
    //   226: aload_1
    //   227: invokevirtual 118	com/db/pwcc/dbmobile/mortgages/model/details/MortgageDetails:getContract	()Lcom/db/pwcc/dbmobile/mortgages/model/details/Contract;
    //   230: invokevirtual 124	com/db/pwcc/dbmobile/mortgages/model/details/Contract:getOriginalAmount	()Ljava/lang/String;
    //   233: astore_2
    //   234: aload_1
    //   235: invokevirtual 127	com/db/pwcc/dbmobile/mortgages/model/details/MortgageDetails:getCurrentBalance	()Ljava/lang/String;
    //   238: astore_1
    //   239: ldc 2
    //   241: ldc -127
    //   243: bipush 116
    //   245: iconst_3
    //   246: invokestatic 93	xxxxxx/uxxxxx:bb00620062bb0062b0062b0062	(Ljava/lang/String;CC)Ljava/lang/String;
    //   249: iconst_2
    //   250: anewarray 72	java/lang/Class
    //   253: dup
    //   254: iconst_0
    //   255: ldc -125
    //   257: aastore
    //   258: dup
    //   259: iconst_1
    //   260: ldc -125
    //   262: aastore
    //   263: invokevirtual 134	java/lang/Class:getDeclaredMethod	(Ljava/lang/String;[Ljava/lang/Class;)Ljava/lang/reflect/Method;
    //   266: astore_3
    //   267: aload_3
    //   268: aload_0
    //   269: iconst_2
    //   270: anewarray 78	java/lang/Object
    //   273: dup
    //   274: iconst_0
    //   275: aload_2
    //   276: aastore
    //   277: dup
    //   278: iconst_1
    //   279: aload_1
    //   280: aastore
    //   281: invokevirtual 84	java/lang/reflect/Method:invoke	(Ljava/lang/Object;[Ljava/lang/Object;)Ljava/lang/Object;
    //   284: astore_1
    //   285: aload_1
    //   286: checkcast 86	java/lang/Integer
    //   289: invokevirtual 87	java/lang/Integer:intValue	()I
    //   292: ireturn
    //   293: astore_1
    //   294: aload_1
    //   295: invokevirtual 103	java/lang/reflect/InvocationTargetException:getCause	()Ljava/lang/Throwable;
    //   298: athrow
    //   299: astore_1
    //   300: aload_1
    //   301: invokevirtual 103	java/lang/reflect/InvocationTargetException:getCause	()Ljava/lang/Throwable;
    //   304: athrow
    //   305: astore_1
    //   306: aload_1
    //   307: invokevirtual 103	java/lang/reflect/InvocationTargetException:getCause	()Ljava/lang/Throwable;
    //   310: athrow
    //   311: astore_1
    //   312: aload_1
    //   313: invokevirtual 103	java/lang/reflect/InvocationTargetException:getCause	()Ljava/lang/Throwable;
    //   316: athrow
    // Local variable table:
    //   start	length	slot	name	signature
    //   0	317	0	this	yyvvyv
    //   0	317	1	paramMortgageDetails	MortgageDetails
    //   116	160	2	localObject	Object
    //   266	2	3	localMethod	java.lang.reflect.Method
    // Exception table:
    //   from	to	target	type
    //   267	285	293	java/lang/reflect/InvocationTargetException
    //   168	178	299	java/lang/reflect/InvocationTargetException
    //   206	216	305	java/lang/reflect/InvocationTargetException
    //   117	127	311	java/lang/reflect/InvocationTargetException
  }
  
  /* Error */
  public void b0075u00750075u0075u00750075u(DbError paramDbError)
  {
    // Byte code:
    //   0: ldc 2
    //   2: invokevirtual 139	java/lang/Class:getSimpleName	()Ljava/lang/String;
    //   5: aload_1
    //   6: invokevirtual 144	com/db/pwcc/dbmobile/model/error/DbError:getLocalizedMessage	()Ljava/lang/String;
    //   9: invokestatic 150	uuuuuu/rvvvrv:bq0071qq00710071q0071q0071	(Ljava/lang/String;Ljava/lang/String;)V
    //   12: getstatic 56	uuuuuu/yyvvyv:bgggggg006700670067	I
    //   15: istore_2
    //   16: iload_2
    //   17: getstatic 58	uuuuuu/yyvvyv:bg0067gggg006700670067	I
    //   20: iload_2
    //   21: iadd
    //   22: imul
    //   23: getstatic 60	uuuuuu/yyvvyv:b00670067gggg006700670067	I
    //   26: irem
    //   27: tableswitch	default:+17->44, 0:+101->128
    //   44: ldc 2
    //   46: ldc 64
    //   48: bipush 92
    //   50: iconst_3
    //   51: invokestatic 93	xxxxxx/uxxxxx:bb00620062bb0062b0062b0062	(Ljava/lang/String;CC)Ljava/lang/String;
    //   54: iconst_0
    //   55: anewarray 72	java/lang/Class
    //   58: invokevirtual 76	java/lang/Class:getMethod	(Ljava/lang/String;[Ljava/lang/Class;)Ljava/lang/reflect/Method;
    //   61: astore 4
    //   63: aload 4
    //   65: aconst_null
    //   66: iconst_0
    //   67: anewarray 78	java/lang/Object
    //   70: invokevirtual 84	java/lang/reflect/Method:invoke	(Ljava/lang/Object;[Ljava/lang/Object;)Ljava/lang/Object;
    //   73: astore 4
    //   75: aload 4
    //   77: checkcast 86	java/lang/Integer
    //   80: invokevirtual 87	java/lang/Integer:intValue	()I
    //   83: putstatic 56	uuuuuu/yyvvyv:bgggggg006700670067	I
    //   86: ldc 2
    //   88: ldc -104
    //   90: bipush 29
    //   92: iconst_5
    //   93: invokestatic 93	xxxxxx/uxxxxx:bb00620062bb0062b0062b0062	(Ljava/lang/String;CC)Ljava/lang/String;
    //   96: iconst_0
    //   97: anewarray 72	java/lang/Class
    //   100: invokevirtual 76	java/lang/Class:getMethod	(Ljava/lang/String;[Ljava/lang/Class;)Ljava/lang/reflect/Method;
    //   103: astore 4
    //   105: aload 4
    //   107: aconst_null
    //   108: iconst_0
    //   109: anewarray 78	java/lang/Object
    //   112: invokevirtual 84	java/lang/reflect/Method:invoke	(Ljava/lang/Object;[Ljava/lang/Object;)Ljava/lang/Object;
    //   115: astore 4
    //   117: aload 4
    //   119: checkcast 86	java/lang/Integer
    //   122: invokevirtual 87	java/lang/Integer:intValue	()I
    //   125: putstatic 62	uuuuuu/yyvvyv:b0067ggggg006700670067	I
    //   128: aload_0
    //   129: invokevirtual 156	uuuuuu/yyvvyv:bkk006Bk006Bk006Bk006Bk	()Z
    //   132: ifne +287 -> 419
    //   135: aload_0
    //   136: aconst_null
    //   137: putfield 158	uuuuuu/yyvvyv:bg00670067006700670067g00670067	Lcom/db/pwcc/dbmobile/mortgages/model/details/MortgageDetails;
    //   140: aload_0
    //   141: aload_1
    //   142: putfield 160	uuuuuu/yyvvyv:b0067g0067006700670067g00670067	Lcom/db/pwcc/dbmobile/model/error/DbError;
    //   145: return
    //   146: getstatic 165	com/db/pwcc/dbmobile/mortgages/R$string:technical_error_retry	I
    //   149: istore_2
    //   150: getstatic 56	uuuuuu/yyvvyv:bgggggg006700670067	I
    //   153: istore_3
    //   154: iload_3
    //   155: getstatic 58	uuuuuu/yyvvyv:bg0067gggg006700670067	I
    //   158: iload_3
    //   159: iadd
    //   160: imul
    //   161: getstatic 60	uuuuuu/yyvvyv:b00670067gggg006700670067	I
    //   164: irem
    //   165: tableswitch	default:+19->184, 0:+66->231
    //   184: bipush 80
    //   186: putstatic 56	uuuuuu/yyvvyv:bgggggg006700670067	I
    //   189: ldc 2
    //   191: ldc -89
    //   193: sipush 163
    //   196: sipush 177
    //   199: iconst_1
    //   200: invokestatic 70	xxxxxx/uxxxxx:bbbb0062b0062b0062b0062	(Ljava/lang/String;CCC)Ljava/lang/String;
    //   203: iconst_0
    //   204: anewarray 72	java/lang/Class
    //   207: invokevirtual 76	java/lang/Class:getMethod	(Ljava/lang/String;[Ljava/lang/Class;)Ljava/lang/reflect/Method;
    //   210: astore_1
    //   211: aload_1
    //   212: aconst_null
    //   213: iconst_0
    //   214: anewarray 78	java/lang/Object
    //   217: invokevirtual 84	java/lang/reflect/Method:invoke	(Ljava/lang/Object;[Ljava/lang/Object;)Ljava/lang/Object;
    //   220: astore_1
    //   221: aload_1
    //   222: checkcast 86	java/lang/Integer
    //   225: invokevirtual 87	java/lang/Integer:intValue	()I
    //   228: putstatic 62	uuuuuu/yyvvyv:b0067ggggg006700670067	I
    //   231: getstatic 56	uuuuuu/yyvvyv:bgggggg006700670067	I
    //   234: getstatic 58	uuuuuu/yyvvyv:bg0067gggg006700670067	I
    //   237: iadd
    //   238: getstatic 56	uuuuuu/yyvvyv:bgggggg006700670067	I
    //   241: imul
    //   242: getstatic 60	uuuuuu/yyvvyv:b00670067gggg006700670067	I
    //   245: irem
    //   246: getstatic 62	uuuuuu/yyvvyv:b0067ggggg006700670067	I
    //   249: if_icmpeq +161 -> 410
    //   252: getstatic 56	uuuuuu/yyvvyv:bgggggg006700670067	I
    //   255: istore_3
    //   256: iload_3
    //   257: getstatic 58	uuuuuu/yyvvyv:bg0067gggg006700670067	I
    //   260: iload_3
    //   261: iadd
    //   262: imul
    //   263: getstatic 60	uuuuuu/yyvvyv:b00670067gggg006700670067	I
    //   266: irem
    //   267: tableswitch	default:+17->284, 0:+97->364
    //   284: ldc 2
    //   286: ldc -87
    //   288: bipush 11
    //   290: iconst_5
    //   291: invokestatic 93	xxxxxx/uxxxxx:bb00620062bb0062b0062b0062	(Ljava/lang/String;CC)Ljava/lang/String;
    //   294: iconst_0
    //   295: anewarray 72	java/lang/Class
    //   298: invokevirtual 76	java/lang/Class:getMethod	(Ljava/lang/String;[Ljava/lang/Class;)Ljava/lang/reflect/Method;
    //   301: astore_1
    //   302: aload_1
    //   303: aconst_null
    //   304: iconst_0
    //   305: anewarray 78	java/lang/Object
    //   308: invokevirtual 84	java/lang/reflect/Method:invoke	(Ljava/lang/Object;[Ljava/lang/Object;)Ljava/lang/Object;
    //   311: astore_1
    //   312: aload_1
    //   313: checkcast 86	java/lang/Integer
    //   316: invokevirtual 87	java/lang/Integer:intValue	()I
    //   319: putstatic 56	uuuuuu/yyvvyv:bgggggg006700670067	I
    //   322: ldc 2
    //   324: ldc -85
    //   326: sipush 229
    //   329: sipush 155
    //   332: iconst_0
    //   333: invokestatic 70	xxxxxx/uxxxxx:bbbb0062b0062b0062b0062	(Ljava/lang/String;CCC)Ljava/lang/String;
    //   336: iconst_0
    //   337: anewarray 72	java/lang/Class
    //   340: invokevirtual 76	java/lang/Class:getMethod	(Ljava/lang/String;[Ljava/lang/Class;)Ljava/lang/reflect/Method;
    //   343: astore_1
    //   344: aload_1
    //   345: aconst_null
    //   346: iconst_0
    //   347: anewarray 78	java/lang/Object
    //   350: invokevirtual 84	java/lang/reflect/Method:invoke	(Ljava/lang/Object;[Ljava/lang/Object;)Ljava/lang/Object;
    //   353: astore_1
    //   354: aload_1
    //   355: checkcast 86	java/lang/Integer
    //   358: invokevirtual 87	java/lang/Integer:intValue	()I
    //   361: putstatic 62	uuuuuu/yyvvyv:b0067ggggg006700670067	I
    //   364: ldc 2
    //   366: ldc -83
    //   368: bipush 122
    //   370: sipush 150
    //   373: iconst_2
    //   374: invokestatic 70	xxxxxx/uxxxxx:bbbb0062b0062b0062b0062	(Ljava/lang/String;CCC)Ljava/lang/String;
    //   377: iconst_0
    //   378: anewarray 72	java/lang/Class
    //   381: invokevirtual 76	java/lang/Class:getMethod	(Ljava/lang/String;[Ljava/lang/Class;)Ljava/lang/reflect/Method;
    //   384: astore_1
    //   385: aload_1
    //   386: aconst_null
    //   387: iconst_0
    //   388: anewarray 78	java/lang/Object
    //   391: invokevirtual 84	java/lang/reflect/Method:invoke	(Ljava/lang/Object;[Ljava/lang/Object;)Ljava/lang/Object;
    //   394: astore_1
    //   395: aload_1
    //   396: checkcast 86	java/lang/Integer
    //   399: invokevirtual 87	java/lang/Integer:intValue	()I
    //   402: putstatic 56	uuuuuu/yyvvyv:bgggggg006700670067	I
    //   405: bipush 14
    //   407: putstatic 62	uuuuuu/yyvvyv:b0067ggggg006700670067	I
    //   410: aload 4
    //   412: iload_2
    //   413: invokeinterface 179 2 0
    //   418: return
    //   419: aload_0
    //   420: getfield 183	uuuuuu/yyvvyv:bnnnnn006E006E006En	Luuuuuu/ttssst$tsssst;
    //   423: checkcast 175	uuuuuu/vyyvyv$vvyvyv
    //   426: astore 4
    //   428: aload_0
    //   429: aload_1
    //   430: invokevirtual 187	uuuuuu/yyvvyv:boo006F006F006F006Fo006F006F006F	(Lcom/db/pwcc/dbmobile/model/error/DbError;)Z
    //   433: ifeq -287 -> 146
    //   436: getstatic 190	com/db/pwcc/dbmobile/mortgages/R$string:check_internet_connection	I
    //   439: istore_2
    //   440: goto -30 -> 410
    //   443: astore_1
    //   444: aload_1
    //   445: invokevirtual 103	java/lang/reflect/InvocationTargetException:getCause	()Ljava/lang/Throwable;
    //   448: athrow
    //   449: astore_1
    //   450: aload_1
    //   451: invokevirtual 103	java/lang/reflect/InvocationTargetException:getCause	()Ljava/lang/Throwable;
    //   454: athrow
    //   455: astore_1
    //   456: aload_1
    //   457: invokevirtual 103	java/lang/reflect/InvocationTargetException:getCause	()Ljava/lang/Throwable;
    //   460: athrow
    //   461: astore_1
    //   462: aload_1
    //   463: invokevirtual 103	java/lang/reflect/InvocationTargetException:getCause	()Ljava/lang/Throwable;
    //   466: athrow
    //   467: astore_1
    //   468: aload_1
    //   469: invokevirtual 103	java/lang/reflect/InvocationTargetException:getCause	()Ljava/lang/Throwable;
    //   472: athrow
    //   473: astore_1
    //   474: aload_1
    //   475: invokevirtual 103	java/lang/reflect/InvocationTargetException:getCause	()Ljava/lang/Throwable;
    //   478: athrow
    // Local variable table:
    //   start	length	slot	name	signature
    //   0	479	0	this	yyvvyv
    //   0	479	1	paramDbError	DbError
    //   15	425	2	i	int
    //   153	110	3	j	int
    //   61	366	4	localObject	Object
    // Exception table:
    //   from	to	target	type
    //   385	395	443	java/lang/reflect/InvocationTargetException
    //   211	221	449	java/lang/reflect/InvocationTargetException
    //   302	312	455	java/lang/reflect/InvocationTargetException
    //   344	354	461	java/lang/reflect/InvocationTargetException
    //   63	75	467	java/lang/reflect/InvocationTargetException
    //   105	117	473	java/lang/reflect/InvocationTargetException
  }
  
  /* Error */
  public void b0075u0075uu0075u00750075u()
  {
    // Byte code:
    //   0: getstatic 197	uuuuuu/vvrvrv:bhh00680068hh006800680068	Luuuuuu/vvrvrv;
    //   3: astore 6
    //   5: getstatic 56	uuuuuu/yyvvyv:bgggggg006700670067	I
    //   8: istore_1
    //   9: getstatic 58	uuuuuu/yyvvyv:bg0067gggg006700670067	I
    //   12: istore_2
    //   13: getstatic 56	uuuuuu/yyvvyv:bgggggg006700670067	I
    //   16: istore_3
    //   17: getstatic 56	uuuuuu/yyvvyv:bgggggg006700670067	I
    //   20: istore 4
    //   22: getstatic 58	uuuuuu/yyvvyv:bg0067gggg006700670067	I
    //   25: istore 5
    //   27: ldc 2
    //   29: ldc -57
    //   31: bipush 29
    //   33: iconst_5
    //   34: invokestatic 93	xxxxxx/uxxxxx:bb00620062bb0062b0062b0062	(Ljava/lang/String;CC)Ljava/lang/String;
    //   37: iconst_0
    //   38: anewarray 72	java/lang/Class
    //   41: invokevirtual 76	java/lang/Class:getMethod	(Ljava/lang/String;[Ljava/lang/Class;)Ljava/lang/reflect/Method;
    //   44: astore 7
    //   46: aload 7
    //   48: aconst_null
    //   49: iconst_0
    //   50: anewarray 78	java/lang/Object
    //   53: invokevirtual 84	java/lang/reflect/Method:invoke	(Ljava/lang/Object;[Ljava/lang/Object;)Ljava/lang/Object;
    //   56: astore 7
    //   58: iload 5
    //   60: iload 4
    //   62: iadd
    //   63: iload 4
    //   65: imul
    //   66: aload 7
    //   68: checkcast 86	java/lang/Integer
    //   71: invokevirtual 87	java/lang/Integer:intValue	()I
    //   74: irem
    //   75: tableswitch	default:+17->92, 0:+65->140
    //   92: bipush 58
    //   94: putstatic 56	uuuuuu/yyvvyv:bgggggg006700670067	I
    //   97: ldc 2
    //   99: ldc -55
    //   101: sipush 179
    //   104: iconst_5
    //   105: invokestatic 93	xxxxxx/uxxxxx:bb00620062bb0062b0062b0062	(Ljava/lang/String;CC)Ljava/lang/String;
    //   108: iconst_0
    //   109: anewarray 72	java/lang/Class
    //   112: invokevirtual 76	java/lang/Class:getMethod	(Ljava/lang/String;[Ljava/lang/Class;)Ljava/lang/reflect/Method;
    //   115: astore 7
    //   117: aload 7
    //   119: aconst_null
    //   120: iconst_0
    //   121: anewarray 78	java/lang/Object
    //   124: invokevirtual 84	java/lang/reflect/Method:invoke	(Ljava/lang/Object;[Ljava/lang/Object;)Ljava/lang/Object;
    //   127: astore 7
    //   129: aload 7
    //   131: checkcast 86	java/lang/Integer
    //   134: invokevirtual 87	java/lang/Integer:intValue	()I
    //   137: putstatic 62	uuuuuu/yyvvyv:b0067ggggg006700670067	I
    //   140: iload_2
    //   141: iload_1
    //   142: iadd
    //   143: iload_3
    //   144: imul
    //   145: getstatic 60	uuuuuu/yyvvyv:b00670067gggg006700670067	I
    //   148: irem
    //   149: getstatic 62	uuuuuu/yyvvyv:b0067ggggg006700670067	I
    //   152: if_icmpeq +252 -> 404
    //   155: ldc 2
    //   157: ldc -53
    //   159: bipush 21
    //   161: iconst_1
    //   162: invokestatic 93	xxxxxx/uxxxxx:bb00620062bb0062b0062b0062	(Ljava/lang/String;CC)Ljava/lang/String;
    //   165: iconst_0
    //   166: anewarray 72	java/lang/Class
    //   169: invokevirtual 76	java/lang/Class:getMethod	(Ljava/lang/String;[Ljava/lang/Class;)Ljava/lang/reflect/Method;
    //   172: astore 7
    //   174: aload 7
    //   176: aconst_null
    //   177: iconst_0
    //   178: anewarray 78	java/lang/Object
    //   181: invokevirtual 84	java/lang/reflect/Method:invoke	(Ljava/lang/Object;[Ljava/lang/Object;)Ljava/lang/Object;
    //   184: astore 7
    //   186: aload 7
    //   188: checkcast 86	java/lang/Integer
    //   191: invokevirtual 87	java/lang/Integer:intValue	()I
    //   194: istore_1
    //   195: iload_1
    //   196: getstatic 58	uuuuuu/yyvvyv:bg0067gggg006700670067	I
    //   199: iload_1
    //   200: iadd
    //   201: imul
    //   202: getstatic 60	uuuuuu/yyvvyv:b00670067gggg006700670067	I
    //   205: irem
    //   206: tableswitch	default:+18->224, 0:+112->318
    //   224: ldc 2
    //   226: ldc -51
    //   228: sipush 253
    //   231: sipush 213
    //   234: iconst_2
    //   235: invokestatic 70	xxxxxx/uxxxxx:bbbb0062b0062b0062b0062	(Ljava/lang/String;CCC)Ljava/lang/String;
    //   238: iconst_0
    //   239: anewarray 72	java/lang/Class
    //   242: invokevirtual 76	java/lang/Class:getMethod	(Ljava/lang/String;[Ljava/lang/Class;)Ljava/lang/reflect/Method;
    //   245: astore 7
    //   247: aload 7
    //   249: aconst_null
    //   250: iconst_0
    //   251: anewarray 78	java/lang/Object
    //   254: invokevirtual 84	java/lang/reflect/Method:invoke	(Ljava/lang/Object;[Ljava/lang/Object;)Ljava/lang/Object;
    //   257: astore 7
    //   259: aload 7
    //   261: checkcast 86	java/lang/Integer
    //   264: invokevirtual 87	java/lang/Integer:intValue	()I
    //   267: putstatic 56	uuuuuu/yyvvyv:bgggggg006700670067	I
    //   270: bipush 12
    //   272: putstatic 62	uuuuuu/yyvvyv:b0067ggggg006700670067	I
    //   275: getstatic 56	uuuuuu/yyvvyv:bgggggg006700670067	I
    //   278: istore_1
    //   279: iload_1
    //   280: getstatic 58	uuuuuu/yyvvyv:bg0067gggg006700670067	I
    //   283: iload_1
    //   284: iadd
    //   285: imul
    //   286: getstatic 60	uuuuuu/yyvvyv:b00670067gggg006700670067	I
    //   289: irem
    //   290: tableswitch	default:+18->308, 0:+28->318
    //   308: bipush 38
    //   310: putstatic 56	uuuuuu/yyvvyv:bgggggg006700670067	I
    //   313: bipush 16
    //   315: putstatic 62	uuuuuu/yyvvyv:b0067ggggg006700670067	I
    //   318: ldc 2
    //   320: ldc -49
    //   322: sipush 232
    //   325: iconst_2
    //   326: invokestatic 93	xxxxxx/uxxxxx:bb00620062bb0062b0062b0062	(Ljava/lang/String;CC)Ljava/lang/String;
    //   329: iconst_0
    //   330: anewarray 72	java/lang/Class
    //   333: invokevirtual 76	java/lang/Class:getMethod	(Ljava/lang/String;[Ljava/lang/Class;)Ljava/lang/reflect/Method;
    //   336: astore 7
    //   338: aload 7
    //   340: aconst_null
    //   341: iconst_0
    //   342: anewarray 78	java/lang/Object
    //   345: invokevirtual 84	java/lang/reflect/Method:invoke	(Ljava/lang/Object;[Ljava/lang/Object;)Ljava/lang/Object;
    //   348: astore 7
    //   350: aload 7
    //   352: checkcast 86	java/lang/Integer
    //   355: invokevirtual 87	java/lang/Integer:intValue	()I
    //   358: putstatic 56	uuuuuu/yyvvyv:bgggggg006700670067	I
    //   361: ldc 2
    //   363: ldc -47
    //   365: sipush 196
    //   368: iconst_1
    //   369: invokestatic 93	xxxxxx/uxxxxx:bb00620062bb0062b0062b0062	(Ljava/lang/String;CC)Ljava/lang/String;
    //   372: iconst_0
    //   373: anewarray 72	java/lang/Class
    //   376: invokevirtual 76	java/lang/Class:getMethod	(Ljava/lang/String;[Ljava/lang/Class;)Ljava/lang/reflect/Method;
    //   379: astore 7
    //   381: aload 7
    //   383: aconst_null
    //   384: iconst_0
    //   385: anewarray 78	java/lang/Object
    //   388: invokevirtual 84	java/lang/reflect/Method:invoke	(Ljava/lang/Object;[Ljava/lang/Object;)Ljava/lang/Object;
    //   391: astore 7
    //   393: aload 7
    //   395: checkcast 86	java/lang/Integer
    //   398: invokevirtual 87	java/lang/Integer:intValue	()I
    //   401: putstatic 62	uuuuuu/yyvvyv:b0067ggggg006700670067	I
    //   404: aload 6
    //   406: invokestatic 215	uuuuuu/rrvvrv:b0071q0071qq0071q0071q0071	(Luuuuuu/vvrvrv;)V
    //   409: aload_0
    //   410: getfield 183	uuuuuu/yyvvyv:bnnnnn006E006E006En	Luuuuuu/ttssst$tsssst;
    //   413: checkcast 175	uuuuuu/vyyvyv$vvyvyv
    //   416: getstatic 218	com/db/pwcc/dbmobile/mortgages/R$string:mortgage_info_title_protection	I
    //   419: getstatic 221	com/db/pwcc/dbmobile/mortgages/R$string:mortgage_info_content_protection	I
    //   422: invokeinterface 225 3 0
    //   427: return
    //   428: astore 6
    //   430: aload 6
    //   432: invokevirtual 103	java/lang/reflect/InvocationTargetException:getCause	()Ljava/lang/Throwable;
    //   435: athrow
    //   436: astore 6
    //   438: aload 6
    //   440: invokevirtual 103	java/lang/reflect/InvocationTargetException:getCause	()Ljava/lang/Throwable;
    //   443: athrow
    //   444: astore 6
    //   446: aload 6
    //   448: invokevirtual 103	java/lang/reflect/InvocationTargetException:getCause	()Ljava/lang/Throwable;
    //   451: athrow
    //   452: astore 6
    //   454: aload 6
    //   456: invokevirtual 103	java/lang/reflect/InvocationTargetException:getCause	()Ljava/lang/Throwable;
    //   459: athrow
    //   460: astore 6
    //   462: aload 6
    //   464: invokevirtual 103	java/lang/reflect/InvocationTargetException:getCause	()Ljava/lang/Throwable;
    //   467: athrow
    //   468: astore 6
    //   470: aload 6
    //   472: invokevirtual 103	java/lang/reflect/InvocationTargetException:getCause	()Ljava/lang/Throwable;
    //   475: athrow
    // Local variable table:
    //   start	length	slot	name	signature
    //   0	476	0	this	yyvvyv
    //   8	278	1	i	int
    //   12	131	2	j	int
    //   16	129	3	k	int
    //   20	46	4	m	int
    //   25	38	5	n	int
    //   3	402	6	localVvrvrv	vvrvrv
    //   428	3	6	localInvocationTargetException1	java.lang.reflect.InvocationTargetException
    //   436	3	6	localInvocationTargetException2	java.lang.reflect.InvocationTargetException
    //   444	3	6	localInvocationTargetException3	java.lang.reflect.InvocationTargetException
    //   452	3	6	localInvocationTargetException4	java.lang.reflect.InvocationTargetException
    //   460	3	6	localInvocationTargetException5	java.lang.reflect.InvocationTargetException
    //   468	3	6	localInvocationTargetException6	java.lang.reflect.InvocationTargetException
    //   44	350	7	localObject	Object
    // Exception table:
    //   from	to	target	type
    //   46	58	428	java/lang/reflect/InvocationTargetException
    //   174	186	436	java/lang/reflect/InvocationTargetException
    //   338	350	444	java/lang/reflect/InvocationTargetException
    //   381	393	452	java/lang/reflect/InvocationTargetException
    //   247	259	460	java/lang/reflect/InvocationTargetException
    //   117	129	468	java/lang/reflect/InvocationTargetException
  }
  
  /* Error */
  public void b0075uu0075u0075u00750075u(vyyvyv.vvyvyv paramVvyvyv)
  {
    // Byte code:
    //   0: aload_0
    //   1: aload_1
    //   2: invokespecial 231	uuuuuu/qppppp:ba0061a0061a0061a0061aa	(Luuuuuu/ttssst$tsssst;)V
    //   5: aload_0
    //   6: getfield 158	uuuuuu/yyvvyv:bg00670067006700670067g00670067	Lcom/db/pwcc/dbmobile/mortgages/model/details/MortgageDetails;
    //   9: ifnull +270 -> 279
    //   12: aload_0
    //   13: getfield 158	uuuuuu/yyvvyv:bg00670067006700670067g00670067	Lcom/db/pwcc/dbmobile/mortgages/model/details/MortgageDetails;
    //   16: astore_1
    //   17: ldc 2
    //   19: ldc -23
    //   21: bipush 101
    //   23: iconst_3
    //   24: invokestatic 93	xxxxxx/uxxxxx:bb00620062bb0062b0062b0062	(Ljava/lang/String;CC)Ljava/lang/String;
    //   27: iconst_1
    //   28: anewarray 72	java/lang/Class
    //   31: dup
    //   32: iconst_0
    //   33: ldc 114
    //   35: aastore
    //   36: invokevirtual 76	java/lang/Class:getMethod	(Ljava/lang/String;[Ljava/lang/Class;)Ljava/lang/reflect/Method;
    //   39: astore 11
    //   41: aload 11
    //   43: aload_0
    //   44: iconst_1
    //   45: anewarray 78	java/lang/Object
    //   48: dup
    //   49: iconst_0
    //   50: aload_1
    //   51: aastore
    //   52: invokevirtual 84	java/lang/reflect/Method:invoke	(Ljava/lang/Object;[Ljava/lang/Object;)Ljava/lang/Object;
    //   55: pop
    //   56: aload_0
    //   57: aconst_null
    //   58: putfield 158	uuuuuu/yyvvyv:bg00670067006700670067g00670067	Lcom/db/pwcc/dbmobile/mortgages/model/details/MortgageDetails;
    //   61: getstatic 56	uuuuuu/yyvvyv:bgggggg006700670067	I
    //   64: istore_2
    //   65: iload_2
    //   66: getstatic 58	uuuuuu/yyvvyv:bg0067gggg006700670067	I
    //   69: iload_2
    //   70: iadd
    //   71: imul
    //   72: getstatic 60	uuuuuu/yyvvyv:b00670067gggg006700670067	I
    //   75: irem
    //   76: tableswitch	default:+20->96, 0:+202->278
    //   96: ldc 2
    //   98: ldc -21
    //   100: bipush 19
    //   102: iconst_5
    //   103: invokestatic 93	xxxxxx/uxxxxx:bb00620062bb0062b0062b0062	(Ljava/lang/String;CC)Ljava/lang/String;
    //   106: iconst_0
    //   107: anewarray 72	java/lang/Class
    //   110: invokevirtual 76	java/lang/Class:getMethod	(Ljava/lang/String;[Ljava/lang/Class;)Ljava/lang/reflect/Method;
    //   113: astore_1
    //   114: aload_1
    //   115: aconst_null
    //   116: iconst_0
    //   117: anewarray 78	java/lang/Object
    //   120: invokevirtual 84	java/lang/reflect/Method:invoke	(Ljava/lang/Object;[Ljava/lang/Object;)Ljava/lang/Object;
    //   123: astore_1
    //   124: aload_1
    //   125: checkcast 86	java/lang/Integer
    //   128: invokevirtual 87	java/lang/Integer:intValue	()I
    //   131: putstatic 56	uuuuuu/yyvvyv:bgggggg006700670067	I
    //   134: bipush 88
    //   136: putstatic 62	uuuuuu/yyvvyv:b0067ggggg006700670067	I
    //   139: getstatic 56	uuuuuu/yyvvyv:bgggggg006700670067	I
    //   142: istore_2
    //   143: getstatic 58	uuuuuu/yyvvyv:bg0067gggg006700670067	I
    //   146: istore_3
    //   147: getstatic 56	uuuuuu/yyvvyv:bgggggg006700670067	I
    //   150: istore 4
    //   152: ldc 2
    //   154: ldc -19
    //   156: bipush 98
    //   158: bipush 10
    //   160: iconst_1
    //   161: invokestatic 70	xxxxxx/uxxxxx:bbbb0062b0062b0062b0062	(Ljava/lang/String;CCC)Ljava/lang/String;
    //   164: iconst_0
    //   165: anewarray 72	java/lang/Class
    //   168: invokevirtual 76	java/lang/Class:getMethod	(Ljava/lang/String;[Ljava/lang/Class;)Ljava/lang/reflect/Method;
    //   171: astore_1
    //   172: aload_1
    //   173: aconst_null
    //   174: iconst_0
    //   175: anewarray 78	java/lang/Object
    //   178: invokevirtual 84	java/lang/reflect/Method:invoke	(Ljava/lang/Object;[Ljava/lang/Object;)Ljava/lang/Object;
    //   181: astore_1
    //   182: iload 4
    //   184: iload_2
    //   185: iload_3
    //   186: iadd
    //   187: imul
    //   188: aload_1
    //   189: checkcast 86	java/lang/Integer
    //   192: invokevirtual 87	java/lang/Integer:intValue	()I
    //   195: irem
    //   196: getstatic 62	uuuuuu/yyvvyv:b0067ggggg006700670067	I
    //   199: if_icmpeq +79 -> 278
    //   202: ldc 2
    //   204: ldc -17
    //   206: bipush 65
    //   208: iconst_5
    //   209: invokestatic 93	xxxxxx/uxxxxx:bb00620062bb0062b0062b0062	(Ljava/lang/String;CC)Ljava/lang/String;
    //   212: iconst_0
    //   213: anewarray 72	java/lang/Class
    //   216: invokevirtual 76	java/lang/Class:getMethod	(Ljava/lang/String;[Ljava/lang/Class;)Ljava/lang/reflect/Method;
    //   219: astore_1
    //   220: aload_1
    //   221: aconst_null
    //   222: iconst_0
    //   223: anewarray 78	java/lang/Object
    //   226: invokevirtual 84	java/lang/reflect/Method:invoke	(Ljava/lang/Object;[Ljava/lang/Object;)Ljava/lang/Object;
    //   229: astore_1
    //   230: aload_1
    //   231: checkcast 86	java/lang/Integer
    //   234: invokevirtual 87	java/lang/Integer:intValue	()I
    //   237: putstatic 56	uuuuuu/yyvvyv:bgggggg006700670067	I
    //   240: ldc 2
    //   242: ldc -15
    //   244: bipush 33
    //   246: iconst_2
    //   247: invokestatic 93	xxxxxx/uxxxxx:bb00620062bb0062b0062b0062	(Ljava/lang/String;CC)Ljava/lang/String;
    //   250: iconst_0
    //   251: anewarray 72	java/lang/Class
    //   254: invokevirtual 76	java/lang/Class:getMethod	(Ljava/lang/String;[Ljava/lang/Class;)Ljava/lang/reflect/Method;
    //   257: astore_1
    //   258: aload_1
    //   259: aconst_null
    //   260: iconst_0
    //   261: anewarray 78	java/lang/Object
    //   264: invokevirtual 84	java/lang/reflect/Method:invoke	(Ljava/lang/Object;[Ljava/lang/Object;)Ljava/lang/Object;
    //   267: astore_1
    //   268: aload_1
    //   269: checkcast 86	java/lang/Integer
    //   272: invokevirtual 87	java/lang/Integer:intValue	()I
    //   275: putstatic 62	uuuuuu/yyvvyv:b0067ggggg006700670067	I
    //   278: return
    //   279: aload_0
    //   280: getfield 160	uuuuuu/yyvvyv:b0067g0067006700670067g00670067	Lcom/db/pwcc/dbmobile/model/error/DbError;
    //   283: ifnull -5 -> 278
    //   286: aload_0
    //   287: getfield 160	uuuuuu/yyvvyv:b0067g0067006700670067g00670067	Lcom/db/pwcc/dbmobile/model/error/DbError;
    //   290: astore_1
    //   291: getstatic 56	uuuuuu/yyvvyv:bgggggg006700670067	I
    //   294: istore_2
    //   295: getstatic 58	uuuuuu/yyvvyv:bg0067gggg006700670067	I
    //   298: istore_3
    //   299: getstatic 56	uuuuuu/yyvvyv:bgggggg006700670067	I
    //   302: istore 4
    //   304: getstatic 60	uuuuuu/yyvvyv:b00670067gggg006700670067	I
    //   307: istore 5
    //   309: getstatic 62	uuuuuu/yyvvyv:b0067ggggg006700670067	I
    //   312: istore 6
    //   314: getstatic 56	uuuuuu/yyvvyv:bgggggg006700670067	I
    //   317: istore 7
    //   319: getstatic 58	uuuuuu/yyvvyv:bg0067gggg006700670067	I
    //   322: istore 8
    //   324: getstatic 56	uuuuuu/yyvvyv:bgggggg006700670067	I
    //   327: istore 9
    //   329: getstatic 60	uuuuuu/yyvvyv:b00670067gggg006700670067	I
    //   332: istore 10
    //   334: ldc 2
    //   336: ldc -13
    //   338: sipush 174
    //   341: iconst_3
    //   342: invokestatic 93	xxxxxx/uxxxxx:bb00620062bb0062b0062b0062	(Ljava/lang/String;CC)Ljava/lang/String;
    //   345: iconst_0
    //   346: anewarray 72	java/lang/Class
    //   349: invokevirtual 76	java/lang/Class:getMethod	(Ljava/lang/String;[Ljava/lang/Class;)Ljava/lang/reflect/Method;
    //   352: astore 11
    //   354: aload 11
    //   356: aconst_null
    //   357: iconst_0
    //   358: anewarray 78	java/lang/Object
    //   361: invokevirtual 84	java/lang/reflect/Method:invoke	(Ljava/lang/Object;[Ljava/lang/Object;)Ljava/lang/Object;
    //   364: astore 11
    //   366: iload 7
    //   368: iload 8
    //   370: iadd
    //   371: iload 9
    //   373: imul
    //   374: iload 10
    //   376: irem
    //   377: aload 11
    //   379: checkcast 86	java/lang/Integer
    //   382: invokevirtual 87	java/lang/Integer:intValue	()I
    //   385: if_icmpeq +51 -> 436
    //   388: ldc 2
    //   390: ldc -11
    //   392: sipush 211
    //   395: iconst_2
    //   396: invokestatic 93	xxxxxx/uxxxxx:bb00620062bb0062b0062b0062	(Ljava/lang/String;CC)Ljava/lang/String;
    //   399: iconst_0
    //   400: anewarray 72	java/lang/Class
    //   403: invokevirtual 76	java/lang/Class:getMethod	(Ljava/lang/String;[Ljava/lang/Class;)Ljava/lang/reflect/Method;
    //   406: astore 11
    //   408: aload 11
    //   410: aconst_null
    //   411: iconst_0
    //   412: anewarray 78	java/lang/Object
    //   415: invokevirtual 84	java/lang/reflect/Method:invoke	(Ljava/lang/Object;[Ljava/lang/Object;)Ljava/lang/Object;
    //   418: astore 11
    //   420: aload 11
    //   422: checkcast 86	java/lang/Integer
    //   425: invokevirtual 87	java/lang/Integer:intValue	()I
    //   428: putstatic 56	uuuuuu/yyvvyv:bgggggg006700670067	I
    //   431: bipush 92
    //   433: putstatic 62	uuuuuu/yyvvyv:b0067ggggg006700670067	I
    //   436: iload_2
    //   437: iload_3
    //   438: iadd
    //   439: iload 4
    //   441: imul
    //   442: iload 5
    //   444: irem
    //   445: iload 6
    //   447: if_icmpeq +51 -> 498
    //   450: bipush 10
    //   452: putstatic 56	uuuuuu/yyvvyv:bgggggg006700670067	I
    //   455: ldc 2
    //   457: ldc -85
    //   459: sipush 130
    //   462: iconst_3
    //   463: invokestatic 93	xxxxxx/uxxxxx:bb00620062bb0062b0062b0062	(Ljava/lang/String;CC)Ljava/lang/String;
    //   466: iconst_0
    //   467: anewarray 72	java/lang/Class
    //   470: invokevirtual 76	java/lang/Class:getMethod	(Ljava/lang/String;[Ljava/lang/Class;)Ljava/lang/reflect/Method;
    //   473: astore 11
    //   475: aload 11
    //   477: aconst_null
    //   478: iconst_0
    //   479: anewarray 78	java/lang/Object
    //   482: invokevirtual 84	java/lang/reflect/Method:invoke	(Ljava/lang/Object;[Ljava/lang/Object;)Ljava/lang/Object;
    //   485: astore 11
    //   487: aload 11
    //   489: checkcast 86	java/lang/Integer
    //   492: invokevirtual 87	java/lang/Integer:intValue	()I
    //   495: putstatic 62	uuuuuu/yyvvyv:b0067ggggg006700670067	I
    //   498: ldc 2
    //   500: ldc -9
    //   502: bipush 28
    //   504: iconst_3
    //   505: invokestatic 93	xxxxxx/uxxxxx:bb00620062bb0062b0062b0062	(Ljava/lang/String;CC)Ljava/lang/String;
    //   508: iconst_1
    //   509: anewarray 72	java/lang/Class
    //   512: dup
    //   513: iconst_0
    //   514: ldc -115
    //   516: aastore
    //   517: invokevirtual 76	java/lang/Class:getMethod	(Ljava/lang/String;[Ljava/lang/Class;)Ljava/lang/reflect/Method;
    //   520: astore 11
    //   522: aload 11
    //   524: aload_0
    //   525: iconst_1
    //   526: anewarray 78	java/lang/Object
    //   529: dup
    //   530: iconst_0
    //   531: aload_1
    //   532: aastore
    //   533: invokevirtual 84	java/lang/reflect/Method:invoke	(Ljava/lang/Object;[Ljava/lang/Object;)Ljava/lang/Object;
    //   536: pop
    //   537: aload_0
    //   538: aconst_null
    //   539: putfield 160	uuuuuu/yyvvyv:b0067g0067006700670067g00670067	Lcom/db/pwcc/dbmobile/model/error/DbError;
    //   542: return
    //   543: astore_1
    //   544: aload_1
    //   545: invokevirtual 103	java/lang/reflect/InvocationTargetException:getCause	()Ljava/lang/Throwable;
    //   548: athrow
    //   549: astore_1
    //   550: aload_1
    //   551: invokevirtual 103	java/lang/reflect/InvocationTargetException:getCause	()Ljava/lang/Throwable;
    //   554: athrow
    //   555: astore_1
    //   556: aload_1
    //   557: invokevirtual 103	java/lang/reflect/InvocationTargetException:getCause	()Ljava/lang/Throwable;
    //   560: athrow
    //   561: astore_1
    //   562: aload_1
    //   563: invokevirtual 103	java/lang/reflect/InvocationTargetException:getCause	()Ljava/lang/Throwable;
    //   566: athrow
    //   567: astore_1
    //   568: aload_1
    //   569: invokevirtual 103	java/lang/reflect/InvocationTargetException:getCause	()Ljava/lang/Throwable;
    //   572: athrow
    //   573: astore_1
    //   574: aload_1
    //   575: invokevirtual 103	java/lang/reflect/InvocationTargetException:getCause	()Ljava/lang/Throwable;
    //   578: athrow
    //   579: astore_1
    //   580: aload_1
    //   581: invokevirtual 103	java/lang/reflect/InvocationTargetException:getCause	()Ljava/lang/Throwable;
    //   584: athrow
    //   585: astore_1
    //   586: aload_1
    //   587: invokevirtual 103	java/lang/reflect/InvocationTargetException:getCause	()Ljava/lang/Throwable;
    //   590: athrow
    //   591: astore_1
    //   592: aload_1
    //   593: invokevirtual 103	java/lang/reflect/InvocationTargetException:getCause	()Ljava/lang/Throwable;
    //   596: athrow
    // Local variable table:
    //   start	length	slot	name	signature
    //   0	597	0	this	yyvvyv
    //   0	597	1	paramVvyvyv	vyyvyv.vvyvyv
    //   64	375	2	i	int
    //   146	293	3	j	int
    //   150	292	4	k	int
    //   307	138	5	m	int
    //   312	136	6	n	int
    //   317	54	7	i1	int
    //   322	49	8	i2	int
    //   327	47	9	i3	int
    //   332	45	10	i4	int
    //   39	484	11	localObject	Object
    // Exception table:
    //   from	to	target	type
    //   354	366	543	java/lang/reflect/InvocationTargetException
    //   522	537	549	java/lang/reflect/InvocationTargetException
    //   41	56	555	java/lang/reflect/InvocationTargetException
    //   475	487	561	java/lang/reflect/InvocationTargetException
    //   114	124	567	java/lang/reflect/InvocationTargetException
    //   172	182	573	java/lang/reflect/InvocationTargetException
    //   408	420	579	java/lang/reflect/InvocationTargetException
    //   220	230	585	java/lang/reflect/InvocationTargetException
    //   258	268	591	java/lang/reflect/InvocationTargetException
  }
  
  /* Error */
  public String b0075uuuu0075u00750075u(String paramString1, String paramString2, java.util.Locale paramLocale)
  {
    // Byte code:
    //   0: getstatic 56	uuuuuu/yyvvyv:bgggggg006700670067	I
    //   3: istore 4
    //   5: getstatic 58	uuuuuu/yyvvyv:bg0067gggg006700670067	I
    //   8: istore 5
    //   10: getstatic 56	uuuuuu/yyvvyv:bgggggg006700670067	I
    //   13: getstatic 58	uuuuuu/yyvvyv:bg0067gggg006700670067	I
    //   16: iadd
    //   17: getstatic 56	uuuuuu/yyvvyv:bgggggg006700670067	I
    //   20: imul
    //   21: getstatic 60	uuuuuu/yyvvyv:b00670067gggg006700670067	I
    //   24: irem
    //   25: getstatic 62	uuuuuu/yyvvyv:b0067ggggg006700670067	I
    //   28: if_icmpeq +53 -> 81
    //   31: ldc 2
    //   33: ldc -5
    //   35: sipush 162
    //   38: bipush 107
    //   40: iconst_1
    //   41: invokestatic 70	xxxxxx/uxxxxx:bbbb0062b0062b0062b0062	(Ljava/lang/String;CCC)Ljava/lang/String;
    //   44: iconst_0
    //   45: anewarray 72	java/lang/Class
    //   48: invokevirtual 76	java/lang/Class:getMethod	(Ljava/lang/String;[Ljava/lang/Class;)Ljava/lang/reflect/Method;
    //   51: astore 8
    //   53: aload 8
    //   55: aconst_null
    //   56: iconst_0
    //   57: anewarray 78	java/lang/Object
    //   60: invokevirtual 84	java/lang/reflect/Method:invoke	(Ljava/lang/Object;[Ljava/lang/Object;)Ljava/lang/Object;
    //   63: astore 8
    //   65: aload 8
    //   67: checkcast 86	java/lang/Integer
    //   70: invokevirtual 87	java/lang/Integer:intValue	()I
    //   73: putstatic 56	uuuuuu/yyvvyv:bgggggg006700670067	I
    //   76: bipush 57
    //   78: putstatic 62	uuuuuu/yyvvyv:b0067ggggg006700670067	I
    //   81: getstatic 60	uuuuuu/yyvvyv:b00670067gggg006700670067	I
    //   84: istore 6
    //   86: getstatic 56	uuuuuu/yyvvyv:bgggggg006700670067	I
    //   89: istore 7
    //   91: iload 7
    //   93: getstatic 58	uuuuuu/yyvvyv:bg0067gggg006700670067	I
    //   96: iload 7
    //   98: iadd
    //   99: imul
    //   100: getstatic 60	uuuuuu/yyvvyv:b00670067gggg006700670067	I
    //   103: irem
    //   104: tableswitch	default:+20->124, 0:+70->174
    //   124: ldc 2
    //   126: ldc -3
    //   128: sipush 153
    //   131: bipush 84
    //   133: iconst_1
    //   134: invokestatic 70	xxxxxx/uxxxxx:bbbb0062b0062b0062b0062	(Ljava/lang/String;CCC)Ljava/lang/String;
    //   137: iconst_0
    //   138: anewarray 72	java/lang/Class
    //   141: invokevirtual 76	java/lang/Class:getMethod	(Ljava/lang/String;[Ljava/lang/Class;)Ljava/lang/reflect/Method;
    //   144: astore 8
    //   146: aload 8
    //   148: aconst_null
    //   149: iconst_0
    //   150: anewarray 78	java/lang/Object
    //   153: invokevirtual 84	java/lang/reflect/Method:invoke	(Ljava/lang/Object;[Ljava/lang/Object;)Ljava/lang/Object;
    //   156: astore 8
    //   158: aload 8
    //   160: checkcast 86	java/lang/Integer
    //   163: invokevirtual 87	java/lang/Integer:intValue	()I
    //   166: putstatic 56	uuuuuu/yyvvyv:bgggggg006700670067	I
    //   169: bipush 42
    //   171: putstatic 62	uuuuuu/yyvvyv:b0067ggggg006700670067	I
    //   174: iload 4
    //   176: iload 4
    //   178: iload 5
    //   180: iadd
    //   181: imul
    //   182: iload 6
    //   184: irem
    //   185: tableswitch	default:+19->204, 0:+111->296
    //   204: ldc 2
    //   206: ldc -1
    //   208: sipush 169
    //   211: bipush 93
    //   213: iconst_0
    //   214: invokestatic 70	xxxxxx/uxxxxx:bbbb0062b0062b0062b0062	(Ljava/lang/String;CCC)Ljava/lang/String;
    //   217: iconst_0
    //   218: anewarray 72	java/lang/Class
    //   221: invokevirtual 76	java/lang/Class:getMethod	(Ljava/lang/String;[Ljava/lang/Class;)Ljava/lang/reflect/Method;
    //   224: astore 8
    //   226: aload 8
    //   228: aconst_null
    //   229: iconst_0
    //   230: anewarray 78	java/lang/Object
    //   233: invokevirtual 84	java/lang/reflect/Method:invoke	(Ljava/lang/Object;[Ljava/lang/Object;)Ljava/lang/Object;
    //   236: astore 8
    //   238: aload 8
    //   240: checkcast 86	java/lang/Integer
    //   243: invokevirtual 87	java/lang/Integer:intValue	()I
    //   246: putstatic 56	uuuuuu/yyvvyv:bgggggg006700670067	I
    //   249: ldc 2
    //   251: ldc_w 257
    //   254: sipush 201
    //   257: sipush 204
    //   260: iconst_1
    //   261: invokestatic 70	xxxxxx/uxxxxx:bbbb0062b0062b0062b0062	(Ljava/lang/String;CCC)Ljava/lang/String;
    //   264: iconst_0
    //   265: anewarray 72	java/lang/Class
    //   268: invokevirtual 76	java/lang/Class:getMethod	(Ljava/lang/String;[Ljava/lang/Class;)Ljava/lang/reflect/Method;
    //   271: astore 8
    //   273: aload 8
    //   275: aconst_null
    //   276: iconst_0
    //   277: anewarray 78	java/lang/Object
    //   280: invokevirtual 84	java/lang/reflect/Method:invoke	(Ljava/lang/Object;[Ljava/lang/Object;)Ljava/lang/Object;
    //   283: astore 8
    //   285: aload 8
    //   287: checkcast 86	java/lang/Integer
    //   290: invokevirtual 87	java/lang/Integer:intValue	()I
    //   293: putstatic 62	uuuuuu/yyvvyv:b0067ggggg006700670067	I
    //   296: new 51	java/math/BigDecimal
    //   299: dup
    //   300: aload_1
    //   301: invokespecial 260	java/math/BigDecimal:<init>	(Ljava/lang/String;)V
    //   304: invokevirtual 264	java/math/BigDecimal:negate	()Ljava/math/BigDecimal;
    //   307: astore_1
    //   308: getstatic 56	uuuuuu/yyvvyv:bgggggg006700670067	I
    //   311: getstatic 58	uuuuuu/yyvvyv:bg0067gggg006700670067	I
    //   314: iadd
    //   315: getstatic 56	uuuuuu/yyvvyv:bgggggg006700670067	I
    //   318: imul
    //   319: getstatic 60	uuuuuu/yyvvyv:b00670067gggg006700670067	I
    //   322: irem
    //   323: getstatic 62	uuuuuu/yyvvyv:b0067ggggg006700670067	I
    //   326: if_icmpeq +91 -> 417
    //   329: ldc 2
    //   331: ldc -15
    //   333: sipush 138
    //   336: iconst_0
    //   337: invokestatic 93	xxxxxx/uxxxxx:bb00620062bb0062b0062b0062	(Ljava/lang/String;CC)Ljava/lang/String;
    //   340: iconst_0
    //   341: anewarray 72	java/lang/Class
    //   344: invokevirtual 76	java/lang/Class:getMethod	(Ljava/lang/String;[Ljava/lang/Class;)Ljava/lang/reflect/Method;
    //   347: astore 8
    //   349: aload 8
    //   351: aconst_null
    //   352: iconst_0
    //   353: anewarray 78	java/lang/Object
    //   356: invokevirtual 84	java/lang/reflect/Method:invoke	(Ljava/lang/Object;[Ljava/lang/Object;)Ljava/lang/Object;
    //   359: astore 8
    //   361: aload 8
    //   363: checkcast 86	java/lang/Integer
    //   366: invokevirtual 87	java/lang/Integer:intValue	()I
    //   369: putstatic 56	uuuuuu/yyvvyv:bgggggg006700670067	I
    //   372: ldc 2
    //   374: ldc_w 266
    //   377: bipush 112
    //   379: bipush 15
    //   381: iconst_2
    //   382: invokestatic 70	xxxxxx/uxxxxx:bbbb0062b0062b0062b0062	(Ljava/lang/String;CCC)Ljava/lang/String;
    //   385: iconst_0
    //   386: anewarray 72	java/lang/Class
    //   389: invokevirtual 76	java/lang/Class:getMethod	(Ljava/lang/String;[Ljava/lang/Class;)Ljava/lang/reflect/Method;
    //   392: astore 8
    //   394: aload 8
    //   396: aconst_null
    //   397: iconst_0
    //   398: anewarray 78	java/lang/Object
    //   401: invokevirtual 84	java/lang/reflect/Method:invoke	(Ljava/lang/Object;[Ljava/lang/Object;)Ljava/lang/Object;
    //   404: astore 8
    //   406: aload 8
    //   408: checkcast 86	java/lang/Integer
    //   411: invokevirtual 87	java/lang/Integer:intValue	()I
    //   414: putstatic 62	uuuuuu/yyvvyv:b0067ggggg006700670067	I
    //   417: aload_1
    //   418: aload_2
    //   419: aload_3
    //   420: invokestatic 272	uuuuuu/hhhpph:bw0077wwwwww0077w	(Ljava/math/BigDecimal;Ljava/lang/String;Ljava/util/Locale;)Ljava/lang/String;
    //   423: areturn
    //   424: astore_1
    //   425: aload_1
    //   426: invokevirtual 103	java/lang/reflect/InvocationTargetException:getCause	()Ljava/lang/Throwable;
    //   429: athrow
    //   430: astore_1
    //   431: aload_1
    //   432: invokevirtual 103	java/lang/reflect/InvocationTargetException:getCause	()Ljava/lang/Throwable;
    //   435: athrow
    //   436: astore_1
    //   437: aload_1
    //   438: invokevirtual 103	java/lang/reflect/InvocationTargetException:getCause	()Ljava/lang/Throwable;
    //   441: athrow
    //   442: astore_1
    //   443: aload_1
    //   444: invokevirtual 103	java/lang/reflect/InvocationTargetException:getCause	()Ljava/lang/Throwable;
    //   447: athrow
    //   448: astore_1
    //   449: aload_1
    //   450: invokevirtual 103	java/lang/reflect/InvocationTargetException:getCause	()Ljava/lang/Throwable;
    //   453: athrow
    //   454: astore_1
    //   455: aload_1
    //   456: invokevirtual 103	java/lang/reflect/InvocationTargetException:getCause	()Ljava/lang/Throwable;
    //   459: athrow
    // Local variable table:
    //   start	length	slot	name	signature
    //   0	460	0	this	yyvvyv
    //   0	460	1	paramString1	String
    //   0	460	2	paramString2	String
    //   0	460	3	paramLocale	java.util.Locale
    //   3	179	4	i	int
    //   8	173	5	j	int
    //   84	101	6	k	int
    //   89	11	7	m	int
    //   51	356	8	localObject	Object
    // Exception table:
    //   from	to	target	type
    //   226	238	424	java/lang/reflect/InvocationTargetException
    //   273	285	430	java/lang/reflect/InvocationTargetException
    //   53	65	436	java/lang/reflect/InvocationTargetException
    //   349	361	442	java/lang/reflect/InvocationTargetException
    //   394	406	448	java/lang/reflect/InvocationTargetException
    //   146	158	454	java/lang/reflect/InvocationTargetException
  }
  
  /* Error */
  public void bu007500750075u0075u00750075u(MortgageDetails paramMortgageDetails)
  {
    // Byte code:
    //   0: aload_0
    //   1: invokevirtual 156	uuuuuu/yyvvyv:bkk006Bk006Bk006Bk006Bk	()Z
    //   4: ifne +14 -> 18
    //   7: aload_0
    //   8: aload_1
    //   9: putfield 158	uuuuuu/yyvvyv:bg00670067006700670067g00670067	Lcom/db/pwcc/dbmobile/mortgages/model/details/MortgageDetails;
    //   12: aload_0
    //   13: aconst_null
    //   14: putfield 160	uuuuuu/yyvvyv:b0067g0067006700670067g00670067	Lcom/db/pwcc/dbmobile/model/error/DbError;
    //   17: return
    //   18: new 292	uuuuuu/xxxxxs
    //   21: dup
    //   22: invokespecial 293	uuuuuu/xxxxxs:<init>	()V
    //   25: astore_3
    //   26: aload_0
    //   27: getfield 183	uuuuuu/yyvvyv:bnnnnn006E006E006En	Luuuuuu/ttssst$tsssst;
    //   30: checkcast 175	uuuuuu/vyyvyv$vvyvyv
    //   33: aload_3
    //   34: aload_1
    //   35: invokevirtual 296	com/db/pwcc/dbmobile/mortgages/model/details/MortgageDetails:getIban	()Ljava/lang/String;
    //   38: invokevirtual 300	uuuuuu/xxxxxs:bkk006B006Bk006B006Bk006B006B	(Ljava/lang/String;)Ljava/lang/String;
    //   41: invokeinterface 303 2 0
    //   46: aload_0
    //   47: getfield 183	uuuuuu/yyvvyv:bnnnnn006E006E006En	Luuuuuu/ttssst$tsssst;
    //   50: checkcast 175	uuuuuu/vyyvyv$vvyvyv
    //   53: new 305	uuuuuu/mmqqqq
    //   56: dup
    //   57: aload_1
    //   58: invokespecial 307	uuuuuu/mmqqqq:<init>	(Lcom/db/pwcc/dbmobile/mortgages/model/details/MortgageDetails;)V
    //   61: aload_0
    //   62: getfield 183	uuuuuu/yyvvyv:bnnnnn006E006E006En	Luuuuuu/ttssst$tsssst;
    //   65: checkcast 175	uuuuuu/vyyvyv$vvyvyv
    //   68: invokeinterface 311 1 0
    //   73: invokevirtual 315	uuuuuu/mmqqqq:b007500750075u00750075007500750075u	(Landroid/content/res/Resources;)Ljava/util/List;
    //   76: invokeinterface 319 2 0
    //   81: aload_0
    //   82: getfield 183	uuuuuu/yyvvyv:bnnnnn006E006E006En	Luuuuuu/ttssst$tsssst;
    //   85: checkcast 175	uuuuuu/vyyvyv$vvyvyv
    //   88: aload_1
    //   89: invokevirtual 118	com/db/pwcc/dbmobile/mortgages/model/details/MortgageDetails:getContract	()Lcom/db/pwcc/dbmobile/mortgages/model/details/Contract;
    //   92: invokevirtual 322	com/db/pwcc/dbmobile/mortgages/model/details/Contract:isUnscheduledPaymentOptionAvailable	()Z
    //   95: invokeinterface 326 2 0
    //   100: aload_0
    //   101: getfield 183	uuuuuu/yyvvyv:bnnnnn006E006E006En	Luuuuuu/ttssst$tsssst;
    //   104: checkcast 175	uuuuuu/vyyvyv$vvyvyv
    //   107: aload_1
    //   108: invokevirtual 118	com/db/pwcc/dbmobile/mortgages/model/details/MortgageDetails:getContract	()Lcom/db/pwcc/dbmobile/mortgages/model/details/Contract;
    //   111: invokevirtual 329	com/db/pwcc/dbmobile/mortgages/model/details/Contract:isLoanInsuranceAvailable	()Z
    //   114: invokeinterface 332 2 0
    //   119: aload_0
    //   120: getfield 183	uuuuuu/yyvvyv:bnnnnn006E006E006En	Luuuuuu/ttssst$tsssst;
    //   123: checkcast 175	uuuuuu/vyyvyv$vvyvyv
    //   126: astore_3
    //   127: ldc 2
    //   129: ldc_w 334
    //   132: sipush 133
    //   135: sipush 212
    //   138: iconst_2
    //   139: invokestatic 70	xxxxxx/uxxxxx:bbbb0062b0062b0062b0062	(Ljava/lang/String;CCC)Ljava/lang/String;
    //   142: iconst_1
    //   143: anewarray 72	java/lang/Class
    //   146: dup
    //   147: iconst_0
    //   148: ldc 114
    //   150: aastore
    //   151: invokevirtual 76	java/lang/Class:getMethod	(Ljava/lang/String;[Ljava/lang/Class;)Ljava/lang/reflect/Method;
    //   154: astore 4
    //   156: aload 4
    //   158: aload_0
    //   159: iconst_1
    //   160: anewarray 78	java/lang/Object
    //   163: dup
    //   164: iconst_0
    //   165: aload_1
    //   166: aastore
    //   167: invokevirtual 84	java/lang/reflect/Method:invoke	(Ljava/lang/Object;[Ljava/lang/Object;)Ljava/lang/Object;
    //   170: astore 4
    //   172: aload 4
    //   174: checkcast 86	java/lang/Integer
    //   177: invokevirtual 87	java/lang/Integer:intValue	()I
    //   180: istore_2
    //   181: ldc 2
    //   183: ldc_w 336
    //   186: bipush 114
    //   188: iconst_1
    //   189: invokestatic 93	xxxxxx/uxxxxx:bb00620062bb0062b0062b0062	(Ljava/lang/String;CC)Ljava/lang/String;
    //   192: iconst_1
    //   193: anewarray 72	java/lang/Class
    //   196: dup
    //   197: iconst_0
    //   198: ldc 114
    //   200: aastore
    //   201: invokevirtual 76	java/lang/Class:getMethod	(Ljava/lang/String;[Ljava/lang/Class;)Ljava/lang/reflect/Method;
    //   204: astore 4
    //   206: aload 4
    //   208: aload_0
    //   209: iconst_1
    //   210: anewarray 78	java/lang/Object
    //   213: dup
    //   214: iconst_0
    //   215: aload_1
    //   216: aastore
    //   217: invokevirtual 84	java/lang/reflect/Method:invoke	(Ljava/lang/Object;[Ljava/lang/Object;)Ljava/lang/Object;
    //   220: astore_1
    //   221: aload_3
    //   222: iload_2
    //   223: aload_1
    //   224: checkcast 131	java/lang/String
    //   227: invokeinterface 340 3 0
    //   232: aload_0
    //   233: getfield 183	uuuuuu/yyvvyv:bnnnnn006E006E006En	Luuuuuu/ttssst$tsssst;
    //   236: checkcast 175	uuuuuu/vyyvyv$vvyvyv
    //   239: invokeinterface 343 1 0
    //   244: new 345	java/lang/NullPointerException
    //   247: dup
    //   248: invokespecial 346	java/lang/NullPointerException:<init>	()V
    //   251: athrow
    //   252: astore_1
    //   253: bipush 65
    //   255: putstatic 56	uuuuuu/yyvvyv:bgggggg006700670067	I
    //   258: new 345	java/lang/NullPointerException
    //   261: dup
    //   262: invokespecial 346	java/lang/NullPointerException:<init>	()V
    //   265: athrow
    //   266: astore_1
    //   267: ldc 2
    //   269: ldc_w 348
    //   272: sipush 129
    //   275: iconst_0
    //   276: invokestatic 93	xxxxxx/uxxxxx:bb00620062bb0062b0062b0062	(Ljava/lang/String;CC)Ljava/lang/String;
    //   279: iconst_0
    //   280: anewarray 72	java/lang/Class
    //   283: invokevirtual 76	java/lang/Class:getMethod	(Ljava/lang/String;[Ljava/lang/Class;)Ljava/lang/reflect/Method;
    //   286: astore_1
    //   287: aload_1
    //   288: aconst_null
    //   289: iconst_0
    //   290: anewarray 78	java/lang/Object
    //   293: invokevirtual 84	java/lang/reflect/Method:invoke	(Ljava/lang/Object;[Ljava/lang/Object;)Ljava/lang/Object;
    //   296: astore_1
    //   297: aload_1
    //   298: checkcast 86	java/lang/Integer
    //   301: invokevirtual 87	java/lang/Integer:intValue	()I
    //   304: putstatic 56	uuuuuu/yyvvyv:bgggggg006700670067	I
    //   307: new 345	java/lang/NullPointerException
    //   310: dup
    //   311: invokespecial 346	java/lang/NullPointerException:<init>	()V
    //   314: athrow
    //   315: astore_1
    //   316: bipush 18
    //   318: putstatic 56	uuuuuu/yyvvyv:bgggggg006700670067	I
    //   321: getstatic 56	uuuuuu/yyvvyv:bgggggg006700670067	I
    //   324: getstatic 58	uuuuuu/yyvvyv:bg0067gggg006700670067	I
    //   327: iadd
    //   328: getstatic 56	uuuuuu/yyvvyv:bgggggg006700670067	I
    //   331: imul
    //   332: getstatic 60	uuuuuu/yyvvyv:b00670067gggg006700670067	I
    //   335: irem
    //   336: getstatic 62	uuuuuu/yyvvyv:b0067ggggg006700670067	I
    //   339: if_icmpeq -322 -> 17
    //   342: bipush 50
    //   344: putstatic 56	uuuuuu/yyvvyv:bgggggg006700670067	I
    //   347: bipush 26
    //   349: putstatic 62	uuuuuu/yyvvyv:b0067ggggg006700670067	I
    //   352: return
    //   353: astore_1
    //   354: aload_1
    //   355: invokevirtual 103	java/lang/reflect/InvocationTargetException:getCause	()Ljava/lang/Throwable;
    //   358: athrow
    //   359: astore_1
    //   360: aload_1
    //   361: invokevirtual 103	java/lang/reflect/InvocationTargetException:getCause	()Ljava/lang/Throwable;
    //   364: athrow
    //   365: astore_1
    //   366: aload_1
    //   367: invokevirtual 103	java/lang/reflect/InvocationTargetException:getCause	()Ljava/lang/Throwable;
    //   370: athrow
    // Local variable table:
    //   start	length	slot	name	signature
    //   0	371	0	this	yyvvyv
    //   0	371	1	paramMortgageDetails	MortgageDetails
    //   180	43	2	i	int
    //   25	197	3	localObject1	Object
    //   154	53	4	localObject2	Object
    // Exception table:
    //   from	to	target	type
    //   244	252	252	java/lang/Exception
    //   258	266	266	java/lang/Exception
    //   307	315	315	java/lang/Exception
    //   156	172	353	java/lang/reflect/InvocationTargetException
    //   287	297	359	java/lang/reflect/InvocationTargetException
    //   206	221	365	java/lang/reflect/InvocationTargetException
  }
  
  /* Error */
  public void bu00750075uu0075u00750075u()
  {
    // Byte code:
    //   0: getstatic 352	uuuuuu/vvrvrv:b0068h00680068hh006800680068	Luuuuuu/vvrvrv;
    //   3: invokestatic 215	uuuuuu/rrvvrv:b0071q0071qq0071q0071q0071	(Luuuuuu/vvrvrv;)V
    //   6: aload_0
    //   7: getfield 183	uuuuuu/yyvvyv:bnnnnn006E006E006En	Luuuuuu/ttssst$tsssst;
    //   10: checkcast 175	uuuuuu/vyyvyv$vvyvyv
    //   13: getstatic 355	com/db/pwcc/dbmobile/mortgages/R$string:mortgage_info_title_unscheduled_repayment	I
    //   16: getstatic 358	com/db/pwcc/dbmobile/mortgages/R$string:mortgage_info_content_unscheduled_repayment	I
    //   19: invokeinterface 225 3 0
    //   24: getstatic 56	uuuuuu/yyvvyv:bgggggg006700670067	I
    //   27: istore_1
    //   28: iload_1
    //   29: getstatic 58	uuuuuu/yyvvyv:bg0067gggg006700670067	I
    //   32: iload_1
    //   33: iadd
    //   34: imul
    //   35: getstatic 60	uuuuuu/yyvvyv:b00670067gggg006700670067	I
    //   38: irem
    //   39: tableswitch	default:+17->56, 0:+27->66
    //   56: bipush 93
    //   58: putstatic 56	uuuuuu/yyvvyv:bgggggg006700670067	I
    //   61: bipush 99
    //   63: putstatic 62	uuuuuu/yyvvyv:b0067ggggg006700670067	I
    //   66: ldc 2
    //   68: ldc_w 360
    //   71: sipush 194
    //   74: sipush 232
    //   77: iconst_0
    //   78: invokestatic 70	xxxxxx/uxxxxx:bbbb0062b0062b0062b0062	(Ljava/lang/String;CCC)Ljava/lang/String;
    //   81: iconst_0
    //   82: anewarray 72	java/lang/Class
    //   85: invokevirtual 76	java/lang/Class:getMethod	(Ljava/lang/String;[Ljava/lang/Class;)Ljava/lang/reflect/Method;
    //   88: astore_2
    //   89: aload_2
    //   90: aconst_null
    //   91: iconst_0
    //   92: anewarray 78	java/lang/Object
    //   95: invokevirtual 84	java/lang/reflect/Method:invoke	(Ljava/lang/Object;[Ljava/lang/Object;)Ljava/lang/Object;
    //   98: astore_2
    //   99: aload_2
    //   100: checkcast 86	java/lang/Integer
    //   103: invokevirtual 87	java/lang/Integer:intValue	()I
    //   106: istore_1
    //   107: iload_1
    //   108: getstatic 58	uuuuuu/yyvvyv:bg0067gggg006700670067	I
    //   111: iload_1
    //   112: iadd
    //   113: imul
    //   114: getstatic 60	uuuuuu/yyvvyv:b00670067gggg006700670067	I
    //   117: irem
    //   118: tableswitch	default:+18->136, 0:+251->369
    //   136: bipush 32
    //   138: putstatic 56	uuuuuu/yyvvyv:bgggggg006700670067	I
    //   141: ldc 2
    //   143: ldc_w 362
    //   146: sipush 253
    //   149: iconst_2
    //   150: invokestatic 93	xxxxxx/uxxxxx:bb00620062bb0062b0062b0062	(Ljava/lang/String;CC)Ljava/lang/String;
    //   153: iconst_0
    //   154: anewarray 72	java/lang/Class
    //   157: invokevirtual 76	java/lang/Class:getMethod	(Ljava/lang/String;[Ljava/lang/Class;)Ljava/lang/reflect/Method;
    //   160: astore_2
    //   161: aload_2
    //   162: aconst_null
    //   163: iconst_0
    //   164: anewarray 78	java/lang/Object
    //   167: invokevirtual 84	java/lang/reflect/Method:invoke	(Ljava/lang/Object;[Ljava/lang/Object;)Ljava/lang/Object;
    //   170: astore_2
    //   171: aload_2
    //   172: checkcast 86	java/lang/Integer
    //   175: invokevirtual 87	java/lang/Integer:intValue	()I
    //   178: putstatic 62	uuuuuu/yyvvyv:b0067ggggg006700670067	I
    //   181: ldc 2
    //   183: ldc_w 280
    //   186: bipush 65
    //   188: iconst_3
    //   189: invokestatic 93	xxxxxx/uxxxxx:bb00620062bb0062b0062b0062	(Ljava/lang/String;CC)Ljava/lang/String;
    //   192: iconst_0
    //   193: anewarray 72	java/lang/Class
    //   196: invokevirtual 76	java/lang/Class:getMethod	(Ljava/lang/String;[Ljava/lang/Class;)Ljava/lang/reflect/Method;
    //   199: astore_2
    //   200: aload_2
    //   201: aconst_null
    //   202: iconst_0
    //   203: anewarray 78	java/lang/Object
    //   206: invokevirtual 84	java/lang/reflect/Method:invoke	(Ljava/lang/Object;[Ljava/lang/Object;)Ljava/lang/Object;
    //   209: astore_2
    //   210: aload_2
    //   211: checkcast 86	java/lang/Integer
    //   214: invokevirtual 87	java/lang/Integer:intValue	()I
    //   217: istore_1
    //   218: iload_1
    //   219: getstatic 58	uuuuuu/yyvvyv:bg0067gggg006700670067	I
    //   222: iload_1
    //   223: iadd
    //   224: imul
    //   225: getstatic 60	uuuuuu/yyvvyv:b00670067gggg006700670067	I
    //   228: irem
    //   229: tableswitch	default:+19->248, 0:+140->369
    //   248: iconst_0
    //   249: putstatic 56	uuuuuu/yyvvyv:bgggggg006700670067	I
    //   252: ldc 2
    //   254: ldc_w 364
    //   257: sipush 254
    //   260: iconst_0
    //   261: invokestatic 93	xxxxxx/uxxxxx:bb00620062bb0062b0062b0062	(Ljava/lang/String;CC)Ljava/lang/String;
    //   264: iconst_0
    //   265: anewarray 72	java/lang/Class
    //   268: invokevirtual 76	java/lang/Class:getMethod	(Ljava/lang/String;[Ljava/lang/Class;)Ljava/lang/reflect/Method;
    //   271: astore_2
    //   272: aload_2
    //   273: aconst_null
    //   274: iconst_0
    //   275: anewarray 78	java/lang/Object
    //   278: invokevirtual 84	java/lang/reflect/Method:invoke	(Ljava/lang/Object;[Ljava/lang/Object;)Ljava/lang/Object;
    //   281: astore_2
    //   282: aload_2
    //   283: checkcast 86	java/lang/Integer
    //   286: invokevirtual 87	java/lang/Integer:intValue	()I
    //   289: istore_1
    //   290: iload_1
    //   291: getstatic 58	uuuuuu/yyvvyv:bg0067gggg006700670067	I
    //   294: iload_1
    //   295: iadd
    //   296: imul
    //   297: getstatic 60	uuuuuu/yyvvyv:b00670067gggg006700670067	I
    //   300: irem
    //   301: tableswitch	default:+19->320, 0:+63->364
    //   320: bipush 30
    //   322: putstatic 56	uuuuuu/yyvvyv:bgggggg006700670067	I
    //   325: ldc 2
    //   327: ldc_w 366
    //   330: bipush 9
    //   332: iconst_1
    //   333: invokestatic 93	xxxxxx/uxxxxx:bb00620062bb0062b0062b0062	(Ljava/lang/String;CC)Ljava/lang/String;
    //   336: iconst_0
    //   337: anewarray 72	java/lang/Class
    //   340: invokevirtual 76	java/lang/Class:getMethod	(Ljava/lang/String;[Ljava/lang/Class;)Ljava/lang/reflect/Method;
    //   343: astore_2
    //   344: aload_2
    //   345: aconst_null
    //   346: iconst_0
    //   347: anewarray 78	java/lang/Object
    //   350: invokevirtual 84	java/lang/reflect/Method:invoke	(Ljava/lang/Object;[Ljava/lang/Object;)Ljava/lang/Object;
    //   353: astore_2
    //   354: aload_2
    //   355: checkcast 86	java/lang/Integer
    //   358: invokevirtual 87	java/lang/Integer:intValue	()I
    //   361: putstatic 62	uuuuuu/yyvvyv:b0067ggggg006700670067	I
    //   364: bipush 72
    //   366: putstatic 62	uuuuuu/yyvvyv:b0067ggggg006700670067	I
    //   369: return
    //   370: astore_2
    //   371: aload_2
    //   372: invokevirtual 103	java/lang/reflect/InvocationTargetException:getCause	()Ljava/lang/Throwable;
    //   375: athrow
    //   376: astore_2
    //   377: aload_2
    //   378: invokevirtual 103	java/lang/reflect/InvocationTargetException:getCause	()Ljava/lang/Throwable;
    //   381: athrow
    //   382: astore_2
    //   383: aload_2
    //   384: invokevirtual 103	java/lang/reflect/InvocationTargetException:getCause	()Ljava/lang/Throwable;
    //   387: athrow
    //   388: astore_2
    //   389: aload_2
    //   390: invokevirtual 103	java/lang/reflect/InvocationTargetException:getCause	()Ljava/lang/Throwable;
    //   393: athrow
    //   394: astore_2
    //   395: aload_2
    //   396: invokevirtual 103	java/lang/reflect/InvocationTargetException:getCause	()Ljava/lang/Throwable;
    //   399: athrow
    // Local variable table:
    //   start	length	slot	name	signature
    //   0	400	0	this	yyvvyv
    //   27	270	1	i	int
    //   88	267	2	localObject	Object
    //   370	2	2	localInvocationTargetException1	java.lang.reflect.InvocationTargetException
    //   376	2	2	localInvocationTargetException2	java.lang.reflect.InvocationTargetException
    //   382	2	2	localInvocationTargetException3	java.lang.reflect.InvocationTargetException
    //   388	2	2	localInvocationTargetException4	java.lang.reflect.InvocationTargetException
    //   394	2	2	localInvocationTargetException5	java.lang.reflect.InvocationTargetException
    // Exception table:
    //   from	to	target	type
    //   272	282	370	java/lang/reflect/InvocationTargetException
    //   200	210	376	java/lang/reflect/InvocationTargetException
    //   161	171	382	java/lang/reflect/InvocationTargetException
    //   89	99	388	java/lang/reflect/InvocationTargetException
    //   344	354	394	java/lang/reflect/InvocationTargetException
  }
  
  /* Error */
  public String bu0075uuu0075u00750075u(MortgageDetails paramMortgageDetails)
  {
    // Byte code:
    //   0: new 44	uuuuuu/mmmqqq
    //   3: dup
    //   4: invokespecial 45	uuuuuu/mmmqqq:<init>	()V
    //   7: astore 8
    //   9: aload 8
    //   11: aload_1
    //   12: invokevirtual 118	com/db/pwcc/dbmobile/mortgages/model/details/MortgageDetails:getContract	()Lcom/db/pwcc/dbmobile/mortgages/model/details/Contract;
    //   15: invokevirtual 124	com/db/pwcc/dbmobile/mortgages/model/details/Contract:getOriginalAmount	()Ljava/lang/String;
    //   18: aload_1
    //   19: invokevirtual 127	com/db/pwcc/dbmobile/mortgages/model/details/MortgageDetails:getCurrentBalance	()Ljava/lang/String;
    //   22: invokevirtual 49	uuuuuu/mmmqqq:bu00750075007500750075007500750075u	(Ljava/lang/String;Ljava/lang/String;)Ljava/math/BigDecimal;
    //   25: astore_1
    //   26: ldc 2
    //   28: ldc_w 370
    //   31: bipush 90
    //   33: iconst_5
    //   34: invokestatic 93	xxxxxx/uxxxxx:bb00620062bb0062b0062b0062	(Ljava/lang/String;CC)Ljava/lang/String;
    //   37: iconst_0
    //   38: anewarray 72	java/lang/Class
    //   41: invokevirtual 76	java/lang/Class:getMethod	(Ljava/lang/String;[Ljava/lang/Class;)Ljava/lang/reflect/Method;
    //   44: astore 9
    //   46: aload 9
    //   48: aconst_null
    //   49: iconst_0
    //   50: anewarray 78	java/lang/Object
    //   53: invokevirtual 84	java/lang/reflect/Method:invoke	(Ljava/lang/Object;[Ljava/lang/Object;)Ljava/lang/Object;
    //   56: astore 9
    //   58: aload 9
    //   60: checkcast 86	java/lang/Integer
    //   63: invokevirtual 87	java/lang/Integer:intValue	()I
    //   66: istore_2
    //   67: getstatic 58	uuuuuu/yyvvyv:bg0067gggg006700670067	I
    //   70: istore_3
    //   71: ldc 2
    //   73: ldc_w 372
    //   76: sipush 210
    //   79: sipush 132
    //   82: iconst_3
    //   83: invokestatic 70	xxxxxx/uxxxxx:bbbb0062b0062b0062b0062	(Ljava/lang/String;CCC)Ljava/lang/String;
    //   86: iconst_0
    //   87: anewarray 72	java/lang/Class
    //   90: invokevirtual 76	java/lang/Class:getMethod	(Ljava/lang/String;[Ljava/lang/Class;)Ljava/lang/reflect/Method;
    //   93: astore 9
    //   95: aload 9
    //   97: aconst_null
    //   98: iconst_0
    //   99: anewarray 78	java/lang/Object
    //   102: invokevirtual 84	java/lang/reflect/Method:invoke	(Ljava/lang/Object;[Ljava/lang/Object;)Ljava/lang/Object;
    //   105: astore 9
    //   107: aload 9
    //   109: checkcast 86	java/lang/Integer
    //   112: invokevirtual 87	java/lang/Integer:intValue	()I
    //   115: istore 4
    //   117: getstatic 58	uuuuuu/yyvvyv:bg0067gggg006700670067	I
    //   120: istore 5
    //   122: ldc 2
    //   124: ldc_w 284
    //   127: bipush 30
    //   129: iconst_0
    //   130: invokestatic 93	xxxxxx/uxxxxx:bb00620062bb0062b0062b0062	(Ljava/lang/String;CC)Ljava/lang/String;
    //   133: iconst_0
    //   134: anewarray 72	java/lang/Class
    //   137: invokevirtual 76	java/lang/Class:getMethod	(Ljava/lang/String;[Ljava/lang/Class;)Ljava/lang/reflect/Method;
    //   140: astore 9
    //   142: aload 9
    //   144: aconst_null
    //   145: iconst_0
    //   146: anewarray 78	java/lang/Object
    //   149: invokevirtual 84	java/lang/reflect/Method:invoke	(Ljava/lang/Object;[Ljava/lang/Object;)Ljava/lang/Object;
    //   152: astore 9
    //   154: aload 9
    //   156: checkcast 86	java/lang/Integer
    //   159: invokevirtual 87	java/lang/Integer:intValue	()I
    //   162: iload 5
    //   164: iload 4
    //   166: iadd
    //   167: imul
    //   168: getstatic 60	uuuuuu/yyvvyv:b00670067gggg006700670067	I
    //   171: irem
    //   172: getstatic 62	uuuuuu/yyvvyv:b0067ggggg006700670067	I
    //   175: if_icmpeq +91 -> 266
    //   178: ldc 2
    //   180: ldc_w 374
    //   183: bipush 69
    //   185: bipush 85
    //   187: iconst_3
    //   188: invokestatic 70	xxxxxx/uxxxxx:bbbb0062b0062b0062b0062	(Ljava/lang/String;CCC)Ljava/lang/String;
    //   191: iconst_0
    //   192: anewarray 72	java/lang/Class
    //   195: invokevirtual 76	java/lang/Class:getMethod	(Ljava/lang/String;[Ljava/lang/Class;)Ljava/lang/reflect/Method;
    //   198: astore 9
    //   200: aload 9
    //   202: aconst_null
    //   203: iconst_0
    //   204: anewarray 78	java/lang/Object
    //   207: invokevirtual 84	java/lang/reflect/Method:invoke	(Ljava/lang/Object;[Ljava/lang/Object;)Ljava/lang/Object;
    //   210: astore 9
    //   212: aload 9
    //   214: checkcast 86	java/lang/Integer
    //   217: invokevirtual 87	java/lang/Integer:intValue	()I
    //   220: putstatic 56	uuuuuu/yyvvyv:bgggggg006700670067	I
    //   223: ldc 2
    //   225: ldc_w 376
    //   228: bipush 121
    //   230: iconst_3
    //   231: invokestatic 93	xxxxxx/uxxxxx:bb00620062bb0062b0062b0062	(Ljava/lang/String;CC)Ljava/lang/String;
    //   234: iconst_0
    //   235: anewarray 72	java/lang/Class
    //   238: invokevirtual 76	java/lang/Class:getMethod	(Ljava/lang/String;[Ljava/lang/Class;)Ljava/lang/reflect/Method;
    //   241: astore 9
    //   243: aload 9
    //   245: aconst_null
    //   246: iconst_0
    //   247: anewarray 78	java/lang/Object
    //   250: invokevirtual 84	java/lang/reflect/Method:invoke	(Ljava/lang/Object;[Ljava/lang/Object;)Ljava/lang/Object;
    //   253: astore 9
    //   255: aload 9
    //   257: checkcast 86	java/lang/Integer
    //   260: invokevirtual 87	java/lang/Integer:intValue	()I
    //   263: putstatic 62	uuuuuu/yyvvyv:b0067ggggg006700670067	I
    //   266: ldc 2
    //   268: ldc_w 378
    //   271: bipush 51
    //   273: iconst_4
    //   274: invokestatic 93	xxxxxx/uxxxxx:bb00620062bb0062b0062b0062	(Ljava/lang/String;CC)Ljava/lang/String;
    //   277: iconst_0
    //   278: anewarray 72	java/lang/Class
    //   281: invokevirtual 76	java/lang/Class:getMethod	(Ljava/lang/String;[Ljava/lang/Class;)Ljava/lang/reflect/Method;
    //   284: astore 9
    //   286: aload 9
    //   288: aconst_null
    //   289: iconst_0
    //   290: anewarray 78	java/lang/Object
    //   293: invokevirtual 84	java/lang/reflect/Method:invoke	(Ljava/lang/Object;[Ljava/lang/Object;)Ljava/lang/Object;
    //   296: astore 9
    //   298: aload 9
    //   300: checkcast 86	java/lang/Integer
    //   303: invokevirtual 87	java/lang/Integer:intValue	()I
    //   306: istore 4
    //   308: getstatic 58	uuuuuu/yyvvyv:bg0067gggg006700670067	I
    //   311: istore 5
    //   313: ldc 2
    //   315: ldc_w 380
    //   318: sipush 233
    //   321: iconst_1
    //   322: invokestatic 93	xxxxxx/uxxxxx:bb00620062bb0062b0062b0062	(Ljava/lang/String;CC)Ljava/lang/String;
    //   325: iconst_0
    //   326: anewarray 72	java/lang/Class
    //   329: invokevirtual 76	java/lang/Class:getMethod	(Ljava/lang/String;[Ljava/lang/Class;)Ljava/lang/reflect/Method;
    //   332: astore 9
    //   334: aload 9
    //   336: aconst_null
    //   337: iconst_0
    //   338: anewarray 78	java/lang/Object
    //   341: invokevirtual 84	java/lang/reflect/Method:invoke	(Ljava/lang/Object;[Ljava/lang/Object;)Ljava/lang/Object;
    //   344: astore 9
    //   346: aload 9
    //   348: checkcast 86	java/lang/Integer
    //   351: invokevirtual 87	java/lang/Integer:intValue	()I
    //   354: istore 6
    //   356: getstatic 60	uuuuuu/yyvvyv:b00670067gggg006700670067	I
    //   359: istore 7
    //   361: ldc 2
    //   363: ldc_w 382
    //   366: bipush 17
    //   368: iconst_4
    //   369: invokestatic 93	xxxxxx/uxxxxx:bb00620062bb0062b0062b0062	(Ljava/lang/String;CC)Ljava/lang/String;
    //   372: iconst_0
    //   373: anewarray 72	java/lang/Class
    //   376: invokevirtual 76	java/lang/Class:getMethod	(Ljava/lang/String;[Ljava/lang/Class;)Ljava/lang/reflect/Method;
    //   379: astore 9
    //   381: aload 9
    //   383: aconst_null
    //   384: iconst_0
    //   385: anewarray 78	java/lang/Object
    //   388: invokevirtual 84	java/lang/reflect/Method:invoke	(Ljava/lang/Object;[Ljava/lang/Object;)Ljava/lang/Object;
    //   391: astore 9
    //   393: iload 6
    //   395: iload 5
    //   397: iload 4
    //   399: iadd
    //   400: imul
    //   401: iload 7
    //   403: irem
    //   404: aload 9
    //   406: checkcast 86	java/lang/Integer
    //   409: invokevirtual 87	java/lang/Integer:intValue	()I
    //   412: if_icmpeq +51 -> 463
    //   415: bipush 62
    //   417: putstatic 56	uuuuuu/yyvvyv:bgggggg006700670067	I
    //   420: ldc 2
    //   422: ldc_w 384
    //   425: bipush 60
    //   427: iconst_3
    //   428: invokestatic 93	xxxxxx/uxxxxx:bb00620062bb0062b0062b0062	(Ljava/lang/String;CC)Ljava/lang/String;
    //   431: iconst_0
    //   432: anewarray 72	java/lang/Class
    //   435: invokevirtual 76	java/lang/Class:getMethod	(Ljava/lang/String;[Ljava/lang/Class;)Ljava/lang/reflect/Method;
    //   438: astore 9
    //   440: aload 9
    //   442: aconst_null
    //   443: iconst_0
    //   444: anewarray 78	java/lang/Object
    //   447: invokevirtual 84	java/lang/reflect/Method:invoke	(Ljava/lang/Object;[Ljava/lang/Object;)Ljava/lang/Object;
    //   450: astore 9
    //   452: aload 9
    //   454: checkcast 86	java/lang/Integer
    //   457: invokevirtual 87	java/lang/Integer:intValue	()I
    //   460: putstatic 62	uuuuuu/yyvvyv:b0067ggggg006700670067	I
    //   463: iload_2
    //   464: iload_3
    //   465: iadd
    //   466: iload_2
    //   467: imul
    //   468: getstatic 60	uuuuuu/yyvvyv:b00670067gggg006700670067	I
    //   471: irem
    //   472: tableswitch	default:+20->492, 0:+68->540
    //   492: ldc 2
    //   494: ldc_w 386
    //   497: bipush 115
    //   499: iconst_3
    //   500: invokestatic 93	xxxxxx/uxxxxx:bb00620062bb0062b0062b0062	(Ljava/lang/String;CC)Ljava/lang/String;
    //   503: iconst_0
    //   504: anewarray 72	java/lang/Class
    //   507: invokevirtual 76	java/lang/Class:getMethod	(Ljava/lang/String;[Ljava/lang/Class;)Ljava/lang/reflect/Method;
    //   510: astore 9
    //   512: aload 9
    //   514: aconst_null
    //   515: iconst_0
    //   516: anewarray 78	java/lang/Object
    //   519: invokevirtual 84	java/lang/reflect/Method:invoke	(Ljava/lang/Object;[Ljava/lang/Object;)Ljava/lang/Object;
    //   522: astore 9
    //   524: aload 9
    //   526: checkcast 86	java/lang/Integer
    //   529: invokevirtual 87	java/lang/Integer:intValue	()I
    //   532: putstatic 56	uuuuuu/yyvvyv:bgggggg006700670067	I
    //   535: bipush 9
    //   537: putstatic 62	uuuuuu/yyvvyv:b0067ggggg006700670067	I
    //   540: aload_0
    //   541: getfield 183	uuuuuu/yyvvyv:bnnnnn006E006E006En	Luuuuuu/ttssst$tsssst;
    //   544: checkcast 175	uuuuuu/vyyvyv$vvyvyv
    //   547: astore 9
    //   549: getstatic 56	uuuuuu/yyvvyv:bgggggg006700670067	I
    //   552: getstatic 58	uuuuuu/yyvvyv:bg0067gggg006700670067	I
    //   555: iadd
    //   556: getstatic 56	uuuuuu/yyvvyv:bgggggg006700670067	I
    //   559: imul
    //   560: getstatic 60	uuuuuu/yyvvyv:b00670067gggg006700670067	I
    //   563: irem
    //   564: getstatic 62	uuuuuu/yyvvyv:b0067ggggg006700670067	I
    //   567: if_icmpeq +51 -> 618
    //   570: ldc 2
    //   572: ldc_w 388
    //   575: bipush 51
    //   577: iconst_3
    //   578: invokestatic 93	xxxxxx/uxxxxx:bb00620062bb0062b0062b0062	(Ljava/lang/String;CC)Ljava/lang/String;
    //   581: iconst_0
    //   582: anewarray 72	java/lang/Class
    //   585: invokevirtual 76	java/lang/Class:getMethod	(Ljava/lang/String;[Ljava/lang/Class;)Ljava/lang/reflect/Method;
    //   588: astore 10
    //   590: aload 10
    //   592: aconst_null
    //   593: iconst_0
    //   594: anewarray 78	java/lang/Object
    //   597: invokevirtual 84	java/lang/reflect/Method:invoke	(Ljava/lang/Object;[Ljava/lang/Object;)Ljava/lang/Object;
    //   600: astore 10
    //   602: aload 10
    //   604: checkcast 86	java/lang/Integer
    //   607: invokevirtual 87	java/lang/Integer:intValue	()I
    //   610: putstatic 56	uuuuuu/yyvvyv:bgggggg006700670067	I
    //   613: bipush 28
    //   615: putstatic 62	uuuuuu/yyvvyv:b0067ggggg006700670067	I
    //   618: aload 8
    //   620: aload 9
    //   622: invokeinterface 311 1 0
    //   627: aload_1
    //   628: invokevirtual 392	uuuuuu/mmmqqq:b007500750075007500750075007500750075u	(Landroid/content/res/Resources;Ljava/math/BigDecimal;)Ljava/lang/String;
    //   631: areturn
    //   632: astore_1
    //   633: aload_1
    //   634: invokevirtual 103	java/lang/reflect/InvocationTargetException:getCause	()Ljava/lang/Throwable;
    //   637: athrow
    //   638: astore_1
    //   639: aload_1
    //   640: invokevirtual 103	java/lang/reflect/InvocationTargetException:getCause	()Ljava/lang/Throwable;
    //   643: athrow
    //   644: astore_1
    //   645: aload_1
    //   646: invokevirtual 103	java/lang/reflect/InvocationTargetException:getCause	()Ljava/lang/Throwable;
    //   649: athrow
    //   650: astore_1
    //   651: aload_1
    //   652: invokevirtual 103	java/lang/reflect/InvocationTargetException:getCause	()Ljava/lang/Throwable;
    //   655: athrow
    //   656: astore_1
    //   657: aload_1
    //   658: invokevirtual 103	java/lang/reflect/InvocationTargetException:getCause	()Ljava/lang/Throwable;
    //   661: athrow
    //   662: astore_1
    //   663: aload_1
    //   664: invokevirtual 103	java/lang/reflect/InvocationTargetException:getCause	()Ljava/lang/Throwable;
    //   667: athrow
    //   668: astore_1
    //   669: aload_1
    //   670: invokevirtual 103	java/lang/reflect/InvocationTargetException:getCause	()Ljava/lang/Throwable;
    //   673: athrow
    //   674: astore_1
    //   675: aload_1
    //   676: invokevirtual 103	java/lang/reflect/InvocationTargetException:getCause	()Ljava/lang/Throwable;
    //   679: athrow
    //   680: astore_1
    //   681: aload_1
    //   682: invokevirtual 103	java/lang/reflect/InvocationTargetException:getCause	()Ljava/lang/Throwable;
    //   685: athrow
    //   686: astore_1
    //   687: aload_1
    //   688: invokevirtual 103	java/lang/reflect/InvocationTargetException:getCause	()Ljava/lang/Throwable;
    //   691: athrow
    //   692: astore_1
    //   693: aload_1
    //   694: invokevirtual 103	java/lang/reflect/InvocationTargetException:getCause	()Ljava/lang/Throwable;
    //   697: athrow
    // Local variable table:
    //   start	length	slot	name	signature
    //   0	698	0	this	yyvvyv
    //   0	698	1	paramMortgageDetails	MortgageDetails
    //   66	402	2	i	int
    //   70	396	3	j	int
    //   115	285	4	k	int
    //   120	280	5	m	int
    //   354	47	6	n	int
    //   359	45	7	i1	int
    //   7	612	8	localMmmqqq	mmmqqq
    //   44	577	9	localObject1	Object
    //   588	15	10	localObject2	Object
    // Exception table:
    //   from	to	target	type
    //   46	58	632	java/lang/reflect/InvocationTargetException
    //   95	107	638	java/lang/reflect/InvocationTargetException
    //   142	154	644	java/lang/reflect/InvocationTargetException
    //   590	602	650	java/lang/reflect/InvocationTargetException
    //   286	298	656	java/lang/reflect/InvocationTargetException
    //   334	346	662	java/lang/reflect/InvocationTargetException
    //   381	393	668	java/lang/reflect/InvocationTargetException
    //   512	524	674	java/lang/reflect/InvocationTargetException
    //   200	212	680	java/lang/reflect/InvocationTargetException
    //   243	255	686	java/lang/reflect/InvocationTargetException
    //   440	452	692	java/lang/reflect/InvocationTargetException
  }
  
  public void buu0075uu0075u00750075u(String paramString)
  {
    throw new Runtime("d2j fail translate: java.lang.IndexOutOfBoundsException: fromIndex < 0: -1\n\tat java.util.BitSet.nextSetBit(BitSet.java:712)\n\tat com.googlecode.dex2jar.ir.ts.array.FillArrayTransformer.makeSureAllElementAreAssigned(FillArrayTransformer.java:505)\n\tat com.googlecode.dex2jar.ir.ts.array.FillArrayTransformer.transformReportChanged(FillArrayTransformer.java:123)\n\tat com.googlecode.dex2jar.ir.ts.StatedTransformer.transform(StatedTransformer.java:10)\n\tat com.googlecode.d2j.dex.Dex2jar$2.optimize(Dex2jar.java:149)\n\tat com.googlecode.d2j.dex.Dex2Asm.convertCode(Dex2Asm.java:414)\n\tat com.googlecode.d2j.dex.ExDex2Asm.convertCode(ExDex2Asm.java:42)\n\tat com.googlecode.d2j.dex.Dex2jar$2.convertCode(Dex2jar.java:128)\n\tat com.googlecode.d2j.dex.Dex2Asm.convertMethod(Dex2Asm.java:509)\n\tat com.googlecode.d2j.dex.Dex2Asm.convertClass(Dex2Asm.java:406)\n\tat com.googlecode.d2j.dex.Dex2Asm.convertDex(Dex2Asm.java:422)\n\tat com.googlecode.d2j.dex.Dex2jar.doTranslate(Dex2jar.java:172)\n\tat com.googlecode.d2j.dex.Dex2jar.to(Dex2jar.java:272)\n\tat com.googlecode.dex2jar.tools.Dex2jarCmd.doCommandLine(Dex2jarCmd.java:108)\n\tat com.googlecode.dex2jar.tools.BaseCmd.doMain(BaseCmd.java:288)\n\tat com.googlecode.dex2jar.tools.Dex2jarCmd.main(Dex2jarCmd.java:32)\n");
  }
  
  /* Error */
  public void buuuuu0075u00750075u()
  {
    // Byte code:
    //   0: aload_0
    //   1: getfield 405	uuuuuu/yyvvyv:b006En006E006E006En006E006En	Luuuuuu/ggyggy;
    //   4: astore 4
    //   6: getstatic 411	uuuuuu/gyyygy$yyyygy:bkkk006Bk006Bk006Bk	Luuuuuu/gyyygy$yyyygy;
    //   9: astore 5
    //   11: getstatic 56	uuuuuu/yyvvyv:bgggggg006700670067	I
    //   14: getstatic 58	uuuuuu/yyvvyv:bg0067gggg006700670067	I
    //   17: iadd
    //   18: getstatic 56	uuuuuu/yyvvyv:bgggggg006700670067	I
    //   21: imul
    //   22: getstatic 60	uuuuuu/yyvvyv:b00670067gggg006700670067	I
    //   25: irem
    //   26: getstatic 62	uuuuuu/yyvvyv:b0067ggggg006700670067	I
    //   29: if_icmpeq +82 -> 111
    //   32: getstatic 56	uuuuuu/yyvvyv:bgggggg006700670067	I
    //   35: getstatic 58	uuuuuu/yyvvyv:bg0067gggg006700670067	I
    //   38: iadd
    //   39: getstatic 56	uuuuuu/yyvvyv:bgggggg006700670067	I
    //   42: imul
    //   43: getstatic 60	uuuuuu/yyvvyv:b00670067gggg006700670067	I
    //   46: irem
    //   47: getstatic 62	uuuuuu/yyvvyv:b0067ggggg006700670067	I
    //   50: if_icmpeq +13 -> 63
    //   53: bipush 55
    //   55: putstatic 56	uuuuuu/yyvvyv:bgggggg006700670067	I
    //   58: bipush 55
    //   60: putstatic 62	uuuuuu/yyvvyv:b0067ggggg006700670067	I
    //   63: ldc 2
    //   65: ldc_w 413
    //   68: bipush 52
    //   70: iconst_1
    //   71: invokestatic 93	xxxxxx/uxxxxx:bb00620062bb0062b0062b0062	(Ljava/lang/String;CC)Ljava/lang/String;
    //   74: iconst_0
    //   75: anewarray 72	java/lang/Class
    //   78: invokevirtual 76	java/lang/Class:getMethod	(Ljava/lang/String;[Ljava/lang/Class;)Ljava/lang/reflect/Method;
    //   81: astore 6
    //   83: aload 6
    //   85: aconst_null
    //   86: iconst_0
    //   87: anewarray 78	java/lang/Object
    //   90: invokevirtual 84	java/lang/reflect/Method:invoke	(Ljava/lang/Object;[Ljava/lang/Object;)Ljava/lang/Object;
    //   93: astore 6
    //   95: aload 6
    //   97: checkcast 86	java/lang/Integer
    //   100: invokevirtual 87	java/lang/Integer:intValue	()I
    //   103: putstatic 56	uuuuuu/yyvvyv:bgggggg006700670067	I
    //   106: bipush 94
    //   108: putstatic 62	uuuuuu/yyvvyv:b0067ggggg006700670067	I
    //   111: aload 4
    //   113: aload 5
    //   115: invokevirtual 419	uuuuuu/ggyggy:b0070007000700070pp00700070pp	(Luuuuuu/gyyygy$yyyygy;)Luuuuuu/yyyggy;
    //   118: iconst_1
    //   119: anewarray 78	java/lang/Object
    //   122: dup
    //   123: iconst_0
    //   124: getstatic 425	uuuuuu/lolllo:b0071qqqqqqq0071	Luuuuuu/lolllo;
    //   127: invokevirtual 428	uuuuuu/lolllo:name	()Ljava/lang/String;
    //   130: aastore
    //   131: invokeinterface 434 2 0
    //   136: getstatic 56	uuuuuu/yyvvyv:bgggggg006700670067	I
    //   139: istore_1
    //   140: getstatic 58	uuuuuu/yyvvyv:bg0067gggg006700670067	I
    //   143: istore_2
    //   144: ldc 2
    //   146: ldc_w 436
    //   149: bipush 17
    //   151: iconst_4
    //   152: invokestatic 93	xxxxxx/uxxxxx:bb00620062bb0062b0062b0062	(Ljava/lang/String;CC)Ljava/lang/String;
    //   155: iconst_0
    //   156: anewarray 72	java/lang/Class
    //   159: invokevirtual 76	java/lang/Class:getMethod	(Ljava/lang/String;[Ljava/lang/Class;)Ljava/lang/reflect/Method;
    //   162: astore 4
    //   164: aload 4
    //   166: aconst_null
    //   167: iconst_0
    //   168: anewarray 78	java/lang/Object
    //   171: invokevirtual 84	java/lang/reflect/Method:invoke	(Ljava/lang/Object;[Ljava/lang/Object;)Ljava/lang/Object;
    //   174: astore 4
    //   176: aload 4
    //   178: checkcast 86	java/lang/Integer
    //   181: invokevirtual 87	java/lang/Integer:intValue	()I
    //   184: istore_3
    //   185: iload_3
    //   186: getstatic 58	uuuuuu/yyvvyv:bg0067gggg006700670067	I
    //   189: iload_3
    //   190: iadd
    //   191: imul
    //   192: getstatic 60	uuuuuu/yyvvyv:b00670067gggg006700670067	I
    //   195: irem
    //   196: tableswitch	default:+20->216, 0:+30->226
    //   216: bipush 40
    //   218: putstatic 56	uuuuuu/yyvvyv:bgggggg006700670067	I
    //   221: bipush 82
    //   223: putstatic 62	uuuuuu/yyvvyv:b0067ggggg006700670067	I
    //   226: iload_1
    //   227: iload_2
    //   228: iadd
    //   229: getstatic 56	uuuuuu/yyvvyv:bgggggg006700670067	I
    //   232: imul
    //   233: getstatic 60	uuuuuu/yyvvyv:b00670067gggg006700670067	I
    //   236: irem
    //   237: getstatic 62	uuuuuu/yyvvyv:b0067ggggg006700670067	I
    //   240: if_icmpeq +13 -> 253
    //   243: bipush 84
    //   245: putstatic 56	uuuuuu/yyvvyv:bgggggg006700670067	I
    //   248: bipush 8
    //   250: putstatic 62	uuuuuu/yyvvyv:b0067ggggg006700670067	I
    //   253: return
    //   254: astore 4
    //   256: aload 4
    //   258: invokevirtual 103	java/lang/reflect/InvocationTargetException:getCause	()Ljava/lang/Throwable;
    //   261: athrow
    //   262: astore 4
    //   264: aload 4
    //   266: invokevirtual 103	java/lang/reflect/InvocationTargetException:getCause	()Ljava/lang/Throwable;
    //   269: athrow
    // Local variable table:
    //   start	length	slot	name	signature
    //   0	270	0	this	yyvvyv
    //   139	90	1	i	int
    //   143	86	2	j	int
    //   184	8	3	k	int
    //   4	173	4	localObject1	Object
    //   254	3	4	localInvocationTargetException1	java.lang.reflect.InvocationTargetException
    //   262	3	4	localInvocationTargetException2	java.lang.reflect.InvocationTargetException
    //   9	105	5	localYyyygy	gyyygy.yyyygy
    //   81	15	6	localObject2	Object
    // Exception table:
    //   from	to	target	type
    //   164	176	254	java/lang/reflect/InvocationTargetException
    //   83	95	262	java/lang/reflect/InvocationTargetException
  }
}
