package uuuuuu;

import android.content.Context;
import com.db.pwcc.dbmobile.multi_bank_aggregator.model.MbaSecurityPositions;
import java.lang.reflect.InvocationTargetException;
import java.lang.reflect.Method;
import javax.inject.Inject;
import rx.Observable;
import xxxxxx.uxxxxx;

public class yyyhhy
  extends hyyhhy<MbaSecurityPositions>
{
  public static int b00700070p00700070pp0070p = 0;
  public static int b0070p007000700070pp0070p = 2;
  public static int bp0070p00700070pp0070p = 73;
  public static int bpp007000700070pp0070p = 1;
  public aaalla b007000700070p0070pp0070p;
  public Observable<MbaSecurityPositions> b0070p0070p0070pp0070p;
  @Inject
  public pqqqqq b0070pp00700070pp0070p;
  public vxvxvv.xvvxvv bp00700070p0070pp0070p = new yyyhhy.1(this);
  public lallaa bppp00700070pp0070p;
  
  public yyyhhy(Context paramContext)
  {
    heehhe.b006F006F006Foo006F006F006F006Fo(paramContext).ba0061a00610061a0061006100610061(this);
    this.bppp00700070pp0070p = new lallaa();
    this.b007000700070p0070pp0070p = new aaalla();
  }
  
  public static int b006F006F006F006Foo006Fooo()
  {
    return 2;
  }
  
  public static int b006Fooo006Fo006Fooo()
  {
    return 1;
  }
  
  public static int bo006F006F006Foo006Fooo()
  {
    return 58;
  }
  
  public static int boooo006Fo006Fooo()
  {
    return 0;
  }
  
  public void b006F006Foo006Fo006Fooo(MbaSecurityPositions paramMbaSecurityPositions)
  {
    if ((!bkk006Bk006Bk006Bk006Bk()) || (((yhhhyy.yyhhyy)this.bnnnnn006E006E006En).isActivityFinishing())) {
      return;
    }
    for (;;)
    {
      int i = bp0070p00700070pp0070p;
      switch (i * (bpp007000700070pp0070p + i) % b0070p007000700070pp0070p)
      {
      default: 
        bp0070p00700070pp0070p = 39;
        paramMbaSecurityPositions = yyyhhy.class.getMethod(uxxxxx.bbbb0062b0062b0062b0062("6B\002\001\006\025}|\002\021yx}\r54srw\007/.-", 'Æ', 'ã', '\000'), new Class[0]);
      }
      try
      {
        paramMbaSecurityPositions = paramMbaSecurityPositions.invoke(null, new Object[0]);
        b00700070p00700070pp0070p = ((Integer)paramMbaSecurityPositions).intValue();
        ((yhhhyy.yyhhyy)this.bnnnnn006E006E006En).displayNoTransactionsLabel();
        return;
      }
      catch (InvocationTargetException paramMbaSecurityPositions)
      {
        Object localObject;
        throw paramMbaSecurityPositions.getCause();
      }
      if ((bp0070p00700070pp0070p + bpp007000700070pp0070p) * bp0070p00700070pp0070p % b0070p007000700070pp0070p != b00700070p00700070pp0070p)
      {
        i = bp0070p00700070pp0070p;
        switch (i * (bpp007000700070pp0070p + i) % b0070p007000700070pp0070p)
        {
        default: 
          bp0070p00700070pp0070p = 5;
          localObject = yyyhhy.class.getMethod(uxxxxx.bbbb0062b0062b0062b0062("\017\033ZY^mVUZiRQVe\016\rLKP_\b\007\006", '[', '\b', '\001'), new Class[0]);
        }
      }
      try
      {
        localObject = ((Method)localObject).invoke(null, new Object[0]);
        b00700070p00700070pp0070p = ((Integer)localObject).intValue();
        bp0070p00700070pp0070p = 45;
        localObject = yyyhhy.class.getMethod(uxxxxx.bb00620062bb0062b0062b0062("Vb\"!&5\036\035\"1\032\031\036-UT\024\023\030'ONM", '\006', '\004'), new Class[0]);
      }
      catch (InvocationTargetException paramMbaSecurityPositions)
      {
        try
        {
          localObject = ((Method)localObject).invoke(null, new Object[0]);
          b00700070p00700070pp0070p = ((Integer)localObject).intValue();
          localObject = yyyhhy.class.getMethod(uxxxxx.bb00620062bb0062b0062b0062("jx:;BS}~@AHY\004EFM^\t\n\013", '', '\002'), new Class[] { MbaSecurityPositions.class });
          try
          {
            localObject = ((Method)localObject).invoke(this, new Object[] { paramMbaSecurityPositions });
            if (!((Boolean)localObject).booleanValue()) {
              continue;
            }
            ((yhhhyy.yyhhyy)this.bnnnnn006E006E006En).displayTransactions(paramMbaSecurityPositions);
            i = bp0070p00700070pp0070p;
            switch (i * (bpp007000700070pp0070p + i) % b0070p007000700070pp0070p)
            {
            }
            paramMbaSecurityPositions = yyyhhy.class.getMethod(uxxxxx.bb00620062bb0062b0062b0062("\\h(',;$#(7 \037$3[Z\032\031\036-UTS", '', '\004'), new Class[0]);
          }
          catch (InvocationTargetException paramMbaSecurityPositions)
          {
            throw paramMbaSecurityPositions.getCause();
          }
        }
        catch (InvocationTargetException paramMbaSecurityPositions)
        {
          throw paramMbaSecurityPositions.getCause();
        }
        try
        {
          paramMbaSecurityPositions = paramMbaSecurityPositions.invoke(null, new Object[0]);
          bp0070p00700070pp0070p = ((Integer)paramMbaSecurityPositions).intValue();
          b00700070p00700070pp0070p = 61;
          return;
        }
        catch (InvocationTargetException paramMbaSecurityPositions)
        {
          throw paramMbaSecurityPositions.getCause();
        }
        paramMbaSecurityPositions = paramMbaSecurityPositions;
        throw paramMbaSecurityPositions.getCause();
      }
    }
  }
  
  /* Error */
  public void b006Fo006F006F006F006Foooo()
  {
    // Byte code:
    //   0: aload_0
    //   1: getfield 228	uuuuuu/yyyhhy:b0070p0070p0070pp0070p	Lrx/Observable;
    //   4: ifnonnull +4 -> 8
    //   7: return
    //   8: aload_0
    //   9: getfield 228	uuuuuu/yyyhhy:b0070p0070p0070pp0070p	Lrx/Observable;
    //   12: invokestatic 234	rx/schedulers/Schedulers:io	()Lrx/Scheduler;
    //   15: invokevirtual 240	rx/Observable:subscribeOn	(Lrx/Scheduler;)Lrx/Observable;
    //   18: invokestatic 245	rx/android/schedulers/AndroidSchedulers:mainThread	()Lrx/Scheduler;
    //   21: invokevirtual 248	rx/Observable:observeOn	(Lrx/Scheduler;)Lrx/Observable;
    //   24: astore_2
    //   25: getstatic 68	uuuuuu/yyyhhy:bp0070p00700070pp0070p	I
    //   28: istore_1
    //   29: iload_1
    //   30: getstatic 70	uuuuuu/yyyhhy:bpp007000700070pp0070p	I
    //   33: iload_1
    //   34: iadd
    //   35: imul
    //   36: getstatic 72	uuuuuu/yyyhhy:b0070p007000700070pp0070p	I
    //   39: irem
    //   40: tableswitch	default:+20->60, 0:+128->168
    //   60: bipush 70
    //   62: putstatic 68	uuuuuu/yyyhhy:bp0070p00700070pp0070p	I
    //   65: bipush 38
    //   67: putstatic 74	uuuuuu/yyyhhy:b00700070p00700070pp0070p	I
    //   70: getstatic 68	uuuuuu/yyyhhy:bp0070p00700070pp0070p	I
    //   73: getstatic 70	uuuuuu/yyyhhy:bpp007000700070pp0070p	I
    //   76: iadd
    //   77: getstatic 68	uuuuuu/yyyhhy:bp0070p00700070pp0070p	I
    //   80: imul
    //   81: getstatic 72	uuuuuu/yyyhhy:b0070p007000700070pp0070p	I
    //   84: irem
    //   85: getstatic 74	uuuuuu/yyyhhy:b00700070p00700070pp0070p	I
    //   88: if_icmpeq +80 -> 168
    //   91: ldc 2
    //   93: ldc -6
    //   95: sipush 171
    //   98: iconst_2
    //   99: invokestatic 107	xxxxxx/uxxxxx:bb00620062bb0062b0062b0062	(Ljava/lang/String;CC)Ljava/lang/String;
    //   102: iconst_0
    //   103: anewarray 84	java/lang/Class
    //   106: invokevirtual 88	java/lang/Class:getMethod	(Ljava/lang/String;[Ljava/lang/Class;)Ljava/lang/reflect/Method;
    //   109: astore_3
    //   110: aload_3
    //   111: aconst_null
    //   112: iconst_0
    //   113: anewarray 90	java/lang/Object
    //   116: invokevirtual 96	java/lang/reflect/Method:invoke	(Ljava/lang/Object;[Ljava/lang/Object;)Ljava/lang/Object;
    //   119: astore_3
    //   120: aload_3
    //   121: checkcast 98	java/lang/Integer
    //   124: invokevirtual 101	java/lang/Integer:intValue	()I
    //   127: putstatic 68	uuuuuu/yyyhhy:bp0070p00700070pp0070p	I
    //   130: ldc 2
    //   132: ldc -125
    //   134: bipush 49
    //   136: iconst_3
    //   137: invokestatic 107	xxxxxx/uxxxxx:bb00620062bb0062b0062b0062	(Ljava/lang/String;CC)Ljava/lang/String;
    //   140: iconst_0
    //   141: anewarray 84	java/lang/Class
    //   144: invokevirtual 88	java/lang/Class:getMethod	(Ljava/lang/String;[Ljava/lang/Class;)Ljava/lang/reflect/Method;
    //   147: astore_3
    //   148: aload_3
    //   149: aconst_null
    //   150: iconst_0
    //   151: anewarray 90	java/lang/Object
    //   154: invokevirtual 96	java/lang/reflect/Method:invoke	(Ljava/lang/Object;[Ljava/lang/Object;)Ljava/lang/Object;
    //   157: astore_3
    //   158: aload_3
    //   159: checkcast 98	java/lang/Integer
    //   162: invokevirtual 101	java/lang/Integer:intValue	()I
    //   165: putstatic 74	uuuuuu/yyyhhy:b00700070p00700070pp0070p	I
    //   168: new 252	uuuuuu/yyyhhy$2
    //   171: dup
    //   172: aload_0
    //   173: invokespecial 253	uuuuuu/yyyhhy$2:<init>	(Luuuuuu/yyyhhy;)V
    //   176: astore_3
    //   177: new 255	uuuuuu/yyyhhy$3
    //   180: dup
    //   181: aload_0
    //   182: invokespecial 256	uuuuuu/yyyhhy$3:<init>	(Luuuuuu/yyyhhy;)V
    //   185: astore 4
    //   187: getstatic 68	uuuuuu/yyyhhy:bp0070p00700070pp0070p	I
    //   190: istore_1
    //   191: iload_1
    //   192: getstatic 70	uuuuuu/yyyhhy:bpp007000700070pp0070p	I
    //   195: iload_1
    //   196: iadd
    //   197: imul
    //   198: getstatic 72	uuuuuu/yyyhhy:b0070p007000700070pp0070p	I
    //   201: irem
    //   202: tableswitch	default:+18->220, 0:+66->268
    //   220: ldc 2
    //   222: ldc -79
    //   224: sipush 138
    //   227: iconst_0
    //   228: invokestatic 107	xxxxxx/uxxxxx:bb00620062bb0062b0062b0062	(Ljava/lang/String;CC)Ljava/lang/String;
    //   231: iconst_0
    //   232: anewarray 84	java/lang/Class
    //   235: invokevirtual 88	java/lang/Class:getMethod	(Ljava/lang/String;[Ljava/lang/Class;)Ljava/lang/reflect/Method;
    //   238: astore 5
    //   240: aload 5
    //   242: aconst_null
    //   243: iconst_0
    //   244: anewarray 90	java/lang/Object
    //   247: invokevirtual 96	java/lang/reflect/Method:invoke	(Ljava/lang/Object;[Ljava/lang/Object;)Ljava/lang/Object;
    //   250: astore 5
    //   252: aload 5
    //   254: checkcast 98	java/lang/Integer
    //   257: invokevirtual 101	java/lang/Integer:intValue	()I
    //   260: putstatic 68	uuuuuu/yyyhhy:bp0070p00700070pp0070p	I
    //   263: bipush 74
    //   265: putstatic 74	uuuuuu/yyyhhy:b00700070p00700070pp0070p	I
    //   268: aload_2
    //   269: aload_3
    //   270: aload 4
    //   272: invokevirtual 260	rx/Observable:subscribe	(Lrx/functions/Action1;Lrx/functions/Action1;)Lrx/Subscription;
    //   275: pop
    //   276: getstatic 68	uuuuuu/yyyhhy:bp0070p00700070pp0070p	I
    //   279: getstatic 70	uuuuuu/yyyhhy:bpp007000700070pp0070p	I
    //   282: iadd
    //   283: getstatic 68	uuuuuu/yyyhhy:bp0070p00700070pp0070p	I
    //   286: imul
    //   287: getstatic 72	uuuuuu/yyyhhy:b0070p007000700070pp0070p	I
    //   290: irem
    //   291: getstatic 74	uuuuuu/yyyhhy:b00700070p00700070pp0070p	I
    //   294: if_icmpeq -287 -> 7
    //   297: ldc 2
    //   299: ldc_w 262
    //   302: sipush 136
    //   305: sipush 200
    //   308: iconst_1
    //   309: invokestatic 82	xxxxxx/uxxxxx:bbbb0062b0062b0062b0062	(Ljava/lang/String;CCC)Ljava/lang/String;
    //   312: iconst_0
    //   313: anewarray 84	java/lang/Class
    //   316: invokevirtual 88	java/lang/Class:getMethod	(Ljava/lang/String;[Ljava/lang/Class;)Ljava/lang/reflect/Method;
    //   319: astore_2
    //   320: aload_2
    //   321: aconst_null
    //   322: iconst_0
    //   323: anewarray 90	java/lang/Object
    //   326: invokevirtual 96	java/lang/reflect/Method:invoke	(Ljava/lang/Object;[Ljava/lang/Object;)Ljava/lang/Object;
    //   329: astore_2
    //   330: aload_2
    //   331: checkcast 98	java/lang/Integer
    //   334: invokevirtual 101	java/lang/Integer:intValue	()I
    //   337: putstatic 68	uuuuuu/yyyhhy:bp0070p00700070pp0070p	I
    //   340: iconst_3
    //   341: putstatic 74	uuuuuu/yyyhhy:b00700070p00700070pp0070p	I
    //   344: return
    //   345: astore_2
    //   346: aload_2
    //   347: invokevirtual 121	java/lang/reflect/InvocationTargetException:getCause	()Ljava/lang/Throwable;
    //   350: athrow
    //   351: astore_2
    //   352: aload_2
    //   353: invokevirtual 121	java/lang/reflect/InvocationTargetException:getCause	()Ljava/lang/Throwable;
    //   356: athrow
    //   357: astore_2
    //   358: aload_2
    //   359: invokevirtual 121	java/lang/reflect/InvocationTargetException:getCause	()Ljava/lang/Throwable;
    //   362: athrow
    //   363: astore_2
    //   364: aload_2
    //   365: invokevirtual 121	java/lang/reflect/InvocationTargetException:getCause	()Ljava/lang/Throwable;
    //   368: athrow
    // Local variable table:
    //   start	length	slot	name	signature
    //   0	369	0	this	yyyhhy
    //   28	170	1	i	int
    //   24	307	2	localObject1	Object
    //   345	2	2	localInvocationTargetException1	InvocationTargetException
    //   351	2	2	localInvocationTargetException2	InvocationTargetException
    //   357	2	2	localInvocationTargetException3	InvocationTargetException
    //   363	2	2	localInvocationTargetException4	InvocationTargetException
    //   109	161	3	localObject2	Object
    //   185	86	4	local3	yyyhhy.3
    //   238	15	5	localObject3	Object
    // Exception table:
    //   from	to	target	type
    //   320	330	345	java/lang/reflect/InvocationTargetException
    //   240	252	351	java/lang/reflect/InvocationTargetException
    //   110	120	357	java/lang/reflect/InvocationTargetException
    //   148	158	363	java/lang/reflect/InvocationTargetException
  }
  
  /* Error */
  public void b006Fo006Fo006F006Foooo()
  {
    // Byte code:
    //   0: aload_0
    //   1: getfield 127	uuuuuu/yyyhhy:bnnnnn006E006E006En	Luuuuuu/ttssst$tsssst;
    //   4: astore 6
    //   6: getstatic 68	uuuuuu/yyyhhy:bp0070p00700070pp0070p	I
    //   9: istore_1
    //   10: getstatic 70	uuuuuu/yyyhhy:bpp007000700070pp0070p	I
    //   13: istore_2
    //   14: getstatic 68	uuuuuu/yyyhhy:bp0070p00700070pp0070p	I
    //   17: istore_3
    //   18: getstatic 72	uuuuuu/yyyhhy:b0070p007000700070pp0070p	I
    //   21: istore 4
    //   23: getstatic 74	uuuuuu/yyyhhy:b00700070p00700070pp0070p	I
    //   26: istore 5
    //   28: getstatic 68	uuuuuu/yyyhhy:bp0070p00700070pp0070p	I
    //   31: getstatic 70	uuuuuu/yyyhhy:bpp007000700070pp0070p	I
    //   34: iadd
    //   35: getstatic 68	uuuuuu/yyyhhy:bp0070p00700070pp0070p	I
    //   38: imul
    //   39: getstatic 72	uuuuuu/yyyhhy:b0070p007000700070pp0070p	I
    //   42: irem
    //   43: getstatic 74	uuuuuu/yyyhhy:b00700070p00700070pp0070p	I
    //   46: if_icmpeq +52 -> 98
    //   49: bipush 81
    //   51: putstatic 68	uuuuuu/yyyhhy:bp0070p00700070pp0070p	I
    //   54: ldc 2
    //   56: ldc_w 265
    //   59: sipush 178
    //   62: iconst_5
    //   63: invokestatic 107	xxxxxx/uxxxxx:bb00620062bb0062b0062b0062	(Ljava/lang/String;CC)Ljava/lang/String;
    //   66: iconst_0
    //   67: anewarray 84	java/lang/Class
    //   70: invokevirtual 88	java/lang/Class:getMethod	(Ljava/lang/String;[Ljava/lang/Class;)Ljava/lang/reflect/Method;
    //   73: astore 7
    //   75: aload 7
    //   77: aconst_null
    //   78: iconst_0
    //   79: anewarray 90	java/lang/Object
    //   82: invokevirtual 96	java/lang/reflect/Method:invoke	(Ljava/lang/Object;[Ljava/lang/Object;)Ljava/lang/Object;
    //   85: astore 7
    //   87: aload 7
    //   89: checkcast 98	java/lang/Integer
    //   92: invokevirtual 101	java/lang/Integer:intValue	()I
    //   95: putstatic 74	uuuuuu/yyyhhy:b00700070p00700070pp0070p	I
    //   98: iload_1
    //   99: iload_2
    //   100: iadd
    //   101: iload_3
    //   102: imul
    //   103: iload 4
    //   105: irem
    //   106: iload 5
    //   108: if_icmpeq +50 -> 158
    //   111: bipush 62
    //   113: putstatic 68	uuuuuu/yyyhhy:bp0070p00700070pp0070p	I
    //   116: ldc 2
    //   118: ldc -102
    //   120: bipush 113
    //   122: iconst_5
    //   123: invokestatic 107	xxxxxx/uxxxxx:bb00620062bb0062b0062b0062	(Ljava/lang/String;CC)Ljava/lang/String;
    //   126: iconst_0
    //   127: anewarray 84	java/lang/Class
    //   130: invokevirtual 88	java/lang/Class:getMethod	(Ljava/lang/String;[Ljava/lang/Class;)Ljava/lang/reflect/Method;
    //   133: astore 7
    //   135: aload 7
    //   137: aconst_null
    //   138: iconst_0
    //   139: anewarray 90	java/lang/Object
    //   142: invokevirtual 96	java/lang/reflect/Method:invoke	(Ljava/lang/Object;[Ljava/lang/Object;)Ljava/lang/Object;
    //   145: astore 7
    //   147: aload 7
    //   149: checkcast 98	java/lang/Integer
    //   152: invokevirtual 101	java/lang/Integer:intValue	()I
    //   155: putstatic 74	uuuuuu/yyyhhy:b00700070p00700070pp0070p	I
    //   158: aload 6
    //   160: checkcast 201	uuuuuu/yhhhyy$yyhhyy
    //   163: astore 6
    //   165: getstatic 68	uuuuuu/yyyhhy:bp0070p00700070pp0070p	I
    //   168: istore_1
    //   169: getstatic 70	uuuuuu/yyyhhy:bpp007000700070pp0070p	I
    //   172: istore_2
    //   173: getstatic 68	uuuuuu/yyyhhy:bp0070p00700070pp0070p	I
    //   176: istore_3
    //   177: ldc 2
    //   179: ldc_w 267
    //   182: sipush 192
    //   185: iconst_4
    //   186: invokestatic 107	xxxxxx/uxxxxx:bb00620062bb0062b0062b0062	(Ljava/lang/String;CC)Ljava/lang/String;
    //   189: iconst_0
    //   190: anewarray 84	java/lang/Class
    //   193: invokevirtual 88	java/lang/Class:getMethod	(Ljava/lang/String;[Ljava/lang/Class;)Ljava/lang/reflect/Method;
    //   196: astore 7
    //   198: aload 7
    //   200: aconst_null
    //   201: iconst_0
    //   202: anewarray 90	java/lang/Object
    //   205: invokevirtual 96	java/lang/reflect/Method:invoke	(Ljava/lang/Object;[Ljava/lang/Object;)Ljava/lang/Object;
    //   208: astore 7
    //   210: aload 7
    //   212: checkcast 98	java/lang/Integer
    //   215: invokevirtual 101	java/lang/Integer:intValue	()I
    //   218: istore 4
    //   220: ldc 2
    //   222: ldc_w 269
    //   225: bipush 24
    //   227: sipush 129
    //   230: iconst_3
    //   231: invokestatic 82	xxxxxx/uxxxxx:bbbb0062b0062b0062b0062	(Ljava/lang/String;CCC)Ljava/lang/String;
    //   234: iconst_0
    //   235: anewarray 84	java/lang/Class
    //   238: invokevirtual 88	java/lang/Class:getMethod	(Ljava/lang/String;[Ljava/lang/Class;)Ljava/lang/reflect/Method;
    //   241: astore 7
    //   243: aload 7
    //   245: aconst_null
    //   246: iconst_0
    //   247: anewarray 90	java/lang/Object
    //   250: invokevirtual 96	java/lang/reflect/Method:invoke	(Ljava/lang/Object;[Ljava/lang/Object;)Ljava/lang/Object;
    //   253: astore 7
    //   255: iload_3
    //   256: iload_1
    //   257: iload_2
    //   258: iadd
    //   259: imul
    //   260: iload 4
    //   262: irem
    //   263: aload 7
    //   265: checkcast 98	java/lang/Integer
    //   268: invokevirtual 101	java/lang/Integer:intValue	()I
    //   271: if_icmpeq +96 -> 367
    //   274: getstatic 68	uuuuuu/yyyhhy:bp0070p00700070pp0070p	I
    //   277: istore_1
    //   278: iload_1
    //   279: getstatic 70	uuuuuu/yyyhhy:bpp007000700070pp0070p	I
    //   282: iload_1
    //   283: iadd
    //   284: imul
    //   285: getstatic 72	uuuuuu/yyyhhy:b0070p007000700070pp0070p	I
    //   288: irem
    //   289: tableswitch	default:+19->308, 0:+29->318
    //   308: bipush 58
    //   310: putstatic 68	uuuuuu/yyyhhy:bp0070p00700070pp0070p	I
    //   313: bipush 84
    //   315: putstatic 74	uuuuuu/yyyhhy:b00700070p00700070pp0070p	I
    //   318: bipush 20
    //   320: putstatic 68	uuuuuu/yyyhhy:bp0070p00700070pp0070p	I
    //   323: ldc 2
    //   325: ldc_w 271
    //   328: sipush 221
    //   331: iconst_4
    //   332: invokestatic 107	xxxxxx/uxxxxx:bb00620062bb0062b0062b0062	(Ljava/lang/String;CC)Ljava/lang/String;
    //   335: iconst_0
    //   336: anewarray 84	java/lang/Class
    //   339: invokevirtual 88	java/lang/Class:getMethod	(Ljava/lang/String;[Ljava/lang/Class;)Ljava/lang/reflect/Method;
    //   342: astore 7
    //   344: aload 7
    //   346: aconst_null
    //   347: iconst_0
    //   348: anewarray 90	java/lang/Object
    //   351: invokevirtual 96	java/lang/reflect/Method:invoke	(Ljava/lang/Object;[Ljava/lang/Object;)Ljava/lang/Object;
    //   354: astore 7
    //   356: aload 7
    //   358: checkcast 98	java/lang/Integer
    //   361: invokevirtual 101	java/lang/Integer:intValue	()I
    //   364: putstatic 74	uuuuuu/yyyhhy:b00700070p00700070pp0070p	I
    //   367: aload 6
    //   369: getstatic 276	com/db/pwcc/dbmobile/financial_overview/R$string:mba_loading_dialog	I
    //   372: invokeinterface 280 2 0
    //   377: aload_0
    //   378: getfield 59	uuuuuu/yyyhhy:b007000700070p0070pp0070p	Luuuuuu/aaalla;
    //   381: aload_0
    //   382: getfield 38	uuuuuu/yyyhhy:bp00700070p0070pp0070p	Luuuuuu/vxvxvv$xvvxvv;
    //   385: aload_0
    //   386: getfield 284	uuuuuu/yyyhhy:b006E006E006E006E006En006E006En	Luuuuuu/hyhyhh;
    //   389: invokevirtual 290	uuuuuu/hyhyhh:b0070pp007000700070p007000700070	()Ljava/lang/String;
    //   392: aload_0
    //   393: getfield 294	uuuuuu/yyyhhy:bpppp0070pp0070p	Ljava/lang/String;
    //   396: invokevirtual 298	uuuuuu/aaalla:bu0075007500750075u0075007500750075	(Luuuuuu/vxvxvv$xvvxvv;Ljava/lang/String;Ljava/lang/String;)V
    //   399: return
    //   400: astore 6
    //   402: aload 6
    //   404: invokevirtual 121	java/lang/reflect/InvocationTargetException:getCause	()Ljava/lang/Throwable;
    //   407: athrow
    //   408: astore 6
    //   410: aload 6
    //   412: invokevirtual 121	java/lang/reflect/InvocationTargetException:getCause	()Ljava/lang/Throwable;
    //   415: athrow
    //   416: astore 6
    //   418: aload 6
    //   420: invokevirtual 121	java/lang/reflect/InvocationTargetException:getCause	()Ljava/lang/Throwable;
    //   423: athrow
    //   424: astore 6
    //   426: aload 6
    //   428: invokevirtual 121	java/lang/reflect/InvocationTargetException:getCause	()Ljava/lang/Throwable;
    //   431: athrow
    //   432: astore 6
    //   434: aload 6
    //   436: invokevirtual 121	java/lang/reflect/InvocationTargetException:getCause	()Ljava/lang/Throwable;
    //   439: athrow
    // Local variable table:
    //   start	length	slot	name	signature
    //   0	440	0	this	yyyhhy
    //   9	276	1	i	int
    //   13	246	2	j	int
    //   17	243	3	k	int
    //   21	242	4	m	int
    //   26	83	5	n	int
    //   4	364	6	localObject1	Object
    //   400	3	6	localInvocationTargetException1	InvocationTargetException
    //   408	3	6	localInvocationTargetException2	InvocationTargetException
    //   416	3	6	localInvocationTargetException3	InvocationTargetException
    //   424	3	6	localInvocationTargetException4	InvocationTargetException
    //   432	3	6	localInvocationTargetException5	InvocationTargetException
    //   73	284	7	localObject2	Object
    // Exception table:
    //   from	to	target	type
    //   198	210	400	java/lang/reflect/InvocationTargetException
    //   243	255	408	java/lang/reflect/InvocationTargetException
    //   344	356	416	java/lang/reflect/InvocationTargetException
    //   135	147	424	java/lang/reflect/InvocationTargetException
    //   75	87	432	java/lang/reflect/InvocationTargetException
  }
  
  /* Error */
  public void bo006F006Fo006F006Foooo()
  {
    // Byte code:
    //   0: iconst_0
    //   1: istore_1
    //   2: iload_1
    //   3: iconst_0
    //   4: idiv
    //   5: istore_1
    //   6: goto -4 -> 2
    //   9: astore_3
    //   10: ldc 2
    //   12: ldc_w 335
    //   15: bipush 76
    //   17: iconst_0
    //   18: invokestatic 107	xxxxxx/uxxxxx:bb00620062bb0062b0062b0062	(Ljava/lang/String;CC)Ljava/lang/String;
    //   21: iconst_0
    //   22: anewarray 84	java/lang/Class
    //   25: invokevirtual 88	java/lang/Class:getMethod	(Ljava/lang/String;[Ljava/lang/Class;)Ljava/lang/reflect/Method;
    //   28: astore_3
    //   29: aload_3
    //   30: aconst_null
    //   31: iconst_0
    //   32: anewarray 90	java/lang/Object
    //   35: invokevirtual 96	java/lang/reflect/Method:invoke	(Ljava/lang/Object;[Ljava/lang/Object;)Ljava/lang/Object;
    //   38: astore_3
    //   39: aload_3
    //   40: checkcast 98	java/lang/Integer
    //   43: invokevirtual 101	java/lang/Integer:intValue	()I
    //   46: putstatic 68	uuuuuu/yyyhhy:bp0070p00700070pp0070p	I
    //   49: getstatic 68	uuuuuu/yyyhhy:bp0070p00700070pp0070p	I
    //   52: getstatic 70	uuuuuu/yyyhhy:bpp007000700070pp0070p	I
    //   55: iadd
    //   56: getstatic 68	uuuuuu/yyyhhy:bp0070p00700070pp0070p	I
    //   59: imul
    //   60: getstatic 72	uuuuuu/yyyhhy:b0070p007000700070pp0070p	I
    //   63: irem
    //   64: getstatic 74	uuuuuu/yyyhhy:b00700070p00700070pp0070p	I
    //   67: if_icmpeq +48 -> 115
    //   70: bipush 28
    //   72: putstatic 68	uuuuuu/yyyhhy:bp0070p00700070pp0070p	I
    //   75: ldc 2
    //   77: ldc_w 337
    //   80: sipush 252
    //   83: iconst_1
    //   84: invokestatic 107	xxxxxx/uxxxxx:bb00620062bb0062b0062b0062	(Ljava/lang/String;CC)Ljava/lang/String;
    //   87: iconst_0
    //   88: anewarray 84	java/lang/Class
    //   91: invokevirtual 88	java/lang/Class:getMethod	(Ljava/lang/String;[Ljava/lang/Class;)Ljava/lang/reflect/Method;
    //   94: astore_3
    //   95: aload_3
    //   96: aconst_null
    //   97: iconst_0
    //   98: anewarray 90	java/lang/Object
    //   101: invokevirtual 96	java/lang/reflect/Method:invoke	(Ljava/lang/Object;[Ljava/lang/Object;)Ljava/lang/Object;
    //   104: astore_3
    //   105: aload_3
    //   106: checkcast 98	java/lang/Integer
    //   109: invokevirtual 101	java/lang/Integer:intValue	()I
    //   112: putstatic 74	uuuuuu/yyyhhy:b00700070p00700070pp0070p	I
    //   115: aload_0
    //   116: getfield 54	uuuuuu/yyyhhy:bppp00700070pp0070p	Luuuuuu/lallaa;
    //   119: astore_3
    //   120: aload_0
    //   121: getfield 284	uuuuuu/yyyhhy:b006E006E006E006E006En006E006En	Luuuuuu/hyhyhh;
    //   124: invokevirtual 290	uuuuuu/hyhyhh:b0070pp007000700070p007000700070	()Ljava/lang/String;
    //   127: astore 4
    //   129: aload_0
    //   130: getfield 294	uuuuuu/yyyhhy:bpppp0070pp0070p	Ljava/lang/String;
    //   133: astore 5
    //   135: getstatic 68	uuuuuu/yyyhhy:bp0070p00700070pp0070p	I
    //   138: istore_1
    //   139: iload_1
    //   140: getstatic 70	uuuuuu/yyyhhy:bpp007000700070pp0070p	I
    //   143: iload_1
    //   144: iadd
    //   145: imul
    //   146: getstatic 72	uuuuuu/yyyhhy:b0070p007000700070pp0070p	I
    //   149: irem
    //   150: tableswitch	default:+18->168, 0:+70->220
    //   168: ldc 2
    //   170: ldc_w 339
    //   173: sipush 160
    //   176: sipush 153
    //   179: iconst_0
    //   180: invokestatic 82	xxxxxx/uxxxxx:bbbb0062b0062b0062b0062	(Ljava/lang/String;CCC)Ljava/lang/String;
    //   183: iconst_0
    //   184: anewarray 84	java/lang/Class
    //   187: invokevirtual 88	java/lang/Class:getMethod	(Ljava/lang/String;[Ljava/lang/Class;)Ljava/lang/reflect/Method;
    //   190: astore 6
    //   192: aload 6
    //   194: aconst_null
    //   195: iconst_0
    //   196: anewarray 90	java/lang/Object
    //   199: invokevirtual 96	java/lang/reflect/Method:invoke	(Ljava/lang/Object;[Ljava/lang/Object;)Ljava/lang/Object;
    //   202: astore 6
    //   204: aload 6
    //   206: checkcast 98	java/lang/Integer
    //   209: invokevirtual 101	java/lang/Integer:intValue	()I
    //   212: putstatic 68	uuuuuu/yyyhhy:bp0070p00700070pp0070p	I
    //   215: bipush 96
    //   217: putstatic 74	uuuuuu/yyyhhy:b00700070p00700070pp0070p	I
    //   220: aload_3
    //   221: aload 4
    //   223: aload 5
    //   225: invokevirtual 343	uuuuuu/lallaa:b0069iii00690069iiii	(Ljava/lang/String;Ljava/lang/String;)Lrx/Observable;
    //   228: astore_3
    //   229: ldc 2
    //   231: ldc_w 345
    //   234: bipush 127
    //   236: iconst_3
    //   237: invokestatic 107	xxxxxx/uxxxxx:bb00620062bb0062b0062b0062	(Ljava/lang/String;CC)Ljava/lang/String;
    //   240: iconst_0
    //   241: anewarray 84	java/lang/Class
    //   244: invokevirtual 88	java/lang/Class:getMethod	(Ljava/lang/String;[Ljava/lang/Class;)Ljava/lang/reflect/Method;
    //   247: astore 4
    //   249: aload 4
    //   251: aconst_null
    //   252: iconst_0
    //   253: anewarray 90	java/lang/Object
    //   256: invokevirtual 96	java/lang/reflect/Method:invoke	(Ljava/lang/Object;[Ljava/lang/Object;)Ljava/lang/Object;
    //   259: astore 4
    //   261: aload 4
    //   263: checkcast 98	java/lang/Integer
    //   266: invokevirtual 101	java/lang/Integer:intValue	()I
    //   269: istore_1
    //   270: getstatic 70	uuuuuu/yyyhhy:bpp007000700070pp0070p	I
    //   273: istore_2
    //   274: ldc 2
    //   276: ldc_w 347
    //   279: sipush 217
    //   282: iconst_2
    //   283: invokestatic 107	xxxxxx/uxxxxx:bb00620062bb0062b0062b0062	(Ljava/lang/String;CC)Ljava/lang/String;
    //   286: iconst_0
    //   287: anewarray 84	java/lang/Class
    //   290: invokevirtual 88	java/lang/Class:getMethod	(Ljava/lang/String;[Ljava/lang/Class;)Ljava/lang/reflect/Method;
    //   293: astore 4
    //   295: aload 4
    //   297: aconst_null
    //   298: iconst_0
    //   299: anewarray 90	java/lang/Object
    //   302: invokevirtual 96	java/lang/reflect/Method:invoke	(Ljava/lang/Object;[Ljava/lang/Object;)Ljava/lang/Object;
    //   305: astore 4
    //   307: aload 4
    //   309: checkcast 98	java/lang/Integer
    //   312: invokevirtual 101	java/lang/Integer:intValue	()I
    //   315: iload_2
    //   316: iload_1
    //   317: iadd
    //   318: imul
    //   319: getstatic 72	uuuuuu/yyyhhy:b0070p007000700070pp0070p	I
    //   322: irem
    //   323: getstatic 74	uuuuuu/yyyhhy:b00700070p00700070pp0070p	I
    //   326: if_icmpeq +51 -> 377
    //   329: ldc 2
    //   331: ldc -106
    //   333: sipush 130
    //   336: iconst_0
    //   337: invokestatic 107	xxxxxx/uxxxxx:bb00620062bb0062b0062b0062	(Ljava/lang/String;CC)Ljava/lang/String;
    //   340: iconst_0
    //   341: anewarray 84	java/lang/Class
    //   344: invokevirtual 88	java/lang/Class:getMethod	(Ljava/lang/String;[Ljava/lang/Class;)Ljava/lang/reflect/Method;
    //   347: astore 4
    //   349: aload 4
    //   351: aconst_null
    //   352: iconst_0
    //   353: anewarray 90	java/lang/Object
    //   356: invokevirtual 96	java/lang/reflect/Method:invoke	(Ljava/lang/Object;[Ljava/lang/Object;)Ljava/lang/Object;
    //   359: astore 4
    //   361: aload 4
    //   363: checkcast 98	java/lang/Integer
    //   366: invokevirtual 101	java/lang/Integer:intValue	()I
    //   369: putstatic 68	uuuuuu/yyyhhy:bp0070p00700070pp0070p	I
    //   372: bipush 6
    //   374: putstatic 74	uuuuuu/yyyhhy:b00700070p00700070pp0070p	I
    //   377: aload_0
    //   378: aload_3
    //   379: putfield 228	uuuuuu/yyyhhy:b0070p0070p0070pp0070p	Lrx/Observable;
    //   382: return
    //   383: astore_3
    //   384: aload_3
    //   385: invokevirtual 121	java/lang/reflect/InvocationTargetException:getCause	()Ljava/lang/Throwable;
    //   388: athrow
    //   389: astore_3
    //   390: aload_3
    //   391: invokevirtual 121	java/lang/reflect/InvocationTargetException:getCause	()Ljava/lang/Throwable;
    //   394: athrow
    //   395: astore_3
    //   396: aload_3
    //   397: invokevirtual 121	java/lang/reflect/InvocationTargetException:getCause	()Ljava/lang/Throwable;
    //   400: athrow
    //   401: astore_3
    //   402: aload_3
    //   403: invokevirtual 121	java/lang/reflect/InvocationTargetException:getCause	()Ljava/lang/Throwable;
    //   406: athrow
    //   407: astore_3
    //   408: aload_3
    //   409: invokevirtual 121	java/lang/reflect/InvocationTargetException:getCause	()Ljava/lang/Throwable;
    //   412: athrow
    //   413: astore_3
    //   414: aload_3
    //   415: invokevirtual 121	java/lang/reflect/InvocationTargetException:getCause	()Ljava/lang/Throwable;
    //   418: athrow
    // Local variable table:
    //   start	length	slot	name	signature
    //   0	419	0	this	yyyhhy
    //   1	317	1	i	int
    //   273	45	2	j	int
    //   9	1	3	localException	Exception
    //   28	351	3	localObject1	Object
    //   383	2	3	localInvocationTargetException1	InvocationTargetException
    //   389	2	3	localInvocationTargetException2	InvocationTargetException
    //   395	2	3	localInvocationTargetException3	InvocationTargetException
    //   401	2	3	localInvocationTargetException4	InvocationTargetException
    //   407	2	3	localInvocationTargetException5	InvocationTargetException
    //   413	2	3	localInvocationTargetException6	InvocationTargetException
    //   127	235	4	localObject2	Object
    //   133	91	5	str	String
    //   190	15	6	localObject3	Object
    // Exception table:
    //   from	to	target	type
    //   2	6	9	java/lang/Exception
    //   249	261	383	java/lang/reflect/InvocationTargetException
    //   295	307	389	java/lang/reflect/InvocationTargetException
    //   29	39	395	java/lang/reflect/InvocationTargetException
    //   349	361	401	java/lang/reflect/InvocationTargetException
    //   192	204	407	java/lang/reflect/InvocationTargetException
    //   95	105	413	java/lang/reflect/InvocationTargetException
  }
  
  /* Error */
  public boolean bo006Foo006Fo006Fooo(MbaSecurityPositions paramMbaSecurityPositions)
  {
    // Byte code:
    //   0: aload_1
    //   1: ifnonnull +5 -> 6
    //   4: iconst_0
    //   5: ireturn
    //   6: aload_1
    //   7: invokevirtual 353	com/db/pwcc/dbmobile/multi_bank_aggregator/model/MbaSecurityPositions:getSecurityPositions	()Ljava/util/List;
    //   10: ifnull +522 -> 532
    //   13: aload_1
    //   14: invokevirtual 353	com/db/pwcc/dbmobile/multi_bank_aggregator/model/MbaSecurityPositions:getSecurityPositions	()Ljava/util/List;
    //   17: invokeinterface 358 1 0
    //   22: istore 8
    //   24: ldc 2
    //   26: ldc_w 335
    //   29: sipush 239
    //   32: sipush 138
    //   35: iconst_2
    //   36: invokestatic 82	xxxxxx/uxxxxx:bbbb0062b0062b0062b0062	(Ljava/lang/String;CCC)Ljava/lang/String;
    //   39: iconst_0
    //   40: anewarray 84	java/lang/Class
    //   43: invokevirtual 88	java/lang/Class:getMethod	(Ljava/lang/String;[Ljava/lang/Class;)Ljava/lang/reflect/Method;
    //   46: astore 9
    //   48: aload 9
    //   50: aconst_null
    //   51: iconst_0
    //   52: anewarray 90	java/lang/Object
    //   55: invokevirtual 96	java/lang/reflect/Method:invoke	(Ljava/lang/Object;[Ljava/lang/Object;)Ljava/lang/Object;
    //   58: astore 9
    //   60: aload 9
    //   62: checkcast 98	java/lang/Integer
    //   65: invokevirtual 101	java/lang/Integer:intValue	()I
    //   68: istore_2
    //   69: getstatic 70	uuuuuu/yyyhhy:bpp007000700070pp0070p	I
    //   72: istore_3
    //   73: ldc 2
    //   75: ldc_w 360
    //   78: sipush 150
    //   81: iconst_2
    //   82: invokestatic 107	xxxxxx/uxxxxx:bb00620062bb0062b0062b0062	(Ljava/lang/String;CC)Ljava/lang/String;
    //   85: iconst_0
    //   86: anewarray 84	java/lang/Class
    //   89: invokevirtual 88	java/lang/Class:getMethod	(Ljava/lang/String;[Ljava/lang/Class;)Ljava/lang/reflect/Method;
    //   92: astore 9
    //   94: aload 9
    //   96: aconst_null
    //   97: iconst_0
    //   98: anewarray 90	java/lang/Object
    //   101: invokevirtual 96	java/lang/reflect/Method:invoke	(Ljava/lang/Object;[Ljava/lang/Object;)Ljava/lang/Object;
    //   104: astore 9
    //   106: aload 9
    //   108: checkcast 98	java/lang/Integer
    //   111: invokevirtual 101	java/lang/Integer:intValue	()I
    //   114: istore 4
    //   116: getstatic 72	uuuuuu/yyyhhy:b0070p007000700070pp0070p	I
    //   119: istore 5
    //   121: getstatic 74	uuuuuu/yyyhhy:b00700070p00700070pp0070p	I
    //   124: istore 6
    //   126: getstatic 68	uuuuuu/yyyhhy:bp0070p00700070pp0070p	I
    //   129: istore 7
    //   131: iload 7
    //   133: getstatic 70	uuuuuu/yyyhhy:bpp007000700070pp0070p	I
    //   136: iload 7
    //   138: iadd
    //   139: imul
    //   140: getstatic 72	uuuuuu/yyyhhy:b0070p007000700070pp0070p	I
    //   143: irem
    //   144: tableswitch	default:+20->164, 0:+68->212
    //   164: bipush 41
    //   166: putstatic 68	uuuuuu/yyyhhy:bp0070p00700070pp0070p	I
    //   169: ldc 2
    //   171: ldc -106
    //   173: sipush 195
    //   176: iconst_1
    //   177: invokestatic 107	xxxxxx/uxxxxx:bb00620062bb0062b0062b0062	(Ljava/lang/String;CC)Ljava/lang/String;
    //   180: iconst_0
    //   181: anewarray 84	java/lang/Class
    //   184: invokevirtual 88	java/lang/Class:getMethod	(Ljava/lang/String;[Ljava/lang/Class;)Ljava/lang/reflect/Method;
    //   187: astore 9
    //   189: aload 9
    //   191: aconst_null
    //   192: iconst_0
    //   193: anewarray 90	java/lang/Object
    //   196: invokevirtual 96	java/lang/reflect/Method:invoke	(Ljava/lang/Object;[Ljava/lang/Object;)Ljava/lang/Object;
    //   199: astore 9
    //   201: aload 9
    //   203: checkcast 98	java/lang/Integer
    //   206: invokevirtual 101	java/lang/Integer:intValue	()I
    //   209: putstatic 74	uuuuuu/yyyhhy:b00700070p00700070pp0070p	I
    //   212: iload 4
    //   214: iload_3
    //   215: iload_2
    //   216: iadd
    //   217: imul
    //   218: iload 5
    //   220: irem
    //   221: iload 6
    //   223: if_icmpeq +53 -> 276
    //   226: bipush 67
    //   228: putstatic 68	uuuuuu/yyyhhy:bp0070p00700070pp0070p	I
    //   231: ldc 2
    //   233: ldc_w 362
    //   236: sipush 179
    //   239: iconst_3
    //   240: iconst_3
    //   241: invokestatic 82	xxxxxx/uxxxxx:bbbb0062b0062b0062b0062	(Ljava/lang/String;CCC)Ljava/lang/String;
    //   244: iconst_0
    //   245: anewarray 84	java/lang/Class
    //   248: invokevirtual 88	java/lang/Class:getMethod	(Ljava/lang/String;[Ljava/lang/Class;)Ljava/lang/reflect/Method;
    //   251: astore 9
    //   253: aload 9
    //   255: aconst_null
    //   256: iconst_0
    //   257: anewarray 90	java/lang/Object
    //   260: invokevirtual 96	java/lang/reflect/Method:invoke	(Ljava/lang/Object;[Ljava/lang/Object;)Ljava/lang/Object;
    //   263: astore 9
    //   265: aload 9
    //   267: checkcast 98	java/lang/Integer
    //   270: invokevirtual 101	java/lang/Integer:intValue	()I
    //   273: putstatic 74	uuuuuu/yyyhhy:b00700070p00700070pp0070p	I
    //   276: iload 8
    //   278: ifne +254 -> 532
    //   281: getstatic 68	uuuuuu/yyyhhy:bp0070p00700070pp0070p	I
    //   284: istore_2
    //   285: getstatic 70	uuuuuu/yyyhhy:bpp007000700070pp0070p	I
    //   288: istore_3
    //   289: ldc 2
    //   291: ldc_w 364
    //   294: sipush 152
    //   297: bipush 71
    //   299: iconst_1
    //   300: invokestatic 82	xxxxxx/uxxxxx:bbbb0062b0062b0062b0062	(Ljava/lang/String;CCC)Ljava/lang/String;
    //   303: iconst_0
    //   304: anewarray 84	java/lang/Class
    //   307: invokevirtual 88	java/lang/Class:getMethod	(Ljava/lang/String;[Ljava/lang/Class;)Ljava/lang/reflect/Method;
    //   310: astore 9
    //   312: aload 9
    //   314: aconst_null
    //   315: iconst_0
    //   316: anewarray 90	java/lang/Object
    //   319: invokevirtual 96	java/lang/reflect/Method:invoke	(Ljava/lang/Object;[Ljava/lang/Object;)Ljava/lang/Object;
    //   322: astore 9
    //   324: iload_3
    //   325: iload_2
    //   326: iadd
    //   327: iload_2
    //   328: imul
    //   329: aload 9
    //   331: checkcast 98	java/lang/Integer
    //   334: invokevirtual 101	java/lang/Integer:intValue	()I
    //   337: irem
    //   338: tableswitch	default:+18->356, 0:+66->404
    //   356: ldc 2
    //   358: ldc_w 366
    //   361: bipush 70
    //   363: iconst_4
    //   364: invokestatic 107	xxxxxx/uxxxxx:bb00620062bb0062b0062b0062	(Ljava/lang/String;CC)Ljava/lang/String;
    //   367: iconst_0
    //   368: anewarray 84	java/lang/Class
    //   371: invokevirtual 88	java/lang/Class:getMethod	(Ljava/lang/String;[Ljava/lang/Class;)Ljava/lang/reflect/Method;
    //   374: astore 9
    //   376: aload 9
    //   378: aconst_null
    //   379: iconst_0
    //   380: anewarray 90	java/lang/Object
    //   383: invokevirtual 96	java/lang/reflect/Method:invoke	(Ljava/lang/Object;[Ljava/lang/Object;)Ljava/lang/Object;
    //   386: astore 9
    //   388: aload 9
    //   390: checkcast 98	java/lang/Integer
    //   393: invokevirtual 101	java/lang/Integer:intValue	()I
    //   396: putstatic 68	uuuuuu/yyyhhy:bp0070p00700070pp0070p	I
    //   399: bipush 14
    //   401: putstatic 74	uuuuuu/yyyhhy:b00700070p00700070pp0070p	I
    //   404: aload_1
    //   405: invokevirtual 353	com/db/pwcc/dbmobile/multi_bank_aggregator/model/MbaSecurityPositions:getSecurityPositions	()Ljava/util/List;
    //   408: iconst_0
    //   409: invokeinterface 370 2 0
    //   414: checkcast 372	com/db/pwcc/dbmobile/multi_bank_aggregator/model/MbaSecurity
    //   417: ifnull +115 -> 532
    //   420: getstatic 68	uuuuuu/yyyhhy:bp0070p00700070pp0070p	I
    //   423: istore_2
    //   424: ldc 2
    //   426: ldc_w 374
    //   429: bipush 36
    //   431: bipush 24
    //   433: iconst_1
    //   434: invokestatic 82	xxxxxx/uxxxxx:bbbb0062b0062b0062b0062	(Ljava/lang/String;CCC)Ljava/lang/String;
    //   437: iconst_0
    //   438: anewarray 84	java/lang/Class
    //   441: invokevirtual 88	java/lang/Class:getMethod	(Ljava/lang/String;[Ljava/lang/Class;)Ljava/lang/reflect/Method;
    //   444: astore_1
    //   445: aload_1
    //   446: aconst_null
    //   447: iconst_0
    //   448: anewarray 90	java/lang/Object
    //   451: invokevirtual 96	java/lang/reflect/Method:invoke	(Ljava/lang/Object;[Ljava/lang/Object;)Ljava/lang/Object;
    //   454: astore_1
    //   455: aload_1
    //   456: checkcast 98	java/lang/Integer
    //   459: invokevirtual 101	java/lang/Integer:intValue	()I
    //   462: iload_2
    //   463: iadd
    //   464: getstatic 68	uuuuuu/yyyhhy:bp0070p00700070pp0070p	I
    //   467: imul
    //   468: getstatic 72	uuuuuu/yyyhhy:b0070p007000700070pp0070p	I
    //   471: irem
    //   472: getstatic 74	uuuuuu/yyyhhy:b00700070p00700070pp0070p	I
    //   475: if_icmpeq +13 -> 488
    //   478: bipush 60
    //   480: putstatic 68	uuuuuu/yyyhhy:bp0070p00700070pp0070p	I
    //   483: bipush 24
    //   485: putstatic 74	uuuuuu/yyyhhy:b00700070p00700070pp0070p	I
    //   488: iconst_1
    //   489: ireturn
    //   490: astore_1
    //   491: aload_1
    //   492: invokevirtual 121	java/lang/reflect/InvocationTargetException:getCause	()Ljava/lang/Throwable;
    //   495: athrow
    //   496: astore_1
    //   497: aload_1
    //   498: invokevirtual 121	java/lang/reflect/InvocationTargetException:getCause	()Ljava/lang/Throwable;
    //   501: athrow
    //   502: astore_1
    //   503: aload_1
    //   504: invokevirtual 121	java/lang/reflect/InvocationTargetException:getCause	()Ljava/lang/Throwable;
    //   507: athrow
    //   508: astore_1
    //   509: aload_1
    //   510: invokevirtual 121	java/lang/reflect/InvocationTargetException:getCause	()Ljava/lang/Throwable;
    //   513: athrow
    //   514: astore_1
    //   515: aload_1
    //   516: invokevirtual 121	java/lang/reflect/InvocationTargetException:getCause	()Ljava/lang/Throwable;
    //   519: athrow
    //   520: astore_1
    //   521: aload_1
    //   522: invokevirtual 121	java/lang/reflect/InvocationTargetException:getCause	()Ljava/lang/Throwable;
    //   525: athrow
    //   526: astore_1
    //   527: aload_1
    //   528: invokevirtual 121	java/lang/reflect/InvocationTargetException:getCause	()Ljava/lang/Throwable;
    //   531: athrow
    //   532: iconst_0
    //   533: ireturn
    // Local variable table:
    //   start	length	slot	name	signature
    //   0	534	0	this	yyyhhy
    //   0	534	1	paramMbaSecurityPositions	MbaSecurityPositions
    //   68	396	2	i	int
    //   72	255	3	j	int
    //   114	104	4	k	int
    //   119	102	5	m	int
    //   124	100	6	n	int
    //   129	11	7	i1	int
    //   22	255	8	bool	boolean
    //   46	343	9	localObject	Object
    // Exception table:
    //   from	to	target	type
    //   445	455	490	java/lang/reflect/InvocationTargetException
    //   312	324	496	java/lang/reflect/InvocationTargetException
    //   376	388	502	java/lang/reflect/InvocationTargetException
    //   48	60	508	java/lang/reflect/InvocationTargetException
    //   94	106	514	java/lang/reflect/InvocationTargetException
    //   253	265	520	java/lang/reflect/InvocationTargetException
    //   189	201	526	java/lang/reflect/InvocationTargetException
  }
}
