package uuuuuu;

import com.db.pwcc.dbmobile.multi_bank_aggregator.model.MbaSecurity;

public class yyyhyy
  extends ssssst<yhhyyy.hyhyyy>
{
  public static int b007000700070pp007000700070p = 67;
  public static int b0070pp0070p007000700070p = 1;
  public static int bp0070p0070p007000700070p = 2;
  public static int bppp0070p007000700070p;
  private final MbaSecurity bp00700070pp007000700070p;
  
  public yyyhyy(MbaSecurity paramMbaSecurity)
  {
    this.bp00700070pp007000700070p = paramMbaSecurity;
  }
  
  public static int b006Fooo006F006F006Fooo()
  {
    return 2;
  }
  
  public static int bo006Foo006F006F006Fooo()
  {
    return 13;
  }
  
  /* Error */
  public void b006F006Foo006F006F006Fooo(yhhyyy.hyhyyy paramHyhyyy)
  {
    // Byte code:
    //   0: getstatic 32	uuuuuu/yyyhyy:b007000700070pp007000700070p	I
    //   3: getstatic 34	uuuuuu/yyyhyy:b0070pp0070p007000700070p	I
    //   6: iadd
    //   7: getstatic 32	uuuuuu/yyyhyy:b007000700070pp007000700070p	I
    //   10: imul
    //   11: getstatic 36	uuuuuu/yyyhyy:bp0070p0070p007000700070p	I
    //   14: irem
    //   15: getstatic 38	uuuuuu/yyyhyy:bppp0070p007000700070p	I
    //   18: if_icmpeq +419 -> 437
    //   21: getstatic 32	uuuuuu/yyyhyy:b007000700070pp007000700070p	I
    //   24: istore_2
    //   25: iload_2
    //   26: getstatic 34	uuuuuu/yyyhyy:b0070pp0070p007000700070p	I
    //   29: iload_2
    //   30: iadd
    //   31: imul
    //   32: getstatic 36	uuuuuu/yyyhyy:bp0070p0070p007000700070p	I
    //   35: irem
    //   36: tableswitch	default:+20->56, 0:+108->144
    //   56: ldc 2
    //   58: ldc 40
    //   60: sipush 186
    //   63: bipush 78
    //   65: iconst_3
    //   66: invokestatic 46	xxxxxx/uxxxxx:bbbb0062b0062b0062b0062	(Ljava/lang/String;CCC)Ljava/lang/String;
    //   69: iconst_0
    //   70: anewarray 48	java/lang/Class
    //   73: invokevirtual 52	java/lang/Class:getMethod	(Ljava/lang/String;[Ljava/lang/Class;)Ljava/lang/reflect/Method;
    //   76: astore 4
    //   78: aload 4
    //   80: aconst_null
    //   81: iconst_0
    //   82: anewarray 54	java/lang/Object
    //   85: invokevirtual 60	java/lang/reflect/Method:invoke	(Ljava/lang/Object;[Ljava/lang/Object;)Ljava/lang/Object;
    //   88: astore 4
    //   90: aload 4
    //   92: checkcast 62	java/lang/Integer
    //   95: invokevirtual 65	java/lang/Integer:intValue	()I
    //   98: putstatic 32	uuuuuu/yyyhyy:b007000700070pp007000700070p	I
    //   101: ldc 2
    //   103: ldc 67
    //   105: sipush 215
    //   108: iconst_5
    //   109: invokestatic 71	xxxxxx/uxxxxx:bb00620062bb0062b0062b0062	(Ljava/lang/String;CC)Ljava/lang/String;
    //   112: iconst_0
    //   113: anewarray 48	java/lang/Class
    //   116: invokevirtual 52	java/lang/Class:getMethod	(Ljava/lang/String;[Ljava/lang/Class;)Ljava/lang/reflect/Method;
    //   119: astore 4
    //   121: aload 4
    //   123: aconst_null
    //   124: iconst_0
    //   125: anewarray 54	java/lang/Object
    //   128: invokevirtual 60	java/lang/reflect/Method:invoke	(Ljava/lang/Object;[Ljava/lang/Object;)Ljava/lang/Object;
    //   131: astore 4
    //   133: aload 4
    //   135: checkcast 62	java/lang/Integer
    //   138: invokevirtual 65	java/lang/Integer:intValue	()I
    //   141: putstatic 38	uuuuuu/yyyhyy:bppp0070p007000700070p	I
    //   144: ldc 2
    //   146: ldc 73
    //   148: bipush 102
    //   150: sipush 131
    //   153: iconst_1
    //   154: invokestatic 46	xxxxxx/uxxxxx:bbbb0062b0062b0062b0062	(Ljava/lang/String;CCC)Ljava/lang/String;
    //   157: iconst_0
    //   158: anewarray 48	java/lang/Class
    //   161: invokevirtual 52	java/lang/Class:getMethod	(Ljava/lang/String;[Ljava/lang/Class;)Ljava/lang/reflect/Method;
    //   164: astore 4
    //   166: aload 4
    //   168: aconst_null
    //   169: iconst_0
    //   170: anewarray 54	java/lang/Object
    //   173: invokevirtual 60	java/lang/reflect/Method:invoke	(Ljava/lang/Object;[Ljava/lang/Object;)Ljava/lang/Object;
    //   176: astore 4
    //   178: aload 4
    //   180: checkcast 62	java/lang/Integer
    //   183: invokevirtual 65	java/lang/Integer:intValue	()I
    //   186: putstatic 32	uuuuuu/yyyhyy:b007000700070pp007000700070p	I
    //   189: ldc 2
    //   191: ldc 75
    //   193: bipush 55
    //   195: sipush 166
    //   198: iconst_3
    //   199: invokestatic 46	xxxxxx/uxxxxx:bbbb0062b0062b0062b0062	(Ljava/lang/String;CCC)Ljava/lang/String;
    //   202: iconst_0
    //   203: anewarray 48	java/lang/Class
    //   206: invokevirtual 52	java/lang/Class:getMethod	(Ljava/lang/String;[Ljava/lang/Class;)Ljava/lang/reflect/Method;
    //   209: astore 4
    //   211: aload 4
    //   213: aconst_null
    //   214: iconst_0
    //   215: anewarray 54	java/lang/Object
    //   218: invokevirtual 60	java/lang/reflect/Method:invoke	(Ljava/lang/Object;[Ljava/lang/Object;)Ljava/lang/Object;
    //   221: astore 4
    //   223: aload 4
    //   225: checkcast 62	java/lang/Integer
    //   228: invokevirtual 65	java/lang/Integer:intValue	()I
    //   231: putstatic 38	uuuuuu/yyyhyy:bppp0070p007000700070p	I
    //   234: getstatic 32	uuuuuu/yyyhyy:b007000700070pp007000700070p	I
    //   237: istore_2
    //   238: getstatic 34	uuuuuu/yyyhyy:b0070pp0070p007000700070p	I
    //   241: istore_3
    //   242: ldc 2
    //   244: ldc 77
    //   246: sipush 207
    //   249: iconst_2
    //   250: invokestatic 71	xxxxxx/uxxxxx:bb00620062bb0062b0062b0062	(Ljava/lang/String;CC)Ljava/lang/String;
    //   253: iconst_0
    //   254: anewarray 48	java/lang/Class
    //   257: invokevirtual 52	java/lang/Class:getMethod	(Ljava/lang/String;[Ljava/lang/Class;)Ljava/lang/reflect/Method;
    //   260: astore 4
    //   262: aload 4
    //   264: aconst_null
    //   265: iconst_0
    //   266: anewarray 54	java/lang/Object
    //   269: invokevirtual 60	java/lang/reflect/Method:invoke	(Ljava/lang/Object;[Ljava/lang/Object;)Ljava/lang/Object;
    //   272: astore 4
    //   274: iload_3
    //   275: iload_2
    //   276: iadd
    //   277: iload_2
    //   278: imul
    //   279: aload 4
    //   281: checkcast 62	java/lang/Integer
    //   284: invokevirtual 65	java/lang/Integer:intValue	()I
    //   287: irem
    //   288: tableswitch	default:+20->308, 0:+149->437
    //   308: ldc 2
    //   310: ldc 79
    //   312: bipush 106
    //   314: sipush 234
    //   317: iconst_3
    //   318: invokestatic 46	xxxxxx/uxxxxx:bbbb0062b0062b0062b0062	(Ljava/lang/String;CCC)Ljava/lang/String;
    //   321: iconst_0
    //   322: anewarray 48	java/lang/Class
    //   325: invokevirtual 52	java/lang/Class:getMethod	(Ljava/lang/String;[Ljava/lang/Class;)Ljava/lang/reflect/Method;
    //   328: astore 4
    //   330: aload 4
    //   332: aconst_null
    //   333: iconst_0
    //   334: anewarray 54	java/lang/Object
    //   337: invokevirtual 60	java/lang/reflect/Method:invoke	(Ljava/lang/Object;[Ljava/lang/Object;)Ljava/lang/Object;
    //   340: astore 4
    //   342: aload 4
    //   344: checkcast 62	java/lang/Integer
    //   347: invokevirtual 65	java/lang/Integer:intValue	()I
    //   350: putstatic 32	uuuuuu/yyyhyy:b007000700070pp007000700070p	I
    //   353: bipush 57
    //   355: putstatic 38	uuuuuu/yyyhyy:bppp0070p007000700070p	I
    //   358: ldc 2
    //   360: ldc 81
    //   362: sipush 215
    //   365: iconst_4
    //   366: invokestatic 71	xxxxxx/uxxxxx:bb00620062bb0062b0062b0062	(Ljava/lang/String;CC)Ljava/lang/String;
    //   369: iconst_0
    //   370: anewarray 48	java/lang/Class
    //   373: invokevirtual 52	java/lang/Class:getMethod	(Ljava/lang/String;[Ljava/lang/Class;)Ljava/lang/reflect/Method;
    //   376: astore 4
    //   378: aload 4
    //   380: aconst_null
    //   381: iconst_0
    //   382: anewarray 54	java/lang/Object
    //   385: invokevirtual 60	java/lang/reflect/Method:invoke	(Ljava/lang/Object;[Ljava/lang/Object;)Ljava/lang/Object;
    //   388: astore 4
    //   390: aload 4
    //   392: checkcast 62	java/lang/Integer
    //   395: invokevirtual 65	java/lang/Integer:intValue	()I
    //   398: istore_2
    //   399: iload_2
    //   400: getstatic 34	uuuuuu/yyyhyy:b0070pp0070p007000700070p	I
    //   403: iload_2
    //   404: iadd
    //   405: imul
    //   406: getstatic 36	uuuuuu/yyyhyy:bp0070p0070p007000700070p	I
    //   409: irem
    //   410: tableswitch	default:+18->428, 0:+27->437
    //   428: bipush 22
    //   430: putstatic 32	uuuuuu/yyyhyy:b007000700070pp007000700070p	I
    //   433: iconst_4
    //   434: putstatic 38	uuuuuu/yyyhyy:bppp0070p007000700070p	I
    //   437: aload_0
    //   438: aload_1
    //   439: invokespecial 85	uuuuuu/ssssst:ba0061a0061a0061a0061aa	(Luuuuuu/ttssst$tsssst;)V
    //   442: aload_1
    //   443: aload_0
    //   444: getfield 22	uuuuuu/yyyhyy:bp00700070pp007000700070p	Lcom/db/pwcc/dbmobile/multi_bank_aggregator/model/MbaSecurity;
    //   447: invokeinterface 90 2 0
    //   452: return
    //   453: astore_1
    //   454: aload_1
    //   455: invokevirtual 94	java/lang/reflect/InvocationTargetException:getCause	()Ljava/lang/Throwable;
    //   458: athrow
    //   459: astore_1
    //   460: aload_1
    //   461: invokevirtual 94	java/lang/reflect/InvocationTargetException:getCause	()Ljava/lang/Throwable;
    //   464: athrow
    //   465: astore_1
    //   466: aload_1
    //   467: invokevirtual 94	java/lang/reflect/InvocationTargetException:getCause	()Ljava/lang/Throwable;
    //   470: athrow
    //   471: astore_1
    //   472: aload_1
    //   473: invokevirtual 94	java/lang/reflect/InvocationTargetException:getCause	()Ljava/lang/Throwable;
    //   476: athrow
    //   477: astore_1
    //   478: aload_1
    //   479: invokevirtual 94	java/lang/reflect/InvocationTargetException:getCause	()Ljava/lang/Throwable;
    //   482: athrow
    //   483: astore_1
    //   484: aload_1
    //   485: invokevirtual 94	java/lang/reflect/InvocationTargetException:getCause	()Ljava/lang/Throwable;
    //   488: athrow
    //   489: astore_1
    //   490: aload_1
    //   491: invokevirtual 94	java/lang/reflect/InvocationTargetException:getCause	()Ljava/lang/Throwable;
    //   494: athrow
    // Local variable table:
    //   start	length	slot	name	signature
    //   0	495	0	this	yyyhyy
    //   0	495	1	paramHyhyyy	yhhyyy.hyhyyy
    //   24	382	2	i	int
    //   241	36	3	j	int
    //   76	315	4	localObject	Object
    // Exception table:
    //   from	to	target	type
    //   166	178	453	java/lang/reflect/InvocationTargetException
    //   262	274	459	java/lang/reflect/InvocationTargetException
    //   330	342	465	java/lang/reflect/InvocationTargetException
    //   378	390	471	java/lang/reflect/InvocationTargetException
    //   211	223	477	java/lang/reflect/InvocationTargetException
    //   78	90	483	java/lang/reflect/InvocationTargetException
    //   121	133	489	java/lang/reflect/InvocationTargetException
  }
}
