package com.google.android.gms.internal;

import com.google.android.gms.common.internal.zzbq;
import java.net.URL;
import java.util.Map;

final class zzcjs
  implements Runnable
{
  private final URL zza;
  private final byte[] zzb;
  private final zzcjq zzc;
  private final String zzd;
  private final Map<String, String> zze;
  
  public zzcjs(String paramString, URL paramURL, byte[] paramArrayOfByte, Map<String, String> paramMap, zzcjq paramZzcjq)
  {
    zzbq.zza(paramURL);
    zzbq.zza(paramArrayOfByte);
    Object localObject;
    zzbq.zza(localObject);
    this.zza = paramArrayOfByte;
    this.zzb = paramMap;
    this.zzc = localObject;
    this.zzd = paramURL;
    this.zze = paramZzcjq;
  }
  
  /* Error */
  public final void run()
  {
    // Byte code:
    //   0: aload_0
    //   1: getfield 23	com/google/android/gms/internal/zzcjs:zzf	Lcom/google/android/gms/internal/zzcjo;
    //   4: invokevirtual 54	com/google/android/gms/internal/zzcli:zzb	()V
    //   7: aconst_null
    //   8: astore 6
    //   10: aconst_null
    //   11: astore 5
    //   13: aload_0
    //   14: getfield 23	com/google/android/gms/internal/zzcjs:zzf	Lcom/google/android/gms/internal/zzcjo;
    //   17: aload_0
    //   18: getfield 36	com/google/android/gms/internal/zzcjs:zza	Ljava/net/URL;
    //   21: invokevirtual 59	com/google/android/gms/internal/zzcjo:zza	(Ljava/net/URL;)Ljava/net/HttpURLConnection;
    //   24: astore_2
    //   25: aload_0
    //   26: getfield 44	com/google/android/gms/internal/zzcjs:zze	Ljava/util/Map;
    //   29: ifnull +65 -> 94
    //   32: aload_0
    //   33: getfield 44	com/google/android/gms/internal/zzcjs:zze	Ljava/util/Map;
    //   36: invokeinterface 65 1 0
    //   41: invokeinterface 71 1 0
    //   46: astore_3
    //   47: aload_3
    //   48: invokeinterface 77 1 0
    //   53: ifeq +41 -> 94
    //   56: aload_3
    //   57: invokeinterface 81 1 0
    //   62: checkcast 83	java/util/Map$Entry
    //   65: astore 4
    //   67: aload_2
    //   68: aload 4
    //   70: invokeinterface 86 1 0
    //   75: checkcast 88	java/lang/String
    //   78: aload 4
    //   80: invokeinterface 91 1 0
    //   85: checkcast 88	java/lang/String
    //   88: invokevirtual 97	java/net/HttpURLConnection:addRequestProperty	(Ljava/lang/String;Ljava/lang/String;)V
    //   91: goto -44 -> 47
    //   94: aload_0
    //   95: getfield 38	com/google/android/gms/internal/zzcjs:zzb	[B
    //   98: ifnull +126 -> 224
    //   101: aload_0
    //   102: getfield 23	com/google/android/gms/internal/zzcjs:zzf	Lcom/google/android/gms/internal/zzcjo;
    //   105: invokevirtual 101	com/google/android/gms/internal/zzcli:zzp	()Lcom/google/android/gms/internal/zzcnp;
    //   108: aload_0
    //   109: getfield 38	com/google/android/gms/internal/zzcjs:zzb	[B
    //   112: invokevirtual 106	com/google/android/gms/internal/zzcnp:zza	([B)[B
    //   115: astore 4
    //   117: aload_0
    //   118: getfield 23	com/google/android/gms/internal/zzcjs:zzf	Lcom/google/android/gms/internal/zzcjo;
    //   121: invokevirtual 110	com/google/android/gms/internal/zzcli:zzt	()Lcom/google/android/gms/internal/zzcjk;
    //   124: invokevirtual 116	com/google/android/gms/internal/zzcjk:zzae	()Lcom/google/android/gms/internal/zzcjm;
    //   127: ldc 118
    //   129: aload 4
    //   131: arraylength
    //   132: invokestatic 124	java/lang/Integer:valueOf	(I)Ljava/lang/Integer;
    //   135: invokevirtual 129	com/google/android/gms/internal/zzcjm:zza	(Ljava/lang/String;Ljava/lang/Object;)V
    //   138: aload_2
    //   139: iconst_1
    //   140: invokevirtual 133	java/net/HttpURLConnection:setDoOutput	(Z)V
    //   143: aload_2
    //   144: ldc -121
    //   146: ldc -119
    //   148: invokevirtual 97	java/net/HttpURLConnection:addRequestProperty	(Ljava/lang/String;Ljava/lang/String;)V
    //   151: aload_2
    //   152: aload 4
    //   154: arraylength
    //   155: invokevirtual 141	java/net/HttpURLConnection:setFixedLengthStreamingMode	(I)V
    //   158: aload_2
    //   159: invokevirtual 144	java/net/HttpURLConnection:connect	()V
    //   162: aload_2
    //   163: invokevirtual 148	java/net/HttpURLConnection:getOutputStream	()Ljava/io/OutputStream;
    //   166: astore_3
    //   167: aload_3
    //   168: aload 4
    //   170: invokevirtual 154	java/io/OutputStream:write	([B)V
    //   173: aload_3
    //   174: invokevirtual 157	java/io/OutputStream:close	()V
    //   177: goto +47 -> 224
    //   180: astore 7
    //   182: aconst_null
    //   183: astore 6
    //   185: iconst_0
    //   186: istore_1
    //   187: aload_3
    //   188: astore 5
    //   190: aload_2
    //   191: astore 4
    //   193: aload 7
    //   195: astore_2
    //   196: aload 6
    //   198: astore_3
    //   199: goto +163 -> 362
    //   202: astore 5
    //   204: aconst_null
    //   205: astore 7
    //   207: iconst_0
    //   208: istore_1
    //   209: aload_3
    //   210: astore 6
    //   212: aload_2
    //   213: astore 4
    //   215: aload 5
    //   217: astore_2
    //   218: aload 7
    //   220: astore_3
    //   221: goto +230 -> 451
    //   224: aload_2
    //   225: invokevirtual 161	java/net/HttpURLConnection:getResponseCode	()I
    //   228: istore_1
    //   229: aload_2
    //   230: invokevirtual 165	java/net/HttpURLConnection:getHeaderFields	()Ljava/util/Map;
    //   233: astore_3
    //   234: aload_0
    //   235: getfield 23	com/google/android/gms/internal/zzcjs:zzf	Lcom/google/android/gms/internal/zzcjo;
    //   238: aload_2
    //   239: invokestatic 168	com/google/android/gms/internal/zzcjo:zza	(Lcom/google/android/gms/internal/zzcjo;Ljava/net/HttpURLConnection;)[B
    //   242: astore 4
    //   244: aload_2
    //   245: ifnull +7 -> 252
    //   248: aload_2
    //   249: invokevirtual 171	java/net/HttpURLConnection:disconnect	()V
    //   252: aload_0
    //   253: getfield 23	com/google/android/gms/internal/zzcjs:zzf	Lcom/google/android/gms/internal/zzcjo;
    //   256: invokevirtual 175	com/google/android/gms/internal/zzcli:zzs	()Lcom/google/android/gms/internal/zzckf;
    //   259: astore_2
    //   260: new 177	com/google/android/gms/internal/zzcjr
    //   263: dup
    //   264: aload_0
    //   265: getfield 42	com/google/android/gms/internal/zzcjs:zzd	Ljava/lang/String;
    //   268: aload_0
    //   269: getfield 40	com/google/android/gms/internal/zzcjs:zzc	Lcom/google/android/gms/internal/zzcjq;
    //   272: iload_1
    //   273: aconst_null
    //   274: aload 4
    //   276: aload_3
    //   277: aconst_null
    //   278: invokespecial 180	com/google/android/gms/internal/zzcjr:<init>	(Ljava/lang/String;Lcom/google/android/gms/internal/zzcjq;ILjava/lang/Throwable;[BLjava/util/Map;Lcom/google/android/gms/internal/zzcjp;)V
    //   281: astore_3
    //   282: aload_2
    //   283: aload_3
    //   284: invokevirtual 185	com/google/android/gms/internal/zzckf:zza	(Ljava/lang/Runnable;)V
    //   287: return
    //   288: astore 6
    //   290: aload_2
    //   291: astore 4
    //   293: aload 6
    //   295: astore_2
    //   296: goto +66 -> 362
    //   299: astore 5
    //   301: aload_2
    //   302: astore 4
    //   304: aload 5
    //   306: astore_2
    //   307: goto +144 -> 451
    //   310: astore 6
    //   312: aconst_null
    //   313: astore_3
    //   314: aload_2
    //   315: astore 4
    //   317: aload 6
    //   319: astore_2
    //   320: goto +42 -> 362
    //   323: astore 5
    //   325: aconst_null
    //   326: astore_3
    //   327: aload_2
    //   328: astore 4
    //   330: aload 5
    //   332: astore_2
    //   333: goto +118 -> 451
    //   336: astore_3
    //   337: aload_2
    //   338: astore 4
    //   340: aload_3
    //   341: astore_2
    //   342: goto +16 -> 358
    //   345: astore_3
    //   346: aload_2
    //   347: astore 4
    //   349: aload_3
    //   350: astore_2
    //   351: goto +96 -> 447
    //   354: astore_2
    //   355: aconst_null
    //   356: astore 4
    //   358: aconst_null
    //   359: astore_3
    //   360: iconst_0
    //   361: istore_1
    //   362: aload 5
    //   364: ifnull +37 -> 401
    //   367: aload 5
    //   369: invokevirtual 157	java/io/OutputStream:close	()V
    //   372: goto +29 -> 401
    //   375: astore 5
    //   377: aload_0
    //   378: getfield 23	com/google/android/gms/internal/zzcjs:zzf	Lcom/google/android/gms/internal/zzcjo;
    //   381: invokevirtual 110	com/google/android/gms/internal/zzcli:zzt	()Lcom/google/android/gms/internal/zzcjk;
    //   384: invokevirtual 188	com/google/android/gms/internal/zzcjk:zzy	()Lcom/google/android/gms/internal/zzcjm;
    //   387: ldc -66
    //   389: aload_0
    //   390: getfield 42	com/google/android/gms/internal/zzcjs:zzd	Ljava/lang/String;
    //   393: invokestatic 193	com/google/android/gms/internal/zzcjk:zza	(Ljava/lang/String;)Ljava/lang/Object;
    //   396: aload 5
    //   398: invokevirtual 196	com/google/android/gms/internal/zzcjm:zza	(Ljava/lang/String;Ljava/lang/Object;Ljava/lang/Object;)V
    //   401: aload 4
    //   403: ifnull +8 -> 411
    //   406: aload 4
    //   408: invokevirtual 171	java/net/HttpURLConnection:disconnect	()V
    //   411: aload_0
    //   412: getfield 23	com/google/android/gms/internal/zzcjs:zzf	Lcom/google/android/gms/internal/zzcjo;
    //   415: invokevirtual 175	com/google/android/gms/internal/zzcli:zzs	()Lcom/google/android/gms/internal/zzckf;
    //   418: new 177	com/google/android/gms/internal/zzcjr
    //   421: dup
    //   422: aload_0
    //   423: getfield 42	com/google/android/gms/internal/zzcjs:zzd	Ljava/lang/String;
    //   426: aload_0
    //   427: getfield 40	com/google/android/gms/internal/zzcjs:zzc	Lcom/google/android/gms/internal/zzcjq;
    //   430: iload_1
    //   431: aconst_null
    //   432: aconst_null
    //   433: aload_3
    //   434: aconst_null
    //   435: invokespecial 180	com/google/android/gms/internal/zzcjr:<init>	(Ljava/lang/String;Lcom/google/android/gms/internal/zzcjq;ILjava/lang/Throwable;[BLjava/util/Map;Lcom/google/android/gms/internal/zzcjp;)V
    //   438: invokevirtual 185	com/google/android/gms/internal/zzckf:zza	(Ljava/lang/Runnable;)V
    //   441: aload_2
    //   442: athrow
    //   443: astore_2
    //   444: aconst_null
    //   445: astore 4
    //   447: aconst_null
    //   448: astore_3
    //   449: iconst_0
    //   450: istore_1
    //   451: aload 6
    //   453: ifnull +37 -> 490
    //   456: aload 6
    //   458: invokevirtual 157	java/io/OutputStream:close	()V
    //   461: goto +29 -> 490
    //   464: astore 5
    //   466: aload_0
    //   467: getfield 23	com/google/android/gms/internal/zzcjs:zzf	Lcom/google/android/gms/internal/zzcjo;
    //   470: invokevirtual 110	com/google/android/gms/internal/zzcli:zzt	()Lcom/google/android/gms/internal/zzcjk;
    //   473: invokevirtual 188	com/google/android/gms/internal/zzcjk:zzy	()Lcom/google/android/gms/internal/zzcjm;
    //   476: ldc -66
    //   478: aload_0
    //   479: getfield 42	com/google/android/gms/internal/zzcjs:zzd	Ljava/lang/String;
    //   482: invokestatic 193	com/google/android/gms/internal/zzcjk:zza	(Ljava/lang/String;)Ljava/lang/Object;
    //   485: aload 5
    //   487: invokevirtual 196	com/google/android/gms/internal/zzcjm:zza	(Ljava/lang/String;Ljava/lang/Object;Ljava/lang/Object;)V
    //   490: aload 4
    //   492: ifnull +8 -> 500
    //   495: aload 4
    //   497: invokevirtual 171	java/net/HttpURLConnection:disconnect	()V
    //   500: aload_0
    //   501: getfield 23	com/google/android/gms/internal/zzcjs:zzf	Lcom/google/android/gms/internal/zzcjo;
    //   504: invokevirtual 175	com/google/android/gms/internal/zzcli:zzs	()Lcom/google/android/gms/internal/zzckf;
    //   507: astore 4
    //   509: new 177	com/google/android/gms/internal/zzcjr
    //   512: dup
    //   513: aload_0
    //   514: getfield 42	com/google/android/gms/internal/zzcjs:zzd	Ljava/lang/String;
    //   517: aload_0
    //   518: getfield 40	com/google/android/gms/internal/zzcjs:zzc	Lcom/google/android/gms/internal/zzcjq;
    //   521: iload_1
    //   522: aload_2
    //   523: aconst_null
    //   524: aload_3
    //   525: aconst_null
    //   526: invokespecial 180	com/google/android/gms/internal/zzcjr:<init>	(Ljava/lang/String;Lcom/google/android/gms/internal/zzcjq;ILjava/lang/Throwable;[BLjava/util/Map;Lcom/google/android/gms/internal/zzcjp;)V
    //   529: astore_3
    //   530: aload 4
    //   532: astore_2
    //   533: goto -251 -> 282
    // Local variable table:
    //   start	length	slot	name	signature
    //   0	536	0	this	zzcjs
    //   186	336	1	i	int
    //   24	327	2	localObject1	Object
    //   354	88	2	localObject2	Object
    //   443	80	2	localIOException1	java.io.IOException
    //   532	1	2	localObject3	Object
    //   46	281	3	localObject4	Object
    //   336	5	3	localObject5	Object
    //   345	5	3	localIOException2	java.io.IOException
    //   359	171	3	localObject6	Object
    //   65	466	4	localObject7	Object
    //   11	178	5	localObject8	Object
    //   202	14	5	localIOException3	java.io.IOException
    //   299	6	5	localIOException4	java.io.IOException
    //   323	45	5	localIOException5	java.io.IOException
    //   375	22	5	localIOException6	java.io.IOException
    //   464	22	5	localIOException7	java.io.IOException
    //   8	203	6	localObject9	Object
    //   288	6	6	localObject10	Object
    //   310	147	6	localObject11	Object
    //   180	14	7	localObject12	Object
    //   205	14	7	localObject13	Object
    // Exception table:
    //   from	to	target	type
    //   167	177	180	finally
    //   167	177	202	java/io/IOException
    //   234	244	288	finally
    //   234	244	299	java/io/IOException
    //   229	234	310	finally
    //   229	234	323	java/io/IOException
    //   25	47	336	finally
    //   47	91	336	finally
    //   94	167	336	finally
    //   224	229	336	finally
    //   25	47	345	java/io/IOException
    //   47	91	345	java/io/IOException
    //   94	167	345	java/io/IOException
    //   224	229	345	java/io/IOException
    //   13	25	354	finally
    //   367	372	375	java/io/IOException
    //   13	25	443	java/io/IOException
    //   456	461	464	java/io/IOException
  }
}
