package com.google.android.gms.internal;

import java.util.concurrent.atomic.AtomicReference;

final class zzcmq
  implements Runnable
{
  zzcmq(zzcmf paramZzcmf, AtomicReference paramAtomicReference, String paramString1, String paramString2, String paramString3, boolean paramBoolean, zzcig paramZzcig) {}
  
  /* Error */
  public final void run()
  {
    // Byte code:
    //   0: aload_0
    //   1: getfield 24	com/google/android/gms/internal/zzcmq:zza	Ljava/util/concurrent/atomic/AtomicReference;
    //   4: astore_3
    //   5: aload_3
    //   6: monitorenter
    //   7: aload_0
    //   8: getfield 22	com/google/android/gms/internal/zzcmq:zzg	Lcom/google/android/gms/internal/zzcmf;
    //   11: invokestatic 46	com/google/android/gms/internal/zzcmf:zzd	(Lcom/google/android/gms/internal/zzcmf;)Lcom/google/android/gms/internal/zzcjc;
    //   14: astore_1
    //   15: aload_1
    //   16: ifnonnull +53 -> 69
    //   19: aload_0
    //   20: getfield 22	com/google/android/gms/internal/zzcmq:zzg	Lcom/google/android/gms/internal/zzcmf;
    //   23: invokevirtual 52	com/google/android/gms/internal/zzcli:zzt	()Lcom/google/android/gms/internal/zzcjk;
    //   26: invokevirtual 58	com/google/android/gms/internal/zzcjk:zzy	()Lcom/google/android/gms/internal/zzcjm;
    //   29: ldc 60
    //   31: aload_0
    //   32: getfield 26	com/google/android/gms/internal/zzcmq:zzb	Ljava/lang/String;
    //   35: invokestatic 63	com/google/android/gms/internal/zzcjk:zza	(Ljava/lang/String;)Ljava/lang/Object;
    //   38: aload_0
    //   39: getfield 28	com/google/android/gms/internal/zzcmq:zzc	Ljava/lang/String;
    //   42: aload_0
    //   43: getfield 30	com/google/android/gms/internal/zzcmq:zzd	Ljava/lang/String;
    //   46: invokevirtual 68	com/google/android/gms/internal/zzcjm:zza	(Ljava/lang/String;Ljava/lang/Object;Ljava/lang/Object;Ljava/lang/Object;)V
    //   49: aload_0
    //   50: getfield 24	com/google/android/gms/internal/zzcmq:zza	Ljava/util/concurrent/atomic/AtomicReference;
    //   53: invokestatic 74	java/util/Collections:emptyList	()Ljava/util/List;
    //   56: invokevirtual 80	java/util/concurrent/atomic/AtomicReference:set	(Ljava/lang/Object;)V
    //   59: aload_0
    //   60: getfield 24	com/google/android/gms/internal/zzcmq:zza	Ljava/util/concurrent/atomic/AtomicReference;
    //   63: invokevirtual 83	java/lang/Object:notify	()V
    //   66: aload_3
    //   67: monitorexit
    //   68: return
    //   69: aload_0
    //   70: getfield 26	com/google/android/gms/internal/zzcmq:zzb	Ljava/lang/String;
    //   73: invokestatic 89	android/text/TextUtils:isEmpty	(Ljava/lang/CharSequence;)Z
    //   76: ifeq +39 -> 115
    //   79: aload_0
    //   80: getfield 24	com/google/android/gms/internal/zzcmq:zza	Ljava/util/concurrent/atomic/AtomicReference;
    //   83: astore_2
    //   84: aload_1
    //   85: aload_0
    //   86: getfield 28	com/google/android/gms/internal/zzcmq:zzc	Ljava/lang/String;
    //   89: aload_0
    //   90: getfield 30	com/google/android/gms/internal/zzcmq:zzd	Ljava/lang/String;
    //   93: aload_0
    //   94: getfield 32	com/google/android/gms/internal/zzcmq:zze	Z
    //   97: aload_0
    //   98: getfield 34	com/google/android/gms/internal/zzcmq:zzf	Lcom/google/android/gms/internal/zzcig;
    //   101: invokeinterface 94 5 0
    //   106: astore_1
    //   107: aload_2
    //   108: aload_1
    //   109: invokevirtual 80	java/util/concurrent/atomic/AtomicReference:set	(Ljava/lang/Object;)V
    //   112: goto +34 -> 146
    //   115: aload_0
    //   116: getfield 24	com/google/android/gms/internal/zzcmq:zza	Ljava/util/concurrent/atomic/AtomicReference;
    //   119: astore_2
    //   120: aload_1
    //   121: aload_0
    //   122: getfield 26	com/google/android/gms/internal/zzcmq:zzb	Ljava/lang/String;
    //   125: aload_0
    //   126: getfield 28	com/google/android/gms/internal/zzcmq:zzc	Ljava/lang/String;
    //   129: aload_0
    //   130: getfield 30	com/google/android/gms/internal/zzcmq:zzd	Ljava/lang/String;
    //   133: aload_0
    //   134: getfield 32	com/google/android/gms/internal/zzcmq:zze	Z
    //   137: invokeinterface 97 5 0
    //   142: astore_1
    //   143: goto -36 -> 107
    //   146: aload_0
    //   147: getfield 22	com/google/android/gms/internal/zzcmq:zzg	Lcom/google/android/gms/internal/zzcmf;
    //   150: invokestatic 100	com/google/android/gms/internal/zzcmf:zze	(Lcom/google/android/gms/internal/zzcmf;)V
    //   153: aload_0
    //   154: getfield 24	com/google/android/gms/internal/zzcmq:zza	Ljava/util/concurrent/atomic/AtomicReference;
    //   157: astore_1
    //   158: aload_1
    //   159: invokevirtual 83	java/lang/Object:notify	()V
    //   162: goto +53 -> 215
    //   165: astore_1
    //   166: goto +52 -> 218
    //   169: astore_1
    //   170: aload_0
    //   171: getfield 22	com/google/android/gms/internal/zzcmq:zzg	Lcom/google/android/gms/internal/zzcmf;
    //   174: invokevirtual 52	com/google/android/gms/internal/zzcli:zzt	()Lcom/google/android/gms/internal/zzcjk;
    //   177: invokevirtual 58	com/google/android/gms/internal/zzcjk:zzy	()Lcom/google/android/gms/internal/zzcjm;
    //   180: ldc 60
    //   182: aload_0
    //   183: getfield 26	com/google/android/gms/internal/zzcmq:zzb	Ljava/lang/String;
    //   186: invokestatic 63	com/google/android/gms/internal/zzcjk:zza	(Ljava/lang/String;)Ljava/lang/Object;
    //   189: aload_0
    //   190: getfield 28	com/google/android/gms/internal/zzcmq:zzc	Ljava/lang/String;
    //   193: aload_1
    //   194: invokevirtual 68	com/google/android/gms/internal/zzcjm:zza	(Ljava/lang/String;Ljava/lang/Object;Ljava/lang/Object;Ljava/lang/Object;)V
    //   197: aload_0
    //   198: getfield 24	com/google/android/gms/internal/zzcmq:zza	Ljava/util/concurrent/atomic/AtomicReference;
    //   201: invokestatic 74	java/util/Collections:emptyList	()Ljava/util/List;
    //   204: invokevirtual 80	java/util/concurrent/atomic/AtomicReference:set	(Ljava/lang/Object;)V
    //   207: aload_0
    //   208: getfield 24	com/google/android/gms/internal/zzcmq:zza	Ljava/util/concurrent/atomic/AtomicReference;
    //   211: astore_1
    //   212: goto -54 -> 158
    //   215: aload_3
    //   216: monitorexit
    //   217: return
    //   218: aload_0
    //   219: getfield 24	com/google/android/gms/internal/zzcmq:zza	Ljava/util/concurrent/atomic/AtomicReference;
    //   222: invokevirtual 83	java/lang/Object:notify	()V
    //   225: aload_1
    //   226: athrow
    //   227: astore_1
    //   228: aload_3
    //   229: monitorexit
    //   230: aload_1
    //   231: athrow
    // Local variable table:
    //   start	length	slot	name	signature
    //   0	232	0	this	zzcmq
    //   14	145	1	localObject1	Object
    //   165	1	1	localObject2	Object
    //   169	25	1	localRemoteException	android.os.RemoteException
    //   211	15	1	localAtomicReference1	AtomicReference
    //   227	4	1	localObject3	Object
    //   83	37	2	localAtomicReference2	AtomicReference
    // Exception table:
    //   from	to	target	type
    //   7	15	165	finally
    //   19	59	165	finally
    //   69	107	165	finally
    //   107	112	165	finally
    //   115	143	165	finally
    //   146	153	165	finally
    //   170	207	165	finally
    //   7	15	169	android/os/RemoteException
    //   19	59	169	android/os/RemoteException
    //   69	107	169	android/os/RemoteException
    //   107	112	169	android/os/RemoteException
    //   115	143	169	android/os/RemoteException
    //   146	153	169	android/os/RemoteException
    //   59	68	227	finally
    //   153	158	227	finally
    //   158	162	227	finally
    //   207	212	227	finally
    //   215	217	227	finally
    //   218	227	227	finally
    //   228	230	227	finally
  }
}
