package com.google.android.gms.internal;

import android.os.Binder;
import android.os.Bundle;
import android.os.IBinder;
import android.os.IInterface;
import android.os.Parcel;
import com.google.android.gms.dynamic.zzd;
import com.google.android.gms.dynamic.zzd.zza;
import java.util.ArrayList;
import java.util.List;

public abstract interface zzct
  extends IInterface
{
  public abstract String a();
  
  public abstract List b();
  
  public abstract String c();
  
  public abstract zzcn d();
  
  public abstract String e();
  
  public abstract String f();
  
  public abstract zzd g();
  
  public abstract Bundle h();
  
  public abstract void i();
  
  public static abstract class zza
    extends Binder
    implements zzct
  {
    public zza()
    {
      attachInterface(this, "com.google.android.gms.ads.internal.formats.client.INativeContentAd");
    }
    
    public static zzct a(IBinder paramIBinder)
    {
      if (paramIBinder == null) {
        return null;
      }
      IInterface localIInterface = paramIBinder.queryLocalInterface("com.google.android.gms.ads.internal.formats.client.INativeContentAd");
      if ((localIInterface != null) && ((localIInterface instanceof zzct))) {
        return (zzct)localIInterface;
      }
      return new zza(paramIBinder);
    }
    
    public IBinder asBinder()
    {
      return this;
    }
    
    public boolean onTransact(int paramInt1, Parcel paramParcel1, Parcel paramParcel2, int paramInt2)
    {
      zzd localZzd = null;
      zzcn localZzcn = null;
      switch (paramInt1)
      {
      default: 
        return super.onTransact(paramInt1, paramParcel1, paramParcel2, paramInt2);
      case 1598968902: 
        paramParcel2.writeString("com.google.android.gms.ads.internal.formats.client.INativeContentAd");
        return true;
      case 2: 
        paramParcel1.enforceInterface("com.google.android.gms.ads.internal.formats.client.INativeContentAd");
        localZzd = g();
        paramParcel2.writeNoException();
        paramParcel1 = localZzcn;
        if (localZzd != null) {
          paramParcel1 = localZzd.asBinder();
        }
        paramParcel2.writeStrongBinder(paramParcel1);
        return true;
      case 3: 
        paramParcel1.enforceInterface("com.google.android.gms.ads.internal.formats.client.INativeContentAd");
        paramParcel1 = a();
        paramParcel2.writeNoException();
        paramParcel2.writeString(paramParcel1);
        return true;
      case 4: 
        paramParcel1.enforceInterface("com.google.android.gms.ads.internal.formats.client.INativeContentAd");
        paramParcel1 = b();
        paramParcel2.writeNoException();
        paramParcel2.writeList(paramParcel1);
        return true;
      case 5: 
        paramParcel1.enforceInterface("com.google.android.gms.ads.internal.formats.client.INativeContentAd");
        paramParcel1 = c();
        paramParcel2.writeNoException();
        paramParcel2.writeString(paramParcel1);
        return true;
      case 6: 
        paramParcel1.enforceInterface("com.google.android.gms.ads.internal.formats.client.INativeContentAd");
        localZzcn = d();
        paramParcel2.writeNoException();
        paramParcel1 = localZzd;
        if (localZzcn != null) {
          paramParcel1 = localZzcn.asBinder();
        }
        paramParcel2.writeStrongBinder(paramParcel1);
        return true;
      case 7: 
        paramParcel1.enforceInterface("com.google.android.gms.ads.internal.formats.client.INativeContentAd");
        paramParcel1 = e();
        paramParcel2.writeNoException();
        paramParcel2.writeString(paramParcel1);
        return true;
      case 8: 
        paramParcel1.enforceInterface("com.google.android.gms.ads.internal.formats.client.INativeContentAd");
        paramParcel1 = f();
        paramParcel2.writeNoException();
        paramParcel2.writeString(paramParcel1);
        return true;
      case 9: 
        paramParcel1.enforceInterface("com.google.android.gms.ads.internal.formats.client.INativeContentAd");
        paramParcel1 = h();
        paramParcel2.writeNoException();
        if (paramParcel1 != null)
        {
          paramParcel2.writeInt(1);
          paramParcel1.writeToParcel(paramParcel2, 1);
        }
        for (;;)
        {
          return true;
          paramParcel2.writeInt(0);
        }
      }
      paramParcel1.enforceInterface("com.google.android.gms.ads.internal.formats.client.INativeContentAd");
      i();
      paramParcel2.writeNoException();
      return true;
    }
    
    private static class zza
      implements zzct
    {
      private IBinder a;
      
      zza(IBinder paramIBinder)
      {
        this.a = paramIBinder;
      }
      
      public String a()
      {
        Parcel localParcel1 = Parcel.obtain();
        Parcel localParcel2 = Parcel.obtain();
        try
        {
          localParcel1.writeInterfaceToken("com.google.android.gms.ads.internal.formats.client.INativeContentAd");
          this.a.transact(3, localParcel1, localParcel2, 0);
          localParcel2.readException();
          String str = localParcel2.readString();
          return str;
        }
        finally
        {
          localParcel2.recycle();
          localParcel1.recycle();
        }
      }
      
      public IBinder asBinder()
      {
        return this.a;
      }
      
      public List b()
      {
        Parcel localParcel1 = Parcel.obtain();
        Parcel localParcel2 = Parcel.obtain();
        try
        {
          localParcel1.writeInterfaceToken("com.google.android.gms.ads.internal.formats.client.INativeContentAd");
          this.a.transact(4, localParcel1, localParcel2, 0);
          localParcel2.readException();
          ArrayList localArrayList = localParcel2.readArrayList(getClass().getClassLoader());
          return localArrayList;
        }
        finally
        {
          localParcel2.recycle();
          localParcel1.recycle();
        }
      }
      
      public String c()
      {
        Parcel localParcel1 = Parcel.obtain();
        Parcel localParcel2 = Parcel.obtain();
        try
        {
          localParcel1.writeInterfaceToken("com.google.android.gms.ads.internal.formats.client.INativeContentAd");
          this.a.transact(5, localParcel1, localParcel2, 0);
          localParcel2.readException();
          String str = localParcel2.readString();
          return str;
        }
        finally
        {
          localParcel2.recycle();
          localParcel1.recycle();
        }
      }
      
      public zzcn d()
      {
        Parcel localParcel1 = Parcel.obtain();
        Parcel localParcel2 = Parcel.obtain();
        try
        {
          localParcel1.writeInterfaceToken("com.google.android.gms.ads.internal.formats.client.INativeContentAd");
          this.a.transact(6, localParcel1, localParcel2, 0);
          localParcel2.readException();
          zzcn localZzcn = zzcn.zza.a(localParcel2.readStrongBinder());
          return localZzcn;
        }
        finally
        {
          localParcel2.recycle();
          localParcel1.recycle();
        }
      }
      
      public String e()
      {
        Parcel localParcel1 = Parcel.obtain();
        Parcel localParcel2 = Parcel.obtain();
        try
        {
          localParcel1.writeInterfaceToken("com.google.android.gms.ads.internal.formats.client.INativeContentAd");
          this.a.transact(7, localParcel1, localParcel2, 0);
          localParcel2.readException();
          String str = localParcel2.readString();
          return str;
        }
        finally
        {
          localParcel2.recycle();
          localParcel1.recycle();
        }
      }
      
      public String f()
      {
        Parcel localParcel1 = Parcel.obtain();
        Parcel localParcel2 = Parcel.obtain();
        try
        {
          localParcel1.writeInterfaceToken("com.google.android.gms.ads.internal.formats.client.INativeContentAd");
          this.a.transact(8, localParcel1, localParcel2, 0);
          localParcel2.readException();
          String str = localParcel2.readString();
          return str;
        }
        finally
        {
          localParcel2.recycle();
          localParcel1.recycle();
        }
      }
      
      public zzd g()
      {
        Parcel localParcel1 = Parcel.obtain();
        Parcel localParcel2 = Parcel.obtain();
        try
        {
          localParcel1.writeInterfaceToken("com.google.android.gms.ads.internal.formats.client.INativeContentAd");
          this.a.transact(2, localParcel1, localParcel2, 0);
          localParcel2.readException();
          zzd localZzd = zzd.zza.a(localParcel2.readStrongBinder());
          return localZzd;
        }
        finally
        {
          localParcel2.recycle();
          localParcel1.recycle();
        }
      }
      
      /* Error */
      public Bundle h()
      {
        // Byte code:
        //   0: invokestatic 26	android/os/Parcel:obtain	()Landroid/os/Parcel;
        //   3: astore_2
        //   4: invokestatic 26	android/os/Parcel:obtain	()Landroid/os/Parcel;
        //   7: astore_3
        //   8: aload_2
        //   9: ldc 28
        //   11: invokevirtual 32	android/os/Parcel:writeInterfaceToken	(Ljava/lang/String;)V
        //   14: aload_0
        //   15: getfield 18	com/google/android/gms/internal/zzct$zza$zza:a	Landroid/os/IBinder;
        //   18: bipush 9
        //   20: aload_2
        //   21: aload_3
        //   22: iconst_0
        //   23: invokeinterface 38 5 0
        //   28: pop
        //   29: aload_3
        //   30: invokevirtual 41	android/os/Parcel:readException	()V
        //   33: aload_3
        //   34: invokevirtual 91	android/os/Parcel:readInt	()I
        //   37: ifeq +26 -> 63
        //   40: getstatic 97	android/os/Bundle:CREATOR	Landroid/os/Parcelable$Creator;
        //   43: aload_3
        //   44: invokeinterface 103 2 0
        //   49: checkcast 93	android/os/Bundle
        //   52: astore_1
        //   53: aload_3
        //   54: invokevirtual 47	android/os/Parcel:recycle	()V
        //   57: aload_2
        //   58: invokevirtual 47	android/os/Parcel:recycle	()V
        //   61: aload_1
        //   62: areturn
        //   63: aconst_null
        //   64: astore_1
        //   65: goto -12 -> 53
        //   68: astore_1
        //   69: aload_3
        //   70: invokevirtual 47	android/os/Parcel:recycle	()V
        //   73: aload_2
        //   74: invokevirtual 47	android/os/Parcel:recycle	()V
        //   77: aload_1
        //   78: athrow
        // Local variable table:
        //   start	length	slot	name	signature
        //   0	79	0	this	zza
        //   52	13	1	localBundle	Bundle
        //   68	10	1	localObject	Object
        //   3	71	2	localParcel1	Parcel
        //   7	63	3	localParcel2	Parcel
        // Exception table:
        //   from	to	target	type
        //   8	53	68	finally
      }
      
      public void i()
      {
        Parcel localParcel1 = Parcel.obtain();
        Parcel localParcel2 = Parcel.obtain();
        try
        {
          localParcel1.writeInterfaceToken("com.google.android.gms.ads.internal.formats.client.INativeContentAd");
          this.a.transact(10, localParcel1, localParcel2, 0);
          localParcel2.readException();
          return;
        }
        finally
        {
          localParcel2.recycle();
          localParcel1.recycle();
        }
      }
    }
  }
}
