package com.mobile.ui.ics.activity;

import com.mobile.ui.common.activity.AppTimeoutActivity;

public class IcsChequeImageReviewActivity
  extends AppTimeoutActivity
{
  private static final String EXTRA_ACCOUNT_TYPE = "/C@?/N145BICJVLRJ@";
  private static final String EXTRA_DEPOSIT_AMOUNT = "#50-\0338\034\034&$'\034&0\021\034\035\"\032\037";
  private static final String EXTRA_FROM_HISTORY = "w\f\t\bw\027~\f\n\t\034\006\b\023\025\021\025\035";
  private static final String EXTRA_ICS_DEPOSIT_CHEQUE_HISTORY_IMAGE_VIEW_MODEL = "\017!\034\031\007$\r\006\025 \004\004\016\f\017\004\016\030z~z\006\tw\021xx\002\002{}\004\tqtgli\003xjev}jk__e";
  private static final String EXTRA_SIDE_OF_IMAGE = "ASNK9VI>88Q@6N7:-2/";
  public static int b043Bлл043B043Bлл043B = 1;
  public static int bл043B043B043B043Bлл043B = 0;
  public static int bл043Bл043B043Bлл043B = 2;
  public static int bллл043B043Bлл043B = 48;
  
  /* Error */
  static
  {
    // Byte code:
    //   0: getstatic 35	com/mobile/ui/ics/activity/IcsChequeImageReviewActivity:EXTRA_ACCOUNT_TYPE	Ljava/lang/String;
    //   3: sipush 162
    //   6: iconst_1
    //   7: invokestatic 41	kkkkkk/gguuuu:bккккк043Aкк043A043A	(Ljava/lang/String;CC)Ljava/lang/String;
    //   10: astore_1
    //   11: invokestatic 45	com/mobile/ui/ics/activity/IcsChequeImageReviewActivity:b043B043Bл043B043Bлл043B	()I
    //   14: getstatic 47	com/mobile/ui/ics/activity/IcsChequeImageReviewActivity:b043Bлл043B043Bлл043B	I
    //   17: iadd
    //   18: invokestatic 45	com/mobile/ui/ics/activity/IcsChequeImageReviewActivity:b043B043Bл043B043Bлл043B	()I
    //   21: imul
    //   22: getstatic 49	com/mobile/ui/ics/activity/IcsChequeImageReviewActivity:bл043Bл043B043Bлл043B	I
    //   25: irem
    //   26: getstatic 51	com/mobile/ui/ics/activity/IcsChequeImageReviewActivity:bл043B043B043B043Bлл043B	I
    //   29: if_icmpeq +58 -> 87
    //   32: invokestatic 45	com/mobile/ui/ics/activity/IcsChequeImageReviewActivity:b043B043Bл043B043Bлл043B	()I
    //   35: putstatic 53	com/mobile/ui/ics/activity/IcsChequeImageReviewActivity:bллл043B043Bлл043B	I
    //   38: getstatic 53	com/mobile/ui/ics/activity/IcsChequeImageReviewActivity:bллл043B043Bлл043B	I
    //   41: istore_0
    //   42: iload_0
    //   43: getstatic 47	com/mobile/ui/ics/activity/IcsChequeImageReviewActivity:b043Bлл043B043Bлл043B	I
    //   46: iload_0
    //   47: iadd
    //   48: imul
    //   49: getstatic 49	com/mobile/ui/ics/activity/IcsChequeImageReviewActivity:bл043Bл043B043Bлл043B	I
    //   52: irem
    //   53: tableswitch	default:+19->72, 0:+29->82
    //   72: bipush 99
    //   74: putstatic 53	com/mobile/ui/ics/activity/IcsChequeImageReviewActivity:bллл043B043Bлл043B	I
    //   77: bipush 50
    //   79: putstatic 51	com/mobile/ui/ics/activity/IcsChequeImageReviewActivity:bл043B043B043B043Bлл043B	I
    //   82: bipush 65
    //   84: putstatic 51	com/mobile/ui/ics/activity/IcsChequeImageReviewActivity:bл043B043B043B043Bлл043B	I
    //   87: iconst_0
    //   88: tableswitch	default:+24->112, 0:+51->139, 1:+-1->87
    //   112: iconst_0
    //   113: tableswitch	default:+23->136, 0:+26->139, 1:+-26->87
    //   136: goto -24 -> 112
    //   139: aload_1
    //   140: putstatic 35	com/mobile/ui/ics/activity/IcsChequeImageReviewActivity:EXTRA_ACCOUNT_TYPE	Ljava/lang/String;
    //   143: getstatic 55	com/mobile/ui/ics/activity/IcsChequeImageReviewActivity:EXTRA_DEPOSIT_AMOUNT	Ljava/lang/String;
    //   146: sipush 144
    //   149: iconst_3
    //   150: invokestatic 41	kkkkkk/gguuuu:bккккк043Aкк043A043A	(Ljava/lang/String;CC)Ljava/lang/String;
    //   153: putstatic 55	com/mobile/ui/ics/activity/IcsChequeImageReviewActivity:EXTRA_DEPOSIT_AMOUNT	Ljava/lang/String;
    //   156: getstatic 57	com/mobile/ui/ics/activity/IcsChequeImageReviewActivity:EXTRA_FROM_HISTORY	Ljava/lang/String;
    //   159: sipush 152
    //   162: iconst_4
    //   163: invokestatic 41	kkkkkk/gguuuu:bккккк043Aкк043A043A	(Ljava/lang/String;CC)Ljava/lang/String;
    //   166: putstatic 57	com/mobile/ui/ics/activity/IcsChequeImageReviewActivity:EXTRA_FROM_HISTORY	Ljava/lang/String;
    //   169: getstatic 59	com/mobile/ui/ics/activity/IcsChequeImageReviewActivity:EXTRA_ICS_DEPOSIT_CHEQUE_HISTORY_IMAGE_VIEW_MODEL	Ljava/lang/String;
    //   172: sipush 154
    //   175: iconst_3
    //   176: invokestatic 41	kkkkkk/gguuuu:bккккк043Aкк043A043A	(Ljava/lang/String;CC)Ljava/lang/String;
    //   179: astore_1
    //   180: aload_1
    //   181: putstatic 59	com/mobile/ui/ics/activity/IcsChequeImageReviewActivity:EXTRA_ICS_DEPOSIT_CHEQUE_HISTORY_IMAGE_VIEW_MODEL	Ljava/lang/String;
    //   184: getstatic 61	com/mobile/ui/ics/activity/IcsChequeImageReviewActivity:EXTRA_SIDE_OF_IMAGE	Ljava/lang/String;
    //   187: sipush 213
    //   190: iconst_2
    //   191: invokestatic 41	kkkkkk/gguuuu:bккккк043Aкк043A043A	(Ljava/lang/String;CC)Ljava/lang/String;
    //   194: putstatic 61	com/mobile/ui/ics/activity/IcsChequeImageReviewActivity:EXTRA_SIDE_OF_IMAGE	Ljava/lang/String;
    //   197: return
    //   198: astore_1
    //   199: aload_1
    //   200: athrow
    //   201: astore_1
    //   202: aload_1
    //   203: athrow
    // Local variable table:
    //   start	length	slot	name	signature
    //   41	8	0	i	int
    //   10	171	1	str	String
    //   198	2	1	localException1	Exception
    //   201	2	1	localException2	Exception
    // Exception table:
    //   from	to	target	type
    //   0	11	198	java/lang/Exception
    //   139	156	198	java/lang/Exception
    //   180	197	198	java/lang/Exception
    //   156	180	201	java/lang/Exception
  }
  
  public IcsChequeImageReviewActivity() {}
  
  public static int b043B043Bл043B043Bлл043B()
  {
    return 28;
  }
  
  public static int b043Bл043B043B043Bлл043B()
  {
    return 2;
  }
  
  public static int bлл043B043B043Bлл043B()
  {
    return 0;
  }
  
  /* Error */
  public static android.content.Intent getIntent(android.content.Context paramContext, boolean paramBoolean1, com.mobile.ui.ics.mvp.IcsChequeImageViewModel paramIcsChequeImageViewModel, boolean paramBoolean2, String paramString1, String paramString2)
  {
    // Byte code:
    //   0: new 71	android/content/Intent
    //   3: dup
    //   4: aload_0
    //   5: ldc 2
    //   7: invokespecial 74	android/content/Intent:<init>	(Landroid/content/Context;Ljava/lang/Class;)V
    //   10: astore_0
    //   11: aload_0
    //   12: ldc 76
    //   14: sipush 154
    //   17: iconst_0
    //   18: invokestatic 41	kkkkkk/gguuuu:bккккк043Aкк043A043A	(Ljava/lang/String;CC)Ljava/lang/String;
    //   21: iload_1
    //   22: invokevirtual 80	android/content/Intent:putExtra	(Ljava/lang/String;Z)Landroid/content/Intent;
    //   25: pop
    //   26: aload_0
    //   27: ldc 82
    //   29: bipush 52
    //   31: sipush 149
    //   34: iconst_3
    //   35: invokestatic 86	kkkkkk/gguuuu:bк043Aккк043Aкк043A043A	(Ljava/lang/String;CCC)Ljava/lang/String;
    //   38: aload_2
    //   39: invokevirtual 89	android/content/Intent:putExtra	(Ljava/lang/String;Landroid/os/Parcelable;)Landroid/content/Intent;
    //   42: pop
    //   43: getstatic 53	com/mobile/ui/ics/activity/IcsChequeImageReviewActivity:bллл043B043Bлл043B	I
    //   46: istore 6
    //   48: iload 6
    //   50: getstatic 47	com/mobile/ui/ics/activity/IcsChequeImageReviewActivity:b043Bлл043B043Bлл043B	I
    //   53: iload 6
    //   55: iadd
    //   56: imul
    //   57: getstatic 49	com/mobile/ui/ics/activity/IcsChequeImageReviewActivity:bл043Bл043B043Bлл043B	I
    //   60: irem
    //   61: tableswitch	default:+19->80, 0:+29->90
    //   80: bipush 67
    //   82: putstatic 53	com/mobile/ui/ics/activity/IcsChequeImageReviewActivity:bллл043B043Bлл043B	I
    //   85: bipush 82
    //   87: putstatic 47	com/mobile/ui/ics/activity/IcsChequeImageReviewActivity:b043Bлл043B043Bлл043B	I
    //   90: aload_0
    //   91: ldc 91
    //   93: bipush 16
    //   95: iconst_4
    //   96: invokestatic 41	kkkkkk/gguuuu:bккккк043Aкк043A043A	(Ljava/lang/String;CC)Ljava/lang/String;
    //   99: iload_3
    //   100: invokevirtual 80	android/content/Intent:putExtra	(Ljava/lang/String;Z)Landroid/content/Intent;
    //   103: pop
    //   104: aload_0
    //   105: ldc 93
    //   107: bipush 20
    //   109: sipush 249
    //   112: iconst_3
    //   113: invokestatic 86	kkkkkk/gguuuu:bк043Aккк043Aкк043A043A	(Ljava/lang/String;CCC)Ljava/lang/String;
    //   116: aload 5
    //   118: invokevirtual 96	android/content/Intent:putExtra	(Ljava/lang/String;Ljava/lang/String;)Landroid/content/Intent;
    //   121: pop
    //   122: aload_0
    //   123: ldc 98
    //   125: sipush 192
    //   128: bipush 85
    //   130: iconst_3
    //   131: invokestatic 86	kkkkkk/gguuuu:bк043Aккк043Aкк043A043A	(Ljava/lang/String;CCC)Ljava/lang/String;
    //   134: aload 4
    //   136: invokevirtual 96	android/content/Intent:putExtra	(Ljava/lang/String;Ljava/lang/String;)Landroid/content/Intent;
    //   139: pop
    //   140: iconst_0
    //   141: tableswitch	default:+23->164, 0:+50->191, 1:+-1->140
    //   164: iconst_1
    //   165: tableswitch	default:+23->188, 0:+-25->140, 1:+26->191
    //   188: goto -24 -> 164
    //   191: getstatic 53	com/mobile/ui/ics/activity/IcsChequeImageReviewActivity:bллл043B043Bлл043B	I
    //   194: istore 6
    //   196: iload 6
    //   198: getstatic 47	com/mobile/ui/ics/activity/IcsChequeImageReviewActivity:b043Bлл043B043Bлл043B	I
    //   201: iload 6
    //   203: iadd
    //   204: imul
    //   205: getstatic 49	com/mobile/ui/ics/activity/IcsChequeImageReviewActivity:bл043Bл043B043Bлл043B	I
    //   208: irem
    //   209: tableswitch	default:+19->228, 0:+31->240
    //   228: invokestatic 45	com/mobile/ui/ics/activity/IcsChequeImageReviewActivity:b043B043Bл043B043Bлл043B	()I
    //   231: putstatic 53	com/mobile/ui/ics/activity/IcsChequeImageReviewActivity:bллл043B043Bлл043B	I
    //   234: invokestatic 45	com/mobile/ui/ics/activity/IcsChequeImageReviewActivity:b043B043Bл043B043Bлл043B	()I
    //   237: putstatic 47	com/mobile/ui/ics/activity/IcsChequeImageReviewActivity:b043Bлл043B043Bлл043B	I
    //   240: aload_0
    //   241: areturn
    //   242: astore_0
    //   243: aload_0
    //   244: athrow
    //   245: astore_0
    //   246: aload_0
    //   247: athrow
    // Local variable table:
    //   start	length	slot	name	signature
    //   0	248	0	paramContext	android.content.Context
    //   0	248	1	paramBoolean1	boolean
    //   0	248	2	paramIcsChequeImageViewModel	com.mobile.ui.ics.mvp.IcsChequeImageViewModel
    //   0	248	3	paramBoolean2	boolean
    //   0	248	4	paramString1	String
    //   0	248	5	paramString2	String
    //   46	159	6	i	int
    // Exception table:
    //   from	to	target	type
    //   0	43	242	java/lang/Exception
    //   90	104	242	java/lang/Exception
    //   104	140	245	java/lang/Exception
  }
  
  /* Error */
  public java.util.Map<String, android.os.Bundle> getDeepLinkMap(android.content.Context paramContext)
  {
    // Byte code:
    //   0: getstatic 53	com/mobile/ui/ics/activity/IcsChequeImageReviewActivity:bллл043B043Bлл043B	I
    //   3: getstatic 47	com/mobile/ui/ics/activity/IcsChequeImageReviewActivity:b043Bлл043B043Bлл043B	I
    //   6: iadd
    //   7: getstatic 53	com/mobile/ui/ics/activity/IcsChequeImageReviewActivity:bллл043B043Bлл043B	I
    //   10: imul
    //   11: invokestatic 102	com/mobile/ui/ics/activity/IcsChequeImageReviewActivity:b043Bл043B043B043Bлл043B	()I
    //   14: irem
    //   15: invokestatic 104	com/mobile/ui/ics/activity/IcsChequeImageReviewActivity:bлл043B043B043Bлл043B	()I
    //   18: if_icmpeq +15 -> 33
    //   21: invokestatic 45	com/mobile/ui/ics/activity/IcsChequeImageReviewActivity:b043B043Bл043B043Bлл043B	()I
    //   24: putstatic 53	com/mobile/ui/ics/activity/IcsChequeImageReviewActivity:bллл043B043Bлл043B	I
    //   27: invokestatic 45	com/mobile/ui/ics/activity/IcsChequeImageReviewActivity:b043B043Bл043B043Bлл043B	()I
    //   30: putstatic 47	com/mobile/ui/ics/activity/IcsChequeImageReviewActivity:b043Bлл043B043Bлл043B	I
    //   33: iconst_1
    //   34: tableswitch	default:+22->56, 0:+-34->0, 1:+49->83
    //   56: iconst_0
    //   57: tableswitch	default:+23->80, 0:+26->83, 1:+-57->0
    //   80: goto -24 -> 56
    //   83: getstatic 53	com/mobile/ui/ics/activity/IcsChequeImageReviewActivity:bллл043B043Bлл043B	I
    //   86: istore_2
    //   87: getstatic 47	com/mobile/ui/ics/activity/IcsChequeImageReviewActivity:b043Bлл043B043Bлл043B	I
    //   90: istore_3
    //   91: getstatic 49	com/mobile/ui/ics/activity/IcsChequeImageReviewActivity:bл043Bл043B043Bлл043B	I
    //   94: istore 4
    //   96: iload_2
    //   97: iload_3
    //   98: iload_2
    //   99: iadd
    //   100: imul
    //   101: iload 4
    //   103: irem
    //   104: tableswitch	default:+20->124, 0:+32->136
    //   124: invokestatic 45	com/mobile/ui/ics/activity/IcsChequeImageReviewActivity:b043B043Bл043B043Bлл043B	()I
    //   127: putstatic 53	com/mobile/ui/ics/activity/IcsChequeImageReviewActivity:bллл043B043Bлл043B	I
    //   130: invokestatic 45	com/mobile/ui/ics/activity/IcsChequeImageReviewActivity:b043B043Bл043B043Bлл043B	()I
    //   133: putstatic 47	com/mobile/ui/ics/activity/IcsChequeImageReviewActivity:b043Bлл043B043Bлл043B	I
    //   136: ldc 106
    //   138: bipush 29
    //   140: sipush 220
    //   143: iconst_1
    //   144: invokestatic 86	kkkkkk/gguuuu:bк043Aккк043Aкк043A043A	(Ljava/lang/String;CCC)Ljava/lang/String;
    //   147: invokestatic 112	kkkkkk/nuuuun$uunuun:b043F043F043F043Fпп043F043F043Fп	(Ljava/lang/String;)Ljava/util/Map;
    //   150: astore_1
    //   151: aload_1
    //   152: areturn
    //   153: astore_1
    //   154: aload_1
    //   155: athrow
    //   156: astore_1
    //   157: aload_1
    //   158: athrow
    // Local variable table:
    //   start	length	slot	name	signature
    //   0	159	0	this	IcsChequeImageReviewActivity
    //   0	159	1	paramContext	android.content.Context
    //   86	15	2	i	int
    //   90	10	3	j	int
    //   94	10	4	k	int
    // Exception table:
    //   from	to	target	type
    //   83	96	153	java/lang/Exception
    //   136	151	153	java/lang/Exception
    //   124	136	156	java/lang/Exception
  }
  
  /* Error */
  protected int getLayoutId()
  {
    // Byte code:
    //   0: getstatic 53	com/mobile/ui/ics/activity/IcsChequeImageReviewActivity:bллл043B043Bлл043B	I
    //   3: istore_1
    //   4: iload_1
    //   5: getstatic 47	com/mobile/ui/ics/activity/IcsChequeImageReviewActivity:b043Bлл043B043Bлл043B	I
    //   8: iload_1
    //   9: iadd
    //   10: imul
    //   11: getstatic 49	com/mobile/ui/ics/activity/IcsChequeImageReviewActivity:bл043Bл043B043Bлл043B	I
    //   14: irem
    //   15: tableswitch	default:+17->32, 0:+29->44
    //   32: invokestatic 45	com/mobile/ui/ics/activity/IcsChequeImageReviewActivity:b043B043Bл043B043Bлл043B	()I
    //   35: putstatic 53	com/mobile/ui/ics/activity/IcsChequeImageReviewActivity:bллл043B043Bлл043B	I
    //   38: invokestatic 45	com/mobile/ui/ics/activity/IcsChequeImageReviewActivity:b043B043Bл043B043Bлл043B	()I
    //   41: putstatic 47	com/mobile/ui/ics/activity/IcsChequeImageReviewActivity:b043Bлл043B043Bлл043B	I
    //   44: iconst_1
    //   45: tableswitch	default:+23->68, 0:+-45->0, 1:+50->95
    //   68: iconst_0
    //   69: tableswitch	default:+23->92, 0:+26->95, 1:+-69->0
    //   92: goto -24 -> 68
    //   95: getstatic 120	com/mobile/ui/R$layout:activity_ics_cheque_deposit_image_review	I
    //   98: istore_1
    //   99: invokestatic 45	com/mobile/ui/ics/activity/IcsChequeImageReviewActivity:b043B043Bл043B043Bлл043B	()I
    //   102: istore_2
    //   103: getstatic 47	com/mobile/ui/ics/activity/IcsChequeImageReviewActivity:b043Bлл043B043Bлл043B	I
    //   106: istore_3
    //   107: getstatic 49	com/mobile/ui/ics/activity/IcsChequeImageReviewActivity:bл043Bл043B043Bлл043B	I
    //   110: istore 4
    //   112: iload_2
    //   113: iload_3
    //   114: iload_2
    //   115: iadd
    //   116: imul
    //   117: iload 4
    //   119: irem
    //   120: tableswitch	default:+20->140, 0:+31->151
    //   140: bipush 43
    //   142: putstatic 53	com/mobile/ui/ics/activity/IcsChequeImageReviewActivity:bллл043B043Bлл043B	I
    //   145: invokestatic 45	com/mobile/ui/ics/activity/IcsChequeImageReviewActivity:b043B043Bл043B043Bлл043B	()I
    //   148: putstatic 47	com/mobile/ui/ics/activity/IcsChequeImageReviewActivity:b043Bлл043B043Bлл043B	I
    //   151: iload_1
    //   152: ireturn
    //   153: astore 5
    //   155: aload 5
    //   157: athrow
    //   158: astore 5
    //   160: aload 5
    //   162: athrow
    // Local variable table:
    //   start	length	slot	name	signature
    //   0	163	0	this	IcsChequeImageReviewActivity
    //   3	149	1	i	int
    //   102	15	2	j	int
    //   106	10	3	k	int
    //   110	10	4	m	int
    //   153	3	5	localException1	Exception
    //   158	3	5	localException2	Exception
    // Exception table:
    //   from	to	target	type
    //   95	112	153	java/lang/Exception
    //   140	151	158	java/lang/Exception
  }
  
  /* Error */
  protected void onCreate(@android.support.annotation.Nullable android.os.Bundle paramBundle)
  {
    // Byte code:
    //   0: aload_0
    //   1: invokevirtual 127	com/mobile/ui/ics/activity/IcsChequeImageReviewActivity:getApplicationContext	()Landroid/content/Context;
    //   4: invokestatic 133	kkkkkk/nkkkkk:bЗЗ0417З0417З0417041704170417	(Landroid/content/Context;)V
    //   7: aload_0
    //   8: invokevirtual 127	com/mobile/ui/ics/activity/IcsChequeImageReviewActivity:getApplicationContext	()Landroid/content/Context;
    //   11: invokestatic 138	kkkkkk/nnnkkk:bхх0445ххххххх	(Landroid/content/Context;)V
    //   14: aload_0
    //   15: invokevirtual 127	com/mobile/ui/ics/activity/IcsChequeImageReviewActivity:getApplicationContext	()Landroid/content/Context;
    //   18: invokestatic 143	kkkkkk/nknnkk:bх0445ххх04450445ххх	(Landroid/content/Context;)V
    //   21: aload_0
    //   22: aload_1
    //   23: invokespecial 145	com/mobile/ui/common/activity/AppTimeoutActivity:onCreate	(Landroid/os/Bundle;)V
    //   26: aload_0
    //   27: invokevirtual 148	com/mobile/ui/ics/activity/IcsChequeImageReviewActivity:getIntent	()Landroid/content/Intent;
    //   30: ldc -106
    //   32: bipush 111
    //   34: sipush 241
    //   37: iconst_3
    //   38: invokestatic 86	kkkkkk/gguuuu:bк043Aккк043Aкк043A043A	(Ljava/lang/String;CCC)Ljava/lang/String;
    //   41: iconst_0
    //   42: invokevirtual 154	android/content/Intent:getBooleanExtra	(Ljava/lang/String;Z)Z
    //   45: istore_2
    //   46: aload_0
    //   47: invokevirtual 148	com/mobile/ui/ics/activity/IcsChequeImageReviewActivity:getIntent	()Landroid/content/Intent;
    //   50: ldc -100
    //   52: sipush 206
    //   55: iconst_1
    //   56: invokestatic 41	kkkkkk/gguuuu:bккккк043Aкк043A043A	(Ljava/lang/String;CC)Ljava/lang/String;
    //   59: invokevirtual 160	android/content/Intent:getParcelableExtra	(Ljava/lang/String;)Landroid/os/Parcelable;
    //   62: checkcast 162	com/mobile/ui/ics/mvp/IcsChequeImageViewModel
    //   65: astore_1
    //   66: aload_0
    //   67: invokevirtual 148	com/mobile/ui/ics/activity/IcsChequeImageReviewActivity:getIntent	()Landroid/content/Intent;
    //   70: ldc -92
    //   72: sipush 194
    //   75: bipush 61
    //   77: iconst_0
    //   78: invokestatic 86	kkkkkk/gguuuu:bк043Aккк043Aкк043A043A	(Ljava/lang/String;CCC)Ljava/lang/String;
    //   81: iconst_0
    //   82: invokevirtual 154	android/content/Intent:getBooleanExtra	(Ljava/lang/String;Z)Z
    //   85: istore_3
    //   86: aload_0
    //   87: invokevirtual 148	com/mobile/ui/ics/activity/IcsChequeImageReviewActivity:getIntent	()Landroid/content/Intent;
    //   90: ldc -90
    //   92: bipush 89
    //   94: sipush 192
    //   97: iconst_2
    //   98: invokestatic 86	kkkkkk/gguuuu:bк043Aккк043Aкк043A043A	(Ljava/lang/String;CCC)Ljava/lang/String;
    //   101: invokevirtual 170	android/content/Intent:getStringExtra	(Ljava/lang/String;)Ljava/lang/String;
    //   104: astore 4
    //   106: aload_0
    //   107: invokevirtual 148	com/mobile/ui/ics/activity/IcsChequeImageReviewActivity:getIntent	()Landroid/content/Intent;
    //   110: ldc -84
    //   112: bipush 92
    //   114: iconst_0
    //   115: invokestatic 41	kkkkkk/gguuuu:bккккк043Aкк043A043A	(Ljava/lang/String;CC)Ljava/lang/String;
    //   118: invokevirtual 170	android/content/Intent:getStringExtra	(Ljava/lang/String;)Ljava/lang/String;
    //   121: astore 5
    //   123: aload_0
    //   124: invokevirtual 176	com/mobile/ui/ics/activity/IcsChequeImageReviewActivity:getSupportFragmentManager	()Landroid/support/v4/app/FragmentManager;
    //   127: invokevirtual 182	android/support/v4/app/FragmentManager:beginTransaction	()Landroid/support/v4/app/FragmentTransaction;
    //   130: getstatic 187	com/mobile/ui/R$id:icsChequeImageReviewContainer	I
    //   133: iload_2
    //   134: aload_1
    //   135: iload_3
    //   136: aload 4
    //   138: aload 5
    //   140: invokestatic 193	com/mobile/ui/ics/fragment/IcsChequeImageReviewFragment:newInstance	(ZLcom/mobile/ui/ics/mvp/IcsChequeImageViewModel;ZLjava/lang/String;Ljava/lang/String;)Lcom/mobile/ui/ics/fragment/IcsChequeImageReviewFragment;
    //   143: invokevirtual 199	android/support/v4/app/FragmentTransaction:replace	(ILandroid/support/v4/app/Fragment;)Landroid/support/v4/app/FragmentTransaction;
    //   146: invokevirtual 202	android/support/v4/app/FragmentTransaction:commit	()I
    //   149: pop
    //   150: return
    //   151: astore_1
    //   152: aload_1
    //   153: athrow
    //   154: astore_1
    //   155: aload_1
    //   156: athrow
    // Local variable table:
    //   start	length	slot	name	signature
    //   0	157	0	this	IcsChequeImageReviewActivity
    //   0	157	1	paramBundle	android.os.Bundle
    //   45	89	2	bool1	boolean
    //   85	51	3	bool2	boolean
    //   104	33	4	str1	String
    //   121	18	5	str2	String
    // Exception table:
    //   from	to	target	type
    //   0	123	151	java/lang/Exception
    //   123	150	154	java/lang/Exception
  }
  
  /* Error */
  protected boolean shouldRestartAppIfSecureCoreNotInitialized()
  {
    // Byte code:
    //   0: getstatic 53	com/mobile/ui/ics/activity/IcsChequeImageReviewActivity:bллл043B043Bлл043B	I
    //   3: istore_1
    //   4: getstatic 47	com/mobile/ui/ics/activity/IcsChequeImageReviewActivity:b043Bлл043B043Bлл043B	I
    //   7: istore_2
    //   8: getstatic 49	com/mobile/ui/ics/activity/IcsChequeImageReviewActivity:bл043Bл043B043Bлл043B	I
    //   11: istore_3
    //   12: iload_1
    //   13: iload_2
    //   14: iload_1
    //   15: iadd
    //   16: imul
    //   17: iload_3
    //   18: irem
    //   19: tableswitch	default:+17->36, 0:+59->78
    //   36: getstatic 53	com/mobile/ui/ics/activity/IcsChequeImageReviewActivity:bллл043B043Bлл043B	I
    //   39: getstatic 47	com/mobile/ui/ics/activity/IcsChequeImageReviewActivity:b043Bлл043B043Bлл043B	I
    //   42: iadd
    //   43: getstatic 53	com/mobile/ui/ics/activity/IcsChequeImageReviewActivity:bллл043B043Bлл043B	I
    //   46: imul
    //   47: getstatic 49	com/mobile/ui/ics/activity/IcsChequeImageReviewActivity:bл043Bл043B043Bлл043B	I
    //   50: irem
    //   51: getstatic 51	com/mobile/ui/ics/activity/IcsChequeImageReviewActivity:bл043B043B043B043Bлл043B	I
    //   54: if_icmpeq +14 -> 68
    //   57: bipush 12
    //   59: putstatic 53	com/mobile/ui/ics/activity/IcsChequeImageReviewActivity:bллл043B043Bлл043B	I
    //   62: invokestatic 45	com/mobile/ui/ics/activity/IcsChequeImageReviewActivity:b043B043Bл043B043Bлл043B	()I
    //   65: putstatic 51	com/mobile/ui/ics/activity/IcsChequeImageReviewActivity:bл043B043B043B043Bлл043B	I
    //   68: bipush 64
    //   70: putstatic 53	com/mobile/ui/ics/activity/IcsChequeImageReviewActivity:bллл043B043Bлл043B	I
    //   73: bipush 47
    //   75: putstatic 51	com/mobile/ui/ics/activity/IcsChequeImageReviewActivity:bл043B043B043B043Bлл043B	I
    //   78: iconst_1
    //   79: ireturn
    //   80: astore 4
    //   82: aload 4
    //   84: athrow
    //   85: astore 4
    //   87: aload 4
    //   89: athrow
    // Local variable table:
    //   start	length	slot	name	signature
    //   0	90	0	this	IcsChequeImageReviewActivity
    //   3	14	1	i	int
    //   7	9	2	j	int
    //   11	8	3	k	int
    //   80	3	4	localException1	Exception
    //   85	3	4	localException2	Exception
    // Exception table:
    //   from	to	target	type
    //   0	12	80	java/lang/Exception
    //   68	78	85	java/lang/Exception
  }
  
  public boolean shouldShowToolbar()
  {
    switch (0)
    {
    case 1: 
    default: 
      for (;;)
      {
        switch (1)
        {
        }
      }
    }
    if ((bллл043B043Bлл043B + b043Bлл043B043Bлл043B) * bллл043B043Bлл043B % bл043Bл043B043Bлл043B != bлл043B043B043Bлл043B())
    {
      bллл043B043Bлл043B = b043B043Bл043B043Bлл043B();
      bл043B043B043B043Bлл043B = 67;
    }
    return false;
  }
}
