package com.mobile.ui.ics.activity;

import android.content.Context;
import android.content.Intent;
import android.os.Bundle;
import com.mobile.ui.common.activity.AppTimeoutActivity;
import java.util.Map;
import kkkkkk.gguuuu;
import kkkkkk.nuuuun.uunuun;

public class IcsViewDemoActivity
  extends AppTimeoutActivity
{
  public static int b043Bл043B043B043Bл043B043B = 2;
  public static int b043Bлллл043B043B043B = 0;
  public static int bл043B043B043B043Bл043B043B = 72;
  public static int bллллл043B043B043B = 1;
  
  public IcsViewDemoActivity() {}
  
  public static int b043B043B043B043B043Bл043B043B()
  {
    return 0;
  }
  
  public static int b043B043Bл043B043Bл043B043B()
  {
    return 86;
  }
  
  public static int bл043Bллл043B043B043B()
  {
    return 2;
  }
  
  public static int bлл043B043B043Bл043B043B()
  {
    return 1;
  }
  
  public static Intent getIntent(Context paramContext)
  {
    switch (0)
    {
    case 1: 
    default: 
      for (;;)
      {
        switch (1)
        {
        }
      }
    }
    paramContext = new Intent(paramContext, IcsViewDemoActivity.class);
    if ((bл043B043B043B043Bл043B043B + bллллл043B043B043B) * bл043B043B043B043Bл043B043B % b043Bл043B043B043Bл043B043B != b043B043B043B043B043Bл043B043B())
    {
      bл043B043B043B043Bл043B043B = b043B043Bл043B043Bл043B043B();
      bллллл043B043B043B = b043B043Bл043B043Bл043B043B();
    }
    int i = b043B043Bл043B043Bл043B043B();
    switch (i * (bлл043B043B043Bл043B043B() + i) % b043Bл043B043B043Bл043B043B)
    {
    default: 
      b043Bл043B043B043Bл043B043B = 89;
    }
    return paramContext;
  }
  
  public Map<String, Bundle> getDeepLinkMap(Context paramContext)
  {
    if ((bл043B043B043B043Bл043B043B + bллллл043B043B043B) * bл043B043B043B043Bл043B043B % b043Bл043B043B043Bл043B043B != b043Bлллл043B043B043B)
    {
      bл043B043B043B043Bл043B043B = 35;
      b043Bлллл043B043B043B = b043B043Bл043B043Bл043B043B();
    }
    try
    {
      paramContext = nuuuun.uunuun.b043F043F043F043Fпп043F043F043Fп(gguuuu.bккккк043Aкк043A043A("\\Wh#ma^q(`bkn", '¸', '\004'));
      return paramContext;
    }
    catch (Exception paramContext)
    {
      throw paramContext;
    }
  }
  
  /* Error */
  protected int getLayoutId()
  {
    // Byte code:
    //   0: getstatic 70	com/mobile/ui/R$layout:activity_ics_view_demo	I
    //   3: istore_1
    //   4: getstatic 32	com/mobile/ui/ics/activity/IcsViewDemoActivity:bл043B043B043B043Bл043B043B	I
    //   7: istore_2
    //   8: invokestatic 42	com/mobile/ui/ics/activity/IcsViewDemoActivity:bлл043B043B043Bл043B043B	()I
    //   11: istore_3
    //   12: getstatic 32	com/mobile/ui/ics/activity/IcsViewDemoActivity:bл043B043B043B043Bл043B043B	I
    //   15: istore 4
    //   17: getstatic 36	com/mobile/ui/ics/activity/IcsViewDemoActivity:b043Bл043B043B043Bл043B043B	I
    //   20: istore 5
    //   22: getstatic 48	com/mobile/ui/ics/activity/IcsViewDemoActivity:b043Bлллл043B043B043B	I
    //   25: istore 6
    //   27: iload_2
    //   28: iload_3
    //   29: iadd
    //   30: iload 4
    //   32: imul
    //   33: iload 5
    //   35: irem
    //   36: iload 6
    //   38: if_icmpeq +57 -> 95
    //   41: invokestatic 40	com/mobile/ui/ics/activity/IcsViewDemoActivity:b043B043Bл043B043Bл043B043B	()I
    //   44: putstatic 32	com/mobile/ui/ics/activity/IcsViewDemoActivity:bл043B043B043B043Bл043B043B	I
    //   47: bipush 51
    //   49: putstatic 48	com/mobile/ui/ics/activity/IcsViewDemoActivity:b043Bлллл043B043B043B	I
    //   52: getstatic 32	com/mobile/ui/ics/activity/IcsViewDemoActivity:bл043B043B043B043Bл043B043B	I
    //   55: istore_2
    //   56: iload_2
    //   57: getstatic 34	com/mobile/ui/ics/activity/IcsViewDemoActivity:bллллл043B043B043B	I
    //   60: iload_2
    //   61: iadd
    //   62: imul
    //   63: getstatic 36	com/mobile/ui/ics/activity/IcsViewDemoActivity:b043Bл043B043B043Bл043B043B	I
    //   66: irem
    //   67: tableswitch	default:+17->84, 0:+28->95
    //   84: invokestatic 40	com/mobile/ui/ics/activity/IcsViewDemoActivity:b043B043Bл043B043Bл043B043B	()I
    //   87: putstatic 32	com/mobile/ui/ics/activity/IcsViewDemoActivity:bл043B043B043B043Bл043B043B	I
    //   90: bipush 41
    //   92: putstatic 48	com/mobile/ui/ics/activity/IcsViewDemoActivity:b043Bлллл043B043B043B	I
    //   95: iload_1
    //   96: ireturn
    //   97: astore 7
    //   99: aload 7
    //   101: athrow
    //   102: astore 7
    //   104: aload 7
    //   106: athrow
    // Local variable table:
    //   start	length	slot	name	signature
    //   0	107	0	this	IcsViewDemoActivity
    //   3	93	1	i	int
    //   7	56	2	j	int
    //   11	19	3	k	int
    //   15	18	4	m	int
    //   20	16	5	n	int
    //   25	14	6	i1	int
    //   97	3	7	localException1	Exception
    //   102	3	7	localException2	Exception
    // Exception table:
    //   from	to	target	type
    //   0	4	97	java/lang/Exception
    //   41	52	97	java/lang/Exception
    //   4	27	102	java/lang/Exception
  }
  
  /* Error */
  protected void onCreate(@android.support.annotation.Nullable Bundle paramBundle)
  {
    // Byte code:
    //   0: aload_0
    //   1: invokevirtual 77	com/mobile/ui/ics/activity/IcsViewDemoActivity:getApplicationContext	()Landroid/content/Context;
    //   4: invokestatic 83	kkkkkk/nkkkkk:bЗЗ0417З0417З0417041704170417	(Landroid/content/Context;)V
    //   7: aload_0
    //   8: invokevirtual 77	com/mobile/ui/ics/activity/IcsViewDemoActivity:getApplicationContext	()Landroid/content/Context;
    //   11: invokestatic 88	kkkkkk/nnnkkk:bхх0445ххххххх	(Landroid/content/Context;)V
    //   14: aload_0
    //   15: invokevirtual 77	com/mobile/ui/ics/activity/IcsViewDemoActivity:getApplicationContext	()Landroid/content/Context;
    //   18: invokestatic 93	kkkkkk/nknnkk:bх0445ххх04450445ххх	(Landroid/content/Context;)V
    //   21: iconst_0
    //   22: tableswitch	default:+22->44, 0:+81->103, 1:+-1->21
    //   44: getstatic 32	com/mobile/ui/ics/activity/IcsViewDemoActivity:bл043B043B043B043Bл043B043B	I
    //   47: getstatic 34	com/mobile/ui/ics/activity/IcsViewDemoActivity:bллллл043B043B043B	I
    //   50: iadd
    //   51: getstatic 32	com/mobile/ui/ics/activity/IcsViewDemoActivity:bл043B043B043B043Bл043B043B	I
    //   54: imul
    //   55: getstatic 36	com/mobile/ui/ics/activity/IcsViewDemoActivity:b043Bл043B043B043Bл043B043B	I
    //   58: irem
    //   59: getstatic 48	com/mobile/ui/ics/activity/IcsViewDemoActivity:b043Bлллл043B043B043B	I
    //   62: if_icmpeq +14 -> 76
    //   65: invokestatic 40	com/mobile/ui/ics/activity/IcsViewDemoActivity:b043B043Bл043B043Bл043B043B	()I
    //   68: putstatic 32	com/mobile/ui/ics/activity/IcsViewDemoActivity:bл043B043B043B043Bл043B043B	I
    //   71: bipush 71
    //   73: putstatic 48	com/mobile/ui/ics/activity/IcsViewDemoActivity:b043Bлллл043B043B043B	I
    //   76: iconst_1
    //   77: tableswitch	default:+23->100, 0:+-56->21, 1:+26->103
    //   100: goto -56 -> 44
    //   103: aload_0
    //   104: aload_1
    //   105: invokespecial 95	com/mobile/ui/common/activity/AppTimeoutActivity:onCreate	(Landroid/os/Bundle;)V
    //   108: aload_0
    //   109: getstatic 100	com/mobile/ui/R$string:accessibility_ics_view_demo_page_message	I
    //   112: invokevirtual 104	com/mobile/ui/ics/activity/IcsViewDemoActivity:setTitle	(I)V
    //   115: aload_1
    //   116: ifnonnull +66 -> 182
    //   119: getstatic 32	com/mobile/ui/ics/activity/IcsViewDemoActivity:bл043B043B043B043Bл043B043B	I
    //   122: istore_2
    //   123: getstatic 34	com/mobile/ui/ics/activity/IcsViewDemoActivity:bллллл043B043B043B	I
    //   126: istore_3
    //   127: iload_2
    //   128: iload_3
    //   129: iadd
    //   130: getstatic 32	com/mobile/ui/ics/activity/IcsViewDemoActivity:bл043B043B043B043Bл043B043B	I
    //   133: imul
    //   134: getstatic 36	com/mobile/ui/ics/activity/IcsViewDemoActivity:b043Bл043B043B043Bл043B043B	I
    //   137: irem
    //   138: getstatic 48	com/mobile/ui/ics/activity/IcsViewDemoActivity:b043Bлллл043B043B043B	I
    //   141: if_icmpeq +13 -> 154
    //   144: bipush 36
    //   146: putstatic 32	com/mobile/ui/ics/activity/IcsViewDemoActivity:bл043B043B043B043Bл043B043B	I
    //   149: bipush 96
    //   151: putstatic 48	com/mobile/ui/ics/activity/IcsViewDemoActivity:b043Bлллл043B043B043B	I
    //   154: aload_0
    //   155: invokevirtual 108	com/mobile/ui/ics/activity/IcsViewDemoActivity:getSupportFragmentManager	()Landroid/support/v4/app/FragmentManager;
    //   158: invokevirtual 114	android/support/v4/app/FragmentManager:beginTransaction	()Landroid/support/v4/app/FragmentTransaction;
    //   161: astore_1
    //   162: getstatic 119	com/mobile/ui/R$id:fragmentContainer	I
    //   165: istore_2
    //   166: invokestatic 125	com/mobile/ui/ics/fragment/IcsViewDemoFragment:newInstance	()Lcom/mobile/ui/ics/fragment/IcsViewDemoFragment;
    //   169: astore 4
    //   171: aload_1
    //   172: iload_2
    //   173: aload 4
    //   175: invokevirtual 131	android/support/v4/app/FragmentTransaction:replace	(ILandroid/support/v4/app/Fragment;)Landroid/support/v4/app/FragmentTransaction;
    //   178: invokevirtual 134	android/support/v4/app/FragmentTransaction:commit	()I
    //   181: pop
    //   182: return
    //   183: astore_1
    //   184: aload_1
    //   185: athrow
    //   186: astore_1
    //   187: aload_1
    //   188: athrow
    // Local variable table:
    //   start	length	slot	name	signature
    //   0	189	0	this	IcsViewDemoActivity
    //   0	189	1	paramBundle	Bundle
    //   122	51	2	i	int
    //   126	4	3	j	int
    //   169	5	4	localIcsViewDemoFragment	com.mobile.ui.ics.fragment.IcsViewDemoFragment
    // Exception table:
    //   from	to	target	type
    //   0	21	183	java/lang/Exception
    //   103	115	183	java/lang/Exception
    //   119	127	183	java/lang/Exception
    //   154	171	183	java/lang/Exception
    //   127	154	186	java/lang/Exception
    //   171	182	186	java/lang/Exception
  }
  
  /* Error */
  protected boolean shouldRestartAppIfSecureCoreNotInitialized()
  {
    // Byte code:
    //   0: iconst_0
    //   1: tableswitch	default:+23->24, 0:+50->51, 1:+-1->0
    //   24: iconst_1
    //   25: tableswitch	default:+23->48, 0:+-25->0, 1:+26->51
    //   48: goto -24 -> 24
    //   51: getstatic 32	com/mobile/ui/ics/activity/IcsViewDemoActivity:bл043B043B043B043Bл043B043B	I
    //   54: istore_1
    //   55: getstatic 34	com/mobile/ui/ics/activity/IcsViewDemoActivity:bллллл043B043B043B	I
    //   58: istore_2
    //   59: getstatic 32	com/mobile/ui/ics/activity/IcsViewDemoActivity:bл043B043B043B043Bл043B043B	I
    //   62: istore_3
    //   63: getstatic 36	com/mobile/ui/ics/activity/IcsViewDemoActivity:b043Bл043B043B043Bл043B043B	I
    //   66: istore 4
    //   68: invokestatic 38	com/mobile/ui/ics/activity/IcsViewDemoActivity:b043B043B043B043B043Bл043B043B	()I
    //   71: istore 5
    //   73: iload_1
    //   74: iload_2
    //   75: iadd
    //   76: iload_3
    //   77: imul
    //   78: iload 4
    //   80: irem
    //   81: iload 5
    //   83: if_icmpeq +14 -> 97
    //   86: invokestatic 40	com/mobile/ui/ics/activity/IcsViewDemoActivity:b043B043Bл043B043Bл043B043B	()I
    //   89: putstatic 32	com/mobile/ui/ics/activity/IcsViewDemoActivity:bл043B043B043B043Bл043B043B	I
    //   92: bipush 34
    //   94: putstatic 48	com/mobile/ui/ics/activity/IcsViewDemoActivity:b043Bлллл043B043B043B	I
    //   97: getstatic 32	com/mobile/ui/ics/activity/IcsViewDemoActivity:bл043B043B043B043Bл043B043B	I
    //   100: istore_1
    //   101: iload_1
    //   102: invokestatic 42	com/mobile/ui/ics/activity/IcsViewDemoActivity:bлл043B043B043Bл043B043B	()I
    //   105: iload_1
    //   106: iadd
    //   107: imul
    //   108: invokestatic 139	com/mobile/ui/ics/activity/IcsViewDemoActivity:bл043Bллл043B043B043B	()I
    //   111: irem
    //   112: tableswitch	default:+20->132, 0:+29->141
    //   132: bipush 74
    //   134: putstatic 32	com/mobile/ui/ics/activity/IcsViewDemoActivity:bл043B043B043B043Bл043B043B	I
    //   137: iconst_1
    //   138: putstatic 48	com/mobile/ui/ics/activity/IcsViewDemoActivity:b043Bлллл043B043B043B	I
    //   141: iconst_1
    //   142: ireturn
    //   143: astore 6
    //   145: aload 6
    //   147: athrow
    //   148: astore 6
    //   150: aload 6
    //   152: athrow
    // Local variable table:
    //   start	length	slot	name	signature
    //   0	153	0	this	IcsViewDemoActivity
    //   54	54	1	i	int
    //   58	18	2	j	int
    //   62	16	3	k	int
    //   66	15	4	m	int
    //   71	13	5	n	int
    //   143	3	6	localException1	Exception
    //   148	3	6	localException2	Exception
    // Exception table:
    //   from	to	target	type
    //   51	73	143	java/lang/Exception
    //   86	97	148	java/lang/Exception
  }
  
  public boolean shouldShowToolbar()
  {
    return false;
  }
}
