package o;

import android.content.Context;
import android.widget.Toast;
import java.io.UnsupportedEncodingException;

public abstract class aa
  implements ad
{
  private static int ʼ;
  private static byte ˊ;
  private static long ˋ;
  private static char[] ˎ;
  private static int ॱ = 0;
  private final Context ˏ;
  
  static
  {
    ʼ = 1;
    ॱ();
    ˊ = -102;
    int i;
    do
    {
      return;
      i = ʼ + 67;
      ॱ = i % 128;
    } while (i % 2 != 0);
  }
  
  public aa(Context paramContext)
  {
    this.ˏ = paramContext;
  }
  
  private static String ˎ(char paramChar, int paramInt1, int paramInt2)
  {
    Object localObject;
    int i;
    for (;;)
    {
      localObject = new char[paramInt2];
      i = 0;
      break;
    }
    localObject[i] = ((char)(int)(ˎ[(paramInt1 + i)] ^ i * ˋ ^ paramChar));
    i += 1;
    break label253;
    label47:
    int j;
    switch (j)
    {
    default: 
      break;
      label80:
      do
      {
        paramChar = '\001';
        break;
        paramChar = ʼ + 53;
        ॱ = paramChar % '';
      } while (paramChar % '\002' != 0);
      break label237;
      return localObject;
    }
    label237:
    label242:
    label253:
    label254:
    for (;;)
    {
      j = 1;
      break label47;
      j = ʼ + 65;
      ॱ = j % 128;
      if (j % 2 == 0)
      {
        break;
        break label242;
        localObject = new String((char[])localObject);
        break label80;
      }
      for (;;)
      {
        switch (paramChar)
        {
        case '\000': 
        default: 
          return localObject;
        }
        paramChar = 27 / 0;
        return localObject;
        localObject[i] = ((char)(int)(ˎ[(paramInt1 >> i)] & i * ˋ | paramChar));
        i += 105;
        break label253;
        j = 0;
        break;
        paramChar = '\000';
      }
      for (;;)
      {
        if (i < paramInt2) {
          break label254;
        }
        break;
      }
    }
  }
  
  private String ॱ(String paramString)
  {
    int i;
    int j;
    switch (i)
    {
    default: 
      break label211;
      break;
      for (;;)
      {
        j = ॱ + 39;
        ʼ = j % 128;
        if (j % 2 == 0) {
          break;
        }
        break;
        label65:
        switch (j)
        {
        }
      }
      break;
    }
    for (;;)
    {
      try
      {
        j = arrayOfByte.length;
        if (i >= j)
        {
          continue;
          i = ʼ + 47;
          ॱ = i % 128;
          if (i % 2 != 0) {
            continue;
          }
          continue;
          j = 0;
          break label65;
          arrayOfByte = paramString.getBytes(ˎ('\000', 89, 60).intern());
          paramString = new byte[arrayOfByte.length];
          i = 1;
          continue;
        }
        j = 1;
        break label65;
        i = 19;
        break;
        i = 79;
      }
      catch (UnsupportedEncodingException paramString)
      {
        byte[] arrayOfByte;
        label211:
        throw new RuntimeException(paramString);
      }
      paramString[i] = ((byte)(arrayOfByte[(arrayOfByte.length - i - 1)] ^ ˊ));
      i += 1;
      continue;
      arrayOfByte = paramString.getBytes(ˎ('\000', 118, 10).intern());
      paramString = new byte[arrayOfByte.length];
      i = 0;
    }
    paramString = new String(paramString, ˎ('\000', 128, 5).intern());
    return paramString;
  }
  
  static void ॱ()
  {
    ˋ = 1553636662327003175L;
    ˎ = new char[] { -18181, -3901, 10427, 24711, 6876, 21239, -30049, -15682, 14918, 29188, -21983, -7296, 23520, -27771, -13491, 833, 31519, -19658, -5900, 8344, -26456, -12288, 2162, 16430, -17983, -3611, 10635, 24921, -9915, 4373, 18746, -30997, -353, 14077, 109, 18498, -28611, -10234, 8445, 26788, -20337, 116, 18510, -28614, -10215, 8441, -11858, -26235, 16877, 2508, -3788, -18080, 24915, -17144, -2781, 11595, 25962, -25198, -10800, 3573, 17492, -972, 13393, 27801, -23403, -9013, 5346, 20256, -30900, 16252, 30676, -20601, -6240, 7700, 22060, -29117, -14717, 32429, -18749, -4429, 8473, 22852, -28375, -25878, -11566, 2727, 17030, -17806, -3536, 10758, 25582, 67, 18504, -28612, -10224, 8413, 26803, -20326, -1729, 16735, -30406, -11790, 6533, 25085, 23369, 4984, -13546, -31955, 31699, 13191, -5196, -23944, 6781, -11749, -29992, 17122, 14982, -3419, 73, 18548, -28671, -10152, 8356, 26875, -20257, -1752, 16661, -30354, 85, 18547, -28664, -10152, 8356 };
  }
  
  public void a_(String paramString)
  {
    break label60;
    int i = 97;
    break label196;
    i = 0;
    for (;;)
    {
      label14:
      Toast.makeText(this.ˏ, (CharSequence)paramString, 1).show();
      break label97;
      label32:
      vq.ˎ(paramString, ˎ('\000', 38, 1).intern());
      if (this.ˏ != null) {
        break;
      }
      break label187;
      return;
      label60:
      break label124;
      return;
      return;
      for (;;)
      {
        try
        {
          localObject = ˎ('\000', 34, 7);
        }
        catch (Exception paramString)
        {
          Object localObject;
          label97:
          label124:
          throw paramString;
        }
        try
        {
          localObject = ((String)localObject).intern();
          vq.ˎ(paramString, (String)localObject);
          localObject = this.ˏ;
          if (localObject != null) {
            break label14;
          }
          return;
        }
        catch (Exception paramString)
        {
          throw paramString;
        }
        i = ॱ + 59;
        ʼ = i % 128;
        if (i % 2 == 0) {
          break label182;
        }
        break;
        i = ʼ + 91;
        ॱ = i % 128;
        if (i % 2 != 0) {
          break label32;
        }
      }
      for (;;)
      {
        switch (i)
        {
        }
        break;
        label182:
        i = 1;
      }
      label187:
      i = 14;
      label196:
      switch (i)
      {
      }
    }
  }
  
  /* Error */
  public void ˎ(String paramString1, String paramString2)
  {
    // Byte code:
    //   0: goto +79 -> 79
    //   3: new 221	java/lang/NullPointerException
    //   6: dup
    //   7: invokespecial 222	java/lang/NullPointerException:<init>	()V
    //   10: athrow
    //   11: getstatic 23	o/aa:ʼ	I
    //   14: iconst_1
    //   15: iadd
    //   16: istore_3
    //   17: iload_3
    //   18: sipush 128
    //   21: irem
    //   22: putstatic 21	o/aa:ॱ	I
    //   25: iload_3
    //   26: iconst_2
    //   27: irem
    //   28: ifeq +6 -> 34
    //   31: goto +103 -> 134
    //   34: goto +337 -> 371
    //   37: goto +147 -> 184
    //   40: iconst_1
    //   41: istore_3
    //   42: goto +299 -> 341
    //   45: goto +192 -> 237
    //   48: aload 5
    //   50: ldc -33
    //   52: bipush 53
    //   54: bipush 30
    //   56: invokestatic 49	o/aa:ˎ	(CII)Ljava/lang/String;
    //   59: invokevirtual 53	java/lang/String:intern	()Ljava/lang/String;
    //   62: invokestatic 225	o/vq:ˋ	(Ljava/lang/Object;Ljava/lang/String;)V
    //   65: aload_0
    //   66: aload_1
    //   67: aload_2
    //   68: aload 5
    //   70: invokevirtual 228	o/aa:ˎ	(Ljava/lang/String;Ljava/lang/String;Ljava/lang/String;)V
    //   73: goto +9 -> 82
    //   76: astore_1
    //   77: aload_1
    //   78: athrow
    //   79: goto +161 -> 240
    //   82: getstatic 21	o/aa:ॱ	I
    //   85: bipush 109
    //   87: iadd
    //   88: istore_3
    //   89: iload_3
    //   90: sipush 128
    //   93: irem
    //   94: putstatic 23	o/aa:ʼ	I
    //   97: iload_3
    //   98: iconst_2
    //   99: irem
    //   100: ifne +6 -> 106
    //   103: goto +131 -> 234
    //   106: goto -61 -> 45
    //   109: getstatic 23	o/aa:ʼ	I
    //   112: bipush 21
    //   114: iadd
    //   115: istore_3
    //   116: iload_3
    //   117: sipush 128
    //   120: irem
    //   121: putstatic 21	o/aa:ॱ	I
    //   124: iload_3
    //   125: iconst_2
    //   126: irem
    //   127: ifeq +6 -> 133
    //   130: goto -127 -> 3
    //   133: return
    //   134: iconst_1
    //   135: istore_3
    //   136: goto +147 -> 283
    //   139: aload_0
    //   140: aload 6
    //   142: iconst_4
    //   143: invokevirtual 232	java/lang/String:substring	(I)Ljava/lang/String;
    //   146: invokespecial 234	o/aa:ॱ	(Ljava/lang/String;)Ljava/lang/String;
    //   149: invokevirtual 53	java/lang/String:intern	()Ljava/lang/String;
    //   152: astore 5
    //   154: iconst_3
    //   155: iconst_0
    //   156: idiv
    //   157: istore_3
    //   158: goto -110 -> 48
    //   161: aload_0
    //   162: aload 6
    //   164: iconst_4
    //   165: invokevirtual 232	java/lang/String:substring	(I)Ljava/lang/String;
    //   168: invokespecial 234	o/aa:ॱ	(Ljava/lang/String;)Ljava/lang/String;
    //   171: invokevirtual 53	java/lang/String:intern	()Ljava/lang/String;
    //   174: astore 5
    //   176: goto -128 -> 48
    //   179: iconst_0
    //   180: istore_3
    //   181: goto +160 -> 341
    //   184: aload_0
    //   185: getfield 34	o/aa:ˏ	Landroid/content/Context;
    //   188: astore 5
    //   190: getstatic 239	o/h$if:ok	I
    //   193: istore_3
    //   194: aload 5
    //   196: iload_3
    //   197: invokevirtual 244	android/content/Context:getString	(I)Ljava/lang/String;
    //   200: astore 6
    //   202: ldc -11
    //   204: iconst_0
    //   205: iconst_4
    //   206: invokestatic 49	o/aa:ˎ	(CII)Ljava/lang/String;
    //   209: astore 5
    //   211: aload 6
    //   213: aload 5
    //   215: invokevirtual 53	java/lang/String:intern	()Ljava/lang/String;
    //   218: invokevirtual 249	java/lang/String:startsWith	(Ljava/lang/String;)Z
    //   221: istore 4
    //   223: iload 4
    //   225: ifeq +6 -> 231
    //   228: goto -188 -> 40
    //   231: goto -52 -> 179
    //   234: goto -189 -> 45
    //   237: goto -128 -> 109
    //   240: aload_1
    //   241: iconst_0
    //   242: bipush 41
    //   244: iconst_5
    //   245: invokestatic 49	o/aa:ˎ	(CII)Ljava/lang/String;
    //   248: invokevirtual 53	java/lang/String:intern	()Ljava/lang/String;
    //   251: invokestatic 218	o/vq:ˎ	(Ljava/lang/Object;Ljava/lang/String;)V
    //   254: aload_2
    //   255: ldc -6
    //   257: bipush 46
    //   259: bipush 7
    //   261: invokestatic 49	o/aa:ˎ	(CII)Ljava/lang/String;
    //   264: invokevirtual 53	java/lang/String:intern	()Ljava/lang/String;
    //   267: invokestatic 218	o/vq:ˎ	(Ljava/lang/Object;Ljava/lang/String;)V
    //   270: aload_0
    //   271: getfield 34	o/aa:ˏ	Landroid/content/Context;
    //   274: ifnull +6 -> 280
    //   277: goto +34 -> 311
    //   280: goto -43 -> 237
    //   283: iload_3
    //   284: tableswitch	default:+24->308, 0:+-123->161, 1:+-145->139
    //   308: goto -169 -> 139
    //   311: getstatic 23	o/aa:ʼ	I
    //   314: bipush 57
    //   316: iadd
    //   317: istore_3
    //   318: iload_3
    //   319: sipush 128
    //   322: irem
    //   323: putstatic 21	o/aa:ॱ	I
    //   326: iload_3
    //   327: iconst_2
    //   328: irem
    //   329: ifeq +6 -> 335
    //   332: goto -295 -> 37
    //   335: goto -151 -> 184
    //   338: astore_1
    //   339: aload_1
    //   340: athrow
    //   341: aload 6
    //   343: astore 5
    //   345: iload_3
    //   346: tableswitch	default:+22->368, 0:+-298->48, 1:+-335->11
    //   368: goto -357 -> 11
    //   371: iconst_0
    //   372: istore_3
    //   373: goto -90 -> 283
    // Local variable table:
    //   start	length	slot	name	signature
    //   0	376	0	this	aa
    //   0	376	1	paramString1	String
    //   0	376	2	paramString2	String
    //   16	357	3	i	int
    //   221	3	4	bool	boolean
    //   48	296	5	localObject	Object
    //   140	202	6	str	String
    // Exception table:
    //   from	to	target	type
    //   184	190	76	java/lang/Exception
    //   190	194	76	java/lang/Exception
    //   194	202	76	java/lang/Exception
    //   202	211	76	java/lang/Exception
    //   211	223	76	java/lang/Exception
    //   202	211	338	java/lang/Exception
  }
  
  /* Error */
  public void ˎ(String paramString1, String paramString2, String paramString3)
  {
    // Byte code:
    //   0: goto +162 -> 162
    //   3: bipush 51
    //   5: istore 4
    //   7: goto +229 -> 236
    //   10: aload_0
    //   11: getfield 34	o/aa:ˏ	Landroid/content/Context;
    //   14: astore 5
    //   16: invokestatic 256	o/e:F_	()Lo/e;
    //   19: astore 6
    //   21: aload 6
    //   23: iconst_0
    //   24: bipush 20
    //   26: bipush 56
    //   28: invokestatic 49	o/aa:ˎ	(CII)Ljava/lang/String;
    //   31: invokevirtual 53	java/lang/String:intern	()Ljava/lang/String;
    //   34: invokestatic 225	o/vq:ˋ	(Ljava/lang/Object;Ljava/lang/String;)V
    //   37: aload 5
    //   39: aload 6
    //   41: invokevirtual 259	o/e:ˊ	()Lo/l;
    //   44: invokestatic 262	o/vq:ˊ	(Ljava/lang/Object;Ljava/lang/Object;)Z
    //   47: ifeq +6 -> 53
    //   50: goto -47 -> 3
    //   53: goto +112 -> 165
    //   56: invokestatic 256	o/e:F_	()Lo/e;
    //   59: astore 5
    //   61: aload 5
    //   63: iconst_0
    //   64: bipush 91
    //   66: bipush 13
    //   68: invokestatic 49	o/aa:ˎ	(CII)Ljava/lang/String;
    //   71: invokevirtual 53	java/lang/String:intern	()Ljava/lang/String;
    //   74: invokestatic 225	o/vq:ˋ	(Ljava/lang/Object;Ljava/lang/String;)V
    //   77: aload 5
    //   79: invokevirtual 259	o/e:ˊ	()Lo/l;
    //   82: checkcast 241	android/content/Context
    //   85: astore 5
    //   87: goto +213 -> 300
    //   90: getstatic 21	o/aa:ॱ	I
    //   93: bipush 39
    //   95: iadd
    //   96: istore 4
    //   98: iload 4
    //   100: sipush 128
    //   103: irem
    //   104: putstatic 23	o/aa:ʼ	I
    //   107: iload 4
    //   109: iconst_2
    //   110: irem
    //   111: ifne +6 -> 117
    //   114: goto +6 -> 120
    //   117: goto -61 -> 56
    //   120: invokestatic 256	o/e:F_	()Lo/e;
    //   123: astore 5
    //   125: aload 5
    //   127: iconst_0
    //   128: bipush 48
    //   130: iconst_3
    //   131: invokestatic 49	o/aa:ˎ	(CII)Ljava/lang/String;
    //   134: invokevirtual 53	java/lang/String:intern	()Ljava/lang/String;
    //   137: invokestatic 225	o/vq:ˋ	(Ljava/lang/Object;Ljava/lang/String;)V
    //   140: aload 5
    //   142: invokevirtual 259	o/e:ˊ	()Lo/l;
    //   145: checkcast 241	android/content/Context
    //   148: astore 5
    //   150: goto +150 -> 300
    //   153: aload_0
    //   154: getfield 34	o/aa:ˏ	Landroid/content/Context;
    //   157: astore 5
    //   159: goto +22 -> 181
    //   162: goto +209 -> 371
    //   165: bipush 83
    //   167: istore 4
    //   169: goto +67 -> 236
    //   172: astore_1
    //   173: aload_1
    //   174: athrow
    //   175: iconst_1
    //   176: istore 4
    //   178: goto +165 -> 343
    //   181: goto +119 -> 300
    //   184: iconst_0
    //   185: istore 4
    //   187: goto +156 -> 343
    //   190: aload_0
    //   191: getfield 34	o/aa:ˏ	Landroid/content/Context;
    //   194: astore 5
    //   196: invokestatic 256	o/e:F_	()Lo/e;
    //   199: astore 6
    //   201: aload 6
    //   203: iconst_0
    //   204: bipush 91
    //   206: bipush 13
    //   208: invokestatic 49	o/aa:ˎ	(CII)Ljava/lang/String;
    //   211: invokevirtual 53	java/lang/String:intern	()Ljava/lang/String;
    //   214: invokestatic 225	o/vq:ˋ	(Ljava/lang/Object;Ljava/lang/String;)V
    //   217: aload 5
    //   219: aload 6
    //   221: invokevirtual 259	o/e:ˊ	()Lo/l;
    //   224: invokestatic 262	o/vq:ˊ	(Ljava/lang/Object;Ljava/lang/Object;)Z
    //   227: ifeq +6 -> 233
    //   230: goto -46 -> 184
    //   233: goto -58 -> 175
    //   236: iload 4
    //   238: lookupswitch	default:+26->264, 51:+-148->90, 83:+-85->153
    //   264: goto -111 -> 153
    //   267: astore_1
    //   268: aload_1
    //   269: athrow
    //   270: getstatic 23	o/aa:ʼ	I
    //   273: bipush 81
    //   275: iadd
    //   276: istore 4
    //   278: iload 4
    //   280: sipush 128
    //   283: irem
    //   284: putstatic 21	o/aa:ॱ	I
    //   287: iload 4
    //   289: iconst_2
    //   290: irem
    //   291: ifeq +6 -> 297
    //   294: goto -284 -> 10
    //   297: goto -107 -> 190
    //   300: aload 5
    //   302: sipush 23338
    //   305: bipush 104
    //   307: bipush 14
    //   309: invokestatic 49	o/aa:ˎ	(CII)Ljava/lang/String;
    //   312: invokevirtual 53	java/lang/String:intern	()Ljava/lang/String;
    //   315: invokestatic 225	o/vq:ˋ	(Ljava/lang/Object;Ljava/lang/String;)V
    //   318: new 264	o/B
    //   321: dup
    //   322: aload 5
    //   324: aload_1
    //   325: aload_2
    //   326: aload_3
    //   327: invokespecial 267	o/B:<init>	(Landroid/content/Context;Ljava/lang/String;Ljava/lang/String;Ljava/lang/String;)V
    //   330: iconst_1
    //   331: invokevirtual 270	o/B:ˋ	(Z)Lo/ᐸ$If;
    //   334: iconst_0
    //   335: invokevirtual 274	o/ᐸ$If:ˎ	(Z)Lo/ᐸ$If;
    //   338: invokevirtual 277	o/ᐸ$If:ˏ	()Lo/ᐸ;
    //   341: pop
    //   342: return
    //   343: iload 4
    //   345: tableswitch	default:+23->368, 0:+-255->90, 1:+-192->153
    //   368: goto -278 -> 90
    //   371: iconst_0
    //   372: bipush 41
    //   374: iconst_5
    //   375: invokestatic 49	o/aa:ˎ	(CII)Ljava/lang/String;
    //   378: astore 5
    //   380: aload 5
    //   382: invokevirtual 53	java/lang/String:intern	()Ljava/lang/String;
    //   385: astore 5
    //   387: aload_1
    //   388: aload 5
    //   390: invokestatic 218	o/vq:ˎ	(Ljava/lang/Object;Ljava/lang/String;)V
    //   393: aload_2
    //   394: ldc -6
    //   396: bipush 46
    //   398: bipush 7
    //   400: invokestatic 49	o/aa:ˎ	(CII)Ljava/lang/String;
    //   403: invokevirtual 53	java/lang/String:intern	()Ljava/lang/String;
    //   406: invokestatic 218	o/vq:ˎ	(Ljava/lang/Object;Ljava/lang/String;)V
    //   409: aload_3
    //   410: ldc_w 278
    //   413: bipush 83
    //   415: bipush 8
    //   417: invokestatic 49	o/aa:ˎ	(CII)Ljava/lang/String;
    //   420: invokevirtual 53	java/lang/String:intern	()Ljava/lang/String;
    //   423: invokestatic 218	o/vq:ˎ	(Ljava/lang/Object;Ljava/lang/String;)V
    //   426: aload_0
    //   427: getfield 34	o/aa:ˏ	Landroid/content/Context;
    //   430: astore 5
    //   432: aload 5
    //   434: ifnull +6 -> 440
    //   437: goto -167 -> 270
    //   440: return
    // Local variable table:
    //   start	length	slot	name	signature
    //   0	441	0	this	aa
    //   0	441	1	paramString1	String
    //   0	441	2	paramString2	String
    //   0	441	3	paramString3	String
    //   5	339	4	i	int
    //   14	419	5	localObject	Object
    //   19	201	6	localE	e
    // Exception table:
    //   from	to	target	type
    //   387	432	172	java/lang/Exception
    //   371	380	267	java/lang/Exception
    //   380	387	267	java/lang/Exception
    //   387	432	267	java/lang/Exception
  }
  
  public final Context ˏ()
  {
    break label87;
    label3:
    Context localContext = this.ˏ;
    int i = null.length;
    return localContext;
    for (;;)
    {
      switch (i)
      {
      case 92: 
      default: 
        break label3;
        label43:
        i = 63;
      }
    }
    label87:
    for (;;)
    {
      i = ॱ + 51;
      ʼ = i % 128;
      if (i % 2 != 0)
      {
        break label43;
        return this.ˏ;
      }
      i = 92;
      break;
    }
  }
  
  public void ˏ(int paramInt)
  {
    break label147;
    paramInt = ʼ + 103;
    ॱ = paramInt % 128;
    label30:
    label43:
    String str3;
    label77:
    int i;
    if (paramInt % 2 == 0)
    {
      break label146;
      if (this.ˏ == null)
      {
        break label85;
        str3 = this.ˏ.getString(paramInt);
        if (str3.startsWith(ˎ(47358, 0, 4).intern())) {
          break label112;
        }
        break label235;
        break label90;
      }
      else
      {
        i = 1;
        break label208;
      }
      label85:
      i = 0;
      break label208;
    }
    for (;;)
    {
      try
      {
        label90:
        String str1 = ॱ(str3.substring(4));
        try
        {
          str1 = str1.intern();
        }
        catch (Exception localException1)
        {
          throw localException1;
        }
        label112:
        paramInt = 0;
        String str2 = str3;
        switch (paramInt)
        {
        default: 
          str2 = str3;
        }
      }
      catch (Exception localException2)
      {
        label146:
        label147:
        throw localException2;
      }
      return;
      break label30;
      return;
      paramInt = ॱ + 89;
      ʼ = paramInt % 128;
      if (paramInt % 2 == 0) {
        break label77;
      }
      continue;
      vq.ˋ(localException2, ˎ('ᪿ', 4, 30).intern());
      a_(localException2);
      break;
      continue;
      label208:
      switch (i)
      {
      }
      break label43;
      label235:
      paramInt = 1;
    }
  }
}
