package o;

import android.content.Context;
import android.util.AttributeSet;

public final class aD
  extends ɭ
  implements ɭ.if
{
  private static int ˎ = 1;
  private static int ˏ = 0;
  private static int ॱ = 109;
  private If ˋ;
  
  public aD(Context paramContext)
  {
    super(paramContext);
  }
  
  public aD(Context paramContext, AttributeSet paramAttributeSet)
  {
    super(paramContext, paramAttributeSet);
  }
  
  /* Error */
  public aD(Context paramContext, AttributeSet paramAttributeSet, int paramInt)
  {
    // Byte code:
    //   0: goto +6 -> 6
    //   3: astore_1
    //   4: aload_1
    //   5: athrow
    //   6: sipush 219
    //   9: bipush 7
    //   11: bipush 7
    //   13: newarray char
    //   15: dup
    //   16: iconst_0
    //   17: ldc 27
    //   19: castore
    //   20: dup
    //   21: iconst_1
    //   22: ldc 28
    //   24: castore
    //   25: dup
    //   26: iconst_2
    //   27: ldc 29
    //   29: castore
    //   30: dup
    //   31: iconst_3
    //   32: ldc 30
    //   34: castore
    //   35: dup
    //   36: iconst_4
    //   37: ldc 31
    //   39: castore
    //   40: dup
    //   41: iconst_5
    //   42: ldc 32
    //   44: castore
    //   45: dup
    //   46: bipush 6
    //   48: ldc 30
    //   50: castore
    //   51: bipush 7
    //   53: iconst_0
    //   54: invokestatic 35	o/aD:ˎ	(II[CIZ)Ljava/lang/String;
    //   57: astore 4
    //   59: aload 4
    //   61: invokevirtual 41	java/lang/String:intern	()Ljava/lang/String;
    //   64: astore 4
    //   66: aload_1
    //   67: aload 4
    //   69: invokestatic 46	o/vq:ˎ	(Ljava/lang/Object;Ljava/lang/String;)V
    //   72: aload_0
    //   73: aload_1
    //   74: aload_2
    //   75: iload_3
    //   76: invokespecial 56	o/ɭ:<init>	(Landroid/content/Context;Landroid/util/AttributeSet;I)V
    //   79: return
    //   80: astore_1
    //   81: aload_1
    //   82: athrow
    // Local variable table:
    //   start	length	slot	name	signature
    //   0	83	0	this	aD
    //   0	83	1	paramContext	Context
    //   0	83	2	paramAttributeSet	AttributeSet
    //   0	83	3	paramInt	int
    //   57	11	4	str	String
    // Exception table:
    //   from	to	target	type
    //   6	59	3	java/lang/Exception
    //   59	66	3	java/lang/Exception
    //   66	72	3	java/lang/Exception
    //   72	79	3	java/lang/Exception
    //   66	72	80	java/lang/Exception
  }
  
  /* Error */
  private static String ˎ(int paramInt1, int paramInt2, char[] paramArrayOfChar, int paramInt3, boolean paramBoolean)
  {
    // Byte code:
    //   0: goto +353 -> 353
    //   3: aload_2
    //   4: iload_0
    //   5: aload 7
    //   7: iload 5
    //   9: iload_0
    //   10: isub
    //   11: iconst_0
    //   12: irem
    //   13: caload
    //   14: castore
    //   15: iload_0
    //   16: bipush 34
    //   18: iadd
    //   19: istore_0
    //   20: goto +245 -> 265
    //   23: iload_3
    //   24: lookupswitch	default:+28->52, 3:+401->425, 69:+58->82
    //   52: goto +373 -> 425
    //   55: iload 4
    //   57: ifeq +6 -> 63
    //   60: goto +187 -> 247
    //   63: aload 7
    //   65: astore_2
    //   66: goto +211 -> 277
    //   69: iconst_3
    //   70: istore_3
    //   71: goto -48 -> 23
    //   74: iconst_1
    //   75: istore_0
    //   76: goto +315 -> 391
    //   79: goto +198 -> 277
    //   82: iload 6
    //   84: ifle +6 -> 90
    //   87: goto -13 -> 74
    //   90: goto +266 -> 356
    //   93: iload_1
    //   94: newarray char
    //   96: astore 7
    //   98: iload_3
    //   99: istore 6
    //   101: iconst_0
    //   102: istore_3
    //   103: iload_1
    //   104: istore 5
    //   106: iload_3
    //   107: istore_1
    //   108: goto +224 -> 332
    //   111: aload_2
    //   112: iload_0
    //   113: aload 7
    //   115: iload 5
    //   117: iload_0
    //   118: isub
    //   119: iconst_1
    //   120: isub
    //   121: caload
    //   122: castore
    //   123: iload_0
    //   124: iconst_1
    //   125: iadd
    //   126: istore_0
    //   127: goto +138 -> 265
    //   130: getstatic 21	o/aD:ˎ	I
    //   133: bipush 53
    //   135: iadd
    //   136: istore_1
    //   137: iload_1
    //   138: sipush 128
    //   141: irem
    //   142: putstatic 19	o/aD:ˏ	I
    //   145: iload_1
    //   146: iconst_2
    //   147: irem
    //   148: ifeq +6 -> 154
    //   151: goto +196 -> 347
    //   154: goto +190 -> 344
    //   157: getstatic 19	o/aD:ˏ	I
    //   160: bipush 19
    //   162: iadd
    //   163: istore_3
    //   164: iload_3
    //   165: sipush 128
    //   168: irem
    //   169: putstatic 21	o/aD:ˎ	I
    //   172: iload_3
    //   173: iconst_2
    //   174: irem
    //   175: ifne +6 -> 181
    //   178: goto +172 -> 350
    //   181: goto +151 -> 332
    //   184: astore_2
    //   185: aload_2
    //   186: athrow
    //   187: getstatic 19	o/aD:ˏ	I
    //   190: bipush 61
    //   192: iadd
    //   193: istore_1
    //   194: iload_1
    //   195: sipush 128
    //   198: irem
    //   199: putstatic 21	o/aD:ˎ	I
    //   202: iload_1
    //   203: iconst_2
    //   204: irem
    //   205: ifne +6 -> 211
    //   208: goto -205 -> 3
    //   211: goto -100 -> 111
    //   214: goto +235 -> 449
    //   217: getstatic 19	o/aD:ˏ	I
    //   220: bipush 97
    //   222: iadd
    //   223: istore_0
    //   224: iload_0
    //   225: sipush 128
    //   228: irem
    //   229: putstatic 21	o/aD:ˎ	I
    //   232: iload_0
    //   233: iconst_2
    //   234: irem
    //   235: ifne +6 -> 241
    //   238: goto +6 -> 244
    //   241: goto +45 -> 286
    //   244: goto +42 -> 286
    //   247: iload 5
    //   249: newarray char
    //   251: astore_2
    //   252: iconst_0
    //   253: istore_0
    //   254: goto -124 -> 130
    //   257: iload_1
    //   258: newarray char
    //   260: astore 7
    //   262: goto -164 -> 98
    //   265: iload_0
    //   266: iload 5
    //   268: if_icmpge +6 -> 274
    //   271: goto -84 -> 187
    //   274: goto -195 -> 79
    //   277: new 37	java/lang/String
    //   280: dup
    //   281: aload_2
    //   282: invokespecial 59	java/lang/String:<init>	([C)V
    //   285: areturn
    //   286: iload 5
    //   288: newarray char
    //   290: astore_2
    //   291: aload 7
    //   293: iconst_0
    //   294: aload_2
    //   295: iconst_0
    //   296: iload 5
    //   298: invokestatic 65	java/lang/System:arraycopy	(Ljava/lang/Object;ILjava/lang/Object;II)V
    //   301: aload_2
    //   302: iconst_0
    //   303: aload 7
    //   305: iload 5
    //   307: iload 6
    //   309: isub
    //   310: iload 6
    //   312: invokestatic 65	java/lang/System:arraycopy	(Ljava/lang/Object;ILjava/lang/Object;II)V
    //   315: aload_2
    //   316: iload 6
    //   318: aload 7
    //   320: iconst_0
    //   321: iload 5
    //   323: iload 6
    //   325: isub
    //   326: invokestatic 65	java/lang/System:arraycopy	(Ljava/lang/Object;ILjava/lang/Object;II)V
    //   329: goto -274 -> 55
    //   332: iload_1
    //   333: iload 5
    //   335: if_icmpge +6 -> 341
    //   338: goto -269 -> 69
    //   341: goto +78 -> 419
    //   344: goto -79 -> 265
    //   347: goto -82 -> 265
    //   350: goto -18 -> 332
    //   353: goto +8 -> 361
    //   356: iconst_0
    //   357: istore_0
    //   358: goto +33 -> 391
    //   361: getstatic 19	o/aD:ˏ	I
    //   364: bipush 37
    //   366: iadd
    //   367: istore 5
    //   369: iload 5
    //   371: sipush 128
    //   374: irem
    //   375: putstatic 21	o/aD:ˎ	I
    //   378: iload 5
    //   380: iconst_2
    //   381: irem
    //   382: ifne +6 -> 388
    //   385: goto -128 -> 257
    //   388: goto -295 -> 93
    //   391: iload_0
    //   392: tableswitch	default:+24->416, 0:+-337->55, 1:+-175->217
    //   416: goto -361 -> 55
    //   419: bipush 69
    //   421: istore_3
    //   422: goto -399 -> 23
    //   425: getstatic 19	o/aD:ˏ	I
    //   428: bipush 113
    //   430: iadd
    //   431: istore_3
    //   432: iload_3
    //   433: sipush 128
    //   436: irem
    //   437: putstatic 21	o/aD:ˎ	I
    //   440: iload_3
    //   441: iconst_2
    //   442: irem
    //   443: ifne +6 -> 449
    //   446: goto -232 -> 214
    //   449: aload 7
    //   451: iload_1
    //   452: iload_0
    //   453: aload_2
    //   454: iload_1
    //   455: caload
    //   456: iadd
    //   457: i2c
    //   458: castore
    //   459: aload 7
    //   461: iload_1
    //   462: aload 7
    //   464: iload_1
    //   465: caload
    //   466: getstatic 23	o/aD:ॱ	I
    //   469: isub
    //   470: i2c
    //   471: castore
    //   472: iload_1
    //   473: iconst_1
    //   474: iadd
    //   475: istore_1
    //   476: goto -319 -> 157
    // Local variable table:
    //   start	length	slot	name	signature
    //   0	479	0	paramInt1	int
    //   0	479	1	paramInt2	int
    //   0	479	2	paramArrayOfChar	char[]
    //   0	479	3	paramInt3	int
    //   0	479	4	paramBoolean	boolean
    //   7	375	5	i	int
    //   82	244	6	j	int
    //   5	458	7	arrayOfChar	char[]
    // Exception table:
    //   from	to	target	type
    //   291	301	184	java/lang/Exception
    //   301	315	184	java/lang/Exception
    //   315	329	184	java/lang/Exception
    //   425	432	184	java/lang/Exception
    //   432	440	184	java/lang/Exception
  }
  
  /* Error */
  public final void setOnScrollStatusChangedListener(If paramIf)
  {
    // Byte code:
    //   0: goto +250 -> 250
    //   3: bipush 45
    //   5: istore_2
    //   6: goto +209 -> 215
    //   9: aload_1
    //   10: sipush 212
    //   13: bipush 29
    //   15: bipush 29
    //   17: newarray char
    //   19: dup
    //   20: iconst_0
    //   21: ldc 68
    //   23: castore
    //   24: dup
    //   25: iconst_1
    //   26: ldc 69
    //   28: castore
    //   29: dup
    //   30: iconst_2
    //   31: ldc 29
    //   33: castore
    //   34: dup
    //   35: iconst_3
    //   36: ldc 70
    //   38: castore
    //   39: dup
    //   40: iconst_4
    //   41: ldc 71
    //   43: castore
    //   44: dup
    //   45: iconst_5
    //   46: ldc 28
    //   48: castore
    //   49: dup
    //   50: bipush 6
    //   52: ldc 72
    //   54: castore
    //   55: dup
    //   56: bipush 7
    //   58: ldc 73
    //   60: castore
    //   61: dup
    //   62: bipush 8
    //   64: ldc 74
    //   66: castore
    //   67: dup
    //   68: bipush 9
    //   70: ldc 75
    //   72: castore
    //   73: dup
    //   74: bipush 10
    //   76: ldc 71
    //   78: castore
    //   79: dup
    //   80: bipush 11
    //   82: ldc 75
    //   84: castore
    //   85: dup
    //   86: bipush 12
    //   88: ldc 76
    //   90: castore
    //   91: dup
    //   92: bipush 13
    //   94: ldc 77
    //   96: castore
    //   97: dup
    //   98: bipush 14
    //   100: ldc 77
    //   102: castore
    //   103: dup
    //   104: bipush 15
    //   106: ldc 78
    //   108: castore
    //   109: dup
    //   110: bipush 16
    //   112: ldc 79
    //   114: castore
    //   115: dup
    //   116: bipush 17
    //   118: ldc 80
    //   120: castore
    //   121: dup
    //   122: bipush 18
    //   124: ldc 76
    //   126: castore
    //   127: dup
    //   128: bipush 19
    //   130: ldc 70
    //   132: castore
    //   133: dup
    //   134: bipush 20
    //   136: ldc 78
    //   138: castore
    //   139: dup
    //   140: bipush 21
    //   142: ldc 79
    //   144: castore
    //   145: dup
    //   146: bipush 22
    //   148: ldc 69
    //   150: castore
    //   151: dup
    //   152: bipush 23
    //   154: ldc 70
    //   156: castore
    //   157: dup
    //   158: bipush 24
    //   160: ldc 69
    //   162: castore
    //   163: dup
    //   164: bipush 25
    //   166: ldc 75
    //   168: castore
    //   169: dup
    //   170: bipush 26
    //   172: ldc 73
    //   174: castore
    //   175: dup
    //   176: bipush 27
    //   178: ldc 81
    //   180: castore
    //   181: dup
    //   182: bipush 28
    //   184: ldc 82
    //   186: castore
    //   187: bipush 21
    //   189: iconst_1
    //   190: invokestatic 35	o/aD:ˎ	(II[CIZ)Ljava/lang/String;
    //   193: invokevirtual 41	java/lang/String:intern	()Ljava/lang/String;
    //   196: invokestatic 46	o/vq:ˎ	(Ljava/lang/Object;Ljava/lang/String;)V
    //   199: aload_0
    //   200: aload_0
    //   201: checkcast 6	o/ɭ$if
    //   204: invokevirtual 86	o/aD:setOnScrollChangeListener	(Lo/ɭ$if;)V
    //   207: aload_0
    //   208: aload_1
    //   209: putfield 88	o/aD:ˋ	Lo/aD$If;
    //   212: goto +44 -> 256
    //   215: iload_2
    //   216: lookupswitch	default:+28->244, 13:+96->312, 45:+-207->9
    //   244: goto +68 -> 312
    //   247: astore_1
    //   248: aload_1
    //   249: athrow
    //   250: goto +35 -> 285
    //   253: astore_1
    //   254: aload_1
    //   255: athrow
    //   256: getstatic 19	o/aD:ˏ	I
    //   259: bipush 99
    //   261: iadd
    //   262: istore_2
    //   263: iload_2
    //   264: sipush 128
    //   267: irem
    //   268: putstatic 21	o/aD:ˎ	I
    //   271: iload_2
    //   272: iconst_2
    //   273: irem
    //   274: ifne +4 -> 278
    //   277: return
    //   278: return
    //   279: bipush 13
    //   281: istore_2
    //   282: goto -67 -> 215
    //   285: getstatic 19	o/aD:ˏ	I
    //   288: bipush 35
    //   290: iadd
    //   291: istore_2
    //   292: iload_2
    //   293: sipush 128
    //   296: irem
    //   297: putstatic 21	o/aD:ˎ	I
    //   300: iload_2
    //   301: iconst_2
    //   302: irem
    //   303: ifne +6 -> 309
    //   306: goto -27 -> 279
    //   309: goto -306 -> 3
    //   312: sipush 17708
    //   315: bipush 67
    //   317: bipush 29
    //   319: newarray char
    //   321: dup
    //   322: iconst_0
    //   323: ldc 68
    //   325: castore
    //   326: dup
    //   327: iconst_1
    //   328: ldc 69
    //   330: castore
    //   331: dup
    //   332: iconst_2
    //   333: ldc 29
    //   335: castore
    //   336: dup
    //   337: iconst_3
    //   338: ldc 70
    //   340: castore
    //   341: dup
    //   342: iconst_4
    //   343: ldc 71
    //   345: castore
    //   346: dup
    //   347: iconst_5
    //   348: ldc 28
    //   350: castore
    //   351: dup
    //   352: bipush 6
    //   354: ldc 72
    //   356: castore
    //   357: dup
    //   358: bipush 7
    //   360: ldc 73
    //   362: castore
    //   363: dup
    //   364: bipush 8
    //   366: ldc 74
    //   368: castore
    //   369: dup
    //   370: bipush 9
    //   372: ldc 75
    //   374: castore
    //   375: dup
    //   376: bipush 10
    //   378: ldc 71
    //   380: castore
    //   381: dup
    //   382: bipush 11
    //   384: ldc 75
    //   386: castore
    //   387: dup
    //   388: bipush 12
    //   390: ldc 76
    //   392: castore
    //   393: dup
    //   394: bipush 13
    //   396: ldc 77
    //   398: castore
    //   399: dup
    //   400: bipush 14
    //   402: ldc 77
    //   404: castore
    //   405: dup
    //   406: bipush 15
    //   408: ldc 78
    //   410: castore
    //   411: dup
    //   412: bipush 16
    //   414: ldc 79
    //   416: castore
    //   417: dup
    //   418: bipush 17
    //   420: ldc 80
    //   422: castore
    //   423: dup
    //   424: bipush 18
    //   426: ldc 76
    //   428: castore
    //   429: dup
    //   430: bipush 19
    //   432: ldc 70
    //   434: castore
    //   435: dup
    //   436: bipush 20
    //   438: ldc 78
    //   440: castore
    //   441: dup
    //   442: bipush 21
    //   444: ldc 79
    //   446: castore
    //   447: dup
    //   448: bipush 22
    //   450: ldc 69
    //   452: castore
    //   453: dup
    //   454: bipush 23
    //   456: ldc 70
    //   458: castore
    //   459: dup
    //   460: bipush 24
    //   462: ldc 69
    //   464: castore
    //   465: dup
    //   466: bipush 25
    //   468: ldc 75
    //   470: castore
    //   471: dup
    //   472: bipush 26
    //   474: ldc 73
    //   476: castore
    //   477: dup
    //   478: bipush 27
    //   480: ldc 81
    //   482: castore
    //   483: dup
    //   484: bipush 28
    //   486: ldc 82
    //   488: castore
    //   489: bipush 102
    //   491: iconst_0
    //   492: invokestatic 35	o/aD:ˎ	(II[CIZ)Ljava/lang/String;
    //   495: astore_3
    //   496: aload_3
    //   497: invokevirtual 41	java/lang/String:intern	()Ljava/lang/String;
    //   500: astore_3
    //   501: aload_1
    //   502: aload_3
    //   503: invokestatic 46	o/vq:ˎ	(Ljava/lang/Object;Ljava/lang/String;)V
    //   506: aload_0
    //   507: checkcast 6	o/ɭ$if
    //   510: astore_3
    //   511: aload_0
    //   512: aload_3
    //   513: invokevirtual 86	o/aD:setOnScrollChangeListener	(Lo/ɭ$if;)V
    //   516: aload_0
    //   517: aload_1
    //   518: putfield 88	o/aD:ˋ	Lo/aD$If;
    //   521: goto -265 -> 256
    // Local variable table:
    //   start	length	slot	name	signature
    //   0	524	0	this	aD
    //   0	524	1	paramIf	If
    //   5	298	2	i	int
    //   495	18	3	localObject	Object
    // Exception table:
    //   from	to	target	type
    //   496	501	247	java/lang/Exception
    //   501	506	247	java/lang/Exception
    //   312	496	253	java/lang/Exception
    //   506	511	253	java/lang/Exception
  }
  
  /* Error */
  public void ˊ(ɭ paramɭ, int paramInt1, int paramInt2, int paramInt3, int paramInt4)
  {
    // Byte code:
    //   0: goto +510 -> 510
    //   3: iload_3
    //   4: iload 5
    //   6: if_icmpge +6 -> 12
    //   9: goto +246 -> 255
    //   12: goto +501 -> 513
    //   15: getstatic 95	o/H:ॱ	Lo/H;
    //   18: astore_1
    //   19: goto +594 -> 613
    //   22: bipush 14
    //   24: istore_2
    //   25: goto +6 -> 31
    //   28: goto +74 -> 102
    //   31: iload_2
    //   32: lookupswitch	default:+28->60, 14:+554->586, 67:+-29->3
    //   60: goto +526 -> 586
    //   63: goto +550 -> 613
    //   66: bipush 59
    //   68: istore_2
    //   69: goto +50 -> 119
    //   72: return
    //   73: iload_2
    //   74: tableswitch	default:+22->96, 0:+-2->72, 1:+383->457
    //   96: goto +361 -> 457
    //   99: goto +233 -> 332
    //   102: getstatic 97	o/H:ˊ	Lo/H;
    //   105: astore_1
    //   106: goto +507 -> 613
    //   109: getstatic 99	o/H:ˎ	Lo/H;
    //   112: astore_1
    //   113: goto +424 -> 537
    //   116: goto +190 -> 306
    //   119: iload_2
    //   120: lookupswitch	default:+28->148, 59:+338->458, 86:+186->306
    //   148: goto +310 -> 458
    //   151: iload_2
    //   152: lookupswitch	default:+28->180, 1:+168->320, 68:+-137->15
    //   180: goto -165 -> 15
    //   183: goto +430 -> 613
    //   186: astore_1
    //   187: aload_1
    //   188: athrow
    //   189: bipush 68
    //   191: istore_2
    //   192: goto -41 -> 151
    //   195: bipush 67
    //   197: istore_2
    //   198: goto -167 -> 31
    //   201: getstatic 21	o/aD:ˎ	I
    //   204: bipush 81
    //   206: iadd
    //   207: istore_2
    //   208: iload_2
    //   209: sipush 128
    //   212: irem
    //   213: putstatic 19	o/aD:ˏ	I
    //   216: iload_2
    //   217: iconst_2
    //   218: irem
    //   219: ifeq +6 -> 225
    //   222: goto +268 -> 490
    //   225: goto +66 -> 291
    //   228: getstatic 21	o/aD:ˎ	I
    //   231: bipush 79
    //   233: iadd
    //   234: istore_2
    //   235: iload_2
    //   236: sipush 128
    //   239: irem
    //   240: putstatic 19	o/aD:ˏ	I
    //   243: iload_2
    //   244: iconst_2
    //   245: irem
    //   246: ifeq +6 -> 252
    //   249: goto -221 -> 28
    //   252: goto -150 -> 102
    //   255: getstatic 101	o/H:ˋ	Lo/H;
    //   258: astore_1
    //   259: goto +354 -> 613
    //   262: getstatic 19	o/aD:ˏ	I
    //   265: istore_2
    //   266: iload_2
    //   267: bipush 117
    //   269: iadd
    //   270: istore_2
    //   271: iload_2
    //   272: sipush 128
    //   275: irem
    //   276: putstatic 21	o/aD:ˎ	I
    //   279: iload_2
    //   280: iconst_2
    //   281: irem
    //   282: ifne +6 -> 288
    //   285: goto +200 -> 485
    //   288: goto +283 -> 571
    //   291: aload_0
    //   292: getfield 88	o/aD:ˋ	Lo/aD$If;
    //   295: astore_1
    //   296: aload_1
    //   297: ifnull +6 -> 303
    //   300: goto +38 -> 338
    //   303: goto +222 -> 525
    //   306: aload 6
    //   308: aload_1
    //   309: invokeinterface 104 2 0
    //   314: return
    //   315: iconst_1
    //   316: istore_2
    //   317: goto -166 -> 151
    //   320: getstatic 95	o/H:ॱ	Lo/H;
    //   323: astore_1
    //   324: new 106	java/lang/NullPointerException
    //   327: dup
    //   328: invokespecial 108	java/lang/NullPointerException:<init>	()V
    //   331: athrow
    //   332: invokestatic 110	o/vq:ˎ	()V
    //   335: goto -219 -> 116
    //   338: aload_0
    //   339: iconst_0
    //   340: invokevirtual 114	o/aD:getChildAt	(I)Landroid/view/View;
    //   343: astore_1
    //   344: aload_1
    //   345: sipush 194
    //   348: bipush 13
    //   350: bipush 13
    //   352: newarray char
    //   354: dup
    //   355: iconst_0
    //   356: ldc 115
    //   358: castore
    //   359: dup
    //   360: iconst_1
    //   361: ldc 116
    //   363: castore
    //   364: dup
    //   365: iconst_2
    //   366: ldc 76
    //   368: castore
    //   369: dup
    //   370: iconst_3
    //   371: ldc 117
    //   373: castore
    //   374: dup
    //   375: iconst_4
    //   376: ldc 118
    //   378: castore
    //   379: dup
    //   380: iconst_5
    //   381: ldc 119
    //   383: castore
    //   384: dup
    //   385: bipush 6
    //   387: ldc 120
    //   389: castore
    //   390: dup
    //   391: bipush 7
    //   393: ldc 121
    //   395: castore
    //   396: dup
    //   397: bipush 8
    //   399: ldc 116
    //   401: castore
    //   402: dup
    //   403: bipush 9
    //   405: ldc 122
    //   407: castore
    //   408: dup
    //   409: bipush 10
    //   411: ldc 123
    //   413: castore
    //   414: dup
    //   415: bipush 11
    //   417: ldc 124
    //   419: castore
    //   420: dup
    //   421: bipush 12
    //   423: ldc 125
    //   425: castore
    //   426: bipush 11
    //   428: iconst_1
    //   429: invokestatic 35	o/aD:ˎ	(II[CIZ)Ljava/lang/String;
    //   432: invokevirtual 41	java/lang/String:intern	()Ljava/lang/String;
    //   435: invokestatic 127	o/vq:ˋ	(Ljava/lang/Object;Ljava/lang/String;)V
    //   438: iload_3
    //   439: aload_1
    //   440: invokevirtual 133	android/view/View:getBottom	()I
    //   443: aload_0
    //   444: invokevirtual 136	o/aD:getMeasuredHeight	()I
    //   447: isub
    //   448: if_icmplt +6 -> 454
    //   451: goto -342 -> 109
    //   454: goto +122 -> 576
    //   457: return
    //   458: getstatic 19	o/aD:ˏ	I
    //   461: bipush 65
    //   463: iadd
    //   464: istore_2
    //   465: iload_2
    //   466: sipush 128
    //   469: irem
    //   470: putstatic 21	o/aD:ˎ	I
    //   473: iload_2
    //   474: iconst_2
    //   475: irem
    //   476: ifne +6 -> 482
    //   479: goto -380 -> 99
    //   482: goto -150 -> 332
    //   485: iconst_1
    //   486: istore_2
    //   487: goto -414 -> 73
    //   490: aload_0
    //   491: getfield 88	o/aD:ˋ	Lo/aD$If;
    //   494: astore_1
    //   495: bipush 30
    //   497: iconst_0
    //   498: idiv
    //   499: istore_2
    //   500: aload_1
    //   501: ifnull +6 -> 507
    //   504: goto -166 -> 338
    //   507: goto +18 -> 525
    //   510: goto -309 -> 201
    //   513: iload_3
    //   514: iload 5
    //   516: if_icmple +6 -> 522
    //   519: goto -291 -> 228
    //   522: goto +42 -> 564
    //   525: goto -263 -> 262
    //   528: astore_1
    //   529: aload_1
    //   530: athrow
    //   531: bipush 86
    //   533: istore_2
    //   534: goto -415 -> 119
    //   537: getstatic 19	o/aD:ˏ	I
    //   540: bipush 23
    //   542: iadd
    //   543: istore_2
    //   544: iload_2
    //   545: sipush 128
    //   548: irem
    //   549: putstatic 21	o/aD:ˎ	I
    //   552: iload_2
    //   553: iconst_2
    //   554: irem
    //   555: ifne +6 -> 561
    //   558: goto -495 -> 63
    //   561: goto -378 -> 183
    //   564: getstatic 138	o/H:ˏ	Lo/H;
    //   567: astore_1
    //   568: goto +45 -> 613
    //   571: iconst_0
    //   572: istore_2
    //   573: goto -500 -> 73
    //   576: iload_3
    //   577: ifne +6 -> 583
    //   580: goto -558 -> 22
    //   583: goto -388 -> 195
    //   586: getstatic 21	o/aD:ˎ	I
    //   589: bipush 11
    //   591: iadd
    //   592: istore_2
    //   593: iload_2
    //   594: sipush 128
    //   597: irem
    //   598: putstatic 19	o/aD:ˏ	I
    //   601: iload_2
    //   602: iconst_2
    //   603: irem
    //   604: ifeq +6 -> 610
    //   607: goto -292 -> 315
    //   610: goto -421 -> 189
    //   613: aload_0
    //   614: getfield 88	o/aD:ˋ	Lo/aD$If;
    //   617: astore 6
    //   619: aload 6
    //   621: ifnonnull +6 -> 627
    //   624: goto -558 -> 66
    //   627: goto -96 -> 531
    // Local variable table:
    //   start	length	slot	name	signature
    //   0	630	0	this	aD
    //   0	630	1	paramɭ	ɭ
    //   0	630	2	paramInt1	int
    //   0	630	3	paramInt2	int
    //   0	630	4	paramInt3	int
    //   0	630	5	paramInt4	int
    //   306	314	6	localIf	If
    // Exception table:
    //   from	to	target	type
    //   262	266	186	java/lang/Exception
    //   271	279	186	java/lang/Exception
    //   586	593	186	java/lang/Exception
    //   593	601	186	java/lang/Exception
    //   490	495	528	java/lang/Exception
  }
  
  public static abstract interface If
  {
    public abstract void ˋ(H paramH);
  }
}
